{
  "type": "Feature",
  "properties": {
    "iso:country":"US",
    "sg:address":"40 N Chester Rd",
    "sg:city":"West Chester",
    "sg:classifiers":[
        {
            "category":"Professional",
            "subcategory":"Computer Services",
            "type":"Services"
        }
    ],
    "sg:phone":"+1   ",
    "sg:postcode":"19380",
    "sg:province":"PA",
    "sg:tags":[
        "datum"
    ],
    "wof:name":"Resource Management Intl",
    "wof:placetype":"venue"
},
  "geometry": {"coordinates":[-75.525767,39.968168],"type":"Point"}
}