{
  "type": "Feature",
  "properties": {
    "iso:country":"US",
    "sg:address":"4 S Prince St",
    "sg:city":"Millersville",
    "sg:classifiers":[
        {
            "category":"Restaurant",
            "type":"Food & Drink"
        }
    ],
    "sg:phone":"+1 717 871 6899",
    "sg:postcode":"17551",
    "sg:province":"PA",
    "sg:tags":[
        "eating"
    ],
    "wof:name":"Far East Cafe",
    "wof:placetype":"venue"
},
  "geometry": {"coordinates":[-76.358037,39.994681],"type":"Point"}
}