{
  "type": "Feature",
  "properties": {
    "iso:country":"US",
    "sg:address":"2804 W 10th St",
    "sg:city":"Chester",
    "sg:classifiers":[
        {
            "category":"Health Services",
            "subcategory":"Doctor",
            "type":"Services"
        }
    ],
    "sg:phone":"+1 610 494 0464",
    "sg:postcode":"19013",
    "sg:province":"PA",
    "sg:tags":[
        "dentist"
    ],
    "wof:name":"Gruszka & Graybill",
    "wof:placetype":"venue"
},
  "geometry": {"coordinates":[-75.397851,39.836155],"type":"Point"}
}