{
  "type": "Feature",
  "properties": {
    "iso:country":"US",
    "sg:address":"129 Chestnut St",
    "sg:city":"Edinboro",
    "sg:classifiers":[
        {
            "category":"Real Estate",
            "subcategory":"Real Estate Operator",
            "type":"Services"
        }
    ],
    "sg:phone":"+1 814 734 4613",
    "sg:postcode":"16412",
    "sg:province":"PA",
    "sg:tags":[
        "apartment"
    ],
    "wof:name":"Chestnut Knoll Assoc",
    "wof:placetype":"venue"
},
  "geometry": {"coordinates":[-80.13642900000001,41.870834],"type":"Point"}
}