{
  "type": "Feature",
  "properties": {
    "addr:full":"913 Dewey Ave New Castle PA 16101",
    "addr:housenumber":"913",
    "addr:postcode":"16101",
    "addr:street":"Dewey Ave",
    "iso:country":"US",
    "sg:address":"913 Dewey Ave",
    "sg:city":"New Castle",
    "sg:classifiers":[
        {
            "category":"Building & Trades",
            "subcategory":"Landscaping Services",
            "type":"Services"
        }
    ],
    "sg:phone":"+1 724 651 7977",
    "sg:postcode":"16101",
    "sg:province":"PA",
    "sg:tags":[
        "lawn",
        "maintenance",
        "grounds"
    ],
    "wof:name":"Lucchino Contracting",
    "wof:placetype":"venue"
},
  "geometry": {"coordinates":[-80.327788,41.008366],"type":"Point"}
}