{
  "type": "Feature",
  "properties": {
    "addr:full":"439 S Macdade Blvd  Glenolden PA 19036",
    "addr:housenumber":"439",
    "addr:postcode":"19036",
    "addr:street":"S Macdade Blvd",
    "iso:country":"US",
    "sg:address":"439 S Macdade Blvd ",
    "sg:city":"Glenolden",
    "sg:classifiers":[
        {
            "category":"Restaurant",
            "type":"Food & Drink"
        }
    ],
    "sg:menulink":"http://www.allmenus.com/pa/glenolden/289209-not-just-wings/menu/",
    "sg:phone":"+1 484 494 0194",
    "sg:postcode":"19036",
    "sg:province":"PA",
    "sg:tags":[
        "barbecue",
        "american",
        "wing"
    ],
    "wof:name":"Not Just Wings",
    "wof:placetype":"venue"
},
  "geometry": {"coordinates":[-75.30126799999999,39.900803],"type":"Point"}
}