{
  "type": "Feature",
  "properties": {
    "addr:full":"115 Gibraltar Rd Horsham PA 19044",
    "addr:housenumber":"115",
    "addr:postcode":"19044",
    "addr:street":"Gibraltar Rd",
    "iso:country":"US",
    "sg:address":"115 Gibraltar Rd",
    "sg:city":"Horsham",
    "sg:classifiers":[
        {
            "category":"Professional",
            "subcategory":"Computer Services",
            "type":"Services"
        }
    ],
    "sg:phone":"+1   ",
    "sg:postcode":"19044",
    "sg:province":"PA",
    "sg:tags":[
        "information",
        "retrieval"
    ],
    "wof:name":"AT&T",
    "wof:placetype":"venue"
},
  "geometry": {"coordinates":[-75.129813,40.170094],"type":"Point"}
}