{
  "type": "Feature",
  "properties": {
    "iso:country":"US",
    "sg:address":"236 E 11th St",
    "sg:city":"Erie",
    "sg:classifiers":[
        {
            "category":"Organizations",
            "subcategory":"Religious Organization",
            "type":"Services"
        }
    ],
    "sg:phone":"+1 814 456 4011",
    "sg:postcode":"16503",
    "sg:province":"PA",
    "sg:tags":[
        "church"
    ],
    "sg:website":"www.stjamesamec.org",
    "wof:name":"St James African Methodist Chr",
    "wof:placetype":"venue"
},
  "geometry": {"coordinates":[-80.076511,42.126502],"type":"Point"}
}