{
  "type": "Feature",
  "properties": {
    "iso:country":"US",
    "sg:address":"3 Short St",
    "sg:city":"Pittsburgh",
    "sg:classifiers":[
        {
            "category":"Building & Trades",
            "subcategory":"Construction",
            "type":"Services"
        }
    ],
    "sg:phone":"+1   ",
    "sg:postcode":"15215",
    "sg:province":"PA",
    "sg:tags":[
        "contractor"
    ],
    "wof:name":"Keith Clouse Construction",
    "wof:placetype":"venue"
},
  "geometry": {"coordinates":[-79.923311,40.501636],"type":"Point"}
}