{
  "type": "Feature",
  "properties": {
    "addr:full":"800 Main St Royersford PA 19468",
    "addr:housenumber":"800",
    "addr:postcode":"19468",
    "addr:street":"Main St",
    "iso:country":"US",
    "sg:address":"800 Main St",
    "sg:city":"Royersford",
    "sg:classifiers":[
        {
            "category":"Restaurant",
            "type":"Food & Drink"
        }
    ],
    "sg:menulink":"http://www.allmenus.com/pa/royersford/66245-dominos-pizza/menu/",
    "sg:phone":"+1 215 362 8000",
    "sg:postcode":"19468",
    "sg:province":"PA",
    "sg:tags":[
        "american",
        "wing",
        "pizza"
    ],
    "wof:name":"Domino's Pizza",
    "wof:placetype":"venue"
},
  "geometry": {"coordinates":[-75.532304,40.190857],"type":"Point"}
}