{
  "type": "Feature",
  "properties": {
    "iso:country":"US",
    "sg:address":"13 E State St",
    "sg:city":"Media",
    "sg:classifiers":[
        {
            "category":"Shopping",
            "subcategory":"Used Merchandise",
            "type":"Retail Goods"
        }
    ],
    "sg:phone":"+1 610 566 1502",
    "sg:postcode":"19063",
    "sg:province":"PA",
    "sg:tags":[
        "shop",
        "thrift"
    ],
    "wof:name":"Attic Thrift Shop",
    "wof:placetype":"venue"
},
  "geometry": {"coordinates":[-75.389096,39.917954],"type":"Point"}
}