{
  "type": "Feature",
  "properties": {
    "addr:full":"1 Buttonwood Sq Philadelphia PA 19130",
    "addr:housenumber":"1",
    "addr:postcode":"19130",
    "addr:street":"Buttonwood Sq",
    "iso:country":"US",
    "sg:address":"1 Buttonwood Sq",
    "sg:city":"Philadelphia",
    "sg:classifiers":[
        {
            "category":"Personal",
            "subcategory":"Nail Salon",
            "type":"Services"
        }
    ],
    "sg:phone":"+1 215 557 7464",
    "sg:postcode":"19130",
    "sg:province":"PA",
    "wof:name":"Polaris Nail Spa",
    "wof:placetype":"venue"
},
  "geometry": {"coordinates":[-75.169376,39.962645],"type":"Point"}
}