{
  "type": "Feature",
  "properties": {
    "iso:country":"US",
    "sg:address":"1306 Swarthmore Ave",
    "sg:city":"Folsom",
    "sg:classifiers":[
        {
            "category":"Organizations",
            "subcategory":"Non-profit Organization",
            "type":"Services"
        }
    ],
    "sg:phone":"+1 610 583 2107",
    "sg:postcode":"19033",
    "sg:province":"PA",
    "sg:tags":[
        "fund",
        "raising"
    ],
    "wof:name":"Philadelphia Relief Fund",
    "wof:placetype":"venue"
},
  "geometry": {"coordinates":[-75.332751,39.900401],"type":"Point"}
}