{
  "type": "Feature",
  "properties": {
    "iso:country":"US",
    "sg:address":"137 S 8th St",
    "sg:city":"Bangor",
    "sg:classifiers":[
        {
            "category":"Manufacturing",
            "subcategory":"Printing",
            "type":"Manufacturing & Wholesale Goods"
        }
    ],
    "sg:phone":"+1   ",
    "sg:postcode":"18013",
    "sg:province":"PA",
    "sg:tags":[
        "photography",
        "tours",
        "virtual"
    ],
    "wof:name":"Geocentric Production Inc",
    "wof:placetype":"venue"
},
  "geometry": {"coordinates":[-75.215765,40.865707],"type":"Point"}
}