{
  "type": "Feature",
  "properties": {
    "addr:full":"7105 Harrison Ave Swissvale PA 15218",
    "addr:housenumber":"7105",
    "addr:postcode":"15218",
    "addr:street":"Harrison Ave",
    "iso:country":"US",
    "sg:address":"7105 Harrison Ave",
    "sg:city":"Swissvale",
    "sg:classifiers":[
        {
            "category":"Professional",
            "type":"Services"
        }
    ],
    "sg:phone":"+1 412 243 4268",
    "sg:postcode":"15218",
    "sg:province":"PA",
    "sg:tags":[
        "establishment"
    ],
    "wof:name":"Degiroma Inc",
    "wof:placetype":"venue"
},
  "geometry": {"coordinates":[-79.89609299999999,40.422818],"type":"Point"}
}