{
  "type": "Feature",
  "properties": {
    "iso:country":"US",
    "sg:address":"5369 US Hwy 15",
    "sg:city":"Montgomery",
    "sg:classifiers":[
        {
            "category":"Retail",
            "subcategory":"Auto Repair",
            "type":"Services"
        }
    ],
    "sg:phone":"+1 570 547 7212",
    "sg:postcode":"17752",
    "sg:province":"PA",
    "sg:tags":[
        "repairing",
        "automobile"
    ],
    "wof:name":"Transmission Depot",
    "wof:placetype":"venue"
},
  "geometry": {"coordinates":[-76.915665,41.19226],"type":"Point"}
}