{
  "type": "Feature",
  "properties": {
    "addr:full":"700 Schuylkill Manor Rd Pottsville PA 17901",
    "addr:housenumber":"700",
    "addr:postcode":"17901",
    "addr:street":"Schuylkill Manor Rd",
    "iso:country":"US",
    "sg:address":"700 Schuylkill Manor Rd",
    "sg:city":"Pottsville",
    "sg:classifiers":[
        {
            "category":"Health Services",
            "subcategory":"Doctor",
            "type":"Services"
        }
    ],
    "sg:phone":"+1 570 622 4113",
    "sg:postcode":"17901",
    "sg:province":"PA",
    "sg:tags":[
        "physician",
        "surgeon",
        "medical"
    ],
    "wof:name":"Pottsville Cancer Clinic",
    "wof:placetype":"venue"
},
  "geometry": {"coordinates":[-76.18671399999999,40.692149],"type":"Point"}
}