{
  "type": "Feature",
  "properties": {
    "iso:country":"US",
    "sg:address":"3092 N Sugan Rd",
    "sg:city":"Solebury",
    "sg:classifiers":[
        {
            "category":"Government",
            "subcategory":"Office",
            "type":"Public Place"
        }
    ],
    "sg:phone":"+1 215 297 5656",
    "sg:postcode":"18963",
    "sg:province":"PA",
    "sg:tags":[
        "village"
    ],
    "wof:name":"Solebury Township Office",
    "wof:placetype":"venue"
},
  "geometry": {"coordinates":[-75.009895,40.381818],"type":"Point"}
}