{
  "type": "Feature",
  "properties": {
    "iso:country":"US",
    "sg:address":"505 E Market St",
    "sg:city":"York",
    "sg:classifiers":[
        {
            "category":"Shopping",
            "subcategory":"Hobbies, Toys, & Games",
            "type":"Retail Goods"
        }
    ],
    "sg:phone":"+1   ",
    "sg:postcode":"17406",
    "sg:province":"PA",
    "wof:name":"Another Choice",
    "wof:placetype":"venue"
},
  "geometry": {"coordinates":[-76.598011,40.007584],"type":"Point"}
}