{
  "type": "Feature",
  "properties": {
    "iso:country":"US",
    "sg:address":"1388 N Perry Hwy",
    "sg:city":"Mercer",
    "sg:classifiers":[
        {
            "category":"Professional",
            "subcategory":"Business Services",
            "type":"Services"
        }
    ],
    "sg:phone":"+1   ",
    "sg:postcode":"16137",
    "sg:province":"PA",
    "wof:name":"International Assoc Lion Club",
    "wof:placetype":"venue"
},
  "geometry": {"coordinates":[-80.23276799999999,41.313194],"type":"Point"}
}