{
  "type": "Feature",
  "properties": {
    "iso:country":"US",
    "sg:address":"342 Hilltop Rd",
    "sg:city":"Friedens",
    "sg:classifiers":[
        {
            "category":"Insurance",
            "subcategory":"Insurance Agent",
            "type":"Services"
        }
    ],
    "sg:phone":"+1   ",
    "sg:postcode":"15541",
    "sg:province":"PA",
    "sg:tags":[
        "broker"
    ],
    "wof:name":"R E Brown",
    "wof:placetype":"venue"
},
  "geometry": {"coordinates":[-78.988179,40.04809],"type":"Point"}
}