{
  "type": "Feature",
  "properties": {
    "iso:country":"US",
    "sg:address":"867 Tioga St",
    "sg:city":"Benton",
    "sg:classifiers":[
        {
            "category":"Government",
            "subcategory":"Office",
            "type":"Public Place"
        }
    ],
    "sg:phone":"+1   ",
    "sg:postcode":"17866",
    "sg:province":"PA",
    "sg:tags":[
        "executive"
    ],
    "wof:name":"Fairmount Township Municipal",
    "wof:placetype":"venue"
},
  "geometry": {"coordinates":[-76.544977,40.7889],"type":"Point"}
}