{
  "type": "Feature",
  "properties": {
    "addr:full":"610 Dallas St York PA 17403",
    "addr:housenumber":"610",
    "addr:postcode":"17403",
    "addr:street":"Dallas St",
    "iso:country":"US",
    "sg:address":"610 Dallas St",
    "sg:city":"York",
    "sg:classifiers":[
        {
            "category":"Wholesale",
            "subcategory":"Drugs",
            "type":"Manufacturing & Wholesale Goods"
        }
    ],
    "sg:phone":"+1   ",
    "sg:postcode":"17403",
    "sg:province":"PA",
    "wof:name":"N Jean McNutt",
    "wof:placetype":"venue"
},
  "geometry": {"coordinates":[-76.70786200000001,39.958691],"type":"Point"}
}