{
  "type": "Feature",
  "properties": {
    "iso:country":"US",
    "sg:address":"2302 N Mascher St",
    "sg:city":"Philadelphia",
    "sg:classifiers":[
        {
            "category":"Organizations",
            "subcategory":"Religious Organization",
            "type":"Services"
        }
    ],
    "sg:phone":"+1 215 426 1001",
    "sg:postcode":"19133",
    "sg:province":"PA",
    "wof:name":"Igelisa De Dios Inc",
    "wof:placetype":"venue"
},
  "geometry": {"coordinates":[-75.13432899999999,39.985129],"type":"Point"}
}