{
  "type": "Feature",
  "properties": {
    "iso:country":"US",
    "sg:address":"4620 Longshore Ave",
    "sg:city":"Philadelphia",
    "sg:classifiers":[
        {
            "category":"Government",
            "subcategory":"Post Office",
            "type":"Public Place"
        }
    ],
    "sg:phone":"+1   ",
    "sg:postcode":"19135",
    "sg:province":"PA",
    "sg:tags":[
        "postal",
        "us"
    ],
    "wof:name":"US Post Office",
    "wof:placetype":"venue"
},
  "geometry": {"coordinates":[-75.04408599999999,40.027048],"type":"Point"}
}