{
  "type": "Feature",
  "properties": {
    "addr:full":"512 Bainbridge St Philadelphia PA 19147",
    "addr:housenumber":"512",
    "addr:postcode":"19147",
    "addr:street":"Bainbridge St",
    "iso:country":"US",
    "sg:address":"512 Bainbridge St",
    "sg:city":"Philadelphia",
    "sg:classifiers":[
        {
            "category":"Retail",
            "subcategory":"Photofinishing",
            "type":"Services"
        }
    ],
    "sg:phone":"+1 215 925 2310",
    "sg:postcode":"19147",
    "sg:province":"PA",
    "sg:tags":[
        "photo"
    ],
    "wof:name":"Robert A Martin",
    "wof:placetype":"venue"
},
  "geometry": {"coordinates":[-75.151685,39.940961],"type":"Point"}
}