{
  "type": "Feature",
  "properties": {
    "addr:full":"648 S 57th St Philadelphia PA 19143",
    "addr:housenumber":"648",
    "addr:postcode":"19143",
    "addr:street":"S 57Th St",
    "iso:country":"US",
    "sg:address":"648 S 57th St",
    "sg:city":"Philadelphia",
    "sg:classifiers":[
        {
            "category":"Organizations",
            "subcategory":"Religious Organization",
            "type":"Services"
        }
    ],
    "sg:phone":"+1 215 474 2288",
    "sg:postcode":"19143",
    "sg:province":"PA",
    "sg:tags":[
        "church"
    ],
    "wof:name":"True House Of God",
    "wof:placetype":"venue"
},
  "geometry": {"coordinates":[-75.237224,39.950324],"type":"Point"}
}