{
  "type": "Feature",
  "properties": {
    "iso:country":"US",
    "sg:address":"2570 Boyce Plaza Rd",
    "sg:city":"Pittsburgh",
    "sg:classifiers":[
        {
            "category":"Banks & Credit Unions",
            "subcategory":"Financial Services",
            "type":"Services"
        }
    ],
    "sg:phone":"+1 412 220 7577",
    "sg:postcode":"15241",
    "sg:province":"PA",
    "sg:tags":[
        "broker",
        "mortgage"
    ],
    "wof:name":"Singlesource Property Solutions",
    "wof:placetype":"venue"
},
  "geometry": {"coordinates":[-80.114316,40.320933],"type":"Point"}
}