{
  "type": "Feature",
  "properties": {
    "addr:full":"5300 Whitaker Ave Philadelphia PA 19124",
    "addr:housenumber":"5300",
    "addr:postcode":"19124",
    "addr:street":"Whitaker Ave",
    "iso:country":"US",
    "sg:address":"5300 Whitaker Ave",
    "sg:city":"Philadelphia",
    "sg:classifiers":[
        {
            "category":"Professional",
            "type":"Services"
        }
    ],
    "sg:phone":"+1 215 288 9114",
    "sg:postcode":"19124",
    "sg:province":"PA",
    "sg:tags":[
        "establishment"
    ],
    "wof:name":"Jomar",
    "wof:placetype":"venue"
},
  "geometry": {"coordinates":[-75.102379,40.032118],"type":"Point"}
}