{
  "type": "Feature",
  "properties": {
    "iso:country":"US",
    "sg:address":"1721 Oak Hill Dr",
    "sg:city":"Huntingdon Vly",
    "sg:classifiers":[
        {
            "category":"Organizations",
            "subcategory":"Professional Association",
            "type":"Services"
        }
    ],
    "sg:phone":"+1 215 947 6018",
    "sg:postcode":"19006",
    "sg:province":"PA",
    "wof:name":"Tall Trees HOA Guard House",
    "wof:placetype":"venue"
},
  "geometry": {"coordinates":[-75.07543,40.10919],"type":"Point"}
}