{
  "type": "Feature",
  "properties": {
    "addr:full":"490 Belfast Rd Nazareth PA 18064",
    "addr:housenumber":"490",
    "addr:postcode":"18064",
    "addr:street":"Belfast Rd",
    "iso:country":"US",
    "sg:address":"490 Belfast Rd",
    "sg:city":"Nazareth",
    "sg:classifiers":[
        {
            "category":"Manufacturing",
            "subcategory":"Rubber & Plastics",
            "type":"Manufacturing & Wholesale Goods"
        }
    ],
    "sg:phone":"+1 610 759 1807",
    "sg:postcode":"18064",
    "sg:province":"PA",
    "sg:tags":[
        "forming"
    ],
    "sg:website":"www.speckplastics.com",
    "wof:name":"Speck Plastics Inc",
    "wof:placetype":"venue"
},
  "geometry": {"coordinates":[-75.28027899999999,40.780544],"type":"Point"}
}