{
  "type": "Feature",
  "properties": {
    "iso:country":"US",
    "sg:address":"3515 Washington Rd Ste 518",
    "sg:city":"Canonsburg",
    "sg:classifiers":[
        {
            "category":"Health Services",
            "subcategory":"Health Practitioner",
            "type":"Services"
        }
    ],
    "sg:phone":"+1 724 941 8730",
    "sg:postcode":"15317",
    "sg:province":"PA",
    "sg:tags":[
        "nutritionist"
    ],
    "sg:website":"www.bariatricsworks.com",
    "wof:name":"Bariatric Weight Loss",
    "wof:placetype":"venue"
},
  "geometry": {"coordinates":[-80.1259,40.275299],"type":"Point"}
}