{
  "type": "Feature",
  "properties": {
    "addr:full":"13460 Monterey Ln Blue Ridge Summit PA 17214",
    "addr:housenumber":"13460",
    "addr:postcode":"17214",
    "addr:street":"Monterey Ln",
    "iso:country":"US",
    "sg:address":"13460 Monterey Ln",
    "sg:city":"Blue Ridge Summit",
    "sg:classifiers":[
        {
            "category":"Professional",
            "type":"Services"
        }
    ],
    "sg:phone":"+1 717 794 2446",
    "sg:postcode":"17214",
    "sg:province":"PA",
    "sg:tags":[
        "caterer"
    ],
    "wof:name":"Summit Business Group",
    "wof:placetype":"venue"
},
  "geometry": {"coordinates":[-77.47110000000001,39.725399],"type":"Point"}
}