{
  "type": "Feature",
  "properties": {
    "addr:full":"5758 Township Line Rd Pipersville PA 18947",
    "addr:housenumber":"5758",
    "addr:postcode":"18947",
    "addr:street":"Township Line Rd",
    "iso:country":"US",
    "sg:address":"5758 Township Line Rd",
    "sg:city":"Pipersville",
    "sg:classifiers":[
        {
            "category":"Building & Trades",
            "subcategory":"Construction",
            "type":"Services"
        }
    ],
    "sg:phone":"+1 215 766 4850",
    "sg:postcode":"18947",
    "sg:province":"PA",
    "sg:tags":[
        "carpentry",
        "contractor"
    ],
    "wof:name":"Kurtco",
    "wof:placetype":"venue"
},
  "geometry": {"coordinates":[-75.139605,40.409147],"type":"Point"}
}