{
  "type": "Feature",
  "properties": {
    "iso:country":"US",
    "sg:address":"49 Renaissance Dr",
    "sg:city":"Irwin",
    "sg:classifiers":[
        {
            "category":"Shopping",
            "subcategory":"Gifts & Souvenirs",
            "type":"Retail Goods"
        }
    ],
    "sg:phone":"+1 724 864 7562",
    "sg:postcode":"15642",
    "sg:province":"PA",
    "sg:tags":[
        "shop"
    ],
    "wof:name":"Margies Tea And Gift Shop",
    "wof:placetype":"venue"
},
  "geometry": {"coordinates":[-79.665611,40.30357],"type":"Point"}
}