{
  "type": "Feature",
  "properties": {
    "iso:country":"US",
    "sg:address":"6741 Lebanon Ave",
    "sg:city":"Philadelphia",
    "sg:classifiers":[
        {
            "category":"Education",
            "subcategory":"Special Training",
            "type":"Public Place"
        }
    ],
    "sg:phone":"+1 215 473 8070",
    "sg:postcode":"19151",
    "sg:province":"PA",
    "sg:tags":[
        "center"
    ],
    "wof:name":"Dreams Learning Ctr",
    "wof:placetype":"venue"
},
  "geometry": {"coordinates":[-75.255264,39.975626],"type":"Point"}
}