{
  "type": "Feature",
  "properties": {
    "iso:country":"US",
    "sg:address":"112 E State St",
    "sg:city":"Kennett Square",
    "sg:classifiers":[
        {
            "category":"Shopping",
            "subcategory":"Clothing, Apparel, & Fashions",
            "type":"Retail Goods"
        }
    ],
    "sg:phone":"+1 610 444 3228",
    "sg:postcode":"19348",
    "sg:province":"PA",
    "sg:tags":[
        "item",
        "boutique"
    ],
    "wof:name":"Sache Boutique LTD",
    "wof:placetype":"venue"
},
  "geometry": {"coordinates":[-75.711457,39.846669],"type":"Point"}
}