{
  "type": "Feature",
  "properties": {
    "iso:country":"US",
    "sg:address":"122 Front St",
    "sg:city":"New Berlin",
    "sg:classifiers":[
        {
            "category":"Professional",
            "subcategory":"Engineering",
            "type":"Services"
        }
    ],
    "sg:phone":"+1 570 966 2860",
    "sg:postcode":"17855",
    "sg:province":"PA",
    "sg:tags":[
        "engineer"
    ],
    "wof:name":"J A Coukart & Assoc",
    "wof:placetype":"venue"
},
  "geometry": {"coordinates":[-76.990117,40.877195],"type":"Point"}
}