{
  "type": "Feature",
  "properties": {
    "iso:country":"US",
    "sg:address":"399 Market St Ste 1",
    "sg:city":"Philadelphia",
    "sg:classifiers":[
        {
            "category":"Communications",
            "subcategory":"Newspaper",
            "type":"Services"
        }
    ],
    "sg:phone":"+1 215 925 1998",
    "sg:postcode":"19106",
    "sg:province":"PA",
    "wof:name":"Barry's Lobby Shop",
    "wof:placetype":"venue"
},
  "geometry": {"coordinates":[-75.147263,39.950371],"type":"Point"}
}