{
  "type": "Feature",
  "properties": {
    "iso:country":"US",
    "sg:address":"1200 Mifflin St",
    "sg:city":"Saxton",
    "sg:classifiers":[
        {
            "category":"Personal",
            "subcategory":"Beauty Salon",
            "type":"Services"
        }
    ],
    "sg:phone":"+1   ",
    "sg:postcode":"16678",
    "sg:province":"PA",
    "sg:tags":[
        "shop"
    ],
    "wof:name":"Sharons Styling Salon",
    "wof:placetype":"venue"
},
  "geometry": {"coordinates":[-78.25242299999999,40.215394],"type":"Point"}
}