{
  "type": "Feature",
  "properties": {
    "iso:country":"US",
    "sg:address":"6725 Frankford Ave",
    "sg:city":"Philadelphia",
    "sg:classifiers":[
        {
            "category":"Shopping",
            "subcategory":"News",
            "type":"Retail Goods"
        }
    ],
    "sg:phone":"+1 215 624 5113",
    "sg:postcode":"19135",
    "sg:province":"PA",
    "wof:name":"RNS News",
    "wof:placetype":"venue"
},
  "geometry": {"coordinates":[-75.051373,40.032098],"type":"Point"}
}