{
  "type": "Feature",
  "properties": {
    "addr:full":"123 Tower Rd Jamestown PA 16134",
    "addr:housenumber":"123",
    "addr:postcode":"16134",
    "addr:street":"Tower Rd",
    "iso:country":"US",
    "sg:address":"123 Tower Rd",
    "sg:city":"Jamestown",
    "sg:classifiers":[
        {
            "category":"Retail",
            "subcategory":"Repair Shop",
            "type":"Services"
        }
    ],
    "sg:phone":"+1 724 932 5784",
    "sg:postcode":"16134",
    "sg:province":"PA",
    "sg:tags":[
        "lock",
        "locksmith"
    ],
    "wof:name":"Jerry's Lock & Key",
    "wof:placetype":"venue"
},
  "geometry": {"coordinates":[-80.41167299999999,41.478749],"type":"Point"}
}