{
  "type": "Feature",
  "properties": {
    "iso:country":"US",
    "sg:address":"2045 Westgate Dr Ste 203",
    "sg:city":"Bethlehem",
    "sg:classifiers":[
        {
            "category":"Health Services",
            "subcategory":"Doctor",
            "type":"Services"
        }
    ],
    "sg:phone":"+1 610 868 8460",
    "sg:postcode":"18017",
    "sg:province":"PA",
    "wof:name":"Field-Munves Ellen MD",
    "wof:placetype":"venue"
},
  "geometry": {"coordinates":[-75.407501,40.640701],"type":"Point"}
}