{
  "type": "Feature",
  "properties": {
    "addr:full":"766 Shenango Rd Beaver Falls PA 15010",
    "addr:housenumber":"766",
    "addr:postcode":"15010",
    "addr:street":"Shenango Rd",
    "iso:country":"US",
    "sg:address":"766 Shenango Rd",
    "sg:city":"Beaver Falls",
    "sg:classifiers":[
        {
            "category":"Home & Garden",
            "subcategory":"Garden Supply",
            "type":"Retail Goods"
        }
    ],
    "sg:phone":"+1   ",
    "sg:postcode":"15010",
    "sg:province":"PA",
    "sg:tags":[
        "nursery"
    ],
    "wof:name":"Man- Care-A -Ban",
    "wof:placetype":"venue"
},
  "geometry": {"coordinates":[-80.37487400000001,40.776441],"type":"Point"}
}