{
  "type": "Feature",
  "properties": {
    "iso:country":"US",
    "sg:address":"5224 Surrey Ct",
    "sg:city":"Allentown",
    "sg:classifiers":[
        {
            "category":"Building & Trades",
            "subcategory":"Construction",
            "type":"Services"
        }
    ],
    "sg:phone":"+1   ",
    "sg:postcode":"18104",
    "sg:province":"PA",
    "sg:tags":[
        "new",
        "commercial"
    ],
    "wof:name":"P Beri & Associates",
    "wof:placetype":"venue"
},
  "geometry": {"coordinates":[-75.567314,40.579617],"type":"Point"}
}