{
  "type": "Feature",
  "properties": {
    "addr:full":"605 Scenery Dr Elizabeth PA 15037",
    "addr:housenumber":"605",
    "addr:postcode":"15037",
    "addr:street":"Scenery Dr",
    "iso:country":"US",
    "sg:address":"605 Scenery Dr",
    "sg:city":"Elizabeth",
    "sg:classifiers":[
        {
            "category":"Personal",
            "subcategory":"Barber",
            "type":"Services"
        }
    ],
    "sg:phone":"+1 412 751 2477",
    "sg:postcode":"15037",
    "sg:province":"PA",
    "wof:name":"Joes Barber & Styling Center",
    "wof:placetype":"venue"
},
  "geometry": {"coordinates":[-79.83767,40.272583],"type":"Point"}
}