{
  "type": "Feature",
  "properties": {
    "iso:country":"US",
    "sg:address":"505 Princeton Dr",
    "sg:city":"King Of Prussia",
    "sg:classifiers":[
        {
            "category":"Professional",
            "subcategory":"Management & Consulting",
            "type":"Services"
        }
    ],
    "sg:phone":"+1 610 265 4058",
    "sg:postcode":"19406",
    "sg:province":"PA",
    "sg:tags":[
        "consultant"
    ],
    "wof:name":"Laurence Leonard SCD Inc",
    "wof:placetype":"venue"
},
  "geometry": {"coordinates":[-75.366573,40.107217],"type":"Point"}
}