{
  "type": "Feature",
  "properties": {
    "iso:country":"US",
    "sg:address":"1335 W Montgomery St",
    "sg:city":"Coal Township",
    "sg:classifiers":[
        {
            "category":"Recreation",
            "type":"Entertainment"
        }
    ],
    "sg:phone":"+1 570 648 3390",
    "sg:postcode":"17866",
    "sg:province":"PA",
    "sg:tags":[
        "parlor",
        "billiard"
    ],
    "wof:name":"Kosmer Pool Room",
    "wof:placetype":"venue"
},
  "geometry": {"coordinates":[-76.57236,40.782143],"type":"Point"}
}