{
  "type": "Feature",
  "properties": {
    "iso:country":"US",
    "sg:address":"2929 N 5th St",
    "sg:city":"Philadelphia",
    "sg:classifiers":[
        {
            "category":"Personal",
            "subcategory":"Tattoo Parlor",
            "type":"Services"
        }
    ],
    "sg:phone":"+1 215 427 9688",
    "sg:postcode":"19133",
    "sg:province":"PA",
    "sg:tags":[
        "tattooing"
    ],
    "wof:name":"Blazing Hot Tattoo's",
    "wof:placetype":"venue"
},
  "geometry": {"coordinates":[-75.139194,39.99622],"type":"Point"}
}