{
  "type": "Feature",
  "properties": {
    "iso:country":"US",
    "sg:address":"3200 Universal Rd",
    "sg:city":"Pittsburgh",
    "sg:classifiers":[
        {
            "category":"Building & Trades",
            "subcategory":"Construction",
            "type":"Services"
        }
    ],
    "sg:phone":"+1 412 793 3950",
    "sg:postcode":"15235",
    "sg:province":"PA",
    "sg:tags":[
        "drywall",
        "contractor"
    ],
    "wof:name":"William Shula",
    "wof:placetype":"venue"
},
  "geometry": {"coordinates":[-79.781025,40.484637],"type":"Point"}
}