{
  "type": "Feature",
  "properties": {
    "iso:country":"US",
    "sg:address":"1421 W Porter St",
    "sg:city":"Philadelphia",
    "sg:classifiers":[
        {
            "category":"Organizations",
            "subcategory":"Religious Organization",
            "type":"Services"
        }
    ],
    "sg:phone":"+1 215 467 8604",
    "sg:postcode":"19145",
    "sg:province":"PA",
    "sg:tags":[
        "clergy"
    ],
    "wof:name":"Roger Hickernell",
    "wof:placetype":"venue"
},
  "geometry": {"coordinates":[-75.17181100000001,39.919598],"type":"Point"}
}