{
  "type": "Feature",
  "properties": {
    "addr:full":"410 Glenn Ave Bloomsburg PA 17815",
    "addr:housenumber":"410",
    "addr:postcode":"17815",
    "addr:street":"Glenn Ave",
    "iso:country":"US",
    "sg:address":"410 Glenn Ave",
    "sg:city":"Bloomsburg",
    "sg:classifiers":[
        {
            "category":"Health Services",
            "subcategory":"Doctor",
            "type":"Services"
        }
    ],
    "sg:phone":"+1 570 784 6077",
    "sg:postcode":"17815",
    "sg:province":"PA",
    "sg:tags":[
        "physician",
        "surgeon",
        "osteopathic"
    ],
    "wof:name":"John L Runyan Dr Do",
    "wof:placetype":"venue"
},
  "geometry": {"coordinates":[-76.453947,41.009039],"type":"Point"}
}