{
  "type": "Feature",
  "properties": {
    "addr:full":"401 Adams Ave Scranton PA 18510",
    "addr:housenumber":"401",
    "addr:postcode":"18510",
    "addr:street":"Adams Ave",
    "iso:country":"US",
    "sg:address":"401 Adams Ave",
    "sg:city":"Scranton",
    "sg:classifiers":[
        {
            "category":"Health Services",
            "subcategory":"Doctor",
            "type":"Services"
        }
    ],
    "sg:phone":"+1 570 347 3322",
    "sg:postcode":"18510",
    "sg:province":"PA",
    "sg:tags":[
        "dentist"
    ],
    "wof:name":"Alan Firestone's Childrens",
    "wof:placetype":"venue"
},
  "geometry": {"coordinates":[-75.65838599999999,41.410645],"type":"Point"}
}