{
  "type": "Feature",
  "properties": {
    "addr:full":"1430 Graham Ave Windber PA 15963",
    "addr:housenumber":"1430",
    "addr:postcode":"15963",
    "addr:street":"Graham Ave",
    "iso:country":"US",
    "sg:address":"1430 Graham Ave",
    "sg:city":"Windber",
    "sg:classifiers":[
        {
            "category":"Professional",
            "subcategory":"Accounting & Tax Preparation",
            "type":"Services"
        }
    ],
    "sg:phone":"+1 814 467 8453",
    "sg:postcode":"15963",
    "sg:province":"PA",
    "sg:tags":[
        "return",
        "filing"
    ],
    "wof:name":"H & R Block Tax Svc",
    "wof:placetype":"venue"
},
  "geometry": {"coordinates":[-78.8312,40.23546],"type":"Point"}
}