{
  "type": "Feature",
  "properties": {
    "addr:full":"340 Albert St Turtle Creek PA 15145",
    "addr:housenumber":"340",
    "addr:postcode":"15145",
    "addr:street":"Albert St",
    "iso:country":"US",
    "sg:address":"340 Albert St",
    "sg:city":"Turtle Creek",
    "sg:classifiers":[
        {
            "category":"Banks & Credit Unions",
            "subcategory":"Bank",
            "type":"Services"
        }
    ],
    "sg:phone":"+1   ",
    "sg:postcode":"15145",
    "sg:province":"PA",
    "sg:tags":[
        "loan",
        "broker"
    ],
    "wof:name":"Janet Cortinovis",
    "wof:placetype":"venue"
},
  "geometry": {"coordinates":[-79.819301,40.407143],"type":"Point"}
}