{
  "type": "Feature",
  "properties": {
    "iso:country":"US",
    "sg:address":"860 Dietz Rd",
    "sg:city":"York",
    "sg:classifiers":[
        {
            "category":"Building & Trades",
            "subcategory":"Construction",
            "type":"Services"
        }
    ],
    "sg:phone":"+1 717 244 5777",
    "sg:postcode":"17402",
    "sg:province":"PA",
    "sg:tags":[
        "masonry",
        "contractor"
    ],
    "wof:name":"L Myers Merlin Masonry Contrs",
    "wof:placetype":"venue"
},
  "geometry": {"coordinates":[-76.61206900000001,39.94226],"type":"Point"}
}