{
  "type": "Feature",
  "properties": {
    "addr:full":"426 Primos Ave Folcroft PA 19032",
    "addr:housenumber":"426",
    "addr:postcode":"19032",
    "addr:street":"Primos Ave",
    "iso:country":"US",
    "sg:address":"426 Primos Ave",
    "sg:city":"Folcroft",
    "sg:classifiers":[
        {
            "category":"Social Services",
            "subcategory":"Child Care",
            "type":"Services"
        }
    ],
    "sg:phone":"+1   ",
    "sg:postcode":"19032",
    "sg:province":"PA",
    "sg:tags":[
        "day"
    ],
    "wof:name":"Munchkin Land Day Care Center",
    "wof:placetype":"venue"
},
  "geometry": {"coordinates":[-75.278764,39.898298],"type":"Point"}
}