{
  "type": "Feature",
  "properties": {
    "addr:full":"67 S 5th Ave Coatesville PA 19320",
    "addr:housenumber":"67",
    "addr:postcode":"19320",
    "addr:street":"S 5Th Ave",
    "iso:country":"US",
    "sg:address":"67 S 5th Ave",
    "sg:city":"Coatesville",
    "sg:classifiers":[
        {
            "category":"Food & Beverages",
            "subcategory":"Groceries & Convenience Stores",
            "type":"Retail Goods"
        }
    ],
    "sg:phone":"+1   ",
    "sg:postcode":"19320",
    "sg:province":"PA",
    "wof:name":"Sam & Laurie Grocery & Deli",
    "wof:placetype":"venue"
},
  "geometry": {"coordinates":[-75.81568900000001,39.982873],"type":"Point"}
}