{
  "type": "Feature",
  "properties": {
    "iso:country":"US",
    "sg:address":"4627 Spruce St",
    "sg:city":"Philadelphia",
    "sg:classifiers":[
        {
            "category":"Professional",
            "subcategory":"Research",
            "type":"Services"
        }
    ],
    "sg:phone":"+1   ",
    "sg:postcode":"19139",
    "sg:province":"PA",
    "sg:tags":[
        "nonphysical",
        "commercial"
    ],
    "wof:name":"Vaughn Napoleon Ndr",
    "wof:placetype":"venue"
},
  "geometry": {"coordinates":[-75.21608000000001,39.953433],"type":"Point"}
}