{
  "type": "Feature",
  "properties": {
    "addr:full":"617 Tree St Philadelphia PA 19148",
    "addr:housenumber":"617",
    "addr:postcode":"19148",
    "addr:street":"Tree St",
    "iso:country":"US",
    "sg:address":"617 Tree St",
    "sg:city":"Philadelphia",
    "sg:classifiers":[
        {
            "category":"Building & Trades",
            "subcategory":"Construction",
            "type":"Services"
        }
    ],
    "sg:phone":"+1 215 468 2012",
    "sg:postcode":"19148",
    "sg:province":"PA",
    "sg:tags":[
        "contractor"
    ],
    "wof:name":"Security Ironworks",
    "wof:placetype":"venue"
},
  "geometry": {"coordinates":[-75.158368,39.921289],"type":"Point"}
}