{
  "type": "Feature",
  "properties": {
    "iso:country":"US",
    "sg:address":"90 Walker Ln",
    "sg:city":"Newtown",
    "sg:classifiers":[
        {
            "category":"Manufacturing",
            "subcategory":"Printing",
            "type":"Manufacturing & Wholesale Goods"
        }
    ],
    "sg:phone":"+1 215 579 4200",
    "sg:postcode":"18940",
    "sg:province":"PA",
    "sg:tags":[
        "bureau",
        "typography"
    ],
    "wof:name":"Bucks County Digital Imaging",
    "wof:placetype":"venue"
},
  "geometry": {"coordinates":[-74.912263,40.227969],"type":"Point"}
}