{
  "type": "Feature",
  "properties": {
    "iso:country":"US",
    "sg:address":"3610 Forest Ave",
    "sg:city":"Homestead",
    "sg:classifiers":[
        {
            "category":"Banks & Credit Unions",
            "subcategory":"Investment Brokerage",
            "type":"Services"
        }
    ],
    "sg:phone":"+1 412 462 5282",
    "sg:postcode":"15120",
    "sg:province":"PA",
    "sg:tags":[
        "fund",
        "security",
        "mutual"
    ],
    "sg:website":"http://www.fscorp.com",
    "wof:name":"Advantage Capital Corporation",
    "wof:placetype":"venue"
},
  "geometry": {"coordinates":[-79.90813,40.384838],"type":"Point"}
}