{
  "type": "Feature",
  "properties": {
    "iso:country":"US",
    "sg:address":"293 Little Chicago Rd",
    "sg:city":"Carmichaels",
    "sg:classifiers":[
        {
            "category":"Home & Garden",
            "subcategory":"Building Materials",
            "type":"Retail Goods"
        }
    ],
    "sg:phone":"+1 724 966 5885",
    "sg:postcode":"15320",
    "sg:province":"PA",
    "sg:tags":[
        "garage",
        "opener",
        "door"
    ],
    "wof:name":"Garage Doors By Chris",
    "wof:placetype":"venue"
},
  "geometry": {"coordinates":[-79.960753,39.860052],"type":"Point"}
}