{
  "type": "Feature",
  "properties": {
    "iso:country":"US",
    "sg:address":"9804 Three Degree Rd",
    "sg:city":"Allison Park",
    "sg:classifiers":[
        {
            "category":"Health Services",
            "subcategory":"Doctor",
            "type":"Services"
        }
    ],
    "sg:phone":"+1 412 635 9768",
    "sg:postcode":"15101",
    "sg:province":"PA",
    "sg:tags":[
        "physician",
        "surgeon"
    ],
    "wof:name":"Robert P Hennon MD",
    "wof:placetype":"venue"
},
  "geometry": {"coordinates":[-80.000749,40.587244],"type":"Point"}
}