{
  "type": "Feature",
  "properties": {
    "iso:country":"US",
    "sg:address":"4101 Post Rd",
    "sg:city":"Marcus Hook",
    "sg:classifiers":[
        {
            "category":"Manufacturing",
            "subcategory":"Petroleum Products",
            "type":"Manufacturing & Wholesale Goods"
        }
    ],
    "sg:phone":"+1   ",
    "sg:postcode":"19061",
    "sg:province":"PA",
    "sg:tags":[
        "refining"
    ],
    "wof:name":"Conocophillips Company",
    "wof:placetype":"venue"
},
  "geometry": {"coordinates":[-75.40574599999999,39.826074],"type":"Point"}
}