{
  "type": "Feature",
  "properties": {
    "iso:country":"US",
    "sg:address":"709 Union Blvd",
    "sg:city":"Allentown",
    "sg:classifiers":[
        {
            "category":"Food & Beverages",
            "subcategory":"Bakery",
            "type":"Retail Goods"
        }
    ],
    "sg:phone":"+1 610 432 2222",
    "sg:postcode":"18109",
    "sg:province":"PA",
    "sg:tags":[
        "doughnut"
    ],
    "wof:name":"Dunkin Donuts",
    "wof:placetype":"venue"
},
  "geometry": {"coordinates":[-75.447953,40.624126],"type":"Point"}
}