{
  "type": "Feature",
  "properties": {
    "iso:country":"US",
    "sg:address":"2379 Byecroft Rd",
    "sg:city":"Buckingham",
    "sg:classifiers":[
        {
            "category":"Health Services",
            "subcategory":"Doctor",
            "type":"Services"
        }
    ],
    "sg:phone":"+1 215 794 7128",
    "sg:postcode":"18912",
    "sg:province":"PA",
    "wof:name":"Ettinger Bruce E Dr",
    "wof:placetype":"venue"
},
  "geometry": {"coordinates":[-75.03198,40.33586],"type":"Point"}
}