{
  "type": "Feature",
  "properties": {
    "addr:full":"116 Lehigh Valley Mall Whitehall PA 18052",
    "addr:housenumber":"116",
    "addr:postcode":"18052",
    "addr:street":"Lehigh Valley Mall",
    "iso:country":"US",
    "sg:address":"116 Lehigh Valley Mall",
    "sg:city":"Whitehall",
    "sg:classifiers":[
        {
            "category":"Shopping",
            "subcategory":"Clothing, Apparel, & Fashions",
            "type":"Retail Goods"
        }
    ],
    "sg:phone":"+1 610 266 9708",
    "sg:postcode":"18052",
    "sg:province":"PA",
    "sg:tags":[
        "accessory",
        "clothing",
        "women's"
    ],
    "sg:website":"www.expressfashion.com",
    "wof:name":"Express",
    "wof:placetype":"venue"
},
  "geometry": {"coordinates":[-75.481201,40.633301],"type":"Point"}
}