{
  "type": "Feature",
  "properties": {
    "addr:full":"186 Shenks Ferry Rd Conestoga PA 17516",
    "addr:housenumber":"186",
    "addr:postcode":"17516",
    "addr:street":"Shenks Ferry Rd",
    "iso:country":"US",
    "sg:address":"186 Shenks Ferry Rd",
    "sg:city":"Conestoga",
    "sg:classifiers":[
        {
            "category":"Building & Trades",
            "subcategory":"Construction",
            "type":"Services"
        }
    ],
    "sg:phone":"+1 717 629 2756",
    "sg:postcode":"17516",
    "sg:province":"PA",
    "sg:tags":[
        "demolition",
        "contractor"
    ],
    "wof:name":"Conestoga Land Clearing",
    "wof:placetype":"venue"
},
  "geometry": {"coordinates":[-76.355752,39.920504],"type":"Point"}
}