{
  "type": "Feature",
  "properties": {
    "iso:country":"US",
    "sg:address":"728 Christian St",
    "sg:city":"Philadelphia",
    "sg:classifiers":[
        {
            "category":"Professional",
            "subcategory":"Accounting & Tax Preparation",
            "type":"Services"
        }
    ],
    "sg:phone":"+1 215 923 9367",
    "sg:postcode":"19147",
    "sg:province":"PA",
    "sg:tags":[
        "return",
        "filing"
    ],
    "wof:name":"1040 Now",
    "wof:placetype":"venue"
},
  "geometry": {"coordinates":[-75.15601100000001,39.938379],"type":"Point"}
}