{
  "type": "Feature",
  "properties": {
    "addr:full":"4611 Lycoming Mall Dr Montoursville PA 17754",
    "addr:housenumber":"4611",
    "addr:postcode":"17754",
    "addr:street":"Lycoming Mall Dr",
    "iso:country":"US",
    "sg:address":"4611 Lycoming Mall Dr",
    "sg:city":"Montoursville",
    "sg:classifiers":[
        {
            "category":"Recreation",
            "type":"Entertainment"
        },
        {
            "category":"Shopping",
            "subcategory":"Bicycles & Sporting Goods",
            "type":"Retail Goods"
        }
    ],
    "sg:phone":"+1 570 368 1497",
    "sg:postcode":"17754",
    "sg:province":"PA",
    "sg:tags":[
        "paint",
        "ball",
        "sport"
    ],
    "wof:name":"Point-Break Paint Ball",
    "wof:placetype":"venue"
},
  "geometry": {"coordinates":[-76.888876,41.245218],"type":"Point"}
}