{
  "type": "Feature",
  "properties": {
    "iso:country":"US",
    "sg:address":"710 W Chocolate Ave",
    "sg:city":"Hershey",
    "sg:classifiers":[
        {
            "category":"Shopping",
            "subcategory":"Computers & Home Electronics",
            "type":"Retail Goods"
        }
    ],
    "sg:phone":"+1 717 533 3670",
    "sg:postcode":"17033",
    "sg:province":"PA",
    "sg:tags":[
        "furniture",
        "store",
        "software"
    ],
    "wof:name":"Staples the Office Superstore",
    "wof:placetype":"venue"
},
  "geometry": {"coordinates":[-76.664703,40.2803],"type":"Point"}
}