{
  "type": "Feature",
  "properties": {
    "iso:country":"US",
    "sg:address":"340 Glen Gary Rd",
    "sg:city":"Havertown",
    "sg:classifiers":[
        {
            "category":"Wholesale",
            "subcategory":"Construction Materials",
            "type":"Manufacturing & Wholesale Goods"
        }
    ],
    "sg:phone":"+1   ",
    "sg:postcode":"19083",
    "sg:province":"PA",
    "sg:tags":[
        "hardware"
    ],
    "wof:name":"Dan Eisenfeld & Associates",
    "wof:placetype":"venue"
},
  "geometry": {"coordinates":[-75.332142,39.972749],"type":"Point"}
}