{
  "type": "Feature",
  "properties": {
    "iso:country":"US",
    "sg:address":"845 3rd Ave",
    "sg:city":"Mountain Top",
    "sg:classifiers":[
        {
            "category":"Professional",
            "type":"Services"
        }
    ],
    "sg:phone":"+1   ",
    "sg:postcode":"18707",
    "sg:province":"PA",
    "wof:name":"Autumn Winds Inc",
    "wof:placetype":"venue"
},
  "geometry": {"coordinates":[-75.943258,41.120347],"type":"Point"}
}