{
  "type": "Feature",
  "properties": {
    "iso:country":"US",
    "sg:address":"2760 E Pacific St",
    "sg:city":"Philadelphia",
    "sg:classifiers":[
        {
            "category":"Building & Trades",
            "subcategory":"Locksmith",
            "type":"Services"
        }
    ],
    "sg:phone":"+1 215 525 5986",
    "sg:postcode":"19134",
    "sg:province":"PA",
    "sg:tags":[
        "key"
    ],
    "wof:name":"Emergency Locksmith",
    "wof:placetype":"venue"
},
  "geometry": {"coordinates":[-75.091419,39.988462],"type":"Point"}
}