{
  "type": "Feature",
  "properties": {
    "iso:country":"US",
    "sg:address":"1490 Adams Ave",
    "sg:city":"Harrisburg",
    "sg:classifiers":[
        {
            "category":"Manufacturing",
            "subcategory":"Printing",
            "type":"Manufacturing & Wholesale Goods"
        }
    ],
    "sg:phone":"+1 717 671 8825",
    "sg:postcode":"17112",
    "sg:province":"PA",
    "sg:tags":[
        "printer"
    ],
    "wof:name":"Cooper Printing",
    "wof:placetype":"venue"
},
  "geometry": {"coordinates":[-76.804969,40.341425],"type":"Point"}
}