{
  "type": "Feature",
  "properties": {
    "addr:full":"145 E 8th Ave Homestead PA 15120",
    "addr:housenumber":"145",
    "addr:postcode":"15120",
    "addr:street":"E 8Th Ave",
    "iso:country":"US",
    "sg:address":"145 E 8th Ave",
    "sg:city":"Homestead",
    "sg:classifiers":[
        {
            "category":"Banks & Credit Unions",
            "subcategory":"Bank",
            "type":"Services"
        }
    ],
    "sg:phone":"+1   ",
    "sg:postcode":"15120",
    "sg:province":"PA",
    "sg:tags":[
        "national",
        "commercial"
    ],
    "wof:name":"PNC",
    "wof:placetype":"venue"
},
  "geometry": {"coordinates":[-79.911446,40.40663],"type":"Point"}
}