{
  "type": "Feature",
  "properties": {
    "iso:country":"US",
    "sg:address":"5440 N 6th St",
    "sg:city":"Philadelphia",
    "sg:classifiers":[
        {
            "category":"Freight",
            "type":"Transportation"
        }
    ],
    "sg:phone":"+1 215 455 5555",
    "sg:postcode":"19120",
    "sg:province":"PA",
    "sg:tags":[
        "warehouse",
        "self"
    ],
    "wof:name":"Mr Storage",
    "wof:placetype":"venue"
},
  "geometry": {"coordinates":[-75.13291700000001,40.034887],"type":"Point"}
}