{
  "type": "Feature",
  "properties": {
    "addr:full":"32 Plumly Way Southampton PA 18966",
    "addr:housenumber":"32",
    "addr:postcode":"18966",
    "addr:street":"Plumly Way",
    "iso:country":"US",
    "sg:address":"32 Plumly Way",
    "sg:city":"Southampton",
    "sg:classifiers":[
        {
            "category":"Professional",
            "subcategory":"Accounting & Tax Preparation",
            "type":"Services"
        }
    ],
    "sg:phone":"+1 215 579 1465",
    "sg:postcode":"18966",
    "sg:province":"PA",
    "sg:tags":[
        "accountant"
    ],
    "wof:name":"Fast Track Accounting Services",
    "wof:placetype":"venue"
},
  "geometry": {"coordinates":[-74.966144,40.207142],"type":"Point"}
}