{
  "type": "Feature",
  "properties": {
    "addr:full":"2395 York Rd Jamison PA 18929",
    "addr:housenumber":"2395",
    "addr:postcode":"18929",
    "addr:street":"York Rd",
    "iso:country":"US",
    "sg:address":"2395 York Rd",
    "sg:city":"Jamison",
    "sg:classifiers":[
        {
            "category":"Retail",
            "subcategory":"Laundry & Dry Cleaning",
            "type":"Services"
        }
    ],
    "sg:phone":"+1   ",
    "sg:postcode":"18929",
    "sg:province":"PA",
    "sg:tags":[
        "drycleaning",
        "plant"
    ],
    "wof:name":"Janes Cleaners",
    "wof:placetype":"venue"
},
  "geometry": {"coordinates":[-75.086516,40.260805],"type":"Point"}
}