{
  "type": "Feature",
  "properties": {
    "iso:country":"US",
    "sg:address":"675 Estelle Dr",
    "sg:city":"Lancaster",
    "sg:classifiers":[
        {
            "category":"Professional",
            "subcategory":"Lawyer & Legal Services",
            "type":"Services"
        }
    ],
    "sg:phone":"+1 717 898 9898",
    "sg:postcode":"17601",
    "sg:province":"PA",
    "sg:tags":[
        "attorney"
    ],
    "wof:name":"James F Heinly Law Offices",
    "wof:placetype":"venue"
},
  "geometry": {"coordinates":[-76.39783199999999,40.054693],"type":"Point"}
}