{
  "type": "Feature",
  "properties": {
    "iso:country":"US",
    "sg:address":"733 Main St",
    "sg:city":"Avoca",
    "sg:classifiers":[
        {
            "category":"Social Services",
            "subcategory":"Child Care",
            "type":"Services"
        }
    ],
    "sg:phone":"+1 570 457 2425",
    "sg:postcode":"18641",
    "sg:province":"PA",
    "wof:name":"Close To Home Child Care",
    "wof:placetype":"venue"
},
  "geometry": {"coordinates":[-75.740965,41.339006],"type":"Point"}
}