{
  "type": "Feature",
  "properties": {
    "addr:full":"3497 Industrial Hwy York PA 17402",
    "addr:housenumber":"3497",
    "addr:postcode":"17402",
    "addr:street":"Industrial Hwy",
    "iso:country":"US",
    "sg:address":"3497 Industrial Hwy",
    "sg:city":"York",
    "sg:classifiers":[
        {
            "category":"Insurance",
            "subcategory":"Insurance Agent",
            "type":"Services"
        },
        {
            "category":"Insurance",
            "subcategory":"Hazard Insurance",
            "type":"Services"
        }
    ],
    "sg:phone":"+1 717 755 7440",
    "sg:postcode":"17402",
    "sg:province":"PA",
    "sg:tags":[
        "consultant",
        "commercial",
        "analyst",
        "business"
    ],
    "wof:name":"Integrated Financial Resource Group",
    "wof:placetype":"venue"
},
  "geometry": {"coordinates":[-76.654788,39.983277],"type":"Point"}
}