{
  "type": "Feature",
  "properties": {
    "addr:full":"40 N Center St Canton PA 17724",
    "addr:housenumber":"40",
    "addr:postcode":"17724",
    "addr:street":"N Center St",
    "iso:country":"US",
    "sg:address":"40 N Center St",
    "sg:city":"Canton",
    "sg:classifiers":[
        {
            "category":"Retail",
            "subcategory":"Funeral Services",
            "type":"Services"
        }
    ],
    "sg:phone":"+1 570 673 3193",
    "sg:postcode":"17724",
    "sg:province":"PA",
    "sg:tags":[
        "director"
    ],
    "wof:name":"Morse & Kleese Funeral Home",
    "wof:placetype":"venue"
},
  "geometry": {"coordinates":[-76.851874,41.656403],"type":"Point"}
}