{
  "type": "Feature",
  "properties": {
    "iso:country":"US",
    "sg:address":"118 W High St",
    "sg:city":"Topton",
    "sg:classifiers":[
        {
            "category":"Manufacturing",
            "subcategory":"Tools & Machinery",
            "type":"Manufacturing & Wholesale Goods"
        }
    ],
    "sg:phone":"+1   ",
    "sg:postcode":"19562",
    "sg:province":"PA",
    "sg:tags":[
        "surgical",
        "mfg"
    ],
    "wof:name":"Specailty Milworks",
    "wof:placetype":"venue"
},
  "geometry": {"coordinates":[-75.71072100000001,40.5046],"type":"Point"}
}