{
  "type": "Feature",
  "properties": {
    "iso:country":"US",
    "sg:address":"3045 Main St",
    "sg:city":"West Middlesex",
    "sg:classifiers":[
        {
            "category":"Real Estate",
            "subcategory":"Real Estate Operator",
            "type":"Services"
        }
    ],
    "sg:phone":"+1   ",
    "sg:postcode":"16159",
    "sg:province":"PA",
    "sg:tags":[
        "building",
        "apartment"
    ],
    "wof:name":"A G Evans Apartment Rentals",
    "wof:placetype":"venue"
},
  "geometry": {"coordinates":[-80.451004,41.174986],"type":"Point"}
}