{
  "type": "Feature",
  "properties": {
    "iso:country":"US",
    "sg:address":"230 Osceola Mill Rd",
    "sg:city":"Gordonville",
    "sg:classifiers":[
        {
            "category":"Building & Trades",
            "subcategory":"Construction",
            "type":"Services"
        }
    ],
    "sg:phone":"+1   ",
    "sg:postcode":"17529",
    "sg:province":"PA",
    "sg:tags":[
        "home"
    ],
    "wof:name":"Dave Esh Builders",
    "wof:placetype":"venue"
},
  "geometry": {"coordinates":[-76.083339,40.02626],"type":"Point"}
}