{
  "type": "Feature",
  "properties": {
    "iso:country":"US",
    "sg:address":"1315 Walnut St Ste 1714",
    "sg:city":"Philadelphia",
    "sg:classifiers":[
        {
            "category":"Building & Trades",
            "subcategory":"Construction",
            "type":"Services"
        }
    ],
    "sg:phone":"+1 215 717 1094",
    "sg:postcode":"19107",
    "sg:province":"PA",
    "sg:tags":[
        "interior",
        "design"
    ],
    "wof:name":"Michael Shannon Designs",
    "wof:placetype":"venue"
},
  "geometry": {"coordinates":[-75.162902,39.949195],"type":"Point"}
}