{
  "type": "Feature",
  "properties": {
    "iso:country":"US",
    "sg:address":"3 Glenn Cir",
    "sg:city":"Glenside",
    "sg:classifiers":[
        {
            "category":"Health Services",
            "subcategory":"Clinic",
            "type":"Services"
        }
    ],
    "sg:phone":"+1   ",
    "sg:postcode":"19038",
    "sg:province":"PA",
    "sg:tags":[
        "home",
        "care"
    ],
    "wof:name":"Special Care Nurses",
    "wof:placetype":"venue"
},
  "geometry": {"coordinates":[-75.211477,40.095194],"type":"Point"}
}