{
  "type": "Feature",
  "properties": {
    "iso:country":"US",
    "sg:address":"2500 Hamilton Ave",
    "sg:city":"Glenshaw",
    "sg:classifiers":[
        {
            "category":"Professional",
            "subcategory":"Advertising",
            "type":"Services"
        }
    ],
    "sg:phone":"+1   ",
    "sg:postcode":"15116",
    "sg:province":"PA",
    "sg:tags":[
        "agency"
    ],
    "wof:name":"Telxtra LLC",
    "wof:placetype":"venue"
},
  "geometry": {"coordinates":[-79.980193,40.538989],"type":"Point"}
}