{
  "type": "Feature",
  "properties": {
    "iso:country":"US",
    "sg:address":"2 Walnut Grove Dr",
    "sg:city":"Horsham",
    "sg:classifiers":[
        {
            "category":"Banks & Credit Unions",
            "subcategory":"Bank",
            "type":"Services"
        }
    ],
    "sg:phone":"+1   ",
    "sg:postcode":"19044",
    "sg:province":"PA",
    "sg:tags":[
        "personal",
        "institution"
    ],
    "wof:name":"HFC",
    "wof:placetype":"venue"
},
  "geometry": {"coordinates":[-75.14258100000001,40.167056],"type":"Point"}
}