{
  "type": "Feature",
  "properties": {
    "addr:full":"254 Twin Hills Dr Pittsburgh PA 15216",
    "addr:housenumber":"254",
    "addr:postcode":"15216",
    "addr:street":"Twin Hills Dr",
    "iso:country":"US",
    "sg:address":"254 Twin Hills Dr",
    "sg:city":"Pittsburgh",
    "sg:classifiers":[
        {
            "category":"Insurance",
            "subcategory":"Insurance Agent",
            "type":"Services"
        }
    ],
    "sg:phone":"+1   ",
    "sg:postcode":"15216",
    "sg:province":"PA",
    "wof:name":"Wm J Eckenrode Insurance",
    "wof:placetype":"venue"
},
  "geometry": {"coordinates":[-80.05055,40.398615],"type":"Point"}
}