{
  "type": "Feature",
  "properties": {
    "iso:country":"US",
    "sg:address":"305 S Balderston Dr",
    "sg:city":"Exton",
    "sg:classifiers":[
        {
            "category":"Social Services",
            "subcategory":"Child Care",
            "type":"Services"
        }
    ],
    "sg:phone":"+1   ",
    "sg:postcode":"19341",
    "sg:province":"PA",
    "sg:tags":[
        "day"
    ],
    "wof:name":"Clerys Group Day Care",
    "wof:placetype":"venue"
},
  "geometry": {"coordinates":[-75.65307,40.031172],"type":"Point"}
}