{
  "type": "Feature",
  "properties": {
    "iso:country":"US",
    "sg:address":"5309 Chancellor St",
    "sg:city":"Philadelphia",
    "sg:classifiers":[
        {
            "category":"Community Center",
            "subcategory":"Youth",
            "type":"Public Place"
        }
    ],
    "sg:phone":"+1 215 983 8426",
    "sg:postcode":"19139",
    "sg:province":"PA",
    "wof:name":"Girl U Can Do It Inc",
    "wof:placetype":"venue"
},
  "geometry": {"coordinates":[-75.22775300000001,39.956649],"type":"Point"}
}