{
  "type": "Feature",
  "properties": {
    "iso:country":"US",
    "sg:address":"1124 N 3rd St",
    "sg:city":"Philadelphia",
    "sg:classifiers":[
        {
            "category":"Home & Garden",
            "subcategory":"Household Appliances",
            "type":"Retail Goods"
        },
        {
            "category":"Building & Trades",
            "subcategory":"Construction",
            "type":"Services"
        }
    ],
    "sg:phone":"+1 215 763 4920",
    "sg:postcode":"19123",
    "sg:province":"PA",
    "sg:tags":[
        "repair",
        "dishwashing",
        "system",
        "specialty",
        "machine",
        "heating",
        "contractor",
        "air conditioning"
    ],
    "sg:website":"http://www.obrienservice.com",
    "wof:name":"O'brien's Service Co. Inc.",
    "wof:placetype":"venue"
},
  "geometry": {"coordinates":[-75.14182599999999,39.968305],"type":"Point"}
}