{
  "type": "Feature",
  "properties": {
    "iso:country":"US",
    "sg:address":"1712 Chestnut St",
    "sg:city":"Philadelphia",
    "sg:classifiers":[
        {
            "category":"Shopping",
            "subcategory":"Department Store",
            "type":"Retail Goods"
        }
    ],
    "sg:phone":"+1 215 972 0488",
    "sg:postcode":"19103",
    "sg:province":"PA",
    "wof:name":"Boltons",
    "wof:placetype":"venue"
},
  "geometry": {"coordinates":[-75.168964,39.951493],"type":"Point"}
}