{
  "type": "Feature",
  "properties": {
    "addr:full":"143 Palsgrove Way Exton PA 19335",
    "addr:housenumber":"143",
    "addr:postcode":"19335",
    "addr:street":"Palsgrove Way",
    "iso:country":"US",
    "sg:address":"143 Palsgrove Way",
    "sg:city":"Exton",
    "sg:classifiers":[
        {
            "category":"Real Estate",
            "subcategory":"Developer",
            "type":"Services"
        }
    ],
    "sg:phone":"+1 610 458 1000",
    "sg:postcode":"19335",
    "sg:province":"PA",
    "wof:name":"Toll Brothers Inc",
    "wof:placetype":"venue"
},
  "geometry": {"coordinates":[-75.694367,40.089752],"type":"Point"}
}