{
  "type": "Feature",
  "properties": {
    "addr:full":"1315 E Passyunk Ave Philadelphia PA 19147",
    "addr:housenumber":"1315",
    "addr:postcode":"19147",
    "addr:street":"E Passyunk Ave",
    "iso:country":"US",
    "sg:address":"1315 E Passyunk Ave",
    "sg:city":"Philadelphia",
    "sg:classifiers":[
        {
            "category":"Retail",
            "subcategory":"Auto Repair",
            "type":"Services"
        }
    ],
    "sg:phone":"+1 215 336 4916",
    "sg:postcode":"19147",
    "sg:province":"PA",
    "sg:tags":[
        "repairing",
        "automobile"
    ],
    "wof:name":"Pat's Auto & Truck Repair Inc",
    "wof:placetype":"venue"
},
  "geometry": {"coordinates":[-75.159897,39.932701],"type":"Point"}
}