{
  "type": "Feature",
  "properties": {
    "iso:country":"US",
    "sg:address":"1701 Dover St",
    "sg:city":"Philadelphia",
    "sg:classifiers":[
        {
            "category":"Building & Trades",
            "subcategory":"Locksmith",
            "type":"Services"
        }
    ],
    "sg:phone":"+1 267 299 1256",
    "sg:postcode":"19102",
    "sg:province":"PA",
    "sg:tags":[
        "key"
    ],
    "wof:name":"Locksmith",
    "wof:placetype":"venue"
},
  "geometry": {"coordinates":[-75.181105,39.98167],"type":"Point"}
}