{
  "type": "Feature",
  "properties": {
    "iso:country":"US",
    "sg:address":"160 Pittsburgh St",
    "sg:city":"Uniontown",
    "sg:classifiers":[
        {
            "category":"Health Services",
            "subcategory":"Doctor",
            "type":"Services"
        }
    ],
    "sg:phone":"+1 724 437 7695",
    "sg:postcode":"15401",
    "sg:province":"PA",
    "sg:tags":[
        "dentist"
    ],
    "wof:name":"Uniontown Orthodontics",
    "wof:placetype":"venue"
},
  "geometry": {"coordinates":[-79.72769,39.906885],"type":"Point"}
}