{
  "type": "Feature",
  "properties": {
    "iso:country":"US",
    "sg:address":"190 Industrial Dr N",
    "sg:city":"Easton",
    "sg:classifiers":[
        {
            "category":"Utilities",
            "subcategory":"Fuel Oil & Lpg",
            "type":"Services"
        },
        {
            "category":"Building & Trades",
            "subcategory":"Construction",
            "type":"Services"
        },
        {
            "category":"Bars & Pubs",
            "subcategory":"Champagne Bar",
            "type":"Food & Drink"
        }
    ],
    "sg:phone":"+1 484 373 4779",
    "sg:postcode":"18042",
    "sg:province":"PA",
    "sg:tags":[
        "system",
        "coke",
        "specialty",
        "contractor",
        "coal",
        "heating",
        "oils-fuel",
        "air conditioning"
    ],
    "sg:website":"http://ahfuel.com",
    "wof:name":"Aerni & Hitzel Fuel Incorporated",
    "wof:placetype":"venue"
},
  "geometry": {"coordinates":[-75.216724,40.671661],"type":"Point"}
}