{
  "type": "Feature",
  "properties": {
    "iso:country":"US",
    "sg:address":"536 Broadway",
    "sg:city":"Pitcairn",
    "sg:classifiers":[
        {
            "category":"Health Services",
            "subcategory":"Podiatrist",
            "type":"Services"
        }
    ],
    "sg:phone":"+1 412 372 4150",
    "sg:postcode":"15140",
    "sg:province":"PA",
    "wof:name":"Amy L Wahl DPM",
    "wof:placetype":"venue"
},
  "geometry": {"coordinates":[-79.777727,40.401891],"type":"Point"}
}