{
  "type": "Feature",
  "properties": {
    "iso:country":"US",
    "sg:address":"304 Delaware Ave",
    "sg:city":"North Versailles",
    "sg:classifiers":[
        {
            "category":"Organizations",
            "subcategory":"Community Association",
            "type":"Services"
        }
    ],
    "sg:phone":"+1   ",
    "sg:postcode":"15137",
    "sg:province":"PA",
    "wof:name":"Masonic Hall",
    "wof:placetype":"venue"
},
  "geometry": {"coordinates":[-79.818091,40.374594],"type":"Point"}
}