{
  "type": "Feature",
  "properties": {
    "iso:country":"US",
    "sg:address":"4355 New Falls Rd",
    "sg:city":"Levittown",
    "sg:classifiers":[
        {
            "category":"Health Services",
            "subcategory":"Chiropractor",
            "type":"Services"
        }
    ],
    "sg:phone":"+1 215 949 3300",
    "sg:postcode":"19056",
    "sg:province":"PA",
    "wof:name":"Hartman Family Chiropractic Center",
    "wof:placetype":"venue"
},
  "geometry": {"coordinates":[-74.880402,40.137299],"type":"Point"}
}