{
  "type": "Feature",
  "properties": {
    "iso:country":"US",
    "sg:address":"337 Nagle Ct",
    "sg:city":"Harrisburg",
    "sg:classifiers":[
        {
            "category":"Professional",
            "subcategory":"Accounting & Tax Preparation",
            "type":"Services"
        }
    ],
    "sg:phone":"+1 717 657 8907",
    "sg:postcode":"17112",
    "sg:province":"PA",
    "sg:tags":[
        "accountant"
    ],
    "wof:name":"Mary L Flynn CPA",
    "wof:placetype":"venue"
},
  "geometry": {"coordinates":[-76.73749599999999,40.325241],"type":"Point"}
}