{
  "type": "Feature",
  "properties": {
    "iso:country":"US",
    "sg:address":"45 W Court St",
    "sg:city":"Doylestown",
    "sg:classifiers":[
        {
            "category":"Professional",
            "subcategory":"Lawyer & Legal Services",
            "type":"Services"
        }
    ],
    "sg:phone":"+1 215 230 8043",
    "sg:postcode":"18901",
    "sg:province":"PA",
    "wof:name":"Hoffman & Edelson",
    "wof:placetype":"venue"
},
  "geometry": {"coordinates":[-75.131401,40.310101],"type":"Point"}
}