{
  "type": "Feature",
  "properties": {
    "iso:country":"US",
    "sg:address":"9066 Old Albion Rd",
    "sg:city":"Girard",
    "sg:classifiers":[
        {
            "category":"Health Services",
            "subcategory":"Hospital",
            "type":"Services"
        }
    ],
    "sg:phone":"+1 814 756 3024",
    "sg:postcode":"16417",
    "sg:province":"PA",
    "sg:tags":[
        "nurse",
        "registry"
    ],
    "wof:name":"Visiting Nurse Assoc Of Erie C",
    "wof:placetype":"venue"
},
  "geometry": {"coordinates":[-80.381809,41.924795],"type":"Point"}
}