{
  "type": "Feature",
  "properties": {
    "iso:country":"US",
    "sg:address":"1101 Daly St",
    "sg:city":"Philadelphia",
    "sg:classifiers":[
        {
            "category":"Shopping",
            "subcategory":"Clothing, Apparel, & Fashions",
            "type":"Retail Goods"
        }
    ],
    "sg:phone":"+1   ",
    "sg:postcode":"19148",
    "sg:province":"PA",
    "wof:name":"Andico",
    "wof:placetype":"venue"
},
  "geometry": {"coordinates":[-75.166465,39.921853],"type":"Point"}
}