{
  "type": "Feature",
  "properties": {
    "iso:country":"US",
    "sg:address":"531 Conchester Hwy",
    "sg:city":"Marcus Hook",
    "sg:classifiers":[
        {
            "category":"Home & Garden",
            "subcategory":"Carpets & Floor Coverings",
            "type":"Retail Goods"
        }
    ],
    "sg:phone":"+1   ",
    "sg:postcode":"19061",
    "sg:province":"PA",
    "wof:name":"Carpets Vinyl & More",
    "wof:placetype":"venue"
},
  "geometry": {"coordinates":[-75.44704400000001,39.849912],"type":"Point"}
}