{
  "type": "Feature",
  "properties": {
    "addr:full":"789 N Locust St Hazleton PA 18201",
    "addr:housenumber":"789",
    "addr:postcode":"18201",
    "addr:street":"N Locust St",
    "iso:country":"US",
    "sg:address":"789 N Locust St",
    "sg:city":"Hazleton",
    "sg:classifiers":[
        {
            "category":"Personal",
            "subcategory":"Tanning Parlor",
            "type":"Services"
        }
    ],
    "sg:phone":"+1 570 459 2606",
    "sg:postcode":"18201",
    "sg:province":"PA",
    "sg:tags":[
        "salon"
    ],
    "wof:name":"Body Shaping Fitness Ctr",
    "wof:placetype":"venue"
},
  "geometry": {"coordinates":[-75.981497,40.967106],"type":"Point"}
}