{
  "type": "Feature",
  "properties": {
    "addr:full":"715 Spruce St Philadelphia PA 19106",
    "addr:housenumber":"715",
    "addr:postcode":"19106",
    "addr:street":"Spruce St",
    "iso:country":"US",
    "sg:address":"715 Spruce St",
    "sg:city":"Philadelphia",
    "sg:classifiers":[
        {
            "category":"Health Services",
            "subcategory":"Doctor",
            "type":"Services"
        }
    ],
    "sg:phone":"+1   ",
    "sg:postcode":"19106",
    "sg:province":"PA",
    "sg:tags":[
        "osteopathic"
    ],
    "wof:name":"Robert J Gill Do",
    "wof:placetype":"venue"
},
  "geometry": {"coordinates":[-75.15455799999999,39.94578],"type":"Point"}
}