{
  "type": "Feature",
  "properties": {
    "addr:full":"2132 Pine St Philadelphia PA 19103",
    "addr:housenumber":"2132",
    "addr:postcode":"19103",
    "addr:street":"Pine St",
    "iso:country":"US",
    "sg:address":"2132 Pine St",
    "sg:city":"Philadelphia",
    "sg:classifiers":[
        {
            "category":"Health Services",
            "subcategory":"Doctor",
            "type":"Services"
        }
    ],
    "sg:phone":"+1 215 732 1200",
    "sg:postcode":"19103",
    "sg:province":"PA",
    "sg:tags":[
        "physician",
        "surgeon"
    ],
    "wof:name":"Morton Herskowitz DO",
    "wof:placetype":"venue"
},
  "geometry": {"coordinates":[-75.17806299999999,39.947097],"type":"Point"}
}