{
  "type": "Feature",
  "properties": {
    "iso:country":"US",
    "sg:address":"4388 Douglas Rd",
    "sg:city":"New Millport",
    "sg:classifiers":[
        {
            "category":"Government",
            "subcategory":"Office",
            "type":"Public Place"
        }
    ],
    "sg:phone":"+1   ",
    "sg:postcode":"16861",
    "sg:province":"PA",
    "sg:tags":[
        "legislative",
        "body"
    ],
    "wof:name":"Supervisors Office",
    "wof:placetype":"venue"
},
  "geometry": {"coordinates":[-78.515823,40.863994],"type":"Point"}
}