{
  "type": "Feature",
  "properties": {
    "addr:full":"206 Old Lancaster Rd Devon PA 19333",
    "addr:housenumber":"206",
    "addr:postcode":"19333",
    "addr:street":"Old Lancaster Rd",
    "iso:country":"US",
    "sg:address":"206 Old Lancaster Rd",
    "sg:city":"Devon",
    "sg:classifiers":[
        {
            "category":"Real Estate",
            "subcategory":"Real Estate Agent",
            "type":"Services"
        }
    ],
    "sg:phone":"+1 610 975 5811",
    "sg:postcode":"19333",
    "sg:province":"PA",
    "wof:name":"Robert B Kurtz Real Estate",
    "wof:placetype":"venue"
},
  "geometry": {"coordinates":[-75.425534,40.049855],"type":"Point"}
}