{
  "type": "Feature",
  "properties": {
    "iso:country":"US",
    "sg:address":"14 Industrial Dr",
    "sg:city":"Du Bois",
    "sg:classifiers":[
        {
            "category":"Wholesale",
            "subcategory":"Sporting Goods",
            "type":"Manufacturing & Wholesale Goods"
        }
    ],
    "sg:phone":"+1   ",
    "sg:postcode":"15801",
    "sg:province":"PA",
    "wof:name":"Millies Bucktails",
    "wof:placetype":"venue"
},
  "geometry": {"coordinates":[-78.73612199999999,41.13124],"type":"Point"}
}