{
  "type": "Feature",
  "properties": {
    "iso:country":"US",
    "sg:address":"400 Fairway Dr",
    "sg:city":"Coraopolis",
    "sg:classifiers":[
        {
            "category":"Banks & Credit Unions",
            "subcategory":"Investment Brokerage",
            "type":"Services"
        }
    ],
    "sg:phone":"+1 412 393 6000",
    "sg:postcode":"15108",
    "sg:province":"PA",
    "sg:tags":[
        "management"
    ],
    "wof:name":"Dqe Financial Corp",
    "wof:placetype":"venue"
},
  "geometry": {"coordinates":[-80.203108,40.494879],"type":"Point"}
}