{
  "type": "Feature",
  "properties": {
    "iso:country":"US",
    "sg:address":"8 Stockton Ave",
    "sg:city":"New Hope",
    "sg:classifiers":[
        {
            "category":"Health Services",
            "subcategory":"Clinic",
            "type":"Services"
        }
    ],
    "sg:phone":"+1 215 862 6360",
    "sg:postcode":"18938",
    "sg:province":"PA",
    "sg:tags":[
        "hypnotherapy"
    ],
    "wof:name":"Apollo Center For Well Being",
    "wof:placetype":"venue"
},
  "geometry": {"coordinates":[-74.953036,40.363537],"type":"Point"}
}