{
  "type": "Feature",
  "properties": {
    "iso:country":"US",
    "sg:address":"103 Hogeland Rd",
    "sg:city":"Southampton",
    "sg:classifiers":[
        {
            "category":"Manufacturing",
            "subcategory":"Apparel",
            "type":"Manufacturing & Wholesale Goods"
        }
    ],
    "sg:phone":"+1   ",
    "sg:postcode":"18966",
    "sg:province":"PA",
    "sg:tags":[
        "business"
    ],
    "wof:name":"First Place Award The",
    "wof:placetype":"venue"
},
  "geometry": {"coordinates":[-75.046673,40.191407],"type":"Point"}
}