{
  "type": "Feature",
  "properties": {
    "addr:full":"116 N Main St Zelienople PA 16063",
    "addr:housenumber":"116",
    "addr:postcode":"16063",
    "addr:street":"N Main St",
    "iso:country":"US",
    "sg:address":"116 N Main St",
    "sg:city":"Zelienople",
    "sg:classifiers":[
        {
            "category":"Professional",
            "subcategory":"Accounting & Tax Preparation",
            "type":"Services"
        }
    ],
    "sg:phone":"+1 724 452 5366",
    "sg:postcode":"16063",
    "sg:province":"PA",
    "sg:tags":[
        "return",
        "filing"
    ],
    "wof:name":"H & R Block Tax Svc",
    "wof:placetype":"venue"
},
  "geometry": {"coordinates":[-80.137214,40.796904],"type":"Point"}
}