{
  "type": "Feature",
  "properties": {
    "addr:full":"411 S Main Ave Scranton PA 18504",
    "addr:housenumber":"411",
    "addr:postcode":"18504",
    "addr:street":"S Main Ave",
    "iso:country":"US",
    "sg:address":"411 S Main Ave",
    "sg:city":"Scranton",
    "sg:classifiers":[
        {
            "category":"Restaurant",
            "type":"Food & Drink"
        }
    ],
    "sg:menulink":"http://www.allmenus.com/pa/scranton/206707-mcdonalds/menu/",
    "sg:phone":"+1 570 457 9900",
    "sg:postcode":"18504",
    "sg:province":"PA",
    "sg:tags":[
        "burger",
        "american"
    ],
    "wof:name":"McDonald's",
    "wof:placetype":"venue"
},
  "geometry": {"coordinates":[-75.68445,41.407947],"type":"Point"}
}