{
  "type": "Feature",
  "properties": {
    "iso:country":"US",
    "sg:address":"14118 State Rte 89",
    "sg:city":"Wattsburg",
    "sg:classifiers":[
        {
            "category":"Manufacturing",
            "subcategory":"Tools & Machinery",
            "type":"Manufacturing & Wholesale Goods"
        }
    ],
    "sg:phone":"+1 814 739 2211",
    "sg:postcode":"16442",
    "sg:province":"PA",
    "sg:tags":[
        "mold"
    ],
    "sg:website":"www.venangomachine.com",
    "wof:name":"Venango Machine Co",
    "wof:placetype":"venue"
},
  "geometry": {"coordinates":[-79.815776,42.01323],"type":"Point"}
}