{
  "type": "Feature",
  "properties": {
    "iso:country":"US",
    "sg:address":"7930 Frankstown Ave",
    "sg:city":"Pittsburgh",
    "sg:classifiers":[
        {
            "category":"Building & Trades",
            "subcategory":"Equipment Rental",
            "type":"Services"
        }
    ],
    "sg:phone":"+1 412 244 9433",
    "sg:postcode":"15221",
    "sg:province":"PA",
    "sg:tags":[
        "heavy",
        "hardware",
        "construction"
    ],
    "wof:name":"Midway Rental Inc",
    "wof:placetype":"venue"
},
  "geometry": {"coordinates":[-79.883437,40.455381],"type":"Point"}
}