{
  "type": "Feature",
  "properties": {
    "addr:full":"1801 N Main St Butler PA 16001",
    "addr:housenumber":"1801",
    "addr:postcode":"16001",
    "addr:street":"N Main St",
    "iso:country":"US",
    "sg:address":"1801 N Main St",
    "sg:city":"Butler",
    "sg:classifiers":[
        {
            "category":"Food & Beverages",
            "subcategory":"Groceries & Convenience Stores",
            "type":"Retail Goods"
        }
    ],
    "sg:phone":"+1 724 285 7965",
    "sg:postcode":"16001",
    "sg:province":"PA",
    "wof:name":"KWIK Fill",
    "wof:placetype":"venue"
},
  "geometry": {"coordinates":[-79.93394000000001,40.911737],"type":"Point"}
}