{
  "type": "Feature",
  "properties": {
    "addr:full":"1301 Skippack Pike Blue Bell PA 19422",
    "addr:housenumber":"1301",
    "addr:postcode":"19422",
    "addr:street":"Skippack Pike",
    "iso:country":"US",
    "sg:address":"1301 Skippack Pike",
    "sg:city":"Blue Bell",
    "sg:classifiers":[
        {
            "category":"Real Estate",
            "subcategory":"Real Estate Operator",
            "type":"Services"
        }
    ],
    "sg:phone":"+1   ",
    "sg:postcode":"19422",
    "sg:province":"PA",
    "sg:tags":[
        "commercial"
    ],
    "wof:name":"Whitemarsh Investment Assoc",
    "wof:placetype":"venue"
},
  "geometry": {"coordinates":[-75.289113,40.166369],"type":"Point"}
}