{
  "type": "Feature",
  "properties": {
    "iso:country":"US",
    "sg:address":"347 Hickory Bottom Rd",
    "sg:city":"Woodbury",
    "sg:classifiers":[
        {
            "category":"Building & Trades",
            "subcategory":"Construction",
            "type":"Services"
        }
    ],
    "sg:phone":"+1 814 766 2272",
    "sg:postcode":"16695",
    "sg:province":"PA",
    "sg:tags":[
        "house"
    ],
    "wof:name":"Oak Hill Construction",
    "wof:placetype":"venue"
},
  "geometry": {"coordinates":[-78.37516599999999,40.20211],"type":"Point"}
}