{
  "type": "Feature",
  "properties": {
    "addr:full":"224 Norwood Dr Beaver Falls PA 15010",
    "addr:housenumber":"224",
    "addr:postcode":"15010",
    "addr:street":"Norwood Dr",
    "iso:country":"US",
    "sg:address":"224 Norwood Dr",
    "sg:city":"Beaver Falls",
    "sg:classifiers":[
        {
            "category":"Manufacturing",
            "subcategory":"Metals",
            "type":"Manufacturing & Wholesale Goods"
        }
    ],
    "sg:phone":"+1 724 843 9400",
    "sg:postcode":"15010",
    "sg:province":"PA",
    "sg:tags":[
        "steel",
        "processing"
    ],
    "sg:website":"www.dbssteel.com",
    "wof:name":"D B & S Steel Corp",
    "wof:placetype":"venue"
},
  "geometry": {"coordinates":[-80.33632299999999,40.796907],"type":"Point"}
}