{
  "type": "Feature",
  "properties": {
    "iso:country":"US",
    "sg:address":"6500 Steubenville Pike",
    "sg:city":"Pittsburgh",
    "sg:classifiers":[
        {
            "category":"Personal",
            "subcategory":"Nail Salon",
            "type":"Services"
        }
    ],
    "sg:phone":"+1 412 787 9490",
    "sg:postcode":"15205",
    "sg:province":"PA",
    "wof:name":"Nail Studio II",
    "wof:placetype":"venue"
},
  "geometry": {"coordinates":[-80.160714,40.449286],"type":"Point"}
}