{
  "type": "Feature",
  "properties": {
    "iso:country":"US",
    "sg:address":"1600 S Queen St",
    "sg:city":"York",
    "sg:classifiers":[
        {
            "category":"Health Services",
            "subcategory":"Doctor",
            "type":"Services"
        }
    ],
    "sg:phone":"+1   ",
    "sg:postcode":"17403",
    "sg:province":"PA",
    "wof:name":"Daniel G Laux DMD",
    "wof:placetype":"venue"
},
  "geometry": {"coordinates":[-76.705184,39.942747],"type":"Point"}
}