{
  "type": "Feature",
  "properties": {
    "iso:country":"US",
    "sg:address":"140 S 13th St",
    "sg:city":"Harrisburg",
    "sg:classifiers":[
        {
            "category":"Personal",
            "subcategory":"Beauty Salon",
            "type":"Services"
        }
    ],
    "sg:phone":"+1 717 238 4540",
    "sg:postcode":"17104",
    "sg:province":"PA",
    "wof:name":"Maureen's African Hairbraiding",
    "wof:placetype":"venue"
},
  "geometry": {"coordinates":[-76.868863,40.26305],"type":"Point"}
}