{
  "type": "Feature",
  "properties": {
    "addr:full":"105 Shenot Rd Wexford PA 15090",
    "addr:housenumber":"105",
    "addr:postcode":"15090",
    "addr:street":"Shenot Rd",
    "iso:country":"US",
    "sg:address":"105 Shenot Rd",
    "sg:city":"Wexford",
    "sg:classifiers":[
        {
            "category":"Retail",
            "subcategory":"Pet Boarding",
            "type":"Services"
        }
    ],
    "sg:phone":"+1 724 940 5944",
    "sg:postcode":"15090",
    "sg:province":"PA",
    "sg:tags":[
        "boarding/pet",
        "sitting"
    ],
    "wof:name":"Animal House Supply",
    "wof:placetype":"venue"
},
  "geometry": {"coordinates":[-80.089798,40.640499],"type":"Point"}
}