{
  "type": "Feature",
  "properties": {
    "addr:full":"22 N High St West Chester PA 19380",
    "addr:housenumber":"22",
    "addr:postcode":"19380",
    "addr:street":"N High St",
    "iso:country":"US",
    "sg:address":"22 N High St",
    "sg:city":"West Chester",
    "sg:classifiers":[
        {
            "category":"Professional",
            "subcategory":"Lawyer & Legal Services",
            "type":"Services"
        }
    ],
    "sg:phone":"+1 484 887 1000",
    "sg:postcode":"19380",
    "sg:province":"PA",
    "sg:tags":[
        "attorney"
    ],
    "wof:name":"Ciccarelli Law Ofc",
    "wof:placetype":"venue"
},
  "geometry": {"coordinates":[-75.605628,39.960821],"type":"Point"}
}