{
  "type": "Feature",
  "properties": {
    "addr:full":"57 N Pershing Ave York PA 17401",
    "addr:housenumber":"57",
    "addr:postcode":"17401",
    "addr:street":"N Pershing Ave",
    "iso:country":"US",
    "sg:address":"57 N Pershing Ave",
    "sg:city":"York",
    "sg:classifiers":[
        {
            "category":"Bars & Pubs",
            "type":"Food & Drink"
        }
    ],
    "sg:phone":"+1 717 854 1714",
    "sg:postcode":"17401",
    "sg:province":"PA",
    "sg:tags":[
        "tavern"
    ],
    "wof:name":"First Capital Dispensing Co",
    "wof:placetype":"venue"
},
  "geometry": {"coordinates":[-76.73208099999999,39.962342],"type":"Point"}
}