{
  "type": "Feature",
  "properties": {
    "iso:country":"US",
    "sg:address":"22 Mc Govern Ave",
    "sg:city":"Lancaster",
    "sg:classifiers":[
        {
            "category":"Manufacturing",
            "subcategory":"Printing",
            "type":"Manufacturing & Wholesale Goods"
        }
    ],
    "sg:phone":"+1 717 854 0522",
    "sg:postcode":"17602",
    "sg:province":"PA",
    "sg:tags":[
        "newspaper"
    ],
    "wof:name":"Fly Magazine",
    "wof:placetype":"venue"
},
  "geometry": {"coordinates":[-76.308263,40.053552],"type":"Point"}
}