{
  "type": "Feature",
  "properties": {
    "iso:country":"US",
    "sg:address":"7264 Penn Dr",
    "sg:city":"Allentown",
    "sg:classifiers":[
        {
            "category":"Building & Trades",
            "subcategory":"Plumbing",
            "type":"Services"
        }
    ],
    "sg:phone":"+1   ",
    "sg:postcode":"18106",
    "sg:province":"PA",
    "sg:tags":[
        "refrigeration",
        "air",
        "electrical",
        "conditioning",
        "contractor"
    ],
    "wof:name":"Remco Inc of Allentown",
    "wof:placetype":"venue"
},
  "geometry": {"coordinates":[-75.609881,40.579588],"type":"Point"}
}