{
  "type": "Feature",
  "properties": {
    "iso:country":"US",
    "sg:address":"24 Jeffrey Rd",
    "sg:city":"Reading",
    "sg:classifiers":[
        {
            "category":"Professional",
            "subcategory":"Engineering",
            "type":"Services"
        },
        {
            "category":"Professional",
            "subcategory":"Computer Services",
            "type":"Services"
        }
    ],
    "sg:phone":"+1 610 375 4408",
    "sg:postcode":"19601",
    "sg:province":"PA",
    "sg:tags":[
        "engineer",
        "consultant",
        "designer",
        "system",
        "integration"
    ],
    "wof:name":"Nova Source Technologies",
    "wof:placetype":"venue"
},
  "geometry": {"coordinates":[-75.96148700000001,40.357447],"type":"Point"}
}