{
  "type": "Feature",
  "properties": {
    "iso:country":"US",
    "sg:address":"2507 Gettysburg Rd",
    "sg:city":"Camp Hill",
    "sg:classifiers":[
        {
            "category":"Personal",
            "subcategory":"Massage",
            "type":"Services"
        }
    ],
    "sg:phone":"+1 717 920 9355",
    "sg:postcode":"17011",
    "sg:province":"PA",
    "wof:name":"Massage Therapy Associates",
    "wof:placetype":"venue"
},
  "geometry": {"coordinates":[-76.925697,40.228298],"type":"Point"}
}