{
  "type": "Feature",
  "properties": {
    "iso:country":"US",
    "sg:address":"548 Baldwin St",
    "sg:city":"Bridgeville",
    "sg:classifiers":[
        {
            "category":"Autos & Motor Vehicles",
            "subcategory":"Automobile Sales",
            "type":"Retail Goods"
        }
    ],
    "sg:phone":"+1 412 221 9099",
    "sg:postcode":"15017",
    "sg:province":"PA",
    "sg:tags":[
        "car",
        "dealer"
    ],
    "wof:name":"Mc B Motorcars",
    "wof:placetype":"venue"
},
  "geometry": {"coordinates":[-80.10794799999999,40.357791],"type":"Point"}
}