{
  "type": "Feature",
  "properties": {
    "iso:country":"US",
    "sg:address":"2126 E 33rd St",
    "sg:city":"Erie",
    "sg:classifiers":[
        {
            "category":"Manufacturing",
            "subcategory":"Food",
            "type":"Manufacturing & Wholesale Goods"
        }
    ],
    "sg:phone":"+1 814 899 0886",
    "sg:postcode":"16510",
    "sg:province":"PA",
    "sg:tags":[
        "bakery",
        "product",
        "mfg"
    ],
    "sg:website":"www.jtmfoods.com",
    "wof:name":"JTM Foods Inc",
    "wof:placetype":"venue"
},
  "geometry": {"coordinates":[-80.02118299999999,42.124089],"type":"Point"}
}