{
  "type": "Feature",
  "properties": {
    "iso:country":"US",
    "sg:address":"34 Main St",
    "sg:city":"Seven Valleys",
    "sg:classifiers":[
        {
            "category":"Building & Trades",
            "subcategory":"Landscaping Services",
            "type":"Services"
        }
    ],
    "sg:phone":"+1 717 428 3099",
    "sg:postcode":"17360",
    "sg:province":"PA",
    "sg:tags":[
        "landscape",
        "contractor"
    ],
    "wof:name":"Dietrich's Lawn Care",
    "wof:placetype":"venue"
},
  "geometry": {"coordinates":[-76.77237599999999,39.854652],"type":"Point"}
}