{
  "type": "Feature",
  "properties": {
    "iso:country":"US",
    "sg:address":"1363 W Main St",
    "sg:city":"Ephrata",
    "sg:classifiers":[
        {
            "category":"Professional",
            "type":"Services"
        },
        {
            "category":"Restaurant",
            "type":"Food & Drink"
        },
        {
            "category":"Retail",
            "subcategory":"Event Space",
            "type":"Services"
        }
    ],
    "sg:phone":"+1 717 733 0303",
    "sg:postcode":"17522",
    "sg:province":"PA",
    "sg:tags":[
        "style",
        "family",
        "facility",
        "banquet",
        "reception",
        "caterer",
        "hall",
        "pizza"
    ],
    "sg:website":"http://www.twocousinsephrata.com",
    "wof:name":"Two Cousins Family Restaurant",
    "wof:placetype":"venue"
},
  "geometry": {"coordinates":[-76.20023,40.195446],"type":"Point"}
}