{
  "type": "Feature",
  "properties": {
    "addr:full":"40 Shraders Ln Irwin PA 15642",
    "addr:housenumber":"40",
    "addr:postcode":"15642",
    "addr:street":"Shraders Ln",
    "iso:country":"US",
    "sg:address":"40 Shraders Ln",
    "sg:city":"Irwin",
    "sg:classifiers":[
        {
            "category":"Real Estate",
            "subcategory":"Real Estate Operator",
            "type":"Services"
        }
    ],
    "sg:phone":"+1   ",
    "sg:postcode":"15642",
    "sg:province":"PA",
    "sg:tags":[
        "building",
        "apartment"
    ],
    "wof:name":"Burke Shrader Apartments",
    "wof:placetype":"venue"
},
  "geometry": {"coordinates":[-79.751329,40.337212],"type":"Point"}
}