{
  "type": "Feature",
  "properties": {
    "iso:country":"US",
    "sg:address":"90 W Willow Rd",
    "sg:city":"Willow Street",
    "sg:classifiers":[
        {
            "category":"Banks & Credit Unions",
            "subcategory":"Bank",
            "type":"Services"
        }
    ],
    "sg:phone":"+1 717 464 5525",
    "sg:postcode":"17584",
    "sg:province":"PA",
    "wof:name":"Blue Ball National Bank",
    "wof:placetype":"venue"
},
  "geometry": {"coordinates":[-76.28596899999999,39.973209],"type":"Point"}
}