{
  "type": "Feature",
  "properties": {
    "iso:country":"US",
    "sg:address":"47 E North St",
    "sg:city":"Carlisle",
    "sg:classifiers":[
        {
            "category":"Retail",
            "subcategory":"Laundry & Dry Cleaning",
            "type":"Services"
        }
    ],
    "sg:phone":"+1 717 249 0409",
    "sg:postcode":"17013",
    "sg:province":"PA",
    "sg:tags":[
        "cleaners",
        "rug",
        "carpet"
    ],
    "wof:name":"Premier Carpet Care",
    "wof:placetype":"venue"
},
  "geometry": {"coordinates":[-77.18737400000001,40.204516],"type":"Point"}
}