{
  "type": "Feature",
  "properties": {
    "iso:country":"US",
    "sg:address":"3111 N Shedwick St",
    "sg:city":"Philadelphia",
    "sg:classifiers":[
        {
            "category":"Retail",
            "subcategory":"Auto Repair",
            "type":"Services"
        }
    ],
    "sg:phone":"+1 215 225 4754",
    "sg:postcode":"19132",
    "sg:province":"PA",
    "sg:tags":[
        "repairing",
        "automobile"
    ],
    "wof:name":"Bud's Auto Repair",
    "wof:placetype":"venue"
},
  "geometry": {"coordinates":[-75.18609600000001,40.004799],"type":"Point"}
}