{
  "type": "Feature",
  "properties": {
    "addr:full":"660 Chestnut St Philadelphia PA 19106",
    "addr:housenumber":"660",
    "addr:postcode":"19106",
    "addr:street":"Chestnut St",
    "iso:country":"US",
    "sg:address":"660 Chestnut St",
    "sg:city":"Philadelphia",
    "sg:classifiers":[
        {
            "category":"Organizations",
            "subcategory":"Non-profit Organization",
            "type":"Services"
        }
    ],
    "sg:phone":"+1 215 440 5500",
    "sg:postcode":"19106",
    "sg:province":"PA",
    "sg:tags":[
        "public",
        "government"
    ],
    "sg:website":"www.centercityphila.org",
    "wof:name":"Center City District",
    "wof:placetype":"venue"
},
  "geometry": {"coordinates":[-75.151707,39.949341],"type":"Point"}
}