{
  "type": "Feature",
  "properties": {
    "iso:country":"US",
    "sg:address":"646 W Lancaster Ave",
    "sg:city":"Bryn Mawr",
    "sg:classifiers":[
        {
            "category":"Home & Garden",
            "subcategory":"Furniture",
            "type":"Retail Goods"
        }
    ],
    "sg:phone":"+1   ",
    "sg:postcode":"19010",
    "sg:province":"PA",
    "wof:name":"Storehouse Inc",
    "wof:placetype":"venue"
},
  "geometry": {"coordinates":[-75.312524,40.018472],"type":"Point"}
}