{
  "type": "Feature",
  "properties": {
    "iso:country":"US",
    "sg:address":"1470 E High St",
    "sg:city":"Pottstown",
    "sg:classifiers":[
        {
            "category":"Banks & Credit Unions",
            "subcategory":"Bank",
            "type":"Services"
        }
    ],
    "sg:phone":"+1   ",
    "sg:postcode":"19464",
    "sg:province":"PA",
    "sg:tags":[
        "national"
    ],
    "wof:name":"Wachovia Bank National Assn",
    "wof:placetype":"venue"
},
  "geometry": {"coordinates":[-75.615655,40.243881],"type":"Point"}
}