{
  "type": "Feature",
  "properties": {
    "iso:country":"US",
    "sg:address":"212 Outlet Way",
    "sg:city":"Greensburg",
    "sg:classifiers":[
        {
            "category":"Manufacturing",
            "subcategory":"Tools & Machinery",
            "type":"Manufacturing & Wholesale Goods"
        }
    ],
    "sg:phone":"+1 724 834 5690",
    "sg:postcode":"15601",
    "sg:province":"PA",
    "sg:tags":[
        "physician",
        "surgeon"
    ],
    "wof:name":"Cardiac Telecom Corp",
    "wof:placetype":"venue"
},
  "geometry": {"coordinates":[-79.503309,40.306656],"type":"Point"}
}