{
  "type": "Feature",
  "properties": {
    "addr:full":"228 Provost Rd Pittsburgh PA 15227",
    "addr:housenumber":"228",
    "addr:postcode":"15227",
    "addr:street":"Provost Rd",
    "iso:country":"US",
    "sg:address":"228 Provost Rd",
    "sg:city":"Pittsburgh",
    "sg:classifiers":[
        {
            "category":"Professional",
            "subcategory":"Business Services",
            "type":"Services"
        }
    ],
    "sg:phone":"+1 412 885 1134",
    "sg:postcode":"15227",
    "sg:province":"PA",
    "sg:tags":[
        "drafting"
    ],
    "wof:name":"Bettan Drafting & Design",
    "wof:placetype":"venue"
},
  "geometry": {"coordinates":[-79.99413199999999,40.376727],"type":"Point"}
}