{
  "type": "Feature",
  "properties": {
    "addr:full":"2443 Lehigh St Allentown PA 18103",
    "addr:housenumber":"2443",
    "addr:postcode":"18103",
    "addr:street":"Lehigh St",
    "iso:country":"US",
    "sg:address":"2443 Lehigh St",
    "sg:city":"Allentown",
    "sg:classifiers":[
        {
            "category":"Autos & Motor Vehicles",
            "subcategory":"Automobile Sales",
            "type":"Retail Goods"
        },
        {
            "category":"Retail",
            "subcategory":"Auto Rental",
            "type":"Services"
        }
    ],
    "sg:phone":"+1 610 791 4561",
    "sg:postcode":"18103",
    "sg:province":"PA",
    "sg:tags":[
        "car",
        "leasing",
        "truck"
    ],
    "sg:website":"http://budget.com/IYP_tl",
    "wof:name":"Budget Rent A Car",
    "wof:placetype":"venue"
},
  "geometry": {"coordinates":[-75.48231,40.568821],"type":"Point"}
}