{
  "type": "Feature",
  "properties": {
    "addr:full":"449 N 6th St Allentown PA 18102",
    "addr:housenumber":"449",
    "addr:postcode":"18102",
    "addr:street":"N 6Th St",
    "iso:country":"US",
    "sg:address":"449 N 6th St",
    "sg:city":"Allentown",
    "sg:classifiers":[
        {
            "category":"Wholesale",
            "subcategory":"Beer",
            "type":"Manufacturing & Wholesale Goods"
        }
    ],
    "sg:phone":"+1 610 439 7303",
    "sg:postcode":"18102",
    "sg:province":"PA",
    "sg:tags":[
        "ale"
    ],
    "wof:name":"M L Beer Inc",
    "wof:placetype":"venue"
},
  "geometry": {"coordinates":[-75.47279899999999,40.609088],"type":"Point"}
}