{
  "type": "Feature",
  "properties": {
    "iso:country":"US",
    "sg:address":"1072 Shelly Rd",
    "sg:city":"Manheim",
    "sg:classifiers":[
        {
            "category":"Banks & Credit Unions",
            "subcategory":"Bank",
            "type":"Services"
        }
    ],
    "sg:phone":"+1 717 234 8484",
    "sg:postcode":"17545",
    "sg:province":"PA",
    "sg:tags":[
        "loan",
        "real estate"
    ],
    "sg:website":"www.psecu.net",
    "wof:name":"Psecu",
    "wof:placetype":"venue"
},
  "geometry": {"coordinates":[-76.444688,40.152109],"type":"Point"}
}