{
  "type": "Feature",
  "properties": {
    "iso:country":"US",
    "sg:address":"119 E Main St",
    "sg:city":"Macungie",
    "sg:classifiers":[
        {
            "category":"Professional",
            "subcategory":"Lawyer & Legal Services",
            "type":"Services"
        }
    ],
    "sg:phone":"+1   ",
    "sg:postcode":"18062",
    "sg:province":"PA",
    "wof:name":"Donald S Esq",
    "wof:placetype":"venue"
},
  "geometry": {"coordinates":[-75.554068,40.514986],"type":"Point"}
}