{
  "type": "Feature",
  "properties": {
    "addr:full":"1609 Ashurst Rd Philadelphia PA 19151",
    "addr:housenumber":"1609",
    "addr:postcode":"19151",
    "addr:street":"Ashurst Rd",
    "iso:country":"US",
    "sg:address":"1609 Ashurst Rd",
    "sg:city":"Philadelphia",
    "sg:classifiers":[
        {
            "category":"Health Services",
            "subcategory":"Optometrist",
            "type":"Services"
        }
    ],
    "sg:phone":"+1 215 477 5188",
    "sg:postcode":"19151",
    "sg:province":"PA",
    "wof:name":"Dr Aaron Optmtrst Pestcoe",
    "wof:placetype":"venue"
},
  "geometry": {"coordinates":[-75.27152599999999,39.972853],"type":"Point"}
}