{
  "type": "Feature",
  "properties": {
    "addr:full":"6712 Horrocks St Philadelphia PA 19149",
    "addr:housenumber":"6712",
    "addr:postcode":"19149",
    "addr:street":"Horrocks St",
    "iso:country":"US",
    "sg:address":"6712 Horrocks St",
    "sg:city":"Philadelphia",
    "sg:classifiers":[
        {
            "category":"Shopping",
            "subcategory":"Gifts & Souvenirs",
            "type":"Retail Goods"
        }
    ],
    "sg:phone":"+1   ",
    "sg:postcode":"19149",
    "sg:province":"PA",
    "wof:name":"Mimis Gifts",
    "wof:placetype":"venue"
},
  "geometry": {"coordinates":[-75.069034,40.042181],"type":"Point"}
}