{
  "type": "Feature",
  "properties": {
    "addr:full":"25 N Main St Muncy PA 17756",
    "addr:housenumber":"25",
    "addr:postcode":"17756",
    "addr:street":"N Main St",
    "iso:country":"US",
    "sg:address":"25 N Main St",
    "sg:city":"Muncy",
    "sg:classifiers":[
        {
            "category":"Real Estate",
            "subcategory":"Real Estate Agent",
            "type":"Services"
        }
    ],
    "sg:phone":"+1   ",
    "sg:postcode":"17756",
    "sg:province":"PA",
    "wof:name":"Long Ridge Realty Services",
    "wof:placetype":"venue"
},
  "geometry": {"coordinates":[-76.78625099999999,41.206143],"type":"Point"}
}