{
  "type": "Feature",
  "properties": {
    "iso:country":"US",
    "sg:address":"33 Gary St",
    "sg:city":"Carnegie",
    "sg:classifiers":[
        {
            "category":"Building & Trades",
            "subcategory":"Construction",
            "type":"Services"
        }
    ],
    "sg:phone":"+1 412 429 4091",
    "sg:postcode":"15106",
    "sg:province":"PA",
    "sg:tags":[
        "mason",
        "masonry",
        "industrial",
        "contractors-commercial",
        "contractor"
    ],
    "wof:name":"P Marini & Son Inc",
    "wof:placetype":"venue"
},
  "geometry": {"coordinates":[-80.074792,40.417897],"type":"Point"}
}