{
  "type": "Feature",
  "properties": {
    "iso:country":"US",
    "sg:address":"2063 Snyder Ave",
    "sg:city":"Philadelphia",
    "sg:classifiers":[
        {
            "category":"Social Services",
            "subcategory":"Child Care",
            "type":"Services"
        }
    ],
    "sg:phone":"+1 215 465 4584",
    "sg:postcode":"19145",
    "sg:province":"PA",
    "sg:tags":[
        "day"
    ],
    "wof:name":"Open Arms Childcare",
    "wof:placetype":"venue"
},
  "geometry": {"coordinates":[-75.180948,39.926005],"type":"Point"}
}