{
  "type": "Feature",
  "properties": {
    "iso:country":"US",
    "sg:address":"203 Main St",
    "sg:city":"Stroudsburg",
    "sg:classifiers":[
        {
            "category":"Utilities",
            "subcategory":"Natural Gas",
            "type":"Services"
        }
    ],
    "sg:phone":"+1   ",
    "sg:postcode":"18360",
    "sg:province":"PA",
    "wof:name":"Pfg Gas Inc",
    "wof:placetype":"venue"
},
  "geometry": {"coordinates":[-75.18682200000001,40.991196],"type":"Point"}
}