{
  "type": "Feature",
  "properties": {
    "addr:full":"17 Hillside Ln Doylestown PA 18901",
    "addr:housenumber":"17",
    "addr:postcode":"18901",
    "addr:street":"Hillside Ln",
    "iso:country":"US",
    "sg:address":"17 Hillside Ln",
    "sg:city":"Doylestown",
    "sg:classifiers":[
        {
            "category":"Food & Beverages",
            "subcategory":"Candy",
            "type":"Retail Goods"
        }
    ],
    "sg:phone":"+1   ",
    "sg:postcode":"18901",
    "sg:province":"PA",
    "wof:name":"Mercer Chocolates LLC",
    "wof:placetype":"venue"
},
  "geometry": {"coordinates":[-75.11465699999999,40.294423],"type":"Point"}
}