{
  "type": "Feature",
  "properties": {
    "iso:country":"US",
    "sg:address":"2761 Old Orchard Rd",
    "sg:city":"Lancaster",
    "sg:classifiers":[
        {
            "category":"Professional",
            "type":"Services"
        }
    ],
    "sg:phone":"+1 717 291 7203",
    "sg:postcode":"17601",
    "sg:province":"PA",
    "sg:tags":[
        "establishment"
    ],
    "wof:name":"Earl Freeman Armstrong World",
    "wof:placetype":"venue"
},
  "geometry": {"coordinates":[-76.258506,40.095929],"type":"Point"}
}