{
  "type": "Feature",
  "properties": {
    "iso:country":"US",
    "sg:address":"900 Chartiers Ave",
    "sg:city":"Pittsburgh",
    "sg:classifiers":[
        {
            "category":"Retail",
            "subcategory":"Funeral Services",
            "type":"Services"
        }
    ],
    "sg:phone":"+1 412 921 1705",
    "sg:postcode":"15220",
    "sg:province":"PA",
    "sg:tags":[
        "cemetery"
    ],
    "wof:name":"Staab Anthony G Funrl Hme",
    "wof:placetype":"venue"
},
  "geometry": {"coordinates":[-80.039703,40.443298],"type":"Point"}
}