{
  "type": "Feature",
  "properties": {
    "addr:full":"817 S George St York PA 17403",
    "addr:housenumber":"817",
    "addr:postcode":"17403",
    "addr:street":"S George St",
    "iso:country":"US",
    "sg:address":"817 S George St",
    "sg:city":"York",
    "sg:classifiers":[
        {
            "category":"Health Services",
            "subcategory":"Health Practitioner",
            "type":"Services"
        }
    ],
    "sg:phone":"+1 717 845 3884",
    "sg:postcode":"17403",
    "sg:province":"PA",
    "sg:tags":[
        "psychologist"
    ],
    "wof:name":"De Sau Holmes-Pearson Assoc",
    "wof:placetype":"venue"
},
  "geometry": {"coordinates":[-76.722179,39.950599],"type":"Point"}
}