{
  "type": "Feature",
  "properties": {
    "iso:country":"US",
    "sg:address":"7900 Old York Rd",
    "sg:city":"Elkins Park",
    "sg:classifiers":[
        {
            "category":"Health Services",
            "subcategory":"Health Practitioner",
            "type":"Services"
        }
    ],
    "sg:phone":"+1   ",
    "sg:postcode":"19027",
    "sg:province":"PA",
    "wof:name":"Carole Sklar",
    "wof:placetype":"venue"
},
  "geometry": {"coordinates":[-75.12949399999999,40.074684],"type":"Point"}
}