{
  "type": "Feature",
  "properties": {
    "addr:full":"529A Foundry Rd Norristown PA 19403",
    "addr:housenumber":"529a",
    "addr:postcode":"19403",
    "addr:street":"Foundry Rd",
    "iso:country":"US",
    "sg:address":"529A Foundry Rd",
    "sg:city":"Norristown",
    "sg:classifiers":[
        {
            "category":"Professional",
            "subcategory":"Computer Services",
            "type":"Services"
        }
    ],
    "sg:phone":"+1 267 222 8465",
    "sg:postcode":"19403",
    "sg:province":"PA",
    "sg:tags":[
        "designer",
        "technical",
        "consultant",
        "assistance",
        "system",
        "support"
    ],
    "sg:website":"http://www.gigabiter.com",
    "wof:name":"Gigabiter Gov",
    "wof:placetype":"venue"
},
  "geometry": {"coordinates":[-75.371691,40.153989],"type":"Point"}
}