{
  "type": "Feature",
  "properties": {
    "iso:country":"US",
    "sg:address":"1545 Oregon Pike",
    "sg:city":"Lancaster",
    "sg:classifiers":[
        {
            "category":"Professional",
            "subcategory":"Research",
            "type":"Services"
        }
    ],
    "sg:phone":"+1 717 295 9104",
    "sg:postcode":"17601",
    "sg:province":"PA",
    "sg:tags":[
        "foundation",
        "philanthropic"
    ],
    "wof:name":"Financial Foundations",
    "wof:placetype":"venue"
},
  "geometry": {"coordinates":[-76.305549,40.06381],"type":"Point"}
}