{
  "type": "Feature",
  "properties": {
    "iso:country":"US",
    "sg:address":"660 E Pittsburgh St",
    "sg:city":"Greensburg",
    "sg:classifiers":[
        {
            "category":"Real Estate",
            "subcategory":"Real Estate Operator",
            "type":"Services"
        }
    ],
    "sg:phone":"+1   ",
    "sg:postcode":"15601",
    "sg:province":"PA",
    "sg:tags":[
        "property",
        "lessor"
    ],
    "wof:name":"Davis Center",
    "wof:placetype":"venue"
},
  "geometry": {"coordinates":[-79.530599,40.302846],"type":"Point"}
}