{
  "type": "Feature",
  "properties": {
    "addr:full":"1150 Greenwood Rd York PA 17408",
    "addr:housenumber":"1150",
    "addr:postcode":"17408",
    "addr:street":"Greenwood Rd",
    "iso:country":"US",
    "sg:address":"1150 Greenwood Rd",
    "sg:city":"York",
    "sg:classifiers":[
        {
            "category":"Retail",
            "subcategory":"Auto Repair",
            "type":"Services"
        }
    ],
    "sg:phone":"+1   ",
    "sg:postcode":"17408",
    "sg:province":"PA",
    "sg:tags":[
        "automotive",
        "general"
    ],
    "wof:name":"Zechs Service Center",
    "wof:placetype":"venue"
},
  "geometry": {"coordinates":[-76.790649,39.961401],"type":"Point"}
}