{
  "type": "Feature",
  "properties": {
    "addr:full":"1010 Oak Ave Croydon PA 19021",
    "addr:housenumber":"1010",
    "addr:postcode":"19021",
    "addr:street":"Oak Ave",
    "iso:country":"US",
    "sg:address":"1010 Oak Ave",
    "sg:city":"Croydon",
    "sg:classifiers":[
        {
            "category":"Manufacturing",
            "subcategory":"Tools & Machinery",
            "type":"Manufacturing & Wholesale Goods"
        }
    ],
    "sg:phone":"+1 215 785 2499",
    "sg:postcode":"19021",
    "sg:province":"PA",
    "sg:tags":[
        "machine",
        "shop",
        "industrial",
        "mfg"
    ],
    "wof:name":"Swissco Precision Machining LL",
    "wof:placetype":"venue"
},
  "geometry": {"coordinates":[-74.885125,40.089874],"type":"Point"}
}