{
  "type": "Feature",
  "properties": {
    "iso:country":"US",
    "sg:address":"52 E Elmira St",
    "sg:city":"Mansfield",
    "sg:classifiers":[
        {
            "category":"Retail",
            "subcategory":"Repair Shop",
            "type":"Services"
        }
    ],
    "sg:phone":"+1 570 662 3401",
    "sg:postcode":"16933",
    "sg:province":"PA",
    "sg:tags":[
        "lock",
        "locksmith"
    ],
    "wof:name":"Larry's Locksmithing",
    "wof:placetype":"venue"
},
  "geometry": {"coordinates":[-77.077252,41.809091],"type":"Point"}
}