{
  "type": "Feature",
  "properties": {
    "iso:country":"US",
    "sg:address":"229 Butler Rd",
    "sg:city":"Kittanning",
    "sg:classifiers":[
        {
            "category":"Insurance",
            "subcategory":"Insurance Agent",
            "type":"Services"
        }
    ],
    "sg:phone":"+1   ",
    "sg:postcode":"16201",
    "sg:province":"PA",
    "wof:name":"Rearick & Co",
    "wof:placetype":"venue"
},
  "geometry": {"coordinates":[-79.532577,40.808877],"type":"Point"}
}