{
  "type": "Feature",
  "properties": {
    "iso:country":"US",
    "sg:address":"1525 Buena Vista St",
    "sg:city":"Pittsburgh",
    "sg:classifiers":[
        {
            "category":"Building & Trades",
            "subcategory":"Construction",
            "type":"Services"
        }
    ],
    "sg:phone":"+1 412 322 8498",
    "sg:postcode":"15212",
    "sg:province":"PA",
    "sg:tags":[
        "contractor"
    ],
    "wof:name":"Bruder Construction",
    "wof:placetype":"venue"
},
  "geometry": {"coordinates":[-80.01468199999999,40.457089],"type":"Point"}
}