{
  "type": "Feature",
  "properties": {
    "iso:country":"US",
    "sg:address":"505 Mecklem Ln",
    "sg:city":"Ellwood City",
    "sg:classifiers":[
        {
            "category":"Manufacturing",
            "subcategory":"Aerospace",
            "type":"Manufacturing & Wholesale Goods"
        }
    ],
    "sg:phone":"+1   ",
    "sg:postcode":"16117",
    "sg:province":"PA",
    "sg:tags":[
        "secondary",
        "metal",
        "producer",
        "nonferrous"
    ],
    "wof:name":"Honeywell",
    "wof:placetype":"venue"
},
  "geometry": {"coordinates":[-80.26228,40.847174],"type":"Point"}
}