{
  "type": "Feature",
  "properties": {
    "iso:country":"US",
    "sg:address":"254 S 11th St",
    "sg:city":"Philadelphia",
    "sg:classifiers":[
        {
            "category":"Arts & Performance",
            "subcategory":"Theater",
            "type":"Entertainment"
        }
    ],
    "sg:phone":"+1   ",
    "sg:postcode":"19107",
    "sg:province":"PA",
    "wof:name":"Life Boyz Entertainment",
    "wof:placetype":"venue"
},
  "geometry": {"coordinates":[-75.15947799999999,39.9467],"type":"Point"}
}