{
  "type": "Feature",
  "properties": {
    "addr:full":"500 Main St Bentleyville PA 15314",
    "addr:housenumber":"500",
    "addr:postcode":"15314",
    "addr:street":"Main St",
    "iso:country":"US",
    "sg:address":"500 Main St",
    "sg:city":"Bentleyville",
    "sg:classifiers":[
        {
            "category":"Recreation",
            "type":"Entertainment"
        }
    ],
    "sg:phone":"+1 724 239 4851",
    "sg:postcode":"15314",
    "sg:province":"PA",
    "sg:tags":[
        "club",
        "military",
        "veteran",
        "sport",
        "membership"
    ],
    "sg:website":"http://www.legion.org",
    "wof:name":"American Legion",
    "wof:placetype":"venue"
},
  "geometry": {"coordinates":[-80.00833900000001,40.116779],"type":"Point"}
}