{
  "type": "Feature",
  "properties": {
    "iso:country":"US",
    "sg:address":"2906 William Penn Hwy",
    "sg:city":"Easton",
    "sg:classifiers":[
        {
            "category":"Social Services",
            "type":"Services"
        }
    ],
    "sg:phone":"+1 610 250 0100",
    "sg:postcode":"18045",
    "sg:province":"PA",
    "sg:tags":[
        "organization",
        "welfare"
    ],
    "sg:website":"www.bbbslv.org",
    "wof:name":"Big Brothers & Big Sisters",
    "wof:placetype":"venue"
},
  "geometry": {"coordinates":[-75.258261,40.678892],"type":"Point"}
}