{
  "type": "Feature",
  "properties": {
    "addr:full":"5238 Butler St Pittsburgh PA 15201",
    "addr:housenumber":"5238",
    "addr:postcode":"15201",
    "addr:street":"Butler St",
    "iso:country":"US",
    "sg:address":"5238 Butler St",
    "sg:city":"Pittsburgh",
    "sg:classifiers":[
        {
            "category":"Bars & Pubs",
            "type":"Food & Drink"
        }
    ],
    "sg:phone":"+1 412 781 7373",
    "sg:postcode":"15201",
    "sg:province":"PA",
    "wof:name":"Bottles Pub",
    "wof:placetype":"venue"
},
  "geometry": {"coordinates":[-79.954133,40.480645],"type":"Point"}
}