{
  "type": "Feature",
  "properties": {
    "iso:country":"US",
    "sg:address":"155 Branchton Rd",
    "sg:city":"Slippery Rock",
    "sg:classifiers":[
        {
            "category":"Government",
            "subcategory":"Office",
            "type":"Public Place"
        }
    ],
    "sg:phone":"+1 724 794 6440",
    "sg:postcode":"16057",
    "sg:province":"PA",
    "sg:tags":[
        "village"
    ],
    "wof:name":"Senior Center",
    "wof:placetype":"venue"
},
  "geometry": {"coordinates":[-80.040035,41.070624],"type":"Point"}
}