{
  "type": "Feature",
  "properties": {
    "addr:full":"1900 Barley Rd York PA 17408",
    "addr:housenumber":"1900",
    "addr:postcode":"17408",
    "addr:street":"Barley Rd",
    "iso:country":"US",
    "sg:address":"1900 Barley Rd",
    "sg:city":"York",
    "sg:classifiers":[
        {
            "category":"Real Estate",
            "subcategory":"Real Estate Operator",
            "type":"Services"
        }
    ],
    "sg:phone":"+1 717 767 1184",
    "sg:postcode":"17408",
    "sg:province":"PA",
    "sg:tags":[
        "building",
        "apartment"
    ],
    "wof:name":"Manchester Heights Apartments",
    "wof:placetype":"venue"
},
  "geometry": {"coordinates":[-76.780586,39.979615],"type":"Point"}
}