{
  "type": "Feature",
  "properties": {
    "iso:country":"US",
    "sg:address":"2310 State St",
    "sg:city":"Erie",
    "sg:classifiers":[
        {
            "category":"Home & Garden",
            "subcategory":"Hardware",
            "type":"Retail Goods"
        }
    ],
    "sg:phone":"+1   ",
    "sg:postcode":"16503",
    "sg:province":"PA",
    "wof:name":"Carnevals Interstate Security",
    "wof:placetype":"venue"
},
  "geometry": {"coordinates":[-80.074817,42.113672],"type":"Point"}
}