{
  "type": "Feature",
  "properties": {
    "iso:country":"US",
    "sg:address":"1 N Main St",
    "sg:city":"Carbondale",
    "sg:classifiers":[
        {
            "category":"Government",
            "subcategory":"Office",
            "type":"Public Place"
        }
    ],
    "sg:phone":"+1 570 282 4110",
    "sg:postcode":"18407",
    "sg:province":"PA",
    "sg:tags":[
        "village"
    ],
    "wof:name":"Carbondale City Offices",
    "wof:placetype":"venue"
},
  "geometry": {"coordinates":[-75.502608,41.572531],"type":"Point"}
}