{
  "type": "Feature",
  "properties": {
    "iso:country":"US",
    "sg:address":"12041 Patton Dr",
    "sg:city":"Irwin",
    "sg:classifiers":[
        {
            "category":"Building & Trades",
            "subcategory":"Construction",
            "type":"Services"
        }
    ],
    "sg:phone":"+1   ",
    "sg:postcode":"15642",
    "sg:province":"PA",
    "sg:tags":[
        "house"
    ],
    "wof:name":"Klipa General Contractin",
    "wof:placetype":"venue"
},
  "geometry": {"coordinates":[-79.742199,40.323716],"type":"Point"}
}