{
  "type": "Feature",
  "properties": {
    "addr:full":"42 Wabash St West End Village Pittsburgh PA 15220",
    "addr:housenumber":"42",
    "addr:postcode":"15220",
    "addr:street":"Wabash St West End Village",
    "iso:country":"US",
    "sg:address":"42 Wabash St West End Village",
    "sg:city":"Pittsburgh",
    "sg:classifiers":[
        {
            "category":"Coffee & Tea",
            "type":"Food & Drink"
        }
    ],
    "sg:phone":"+1 412 458 1202",
    "sg:postcode":"15220",
    "sg:province":"PA",
    "sg:website":"www.zoesherbsteas.com",
    "wof:name":"Zoe's Herbs & Teas",
    "wof:placetype":"venue"
},
  "geometry": {"coordinates":[-80.034599,40.440187],"type":"Point"}
}