{
  "type": "Feature",
  "properties": {
    "iso:country":"US",
    "sg:address":"35 W Pittsburgh St",
    "sg:city":"Greensburg",
    "sg:classifiers":[
        {
            "category":"Professional",
            "subcategory":"Lawyer & Legal Services",
            "type":"Services"
        }
    ],
    "sg:phone":"+1 724 836 4871",
    "sg:postcode":"15601",
    "sg:province":"PA",
    "sg:tags":[
        "attorney",
        "practice"
    ],
    "wof:name":"Burkley, Kenneth",
    "wof:placetype":"venue"
},
  "geometry": {"coordinates":[-79.54535799999999,40.302261],"type":"Point"}
}