{
  "type": "Feature",
  "properties": {
    "iso:country":"US",
    "sg:address":"2026 S 13th St",
    "sg:city":"Philadelphia",
    "sg:classifiers":[
        {
            "category":"Place Of Worship",
            "subcategory":"Church",
            "type":"Public Place"
        },
        {
            "category":"Place Of Worship",
            "type":"Public Place"
        }
    ],
    "sg:phone":"+1 215 465 3500",
    "sg:postcode":"19148",
    "sg:province":"PA",
    "sg:tags":[
        "churches-pentecostal-independent",
        "churches-pentecostal"
    ],
    "wof:name":"I F G F Inc",
    "wof:placetype":"venue"
},
  "geometry": {"coordinates":[-75.16748,39.924549],"type":"Point"}
}