{
  "type": "Feature",
  "properties": {
    "iso:country":"US",
    "sg:address":"6163 Woodland Ave",
    "sg:city":"Philadelphia",
    "sg:classifiers":[
        {
            "category":"Shopping",
            "subcategory":"Discount & Variety Stores",
            "type":"Retail Goods"
        }
    ],
    "sg:phone":"+1   ",
    "sg:postcode":"19142",
    "sg:province":"PA",
    "wof:name":"Youngs Health & Beauty Aids",
    "wof:placetype":"venue"
},
  "geometry": {"coordinates":[-75.230811,39.928136],"type":"Point"}
}