{
  "type": "Feature",
  "properties": {
    "addr:full":"434 W Aaron Dr State College PA 16803",
    "addr:housenumber":"434",
    "addr:postcode":"16803",
    "addr:street":"W Aaron Dr",
    "iso:country":"US",
    "sg:address":"434 W Aaron Dr",
    "sg:city":"State College",
    "sg:classifiers":[
        {
            "category":"Personal",
            "subcategory":"Beauty Salon",
            "type":"Services"
        }
    ],
    "sg:phone":"+1 814 234 3770",
    "sg:postcode":"16803",
    "sg:province":"PA",
    "wof:name":"That Special Touch",
    "wof:placetype":"venue"
},
  "geometry": {"coordinates":[-77.89344699999999,40.806056],"type":"Point"}
}