{
  "type": "Feature",
  "properties": {
    "addr:full":"213 Douglass St Reading PA 19601",
    "addr:housenumber":"213",
    "addr:postcode":"19601",
    "addr:street":"Douglass St",
    "iso:country":"US",
    "sg:address":"213 Douglass St",
    "sg:city":"Reading",
    "sg:classifiers":[
        {
            "category":"Place Of Worship",
            "type":"Public Place"
        }
    ],
    "sg:phone":"+1 610 587 3216",
    "sg:postcode":"19601",
    "sg:province":"PA",
    "sg:tags":[
        "church"
    ],
    "wof:name":"Saint David",
    "wof:placetype":"venue"
},
  "geometry": {"coordinates":[-75.932714,40.34756],"type":"Point"}
}