{
  "type": "Feature",
  "properties": {
    "addr:full":"908 Gill Hall Rd Clairton PA 15025",
    "addr:housenumber":"908",
    "addr:postcode":"15025",
    "addr:street":"Gill Hall Rd",
    "iso:country":"US",
    "sg:address":"908 Gill Hall Rd",
    "sg:city":"Clairton",
    "sg:classifiers":[
        {
            "category":"Social Services",
            "subcategory":"Child Care",
            "type":"Services"
        }
    ],
    "sg:phone":"+1   ",
    "sg:postcode":"15025",
    "sg:province":"PA",
    "sg:tags":[
        "day"
    ],
    "wof:name":"Frank Lesters Playcare",
    "wof:placetype":"venue"
},
  "geometry": {"coordinates":[-79.96240899999999,40.298647],"type":"Point"}
}