{
  "type": "Feature",
  "properties": {
    "iso:country":"US",
    "sg:address":"300 N Wales Rd",
    "sg:city":"North Wales",
    "sg:classifiers":[
        {
            "category":"Wholesale",
            "subcategory":"Vending Machines",
            "type":"Manufacturing & Wholesale Goods"
        }
    ],
    "sg:phone":"+1   ",
    "sg:postcode":"19454",
    "sg:province":"PA",
    "sg:tags":[
        "operator"
    ],
    "wof:name":"Roosevelt Vending Co",
    "wof:placetype":"venue"
},
  "geometry": {"coordinates":[-75.260375,40.23087],"type":"Point"}
}