{
  "type": "Feature",
  "properties": {
    "iso:country":"US",
    "sg:address":"1155 Allegheny Ave",
    "sg:city":"Oakmont",
    "sg:classifiers":[
        {
            "category":"Manufacturing",
            "subcategory":"Metals",
            "type":"Manufacturing & Wholesale Goods"
        },
        {
            "category":"Home & Garden",
            "subcategory":"Building Materials",
            "type":"Retail Goods"
        },
        {
            "category":"Building & Trades",
            "subcategory":"Construction",
            "type":"Services"
        },
        {
            "category":"Manufacturing",
            "subcategory":"Building Materials",
            "type":"Manufacturing & Wholesale Goods"
        },
        {
            "category":"Manufacturing",
            "subcategory":"Glass & Minerals",
            "type":"Manufacturing & Wholesale Goods"
        }
    ],
    "sg:phone":"+1 412 826 1000",
    "sg:postcode":"15139",
    "sg:province":"PA",
    "sg:tags":[
        "windows-metal",
        "shape",
        "frames",
        "contractor",
        "special",
        "windows-repair",
        "improvement",
        "glass-wholesale",
        "window",
        "doors",
        "circle",
        "gazebo",
        "door",
        "storm",
        "accessory",
        "manufacturer",
        "installation",
        "altering",
        "remodeling",
        "builder",
        "patio",
        "replacement"
    ],
    "sg:website":"http://www.thermotwin.com",
    "wof:name":"Thermo Twin Windows",
    "wof:placetype":"venue"
},
  "geometry": {"coordinates":[-79.839219,40.528111],"type":"Point"}
}