{
  "type": "Feature",
  "properties": {
    "iso:country":"US",
    "sg:address":"110 W Orange St",
    "sg:city":"Lancaster",
    "sg:classifiers":[
        {
            "category":"Manufacturing",
            "subcategory":"Printing",
            "type":"Manufacturing & Wholesale Goods"
        }
    ],
    "sg:phone":"+1 717 397 0363",
    "sg:postcode":"17603",
    "sg:province":"PA",
    "sg:tags":[
        "printer"
    ],
    "wof:name":"Barlain Printing Inc",
    "wof:placetype":"venue"
},
  "geometry": {"coordinates":[-76.308717,40.039168],"type":"Point"}
}