{
  "type": "Feature",
  "properties": {
    "addr:full":"2055 S 3rd St Steelton PA 17113",
    "addr:housenumber":"2055",
    "addr:postcode":"17113",
    "addr:street":"S 3Rd St",
    "iso:country":"US",
    "sg:address":"2055 S 3rd St",
    "sg:city":"Steelton",
    "sg:classifiers":[
        {
            "category":"Shopping",
            "subcategory":"Hobbies, Toys, & Games",
            "type":"Retail Goods"
        }
    ],
    "sg:phone":"+1 717 939 4504",
    "sg:postcode":"17113",
    "sg:province":"PA",
    "sg:tags":[
        "equipment",
        "ceramic",
        "supply"
    ],
    "wof:name":"Row's Tackle & Ceramics",
    "wof:placetype":"venue"
},
  "geometry": {"coordinates":[-76.811117,40.217178],"type":"Point"}
}