{
  "type": "Feature",
  "properties": {
    "iso:country":"US",
    "sg:address":"366 S Mount Vernon Ave",
    "sg:city":"Uniontown",
    "sg:classifiers":[
        {
            "category":"Sports & Exercise",
            "subcategory":"Bowling",
            "type":"Entertainment"
        }
    ],
    "sg:phone":"+1 724 438 3323",
    "sg:postcode":"15401",
    "sg:province":"PA",
    "sg:tags":[
        "alley"
    ],
    "wof:name":"Mt Vernon Bowl",
    "wof:placetype":"venue"
},
  "geometry": {"coordinates":[-79.740013,39.894611],"type":"Point"}
}