{
  "type": "Feature",
  "properties": {
    "addr:full":"19 E Springfield Rd Springfield PA 19064",
    "addr:housenumber":"19",
    "addr:postcode":"19064",
    "addr:street":"E Springfield Rd",
    "iso:country":"US",
    "sg:address":"19 E Springfield Rd",
    "sg:city":"Springfield",
    "sg:classifiers":[
        {
            "category":"Shopping",
            "subcategory":"Optical Goods",
            "type":"Retail Goods"
        }
    ],
    "sg:phone":"+1 610 543 9275",
    "sg:postcode":"19064",
    "sg:province":"PA",
    "sg:tags":[
        "optician"
    ],
    "wof:name":"Springfield Opticians",
    "wof:placetype":"venue"
},
  "geometry": {"coordinates":[-75.328873,39.933782],"type":"Point"}
}