{
  "type": "Feature",
  "properties": {
    "addr:full":"5021 Noblestown Rd Oakdale PA 15071",
    "addr:housenumber":"5021",
    "addr:postcode":"15071",
    "addr:street":"Noblestown Rd",
    "iso:country":"US",
    "sg:address":"5021 Noblestown Rd",
    "sg:city":"Oakdale",
    "sg:classifiers":[
        {
            "category":"Retail",
            "subcategory":"Portrait Studio",
            "type":"Services"
        }
    ],
    "sg:phone":"+1 724 693 8032",
    "sg:postcode":"15071",
    "sg:province":"PA",
    "sg:tags":[
        "photographer"
    ],
    "sg:website":"www.bordo.com",
    "wof:name":"Bordo Photography",
    "wof:placetype":"venue"
},
  "geometry": {"coordinates":[-80.185472,40.39784],"type":"Point"}
}