{
  "type": "Feature",
  "properties": {
    "iso:country":"US",
    "sg:address":"5252 Spruce St",
    "sg:city":"Philadelphia",
    "sg:classifiers":[
        {
            "category":"Personal",
            "subcategory":"Beauty Salon",
            "type":"Services"
        }
    ],
    "sg:phone":"+1 215 471 8193",
    "sg:postcode":"19139",
    "sg:province":"PA",
    "wof:name":"Selective Beauty Salon",
    "wof:placetype":"venue"
},
  "geometry": {"coordinates":[-75.227182,39.95463],"type":"Point"}
}