{
  "type": "Feature",
  "properties": {
    "addr:full":"1009 Staghorn Rd Stroudsburg PA 18360",
    "addr:housenumber":"1009",
    "addr:postcode":"18360",
    "addr:street":"Staghorn Rd",
    "iso:country":"US",
    "sg:address":"1009 Staghorn Rd",
    "sg:city":"Stroudsburg",
    "sg:classifiers":[
        {
            "category":"Banks & Credit Unions",
            "subcategory":"Bank",
            "type":"Services"
        }
    ],
    "sg:phone":"+1 570 402 1086",
    "sg:postcode":"18360",
    "sg:province":"PA",
    "sg:tags":[
        "mortgage",
        "loan",
        "broker",
        "real estate"
    ],
    "sg:website":"www.mortgagesfirst.com",
    "wof:name":"Mortgages First Associates LLC",
    "wof:placetype":"venue"
},
  "geometry": {"coordinates":[-75.31635300000001,40.954092],"type":"Point"}
}