{
  "type": "Feature",
  "properties": {
    "addr:full":"2441 Butler Logan Rd Tarentum PA 15084",
    "addr:housenumber":"2441",
    "addr:postcode":"15084",
    "addr:street":"Butler Logan Rd",
    "iso:country":"US",
    "sg:address":"2441 Butler Logan Rd",
    "sg:city":"Tarentum",
    "sg:classifiers":[
        {
            "category":"Farming",
            "subcategory":"Farm",
            "type":"Manufacturing & Wholesale Goods"
        }
    ],
    "sg:phone":"+1   ",
    "sg:postcode":"15084",
    "sg:province":"PA",
    "sg:tags":[
        "crop",
        "general"
    ],
    "wof:name":"Windy Knoll Farms",
    "wof:placetype":"venue"
},
  "geometry": {"coordinates":[-79.80442499999999,40.588935],"type":"Point"}
}