{
  "type": "Feature",
  "properties": {
    "iso:country":"US",
    "sg:address":"3964 Newark Rd",
    "sg:city":"Oxford",
    "sg:classifiers":[
        {
            "category":"Farming",
            "subcategory":"Dairy Farm",
            "type":"Manufacturing & Wholesale Goods"
        }
    ],
    "sg:phone":"+1   ",
    "sg:postcode":"19363",
    "sg:province":"PA",
    "wof:name":"Yarnell Farms",
    "wof:placetype":"venue"
},
  "geometry": {"coordinates":[-75.95541299999999,39.847437],"type":"Point"}
}