{
  "type": "Feature",
  "properties": {
    "iso:country":"US",
    "sg:address":"634 Bloom St",
    "sg:city":"Danville",
    "sg:classifiers":[
        {
            "category":"Retail",
            "subcategory":"Repair Shop",
            "type":"Services"
        }
    ],
    "sg:phone":"+1 570 275 7743",
    "sg:postcode":"17821",
    "sg:province":"PA",
    "sg:tags":[
        "appliance"
    ],
    "wof:name":"Jim's Appliance",
    "wof:placetype":"venue"
},
  "geometry": {"coordinates":[-76.60588799999999,40.965007],"type":"Point"}
}