{
  "type": "Feature",
  "properties": {
    "iso:country":"US",
    "sg:address":"979 Bethlehem Pike",
    "sg:city":"Montgomeryville",
    "sg:classifiers":[
        {
            "category":"Shopping",
            "subcategory":"Books",
            "type":"Retail Goods"
        }
    ],
    "sg:phone":"+1   ",
    "sg:postcode":"18915",
    "sg:province":"PA",
    "wof:name":"Atlantic Books - Minnesota",
    "wof:placetype":"venue"
},
  "geometry": {"coordinates":[-75.261926,40.283977],"type":"Point"}
}