{
  "type": "Feature",
  "properties": {
    "iso:country":"US",
    "sg:address":"6 Oak Ln",
    "sg:city":"Port Royal",
    "sg:classifiers":[
        {
            "category":"Freight",
            "type":"Transportation"
        }
    ],
    "sg:phone":"+1   ",
    "sg:postcode":"17082",
    "sg:province":"PA",
    "sg:tags":[
        "operator",
        "local",
        "trucking"
    ],
    "wof:name":"Hambright Trucking",
    "wof:placetype":"venue"
},
  "geometry": {"coordinates":[-77.506879,40.517469],"type":"Point"}
}