{
  "type": "Feature",
  "properties": {
    "addr:full":"1901 Darby Rd Havertown PA 19083",
    "addr:housenumber":"1901",
    "addr:postcode":"19083",
    "addr:street":"Darby Rd",
    "iso:country":"US",
    "sg:address":"1901 Darby Rd",
    "sg:city":"Havertown",
    "sg:classifiers":[
        {
            "category":"Shopping",
            "subcategory":"Gifts & Souvenirs",
            "type":"Retail Goods"
        }
    ],
    "sg:phone":"+1 610 853 2202",
    "sg:postcode":"19083",
    "sg:province":"PA",
    "wof:name":"Irish Shop",
    "wof:placetype":"venue"
},
  "geometry": {"coordinates":[-75.307349,39.98493],"type":"Point"}
}