{
  "type": "Feature",
  "properties": {
    "iso:country":"US",
    "sg:address":"3168 Harvest Rd",
    "sg:city":"Elizabethtown",
    "sg:phone":"+1   ",
    "sg:postcode":"17022",
    "sg:province":"PA",
    "sg:tags":[
        "farm",
        "corn",
        "soybean"
    ],
    "wof:name":"Deerun Farm",
    "wof:placetype":"venue"
},
  "geometry": {"coordinates":[-76.531919,40.188155],"type":"Point"}
}