{
  "type": "Feature",
  "properties": {
    "iso:country":"US",
    "sg:address":"2 East Dr",
    "sg:city":"Mechanicsburg",
    "sg:classifiers":[
        {
            "category":"Building & Trades",
            "subcategory":"Plumbing",
            "type":"Services"
        }
    ],
    "sg:phone":"+1 717 506 7707",
    "sg:postcode":"17050",
    "sg:province":"PA",
    "sg:website":"www.assocproducts.com",
    "wof:name":"Mr Rooter",
    "wof:placetype":"venue"
},
  "geometry": {"coordinates":[-77.00748,40.226696],"type":"Point"}
}