{
  "type": "Feature",
  "properties": {
    "addr:full":"608 E McMurray Rd Canonsburg PA 15317",
    "addr:housenumber":"608",
    "addr:postcode":"15317",
    "addr:street":"E Mcmurray Rd",
    "iso:country":"US",
    "sg:address":"608 E McMurray Rd",
    "sg:city":"Canonsburg",
    "sg:classifiers":[
        {
            "category":"Health Services",
            "subcategory":"Dentist",
            "type":"Services"
        }
    ],
    "sg:phone":"+1 724 942 1400",
    "sg:postcode":"15317",
    "sg:province":"PA",
    "sg:website":"www.prucedental.com",
    "wof:name":"Pruce Robt L DMD",
    "wof:placetype":"venue"
},
  "geometry": {"coordinates":[-80.08380099999999,40.279301],"type":"Point"}
}