{
  "type": "Feature",
  "properties": {
    "iso:country":"US",
    "sg:address":"201 W Market St",
    "sg:city":"Middleburg",
    "sg:classifiers":[
        {
            "category":"Shopping",
            "subcategory":"Gifts & Souvenirs",
            "type":"Retail Goods"
        }
    ],
    "sg:phone":"+1 570 837 1941",
    "sg:postcode":"17842",
    "sg:province":"PA",
    "sg:tags":[
        "shop"
    ],
    "wof:name":"Youngnow Global",
    "wof:placetype":"venue"
},
  "geometry": {"coordinates":[-77.051035,40.791502],"type":"Point"}
}