{
  "type": "Feature",
  "properties": {
    "iso:country":"US",
    "sg:address":"83 Main St",
    "sg:city":"Wellsboro",
    "sg:classifiers":[
        {
            "category":"Bars & Pubs",
            "type":"Food & Drink"
        }
    ],
    "sg:phone":"+1   ",
    "sg:postcode":"16901",
    "sg:province":"PA",
    "sg:tags":[
        "drinking"
    ],
    "wof:name":"Joe Picks Inc",
    "wof:placetype":"venue"
},
  "geometry": {"coordinates":[-77.301042,41.748041],"type":"Point"}
}