{
  "type": "Feature",
  "properties": {
    "iso:country":"US",
    "sg:address":"2019 Bridge Rd",
    "sg:city":"Schwenksville",
    "sg:classifiers":[
        {
            "category":"Retail",
            "subcategory":"Auto Repair",
            "type":"Services"
        }
    ],
    "sg:phone":"+1 610 584 4444",
    "sg:postcode":"19473",
    "sg:province":"PA",
    "wof:name":"Skip's Garage",
    "wof:placetype":"venue"
},
  "geometry": {"coordinates":[-75.40510399999999,40.229227],"type":"Point"}
}