{
  "type": "Feature",
  "properties": {
    "iso:country":"US",
    "sg:address":"1562 James St",
    "sg:city":"Monroeville",
    "sg:classifiers":[
        {
            "category":"Real Estate",
            "subcategory":"Real Estate Operator",
            "type":"Services"
        }
    ],
    "sg:phone":"+1   ",
    "sg:postcode":"15146",
    "sg:province":"PA",
    "sg:tags":[
        "building",
        "nonresidential"
    ],
    "wof:name":"Wilson Blake Zambrano Suzanne",
    "wof:placetype":"venue"
},
  "geometry": {"coordinates":[-79.801981,40.42126],"type":"Point"}
}