{
  "type": "Feature",
  "properties": {
    "iso:country":"US",
    "sg:address":"439 N Pike Rd",
    "sg:city":"Sarver",
    "sg:phone":"+1   ",
    "sg:postcode":"16055",
    "sg:province":"PA",
    "sg:tags":[
        "farm"
    ],
    "wof:name":"Paul Meyers Farm",
    "wof:placetype":"venue"
},
  "geometry": {"coordinates":[-79.776522,40.756606],"type":"Point"}
}