{
  "type": "Feature",
  "properties": {
    "iso:country":"US",
    "sg:address":"505 Fairmont Ave",
    "sg:city":"Trafford",
    "sg:classifiers":[
        {
            "category":"Real Estate",
            "subcategory":"Real Estate Agent",
            "type":"Services"
        }
    ],
    "sg:phone":"+1   ",
    "sg:postcode":"15085",
    "sg:province":"PA",
    "wof:name":"Seans Real Estate Service LLC",
    "wof:placetype":"venue"
},
  "geometry": {"coordinates":[-79.756733,40.386643],"type":"Point"}
}