{
  "type": "Feature",
  "properties": {
    "addr:full":"315 N 52nd St Philadelphia PA 19139",
    "addr:housenumber":"315",
    "addr:postcode":"19139",
    "addr:street":"N 52Nd St",
    "iso:country":"US",
    "sg:address":"315 N 52nd St",
    "sg:city":"Philadelphia",
    "sg:classifiers":[
        {
            "category":"Professional",
            "type":"Services"
        }
    ],
    "sg:phone":"+1   ",
    "sg:postcode":"19139",
    "sg:province":"PA",
    "wof:name":"Patricio A Genao",
    "wof:placetype":"venue"
},
  "geometry": {"coordinates":[-75.22463999999999,39.965182],"type":"Point"}
}