{
  "type": "Feature",
  "properties": {
    "addr:full":"8201 Germantown Ave Philadelphia PA 19118",
    "addr:housenumber":"8201",
    "addr:postcode":"19118",
    "addr:street":"Germantown Ave",
    "iso:country":"US",
    "sg:address":"8201 Germantown Ave",
    "sg:city":"Philadelphia",
    "sg:classifiers":[
        {
            "category":"Restaurant",
            "type":"Food & Drink"
        }
    ],
    "sg:menulink":"http://www.allmenus.com/pa/philadelphia/262271-solaris-grille/menu/",
    "sg:phone":"+1 215 242 3400",
    "sg:postcode":"19118",
    "sg:province":"PA",
    "sg:tags":[
        "new",
        "american"
    ],
    "wof:name":"Solaris Grille",
    "wof:placetype":"venue"
},
  "geometry": {"coordinates":[-75.202663,40.07321],"type":"Point"}
}