{
  "type": "Feature",
  "properties": {
    "iso:country":"US",
    "sg:address":"510 3rd Ave",
    "sg:city":"Duncansville",
    "sg:classifiers":[
        {
            "category":"Health Services",
            "subcategory":"Doctor",
            "type":"Services"
        }
    ],
    "sg:phone":"+1   ",
    "sg:postcode":"16635",
    "sg:province":"PA",
    "wof:name":"Locker Neal H DMD",
    "wof:placetype":"venue"
},
  "geometry": {"coordinates":[-78.41959,40.427555],"type":"Point"}
}