{
  "type": "Feature",
  "properties": {
    "addr:full":"6 E Slocum St Philadelphia PA 19119",
    "addr:housenumber":"6",
    "addr:postcode":"19119",
    "addr:street":"E Slocum St",
    "iso:country":"US",
    "sg:address":"6 E Slocum St",
    "sg:city":"Philadelphia",
    "sg:classifiers":[
        {
            "category":"Organizations",
            "subcategory":"Religious Organization",
            "type":"Services"
        }
    ],
    "sg:phone":"+1 215 843 3382",
    "sg:postcode":"19119",
    "sg:province":"PA",
    "sg:tags":[
        "clergy"
    ],
    "wof:name":"Carla Harris",
    "wof:placetype":"venue"
},
  "geometry": {"coordinates":[-75.184438,40.05484],"type":"Point"}
}