{
  "type": "Feature",
  "properties": {
    "iso:country":"US",
    "sg:address":"2 Main St",
    "sg:city":"Coal Township",
    "sg:classifiers":[
        {
            "category":"Food & Beverages",
            "subcategory":"Groceries & Convenience Stores",
            "type":"Retail Goods"
        }
    ],
    "sg:phone":"+1 570 648 9663",
    "sg:postcode":"17866",
    "sg:province":"PA",
    "sg:tags":[
        "automotive",
        "station",
        "gas",
        "re",
        "general"
    ],
    "wof:name":"Mayton Mini Mart & Garage",
    "wof:placetype":"venue"
},
  "geometry": {"coordinates":[-76.521874,40.78744],"type":"Point"}
}