{
  "type": "Feature",
  "properties": {
    "addr:full":"2727 W 18th St Erie PA 16505",
    "addr:housenumber":"2727",
    "addr:postcode":"16505",
    "addr:street":"W 18Th St",
    "iso:country":"US",
    "sg:address":"2727 W 18th St",
    "sg:city":"Erie",
    "sg:classifiers":[
        {
            "category":"Home & Garden",
            "subcategory":"Building Materials",
            "type":"Retail Goods"
        }
    ],
    "sg:phone":"+1 814 833 7734",
    "sg:postcode":"16505",
    "sg:province":"PA",
    "sg:tags":[
        "truss"
    ],
    "sg:website":"www.locinc1.com",
    "wof:name":"Loc Inc",
    "wof:placetype":"venue"
},
  "geometry": {"coordinates":[-80.138465,42.095936],"type":"Point"}
}