{
  "type": "Feature",
  "properties": {
    "addr:full":"3401 Collins St Philadelphia PA 19134",
    "addr:housenumber":"3401",
    "addr:postcode":"19134",
    "addr:street":"Collins St",
    "iso:country":"US",
    "sg:address":"3401 Collins St",
    "sg:city":"Philadelphia",
    "sg:classifiers":[
        {
            "category":"Freight",
            "type":"Transportation"
        }
    ],
    "sg:phone":"+1 215 288 8258",
    "sg:postcode":"19134",
    "sg:province":"PA",
    "sg:tags":[
        "commercial",
        "storage"
    ],
    "wof:name":"Value Storage",
    "wof:placetype":"venue"
},
  "geometry": {"coordinates":[-75.10230199999999,39.995584],"type":"Point"}
}