{
  "type": "Feature",
  "properties": {
    "iso:country":"US",
    "sg:address":"808 Bethlehem Pike",
    "sg:city":"Flourtown",
    "sg:classifiers":[
        {
            "category":"Professional",
            "subcategory":"Accounting & Tax Preparation",
            "type":"Services"
        }
    ],
    "sg:phone":"+1 215 233 8981",
    "sg:postcode":"19031",
    "sg:province":"PA",
    "sg:tags":[
        "accountant"
    ],
    "wof:name":"Ford & Assoc",
    "wof:placetype":"venue"
},
  "geometry": {"coordinates":[-75.214096,40.111401],"type":"Point"}
}