{
  "type": "Feature",
  "properties": {
    "iso:country":"US",
    "sg:address":"585 Sportsman Rd",
    "sg:city":"Denver",
    "sg:classifiers":[
        {
            "category":"Organizations",
            "subcategory":"Community Association",
            "type":"Services"
        }
    ],
    "sg:phone":"+1 717 336 2997",
    "sg:postcode":"17517",
    "sg:province":"PA",
    "wof:name":"Cocalico Sportsman Associates",
    "wof:placetype":"venue"
},
  "geometry": {"coordinates":[-76.168228,40.27337],"type":"Point"}
}