{
  "type": "Feature",
  "properties": {
    "iso:country":"US",
    "sg:address":"575 Trail Rd",
    "sg:city":"Hummelstown",
    "sg:classifiers":[
        {
            "category":"Building & Trades",
            "subcategory":"Construction",
            "type":"Services"
        }
    ],
    "sg:phone":"+1   ",
    "sg:postcode":"17036",
    "sg:province":"PA",
    "sg:tags":[
        "home",
        "general",
        "family",
        "contractor"
    ],
    "wof:name":"Dennis L Hess Construction",
    "wof:placetype":"venue"
},
  "geometry": {"coordinates":[-76.66014199999999,40.33028],"type":"Point"}
}