{
  "type": "Feature",
  "properties": {
    "iso:country":"US",
    "sg:address":"200 Alan Wood Rd",
    "sg:city":"Conshohocken",
    "sg:classifiers":[
        {
            "category":"Wholesale",
            "subcategory":"Painting Supplies",
            "type":"Manufacturing & Wholesale Goods"
        },
        {
            "category":"Home & Garden",
            "subcategory":"Hardware",
            "type":"Retail Goods"
        },
        {
            "category":"Home & Garden",
            "subcategory":"Building Materials",
            "type":"Retail Goods"
        },
        {
            "category":"Manufacturing",
            "subcategory":"Tools & Machinery",
            "type":"Manufacturing & Wholesale Goods"
        }
    ],
    "sg:phone":"+1 610 834 1228",
    "sg:postcode":"19428",
    "sg:province":"PA",
    "sg:tags":[
        "paint",
        "store",
        "improvement"
    ],
    "sg:website":"http://www.homedepot.com",
    "wof:name":"The Home Depot",
    "wof:placetype":"venue"
},
  "geometry": {"coordinates":[-75.307704,40.095814],"type":"Point"}
}