{
  "type": "Feature",
  "properties": {
    "iso:country":"US",
    "sg:address":"260 Main St",
    "sg:city":"Greenville",
    "sg:classifiers":[
        {
            "category":"Social Services",
            "type":"Services"
        }
    ],
    "sg:phone":"+1   ",
    "sg:postcode":"16125",
    "sg:province":"PA",
    "wof:name":"Zions Youth Center",
    "wof:placetype":"venue"
},
  "geometry": {"coordinates":[-80.38650800000001,41.405903],"type":"Point"}
}