{
  "type": "Feature",
  "properties": {
    "iso:country":"US",
    "sg:address":"339 Ott Town Rd",
    "sg:city":"Everett",
    "sg:classifiers":[
        {
            "category":"Manufacturing",
            "subcategory":"Tools & Machinery",
            "type":"Manufacturing & Wholesale Goods"
        }
    ],
    "sg:phone":"+1   ",
    "sg:postcode":"15537",
    "sg:province":"PA",
    "sg:tags":[
        "machine",
        "shop",
        "works",
        "die"
    ],
    "wof:name":"Deasey Machine Tl & Die Works",
    "wof:placetype":"venue"
},
  "geometry": {"coordinates":[-78.44875999999999,39.978684],"type":"Point"}
}