{
  "type": "Feature",
  "properties": {
    "addr:full":"907 Scalp Ave Johnstown PA 15904",
    "addr:housenumber":"907",
    "addr:postcode":"15904",
    "addr:street":"Scalp Ave",
    "iso:country":"US",
    "sg:address":"907 Scalp Ave",
    "sg:city":"Johnstown",
    "sg:classifiers":[
        {
            "category":"Wholesale",
            "subcategory":"Machinery & Supplies",
            "type":"Manufacturing & Wholesale Goods"
        }
    ],
    "sg:phone":"+1   ",
    "sg:postcode":"15904",
    "sg:province":"PA",
    "sg:tags":[
        "equipment",
        "establishment"
    ],
    "wof:name":"East Coast Salon Services",
    "wof:placetype":"venue"
},
  "geometry": {"coordinates":[-78.865436,40.286178],"type":"Point"}
}