{
  "type": "Feature",
  "properties": {
    "iso:country":"US",
    "sg:address":"2212 Cottman Ave",
    "sg:city":"Philadelphia",
    "sg:classifiers":[
        {
            "category":"Bars & Pubs",
            "type":"Food & Drink"
        }
    ],
    "sg:phone":"+1 215 745 1292",
    "sg:postcode":"19149",
    "sg:province":"PA",
    "sg:tags":[
        "tavern",
        "restaurant"
    ],
    "sg:website":"http://www.nicksnortheast.com",
    "wof:name":"Nick's Roast Beef",
    "wof:placetype":"venue"
},
  "geometry": {"coordinates":[-75.061972,40.048892],"type":"Point"}
}