{
  "type": "Feature",
  "properties": {
    "iso:country":"US",
    "sg:address":"843 Chestnut St",
    "sg:city":"Philadelphia",
    "sg:classifiers":[
        {
            "category":"Shopping",
            "subcategory":"Jewelry",
            "type":"Retail Goods"
        }
    ],
    "sg:phone":"+1 215 928 0933",
    "sg:postcode":"19107",
    "sg:province":"PA",
    "sg:tags":[
        "jeweler"
    ],
    "wof:name":"London Jewelry",
    "wof:placetype":"venue"
},
  "geometry": {"coordinates":[-75.154962,39.949799],"type":"Point"}
}