{
  "type": "Feature",
  "properties": {
    "iso:country":"US",
    "sg:address":"1205 Main St",
    "sg:city":"Pittsburgh",
    "sg:classifiers":[
        {
            "category":"Government",
            "subcategory":"Court House",
            "type":"Public Place"
        }
    ],
    "sg:phone":"+1   ",
    "sg:postcode":"15215",
    "sg:province":"PA",
    "wof:name":"Magisterial District 05-2-04",
    "wof:placetype":"venue"
},
  "geometry": {"coordinates":[-79.929495,40.494246],"type":"Point"}
}