{
  "type": "Feature",
  "properties": {
    "iso:country":"US",
    "sg:address":"310 Valley Rd",
    "sg:city":"Merion Station",
    "sg:classifiers":[
        {
            "category":"Professional",
            "type":"Services"
        }
    ],
    "sg:phone":"+1   ",
    "sg:postcode":"19066",
    "sg:province":"PA",
    "wof:name":"Gerald Rifkin",
    "wof:placetype":"venue"
},
  "geometry": {"coordinates":[-75.252411,40.002653],"type":"Point"}
}