{
  "type": "Feature",
  "properties": {
    "iso:country":"US",
    "sg:address":"2 E Tioga St",
    "sg:city":"Tunkhannock",
    "sg:classifiers":[
        {
            "category":"Shopping",
            "subcategory":"Department Store",
            "type":"Retail Goods"
        },
        {
            "category":"Shopping",
            "subcategory":"Clothing, Apparel, & Fashions",
            "type":"Retail Goods"
        }
    ],
    "sg:phone":"+1 570 836 2105",
    "sg:postcode":"18657",
    "sg:province":"PA",
    "sg:tags":[
        "clothing"
    ],
    "wof:name":"Fitze's Inc",
    "wof:placetype":"venue"
},
  "geometry": {"coordinates":[-75.948357,41.53862],"type":"Point"}
}