{
  "type": "Feature",
  "properties": {
    "addr:full":"1521 Frankstown Rd Johnstown PA 15902",
    "addr:housenumber":"1521",
    "addr:postcode":"15902",
    "addr:street":"Frankstown Rd",
    "iso:country":"US",
    "sg:address":"1521 Frankstown Rd",
    "sg:city":"Johnstown",
    "sg:classifiers":[
        {
            "category":"Restaurant",
            "type":"Food & Drink"
        }
    ],
    "sg:phone":"+1 814 539 4534",
    "sg:postcode":"15902",
    "sg:province":"PA",
    "sg:tags":[
        "banquet",
        "rooms"
    ],
    "wof:name":"Amber Rose Banquet Facility",
    "wof:placetype":"venue"
},
  "geometry": {"coordinates":[-78.86703199999999,40.324616],"type":"Point"}
}