{
  "type": "Feature",
  "properties": {
    "addr:full":"206 Seneca St Oil City PA 16301",
    "addr:housenumber":"206",
    "addr:postcode":"16301",
    "addr:street":"Seneca St",
    "iso:country":"US",
    "sg:address":"206 Seneca St",
    "sg:city":"Oil City",
    "sg:classifiers":[
        {
            "category":"Education",
            "subcategory":"College",
            "type":"Public Place"
        }
    ],
    "sg:phone":"+1 814 677 3152",
    "sg:postcode":"16301",
    "sg:province":"PA",
    "sg:tags":[
        "academic",
        "school"
    ],
    "wof:name":"Clarion University Of Pa",
    "wof:placetype":"venue"
},
  "geometry": {"coordinates":[-79.708365,41.433135],"type":"Point"}
}