{
  "type": "Feature",
  "properties": {
    "iso:country":"US",
    "sg:address":"608 Center St",
    "sg:city":"Smithton",
    "sg:classifiers":[
        {
            "category":"Wholesale",
            "subcategory":"Chemicals & Plastics",
            "type":"Manufacturing & Wholesale Goods"
        }
    ],
    "sg:phone":"+1 724 872 9404",
    "sg:postcode":"15479",
    "sg:province":"PA",
    "sg:tags":[
        "equipment",
        "melting",
        "ice",
        "supply"
    ],
    "wof:name":"Elizabeth Milling Co",
    "wof:placetype":"venue"
},
  "geometry": {"coordinates":[-79.743049,40.155495],"type":"Point"}
}