{
  "type": "Feature",
  "properties": {
    "iso:country":"US",
    "sg:address":"736 W 9th St",
    "sg:city":"Hazleton",
    "sg:classifiers":[
        {
            "category":"Manufacturing",
            "subcategory":"Apparel",
            "type":"Manufacturing & Wholesale Goods"
        }
    ],
    "sg:phone":"+1 570 454 8211",
    "sg:postcode":"18201",
    "sg:province":"PA",
    "sg:tags":[
        "dress",
        "mfg"
    ],
    "wof:name":"Mountain City Mfg Co",
    "wof:placetype":"venue"
},
  "geometry": {"coordinates":[-75.985609,40.963238],"type":"Point"}
}