{
  "type": "Feature",
  "properties": {
    "iso:country":"US",
    "sg:address":"327 N Negley Ave",
    "sg:city":"Pittsburgh",
    "sg:classifiers":[
        {
            "category":"Education",
            "subcategory":"School",
            "type":"Public Place"
        }
    ],
    "sg:phone":"+1   ",
    "sg:postcode":"15206",
    "sg:province":"PA",
    "wof:name":"Urban League of Pittsburgh Cs",
    "wof:placetype":"venue"
},
  "geometry": {"coordinates":[-79.929113,40.466163],"type":"Point"}
}