{
  "type": "Feature",
  "properties": {
    "iso:country":"US",
    "sg:address":"71 E Silver St",
    "sg:city":"Sharon",
    "sg:classifiers":[
        {
            "category":"Retail",
            "subcategory":"Portrait Studio",
            "type":"Services"
        }
    ],
    "sg:phone":"+1 724 981 1995",
    "sg:postcode":"16146",
    "sg:province":"PA",
    "sg:tags":[
        "photographer"
    ],
    "wof:name":"Dave Vernon Photography",
    "wof:placetype":"venue"
},
  "geometry": {"coordinates":[-80.507665,41.234563],"type":"Point"}
}