{
  "type": "Feature",
  "properties": {
    "iso:country":"US",
    "sg:address":"103 N 5th St",
    "sg:city":"Minersville",
    "sg:classifiers":[
        {
            "category":"Building & Trades",
            "subcategory":"Construction",
            "type":"Services"
        }
    ],
    "sg:phone":"+1   ",
    "sg:postcode":"17954",
    "sg:province":"PA",
    "sg:tags":[
        "house"
    ],
    "wof:name":"Kap General Contractor",
    "wof:placetype":"venue"
},
  "geometry": {"coordinates":[-76.26558300000001,40.693363],"type":"Point"}
}