{
  "type": "Feature",
  "properties": {
    "iso:country":"US",
    "sg:address":"160 Leisie Rd",
    "sg:city":"Renfrew",
    "sg:classifiers":[
        {
            "category":"Building & Trades",
            "subcategory":"Electrical",
            "type":"Services"
        }
    ],
    "sg:phone":"+1 724 586 2831",
    "sg:postcode":"16053",
    "sg:province":"PA",
    "sg:tags":[
        "electrician",
        "contractor"
    ],
    "wof:name":"Joseph Scherer Electrical",
    "wof:placetype":"venue"
},
  "geometry": {"coordinates":[-79.982067,40.76775],"type":"Point"}
}