{
  "type": "Feature",
  "properties": {
    "iso:country":"US",
    "sg:address":"5200 Centre Ave Ste 606",
    "sg:city":"Pittsburgh",
    "sg:classifiers":[
        {
            "category":"Health Services",
            "subcategory":"Doctor",
            "type":"Services"
        },
        {
            "category":"Health Services",
            "subcategory":"Hospital",
            "type":"Services"
        },
        {
            "category":"Health Services",
            "subcategory":"Podiatrist",
            "type":"Services"
        }
    ],
    "sg:phone":"+1 412 683 9422",
    "sg:postcode":"15232",
    "sg:province":"PA",
    "sg:tags":[
        "physician",
        "oncology",
        "surgeons",
        "sleep",
        "treatment",
        "surgeon",
        "gynecologic",
        "disorders-information"
    ],
    "wof:name":"Bloom, Elena J Dr",
    "wof:placetype":"venue"
},
  "geometry": {"coordinates":[-79.94149,40.455029],"type":"Point"}
}