{
  "type": "Feature",
  "properties": {
    "addr:full":"37 Ashland Ave Bala Cynwyd PA 19004",
    "addr:housenumber":"37",
    "addr:postcode":"19004",
    "addr:street":"Ashland Ave",
    "iso:country":"US",
    "sg:address":"37 Ashland Ave",
    "sg:city":"Bala Cynwyd",
    "sg:classifiers":[
        {
            "category":"Building & Trades",
            "subcategory":"Locksmith",
            "type":"Services"
        }
    ],
    "sg:phone":"+1 484 446 3269",
    "sg:postcode":"19004",
    "sg:province":"PA",
    "sg:tags":[
        "key"
    ],
    "wof:name":"Always Affective Available Emergency Locksmith",
    "wof:placetype":"venue"
},
  "geometry": {"coordinates":[-75.232569,40.026215],"type":"Point"}
}