{
  "type": "Feature",
  "properties": {
    "addr:full":"227 Market St Philadelphia PA 19195",
    "addr:housenumber":"227",
    "addr:postcode":"19195",
    "addr:street":"Market St",
    "iso:country":"US",
    "sg:address":"227 Market St",
    "sg:city":"Philadelphia",
    "sg:classifiers":[
        {
            "category":"Food & Beverages",
            "subcategory":"Liquor & Beverages",
            "type":"Retail Goods"
        },
        {
            "category":"Shopping",
            "type":"Retail Goods"
        }
    ],
    "sg:phone":"+1 215 627 9463",
    "sg:postcode":"19195",
    "sg:province":"PA",
    "sg:tags":[
        "beer",
        "spirit",
        "wine"
    ],
    "sg:website":"www.pinotboutique.com",
    "wof:name":"Pinot",
    "wof:placetype":"venue"
},
  "geometry": {"coordinates":[-75.144644,39.95022],"type":"Point"}
}