{
  "type": "Feature",
  "properties": {
    "iso:country":"US",
    "sg:address":"111 E Baltimore Ave ",
    "sg:city":"Clifton Heights",
    "sg:classifiers":[
        {
            "category":"Restaurant",
            "type":"Food & Drink"
        }
    ],
    "sg:menulink":"http://www.allmenus.com/pa/clifton-heights/289082-philly-wings--things/menu/",
    "sg:phone":"+1 610 622 3100",
    "sg:postcode":"19018",
    "sg:province":"PA",
    "sg:tags":[
        "barbecue",
        "american",
        "wing"
    ],
    "wof:name":"Philly Wings & Things",
    "wof:placetype":"venue"
},
  "geometry": {"coordinates":[-75.29512800000001,39.93021],"type":"Point"}
}