{
  "type": "Feature",
  "properties": {
    "iso:country":"US",
    "sg:address":"2565 Susquehanna Rd",
    "sg:city":"Abington",
    "sg:classifiers":[
        {
            "category":"Exhibition Hall",
            "type":"Public Place"
        }
    ],
    "sg:phone":"+1 215 886 6217",
    "sg:postcode":"19001",
    "sg:province":"PA",
    "sg:tags":[
        "halls",
        "ballroom",
        "auditorium"
    ],
    "wof:name":"Ymca",
    "wof:placetype":"venue"
},
  "geometry": {"coordinates":[-75.14058199999999,40.125217],"type":"Point"}
}