{
  "type": "Feature",
  "properties": {
    "addr:full":"230 S Broad St Ste 400 Philadelphia PA 19102",
    "addr:housenumber":"230",
    "addr:postcode":"19102",
    "addr:street":"S Broad St Ste 400",
    "iso:country":"US",
    "sg:address":"230 S Broad St Ste 400",
    "sg:city":"Philadelphia",
    "sg:classifiers":[
        {
            "category":"Professional",
            "subcategory":"Accounting & Tax Preparation",
            "type":"Services"
        },
        {
            "category":"Professional",
            "subcategory":"Lawyer & Legal Services",
            "type":"Services"
        }
    ],
    "sg:phone":"+1 267 687 1149",
    "sg:postcode":"19102",
    "sg:province":"PA",
    "sg:tags":[
        "accountant"
    ],
    "sg:website":"www.mandalelaw.com",
    "wof:name":"Mandale Kaufmann - A Boutique Tax Law Practice",
    "wof:placetype":"venue"
},
  "geometry": {"coordinates":[-75.164953,39.948209],"type":"Point"}
}