{
  "type": "Feature",
  "properties": {
    "iso:country":"US",
    "sg:address":"6547 N 7th St",
    "sg:city":"Philadelphia",
    "sg:classifiers":[
        {
            "category":"Place Of Worship",
            "subcategory":"Church",
            "type":"Public Place"
        },
        {
            "category":"Place Of Worship",
            "type":"Public Place"
        }
    ],
    "sg:phone":"+1 215 424 1884",
    "sg:postcode":"19126",
    "sg:province":"PA",
    "sg:tags":[
        "testament",
        "christ-new",
        "christ",
        "churches-church"
    ],
    "wof:name":"Oak Lane United Church Of Christ",
    "wof:placetype":"venue"
},
  "geometry": {"coordinates":[-75.130954,40.05141],"type":"Point"}
}