{
  "type": "Feature",
  "properties": {
    "iso:country":"US",
    "sg:address":"117 S Market St",
    "sg:city":"Elizabethtown",
    "sg:classifiers":[
        {
            "category":"Professional",
            "subcategory":"Computer Services",
            "type":"Services"
        }
    ],
    "sg:phone":"+1 717 361 9958",
    "sg:postcode":"17022",
    "sg:province":"PA",
    "sg:tags":[
        "prepackaged",
        "software"
    ],
    "wof:name":"Perfect Order",
    "wof:placetype":"venue"
},
  "geometry": {"coordinates":[-76.604986,40.150068],"type":"Point"}
}