{
  "type": "Feature",
  "properties": {
    "iso:country":"US",
    "sg:address":"426 Horner Church Rd",
    "sg:city":"Stoystown",
    "sg:classifiers":[
        {
            "category":"Education",
            "subcategory":"School",
            "type":"Public Place"
        }
    ],
    "sg:phone":"+1   ",
    "sg:postcode":"15563",
    "sg:province":"PA",
    "sg:tags":[
        "organization",
        "religious"
    ],
    "wof:name":"Somerset Mennonite School",
    "wof:placetype":"venue"
},
  "geometry": {"coordinates":[-79.00368400000001,40.121993],"type":"Point"}
}