{
  "type": "Feature",
  "properties": {
    "iso:country":"US",
    "sg:address":"1909 Ritner Hwy",
    "sg:city":"Carlisle",
    "sg:classifiers":[
        {
            "category":"Health Services",
            "subcategory":"Dentist",
            "type":"Services"
        }
    ],
    "sg:phone":"+1 717 249 1646",
    "sg:postcode":"17013",
    "sg:province":"PA",
    "wof:name":"Perkins Allyn G DMD",
    "wof:placetype":"venue"
},
  "geometry": {"coordinates":[-77.24140199999999,40.191002],"type":"Point"}
}