{
  "type": "Feature",
  "properties": {
    "iso:country":"US",
    "sg:address":"56 E Emaus St",
    "sg:city":"Middletown",
    "sg:classifiers":[
        {
            "category":"Shopping",
            "subcategory":"Used Merchandise",
            "type":"Retail Goods"
        }
    ],
    "sg:phone":"+1 717 944 2707",
    "sg:postcode":"17057",
    "sg:province":"PA",
    "sg:tags":[
        "antique"
    ],
    "wof:name":"Middletown Manor Antq",
    "wof:placetype":"venue"
},
  "geometry": {"coordinates":[-76.72980200000001,40.194707],"type":"Point"}
}