{
  "type": "Feature",
  "properties": {
    "addr:full":"6554 Frankford Ave Philadelphia PA 19135",
    "addr:housenumber":"6554",
    "addr:postcode":"19135",
    "addr:street":"Frankford Ave",
    "iso:country":"US",
    "sg:address":"6554 Frankford Ave",
    "sg:city":"Philadelphia",
    "sg:classifiers":[
        {
            "category":"Autos & Motor Vehicles",
            "subcategory":"Fuel & Gas Station",
            "type":"Retail Goods"
        },
        {
            "category":"Retail",
            "subcategory":"Auto Repair",
            "type":"Services"
        }
    ],
    "sg:phone":"+1 215 624 8233",
    "sg:postcode":"19135",
    "sg:province":"PA",
    "sg:tags":[
        "automobile",
        "inspection",
        "diagnostic"
    ],
    "wof:name":"Magee Auto Service",
    "wof:placetype":"venue"
},
  "geometry": {"coordinates":[-75.055138,40.030396],"type":"Point"}
}