{
  "type": "Feature",
  "properties": {
    "iso:country":"US",
    "sg:address":"1210 Braun Rd",
    "sg:city":"Bethel Park",
    "sg:classifiers":[
        {
            "category":"Building & Trades",
            "subcategory":"Construction",
            "type":"Services"
        }
    ],
    "sg:phone":"+1 412 833 5514",
    "sg:postcode":"15102",
    "sg:province":"PA",
    "sg:tags":[
        "contractor"
    ],
    "wof:name":"Tommarello Leo & Son",
    "wof:placetype":"venue"
},
  "geometry": {"coordinates":[-80.042198,40.291302],"type":"Point"}
}