{
  "type": "Feature",
  "properties": {
    "addr:full":"1741 Hempstead Rd Lancaster PA 17601",
    "addr:housenumber":"1741",
    "addr:postcode":"17601",
    "addr:street":"Hempstead Rd",
    "iso:country":"US",
    "sg:address":"1741 Hempstead Rd",
    "sg:city":"Lancaster",
    "sg:classifiers":[
        {
            "category":"Professional",
            "subcategory":"Detective & Security Services",
            "type":"Services"
        }
    ],
    "sg:phone":"+1 717 413 1930",
    "sg:postcode":"17601",
    "sg:province":"PA",
    "sg:tags":[
        "information",
        "bureau"
    ],
    "wof:name":"R T R Services",
    "wof:placetype":"venue"
},
  "geometry": {"coordinates":[-76.252427,40.049097],"type":"Point"}
}