{
  "type": "Feature",
  "properties": {
    "addr:full":"S Mall Allentown PA 18101",
    "addr:postcode":"18101",
    "addr:street":"S Mall",
    "iso:country":"US",
    "sg:address":"S Mall",
    "sg:city":"Allentown",
    "sg:classifiers":[
        {
            "category":"Shopping",
            "subcategory":"Shoes",
            "type":"Retail Goods"
        }
    ],
    "sg:phone":"+1 610 791 5177",
    "sg:postcode":"18101",
    "sg:province":"PA",
    "sg:tags":[
        "store"
    ],
    "sg:website":"www.footlocker.com",
    "wof:name":"Foot Locker",
    "wof:placetype":"venue"
},
  "geometry": {"coordinates":[-75.474098,40.6031],"type":"Point"}
}