{
  "type": "Feature",
  "properties": {
    "addr:full":"1067 Baltimore Pike Media PA 19063",
    "addr:housenumber":"1067",
    "addr:postcode":"19063",
    "addr:street":"Baltimore Pike",
    "iso:country":"US",
    "sg:address":"1067 Baltimore Pike",
    "sg:city":"Media",
    "sg:classifiers":[
        {
            "category":"Shopping",
            "type":"Retail Goods"
        }
    ],
    "sg:phone":"+1 610 566 0171",
    "sg:postcode":"19063",
    "sg:province":"PA",
    "sg:tags":[
        "ice"
    ],
    "wof:name":"Rita's Water Ice",
    "wof:placetype":"venue"
},
  "geometry": {"coordinates":[-75.434286,39.913759],"type":"Point"}
}