{
  "type": "Feature",
  "properties": {
    "iso:country":"US",
    "sg:address":"10 Erford Rd",
    "sg:city":"Lemoyne",
    "sg:classifiers":[
        {
            "category":"Education",
            "subcategory":"Preschool",
            "type":"Public Place"
        },
        {
            "category":"Education",
            "subcategory":"School",
            "type":"Public Place"
        }
    ],
    "sg:phone":"+1 717 763 7811",
    "sg:postcode":"17043",
    "sg:province":"PA",
    "sg:tags":[
        "high",
        "middle",
        "elementary"
    ],
    "sg:website":"www.harrisburgacademy.org",
    "wof:name":"Harrisburg Academy",
    "wof:placetype":"venue"
},
  "geometry": {"coordinates":[-76.91330000000001,40.252998],"type":"Point"}
}