{
  "type": "Feature",
  "properties": {
    "iso:country":"US",
    "sg:address":"340 Ashbourne Rd",
    "sg:city":"Elkins Park",
    "sg:classifiers":[
        {
            "category":"Education",
            "subcategory":"Special Training",
            "type":"Public Place"
        }
    ],
    "sg:phone":"+1   ",
    "sg:postcode":"19027",
    "sg:province":"PA",
    "wof:name":"Elkins Park Music",
    "wof:placetype":"venue"
},
  "geometry": {"coordinates":[-75.12432800000001,40.068058],"type":"Point"}
}