{
  "type": "Feature",
  "properties": {
    "iso:country":"US",
    "sg:address":"912 Walnut St",
    "sg:city":"Mckeesport",
    "sg:classifiers":[
        {
            "category":"Wholesale",
            "subcategory":"Beer",
            "type":"Manufacturing & Wholesale Goods"
        }
    ],
    "sg:phone":"+1 412 664 7785",
    "sg:postcode":"15132",
    "sg:province":"PA",
    "sg:tags":[
        "ale"
    ],
    "wof:name":"Tube City Distributing Co",
    "wof:placetype":"venue"
},
  "geometry": {"coordinates":[-79.86389,40.346109],"type":"Point"}
}