{
  "type": "Feature",
  "properties": {
    "iso:country":"US",
    "sg:address":"1731 Spring Garden St",
    "sg:city":"Philadelphia",
    "sg:classifiers":[
        {
            "category":"Professional",
            "subcategory":"Lawyer & Legal Services",
            "type":"Services"
        }
    ],
    "sg:phone":"+1   ",
    "sg:postcode":"19130",
    "sg:province":"PA",
    "sg:tags":[
        "attorney"
    ],
    "wof:name":"Gay & Chacker",
    "wof:placetype":"venue"
},
  "geometry": {"coordinates":[-75.167475,39.963328],"type":"Point"}
}