{
  "type": "Feature",
  "properties": {
    "iso:country":"US",
    "sg:address":"2013 Chestnut St",
    "sg:city":"Philadelphia",
    "sg:classifiers":[
        {
            "category":"Restaurant",
            "type":"Food & Drink"
        }
    ],
    "sg:phone":"+1 215 567 3142",
    "sg:postcode":"19103",
    "sg:province":"PA",
    "wof:name":"Midtown Iv Restaurants Inc",
    "wof:placetype":"venue"
},
  "geometry": {"coordinates":[-75.173711,39.952091],"type":"Point"}
}