{
  "type": "Feature",
  "properties": {
    "iso:country":"US",
    "sg:address":"34 S 6th Ct",
    "sg:city":"Hamburg",
    "sg:classifiers":[
        {
            "category":"Building & Trades",
            "subcategory":"Electrical",
            "type":"Services"
        }
    ],
    "sg:phone":"+1 717 266 8700",
    "sg:postcode":"19526",
    "sg:province":"PA",
    "sg:tags":[
        "electric",
        "contractor"
    ],
    "wof:name":"J D Book Electrical Contract",
    "wof:placetype":"venue"
},
  "geometry": {"coordinates":[-75.976507,40.545588],"type":"Point"}
}