{
  "type": "Feature",
  "properties": {
    "iso:country":"US",
    "sg:address":"319 Elwyn Ave",
    "sg:city":"Springdale",
    "sg:classifiers":[
        {
            "category":"Building & Trades",
            "subcategory":"Construction",
            "type":"Services"
        }
    ],
    "sg:phone":"+1   ",
    "sg:postcode":"15144",
    "sg:province":"PA",
    "sg:tags":[
        "house"
    ],
    "wof:name":"Building Traditions Inc",
    "wof:placetype":"venue"
},
  "geometry": {"coordinates":[-79.788989,40.544246],"type":"Point"}
}