{
  "type": "Feature",
  "properties": {
    "iso:country":"US",
    "sg:address":"265 Lonesome Ln",
    "sg:city":"Palmerton",
    "sg:classifiers":[
        {
            "category":"Professional",
            "subcategory":"Accounting & Tax Preparation",
            "type":"Services"
        }
    ],
    "sg:phone":"+1 610 681 7973",
    "sg:postcode":"18071",
    "sg:province":"PA",
    "sg:tags":[
        "return",
        "preparation-business"
    ],
    "wof:name":"Nemeth Tax Service",
    "wof:placetype":"venue"
},
  "geometry": {"coordinates":[-75.521052,40.857781],"type":"Point"}
}