{
  "type": "Feature",
  "properties": {
    "iso:country":"US",
    "sg:address":"206 N 5th St",
    "sg:city":"Youngwood",
    "sg:classifiers":[
        {
            "category":"Professional",
            "subcategory":"Engineering",
            "type":"Services"
        }
    ],
    "sg:phone":"+1   ",
    "sg:postcode":"15697",
    "sg:province":"PA",
    "wof:name":"ESP Engineering",
    "wof:placetype":"venue"
},
  "geometry": {"coordinates":[-79.578369,40.242386],"type":"Point"}
}