{
  "type": "Feature",
  "properties": {
    "iso:country":"US",
    "sg:address":"1770 Lincoln Hwy E",
    "sg:city":"Lancaster",
    "sg:classifiers":[
        {
            "category":"Shopping",
            "subcategory":"Books",
            "type":"Retail Goods"
        }
    ],
    "sg:phone":"+1 717 393 9363",
    "sg:postcode":"17602",
    "sg:province":"PA",
    "sg:tags":[
        "dealer"
    ],
    "wof:name":"HACC Bookstore Lancaster",
    "wof:placetype":"venue"
},
  "geometry": {"coordinates":[-76.25842799999999,40.036604],"type":"Point"}
}