{
  "type": "Feature",
  "properties": {
    "iso:country":"US",
    "sg:address":"1096 Green Holly Rd",
    "sg:city":"Clarks Summit",
    "sg:classifiers":[
        {
            "category":"Real Estate",
            "subcategory":"Real Estate Operator",
            "type":"Services"
        }
    ],
    "sg:phone":"+1   ",
    "sg:postcode":"18411",
    "sg:province":"PA",
    "sg:tags":[
        "building",
        "apartment"
    ],
    "wof:name":"Laurel Wood Apartments",
    "wof:placetype":"venue"
},
  "geometry": {"coordinates":[-75.717996,41.49922],"type":"Point"}
}