{
  "type": "Feature",
  "properties": {
    "iso:country":"US",
    "sg:address":"1916 2nd Ave",
    "sg:city":"Altoona",
    "sg:classifiers":[
        {
            "category":"Building & Trades",
            "subcategory":"Construction",
            "type":"Services"
        }
    ],
    "sg:phone":"+1 814 942 8593",
    "sg:postcode":"16602",
    "sg:province":"PA",
    "sg:tags":[
        "contractor"
    ],
    "wof:name":"Mark Phillips Drywall",
    "wof:placetype":"venue"
},
  "geometry": {"coordinates":[-78.39896400000001,40.503523],"type":"Point"}
}