{
  "type": "Feature",
  "properties": {
    "addr:full":"140 S 3rd St Lehighton PA 18235",
    "addr:housenumber":"140",
    "addr:postcode":"18235",
    "addr:street":"S 3Rd St",
    "iso:country":"US",
    "sg:address":"140 S 3rd St",
    "sg:city":"Lehighton",
    "sg:classifiers":[
        {
            "category":"Government",
            "subcategory":"Fire Station",
            "type":"Public Place"
        }
    ],
    "sg:phone":"+1 610 377 2449",
    "sg:postcode":"18235",
    "sg:province":"PA",
    "sg:tags":[
        "department"
    ],
    "wof:name":"Lehighton Borough Fire Dept 1",
    "wof:placetype":"venue"
},
  "geometry": {"coordinates":[-75.71199799999999,40.832239],"type":"Point"}
}