{
  "type": "Feature",
  "properties": {
    "iso:country":"US",
    "sg:address":"1059 3rd St",
    "sg:city":"Whitehall",
    "sg:classifiers":[
        {
            "category":"Home & Garden",
            "subcategory":"Building Materials",
            "type":"Retail Goods"
        },
        {
            "category":"Wholesale",
            "subcategory":"Auto Parts",
            "type":"Manufacturing & Wholesale Goods"
        }
    ],
    "sg:phone":"+1 610 266 0555",
    "sg:postcode":"18052",
    "sg:province":"PA",
    "sg:tags":[
        "plate",
        "window",
        "glass",
        "replacement"
    ],
    "wof:name":"Lehigh Valley Auto Glass Inc",
    "wof:placetype":"venue"
},
  "geometry": {"coordinates":[-75.47227700000001,40.640088],"type":"Point"}
}