{
  "type": "Feature",
  "properties": {
    "iso:country":"US",
    "sg:address":"113 W North St",
    "sg:city":"Wilkes Barre",
    "sg:classifiers":[
        {
            "category":"Government",
            "subcategory":"Office",
            "type":"Public Place"
        }
    ],
    "sg:phone":"+1   ",
    "sg:postcode":"18701",
    "sg:province":"PA",
    "sg:tags":[
        "program",
        "administrative"
    ],
    "wof:name":"County of Luzerne",
    "wof:placetype":"venue"
},
  "geometry": {"coordinates":[-75.878047,41.25183],"type":"Point"}
}