{
  "type": "Feature",
  "properties": {
    "iso:country":"US",
    "sg:address":"843 E Baltimore Pike",
    "sg:city":"Kennett Square",
    "sg:classifiers":[
        {
            "category":"Restaurant",
            "type":"Food & Drink"
        }
    ],
    "sg:phone":"+1 610 444 2220",
    "sg:postcode":"19348",
    "sg:province":"PA",
    "sg:tags":[
        "chinese"
    ],
    "wof:name":"King's Island Chinese Restaurant",
    "wof:placetype":"venue"
},
  "geometry": {"coordinates":[-75.683296,39.861698],"type":"Point"}
}