{
  "type": "Feature",
  "properties": {
    "iso:country":"US",
    "sg:address":"1420 Locust St Ste 410",
    "sg:city":"Philadelphia",
    "sg:classifiers":[
        {
            "category":"Real Estate",
            "subcategory":"Real Estate Services",
            "type":"Services"
        }
    ],
    "sg:phone":"+1 215 735 9096",
    "sg:postcode":"19102",
    "sg:province":"PA",
    "sg:tags":[
        "management",
        "condominium"
    ],
    "wof:name":"Academy House Condo",
    "wof:placetype":"venue"
},
  "geometry": {"coordinates":[-75.16484,39.948243],"type":"Point"}
}