{
  "type": "Feature",
  "properties": {
    "addr:full":"3 Cornerstone Dr Langhorne PA 19047",
    "addr:housenumber":"3",
    "addr:postcode":"19047",
    "addr:street":"Cornerstone Dr",
    "iso:country":"US",
    "sg:address":"3 Cornerstone Dr",
    "sg:city":"Langhorne",
    "sg:classifiers":[
        {
            "category":"Health Services",
            "subcategory":"Doctor",
            "type":"Services"
        }
    ],
    "sg:phone":"+1 215 752 4040",
    "sg:postcode":"19047",
    "sg:province":"PA",
    "sg:tags":[
        "physician",
        "surgeon"
    ],
    "wof:name":"Thanki Ashok MD",
    "wof:placetype":"venue"
},
  "geometry": {"coordinates":[-74.888993,40.188017],"type":"Point"}
}