{
  "type": "Feature",
  "properties": {
    "addr:full":"2429 Wharton St Philadelphia PA 19146",
    "addr:housenumber":"2429",
    "addr:postcode":"19146",
    "addr:street":"Wharton St",
    "iso:country":"US",
    "sg:address":"2429 Wharton St",
    "sg:city":"Philadelphia",
    "sg:classifiers":[
        {
            "category":"Parking",
            "type":"Transportation"
        }
    ],
    "sg:phone":"+1 215 463 9111",
    "sg:postcode":"19146",
    "sg:province":"PA",
    "wof:name":"B & J Wood Flooring",
    "wof:placetype":"venue"
},
  "geometry": {"coordinates":[-75.184938,39.936526],"type":"Point"}
}