{
  "type": "Feature",
  "properties": {
    "iso:country":"US",
    "sg:address":"193 Lemoyne Ave",
    "sg:city":"Washington",
    "sg:classifiers":[
        {
            "category":"Banks & Credit Unions",
            "subcategory":"Investment Brokerage",
            "type":"Services"
        }
    ],
    "sg:phone":"+1   ",
    "sg:postcode":"15301",
    "sg:province":"PA",
    "sg:tags":[
        "advisory"
    ],
    "wof:name":"Private Financial Services",
    "wof:placetype":"venue"
},
  "geometry": {"coordinates":[-80.22786600000001,40.173669],"type":"Point"}
}