{
  "type": "Feature",
  "properties": {
    "iso:country":"US",
    "sg:address":"402 W Marshall St",
    "sg:city":"Norristown",
    "sg:classifiers":[
        {
            "category":"Personal",
            "subcategory":"Barber",
            "type":"Services"
        }
    ],
    "sg:phone":"+1 610 272 3777",
    "sg:postcode":"19401",
    "sg:province":"PA",
    "wof:name":"Poindexters Barber Shop",
    "wof:placetype":"venue"
},
  "geometry": {"coordinates":[-75.34904400000001,40.120045],"type":"Point"}
}