{
  "type": "Feature",
  "properties": {
    "iso:country":"US",
    "sg:address":"915 Grandon Way",
    "sg:city":"Mechanicsburg",
    "sg:classifiers":[
        {
            "category":"Internet Cafe",
            "subcategory":"None",
            "type":"Food & Drink"
        }
    ],
    "sg:phone":"+1 717 697 1900",
    "sg:postcode":"17050",
    "sg:province":"PA",
    "sg:tags":[
        "directory",
        "product"
    ],
    "wof:name":"Snojax Inc",
    "wof:placetype":"venue"
},
  "geometry": {"coordinates":[-76.975548,40.264061],"type":"Point"}
}