{
  "type": "Feature",
  "properties": {
    "addr:full":"568 E Old York Rd Boiling Springs PA 17013",
    "addr:housenumber":"568",
    "addr:postcode":"17013",
    "addr:street":"E Old York Rd",
    "iso:country":"US",
    "sg:address":"568 E Old York Rd",
    "sg:city":"Boiling Springs",
    "sg:classifiers":[
        {
            "category":"Professional",
            "subcategory":"Business Services",
            "type":"Services"
        }
    ],
    "sg:phone":"+1 717 241 2222",
    "sg:postcode":"17013",
    "sg:province":"PA",
    "sg:tags":[
        "auctioneer"
    ],
    "wof:name":"White Rose Auctions",
    "wof:placetype":"venue"
},
  "geometry": {"coordinates":[-77.151106,40.152288],"type":"Point"}
}