{
  "type": "Feature",
  "properties": {
    "addr:full":"1600 Black Rock Rd Royersford PA 19468",
    "addr:housenumber":"1600",
    "addr:postcode":"19468",
    "addr:street":"Black Rock Rd",
    "iso:country":"US",
    "sg:address":"1600 Black Rock Rd",
    "sg:city":"Royersford",
    "sg:classifiers":[
        {
            "category":"Social Services",
            "subcategory":"Adult Care",
            "type":"Services"
        }
    ],
    "sg:phone":"+1   ",
    "sg:postcode":"19468",
    "sg:province":"PA",
    "sg:tags":[
        "residential",
        "executive"
    ],
    "wof:name":"Geriatric & Rehabilitation Ctr",
    "wof:placetype":"venue"
},
  "geometry": {"coordinates":[-75.512383,40.159385],"type":"Point"}
}