{
  "type": "Feature",
  "properties": {
    "addr:full":"221 Commercial Ave Pittsburgh PA 15215",
    "addr:housenumber":"221",
    "addr:postcode":"15215",
    "addr:street":"Commercial Ave",
    "iso:country":"US",
    "sg:address":"221 Commercial Ave",
    "sg:city":"Pittsburgh",
    "sg:classifiers":[
        {
            "category":"Banks & Credit Unions",
            "subcategory":"Bank",
            "type":"Services"
        }
    ],
    "sg:phone":"+1   ",
    "sg:postcode":"15215",
    "sg:province":"PA",
    "sg:tags":[
        "broker",
        "mortgage"
    ],
    "wof:name":"Allied Home Mrtg Capitl Corp",
    "wof:placetype":"venue"
},
  "geometry": {"coordinates":[-79.904,40.490194],"type":"Point"}
}