{
  "type": "Feature",
  "properties": {
    "addr:full":"508 N 3rd St Harrisburg PA 17101",
    "addr:housenumber":"508",
    "addr:postcode":"17101",
    "addr:street":"N 3Rd St",
    "iso:country":"US",
    "sg:address":"508 N 3rd St",
    "sg:city":"Harrisburg",
    "sg:classifiers":[
        {
            "category":"Organizations",
            "subcategory":"Labor Organization",
            "type":"Services"
        }
    ],
    "sg:phone":"+1 717 234 2568",
    "sg:postcode":"17101",
    "sg:province":"PA",
    "wof:name":"Independent State Store Union",
    "wof:placetype":"venue"
},
  "geometry": {"coordinates":[-76.885347,40.264453],"type":"Point"}
}