{
  "type": "Feature",
  "properties": {
    "addr:full":"311 Adams Ave Scranton PA 18503",
    "addr:housenumber":"311",
    "addr:postcode":"18503",
    "addr:street":"Adams Ave",
    "iso:country":"US",
    "sg:address":"311 Adams Ave",
    "sg:city":"Scranton",
    "sg:classifiers":[
        {
            "category":"Shopping",
            "type":"Retail Goods"
        }
    ],
    "sg:phone":"+1 570 963 0337",
    "sg:postcode":"18503",
    "sg:province":"PA",
    "sg:tags":[
        "cosmetic",
        "perfume"
    ],
    "wof:name":"Essence Of Paradise",
    "wof:placetype":"venue"
},
  "geometry": {"coordinates":[-75.65986599999999,41.409386],"type":"Point"}
}