{
  "type": "Feature",
  "properties": {
    "iso:country":"US",
    "sg:address":"3428 Derry St",
    "sg:city":"Harrisburg",
    "sg:classifiers":[
        {
            "category":"Personal",
            "subcategory":"Beauty Salon",
            "type":"Services"
        }
    ],
    "sg:phone":"+1 717 564 7220",
    "sg:postcode":"17111",
    "sg:province":"PA",
    "sg:tags":[
        "nail",
        "shop",
        "manicuring"
    ],
    "wof:name":"Sami's Nail Salon",
    "wof:placetype":"venue"
},
  "geometry": {"coordinates":[-76.832497,40.258999],"type":"Point"}
}