{
  "type": "Feature",
  "properties": {
    "addr:full":"3004 Hempland Rd Lancaster PA 17601",
    "addr:housenumber":"3004",
    "addr:postcode":"17601",
    "addr:street":"Hempland Rd",
    "iso:country":"US",
    "sg:address":"3004 Hempland Rd",
    "sg:city":"Lancaster",
    "sg:classifiers":[
        {
            "category":"Personal",
            "type":"Services"
        }
    ],
    "sg:phone":"+1 717 390 0760",
    "sg:postcode":"17601",
    "sg:province":"PA",
    "sg:tags":[
        "therapist",
        "massage"
    ],
    "sg:website":"www.tranquility-center.com",
    "wof:name":"Tranquility Ctr For Well-Being",
    "wof:placetype":"venue"
},
  "geometry": {"coordinates":[-76.405264,40.047468],"type":"Point"}
}