{
  "type": "Feature",
  "properties": {
    "addr:full":"2140 Ardmore Blvd Wilkinsburg PA 15221",
    "addr:housenumber":"2140",
    "addr:postcode":"15221",
    "addr:street":"Ardmore Blvd",
    "iso:country":"US",
    "sg:address":"2140 Ardmore Blvd",
    "sg:city":"Wilkinsburg",
    "sg:classifiers":[
        {
            "category":"Organizations",
            "subcategory":"Religious Organization",
            "type":"Services"
        }
    ],
    "sg:phone":"+1 412 371 2299",
    "sg:postcode":"15221",
    "sg:province":"PA",
    "sg:tags":[
        "church"
    ],
    "wof:name":"Protestant Reformed Mission",
    "wof:placetype":"venue"
},
  "geometry": {"coordinates":[-79.84917,40.418754],"type":"Point"}
}