{
  "type": "Feature",
  "properties": {
    "addr:full":"100 Fleet St Pittsburgh PA 15220",
    "addr:housenumber":"100",
    "addr:postcode":"15220",
    "addr:street":"Fleet St",
    "iso:country":"US",
    "sg:address":"100 Fleet St",
    "sg:city":"Pittsburgh",
    "sg:classifiers":[
        {
            "category":"Health Services",
            "subcategory":"Doctor",
            "type":"Services"
        }
    ],
    "sg:phone":"+1 412 922 1400",
    "sg:postcode":"15220",
    "sg:province":"PA",
    "sg:tags":[
        "physician",
        "surgeon"
    ],
    "wof:name":"Advanced Ultrasound",
    "wof:placetype":"venue"
},
  "geometry": {"coordinates":[-80.048222,40.421434],"type":"Point"}
}