{
  "type": "Feature",
  "properties": {
    "addr:full":"140 W Main St Troy PA 16947",
    "addr:housenumber":"140",
    "addr:postcode":"16947",
    "addr:street":"W Main St",
    "iso:country":"US",
    "sg:address":"140 W Main St",
    "sg:city":"Troy",
    "sg:classifiers":[
        {
            "category":"Travel",
            "subcategory":"Hotels & Motels",
            "type":"Entertainment"
        }
    ],
    "sg:phone":"+1   ",
    "sg:postcode":"16947",
    "sg:province":"PA",
    "sg:tags":[
        "operation"
    ],
    "wof:name":"Holcomb Gest Hse Bed Breakfast",
    "wof:placetype":"venue"
},
  "geometry": {"coordinates":[-76.790235,41.786231],"type":"Point"}
}