{
  "type": "Feature",
  "properties": {
    "addr:full":"712 Fire Ln Bethlehem PA 18015",
    "addr:housenumber":"712",
    "addr:postcode":"18015",
    "addr:street":"Fire Ln",
    "iso:country":"US",
    "sg:address":"712 Fire Ln",
    "sg:city":"Bethlehem",
    "sg:classifiers":[
        {
            "category":"Banks & Credit Unions",
            "subcategory":"Investment Brokerage",
            "type":"Services"
        }
    ],
    "sg:phone":"+1   ",
    "sg:postcode":"18015",
    "sg:province":"PA",
    "sg:tags":[
        "preparation",
        "advisory",
        "tax",
        "return"
    ],
    "wof:name":"McMann Tax Service",
    "wof:placetype":"venue"
},
  "geometry": {"coordinates":[-75.346654,40.597372],"type":"Point"}
}