{
  "type": "Feature",
  "properties": {
    "iso:country":"US",
    "sg:address":"450 Blank School Rd",
    "sg:city":"Greensburg",
    "sg:classifiers":[
        {
            "category":"Building & Trades",
            "subcategory":"Plumbing",
            "type":"Services"
        }
    ],
    "sg:phone":"+1   ",
    "sg:postcode":"15601",
    "sg:province":"PA",
    "sg:tags":[
        "contractor"
    ],
    "wof:name":"Sunglow Radiant Heating",
    "wof:placetype":"venue"
},
  "geometry": {"coordinates":[-79.53401100000001,40.323456],"type":"Point"}
}