{
  "type": "Feature",
  "properties": {
    "iso:country":"US",
    "sg:address":"500 Arch St",
    "sg:city":"Philadelphia",
    "sg:classifiers":[
        {
            "category":"Travel",
            "subcategory":"Travel Agent",
            "type":"Entertainment"
        }
    ],
    "sg:phone":"+1 215 629 5801",
    "sg:postcode":"19106",
    "sg:province":"PA",
    "sg:tags":[
        "information",
        "tourist"
    ],
    "wof:name":"Historic Philadelphia Inc",
    "wof:placetype":"venue"
},
  "geometry": {"coordinates":[-75.14992599999999,39.952757],"type":"Point"}
}