{
  "type": "Feature",
  "properties": {
    "iso:country":"US",
    "sg:address":"6015 Allentown Blvd",
    "sg:city":"Harrisburg",
    "sg:classifiers":[
        {
            "category":"Personal",
            "subcategory":"Tanning Parlor",
            "type":"Services"
        }
    ],
    "sg:phone":"+1 717 671 5776",
    "sg:postcode":"17112",
    "sg:province":"PA",
    "sg:tags":[
        "salon"
    ],
    "wof:name":"Tansations",
    "wof:placetype":"venue"
},
  "geometry": {"coordinates":[-76.78710700000001,40.323067],"type":"Point"}
}