{
  "type": "Feature",
  "properties": {
    "iso:country":"US",
    "sg:address":"15005 Bustleton Ave",
    "sg:city":"Philadelphia",
    "sg:classifiers":[
        {
            "category":"Restaurant",
            "type":"Food & Drink"
        }
    ],
    "sg:phone":"+1   ",
    "sg:postcode":"19116",
    "sg:province":"PA",
    "sg:tags":[
        "eating"
    ],
    "wof:name":"Kleopatra Inc",
    "wof:placetype":"venue"
},
  "geometry": {"coordinates":[-75.009073,40.134293],"type":"Point"}
}