{
  "type": "Feature",
  "properties": {
    "addr:full":"4205 Main St Philadelphia PA 19127",
    "addr:housenumber":"4205",
    "addr:postcode":"19127",
    "addr:street":"Main St",
    "iso:country":"US",
    "sg:address":"4205 Main St",
    "sg:city":"Philadelphia",
    "sg:classifiers":[
        {
            "category":"Personal",
            "subcategory":"Beauty Salon",
            "type":"Services"
        }
    ],
    "sg:phone":"+1 215 930 0394",
    "sg:postcode":"19127",
    "sg:province":"PA",
    "sg:tags":[
        "shop"
    ],
    "wof:name":"Ground Zero Hair Salon",
    "wof:placetype":"venue"
},
  "geometry": {"coordinates":[-75.222616,40.025134],"type":"Point"}
}