{
  "type": "Feature",
  "properties": {
    "iso:country":"US",
    "sg:address":"439 Countyline St",
    "sg:city":"New Castle",
    "sg:classifiers":[
        {
            "category":"Organizations",
            "subcategory":"Religious Organization",
            "type":"Services"
        }
    ],
    "sg:phone":"+1 724 652 0541",
    "sg:postcode":"16101",
    "sg:province":"PA",
    "wof:name":"Second Presbyterian Church",
    "wof:placetype":"venue"
},
  "geometry": {"coordinates":[-80.341348,40.997788],"type":"Point"}
}