{
  "type": "Feature",
  "properties": {
    "addr:full":"424 6th Ave Pittsburgh PA 15219",
    "addr:housenumber":"424",
    "addr:postcode":"15219",
    "addr:street":"6Th Ave",
    "iso:country":"US",
    "sg:address":"424 6th Ave",
    "sg:city":"Pittsburgh",
    "sg:classifiers":[
        {
            "category":"Professional",
            "subcategory":"Management & Consulting",
            "type":"Services"
        }
    ],
    "sg:phone":"+1 412 325 6991",
    "sg:postcode":"15219",
    "sg:province":"PA",
    "sg:tags":[
        "fuel"
    ],
    "wof:name":"Olszak Management Consult",
    "wof:placetype":"venue"
},
  "geometry": {"coordinates":[-79.99592199999999,40.440799],"type":"Point"}
}