{
  "type": "Feature",
  "properties": {
    "addr:full":"656 Main St Hellertown PA 18055",
    "addr:housenumber":"656",
    "addr:postcode":"18055",
    "addr:street":"Main St",
    "iso:country":"US",
    "sg:address":"656 Main St",
    "sg:city":"Hellertown",
    "sg:classifiers":[
        {
            "category":"Professional",
            "subcategory":"Lawyer & Legal Services",
            "type":"Services"
        }
    ],
    "sg:phone":"+1 610 838 5500",
    "sg:postcode":"18055",
    "sg:province":"PA",
    "wof:name":"Gordon Charles William",
    "wof:placetype":"venue"
},
  "geometry": {"coordinates":[-75.34079699999999,40.578999],"type":"Point"}
}