{
  "type": "Feature",
  "properties": {
    "addr:full":"1128 N 18th St Allentown PA 18104",
    "addr:housenumber":"1128",
    "addr:postcode":"18104",
    "addr:street":"N 18Th St",
    "iso:country":"US",
    "sg:address":"1128 N 18th St",
    "sg:city":"Allentown",
    "sg:classifiers":[
        {
            "category":"Professional",
            "subcategory":"Advertising",
            "type":"Services"
        }
    ],
    "sg:phone":"+1 610 435 1053",
    "sg:postcode":"18104",
    "sg:province":"PA",
    "sg:tags":[
        "agency"
    ],
    "wof:name":"A LA Carte Advertising",
    "wof:placetype":"venue"
},
  "geometry": {"coordinates":[-75.502748,40.613574],"type":"Point"}
}