{
  "type": "Feature",
  "properties": {
    "iso:country":"US",
    "sg:address":"7500 Brooktree Rd",
    "sg:city":"Wexford",
    "sg:classifiers":[
        {
            "category":"Professional",
            "type":"Services"
        },
        {
            "category":"Banks & Credit Unions",
            "subcategory":"Financial Services",
            "type":"Services"
        }
    ],
    "sg:phone":"+1 724 940 2666",
    "sg:postcode":"15090",
    "sg:province":"PA",
    "sg:website":"www.dnb.com",
    "wof:name":"Dun & Bradstreet",
    "wof:placetype":"venue"
},
  "geometry": {"coordinates":[-80.059922,40.614071],"type":"Point"}
}