{
  "type": "Feature",
  "properties": {
    "addr:full":"500 E Main St Carnegie PA 15106",
    "addr:housenumber":"500",
    "addr:postcode":"15106",
    "addr:street":"E Main St",
    "iso:country":"US",
    "sg:address":"500 E Main St",
    "sg:city":"Carnegie",
    "sg:classifiers":[
        {
            "category":"Coffee & Tea",
            "type":"Food & Drink"
        },
        {
            "category":"Bakery",
            "type":"Food & Drink"
        },
        {
            "category":"Donuts",
            "type":"Food & Drink"
        }
    ],
    "sg:menulink":"http://www.allmenus.com/pa/carnegie/222474-donut-connection/menu/",
    "sg:phone":"+1 412 276 8870",
    "sg:postcode":"15106",
    "sg:province":"PA",
    "sg:tags":[
        "american",
        "pastry"
    ],
    "wof:name":"Donut Connection",
    "wof:placetype":"venue"
},
  "geometry": {"coordinates":[-80.08149,40.410814],"type":"Point"}
}