{
  "type": "Feature",
  "properties": {
    "iso:country":"US",
    "sg:address":"1570 Garrett Rd",
    "sg:city":"Upper Darby",
    "sg:classifiers":[
        {
            "category":"Education",
            "subcategory":"Vocational School",
            "type":"Public Place"
        }
    ],
    "sg:phone":"+1   ",
    "sg:postcode":"19082",
    "sg:province":"PA",
    "wof:name":"Star Technical Institute",
    "wof:placetype":"venue"
},
  "geometry": {"coordinates":[-75.274185,39.955128],"type":"Point"}
}