{
  "type": "Feature",
  "properties": {
    "iso:country":"US",
    "sg:address":"1 Constitution Blvd",
    "sg:city":"Aliquippa",
    "sg:classifiers":[
        {
            "category":"Personal",
            "type":"Services"
        },
        {
            "category":"Structure",
            "subcategory":"Warehouse",
            "type":"Public Place"
        },
        {
            "category":"Retail",
            "subcategory":"Storage",
            "type":"Services"
        }
    ],
    "sg:phone":"+1 724 375 3333",
    "sg:postcode":"15001",
    "sg:province":"PA",
    "sg:tags":[
        "household",
        "full",
        "commercial",
        "warehouses-public-commercial",
        "mover"
    ],
    "wof:name":"Michelle's Self Storage",
    "wof:placetype":"venue"
},
  "geometry": {"coordinates":[-80.243416,40.61788],"type":"Point"}
}