{
  "type": "Feature",
  "properties": {
    "addr:full":"511 Treasure Lake Du Bois PA 15801",
    "addr:housenumber":"511",
    "addr:postcode":"15801",
    "addr:street":"Treasure Lake Du Bois",
    "iso:country":"US",
    "sg:address":"511 Treasure Lake",
    "sg:city":"Du Bois",
    "sg:classifiers":[
        {
            "category":"Insurance",
            "subcategory":"Insurance Agent",
            "type":"Services"
        }
    ],
    "sg:phone":"+1   ",
    "sg:postcode":"15801",
    "sg:province":"PA",
    "sg:tags":[
        "real estate"
    ],
    "wof:name":"Bechtel Agency",
    "wof:placetype":"venue"
},
  "geometry": {"coordinates":[-78.70965700000001,41.160298],"type":"Point"}
}