{
  "type": "Feature",
  "properties": {
    "addr:full":"72 Harris Hill Rd Shavertown PA 18708",
    "addr:housenumber":"72",
    "addr:postcode":"18708",
    "addr:street":"Harris Hill Rd",
    "iso:country":"US",
    "sg:address":"72 Harris Hill Rd",
    "sg:city":"Shavertown",
    "sg:classifiers":[
        {
            "category":"Professional",
            "type":"Services"
        }
    ],
    "sg:phone":"+1   ",
    "sg:postcode":"18708",
    "sg:province":"PA",
    "wof:name":"Robert Weiskerger Co",
    "wof:placetype":"venue"
},
  "geometry": {"coordinates":[-75.927521,41.314609],"type":"Point"}
}