{
  "type": "Feature",
  "properties": {
    "iso:country":"US",
    "sg:address":"243 Ekastown Rd",
    "sg:city":"Sarver",
    "sg:classifiers":[
        {
            "category":"Health Services",
            "subcategory":"Health Practitioner",
            "type":"Services"
        }
    ],
    "sg:phone":"+1 724 353 9144",
    "sg:postcode":"16055",
    "sg:province":"PA",
    "sg:tags":[
        "nurse",
        "registry"
    ],
    "wof:name":"Special Needs Nursing Care Inc",
    "wof:placetype":"venue"
},
  "geometry": {"coordinates":[-79.735951,40.673911],"type":"Point"}
}