{
  "type": "Feature",
  "properties": {
    "addr:full":"270 Calhoun Rd Aliquippa PA 15001",
    "addr:housenumber":"270",
    "addr:postcode":"15001",
    "addr:street":"Calhoun Rd",
    "iso:country":"US",
    "sg:address":"270 Calhoun Rd",
    "sg:city":"Aliquippa",
    "sg:classifiers":[
        {
            "category":"Building & Trades",
            "subcategory":"Construction",
            "type":"Services"
        }
    ],
    "sg:phone":"+1   ",
    "sg:postcode":"15001",
    "sg:province":"PA",
    "sg:tags":[
        "contractor"
    ],
    "wof:name":"Fetchin Masonry",
    "wof:placetype":"venue"
},
  "geometry": {"coordinates":[-80.381428,40.592764],"type":"Point"}
}