{
  "type": "Feature",
  "properties": {
    "iso:country":"US",
    "sg:address":"7 Birch Dr",
    "sg:city":"Thompsontown",
    "sg:classifiers":[
        {
            "category":"Building & Trades",
            "subcategory":"Construction",
            "type":"Services"
        }
    ],
    "sg:phone":"+1   ",
    "sg:postcode":"17094",
    "sg:province":"PA",
    "sg:tags":[
        "floor",
        "laying",
        "contractor"
    ],
    "wof:name":"Eichman Hardwood Floors",
    "wof:placetype":"venue"
},
  "geometry": {"coordinates":[-77.241415,40.573271],"type":"Point"}
}