{
  "type": "Feature",
  "properties": {
    "addr:full":"1584 W Main St Exd Grove City PA 16127",
    "addr:housenumber":"1584",
    "addr:postcode":"16127",
    "addr:street":"W Main St Exd",
    "iso:country":"US",
    "sg:address":"1584 W Main St Exd",
    "sg:city":"Grove City",
    "sg:classifiers":[
        {
            "category":"Building & Trades",
            "subcategory":"Plumbing",
            "type":"Services"
        }
    ],
    "sg:phone":"+1   ",
    "sg:postcode":"16127",
    "sg:province":"PA",
    "sg:tags":[
        "contractor"
    ],
    "wof:name":"Hovis Plumbing & Heating",
    "wof:placetype":"venue"
},
  "geometry": {"coordinates":[-80.11523800000001,41.170085],"type":"Point"}
}