{
  "type": "Feature",
  "properties": {
    "iso:country":"US",
    "sg:address":"7 Holly Ct",
    "sg:city":"Danville",
    "sg:classifiers":[
        {
            "category":"Recreation",
            "type":"Entertainment"
        }
    ],
    "sg:phone":"+1   ",
    "sg:postcode":"17821",
    "sg:province":"PA",
    "sg:tags":[
        "club",
        "membership"
    ],
    "wof:name":"Cotton Club",
    "wof:placetype":"venue"
},
  "geometry": {"coordinates":[-76.589399,40.968857],"type":"Point"}
}