{
  "type": "Feature",
  "properties": {
    "iso:country":"US",
    "sg:address":"6516 Easton Rd",
    "sg:city":"Pipersville",
    "sg:classifiers":[
        {
            "category":"Home & Garden",
            "subcategory":"Home Furnishings",
            "type":"Retail Goods"
        }
    ],
    "sg:phone":"+1 215 766 0331",
    "sg:postcode":"18947",
    "sg:province":"PA",
    "sg:tags":[
        "decor"
    ],
    "sg:website":"www.piperclassics.com/",
    "wof:name":"Piper Classics",
    "wof:placetype":"venue"
},
  "geometry": {"coordinates":[-75.15226699999999,40.40683],"type":"Point"}
}