{
  "type": "Feature",
  "properties": {
    "iso:country":"US",
    "sg:address":"402 5th St",
    "sg:city":"Easton",
    "sg:classifiers":[
        {
            "category":"Bars & Pubs",
            "type":"Food & Drink"
        }
    ],
    "sg:phone":"+1   ",
    "sg:postcode":"18042",
    "sg:province":"PA",
    "sg:tags":[
        "drinking"
    ],
    "wof:name":"West Estn A A",
    "wof:placetype":"venue"
},
  "geometry": {"coordinates":[-75.239053,40.677203],"type":"Point"}
}