{
  "type": "Feature",
  "properties": {
    "iso:country":"US",
    "sg:address":"140 N 5th St",
    "sg:city":"Connellsville",
    "sg:classifiers":[
        {
            "category":"Building & Trades",
            "subcategory":"Construction",
            "type":"Services"
        }
    ],
    "sg:phone":"+1 724 626 2790",
    "sg:postcode":"15425",
    "sg:province":"PA",
    "sg:tags":[
        "home",
        "residential",
        "remodeling",
        "improvement"
    ],
    "wof:name":"Brooks Quality Remodeling Co",
    "wof:placetype":"venue"
},
  "geometry": {"coordinates":[-79.597829,40.018427],"type":"Point"}
}