{
  "type": "Feature",
  "properties": {
    "iso:country":"US",
    "sg:address":"1720 Metropolitan St",
    "sg:city":"Pittsburgh",
    "sg:classifiers":[
        {
            "category":"Building & Trades",
            "subcategory":"Construction",
            "type":"Services"
        }
    ],
    "sg:phone":"+1 412 321 4901",
    "sg:postcode":"15233",
    "sg:province":"PA",
    "sg:tags":[
        "commercial",
        "contractor"
    ],
    "sg:website":"www.mascaroconst.com",
    "wof:name":"Mascaro Construction Company Lp",
    "wof:placetype":"venue"
},
  "geometry": {"coordinates":[-80.031403,40.4561],"type":"Point"}
}