{
  "type": "Feature",
  "properties": {
    "iso:country":"US",
    "sg:address":"1377 Spencer Ave",
    "sg:city":"Lancaster",
    "sg:classifiers":[
        {
            "category":"Professional",
            "subcategory":"Management & Consulting",
            "type":"Services"
        },
        {
            "category":"Building & Trades",
            "subcategory":"Construction",
            "type":"Services"
        }
    ],
    "sg:phone":"+1 717 394 1454",
    "sg:postcode":"17603",
    "sg:province":"PA",
    "sg:tags":[
        "consultant",
        "hotel",
        "apartment",
        "business"
    ],
    "sg:website":"www.themanorgroup.com",
    "wof:name":"Manor Management Group",
    "wof:placetype":"venue"
},
  "geometry": {"coordinates":[-76.33278300000001,40.026609],"type":"Point"}
}