{
  "type": "Feature",
  "properties": {
    "addr:full":"2007 Chestnut St Philadelphia PA 19103",
    "addr:housenumber":"2007",
    "addr:postcode":"19103",
    "addr:street":"Chestnut St",
    "iso:country":"US",
    "sg:address":"2007 Chestnut St",
    "sg:city":"Philadelphia",
    "sg:classifiers":[
        {
            "category":"Health Services",
            "subcategory":"Chiropractor",
            "type":"Services"
        }
    ],
    "sg:phone":"+1 215 988 1898",
    "sg:postcode":"19103",
    "sg:province":"PA",
    "wof:name":"Rittenhouse Chiropractic",
    "wof:placetype":"venue"
},
  "geometry": {"coordinates":[-75.17396100000001,39.952179],"type":"Point"}
}