{
  "type": "Feature",
  "properties": {
    "addr:full":"607 Monroe St Stroudsburg PA 18360",
    "addr:housenumber":"607",
    "addr:postcode":"18360",
    "addr:street":"Monroe St",
    "iso:country":"US",
    "sg:address":"607 Monroe St",
    "sg:city":"Stroudsburg",
    "sg:classifiers":[
        {
            "category":"Professional",
            "subcategory":"Lawyer & Legal Services",
            "type":"Services"
        }
    ],
    "sg:phone":"+1   ",
    "sg:postcode":"18360",
    "sg:province":"PA",
    "wof:name":"Lockwood & Jackson",
    "wof:placetype":"venue"
},
  "geometry": {"coordinates":[-75.193674,40.986715],"type":"Point"}
}