{
  "type": "Feature",
  "properties": {
    "addr:full":"219 Walnut Hill Rd Millersville PA 17551",
    "addr:housenumber":"219",
    "addr:postcode":"17551",
    "addr:street":"Walnut Hill Rd",
    "iso:country":"US",
    "sg:address":"219 Walnut Hill Rd",
    "sg:city":"Millersville",
    "sg:classifiers":[
        {
            "category":"Organizations",
            "subcategory":"Community Association",
            "type":"Services"
        }
    ],
    "sg:phone":"+1 717 872 9998",
    "sg:postcode":"17551",
    "sg:province":"PA",
    "sg:tags":[
        "military",
        "veteran"
    ],
    "wof:name":"Veterans Of Foreign Wars",
    "wof:placetype":"venue"
},
  "geometry": {"coordinates":[-76.36775400000001,39.989756],"type":"Point"}
}