{
  "type": "Feature",
  "properties": {
    "addr:full":"4260 Tackawanna St Philadelphia PA 19124",
    "addr:housenumber":"4260",
    "addr:postcode":"19124",
    "addr:street":"Tackawanna St",
    "iso:country":"US",
    "sg:address":"4260 Tackawanna St",
    "sg:city":"Philadelphia",
    "sg:classifiers":[
        {
            "category":"Wholesale",
            "subcategory":"Furniture",
            "type":"Manufacturing & Wholesale Goods"
        }
    ],
    "sg:phone":"+1 215 743 4614",
    "sg:postcode":"19124",
    "sg:province":"PA",
    "wof:name":"Cramco Distributing",
    "wof:placetype":"venue"
},
  "geometry": {"coordinates":[-75.085398,40.009231],"type":"Point"}
}