{
  "type": "Feature",
  "properties": {
    "addr:full":"1005 Caroline St Nanty Glo PA 15943",
    "addr:housenumber":"1005",
    "addr:postcode":"15943",
    "addr:street":"Caroline St",
    "iso:country":"US",
    "sg:address":"1005 Caroline St",
    "sg:city":"Nanty Glo",
    "sg:classifiers":[
        {
            "category":"Education",
            "subcategory":"School",
            "type":"Public Place"
        }
    ],
    "sg:phone":"+1 814 749 9031",
    "sg:postcode":"15943",
    "sg:province":"PA",
    "wof:name":"St Mary's School",
    "wof:placetype":"venue"
},
  "geometry": {"coordinates":[-78.83822000000001,40.470952],"type":"Point"}
}