{
  "type": "Feature",
  "properties": {
    "addr:full":"5375 Progress Blvd Bethel Park PA 15102",
    "addr:housenumber":"5375",
    "addr:postcode":"15102",
    "addr:street":"Progress Blvd",
    "iso:country":"US",
    "sg:address":"5375 Progress Blvd",
    "sg:city":"Bethel Park",
    "sg:classifiers":[
        {
            "category":"Autos & Motor Vehicles",
            "subcategory":"Auto Supplies",
            "type":"Retail Goods"
        }
    ],
    "sg:phone":"+1 412 831 1810",
    "sg:postcode":"15102",
    "sg:province":"PA",
    "sg:tags":[
        "tire"
    ],
    "wof:name":"Rich's Truck Tire Svc",
    "wof:placetype":"venue"
},
  "geometry": {"coordinates":[-80.04232,40.323396],"type":"Point"}
}