{
  "type": "Feature",
  "properties": {
    "iso:country":"US",
    "sg:address":"2380 Upper Ridge Rd",
    "sg:city":"Perkiomenville",
    "sg:classifiers":[
        {
            "category":"Building & Trades",
            "subcategory":"Plumbing",
            "type":"Services"
        }
    ],
    "sg:phone":"+1   ",
    "sg:postcode":"18074",
    "sg:province":"PA",
    "sg:tags":[
        "contractor"
    ],
    "wof:name":"Temp-Tech Service Co",
    "wof:placetype":"venue"
},
  "geometry": {"coordinates":[-75.474508,40.325231],"type":"Point"}
}