{
  "type": "Feature",
  "properties": {
    "iso:country":"US",
    "sg:address":"188 2nd St",
    "sg:city":"Highspire",
    "sg:classifiers":[
        {
            "category":"Personal",
            "subcategory":"Beauty Salon",
            "type":"Services"
        }
    ],
    "sg:phone":"+1 717 939 8920",
    "sg:postcode":"17034",
    "sg:province":"PA",
    "wof:name":"Skie's The Limit",
    "wof:placetype":"venue"
},
  "geometry": {"coordinates":[-76.791382,40.209351],"type":"Point"}
}