{
  "type": "Feature",
  "properties": {
    "iso:country":"US",
    "sg:address":"1280 Conewango Ave",
    "sg:city":"Warren",
    "sg:classifiers":[
        {
            "category":"Real Estate",
            "subcategory":"Real Estate Operator",
            "type":"Services"
        }
    ],
    "sg:phone":"+1   ",
    "sg:postcode":"16365",
    "sg:province":"PA",
    "sg:tags":[
        "property",
        "lessor"
    ],
    "wof:name":"Act Electrical Co",
    "wof:placetype":"venue"
},
  "geometry": {"coordinates":[-79.148764,41.867454],"type":"Point"}
}