{
  "type": "Feature",
  "properties": {
    "iso:country":"US",
    "sg:address":"200 W 3rd Ave",
    "sg:city":"Warren",
    "sg:classifiers":[
        {
            "category":"Real Estate",
            "subcategory":"Real Estate Agent",
            "type":"Services"
        }
    ],
    "sg:phone":"+1   ",
    "sg:postcode":"16365",
    "sg:province":"PA",
    "wof:name":"Daley Real Estate",
    "wof:placetype":"venue"
},
  "geometry": {"coordinates":[-79.14578,41.846643],"type":"Point"}
}