{
  "type": "Feature",
  "properties": {
    "iso:country":"US",
    "sg:address":"400 Maple Shade Rd",
    "sg:city":"Kirkwood",
    "sg:classifiers":[
        {
            "category":"Restaurant",
            "type":"Food & Drink"
        }
    ],
    "sg:phone":"+1   ",
    "sg:postcode":"17536",
    "sg:province":"PA",
    "sg:tags":[
        "eating"
    ],
    "wof:name":"Reinharts Sub Shop",
    "wof:placetype":"venue"
},
  "geometry": {"coordinates":[-76.077423,39.856536],"type":"Point"}
}