{
  "type": "Feature",
  "properties": {
    "addr:full":"6949 Sisto St Verona PA 15147",
    "addr:housenumber":"6949",
    "addr:postcode":"15147",
    "addr:street":"Sisto St",
    "iso:country":"US",
    "sg:address":"6949 Sisto St",
    "sg:city":"Verona",
    "sg:classifiers":[
        {
            "category":"Organizations",
            "subcategory":"Non-profit Organization",
            "type":"Services"
        }
    ],
    "sg:phone":"+1 412 828 4565",
    "sg:postcode":"15147",
    "sg:province":"PA",
    "wof:name":"ISA",
    "wof:placetype":"venue"
},
  "geometry": {"coordinates":[-79.842232,40.502611],"type":"Point"}
}