{
  "type": "Feature",
  "properties": {
    "addr:full":"1234 W Chester Pike Wayne PA 19083",
    "addr:housenumber":"1234",
    "addr:postcode":"19083",
    "addr:street":"W Chester Pike",
    "iso:country":"US",
    "sg:address":"1234 W Chester Pike",
    "sg:city":"Wayne",
    "sg:classifiers":[
        {
            "category":"Banks & Credit Unions",
            "subcategory":"Investment Brokerage",
            "type":"Services"
        }
    ],
    "sg:phone":"+1   ",
    "sg:postcode":"19083",
    "sg:province":"PA",
    "sg:tags":[
        "advisory"
    ],
    "wof:name":"C A K Capital Management Inc",
    "wof:placetype":"venue"
},
  "geometry": {"coordinates":[-75.318888,39.972772],"type":"Point"}
}