{
  "type": "Feature",
  "properties": {
    "iso:country":"US",
    "sg:address":"3506 Capital City Mall",
    "sg:city":"Camp Hill",
    "sg:classifiers":[
        {
            "category":"Shopping",
            "subcategory":"Optician",
            "type":"Retail Goods"
        }
    ],
    "sg:phone":"+1 717 730 9310",
    "sg:postcode":"17011",
    "sg:province":"PA",
    "sg:tags":[
        "eyewear"
    ],
    "sg:website":"www2.sunglasshut.com",
    "wof:name":"Sunglass Hut International",
    "wof:placetype":"venue"
},
  "geometry": {"coordinates":[-76.930099,40.222599],"type":"Point"}
}