{
  "type": "Feature",
  "properties": {
    "addr:full":"2 Walnut St Belleville PA 17004",
    "addr:housenumber":"2",
    "addr:postcode":"17004",
    "addr:street":"Walnut St",
    "iso:country":"US",
    "sg:address":"2 Walnut St",
    "sg:city":"Belleville",
    "sg:classifiers":[
        {
            "category":"Museum",
            "type":"Entertainment"
        }
    ],
    "sg:phone":"+1 717 935 5574",
    "sg:postcode":"17004",
    "sg:province":"PA",
    "sg:tags":[
        "gallery"
    ],
    "wof:name":"Mennonite Heritage Center",
    "wof:placetype":"venue"
},
  "geometry": {"coordinates":[-77.727502,40.604553],"type":"Point"}
}