{
  "type": "Feature",
  "properties": {
    "addr:full":"2700 S 7th St Philadelphia PA 19148",
    "addr:housenumber":"2700",
    "addr:postcode":"19148",
    "addr:street":"S 7Th St",
    "iso:country":"US",
    "sg:address":"2700 S 7th St",
    "sg:city":"Philadelphia",
    "sg:classifiers":[
        {
            "category":"Restaurant",
            "type":"Food & Drink"
        }
    ],
    "sg:phone":"+1 215 271 5722",
    "sg:postcode":"19148",
    "sg:province":"PA",
    "sg:tags":[
        "pizza"
    ],
    "wof:name":"Ralph & Rickey's Pizza",
    "wof:placetype":"venue"
},
  "geometry": {"coordinates":[-75.160004,39.915199],"type":"Point"}
}