{
  "type": "Feature",
  "properties": {
    "addr:full":"3741 State Rte 257 Seneca PA 16346",
    "addr:housenumber":"3741",
    "addr:postcode":"16346",
    "addr:street":"State Rte 257",
    "iso:country":"US",
    "sg:address":"3741 State Rte 257",
    "sg:city":"Seneca",
    "sg:classifiers":[
        {
            "category":"Real Estate",
            "subcategory":"Real Estate Agent",
            "type":"Services"
        }
    ],
    "sg:phone":"+1 814 677 0079",
    "sg:postcode":"16346",
    "sg:province":"PA",
    "wof:name":"D M Mc Vay & Assoc",
    "wof:placetype":"venue"
},
  "geometry": {"coordinates":[-79.704224,41.397264],"type":"Point"}
}