{
  "type": "Feature",
  "properties": {
    "addr:full":"130 Grand Ave Mars PA 16046",
    "addr:housenumber":"130",
    "addr:postcode":"16046",
    "addr:street":"Grand Ave",
    "iso:country":"US",
    "sg:address":"130 Grand Ave",
    "sg:city":"Mars",
    "sg:classifiers":[
        {
            "category":"Restaurant",
            "type":"Food & Drink"
        }
    ],
    "sg:menulink":"http://www.allmenus.com/pa/mars/292297-postis-pizza/menu/",
    "sg:phone":"+1 724 687 0663",
    "sg:postcode":"16046",
    "sg:province":"PA",
    "sg:tags":[
        "pizza"
    ],
    "wof:name":"Posti's Pizza",
    "wof:placetype":"venue"
},
  "geometry": {"coordinates":[-80.010336,40.696569],"type":"Point"}
}