{
  "type": "Feature",
  "properties": {
    "iso:country":"US",
    "sg:address":"470 S 5th Ave",
    "sg:city":"Clarion",
    "sg:classifiers":[
        {
            "category":"Home & Garden",
            "subcategory":"Carpets & Floor Coverings",
            "type":"Retail Goods"
        }
    ],
    "sg:phone":"+1 814 226 7332",
    "sg:postcode":"16214",
    "sg:province":"PA",
    "wof:name":"Carpet Barn",
    "wof:placetype":"venue"
},
  "geometry": {"coordinates":[-79.390991,41.205236],"type":"Point"}
}