{
  "type": "Feature",
  "properties": {
    "iso:country":"US",
    "sg:address":"1301 W Chester Rd",
    "sg:city":"West Chester",
    "sg:classifiers":[
        {
            "category":"Health Services",
            "subcategory":"Doctor",
            "type":"Services"
        }
    ],
    "sg:phone":"+1 610 429 0850",
    "sg:postcode":"19382",
    "sg:province":"PA",
    "sg:tags":[
        "physician",
        "surgeon"
    ],
    "wof:name":"Family Practice Assoc",
    "wof:placetype":"venue"
},
  "geometry": {"coordinates":[-75.547183,39.911209],"type":"Point"}
}