{
  "type": "Feature",
  "properties": {
    "iso:country":"US",
    "sg:address":"1101 W Dekalb Pike",
    "sg:city":"Wayne",
    "sg:classifiers":[
        {
            "category":"Food & Beverages",
            "subcategory":"Groceries & Convenience Stores",
            "type":"Retail Goods"
        },
        {
            "category":"Manufacturing",
            "subcategory":"Petroleum Products",
            "type":"Manufacturing & Wholesale Goods"
        }
    ],
    "sg:phone":"+1 610 265 8081",
    "sg:postcode":"19087",
    "sg:province":"PA",
    "sg:tags":[
        "station",
        "gas"
    ],
    "sg:website":"www.atlantispetroleum.com",
    "wof:name":"Atlantis Petroleum LLC",
    "wof:placetype":"venue"
},
  "geometry": {"coordinates":[-75.406689,40.081493],"type":"Point"}
}