{
  "type": "Feature",
  "properties": {
    "iso:country":"US",
    "sg:address":"7 Michigan Dr",
    "sg:city":"Reading",
    "sg:classifiers":[
        {
            "category":"Shopping",
            "type":"Retail Goods"
        }
    ],
    "sg:phone":"+1 610 678 3295",
    "sg:postcode":"19608",
    "sg:province":"PA",
    "sg:tags":[
        "merchandise"
    ],
    "wof:name":"Aunt Tiques Collectibles",
    "wof:placetype":"venue"
},
  "geometry": {"coordinates":[-76.027417,40.317473],"type":"Point"}
}