{
  "type": "Feature",
  "properties": {
    "addr:full":"28544 Hwy 27 Guys Mills PA 16327",
    "addr:housenumber":"28544",
    "addr:postcode":"16327",
    "addr:street":"Hwy 27",
    "iso:country":"US",
    "sg:address":"28544 Hwy 27",
    "sg:city":"Guys Mills",
    "sg:classifiers":[
        {
            "category":"Manufacturing",
            "subcategory":"Apparel",
            "type":"Manufacturing & Wholesale Goods"
        }
    ],
    "sg:phone":"+1   ",
    "sg:postcode":"16327",
    "sg:province":"PA",
    "sg:tags":[
        "embroidery"
    ],
    "wof:name":"Pair-A-Dice Designs",
    "wof:placetype":"venue"
},
  "geometry": {"coordinates":[-79.972257,41.596343],"type":"Point"}
}