{
  "type": "Feature",
  "properties": {
    "iso:country":"US",
    "sg:address":"401 Walnut St",
    "sg:city":"Norristown",
    "sg:classifiers":[
        {
            "category":"Restaurant",
            "type":"Food & Drink"
        }
    ],
    "sg:phone":"+1   ",
    "sg:postcode":"19401",
    "sg:province":"PA",
    "sg:tags":[
        "eating"
    ],
    "wof:name":"East Coast Tile & Kitchen",
    "wof:placetype":"venue"
},
  "geometry": {"coordinates":[-75.33622699999999,40.112899],"type":"Point"}
}