{
  "type": "Feature",
  "properties": {
    "iso:country":"US",
    "sg:address":"116 School Rd",
    "sg:city":"Aliquippa",
    "sg:classifiers":[
        {
            "category":"Government",
            "subcategory":"Fire Station",
            "type":"Public Place"
        }
    ],
    "sg:phone":"+1 724 378 4939",
    "sg:postcode":"15001",
    "sg:province":"PA",
    "sg:tags":[
        "department"
    ],
    "wof:name":"Independence Twp Vol Fire Dept",
    "wof:placetype":"venue"
},
  "geometry": {"coordinates":[-80.32788600000001,40.544038],"type":"Point"}
}