{
  "type": "Feature",
  "properties": {
    "iso:country":"US",
    "sg:address":"130 N Centre St",
    "sg:city":"Philipsburg",
    "sg:classifiers":[
        {
            "category":"Shopping",
            "type":"Retail Goods"
        }
    ],
    "sg:phone":"+1 814 342 2480",
    "sg:postcode":"16866",
    "sg:province":"PA",
    "sg:tags":[
        "monument"
    ],
    "wof:name":"Philipsburg Marble & Granite",
    "wof:placetype":"venue"
},
  "geometry": {"coordinates":[-78.221509,40.897779],"type":"Point"}
}