{
  "type": "Feature",
  "properties": {
    "iso:country":"US",
    "sg:address":"49 Wistar Rd",
    "sg:city":"Villanova",
    "sg:classifiers":[
        {
            "category":"Professional",
            "type":"Services"
        }
    ],
    "sg:phone":"+1   ",
    "sg:postcode":"19085",
    "sg:province":"PA",
    "wof:name":"Stanley M Baron",
    "wof:placetype":"venue"
},
  "geometry": {"coordinates":[-75.346412,40.045281],"type":"Point"}
}