{
  "type": "Feature",
  "properties": {
    "iso:country":"US",
    "sg:address":"388 E Main St",
    "sg:city":"Leola",
    "sg:classifiers":[
        {
            "category":"Railroad",
            "type":"Transportation"
        }
    ],
    "sg:phone":"+1   ",
    "sg:postcode":"17540",
    "sg:province":"PA",
    "sg:tags":[
        "rail",
        "local",
        "trucking"
    ],
    "wof:name":"Mar Pro",
    "wof:placetype":"venue"
},
  "geometry": {"coordinates":[-76.144577,40.092627],"type":"Point"}
}