{
  "type": "Feature",
  "properties": {
    "addr:full":"325 E Main St Carnegie PA 15106",
    "addr:housenumber":"325",
    "addr:postcode":"15106",
    "addr:street":"E Main St",
    "iso:country":"US",
    "sg:address":"325 E Main St",
    "sg:city":"Carnegie",
    "sg:classifiers":[
        {
            "category":"Insurance",
            "subcategory":"Insurance Agent",
            "type":"Services"
        }
    ],
    "sg:phone":"+1 412 276 6900",
    "sg:postcode":"15106",
    "sg:province":"PA",
    "wof:name":"Colonial Supplemental Ins",
    "wof:placetype":"venue"
},
  "geometry": {"coordinates":[-80.083354,40.409682],"type":"Point"}
}