{
  "type": "Feature",
  "properties": {
    "iso:country":"US",
    "sg:address":"10782 Lucky Rd",
    "sg:city":"Felton",
    "sg:classifiers":[
        {
            "category":"Farming",
            "subcategory":"Livestock Farm",
            "type":"Manufacturing & Wholesale Goods"
        }
    ],
    "sg:phone":"+1 717 927 6185",
    "sg:postcode":"17322",
    "sg:province":"PA",
    "wof:name":"Thomas C Wasko",
    "wof:placetype":"venue"
},
  "geometry": {"coordinates":[-76.443653,39.905058],"type":"Point"}
}