{
  "type": "Feature",
  "properties": {
    "iso:country":"US",
    "sg:address":"16 S Main St",
    "sg:city":"New Hope",
    "sg:classifiers":[
        {
            "category":"Shopping",
            "type":"Retail Goods"
        }
    ],
    "sg:phone":"+1   ",
    "sg:postcode":"18938",
    "sg:province":"PA",
    "sg:tags":[
        "merchandise"
    ],
    "wof:name":"Youth Stream Transgraphic",
    "wof:placetype":"venue"
},
  "geometry": {"coordinates":[-74.951256,40.363848],"type":"Point"}
}