{
  "type": "Feature",
  "properties": {
    "iso:country":"US",
    "sg:address":"3251 Butler St",
    "sg:city":"Harrisburg",
    "sg:classifiers":[
        {
            "category":"Health Services",
            "subcategory":"Health Practitioner",
            "type":"Services"
        }
    ],
    "sg:phone":"+1 717 233 5900",
    "sg:postcode":"17103",
    "sg:province":"PA",
    "sg:tags":[
        "therapist",
        "physical"
    ],
    "wof:name":"Lehigh Valley Physical Thrpy",
    "wof:placetype":"venue"
},
  "geometry": {"coordinates":[-76.84062,40.275496],"type":"Point"}
}