{
  "type": "Feature",
  "properties": {
    "iso:country":"US",
    "sg:address":"11 E Penn St",
    "sg:city":"Uniontown",
    "sg:classifiers":[
        {
            "category":"Education",
            "subcategory":"School",
            "type":"Public Place"
        }
    ],
    "sg:phone":"+1 724 437 9525",
    "sg:postcode":"15401",
    "sg:province":"PA",
    "sg:website":"www.iu1.k12.pa.us",
    "wof:name":"Fayette Intermediate Unit I",
    "wof:placetype":"venue"
},
  "geometry": {"coordinates":[-79.72414999999999,39.9023],"type":"Point"}
}