{
  "type": "Feature",
  "properties": {
    "addr:full":"228 High St Hanover PA 17331",
    "addr:housenumber":"228",
    "addr:postcode":"17331",
    "addr:street":"High St",
    "iso:country":"US",
    "sg:address":"228 High St",
    "sg:city":"Hanover",
    "sg:classifiers":[
        {
            "category":"Home & Garden",
            "subcategory":"Hardware",
            "type":"Retail Goods"
        }
    ],
    "sg:phone":"+1 717 637 6310",
    "sg:postcode":"17331",
    "sg:province":"PA",
    "wof:name":"J C Tanger Hardware",
    "wof:placetype":"venue"
},
  "geometry": {"coordinates":[-76.988446,39.800893],"type":"Point"}
}