{
  "type": "Feature",
  "properties": {
    "addr:full":"229 Pilgrim Ln Drexel Hill PA 19026",
    "addr:housenumber":"229",
    "addr:postcode":"19026",
    "addr:street":"Pilgrim Ln",
    "iso:country":"US",
    "sg:address":"229 Pilgrim Ln",
    "sg:city":"Drexel Hill",
    "sg:classifiers":[
        {
            "category":"Building & Trades",
            "subcategory":"Construction",
            "type":"Services"
        }
    ],
    "sg:phone":"+1   ",
    "sg:postcode":"19026",
    "sg:province":"PA",
    "sg:tags":[
        "floor",
        "laying",
        "contractor"
    ],
    "wof:name":"Artistic Hardwood Floors",
    "wof:placetype":"venue"
},
  "geometry": {"coordinates":[-75.325935,39.95374],"type":"Point"}
}