{
  "type": "Feature",
  "properties": {
    "iso:country":"US",
    "sg:address":"2414 Lytle Rd Ste 201",
    "sg:city":"Bethel Park",
    "sg:classifiers":[
        {
            "category":"Building & Trades",
            "subcategory":"Construction",
            "type":"Services"
        }
    ],
    "sg:phone":"+1 412 854 9000",
    "sg:postcode":"15102",
    "sg:province":"PA",
    "sg:tags":[
        "contractor"
    ],
    "wof:name":"Lyn Development Corp",
    "wof:placetype":"venue"
},
  "geometry": {"coordinates":[-80.024548,40.33373],"type":"Point"}
}