{
  "type": "Feature",
  "properties": {
    "iso:country":"US",
    "sg:address":"2001 N Front St",
    "sg:city":"Harrisburg",
    "sg:classifiers":[
        {
            "category":"Banks & Credit Unions",
            "subcategory":"Investment Brokerage",
            "type":"Services"
        }
    ],
    "sg:phone":"+1 717 652 6630",
    "sg:postcode":"17102",
    "sg:province":"PA",
    "sg:tags":[
        "consultant",
        "financing"
    ],
    "wof:name":"Johnson Associates",
    "wof:placetype":"venue"
},
  "geometry": {"coordinates":[-76.898932,40.276614],"type":"Point"}
}