{
  "type": "Feature",
  "properties": {
    "iso:country":"US",
    "sg:address":"264 New Castle Rd",
    "sg:city":"Butler",
    "sg:classifiers":[
        {
            "category":"Restaurant",
            "type":"Food & Drink"
        }
    ],
    "sg:menulink":"http://www.allmenus.com/pa/butler/205967-mcdonalds/menu/",
    "sg:phone":"+1 724 283 3257",
    "sg:postcode":"16001",
    "sg:province":"PA",
    "sg:tags":[
        "burger",
        "american"
    ],
    "wof:name":"McDonald's",
    "wof:placetype":"venue"
},
  "geometry": {"coordinates":[-79.93732,40.87212],"type":"Point"}
}