{
  "type": "Feature",
  "properties": {
    "iso:country":"US",
    "sg:address":"15 S Prince St",
    "sg:city":"Millersville",
    "sg:classifiers":[
        {
            "category":"Restaurant",
            "type":"Food & Drink"
        }
    ],
    "sg:phone":"+1 717 872 8300",
    "sg:postcode":"17551",
    "sg:province":"PA",
    "wof:name":"Jack's Family Tavern & Rstrnt",
    "wof:placetype":"venue"
},
  "geometry": {"coordinates":[-76.35795299999999,39.99495],"type":"Point"}
}