{
  "type": "Feature",
  "properties": {
    "iso:country":"US",
    "sg:address":"620 Strathmore Ave",
    "sg:city":"Erie",
    "sg:classifiers":[
        {
            "category":"Professional",
            "subcategory":"Accounting & Tax Preparation",
            "type":"Services"
        }
    ],
    "sg:phone":"+1 814 838 4451",
    "sg:postcode":"16505",
    "sg:province":"PA",
    "sg:tags":[
        "bookkeeping"
    ],
    "wof:name":"Nelson Assoc Nelson Studi",
    "wof:placetype":"venue"
},
  "geometry": {"coordinates":[-80.169425,42.097345],"type":"Point"}
}