{
  "type": "Feature",
  "properties": {
    "iso:country":"US",
    "sg:address":"121 W Girard Ave",
    "sg:city":"Philadelphia",
    "sg:classifiers":[
        {
            "category":"Shopping",
            "type":"Retail Goods"
        }
    ],
    "sg:phone":"+1 215 789 4691",
    "sg:postcode":"19123",
    "sg:province":"PA",
    "sg:tags":[
        "equipment",
        "hospital",
        "rental",
        "medical",
        "supply"
    ],
    "sg:website":"http://www.advancemedicalequipment.net",
    "wof:name":"Advance Medical Equipment",
    "wof:placetype":"venue"
},
  "geometry": {"coordinates":[-75.136945,39.969021],"type":"Point"}
}