{
  "type": "Feature",
  "properties": {
    "iso:country":"US",
    "sg:address":"125 S Patterson St",
    "sg:city":"State College",
    "sg:classifiers":[
        {
            "category":"Shopping",
            "subcategory":"Gifts & Souvenirs",
            "type":"Retail Goods"
        }
    ],
    "sg:phone":"+1   ",
    "sg:postcode":"16801",
    "sg:province":"PA",
    "wof:name":"Aunti G Companion Animal Svcs",
    "wof:placetype":"venue"
},
  "geometry": {"coordinates":[-77.86918799999999,40.787647],"type":"Point"}
}