{
  "type": "Feature",
  "properties": {
    "iso:country":"US",
    "sg:address":"1310 Arch St",
    "sg:city":"Pittsburgh",
    "sg:classifiers":[
        {
            "category":"Real Estate",
            "subcategory":"Real Estate Operator",
            "type":"Services"
        }
    ],
    "sg:phone":"+1 412 231 4121",
    "sg:postcode":"15212",
    "sg:province":"PA",
    "sg:tags":[
        "apartment"
    ],
    "wof:name":"Arch Court Apartments",
    "wof:placetype":"venue"
},
  "geometry": {"coordinates":[-80.00899699999999,40.456886],"type":"Point"}
}