{
  "type": "Feature",
  "properties": {
    "addr:full":"44 E Schoonmaker Ave Monessen PA 15062",
    "addr:housenumber":"44",
    "addr:postcode":"15062",
    "addr:street":"E Schoonmaker Ave",
    "iso:country":"US",
    "sg:address":"44 E Schoonmaker Ave",
    "sg:city":"Monessen",
    "sg:classifiers":[
        {
            "category":"Restaurant",
            "type":"Food & Drink"
        }
    ],
    "sg:phone":"+1 724 684 7711",
    "sg:postcode":"15062",
    "sg:province":"PA",
    "wof:name":"Felicia's Restaurant & Lounge",
    "wof:placetype":"venue"
},
  "geometry": {"coordinates":[-79.877185,40.159436],"type":"Point"}
}