{
  "type": "Feature",
  "properties": {
    "addr:full":"334 Helen St Mc Kees Rocks PA 15136",
    "addr:housenumber":"334",
    "addr:postcode":"15136",
    "addr:street":"Helen St Mc Kees Rocks",
    "iso:country":"US",
    "sg:address":"334 Helen St",
    "sg:city":"Mc Kees Rocks",
    "sg:classifiers":[
        {
            "category":"Professional",
            "type":"Services"
        }
    ],
    "sg:phone":"+1 412 771 7126",
    "sg:postcode":"15136",
    "sg:province":"PA",
    "sg:tags":[
        "establishment"
    ],
    "wof:name":"Vith D",
    "wof:placetype":"venue"
},
  "geometry": {"coordinates":[-80.058188,40.475204],"type":"Point"}
}