{
  "type": "Feature",
  "properties": {
    "iso:country":"US",
    "sg:address":"247 Wildwood Rd",
    "sg:city":"Midland",
    "sg:classifiers":[
        {
            "category":"Farming",
            "subcategory":"Livestock Farm",
            "type":"Manufacturing & Wholesale Goods"
        }
    ],
    "sg:phone":"+1   ",
    "sg:postcode":"15059",
    "sg:province":"PA",
    "sg:tags":[
        "beef",
        "feedlot",
        "cattle"
    ],
    "wof:name":"Frank Justice Farm",
    "wof:placetype":"venue"
},
  "geometry": {"coordinates":[-80.497187,40.715303],"type":"Point"}
}