{
  "type": "Feature",
  "properties": {
    "iso:country":"US",
    "sg:address":"1747 W Broad St",
    "sg:city":"Bethlehem",
    "sg:classifiers":[
        {
            "category":"Building & Trades",
            "subcategory":"Construction",
            "type":"Services"
        }
    ],
    "sg:phone":"+1 610 868 3116",
    "sg:postcode":"18018",
    "sg:province":"PA",
    "sg:tags":[
        "contractor"
    ],
    "wof:name":"West & Son Contractors",
    "wof:placetype":"venue"
},
  "geometry": {"coordinates":[-75.407402,40.6227],"type":"Point"}
}