{
  "type": "Feature",
  "properties": {
    "iso:country":"US",
    "sg:address":"436 Spruce St",
    "sg:city":"Scranton",
    "sg:classifiers":[
        {
            "category":"Real Estate",
            "subcategory":"Real Estate Operator",
            "type":"Services"
        }
    ],
    "sg:phone":"+1   ",
    "sg:postcode":"18503",
    "sg:province":"PA",
    "sg:tags":[
        "building",
        "nonresidential"
    ],
    "wof:name":"Brooks Building Assocs",
    "wof:placetype":"venue"
},
  "geometry": {"coordinates":[-75.663759,41.407913],"type":"Point"}
}