{
  "type": "Feature",
  "properties": {
    "addr:full":"418 W Washington St Corry PA 16407",
    "addr:housenumber":"418",
    "addr:postcode":"16407",
    "addr:street":"W Washington St",
    "iso:country":"US",
    "sg:address":"418 W Washington St",
    "sg:city":"Corry",
    "sg:classifiers":[
        {
            "category":"Manufacturing",
            "subcategory":"Printing",
            "type":"Manufacturing & Wholesale Goods"
        }
    ],
    "sg:phone":"+1 814 664 7816",
    "sg:postcode":"16407",
    "sg:province":"PA",
    "sg:tags":[
        "screen"
    ],
    "wof:name":"Kimmy Kreations Screen Print",
    "wof:placetype":"venue"
},
  "geometry": {"coordinates":[-79.649198,41.921228],"type":"Point"}
}