{
  "type": "Feature",
  "properties": {
    "addr:full":"701 W Butler St Philadelphia PA 19140",
    "addr:housenumber":"701",
    "addr:postcode":"19140",
    "addr:street":"W Butler St",
    "iso:country":"US",
    "sg:address":"701 W Butler St",
    "sg:city":"Philadelphia",
    "sg:classifiers":[
        {
            "category":"Building & Trades",
            "subcategory":"Locksmith",
            "type":"Services"
        }
    ],
    "sg:phone":"+1 267 773 5943",
    "sg:postcode":"19140",
    "sg:province":"PA",
    "sg:tags":[
        "key"
    ],
    "wof:name":"Always Available Locksmith",
    "wof:placetype":"venue"
},
  "geometry": {"coordinates":[-75.14010399999999,40.009566],"type":"Point"}
}