{
  "type": "Feature",
  "properties": {
    "addr:full":"223 S Main St Zelienople PA 16063",
    "addr:housenumber":"223",
    "addr:postcode":"16063",
    "addr:street":"S Main St",
    "iso:country":"US",
    "sg:address":"223 S Main St",
    "sg:city":"Zelienople",
    "sg:classifiers":[
        {
            "category":"Real Estate",
            "subcategory":"Real Estate Agent",
            "type":"Services"
        }
    ],
    "sg:phone":"+1 724 452 1400",
    "sg:postcode":"16063",
    "sg:province":"PA",
    "wof:name":"Northwood Realty Svc",
    "wof:placetype":"venue"
},
  "geometry": {"coordinates":[-80.136775,40.793951],"type":"Point"}
}