{
  "type": "Feature",
  "properties": {
    "addr:full":"1311 E. Carson Street South Side Pittsburgh PA 15203",
    "addr:housenumber":"1311",
    "addr:postcode":"15203",
    "addr:street":"E. Carson Street",
    "iso:country":"US",
    "sg:address":"1311 E. Carson Street South Side",
    "sg:city":"Pittsburgh",
    "sg:classifiers":[
        {
            "category":"Bars & Pubs",
            "subcategory":"Sports Bar",
            "type":"Food & Drink"
        }
    ],
    "sg:phone":"+1 412 488 1311",
    "sg:postcode":"15203",
    "sg:province":"PA",
    "sg:website":"1311Carson.com",
    "wof:name":"Thirteen Eleven",
    "wof:placetype":"venue"
},
  "geometry": {"coordinates":[-79.984827,40.428994],"type":"Point"}
}