{
  "type": "Feature",
  "properties": {
    "addr:full":"1160 Main St Dickson City PA 18519",
    "addr:housenumber":"1160",
    "addr:postcode":"18519",
    "addr:street":"Main St",
    "iso:country":"US",
    "sg:address":"1160 Main St",
    "sg:city":"Dickson City",
    "sg:classifiers":[
        {
            "category":"Home & Garden",
            "subcategory":"Furniture",
            "type":"Retail Goods"
        }
    ],
    "sg:phone":"+1   ",
    "sg:postcode":"18519",
    "sg:province":"PA",
    "sg:tags":[
        "household",
        "wood",
        "mfg"
    ],
    "wof:name":"Nevermark Inc",
    "wof:placetype":"venue"
},
  "geometry": {"coordinates":[-75.61654,41.466091],"type":"Point"}
}