{
  "type": "Feature",
  "properties": {
    "iso:country":"US",
    "sg:address":"1400 Blackhorse Hill Rd",
    "sg:city":"Coatesville",
    "sg:classifiers":[
        {
            "category":"Banks & Credit Unions",
            "subcategory":"Bank",
            "type":"Services"
        }
    ],
    "sg:phone":"+1 610 384 3315",
    "sg:postcode":"19320",
    "sg:province":"PA",
    "sg:tags":[
        "federal"
    ],
    "wof:name":"Citadel Federal Credit Union",
    "wof:placetype":"venue"
},
  "geometry": {"coordinates":[-75.799425,39.999275],"type":"Point"}
}