{
  "type": "Feature",
  "properties": {
    "iso:country":"US",
    "sg:address":"1400 N Washington Ave",
    "sg:city":"Scranton",
    "sg:classifiers":[
        {
            "category":"Shopping",
            "subcategory":"Used Merchandise",
            "type":"Retail Goods"
        }
    ],
    "sg:phone":"+1   ",
    "sg:postcode":"18509",
    "sg:province":"PA",
    "wof:name":"Collectables By Christina",
    "wof:placetype":"venue"
},
  "geometry": {"coordinates":[-75.646777,41.423438],"type":"Point"}
}