{
  "type": "Feature",
  "properties": {
    "iso:country":"US",
    "sg:address":"5 Marie Dr",
    "sg:city":"Lititz",
    "sg:classifiers":[
        {
            "category":"Manufacturing",
            "subcategory":"Tools & Machinery",
            "type":"Manufacturing & Wholesale Goods"
        }
    ],
    "sg:phone":"+1   ",
    "sg:postcode":"17543",
    "sg:province":"PA",
    "sg:tags":[
        "surgical",
        "mfg"
    ],
    "wof:name":"Joycine S Dougery",
    "wof:placetype":"venue"
},
  "geometry": {"coordinates":[-76.28173200000001,40.179222],"type":"Point"}
}