{
  "type": "Feature",
  "properties": {
    "iso:country":"US",
    "sg:address":"334 Reading Ave",
    "sg:city":"Reading",
    "sg:classifiers":[
        {
            "category":"Health Services",
            "subcategory":"Doctor",
            "type":"Services"
        }
    ],
    "sg:phone":"+1 610 777 6639",
    "sg:postcode":"19607",
    "sg:province":"PA",
    "sg:tags":[
        "dentist"
    ],
    "wof:name":"Connie Gaul Gallen DDS",
    "wof:placetype":"venue"
},
  "geometry": {"coordinates":[-75.963363,40.30863],"type":"Point"}
}