{
  "type": "Feature",
  "properties": {
    "iso:country":"US",
    "sg:address":"432 E Montana St",
    "sg:city":"Philadelphia",
    "sg:classifiers":[
        {
            "category":"Retail",
            "subcategory":"Repair Shop",
            "type":"Services"
        }
    ],
    "sg:phone":"+1   ",
    "sg:postcode":"19119",
    "sg:province":"PA",
    "sg:tags":[
        "residential",
        "cleaning"
    ],
    "wof:name":"Clean At Last",
    "wof:placetype":"venue"
},
  "geometry": {"coordinates":[-75.177385,40.056399],"type":"Point"}
}