{
  "type": "Feature",
  "properties": {
    "addr:full":"10065 Hillwood Dr Wattsburg PA 16442",
    "addr:housenumber":"10065",
    "addr:postcode":"16442",
    "addr:street":"Hillwood Dr",
    "iso:country":"US",
    "sg:address":"10065 Hillwood Dr",
    "sg:city":"Wattsburg",
    "sg:classifiers":[
        {
            "category":"Professional",
            "subcategory":"Business Services",
            "type":"Services"
        }
    ],
    "sg:phone":"+1   ",
    "sg:postcode":"16442",
    "sg:province":"PA",
    "wof:name":"Way-FM Media Group Inc",
    "wof:placetype":"venue"
},
  "geometry": {"coordinates":[-79.794105,42.007807],"type":"Point"}
}