{
  "type": "Feature",
  "properties": {
    "addr:full":"345 S Cedar Crest Blvd Allentown PA 18103",
    "addr:housenumber":"345",
    "addr:postcode":"18103",
    "addr:street":"S Cedar Crest Blvd",
    "iso:country":"US",
    "sg:address":"345 S Cedar Crest Blvd",
    "sg:city":"Allentown",
    "sg:classifiers":[
        {
            "category":"Bakery",
            "type":"Food & Drink"
        },
        {
            "category":"Bagels",
            "type":"Food & Drink"
        }
    ],
    "sg:menulink":"http://www.allmenus.com/pa/south-whitehall/219064-chesapeake-bagel-bakery/menu/",
    "sg:phone":"+1 610 439 7900",
    "sg:postcode":"18103",
    "sg:province":"PA",
    "sg:tags":[
        "american",
        "pastry"
    ],
    "wof:name":"Chesapeake Bagel Bakery",
    "wof:placetype":"venue"
},
  "geometry": {"coordinates":[-75.52274,40.583868],"type":"Point"}
}