{
  "type": "Feature",
  "properties": {
    "addr:full":"2615 E Street Rd Bensalem PA 19020",
    "addr:housenumber":"2615",
    "addr:postcode":"19020",
    "addr:street":"E Street Rd",
    "iso:country":"US",
    "sg:address":"2615 E Street Rd",
    "sg:city":"Bensalem",
    "sg:classifiers":[
        {
            "category":"Personal",
            "subcategory":"Beauty Salon",
            "type":"Services"
        }
    ],
    "sg:phone":"+1 215 638 3996",
    "sg:postcode":"19020",
    "sg:province":"PA",
    "sg:tags":[
        "shop"
    ],
    "wof:name":"Style Studio",
    "wof:placetype":"venue"
},
  "geometry": {"coordinates":[-74.95213800000001,40.107985],"type":"Point"}
}