{
  "type": "Feature",
  "properties": {
    "addr:full":"330 W 6th St Hazleton PA 18201",
    "addr:housenumber":"330",
    "addr:postcode":"18201",
    "addr:street":"W 6Th St",
    "iso:country":"US",
    "sg:address":"330 W 6th St",
    "sg:city":"Hazleton",
    "sg:classifiers":[
        {
            "category":"Manufacturing",
            "subcategory":"Wood Products",
            "type":"Manufacturing & Wholesale Goods"
        }
    ],
    "sg:phone":"+1 570 454 6436",
    "sg:postcode":"18201",
    "sg:province":"PA",
    "wof:name":"Rosco Products",
    "wof:placetype":"venue"
},
  "geometry": {"coordinates":[-75.978565,40.962696],"type":"Point"}
}