{
  "type": "Feature",
  "properties": {
    "iso:country":"US",
    "sg:address":"3540 N 5th Street Hwy",
    "sg:city":"Reading",
    "sg:classifiers":[
        {
            "category":"Autos & Motor Vehicles",
            "subcategory":"Auto Supplies",
            "type":"Retail Goods"
        }
    ],
    "sg:phone":"+1 610 939 9600",
    "sg:postcode":"19605",
    "sg:province":"PA",
    "sg:tags":[
        "automobile",
        "parts"
    ],
    "wof:name":"Autozone",
    "wof:placetype":"venue"
},
  "geometry": {"coordinates":[-75.92755200000001,40.38887],"type":"Point"}
}