{
  "type": "Feature",
  "properties": {
    "iso:country":"US",
    "sg:address":"120 Church Ln",
    "sg:city":"Upper Darby",
    "sg:classifiers":[
        {
            "category":"Retail",
            "subcategory":"Auto Repair",
            "type":"Services"
        }
    ],
    "sg:phone":"+1 610 623 3980",
    "sg:postcode":"19082",
    "sg:province":"PA",
    "wof:name":"T & J Auto",
    "wof:placetype":"venue"
},
  "geometry": {"coordinates":[-75.256236,39.940672],"type":"Point"}
}