{
  "type": "Feature",
  "properties": {
    "addr:full":"246 Coral Dr Pittsburgh PA 15241",
    "addr:housenumber":"246",
    "addr:postcode":"15241",
    "addr:street":"Coral Dr",
    "iso:country":"US",
    "sg:address":"246 Coral Dr",
    "sg:city":"Pittsburgh",
    "sg:classifiers":[
        {
            "category":"Building & Trades",
            "subcategory":"Construction",
            "type":"Services"
        }
    ],
    "sg:phone":"+1   ",
    "sg:postcode":"15241",
    "sg:province":"PA",
    "sg:tags":[
        "hanging",
        "contractor"
    ],
    "wof:name":"Wall Finishes",
    "wof:placetype":"venue"
},
  "geometry": {"coordinates":[-80.066934,40.321088],"type":"Point"}
}