{
  "type": "Feature",
  "properties": {
    "addr:full":"509 Main St Red Hill PA 18076",
    "addr:housenumber":"509",
    "addr:postcode":"18076",
    "addr:street":"Main St",
    "iso:country":"US",
    "sg:address":"509 Main St",
    "sg:city":"Red Hill",
    "sg:classifiers":[
        {
            "category":"Shopping",
            "subcategory":"Used Merchandise",
            "type":"Retail Goods"
        }
    ],
    "sg:phone":"+1 215 679 7793",
    "sg:postcode":"18076",
    "sg:province":"PA",
    "sg:tags":[
        "shop",
        "consignment"
    ],
    "wof:name":"Children's Treasures",
    "wof:placetype":"venue"
},
  "geometry": {"coordinates":[-75.483203,40.377392],"type":"Point"}
}