{
  "type": "Feature",
  "properties": {
    "addr:full":"8724 New Falls Rd Levittown PA 19054",
    "addr:housenumber":"8724",
    "addr:postcode":"19054",
    "addr:street":"New Falls Rd Levittown",
    "iso:country":"US",
    "sg:address":"8724 New Falls Rd",
    "sg:city":"Levittown",
    "sg:classifiers":[
        {
            "category":"Shopping",
            "subcategory":"Used Merchandise",
            "type":"Retail Goods"
        }
    ],
    "sg:phone":"+1 215 547 2547",
    "sg:postcode":"19054",
    "sg:province":"PA",
    "sg:tags":[
        "shop",
        "thrift"
    ],
    "wof:name":"Salvation Army Thrift Store",
    "wof:placetype":"venue"
},
  "geometry": {"coordinates":[-74.83245100000001,40.172875],"type":"Point"}
}