{
  "type": "Feature",
  "properties": {
    "addr:full":"1566 River Rd Mt Bethel PA 18343",
    "addr:housenumber":"1566",
    "addr:postcode":"18343",
    "addr:street":"River Rd",
    "iso:country":"US",
    "sg:address":"1566 River Rd",
    "sg:city":"Mt Bethel",
    "sg:classifiers":[
        {
            "category":"Shopping",
            "subcategory":"Florist",
            "type":"Retail Goods"
        }
    ],
    "sg:phone":"+1 570 897 0135",
    "sg:postcode":"18343",
    "sg:province":"PA",
    "wof:name":"Denise's Design",
    "wof:placetype":"venue"
},
  "geometry": {"coordinates":[-75.07166700000001,40.852553],"type":"Point"}
}