{
  "type": "Feature",
  "properties": {
    "addr:full":"4317 S Creek Rd Chadds Ford PA 19317",
    "addr:housenumber":"4317",
    "addr:postcode":"19317",
    "addr:street":"S Creek Rd",
    "iso:country":"US",
    "sg:address":"4317 S Creek Rd",
    "sg:city":"Chadds Ford",
    "sg:classifiers":[
        {
            "category":"Wholesale",
            "subcategory":"Fruits & Vegetables",
            "type":"Manufacturing & Wholesale Goods"
        }
    ],
    "sg:phone":"+1 610 388 0656",
    "sg:postcode":"19317",
    "sg:province":"PA",
    "sg:tags":[
        "veggie"
    ],
    "wof:name":"Siw Vegetables",
    "wof:placetype":"venue"
},
  "geometry": {"coordinates":[-75.596613,39.845959],"type":"Point"}
}