{
  "type": "Feature",
  "properties": {
    "addr:full":"839 Biglerville Rd Gettysburg PA 17325",
    "addr:housenumber":"839",
    "addr:postcode":"17325",
    "addr:street":"Biglerville Rd",
    "iso:country":"US",
    "sg:address":"839 Biglerville Rd",
    "sg:city":"Gettysburg",
    "sg:classifiers":[
        {
            "category":"Shopping",
            "subcategory":"Clothing, Apparel, & Fashions",
            "type":"Retail Goods"
        }
    ],
    "sg:phone":"+1 717 338 9038",
    "sg:postcode":"17325",
    "sg:province":"PA",
    "wof:name":"El Sangarito Mexican Store",
    "wof:placetype":"venue"
},
  "geometry": {"coordinates":[-77.23203700000001,39.84877],"type":"Point"}
}