{
  "type": "Feature",
  "properties": {
    "iso:country":"US",
    "sg:address":"138 W Main St",
    "sg:city":"Ridgway",
    "sg:classifiers":[
        {
            "category":"Retail",
            "subcategory":"Auto Rental",
            "type":"Services"
        }
    ],
    "sg:phone":"+1   ",
    "sg:postcode":"15853",
    "sg:province":"PA",
    "sg:tags":[
        "truck"
    ],
    "wof:name":"U-Haul",
    "wof:placetype":"venue"
},
  "geometry": {"coordinates":[-78.739096,41.420916],"type":"Point"}
}