{
  "type": "Feature",
  "properties": {
    "addr:full":"1417 Limekiln Pike Dresher PA 19025",
    "addr:housenumber":"1417",
    "addr:postcode":"19025",
    "addr:street":"Limekiln Pike",
    "iso:country":"US",
    "sg:address":"1417 Limekiln Pike",
    "sg:city":"Dresher",
    "sg:classifiers":[
        {
            "category":"Professional",
            "type":"Services"
        }
    ],
    "sg:phone":"+1   ",
    "sg:postcode":"19025",
    "sg:province":"PA",
    "wof:name":"Innovative Data Concepts",
    "wof:placetype":"venue"
},
  "geometry": {"coordinates":[-75.176164,40.155486],"type":"Point"}
}