{
  "type": "Feature",
  "properties": {
    "iso:country":"US",
    "sg:address":"404 State Rte 313",
    "sg:city":"Dublin",
    "sg:classifiers":[
        {
            "category":"Health Services",
            "subcategory":"Doctor",
            "type":"Services"
        }
    ],
    "sg:phone":"+1   ",
    "sg:postcode":"18917",
    "sg:province":"PA",
    "wof:name":"Paul E Schnupp Jr DDS",
    "wof:placetype":"venue"
},
  "geometry": {"coordinates":[-75.193806,40.366019],"type":"Point"}
}