{
  "type": "Feature",
  "properties": {
    "iso:country":"US",
    "sg:address":"8 State St",
    "sg:city":"Everett",
    "sg:classifiers":[
        {
            "category":"Wholesale",
            "subcategory":"Machinery & Supplies",
            "type":"Manufacturing & Wholesale Goods"
        }
    ],
    "sg:phone":"+1 814 652 5733",
    "sg:postcode":"15537",
    "sg:province":"PA",
    "sg:tags":[
        "pump"
    ],
    "wof:name":"Gerald W Clark Well Drilling",
    "wof:placetype":"venue"
},
  "geometry": {"coordinates":[-78.36936300000001,40.009981],"type":"Point"}
}