{
  "type": "Feature",
  "properties": {
    "iso:country":"US",
    "sg:address":"70 Quarry Rd",
    "sg:city":"Downingtown",
    "sg:classifiers":[
        {
            "category":"Shopping",
            "subcategory":"Bicycles & Sporting Goods",
            "type":"Retail Goods"
        }
    ],
    "sg:phone":"+1   ",
    "sg:postcode":"19335",
    "sg:province":"PA",
    "wof:name":"Orvis Company Inc",
    "wof:placetype":"venue"
},
  "geometry": {"coordinates":[-75.675032,40.018257],"type":"Point"}
}