{
  "type": "Feature",
  "properties": {
    "iso:country":"US",
    "sg:address":"1115 Lindley Ave",
    "sg:city":"Philadelphia",
    "sg:classifiers":[
        {
            "category":"Wholesale",
            "subcategory":"Painting Supplies",
            "type":"Manufacturing & Wholesale Goods"
        },
        {
            "category":"Home & Garden",
            "subcategory":"Building Materials",
            "type":"Retail Goods"
        },
        {
            "category":"Building & Trades",
            "subcategory":"Construction",
            "type":"Services"
        }
    ],
    "sg:phone":"+1 215 329 1484",
    "sg:postcode":"19141",
    "sg:province":"PA",
    "sg:tags":[
        "paint",
        "wallpaper",
        "wallcoverings",
        "wallcoverings-installation"
    ],
    "wof:name":"J & J Painting & Maintenance",
    "wof:placetype":"venue"
},
  "geometry": {"coordinates":[-75.142014,40.030041],"type":"Point"}
}