{
  "type": "Feature",
  "properties": {
    "iso:country":"US",
    "sg:address":"778 Eastside Dr",
    "sg:city":"Landisville",
    "sg:classifiers":[
        {
            "category":"Building & Trades",
            "subcategory":"Construction",
            "type":"Services"
        }
    ],
    "sg:phone":"+1 717 898 9610",
    "sg:postcode":"17538",
    "sg:province":"PA",
    "sg:tags":[
        "concrete",
        "contractor"
    ],
    "wof:name":"Miller Robert J Concrete Contr",
    "wof:placetype":"venue"
},
  "geometry": {"coordinates":[-76.408877,40.076894],"type":"Point"}
}