{
  "type": "Feature",
  "properties": {
    "iso:country":"US",
    "sg:address":"333 Cottage Pl",
    "sg:city":"Lewistown",
    "sg:classifiers":[
        {
            "category":"Professional",
            "type":"Services"
        }
    ],
    "sg:phone":"+1   ",
    "sg:postcode":"17044",
    "sg:province":"PA",
    "wof:name":"Appalachian Conservancy",
    "wof:placetype":"venue"
},
  "geometry": {"coordinates":[-77.57423900000001,40.619934],"type":"Point"}
}