{
  "type": "Feature",
  "properties": {
    "iso:country":"US",
    "sg:address":"1132 Rose Glen Rd",
    "sg:city":"Gladwyne",
    "sg:classifiers":[
        {
            "category":"Professional",
            "subcategory":"Management & Consulting",
            "type":"Services"
        }
    ],
    "sg:phone":"+1 610 649 0843",
    "sg:postcode":"19035",
    "sg:province":"PA",
    "sg:tags":[
        "consultant",
        "business"
    ],
    "wof:name":"Three Degrees Enterprises",
    "wof:placetype":"venue"
},
  "geometry": {"coordinates":[-75.277726,40.040425],"type":"Point"}
}