{
  "type": "Feature",
  "properties": {
    "addr:full":"2087 Market St Auburn PA 17922",
    "addr:housenumber":"2087",
    "addr:postcode":"17922",
    "addr:street":"Market St",
    "iso:country":"US",
    "sg:address":"2087 Market St",
    "sg:city":"Auburn",
    "sg:classifiers":[
        {
            "category":"Shopping",
            "subcategory":"Tobacco",
            "type":"Retail Goods"
        }
    ],
    "sg:phone":"+1   ",
    "sg:postcode":"17922",
    "sg:province":"PA",
    "sg:tags":[
        "product"
    ],
    "wof:name":"Everything Tobacco",
    "wof:placetype":"venue"
},
  "geometry": {"coordinates":[-76.08509599999999,40.604889],"type":"Point"}
}