{
  "type": "Feature",
  "properties": {
    "iso:country":"US",
    "sg:address":"1387 Wilmington Pike",
    "sg:city":"West Chester",
    "sg:classifiers":[
        {
            "category":"Personal",
            "type":"Services"
        },
        {
            "category":"Retail",
            "subcategory":"Laundry & Dry Cleaning",
            "type":"Services"
        }
    ],
    "sg:phone":"+1 610 399 9190",
    "sg:postcode":"19382",
    "sg:province":"PA",
    "sg:tags":[
        "sewing",
        "alteration"
    ],
    "wof:name":"Dilworthtown Cleaners",
    "wof:placetype":"venue"
},
  "geometry": {"coordinates":[-75.564499,39.902302],"type":"Point"}
}