{
  "type": "Feature",
  "properties": {
    "addr:full":"44 Foxanna Dr Carlisle PA 17015",
    "addr:housenumber":"44",
    "addr:postcode":"17015",
    "addr:street":"Foxanna Dr",
    "iso:country":"US",
    "sg:address":"44 Foxanna Dr",
    "sg:city":"Carlisle",
    "sg:classifiers":[
        {
            "category":"Freight",
            "type":"Transportation"
        }
    ],
    "sg:phone":"+1   ",
    "sg:postcode":"17015",
    "sg:province":"PA",
    "sg:tags":[
        "operator",
        "local",
        "trucking"
    ],
    "wof:name":"Wenger Hauling",
    "wof:placetype":"venue"
},
  "geometry": {"coordinates":[-77.08330599999999,40.266666],"type":"Point"}
}