{
  "type": "Feature",
  "properties": {
    "addr:full":"3200 W 32nd St Erie PA 16506",
    "addr:housenumber":"3200",
    "addr:postcode":"16506",
    "addr:street":"W 32Nd St",
    "iso:country":"US",
    "sg:address":"3200 W 32nd St",
    "sg:city":"Erie",
    "sg:classifiers":[
        {
            "category":"Real Estate",
            "subcategory":"Surveying",
            "type":"Services"
        }
    ],
    "sg:phone":"+1 814 833 3900",
    "sg:postcode":"16506",
    "sg:province":"PA",
    "sg:tags":[
        "surveyor"
    ],
    "wof:name":"Charles L Weislogel Surveyors",
    "wof:placetype":"venue"
},
  "geometry": {"coordinates":[-80.14217600000001,42.08047],"type":"Point"}
}