{
  "type": "Feature",
  "properties": {
    "iso:country":"US",
    "sg:address":"101 Pleasantview Dr",
    "sg:city":"Midland",
    "sg:classifiers":[
        {
            "category":"Wholesale",
            "subcategory":"Office Equipment",
            "type":"Manufacturing & Wholesale Goods"
        },
        {
            "category":"Shopping",
            "type":"Retail Goods"
        }
    ],
    "sg:phone":"+1 724 643 1222",
    "sg:postcode":"15059",
    "sg:province":"PA",
    "sg:tags":[
        "machine",
        "duplicating",
        "merchandise",
        "copying"
    ],
    "wof:name":"Speerhas Business Machine Inc",
    "wof:placetype":"venue"
},
  "geometry": {"coordinates":[-80.473095,40.688797],"type":"Point"}
}