{
  "type": "Feature",
  "properties": {
    "iso:country":"US",
    "sg:address":"16 Park Ave",
    "sg:city":"Warren",
    "sg:classifiers":[
        {
            "category":"Health Services",
            "subcategory":"Doctor",
            "type":"Services"
        }
    ],
    "sg:phone":"+1   ",
    "sg:postcode":"16365",
    "sg:province":"PA",
    "sg:tags":[
        "medical"
    ],
    "wof:name":"Beta Glucan Express",
    "wof:placetype":"venue"
},
  "geometry": {"coordinates":[-79.123442,41.831301],"type":"Point"}
}