{
  "type": "Feature",
  "properties": {
    "addr:full":"149 N Broad St Ridgway PA 15853",
    "addr:housenumber":"149",
    "addr:postcode":"15853",
    "addr:street":"N Broad St",
    "iso:country":"US",
    "sg:address":"149 N Broad St",
    "sg:city":"Ridgway",
    "sg:classifiers":[
        {
            "category":"Home & Garden",
            "subcategory":"Hardware",
            "type":"Retail Goods"
        }
    ],
    "sg:phone":"+1 814 772 0361",
    "sg:postcode":"15853",
    "sg:province":"PA",
    "wof:name":"H & A Hardware",
    "wof:placetype":"venue"
},
  "geometry": {"coordinates":[-78.731291,41.424519],"type":"Point"}
}