{
  "type": "Feature",
  "properties": {
    "iso:country":"US",
    "sg:address":"1410 Baltimore Pike",
    "sg:city":"Chadds Ford",
    "sg:classifiers":[
        {
            "category":"Restaurant",
            "type":"Food & Drink"
        }
    ],
    "sg:phone":"+1 610 388 7061",
    "sg:postcode":"19317",
    "sg:province":"PA",
    "sg:tags":[
        "diner"
    ],
    "sg:website":"www.hanks-place.net",
    "wof:name":"Hank's Place",
    "wof:placetype":"venue"
},
  "geometry": {"coordinates":[-75.655726,39.868167],"type":"Point"}
}