{
  "type": "Feature",
  "properties": {
    "addr:full":"1056 Orchard Ave Greensburg PA 15601",
    "addr:housenumber":"1056",
    "addr:postcode":"15601",
    "addr:street":"Orchard Ave",
    "iso:country":"US",
    "sg:address":"1056 Orchard Ave",
    "sg:city":"Greensburg",
    "sg:classifiers":[
        {
            "category":"Professional",
            "subcategory":"Management & Consulting",
            "type":"Services"
        }
    ],
    "sg:phone":"+1 724 836 5267",
    "sg:postcode":"15601",
    "sg:province":"PA",
    "sg:tags":[
        "financial"
    ],
    "wof:name":"Summit Consulting",
    "wof:placetype":"venue"
},
  "geometry": {"coordinates":[-79.541675,40.288131],"type":"Point"}
}