{
  "type": "Feature",
  "properties": {
    "addr:full":"403 Hill St Peckville PA 18452",
    "addr:housenumber":"403",
    "addr:postcode":"18452",
    "addr:street":"Hill St",
    "iso:country":"US",
    "sg:address":"403 Hill St",
    "sg:city":"Peckville",
    "sg:classifiers":[
        {
            "category":"Real Estate",
            "subcategory":"Surveying",
            "type":"Services"
        }
    ],
    "sg:phone":"+1 570 489 7704",
    "sg:postcode":"18452",
    "sg:province":"PA",
    "sg:tags":[
        "surveyor"
    ],
    "wof:name":"Pro Line Surveying",
    "wof:placetype":"venue"
},
  "geometry": {"coordinates":[-75.569163,41.483555],"type":"Point"}
}