{
  "type": "Feature",
  "properties": {
    "addr:full":"735 N Warren Ave Apollo PA 15613",
    "addr:housenumber":"735",
    "addr:postcode":"15613",
    "addr:street":"N Warren Ave",
    "iso:country":"US",
    "sg:address":"735 N Warren Ave",
    "sg:city":"Apollo",
    "sg:classifiers":[
        {
            "category":"Building & Trades",
            "subcategory":"Construction",
            "type":"Services"
        }
    ],
    "sg:phone":"+1 724 478 3501",
    "sg:postcode":"15613",
    "sg:province":"PA",
    "sg:tags":[
        "concrete",
        "contractor"
    ],
    "wof:name":"Stefaniak Floors & Constr",
    "wof:placetype":"venue"
},
  "geometry": {"coordinates":[-79.566248,40.587077],"type":"Point"}
}