{
  "type": "Feature",
  "properties": {
    "iso:country":"US",
    "sg:address":"96 State Rte 611",
    "sg:city":"Swiftwater",
    "sg:classifiers":[
        {
            "category":"Banks & Credit Unions",
            "subcategory":"Bank",
            "type":"Services"
        }
    ],
    "sg:phone":"+1 570 895 2471",
    "sg:postcode":"18327",
    "sg:province":"PA",
    "sg:tags":[
        "loan",
        "real estate"
    ],
    "wof:name":"First West Mortgage Bankers",
    "wof:placetype":"venue"
},
  "geometry": {"coordinates":[-75.14451699999999,40.985022],"type":"Point"}
}