{
  "type": "Feature",
  "properties": {
    "iso:country":"US",
    "sg:address":"1941 S 20th St",
    "sg:city":"Philadelphia",
    "sg:classifiers":[
        {
            "category":"Social Services",
            "type":"Services"
        },
        {
            "category":"Banks & Credit Unions",
            "subcategory":"Atm",
            "type":"Services"
        }
    ],
    "sg:phone":"+1 215 755 0295",
    "sg:postcode":"19145",
    "sg:province":"PA",
    "sg:tags":[
        "program",
        "services-information",
        "referral",
        "location"
    ],
    "wof:name":"J M Systems Inc",
    "wof:placetype":"venue"
},
  "geometry": {"coordinates":[-75.178883,39.927189],"type":"Point"}
}