{
  "type": "Feature",
  "properties": {
    "iso:country":"US",
    "sg:address":"1550 Market St",
    "sg:city":"Philadelphia",
    "sg:classifiers":[
        {
            "category":"Banks & Credit Unions",
            "subcategory":"Financial Services",
            "type":"Services"
        }
    ],
    "sg:phone":"+1 267 207 2738",
    "sg:postcode":"19102",
    "sg:province":"PA",
    "sg:tags":[
        "broker",
        "mortgage"
    ],
    "wof:name":"Mid Atlantic Mortgage Specialists",
    "wof:placetype":"venue"
},
  "geometry": {"coordinates":[-75.166093,39.952571],"type":"Point"}
}