{
  "type": "Feature",
  "properties": {
    "iso:country":"US",
    "sg:address":"1909 Babcock Blvd",
    "sg:city":"Pittsburgh",
    "sg:classifiers":[
        {
            "category":"Personal",
            "type":"Services"
        },
        {
            "category":"Retail",
            "subcategory":"Storage",
            "type":"Services"
        }
    ],
    "sg:phone":"+1 412 795 5353",
    "sg:postcode":"15209",
    "sg:province":"PA",
    "sg:tags":[
        "moving-self",
        "full",
        "self",
        "recreational",
        "commercial",
        "campers-storage",
        "vehicle",
        "mover",
        "household"
    ],
    "sg:website":"http://www.atlasselfstorage.net",
    "wof:name":"Atlas Self Storage Centers",
    "wof:placetype":"venue"
},
  "geometry": {"coordinates":[-79.988058,40.504066],"type":"Point"}
}