{
  "type": "Feature",
  "properties": {
    "iso:country":"US",
    "sg:address":"435 Marsh Rd",
    "sg:city":"Elverson",
    "sg:classifiers":[
        {
            "category":"Building & Trades",
            "subcategory":"Plumbing",
            "type":"Services"
        }
    ],
    "sg:phone":"+1   ",
    "sg:postcode":"19520",
    "sg:province":"PA",
    "sg:tags":[
        "closed",
        "contractor"
    ],
    "wof:name":"Stephen Christianse",
    "wof:placetype":"venue"
},
  "geometry": {"coordinates":[-75.780896,40.136509],"type":"Point"}
}