{
  "type": "Feature",
  "properties": {
    "iso:country":"US",
    "sg:address":"11279 Perry Hwy Ste 507",
    "sg:city":"Wexford",
    "sg:classifiers":[
        {
            "category":"Insurance",
            "subcategory":"Hazard Insurance",
            "type":"Services"
        }
    ],
    "sg:phone":"+1 724 933 7320",
    "sg:postcode":"15090",
    "sg:province":"PA",
    "sg:tags":[
        "commercial",
        "business"
    ],
    "wof:name":"Insurance Solutions Group, Inc.",
    "wof:placetype":"venue"
},
  "geometry": {"coordinates":[-80.054283,40.621811],"type":"Point"}
}