{
  "type": "Feature",
  "properties": {
    "addr:full":"100 E Swedesford Rd Exton PA 19341",
    "addr:housenumber":"100",
    "addr:postcode":"19341",
    "addr:street":"E Swedesford Rd",
    "iso:country":"US",
    "sg:address":"100 E Swedesford Rd",
    "sg:city":"Exton",
    "sg:classifiers":[
        {
            "category":"Restaurant",
            "type":"Food & Drink"
        }
    ],
    "sg:phone":"+1   ",
    "sg:postcode":"19341",
    "sg:province":"PA",
    "sg:tags":[
        "eating"
    ],
    "wof:name":"McDonalds",
    "wof:placetype":"venue"
},
  "geometry": {"coordinates":[-75.629527,40.033321],"type":"Point"}
}