{
  "type": "Feature",
  "properties": {
    "addr:full":"1222 Fox Den Rd Chambersburg PA 17202",
    "addr:housenumber":"1222",
    "addr:postcode":"17202",
    "addr:street":"Fox Den Rd",
    "iso:country":"US",
    "sg:address":"1222 Fox Den Rd",
    "sg:city":"Chambersburg",
    "sg:classifiers":[
        {
            "category":"Freight",
            "type":"Transportation"
        }
    ],
    "sg:phone":"+1   ",
    "sg:postcode":"17202",
    "sg:province":"PA",
    "sg:tags":[
        "operator",
        "local",
        "trucking"
    ],
    "wof:name":"Knouse Trucking Inc",
    "wof:placetype":"venue"
},
  "geometry": {"coordinates":[-80.19882200000001,40.18358],"type":"Point"}
}