{
  "type": "Feature",
  "properties": {
    "iso:country":"US",
    "sg:address":"299 Sugarloaf Heights Rd",
    "sg:city":"Drums",
    "sg:classifiers":[
        {
            "category":"Retail",
            "subcategory":"Repair Shop",
            "type":"Services"
        }
    ],
    "sg:phone":"+1 570 708 2935",
    "sg:postcode":"18222",
    "sg:province":"PA",
    "sg:tags":[
        "lock",
        "locksmith"
    ],
    "wof:name":"Beck's Lock & Key",
    "wof:placetype":"venue"
},
  "geometry": {"coordinates":[-76.03954899999999,41.042581],"type":"Point"}
}