{
  "type": "Feature",
  "properties": {
    "iso:country":"US",
    "sg:address":"316 S Market St",
    "sg:city":"Millersburg",
    "sg:classifiers":[
        {
            "category":"Autos & Motor Vehicles",
            "subcategory":"Automobile Sales",
            "type":"Retail Goods"
        }
    ],
    "sg:phone":"+1 717 692 3096",
    "sg:postcode":"17061",
    "sg:province":"PA",
    "sg:tags":[
        "car",
        "dealer"
    ],
    "wof:name":"Steve Strawser Auto Sales",
    "wof:placetype":"venue"
},
  "geometry": {"coordinates":[-76.961743,40.534734],"type":"Point"}
}