{
  "type": "Feature",
  "properties": {
    "iso:country":"US",
    "sg:address":"401 Mill St",
    "sg:city":"Bristol",
    "sg:classifiers":[
        {
            "category":"Wholesale",
            "subcategory":"Apparel",
            "type":"Manufacturing & Wholesale Goods"
        }
    ],
    "sg:phone":"+1   ",
    "sg:postcode":"19007",
    "sg:province":"PA",
    "sg:tags":[
        "me",
        "used",
        "clothing",
        "furniture"
    ],
    "wof:name":"Finders Keepers",
    "wof:placetype":"venue"
},
  "geometry": {"coordinates":[-74.859897,40.096694],"type":"Point"}
}