{
  "type": "Feature",
  "properties": {
    "iso:country":"US",
    "sg:address":"1215 Meadow Ln",
    "sg:city":"Steelton",
    "sg:classifiers":[
        {
            "category":"Building & Trades",
            "subcategory":"Plumbing",
            "type":"Services"
        }
    ],
    "sg:phone":"+1 717 831 0341",
    "sg:postcode":"17113",
    "sg:province":"PA",
    "sg:tags":[
        "plumbing",
        "contractor"
    ],
    "wof:name":"Ace Plumbing & Heating",
    "wof:placetype":"venue"
},
  "geometry": {"coordinates":[-76.812787,40.242826],"type":"Point"}
}