{
  "type": "Feature",
  "properties": {
    "iso:country":"US",
    "sg:address":"803 McGovern Rd",
    "sg:city":"Houston",
    "sg:classifiers":[
        {
            "category":"Education",
            "subcategory":"School",
            "type":"Public Place"
        }
    ],
    "sg:phone":"+1 724 745 4700",
    "sg:postcode":"15342",
    "sg:province":"PA",
    "sg:tags":[
        "elementary"
    ],
    "wof:name":"Allison Park Elementary School",
    "wof:placetype":"venue"
},
  "geometry": {"coordinates":[-80.226196,40.2327],"type":"Point"}
}