{
  "type": "Feature",
  "properties": {
    "iso:country":"US",
    "sg:address":"3701 Market St",
    "sg:city":"Philadelphia",
    "sg:classifiers":[
        {
            "category":"Professional",
            "subcategory":"Research",
            "type":"Services"
        }
    ],
    "sg:phone":"+1   ",
    "sg:postcode":"19104",
    "sg:province":"PA",
    "sg:tags":[
        "development",
        "bio",
        "tech"
    ],
    "wof:name":"Biotech Studio LLC",
    "wof:placetype":"venue"
},
  "geometry": {"coordinates":[-75.19800600000001,39.956654],"type":"Point"}
}