{
  "type": "Feature",
  "properties": {
    "iso:country":"US",
    "sg:address":"764 Magaro Rd",
    "sg:city":"Enola",
    "sg:classifiers":[
        {
            "category":"Building & Trades",
            "subcategory":"Plumbing",
            "type":"Services"
        }
    ],
    "sg:phone":"+1   ",
    "sg:postcode":"17025",
    "sg:province":"PA",
    "sg:tags":[
        "contractor"
    ],
    "wof:name":"Stones Plumbing & Heating",
    "wof:placetype":"venue"
},
  "geometry": {"coordinates":[-76.959003,40.282154],"type":"Point"}
}