{
  "type": "Feature",
  "properties": {
    "iso:country":"US",
    "sg:address":"503 W Lancaster Ave # 210",
    "sg:city":"Wayne",
    "sg:classifiers":[
        {
            "category":"Home & Garden",
            "subcategory":"Furniture",
            "type":"Retail Goods"
        }
    ],
    "sg:phone":"+1 610 989 9665",
    "sg:postcode":"19087",
    "sg:province":"PA",
    "sg:tags":[
        "store"
    ],
    "wof:name":"Interiors",
    "wof:placetype":"venue"
},
  "geometry": {"coordinates":[-75.401993,40.044781],"type":"Point"}
}