{
  "type": "Feature",
  "properties": {
    "addr:full":"1569 Medical Dr Pottstown PA 19464",
    "addr:housenumber":"1569",
    "addr:postcode":"19464",
    "addr:street":"Medical Dr",
    "iso:country":"US",
    "sg:address":"1569 Medical Dr",
    "sg:city":"Pottstown",
    "sg:classifiers":[
        {
            "category":"Health Services",
            "subcategory":"Doctor",
            "type":"Services"
        }
    ],
    "sg:phone":"+1 610 323 8161",
    "sg:postcode":"19464",
    "sg:province":"PA",
    "sg:tags":[
        "physician",
        "surgeon",
        "medical"
    ],
    "wof:name":"Independence Orthopedics Ltd",
    "wof:placetype":"venue"
},
  "geometry": {"coordinates":[-75.613207,40.239389],"type":"Point"}
}