{
  "type": "Feature",
  "properties": {
    "iso:country":"US",
    "sg:address":"519 N Franklin St",
    "sg:city":"York",
    "sg:classifiers":[
        {
            "category":"Home & Garden",
            "subcategory":"Furniture",
            "type":"Retail Goods"
        }
    ],
    "sg:phone":"+1 717 848 2900",
    "sg:postcode":"17403",
    "sg:province":"PA",
    "wof:name":"Office Furniture Outlet",
    "wof:placetype":"venue"
},
  "geometry": {"coordinates":[-76.716336,39.972315],"type":"Point"}
}