{
  "type": "Feature",
  "properties": {
    "iso:country":"US",
    "sg:address":"606 Redwood Ct",
    "sg:city":"Cranberry Township",
    "sg:classifiers":[
        {
            "category":"Professional",
            "type":"Services"
        }
    ],
    "sg:phone":"+1   ",
    "sg:postcode":"16066",
    "sg:province":"PA",
    "wof:name":"Two Designing Women",
    "wof:placetype":"venue"
},
  "geometry": {"coordinates":[-80.079728,40.732523],"type":"Point"}
}