{
  "type": "Feature",
  "properties": {
    "iso:country":"US",
    "sg:address":"755 Barkeyville Rd",
    "sg:city":"Grove City",
    "sg:classifiers":[
        {
            "category":"Building & Trades",
            "subcategory":"Construction",
            "type":"Services"
        }
    ],
    "sg:phone":"+1 724 458 9599",
    "sg:postcode":"16127",
    "sg:province":"PA",
    "sg:tags":[
        "general",
        "contractor"
    ],
    "wof:name":"Kilian Construction",
    "wof:placetype":"venue"
},
  "geometry": {"coordinates":[-80.05632900000001,41.17091],"type":"Point"}
}