{
  "type": "Feature",
  "properties": {
    "iso:country":"US",
    "sg:address":"1710 Chelsea Ave",
    "sg:city":"Bethlehem",
    "sg:classifiers":[
        {
            "category":"Professional",
            "subcategory":"Advertising",
            "type":"Services"
        }
    ],
    "sg:phone":"+1   ",
    "sg:postcode":"18018",
    "sg:province":"PA",
    "sg:tags":[
        "website"
    ],
    "wof:name":"Lehigh Valley Events",
    "wof:placetype":"venue"
},
  "geometry": {"coordinates":[-75.376541,40.637209],"type":"Point"}
}