{
  "type": "Feature",
  "properties": {
    "iso:country":"US",
    "sg:address":"1510 Dekalb Pike",
    "sg:city":"Blue Bell",
    "sg:classifiers":[
        {
            "category":"Arena",
            "subcategory":"Sports Club",
            "type":"Entertainment"
        }
    ],
    "sg:phone":"+1 610 277 7771",
    "sg:postcode":"19422",
    "sg:province":"PA",
    "sg:tags":[
        "martial art"
    ],
    "wof:name":"Tae Kwon DO Byung Y Kwak",
    "wof:placetype":"venue"
},
  "geometry": {"coordinates":[-75.30210099999999,40.155102],"type":"Point"}
}