{
  "type": "Feature",
  "properties": {
    "iso:country":"US",
    "sg:address":"597 Harman Rd",
    "sg:city":"Halifax",
    "sg:classifiers":[
        {
            "category":"Shopping",
            "subcategory":"Hobbies, Toys, & Games",
            "type":"Retail Goods"
        }
    ],
    "sg:phone":"+1 717 362 9518",
    "sg:postcode":"17032",
    "sg:province":"PA",
    "sg:tags":[
        "house",
        "doll",
        "accessory"
    ],
    "wof:name":"B Crist Miniatures",
    "wof:placetype":"venue"
},
  "geometry": {"coordinates":[-76.788628,40.532688],"type":"Point"}
}