{
  "type": "Feature",
  "properties": {
    "iso:country":"US",
    "sg:address":"5000 5th Ave",
    "sg:city":"Pittsburgh",
    "sg:classifiers":[
        {
            "category":"Professional",
            "type":"Services"
        }
    ],
    "sg:phone":"+1   ",
    "sg:postcode":"15232",
    "sg:province":"PA",
    "wof:name":"Morrison Foundation",
    "wof:placetype":"venue"
},
  "geometry": {"coordinates":[-79.94092999999999,40.447534],"type":"Point"}
}