{
  "type": "Feature",
  "properties": {
    "addr:full":"408 Kidder St Wilkes Barre PA 18702",
    "addr:housenumber":"408",
    "addr:postcode":"18702",
    "addr:street":"Kidder St",
    "iso:country":"US",
    "sg:address":"408 Kidder St",
    "sg:city":"Wilkes Barre",
    "sg:classifiers":[
        {
            "category":"Retail",
            "subcategory":"Auto Rental",
            "type":"Services"
        }
    ],
    "sg:phone":"+1 570 829 3411",
    "sg:postcode":"18702",
    "sg:province":"PA",
    "sg:tags":[
        "renting",
        "automobile",
        "car"
    ],
    "wof:name":"Enterprise Rent-A-Car Company",
    "wof:placetype":"venue"
},
  "geometry": {"coordinates":[-75.85615,41.249976],"type":"Point"}
}