{
  "type": "Feature",
  "properties": {
    "addr:full":"6712 Ridge Ave Philadelphia PA 19128",
    "addr:housenumber":"6712",
    "addr:postcode":"19128",
    "addr:street":"Ridge Ave",
    "iso:country":"US",
    "sg:address":"6712 Ridge Ave",
    "sg:city":"Philadelphia",
    "sg:classifiers":[
        {
            "category":"Retail",
            "subcategory":"Veterinary Services",
            "type":"Services"
        }
    ],
    "sg:phone":"+1 215 482 3037",
    "sg:postcode":"19128",
    "sg:province":"PA",
    "wof:name":"Roxborough Animal Hospital",
    "wof:placetype":"venue"
},
  "geometry": {"coordinates":[-75.224942,40.040677],"type":"Point"}
}