{
  "type": "Feature",
  "properties": {
    "iso:country":"US",
    "sg:address":"227 N 10th St",
    "sg:city":"Philadelphia",
    "sg:classifiers":[
        {
            "category":"Shopping",
            "subcategory":"Clothing, Apparel, & Fashions",
            "type":"Retail Goods"
        },
        {
            "category":"Shopping",
            "subcategory":"Shoes",
            "type":"Retail Goods"
        }
    ],
    "sg:phone":"+1 215 351 7978",
    "sg:postcode":"19107",
    "sg:province":"PA",
    "sg:tags":[
        "men's",
        "clothing",
        "store",
        "women's"
    ],
    "sg:website":"abakustakeout.com",
    "wof:name":"Abakus Takeout",
    "wof:placetype":"venue"
},
  "geometry": {"coordinates":[-75.155553,39.95615],"type":"Point"}
}