{
  "type": "Feature",
  "properties": {
    "iso:country":"US",
    "sg:address":"11 Crozerville Rd",
    "sg:city":"Aston",
    "sg:classifiers":[
        {
            "category":"Manufacturing",
            "subcategory":"Tools & Machinery",
            "type":"Manufacturing & Wholesale Goods"
        }
    ],
    "sg:phone":"+1 610 459 4300",
    "sg:postcode":"19014",
    "sg:province":"PA",
    "sg:tags":[
        "plastic"
    ],
    "sg:website":"www.maguire.com",
    "wof:name":"Maguire Products Inc",
    "wof:placetype":"venue"
},
  "geometry": {"coordinates":[-75.46259000000001,39.877516],"type":"Point"}
}