{
  "type": "Feature",
  "properties": {
    "iso:country":"US",
    "sg:address":"645 W Porter St",
    "sg:city":"Philadelphia",
    "sg:classifiers":[
        {
            "category":"Building & Trades",
            "subcategory":"Construction",
            "type":"Services"
        }
    ],
    "sg:phone":"+1 215 339 4004",
    "sg:postcode":"19148",
    "sg:province":"PA",
    "sg:tags":[
        "home",
        "improvement",
        "house"
    ],
    "wof:name":"Supreme Siding & Remodeling Inc",
    "wof:placetype":"venue"
},
  "geometry": {"coordinates":[-75.158835,39.917843],"type":"Point"}
}