{
  "type": "Feature",
  "properties": {
    "iso:country":"US",
    "sg:address":"1013 Edmonds Ave",
    "sg:city":"Drexel Hill",
    "sg:classifiers":[
        {
            "category":"Building & Trades",
            "subcategory":"Construction",
            "type":"Services"
        }
    ],
    "sg:phone":"+1 610 789 2144",
    "sg:postcode":"19026",
    "sg:province":"PA",
    "sg:tags":[
        "carpentry",
        "contractor"
    ],
    "wof:name":"Dublin Builders",
    "wof:placetype":"venue"
},
  "geometry": {"coordinates":[-75.30646900000001,39.958513],"type":"Point"}
}