{
  "type": "Feature",
  "properties": {
    "addr:full":"170 N Memorial Hwy Shavertown PA 18708",
    "addr:housenumber":"170",
    "addr:postcode":"18708",
    "addr:street":"N Memorial Hwy",
    "iso:country":"US",
    "sg:address":"170 N Memorial Hwy",
    "sg:city":"Shavertown",
    "sg:classifiers":[
        {
            "category":"Health Services",
            "subcategory":"Optometrist",
            "type":"Services"
        }
    ],
    "sg:phone":"+1 570 675 3627",
    "sg:postcode":"18708",
    "sg:province":"PA",
    "wof:name":"Northeastern Eye Institute",
    "wof:placetype":"venue"
},
  "geometry": {"coordinates":[-75.94253399999999,41.322998],"type":"Point"}
}