{
  "type": "Feature",
  "properties": {
    "iso:country":"US",
    "sg:address":"10 Alto Rd",
    "sg:city":"Pittston",
    "sg:classifiers":[
        {
            "category":"Building & Trades",
            "subcategory":"Equipment Rental",
            "type":"Services"
        }
    ],
    "sg:phone":"+1 570 655 8368",
    "sg:postcode":"18640",
    "sg:province":"PA",
    "sg:tags":[
        "camping"
    ],
    "wof:name":"J and S Party Tent Rental",
    "wof:placetype":"venue"
},
  "geometry": {"coordinates":[-75.801035,41.311608],"type":"Point"}
}