{
  "type": "Feature",
  "properties": {
    "addr:city":"Erie",
    "addr:full":"150 East Front Street Erie, Pa 16507-1594",
    "addr:house_number":"150",
    "addr:housenumber":"150",
    "addr:phone":"+1 814-452-2744",
    "addr:postcode":"16507-1594",
    "addr:road":"East Front Street",
    "addr:state":"PA",
    "addr:street":"E Front St",
    "iso:country":"US",
    "sg:address":"150 E Front St",
    "sg:city":"Erie",
    "sg:classifiers":[
        {
            "category":"Organizations",
            "subcategory":"Non-profit Organization",
            "type":"Services"
        }
    ],
    "sg:phone":"+1 814 452 2744",
    "sg:postcode":"16507",
    "sg:province":"PA",
    "sg:tags":[
        "fund",
        "raising"
    ],
    "sg:website":"www.brigniagara.org",
    "wof:airports":[
        102524857
    ],
    "wof:name":"Flagship Niagara League",
    "wof:placetype":"venue"
},
  "geometry": {"coordinates":[-80.08377,42.13612],"type":"Point"}
}