{
  "type": "Feature",
  "properties": {
    "addr:full":"173 W Frederick St Millersville PA 17551",
    "addr:housenumber":"173",
    "addr:postcode":"17551",
    "addr:street":"W Frederick St",
    "iso:country":"US",
    "sg:address":"173 W Frederick St",
    "sg:city":"Millersville",
    "sg:classifiers":[
        {
            "category":"Retail",
            "subcategory":"Portrait Studio",
            "type":"Services"
        }
    ],
    "sg:phone":"+1 717 872 2183",
    "sg:postcode":"17551",
    "sg:province":"PA",
    "sg:tags":[
        "photographer"
    ],
    "wof:name":"Crystal Photographic Svc",
    "wof:placetype":"venue"
},
  "geometry": {"coordinates":[-76.35999099999999,39.996471],"type":"Point"}
}