{
  "type": "Feature",
  "properties": {
    "addr:full":"2102 Northway Rd Williamsport PA 17701",
    "addr:housenumber":"2102",
    "addr:postcode":"17701",
    "addr:street":"Northway Rd",
    "iso:country":"US",
    "sg:address":"2102 Northway Rd",
    "sg:city":"Williamsport",
    "sg:classifiers":[
        {
            "category":"Retail",
            "subcategory":"Funeral Services",
            "type":"Services"
        }
    ],
    "sg:phone":"+1   ",
    "sg:postcode":"17701",
    "sg:province":"PA",
    "wof:name":"Kaufman Funeral Home Inc",
    "wof:placetype":"venue"
},
  "geometry": {"coordinates":[-76.974092,41.269243],"type":"Point"}
}