{
  "type": "Feature",
  "properties": {
    "iso:country":"US",
    "sg:address":"32 N Center St",
    "sg:city":"Corry",
    "sg:classifiers":[
        {
            "category":"Retail",
            "subcategory":"Repair Shop",
            "type":"Services"
        }
    ],
    "sg:phone":"+1 814 664 3228",
    "sg:postcode":"16407",
    "sg:province":"PA",
    "sg:tags":[
        "lock",
        "locksmith"
    ],
    "wof:name":"Jaquith Locksmith Safe & Key",
    "wof:placetype":"venue"
},
  "geometry": {"coordinates":[-79.640378,41.920627],"type":"Point"}
}