{
  "type": "Feature",
  "properties": {
    "addr:full":"5000 Steubenville Pike Pittsburgh PA 15205",
    "addr:housenumber":"5000",
    "addr:postcode":"15205",
    "addr:street":"Steubenville Pike",
    "iso:country":"US",
    "sg:address":"5000 Steubenville Pike",
    "sg:city":"Pittsburgh",
    "sg:classifiers":[
        {
            "category":"Building & Trades",
            "subcategory":"Construction",
            "type":"Services"
        }
    ],
    "sg:phone":"+1 412 788 1046",
    "sg:postcode":"15205",
    "sg:province":"PA",
    "sg:tags":[
        "contractor"
    ],
    "sg:website":"www.mooreconcretepumpinganddrill...",
    "wof:name":"Edi Enviro Drill Inc",
    "wof:placetype":"venue"
},
  "geometry": {"coordinates":[-80.116501,40.450298],"type":"Point"}
}