{
  "type": "Feature",
  "properties": {
    "iso:country":"US",
    "sg:address":"272 Mummerts Church Rd",
    "sg:city":"Abbottstown",
    "sg:classifiers":[
        {
            "category":"Government",
            "subcategory":"Police Station",
            "type":"Public Place"
        }
    ],
    "sg:phone":"+1 717 259 8597",
    "sg:postcode":"17301",
    "sg:province":"PA",
    "sg:tags":[
        "department"
    ],
    "wof:name":"Hamilton Township Police Dept",
    "wof:placetype":"venue"
},
  "geometry": {"coordinates":[-76.98775999999999,39.908597],"type":"Point"}
}