{
  "type": "Feature",
  "properties": {
    "iso:country":"US",
    "sg:address":"257 Tylersburg Rd",
    "sg:city":"Leeper",
    "sg:classifiers":[
        {
            "category":"Building & Trades",
            "subcategory":"Construction",
            "type":"Services"
        }
    ],
    "sg:phone":"+1 814 744 6277",
    "sg:postcode":"16233",
    "sg:province":"PA",
    "sg:tags":[
        "excavation",
        "contractor"
    ],
    "wof:name":"Ochs Stump Grinding",
    "wof:placetype":"venue"
},
  "geometry": {"coordinates":[-79.321589,41.360248],"type":"Point"}
}