{
  "type": "Feature",
  "properties": {
    "iso:country":"US",
    "sg:address":"77 Main St W",
    "sg:city":"Girard",
    "sg:classifiers":[
        {
            "category":"Sports & Exercise",
            "subcategory":"Gym",
            "type":"Entertainment"
        }
    ],
    "sg:phone":"+1 814 774 0220",
    "sg:postcode":"16417",
    "sg:province":"PA",
    "sg:tags":[
        "fitness",
        "physical",
        "facility"
    ],
    "wof:name":"Body Temple",
    "wof:placetype":"venue"
},
  "geometry": {"coordinates":[-80.317267,42.000581],"type":"Point"}
}