{
  "type": "Feature",
  "properties": {
    "addr:full":"578 Main St Lykens PA 17048",
    "addr:housenumber":"578",
    "addr:postcode":"17048",
    "addr:street":"Main St",
    "iso:country":"US",
    "sg:address":"578 Main St",
    "sg:city":"Lykens",
    "sg:classifiers":[
        {
            "category":"Restaurant",
            "type":"Food & Drink"
        }
    ],
    "sg:phone":"+1 717 453 7988",
    "sg:postcode":"17048",
    "sg:province":"PA",
    "sg:tags":[
        "pizza"
    ],
    "wof:name":"Nino's Italian Restaurant",
    "wof:placetype":"venue"
},
  "geometry": {"coordinates":[-76.700963,40.567092],"type":"Point"}
}