{
  "type": "Feature",
  "properties": {
    "iso:country":"US",
    "sg:address":"1 Highland Ave",
    "sg:city":"Bethlehem",
    "sg:classifiers":[
        {
            "category":"Manufacturing",
            "subcategory":"Chemicals & Compounds",
            "type":"Manufacturing & Wholesale Goods"
        }
    ],
    "sg:phone":"+1 610 882 8621",
    "sg:postcode":"18017",
    "sg:province":"PA",
    "sg:tags":[
        "inorganic",
        "industrial",
        "chemicals-wholesale",
        "manufacturer",
        "mfg"
    ],
    "sg:website":"http://www.specialtyminerals.com",
    "wof:name":"Specialty Minerals Inc.",
    "wof:placetype":"venue"
},
  "geometry": {"coordinates":[-75.37333700000001,40.66975],"type":"Point"}
}