{
  "type": "Feature",
  "properties": {
    "addr:full":"131 E 3rd St Lewistown PA 17044",
    "addr:housenumber":"131",
    "addr:postcode":"17044",
    "addr:street":"E 3Rd St",
    "iso:country":"US",
    "sg:address":"131 E 3rd St",
    "sg:city":"Lewistown",
    "sg:phone":"+1   ",
    "sg:postcode":"17044",
    "sg:province":"PA",
    "sg:tags":[
        "farm",
        "corn",
        "soybean"
    ],
    "wof:name":"William Ammon",
    "wof:placetype":"venue"
},
  "geometry": {"coordinates":[-77.573234,40.599992],"type":"Point"}
}