{
  "type": "Feature",
  "properties": {
    "addr:full":"683 Lancaster Pike New Providence PA 17560",
    "addr:housenumber":"683",
    "addr:postcode":"17560",
    "addr:street":"Lancaster Pike",
    "iso:country":"US",
    "sg:address":"683 Lancaster Pike",
    "sg:city":"New Providence",
    "sg:classifiers":[
        {
            "category":"Communications",
            "subcategory":"Radio Station",
            "type":"Services"
        }
    ],
    "sg:phone":"+1 717 284 4123",
    "sg:postcode":"17560",
    "sg:province":"PA",
    "sg:tags":[
        "company",
        "broadcasting"
    ],
    "sg:website":"www.wdac.com",
    "wof:name":"WDAC",
    "wof:placetype":"venue"
},
  "geometry": {"coordinates":[-76.238001,39.890232],"type":"Point"}
}