{
  "type": "Feature",
  "properties": {
    "addr:full":"161 S McKean St Kittanning PA 16201",
    "addr:housenumber":"161",
    "addr:postcode":"16201",
    "addr:street":"S Mckean St",
    "iso:country":"US",
    "sg:address":"161 S McKean St",
    "sg:city":"Kittanning",
    "sg:classifiers":[
        {
            "category":"Wholesale",
            "subcategory":"Books, Periodicals, & Newspapers",
            "type":"Manufacturing & Wholesale Goods"
        }
    ],
    "sg:phone":"+1   ",
    "sg:postcode":"16201",
    "sg:province":"PA",
    "sg:tags":[
        "magazine",
        "newsstand"
    ],
    "wof:name":"Kittanning News",
    "wof:placetype":"venue"
},
  "geometry": {"coordinates":[-79.517853,40.814035],"type":"Point"}
}