{
  "type": "Feature",
  "properties": {
    "addr:full":"3300 Hartzdale Dr Camp Hill PA 17011",
    "addr:postcode":"3300;17011",
    "addr:street":"Hartzdale Dr",
    "iso:country":"US",
    "sg:address":"3300 Hartzdale Dr",
    "sg:city":"Camp Hill",
    "sg:classifiers":[
        {
            "category":"Manufacturing",
            "subcategory":"Food",
            "type":"Manufacturing & Wholesale Goods"
        }
    ],
    "sg:phone":"+1   ",
    "sg:postcode":"17011",
    "sg:province":"PA",
    "sg:tags":[
        "cookie",
        "mfg"
    ],
    "wof:name":"Cookie Bouquet",
    "wof:placetype":"venue"
},
  "geometry": {"coordinates":[-76.925628,40.228365],"type":"Point"}
}