{
  "type": "Feature",
  "properties": {
    "iso:country":"US",
    "sg:address":"310 S Juniper St",
    "sg:city":"Philadelphia",
    "sg:classifiers":[
        {
            "category":"Professional",
            "subcategory":"Management & Consulting",
            "type":"Services"
        }
    ],
    "sg:phone":"+1 215 735 0500",
    "sg:postcode":"19107",
    "sg:province":"PA",
    "sg:tags":[
        "international",
        "consultant"
    ],
    "wof:name":"Overseas Strategic Consulting",
    "wof:placetype":"venue"
},
  "geometry": {"coordinates":[-75.163929,39.94596],"type":"Point"}
}