{
  "type": "Feature",
  "properties": {
    "iso:country":"US",
    "sg:address":"355 Lancaster Ave",
    "sg:city":"Haverford",
    "sg:classifiers":[
        {
            "category":"Banks & Credit Unions",
            "subcategory":"Bank",
            "type":"Services"
        }
    ],
    "sg:phone":"+1 610 896 7790",
    "sg:postcode":"19041",
    "sg:province":"PA",
    "sg:tags":[
        "loan",
        "real estate"
    ],
    "wof:name":"Madison Mortgage Svc",
    "wof:placetype":"venue"
},
  "geometry": {"coordinates":[-75.298693,40.011804],"type":"Point"}
}