{
  "type": "Feature",
  "properties": {
    "iso:country":"US",
    "sg:address":"114 Large St",
    "sg:city":"Meyersdale",
    "sg:classifiers":[
        {
            "category":"Farming",
            "subcategory":"Farm & Veterinary Services",
            "type":"Manufacturing & Wholesale Goods"
        }
    ],
    "sg:phone":"+1 814 634 0706",
    "sg:postcode":"15552",
    "sg:province":"PA",
    "wof:name":"Century Farms Enterprises",
    "wof:placetype":"venue"
},
  "geometry": {"coordinates":[-79.022564,39.812015],"type":"Point"}
}