{
  "type": "Feature",
  "properties": {
    "iso:country":"US",
    "sg:address":"303 Countryview Dr",
    "sg:city":"Bryn Mawr",
    "sg:classifiers":[
        {
            "category":"Health Services",
            "subcategory":"Doctor",
            "type":"Services"
        }
    ],
    "sg:phone":"+1   ",
    "sg:postcode":"19010",
    "sg:province":"PA",
    "sg:tags":[
        "medical"
    ],
    "wof:name":"St Agnes Anesthesia Svcs PC",
    "wof:placetype":"venue"
},
  "geometry": {"coordinates":[-75.351862,40.006851],"type":"Point"}
}