{
  "type": "Feature",
  "properties": {
    "iso:country":"US",
    "sg:address":"800 Diminjan Ln",
    "sg:city":"Harleysville",
    "sg:classifiers":[
        {
            "category":"Building & Trades",
            "subcategory":"Construction",
            "type":"Services"
        }
    ],
    "sg:phone":"+1 215 287 9772",
    "sg:postcode":"19438",
    "sg:province":"PA",
    "sg:tags":[
        "house",
        "contractor"
    ],
    "wof:name":"A&J Construction Inc",
    "wof:placetype":"venue"
},
  "geometry": {"coordinates":[-75.422726,40.300063],"type":"Point"}
}