{
  "type": "Feature",
  "properties": {
    "iso:country":"US",
    "sg:address":"50 Mill Rd",
    "sg:city":"Frackville",
    "sg:classifiers":[
        {
            "category":"Shopping",
            "subcategory":"Gifts & Souvenirs",
            "type":"Retail Goods"
        }
    ],
    "sg:phone":"+1 570 874 7085",
    "sg:postcode":"17964",
    "sg:province":"PA",
    "sg:tags":[
        "shop"
    ],
    "wof:name":"C P Ceramics & Gifts",
    "wof:placetype":"venue"
},
  "geometry": {"coordinates":[-76.58203399999999,40.699691],"type":"Point"}
}