{
  "type": "Feature",
  "properties": {
    "addr:full":"4308 Manayunk Ave Philadelphia PA 19128",
    "addr:housenumber":"4308",
    "addr:postcode":"19128",
    "addr:street":"Manayunk Ave",
    "iso:country":"US",
    "sg:address":"4308 Manayunk Ave",
    "sg:city":"Philadelphia",
    "sg:classifiers":[
        {
            "category":"Wholesale",
            "subcategory":"Hardware",
            "type":"Manufacturing & Wholesale Goods"
        }
    ],
    "sg:phone":"+1   ",
    "sg:postcode":"19128",
    "sg:province":"PA",
    "sg:tags":[
        "refrigeration"
    ],
    "wof:name":"Newmeyer Refridgeration",
    "wof:placetype":"venue"
},
  "geometry": {"coordinates":[-75.21663100000001,40.027602],"type":"Point"}
}