{
  "type": "Feature",
  "properties": {
    "iso:country":"US",
    "sg:address":"1711 Connor Dr",
    "sg:city":"South Park",
    "sg:classifiers":[
        {
            "category":"Wholesale",
            "subcategory":"Machinery & Supplies",
            "type":"Manufacturing & Wholesale Goods"
        }
    ],
    "sg:phone":"+1 412 655 9555",
    "sg:postcode":"15129",
    "sg:province":"PA",
    "sg:tags":[
        "valve"
    ],
    "wof:name":"Roy Dalzell Co",
    "wof:placetype":"venue"
},
  "geometry": {"coordinates":[-79.978353,40.279948],"type":"Point"}
}