{
  "type": "Feature",
  "properties": {
    "iso:country":"US",
    "sg:address":"1020 Locust St",
    "sg:city":"Philadelphia",
    "sg:classifiers":[
        {
            "category":"Health Services",
            "subcategory":"Doctor",
            "type":"Services"
        }
    ],
    "sg:phone":"+1 215 955 5060",
    "sg:postcode":"19107",
    "sg:province":"PA",
    "sg:tags":[
        "physician",
        "surgeon"
    ],
    "wof:name":"Thomas Jefferson Univ Hospital",
    "wof:placetype":"venue"
},
  "geometry": {"coordinates":[-75.15897699999999,39.94743],"type":"Point"}
}