{
  "type": "Feature",
  "properties": {
    "iso:country":"US",
    "sg:address":"430 Main St",
    "sg:city":"Schwenksville",
    "sg:classifiers":[
        {
            "category":"Home & Garden",
            "subcategory":"Household Appliances",
            "type":"Retail Goods"
        }
    ],
    "sg:phone":"+1   ",
    "sg:postcode":"19426",
    "sg:province":"PA",
    "sg:tags":[
        "repair",
        "electrical"
    ],
    "wof:name":"Rainbow",
    "wof:placetype":"venue"
},
  "geometry": {"coordinates":[-75.463628,40.256589],"type":"Point"}
}