{
  "type": "Feature",
  "properties": {
    "addr:full":"18228 Conneaut Lake Rd Meadville PA 16335",
    "addr:housenumber":"18228",
    "addr:postcode":"16335",
    "addr:street":"Conneaut Lake Rd",
    "iso:country":"US",
    "sg:address":"18228 Conneaut Lake Rd",
    "sg:city":"Meadville",
    "sg:classifiers":[
        {
            "category":"Restaurant",
            "type":"Food & Drink"
        }
    ],
    "sg:menulink":"http://www.allmenus.com/pa/vernon/158322-chovys-itlaian-casual/menu/",
    "sg:phone":"+1 814 724 1286",
    "sg:postcode":"16335",
    "sg:province":"PA",
    "sg:tags":[
        "italian"
    ],
    "wof:name":"Chovy's Itlaian Casual",
    "wof:placetype":"venue"
},
  "geometry": {"coordinates":[-80.18836899999999,41.624504],"type":"Point"}
}