{
  "type": "Feature",
  "properties": {
    "iso:country":"US",
    "sg:address":"34 Grant St",
    "sg:city":"Hunlock Creek",
    "sg:classifiers":[
        {
            "category":"Retail",
            "subcategory":"Auto Repair",
            "type":"Services"
        }
    ],
    "sg:phone":"+1 570 477 1525",
    "sg:postcode":"18655",
    "sg:province":"PA",
    "sg:tags":[
        "general"
    ],
    "wof:name":"Northeast Garage Cabinets",
    "wof:placetype":"venue"
},
  "geometry": {"coordinates":[-76.15505,41.151083],"type":"Point"}
}