{
  "type": "Feature",
  "properties": {
    "iso:country":"US",
    "sg:address":"1 Oak St",
    "sg:city":"Kane",
    "sg:classifiers":[
        {
            "category":"Autos & Motor Vehicles",
            "subcategory":"Fuel & Gas Station",
            "type":"Retail Goods"
        }
    ],
    "sg:phone":"+1   ",
    "sg:postcode":"16735",
    "sg:province":"PA",
    "sg:tags":[
        "station",
        "gasoline"
    ],
    "wof:name":"Oak Street Keystone 767",
    "wof:placetype":"venue"
},
  "geometry": {"coordinates":[-78.81451,41.667781],"type":"Point"}
}