{
  "type": "Feature",
  "properties": {
    "iso:country":"US",
    "sg:address":"6814 Lower York Rd",
    "sg:city":"New Hope",
    "sg:classifiers":[
        {
            "category":"Freight",
            "type":"Transportation"
        }
    ],
    "sg:phone":"+1 215 862 6933",
    "sg:postcode":"18938",
    "sg:province":"PA",
    "sg:tags":[
        "commercial",
        "storage"
    ],
    "wof:name":"Magill Mini Storage Facility",
    "wof:placetype":"venue"
},
  "geometry": {"coordinates":[-74.976105,40.359309],"type":"Point"}
}