{
  "type": "Feature",
  "properties": {
    "addr:full":"120 Plank Rd York Springs PA 17372",
    "addr:housenumber":"120",
    "addr:postcode":"17372",
    "addr:street":"Plank Rd",
    "iso:country":"US",
    "sg:address":"120 Plank Rd",
    "sg:city":"York Springs",
    "sg:classifiers":[
        {
            "category":"Wholesale",
            "subcategory":"Electrical",
            "type":"Manufacturing & Wholesale Goods"
        }
    ],
    "sg:phone":"+1 717 338 1513",
    "sg:postcode":"17372",
    "sg:province":"PA",
    "sg:tags":[
        "fire",
        "alarm",
        "system"
    ],
    "wof:name":"D W Security Inc",
    "wof:placetype":"venue"
},
  "geometry": {"coordinates":[-77.09894,40.012657],"type":"Point"}
}