{
  "type": "Feature",
  "properties": {
    "iso:country":"US",
    "sg:address":"106 W High St",
    "sg:city":"New Bloomfield",
    "sg:classifiers":[
        {
            "category":"Organizations",
            "subcategory":"Religious Organization",
            "type":"Services"
        }
    ],
    "sg:phone":"+1 717 834 4757",
    "sg:postcode":"17068",
    "sg:province":"PA",
    "sg:tags":[
        "church"
    ],
    "wof:name":"Trinity United Church Of Chris",
    "wof:placetype":"venue"
},
  "geometry": {"coordinates":[-77.189922,40.419896],"type":"Point"}
}