{
  "type": "Feature",
  "properties": {
    "iso:country":"US",
    "sg:address":"496 Bestwick Rd",
    "sg:city":"Mercer",
    "sg:classifiers":[
        {
            "category":"Sports & Exercise",
            "subcategory":"Golf",
            "type":"Entertainment"
        }
    ],
    "sg:phone":"+1 724 662 1999",
    "sg:postcode":"16137",
    "sg:province":"PA",
    "sg:tags":[
        "course",
        "public"
    ],
    "wof:name":"Spring Valley Public Golf Club",
    "wof:placetype":"venue"
},
  "geometry": {"coordinates":[-80.269773,41.225401],"type":"Point"}
}