{
  "type": "Feature",
  "properties": {
    "addr:full":"708 Chestnut St Philadelphia PA 19106",
    "addr:housenumber":"708",
    "addr:postcode":"19106",
    "addr:street":"Chestnut St",
    "iso:country":"US",
    "sg:address":"708 Chestnut St",
    "sg:city":"Philadelphia",
    "sg:classifiers":[
        {
            "category":"Restaurant",
            "type":"Food & Drink"
        }
    ],
    "sg:phone":"+1 215 928 9463",
    "sg:postcode":"19106",
    "sg:province":"PA",
    "wof:name":"Park Salad Bar",
    "wof:placetype":"venue"
},
  "geometry": {"coordinates":[-75.15280199999999,39.949699],"type":"Point"}
}