{
  "type": "Feature",
  "properties": {
    "addr:full":"1446 Greenmount Ave South Hills PA 15216",
    "addr:housenumber":"1446",
    "addr:postcode":"15216",
    "addr:street":"Greenmount Ave South Hills",
    "iso:country":"US",
    "sg:address":"1446 Greenmount Ave",
    "sg:city":"South Hills",
    "sg:classifiers":[
        {
            "category":"Building & Trades",
            "subcategory":"Plumbing",
            "type":"Services"
        }
    ],
    "sg:phone":"+1 412 885 6220",
    "sg:postcode":"15216",
    "sg:province":"PA",
    "sg:tags":[
        "plumbing",
        "contractor"
    ],
    "wof:name":"James R Ramsey Jr",
    "wof:placetype":"venue"
},
  "geometry": {"coordinates":[-80.041518,40.392558],"type":"Point"}
}