{
  "type": "Feature",
  "properties": {
    "iso:country":"US",
    "sg:address":"1515 Market St",
    "sg:city":"Philadelphia",
    "sg:classifiers":[
        {
            "category":"Health Services",
            "subcategory":"Health Practitioner",
            "type":"Services"
        }
    ],
    "sg:phone":"+1 215 564 1442",
    "sg:postcode":"19102",
    "sg:province":"PA",
    "sg:tags":[
        "psychologist"
    ],
    "wof:name":"Rhr Intl Co",
    "wof:placetype":"venue"
},
  "geometry": {"coordinates":[-75.16666600000001,39.952824],"type":"Point"}
}