{
  "type": "Feature",
  "properties": {
    "addr:full":"104 Misty Mdw Perkasie PA 18944",
    "addr:housenumber":"104",
    "addr:postcode":"18944",
    "addr:street":"Misty Mdw",
    "iso:country":"US",
    "sg:address":"104 Misty Mdw",
    "sg:city":"Perkasie",
    "sg:classifiers":[
        {
            "category":"Building & Trades",
            "subcategory":"Construction",
            "type":"Services"
        }
    ],
    "sg:phone":"+1   ",
    "sg:postcode":"18944",
    "sg:province":"PA",
    "sg:tags":[
        "house"
    ],
    "wof:name":"Mark Lewis Building & Rmdlg",
    "wof:placetype":"venue"
},
  "geometry": {"coordinates":[-75.276904,40.360769],"type":"Point"}
}