{
  "type": "Feature",
  "properties": {
    "addr:full":"192 Middletown Rd  Glen Mills PA 19342",
    "addr:housenumber":"192",
    "addr:postcode":"19342",
    "addr:street":"Middletown Rd",
    "iso:country":"US",
    "sg:address":"192 Middletown Rd ",
    "sg:city":"Glen Mills",
    "sg:classifiers":[
        {
            "category":"Restaurant",
            "type":"Food & Drink"
        }
    ],
    "sg:menulink":"http://www.allmenus.com/pa/thornbury/289258-duffers-tavern/menu/",
    "sg:phone":"+1 610 358 5050",
    "sg:postcode":"19342",
    "sg:province":"PA",
    "sg:tags":[
        "american",
        "pub"
    ],
    "wof:name":"Duffer's Tavern",
    "wof:placetype":"venue"
},
  "geometry": {"coordinates":[-75.505093,39.946997],"type":"Point"}
}