{
  "type": "Feature",
  "properties": {
    "iso:country":"US",
    "sg:address":"248 Main St",
    "sg:city":"Olyphant",
    "sg:phone":"+1 570 489 6697",
    "sg:postcode":"18447",
    "sg:province":"PA",
    "sg:tags":[
        "shelving"
    ],
    "sg:website":"www.binwarehouse.com",
    "wof:name":"Albern Enterprises",
    "wof:placetype":"venue"
},
  "geometry": {"coordinates":[-75.60615900000001,41.472787],"type":"Point"}
}