{
  "type": "Feature",
  "properties": {
    "iso:country":"US",
    "sg:address":"8369 Fisher Rd",
    "sg:city":"Elkins Park",
    "sg:classifiers":[
        {
            "category":"Real Estate",
            "subcategory":"Developer",
            "type":"Services"
        }
    ],
    "sg:phone":"+1   ",
    "sg:postcode":"19027",
    "sg:province":"PA",
    "wof:name":"Winther Investments Inc",
    "wof:placetype":"venue"
},
  "geometry": {"coordinates":[-75.12099499999999,40.082788],"type":"Point"}
}