{
  "type": "Feature",
  "properties": {
    "iso:country":"US",
    "sg:address":"3501 N Front St",
    "sg:city":"Philadelphia",
    "sg:classifiers":[
        {
            "category":"Wholesale",
            "subcategory":"Painting Supplies",
            "type":"Manufacturing & Wholesale Goods"
        },
        {
            "category":"Home & Garden",
            "subcategory":"Garden Supply",
            "type":"Retail Goods"
        },
        {
            "category":"Wholesale",
            "subcategory":"Construction Materials",
            "type":"Manufacturing & Wholesale Goods"
        },
        {
            "category":"Home & Garden",
            "subcategory":"Hardware",
            "type":"Retail Goods"
        }
    ],
    "sg:phone":"+1 215 634 5801",
    "sg:postcode":"19140",
    "sg:province":"PA",
    "sg:tags":[
        "lawn",
        "paint",
        "equipment",
        "part",
        "plumbing",
        "fixtures",
        "store"
    ],
    "sg:website":"www.truevalue.com",
    "wof:name":"Stein True Value Hardware",
    "wof:placetype":"venue"
},
  "geometry": {"coordinates":[-75.12840300000001,40.003201],"type":"Point"}
}