{
  "type": "Feature",
  "properties": {
    "iso:country":"US",
    "sg:address":"600 Church Rd",
    "sg:city":"Jenkintown",
    "sg:classifiers":[
        {
            "category":"Real Estate",
            "subcategory":"Developer",
            "type":"Services"
        }
    ],
    "sg:phone":"+1 215 663 1250",
    "sg:postcode":"19046",
    "sg:province":"PA",
    "sg:tags":[
        "cemetery"
    ],
    "wof:name":"Montefiore Cemetery Co",
    "wof:placetype":"venue"
},
  "geometry": {"coordinates":[-75.090503,40.07796],"type":"Point"}
}