{
  "type": "Feature",
  "properties": {
    "addr:full":"125 Wallace St Clearfield PA 16830",
    "addr:housenumber":"125",
    "addr:postcode":"16830",
    "addr:street":"Wallace St",
    "iso:country":"US",
    "sg:address":"125 Wallace St",
    "sg:city":"Clearfield",
    "sg:classifiers":[
        {
            "category":"Health Services",
            "subcategory":"Doctor",
            "type":"Services"
        }
    ],
    "sg:phone":"+1 814 765 8363",
    "sg:postcode":"16830",
    "sg:province":"PA",
    "sg:tags":[
        "dentist"
    ],
    "wof:name":"Henninger Dental & Assoc",
    "wof:placetype":"venue"
},
  "geometry": {"coordinates":[-78.442215,41.018504],"type":"Point"}
}