{
  "type": "Feature",
  "properties": {
    "addr:full":"400 N Main St Athens PA 18810",
    "addr:housenumber":"400",
    "addr:postcode":"18810",
    "addr:street":"N Main St",
    "iso:country":"US",
    "sg:address":"400 N Main St",
    "sg:city":"Athens",
    "sg:classifiers":[
        {
            "category":"Health Services",
            "subcategory":"Doctor",
            "type":"Services"
        }
    ],
    "sg:phone":"+1   ",
    "sg:postcode":"18810",
    "sg:province":"PA",
    "wof:name":"Mordern Denstry",
    "wof:placetype":"venue"
},
  "geometry": {"coordinates":[-76.5223,41.968992],"type":"Point"}
}