{
  "type": "Feature",
  "properties": {
    "iso:country":"US",
    "sg:address":"305 Church Rd",
    "sg:city":"Bethel Park",
    "sg:classifiers":[
        {
            "category":"Sports & Exercise",
            "subcategory":"Ice Rink",
            "type":"Entertainment"
        }
    ],
    "sg:phone":"+1 412 833 8500",
    "sg:postcode":"15102",
    "sg:province":"PA",
    "sg:tags":[
        "skating"
    ],
    "sg:website":"www.bladerunnersice.com",
    "wof:name":"Bladerunners Ice Complex-Bethel Park",
    "wof:placetype":"venue"
},
  "geometry": {"coordinates":[-80.044701,40.335899],"type":"Point"}
}