{
  "type": "Feature",
  "properties": {
    "iso:country":"US",
    "sg:address":"131 W Main St",
    "sg:city":"Schuylkill Haven",
    "sg:classifiers":[
        {
            "category":"Food & Beverages",
            "subcategory":"Groceries & Convenience Stores",
            "type":"Retail Goods"
        }
    ],
    "sg:phone":"+1 570 385 3141",
    "sg:postcode":"17972",
    "sg:province":"PA",
    "sg:tags":[
        "grocer"
    ],
    "wof:name":"Boyer's IGA",
    "wof:placetype":"venue"
},
  "geometry": {"coordinates":[-76.174244,40.627119],"type":"Point"}
}