{
  "type": "Feature",
  "properties": {
    "addr:full":"107 Mill St Verona PA 15147",
    "addr:housenumber":"107",
    "addr:postcode":"15147",
    "addr:street":"Mill St",
    "iso:country":"US",
    "sg:address":"107 Mill St",
    "sg:city":"Verona",
    "sg:classifiers":[
        {
            "category":"Professional",
            "type":"Services"
        }
    ],
    "sg:phone":"+1   ",
    "sg:postcode":"15147",
    "sg:province":"PA",
    "wof:name":"American Federation of St",
    "wof:placetype":"venue"
},
  "geometry": {"coordinates":[-79.794911,40.509343],"type":"Point"}
}