{
  "type": "Feature",
  "properties": {
    "iso:country":"US",
    "sg:address":"907 6th Blvd",
    "sg:city":"Brownsville",
    "sg:classifiers":[
        {
            "category":"Building & Trades",
            "subcategory":"Electrical",
            "type":"Services"
        }
    ],
    "sg:phone":"+1   ",
    "sg:postcode":"15417",
    "sg:province":"PA",
    "sg:tags":[
        "personal",
        "electrical",
        "contractor"
    ],
    "wof:name":"Beck Electric",
    "wof:placetype":"venue"
},
  "geometry": {"coordinates":[-79.886489,40.028829],"type":"Point"}
}