{
  "type": "Feature",
  "properties": {
    "addr:full":"2628 Brownsville Rd Pittsburgh PA 15227",
    "addr:housenumber":"2628",
    "addr:postcode":"15227",
    "addr:street":"Brownsville Rd",
    "iso:country":"US",
    "sg:address":"2628 Brownsville Rd",
    "sg:city":"Pittsburgh",
    "sg:classifiers":[
        {
            "category":"Personal",
            "subcategory":"Beauty Salon",
            "type":"Services"
        }
    ],
    "sg:phone":"+1 412 882 7002",
    "sg:postcode":"15227",
    "sg:province":"PA",
    "sg:tags":[
        "manicuring"
    ],
    "wof:name":"Nail Care Plus",
    "wof:placetype":"venue"
},
  "geometry": {"coordinates":[-79.978157,40.384773],"type":"Point"}
}