{
  "type": "Feature",
  "properties": {
    "iso:country":"US",
    "sg:address":"7805 McKnight Rd",
    "sg:city":"Pittsburgh",
    "sg:classifiers":[
        {
            "category":"Professional",
            "subcategory":"Engineering",
            "type":"Services"
        }
    ],
    "sg:phone":"+1 412 635 8220",
    "sg:postcode":"15237",
    "sg:province":"PA",
    "sg:tags":[
        "engineer"
    ],
    "wof:name":"Landtech Engineering Inc",
    "wof:placetype":"venue"
},
  "geometry": {"coordinates":[-80.019639,40.550188],"type":"Point"}
}