{
  "type": "Feature",
  "properties": {
    "iso:country":"US",
    "sg:address":"525 S 8th St",
    "sg:city":"Lebanon",
    "sg:classifiers":[
        {
            "category":"Professional",
            "subcategory":"Lawyer & Legal Services",
            "type":"Services"
        }
    ],
    "sg:phone":"+1 717 274 1421",
    "sg:postcode":"17042",
    "sg:province":"PA",
    "sg:tags":[
        "attorney",
        "practice"
    ],
    "wof:name":"Coyle Edward J",
    "wof:placetype":"venue"
},
  "geometry": {"coordinates":[-76.423616,40.331883],"type":"Point"}
}