{
  "type": "Feature",
  "properties": {
    "iso:country":"US",
    "sg:address":"43 Constitution Ave",
    "sg:city":"Doylestown",
    "sg:classifiers":[
        {
            "category":"Building & Trades",
            "subcategory":"Electrical",
            "type":"Services"
        }
    ],
    "sg:phone":"+1 215 489 7167",
    "sg:postcode":"18901",
    "sg:province":"PA",
    "sg:tags":[
        "electrical",
        "electric",
        "contractor"
    ],
    "wof:name":"Armitage Electrical Servi",
    "wof:placetype":"venue"
},
  "geometry": {"coordinates":[-75.151736,40.313907],"type":"Point"}
}