{
  "type": "Feature",
  "properties": {
    "iso:country":"US",
    "sg:address":"141 S 24th St",
    "sg:city":"Philadelphia",
    "sg:classifiers":[
        {
            "category":"Professional",
            "subcategory":"Business Services",
            "type":"Services"
        }
    ],
    "sg:phone":"+1 610 644 7209",
    "sg:postcode":"19103",
    "sg:province":"PA",
    "sg:tags":[
        "relation",
        "public"
    ],
    "sg:website":"www.omnicourier.net",
    "wof:name":"Omni Courier",
    "wof:placetype":"venue"
},
  "geometry": {"coordinates":[-75.17923500000001,39.951551],"type":"Point"}
}