{
  "type": "Feature",
  "properties": {
    "addr:full":"2773 Darlington Rd Beaver Falls PA 15010",
    "addr:housenumber":"2773",
    "addr:postcode":"15010",
    "addr:street":"Darlington Rd",
    "iso:country":"US",
    "sg:address":"2773 Darlington Rd",
    "sg:city":"Beaver Falls",
    "sg:classifiers":[
        {
            "category":"Wholesale",
            "subcategory":"Metals & Minerals",
            "type":"Manufacturing & Wholesale Goods"
        }
    ],
    "sg:phone":"+1 724 856 7070",
    "sg:postcode":"15010",
    "sg:province":"PA",
    "sg:tags":[
        "steel",
        "warehouse"
    ],
    "wof:name":"H R Evans LTD",
    "wof:placetype":"venue"
},
  "geometry": {"coordinates":[-80.39543399999999,40.78133],"type":"Point"}
}