{
  "type": "Feature",
  "properties": {
    "iso:country":"US",
    "sg:address":"1055 Moss St",
    "sg:city":"Reading",
    "sg:classifiers":[
        {
            "category":"Building & Trades",
            "subcategory":"Cleaning & Sanitation",
            "type":"Services"
        }
    ],
    "sg:phone":"+1 610 373 8673",
    "sg:postcode":"19604",
    "sg:province":"PA",
    "sg:tags":[
        "maintenance"
    ],
    "wof:name":"R & R Janitorial",
    "wof:placetype":"venue"
},
  "geometry": {"coordinates":[-75.918599,40.350592],"type":"Point"}
}