{
  "type": "Feature",
  "properties": {
    "iso:country":"US",
    "sg:address":"19 S 5th Ave",
    "sg:city":"Clarion",
    "sg:classifiers":[
        {
            "category":"Shopping",
            "subcategory":"Florist",
            "type":"Retail Goods"
        },
        {
            "category":"Shopping",
            "subcategory":"Gifts & Souvenirs",
            "type":"Retail Goods"
        }
    ],
    "sg:phone":"+1 814 226 4974",
    "sg:postcode":"16214",
    "sg:province":"PA",
    "sg:tags":[
        "shop"
    ],
    "wof:name":"Knot n Plant Place",
    "wof:placetype":"venue"
},
  "geometry": {"coordinates":[-79.38602400000001,41.214174],"type":"Point"}
}