{
  "type": "Feature",
  "properties": {
    "iso:country":"US",
    "sg:address":"132 Bingaman Rd",
    "sg:city":"Reading",
    "sg:classifiers":[
        {
            "category":"Building & Trades",
            "subcategory":"Construction",
            "type":"Services"
        }
    ],
    "sg:phone":"+1   ",
    "sg:postcode":"19606",
    "sg:province":"PA",
    "sg:tags":[
        "hanging",
        "contractor"
    ],
    "wof:name":"Creative Contracting",
    "wof:placetype":"venue"
},
  "geometry": {"coordinates":[-75.885277,40.365679],"type":"Point"}
}