{
  "type": "Feature",
  "properties": {
    "iso:country":"US",
    "sg:address":"40 Fern Dr",
    "sg:city":"Boyertown",
    "sg:classifiers":[
        {
            "category":"Building & Trades",
            "subcategory":"Plumbing",
            "type":"Services"
        }
    ],
    "sg:phone":"+1   ",
    "sg:postcode":"19512",
    "sg:province":"PA",
    "sg:tags":[
        "contractor"
    ],
    "wof:name":"Stan L Moyer Plumbing",
    "wof:placetype":"venue"
},
  "geometry": {"coordinates":[-75.69156599999999,40.319382],"type":"Point"}
}