{
  "type": "Feature",
  "properties": {
    "iso:country":"US",
    "sg:address":"111 W 4th St",
    "sg:city":"Bridgeport",
    "sg:classifiers":[
        {
            "category":"Personal",
            "subcategory":"Beauty Salon",
            "type":"Services"
        }
    ],
    "sg:phone":"+1 610 277 0626",
    "sg:postcode":"19405",
    "sg:province":"PA",
    "wof:name":"Style Corner Inc",
    "wof:placetype":"venue"
},
  "geometry": {"coordinates":[-75.344666,40.105595],"type":"Point"}
}