{
  "type": "Feature",
  "properties": {
    "iso:country":"US",
    "sg:address":"32 S Brady St",
    "sg:city":"Du Bois",
    "sg:classifiers":[
        {
            "category":"Personal",
            "type":"Services"
        }
    ],
    "sg:phone":"+1 814 375 5570",
    "sg:postcode":"15801",
    "sg:province":"PA",
    "wof:name":"Tainted Flesh Tattoo Studio",
    "wof:placetype":"venue"
},
  "geometry": {"coordinates":[-78.762596,41.118379],"type":"Point"}
}