{
  "type": "Feature",
  "properties": {
    "addr:full":"1710 Greengarden Rd Erie PA 16502",
    "addr:housenumber":"1710",
    "addr:postcode":"16502",
    "addr:street":"Greengarden Rd",
    "iso:country":"US",
    "sg:address":"1710 Greengarden Rd",
    "sg:city":"Erie",
    "sg:classifiers":[
        {
            "category":"Freight",
            "type":"Transportation"
        },
        {
            "category":"Building & Trades",
            "subcategory":"Construction",
            "type":"Services"
        }
    ],
    "sg:phone":"+1 814 454 4891",
    "sg:postcode":"16502",
    "sg:province":"PA",
    "sg:tags":[
        "warehouse",
        "industrial"
    ],
    "wof:name":"Lake Erie Warehouse & Dist Ctr",
    "wof:placetype":"venue"
},
  "geometry": {"coordinates":[-80.11289499999999,42.105801],"type":"Point"}
}