{
  "type": "Feature",
  "properties": {
    "iso:country":"US",
    "sg:address":"3620 E Prospect Rd",
    "sg:city":"York",
    "sg:classifiers":[
        {
            "category":"Education",
            "subcategory":"School",
            "type":"Public Place"
        }
    ],
    "sg:phone":"+1 717 755 9835",
    "sg:postcode":"17402",
    "sg:province":"PA",
    "sg:tags":[
        "elementary"
    ],
    "wof:name":"Locust Grove Elementary School",
    "wof:placetype":"venue"
},
  "geometry": {"coordinates":[-76.62112999999999,39.962404],"type":"Point"}
}