{
  "type": "Feature",
  "properties": {
    "addr:full":"715 Ewing St New Kensington PA 15068",
    "addr:housenumber":"715",
    "addr:postcode":"15068",
    "addr:street":"Ewing St",
    "iso:country":"US",
    "sg:address":"715 Ewing St",
    "sg:city":"New Kensington",
    "sg:classifiers":[
        {
            "category":"Retail",
            "subcategory":"Repair Shop",
            "type":"Services"
        }
    ],
    "sg:phone":"+1   ",
    "sg:postcode":"15068",
    "sg:province":"PA",
    "sg:tags":[
        "equipment",
        "material",
        "handling",
        "hydraulic"
    ],
    "wof:name":"Zampogna Carts",
    "wof:placetype":"venue"
},
  "geometry": {"coordinates":[-79.766463,40.583071],"type":"Point"}
}