{
  "type": "Feature",
  "properties": {
    "addr:full":"122 E Poplar St Palmyra PA 17078",
    "addr:housenumber":"122",
    "addr:postcode":"17078",
    "addr:street":"E Poplar St",
    "iso:country":"US",
    "sg:address":"122 E Poplar St",
    "sg:city":"Palmyra",
    "sg:classifiers":[
        {
            "category":"Professional",
            "subcategory":"Engineering",
            "type":"Services"
        }
    ],
    "sg:phone":"+1   ",
    "sg:postcode":"17078",
    "sg:province":"PA",
    "sg:tags":[
        "per",
        "real estate"
    ],
    "wof:name":"Patricia Greene Rentals",
    "wof:placetype":"venue"
},
  "geometry": {"coordinates":[-76.60117700000001,40.31899],"type":"Point"}
}