{
  "type": "Feature",
  "properties": {
    "addr:full":"1209 Vilsmeier Rd Lansdale PA 19446",
    "addr:housenumber":"1209",
    "addr:postcode":"19446",
    "addr:street":"Vilsmeier Rd",
    "iso:country":"US",
    "sg:address":"1209 Vilsmeier Rd",
    "sg:city":"Lansdale",
    "sg:classifiers":[
        {
            "category":"Home & Garden",
            "subcategory":"Building Materials",
            "type":"Retail Goods"
        }
    ],
    "sg:phone":"+1 215 361 2311",
    "sg:postcode":"19446",
    "sg:province":"PA",
    "sg:tags":[
        "installs",
        "garage",
        "door"
    ],
    "wof:name":"J & A Doors Inc",
    "wof:placetype":"venue"
},
  "geometry": {"coordinates":[-75.249071,40.245624],"type":"Point"}
}