{
  "type": "Feature",
  "properties": {
    "iso:country":"US",
    "sg:address":"221 Vine St",
    "sg:city":"Philadelphia",
    "sg:classifiers":[
        {
            "category":"Real Estate",
            "subcategory":"Real Estate Agent",
            "type":"Services"
        }
    ],
    "sg:phone":"+1 215 925 7500",
    "sg:postcode":"19106",
    "sg:province":"PA",
    "wof:name":"Tucker Realty Corp",
    "wof:placetype":"venue"
},
  "geometry": {"coordinates":[-75.143283,39.95578],"type":"Point"}
}