{
  "type": "Feature",
  "properties": {
    "addr:full":"515 Main St Moosic PA 18507",
    "addr:housenumber":"515",
    "addr:postcode":"18507",
    "addr:street":"Main St",
    "iso:country":"US",
    "sg:address":"515 Main St",
    "sg:city":"Moosic",
    "sg:classifiers":[
        {
            "category":"Restaurant",
            "type":"Food & Drink"
        },
        {
            "category":"Shopping",
            "subcategory":"Gifts & Souvenirs",
            "type":"Retail Goods"
        }
    ],
    "sg:phone":"+1 570 451 7467",
    "sg:postcode":"18507",
    "sg:province":"PA",
    "wof:name":"Delia's Primitives Gift Shoppe",
    "wof:placetype":"venue"
},
  "geometry": {"coordinates":[-75.73348300000001,41.355754],"type":"Point"}
}