{
  "type": "Feature",
  "properties": {
    "addr:full":"47 Crystal St East Stroudsburg PA 18301",
    "addr:housenumber":"47",
    "addr:postcode":"18301",
    "addr:street":"Crystal St",
    "iso:country":"US",
    "sg:address":"47 Crystal St",
    "sg:city":"East Stroudsburg",
    "sg:classifiers":[
        {
            "category":"Health Services",
            "subcategory":"Optometrist",
            "type":"Services"
        }
    ],
    "sg:phone":"+1 570 421 4141",
    "sg:postcode":"18301",
    "sg:province":"PA",
    "wof:name":"Scott A Huggler OD",
    "wof:placetype":"venue"
},
  "geometry": {"coordinates":[-75.18186,40.998641],"type":"Point"}
}