{
  "type": "Feature",
  "properties": {
    "addr:full":"54 Woodhaven Dr Pittsburgh PA 15228",
    "addr:housenumber":"54",
    "addr:postcode":"15228",
    "addr:street":"Woodhaven Dr",
    "iso:country":"US",
    "sg:address":"54 Woodhaven Dr",
    "sg:city":"Pittsburgh",
    "sg:classifiers":[
        {
            "category":"Professional",
            "subcategory":"Management & Consulting",
            "type":"Services"
        }
    ],
    "sg:phone":"+1 412 388 1129",
    "sg:postcode":"15228",
    "sg:province":"PA",
    "sg:tags":[
        "consultant"
    ],
    "wof:name":"Marquesen Consulting Corp",
    "wof:placetype":"venue"
},
  "geometry": {"coordinates":[-80.05153900000001,40.366112],"type":"Point"}
}