{
  "type": "Feature",
  "properties": {
    "iso:country":"US",
    "sg:address":"516 E Jamestown Rd",
    "sg:city":"Greenville",
    "sg:classifiers":[
        {
            "category":"Place Of Worship",
            "subcategory":"Church",
            "type":"Public Place"
        },
        {
            "category":"Place Of Worship",
            "type":"Public Place"
        }
    ],
    "sg:phone":"+1 724 932 5292",
    "sg:postcode":"16125",
    "sg:province":"PA",
    "sg:tags":[
        "churches-baptist-general",
        "churches-interdenominational",
        "churches-baptist",
        "churches-various",
        "denomination"
    ],
    "wof:name":"Harvest Baptist Church",
    "wof:placetype":"venue"
},
  "geometry": {"coordinates":[-80.399179,41.448606],"type":"Point"}
}