{
  "type": "Feature",
  "properties": {
    "iso:country":"US",
    "sg:address":"230 N 2nd St",
    "sg:city":"Philadelphia",
    "sg:classifiers":[
        {
            "category":"Shopping",
            "subcategory":"Music",
            "type":"Retail Goods"
        }
    ],
    "sg:phone":"+1   ",
    "sg:postcode":"19106",
    "sg:province":"PA",
    "wof:name":"Fairwell Records LLC",
    "wof:placetype":"venue"
},
  "geometry": {"coordinates":[-75.142736,39.954916],"type":"Point"}
}