{
  "type": "Feature",
  "properties": {
    "addr:full":"103 Hoffecker Rd Phoenixville PA 19460",
    "addr:housenumber":"103",
    "addr:postcode":"19460",
    "addr:street":"Hoffecker Rd",
    "iso:country":"US",
    "sg:address":"103 Hoffecker Rd",
    "sg:city":"Phoenixville",
    "sg:classifiers":[
        {
            "category":"Manufacturing",
            "subcategory":"Tools & Machinery",
            "type":"Manufacturing & Wholesale Goods"
        }
    ],
    "sg:phone":"+1 610 495 9930",
    "sg:postcode":"19460",
    "sg:province":"PA",
    "sg:tags":[
        "industry",
        "business",
        "mfg"
    ],
    "wof:name":"Ecosoft Systems Inc",
    "wof:placetype":"venue"
},
  "geometry": {"coordinates":[-75.600363,40.153704],"type":"Point"}
}