{
  "type": "Feature",
  "properties": {
    "iso:country":"US",
    "sg:address":"1029 S Mill St",
    "sg:city":"New Castle",
    "sg:classifiers":[
        {
            "category":"Wholesale",
            "subcategory":"Non-durable Goods",
            "type":"Manufacturing & Wholesale Goods"
        },
        {
            "category":"Shopping",
            "subcategory":"Gifts & Souvenirs",
            "type":"Retail Goods"
        }
    ],
    "sg:phone":"+1 724 652 7600",
    "sg:postcode":"16101",
    "sg:province":"PA",
    "sg:tags":[
        "party",
        "supply"
    ],
    "wof:name":"Keystone Specialty Company",
    "wof:placetype":"venue"
},
  "geometry": {"coordinates":[-80.343862,40.988295],"type":"Point"}
}