{
  "type": "Feature",
  "properties": {
    "iso:country":"US",
    "sg:address":"2913 Walnut St",
    "sg:city":"Mckeesport",
    "sg:classifiers":[
        {
            "category":"Food & Beverages",
            "subcategory":"Fruits & Vegetables",
            "type":"Retail Goods"
        },
        {
            "category":"Wholesale",
            "subcategory":"Fruits & Vegetables",
            "type":"Manufacturing & Wholesale Goods"
        }
    ],
    "sg:phone":"+1 412 672 8229",
    "sg:postcode":"15132",
    "sg:province":"PA",
    "sg:tags":[
        "grocer",
        "produce"
    ],
    "wof:name":"Sunshine Produce",
    "wof:placetype":"venue"
},
  "geometry": {"coordinates":[-79.844669,40.33169],"type":"Point"}
}