{
  "type": "Feature",
  "properties": {
    "addr:full":"204 Woodward Ave Lock Haven PA 17745",
    "addr:housenumber":"204",
    "addr:postcode":"17745",
    "addr:street":"Woodward Ave",
    "iso:country":"US",
    "sg:address":"204 Woodward Ave",
    "sg:city":"Lock Haven",
    "sg:classifiers":[
        {
            "category":"Restaurant",
            "type":"Food & Drink"
        }
    ],
    "sg:phone":"+1 570 748 4307",
    "sg:postcode":"17745",
    "sg:province":"PA",
    "sg:tags":[
        "american"
    ],
    "wof:name":"Second Cup",
    "wof:placetype":"venue"
},
  "geometry": {"coordinates":[-77.423675,41.143848],"type":"Point"}
}