{
  "type": "Feature",
  "properties": {
    "iso:country":"US",
    "sg:address":"1701 Union Blvd",
    "sg:city":"Allentown",
    "sg:classifiers":[
        {
            "category":"Education",
            "subcategory":"Dance Studio",
            "type":"Public Place"
        }
    ],
    "sg:phone":"+1 610 434 2509",
    "sg:postcode":"18109",
    "sg:province":"PA",
    "sg:tags":[
        "instruction",
        "dancing"
    ],
    "wof:name":"Dance Addictions",
    "wof:placetype":"venue"
},
  "geometry": {"coordinates":[-75.429541,40.625339],"type":"Point"}
}