{
  "type": "Feature",
  "properties": {
    "iso:country":"US",
    "sg:address":"411 Clinton Rd",
    "sg:city":"Harrisburg",
    "sg:classifiers":[
        {
            "category":"Government",
            "subcategory":"Post Office",
            "type":"Public Place"
        }
    ],
    "sg:phone":"+1 717 580 7653",
    "sg:postcode":"17109",
    "sg:province":"PA",
    "sg:tags":[
        "delivery",
        "courier"
    ],
    "wof:name":"Bry Fry Knight Inc",
    "wof:placetype":"venue"
},
  "geometry": {"coordinates":[-76.839631,40.293545],"type":"Point"}
}