{
  "type": "Feature",
  "properties": {
    "addr:full":"372 E Main St Bradford PA 16701",
    "addr:housenumber":"372",
    "addr:postcode":"16701",
    "addr:street":"E Main St",
    "iso:country":"US",
    "sg:address":"372 E Main St",
    "sg:city":"Bradford",
    "sg:classifiers":[
        {
            "category":"Retail",
            "subcategory":"Funeral Services",
            "type":"Services"
        }
    ],
    "sg:phone":"+1 814 368 6337",
    "sg:postcode":"16701",
    "sg:province":"PA",
    "sg:tags":[
        "director"
    ],
    "wof:name":"Hollenbeck-Cahill Funeral Home",
    "wof:placetype":"venue"
},
  "geometry": {"coordinates":[-78.627741,41.963848],"type":"Point"}
}