{
  "type": "Feature",
  "properties": {
    "iso:country":"US",
    "sg:address":"576 Churchtown Rd",
    "sg:city":"Honey Brook",
    "sg:classifiers":[
        {
            "category":"Farming",
            "subcategory":"Livestock Farm",
            "type":"Manufacturing & Wholesale Goods"
        }
    ],
    "sg:phone":"+1   ",
    "sg:postcode":"19344",
    "sg:province":"PA",
    "sg:tags":[
        "beef",
        "feedlot",
        "cattle"
    ],
    "wof:name":"Fisher Elam",
    "wof:placetype":"venue"
},
  "geometry": {"coordinates":[-75.947873,40.072555],"type":"Point"}
}