{
  "type": "Feature",
  "properties": {
    "addr:full":"3330 Bristol Rd Bensalem PA 19020",
    "addr:housenumber":"3330",
    "addr:postcode":"19020",
    "addr:street":"Bristol Rd",
    "iso:country":"US",
    "sg:address":"3330 Bristol Rd",
    "sg:city":"Bensalem",
    "sg:classifiers":[
        {
            "category":"Retail",
            "subcategory":"Laundry & Dry Cleaning",
            "type":"Services"
        }
    ],
    "sg:phone":"+1 215 752 8990",
    "sg:postcode":"19020",
    "sg:province":"PA",
    "wof:name":"Bensalem Cleaners",
    "wof:placetype":"venue"
},
  "geometry": {"coordinates":[-74.9431,40.136398],"type":"Point"}
}