{
  "type": "Feature",
  "properties": {
    "iso:country":"US",
    "sg:address":"50 County Line Ln",
    "sg:city":"Newburg",
    "sg:classifiers":[
        {
            "category":"Farming",
            "subcategory":"Nursery",
            "type":"Manufacturing & Wholesale Goods"
        }
    ],
    "sg:phone":"+1 717 423 6182",
    "sg:postcode":"17240",
    "sg:province":"PA",
    "sg:tags":[
        "grower",
        "nursery-wholesale"
    ],
    "wof:name":"Rich View Greenhouse",
    "wof:placetype":"venue"
},
  "geometry": {"coordinates":[-77.590378,40.136929],"type":"Point"}
}