{
  "type": "Feature",
  "properties": {
    "iso:country":"US",
    "sg:address":"100 Commercial St",
    "sg:city":"Bridgeville",
    "sg:classifiers":[
        {
            "category":"Insurance",
            "subcategory":"Hazard Insurance",
            "type":"Services"
        }
    ],
    "sg:phone":"+1 412 257 4803",
    "sg:postcode":"15017",
    "sg:province":"PA",
    "sg:tags":[
        "warranty",
        "automobile",
        "processing"
    ],
    "sg:website":"www.greatlakeswarranty.com",
    "wof:name":"Great Lakes Warranty Corp",
    "wof:placetype":"venue"
},
  "geometry": {"coordinates":[-80.105971,40.362429],"type":"Point"}
}