{
  "type": "Feature",
  "properties": {
    "addr:full":"15865 Dutch St Centerville PA 16404",
    "addr:housenumber":"15865",
    "addr:postcode":"16404",
    "addr:street":"Dutch St",
    "iso:country":"US",
    "sg:address":"15865 Dutch St",
    "sg:city":"Centerville",
    "sg:classifiers":[
        {
            "category":"Real Estate",
            "subcategory":"Real Estate Agent",
            "type":"Services"
        }
    ],
    "sg:phone":"+1   ",
    "sg:postcode":"16404",
    "sg:province":"PA",
    "wof:name":"Norman A Thomas",
    "wof:placetype":"venue"
},
  "geometry": {"coordinates":[-79.78531,41.700233],"type":"Point"}
}