{
  "type": "Feature",
  "properties": {
    "addr:full":"671 Moore Rd King Of Prussia PA 19406",
    "addr:housenumber":"671",
    "addr:postcode":"19406",
    "addr:street":"Moore Rd",
    "iso:country":"US",
    "sg:address":"671 Moore Rd",
    "sg:city":"King Of Prussia",
    "sg:classifiers":[
        {
            "category":"Professional",
            "subcategory":"Engineering",
            "type":"Services"
        }
    ],
    "sg:phone":"+1   ",
    "sg:postcode":"19406",
    "sg:province":"PA",
    "sg:tags":[
        "consulting",
        "engineer"
    ],
    "wof:name":"URS",
    "wof:placetype":"venue"
},
  "geometry": {"coordinates":[-75.41130800000001,40.098003],"type":"Point"}
}