{
  "type": "Feature",
  "properties": {
    "addr:full":"516 Sterner Mill Rd Feasterville Trevose PA 19053",
    "addr:housenumber":"516",
    "addr:postcode":"19053",
    "addr:street":"Sterner Mill Rd",
    "iso:country":"US",
    "sg:address":"516 Sterner Mill Rd",
    "sg:city":"Feasterville Trevose",
    "sg:classifiers":[
        {
            "category":"Freight",
            "type":"Transportation"
        }
    ],
    "sg:phone":"+1   ",
    "sg:postcode":"19053",
    "sg:province":"PA",
    "sg:tags":[
        "operator",
        "trucking"
    ],
    "wof:name":"Delaware Valley Auto Transport",
    "wof:placetype":"venue"
},
  "geometry": {"coordinates":[-74.995474,40.137865],"type":"Point"}
}