{
  "type": "Feature",
  "properties": {
    "iso:country":"US",
    "sg:address":"305 Hummel Ave",
    "sg:city":"Lemoyne",
    "sg:classifiers":[
        {
            "category":"Shopping",
            "subcategory":"Clothing, Apparel, & Fashions",
            "type":"Retail Goods"
        }
    ],
    "sg:phone":"+1 717 909 0684",
    "sg:postcode":"17043",
    "sg:province":"PA",
    "sg:tags":[
        "apparel",
        "women's"
    ],
    "wof:name":"Fabulous Fashions",
    "wof:placetype":"venue"
},
  "geometry": {"coordinates":[-76.891798,40.244388],"type":"Point"}
}