{
  "type": "Feature",
  "properties": {
    "addr:full":"225 E City Ave Bala Cynwyd PA 19004",
    "addr:housenumber":"225",
    "addr:postcode":"19004",
    "addr:street":"E City Ave",
    "iso:country":"US",
    "sg:address":"225 E City Ave",
    "sg:city":"Bala Cynwyd",
    "sg:classifiers":[
        {
            "category":"Social Services",
            "type":"Services"
        }
    ],
    "sg:phone":"+1   ",
    "sg:postcode":"19004",
    "sg:province":"PA",
    "wof:name":"Juvenile Dbetes RES Foundation",
    "wof:placetype":"venue"
},
  "geometry": {"coordinates":[-75.22045799999999,40.004157],"type":"Point"}
}