{
  "type": "Feature",
  "properties": {
    "addr:full":"438 E Girard Ave Philadelphia PA 19125",
    "addr:housenumber":"438",
    "addr:postcode":"19125",
    "addr:street":"E Girard Ave",
    "iso:country":"US",
    "sg:address":"438 E Girard Ave",
    "sg:city":"Philadelphia",
    "sg:classifiers":[
        {
            "category":"Personal",
            "subcategory":"Beauty Salon",
            "type":"Services"
        }
    ],
    "sg:phone":"+1 215 629 2999",
    "sg:postcode":"19125",
    "sg:province":"PA",
    "sg:tags":[
        "cosmetics-wholesale",
        "manufacturer"
    ],
    "sg:website":"http://www.soapsations.com",
    "wof:name":"Beekman's C.O.P.A. Soaps",
    "wof:placetype":"venue"
},
  "geometry": {"coordinates":[-75.12935400000001,39.970542],"type":"Point"}
}