{
  "type": "Feature",
  "properties": {
    "addr:full":"1600 Arch Street Philadelphia PA 19103",
    "addr:housenumber":"1600",
    "addr:postcode":"19103",
    "addr:street":"Arch Street",
    "iso:country":"US",
    "sg:address":"1600 Arch Street",
    "sg:city":"Philadelphia",
    "sg:classifiers":[
        {
            "category":"Personal",
            "subcategory":"Hair Removal",
            "type":"Services"
        }
    ],
    "sg:phone":"+1 215 567 0097",
    "sg:postcode":"19103",
    "sg:province":"PA",
    "sg:website":"lucypeters.com",
    "wof:name":"Lucy Peters International Ltd",
    "wof:placetype":"venue"
},
  "geometry": {"coordinates":[-75.167019,39.954836],"type":"Point"}
}