{
  "type": "Feature",
  "properties": {
    "addr:full":"2721 Cecil B Moore Ave Philadelphia PA 19121",
    "addr:housenumber":"2721",
    "addr:postcode":"19121",
    "addr:street":"Cecil B Moore Ave",
    "iso:country":"US",
    "sg:address":"2721 Cecil B Moore Ave",
    "sg:city":"Philadelphia",
    "sg:classifiers":[
        {
            "category":"Social Services",
            "subcategory":"Child Care",
            "type":"Services"
        }
    ],
    "sg:phone":"+1 215 236 5024",
    "sg:postcode":"19121",
    "sg:province":"PA",
    "sg:tags":[
        "day"
    ],
    "wof:name":"Community Concern N 13 Mltprpse Lrnng & Dy Cre Ctr",
    "wof:placetype":"venue"
},
  "geometry": {"coordinates":[-75.179802,39.9814],"type":"Point"}
}