{
  "type": "Feature",
  "properties": {
    "iso:country":"US",
    "sg:address":"1 Smithfield St",
    "sg:city":"Pittsburgh",
    "sg:classifiers":[
        {
            "category":"Social Services",
            "subcategory":"Child Care",
            "type":"Services"
        }
    ],
    "sg:phone":"+1 412 456 1606",
    "sg:postcode":"15222",
    "sg:province":"PA",
    "sg:tags":[
        "day"
    ],
    "wof:name":"Louise Child Care",
    "wof:placetype":"venue"
},
  "geometry": {"coordinates":[-79.997803,40.443802],"type":"Point"}
}