{
  "type": "Feature",
  "properties": {
    "addr:full":"454 Hilldale Rd Holtwood PA 17532",
    "addr:housenumber":"454",
    "addr:postcode":"17532",
    "addr:street":"Hilldale Rd",
    "iso:country":"US",
    "sg:address":"454 Hilldale Rd",
    "sg:city":"Holtwood",
    "sg:classifiers":[
        {
            "category":"Building & Trades",
            "subcategory":"Construction",
            "type":"Services"
        }
    ],
    "sg:phone":"+1   ",
    "sg:postcode":"17532",
    "sg:province":"PA",
    "sg:tags":[
        "excavation",
        "contractor"
    ],
    "wof:name":"McElroy Contractors LLC",
    "wof:placetype":"venue"
},
  "geometry": {"coordinates":[-76.316479,39.875838],"type":"Point"}
}