{
  "type": "Feature",
  "properties": {
    "iso:country":"US",
    "sg:address":"1349 Shaw Mines Rd",
    "sg:city":"Meyersdale",
    "sg:classifiers":[
        {
            "category":"Education",
            "subcategory":"School",
            "type":"Public Place"
        }
    ],
    "sg:phone":"+1 814 634 8311",
    "sg:postcode":"15552",
    "sg:province":"PA",
    "sg:website":"www.masd.net",
    "wof:name":"Meyersdale Area High School",
    "wof:placetype":"venue"
},
  "geometry": {"coordinates":[-79.04495199999999,39.797424],"type":"Point"}
}