{
  "type": "Feature",
  "properties": {
    "addr:full":"301 Wood St New Bethlehem PA 16242",
    "addr:housenumber":"301",
    "addr:postcode":"16242",
    "addr:street":"Wood St",
    "iso:country":"US",
    "sg:address":"301 Wood St",
    "sg:city":"New Bethlehem",
    "sg:classifiers":[
        {
            "category":"Restaurant",
            "type":"Food & Drink"
        }
    ],
    "sg:phone":"+1 814 275 9707",
    "sg:postcode":"16242",
    "sg:province":"PA",
    "wof:name":"Sirena Pizza",
    "wof:placetype":"venue"
},
  "geometry": {"coordinates":[-79.331451,41.002991],"type":"Point"}
}