{
  "type": "Feature",
  "properties": {
    "addr:full":"933 Penn Ave Pittsburgh PA 15222",
    "addr:housenumber":"933",
    "addr:postcode":"15222",
    "addr:street":"Penn Ave",
    "iso:country":"US",
    "sg:address":"933 Penn Ave",
    "sg:city":"Pittsburgh",
    "sg:classifiers":[
        {
            "category":"Government",
            "subcategory":"Office",
            "type":"Public Place"
        }
    ],
    "sg:phone":"+1   ",
    "sg:postcode":"15222",
    "sg:province":"PA",
    "sg:tags":[
        "operations",
        "compliance",
        "tax",
        "unit",
        "bankruptcy"
    ],
    "wof:name":"Bankruptcy & Compliance Units",
    "wof:placetype":"venue"
},
  "geometry": {"coordinates":[-79.995802,40.444316],"type":"Point"}
}