{
  "type": "Feature",
  "properties": {
    "iso:country":"US",
    "sg:address":"62 Lamppost Ln",
    "sg:city":"Lancaster",
    "sg:classifiers":[
        {
            "category":"Retail",
            "subcategory":"Portrait Studio",
            "type":"Services"
        }
    ],
    "sg:phone":"+1 717 464 1554",
    "sg:postcode":"17602",
    "sg:province":"PA",
    "sg:tags":[
        "photographer"
    ],
    "wof:name":"Steve's Photography",
    "wof:placetype":"venue"
},
  "geometry": {"coordinates":[-76.24467300000001,40.00083],"type":"Point"}
}