{
  "type": "Feature",
  "properties": {
    "iso:country":"US",
    "sg:address":"405 Frederick Ave",
    "sg:city":"Sewickley",
    "sg:classifiers":[
        {
            "category":"Place Of Worship",
            "subcategory":"Church",
            "type":"Public Place"
        },
        {
            "category":"Place Of Worship",
            "type":"Public Place"
        }
    ],
    "sg:phone":"+1 412 741 1790",
    "sg:postcode":"15143",
    "sg:province":"PA",
    "sg:tags":[
        "churches-episcopal-anglican",
        "churches-episcopal"
    ],
    "wof:name":"Needle's Eye, The",
    "wof:placetype":"venue"
},
  "geometry": {"coordinates":[-80.184234,40.538874],"type":"Point"}
}