{
  "type": "Feature",
  "properties": {
    "iso:country":"US",
    "sg:address":"3425 E Market St",
    "sg:city":"York",
    "sg:classifiers":[
        {
            "category":"Retail",
            "subcategory":"Repair Shop",
            "type":"Services"
        }
    ],
    "sg:phone":"+1 717 757 0608",
    "sg:postcode":"17402",
    "sg:province":"PA",
    "sg:tags":[
        "screen"
    ],
    "wof:name":"York Associates",
    "wof:placetype":"venue"
},
  "geometry": {"coordinates":[-76.65297099999999,39.982046],"type":"Point"}
}