{
  "type": "Feature",
  "properties": {
    "addr:full":"5738 Smithfield St Mckeesport PA 15135",
    "addr:housenumber":"5738",
    "addr:postcode":"15135",
    "addr:street":"Smithfield St",
    "iso:country":"US",
    "sg:address":"5738 Smithfield St",
    "sg:city":"Mckeesport",
    "sg:classifiers":[
        {
            "category":"Autos & Motor Vehicles",
            "subcategory":"Fuel & Gas Station",
            "type":"Retail Goods"
        }
    ],
    "sg:phone":"+1 412 754 1490",
    "sg:postcode":"15135",
    "sg:province":"PA",
    "wof:name":"Burke Lee's Filling Station",
    "wof:placetype":"venue"
},
  "geometry": {"coordinates":[-79.825761,40.310952],"type":"Point"}
}