{
  "type": "Feature",
  "properties": {
    "iso:country":"US",
    "sg:address":"104 Bettys Ln",
    "sg:city":"Montgomeryville",
    "sg:classifiers":[
        {
            "category":"Retail",
            "subcategory":"Auto Rental",
            "type":"Services"
        }
    ],
    "sg:phone":"+1 215 855 2005",
    "sg:postcode":"18936",
    "sg:province":"PA",
    "sg:tags":[
        "car"
    ],
    "wof:name":"A-A-A Auto Rental",
    "wof:placetype":"venue"
},
  "geometry": {"coordinates":[-75.230003,40.229198],"type":"Point"}
}