{
  "type": "Feature",
  "properties": {
    "iso:country":"US",
    "sg:address":"1005 Brookside Rd",
    "sg:city":"Allentown",
    "sg:classifiers":[
        {
            "category":"Real Estate",
            "subcategory":"Real Estate Agent",
            "type":"Services"
        }
    ],
    "sg:phone":"+1 610 395 5195",
    "sg:postcode":"18106",
    "sg:province":"PA",
    "sg:tags":[
        "appraiser"
    ],
    "wof:name":"Star Appraisers",
    "wof:placetype":"venue"
},
  "geometry": {"coordinates":[-75.553545,40.562123],"type":"Point"}
}