{
  "type": "Feature",
  "properties": {
    "addr:full":"306 Wexford Ct Aston PA 19014",
    "addr:housenumber":"306",
    "addr:postcode":"19014",
    "addr:street":"Wexford Ct Aston",
    "iso:country":"US",
    "sg:address":"306 Wexford Ct",
    "sg:city":"Aston",
    "sg:classifiers":[
        {
            "category":"Wholesale",
            "subcategory":"Hardware",
            "type":"Manufacturing & Wholesale Goods"
        }
    ],
    "sg:phone":"+1 610 558 1518",
    "sg:postcode":"19014",
    "sg:province":"PA",
    "sg:tags":[
        "purifying",
        "cleaning",
        "air"
    ],
    "wof:name":"Pristine Air Environment",
    "wof:placetype":"venue"
},
  "geometry": {"coordinates":[-75.435362,39.884568],"type":"Point"}
}