{
  "type": "Feature",
  "properties": {
    "iso:country":"US",
    "sg:address":"875 Upland Ave ",
    "sg:city":"Chester",
    "sg:classifiers":[
        {
            "category":"Restaurant",
            "type":"Food & Drink"
        }
    ],
    "sg:menulink":"http://www.allmenus.com/pa/upland/287212-great-wall-chinese-restaurant/menu/",
    "sg:phone":"+1 610 872 0330",
    "sg:postcode":"19013",
    "sg:province":"PA",
    "sg:tags":[
        "asian",
        "chinese"
    ],
    "wof:name":"Great Wall Chinese Restaurant",
    "wof:placetype":"venue"
},
  "geometry": {"coordinates":[-75.37466499999999,39.85727],"type":"Point"}
}