{
  "type": "Feature",
  "properties": {
    "iso:country":"US",
    "sg:address":"800 W State St",
    "sg:city":"Doylestown",
    "sg:classifiers":[
        {
            "category":"Health Services",
            "subcategory":"Doctor",
            "type":"Services"
        }
    ],
    "sg:phone":"+1 215 348 3936",
    "sg:postcode":"18901",
    "sg:province":"PA",
    "sg:tags":[
        "orthopedist"
    ],
    "wof:name":"Handy Robert W MD",
    "wof:placetype":"venue"
},
  "geometry": {"coordinates":[-75.147386,40.302969],"type":"Point"}
}