{
  "type": "Feature",
  "properties": {
    "iso:country":"US",
    "sg:address":"2700 Saucon Valley Rd",
    "sg:city":"Center Valley",
    "sg:classifiers":[
        {
            "category":"Retail",
            "subcategory":"Auto Rental",
            "type":"Services"
        }
    ],
    "sg:phone":"+1 610 791 2388",
    "sg:postcode":"18034",
    "sg:province":"PA",
    "sg:tags":[
        "renting",
        "truck",
        "leasing"
    ],
    "wof:name":"Budget Truck Rental",
    "wof:placetype":"venue"
},
  "geometry": {"coordinates":[-75.40540300000001,40.557562],"type":"Point"}
}