{
  "type": "Feature",
  "properties": {
    "iso:country":"US",
    "sg:address":"215 Bittersweet Dr",
    "sg:city":"Hershey",
    "sg:classifiers":[
        {
            "category":"Health Services",
            "subcategory":"Doctor",
            "type":"Services"
        }
    ],
    "sg:phone":"+1   ",
    "sg:postcode":"17033",
    "sg:province":"PA",
    "wof:name":"Donald E Santry DMD",
    "wof:placetype":"venue"
},
  "geometry": {"coordinates":[-76.65636499999999,40.242451],"type":"Point"}
}