{
  "type": "Feature",
  "properties": {
    "addr:full":"559 Crestview Dr Transfer PA 16154",
    "addr:housenumber":"559",
    "addr:postcode":"16154",
    "addr:street":"Crestview Dr",
    "iso:country":"US",
    "sg:address":"559 Crestview Dr",
    "sg:city":"Transfer",
    "sg:classifiers":[
        {
            "category":"Travel",
            "subcategory":"Campground",
            "type":"Entertainment"
        }
    ],
    "sg:phone":"+1 724 962 9800",
    "sg:postcode":"16154",
    "sg:province":"PA",
    "sg:tags":[
        "trailer"
    ],
    "wof:name":"Shenango Valley Rv Park",
    "wof:placetype":"venue"
},
  "geometry": {"coordinates":[-80.394524,41.342124],"type":"Point"}
}