{
  "type": "Feature",
  "properties": {
    "iso:country":"US",
    "sg:address":"1050 N Mountain Rd",
    "sg:city":"Harrisburg",
    "sg:classifiers":[
        {
            "category":"Shopping",
            "type":"Retail Goods"
        },
        {
            "category":"Retail",
            "subcategory":"Animal Services",
            "type":"Services"
        }
    ],
    "sg:phone":"+1 717 545 0605",
    "sg:postcode":"17112",
    "sg:province":"PA",
    "sg:tags":[
        "pet",
        "shop"
    ],
    "wof:name":"Lower Paxton Pet Parlor Dog",
    "wof:placetype":"venue"
},
  "geometry": {"coordinates":[-76.79128,40.336197],"type":"Point"}
}