{
  "type": "Feature",
  "properties": {
    "iso:country":"US",
    "sg:address":"37 W Main St",
    "sg:city":"Bloomsburg",
    "sg:classifiers":[
        {
            "category":"Banks & Credit Unions",
            "subcategory":"Bank",
            "type":"Services"
        }
    ],
    "sg:phone":"+1 570 784 1144",
    "sg:postcode":"17815",
    "sg:province":"PA",
    "wof:name":"FNB Bank",
    "wof:placetype":"venue"
},
  "geometry": {"coordinates":[-76.45723099999999,41.002934],"type":"Point"}
}