{
  "type": "Feature",
  "properties": {
    "addr:full":"1021 Pontiac Rd Drexel Hill PA 19026",
    "addr:housenumber":"1021",
    "addr:postcode":"19026",
    "addr:street":"Pontiac Rd",
    "iso:country":"US",
    "sg:address":"1021 Pontiac Rd",
    "sg:city":"Drexel Hill",
    "sg:classifiers":[
        {
            "category":"Health Services",
            "subcategory":"Doctor",
            "type":"Services"
        }
    ],
    "sg:phone":"+1   ",
    "sg:postcode":"19026",
    "sg:province":"PA",
    "wof:name":"Dennis A Quagliariello DDS",
    "wof:placetype":"venue"
},
  "geometry": {"coordinates":[-75.324229,39.95445],"type":"Point"}
}