{
  "type": "Feature",
  "properties": {
    "iso:country":"US",
    "sg:address":"215 Church St",
    "sg:city":"Brownsville",
    "sg:classifiers":[
        {
            "category":"Organizations",
            "subcategory":"Religious Organization",
            "type":"Services"
        }
    ],
    "sg:phone":"+1   ",
    "sg:postcode":"15417",
    "sg:province":"PA",
    "wof:name":"Maranatha Assembly of God",
    "wof:placetype":"venue"
},
  "geometry": {"coordinates":[-79.880534,40.023888],"type":"Point"}
}