{
  "type": "Feature",
  "properties": {
    "addr:full":"1911 S Braddock Ave Pittsburgh PA 15218",
    "addr:housenumber":"1911",
    "addr:postcode":"15218",
    "addr:street":"S Braddock Ave",
    "iso:country":"US",
    "sg:address":"1911 S Braddock Ave",
    "sg:city":"Pittsburgh",
    "sg:classifiers":[
        {
            "category":"Restaurant",
            "type":"Food & Drink"
        }
    ],
    "sg:menulink":"http://www.allmenus.com/pa/swissvale/175447-arbys/menu/",
    "sg:phone":"+1 412 351 5100",
    "sg:postcode":"15218",
    "sg:province":"PA",
    "sg:tags":[
        "burger",
        "american"
    ],
    "wof:name":"Arby's",
    "wof:placetype":"venue"
},
  "geometry": {"coordinates":[-79.885741,40.422558],"type":"Point"}
}