{
  "type": "Feature",
  "properties": {
    "addr:full":"1508 Bakerstown Rd Tarentum PA 15084",
    "addr:housenumber":"1508",
    "addr:postcode":"15084",
    "addr:street":"Bakerstown Rd",
    "iso:country":"US",
    "sg:address":"1508 Bakerstown Rd",
    "sg:city":"Tarentum",
    "sg:classifiers":[
        {
            "category":"Organizations",
            "subcategory":"Community Association",
            "type":"Services"
        }
    ],
    "sg:phone":"+1   ",
    "sg:postcode":"15084",
    "sg:province":"PA",
    "wof:name":"Optimist International",
    "wof:placetype":"venue"
},
  "geometry": {"coordinates":[-79.77363699999999,40.607165],"type":"Point"}
}