{
  "type": "Feature",
  "properties": {
    "addr:full":"1510 Hooker Rd Karns City PA 16041",
    "addr:housenumber":"1510",
    "addr:postcode":"16041",
    "addr:street":"Hooker Rd",
    "iso:country":"US",
    "sg:address":"1510 Hooker Rd",
    "sg:city":"Karns City",
    "sg:classifiers":[
        {
            "category":"Manufacturing",
            "subcategory":"Printing",
            "type":"Manufacturing & Wholesale Goods"
        }
    ],
    "sg:phone":"+1 724 756 5545",
    "sg:postcode":"16041",
    "sg:province":"PA",
    "sg:tags":[
        "lithographic",
        "printer",
        "commercial"
    ],
    "wof:name":"Don Slabe Printing",
    "wof:placetype":"venue"
},
  "geometry": {"coordinates":[-79.744955,40.995193],"type":"Point"}
}