{
  "type": "Feature",
  "properties": {
    "iso:country":"US",
    "sg:address":"2117 W Main St",
    "sg:city":"Norristown",
    "sg:classifiers":[
        {
            "category":"Food & Beverages",
            "subcategory":"Bakery",
            "type":"Retail Goods"
        }
    ],
    "sg:phone":"+1 610 630 9180",
    "sg:postcode":"19403",
    "sg:province":"PA",
    "sg:tags":[
        "sandwich"
    ],
    "wof:name":"Pudge's II Jeffersonville",
    "wof:placetype":"venue"
},
  "geometry": {"coordinates":[-75.382301,40.135899],"type":"Point"}
}