{
  "type": "Feature",
  "properties": {
    "iso:country":"US",
    "sg:address":"1856 Delmar Dr ",
    "sg:city":"Folcroft",
    "sg:classifiers":[
        {
            "category":"Restaurant",
            "type":"Food & Drink"
        }
    ],
    "sg:menulink":"http://www.allmenus.com/pa/folcroft/291576-lafayette-pizza/menu/",
    "sg:phone":"+1 610 327 9800",
    "sg:postcode":"19032",
    "sg:province":"PA",
    "sg:tags":[
        "seafood",
        "sandwich",
        "salad"
    ],
    "wof:name":"Lafayette Pizza",
    "wof:placetype":"venue"
},
  "geometry": {"coordinates":[-75.28285099999999,39.892268],"type":"Point"}
}