{
  "type": "Feature",
  "properties": {
    "addr:full":"1524 Lincoln Way White Oak PA 15131",
    "addr:housenumber":"1524",
    "addr:postcode":"15131",
    "addr:street":"Lincoln Way",
    "iso:country":"US",
    "sg:address":"1524 Lincoln Way",
    "sg:city":"White Oak",
    "sg:classifiers":[
        {
            "category":"Professional",
            "subcategory":"Accounting & Tax Preparation",
            "type":"Services"
        }
    ],
    "sg:phone":"+1 412 672 3210",
    "sg:postcode":"15131",
    "sg:province":"PA",
    "sg:tags":[
        "accountant"
    ],
    "wof:name":"Jayson L Weinberg CPA",
    "wof:placetype":"venue"
},
  "geometry": {"coordinates":[-79.817549,40.348346],"type":"Point"}
}