{
  "type": "Feature",
  "properties": {
    "addr:full":"4804 Chester Ave Philadelphia PA 19143",
    "addr:housenumber":"4804",
    "addr:postcode":"19143",
    "addr:street":"Chester Ave",
    "iso:country":"US",
    "sg:address":"4804 Chester Ave",
    "sg:city":"Philadelphia",
    "sg:classifiers":[
        {
            "category":"Social Services",
            "subcategory":"Job Training",
            "type":"Services"
        }
    ],
    "sg:phone":"+1 215 724 5618",
    "sg:postcode":"19143",
    "sg:province":"PA",
    "sg:tags":[
        "rehabilitation"
    ],
    "wof:name":"Friends Rehabilitation Program",
    "wof:placetype":"venue"
},
  "geometry": {"coordinates":[-75.21643,39.944152],"type":"Point"}
}