{
  "type": "Feature",
  "properties": {
    "iso:country":"US",
    "sg:address":"12 W Newport Rd",
    "sg:city":"Lititz",
    "sg:classifiers":[
        {
            "category":"Restaurant",
            "type":"Food & Drink"
        }
    ],
    "sg:phone":"+1   ",
    "sg:postcode":"17543",
    "sg:province":"PA",
    "sg:tags":[
        "eating"
    ],
    "wof:name":"Lititz Fmly Cupboard Restauran",
    "wof:placetype":"venue"
},
  "geometry": {"coordinates":[-76.31066199999999,40.177111],"type":"Point"}
}