{
  "type": "Feature",
  "properties": {
    "addr:full":"1611 Peach St Erie PA 16501",
    "addr:housenumber":"1611",
    "addr:postcode":"16501",
    "addr:street":"Peach St",
    "iso:country":"US",
    "sg:address":"1611 Peach St",
    "sg:city":"Erie",
    "sg:classifiers":[
        {
            "category":"Banks & Credit Unions",
            "subcategory":"Investment Brokerage",
            "type":"Services"
        }
    ],
    "sg:phone":"+1 814 459 7071",
    "sg:postcode":"16501",
    "sg:province":"PA",
    "sg:tags":[
        "security"
    ],
    "wof:name":"Linsco Private Ledger",
    "wof:placetype":"venue"
},
  "geometry": {"coordinates":[-80.07977099999999,42.118778],"type":"Point"}
}