{
  "type": "Feature",
  "properties": {
    "iso:country":"US",
    "sg:address":"224 Moore St",
    "sg:city":"Philadelphia",
    "sg:classifiers":[
        {
            "category":"Manufacturing",
            "subcategory":"Wood Products",
            "type":"Manufacturing & Wholesale Goods"
        }
    ],
    "sg:phone":"+1 215 339 5333",
    "sg:postcode":"19148",
    "sg:province":"PA",
    "sg:tags":[
        "picture",
        "frame"
    ],
    "wof:name":"Madd Frames",
    "wof:placetype":"venue"
},
  "geometry": {"coordinates":[-75.151489,39.925666],"type":"Point"}
}