{
  "type": "Feature",
  "properties": {
    "iso:country":"US",
    "sg:address":"13149 Ridge Rd",
    "sg:city":"North Huntingdon",
    "sg:classifiers":[
        {
            "category":"Health Services",
            "subcategory":"Doctor",
            "type":"Services"
        }
    ],
    "sg:phone":"+1 724 287 0099",
    "sg:postcode":"15642",
    "sg:province":"PA",
    "sg:tags":[
        "dentist"
    ],
    "wof:name":"Denture Center",
    "wof:placetype":"venue"
},
  "geometry": {"coordinates":[-79.763014,40.317042],"type":"Point"}
}