{
  "type": "Feature",
  "properties": {
    "iso:country":"US",
    "sg:address":"152 Bender Mill Rd",
    "sg:city":"Lancaster",
    "sg:classifiers":[
        {
            "category":"Building & Trades",
            "subcategory":"Plumbing",
            "type":"Services"
        }
    ],
    "sg:phone":"+1   ",
    "sg:postcode":"17603",
    "sg:province":"PA",
    "sg:tags":[
        "air",
        "heating",
        "conditioning",
        "contractor"
    ],
    "wof:name":"J & G Heating & AC",
    "wof:placetype":"venue"
},
  "geometry": {"coordinates":[-76.39913199999999,39.994442],"type":"Point"}
}