{
  "type": "Feature",
  "properties": {
    "iso:country":"US",
    "sg:address":"615 Park Ave",
    "sg:city":"Hershey",
    "sg:classifiers":[
        {
            "category":"Fast Food",
            "type":"Food & Drink"
        }
    ],
    "sg:phone":"+1 717 312 1126",
    "sg:postcode":"17033",
    "sg:province":"PA",
    "sg:website":"www.wendys.com",
    "wof:name":"Wendy's",
    "wof:placetype":"venue"
},
  "geometry": {"coordinates":[-76.652225,40.294023],"type":"Point"}
}