{
  "type": "Feature",
  "properties": {
    "iso:country":"US",
    "sg:address":"4801 Hazel Ave",
    "sg:city":"Feastervl Trvs",
    "sg:classifiers":[
        {
            "category":"Home & Garden",
            "subcategory":"Household Appliances",
            "type":"Retail Goods"
        }
    ],
    "sg:phone":"+1 215 942 8930",
    "sg:postcode":"19053",
    "sg:province":"PA",
    "wof:name":"Overlander's",
    "wof:placetype":"venue"
},
  "geometry": {"coordinates":[-74.974891,40.150104],"type":"Point"}
}