{
  "type": "Feature",
  "properties": {
    "iso:country":"US",
    "sg:address":"86 W Union St",
    "sg:city":"Canton",
    "sg:classifiers":[
        {
            "category":"Bars & Pubs",
            "type":"Food & Drink"
        }
    ],
    "sg:phone":"+1   ",
    "sg:postcode":"17724",
    "sg:province":"PA",
    "sg:tags":[
        "drinking",
        "operation"
    ],
    "wof:name":"Park Hotel Paystation",
    "wof:placetype":"venue"
},
  "geometry": {"coordinates":[-76.859544,41.655536],"type":"Point"}
}