{
  "type": "Feature",
  "properties": {
    "addr:full":"196 Tabey Rd Mill Run PA 15464",
    "addr:housenumber":"196",
    "addr:postcode":"15464",
    "addr:street":"Tabey Rd",
    "iso:country":"US",
    "sg:address":"196 Tabey Rd",
    "sg:city":"Mill Run",
    "sg:classifiers":[
        {
            "category":"Retail",
            "subcategory":"Repair Shop",
            "type":"Services"
        }
    ],
    "sg:phone":"+1 724 455 2225",
    "sg:postcode":"15464",
    "sg:province":"PA",
    "sg:tags":[
        "taxidermist"
    ],
    "wof:name":"Laurel Mountain Taxidermy",
    "wof:placetype":"venue"
},
  "geometry": {"coordinates":[-79.414947,39.966064],"type":"Point"}
}