{
  "type": "Feature",
  "properties": {
    "addr:full":"112 Bonnie Ln Hollidaysburg PA 16648",
    "addr:housenumber":"112",
    "addr:postcode":"16648",
    "addr:street":"Bonnie Ln",
    "iso:country":"US",
    "sg:address":"112 Bonnie Ln",
    "sg:city":"Hollidaysburg",
    "sg:classifiers":[
        {
            "category":"Real Estate",
            "subcategory":"Real Estate Agent",
            "type":"Services"
        }
    ],
    "sg:phone":"+1   ",
    "sg:postcode":"16648",
    "sg:province":"PA",
    "wof:name":"Roland R Sleek Sr",
    "wof:placetype":"venue"
},
  "geometry": {"coordinates":[-78.368094,40.44271],"type":"Point"}
}