{
  "type": "Feature",
  "properties": {
    "iso:country":"US",
    "sg:address":"454 Acorn Ln",
    "sg:city":"Downingtown",
    "sg:classifiers":[
        {
            "category":"Shopping",
            "subcategory":"Clothing, Apparel, & Fashions",
            "type":"Retail Goods"
        }
    ],
    "sg:phone":"+1 610 269 1036",
    "sg:postcode":"19335",
    "sg:province":"PA",
    "sg:tags":[
        "uniform"
    ],
    "sg:website":"http://www.dynamicteamsports.com",
    "wof:name":"Cycle Venture",
    "wof:placetype":"venue"
},
  "geometry": {"coordinates":[-75.694131,40.006128],"type":"Point"}
}