{
  "type": "Feature",
  "properties": {
    "iso:country":"US",
    "sg:address":"429 Frystown Rd",
    "sg:city":"Myerstown",
    "sg:classifiers":[
        {
            "category":"Sports & Exercise",
            "subcategory":"Gym",
            "type":"Entertainment"
        }
    ],
    "sg:phone":"+1 717 933 5337",
    "sg:postcode":"17067",
    "sg:province":"PA",
    "sg:tags":[
        "club",
        "health",
        "studio",
        "gymnasium"
    ],
    "wof:name":"Shape Shoppe",
    "wof:placetype":"venue"
},
  "geometry": {"coordinates":[-76.32953999999999,40.450046],"type":"Point"}
}