{
  "type": "Feature",
  "properties": {
    "iso:country":"US",
    "sg:address":"8500 Brooktree Rd",
    "sg:city":"Wexford",
    "sg:classifiers":[
        {
            "category":"Professional",
            "subcategory":"Employment Agencies",
            "type":"Services"
        }
    ],
    "sg:phone":"+1   ",
    "sg:postcode":"15090",
    "sg:province":"PA",
    "sg:tags":[
        "help",
        "supply"
    ],
    "wof:name":"Manpower",
    "wof:placetype":"venue"
},
  "geometry": {"coordinates":[-80.057526,40.614207],"type":"Point"}
}