{
  "type": "Feature",
  "properties": {
    "iso:country":"US",
    "sg:address":"3636 N Marshall St",
    "sg:city":"Philadelphia",
    "sg:classifiers":[
        {
            "category":"Retail",
            "subcategory":"Animal Services",
            "type":"Services"
        }
    ],
    "sg:phone":"+1 215 225 4250",
    "sg:postcode":"19140",
    "sg:province":"PA",
    "wof:name":"Philadelphia K-9 Academy",
    "wof:placetype":"venue"
},
  "geometry": {"coordinates":[-75.139827,40.007184],"type":"Point"}
}