{
  "type": "Feature",
  "properties": {
    "addr:full":"1500 N Hills Ave Willow Grove PA 19090",
    "addr:housenumber":"1500",
    "addr:postcode":"19090",
    "addr:street":"N Hills Ave",
    "iso:country":"US",
    "sg:address":"1500 N Hills Ave",
    "sg:city":"Willow Grove",
    "sg:classifiers":[
        {
            "category":"Social Services",
            "subcategory":"Child Care",
            "type":"Services"
        }
    ],
    "sg:phone":"+1 215 657 1699",
    "sg:postcode":"19090",
    "sg:province":"PA",
    "sg:tags":[
        "kindergarten",
        "academic",
        "school"
    ],
    "wof:name":"Reform Church Nursery School",
    "wof:placetype":"venue"
},
  "geometry": {"coordinates":[-75.141685,40.14227],"type":"Point"}
}