{
  "type": "Feature",
  "properties": {
    "addr:full":"270 Geiger Rd Philadelphia PA 19115",
    "addr:housenumber":"270",
    "addr:postcode":"19115",
    "addr:street":"Geiger Rd",
    "iso:country":"US",
    "sg:address":"270 Geiger Rd",
    "sg:city":"Philadelphia",
    "sg:classifiers":[
        {
            "category":"Wholesale",
            "subcategory":"Electrical",
            "type":"Manufacturing & Wholesale Goods"
        }
    ],
    "sg:phone":"+1   ",
    "sg:postcode":"19115",
    "sg:province":"PA",
    "sg:tags":[
        "equipment"
    ],
    "wof:name":"Main Line Fire & Security",
    "wof:placetype":"venue"
},
  "geometry": {"coordinates":[-75.044735,40.106445],"type":"Point"}
}