{
  "type": "Feature",
  "properties": {
    "iso:country":"US",
    "sg:address":"501 Corporate Dr",
    "sg:city":"Canonsburg",
    "sg:classifiers":[
        {
            "category":"Health Services",
            "subcategory":"Dentist",
            "type":"Services"
        }
    ],
    "sg:phone":"+1 724 746 5020",
    "sg:postcode":"15317",
    "sg:province":"PA",
    "wof:name":"Southpointe Dentistry",
    "wof:placetype":"venue"
},
  "geometry": {"coordinates":[-80.17269899999999,40.297501],"type":"Point"}
}