{
  "type": "Feature",
  "properties": {
    "iso:country":"US",
    "sg:address":"1054 E Lycoming St",
    "sg:city":"Philadelphia",
    "sg:classifiers":[
        {
            "category":"Restaurant",
            "type":"Food & Drink"
        }
    ],
    "sg:phone":"+1 215 289 2855",
    "sg:postcode":"19124",
    "sg:province":"PA",
    "sg:tags":[
        "delicatessen"
    ],
    "wof:name":"Juniata Super Mart",
    "wof:placetype":"venue"
},
  "geometry": {"coordinates":[-75.106612,40.00966],"type":"Point"}
}