{
  "type": "Feature",
  "properties": {
    "iso:country":"US",
    "sg:address":"1 Sandy Dr",
    "sg:city":"Morrisville",
    "sg:classifiers":[
        {
            "category":"Professional",
            "subcategory":"Management & Consulting",
            "type":"Services"
        }
    ],
    "sg:phone":"+1   ",
    "sg:postcode":"19067",
    "sg:province":"PA",
    "sg:tags":[
        "tobacco",
        "direct",
        "sales",
        "p",
        "news",
        "retail"
    ],
    "wof:name":"Pennsylvania News",
    "wof:placetype":"venue"
},
  "geometry": {"coordinates":[-74.818833,40.207994],"type":"Point"}
}