{
  "type": "Feature",
  "properties": {
    "iso:country":"US",
    "sg:address":"1128 State Rte 56",
    "sg:city":"Apollo",
    "sg:classifiers":[
        {
            "category":"Building & Trades",
            "subcategory":"Electrical",
            "type":"Services"
        }
    ],
    "sg:phone":"+1   ",
    "sg:postcode":"15613",
    "sg:province":"PA",
    "sg:tags":[
        "electrical",
        "contractor"
    ],
    "wof:name":"Frickes Electric",
    "wof:placetype":"venue"
},
  "geometry": {"coordinates":[-79.56449499999999,40.590179],"type":"Point"}
}