{
  "type": "Feature",
  "properties": {
    "iso:country":"US",
    "sg:address":"3900 N Franklin St",
    "sg:city":"Philadelphia",
    "sg:classifiers":[
        {
            "category":"Food & Beverages",
            "subcategory":"Groceries & Convenience Stores",
            "type":"Retail Goods"
        }
    ],
    "sg:phone":"+1 215 229 0826",
    "sg:postcode":"19140",
    "sg:province":"PA",
    "wof:name":"Ramo Grocery",
    "wof:placetype":"venue"
},
  "geometry": {"coordinates":[-75.140612,40.011047],"type":"Point"}
}