{
  "type": "Feature",
  "properties": {
    "iso:country":"US",
    "sg:address":"631 Brinker Ave",
    "sg:city":"Latrobe",
    "sg:classifiers":[
        {
            "category":"Professional",
            "type":"Services"
        }
    ],
    "sg:phone":"+1   ",
    "sg:postcode":"15650",
    "sg:province":"PA",
    "wof:name":"Grand Chapter of Pennsylv",
    "wof:placetype":"venue"
},
  "geometry": {"coordinates":[-79.37820000000001,40.319498],"type":"Point"}
}