{
  "type": "Feature",
  "properties": {
    "addr:full":"316 East St Bloomsburg PA 17815",
    "addr:housenumber":"316",
    "addr:postcode":"17815",
    "addr:street":"East St",
    "iso:country":"US",
    "sg:address":"316 East St",
    "sg:city":"Bloomsburg",
    "sg:classifiers":[
        {
            "category":"Real Estate",
            "subcategory":"Real Estate Agent",
            "type":"Services"
        }
    ],
    "sg:phone":"+1   ",
    "sg:postcode":"17815",
    "sg:province":"PA",
    "wof:name":"Fritz Real Estate",
    "wof:placetype":"venue"
},
  "geometry": {"coordinates":[-76.451632,41.003149],"type":"Point"}
}