{
  "type": "Feature",
  "properties": {
    "iso:country":"US",
    "sg:address":"1100 E Lancaster Ave",
    "sg:city":"Downingtown",
    "sg:classifiers":[
        {
            "category":"Social Services",
            "type":"Services"
        }
    ],
    "sg:phone":"+1 610 466 9780",
    "sg:postcode":"19335",
    "sg:province":"PA",
    "sg:tags":[
        "organization",
        "welfare"
    ],
    "wof:name":"Chester County Cares",
    "wof:placetype":"venue"
},
  "geometry": {"coordinates":[-75.675738,40.018974],"type":"Point"}
}