{
  "type": "Feature",
  "properties": {
    "iso:country":"US",
    "sg:address":"1226 Perry Hwy",
    "sg:city":"Mercer",
    "sg:classifiers":[
        {
            "category":"Restaurant",
            "type":"Food & Drink"
        }
    ],
    "sg:phone":"+1   ",
    "sg:postcode":"16137",
    "sg:province":"PA",
    "sg:tags":[
        "eating"
    ],
    "wof:name":"Springfield Restaurant Group",
    "wof:placetype":"venue"
},
  "geometry": {"coordinates":[-80.23218,41.174418],"type":"Point"}
}