{
  "type": "Feature",
  "properties": {
    "addr:full":"201 W Front St Frnt Media PA 19063",
    "addr:housenumber":"201",
    "addr:postcode":"19063",
    "addr:street":"W Front St",
    "iso:country":"US",
    "sg:address":"201 W Front St Frnt",
    "sg:city":"Media",
    "sg:classifiers":[
        {
            "category":"Government",
            "subcategory":"Office",
            "type":"Public Place"
        }
    ],
    "sg:phone":"+1 610 874 8780",
    "sg:postcode":"19063",
    "sg:province":"PA",
    "sg:tags":[
        "parish",
        "government-county"
    ],
    "sg:website":"http://www.manoafire.com",
    "wof:name":"Office Of Consumer Affairs",
    "wof:placetype":"venue"
},
  "geometry": {"coordinates":[-75.38542200000001,39.918289],"type":"Point"}
}