{
  "type": "Feature",
  "properties": {
    "addr:full":"385 W Bridge St New Hope PA 18938",
    "addr:housenumber":"385",
    "addr:postcode":"18938",
    "addr:street":"W Bridge St",
    "iso:country":"US",
    "sg:address":"385 W Bridge St",
    "sg:city":"New Hope",
    "sg:classifiers":[
        {
            "category":"Travel",
            "subcategory":"Hotels & Motels",
            "type":"Entertainment"
        },
        {
            "category":"Restaurant",
            "type":"Food & Drink"
        }
    ],
    "sg:phone":"+1 215 862 2081",
    "sg:postcode":"18938",
    "sg:province":"PA",
    "sg:website":"www.theravennewhope.com",
    "wof:name":"The Raven",
    "wof:placetype":"venue"
},
  "geometry": {"coordinates":[-74.96731200000001,40.362031],"type":"Point"}
}