{
  "type": "Feature",
  "properties": {
    "iso:country":"US",
    "sg:address":"31 S 3rd St",
    "sg:city":"Philadelphia",
    "sg:classifiers":[
        {
            "category":"Shopping",
            "subcategory":"Gifts & Souvenirs",
            "type":"Retail Goods"
        },
        {
            "category":"Shopping",
            "subcategory":"Florist",
            "type":"Retail Goods"
        }
    ],
    "sg:phone":"+1 215 925 2882",
    "sg:postcode":"19106",
    "sg:province":"PA",
    "sg:tags":[
        "basket",
        "shop"
    ],
    "sg:website":"http://www.oldcityflowers.com",
    "wof:name":"Old City Flowers",
    "wof:placetype":"venue"
},
  "geometry": {"coordinates":[-75.145866,39.949329],"type":"Point"}
}