{
  "type": "Feature",
  "properties": {
    "iso:country":"US",
    "sg:address":"341 Palmer St",
    "sg:city":"Plymouth",
    "sg:classifiers":[
        {
            "category":"Building & Trades",
            "subcategory":"Construction",
            "type":"Services"
        }
    ],
    "sg:phone":"+1   ",
    "sg:postcode":"18651",
    "sg:province":"PA",
    "sg:tags":[
        "remodeling",
        "contractor"
    ],
    "wof:name":"McManus Construction",
    "wof:placetype":"venue"
},
  "geometry": {"coordinates":[-75.938928,41.244025],"type":"Point"}
}