{
  "type": "Feature",
  "properties": {
    "addr:full":"13277 Leslie Rd Meadville PA 16335",
    "addr:housenumber":"13277",
    "addr:postcode":"16335",
    "addr:street":"Leslie Rd",
    "iso:country":"US",
    "sg:address":"13277 Leslie Rd",
    "sg:city":"Meadville",
    "sg:classifiers":[
        {
            "category":"Organizations",
            "subcategory":"Community Association",
            "type":"Services"
        }
    ],
    "sg:phone":"+1   ",
    "sg:postcode":"16335",
    "sg:province":"PA",
    "wof:name":"Delta Kappa Gamma Society",
    "wof:placetype":"venue"
},
  "geometry": {"coordinates":[-80.114051,41.652555],"type":"Point"}
}