{
  "type": "Feature",
  "properties": {
    "iso:country":"US",
    "sg:address":"801 N 8th St",
    "sg:city":"Philadelphia",
    "sg:classifiers":[
        {
            "category":"Place Of Worship",
            "subcategory":"Church",
            "type":"Public Place"
        },
        {
            "category":"Place Of Worship",
            "type":"Public Place"
        }
    ],
    "sg:phone":"+1 215 829 4350",
    "sg:postcode":"19123",
    "sg:province":"PA",
    "sg:tags":[
        "churches-catholic-traditional",
        "churches-catholic"
    ],
    "wof:name":"Ukranian Cathedral Cafeteria",
    "wof:placetype":"venue"
},
  "geometry": {"coordinates":[-75.15107,39.96553],"type":"Point"}
}