{
  "type": "Feature",
  "properties": {
    "addr:full":"410 Blossom Dr Mount Wolf PA 17347",
    "addr:housenumber":"410",
    "addr:postcode":"17347",
    "addr:street":"Blossom Dr",
    "iso:country":"US",
    "sg:address":"410 Blossom Dr",
    "sg:city":"Mount Wolf",
    "sg:classifiers":[
        {
            "category":"Shopping",
            "subcategory":"Catalog Store",
            "type":"Retail Goods"
        }
    ],
    "sg:phone":"+1   ",
    "sg:postcode":"17347",
    "sg:province":"PA",
    "sg:tags":[
        "indoor",
        "sales",
        "air",
        "filter",
        "internet",
        "quality"
    ],
    "wof:name":"Furnace Filter Warehouse LLP",
    "wof:placetype":"venue"
},
  "geometry": {"coordinates":[-76.69069399999999,40.044747],"type":"Point"}
}