{
  "type": "Feature",
  "properties": {
    "iso:country":"US",
    "sg:address":"98 Highland Ave",
    "sg:city":"Oaks",
    "sg:classifiers":[
        {
            "category":"Professional",
            "subcategory":"Printing & Photocopies",
            "type":"Services"
        }
    ],
    "sg:phone":"+1 610 666 9285",
    "sg:postcode":"19403",
    "sg:province":"PA",
    "sg:tags":[
        "duplicating",
        "copying"
    ],
    "wof:name":"Partners Press",
    "wof:placetype":"venue"
},
  "geometry": {"coordinates":[-75.398494,40.152297],"type":"Point"}
}