{
  "type": "Feature",
  "properties": {
    "iso:country":"US",
    "sg:address":"769 Humphreys Rd",
    "sg:city":"Ardmore",
    "sg:phone":"+1 610 613 6927",
    "sg:postcode":"19003",
    "sg:province":"PA",
    "wof:name":"17 Mile",
    "wof:placetype":"venue"
},
  "geometry": {"coordinates":[-75.29792,39.999329],"type":"Point"}
}