{
  "type": "Feature",
  "properties": {
    "iso:country":"US",
    "sg:address":"2092 Long Level Rd",
    "sg:city":"Wrightsville",
    "sg:classifiers":[
        {
            "category":"Shopping",
            "subcategory":"Bicycles & Sporting Goods",
            "type":"Retail Goods"
        }
    ],
    "sg:phone":"+1 717 252 1616",
    "sg:postcode":"17368",
    "sg:province":"PA",
    "wof:name":"Shank's Mare Outfitters",
    "wof:placetype":"venue"
},
  "geometry": {"coordinates":[-76.492181,39.970065],"type":"Point"}
}