{
  "type": "Feature",
  "properties": {
    "addr:full":"221 7th St Pittsburgh PA 15238",
    "addr:housenumber":"221",
    "addr:postcode":"15238",
    "addr:street":"7Th St",
    "iso:country":"US",
    "sg:address":"221 7th St",
    "sg:city":"Pittsburgh",
    "sg:classifiers":[
        {
            "category":"Professional",
            "subcategory":"Computer Services",
            "type":"Services"
        }
    ],
    "sg:phone":"+1   ",
    "sg:postcode":"15238",
    "sg:province":"PA",
    "sg:tags":[
        "engineering",
        "programing",
        "custom"
    ],
    "wof:name":"I squared T",
    "wof:placetype":"venue"
},
  "geometry": {"coordinates":[-79.863026,40.491652],"type":"Point"}
}