{
  "type": "Feature",
  "properties": {
    "iso:country":"US",
    "sg:address":"528 2nd Street Pike",
    "sg:city":"Southampton",
    "sg:classifiers":[
        {
            "category":"Restaurant",
            "type":"Food & Drink"
        }
    ],
    "sg:phone":"+1   ",
    "sg:postcode":"18966",
    "sg:province":"PA",
    "wof:name":"Robin Hood of Southampton Inc",
    "wof:placetype":"venue"
},
  "geometry": {"coordinates":[-75.044697,40.171603],"type":"Point"}
}