{
  "type": "Feature",
  "properties": {
    "addr:full":"474 Pike Rd Huntingdon Vly PA 19006",
    "addr:housenumber":"474",
    "addr:postcode":"19006",
    "addr:street":"Pike Rd",
    "iso:country":"US",
    "sg:address":"474 Pike Rd",
    "sg:city":"Huntingdon Vly",
    "sg:classifiers":[
        {
            "category":"Manufacturing",
            "subcategory":"Metals",
            "type":"Manufacturing & Wholesale Goods"
        }
    ],
    "sg:phone":"+1 215 355 0708",
    "sg:postcode":"19006",
    "sg:province":"PA",
    "sg:tags":[
        "coating"
    ],
    "wof:name":"Penn Protective Coatings Corp",
    "wof:placetype":"venue"
},
  "geometry": {"coordinates":[-75.025437,40.149333],"type":"Point"}
}