{
  "type": "Feature",
  "properties": {
    "iso:country":"US",
    "sg:address":"143 Backbone Rd",
    "sg:city":"Claysville",
    "sg:classifiers":[
        {
            "category":"Recreation",
            "subcategory":"Dog Park",
            "type":"Entertainment"
        },
        {
            "category":"Shopping",
            "subcategory":"Pets & Pet Supplies",
            "type":"Retail Goods"
        },
        {
            "category":"Retail",
            "subcategory":"Pet Boarding",
            "type":"Services"
        },
        {
            "category":"Retail",
            "subcategory":"Animal Services",
            "type":"Services"
        }
    ],
    "sg:phone":"+1 724 663 3647",
    "sg:postcode":"15323",
    "sg:province":"PA",
    "sg:tags":[
        "training",
        "exercising",
        "kennel",
        "sitting"
    ],
    "wof:name":"Crosswinds K 9",
    "wof:placetype":"venue"
},
  "geometry": {"coordinates":[-80.461868,40.182838],"type":"Point"}
}