{
  "type": "Feature",
  "properties": {
    "iso:country":"US",
    "sg:address":"141 Smith Rd",
    "sg:city":"Sarver",
    "sg:classifiers":[
        {
            "category":"Building & Trades",
            "subcategory":"Construction",
            "type":"Services"
        }
    ],
    "sg:phone":"+1 724 353 2334",
    "sg:postcode":"16055",
    "sg:province":"PA",
    "sg:tags":[
        "excavation",
        "excavating",
        "work",
        "contractor"
    ],
    "wof:name":"T C & T R Kelley Excavating",
    "wof:placetype":"venue"
},
  "geometry": {"coordinates":[-79.730628,40.732485],"type":"Point"}
}