{
  "type": "Feature",
  "properties": {
    "iso:country":"US",
    "sg:address":"4 Ferndale Rd",
    "sg:city":"New Philadelphia",
    "sg:classifiers":[
        {
            "category":"Building & Trades",
            "subcategory":"Construction",
            "type":"Services"
        }
    ],
    "sg:phone":"+1   ",
    "sg:postcode":"17959",
    "sg:province":"PA",
    "sg:tags":[
        "concrete",
        "contractor"
    ],
    "wof:name":"Ed Yeneshosky Contracting",
    "wof:placetype":"venue"
},
  "geometry": {"coordinates":[-76.11070599999999,40.717665],"type":"Point"}
}