{
  "type": "Feature",
  "properties": {
    "iso:country":"US",
    "sg:address":"5041 Frankford Ave",
    "sg:city":"Philadelphia",
    "sg:classifiers":[
        {
            "category":"Personal",
            "subcategory":"Beauty Salon",
            "type":"Services"
        }
    ],
    "sg:phone":"+1 215 744 4885",
    "sg:postcode":"19124",
    "sg:province":"PA",
    "sg:tags":[
        "shop"
    ],
    "wof:name":"African American Hair Braiding",
    "wof:placetype":"venue"
},
  "geometry": {"coordinates":[-75.07991800000001,40.020832],"type":"Point"}
}