{
  "type": "Feature",
  "properties": {
    "addr:full":"1900 Washington Rd Pittsburgh PA 15241",
    "addr:housenumber":"1900",
    "addr:postcode":"15241",
    "addr:street":"Washington Rd",
    "iso:country":"US",
    "sg:address":"1900 Washington Rd",
    "sg:city":"Pittsburgh",
    "sg:classifiers":[
        {
            "category":"Food & Beverages",
            "subcategory":"Specialty",
            "type":"Retail Goods"
        }
    ],
    "sg:phone":"+1 412 835 9624",
    "sg:postcode":"15241",
    "sg:province":"PA",
    "sg:tags":[
        "health",
        "diet"
    ],
    "wof:name":"General Nutrition Ctr",
    "wof:placetype":"venue"
},
  "geometry": {"coordinates":[-80.057187,40.34619],"type":"Point"}
}