{
  "type": "Feature",
  "properties": {
    "addr:full":"1414 E Cedar St Allentown PA 18109",
    "addr:housenumber":"1414",
    "addr:postcode":"18109",
    "addr:street":"E Cedar St",
    "iso:country":"US",
    "sg:address":"1414 E Cedar St",
    "sg:city":"Allentown",
    "sg:classifiers":[
        {
            "category":"Education",
            "subcategory":"School",
            "type":"Public Place"
        }
    ],
    "sg:phone":"+1 610 821 9443",
    "sg:postcode":"18109",
    "sg:province":"PA",
    "sg:website":"www.lvchs.org",
    "wof:name":"Lehigh Valley Christian High School",
    "wof:placetype":"venue"
},
  "geometry": {"coordinates":[-75.43229700000001,40.6231],"type":"Point"}
}