{
  "type": "Feature",
  "properties": {
    "addr:full":"1677 Georgetown Rd Sandy Lake PA 16145",
    "addr:housenumber":"1677",
    "addr:postcode":"16145",
    "addr:street":"Georgetown Rd",
    "iso:country":"US",
    "sg:address":"1677 Georgetown Rd",
    "sg:city":"Sandy Lake",
    "sg:classifiers":[
        {
            "category":"Farming",
            "subcategory":"Dairy Farm",
            "type":"Manufacturing & Wholesale Goods"
        }
    ],
    "sg:phone":"+1   ",
    "sg:postcode":"16145",
    "sg:province":"PA",
    "wof:name":"Andrew Helmuth Farm",
    "wof:placetype":"venue"
},
  "geometry": {"coordinates":[-80.081532,41.411705],"type":"Point"}
}