{
  "type": "Feature",
  "properties": {
    "iso:country":"US",
    "sg:address":"501 E Main St",
    "sg:city":"Wilkes Barre",
    "sg:classifiers":[
        {
            "category":"Banks & Credit Unions",
            "subcategory":"Bank",
            "type":"Services"
        }
    ],
    "sg:phone":"+1   ",
    "sg:postcode":"18702",
    "sg:province":"PA",
    "sg:tags":[
        "state"
    ],
    "wof:name":"Area 1 Carpenters Credit Un",
    "wof:placetype":"venue"
},
  "geometry": {"coordinates":[-75.82341599999999,41.266041],"type":"Point"}
}