{
  "type": "Feature",
  "properties": {
    "iso:country":"US",
    "sg:address":"2976 E State St",
    "sg:city":"Hermitage",
    "sg:classifiers":[
        {
            "category":"Building & Trades",
            "subcategory":"Equipment Rental",
            "type":"Services"
        },
        {
            "category":"Building & Trades",
            "subcategory":"Construction",
            "type":"Services"
        }
    ],
    "sg:phone":"+1 724 981 5800",
    "sg:postcode":"16148",
    "sg:province":"PA",
    "sg:tags":[
        "yard",
        "scaffolding",
        "lift",
        "aerial",
        "store",
        "contractors'"
    ],
    "sg:website":"http://equipmentrentaloptions.com",
    "wof:name":"Equipment Rental Options",
    "wof:placetype":"venue"
},
  "geometry": {"coordinates":[-80.454666,41.233379],"type":"Point"}
}