{
  "type": "Feature",
  "properties": {
    "iso:country":"US",
    "sg:address":"7 S Main St",
    "sg:city":"Shickshinny",
    "sg:classifiers":[
        {
            "category":"Health Services",
            "subcategory":"Doctor",
            "type":"Services"
        }
    ],
    "sg:phone":"+1   ",
    "sg:postcode":"18655",
    "sg:province":"PA",
    "sg:tags":[
        "medical"
    ],
    "wof:name":"Devon R Poesnecker",
    "wof:placetype":"venue"
},
  "geometry": {"coordinates":[-76.150521,41.152804],"type":"Point"}
}