{
  "type": "Feature",
  "properties": {
    "iso:country":"US",
    "sg:address":"308 Main St",
    "sg:city":"Royersford",
    "sg:classifiers":[
        {
            "category":"Banks & Credit Unions",
            "subcategory":"Bank",
            "type":"Services"
        }
    ],
    "sg:phone":"+1 610 948 3400",
    "sg:postcode":"19468",
    "sg:province":"PA",
    "wof:name":"Superior Credit Union",
    "wof:placetype":"venue"
},
  "geometry": {"coordinates":[-75.53907599999999,40.185255],"type":"Point"}
}