{
  "type": "Feature",
  "properties": {
    "addr:full":"109 N Chester Pike Glenolden PA 19036",
    "addr:housenumber":"109",
    "addr:postcode":"19036",
    "addr:street":"N Chester Pike",
    "iso:country":"US",
    "sg:address":"109 N Chester Pike",
    "sg:city":"Glenolden",
    "sg:classifiers":[
        {
            "category":"Home & Garden",
            "subcategory":"Carpets & Floor Coverings",
            "type":"Retail Goods"
        }
    ],
    "sg:phone":"+1 610 586 3222",
    "sg:postcode":"19036",
    "sg:province":"PA",
    "sg:tags":[
        "dealer",
        "rug"
    ],
    "wof:name":"Dogum Rugs & Carpets Co",
    "wof:placetype":"venue"
},
  "geometry": {"coordinates":[-75.286041,39.901824],"type":"Point"}
}