{
  "type": "Feature",
  "properties": {
    "iso:country":"US",
    "sg:address":"11561 Hwy 285",
    "sg:city":"Conneaut Lake",
    "sg:classifiers":[
        {
            "category":"Farming",
            "subcategory":"Dairy Farm",
            "type":"Manufacturing & Wholesale Goods"
        }
    ],
    "sg:phone":"+1 814 382 3245",
    "sg:postcode":"16316",
    "sg:province":"PA",
    "wof:name":"Allen Farms",
    "wof:placetype":"venue"
},
  "geometry": {"coordinates":[-80.28788,41.574376],"type":"Point"}
}