{
  "type": "Feature",
  "properties": {
    "iso:country":"US",
    "sg:address":"77 W High St",
    "sg:city":"Pottstown",
    "sg:classifiers":[
        {
            "category":"Building & Trades",
            "subcategory":"Equipment Rental",
            "type":"Services"
        }
    ],
    "sg:phone":"+1 610 970 7368",
    "sg:postcode":"19464",
    "sg:province":"PA",
    "sg:tags":[
        "yard"
    ],
    "wof:name":"Total Rental",
    "wof:placetype":"venue"
},
  "geometry": {"coordinates":[-75.659088,40.247343],"type":"Point"}
}