{
  "type": "Feature",
  "properties": {
    "iso:country":"US",
    "sg:address":"22 Colonial Rd",
    "sg:city":"Harrisburg",
    "sg:classifiers":[
        {
            "category":"Shopping",
            "subcategory":"Hobbies, Toys, & Games",
            "type":"Retail Goods"
        }
    ],
    "sg:phone":"+1 717 540 0368",
    "sg:postcode":"17109",
    "sg:province":"PA",
    "sg:tags":[
        "toy",
        "store"
    ],
    "sg:website":"www.toysrus.com",
    "wof:name":"Toys R Us",
    "wof:placetype":"venue"
},
  "geometry": {"coordinates":[-76.82092400000001,40.299081],"type":"Point"}
}