{
  "type": "Feature",
  "properties": {
    "iso:country":"US",
    "sg:address":"200 S 43rd St",
    "sg:city":"Philadelphia",
    "sg:classifiers":[
        {
            "category":"Restaurant",
            "type":"Food & Drink"
        }
    ],
    "sg:menulink":"http://www.allmenus.com/pa/philadelphia/18745-pasquallys-pasta-and-pizza/menu/",
    "sg:phone":"+1 215 387 6100",
    "sg:postcode":"19104",
    "sg:province":"PA",
    "sg:tags":[
        "sandwich",
        "cheesesteaks",
        "burger",
        "american",
        "chicken",
        "pizza",
        "wing",
        "italian"
    ],
    "wof:name":"Pasquallys Pasta and Pizza",
    "wof:placetype":"venue"
},
  "geometry": {"coordinates":[-75.210629,39.972028],"type":"Point"}
}