{
  "type": "Feature",
  "properties": {
    "addr:full":"115 N Broad St Doylestown PA 18901",
    "addr:housenumber":"115",
    "addr:postcode":"18901",
    "addr:street":"N Broad St",
    "iso:country":"US",
    "sg:address":"115 N Broad St",
    "sg:city":"Doylestown",
    "sg:classifiers":[
        {
            "category":"Professional",
            "subcategory":"Accounting & Tax Preparation",
            "type":"Services"
        }
    ],
    "sg:phone":"+1 215 348 9268",
    "sg:postcode":"18901",
    "sg:province":"PA",
    "sg:tags":[
        "bookkeeping",
        "general"
    ],
    "wof:name":"Biz Visors Inc",
    "wof:placetype":"venue"
},
  "geometry": {"coordinates":[-75.129994,40.312729],"type":"Point"}
}