{
  "type": "Feature",
  "properties": {
    "iso:country":"US",
    "sg:address":"5163 National Pike",
    "sg:city":"Markleysburg",
    "sg:classifiers":[
        {
            "category":"Professional",
            "subcategory":"Detective & Security Services",
            "type":"Services"
        }
    ],
    "sg:phone":"+1 724 329 2155",
    "sg:postcode":"15459",
    "sg:province":"PA",
    "sg:tags":[
        "investigator"
    ],
    "wof:name":"Pre Employment Screening",
    "wof:placetype":"venue"
},
  "geometry": {"coordinates":[-79.45646000000001,39.7632],"type":"Point"}
}