{
  "type": "Feature",
  "properties": {
    "iso:country":"US",
    "sg:address":"2691 Johnson Dr",
    "sg:city":"Chambersburg",
    "sg:classifiers":[
        {
            "category":"Wholesale",
            "subcategory":"Machinery & Supplies",
            "type":"Manufacturing & Wholesale Goods"
        }
    ],
    "sg:phone":"+1 717 709 1091",
    "sg:postcode":"17201",
    "sg:province":"PA",
    "sg:tags":[
        "machine",
        "tool"
    ],
    "wof:name":"Geisinger Machine Svc Inc",
    "wof:placetype":"venue"
},
  "geometry": {"coordinates":[-77.659547,39.989101],"type":"Point"}
}