{
  "type": "Feature",
  "properties": {
    "iso:country":"US",
    "sg:address":"16 Ann St",
    "sg:city":"West Pittston",
    "sg:classifiers":[
        {
            "category":"Retail",
            "subcategory":"Portrait Studio",
            "type":"Services"
        }
    ],
    "sg:phone":"+1 570 655 9944",
    "sg:postcode":"18643",
    "sg:province":"PA",
    "sg:tags":[
        "photographer"
    ],
    "wof:name":"Clarke Studios",
    "wof:placetype":"venue"
},
  "geometry": {"coordinates":[-75.796179,41.336124],"type":"Point"}
}