{
  "type": "Feature",
  "properties": {
    "iso:country":"US",
    "sg:address":"2712 Center St",
    "sg:city":"Pittsburgh",
    "sg:classifiers":[
        {
            "category":"Personal",
            "subcategory":"Nail Salon",
            "type":"Services"
        }
    ],
    "sg:phone":"+1 412 922 7981",
    "sg:postcode":"15205",
    "sg:province":"PA",
    "wof:name":"Fingers and Toes Nail Sa",
    "wof:placetype":"venue"
},
  "geometry": {"coordinates":[-80.064871,40.444165],"type":"Point"}
}