{
  "type": "Feature",
  "properties": {
    "addr:full":"106 Burton Ave Washington PA 15301",
    "addr:housenumber":"106",
    "addr:postcode":"15301",
    "addr:street":"Burton Ave",
    "iso:country":"US",
    "sg:address":"106 Burton Ave",
    "sg:city":"Washington",
    "sg:classifiers":[
        {
            "category":"Building & Trades",
            "subcategory":"Construction",
            "type":"Services"
        }
    ],
    "sg:phone":"+1   ",
    "sg:postcode":"15301",
    "sg:province":"PA",
    "sg:tags":[
        "contractor"
    ],
    "wof:name":"Reihner Contracting",
    "wof:placetype":"venue"
},
  "geometry": {"coordinates":[-80.244608,40.175638],"type":"Point"}
}