{
  "type": "Feature",
  "properties": {
    "iso:country":"US",
    "sg:address":"955 Mearns Rd",
    "sg:city":"Warminster",
    "sg:classifiers":[
        {
            "category":"Professional",
            "subcategory":"Engineering",
            "type":"Services"
        }
    ],
    "sg:phone":"+1 215 672 3200",
    "sg:postcode":"18974",
    "sg:province":"PA",
    "sg:tags":[
        "engineer"
    ],
    "wof:name":"Veridian Engineering",
    "wof:placetype":"venue"
},
  "geometry": {"coordinates":[-75.08335599999999,40.213173],"type":"Point"}
}