{
  "type": "Feature",
  "properties": {
    "addr:full":"707 River St Peckville PA 18452",
    "addr:housenumber":"707",
    "addr:postcode":"18452",
    "addr:street":"River St",
    "iso:country":"US",
    "sg:address":"707 River St",
    "sg:city":"Peckville",
    "sg:classifiers":[
        {
            "category":"Wholesale",
            "subcategory":"Home Furnishings",
            "type":"Manufacturing & Wholesale Goods"
        },
        {
            "category":"Wholesale",
            "subcategory":"Durable Goods & Equipment",
            "type":"Manufacturing & Wholesale Goods"
        }
    ],
    "sg:phone":"+1 570 489 8696",
    "sg:postcode":"18452",
    "sg:province":"PA",
    "sg:tags":[
        "basket",
        "importer",
        "floor",
        "covering"
    ],
    "wof:name":"International Basket Co",
    "wof:placetype":"venue"
},
  "geometry": {"coordinates":[-75.57716600000001,41.478147],"type":"Point"}
}