{
  "type": "Feature",
  "properties": {
    "iso:country":"US",
    "sg:address":"815 Heather Pl",
    "sg:city":"Pittsburgh",
    "sg:classifiers":[
        {
            "category":"Professional",
            "subcategory":"Computer Services",
            "type":"Services"
        }
    ],
    "sg:phone":"+1 412 369 9880",
    "sg:postcode":"15237",
    "sg:province":"PA",
    "sg:tags":[
        "consultant",
        "designer"
    ],
    "wof:name":"Arcadia System Integrators",
    "wof:placetype":"venue"
},
  "geometry": {"coordinates":[-80.023067,40.574216],"type":"Point"}
}