{
  "type": "Feature",
  "properties": {
    "iso:country":"US",
    "sg:address":"9 S Mercer St",
    "sg:city":"Greenville",
    "sg:classifiers":[
        {
            "category":"Building & Trades",
            "subcategory":"Construction",
            "type":"Services"
        }
    ],
    "sg:phone":"+1   ",
    "sg:postcode":"16125",
    "sg:province":"PA",
    "sg:tags":[
        "new",
        "family",
        "home"
    ],
    "wof:name":"BMW Development Corp",
    "wof:placetype":"venue"
},
  "geometry": {"coordinates":[-80.387321,41.405172],"type":"Point"}
}