{
  "type": "Feature",
  "properties": {
    "iso:country":"US",
    "sg:address":"4391 Richmond St",
    "sg:city":"Philadelphia",
    "sg:classifiers":[
        {
            "category":"Autos & Motor Vehicles",
            "subcategory":"Fuel & Gas Station",
            "type":"Retail Goods"
        }
    ],
    "sg:phone":"+1 215 744 3343",
    "sg:postcode":"19137",
    "sg:province":"PA",
    "sg:tags":[
        "oil"
    ],
    "wof:name":"Dom's Auto Svc Ctr",
    "wof:placetype":"venue"
},
  "geometry": {"coordinates":[-75.07380499999999,39.997002],"type":"Point"}
}