{
  "type": "Feature",
  "properties": {
    "iso:country":"US",
    "sg:address":"1213 W 28th St",
    "sg:city":"Erie",
    "sg:classifiers":[
        {
            "category":"Retail",
            "subcategory":"Car Wash",
            "type":"Services"
        }
    ],
    "sg:phone":"+1 814 864 9120",
    "sg:postcode":"16508",
    "sg:province":"PA",
    "sg:tags":[
        "truck",
        "cleaning"
    ],
    "wof:name":"Aquatronic Mobile Pressure",
    "wof:placetype":"venue"
},
  "geometry": {"coordinates":[-80.097177,42.10116],"type":"Point"}
}