{
  "type": "Feature",
  "properties": {
    "iso:country":"US",
    "sg:address":"210 3rd Ave",
    "sg:city":"Lock Haven",
    "sg:classifiers":[
        {
            "category":"Building & Trades",
            "subcategory":"Equipment Rental",
            "type":"Services"
        }
    ],
    "sg:phone":"+1 570 748 6331",
    "sg:postcode":"17745",
    "sg:province":"PA",
    "sg:tags":[
        "heavy",
        "construction",
        "yard"
    ],
    "wof:name":"Ron's Rental",
    "wof:placetype":"venue"
},
  "geometry": {"coordinates":[-77.46281399999999,41.130645],"type":"Point"}
}