{
  "type": "Feature",
  "properties": {
    "addr:full":"227 Hathaway St E Girard PA 16417",
    "addr:housenumber":"227",
    "addr:postcode":"16417",
    "addr:street":"Hathaway St E",
    "iso:country":"US",
    "sg:address":"227 Hathaway St E",
    "sg:city":"Girard",
    "sg:classifiers":[
        {
            "category":"Shopping",
            "subcategory":"Bicycles & Sporting Goods",
            "type":"Retail Goods"
        }
    ],
    "sg:phone":"+1 814 774 9494",
    "sg:postcode":"16417",
    "sg:province":"PA",
    "sg:tags":[
        "equipment",
        "golf",
        "supply"
    ],
    "wof:name":"Pinhawk Golf Shop",
    "wof:placetype":"venue"
},
  "geometry": {"coordinates":[-80.318951,42.008564],"type":"Point"}
}