{
  "type": "Feature",
  "properties": {
    "iso:country":"US",
    "sg:address":"398 Grandview Rd",
    "sg:city":"Curwensville",
    "sg:classifiers":[
        {
            "category":"Place Of Worship",
            "subcategory":"Church",
            "type":"Public Place"
        },
        {
            "category":"Place Of Worship",
            "type":"Public Place"
        }
    ],
    "sg:phone":"+1 814 236 0810",
    "sg:postcode":"16833",
    "sg:province":"PA",
    "sg:tags":[
        "churches-interdenominational",
        "denomination",
        "churches-various",
        "churches-non-denominational"
    ],
    "wof:name":"Faith Bible Church",
    "wof:placetype":"venue"
},
  "geometry": {"coordinates":[-78.584584,40.929039],"type":"Point"}
}