{
  "type": "Feature",
  "properties": {
    "addr:full":"301 Market St Bangor PA 18013",
    "addr:housenumber":"301",
    "addr:postcode":"18013",
    "addr:street":"Market St",
    "iso:country":"US",
    "sg:address":"301 Market St",
    "sg:city":"Bangor",
    "sg:classifiers":[
        {
            "category":"Organizations",
            "subcategory":"Religious Organization",
            "type":"Services"
        }
    ],
    "sg:phone":"+1 610 588 4536",
    "sg:postcode":"18013",
    "sg:province":"PA",
    "sg:tags":[
        "church"
    ],
    "wof:name":"St John's United Church-Christ",
    "wof:placetype":"venue"
},
  "geometry": {"coordinates":[-75.209439,40.867124],"type":"Point"}
}