{
  "type": "Feature",
  "properties": {
    "iso:country":"US",
    "sg:address":"170 Old Route 22",
    "sg:city":"Jonestown",
    "sg:classifiers":[
        {
            "category":"Retail",
            "subcategory":"Auto Repair",
            "type":"Services"
        },
        {
            "category":"Local Transit",
            "type":"Transportation"
        }
    ],
    "sg:phone":"+1 717 865 9427",
    "sg:postcode":"17038",
    "sg:province":"PA",
    "sg:tags":[
        "equipment",
        "removal",
        "trailers-repair",
        "snow"
    ],
    "wof:name":"Jonestown Ag Repair",
    "wof:placetype":"venue"
},
  "geometry": {"coordinates":[-76.463684,40.422894],"type":"Point"}
}