{
  "type": "Feature",
  "properties": {
    "addr:full":"1010 Hazleton Apartment West Hazleton PA 18202",
    "addr:housenumber":"1010;apartment",
    "addr:postcode":"18202",
    "addr:street":"West",
    "iso:country":"US",
    "sg:address":"1010 Hazleton Apartment",
    "sg:city":"West Hazleton",
    "sg:classifiers":[
        {
            "category":"Professional",
            "type":"Services"
        }
    ],
    "sg:phone":"+1 570 459 9901",
    "sg:postcode":"18202",
    "sg:province":"PA",
    "sg:tags":[
        "establishment"
    ],
    "wof:name":"Harry's U Pull It",
    "wof:placetype":"venue"
},
  "geometry": {"coordinates":[-75.98398,40.975447],"type":"Point"}
}