{
  "type": "Feature",
  "properties": {
    "addr:full":"997 S Lewis Rd Collegeville PA 19426",
    "addr:housenumber":"997",
    "addr:postcode":"19426",
    "addr:street":"S Lewis Rd",
    "iso:country":"US",
    "sg:address":"997 S Lewis Rd",
    "sg:city":"Collegeville",
    "sg:classifiers":[
        {
            "category":"Manufacturing",
            "subcategory":"Printing",
            "type":"Manufacturing & Wholesale Goods"
        }
    ],
    "sg:phone":"+1 610 489 4203",
    "sg:postcode":"19426",
    "sg:province":"PA",
    "sg:tags":[
        "commercial"
    ],
    "wof:name":"Spectrum Graphics",
    "wof:placetype":"venue"
},
  "geometry": {"coordinates":[-75.495499,40.190753],"type":"Point"}
}