{
  "type": "Feature",
  "properties": {
    "iso:country":"US",
    "sg:address":"342 Depot St",
    "sg:city":"St Marys",
    "sg:classifiers":[
        {
            "category":"Personal",
            "subcategory":"Beauty Salon",
            "type":"Services"
        },
        {
            "category":"Sports & Exercise",
            "subcategory":"Gym",
            "type":"Entertainment"
        }
    ],
    "sg:phone":"+1 814 834 3843",
    "sg:postcode":"15857",
    "sg:province":"PA",
    "sg:tags":[
        "shop",
        "fitness",
        "physical",
        "facility"
    ],
    "wof:name":"Circuit Zone",
    "wof:placetype":"venue"
},
  "geometry": {"coordinates":[-78.556468,41.429777],"type":"Point"}
}