{
  "type": "Feature",
  "properties": {
    "addr:full":"1501 E Lycoming St Philadelphia PA 19124",
    "addr:housenumber":"1501",
    "addr:postcode":"19124",
    "addr:street":"E Lycoming St",
    "iso:country":"US",
    "sg:address":"1501 E Lycoming St",
    "sg:city":"Philadelphia",
    "sg:classifiers":[
        {
            "category":"Government",
            "subcategory":"Office",
            "type":"Public Place"
        }
    ],
    "sg:phone":"+1   ",
    "sg:postcode":"19124",
    "sg:province":"PA",
    "sg:tags":[
        "laboratory",
        "air",
        "pollution"
    ],
    "wof:name":"Phila Health Dept-AMS Lab",
    "wof:placetype":"venue"
},
  "geometry": {"coordinates":[-75.097717,40.008564],"type":"Point"}
}