{
  "type": "Feature",
  "properties": {
    "iso:country":"US",
    "sg:address":"2306 Bedford Ave",
    "sg:city":"Pittsburgh",
    "sg:classifiers":[
        {
            "category":"Real Estate",
            "subcategory":"Developer",
            "type":"Services"
        }
    ],
    "sg:phone":"+1 412 681 9421",
    "sg:postcode":"15219",
    "sg:province":"PA",
    "wof:name":"Bedford Partnership",
    "wof:placetype":"venue"
},
  "geometry": {"coordinates":[-79.974627,40.449714],"type":"Point"}
}