{
  "type": "Feature",
  "properties": {
    "iso:country":"US",
    "sg:address":"9259 Springboro Rd",
    "sg:city":"Springboro",
    "sg:classifiers":[
        {
            "category":"Government",
            "subcategory":"Office",
            "type":"Public Place"
        }
    ],
    "sg:phone":"+1 814 587 3199",
    "sg:postcode":"16435",
    "sg:province":"PA",
    "sg:tags":[
        "city",
        "taxation"
    ],
    "wof:name":"Spring Twp Assessor",
    "wof:placetype":"venue"
},
  "geometry": {"coordinates":[-80.35421599999999,41.801128],"type":"Point"}
}