{
  "type": "Feature",
  "properties": {
    "addr:full":"37 Northwood Rd Newtown Square PA 19073",
    "addr:housenumber":"37",
    "addr:postcode":"19073",
    "addr:street":"Northwood Rd",
    "iso:country":"US",
    "sg:address":"37 Northwood Rd",
    "sg:city":"Newtown Square",
    "sg:classifiers":[
        {
            "category":"Freight",
            "type":"Transportation"
        }
    ],
    "sg:phone":"+1   ",
    "sg:postcode":"19073",
    "sg:province":"PA",
    "sg:tags":[
        "operator",
        "local",
        "trucking"
    ],
    "wof:name":"Thomas E Ford",
    "wof:placetype":"venue"
},
  "geometry": {"coordinates":[-75.37829000000001,39.987116],"type":"Point"}
}