{
  "type": "Feature",
  "properties": {
    "addr:full":"204 N Constitution Ave New Freedom PA 17349",
    "addr:housenumber":"204",
    "addr:postcode":"17349",
    "addr:street":"N Constitution Ave",
    "iso:country":"US",
    "sg:address":"204 N Constitution Ave",
    "sg:city":"New Freedom",
    "sg:classifiers":[
        {
            "category":"Home & Garden",
            "subcategory":"Furniture",
            "type":"Retail Goods"
        }
    ],
    "sg:phone":"+1 717 235 6356",
    "sg:postcode":"17349",
    "sg:province":"PA",
    "wof:name":"Once Again Home Furnishings",
    "wof:placetype":"venue"
},
  "geometry": {"coordinates":[-76.69500499999999,39.741735],"type":"Point"}
}