{
  "type": "Feature",
  "properties": {
    "iso:country":"US",
    "sg:address":"40 E Court St",
    "sg:city":"Doylestown",
    "sg:classifiers":[
        {
            "category":"Professional",
            "subcategory":"Lawyer & Legal Services",
            "type":"Services"
        }
    ],
    "sg:phone":"+1 215 348 3183",
    "sg:postcode":"18901",
    "sg:province":"PA",
    "sg:tags":[
        "divorce",
        "law",
        "family"
    ],
    "wof:name":"Carlson Kathryn G Attorney",
    "wof:placetype":"venue"
},
  "geometry": {"coordinates":[-75.12960099999999,40.311699],"type":"Point"}
}