{
  "type": "Feature",
  "properties": {
    "iso:country":"US",
    "sg:address":"68 Coal Mine Rd",
    "sg:city":"Bloomsburg",
    "sg:classifiers":[
        {
            "category":"Shopping",
            "subcategory":"Bicycles & Sporting Goods",
            "type":"Retail Goods"
        }
    ],
    "sg:phone":"+1 570 458 5938",
    "sg:postcode":"17815",
    "sg:province":"PA",
    "sg:tags":[
        "equipment",
        "archery",
        "supply"
    ],
    "wof:name":"Chuck's Archery",
    "wof:placetype":"venue"
},
  "geometry": {"coordinates":[-76.590547,41.10987],"type":"Point"}
}