{
  "type": "Feature",
  "properties": {
    "iso:country":"US",
    "sg:address":"346 Reed St",
    "sg:city":"Reading",
    "sg:classifiers":[
        {
            "category":"Retail",
            "subcategory":"Auto Repair",
            "type":"Services"
        }
    ],
    "sg:phone":"+1 610 396 9750",
    "sg:postcode":"19601",
    "sg:province":"PA",
    "sg:tags":[
        "body",
        "technician",
        "painting",
        "automobile"
    ],
    "wof:name":"Ponce's Garage",
    "wof:placetype":"venue"
},
  "geometry": {"coordinates":[-75.92484399999999,40.340962],"type":"Point"}
}