{
  "type": "Feature",
  "properties": {
    "iso:country":"US",
    "sg:address":"426 Rodi Rd",
    "sg:city":"Pittsburgh",
    "sg:classifiers":[
        {
            "category":"Retail",
            "subcategory":"Auto Repair",
            "type":"Services"
        }
    ],
    "sg:phone":"+1 412 243 5400",
    "sg:postcode":"15235",
    "sg:province":"PA",
    "sg:tags":[
        "repairing",
        "automobile"
    ],
    "wof:name":"PROCARE",
    "wof:placetype":"venue"
},
  "geometry": {"coordinates":[-79.825233,40.453463],"type":"Point"}
}