{
  "type": "Feature",
  "properties": {
    "iso:country":"US",
    "sg:address":"440 Font Rd",
    "sg:city":"Downingtown",
    "sg:classifiers":[
        {
            "category":"Freight",
            "type":"Transportation"
        }
    ],
    "sg:phone":"+1   ",
    "sg:postcode":"19335",
    "sg:province":"PA",
    "sg:tags":[
        "distance",
        "long",
        "trucking"
    ],
    "wof:name":"Jerald S Levine Trucking",
    "wof:placetype":"venue"
},
  "geometry": {"coordinates":[-75.703136,40.099647],"type":"Point"}
}