{
  "type": "Feature",
  "properties": {
    "iso:country":"US",
    "sg:address":"323 Smith Ave",
    "sg:city":"Hermitage",
    "sg:classifiers":[
        {
            "category":"Banks & Credit Unions",
            "subcategory":"Financial Services",
            "type":"Services"
        }
    ],
    "sg:phone":"+1 724 342 7446",
    "sg:postcode":"16148",
    "sg:province":"PA",
    "sg:tags":[
        "loan"
    ],
    "wof:name":"Consolidated Mortgage",
    "wof:placetype":"venue"
},
  "geometry": {"coordinates":[-80.48297700000001,41.228377],"type":"Point"}
}