{
  "type": "Feature",
  "properties": {
    "iso:country":"US",
    "sg:address":"3292 State Hill Rd",
    "sg:city":"Reading",
    "sg:classifiers":[
        {
            "category":"Building & Trades",
            "subcategory":"Construction",
            "type":"Services"
        }
    ],
    "sg:phone":"+1 610 670 0230",
    "sg:postcode":"19608",
    "sg:province":"PA",
    "sg:tags":[
        "c",
        "house",
        "improvement",
        "hanging",
        "home",
        "contractor"
    ],
    "wof:name":"D & D Painting Contractors",
    "wof:placetype":"venue"
},
  "geometry": {"coordinates":[-76.007938,40.348444],"type":"Point"}
}