{
  "type": "Feature",
  "properties": {
    "iso:country":"US",
    "sg:address":"744 Rebecca Ave",
    "sg:city":"Pittsburgh",
    "sg:classifiers":[
        {
            "category":"Retail",
            "subcategory":"Auto Repair",
            "type":"Services"
        }
    ],
    "sg:phone":"+1 412 242 8342",
    "sg:postcode":"15221",
    "sg:province":"PA",
    "sg:tags":[
        "body",
        "general"
    ],
    "wof:name":"Supreme Automotive",
    "wof:placetype":"venue"
},
  "geometry": {"coordinates":[-79.88374399999999,40.439572],"type":"Point"}
}