{
  "type": "Feature",
  "properties": {
    "addr:full":"614 N Easton Rd Glenside PA 19038",
    "addr:housenumber":"614",
    "addr:postcode":"19038",
    "addr:street":"N Easton Rd",
    "iso:country":"US",
    "sg:address":"614 N Easton Rd",
    "sg:city":"Glenside",
    "sg:classifiers":[
        {
            "category":"Health Services",
            "subcategory":"Hospital",
            "type":"Services"
        },
        {
            "category":"Health Services",
            "subcategory":"Clinic",
            "type":"Services"
        }
    ],
    "sg:phone":"+1 215 884 9770",
    "sg:postcode":"19038",
    "sg:province":"PA",
    "sg:tags":[
        "mental",
        "facility"
    ],
    "sg:website":"www.salisb.com",
    "wof:name":"Milestones Community Hlth Care",
    "wof:placetype":"venue"
},
  "geometry": {"coordinates":[-75.14361700000001,40.110822],"type":"Point"}
}