{
  "type": "Feature",
  "properties": {
    "iso:country":"US",
    "sg:address":"1030 E Willow Grove Ave",
    "sg:city":"Glenside",
    "sg:classifiers":[
        {
            "category":"Real Estate",
            "subcategory":"Real Estate Agent",
            "type":"Services"
        }
    ],
    "sg:phone":"+1 215 233 3536",
    "sg:postcode":"19038",
    "sg:province":"PA",
    "sg:tags":[
        "inspection"
    ],
    "wof:name":"American Home Inspection Inc",
    "wof:placetype":"venue"
},
  "geometry": {"coordinates":[-75.188192,40.082692],"type":"Point"}
}