{
  "type": "Feature",
  "properties": {
    "iso:country":"US",
    "sg:address":"4619 Peach St",
    "sg:city":"Erie",
    "sg:classifiers":[
        {
            "category":"Building & Trades",
            "subcategory":"Construction",
            "type":"Services"
        }
    ],
    "sg:phone":"+1   ",
    "sg:postcode":"16509",
    "sg:province":"PA",
    "sg:tags":[
        "house",
        "carpentry",
        "r",
        "contractor"
    ],
    "wof:name":"Susol Emil & Son Home Imprvs",
    "wof:placetype":"venue"
},
  "geometry": {"coordinates":[-80.087569,42.086106],"type":"Point"}
}