{
  "type": "Feature",
  "properties": {
    "iso:country":"US",
    "sg:address":"425 Rte 88",
    "sg:city":"Carmichaels",
    "sg:classifiers":[
        {
            "category":"Autos & Motor Vehicles",
            "subcategory":"Auto Supplies",
            "type":"Retail Goods"
        }
    ],
    "sg:phone":"+1 724 966 8400",
    "sg:postcode":"15320",
    "sg:province":"PA",
    "sg:tags":[
        "automobile",
        "parts"
    ],
    "wof:name":"Kelly Auto Supply",
    "wof:placetype":"venue"
},
  "geometry": {"coordinates":[-79.990129,39.905295],"type":"Point"}
}