{
  "type": "Feature",
  "properties": {
    "addr:full":"376 Bonners Hill Rd York Springs PA 17372",
    "addr:housenumber":"376",
    "addr:postcode":"17372",
    "addr:street":"Bonners Hill Rd",
    "iso:country":"US",
    "sg:address":"376 Bonners Hill Rd",
    "sg:city":"York Springs",
    "sg:classifiers":[
        {
            "category":"Professional",
            "type":"Services"
        }
    ],
    "sg:phone":"+1   ",
    "sg:postcode":"17372",
    "sg:province":"PA",
    "wof:name":"Lory Williams",
    "wof:placetype":"venue"
},
  "geometry": {"coordinates":[-77.099401,40.02329],"type":"Point"}
}