{
  "type": "Feature",
  "properties": {
    "iso:country":"US",
    "sg:address":"224 Walters Ave",
    "sg:city":"Wernersville",
    "sg:classifiers":[
        {
            "category":"Freight",
            "type":"Transportation"
        }
    ],
    "sg:phone":"+1   ",
    "sg:postcode":"19565",
    "sg:province":"PA",
    "sg:tags":[
        "trucking"
    ],
    "wof:name":"Dwayne Guistwite",
    "wof:placetype":"venue"
},
  "geometry": {"coordinates":[-76.093155,40.324499],"type":"Point"}
}