{
  "type": "Feature",
  "properties": {
    "iso:country":"US",
    "sg:address":"506 S State St",
    "sg:city":"Du Bois",
    "sg:classifiers":[
        {
            "category":"Real Estate",
            "subcategory":"Surveying",
            "type":"Services"
        }
    ],
    "sg:phone":"+1   ",
    "sg:postcode":"15801",
    "sg:province":"PA",
    "wof:name":"Thomas M Dusky",
    "wof:placetype":"venue"
},
  "geometry": {"coordinates":[-78.77223600000001,41.116782],"type":"Point"}
}