{
  "type": "Feature",
  "properties": {
    "addr:full":"401 S Bryn Mawr Ave Bryn Mawr PA 19010",
    "addr:housenumber":"401",
    "addr:postcode":"19010",
    "addr:street":"S Bryn Mawr Ave",
    "iso:country":"US",
    "sg:address":"401 S Bryn Mawr Ave",
    "sg:city":"Bryn Mawr",
    "sg:classifiers":[
        {
            "category":"Education",
            "subcategory":"School",
            "type":"Public Place"
        }
    ],
    "sg:phone":"+1   ",
    "sg:postcode":"19010",
    "sg:province":"PA",
    "sg:tags":[
        "child",
        "day",
        "care"
    ],
    "wof:name":"St Aloysius Academy",
    "wof:placetype":"venue"
},
  "geometry": {"coordinates":[-75.339601,40.014013],"type":"Point"}
}