{
  "type": "Feature",
  "properties": {
    "iso:country":"US",
    "sg:address":"250 Mount Misery Rd",
    "sg:city":"New Oxford",
    "sg:classifiers":[
        {
            "category":"Manufacturing",
            "subcategory":"Printing",
            "type":"Manufacturing & Wholesale Goods"
        }
    ],
    "sg:phone":"+1   ",
    "sg:postcode":"17350",
    "sg:province":"PA",
    "sg:tags":[
        "lithographic",
        "commercial"
    ],
    "wof:name":"Genes Printing Serv",
    "wof:placetype":"venue"
},
  "geometry": {"coordinates":[-77.04211100000001,39.834506],"type":"Point"}
}