{
  "type": "Feature",
  "properties": {
    "addr:full":"369 Eden Rd Quarryville PA 17566",
    "addr:housenumber":"369",
    "addr:postcode":"17566",
    "addr:street":"Eden Rd",
    "iso:country":"US",
    "sg:address":"369 Eden Rd",
    "sg:city":"Quarryville",
    "sg:classifiers":[
        {
            "category":"Building & Trades",
            "subcategory":"Construction",
            "type":"Services"
        }
    ],
    "sg:phone":"+1   ",
    "sg:postcode":"17566",
    "sg:province":"PA",
    "sg:tags":[
        "contractor"
    ],
    "wof:name":"Collins Spray Foam Insulation",
    "wof:placetype":"venue"
},
  "geometry": {"coordinates":[-76.13464399999999,39.914099],"type":"Point"}
}