{
  "type": "Feature",
  "properties": {
    "addr:full":"828 Willowbrook Dr Norristown PA 19403",
    "addr:housenumber":"828",
    "addr:postcode":"19403",
    "addr:street":"Willowbrook Dr",
    "iso:country":"US",
    "sg:address":"828 Willowbrook Dr",
    "sg:city":"Norristown",
    "sg:classifiers":[
        {
            "category":"Professional",
            "subcategory":"Business Services",
            "type":"Services"
        }
    ],
    "sg:phone":"+1 610 539 4449",
    "sg:postcode":"19403",
    "sg:province":"PA",
    "sg:tags":[
        "notary"
    ],
    "wof:name":"LA Sorda's Notary Svc",
    "wof:placetype":"venue"
},
  "geometry": {"coordinates":[-75.39685,40.131564],"type":"Point"}
}