{
  "type": "Feature",
  "properties": {
    "addr:full":"101 U P Church Rd Ligonier PA 15658",
    "addr:housenumber":"101",
    "addr:postcode":"15658",
    "addr:street":"U P Church Rd",
    "iso:country":"US",
    "sg:address":"101 U P Church Rd",
    "sg:city":"Ligonier",
    "sg:classifiers":[
        {
            "category":"Building & Trades",
            "subcategory":"Construction",
            "type":"Services"
        }
    ],
    "sg:phone":"+1   ",
    "sg:postcode":"15658",
    "sg:province":"PA",
    "sg:tags":[
        "excavation",
        "contractor"
    ],
    "wof:name":"Hays Contracting",
    "wof:placetype":"venue"
},
  "geometry": {"coordinates":[-79.310332,40.179871],"type":"Point"}
}