{
  "type": "Feature",
  "properties": {
    "iso:country":"US",
    "sg:address":"743 N Beatty St",
    "sg:city":"Pittsburgh",
    "sg:classifiers":[
        {
            "category":"Shopping",
            "subcategory":"Clothing, Apparel, & Fashions",
            "type":"Retail Goods"
        }
    ],
    "sg:phone":"+1   ",
    "sg:postcode":"15206",
    "sg:province":"PA",
    "wof:name":"Bridge Spotters Corp",
    "wof:placetype":"venue"
},
  "geometry": {"coordinates":[-79.92257600000001,40.469143],"type":"Point"}
}