{
  "type": "Feature",
  "properties": {
    "iso:country":"US",
    "sg:address":"1343 Piedmont Dr",
    "sg:city":"Downingtown",
    "sg:classifiers":[
        {
            "category":"Building & Trades",
            "subcategory":"Electrical",
            "type":"Services"
        }
    ],
    "sg:phone":"+1 610 269 2234",
    "sg:postcode":"19335",
    "sg:province":"PA",
    "sg:tags":[
        "electrical",
        "contractor"
    ],
    "wof:name":"Jamac Inc",
    "wof:placetype":"venue"
},
  "geometry": {"coordinates":[-75.71397,39.975223],"type":"Point"}
}