{
  "type": "Feature",
  "properties": {
    "addr:full":"700 Arch St Philadelphia PA 19106",
    "addr:housenumber":"700",
    "addr:postcode":"19106",
    "addr:street":"Arch St",
    "iso:country":"US",
    "sg:address":"700 Arch St",
    "sg:city":"Philadelphia",
    "sg:classifiers":[
        {
            "category":"Government",
            "subcategory":"Jail",
            "type":"Public Place"
        }
    ],
    "sg:phone":"+1   ",
    "sg:postcode":"19106",
    "sg:province":"PA",
    "sg:tags":[
        "prison"
    ],
    "wof:name":"Fdc Philadelphia",
    "wof:placetype":"venue"
},
  "geometry": {"coordinates":[-75.153143,39.953153],"type":"Point"}
}