{
  "type": "Feature",
  "properties": {
    "iso:country":"US",
    "sg:address":"2644 Mosside Blvd",
    "sg:city":"Monroeville",
    "sg:classifiers":[
        {
            "category":"Health Services",
            "subcategory":"Podiatrist",
            "type":"Services"
        }
    ],
    "sg:phone":"+1 412 372 0600",
    "sg:postcode":"15146",
    "sg:province":"PA",
    "wof:name":"Ankle & Foot Ctr",
    "wof:placetype":"venue"
},
  "geometry": {"coordinates":[-79.752503,40.433475],"type":"Point"}
}