{
  "type": "Feature",
  "properties": {
    "iso:country":"US",
    "sg:address":"119 Station Rd",
    "sg:city":"Cheyney",
    "sg:classifiers":[
        {
            "category":"Government",
            "subcategory":"Post Office",
            "type":"Public Place"
        }
    ],
    "sg:phone":"+1 610 399 0239",
    "sg:postcode":"19319",
    "sg:province":"PA",
    "wof:name":"US Post Office",
    "wof:placetype":"venue"
},
  "geometry": {"coordinates":[-75.52145400000001,39.929065],"type":"Point"}
}