{
  "type": "Feature",
  "properties": {
    "iso:country":"US",
    "sg:address":"3934 Quaker Valley Rd",
    "sg:city":"Alum Bank",
    "sg:classifiers":[
        {
            "category":"Organizations",
            "subcategory":"Religious Organization",
            "type":"Services"
        }
    ],
    "sg:phone":"+1 814 839 2880",
    "sg:postcode":"15521",
    "sg:province":"PA",
    "sg:tags":[
        "church"
    ],
    "wof:name":"Pleasantville Assembly-God Chr",
    "wof:placetype":"venue"
},
  "geometry": {"coordinates":[-78.60181300000001,40.173942],"type":"Point"}
}