{
  "type": "Feature",
  "properties": {
    "iso:country":"US",
    "sg:address":"118 S Anderson St",
    "sg:city":"Bedford",
    "sg:classifiers":[
        {
            "category":"Health Services",
            "subcategory":"Doctor",
            "type":"Services"
        }
    ],
    "sg:phone":"+1 814 623 2146",
    "sg:postcode":"15522",
    "sg:province":"PA",
    "sg:tags":[
        "physician",
        "surgeon"
    ],
    "wof:name":"University-Pittsburg Med Ctr",
    "wof:placetype":"venue"
},
  "geometry": {"coordinates":[-78.494129,40.018625],"type":"Point"}
}