{
  "type": "Feature",
  "properties": {
    "iso:country":"US",
    "sg:address":"354 Darlington Rd",
    "sg:city":"Media",
    "sg:classifiers":[
        {
            "category":"Real Estate",
            "subcategory":"Developer",
            "type":"Services"
        }
    ],
    "sg:phone":"+1   ",
    "sg:postcode":"19063",
    "sg:province":"PA",
    "sg:tags":[
        "land",
        "subdivider"
    ],
    "wof:name":"Halliday Properties Inc",
    "wof:placetype":"venue"
},
  "geometry": {"coordinates":[-75.458511,39.914984],"type":"Point"}
}