{
  "type": "Feature",
  "properties": {
    "addr:full":"475 E 2nd Ave Williamsport PA 17702",
    "addr:housenumber":"475",
    "addr:postcode":"17702",
    "addr:street":"E 2Nd Ave",
    "iso:country":"US",
    "sg:address":"475 E 2nd Ave",
    "sg:city":"Williamsport",
    "sg:classifiers":[
        {
            "category":"Retail",
            "subcategory":"Repair Shop",
            "type":"Services"
        }
    ],
    "sg:phone":"+1 570 323 9352",
    "sg:postcode":"17702",
    "sg:province":"PA",
    "sg:tags":[
        "equipment",
        "audio",
        "video"
    ],
    "wof:name":"Audio Services",
    "wof:placetype":"venue"
},
  "geometry": {"coordinates":[-76.98974,41.237388],"type":"Point"}
}