{
  "type": "Feature",
  "properties": {
    "iso:country":"US",
    "sg:address":"9200 Darrell Dr",
    "sg:city":"Pittsburgh",
    "sg:classifiers":[
        {
            "category":"Wholesale",
            "subcategory":"Computers",
            "type":"Manufacturing & Wholesale Goods"
        }
    ],
    "sg:phone":"+1 412 367 5988",
    "sg:postcode":"15237",
    "sg:province":"PA",
    "sg:tags":[
        "d",
        "mfg"
    ],
    "wof:name":"Icon Computer Units",
    "wof:placetype":"venue"
},
  "geometry": {"coordinates":[-80.031347,40.574104],"type":"Point"}
}