{
  "type": "Feature",
  "properties": {
    "iso:country":"US",
    "sg:address":"4 Widgeon Dr",
    "sg:city":"Pittsburgh",
    "sg:classifiers":[
        {
            "category":"Social Services",
            "subcategory":"Job Training",
            "type":"Services"
        }
    ],
    "sg:phone":"+1 412 767 4103",
    "sg:postcode":"15238",
    "sg:province":"PA",
    "sg:tags":[
        "nursing",
        "homes-skilled",
        "facility"
    ],
    "wof:name":"Meritcare",
    "wof:placetype":"venue"
},
  "geometry": {"coordinates":[-79.907922,40.554628],"type":"Point"}
}