{
  "type": "Feature",
  "properties": {
    "addr:full":"2034 N Lambert St Philadelphia PA 19121",
    "addr:housenumber":"2034",
    "addr:postcode":"19121",
    "addr:street":"N Lambert St",
    "iso:country":"US",
    "sg:address":"2034 N Lambert St",
    "sg:city":"Philadelphia",
    "sg:classifiers":[
        {
            "category":"Retail",
            "subcategory":"Laundry & Dry Cleaning",
            "type":"Services"
        }
    ],
    "sg:phone":"+1 215 765 0587",
    "sg:postcode":"19121",
    "sg:province":"PA",
    "sg:tags":[
        "cleaner",
        "rug",
        "carpet"
    ],
    "wof:name":"Carpet Cleaning D Ragin and P Titus",
    "wof:placetype":"venue"
},
  "geometry": {"coordinates":[-75.167537,39.985122],"type":"Point"}
}