{
  "type": "Feature",
  "properties": {
    "iso:country":"US",
    "sg:address":"31 S Main St",
    "sg:city":"Phoenixville",
    "sg:classifiers":[
        {
            "category":"Professional",
            "subcategory":"Advertising",
            "type":"Services"
        }
    ],
    "sg:phone":"+1 610 935 7073",
    "sg:postcode":"19460",
    "sg:province":"PA",
    "sg:tags":[
        "agency",
        "specialty"
    ],
    "wof:name":"Good Group",
    "wof:placetype":"venue"
},
  "geometry": {"coordinates":[-75.51595399999999,40.133338],"type":"Point"}
}