{
  "type": "Feature",
  "properties": {
    "iso:country":"US",
    "sg:address":"128 N 10th St",
    "sg:city":"Philadelphia",
    "sg:classifiers":[
        {
            "category":"Professional",
            "subcategory":"Business Services",
            "type":"Services"
        }
    ],
    "sg:phone":"+1 215 238 8983",
    "sg:postcode":"19107",
    "sg:province":"PA",
    "wof:name":"Shun Jie",
    "wof:placetype":"venue"
},
  "geometry": {"coordinates":[-75.15597200000001,39.955364],"type":"Point"}
}