{
  "type": "Feature",
  "properties": {
    "iso:country":"US",
    "sg:address":"15 S Main St Ste 2",
    "sg:city":"Manheim",
    "sg:classifiers":[
        {
            "category":"Professional",
            "subcategory":"Management & Consulting",
            "type":"Services"
        },
        {
            "category":"Professional",
            "subcategory":"Business Services",
            "type":"Services"
        }
    ],
    "sg:phone":"+1 717 664 7616",
    "sg:postcode":"17545",
    "sg:province":"PA",
    "sg:tags":[
        "consultant",
        "coach"
    ],
    "sg:website":"http://www.strattonconsulting.com",
    "wof:name":"Stratton Consulting Group",
    "wof:placetype":"venue"
},
  "geometry": {"coordinates":[-76.394386,40.16309],"type":"Point"}
}