{
  "type": "Feature",
  "properties": {
    "iso:country":"US",
    "sg:address":"499 Easton Rd",
    "sg:city":"Horsham",
    "sg:classifiers":[
        {
            "category":"Wholesale",
            "subcategory":"Electrical",
            "type":"Manufacturing & Wholesale Goods"
        },
        {
            "category":"Wholesale",
            "subcategory":"Durable Goods & Equipment",
            "type":"Manufacturing & Wholesale Goods"
        }
    ],
    "sg:phone":"+1 215 674 2937",
    "sg:postcode":"19044",
    "sg:province":"PA",
    "sg:tags":[
        "electronic",
        "representative",
        "manufacturer"
    ],
    "wof:name":"Jacobsen Associates Inc",
    "wof:placetype":"venue"
},
  "geometry": {"coordinates":[-75.130816,40.180904],"type":"Point"}
}