{
  "type": "Feature",
  "properties": {
    "iso:country":"US",
    "sg:address":"541 Golden St",
    "sg:city":"Lititz",
    "sg:classifiers":[
        {
            "category":"Professional",
            "subcategory":"Business Services",
            "type":"Services"
        }
    ],
    "sg:phone":"+1 717 538 9514",
    "sg:postcode":"17543",
    "sg:province":"PA",
    "sg:tags":[
        "consultant",
        "coach"
    ],
    "wof:name":"Yahweh Consulting",
    "wof:placetype":"venue"
},
  "geometry": {"coordinates":[-76.31464200000001,40.146042],"type":"Point"}
}