{
  "type": "Feature",
  "properties": {
    "iso:country":"US",
    "sg:address":"13 Boathouse Row",
    "sg:city":"Philadelphia",
    "sg:classifiers":[
        {
            "category":"Organizations",
            "subcategory":"Community Association",
            "type":"Services"
        }
    ],
    "sg:phone":"+1 215 765 9244",
    "sg:postcode":"19130",
    "sg:province":"PA",
    "sg:tags":[
        "club",
        "nightlife"
    ],
    "wof:name":"Undine Barge Club",
    "wof:placetype":"venue"
},
  "geometry": {"coordinates":[-75.184826,39.969391],"type":"Point"}
}