{
  "type": "Feature",
  "properties": {
    "iso:country":"US",
    "sg:address":"885 Bremer Rd",
    "sg:city":"Dover",
    "sg:classifiers":[
        {
            "category":"Building & Trades",
            "subcategory":"Landscaping Services",
            "type":"Services"
        }
    ],
    "sg:phone":"+1 717 266 0137",
    "sg:postcode":"17315",
    "sg:province":"PA",
    "sg:tags":[
        "landscape",
        "contractor"
    ],
    "wof:name":"Johns Landscaping and Mowing",
    "wof:placetype":"venue"
},
  "geometry": {"coordinates":[-76.83085699999999,40.06019],"type":"Point"}
}