{
  "type": "Feature",
  "properties": {
    "addr:full":"1017 Elm St Bristol PA 19007",
    "addr:housenumber":"1017",
    "addr:postcode":"19007",
    "addr:street":"Elm St",
    "iso:country":"US",
    "sg:address":"1017 Elm St",
    "sg:city":"Bristol",
    "sg:classifiers":[
        {
            "category":"Food & Beverages",
            "subcategory":"Groceries & Convenience Stores",
            "type":"Retail Goods"
        }
    ],
    "sg:phone":"+1   ",
    "sg:postcode":"19007",
    "sg:province":"PA",
    "wof:name":"Sanchez Pizza & Deli Express",
    "wof:placetype":"venue"
},
  "geometry": {"coordinates":[-74.849053,40.103819],"type":"Point"}
}