{
  "type": "Feature",
  "properties": {
    "iso:country":"US",
    "sg:address":"1807 Walnut Ave",
    "sg:city":"Oreland",
    "sg:classifiers":[
        {
            "category":"Manufacturing",
            "subcategory":"Textiles",
            "type":"Manufacturing & Wholesale Goods"
        }
    ],
    "sg:phone":"+1 215 884 3614",
    "sg:postcode":"19075",
    "sg:province":"PA",
    "sg:tags":[
        "knitting",
        "mills"
    ],
    "sg:website":"www.chapelhillmfg.com",
    "wof:name":"Chapel Hill Mfg Co",
    "wof:placetype":"venue"
},
  "geometry": {"coordinates":[-75.197676,40.122727],"type":"Point"}
}