{
  "type": "Feature",
  "properties": {
    "addr:full":"2740 Mosside Blvd Monroeville PA 15146",
    "addr:housenumber":"2740",
    "addr:postcode":"15146",
    "addr:street":"Mosside Blvd",
    "iso:country":"US",
    "sg:address":"2740 Mosside Blvd",
    "sg:city":"Monroeville",
    "sg:classifiers":[
        {
            "category":"Restaurant",
            "type":"Food & Drink"
        }
    ],
    "sg:menulink":"http://www.allmenus.com/pa/monroeville/10902-max--ermas/menu/",
    "sg:phone":"+1 412 372 3262",
    "sg:postcode":"15146",
    "sg:province":"PA",
    "sg:tags":[
        "american"
    ],
    "wof:name":"Max & Erma's",
    "wof:placetype":"venue"
},
  "geometry": {"coordinates":[-79.757514,40.436405],"type":"Point"}
}