{
  "type": "Feature",
  "properties": {
    "iso:country":"US",
    "sg:address":"195 Justice Dr",
    "sg:city":"Newtown",
    "sg:classifiers":[
        {
            "category":"Shopping",
            "subcategory":"Computers & Home Electronics",
            "type":"Retail Goods"
        }
    ],
    "sg:phone":"+1 215 968 0180",
    "sg:postcode":"18940",
    "sg:province":"PA",
    "sg:tags":[
        "equipment",
        "dealer"
    ],
    "wof:name":"Peripherals & Communications",
    "wof:placetype":"venue"
},
  "geometry": {"coordinates":[-74.965011,40.243093],"type":"Point"}
}