{
  "type": "Feature",
  "properties": {
    "addr:full":"351 Buffalo St Beaver PA 15009",
    "addr:housenumber":"351",
    "addr:postcode":"15009",
    "addr:street":"Buffalo St",
    "iso:country":"US",
    "sg:address":"351 Buffalo St",
    "sg:city":"Beaver",
    "sg:classifiers":[
        {
            "category":"Real Estate",
            "subcategory":"Developer",
            "type":"Services"
        }
    ],
    "sg:phone":"+1 724 774 8039",
    "sg:postcode":"15009",
    "sg:province":"PA",
    "sg:tags":[
        "cemetery"
    ],
    "wof:name":"Beaver Cemetery",
    "wof:placetype":"venue"
},
  "geometry": {"coordinates":[-80.31388099999999,40.693816],"type":"Point"}
}