{
  "type": "Feature",
  "properties": {
    "iso:country":"US",
    "sg:address":"421 Sycamore Ave",
    "sg:city":"Merion Station",
    "sg:classifiers":[
        {
            "category":"Organizations",
            "subcategory":"Membership Organization",
            "type":"Services"
        }
    ],
    "sg:phone":"+1   ",
    "sg:postcode":"19066",
    "sg:province":"PA",
    "wof:name":"National Sports & Gaming Assn",
    "wof:placetype":"venue"
},
  "geometry": {"coordinates":[-75.249123,40.001328],"type":"Point"}
}