{
  "type": "Feature",
  "properties": {
    "addr:full":"210 Camp Strauss Rd Bethel PA 19507",
    "addr:housenumber":"210",
    "addr:postcode":"19507",
    "addr:street":"Camp Strauss Rd",
    "iso:country":"US",
    "sg:address":"210 Camp Strauss Rd",
    "sg:city":"Bethel",
    "sg:classifiers":[
        {
            "category":"Professional",
            "type":"Services"
        }
    ],
    "sg:phone":"+1   ",
    "sg:postcode":"19507",
    "sg:province":"PA",
    "wof:name":"Carmel J Etchberger",
    "wof:placetype":"venue"
},
  "geometry": {"coordinates":[-76.408288,40.48616],"type":"Point"}
}