{
  "type": "Feature",
  "properties": {
    "addr:full":"105 Shippen Rd Glenside PA 19038",
    "addr:housenumber":"105",
    "addr:postcode":"19038",
    "addr:street":"Shippen Rd",
    "iso:country":"US",
    "sg:address":"105 Shippen Rd",
    "sg:city":"Glenside",
    "sg:classifiers":[
        {
            "category":"Professional",
            "subcategory":"Accounting & Tax Preparation",
            "type":"Services"
        }
    ],
    "sg:phone":"+1 215 836 4268",
    "sg:postcode":"19038",
    "sg:province":"PA",
    "sg:tags":[
        "public",
        "accountants-certified"
    ],
    "wof:name":"Thomas Cotton Cpa",
    "wof:placetype":"venue"
},
  "geometry": {"coordinates":[-75.20809199999999,40.098828],"type":"Point"}
}