{
  "type": "Feature",
  "properties": {
    "iso:country":"US",
    "sg:address":"224 Boyles Ave",
    "sg:city":"New Castle",
    "sg:classifiers":[
        {
            "category":"Food & Beverages",
            "subcategory":"Groceries & Convenience Stores",
            "type":"Retail Goods"
        }
    ],
    "sg:phone":"+1 814 466 6809",
    "sg:postcode":"16101",
    "sg:province":"PA",
    "wof:name":"Uni-Mart",
    "wof:placetype":"venue"
},
  "geometry": {"coordinates":[-80.340197,41.007647],"type":"Point"}
}