{
  "type": "Feature",
  "properties": {
    "iso:country":"US",
    "sg:address":"101 E Main St",
    "sg:city":"Brookville",
    "sg:classifiers":[
        {
            "category":"Professional",
            "subcategory":"Advertising",
            "type":"Services"
        }
    ],
    "sg:phone":"+1   ",
    "sg:postcode":"15825",
    "sg:province":"PA",
    "sg:tags":[
        "representative"
    ],
    "wof:name":"Wwjl-LP 959 FM",
    "wof:placetype":"venue"
},
  "geometry": {"coordinates":[-79.077162,41.160176],"type":"Point"}
}