{
  "type": "Feature",
  "properties": {
    "addr:full":"2407 Juniata Gap Rd Altoona PA 16601",
    "addr:postcode":"2407;16601",
    "addr:street":"Juniata Gap Rd",
    "iso:country":"US",
    "sg:address":"2407 Juniata Gap Rd",
    "sg:city":"Altoona",
    "sg:classifiers":[
        {
            "category":"Home & Garden",
            "subcategory":"Garden Supply",
            "type":"Retail Goods"
        }
    ],
    "sg:phone":"+1 814 942 7645",
    "sg:postcode":"16601",
    "sg:province":"PA",
    "sg:tags":[
        "repair"
    ],
    "wof:name":"Small Engine Shop",
    "wof:placetype":"venue"
},
  "geometry": {"coordinates":[-78.402219,40.534336],"type":"Point"}
}