{
  "type": "Feature",
  "properties": {
    "addr:full":"1528 Leeds Ave Monessen PA 15062",
    "addr:housenumber":"1528",
    "addr:postcode":"15062",
    "addr:street":"Leeds Ave",
    "iso:country":"US",
    "sg:address":"1528 Leeds Ave",
    "sg:city":"Monessen",
    "sg:classifiers":[
        {
            "category":"Real Estate",
            "subcategory":"Developer",
            "type":"Services"
        }
    ],
    "sg:phone":"+1   ",
    "sg:postcode":"15062",
    "sg:province":"PA",
    "sg:tags":[
        "cemetery"
    ],
    "wof:name":"Grandview Cemetery Association",
    "wof:placetype":"venue"
},
  "geometry": {"coordinates":[-79.88883,40.14486],"type":"Point"}
}