{
  "type": "Feature",
  "properties": {
    "iso:country":"US",
    "sg:address":"156 Pleasant Dr",
    "sg:city":"Aliquippa",
    "sg:classifiers":[
        {
            "category":"Autos & Motor Vehicles",
            "subcategory":"Fuel & Gas Station",
            "type":"Retail Goods"
        }
    ],
    "sg:phone":"+1 724 375 0999",
    "sg:postcode":"15001",
    "sg:province":"PA",
    "sg:tags":[
        "oil"
    ],
    "wof:name":"Friend's Sunoco",
    "wof:placetype":"venue"
},
  "geometry": {"coordinates":[-80.317267,40.634888],"type":"Point"}
}