{
  "type": "Feature",
  "properties": {
    "iso:country":"US",
    "sg:address":"809 Liberty Ave",
    "sg:city":"Pittsburgh",
    "sg:classifiers":[
        {
            "category":"Cinema",
            "subcategory":"Movie Theater",
            "type":"Entertainment"
        }
    ],
    "sg:phone":"+1   ",
    "sg:postcode":"15222",
    "sg:province":"PA",
    "sg:tags":[
        "motion",
        "picture"
    ],
    "wof:name":"Art Cinema",
    "wof:placetype":"venue"
},
  "geometry": {"coordinates":[-79.99757099999999,40.443107],"type":"Point"}
}