{
  "type": "Feature",
  "properties": {
    "addr:full":"4429 Pennell Rd Aston PA 19014",
    "addr:housenumber":"4429",
    "addr:postcode":"19014",
    "addr:street":"Pennell Rd",
    "iso:country":"US",
    "sg:address":"4429 Pennell Rd",
    "sg:city":"Aston",
    "sg:classifiers":[
        {
            "category":"Personal",
            "subcategory":"Beauty Salon",
            "type":"Services"
        }
    ],
    "sg:phone":"+1 610 494 8990",
    "sg:postcode":"19014",
    "sg:province":"PA",
    "wof:name":"Your Hair Salon",
    "wof:placetype":"venue"
},
  "geometry": {"coordinates":[-75.428832,39.870445],"type":"Point"}
}