{
  "type": "Feature",
  "properties": {
    "iso:country":"US",
    "sg:address":"185 Levittown Pkwy",
    "sg:city":"Levittown",
    "sg:classifiers":[
        {
            "category":"Shopping",
            "subcategory":"Shoes",
            "type":"Retail Goods"
        }
    ],
    "sg:phone":"+1 215 269 6914",
    "sg:postcode":"19055",
    "sg:province":"PA",
    "sg:tags":[
        "store"
    ],
    "sg:website":"www.tacobell.com",
    "wof:name":"Taco Bell",
    "wof:placetype":"venue"
},
  "geometry": {"coordinates":[-74.82055,40.143991],"type":"Point"}
}