{
  "type": "Feature",
  "properties": {
    "addr:full":"520 Ash St Johnstown PA 15902",
    "addr:housenumber":"520",
    "addr:postcode":"15902",
    "addr:street":"Ash St",
    "iso:country":"US",
    "sg:address":"520 Ash St",
    "sg:city":"Johnstown",
    "sg:classifiers":[
        {
            "category":"Wholesale",
            "subcategory":"Machinery & Supplies",
            "type":"Manufacturing & Wholesale Goods"
        }
    ],
    "sg:phone":"+1 814 539 8945",
    "sg:postcode":"15902",
    "sg:province":"PA",
    "sg:tags":[
        "equipment",
        "establishment"
    ],
    "wof:name":"Lipari Gowns Inc",
    "wof:placetype":"venue"
},
  "geometry": {"coordinates":[-78.908142,40.312299],"type":"Point"}
}