{
  "type": "Feature",
  "properties": {
    "addr:full":"5763 Nassau Rd Philadelphia PA 19131",
    "addr:housenumber":"5763",
    "addr:postcode":"19131",
    "addr:street":"Nassau Rd",
    "iso:country":"US",
    "sg:address":"5763 Nassau Rd",
    "sg:city":"Philadelphia",
    "sg:classifiers":[
        {
            "category":"Manufacturing",
            "subcategory":"Printing",
            "type":"Manufacturing & Wholesale Goods"
        }
    ],
    "sg:phone":"+1   ",
    "sg:postcode":"19131",
    "sg:province":"PA",
    "sg:tags":[
        "publishing"
    ],
    "wof:name":"Marbert Publishing Co",
    "wof:placetype":"venue"
},
  "geometry": {"coordinates":[-75.23848700000001,39.97994],"type":"Point"}
}