{
  "type": "Feature",
  "properties": {
    "iso:country":"US",
    "sg:address":"100 Hanover Ln",
    "sg:city":"Harrisburg",
    "sg:classifiers":[
        {
            "category":"Real Estate",
            "subcategory":"Real Estate Agent",
            "type":"Services"
        }
    ],
    "sg:phone":"+1 717 238 6724",
    "sg:postcode":"17112",
    "sg:province":"PA",
    "sg:tags":[
        "authorities",
        "housing"
    ],
    "wof:name":"Harrisburg Housing Authority",
    "wof:placetype":"venue"
},
  "geometry": {"coordinates":[-76.74897,40.333957],"type":"Point"}
}