{
  "type": "Feature",
  "properties": {
    "addr:full":"8 N Main St Ashley PA 18706",
    "addr:housenumber":"8",
    "addr:postcode":"18706",
    "addr:street":"N Main St",
    "iso:country":"US",
    "sg:address":"8 N Main St",
    "sg:city":"Ashley",
    "sg:classifiers":[
        {
            "category":"Recreation",
            "type":"Entertainment"
        },
        {
            "category":"Government",
            "subcategory":"Fire Station",
            "type":"Public Place"
        }
    ],
    "sg:phone":"+1 570 825 9187",
    "sg:postcode":"18706",
    "sg:province":"PA",
    "sg:tags":[
        "department",
        "club",
        "membership",
        "executive"
    ],
    "wof:name":"Ashley Fire Department",
    "wof:placetype":"venue"
},
  "geometry": {"coordinates":[-75.89910399999999,41.214441],"type":"Point"}
}