{
  "type": "Feature",
  "properties": {
    "addr:full":"921 Pike St Lemont PA 16851",
    "addr:housenumber":"921",
    "addr:postcode":"16851",
    "addr:street":"Pike St",
    "iso:country":"US",
    "sg:address":"921 Pike St",
    "sg:city":"Lemont",
    "sg:classifiers":[
        {
            "category":"Home & Garden",
            "subcategory":"Carpets & Floor Coverings",
            "type":"Retail Goods"
        }
    ],
    "sg:phone":"+1 814 234 4775",
    "sg:postcode":"16851",
    "sg:province":"PA",
    "sg:tags":[
        "material"
    ],
    "wof:name":"Complete Floor Covering-Lemont",
    "wof:placetype":"venue"
},
  "geometry": {"coordinates":[-77.818811,40.809232],"type":"Point"}
}