{
  "type": "Feature",
  "properties": {
    "iso:country":"US",
    "sg:address":"212 Edgewood Ave",
    "sg:city":"Johnstown",
    "sg:classifiers":[
        {
            "category":"Manufacturing",
            "subcategory":"Tools & Machinery",
            "type":"Manufacturing & Wholesale Goods"
        }
    ],
    "sg:phone":"+1   ",
    "sg:postcode":"15906",
    "sg:province":"PA",
    "sg:tags":[
        "equipment",
        "mfg"
    ],
    "wof:name":"Armour Penrose",
    "wof:placetype":"venue"
},
  "geometry": {"coordinates":[-78.946704,40.341959],"type":"Point"}
}