{
  "type": "Feature",
  "properties": {
    "iso:country":"US",
    "sg:address":"5812 Kennedy Ave",
    "sg:city":"Export",
    "sg:classifiers":[
        {
            "category":"Professional",
            "subcategory":"Business Services",
            "type":"Services"
        }
    ],
    "sg:phone":"+1 724 327 3024",
    "sg:postcode":"15632",
    "sg:province":"PA",
    "sg:tags":[
        "auctioneer"
    ],
    "wof:name":"Bill Anderson & Assoc",
    "wof:placetype":"venue"
},
  "geometry": {"coordinates":[-79.625967,40.418392],"type":"Point"}
}