{
  "type": "Feature",
  "properties": {
    "iso:country":"US",
    "sg:address":"603 Lakeshore Dr",
    "sg:city":"Lakeville",
    "sg:classifiers":[
        {
            "category":"Building & Trades",
            "subcategory":"Equipment Rental",
            "type":"Services"
        }
    ],
    "sg:phone":"+1 570 226 9363",
    "sg:postcode":"18438",
    "sg:province":"PA",
    "sg:tags":[
        "contractors'"
    ],
    "wof:name":"Pauline's Concrete Pumping Company Inc",
    "wof:placetype":"venue"
},
  "geometry": {"coordinates":[-75.22440400000001,41.441344],"type":"Point"}
}