{
  "type": "Feature",
  "properties": {
    "addr:full":"1538 Haines Rd Levittown PA 19055",
    "addr:housenumber":"1538",
    "addr:postcode":"19055",
    "addr:street":"Haines Rd Levittown",
    "iso:country":"US",
    "sg:address":"1538 Haines Rd",
    "sg:city":"Levittown",
    "sg:classifiers":[
        {
            "category":"Restaurant",
            "type":"Food & Drink"
        }
    ],
    "sg:phone":"+1 215 945 0207",
    "sg:postcode":"19055",
    "sg:province":"PA",
    "sg:tags":[
        "eating"
    ],
    "wof:name":"Turkish Coffee",
    "wof:placetype":"venue"
},
  "geometry": {"coordinates":[-74.83291199999999,40.136716],"type":"Point"}
}