{
  "type": "Feature",
  "properties": {
    "addr:full":"825 S 25th St Easton PA 18045",
    "addr:housenumber":"825",
    "addr:postcode":"18045",
    "addr:street":"S 25Th St",
    "iso:country":"US",
    "sg:address":"825 S 25th St",
    "sg:city":"Easton",
    "sg:classifiers":[
        {
            "category":"Personal",
            "type":"Services"
        }
    ],
    "sg:phone":"+1 484 373 0203",
    "sg:postcode":"18045",
    "sg:province":"PA",
    "sg:tags":[
        "control",
        "weight"
    ],
    "wof:name":"L A Weight Loss Ctr",
    "wof:placetype":"venue"
},
  "geometry": {"coordinates":[-75.246809,40.678028],"type":"Point"}
}