{
  "type": "Feature",
  "properties": {
    "addr:full":"920 Smith Rd Homer City PA 15748",
    "addr:housenumber":"920",
    "addr:postcode":"15748",
    "addr:street":"Smith Rd",
    "iso:country":"US",
    "sg:address":"920 Smith Rd",
    "sg:city":"Homer City",
    "sg:classifiers":[
        {
            "category":"Shopping",
            "subcategory":"Gifts & Souvenirs",
            "type":"Retail Goods"
        }
    ],
    "sg:phone":"+1   ",
    "sg:postcode":"15748",
    "sg:province":"PA",
    "wof:name":"Locust Grove Baskets & Greenho",
    "wof:placetype":"venue"
},
  "geometry": {"coordinates":[-79.19732,40.546017],"type":"Point"}
}