{
  "type": "Feature",
  "properties": {
    "iso:country":"US",
    "sg:address":"121 Wildwood Dr",
    "sg:city":"Butler",
    "sg:classifiers":[
        {
            "category":"Real Estate",
            "subcategory":"Developer",
            "type":"Services"
        }
    ],
    "sg:phone":"+1   ",
    "sg:postcode":"16002",
    "sg:province":"PA",
    "sg:tags":[
        "home",
        "contractor"
    ],
    "wof:name":"D L Delo",
    "wof:placetype":"venue"
},
  "geometry": {"coordinates":[-79.939243,40.796696],"type":"Point"}
}