{
  "type": "Feature",
  "properties": {
    "addr:full":"1170 Oneill Hwy Dunmore PA 18512",
    "addr:housenumber":"1170",
    "addr:postcode":"18512",
    "addr:street":"Oneill Hwy",
    "iso:country":"US",
    "sg:address":"1170 Oneill Hwy",
    "sg:city":"Dunmore",
    "sg:classifiers":[
        {
            "category":"Restaurant",
            "type":"Food & Drink"
        }
    ],
    "sg:menulink":"http://www.allmenus.com/pa/dunmore/172937-wendys/menu/",
    "sg:phone":"+1 570 347 4466",
    "sg:postcode":"18512",
    "sg:province":"PA",
    "sg:tags":[
        "burger",
        "american",
        "soup"
    ],
    "wof:name":"Wendy's",
    "wof:placetype":"venue"
},
  "geometry": {"coordinates":[-75.618527,41.437655],"type":"Point"}
}