{
  "type": "Feature",
  "properties": {
    "addr:full":"53 Main St Strattanville PA 16258",
    "addr:housenumber":"53",
    "addr:postcode":"16258",
    "addr:street":"Main St",
    "iso:country":"US",
    "sg:address":"53 Main St",
    "sg:city":"Strattanville",
    "sg:classifiers":[
        {
            "category":"Retail",
            "subcategory":"Repair Shop",
            "type":"Services"
        }
    ],
    "sg:phone":"+1 814 764 5561",
    "sg:postcode":"16258",
    "sg:province":"PA",
    "sg:tags":[
        "upholsterer"
    ],
    "wof:name":"Williams Upholstery",
    "wof:placetype":"venue"
},
  "geometry": {"coordinates":[-79.31868299999999,41.200926],"type":"Point"}
}