{
  "type": "Feature",
  "properties": {
    "addr:full":"8335 Torresdale Ave Philadelphia PA 19136",
    "addr:housenumber":"8335",
    "addr:postcode":"19136",
    "addr:street":"Torresdale Ave",
    "iso:country":"US",
    "sg:address":"8335 Torresdale Ave",
    "sg:city":"Philadelphia",
    "sg:classifiers":[
        {
            "category":"Retail",
            "subcategory":"Auto Repair",
            "type":"Services"
        }
    ],
    "sg:phone":"+1 215 331 5990",
    "sg:postcode":"19136",
    "sg:province":"PA",
    "sg:tags":[
        "transmission"
    ],
    "wof:name":"Northeast Transmission & Auto",
    "wof:placetype":"venue"
},
  "geometry": {"coordinates":[-75.015443,40.040216],"type":"Point"}
}