{
  "type": "Feature",
  "properties": {
    "iso:country":"US",
    "sg:address":"3100 Cabot Blvd W",
    "sg:city":"Langhorne",
    "sg:classifiers":[
        {
            "category":"Travel",
            "subcategory":"Hotels & Motels",
            "type":"Entertainment"
        }
    ],
    "sg:phone":"+1 215 750 6200",
    "sg:postcode":"19047",
    "sg:province":"PA",
    "sg:tags":[
        "operation"
    ],
    "wof:name":"Red Roof Inn",
    "wof:placetype":"venue"
},
  "geometry": {"coordinates":[-74.87845,40.190556],"type":"Point"}
}