{
  "type": "Feature",
  "properties": {
    "addr:full":"255 S Memorial Hwy Shavertown PA 18708",
    "addr:housenumber":"255",
    "addr:postcode":"18708",
    "addr:street":"S Memorial Hwy",
    "iso:country":"US",
    "sg:address":"255 S Memorial Hwy",
    "sg:city":"Shavertown",
    "sg:classifiers":[
        {
            "category":"Restaurant",
            "type":"Food & Drink"
        }
    ],
    "sg:phone":"+1 570 675 2582",
    "sg:postcode":"18708",
    "sg:province":"PA",
    "sg:tags":[
        "caterer"
    ],
    "wof:name":"Klassic Catering",
    "wof:placetype":"venue"
},
  "geometry": {"coordinates":[-75.927527,41.301167],"type":"Point"}
}