{
  "type": "Feature",
  "properties": {
    "addr:full":"3942 W Ridge Rd Erie PA 16506",
    "addr:housenumber":"3942",
    "addr:postcode":"16506",
    "addr:street":"W Ridge Rd",
    "iso:country":"US",
    "sg:address":"3942 W Ridge Rd",
    "sg:city":"Erie",
    "sg:classifiers":[
        {
            "category":"Real Estate",
            "subcategory":"Real Estate Agent",
            "type":"Services"
        }
    ],
    "sg:phone":"+1   ",
    "sg:postcode":"16506",
    "sg:province":"PA",
    "wof:name":"Richard A Smith Assoc Realtors",
    "wof:placetype":"venue"
},
  "geometry": {"coordinates":[-80.163303,42.079687],"type":"Point"}
}