{
  "type": "Feature",
  "properties": {
    "addr:full":"20 N Hampton St Lock Haven PA 17745",
    "addr:housenumber":"20",
    "addr:postcode":"17745",
    "addr:street":"N Hampton St",
    "iso:country":"US",
    "sg:address":"20 N Hampton St",
    "sg:city":"Lock Haven",
    "sg:classifiers":[
        {
            "category":"Freight",
            "type":"Transportation"
        }
    ],
    "sg:phone":"+1 570 748 7765",
    "sg:postcode":"17745",
    "sg:province":"PA",
    "sg:tags":[
        "vault",
        "safe"
    ],
    "sg:website":"www.atmspecialties.com",
    "wof:name":"ATM Specialties",
    "wof:placetype":"venue"
},
  "geometry": {"coordinates":[-77.460382,41.13221],"type":"Point"}
}