{
  "type": "Feature",
  "properties": {
    "iso:country":"US",
    "sg:address":"310 Lincoln Ave",
    "sg:city":"Bangor",
    "sg:classifiers":[
        {
            "category":"Building & Trades",
            "subcategory":"Construction",
            "type":"Services"
        }
    ],
    "sg:phone":"+1   ",
    "sg:postcode":"18013",
    "sg:province":"PA",
    "sg:tags":[
        "contractor"
    ],
    "wof:name":"Deville Enterprises",
    "wof:placetype":"venue"
},
  "geometry": {"coordinates":[-75.218046,40.879078],"type":"Point"}
}