{
  "type": "Feature",
  "properties": {
    "addr:full":"3535 Gray St Reading PA 19605",
    "addr:housenumber":"3535",
    "addr:postcode":"19605",
    "addr:street":"Gray St",
    "iso:country":"US",
    "sg:address":"3535 Gray St",
    "sg:city":"Reading",
    "sg:classifiers":[
        {
            "category":"Shopping",
            "subcategory":"Jewelry",
            "type":"Retail Goods"
        }
    ],
    "sg:phone":"+1   ",
    "sg:postcode":"19605",
    "sg:province":"PA",
    "wof:name":"Ed Ratajczak",
    "wof:placetype":"venue"
},
  "geometry": {"coordinates":[-75.910115,40.393825],"type":"Point"}
}