{
  "type": "Feature",
  "properties": {
    "iso:country":"US",
    "sg:address":"110 Old Kennett Rd",
    "sg:city":"Kennett Square",
    "sg:classifiers":[
        {
            "category":"Professional",
            "subcategory":"Management & Consulting",
            "type":"Services"
        }
    ],
    "sg:phone":"+1 610 925 1976",
    "sg:postcode":"19348",
    "sg:province":"PA",
    "sg:tags":[
        "counselor",
        "public",
        "relations"
    ],
    "wof:name":"Darman & Assoc",
    "wof:placetype":"venue"
},
  "geometry": {"coordinates":[-75.70217100000001,39.829827],"type":"Point"}
}