{
  "type": "Feature",
  "properties": {
    "addr:full":"203 N Clifton Ave Clifton Heights PA 19018",
    "addr:housenumber":"203",
    "addr:postcode":"19018",
    "addr:street":"N Clifton Ave",
    "iso:country":"US",
    "sg:address":"203 N Clifton Ave",
    "sg:city":"Clifton Heights",
    "sg:classifiers":[
        {
            "category":"Autos & Motor Vehicles",
            "subcategory":"Auto Supplies",
            "type":"Retail Goods"
        }
    ],
    "sg:phone":"+1   ",
    "sg:postcode":"19018",
    "sg:province":"PA",
    "sg:tags":[
        "installer",
        "retailer",
        "tire"
    ],
    "wof:name":"Wheel World Racing",
    "wof:placetype":"venue"
},
  "geometry": {"coordinates":[-75.28949,39.92571],"type":"Point"}
}