{
  "type": "Feature",
  "properties": {
    "iso:country":"US",
    "sg:address":"1180 Mapleview Dr",
    "sg:city":"Washington",
    "sg:classifiers":[
        {
            "category":"Restaurant",
            "type":"Food & Drink"
        }
    ],
    "sg:phone":"+1 724 743 3636",
    "sg:postcode":"15301",
    "sg:province":"PA",
    "sg:tags":[
        "house",
        "seafood",
        "steak",
        "american",
        "barbecue"
    ],
    "sg:website":"http://www.geocities.com/auggiesroadhouse",
    "wof:name":"Auggie's Roadhouse",
    "wof:placetype":"venue"
},
  "geometry": {"coordinates":[-80.185084,40.22571],"type":"Point"}
}