{
  "type": "Feature",
  "properties": {
    "iso:country":"US",
    "sg:address":"203 Franklin Ave",
    "sg:city":"Cheltenham",
    "sg:classifiers":[
        {
            "category":"Building & Trades",
            "subcategory":"Plumbing",
            "type":"Services"
        }
    ],
    "sg:phone":"+1 215 379 3070",
    "sg:postcode":"19012",
    "sg:province":"PA",
    "sg:tags":[
        "contractor"
    ],
    "wof:name":"Paragon Contractors",
    "wof:placetype":"venue"
},
  "geometry": {"coordinates":[-75.092606,40.063034],"type":"Point"}
}