{
  "type": "Feature",
  "properties": {
    "addr:full":"5117 Old Philadelphia Pike Kinzers PA 17535",
    "addr:housenumber":"5117",
    "addr:postcode":"17535",
    "addr:street":"Old Philadelphia Pike",
    "iso:country":"US",
    "sg:address":"5117 Old Philadelphia Pike",
    "sg:city":"Kinzers",
    "sg:classifiers":[
        {
            "category":"Organizations",
            "subcategory":"Religious Organization",
            "type":"Services"
        }
    ],
    "sg:phone":"+1 717 768 4699",
    "sg:postcode":"17535",
    "sg:province":"PA",
    "sg:tags":[
        "church"
    ],
    "wof:name":"Living Hope Intl Ministries",
    "wof:placetype":"venue"
},
  "geometry": {"coordinates":[-76.040308,40.037656],"type":"Point"}
}