{
  "type": "Feature",
  "properties": {
    "addr:full":"1208 Birch Ave Yardley PA 19067",
    "addr:housenumber":"1208",
    "addr:postcode":"19067",
    "addr:street":"Birch Ave",
    "iso:country":"US",
    "sg:address":"1208 Birch Ave",
    "sg:city":"Yardley",
    "sg:classifiers":[
        {
            "category":"Health Services",
            "subcategory":"Doctor",
            "type":"Services"
        }
    ],
    "sg:phone":"+1 215 295 9028",
    "sg:postcode":"19067",
    "sg:province":"PA",
    "sg:tags":[
        "physician",
        "surgeon"
    ],
    "wof:name":"I Sharim Md",
    "wof:placetype":"venue"
},
  "geometry": {"coordinates":[-74.800118,40.215455],"type":"Point"}
}