{
  "type": "Feature",
  "properties": {
    "iso:country":"US",
    "sg:address":"2010 Ridge Rd",
    "sg:city":"Woxall",
    "sg:classifiers":[
        {
            "category":"Wholesale",
            "subcategory":"Auto Parts",
            "type":"Manufacturing & Wholesale Goods"
        }
    ],
    "sg:phone":"+1 215 234 4386",
    "sg:postcode":"18054",
    "sg:province":"PA",
    "sg:tags":[
        "automobile",
        "rebuilt"
    ],
    "sg:website":"www.woodwardtoyota.com",
    "wof:name":"Oren M Woodward & Sons Inc",
    "wof:placetype":"venue"
},
  "geometry": {"coordinates":[-75.439993,40.319697],"type":"Point"}
}