{
  "type": "Feature",
  "properties": {
    "iso:country":"US",
    "sg:address":"1031 Sanatoga Rd",
    "sg:city":"Pottstown",
    "sg:classifiers":[
        {
            "category":"Professional",
            "subcategory":"Accounting & Tax Preparation",
            "type":"Services"
        }
    ],
    "sg:phone":"+1 610 495 1776",
    "sg:postcode":"19465",
    "sg:province":"PA",
    "wof:name":"Medi-Claims Plus",
    "wof:placetype":"venue"
},
  "geometry": {"coordinates":[-75.60627100000001,40.206898],"type":"Point"}
}