{
  "type": "Feature",
  "properties": {
    "addr:full":"233 Mickley Rd Whitehall PA 18052",
    "addr:housenumber":"233",
    "addr:postcode":"18052",
    "addr:street":"Mickley Rd",
    "iso:country":"US",
    "sg:address":"233 Mickley Rd",
    "sg:city":"Whitehall",
    "sg:classifiers":[
        {
            "category":"Building & Trades",
            "subcategory":"Equipment Rental",
            "type":"Services"
        }
    ],
    "sg:phone":"+1 610 435 6990",
    "sg:postcode":"18052",
    "sg:province":"PA",
    "sg:tags":[
        "pay",
        "vending",
        "telephone",
        "maintenance"
    ],
    "wof:name":"Pennsylvania Pay Telephone",
    "wof:placetype":"venue"
},
  "geometry": {"coordinates":[-75.483724,40.621183],"type":"Point"}
}