{
  "type": "Feature",
  "properties": {
    "iso:country":"US",
    "sg:address":"159 S 2nd St",
    "sg:city":"Sunbury",
    "sg:classifiers":[
        {
            "category":"Real Estate",
            "subcategory":"Architect",
            "type":"Services"
        }
    ],
    "sg:phone":"+1   ",
    "sg:postcode":"17801",
    "sg:province":"PA",
    "wof:name":"Architecture By Seiple Ltd",
    "wof:placetype":"venue"
},
  "geometry": {"coordinates":[-76.796093,40.859988],"type":"Point"}
}