{
  "type": "Feature",
  "properties": {
    "iso:country":"US",
    "sg:address":"2243 Hunterstown Hampton Rd",
    "sg:city":"New Oxford",
    "sg:classifiers":[
        {
            "category":"Organizations",
            "subcategory":"Religious Organization",
            "type":"Services"
        }
    ],
    "sg:phone":"+1   ",
    "sg:postcode":"17350",
    "sg:province":"PA",
    "wof:name":"Saint Johns Untd Church Christ",
    "wof:placetype":"venue"
},
  "geometry": {"coordinates":[-77.09442300000001,39.903909],"type":"Point"}
}