{
  "type": "Feature",
  "properties": {
    "addr:full":"1335 Cinnamon Dr Fort Washington PA 19034",
    "addr:housenumber":"1335",
    "addr:postcode":"19034",
    "addr:street":"Cinnamon Dr",
    "iso:country":"US",
    "sg:address":"1335 Cinnamon Dr",
    "sg:city":"Fort Washington",
    "sg:classifiers":[
        {
            "category":"Manufacturing",
            "subcategory":"Printing",
            "type":"Manufacturing & Wholesale Goods"
        }
    ],
    "sg:phone":"+1   ",
    "sg:postcode":"19034",
    "sg:province":"PA",
    "sg:tags":[
        "publishing"
    ],
    "wof:name":"Braymar Publishing Co",
    "wof:placetype":"venue"
},
  "geometry": {"coordinates":[-75.181229,40.146162],"type":"Point"}
}