{
  "type": "Feature",
  "properties": {
    "iso:country":"US",
    "sg:address":"317 Mahoning Ave",
    "sg:city":"New Castle",
    "sg:classifiers":[
        {
            "category":"Retail",
            "subcategory":"Auto Repair",
            "type":"Services"
        }
    ],
    "sg:phone":"+1 724 657 8825",
    "sg:postcode":"16102",
    "sg:province":"PA",
    "sg:tags":[
        "repairing",
        "automobile"
    ],
    "wof:name":"Wilson's Automotive Svc",
    "wof:placetype":"venue"
},
  "geometry": {"coordinates":[-80.357159,40.981843],"type":"Point"}
}