{
  "type": "Feature",
  "properties": {
    "iso:country":"US",
    "sg:address":"323 N Marshall St",
    "sg:city":"Allentown",
    "sg:classifiers":[
        {
            "category":"Professional",
            "subcategory":"Lawyer & Legal Services",
            "type":"Services"
        }
    ],
    "sg:phone":"+1 610 435 9741",
    "sg:postcode":"18104",
    "sg:province":"PA",
    "sg:tags":[
        "attorney"
    ],
    "wof:name":"Michael P Mc Intyre",
    "wof:placetype":"venue"
},
  "geometry": {"coordinates":[-75.523036,40.594117],"type":"Point"}
}