{
  "type": "Feature",
  "properties": {
    "addr:full":"124 Fineview Rd Camp Hill PA 17011",
    "addr:housenumber":"124",
    "addr:postcode":"17011",
    "addr:street":"Fineview Rd",
    "iso:country":"US",
    "sg:address":"124 Fineview Rd",
    "sg:city":"Camp Hill",
    "sg:classifiers":[
        {
            "category":"Real Estate",
            "subcategory":"Real Estate Agent",
            "type":"Services"
        }
    ],
    "sg:phone":"+1 717 763 8008",
    "sg:postcode":"17011",
    "sg:province":"PA",
    "wof:name":"Benjamin De Francesco",
    "wof:placetype":"venue"
},
  "geometry": {"coordinates":[-76.887016,40.21778],"type":"Point"}
}