{
  "type": "Feature",
  "properties": {
    "addr:full":"151 Weller Rd Barto PA 19504",
    "addr:housenumber":"151",
    "addr:postcode":"19504",
    "addr:street":"Weller Rd",
    "iso:country":"US",
    "sg:address":"151 Weller Rd",
    "sg:city":"Barto",
    "sg:classifiers":[
        {
            "category":"Home & Garden",
            "subcategory":"Home Furnishings",
            "type":"Retail Goods"
        }
    ],
    "sg:phone":"+1   ",
    "sg:postcode":"19504",
    "sg:province":"PA",
    "wof:name":"Austerberry Mark",
    "wof:placetype":"venue"
},
  "geometry": {"coordinates":[-75.56524400000001,40.362656],"type":"Point"}
}