{
  "type": "Feature",
  "properties": {
    "iso:country":"US",
    "sg:address":"312 S Ridge Rd",
    "sg:city":"Perkasie",
    "sg:classifiers":[
        {
            "category":"Personal",
            "subcategory":"Beauty Salon",
            "type":"Services"
        }
    ],
    "sg:phone":"+1 215 257 6971",
    "sg:postcode":"18944",
    "sg:province":"PA",
    "wof:name":"Nancy Kuhns Beauty Shop",
    "wof:placetype":"venue"
},
  "geometry": {"coordinates":[-75.30855699999999,40.376216],"type":"Point"}
}