{
  "type": "Feature",
  "properties": {
    "iso:country":"US",
    "sg:address":"114 N Wales Rd",
    "sg:city":"North Wales",
    "sg:classifiers":[
        {
            "category":"Building & Trades",
            "subcategory":"Construction",
            "type":"Services"
        }
    ],
    "sg:phone":"+1   ",
    "sg:postcode":"19454",
    "sg:province":"PA",
    "sg:tags":[
        "excavation",
        "contractor"
    ],
    "wof:name":"C W Excavating",
    "wof:placetype":"venue"
},
  "geometry": {"coordinates":[-75.259264,40.231287],"type":"Point"}
}