{
  "type": "Feature",
  "properties": {
    "iso:country":"US",
    "sg:address":"1201 Moore St",
    "sg:city":"Philadelphia",
    "sg:classifiers":[
        {
            "category":"Shopping",
            "subcategory":"Clothing, Apparel, & Fashions",
            "type":"Retail Goods"
        }
    ],
    "sg:phone":"+1 215 468 0186",
    "sg:postcode":"19148",
    "sg:province":"PA",
    "sg:tags":[
        "tailor",
        "alteration",
        "sewing"
    ],
    "wof:name":"Rita's Alterations",
    "wof:placetype":"venue"
},
  "geometry": {"coordinates":[-75.165398,39.927502],"type":"Point"}
}