{
  "type": "Feature",
  "properties": {
    "iso:country":"US",
    "sg:address":"124 Hamilton St",
    "sg:city":"Indiana",
    "sg:classifiers":[
        {
            "category":"Organizations",
            "subcategory":"Religious Organization",
            "type":"Services"
        }
    ],
    "sg:phone":"+1 724 463 3828",
    "sg:postcode":"15701",
    "sg:province":"PA",
    "sg:tags":[
        "clergy"
    ],
    "wof:name":"Brad Lauster",
    "wof:placetype":"venue"
},
  "geometry": {"coordinates":[-79.18230699999999,40.616631],"type":"Point"}
}