{
  "type": "Feature",
  "properties": {
    "iso:country":"US",
    "sg:address":"1231 Ranck Mill Rd",
    "sg:city":"Lancaster",
    "sg:classifiers":[
        {
            "category":"Manufacturing",
            "subcategory":"Retail Goods",
            "type":"Manufacturing & Wholesale Goods"
        },
        {
            "category":"Wholesale",
            "subcategory":"Durable Goods & Equipment",
            "type":"Manufacturing & Wholesale Goods"
        }
    ],
    "sg:phone":"+1 717 392 7565",
    "sg:postcode":"17602",
    "sg:province":"PA",
    "sg:tags":[
        "fire",
        "extinguisher",
        "product",
        "mfg"
    ],
    "wof:name":"J L Industries",
    "wof:placetype":"venue"
},
  "geometry": {"coordinates":[-76.276145,40.044544],"type":"Point"}
}