{
  "type": "Feature",
  "properties": {
    "iso:country":"US",
    "sg:address":"611 E Main St",
    "sg:city":"Hummelstown",
    "sg:classifiers":[
        {
            "category":"Restaurant",
            "type":"Food & Drink"
        }
    ],
    "sg:phone":"+1   ",
    "sg:postcode":"17036",
    "sg:province":"PA",
    "sg:tags":[
        "eating"
    ],
    "wof:name":"McDonalds",
    "wof:placetype":"venue"
},
  "geometry": {"coordinates":[-76.68958600000001,40.268682],"type":"Point"}
}