{
  "type": "Feature",
  "properties": {
    "addr:full":"410 Lancaster Ave Haverford PA 19041",
    "addr:housenumber":"410",
    "addr:postcode":"19041",
    "addr:street":"Lancaster Ave",
    "iso:country":"US",
    "sg:address":"410 Lancaster Ave",
    "sg:city":"Haverford",
    "sg:classifiers":[
        {
            "category":"Health Services",
            "subcategory":"Clinic",
            "type":"Services"
        }
    ],
    "sg:phone":"+1 610 645 0506",
    "sg:postcode":"19041",
    "sg:province":"PA",
    "sg:tags":[
        "specialty",
        "outpatient"
    ],
    "wof:name":"Pediatric Occupational Therapy",
    "wof:placetype":"venue"
},
  "geometry": {"coordinates":[-75.303284,40.013967],"type":"Point"}
}