{
  "type": "Feature",
  "properties": {
    "iso:country":"US",
    "sg:address":"346 S Main St",
    "sg:city":"Shrewsbury",
    "sg:classifiers":[
        {
            "category":"Social Services",
            "type":"Services"
        }
    ],
    "sg:phone":"+1 717 235 3629",
    "sg:postcode":"17361",
    "sg:province":"PA",
    "sg:tags":[
        "agency",
        "adoption"
    ],
    "wof:name":"Adoption Services Inc",
    "wof:placetype":"venue"
},
  "geometry": {"coordinates":[-76.678003,39.755941],"type":"Point"}
}