{
  "type": "Feature",
  "properties": {
    "iso:country":"US",
    "sg:address":"119 Sandro St",
    "sg:city":"Indiana",
    "sg:classifiers":[
        {
            "category":"Health Services",
            "subcategory":"Doctor",
            "type":"Services"
        }
    ],
    "sg:phone":"+1   ",
    "sg:postcode":"15701",
    "sg:province":"PA",
    "sg:tags":[
        "medical"
    ],
    "wof:name":"Sharad Ghate MD",
    "wof:placetype":"venue"
},
  "geometry": {"coordinates":[-79.144155,40.573369],"type":"Point"}
}