{
  "type": "Feature",
  "properties": {
    "iso:country":"US",
    "sg:address":"1505 Makefield Rd",
    "sg:city":"Morrisville",
    "sg:classifiers":[
        {
            "category":"Social Services",
            "subcategory":"Child Care",
            "type":"Services"
        }
    ],
    "sg:phone":"+1   ",
    "sg:postcode":"19067",
    "sg:province":"PA",
    "sg:tags":[
        "day"
    ],
    "wof:name":"Loch Industries",
    "wof:placetype":"venue"
},
  "geometry": {"coordinates":[-74.82257799999999,40.208442],"type":"Point"}
}