{
  "type": "Feature",
  "properties": {
    "addr:full":"4611 Wayne Ave Philadelphia PA 19144",
    "addr:housenumber":"4611",
    "addr:postcode":"19144",
    "addr:street":"Wayne Ave",
    "iso:country":"US",
    "sg:address":"4611 Wayne Ave",
    "sg:city":"Philadelphia",
    "sg:classifiers":[
        {
            "category":"Banks & Credit Unions",
            "subcategory":"Bank",
            "type":"Services"
        }
    ],
    "sg:phone":"+1   ",
    "sg:postcode":"19144",
    "sg:province":"PA",
    "sg:tags":[
        "broker",
        "mortgage"
    ],
    "wof:name":"American Mrtg Spcialists 1 Inc",
    "wof:placetype":"venue"
},
  "geometry": {"coordinates":[-75.16349099999999,40.02312],"type":"Point"}
}