{
  "type": "Feature",
  "properties": {
    "iso:country":"US",
    "sg:address":"706 Cherry Ln",
    "sg:city":"Clearville",
    "sg:classifiers":[
        {
            "category":"Professional",
            "type":"Services"
        }
    ],
    "sg:phone":"+1   ",
    "sg:postcode":"15535",
    "sg:province":"PA",
    "wof:name":"Brandon Chamberlain",
    "wof:placetype":"venue"
},
  "geometry": {"coordinates":[-78.384511,39.91813],"type":"Point"}
}