{
  "type": "Feature",
  "properties": {
    "iso:country":"US",
    "sg:address":"1022 Filmore Ave",
    "sg:city":"Erie",
    "sg:classifiers":[
        {
            "category":"Real Estate",
            "subcategory":"Real Estate Operator",
            "type":"Services"
        }
    ],
    "sg:phone":"+1   ",
    "sg:postcode":"16505",
    "sg:province":"PA",
    "sg:tags":[
        "building",
        "apartment"
    ],
    "wof:name":"Renewed Rentals",
    "wof:placetype":"venue"
},
  "geometry": {"coordinates":[-80.143666,42.102001],"type":"Point"}
}