{
  "type": "Feature",
  "properties": {
    "addr:full":"4403 Peach St Erie PA 16509",
    "addr:housenumber":"4403",
    "addr:postcode":"16509",
    "addr:street":"Peach St",
    "iso:country":"US",
    "sg:address":"4403 Peach St",
    "sg:city":"Erie",
    "sg:classifiers":[
        {
            "category":"Bakery",
            "type":"Food & Drink"
        }
    ],
    "sg:menulink":"http://www.allmenus.com/pa/erie/102216-perkins-restaurant--bakery/menu/",
    "sg:phone":"+1 814 864 0497",
    "sg:postcode":"16509",
    "sg:province":"PA",
    "sg:tags":[
        "sandwich",
        "salad",
        "soup",
        "american",
        "pastry",
        "wrap"
    ],
    "wof:name":"Perkins Restaurant & Bakery",
    "wof:placetype":"venue"
},
  "geometry": {"coordinates":[-80.086285,42.088394],"type":"Point"}
}