{
  "type": "Feature",
  "properties": {
    "iso:country":"US",
    "sg:address":"770 2nd Street Pike Ste B",
    "sg:city":"Richboro",
    "sg:classifiers":[
        {
            "category":"Airline",
            "type":"Transportation"
        },
        {
            "category":"Travel",
            "subcategory":"Travel Agent",
            "type":"Entertainment"
        }
    ],
    "sg:phone":"+1 215 322 0120",
    "sg:postcode":"18954",
    "sg:province":"PA",
    "sg:tags":[
        "ticket",
        "agency",
        "services-commercial"
    ],
    "wof:name":"Richboro Travel Service, Inc",
    "wof:placetype":"venue"
},
  "geometry": {"coordinates":[-75.015145,40.208339],"type":"Point"}
}