{
  "type": "Feature",
  "properties": {
    "iso:country":"US",
    "sg:address":"2011 Strouse Rd",
    "sg:city":"Williamsport",
    "sg:classifiers":[
        {
            "category":"Retail",
            "subcategory":"Auto Repair",
            "type":"Services"
        }
    ],
    "sg:phone":"+1 570 494 2362",
    "sg:postcode":"17701",
    "sg:province":"PA",
    "sg:tags":[
        "repairing",
        "automobile"
    ],
    "wof:name":"Lycoming Auto Svc",
    "wof:placetype":"venue"
},
  "geometry": {"coordinates":[-77.052791,41.28422],"type":"Point"}
}