{
  "type": "Feature",
  "properties": {
    "addr:full":"1002 2nd St Cresson PA 16630",
    "addr:housenumber":"1002",
    "addr:postcode":"16630",
    "addr:street":"2Nd St",
    "iso:country":"US",
    "sg:address":"1002 2nd St",
    "sg:city":"Cresson",
    "sg:classifiers":[
        {
            "category":"Food & Beverages",
            "subcategory":"Groceries & Convenience Stores",
            "type":"Retail Goods"
        }
    ],
    "sg:phone":"+1   ",
    "sg:postcode":"16630",
    "sg:province":"PA",
    "wof:name":"West End Market",
    "wof:placetype":"venue"
},
  "geometry": {"coordinates":[-78.591106,40.460727],"type":"Point"}
}