{
  "type": "Feature",
  "properties": {
    "addr:full":"601 E Dubois Ave Du Bois PA 15801",
    "addr:housenumber":"601",
    "addr:postcode":"15801",
    "addr:street":"E Dubois Ave Du Bois",
    "iso:country":"US",
    "sg:address":"601 E Dubois Ave",
    "sg:city":"Du Bois",
    "sg:classifiers":[
        {
            "category":"Manufacturing",
            "subcategory":"Food",
            "type":"Manufacturing & Wholesale Goods"
        }
    ],
    "sg:phone":"+1 814 371 2920",
    "sg:postcode":"15801",
    "sg:province":"PA",
    "sg:tags":[
        "bottler"
    ],
    "wof:name":"Coca-Cola Bottling Co",
    "wof:placetype":"venue"
},
  "geometry": {"coordinates":[-78.746706,41.12538],"type":"Point"}
}