{
  "type": "Feature",
  "properties": {
    "addr:full":"1419 Hubbard St Pittsburgh PA 15212",
    "addr:housenumber":"1419",
    "addr:postcode":"15212",
    "addr:street":"Hubbard St",
    "iso:country":"US",
    "sg:address":"1419 Hubbard St",
    "sg:city":"Pittsburgh",
    "sg:classifiers":[
        {
            "category":"Manufacturing",
            "subcategory":"Printing",
            "type":"Manufacturing & Wholesale Goods"
        }
    ],
    "sg:phone":"+1   ",
    "sg:postcode":"15212",
    "sg:province":"PA",
    "sg:tags":[
        "miscellaneous",
        "publishing"
    ],
    "wof:name":"Fraidy Kat Design",
    "wof:placetype":"venue"
},
  "geometry": {"coordinates":[-80.03652099999999,40.478068],"type":"Point"}
}