{
  "type": "Feature",
  "properties": {
    "iso:country":"US",
    "sg:address":"110 Franklin St Ste 500",
    "sg:city":"Johnstown",
    "sg:classifiers":[
        {
            "category":"Health Services",
            "subcategory":"Medical Lab",
            "type":"Services"
        }
    ],
    "sg:phone":"+1 814 539 9057",
    "sg:postcode":"15901",
    "sg:province":"PA",
    "wof:name":"Pennsylvania State Coroners Association",
    "wof:placetype":"venue"
},
  "geometry": {"coordinates":[-78.917168,40.32629],"type":"Point"}
}