{
  "type": "Feature",
  "properties": {
    "iso:country":"US",
    "sg:address":"20 Donaldson St",
    "sg:city":"Doylestown",
    "sg:classifiers":[
        {
            "category":"Shopping",
            "subcategory":"Books",
            "type":"Retail Goods"
        }
    ],
    "sg:phone":"+1   ",
    "sg:postcode":"18901",
    "sg:province":"PA",
    "wof:name":"Booktenders Childrens Bkstr",
    "wof:placetype":"venue"
},
  "geometry": {"coordinates":[-75.129504,40.310266],"type":"Point"}
}