{
  "type": "Feature",
  "properties": {
    "addr:full":"43 S Lansdowne Ave Lansdowne PA 19050",
    "addr:housenumber":"43",
    "addr:postcode":"19050",
    "addr:street":"S Lansdowne Ave",
    "iso:country":"US",
    "sg:address":"43 S Lansdowne Ave",
    "sg:city":"Lansdowne",
    "sg:classifiers":[
        {
            "category":"Health Services",
            "subcategory":"Dentist",
            "type":"Services"
        }
    ],
    "sg:phone":"+1 215 792 6140",
    "sg:postcode":"19050",
    "sg:province":"PA",
    "sg:tags":[
        "denture",
        "dentists-prosthodontists"
    ],
    "sg:website":"http://Appledenturecenter.com",
    "wof:name":"Apple Denture Center P.C. - Joel B Cooper D.M.D",
    "wof:placetype":"venue"
},
  "geometry": {"coordinates":[-75.27199299999999,39.936698],"type":"Point"}
}