{
  "type": "Feature",
  "properties": {
    "addr:full":"4971 State Rte 287 Salladasburg PA 17740",
    "addr:housenumber":"4971",
    "addr:postcode":"17740",
    "addr:street":"State Rte 287 Salladasburg",
    "iso:country":"US",
    "sg:address":"4971 State Rte 287",
    "sg:city":"Salladasburg",
    "sg:classifiers":[
        {
            "category":"Personal",
            "subcategory":"Beauty Salon",
            "type":"Services"
        }
    ],
    "sg:phone":"+1 570 398 4681",
    "sg:postcode":"17740",
    "sg:province":"PA",
    "wof:name":"Shirley Sellinger Beauty Salon",
    "wof:placetype":"venue"
},
  "geometry": {"coordinates":[-77.228071,41.286901],"type":"Point"}
}