{
  "type": "Feature",
  "properties": {
    "iso:country":"US",
    "sg:address":"310 Clifford Ave",
    "sg:city":"Apollo",
    "sg:classifiers":[
        {
            "category":"Home & Garden",
            "subcategory":"Building Materials",
            "type":"Retail Goods"
        }
    ],
    "sg:phone":"+1   ",
    "sg:postcode":"15613",
    "sg:province":"PA",
    "wof:name":"Stanford Home Center",
    "wof:placetype":"venue"
},
  "geometry": {"coordinates":[-79.568319,40.583942],"type":"Point"}
}