{
  "type": "Feature",
  "properties": {
    "iso:country":"US",
    "sg:address":"12 W Germantown Pike",
    "sg:city":"Norristown",
    "sg:classifiers":[
        {
            "category":"Retail",
            "subcategory":"Auto Repair",
            "type":"Services"
        }
    ],
    "sg:phone":"+1 610 277 7075",
    "sg:postcode":"19401",
    "sg:province":"PA",
    "sg:tags":[
        "automotive"
    ],
    "sg:website":"www.jiffylube.com",
    "wof:name":"Jiffy Lube",
    "wof:placetype":"venue"
},
  "geometry": {"coordinates":[-75.31300400000001,40.1423],"type":"Point"}
}