{
  "type": "Feature",
  "properties": {
    "iso:country":"US",
    "sg:address":"321 W State St",
    "sg:city":"Media",
    "sg:classifiers":[
        {
            "category":"Arts & Performance",
            "subcategory":"Theater",
            "type":"Entertainment"
        }
    ],
    "sg:phone":"+1   ",
    "sg:postcode":"19063",
    "sg:province":"PA",
    "wof:name":"S P A",
    "wof:placetype":"venue"
},
  "geometry": {"coordinates":[-75.394566,39.918721],"type":"Point"}
}