{
  "type": "Feature",
  "properties": {
    "iso:country":"US",
    "sg:address":"622 S 4th St Ste 63671",
    "sg:city":"Philadelphia",
    "sg:classifiers":[
        {
            "category":"Transit Center",
            "subcategory":"Passenger",
            "type":"Transportation"
        }
    ],
    "sg:phone":"+1 877 245 3877",
    "sg:postcode":"19147",
    "sg:province":"PA",
    "sg:website":"www.chariotsofphilly.com",
    "wof:name":"Chariots Of Philly",
    "wof:placetype":"venue"
},
  "geometry": {"coordinates":[-75.149238,39.941443],"type":"Point"}
}