{
  "type": "Feature",
  "properties": {
    "addr:full":"111 Pinehurst Ln Gibsonia PA 15044",
    "addr:housenumber":"111",
    "addr:postcode":"15044",
    "addr:street":"Pinehurst Ln",
    "iso:country":"US",
    "sg:address":"111 Pinehurst Ln",
    "sg:city":"Gibsonia",
    "sg:classifiers":[
        {
            "category":"Wholesale",
            "subcategory":"Auto Parts",
            "type":"Manufacturing & Wholesale Goods"
        }
    ],
    "sg:phone":"+1   ",
    "sg:postcode":"15044",
    "sg:province":"PA",
    "sg:tags":[
        "automobile",
        "representative",
        "mfg"
    ],
    "wof:name":"Seifert-Mulcahey Associates",
    "wof:placetype":"venue"
},
  "geometry": {"coordinates":[-80.02310300000001,40.672137],"type":"Point"}
}