{
  "type": "Feature",
  "properties": {
    "iso:country":"US",
    "sg:address":"6001 University Blvd",
    "sg:city":"Coraopolis",
    "sg:classifiers":[
        {
            "category":"Education",
            "subcategory":"Library",
            "type":"Public Place"
        },
        {
            "category":"Shopping",
            "subcategory":"Books",
            "type":"Retail Goods"
        },
        {
            "category":"Education",
            "subcategory":"University",
            "type":"Public Place"
        },
        {
            "category":"Education",
            "subcategory":"School",
            "type":"Public Place"
        }
    ],
    "sg:phone":"+1 412 262 8200",
    "sg:postcode":"15108",
    "sg:province":"PA",
    "sg:tags":[
        "college",
        "store"
    ],
    "sg:website":"http://www.bkstore.com",
    "wof:name":"Robert Morris University",
    "wof:placetype":"venue"
},
  "geometry": {"coordinates":[-80.21785,40.519772],"type":"Point"}
}