{
  "type": "Feature",
  "properties": {
    "addr:full":"101 W Middle St Gettysburg PA 17325",
    "addr:housenumber":"101",
    "addr:postcode":"17325",
    "addr:street":"W Middle St",
    "iso:country":"US",
    "sg:address":"101 W Middle St",
    "sg:city":"Gettysburg",
    "sg:classifiers":[
        {
            "category":"Professional",
            "subcategory":"Lawyer & Legal Services",
            "type":"Services"
        }
    ],
    "sg:phone":"+1 717 337 3353",
    "sg:postcode":"17325",
    "sg:province":"PA",
    "sg:tags":[
        "attorney"
    ],
    "wof:name":"John W Phillips Law Office",
    "wof:placetype":"venue"
},
  "geometry": {"coordinates":[-77.23330199999999,39.829724],"type":"Point"}
}