{
  "type": "Feature",
  "properties": {
    "iso:country":"US",
    "sg:address":"207 Dekalb St",
    "sg:city":"Bridgeport",
    "sg:classifiers":[
        {
            "category":"Professional",
            "subcategory":"Advertising",
            "type":"Services"
        }
    ],
    "sg:phone":"+1   ",
    "sg:postcode":"19405",
    "sg:province":"PA",
    "sg:tags":[
        "representative"
    ],
    "wof:name":"Graphic Solutions",
    "wof:placetype":"venue"
},
  "geometry": {"coordinates":[-75.345755,40.107398],"type":"Point"}
}