{
  "type": "Feature",
  "properties": {
    "addr:full":"440 N 8th St Philadelphia PA 19123",
    "addr:housenumber":"440",
    "addr:postcode":"19123",
    "addr:street":"N 8Th St",
    "iso:country":"US",
    "sg:address":"440 N 8th St",
    "sg:city":"Philadelphia",
    "sg:classifiers":[
        {
            "category":"Local Transit",
            "type":"Transportation"
        }
    ],
    "sg:phone":"+1 215 626 2600",
    "sg:postcode":"19123",
    "sg:province":"PA",
    "sg:tags":[
        "ambulance"
    ],
    "wof:name":"Med Tech Ambulance Svc Inc",
    "wof:placetype":"venue"
},
  "geometry": {"coordinates":[-75.151881,39.960507],"type":"Point"}
}