{
  "type": "Feature",
  "properties": {
    "iso:country":"US",
    "sg:address":"1143 Cochrans Mill Rd",
    "sg:city":"Pleasant Hills",
    "sg:classifiers":[
        {
            "category":"Professional",
            "subcategory":"Accounting & Tax Preparation",
            "type":"Services"
        }
    ],
    "sg:phone":"+1 412 653 6129",
    "sg:postcode":"15236",
    "sg:province":"PA",
    "sg:tags":[
        "accountant"
    ],
    "wof:name":"David A Cormany & Assoc",
    "wof:placetype":"venue"
},
  "geometry": {"coordinates":[-79.980388,40.318959],"type":"Point"}
}