{
  "type": "Feature",
  "properties": {
    "addr:full":"120 Charles St Hooversville PA 15936",
    "addr:housenumber":"120",
    "addr:postcode":"15936",
    "addr:street":"Charles St",
    "iso:country":"US",
    "sg:address":"120 Charles St",
    "sg:city":"Hooversville",
    "sg:classifiers":[
        {
            "category":"Organizations",
            "subcategory":"Religious Organization",
            "type":"Services"
        }
    ],
    "sg:phone":"+1 814 798 3671",
    "sg:postcode":"15936",
    "sg:province":"PA",
    "sg:tags":[
        "church"
    ],
    "wof:name":"Hooversville United Methodist",
    "wof:placetype":"venue"
},
  "geometry": {"coordinates":[-78.91204399999999,40.150187],"type":"Point"}
}