{
  "type": "Feature",
  "properties": {
    "iso:country":"US",
    "sg:address":"102 W Union St",
    "sg:city":"Allentown",
    "sg:classifiers":[
        {
            "category":"Retail",
            "subcategory":"Auto Repair",
            "type":"Services"
        }
    ],
    "sg:phone":"+1 610 432 2888",
    "sg:postcode":"18102",
    "sg:province":"PA",
    "wof:name":"J & J Inspection Station",
    "wof:placetype":"venue"
},
  "geometry": {"coordinates":[-75.457149,40.605315],"type":"Point"}
}