{
  "type": "Feature",
  "properties": {
    "iso:country":"US",
    "sg:address":"650 Smithfield St Ste 2600",
    "sg:city":"Pittsburgh",
    "sg:classifiers":[
        {
            "category":"Building & Trades",
            "subcategory":"Construction",
            "type":"Services"
        },
        {
            "category":"Real Estate",
            "subcategory":"Architect",
            "type":"Services"
        }
    ],
    "sg:phone":"+1 412 394 5387",
    "sg:postcode":"15222",
    "sg:province":"PA",
    "sg:tags":[
        "interior",
        "design"
    ],
    "wof:name":"Moore Sara W",
    "wof:placetype":"venue"
},
  "geometry": {"coordinates":[-79.997101,40.442402],"type":"Point"}
}