{
  "type": "Feature",
  "properties": {
    "addr:full":"600 Dresher Rd Horsham PA 19044",
    "addr:housenumber":"600",
    "addr:postcode":"19044",
    "addr:street":"Dresher Rd",
    "iso:country":"US",
    "sg:address":"600 Dresher Rd",
    "sg:city":"Horsham",
    "sg:classifiers":[
        {
            "category":"Insurance",
            "subcategory":"Life Insurance",
            "type":"Services"
        }
    ],
    "sg:phone":"+1 215 956 8000",
    "sg:postcode":"19044",
    "sg:province":"PA",
    "sg:tags":[
        "carrier"
    ],
    "sg:website":"www.pennmutual.com",
    "wof:name":"Penn Mutual Life Insurance Co",
    "wof:placetype":"venue"
},
  "geometry": {"coordinates":[-75.14446599999999,40.168766],"type":"Point"}
}