{
  "type": "Feature",
  "properties": {
    "addr:full":"17 Sweetwater Cir Ambler PA 19002",
    "addr:housenumber":"17",
    "addr:postcode":"19002",
    "addr:street":"Sweetwater Cir",
    "iso:country":"US",
    "sg:address":"17 Sweetwater Cir",
    "sg:city":"Ambler",
    "sg:classifiers":[
        {
            "category":"Real Estate",
            "subcategory":"Real Estate Agent",
            "type":"Services"
        }
    ],
    "sg:phone":"+1   ",
    "sg:postcode":"19002",
    "sg:province":"PA",
    "wof:name":"Ted Rich",
    "wof:placetype":"venue"
},
  "geometry": {"coordinates":[-75.236056,40.190011],"type":"Point"}
}