{
  "type": "Feature",
  "properties": {
    "iso:country":"US",
    "sg:address":"829 Loucks Mill Rd",
    "sg:city":"York",
    "sg:classifiers":[
        {
            "category":"Manufacturing",
            "subcategory":"Metals",
            "type":"Manufacturing & Wholesale Goods"
        }
    ],
    "sg:phone":"+1 717 854 9571",
    "sg:postcode":"17402",
    "sg:province":"PA",
    "sg:tags":[
        "rolling",
        "drawing",
        "aluminum"
    ],
    "wof:name":"New York Wire Co",
    "wof:placetype":"venue"
},
  "geometry": {"coordinates":[-76.722909,39.978298],"type":"Point"}
}