{
  "type": "Feature",
  "properties": {
    "iso:country":"US",
    "sg:address":"5198 Watters Rd",
    "sg:city":"New Kensington",
    "sg:classifiers":[
        {
            "category":"Building & Trades",
            "subcategory":"Construction",
            "type":"Services"
        }
    ],
    "sg:phone":"+1   ",
    "sg:postcode":"15068",
    "sg:province":"PA",
    "sg:tags":[
        "contractor"
    ],
    "wof:name":"Gary Ferich",
    "wof:placetype":"venue"
},
  "geometry": {"coordinates":[-79.67821000000001,40.59185],"type":"Point"}
}