{
  "type": "Feature",
  "properties": {
    "addr:full":"610 Delp Rd Lancaster PA 17601",
    "addr:housenumber":"610",
    "addr:postcode":"17601",
    "addr:street":"Delp Rd",
    "iso:country":"US",
    "sg:address":"610 Delp Rd",
    "sg:city":"Lancaster",
    "sg:classifiers":[
        {
            "category":"Wholesale",
            "subcategory":"Hardware",
            "type":"Manufacturing & Wholesale Goods"
        }
    ],
    "sg:phone":"+1 717 560 4400",
    "sg:postcode":"17601",
    "sg:province":"PA",
    "sg:tags":[
        "parts",
        "refrigerating"
    ],
    "wof:name":"United Refrigeration",
    "wof:placetype":"venue"
},
  "geometry": {"coordinates":[-76.343068,40.084458],"type":"Point"}
}