{
  "type": "Feature",
  "properties": {
    "iso:country":"US",
    "sg:address":"420 E North Ave",
    "sg:city":"Pittsburgh",
    "sg:classifiers":[
        {
            "category":"Health Services",
            "subcategory":"Doctor",
            "type":"Services"
        }
    ],
    "sg:phone":"+1 412 359 6200",
    "sg:postcode":"15212",
    "sg:province":"PA",
    "wof:name":"Whiting Donald MD",
    "wof:placetype":"venue"
},
  "geometry": {"coordinates":[-80.0056,40.460899],"type":"Point"}
}