{
  "type": "Feature",
  "properties": {
    "addr:full":"215 N Main St Milroy PA 17063",
    "addr:housenumber":"215",
    "addr:postcode":"17063",
    "addr:street":"N Main St",
    "iso:country":"US",
    "sg:address":"215 N Main St",
    "sg:city":"Milroy",
    "sg:classifiers":[
        {
            "category":"Banks & Credit Unions",
            "subcategory":"Financial Services",
            "type":"Services"
        }
    ],
    "sg:phone":"+1 717 667 2607",
    "sg:postcode":"17063",
    "sg:province":"PA",
    "sg:tags":[
        "loan",
        "financing"
    ],
    "wof:name":"J & Ds Van Leasing Inc",
    "wof:placetype":"venue"
},
  "geometry": {"coordinates":[-77.59035299999999,40.713911],"type":"Point"}
}