{
  "type": "Feature",
  "properties": {
    "addr:full":"364 E 2nd St Coudersport PA 16915",
    "addr:housenumber":"364",
    "addr:postcode":"16915",
    "addr:street":"E 2Nd St",
    "iso:country":"US",
    "sg:address":"364 E 2nd St",
    "sg:city":"Coudersport",
    "sg:classifiers":[
        {
            "category":"Professional",
            "subcategory":"Accounting & Tax Preparation",
            "type":"Services"
        }
    ],
    "sg:phone":"+1 814 274 8246",
    "sg:postcode":"16915",
    "sg:province":"PA",
    "sg:tags":[
        "return",
        "filing"
    ],
    "wof:name":"H & R Block Tax Svc",
    "wof:placetype":"venue"
},
  "geometry": {"coordinates":[-78.00501199999999,41.774831],"type":"Point"}
}