{
  "type": "Feature",
  "properties": {
    "addr:full":"2090 Mercer West Middlesex Rd Mercer PA 16137",
    "addr:housenumber":"2090",
    "addr:postcode":"16137",
    "addr:street":"Mercer West Middlesex Rd",
    "iso:country":"US",
    "sg:address":"2090 Mercer West Middlesex Rd",
    "sg:city":"Mercer",
    "sg:classifiers":[
        {
            "category":"Organizations",
            "subcategory":"Religious Organization",
            "type":"Services"
        }
    ],
    "sg:phone":"+1 724 347 4752",
    "sg:postcode":"16137",
    "sg:province":"PA",
    "sg:tags":[
        "church"
    ],
    "wof:name":"Lebanon United Presbyterian",
    "wof:placetype":"venue"
},
  "geometry": {"coordinates":[-80.362649,41.19908],"type":"Point"}
}