{
  "type": "Feature",
  "properties": {
    "iso:country":"US",
    "sg:address":"580 W Broadway",
    "sg:city":"Red Lion",
    "sg:classifiers":[
        {
            "category":"Banks & Credit Unions",
            "subcategory":"Bank",
            "type":"Services"
        }
    ],
    "sg:phone":"+1 717 246 1633",
    "sg:postcode":"17356",
    "sg:province":"PA",
    "sg:tags":[
        "loan",
        "real estate"
    ],
    "wof:name":"Waypoint Bank",
    "wof:placetype":"venue"
},
  "geometry": {"coordinates":[-76.61385900000001,39.896976],"type":"Point"}
}