{
  "type": "Feature",
  "properties": {
    "iso:country":"US",
    "sg:address":"661 W Germantown Pike",
    "sg:city":"Plymouth Meeting",
    "sg:classifiers":[
        {
            "category":"Banks & Credit Unions",
            "subcategory":"Bank",
            "type":"Services"
        }
    ],
    "sg:phone":"+1 610 000 1111",
    "sg:postcode":"19462",
    "sg:province":"PA",
    "wof:name":"Bank Of America",
    "wof:placetype":"venue"
},
  "geometry": {"coordinates":[-75.287299,40.119949],"type":"Point"}
}