{
  "type": "Feature",
  "properties": {
    "iso:country":"US",
    "sg:address":"1990 Washington Rd",
    "sg:city":"Washington",
    "sg:classifiers":[
        {
            "category":"Building & Trades",
            "subcategory":"Construction",
            "type":"Services"
        }
    ],
    "sg:phone":"+1 724 746 6700",
    "sg:postcode":"15301",
    "sg:province":"PA",
    "sg:tags":[
        "contractor"
    ],
    "wof:name":"Summit Homes",
    "wof:placetype":"venue"
},
  "geometry": {"coordinates":[-80.18450199999999,40.225201],"type":"Point"}
}