{
  "type": "Feature",
  "properties": {
    "addr:full":"526 S Main St Shrewsbury PA 17361",
    "addr:housenumber":"526",
    "addr:postcode":"17361",
    "addr:street":"S Main St",
    "iso:country":"US",
    "sg:address":"526 S Main St",
    "sg:city":"Shrewsbury",
    "sg:classifiers":[
        {
            "category":"Restaurant",
            "type":"Food & Drink"
        }
    ],
    "sg:phone":"+1 717 227 4846",
    "sg:postcode":"17361",
    "sg:province":"PA",
    "wof:name":"Mama's Pizza",
    "wof:placetype":"venue"
},
  "geometry": {"coordinates":[-76.677639,39.753553],"type":"Point"}
}