{
  "type": "Feature",
  "properties": {
    "iso:country":"US",
    "sg:address":"300 Penn St",
    "sg:city":"Pennsburg",
    "sg:classifiers":[
        {
            "category":"Manufacturing",
            "subcategory":"Retail Goods",
            "type":"Manufacturing & Wholesale Goods"
        }
    ],
    "sg:phone":"+1 215 679 7515",
    "sg:postcode":"18073",
    "sg:province":"PA",
    "sg:tags":[
        "manufacturer"
    ],
    "wof:name":"Mutual Industries Aero Space",
    "wof:placetype":"venue"
},
  "geometry": {"coordinates":[-75.495908,40.399283],"type":"Point"}
}