{
  "type": "Feature",
  "properties": {
    "iso:country":"US",
    "sg:address":"1628 E State St",
    "sg:city":"Hermitage",
    "sg:classifiers":[
        {
            "category":"Real Estate",
            "subcategory":"Real Estate Agent",
            "type":"Services"
        }
    ],
    "sg:phone":"+1 724 347 0145",
    "sg:postcode":"16148",
    "sg:province":"PA",
    "wof:name":"Homeowners Realty Biz",
    "wof:placetype":"venue"
},
  "geometry": {"coordinates":[-80.479416,41.233151],"type":"Point"}
}