{
  "type": "Feature",
  "properties": {
    "iso:country":"US",
    "sg:address":"44 Impala Dr",
    "sg:city":"Dillsburg",
    "sg:classifiers":[
        {
            "category":"Government",
            "subcategory":"Office",
            "type":"Public Place"
        }
    ],
    "sg:phone":"+1   ",
    "sg:postcode":"17019",
    "sg:province":"PA",
    "sg:tags":[
        "banking"
    ],
    "wof:name":"Dept of Banking Pennsylvania",
    "wof:placetype":"venue"
},
  "geometry": {"coordinates":[-77.03319999999999,40.117984],"type":"Point"}
}