{
  "type": "Feature",
  "properties": {
    "addr:full":"956 N Hermitage Rd Hermitage PA 16148",
    "addr:housenumber":"956",
    "addr:postcode":"16148",
    "addr:street":"N Hermitage Rd",
    "iso:country":"US",
    "sg:address":"956 N Hermitage Rd",
    "sg:city":"Hermitage",
    "sg:classifiers":[
        {
            "category":"Shopping",
            "subcategory":"Pharmacy",
            "type":"Retail Goods"
        }
    ],
    "sg:phone":"+1 724 983 8451",
    "sg:postcode":"16148",
    "sg:province":"PA",
    "wof:name":"Medicine Shoppe Pharmacy",
    "wof:placetype":"venue"
},
  "geometry": {"coordinates":[-80.45090999999999,41.252988],"type":"Point"}
}