{
  "type": "Feature",
  "properties": {
    "addr:full":"10786 Wildman Rd Wattsburg PA 16442",
    "addr:housenumber":"10786",
    "addr:postcode":"16442",
    "addr:street":"Wildman Rd",
    "iso:country":"US",
    "sg:address":"10786 Wildman Rd",
    "sg:city":"Wattsburg",
    "sg:classifiers":[
        {
            "category":"Building & Trades",
            "subcategory":"Construction",
            "type":"Services"
        },
        {
            "category":"Military Area",
            "subcategory":"Armory",
            "type":"Public Place"
        }
    ],
    "sg:phone":"+1 814 725 4946",
    "sg:postcode":"16442",
    "sg:province":"PA",
    "sg:tags":[
        "repair",
        "fence-sales",
        "fence",
        "contractor"
    ],
    "wof:name":"Keystone Fence Co",
    "wof:placetype":"venue"
},
  "geometry": {"coordinates":[-79.839533,42.096291],"type":"Point"}
}