{
  "type": "Feature",
  "properties": {
    "iso:country":"US",
    "sg:address":"6832 Frankford Ave",
    "sg:city":"Philadelphia",
    "sg:classifiers":[
        {
            "category":"Autos & Motor Vehicles",
            "subcategory":"Automobile Sales",
            "type":"Retail Goods"
        }
    ],
    "sg:phone":"+1 215 624 8700",
    "sg:postcode":"19135",
    "sg:province":"PA",
    "sg:tags":[
        "car",
        "dealer"
    ],
    "wof:name":"Visco Auto Sales Inc",
    "wof:placetype":"venue"
},
  "geometry": {"coordinates":[-75.050526,40.032472],"type":"Point"}
}