{
  "type": "Feature",
  "properties": {
    "iso:country":"US",
    "sg:address":"7604 City Ave",
    "sg:city":"Philadelphia",
    "sg:classifiers":[
        {
            "category":"Cinema",
            "subcategory":"Movie Rental",
            "type":"Entertainment"
        }
    ],
    "sg:phone":"+1 215 877 0487",
    "sg:postcode":"19151",
    "sg:province":"PA",
    "sg:tags":[
        "leasing",
        "video",
        "disc",
        "tape"
    ],
    "wof:name":"Blockbuster Video",
    "wof:placetype":"venue"
},
  "geometry": {"coordinates":[-75.271415,39.979146],"type":"Point"}
}