{
  "type": "Feature",
  "properties": {
    "iso:country":"US",
    "sg:address":"1 Marlbrook Ln",
    "sg:city":"Lansdale",
    "sg:classifiers":[
        {
            "category":"Real Estate",
            "subcategory":"Real Estate Operator",
            "type":"Services"
        }
    ],
    "sg:phone":"+1 215 368 5210",
    "sg:postcode":"19446",
    "sg:province":"PA",
    "sg:tags":[
        "apartment"
    ],
    "wof:name":"Willowyck At Gwynedd Square",
    "wof:placetype":"venue"
},
  "geometry": {"coordinates":[-75.304703,40.2229],"type":"Point"}
}