{
  "type": "Feature",
  "properties": {
    "addr:full":"230 N 10th St Philadelphia PA 19107",
    "addr:housenumber":"230",
    "addr:postcode":"19107",
    "addr:street":"N 10Th St",
    "iso:country":"US",
    "sg:address":"230 N 10th St",
    "sg:city":"Philadelphia",
    "sg:classifiers":[
        {
            "category":"Shopping",
            "subcategory":"Gifts & Souvenirs",
            "type":"Retail Goods"
        }
    ],
    "sg:phone":"+1 215 928 1962",
    "sg:postcode":"19107",
    "sg:province":"PA",
    "sg:tags":[
        "novelty"
    ],
    "wof:name":"Hong Fook Co",
    "wof:placetype":"venue"
},
  "geometry": {"coordinates":[-75.15574700000001,39.956288],"type":"Point"}
}