{
  "type": "Feature",
  "properties": {
    "iso:country":"US",
    "sg:address":"254 N Lincoln Ave",
    "sg:city":"Lebanon",
    "sg:classifiers":[
        {
            "category":"Real Estate",
            "subcategory":"Real Estate Operator",
            "type":"Services"
        }
    ],
    "sg:phone":"+1 717 274 7520",
    "sg:postcode":"17046",
    "sg:province":"PA",
    "sg:tags":[
        "building",
        "nonresidential"
    ],
    "wof:name":"Lincoln Fifth Corp",
    "wof:placetype":"venue"
},
  "geometry": {"coordinates":[-76.411344,40.344186],"type":"Point"}
}