{
  "type": "Feature",
  "properties": {
    "iso:country":"US",
    "sg:address":"804 N 38th St",
    "sg:city":"Philadelphia",
    "sg:classifiers":[
        {
            "category":"Travel",
            "subcategory":"Bed & Breakfast",
            "type":"Entertainment"
        }
    ],
    "sg:phone":"+1 215 386 7784",
    "sg:postcode":"19104",
    "sg:province":"PA",
    "sg:tags":[
        "boarding",
        "room",
        "house",
        "convalescent",
        "home",
        "nursing"
    ],
    "wof:name":"Ragin's Personal Care Home",
    "wof:placetype":"venue"
},
  "geometry": {"coordinates":[-75.19826399999999,39.968026],"type":"Point"}
}