{
  "type": "Feature",
  "properties": {
    "iso:country":"US",
    "sg:address":"75 Lancaster Ave",
    "sg:city":"Malvern",
    "sg:classifiers":[
        {
            "category":"Education",
            "subcategory":"Special Training",
            "type":"Public Place"
        },
        {
            "category":"Education",
            "subcategory":"Preschool",
            "type":"Public Place"
        },
        {
            "category":"Education",
            "subcategory":"School",
            "type":"Public Place"
        }
    ],
    "sg:phone":"+1 610 240 0442",
    "sg:postcode":"19355",
    "sg:province":"PA",
    "sg:tags":[
        "kindergarten",
        "educational",
        "k-",
        "private"
    ],
    "wof:name":"International Montessori Schl",
    "wof:placetype":"venue"
},
  "geometry": {"coordinates":[-75.52745400000001,40.04339],"type":"Point"}
}