{
  "type": "Feature",
  "properties": {
    "iso:country":"US",
    "sg:address":"119 Fire Academy Rd",
    "sg:city":"Homer City",
    "sg:classifiers":[
        {
            "category":"Manufacturing",
            "subcategory":"Signs",
            "type":"Manufacturing & Wholesale Goods"
        }
    ],
    "sg:phone":"+1 724 479 2499",
    "sg:postcode":"15748",
    "sg:province":"PA",
    "sg:tags":[
        "specialty",
        "mfg"
    ],
    "wof:name":"A Victory Signs",
    "wof:placetype":"venue"
},
  "geometry": {"coordinates":[-79.15272,40.53487],"type":"Point"}
}