{
  "type": "Feature",
  "properties": {
    "iso:country":"US",
    "sg:address":"14 Village Dr",
    "sg:city":"Uwchland",
    "sg:classifiers":[
        {
            "category":"Building & Trades",
            "subcategory":"Construction",
            "type":"Services"
        }
    ],
    "sg:phone":"+1 610 280 6900",
    "sg:postcode":"19473",
    "sg:province":"PA",
    "sg:tags":[
        "contractor"
    ],
    "wof:name":"Chalfont St Giles",
    "wof:placetype":"venue"
},
  "geometry": {"coordinates":[-75.461856,40.273464],"type":"Point"}
}