{
  "type": "Feature",
  "properties": {
    "iso:country":"US",
    "sg:address":"1 Fallowfield Ave",
    "sg:city":"Charleroi",
    "sg:classifiers":[
        {
            "category":"Autos & Motor Vehicles",
            "subcategory":"Auto Supplies",
            "type":"Retail Goods"
        }
    ],
    "sg:phone":"+1 724 489 4114",
    "sg:postcode":"15022",
    "sg:province":"PA",
    "sg:tags":[
        "alternator",
        "generator"
    ],
    "wof:name":"Mon-Valley Alternator",
    "wof:placetype":"venue"
},
  "geometry": {"coordinates":[-79.89370599999999,40.133894],"type":"Point"}
}