{
  "type": "Feature",
  "properties": {
    "addr:full":"14 S Jackson St Media PA 19063",
    "addr:housenumber":"14",
    "addr:postcode":"19063",
    "addr:street":"S Jackson St",
    "iso:country":"US",
    "sg:address":"14 S Jackson St",
    "sg:city":"Media",
    "sg:classifiers":[
        {
            "category":"Wholesale",
            "subcategory":"Electrical",
            "type":"Manufacturing & Wholesale Goods"
        }
    ],
    "sg:phone":"+1 610 891 1433",
    "sg:postcode":"19063",
    "sg:province":"PA",
    "sg:tags":[
        "lighting",
        "fixture",
        "equipment"
    ],
    "sg:website":"www.phillylights.com",
    "wof:name":"Lighting Solutions Inc",
    "wof:placetype":"venue"
},
  "geometry": {"coordinates":[-75.389477,39.917929],"type":"Point"}
}