{
  "type": "Feature",
  "properties": {
    "iso:country":"US",
    "sg:address":"500 Galleria Dr",
    "sg:city":"Johnstown",
    "sg:classifiers":[
        {
            "category":"Food & Beverages",
            "subcategory":"Bakery",
            "type":"Retail Goods"
        }
    ],
    "sg:phone":"+1   ",
    "sg:postcode":"15904",
    "sg:province":"PA",
    "sg:tags":[
        "eating",
        "mfg"
    ],
    "wof:name":"Pretzel Gourmet",
    "wof:placetype":"venue"
},
  "geometry": {"coordinates":[-78.83332299999999,40.302036],"type":"Point"}
}