{
  "type": "Feature",
  "properties": {
    "addr:full":"607 Chicagoan St Mckeesport PA 15135",
    "addr:housenumber":"607",
    "addr:postcode":"15135",
    "addr:street":"Chicagoan St",
    "iso:country":"US",
    "sg:address":"607 Chicagoan St",
    "sg:city":"Mckeesport",
    "sg:classifiers":[
        {
            "category":"Manufacturing",
            "subcategory":"Furniture",
            "type":"Manufacturing & Wholesale Goods"
        }
    ],
    "sg:phone":"+1 412 751 8755",
    "sg:postcode":"15135",
    "sg:province":"PA",
    "sg:tags":[
        "equipment",
        "supply"
    ],
    "wof:name":"Liberty Electronics",
    "wof:placetype":"venue"
},
  "geometry": {"coordinates":[-79.81050500000001,40.312795],"type":"Point"}
}