{
  "type": "Feature",
  "properties": {
    "iso:country":"US",
    "sg:address":"5661 Furnace Hill Rd",
    "sg:city":"Zionsville",
    "sg:classifiers":[
        {
            "category":"Building & Trades",
            "subcategory":"Landscaping Services",
            "type":"Services"
        }
    ],
    "sg:phone":"+1   ",
    "sg:postcode":"18092",
    "sg:province":"PA",
    "sg:tags":[
        "landscape",
        "business"
    ],
    "wof:name":"John F Kennedy PA",
    "wof:placetype":"venue"
},
  "geometry": {"coordinates":[-75.55179099999999,40.481634],"type":"Point"}
}