{
  "type": "Feature",
  "properties": {
    "addr:full":"6823 Paxton St Harrisburg PA 17111",
    "addr:housenumber":"6823",
    "addr:postcode":"17111",
    "addr:street":"Paxton St",
    "iso:country":"US",
    "sg:address":"6823 Paxton St",
    "sg:city":"Harrisburg",
    "sg:classifiers":[
        {
            "category":"Utilities",
            "subcategory":"Fuel Oil & Lpg",
            "type":"Services"
        }
    ],
    "sg:phone":"+1   ",
    "sg:postcode":"17111",
    "sg:province":"PA",
    "sg:tags":[
        "propane",
        "gas"
    ],
    "wof:name":"AmeriGas",
    "wof:placetype":"venue"
},
  "geometry": {"coordinates":[-76.76338699999999,40.261053],"type":"Point"}
}