{
  "type": "Feature",
  "properties": {
    "iso:country":"US",
    "sg:address":"216 Green Ct",
    "sg:city":"Pittsburgh",
    "sg:classifiers":[
        {
            "category":"Banks & Credit Unions",
            "subcategory":"Financial Services",
            "type":"Services"
        }
    ],
    "sg:phone":"+1 412 881 1116",
    "sg:postcode":"15234",
    "sg:province":"PA",
    "sg:tags":[
        "broker",
        "mortgage"
    ],
    "wof:name":"Forbes Financial Group",
    "wof:placetype":"venue"
},
  "geometry": {"coordinates":[-80.012141,40.366608],"type":"Point"}
}