{
  "type": "Feature",
  "properties": {
    "addr:full":"1031 4th Ave Coraopolis PA 15108",
    "addr:housenumber":"1031",
    "addr:postcode":"15108",
    "addr:street":"4Th Ave",
    "iso:country":"US",
    "sg:address":"1031 4th Ave",
    "sg:city":"Coraopolis",
    "sg:classifiers":[
        {
            "category":"Professional",
            "subcategory":"Testing Lab",
            "type":"Services"
        }
    ],
    "sg:phone":"+1   ",
    "sg:postcode":"15108",
    "sg:province":"PA",
    "sg:tags":[
        "laboratory",
        "engineering",
        "material"
    ],
    "wof:name":"Jeff Zell Consultants Inc",
    "wof:placetype":"venue"
},
  "geometry": {"coordinates":[-80.162524,40.518041],"type":"Point"}
}