{
  "type": "Feature",
  "properties": {
    "iso:country":"US",
    "sg:address":"1741 Goucher St",
    "sg:city":"Johnstown",
    "sg:classifiers":[
        {
            "category":"Shopping",
            "subcategory":"Pharmacy",
            "type":"Retail Goods"
        }
    ],
    "sg:phone":"+1   ",
    "sg:postcode":"15905",
    "sg:province":"PA",
    "wof:name":"Westmont Rexall",
    "wof:placetype":"venue"
},
  "geometry": {"coordinates":[-78.954517,40.322323],"type":"Point"}
}