{
  "type": "Feature",
  "properties": {
    "addr:full":"20245 Rte 19 Cranberry Twp PA 16066",
    "addr:housenumber":"20245",
    "addr:postcode":"16066",
    "addr:street":"Rte 19",
    "iso:country":"US",
    "sg:address":"20245 Rte 19",
    "sg:city":"Cranberry Twp",
    "sg:classifiers":[
        {
            "category":"Utilities",
            "subcategory":"Mobile Phone",
            "type":"Services"
        }
    ],
    "sg:phone":"+1 724 743 0243",
    "sg:postcode":"16066",
    "sg:province":"PA",
    "sg:tags":[
        "telephone",
        "cellular"
    ],
    "wof:name":"Wireless Retail Inc",
    "wof:placetype":"venue"
},
  "geometry": {"coordinates":[-80.10206599999999,40.688098],"type":"Point"}
}