{
  "type": "Feature",
  "properties": {
    "iso:country":"US",
    "sg:address":"325 Mc Kinley Ave",
    "sg:city":"East Vandergrift",
    "sg:classifiers":[
        {
            "category":"Organizations",
            "subcategory":"Community Association",
            "type":"Services"
        }
    ],
    "sg:phone":"+1 724 568 1763",
    "sg:postcode":"15629",
    "sg:province":"PA",
    "sg:tags":[
        "club"
    ],
    "wof:name":"Polish Club",
    "wof:placetype":"venue"
},
  "geometry": {"coordinates":[-79.56218200000001,40.598479],"type":"Point"}
}