{
  "type": "Feature",
  "properties": {
    "iso:country":"US",
    "sg:address":"4502 10th Ave",
    "sg:city":"Temple",
    "sg:classifiers":[
        {
            "category":"Building & Trades",
            "subcategory":"Construction",
            "type":"Services"
        }
    ],
    "sg:phone":"+1   ",
    "sg:postcode":"19560",
    "sg:province":"PA",
    "sg:tags":[
        "house",
        "c",
        "hanging",
        "contractor"
    ],
    "wof:name":"Moser & Schwank",
    "wof:placetype":"venue"
},
  "geometry": {"coordinates":[-75.91888899999999,40.403764],"type":"Point"}
}