{
  "type": "Feature",
  "properties": {
    "iso:country":"US",
    "sg:address":"523 Plymouth Rd",
    "sg:city":"Plymouth Meeting",
    "sg:classifiers":[
        {
            "category":"Professional",
            "subcategory":"Management & Consulting",
            "type":"Services"
        }
    ],
    "sg:phone":"+1   ",
    "sg:postcode":"19462",
    "sg:province":"PA",
    "sg:tags":[
        "consultant",
        "health"
    ],
    "wof:name":"Cigna",
    "wof:placetype":"venue"
},
  "geometry": {"coordinates":[-75.298434,40.116198],"type":"Point"}
}