{
  "type": "Feature",
  "properties": {
    "iso:country":"US",
    "sg:address":"115 E Walnut St",
    "sg:city":"Lebanon",
    "sg:classifiers":[
        {
            "category":"Health Services",
            "subcategory":"Doctor",
            "type":"Services"
        }
    ],
    "sg:phone":"+1   ",
    "sg:postcode":"17042",
    "sg:province":"PA",
    "sg:tags":[
        "medical"
    ],
    "wof:name":"Allergy & Asthma Center",
    "wof:placetype":"venue"
},
  "geometry": {"coordinates":[-76.409306,40.337965],"type":"Point"}
}