{
  "type": "Feature",
  "properties": {
    "iso:country":"US",
    "sg:address":"27 Geist Rd",
    "sg:city":"Lancaster",
    "sg:classifiers":[
        {
            "category":"Building & Trades",
            "subcategory":"Landscaping Services",
            "type":"Services"
        }
    ],
    "sg:phone":"+1   ",
    "sg:postcode":"17601",
    "sg:province":"PA",
    "sg:tags":[
        "landscape"
    ],
    "wof:name":"Rays Property Care",
    "wof:placetype":"venue"
},
  "geometry": {"coordinates":[-76.22303599999999,40.080582],"type":"Point"}
}