{
  "type": "Feature",
  "properties": {
    "iso:country":"US",
    "sg:address":"128 W King St",
    "sg:city":"Littlestown",
    "sg:classifiers":[
        {
            "category":"Banks & Credit Unions",
            "subcategory":"Bank",
            "type":"Services"
        }
    ],
    "sg:phone":"+1 717 359 1319",
    "sg:postcode":"17340",
    "sg:province":"PA",
    "sg:tags":[
        "financing"
    ],
    "wof:name":"Summit Financial",
    "wof:placetype":"venue"
},
  "geometry": {"coordinates":[-77.092173,39.743047],"type":"Point"}
}