{
  "type": "Feature",
  "properties": {
    "iso:country":"US",
    "sg:address":"25 S Clinton St",
    "sg:city":"Doylestown",
    "sg:classifiers":[
        {
            "category":"Personal",
            "subcategory":"Barber",
            "type":"Services"
        }
    ],
    "sg:phone":"+1 215 348 0180",
    "sg:postcode":"18901",
    "sg:province":"PA",
    "sg:website":"www.impacthairdesign.com",
    "wof:name":"Impact Hair Designs",
    "wof:placetype":"venue"
},
  "geometry": {"coordinates":[-75.13243799999999,40.308324],"type":"Point"}
}