{
  "type": "Feature",
  "properties": {
    "addr:full":"200 Towne Mall New Castle PA 16101",
    "addr:housenumber":"200",
    "addr:postcode":"16101",
    "addr:street":"Towne Mall",
    "iso:country":"US",
    "sg:address":"200 Towne Mall",
    "sg:city":"New Castle",
    "sg:classifiers":[
        {
            "category":"Shopping",
            "subcategory":"Department Store",
            "type":"Retail Goods"
        }
    ],
    "sg:phone":"+1   ",
    "sg:postcode":"16101",
    "sg:province":"PA",
    "wof:name":"Sears",
    "wof:placetype":"venue"
},
  "geometry": {"coordinates":[-80.346467,40.997626],"type":"Point"}
}