{
  "type": "Feature",
  "properties": {
    "iso:country":"US",
    "sg:address":"125 E High St",
    "sg:city":"Bellefonte",
    "sg:classifiers":[
        {
            "category":"Real Estate",
            "subcategory":"Real Estate Services",
            "type":"Services"
        }
    ],
    "sg:phone":"+1   ",
    "sg:postcode":"16823",
    "sg:province":"PA",
    "sg:tags":[
        "abstract",
        "title"
    ],
    "wof:name":"Epic Settlement Services",
    "wof:placetype":"venue"
},
  "geometry": {"coordinates":[-77.777725,40.912364],"type":"Point"}
}