{
  "type": "Feature",
  "properties": {
    "addr:full":"2168 Old Harrisburg Rd Gettysburg PA 17325",
    "addr:housenumber":"2168",
    "addr:postcode":"17325",
    "addr:street":"Old Harrisburg Rd",
    "iso:country":"US",
    "sg:address":"2168 Old Harrisburg Rd",
    "sg:city":"Gettysburg",
    "sg:classifiers":[
        {
            "category":"Building & Trades",
            "subcategory":"Plumbing",
            "type":"Services"
        }
    ],
    "sg:phone":"+1   ",
    "sg:postcode":"17325",
    "sg:province":"PA",
    "sg:tags":[
        "electrical",
        "contractor"
    ],
    "wof:name":"A W Smith & Associates",
    "wof:placetype":"venue"
},
  "geometry": {"coordinates":[-77.19656500000001,39.882044],"type":"Point"}
}