{
  "type": "Feature",
  "properties": {
    "iso:country":"US",
    "sg:address":"599 Sussex Rd",
    "sg:city":"Wynnewood",
    "sg:classifiers":[
        {
            "category":"Professional",
            "subcategory":"Research",
            "type":"Services"
        }
    ],
    "sg:phone":"+1 610 642 9111",
    "sg:postcode":"19096",
    "sg:province":"PA",
    "sg:tags":[
        "market",
        "analysis"
    ],
    "wof:name":"Epocrates",
    "wof:placetype":"venue"
},
  "geometry": {"coordinates":[-75.28052599999999,39.999133],"type":"Point"}
}