{
  "type": "Feature",
  "properties": {
    "iso:country":"US",
    "sg:address":"419 Wood St",
    "sg:city":"New Bethlehem",
    "sg:classifiers":[
        {
            "category":"Shopping",
            "subcategory":"Computers & Home Electronics",
            "type":"Retail Goods"
        }
    ],
    "sg:phone":"+1   ",
    "sg:postcode":"16242",
    "sg:province":"PA",
    "sg:tags":[
        "mfg"
    ],
    "wof:name":"S M Art Signs",
    "wof:placetype":"venue"
},
  "geometry": {"coordinates":[-79.331541,41.004615],"type":"Point"}
}