{
  "type": "Feature",
  "properties": {
    "iso:country":"US",
    "sg:address":"915 Ridge Ave",
    "sg:city":"Pittsburgh",
    "sg:classifiers":[
        {
            "category":"Professional",
            "subcategory":"Testing Lab",
            "type":"Services"
        }
    ],
    "sg:phone":"+1   ",
    "sg:postcode":"15212",
    "sg:province":"PA",
    "sg:tags":[
        "laboratory"
    ],
    "wof:name":"Sterling Reference Laboratorie",
    "wof:placetype":"venue"
},
  "geometry": {"coordinates":[-80.01699499999999,40.449853],"type":"Point"}
}