{
  "type": "Feature",
  "properties": {
    "addr:full":"6250 Baltimore Ave Lansdowne PA 19050",
    "addr:housenumber":"6250",
    "addr:postcode":"19050",
    "addr:street":"Baltimore Ave",
    "iso:country":"US",
    "sg:address":"6250 Baltimore Ave",
    "sg:city":"Lansdowne",
    "sg:classifiers":[
        {
            "category":"Manufacturing",
            "subcategory":"Paper Products",
            "type":"Manufacturing & Wholesale Goods"
        }
    ],
    "sg:phone":"+1   ",
    "sg:postcode":"19050",
    "sg:province":"PA",
    "sg:tags":[
        "company",
        "holding"
    ],
    "wof:name":"Union Packaging Group Inc",
    "wof:placetype":"venue"
},
  "geometry": {"coordinates":[-75.249352,39.942448],"type":"Point"}
}