{
  "type": "Feature",
  "properties": {
    "iso:country":"US",
    "sg:address":"60 N Washington St",
    "sg:city":"Greencastle",
    "sg:classifiers":[
        {
            "category":"Government",
            "subcategory":"Office",
            "type":"Public Place"
        }
    ],
    "sg:phone":"+1 717 597 9506",
    "sg:postcode":"17225",
    "sg:province":"PA",
    "sg:tags":[
        "parish",
        "government-county"
    ],
    "wof:name":"Police Non Emergency Business",
    "wof:placetype":"venue"
},
  "geometry": {"coordinates":[-77.725519,39.790507],"type":"Point"}
}