{
  "type": "Feature",
  "properties": {
    "iso:country":"US",
    "sg:address":"580 Easton Rd",
    "sg:city":"Warrington",
    "sg:classifiers":[
        {
            "category":"Food & Beverages",
            "subcategory":"Groceries & Convenience Stores",
            "type":"Retail Goods"
        }
    ],
    "sg:phone":"+1 215 343 9745",
    "sg:postcode":"18976",
    "sg:province":"PA",
    "sg:tags":[
        "gas"
    ],
    "wof:name":"A Plus Mini Mart",
    "wof:placetype":"venue"
},
  "geometry": {"coordinates":[-75.13870199999999,40.229099],"type":"Point"}
}