{
  "type": "Feature",
  "properties": {
    "iso:country":"US",
    "sg:address":"300 Conshohocken State Rd",
    "sg:city":"Philadelphia",
    "sg:classifiers":[
        {
            "category":"Professional",
            "subcategory":"Lawyer & Legal Services",
            "type":"Services"
        }
    ],
    "sg:phone":"+1 610 828 8555",
    "sg:postcode":"19102",
    "sg:province":"PA",
    "wof:name":"Chamberlain Hrdlicka",
    "wof:placetype":"venue"
},
  "geometry": {"coordinates":[-75.260457,40.027842],"type":"Point"}
}