{
  "type": "Feature",
  "properties": {
    "iso:country":"US",
    "sg:address":"68 Coulter Ave",
    "sg:city":"Ardmore",
    "sg:classifiers":[
        {
            "category":"Shopping",
            "subcategory":"Clothing, Apparel, & Fashions",
            "type":"Retail Goods"
        }
    ],
    "sg:phone":"+1   ",
    "sg:postcode":"19003",
    "sg:province":"PA",
    "sg:tags":[
        "fur"
    ],
    "wof:name":"Tarnopol Furs",
    "wof:placetype":"venue"
},
  "geometry": {"coordinates":[-75.285774,40.007813],"type":"Point"}
}