{
  "type": "Feature",
  "properties": {
    "iso:country":"US",
    "sg:address":"104 Metoxet St",
    "sg:city":"Ridgway",
    "sg:classifiers":[
        {
            "category":"Health Services",
            "subcategory":"Health Practitioner",
            "type":"Services"
        }
    ],
    "sg:phone":"+1 814 788 5534",
    "sg:postcode":"15853",
    "sg:province":"PA",
    "sg:tags":[
        "pathologist",
        "speech"
    ],
    "wof:name":"Elk Regional Health Ctr",
    "wof:placetype":"venue"
},
  "geometry": {"coordinates":[-78.729765,41.418197],"type":"Point"}
}