{
  "type": "Feature",
  "properties": {
    "iso:country":"US",
    "sg:address":"249 Old Kennett Rd",
    "sg:city":"Kennett Square",
    "sg:classifiers":[
        {
            "category":"Real Estate",
            "subcategory":"Real Estate Operator",
            "type":"Services"
        }
    ],
    "sg:phone":"+1   ",
    "sg:postcode":"19348",
    "sg:province":"PA",
    "sg:tags":[
        "property",
        "lessor"
    ],
    "wof:name":"Apex Property Management",
    "wof:placetype":"venue"
},
  "geometry": {"coordinates":[-75.689455,39.826294],"type":"Point"}
}