{
  "type": "Feature",
  "properties": {
    "addr:full":"1112 S 8th St Philadelphia PA 19147",
    "addr:housenumber":"1112",
    "addr:postcode":"19147",
    "addr:street":"S 8Th St",
    "iso:country":"US",
    "sg:address":"1112 S 8th St",
    "sg:city":"Philadelphia",
    "sg:classifiers":[
        {
            "category":"Retail",
            "subcategory":"Auto Repair",
            "type":"Services"
        }
    ],
    "sg:phone":"+1 800 671 9220",
    "sg:postcode":"19147",
    "sg:province":"PA",
    "sg:tags":[
        "engine",
        "exhaust",
        "exchanging",
        "automotive"
    ],
    "sg:website":"http://www.authorizedmotorservice.com",
    "wof:name":"Authorized Motor Service Inc",
    "wof:placetype":"venue"
},
  "geometry": {"coordinates":[-75.156898,39.936001],"type":"Point"}
}