{
  "type": "Feature",
  "properties": {
    "iso:country":"US",
    "sg:address":"20 Beech St",
    "sg:city":"Carlisle",
    "sg:classifiers":[
        {
            "category":"Building & Trades",
            "subcategory":"Construction",
            "type":"Services"
        }
    ],
    "sg:phone":"+1   ",
    "sg:postcode":"17013",
    "sg:province":"PA",
    "sg:tags":[
        "specializing",
        "industrial",
        "commercial",
        "roof",
        "contractor"
    ],
    "wof:name":"Energy Savers Contracting Inc",
    "wof:placetype":"venue"
},
  "geometry": {"coordinates":[-77.16939000000001,40.194586],"type":"Point"}
}