{
  "type": "Feature",
  "properties": {
    "iso:country":"US",
    "sg:address":"17 Cottage St",
    "sg:city":"Carbondale",
    "sg:classifiers":[
        {
            "category":"Building & Trades",
            "subcategory":"Construction",
            "type":"Services"
        }
    ],
    "sg:phone":"+1   ",
    "sg:postcode":"18407",
    "sg:province":"PA",
    "sg:tags":[
        "contractor"
    ],
    "wof:name":"Mike Staples",
    "wof:placetype":"venue"
},
  "geometry": {"coordinates":[-75.518097,41.563378],"type":"Point"}
}