{
  "type": "Feature",
  "properties": {
    "addr:full":"1705 Pineford Dr Middletown PA 17057",
    "addr:housenumber":"1705",
    "addr:postcode":"17057",
    "addr:street":"Pineford Dr",
    "iso:country":"US",
    "sg:address":"1705 Pineford Dr",
    "sg:city":"Middletown",
    "sg:classifiers":[
        {
            "category":"Organizations",
            "subcategory":"Religious Organization",
            "type":"Services"
        }
    ],
    "sg:phone":"+1 717 236 3111",
    "sg:postcode":"17057",
    "sg:province":"PA",
    "sg:tags":[
        "church"
    ],
    "wof:name":"Hillside Seventh Day Adventist",
    "wof:placetype":"venue"
},
  "geometry": {"coordinates":[-76.71889299999999,40.198533],"type":"Point"}
}