{
  "type": "Feature",
  "properties": {
    "iso:country":"US",
    "sg:address":"1101 Lincoln Hwy",
    "sg:city":"North Versailles",
    "sg:classifiers":[
        {
            "category":"Autos & Motor Vehicles",
            "subcategory":"Automobile Sales",
            "type":"Retail Goods"
        }
    ],
    "sg:phone":"+1 412 829 7666",
    "sg:postcode":"15137",
    "sg:province":"PA",
    "wof:name":"Fisher Auto Sales Inc",
    "wof:placetype":"venue"
},
  "geometry": {"coordinates":[-79.802509,40.377731],"type":"Point"}
}