{
  "type": "Feature",
  "properties": {
    "iso:country":"US",
    "sg:address":"284 W Market St",
    "sg:city":"York",
    "sg:classifiers":[
        {
            "category":"Professional",
            "subcategory":"Advertising",
            "type":"Services"
        }
    ],
    "sg:phone":"+1   ",
    "sg:postcode":"17401",
    "sg:province":"PA",
    "sg:tags":[
        "agency"
    ],
    "wof:name":"Robbins Mktg Communications",
    "wof:placetype":"venue"
},
  "geometry": {"coordinates":[-76.733953,39.96053],"type":"Point"}
}