{
  "type": "Feature",
  "properties": {
    "addr:full":"1500 Vine St Middletown PA 17057",
    "addr:housenumber":"1500",
    "addr:postcode":"17057",
    "addr:street":"Vine St",
    "iso:country":"US",
    "sg:address":"1500 Vine St",
    "sg:city":"Middletown",
    "sg:classifiers":[
        {
            "category":"Recreation",
            "type":"Entertainment"
        }
    ],
    "sg:phone":"+1 717 944 6029",
    "sg:postcode":"17057",
    "sg:province":"PA",
    "wof:name":"Justamere Farm",
    "wof:placetype":"venue"
},
  "geometry": {"coordinates":[-76.721965,40.211169],"type":"Point"}
}