{
  "type": "Feature",
  "properties": {
    "addr:full":"1982 Locust Ln Harrisburg PA 17109",
    "addr:housenumber":"1982",
    "addr:postcode":"17109",
    "addr:street":"Locust Ln",
    "iso:country":"US",
    "sg:address":"1982 Locust Ln",
    "sg:city":"Harrisburg",
    "sg:classifiers":[
        {
            "category":"Communications",
            "subcategory":"Radio Station",
            "type":"Services"
        }
    ],
    "sg:phone":"+1 717 232 8400",
    "sg:postcode":"17109",
    "sg:province":"PA",
    "sg:tags":[
        "broadcasting"
    ],
    "sg:website":"www.radiopa.com",
    "wof:name":"Radio Pennsylvania Network",
    "wof:placetype":"venue"
},
  "geometry": {"coordinates":[-76.860703,40.2869],"type":"Point"}
}