{
  "type": "Feature",
  "properties": {
    "iso:country":"US",
    "sg:address":"410 Short St",
    "sg:city":"Ellwood City",
    "sg:classifiers":[
        {
            "category":"Real Estate",
            "subcategory":"Real Estate Agent",
            "type":"Services"
        }
    ],
    "sg:phone":"+1   ",
    "sg:postcode":"16117",
    "sg:province":"PA",
    "wof:name":"Rj Schill Manor Assoc",
    "wof:placetype":"venue"
},
  "geometry": {"coordinates":[-80.28763499999999,40.857411],"type":"Point"}
}