{
  "type": "Feature",
  "properties": {
    "addr:full":"5120 Harmony Grove Rd Dover PA 17315",
    "addr:housenumber":"5120",
    "addr:postcode":"17315",
    "addr:street":"Harmony Grove Rd",
    "iso:country":"US",
    "sg:address":"5120 Harmony Grove Rd",
    "sg:city":"Dover",
    "sg:classifiers":[
        {
            "category":"Professional",
            "type":"Services"
        }
    ],
    "sg:phone":"+1   ",
    "sg:postcode":"17315",
    "sg:province":"PA",
    "wof:name":"Byers Chassis Kits",
    "wof:placetype":"venue"
},
  "geometry": {"coordinates":[-76.86706599999999,40.007761],"type":"Point"}
}