{
  "type": "Feature",
  "properties": {
    "addr:full":"24 E Main St Ephrata PA 17522",
    "addr:housenumber":"24",
    "addr:postcode":"17522",
    "addr:street":"E Main St",
    "iso:country":"US",
    "sg:address":"24 E Main St",
    "sg:city":"Ephrata",
    "sg:classifiers":[
        {
            "category":"Shopping",
            "subcategory":"Florist",
            "type":"Retail Goods"
        }
    ],
    "sg:phone":"+1 717 859 5800",
    "sg:postcode":"17522",
    "sg:province":"PA",
    "wof:name":"Celebrations",
    "wof:placetype":"venue"
},
  "geometry": {"coordinates":[-76.176766,40.178272],"type":"Point"}
}