{
  "type": "Feature",
  "properties": {
    "iso:country":"US",
    "sg:address":"1543 Church St",
    "sg:city":"Philadelphia",
    "sg:classifiers":[
        {
            "category":"Wholesale",
            "subcategory":"Groceries",
            "type":"Manufacturing & Wholesale Goods"
        }
    ],
    "sg:phone":"+1 215 288 1727",
    "sg:postcode":"19124",
    "sg:province":"PA",
    "sg:tags":[
        "food",
        "product"
    ],
    "wof:name":"New England Pizza System Inc",
    "wof:placetype":"venue"
},
  "geometry": {"coordinates":[-75.088814,40.011088],"type":"Point"}
}