{
  "type": "Feature",
  "properties": {
    "addr:full":"146 N 2nd St Hughesville PA 17737",
    "addr:housenumber":"146",
    "addr:postcode":"17737",
    "addr:street":"N 2Nd St",
    "iso:country":"US",
    "sg:address":"146 N 2nd St",
    "sg:city":"Hughesville",
    "sg:classifiers":[
        {
            "category":"Shopping",
            "subcategory":"Bicycles & Sporting Goods",
            "type":"Retail Goods"
        }
    ],
    "sg:phone":"+1   ",
    "sg:postcode":"17737",
    "sg:province":"PA",
    "wof:name":"Andrews Gun Shop",
    "wof:placetype":"venue"
},
  "geometry": {"coordinates":[-76.720483,41.242949],"type":"Point"}
}