{
  "type": "Feature",
  "properties": {
    "iso:country":"US",
    "sg:address":"117 Starview Ln",
    "sg:city":"Cranberry Twp",
    "sg:classifiers":[
        {
            "category":"Professional",
            "subcategory":"Business Services",
            "type":"Services"
        },
        {
            "category":"Education",
            "subcategory":"Vocational School",
            "type":"Public Place"
        }
    ],
    "sg:phone":"+1 724 742 3260",
    "sg:postcode":"16066",
    "sg:province":"PA",
    "sg:tags":[
        "lecture",
        "management",
        "bureau",
        "seminar"
    ],
    "wof:name":"Advanced Sales Dynamics",
    "wof:placetype":"venue"
},
  "geometry": {"coordinates":[-80.089471,40.708324],"type":"Point"}
}