{
  "type": "Feature",
  "properties": {
    "iso:country":"US",
    "sg:address":"283 Atlas Cherry Valley Rd",
    "sg:city":"Burgettstown",
    "sg:classifiers":[
        {
            "category":"Wholesale",
            "subcategory":"Vending Machines",
            "type":"Manufacturing & Wholesale Goods"
        }
    ],
    "sg:phone":"+1   ",
    "sg:postcode":"15021",
    "sg:province":"PA",
    "sg:tags":[
        "operator"
    ],
    "wof:name":"Verelst Auto Wreaking",
    "wof:placetype":"venue"
},
  "geometry": {"coordinates":[-80.36684,40.354204],"type":"Point"}
}