{
  "type": "Feature",
  "properties": {
    "iso:country":"US",
    "sg:address":"318 Delmont Ave",
    "sg:city":"Belle Vernon",
    "sg:classifiers":[
        {
            "category":"Professional",
            "subcategory":"Computer Services",
            "type":"Services"
        }
    ],
    "sg:phone":"+1   ",
    "sg:postcode":"15012",
    "sg:province":"PA",
    "sg:tags":[
        "related"
    ],
    "wof:name":"Sns Enterprise",
    "wof:placetype":"venue"
},
  "geometry": {"coordinates":[-79.851632,40.125976],"type":"Point"}
}