{
  "type": "Feature",
  "properties": {
    "addr:full":"1046 Harvard Rd Monroeville PA 15146",
    "addr:housenumber":"1046",
    "addr:postcode":"15146",
    "addr:street":"Harvard Rd",
    "iso:country":"US",
    "sg:address":"1046 Harvard Rd",
    "sg:city":"Monroeville",
    "sg:classifiers":[
        {
            "category":"Manufacturing",
            "subcategory":"Tools & Machinery",
            "type":"Manufacturing & Wholesale Goods"
        }
    ],
    "sg:phone":"+1   ",
    "sg:postcode":"15146",
    "sg:province":"PA",
    "sg:tags":[
        "sell",
        "dyeing",
        "for",
        "textile",
        "equipment",
        "promote"
    ],
    "wof:name":"Brazzoli of The Americas Inc",
    "wof:placetype":"venue"
},
  "geometry": {"coordinates":[-79.75336900000001,40.415307],"type":"Point"}
}