{
  "type": "Feature",
  "properties": {
    "addr:full":"44 Natural Springs Rd Gettysburg PA 17325",
    "addr:housenumber":"44",
    "addr:postcode":"17325",
    "addr:street":"Natural Springs Rd",
    "iso:country":"US",
    "sg:address":"44 Natural Springs Rd",
    "sg:city":"Gettysburg",
    "sg:classifiers":[
        {
            "category":"Restaurant",
            "type":"Food & Drink"
        }
    ],
    "sg:phone":"+1   ",
    "sg:postcode":"17325",
    "sg:province":"PA",
    "sg:tags":[
        "eating"
    ],
    "wof:name":"Papa Johns",
    "wof:placetype":"venue"
},
  "geometry": {"coordinates":[-77.208265,39.839551],"type":"Point"}
}