{
  "type": "Feature",
  "properties": {
    "iso:country":"US",
    "sg:address":"4728 Molly Pitcher Hwy",
    "sg:city":"Chambersburg",
    "sg:classifiers":[
        {
            "category":"Autos & Motor Vehicles",
            "subcategory":"Automobile Sales",
            "type":"Retail Goods"
        }
    ],
    "sg:phone":"+1 717 375 2699",
    "sg:postcode":"17201",
    "sg:province":"PA",
    "sg:tags":[
        "truck"
    ],
    "wof:name":"Martin's Farm Trucks",
    "wof:placetype":"venue"
},
  "geometry": {"coordinates":[-77.693262,39.868463],"type":"Point"}
}