{
  "type": "Feature",
  "properties": {
    "iso:country":"US",
    "sg:address":"680 Bridge Valley Rd",
    "sg:city":"Pequea",
    "sg:classifiers":[
        {
            "category":"Building & Trades",
            "subcategory":"Construction",
            "type":"Services"
        }
    ],
    "sg:phone":"+1 717 284 2863",
    "sg:postcode":"17565",
    "sg:province":"PA",
    "sg:tags":[
        "contractor"
    ],
    "wof:name":"Michael R Eshleman",
    "wof:placetype":"venue"
},
  "geometry": {"coordinates":[-76.36811299999999,39.885832],"type":"Point"}
}