{
  "type": "Feature",
  "properties": {
    "addr:full":"705 Chestnut St 384 Emmaus PA 18049",
    "addr:housenumber":"705;384",
    "addr:postcode":"18049",
    "addr:street":"Chestnut St",
    "iso:country":"US",
    "sg:address":"705 Chestnut St 384",
    "sg:city":"Emmaus",
    "sg:classifiers":[
        {
            "category":"Social Services",
            "type":"Services"
        }
    ],
    "sg:phone":"+1 215 234 9677",
    "sg:postcode":"18049",
    "sg:province":"PA",
    "sg:tags":[
        "program",
        "services-information",
        "referral"
    ],
    "wof:name":"Quantum Referrals",
    "wof:placetype":"venue"
},
  "geometry": {"coordinates":[-75.498845,40.532009],"type":"Point"}
}