{
  "type": "Feature",
  "properties": {
    "iso:country":"US",
    "sg:address":"601 Washington Ave",
    "sg:city":"Charleroi",
    "sg:classifiers":[
        {
            "category":"Organizations",
            "subcategory":"Religious Organization",
            "type":"Services"
        }
    ],
    "sg:phone":"+1 724 483 4908",
    "sg:postcode":"15022",
    "sg:province":"PA",
    "sg:tags":[
        "church"
    ],
    "wof:name":"Christ Lutheran Church",
    "wof:placetype":"venue"
},
  "geometry": {"coordinates":[-79.90132699999999,40.139641],"type":"Point"}
}