{
  "type": "Feature",
  "properties": {
    "iso:country":"US",
    "sg:address":"5167 Brownsville Rd",
    "sg:city":"Pittsburgh",
    "sg:classifiers":[
        {
            "category":"Manufacturing",
            "subcategory":"Tools & Machinery",
            "type":"Manufacturing & Wholesale Goods"
        }
    ],
    "sg:phone":"+1 412 653 6678",
    "sg:postcode":"15236",
    "sg:province":"PA",
    "sg:tags":[
        "equipment",
        "industrial",
        "power",
        "mfg"
    ],
    "wof:name":"Vaccari Enterprises Inc",
    "wof:placetype":"venue"
},
  "geometry": {"coordinates":[-79.98643800000001,40.34571],"type":"Point"}
}