{
  "type": "Feature",
  "properties": {
    "addr:full":"184 N Wales Rd North Wales PA 19454",
    "addr:housenumber":"184",
    "addr:postcode":"19454",
    "addr:street":"N Wales Rd",
    "iso:country":"US",
    "sg:address":"184 N Wales Rd",
    "sg:city":"North Wales",
    "sg:classifiers":[
        {
            "category":"Shopping",
            "subcategory":"Gifts & Souvenirs",
            "type":"Retail Goods"
        }
    ],
    "sg:phone":"+1 215 362 5153",
    "sg:postcode":"19454",
    "sg:province":"PA",
    "sg:tags":[
        "shop"
    ],
    "wof:name":"Things Remembered",
    "wof:placetype":"venue"
},
  "geometry": {"coordinates":[-75.25964999999999,40.23113],"type":"Point"}
}