{
  "type": "Feature",
  "properties": {
    "iso:country":"US",
    "sg:address":"4301 Rising Sun Ave",
    "sg:city":"Philadelphia",
    "sg:classifiers":[
        {
            "category":"Education",
            "subcategory":"School",
            "type":"Public Place"
        }
    ],
    "sg:phone":"+1 215 329 5484",
    "sg:postcode":"19140",
    "sg:province":"PA",
    "wof:name":"Safe-Base Family Reunification Program",
    "wof:placetype":"venue"
},
  "geometry": {"coordinates":[-75.12960099999999,40.016102],"type":"Point"}
}