{
  "type": "Feature",
  "properties": {
    "iso:country":"US",
    "sg:address":"1590 Townhall Rd W",
    "sg:city":"Erie",
    "sg:classifiers":[
        {
            "category":"Autos & Motor Vehicles",
            "subcategory":"Auto Supplies",
            "type":"Retail Goods"
        },
        {
            "category":"Wholesale",
            "subcategory":"Auto Parts",
            "type":"Manufacturing & Wholesale Goods"
        }
    ],
    "sg:phone":"+1 814 864 4931",
    "sg:postcode":"16509",
    "sg:province":"PA",
    "sg:tags":[
        "automotive",
        "automobile"
    ],
    "wof:name":"Suburban Auto Supply Company",
    "wof:placetype":"venue"
},
  "geometry": {"coordinates":[-80.05061000000001,42.030622],"type":"Point"}
}