{
  "type": "Feature",
  "properties": {
    "iso:country":"US",
    "sg:address":"818 Rolling Hills Rd",
    "sg:city":"Ottsville",
    "sg:classifiers":[
        {
            "category":"Building & Trades",
            "subcategory":"Construction",
            "type":"Services"
        }
    ],
    "sg:phone":"+1   ",
    "sg:postcode":"18942",
    "sg:province":"PA",
    "sg:tags":[
        "house"
    ],
    "wof:name":"Wayne AA Rickert Construction",
    "wof:placetype":"venue"
},
  "geometry": {"coordinates":[-75.172625,40.43502],"type":"Point"}
}