{
  "type": "Feature",
  "properties": {
    "iso:country":"US",
    "sg:address":"3050 N 5th Street Hwy",
    "sg:city":"Reading",
    "sg:classifiers":[
        {
            "category":"Shopping",
            "subcategory":"Jewelry",
            "type":"Retail Goods"
        }
    ],
    "sg:phone":"+1 610 929 4699",
    "sg:postcode":"19605",
    "sg:province":"PA",
    "sg:tags":[
        "jeweler"
    ],
    "wof:name":"Golden Links",
    "wof:placetype":"venue"
},
  "geometry": {"coordinates":[-75.92755,40.383165],"type":"Point"}
}