{
  "type": "Feature",
  "properties": {
    "addr:full":"145 S Church St Parkesburg PA 19365",
    "addr:housenumber":"145",
    "addr:postcode":"19365",
    "addr:street":"S Church St",
    "iso:country":"US",
    "sg:address":"145 S Church St",
    "sg:city":"Parkesburg",
    "sg:classifiers":[
        {
            "category":"Retail",
            "subcategory":"Auto Repair",
            "type":"Services"
        }
    ],
    "sg:phone":"+1 610 857 3536",
    "sg:postcode":"19365",
    "sg:province":"PA",
    "sg:tags":[
        "repairing",
        "automobile"
    ],
    "wof:name":"Walton's Auto Repair",
    "wof:placetype":"venue"
},
  "geometry": {"coordinates":[-75.91314199999999,39.960024],"type":"Point"}
}