{
  "type": "Feature",
  "properties": {
    "iso:country":"US",
    "sg:address":"5706 Glades Pike",
    "sg:city":"Somerset",
    "sg:classifiers":[
        {
            "category":"Health Services",
            "subcategory":"Clinic",
            "type":"Services"
        }
    ],
    "sg:phone":"+1 814 444 1308",
    "sg:postcode":"15501",
    "sg:province":"PA",
    "wof:name":"PHS Health Svc",
    "wof:placetype":"venue"
},
  "geometry": {"coordinates":[-79.042875,40.002682],"type":"Point"}
}