{
  "type": "Feature",
  "properties": {
    "addr:full":"1905 E Allegheny Ave Philadelphia PA 19134",
    "addr:housenumber":"1905",
    "addr:postcode":"19134",
    "addr:street":"E Allegheny Ave",
    "iso:country":"US",
    "sg:address":"1905 E Allegheny Ave",
    "sg:city":"Philadelphia",
    "sg:classifiers":[
        {
            "category":"Real Estate",
            "subcategory":"Real Estate Services",
            "type":"Services"
        },
        {
            "category":"Real Estate",
            "subcategory":"Surveying",
            "type":"Services"
        },
        {
            "category":"Real Estate",
            "subcategory":"Real Estate Agent",
            "type":"Services"
        }
    ],
    "sg:phone":"+1 215 425 3500",
    "sg:postcode":"19134",
    "sg:province":"PA",
    "sg:tags":[
        "management",
        "appraisers-commercial",
        "broker",
        "industrial",
        "buyer",
        "appraiser"
    ],
    "sg:website":"www.nicksrealestate.com",
    "wof:name":"Nick's Real Estate",
    "wof:placetype":"venue"
},
  "geometry": {"coordinates":[-75.11199999999999,39.995098],"type":"Point"}
}