{
  "type": "Feature",
  "properties": {
    "addr:full":"2301 7th Ave Altoona PA 16602",
    "addr:housenumber":"2301",
    "addr:postcode":"16602",
    "addr:street":"7Th Ave",
    "iso:country":"US",
    "sg:address":"2301 7th Ave",
    "sg:city":"Altoona",
    "sg:classifiers":[
        {
            "category":"Shopping",
            "subcategory":"Discount & Variety Stores",
            "type":"Retail Goods"
        },
        {
            "category":"Home & Garden",
            "subcategory":"Hardware",
            "type":"Retail Goods"
        }
    ],
    "sg:phone":"+1 814 943 0629",
    "sg:postcode":"16602",
    "sg:province":"PA",
    "sg:tags":[
        "operator",
        "dwelling"
    ],
    "wof:name":"Austin's Market",
    "wof:placetype":"venue"
},
  "geometry": {"coordinates":[-78.40661799999999,40.503015],"type":"Point"}
}