{
  "type": "Feature",
  "properties": {
    "iso:country":"US",
    "sg:address":"902 Pulaski Mercer Rd",
    "sg:city":"New Wilmington",
    "sg:classifiers":[
        {
            "category":"Building & Trades",
            "subcategory":"Plumbing",
            "type":"Services"
        }
    ],
    "sg:phone":"+1 724 730 3951",
    "sg:postcode":"16142",
    "sg:province":"PA",
    "sg:tags":[
        "conditioning",
        "air",
        "system",
        "contractor"
    ],
    "wof:name":"Castellan Heating & Cooling",
    "wof:placetype":"venue"
},
  "geometry": {"coordinates":[-80.346299,41.162265],"type":"Point"}
}