{
  "type": "Feature",
  "properties": {
    "iso:country":"US",
    "sg:address":"1665 Bern Rd",
    "sg:city":"Reading",
    "sg:classifiers":[
        {
            "category":"Shopping",
            "subcategory":"Clothing, Apparel, & Fashions",
            "type":"Retail Goods"
        }
    ],
    "sg:phone":"+1   ",
    "sg:postcode":"19610",
    "sg:province":"PA",
    "wof:name":"Victorias Secret",
    "wof:placetype":"venue"
},
  "geometry": {"coordinates":[-75.97273300000001,40.338391],"type":"Point"}
}