{
  "type": "Feature",
  "properties": {
    "iso:country":"US",
    "sg:address":"704 Keystone Rd",
    "sg:city":"Lake Ariel",
    "sg:classifiers":[
        {
            "category":"Professional",
            "subcategory":"Accounting & Tax Preparation",
            "type":"Services"
        }
    ],
    "sg:phone":"+1 570 689 0298",
    "sg:postcode":"18436",
    "sg:province":"PA",
    "sg:tags":[
        "return"
    ],
    "wof:name":"Broody Associates",
    "wof:placetype":"venue"
},
  "geometry": {"coordinates":[-75.39979599999999,41.459723],"type":"Point"}
}