{
  "type": "Feature",
  "properties": {
    "iso:country":"US",
    "sg:address":"74 S Groffdale Rd",
    "sg:city":"Leola",
    "sg:classifiers":[
        {
            "category":"Building & Trades",
            "subcategory":"Equipment Rental",
            "type":"Services"
        }
    ],
    "sg:phone":"+1 717 354 5459",
    "sg:postcode":"17540",
    "sg:province":"PA",
    "sg:tags":[
        "toilet"
    ],
    "wof:name":"Given's Disposal Svc",
    "wof:placetype":"venue"
},
  "geometry": {"coordinates":[-76.138447,40.089816],"type":"Point"}
}