{
  "type": "Feature",
  "properties": {
    "iso:country":"US",
    "sg:address":"950 Greentree Rd",
    "sg:city":"Pittsburgh",
    "sg:classifiers":[
        {
            "category":"Professional",
            "subcategory":"Computer Services",
            "type":"Services"
        }
    ],
    "sg:phone":"+1   ",
    "sg:postcode":"15220",
    "sg:province":"PA",
    "sg:tags":[
        "programing",
        "custom"
    ],
    "wof:name":"Bristol I D Technologies",
    "wof:placetype":"venue"
},
  "geometry": {"coordinates":[-80.046418,40.420536],"type":"Point"}
}