{
  "type": "Feature",
  "properties": {
    "iso:country":"US",
    "sg:address":"619 S Mount Vernon Cir",
    "sg:city":"Bensalem",
    "sg:classifiers":[
        {
            "category":"Building & Trades",
            "subcategory":"Construction",
            "type":"Services"
        }
    ],
    "sg:phone":"+1 610 446 6862",
    "sg:postcode":"19020",
    "sg:province":"PA",
    "sg:tags":[
        "home",
        "builder"
    ],
    "wof:name":"Harwin Homes Bensalem Village",
    "wof:placetype":"venue"
},
  "geometry": {"coordinates":[-74.909339,40.108868],"type":"Point"}
}