{
  "type": "Feature",
  "properties": {
    "iso:country":"US",
    "sg:address":"3545 W Newport Rd",
    "sg:city":"Intercourse",
    "sg:classifiers":[
        {
            "category":"Government",
            "subcategory":"Office",
            "type":"Public Place"
        }
    ],
    "sg:phone":"+1 717 768 8585",
    "sg:postcode":"17572",
    "sg:province":"PA",
    "sg:tags":[
        "village"
    ],
    "sg:website":"www.leacocktwp.com",
    "wof:name":"Leacock Township Supervisors",
    "wof:placetype":"venue"
},
  "geometry": {"coordinates":[-76.112814,40.043152],"type":"Point"}
}