{
  "type": "Feature",
  "properties": {
    "iso:country":"US",
    "sg:address":"2400 Schoenersville Rd",
    "sg:city":"Allentown",
    "sg:classifiers":[
        {
            "category":"Building & Trades",
            "subcategory":"Construction",
            "type":"Services"
        }
    ],
    "sg:phone":"+1 610 264 2680",
    "sg:postcode":"18109",
    "sg:province":"PA",
    "sg:tags":[
        "tile",
        "dealer"
    ],
    "wof:name":"Cari Imported Tiles LTD",
    "wof:placetype":"venue"
},
  "geometry": {"coordinates":[-75.420518,40.659653],"type":"Point"}
}