{
  "type": "Feature",
  "properties": {
    "addr:full":"295 W 49th St Reading PA 19606",
    "addr:housenumber":"295",
    "addr:postcode":"19606",
    "addr:street":"W 49Th St",
    "iso:country":"US",
    "sg:address":"295 W 49th St",
    "sg:city":"Reading",
    "sg:classifiers":[
        {
            "category":"Wholesale",
            "subcategory":"Machinery & Supplies",
            "type":"Manufacturing & Wholesale Goods"
        }
    ],
    "sg:phone":"+1 610 370 1442",
    "sg:postcode":"19606",
    "sg:province":"PA",
    "sg:tags":[
        "equipment",
        "railroad"
    ],
    "wof:name":"J Mikulsky Railway Supply Co",
    "wof:placetype":"venue"
},
  "geometry": {"coordinates":[-75.859775,40.300247],"type":"Point"}
}