{
  "type": "Feature",
  "properties": {
    "iso:country":"US",
    "sg:address":"1608 Walnut St Ste 1700",
    "sg:city":"Philadelphia",
    "sg:classifiers":[
        {
            "category":"Professional",
            "subcategory":"Lawyer & Legal Services",
            "type":"Services"
        }
    ],
    "sg:phone":"+1 215 546 8200",
    "sg:postcode":"19103",
    "sg:province":"PA",
    "sg:tags":[
        "personal",
        "injury"
    ],
    "sg:website":"www.hbnlawfirm.com/",
    "wof:name":"Howard Brenner & Nass PC",
    "wof:placetype":"venue"
},
  "geometry": {"coordinates":[-75.1681,39.949795],"type":"Point"}
}