{
  "type": "Feature",
  "properties": {
    "addr:full":"1142 Basin Rd West Chester PA 19382",
    "addr:housenumber":"1142",
    "addr:postcode":"19382",
    "addr:street":"Basin Rd",
    "iso:country":"US",
    "sg:address":"1142 Basin Rd",
    "sg:city":"West Chester",
    "sg:classifiers":[
        {
            "category":"Insurance",
            "subcategory":"Insurance Agent",
            "type":"Services"
        }
    ],
    "sg:phone":"+1 610 696 8893",
    "sg:postcode":"19382",
    "sg:province":"PA",
    "sg:tags":[
        "adjuster"
    ],
    "wof:name":"Frontier Adjusters America Inc",
    "wof:placetype":"venue"
},
  "geometry": {"coordinates":[-75.5656,39.963824],"type":"Point"}
}