{
  "type": "Feature",
  "properties": {
    "iso:country":"US",
    "sg:address":"6543 Madison St",
    "sg:city":"New Tripoli",
    "sg:classifiers":[
        {
            "category":"Freight",
            "type":"Transportation"
        }
    ],
    "sg:phone":"+1   ",
    "sg:postcode":"18066",
    "sg:province":"PA",
    "sg:tags":[
        "operator",
        "local",
        "trucking"
    ],
    "wof:name":"Squew Trucking",
    "wof:placetype":"venue"
},
  "geometry": {"coordinates":[-75.756935,40.673017],"type":"Point"}
}