{
  "type": "Feature",
  "properties": {
    "addr:full":"5 Lawnton Rd Willow Grove PA 19090",
    "addr:housenumber":"5",
    "addr:postcode":"19090",
    "addr:street":"Lawnton Rd",
    "iso:country":"US",
    "sg:address":"5 Lawnton Rd",
    "sg:city":"Willow Grove",
    "sg:classifiers":[
        {
            "category":"Building & Trades",
            "subcategory":"Construction",
            "type":"Services"
        }
    ],
    "sg:phone":"+1 215 659 2442",
    "sg:postcode":"19090",
    "sg:province":"PA",
    "sg:tags":[
        "house"
    ],
    "wof:name":"Exterior Edge",
    "wof:placetype":"venue"
},
  "geometry": {"coordinates":[-75.126672,40.14871],"type":"Point"}
}