{
  "type": "Feature",
  "properties": {
    "iso:country":"US",
    "sg:address":"235 S 8th St",
    "sg:city":"Philadelphia",
    "sg:classifiers":[
        {
            "category":"Professional",
            "subcategory":"Lawyer & Legal Services",
            "type":"Services"
        }
    ],
    "sg:phone":"+1   ",
    "sg:postcode":"19106",
    "sg:province":"PA",
    "wof:name":"Peruto A Charles",
    "wof:placetype":"venue"
},
  "geometry": {"coordinates":[-75.15466000000001,39.946194],"type":"Point"}
}