{
  "type": "Feature",
  "properties": {
    "iso:country":"US",
    "sg:address":"259 Exton Square Mall",
    "sg:city":"Exton",
    "sg:classifiers":[
        {
            "category":"Shopping",
            "subcategory":"Shoes",
            "type":"Retail Goods"
        }
    ],
    "sg:phone":"+1   ",
    "sg:postcode":"19341",
    "sg:province":"PA",
    "wof:name":"Genesco Inc",
    "wof:placetype":"venue"
},
  "geometry": {"coordinates":[-75.626029,40.032889],"type":"Point"}
}