{
  "type": "Feature",
  "properties": {
    "iso:country":"US",
    "sg:address":"540 Pennsylvania Ave",
    "sg:city":"Fort Washington",
    "sg:classifiers":[
        {
            "category":"Professional",
            "subcategory":"Computer Services",
            "type":"Services"
        }
    ],
    "sg:phone":"+1   ",
    "sg:postcode":"19034",
    "sg:province":"PA",
    "sg:tags":[
        "design",
        "system",
        "programing",
        "custom"
    ],
    "wof:name":"Donor Perfect",
    "wof:placetype":"venue"
},
  "geometry": {"coordinates":[-75.205427,40.13363],"type":"Point"}
}