{
  "type": "Feature",
  "properties": {
    "addr:full":"7970 Orangeville Rd Sharpsville PA 16150",
    "addr:postcode":"7970;16150",
    "addr:street":"Orangeville Rd",
    "iso:country":"US",
    "sg:address":"7970 Orangeville Rd",
    "sg:city":"Sharpsville",
    "sg:classifiers":[
        {
            "category":"Retail",
            "subcategory":"Auto Repair",
            "type":"Services"
        }
    ],
    "sg:phone":"+1 724 646 2811",
    "sg:postcode":"16150",
    "sg:province":"PA",
    "sg:tags":[
        "repairing",
        "automobile"
    ],
    "wof:name":"Frank Myers Automotive",
    "wof:placetype":"venue"
},
  "geometry": {"coordinates":[-80.51912799999999,41.343099],"type":"Point"}
}