{
  "type": "Feature",
  "properties": {
    "addr:full":"3415 Wallace St Erie PA 16504",
    "addr:housenumber":"3415",
    "addr:postcode":"16504",
    "addr:street":"Wallace St",
    "iso:country":"US",
    "sg:address":"3415 Wallace St",
    "sg:city":"Erie",
    "sg:classifiers":[
        {
            "category":"Organizations",
            "subcategory":"Religious Organization",
            "type":"Services"
        }
    ],
    "sg:phone":"+1 814 825 8140",
    "sg:postcode":"16504",
    "sg:province":"PA",
    "sg:tags":[
        "church"
    ],
    "wof:name":"Sts Peter & Paul Catholic Chr",
    "wof:placetype":"venue"
},
  "geometry": {"coordinates":[-80.057485,42.108344],"type":"Point"}
}