{
  "type": "Feature",
  "properties": {
    "iso:country":"US",
    "sg:address":"1001 Lincoln Hwy",
    "sg:city":"Exton",
    "sg:phone":"+1 610 644 7113",
    "sg:postcode":"19320",
    "sg:province":"PA",
    "sg:tags":[
        "oil"
    ],
    "wof:name":"Diamond Fuel Oil",
    "wof:placetype":"venue"
},
  "geometry": {"coordinates":[-75.85125600000001,39.984314],"type":"Point"}
}