{
  "type": "Feature",
  "properties": {
    "iso:country":"US",
    "sg:address":"Northgate Plz",
    "sg:city":"Zelienople",
    "sg:classifiers":[
        {
            "category":"Personal",
            "subcategory":"Barber",
            "type":"Services"
        }
    ],
    "sg:phone":"+1 724 452 5500",
    "sg:postcode":"16063",
    "sg:province":"PA",
    "wof:name":"Super Styles",
    "wof:placetype":"venue"
},
  "geometry": {"coordinates":[-80.137497,40.772301],"type":"Point"}
}