{
  "type": "Feature",
  "properties": {
    "iso:country":"US",
    "sg:address":"841 Chestnut St",
    "sg:city":"Philadelphia",
    "sg:classifiers":[
        {
            "category":"Deli",
            "type":"Food & Drink"
        }
    ],
    "sg:phone":"+1 215 625 0411",
    "sg:postcode":"19107",
    "sg:province":"PA",
    "wof:name":"Express Breakfast & Lunch",
    "wof:placetype":"venue"
},
  "geometry": {"coordinates":[-75.154602,39.949699],"type":"Point"}
}