{
  "type": "Feature",
  "properties": {
    "iso:country":"US",
    "sg:address":"3033 New Butler Rd",
    "sg:city":"New Castle",
    "sg:classifiers":[
        {
            "category":"Organizations",
            "subcategory":"Professional Association",
            "type":"Services"
        }
    ],
    "sg:phone":"+1   ",
    "sg:postcode":"16101",
    "sg:province":"PA",
    "wof:name":"Psea",
    "wof:placetype":"venue"
},
  "geometry": {"coordinates":[-80.274243,40.975211],"type":"Point"}
}