{
  "type": "Feature",
  "properties": {
    "addr:full":"2520 Grant Ave Philadelphia PA 19114",
    "addr:housenumber":"2520",
    "addr:postcode":"19114",
    "addr:street":"Grant Ave",
    "iso:country":"US",
    "sg:address":"2520 Grant Ave",
    "sg:city":"Philadelphia",
    "sg:classifiers":[
        {
            "category":"Banks & Credit Unions",
            "subcategory":"Bank",
            "type":"Services"
        }
    ],
    "sg:phone":"+1 215 673 9155",
    "sg:postcode":"19114",
    "sg:province":"PA",
    "sg:tags":[
        "state",
        "commercial"
    ],
    "wof:name":"Commerce Bank NA",
    "wof:placetype":"venue"
},
  "geometry": {"coordinates":[-75.02184699999999,40.076932],"type":"Point"}
}