{
  "type": "Feature",
  "properties": {
    "addr:full":"10285 Taft St Irwin PA 15642",
    "addr:housenumber":"10285",
    "addr:postcode":"15642",
    "addr:street":"Taft St",
    "iso:country":"US",
    "sg:address":"10285 Taft St",
    "sg:city":"Irwin",
    "sg:classifiers":[
        {
            "category":"Real Estate",
            "subcategory":"Real Estate Agent",
            "type":"Services"
        }
    ],
    "sg:phone":"+1 724 864 3518",
    "sg:postcode":"15642",
    "sg:province":"PA",
    "wof:name":"Norwin Properties Co",
    "wof:placetype":"venue"
},
  "geometry": {"coordinates":[-79.702845,40.338086],"type":"Point"}
}