{
  "type": "Feature",
  "properties": {
    "iso:country":"US",
    "sg:address":"1527 Brandywine St",
    "sg:city":"Philadelphia",
    "sg:classifiers":[
        {
            "category":"Professional",
            "type":"Services"
        }
    ],
    "sg:phone":"+1   ",
    "sg:postcode":"19130",
    "sg:province":"PA",
    "wof:name":"Cindy Lane",
    "wof:placetype":"venue"
},
  "geometry": {"coordinates":[-75.164181,39.963564],"type":"Point"}
}