{
  "type": "Feature",
  "properties": {
    "iso:country":"US",
    "sg:address":"2 Beidler Dr",
    "sg:city":"Shippensburg",
    "sg:classifiers":[
        {
            "category":"Real Estate",
            "subcategory":"Real Estate Operator",
            "type":"Services"
        }
    ],
    "sg:phone":"+1   ",
    "sg:postcode":"17257",
    "sg:province":"PA",
    "sg:tags":[
        "mall",
        "shopping"
    ],
    "wof:name":"Meadowlands Mall Inc",
    "wof:placetype":"venue"
},
  "geometry": {"coordinates":[-77.455275,40.126335],"type":"Point"}
}