{
  "type": "Feature",
  "properties": {
    "iso:country":"US",
    "sg:address":"477 E Main St",
    "sg:city":"Collegeville",
    "sg:classifiers":[
        {
            "category":"Building & Trades",
            "subcategory":"Electrical",
            "type":"Services"
        }
    ],
    "sg:phone":"+1 610 489 6519",
    "sg:postcode":"19426",
    "sg:province":"PA",
    "sg:tags":[
        "electric",
        "contractor"
    ],
    "wof:name":"Dougherty Electric Svc Co",
    "wof:placetype":"venue"
},
  "geometry": {"coordinates":[-75.455541,40.190278],"type":"Point"}
}