{
  "type": "Feature",
  "properties": {
    "addr:full":"8 Old Ridge Village Chadds Ford PA 19317",
    "addr:housenumber":"8",
    "addr:postcode":"19317",
    "addr:street":"Old Ridge Village",
    "iso:country":"US",
    "sg:address":"8 Old Ridge Village",
    "sg:city":"Chadds Ford",
    "sg:classifiers":[
        {
            "category":"Shopping",
            "subcategory":"Florist",
            "type":"Retail Goods"
        }
    ],
    "sg:phone":"+1   ",
    "sg:postcode":"19317",
    "sg:province":"PA",
    "wof:name":"Town and Country Florist",
    "wof:placetype":"venue"
},
  "geometry": {"coordinates":[-75.54734999999999,39.865035],"type":"Point"}
}