{
  "type": "Feature",
  "properties": {
    "iso:country":"US",
    "sg:address":"34 S Railroad St",
    "sg:city":"Tamaqua",
    "sg:classifiers":[
        {
            "category":"Health Services",
            "subcategory":"Doctor",
            "type":"Services"
        }
    ],
    "sg:phone":"+1 570 645 5553",
    "sg:postcode":"18252",
    "sg:province":"PA",
    "sg:tags":[
        "physician",
        "surgeon"
    ],
    "wof:name":"Kailash R Makhijia MD",
    "wof:placetype":"venue"
},
  "geometry": {"coordinates":[-75.970377,40.797029],"type":"Point"}
}