{
  "type": "Feature",
  "properties": {
    "addr:full":"26 Clear Run Dr Shrewsbury PA 17361",
    "addr:housenumber":"26",
    "addr:postcode":"17361",
    "addr:street":"Clear Run Dr",
    "iso:country":"US",
    "sg:address":"26 Clear Run Dr",
    "sg:city":"Shrewsbury",
    "sg:classifiers":[
        {
            "category":"Restaurant",
            "type":"Food & Drink"
        }
    ],
    "sg:phone":"+1   ",
    "sg:postcode":"17361",
    "sg:province":"PA",
    "sg:tags":[
        "eating"
    ],
    "wof:name":"Sopranos Cafe",
    "wof:placetype":"venue"
},
  "geometry": {"coordinates":[-76.675865,39.777955],"type":"Point"}
}