{
  "type": "Feature",
  "properties": {
    "iso:country":"US",
    "sg:address":"14 E Main St",
    "sg:city":"Ringtown",
    "sg:classifiers":[
        {
            "category":"Restaurant",
            "type":"Food & Drink"
        }
    ],
    "sg:phone":"+1   ",
    "sg:postcode":"17967",
    "sg:province":"PA",
    "sg:tags":[
        "eating"
    ],
    "wof:name":"Boyers Country Pizza",
    "wof:placetype":"venue"
},
  "geometry": {"coordinates":[-76.228482,40.859047],"type":"Point"}
}