{
  "type": "Feature",
  "properties": {
    "iso:country":"US",
    "sg:address":"304 N Star Rd",
    "sg:city":"Strasburg",
    "sg:classifiers":[
        {
            "category":"Shopping",
            "subcategory":"Stationery & Office Supplies",
            "type":"Retail Goods"
        },
        {
            "category":"Shopping",
            "subcategory":"Crafts & Fabrics",
            "type":"Retail Goods"
        }
    ],
    "sg:phone":"+1 717 687 9536",
    "sg:postcode":"17579",
    "sg:province":"PA",
    "sg:tags":[
        "art",
        "store"
    ],
    "wof:name":"Rubberbuggy",
    "wof:placetype":"venue"
},
  "geometry": {"coordinates":[-76.182569,39.992466],"type":"Point"}
}