{
  "type": "Feature",
  "properties": {
    "iso:country":"US",
    "sg:address":"1110 Chartiers Ave",
    "sg:city":"Mc Kees Rocks",
    "sg:classifiers":[
        {
            "category":"Professional",
            "subcategory":"Business Services",
            "type":"Services"
        }
    ],
    "sg:phone":"+1 412 771 1896",
    "sg:postcode":"15136",
    "sg:province":"PA",
    "sg:tags":[
        "notary"
    ],
    "wof:name":"Joyce Mays Notary Public",
    "wof:placetype":"venue"
},
  "geometry": {"coordinates":[-80.069,40.464901],"type":"Point"}
}