{
  "type": "Feature",
  "properties": {
    "addr:full":"287 W Main St Hummelstown PA 17036",
    "addr:housenumber":"287",
    "addr:postcode":"17036",
    "addr:street":"W Main St",
    "iso:country":"US",
    "sg:address":"287 W Main St",
    "sg:city":"Hummelstown",
    "sg:classifiers":[
        {
            "category":"Personal",
            "subcategory":"Beauty Salon",
            "type":"Services"
        }
    ],
    "sg:phone":"+1 717 566 0520",
    "sg:postcode":"17036",
    "sg:province":"PA",
    "sg:tags":[
        "shop"
    ],
    "wof:name":"Styles For You By Lisa and Sue",
    "wof:placetype":"venue"
},
  "geometry": {"coordinates":[-76.714566,40.264769],"type":"Point"}
}