{
  "type": "Feature",
  "properties": {
    "addr:full":"201 N Market St Carmichaels PA 15320",
    "addr:housenumber":"201",
    "addr:postcode":"15320",
    "addr:street":"N Market St",
    "iso:country":"US",
    "sg:address":"201 N Market St",
    "sg:city":"Carmichaels",
    "sg:classifiers":[
        {
            "category":"Building & Trades",
            "subcategory":"Plumbing",
            "type":"Services"
        }
    ],
    "sg:phone":"+1   ",
    "sg:postcode":"15320",
    "sg:province":"PA",
    "sg:tags":[
        "contractor"
    ],
    "wof:name":"Novotny Heating & Cooling",
    "wof:placetype":"venue"
},
  "geometry": {"coordinates":[-79.97590599999999,39.897686],"type":"Point"}
}