{
  "type": "Feature",
  "properties": {
    "addr:full":"1109 Brandywine St Philadelphia PA 19123",
    "addr:housenumber":"1109",
    "addr:postcode":"19123",
    "addr:street":"Brandywine St",
    "iso:country":"US",
    "sg:address":"1109 Brandywine St",
    "sg:city":"Philadelphia",
    "sg:classifiers":[
        {
            "category":"Professional",
            "subcategory":"Lawyer & Legal Services",
            "type":"Services"
        }
    ],
    "sg:phone":"+1 215 235 0590",
    "sg:postcode":"19123",
    "sg:province":"PA",
    "wof:name":"Godoy Freddy",
    "wof:placetype":"venue"
},
  "geometry": {"coordinates":[-75.156098,39.962471],"type":"Point"}
}