{
  "type": "Feature",
  "properties": {
    "iso:country":"US",
    "sg:address":"1928 Woodfield Dr",
    "sg:city":"Jamison",
    "sg:classifiers":[
        {
            "category":"Shopping",
            "type":"Retail Goods"
        }
    ],
    "sg:phone":"+1 215 343 4414",
    "sg:postcode":"18929",
    "sg:province":"PA",
    "sg:tags":[
        "religious"
    ],
    "sg:website":"www.spiritualblessing.com",
    "wof:name":"SPIRITUALBLESSING.COM",
    "wof:placetype":"venue"
},
  "geometry": {"coordinates":[-75.09491800000001,40.254739],"type":"Point"}
}