{
  "type": "Feature",
  "properties": {
    "iso:country":"US",
    "sg:address":"670 Overlys Grove Rd",
    "sg:city":"New Holland",
    "sg:classifiers":[
        {
            "category":"Real Estate",
            "subcategory":"Real Estate Agent",
            "type":"Services"
        }
    ],
    "sg:phone":"+1 717 354 8915",
    "sg:postcode":"17557",
    "sg:province":"PA",
    "sg:tags":[
        "cooperative"
    ],
    "wof:name":"Genex Co Op Inc",
    "wof:placetype":"venue"
},
  "geometry": {"coordinates":[-76.046272,40.085413],"type":"Point"}
}