{
  "type": "Feature",
  "properties": {
    "iso:country":"US",
    "sg:address":"122 Penn Ave",
    "sg:city":"Telford",
    "sg:classifiers":[
        {
            "category":"Government",
            "subcategory":"Office",
            "type":"Public Place"
        }
    ],
    "sg:phone":"+1   ",
    "sg:postcode":"18969",
    "sg:province":"PA",
    "sg:tags":[
        "city"
    ],
    "wof:name":"Telford Borough",
    "wof:placetype":"venue"
},
  "geometry": {"coordinates":[-75.329442,40.324383],"type":"Point"}
}