{
  "type": "Feature",
  "properties": {
    "iso:country":"US",
    "sg:address":"310 Grant St",
    "sg:city":"Pittsburgh",
    "sg:classifiers":[
        {
            "category":"Professional",
            "subcategory":"Accounting & Tax Preparation",
            "type":"Services"
        }
    ],
    "sg:phone":"+1 412 281 8270",
    "sg:postcode":"15219",
    "sg:province":"PA",
    "sg:tags":[
        "accountant",
        "public",
        "certified"
    ],
    "wof:name":"Love Scherle & Bauer PC CPA",
    "wof:placetype":"venue"
},
  "geometry": {"coordinates":[-79.997708,40.437975],"type":"Point"}
}