{
  "type": "Feature",
  "properties": {
    "addr:full":"53 Salem Ave Carbondale PA 18407",
    "addr:housenumber":"53",
    "addr:postcode":"18407",
    "addr:street":"Salem Ave",
    "iso:country":"US",
    "sg:address":"53 Salem Ave",
    "sg:city":"Carbondale",
    "sg:classifiers":[
        {
            "category":"Shopping",
            "subcategory":"Jewelry",
            "type":"Retail Goods"
        }
    ],
    "sg:phone":"+1 570 281 9770",
    "sg:postcode":"18407",
    "sg:province":"PA",
    "sg:tags":[
        "jeweler"
    ],
    "wof:name":"Cerminaro Jeweler and Boutique",
    "wof:placetype":"venue"
},
  "geometry": {"coordinates":[-75.500755,41.573063],"type":"Point"}
}