{
  "type": "Feature",
  "properties": {
    "addr:full":"10 Central Ave Cheltenham PA 19012",
    "addr:housenumber":"10",
    "addr:postcode":"19012",
    "addr:street":"Central Ave",
    "iso:country":"US",
    "sg:address":"10 Central Ave",
    "sg:city":"Cheltenham",
    "sg:classifiers":[
        {
            "category":"Insurance",
            "subcategory":"Insurance Agent",
            "type":"Services"
        }
    ],
    "sg:phone":"+1 215 742 3753",
    "sg:postcode":"19012",
    "sg:province":"PA",
    "wof:name":"David J Bernhardt",
    "wof:placetype":"venue"
},
  "geometry": {"coordinates":[-75.09114599999999,40.064605],"type":"Point"}
}