{
  "type": "Feature",
  "properties": {
    "addr:full":"253 Main St Royersford PA 19468",
    "addr:housenumber":"253",
    "addr:postcode":"19468",
    "addr:street":"Main St",
    "iso:country":"US",
    "sg:address":"253 Main St",
    "sg:city":"Royersford",
    "sg:classifiers":[
        {
            "category":"Retail",
            "subcategory":"Repair Shop",
            "type":"Services"
        }
    ],
    "sg:phone":"+1 610 323 1384",
    "sg:postcode":"19468",
    "sg:province":"PA",
    "sg:tags":[
        "television",
        "radio"
    ],
    "wof:name":"Albright & Schwoyer",
    "wof:placetype":"venue"
},
  "geometry": {"coordinates":[-75.541478,40.183617],"type":"Point"}
}