{
  "type": "Feature",
  "properties": {
    "addr:full":"123 S Mechanic St Smethport PA 16749",
    "addr:housenumber":"123",
    "addr:postcode":"16749",
    "addr:street":"S Mechanic St",
    "iso:country":"US",
    "sg:address":"123 S Mechanic St",
    "sg:city":"Smethport",
    "sg:classifiers":[
        {
            "category":"Education",
            "subcategory":"Library",
            "type":"Public Place"
        }
    ],
    "sg:phone":"+1 814 887 9262",
    "sg:postcode":"16749",
    "sg:province":"PA",
    "wof:name":"Hamlin Memorial Library",
    "wof:placetype":"venue"
},
  "geometry": {"coordinates":[-78.441652,41.808575],"type":"Point"}
}