{
  "type": "Feature",
  "properties": {
    "iso:country":"US",
    "sg:address":"418 N Irving St",
    "sg:city":"Allentown",
    "sg:classifiers":[
        {
            "category":"Shopping",
            "subcategory":"Department Store",
            "type":"Retail Goods"
        },
        {
            "category":"Wholesale",
            "subcategory":"Non-durable Goods",
            "type":"Manufacturing & Wholesale Goods"
        },
        {
            "category":"Professional",
            "subcategory":"Business Services",
            "type":"Services"
        },
        {
            "category":"Shopping",
            "subcategory":"Discount & Variety Stores",
            "type":"Retail Goods"
        }
    ],
    "sg:phone":"+1 610 433 9890",
    "sg:postcode":"18109",
    "sg:province":"PA",
    "sg:tags":[
        "broker",
        "merchandise",
        "merchandise-wholesale"
    ],
    "wof:name":"J & L Wholesale Distributor",
    "wof:placetype":"venue"
},
  "geometry": {"coordinates":[-75.44162900000001,40.616315],"type":"Point"}
}