{
  "type": "Feature",
  "properties": {
    "addr:full":"5501 N Front St Philadelphia PA 19120",
    "addr:housenumber":"5501",
    "addr:postcode":"19120",
    "addr:street":"N Front St",
    "iso:country":"US",
    "sg:address":"5501 N Front St",
    "sg:city":"Philadelphia",
    "sg:classifiers":[
        {
            "category":"Restaurant",
            "type":"Food & Drink"
        }
    ],
    "sg:phone":"+1 215 276 1964",
    "sg:postcode":"19120",
    "sg:province":"PA",
    "wof:name":"Grande Pizza",
    "wof:placetype":"venue"
},
  "geometry": {"coordinates":[-75.12170399999999,40.034569],"type":"Point"}
}