{
  "type": "Feature",
  "properties": {
    "iso:country":"US",
    "sg:address":"51 Crosby Brown Rd",
    "sg:city":"Gladwyne",
    "sg:classifiers":[
        {
            "category":"Communications",
            "subcategory":"Film & Video Production",
            "type":"Services"
        }
    ],
    "sg:phone":"+1   ",
    "sg:postcode":"19035",
    "sg:province":"PA",
    "sg:tags":[
        "motion"
    ],
    "wof:name":"Sideh20 Productions Inc",
    "wof:placetype":"venue"
},
  "geometry": {"coordinates":[-75.276315,40.027243],"type":"Point"}
}