{
  "type": "Feature",
  "properties": {
    "iso:country":"US",
    "sg:address":"208 Saint Johns Church Rd",
    "sg:city":"Greensburg",
    "sg:classifiers":[
        {
            "category":"Building & Trades",
            "subcategory":"Plumbing",
            "type":"Services"
        }
    ],
    "sg:phone":"+1   ",
    "sg:postcode":"15601",
    "sg:province":"PA",
    "sg:tags":[
        "plumbing",
        "heating",
        "contractor"
    ],
    "wof:name":"Harding & Sons Mech Contrs",
    "wof:placetype":"venue"
},
  "geometry": {"coordinates":[-79.586843,40.275773],"type":"Point"}
}