{
  "type": "Feature",
  "properties": {
    "iso:country":"US",
    "sg:address":"25 Crestwood Ct",
    "sg:city":"Brookville",
    "sg:classifiers":[
        {
            "category":"Retail",
            "subcategory":"Auto Repair",
            "type":"Services"
        }
    ],
    "sg:phone":"+1   ",
    "sg:postcode":"15825",
    "sg:province":"PA",
    "sg:tags":[
        "landscaping",
        "general",
        "electrical",
        "contractor"
    ],
    "wof:name":"Lewis Saxton",
    "wof:placetype":"venue"
},
  "geometry": {"coordinates":[-79.06444399999999,41.163558],"type":"Point"}
}