{
  "type": "Feature",
  "properties": {
    "addr:full":"430 N 4th St Sunbury PA 17801",
    "addr:housenumber":"430",
    "addr:postcode":"17801",
    "addr:street":"N 4Th St",
    "iso:country":"US",
    "sg:address":"430 N 4th St",
    "sg:city":"Sunbury",
    "sg:classifiers":[
        {
            "category":"Personal",
            "subcategory":"Beauty Salon",
            "type":"Services"
        }
    ],
    "sg:phone":"+1 570 286 5409",
    "sg:postcode":"17801",
    "sg:province":"PA",
    "wof:name":"Barbara Leiby Beauty Salon",
    "wof:placetype":"venue"
},
  "geometry": {"coordinates":[-76.78847500000001,40.865867],"type":"Point"}
}