{
  "type": "Feature",
  "properties": {
    "iso:country":"US",
    "sg:address":"1299 S Market St",
    "sg:city":"Elizabethtown",
    "sg:classifiers":[
        {
            "category":"Home & Garden",
            "subcategory":"Carpets & Floor Coverings",
            "type":"Retail Goods"
        }
    ],
    "sg:phone":"+1 717 367 4290",
    "sg:postcode":"17022",
    "sg:province":"PA",
    "sg:tags":[
        "installs",
        "material"
    ],
    "wof:name":"Hiestand Nevin Floor Covering",
    "wof:placetype":"venue"
},
  "geometry": {"coordinates":[-76.590698,40.140411],"type":"Point"}
}