{
  "type": "Feature",
  "properties": {
    "iso:country":"US",
    "sg:address":"252 Kalos St",
    "sg:city":"Philadelphia",
    "sg:classifiers":[
        {
            "category":"Education",
            "subcategory":"Special Training",
            "type":"Public Place"
        }
    ],
    "sg:phone":"+1 215 487 2214",
    "sg:postcode":"19128",
    "sg:province":"PA",
    "sg:tags":[
        "instruction",
        "music"
    ],
    "wof:name":"Aaron Vocal Studio",
    "wof:placetype":"venue"
},
  "geometry": {"coordinates":[-75.206717,40.0189],"type":"Point"}
}