{
  "type": "Feature",
  "properties": {
    "iso:country":"US",
    "sg:address":"845 Wyoming Ave",
    "sg:city":"Kingston",
    "sg:classifiers":[
        {
            "category":"Food & Beverages",
            "subcategory":"Candy",
            "type":"Retail Goods"
        }
    ],
    "sg:phone":"+1 570 287 3330",
    "sg:postcode":"18704",
    "sg:province":"PA",
    "wof:name":"Gertrude Hawk Chocolate Shops",
    "wof:placetype":"venue"
},
  "geometry": {"coordinates":[-75.882526,41.275266],"type":"Point"}
}