{
  "type": "Feature",
  "properties": {
    "iso:country":"US",
    "sg:address":"405 Ross Ave",
    "sg:city":"Pittsburgh",
    "sg:classifiers":[
        {
            "category":"Health Services",
            "subcategory":"Doctor",
            "type":"Services"
        }
    ],
    "sg:phone":"+1   ",
    "sg:postcode":"15221",
    "sg:province":"PA",
    "sg:tags":[
        "medical"
    ],
    "wof:name":"Abraham A Constantino MD",
    "wof:placetype":"venue"
},
  "geometry": {"coordinates":[-79.88961399999999,40.444425],"type":"Point"}
}