{
  "type": "Feature",
  "properties": {
    "addr:full":"236 Malone Ridge Rd Washington PA 15301",
    "addr:housenumber":"236",
    "addr:postcode":"15301",
    "addr:street":"Malone Ridge Rd",
    "iso:country":"US",
    "sg:address":"236 Malone Ridge Rd",
    "sg:city":"Washington",
    "sg:classifiers":[
        {
            "category":"Professional",
            "subcategory":"Management & Consulting",
            "type":"Services"
        }
    ],
    "sg:phone":"+1 724 249 2622",
    "sg:postcode":"15301",
    "sg:province":"PA",
    "sg:tags":[
        "consultant"
    ],
    "wof:name":"Bt Consulting Service",
    "wof:placetype":"venue"
},
  "geometry": {"coordinates":[-80.30868599999999,40.215928],"type":"Point"}
}