{
  "type": "Feature",
  "properties": {
    "iso:country":"US",
    "sg:address":"349 E Springfield Rd",
    "sg:city":"Springfield",
    "sg:classifiers":[
        {
            "category":"Professional",
            "type":"Services"
        }
    ],
    "sg:phone":"+1   ",
    "sg:postcode":"19064",
    "sg:province":"PA",
    "wof:name":"Pro Line Chemical",
    "wof:placetype":"venue"
},
  "geometry": {"coordinates":[-75.321028,39.930712],"type":"Point"}
}