{
  "type": "Feature",
  "properties": {
    "iso:country":"US",
    "sg:address":"1992 Butler Pike",
    "sg:city":"Conshohocken",
    "sg:classifiers":[
        {
            "category":"Shopping",
            "subcategory":"Bicycles & Sporting Goods",
            "type":"Retail Goods"
        },
        {
            "category":"Shopping",
            "subcategory":"Clothing, Apparel, & Fashions",
            "type":"Retail Goods"
        }
    ],
    "sg:phone":"+1 610 238 4770",
    "sg:postcode":"19428",
    "sg:province":"PA",
    "sg:tags":[
        "summer",
        "sportswear",
        "team"
    ],
    "wof:name":"Wave One Sports Inc",
    "wof:placetype":"venue"
},
  "geometry": {"coordinates":[-75.286519,40.094359],"type":"Point"}
}