{
  "type": "Feature",
  "properties": {
    "iso:country":"US",
    "sg:address":"70 Valley Stream Pkwy",
    "sg:city":"Malvern",
    "sg:classifiers":[
        {
            "category":"Wholesale",
            "subcategory":"Stationery",
            "type":"Manufacturing & Wholesale Goods"
        }
    ],
    "sg:phone":"+1 610 296 8000",
    "sg:postcode":"19355",
    "sg:province":"PA",
    "sg:tags":[
        "supply"
    ],
    "sg:website":"www.ikon.com",
    "wof:name":"IKON Office Solutions Inc",
    "wof:placetype":"venue"
},
  "geometry": {"coordinates":[-75.52522500000001,40.057908],"type":"Point"}
}