{
  "type": "Feature",
  "properties": {
    "iso:country":"US",
    "sg:address":"1574 Seibert Rd",
    "sg:city":"Bellefonte",
    "sg:classifiers":[
        {
            "category":"Farming",
            "subcategory":"Dairy Farm",
            "type":"Manufacturing & Wholesale Goods"
        }
    ],
    "sg:phone":"+1   ",
    "sg:postcode":"16823",
    "sg:province":"PA",
    "wof:name":"Jesse Schaeffer",
    "wof:placetype":"venue"
},
  "geometry": {"coordinates":[-77.81835599999999,40.882447],"type":"Point"}
}