{
  "type": "Feature",
  "properties": {
    "addr:full":"1916 Lycoming Creek Rd Williamsport PA 17701",
    "addr:housenumber":"1916",
    "addr:postcode":"17701",
    "addr:street":"Lycoming Creek Rd",
    "iso:country":"US",
    "sg:address":"1916 Lycoming Creek Rd",
    "sg:city":"Williamsport",
    "sg:classifiers":[
        {
            "category":"Food & Beverages",
            "subcategory":"Groceries & Convenience Stores",
            "type":"Retail Goods"
        }
    ],
    "sg:phone":"+1   ",
    "sg:postcode":"17701",
    "sg:province":"PA",
    "wof:name":"Weis Markets",
    "wof:placetype":"venue"
},
  "geometry": {"coordinates":[-77.04361,41.256388],"type":"Point"}
}