{
  "type": "Feature",
  "properties": {
    "addr:full":"297 Beaver St Hastings PA 16646",
    "addr:housenumber":"297",
    "addr:postcode":"16646",
    "addr:street":"Beaver St",
    "iso:country":"US",
    "sg:address":"297 Beaver St",
    "sg:city":"Hastings",
    "sg:classifiers":[
        {
            "category":"Banks & Credit Unions",
            "subcategory":"Bank",
            "type":"Services"
        }
    ],
    "sg:phone":"+1 814 247 6541",
    "sg:postcode":"16646",
    "sg:province":"PA",
    "wof:name":"First National Bank",
    "wof:placetype":"venue"
},
  "geometry": {"coordinates":[-78.713728,40.66381],"type":"Point"}
}