{
  "type": "Feature",
  "properties": {
    "iso:country":"US",
    "sg:address":"1817 Pittsburgh St",
    "sg:city":"Cheswick",
    "sg:classifiers":[
        {
            "category":"Communications",
            "type":"Services"
        }
    ],
    "sg:phone":"+1 724 274 6015",
    "sg:postcode":"15024",
    "sg:province":"PA",
    "wof:name":"Communications Workers",
    "wof:placetype":"venue"
},
  "geometry": {"coordinates":[-79.794954,40.54101],"type":"Point"}
}