{
  "type": "Feature",
  "properties": {
    "addr:full":"1018 Dekalb Pike Blue Bell PA 19422",
    "addr:housenumber":"1018",
    "addr:postcode":"19422",
    "addr:street":"Dekalb Pike",
    "iso:country":"US",
    "sg:address":"1018 Dekalb Pike",
    "sg:city":"Blue Bell",
    "sg:classifiers":[
        {
            "category":"Bakery",
            "type":"Food & Drink"
        }
    ],
    "sg:phone":"+1 610 275 5535",
    "sg:postcode":"19422",
    "sg:province":"PA",
    "sg:website":"www.romabakerybluebell.net",
    "wof:name":"Roma Bakery",
    "wof:placetype":"venue"
},
  "geometry": {"coordinates":[-75.292599,40.164005],"type":"Point"}
}