{
  "type": "Feature",
  "properties": {
    "addr:full":"6336 Hilltop Rd Orefield PA 18069",
    "addr:housenumber":"6336",
    "addr:postcode":"18069",
    "addr:street":"Hilltop Rd",
    "iso:country":"US",
    "sg:address":"6336 Hilltop Rd",
    "sg:city":"Orefield",
    "sg:classifiers":[
        {
            "category":"Banks & Credit Unions",
            "subcategory":"Investment Brokerage",
            "type":"Services"
        }
    ],
    "sg:phone":"+1   ",
    "sg:postcode":"18069",
    "sg:province":"PA",
    "sg:tags":[
        "advisory"
    ],
    "wof:name":"Hartranft Financial Planning",
    "wof:placetype":"venue"
},
  "geometry": {"coordinates":[-75.611469,40.602414],"type":"Point"}
}