{
  "type": "Feature",
  "properties": {
    "iso:country":"US",
    "sg:address":"409 Beatty Rd",
    "sg:city":"Monroeville",
    "sg:classifiers":[
        {
            "category":"Retail",
            "subcategory":"Repair Shop",
            "type":"Services"
        }
    ],
    "sg:phone":"+1   ",
    "sg:postcode":"15146",
    "sg:province":"PA",
    "sg:tags":[
        "equipment"
    ],
    "wof:name":"Gateway Office Equipment Corp",
    "wof:placetype":"venue"
},
  "geometry": {"coordinates":[-79.761433,40.448224],"type":"Point"}
}