{
  "type": "Feature",
  "properties": {
    "addr:full":"1111 State Rd Laurelton PA 17815",
    "addr:housenumber":"1111",
    "addr:postcode":"17815",
    "addr:street":"State Rd",
    "iso:country":"US",
    "sg:address":"1111 State Rd",
    "sg:city":"Laurelton",
    "sg:classifiers":[
        {
            "category":"Organizations",
            "subcategory":"Professional Association",
            "type":"Services"
        }
    ],
    "sg:phone":"+1 570 922 1445",
    "sg:postcode":"17815",
    "sg:province":"PA",
    "wof:name":"Union County West End Fair",
    "wof:placetype":"venue"
},
  "geometry": {"coordinates":[-76.27967700000001,40.93768],"type":"Point"}
}