{
  "type": "Feature",
  "properties": {
    "iso:country":"US",
    "sg:address":"361 S 11th St",
    "sg:city":"Quakertown",
    "sg:classifiers":[
        {
            "category":"Health Services",
            "subcategory":"Optometrist",
            "type":"Services"
        }
    ],
    "sg:phone":"+1   ",
    "sg:postcode":"18951",
    "sg:province":"PA",
    "wof:name":"Walker Daniel T Od",
    "wof:placetype":"venue"
},
  "geometry": {"coordinates":[-75.35162200000001,40.43462],"type":"Point"}
}