{
  "type": "Feature",
  "properties": {
    "addr:full":"5 Hilltop Rd Grantville PA 17007",
    "addr:housenumber":"5",
    "addr:postcode":"17007",
    "addr:street":"Hilltop Rd",
    "iso:country":"US",
    "sg:address":"5 Hilltop Rd",
    "sg:city":"Grantville",
    "sg:classifiers":[
        {
            "category":"Manufacturing",
            "subcategory":"Apparel",
            "type":"Manufacturing & Wholesale Goods"
        }
    ],
    "sg:phone":"+1   ",
    "sg:postcode":"17007",
    "sg:province":"PA",
    "sg:tags":[
        "art",
        "needlework",
        "embroidery"
    ],
    "wof:name":"A To Z Embroidery",
    "wof:placetype":"venue"
},
  "geometry": {"coordinates":[-77.12682,40.151078],"type":"Point"}
}