{
  "type": "Feature",
  "properties": {
    "iso:country":"US",
    "sg:address":"504 State St",
    "sg:city":"Erie",
    "sg:classifiers":[
        {
            "category":"Professional",
            "subcategory":"Lawyer & Legal Services",
            "type":"Services"
        }
    ],
    "sg:phone":"+1 814 455 3100",
    "sg:postcode":"16503",
    "sg:province":"PA",
    "sg:tags":[
        "attorney"
    ],
    "wof:name":"Damon C Hopkins",
    "wof:placetype":"venue"
},
  "geometry": {"coordinates":[-80.085671,42.129988],"type":"Point"}
}