{
  "type": "Feature",
  "properties": {
    "iso:country":"US",
    "sg:address":"372 Hopwood Coolspring Rd",
    "sg:city":"Hopwood",
    "sg:classifiers":[
        {
            "category":"Shopping",
            "subcategory":"Mobile Phones",
            "type":"Retail Goods"
        }
    ],
    "sg:phone":"+1 724 438 1000",
    "sg:postcode":"15445",
    "sg:province":"PA",
    "sg:tags":[
        "home"
    ],
    "wof:name":"National Pike Sales",
    "wof:placetype":"venue"
},
  "geometry": {"coordinates":[-79.68396,39.890526],"type":"Point"}
}