{
  "type": "Feature",
  "properties": {
    "iso:country":"US",
    "sg:address":"112 Store Ln",
    "sg:city":"Lebanon",
    "sg:classifiers":[
        {
            "category":"Personal",
            "subcategory":"Barber",
            "type":"Services"
        }
    ],
    "sg:phone":"+1 717 273 3859",
    "sg:postcode":"17083",
    "sg:province":"PA",
    "wof:name":"Dishong's Barber Shop",
    "wof:placetype":"venue"
},
  "geometry": {"coordinates":[-76.38960899999999,40.281932],"type":"Point"}
}