{
  "type": "Feature",
  "properties": {
    "iso:country":"US",
    "sg:address":"3012 Butler Pike",
    "sg:city":"Conshohocken",
    "sg:classifiers":[
        {
            "category":"Insurance",
            "subcategory":"Hazard Insurance",
            "type":"Services"
        }
    ],
    "sg:phone":"+1 610 825 3223",
    "sg:postcode":"19428",
    "sg:province":"PA",
    "sg:website":"http://www.billweychert.com",
    "wof:name":"State Farm Insurance Agent-Bill Weychert",
    "wof:placetype":"venue"
},
  "geometry": {"coordinates":[-75.285999,40.094855],"type":"Point"}
}