{
  "type": "Feature",
  "properties": {
    "iso:country":"US",
    "sg:address":"408 Summit Rd",
    "sg:city":"New Cumberland",
    "sg:classifiers":[
        {
            "category":"Building & Trades",
            "subcategory":"Pest Control",
            "type":"Services"
        }
    ],
    "sg:phone":"+1 717 774 7673",
    "sg:postcode":"17070",
    "sg:province":"PA",
    "wof:name":"Banks Pest Control",
    "wof:placetype":"venue"
},
  "geometry": {"coordinates":[-76.864799,40.201302],"type":"Point"}
}