{
  "type": "Feature",
  "properties": {
    "addr:full":"1938 Stout Dr Warminster PA 18974",
    "addr:housenumber":"1938",
    "addr:postcode":"18974",
    "addr:street":"Stout Dr",
    "iso:country":"US",
    "sg:address":"1938 Stout Dr",
    "sg:city":"Warminster",
    "sg:classifiers":[
        {
            "category":"Wholesale",
            "subcategory":"Machinery & Supplies",
            "type":"Manufacturing & Wholesale Goods"
        }
    ],
    "sg:phone":"+1 215 443 9090",
    "sg:postcode":"18974",
    "sg:province":"PA",
    "sg:tags":[
        "equipment",
        "material",
        "handling"
    ],
    "sg:website":"www.omnilift-inc.com",
    "wof:name":"Omnilift Inc",
    "wof:placetype":"venue"
},
  "geometry": {"coordinates":[-75.071609,40.225878],"type":"Point"}
}