{
  "type": "Feature",
  "properties": {
    "iso:country":"US",
    "sg:address":"525 Power Rd",
    "sg:city":"Manheim",
    "sg:classifiers":[
        {
            "category":"Farming",
            "subcategory":"Dairy Farm",
            "type":"Manufacturing & Wholesale Goods"
        }
    ],
    "sg:phone":"+1   ",
    "sg:postcode":"17545",
    "sg:province":"PA",
    "wof:name":"Luther Patches",
    "wof:placetype":"venue"
},
  "geometry": {"coordinates":[-76.39284000000001,40.153382],"type":"Point"}
}