{
  "type": "Feature",
  "properties": {
    "iso:country":"US",
    "sg:address":"2900 S 70th St",
    "sg:city":"Philadelphia",
    "sg:classifiers":[
        {
            "category":"Food & Beverages",
            "subcategory":"Groceries & Convenience Stores",
            "type":"Retail Goods"
        }
    ],
    "sg:phone":"+1 215 365 0137",
    "sg:postcode":"19142",
    "sg:province":"PA",
    "wof:name":"7-11 No 26291",
    "wof:placetype":"venue"
},
  "geometry": {"coordinates":[-75.23290299999999,39.9132],"type":"Point"}
}