{
  "type": "Feature",
  "properties": {
    "iso:country":"US",
    "sg:address":"4927 Centre Ave",
    "sg:city":"Pittsburgh",
    "sg:classifiers":[
        {
            "category":"Health Services",
            "subcategory":"Podiatrist",
            "type":"Services"
        }
    ],
    "sg:phone":"+1 412 683 8378",
    "sg:postcode":"15213",
    "sg:province":"PA",
    "sg:tags":[
        "equipment",
        "supply"
    ],
    "wof:name":"Advanced Medical Imaging Pc",
    "wof:placetype":"venue"
},
  "geometry": {"coordinates":[-79.94584999999999,40.453741],"type":"Point"}
}