{
  "type": "Feature",
  "properties": {
    "iso:country":"US",
    "sg:address":"5029 Library Rd",
    "sg:city":"Bethel Park",
    "sg:classifiers":[
        {
            "category":"Retail",
            "subcategory":"Laundry & Dry Cleaning",
            "type":"Services"
        }
    ],
    "sg:phone":"+1 412 831 0595",
    "sg:postcode":"15102",
    "sg:province":"PA",
    "sg:tags":[
        "cleaner"
    ],
    "wof:name":"Model Cleaners",
    "wof:placetype":"venue"
},
  "geometry": {"coordinates":[-80.0261,40.341599],"type":"Point"}
}