{
  "type": "Feature",
  "properties": {
    "addr:full":"58 Camp Victory Rd Millville PA 17846",
    "addr:housenumber":"58",
    "addr:postcode":"17846",
    "addr:street":"Camp Victory Rd",
    "iso:country":"US",
    "sg:address":"58 Camp Victory Rd",
    "sg:city":"Millville",
    "sg:classifiers":[
        {
            "category":"Travel",
            "subcategory":"Campground",
            "type":"Entertainment"
        }
    ],
    "sg:phone":"+1 570 458 6530",
    "sg:postcode":"17846",
    "sg:province":"PA",
    "sg:tags":[
        "camp"
    ],
    "sg:website":"www.campvictory.org",
    "wof:name":"Camp Victory",
    "wof:placetype":"venue"
},
  "geometry": {"coordinates":[-76.4954,41.11561],"type":"Point"}
}