{
  "type": "Feature",
  "properties": {
    "iso:country":"US",
    "sg:address":"496 Front St",
    "sg:city":"Wilkes Barre",
    "sg:classifiers":[
        {
            "category":"Government",
            "subcategory":"Office",
            "type":"Public Place"
        }
    ],
    "sg:phone":"+1   ",
    "sg:postcode":"18706",
    "sg:province":"PA",
    "sg:tags":[
        "executive"
    ],
    "wof:name":"Warrior Run Borough Cente",
    "wof:placetype":"venue"
},
  "geometry": {"coordinates":[-75.952257,41.192389],"type":"Point"}
}