{
  "type": "Feature",
  "properties": {
    "iso:country":"US",
    "sg:address":"1828 Liberty Way",
    "sg:city":"Valencia",
    "sg:classifiers":[
        {
            "category":"Building & Trades",
            "subcategory":"Construction",
            "type":"Services"
        }
    ],
    "sg:phone":"+1   ",
    "sg:postcode":"16059",
    "sg:province":"PA",
    "sg:tags":[
        "house"
    ],
    "wof:name":"Custom Homes By Eric Knapp",
    "wof:placetype":"venue"
},
  "geometry": {"coordinates":[-79.984145,40.690174],"type":"Point"}
}