{
  "type": "Feature",
  "properties": {
    "addr:full":"1066 S New St West Chester PA 19382",
    "addr:housenumber":"1066",
    "addr:postcode":"19382",
    "addr:street":"S New St",
    "iso:country":"US",
    "sg:address":"1066 S New St",
    "sg:city":"West Chester",
    "sg:classifiers":[
        {
            "category":"Organizations",
            "subcategory":"Religious Organization",
            "type":"Services"
        }
    ],
    "sg:phone":"+1 610 692 8280",
    "sg:postcode":"19382",
    "sg:province":"PA",
    "sg:website":"www.lovingshepherd.org",
    "wof:name":"Church of the Loving Shepherd",
    "wof:placetype":"venue"
},
  "geometry": {"coordinates":[-75.59807600000001,39.923472],"type":"Point"}
}