{
  "type": "Feature",
  "properties": {
    "iso:country":"US",
    "sg:address":"1248 Griffith Rd",
    "sg:city":"Ligonier",
    "sg:classifiers":[
        {
            "category":"Banks & Credit Unions",
            "subcategory":"Investment Brokerage",
            "type":"Services"
        },
        {
            "category":"Professional",
            "subcategory":"Management & Consulting",
            "type":"Services"
        }
    ],
    "sg:phone":"+1 724 238 9655",
    "sg:postcode":"15658",
    "sg:province":"PA",
    "sg:tags":[
        "consultant",
        "planning",
        "financial",
        "insurance"
    ],
    "wof:name":"Advisor Group The Inc",
    "wof:placetype":"venue"
},
  "geometry": {"coordinates":[-79.177677,40.253467],"type":"Point"}
}