{
  "type": "Feature",
  "properties": {
    "iso:country":"US",
    "sg:address":"67 Lee St",
    "sg:city":"Stewartstown",
    "sg:classifiers":[
        {
            "category":"Professional",
            "type":"Services"
        }
    ],
    "sg:phone":"+1   ",
    "sg:postcode":"17363",
    "sg:province":"PA",
    "wof:name":"Innovtive Cncpts Unlimited LLP",
    "wof:placetype":"venue"
},
  "geometry": {"coordinates":[-76.598198,39.757525],"type":"Point"}
}