{
  "type": "Feature",
  "properties": {
    "addr:full":"3212 Frankford Ave Philadelphia PA 19134",
    "addr:housenumber":"3212",
    "addr:postcode":"19134",
    "addr:street":"Frankford Ave",
    "iso:country":"US",
    "sg:address":"3212 Frankford Ave",
    "sg:city":"Philadelphia",
    "sg:classifiers":[
        {
            "category":"Building & Trades",
            "subcategory":"Construction",
            "type":"Services"
        }
    ],
    "sg:phone":"+1 215 426 9400",
    "sg:postcode":"19134",
    "sg:province":"PA",
    "sg:tags":[
        "home",
        "builder",
        "improvement"
    ],
    "wof:name":"Bellorama Home Improvement Inc",
    "wof:placetype":"venue"
},
  "geometry": {"coordinates":[-75.109787,39.993214],"type":"Point"}
}