{
  "type": "Feature",
  "properties": {
    "iso:country":"US",
    "sg:address":"175 Si Rode Ln",
    "sg:city":"York Haven",
    "sg:classifiers":[
        {
            "category":"Building & Trades",
            "subcategory":"Construction",
            "type":"Services"
        }
    ],
    "sg:phone":"+1   ",
    "sg:postcode":"17370",
    "sg:province":"PA",
    "sg:tags":[
        "house"
    ],
    "wof:name":"J & TS Home Improvements",
    "wof:placetype":"venue"
},
  "geometry": {"coordinates":[-76.74758199999999,40.116699],"type":"Point"}
}