{
  "type": "Feature",
  "properties": {
    "iso:country":"US",
    "sg:address":"1608 Spruce St Fl 3",
    "sg:city":"Philadelphia",
    "sg:classifiers":[
        {
            "category":"Real Estate",
            "subcategory":"Real Estate Services",
            "type":"Services"
        },
        {
            "category":"Real Estate",
            "subcategory":"Real Estate Agent",
            "type":"Services"
        }
    ],
    "sg:phone":"+1 215 735 9808",
    "sg:postcode":"19103",
    "sg:province":"PA",
    "sg:tags":[
        "management"
    ],
    "wof:name":"Chancellor Properties, Inc.",
    "wof:placetype":"venue"
},
  "geometry": {"coordinates":[-75.168474,39.947444],"type":"Point"}
}