{
  "type": "Feature",
  "properties": {
    "iso:country":"US",
    "sg:address":"326 N Front St",
    "sg:city":"Harrisburg",
    "sg:classifiers":[
        {
            "category":"Insurance",
            "subcategory":"Insurance Agent",
            "type":"Services"
        }
    ],
    "sg:phone":"+1 717 939 4848",
    "sg:postcode":"17113",
    "sg:province":"PA",
    "sg:tags":[
        "agency"
    ],
    "wof:name":"O'Hara Insurance",
    "wof:placetype":"venue"
},
  "geometry": {"coordinates":[-76.845618,40.236746],"type":"Point"}
}