{
  "type": "Feature",
  "properties": {
    "iso:country":"US",
    "sg:address":"1899 Plank Rd",
    "sg:city":"Carrolltown",
    "sg:classifiers":[
        {
            "category":"Shopping",
            "subcategory":"Clothing, Apparel, & Fashions",
            "type":"Retail Goods"
        }
    ],
    "sg:phone":"+1 814 344 2022",
    "sg:postcode":"15722",
    "sg:province":"PA",
    "sg:tags":[
        "shop",
        "bridal"
    ],
    "wof:name":"Bridal Expressions",
    "wof:placetype":"venue"
},
  "geometry": {"coordinates":[-78.712992,40.588941],"type":"Point"}
}