{
  "type": "Feature",
  "properties": {
    "addr:full":"7712 Morgan Ln Glenside PA 19038",
    "addr:housenumber":"7712",
    "addr:postcode":"19038",
    "addr:street":"Morgan Ln",
    "iso:country":"US",
    "sg:address":"7712 Morgan Ln",
    "sg:city":"Glenside",
    "sg:classifiers":[
        {
            "category":"Real Estate",
            "subcategory":"Real Estate Agent",
            "type":"Services"
        }
    ],
    "sg:phone":"+1   ",
    "sg:postcode":"19038",
    "sg:province":"PA",
    "wof:name":"Nolan Enterprises Inc",
    "wof:placetype":"venue"
},
  "geometry": {"coordinates":[-75.175864,40.089998],"type":"Point"}
}