{
  "type": "Feature",
  "properties": {
    "iso:country":"US",
    "sg:address":"742 Main St",
    "sg:city":"Bethlehem",
    "sg:classifiers":[
        {
            "category":"Professional",
            "subcategory":"Lawyer & Legal Services",
            "type":"Services"
        }
    ],
    "sg:phone":"+1 610 419 9790",
    "sg:postcode":"18018",
    "sg:province":"PA",
    "sg:website":"www.meshkovbreslin.com",
    "wof:name":"Meshkov & Breslin",
    "wof:placetype":"venue"
},
  "geometry": {"coordinates":[-75.381666,40.624567],"type":"Point"}
}