{
  "type": "Feature",
  "properties": {
    "iso:country":"US",
    "sg:address":"78 Timberline Dr",
    "sg:city":"Reading",
    "sg:classifiers":[
        {
            "category":"Shopping",
            "subcategory":"Musical Instruments",
            "type":"Retail Goods"
        }
    ],
    "sg:phone":"+1   ",
    "sg:postcode":"19610",
    "sg:province":"PA",
    "wof:name":"Zeswitz Music Store",
    "wof:placetype":"venue"
},
  "geometry": {"coordinates":[-75.972756,40.33311],"type":"Point"}
}