{
  "type": "Feature",
  "properties": {
    "iso:country":"US",
    "sg:address":"436 W 2nd St",
    "sg:city":"Williamsburg",
    "sg:classifiers":[
        {
            "category":"Freight",
            "type":"Transportation"
        }
    ],
    "sg:phone":"+1   ",
    "sg:postcode":"16693",
    "sg:province":"PA",
    "sg:tags":[
        "operator",
        "trucking"
    ],
    "wof:name":"Fisher Sales & Service",
    "wof:placetype":"venue"
},
  "geometry": {"coordinates":[-78.202473,40.461641],"type":"Point"}
}