{
  "type": "Feature",
  "properties": {
    "iso:country":"US",
    "sg:address":"400 Agnew Rd",
    "sg:city":"Jeannette",
    "sg:classifiers":[
        {
            "category":"Retail",
            "subcategory":"Auto Repair",
            "type":"Services"
        }
    ],
    "sg:phone":"+1   ",
    "sg:postcode":"15644",
    "sg:province":"PA",
    "sg:tags":[
        "automotive",
        "general"
    ],
    "wof:name":"H & B Auto Machine & Parts",
    "wof:placetype":"venue"
},
  "geometry": {"coordinates":[-79.60728899999999,40.32138],"type":"Point"}
}