{
  "type": "Feature",
  "properties": {
    "iso:country":"US",
    "sg:address":"141 E Union St",
    "sg:city":"Canton",
    "sg:classifiers":[
        {
            "category":"Education",
            "subcategory":"School",
            "type":"Public Place"
        }
    ],
    "sg:phone":"+1 570 673 5196",
    "sg:postcode":"17724",
    "sg:province":"PA",
    "sg:website":"www.canton.k12.pa.us",
    "wof:name":"Canton Area Elementary School",
    "wof:placetype":"venue"
},
  "geometry": {"coordinates":[-76.84374099999999,41.657714],"type":"Point"}
}