{
  "type": "Feature",
  "properties": {
    "addr:full":"4265 Richmond St Philadelphia PA 19137",
    "addr:housenumber":"4265",
    "addr:postcode":"19137",
    "addr:street":"Richmond St",
    "iso:country":"US",
    "sg:address":"4265 Richmond St",
    "sg:city":"Philadelphia",
    "sg:classifiers":[
        {
            "category":"Banks & Credit Unions",
            "subcategory":"Bank",
            "type":"Services"
        }
    ],
    "sg:phone":"+1 215 535 7350",
    "sg:postcode":"19137",
    "sg:province":"PA",
    "sg:tags":[
        "cashing",
        "check"
    ],
    "wof:name":"United Check Cashing Co",
    "wof:placetype":"venue"
},
  "geometry": {"coordinates":[-75.074752,39.996565],"type":"Point"}
}