{
  "type": "Feature",
  "properties": {
    "iso:country":"US",
    "sg:address":"215 N Clifton Ave",
    "sg:city":"Clifton Heights",
    "sg:classifiers":[
        {
            "category":"Retail",
            "subcategory":"Auto Repair",
            "type":"Services"
        }
    ],
    "sg:phone":"+1   ",
    "sg:postcode":"19018",
    "sg:province":"PA",
    "sg:tags":[
        "general"
    ],
    "wof:name":"Toms Auto Repair Inc",
    "wof:placetype":"venue"
},
  "geometry": {"coordinates":[-75.289418,39.925604],"type":"Point"}
}