{
  "type": "Feature",
  "properties": {
    "iso:country":"US",
    "sg:address":"2418 W York St",
    "sg:city":"Philadelphia",
    "sg:classifiers":[
        {
            "category":"Health Services",
            "subcategory":"Doctor",
            "type":"Services"
        }
    ],
    "sg:phone":"+1 215 226 0331",
    "sg:postcode":"19132",
    "sg:province":"PA",
    "sg:tags":[
        "podiatrist"
    ],
    "wof:name":"Mitchell Keith DPM",
    "wof:placetype":"venue"
},
  "geometry": {"coordinates":[-75.172203,39.9916],"type":"Point"}
}