{
  "type": "Feature",
  "properties": {
    "iso:country":"US",
    "sg:address":"105 Spencer Rd",
    "sg:city":"Devon",
    "sg:classifiers":[
        {
            "category":"Banks & Credit Unions",
            "subcategory":"Financial Services",
            "type":"Services"
        }
    ],
    "sg:phone":"+1   ",
    "sg:postcode":"19333",
    "sg:province":"PA",
    "sg:tags":[
        "trust",
        "nonprofit",
        "management"
    ],
    "wof:name":"Charitable Mooney Trust",
    "wof:placetype":"venue"
},
  "geometry": {"coordinates":[-75.427142,40.052884],"type":"Point"}
}