{
  "type": "Feature",
  "properties": {
    "iso:country":"US",
    "sg:address":"1063 Mosser Rd Apt G206",
    "sg:city":"Breinigsville",
    "sg:classifiers":[
        {
            "category":"Building & Trades",
            "subcategory":"Construction",
            "type":"Services"
        }
    ],
    "sg:phone":"+1 610 217 3075",
    "sg:postcode":"18031",
    "sg:province":"PA",
    "sg:tags":[
        "wallcoverings-installation",
        "wallpaper",
        "painting",
        "contractor"
    ],
    "wof:name":"Hartz Painting And Construction",
    "wof:placetype":"venue"
},
  "geometry": {"coordinates":[-75.61599200000001,40.550784],"type":"Point"}
}