{
  "type": "Feature",
  "properties": {
    "addr:full":"1507 Market St Camp Hill PA 17011",
    "addr:housenumber":"1507",
    "addr:postcode":"17011",
    "addr:street":"Market St",
    "iso:country":"US",
    "sg:address":"1507 Market St",
    "sg:city":"Camp Hill",
    "sg:classifiers":[
        {
            "category":"Building & Trades",
            "subcategory":"Cleaning & Sanitation",
            "type":"Services"
        }
    ],
    "sg:phone":"+1 717 737 9096",
    "sg:postcode":"17011",
    "sg:province":"PA",
    "sg:tags":[
        "carpet"
    ],
    "sg:website":"www.servpro.com",
    "wof:name":"Servpro of Camp Hill",
    "wof:placetype":"venue"
},
  "geometry": {"coordinates":[-76.911146,40.240558],"type":"Point"}
}