{
  "type": "Feature",
  "properties": {
    "addr:full":"118 Hillview Dr Valencia PA 16059",
    "addr:housenumber":"118",
    "addr:postcode":"16059",
    "addr:street":"Hillview Dr",
    "iso:country":"US",
    "sg:address":"118 Hillview Dr",
    "sg:city":"Valencia",
    "sg:classifiers":[
        {
            "category":"Building & Trades",
            "subcategory":"Landscaping Services",
            "type":"Services"
        }
    ],
    "sg:phone":"+1   ",
    "sg:postcode":"16059",
    "sg:province":"PA",
    "wof:name":"Douds Lawn Care",
    "wof:placetype":"venue"
},
  "geometry": {"coordinates":[-79.93816099999999,40.68078],"type":"Point"}
}