{
  "type": "Feature",
  "properties": {
    "iso:country":"US",
    "sg:address":"2119 Ambassador Dr",
    "sg:city":"Lancaster",
    "sg:classifiers":[
        {
            "category":"Organizations",
            "subcategory":"Community Association",
            "type":"Services"
        }
    ],
    "sg:phone":"+1   ",
    "sg:postcode":"17603",
    "sg:province":"PA",
    "sg:tags":[
        "national",
        "honor",
        "fraternity"
    ],
    "wof:name":"PHI Sgma PI Nat Hnor Frternity",
    "wof:placetype":"venue"
},
  "geometry": {"coordinates":[-76.35971000000001,40.043038],"type":"Point"}
}