{
  "type": "Feature",
  "properties": {
    "iso:country":"US",
    "sg:address":"4783 Havana Dr",
    "sg:city":"Pittsburgh",
    "sg:classifiers":[
        {
            "category":"Building & Trades",
            "subcategory":"Construction",
            "type":"Services"
        }
    ],
    "sg:phone":"+1 412 795 3588",
    "sg:postcode":"15239",
    "sg:province":"PA",
    "sg:tags":[
        "contractor"
    ],
    "wof:name":"Plum Glass Block Co",
    "wof:placetype":"venue"
},
  "geometry": {"coordinates":[-79.70757500000001,40.478613],"type":"Point"}
}