{
  "type": "Feature",
  "properties": {
    "iso:country":"US",
    "sg:address":"824 Dover Rd",
    "sg:city":"Wynnewood",
    "sg:classifiers":[
        {
            "category":"Social Services",
            "type":"Services"
        },
        {
            "category":"Personal",
            "type":"Services"
        }
    ],
    "sg:phone":"+1 610 642 8075",
    "sg:postcode":"19096",
    "sg:province":"PA",
    "sg:tags":[
        "family",
        "counselors-licensed",
        "individual",
        "marriage",
        "child",
        "professional",
        "counselor"
    ],
    "wof:name":"Shralow Rhoda R Counselor",
    "wof:placetype":"venue"
},
  "geometry": {"coordinates":[-75.28227699999999,39.984436],"type":"Point"}
}