{
  "type": "Feature",
  "properties": {
    "iso:country":"US",
    "sg:address":"77 S Main St",
    "sg:city":"Union City",
    "sg:classifiers":[
        {
            "category":"Manufacturing",
            "subcategory":"Furniture",
            "type":"Manufacturing & Wholesale Goods"
        }
    ],
    "sg:phone":"+1   ",
    "sg:postcode":"16438",
    "sg:province":"PA",
    "sg:tags":[
        "household",
        "wood",
        "mfg"
    ],
    "wof:name":"Ethan Allen Inc",
    "wof:placetype":"venue"
},
  "geometry": {"coordinates":[-79.848536,41.894766],"type":"Point"}
}