{
  "type": "Feature",
  "properties": {
    "iso:country":"US",
    "sg:address":"15 W Mohler Church Rd",
    "sg:city":"Ephrata",
    "sg:classifiers":[
        {
            "category":"Building & Trades",
            "subcategory":"Construction",
            "type":"Services"
        }
    ],
    "sg:phone":"+1 717 733 1833",
    "sg:postcode":"17522",
    "sg:province":"PA",
    "sg:tags":[
        "resurfacing",
        "laying",
        "refinishing",
        "floor"
    ],
    "sg:website":"www.seamlesssystems.com",
    "wof:name":"Commonweatlh Seamless Systems",
    "wof:placetype":"venue"
},
  "geometry": {"coordinates":[-76.162909,40.190757],"type":"Point"}
}