{
  "type": "Feature",
  "properties": {
    "iso:country":"US",
    "sg:address":"512 Center St",
    "sg:city":"Scranton",
    "sg:classifiers":[
        {
            "category":"Government",
            "subcategory":"Fire Station",
            "type":"Public Place"
        }
    ],
    "sg:phone":"+1   ",
    "sg:postcode":"18512",
    "sg:province":"PA",
    "sg:tags":[
        "department",
        "volunteer"
    ],
    "wof:name":"Throop Hose Company No 1",
    "wof:placetype":"venue"
},
  "geometry": {"coordinates":[-75.62316300000001,41.418066],"type":"Point"}
}