{
  "type": "Feature",
  "properties": {
    "addr:full":"1514 Norcross Rd Erie PA 16510",
    "addr:housenumber":"1514",
    "addr:postcode":"16510",
    "addr:street":"Norcross Rd",
    "iso:country":"US",
    "sg:address":"1514 Norcross Rd",
    "sg:city":"Erie",
    "sg:classifiers":[
        {
            "category":"Organizations",
            "subcategory":"Non-profit Organization",
            "type":"Services"
        }
    ],
    "sg:phone":"+1 814 825 4359",
    "sg:postcode":"16510",
    "sg:province":"PA",
    "sg:website":"www.bellevalleyfire.org",
    "wof:name":"Belle Valley Fire Dept Inc",
    "wof:placetype":"venue"
},
  "geometry": {"coordinates":[-80.027141,42.103019],"type":"Point"}
}