{
  "type": "Feature",
  "properties": {
    "iso:country":"US",
    "sg:address":"25 S Main St",
    "sg:city":"Yardley",
    "sg:classifiers":[
        {
            "category":"Shopping",
            "subcategory":"Baby Store",
            "type":"Retail Goods"
        }
    ],
    "sg:phone":"+1 215 493 7288",
    "sg:postcode":"19067",
    "sg:province":"PA",
    "sg:tags":[
        "children's",
        "infant",
        "wear"
    ],
    "wof:name":"Hollywood Kids Inc",
    "wof:placetype":"venue"
},
  "geometry": {"coordinates":[-74.83827100000001,40.24196],"type":"Point"}
}