{
  "type": "Feature",
  "properties": {
    "addr:full":"4240 Greensburg Pike Pittsburgh PA 15221",
    "addr:housenumber":"4240",
    "addr:postcode":"15221",
    "addr:street":"Greensburg Pike",
    "iso:country":"US",
    "sg:address":"4240 Greensburg Pike",
    "sg:city":"Pittsburgh",
    "sg:classifiers":[
        {
            "category":"Insurance",
            "subcategory":"Insurance Agent",
            "type":"Services"
        }
    ],
    "sg:phone":"+1   ",
    "sg:postcode":"15221",
    "sg:province":"PA",
    "sg:tags":[
        "broker"
    ],
    "wof:name":"Research Underwriters",
    "wof:placetype":"venue"
},
  "geometry": {"coordinates":[-79.84024100000001,40.418083],"type":"Point"}
}