{
  "type": "Feature",
  "properties": {
    "iso:country":"US",
    "sg:address":"16412 State Rte 8",
    "sg:city":"Union City",
    "sg:classifiers":[
        {
            "category":"Autos & Motor Vehicles",
            "subcategory":"Automobile Sales",
            "type":"Retail Goods"
        }
    ],
    "sg:phone":"+1 814 438 9990",
    "sg:postcode":"16438",
    "sg:province":"PA",
    "sg:tags":[
        "car",
        "dealer"
    ],
    "wof:name":"Top Gun Motors Inc",
    "wof:placetype":"venue"
},
  "geometry": {"coordinates":[-79.845967,41.887814],"type":"Point"}
}