{
  "type": "Feature",
  "properties": {
    "iso:country":"US",
    "sg:address":"510 Main St",
    "sg:city":"Irwin",
    "sg:classifiers":[
        {
            "category":"Home & Garden",
            "subcategory":"Furniture",
            "type":"Retail Goods"
        },
        {
            "category":"Home & Garden",
            "subcategory":"Carpets & Floor Coverings",
            "type":"Retail Goods"
        }
    ],
    "sg:phone":"+1 724 864 2892",
    "sg:postcode":"15642",
    "sg:province":"PA",
    "wof:name":"Klingensmith Furniture & Crpt",
    "wof:placetype":"venue"
},
  "geometry": {"coordinates":[-79.711282,40.330541],"type":"Point"}
}