{
  "type": "Feature",
  "properties": {
    "iso:country":"US",
    "sg:address":"90 Mill St",
    "sg:city":"Fawn Grove",
    "sg:classifiers":[
        {
            "category":"Professional",
            "type":"Services"
        }
    ],
    "sg:phone":"+1   ",
    "sg:postcode":"17321",
    "sg:province":"PA",
    "wof:name":"J D Eckman Inc",
    "wof:placetype":"venue"
},
  "geometry": {"coordinates":[-76.449471,39.732504],"type":"Point"}
}