{
  "type": "Feature",
  "properties": {
    "iso:country":"US",
    "sg:address":"222 Wyoming Ave",
    "sg:city":"Scranton",
    "sg:classifiers":[
        {
            "category":"Professional",
            "subcategory":"Lawyer & Legal Services",
            "type":"Services"
        }
    ],
    "sg:phone":"+1 570 346 9929",
    "sg:postcode":"18503",
    "sg:province":"PA",
    "sg:tags":[
        "attorney"
    ],
    "wof:name":"Kim A Giombetti",
    "wof:placetype":"venue"
},
  "geometry": {"coordinates":[-75.66391400000001,41.409667],"type":"Point"}
}