{
  "type": "Feature",
  "properties": {
    "addr:full":"128 Baltimore Pike Chadds Ford PA 19317",
    "addr:housenumber":"128",
    "addr:postcode":"19317",
    "addr:street":"Baltimore Pike",
    "iso:country":"US",
    "sg:address":"128 Baltimore Pike",
    "sg:city":"Chadds Ford",
    "sg:classifiers":[
        {
            "category":"Restaurant",
            "type":"Food & Drink"
        }
    ],
    "sg:phone":"+1 610 361 8823",
    "sg:postcode":"19317",
    "sg:province":"PA",
    "wof:name":"Salad Gallery",
    "wof:placetype":"venue"
},
  "geometry": {"coordinates":[-75.60700199999999,39.862701],"type":"Point"}
}