{
  "type": "Feature",
  "properties": {
    "iso:country":"US",
    "sg:address":"17 Hillside Ave",
    "sg:city":"Souderton",
    "sg:classifiers":[
        {
            "category":"Building & Trades",
            "subcategory":"Landscaping Services",
            "type":"Services"
        }
    ],
    "sg:phone":"+1   ",
    "sg:postcode":"18964",
    "sg:province":"PA",
    "sg:tags":[
        "landscape"
    ],
    "wof:name":"Timber Springs Landscape Co",
    "wof:placetype":"venue"
},
  "geometry": {"coordinates":[-75.32409,40.310704],"type":"Point"}
}