{
  "type": "Feature",
  "properties": {
    "addr:full":"1845 Overlook Rd Feastervl Trvs PA 19053",
    "addr:housenumber":"1845",
    "addr:postcode":"19053",
    "addr:street":"Overlook Rd",
    "iso:country":"US",
    "sg:address":"1845 Overlook Rd",
    "sg:city":"Feastervl Trvs",
    "sg:classifiers":[
        {
            "category":"Building & Trades",
            "subcategory":"Construction",
            "type":"Services"
        }
    ],
    "sg:phone":"+1 215 953 6818",
    "sg:postcode":"19053",
    "sg:province":"PA",
    "sg:tags":[
        "general",
        "contractor"
    ],
    "wof:name":"New Mellinian Contractor",
    "wof:placetype":"venue"
},
  "geometry": {"coordinates":[-74.98025,40.157106],"type":"Point"}
}