{
  "type": "Feature",
  "properties": {
    "iso:country":"US",
    "sg:address":"1200 New Rodgers Rd",
    "sg:city":"Bristol",
    "sg:classifiers":[
        {
            "category":"Real Estate",
            "subcategory":"Real Estate Operator",
            "type":"Services"
        }
    ],
    "sg:phone":"+1 215 781 3900",
    "sg:postcode":"19007",
    "sg:province":"PA",
    "sg:tags":[
        "building",
        "parks"
    ],
    "wof:name":"R M Benbow Properties Inc",
    "wof:placetype":"venue"
},
  "geometry": {"coordinates":[-74.878854,40.110999],"type":"Point"}
}