{
  "type": "Feature",
  "properties": {
    "addr:full":"6 Summer Dr Dillsburg PA 17019",
    "addr:housenumber":"6",
    "addr:postcode":"17019",
    "addr:street":"Summer Dr",
    "iso:country":"US",
    "sg:address":"6 Summer Dr",
    "sg:city":"Dillsburg",
    "sg:classifiers":[
        {
            "category":"Building & Trades",
            "subcategory":"Construction",
            "type":"Services"
        }
    ],
    "sg:phone":"+1 717 432 0606",
    "sg:postcode":"17019",
    "sg:province":"PA",
    "sg:tags":[
        "excavating",
        "contractor"
    ],
    "wof:name":"Follmer Excavating Inc",
    "wof:placetype":"venue"
},
  "geometry": {"coordinates":[-76.991679,40.138459],"type":"Point"}
}