{
  "type": "Feature",
  "properties": {
    "iso:country":"US",
    "sg:address":"172 Morrell Rd",
    "sg:city":"Dunbar",
    "sg:classifiers":[
        {
            "category":"Personal",
            "subcategory":"Beauty Salon",
            "type":"Services"
        }
    ],
    "sg:phone":"+1 724 628 3330",
    "sg:postcode":"15431",
    "sg:province":"PA",
    "wof:name":"Hair It Is",
    "wof:placetype":"venue"
},
  "geometry": {"coordinates":[-79.612617,39.988925],"type":"Point"}
}