{
  "type": "Feature",
  "properties": {
    "iso:country":"US",
    "sg:address":"428 Forbes Ave Ste 1600",
    "sg:city":"Pittsburgh",
    "sg:classifiers":[
        {
            "category":"Professional",
            "subcategory":"Lawyer & Legal Services",
            "type":"Services"
        }
    ],
    "sg:phone":"+1 412 261 1904",
    "sg:postcode":"15219",
    "sg:province":"PA",
    "wof:name":"Snarey Kenneth A ESQ",
    "wof:placetype":"venue"
},
  "geometry": {"coordinates":[-79.9981,40.438999],"type":"Point"}
}