{
  "type": "Feature",
  "properties": {
    "addr:full":"315 W Emaus Ave Allentown PA 18103",
    "addr:housenumber":"315",
    "addr:postcode":"18103",
    "addr:street":"W Emaus Ave",
    "iso:country":"US",
    "sg:address":"315 W Emaus Ave",
    "sg:city":"Allentown",
    "sg:classifiers":[
        {
            "category":"Building & Trades",
            "subcategory":"Construction",
            "type":"Services"
        }
    ],
    "sg:phone":"+1 610 797 1931",
    "sg:postcode":"18103",
    "sg:province":"PA",
    "wof:name":"Neon By Frack Inc",
    "wof:placetype":"venue"
},
  "geometry": {"coordinates":[-75.45384300000001,40.578148],"type":"Point"}
}