{
  "type": "Feature",
  "properties": {
    "addr:full":"950 W Trenton Ave Morrisville PA 19067",
    "addr:housenumber":"950",
    "addr:postcode":"19067",
    "addr:street":"W Trenton Ave",
    "iso:country":"US",
    "sg:address":"950 W Trenton Ave",
    "sg:city":"Morrisville",
    "sg:classifiers":[
        {
            "category":"Government",
            "subcategory":"Post Office",
            "type":"Public Place"
        }
    ],
    "sg:phone":"+1   ",
    "sg:postcode":"19067",
    "sg:province":"PA",
    "sg:tags":[
        "postal",
        "us"
    ],
    "wof:name":"Morrisville Main Office",
    "wof:placetype":"venue"
},
  "geometry": {"coordinates":[-74.81247,40.198331],"type":"Point"}
}