{
  "type": "Feature",
  "properties": {
    "iso:country":"US",
    "sg:address":"330 N Chester Rd",
    "sg:city":"West Chester",
    "sg:classifiers":[
        {
            "category":"Communications",
            "subcategory":"Film & Video Production",
            "type":"Services"
        }
    ],
    "sg:phone":"+1 610 240 0288",
    "sg:postcode":"19380",
    "sg:province":"PA",
    "sg:tags":[
        "taping"
    ],
    "wof:name":"Shooters Inc Post & Transfer",
    "wof:placetype":"venue"
},
  "geometry": {"coordinates":[-75.53556,39.975847],"type":"Point"}
}