{
  "type": "Feature",
  "properties": {
    "iso:country":"US",
    "sg:address":"76 Parker Rd",
    "sg:city":"Newville",
    "sg:classifiers":[
        {
            "category":"Farming",
            "subcategory":"Dairy Farm",
            "type":"Manufacturing & Wholesale Goods"
        }
    ],
    "sg:phone":"+1   ",
    "sg:postcode":"17241",
    "sg:province":"PA",
    "sg:tags":[
        "cheese"
    ],
    "wof:name":"Newswanger Wilmer Farm",
    "wof:placetype":"venue"
},
  "geometry": {"coordinates":[-77.383335,40.154143],"type":"Point"}
}