{
  "type": "Feature",
  "properties": {
    "iso:country":"US",
    "sg:address":"3949 Perkiomen Ave",
    "sg:city":"Reading",
    "sg:classifiers":[
        {
            "category":"Shopping",
            "subcategory":"Bicycles & Sporting Goods",
            "type":"Retail Goods"
        }
    ],
    "sg:phone":"+1 610 779 8360",
    "sg:postcode":"19606",
    "sg:province":"PA",
    "sg:tags":[
        "equipment",
        "hockey",
        "supply"
    ],
    "sg:website":"http://www.playitagainsports.com",
    "wof:name":"Play It Again Sports",
    "wof:placetype":"venue"
},
  "geometry": {"coordinates":[-75.87061300000001,40.314581],"type":"Point"}
}