{
  "type": "Feature",
  "properties": {
    "iso:country":"US",
    "sg:address":"2326 W 4th St",
    "sg:city":"Williamsport",
    "sg:classifiers":[
        {
            "category":"Personal",
            "subcategory":"Beauty Salon",
            "type":"Services"
        }
    ],
    "sg:phone":"+1 570 322 7299",
    "sg:postcode":"17701",
    "sg:province":"PA",
    "wof:name":"Talk Of The Town",
    "wof:placetype":"venue"
},
  "geometry": {"coordinates":[-77.060677,41.238578],"type":"Point"}
}