{
  "type": "Feature",
  "properties": {
    "iso:country":"US",
    "sg:address":"13 Christine Ln",
    "sg:city":"Charleroi",
    "sg:classifiers":[
        {
            "category":"Health Services",
            "subcategory":"Doctor",
            "type":"Services"
        }
    ],
    "sg:phone":"+1   ",
    "sg:postcode":"15022",
    "sg:province":"PA",
    "wof:name":"Michael E Erdely DDS",
    "wof:placetype":"venue"
},
  "geometry": {"coordinates":[-79.915628,40.133539],"type":"Point"}
}