{
  "type": "Feature",
  "properties": {
    "iso:country":"US",
    "sg:address":"578 Liberty St Apt 2",
    "sg:city":"Corry",
    "sg:classifiers":[
        {
            "category":"Transit Center",
            "subcategory":"Freight",
            "type":"Transportation"
        },
        {
            "category":"Freight",
            "type":"Transportation"
        }
    ],
    "sg:phone":"+1 814 663 5173",
    "sg:postcode":"16407",
    "sg:province":"PA",
    "sg:tags":[
        "local",
        "trucking-motor",
        "trucking"
    ],
    "wof:name":"Johnson Trucking",
    "wof:placetype":"venue"
},
  "geometry": {"coordinates":[-79.629895,41.922788],"type":"Point"}
}