{
  "type": "Feature",
  "properties": {
    "addr:full":"614 Main St Pittsburgh PA 15215",
    "addr:housenumber":"614",
    "addr:postcode":"15215",
    "addr:street":"Main St",
    "iso:country":"US",
    "sg:address":"614 Main St",
    "sg:city":"Pittsburgh",
    "sg:classifiers":[
        {
            "category":"Social Services",
            "type":"Services"
        }
    ],
    "sg:phone":"+1 412 782 6855",
    "sg:postcode":"15215",
    "sg:province":"PA",
    "sg:tags":[
        "organization",
        "welfare"
    ],
    "wof:name":"All Of Us Care",
    "wof:placetype":"venue"
},
  "geometry": {"coordinates":[-79.935267,40.494712],"type":"Point"}
}