{
  "type": "Feature",
  "properties": {
    "iso:country":"US",
    "sg:address":"538 Cumberland St",
    "sg:city":"Lebanon",
    "sg:classifiers":[
        {
            "category":"Shopping",
            "type":"Retail Goods"
        }
    ],
    "sg:phone":"+1   ",
    "sg:postcode":"17042",
    "sg:province":"PA",
    "sg:tags":[
        "miscellaneous",
        "store"
    ],
    "wof:name":"Lebanon Stamp & Coin Shop",
    "wof:placetype":"venue"
},
  "geometry": {"coordinates":[-76.420412,40.339551],"type":"Point"}
}