{
  "type": "Feature",
  "properties": {
    "iso:country":"US",
    "sg:address":"114 Mifflin St",
    "sg:city":"Bristol",
    "sg:classifiers":[
        {
            "category":"Real Estate",
            "subcategory":"Developer",
            "type":"Services"
        }
    ],
    "sg:phone":"+1   ",
    "sg:postcode":"19007",
    "sg:province":"PA",
    "sg:tags":[
        "development"
    ],
    "wof:name":"Victorian Square Associates",
    "wof:placetype":"venue"
},
  "geometry": {"coordinates":[-74.862596,40.099071],"type":"Point"}
}