{
  "type": "Feature",
  "properties": {
    "addr:full":"62 Ames Way Leesport PA 19533",
    "addr:housenumber":"62",
    "addr:postcode":"19533",
    "addr:street":"Ames Way",
    "iso:country":"US",
    "sg:address":"62 Ames Way",
    "sg:city":"Leesport",
    "sg:classifiers":[
        {
            "category":"Education",
            "subcategory":"School",
            "type":"Public Place"
        }
    ],
    "sg:phone":"+1 610 926 4165",
    "sg:postcode":"19533",
    "sg:province":"PA",
    "wof:name":"Schuyl Valley Elementary Sch",
    "wof:placetype":"venue"
},
  "geometry": {"coordinates":[-75.95061699999999,40.445953],"type":"Point"}
}