{
  "type": "Feature",
  "properties": {
    "iso:country":"US",
    "sg:address":"2228 2nd Ave",
    "sg:city":"Altoona",
    "sg:classifiers":[
        {
            "category":"Building & Trades",
            "subcategory":"Construction",
            "type":"Services"
        }
    ],
    "sg:phone":"+1   ",
    "sg:postcode":"16602",
    "sg:province":"PA",
    "sg:tags":[
        "house"
    ],
    "wof:name":"Josh Burke Construction",
    "wof:placetype":"venue"
},
  "geometry": {"coordinates":[-78.40152999999999,40.50062],"type":"Point"}
}