{
  "type": "Feature",
  "properties": {
    "addr:full":"2605 W Grandview Blvd Erie PA 16506",
    "addr:housenumber":"2605",
    "addr:postcode":"16506",
    "addr:street":"W Grandview Blvd",
    "iso:country":"US",
    "sg:address":"2605 W Grandview Blvd",
    "sg:city":"Erie",
    "sg:classifiers":[
        {
            "category":"Building & Trades",
            "subcategory":"Cleaning & Sanitation",
            "type":"Services"
        }
    ],
    "sg:phone":"+1 814 833 1287",
    "sg:postcode":"16506",
    "sg:province":"PA",
    "sg:tags":[
        "janitor"
    ],
    "wof:name":"Hess's Clean Sweep",
    "wof:placetype":"venue"
},
  "geometry": {"coordinates":[-80.11865400000001,42.074984],"type":"Point"}
}