{
  "type": "Feature",
  "properties": {
    "addr:full":"3072 Kenwick Cir Bethlehem PA 18017",
    "addr:housenumber":"3072",
    "addr:postcode":"18017",
    "addr:street":"Kenwick Cir",
    "iso:country":"US",
    "sg:address":"3072 Kenwick Cir",
    "sg:city":"Bethlehem",
    "sg:classifiers":[
        {
            "category":"Building & Trades",
            "subcategory":"Construction",
            "type":"Services"
        }
    ],
    "sg:phone":"+1   ",
    "sg:postcode":"18017",
    "sg:province":"PA",
    "sg:tags":[
        "house",
        "contractor"
    ],
    "wof:name":"RC Builders Inc",
    "wof:placetype":"venue"
},
  "geometry": {"coordinates":[-75.393271,40.656436],"type":"Point"}
}