{
  "type": "Feature",
  "properties": {
    "iso:country":"US",
    "sg:address":"3025 W Clearfield St",
    "sg:city":"Philadelphia",
    "sg:classifiers":[
        {
            "category":"Social Services",
            "type":"Services"
        }
    ],
    "sg:phone":"+1   ",
    "sg:postcode":"19132",
    "sg:province":"PA",
    "wof:name":"Womens Humane Society",
    "wof:placetype":"venue"
},
  "geometry": {"coordinates":[-75.180144,40.003549],"type":"Point"}
}