{
  "type": "Feature",
  "properties": {
    "addr:full":"1 Main St Luzerne PA 18709",
    "addr:housenumber":"1",
    "addr:postcode":"18709",
    "addr:street":"Main St",
    "iso:country":"US",
    "sg:address":"1 Main St",
    "sg:city":"Luzerne",
    "sg:classifiers":[
        {
            "category":"Insurance",
            "subcategory":"Insurance Agent",
            "type":"Services"
        }
    ],
    "sg:phone":"+1   ",
    "sg:postcode":"18709",
    "sg:province":"PA",
    "wof:name":"Back Mountain Prof Insur",
    "wof:placetype":"venue"
},
  "geometry": {"coordinates":[-75.893215,41.283122],"type":"Point"}
}