{
  "type": "Feature",
  "properties": {
    "addr:full":"528 W Hanover St Hanover PA 17331",
    "addr:housenumber":"528",
    "addr:postcode":"17331",
    "addr:street":"W Hanover St",
    "iso:country":"US",
    "sg:address":"528 W Hanover St",
    "sg:city":"Hanover",
    "sg:classifiers":[
        {
            "category":"Shopping",
            "subcategory":"Clothing, Apparel, & Fashions",
            "type":"Retail Goods"
        }
    ],
    "sg:phone":"+1   ",
    "sg:postcode":"17331",
    "sg:province":"PA",
    "wof:name":"American Outfitters Inc",
    "wof:placetype":"venue"
},
  "geometry": {"coordinates":[-76.984686,39.793267],"type":"Point"}
}