{
  "type": "Feature",
  "properties": {
    "addr:full":"708 Lawn Ave Sellersville PA 18960",
    "addr:housenumber":"708",
    "addr:postcode":"18960",
    "addr:street":"Lawn Ave",
    "iso:country":"US",
    "sg:address":"708 Lawn Ave",
    "sg:city":"Sellersville",
    "sg:classifiers":[
        {
            "category":"Manufacturing",
            "subcategory":"Metals",
            "type":"Manufacturing & Wholesale Goods"
        }
    ],
    "sg:phone":"+1 215 257 6862",
    "sg:postcode":"18960",
    "sg:province":"PA",
    "sg:tags":[
        "treating",
        "abrasive",
        "heat",
        "mfg"
    ],
    "sg:website":"www.thomasregional.com",
    "wof:name":"Precision Finishing Inc",
    "wof:placetype":"venue"
},
  "geometry": {"coordinates":[-75.323893,40.362326],"type":"Point"}
}