{
  "type": "Feature",
  "properties": {
    "iso:country":"US",
    "sg:address":"2460 Bristol Rd",
    "sg:city":"Bensalem",
    "sg:classifiers":[
        {
            "category":"Banks & Credit Unions",
            "subcategory":"Bank",
            "type":"Services"
        }
    ],
    "sg:phone":"+1 215 757 5900",
    "sg:postcode":"19020",
    "sg:province":"PA",
    "wof:name":"First Service Bank",
    "wof:placetype":"venue"
},
  "geometry": {"coordinates":[-74.934318,40.133667],"type":"Point"}
}