{
  "type": "Feature",
  "properties": {
    "iso:country":"US",
    "sg:address":"115 Cameltown Hill Rd",
    "sg:city":"Danville",
    "sg:classifiers":[
        {
            "category":"Building & Trades",
            "subcategory":"Construction",
            "type":"Services"
        }
    ],
    "sg:phone":"+1   ",
    "sg:postcode":"17821",
    "sg:province":"PA",
    "sg:tags":[
        "general",
        "contractor"
    ],
    "wof:name":"Randi S Olshefski Contracting",
    "wof:placetype":"venue"
},
  "geometry": {"coordinates":[-76.642511,41.00312],"type":"Point"}
}