{
  "type": "Feature",
  "properties": {
    "iso:country":"US",
    "sg:address":"500 N Shamokin St",
    "sg:city":"Shamokin",
    "sg:classifiers":[
        {
            "category":"Education",
            "subcategory":"School",
            "type":"Public Place"
        }
    ],
    "sg:phone":"+1   ",
    "sg:postcode":"17872",
    "sg:province":"PA",
    "wof:name":"Line Mountain Middle School",
    "wof:placetype":"venue"
},
  "geometry": {"coordinates":[-76.551164,40.791692],"type":"Point"}
}