{
  "type": "Feature",
  "properties": {
    "addr:full":"516 Mill St Danville PA 17821",
    "addr:housenumber":"516",
    "addr:postcode":"17821",
    "addr:street":"Mill St",
    "iso:country":"US",
    "sg:address":"516 Mill St",
    "sg:city":"Danville",
    "sg:classifiers":[
        {
            "category":"Health Services",
            "subcategory":"Health Practitioner",
            "type":"Services"
        }
    ],
    "sg:phone":"+1 570 271 0966",
    "sg:postcode":"17821",
    "sg:province":"PA",
    "sg:tags":[
        "psychologist"
    ],
    "wof:name":"Carl L Payne",
    "wof:placetype":"venue"
},
  "geometry": {"coordinates":[-76.615945,40.965847],"type":"Point"}
}