{
  "type": "Feature",
  "properties": {
    "iso:country":"US",
    "sg:address":"3551 S Broad St",
    "sg:city":"Philadelphia",
    "sg:classifiers":[
        {
            "category":"Professional",
            "type":"Services"
        }
    ],
    "sg:phone":"+1 215 336 0638",
    "sg:postcode":"19148",
    "sg:province":"PA",
    "sg:tags":[
        "establishment"
    ],
    "wof:name":"Atlantic City Press",
    "wof:placetype":"venue"
},
  "geometry": {"coordinates":[-75.173132,39.906673],"type":"Point"}
}