{
  "type": "Feature",
  "properties": {
    "addr:full":"564 Dianthus St Irwin PA 15642",
    "addr:housenumber":"564",
    "addr:postcode":"15642",
    "addr:street":"Dianthus St",
    "iso:country":"US",
    "sg:address":"564 Dianthus St",
    "sg:city":"Irwin",
    "sg:classifiers":[
        {
            "category":"Professional",
            "type":"Services"
        }
    ],
    "sg:phone":"+1   ",
    "sg:postcode":"15642",
    "sg:province":"PA",
    "wof:name":"Lisa A Offman",
    "wof:placetype":"venue"
},
  "geometry": {"coordinates":[-79.71528600000001,40.319107],"type":"Point"}
}