{
  "type": "Feature",
  "properties": {
    "addr:full":"900 Taylor Dr Folcroft PA 19032",
    "addr:housenumber":"900",
    "addr:postcode":"19032",
    "addr:street":"Taylor Dr",
    "iso:country":"US",
    "sg:address":"900 Taylor Dr",
    "sg:city":"Folcroft",
    "sg:classifiers":[
        {
            "category":"Building & Trades",
            "subcategory":"Landscaping Services",
            "type":"Services"
        }
    ],
    "sg:phone":"+1   ",
    "sg:postcode":"19032",
    "sg:province":"PA",
    "wof:name":"Walts Tree Service Inc",
    "wof:placetype":"venue"
},
  "geometry": {"coordinates":[-75.28620600000001,39.884034],"type":"Point"}
}