{
  "type": "Feature",
  "properties": {
    "iso:country":"US",
    "sg:address":"8000 State Rd",
    "sg:city":"Philadelphia",
    "sg:classifiers":[
        {
            "category":"Wholesale",
            "subcategory":"Machinery & Supplies",
            "type":"Manufacturing & Wholesale Goods"
        }
    ],
    "sg:phone":"+1   ",
    "sg:postcode":"19136",
    "sg:province":"PA",
    "sg:tags":[
        "hardware",
        "industrial"
    ],
    "wof:name":"Plastic & Metal Products Corp",
    "wof:placetype":"venue"
},
  "geometry": {"coordinates":[-75.021568,40.031354],"type":"Point"}
}