{
  "type": "Feature",
  "properties": {
    "iso:country":"US",
    "sg:address":"6672 Baltimore Pike",
    "sg:city":"Littlestown",
    "sg:classifiers":[
        {
            "category":"Home & Garden",
            "subcategory":"Building Materials",
            "type":"Retail Goods"
        }
    ],
    "sg:phone":"+1   ",
    "sg:postcode":"17340",
    "sg:province":"PA",
    "sg:tags":[
        "label",
        "wear",
        "private",
        "casual"
    ],
    "wof:name":"Live Free Inc",
    "wof:placetype":"venue"
},
  "geometry": {"coordinates":[-77.067136,39.721338],"type":"Point"}
}