{
  "type": "Feature",
  "properties": {
    "addr:full":"2401 Park Dr Harrisburg PA 17110",
    "addr:housenumber":"2401",
    "addr:postcode":"17110",
    "addr:street":"Park Dr",
    "iso:country":"US",
    "sg:address":"2401 Park Dr",
    "sg:city":"Harrisburg",
    "sg:classifiers":[
        {
            "category":"Professional",
            "subcategory":"Detective & Security Services",
            "type":"Services"
        }
    ],
    "sg:phone":"+1 717 364 1094",
    "sg:postcode":"17110",
    "sg:province":"PA",
    "wof:name":"Internet Systems Defense",
    "wof:placetype":"venue"
},
  "geometry": {"coordinates":[-76.841404,40.308834],"type":"Point"}
}