{
  "type": "Feature",
  "properties": {
    "addr:full":"77 Van Horn Dr Warminster PA 18974",
    "addr:housenumber":"77",
    "addr:postcode":"18974",
    "addr:street":"Van Horn Dr",
    "iso:country":"US",
    "sg:address":"77 Van Horn Dr",
    "sg:city":"Warminster",
    "sg:classifiers":[
        {
            "category":"Food & Beverages",
            "subcategory":"Groceries & Convenience Stores",
            "type":"Retail Goods"
        }
    ],
    "sg:phone":"+1   ",
    "sg:postcode":"18974",
    "sg:province":"PA",
    "wof:name":"C & D Dell Inc",
    "wof:placetype":"venue"
},
  "geometry": {"coordinates":[-75.084903,40.18555],"type":"Point"}
}