{
  "type": "Feature",
  "properties": {
    "iso:country":"US",
    "sg:address":"451 Main St",
    "sg:city":"Berlin",
    "sg:classifiers":[
        {
            "category":"Personal",
            "subcategory":"Beauty Salon",
            "type":"Services"
        }
    ],
    "sg:phone":"+1 814 267 4241",
    "sg:postcode":"15530",
    "sg:province":"PA",
    "sg:tags":[
        "shop"
    ],
    "wof:name":"New Creations Family Hair Saln",
    "wof:placetype":"venue"
},
  "geometry": {"coordinates":[-78.959109,39.921008],"type":"Point"}
}