{
  "type": "Feature",
  "properties": {
    "iso:country":"US",
    "sg:address":"110 Lincoln Hwy",
    "sg:city":"Fairless Hills",
    "sg:classifiers":[
        {
            "category":"Insurance",
            "subcategory":"Insurance Agent",
            "type":"Services"
        }
    ],
    "sg:phone":"+1 215 269 2036",
    "sg:postcode":"19030",
    "sg:province":"PA",
    "wof:name":"AAA Insurance",
    "wof:placetype":"venue"
},
  "geometry": {"coordinates":[-74.868702,40.180675],"type":"Point"}
}