{
  "type": "Feature",
  "properties": {
    "addr:full":"1295 Millmont Rd Millmont PA 17845",
    "addr:housenumber":"1295",
    "addr:postcode":"17845",
    "addr:street":"Millmont Rd",
    "iso:country":"US",
    "sg:address":"1295 Millmont Rd",
    "sg:city":"Millmont",
    "sg:classifiers":[
        {
            "category":"Government",
            "subcategory":"Post Office",
            "type":"Public Place"
        }
    ],
    "sg:phone":"+1 800 275 8777",
    "sg:postcode":"17845",
    "sg:province":"PA",
    "sg:website":"http://www.usps.com",
    "wof:name":"USPS - United States Post Office - Millmont Main Office",
    "wof:placetype":"venue"
},
  "geometry": {"coordinates":[-77.140511,40.886731],"type":"Point"}
}