{
  "type": "Feature",
  "properties": {
    "iso:country":"US",
    "sg:address":"16 Esther Ln",
    "sg:city":"Dillsburg",
    "sg:classifiers":[
        {
            "category":"Transit Center",
            "subcategory":"Freight",
            "type":"Transportation"
        }
    ],
    "sg:phone":"+1 717 432 1758",
    "sg:postcode":"17019",
    "sg:province":"PA",
    "sg:tags":[
        "trucking-light",
        "hauling"
    ],
    "wof:name":"Smith S Helpful Haulers",
    "wof:placetype":"venue"
},
  "geometry": {"coordinates":[-77.04507700000001,40.127768],"type":"Point"}
}