{
  "type": "Feature",
  "properties": {
    "iso:country":"US",
    "sg:address":"700 Tanglewood Rd",
    "sg:city":"Muncy",
    "sg:classifiers":[
        {
            "category":"Real Estate",
            "subcategory":"Real Estate Operator",
            "type":"Services"
        }
    ],
    "sg:phone":"+1 570 546 5635",
    "sg:postcode":"17756",
    "sg:province":"PA",
    "sg:tags":[
        "apartment"
    ],
    "wof:name":"Glade Side Apartments",
    "wof:placetype":"venue"
},
  "geometry": {"coordinates":[-76.77671599999999,41.196079],"type":"Point"}
}