{
  "type": "Feature",
  "properties": {
    "iso:country":"US",
    "sg:address":"441 N Lewis Rd",
    "sg:city":"Royersford",
    "sg:classifiers":[
        {
            "category":"Social Services",
            "subcategory":"Child Care",
            "type":"Services"
        }
    ],
    "sg:phone":"+1   ",
    "sg:postcode":"19468",
    "sg:province":"PA",
    "sg:tags":[
        "day"
    ],
    "wof:name":"Country Tyme Early Educatn Ctr",
    "wof:placetype":"venue"
},
  "geometry": {"coordinates":[-75.54138399999999,40.206057],"type":"Point"}
}