{
  "type": "Feature",
  "properties": {
    "iso:country":"US",
    "sg:address":"161 Tinkham Rd",
    "sg:city":"Waverly",
    "sg:classifiers":[
        {
            "category":"Wholesale",
            "subcategory":"Auto Parts",
            "type":"Manufacturing & Wholesale Goods"
        }
    ],
    "sg:phone":"+1 607 565 4432",
    "sg:postcode":"14892",
    "sg:province":"PA",
    "sg:tags":[
        "automobile",
        "wrecking"
    ],
    "wof:name":"Williams Auto Salvage",
    "wof:placetype":"venue"
},
  "geometry": {"coordinates":[-76.46746400000001,42.115574],"type":"Point"}
}