{
  "type": "Feature",
  "properties": {
    "addr:full":"7101 New Falls Rd Levittown PA 19055",
    "addr:housenumber":"7101",
    "addr:postcode":"19055",
    "addr:street":"New Falls Rd Levittown",
    "iso:country":"US",
    "sg:address":"7101 New Falls Rd",
    "sg:city":"Levittown",
    "sg:classifiers":[
        {
            "category":"Banks & Credit Unions",
            "subcategory":"Bank",
            "type":"Services"
        }
    ],
    "sg:phone":"+1   ",
    "sg:postcode":"19055",
    "sg:province":"PA",
    "sg:tags":[
        "cashing",
        "check"
    ],
    "wof:name":"Ace Cash Express",
    "wof:placetype":"venue"
},
  "geometry": {"coordinates":[-74.859028,40.151771],"type":"Point"}
}