{
  "type": "Feature",
  "properties": {
    "iso:country":"US",
    "sg:address":"1609 Brentwood Dr",
    "sg:city":"Greenville",
    "sg:classifiers":[
        {
            "category":"Social Services",
            "type":"Services"
        }
    ],
    "sg:phone":"+1   ",
    "sg:postcode":"16125",
    "sg:province":"PA",
    "wof:name":"Dance Connection Center",
    "wof:placetype":"venue"
},
  "geometry": {"coordinates":[-80.396598,41.337973],"type":"Point"}
}