{
  "type": "Feature",
  "properties": {
    "iso:country":"US",
    "sg:address":"1015 Nedro Ave",
    "sg:city":"Philadelphia",
    "sg:classifiers":[
        {
            "category":"Manufacturing",
            "subcategory":"Building Materials",
            "type":"Manufacturing & Wholesale Goods"
        },
        {
            "category":"Home & Garden",
            "subcategory":"Carpets & Floor Coverings",
            "type":"Retail Goods"
        }
    ],
    "sg:phone":"+1 215 927 4151",
    "sg:postcode":"19141",
    "sg:province":"PA",
    "sg:tags":[
        "materials-wholesale",
        "manufacturer"
    ],
    "wof:name":"Haynes Hardwood Floor Rfnshng",
    "wof:placetype":"venue"
},
  "geometry": {"coordinates":[-75.13757,40.042099],"type":"Point"}
}