{
  "type": "Feature",
  "properties": {
    "addr:full":"1000 David Ln Jeannette PA 15644",
    "addr:housenumber":"1000",
    "addr:postcode":"15644",
    "addr:street":"David Ln",
    "iso:country":"US",
    "sg:address":"1000 David Ln",
    "sg:city":"Jeannette",
    "sg:classifiers":[
        {
            "category":"Restaurant",
            "type":"Food & Drink"
        }
    ],
    "sg:phone":"+1   ",
    "sg:postcode":"15644",
    "sg:province":"PA",
    "sg:tags":[
        "eating"
    ],
    "wof:name":"Dairy Queen",
    "wof:placetype":"venue"
},
  "geometry": {"coordinates":[-79.59912,40.354569],"type":"Point"}
}