{
  "type": "Feature",
  "properties": {
    "iso:country":"US",
    "sg:address":"208 Colony Ct",
    "sg:city":"Pittsburgh",
    "sg:classifiers":[
        {
            "category":"Building & Trades",
            "subcategory":"Construction",
            "type":"Services"
        }
    ],
    "sg:phone":"+1   ",
    "sg:postcode":"15205",
    "sg:province":"PA",
    "sg:tags":[
        "hanging",
        "contractor"
    ],
    "wof:name":"Angelos Painting",
    "wof:placetype":"venue"
},
  "geometry": {"coordinates":[-80.10012,40.429505],"type":"Point"}
}