{
  "type": "Feature",
  "properties": {
    "iso:country":"US",
    "sg:address":"5187 Library Rd",
    "sg:city":"Bethel Park",
    "sg:classifiers":[
        {
            "category":"Health Services",
            "subcategory":"Doctor",
            "type":"Services"
        }
    ],
    "sg:phone":"+1 412 835 4886",
    "sg:postcode":"15102",
    "sg:province":"PA",
    "sg:tags":[
        "physician",
        "surgeon"
    ],
    "wof:name":"Fatigati & Nalin",
    "wof:placetype":"venue"
},
  "geometry": {"coordinates":[-80.024198,40.335603],"type":"Point"}
}