{
  "type": "Feature",
  "properties": {
    "addr:full":"344 Center Ave Pittsburgh PA 15229",
    "addr:housenumber":"344",
    "addr:postcode":"15229",
    "addr:street":"Center Ave",
    "iso:country":"US",
    "sg:address":"344 Center Ave",
    "sg:city":"Pittsburgh",
    "sg:classifiers":[
        {
            "category":"Health Services",
            "subcategory":"Doctor",
            "type":"Services"
        }
    ],
    "sg:phone":"+1   ",
    "sg:postcode":"15229",
    "sg:province":"PA",
    "wof:name":"Bruce D Cohen",
    "wof:placetype":"venue"
},
  "geometry": {"coordinates":[-80.022496,40.515987],"type":"Point"}
}