{
  "type": "Feature",
  "properties": {
    "addr:full":"341 Brookline Blvd Havertown PA 19083",
    "addr:housenumber":"341",
    "addr:postcode":"19083",
    "addr:street":"Brookline Blvd",
    "iso:country":"US",
    "sg:address":"341 Brookline Blvd",
    "sg:city":"Havertown",
    "sg:classifiers":[
        {
            "category":"Social Services",
            "type":"Services"
        }
    ],
    "sg:phone":"+1   ",
    "sg:postcode":"19083",
    "sg:province":"PA",
    "wof:name":"Havertown Counseling Center",
    "wof:placetype":"venue"
},
  "geometry": {"coordinates":[-75.29634299999999,39.98205],"type":"Point"}
}