{
  "type": "Feature",
  "properties": {
    "iso:country":"US",
    "sg:address":"RR 2 Box 75",
    "sg:city":"Dalton",
    "sg:classifiers":[
        {
            "category":"Personal",
            "subcategory":"Beauty Salon",
            "type":"Services"
        }
    ],
    "sg:phone":"+1 570 586 3610",
    "sg:postcode":"18414",
    "sg:province":"PA",
    "wof:name":"Kdny Salon",
    "wof:placetype":"venue"
},
  "geometry": {"coordinates":[-75.789562,41.488115],"type":"Point"}
}