{
  "type": "Feature",
  "properties": {
    "iso:country":"US",
    "sg:address":"2020 Garrett Rd",
    "sg:city":"Lansdowne",
    "sg:classifiers":[
        {
            "category":"Real Estate",
            "subcategory":"Real Estate Operator",
            "type":"Services"
        }
    ],
    "sg:phone":"+1   ",
    "sg:postcode":"19050",
    "sg:province":"PA",
    "sg:tags":[
        "building",
        "apartment"
    ],
    "wof:name":"Lin Way Manor Apts",
    "wof:placetype":"venue"
},
  "geometry": {"coordinates":[-75.280395,39.952188],"type":"Point"}
}