{
  "type": "Feature",
  "properties": {
    "iso:country":"US",
    "sg:address":"786 S Front St",
    "sg:city":"Philadelphia",
    "sg:classifiers":[
        {
            "category":"Professional",
            "subcategory":"Art Services",
            "type":"Services"
        }
    ],
    "sg:phone":"+1   ",
    "sg:postcode":"19147",
    "sg:province":"PA",
    "sg:tags":[
        "printing",
        "graphic",
        "design"
    ],
    "wof:name":"Virtual Graphic Arts",
    "wof:placetype":"venue"
},
  "geometry": {"coordinates":[-75.144824,39.938074],"type":"Point"}
}