{
  "type": "Feature",
  "properties": {
    "addr:full":"234 N Whiteoak St Kutztown PA 19530",
    "addr:housenumber":"234",
    "addr:postcode":"19530",
    "addr:street":"N Whiteoak St",
    "iso:country":"US",
    "sg:address":"234 N Whiteoak St",
    "sg:city":"Kutztown",
    "sg:classifiers":[
        {
            "category":"Retail",
            "subcategory":"Laundry & Dry Cleaning",
            "type":"Services"
        }
    ],
    "sg:phone":"+1 610 683 7903",
    "sg:postcode":"19530",
    "sg:province":"PA",
    "sg:tags":[
        "cleaners"
    ],
    "wof:name":"Kelchner Cleaners Inc",
    "wof:placetype":"venue"
},
  "geometry": {"coordinates":[-75.781127,40.517396],"type":"Point"}
}