{
  "type": "Feature",
  "properties": {
    "iso:country":"US",
    "sg:address":"124 Sumac St",
    "sg:city":"Philadelphia",
    "sg:classifiers":[
        {
            "category":"Arts & Performance",
            "subcategory":"Music",
            "type":"Entertainment"
        }
    ],
    "sg:phone":"+1 215 483 4834",
    "sg:postcode":"19128",
    "sg:province":"PA",
    "sg:tags":[
        "band",
        "orchestra"
    ],
    "wof:name":"Swing Shift",
    "wof:placetype":"venue"
},
  "geometry": {"coordinates":[-75.208923,40.017391],"type":"Point"}
}