{
  "type": "Feature",
  "properties": {
    "addr:full":"313 3rd St Darlington PA 16115",
    "addr:housenumber":"313",
    "addr:postcode":"16115",
    "addr:street":"3Rd St",
    "iso:country":"US",
    "sg:address":"313 3rd St",
    "sg:city":"Darlington",
    "sg:classifiers":[
        {
            "category":"Professional",
            "type":"Services"
        }
    ],
    "sg:phone":"+1   ",
    "sg:postcode":"16115",
    "sg:province":"PA",
    "wof:name":"Benton Sunset Tan & Tattoos",
    "wof:placetype":"venue"
},
  "geometry": {"coordinates":[-80.421401,40.810515],"type":"Point"}
}