{
  "type": "Feature",
  "properties": {
    "iso:country":"US",
    "sg:address":"120 5th Ave",
    "sg:city":"West View",
    "sg:classifiers":[
        {
            "category":"Insurance",
            "subcategory":"Insurance Agent",
            "type":"Services"
        }
    ],
    "sg:phone":"+1 412 544 4185",
    "sg:postcode":"15229",
    "sg:province":"PA",
    "wof:name":"Alliance Ventures Inc",
    "wof:placetype":"venue"
},
  "geometry": {"coordinates":[-80.022757,40.528791],"type":"Point"}
}