{
  "type": "Feature",
  "properties": {
    "addr:full":"304 East St Warren PA 16365",
    "addr:housenumber":"304",
    "addr:postcode":"16365",
    "addr:street":"East St",
    "iso:country":"US",
    "sg:address":"304 East St",
    "sg:city":"Warren",
    "sg:classifiers":[
        {
            "category":"Retail",
            "subcategory":"Funeral Services",
            "type":"Services"
        }
    ],
    "sg:phone":"+1   ",
    "sg:postcode":"16365",
    "sg:province":"PA",
    "wof:name":"Donald E Lewis Funeral Home",
    "wof:placetype":"venue"
},
  "geometry": {"coordinates":[-79.14412,41.848356],"type":"Point"}
}