{
  "type": "Feature",
  "properties": {
    "iso:country":"US",
    "sg:address":"142 Cinnamon Hill Rd",
    "sg:city":"King Of Prussia",
    "sg:classifiers":[
        {
            "category":"Building & Trades",
            "subcategory":"Landscaping Services",
            "type":"Services"
        }
    ],
    "sg:phone":"+1   ",
    "sg:postcode":"19406",
    "sg:province":"PA",
    "wof:name":"Lawn Cutting Service",
    "wof:placetype":"venue"
},
  "geometry": {"coordinates":[-75.373801,40.104933],"type":"Point"}
}