{
  "type": "Feature",
  "properties": {
    "iso:country":"US",
    "sg:address":"3782 W Main St",
    "sg:city":"Belleville",
    "sg:classifiers":[
        {
            "category":"Travel",
            "subcategory":"Hotels & Motels",
            "type":"Entertainment"
        }
    ],
    "sg:phone":"+1 717 935 2327",
    "sg:postcode":"17004",
    "sg:province":"PA",
    "sg:tags":[
        "breakfast",
        "accommodation",
        "bed"
    ],
    "wof:name":"Mercer & Bratt Bed & Breakfast",
    "wof:placetype":"venue"
},
  "geometry": {"coordinates":[-77.73276300000001,40.603013],"type":"Point"}
}