{
  "type": "Feature",
  "properties": {
    "iso:country":"US",
    "sg:address":"7641 Burkholder Rd",
    "sg:city":"Waynesboro",
    "sg:classifiers":[
        {
            "category":"Food & Beverages",
            "subcategory":"Specialty",
            "type":"Retail Goods"
        }
    ],
    "sg:phone":"+1 717 762 8314",
    "sg:postcode":"17268",
    "sg:province":"PA",
    "wof:name":"Herb Corner",
    "wof:placetype":"venue"
},
  "geometry": {"coordinates":[-77.600098,39.822376],"type":"Point"}
}