{
  "type": "Feature",
  "properties": {
    "addr:full":"1260 Connellsville Rd Lemont Furnace PA 15456",
    "addr:housenumber":"1260",
    "addr:postcode":"15456",
    "addr:street":"Connellsville Rd",
    "iso:country":"US",
    "sg:address":"1260 Connellsville Rd",
    "sg:city":"Lemont Furnace",
    "sg:classifiers":[
        {
            "category":"Shopping",
            "subcategory":"Gifts & Souvenirs",
            "type":"Retail Goods"
        }
    ],
    "sg:phone":"+1   ",
    "sg:postcode":"15456",
    "sg:province":"PA",
    "wof:name":"Debra Collins",
    "wof:placetype":"venue"
},
  "geometry": {"coordinates":[-79.68407999999999,39.91364],"type":"Point"}
}