{
  "type": "Feature",
  "properties": {
    "addr:full":"517 South St Lykens PA 17048",
    "addr:housenumber":"517",
    "addr:postcode":"17048",
    "addr:street":"South St",
    "iso:country":"US",
    "sg:address":"517 South St",
    "sg:city":"Lykens",
    "sg:classifiers":[
        {
            "category":"Health Services",
            "subcategory":"Doctor",
            "type":"Services"
        }
    ],
    "sg:phone":"+1 717 453 1075",
    "sg:postcode":"17048",
    "sg:province":"PA",
    "sg:tags":[
        "medicine",
        "physician",
        "practice",
        "surgeons",
        "family"
    ],
    "sg:website":"http://www.fpcdoctors.com",
    "wof:name":"Family Practice Center, P.C.",
    "wof:placetype":"venue"
},
  "geometry": {"coordinates":[-76.703248,40.565159],"type":"Point"}
}