{
  "type": "Feature",
  "properties": {
    "addr:full":"701 W High St Pottstown PA 19464",
    "addr:housenumber":"701",
    "addr:postcode":"19464",
    "addr:street":"W High St",
    "iso:country":"US",
    "sg:address":"701 W High St",
    "sg:city":"Pottstown",
    "sg:classifiers":[
        {
            "category":"Food & Beverages",
            "subcategory":"Liquor & Beverages",
            "type":"Retail Goods"
        },
        {
            "category":"Wholesale",
            "subcategory":"Beer",
            "type":"Manufacturing & Wholesale Goods"
        }
    ],
    "sg:phone":"+1 610 326 4876",
    "sg:postcode":"19464",
    "sg:province":"PA",
    "sg:tags":[
        "ale"
    ],
    "wof:name":"A J Beverages",
    "wof:placetype":"venue"
},
  "geometry": {"coordinates":[-75.679317,40.246643],"type":"Point"}
}