{
  "type": "Feature",
  "properties": {
    "iso:country":"US",
    "sg:address":"5375 William Flynn Hwy",
    "sg:city":"Gibsonia",
    "sg:classifiers":[
        {
            "category":"Banks & Credit Unions",
            "subcategory":"Bank",
            "type":"Services"
        }
    ],
    "sg:phone":"+1 724 443 0250",
    "sg:postcode":"15044",
    "sg:province":"PA",
    "sg:tags":[
        "loan"
    ],
    "wof:name":"Dollar Bank",
    "wof:placetype":"venue"
},
  "geometry": {"coordinates":[-79.94556,40.617806],"type":"Point"}
}