{
  "type": "Feature",
  "properties": {
    "addr:full":"21 S Wayne St Lewistown PA 17044",
    "addr:housenumber":"21",
    "addr:postcode":"17044",
    "addr:street":"S Wayne St",
    "iso:country":"US",
    "sg:address":"21 S Wayne St",
    "sg:city":"Lewistown",
    "sg:classifiers":[
        {
            "category":"Banks & Credit Unions",
            "subcategory":"Investment Brokerage",
            "type":"Services"
        }
    ],
    "sg:phone":"+1 717 248 1577",
    "sg:postcode":"17044",
    "sg:province":"PA",
    "sg:tags":[
        "consultant",
        "planning",
        "financial"
    ],
    "wof:name":"American Express Financial Adv",
    "wof:placetype":"venue"
},
  "geometry": {"coordinates":[-77.575642,40.596439],"type":"Point"}
}