{
  "type": "Feature",
  "properties": {
    "iso:country":"US",
    "sg:address":"4035 Kottler Dr",
    "sg:city":"Lafayette Hill",
    "sg:classifiers":[
        {
            "category":"Professional",
            "subcategory":"Management & Consulting",
            "type":"Services"
        }
    ],
    "sg:phone":"+1 610 834 0884",
    "sg:postcode":"19444",
    "sg:province":"PA",
    "sg:tags":[
        "consultant",
        "security",
        "system"
    ],
    "sg:website":"www.securityresourcesgroup.net",
    "wof:name":"Security Resources Group",
    "wof:placetype":"venue"
},
  "geometry": {"coordinates":[-75.250274,40.088025],"type":"Point"}
}