{
  "type": "Feature",
  "properties": {
    "addr:full":"243 Philmont Ave Feastervl Trvs PA 19053",
    "addr:housenumber":"243",
    "addr:postcode":"19053",
    "addr:street":"Philmont Ave",
    "iso:country":"US",
    "sg:address":"243 Philmont Ave",
    "sg:city":"Feastervl Trvs",
    "sg:classifiers":[
        {
            "category":"Retail",
            "subcategory":"Auto Repair",
            "type":"Services"
        }
    ],
    "sg:phone":"+1 215 364 4340",
    "sg:postcode":"19053",
    "sg:province":"PA",
    "sg:tags":[
        "body",
        "automobile",
        "painting"
    ],
    "wof:name":"Express Collison",
    "wof:placetype":"venue"
},
  "geometry": {"coordinates":[-75.004166,40.133839],"type":"Point"}
}