{
  "type": "Feature",
  "properties": {
    "addr:full":"323 Bainbridge St Philadelphia PA 19147",
    "addr:housenumber":"323",
    "addr:postcode":"19147",
    "addr:street":"Bainbridge St",
    "iso:country":"US",
    "sg:address":"323 Bainbridge St",
    "sg:city":"Philadelphia",
    "sg:classifiers":[
        {
            "category":"Shopping",
            "subcategory":"Pets & Pet Supplies",
            "type":"Retail Goods"
        },
        {
            "category":"Retail",
            "subcategory":"Veterinary Services",
            "type":"Services"
        }
    ],
    "sg:phone":"+1 215 925 5753",
    "sg:postcode":"19147",
    "sg:province":"PA",
    "sg:tags":[
        "product",
        "hospital",
        "specialty",
        "clinic",
        "health",
        "animal",
        "veterinarian"
    ],
    "sg:website":"queenvillageah.com",
    "wof:name":"Queen Village Animal Hospital",
    "wof:placetype":"venue"
},
  "geometry": {"coordinates":[-75.148201,39.940399],"type":"Point"}
}