{
  "type": "Feature",
  "properties": {
    "addr:full":"2350 Stewart St Philadelphia PA 19121",
    "addr:housenumber":"2350",
    "addr:postcode":"19121",
    "addr:street":"Stewart St",
    "iso:country":"US",
    "sg:address":"2350 Stewart St",
    "sg:city":"Philadelphia",
    "sg:classifiers":[
        {
            "category":"Real Estate",
            "subcategory":"Real Estate Agent",
            "type":"Services"
        }
    ],
    "sg:phone":"+1   ",
    "sg:postcode":"19121",
    "sg:province":"PA",
    "wof:name":"Ann & Associates",
    "wof:placetype":"venue"
},
  "geometry": {"coordinates":[-75.17418499999999,39.977406],"type":"Point"}
}