{
  "type": "Feature",
  "properties": {
    "addr:full":"5930 Ogontz Ave Philadelphia PA 19141",
    "addr:housenumber":"5930",
    "addr:postcode":"19141",
    "addr:street":"Ogontz Ave",
    "iso:country":"US",
    "sg:address":"5930 Ogontz Ave",
    "sg:city":"Philadelphia",
    "sg:classifiers":[
        {
            "category":"Personal",
            "subcategory":"Barber",
            "type":"Services"
        }
    ],
    "sg:phone":"+1 215 927 5393",
    "sg:postcode":"19141",
    "sg:province":"PA",
    "wof:name":"Invasions Barber Shop",
    "wof:placetype":"venue"
},
  "geometry": {"coordinates":[-75.149674,40.04467],"type":"Point"}
}