{
  "type": "Feature",
  "properties": {
    "addr:full":"622 Russellwood Ave Mc Kees Rocks PA 15136",
    "addr:housenumber":"622",
    "addr:postcode":"15136",
    "addr:street":"Russellwood Ave Mc Kees Rocks",
    "iso:country":"US",
    "sg:address":"622 Russellwood Ave",
    "sg:city":"Mc Kees Rocks",
    "sg:classifiers":[
        {
            "category":"Organizations",
            "subcategory":"Religious Organization",
            "type":"Services"
        }
    ],
    "sg:phone":"+1 412 331 6332",
    "sg:postcode":"15136",
    "sg:province":"PA",
    "sg:tags":[
        "church"
    ],
    "wof:name":"First Baptist Church",
    "wof:placetype":"venue"
},
  "geometry": {"coordinates":[-80.07374799999999,40.471793],"type":"Point"}
}