{
  "type": "Feature",
  "properties": {
    "addr:full":"11 Blakeslee Boulevard Dr E Lehighton PA 18235",
    "addr:housenumber":"11",
    "addr:postcode":"18235",
    "addr:street":"Blakeslee Boulevard Dr E",
    "iso:country":"US",
    "sg:address":"11 Blakeslee Boulevard Dr E",
    "sg:city":"Lehighton",
    "sg:classifiers":[
        {
            "category":"Government",
            "subcategory":"Office",
            "type":"Public Place"
        }
    ],
    "sg:phone":"+1 610 377 4008",
    "sg:postcode":"18235",
    "sg:province":"PA",
    "sg:tags":[
        "village"
    ],
    "wof:name":"Lehighton Borough Sewage Plant",
    "wof:placetype":"venue"
},
  "geometry": {"coordinates":[-75.70469199999999,40.82684],"type":"Point"}
}