{
  "type": "Feature",
  "properties": {
    "addr:full":"4407 Main St Philadelphia PA 19127",
    "addr:housenumber":"4407",
    "addr:postcode":"19127",
    "addr:street":"Main St",
    "iso:country":"US",
    "sg:address":"4407 Main St",
    "sg:city":"Philadelphia",
    "sg:classifiers":[
        {
            "category":"Shopping",
            "subcategory":"Optical Goods",
            "type":"Retail Goods"
        }
    ],
    "sg:phone":"+1 215 487 2711",
    "sg:postcode":"19127",
    "sg:province":"PA",
    "sg:tags":[
        "optician",
        "eyewear"
    ],
    "sg:website":"theeyeglassworks.com",
    "wof:name":"Eyeglass Works the",
    "wof:placetype":"venue"
},
  "geometry": {"coordinates":[-75.225098,40.025902],"type":"Point"}
}