{
  "type": "Feature",
  "properties": {
    "iso:country":"US",
    "sg:address":"178 Brush Valley Rd",
    "sg:city":"Boalsburg",
    "sg:classifiers":[
        {
            "category":"Real Estate",
            "subcategory":"Real Estate Agent",
            "type":"Services"
        }
    ],
    "sg:phone":"+1   ",
    "sg:postcode":"16827",
    "sg:province":"PA",
    "wof:name":"Canadian Pacific Realty",
    "wof:placetype":"venue"
},
  "geometry": {"coordinates":[-77.781297,40.799452],"type":"Point"}
}