{
  "type": "Feature",
  "properties": {
    "iso:country":"US",
    "sg:address":"5650 Wattsburg Rd",
    "sg:city":"Erie",
    "sg:classifiers":[
        {
            "category":"Shopping",
            "subcategory":"Gifts & Souvenirs",
            "type":"Retail Goods"
        }
    ],
    "sg:phone":"+1   ",
    "sg:postcode":"16509",
    "sg:province":"PA",
    "sg:tags":[
        "shop",
        "novelty"
    ],
    "wof:name":"Fairfield Company",
    "wof:placetype":"venue"
},
  "geometry": {"coordinates":[-80.01787299999999,42.100001],"type":"Point"}
}