{
  "type": "Feature",
  "properties": {
    "addr:full":"453 Baltimore Pike Ste 2 Springfield PA 19064",
    "addr:housenumber":"453",
    "addr:postcode":"19064",
    "addr:street":"Baltimore Pike Ste 2",
    "iso:country":"US",
    "sg:address":"453 Baltimore Pike Ste 2",
    "sg:city":"Springfield",
    "sg:classifiers":[
        {
            "category":"Banks & Credit Unions",
            "subcategory":"Investment Brokerage",
            "type":"Services"
        },
        {
            "category":"Insurance",
            "subcategory":"Hazard Insurance",
            "type":"Services"
        }
    ],
    "sg:phone":"+1 610 543 3757",
    "sg:postcode":"19064",
    "sg:province":"PA",
    "sg:tags":[
        "commercial",
        "agent",
        "business",
        "resume"
    ],
    "sg:website":"http://www.beneservonline.com",
    "wof:name":"Beneserv",
    "wof:placetype":"venue"
},
  "geometry": {"coordinates":[-75.32287100000001,39.920914],"type":"Point"}
}