{
  "type": "Feature",
  "properties": {
    "addr:full":"41 W Otterman St Greensburg PA 15601",
    "addr:housenumber":"41",
    "addr:postcode":"15601",
    "addr:street":"W Otterman St",
    "iso:country":"US",
    "sg:address":"41 W Otterman St",
    "sg:city":"Greensburg",
    "sg:classifiers":[
        {
            "category":"Museum",
            "type":"Entertainment"
        }
    ],
    "sg:phone":"+1   ",
    "sg:postcode":"15601",
    "sg:province":"PA",
    "sg:tags":[
        "gallery"
    ],
    "wof:name":"Elizabeth Hanna Guild",
    "wof:placetype":"venue"
},
  "geometry": {"coordinates":[-79.54541500000001,40.303407],"type":"Point"}
}