{
  "type": "Feature",
  "properties": {
    "addr:full":"4167 Main St #1 Philadelphia PA 19127",
    "addr:housenumber":"4167",
    "addr:postcode":"19127",
    "addr:street":"Main St # 1",
    "iso:country":"US",
    "sg:address":"4167 Main St #1",
    "sg:city":"Philadelphia",
    "sg:classifiers":[
        {
            "category":"Personal",
            "subcategory":"Beauty Salon",
            "type":"Services"
        }
    ],
    "sg:phone":"+1 215 482 9900",
    "sg:postcode":"19127",
    "sg:province":"PA",
    "sg:tags":[
        "hair"
    ],
    "wof:name":"Glow Salon",
    "wof:placetype":"venue"
},
  "geometry": {"coordinates":[-75.219909,40.023421],"type":"Point"}
}