{
  "type": "Feature",
  "properties": {
    "iso:country":"US",
    "sg:address":"3262 Glase Rd",
    "sg:city":"Danielsville",
    "sg:classifiers":[
        {
            "category":"Building & Trades",
            "subcategory":"Electrical",
            "type":"Services"
        }
    ],
    "sg:phone":"+1 610 837 9248",
    "sg:postcode":"18038",
    "sg:province":"PA",
    "sg:tags":[
        "installation"
    ],
    "wof:name":"Quality Home Svc",
    "wof:placetype":"venue"
},
  "geometry": {"coordinates":[-75.473873,40.784791],"type":"Point"}
}