{
  "type": "Feature",
  "properties": {
    "iso:country":"US",
    "sg:address":"1120 Renee Cir",
    "sg:city":"Feasterville Trevose",
    "sg:classifiers":[
        {
            "category":"Social Services",
            "type":"Services"
        }
    ],
    "sg:phone":"+1   ",
    "sg:postcode":"19053",
    "sg:province":"PA",
    "wof:name":"Baby Adoption Services Inc",
    "wof:placetype":"venue"
},
  "geometry": {"coordinates":[-75.007302,40.159318],"type":"Point"}
}