{
  "type": "Feature",
  "properties": {
    "iso:country":"US",
    "sg:address":"10 W Broad St",
    "sg:city":"Tamaqua",
    "sg:classifiers":[
        {
            "category":"Home & Garden",
            "subcategory":"Hardware",
            "type":"Retail Goods"
        }
    ],
    "sg:phone":"+1   ",
    "sg:postcode":"18252",
    "sg:province":"PA",
    "sg:tags":[
        "sales"
    ],
    "wof:name":"M&S Hardware",
    "wof:placetype":"venue"
},
  "geometry": {"coordinates":[-75.969627,40.797334],"type":"Point"}
}