{
  "type": "Feature",
  "properties": {
    "addr:full":"373 Shady Ln Huntingdon Valley PA 19006",
    "addr:housenumber":"373",
    "addr:postcode":"19006",
    "addr:street":"Shady Ln",
    "iso:country":"US",
    "sg:address":"373 Shady Ln",
    "sg:city":"Huntingdon Valley",
    "sg:classifiers":[
        {
            "category":"Freight",
            "type":"Transportation"
        }
    ],
    "sg:phone":"+1   ",
    "sg:postcode":"19006",
    "sg:province":"PA",
    "sg:tags":[
        "operator",
        "local",
        "trucking"
    ],
    "wof:name":"Oneill Trucking",
    "wof:placetype":"venue"
},
  "geometry": {"coordinates":[-75.09074099999999,40.085907],"type":"Point"}
}