{
  "type": "Feature",
  "properties": {
    "addr:full":"6 E Simpson St Mechanicsburg PA 17055",
    "addr:housenumber":"6",
    "addr:postcode":"17055",
    "addr:street":"E Simpson St",
    "iso:country":"US",
    "sg:address":"6 E Simpson St",
    "sg:city":"Mechanicsburg",
    "sg:classifiers":[
        {
            "category":"Shopping",
            "subcategory":"Clothing, Apparel, & Fashions",
            "type":"Retail Goods"
        }
    ],
    "sg:phone":"+1   ",
    "sg:postcode":"17055",
    "sg:province":"PA",
    "sg:tags":[
        "t"
    ],
    "wof:name":"Greggs Novelty T-Shirts",
    "wof:placetype":"venue"
},
  "geometry": {"coordinates":[-77.00496699999999,40.211752],"type":"Point"}
}