{
  "type": "Feature",
  "properties": {
    "iso:country":"US",
    "sg:address":"2606 Brownsville Rd",
    "sg:city":"Pittsburgh",
    "sg:classifiers":[
        {
            "category":"Manufacturing",
            "subcategory":"Textiles",
            "type":"Manufacturing & Wholesale Goods"
        },
        {
            "category":"Manufacturing",
            "subcategory":"Printing",
            "type":"Manufacturing & Wholesale Goods"
        }
    ],
    "sg:phone":"+1 412 881 4114",
    "sg:postcode":"15227",
    "sg:province":"PA",
    "sg:tags":[
        "on",
        "screen",
        "fabric"
    ],
    "wof:name":"All Adds Up",
    "wof:placetype":"venue"
},
  "geometry": {"coordinates":[-79.977981,40.384508],"type":"Point"}
}