{
  "type": "Feature",
  "properties": {
    "iso:country":"US",
    "sg:address":"301 W Chester Pike",
    "sg:city":"Havertown",
    "sg:classifiers":[
        {
            "category":"Health Services",
            "subcategory":"Doctor",
            "type":"Services"
        }
    ],
    "sg:phone":"+1 610 446 8003",
    "sg:postcode":"19083",
    "sg:province":"PA",
    "sg:tags":[
        "physician",
        "surgeon"
    ],
    "wof:name":"Facial Plastic Surgery",
    "wof:placetype":"venue"
},
  "geometry": {"coordinates":[-75.30237700000001,39.96997],"type":"Point"}
}