{
  "type": "Feature",
  "properties": {
    "iso:country":"US",
    "sg:address":"650 S Enola Rd",
    "sg:city":"Enola",
    "sg:classifiers":[
        {
            "category":"Manufacturing",
            "subcategory":"Signs",
            "type":"Manufacturing & Wholesale Goods"
        }
    ],
    "sg:phone":"+1 717 732 8900",
    "sg:postcode":"17025",
    "sg:province":"PA",
    "wof:name":"Penn Sign Co",
    "wof:placetype":"venue"
},
  "geometry": {"coordinates":[-76.92400600000001,40.279151],"type":"Point"}
}