{
  "type": "Feature",
  "properties": {
    "iso:country":"US",
    "sg:address":"4415 Chestnut St",
    "sg:city":"Philadelphia",
    "sg:classifiers":[
        {
            "category":"Banks & Credit Unions",
            "subcategory":"Bank",
            "type":"Services"
        }
    ],
    "sg:phone":"+1 215 222 6602",
    "sg:postcode":"19104",
    "sg:province":"PA",
    "sg:tags":[
        "loan",
        "real estate"
    ],
    "wof:name":"Carteret Mortgage Corp",
    "wof:placetype":"venue"
},
  "geometry": {"coordinates":[-75.211167,39.956805],"type":"Point"}
}