{
  "type": "Feature",
  "properties": {
    "iso:country":"US",
    "sg:address":"4307 N 8th St",
    "sg:city":"Philadelphia",
    "sg:classifiers":[
        {
            "category":"Professional",
            "type":"Services"
        }
    ],
    "sg:phone":"+1   ",
    "sg:postcode":"19140",
    "sg:province":"PA",
    "wof:name":"David E Coit Sr",
    "wof:placetype":"venue"
},
  "geometry": {"coordinates":[-75.139357,40.018654],"type":"Point"}
}