{
  "type": "Feature",
  "properties": {
    "iso:country":"US",
    "sg:address":"1248 N 30th St",
    "sg:city":"Philadelphia",
    "sg:classifiers":[
        {
            "category":"Travel",
            "subcategory":"Travel Agent",
            "type":"Entertainment"
        }
    ],
    "sg:phone":"+1 215 954 2487",
    "sg:postcode":"19121",
    "sg:province":"PA",
    "sg:tags":[
        "agency",
        "services-commercial"
    ],
    "wof:name":"Travel By Mo E Co",
    "wof:placetype":"venue"
},
  "geometry": {"coordinates":[-75.18480700000001,39.976151],"type":"Point"}
}