{
  "type": "Feature",
  "properties": {
    "addr:full":"1012 N Bethlehem Pike Lower Gwynedd PA 19002",
    "addr:housenumber":"1012",
    "addr:postcode":"19002",
    "addr:street":"N Bethlehem Pike",
    "iso:country":"US",
    "sg:address":"1012 N Bethlehem Pike",
    "sg:city":"Lower Gwynedd",
    "sg:classifiers":[
        {
            "category":"Manufacturing",
            "subcategory":"Tools & Machinery",
            "type":"Manufacturing & Wholesale Goods"
        }
    ],
    "sg:phone":"+1 215 540 0820",
    "sg:postcode":"19002",
    "sg:province":"PA",
    "sg:tags":[
        "transmission",
        "power"
    ],
    "wof:name":"Gear & Drive Systems Inc",
    "wof:placetype":"venue"
},
  "geometry": {"coordinates":[-75.227121,40.182594],"type":"Point"}
}