{
  "type": "Feature",
  "properties": {
    "addr:full":"4440 N 4th St Philadelphia PA 19140",
    "addr:housenumber":"4440",
    "addr:postcode":"19140",
    "addr:street":"N 4Th St",
    "iso:country":"US",
    "sg:address":"4440 N 4th St",
    "sg:city":"Philadelphia",
    "sg:classifiers":[
        {
            "category":"Retail",
            "subcategory":"Laundry & Dry Cleaning",
            "type":"Services"
        },
        {
            "category":"Building & Trades",
            "subcategory":"Cleaning & Sanitation",
            "type":"Services"
        }
    ],
    "sg:phone":"+1 215 457 1330",
    "sg:postcode":"19140",
    "sg:province":"PA",
    "sg:tags":[
        "cleaner",
        "house"
    ],
    "wof:name":"C&M Home Repairs & Drain Clean",
    "wof:placetype":"venue"
},
  "geometry": {"coordinates":[-75.13252900000001,40.018491],"type":"Point"}
}