{
  "type": "Feature",
  "properties": {
    "addr:full":"4201 Neshaminy Blvd Bensalem PA 19020",
    "addr:housenumber":"4201",
    "addr:postcode":"19020",
    "addr:street":"Neshaminy Blvd",
    "iso:country":"US",
    "sg:address":"4201 Neshaminy Blvd",
    "sg:city":"Bensalem",
    "sg:classifiers":[
        {
            "category":"Professional",
            "subcategory":"Business Services",
            "type":"Services"
        }
    ],
    "sg:phone":"+1 215 396 9555",
    "sg:postcode":"19020",
    "sg:province":"PA",
    "sg:tags":[
        "license"
    ],
    "wof:name":"Pennsylvania Industries-Blind",
    "wof:placetype":"venue"
},
  "geometry": {"coordinates":[-74.937083,40.144001],"type":"Point"}
}