{
  "type": "Feature",
  "properties": {
    "addr:full":"130 Illig Dr Hookstown PA 15050",
    "addr:housenumber":"130",
    "addr:postcode":"15050",
    "addr:street":"Illig Dr",
    "iso:country":"US",
    "sg:address":"130 Illig Dr",
    "sg:city":"Hookstown",
    "sg:classifiers":[
        {
            "category":"Freight",
            "type":"Transportation"
        }
    ],
    "sg:phone":"+1   ",
    "sg:postcode":"15050",
    "sg:province":"PA",
    "sg:tags":[
        "operator",
        "local",
        "trucking"
    ],
    "wof:name":"Lydick S Notary Trucking",
    "wof:placetype":"venue"
},
  "geometry": {"coordinates":[-80.450559,40.555473],"type":"Point"}
}