{
  "type": "Feature",
  "properties": {
    "iso:country":"US",
    "sg:address":"5658 Terrace Ave",
    "sg:city":"Bensalem",
    "sg:classifiers":[
        {
            "category":"Building & Trades",
            "subcategory":"Construction",
            "type":"Services"
        }
    ],
    "sg:phone":"+1 215 639 9360",
    "sg:postcode":"19020",
    "sg:province":"PA",
    "sg:tags":[
        "contractor",
        "painting",
        "hanging"
    ],
    "wof:name":"Charles M Interiors",
    "wof:placetype":"venue"
},
  "geometry": {"coordinates":[-74.906386,40.121472],"type":"Point"}
}