{
  "type": "Feature",
  "properties": {
    "addr:full":"324 Erie Ave Renovo PA 17764",
    "addr:housenumber":"324",
    "addr:postcode":"17764",
    "addr:street":"Erie Ave",
    "iso:country":"US",
    "sg:address":"324 Erie Ave",
    "sg:city":"Renovo",
    "sg:classifiers":[
        {
            "category":"Food & Beverages",
            "subcategory":"Liquor & Beverages",
            "type":"Retail Goods"
        }
    ],
    "sg:phone":"+1   ",
    "sg:postcode":"17764",
    "sg:province":"PA",
    "sg:tags":[
        "alcoholic"
    ],
    "wof:name":"Suts Six Pack",
    "wof:placetype":"venue"
},
  "geometry": {"coordinates":[-77.756338,41.326741],"type":"Point"}
}