{
  "type": "Feature",
  "properties": {
    "addr:full":"304 N Front St Liverpool PA 17045",
    "addr:housenumber":"304",
    "addr:postcode":"17045",
    "addr:street":"N Front St",
    "iso:country":"US",
    "sg:address":"304 N Front St",
    "sg:city":"Liverpool",
    "sg:classifiers":[
        {
            "category":"Restaurant",
            "type":"Food & Drink"
        }
    ],
    "sg:phone":"+1 717 444 3808",
    "sg:postcode":"17045",
    "sg:province":"PA",
    "wof:name":"Karen's Cafe",
    "wof:placetype":"venue"
},
  "geometry": {"coordinates":[-76.987757,40.576095],"type":"Point"}
}