{
  "type": "Feature",
  "properties": {
    "addr:city":"Philadelphia",
    "addr:full":"3304 W Queen Lane Philadelphia, Pa 19129",
    "addr:house_number":"3304",
    "addr:housenumber":"3304",
    "addr:phone":"+1 215-848-8396",
    "addr:postcode":"19129",
    "addr:road":"W Queen Lane",
    "addr:state":"PA",
    "addr:street":"W Queen Ln",
    "iso:country":"US",
    "sg:address":"3304 W Queen Ln",
    "sg:city":"Philadelphia",
    "sg:classifiers":[
        {
            "category":"Landmark",
            "subcategory":"Historic",
            "type":"Public Place"
        }
    ],
    "sg:phone":"+1 215 848 8396",
    "sg:postcode":"19129",
    "sg:province":"PA",
    "sg:tags":[
        "historical"
    ],
    "wof:airports":[
        102529403,
        102530381
    ],
    "wof:name":"East Falls Historical Society",
    "wof:placetype":"venue"
},
  "geometry": {"coordinates":[-75.18782,40.01506],"type":"Point"}
}