{
  "type": "Feature",
  "properties": {
    "addr:full":"3304 W Queen Ln Philadelphia PA 19129",
    "addr:housenumber":"3304",
    "addr:postcode":"19129",
    "addr:street":"W Queen Ln",
    "iso:country":"US",
    "sg:address":"3304 W Queen Ln",
    "sg:city":"Philadelphia",
    "sg:classifiers":[
        {
            "category":"Landmark",
            "subcategory":"Historic",
            "type":"Public Place"
        }
    ],
    "sg:phone":"+1 215 848 8396",
    "sg:postcode":"19129",
    "sg:province":"PA",
    "sg:tags":[
        "historical"
    ],
    "wof:name":"East Falls Historical Society",
    "wof:placetype":"venue"
},
  "geometry": {"coordinates":[-75.18712600000001,40.015835],"type":"Point"}
}