{
  "type": "Feature",
  "properties": {
    "iso:country":"US",
    "sg:address":"525 Wallace Rd",
    "sg:city":"Wexford",
    "sg:classifiers":[
        {
            "category":"Shopping",
            "subcategory":"Antiques",
            "type":"Retail Goods"
        }
    ],
    "sg:phone":"+1 724 935 1990",
    "sg:postcode":"15090",
    "sg:province":"PA",
    "wof:name":"Red Chimney Shoppe",
    "wof:placetype":"venue"
},
  "geometry": {"coordinates":[-80.055496,40.651501],"type":"Point"}
}