{
  "type": "Feature",
  "properties": {
    "iso:country":"US",
    "sg:address":"37 Wabash St",
    "sg:city":"Pittsburgh",
    "sg:classifiers":[
        {
            "category":"Building & Trades",
            "subcategory":"Construction",
            "type":"Services"
        }
    ],
    "sg:phone":"+1 412 921 6444",
    "sg:postcode":"15220",
    "sg:province":"PA",
    "sg:tags":[
        "designer"
    ],
    "wof:name":"Mc Guire Design Group",
    "wof:placetype":"venue"
},
  "geometry": {"coordinates":[-80.03456799999999,40.440755],"type":"Point"}
}