{
  "type": "Feature",
  "properties": {
    "iso:country":"US",
    "sg:address":"318 Colonial Rd",
    "sg:city":"Perkiomenville",
    "sg:classifiers":[
        {
            "category":"Museum",
            "type":"Entertainment"
        }
    ],
    "sg:phone":"+1 610 754 9238",
    "sg:postcode":"18074",
    "sg:province":"PA",
    "sg:tags":[
        "gallery"
    ],
    "wof:name":"Goschenhoppen Historians Inc",
    "wof:placetype":"venue"
},
  "geometry": {"coordinates":[-75.541613,40.292013],"type":"Point"}
}