{
  "type": "Feature",
  "properties": {
    "iso:country":"US",
    "sg:address":"318 W Cunningham St",
    "sg:city":"Butler",
    "sg:classifiers":[
        {
            "category":"Professional",
            "subcategory":"Lawyer & Legal Services",
            "type":"Services"
        }
    ],
    "sg:phone":"+1 724 283 3313",
    "sg:postcode":"16001",
    "sg:province":"PA",
    "sg:tags":[
        "attorney"
    ],
    "wof:name":"J Stevenson Suess",
    "wof:placetype":"venue"
},
  "geometry": {"coordinates":[-79.898714,40.859946],"type":"Point"}
}