{
  "type": "Feature",
  "properties": {
    "iso:country":"US",
    "sg:address":"427 E Ohio St",
    "sg:city":"Pittsburgh",
    "sg:classifiers":[
        {
            "category":"Retail",
            "subcategory":"Repair Shop",
            "type":"Services"
        }
    ],
    "sg:phone":"+1 412 323 0771",
    "sg:postcode":"15212",
    "sg:province":"PA",
    "sg:tags":[
        "equipment",
        "photographic"
    ],
    "wof:name":"Camera Service Of Pittsburgh",
    "wof:placetype":"venue"
},
  "geometry": {"coordinates":[-80.000631,40.453393],"type":"Point"}
}