{
  "type": "Feature",
  "properties": {
    "addr:full":"2052 W State St New Castle PA 16101",
    "addr:housenumber":"2052",
    "addr:postcode":"16101",
    "addr:street":"W State St",
    "iso:country":"US",
    "sg:address":"2052 W State St",
    "sg:city":"New Castle",
    "sg:classifiers":[
        {
            "category":"Banks & Credit Unions",
            "subcategory":"Bank",
            "type":"Services"
        }
    ],
    "sg:phone":"+1 724 657 8860",
    "sg:postcode":"16101",
    "sg:province":"PA",
    "sg:tags":[
        "institution",
        "business"
    ],
    "wof:name":"Equity One Inc",
    "wof:placetype":"venue"
},
  "geometry": {"coordinates":[-80.383751,41.008282],"type":"Point"}
}