{
  "type": "Feature",
  "properties": {
    "addr:full":"514 S 69th St Upper Darby PA 19082",
    "addr:housenumber":"514",
    "addr:postcode":"19082",
    "addr:street":"S 69Th St",
    "iso:country":"US",
    "sg:address":"514 S 69th St",
    "sg:city":"Upper Darby",
    "sg:classifiers":[
        {
            "category":"Restaurant",
            "type":"Food & Drink"
        }
    ],
    "sg:phone":"+1   ",
    "sg:postcode":"19082",
    "sg:province":"PA",
    "sg:tags":[
        "eating"
    ],
    "wof:name":"Pops Barrell Inn",
    "wof:placetype":"venue"
},
  "geometry": {"coordinates":[-75.25635699999999,39.951927],"type":"Point"}
}