{
  "type": "Feature",
  "properties": {
    "addr:full":"450 N Narberth Ave Narberth PA 19072",
    "addr:housenumber":"450",
    "addr:postcode":"19072",
    "addr:street":"N Narberth Ave",
    "iso:country":"US",
    "sg:address":"450 N Narberth Ave",
    "sg:city":"Narberth",
    "sg:classifiers":[
        {
            "category":"Professional",
            "subcategory":"Lawyer & Legal Services",
            "type":"Services"
        }
    ],
    "sg:phone":"+1 610 668 0770",
    "sg:postcode":"19072",
    "sg:province":"PA",
    "wof:name":"Lundy Stuart R Attorney",
    "wof:placetype":"venue"
},
  "geometry": {"coordinates":[-75.262299,40.011799],"type":"Point"}
}