{
  "type": "Feature",
  "properties": {
    "iso:country":"US",
    "sg:address":"398 Maplewood Ave",
    "sg:city":"Ambridge",
    "sg:classifiers":[
        {
            "category":"Health Services",
            "subcategory":"Doctor",
            "type":"Services"
        }
    ],
    "sg:phone":"+1 724 266 1209",
    "sg:postcode":"15003",
    "sg:province":"PA",
    "sg:tags":[
        "dentist"
    ],
    "wof:name":"M A Harris & Assoc",
    "wof:placetype":"venue"
},
  "geometry": {"coordinates":[-80.22496099999999,40.581869],"type":"Point"}
}