{
  "type": "Feature",
  "properties": {
    "iso:country":"US",
    "sg:address":"2000 Lincoln Rd",
    "sg:city":"Pittsburgh",
    "sg:classifiers":[
        {
            "category":"Building & Trades",
            "subcategory":"Construction",
            "type":"Services"
        }
    ],
    "sg:phone":"+1 412 361 4500",
    "sg:postcode":"15235",
    "sg:province":"PA",
    "sg:tags":[
        "industrial",
        "commercial",
        "contractor"
    ],
    "sg:website":"www.jendoco.com",
    "wof:name":"Jendoco Construction Corp",
    "wof:placetype":"venue"
},
  "geometry": {"coordinates":[-79.877571,40.477672],"type":"Point"}
}