{
  "type": "Feature",
  "properties": {
    "iso:country":"US",
    "sg:address":"47 S Bingaman St",
    "sg:city":"Reading",
    "sg:classifiers":[
        {
            "category":"Restaurant",
            "type":"Food & Drink"
        }
    ],
    "sg:phone":"+1 610 406 0126",
    "sg:postcode":"19606",
    "sg:province":"PA",
    "sg:tags":[
        "eating"
    ],
    "wof:name":"Frank & Diannah's Arbor Inn",
    "wof:placetype":"venue"
},
  "geometry": {"coordinates":[-75.872001,40.327519],"type":"Point"}
}