{
  "type": "Feature",
  "properties": {
    "iso:country":"US",
    "sg:address":"1238 Spring Garden St",
    "sg:city":"Philadelphia",
    "sg:classifiers":[
        {
            "category":"Shopping",
            "subcategory":"Beauty & Cosmetics",
            "type":"Retail Goods"
        }
    ],
    "sg:phone":"+1 215 922 6912",
    "sg:postcode":"19123",
    "sg:province":"PA",
    "sg:tags":[
        "supply"
    ],
    "wof:name":"Spring Garden Beauty Center",
    "wof:placetype":"venue"
},
  "geometry": {"coordinates":[-75.159103,39.962002],"type":"Point"}
}