{
  "type": "Feature",
  "properties": {
    "iso:country":"US",
    "sg:address":"2874 Wimbledon Ln",
    "sg:city":"Lancaster",
    "sg:classifiers":[
        {
            "category":"Wholesale",
            "subcategory":"Non-durable Goods",
            "type":"Manufacturing & Wholesale Goods"
        }
    ],
    "sg:phone":"+1 717 898 4797",
    "sg:postcode":"17601",
    "sg:province":"PA",
    "sg:tags":[
        "shop",
        "item",
        "executive",
        "gift",
        "promotional"
    ],
    "sg:website":"http://www.insightideas.com",
    "wof:name":"In Sight",
    "wof:placetype":"venue"
},
  "geometry": {"coordinates":[-76.3862,40.064732],"type":"Point"}
}