{
  "type": "Feature",
  "properties": {
    "iso:country":"US",
    "sg:address":"2000 Chestnut St",
    "sg:city":"Camp Hill",
    "sg:classifiers":[
        {
            "category":"Organizations",
            "subcategory":"Religious Organization",
            "type":"Services"
        }
    ],
    "sg:phone":"+1   ",
    "sg:postcode":"17011",
    "sg:province":"PA",
    "wof:name":"Trinity Lutheran Church",
    "wof:placetype":"venue"
},
  "geometry": {"coordinates":[-76.916735,40.238934],"type":"Point"}
}