{
  "type": "Feature",
  "properties": {
    "iso:country":"US",
    "sg:address":"231 S 24th St",
    "sg:city":"Philadelphia",
    "sg:classifiers":[
        {
            "category":"Restaurant",
            "type":"Food & Drink"
        }
    ],
    "sg:phone":"+1 215 732 8335",
    "sg:postcode":"19103",
    "sg:province":"PA",
    "sg:tags":[
        "breakfast",
        "brunch"
    ],
    "wof:name":"Sandy's Lunch",
    "wof:placetype":"venue"
},
  "geometry": {"coordinates":[-75.179703,39.9501],"type":"Point"}
}