{
  "type": "Feature",
  "properties": {
    "iso:country":"US",
    "sg:address":"28 E 3rd St",
    "sg:city":"Lewistown",
    "sg:classifiers":[
        {
            "category":"Insurance",
            "subcategory":"Insurance Agent",
            "type":"Services"
        }
    ],
    "sg:phone":"+1   ",
    "sg:postcode":"17044",
    "sg:province":"PA",
    "wof:name":"Robert T Richard",
    "wof:placetype":"venue"
},
  "geometry": {"coordinates":[-77.575275,40.598588],"type":"Point"}
}