{
  "type": "Feature",
  "properties": {
    "iso:country":"US",
    "sg:address":"4016 Market St",
    "sg:city":"Philadelphia",
    "sg:classifiers":[
        {
            "category":"Personal",
            "subcategory":"Nail Salon",
            "type":"Services"
        }
    ],
    "sg:phone":"+1 215 387 3792",
    "sg:postcode":"19104",
    "sg:province":"PA",
    "wof:name":"Nancy's Le Nails",
    "wof:placetype":"venue"
},
  "geometry": {"coordinates":[-75.202456,39.957213],"type":"Point"}
}