{
  "type": "Feature",
  "properties": {
    "iso:country":"US",
    "sg:address":"1901 Washington St",
    "sg:city":"Carnegie",
    "sg:classifiers":[
        {
            "category":"Building & Trades",
            "subcategory":"Construction",
            "type":"Services"
        }
    ],
    "sg:phone":"+1 412 787 3816",
    "sg:postcode":"15106",
    "sg:province":"PA",
    "sg:tags":[
        "contractor"
    ],
    "wof:name":"Holzer & Jesko Quality Exteriors",
    "wof:placetype":"venue"
},
  "geometry": {"coordinates":[-80.088089,40.388759],"type":"Point"}
}