{
  "type": "Feature",
  "properties": {
    "iso:country":"US",
    "sg:address":"52 N 8th St",
    "sg:city":"Philadelphia",
    "sg:classifiers":[
        {
            "category":"Personal",
            "subcategory":"Shoe Repair & Shine",
            "type":"Services"
        }
    ],
    "sg:phone":"+1 215 922 8516",
    "sg:postcode":"19107",
    "sg:province":"PA",
    "sg:website":"www.domsshoe.com",
    "wof:name":"Dom's Shoe Service",
    "wof:placetype":"venue"
},
  "geometry": {"coordinates":[-75.153198,39.952202],"type":"Point"}
}