{
  "type": "Feature",
  "properties": {
    "iso:country":"US",
    "sg:address":"61 AND HAZEL AVE",
    "sg:city":"Philadelphia",
    "sg:classifiers":[
        {
            "category":"Place Of Worship",
            "subcategory":"Church",
            "type":"Public Place"
        },
        {
            "category":"Place Of Worship",
            "type":"Public Place"
        }
    ],
    "sg:phone":"+1 215 747 2605",
    "sg:postcode":"19143",
    "sg:province":"PA",
    "sg:tags":[
        "churches-episcopal-anglican",
        "churches-episcopal"
    ],
    "wof:name":"St George St Barnabas Episcopal Church",
    "wof:placetype":"venue"
},
  "geometry": {"coordinates":[-75.214462,39.935509],"type":"Point"}
}