{
  "type": "Feature",
  "properties": {
    "addr:full":"870 N 28th St Philadelphia PA 19130",
    "addr:housenumber":"870",
    "addr:postcode":"19130",
    "addr:street":"N 28Th St",
    "iso:country":"US",
    "sg:address":"870 N 28th St",
    "sg:city":"Philadelphia",
    "sg:classifiers":[
        {
            "category":"Wholesale",
            "subcategory":"Hardware",
            "type":"Manufacturing & Wholesale Goods"
        }
    ],
    "sg:phone":"+1 215 235 0975",
    "sg:postcode":"19130",
    "sg:province":"PA",
    "sg:tags":[
        "plumbing",
        "fixture",
        "supply"
    ],
    "wof:name":"M E Levitt Assoc",
    "wof:placetype":"venue"
},
  "geometry": {"coordinates":[-75.182315,39.972455],"type":"Point"}
}