{
  "type": "Feature",
  "properties": {
    "addr:full":"1650 Market St Philadelphia PA 19103",
    "addr:housenumber":"1650",
    "addr:postcode":"19103",
    "addr:street":"Market St",
    "iso:country":"US",
    "sg:address":"1650 Market St",
    "sg:city":"Philadelphia",
    "sg:classifiers":[
        {
            "category":"Professional",
            "type":"Services"
        }
    ],
    "sg:phone":"+1 215 419 6090",
    "sg:postcode":"19103",
    "sg:province":"PA",
    "sg:tags":[
        "establishment"
    ],
    "wof:name":"Philadelphia International",
    "wof:placetype":"venue"
},
  "geometry": {"coordinates":[-75.167835,39.9528],"type":"Point"}
}