{
  "type": "Feature",
  "properties": {
    "iso:country":"US",
    "sg:address":"3940 Nebraska Ave",
    "sg:city":"Levittown",
    "sg:phone":"+1   ",
    "sg:postcode":"19056",
    "sg:province":"PA",
    "sg:tags":[
        "installation",
        "commercial",
        "sales",
        "equipment"
    ],
    "wof:name":"Beverage & Eqp Svc Technicians",
    "wof:placetype":"venue"
},
  "geometry": {"coordinates":[-74.891622,40.128049],"type":"Point"}
}