{
  "type": "Feature",
  "properties": {
    "iso:country":"US",
    "sg:address":"108 W Country Barn Rd",
    "sg:city":"Houston",
    "sg:classifiers":[
        {
            "category":"Wholesale",
            "subcategory":"Machinery & Supplies",
            "type":"Manufacturing & Wholesale Goods"
        }
    ],
    "sg:phone":"+1   ",
    "sg:postcode":"15342",
    "sg:province":"PA",
    "sg:tags":[
        "packing",
        "industrial"
    ],
    "wof:name":"Chartiers Industries",
    "wof:placetype":"venue"
},
  "geometry": {"coordinates":[-80.236429,40.23487],"type":"Point"}
}