{
  "type": "Feature",
  "properties": {
    "addr:full":"140 Betty Jane Ct Pittsburgh PA 15235",
    "addr:housenumber":"140",
    "addr:postcode":"15235",
    "addr:street":"Betty Jane Ct",
    "iso:country":"US",
    "sg:address":"140 Betty Jane Ct",
    "sg:city":"Pittsburgh",
    "sg:classifiers":[
        {
            "category":"Retail",
            "subcategory":"Laundry & Dry Cleaning",
            "type":"Services"
        }
    ],
    "sg:phone":"+1 412 371 5424",
    "sg:postcode":"15235",
    "sg:province":"PA",
    "sg:tags":[
        "cleaners",
        "rug",
        "carpet"
    ],
    "wof:name":"Carpet Essentials",
    "wof:placetype":"venue"
},
  "geometry": {"coordinates":[-79.844694,40.470979],"type":"Point"}
}