{
  "type": "Feature",
  "properties": {
    "iso:country":"US",
    "sg:address":"415 Pine St",
    "sg:city":"Renovo",
    "sg:classifiers":[
        {
            "category":"Social Services",
            "type":"Services"
        }
    ],
    "sg:phone":"+1   ",
    "sg:postcode":"17764",
    "sg:province":"PA",
    "wof:name":"Step Inc",
    "wof:placetype":"venue"
},
  "geometry": {"coordinates":[-77.743655,41.325043],"type":"Point"}
}