{
  "type": "Feature",
  "properties": {
    "iso:country":"US",
    "sg:address":"617 S Ruby St",
    "sg:city":"Derry",
    "sg:classifiers":[
        {
            "category":"Retail",
            "subcategory":"Auto Repair",
            "type":"Services"
        }
    ],
    "sg:phone":"+1 724 694 8334",
    "sg:postcode":"15627",
    "sg:province":"PA",
    "sg:tags":[
        "repairing",
        "automobile"
    ],
    "wof:name":"Geary's Auto Svc",
    "wof:placetype":"venue"
},
  "geometry": {"coordinates":[-79.304519,40.321668],"type":"Point"}
}