{
  "type": "Feature",
  "properties": {
    "iso:country":"US",
    "sg:address":"549 Adams Ave",
    "sg:city":"Philadelphia",
    "sg:classifiers":[
        {
            "category":"Shopping",
            "subcategory":"Jewelry",
            "type":"Retail Goods"
        }
    ],
    "sg:phone":"+1 215 722 7890",
    "sg:postcode":"19120",
    "sg:province":"PA",
    "wof:name":"Castor Jewelers",
    "wof:placetype":"venue"
},
  "geometry": {"coordinates":[-75.10863000000001,40.036603],"type":"Point"}
}