{
  "type": "Feature",
  "properties": {
    "iso:country":"US",
    "sg:address":"1290 Maple St",
    "sg:city":"Glenwillard",
    "sg:classifiers":[
        {
            "category":"Marine",
            "type":"Transportation"
        }
    ],
    "sg:phone":"+1   ",
    "sg:postcode":"15001",
    "sg:province":"PA",
    "sg:tags":[
        "scrap",
        "salvaging"
    ],
    "wof:name":"River Salvage Company Inc",
    "wof:placetype":"venue"
},
  "geometry": {"coordinates":[-80.227395,40.5653],"type":"Point"}
}