{
  "type": "Feature",
  "properties": {
    "iso:country":"US",
    "sg:address":"321 W Douglasville Rd",
    "sg:city":"Nazareth",
    "sg:classifiers":[
        {
            "category":"Building & Trades",
            "subcategory":"Construction",
            "type":"Services"
        }
    ],
    "sg:phone":"+1   ",
    "sg:postcode":"18064",
    "sg:province":"PA",
    "sg:tags":[
        "home",
        "remodeling"
    ],
    "wof:name":"Greg S Custom Remodeling",
    "wof:placetype":"venue"
},
  "geometry": {"coordinates":[-75.33411700000001,40.774017],"type":"Point"}
}