{
  "type": "Feature",
  "properties": {
    "iso:country":"US",
    "sg:address":"432 Maplewood Ave",
    "sg:city":"Ambridge",
    "sg:classifiers":[
        {
            "category":"Professional",
            "subcategory":"Business Services",
            "type":"Services"
        }
    ],
    "sg:phone":"+1   ",
    "sg:postcode":"15003",
    "sg:province":"PA",
    "sg:tags":[
        "packaging",
        "supply"
    ],
    "wof:name":"Tapemaster Inc",
    "wof:placetype":"venue"
},
  "geometry": {"coordinates":[-80.226737,40.584322],"type":"Point"}
}