{
  "type": "Feature",
  "properties": {
    "addr:full":"13 Ridge Rd Chadds Ford PA 19317",
    "addr:housenumber":"13",
    "addr:postcode":"19317",
    "addr:street":"Ridge Rd",
    "iso:country":"US",
    "sg:address":"13 Ridge Rd",
    "sg:city":"Chadds Ford",
    "sg:classifiers":[
        {
            "category":"Professional",
            "subcategory":"Lawyer & Legal Services",
            "type":"Services"
        }
    ],
    "sg:phone":"+1   ",
    "sg:postcode":"19317",
    "sg:province":"PA",
    "wof:name":"Lonzetta Maria R",
    "wof:placetype":"venue"
},
  "geometry": {"coordinates":[-75.575744,39.839307],"type":"Point"}
}