{
  "type": "Feature",
  "properties": {
    "iso:country":"US",
    "sg:address":"1004 Race St",
    "sg:city":"Philadelphia",
    "sg:classifiers":[
        {
            "category":"Restaurant",
            "type":"Food & Drink"
        }
    ],
    "sg:phone":"+1 215 925 3837",
    "sg:postcode":"19176",
    "sg:province":"PA",
    "sg:tags":[
        "seafood",
        "chinese"
    ],
    "wof:name":"Ken's Seafood Restaurant",
    "wof:placetype":"venue"
},
  "geometry": {"coordinates":[-75.15621,39.9552],"type":"Point"}
}