{
  "type": "Feature",
  "properties": {
    "iso:country":"US",
    "sg:address":"354 Main St",
    "sg:city":"Seanor",
    "sg:classifiers":[
        {
            "category":"Social Services",
            "subcategory":"Child Care",
            "type":"Services"
        }
    ],
    "sg:phone":"+1 814 467 5635",
    "sg:postcode":"15953",
    "sg:province":"PA",
    "wof:name":"Figard's Family Daycare",
    "wof:placetype":"venue"
},
  "geometry": {"coordinates":[-78.892315,40.206913],"type":"Point"}
}