{
  "type": "Feature",
  "properties": {
    "addr:full":"21 N 52nd St Philadelphia PA 19139",
    "addr:housenumber":"21",
    "addr:postcode":"19139",
    "addr:street":"N 52Nd St",
    "iso:country":"US",
    "sg:address":"21 N 52nd St",
    "sg:city":"Philadelphia",
    "sg:classifiers":[
        {
            "category":"Professional",
            "subcategory":"Research",
            "type":"Services"
        }
    ],
    "sg:phone":"+1 215 472 2200",
    "sg:postcode":"19139",
    "sg:province":"PA",
    "sg:tags":[
        "development",
        "laboratories-research",
        "noncommercial"
    ],
    "wof:name":"Masters Rehab",
    "wof:placetype":"venue"
},
  "geometry": {"coordinates":[-75.22478,39.960556],"type":"Point"}
}