{
  "type": "Feature",
  "properties": {
    "iso:country":"US",
    "sg:address":"545 Barclay Dr",
    "sg:city":"Bethlehem",
    "sg:classifiers":[
        {
            "category":"Professional",
            "subcategory":"Research",
            "type":"Services"
        }
    ],
    "sg:phone":"+1 610 867 6501",
    "sg:postcode":"18017",
    "sg:province":"PA",
    "sg:tags":[
        "environmental",
        "ecological"
    ],
    "wof:name":"Terra Technologies",
    "wof:placetype":"venue"
},
  "geometry": {"coordinates":[-75.368816,40.654438],"type":"Point"}
}