{
  "type": "Feature",
  "properties": {
    "addr:full":"2620 Memorial Blvd Connellsville PA 15425",
    "addr:housenumber":"2620",
    "addr:postcode":"15425",
    "addr:street":"Memorial Blvd",
    "iso:country":"US",
    "sg:address":"2620 Memorial Blvd",
    "sg:city":"Connellsville",
    "sg:classifiers":[
        {
            "category":"Shopping",
            "type":"Retail Goods"
        }
    ],
    "sg:phone":"+1 724 626 8908",
    "sg:postcode":"15425",
    "sg:province":"PA",
    "sg:tags":[
        "hearing",
        "equipment",
        "supply",
        "impaired"
    ],
    "wof:name":"Audiologic & Hearing Aid Svc",
    "wof:placetype":"venue"
},
  "geometry": {"coordinates":[-79.56165,40.05535],"type":"Point"}
}