{
  "type": "Feature",
  "properties": {
    "iso:country":"US",
    "sg:address":"701 Wilson St",
    "sg:city":"Chester",
    "sg:classifiers":[
        {
            "category":"Restaurant",
            "type":"Food & Drink"
        }
    ],
    "sg:phone":"+1   ",
    "sg:postcode":"19013",
    "sg:province":"PA",
    "sg:tags":[
        "eating"
    ],
    "wof:name":"Aprils Kitchen",
    "wof:placetype":"venue"
},
  "geometry": {"coordinates":[-75.392129,39.836581],"type":"Point"}
}