{
  "type": "Feature",
  "properties": {
    "iso:country":"US",
    "sg:address":"98 Hardt Hill Rd",
    "sg:city":"Bechtelsville",
    "sg:classifiers":[
        {
            "category":"Building & Trades",
            "subcategory":"Construction",
            "type":"Services"
        }
    ],
    "sg:phone":"+1   ",
    "sg:postcode":"19505",
    "sg:province":"PA",
    "sg:tags":[
        "excavation",
        "contractor"
    ],
    "wof:name":"L&S Contractors",
    "wof:placetype":"venue"
},
  "geometry": {"coordinates":[-75.63276999999999,40.415899],"type":"Point"}
}