{
  "type": "Feature",
  "properties": {
    "addr:full":"141 League St Philadelphia PA 19147",
    "addr:housenumber":"141",
    "addr:postcode":"19147",
    "addr:street":"League St",
    "iso:country":"US",
    "sg:address":"141 League St",
    "sg:city":"Philadelphia",
    "sg:classifiers":[
        {
            "category":"Professional",
            "subcategory":"Art Services",
            "type":"Services"
        }
    ],
    "sg:phone":"+1 215 755 7500",
    "sg:postcode":"19147",
    "sg:province":"PA",
    "sg:tags":[
        "photography",
        "commercial"
    ],
    "sg:website":"www.michaeldavidstudio.com",
    "wof:name":"Michael David Photography",
    "wof:placetype":"venue"
},
  "geometry": {"coordinates":[-75.146682,39.934144],"type":"Point"}
}