{
  "type": "Feature",
  "properties": {
    "iso:country":"US",
    "sg:address":"2711 Ellwood Rd",
    "sg:city":"New Castle",
    "sg:classifiers":[
        {
            "category":"Sports & Exercise",
            "subcategory":"Golf",
            "type":"Entertainment"
        }
    ],
    "sg:phone":"+1 724 658 8021",
    "sg:postcode":"16101",
    "sg:province":"PA",
    "sg:tags":[
        "course",
        "executive",
        "public"
    ],
    "wof:name":"Sylvan Heights Golf Course",
    "wof:placetype":"venue"
},
  "geometry": {"coordinates":[-80.311508,40.968967],"type":"Point"}
}