{
  "type": "Feature",
  "properties": {
    "iso:country":"US",
    "sg:address":"701 Ostrum St",
    "sg:city":"Fountain Hill",
    "sg:classifiers":[
        {
            "category":"Health Services",
            "subcategory":"Doctor",
            "type":"Services"
        }
    ],
    "sg:phone":"+1 610 866 2929",
    "sg:postcode":"18015",
    "sg:province":"PA",
    "sg:tags":[
        "physician",
        "surgeon"
    ],
    "wof:name":"Hillside Obgyn Assoc",
    "wof:placetype":"venue"
},
  "geometry": {"coordinates":[-75.392606,40.60861],"type":"Point"}
}