{
  "type": "Feature",
  "properties": {
    "iso:country":"US",
    "sg:address":"1005 Highland Ave",
    "sg:city":"Beaver Falls",
    "sg:classifiers":[
        {
            "category":"Building & Trades",
            "subcategory":"Construction",
            "type":"Services"
        }
    ],
    "sg:phone":"+1 724 846 3346",
    "sg:postcode":"15010",
    "sg:province":"PA",
    "sg:tags":[
        "home",
        "house",
        "improvement"
    ],
    "wof:name":"Manipole Frank K Improvements",
    "wof:placetype":"venue"
},
  "geometry": {"coordinates":[-80.337648,40.750528],"type":"Point"}
}