{
  "type": "Feature",
  "properties": {
    "iso:country":"US",
    "sg:address":"285 Cypress Hill Dr",
    "sg:city":"Pittsburgh",
    "sg:classifiers":[
        {
            "category":"Manufacturing",
            "subcategory":"Printing",
            "type":"Manufacturing & Wholesale Goods"
        }
    ],
    "sg:phone":"+1   ",
    "sg:postcode":"15235",
    "sg:province":"PA",
    "sg:tags":[
        "lithographic",
        "commercial"
    ],
    "wof:name":"Palumbo Printing",
    "wof:placetype":"venue"
},
  "geometry": {"coordinates":[-79.784194,40.48092],"type":"Point"}
}