{
  "type": "Feature",
  "properties": {
    "addr:full":"48 Country Ln Royersford PA 19465",
    "addr:housenumber":"48",
    "addr:postcode":"19465",
    "addr:street":"Country Ln",
    "iso:country":"US",
    "sg:address":"48 Country Ln",
    "sg:city":"Royersford",
    "sg:classifiers":[
        {
            "category":"Shopping",
            "subcategory":"Bicycles & Sporting Goods",
            "type":"Retail Goods"
        }
    ],
    "sg:phone":"+1 610 948 8770",
    "sg:postcode":"19465",
    "sg:province":"PA",
    "sg:tags":[
        "equipment",
        "golf",
        "supply"
    ],
    "sg:website":"www.sscc.org",
    "wof:name":"Tony De Gisi Golf Shop",
    "wof:placetype":"venue"
},
  "geometry": {"coordinates":[-75.62846999999999,40.220118],"type":"Point"}
}