{
  "type": "Feature",
  "properties": {
    "addr:full":"2380 W Bakersville Edie Rd Somerset PA 15501",
    "addr:housenumber":"2380",
    "addr:postcode":"15501",
    "addr:street":"W Bakersville Edie Rd",
    "iso:country":"US",
    "sg:address":"2380 W Bakersville Edie Rd",
    "sg:city":"Somerset",
    "sg:classifiers":[
        {
            "category":"Food & Beverages",
            "subcategory":"Groceries & Convenience Stores",
            "type":"Retail Goods"
        }
    ],
    "sg:phone":"+1 814 445 4896",
    "sg:postcode":"15501",
    "sg:province":"PA",
    "wof:name":"Cogo's",
    "wof:placetype":"venue"
},
  "geometry": {"coordinates":[-79.21347799999999,40.035006],"type":"Point"}
}