{
  "type": "Feature",
  "properties": {
    "addr:full":"584 Centerville Rd Landisville PA 17557",
    "addr:housenumber":"584",
    "addr:postcode":"17557",
    "addr:street":"Centerville Rd",
    "iso:country":"US",
    "sg:address":"584 Centerville Rd",
    "sg:city":"Landisville",
    "sg:classifiers":[
        {
            "category":"Building & Trades",
            "subcategory":"Plumbing",
            "type":"Services"
        }
    ],
    "sg:phone":"+1   ",
    "sg:postcode":"17557",
    "sg:province":"PA",
    "sg:tags":[
        "contractor"
    ],
    "wof:name":"Blockbuster",
    "wof:placetype":"venue"
},
  "geometry": {"coordinates":[-76.079527,40.160077],"type":"Point"}
}