{
  "type": "Feature",
  "properties": {
    "iso:country":"US",
    "sg:address":"3306 Allendale St",
    "sg:city":"Pittsburgh",
    "sg:classifiers":[
        {
            "category":"Building & Trades",
            "subcategory":"Landscaping Services",
            "type":"Services"
        }
    ],
    "sg:phone":"+1   ",
    "sg:postcode":"15204",
    "sg:province":"PA",
    "wof:name":"Maust Lawn Care & Landscaping",
    "wof:placetype":"venue"
},
  "geometry": {"coordinates":[-80.06258699999999,40.456818],"type":"Point"}
}