{
  "type": "Feature",
  "properties": {
    "iso:country":"US",
    "sg:address":"2960 Clymer Ave",
    "sg:city":"Telford",
    "sg:classifiers":[
        {
            "category":"Autos & Motor Vehicles",
            "subcategory":"Auto Supplies",
            "type":"Retail Goods"
        }
    ],
    "sg:phone":"+1 215 723 1824",
    "sg:postcode":"18969",
    "sg:province":"PA",
    "wof:name":"Bux Mont Air Inc",
    "wof:placetype":"venue"
},
  "geometry": {"coordinates":[-75.33053200000001,40.342262],"type":"Point"}
}