{
  "type": "Feature",
  "properties": {
    "iso:country":"US",
    "sg:address":"117 Oak Ln",
    "sg:city":"Beaver Falls",
    "sg:classifiers":[
        {
            "category":"Freight",
            "type":"Transportation"
        }
    ],
    "sg:phone":"+1   ",
    "sg:postcode":"15010",
    "sg:province":"PA",
    "sg:tags":[
        "trucking"
    ],
    "wof:name":"Walter Miller Trucking",
    "wof:placetype":"venue"
},
  "geometry": {"coordinates":[-80.305396,40.796646],"type":"Point"}
}