{
  "type": "Feature",
  "properties": {
    "iso:country":"US",
    "sg:address":"14 W 4th St",
    "sg:city":"Bethlehem",
    "sg:classifiers":[
        {
            "category":"Shopping",
            "subcategory":"Bicycles & Sporting Goods",
            "type":"Retail Goods"
        }
    ],
    "sg:phone":"+1 610 866 0540",
    "sg:postcode":"18015",
    "sg:province":"PA",
    "sg:website":"www.Homebase610.com",
    "wof:name":"Homebase Skateshop",
    "wof:placetype":"venue"
},
  "geometry": {"coordinates":[-75.378987,40.610441],"type":"Point"}
}