{
  "type": "Feature",
  "properties": {
    "iso:country":"US",
    "sg:address":"488 Main St",
    "sg:city":"Harleysville",
    "sg:classifiers":[
        {
            "category":"Restaurant",
            "type":"Food & Drink"
        }
    ],
    "sg:menulink":"http://www.allmenus.com/pa/lower-salford/133742-subway/menu/",
    "sg:phone":"+1 215 256 6040",
    "sg:postcode":"19438",
    "sg:province":"PA",
    "sg:tags":[
        "american",
        "sandwich"
    ],
    "wof:name":"Subway",
    "wof:placetype":"venue"
},
  "geometry": {"coordinates":[-75.387066,40.279121],"type":"Point"}
}