{
  "type": "Feature",
  "properties": {
    "addr:full":"126 N Main St Wilkes Barre PA 18705",
    "addr:housenumber":"126",
    "addr:postcode":"18705",
    "addr:street":"N Main St",
    "iso:country":"US",
    "sg:address":"126 N Main St",
    "sg:city":"Wilkes Barre",
    "sg:classifiers":[
        {
            "category":"Government",
            "subcategory":"Fire Station",
            "type":"Public Place"
        }
    ],
    "sg:phone":"+1   ",
    "sg:postcode":"18705",
    "sg:province":"PA",
    "sg:tags":[
        "firefighting"
    ],
    "wof:name":"Plains Township Fire Dept",
    "wof:placetype":"venue"
},
  "geometry": {"coordinates":[-75.848912,41.277386],"type":"Point"}
}