{
  "type": "Feature",
  "properties": {
    "iso:country":"US",
    "sg:address":"27 S Lansdowne Ave",
    "sg:city":"Lansdowne",
    "sg:classifiers":[
        {
            "category":"Professional",
            "subcategory":"Accounting & Tax Preparation",
            "type":"Services"
        }
    ],
    "sg:phone":"+1 610 824 5315",
    "sg:postcode":"19050",
    "sg:province":"PA",
    "sg:tags":[
        "return",
        "filing"
    ],
    "wof:name":"Heinly & Assoc Inc",
    "wof:placetype":"venue"
},
  "geometry": {"coordinates":[-75.272109,39.937212],"type":"Point"}
}