{
  "type": "Feature",
  "properties": {
    "iso:country":"US",
    "sg:address":"4385 Kaby St",
    "sg:city":"Harrisburg",
    "sg:classifiers":[
        {
            "category":"Building & Trades",
            "subcategory":"Construction",
            "type":"Services"
        }
    ],
    "sg:phone":"+1   ",
    "sg:postcode":"17110",
    "sg:province":"PA",
    "wof:name":"Trumbull Corporation",
    "wof:placetype":"venue"
},
  "geometry": {"coordinates":[-76.895135,40.324432],"type":"Point"}
}