{
  "type": "Feature",
  "properties": {
    "iso:country":"US",
    "sg:address":"2013 S 20th St",
    "sg:city":"Philadelphia",
    "sg:classifiers":[
        {
            "category":"Retail",
            "subcategory":"Auto Repair",
            "type":"Services"
        }
    ],
    "sg:phone":"+1 215 465 2396",
    "sg:postcode":"19145",
    "sg:province":"PA",
    "wof:name":"Twentieth Century Garage",
    "wof:placetype":"venue"
},
  "geometry": {"coordinates":[-75.17890199999999,39.926701],"type":"Point"}
}