{
  "type": "Feature",
  "properties": {
    "iso:country":"US",
    "sg:address":"24 Hill St",
    "sg:city":"Sayre",
    "sg:classifiers":[
        {
            "category":"Building & Trades",
            "subcategory":"Construction",
            "type":"Services"
        }
    ],
    "sg:phone":"+1   ",
    "sg:postcode":"18840",
    "sg:province":"PA",
    "sg:tags":[
        "carpentry",
        "contractor"
    ],
    "wof:name":"Harrys Construction",
    "wof:placetype":"venue"
},
  "geometry": {"coordinates":[-76.53137599999999,41.994627],"type":"Point"}
}