{
  "type": "Feature",
  "properties": {
    "addr:full":"910 Century Dr Mechanicsburg PA 17055",
    "addr:housenumber":"910",
    "addr:postcode":"17055",
    "addr:street":"Century Dr",
    "iso:country":"US",
    "sg:address":"910 Century Dr",
    "sg:city":"Mechanicsburg",
    "sg:classifiers":[
        {
            "category":"Health Services",
            "subcategory":"Doctor",
            "type":"Services"
        }
    ],
    "sg:phone":"+1 717 506 4720",
    "sg:postcode":"17055",
    "sg:province":"PA",
    "wof:name":"Fahnestock Julienne MD",
    "wof:placetype":"venue"
},
  "geometry": {"coordinates":[-76.964119,40.211069],"type":"Point"}
}