{
  "type": "Feature",
  "properties": {
    "iso:country":"US",
    "sg:address":"633 Mount Royal Blvd",
    "sg:city":"Pittsburgh",
    "sg:classifiers":[
        {
            "category":"Health Services",
            "subcategory":"Chiropractor",
            "type":"Services"
        }
    ],
    "sg:phone":"+1 412 486 6060",
    "sg:postcode":"15223",
    "sg:province":"PA",
    "wof:name":"Acierno Family Chiropractic",
    "wof:placetype":"venue"
},
  "geometry": {"coordinates":[-79.95899900000001,40.513713],"type":"Point"}
}