{
  "type": "Feature",
  "properties": {
    "addr:full":"1523 Orland St Philadelphia PA 19126",
    "addr:housenumber":"1523",
    "addr:postcode":"19126",
    "addr:street":"Orland St",
    "iso:country":"US",
    "sg:address":"1523 Orland St",
    "sg:city":"Philadelphia",
    "sg:classifiers":[
        {
            "category":"Organizations",
            "subcategory":"Religious Organization",
            "type":"Services"
        }
    ],
    "sg:phone":"+1   ",
    "sg:postcode":"19126",
    "sg:province":"PA",
    "sg:tags":[
        "development",
        "group",
        "community",
        "social"
    ],
    "wof:name":"Zoe Fellowship of Churches",
    "wof:placetype":"venue"
},
  "geometry": {"coordinates":[-75.14435899999999,40.054585],"type":"Point"}
}