{
  "type": "Feature",
  "properties": {
    "addr:full":"740 Sansom St Philadelphia PA 19106",
    "addr:housenumber":"740",
    "addr:postcode":"19106",
    "addr:street":"Sansom St",
    "iso:country":"US",
    "sg:address":"740 Sansom St",
    "sg:city":"Philadelphia",
    "sg:classifiers":[
        {
            "category":"Shopping",
            "subcategory":"Jewelry",
            "type":"Retail Goods"
        }
    ],
    "sg:phone":"+1 215 413 2606",
    "sg:postcode":"19106",
    "sg:province":"PA",
    "sg:tags":[
        "diamond"
    ],
    "wof:name":"Thuy",
    "wof:placetype":"venue"
},
  "geometry": {"coordinates":[-75.153594,39.948625],"type":"Point"}
}