{
  "type": "Feature",
  "properties": {
    "iso:country":"US",
    "sg:address":"4054 Chestnut St",
    "sg:city":"Philadelphia",
    "sg:classifiers":[
        {
            "category":"Professional",
            "subcategory":"Lawyer & Legal Services",
            "type":"Services"
        }
    ],
    "sg:phone":"+1   ",
    "sg:postcode":"19104",
    "sg:province":"PA",
    "wof:name":"Daniel E Orr",
    "wof:placetype":"venue"
},
  "geometry": {"coordinates":[-75.204776,39.955867],"type":"Point"}
}