{
  "type": "Feature",
  "properties": {
    "addr:full":"70 W King St Ste B Chambersburg PA 17201",
    "addr:housenumber":"70",
    "addr:postcode":"17201",
    "addr:street":"W King St Ste B",
    "iso:country":"US",
    "sg:address":"70 W King St Ste B",
    "sg:city":"Chambersburg",
    "sg:classifiers":[
        {
            "category":"Professional",
            "subcategory":"Lawyer & Legal Services",
            "type":"Services"
        }
    ],
    "sg:phone":"+1 717 264 9900",
    "sg:postcode":"17201",
    "sg:province":"PA",
    "sg:tags":[
        "plan"
    ],
    "wof:name":"David B Dowling",
    "wof:placetype":"venue"
},
  "geometry": {"coordinates":[-77.662811,39.93932],"type":"Point"}
}