{
  "type": "Feature",
  "properties": {
    "addr:full":"800 S Market St Elizabethtown PA 17022",
    "addr:housenumber":"800",
    "addr:postcode":"17022",
    "addr:street":"S Market St",
    "iso:country":"US",
    "sg:address":"800 S Market St",
    "sg:city":"Elizabethtown",
    "sg:classifiers":[
        {
            "category":"Autos & Motor Vehicles",
            "subcategory":"Auto Supplies",
            "type":"Retail Goods"
        }
    ],
    "sg:phone":"+1 717 361 2587",
    "sg:postcode":"17022",
    "sg:province":"PA",
    "sg:tags":[
        "automobile",
        "parts"
    ],
    "wof:name":"Advance Auto Parts 5978",
    "wof:placetype":"venue"
},
  "geometry": {"coordinates":[-76.598091,40.143788],"type":"Point"}
}