{
  "type": "Feature",
  "properties": {
    "iso:country":"US",
    "sg:address":"95 S 20th St",
    "sg:city":"Pittsburgh",
    "sg:classifiers":[
        {
            "category":"Building & Trades",
            "subcategory":"Plumbing",
            "type":"Services"
        },
        {
            "category":"Building & Trades",
            "subcategory":"Construction",
            "type":"Services"
        },
        {
            "category":"Building & Trades",
            "subcategory":"Cleaning & Sanitation",
            "type":"Services"
        }
    ],
    "sg:phone":"+1 412 431 7455",
    "sg:postcode":"15203",
    "sg:province":"PA",
    "sg:tags":[
        "cleaner",
        "plumber",
        "industrial",
        "repairer",
        "specialty",
        "system",
        "heating",
        "plumbing-drain",
        "contractor",
        "air conditioning",
        "sewer",
        "contractors-commercial"
    ],
    "sg:website":"http://www.southsideplumb.com",
    "wof:name":"South Side Plumbing & Heating Co.",
    "wof:placetype":"venue"
},
  "geometry": {"coordinates":[-79.977631,40.4286],"type":"Point"}
}