{
  "type": "Feature",
  "properties": {
    "iso:country":"US",
    "sg:address":"255 Weirich Ave",
    "sg:city":"Washington",
    "sg:classifiers":[
        {
            "category":"Retail",
            "subcategory":"Auto Repair",
            "type":"Services"
        }
    ],
    "sg:phone":"+1 724 229 5226",
    "sg:postcode":"15301",
    "sg:province":"PA",
    "sg:tags":[
        "body",
        "automotive",
        "shop"
    ],
    "wof:name":"Woodhouse Auto Body",
    "wof:placetype":"venue"
},
  "geometry": {"coordinates":[-80.27351899999999,40.179849],"type":"Point"}
}