{
  "type": "Feature",
  "properties": {
    "addr:full":"444 Kirkland Rd Clymer PA 15728",
    "addr:housenumber":"444",
    "addr:postcode":"15728",
    "addr:street":"Kirkland Rd",
    "iso:country":"US",
    "sg:address":"444 Kirkland Rd",
    "sg:city":"Clymer",
    "sg:classifiers":[
        {
            "category":"Autos & Motor Vehicles",
            "subcategory":"Automobile Sales",
            "type":"Retail Goods"
        }
    ],
    "sg:phone":"+1   ",
    "sg:postcode":"15728",
    "sg:province":"PA",
    "sg:tags":[
        "used"
    ],
    "wof:name":"Torrell Auto Sales",
    "wof:placetype":"venue"
},
  "geometry": {"coordinates":[-79.040442,40.680592],"type":"Point"}
}