{
  "type": "Feature",
  "properties": {
    "addr:full":"109 E Main St Westfield PA 16950",
    "addr:housenumber":"109",
    "addr:postcode":"16950",
    "addr:street":"E Main St",
    "iso:country":"US",
    "sg:address":"109 E Main St",
    "sg:city":"Westfield",
    "sg:classifiers":[
        {
            "category":"Personal",
            "subcategory":"Beauty Salon",
            "type":"Services"
        }
    ],
    "sg:phone":"+1 814 367 5544",
    "sg:postcode":"16950",
    "sg:province":"PA",
    "wof:name":"June Mays Cut-N-Curl",
    "wof:placetype":"venue"
},
  "geometry": {"coordinates":[-77.536085,41.920362],"type":"Point"}
}