{
  "type": "Feature",
  "properties": {
    "iso:country":"US",
    "sg:address":"100 N 20th St Ste 400",
    "sg:city":"Philadelphia",
    "sg:classifiers":[
        {
            "category":"Health Services",
            "subcategory":"Hospital",
            "type":"Services"
        }
    ],
    "sg:phone":"+1 215 241 7991",
    "sg:postcode":"19103",
    "sg:province":"PA",
    "sg:tags":[
        "nurse",
        "registry"
    ],
    "wof:name":"Nanda",
    "wof:placetype":"venue"
},
  "geometry": {"coordinates":[-75.172821,39.955589],"type":"Point"}
}