{
  "type": "Feature",
  "properties": {
    "addr:full":"135 S 18th St Philadelphia PA 19103",
    "addr:housenumber":"135",
    "addr:postcode":"19103",
    "addr:street":"S 18Th St",
    "iso:country":"US",
    "sg:address":"135 S 18th St",
    "sg:city":"Philadelphia",
    "sg:classifiers":[
        {
            "category":"Professional",
            "type":"Services"
        }
    ],
    "sg:phone":"+1 215 557 0733",
    "sg:postcode":"19103",
    "sg:province":"PA",
    "sg:tags":[
        "establishment"
    ],
    "wof:name":"Benjamin Franklin Tercentenary",
    "wof:placetype":"venue"
},
  "geometry": {"coordinates":[-75.17066699999999,39.950131],"type":"Point"}
}