{
  "type": "Feature",
  "properties": {
    "iso:country":"US",
    "sg:address":"392 Faggs Manor Rd",
    "sg:city":"Cochranville",
    "sg:classifiers":[
        {
            "category":"Freight",
            "type":"Transportation"
        }
    ],
    "sg:phone":"+1   ",
    "sg:postcode":"19330",
    "sg:province":"PA",
    "sg:tags":[
        "operator",
        "trucking"
    ],
    "wof:name":"KG Cleaver Trucking",
    "wof:placetype":"venue"
},
  "geometry": {"coordinates":[-75.911225,39.87103],"type":"Point"}
}