{
  "type": "Feature",
  "properties": {
    "iso:country":"US",
    "sg:address":"3300 Frankford Ave",
    "sg:city":"Philadelphia",
    "sg:classifiers":[
        {
            "category":"Retail",
            "subcategory":"Auto Repair",
            "type":"Services"
        }
    ],
    "sg:phone":"+1 215 940 0391",
    "sg:postcode":"19134",
    "sg:province":"PA",
    "sg:tags":[
        "repairing",
        "automobile"
    ],
    "wof:name":"Quaker City Engines",
    "wof:placetype":"venue"
},
  "geometry": {"coordinates":[-75.106201,39.994999],"type":"Point"}
}