{
  "type": "Feature",
  "properties": {
    "iso:country":"US",
    "sg:address":"1328 Johnson Mill Rd",
    "sg:city":"Lewisburg",
    "sg:classifiers":[
        {
            "category":"Retail",
            "subcategory":"Auto Repair",
            "type":"Services"
        }
    ],
    "sg:phone":"+1 570 523 9315",
    "sg:postcode":"17837",
    "sg:province":"PA",
    "sg:tags":[
        "body",
        "painting",
        "repairing",
        "automobile"
    ],
    "wof:name":"Mick's Auto Body",
    "wof:placetype":"venue"
},
  "geometry": {"coordinates":[-76.97044200000001,40.964296],"type":"Point"}
}