{
  "type": "Feature",
  "properties": {
    "addr:full":"202 S 13th St Philadelphia PA 19107",
    "addr:housenumber":"202",
    "addr:postcode":"19107",
    "addr:street":"S 13Th St",
    "iso:country":"US",
    "sg:address":"202 S 13th St",
    "sg:city":"Philadelphia",
    "sg:classifiers":[
        {
            "category":"Restaurant",
            "type":"Food & Drink"
        }
    ],
    "sg:phone":"+1   ",
    "sg:postcode":"19107",
    "sg:province":"PA",
    "sg:tags":[
        "bar"
    ],
    "wof:name":"Woodys",
    "wof:placetype":"venue"
},
  "geometry": {"coordinates":[-75.162239,39.948892],"type":"Point"}
}