{
  "type": "Feature",
  "properties": {
    "iso:country":"US",
    "sg:address":"231 Market St",
    "sg:city":"New Cumberland",
    "sg:classifiers":[
        {
            "category":"Building & Trades",
            "subcategory":"Plumbing",
            "type":"Services"
        },
        {
            "category":"Retail",
            "subcategory":"Repair Shop",
            "type":"Services"
        }
    ],
    "sg:phone":"+1 717 774 4827",
    "sg:postcode":"17070",
    "sg:province":"PA",
    "sg:tags":[
        "water",
        "heater",
        "contractor"
    ],
    "wof:name":"Gingrich's Plumbing & Heating",
    "wof:placetype":"venue"
},
  "geometry": {"coordinates":[-76.863297,40.2271],"type":"Point"}
}