{
  "type": "Feature",
  "properties": {
    "iso:country":"US",
    "sg:address":"352 Bepler Ave",
    "sg:city":"Pittsburgh",
    "sg:classifiers":[
        {
            "category":"Shopping",
            "subcategory":"Gifts & Souvenirs",
            "type":"Retail Goods"
        }
    ],
    "sg:phone":"+1   ",
    "sg:postcode":"15229",
    "sg:province":"PA",
    "wof:name":"Award Winning Baskets",
    "wof:placetype":"venue"
},
  "geometry": {"coordinates":[-80.01153600000001,40.503004],"type":"Point"}
}