{
  "type": "Feature",
  "properties": {
    "iso:country":"US",
    "sg:address":"1315 Walnut St",
    "sg:city":"Philadelphia",
    "sg:classifiers":[
        {
            "category":"Social Services",
            "type":"Services"
        }
    ],
    "sg:phone":"+1 215 482 4700",
    "sg:postcode":"19107",
    "sg:province":"PA",
    "sg:tags":[
        "counselor",
        "marriage",
        "family"
    ],
    "wof:name":"Philip H Friedman PHD",
    "wof:placetype":"venue"
},
  "geometry": {"coordinates":[-75.162576,39.949191],"type":"Point"}
}