{
  "type": "Feature",
  "properties": {
    "addr:full":"1722 Sumneytown Pike Kulpsville PA 19446",
    "addr:housenumber":"1722",
    "addr:postcode":"19446",
    "addr:street":"Sumneytown Pike",
    "iso:country":"US",
    "sg:address":"1722 Sumneytown Pike",
    "sg:city":"Kulpsville",
    "sg:classifiers":[
        {
            "category":"Wholesale",
            "subcategory":"Chemicals & Plastics",
            "type":"Manufacturing & Wholesale Goods"
        }
    ],
    "sg:phone":"+1 215 412 8888",
    "sg:postcode":"19446",
    "sg:province":"PA",
    "sg:tags":[
        "plant"
    ],
    "wof:name":"Olympic Horticultural Products",
    "wof:placetype":"venue"
},
  "geometry": {"coordinates":[-75.340335,40.244896],"type":"Point"}
}