{
  "type": "Feature",
  "properties": {
    "iso:country":"US",
    "sg:address":"7 E Orange St",
    "sg:city":"Shippensburg",
    "sg:classifiers":[
        {
            "category":"Health Services",
            "subcategory":"Hospital",
            "type":"Services"
        }
    ],
    "sg:phone":"+1 717 532 4233",
    "sg:postcode":"17257",
    "sg:province":"PA",
    "sg:tags":[
        "mental"
    ],
    "wof:name":"New Visions Inc",
    "wof:placetype":"venue"
},
  "geometry": {"coordinates":[-77.518818,40.049481],"type":"Point"}
}