{
  "type": "Feature",
  "properties": {
    "iso:country":"US",
    "sg:address":"104 W Blake Ave",
    "sg:city":"Connellsville",
    "sg:classifiers":[
        {
            "category":"Wholesale",
            "subcategory":"Machinery & Supplies",
            "type":"Manufacturing & Wholesale Goods"
        }
    ],
    "sg:phone":"+1 724 626 1311",
    "sg:postcode":"15425",
    "sg:province":"PA",
    "sg:tags":[
        "contractor"
    ],
    "wof:name":"Industrial Tractor Parts Of Pa",
    "wof:placetype":"venue"
},
  "geometry": {"coordinates":[-79.581129,40.035621],"type":"Point"}
}