{
  "type": "Feature",
  "properties": {
    "iso:country":"US",
    "sg:address":"573 Kellers Rd",
    "sg:city":"Quakertown",
    "sg:classifiers":[
        {
            "category":"Building & Trades",
            "subcategory":"Construction",
            "type":"Services"
        }
    ],
    "sg:phone":"+1 610 282 1961",
    "sg:postcode":"18951",
    "sg:province":"PA",
    "sg:tags":[
        "mover",
        "erectors",
        "machinery",
        "mechanical"
    ],
    "wof:name":"King Mechanical Inc",
    "wof:placetype":"venue"
},
  "geometry": {"coordinates":[-75.357361,40.493409],"type":"Point"}
}