{
  "type": "Feature",
  "properties": {
    "iso:country":"US",
    "sg:address":"3 Laurel Cir",
    "sg:city":"Newtown",
    "sg:classifiers":[
        {
            "category":"Building & Trades",
            "subcategory":"Construction",
            "type":"Services"
        }
    ],
    "sg:phone":"+1 215 497 9532",
    "sg:postcode":"18940",
    "sg:province":"PA",
    "sg:tags":[
        "altering",
        "house",
        "remodeling",
        "contractor"
    ],
    "wof:name":"Kese Team Inc",
    "wof:placetype":"venue"
},
  "geometry": {"coordinates":[-74.96453200000001,40.260932],"type":"Point"}
}