{
  "type": "Feature",
  "properties": {
    "addr:full":"2385 W Cheltenham Ave Philadelphia PA 19150",
    "addr:housenumber":"2385",
    "addr:postcode":"19150",
    "addr:street":"W Cheltenham Ave",
    "iso:country":"US",
    "sg:address":"2385 W Cheltenham Ave",
    "sg:city":"Philadelphia",
    "sg:classifiers":[
        {
            "category":"Shopping",
            "subcategory":"Clothing, Apparel, & Fashions",
            "type":"Retail Goods"
        },
        {
            "category":"Wholesale",
            "subcategory":"Apparel",
            "type":"Manufacturing & Wholesale Goods"
        },
        {
            "category":"Shopping",
            "subcategory":"Shoes",
            "type":"Retail Goods"
        }
    ],
    "sg:phone":"+1 215 884 0492",
    "sg:postcode":"19150",
    "sg:province":"PA",
    "sg:tags":[
        "shoes-wholesale",
        "clothing",
        "store",
        "manufacturer"
    ],
    "sg:website":"http://www.genesco.com",
    "wof:name":"Underground Station",
    "wof:placetype":"venue"
},
  "geometry": {"coordinates":[-75.15652300000001,40.07311],"type":"Point"}
}