{
  "type": "Feature",
  "properties": {
    "iso:country":"US",
    "sg:address":"1208 Swan Rd",
    "sg:city":"Atglen",
    "sg:classifiers":[
        {
            "category":"Restaurant",
            "type":"Food & Drink"
        }
    ],
    "sg:phone":"+1   ",
    "sg:postcode":"19310",
    "sg:province":"PA",
    "sg:tags":[
        "shop",
        "ice",
        "cream"
    ],
    "wof:name":"Leola Frizz & Freeze",
    "wof:placetype":"venue"
},
  "geometry": {"coordinates":[-75.968735,39.967431],"type":"Point"}
}