{
  "type": "Feature",
  "properties": {
    "iso:country":"US",
    "sg:address":"8815 Germantown Ave",
    "sg:city":"Philadelphia",
    "sg:classifiers":[
        {
            "category":"Health Services",
            "subcategory":"Doctor",
            "type":"Services"
        }
    ],
    "sg:phone":"+1   ",
    "sg:postcode":"19118",
    "sg:province":"PA",
    "sg:tags":[
        "medical"
    ],
    "wof:name":"Keumsoon Hong MD",
    "wof:placetype":"venue"
},
  "geometry": {"coordinates":[-75.21393999999999,40.07926],"type":"Point"}
}