{
  "type": "Feature",
  "properties": {
    "iso:country":"US",
    "sg:address":"5010 N Franklin St",
    "sg:city":"Philadelphia",
    "sg:classifiers":[
        {
            "category":"Organizations",
            "subcategory":"Religious Organization",
            "type":"Services"
        }
    ],
    "sg:phone":"+1 215 324 3294",
    "sg:postcode":"19120",
    "sg:province":"PA",
    "sg:tags":[
        "clergy"
    ],
    "wof:name":"Blanche D Carr",
    "wof:placetype":"venue"
},
  "geometry": {"coordinates":[-75.13653100000001,40.029192],"type":"Point"}
}