{
  "type": "Feature",
  "properties": {
    "iso:country":"US",
    "sg:address":"1020 Center Ave",
    "sg:city":"Pittsburgh",
    "sg:classifiers":[
        {
            "category":"Health Services",
            "subcategory":"Doctor",
            "type":"Services"
        }
    ],
    "sg:phone":"+1   ",
    "sg:postcode":"15229",
    "sg:province":"PA",
    "sg:tags":[
        "medical"
    ],
    "wof:name":"Donald R Shoenthal MD",
    "wof:placetype":"venue"
},
  "geometry": {"coordinates":[-80.03483199999999,40.5173],"type":"Point"}
}