{
  "type": "Feature",
  "properties": {
    "iso:country":"US",
    "sg:address":"1516 E Woodlawn St",
    "sg:city":"Allentown",
    "sg:classifiers":[
        {
            "category":"Wholesale",
            "subcategory":"Vending Machines",
            "type":"Manufacturing & Wholesale Goods"
        }
    ],
    "sg:phone":"+1 610 433 3800",
    "sg:postcode":"18109",
    "sg:province":"PA",
    "sg:tags":[
        "park",
        "amusement"
    ],
    "wof:name":"Kohas Amusement Vending Co",
    "wof:placetype":"venue"
},
  "geometry": {"coordinates":[-75.433998,40.629799],"type":"Point"}
}