{
  "type": "Feature",
  "properties": {
    "iso:country":"US",
    "sg:address":"140 Applewood Dr",
    "sg:city":"Easton",
    "sg:classifiers":[
        {
            "category":"Retail",
            "subcategory":"Auto Repair",
            "type":"Services"
        }
    ],
    "sg:phone":"+1   ",
    "sg:postcode":"18045",
    "sg:province":"PA",
    "sg:tags":[
        "engine"
    ],
    "wof:name":"Executive Auto Sport Inc",
    "wof:placetype":"venue"
},
  "geometry": {"coordinates":[-75.252225,40.660315],"type":"Point"}
}