{
  "type": "Feature",
  "properties": {
    "iso:country":"US",
    "sg:address":"16808 Shreve Run Rd",
    "sg:city":"Pleasantville",
    "sg:classifiers":[
        {
            "category":"Building & Trades",
            "subcategory":"Construction",
            "type":"Services"
        }
    ],
    "sg:phone":"+1   ",
    "sg:postcode":"16341",
    "sg:province":"PA",
    "sg:tags":[
        "excavation",
        "operator",
        "contractor",
        "local",
        "trucking"
    ],
    "wof:name":"Stewart Robert C",
    "wof:placetype":"venue"
},
  "geometry": {"coordinates":[-79.592938,41.596383],"type":"Point"}
}