{
  "type": "Feature",
  "properties": {
    "iso:country":"US",
    "sg:address":"1704 Walnut St",
    "sg:city":"Philadelphia",
    "sg:classifiers":[
        {
            "category":"Real Estate",
            "subcategory":"Architect",
            "type":"Services"
        }
    ],
    "sg:phone":"+1 215 546 3155",
    "sg:postcode":"19103",
    "sg:province":"PA",
    "wof:name":"Rola Raymond F Architect",
    "wof:placetype":"venue"
},
  "geometry": {"coordinates":[-75.169197,39.949799],"type":"Point"}
}