{
  "type": "Feature",
  "properties": {
    "iso:country":"US",
    "sg:address":"216 Power Ave",
    "sg:city":"Clearfield",
    "sg:classifiers":[
        {
            "category":"Building & Trades",
            "subcategory":"Construction",
            "type":"Services"
        }
    ],
    "sg:phone":"+1 814 765 7730",
    "sg:postcode":"16830",
    "sg:province":"PA",
    "sg:tags":[
        "general",
        "contractor"
    ],
    "wof:name":"Helsel Contracting",
    "wof:placetype":"venue"
},
  "geometry": {"coordinates":[-78.437636,41.017052],"type":"Point"}
}