{
  "type": "Feature",
  "properties": {
    "iso:country":"US",
    "sg:address":"517 Church Ln ",
    "sg:city":"Lansdowne",
    "sg:classifiers":[
        {
            "category":"Restaurant",
            "type":"Food & Drink"
        }
    ],
    "sg:menulink":"http://www.allmenus.com/pa/yeadon/289050-majors-yeadon-market/menu/",
    "sg:phone":"+1 610 622 2234",
    "sg:postcode":"19050",
    "sg:province":"PA",
    "sg:tags":[
        "american"
    ],
    "wof:name":"Major's Yeadon Market",
    "wof:placetype":"venue"
},
  "geometry": {"coordinates":[-75.254637,39.937612],"type":"Point"}
}