{
  "type": "Feature",
  "properties": {
    "addr:full":"506 E Uwchlan Ave Uwchland PA 19425",
    "addr:housenumber":"506",
    "addr:postcode":"19425",
    "addr:street":"E Uwchlan Ave",
    "iso:country":"US",
    "sg:address":"506 E Uwchlan Ave",
    "sg:city":"Uwchland",
    "sg:classifiers":[
        {
            "category":"Wholesale",
            "subcategory":"Construction Materials",
            "type":"Manufacturing & Wholesale Goods"
        }
    ],
    "sg:phone":"+1 610 524 6240",
    "sg:postcode":"19425",
    "sg:province":"PA",
    "sg:tags":[
        "fence"
    ],
    "wof:name":"Lionville Fence Co",
    "wof:placetype":"venue"
},
  "geometry": {"coordinates":[-75.648225,40.065971],"type":"Point"}
}