{
  "type": "Feature",
  "properties": {
    "addr:full":"17 E 9th St Waterford PA 16441",
    "addr:housenumber":"17",
    "addr:postcode":"16441",
    "addr:street":"E 9Th St",
    "iso:country":"US",
    "sg:address":"17 E 9th St",
    "sg:city":"Waterford",
    "sg:classifiers":[
        {
            "category":"Real Estate",
            "subcategory":"Surveying",
            "type":"Services"
        }
    ],
    "sg:phone":"+1 814 796 4094",
    "sg:postcode":"16441",
    "sg:province":"PA",
    "sg:tags":[
        "surveyor",
        "land",
        "engineer"
    ],
    "wof:name":"Mitchell Surveying Inc",
    "wof:placetype":"venue"
},
  "geometry": {"coordinates":[-79.989153,41.95052],"type":"Point"}
}