{
  "type": "Feature",
  "properties": {
    "iso:country":"US",
    "sg:address":"450 Schoonmaker Ave",
    "sg:city":"Monessen",
    "sg:classifiers":[
        {
            "category":"Shopping",
            "subcategory":"Bicycles & Sporting Goods",
            "type":"Retail Goods"
        }
    ],
    "sg:phone":"+1 724 684 6808",
    "sg:postcode":"15062",
    "sg:province":"PA",
    "wof:name":"Fast Boys Sports Collectibles",
    "wof:placetype":"venue"
},
  "geometry": {"coordinates":[-79.885115,40.160817],"type":"Point"}
}