{
  "type": "Feature",
  "properties": {
    "iso:country":"US",
    "sg:address":"6 Milroy St",
    "sg:city":"Pittsburgh",
    "sg:classifiers":[
        {
            "category":"Building & Trades",
            "subcategory":"Cleaning & Sanitation",
            "type":"Services"
        }
    ],
    "sg:phone":"+1   ",
    "sg:postcode":"15214",
    "sg:province":"PA",
    "sg:tags":[
        "maintenance"
    ],
    "wof:name":"Ambassador Cleaning Service",
    "wof:placetype":"venue"
},
  "geometry": {"coordinates":[-80.010661,40.476416],"type":"Point"}
}