{
  "type": "Feature",
  "properties": {
    "iso:country":"US",
    "sg:address":"255 Posey Ln",
    "sg:city":"Red Lion",
    "sg:classifiers":[
        {
            "category":"Building & Trades",
            "subcategory":"Plumbing",
            "type":"Services"
        }
    ],
    "sg:phone":"+1   ",
    "sg:postcode":"17356",
    "sg:province":"PA",
    "sg:tags":[
        "contractor"
    ],
    "wof:name":"Posey Wayne Plumbing",
    "wof:placetype":"venue"
},
  "geometry": {"coordinates":[-76.607147,39.91299],"type":"Point"}
}