{
  "type": "Feature",
  "properties": {
    "addr:full":"25 Laurel St York PA 17404",
    "addr:housenumber":"25",
    "addr:postcode":"17404",
    "addr:street":"Laurel St",
    "iso:country":"US",
    "sg:address":"25 Laurel St",
    "sg:city":"York",
    "sg:classifiers":[
        {
            "category":"Building & Trades",
            "subcategory":"Construction",
            "type":"Services"
        }
    ],
    "sg:phone":"+1   ",
    "sg:postcode":"17404",
    "sg:province":"PA",
    "sg:tags":[
        "house"
    ],
    "wof:name":"Craig W Horowitz",
    "wof:placetype":"venue"
},
  "geometry": {"coordinates":[-76.732716,39.977401],"type":"Point"}
}