{
  "type": "Feature",
  "properties": {
    "iso:country":"US",
    "sg:address":"3 Canterbury Ct",
    "sg:city":"Lititz",
    "sg:classifiers":[
        {
            "category":"Professional",
            "type":"Services"
        }
    ],
    "sg:phone":"+1 717 627 3920",
    "sg:postcode":"17543",
    "sg:province":"PA",
    "wof:name":"Key 2 Training",
    "wof:placetype":"venue"
},
  "geometry": {"coordinates":[-76.28582,40.139178],"type":"Point"}
}