{
  "type": "Feature",
  "properties": {
    "iso:country":"US",
    "sg:address":"1001 Milford St",
    "sg:city":"Easton",
    "sg:classifiers":[
        {
            "category":"Professional",
            "type":"Services"
        }
    ],
    "sg:phone":"+1   ",
    "sg:postcode":"18045",
    "sg:province":"PA",
    "wof:name":"Wayne Mitman",
    "wof:placetype":"venue"
},
  "geometry": {"coordinates":[-75.25369499999999,40.671242],"type":"Point"}
}