{
  "type": "Feature",
  "properties": {
    "iso:country":"US",
    "sg:address":"3111 Banksville Rd",
    "sg:city":"Pittsburgh",
    "sg:classifiers":[
        {
            "category":"Wholesale",
            "subcategory":"Non-durable Goods",
            "type":"Manufacturing & Wholesale Goods"
        }
    ],
    "sg:phone":"+1   ",
    "sg:postcode":"15216",
    "sg:province":"PA",
    "sg:tags":[
        "clothing"
    ],
    "wof:name":"Brideshow",
    "wof:placetype":"venue"
},
  "geometry": {"coordinates":[-80.04435100000001,40.399629],"type":"Point"}
}