{
  "type": "Feature",
  "properties": {
    "addr:full":"7 Pine Tree Dr New Cumberland PA 17070",
    "addr:housenumber":"7",
    "addr:postcode":"17070",
    "addr:street":"Pine Tree Dr",
    "iso:country":"US",
    "sg:address":"7 Pine Tree Dr",
    "sg:city":"New Cumberland",
    "sg:classifiers":[
        {
            "category":"Restaurant",
            "type":"Food & Drink"
        }
    ],
    "sg:phone":"+1   ",
    "sg:postcode":"17070",
    "sg:province":"PA",
    "sg:tags":[
        "eating"
    ],
    "wof:name":"Pulitis Ristorante",
    "wof:placetype":"venue"
},
  "geometry": {"coordinates":[-76.88780199999999,40.203986],"type":"Point"}
}