{
  "type": "Feature",
  "properties": {
    "iso:country":"US",
    "sg:address":"4912 Route 309",
    "sg:city":"Schnecksville",
    "sg:classifiers":[
        {
            "category":"Insurance",
            "subcategory":"Hazard Insurance",
            "type":"Services"
        }
    ],
    "sg:phone":"+1 610 799 3044",
    "sg:postcode":"18078",
    "sg:province":"PA",
    "sg:tags":[
        "commercial",
        "business"
    ],
    "wof:name":"Best's Insurance Agency",
    "wof:placetype":"venue"
},
  "geometry": {"coordinates":[-75.614085,40.673197],"type":"Point"}
}