{
  "type": "Feature",
  "properties": {
    "addr:full":"63 Wilson Rd Scenery Hill PA 15360",
    "addr:housenumber":"63",
    "addr:postcode":"15360",
    "addr:street":"Wilson Rd",
    "iso:country":"US",
    "sg:address":"63 Wilson Rd",
    "sg:city":"Scenery Hill",
    "sg:classifiers":[
        {
            "category":"Wholesale",
            "subcategory":"Books, Periodicals, & Newspapers",
            "type":"Manufacturing & Wholesale Goods"
        }
    ],
    "sg:phone":"+1   ",
    "sg:postcode":"15360",
    "sg:province":"PA",
    "wof:name":"Sweetwater Prod",
    "wof:placetype":"venue"
},
  "geometry": {"coordinates":[-80.078395,40.057975],"type":"Point"}
}