{
  "type": "Feature",
  "properties": {
    "iso:country":"US",
    "sg:address":"4100 Main St Ste 303",
    "sg:city":"Philadelphia",
    "sg:classifiers":[
        {
            "category":"Arts & Performance",
            "subcategory":"Music",
            "type":"Entertainment"
        }
    ],
    "sg:phone":"+1 215 483 6100",
    "sg:postcode":"19127",
    "sg:province":"PA",
    "sg:tags":[
        "band",
        "orchestra"
    ],
    "wof:name":"Ruben, Peter Scott Orchestras",
    "wof:placetype":"venue"
},
  "geometry": {"coordinates":[-75.218277,40.022202],"type":"Point"}
}