{
  "type": "Feature",
  "properties": {
    "addr:full":"118 Maple Ave Milton PA 17847",
    "addr:housenumber":"118",
    "addr:postcode":"17847",
    "addr:street":"Maple Ave",
    "iso:country":"US",
    "sg:address":"118 Maple Ave",
    "sg:city":"Milton",
    "sg:classifiers":[
        {
            "category":"Home & Garden",
            "subcategory":"Household Appliances",
            "type":"Retail Goods"
        }
    ],
    "sg:phone":"+1   ",
    "sg:postcode":"17847",
    "sg:province":"PA",
    "wof:name":"Dans Appliance Service",
    "wof:placetype":"venue"
},
  "geometry": {"coordinates":[-76.851417,41.016816],"type":"Point"}
}