{
  "type": "Feature",
  "properties": {
    "addr:full":"644 N Hanover St Carlisle PA 17013",
    "addr:housenumber":"644",
    "addr:postcode":"17013",
    "addr:street":"N Hanover St",
    "iso:country":"US",
    "sg:address":"644 N Hanover St",
    "sg:city":"Carlisle",
    "sg:classifiers":[
        {
            "category":"Building & Trades",
            "subcategory":"Electrical",
            "type":"Services"
        }
    ],
    "sg:phone":"+1   ",
    "sg:postcode":"17013",
    "sg:province":"PA",
    "sg:tags":[
        "electrical",
        "contractor"
    ],
    "wof:name":"Malavenda Electric Co",
    "wof:placetype":"venue"
},
  "geometry": {"coordinates":[-77.18470000000001,40.208673],"type":"Point"}
}