{
  "type": "Feature",
  "properties": {
    "iso:country":"US",
    "sg:address":"100 High St",
    "sg:city":"Pittsburgh",
    "sg:classifiers":[
        {
            "category":"Utilities",
            "type":"Services"
        }
    ],
    "sg:phone":"+1   ",
    "sg:postcode":"15223",
    "sg:province":"PA",
    "sg:tags":[
        "company",
        "holding"
    ],
    "wof:name":"Inter-Power U S A Inc",
    "wof:placetype":"venue"
},
  "geometry": {"coordinates":[-79.948151,40.49941],"type":"Point"}
}