{
  "type": "Feature",
  "properties": {
    "addr:full":"1180 N Sharpsville Ave Sharon PA 16146",
    "addr:housenumber":"1180",
    "addr:postcode":"16146",
    "addr:street":"N Sharpsville Ave",
    "iso:country":"US",
    "sg:address":"1180 N Sharpsville Ave",
    "sg:city":"Sharon",
    "sg:classifiers":[
        {
            "category":"Personal",
            "subcategory":"Beauty Salon",
            "type":"Services"
        }
    ],
    "sg:phone":"+1 724 342 7554",
    "sg:postcode":"16146",
    "sg:province":"PA",
    "wof:name":"Kat's Place",
    "wof:placetype":"venue"
},
  "geometry": {"coordinates":[-80.50336900000001,41.248553],"type":"Point"}
}