{
  "type": "Feature",
  "properties": {
    "iso:country":"US",
    "sg:address":"3545 Welsh Rd",
    "sg:city":"Philadelphia",
    "sg:classifiers":[
        {
            "category":"Restaurant",
            "type":"Food & Drink"
        }
    ],
    "sg:phone":"+1 215 335 1850",
    "sg:postcode":"19136",
    "sg:province":"PA",
    "sg:tags":[
        "eating"
    ],
    "wof:name":"Guido's Ristorante Italiano",
    "wof:placetype":"venue"
},
  "geometry": {"coordinates":[-75.026179,40.044641],"type":"Point"}
}