{
  "type": "Feature",
  "properties": {
    "iso:country":"US",
    "sg:address":"3478 Old Bethlehem Pike",
    "sg:city":"Coopersburg",
    "sg:classifiers":[
        {
            "category":"Building & Trades",
            "subcategory":"Construction",
            "type":"Services"
        }
    ],
    "sg:phone":"+1   ",
    "sg:postcode":"18036",
    "sg:province":"PA",
    "sg:tags":[
        "contractor"
    ],
    "wof:name":"Complete Drywall Inc",
    "wof:placetype":"venue"
},
  "geometry": {"coordinates":[-75.393553,40.497752],"type":"Point"}
}