{
  "type": "Feature",
  "properties": {
    "iso:country":"US",
    "sg:address":"95 Rose Rd",
    "sg:city":"Saltsburg",
    "sg:classifiers":[
        {
            "category":"Food & Beverages",
            "subcategory":"Fruits & Vegetables",
            "type":"Retail Goods"
        }
    ],
    "sg:phone":"+1   ",
    "sg:postcode":"15681",
    "sg:province":"PA",
    "wof:name":"Olliver Vegetable Farms",
    "wof:placetype":"venue"
},
  "geometry": {"coordinates":[-79.399609,40.517756],"type":"Point"}
}