{
  "type": "Feature",
  "properties": {
    "iso:country":"US",
    "sg:address":"281 Piney Hill Rd",
    "sg:city":"Airville",
    "sg:classifiers":[
        {
            "category":"Building & Trades",
            "subcategory":"Plumbing",
            "type":"Services"
        }
    ],
    "sg:phone":"+1 717 862 3157",
    "sg:postcode":"17302",
    "sg:province":"PA",
    "sg:tags":[
        "plumbing",
        "contractor"
    ],
    "wof:name":"Mike's Mechanical Inc",
    "wof:placetype":"venue"
},
  "geometry": {"coordinates":[-76.427937,39.795769],"type":"Point"}
}