{
  "type": "Feature",
  "properties": {
    "iso:country":"US",
    "sg:address":"4523 Springfield Ave",
    "sg:city":"Philadelphia",
    "sg:classifiers":[
        {
            "category":"Organizations",
            "subcategory":"Religious Organization",
            "type":"Services"
        }
    ],
    "sg:phone":"+1 215 382 1130",
    "sg:postcode":"19143",
    "sg:province":"PA",
    "wof:name":"Vineyard Community Church",
    "wof:placetype":"venue"
},
  "geometry": {"coordinates":[-75.212974,39.948698],"type":"Point"}
}