{
  "type": "Feature",
  "properties": {
    "addr:full":"305 Bryan St Havertown PA 19083",
    "addr:housenumber":"305",
    "addr:postcode":"19083",
    "addr:street":"Bryan St",
    "iso:country":"US",
    "sg:address":"305 Bryan St",
    "sg:city":"Havertown",
    "sg:classifiers":[
        {
            "category":"Education",
            "subcategory":"Special Training",
            "type":"Public Place"
        }
    ],
    "sg:phone":"+1 610 449 6311",
    "sg:postcode":"19083",
    "sg:province":"PA",
    "sg:tags":[
        "tutoring"
    ],
    "sg:website":"www.advancetestreview.com",
    "wof:name":"Advance Test Review",
    "wof:placetype":"venue"
},
  "geometry": {"coordinates":[-75.30412699999999,39.966379],"type":"Point"}
}