{
  "type": "Feature",
  "properties": {
    "addr:full":"1500 Washington Rd Pittsburgh PA 15228",
    "addr:housenumber":"1500",
    "addr:postcode":"15228",
    "addr:street":"Washington Rd",
    "iso:country":"US",
    "sg:address":"1500 Washington Rd",
    "sg:city":"Pittsburgh",
    "sg:classifiers":[
        {
            "category":"Cinema",
            "subcategory":"Movie Theater",
            "type":"Entertainment"
        }
    ],
    "sg:phone":"+1   ",
    "sg:postcode":"15228",
    "sg:province":"PA",
    "wof:name":"Carmike Cinemas",
    "wof:placetype":"venue"
},
  "geometry": {"coordinates":[-80.05036200000001,40.356062],"type":"Point"}
}