{
  "type": "Feature",
  "properties": {
    "iso:country":"US",
    "sg:address":"2535 Heidlersburg Rd",
    "sg:city":"Gettysburg",
    "sg:classifiers":[
        {
            "category":"Freight",
            "type":"Transportation"
        }
    ],
    "sg:phone":"+1 717 528 8038",
    "sg:postcode":"17325",
    "sg:province":"PA",
    "sg:tags":[
        "commercial",
        "storage",
        "general"
    ],
    "wof:name":"Keller's 234 Mini Storage",
    "wof:placetype":"venue"
},
  "geometry": {"coordinates":[-77.15571,39.948635],"type":"Point"}
}