{
  "type": "Feature",
  "properties": {
    "iso:country":"US",
    "sg:address":"233 Thornberry Cir",
    "sg:city":"Pittsburgh",
    "sg:classifiers":[
        {
            "category":"Wholesale",
            "subcategory":"Medical Equipment & Supplies",
            "type":"Manufacturing & Wholesale Goods"
        }
    ],
    "sg:phone":"+1   ",
    "sg:postcode":"15234",
    "sg:province":"PA",
    "wof:name":"Dade Behring Inc",
    "wof:placetype":"venue"
},
  "geometry": {"coordinates":[-80.040189,40.353511],"type":"Point"}
}