{
  "type": "Feature",
  "properties": {
    "addr:full":"2201 E Butler St Philadelphia PA 19137",
    "addr:housenumber":"2201",
    "addr:postcode":"19137",
    "addr:street":"E Butler St",
    "iso:country":"US",
    "sg:address":"2201 E Butler St",
    "sg:city":"Philadelphia",
    "sg:classifiers":[
        {
            "category":"Transit Center",
            "subcategory":"Freight",
            "type":"Transportation"
        },
        {
            "category":"Freight",
            "type":"Transportation"
        }
    ],
    "sg:phone":"+1 215 533 5583",
    "sg:postcode":"19137",
    "sg:province":"PA",
    "sg:tags":[
        "trucking-motor",
        "trucking"
    ],
    "wof:name":"Emt Trucking",
    "wof:placetype":"venue"
},
  "geometry": {"coordinates":[-75.094566,39.99873],"type":"Point"}
}