{
  "type": "Feature",
  "properties": {
    "addr:full":"1165 Valley Forge Rd Wayne PA 19087",
    "addr:housenumber":"1165",
    "addr:postcode":"19087",
    "addr:street":"Valley Forge Rd",
    "iso:country":"US",
    "sg:address":"1165 Valley Forge Rd",
    "sg:city":"Wayne",
    "sg:classifiers":[
        {
            "category":"Autos & Motor Vehicles",
            "subcategory":"Fuel & Gas Station",
            "type":"Retail Goods"
        }
    ],
    "sg:phone":"+1   ",
    "sg:postcode":"19087",
    "sg:province":"PA",
    "sg:tags":[
        "station",
        "gasoline"
    ],
    "wof:name":"Mobil",
    "wof:placetype":"venue"
},
  "geometry": {"coordinates":[-75.43932,40.074779],"type":"Point"}
}