{
  "type": "Feature",
  "properties": {
    "iso:country":"US",
    "sg:address":"80 Hemlock Dr",
    "sg:city":"Southampton",
    "sg:classifiers":[
        {
            "category":"Food & Beverages",
            "subcategory":"Groceries & Convenience Stores",
            "type":"Retail Goods"
        }
    ],
    "sg:phone":"+1   ",
    "sg:postcode":"18966",
    "sg:province":"PA",
    "wof:name":"Larry Feinman",
    "wof:placetype":"venue"
},
  "geometry": {"coordinates":[-74.951127,40.191702],"type":"Point"}
}