{
  "type": "Feature",
  "properties": {
    "iso:country":"US",
    "sg:address":"376 White Ave",
    "sg:city":"Sharon",
    "sg:classifiers":[
        {
            "category":"Professional",
            "subcategory":"Accounting & Tax Preparation",
            "type":"Services"
        }
    ],
    "sg:phone":"+1 724 981 0371",
    "sg:postcode":"16146",
    "sg:province":"OH",
    "sg:tags":[
        "consultant"
    ],
    "wof:name":"Papp Tax Advisory Svc",
    "wof:placetype":"venue"
},
  "geometry": {"coordinates":[-80.487899,41.228539],"type":"Point"}
}