{
  "type": "Feature",
  "properties": {
    "iso:country":"US",
    "sg:address":"2301 Edinboro Rd",
    "sg:city":"Erie",
    "sg:classifiers":[
        {
            "category":"Health Services",
            "subcategory":"Nursing And Care Facility",
            "type":"Services"
        }
    ],
    "sg:phone":"+1 814 860 7100",
    "sg:postcode":"16509",
    "sg:province":"PA",
    "sg:tags":[
        "home",
        "convalescent"
    ],
    "sg:website":"www.springhillerie.org",
    "wof:name":"Forestview Skilled Nursing Ctr",
    "wof:placetype":"venue"
},
  "geometry": {"coordinates":[-80.104882,42.057254],"type":"Point"}
}