{
  "type": "Feature",
  "properties": {
    "iso:country":"US",
    "sg:address":"115 S 19th St",
    "sg:city":"Lebanon",
    "sg:classifiers":[
        {
            "category":"Freight",
            "type":"Transportation"
        }
    ],
    "sg:phone":"+1   ",
    "sg:postcode":"17042",
    "sg:province":"PA",
    "sg:tags":[
        "operator",
        "local",
        "trucking"
    ],
    "wof:name":"Terry L Wolfe Trucking",
    "wof:placetype":"venue"
},
  "geometry": {"coordinates":[-76.443719,40.336383],"type":"Point"}
}