{
  "type": "Feature",
  "properties": {
    "addr:full":"225 W Station Square Dr Pittsburgh PA 15219",
    "addr:housenumber":"225",
    "addr:postcode":"15219",
    "addr:street":"W Station Square Dr",
    "iso:country":"US",
    "sg:address":"225 W Station Square Dr",
    "sg:city":"Pittsburgh",
    "sg:phone":"+1 412 765 3200",
    "sg:postcode":"15219",
    "sg:province":"PA",
    "sg:website":"http://www.kikupittsburgh.net",
    "wof:name":"Kiku Japanese Restaurant",
    "wof:placetype":"venue"
},
  "geometry": {"coordinates":[-80.01339,40.438126],"type":"Point"}
}