{
  "type": "Feature",
  "properties": {
    "addr:full":"7 Hill Rd New Bloomfield PA 17020",
    "addr:housenumber":"7",
    "addr:postcode":"17020",
    "addr:street":"Hill Rd",
    "iso:country":"US",
    "sg:address":"7 Hill Rd",
    "sg:city":"New Bloomfield",
    "sg:phone":"+1   ",
    "sg:postcode":"17020",
    "sg:province":"PA",
    "sg:tags":[
        "farm",
        "corn"
    ],
    "wof:name":"Ray Dillman",
    "wof:placetype":"venue"
},
  "geometry": {"coordinates":[-77.012153,40.357111],"type":"Point"}
}