{
  "type": "Feature",
  "properties": {
    "addr:full":"5253 Church View Rd New Enterprise PA 16664",
    "addr:housenumber":"5253",
    "addr:postcode":"16664",
    "addr:street":"Church View Rd",
    "iso:country":"US",
    "sg:address":"5253 Church View Rd",
    "sg:city":"New Enterprise",
    "sg:classifiers":[
        {
            "category":"Wholesale",
            "subcategory":"Machinery & Supplies",
            "type":"Manufacturing & Wholesale Goods"
        }
    ],
    "sg:phone":"+1 814 766 2102",
    "sg:postcode":"16664",
    "sg:province":"PA",
    "sg:tags":[
        "farm",
        "equipment"
    ],
    "wof:name":"Cove Tractor",
    "wof:placetype":"venue"
},
  "geometry": {"coordinates":[-78.379999,40.161272],"type":"Point"}
}