{
  "type": "Feature",
  "properties": {
    "iso:country":"US",
    "sg:address":"617 N 19th St",
    "sg:city":"Allentown",
    "sg:classifiers":[
        {
            "category":"Restaurant",
            "type":"Food & Drink"
        }
    ],
    "sg:phone":"+1 610 437 5358",
    "sg:postcode":"18104",
    "sg:province":"PA",
    "sg:tags":[
        "lounge",
        "cocktail"
    ],
    "sg:website":"www.theshantyrest.com",
    "wof:name":"Shanty Restaurant The",
    "wof:placetype":"venue"
},
  "geometry": {"coordinates":[-75.500687,40.604531],"type":"Point"}
}