{
  "type": "Feature",
  "properties": {
    "iso:country":"US",
    "sg:address":"1554 State Rte 903",
    "sg:city":"Jim Thorpe",
    "sg:classifiers":[
        {
            "category":"Real Estate",
            "subcategory":"Real Estate Agent",
            "type":"Services"
        }
    ],
    "sg:phone":"+1   ",
    "sg:postcode":"18229",
    "sg:province":"PA",
    "wof:name":"Opus One Ltd",
    "wof:placetype":"venue"
},
  "geometry": {"coordinates":[-75.716385,40.887162],"type":"Point"}
}