{
  "type": "Feature",
  "properties": {
    "iso:country":"US",
    "sg:address":"327 Ferry St",
    "sg:city":"Danville",
    "sg:classifiers":[
        {
            "category":"Social Services",
            "type":"Services"
        }
    ],
    "sg:phone":"+1 570 275 2500",
    "sg:postcode":"17821",
    "sg:province":"PA",
    "sg:tags":[
        "mission"
    ],
    "wof:name":"Good Samaritan Mission Ctr",
    "wof:placetype":"venue"
},
  "geometry": {"coordinates":[-76.616164,40.962196],"type":"Point"}
}