{
  "type": "Feature",
  "properties": {
    "iso:country":"US",
    "sg:address":"221 W Roosevelt Blvd",
    "sg:city":"Philadelphia",
    "sg:classifiers":[
        {
            "category":"Retail",
            "subcategory":"Auto Repair",
            "type":"Services"
        }
    ],
    "sg:phone":"+1 215 324 1990",
    "sg:postcode":"19120",
    "sg:province":"PA",
    "sg:tags":[
        "body",
        "shop"
    ],
    "wof:name":"Rockland Collision Center",
    "wof:placetype":"venue"
},
  "geometry": {"coordinates":[-75.129204,40.024899],"type":"Point"}
}