{
  "type": "Feature",
  "properties": {
    "iso:country":"US",
    "sg:address":"1829 Old York Rd",
    "sg:city":"Abington",
    "sg:classifiers":[
        {
            "category":"Retail",
            "subcategory":"Auto Repair",
            "type":"Services"
        }
    ],
    "sg:phone":"+1   ",
    "sg:postcode":"19001",
    "sg:province":"PA",
    "sg:tags":[
        "general"
    ],
    "wof:name":"Getty Gas N Auto Service",
    "wof:placetype":"venue"
},
  "geometry": {"coordinates":[-75.114119,40.136129],"type":"Point"}
}