{
  "type": "Feature",
  "properties": {
    "iso:country":"US",
    "sg:address":"40 Carpenter Ln",
    "sg:city":"Irwin",
    "sg:classifiers":[
        {
            "category":"Personal",
            "subcategory":"Barber",
            "type":"Services"
        }
    ],
    "sg:phone":"+1   ",
    "sg:postcode":"15642",
    "sg:province":"PA",
    "sg:tags":[
        "shop",
        "beauty"
    ],
    "wof:name":"Hairquarters",
    "wof:placetype":"venue"
},
  "geometry": {"coordinates":[-79.765215,40.345472],"type":"Point"}
}