{
  "type": "Feature",
  "properties": {
    "iso:country":"US",
    "sg:address":"6010 Penn Ave",
    "sg:city":"Stoystown",
    "sg:classifiers":[
        {
            "category":"Farming",
            "subcategory":"Dairy Farm",
            "type":"Manufacturing & Wholesale Goods"
        }
    ],
    "sg:phone":"+1   ",
    "sg:postcode":"15563",
    "sg:province":"PA",
    "wof:name":"Donald Saintclair",
    "wof:placetype":"venue"
},
  "geometry": {"coordinates":[-79.040807,40.116155],"type":"Point"}
}