{
  "type": "Feature",
  "properties": {
    "iso:country":"US",
    "sg:address":"2424 E York St",
    "sg:city":"Philadelphia",
    "sg:classifiers":[
        {
            "category":"Manufacturing",
            "subcategory":"Metals",
            "type":"Manufacturing & Wholesale Goods"
        }
    ],
    "sg:phone":"+1   ",
    "sg:postcode":"19125",
    "sg:province":"PA",
    "sg:tags":[
        "hardware",
        "stampings",
        "mfg"
    ],
    "wof:name":"Holtz Jacob Acquisition Co",
    "wof:placetype":"venue"
},
  "geometry": {"coordinates":[-75.124134,39.977414],"type":"Point"}
}