{
  "type": "Feature",
  "properties": {
    "addr:full":"125 Reeser Hill Rd York Haven PA 17370",
    "addr:housenumber":"125",
    "addr:postcode":"17370",
    "addr:street":"Reeser Hill Rd",
    "iso:country":"US",
    "sg:address":"125 Reeser Hill Rd",
    "sg:city":"York Haven",
    "sg:classifiers":[
        {
            "category":"Autos & Motor Vehicles",
            "subcategory":"Fuel & Gas Station",
            "type":"Retail Goods"
        }
    ],
    "sg:phone":"+1 717 266 1366",
    "sg:postcode":"17370",
    "sg:province":"PA",
    "sg:tags":[
        "oil"
    ],
    "wof:name":"Shell",
    "wof:placetype":"venue"
},
  "geometry": {"coordinates":[-76.74386800000001,40.12049],"type":"Point"}
}