{
  "type": "Feature",
  "properties": {
    "iso:country":"US",
    "sg:address":"40 Grant St",
    "sg:city":"Cokeburg",
    "sg:classifiers":[
        {
            "category":"Food & Beverages",
            "subcategory":"Groceries & Convenience Stores",
            "type":"Retail Goods"
        }
    ],
    "sg:phone":"+1 724 945 6446",
    "sg:postcode":"15324",
    "sg:province":"PA",
    "sg:tags":[
        "grocer"
    ],
    "wof:name":"Berardinelli Grocery",
    "wof:placetype":"venue"
},
  "geometry": {"coordinates":[-80.06661200000001,40.103817],"type":"Point"}
}