{
  "type": "Feature",
  "properties": {
    "iso:country":"US",
    "sg:address":"1500 Morris St",
    "sg:city":"Philadelphia",
    "sg:classifiers":[
        {
            "category":"Wholesale",
            "subcategory":"Fruits & Vegetables",
            "type":"Manufacturing & Wholesale Goods"
        }
    ],
    "sg:phone":"+1 215 463 3625",
    "sg:postcode":"19145",
    "sg:province":"PA",
    "sg:tags":[
        "veggie"
    ],
    "wof:name":"Morris Minimarket",
    "wof:placetype":"venue"
},
  "geometry": {"coordinates":[-75.17040299999999,39.9296],"type":"Point"}
}