{
  "type": "Feature",
  "properties": {
    "addr:full":"87 1st St Millersburg PA 17061",
    "addr:housenumber":"87",
    "addr:postcode":"17061",
    "addr:street":"1St St",
    "iso:country":"US",
    "sg:address":"87 1st St",
    "sg:city":"Millersburg",
    "sg:classifiers":[
        {
            "category":"Home & Garden",
            "subcategory":"Household Appliances",
            "type":"Retail Goods"
        }
    ],
    "sg:phone":"+1 717 692 2024",
    "sg:postcode":"17061",
    "sg:province":"PA",
    "wof:name":"Bolig's Propane Inc",
    "wof:placetype":"venue"
},
  "geometry": {"coordinates":[-76.96160399999999,40.534912],"type":"Point"}
}