{
  "type": "Feature",
  "properties": {
    "iso:country":"US",
    "sg:address":"199 Waterson Rd",
    "sg:city":"Clarion",
    "sg:classifiers":[
        {
            "category":"Farming",
            "subcategory":"Farm",
            "type":"Manufacturing & Wholesale Goods"
        }
    ],
    "sg:phone":"+1   ",
    "sg:postcode":"16214",
    "sg:province":"PA",
    "sg:tags":[
        "crop",
        "general"
    ],
    "wof:name":"Burns Farms II",
    "wof:placetype":"venue"
},
  "geometry": {"coordinates":[-79.32888800000001,41.168286],"type":"Point"}
}