{
  "type": "Feature",
  "properties": {
    "iso:country":"US",
    "sg:address":"8 Pettebone St",
    "sg:city":"Kingston",
    "sg:classifiers":[
        {
            "category":"Manufacturing",
            "subcategory":"Buildings",
            "type":"Manufacturing & Wholesale Goods"
        },
        {
            "category":"Building & Trades",
            "subcategory":"Construction",
            "type":"Services"
        }
    ],
    "sg:phone":"+1 570 760 7108",
    "sg:postcode":"18704",
    "sg:province":"PA",
    "sg:tags":[
        "home",
        "builder",
        "contractor"
    ],
    "wof:name":"Don Rackus Construction",
    "wof:placetype":"venue"
},
  "geometry": {"coordinates":[-75.893479,41.290488],"type":"Point"}
}