{
  "type": "Feature",
  "properties": {
    "addr:full":"1205 Buffalo St Franklin PA 16323",
    "addr:housenumber":"1205",
    "addr:postcode":"16323",
    "addr:street":"Buffalo St",
    "iso:country":"US",
    "sg:address":"1205 Buffalo St",
    "sg:city":"Franklin",
    "sg:classifiers":[
        {
            "category":"Organizations",
            "subcategory":"Community Association",
            "type":"Services"
        }
    ],
    "sg:phone":"+1 814 432 5310",
    "sg:postcode":"16323",
    "sg:province":"PA",
    "sg:tags":[
        "fraternal"
    ],
    "wof:name":"Fraternal Order Of Eagles",
    "wof:placetype":"venue"
},
  "geometry": {"coordinates":[-79.82921399999999,41.396487],"type":"Point"}
}