{
  "type": "Feature",
  "properties": {
    "addr:full":"105 W Sandy Ridge Rd Doylestown PA 18901",
    "addr:housenumber":"105",
    "addr:postcode":"18901",
    "addr:street":"W Sandy Ridge Rd",
    "iso:country":"US",
    "sg:address":"105 W Sandy Ridge Rd",
    "sg:city":"Doylestown",
    "sg:classifiers":[
        {
            "category":"Freight",
            "type":"Transportation"
        }
    ],
    "sg:phone":"+1   ",
    "sg:postcode":"18901",
    "sg:province":"PA",
    "sg:tags":[
        "operator",
        "local",
        "trucking"
    ],
    "wof:name":"Perrines Trucking Inc",
    "wof:placetype":"venue"
},
  "geometry": {"coordinates":[-75.17292399999999,40.304451],"type":"Point"}
}