{
  "type": "Feature",
  "properties": {
    "iso:country":"US",
    "sg:address":"2600 Philmont Ave",
    "sg:city":"Huntingdon Vly",
    "sg:classifiers":[
        {
            "category":"Health Services",
            "subcategory":"Doctor",
            "type":"Services"
        }
    ],
    "sg:phone":"+1 215 947 4910",
    "sg:postcode":"19006",
    "sg:province":"PA",
    "sg:tags":[
        "dentist"
    ],
    "wof:name":"Irving A Kraft DDS",
    "wof:placetype":"venue"
},
  "geometry": {"coordinates":[-75.05150399999999,40.121964],"type":"Point"}
}