{
  "type": "Feature",
  "properties": {
    "iso:country":"US",
    "sg:address":"3337 Kensington Ave",
    "sg:city":"Philadelphia",
    "sg:classifiers":[
        {
            "category":"Building & Trades",
            "subcategory":"Locksmith",
            "type":"Services"
        }
    ],
    "sg:phone":"+1 267 702 1163",
    "sg:postcode":"19134",
    "sg:province":"PA",
    "sg:tags":[
        "key"
    ],
    "wof:name":"All Day All Night Emergency Locksmith",
    "wof:placetype":"venue"
},
  "geometry": {"coordinates":[-75.10978299999999,39.99833],"type":"Point"}
}