{
  "type": "Feature",
  "properties": {
    "addr:full":"773 Durham Rd Newtown PA 18940",
    "addr:housenumber":"773",
    "addr:postcode":"18940",
    "addr:street":"Durham Rd",
    "iso:country":"US",
    "sg:address":"773 Durham Rd",
    "sg:city":"Newtown",
    "sg:classifiers":[
        {
            "category":"Retail",
            "subcategory":"Auto Repair",
            "type":"Services"
        }
    ],
    "sg:phone":"+1 215 598 3251",
    "sg:postcode":"18940",
    "sg:province":"PA",
    "sg:tags":[
        "body",
        "automobile",
        "painting",
        "repairing"
    ],
    "wof:name":"Anchor Auto Service",
    "wof:placetype":"venue"
},
  "geometry": {"coordinates":[-74.93771,40.236094],"type":"Point"}
}