{
  "type": "Feature",
  "properties": {
    "iso:country":"US",
    "sg:address":"114 W Catawissa St",
    "sg:city":"Nesquehoning",
    "sg:classifiers":[
        {
            "category":"Government",
            "subcategory":"Office",
            "type":"Public Place"
        }
    ],
    "sg:phone":"+1   ",
    "sg:postcode":"18240",
    "sg:province":"PA",
    "sg:tags":[
        "executive"
    ],
    "wof:name":"Borough of Nesquehoning",
    "wof:placetype":"venue"
},
  "geometry": {"coordinates":[-75.81319999999999,40.863597],"type":"Point"}
}