{
  "type": "Feature",
  "properties": {
    "iso:country":"US",
    "sg:address":"3147 Library Rd",
    "sg:city":"Pittsburgh",
    "sg:classifiers":[
        {
            "category":"Retail",
            "subcategory":"Repair Shop",
            "type":"Services"
        }
    ],
    "sg:phone":"+1 412 884 4944",
    "sg:postcode":"15234",
    "sg:province":"PA",
    "sg:tags":[
        "television",
        "radio"
    ],
    "wof:name":"J Rudy Assoc",
    "wof:placetype":"venue"
},
  "geometry": {"coordinates":[-80.006868,40.3732],"type":"Point"}
}