{
  "type": "Feature",
  "properties": {
    "iso:country":"US",
    "sg:address":"1844 Ardmore Blvd",
    "sg:city":"Pittsburgh",
    "sg:classifiers":[
        {
            "category":"Professional",
            "subcategory":"Accounting & Tax Preparation",
            "type":"Services"
        }
    ],
    "sg:phone":"+1 412 371 5540",
    "sg:postcode":"15221",
    "sg:province":"PA",
    "sg:tags":[
        "accountant"
    ],
    "wof:name":"Parrotta's Accounting & Tax",
    "wof:placetype":"venue"
},
  "geometry": {"coordinates":[-79.860257,40.425128],"type":"Point"}
}