{
  "type": "Feature",
  "properties": {
    "addr:full":"104 W Wayne St Butler PA 16001",
    "addr:housenumber":"104",
    "addr:postcode":"16001",
    "addr:street":"W Wayne St",
    "iso:country":"US",
    "sg:address":"104 W Wayne St",
    "sg:city":"Butler",
    "sg:classifiers":[
        {
            "category":"Restaurant",
            "type":"Food & Drink"
        }
    ],
    "sg:phone":"+1 724 287 5033",
    "sg:postcode":"16001",
    "sg:province":"PA",
    "wof:name":"Natili Restaurant & Lounge",
    "wof:placetype":"venue"
},
  "geometry": {"coordinates":[-79.896165,40.857144],"type":"Point"}
}