{
  "type": "Feature",
  "properties": {
    "iso:country":"US",
    "sg:address":"4208 Bethlehem Pike",
    "sg:city":"Telford",
    "sg:classifiers":[
        {
            "category":"Professional",
            "subcategory":"Testing Lab",
            "type":"Services"
        }
    ],
    "sg:phone":"+1 215 345 8366",
    "sg:postcode":"18969",
    "sg:province":"PA",
    "sg:tags":[
        "laboratory"
    ],
    "sg:website":"www.analab.com",
    "wof:name":"Analytical Laboratories Inc",
    "wof:placetype":"venue"
},
  "geometry": {"coordinates":[-75.30323199999999,40.327855],"type":"Point"}
}