{
  "type": "Feature",
  "properties": {
    "iso:country":"US",
    "sg:address":"1615 Hill St",
    "sg:city":"Mc Keesport",
    "sg:classifiers":[
        {
            "category":"Restaurant",
            "type":"Food & Drink"
        }
    ],
    "sg:phone":"+1   ",
    "sg:postcode":"15131",
    "sg:province":"PA",
    "sg:tags":[
        "eating"
    ],
    "wof:name":"Stratigos Banquet Center",
    "wof:placetype":"venue"
},
  "geometry": {"coordinates":[-79.810288,40.346993],"type":"Point"}
}