{
  "type": "Feature",
  "properties": {
    "iso:country":"US",
    "sg:address":"1008 Graham Ave",
    "sg:city":"Windber",
    "sg:classifiers":[
        {
            "category":"Wholesale",
            "subcategory":"Medical Equipment & Supplies",
            "type":"Manufacturing & Wholesale Goods"
        }
    ],
    "sg:phone":"+1 814 467 1029",
    "sg:postcode":"15963",
    "sg:province":"PA",
    "sg:tags":[
        "hospital"
    ],
    "wof:name":"Windber Home Medical Supply",
    "wof:placetype":"venue"
},
  "geometry": {"coordinates":[-78.83450999999999,40.238009],"type":"Point"}
}