{
  "type": "Feature",
  "properties": {
    "iso:country":"US",
    "sg:address":"404 S 2nd St",
    "sg:city":"Philadelphia",
    "sg:classifiers":[
        {
            "category":"Shopping",
            "subcategory":"Computers & Home Electronics",
            "type":"Retail Goods"
        }
    ],
    "sg:phone":"+1 215 922 3000",
    "sg:postcode":"19147",
    "sg:province":"PA",
    "sg:website":"www.davidmannaudio.com",
    "wof:name":"David Mann Audio",
    "wof:placetype":"venue"
},
  "geometry": {"coordinates":[-75.145426,39.942985],"type":"Point"}
}