{
  "type": "Feature",
  "properties": {
    "addr:full":"11 Pennsylvania Blvd Monessen PA 15062",
    "addr:housenumber":"11",
    "addr:postcode":"15062",
    "addr:street":"Pennsylvania Blvd",
    "iso:country":"US",
    "sg:address":"11 Pennsylvania Blvd",
    "sg:city":"Monessen",
    "sg:classifiers":[
        {
            "category":"Retail",
            "subcategory":"Portrait Studio",
            "type":"Services"
        }
    ],
    "sg:phone":"+1 724 684 4187",
    "sg:postcode":"15062",
    "sg:province":"PA",
    "sg:tags":[
        "photographer"
    ],
    "wof:name":"Gaudio's Video & Photography",
    "wof:placetype":"venue"
},
  "geometry": {"coordinates":[-79.88428999999999,40.14353],"type":"Point"}
}