{
  "type": "Feature",
  "properties": {
    "iso:country":"US",
    "sg:address":"141 W Somerset St",
    "sg:city":"Philadelphia",
    "sg:classifiers":[
        {
            "category":"Social Services",
            "type":"Services"
        }
    ],
    "sg:phone":"+1   ",
    "sg:postcode":"19133",
    "sg:province":"PA",
    "wof:name":"The Lighthouse Inc",
    "wof:placetype":"venue"
},
  "geometry": {"coordinates":[-75.131891,39.992709],"type":"Point"}
}