{
  "type": "Feature",
  "properties": {
    "iso:country":"US",
    "sg:address":"1613 Brookhaven Rd",
    "sg:city":"Wynnewood",
    "sg:classifiers":[
        {
            "category":"Building & Trades",
            "subcategory":"Construction",
            "type":"Services"
        }
    ],
    "sg:phone":"+1   ",
    "sg:postcode":"19096",
    "sg:province":"PA",
    "sg:tags":[
        "company"
    ],
    "wof:name":"Deangelis Bros Ldscp Cnstr Inc",
    "wof:placetype":"venue"
},
  "geometry": {"coordinates":[-75.281301,39.989077],"type":"Point"}
}