{
  "type": "Feature",
  "properties": {
    "iso:country":"US",
    "sg:address":"1241 Carpenter St",
    "sg:city":"Philadelphia",
    "sg:classifiers":[
        {
            "category":"Retail",
            "subcategory":"Portrait Studio",
            "type":"Services"
        },
        {
            "category":"Professional",
            "subcategory":"Art Services",
            "type":"Services"
        }
    ],
    "sg:phone":"+1 215 774 1234",
    "sg:postcode":"19147",
    "sg:province":"PA",
    "sg:tags":[
        "photographer",
        "photography",
        "store"
    ],
    "sg:website":"www.jasenhudson.com",
    "wof:name":"Jasen Hudson Photography",
    "wof:placetype":"venue"
},
  "geometry": {"coordinates":[-75.16397499999999,39.93882],"type":"Point"}
}