{
  "type": "Feature",
  "properties": {
    "addr:full":"4721 McKnight Rd Pittsburgh PA 15237",
    "addr:housenumber":"4721",
    "addr:postcode":"15237",
    "addr:street":"Mcknight Rd",
    "iso:country":"US",
    "sg:address":"4721 McKnight Rd",
    "sg:city":"Pittsburgh",
    "sg:classifiers":[
        {
            "category":"Health Services",
            "subcategory":"Medical Lab",
            "type":"Services"
        }
    ],
    "sg:phone":"+1 412 630 8890",
    "sg:postcode":"15237",
    "sg:province":"PA",
    "sg:tags":[
        "x"
    ],
    "wof:name":"Sharp Medical Imaging",
    "wof:placetype":"venue"
},
  "geometry": {"coordinates":[-80.009552,40.50457],"type":"Point"}
}