{
  "type": "Feature",
  "properties": {
    "addr:full":"56 Gaylord Ave Plymouth PA 18651",
    "addr:housenumber":"56",
    "addr:postcode":"18651",
    "addr:street":"Gaylord Ave",
    "iso:country":"US",
    "sg:address":"56 Gaylord Ave",
    "sg:city":"Plymouth",
    "sg:classifiers":[
        {
            "category":"Retail",
            "subcategory":"Funeral Services",
            "type":"Services"
        }
    ],
    "sg:phone":"+1 570 779 9614",
    "sg:postcode":"18651",
    "sg:province":"PA",
    "sg:tags":[
        "director"
    ],
    "wof:name":"William A Reese Funeral Chapel",
    "wof:placetype":"venue"
},
  "geometry": {"coordinates":[-75.947874,41.241743],"type":"Point"}
}