{
  "type": "Feature",
  "properties": {
    "iso:country":"US",
    "sg:address":"5200 Admire Rd",
    "sg:city":"Thomasville",
    "sg:classifiers":[
        {
            "category":"Manufacturing",
            "subcategory":"Buildings",
            "type":"Manufacturing & Wholesale Goods"
        },
        {
            "category":"Home & Garden",
            "subcategory":"Building Materials",
            "type":"Retail Goods"
        },
        {
            "category":"Building & Trades",
            "subcategory":"Construction",
            "type":"Services"
        }
    ],
    "sg:phone":"+1 717 292 4109",
    "sg:postcode":"17364",
    "sg:province":"PA",
    "sg:tags":[
        "bathroom",
        "installation",
        "altering",
        "windows-repair",
        "builder",
        "contractor",
        "window",
        "planning",
        "replacement",
        "remodeling",
        "kitchen"
    ],
    "wof:name":"Bortner Home Builders Inc",
    "wof:placetype":"venue"
},
  "geometry": {"coordinates":[-76.919121,39.950748],"type":"Point"}
}