{
  "type": "Feature",
  "properties": {
    "iso:country":"US",
    "sg:address":"4519 Frankford Ave",
    "sg:city":"Philadelphia",
    "sg:classifiers":[
        {
            "category":"Personal",
            "subcategory":"Beauty Salon",
            "type":"Services"
        }
    ],
    "sg:phone":"+1 215 744 0844",
    "sg:postcode":"19124",
    "sg:province":"PA",
    "sg:tags":[
        "shop"
    ],
    "wof:name":"Penny S Hair Designs",
    "wof:placetype":"venue"
},
  "geometry": {"coordinates":[-75.086122,40.013882],"type":"Point"}
}