{
  "type": "Feature",
  "properties": {
    "iso:country":"US",
    "sg:address":"89 Bethlehem Pike",
    "sg:city":"Philadelphia",
    "sg:classifiers":[
        {
            "category":"Professional",
            "subcategory":"Lawyer & Legal Services",
            "type":"Services"
        }
    ],
    "sg:phone":"+1 215 753 1270",
    "sg:postcode":"19118",
    "sg:province":"PA",
    "sg:tags":[
        "attorney"
    ],
    "wof:name":"Corporate Counsel",
    "wof:placetype":"venue"
},
  "geometry": {"coordinates":[-75.20805799999999,40.078217],"type":"Point"}
}