{
  "type": "Feature",
  "properties": {
    "iso:country":"US",
    "sg:address":"1108 Sheller Ave",
    "sg:city":"Chambersburg",
    "sg:classifiers":[
        {
            "category":"Shopping",
            "subcategory":"Clothing, Apparel, & Fashions",
            "type":"Retail Goods"
        }
    ],
    "sg:phone":"+1   ",
    "sg:postcode":"17201",
    "sg:province":"PA",
    "wof:name":"Sandys Bridals Inc",
    "wof:placetype":"venue"
},
  "geometry": {"coordinates":[-77.648045,39.913042],"type":"Point"}
}