{
  "type": "Feature",
  "properties": {
    "addr:full":"752 State Hwy 17C Waverly PA 14892",
    "addr:housenumber":"752",
    "addr:postcode":"14892",
    "addr:street":"State Hwy 17C",
    "iso:country":"US",
    "sg:address":"752 State Hwy 17C",
    "sg:city":"Waverly",
    "sg:classifiers":[
        {
            "category":"Retail",
            "subcategory":"Auto Repair",
            "type":"Services"
        }
    ],
    "sg:phone":"+1 607 565 4090",
    "sg:postcode":"14892",
    "sg:province":"PA",
    "sg:tags":[
        "automobile",
        "inspection"
    ],
    "wof:name":"Hopkins Automotive",
    "wof:placetype":"venue"
},
  "geometry": {"coordinates":[-76.47466799999999,42.009229],"type":"Point"}
}