{
  "type": "Feature",
  "properties": {
    "addr:full":"630 S 4th St Philadelphia PA 19147",
    "addr:housenumber":"630",
    "addr:postcode":"19147",
    "addr:street":"S 4Th St",
    "iso:country":"US",
    "sg:address":"630 S 4th St",
    "sg:city":"Philadelphia",
    "sg:classifiers":[
        {
            "category":"Food & Beverages",
            "subcategory":"Candy",
            "type":"Retail Goods"
        }
    ],
    "sg:phone":"+1 215 923 8800",
    "sg:postcode":"19147",
    "sg:province":"PA",
    "sg:tags":[
        "store"
    ],
    "wof:name":"Sweet Tooth",
    "wof:placetype":"venue"
},
  "geometry": {"coordinates":[-75.149252,39.941379],"type":"Point"}
}