{
  "type": "Feature",
  "properties": {
    "addr:full":"1802 Karakung Dr Ardmore PA 19083",
    "addr:housenumber":"1802",
    "addr:postcode":"19083",
    "addr:street":"Karakung Dr",
    "iso:country":"US",
    "sg:address":"1802 Karakung Dr",
    "sg:city":"Ardmore",
    "sg:classifiers":[
        {
            "category":"Restaurant",
            "type":"Food & Drink"
        }
    ],
    "sg:phone":"+1   ",
    "sg:postcode":"19083",
    "sg:province":"PA",
    "sg:tags":[
        "eating"
    ],
    "wof:name":"Cobbs Creek CAF",
    "wof:placetype":"venue"
},
  "geometry": {"coordinates":[-75.296441,39.992694],"type":"Point"}
}