{
  "type": "Feature",
  "properties": {
    "addr:full":"412 N Main St Red Lion PA 17356",
    "addr:housenumber":"412",
    "addr:postcode":"17356",
    "addr:street":"N Main St",
    "iso:country":"US",
    "sg:address":"412 N Main St",
    "sg:city":"Red Lion",
    "sg:classifiers":[
        {
            "category":"Retail",
            "subcategory":"Portrait Studio",
            "type":"Services"
        }
    ],
    "sg:phone":"+1 717 246 2844",
    "sg:postcode":"17356",
    "sg:province":"PA",
    "sg:tags":[
        "photographer"
    ],
    "sg:website":"www.novastudio.net",
    "wof:name":"Nova Studio",
    "wof:placetype":"venue"
},
  "geometry": {"coordinates":[-76.611851,39.906383],"type":"Point"}
}