{
  "type": "Feature",
  "properties": {
    "iso:country":"US",
    "sg:address":"707 Eagleview Blvd",
    "sg:city":"Exton",
    "sg:classifiers":[
        {
            "category":"Fast Food",
            "type":"Food & Drink"
        },
        {
            "category":"Restaurant",
            "type":"Food & Drink"
        }
    ],
    "sg:phone":"+1 610 458 1900",
    "sg:postcode":"19341",
    "sg:province":"PA",
    "sg:tags":[
        "take"
    ],
    "wof:name":"716 Haywood Drive Associates",
    "wof:placetype":"venue"
},
  "geometry": {"coordinates":[-75.677142,40.066623],"type":"Point"}
}