{
  "type": "Feature",
  "properties": {
    "iso:country":"US",
    "sg:address":"2951 Kanes Rd",
    "sg:city":"Willow Grove",
    "sg:classifiers":[
        {
            "category":"Building & Trades",
            "subcategory":"Landscaping Services",
            "type":"Services"
        }
    ],
    "sg:phone":"+1 215 784 9124",
    "sg:postcode":"19090",
    "sg:province":"PA",
    "sg:tags":[
        "tree"
    ],
    "wof:name":"Bob Mc Grath's Tree Svc",
    "wof:placetype":"venue"
},
  "geometry": {"coordinates":[-75.138971,40.142208],"type":"Point"}
}