{
  "type": "Feature",
  "properties": {
    "iso:country":"US",
    "sg:address":"410 E 21st St",
    "sg:city":"Chester",
    "sg:classifiers":[
        {
            "category":"Professional",
            "subcategory":"Management & Consulting",
            "type":"Services"
        }
    ],
    "sg:phone":"+1 610 872 8401",
    "sg:postcode":"19013",
    "sg:province":"PA",
    "sg:tags":[
        "construction"
    ],
    "wof:name":"Mc Gee Co",
    "wof:placetype":"venue"
},
  "geometry": {"coordinates":[-75.360649,39.866551],"type":"Point"}
}