{
  "type": "Feature",
  "properties": {
    "iso:country":"US",
    "sg:address":"600 Pineview Dr",
    "sg:city":"Elizabeth",
    "sg:classifiers":[
        {
            "category":"Wholesale",
            "subcategory":"Durable Goods & Equipment",
            "type":"Manufacturing & Wholesale Goods"
        }
    ],
    "sg:phone":"+1 412 384 2700",
    "sg:postcode":"15037",
    "sg:province":"PA",
    "sg:tags":[
        "importer"
    ],
    "wof:name":"Taddeco Inc",
    "wof:placetype":"venue"
},
  "geometry": {"coordinates":[-79.835435,40.224368],"type":"Point"}
}