{
  "type": "Feature",
  "properties": {
    "iso:country":"US",
    "sg:address":"2662 Gilbert Rd",
    "sg:city":"Effort",
    "sg:classifiers":[
        {
            "category":"Shopping",
            "subcategory":"Bicycles & Sporting Goods",
            "type":"Retail Goods"
        }
    ],
    "sg:phone":"+1   ",
    "sg:postcode":"18330",
    "sg:province":"PA",
    "wof:name":"Keystone Supply",
    "wof:placetype":"venue"
},
  "geometry": {"coordinates":[-75.43589,40.930941],"type":"Point"}
}