{
  "type": "Feature",
  "properties": {
    "iso:country":"US",
    "sg:address":"1145 King Rd",
    "sg:city":"West Chester",
    "sg:classifiers":[
        {
            "category":"Health Services",
            "subcategory":"Nursing And Care Facility",
            "type":"Services"
        }
    ],
    "sg:phone":"+1 610 644 1152",
    "sg:postcode":"19380",
    "sg:province":"PA",
    "sg:tags":[
        "home",
        "convalescent"
    ],
    "wof:name":"Camilla Hall Nursing Home",
    "wof:placetype":"venue"
},
  "geometry": {"coordinates":[-75.591201,40.01706],"type":"Point"}
}