{
  "type": "Feature",
  "properties": {
    "iso:country":"US",
    "sg:address":"132 Main St",
    "sg:city":"Greenville",
    "sg:classifiers":[
        {
            "category":"Shopping",
            "subcategory":"Jewelry",
            "type":"Retail Goods"
        }
    ],
    "sg:phone":"+1   ",
    "sg:postcode":"16125",
    "sg:province":"PA",
    "wof:name":"Neustupa Jewelry Store",
    "wof:placetype":"venue"
},
  "geometry": {"coordinates":[-80.390874,41.40452],"type":"Point"}
}