{
  "type": "Feature",
  "properties": {
    "iso:country":"US",
    "sg:address":"38 N Kennedy Dr",
    "sg:city":"Sugarloaf",
    "sg:classifiers":[
        {
            "category":"Shopping",
            "subcategory":"Computers & Home Electronics",
            "type":"Retail Goods"
        }
    ],
    "sg:phone":"+1   ",
    "sg:postcode":"18237",
    "sg:province":"PA",
    "wof:name":"Good Associates Inc",
    "wof:placetype":"venue"
},
  "geometry": {"coordinates":[-75.993521,40.90321],"type":"Point"}
}