{
  "type": "Feature",
  "properties": {
    "iso:country":"US",
    "sg:address":"20325 Route 19 Unit 15",
    "sg:city":"Cranberry Twp",
    "sg:classifiers":[
        {
            "category":"Shopping",
            "subcategory":"Beauty & Cosmetics",
            "type":"Retail Goods"
        }
    ],
    "sg:phone":"+1 724 779 4480",
    "sg:postcode":"16066",
    "sg:province":"PA",
    "sg:tags":[
        "supply"
    ],
    "sg:website":"www.raylon.com",
    "wof:name":"Raylon Corp",
    "wof:placetype":"venue"
},
  "geometry": {"coordinates":[-80.1045,40.697399],"type":"Point"}
}