{
  "type": "Feature",
  "properties": {
    "iso:country":"US",
    "sg:address":"176 Baird Rd",
    "sg:city":"Edinburg",
    "sg:classifiers":[
        {
            "category":"Farming",
            "subcategory":"Farm",
            "type":"Manufacturing & Wholesale Goods"
        }
    ],
    "sg:phone":"+1 724 964 1140",
    "sg:postcode":"16116",
    "sg:province":"PA",
    "wof:name":"Pennhill Farms",
    "wof:placetype":"venue"
},
  "geometry": {"coordinates":[-80.50255900000001,41.053311],"type":"Point"}
}