{
  "type": "Feature",
  "properties": {
    "iso:country":"US",
    "sg:address":"800 Red Lion Rd",
    "sg:city":"Philadelphia",
    "sg:classifiers":[
        {
            "category":"Retail",
            "subcategory":"Repair Shop",
            "type":"Services"
        }
    ],
    "sg:phone":"+1   ",
    "sg:postcode":"19115",
    "sg:province":"PA",
    "wof:name":"Gerald OBoyle Drain Cleaning",
    "wof:placetype":"venue"
},
  "geometry": {"coordinates":[-75.03023399999999,40.103387],"type":"Point"}
}