{
  "type": "Feature",
  "properties": {
    "addr:full":"1242 E 5th St Berwick PA 18603",
    "addr:housenumber":"1242",
    "addr:postcode":"18603",
    "addr:street":"E 5Th St",
    "iso:country":"US",
    "sg:address":"1242 E 5th St",
    "sg:city":"Berwick",
    "sg:classifiers":[
        {
            "category":"Shopping",
            "subcategory":"Gifts & Souvenirs",
            "type":"Retail Goods"
        }
    ],
    "sg:phone":"+1 717 336 5191",
    "sg:postcode":"18603",
    "sg:province":"PA",
    "sg:tags":[
        "collectible"
    ],
    "wof:name":"James Snyder & Mary Collectibl",
    "wof:placetype":"venue"
},
  "geometry": {"coordinates":[-76.21498699999999,41.065812],"type":"Point"}
}