{
  "type": "Feature",
  "properties": {
    "iso:country":"US",
    "sg:address":"1230 High St",
    "sg:city":"Hanover",
    "sg:classifiers":[
        {
            "category":"Health Services",
            "subcategory":"Doctor",
            "type":"Services"
        }
    ],
    "sg:phone":"+1 717 633 5517",
    "sg:postcode":"17331",
    "sg:province":"PA",
    "sg:tags":[
        "physician",
        "surgeon"
    ],
    "wof:name":"York Health Corp",
    "wof:placetype":"venue"
},
  "geometry": {"coordinates":[-76.998981,39.817184],"type":"Point"}
}