{
  "type": "Feature",
  "properties": {
    "addr:full":"1924 S Sartain St Philadelphia PA 19148",
    "addr:housenumber":"1924",
    "addr:postcode":"19148",
    "addr:street":"S Sartain St",
    "iso:country":"US",
    "sg:address":"1924 S Sartain St",
    "sg:city":"Philadelphia",
    "sg:classifiers":[
        {
            "category":"Building & Trades",
            "subcategory":"Pest Control",
            "type":"Services"
        }
    ],
    "sg:phone":"+1 215 389 4971",
    "sg:postcode":"19148",
    "sg:province":"PA",
    "sg:tags":[
        "industrial",
        "services-commercial"
    ],
    "wof:name":"Nick's Exterminating",
    "wof:placetype":"venue"
},
  "geometry": {"coordinates":[-75.165003,39.92593],"type":"Point"}
}