{
  "type": "Feature",
  "properties": {
    "iso:country":"US",
    "sg:address":"7119 Frankstown Ave",
    "sg:city":"Pittsburgh",
    "sg:classifiers":[
        {
            "category":"Organizations",
            "subcategory":"Religious Organization",
            "type":"Services"
        }
    ],
    "sg:phone":"+1 412 371 9919",
    "sg:postcode":"15208",
    "sg:province":"PA",
    "wof:name":"Carrone Baptist Church",
    "wof:placetype":"venue"
},
  "geometry": {"coordinates":[-79.89658799999999,40.457562],"type":"Point"}
}