{
  "type": "Feature",
  "properties": {
    "addr:full":"301 King St Pottstown PA 19464",
    "addr:housenumber":"301",
    "addr:postcode":"19464",
    "addr:street":"King St",
    "iso:country":"US",
    "sg:address":"301 King St",
    "sg:city":"Pottstown",
    "sg:classifiers":[
        {
            "category":"Organizations",
            "subcategory":"Religious Organization",
            "type":"Services"
        }
    ],
    "sg:phone":"+1 610 326 2273",
    "sg:postcode":"19464",
    "sg:province":"PA",
    "sg:website":"www.fbcpottstown.net",
    "wof:name":"First Baptist Church",
    "wof:placetype":"venue"
},
  "geometry": {"coordinates":[-75.645736,40.246158],"type":"Point"}
}