{
  "type": "Feature",
  "properties": {
    "iso:country":"US",
    "sg:address":"1636 S Front St",
    "sg:city":"Philadelphia",
    "sg:classifiers":[
        {
            "category":"Wholesale",
            "subcategory":"Machinery & Supplies",
            "type":"Manufacturing & Wholesale Goods"
        }
    ],
    "sg:phone":"+1   ",
    "sg:postcode":"19148",
    "sg:province":"PA",
    "wof:name":"AJs Bar & Restaurant Supply",
    "wof:placetype":"venue"
},
  "geometry": {"coordinates":[-75.147262,39.926442],"type":"Point"}
}