{
  "type": "Feature",
  "properties": {
    "addr:full":"850 Scalp Ave Johnstown PA 15904",
    "addr:housenumber":"850",
    "addr:postcode":"15904",
    "addr:street":"Scalp Ave",
    "iso:country":"US",
    "sg:address":"850 Scalp Ave",
    "sg:city":"Johnstown",
    "sg:classifiers":[
        {
            "category":"Recreation",
            "type":"Entertainment"
        }
    ],
    "sg:phone":"+1 814 266 1919",
    "sg:postcode":"15904",
    "sg:province":"PA",
    "wof:name":"Miscues Billiards",
    "wof:placetype":"venue"
},
  "geometry": {"coordinates":[-78.866423,40.28775],"type":"Point"}
}