{
  "type": "Feature",
  "properties": {
    "iso:country":"US",
    "sg:address":"417 N 8th St Ste 503",
    "sg:city":"Philadelphia",
    "sg:classifiers":[
        {
            "category":"Banks & Credit Unions",
            "subcategory":"Investment Brokerage",
            "type":"Services"
        },
        {
            "category":"Banks & Credit Unions",
            "subcategory":"Bank",
            "type":"Services"
        },
        {
            "category":"Banks & Credit Unions",
            "subcategory":"Financial Services",
            "type":"Services"
        }
    ],
    "sg:phone":"+1 215 972 0300",
    "sg:postcode":"19123",
    "sg:province":"PA",
    "sg:tags":[
        "advisory",
        "retirement",
        "annuity",
        "broker",
        "agent",
        "planner",
        "plan",
        "transfer",
        "bond",
        "insurance",
        "stock"
    ],
    "sg:website":"http://www.scharfgroup.net",
    "wof:name":"Scharf Investment Group",
    "wof:placetype":"venue"
},
  "geometry": {"coordinates":[-75.151989,39.958747],"type":"Point"}
}