{
  "type": "Feature",
  "properties": {
    "iso:country":"US",
    "sg:address":"205 Dundon Rd Apt 3",
    "sg:city":"Edinboro",
    "sg:classifiers":[
        {
            "category":"Insurance",
            "subcategory":"Hazard Insurance",
            "type":"Services"
        }
    ],
    "sg:phone":"+1 412 366 8619",
    "sg:postcode":"16412",
    "sg:province":"PA",
    "sg:tags":[
        "commercial",
        "business"
    ],
    "sg:website":"http://www.unitedamerican.com",
    "wof:name":"United American Insurance Company",
    "wof:placetype":"venue"
},
  "geometry": {"coordinates":[-80.11067,41.882792],"type":"Point"}
}