{
  "type": "Feature",
  "properties": {
    "addr:full":"410 N Lime St Lancaster PA 17602",
    "addr:housenumber":"410",
    "addr:postcode":"17602",
    "addr:street":"N Lime St",
    "iso:country":"US",
    "sg:address":"410 N Lime St",
    "sg:city":"Lancaster",
    "sg:classifiers":[
        {
            "category":"Education",
            "subcategory":"College",
            "type":"Public Place"
        }
    ],
    "sg:phone":"+1 717 290 4912",
    "sg:postcode":"17602",
    "sg:province":"PA",
    "sg:tags":[
        "academic",
        "school"
    ],
    "wof:name":"Lancaster Institute For Health",
    "wof:placetype":"venue"
},
  "geometry": {"coordinates":[-76.302764,40.045189],"type":"Point"}
}