{
  "type": "Feature",
  "properties": {
    "iso:country":"US",
    "sg:address":"780 5th Ave",
    "sg:city":"King Of Prussia",
    "sg:classifiers":[
        {
            "category":"Professional",
            "type":"Services"
        }
    ],
    "sg:phone":"+1 610 337 2644",
    "sg:postcode":"19406",
    "sg:province":"PA",
    "sg:tags":[
        "establishment"
    ],
    "wof:name":"True Position",
    "wof:placetype":"venue"
},
  "geometry": {"coordinates":[-75.40479999999999,40.1034],"type":"Point"}
}