{
  "type": "Feature",
  "properties": {
    "iso:country":"US",
    "sg:address":"328 E Lawn Rd",
    "sg:city":"Nazareth",
    "sg:classifiers":[
        {
            "category":"Shopping",
            "subcategory":"Bicycles & Sporting Goods",
            "type":"Retail Goods"
        }
    ],
    "sg:phone":"+1 610 759 2905",
    "sg:postcode":"18064",
    "sg:province":"PA",
    "sg:tags":[
        "item",
        "fishing",
        "hunting"
    ],
    "wof:name":"Mike's Bait & Sport Shop",
    "wof:placetype":"venue"
},
  "geometry": {"coordinates":[-75.29791899999999,40.749438],"type":"Point"}
}