{
  "type": "Feature",
  "properties": {
    "iso:country":"US",
    "sg:address":"411 Flinthill Rd",
    "sg:city":"King Of Prussia",
    "sg:classifiers":[
        {
            "category":"Retail",
            "subcategory":"Auto Repair",
            "type":"Services"
        }
    ],
    "sg:phone":"+1 610 275 2067",
    "sg:postcode":"19406",
    "sg:province":"PA",
    "sg:tags":[
        "general"
    ],
    "wof:name":"Ram Automotive",
    "wof:placetype":"venue"
},
  "geometry": {"coordinates":[-75.335646,40.092342],"type":"Point"}
}