{
  "type": "Feature",
  "properties": {
    "iso:country":"US",
    "sg:address":"1616 Walnut St Ste 1112",
    "sg:city":"Philadelphia",
    "sg:classifiers":[
        {
            "category":"Professional",
            "subcategory":"Lawyer & Legal Services",
            "type":"Services"
        }
    ],
    "sg:phone":"+1 215 735 4800",
    "sg:postcode":"19103",
    "sg:province":"PA",
    "wof:name":"Kofsky the Law Offices of Joel J PC",
    "wof:placetype":"venue"
},
  "geometry": {"coordinates":[-75.167801,39.9496],"type":"Point"}
}