{
  "type": "Feature",
  "properties": {
    "iso:country":"US",
    "sg:address":"1400 Industrial Hwy",
    "sg:city":"Pottstown",
    "sg:classifiers":[
        {
            "category":"Recreation",
            "type":"Entertainment"
        }
    ],
    "sg:phone":"+1 610 323 9600",
    "sg:postcode":"19464",
    "sg:province":"PA",
    "sg:tags":[
        "amusement"
    ],
    "sg:website":"www.actionsportsonline.com",
    "wof:name":"Action Sports",
    "wof:placetype":"venue"
},
  "geometry": {"coordinates":[-75.63040599999999,40.235454],"type":"Point"}
}