{
  "type": "Feature",
  "properties": {
    "iso:country":"US",
    "sg:address":"202 N Broad St",
    "sg:city":"Grove City",
    "sg:classifiers":[
        {
            "category":"Wholesale",
            "subcategory":"Medical Equipment & Supplies",
            "type":"Manufacturing & Wholesale Goods"
        }
    ],
    "sg:phone":"+1 724 458 6612",
    "sg:postcode":"16127",
    "sg:province":"PA",
    "sg:website":"www.mercercountyrehab.com",
    "wof:name":"Mercer County Rehab Supply",
    "wof:placetype":"venue"
},
  "geometry": {"coordinates":[-80.083675,41.163816],"type":"Point"}
}