{
  "type": "Feature",
  "properties": {
    "iso:country":"US",
    "sg:address":"1006 Pennsylvania Ave",
    "sg:city":"Matamoras",
    "sg:classifiers":[
        {
            "category":"Wholesale",
            "subcategory":"Fruits & Vegetables",
            "type":"Manufacturing & Wholesale Goods"
        }
    ],
    "sg:phone":"+1   ",
    "sg:postcode":"18336",
    "sg:province":"PA",
    "sg:tags":[
        "produce"
    ],
    "wof:name":"K A P Company",
    "wof:placetype":"venue"
},
  "geometry": {"coordinates":[-74.70666,41.362784],"type":"Point"}
}