{
  "type": "Feature",
  "properties": {
    "addr:full":"1061 W Main St Valley View PA 17983",
    "addr:housenumber":"1061",
    "addr:postcode":"17983",
    "addr:street":"W Main St",
    "iso:country":"US",
    "sg:address":"1061 W Main St",
    "sg:city":"Valley View",
    "sg:classifiers":[
        {
            "category":"Shopping",
            "subcategory":"Stationery & Office Supplies",
            "type":"Retail Goods"
        }
    ],
    "sg:phone":"+1 570 682 1062",
    "sg:postcode":"17983",
    "sg:province":"PA",
    "wof:name":"Office Mall",
    "wof:placetype":"venue"
},
  "geometry": {"coordinates":[-76.537992,40.646045],"type":"Point"}
}