{
  "type": "Feature",
  "properties": {
    "addr:full":"108 Alana Dr Saxonburg PA 16056",
    "addr:housenumber":"108",
    "addr:postcode":"16056",
    "addr:street":"Alana Dr",
    "iso:country":"US",
    "sg:address":"108 Alana Dr",
    "sg:city":"Saxonburg",
    "sg:classifiers":[
        {
            "category":"Building & Trades",
            "subcategory":"Equipment Rental",
            "type":"Services"
        }
    ],
    "sg:phone":"+1 724 360 5000",
    "sg:postcode":"16056",
    "sg:province":"PA",
    "sg:tags":[
        "yard",
        "leasing",
        "store"
    ],
    "wof:name":"Countryside Capital",
    "wof:placetype":"venue"
},
  "geometry": {"coordinates":[-79.820183,40.766281],"type":"Point"}
}