{
  "type": "Feature",
  "properties": {
    "addr:full":"505 York Rd Jenkintown PA 19046",
    "addr:housenumber":"505",
    "addr:postcode":"19046",
    "addr:street":"York Rd",
    "iso:country":"US",
    "sg:address":"505 York Rd",
    "sg:city":"Jenkintown",
    "sg:classifiers":[
        {
            "category":"Bakery",
            "type":"Food & Drink"
        },
        {
            "category":"Coffee & Tea",
            "type":"Food & Drink"
        },
        {
            "category":"Bagels",
            "type":"Food & Drink"
        },
        {
            "category":"Donuts",
            "type":"Food & Drink"
        }
    ],
    "sg:menulink":"http://www.allmenus.com/pa/jenkintown/143829-dunkin-donuts/menu/",
    "sg:phone":"+1 215 885 0744",
    "sg:postcode":"19046",
    "sg:province":"PA",
    "sg:tags":[
        "american",
        "diner",
        "pastry"
    ],
    "wof:name":"Dunkin' Donuts",
    "wof:placetype":"venue"
},
  "geometry": {"coordinates":[-75.12583600000001,40.099236],"type":"Point"}
}