{
  "type": "Feature",
  "properties": {
    "addr:full":"2 E 28th Division Hwy Lititz PA 17543",
    "addr:housenumber":"2",
    "addr:postcode":"17543",
    "addr:street":"E 28Th Division Hwy",
    "iso:country":"US",
    "sg:address":"2 E 28th Division Hwy",
    "sg:city":"Lititz",
    "sg:classifiers":[
        {
            "category":"Shopping",
            "subcategory":"Crafts & Fabrics",
            "type":"Retail Goods"
        }
    ],
    "sg:phone":"+1   ",
    "sg:postcode":"17543",
    "sg:province":"PA",
    "sg:tags":[
        "sewing"
    ],
    "wof:name":"Ball & Skein Shop",
    "wof:placetype":"venue"
},
  "geometry": {"coordinates":[-76.29914599999999,40.22512],"type":"Point"}
}