{
  "type": "Feature",
  "properties": {
    "iso:country":"US",
    "sg:address":"1980 S Easton Rd",
    "sg:city":"Doylestown",
    "sg:classifiers":[
        {
            "category":"Building & Trades",
            "subcategory":"Construction",
            "type":"Services"
        }
    ],
    "sg:phone":"+1 215 230 1074",
    "sg:postcode":"18901",
    "sg:province":"PA",
    "sg:tags":[
        "contractor"
    ],
    "wof:name":"Heritge Building Group Inc",
    "wof:placetype":"venue"
},
  "geometry": {"coordinates":[-75.12873399999999,40.291351],"type":"Point"}
}