{
  "type": "Feature",
  "properties": {
    "iso:country":"US",
    "sg:address":"4 Fairway Dr",
    "sg:city":"Sewickley",
    "sg:classifiers":[
        {
            "category":"Banks & Credit Unions",
            "subcategory":"Investment Brokerage",
            "type":"Services"
        }
    ],
    "sg:phone":"+1   ",
    "sg:postcode":"15143",
    "sg:province":"PA",
    "sg:tags":[
        "advisory"
    ],
    "wof:name":"Alliance Capital MGT Corp",
    "wof:placetype":"venue"
},
  "geometry": {"coordinates":[-80.17301,40.583296],"type":"Point"}
}