{
  "type": "Feature",
  "properties": {
    "addr:full":"220 N Main St Pleasant Gap PA 16823",
    "addr:housenumber":"220",
    "addr:postcode":"16823",
    "addr:street":"N Main St",
    "iso:country":"US",
    "sg:address":"220 N Main St",
    "sg:city":"Pleasant Gap",
    "sg:classifiers":[
        {
            "category":"Building & Trades",
            "subcategory":"Construction",
            "type":"Services"
        }
    ],
    "sg:phone":"+1 814 280 2815",
    "sg:postcode":"16823",
    "sg:province":"PA",
    "sg:tags":[
        "contractor"
    ],
    "wof:name":"Benjamin's Construction",
    "wof:placetype":"venue"
},
  "geometry": {"coordinates":[-77.75190499999999,40.869097],"type":"Point"}
}