{
  "type": "Feature",
  "properties": {
    "addr:full":"1442 18 Hollow Rd Clearfield PA 16830",
    "addr:housenumber":"1442",
    "addr:postcode":"16830",
    "addr:street":"18 Hollow Rd",
    "iso:country":"US",
    "sg:address":"1442 18 Hollow Rd",
    "sg:city":"Clearfield",
    "sg:classifiers":[
        {
            "category":"Manufacturing",
            "subcategory":"Chemicals & Compounds",
            "type":"Manufacturing & Wholesale Goods"
        }
    ],
    "sg:phone":"+1 814 765 1558",
    "sg:postcode":"16830",
    "sg:province":"PA",
    "sg:tags":[
        "explosive"
    ],
    "wof:name":"Guelich, D. C. Explosive Company (A Close Corporation)",
    "wof:placetype":"venue"
},
  "geometry": {"coordinates":[-78.44995299999999,40.970858],"type":"Point"}
}