{
  "type": "Feature",
  "properties": {
    "iso:country":"US",
    "sg:address":"126 S 52nd St",
    "sg:city":"Philadelphia",
    "sg:classifiers":[
        {
            "category":"Wholesale",
            "subcategory":"Toys & Hobbies",
            "type":"Manufacturing & Wholesale Goods"
        }
    ],
    "sg:phone":"+1   ",
    "sg:postcode":"19139",
    "sg:province":"PA",
    "wof:name":"Power Gamer",
    "wof:placetype":"venue"
},
  "geometry": {"coordinates":[-75.225582,39.957005],"type":"Point"}
}