{
  "type": "Feature",
  "properties": {
    "iso:country":"US",
    "sg:address":"23 Furnace St Exd",
    "sg:city":"Mc Kees Rocks",
    "sg:classifiers":[
        {
            "category":"Shopping",
            "subcategory":"News",
            "type":"Retail Goods"
        }
    ],
    "sg:phone":"+1 412 777 6006",
    "sg:postcode":"15136",
    "sg:province":"PA",
    "wof:name":"News Group",
    "wof:placetype":"venue"
},
  "geometry": {"coordinates":[-80.058898,40.464219],"type":"Point"}
}