{
  "type": "Feature",
  "properties": {
    "addr:full":"1214 Allengrove St Philadelphia PA 19124",
    "addr:housenumber":"1214",
    "addr:postcode":"19124",
    "addr:street":"Allengrove St",
    "iso:country":"US",
    "sg:address":"1214 Allengrove St",
    "sg:city":"Philadelphia",
    "sg:classifiers":[
        {
            "category":"Professional",
            "type":"Services"
        }
    ],
    "sg:phone":"+1   ",
    "sg:postcode":"19124",
    "sg:province":"PA",
    "wof:name":"Nathaniel Miller",
    "wof:placetype":"venue"
},
  "geometry": {"coordinates":[-75.085933,40.022155],"type":"Point"}
}