{
  "type": "Feature",
  "properties": {
    "iso:country":"US",
    "sg:address":"7037 Easton Rd",
    "sg:city":"Pipersville",
    "sg:classifiers":[
        {
            "category":"Wholesale",
            "subcategory":"Farm Supplies",
            "type":"Manufacturing & Wholesale Goods"
        },
        {
            "category":"Shopping",
            "type":"Retail Goods"
        }
    ],
    "sg:phone":"+1 215 766 1475",
    "sg:postcode":"18947",
    "sg:province":"PA",
    "sg:tags":[
        "feed",
        "pet",
        "food"
    ],
    "wof:name":"Peppy Pet Foods & Supplies",
    "wof:placetype":"venue"
},
  "geometry": {"coordinates":[-75.141597,40.429312],"type":"Point"}
}