{
  "type": "Feature",
  "properties": {
    "addr:full":"901 Gravel Pike Schwenksville PA 19473",
    "addr:housenumber":"901",
    "addr:postcode":"19473",
    "addr:street":"Gravel Pike",
    "iso:country":"US",
    "sg:address":"901 Gravel Pike",
    "sg:city":"Schwenksville",
    "sg:classifiers":[
        {
            "category":"Farming",
            "subcategory":"Nursery",
            "type":"Manufacturing & Wholesale Goods"
        }
    ],
    "sg:phone":"+1   ",
    "sg:postcode":"19473",
    "sg:province":"PA",
    "sg:tags":[
        "food",
        "ornamental",
        "farm",
        "crop",
        "covered"
    ],
    "wof:name":"Otts Exotic Plants Inc",
    "wof:placetype":"venue"
},
  "geometry": {"coordinates":[-75.456294,40.240807],"type":"Point"}
}