{
  "type": "Feature",
  "properties": {
    "iso:country":"US",
    "sg:address":"1433 Wethersfield Dr",
    "sg:city":"Allentown",
    "sg:classifiers":[
        {
            "category":"Professional",
            "subcategory":"Lawyer & Legal Services",
            "type":"Services"
        }
    ],
    "sg:phone":"+1 610 395 6327",
    "sg:postcode":"18104",
    "sg:province":"PA",
    "wof:name":"Piosa Michael J Atty",
    "wof:placetype":"venue"
},
  "geometry": {"coordinates":[-75.557503,40.608101],"type":"Point"}
}