{
  "type": "Feature",
  "properties": {
    "iso:country":"US",
    "sg:address":"52 Clay Slate Rd",
    "sg:city":"Oley",
    "sg:classifiers":[
        {
            "category":"Freight",
            "type":"Transportation"
        }
    ],
    "sg:phone":"+1 610 987 9484",
    "sg:postcode":"19547",
    "sg:province":"PA",
    "sg:tags":[
        "trucking"
    ],
    "wof:name":"Warpath Trucking",
    "wof:placetype":"venue"
},
  "geometry": {"coordinates":[-75.776323,40.380937],"type":"Point"}
}