{
  "type": "Feature",
  "properties": {
    "iso:country":"US",
    "sg:address":"2660 Trenton Rd",
    "sg:city":"Levittown",
    "sg:classifiers":[
        {
            "category":"Organizations",
            "subcategory":"Religious Organization",
            "type":"Services"
        }
    ],
    "sg:phone":"+1 215 943 7300",
    "sg:postcode":"19056",
    "sg:province":"PA",
    "sg:tags":[
        "church"
    ],
    "wof:name":"Cornerstone Bible Fellowship",
    "wof:placetype":"venue"
},
  "geometry": {"coordinates":[-74.87974800000001,40.165901],"type":"Point"}
}