{
  "type": "Feature",
  "properties": {
    "iso:country":"US",
    "sg:address":"9 Presidential Blvd",
    "sg:city":"Bala Cynwyd",
    "sg:classifiers":[
        {
            "category":"Building & Trades",
            "subcategory":"Construction",
            "type":"Services"
        }
    ],
    "sg:phone":"+1 610 668 0950",
    "sg:postcode":"19004",
    "sg:province":"PA",
    "sg:tags":[
        "contractor"
    ],
    "wof:name":"Driscoll L F Co",
    "wof:placetype":"venue"
},
  "geometry": {"coordinates":[-75.211304,40.0093],"type":"Point"}
}