{
  "type": "Feature",
  "properties": {
    "addr:full":"1361 Main St Bloomsburg PA 17815",
    "addr:housenumber":"1361",
    "addr:postcode":"17815",
    "addr:street":"Main St",
    "iso:country":"US",
    "sg:address":"1361 Main St",
    "sg:city":"Bloomsburg",
    "sg:classifiers":[
        {
            "category":"Restaurant",
            "type":"Food & Drink"
        }
    ],
    "sg:phone":"+1 570 784 1070",
    "sg:postcode":"17815",
    "sg:province":"PA",
    "wof:name":"Lightstreet Hotel",
    "wof:placetype":"venue"
},
  "geometry": {"coordinates":[-76.42391499999999,41.031663],"type":"Point"}
}