{
  "type": "Feature",
  "properties": {
    "addr:full":"7049 Terminal Sq Upper Darby PA 19082",
    "addr:housenumber":"7049",
    "addr:postcode":"19082",
    "addr:street":"Terminal Sq",
    "iso:country":"US",
    "sg:address":"7049 Terminal Sq",
    "sg:city":"Upper Darby",
    "sg:classifiers":[
        {
            "category":"Bars & Pubs",
            "type":"Food & Drink"
        }
    ],
    "sg:phone":"+1 610 713 9447",
    "sg:postcode":"19082",
    "sg:province":"PA",
    "wof:name":"Club Terminal & Sports Bar",
    "wof:placetype":"venue"
},
  "geometry": {"coordinates":[-75.262912,39.960986],"type":"Point"}
}