{
  "type": "Feature",
  "properties": {
    "iso:country":"US",
    "sg:address":"2418 Felton St",
    "sg:city":"Chester",
    "sg:classifiers":[
        {
            "category":"Wholesale",
            "subcategory":"Vending Machines",
            "type":"Manufacturing & Wholesale Goods"
        }
    ],
    "sg:phone":"+1 610 494 5900",
    "sg:postcode":"19013",
    "sg:province":"PA",
    "sg:tags":[
        "operator"
    ],
    "wof:name":"Automatic Coin Vending Co",
    "wof:placetype":"venue"
},
  "geometry": {"coordinates":[-75.398691,39.84595],"type":"Point"}
}