{
  "type": "Feature",
  "properties": {
    "iso:country":"US",
    "sg:address":"603 W 2nd Ave",
    "sg:city":"Parkesburg",
    "sg:classifiers":[
        {
            "category":"Organizations",
            "subcategory":"Religious Organization",
            "type":"Services"
        }
    ],
    "sg:phone":"+1   ",
    "sg:postcode":"19365",
    "sg:province":"PA",
    "wof:name":"Our Lady of Consulation",
    "wof:placetype":"venue"
},
  "geometry": {"coordinates":[-75.922741,39.95702],"type":"Point"}
}