{
  "type": "Feature",
  "properties": {
    "iso:country":"US",
    "sg:address":"310 Stoke Park Rd",
    "sg:city":"Bethlehem",
    "sg:classifiers":[
        {
            "category":"Deli",
            "type":"Food & Drink"
        },
        {
            "category":"Ice Cream",
            "type":"Food & Drink"
        }
    ],
    "sg:phone":"+1 610 882 3663",
    "sg:postcode":"18017",
    "sg:province":"PA",
    "sg:tags":[
        "frozen",
        "yogurt"
    ],
    "wof:name":"Dave's Deli & Gelato",
    "wof:placetype":"venue"
},
  "geometry": {"coordinates":[-75.388901,40.6609],"type":"Point"}
}