{
  "type": "Feature",
  "properties": {
    "addr:full":"2024 Chevy Chase Dr Harrisburg PA 17110",
    "addr:housenumber":"2024",
    "addr:postcode":"17110",
    "addr:street":"Chevy Chase Dr",
    "iso:country":"US",
    "sg:address":"2024 Chevy Chase Dr",
    "sg:city":"Harrisburg",
    "sg:classifiers":[
        {
            "category":"Wholesale",
            "subcategory":"Groceries",
            "type":"Manufacturing & Wholesale Goods"
        }
    ],
    "sg:phone":"+1 717 651 9441",
    "sg:postcode":"17110",
    "sg:province":"PA",
    "sg:tags":[
        "food",
        "broker"
    ],
    "wof:name":"Damon Marketing",
    "wof:placetype":"venue"
},
  "geometry": {"coordinates":[-76.86523,40.326925],"type":"Point"}
}