{
  "type": "Feature",
  "properties": {
    "iso:country":"US",
    "sg:address":"105 Sycamore Dr",
    "sg:city":"Feasterville Trevose",
    "sg:classifiers":[
        {
            "category":"Manufacturing",
            "subcategory":"Metals",
            "type":"Manufacturing & Wholesale Goods"
        }
    ],
    "sg:phone":"+1   ",
    "sg:postcode":"19053",
    "sg:province":"PA",
    "sg:tags":[
        "blast",
        "furnace",
        "works"
    ],
    "wof:name":"Positrade",
    "wof:placetype":"venue"
},
  "geometry": {"coordinates":[-74.961133,40.160411],"type":"Point"}
}