{
  "type": "Feature",
  "properties": {
    "iso:country":"US",
    "sg:address":"920 S Union St",
    "sg:city":"Kennett Square",
    "sg:classifiers":[
        {
            "category":"Manufacturing",
            "subcategory":"Tools & Machinery",
            "type":"Manufacturing & Wholesale Goods"
        }
    ],
    "sg:phone":"+1 610 444 4660",
    "sg:postcode":"19348",
    "sg:province":"PA",
    "sg:tags":[
        "water",
        "equipment",
        "conditioning",
        "mfg"
    ],
    "wof:name":"Lester Water Inc",
    "wof:placetype":"venue"
},
  "geometry": {"coordinates":[-75.70817099999999,39.835247],"type":"Point"}
}