{
  "type": "Feature",
  "properties": {
    "iso:country":"US",
    "sg:address":"6333 Sprague St",
    "sg:city":"Philadelphia",
    "sg:classifiers":[
        {
            "category":"Social Services",
            "subcategory":"Adult Care",
            "type":"Services"
        }
    ],
    "sg:phone":"+1 215 424 3366",
    "sg:postcode":"19138",
    "sg:province":"PA",
    "sg:tags":[
        "nurses-home"
    ],
    "wof:name":"Johnsons Personal Care Hom",
    "wof:placetype":"venue"
},
  "geometry": {"coordinates":[-75.17215400000001,40.054927],"type":"Point"}
}