{
  "type": "Feature",
  "properties": {
    "addr:full":"2790 Saw Mill Run Blvd Pittsburgh PA 15227",
    "addr:housenumber":"2790",
    "addr:postcode":"15227",
    "addr:street":"Saw Mill Run Blvd",
    "iso:country":"US",
    "sg:address":"2790 Saw Mill Run Blvd",
    "sg:city":"Pittsburgh",
    "sg:classifiers":[
        {
            "category":"Education",
            "subcategory":"Kindergarten",
            "type":"Public Place"
        }
    ],
    "sg:phone":"+1 412 481 9005",
    "sg:postcode":"15227",
    "sg:province":"PA",
    "sg:tags":[
        "school",
        "driving"
    ],
    "wof:name":"Goodwill Industries of Pittsburgh",
    "wof:placetype":"venue"
},
  "geometry": {"coordinates":[-79.991798,40.381901],"type":"Point"}
}