{
  "type": "Feature",
  "properties": {
    "iso:country":"US",
    "sg:address":"53 Hunterstown Hampton Rd",
    "sg:city":"Gettysburg",
    "sg:classifiers":[
        {
            "category":"Building & Trades",
            "subcategory":"Construction",
            "type":"Services"
        }
    ],
    "sg:phone":"+1 717 752 0840",
    "sg:postcode":"17325",
    "sg:province":"PA",
    "sg:tags":[
        "home",
        "improvement"
    ],
    "wof:name":"S J Construction",
    "wof:placetype":"venue"
},
  "geometry": {"coordinates":[-77.159113,39.881722],"type":"Point"}
}