{
  "type": "Feature",
  "properties": {
    "addr:full":"27 W Market St Lewistown PA 17044",
    "addr:housenumber":"27",
    "addr:postcode":"17044",
    "addr:street":"W Market St",
    "iso:country":"US",
    "sg:address":"27 W Market St",
    "sg:city":"Lewistown",
    "sg:classifiers":[
        {
            "category":"Wholesale",
            "subcategory":"Electrical",
            "type":"Manufacturing & Wholesale Goods"
        }
    ],
    "sg:phone":"+1   ",
    "sg:postcode":"17044",
    "sg:province":"PA",
    "sg:tags":[
        "system",
        "microwave"
    ],
    "wof:name":"P & H Electronics Inc",
    "wof:placetype":"venue"
},
  "geometry": {"coordinates":[-77.57511599999999,40.597184],"type":"Point"}
}