{
  "type": "Feature",
  "properties": {
    "iso:country":"US",
    "sg:address":"413 Ellis Rd",
    "sg:city":"Havertown",
    "sg:classifiers":[
        {
            "category":"Shopping",
            "subcategory":"Optical Goods",
            "type":"Retail Goods"
        }
    ],
    "sg:phone":"+1   ",
    "sg:postcode":"19083",
    "sg:province":"PA",
    "wof:name":"Optical Centre",
    "wof:placetype":"venue"
},
  "geometry": {"coordinates":[-75.333738,39.985996],"type":"Point"}
}