{
  "type": "Feature",
  "properties": {
    "addr:full":"6 E Moser Ave Coaldale PA 18218",
    "addr:housenumber":"6",
    "addr:postcode":"18218",
    "addr:street":"E Moser Ave",
    "iso:country":"US",
    "sg:address":"6 E Moser Ave",
    "sg:city":"Coaldale",
    "sg:classifiers":[
        {
            "category":"Recreation",
            "type":"Entertainment"
        }
    ],
    "sg:phone":"+1 570 645 9236",
    "sg:postcode":"18218",
    "sg:province":"PA",
    "sg:tags":[
        "club",
        "sporting",
        "instruction",
        "marksmanship",
        "gun",
        "membership",
        "safety"
    ],
    "wof:name":"Westward Rod & Gun Club",
    "wof:placetype":"venue"
},
  "geometry": {"coordinates":[-75.905952,40.821046],"type":"Point"}
}