{
  "type": "Feature",
  "properties": {
    "iso:country":"US",
    "sg:address":"445 Benner Pike",
    "sg:city":"State College",
    "sg:classifiers":[
        {
            "category":"Home & Garden",
            "subcategory":"Furniture",
            "type":"Retail Goods"
        }
    ],
    "sg:phone":"+1 814 238 5700",
    "sg:postcode":"16801",
    "sg:province":"PA",
    "wof:name":"Norwalk-Furniture Idea Shwrm",
    "wof:placetype":"venue"
},
  "geometry": {"coordinates":[-77.80208,40.834666],"type":"Point"}
}