{
  "type": "Feature",
  "properties": {
    "iso:country":"US",
    "sg:address":"201 Monroe Ct",
    "sg:city":"Southampton",
    "sg:classifiers":[
        {
            "category":"Professional",
            "type":"Services"
        }
    ],
    "sg:phone":"+1   ",
    "sg:postcode":"18966",
    "sg:province":"PA",
    "wof:name":"J & A Power Washing",
    "wof:placetype":"venue"
},
  "geometry": {"coordinates":[-74.966838,40.20965],"type":"Point"}
}