{
  "type": "Feature",
  "properties": {
    "addr:full":"610 Melwood Ave Pittsburgh PA 15213",
    "addr:housenumber":"610",
    "addr:postcode":"15213",
    "addr:street":"Melwood Ave",
    "iso:country":"US",
    "sg:address":"610 Melwood Ave",
    "sg:city":"Pittsburgh",
    "sg:classifiers":[
        {
            "category":"Professional",
            "subcategory":"Detective & Security Services",
            "type":"Services"
        }
    ],
    "sg:phone":"+1   ",
    "sg:postcode":"15213",
    "sg:province":"PA",
    "sg:tags":[
        "protective",
        "electronic"
    ],
    "wof:name":"TBE Incorporated",
    "wof:placetype":"venue"
},
  "geometry": {"coordinates":[-79.95370699999999,40.456409],"type":"Point"}
}