{
  "type": "Feature",
  "properties": {
    "iso:country":"US",
    "sg:address":"811 Lincoln Dr",
    "sg:city":"Brookhaven",
    "sg:classifiers":[
        {
            "category":"Wholesale",
            "subcategory":"Medical Equipment & Supplies",
            "type":"Manufacturing & Wholesale Goods"
        }
    ],
    "sg:phone":"+1 610 872 5636",
    "sg:postcode":"19015",
    "sg:province":"PA",
    "sg:tags":[
        "physician",
        "hospital",
        "surgeon"
    ],
    "sg:website":"http://www.wbmedical.com",
    "wof:name":"West Branch Medical",
    "wof:placetype":"venue"
},
  "geometry": {"coordinates":[-75.40563400000001,39.869017],"type":"Point"}
}