{
  "type": "Feature",
  "properties": {
    "iso:country":"US",
    "sg:address":"1044 Sandy Hill Rd",
    "sg:city":"Irwin",
    "sg:classifiers":[
        {
            "category":"Professional",
            "subcategory":"Computer Services",
            "type":"Services"
        }
    ],
    "sg:phone":"+1 724 744 4094",
    "sg:postcode":"15642",
    "sg:province":"PA",
    "sg:tags":[
        "design",
        "programming",
        "system"
    ],
    "sg:website":"www.corestar-corp.com",
    "wof:name":"Corestar International Corp",
    "wof:placetype":"venue"
},
  "geometry": {"coordinates":[-79.67542400000001,40.350402],"type":"Point"}
}