{
  "type": "Feature",
  "properties": {
    "iso:country":"US",
    "sg:address":"2318 Meetinghouse Rd",
    "sg:city":"Boothwyn",
    "sg:classifiers":[
        {
            "category":"Retail",
            "subcategory":"Auto Repair",
            "type":"Services"
        }
    ],
    "sg:phone":"+1 610 485 0417",
    "sg:postcode":"19061",
    "sg:province":"PA",
    "sg:tags":[
        "repairing",
        "automobile"
    ],
    "wof:name":"Gus's Auto Svc",
    "wof:placetype":"venue"
},
  "geometry": {"coordinates":[-75.452337,39.827554],"type":"Point"}
}