{
  "type": "Feature",
  "properties": {
    "iso:country":"US",
    "sg:address":"481 Cherryhill Dr",
    "sg:city":"Bridgeville",
    "sg:classifiers":[
        {
            "category":"Utilities",
            "subcategory":"Telephone",
            "type":"Services"
        }
    ],
    "sg:phone":"+1   ",
    "sg:postcode":"15017",
    "sg:province":"PA",
    "sg:tags":[
        "communications"
    ],
    "wof:name":"Uptownavenuecom",
    "wof:placetype":"venue"
},
  "geometry": {"coordinates":[-80.144695,40.318931],"type":"Point"}
}