{
  "type": "Feature",
  "properties": {
    "addr:full":"1221 E Carson St Pittsburgh PA 15203",
    "addr:housenumber":"1221",
    "addr:postcode":"15203",
    "addr:street":"E Carson St",
    "iso:country":"US",
    "sg:address":"1221 E Carson St",
    "sg:city":"Pittsburgh",
    "sg:classifiers":[
        {
            "category":"Shopping",
            "subcategory":"Optical Goods",
            "type":"Retail Goods"
        }
    ],
    "sg:phone":"+1 412 431 3139",
    "sg:postcode":"15203",
    "sg:province":"PA",
    "sg:tags":[
        "optician",
        "eyewear"
    ],
    "wof:name":"Roslonski Optical",
    "wof:placetype":"venue"
},
  "geometry": {"coordinates":[-79.985603,40.428902],"type":"Point"}
}