{
  "type": "Feature",
  "properties": {
    "iso:country":"US",
    "sg:address":"1745 Clifford Dr",
    "sg:city":"Erie",
    "sg:classifiers":[
        {
            "category":"Professional",
            "subcategory":"Business Services",
            "type":"Services"
        }
    ],
    "sg:phone":"+1   ",
    "sg:postcode":"16505",
    "sg:province":"PA",
    "wof:name":"Ewm Enterprises",
    "wof:placetype":"venue"
},
  "geometry": {"coordinates":[-80.202567,42.072931],"type":"Point"}
}