{
  "type": "Feature",
  "properties": {
    "iso:country":"US",
    "sg:address":"1332 Hampton Dr",
    "sg:city":"Archbald",
    "sg:classifiers":[
        {
            "category":"Real Estate",
            "subcategory":"Real Estate Agent",
            "type":"Services"
        }
    ],
    "sg:phone":"+1 570 876 5889",
    "sg:postcode":"18403",
    "sg:province":"PA",
    "wof:name":"Robert Lukeski",
    "wof:placetype":"venue"
},
  "geometry": {"coordinates":[-75.556872,41.48253],"type":"Point"}
}