{
  "type": "Feature",
  "properties": {
    "addr:full":"145 Mickley Rd Ste 2 Whitehall PA 18052",
    "addr:housenumber":"145",
    "addr:postcode":"18052",
    "addr:street":"Mickley Rd Ste 2",
    "iso:country":"US",
    "sg:address":"145 Mickley Rd Ste 2",
    "sg:city":"Whitehall",
    "sg:classifiers":[
        {
            "category":"Personal",
            "subcategory":"Nail Salon",
            "type":"Services"
        }
    ],
    "sg:phone":"+1 610 433 5800",
    "sg:postcode":"18052",
    "sg:province":"PA",
    "wof:name":"Absolute Hair Design",
    "wof:placetype":"venue"
},
  "geometry": {"coordinates":[-75.481397,40.620234],"type":"Point"}
}