{
  "type": "Feature",
  "properties": {
    "iso:country":"US",
    "sg:address":"521 S 9th St",
    "sg:city":"Philadelphia",
    "sg:classifiers":[
        {
            "category":"Professional",
            "type":"Services"
        }
    ],
    "sg:phone":"+1 215 923 4817",
    "sg:postcode":"19147",
    "sg:province":"PA",
    "sg:tags":[
        "establishment"
    ],
    "wof:name":"Galatic Odyssey",
    "wof:placetype":"venue"
},
  "geometry": {"coordinates":[-75.156981,39.942593],"type":"Point"}
}