{
  "type": "Feature",
  "properties": {
    "iso:country":"US",
    "sg:address":"4726 Durham Rd",
    "sg:city":"Doylestown",
    "sg:classifiers":[
        {
            "category":"Professional",
            "type":"Services"
        }
    ],
    "sg:phone":"+1   ",
    "sg:postcode":"18901",
    "sg:province":"PA",
    "wof:name":"J Scones Inc",
    "wof:placetype":"venue"
},
  "geometry": {"coordinates":[-75.108368,40.372306],"type":"Point"}
}