{
  "type": "Feature",
  "properties": {
    "addr:full":"334 Rte 356 Apollo PA 15613",
    "addr:housenumber":"334",
    "addr:postcode":"15613",
    "addr:street":"Rte 356",
    "iso:country":"US",
    "sg:address":"334 Rte 356",
    "sg:city":"Apollo",
    "sg:classifiers":[
        {
            "category":"Food & Beverages",
            "subcategory":"Bakery",
            "type":"Retail Goods"
        }
    ],
    "sg:phone":"+1 724 727 2674",
    "sg:postcode":"15613",
    "sg:province":"PA",
    "sg:tags":[
        "baker"
    ],
    "wof:name":"Gail's Ladylocks",
    "wof:placetype":"venue"
},
  "geometry": {"coordinates":[-79.59382600000001,40.575621],"type":"Point"}
}