{
  "type": "Feature",
  "properties": {
    "iso:country":"US",
    "sg:address":"1002 Attilio Ct",
    "sg:city":"Harrison City",
    "sg:classifiers":[
        {
            "category":"Building & Trades",
            "subcategory":"Construction",
            "type":"Services"
        }
    ],
    "sg:phone":"+1 724 744 0756",
    "sg:postcode":"15636",
    "sg:province":"PA",
    "sg:tags":[
        "heavy",
        "public",
        "utility"
    ],
    "wof:name":"Nicassio Enterprises Inc",
    "wof:placetype":"venue"
},
  "geometry": {"coordinates":[-79.653156,40.369566],"type":"Point"}
}