{
  "type": "Feature",
  "properties": {
    "iso:country":"US",
    "sg:address":"62 Taylor Rd",
    "sg:city":"Mc Donald",
    "sg:classifiers":[
        {
            "category":"Health Services",
            "subcategory":"Nursing And Care Facility",
            "type":"Services"
        }
    ],
    "sg:phone":"+1 724 796 6498",
    "sg:postcode":"15057",
    "sg:province":"PA",
    "sg:tags":[
        "personal",
        "home",
        "intermediate"
    ],
    "wof:name":"Mary's Place",
    "wof:placetype":"venue"
},
  "geometry": {"coordinates":[-80.27853500000001,40.3685],"type":"Point"}
}