{
  "type": "Feature",
  "properties": {
    "iso:country":"US",
    "sg:address":"1100 E Moyamensing Ave",
    "sg:city":"Philadelphia",
    "sg:classifiers":[
        {
            "category":"Autos & Motor Vehicles",
            "subcategory":"Auto Supplies",
            "type":"Retail Goods"
        }
    ],
    "sg:phone":"+1 215 467 8468",
    "sg:postcode":"19147",
    "sg:province":"PA",
    "sg:tags":[
        "glass",
        "window",
        "coating",
        "tinting"
    ],
    "wof:name":"Tintsmith",
    "wof:placetype":"venue"
},
  "geometry": {"coordinates":[-75.14821600000001,39.933762],"type":"Point"}
}