{
  "type": "Feature",
  "properties": {
    "iso:country":"US",
    "sg:address":"815 Mt Joy Rd",
    "sg:city":"Mt Joy",
    "sg:classifiers":[
        {
            "category":"Organizations",
            "subcategory":"Religious Organization",
            "type":"Services"
        }
    ],
    "sg:phone":"+1 717 653 1202",
    "sg:postcode":"17552",
    "sg:province":"PA",
    "sg:tags":[
        "church"
    ],
    "sg:website":"www.florincob.org",
    "wof:name":"Florin Church Of The Brethren",
    "wof:placetype":"venue"
},
  "geometry": {"coordinates":[-76.484601,40.121503],"type":"Point"}
}