{
  "type": "Feature",
  "properties": {
    "addr:full":"365 Manor Harrison City Rd Harrison City PA 15665",
    "addr:housenumber":"365",
    "addr:postcode":"15665",
    "addr:street":"Manor Harrison City Rd",
    "iso:country":"US",
    "sg:address":"365 Manor Harrison City Rd",
    "sg:city":"Harrison City",
    "sg:classifiers":[
        {
            "category":"Retail",
            "subcategory":"Auto Repair",
            "type":"Services"
        }
    ],
    "sg:phone":"+1   ",
    "sg:postcode":"15665",
    "sg:province":"PA",
    "sg:tags":[
        "body",
        "automotive",
        "shop"
    ],
    "wof:name":"All Vehicle Service Inc",
    "wof:placetype":"venue"
},
  "geometry": {"coordinates":[-79.67108,40.33647],"type":"Point"}
}