{
  "type": "Feature",
  "properties": {
    "iso:country":"US",
    "sg:address":"508 Harleysville Pike",
    "sg:city":"Harleysville",
    "sg:classifiers":[
        {
            "category":"Professional",
            "type":"Services"
        }
    ],
    "sg:phone":"+1 215 721 8900",
    "sg:postcode":"19438",
    "sg:province":"PA",
    "sg:tags":[
        "caterer"
    ],
    "wof:name":"Expressions Catering",
    "wof:placetype":"venue"
},
  "geometry": {"coordinates":[-75.39762,40.270225],"type":"Point"}
}