{
  "type": "Feature",
  "properties": {
    "iso:country":"US",
    "sg:address":"4000 Industrial Rd",
    "sg:city":"Harrisburg",
    "sg:classifiers":[
        {
            "category":"Wholesale",
            "subcategory":"Groceries",
            "type":"Manufacturing & Wholesale Goods"
        }
    ],
    "sg:phone":"+1   ",
    "sg:postcode":"17110",
    "sg:province":"PA",
    "sg:tags":[
        "frozen",
        "packaged",
        "general"
    ],
    "wof:name":"Sygma",
    "wof:placetype":"venue"
},
  "geometry": {"coordinates":[-76.88786399999999,40.313865],"type":"Point"}
}