{
  "type": "Feature",
  "properties": {
    "addr:full":"2640 Greenville Pike Grampian PA 16838",
    "addr:housenumber":"2640",
    "addr:postcode":"16838",
    "addr:street":"Greenville Pike",
    "iso:country":"US",
    "sg:address":"2640 Greenville Pike",
    "sg:city":"Grampian",
    "sg:classifiers":[
        {
            "category":"Home & Garden",
            "subcategory":"Building Materials",
            "type":"Retail Goods"
        }
    ],
    "sg:phone":"+1 814 236 2449",
    "sg:postcode":"16838",
    "sg:province":"PA",
    "sg:tags":[
        "stone",
        "product"
    ],
    "wof:name":"Russell Stone Products, Inc.",
    "wof:placetype":"venue"
},
  "geometry": {"coordinates":[-78.58835000000001,40.998521],"type":"Point"}
}