{
  "type": "Feature",
  "properties": {
    "addr:full":"2320 E Carson St Pittsburgh PA 15203",
    "addr:housenumber":"2320",
    "addr:postcode":"15203",
    "addr:street":"E Carson St",
    "iso:country":"US",
    "sg:address":"2320 E Carson St",
    "sg:city":"Pittsburgh",
    "sg:classifiers":[
        {
            "category":"Insurance",
            "subcategory":"Insurance Agent",
            "type":"Services"
        }
    ],
    "sg:phone":"+1 412 431 7166",
    "sg:postcode":"15203",
    "sg:province":"PA",
    "wof:name":"State Farm Insurance",
    "wof:placetype":"venue"
},
  "geometry": {"coordinates":[-79.971553,40.428157],"type":"Point"}
}