{
  "type": "Feature",
  "properties": {
    "addr:full":"2360 E Boston St Philadelphia PA 19125",
    "addr:housenumber":"2360",
    "addr:postcode":"19125",
    "addr:street":"E Boston St",
    "iso:country":"US",
    "sg:address":"2360 E Boston St",
    "sg:city":"Philadelphia",
    "sg:classifiers":[
        {
            "category":"Retail",
            "subcategory":"Animal Services",
            "type":"Services"
        }
    ],
    "sg:phone":"+1 215 425 4362",
    "sg:postcode":"19125",
    "sg:province":"PA",
    "sg:tags":[
        "pet",
        "boarding",
        "sitting"
    ],
    "wof:name":"Puppy Love Pet Sitting Group",
    "wof:placetype":"venue"
},
  "geometry": {"coordinates":[-75.12455300000001,39.978895],"type":"Point"}
}