{
  "type": "Feature",
  "properties": {
    "iso:country":"US",
    "sg:address":"506 Curtis Dr",
    "sg:city":"Morrisville",
    "sg:classifiers":[
        {
            "category":"Building & Trades",
            "subcategory":"Plumbing",
            "type":"Services"
        }
    ],
    "sg:phone":"+1 215 946 5881",
    "sg:postcode":"19067",
    "sg:province":"PA",
    "sg:tags":[
        "conditioning",
        "air",
        "system",
        "contractor"
    ],
    "wof:name":"Burns Heating & Cooling",
    "wof:placetype":"venue"
},
  "geometry": {"coordinates":[-74.80821,40.205152],"type":"Point"}
}