{
  "type": "Feature",
  "properties": {
    "addr:full":"555 Sandy Hill Rd Denver PA 17517",
    "addr:housenumber":"555",
    "addr:postcode":"17517",
    "addr:street":"Sandy Hill Rd",
    "iso:country":"US",
    "sg:address":"555 Sandy Hill Rd",
    "sg:city":"Denver",
    "sg:classifiers":[
        {
            "category":"Freight",
            "type":"Transportation"
        }
    ],
    "sg:phone":"+1 717 336 3900",
    "sg:postcode":"17517",
    "sg:province":"PA",
    "sg:tags":[
        "warehouse",
        "storage"
    ],
    "sg:website":"www.denvercoldstorage.com",
    "wof:name":"Denver Cold Storage",
    "wof:placetype":"venue"
},
  "geometry": {"coordinates":[-76.19924899999999,40.246781],"type":"Point"}
}