{
  "type": "Feature",
  "properties": {
    "iso:country":"US",
    "sg:address":"26 Manor Ave",
    "sg:city":"Millersville",
    "sg:classifiers":[
        {
            "category":"Food & Beverages",
            "subcategory":"Groceries & Convenience Stores",
            "type":"Retail Goods"
        }
    ],
    "sg:phone":"+1   ",
    "sg:postcode":"17551",
    "sg:province":"PA",
    "sg:tags":[
        "station",
        "gas"
    ],
    "wof:name":"Turkey Hill 48",
    "wof:placetype":"venue"
},
  "geometry": {"coordinates":[-76.35830900000001,40.008155],"type":"Point"}
}