{
  "type": "Feature",
  "properties": {
    "iso:country":"US",
    "sg:address":"416 N Keystone Ave",
    "sg:city":"Sayre",
    "sg:classifiers":[
        {
            "category":"Place Of Worship",
            "subcategory":"Church",
            "type":"Public Place"
        },
        {
            "category":"Place Of Worship",
            "type":"Public Place"
        },
        {
            "category":"Organizations",
            "subcategory":"Religious Organization",
            "type":"Services"
        }
    ],
    "sg:phone":"+1 570 888 9671",
    "sg:postcode":"18840",
    "sg:province":"PA",
    "sg:tags":[
        "god",
        "churches-church",
        "churches-pentecostal"
    ],
    "wof:name":"First Church Of God",
    "wof:placetype":"venue"
},
  "geometry": {"coordinates":[-76.528526,41.990261],"type":"Point"}
}