{
  "type": "Feature",
  "properties": {
    "addr:full":"2339 Neshaminy Blvd Bensalem PA 19020",
    "addr:housenumber":"2339",
    "addr:postcode":"19020",
    "addr:street":"Neshaminy Blvd",
    "iso:country":"US",
    "sg:address":"2339 Neshaminy Blvd",
    "sg:city":"Bensalem",
    "sg:classifiers":[
        {
            "category":"Food & Beverages",
            "subcategory":"Candy",
            "type":"Retail Goods"
        }
    ],
    "sg:phone":"+1 215 752 7441",
    "sg:postcode":"19020",
    "sg:province":"PA",
    "sg:tags":[
        "store"
    ],
    "sg:website":"www.thechocolatestore.com",
    "wof:name":"Gabe's Candy and Nut House",
    "wof:placetype":"venue"
},
  "geometry": {"coordinates":[-74.92420199999999,40.132099],"type":"Point"}
}