{
  "type": "Feature",
  "properties": {
    "iso:country":"US",
    "sg:address":"2181 Elizabethtown Rd",
    "sg:city":"Elizabethtown",
    "sg:classifiers":[
        {
            "category":"Building & Trades",
            "subcategory":"Construction",
            "type":"Services"
        }
    ],
    "sg:phone":"+1   ",
    "sg:postcode":"17022",
    "sg:province":"PA",
    "sg:tags":[
        "roofing",
        "contractor"
    ],
    "wof:name":"Hackman Brothers",
    "wof:placetype":"venue"
},
  "geometry": {"coordinates":[-76.551914,40.174811],"type":"Point"}
}