{
  "type": "Feature",
  "properties": {
    "iso:country":"US",
    "sg:address":"1615 Page St",
    "sg:city":"Allentown",
    "sg:classifiers":[
        {
            "category":"Building & Trades",
            "subcategory":"Cleaning & Sanitation",
            "type":"Services"
        }
    ],
    "sg:phone":"+1   ",
    "sg:postcode":"18102",
    "sg:province":"PA",
    "sg:tags":[
        "maintenance"
    ],
    "wof:name":"Sunshine Cleaning Service Inc",
    "wof:placetype":"venue"
},
  "geometry": {"coordinates":[-75.49582599999999,40.605416],"type":"Point"}
}