{
  "type": "Feature",
  "properties": {
    "iso:country":"US",
    "sg:address":"124 Fallowfield Ave",
    "sg:city":"Charleroi",
    "sg:classifiers":[
        {
            "category":"Health Services",
            "subcategory":"Chiropractor",
            "type":"Services"
        }
    ],
    "sg:phone":"+1   ",
    "sg:postcode":"15022",
    "sg:province":"PA",
    "wof:name":"Magic City Chiropractic",
    "wof:placetype":"venue"
},
  "geometry": {"coordinates":[-79.89461900000001,40.13481],"type":"Point"}
}