{
  "type": "Feature",
  "properties": {
    "iso:country":"US",
    "sg:address":"2232 Lebanon Valley Mall",
    "sg:city":"Lebanon",
    "sg:classifiers":[
        {
            "category":"Real Estate",
            "subcategory":"Real Estate Services",
            "type":"Services"
        }
    ],
    "sg:phone":"+1 717 279 7797",
    "sg:postcode":"17042",
    "sg:province":"PA",
    "sg:tags":[
        "company",
        "abstract",
        "title"
    ],
    "wof:name":"Eagle Real Estate Settlement S",
    "wof:placetype":"venue"
},
  "geometry": {"coordinates":[-76.453166,40.33976],"type":"Point"}
}