{
  "type": "Feature",
  "properties": {
    "iso:country":"US",
    "sg:address":"217 E Main St",
    "sg:city":"Camp Hill",
    "sg:classifiers":[
        {
            "category":"Shopping",
            "subcategory":"Computers & Home Electronics",
            "type":"Retail Goods"
        }
    ],
    "sg:phone":"+1 717 737 7967",
    "sg:postcode":"17011",
    "sg:province":"PA",
    "wof:name":"R & J Electronics",
    "wof:placetype":"venue"
},
  "geometry": {"coordinates":[-76.951401,40.2239],"type":"Point"}
}