{
  "type": "Feature",
  "properties": {
    "iso:country":"US",
    "sg:address":"7006 Van Camp Rd",
    "sg:city":"Girard",
    "sg:classifiers":[
        {
            "category":"Manufacturing",
            "subcategory":"Metals",
            "type":"Manufacturing & Wholesale Goods"
        }
    ],
    "sg:phone":"+1 814 474 2624",
    "sg:postcode":"16417",
    "sg:province":"PA",
    "sg:tags":[
        "bronze"
    ],
    "wof:name":"Mazzo's Memorials & Bronze",
    "wof:placetype":"venue"
},
  "geometry": {"coordinates":[-80.209159,41.984165],"type":"Point"}
}