{
  "type": "Feature",
  "properties": {
    "iso:country":"US",
    "sg:address":"103 Sunshine Ave",
    "sg:city":"Central City",
    "sg:classifiers":[
        {
            "category":"Social Services",
            "type":"Services"
        }
    ],
    "sg:phone":"+1 814 754 5615",
    "sg:postcode":"15926",
    "sg:province":"PA",
    "sg:tags":[
        "senior",
        "citizen"
    ],
    "wof:name":"Central City Senior Ctr",
    "wof:placetype":"venue"
},
  "geometry": {"coordinates":[-78.806166,40.107996],"type":"Point"}
}