{
  "type": "Feature",
  "properties": {
    "addr:full":"941 Grosstown Rd Pottstown PA 19464",
    "addr:housenumber":"941",
    "addr:postcode":"19464",
    "addr:street":"Grosstown Rd",
    "iso:country":"US",
    "sg:address":"941 Grosstown Rd",
    "sg:city":"Pottstown",
    "sg:classifiers":[
        {
            "category":"Building & Trades",
            "subcategory":"Construction",
            "type":"Services"
        }
    ],
    "sg:phone":"+1   ",
    "sg:postcode":"19464",
    "sg:province":"PA",
    "sg:tags":[
        "house"
    ],
    "wof:name":"Matthew Butts General Contg",
    "wof:placetype":"venue"
},
  "geometry": {"coordinates":[-75.675747,40.260842],"type":"Point"}
}