{
  "type": "Feature",
  "properties": {
    "iso:country":"US",
    "sg:address":"1281 Kramer Mill Rd",
    "sg:city":"Denver",
    "sg:classifiers":[
        {
            "category":"Manufacturing",
            "subcategory":"Chemicals & Compounds",
            "type":"Manufacturing & Wholesale Goods"
        }
    ],
    "sg:phone":"+1 717 336 3641",
    "sg:postcode":"17517",
    "sg:province":"PA",
    "sg:tags":[
        "cleaning"
    ],
    "wof:name":"Stanley Home Products",
    "wof:placetype":"venue"
},
  "geometry": {"coordinates":[-76.081705,40.203237],"type":"Point"}
}