{
  "type": "Feature",
  "properties": {
    "iso:country":"US",
    "sg:address":"4202 Dion Ct",
    "sg:city":"Erie",
    "sg:classifiers":[
        {
            "category":"Professional",
            "subcategory":"Management & Consulting",
            "type":"Services"
        }
    ],
    "sg:phone":"+1 814 833 9909",
    "sg:postcode":"16506",
    "sg:province":"PA",
    "sg:tags":[
        "consultant"
    ],
    "wof:name":"Verocomp Professional Services",
    "wof:placetype":"venue"
},
  "geometry": {"coordinates":[-80.162508,42.060465],"type":"Point"}
}