{
  "type": "Feature",
  "properties": {
    "addr:full":"1640 E Pleasant Valley Blvd Altoona PA 16602",
    "addr:housenumber":"1640",
    "addr:postcode":"16602",
    "addr:street":"E Pleasant Valley Blvd",
    "iso:country":"US",
    "sg:address":"1640 E Pleasant Valley Blvd",
    "sg:city":"Altoona",
    "sg:classifiers":[
        {
            "category":"Shopping",
            "subcategory":"Stationery & Office Supplies",
            "type":"Retail Goods"
        },
        {
            "category":"Home & Garden",
            "subcategory":"Furniture",
            "type":"Retail Goods"
        }
    ],
    "sg:phone":"+1 814 943 1660",
    "sg:postcode":"16602",
    "sg:province":"PA",
    "sg:tags":[
        "machine",
        "repair",
        "business"
    ],
    "sg:website":"www.ellisofficesupply.com",
    "wof:name":"Ellis Office Supply Inc",
    "wof:placetype":"venue"
},
  "geometry": {"coordinates":[-78.355503,40.539518],"type":"Point"}
}