{
  "type": "Feature",
  "properties": {
    "iso:country":"US",
    "sg:address":"356 N Franklin St",
    "sg:city":"Limerick",
    "sg:classifiers":[
        {
            "category":"Building & Trades",
            "subcategory":"Construction",
            "type":"Services"
        }
    ],
    "sg:phone":"+1 610 489 4125",
    "sg:postcode":"19464",
    "sg:province":"PA",
    "sg:tags":[
        "resurfacing",
        "laying",
        "refinishing",
        "floor"
    ],
    "wof:name":"Stan's Linoleum & Tile Co",
    "wof:placetype":"venue"
},
  "geometry": {"coordinates":[-75.641987,40.251196],"type":"Point"}
}