{
  "type": "Feature",
  "properties": {
    "addr:full":"3860 Jeffrey Rd Huntingdon Valley PA 19006",
    "addr:housenumber":"3860",
    "addr:postcode":"19006",
    "addr:street":"Jeffrey Rd",
    "iso:country":"US",
    "sg:address":"3860 Jeffrey Rd",
    "sg:city":"Huntingdon Valley",
    "sg:classifiers":[
        {
            "category":"Building & Trades",
            "subcategory":"Construction",
            "type":"Services"
        }
    ],
    "sg:phone":"+1   ",
    "sg:postcode":"19006",
    "sg:province":"PA",
    "sg:tags":[
        "contractor"
    ],
    "wof:name":"Earl W Peters & Sons Inc",
    "wof:placetype":"venue"
},
  "geometry": {"coordinates":[-75.03499100000001,40.14588],"type":"Point"}
}