{
  "type": "Feature",
  "properties": {
    "addr:full":"708 N Shady Retreat Rd Ste 9 Doylestown PA 18901",
    "addr:housenumber":"708",
    "addr:postcode":"18901",
    "addr:street":"N Shady Retreat Rd Ste 9",
    "iso:country":"US",
    "sg:address":"708 N Shady Retreat Rd Ste 9",
    "sg:city":"Doylestown",
    "sg:classifiers":[
        {
            "category":"Health Services",
            "subcategory":"Doctor",
            "type":"Services"
        }
    ],
    "sg:phone":"+1 215 348 7238",
    "sg:postcode":"18901",
    "sg:province":"PA",
    "wof:name":"Gastroenterology Associates of Bcks & Mntgmry Cnts",
    "wof:placetype":"venue"
},
  "geometry": {"coordinates":[-75.148903,40.312599],"type":"Point"}
}