{
  "type": "Feature",
  "properties": {
    "addr:full":"147 Georgetown Rd Littlestown PA 17340",
    "addr:housenumber":"147",
    "addr:postcode":"17340",
    "addr:street":"Georgetown Rd",
    "iso:country":"US",
    "sg:address":"147 Georgetown Rd",
    "sg:city":"Littlestown",
    "sg:classifiers":[
        {
            "category":"Freight",
            "type":"Transportation"
        }
    ],
    "sg:phone":"+1   ",
    "sg:postcode":"17340",
    "sg:province":"PA",
    "sg:tags":[
        "operator",
        "local",
        "trucking"
    ],
    "wof:name":"C & S Trucking",
    "wof:placetype":"venue"
},
  "geometry": {"coordinates":[-77.113174,39.723108],"type":"Point"}
}