{
  "type": "Feature",
  "properties": {
    "iso:country":"US",
    "sg:address":"5227 Brook Dr",
    "sg:city":"East Petersburg",
    "sg:classifiers":[
        {
            "category":"Shopping",
            "subcategory":"Used Merchandise",
            "type":"Retail Goods"
        }
    ],
    "sg:phone":"+1   ",
    "sg:postcode":"17520",
    "sg:province":"PA",
    "sg:tags":[
        "computer"
    ],
    "wof:name":"Barr Robert Consulting",
    "wof:placetype":"venue"
},
  "geometry": {"coordinates":[-76.342399,40.092579],"type":"Point"}
}