{
  "type": "Feature",
  "properties": {
    "iso:country":"US",
    "sg:address":"51 E Crone Rd",
    "sg:city":"York",
    "sg:classifiers":[
        {
            "category":"Autos & Motor Vehicles",
            "subcategory":"Recreational Vehicle Sales",
            "type":"Retail Goods"
        },
        {
            "category":"Building & Trades",
            "subcategory":"Equipment Rental",
            "type":"Services"
        },
        {
            "category":"Building & Trades",
            "subcategory":"Construction",
            "type":"Services"
        },
        {
            "category":"Manufacturing",
            "subcategory":"Building Materials",
            "type":"Manufacturing & Wholesale Goods"
        },
        {
            "category":"Home & Garden",
            "subcategory":"Carpets & Floor Coverings",
            "type":"Retail Goods"
        }
    ],
    "sg:phone":"+1 717 815 6900",
    "sg:postcode":"17406",
    "sg:province":"PA",
    "sg:tags":[
        "repairing",
        "oil",
        "aerial",
        "scaffolding",
        "field",
        "automobile",
        "rigger",
        "cranes-mobile",
        "facilities-renting",
        "lift",
        "crane"
    ],
    "wof:name":"Eisenhart Crane",
    "wof:placetype":"venue"
},
  "geometry": {"coordinates":[-76.743967,40.028762],"type":"Point"}
}