{
  "type": "Feature",
  "properties": {
    "iso:country":"US",
    "sg:address":"101 Greenwood Ave",
    "sg:city":"Jenkintown",
    "sg:classifiers":[
        {
            "category":"Professional",
            "subcategory":"Management & Consulting",
            "type":"Services"
        }
    ],
    "sg:phone":"+1 215 886 9200",
    "sg:postcode":"19046",
    "sg:province":"PA",
    "sg:tags":[
        "marketing",
        "consultant"
    ],
    "sg:website":"www.tnstelecoms.com",
    "wof:name":"TNS Telecoms",
    "wof:placetype":"venue"
},
  "geometry": {"coordinates":[-75.133685,40.093506],"type":"Point"}
}