{
  "type": "Feature",
  "properties": {
    "iso:country":"US",
    "sg:address":"6412 Old William Penn Hwy",
    "sg:city":"Delmont",
    "sg:classifiers":[
        {
            "category":"Building & Trades",
            "subcategory":"Construction",
            "type":"Services"
        }
    ],
    "sg:phone":"+1 724 468 6111",
    "sg:postcode":"15626",
    "sg:province":"PA",
    "sg:tags":[
        "excavation",
        "contractor",
        "general"
    ],
    "wof:name":"Danmar Contracting Inc",
    "wof:placetype":"venue"
},
  "geometry": {"coordinates":[-79.58466199999999,40.416812],"type":"Point"}
}