{
  "type": "Feature",
  "properties": {
    "iso:country":"US",
    "sg:address":"97 Sam Brooke Cir",
    "sg:city":"Lehighton",
    "sg:classifiers":[
        {
            "category":"Shopping",
            "subcategory":"Mobile Phones",
            "type":"Retail Goods"
        },
        {
            "category":"Building & Trades",
            "subcategory":"Construction",
            "type":"Services"
        }
    ],
    "sg:phone":"+1 570 386 9222",
    "sg:postcode":"18235",
    "sg:province":"PA",
    "sg:tags":[
        "manufactured",
        "housing-communities",
        "home"
    ],
    "wof:name":"Northside Heights Estates Inc",
    "wof:placetype":"venue"
},
  "geometry": {"coordinates":[-75.758886,40.759936],"type":"Point"}
}