{
  "type": "Feature",
  "properties": {
    "iso:country":"US",
    "sg:address":"2349 Railroad St",
    "sg:city":"Pittsburgh",
    "sg:classifiers":[
        {
            "category":"Professional",
            "subcategory":"Research",
            "type":"Services"
        }
    ],
    "sg:phone":"+1 412 434 4775",
    "sg:postcode":"15222",
    "sg:province":"PA",
    "sg:tags":[
        "environmental",
        "ecological"
    ],
    "wof:name":"Zax Environmental",
    "wof:placetype":"venue"
},
  "geometry": {"coordinates":[-79.982692,40.454512],"type":"Point"}
}