{
  "type": "Feature",
  "properties": {
    "iso:country":"US",
    "sg:address":"649 2nd Street Pike",
    "sg:city":"Southampton",
    "sg:classifiers":[
        {
            "category":"Shopping",
            "subcategory":"Music",
            "type":"Retail Goods"
        }
    ],
    "sg:phone":"+1 215 322 5551",
    "sg:postcode":"18966",
    "sg:province":"PA",
    "sg:tags":[
        "video",
        "disc",
        "tape",
        "cassette"
    ],
    "wof:name":"Newtown Video Distributors",
    "wof:placetype":"venue"
},
  "geometry": {"coordinates":[-75.044123,40.173078],"type":"Point"}
}