{
  "type": "Feature",
  "properties": {
    "iso:country":"US",
    "sg:address":"204 N 60th St",
    "sg:city":"Philadelphia",
    "sg:classifiers":[
        {
            "category":"Personal",
            "subcategory":"Beauty Salon",
            "type":"Services"
        }
    ],
    "sg:phone":"+1 215 471 1954",
    "sg:postcode":"19139",
    "sg:province":"PA",
    "wof:name":"Big Bumper's Beauty Salon",
    "wof:placetype":"venue"
},
  "geometry": {"coordinates":[-75.240111,39.965382],"type":"Point"}
}