{
  "type": "Feature",
  "properties": {
    "iso:country":"US",
    "sg:address":"1011 George St",
    "sg:city":"Easton",
    "sg:classifiers":[
        {
            "category":"Real Estate",
            "subcategory":"Real Estate Operator",
            "type":"Services"
        }
    ],
    "sg:phone":"+1 610 923 5024",
    "sg:postcode":"18040",
    "sg:province":"PA",
    "sg:tags":[
        "apartment"
    ],
    "wof:name":"Lafayette Hills Apartments",
    "wof:placetype":"venue"
},
  "geometry": {"coordinates":[-75.22407200000001,40.706711],"type":"Point"}
}