{
  "type": "Feature",
  "properties": {
    "addr:full":"131 W State St Ste D Doylestown PA 18901",
    "addr:housenumber":"131",
    "addr:postcode":"18901",
    "addr:street":"W State St Ste D",
    "iso:country":"US",
    "sg:address":"131 W State St Ste D",
    "sg:city":"Doylestown",
    "sg:classifiers":[
        {
            "category":"Health Services",
            "subcategory":"Doctor",
            "type":"Services"
        }
    ],
    "sg:phone":"+1 215 345 7272",
    "sg:postcode":"18901",
    "sg:province":"PA",
    "sg:tags":[
        "surgeon",
        "oral"
    ],
    "wof:name":"Rokita John R DDS",
    "wof:placetype":"venue"
},
  "geometry": {"coordinates":[-75.133202,40.308701],"type":"Point"}
}