{
  "type": "Feature",
  "properties": {
    "iso:country":"US",
    "sg:address":"917 Columbia Ave",
    "sg:city":"Lancaster",
    "sg:classifiers":[
        {
            "category":"Professional",
            "subcategory":"Business Services",
            "type":"Services"
        }
    ],
    "sg:phone":"+1 717 295 1887",
    "sg:postcode":"17603",
    "sg:province":"PA",
    "sg:tags":[
        "recording",
        "studio"
    ],
    "wof:name":"Lab Rat Records",
    "wof:placetype":"venue"
},
  "geometry": {"coordinates":[-76.324206,40.038366],"type":"Point"}
}