{
  "type": "Feature",
  "properties": {
    "addr:full":"106 W Main St Landisville PA 17538",
    "addr:housenumber":"106",
    "addr:postcode":"17538",
    "addr:street":"W Main St",
    "iso:country":"US",
    "sg:address":"106 W Main St",
    "sg:city":"Landisville",
    "sg:classifiers":[
        {
            "category":"Shopping",
            "subcategory":"Hobbies, Toys, & Games",
            "type":"Retail Goods"
        }
    ],
    "sg:phone":"+1   ",
    "sg:postcode":"17538",
    "sg:province":"PA",
    "wof:name":"Cooltrainscom",
    "wof:placetype":"venue"
},
  "geometry": {"coordinates":[-76.427187,40.101618],"type":"Point"}
}