{
  "type": "Feature",
  "properties": {
    "addr:full":"100 Stanford Dr Newtown PA 18940",
    "addr:housenumber":"100",
    "addr:postcode":"18940",
    "addr:street":"Stanford Dr",
    "iso:country":"US",
    "sg:address":"100 Stanford Dr",
    "sg:city":"Newtown",
    "sg:classifiers":[
        {
            "category":"Organizations",
            "subcategory":"Community Association",
            "type":"Services"
        }
    ],
    "sg:phone":"+1 215 497 0537",
    "sg:postcode":"18940",
    "sg:province":"PA",
    "sg:tags":[
        "club"
    ],
    "wof:name":"Raintree Swim Club",
    "wof:placetype":"venue"
},
  "geometry": {"coordinates":[-74.920357,40.232058],"type":"Point"}
}