{
  "type": "Feature",
  "properties": {
    "iso:country":"US",
    "sg:address":"306 Erie St",
    "sg:city":"Edinboro",
    "sg:classifiers":[
        {
            "category":"Organizations",
            "subcategory":"Religious Organization",
            "type":"Services"
        }
    ],
    "sg:phone":"+1 814 734 5005",
    "sg:postcode":"16412",
    "sg:province":"PA",
    "sg:tags":[
        "church"
    ],
    "wof:name":"Living Waters Assembly Of God",
    "wof:placetype":"venue"
},
  "geometry": {"coordinates":[-80.13009700000001,41.879286],"type":"Point"}
}