{
  "type": "Feature",
  "properties": {
    "iso:country":"US",
    "sg:address":"415 N 4th St",
    "sg:city":"Philipsburg",
    "sg:classifiers":[
        {
            "category":"Bus Charters",
            "type":"Transportation"
        }
    ],
    "sg:phone":"+1 814 342 1930",
    "sg:postcode":"16866",
    "sg:province":"PA",
    "sg:tags":[
        "rental"
    ],
    "wof:name":"Fullington Auto Bus Co",
    "wof:placetype":"venue"
},
  "geometry": {"coordinates":[-78.22260300000001,40.900569],"type":"Point"}
}