{
  "type": "Feature",
  "properties": {
    "iso:country":"US",
    "sg:address":"1100 Merlo St",
    "sg:city":"Nanty Glo",
    "sg:classifiers":[
        {
            "category":"Shopping",
            "subcategory":"Bicycles & Sporting Goods",
            "type":"Retail Goods"
        }
    ],
    "sg:phone":"+1   ",
    "sg:postcode":"15943",
    "sg:province":"PA",
    "wof:name":"Bobs Gun Shop",
    "wof:placetype":"venue"
},
  "geometry": {"coordinates":[-78.830201,40.476886],"type":"Point"}
}