{
  "type": "Feature",
  "properties": {
    "iso:country":"US",
    "sg:address":"401 S 45th St",
    "sg:city":"Philadelphia",
    "sg:classifiers":[
        {
            "category":"Personal",
            "type":"Services"
        },
        {
            "category":"Retail",
            "subcategory":"Laundry & Dry Cleaning",
            "type":"Services"
        }
    ],
    "sg:phone":"+1 215 823 6863",
    "sg:postcode":"19104",
    "sg:province":"PA",
    "sg:tags":[
        "sewing",
        "alteration"
    ],
    "wof:name":"Spruce Hill Cleaners",
    "wof:placetype":"venue"
},
  "geometry": {"coordinates":[-75.212417,39.951752],"type":"Point"}
}