{
  "type": "Feature",
  "properties": {
    "iso:country":"US",
    "sg:address":"301 5th Ave",
    "sg:city":"Mc Keesport",
    "sg:classifiers":[
        {
            "category":"Professional",
            "subcategory":"Lawyer & Legal Services",
            "type":"Services"
        }
    ],
    "sg:phone":"+1   ",
    "sg:postcode":"15132",
    "sg:province":"PA",
    "sg:tags":[
        "executive"
    ],
    "wof:name":"McKeesport City Treasurer",
    "wof:placetype":"venue"
},
  "geometry": {"coordinates":[-79.864271,40.351071],"type":"Point"}
}