{
  "type": "Feature",
  "properties": {
    "iso:country":"US",
    "sg:address":"610 W Rte 897",
    "sg:city":"Reinholds",
    "sg:classifiers":[
        {
            "category":"Restaurant",
            "type":"Food & Drink"
        }
    ],
    "sg:phone":"+1 717 336 7355",
    "sg:postcode":"17569",
    "sg:province":"PA",
    "sg:tags":[
        "eating",
        "vehicle"
    ],
    "wof:name":"Kountry Korner Drive-In",
    "wof:placetype":"venue"
},
  "geometry": {"coordinates":[-76.136698,40.276149],"type":"Point"}
}