{
  "type": "Feature",
  "properties": {
    "addr:full":"5549 Oakwood Dr Mercersburg PA 17236",
    "addr:housenumber":"5549",
    "addr:postcode":"17236",
    "addr:street":"Oakwood Dr",
    "iso:country":"US",
    "sg:address":"5549 Oakwood Dr",
    "sg:city":"Mercersburg",
    "sg:classifiers":[
        {
            "category":"Personal",
            "subcategory":"Beauty Salon",
            "type":"Services"
        }
    ],
    "sg:phone":"+1 717 328 3921",
    "sg:postcode":"17236",
    "sg:province":"PA",
    "wof:name":"Joyce Wolfe Beauty Shop",
    "wof:placetype":"venue"
},
  "geometry": {"coordinates":[-77.909336,39.841065],"type":"Point"}
}