{
  "type": "Feature",
  "properties": {
    "addr:full":"829 State St Lemoyne PA 17043",
    "addr:housenumber":"829",
    "addr:postcode":"17043",
    "addr:street":"State St",
    "iso:country":"US",
    "sg:address":"829 State St",
    "sg:city":"Lemoyne",
    "sg:classifiers":[
        {
            "category":"Shopping",
            "subcategory":"Florist",
            "type":"Retail Goods"
        }
    ],
    "sg:phone":"+1 717 731 0732",
    "sg:postcode":"17043",
    "sg:province":"PA",
    "wof:name":"Bixler Flowers & Gifts",
    "wof:placetype":"venue"
},
  "geometry": {"coordinates":[-76.900854,40.2427],"type":"Point"}
}