{
  "type": "Feature",
  "properties": {
    "iso:country":"US",
    "sg:address":"12 E 9th St",
    "sg:city":"Erie",
    "sg:classifiers":[
        {
            "category":"Professional",
            "subcategory":"Engineering",
            "type":"Services"
        }
    ],
    "sg:phone":"+1   ",
    "sg:postcode":"16501",
    "sg:province":"PA",
    "wof:name":"Tesinc",
    "wof:placetype":"venue"
},
  "geometry": {"coordinates":[-80.08194899999999,42.127002],"type":"Point"}
}