{
  "type": "Feature",
  "properties": {
    "iso:country":"US",
    "sg:address":"206 Fawn Ct",
    "sg:city":"Pittsburgh",
    "sg:classifiers":[
        {
            "category":"Building & Trades",
            "subcategory":"Construction",
            "type":"Services"
        }
    ],
    "sg:phone":"+1   ",
    "sg:postcode":"15239",
    "sg:province":"PA",
    "sg:tags":[
        "excavation",
        "contractor"
    ],
    "wof:name":"J Martin Excavating",
    "wof:placetype":"venue"
},
  "geometry": {"coordinates":[-79.720012,40.458791],"type":"Point"}
}