{
  "type": "Feature",
  "properties": {
    "iso:country":"US",
    "sg:address":"124 Donald Ln",
    "sg:city":"Johnstown",
    "sg:classifiers":[
        {
            "category":"Professional",
            "type":"Services"
        }
    ],
    "sg:phone":"+1   ",
    "sg:postcode":"15904",
    "sg:province":"PA",
    "wof:name":"Jmjj Incorporated",
    "wof:placetype":"venue"
},
  "geometry": {"coordinates":[-78.83968299999999,40.285309],"type":"Point"}
}