{
  "type": "Feature",
  "properties": {
    "addr:full":"748 Pershing St Ellwood City PA 16117",
    "addr:housenumber":"748",
    "addr:postcode":"16117",
    "addr:street":"Pershing St",
    "iso:country":"US",
    "sg:address":"748 Pershing St",
    "sg:city":"Ellwood City",
    "sg:classifiers":[
        {
            "category":"Health Services",
            "subcategory":"Health Practitioner",
            "type":"Services"
        }
    ],
    "sg:phone":"+1   ",
    "sg:postcode":"16117",
    "sg:province":"PA",
    "wof:name":"Elwood Medical Group",
    "wof:placetype":"venue"
},
  "geometry": {"coordinates":[-80.27457699999999,40.870233],"type":"Point"}
}