{
  "type": "Feature",
  "properties": {
    "addr:full":"8 Ironwood St Tunkhannock PA 18657",
    "addr:housenumber":"8",
    "addr:postcode":"18657",
    "addr:street":"Ironwood St",
    "iso:country":"US",
    "sg:address":"8 Ironwood St",
    "sg:city":"Tunkhannock",
    "sg:classifiers":[
        {
            "category":"Organizations",
            "subcategory":"Community Association",
            "type":"Services"
        }
    ],
    "sg:phone":"+1 570 836 6552",
    "sg:postcode":"18657",
    "sg:province":"PA",
    "sg:tags":[
        "club"
    ],
    "sg:website":"http://www.wyomingcountyunitedway.org",
    "wof:name":"Wyoming County Cancer Society Inc",
    "wof:placetype":"venue"
},
  "geometry": {"coordinates":[-75.93953500000001,41.513834],"type":"Point"}
}