{
  "type": "Feature",
  "properties": {
    "iso:country":"US",
    "sg:address":"1720 Sumneytown Pike",
    "sg:city":"Kulpsville",
    "sg:classifiers":[
        {
            "category":"Professional",
            "subcategory":"Detective & Security Services",
            "type":"Services"
        }
    ],
    "sg:phone":"+1 215 362 0200",
    "sg:postcode":"19446",
    "sg:province":"PA",
    "sg:tags":[
        "investigator"
    ],
    "wof:name":"Geib Associates Inc",
    "wof:placetype":"venue"
},
  "geometry": {"coordinates":[-75.340349,40.244907],"type":"Point"}
}