{
  "type": "Feature",
  "properties": {
    "addr:full":"139 E Butler Ave Ambler PA 19002",
    "addr:housenumber":"139",
    "addr:postcode":"19002",
    "addr:street":"E Butler Ave",
    "iso:country":"US",
    "sg:address":"139 E Butler Ave",
    "sg:city":"Ambler",
    "sg:classifiers":[
        {
            "category":"Manufacturing",
            "subcategory":"Printing",
            "type":"Manufacturing & Wholesale Goods"
        }
    ],
    "sg:phone":"+1   ",
    "sg:postcode":"19002",
    "sg:province":"PA",
    "sg:tags":[
        "book",
        "periodical"
    ],
    "wof:name":"Henry Songs Laundry Mat",
    "wof:placetype":"venue"
},
  "geometry": {"coordinates":[-75.221205,40.154894],"type":"Point"}
}