{
  "type": "Feature",
  "properties": {
    "iso:country":"US",
    "sg:address":"125 Strafford Ave",
    "sg:city":"Wayne",
    "sg:classifiers":[
        {
            "category":"Professional",
            "subcategory":"Management & Consulting",
            "type":"Services"
        },
        {
            "category":"Insurance",
            "subcategory":"Insurance Agent",
            "type":"Services"
        }
    ],
    "sg:phone":"+1 610 225 1990",
    "sg:postcode":"19087",
    "sg:province":"PA",
    "sg:tags":[
        "consultant",
        "business"
    ],
    "wof:name":"Patricia M Salmon & Associates",
    "wof:placetype":"venue"
},
  "geometry": {"coordinates":[-75.39801199999999,40.044532],"type":"Point"}
}