{
  "type": "Feature",
  "properties": {
    "iso:country":"US",
    "sg:address":"457 York Rd",
    "sg:city":"Solebury",
    "sg:classifiers":[
        {
            "category":"Retail",
            "subcategory":"Auto Repair",
            "type":"Services"
        }
    ],
    "sg:phone":"+1 215 862 7070",
    "sg:postcode":"18938",
    "sg:province":"PA",
    "wof:name":"Car Doctor",
    "wof:placetype":"venue"
},
  "geometry": {"coordinates":[-74.97190000000001,40.360632],"type":"Point"}
}