{
  "type": "Feature",
  "properties": {
    "addr:full":"13 Colten Dr Cochranville PA 19330",
    "addr:housenumber":"13",
    "addr:postcode":"19330",
    "addr:street":"Colten Dr Cochranville",
    "iso:country":"US",
    "sg:address":"13 Colten Dr",
    "sg:city":"Cochranville",
    "sg:classifiers":[
        {
            "category":"Insurance",
            "subcategory":"Insurance Agent",
            "type":"Services"
        }
    ],
    "sg:phone":"+1   ",
    "sg:postcode":"19330",
    "sg:province":"PA",
    "wof:name":"Cummings & Associates",
    "wof:placetype":"venue"
},
  "geometry": {"coordinates":[-75.875202,39.861062],"type":"Point"}
}