{
  "type": "Feature",
  "properties": {
    "iso:country":"US",
    "sg:address":"415 Constance Dr",
    "sg:city":"Warminster",
    "sg:classifiers":[
        {
            "category":"Building & Trades",
            "subcategory":"Construction",
            "type":"Services"
        }
    ],
    "sg:phone":"+1 215 674 8185",
    "sg:postcode":"18974",
    "sg:province":"PA",
    "sg:tags":[
        "pool",
        "maintenance",
        "swimming"
    ],
    "sg:website":"www.carltonpools.com",
    "wof:name":"Carlton Pools Inc",
    "wof:placetype":"venue"
},
  "geometry": {"coordinates":[-75.089427,40.205337],"type":"Point"}
}