{
  "type": "Feature",
  "properties": {
    "addr:full":"4960 Carlisle Pike Mechanicsburg PA 17050",
    "addr:housenumber":"4960",
    "addr:postcode":"17050",
    "addr:street":"Carlisle Pike",
    "iso:country":"US",
    "sg:address":"4960 Carlisle Pike",
    "sg:city":"Mechanicsburg",
    "sg:classifiers":[
        {
            "category":"Restaurant",
            "type":"Food & Drink"
        }
    ],
    "sg:phone":"+1   ",
    "sg:postcode":"17050",
    "sg:province":"PA",
    "sg:tags":[
        "eating"
    ],
    "wof:name":"Pizza Hut",
    "wof:placetype":"venue"
},
  "geometry": {"coordinates":[-76.97341299999999,40.237222],"type":"Point"}
}