{
  "type": "Feature",
  "properties": {
    "iso:country":"US",
    "sg:address":"8375 Enterprise Ave",
    "sg:city":"Philadelphia",
    "sg:classifiers":[
        {
            "category":"Airline",
            "type":"Transportation"
        }
    ],
    "sg:phone":"+1 215 492 7060",
    "sg:postcode":"19153",
    "sg:province":"PA",
    "sg:tags":[
        "airport"
    ],
    "wof:name":"Atlantic Aviation",
    "wof:placetype":"venue"
},
  "geometry": {"coordinates":[-75.223198,39.883701],"type":"Point"}
}