{
  "type": "Feature",
  "properties": {
    "iso:country":"US",
    "sg:address":"29 E Bridge St",
    "sg:city":"Morrisville",
    "sg:classifiers":[
        {
            "category":"Freight",
            "type":"Transportation"
        }
    ],
    "sg:phone":"+1 215 295 6500",
    "sg:postcode":"19067",
    "sg:province":"PA",
    "sg:tags":[
        "arrangement"
    ],
    "wof:name":"Direct Line Designs",
    "wof:placetype":"venue"
},
  "geometry": {"coordinates":[-74.77515099999999,40.20819],"type":"Point"}
}