{
  "type": "Feature",
  "properties": {
    "iso:country":"US",
    "sg:address":"212 Huckleberry Ct",
    "sg:city":"Wexford",
    "sg:classifiers":[
        {
            "category":"Shopping",
            "subcategory":"Used Merchandise",
            "type":"Retail Goods"
        }
    ],
    "sg:phone":"+1   ",
    "sg:postcode":"15090",
    "sg:province":"PA",
    "sg:tags":[
        "antique",
        "specializing",
        "art",
        "century",
        "item",
        "fine"
    ],
    "wof:name":"So Rare Galleries",
    "wof:placetype":"venue"
},
  "geometry": {"coordinates":[-80.095697,40.638935],"type":"Point"}
}