{
  "type": "Feature",
  "properties": {
    "iso:country":"US",
    "sg:address":"904 N Main St",
    "sg:city":"Punxsutawney",
    "sg:classifiers":[
        {
            "category":"Communications",
            "subcategory":"Radio Station",
            "type":"Services"
        }
    ],
    "sg:phone":"+1   ",
    "sg:postcode":"15767",
    "sg:province":"PA",
    "sg:tags":[
        "broadcasting"
    ],
    "wof:name":"Wpxz-FM Station",
    "wof:placetype":"venue"
},
  "geometry": {"coordinates":[-79.001875,40.957672],"type":"Point"}
}