{
  "type": "Feature",
  "properties": {
    "iso:country":"US",
    "sg:address":"3203 Fairway Dr",
    "sg:city":"Altoona",
    "sg:classifiers":[
        {
            "category":"Home & Garden",
            "subcategory":"Furniture",
            "type":"Retail Goods"
        }
    ],
    "sg:phone":"+1 814 942 1900",
    "sg:postcode":"16602",
    "sg:province":"PA",
    "wof:name":"Capperella Furniture",
    "wof:placetype":"venue"
},
  "geometry": {"coordinates":[-78.39515299999999,40.483906],"type":"Point"}
}