{
  "type": "Feature",
  "properties": {
    "iso:country":"US",
    "sg:address":"171 N Mount Joy St",
    "sg:city":"Elizabethtown",
    "sg:classifiers":[
        {
            "category":"Government",
            "subcategory":"Fire Station",
            "type":"Public Place"
        }
    ],
    "sg:phone":"+1 717 367 5300",
    "sg:postcode":"17022",
    "sg:province":"PA",
    "sg:tags":[
        "department"
    ],
    "sg:website":"www.efd74.com",
    "wof:name":"Friendship Fire & Hose Co",
    "wof:placetype":"venue"
},
  "geometry": {"coordinates":[-76.600646,40.155797],"type":"Point"}
}