{
  "type": "Feature",
  "properties": {
    "iso:country":"US",
    "sg:address":"205 S Main St",
    "sg:city":"Sharpsburg",
    "sg:classifiers":[
        {
            "category":"Professional",
            "type":"Services"
        }
    ],
    "sg:phone":"+1 412 937 3677",
    "sg:postcode":"15215",
    "sg:province":"PA",
    "sg:tags":[
        "establishment"
    ],
    "wof:name":"James Centre",
    "wof:placetype":"venue"
},
  "geometry": {"coordinates":[-79.937754,40.49411],"type":"Point"}
}