{
  "type": "Feature",
  "properties": {
    "addr:full":"100 Rock Rd Pine Grove PA 17963",
    "addr:housenumber":"100",
    "addr:postcode":"17963",
    "addr:street":"Rock Rd",
    "iso:country":"US",
    "sg:address":"100 Rock Rd",
    "sg:city":"Pine Grove",
    "sg:classifiers":[
        {
            "category":"Social Services",
            "type":"Services"
        }
    ],
    "sg:phone":"+1 570 345 3508",
    "sg:postcode":"17963",
    "sg:province":"PA",
    "wof:name":"Evergreen Adult Day Care",
    "wof:placetype":"venue"
},
  "geometry": {"coordinates":[-76.37740599999999,40.539702],"type":"Point"}
}