{
  "type": "Feature",
  "properties": {
    "addr:full":"116 E King St Malvern PA 19355",
    "addr:housenumber":"116",
    "addr:postcode":"19355",
    "addr:street":"E King St",
    "iso:country":"US",
    "sg:address":"116 E King St",
    "sg:city":"Malvern",
    "sg:classifiers":[
        {
            "category":"Professional",
            "type":"Services"
        }
    ],
    "sg:phone":"+1   ",
    "sg:postcode":"19355",
    "sg:province":"PA",
    "wof:name":"Alex Coates",
    "wof:placetype":"venue"
},
  "geometry": {"coordinates":[-75.513172,40.036506],"type":"Point"}
}