{
  "type": "Feature",
  "properties": {
    "iso:country":"US",
    "sg:address":"525 Main St",
    "sg:city":"Towanda",
    "sg:classifiers":[
        {
            "category":"Personal",
            "subcategory":"Beauty Salon",
            "type":"Services"
        }
    ],
    "sg:phone":"+1 570 265 3540",
    "sg:postcode":"18848",
    "sg:province":"PA",
    "sg:tags":[
        "shop"
    ],
    "wof:name":"Mane Street Hair & Nails",
    "wof:placetype":"venue"
},
  "geometry": {"coordinates":[-76.443016,41.765091],"type":"Point"}
}