{
  "type": "Feature",
  "properties": {
    "addr:full":"132 N 10th St Philadelphia PA 19107",
    "addr:housenumber":"132",
    "addr:postcode":"19107",
    "addr:street":"N 10Th St",
    "iso:country":"US",
    "sg:address":"132 N 10th St",
    "sg:city":"Philadelphia",
    "sg:classifiers":[
        {
            "category":"Wholesale",
            "subcategory":"Meat",
            "type":"Manufacturing & Wholesale Goods"
        }
    ],
    "sg:phone":"+1 215 928 1223",
    "sg:postcode":"19107",
    "sg:province":"PA",
    "wof:name":"Winton Wholesale Trading Co",
    "wof:placetype":"venue"
},
  "geometry": {"coordinates":[-75.15598,39.955314],"type":"Point"}
}