{
  "type": "Feature",
  "properties": {
    "iso:country":"US",
    "sg:address":"5001 Louise Dr Ste 201",
    "sg:city":"Mechanicsburg",
    "sg:classifiers":[
        {
            "category":"Banks & Credit Unions",
            "subcategory":"Financial Services",
            "type":"Services"
        }
    ],
    "sg:phone":"+1 717 795 9030",
    "sg:postcode":"17055",
    "sg:province":"PA",
    "sg:tags":[
        "financing"
    ],
    "wof:name":"Americredit Financial Services, Inc.",
    "wof:placetype":"venue"
},
  "geometry": {"coordinates":[-76.96080000000001,40.201553],"type":"Point"}
}