{
  "type": "Feature",
  "properties": {
    "iso:country":"US",
    "sg:address":"1117 Reed St",
    "sg:city":"Philadelphia",
    "sg:classifiers":[
        {
            "category":"Freight",
            "type":"Transportation"
        }
    ],
    "sg:phone":"+1   ",
    "sg:postcode":"19147",
    "sg:province":"PA",
    "sg:tags":[
        "general"
    ],
    "wof:name":"Department of Public Property",
    "wof:placetype":"venue"
},
  "geometry": {"coordinates":[-75.16385200000001,39.932474],"type":"Point"}
}