{
  "type": "Feature",
  "properties": {
    "iso:country":"US",
    "sg:address":"1115 W Gillam Ave",
    "sg:city":"Langhorne",
    "sg:classifiers":[
        {
            "category":"Manufacturing",
            "subcategory":"Tools & Machinery",
            "type":"Manufacturing & Wholesale Goods"
        }
    ],
    "sg:phone":"+1 215 757 7753",
    "sg:postcode":"19047",
    "sg:province":"PA",
    "sg:tags":[
        "machine",
        "repair",
        "shop",
        "machinery-rebuild"
    ],
    "wof:name":"Artcraft Machine And Tool Corp",
    "wof:placetype":"venue"
},
  "geometry": {"coordinates":[-74.937166,40.165878],"type":"Point"}
}