{
  "type": "Feature",
  "properties": {
    "iso:country":"US",
    "sg:address":"1057 N Church St A",
    "sg:city":"Hazleton",
    "sg:classifiers":[
        {
            "category":"Education",
            "subcategory":"College",
            "type":"Public Place"
        },
        {
            "category":"Education",
            "subcategory":"Special Training",
            "type":"Public Place"
        },
        {
            "category":"Education",
            "subcategory":"Vocational School",
            "type":"Public Place"
        }
    ],
    "sg:phone":"+1 570 459 5501",
    "sg:postcode":"18202",
    "sg:province":"PA",
    "sg:tags":[
        "educational",
        "industrial",
        "business",
        "beauty",
        "technical",
        "trade"
    ],
    "wof:name":"Academy Of Hair Design, Inc",
    "wof:placetype":"venue"
},
  "geometry": {"coordinates":[-75.978425,40.974538],"type":"Point"}
}