{
  "type": "Feature",
  "properties": {
    "iso:country":"US",
    "sg:address":"4227 Campbells Run Rd",
    "sg:city":"Pittsburgh",
    "sg:classifiers":[
        {
            "category":"Retail",
            "subcategory":"Repair Shop",
            "type":"Services"
        }
    ],
    "sg:phone":"+1 412 276 4559",
    "sg:postcode":"15205",
    "sg:province":"PA",
    "sg:tags":[
        "repairing",
        "equipment",
        "electric"
    ],
    "wof:name":"Electric Power Systems",
    "wof:placetype":"venue"
},
  "geometry": {"coordinates":[-80.10915900000001,40.425417],"type":"Point"}
}