{
  "type": "Feature",
  "properties": {
    "iso:country":"US",
    "sg:address":"1497 Bedillion Rd",
    "sg:city":"Washington",
    "sg:classifiers":[
        {
            "category":"Recreation",
            "type":"Entertainment"
        }
    ],
    "sg:phone":"+1 724 223 2656",
    "sg:postcode":"15301",
    "sg:province":"PA",
    "sg:tags":[
        "stable"
    ],
    "wof:name":"Clover Hill Stables",
    "wof:placetype":"venue"
},
  "geometry": {"coordinates":[-80.27082900000001,40.090137],"type":"Point"}
}