{
  "type": "Feature",
  "properties": {
    "addr:full":"146 W Philadelphia St York PA 17403",
    "addr:housenumber":"146",
    "addr:postcode":"17403",
    "addr:street":"W Philadelphia St",
    "iso:country":"US",
    "sg:address":"146 W Philadelphia St",
    "sg:city":"York",
    "sg:classifiers":[
        {
            "category":"Professional",
            "subcategory":"Art Services",
            "type":"Services"
        }
    ],
    "sg:phone":"+1   ",
    "sg:postcode":"17403",
    "sg:province":"PA",
    "sg:tags":[
        "commercial",
        "design"
    ],
    "wof:name":"Fleagle & Friends Illustrators",
    "wof:placetype":"venue"
},
  "geometry": {"coordinates":[-76.73230599999999,39.962683],"type":"Point"}
}