{
  "type": "Feature",
  "properties": {
    "iso:country":"US",
    "sg:address":"1818 Market St Fl 12",
    "sg:city":"Philadelphia",
    "sg:classifiers":[
        {
            "category":"Travel",
            "subcategory":"Travel Agent",
            "type":"Entertainment"
        }
    ],
    "sg:phone":"+1 215 299 8096",
    "sg:postcode":"19103",
    "sg:province":"PA",
    "sg:tags":[
        "agency",
        "services-commercial"
    ],
    "sg:website":"http://www.barclaytravel.com",
    "wof:name":"Barclay Travel Agency",
    "wof:placetype":"venue"
},
  "geometry": {"coordinates":[-75.170276,39.953225],"type":"Point"}
}