{
  "type": "Feature",
  "properties": {
    "iso:country":"US",
    "sg:address":"2255 Dorn Rd",
    "sg:city":"Waterford",
    "sg:classifiers":[
        {
            "category":"Building & Trades",
            "subcategory":"Construction",
            "type":"Services"
        }
    ],
    "sg:phone":"+1   ",
    "sg:postcode":"16441",
    "sg:province":"PA",
    "sg:tags":[
        "house"
    ],
    "wof:name":"Tim Will Builders",
    "wof:placetype":"venue"
},
  "geometry": {"coordinates":[-80.07177,42.02936],"type":"Point"}
}