{
  "type": "Feature",
  "properties": {
    "iso:country":"US",
    "sg:address":"2454 E Berlin Rd",
    "sg:city":"East Berlin",
    "sg:classifiers":[
        {
            "category":"Farming",
            "subcategory":"Farm",
            "type":"Manufacturing & Wholesale Goods"
        }
    ],
    "sg:phone":"+1 717 259 9108",
    "sg:postcode":"17316",
    "sg:province":"PA",
    "sg:tags":[
        "general",
        "crop",
        "supply"
    ],
    "wof:name":"Honey Locust Farms",
    "wof:placetype":"venue"
},
  "geometry": {"coordinates":[-77.04688,39.935957],"type":"Point"}
}