{
  "type": "Feature",
  "properties": {
    "iso:country":"US",
    "sg:address":"249 Hospital Dr",
    "sg:city":"Everett",
    "sg:classifiers":[
        {
            "category":"Manufacturing",
            "subcategory":"Chemicals & Compounds",
            "type":"Manufacturing & Wholesale Goods"
        }
    ],
    "sg:phone":"+1   ",
    "sg:postcode":"15537",
    "sg:province":"PA",
    "sg:tags":[
        "preparation",
        "pharmaceutical",
        "mfg"
    ],
    "wof:name":"Industrial Health Svc",
    "wof:placetype":"venue"
},
  "geometry": {"coordinates":[-78.43341700000001,40.026023],"type":"Point"}
}