{
  "type": "Feature",
  "properties": {
    "iso:country":"US",
    "sg:address":"538 Hickory Grade Rd",
    "sg:city":"Bridgeville",
    "sg:classifiers":[
        {
            "category":"Organizations",
            "subcategory":"Religious Organization",
            "type":"Services"
        }
    ],
    "sg:phone":"+1 412 257 1707",
    "sg:postcode":"15017",
    "sg:province":"PA",
    "sg:tags":[
        "church"
    ],
    "sg:website":"www.calvaryfullgospelchurch.org",
    "wof:name":"Calvary Full Gospel Church",
    "wof:placetype":"venue"
},
  "geometry": {"coordinates":[-80.14893600000001,40.346622],"type":"Point"}
}