{
  "type": "Feature",
  "properties": {
    "addr:full":"7515 Castor Ave Philadelphia PA 19152",
    "addr:housenumber":"7515",
    "addr:postcode":"19152",
    "addr:street":"Castor Ave",
    "iso:country":"US",
    "sg:address":"7515 Castor Ave",
    "sg:city":"Philadelphia",
    "sg:classifiers":[
        {
            "category":"Real Estate",
            "subcategory":"Real Estate Agent",
            "type":"Services"
        }
    ],
    "sg:phone":"+1 215 725 9200",
    "sg:postcode":"19152",
    "sg:province":"PA",
    "sg:website":"www.helpusell.com",
    "wof:name":"Help-U-Sell Real Estate",
    "wof:placetype":"venue"
},
  "geometry": {"coordinates":[-75.063164,40.05431],"type":"Point"}
}