{
  "type": "Feature",
  "properties": {
    "iso:country":"US",
    "sg:address":"5 Airy St",
    "sg:city":"Wilkes Barre",
    "sg:classifiers":[
        {
            "category":"Manufacturing",
            "subcategory":"Apparel",
            "type":"Manufacturing & Wholesale Goods"
        }
    ],
    "sg:phone":"+1 570 822 2799",
    "sg:postcode":"18702",
    "sg:province":"PA",
    "sg:tags":[
        "product",
        "mfg",
        "fabricated",
        "textile",
        "flag",
        "banner"
    ],
    "wof:name":"Jim's Flags & Banners",
    "wof:placetype":"venue"
},
  "geometry": {"coordinates":[-75.89397099999999,41.231846],"type":"Point"}
}