{
  "type": "Feature",
  "properties": {
    "iso:country":"US",
    "sg:address":"590 Candlewyck Rd",
    "sg:city":"Lancaster",
    "sg:classifiers":[
        {
            "category":"Real Estate",
            "subcategory":"Real Estate Operator",
            "type":"Services"
        }
    ],
    "sg:phone":"+1 717 569 3606",
    "sg:postcode":"17601",
    "sg:province":"PA",
    "sg:tags":[
        "apartment"
    ],
    "wof:name":"Belair Townhouses",
    "wof:placetype":"venue"
},
  "geometry": {"coordinates":[-76.33601899999999,40.086687],"type":"Point"}
}