{
  "type": "Feature",
  "properties": {
    "addr:full":"545 Mount Tabor Rd Coal Center PA 15423",
    "addr:housenumber":"545",
    "addr:postcode":"15423",
    "addr:street":"Mount Tabor Rd",
    "iso:country":"US",
    "sg:address":"545 Mount Tabor Rd",
    "sg:city":"Coal Center",
    "sg:classifiers":[
        {
            "category":"Retail",
            "subcategory":"Animal Services",
            "type":"Services"
        }
    ],
    "sg:phone":"+1 724 483 1312",
    "sg:postcode":"15423",
    "sg:province":"PA",
    "sg:tags":[
        "pet",
        "grooming",
        "washing"
    ],
    "wof:name":"Pet Bath House",
    "wof:placetype":"venue"
},
  "geometry": {"coordinates":[-79.88118900000001,40.101631],"type":"Point"}
}