{
  "type": "Feature",
  "properties": {
    "addr:full":"453 Lincoln St Carlisle PA 17013",
    "addr:housenumber":"453",
    "addr:postcode":"17013",
    "addr:street":"Lincoln St",
    "iso:country":"US",
    "sg:address":"453 Lincoln St",
    "sg:city":"Carlisle",
    "sg:classifiers":[
        {
            "category":"Building & Trades",
            "subcategory":"Construction",
            "type":"Services"
        }
    ],
    "sg:phone":"+1 717 258 1994",
    "sg:postcode":"17013",
    "sg:province":"PA",
    "sg:tags":[
        "designer",
        "contractor"
    ],
    "sg:website":"www.dmtstudio.com",
    "wof:name":"Dmt Studio Inc",
    "wof:placetype":"venue"
},
  "geometry": {"coordinates":[-77.19952600000001,40.20757],"type":"Point"}
}