{
  "type": "Feature",
  "properties": {
    "addr:full":"731 Vallevista Ave Pittsburgh PA 15234",
    "addr:housenumber":"731",
    "addr:postcode":"15234",
    "addr:street":"Vallevista Ave",
    "iso:country":"US",
    "sg:address":"731 Vallevista Ave",
    "sg:city":"Pittsburgh",
    "sg:classifiers":[
        {
            "category":"Home & Garden",
            "subcategory":"Building Materials",
            "type":"Retail Goods"
        },
        {
            "category":"Building & Trades",
            "subcategory":"Construction",
            "type":"Services"
        },
        {
            "category":"Utilities",
            "subcategory":"Natural Gas",
            "type":"Services"
        }
    ],
    "sg:phone":"+1 412 561 6732",
    "sg:postcode":"15234",
    "sg:province":"PA",
    "sg:tags":[
        "stone",
        "industrial",
        "contractor",
        "concrete",
        "contractors-commercial",
        "masonry",
        "mason"
    ],
    "wof:name":"A Petrelli & Sons",
    "wof:placetype":"venue"
},
  "geometry": {"coordinates":[-80.034221,40.362162],"type":"Point"}
}