{
  "type": "Feature",
  "properties": {
    "iso:country":"US",
    "sg:address":"436 S 44th St",
    "sg:city":"Philadelphia",
    "sg:classifiers":[
        {
            "category":"Building & Trades",
            "subcategory":"Construction",
            "type":"Services"
        }
    ],
    "sg:phone":"+1   ",
    "sg:postcode":"19104",
    "sg:province":"PA",
    "sg:tags":[
        "contractor"
    ],
    "wof:name":"J Dolph Inc",
    "wof:placetype":"venue"
},
  "geometry": {"coordinates":[-75.211135,39.950256],"type":"Point"}
}