{
  "type": "Feature",
  "properties": {
    "iso:country":"US",
    "sg:address":"1422 Manley Rd",
    "sg:city":"West Chester",
    "sg:classifiers":[
        {
            "category":"Food & Beverages",
            "subcategory":"Groceries & Convenience Stores",
            "type":"Retail Goods"
        }
    ],
    "sg:phone":"+1   ",
    "sg:postcode":"19382",
    "sg:province":"PA",
    "sg:tags":[
        "shop",
        "gift"
    ],
    "wof:name":"Barrel Store",
    "wof:placetype":"venue"
},
  "geometry": {"coordinates":[-75.538935,39.962419],"type":"Point"}
}