{
  "type": "Feature",
  "properties": {
    "iso:country":"US",
    "sg:address":"46 W Ridge St",
    "sg:city":"Lansford",
    "sg:classifiers":[
        {
            "category":"Food & Beverages",
            "subcategory":"Liquor & Beverages",
            "type":"Retail Goods"
        }
    ],
    "sg:phone":"+1 570 645 3636",
    "sg:postcode":"18232",
    "sg:province":"PA",
    "sg:tags":[
        "consultant",
        "regulation",
        "commercial",
        "sect",
        "alcoholic"
    ],
    "wof:name":"Wine & Spirits Shoppe 1301",
    "wof:placetype":"venue"
},
  "geometry": {"coordinates":[-75.88549999999999,40.831854],"type":"Point"}
}