{
  "type": "Feature",
  "properties": {
    "iso:country":"US",
    "sg:address":"3245 S Main St",
    "sg:city":"Sandy Lake",
    "sg:classifiers":[
        {
            "category":"Autos & Motor Vehicles",
            "subcategory":"Fuel & Gas Station",
            "type":"Retail Goods"
        }
    ],
    "sg:phone":"+1 724 376 3364",
    "sg:postcode":"16145",
    "sg:province":"PA",
    "sg:tags":[
        "station",
        "gasoline",
        "oil"
    ],
    "wof:name":"Elmer's Service Station",
    "wof:placetype":"venue"
},
  "geometry": {"coordinates":[-80.081828,41.348317],"type":"Point"}
}