{
  "type": "Feature",
  "properties": {
    "addr:full":"57 Beverly Dr Kintnersville PA 18930",
    "addr:housenumber":"57",
    "addr:postcode":"18930",
    "addr:street":"Beverly Dr Kintnersville",
    "iso:country":"US",
    "sg:address":"57 Beverly Dr",
    "sg:city":"Kintnersville",
    "sg:classifiers":[
        {
            "category":"Autos & Motor Vehicles",
            "subcategory":"Automobile Sales",
            "type":"Retail Goods"
        }
    ],
    "sg:phone":"+1 610 847 3325",
    "sg:postcode":"18930",
    "sg:province":"PA",
    "sg:tags":[
        "new",
        "used",
        "car"
    ],
    "wof:name":"Bruce Motors",
    "wof:placetype":"venue"
},
  "geometry": {"coordinates":[-75.187534,40.531585],"type":"Point"}
}