{
  "type": "Feature",
  "properties": {
    "iso:country":"US",
    "sg:address":"2240 S Queen St",
    "sg:city":"York",
    "sg:classifiers":[
        {
            "category":"Professional",
            "subcategory":"Research",
            "type":"Services"
        }
    ],
    "sg:phone":"+1 717 741 0797",
    "sg:postcode":"17402",
    "sg:province":"PA",
    "sg:tags":[
        "laboratory"
    ],
    "wof:name":"National Health Laboratories",
    "wof:placetype":"venue"
},
  "geometry": {"coordinates":[-76.68641100000001,39.927572],"type":"Point"}
}