{
  "type": "Feature",
  "properties": {
    "addr:full":"520 S Broad St Kennett Square PA 19348",
    "addr:housenumber":"520",
    "addr:postcode":"19348",
    "addr:street":"S Broad St",
    "iso:country":"US",
    "sg:address":"520 S Broad St",
    "sg:city":"Kennett Square",
    "sg:classifiers":[
        {
            "category":"Shopping",
            "subcategory":"Shoes",
            "type":"Retail Goods"
        }
    ],
    "sg:phone":"+1 610 444 6560",
    "sg:postcode":"19348",
    "sg:province":"PA",
    "wof:name":"Bostonian Shoe Co",
    "wof:placetype":"venue"
},
  "geometry": {"coordinates":[-75.70931400000001,39.842326],"type":"Point"}
}