{
  "type": "Feature",
  "properties": {
    "iso:country":"US",
    "sg:address":"820 Homestead Rd",
    "sg:city":"Jenkintown",
    "sg:classifiers":[
        {
            "category":"Professional",
            "subcategory":"Lawyer & Legal Services",
            "type":"Services"
        }
    ],
    "sg:phone":"+1 215 572 1459",
    "sg:postcode":"19046",
    "sg:province":"PA",
    "sg:tags":[
        "attorney"
    ],
    "wof:name":"Pamela Reiss",
    "wof:placetype":"venue"
},
  "geometry": {"coordinates":[-75.123823,40.097355],"type":"Point"}
}