{
  "type": "Feature",
  "properties": {
    "addr:full":"404 Locust St Coraopolis PA 15108",
    "addr:housenumber":"404",
    "addr:postcode":"15108",
    "addr:street":"Locust St",
    "iso:country":"US",
    "sg:address":"404 Locust St",
    "sg:city":"Coraopolis",
    "sg:classifiers":[
        {
            "category":"Wholesale",
            "subcategory":"Auto Parts",
            "type":"Manufacturing & Wholesale Goods"
        }
    ],
    "sg:phone":"+1 412 264 7738",
    "sg:postcode":"15108",
    "sg:province":"PA",
    "sg:tags":[
        "automobile",
        "supply"
    ],
    "wof:name":"Station Auto Parts",
    "wof:placetype":"venue"
},
  "geometry": {"coordinates":[-80.17189500000001,40.520485],"type":"Point"}
}