{
  "type": "Feature",
  "properties": {
    "iso:country":"US",
    "sg:address":"524 Noll Rd",
    "sg:city":"Loretto",
    "sg:classifiers":[
        {
            "category":"Professional",
            "type":"Services"
        },
        {
            "category":"Professional",
            "subcategory":"Business Services",
            "type":"Services"
        }
    ],
    "sg:phone":"+1 814 472 8560",
    "sg:postcode":"15940",
    "sg:province":"PA",
    "sg:tags":[
        "forestry",
        "consultant",
        "consulting",
        "coach"
    ],
    "sg:website":"http://www.nollsforestryservices.com",
    "wof:name":"Noll's Forestry Services Inc",
    "wof:placetype":"venue"
},
  "geometry": {"coordinates":[-78.622016,40.522676],"type":"Point"}
}