{
  "type": "Feature",
  "properties": {
    "iso:country":"US",
    "sg:address":"250 Beverly Blvd",
    "sg:city":"Upper Darby",
    "sg:classifiers":[
        {
            "category":"Real Estate",
            "subcategory":"Real Estate Operator",
            "type":"Services"
        }
    ],
    "sg:phone":"+1   ",
    "sg:postcode":"19082",
    "sg:province":"PA",
    "sg:tags":[
        "building",
        "apartment"
    ],
    "wof:name":"Fort Joy Development Co",
    "wof:placetype":"venue"
},
  "geometry": {"coordinates":[-75.270065,39.953959],"type":"Point"}
}