{
  "type": "Feature",
  "properties": {
    "iso:country":"US",
    "sg:address":"1650 N Main St",
    "sg:city":"Butler",
    "sg:classifiers":[
        {
            "category":"Professional",
            "subcategory":"Business Services",
            "type":"Services"
        }
    ],
    "sg:phone":"+1 724 282 9371",
    "sg:postcode":"16001",
    "sg:province":"PA",
    "sg:tags":[
        "paging",
        "answering"
    ],
    "wof:name":"Cost Cutter Consultants",
    "wof:placetype":"venue"
},
  "geometry": {"coordinates":[-79.914846,40.903062],"type":"Point"}
}