{
  "type": "Feature",
  "properties": {
    "addr:full":"57 Mark Dr Delmont PA 15626",
    "addr:housenumber":"57",
    "addr:postcode":"15626",
    "addr:street":"Mark Dr",
    "iso:country":"US",
    "sg:address":"57 Mark Dr",
    "sg:city":"Delmont",
    "sg:classifiers":[
        {
            "category":"Manufacturing",
            "subcategory":"Glass & Minerals",
            "type":"Manufacturing & Wholesale Goods"
        }
    ],
    "sg:phone":"+1 724 468 4181",
    "sg:postcode":"15626",
    "sg:province":"PA",
    "sg:tags":[
        "prod",
        "made"
    ],
    "sg:website":"www.behrenbergglass.com",
    "wof:name":"Behrenberg Glass Co",
    "wof:placetype":"venue"
},
  "geometry": {"coordinates":[-79.577674,40.404375],"type":"Point"}
}