{
  "type": "Feature",
  "properties": {
    "iso:country":"US",
    "sg:address":"20 Spruce St",
    "sg:city":"Danboro",
    "sg:classifiers":[
        {
            "category":"Building & Trades",
            "subcategory":"Construction",
            "type":"Services"
        }
    ],
    "sg:phone":"+1   ",
    "sg:postcode":"18901",
    "sg:province":"PA",
    "sg:tags":[
        "contractor"
    ],
    "wof:name":"Montano Sons Tile & Carpenting",
    "wof:placetype":"venue"
},
  "geometry": {"coordinates":[-75.14160699999999,40.363091],"type":"Point"}
}