{
  "type": "Feature",
  "properties": {
    "iso:country":"US",
    "sg:address":"249 Arch St",
    "sg:city":"Philadelphia",
    "sg:classifiers":[
        {
            "category":"Professional",
            "type":"Services"
        }
    ],
    "sg:phone":"+1 215 592 8400",
    "sg:postcode":"19106",
    "sg:province":"PA",
    "sg:tags":[
        "planning",
        "event"
    ],
    "sg:website":"www.thetrustvenue.com",
    "wof:name":"The Trust \u00a0Venue",
    "wof:placetype":"venue"
},
  "geometry": {"coordinates":[-75.144961,39.952221],"type":"Point"}
}