{
  "type": "Feature",
  "properties": {
    "iso:country":"US",
    "sg:address":"10922 Rte 322",
    "sg:city":"Shippenville",
    "sg:classifiers":[
        {
            "category":"Autos & Motor Vehicles",
            "subcategory":"Automobile Sales",
            "type":"Retail Goods"
        }
    ],
    "sg:phone":"+1 814 226 0700",
    "sg:postcode":"16254",
    "sg:province":"PA",
    "wof:name":"Seneca Motors Inc",
    "wof:placetype":"venue"
},
  "geometry": {"coordinates":[-79.417338,41.236853],"type":"Point"}
}