{
  "type": "Feature",
  "properties": {
    "iso:country":"US",
    "sg:address":"1236 Liberty St",
    "sg:city":"Franklin",
    "sg:classifiers":[
        {
            "category":"Restaurant",
            "type":"Food & Drink"
        }
    ],
    "sg:phone":"+1 814 432 5959",
    "sg:postcode":"16323",
    "sg:province":"PA",
    "sg:tags":[
        "shop",
        "coffee"
    ],
    "wof:name":"Summer House Coffee",
    "wof:placetype":"venue"
},
  "geometry": {"coordinates":[-79.828192,41.397573],"type":"Point"}
}