{
  "type": "Feature",
  "properties": {
    "iso:country":"US",
    "sg:address":"765 Grove Rd",
    "sg:city":"Red Lion",
    "sg:classifiers":[
        {
            "category":"Building & Trades",
            "subcategory":"Landscaping Services",
            "type":"Services"
        }
    ],
    "sg:phone":"+1   ",
    "sg:postcode":"17356",
    "sg:province":"PA",
    "sg:tags":[
        "lawn",
        "landscape",
        "mowing"
    ],
    "wof:name":"Dons Lawn Landscaping",
    "wof:placetype":"venue"
},
  "geometry": {"coordinates":[-76.591865,39.88184],"type":"Point"}
}