{
  "type": "Feature",
  "properties": {
    "addr:full":"7602 Ogontz Ave Philadelphia PA 19150",
    "addr:housenumber":"7602",
    "addr:postcode":"19150",
    "addr:street":"Ogontz Ave",
    "iso:country":"US",
    "sg:address":"7602 Ogontz Ave",
    "sg:city":"Philadelphia",
    "sg:classifiers":[
        {
            "category":"Real Estate",
            "subcategory":"Real Estate Agent",
            "type":"Services"
        }
    ],
    "sg:phone":"+1   ",
    "sg:postcode":"19150",
    "sg:province":"PA",
    "sg:tags":[
        "broker",
        "appraiser",
        "insurance"
    ],
    "wof:name":"Century 21",
    "wof:placetype":"venue"
},
  "geometry": {"coordinates":[-75.157465,40.070733],"type":"Point"}
}