{
  "type": "Feature",
  "properties": {
    "iso:country":"US",
    "sg:address":"829 Disston View Dr",
    "sg:city":"Lititz",
    "sg:classifiers":[
        {
            "category":"Building & Trades",
            "subcategory":"Landscaping Services",
            "type":"Services"
        }
    ],
    "sg:phone":"+1 717 625 4229",
    "sg:postcode":"17543",
    "sg:province":"PA",
    "sg:tags":[
        "designer",
        "landscape"
    ],
    "wof:name":"Earthworks Garden Design",
    "wof:placetype":"venue"
},
  "geometry": {"coordinates":[-76.252432,40.136925],"type":"Point"}
}