{
  "type": "Feature",
  "properties": {
    "iso:country":"US",
    "sg:address":"517 Main St",
    "sg:city":"Carbondale",
    "sg:classifiers":[
        {
            "category":"Shopping",
            "subcategory":"Jewelry",
            "type":"Retail Goods"
        }
    ],
    "sg:phone":"+1   ",
    "sg:postcode":"18407",
    "sg:province":"PA",
    "sg:tags":[
        "repair",
        "work",
        "custom"
    ],
    "wof:name":"Anthonys Jewelers",
    "wof:placetype":"venue"
},
  "geometry": {"coordinates":[-75.525226,41.556722],"type":"Point"}
}