{
  "type": "Feature",
  "properties": {
    "addr:full":"41 Woodbine Ln Danville PA 17821",
    "addr:housenumber":"41",
    "addr:postcode":"17821",
    "addr:street":"Woodbine Ln",
    "iso:country":"US",
    "sg:address":"41 Woodbine Ln",
    "sg:city":"Danville",
    "sg:classifiers":[
        {
            "category":"Health Services",
            "subcategory":"Clinic",
            "type":"Services"
        }
    ],
    "sg:phone":"+1   ",
    "sg:postcode":"17821",
    "sg:province":"PA",
    "sg:tags":[
        "specialty",
        "outpatient"
    ],
    "wof:name":"Valley Rehabilitation",
    "wof:placetype":"venue"
},
  "geometry": {"coordinates":[-76.575599,40.960164],"type":"Point"}
}