{
  "type": "Feature",
  "properties": {
    "addr:full":"212 Denny St West Newton PA 15089",
    "addr:housenumber":"212",
    "addr:postcode":"15089",
    "addr:street":"Denny St West",
    "iso:country":"US",
    "sg:address":"212 Denny St",
    "sg:city":"West Newton",
    "sg:classifiers":[
        {
            "category":"Building & Trades",
            "subcategory":"Construction",
            "type":"Services"
        }
    ],
    "sg:phone":"+1   ",
    "sg:postcode":"15089",
    "sg:province":"PA",
    "sg:tags":[
        "hanging",
        "contractor"
    ],
    "wof:name":"Dennis Seliy Services",
    "wof:placetype":"venue"
},
  "geometry": {"coordinates":[-79.772993,40.208947],"type":"Point"}
}