{
  "type": "Feature",
  "properties": {
    "iso:country":"US",
    "sg:address":"153 Bishops Dr",
    "sg:city":"Chester Heights",
    "sg:classifiers":[
        {
            "category":"Shopping",
            "subcategory":"Hobbies, Toys, & Games",
            "type":"Retail Goods"
        }
    ],
    "sg:phone":"+1 610 558 9514",
    "sg:postcode":"19014",
    "sg:province":"PA",
    "wof:name":"Underground Railroad",
    "wof:placetype":"venue"
},
  "geometry": {"coordinates":[-75.466926,39.878871],"type":"Point"}
}