{
  "type": "Feature",
  "properties": {
    "addr:full":"145 Green Valley Cir Dresher PA 19025",
    "addr:housenumber":"145",
    "addr:postcode":"19025",
    "addr:street":"Green Valley Cir",
    "iso:country":"US",
    "sg:address":"145 Green Valley Cir",
    "sg:city":"Dresher",
    "sg:classifiers":[
        {
            "category":"Restaurant",
            "type":"Food & Drink"
        }
    ],
    "sg:phone":"+1   ",
    "sg:postcode":"19025",
    "sg:province":"PA",
    "sg:tags":[
        "eating"
    ],
    "wof:name":"Cosmos Catering",
    "wof:placetype":"venue"
},
  "geometry": {"coordinates":[-75.160731,40.139832],"type":"Point"}
}