{
  "type": "Feature",
  "properties": {
    "iso:country":"US",
    "sg:address":"3750 Pulaski Ave",
    "sg:city":"Philadelphia",
    "sg:classifiers":[
        {
            "category":"Personal",
            "subcategory":"Beauty Salon",
            "type":"Services"
        }
    ],
    "sg:phone":"+1 215 228 1875",
    "sg:postcode":"19140",
    "sg:province":"PA",
    "sg:tags":[
        "shop"
    ],
    "wof:name":"Shirley's Hair Creation",
    "wof:placetype":"venue"
},
  "geometry": {"coordinates":[-75.156014,40.011341],"type":"Point"}
}