{
  "type": "Feature",
  "properties": {
    "iso:country":"US",
    "sg:address":"735 Walnut St",
    "sg:city":"Philadelphia",
    "sg:classifiers":[
        {
            "category":"Shopping",
            "subcategory":"Jewelry",
            "type":"Retail Goods"
        }
    ],
    "sg:phone":"+1 215 923 3338",
    "sg:postcode":"19106",
    "sg:province":"PA",
    "wof:name":"Weintraut Edward Jeweler",
    "wof:placetype":"venue"
},
  "geometry": {"coordinates":[-75.15329699999999,39.947899],"type":"Point"}
}