{
  "type": "Feature",
  "properties": {
    "iso:country":"US",
    "sg:address":"6272 State Rte 309",
    "sg:city":"New Tripoli",
    "sg:classifiers":[
        {
            "category":"Government",
            "subcategory":"Office",
            "type":"Public Place"
        }
    ],
    "sg:phone":"+1 610 767 1344",
    "sg:postcode":"18066",
    "sg:province":"PA",
    "sg:tags":[
        "village"
    ],
    "wof:name":"Heidelberg Township Mntnc Bldg",
    "wof:placetype":"venue"
},
  "geometry": {"coordinates":[-75.690988,40.683395],"type":"Point"}
}