{
  "type": "Feature",
  "properties": {
    "addr:full":"419 Delaware Rd Fredonia PA 16124",
    "addr:housenumber":"419",
    "addr:postcode":"16124",
    "addr:street":"Delaware Rd",
    "iso:country":"US",
    "sg:address":"419 Delaware Rd",
    "sg:city":"Fredonia",
    "sg:classifiers":[
        {
            "category":"Organizations",
            "subcategory":"Professional Association",
            "type":"Services"
        }
    ],
    "sg:phone":"+1 724 475 4834",
    "sg:postcode":"16124",
    "sg:province":"PA",
    "wof:name":"Mercer County Builder Assn",
    "wof:placetype":"venue"
},
  "geometry": {"coordinates":[-80.262523,41.317714],"type":"Point"}
}