{
  "type": "Feature",
  "properties": {
    "iso:country":"US",
    "sg:address":"43 Stonehurst Ct",
    "sg:city":"Wayne",
    "sg:classifiers":[
        {
            "category":"Wholesale",
            "subcategory":"Durable Goods & Equipment",
            "type":"Manufacturing & Wholesale Goods"
        }
    ],
    "sg:phone":"+1   ",
    "sg:postcode":"19087",
    "sg:province":"PA",
    "wof:name":"Worlds Finest",
    "wof:placetype":"venue"
},
  "geometry": {"coordinates":[-75.447548,40.075608],"type":"Point"}
}