{
  "type": "Feature",
  "properties": {
    "addr:full":"109 N 2nd St North Wales PA 19454",
    "addr:housenumber":"109",
    "addr:postcode":"19454",
    "addr:street":"N 2Nd St",
    "iso:country":"US",
    "sg:address":"109 N 2nd St",
    "sg:city":"North Wales",
    "sg:classifiers":[
        {
            "category":"Organizations",
            "subcategory":"Labor Organization",
            "type":"Services"
        }
    ],
    "sg:phone":"+1 215 699 3278",
    "sg:postcode":"19454",
    "sg:province":"PA",
    "wof:name":"PACE International Union",
    "wof:placetype":"venue"
},
  "geometry": {"coordinates":[-75.279473,40.212091],"type":"Point"}
}