{
  "type": "Feature",
  "properties": {
    "addr:full":"3210 Industrial Blvd Bethel Park PA 15102",
    "addr:housenumber":"3210",
    "addr:postcode":"15102",
    "addr:street":"Industrial Blvd",
    "iso:country":"US",
    "sg:address":"3210 Industrial Blvd",
    "sg:city":"Bethel Park",
    "sg:classifiers":[
        {
            "category":"Manufacturing",
            "subcategory":"Tools & Machinery",
            "type":"Manufacturing & Wholesale Goods"
        }
    ],
    "sg:phone":"+1 412 831 0400",
    "sg:postcode":"15102",
    "sg:province":"PA",
    "sg:tags":[
        "equipment",
        "pump",
        "pumping"
    ],
    "wof:name":"Servi-Sel Inc",
    "wof:placetype":"venue"
},
  "geometry": {"coordinates":[-80.046437,40.321726],"type":"Point"}
}