{
  "type": "Feature",
  "properties": {
    "iso:country":"US",
    "sg:address":"51 Commanders Dr",
    "sg:city":"Washington Crossing",
    "sg:classifiers":[
        {
            "category":"Wholesale",
            "subcategory":"Non-durable Goods",
            "type":"Manufacturing & Wholesale Goods"
        }
    ],
    "sg:phone":"+1   ",
    "sg:postcode":"18977",
    "sg:province":"PA",
    "wof:name":"Maddog Trading Co",
    "wof:placetype":"venue"
},
  "geometry": {"coordinates":[-74.890962,40.29456],"type":"Point"}
}