{
  "type": "Feature",
  "properties": {
    "iso:country":"US",
    "sg:address":"421 E Lawrence Ave",
    "sg:city":"Ellwood City",
    "sg:classifiers":[
        {
            "category":"Autos & Motor Vehicles",
            "subcategory":"Auto Supplies",
            "type":"Retail Goods"
        }
    ],
    "sg:phone":"+1 724 752 1265",
    "sg:postcode":"16117",
    "sg:province":"PA",
    "sg:tags":[
        "automobile",
        "parts"
    ],
    "wof:name":"H & H General Tire",
    "wof:placetype":"venue"
},
  "geometry": {"coordinates":[-80.286997,40.85845],"type":"Point"}
}