{
  "type": "Feature",
  "properties": {
    "iso:country":"US",
    "sg:address":"229 Howard St",
    "sg:city":"Waverly",
    "sg:classifiers":[
        {
            "category":"Manufacturing",
            "subcategory":"Retail Goods",
            "type":"Manufacturing & Wholesale Goods"
        },
        {
            "category":"Manufacturing",
            "subcategory":"Rubber & Plastics",
            "type":"Manufacturing & Wholesale Goods"
        }
    ],
    "sg:phone":"+1 607 565 8187",
    "sg:postcode":"14892",
    "sg:province":"PA",
    "sg:tags":[
        "product",
        "polyester",
        "laminated",
        "mfr",
        "simulated",
        "marble",
        "manufacturer"
    ],
    "wof:name":"Rynone Manufacturing Corp",
    "wof:placetype":"venue"
},
  "geometry": {"coordinates":[-76.532597,42.002629],"type":"Point"}
}