{
  "type": "Feature",
  "properties": {
    "iso:country":"US",
    "sg:address":"660 Beatty Rd",
    "sg:city":"Monroeville",
    "sg:classifiers":[
        {
            "category":"Building & Trades",
            "subcategory":"Construction",
            "type":"Services"
        }
    ],
    "sg:phone":"+1   ",
    "sg:postcode":"15146",
    "sg:province":"PA",
    "sg:tags":[
        "contractor"
    ],
    "wof:name":"Victor Ficorilli Masonry",
    "wof:placetype":"venue"
},
  "geometry": {"coordinates":[-79.742891,40.441742],"type":"Point"}
}