{
  "type": "Feature",
  "properties": {
    "addr:full":"7020 Cresheim Rd Philadelphia PA 19119",
    "addr:housenumber":"7020",
    "addr:postcode":"19119",
    "addr:street":"Cresheim Rd",
    "iso:country":"US",
    "sg:address":"7020 Cresheim Rd",
    "sg:city":"Philadelphia",
    "sg:classifiers":[
        {
            "category":"Shopping",
            "subcategory":"Pets & Pet Supplies",
            "type":"Retail Goods"
        },
        {
            "category":"Retail",
            "subcategory":"Veterinary Services",
            "type":"Services"
        }
    ],
    "sg:phone":"+1 215 247 2353",
    "sg:postcode":"19119",
    "sg:province":"PA",
    "sg:tags":[
        "specialty"
    ],
    "wof:name":"Claws To Paws Sitting Service",
    "wof:placetype":"venue"
},
  "geometry": {"coordinates":[-75.191997,40.054747],"type":"Point"}
}