{
  "type": "Feature",
  "properties": {
    "iso:country":"US",
    "sg:address":"3309 Dekalb Blvd",
    "sg:city":"Norristown",
    "sg:classifiers":[
        {
            "category":"Personal",
            "subcategory":"Nail Salon",
            "type":"Services"
        }
    ],
    "sg:phone":"+1 610 277 8870",
    "sg:postcode":"19401",
    "sg:province":"PA",
    "wof:name":"Salon D'vikal",
    "wof:placetype":"venue"
},
  "geometry": {"coordinates":[-75.308701,40.147598],"type":"Point"}
}