{
  "type": "Feature",
  "properties": {
    "iso:country":"US",
    "sg:address":"2 Country Ln",
    "sg:city":"Lincoln University",
    "sg:classifiers":[
        {
            "category":"Building & Trades",
            "subcategory":"Construction",
            "type":"Services"
        }
    ],
    "sg:phone":"+1   ",
    "sg:postcode":"19352",
    "sg:province":"PA",
    "sg:tags":[
        "residential"
    ],
    "wof:name":"Holl Art Construction",
    "wof:placetype":"venue"
},
  "geometry": {"coordinates":[-75.89196699999999,39.789733],"type":"Point"}
}