{
  "type": "Feature",
  "properties": {
    "iso:country":"US",
    "sg:address":"688 Hidden Valley Rd",
    "sg:city":"King Of Prussia",
    "sg:classifiers":[
        {
            "category":"Wholesale",
            "subcategory":"Non-durable Goods",
            "type":"Manufacturing & Wholesale Goods"
        }
    ],
    "sg:phone":"+1 610 265 4847",
    "sg:postcode":"19406",
    "sg:province":"PA",
    "sg:tags":[
        "advertising"
    ],
    "wof:name":"Designing Ducks",
    "wof:placetype":"venue"
},
  "geometry": {"coordinates":[-75.377512,40.111258],"type":"Point"}
}