{
  "type": "Feature",
  "properties": {
    "addr:full":"3414 4th Ave Beaver Falls PA 15010",
    "addr:housenumber":"3414",
    "addr:postcode":"15010",
    "addr:street":"4Th Ave",
    "iso:country":"US",
    "sg:address":"3414 4th Ave",
    "sg:city":"Beaver Falls",
    "sg:classifiers":[
        {
            "category":"Retail",
            "subcategory":"Laundry & Dry Cleaning",
            "type":"Services"
        }
    ],
    "sg:phone":"+1 724 843 3070",
    "sg:postcode":"15010",
    "sg:province":"PA",
    "sg:tags":[
        "cleaners"
    ],
    "wof:name":"Bonacci Cleaners Inc",
    "wof:placetype":"venue"
},
  "geometry": {"coordinates":[-80.324072,40.776061],"type":"Point"}
}