{
  "type": "Feature",
  "properties": {
    "addr:full":"7 E Main St Fawn Grove PA 17321",
    "addr:housenumber":"7",
    "addr:postcode":"17321",
    "addr:street":"E Main St",
    "iso:country":"US",
    "sg:address":"7 E Main St",
    "sg:city":"Fawn Grove",
    "sg:classifiers":[
        {
            "category":"Government",
            "subcategory":"Post Office",
            "type":"Public Place"
        }
    ],
    "sg:phone":"+1 717 382 4365",
    "sg:postcode":"17321",
    "sg:province":"PA",
    "wof:name":"US Post Office",
    "wof:placetype":"venue"
},
  "geometry": {"coordinates":[-76.450181,39.727741],"type":"Point"}
}