{
  "type": "Feature",
  "properties": {
    "iso:country":"US",
    "sg:address":"1439 N Broad St",
    "sg:city":"Allentown",
    "sg:classifiers":[
        {
            "category":"Real Estate",
            "subcategory":"Developer",
            "type":"Services"
        }
    ],
    "sg:phone":"+1   ",
    "sg:postcode":"18104",
    "sg:province":"PA",
    "wof:name":"Colonial Land & Development Co",
    "wof:placetype":"venue"
},
  "geometry": {"coordinates":[-75.52454,40.612226],"type":"Point"}
}