{
  "type": "Feature",
  "properties": {
    "iso:country":"US",
    "sg:address":"240 N 3rd St",
    "sg:city":"Conneaut Lake",
    "sg:classifiers":[
        {
            "category":"Organizations",
            "subcategory":"Religious Organization",
            "type":"Services"
        }
    ],
    "sg:phone":"+1 814 382 1121",
    "sg:postcode":"16316",
    "sg:province":"PA",
    "sg:tags":[
        "church"
    ],
    "wof:name":"Trinity United Methodist Chr",
    "wof:placetype":"venue"
},
  "geometry": {"coordinates":[-80.30472399999999,41.605477],"type":"Point"}
}