{
  "type": "Feature",
  "properties": {
    "iso:country":"US",
    "sg:address":"138 Jaffrey Rd",
    "sg:city":"Malvern",
    "sg:classifiers":[
        {
            "category":"Real Estate",
            "subcategory":"Real Estate Agent",
            "type":"Services"
        }
    ],
    "sg:phone":"+1 610 644 1369",
    "sg:postcode":"19355",
    "sg:province":"PA",
    "wof:name":"Hansen Development Corp",
    "wof:placetype":"venue"
},
  "geometry": {"coordinates":[-75.493796,40.013955],"type":"Point"}
}