{
  "type": "Feature",
  "properties": {
    "iso:country":"US",
    "sg:address":"2828 Egypt Rd",
    "sg:city":"Norristown",
    "sg:classifiers":[
        {
            "category":"Professional",
            "subcategory":"Research",
            "type":"Services"
        }
    ],
    "sg:phone":"+1   ",
    "sg:postcode":"19403",
    "sg:province":"PA",
    "sg:tags":[
        "nonphysical",
        "commercial"
    ],
    "wof:name":"Haas Assoc",
    "wof:placetype":"venue"
},
  "geometry": {"coordinates":[-75.43629,40.130103],"type":"Point"}
}