{
  "type": "Feature",
  "properties": {
    "iso:country":"US",
    "sg:address":"127 Dogwood Dr",
    "sg:city":"Narvon",
    "sg:classifiers":[
        {
            "category":"Building & Trades",
            "subcategory":"Construction",
            "type":"Services"
        }
    ],
    "sg:phone":"+1   ",
    "sg:postcode":"17555",
    "sg:province":"PA",
    "sg:tags":[
        "house"
    ],
    "wof:name":"Scott Taylor Construction Serv",
    "wof:placetype":"venue"
},
  "geometry": {"coordinates":[-76.010063,40.195883],"type":"Point"}
}