{
  "type": "Feature",
  "properties": {
    "iso:country":"US",
    "sg:address":"340 E Chestnut St",
    "sg:city":"Mifflinburg",
    "sg:classifiers":[
        {
            "category":"Retail",
            "subcategory":"Auto Repair",
            "type":"Services"
        }
    ],
    "sg:phone":"+1 570 966 7860",
    "sg:postcode":"17844",
    "sg:province":"PA",
    "sg:tags":[
        "repairing",
        "automobile"
    ],
    "wof:name":"Steve Shannon Tire & Auto Ctr",
    "wof:placetype":"venue"
},
  "geometry": {"coordinates":[-77.029135,40.924086],"type":"Point"}
}