{
  "type": "Feature",
  "properties": {
    "iso:country":"US",
    "sg:address":"105 Arnold Palmer Dr",
    "sg:city":"Grove City",
    "sg:classifiers":[
        {
            "category":"Real Estate",
            "subcategory":"Real Estate Agent",
            "type":"Services"
        }
    ],
    "sg:phone":"+1   ",
    "sg:postcode":"16127",
    "sg:province":"PA",
    "wof:name":"Jwc Holdings Inc",
    "wof:placetype":"venue"
},
  "geometry": {"coordinates":[-80.12139000000001,41.152771],"type":"Point"}
}