{
  "type": "Feature",
  "properties": {
    "iso:country":"US",
    "sg:address":"566 Miller Ave",
    "sg:city":"Clairton",
    "sg:classifiers":[
        {
            "category":"Shopping",
            "subcategory":"Clothing, Apparel, & Fashions",
            "type":"Retail Goods"
        }
    ],
    "sg:phone":"+1 412 233 2505",
    "sg:postcode":"15025",
    "sg:province":"PA",
    "sg:tags":[
        "a",
        "merchandise"
    ],
    "wof:name":"Jus Us",
    "wof:placetype":"venue"
},
  "geometry": {"coordinates":[-79.883273,40.292837],"type":"Point"}
}