{
  "type": "Feature",
  "properties": {
    "addr:full":"211 Wentzel Rd Mohnton PA 19540",
    "addr:housenumber":"211",
    "addr:postcode":"19540",
    "addr:street":"Wentzel Rd",
    "iso:country":"US",
    "sg:address":"211 Wentzel Rd",
    "sg:city":"Mohnton",
    "sg:classifiers":[
        {
            "category":"Building & Trades",
            "subcategory":"Construction",
            "type":"Services"
        }
    ],
    "sg:phone":"+1   ",
    "sg:postcode":"19540",
    "sg:province":"PA",
    "sg:tags":[
        "contractor"
    ],
    "wof:name":"Ringler Masonry",
    "wof:placetype":"venue"
},
  "geometry": {"coordinates":[-76.020588,40.234152],"type":"Point"}
}