{
  "type": "Feature",
  "properties": {
    "iso:country":"US",
    "sg:address":"113 N New St",
    "sg:city":"Lititz",
    "sg:classifiers":[
        {
            "category":"Real Estate",
            "subcategory":"Real Estate Agent",
            "type":"Services"
        }
    ],
    "sg:phone":"+1   ",
    "sg:postcode":"17543",
    "sg:province":"PA",
    "wof:name":"Apex Realty of Lancaster Ltd",
    "wof:placetype":"venue"
},
  "geometry": {"coordinates":[-76.30341900000001,40.16211],"type":"Point"}
}