{
  "type": "Feature",
  "properties": {
    "addr:full":"338 W Trenton Ave Morrisville PA 19067",
    "addr:housenumber":"338",
    "addr:postcode":"19067",
    "addr:street":"W Trenton Ave",
    "iso:country":"US",
    "sg:address":"338 W Trenton Ave",
    "sg:city":"Morrisville",
    "sg:classifiers":[
        {
            "category":"Shopping",
            "type":"Retail Goods"
        }
    ],
    "sg:phone":"+1 215 736 9600",
    "sg:postcode":"19067",
    "sg:province":"PA",
    "sg:tags":[
        "telephone",
        "cellular"
    ],
    "wof:name":"Best Wireless",
    "wof:placetype":"venue"
},
  "geometry": {"coordinates":[-74.794645,40.21109],"type":"Point"}
}