{
  "type": "Feature",
  "properties": {
    "addr:full":"5365 Cortland Rd New Paris PA 15554",
    "addr:housenumber":"5365",
    "addr:postcode":"15554",
    "addr:street":"Cortland Rd",
    "iso:country":"US",
    "sg:address":"5365 Cortland Rd",
    "sg:city":"New Paris",
    "sg:classifiers":[
        {
            "category":"Food & Beverages",
            "subcategory":"Groceries & Convenience Stores",
            "type":"Retail Goods"
        }
    ],
    "sg:phone":"+1 814 839 4851",
    "sg:postcode":"15554",
    "sg:province":"PA",
    "sg:tags":[
        "independent"
    ],
    "wof:name":"Almac's Market",
    "wof:placetype":"venue"
},
  "geometry": {"coordinates":[-78.633263,40.145596],"type":"Point"}
}