{
  "type": "Feature",
  "properties": {
    "iso:country":"US",
    "sg:address":"1275 York Rd",
    "sg:city":"Gettysburg",
    "sg:classifiers":[
        {
            "category":"Shopping",
            "subcategory":"Discount & Variety Stores",
            "type":"Retail Goods"
        }
    ],
    "sg:phone":"+1 717 337 9700",
    "sg:postcode":"17325",
    "sg:province":"PA",
    "wof:name":"Dollar Tree",
    "wof:placetype":"venue"
},
  "geometry": {"coordinates":[-77.20689900000001,39.840919],"type":"Point"}
}