{
  "type": "Feature",
  "properties": {
    "iso:country":"US",
    "sg:address":"400 Chestnut St",
    "sg:city":"Mifflinburg",
    "sg:classifiers":[
        {
            "category":"Personal",
            "subcategory":"Tattoo Parlor",
            "type":"Services"
        }
    ],
    "sg:phone":"+1 570 966 7566",
    "sg:postcode":"17844",
    "sg:province":"PA",
    "sg:tags":[
        "tattooing"
    ],
    "wof:name":"3-D Art Fx Ta Ttoo & Piercing",
    "wof:placetype":"venue"
},
  "geometry": {"coordinates":[-77.047718,40.917632],"type":"Point"}
}