{
  "type": "Feature",
  "properties": {
    "addr:full":"2935 Byberry Rd Hatboro PA 19040",
    "addr:housenumber":"2935",
    "addr:postcode":"19040",
    "addr:street":"Byberry Rd",
    "iso:country":"US",
    "sg:address":"2935 Byberry Rd",
    "sg:city":"Hatboro",
    "sg:classifiers":[
        {
            "category":"Manufacturing",
            "subcategory":"Tools & Machinery",
            "type":"Manufacturing & Wholesale Goods"
        }
    ],
    "sg:phone":"+1 215 672 6510",
    "sg:postcode":"19040",
    "sg:province":"PA",
    "sg:tags":[
        "machine",
        "shop"
    ],
    "wof:name":"Chesney Precision Inc",
    "wof:placetype":"venue"
},
  "geometry": {"coordinates":[-75.09467100000001,40.170648],"type":"Point"}
}