{
  "type": "Feature",
  "properties": {
    "iso:country":"US",
    "sg:address":"3520 W 26th St",
    "sg:city":"Erie",
    "sg:classifiers":[
        {
            "category":"Education",
            "subcategory":"School",
            "type":"Public Place"
        }
    ],
    "sg:phone":"+1 814 833 1911",
    "sg:postcode":"16506",
    "sg:province":"PA",
    "wof:name":"Educational Correspondence",
    "wof:placetype":"venue"
},
  "geometry": {"coordinates":[-80.154003,42.082137],"type":"Point"}
}