{
  "type": "Feature",
  "properties": {
    "iso:country":"US",
    "sg:address":"600 Pittston Ave",
    "sg:city":"Scranton",
    "sg:classifiers":[
        {
            "category":"Restaurant",
            "type":"Food & Drink"
        }
    ],
    "sg:phone":"+1 570 347 0675",
    "sg:postcode":"18505",
    "sg:province":"PA",
    "sg:tags":[
        "eating",
        "pizza"
    ],
    "wof:name":"Vince The Pizza Prince",
    "wof:placetype":"venue"
},
  "geometry": {"coordinates":[-75.665769,41.398617],"type":"Point"}
}