{
  "type": "Feature",
  "properties": {
    "iso:country":"US",
    "sg:address":"125 W Winona Ave",
    "sg:city":"Norwood",
    "sg:classifiers":[
        {
            "category":"Organizations",
            "subcategory":"Religious Organization",
            "type":"Services"
        }
    ],
    "sg:phone":"+1 610 461 6873",
    "sg:postcode":"19074",
    "sg:province":"PA",
    "sg:tags":[
        "clergy"
    ],
    "wof:name":"John B Cartwright",
    "wof:placetype":"venue"
},
  "geometry": {"coordinates":[-75.30259599999999,39.893008],"type":"Point"}
}