{
  "type": "Feature",
  "properties": {
    "iso:country":"US",
    "sg:address":"2616 Rochester Rd",
    "sg:city":"Cranberry Twp",
    "sg:classifiers":[
        {
            "category":"Shopping",
            "subcategory":"Used Merchandise",
            "type":"Retail Goods"
        }
    ],
    "sg:phone":"+1 724 776 1772",
    "sg:postcode":"16066",
    "sg:province":"PA",
    "sg:tags":[
        "shop",
        "consignment"
    ],
    "wof:name":"Leaps & Bounds",
    "wof:placetype":"venue"
},
  "geometry": {"coordinates":[-80.120679,40.698325],"type":"Point"}
}