{
  "type": "Feature",
  "properties": {
    "iso:country":"US",
    "sg:address":"991 Bushkill Dr",
    "sg:city":"Easton",
    "sg:classifiers":[
        {
            "category":"Autos & Motor Vehicles",
            "subcategory":"Automobile Sales",
            "type":"Retail Goods"
        }
    ],
    "sg:phone":"+1 610 923 9670",
    "sg:postcode":"18042",
    "sg:province":"PA",
    "sg:tags":[
        "car"
    ],
    "sg:website":"http://www.diversifiedautomotive.com",
    "wof:name":"Diversified Automotive Services",
    "wof:placetype":"venue"
},
  "geometry": {"coordinates":[-75.21454300000001,40.701043],"type":"Point"}
}