{
  "type": "Feature",
  "properties": {
    "iso:country":"US",
    "sg:address":"3993 Huntingdon Pike",
    "sg:city":"Huntingdon Vly",
    "sg:classifiers":[
        {
            "category":"Professional",
            "type":"Services"
        }
    ],
    "sg:phone":"+1 215 947 1783",
    "sg:postcode":"19006",
    "sg:province":"PA",
    "sg:tags":[
        "establishment"
    ],
    "wof:name":"MME Inc",
    "wof:placetype":"venue"
},
  "geometry": {"coordinates":[-75.049111,40.157579],"type":"Point"}
}