{
  "type": "Feature",
  "properties": {
    "iso:country":"US",
    "sg:address":"33 N Balph Ave",
    "sg:city":"Bellevue",
    "sg:classifiers":[
        {
            "category":"Retail",
            "subcategory":"Self-service Laundry",
            "type":"Services"
        }
    ],
    "sg:phone":"+1 412 734 1166",
    "sg:postcode":"15202",
    "sg:province":"PA",
    "wof:name":"Bellevue Speed Wash",
    "wof:placetype":"venue"
},
  "geometry": {"coordinates":[-80.055114,40.496316],"type":"Point"}
}