{
  "type": "Feature",
  "properties": {
    "addr:full":"217 Indiana Ave Avonmore PA 15618",
    "addr:housenumber":"217",
    "addr:postcode":"15618",
    "addr:street":"Indiana Ave",
    "iso:country":"US",
    "sg:address":"217 Indiana Ave",
    "sg:city":"Avonmore",
    "sg:classifiers":[
        {
            "category":"Food & Beverages",
            "subcategory":"Groceries & Convenience Stores",
            "type":"Retail Goods"
        }
    ],
    "sg:phone":"+1   ",
    "sg:postcode":"15618",
    "sg:province":"PA",
    "wof:name":"Little Italy",
    "wof:placetype":"venue"
},
  "geometry": {"coordinates":[-79.469781,40.528411],"type":"Point"}
}