{
  "type": "Feature",
  "properties": {
    "iso:country":"US",
    "sg:address":"197 E Main St",
    "sg:city":"Brookville",
    "sg:classifiers":[
        {
            "category":"Building & Trades",
            "subcategory":"Construction",
            "type":"Services"
        }
    ],
    "sg:phone":"+1   ",
    "sg:postcode":"15825",
    "sg:province":"PA",
    "sg:tags":[
        "house"
    ],
    "wof:name":"Aaron G L Sr Windows & Siding",
    "wof:placetype":"venue"
},
  "geometry": {"coordinates":[-79.07868999999999,41.160178],"type":"Point"}
}