{
  "type": "Feature",
  "properties": {
    "iso:country":"US",
    "sg:address":"129 E Main St",
    "sg:city":"Waynesboro",
    "sg:classifiers":[
        {
            "category":"Shopping",
            "subcategory":"Gifts & Souvenirs",
            "type":"Retail Goods"
        }
    ],
    "sg:phone":"+1 717 762 1886",
    "sg:postcode":"17268",
    "sg:province":"PA",
    "sg:tags":[
        "shop"
    ],
    "wof:name":"Country Attic",
    "wof:placetype":"venue"
},
  "geometry": {"coordinates":[-77.57669199999999,39.755186],"type":"Point"}
}