{
  "type": "Feature",
  "properties": {
    "iso:country":"US",
    "sg:address":"7 Kocher Rd",
    "sg:city":"Grove City",
    "sg:classifiers":[
        {
            "category":"Home & Garden",
            "subcategory":"Building Materials",
            "type":"Retail Goods"
        }
    ],
    "sg:phone":"+1 724 458 0844",
    "sg:postcode":"16127",
    "sg:province":"PA",
    "sg:tags":[
        "door"
    ],
    "wof:name":"Bober's Glass Block",
    "wof:placetype":"venue"
},
  "geometry": {"coordinates":[-80.08167299999999,41.145821],"type":"Point"}
}