{
  "type": "Feature",
  "properties": {
    "iso:country":"US",
    "sg:address":"102 College Ave",
    "sg:city":"Delta",
    "sg:classifiers":[
        {
            "category":"Home & Garden",
            "subcategory":"Furniture",
            "type":"Retail Goods"
        }
    ],
    "sg:phone":"+1 717 456 7204",
    "sg:postcode":"17314",
    "sg:province":"PA",
    "wof:name":"Slate Quarry Furniture",
    "wof:placetype":"venue"
},
  "geometry": {"coordinates":[-76.326179,39.726453],"type":"Point"}
}