{
  "type": "Feature",
  "properties": {
    "iso:country":"US",
    "sg:address":"805 E Main St",
    "sg:city":"Norristown",
    "sg:classifiers":[
        {
            "category":"Retail",
            "subcategory":"Auto Repair",
            "type":"Services"
        }
    ],
    "sg:phone":"+1 610 272 3604",
    "sg:postcode":"19401",
    "sg:province":"PA",
    "sg:tags":[
        "wrecker"
    ],
    "wof:name":"De Angelis Garage",
    "wof:placetype":"venue"
},
  "geometry": {"coordinates":[-75.33104299999999,40.109956],"type":"Point"}
}