{
  "type": "Feature",
  "properties": {
    "iso:country":"US",
    "sg:address":"1933 State St",
    "sg:city":"St Marys",
    "sg:classifiers":[
        {
            "category":"Education",
            "subcategory":"Library",
            "type":"Public Place"
        }
    ],
    "sg:phone":"+1 814 781 4350",
    "sg:postcode":"15857",
    "sg:province":"PA",
    "sg:tags":[
        "special",
        "interest"
    ],
    "wof:name":"Keystone Carbon Co Library",
    "wof:placetype":"venue"
},
  "geometry": {"coordinates":[-78.569947,41.421518],"type":"Point"}
}