{
  "type": "Feature",
  "properties": {
    "iso:country":"US",
    "sg:address":"3028 Harvest Rd",
    "sg:city":"Elizabethtown",
    "sg:classifiers":[
        {
            "category":"Building & Trades",
            "subcategory":"Construction",
            "type":"Services"
        }
    ],
    "sg:phone":"+1 717 367 4386",
    "sg:postcode":"17022",
    "sg:province":"PA",
    "sg:tags":[
        "fire",
        "restoration",
        "damage"
    ],
    "wof:name":"Servpro Of New Cumberland",
    "wof:placetype":"venue"
},
  "geometry": {"coordinates":[-76.52950199999999,40.191377],"type":"Point"}
}