{
  "type": "Feature",
  "properties": {
    "iso:country":"US",
    "sg:address":"7729 Main St",
    "sg:city":"Fogelsville",
    "sg:classifiers":[
        {
            "category":"Health Services",
            "subcategory":"Clinic",
            "type":"Services"
        }
    ],
    "sg:phone":"+1   ",
    "sg:postcode":"18051",
    "sg:province":"PA",
    "sg:tags":[
        "specialty",
        "outpatient"
    ],
    "wof:name":"Jeanette Eagan Mental Health",
    "wof:placetype":"venue"
},
  "geometry": {"coordinates":[-75.627137,40.584424],"type":"Point"}
}