{
  "type": "Feature",
  "properties": {
    "iso:country":"US",
    "sg:address":"452 Old 71",
    "sg:city":"Charleroi",
    "sg:classifiers":[
        {
            "category":"Retail",
            "subcategory":"Auto Repair",
            "type":"Services"
        }
    ],
    "sg:phone":"+1 724 483 7382",
    "sg:postcode":"15022",
    "sg:province":"PA",
    "sg:tags":[
        "wheel",
        "axle",
        "alignment"
    ],
    "wof:name":"Frank Rauchfuss' S Garage",
    "wof:placetype":"venue"
},
  "geometry": {"coordinates":[-79.90822900000001,40.128069],"type":"Point"}
}