{
  "type": "Feature",
  "properties": {
    "addr:full":"403 Primrose Dr Greensburg PA 15601",
    "addr:housenumber":"403",
    "addr:postcode":"15601",
    "addr:street":"Primrose Dr",
    "iso:country":"US",
    "sg:address":"403 Primrose Dr",
    "sg:city":"Greensburg",
    "sg:classifiers":[
        {
            "category":"Professional",
            "type":"Services"
        }
    ],
    "sg:phone":"+1   ",
    "sg:postcode":"15601",
    "sg:province":"PA",
    "wof:name":"Peter Cuda",
    "wof:placetype":"venue"
},
  "geometry": {"coordinates":[-79.457109,40.297053],"type":"Point"}
}