{
  "type": "Feature",
  "properties": {
    "iso:country":"US",
    "sg:address":"3233 Amber St",
    "sg:city":"Philadelphia",
    "sg:classifiers":[
        {
            "category":"Professional",
            "subcategory":"Lawyer & Legal Services",
            "type":"Services"
        }
    ],
    "sg:phone":"+1 215 425 8900",
    "sg:postcode":"19134",
    "sg:province":"PA",
    "wof:name":"Richmond Mills Lp",
    "wof:placetype":"venue"
},
  "geometry": {"coordinates":[-75.108177,39.992979],"type":"Point"}
}