{
  "type": "Feature",
  "properties": {
    "addr:full":"5418 Nicholas Ct Pipersville PA 18947",
    "addr:housenumber":"5418",
    "addr:postcode":"18947",
    "addr:street":"Nicholas Ct",
    "iso:country":"US",
    "sg:address":"5418 Nicholas Ct",
    "sg:city":"Pipersville",
    "sg:classifiers":[
        {
            "category":"Professional",
            "type":"Services"
        }
    ],
    "sg:phone":"+1   ",
    "sg:postcode":"18947",
    "sg:province":"PA",
    "wof:name":"Seltzer Corp",
    "wof:placetype":"venue"
},
  "geometry": {"coordinates":[-75.108206,40.383676],"type":"Point"}
}