{
  "type": "Feature",
  "properties": {
    "iso:country":"US",
    "sg:address":"316 Broad St",
    "sg:city":"Montoursville",
    "sg:classifiers":[
        {
            "category":"Insurance",
            "subcategory":"Insurance Agent",
            "type":"Services"
        }
    ],
    "sg:phone":"+1 570 368 8339",
    "sg:postcode":"17754",
    "sg:province":"PA",
    "wof:name":"Donna C Nibert Insurance",
    "wof:placetype":"venue"
},
  "geometry": {"coordinates":[-76.927363,41.24963],"type":"Point"}
}