{
  "type": "Feature",
  "properties": {
    "iso:country":"US",
    "sg:address":"815 Front St",
    "sg:city":"Freeland",
    "sg:classifiers":[
        {
            "category":"Wholesale",
            "subcategory":"Groceries",
            "type":"Manufacturing & Wholesale Goods"
        }
    ],
    "sg:phone":"+1 570 636 0330",
    "sg:postcode":"18224",
    "sg:province":"PA",
    "sg:tags":[
        "confectionery",
        "candy"
    ],
    "wof:name":"Tom's Wholesale",
    "wof:placetype":"venue"
},
  "geometry": {"coordinates":[-75.898038,41.018492],"type":"Point"}
}