{
  "type": "Feature",
  "properties": {
    "addr:full":"441 Hollow Rd Northumberland PA 17820",
    "addr:housenumber":"441",
    "addr:postcode":"17820",
    "addr:street":"Hollow Rd",
    "iso:country":"US",
    "sg:address":"441 Hollow Rd",
    "sg:city":"Northumberland",
    "sg:classifiers":[
        {
            "category":"Utilities",
            "subcategory":"Electric",
            "type":"Services"
        }
    ],
    "sg:phone":"+1   ",
    "sg:postcode":"17820",
    "sg:province":"PA",
    "wof:name":"Fumbery Generations",
    "wof:placetype":"venue"
},
  "geometry": {"coordinates":[-76.44669500000001,40.977285],"type":"Point"}
}