{
  "type": "Feature",
  "properties": {
    "addr:full":"51 Host Rd Womelsdorf PA 19567",
    "addr:postcode":"19567",
    "addr:street":"Host Rd",
    "iso:country":"US",
    "sg:address":"51 Host Rd",
    "sg:city":"Womelsdorf",
    "sg:classifiers":[
        {
            "category":"Utilities",
            "subcategory":"Fuel Oil & Lpg",
            "type":"Services"
        }
    ],
    "sg:phone":"+1 610 589 5840",
    "sg:postcode":"19567",
    "sg:province":"PA",
    "sg:tags":[
        "oils-fuel"
    ],
    "wof:name":"Countryside Fuel Service",
    "wof:placetype":"venue"
},
  "geometry": {"coordinates":[-76.220615,40.413422],"type":"Point"}
}