{
  "type": "Feature",
  "properties": {
    "iso:country":"US",
    "sg:address":"1230 Huntingdon Rd",
    "sg:city":"Abington",
    "sg:classifiers":[
        {
            "category":"School Buses",
            "type":"Transportation"
        }
    ],
    "sg:phone":"+1   ",
    "sg:postcode":"19001",
    "sg:province":"PA",
    "sg:tags":[
        "depot"
    ],
    "wof:name":"Romanos School Bus Service",
    "wof:placetype":"venue"
},
  "geometry": {"coordinates":[-75.116382,40.116003],"type":"Point"}
}