{
  "type": "Feature",
  "properties": {
    "addr:full":"7620 Aynlee Way Harrisburg PA 17112",
    "addr:housenumber":"7620",
    "addr:postcode":"17112",
    "addr:street":"Aynlee Way",
    "iso:country":"US",
    "sg:address":"7620 Aynlee Way",
    "sg:city":"Harrisburg",
    "sg:classifiers":[
        {
            "category":"Personal",
            "subcategory":"Beauty Salon",
            "type":"Services"
        }
    ],
    "sg:phone":"+1 717 583 1925",
    "sg:postcode":"17112",
    "sg:province":"PA",
    "sg:tags":[
        "hair",
        "stylist"
    ],
    "wof:name":"Hair By Tina",
    "wof:placetype":"venue"
},
  "geometry": {"coordinates":[-76.725177,40.328274],"type":"Point"}
}