{
  "type": "Feature",
  "properties": {
    "iso:country":"US",
    "sg:address":"100 Florence St",
    "sg:city":"Pittston",
    "sg:classifiers":[
        {
            "category":"Building & Trades",
            "subcategory":"Landscaping Services",
            "type":"Services"
        }
    ],
    "sg:phone":"+1 570 654 6942",
    "sg:postcode":"18641",
    "sg:province":"PA",
    "sg:tags":[
        "landscape",
        "contractor"
    ],
    "wof:name":"Michael Kaminski Landscaping",
    "wof:placetype":"venue"
},
  "geometry": {"coordinates":[-75.74330500000001,41.318481],"type":"Point"}
}