{
  "type": "Feature",
  "properties": {
    "addr:full":"15 N Front St Steelton PA 17113",
    "addr:housenumber":"15",
    "addr:postcode":"17113",
    "addr:street":"N Front St",
    "iso:country":"US",
    "sg:address":"15 N Front St",
    "sg:city":"Steelton",
    "sg:classifiers":[
        {
            "category":"Building & Trades",
            "subcategory":"Plumbing",
            "type":"Services"
        }
    ],
    "sg:phone":"+1 717 985 0466",
    "sg:postcode":"17113",
    "sg:province":"PA",
    "sg:tags":[
        "heating",
        "contractor"
    ],
    "wof:name":"Junior Mc Lane Co",
    "wof:placetype":"venue"
},
  "geometry": {"coordinates":[-76.840255,40.234801],"type":"Point"}
}