{
  "type": "Feature",
  "properties": {
    "iso:country":"US",
    "sg:address":"12841 Ridge Rd",
    "sg:city":"West Springfield",
    "sg:classifiers":[
        {
            "category":"Real Estate",
            "subcategory":"Real Estate Operator",
            "type":"Services"
        }
    ],
    "sg:phone":"+1   ",
    "sg:postcode":"16443",
    "sg:province":"PA",
    "sg:tags":[
        "building",
        "apartment"
    ],
    "wof:name":"Great Lake Gardens",
    "wof:placetype":"venue"
},
  "geometry": {"coordinates":[-80.444951,41.956961],"type":"Point"}
}