{
  "type": "Feature",
  "properties": {
    "iso:country":"US",
    "sg:address":"121 3rd Ave",
    "sg:city":"New Eagle",
    "sg:classifiers":[
        {
            "category":"Professional",
            "type":"Services"
        }
    ],
    "sg:phone":"+1   ",
    "sg:postcode":"15067",
    "sg:province":"PA",
    "wof:name":"Art Labels",
    "wof:placetype":"venue"
},
  "geometry": {"coordinates":[-79.94367200000001,40.203969],"type":"Point"}
}