{
  "type": "Feature",
  "properties": {
    "iso:country":"US",
    "sg:address":"120 Pine Dr",
    "sg:city":"Greencastle",
    "sg:classifiers":[
        {
            "category":"Wholesale",
            "subcategory":"Machinery & Supplies",
            "type":"Manufacturing & Wholesale Goods"
        }
    ],
    "sg:phone":"+1 717 597 7828",
    "sg:postcode":"17225",
    "sg:province":"PA",
    "sg:tags":[
        "equipment",
        "industrial"
    ],
    "sg:website":"www.transply.com",
    "wof:name":"Transply Inc",
    "wof:placetype":"venue"
},
  "geometry": {"coordinates":[-77.725111,39.751605],"type":"Point"}
}