{
  "type": "Feature",
  "properties": {
    "iso:country":"US",
    "sg:address":"1523 3rd Ave",
    "sg:city":"Duncansville",
    "sg:classifiers":[
        {
            "category":"Autos & Motor Vehicles",
            "subcategory":"Automobile Sales",
            "type":"Retail Goods"
        }
    ],
    "sg:phone":"+1 814 695 9793",
    "sg:postcode":"16635",
    "sg:province":"PA",
    "sg:tags":[
        "car",
        "dealer"
    ],
    "wof:name":"Bob's Used Cars",
    "wof:placetype":"venue"
},
  "geometry": {"coordinates":[-78.43759300000001,40.422134],"type":"Point"}
}