{
  "type": "Feature",
  "properties": {
    "addr:full":"1500 S 53rd St Philadelphia PA 19143",
    "addr:housenumber":"1500",
    "addr:postcode":"19143",
    "addr:street":"S 53Rd St",
    "iso:country":"US",
    "sg:address":"1500 S 53rd St",
    "sg:city":"Philadelphia",
    "sg:classifiers":[
        {
            "category":"Arena",
            "subcategory":"Sports Club",
            "type":"Entertainment"
        }
    ],
    "sg:phone":"+1 215 726 4149",
    "sg:postcode":"19143",
    "sg:province":"PA",
    "sg:tags":[
        "martial art"
    ],
    "wof:name":"Yong Kim",
    "wof:placetype":"venue"
},
  "geometry": {"coordinates":[-75.220392,39.939463],"type":"Point"}
}