{
  "type": "Feature",
  "properties": {
    "addr:full":"9425 Rte 422 W Shelocta PA 15774",
    "addr:postcode":"9425;15774",
    "addr:street":"Rte 422 W",
    "iso:country":"US",
    "sg:address":"9425 Rte 422 W",
    "sg:city":"Shelocta",
    "sg:classifiers":[
        {
            "category":"Wholesale",
            "subcategory":"Metals & Minerals",
            "type":"Manufacturing & Wholesale Goods"
        }
    ],
    "sg:phone":"+1 724 354 5161",
    "sg:postcode":"15774",
    "sg:province":"PA",
    "sg:tags":[
        "coal",
        "broker"
    ],
    "wof:name":"TJS Coal Sales Inc",
    "wof:placetype":"venue"
},
  "geometry": {"coordinates":[-79.300061,40.656915],"type":"Point"}
}