{
  "type": "Feature",
  "properties": {
    "addr:full":"2000 Market St Ste 2975 Philadelphia PA 19103",
    "addr:housenumber":"2000",
    "addr:postcode":"19103",
    "addr:street":"Market St Ste 2975",
    "iso:country":"US",
    "sg:address":"2000 Market St Ste 2975",
    "sg:city":"Philadelphia",
    "sg:classifiers":[
        {
            "category":"Professional",
            "subcategory":"Advertising",
            "type":"Services"
        }
    ],
    "sg:phone":"+1 215 568 5944",
    "sg:postcode":"19103",
    "sg:province":"PA",
    "sg:tags":[
        "agency",
        "specialty"
    ],
    "sg:website":"http://www.cmimedia.com",
    "wof:name":"Communications Media, Inc",
    "wof:placetype":"venue"
},
  "geometry": {"coordinates":[-75.17318,39.953571],"type":"Point"}
}