{
  "type": "Feature",
  "properties": {
    "iso:country":"US",
    "sg:address":"6 W Newport Rd",
    "sg:city":"Lititz",
    "sg:classifiers":[
        {
            "category":"Health Services",
            "subcategory":"Clinic",
            "type":"Services"
        }
    ],
    "sg:phone":"+1 717 625 4757",
    "sg:postcode":"17543",
    "sg:province":"PA",
    "wof:name":"Cornerstone Medical Imaging",
    "wof:placetype":"venue"
},
  "geometry": {"coordinates":[-76.30951899999999,40.176252],"type":"Point"}
}