{
  "type": "Feature",
  "properties": {
    "addr:full":"4423 Locust Ave Philadelphia PA 19104",
    "addr:housenumber":"4423",
    "addr:postcode":"19104",
    "addr:street":"Locust Ave",
    "iso:country":"US",
    "sg:address":"4423 Locust Ave",
    "sg:city":"Philadelphia",
    "sg:classifiers":[
        {
            "category":"Restaurant",
            "type":"Food & Drink"
        }
    ],
    "sg:phone":"+1 215 222 2208",
    "sg:postcode":"19104",
    "sg:province":"PA",
    "sg:tags":[
        "chinese"
    ],
    "sg:website":"www.chinainnphiladelphia.com/",
    "wof:name":"China Inn",
    "wof:placetype":"venue"
},
  "geometry": {"coordinates":[-75.211123,39.954003],"type":"Point"}
}