{
  "type": "Feature",
  "properties": {
    "iso:country":"US",
    "sg:address":"360 Saint Thomas Williamson Rd",
    "sg:city":"St Thomas",
    "sg:classifiers":[
        {
            "category":"Organizations",
            "subcategory":"Religious Organization",
            "type":"Services"
        }
    ],
    "sg:phone":"+1 717 369 3409",
    "sg:postcode":"17252",
    "sg:province":"PA",
    "sg:tags":[
        "church"
    ],
    "wof:name":"United Methodist Church",
    "wof:placetype":"venue"
},
  "geometry": {"coordinates":[-77.795079,39.91399],"type":"Point"}
}