{
  "type": "Feature",
  "properties": {
    "addr:full":"1149 Main St Ellwood City PA 16117",
    "addr:housenumber":"1149",
    "addr:postcode":"16117",
    "addr:street":"Main St",
    "iso:country":"US",
    "sg:address":"1149 Main St",
    "sg:city":"Ellwood City",
    "sg:classifiers":[
        {
            "category":"Building & Trades",
            "subcategory":"Landscaping Services",
            "type":"Services"
        }
    ],
    "sg:phone":"+1   ",
    "sg:postcode":"16117",
    "sg:province":"PA",
    "sg:tags":[
        "landscape"
    ],
    "wof:name":"Pleasant Surroundings",
    "wof:placetype":"venue"
},
  "geometry": {"coordinates":[-80.27044600000001,40.842231],"type":"Point"}
}