{
  "type": "Feature",
  "properties": {
    "iso:country":"US",
    "sg:address":"4967 Leah Dr",
    "sg:city":"Girard",
    "sg:classifiers":[
        {
            "category":"Building & Trades",
            "subcategory":"Landscaping Services",
            "type":"Services"
        }
    ],
    "sg:phone":"+1 814 873 5662",
    "sg:postcode":"16417",
    "sg:province":"PA",
    "sg:tags":[
        "lawn"
    ],
    "wof:name":"Horizon Landscape",
    "wof:placetype":"venue"
},
  "geometry": {"coordinates":[-80.344063,41.993911],"type":"Point"}
}