{
  "type": "Feature",
  "properties": {
    "iso:country":"US",
    "sg:address":"806 E Lawrence Ave",
    "sg:city":"Ellwood City",
    "sg:classifiers":[
        {
            "category":"Professional",
            "subcategory":"Advertising",
            "type":"Services"
        }
    ],
    "sg:phone":"+1 724 752 0661",
    "sg:postcode":"16117",
    "sg:province":"PA",
    "wof:name":"Mc Elwain Auto Group",
    "wof:placetype":"venue"
},
  "geometry": {"coordinates":[-80.29231900000001,40.858503],"type":"Point"}
}