{
  "type": "Feature",
  "properties": {
    "addr:full":"1527 Old Valley Rd West Decatur PA 16878",
    "addr:housenumber":"1527",
    "addr:postcode":"16878",
    "addr:street":"Old Valley Rd",
    "iso:country":"US",
    "sg:address":"1527 Old Valley Rd",
    "sg:city":"West Decatur",
    "sg:classifiers":[
        {
            "category":"Building & Trades",
            "subcategory":"Construction",
            "type":"Services"
        }
    ],
    "sg:phone":"+1   ",
    "sg:postcode":"16878",
    "sg:province":"PA",
    "sg:tags":[
        "residential"
    ],
    "wof:name":"D L Construction",
    "wof:placetype":"venue"
},
  "geometry": {"coordinates":[-78.345883,40.965702],"type":"Point"}
}