{
  "type": "Feature",
  "properties": {
    "addr:full":"413 E Penn St Philadelphia PA 19144",
    "addr:housenumber":"413",
    "addr:postcode":"19144",
    "addr:street":"E Penn St",
    "iso:country":"US",
    "sg:address":"413 E Penn St",
    "sg:city":"Philadelphia",
    "sg:classifiers":[
        {
            "category":"Professional",
            "type":"Services"
        }
    ],
    "sg:phone":"+1 215 438 3099",
    "sg:postcode":"19144",
    "sg:province":"PA",
    "sg:tags":[
        "establishment"
    ],
    "wof:name":"411 Maja League",
    "wof:placetype":"venue"
},
  "geometry": {"coordinates":[-75.163541,40.037146],"type":"Point"}
}