{
  "type": "Feature",
  "properties": {
    "iso:country":"US",
    "sg:address":"920 Penn St",
    "sg:city":"Hollidaysburg",
    "sg:classifiers":[
        {
            "category":"Organizations",
            "subcategory":"Professional Association",
            "type":"Services"
        }
    ],
    "sg:phone":"+1   ",
    "sg:postcode":"16648",
    "sg:province":"PA",
    "wof:name":"Blair Medical Associates",
    "wof:placetype":"venue"
},
  "geometry": {"coordinates":[-78.392118,40.437123],"type":"Point"}
}