{
  "type": "Feature",
  "properties": {
    "iso:country":"US",
    "sg:address":"6149 Saltsburg Rd",
    "sg:city":"Verona",
    "sg:classifiers":[
        {
            "category":"Social Services",
            "type":"Services"
        }
    ],
    "sg:phone":"+1   ",
    "sg:postcode":"15147",
    "sg:province":"PA",
    "sg:tags":[
        "charitable",
        "organization"
    ],
    "wof:name":"Penn Hills Center",
    "wof:placetype":"venue"
},
  "geometry": {"coordinates":[-79.81858699999999,40.484729],"type":"Point"}
}