{
  "type": "Feature",
  "properties": {
    "iso:country":"US",
    "sg:address":"10 Arch St",
    "sg:city":"Carnegie",
    "sg:classifiers":[
        {
            "category":"Wholesale",
            "subcategory":"Metals & Minerals",
            "type":"Manufacturing & Wholesale Goods"
        }
    ],
    "sg:phone":"+1 412 276 2044",
    "sg:postcode":"15106",
    "sg:province":"PA",
    "sg:tags":[
        "specialty"
    ],
    "wof:name":"Samuel Specialty Metals",
    "wof:placetype":"venue"
},
  "geometry": {"coordinates":[-80.084352,40.41257],"type":"Point"}
}