{
  "type": "Feature",
  "properties": {
    "iso:country":"US",
    "sg:address":"708 Lincoln Way E",
    "sg:city":"Mc Connellsburg",
    "sg:classifiers":[
        {
            "category":"Restaurant",
            "type":"Food & Drink"
        }
    ],
    "sg:phone":"+1   ",
    "sg:postcode":"17233",
    "sg:province":"PA",
    "sg:tags":[
        "eating"
    ],
    "wof:name":"McDonalds",
    "wof:placetype":"venue"
},
  "geometry": {"coordinates":[-77.990664,39.929779],"type":"Point"}
}