{
  "type": "Feature",
  "properties": {
    "iso:country":"US",
    "sg:address":"10747 Jeanes St",
    "sg:city":"Philadelphia",
    "sg:classifiers":[
        {
            "category":"Professional",
            "type":"Services"
        }
    ],
    "sg:phone":"+1   ",
    "sg:postcode":"19116",
    "sg:province":"PA",
    "wof:name":"D & U Products Inc",
    "wof:placetype":"venue"
},
  "geometry": {"coordinates":[-75.027851,40.111805],"type":"Point"}
}