{
  "type": "Feature",
  "properties": {
    "addr:full":"10 W Park Rd Havertown PA 19083",
    "addr:housenumber":"10",
    "addr:postcode":"19083",
    "addr:street":"W Park Rd",
    "iso:country":"US",
    "sg:address":"10 W Park Rd",
    "sg:city":"Havertown",
    "sg:classifiers":[
        {
            "category":"Retail",
            "subcategory":"Repair Shop",
            "type":"Services"
        }
    ],
    "sg:phone":"+1 610 446 3121",
    "sg:postcode":"19083",
    "sg:province":"PA",
    "sg:tags":[
        "appliance"
    ],
    "wof:name":"A-Ok Appliance Svc Co",
    "wof:placetype":"venue"
},
  "geometry": {"coordinates":[-75.298872,39.969957],"type":"Point"}
}