{
  "type": "Feature",
  "properties": {
    "addr:full":"808 Luzerne St Johnstown PA 15905",
    "addr:housenumber":"808",
    "addr:postcode":"15905",
    "addr:street":"Luzerne St",
    "iso:country":"US",
    "sg:address":"808 Luzerne St",
    "sg:city":"Johnstown",
    "sg:classifiers":[
        {
            "category":"Shopping",
            "subcategory":"Used Merchandise",
            "type":"Retail Goods"
        }
    ],
    "sg:phone":"+1 814 536 6082",
    "sg:postcode":"15905",
    "sg:province":"PA",
    "sg:tags":[
        "antique"
    ],
    "wof:name":"Black & Black",
    "wof:placetype":"venue"
},
  "geometry": {"coordinates":[-78.938979,40.317196],"type":"Point"}
}