{
  "type": "Feature",
  "properties": {
    "addr:full":"201 Ziegler St Zelienople PA 16063",
    "addr:housenumber":"201",
    "addr:postcode":"16063",
    "addr:street":"Ziegler St",
    "iso:country":"US",
    "sg:address":"201 Ziegler St",
    "sg:city":"Zelienople",
    "sg:classifiers":[
        {
            "category":"Professional",
            "subcategory":"Business Services",
            "type":"Services"
        }
    ],
    "sg:phone":"+1   ",
    "sg:postcode":"16063",
    "sg:province":"PA",
    "wof:name":"Keystone Concrete Construction",
    "wof:placetype":"venue"
},
  "geometry": {"coordinates":[-80.14063400000001,40.792617],"type":"Point"}
}