{
  "type": "Feature",
  "properties": {
    "addr:full":"3661 Williamson Rd Greencastle PA 17225",
    "addr:housenumber":"3661",
    "addr:postcode":"17225",
    "addr:street":"Williamson Rd",
    "iso:country":"US",
    "sg:address":"3661 Williamson Rd",
    "sg:city":"Greencastle",
    "sg:classifiers":[
        {
            "category":"Organizations",
            "subcategory":"Religious Organization",
            "type":"Services"
        }
    ],
    "sg:phone":"+1 717 597 3869",
    "sg:postcode":"17225",
    "sg:province":"PA",
    "sg:tags":[
        "church"
    ],
    "wof:name":"Ebenezer Brethren In Christ",
    "wof:placetype":"venue"
},
  "geometry": {"coordinates":[-77.772133,39.838019],"type":"Point"}
}