{
  "type": "Feature",
  "properties": {
    "addr:full":"1102 E Windhaven Rd Pittsburgh PA 15205",
    "addr:housenumber":"1102",
    "addr:postcode":"15205",
    "addr:street":"E Windhaven Rd",
    "iso:country":"US",
    "sg:address":"1102 E Windhaven Rd",
    "sg:city":"Pittsburgh",
    "sg:classifiers":[
        {
            "category":"Building & Trades",
            "subcategory":"Construction",
            "type":"Services"
        }
    ],
    "sg:phone":"+1 412 787 2748",
    "sg:postcode":"15205",
    "sg:province":"PA",
    "sg:tags":[
        "layer",
        "carpet"
    ],
    "wof:name":"Ralph Seibel Carpet Svc",
    "wof:placetype":"venue"
},
  "geometry": {"coordinates":[-80.102232,40.444213],"type":"Point"}
}