{
  "type": "Feature",
  "properties": {
    "iso:country":"US",
    "sg:address":"33 Midland St",
    "sg:city":"Simpson",
    "sg:classifiers":[
        {
            "category":"Organizations",
            "subcategory":"Religious Organization",
            "type":"Services"
        }
    ],
    "sg:phone":"+1 570 282 2314",
    "sg:postcode":"18407",
    "sg:province":"PA",
    "sg:tags":[
        "church"
    ],
    "wof:name":"St Basil's Russian Church",
    "wof:placetype":"venue"
},
  "geometry": {"coordinates":[-75.48585,41.594623],"type":"Point"}
}