{
  "type": "Feature",
  "properties": {
    "iso:country":"US",
    "sg:address":"971 Liberty Ave",
    "sg:city":"Pittsburgh",
    "sg:phone":"+1 412 456 0460",
    "sg:postcode":"15222",
    "sg:province":"PA",
    "wof:name":"Liberty Tavern",
    "wof:placetype":"venue"
},
  "geometry": {"coordinates":[-79.996169,40.44338],"type":"Point"}
}