{
  "type": "Feature",
  "properties": {
    "addr:full":"27 Walsh Rd Pittsburgh PA 15205",
    "addr:housenumber":"27",
    "addr:postcode":"15205",
    "addr:street":"Walsh Rd",
    "iso:country":"US",
    "sg:address":"27 Walsh Rd",
    "sg:city":"Pittsburgh",
    "sg:classifiers":[
        {
            "category":"Shopping",
            "subcategory":"Mobile Phones",
            "type":"Retail Goods"
        }
    ],
    "sg:phone":"+1 412 921 7010",
    "sg:postcode":"15205",
    "sg:province":"PA",
    "wof:name":"Cricket",
    "wof:placetype":"venue"
},
  "geometry": {"coordinates":[-80.071259,40.439232],"type":"Point"}
}