{
  "type": "Feature",
  "properties": {
    "iso:country":"US",
    "sg:address":"6 Red Oak Rd",
    "sg:city":"Oreland",
    "sg:classifiers":[
        {
            "category":"Retail",
            "subcategory":"Laundry & Dry Cleaning",
            "type":"Services"
        }
    ],
    "sg:phone":"+1   ",
    "sg:postcode":"19075",
    "sg:province":"PA",
    "sg:tags":[
        "fire",
        "water",
        "damage",
        "smoke"
    ],
    "wof:name":"Liberty Clg & Restoration Co",
    "wof:placetype":"venue"
},
  "geometry": {"coordinates":[-75.180296,40.110318],"type":"Point"}
}