{
  "type": "Feature",
  "properties": {
    "iso:country":"US",
    "sg:address":"650 S 13th St",
    "sg:city":"Indiana",
    "sg:classifiers":[
        {
            "category":"Building & Trades",
            "subcategory":"Cleaning & Sanitation",
            "type":"Services"
        }
    ],
    "sg:phone":"+1   ",
    "sg:postcode":"15701",
    "sg:province":"PA",
    "sg:tags":[
        "repair",
        "maintenance",
        "business"
    ],
    "wof:name":"Mgmnt Services Group",
    "wof:placetype":"venue"
},
  "geometry": {"coordinates":[-79.16631099999999,40.610727],"type":"Point"}
}