{
  "type": "Feature",
  "properties": {
    "iso:country":"US",
    "sg:address":"326 Main St",
    "sg:city":"Simpson",
    "sg:classifiers":[
        {
            "category":"Retail",
            "subcategory":"Repair Shop",
            "type":"Services"
        }
    ],
    "sg:phone":"+1 570 282 2835",
    "sg:postcode":"18407",
    "sg:province":"PA",
    "sg:tags":[
        "scooter",
        "motorcycle",
        "motor"
    ],
    "wof:name":"Main Jet Technologies",
    "wof:placetype":"venue"
},
  "geometry": {"coordinates":[-75.528109,41.553372],"type":"Point"}
}