{
  "type": "Feature",
  "properties": {
    "addr:full":"777 Water St Champion PA 15681",
    "addr:housenumber":"777",
    "addr:postcode":"15681",
    "addr:street":"Water St",
    "iso:country":"US",
    "sg:address":"777 Water St",
    "sg:city":"Champion",
    "sg:classifiers":[
        {
            "category":"Professional",
            "subcategory":"Art Services",
            "type":"Services"
        }
    ],
    "sg:phone":"+1 814 352 7377",
    "sg:postcode":"15681",
    "sg:province":"PA",
    "sg:tags":[
        "photographer"
    ],
    "sg:website":"www.mtmphoto.com",
    "wof:name":"Mountain Memories",
    "wof:placetype":"venue"
},
  "geometry": {"coordinates":[-79.45083099999999,40.48266],"type":"Point"}
}