{
  "type": "Feature",
  "properties": {
    "iso:country":"US",
    "sg:address":"2703 5th Ave",
    "sg:city":"Mckeesport",
    "sg:classifiers":[
        {
            "category":"Autos & Motor Vehicles",
            "subcategory":"Automobile Sales",
            "type":"Retail Goods"
        }
    ],
    "sg:phone":"+1 412 678 1561",
    "sg:postcode":"15132",
    "sg:province":"PA",
    "sg:tags":[
        "car",
        "dealer"
    ],
    "wof:name":"Joe's Auto Sales",
    "wof:placetype":"venue"
},
  "geometry": {"coordinates":[-79.83310299999999,40.356901],"type":"Point"}
}