{
  "type": "Feature",
  "properties": {
    "iso:country":"US",
    "sg:address":"5038 Iron Bridge Rd",
    "sg:city":"Waynesboro",
    "sg:phone":"+1   ",
    "sg:postcode":"17268",
    "sg:province":"PA",
    "sg:tags":[
        "farm",
        "corn"
    ],
    "wof:name":"Richard Showalter",
    "wof:placetype":"venue"
},
  "geometry": {"coordinates":[-77.642864,39.727907],"type":"Point"}
}