{
  "type": "Feature",
  "properties": {
    "iso:country":"US",
    "sg:address":"218 W Lloyd St",
    "sg:city":"Ebensburg",
    "sg:classifiers":[
        {
            "category":"Organizations",
            "subcategory":"Religious Organization",
            "type":"Services"
        }
    ],
    "sg:phone":"+1   ",
    "sg:postcode":"15931",
    "sg:province":"PA",
    "wof:name":"Carmelite Community of Word",
    "wof:placetype":"venue"
},
  "geometry": {"coordinates":[-78.727,40.484233],"type":"Point"}
}