{
  "type": "Feature",
  "properties": {
    "iso:country":"US",
    "sg:address":"814 S Main St Exd",
    "sg:city":"Punxsutawney",
    "sg:classifiers":[
        {
            "category":"Wholesale",
            "subcategory":"Groceries",
            "type":"Manufacturing & Wholesale Goods"
        }
    ],
    "sg:phone":"+1 814 938 7430",
    "sg:postcode":"15767",
    "sg:province":"PA",
    "sg:tags":[
        "baker"
    ],
    "wof:name":"Stroehanns Bakeries LLC",
    "wof:placetype":"venue"
},
  "geometry": {"coordinates":[-78.98763099999999,40.929872],"type":"Point"}
}