{
  "type": "Feature",
  "properties": {
    "addr:full":"9115 W Chester Pike Upper Darby PA 19082",
    "addr:housenumber":"9115",
    "addr:postcode":"19082",
    "addr:street":"W Chester Pike",
    "iso:country":"US",
    "sg:address":"9115 W Chester Pike",
    "sg:city":"Upper Darby",
    "sg:classifiers":[
        {
            "category":"Retail",
            "subcategory":"Auto Repair",
            "type":"Services"
        }
    ],
    "sg:phone":"+1   ",
    "sg:postcode":"19082",
    "sg:province":"PA",
    "sg:tags":[
        "automotive"
    ],
    "wof:name":"J Sunys Auto Repair",
    "wof:placetype":"venue"
},
  "geometry": {"coordinates":[-75.291847,39.968025],"type":"Point"}
}