{
  "type": "Feature",
  "properties": {
    "iso:country":"US",
    "sg:address":"112 Townhouse Ln",
    "sg:city":"Lancaster",
    "sg:classifiers":[
        {
            "category":"Manufacturing",
            "subcategory":"Lumber",
            "type":"Manufacturing & Wholesale Goods"
        }
    ],
    "sg:phone":"+1   ",
    "sg:postcode":"17603",
    "sg:province":"PA",
    "sg:tags":[
        "logging"
    ],
    "wof:name":"Bauman Logging",
    "wof:placetype":"venue"
},
  "geometry": {"coordinates":[-76.36641400000001,40.02527],"type":"Point"}
}