{
  "type": "Feature",
  "properties": {
    "iso:country":"US",
    "sg:address":"300 Market St",
    "sg:city":"Johnstown",
    "sg:classifiers":[
        {
            "category":"Building & Trades",
            "subcategory":"Construction",
            "type":"Services"
        }
    ],
    "sg:phone":"+1 814 535 5549",
    "sg:postcode":"15901",
    "sg:province":"PA",
    "sg:tags":[
        "company"
    ],
    "wof:name":"Zamias Construction",
    "wof:placetype":"venue"
},
  "geometry": {"coordinates":[-78.92141100000001,40.323885],"type":"Point"}
}