{
  "type": "Feature",
  "properties": {
    "addr:full":"4141 Ben Miller Rd Gibsonia PA 15044",
    "addr:housenumber":"4141",
    "addr:postcode":"15044",
    "addr:street":"Ben Miller Rd",
    "iso:country":"US",
    "sg:address":"4141 Ben Miller Rd",
    "sg:city":"Gibsonia",
    "sg:classifiers":[
        {
            "category":"Arts & Performance",
            "subcategory":"Theater",
            "type":"Entertainment"
        }
    ],
    "sg:phone":"+1 724 443 5232",
    "sg:postcode":"15044",
    "sg:province":"PA",
    "sg:tags":[
        "live",
        "music"
    ],
    "wof:name":"Denny Dutko Disc Jockey Svc",
    "wof:placetype":"venue"
},
  "geometry": {"coordinates":[-79.95904299999999,40.622962],"type":"Point"}
}