{
  "type": "Feature",
  "properties": {
    "iso:country":"US",
    "sg:address":"147 Birchwood Way",
    "sg:city":"Irwin",
    "sg:classifiers":[
        {
            "category":"Shopping",
            "type":"Retail Goods"
        }
    ],
    "sg:phone":"+1 412 298 9943",
    "sg:postcode":"15642",
    "sg:province":"PA",
    "sg:tags":[
        "merchandising"
    ],
    "wof:name":"Tnt Industries",
    "wof:placetype":"venue"
},
  "geometry": {"coordinates":[-79.681236,40.353458],"type":"Point"}
}