{
  "type": "Feature",
  "properties": {
    "iso:country":"US",
    "sg:address":"4050 Washington Rd",
    "sg:city":"Mc Murray",
    "sg:classifiers":[
        {
            "category":"Real Estate",
            "subcategory":"Real Estate Agent",
            "type":"Services"
        }
    ],
    "sg:phone":"+1 724 941 4897",
    "sg:postcode":"15317",
    "sg:province":"PA",
    "sg:tags":[
        "desk",
        "space"
    ],
    "wof:name":"Rauch Building",
    "wof:placetype":"venue"
},
  "geometry": {"coordinates":[-80.128446,40.270132],"type":"Point"}
}