{
  "type": "Feature",
  "properties": {
    "addr:full":"510 W Chester Rd West Chester PA 19382",
    "addr:housenumber":"510",
    "addr:postcode":"19382",
    "addr:street":"W Chester Rd",
    "iso:country":"US",
    "sg:address":"510 W Chester Rd",
    "sg:city":"West Chester",
    "sg:classifiers":[
        {
            "category":"Building & Trades",
            "subcategory":"Landscaping Services",
            "type":"Services"
        }
    ],
    "sg:phone":"+1 610 344 0794",
    "sg:postcode":"19382",
    "sg:province":"PA",
    "sg:tags":[
        "landscape",
        "contractor"
    ],
    "wof:name":"Finnerty Landscaping",
    "wof:placetype":"venue"
},
  "geometry": {"coordinates":[-75.545214,39.910792],"type":"Point"}
}