{
  "type": "Feature",
  "properties": {
    "iso:country":"US",
    "sg:address":"7 Cross Trl",
    "sg:city":"Fairfield",
    "sg:classifiers":[
        {
            "category":"Travel",
            "subcategory":"Travel Agent",
            "type":"Entertainment"
        }
    ],
    "sg:phone":"+1 717 642 6682",
    "sg:postcode":"17320",
    "sg:province":"PA",
    "sg:tags":[
        "agency",
        "bureau"
    ],
    "wof:name":"Imagination Travel",
    "wof:placetype":"venue"
},
  "geometry": {"coordinates":[-77.38111000000001,39.753928],"type":"Point"}
}