{
  "type": "Feature",
  "properties": {
    "addr:full":"464 W Main St Tremont PA 17981",
    "addr:housenumber":"464",
    "addr:postcode":"17981",
    "addr:street":"W Main St",
    "iso:country":"US",
    "sg:address":"464 W Main St",
    "sg:city":"Tremont",
    "sg:classifiers":[
        {
            "category":"Retail",
            "subcategory":"Animal Services",
            "type":"Services"
        }
    ],
    "sg:phone":"+1 570 695 3392",
    "sg:postcode":"17981",
    "sg:province":"PA",
    "wof:name":"Precious Grooming",
    "wof:placetype":"venue"
},
  "geometry": {"coordinates":[-76.396559,40.626766],"type":"Point"}
}