{
  "type": "Feature",
  "properties": {
    "addr:full":"1314 Axton St Belle Vernon PA 15012",
    "addr:housenumber":"1314",
    "addr:postcode":"15012",
    "addr:street":"Axton St",
    "iso:country":"US",
    "sg:address":"1314 Axton St",
    "sg:city":"Belle Vernon",
    "sg:classifiers":[
        {
            "category":"Government",
            "subcategory":"Fire Station",
            "type":"Public Place"
        }
    ],
    "sg:phone":"+1   ",
    "sg:postcode":"15012",
    "sg:province":"PA",
    "sg:tags":[
        "department",
        "volunteer"
    ],
    "wof:name":"Washington Volunteer Fire Co",
    "wof:placetype":"venue"
},
  "geometry": {"coordinates":[-79.84102,40.118283],"type":"Point"}
}