{
  "type": "Feature",
  "properties": {
    "iso:country":"US",
    "sg:address":"6720 Perkiomen Ave",
    "sg:city":"Birdsboro",
    "sg:classifiers":[
        {
            "category":"Shopping",
            "subcategory":"Used Merchandise",
            "type":"Retail Goods"
        }
    ],
    "sg:phone":"+1 610 404 3868",
    "sg:postcode":"19508",
    "sg:province":"PA",
    "sg:tags":[
        "shop",
        "consignment"
    ],
    "wof:name":"Julie Anne's Cottage",
    "wof:placetype":"venue"
},
  "geometry": {"coordinates":[-75.817582,40.287828],"type":"Point"}
}