{
  "type": "Feature",
  "properties": {
    "addr:full":"Commerce Sq Philadelphia PA 19102",
    "addr:postcode":"19102",
    "addr:street":"Commerce Sq",
    "iso:country":"US",
    "sg:address":"Commerce Sq",
    "sg:city":"Philadelphia",
    "sg:classifiers":[
        {
            "category":"Professional",
            "subcategory":"Lawyer & Legal Services",
            "type":"Services"
        }
    ],
    "sg:phone":"+1 215 851 6702",
    "sg:postcode":"19102",
    "sg:province":"PA",
    "wof:name":"Ziff Lloyd R Atty",
    "wof:placetype":"venue"
},
  "geometry": {"coordinates":[-75.16490400000001,39.949064],"type":"Point"}
}