{
  "type": "Feature",
  "properties": {
    "addr:full":"1545 Devils Elbow Rd Jersey Shore PA 17740",
    "addr:housenumber":"1545",
    "addr:postcode":"17740",
    "addr:street":"Devils Elbow Rd",
    "iso:country":"US",
    "sg:address":"1545 Devils Elbow Rd",
    "sg:city":"Jersey Shore",
    "sg:classifiers":[
        {
            "category":"Autos & Motor Vehicles",
            "subcategory":"Automobile Sales",
            "type":"Retail Goods"
        }
    ],
    "sg:phone":"+1 570 398 1580",
    "sg:postcode":"17740",
    "sg:province":"PA",
    "sg:tags":[
        "car",
        "dealer"
    ],
    "wof:name":"Louis Sheddy Used Auto's",
    "wof:placetype":"venue"
},
  "geometry": {"coordinates":[-77.211378,41.243607],"type":"Point"}
}