{
  "type": "Feature",
  "properties": {
    "addr:full":"26 Cypress Ln Berwyn PA 19312",
    "addr:housenumber":"26",
    "addr:postcode":"19312",
    "addr:street":"Cypress Ln",
    "iso:country":"US",
    "sg:address":"26 Cypress Ln",
    "sg:city":"Berwyn",
    "sg:classifiers":[
        {
            "category":"Professional",
            "subcategory":"Management & Consulting",
            "type":"Services"
        },
        {
            "category":"Professional",
            "subcategory":"Engineering",
            "type":"Services"
        }
    ],
    "sg:phone":"+1 610 695 8069",
    "sg:postcode":"19312",
    "sg:province":"PA",
    "sg:tags":[
        "environmental",
        "ecological",
        "engineer",
        "consultant"
    ],
    "wof:name":"Geologos",
    "wof:placetype":"venue"
},
  "geometry": {"coordinates":[-75.46643,40.053346],"type":"Point"}
}