{
  "type": "Feature",
  "properties": {
    "iso:country":"US",
    "sg:address":"109 Lilac Ct",
    "sg:city":"Northampton",
    "sg:classifiers":[
        {
            "category":"Restaurant",
            "type":"Food & Drink"
        },
        {
            "category":"Food & Beverages",
            "subcategory":"Meat & Fish",
            "type":"Retail Goods"
        }
    ],
    "sg:phone":"+1 610 262 3333",
    "sg:postcode":"18067",
    "sg:province":"PA",
    "sg:tags":[
        "seafood",
        "market"
    ],
    "wof:name":"Northampton Seafood Inc",
    "wof:placetype":"venue"
},
  "geometry": {"coordinates":[-75.49809999999999,40.690498],"type":"Point"}
}