{
  "type": "Feature",
  "properties": {
    "addr:full":"207 Colonial Dr Langhorne PA 19047",
    "addr:housenumber":"207",
    "addr:postcode":"19047",
    "addr:street":"Colonial Dr",
    "iso:country":"US",
    "sg:address":"207 Colonial Dr",
    "sg:city":"Langhorne",
    "sg:classifiers":[
        {
            "category":"Food & Beverages",
            "subcategory":"Specialty",
            "type":"Retail Goods"
        }
    ],
    "sg:phone":"+1 215 752 1270",
    "sg:postcode":"19047",
    "sg:province":"PA",
    "sg:tags":[
        "health",
        "diet"
    ],
    "wof:name":"Nature's Garden Of Health",
    "wof:placetype":"venue"
},
  "geometry": {"coordinates":[-74.938033,40.169049],"type":"Point"}
}