{
  "type": "Feature",
  "properties": {
    "iso:country":"US",
    "sg:address":"280 Kerrwood Dr",
    "sg:city":"Wayne",
    "sg:classifiers":[
        {
            "category":"Home & Garden",
            "subcategory":"Building Materials",
            "type":"Retail Goods"
        }
    ],
    "sg:phone":"+1 610 688 7243",
    "sg:postcode":"19087",
    "sg:province":"PA",
    "sg:tags":[
        "downspouts",
        "gutter"
    ],
    "wof:name":"Tilt 'N Clean Rain Gutter Systems",
    "wof:placetype":"venue"
},
  "geometry": {"coordinates":[-75.390692,40.079595],"type":"Point"}
}