{
  "type": "Feature",
  "properties": {
    "addr:full":"401 E Elm St Conshohocken PA 19428",
    "addr:housenumber":"401",
    "addr:postcode":"19428",
    "addr:street":"E Elm St",
    "iso:country":"US",
    "sg:address":"401 E Elm St",
    "sg:city":"Conshohocken",
    "sg:classifiers":[
        {
            "category":"Social Services",
            "type":"Services"
        }
    ],
    "sg:phone":"+1 610 834 8566",
    "sg:postcode":"19428",
    "sg:province":"PA",
    "sg:tags":[
        "instruction",
        "health",
        "care"
    ],
    "wof:name":"Health Care Resolutions",
    "wof:placetype":"venue"
},
  "geometry": {"coordinates":[-75.29769899999999,40.073153],"type":"Point"}
}