{
  "type": "Feature",
  "properties": {
    "iso:country":"US",
    "sg:address":"2050 Esten Rd",
    "sg:city":"Quakertown",
    "sg:classifiers":[
        {
            "category":"Building & Trades",
            "subcategory":"Landscaping Services",
            "type":"Services"
        }
    ],
    "sg:phone":"+1 215 538 5318",
    "sg:postcode":"18951",
    "sg:province":"PA",
    "sg:tags":[
        "landscape",
        "contractor"
    ],
    "wof:name":"Herb's Landscaping",
    "wof:placetype":"venue"
},
  "geometry": {"coordinates":[-75.39958799999999,40.400565],"type":"Point"}
}