{
  "type": "Feature",
  "properties": {
    "addr:full":"1635 Market St Philadelphia PA 19103",
    "addr:housenumber":"1635",
    "addr:postcode":"19103",
    "addr:street":"Market St",
    "iso:country":"US",
    "sg:address":"1635 Market St",
    "sg:city":"Philadelphia",
    "sg:classifiers":[
        {
            "category":"Professional",
            "subcategory":"Lawyer & Legal Services",
            "type":"Services"
        }
    ],
    "sg:phone":"+1 215 567 2010",
    "sg:postcode":"19103",
    "sg:province":"PA",
    "sg:tags":[
        "attorney"
    ],
    "sg:website":"www.crbcp.com",
    "wof:name":"Caesar Rivise Bernstein Cohen",
    "wof:placetype":"venue"
},
  "geometry": {"coordinates":[-75.16801,39.95298],"type":"Point"}
}