{
  "type": "Feature",
  "properties": {
    "iso:country":"US",
    "sg:address":"238 Romesberg Rd",
    "sg:city":"Rockwood",
    "sg:classifiers":[
        {
            "category":"Building & Trades",
            "subcategory":"Construction",
            "type":"Services"
        }
    ],
    "sg:phone":"+1   ",
    "sg:postcode":"15557",
    "sg:province":"PA",
    "sg:tags":[
        "house"
    ],
    "wof:name":"Glade Run Renovations",
    "wof:placetype":"venue"
},
  "geometry": {"coordinates":[-79.175273,39.925713],"type":"Point"}
}