{
  "type": "Feature",
  "properties": {
    "iso:country":"US",
    "sg:address":"4971 York Rd",
    "sg:city":"New Oxford",
    "sg:classifiers":[
        {
            "category":"Real Estate",
            "subcategory":"Developer",
            "type":"Services"
        }
    ],
    "sg:phone":"+1 717 624 7353",
    "sg:postcode":"17350",
    "sg:province":"PA",
    "sg:tags":[
        "cemetery"
    ],
    "wof:name":"New Oxford Cemetery Assn",
    "wof:placetype":"venue"
},
  "geometry": {"coordinates":[-77.066299,39.862044],"type":"Point"}
}