{
  "type": "Feature",
  "properties": {
    "addr:full":"2000 Cambridge Ave Reading PA 19610",
    "addr:housenumber":"2000",
    "addr:postcode":"19610",
    "addr:street":"Cambridge Ave",
    "iso:country":"US",
    "sg:address":"2000 Cambridge Ave",
    "sg:city":"Reading",
    "sg:classifiers":[
        {
            "category":"Banks & Credit Unions",
            "subcategory":"Bank",
            "type":"Services"
        }
    ],
    "sg:phone":"+1   ",
    "sg:postcode":"19610",
    "sg:province":"PA",
    "sg:tags":[
        "state",
        "commercial"
    ],
    "wof:name":"Fulton Bank",
    "wof:placetype":"venue"
},
  "geometry": {"coordinates":[-75.973555,40.319447],"type":"Point"}
}