{
  "type": "Feature",
  "properties": {
    "iso:country":"US",
    "sg:address":"410 Station Ave",
    "sg:city":"Langhorne",
    "sg:classifiers":[
        {
            "category":"Shopping",
            "subcategory":"Clothing, Apparel, & Fashions",
            "type":"Retail Goods"
        }
    ],
    "sg:phone":"+1   ",
    "sg:postcode":"19047",
    "sg:province":"PA",
    "wof:name":"Trendz Fashion Accessory",
    "wof:placetype":"venue"
},
  "geometry": {"coordinates":[-74.91958200000001,40.170733],"type":"Point"}
}