{
  "type": "Feature",
  "properties": {
    "iso:country":"US",
    "sg:address":"523 W Springettsbury Ave",
    "sg:city":"York",
    "sg:classifiers":[
        {
            "category":"Building & Trades",
            "subcategory":"Electrical",
            "type":"Services"
        }
    ],
    "sg:phone":"+1 717 845 4275",
    "sg:postcode":"17403",
    "sg:province":"PA",
    "sg:tags":[
        "electrical",
        "contractor"
    ],
    "wof:name":"Berkheimer Electric",
    "wof:placetype":"venue"
},
  "geometry": {"coordinates":[-76.734562,39.947253],"type":"Point"}
}