{
  "type": "Feature",
  "properties": {
    "iso:country":"US",
    "sg:address":"2303 Ligonier St",
    "sg:city":"Latrobe",
    "sg:classifiers":[
        {
            "category":"Personal",
            "subcategory":"Piercing",
            "type":"Services"
        }
    ],
    "sg:phone":"+1 724 532 2419",
    "sg:postcode":"15650",
    "sg:province":"PA",
    "sg:tags":[
        "body"
    ],
    "wof:name":"Dermagraffiti",
    "wof:placetype":"venue"
},
  "geometry": {"coordinates":[-79.37464300000001,40.30555],"type":"Point"}
}