{
  "type": "Feature",
  "properties": {
    "iso:country":"US",
    "sg:address":"1472 Hilltop Rd",
    "sg:city":"Pottstown",
    "sg:classifiers":[
        {
            "category":"Building & Trades",
            "subcategory":"Construction",
            "type":"Services"
        }
    ],
    "sg:phone":"+1   ",
    "sg:postcode":"19464",
    "sg:province":"PA",
    "sg:tags":[
        "carpentry",
        "contractor"
    ],
    "wof:name":"Terrence McCrossin",
    "wof:placetype":"venue"
},
  "geometry": {"coordinates":[-75.610013,40.260977],"type":"Point"}
}