{
  "type": "Feature",
  "properties": {
    "iso:country":"US",
    "sg:address":"615 Moore St",
    "sg:city":"Huntingdon",
    "sg:classifiers":[
        {
            "category":"Building & Trades",
            "subcategory":"Construction",
            "type":"Services"
        }
    ],
    "sg:phone":"+1   ",
    "sg:postcode":"16652",
    "sg:province":"PA",
    "sg:tags":[
        "nonresidential"
    ],
    "wof:name":"Er E Bennett Construction",
    "wof:placetype":"venue"
},
  "geometry": {"coordinates":[-78.01328599999999,40.4884],"type":"Point"}
}