{
  "type": "Feature",
  "properties": {
    "addr:full":"6 Cottage Ct Mechanicsburg PA 17050",
    "addr:housenumber":"6",
    "addr:postcode":"17050",
    "addr:street":"Cottage Ct",
    "iso:country":"US",
    "sg:address":"6 Cottage Ct",
    "sg:city":"Mechanicsburg",
    "sg:classifiers":[
        {
            "category":"Home & Garden",
            "subcategory":"Household Appliances",
            "type":"Retail Goods"
        }
    ],
    "sg:phone":"+1   ",
    "sg:postcode":"17050",
    "sg:province":"PA",
    "wof:name":"Kirby of Harrisburg",
    "wof:placetype":"venue"
},
  "geometry": {"coordinates":[-77.02318,40.219559],"type":"Point"}
}