{
  "type": "Feature",
  "properties": {
    "addr:full":"827 Highland Ave Lancaster PA 17603",
    "addr:housenumber":"827",
    "addr:postcode":"17603",
    "addr:street":"Highland Ave",
    "iso:country":"US",
    "sg:address":"827 Highland Ave",
    "sg:city":"Lancaster",
    "sg:classifiers":[
        {
            "category":"Building & Trades",
            "subcategory":"Construction",
            "type":"Services"
        }
    ],
    "sg:phone":"+1   ",
    "sg:postcode":"17603",
    "sg:province":"PA",
    "sg:tags":[
        "carpentry",
        "contractor"
    ],
    "wof:name":"Rachor John",
    "wof:placetype":"venue"
},
  "geometry": {"coordinates":[-76.303059,40.024321],"type":"Point"}
}