{
  "type": "Feature",
  "properties": {
    "addr:full":"2528 W Diamond St  Philadelphia PA 19121",
    "addr:housenumber":"2528",
    "addr:postcode":"19121",
    "addr:street":"W Diamond St",
    "iso:country":"US",
    "sg:address":"2528 W Diamond St ",
    "sg:city":"Philadelphia",
    "sg:classifiers":[
        {
            "category":"Restaurant",
            "type":"Food & Drink"
        }
    ],
    "sg:menulink":"http://www.allmenus.com/pa/philadelphia/287853-charlies-country-ribs/menu/",
    "sg:phone":"+1 215 235 2121",
    "sg:postcode":"19121",
    "sg:province":"PA",
    "sg:tags":[
        "barbecue",
        "american"
    ],
    "wof:name":"Charlies Country Ribs",
    "wof:placetype":"venue"
},
  "geometry": {"coordinates":[-75.175567,39.987098],"type":"Point"}
}