{
  "type": "Feature",
  "properties": {
    "iso:country":"US",
    "sg:address":"4376 Newburg Rd",
    "sg:city":"Nazareth",
    "sg:classifiers":[
        {
            "category":"Wholesale",
            "subcategory":"Fruits & Vegetables",
            "type":"Manufacturing & Wholesale Goods"
        }
    ],
    "sg:phone":"+1 610 759 5737",
    "sg:postcode":"18064",
    "sg:province":"PA",
    "wof:name":"Stephen A Chroust",
    "wof:placetype":"venue"
},
  "geometry": {"coordinates":[-75.332262,40.704328],"type":"Point"}
}