{
  "type": "Feature",
  "properties": {
    "iso:country":"US",
    "sg:address":"31 W 10th St",
    "sg:city":"Tyrone",
    "sg:classifiers":[
        {
            "category":"Shopping",
            "subcategory":"Computers & Home Electronics",
            "type":"Retail Goods"
        }
    ],
    "sg:phone":"+1   ",
    "sg:postcode":"16686",
    "sg:province":"PA",
    "wof:name":"Vaux Electronics",
    "wof:placetype":"venue"
},
  "geometry": {"coordinates":[-78.239392,40.670649],"type":"Point"}
}