{
  "type": "Feature",
  "properties": {
    "iso:country":"US",
    "sg:address":"5 Great Valley Pkwy # 239",
    "sg:city":"Malvern",
    "sg:classifiers":[
        {
            "category":"Professional",
            "subcategory":"Management & Consulting",
            "type":"Services"
        },
        {
            "category":"Professional",
            "subcategory":"Engineering",
            "type":"Services"
        }
    ],
    "sg:phone":"+1 610 648 6270",
    "sg:postcode":"19355",
    "sg:province":"PA",
    "sg:tags":[
        "environmental",
        "ecological",
        "engineer",
        "consultant"
    ],
    "sg:website":"http://www.oakhillco.com",
    "wof:name":"The Oak Hill Company Ltd",
    "wof:placetype":"venue"
},
  "geometry": {"coordinates":[-75.533592,40.064201],"type":"Point"}
}