{
  "type": "Feature",
  "properties": {
    "addr:full":"1257 Greensburg Rd New Kensington PA 15068",
    "addr:housenumber":"1257",
    "addr:postcode":"15068",
    "addr:street":"Greensburg Rd",
    "iso:country":"US",
    "sg:address":"1257 Greensburg Rd",
    "sg:city":"New Kensington",
    "sg:classifiers":[
        {
            "category":"Building & Trades",
            "subcategory":"Construction",
            "type":"Services"
        }
    ],
    "sg:phone":"+1   ",
    "sg:postcode":"15068",
    "sg:province":"PA",
    "sg:tags":[
        "house"
    ],
    "wof:name":"Farkas Home Improvements",
    "wof:placetype":"venue"
},
  "geometry": {"coordinates":[-79.733379,40.547961],"type":"Point"}
}