{
  "type": "Feature",
  "properties": {
    "addr:full":"8 Keystone Ct Leola PA 17540",
    "addr:housenumber":"8",
    "addr:postcode":"17540",
    "addr:street":"Keystone Ct",
    "iso:country":"US",
    "sg:address":"8 Keystone Ct",
    "sg:city":"Leola",
    "sg:classifiers":[
        {
            "category":"Wholesale",
            "subcategory":"Durable Goods & Equipment",
            "type":"Manufacturing & Wholesale Goods"
        }
    ],
    "sg:phone":"+1 717 656 4949",
    "sg:postcode":"17540",
    "sg:province":"PA",
    "sg:tags":[
        "representative",
        "manufacturer"
    ],
    "wof:name":"Garry Lydic Assoc Inc",
    "wof:placetype":"venue"
},
  "geometry": {"coordinates":[-76.205313,40.084777],"type":"Point"}
}