{
  "type": "Feature",
  "properties": {
    "iso:country":"US",
    "sg:address":"752 Mud Level Rd",
    "sg:city":"Shippensburg",
    "sg:classifiers":[
        {
            "category":"Manufacturing",
            "subcategory":"Tools & Machinery",
            "type":"Manufacturing & Wholesale Goods"
        }
    ],
    "sg:phone":"+1   ",
    "sg:postcode":"17257",
    "sg:province":"PA",
    "sg:tags":[
        "farm",
        "mfg"
    ],
    "wof:name":"J R Weaver Machinist",
    "wof:placetype":"venue"
},
  "geometry": {"coordinates":[-77.50743799999999,40.089445],"type":"Point"}
}