{
  "type": "Feature",
  "properties": {
    "iso:country":"US",
    "sg:address":"28 N Barbara St",
    "sg:city":"Mount Joy",
    "sg:classifiers":[
        {
            "category":"Health Services",
            "subcategory":"Doctor",
            "type":"Services"
        }
    ],
    "sg:phone":"+1   ",
    "sg:postcode":"17552",
    "sg:province":"PA",
    "wof:name":"Edward C Kassab DMD",
    "wof:placetype":"venue"
},
  "geometry": {"coordinates":[-76.498965,40.109902],"type":"Point"}
}