{
  "type": "Feature",
  "properties": {
    "iso:country":"US",
    "sg:address":"188 Sides Mill Rd",
    "sg:city":"Strasburg",
    "sg:classifiers":[
        {
            "category":"Manufacturing",
            "subcategory":"Tools & Machinery",
            "type":"Manufacturing & Wholesale Goods"
        }
    ],
    "sg:phone":"+1 717 687 7583",
    "sg:postcode":"17579",
    "sg:province":"PA",
    "sg:tags":[
        "die",
        "maker"
    ],
    "wof:name":"Creative Tool Co",
    "wof:placetype":"venue"
},
  "geometry": {"coordinates":[-76.15896100000001,39.958],"type":"Point"}
}