{
  "type": "Feature",
  "properties": {
    "addr:full":"33 Rock Hill Rd Bala Cynwyd PA 19004",
    "addr:housenumber":"33",
    "addr:postcode":"19004",
    "addr:street":"Rock Hill Rd",
    "iso:country":"US",
    "sg:address":"33 Rock Hill Rd",
    "sg:city":"Bala Cynwyd",
    "sg:classifiers":[
        {
            "category":"Manufacturing",
            "subcategory":"Printing",
            "type":"Manufacturing & Wholesale Goods"
        }
    ],
    "sg:phone":"+1 610 667 1694",
    "sg:postcode":"19004",
    "sg:province":"PA",
    "sg:tags":[
        "printer"
    ],
    "wof:name":"Pathways",
    "wof:placetype":"venue"
},
  "geometry": {"coordinates":[-75.239316,40.018991],"type":"Point"}
}