{
  "type": "Feature",
  "properties": {
    "iso:country":"US",
    "sg:address":"1218 Numidia Dr",
    "sg:city":"Catawissa",
    "sg:classifiers":[
        {
            "category":"Shopping",
            "subcategory":"Discount & Variety Stores",
            "type":"Retail Goods"
        }
    ],
    "sg:phone":"+1 570 799 5641",
    "sg:postcode":"17820",
    "sg:province":"PA",
    "sg:tags":[
        "merchandise",
        "general"
    ],
    "wof:name":"Palachick's General Store",
    "wof:placetype":"venue"
},
  "geometry": {"coordinates":[-76.40383,40.875565],"type":"Point"}
}