{
  "type": "Feature",
  "properties": {
    "addr:full":"425 Mall Blvd King Of Prussia PA 19406",
    "addr:housenumber":"425",
    "addr:postcode":"19406",
    "addr:street":"Mall Blvd",
    "iso:country":"US",
    "sg:address":"425 Mall Blvd",
    "sg:city":"King Of Prussia",
    "sg:classifiers":[
        {
            "category":"Shopping",
            "subcategory":"Clothing, Apparel, & Fashions",
            "type":"Retail Goods"
        }
    ],
    "sg:phone":"+1 610 265 0317",
    "sg:postcode":"19406",
    "sg:province":"PA",
    "sg:tags":[
        "woman",
        "to",
        "bed",
        "linen",
        "wear",
        "ready"
    ],
    "wof:name":"April Cornell",
    "wof:placetype":"venue"
},
  "geometry": {"coordinates":[-75.38633900000001,40.086753],"type":"Point"}
}