{
  "type": "Feature",
  "properties": {
    "iso:country":"US",
    "sg:address":"201 King of Prussia Road Suite 161",
    "sg:city":"Radnor",
    "sg:classifiers":[
        {
            "category":"Professional",
            "subcategory":"Computer Services",
            "type":"Services"
        }
    ],
    "sg:phone":"+1 484 367 7169",
    "sg:postcode":"19087",
    "sg:province":"PA",
    "sg:website":"http://amppholdings.com",
    "wof:name":"AMPP Holdings",
    "wof:placetype":"venue"
},
  "geometry": {"coordinates":[-75.388172,40.080092],"type":"Point"}
}