{
  "type": "Feature",
  "properties": {
    "addr:full":"1236 Saint Lawrence Rd Patton PA 16668",
    "addr:housenumber":"1236",
    "addr:postcode":"16668",
    "addr:street":"Saint Lawrence Rd",
    "iso:country":"US",
    "sg:address":"1236 Saint Lawrence Rd",
    "sg:city":"Patton",
    "sg:classifiers":[
        {
            "category":"Wholesale",
            "subcategory":"Auto Parts",
            "type":"Manufacturing & Wholesale Goods"
        }
    ],
    "sg:phone":"+1   ",
    "sg:postcode":"16668",
    "sg:province":"PA",
    "sg:tags":[
        "automotive",
        "installation",
        "air"
    ],
    "wof:name":"L & L Service & Supply Inc",
    "wof:placetype":"venue"
},
  "geometry": {"coordinates":[-78.647535,40.670188],"type":"Point"}
}