{
  "type": "Feature",
  "properties": {
    "addr:full":"325 Blue Valley Dr Bangor PA 18013",
    "addr:housenumber":"325",
    "addr:postcode":"18013",
    "addr:street":"Blue Valley Dr",
    "iso:country":"US",
    "sg:address":"325 Blue Valley Dr",
    "sg:city":"Bangor",
    "sg:classifiers":[
        {
            "category":"Professional",
            "subcategory":"Computer Services",
            "type":"Services"
        }
    ],
    "sg:phone":"+1 610 588 5350",
    "sg:postcode":"18013",
    "sg:province":"PA",
    "sg:tags":[
        "prepackaged",
        "software"
    ],
    "wof:name":"Computer Connections",
    "wof:placetype":"venue"
},
  "geometry": {"coordinates":[-75.23280200000001,40.871506],"type":"Point"}
}