{
  "type": "Feature",
  "properties": {
    "addr:full":"2550 S 3rd St Philadelphia PA 19148",
    "addr:housenumber":"2550",
    "addr:postcode":"19148",
    "addr:street":"S 3Rd St",
    "iso:country":"US",
    "sg:address":"2550 S 3rd St",
    "sg:city":"Philadelphia",
    "sg:classifiers":[
        {
            "category":"Building & Trades",
            "subcategory":"Locksmith",
            "type":"Services"
        }
    ],
    "sg:phone":"+1 267 702 1201",
    "sg:postcode":"19148",
    "sg:province":"PA",
    "sg:tags":[
        "key"
    ],
    "wof:name":"Anywhere A Locksmith Service",
    "wof:placetype":"venue"
},
  "geometry": {"coordinates":[-75.15288200000001,39.916477],"type":"Point"}
}