{
  "type": "Feature",
  "properties": {
    "addr:full":"1837 Chestnut St Philadelphia PA 19103",
    "addr:housenumber":"1837",
    "addr:postcode":"19103",
    "addr:street":"Chestnut St",
    "iso:country":"US",
    "sg:address":"1837 Chestnut St",
    "sg:city":"Philadelphia",
    "sg:classifiers":[
        {
            "category":"Shopping",
            "subcategory":"Books",
            "type":"Retail Goods"
        }
    ],
    "sg:phone":"+1 215 567 2615",
    "sg:postcode":"19103",
    "sg:province":"PA",
    "sg:tags":[
        "bookstore"
    ],
    "sg:website":"www.robinsbookstore.com",
    "wof:name":"Robin's Bookstore Inc",
    "wof:placetype":"venue"
},
  "geometry": {"coordinates":[-75.17089799999999,39.951801],"type":"Point"}
}