{
  "type": "Feature",
  "properties": {
    "iso:country":"US",
    "sg:address":"1554 Ligonier St",
    "sg:city":"Latrobe",
    "sg:classifiers":[
        {
            "category":"Shopping",
            "subcategory":"Florist",
            "type":"Retail Goods"
        }
    ],
    "sg:phone":"+1 724 539 9739",
    "sg:postcode":"15650",
    "sg:province":"PA",
    "sg:tags":[
        "basket",
        "gift"
    ],
    "sg:website":"http://www.floralfountain.com",
    "wof:name":"Floral Fountain",
    "wof:placetype":"venue"
},
  "geometry": {"coordinates":[-79.379312,40.311685],"type":"Point"}
}