{
  "type": "Feature",
  "properties": {
    "iso:country":"US",
    "sg:address":"901 State St",
    "sg:city":"Lancaster",
    "sg:classifiers":[
        {
            "category":"Restaurant",
            "type":"Food & Drink"
        }
    ],
    "sg:phone":"+1   ",
    "sg:postcode":"17603",
    "sg:province":"PA",
    "sg:tags":[
        "eating"
    ],
    "wof:name":"L Deli Inc",
    "wof:placetype":"venue"
},
  "geometry": {"coordinates":[-76.32285400000001,40.052474],"type":"Point"}
}