{
  "type": "Feature",
  "properties": {
    "iso:country":"US",
    "sg:address":"3010 Stewart St",
    "sg:city":"Mc Keesport",
    "sg:classifiers":[
        {
            "category":"Home & Garden",
            "subcategory":"Home Furnishings",
            "type":"Retail Goods"
        }
    ],
    "sg:phone":"+1   ",
    "sg:postcode":"15132",
    "sg:province":"PA",
    "wof:name":"Lois D Banks",
    "wof:placetype":"venue"
},
  "geometry": {"coordinates":[-79.84234600000001,40.342923],"type":"Point"}
}