{
  "type": "Feature",
  "properties": {
    "iso:country":"US",
    "sg:address":"4340 Gem Ct",
    "sg:city":"Erie",
    "sg:classifiers":[
        {
            "category":"Building & Trades",
            "subcategory":"Plumbing",
            "type":"Services"
        }
    ],
    "sg:phone":"+1   ",
    "sg:postcode":"16504",
    "sg:province":"PA",
    "sg:tags":[
        "contractor"
    ],
    "wof:name":"Marchant Htg & Coolg Systems",
    "wof:placetype":"venue"
},
  "geometry": {"coordinates":[-80.040406,42.105089],"type":"Point"}
}