{
  "type": "Feature",
  "properties": {
    "iso:country":"US",
    "sg:address":"12101 Garnes Rd",
    "sg:city":"Mercersburg",
    "sg:classifiers":[
        {
            "category":"Building & Trades",
            "subcategory":"Construction",
            "type":"Services"
        }
    ],
    "sg:phone":"+1 717 328 3084",
    "sg:postcode":"17236",
    "sg:province":"PA",
    "sg:tags":[
        "masonry",
        "contractor"
    ],
    "wof:name":"Gene Bricker Masonry",
    "wof:placetype":"venue"
},
  "geometry": {"coordinates":[-77.879322,39.756893],"type":"Point"}
}