{
  "type": "Feature",
  "properties": {
    "iso:country":"US",
    "sg:address":"5215 Militia Hill Rd",
    "sg:city":"Plymouth Meeting",
    "sg:classifiers":[
        {
            "category":"Banks & Credit Unions",
            "subcategory":"Financial Services",
            "type":"Services"
        }
    ],
    "sg:phone":"+1 610 941 6200",
    "sg:postcode":"19462",
    "sg:province":"PA",
    "sg:tags":[
        "franchise",
        "operator"
    ],
    "sg:website":"www.partyland.com",
    "wof:name":"Party Land Inc",
    "wof:placetype":"venue"
},
  "geometry": {"coordinates":[-75.248374,40.117636],"type":"Point"}
}