{
  "type": "Feature",
  "properties": {
    "iso:country":"US",
    "sg:address":"464 Sylvania Ave",
    "sg:city":"Glenside",
    "sg:classifiers":[
        {
            "category":"Education",
            "subcategory":"Vocational School",
            "type":"Public Place"
        }
    ],
    "sg:phone":"+1   ",
    "sg:postcode":"19038",
    "sg:province":"PA",
    "sg:tags":[
        "training",
        "computer",
        "disability",
        "consulting"
    ],
    "wof:name":"Young Opportunities Inc",
    "wof:placetype":"venue"
},
  "geometry": {"coordinates":[-75.147401,40.11072],"type":"Point"}
}