{
  "type": "Feature",
  "properties": {
    "iso:country":"US",
    "sg:address":"7300 Frankford Ave",
    "sg:city":"Philadelphia",
    "sg:classifiers":[
        {
            "category":"Shopping",
            "subcategory":"News",
            "type":"Retail Goods"
        }
    ],
    "sg:phone":"+1 215 333 0392",
    "sg:postcode":"19136",
    "sg:province":"PA",
    "sg:tags":[
        "dealer"
    ],
    "wof:name":"Klara Shatri",
    "wof:placetype":"venue"
},
  "geometry": {"coordinates":[-75.039883,40.037121],"type":"Point"}
}