{
  "type": "Feature",
  "properties": {
    "iso:country":"US",
    "sg:address":"4549 Winding Brook Dr",
    "sg:city":"Bensalem",
    "sg:classifiers":[
        {
            "category":"Professional",
            "subcategory":"Business Services",
            "type":"Services"
        }
    ],
    "sg:phone":"+1 267 297 2519",
    "sg:postcode":"19020",
    "sg:province":"PA",
    "sg:tags":[
        "organizing",
        "services-household"
    ],
    "wof:name":"M. F. L. Mgmt. Services",
    "wof:placetype":"venue"
},
  "geometry": {"coordinates":[-74.93176200000001,40.135252],"type":"Point"}
}