{
  "type": "Feature",
  "properties": {
    "addr:full":"1100 S 12th St Altoona PA 16602",
    "addr:housenumber":"1100",
    "addr:postcode":"16602",
    "addr:street":"S 12Th St",
    "iso:country":"US",
    "sg:address":"1100 S 12th St",
    "sg:city":"Altoona",
    "sg:classifiers":[
        {
            "category":"Building & Trades",
            "subcategory":"Construction",
            "type":"Services"
        }
    ],
    "sg:phone":"+1 814 942 6810",
    "sg:postcode":"16602",
    "sg:province":"PA",
    "sg:tags":[
        "general",
        "contractor"
    ],
    "wof:name":"Dynasty Home Improvements",
    "wof:placetype":"venue"
},
  "geometry": {"coordinates":[-78.38256,40.505228],"type":"Point"}
}