{
  "type": "Feature",
  "properties": {
    "addr:full":"3070 Bristol Pike Bensalem PA 19020",
    "addr:housenumber":"3070",
    "addr:postcode":"19020",
    "addr:street":"Bristol Pike",
    "iso:country":"US",
    "sg:address":"3070 Bristol Pike",
    "sg:city":"Bensalem",
    "sg:classifiers":[
        {
            "category":"Professional",
            "subcategory":"Lawyer & Legal Services",
            "type":"Services"
        }
    ],
    "sg:phone":"+1 215 244 0452",
    "sg:postcode":"19020",
    "sg:province":"PA",
    "wof:name":"Chesnov Jahn S Attorney",
    "wof:placetype":"venue"
},
  "geometry": {"coordinates":[-74.93319700000001,40.0853],"type":"Point"}
}