{
  "type": "Feature",
  "properties": {
    "iso:country":"US",
    "sg:address":"445 W Philadelphia St",
    "sg:city":"York",
    "sg:classifiers":[
        {
            "category":"Banks & Credit Unions",
            "subcategory":"Bank",
            "type":"Services"
        }
    ],
    "sg:phone":"+1 717 852 1390",
    "sg:postcode":"17401",
    "sg:province":"PA",
    "wof:name":"Pace Credit Union",
    "wof:placetype":"venue"
},
  "geometry": {"coordinates":[-76.73779399999999,39.960983],"type":"Point"}
}