{
  "type": "Feature",
  "properties": {
    "iso:country":"US",
    "sg:address":"265 Lonesome Ln",
    "sg:city":"Palmerton",
    "sg:classifiers":[
        {
            "category":"Wholesale",
            "subcategory":"Durable Goods & Equipment",
            "type":"Manufacturing & Wholesale Goods"
        }
    ],
    "sg:phone":"+1 610 681 3647",
    "sg:postcode":"18071",
    "sg:province":"PA",
    "sg:tags":[
        "importer"
    ],
    "wof:name":"K 9 Union Importers",
    "wof:placetype":"venue"
},
  "geometry": {"coordinates":[-75.51807100000001,40.853369],"type":"Point"}
}