{
  "type": "Feature",
  "properties": {
    "iso:country":"US",
    "sg:address":"3637 Washington Rd",
    "sg:city":"Canonsburg",
    "sg:classifiers":[
        {
            "category":"Personal",
            "subcategory":"Barber",
            "type":"Services"
        }
    ],
    "sg:phone":"+1   ",
    "sg:postcode":"15317",
    "sg:province":"PA",
    "sg:tags":[
        "shop"
    ],
    "wof:name":"Expressions Hair Fashions",
    "wof:placetype":"venue"
},
  "geometry": {"coordinates":[-80.122978,40.280676],"type":"Point"}
}