{
  "type": "Feature",
  "properties": {
    "addr:full":"119 Reo St Butler PA 16001",
    "addr:housenumber":"119",
    "addr:postcode":"16001",
    "addr:street":"Reo St",
    "iso:country":"US",
    "sg:address":"119 Reo St",
    "sg:city":"Butler",
    "sg:classifiers":[
        {
            "category":"Building & Trades",
            "subcategory":"Construction",
            "type":"Services"
        }
    ],
    "sg:phone":"+1 724 283 6244",
    "sg:postcode":"16001",
    "sg:province":"PA",
    "sg:tags":[
        "excavating",
        "contractor"
    ],
    "wof:name":"Larry Blain",
    "wof:placetype":"venue"
},
  "geometry": {"coordinates":[-79.88265800000001,40.862876],"type":"Point"}
}