{
  "type": "Feature",
  "properties": {
    "iso:country":"US",
    "sg:address":"125 Brooksmill Rd",
    "sg:city":"Grantville",
    "sg:classifiers":[
        {
            "category":"Professional",
            "subcategory":"Management & Consulting",
            "type":"Services"
        }
    ],
    "sg:phone":"+1 717 469 1800",
    "sg:postcode":"17028",
    "sg:province":"PA",
    "sg:tags":[
        "consultant",
        "hospital"
    ],
    "wof:name":"Sunstone Consulting",
    "wof:placetype":"venue"
},
  "geometry": {"coordinates":[-76.70878399999999,40.366406],"type":"Point"}
}