{
  "type": "Feature",
  "properties": {
    "iso:country":"US",
    "sg:address":"270 Eden Rd",
    "sg:city":"Quarryville",
    "sg:classifiers":[
        {
            "category":"Building & Trades",
            "subcategory":"Electrical",
            "type":"Services"
        }
    ],
    "sg:phone":"+1 717 786 2856",
    "sg:postcode":"17566",
    "sg:province":"PA",
    "sg:tags":[
        "electric",
        "contractor"
    ],
    "wof:name":"Ron Rineer's Electrical",
    "wof:placetype":"venue"
},
  "geometry": {"coordinates":[-76.14641,39.917361],"type":"Point"}
}