{
  "type": "Feature",
  "properties": {
    "iso:country":"US",
    "sg:address":"424 Louella Ave",
    "sg:city":"Wayne",
    "sg:classifiers":[
        {
            "category":"Wholesale",
            "subcategory":"Machinery & Supplies",
            "type":"Manufacturing & Wholesale Goods"
        }
    ],
    "sg:phone":"+1   ",
    "sg:postcode":"19087",
    "sg:province":"PA",
    "sg:tags":[
        "equipment",
        "industrial"
    ],
    "wof:name":"Stewart D N Sales Co",
    "wof:placetype":"venue"
},
  "geometry": {"coordinates":[-75.384514,40.037651],"type":"Point"}
}