{
  "type": "Feature",
  "properties": {
    "iso:country":"US",
    "sg:address":"543 Schuylkill Ave",
    "sg:city":"Reading",
    "sg:classifiers":[
        {
            "category":"Organizations",
            "subcategory":"Religious Organization",
            "type":"Services"
        }
    ],
    "sg:phone":"+1 610 655 2787",
    "sg:postcode":"19601",
    "sg:province":"PA",
    "sg:tags":[
        "church"
    ],
    "wof:name":"Assembly Of Christian Churches",
    "wof:placetype":"venue"
},
  "geometry": {"coordinates":[-75.939294,40.34369],"type":"Point"}
}