{
  "type": "Feature",
  "properties": {
    "iso:country":"US",
    "sg:address":"6039 Passyunk Ave",
    "sg:city":"Philadelphia",
    "sg:classifiers":[
        {
            "category":"Cinema",
            "subcategory":"Movie Rental",
            "type":"Entertainment"
        }
    ],
    "sg:phone":"+1   ",
    "sg:postcode":"19153",
    "sg:province":"PA",
    "sg:tags":[
        "video",
        "tape"
    ],
    "wof:name":"Family Video Center",
    "wof:placetype":"venue"
},
  "geometry": {"coordinates":[-75.205721,39.919095],"type":"Point"}
}