{
  "type": "Feature",
  "properties": {
    "addr:full":"53 Ruby Rd Chadds Ford PA 19317",
    "addr:housenumber":"53",
    "addr:postcode":"19317",
    "addr:street":"Ruby Rd",
    "iso:country":"US",
    "sg:address":"53 Ruby Rd",
    "sg:city":"Chadds Ford",
    "sg:classifiers":[
        {
            "category":"Banks & Credit Unions",
            "subcategory":"Investment Brokerage",
            "type":"Services"
        }
    ],
    "sg:phone":"+1 610 459 5399",
    "sg:postcode":"19317",
    "sg:province":"PA",
    "wof:name":"Kenneth Gross Invstmnt Group",
    "wof:placetype":"venue"
},
  "geometry": {"coordinates":[-75.54107500000001,39.851765],"type":"Point"}
}