{
  "type": "Feature",
  "properties": {
    "iso:country":"US",
    "sg:address":"565 Tuscarora Path",
    "sg:city":"Ickesburg",
    "sg:classifiers":[
        {
            "category":"Manufacturing",
            "subcategory":"Food",
            "type":"Manufacturing & Wholesale Goods"
        },
        {
            "category":"Farming",
            "subcategory":"Farm",
            "type":"Manufacturing & Wholesale Goods"
        }
    ],
    "sg:phone":"+1 717 438 3531",
    "sg:postcode":"17037",
    "sg:province":"PA",
    "sg:tags":[
        "corn",
        "product"
    ],
    "wof:name":"Sauder Crest Farm",
    "wof:placetype":"venue"
},
  "geometry": {"coordinates":[-77.358206,40.44935],"type":"Point"}
}