{
  "type": "Feature",
  "properties": {
    "iso:country":"US",
    "sg:address":"625 W Chew St",
    "sg:city":"Allentown",
    "sg:classifiers":[
        {
            "category":"Social Services",
            "subcategory":"Child Care",
            "type":"Services"
        }
    ],
    "sg:phone":"+1 610 434 6065",
    "sg:postcode":"18102",
    "sg:province":"PA",
    "sg:tags":[
        "day"
    ],
    "wof:name":"Growing Connection",
    "wof:placetype":"venue"
},
  "geometry": {"coordinates":[-75.473209,40.606581],"type":"Point"}
}