{
  "type": "Feature",
  "properties": {
    "iso:country":"US",
    "sg:address":"1000 Penn Ave",
    "sg:city":"Pittsburgh",
    "sg:classifiers":[
        {
            "category":"Education",
            "subcategory":"Special Training",
            "type":"Public Place"
        }
    ],
    "sg:phone":"+1 412 201 5140",
    "sg:postcode":"15222",
    "sg:province":"PA",
    "sg:tags":[
        "program"
    ],
    "wof:name":"Tegg Institute",
    "wof:placetype":"venue"
},
  "geometry": {"coordinates":[-79.993859,40.444936],"type":"Point"}
}