{
  "type": "Feature",
  "properties": {
    "iso:country":"US",
    "sg:address":"5144 Irving St",
    "sg:city":"Philadelphia",
    "sg:classifiers":[
        {
            "category":"Building & Trades",
            "subcategory":"Construction",
            "type":"Services"
        }
    ],
    "sg:phone":"+1 215 471 4493",
    "sg:postcode":"19139",
    "sg:province":"PA",
    "sg:tags":[
        "painter"
    ],
    "wof:name":"Richard Morris Painting Co",
    "wof:placetype":"venue"
},
  "geometry": {"coordinates":[-75.225206,39.955032],"type":"Point"}
}