{
  "type": "Feature",
  "properties": {
    "addr:full":"7605 Ogontz Ave Philadelphia PA 19150",
    "addr:housenumber":"7605",
    "addr:postcode":"19150",
    "addr:street":"Ogontz Ave",
    "iso:country":"US",
    "sg:address":"7605 Ogontz Ave",
    "sg:city":"Philadelphia",
    "sg:classifiers":[
        {
            "category":"Shopping",
            "subcategory":"Clothing, Apparel, & Fashions",
            "type":"Retail Goods"
        }
    ],
    "sg:phone":"+1 215 549 1380",
    "sg:postcode":"19150",
    "sg:province":"PA",
    "wof:name":"Rizhards Fashions",
    "wof:placetype":"venue"
},
  "geometry": {"coordinates":[-75.157315,40.070748],"type":"Point"}
}