{
  "type": "Feature",
  "properties": {
    "addr:full":"15 Clover Ln Mechanicsburg PA 17050",
    "addr:housenumber":"15",
    "addr:postcode":"17050",
    "addr:street":"Clover Ln",
    "iso:country":"US",
    "sg:address":"15 Clover Ln",
    "sg:city":"Mechanicsburg",
    "sg:classifiers":[
        {
            "category":"Building & Trades",
            "subcategory":"Construction",
            "type":"Services"
        }
    ],
    "sg:phone":"+1   ",
    "sg:postcode":"17050",
    "sg:province":"PA",
    "sg:tags":[
        "contractor"
    ],
    "wof:name":"Gonzalez Drywall",
    "wof:placetype":"venue"
},
  "geometry": {"coordinates":[-77.031614,40.227145],"type":"Point"}
}