{
  "type": "Feature",
  "properties": {
    "iso:country":"US",
    "sg:address":"3455 Street Rd",
    "sg:city":"Bensalem",
    "sg:classifiers":[
        {
            "category":"Professional",
            "subcategory":"Business Services",
            "type":"Services"
        }
    ],
    "sg:phone":"+1 267 984 7188",
    "sg:postcode":"19020",
    "sg:province":"PA",
    "sg:tags":[
        "organizing",
        "services-household"
    ],
    "wof:name":"Alcom Management",
    "wof:placetype":"venue"
},
  "geometry": {"coordinates":[-74.962497,40.122781],"type":"Point"}
}