{
  "type": "Feature",
  "properties": {
    "addr:full":"1655 Ponderosa Dr Erie PA 16509",
    "addr:housenumber":"1655",
    "addr:postcode":"16509",
    "addr:street":"Ponderosa Dr",
    "iso:country":"US",
    "sg:address":"1655 Ponderosa Dr",
    "sg:city":"Erie",
    "sg:classifiers":[
        {
            "category":"Professional",
            "subcategory":"Management & Consulting",
            "type":"Services"
        }
    ],
    "sg:phone":"+1 814 864 3332",
    "sg:postcode":"16509",
    "sg:province":"PA",
    "sg:tags":[
        "consultant",
        "energy",
        "conservation"
    ],
    "wof:name":"Ener Save Erie",
    "wof:placetype":"venue"
},
  "geometry": {"coordinates":[-80.08004200000001,42.061907],"type":"Point"}
}