{
  "type": "Feature",
  "properties": {
    "addr:full":"2644 Livingston St Philadelphia PA 19125",
    "addr:housenumber":"2644",
    "addr:postcode":"19125",
    "addr:street":"Livingston St",
    "iso:country":"US",
    "sg:address":"2644 Livingston St",
    "sg:city":"Philadelphia",
    "sg:classifiers":[
        {
            "category":"Building & Trades",
            "subcategory":"Construction",
            "type":"Services"
        }
    ],
    "sg:phone":"+1 215 739 1521",
    "sg:postcode":"19125",
    "sg:province":"PA",
    "sg:tags":[
        "system",
        "contractor",
        "air conditioning"
    ],
    "wof:name":"J Sickman Htg Ac",
    "wof:placetype":"venue"
},
  "geometry": {"coordinates":[-75.117182,39.979034],"type":"Point"}
}