{
  "type": "Feature",
  "properties": {
    "addr:full":"1057 Freeport Rd Blawnox PA 15238",
    "addr:housenumber":"1057",
    "addr:postcode":"15238",
    "addr:street":"Freeport Rd",
    "iso:country":"US",
    "sg:address":"1057 Freeport Rd",
    "sg:city":"Blawnox",
    "sg:classifiers":[
        {
            "category":"Home & Garden",
            "subcategory":"Furniture",
            "type":"Retail Goods"
        }
    ],
    "sg:phone":"+1 412 366 7221",
    "sg:postcode":"15238",
    "sg:province":"PA",
    "sg:tags":[
        "mattress"
    ],
    "wof:name":"Mattress Department",
    "wof:placetype":"venue"
},
  "geometry": {"coordinates":[-79.852171,40.509632],"type":"Point"}
}