{
  "type": "Feature",
  "properties": {
    "iso:country":"US",
    "sg:address":"11 Kearney Rd",
    "sg:city":"Brockway",
    "sg:classifiers":[
        {
            "category":"Building & Trades",
            "subcategory":"Construction",
            "type":"Services"
        }
    ],
    "sg:phone":"+1   ",
    "sg:postcode":"15824",
    "sg:province":"PA",
    "sg:tags":[
        "house"
    ],
    "wof:name":"Chamberlin Construction",
    "wof:placetype":"venue"
},
  "geometry": {"coordinates":[-78.80637400000001,41.246544],"type":"Point"}
}