{
  "type": "Feature",
  "properties": {
    "iso:country":"US",
    "sg:address":"128 McGinley Rd",
    "sg:city":"Chicora",
    "sg:classifiers":[
        {
            "category":"Professional",
            "subcategory":"Computer Services",
            "type":"Services"
        }
    ],
    "sg:phone":"+1 724 285 1370",
    "sg:postcode":"16025",
    "sg:province":"PA",
    "sg:tags":[
        "consultant",
        "designer"
    ],
    "wof:name":"R A Svc",
    "wof:placetype":"venue"
},
  "geometry": {"coordinates":[-79.812279,40.943818],"type":"Point"}
}