{
  "type": "Feature",
  "properties": {
    "iso:country":"US",
    "sg:address":"539 Rochester Rd",
    "sg:city":"Pittsburgh",
    "sg:classifiers":[
        {
            "category":"Retail",
            "subcategory":"Repair Shop",
            "type":"Services"
        }
    ],
    "sg:phone":"+1 412 630 2440",
    "sg:postcode":"15237",
    "sg:province":"PA",
    "sg:tags":[
        "building",
        "equipment",
        "product",
        "mfg"
    ],
    "wof:name":"Thyssen General Elevator",
    "wof:placetype":"venue"
},
  "geometry": {"coordinates":[-80.05108799999999,40.53519],"type":"Point"}
}