{
  "type": "Feature",
  "properties": {
    "addr:full":"4055 Linglestown Rd Harrisburg PA 17112",
    "addr:housenumber":"4055",
    "addr:postcode":"17112",
    "addr:street":"Linglestown Rd",
    "iso:country":"US",
    "sg:address":"4055 Linglestown Rd",
    "sg:city":"Harrisburg",
    "sg:classifiers":[
        {
            "category":"Health Services",
            "subcategory":"Chiropractor",
            "type":"Services"
        }
    ],
    "sg:phone":"+1 717 652 5550",
    "sg:postcode":"17112",
    "sg:province":"PA",
    "wof:name":"Boland Chiropractic & Sports",
    "wof:placetype":"venue"
},
  "geometry": {"coordinates":[-76.840872,40.334278],"type":"Point"}
}