{
  "type": "Feature",
  "properties": {
    "iso:country":"US",
    "sg:address":"4055 Linglestown Rd",
    "sg:city":"Harrisburg",
    "sg:classifiers":[
        {
            "category":"Health Services",
            "subcategory":"Chiropractor",
            "type":"Services"
        }
    ],
    "sg:phone":"+1 717 652 5550",
    "sg:postcode":"17112",
    "sg:province":"PA",
    "wof:name":"Boland Chiropractic & Sports",
    "wof:placetype":"venue"
},
  "geometry": {"coordinates":[-76.840872,40.334278],"type":"Point"}
}