{
  "type": "Feature",
  "properties": {
    "iso:country":"US",
    "sg:address":"309 Martindale Rd",
    "sg:city":"Ephrata",
    "sg:classifiers":[
        {
            "category":"Wholesale",
            "subcategory":"Farm Supplies",
            "type":"Manufacturing & Wholesale Goods"
        }
    ],
    "sg:phone":"+1 717 738 4251",
    "sg:postcode":"17522",
    "sg:province":"PA",
    "sg:tags":[
        "feed"
    ],
    "wof:name":"Keystone Mills",
    "wof:placetype":"venue"
},
  "geometry": {"coordinates":[-76.110416,40.156238],"type":"Point"}
}