{
  "type": "Feature",
  "properties": {
    "addr:full":"3211 Carlisle Rd Dover PA 17315",
    "addr:housenumber":"3211",
    "addr:postcode":"17315",
    "addr:street":"Carlisle Rd",
    "iso:country":"US",
    "sg:address":"3211 Carlisle Rd",
    "sg:city":"Dover",
    "sg:classifiers":[
        {
            "category":"Health Services",
            "subcategory":"Optometrist",
            "type":"Services"
        }
    ],
    "sg:phone":"+1   ",
    "sg:postcode":"17315",
    "sg:province":"PA",
    "wof:name":"Loretta Schmidgall",
    "wof:placetype":"venue"
},
  "geometry": {"coordinates":[-76.826184,39.98458],"type":"Point"}
}