{
  "type": "Feature",
  "properties": {
    "iso:country":"US",
    "sg:address":"5547 Germantown Ave",
    "sg:city":"Philadelphia",
    "sg:classifiers":[
        {
            "category":"Restaurant",
            "type":"Food & Drink"
        }
    ],
    "sg:phone":"+1 215 849 0788",
    "sg:postcode":"19144",
    "sg:province":"PA",
    "sg:tags":[
        "style",
        "family",
        "african"
    ],
    "sg:website":"http://www.dahlakrestaurant.com",
    "wof:name":"Dahlak Restaurant",
    "wof:placetype":"venue"
},
  "geometry": {"coordinates":[-75.172978,40.034525],"type":"Point"}
}