{
  "type": "Feature",
  "properties": {
    "iso:country":"US",
    "sg:address":"160 E Church St",
    "sg:city":"Stevens",
    "sg:classifiers":[
        {
            "category":"Freight",
            "type":"Transportation"
        }
    ],
    "sg:phone":"+1   ",
    "sg:postcode":"17578",
    "sg:province":"PA",
    "sg:tags":[
        "operator",
        "local",
        "trucking"
    ],
    "wof:name":"Glenn Mast",
    "wof:placetype":"venue"
},
  "geometry": {"coordinates":[-76.111996,40.199161],"type":"Point"}
}