{
  "type": "Feature",
  "properties": {
    "iso:country":"US",
    "sg:address":"257 W Uwchlan Ave",
    "sg:city":"Downingtown",
    "sg:classifiers":[
        {
            "category":"Banks & Credit Unions",
            "subcategory":"Investment Brokerage",
            "type":"Services"
        }
    ],
    "sg:phone":"+1 610 269 6246",
    "sg:postcode":"19335",
    "sg:province":"PA",
    "sg:tags":[
        "consultant",
        "planning",
        "financial"
    ],
    "wof:name":"Four Seasons Financial Group",
    "wof:placetype":"venue"
},
  "geometry": {"coordinates":[-75.683684,40.029654],"type":"Point"}
}