{
  "type": "Feature",
  "properties": {
    "iso:country":"US",
    "sg:address":"1106 Ironville Pike",
    "sg:city":"Columbia",
    "sg:classifiers":[
        {
            "category":"Autos & Motor Vehicles",
            "subcategory":"Auto Supplies",
            "type":"Retail Goods"
        }
    ],
    "sg:phone":"+1 717 684 9225",
    "sg:postcode":"17512",
    "sg:province":"PA",
    "sg:tags":[
        "equipment",
        "racing",
        "car",
        "automobile"
    ],
    "sg:website":"www.hanksperformance.com",
    "wof:name":"Hank's Performance Products",
    "wof:placetype":"venue"
},
  "geometry": {"coordinates":[-76.493628,40.042559],"type":"Point"}
}