{
  "type": "Feature",
  "properties": {
    "addr:full":"79 N Kendall Ave Bradford PA 16701",
    "addr:housenumber":"79",
    "addr:postcode":"16701",
    "addr:street":"N Kendall Ave",
    "iso:country":"US",
    "sg:address":"79 N Kendall Ave",
    "sg:city":"Bradford",
    "sg:classifiers":[
        {
            "category":"Health Services",
            "subcategory":"Hospital",
            "type":"Services"
        },
        {
            "category":"Social Services",
            "type":"Services"
        }
    ],
    "sg:phone":"+1 814 362 7216",
    "sg:postcode":"16701",
    "sg:province":"PA",
    "sg:tags":[
        "mental"
    ],
    "wof:name":"Early Intervention Services",
    "wof:placetype":"venue"
},
  "geometry": {"coordinates":[-78.62824500000001,41.966725],"type":"Point"}
}