{
  "type": "Feature",
  "properties": {
    "addr:full":"121 S 18th St Philadelphia PA 19103",
    "addr:housenumber":"121",
    "addr:postcode":"19103",
    "addr:street":"S 18Th St",
    "iso:country":"US",
    "sg:address":"121 S 18th St",
    "sg:city":"Philadelphia",
    "sg:classifiers":[
        {
            "category":"Shopping",
            "subcategory":"Shoes",
            "type":"Retail Goods"
        }
    ],
    "sg:phone":"+1 215 854 0907",
    "sg:postcode":"19103",
    "sg:province":"PA",
    "wof:name":"Bottino Shoes",
    "wof:placetype":"venue"
},
  "geometry": {"coordinates":[-75.170393,39.951085],"type":"Point"}
}