{
  "type": "Feature",
  "properties": {
    "iso:country":"US",
    "sg:address":"303 E Chestnut St",
    "sg:city":"Coatesville",
    "sg:classifiers":[
        {
            "category":"Building & Trades",
            "subcategory":"Construction",
            "type":"Services"
        }
    ],
    "sg:phone":"+1   ",
    "sg:postcode":"19320",
    "sg:province":"PA",
    "sg:tags":[
        "hanging",
        "contractor"
    ],
    "wof:name":"Bailey Custom Painting",
    "wof:placetype":"venue"
},
  "geometry": {"coordinates":[-75.817621,39.9852],"type":"Point"}
}