{
  "type": "Feature",
  "properties": {
    "addr:full":"9504 Rising Sun Ave Philadelphia PA 19115",
    "addr:housenumber":"9504",
    "addr:postcode":"19115",
    "addr:street":"Rising Sun Ave",
    "iso:country":"US",
    "sg:address":"9504 Rising Sun Ave",
    "sg:city":"Philadelphia",
    "sg:classifiers":[
        {
            "category":"Organizations",
            "subcategory":"Religious Organization",
            "type":"Services"
        }
    ],
    "sg:phone":"+1 215 673 2386",
    "sg:postcode":"19115",
    "sg:province":"PA",
    "sg:tags":[
        "church"
    ],
    "wof:name":"United Methodist Church",
    "wof:placetype":"venue"
},
  "geometry": {"coordinates":[-75.04625299999999,40.091456],"type":"Point"}
}