{
  "type": "Feature",
  "properties": {
    "iso:country":"US",
    "sg:address":"132 E Catherine St",
    "sg:city":"Somerset",
    "sg:classifiers":[
        {
            "category":"Professional",
            "type":"Services"
        }
    ],
    "sg:phone":"+1 814 445 1426",
    "sg:postcode":"15501",
    "sg:province":"PA",
    "sg:tags":[
        "establishment"
    ],
    "wof:name":"Somerset County Commissioner",
    "wof:placetype":"venue"
},
  "geometry": {"coordinates":[-79.07794699999999,40.010996],"type":"Point"}
}