{
  "type": "Feature",
  "properties": {
    "iso:country":"US",
    "sg:address":"6112 Wallingford Way",
    "sg:city":"Mechanicsburg",
    "sg:classifiers":[
        {
            "category":"Organizations",
            "subcategory":"Religious Organization",
            "type":"Services"
        }
    ],
    "sg:phone":"+1 717 737 9551",
    "sg:postcode":"17050",
    "sg:province":"PA",
    "wof:name":"Kraus Thomas D Rev",
    "wof:placetype":"venue"
},
  "geometry": {"coordinates":[-76.994202,40.270302],"type":"Point"}
}