{
  "type": "Feature",
  "properties": {
    "iso:country":"US",
    "sg:address":"1313 Kennedy St",
    "sg:city":"Duquesne",
    "sg:classifiers":[
        {
            "category":"Bars & Pubs",
            "type":"Food & Drink"
        }
    ],
    "sg:phone":"+1 412 466 1620",
    "sg:postcode":"15110",
    "sg:province":"PA",
    "wof:name":"Buckle's Bar & Grill",
    "wof:placetype":"venue"
},
  "geometry": {"coordinates":[-79.85644499999999,40.367006],"type":"Point"}
}