{
  "type": "Feature",
  "properties": {
    "iso:country":"US",
    "sg:address":"8250 Harmony Grove Rd",
    "sg:city":"Wellsville",
    "sg:classifiers":[
        {
            "category":"Farming",
            "subcategory":"Farm",
            "type":"Manufacturing & Wholesale Goods"
        }
    ],
    "sg:phone":"+1   ",
    "sg:postcode":"17365",
    "sg:province":"PA",
    "sg:tags":[
        "crop",
        "general"
    ],
    "wof:name":"Kitzmiller Farm",
    "wof:placetype":"venue"
},
  "geometry": {"coordinates":[-76.95906600000001,40.046468],"type":"Point"}
}