{
  "type": "Feature",
  "properties": {
    "iso:country":"US",
    "sg:address":"3253 W Germantown Pike",
    "sg:city":"Norristown",
    "sg:classifiers":[
        {
            "category":"Social Services",
            "type":"Services"
        }
    ],
    "sg:phone":"+1 610 489 6671",
    "sg:postcode":"19403",
    "sg:province":"PA",
    "sg:tags":[
        "organization",
        "welfare"
    ],
    "wof:name":"Adventist Community Svc Ctr",
    "wof:placetype":"venue"
},
  "geometry": {"coordinates":[-75.396738,40.171248],"type":"Point"}
}