{
  "type": "Feature",
  "properties": {
    "addr:full":"1075 Milford Dr Bethel Park PA 15102",
    "addr:housenumber":"1075",
    "addr:postcode":"15102",
    "addr:street":"Milford Dr",
    "iso:country":"US",
    "sg:address":"1075 Milford Dr",
    "sg:city":"Bethel Park",
    "sg:classifiers":[
        {
            "category":"Shopping",
            "subcategory":"Musical Instruments",
            "type":"Retail Goods"
        }
    ],
    "sg:phone":"+1 412 831 1233",
    "sg:postcode":"15102",
    "sg:province":"PA",
    "sg:tags":[
        "teacher"
    ],
    "wof:name":"Organcraft",
    "wof:placetype":"venue"
},
  "geometry": {"coordinates":[-80.02780199999999,40.352001],"type":"Point"}
}