{
  "type": "Feature",
  "properties": {
    "iso:country":"US",
    "sg:address":"4170 Perkiomen Ave",
    "sg:city":"Reading",
    "sg:classifiers":[
        {
            "category":"Restaurant",
            "type":"Food & Drink"
        }
    ],
    "sg:phone":"+1 610 370 1040",
    "sg:postcode":"19606",
    "sg:province":"PA",
    "sg:tags":[
        "eating"
    ],
    "wof:name":"O'Malley's Family Restaurant",
    "wof:placetype":"venue"
},
  "geometry": {"coordinates":[-75.86739,40.311064],"type":"Point"}
}