{
  "type": "Feature",
  "properties": {
    "addr:full":"1224 Alexander Dr Hatfield PA 19440",
    "addr:housenumber":"1224",
    "addr:postcode":"19440",
    "addr:street":"Alexander Dr",
    "iso:country":"US",
    "sg:address":"1224 Alexander Dr",
    "sg:city":"Hatfield",
    "sg:classifiers":[
        {
            "category":"Building & Trades",
            "subcategory":"Electrical",
            "type":"Services"
        }
    ],
    "sg:phone":"+1   ",
    "sg:postcode":"19440",
    "sg:province":"PA",
    "sg:tags":[
        "electrical",
        "contractor"
    ],
    "wof:name":"Ashton Electrical Service",
    "wof:placetype":"venue"
},
  "geometry": {"coordinates":[-75.31652,40.276483],"type":"Point"}
}