{
  "type": "Feature",
  "properties": {
    "iso:country":"US",
    "sg:address":"138 E High St",
    "sg:city":"Waynesburg",
    "sg:classifiers":[
        {
            "category":"Shopping",
            "subcategory":"Florist",
            "type":"Retail Goods"
        }
    ],
    "sg:phone":"+1 724 627 6196",
    "sg:postcode":"15370",
    "sg:province":"PA",
    "sg:website":"www.waynesburgfloral.com",
    "wof:name":"Waynesburg Floral Co",
    "wof:placetype":"venue"
},
  "geometry": {"coordinates":[-80.185001,39.896367],"type":"Point"}
}