{
  "type": "Feature",
  "properties": {
    "iso:country":"US",
    "sg:address":"3343 Main St",
    "sg:city":"Harrison City",
    "sg:classifiers":[
        {
            "category":"Retail",
            "subcategory":"Funeral Services",
            "type":"Services"
        }
    ],
    "sg:phone":"+1 724 744 2721",
    "sg:postcode":"15642",
    "sg:province":"PA",
    "sg:tags":[
        "director"
    ],
    "wof:name":"James E Lindsay Funeral Home",
    "wof:placetype":"venue"
},
  "geometry": {"coordinates":[-79.763229,40.291064],"type":"Point"}
}