{
  "type": "Feature",
  "properties": {
    "iso:country":"US",
    "sg:address":"760 N Wales Rd",
    "sg:city":"North Wales",
    "sg:classifiers":[
        {
            "category":"Banks & Credit Unions",
            "subcategory":"Investment Brokerage",
            "type":"Services"
        }
    ],
    "sg:phone":"+1 215 699 1552",
    "sg:postcode":"19446",
    "sg:province":"PA",
    "sg:tags":[
        "consultant",
        "planning",
        "financial"
    ],
    "wof:name":"Dawson & Assoc",
    "wof:placetype":"venue"
},
  "geometry": {"coordinates":[-75.29197000000001,40.195768],"type":"Point"}
}