{
  "type": "Feature",
  "properties": {
    "addr:full":"800 Old Pond Rd Bridgeville PA 15017",
    "addr:housenumber":"800",
    "addr:postcode":"15017",
    "addr:street":"Old Pond Rd",
    "iso:country":"US",
    "sg:address":"800 Old Pond Rd",
    "sg:city":"Bridgeville",
    "sg:classifiers":[
        {
            "category":"Manufacturing",
            "subcategory":"Chemicals & Compounds",
            "type":"Manufacturing & Wholesale Goods"
        },
        {
            "category":"Manufacturing",
            "subcategory":"Tools & Machinery",
            "type":"Manufacturing & Wholesale Goods"
        }
    ],
    "sg:phone":"+1 412 257 9580",
    "sg:postcode":"15017",
    "sg:province":"PA",
    "sg:tags":[
        "for",
        "mfg",
        "system",
        "air",
        "design",
        "purification"
    ],
    "sg:website":"www.tigg.com",
    "wof:name":"Tigg Corp",
    "wof:placetype":"venue"
},
  "geometry": {"coordinates":[-80.119215,40.353417],"type":"Point"}
}