{
  "type": "Feature",
  "properties": {
    "iso:country":"US",
    "sg:address":"145 Hickory Rd",
    "sg:city":"Dingmans Ferry",
    "sg:classifiers":[
        {
            "category":"Building & Trades",
            "subcategory":"Construction",
            "type":"Services"
        }
    ],
    "sg:phone":"+1   ",
    "sg:postcode":"18328",
    "sg:province":"PA",
    "sg:tags":[
        "contractor"
    ],
    "wof:name":"Conklin Contracting",
    "wof:placetype":"venue"
},
  "geometry": {"coordinates":[-74.949699,41.256004],"type":"Point"}
}