{
  "type": "Feature",
  "properties": {
    "addr:full":"14 Sherri Ln Lititz PA 17543",
    "addr:housenumber":"14",
    "addr:postcode":"17543",
    "addr:street":"Sherri Ln",
    "iso:country":"US",
    "sg:address":"14 Sherri Ln",
    "sg:city":"Lititz",
    "sg:classifiers":[
        {
            "category":"Shopping",
            "subcategory":"Clothing, Apparel, & Fashions",
            "type":"Retail Goods"
        }
    ],
    "sg:phone":"+1   ",
    "sg:postcode":"17543",
    "sg:province":"PA",
    "sg:tags":[
        "shop",
        "beauty"
    ],
    "wof:name":"Bitners Beauty Boutique",
    "wof:placetype":"venue"
},
  "geometry": {"coordinates":[-76.26060200000001,40.135227],"type":"Point"}
}