{
  "type": "Feature",
  "properties": {
    "addr:full":"210 Shady Ave Cheswick PA 15024",
    "addr:housenumber":"210",
    "addr:postcode":"15024",
    "addr:street":"Shady Ave",
    "iso:country":"US",
    "sg:address":"210 Shady Ave",
    "sg:city":"Cheswick",
    "sg:classifiers":[
        {
            "category":"Shopping",
            "subcategory":"Bicycles & Sporting Goods",
            "type":"Retail Goods"
        }
    ],
    "sg:phone":"+1   ",
    "sg:postcode":"15024",
    "sg:province":"PA",
    "wof:name":"Richerd Plosak",
    "wof:placetype":"venue"
},
  "geometry": {"coordinates":[-79.796307,40.538424],"type":"Point"}
}