{
  "type": "Feature",
  "properties": {
    "iso:country":"US",
    "sg:address":"62 S Main St",
    "sg:city":"Montrose",
    "sg:classifiers":[
        {
            "category":"Health Services",
            "subcategory":"Doctor",
            "type":"Services"
        }
    ],
    "sg:phone":"+1   ",
    "sg:postcode":"18801",
    "sg:province":"PA",
    "wof:name":"David J Rechlicz Dmb",
    "wof:placetype":"venue"
},
  "geometry": {"coordinates":[-75.88076,41.82983],"type":"Point"}
}