{
  "type": "Feature",
  "properties": {
    "addr:full":"263 S Whitford Rd Exton PA 19341",
    "addr:housenumber":"263",
    "addr:postcode":"19341",
    "addr:street":"S Whitford Rd",
    "iso:country":"US",
    "sg:address":"263 S Whitford Rd",
    "sg:city":"Exton",
    "sg:classifiers":[
        {
            "category":"Wholesale",
            "subcategory":"Machinery & Supplies",
            "type":"Manufacturing & Wholesale Goods"
        }
    ],
    "sg:phone":"+1 484 713 0040",
    "sg:postcode":"19341",
    "sg:province":"PA",
    "sg:tags":[
        "janitor"
    ],
    "wof:name":"Cleaners Proshop",
    "wof:placetype":"venue"
},
  "geometry": {"coordinates":[-75.6404,40.01857],"type":"Point"}
}