{
  "type": "Feature",
  "properties": {
    "iso:country":"US",
    "sg:address":"360 Water St",
    "sg:city":"Conneaut Lake",
    "sg:classifiers":[
        {
            "category":"Restaurant",
            "type":"Food & Drink"
        }
    ],
    "sg:phone":"+1 814 382 3311",
    "sg:postcode":"16316",
    "sg:province":"PA",
    "wof:name":"KFC",
    "wof:placetype":"venue"
},
  "geometry": {"coordinates":[-80.305092,41.603223],"type":"Point"}
}