{
  "type": "Feature",
  "properties": {
    "iso:country":"US",
    "sg:address":"2600 Macdade Blvd",
    "sg:city":"Holmes",
    "sg:classifiers":[
        {
            "category":"Shopping",
            "subcategory":"Computers & Home Electronics",
            "type":"Retail Goods"
        }
    ],
    "sg:phone":"+1 610 583 5175",
    "sg:postcode":"19043",
    "sg:province":"PA",
    "sg:tags":[
        "equipment",
        "video"
    ],
    "wof:name":"Game Store",
    "wof:placetype":"venue"
},
  "geometry": {"coordinates":[-75.304295,39.899801],"type":"Point"}
}