{
  "type": "Feature",
  "properties": {
    "addr:full":"443 Bruceton Rd Markleysburg PA 15459",
    "addr:housenumber":"443",
    "addr:postcode":"15459",
    "addr:street":"Bruceton Rd",
    "iso:country":"US",
    "sg:address":"443 Bruceton Rd",
    "sg:city":"Markleysburg",
    "sg:classifiers":[
        {
            "category":"Building & Trades",
            "subcategory":"Construction",
            "type":"Services"
        }
    ],
    "sg:phone":"+1   ",
    "sg:postcode":"15459",
    "sg:province":"PA",
    "sg:tags":[
        "excavation",
        "contractor"
    ],
    "wof:name":"Jds Backhoe Service",
    "wof:placetype":"venue"
},
  "geometry": {"coordinates":[-79.47179,39.733182],"type":"Point"}
}