{
  "type": "Feature",
  "properties": {
    "iso:country":"US",
    "sg:address":"29 Germania St",
    "sg:city":"Galeton",
    "sg:classifiers":[
        {
            "category":"Insurance",
            "subcategory":"Insurance Agent",
            "type":"Services"
        }
    ],
    "sg:phone":"+1 814 435 1338",
    "sg:postcode":"16922",
    "sg:province":"PA",
    "wof:name":"Richar Insurance & Financial",
    "wof:placetype":"venue"
},
  "geometry": {"coordinates":[-77.64408,41.732649],"type":"Point"}
}