{
  "type": "Feature",
  "properties": {
    "iso:country":"US",
    "sg:address":"5619 Walnut St",
    "sg:city":"Philadelphia",
    "sg:classifiers":[
        {
            "category":"Organizations",
            "subcategory":"Religious Organization",
            "type":"Services"
        }
    ],
    "sg:phone":"+1 215 471 8676",
    "sg:postcode":"19139",
    "sg:province":"PA",
    "sg:tags":[
        "church"
    ],
    "wof:name":"Angora Park Congregation",
    "wof:placetype":"venue"
},
  "geometry": {"coordinates":[-75.23386000000001,39.958052],"type":"Point"}
}