{
  "type": "Feature",
  "properties": {
    "addr:full":"629 Batts Switch Rd Pen Argyl PA 18072",
    "addr:housenumber":"629",
    "addr:postcode":"18072",
    "addr:street":"Batts Switch Rd",
    "iso:country":"US",
    "sg:address":"629 Batts Switch Rd",
    "sg:city":"Pen Argyl",
    "sg:classifiers":[
        {
            "category":"Home & Garden",
            "subcategory":"Furniture",
            "type":"Retail Goods"
        }
    ],
    "sg:phone":"+1 610 759 1826",
    "sg:postcode":"18072",
    "sg:province":"PA",
    "sg:tags":[
        "builder",
        "custom"
    ],
    "wof:name":"Kessler's Fine Woodworking",
    "wof:placetype":"venue"
},
  "geometry": {"coordinates":[-75.28651499999999,40.803709],"type":"Point"}
}