{
  "type": "Feature",
  "properties": {
    "iso:country":"US",
    "sg:address":"1707 Freeport Rd",
    "sg:city":"Natrona Heights",
    "sg:classifiers":[
        {
            "category":"Autos & Motor Vehicles",
            "subcategory":"Auto Supplies",
            "type":"Retail Goods"
        }
    ],
    "sg:phone":"+1 724 224 7900",
    "sg:postcode":"15065",
    "sg:province":"PA",
    "sg:tags":[
        "tire"
    ],
    "wof:name":"Highland Tire Inc",
    "wof:placetype":"venue"
},
  "geometry": {"coordinates":[-79.726315,40.622713],"type":"Point"}
}