{
  "type": "Feature",
  "properties": {
    "addr:full":"20 Fetters Mill Sq Huntingdon Valley PA 19006",
    "addr:housenumber":"20",
    "addr:postcode":"19006",
    "addr:street":"Fetters Mill Sq",
    "iso:country":"US",
    "sg:address":"20 Fetters Mill Sq",
    "sg:city":"Huntingdon Valley",
    "sg:classifiers":[
        {
            "category":"Professional",
            "type":"Services"
        }
    ],
    "sg:phone":"+1   ",
    "sg:postcode":"19006",
    "sg:province":"PA",
    "wof:name":"Milu Inc",
    "wof:placetype":"venue"
},
  "geometry": {"coordinates":[-75.06273299999999,40.12613],"type":"Point"}
}