{
  "type": "Feature",
  "properties": {
    "addr:full":"103 S Mill St New Castle PA 16101",
    "addr:housenumber":"103",
    "addr:postcode":"16101",
    "addr:street":"S Mill St",
    "iso:country":"US",
    "sg:address":"103 S Mill St",
    "sg:city":"New Castle",
    "sg:classifiers":[
        {
            "category":"Professional",
            "type":"Services"
        }
    ],
    "sg:phone":"+1 724 652 1916",
    "sg:postcode":"16101",
    "sg:province":"PA",
    "sg:tags":[
        "establishment"
    ],
    "wof:name":"Stew In Design",
    "wof:placetype":"venue"
},
  "geometry": {"coordinates":[-80.344334,40.998842],"type":"Point"}
}