{
  "type": "Feature",
  "properties": {
    "iso:country":"US",
    "sg:address":"757 Norland Ave",
    "sg:city":"Chambersburg",
    "sg:classifiers":[
        {
            "category":"Health Services",
            "subcategory":"Doctor",
            "type":"Services"
        }
    ],
    "sg:phone":"+1 717 263 0199",
    "sg:postcode":"17201",
    "sg:province":"PA",
    "sg:tags":[
        "physician",
        "surgeon"
    ],
    "wof:name":"Tri State Neurology Ctr",
    "wof:placetype":"venue"
},
  "geometry": {"coordinates":[-77.639295,39.943873],"type":"Point"}
}