{
  "type": "Feature",
  "properties": {
    "iso:country":"US",
    "sg:address":"508 S Millvale Ave",
    "sg:city":"Pittsburgh",
    "sg:classifiers":[
        {
            "category":"Health Services",
            "subcategory":"Podiatrist",
            "type":"Services"
        }
    ],
    "sg:phone":"+1 412 681 6686",
    "sg:postcode":"15224",
    "sg:province":"PA",
    "wof:name":"Daniel R Molcsan DPM",
    "wof:placetype":"venue"
},
  "geometry": {"coordinates":[-79.946062,40.459942],"type":"Point"}
}