{
  "type": "Feature",
  "properties": {
    "iso:country":"US",
    "sg:address":"400 Davis St",
    "sg:city":"Clarks Summit",
    "sg:classifiers":[
        {
            "category":"Insurance",
            "subcategory":"Insurance Agent",
            "type":"Services"
        }
    ],
    "sg:phone":"+1 570 587 7534",
    "sg:postcode":"18411",
    "sg:province":"PA",
    "wof:name":"Mark J Lynn",
    "wof:placetype":"venue"
},
  "geometry": {"coordinates":[-75.702322,41.492946],"type":"Point"}
}