{
  "type": "Feature",
  "properties": {
    "addr:full":"13219 Monterey Ln Blue Ridge Smt PA 17214",
    "addr:housenumber":"13219",
    "addr:postcode":"17214",
    "addr:street":"Monterey Ln",
    "iso:country":"US",
    "sg:address":"13219 Monterey Ln",
    "sg:city":"Blue Ridge Smt",
    "sg:classifiers":[
        {
            "category":"Organizations",
            "subcategory":"Religious Organization",
            "type":"Services"
        }
    ],
    "sg:phone":"+1 717 794 2067",
    "sg:postcode":"17214",
    "sg:province":"PA",
    "sg:tags":[
        "church"
    ],
    "wof:name":"St Rita's Catholic Church",
    "wof:placetype":"venue"
},
  "geometry": {"coordinates":[-77.471119,39.727474],"type":"Point"}
}