{
  "type": "Feature",
  "properties": {
    "iso:country":"US",
    "sg:address":"216 N Jefferson St",
    "sg:city":"Kittanning",
    "sg:classifiers":[
        {
            "category":"Real Estate",
            "subcategory":"Real Estate Agent",
            "type":"Services"
        }
    ],
    "sg:phone":"+1 724 548 5464",
    "sg:postcode":"16201",
    "sg:province":"PA",
    "sg:website":"www.alleghenyrealestate.com",
    "wof:name":"Allegheny Real Estate",
    "wof:placetype":"venue"
},
  "geometry": {"coordinates":[-79.52116700000001,40.815651],"type":"Point"}
}