{
  "type": "Feature",
  "properties": {
    "addr:full":"438 Warren Blvd Broomall PA 19008",
    "addr:housenumber":"438",
    "addr:postcode":"19008",
    "addr:street":"Warren Blvd",
    "iso:country":"US",
    "sg:address":"438 Warren Blvd",
    "sg:city":"Broomall",
    "sg:classifiers":[
        {
            "category":"Building & Trades",
            "subcategory":"Construction",
            "type":"Services"
        }
    ],
    "sg:phone":"+1   ",
    "sg:postcode":"19008",
    "sg:province":"PA",
    "sg:tags":[
        "contractor"
    ],
    "wof:name":"Trimarelli Tile",
    "wof:placetype":"venue"
},
  "geometry": {"coordinates":[-75.345309,39.960717],"type":"Point"}
}