{
  "type": "Feature",
  "properties": {
    "iso:country":"US",
    "sg:address":"20 Windihill Dr",
    "sg:city":"Greensburg",
    "sg:classifiers":[
        {
            "category":"Building & Trades",
            "subcategory":"Construction",
            "type":"Services"
        }
    ],
    "sg:phone":"+1   ",
    "sg:postcode":"15601",
    "sg:province":"PA",
    "sg:tags":[
        "installation",
        "floor"
    ],
    "wof:name":"John Pushwa Floor Installation",
    "wof:placetype":"venue"
},
  "geometry": {"coordinates":[-79.54521099999999,40.331526],"type":"Point"}
}