{
  "type": "Feature",
  "properties": {
    "iso:country":"US",
    "sg:address":"1000 S State St",
    "sg:city":"Clarks Summit",
    "sg:classifiers":[
        {
            "category":"Restaurant",
            "type":"Food & Drink"
        }
    ],
    "sg:phone":"+1 570 587 3236",
    "sg:postcode":"18411",
    "sg:province":"PA",
    "wof:name":"Kyoto",
    "wof:placetype":"venue"
},
  "geometry": {"coordinates":[-75.697818,41.490709],"type":"Point"}
}