{
  "type": "Feature",
  "properties": {
    "iso:country":"US",
    "sg:address":"225 S Broad St",
    "sg:city":"Grove City",
    "sg:classifiers":[
        {
            "category":"Shopping",
            "subcategory":"Gifts & Souvenirs",
            "type":"Retail Goods"
        }
    ],
    "sg:phone":"+1 724 458 0903",
    "sg:postcode":"16127",
    "sg:province":"PA",
    "wof:name":"Berry Patch",
    "wof:placetype":"venue"
},
  "geometry": {"coordinates":[-80.086665,41.159262],"type":"Point"}
}