{
  "type": "Feature",
  "properties": {
    "iso:country":"US",
    "sg:address":"205 S Front St",
    "sg:city":"Harrisburg",
    "sg:classifiers":[
        {
            "category":"Health Services",
            "subcategory":"Doctor",
            "type":"Services"
        },
        {
            "category":"Health Services",
            "subcategory":"Clinic",
            "type":"Services"
        }
    ],
    "sg:phone":"+1 717 231 8360",
    "sg:postcode":"17104",
    "sg:province":"PA",
    "sg:tags":[
        "counseling",
        "mental",
        "psychiatrist"
    ],
    "wof:name":"McGraw Susan Lsw",
    "wof:placetype":"venue"
},
  "geometry": {"coordinates":[-76.8797,40.256901],"type":"Point"}
}