{
  "type": "Feature",
  "properties": {
    "iso:country":"US",
    "sg:address":"2509 Bloom Rd",
    "sg:city":"Danville",
    "sg:classifiers":[
        {
            "category":"Organizations",
            "subcategory":"Religious Organization",
            "type":"Services"
        }
    ],
    "sg:phone":"+1   ",
    "sg:postcode":"17821",
    "sg:province":"PA",
    "wof:name":"Saint James Untd Church Christ",
    "wof:placetype":"venue"
},
  "geometry": {"coordinates":[-76.565929,40.968635],"type":"Point"}
}