{
  "type": "Feature",
  "properties": {
    "addr:full":"200 Greentree Rd Munhall PA 15120",
    "addr:housenumber":"200",
    "addr:postcode":"15120",
    "addr:street":"Greentree Rd",
    "iso:country":"US",
    "sg:address":"200 Greentree Rd",
    "sg:city":"Munhall",
    "sg:classifiers":[
        {
            "category":"Local Transit",
            "type":"Transportation"
        }
    ],
    "sg:phone":"+1 412 462 4858",
    "sg:postcode":"15120",
    "sg:province":"PA",
    "sg:tags":[
        "airport"
    ],
    "wof:name":"Majesty Limousine",
    "wof:placetype":"venue"
},
  "geometry": {"coordinates":[-79.91404799999999,40.383461],"type":"Point"}
}