{
  "type": "Feature",
  "properties": {
    "iso:country":"US",
    "sg:address":"242 Station St",
    "sg:city":"Bridgeville",
    "sg:classifiers":[
        {
            "category":"Insurance",
            "subcategory":"Insurance Agent",
            "type":"Services"
        }
    ],
    "sg:phone":"+1   ",
    "sg:postcode":"15017",
    "sg:province":"PA",
    "sg:tags":[
        "personal"
    ],
    "wof:name":"Progressive Insurance",
    "wof:placetype":"venue"
},
  "geometry": {"coordinates":[-80.114869,40.35911],"type":"Point"}
}