{
  "type": "Feature",
  "properties": {
    "iso:country":"US",
    "sg:address":"304 3rd St",
    "sg:city":"California",
    "sg:classifiers":[
        {
            "category":"Restaurant",
            "type":"Food & Drink"
        }
    ],
    "sg:phone":"+1   ",
    "sg:postcode":"15419",
    "sg:province":"PA",
    "sg:tags":[
        "eating"
    ],
    "wof:name":"Cara Mia Cafe",
    "wof:placetype":"venue"
},
  "geometry": {"coordinates":[-79.8907,40.066656],"type":"Point"}
}