{
  "type": "Feature",
  "properties": {
    "iso:country":"US",
    "sg:address":"370 Perry Hwy",
    "sg:city":"Harmony",
    "sg:classifiers":[
        {
            "category":"Autos & Motor Vehicles",
            "subcategory":"Motorcycle Sales",
            "type":"Retail Goods"
        }
    ],
    "sg:phone":"+1 724 452 7540",
    "sg:postcode":"16037",
    "sg:province":"PA",
    "sg:tags":[
        "scooter"
    ],
    "wof:name":"Harmony Cycle",
    "wof:placetype":"venue"
},
  "geometry": {"coordinates":[-80.122477,40.830383],"type":"Point"}
}