{
  "type": "Feature",
  "properties": {
    "iso:country":"US",
    "sg:address":"550 Donnan Ave",
    "sg:city":"Washington",
    "sg:classifiers":[
        {
            "category":"Organizations",
            "subcategory":"Membership Organization",
            "type":"Services"
        }
    ],
    "sg:phone":"+1   ",
    "sg:postcode":"15301",
    "sg:province":"PA",
    "wof:name":"Washington Flyers Club Inc",
    "wof:placetype":"venue"
},
  "geometry": {"coordinates":[-80.254344,40.178736],"type":"Point"}
}