{
  "type": "Feature",
  "properties": {
    "iso:country":"US",
    "sg:address":"63 Forty Foot Rd",
    "sg:city":"Lansdale",
    "sg:classifiers":[
        {
            "category":"Banks & Credit Unions",
            "subcategory":"Bank",
            "type":"Services"
        }
    ],
    "sg:phone":"+1   ",
    "sg:postcode":"19446",
    "sg:province":"PA",
    "sg:tags":[
        "national",
        "commercial"
    ],
    "wof:name":"Lansdale Office",
    "wof:placetype":"venue"
},
  "geometry": {"coordinates":[-75.319895,40.262476],"type":"Point"}
}