{
  "type": "Feature",
  "properties": {
    "iso:country":"US",
    "sg:address":"726 Church St",
    "sg:city":"Fogelsville",
    "sg:classifiers":[
        {
            "category":"Health Services",
            "subcategory":"Health Practitioner",
            "type":"Services"
        }
    ],
    "sg:phone":"+1 610 530 8392",
    "sg:postcode":"18051",
    "sg:province":"PA",
    "sg:tags":[
        "psychologist"
    ],
    "wof:name":"Veronique Valliere",
    "wof:placetype":"venue"
},
  "geometry": {"coordinates":[-75.628941,40.581351],"type":"Point"}
}