{
  "type": "Feature",
  "properties": {
    "iso:country":"US",
    "sg:address":"RR 1 Box 1460",
    "sg:city":"Factoryville",
    "sg:classifiers":[
        {
            "category":"Professional",
            "subcategory":"Detective & Security Services",
            "type":"Services"
        }
    ],
    "sg:phone":"+1 570 575 3049",
    "sg:postcode":"18419",
    "sg:province":"PA",
    "sg:tags":[
        "information",
        "bureau"
    ],
    "wof:name":"Applied Genius",
    "wof:placetype":"venue"
},
  "geometry": {"coordinates":[-75.88479599999999,41.634153],"type":"Point"}
}