{
  "type": "Feature",
  "properties": {
    "addr:full":"397 E Church Rd King Of Prussia PA 19406",
    "addr:housenumber":"397",
    "addr:postcode":"19406",
    "addr:street":"E Church Rd",
    "iso:country":"US",
    "sg:address":"397 E Church Rd",
    "sg:city":"King Of Prussia",
    "sg:classifiers":[
        {
            "category":"Professional",
            "subcategory":"Research",
            "type":"Services"
        }
    ],
    "sg:phone":"+1 610 239 0621",
    "sg:postcode":"19406",
    "sg:province":"PA",
    "sg:tags":[
        "environmental",
        "ecological"
    ],
    "wof:name":"Environmental Recycling Corp",
    "wof:placetype":"venue"
},
  "geometry": {"coordinates":[-75.34666,40.08941],"type":"Point"}
}