{
  "type": "Feature",
  "properties": {
    "addr:full":"1673 Rte 65 Ellwood City PA 16117",
    "addr:housenumber":"1673",
    "addr:postcode":"16117",
    "addr:street":"Rte 65",
    "iso:country":"US",
    "sg:address":"1673 Rte 65",
    "sg:city":"Ellwood City",
    "sg:classifiers":[
        {
            "category":"Health Services",
            "subcategory":"Doctor",
            "type":"Services"
        }
    ],
    "sg:phone":"+1   ",
    "sg:postcode":"16117",
    "sg:province":"PA",
    "sg:tags":[
        "medical"
    ],
    "wof:name":"Milton Caplan MD",
    "wof:placetype":"venue"
},
  "geometry": {"coordinates":[-80.276043,40.843013],"type":"Point"}
}