{
  "type": "Feature",
  "properties": {
    "addr:full":"400 N Broad St Lansdale PA 19446",
    "addr:housenumber":"400",
    "addr:postcode":"19446",
    "addr:street":"N Broad St",
    "iso:country":"US",
    "sg:address":"400 N Broad St",
    "sg:city":"Lansdale",
    "sg:classifiers":[
        {
            "category":"Social Services",
            "subcategory":"Adult Care",
            "type":"Services"
        }
    ],
    "sg:phone":"+1 215 855 9578",
    "sg:postcode":"19446",
    "sg:province":"PA",
    "sg:tags":[
        "organization",
        "senior",
        "citizen"
    ],
    "wof:name":"Retired Senior Volunteer Prgrm",
    "wof:placetype":"venue"
},
  "geometry": {"coordinates":[-75.28125,40.244077],"type":"Point"}
}