{
  "type": "Feature",
  "properties": {
    "iso:country":"US",
    "sg:address":"1705 Washington Blvd",
    "sg:city":"Easton",
    "sg:classifiers":[
        {
            "category":"Insurance",
            "subcategory":"Insurance Agent",
            "type":"Services"
        }
    ],
    "sg:phone":"+1 610 258 9314",
    "sg:postcode":"18042",
    "sg:province":"PA",
    "wof:name":"State Farm Insurance",
    "wof:placetype":"venue"
},
  "geometry": {"coordinates":[-75.23641000000001,40.686052],"type":"Point"}
}