{
  "type": "Feature",
  "properties": {
    "addr:full":"2 S 9th St Akron PA 17501",
    "addr:housenumber":"2",
    "addr:postcode":"17501",
    "addr:street":"S 9Th St",
    "iso:country":"US",
    "sg:address":"2 S 9th St",
    "sg:city":"Akron",
    "sg:classifiers":[
        {
            "category":"Banks & Credit Unions",
            "subcategory":"Bank",
            "type":"Services"
        }
    ],
    "sg:phone":"+1 717 859 1185",
    "sg:postcode":"17501",
    "sg:province":"PA",
    "sg:tags":[
        "national",
        "commercial"
    ],
    "sg:website":"www.fultonbank.com",
    "wof:name":"Fulton Bank",
    "wof:placetype":"venue"
},
  "geometry": {"coordinates":[-76.20213099999999,40.156346],"type":"Point"}
}