{
  "type": "Feature",
  "properties": {
    "iso:country":"US",
    "sg:address":"107 Founders Ct",
    "sg:city":"Bethlehem",
    "sg:classifiers":[
        {
            "category":"Retail",
            "subcategory":"Repair Shop",
            "type":"Services"
        }
    ],
    "sg:phone":"+1 610 694 8700",
    "sg:postcode":"18020",
    "sg:province":"PA",
    "sg:tags":[
        "spa",
        "hot",
        "tub"
    ],
    "wof:name":"Darby Electric",
    "wof:placetype":"venue"
},
  "geometry": {"coordinates":[-75.309613,40.669403],"type":"Point"}
}