{
  "type": "Feature",
  "properties": {
    "iso:country":"US",
    "sg:address":"335 5th Ave",
    "sg:city":"Mckeesport",
    "sg:classifiers":[
        {
            "category":"Government",
            "subcategory":"Office",
            "type":"Public Place"
        }
    ],
    "sg:phone":"+1 412 672 6970",
    "sg:postcode":"15132",
    "sg:province":"PA",
    "wof:name":"Mc Keesport Family Ctr",
    "wof:placetype":"venue"
},
  "geometry": {"coordinates":[-79.863393,40.351236],"type":"Point"}
}