{
  "type": "Feature",
  "properties": {
    "addr:full":"905 Tower Rd Bristol PA 19007",
    "addr:housenumber":"905",
    "addr:postcode":"19007",
    "addr:street":"Tower Rd",
    "iso:country":"US",
    "sg:address":"905 Tower Rd",
    "sg:city":"Bristol",
    "sg:classifiers":[
        {
            "category":"Health Services",
            "subcategory":"Nursing And Care Facility",
            "type":"Services"
        }
    ],
    "sg:phone":"+1 215 785 3201",
    "sg:postcode":"19007",
    "sg:province":"PA",
    "sg:tags":[
        "home",
        "convalescent"
    ],
    "wof:name":"Silver Lake Nursing & Rehab",
    "wof:placetype":"venue"
},
  "geometry": {"coordinates":[-74.870529,40.107591],"type":"Point"}
}