{
  "type": "Feature",
  "properties": {
    "iso:country":"US",
    "sg:address":"1875 Hempstead Rd",
    "sg:city":"Lancaster",
    "sg:classifiers":[
        {
            "category":"Restaurant",
            "type":"Food & Drink"
        }
    ],
    "sg:menulink":"http://www.allmenus.com/pa/lancaster/107111-soup-man/menu/",
    "sg:phone":"+1 717 396 8460",
    "sg:postcode":"17601",
    "sg:province":"PA",
    "sg:tags":[
        "soup",
        "american",
        "salad"
    ],
    "wof:name":"Soup Man",
    "wof:placetype":"venue"
},
  "geometry": {"coordinates":[-76.256606,40.052903],"type":"Point"}
}