{
  "type": "Feature",
  "properties": {
    "addr:full":"641 Alpha Dr Pittsburgh PA 15238",
    "addr:housenumber":"641",
    "addr:postcode":"15238",
    "addr:street":"Alpha Dr",
    "iso:country":"US",
    "sg:address":"641 Alpha Dr",
    "sg:city":"Pittsburgh",
    "sg:classifiers":[
        {
            "category":"Wholesale",
            "subcategory":"Groceries",
            "type":"Manufacturing & Wholesale Goods"
        }
    ],
    "sg:phone":"+1 412 406 5700",
    "sg:postcode":"15238",
    "sg:province":"PA",
    "sg:tags":[
        "grocers-wholesale"
    ],
    "wof:name":"Hub One Logistics, Ltd.",
    "wof:placetype":"venue"
},
  "geometry": {"coordinates":[-79.870502,40.500878],"type":"Point"}
}