{
  "type": "Feature",
  "properties": {
    "addr:full":"850 Beaver Grade Rd Coraopolis PA 15108",
    "addr:housenumber":"850",
    "addr:postcode":"15108",
    "addr:street":"Beaver Grade Rd",
    "iso:country":"US",
    "sg:address":"850 Beaver Grade Rd",
    "sg:city":"Coraopolis",
    "sg:classifiers":[
        {
            "category":"Travel",
            "subcategory":"Travel Agent",
            "type":"Entertainment"
        }
    ],
    "sg:phone":"+1   ",
    "sg:postcode":"15108",
    "sg:province":"PA",
    "sg:tags":[
        "agency"
    ],
    "wof:name":"Carlson Wagonlet Inc",
    "wof:placetype":"venue"
},
  "geometry": {"coordinates":[-80.21849,40.515021],"type":"Point"}
}