{
  "type": "Feature",
  "properties": {
    "iso:country":"US",
    "sg:address":"5142 Bernville Rd",
    "sg:city":"Bernville",
    "sg:classifiers":[
        {
            "category":"Bakery",
            "type":"Food & Drink"
        }
    ],
    "sg:phone":"+1 610 488 7758",
    "sg:postcode":"19506",
    "sg:province":"PA",
    "wof:name":"Creative Cake Designs-Theresa",
    "wof:placetype":"venue"
},
  "geometry": {"coordinates":[-76.03766899999999,40.404984],"type":"Point"}
}