{
  "type": "Feature",
  "properties": {
    "addr:full":"1250 Slate Hill Rd Camp Hill PA 17011",
    "addr:housenumber":"1250",
    "addr:postcode":"17011",
    "addr:street":"Slate Hill Rd",
    "iso:country":"US",
    "sg:address":"1250 Slate Hill Rd",
    "sg:city":"Camp Hill",
    "sg:classifiers":[
        {
            "category":"Food & Beverages",
            "subcategory":"Candy",
            "type":"Retail Goods"
        }
    ],
    "sg:phone":"+1 717 761 3192",
    "sg:postcode":"17011",
    "sg:province":"PA",
    "sg:tags":[
        "store"
    ],
    "wof:name":"Warrell Corporation",
    "wof:placetype":"venue"
},
  "geometry": {"coordinates":[-76.94470200000001,40.211601],"type":"Point"}
}