{
  "type": "Feature",
  "properties": {
    "addr:full":"934 Market St Marcus Hook PA 19061",
    "addr:housenumber":"934",
    "addr:postcode":"19061",
    "addr:street":"Market St",
    "iso:country":"US",
    "sg:address":"934 Market St",
    "sg:city":"Marcus Hook",
    "sg:classifiers":[
        {
            "category":"Retail",
            "subcategory":"Repair Shop",
            "type":"Services"
        }
    ],
    "sg:phone":"+1   ",
    "sg:postcode":"19061",
    "sg:province":"PA",
    "sg:tags":[
        "electrical"
    ],
    "wof:name":"Philips Alfred N Jr",
    "wof:placetype":"venue"
},
  "geometry": {"coordinates":[-75.417238,39.819826],"type":"Point"}
}