{
  "type": "Feature",
  "properties": {
    "iso:country":"US",
    "sg:address":"700 Greenwood Ave",
    "sg:city":"Jenkintown",
    "sg:classifiers":[
        {
            "category":"Manufacturing",
            "subcategory":"Lumber",
            "type":"Manufacturing & Wholesale Goods"
        }
    ],
    "sg:phone":"+1   ",
    "sg:postcode":"19046",
    "sg:province":"PA",
    "sg:tags":[
        "fire",
        "company",
        "volunteer"
    ],
    "wof:name":"Pioneer Fire Company",
    "wof:placetype":"venue"
},
  "geometry": {"coordinates":[-75.125642,40.095033],"type":"Point"}
}