{
  "type": "Feature",
  "properties": {
    "iso:country":"US",
    "sg:address":"150 S Independence Mall W # 403",
    "sg:city":"Philadelphia",
    "sg:classifiers":[
        {
            "category":"Professional",
            "subcategory":"Business Services",
            "type":"Services"
        }
    ],
    "sg:phone":"+1 215 861 4633",
    "sg:postcode":"19106",
    "sg:province":"PA",
    "sg:tags":[
        "medical",
        "administration"
    ],
    "sg:website":"http://www.officeofinspectorgeneral.com",
    "wof:name":"Regional Representative",
    "wof:placetype":"venue"
},
  "geometry": {"coordinates":[-75.15089399999999,39.948467],"type":"Point"}
}