{
  "type": "Feature",
  "properties": {
    "iso:country":"US",
    "sg:address":"2025 E Allegheny Ave",
    "sg:city":"Philadelphia",
    "sg:classifiers":[
        {
            "category":"Organizations",
            "subcategory":"Religious Organization",
            "type":"Services"
        }
    ],
    "sg:phone":"+1 215 427 1994",
    "sg:postcode":"19134",
    "sg:province":"PA",
    "sg:tags":[
        "church"
    ],
    "wof:name":"Greater Church Of Phila",
    "wof:placetype":"venue"
},
  "geometry": {"coordinates":[-75.11064,39.993653],"type":"Point"}
}