{
  "type": "Feature",
  "properties": {
    "addr:full":"8638 Germantown Ave Philadelphia PA 19118",
    "addr:housenumber":"8638",
    "addr:postcode":"19118",
    "addr:street":"Germantown Ave",
    "iso:country":"US",
    "sg:address":"8638 Germantown Ave",
    "sg:city":"Philadelphia",
    "sg:classifiers":[
        {
            "category":"Shopping",
            "subcategory":"Jewelry",
            "type":"Retail Goods"
        }
    ],
    "sg:phone":"+1 215 247 5486",
    "sg:postcode":"19118",
    "sg:province":"PA",
    "sg:tags":[
        "jeweler"
    ],
    "wof:name":"Bugay's Jewelers",
    "wof:placetype":"venue"
},
  "geometry": {"coordinates":[-75.20772700000001,40.076656],"type":"Point"}
}