{
  "type": "Feature",
  "properties": {
    "addr:full":"RR 2 Box 2267 Factoryville PA 18419",
    "addr:housenumber":"box 2267",
    "addr:postcode":"18419",
    "addr:street":"Rr 2",
    "iso:country":"US",
    "sg:address":"RR 2 Box 2267",
    "sg:city":"Factoryville",
    "sg:classifiers":[
        {
            "category":"Professional",
            "subcategory":"Art Services",
            "type":"Services"
        }
    ],
    "sg:phone":"+1 570 222 9100",
    "sg:postcode":"18419",
    "sg:province":"PA",
    "sg:tags":[
        "interior",
        "designer",
        "decorator"
    ],
    "wof:name":"Interior Images West",
    "wof:placetype":"venue"
},
  "geometry": {"coordinates":[-75.695385,41.616045],"type":"Point"}
}