{
  "type": "Feature",
  "properties": {
    "addr:full":"4 Tara Pl Wallingford PA 19086",
    "addr:housenumber":"4",
    "addr:postcode":"19086",
    "addr:street":"Tara Pl",
    "iso:country":"US",
    "sg:address":"4 Tara Pl",
    "sg:city":"Wallingford",
    "sg:classifiers":[
        {
            "category":"Social Services",
            "type":"Services"
        }
    ],
    "sg:phone":"+1   ",
    "sg:postcode":"19086",
    "sg:province":"PA",
    "wof:name":"Children & Adult Disability Ed",
    "wof:placetype":"venue"
},
  "geometry": {"coordinates":[-75.36837300000001,39.889401],"type":"Point"}
}