{
  "type": "Feature",
  "properties": {
    "iso:country":"US",
    "sg:address":"968 E King St",
    "sg:city":"York",
    "sg:classifiers":[
        {
            "category":"Retail",
            "subcategory":"Auto Repair",
            "type":"Services"
        }
    ],
    "sg:phone":"+1 717 854 8734",
    "sg:postcode":"17403",
    "sg:province":"PA",
    "sg:tags":[
        "body",
        "shop",
        "installation",
        "automobile",
        "alar",
        "automotive",
        "painting",
        "car"
    ],
    "wof:name":"Bob Stough's Body Shop",
    "wof:placetype":"venue"
},
  "geometry": {"coordinates":[-76.708551,39.967874],"type":"Point"}
}