{
  "type": "Feature",
  "properties": {
    "iso:country":"US",
    "sg:address":"45 N 23rd St",
    "sg:city":"Reading",
    "sg:classifiers":[
        {
            "category":"Building & Trades",
            "subcategory":"Construction",
            "type":"Services"
        }
    ],
    "sg:phone":"+1 610 779 1053",
    "sg:postcode":"19606",
    "sg:province":"PA",
    "sg:tags":[
        "house",
        "nonresidential"
    ],
    "wof:name":"Berks Commercial Renovations",
    "wof:placetype":"venue"
},
  "geometry": {"coordinates":[-75.891566,40.328721],"type":"Point"}
}