{
  "type": "Feature",
  "properties": {
    "addr:full":"301 Jacksonville Rd Hatboro PA 19040",
    "addr:housenumber":"301",
    "addr:postcode":"19040",
    "addr:street":"Jacksonville Rd",
    "iso:country":"US",
    "sg:address":"301 Jacksonville Rd",
    "sg:city":"Hatboro",
    "sg:classifiers":[
        {
            "category":"Autos & Motor Vehicles",
            "subcategory":"Motorcycle Sales",
            "type":"Retail Goods"
        }
    ],
    "sg:phone":"+1 215 674 4340",
    "sg:postcode":"19040",
    "sg:province":"PA",
    "sg:tags":[
        "scooter"
    ],
    "wof:name":"Tricked Out Cycles & Customs-T",
    "wof:placetype":"venue"
},
  "geometry": {"coordinates":[-75.098009,40.181727],"type":"Point"}
}