{
  "type": "Feature",
  "properties": {
    "iso:country":"US",
    "sg:address":"1340 Tatamy Rd",
    "sg:city":"Easton",
    "sg:classifiers":[
        {
            "category":"Freight",
            "type":"Transportation"
        }
    ],
    "sg:phone":"+1 610 250 6547",
    "sg:postcode":"18045",
    "sg:province":"PA",
    "sg:tags":[
        "commercial",
        "storage"
    ],
    "wof:name":"A Two Z Self Storage",
    "wof:placetype":"venue"
},
  "geometry": {"coordinates":[-75.256351,40.721524],"type":"Point"}
}