{
  "type": "Feature",
  "properties": {
    "iso:country":"US",
    "sg:address":"1000 Paxton St",
    "sg:city":"Harrisburg",
    "sg:classifiers":[
        {
            "category":"Professional",
            "type":"Services"
        }
    ],
    "sg:phone":"+1 717 233 3673",
    "sg:postcode":"17104",
    "sg:province":"PA",
    "sg:tags":[
        "establishment"
    ],
    "wof:name":"Francis-Fords Inc",
    "wof:placetype":"venue"
},
  "geometry": {"coordinates":[-76.872005,40.255712],"type":"Point"}
}