{
  "type": "Feature",
  "properties": {
    "addr:full":"313 Oak St Emporium PA 15834",
    "addr:housenumber":"313",
    "addr:postcode":"15834",
    "addr:street":"Oak St",
    "iso:country":"US",
    "sg:address":"313 Oak St",
    "sg:city":"Emporium",
    "sg:classifiers":[
        {
            "category":"Retail",
            "subcategory":"Repair Shop",
            "type":"Services"
        }
    ],
    "sg:phone":"+1 814 486 3811",
    "sg:postcode":"15834",
    "sg:province":"PA",
    "sg:tags":[
        "appliance"
    ],
    "wof:name":"Bob's Appliance Svc",
    "wof:placetype":"venue"
},
  "geometry": {"coordinates":[-78.223167,41.511962],"type":"Point"}
}