{
  "type": "Feature",
  "properties": {
    "iso:country":"US",
    "sg:address":"909 Bloom St",
    "sg:city":"Danville",
    "sg:classifiers":[
        {
            "category":"Restaurant",
            "type":"Food & Drink"
        }
    ],
    "sg:menulink":"http://www.allmenus.com/pa/mahoning/133577-subway/menu/",
    "sg:phone":"+1 570 271 0556",
    "sg:postcode":"17821",
    "sg:province":"PA",
    "sg:tags":[
        "american",
        "sandwich"
    ],
    "wof:name":"Subway",
    "wof:placetype":"venue"
},
  "geometry": {"coordinates":[-76.600334,40.965616],"type":"Point"}
}