{
  "type": "Feature",
  "properties": {
    "addr:full":"322 E Main St Leola PA 17540",
    "addr:housenumber":"322",
    "addr:postcode":"17540",
    "addr:street":"E Main St",
    "iso:country":"US",
    "sg:address":"322 E Main St",
    "sg:city":"Leola",
    "sg:classifiers":[
        {
            "category":"Manufacturing",
            "subcategory":"Tools & Machinery",
            "type":"Manufacturing & Wholesale Goods"
        }
    ],
    "sg:phone":"+1 717 656 4878",
    "sg:postcode":"17540",
    "sg:province":"PA",
    "sg:tags":[
        "equipment",
        "hydraulic"
    ],
    "sg:website":"www.beilerhydraulics.com",
    "wof:name":"Beiler Hydraulics",
    "wof:placetype":"venue"
},
  "geometry": {"coordinates":[-76.15033200000001,40.092688],"type":"Point"}
}