{
  "type": "Feature",
  "properties": {
    "iso:country":"US",
    "sg:address":"2208 N 2nd St",
    "sg:city":"Philadelphia",
    "sg:classifiers":[
        {
            "category":"Autos & Motor Vehicles",
            "subcategory":"Automobile Sales",
            "type":"Retail Goods"
        }
    ],
    "sg:phone":"+1 215 426 5052",
    "sg:postcode":"19133",
    "sg:province":"PA",
    "sg:tags":[
        "new",
        "car"
    ],
    "wof:name":"Jag Auto Sales",
    "wof:placetype":"venue"
},
  "geometry": {"coordinates":[-75.13648499999999,39.983879],"type":"Point"}
}