{
  "type": "Feature",
  "properties": {
    "addr:full":"1200 Eberts Ln York PA 17402",
    "addr:housenumber":"1200",
    "addr:postcode":"17402",
    "addr:street":"Eberts Ln",
    "iso:country":"US",
    "sg:address":"1200 Eberts Ln",
    "sg:city":"York",
    "sg:classifiers":[
        {
            "category":"Building & Trades",
            "subcategory":"Landscaping Services",
            "type":"Services"
        }
    ],
    "sg:phone":"+1 717 755 1504",
    "sg:postcode":"17402",
    "sg:province":"PA",
    "sg:tags":[
        "tree"
    ],
    "wof:name":"Hays Tree Farm",
    "wof:placetype":"venue"
},
  "geometry": {"coordinates":[-76.70608199999999,39.979598],"type":"Point"}
}