{
  "type": "Feature",
  "properties": {
    "iso:country":"US",
    "sg:address":"226 W Rittenhouse Sq",
    "sg:city":"Philadelphia",
    "sg:classifiers":[
        {
            "category":"Arts & Performance",
            "subcategory":"Art Gallery",
            "type":"Entertainment"
        }
    ],
    "sg:phone":"+1 215 735 0160",
    "sg:postcode":"19103",
    "sg:province":"PA",
    "sg:tags":[
        "fine",
        "artist"
    ],
    "wof:name":"Joseph C Duffy",
    "wof:placetype":"venue"
},
  "geometry": {"coordinates":[-75.17298599999999,39.949217],"type":"Point"}
}