{
  "type": "Feature",
  "properties": {
    "addr:full":"2331 Market St Camp Hill PA 17011",
    "addr:housenumber":"2331",
    "addr:postcode":"17011",
    "addr:street":"Market St",
    "iso:country":"US",
    "sg:address":"2331 Market St",
    "sg:city":"Camp Hill",
    "sg:classifiers":[
        {
            "category":"Professional",
            "subcategory":"Accounting & Tax Preparation",
            "type":"Services"
        }
    ],
    "sg:phone":"+1 717 763 0888",
    "sg:postcode":"17011",
    "sg:province":"PA",
    "sg:tags":[
        "accountant"
    ],
    "sg:website":"www.kernandcompany.com",
    "wof:name":"Kern & Company PC",
    "wof:placetype":"venue"
},
  "geometry": {"coordinates":[-76.924004,40.240398],"type":"Point"}
}