{
  "type": "Feature",
  "properties": {
    "addr:full":"980 Bridle Path Rd Bethlehem PA 18017",
    "addr:housenumber":"980",
    "addr:postcode":"18017",
    "addr:street":"Bridle Path Rd",
    "iso:country":"US",
    "sg:address":"980 Bridle Path Rd",
    "sg:city":"Bethlehem",
    "sg:classifiers":[
        {
            "category":"Organizations",
            "subcategory":"Religious Organization",
            "type":"Services"
        }
    ],
    "sg:phone":"+1 610 867 0402",
    "sg:postcode":"18017",
    "sg:province":"PA",
    "sg:tags":[
        "church"
    ],
    "wof:name":"St Nicholas Russian Church",
    "wof:placetype":"venue"
},
  "geometry": {"coordinates":[-75.395512,40.648886],"type":"Point"}
}