{
  "type": "Feature",
  "properties": {
    "iso:country":"US",
    "sg:address":"14 Mc Govern Ave",
    "sg:city":"Lancaster",
    "sg:classifiers":[
        {
            "category":"Professional",
            "subcategory":"Business Services",
            "type":"Services"
        }
    ],
    "sg:phone":"+1 717 509 0100",
    "sg:postcode":"17602",
    "sg:province":"PA",
    "sg:tags":[
        "paging",
        "answering"
    ],
    "sg:website":"www.ctsi.com",
    "wof:name":"Commonwealth Telephone Co",
    "wof:placetype":"venue"
},
  "geometry": {"coordinates":[-76.307999,40.053591],"type":"Point"}
}