{
  "type": "Feature",
  "properties": {
    "iso:country":"US",
    "sg:address":"81 Colonial Park Mall",
    "sg:city":"Harrisburg",
    "sg:classifiers":[
        {
            "category":"Shopping",
            "subcategory":"Department Store",
            "type":"Retail Goods"
        }
    ],
    "sg:phone":"+1 717 540 4222",
    "sg:postcode":"17109",
    "sg:province":"PA",
    "sg:website":"www.boscovs.com",
    "wof:name":"Boscov's Department Store",
    "wof:placetype":"venue"
},
  "geometry": {"coordinates":[-76.816113,40.301618],"type":"Point"}
}