{
  "type": "Feature",
  "properties": {
    "iso:country":"US",
    "sg:address":"480 Lancaster Ave Ste 15",
    "sg:city":"Malvern",
    "sg:classifiers":[
        {
            "category":"Health Services",
            "subcategory":"Chiropractor",
            "type":"Services"
        }
    ],
    "sg:phone":"+1 610 640 4440",
    "sg:postcode":"19355",
    "sg:province":"PA",
    "sg:tags":[
        "chiropractic"
    ],
    "wof:name":"Bond Chiropractic Center Inc",
    "wof:placetype":"venue"
},
  "geometry": {"coordinates":[-75.563213,40.036835],"type":"Point"}
}