{
  "type": "Feature",
  "properties": {
    "addr:full":"4027 Butler St Pittsburgh PA 15201",
    "addr:housenumber":"4027",
    "addr:postcode":"15201",
    "addr:street":"Butler St",
    "iso:country":"US",
    "sg:address":"4027 Butler St",
    "sg:city":"Pittsburgh",
    "sg:classifiers":[
        {
            "category":"Professional",
            "type":"Services"
        }
    ],
    "sg:phone":"+1 412 765 1043",
    "sg:postcode":"15201",
    "sg:province":"PA",
    "sg:tags":[
        "establishment"
    ],
    "wof:name":"Robert A Casey & Assoc",
    "wof:placetype":"venue"
},
  "geometry": {"coordinates":[-79.961657,40.469291],"type":"Point"}
}