{
  "type": "Feature",
  "properties": {
    "iso:country":"US",
    "sg:address":"70 Senn Dr",
    "sg:city":"Uwchland",
    "sg:classifiers":[
        {
            "category":"Social Services",
            "subcategory":"Child Care",
            "type":"Services"
        }
    ],
    "sg:phone":"+1 610 458 5428",
    "sg:postcode":"19425",
    "sg:province":"PA",
    "sg:website":"www.brightlightelc.com",
    "wof:name":"Bright Light Early Learning",
    "wof:placetype":"venue"
},
  "geometry": {"coordinates":[-75.679221,40.077664],"type":"Point"}
}