{
  "type": "Feature",
  "properties": {
    "iso:country":"US",
    "sg:address":"510 W Hamilton St",
    "sg:city":"Allentown",
    "sg:classifiers":[
        {
            "category":"Restaurant",
            "type":"Food & Drink"
        }
    ],
    "sg:menulink":"http://www.allmenus.com/pa/allentown/133616-subway/menu/",
    "sg:phone":"+1 610 435 5385",
    "sg:postcode":"18101",
    "sg:province":"PA",
    "sg:tags":[
        "american",
        "sandwich"
    ],
    "wof:name":"Subway",
    "wof:placetype":"venue"
},
  "geometry": {"coordinates":[-75.468403,40.603097],"type":"Point"}
}