{
  "type": "Feature",
  "properties": {
    "iso:country":"US",
    "sg:address":"1201 Monterey St",
    "sg:city":"Pittsburgh",
    "sg:classifiers":[
        {
            "category":"Professional",
            "subcategory":"Management & Consulting",
            "type":"Services"
        }
    ],
    "sg:phone":"+1 412 231 1037",
    "sg:postcode":"15212",
    "sg:province":"PA",
    "sg:tags":[
        "business",
        "architectural",
        "mfg"
    ],
    "wof:name":"Safe Escapeways",
    "wof:placetype":"venue"
},
  "geometry": {"coordinates":[-80.013244,40.456278],"type":"Point"}
}