{
  "type": "Feature",
  "properties": {
    "addr:full":"28 Fraley St Kane PA 16735",
    "addr:housenumber":"28",
    "addr:postcode":"16735",
    "addr:street":"Fraley St",
    "iso:country":"US",
    "sg:address":"28 Fraley St",
    "sg:city":"Kane",
    "sg:classifiers":[
        {
            "category":"Shopping",
            "subcategory":"Used Merchandise",
            "type":"Retail Goods"
        }
    ],
    "sg:phone":"+1 814 837 1235",
    "sg:postcode":"16735",
    "sg:province":"PA",
    "wof:name":"Salvation Army Thrift Store",
    "wof:placetype":"venue"
},
  "geometry": {"coordinates":[-78.811009,41.653266],"type":"Point"}
}