{
  "type": "Feature",
  "properties": {
    "iso:country":"US",
    "sg:address":"105 Braunlich Dr",
    "sg:city":"Pittsburgh",
    "sg:classifiers":[
        {
            "category":"Health Services",
            "subcategory":"Doctor",
            "type":"Services"
        }
    ],
    "sg:phone":"+1 412 366 6369",
    "sg:postcode":"15237",
    "sg:province":"PA",
    "sg:tags":[
        "dentist"
    ],
    "wof:name":"Gregory W Miller DDS",
    "wof:placetype":"venue"
},
  "geometry": {"coordinates":[-80.00395,40.520912],"type":"Point"}
}