{
  "type": "Feature",
  "properties": {
    "iso:country":"US",
    "sg:address":"1106 Chester Ave",
    "sg:city":"Lansdowne",
    "sg:classifiers":[
        {
            "category":"Restaurant",
            "type":"Food & Drink"
        }
    ],
    "sg:phone":"+1 610 394 8840",
    "sg:postcode":"19050",
    "sg:province":"PA",
    "sg:tags":[
        "pizza"
    ],
    "wof:name":"Universal Pizza",
    "wof:placetype":"venue"
},
  "geometry": {"coordinates":[-75.24654200000001,39.926382],"type":"Point"}
}