{
  "type": "Feature",
  "properties": {
    "iso:country":"US",
    "sg:address":"3619 Bird Dr",
    "sg:city":"Erie",
    "sg:classifiers":[
        {
            "category":"Freight",
            "type":"Transportation"
        }
    ],
    "sg:phone":"+1   ",
    "sg:postcode":"16510",
    "sg:province":"PA",
    "sg:tags":[
        "operator",
        "trucking"
    ],
    "wof:name":"Schneider National Inc",
    "wof:placetype":"venue"
},
  "geometry": {"coordinates":[-80.01053,42.125072],"type":"Point"}
}