{
  "type": "Feature",
  "properties": {
    "iso:country":"US",
    "sg:address":"740 Sandy St",
    "sg:city":"Norristown",
    "sg:classifiers":[
        {
            "category":"Organizations",
            "subcategory":"Labor Organization",
            "type":"Services"
        }
    ],
    "sg:phone":"+1 610 279 4036",
    "sg:postcode":"19401",
    "sg:province":"PA",
    "wof:name":"Laborers International Union",
    "wof:placetype":"venue"
},
  "geometry": {"coordinates":[-75.32727300000001,40.11235],"type":"Point"}
}