{
  "type": "Feature",
  "properties": {
    "iso:country":"US",
    "sg:address":"1117 Logan Blvd",
    "sg:city":"Altoona",
    "sg:classifiers":[
        {
            "category":"Health Services",
            "subcategory":"Chiropractor",
            "type":"Services"
        }
    ],
    "sg:phone":"+1 814 944 8483",
    "sg:postcode":"16602",
    "sg:province":"PA",
    "wof:name":"Logan Valley Chiropractic",
    "wof:placetype":"venue"
},
  "geometry": {"coordinates":[-78.40095599999999,40.473872],"type":"Point"}
}