{
  "type": "Feature",
  "properties": {
    "addr:full":"315 E 16th St Erie PA 16503",
    "addr:housenumber":"315",
    "addr:postcode":"16503",
    "addr:street":"E 16Th St",
    "iso:country":"US",
    "sg:address":"315 E 16th St",
    "sg:city":"Erie",
    "sg:classifiers":[
        {
            "category":"Government",
            "subcategory":"Office",
            "type":"Public Place"
        }
    ],
    "sg:phone":"+1   ",
    "sg:postcode":"16503",
    "sg:province":"PA",
    "sg:tags":[
        "city",
        "housing",
        "authority"
    ],
    "wof:name":"Lake City Dwellings",
    "wof:placetype":"venue"
},
  "geometry": {"coordinates":[-80.070678,42.123064],"type":"Point"}
}