{
  "type": "Feature",
  "properties": {
    "iso:country":"US",
    "sg:address":"870 W Main St",
    "sg:city":"New Holland",
    "sg:classifiers":[
        {
            "category":"Restaurant",
            "type":"Food & Drink"
        }
    ],
    "sg:phone":"+1   ",
    "sg:postcode":"17557",
    "sg:province":"PA",
    "sg:tags":[
        "eating"
    ],
    "wof:name":"New Holland Twin Kiss Drive In",
    "wof:placetype":"venue"
},
  "geometry": {"coordinates":[-76.12002099999999,40.092214],"type":"Point"}
}