{
  "type": "Feature",
  "properties": {
    "iso:country":"US",
    "sg:address":"3 Chestnut Rdg",
    "sg:city":"Tannersville",
    "sg:classifiers":[
        {
            "category":"Professional",
            "subcategory":"Management & Consulting",
            "type":"Services"
        }
    ],
    "sg:phone":"+1 570 629 4720",
    "sg:postcode":"18372",
    "sg:province":"PA",
    "sg:tags":[
        "consultant"
    ],
    "wof:name":"Resources Means Funding",
    "wof:placetype":"venue"
},
  "geometry": {"coordinates":[-75.343462,41.060584],"type":"Point"}
}