{
  "type": "Feature",
  "properties": {
    "iso:country":"US",
    "sg:address":"13 Beaver St",
    "sg:city":"Langhorne",
    "sg:classifiers":[
        {
            "category":"Professional",
            "type":"Services"
        }
    ],
    "sg:phone":"+1 215 757 6877",
    "sg:postcode":"19047",
    "sg:province":"PA",
    "sg:tags":[
        "caterer"
    ],
    "sg:website":"www.atasteoftexascatering.com",
    "wof:name":"A Taste of Texas Catering",
    "wof:placetype":"venue"
},
  "geometry": {"coordinates":[-74.914387,40.14373],"type":"Point"}
}