{
  "type": "Feature",
  "properties": {
    "addr:full":"2314 E Carson St Pittsburgh PA 15203",
    "addr:housenumber":"2314",
    "addr:postcode":"15203",
    "addr:street":"E Carson St",
    "iso:country":"US",
    "sg:address":"2314 E Carson St",
    "sg:city":"Pittsburgh",
    "sg:classifiers":[
        {
            "category":"Restaurant",
            "type":"Food & Drink"
        }
    ],
    "sg:phone":"+1   ",
    "sg:postcode":"15203",
    "sg:province":"PA",
    "sg:tags":[
        "eating"
    ],
    "wof:name":"Cupka Cafe II Inc",
    "wof:placetype":"venue"
},
  "geometry": {"coordinates":[-79.97139799999999,40.42815],"type":"Point"}
}