{
  "type": "Feature",
  "properties": {
    "addr:full":"306 High St Lemont Furnace PA 15456",
    "addr:housenumber":"306",
    "addr:postcode":"15456",
    "addr:street":"High St",
    "iso:country":"US",
    "sg:address":"306 High St",
    "sg:city":"Lemont Furnace",
    "sg:classifiers":[
        {
            "category":"Utilities",
            "subcategory":"Refuse",
            "type":"Services"
        }
    ],
    "sg:phone":"+1 724 438 2602",
    "sg:postcode":"15456",
    "sg:province":"PA",
    "sg:tags":[
        "garbage",
        "collection"
    ],
    "wof:name":"Marilungo's Disposal Svc",
    "wof:placetype":"venue"
},
  "geometry": {"coordinates":[-79.667393,39.91414],"type":"Point"}
}