{
  "type": "Feature",
  "properties": {
    "addr:full":"1701 Cowpath Rd Hatfield PA 19440",
    "addr:housenumber":"1701",
    "addr:postcode":"19440",
    "addr:street":"Cowpath Rd",
    "iso:country":"US",
    "sg:address":"1701 Cowpath Rd",
    "sg:city":"Hatfield",
    "sg:classifiers":[
        {
            "category":"Professional",
            "subcategory":"Business Services",
            "type":"Services"
        }
    ],
    "sg:phone":"+1 215 362 8428",
    "sg:postcode":"19440",
    "sg:province":"PA",
    "sg:tags":[
        "auctioneer"
    ],
    "wof:name":"Hatfield Auto Auction",
    "wof:placetype":"venue"
},
  "geometry": {"coordinates":[-75.290037,40.27399],"type":"Point"}
}