{
  "type": "Feature",
  "properties": {
    "iso:country":"US",
    "sg:address":"15028 Hwy 98",
    "sg:city":"Meadville",
    "sg:classifiers":[
        {
            "category":"Organizations",
            "subcategory":"Religious Organization",
            "type":"Services"
        }
    ],
    "sg:phone":"+1 814 337 2480",
    "sg:postcode":"16335",
    "sg:province":"PA",
    "sg:tags":[
        "church"
    ],
    "wof:name":"Denny Chapel",
    "wof:placetype":"venue"
},
  "geometry": {"coordinates":[-80.227192,41.673558],"type":"Point"}
}