{
  "type": "Feature",
  "properties": {
    "iso:country":"US",
    "sg:address":"60 Colony Sq",
    "sg:city":"Pittsburgh",
    "sg:classifiers":[
        {
            "category":"Health Services",
            "subcategory":"Hospital",
            "type":"Services"
        }
    ],
    "sg:phone":"+1   ",
    "sg:postcode":"15239",
    "sg:province":"PA",
    "sg:tags":[
        "psychiatric"
    ],
    "wof:name":"Allegheny East M H/M R Center",
    "wof:placetype":"venue"
},
  "geometry": {"coordinates":[-79.710829,40.462944],"type":"Point"}
}