{
  "type": "Feature",
  "properties": {
    "iso:country":"US",
    "sg:address":"901 S College St",
    "sg:city":"Myerstown",
    "sg:classifiers":[
        {
            "category":"Food & Beverages",
            "subcategory":"Groceries & Convenience Stores",
            "type":"Retail Goods"
        }
    ],
    "sg:phone":"+1 717 866 7193",
    "sg:postcode":"17067",
    "sg:province":"PA",
    "sg:tags":[
        "grocer"
    ],
    "wof:name":"Horning's Roadside Market",
    "wof:placetype":"venue"
},
  "geometry": {"coordinates":[-76.30954300000001,40.357119],"type":"Point"}
}