{
  "type": "Feature",
  "properties": {
    "addr:full":"520 2nd Street Pike Southampton PA 18966",
    "addr:housenumber":"520",
    "addr:postcode":"18966",
    "addr:street":"2Nd Street Pike",
    "iso:country":"US",
    "sg:address":"520 2nd Street Pike",
    "sg:city":"Southampton",
    "sg:classifiers":[
        {
            "category":"Shopping",
            "subcategory":"Clothing, Apparel, & Fashions",
            "type":"Retail Goods"
        }
    ],
    "sg:phone":"+1 215 322 4895",
    "sg:postcode":"18966",
    "sg:province":"PA",
    "wof:name":"Laoma Boutique",
    "wof:placetype":"venue"
},
  "geometry": {"coordinates":[-75.044693,40.171622],"type":"Point"}
}