{
  "type": "Feature",
  "properties": {
    "iso:country":"US",
    "sg:address":"2030 Bellevue Rd",
    "sg:city":"Harrisburg",
    "sg:classifiers":[
        {
            "category":"Shopping",
            "subcategory":"Catalog Store",
            "type":"Retail Goods"
        }
    ],
    "sg:phone":"+1   ",
    "sg:postcode":"17104",
    "sg:province":"PA",
    "sg:tags":[
        "mail",
        "house"
    ],
    "wof:name":"Mark Stephen",
    "wof:placetype":"venue"
},
  "geometry": {"coordinates":[-76.85623,40.267675],"type":"Point"}
}