{
  "type": "Feature",
  "properties": {
    "addr:full":"2023 Ferguson Valley Rd Mc Veytown PA 17051",
    "addr:housenumber":"2023",
    "addr:postcode":"17051",
    "addr:street":"Ferguson Valley Rd",
    "iso:country":"US",
    "sg:address":"2023 Ferguson Valley Rd",
    "sg:city":"Mc Veytown",
    "sg:classifiers":[
        {
            "category":"Building & Trades",
            "subcategory":"Landscaping Services",
            "type":"Services"
        }
    ],
    "sg:phone":"+1   ",
    "sg:postcode":"17051",
    "sg:province":"PA",
    "wof:name":"Clemens Landscaping",
    "wof:placetype":"venue"
},
  "geometry": {"coordinates":[-77.814029,40.424245],"type":"Point"}
}