{
  "type": "Feature",
  "properties": {
    "addr:full":"608 Pocono Blvd Mount Pocono PA 18344",
    "addr:housenumber":"608",
    "addr:postcode":"18344",
    "addr:street":"Pocono Blvd",
    "iso:country":"US",
    "sg:address":"608 Pocono Blvd",
    "sg:city":"Mount Pocono",
    "sg:classifiers":[
        {
            "category":"Restaurant",
            "type":"Food & Drink"
        }
    ],
    "sg:phone":"+1   ",
    "sg:postcode":"18344",
    "sg:province":"PA",
    "sg:tags":[
        "eating"
    ],
    "wof:name":"Burkes Tavern and Restaurant",
    "wof:placetype":"venue"
},
  "geometry": {"coordinates":[-75.36143800000001,41.128789],"type":"Point"}
}