{
  "type": "Feature",
  "properties": {
    "iso:country":"US",
    "sg:address":"60 Sykes St",
    "sg:city":"Sykesville",
    "sg:classifiers":[
        {
            "category":"Bars & Pubs",
            "type":"Food & Drink"
        }
    ],
    "sg:phone":"+1 814 894 2421",
    "sg:postcode":"15865",
    "sg:province":"PA",
    "sg:tags":[
        "drinking",
        "eating"
    ],
    "wof:name":"Rhododendron Bar",
    "wof:placetype":"venue"
},
  "geometry": {"coordinates":[-78.81559,41.055633],"type":"Point"}
}