{
  "type": "Feature",
  "properties": {
    "iso:country":"US",
    "sg:address":"108 Grove Ln",
    "sg:city":"Freeport",
    "sg:classifiers":[
        {
            "category":"Organizations",
            "subcategory":"Religious Organization",
            "type":"Services"
        }
    ],
    "sg:phone":"+1 724 295 9293",
    "sg:postcode":"16260",
    "sg:province":"PA",
    "sg:tags":[
        "church"
    ],
    "wof:name":"Spader Grove United Prsbytrn",
    "wof:placetype":"venue"
},
  "geometry": {"coordinates":[-79.22599200000001,41.4015],"type":"Point"}
}