{
  "type": "Feature",
  "properties": {
    "iso:country":"US",
    "sg:address":"60 Fredonia Rd",
    "sg:city":"Greenville",
    "sg:classifiers":[
        {
            "category":"Organizations",
            "subcategory":"Non-profit Organization",
            "type":"Services"
        }
    ],
    "sg:phone":"+1 724 588 2844",
    "sg:postcode":"16125",
    "sg:province":"PA",
    "sg:tags":[
        "human"
    ],
    "wof:name":"Greenville Community Family",
    "wof:placetype":"venue"
},
  "geometry": {"coordinates":[-80.362286,41.392973],"type":"Point"}
}