{
  "type": "Feature",
  "properties": {
    "iso:country":"US",
    "sg:address":"1001 Trinity Cir",
    "sg:city":"Washington",
    "sg:classifiers":[
        {
            "category":"Restaurant",
            "type":"Food & Drink"
        }
    ],
    "sg:menulink":"http://www.allmenus.com/pa/south-strabane/206870-mcdonalds/menu/",
    "sg:phone":"+1 724 222 9115",
    "sg:postcode":"15301",
    "sg:province":"PA",
    "sg:tags":[
        "burger",
        "american"
    ],
    "wof:name":"McDonald's",
    "wof:placetype":"venue"
},
  "geometry": {"coordinates":[-80.22234,40.185545],"type":"Point"}
}