{
  "type": "Feature",
  "properties": {
    "addr:full":"1 Spruce St East Stroudsburg PA 18301",
    "addr:housenumber":"1",
    "addr:postcode":"18301",
    "addr:street":"Spruce St",
    "iso:country":"US",
    "sg:address":"1 Spruce St",
    "sg:city":"East Stroudsburg",
    "sg:classifiers":[
        {
            "category":"Retail",
            "subcategory":"Repair Shop",
            "type":"Services"
        }
    ],
    "sg:phone":"+1   ",
    "sg:postcode":"18301",
    "sg:province":"PA",
    "sg:tags":[
        "installs",
        "conditioner",
        "refrigerator",
        "air"
    ],
    "wof:name":"Marvins Refrigeration Inc",
    "wof:placetype":"venue"
},
  "geometry": {"coordinates":[-75.185298,41.011113],"type":"Point"}
}