{
  "type": "Feature",
  "properties": {
    "iso:country":"US",
    "sg:address":"4916 Chestnut St",
    "sg:city":"Philadelphia",
    "sg:classifiers":[
        {
            "category":"Real Estate",
            "subcategory":"Developer",
            "type":"Services"
        }
    ],
    "sg:phone":"+1 215 748 1468",
    "sg:postcode":"19139",
    "sg:province":"PA",
    "wof:name":"Plumwood Developers Inc",
    "wof:placetype":"venue"
},
  "geometry": {"coordinates":[-75.219583,39.957797],"type":"Point"}
}