{
  "type": "Feature",
  "properties": {
    "iso:country":"US",
    "sg:address":"5750 Centre Ave",
    "sg:city":"Pittsburgh",
    "sg:classifiers":[
        {
            "category":"Professional",
            "subcategory":"Testing Lab",
            "type":"Services"
        }
    ],
    "sg:phone":"+1   ",
    "sg:postcode":"15232",
    "sg:province":"PA",
    "sg:tags":[
        "laboratory"
    ],
    "wof:name":"D3 Radiation Planning",
    "wof:placetype":"venue"
},
  "geometry": {"coordinates":[-79.930504,40.458191],"type":"Point"}
}