{
  "type": "Feature",
  "properties": {
    "addr:full":"250 Bethlehem Pike Colmar PA 18915",
    "addr:housenumber":"250",
    "addr:postcode":"18915",
    "addr:street":"Bethlehem Pike",
    "iso:country":"US",
    "sg:address":"250 Bethlehem Pike",
    "sg:city":"Colmar",
    "sg:classifiers":[
        {
            "category":"Freight",
            "type":"Transportation"
        }
    ],
    "sg:phone":"+1   ",
    "sg:postcode":"18915",
    "sg:province":"PA",
    "sg:tags":[
        "warehousing"
    ],
    "wof:name":"Colmar Moving & Storage Center",
    "wof:placetype":"venue"
},
  "geometry": {"coordinates":[-75.25874899999999,40.274001],"type":"Point"}
}