{
  "type": "Feature",
  "properties": {
    "iso:country":"US",
    "sg:address":"3055 Black Gap Rd",
    "sg:city":"Chambersburg",
    "sg:classifiers":[
        {
            "category":"Shopping",
            "subcategory":"Clothing, Apparel, & Fashions",
            "type":"Retail Goods"
        }
    ],
    "sg:phone":"+1 717 261 0077",
    "sg:postcode":"17201",
    "sg:province":"PA",
    "wof:name":"Pacific Swimwear",
    "wof:placetype":"venue"
},
  "geometry": {"coordinates":[-77.579775,39.966453],"type":"Point"}
}