{
  "type": "Feature",
  "properties": {
    "iso:country":"US",
    "sg:address":"200 Vernon Rd",
    "sg:city":"Greenville",
    "sg:classifiers":[
        {
            "category":"Autos & Motor Vehicles",
            "subcategory":"Automobile Sales",
            "type":"Retail Goods"
        }
    ],
    "sg:phone":"+1   ",
    "sg:postcode":"16125",
    "sg:province":"PA",
    "sg:tags":[
        "car",
        "used",
        "dealer"
    ],
    "wof:name":"Fast Eddies Wheels-N-Deals LLC",
    "wof:placetype":"venue"
},
  "geometry": {"coordinates":[-80.408823,41.401537],"type":"Point"}
}