{
  "type": "Feature",
  "properties": {
    "addr:full":"324 Hoffman Rd Somerset PA 15501",
    "addr:housenumber":"324",
    "addr:postcode":"15501",
    "addr:street":"Hoffman Rd",
    "iso:country":"US",
    "sg:address":"324 Hoffman Rd",
    "sg:city":"Somerset",
    "sg:classifiers":[
        {
            "category":"Farming",
            "subcategory":"Dairy Farm",
            "type":"Manufacturing & Wholesale Goods"
        }
    ],
    "sg:phone":"+1   ",
    "sg:postcode":"15501",
    "sg:province":"PA",
    "wof:name":"Hoffman Farms",
    "wof:placetype":"venue"
},
  "geometry": {"coordinates":[-79.12789100000001,40.075149],"type":"Point"}
}