{
  "type": "Feature",
  "properties": {
    "iso:country":"US",
    "sg:address":"5345 Allegheny Rd",
    "sg:city":"Manns Choice",
    "sg:classifiers":[
        {
            "category":"Autos & Motor Vehicles",
            "subcategory":"Automobile Sales",
            "type":"Retail Goods"
        }
    ],
    "sg:phone":"+1 814 733 0059",
    "sg:postcode":"15550",
    "sg:province":"PA",
    "sg:tags":[
        "sport",
        "trailer",
        "utility"
    ],
    "wof:name":"T & S Trailer Sales",
    "wof:placetype":"venue"
},
  "geometry": {"coordinates":[-78.61288500000001,40.010359],"type":"Point"}
}