{
  "type": "Feature",
  "properties": {
    "iso:country":"US",
    "sg:address":"1579 Walker Rd",
    "sg:city":"Chambersburg",
    "sg:classifiers":[
        {
            "category":"Retail",
            "subcategory":"Storage",
            "type":"Services"
        }
    ],
    "sg:phone":"+1 717 267 7034",
    "sg:postcode":"17202",
    "sg:province":"PA",
    "sg:tags":[
        "household",
        "commercial"
    ],
    "wof:name":"Bender Boys Inc",
    "wof:placetype":"venue"
},
  "geometry": {"coordinates":[-77.59626,39.941787],"type":"Point"}
}