{
  "type": "Feature",
  "properties": {
    "iso:country":"US",
    "sg:address":"10055 Oakridge Dr",
    "sg:city":"Wexford",
    "sg:classifiers":[
        {
            "category":"Professional",
            "subcategory":"Lawyer & Legal Services",
            "type":"Services"
        }
    ],
    "sg:phone":"+1 724 933 5455",
    "sg:postcode":"15090",
    "sg:province":"PA",
    "sg:tags":[
        "attorney"
    ],
    "wof:name":"William E Brennan",
    "wof:placetype":"venue"
},
  "geometry": {"coordinates":[-80.052791,40.594961],"type":"Point"}
}