{
  "type": "Feature",
  "properties": {
    "iso:country":"US",
    "sg:address":"1050 Weiser St",
    "sg:city":"Reading",
    "sg:classifiers":[
        {
            "category":"Wholesale",
            "subcategory":"Durable Goods & Equipment",
            "type":"Manufacturing & Wholesale Goods"
        }
    ],
    "sg:phone":"+1 610 372 5077",
    "sg:postcode":"19601",
    "sg:province":"PA",
    "sg:tags":[
        "fire",
        "extinguisher"
    ],
    "wof:name":"Mid-Atlantic Fire & Air",
    "wof:placetype":"venue"
},
  "geometry": {"coordinates":[-75.937748,40.350719],"type":"Point"}
}