{
  "type": "Feature",
  "properties": {
    "iso:country":"US",
    "sg:address":"4163 Business 220",
    "sg:city":"Bedford",
    "sg:phone":"+1 814 623 7784",
    "sg:postcode":"15522",
    "sg:province":"PA",
    "wof:name":"220 Truck Repair",
    "wof:placetype":"venue"
},
  "geometry": {"coordinates":[-78.508429,40.046481],"type":"Point"}
}