{
  "type": "Feature",
  "properties": {
    "addr:full":"2404 Wilmington Rd New Castle PA 16105",
    "addr:housenumber":"2404",
    "addr:postcode":"16105",
    "addr:street":"Wilmington Rd New",
    "iso:country":"US",
    "sg:address":"2404 Wilmington Rd",
    "sg:city":"New Castle",
    "sg:classifiers":[
        {
            "category":"Shopping",
            "subcategory":"Clothing, Apparel, & Fashions",
            "type":"Retail Goods"
        }
    ],
    "sg:phone":"+1   ",
    "sg:postcode":"16105",
    "sg:province":"PA",
    "wof:name":"Garys Place",
    "wof:placetype":"venue"
},
  "geometry": {"coordinates":[-80.35401299999999,41.028134],"type":"Point"}
}