{
  "type": "Feature",
  "properties": {
    "addr:full":"3294 Red Lion Rd Philadelphia PA 19114",
    "addr:housenumber":"3294",
    "addr:postcode":"19114",
    "addr:street":"Red Lion Rd",
    "iso:country":"US",
    "sg:address":"3294 Red Lion Rd",
    "sg:city":"Philadelphia",
    "sg:classifiers":[
        {
            "category":"Personal",
            "type":"Services"
        }
    ],
    "sg:phone":"+1   ",
    "sg:postcode":"19114",
    "sg:province":"PA",
    "wof:name":"Golden Glow Sun Studio",
    "wof:placetype":"venue"
},
  "geometry": {"coordinates":[-74.994348,40.08168],"type":"Point"}
}