{
  "type": "Feature",
  "properties": {
    "iso:country":"US",
    "sg:address":"4204 Greenridge Rd",
    "sg:city":"Pittsburgh",
    "sg:classifiers":[
        {
            "category":"Building & Trades",
            "subcategory":"Construction",
            "type":"Services"
        }
    ],
    "sg:phone":"+1 412 563 1551",
    "sg:postcode":"15234",
    "sg:province":"PA",
    "sg:tags":[
        "contractor"
    ],
    "wof:name":"Flacone Brothers Construction Company",
    "wof:placetype":"venue"
},
  "geometry": {"coordinates":[-80.035787,40.358769],"type":"Point"}
}