{
  "type": "Feature",
  "properties": {
    "iso:country":"US",
    "sg:address":"145 Schneider Dr",
    "sg:city":"Lebanon",
    "sg:classifiers":[
        {
            "category":"Local Transit",
            "type":"Transportation"
        }
    ],
    "sg:phone":"+1 717 272 0161",
    "sg:postcode":"17046",
    "sg:province":"PA",
    "sg:tags":[
        "bus",
        "line"
    ],
    "wof:name":"Capitol Trailways",
    "wof:placetype":"venue"
},
  "geometry": {"coordinates":[-76.415629,40.342845],"type":"Point"}
}