{
  "type": "Feature",
  "properties": {
    "addr:full":"9571 Lincoln Hwy Bedford PA 15522",
    "addr:housenumber":"9571",
    "addr:postcode":"15522",
    "addr:street":"Lincoln Hwy",
    "iso:country":"US",
    "sg:address":"9571 Lincoln Hwy",
    "sg:city":"Bedford",
    "sg:classifiers":[
        {
            "category":"Food & Beverages",
            "subcategory":"Fruits & Vegetables",
            "type":"Retail Goods"
        }
    ],
    "sg:phone":"+1 814 623 5642",
    "sg:postcode":"15522",
    "sg:province":"PA",
    "sg:tags":[
        "produce"
    ],
    "wof:name":"Mile Level Country Market",
    "wof:placetype":"venue"
},
  "geometry": {"coordinates":[-78.46208,40.02051],"type":"Point"}
}