{
  "type": "Feature",
  "properties": {
    "iso:country":"US",
    "sg:address":"817 N Chester Rd",
    "sg:city":"West Chester",
    "sg:classifiers":[
        {
            "category":"Manufacturing",
            "subcategory":"Electronics",
            "type":"Manufacturing & Wholesale Goods"
        }
    ],
    "sg:phone":"+1   ",
    "sg:postcode":"19380",
    "sg:province":"PA",
    "sg:tags":[
        "electronic",
        "component",
        "d",
        "mfg"
    ],
    "wof:name":"Esco",
    "wof:placetype":"venue"
},
  "geometry": {"coordinates":[-75.544252,39.994591],"type":"Point"}
}