{
  "type": "Feature",
  "properties": {
    "iso:country":"US",
    "sg:address":"45 Buck Rd",
    "sg:city":"Southampton",
    "sg:classifiers":[
        {
            "category":"Local Transit",
            "type":"Transportation"
        }
    ],
    "sg:phone":"+1 215 355 3233",
    "sg:postcode":"18966",
    "sg:province":"PA",
    "sg:tags":[
        "limousine"
    ],
    "sg:website":"www.aristalimousine.com",
    "wof:name":"Arista Limousine Inc",
    "wof:placetype":"venue"
},
  "geometry": {"coordinates":[-74.98693299999999,40.170556],"type":"Point"}
}