{
  "type": "Feature",
  "properties": {
    "addr:full":"66 Rotterdam Rd W Southampton PA 18966",
    "addr:housenumber":"66",
    "addr:postcode":"18966",
    "addr:street":"Rotterdam Rd W",
    "iso:country":"US",
    "sg:address":"66 Rotterdam Rd W",
    "sg:city":"Southampton",
    "sg:classifiers":[
        {
            "category":"Organizations",
            "subcategory":"Community Association",
            "type":"Services"
        }
    ],
    "sg:phone":"+1   ",
    "sg:postcode":"18966",
    "sg:province":"PA",
    "wof:name":"Gurnsey Hall Condo Assoc",
    "wof:placetype":"venue"
},
  "geometry": {"coordinates":[-74.979529,40.202237],"type":"Point"}
}