{
  "type": "Feature",
  "properties": {
    "iso:country":"US",
    "sg:address":"1611 Gingrich Rd",
    "sg:city":"Middletown",
    "sg:classifiers":[
        {
            "category":"Farming",
            "subcategory":"Farm",
            "type":"Manufacturing & Wholesale Goods"
        }
    ],
    "sg:phone":"+1   ",
    "sg:postcode":"17057",
    "sg:province":"PA",
    "sg:tags":[
        "crop",
        "general"
    ],
    "wof:name":"Dale L Brandt",
    "wof:placetype":"venue"
},
  "geometry": {"coordinates":[-76.70916200000001,40.163933],"type":"Point"}
}