{
  "type": "Feature",
  "properties": {
    "addr:full":"290 S Columbus Ave Littlestown PA 17340",
    "addr:housenumber":"290",
    "addr:postcode":"17340",
    "addr:street":"S Columbus Ave",
    "iso:country":"US",
    "sg:address":"290 S Columbus Ave",
    "sg:city":"Littlestown",
    "sg:classifiers":[
        {
            "category":"Banks & Credit Unions",
            "subcategory":"Bank",
            "type":"Services"
        }
    ],
    "sg:phone":"+1 717 359 9591",
    "sg:postcode":"17340",
    "sg:province":"PA",
    "sg:tags":[
        "loan",
        "mortgage",
        "real estate"
    ],
    "wof:name":"Professional Mortgage Cnsltnts",
    "wof:placetype":"venue"
},
  "geometry": {"coordinates":[-77.092636,39.737428],"type":"Point"}
}