{
  "type": "Feature",
  "properties": {
    "iso:country":"US",
    "sg:address":"1506 E Lincoln Hwy",
    "sg:city":"Langhorne",
    "sg:classifiers":[
        {
            "category":"Retail",
            "subcategory":"Auto Repair",
            "type":"Services"
        }
    ],
    "sg:phone":"+1 215 757 7080",
    "sg:postcode":"19047",
    "sg:province":"PA",
    "sg:tags":[
        "body",
        "automobile",
        "painting",
        "repairing"
    ],
    "wof:name":"Ebert Collision Specialis",
    "wof:placetype":"venue"
},
  "geometry": {"coordinates":[-74.892658,40.170727],"type":"Point"}
}