{
  "type": "Feature",
  "properties": {
    "iso:country":"US",
    "sg:address":"608 Crooked Creek Rd",
    "sg:city":"Gettysburg",
    "sg:classifiers":[
        {
            "category":"Farming",
            "subcategory":"Dairy Farm",
            "type":"Manufacturing & Wholesale Goods"
        }
    ],
    "sg:phone":"+1   ",
    "sg:postcode":"17325",
    "sg:province":"PA",
    "wof:name":"Leo Redding",
    "wof:placetype":"venue"
},
  "geometry": {"coordinates":[-77.287887,39.874793],"type":"Point"}
}