{
  "type": "Feature",
  "properties": {
    "iso:country":"US",
    "sg:address":"422 Elfort Dr",
    "sg:city":"Pittsburgh",
    "sg:classifiers":[
        {
            "category":"Autos & Motor Vehicles",
            "subcategory":"Auto Supplies",
            "type":"Retail Goods"
        }
    ],
    "sg:phone":"+1   ",
    "sg:postcode":"15235",
    "sg:province":"PA",
    "wof:name":"Smooth Ride Inc",
    "wof:placetype":"venue"
},
  "geometry": {"coordinates":[-79.79834,40.493367],"type":"Point"}
}