{
  "type": "Feature",
  "properties": {
    "iso:country":"US",
    "sg:address":"2555 Washington Rd",
    "sg:city":"Pittsburgh",
    "sg:classifiers":[
        {
            "category":"Shopping",
            "subcategory":"Jewelry",
            "type":"Retail Goods"
        }
    ],
    "sg:phone":"+1   ",
    "sg:postcode":"15241",
    "sg:province":"PA",
    "sg:tags":[
        "stone",
        "metal",
        "precious"
    ],
    "wof:name":"Maureen OBrien & Associates",
    "wof:placetype":"venue"
},
  "geometry": {"coordinates":[-80.089629,40.314016],"type":"Point"}
}