{
  "type": "Feature",
  "properties": {
    "iso:country":"US",
    "sg:address":"4801 Greenway Ave",
    "sg:city":"Philadelphia",
    "sg:classifiers":[
        {
            "category":"Retail",
            "subcategory":"Auto Repair",
            "type":"Services"
        }
    ],
    "sg:phone":"+1 215 726 5300",
    "sg:postcode":"19143",
    "sg:province":"PA",
    "sg:tags":[
        "body",
        "shop",
        "painting",
        "automobile"
    ],
    "wof:name":"Ludlow Auto Repair Shop",
    "wof:placetype":"venue"
},
  "geometry": {"coordinates":[-75.21260100000001,39.942501],"type":"Point"}
}