{
  "type": "Feature",
  "properties": {
    "iso:country":"US",
    "sg:address":"1030 E Willow Grove Ave",
    "sg:city":"Glenside",
    "sg:classifiers":[
        {
            "category":"Health Services",
            "subcategory":"Doctor",
            "type":"Services"
        }
    ],
    "sg:phone":"+1   ",
    "sg:postcode":"19038",
    "sg:province":"PA",
    "wof:name":"Gary L Stevens DDS",
    "wof:placetype":"venue"
},
  "geometry": {"coordinates":[-75.188192,40.082692],"type":"Point"}
}