{
  "type": "Feature",
  "properties": {
    "addr:full":"60 Musante Ave Warren PA 16365",
    "addr:housenumber":"60",
    "addr:postcode":"16365",
    "addr:street":"Musante Ave",
    "iso:country":"US",
    "sg:address":"60 Musante Ave",
    "sg:city":"Warren",
    "sg:classifiers":[
        {
            "category":"Utilities",
            "subcategory":"Natural Gas",
            "type":"Services"
        }
    ],
    "sg:phone":"+1   ",
    "sg:postcode":"16365",
    "sg:province":"PA",
    "wof:name":"Columbia",
    "wof:placetype":"venue"
},
  "geometry": {"coordinates":[-79.15128,41.832779],"type":"Point"}
}