{
  "type": "Feature",
  "properties": {
    "addr:full":"198 W Liberty St Lancaster PA 17603",
    "addr:housenumber":"198",
    "addr:postcode":"17603",
    "addr:street":"W Liberty St",
    "iso:country":"US",
    "sg:address":"198 W Liberty St",
    "sg:city":"Lancaster",
    "sg:classifiers":[
        {
            "category":"Wholesale",
            "subcategory":"Farm Supplies",
            "type":"Manufacturing & Wholesale Goods"
        }
    ],
    "sg:phone":"+1 717 394 2676",
    "sg:postcode":"17603",
    "sg:province":"PA",
    "sg:tags":[
        "leaf",
        "tobacco"
    ],
    "sg:website":"www.universalleaf.com",
    "wof:name":"Lancaster Leaf Tobacco Co",
    "wof:placetype":"venue"
},
  "geometry": {"coordinates":[-76.31107,40.051871],"type":"Point"}
}