{
  "type": "Feature",
  "properties": {
    "addr:full":"114 W Venango St Mercer PA 16137",
    "addr:housenumber":"114",
    "addr:postcode":"16137",
    "addr:street":"W Venango St",
    "iso:country":"US",
    "sg:address":"114 W Venango St",
    "sg:city":"Mercer",
    "sg:classifiers":[
        {
            "category":"Travel",
            "subcategory":"Campground",
            "type":"Entertainment"
        }
    ],
    "sg:phone":"+1 724 662 4481",
    "sg:postcode":"16137",
    "sg:province":"PA",
    "wof:name":"Camping Assn Of Presbyteries",
    "wof:placetype":"venue"
},
  "geometry": {"coordinates":[-80.239835,41.228574],"type":"Point"}
}