{
  "type": "Feature",
  "properties": {
    "iso:country":"US",
    "sg:address":"366 Middletown Rd",
    "sg:city":"Hummelstown",
    "sg:classifiers":[
        {
            "category":"Restaurant",
            "type":"Food & Drink"
        }
    ],
    "sg:phone":"+1   ",
    "sg:postcode":"17036",
    "sg:province":"PA",
    "sg:tags":[
        "eating"
    ],
    "wof:name":"Willowood Cafe & Creamery",
    "wof:placetype":"venue"
},
  "geometry": {"coordinates":[-76.709053,40.255273],"type":"Point"}
}