{
  "type": "Feature",
  "properties": {
    "iso:country":"US",
    "sg:address":"415 Moon Clinton Rd",
    "sg:city":"Coraopolis",
    "sg:classifiers":[
        {
            "category":"Professional",
            "subcategory":"Engineering",
            "type":"Services"
        }
    ],
    "sg:phone":"+1 412 262 5400",
    "sg:postcode":"15108",
    "sg:province":"PA",
    "sg:tags":[
        "engineer"
    ],
    "sg:website":"www.lrkimball.com",
    "wof:name":"L Robert Kimball & Assoc Inc",
    "wof:placetype":"venue"
},
  "geometry": {"coordinates":[-80.238496,40.508959],"type":"Point"}
}