{
  "type": "Feature",
  "properties": {
    "iso:country":"US",
    "sg:address":"408 Doylestown Pike",
    "sg:city":"Montgomeryville",
    "sg:classifiers":[
        {
            "category":"Food & Beverages",
            "subcategory":"Liquor & Beverages",
            "type":"Retail Goods"
        }
    ],
    "sg:phone":"+1   ",
    "sg:postcode":"18944",
    "sg:province":"PA",
    "sg:tags":[
        "distributor",
        "beer",
        "soda"
    ],
    "wof:name":"Deons Cases & Kegs",
    "wof:placetype":"venue"
},
  "geometry": {"coordinates":[-75.217426,40.380977],"type":"Point"}
}