{
  "type": "Feature",
  "properties": {
    "iso:country":"US",
    "sg:address":"5342 Pleasant Ridge Rd",
    "sg:city":"Needmore",
    "sg:classifiers":[
        {
            "category":"Real Estate",
            "subcategory":"Real Estate Operator",
            "type":"Services"
        }
    ],
    "sg:phone":"+1   ",
    "sg:postcode":"17238",
    "sg:province":"PA",
    "sg:tags":[
        "property",
        "lessor"
    ],
    "wof:name":"Ross Deshong",
    "wof:placetype":"venue"
},
  "geometry": {"coordinates":[-78.11233,39.924721],"type":"Point"}
}