{
  "type": "Feature",
  "properties": {
    "addr:full":"30 Dustys Ln Glen Rock PA 17327",
    "addr:housenumber":"30",
    "addr:postcode":"17327",
    "addr:street":"Dustys Ln",
    "iso:country":"US",
    "sg:address":"30 Dustys Ln",
    "sg:city":"Glen Rock",
    "sg:classifiers":[
        {
            "category":"Real Estate",
            "subcategory":"Real Estate Agent",
            "type":"Services"
        }
    ],
    "sg:phone":"+1 717 235 7755",
    "sg:postcode":"17327",
    "sg:province":"PA",
    "wof:name":"Dick Pace Realtor",
    "wof:placetype":"venue"
},
  "geometry": {"coordinates":[-76.729343,39.785636],"type":"Point"}
}