{
  "type": "Feature",
  "properties": {
    "iso:country":"US",
    "sg:address":"207 E Carroll St",
    "sg:city":"Carrolltown",
    "sg:classifiers":[
        {
            "category":"Home & Garden",
            "subcategory":"Carpets & Floor Coverings",
            "type":"Retail Goods"
        }
    ],
    "sg:phone":"+1 814 344 8689",
    "sg:postcode":"15722",
    "sg:province":"PA",
    "sg:tags":[
        "dealer",
        "rug"
    ],
    "sg:website":"www.carpetone.com",
    "wof:name":"P J Stevens Carpet One",
    "wof:placetype":"venue"
},
  "geometry": {"coordinates":[-78.70501899999999,40.602806],"type":"Point"}
}