{
  "type": "Feature",
  "properties": {
    "addr:full":"2141 Cross St Philadelphia PA 19146",
    "addr:housenumber":"2141",
    "addr:postcode":"19146",
    "addr:street":"Cross St",
    "iso:country":"US",
    "sg:address":"2141 Cross St",
    "sg:city":"Philadelphia",
    "sg:classifiers":[
        {
            "category":"Organizations",
            "subcategory":"Religious Organization",
            "type":"Services"
        }
    ],
    "sg:phone":"+1 215 271 5304",
    "sg:postcode":"19146",
    "sg:province":"PA",
    "sg:tags":[
        "church"
    ],
    "wof:name":"Holy Trinity Church",
    "wof:placetype":"venue"
},
  "geometry": {"coordinates":[-75.18081599999999,39.932583],"type":"Point"}
}