{
  "type": "Feature",
  "properties": {
    "addr:full":"2 Willow Ct Harrisburg PA 17110",
    "addr:housenumber":"2",
    "addr:postcode":"17110",
    "addr:street":"Willow Ct",
    "iso:country":"US",
    "sg:address":"2 Willow Ct",
    "sg:city":"Harrisburg",
    "sg:classifiers":[
        {
            "category":"Government",
            "subcategory":"Office",
            "type":"Public Place"
        }
    ],
    "sg:phone":"+1   ",
    "sg:postcode":"17110",
    "sg:province":"PA",
    "sg:tags":[
        "program",
        "administrative"
    ],
    "wof:name":"Bureau Data & Claims",
    "wof:placetype":"venue"
},
  "geometry": {"coordinates":[-76.879139,40.313857],"type":"Point"}
}