{
  "type": "Feature",
  "properties": {
    "iso:country":"US",
    "sg:address":"209 Spring St",
    "sg:city":"Sayre",
    "sg:classifiers":[
        {
            "category":"Autos & Motor Vehicles",
            "subcategory":"Boat Sales",
            "type":"Retail Goods"
        }
    ],
    "sg:phone":"+1 570 888 2255",
    "sg:postcode":"18840",
    "sg:province":"PA",
    "sg:tags":[
        "recreational",
        "sales",
        "dealer"
    ],
    "sg:website":"www.joesmarine.com",
    "wof:name":"Joe's Marine Inc",
    "wof:placetype":"venue"
},
  "geometry": {"coordinates":[-76.522131,41.995736],"type":"Point"}
}