{
  "type": "Feature",
  "properties": {
    "iso:country":"US",
    "sg:address":"599 Black Ave",
    "sg:city":"Chambersburg",
    "sg:classifiers":[
        {
            "category":"Professional",
            "subcategory":"Engineering",
            "type":"Services"
        },
        {
            "category":"Wholesale",
            "subcategory":"Auto Parts",
            "type":"Manufacturing & Wholesale Goods"
        }
    ],
    "sg:phone":"+1 717 263 7455",
    "sg:postcode":"17201",
    "sg:province":"PA",
    "sg:tags":[
        "wheel",
        "repair",
        "frame",
        "contractor",
        "chassis",
        "general",
        "alignment"
    ],
    "wof:name":"Gaumer's Chassis Engineering",
    "wof:placetype":"venue"
},
  "geometry": {"coordinates":[-77.66448099999999,39.927612],"type":"Point"}
}