{
  "type": "Feature",
  "properties": {
    "iso:country":"US",
    "sg:address":"519 Judith Dr",
    "sg:city":"Pittsburgh",
    "sg:classifiers":[
        {
            "category":"Professional",
            "type":"Services"
        }
    ],
    "sg:phone":"+1 412 650 8891",
    "sg:postcode":"15236",
    "sg:province":"PA",
    "wof:name":"Northwestern Human Svc",
    "wof:placetype":"venue"
},
  "geometry": {"coordinates":[-80.00185500000001,40.344897],"type":"Point"}
}