{
  "type": "Feature",
  "properties": {
    "iso:country":"US",
    "sg:address":"737 E Main St",
    "sg:city":"Reynoldsville",
    "sg:classifiers":[
        {
            "category":"Social Services",
            "subcategory":"Adult Care",
            "type":"Services"
        }
    ],
    "sg:phone":"+1 814 653 2222",
    "sg:postcode":"15851",
    "sg:province":"PA",
    "sg:tags":[
        "home",
        "convalescent",
        "nursing",
        "residential"
    ],
    "wof:name":"Morning Glow Manor",
    "wof:placetype":"venue"
},
  "geometry": {"coordinates":[-78.88479100000001,41.092171],"type":"Point"}
}