{
  "type": "Feature",
  "properties": {
    "iso:country":"US",
    "sg:address":"55 E Cherry Ln",
    "sg:city":"Souderton",
    "sg:classifiers":[
        {
            "category":"Professional",
            "subcategory":"Advertising",
            "type":"Services"
        }
    ],
    "sg:phone":"+1 215 723 9200",
    "sg:postcode":"18964",
    "sg:province":"PA",
    "sg:tags":[
        "agency",
        "specialty"
    ],
    "sg:website":"http://www.ccmcreative.com",
    "wof:name":"C C M Creative",
    "wof:placetype":"venue"
},
  "geometry": {"coordinates":[-75.31047,40.309931],"type":"Point"}
}