{
  "type": "Feature",
  "properties": {
    "addr:full":"2050 E High St Pottstown PA 19464",
    "addr:housenumber":"2050",
    "addr:postcode":"19464",
    "addr:street":"E High St",
    "iso:country":"US",
    "sg:address":"2050 E High St",
    "sg:city":"Pottstown",
    "sg:classifiers":[
        {
            "category":"Professional",
            "subcategory":"Lawyer & Legal Services",
            "type":"Services"
        }
    ],
    "sg:phone":"+1 610 970 4961",
    "sg:postcode":"19464",
    "sg:province":"PA",
    "sg:tags":[
        "attorney",
        "law",
        "family",
        "duo",
        "divorce",
        "criminal",
        "dwi"
    ],
    "sg:website":"http://www.garner-bauer.com",
    "wof:name":"Garner & Bauer Attorneys at Law",
    "wof:placetype":"venue"
},
  "geometry": {"coordinates":[-75.6067,40.244085],"type":"Point"}
}