{
  "type": "Feature",
  "properties": {
    "addr:full":"701 Horsham Rd Horsham PA 19044",
    "addr:housenumber":"701",
    "addr:postcode":"19044",
    "addr:street":"Horsham Rd",
    "iso:country":"US",
    "sg:address":"701 Horsham Rd",
    "sg:city":"Horsham",
    "sg:classifiers":[
        {
            "category":"Insurance",
            "subcategory":"Insurance Agent",
            "type":"Services"
        }
    ],
    "sg:phone":"+1 215 957 6300",
    "sg:postcode":"19044",
    "sg:province":"PA",
    "wof:name":"Lawrence J Kelly",
    "wof:placetype":"venue"
},
  "geometry": {"coordinates":[-75.152936,40.192467],"type":"Point"}
}