{
  "type": "Feature",
  "properties": {
    "iso:country":"US",
    "sg:address":"421 Manor Rd",
    "sg:city":"Harrison City",
    "sg:classifiers":[
        {
            "category":"Professional",
            "subcategory":"Business Services",
            "type":"Services"
        }
    ],
    "sg:phone":"+1   ",
    "sg:postcode":"15626",
    "sg:province":"PA",
    "wof:name":"Dennis M Kupcheck Gen Contr",
    "wof:placetype":"venue"
},
  "geometry": {"coordinates":[-79.586371,40.405103],"type":"Point"}
}