{
  "type": "Feature",
  "properties": {
    "addr:full":"Montgomery St and Thompson St Philadelphia PA 19125",
    "addr:postcode":"19125",
    "addr:street":"Montgomery St And Thompson St",
    "iso:country":"US",
    "sg:address":"Montgomery St and Thompson St",
    "sg:city":"Philadelphia",
    "sg:classifiers":[
        {
            "category":"Restaurant",
            "type":"Food & Drink"
        }
    ],
    "sg:postcode":"19125",
    "sg:province":"PA",
    "wof:name":"Mandy's Deli",
    "wof:placetype":"venue"
},
  "geometry": {"coordinates":[-75.12790699999999,39.97282],"type":"Point"}
}