{
  "type": "Feature",
  "properties": {
    "addr:full":"5020 Ogontz Ave Philadelphia PA 19141",
    "addr:housenumber":"5020",
    "addr:postcode":"19141",
    "addr:street":"Ogontz Ave",
    "iso:country":"US",
    "sg:address":"5020 Ogontz Ave",
    "sg:city":"Philadelphia",
    "sg:classifiers":[
        {
            "category":"Shopping",
            "type":"Retail Goods"
        }
    ],
    "sg:phone":"+1   ",
    "sg:postcode":"19141",
    "sg:province":"PA",
    "sg:tags":[
        "merchandise"
    ],
    "wof:name":"Afrikah World Art",
    "wof:placetype":"venue"
},
  "geometry": {"coordinates":[-75.153289,40.030131],"type":"Point"}
}