{
  "type": "Feature",
  "properties": {
    "addr:full":"1133 Glenn St Philadelphia PA 19115",
    "addr:housenumber":"1133",
    "addr:postcode":"19115",
    "addr:street":"Glenn St",
    "iso:country":"US",
    "sg:address":"1133 Glenn St",
    "sg:city":"Philadelphia",
    "sg:classifiers":[
        {
            "category":"Professional",
            "subcategory":"Lawyer & Legal Services",
            "type":"Services"
        }
    ],
    "sg:phone":"+1 215 464 1023",
    "sg:postcode":"19115",
    "sg:province":"PA",
    "sg:tags":[
        "arbitration"
    ],
    "wof:name":"Francis J Domzalski",
    "wof:placetype":"venue"
},
  "geometry": {"coordinates":[-75.035839,40.1017],"type":"Point"}
}