{
  "type": "Feature",
  "properties": {
    "iso:country":"US",
    "sg:address":"1194 Elberta Ave",
    "sg:city":"Bensalem",
    "sg:classifiers":[
        {
            "category":"Building & Trades",
            "subcategory":"Electrical",
            "type":"Services"
        }
    ],
    "sg:phone":"+1 215 633 9232",
    "sg:postcode":"19020",
    "sg:province":"PA",
    "sg:tags":[
        "electrical",
        "contractor"
    ],
    "wof:name":"Daniel Frantz Electric",
    "wof:placetype":"venue"
},
  "geometry": {"coordinates":[-74.916678,40.111271],"type":"Point"}
}