{
  "type": "Feature",
  "properties": {
    "iso:country":"US",
    "sg:address":"3362 Millers Run Rd",
    "sg:city":"Cecil",
    "sg:classifiers":[
        {
            "category":"Professional",
            "subcategory":"Employment Agencies",
            "type":"Services"
        }
    ],
    "sg:phone":"+1   ",
    "sg:postcode":"15321",
    "sg:province":"PA",
    "wof:name":"Specialty Personnel Services",
    "wof:placetype":"venue"
},
  "geometry": {"coordinates":[-80.201171,40.319859],"type":"Point"}
}