{
  "type": "Feature",
  "properties": {
    "iso:country":"US",
    "sg:address":"1986 White Cloud Rd",
    "sg:city":"Leechburg",
    "sg:classifiers":[
        {
            "category":"Structure",
            "subcategory":"Office Building",
            "type":"Public Place"
        }
    ],
    "sg:phone":"+1 724 845 3262",
    "sg:postcode":"15656",
    "sg:province":"PA",
    "sg:tags":[
        "park"
    ],
    "wof:name":"Full Moon Properties",
    "wof:placetype":"venue"
},
  "geometry": {"coordinates":[-79.66269699999999,40.624119],"type":"Point"}
}