{
  "type": "Feature",
  "properties": {
    "iso:country":"US",
    "sg:address":"1 Manor Dr",
    "sg:city":"Chalfont",
    "sg:classifiers":[
        {
            "category":"Social Services",
            "subcategory":"Child Care",
            "type":"Services"
        },
        {
            "category":"Education",
            "subcategory":"Preschool",
            "type":"Public Place"
        },
        {
            "category":"Education",
            "subcategory":"School",
            "type":"Public Place"
        }
    ],
    "sg:phone":"+1 215 997 9085",
    "sg:postcode":"18914",
    "sg:province":"PA",
    "sg:tags":[
        "elementary",
        "day"
    ],
    "wof:name":"Carefree Learning Center",
    "wof:placetype":"venue"
},
  "geometry": {"coordinates":[-75.21839900000001,40.280201],"type":"Point"}
}