{
  "type": "Feature",
  "properties": {
    "iso:country":"US",
    "sg:address":"1714 N Mascher St",
    "sg:city":"Philadelphia",
    "sg:classifiers":[
        {
            "category":"Shopping",
            "subcategory":"Jewelry",
            "type":"Retail Goods"
        }
    ],
    "sg:phone":"+1   ",
    "sg:postcode":"19122",
    "sg:province":"PA",
    "wof:name":"Amazulu On Eighth",
    "wof:placetype":"venue"
},
  "geometry": {"coordinates":[-75.13613700000001,39.976228],"type":"Point"}
}