{
  "type": "Feature",
  "properties": {
    "addr:full":"2500 Belmont Ave Philadelphia PA 19131",
    "addr:housenumber":"2500",
    "addr:postcode":"19131",
    "addr:street":"Belmont Ave",
    "iso:country":"US",
    "sg:address":"2500 Belmont Ave",
    "sg:city":"Philadelphia",
    "sg:classifiers":[
        {
            "category":"Real Estate",
            "subcategory":"Real Estate Operator",
            "type":"Services"
        }
    ],
    "sg:phone":"+1 215 477 6363",
    "sg:postcode":"19131",
    "sg:province":"PA",
    "sg:tags":[
        "apartment"
    ],
    "wof:name":"Carlene Apartments",
    "wof:placetype":"venue"
},
  "geometry": {"coordinates":[-75.219041,39.997099],"type":"Point"}
}