{
  "type": "Feature",
  "properties": {
    "iso:country":"US",
    "sg:address":"3882 Delta Rd",
    "sg:city":"Airville",
    "sg:classifiers":[
        {
            "category":"Retail",
            "subcategory":"Repair Shop",
            "type":"Services"
        }
    ],
    "sg:phone":"+1   ",
    "sg:postcode":"17302",
    "sg:province":"PA",
    "wof:name":"Marion D S Cnc Services",
    "wof:placetype":"venue"
},
  "geometry": {"coordinates":[-76.393401,39.823366],"type":"Point"}
}