{
  "type": "Feature",
  "properties": {
    "iso:country":"US",
    "sg:address":"1219 Kiester Rd",
    "sg:city":"Slippery Rock",
    "sg:classifiers":[
        {
            "category":"Farming",
            "subcategory":"Livestock Farm",
            "type":"Manufacturing & Wholesale Goods"
        }
    ],
    "sg:phone":"+1   ",
    "sg:postcode":"16057",
    "sg:province":"PA",
    "sg:tags":[
        "equine"
    ],
    "wof:name":"Abbott Farm",
    "wof:placetype":"venue"
},
  "geometry": {"coordinates":[-79.94679600000001,41.042387],"type":"Point"}
}