{
  "type": "Feature",
  "properties": {
    "iso:country":"US",
    "sg:address":"178 Pleasantview Dr",
    "sg:city":"Midland",
    "sg:classifiers":[
        {
            "category":"School Buses",
            "type":"Transportation"
        }
    ],
    "sg:phone":"+1   ",
    "sg:postcode":"15059",
    "sg:province":"PA",
    "wof:name":"Shank Bus Company Inc",
    "wof:placetype":"venue"
},
  "geometry": {"coordinates":[-80.488998,40.689461],"type":"Point"}
}