{
  "type": "Feature",
  "properties": {
    "iso:country":"US",
    "sg:address":"6634 Chew Ave",
    "sg:city":"Philadelphia",
    "sg:classifiers":[
        {
            "category":"Professional",
            "subcategory":"Accounting & Tax Preparation",
            "type":"Services"
        }
    ],
    "sg:phone":"+1 215 848 5281",
    "sg:postcode":"19119",
    "sg:province":"PA",
    "sg:tags":[
        "return",
        "filing"
    ],
    "wof:name":"Maud Tax Consulting",
    "wof:placetype":"venue"
},
  "geometry": {"coordinates":[-75.17974100000001,40.054649],"type":"Point"}
}