{
  "type": "Feature",
  "properties": {
    "iso:country":"US",
    "sg:address":"436 Todd Farm Rd",
    "sg:city":"Belle Vernon",
    "sg:classifiers":[
        {
            "category":"Building & Trades",
            "subcategory":"Construction",
            "type":"Services"
        }
    ],
    "sg:phone":"+1   ",
    "sg:postcode":"15012",
    "sg:province":"PA",
    "sg:tags":[
        "house"
    ],
    "wof:name":"M&S Contracting & Cabling",
    "wof:placetype":"venue"
},
  "geometry": {"coordinates":[-79.783016,40.13672],"type":"Point"}
}