{
  "type": "Feature",
  "properties": {
    "addr:full":"1465 W Broad St Quakertown PA 18951",
    "addr:housenumber":"1465",
    "addr:postcode":"18951",
    "addr:street":"W Broad St",
    "iso:country":"US",
    "sg:address":"1465 W Broad St",
    "sg:city":"Quakertown",
    "sg:classifiers":[
        {
            "category":"Utilities",
            "subcategory":"Mobile Phone",
            "type":"Services"
        }
    ],
    "sg:phone":"+1   ",
    "sg:postcode":"18951",
    "sg:province":"PA",
    "sg:tags":[
        "communication",
        "radiotelephone"
    ],
    "wof:name":"Cingular Wireless LLC",
    "wof:placetype":"venue"
},
  "geometry": {"coordinates":[-75.35830199999999,40.443725],"type":"Point"}
}