{
  "type": "Feature",
  "properties": {
    "iso:country":"US",
    "sg:address":"272 Shady Ave",
    "sg:city":"Pittsburgh",
    "sg:classifiers":[
        {
            "category":"Real Estate",
            "subcategory":"Real Estate Operator",
            "type":"Services"
        }
    ],
    "sg:phone":"+1 412 661 1151",
    "sg:postcode":"15206",
    "sg:province":"PA",
    "sg:tags":[
        "apartment"
    ],
    "sg:website":"www.franklin-west.com",
    "wof:name":"Franklin West Inc",
    "wof:placetype":"venue"
},
  "geometry": {"coordinates":[-79.922341,40.457969],"type":"Point"}
}