{
  "type": "Feature",
  "properties": {
    "iso:country":"US",
    "sg:address":"1650 Metropolitan St",
    "sg:city":"Pittsburgh",
    "sg:classifiers":[
        {
            "category":"Professional",
            "type":"Services"
        }
    ],
    "sg:phone":"+1 412 258 0060",
    "sg:postcode":"15233",
    "sg:province":"PA",
    "sg:tags":[
        "establishment"
    ],
    "wof:name":"BIDCO",
    "wof:placetype":"venue"
},
  "geometry": {"coordinates":[-80.03156,40.456484],"type":"Point"}
}