{
  "type": "Feature",
  "properties": {
    "iso:country":"US",
    "sg:address":"802 N 10th St Ste Frnt",
    "sg:city":"Allentown",
    "sg:classifiers":[
        {
            "category":"Food & Beverages",
            "subcategory":"Groceries & Convenience Stores",
            "type":"Retail Goods"
        }
    ],
    "sg:phone":"+1 484 664 7769",
    "sg:postcode":"18102",
    "sg:province":"PA",
    "wof:name":"Ali's 10th St Market",
    "wof:placetype":"venue"
},
  "geometry": {"coordinates":[-75.483419,40.611827],"type":"Point"}
}