{
  "type": "Feature",
  "properties": {
    "addr:full":"44 S Pitt St Carlisle PA 17013",
    "addr:housenumber":"44",
    "addr:postcode":"17013",
    "addr:street":"S Pitt St",
    "iso:country":"US",
    "sg:address":"44 S Pitt St",
    "sg:city":"Carlisle",
    "sg:classifiers":[
        {
            "category":"Health Services",
            "subcategory":"Dentist",
            "type":"Services"
        }
    ],
    "sg:phone":"+1 717 249 7373",
    "sg:postcode":"17013",
    "sg:province":"PA",
    "wof:name":"Krajack G Ronald Dntst",
    "wof:placetype":"venue"
},
  "geometry": {"coordinates":[-77.19180299999999,40.2006],"type":"Point"}
}