{
  "type": "Feature",
  "properties": {
    "iso:country":"US",
    "sg:address":"389 Oxford Dr",
    "sg:city":"Bethlehem",
    "sg:classifiers":[
        {
            "category":"Professional",
            "subcategory":"Lawyer & Legal Services",
            "type":"Services"
        }
    ],
    "sg:phone":"+1 610 691 1572",
    "sg:postcode":"18017",
    "sg:province":"PA",
    "wof:name":"Boyer Richd F Atty",
    "wof:placetype":"venue"
},
  "geometry": {"coordinates":[-75.373497,40.661999],"type":"Point"}
}