{
  "type": "Feature",
  "properties": {
    "iso:country":"US",
    "sg:address":"2520 Leechburg Rd",
    "sg:city":"Lower Burrell",
    "sg:classifiers":[
        {
            "category":"Shopping",
            "subcategory":"Gifts & Souvenirs",
            "type":"Retail Goods"
        }
    ],
    "sg:phone":"+1 724 337 4450",
    "sg:postcode":"15068",
    "sg:province":"PA",
    "sg:tags":[
        "shop"
    ],
    "wof:name":"Donna's Gift Baskets",
    "wof:placetype":"venue"
},
  "geometry": {"coordinates":[-79.74660900000001,40.58764],"type":"Point"}
}