{
  "type": "Feature",
  "properties": {
    "iso:country":"US",
    "sg:address":"1227 W Chester Rd",
    "sg:city":"West Chester",
    "sg:classifiers":[
        {
            "category":"Travel",
            "subcategory":"Hotels & Motels",
            "type":"Entertainment"
        }
    ],
    "sg:phone":"+1   ",
    "sg:postcode":"19382",
    "sg:province":"PA",
    "sg:tags":[
        "operation"
    ],
    "wof:name":"Goshen Inn",
    "wof:placetype":"venue"
},
  "geometry": {"coordinates":[-75.547039,39.911179],"type":"Point"}
}