{
  "type": "Feature",
  "properties": {
    "iso:country":"US",
    "sg:address":"45 Lunger Dr",
    "sg:city":"Bloomsburg",
    "sg:classifiers":[
        {
            "category":"Government",
            "subcategory":"Office",
            "type":"Public Place"
        }
    ],
    "sg:phone":"+1 570 387 4250",
    "sg:postcode":"17815",
    "sg:province":"PA",
    "sg:tags":[
        "government-state"
    ],
    "sg:website":"http://www.penndotcrm.org",
    "wof:name":"Maintenance District 3-1 & 3-3",
    "wof:placetype":"venue"
},
  "geometry": {"coordinates":[-76.486519,41.01243],"type":"Point"}
}