{
  "type": "Feature",
  "properties": {
    "iso:country":"US",
    "sg:address":"1456 Barton Dr",
    "sg:city":"Fort Washington",
    "sg:classifiers":[
        {
            "category":"Wholesale",
            "subcategory":"Apparel",
            "type":"Manufacturing & Wholesale Goods"
        }
    ],
    "sg:phone":"+1 215 643 4951",
    "sg:postcode":"19034",
    "sg:province":"PA",
    "sg:tags":[
        "shoes"
    ],
    "wof:name":"Victor A LA Hood Inc",
    "wof:placetype":"venue"
},
  "geometry": {"coordinates":[-75.186425,40.141435],"type":"Point"}
}