{
  "type": "Feature",
  "properties": {
    "iso:country":"US",
    "sg:address":"2005 Market St Ste 1800",
    "sg:city":"Philadelphia",
    "sg:classifiers":[
        {
            "category":"Professional",
            "subcategory":"Lawyer & Legal Services",
            "type":"Services"
        }
    ],
    "sg:phone":"+1 215 851 6700",
    "sg:postcode":"19103",
    "sg:province":"PA",
    "wof:name":"Harkins Cunnigham",
    "wof:placetype":"venue"
},
  "geometry": {"coordinates":[-75.17330200000001,39.953602],"type":"Point"}
}