{
  "type": "Feature",
  "properties": {
    "iso:country":"US",
    "sg:address":"500 Baltimore Pike",
    "sg:city":"Springfield",
    "sg:classifiers":[
        {
            "category":"Shopping",
            "subcategory":"Bicycles & Sporting Goods",
            "type":"Retail Goods"
        }
    ],
    "sg:phone":"+1 610 544 1410",
    "sg:postcode":"19064",
    "sg:province":"PA",
    "wof:name":"C & M Sporting Goods",
    "wof:placetype":"venue"
},
  "geometry": {"coordinates":[-75.324445,39.920297],"type":"Point"}
}