{
  "type": "Feature",
  "properties": {
    "iso:country":"US",
    "sg:address":"735 Church Ln",
    "sg:city":"Yeadon",
    "sg:classifiers":[
        {
            "category":"Banks & Credit Unions",
            "subcategory":"Bank",
            "type":"Services"
        }
    ],
    "sg:phone":"+1 610 284 1212",
    "sg:postcode":"19050",
    "sg:province":"PA",
    "wof:name":"Citizens Bank",
    "wof:placetype":"venue"
},
  "geometry": {"coordinates":[-75.25,39.9333],"type":"Point"}
}