{
  "type": "Feature",
  "properties": {
    "iso:country":"US",
    "sg:address":"1361 Skelp Level Rd",
    "sg:city":"Downingtown",
    "sg:classifiers":[
        {
            "category":"Professional",
            "subcategory":"Computer Services",
            "type":"Services"
        }
    ],
    "sg:phone":"+1   ",
    "sg:postcode":"19335",
    "sg:province":"PA",
    "sg:tags":[
        "related"
    ],
    "wof:name":"Journey Technical Services",
    "wof:placetype":"venue"
},
  "geometry": {"coordinates":[-75.68153700000001,39.99484],"type":"Point"}
}