{
  "type": "Feature",
  "properties": {
    "iso:country":"US",
    "sg:address":"2327 N Van Pelt St",
    "sg:city":"Philadelphia",
    "sg:classifiers":[
        {
            "category":"Utilities",
            "subcategory":"Water",
            "type":"Services"
        }
    ],
    "sg:phone":"+1 215 227 4021",
    "sg:postcode":"19132",
    "sg:province":"PA",
    "sg:tags":[
        "bulk",
        "companies-bottled"
    ],
    "wof:name":"Eric Waters",
    "wof:placetype":"venue"
},
  "geometry": {"coordinates":[-75.167773,39.989828],"type":"Point"}
}