{
  "type": "Feature",
  "properties": {
    "iso:country":"US",
    "sg:address":"600 Grant St",
    "sg:city":"Pittsburgh",
    "sg:classifiers":[
        {
            "category":"Social Services",
            "subcategory":"Child Care",
            "type":"Services"
        },
        {
            "category":"Education",
            "subcategory":"Preschool",
            "type":"Public Place"
        },
        {
            "category":"Education",
            "subcategory":"School",
            "type":"Public Place"
        }
    ],
    "sg:phone":"+1 412 765 3973",
    "sg:postcode":"15219",
    "sg:province":"PA",
    "sg:tags":[
        "elementary",
        "day"
    ],
    "sg:website":"www.kindercare.com/Our-Centers/C...",
    "wof:name":"Downtown Kindercare",
    "wof:placetype":"venue"
},
  "geometry": {"coordinates":[-79.99578,40.440614],"type":"Point"}
}