{
  "type": "Feature",
  "properties": {
    "addr:full":"1507 Saw Mill Run Blvd Pittsburgh PA 15210",
    "addr:housenumber":"1507",
    "addr:postcode":"15210",
    "addr:street":"Saw Mill Run Blvd",
    "iso:country":"US",
    "sg:address":"1507 Saw Mill Run Blvd",
    "sg:city":"Pittsburgh",
    "sg:classifiers":[
        {
            "category":"Autos & Motor Vehicles",
            "subcategory":"Automobile Sales",
            "type":"Retail Goods"
        }
    ],
    "sg:phone":"+1   ",
    "sg:postcode":"15210",
    "sg:province":"PA",
    "sg:tags":[
        "used"
    ],
    "wof:name":"A-1 Auto Mart",
    "wof:placetype":"venue"
},
  "geometry": {"coordinates":[-79.99943399999999,40.397857],"type":"Point"}
}