{
  "type": "Feature",
  "properties": {
    "addr:full":"1904 Broad St Perkasie PA 18944",
    "addr:housenumber":"1904",
    "addr:postcode":"18944",
    "addr:street":"Broad St",
    "iso:country":"US",
    "sg:address":"1904 Broad St",
    "sg:city":"Perkasie",
    "sg:classifiers":[
        {
            "category":"Farming",
            "subcategory":"Livestock Farm",
            "type":"Manufacturing & Wholesale Goods"
        }
    ],
    "sg:phone":"+1   ",
    "sg:postcode":"18944",
    "sg:province":"PA",
    "sg:tags":[
        "specialty",
        "animal"
    ],
    "wof:name":"Quarter Mile Farm",
    "wof:placetype":"venue"
},
  "geometry": {"coordinates":[-75.190703,40.358811],"type":"Point"}
}