{
  "type": "Feature",
  "properties": {
    "addr:full":"1200 Trevanion Ave Pittsburgh PA 15218",
    "addr:housenumber":"1200",
    "addr:postcode":"15218",
    "addr:street":"Trevanion Ave",
    "iso:country":"US",
    "sg:address":"1200 Trevanion Ave",
    "sg:city":"Pittsburgh",
    "sg:classifiers":[
        {
            "category":"Building & Trades",
            "subcategory":"Cleaning & Sanitation",
            "type":"Services"
        }
    ],
    "sg:phone":"+1   ",
    "sg:postcode":"15218",
    "sg:province":"PA",
    "sg:tags":[
        "bu",
        "window",
        "janitorial",
        "house"
    ],
    "wof:name":"George Joe Win Clg & Janitoria",
    "wof:placetype":"venue"
},
  "geometry": {"coordinates":[-79.89735400000001,40.42771],"type":"Point"}
}