{
  "type": "Feature",
  "properties": {
    "iso:country":"US",
    "sg:address":"215 Devonwood Dr",
    "sg:city":"Pittsburgh",
    "sg:classifiers":[
        {
            "category":"Shopping",
            "subcategory":"Hobbies, Toys, & Games",
            "type":"Retail Goods"
        }
    ],
    "sg:phone":"+1   ",
    "sg:postcode":"15241",
    "sg:province":"PA",
    "wof:name":"Kidding Around",
    "wof:placetype":"venue"
},
  "geometry": {"coordinates":[-80.072489,40.341041],"type":"Point"}
}