{
  "type": "Feature",
  "properties": {
    "iso:country":"US",
    "sg:address":"624 E Girard Ave",
    "sg:city":"Philadelphia",
    "sg:classifiers":[
        {
            "category":"Professional",
            "subcategory":"Lawyer & Legal Services",
            "type":"Services"
        }
    ],
    "sg:phone":"+1 215 425 6188",
    "sg:postcode":"19125",
    "sg:province":"PA",
    "sg:tags":[
        "divorce",
        "law",
        "family"
    ],
    "wof:name":"Allied Legal Services PC",
    "wof:placetype":"venue"
},
  "geometry": {"coordinates":[-75.126086,39.971333],"type":"Point"}
}