{
  "type": "Feature",
  "properties": {
    "iso:country":"US",
    "sg:address":"419 Brook Dr",
    "sg:city":"Spring City",
    "sg:classifiers":[
        {
            "category":"Building & Trades",
            "subcategory":"Construction",
            "type":"Services"
        }
    ],
    "sg:phone":"+1   ",
    "sg:postcode":"19475",
    "sg:province":"PA",
    "sg:tags":[
        "house"
    ],
    "wof:name":"Timberline Construction",
    "wof:placetype":"venue"
},
  "geometry": {"coordinates":[-75.548147,40.163127],"type":"Point"}
}