{
  "type": "Feature",
  "properties": {
    "addr:full":"1741 Bower Hill Rd Pittsburgh PA 15243",
    "addr:housenumber":"1741",
    "addr:postcode":"15243",
    "addr:street":"Bower Hill Rd",
    "iso:country":"US",
    "sg:address":"1741 Bower Hill Rd",
    "sg:city":"Pittsburgh",
    "sg:classifiers":[
        {
            "category":"Professional",
            "type":"Services"
        }
    ],
    "sg:phone":"+1   ",
    "sg:postcode":"15243",
    "sg:province":"PA",
    "wof:name":"Nancey Srinivasagam",
    "wof:placetype":"venue"
},
  "geometry": {"coordinates":[-80.08385699999999,40.36907],"type":"Point"}
}