{
  "type": "Feature",
  "properties": {
    "addr:full":"911 W Linden St Allentown PA 18101",
    "addr:housenumber":"911",
    "addr:postcode":"18101",
    "addr:street":"W Linden St",
    "iso:country":"US",
    "sg:address":"911 W Linden St",
    "sg:city":"Allentown",
    "sg:phone":"+1 610 432 3044",
    "sg:postcode":"18101",
    "sg:province":"PA",
    "sg:website":"http://www.familywashday.com",
    "wof:name":"Family Wash Day",
    "wof:placetype":"venue"
},
  "geometry": {"coordinates":[-75.476496,40.6025],"type":"Point"}
}