{
  "type": "Feature",
  "properties": {
    "iso:country":"US",
    "sg:address":"701 N 8th St",
    "sg:city":"Philadelphia",
    "sg:classifiers":[
        {
            "category":"Social Services",
            "type":"Services"
        }
    ],
    "sg:phone":"+1 215 923 4115",
    "sg:postcode":"19123",
    "sg:province":"PA",
    "sg:tags":[
        "organization",
        "welfare"
    ],
    "wof:name":"Friends Neighborhood Guild",
    "wof:placetype":"venue"
},
  "geometry": {"coordinates":[-75.15105200000001,39.965517],"type":"Point"}
}