{
  "type": "Feature",
  "properties": {
    "iso:country":"US",
    "sg:address":"56 E Uwchlan Ave",
    "sg:city":"Exton",
    "sg:classifiers":[
        {
            "category":"Shopping",
            "subcategory":"Computers & Home Electronics",
            "type":"Retail Goods"
        }
    ],
    "sg:phone":"+1 610 873 4200",
    "sg:postcode":"19341",
    "sg:province":"PA",
    "sg:tags":[
        "software"
    ],
    "wof:name":"C/F Software Solutions",
    "wof:placetype":"venue"
},
  "geometry": {"coordinates":[-75.65549799999999,40.058889],"type":"Point"}
}