{
  "type": "Feature",
  "properties": {
    "iso:country":"US",
    "sg:address":"423 N 21st St",
    "sg:city":"Camp Hill",
    "sg:classifiers":[
        {
            "category":"Health Services",
            "subcategory":"Doctor",
            "type":"Services"
        }
    ],
    "sg:phone":"+1 717 975 1801",
    "sg:postcode":"17011",
    "sg:province":"PA",
    "sg:tags":[
        "physician",
        "surgeon"
    ],
    "wof:name":"Siegelbaum Gunder & Lacey Gas",
    "wof:placetype":"venue"
},
  "geometry": {"coordinates":[-76.922758,40.249429],"type":"Point"}
}