{
  "type": "Feature",
  "properties": {
    "addr:full":"850 Rostraver Rd Belle Vernon PA 15012",
    "addr:housenumber":"850",
    "addr:postcode":"15012",
    "addr:street":"Rostraver Rd",
    "iso:country":"US",
    "sg:address":"850 Rostraver Rd",
    "sg:city":"Belle Vernon",
    "sg:classifiers":[
        {
            "category":"Shopping",
            "subcategory":"Shoes",
            "type":"Retail Goods"
        }
    ],
    "sg:phone":"+1 724 929 4634",
    "sg:postcode":"15012",
    "sg:province":"PA",
    "sg:tags":[
        "shoe",
        "store"
    ],
    "wof:name":"Payless Shoe Source",
    "wof:placetype":"venue"
},
  "geometry": {"coordinates":[-79.842727,40.137347],"type":"Point"}
}