{
  "type": "Feature",
  "properties": {
    "addr:full":"10 Union St Oil City PA 16301",
    "addr:housenumber":"10",
    "addr:postcode":"16301",
    "addr:street":"Union St",
    "iso:country":"US",
    "sg:address":"10 Union St",
    "sg:city":"Oil City",
    "sg:classifiers":[
        {
            "category":"Manufacturing",
            "subcategory":"Tools & Machinery",
            "type":"Manufacturing & Wholesale Goods"
        }
    ],
    "sg:phone":"+1 814 676 5210",
    "sg:postcode":"16301",
    "sg:province":"PA",
    "sg:tags":[
        "machine",
        "shop"
    ],
    "wof:name":"S Williams Machining Co",
    "wof:placetype":"venue"
},
  "geometry": {"coordinates":[-79.701767,41.446574],"type":"Point"}
}