{
  "type": "Feature",
  "properties": {
    "iso:country":"US",
    "sg:address":"805 Hiesters Ln",
    "sg:city":"Reading",
    "sg:classifiers":[
        {
            "category":"Shopping",
            "type":"Retail Goods"
        }
    ],
    "sg:phone":"+1 610 929 8443",
    "sg:postcode":"19605",
    "sg:province":"PA",
    "sg:tags":[
        "coin",
        "merchandise",
        "supply"
    ],
    "wof:name":"All U S Coins & More",
    "wof:placetype":"venue"
},
  "geometry": {"coordinates":[-75.92096600000001,40.364819],"type":"Point"}
}