{
  "type": "Feature",
  "properties": {
    "addr:full":"36 Locust St Macungie PA 18062",
    "addr:housenumber":"36",
    "addr:postcode":"18062",
    "addr:street":"Locust St",
    "iso:country":"US",
    "sg:address":"36 Locust St",
    "sg:city":"Macungie",
    "sg:classifiers":[
        {
            "category":"Health Services",
            "subcategory":"Doctor",
            "type":"Services"
        }
    ],
    "sg:phone":"+1   ",
    "sg:postcode":"18062",
    "sg:province":"PA",
    "sg:tags":[
        "osteopathic"
    ],
    "wof:name":"Doggie Do",
    "wof:placetype":"venue"
},
  "geometry": {"coordinates":[-75.556781,40.514723],"type":"Point"}
}