{
  "type": "Feature",
  "properties": {
    "addr:full":"8 Sugar Maple Ln Horsham PA 19044",
    "addr:housenumber":"8",
    "addr:postcode":"19044",
    "addr:street":"Sugar Maple Ln",
    "iso:country":"US",
    "sg:address":"8 Sugar Maple Ln",
    "sg:city":"Horsham",
    "sg:classifiers":[
        {
            "category":"Professional",
            "type":"Services"
        }
    ],
    "sg:phone":"+1   ",
    "sg:postcode":"19044",
    "sg:province":"PA",
    "wof:name":"Warner Fricker Jr",
    "wof:placetype":"venue"
},
  "geometry": {"coordinates":[-75.155001,40.167268],"type":"Point"}
}