{
  "type": "Feature",
  "properties": {
    "iso:country":"US",
    "sg:address":"939 Horsham Rd",
    "sg:city":"Montgomeryville",
    "sg:classifiers":[
        {
            "category":"Health Services",
            "subcategory":"Chiropractor",
            "type":"Services"
        }
    ],
    "sg:phone":"+1 215 368 3331",
    "sg:postcode":"19446",
    "sg:province":"PA",
    "wof:name":"Bassion Chiropractic Ctr",
    "wof:placetype":"venue"
},
  "geometry": {"coordinates":[-75.23258800000001,40.240373],"type":"Point"}
}