{
  "type": "Feature",
  "properties": {
    "addr:full":"252 W Swamp Rd Doylestown PA 18901",
    "addr:housenumber":"252",
    "addr:postcode":"18901",
    "addr:street":"W Swamp Rd",
    "iso:country":"US",
    "sg:address":"252 W Swamp Rd",
    "sg:city":"Doylestown",
    "sg:classifiers":[
        {
            "category":"Health Services",
            "subcategory":"Doctor",
            "type":"Services"
        }
    ],
    "sg:phone":"+1 215 348 1706",
    "sg:postcode":"18901",
    "sg:province":"PA",
    "sg:tags":[
        "practice",
        "family"
    ],
    "sg:website":"www.centralbuckschamber.org",
    "wof:name":"Wassel Antoinette MD",
    "wof:placetype":"venue"
},
  "geometry": {"coordinates":[-75.137398,40.333],"type":"Point"}
}