{
  "type": "Feature",
  "properties": {
    "iso:country":"US",
    "sg:address":"3750 Hamilton Blvd",
    "sg:city":"Allentown",
    "sg:classifiers":[
        {
            "category":"Restaurant",
            "type":"Food & Drink"
        }
    ],
    "sg:phone":"+1 610 432 4420",
    "sg:postcode":"18103",
    "sg:province":"PA",
    "sg:tags":[
        "eating"
    ],
    "wof:name":"Mangos Coastal Cuisine",
    "wof:placetype":"venue"
},
  "geometry": {"coordinates":[-75.533171,40.574965],"type":"Point"}
}