{
  "type": "Feature",
  "properties": {
    "iso:country":"US",
    "sg:address":"229 Mercer St",
    "sg:city":"Butler",
    "sg:classifiers":[
        {
            "category":"Manufacturing",
            "subcategory":"Tools & Machinery",
            "type":"Manufacturing & Wholesale Goods"
        }
    ],
    "sg:phone":"+1 724 452 6220",
    "sg:postcode":"16001",
    "sg:province":"PA",
    "sg:tags":[
        "filter"
    ],
    "wof:name":"Exchange At Harmony",
    "wof:placetype":"venue"
},
  "geometry": {"coordinates":[-79.906638,40.864222],"type":"Point"}
}