{
  "type": "Feature",
  "properties": {
    "iso:country":"US",
    "sg:address":"767 US Hwy 22",
    "sg:city":"Lewistown",
    "sg:classifiers":[
        {
            "category":"Travel",
            "subcategory":"Hotels & Motels",
            "type":"Entertainment"
        }
    ],
    "sg:phone":"+1 717 248 3921",
    "sg:postcode":"17044",
    "sg:province":"PA",
    "wof:name":"Stevens Motel",
    "wof:placetype":"venue"
},
  "geometry": {"coordinates":[-77.592973,40.592395],"type":"Point"}
}