{
  "type": "Feature",
  "properties": {
    "iso:country":"US",
    "sg:address":"51 Kennedy Dr",
    "sg:city":"Hanover",
    "sg:classifiers":[
        {
            "category":"Personal",
            "subcategory":"Beauty Salon",
            "type":"Services"
        }
    ],
    "sg:phone":"+1 717 632 4002",
    "sg:postcode":"17331",
    "sg:province":"PA",
    "wof:name":"Country Clip N' Curl",
    "wof:placetype":"venue"
},
  "geometry": {"coordinates":[-76.962276,39.747083],"type":"Point"}
}