{
  "type": "Feature",
  "properties": {
    "iso:country":"US",
    "sg:address":"34 Charleston St",
    "sg:city":"Wellsboro",
    "sg:classifiers":[
        {
            "category":"Restaurant",
            "type":"Food & Drink"
        }
    ],
    "sg:phone":"+1 570 724 9090",
    "sg:postcode":"16901",
    "sg:province":"PA",
    "wof:name":"Back Street Bar & Lounge",
    "wof:placetype":"venue"
},
  "geometry": {"coordinates":[-77.29231299999999,41.750412],"type":"Point"}
}