{
  "type": "Feature",
  "properties": {
    "addr:full":"12027 Perry Hwy Wexford PA 15090",
    "addr:housenumber":"12027",
    "addr:postcode":"15090",
    "addr:street":"Perry Hwy",
    "iso:country":"US",
    "sg:address":"12027 Perry Hwy",
    "sg:city":"Wexford",
    "sg:classifiers":[
        {
            "category":"Ice Cream",
            "type":"Food & Drink"
        }
    ],
    "sg:menulink":"http://www.allmenus.com/pa/pine/230234-marble-slab-creamery/menu/",
    "sg:phone":"+1 724 940 4010",
    "sg:postcode":"15090",
    "sg:province":"PA",
    "sg:tags":[
        "american"
    ],
    "wof:name":"Marble Slab Creamery",
    "wof:placetype":"venue"
},
  "geometry": {"coordinates":[-80.059408,40.633083],"type":"Point"}
}