{
  "type": "Feature",
  "properties": {
    "iso:country":"US",
    "sg:address":"3717 Station Ave",
    "sg:city":"Center Valley",
    "sg:classifiers":[
        {
            "category":"Building & Trades",
            "subcategory":"Landscaping Services",
            "type":"Services"
        }
    ],
    "sg:phone":"+1 610 282 0670",
    "sg:postcode":"18034",
    "sg:province":"PA",
    "sg:tags":[
        "landscape",
        "contractor"
    ],
    "wof:name":"Godshall's Lawn Maintenance",
    "wof:placetype":"venue"
},
  "geometry": {"coordinates":[-75.390856,40.528956],"type":"Point"}
}