{
  "type": "Feature",
  "properties": {
    "addr:full":"100 County Line Rd Philadelphia PA 19116",
    "addr:housenumber":"100",
    "addr:postcode":"19116",
    "addr:street":"County Line Rd",
    "iso:country":"US",
    "sg:address":"100 County Line Rd",
    "sg:city":"Philadelphia",
    "sg:classifiers":[
        {
            "category":"Banks & Credit Unions",
            "subcategory":"Bank",
            "type":"Services"
        }
    ],
    "sg:phone":"+1 215 673 2669",
    "sg:postcode":"19116",
    "sg:province":"PA",
    "sg:tags":[
        "loan",
        "real estate"
    ],
    "wof:name":"Global Home Loans & Finance",
    "wof:placetype":"venue"
},
  "geometry": {"coordinates":[-75.01457499999999,40.137693],"type":"Point"}
}