{
  "type": "Feature",
  "properties": {
    "iso:country":"US",
    "sg:address":"636 Alpha Dr",
    "sg:city":"Pittsburgh",
    "sg:classifiers":[
        {
            "category":"Wholesale",
            "subcategory":"Machinery & Supplies",
            "type":"Manufacturing & Wholesale Goods"
        }
    ],
    "sg:phone":"+1 412 963 7070",
    "sg:postcode":"15238",
    "sg:province":"PA",
    "sg:tags":[
        "pump"
    ],
    "wof:name":"Buckley Associates Inc",
    "wof:placetype":"venue"
},
  "geometry": {"coordinates":[-79.870317,40.505786],"type":"Point"}
}