{
  "type": "Feature",
  "properties": {
    "addr:full":"235 Main St Dickson City PA 18519",
    "addr:housenumber":"235",
    "addr:postcode":"18519",
    "addr:street":"Main St",
    "iso:country":"US",
    "sg:address":"235 Main St",
    "sg:city":"Dickson City",
    "sg:classifiers":[
        {
            "category":"Sports & Exercise",
            "subcategory":"Gym",
            "type":"Entertainment"
        }
    ],
    "sg:phone":"+1 570 307 1243",
    "sg:postcode":"18519",
    "sg:province":"PA",
    "sg:tags":[
        "facility",
        "club",
        "gymnasium",
        "health",
        "fitness",
        "studio",
        "physical"
    ],
    "wof:name":"Curves For Women",
    "wof:placetype":"venue"
},
  "geometry": {"coordinates":[-75.636582,41.451661],"type":"Point"}
}