{
  "type": "Feature",
  "properties": {
    "iso:country":"US",
    "sg:address":"328 N Mulberry St",
    "sg:city":"Lancaster",
    "sg:classifiers":[
        {
            "category":"Wholesale",
            "subcategory":"Machinery & Supplies",
            "type":"Manufacturing & Wholesale Goods"
        }
    ],
    "sg:phone":"+1 717 393 1901",
    "sg:postcode":"17603",
    "sg:province":"PA",
    "sg:tags":[
        "industrial",
        "equipment",
        "used",
        "machinery-new",
        "supplies-wholesale"
    ],
    "wof:name":"Eisupply",
    "wof:placetype":"venue"
},
  "geometry": {"coordinates":[-76.311408,40.042695],"type":"Point"}
}