{
  "type": "Feature",
  "properties": {
    "iso:country":"US",
    "sg:address":"6945 US 322 Unit 607",
    "sg:city":"Cranberry",
    "sg:classifiers":[
        {
            "category":"Shopping",
            "subcategory":"Department Store",
            "type":"Retail Goods"
        }
    ],
    "sg:phone":"+1 814 677 0400",
    "sg:postcode":"16319",
    "sg:province":"PA",
    "sg:website":"http://www.bonton.com/",
    "wof:name":"Bon-Ton Stores",
    "wof:placetype":"venue"
},
  "geometry": {"coordinates":[-79.71880400000001,41.351687],"type":"Point"}
}