{
  "type": "Feature",
  "properties": {
    "addr:full":"250 Rock Hill Rd Bala Cynwyd PA 19004",
    "addr:housenumber":"250",
    "addr:postcode":"19004",
    "addr:street":"Rock Hill Rd",
    "iso:country":"US",
    "sg:address":"250 Rock Hill Rd",
    "sg:city":"Bala Cynwyd",
    "sg:classifiers":[
        {
            "category":"Banks & Credit Unions",
            "subcategory":"Financial Services",
            "type":"Services"
        }
    ],
    "sg:phone":"+1 610 664 7474",
    "sg:postcode":"19004",
    "sg:province":"PA",
    "wof:name":"Fleetway Capital Corp",
    "wof:placetype":"venue"
},
  "geometry": {"coordinates":[-75.2313,40.021702],"type":"Point"}
}