{
  "type": "Feature",
  "properties": {
    "iso:country":"US",
    "sg:address":"1183 Baltimore Pike",
    "sg:city":"Springfield",
    "sg:classifiers":[
        {
            "category":"Travel",
            "subcategory":"Travel Agent",
            "type":"Entertainment"
        }
    ],
    "sg:phone":"+1 610 328 5300",
    "sg:postcode":"19064",
    "sg:province":"PA",
    "sg:tags":[
        "agency",
        "bureau"
    ],
    "sg:website":"www.wtvacations.com",
    "wof:name":"Westminster Travel Agency",
    "wof:placetype":"venue"
},
  "geometry": {"coordinates":[-75.347841,39.91352],"type":"Point"}
}