{
  "type": "Feature",
  "properties": {
    "addr:full":"130 Airport Rd Hazleton PA 18202",
    "addr:housenumber":"130",
    "addr:postcode":"18202",
    "addr:street":"Airport Rd",
    "iso:country":"US",
    "sg:address":"130 Airport Rd",
    "sg:city":"Hazleton",
    "sg:classifiers":[
        {
            "category":"Health Services",
            "subcategory":"Doctor",
            "type":"Services"
        }
    ],
    "sg:phone":"+1 570 453 1110",
    "sg:postcode":"18202",
    "sg:province":"PA",
    "sg:tags":[
        "medical"
    ],
    "wof:name":"Raymond Khoudary MD",
    "wof:placetype":"venue"
},
  "geometry": {"coordinates":[-75.993962,40.992614],"type":"Point"}
}