{
  "type": "Feature",
  "properties": {
    "addr:full":"316 S Park Ave Mercersburg PA 17236",
    "addr:housenumber":"316",
    "addr:postcode":"17236",
    "addr:street":"S Park Ave",
    "iso:country":"US",
    "sg:address":"316 S Park Ave",
    "sg:city":"Mercersburg",
    "sg:classifiers":[
        {
            "category":"Professional",
            "type":"Services"
        }
    ],
    "sg:phone":"+1   ",
    "sg:postcode":"17236",
    "sg:province":"PA",
    "wof:name":"Biznesstobiznesscom LLC",
    "wof:placetype":"venue"
},
  "geometry": {"coordinates":[-77.907765,39.82429],"type":"Point"}
}