{
  "type": "Feature",
  "properties": {
    "iso:country":"US",
    "sg:address":"102 Apple Hill Rd",
    "sg:city":"Hatboro",
    "sg:classifiers":[
        {
            "category":"Professional",
            "subcategory":"Art Services",
            "type":"Services"
        }
    ],
    "sg:phone":"+1 215 674 8655",
    "sg:postcode":"19040",
    "sg:province":"PA",
    "sg:tags":[
        "photographer"
    ],
    "wof:name":"Macnabb Photography",
    "wof:placetype":"venue"
},
  "geometry": {"coordinates":[-75.115167,40.18739],"type":"Point"}
}