{
  "type": "Feature",
  "properties": {
    "iso:country":"US",
    "sg:address":"527 E Drinker St",
    "sg:city":"Scranton",
    "sg:classifiers":[
        {
            "category":"Building & Trades",
            "subcategory":"Construction",
            "type":"Services"
        }
    ],
    "sg:phone":"+1   ",
    "sg:postcode":"18512",
    "sg:province":"PA",
    "sg:tags":[
        "house"
    ],
    "wof:name":"Less Pay Home Improvement",
    "wof:placetype":"venue"
},
  "geometry": {"coordinates":[-75.621219,41.419851],"type":"Point"}
}