{
  "type": "Feature",
  "properties": {
    "addr:full":"434 Main St Johnstown PA 15901",
    "addr:housenumber":"434",
    "addr:postcode":"15901",
    "addr:street":"Main St",
    "iso:country":"US",
    "sg:address":"434 Main St",
    "sg:city":"Johnstown",
    "sg:classifiers":[
        {
            "category":"Shopping",
            "subcategory":"Pharmacy",
            "type":"Retail Goods"
        }
    ],
    "sg:phone":"+1 814 536 3807",
    "sg:postcode":"15901",
    "sg:province":"PA",
    "sg:tags":[
        "drug",
        "store"
    ],
    "wof:name":"Eckerd",
    "wof:placetype":"venue"
},
  "geometry": {"coordinates":[-78.91808899999999,40.325156],"type":"Point"}
}