{
  "type": "Feature",
  "properties": {
    "iso:country":"US",
    "sg:address":"5401 Walnut St",
    "sg:city":"Pittsburgh",
    "sg:classifiers":[
        {
            "category":"Restaurant",
            "type":"Food & Drink"
        }
    ],
    "sg:phone":"+1 412 688 8424",
    "sg:postcode":"15232",
    "sg:province":"PA",
    "sg:tags":[
        "eating"
    ],
    "wof:name":"My Thai Restaurant",
    "wof:placetype":"venue"
},
  "geometry": {"coordinates":[-79.935125,40.45076],"type":"Point"}
}