{
  "type": "Feature",
  "properties": {
    "iso:country":"US",
    "sg:address":"600 W New Castle St",
    "sg:city":"Zelienople",
    "sg:classifiers":[
        {
            "category":"Shopping",
            "subcategory":"Beauty & Cosmetics",
            "type":"Retail Goods"
        }
    ],
    "sg:phone":"+1   ",
    "sg:postcode":"16063",
    "sg:province":"PA",
    "sg:tags":[
        "merchandise"
    ],
    "wof:name":"Luanne Cosmetics",
    "wof:placetype":"venue"
},
  "geometry": {"coordinates":[-80.145088,40.794781],"type":"Point"}
}