{
  "type": "Feature",
  "properties": {
    "iso:country":"US",
    "sg:address":"2620 Washington Rd",
    "sg:city":"Canonsburg",
    "sg:classifiers":[
        {
            "category":"Banks & Credit Unions",
            "subcategory":"Bank",
            "type":"Services"
        }
    ],
    "sg:phone":"+1 724 743 5860",
    "sg:postcode":"15317",
    "sg:province":"PA",
    "sg:website":"www.53.com",
    "wof:name":"Fifth Third Bank",
    "wof:placetype":"venue"
},
  "geometry": {"coordinates":[-80.155604,40.254872],"type":"Point"}
}