{
  "type": "Feature",
  "properties": {
    "addr:full":"1818 Market St Philadelphia PA 19103",
    "addr:housenumber":"1818",
    "addr:postcode":"19103",
    "addr:street":"Market St",
    "iso:country":"US",
    "sg:address":"1818 Market St",
    "sg:city":"Philadelphia",
    "sg:classifiers":[
        {
            "category":"Professional",
            "subcategory":"Lawyer & Legal Services",
            "type":"Services"
        }
    ],
    "sg:phone":"+1 215 751 2883",
    "sg:postcode":"19103",
    "sg:province":"PA",
    "wof:name":"Bennett Jo",
    "wof:placetype":"venue"
},
  "geometry": {"coordinates":[-75.170249,39.953081],"type":"Point"}
}