{
  "type": "Feature",
  "properties": {
    "addr:full":"300 Market St Philadelphia PA 19106",
    "addr:housenumber":"300",
    "addr:postcode":"19106",
    "addr:street":"Market St",
    "iso:country":"US",
    "sg:address":"300 Market St",
    "sg:city":"Philadelphia",
    "sg:classifiers":[
        {
            "category":"Building & Trades",
            "subcategory":"Locksmith",
            "type":"Services"
        }
    ],
    "sg:phone":"+1 215 525 6715",
    "sg:postcode":"19106",
    "sg:province":"PA",
    "sg:tags":[
        "key"
    ],
    "wof:name":"Locksmith 24 Hours",
    "wof:placetype":"venue"
},
  "geometry": {"coordinates":[-75.145701,39.950014],"type":"Point"}
}