{
  "type": "Feature",
  "properties": {
    "iso:country":"US",
    "sg:address":"6031 Baptist Rd",
    "sg:city":"Pittsburgh",
    "sg:classifiers":[
        {
            "category":"Social Services",
            "subcategory":"Child Care",
            "type":"Services"
        }
    ],
    "sg:phone":"+1   ",
    "sg:postcode":"15236",
    "sg:province":"PA",
    "sg:tags":[
        "day"
    ],
    "wof:name":"Adlaur Inc",
    "wof:placetype":"venue"
},
  "geometry": {"coordinates":[-80.014617,40.345142],"type":"Point"}
}