{
  "type": "Feature",
  "properties": {
    "addr:full":"103 Neshaminy Mall Bensalem PA 19020",
    "addr:housenumber":"103",
    "addr:postcode":"19020",
    "addr:street":"Neshaminy Mall",
    "iso:country":"US",
    "sg:address":"103 Neshaminy Mall",
    "sg:city":"Bensalem",
    "sg:classifiers":[
        {
            "category":"Health Services",
            "subcategory":"Optometrist",
            "type":"Services"
        },
        {
            "category":"Shopping",
            "subcategory":"Optician",
            "type":"Retail Goods"
        }
    ],
    "sg:phone":"+1 215 942 7861",
    "sg:postcode":"19020",
    "sg:province":"PA",
    "sg:tags":[
        "eyewear"
    ],
    "wof:name":"Eye Wise",
    "wof:placetype":"venue"
},
  "geometry": {"coordinates":[-74.957097,40.140428],"type":"Point"}
}