{
  "type": "Feature",
  "properties": {
    "iso:country":"US",
    "sg:address":"4508 Old Bethlehem Pike",
    "sg:city":"Center Valley",
    "sg:classifiers":[
        {
            "category":"Restaurant",
            "type":"Food & Drink"
        }
    ],
    "sg:phone":"+1 610 865 8166",
    "sg:postcode":"18034",
    "sg:province":"PA",
    "sg:tags":[
        "french"
    ],
    "sg:website":"www.manor-house-inn.com",
    "wof:name":"Manor House Inn",
    "wof:placetype":"venue"
},
  "geometry": {"coordinates":[-75.39589700000001,40.561199],"type":"Point"}
}