{
  "type": "Feature",
  "properties": {
    "iso:country":"US",
    "sg:address":"528 Garland Dr",
    "sg:city":"Carlisle",
    "sg:classifiers":[
        {
            "category":"Organizations",
            "subcategory":"Religious Organization",
            "type":"Services"
        }
    ],
    "sg:phone":"+1 717 243 4571",
    "sg:postcode":"17013",
    "sg:province":"PA",
    "sg:website":"www.secondprescarlisle.com",
    "wof:name":"Second Presbyterian Church",
    "wof:placetype":"venue"
},
  "geometry": {"coordinates":[-77.205803,40.1856],"type":"Point"}
}