{
  "type": "Feature",
  "properties": {
    "addr:full":"4185 N George St Exd Manchester PA 17345",
    "addr:housenumber":"4185",
    "addr:postcode":"17345",
    "addr:street":"N George St Exd",
    "iso:country":"US",
    "sg:address":"4185 N George St Exd",
    "sg:city":"Manchester",
    "sg:classifiers":[
        {
            "category":"Social Services",
            "subcategory":"Job Training",
            "type":"Services"
        }
    ],
    "sg:phone":"+1 717 266 6731",
    "sg:postcode":"17345",
    "sg:province":"PA",
    "sg:tags":[
        "rehabilitation"
    ],
    "wof:name":"Healthsouth Rehabilitation Ctr",
    "wof:placetype":"venue"
},
  "geometry": {"coordinates":[-76.724084,40.044524],"type":"Point"}
}