{
  "type": "Feature",
  "properties": {
    "iso:country":"US",
    "sg:address":"204 Railroad Drive",
    "sg:city":"Ivyland",
    "sg:classifiers":[
        {
            "category":"Professional",
            "subcategory":"Computer Services",
            "type":"Services"
        }
    ],
    "sg:phone":"+1 888 321 9630",
    "sg:postcode":"18974",
    "sg:province":"PA",
    "sg:website":"http://www.drexelmetals.com/",
    "wof:name":"Drexel Metals",
    "wof:placetype":"venue"
},
  "geometry": {"coordinates":[-75.064786,40.225205],"type":"Point"}
}