{
  "type": "Feature",
  "properties": {
    "iso:country":"US",
    "sg:address":"1717 Teesdale St",
    "sg:city":"Philadelphia",
    "sg:classifiers":[
        {
            "category":"Arena",
            "subcategory":"Sports Club",
            "type":"Entertainment"
        }
    ],
    "sg:phone":"+1 215 342 9659",
    "sg:postcode":"19111",
    "sg:province":"PA",
    "sg:tags":[
        "martial art",
        "instruction"
    ],
    "wof:name":"Kwon, Ok",
    "wof:placetype":"venue"
},
  "geometry": {"coordinates":[-75.070301,40.054657],"type":"Point"}
}