{
  "type": "Feature",
  "properties": {
    "iso:country":"US",
    "sg:address":"1207 Allegheny Ave",
    "sg:city":"Pittsburgh",
    "sg:classifiers":[
        {
            "category":"Bars & Pubs",
            "type":"Food & Drink"
        }
    ],
    "sg:phone":"+1 412 231 9216",
    "sg:postcode":"15233",
    "sg:province":"PA",
    "sg:tags":[
        "drinking"
    ],
    "wof:name":"Duke's Tavern",
    "wof:placetype":"venue"
},
  "geometry": {"coordinates":[-80.019811,40.454021],"type":"Point"}
}