{
  "type": "Feature",
  "properties": {
    "addr:full":"602 Chestnut St Emmaus PA 18049",
    "addr:housenumber":"602",
    "addr:postcode":"18049",
    "addr:street":"Chestnut St",
    "iso:country":"US",
    "sg:address":"602 Chestnut St",
    "sg:city":"Emmaus",
    "sg:classifiers":[
        {
            "category":"Food & Beverages",
            "subcategory":"Groceries & Convenience Stores",
            "type":"Retail Goods"
        }
    ],
    "sg:phone":"+1 610 965 5202",
    "sg:postcode":"18049",
    "sg:province":"PA",
    "wof:name":"Turkey Hill Minit Market",
    "wof:placetype":"venue"
},
  "geometry": {"coordinates":[-75.498718,40.532002],"type":"Point"}
}