{
  "type": "Feature",
  "properties": {
    "iso:country":"US",
    "sg:address":"407 N Main St",
    "sg:city":"Doylestown",
    "sg:classifiers":[
        {
            "category":"Health Services",
            "subcategory":"Dentist",
            "type":"Services"
        }
    ],
    "sg:phone":"+1 215 348 1192",
    "sg:postcode":"18901",
    "sg:province":"PA",
    "sg:website":"www.vidaknightdental.com",
    "wof:name":"Vida & Knight Dental Associates PC",
    "wof:placetype":"venue"
},
  "geometry": {"coordinates":[-75.130484,40.318929],"type":"Point"}
}