{
  "type": "Feature",
  "properties": {
    "iso:country":"US",
    "sg:address":"1811 W Liberty Ave",
    "sg:city":"Pittsburgh",
    "sg:classifiers":[
        {
            "category":"Home & Garden",
            "subcategory":"Home Furnishings",
            "type":"Retail Goods"
        }
    ],
    "sg:phone":"+1 412 531 8595",
    "sg:postcode":"15226",
    "sg:province":"PA",
    "sg:tags":[
        "installs",
        "fireplace",
        "accessory"
    ],
    "wof:name":"Artcraft Fireplace Inc",
    "wof:placetype":"venue"
},
  "geometry": {"coordinates":[-80.01809799999999,40.407703],"type":"Point"}
}