{
  "type": "Feature",
  "properties": {
    "iso:country":"US",
    "sg:address":"100 5th Ave",
    "sg:city":"Pittsburgh",
    "sg:classifiers":[
        {
            "category":"Restaurant",
            "type":"Food & Drink"
        }
    ],
    "sg:phone":"+1 412 281 2771",
    "sg:postcode":"15219",
    "sg:province":"PA",
    "sg:tags":[
        "barbeque"
    ],
    "wof:name":"A & J Ribs",
    "wof:placetype":"venue"
},
  "geometry": {"coordinates":[-80.002889,40.441406],"type":"Point"}
}