{
  "type": "Feature",
  "properties": {
    "iso:country":"US",
    "sg:address":"860 Broad St",
    "sg:city":"Emmaus",
    "sg:classifiers":[
        {
            "category":"Real Estate",
            "subcategory":"Real Estate Agent",
            "type":"Services"
        }
    ],
    "sg:phone":"+1   ",
    "sg:postcode":"18049",
    "sg:province":"PA",
    "wof:name":"Rental Advantage",
    "wof:placetype":"venue"
},
  "geometry": {"coordinates":[-75.499304,40.529352],"type":"Point"}
}