{
  "type": "Feature",
  "properties": {
    "addr:full":"7401 Bristol Pike Levittown PA 19057",
    "addr:housenumber":"7401",
    "addr:postcode":"19057",
    "addr:street":"Bristol Pike Levittown",
    "iso:country":"US",
    "sg:address":"7401 Bristol Pike",
    "sg:city":"Levittown",
    "sg:classifiers":[
        {
            "category":"Autos & Motor Vehicles",
            "subcategory":"Automobile Sales",
            "type":"Retail Goods"
        }
    ],
    "sg:phone":"+1   ",
    "sg:postcode":"19057",
    "sg:province":"PA",
    "sg:tags":[
        "used"
    ],
    "wof:name":"Greggs Fine Autos",
    "wof:placetype":"venue"
},
  "geometry": {"coordinates":[-74.83253499999999,40.131059],"type":"Point"}
}