{
  "type": "Feature",
  "properties": {
    "addr:full":"2107 W Toronto St Philadelphia PA 19132",
    "addr:housenumber":"2107",
    "addr:postcode":"19132",
    "addr:street":"W Toronto St",
    "iso:country":"US",
    "sg:address":"2107 W Toronto St",
    "sg:city":"Philadelphia",
    "sg:classifiers":[
        {
            "category":"Organizations",
            "subcategory":"Religious Organization",
            "type":"Services"
        }
    ],
    "sg:phone":"+1 215 225 0318",
    "sg:postcode":"19132",
    "sg:province":"PA",
    "wof:name":"Beloved Baptist",
    "wof:placetype":"venue"
},
  "geometry": {"coordinates":[-75.16488200000001,40.00086],"type":"Point"}
}