{
  "type": "Feature",
  "properties": {
    "iso:country":"US",
    "sg:address":"2702 Temple Dr",
    "sg:city":"Reading",
    "sg:classifiers":[
        {
            "category":"Wholesale",
            "subcategory":"Auto Parts",
            "type":"Manufacturing & Wholesale Goods"
        }
    ],
    "sg:phone":"+1   ",
    "sg:postcode":"19608",
    "sg:province":"PA",
    "sg:tags":[
        "automotive",
        "replacement"
    ],
    "wof:name":"Tercha Auto Supply Inc",
    "wof:placetype":"venue"
},
  "geometry": {"coordinates":[-76.007052,40.308497],"type":"Point"}
}