{
  "type": "Feature",
  "properties": {
    "iso:country":"US",
    "sg:address":"17 Edgewood Rd",
    "sg:city":"Boyertown",
    "sg:classifiers":[
        {
            "category":"Utilities",
            "subcategory":"Fuel Oil & Lpg",
            "type":"Services"
        }
    ],
    "sg:phone":"+1 610 689 5379",
    "sg:postcode":"19512",
    "sg:province":"PA",
    "sg:tags":[
        "firewood"
    ],
    "wof:name":"Hahn Firewood & Logging",
    "wof:placetype":"venue"
},
  "geometry": {"coordinates":[-75.699972,40.330227],"type":"Point"}
}