{
  "type": "Feature",
  "properties": {
    "iso:country":"US",
    "sg:address":"1418 W Girard Ave",
    "sg:city":"Philadelphia",
    "sg:classifiers":[
        {
            "category":"Restaurant",
            "type":"Food & Drink"
        }
    ],
    "sg:menulink":"http://www.allmenus.com/pa/philadelphia/221178-girard-garden-rest/menu/",
    "sg:phone":"+1 215 236 5800",
    "sg:postcode":"19130",
    "sg:province":"PA",
    "sg:tags":[
        "asian",
        "chinese"
    ],
    "wof:name":"Girard Garden Rest",
    "wof:placetype":"venue"
},
  "geometry": {"coordinates":[-75.16031599999999,39.97158],"type":"Point"}
}