{
  "type": "Feature",
  "properties": {
    "addr:full":"37 S Euclid Ave Pittsburgh PA 15202",
    "addr:housenumber":"37",
    "addr:postcode":"15202",
    "addr:street":"S Euclid Ave",
    "iso:country":"US",
    "sg:address":"37 S Euclid Ave",
    "sg:city":"Pittsburgh",
    "sg:classifiers":[
        {
            "category":"Professional",
            "type":"Services"
        }
    ],
    "sg:phone":"+1   ",
    "sg:postcode":"15202",
    "sg:province":"PA",
    "wof:name":"Abak Inc",
    "wof:placetype":"venue"
},
  "geometry": {"coordinates":[-80.051007,40.492624],"type":"Point"}
}