{
  "type": "Feature",
  "properties": {
    "addr:full":"529 N 2nd St Allentown PA 18102",
    "addr:housenumber":"529",
    "addr:postcode":"18102",
    "addr:street":"N 2Nd St",
    "iso:country":"US",
    "sg:address":"529 N 2nd St",
    "sg:city":"Allentown",
    "sg:classifiers":[
        {
            "category":"Building & Trades",
            "subcategory":"Construction",
            "type":"Services"
        }
    ],
    "sg:phone":"+1 610 432 4201",
    "sg:postcode":"18102",
    "sg:province":"PA",
    "sg:tags":[
        "general",
        "contractor"
    ],
    "wof:name":"Kassis Construction",
    "wof:placetype":"venue"
},
  "geometry": {"coordinates":[-75.463443,40.613199],"type":"Point"}
}