{
  "type": "Feature",
  "properties": {
    "addr:full":"100 Wallrose Heights Rd Baden PA 15005",
    "addr:housenumber":"100",
    "addr:postcode":"15005",
    "addr:street":"Wallrose Heights Rd",
    "iso:country":"US",
    "sg:address":"100 Wallrose Heights Rd",
    "sg:city":"Baden",
    "sg:classifiers":[
        {
            "category":"Home & Garden",
            "subcategory":"Garden Supply",
            "type":"Retail Goods"
        }
    ],
    "sg:phone":"+1 724 266 6947",
    "sg:postcode":"15005",
    "sg:province":"PA",
    "sg:tags":[
        "nursery",
        "gardening"
    ],
    "wof:name":"Zaccagnini Frank",
    "wof:placetype":"venue"
},
  "geometry": {"coordinates":[-80.154999,40.637699],"type":"Point"}
}