{
  "type": "Feature",
  "properties": {
    "iso:country":"US",
    "sg:address":"485 Business Park Ln",
    "sg:city":"Allentown",
    "sg:classifiers":[
        {
            "category":"Personal",
            "subcategory":"Tattoo Parlor",
            "type":"Services"
        }
    ],
    "sg:phone":"+1 610 433 7261",
    "sg:postcode":"18109",
    "sg:province":"PA",
    "wof:name":"National Tattoo Association",
    "wof:placetype":"venue"
},
  "geometry": {"coordinates":[-75.45729799999999,40.6287],"type":"Point"}
}