{
  "type": "Feature",
  "properties": {
    "iso:country":"US",
    "sg:address":"2042 General Alexander Dr",
    "sg:city":"Malvern",
    "sg:classifiers":[
        {
            "category":"Food & Beverages",
            "subcategory":"Liquor & Beverages",
            "type":"Retail Goods"
        }
    ],
    "sg:phone":"+1 610 647 4888",
    "sg:postcode":"19355",
    "sg:province":"PA",
    "sg:tags":[
        "wine"
    ],
    "sg:website":"www.localwineevents.com",
    "wof:name":"LOCALWINEEVENTS.COM",
    "wof:placetype":"venue"
},
  "geometry": {"coordinates":[-75.46983,40.082818],"type":"Point"}
}