{
  "type": "Feature",
  "properties": {
    "addr:full":"3 Whittley Ct Carlisle PA 17015",
    "addr:housenumber":"3",
    "addr:postcode":"17015",
    "addr:street":"Whittley Ct",
    "iso:country":"US",
    "sg:address":"3 Whittley Ct",
    "sg:city":"Carlisle",
    "sg:classifiers":[
        {
            "category":"Wholesale",
            "subcategory":"Books, Periodicals, & Newspapers",
            "type":"Manufacturing & Wholesale Goods"
        }
    ],
    "sg:phone":"+1   ",
    "sg:postcode":"17015",
    "sg:province":"PA",
    "wof:name":"Christian Lterature For Africa",
    "wof:placetype":"venue"
},
  "geometry": {"coordinates":[-77.150216,40.175703],"type":"Point"}
}