{
  "type": "Feature",
  "properties": {
    "iso:country":"US",
    "sg:address":"138 N Lime St",
    "sg:city":"Lancaster",
    "sg:classifiers":[
        {
            "category":"Professional",
            "type":"Services"
        }
    ],
    "sg:phone":"+1   ",
    "sg:postcode":"17602",
    "sg:province":"PA",
    "wof:name":"Pr/Texas Inc",
    "wof:placetype":"venue"
},
  "geometry": {"coordinates":[-76.30199399999999,40.041374],"type":"Point"}
}