{
  "type": "Feature",
  "properties": {
    "addr:full":"55 Commerce Dr Reading PA 19610",
    "addr:housenumber":"55",
    "addr:postcode":"19610",
    "addr:street":"Commerce Dr",
    "iso:country":"US",
    "sg:address":"55 Commerce Dr",
    "sg:city":"Reading",
    "sg:classifiers":[
        {
            "category":"Real Estate",
            "subcategory":"Real Estate Services",
            "type":"Services"
        }
    ],
    "sg:phone":"+1   ",
    "sg:postcode":"19610",
    "sg:province":"PA",
    "sg:tags":[
        "abstract",
        "title"
    ],
    "wof:name":"Lawyers Title",
    "wof:placetype":"venue"
},
  "geometry": {"coordinates":[-75.989604,40.347354],"type":"Point"}
}