{
  "type": "Feature",
  "properties": {
    "iso:country":"US",
    "sg:address":"100 Evergreen Dr",
    "sg:city":"Glen Mills",
    "sg:classifiers":[
        {
            "category":"Professional",
            "type":"Services"
        }
    ],
    "sg:phone":"+1 610 358 2429",
    "sg:postcode":"19320",
    "sg:province":"PA",
    "wof:name":"Galan Inc",
    "wof:placetype":"venue"
},
  "geometry": {"coordinates":[-75.82889,40.005863],"type":"Point"}
}