{
  "type": "Feature",
  "properties": {
    "addr:full":"1005 W 4th Ave Derry PA 15627",
    "addr:housenumber":"1005",
    "addr:postcode":"15627",
    "addr:street":"W 4Th Ave",
    "iso:country":"US",
    "sg:address":"1005 W 4th Ave",
    "sg:city":"Derry",
    "sg:classifiers":[
        {
            "category":"Retail",
            "subcategory":"Auto Rental",
            "type":"Services"
        }
    ],
    "sg:phone":"+1   ",
    "sg:postcode":"15627",
    "sg:province":"PA",
    "sg:tags":[
        "truck"
    ],
    "wof:name":"Jim Struble",
    "wof:placetype":"venue"
},
  "geometry": {"coordinates":[-79.307095,40.324399],"type":"Point"}
}