{
  "type": "Feature",
  "properties": {
    "addr:full":"711 Old Clairton Rd Pittsburgh PA 15236",
    "addr:housenumber":"711",
    "addr:postcode":"15236",
    "addr:street":"Old Clairton Rd",
    "iso:country":"US",
    "sg:address":"711 Old Clairton Rd",
    "sg:city":"Pittsburgh",
    "sg:classifiers":[
        {
            "category":"Organizations",
            "subcategory":"Religious Organization",
            "type":"Services"
        }
    ],
    "sg:phone":"+1 412 653 6930",
    "sg:postcode":"15236",
    "sg:province":"PA",
    "sg:tags":[
        "church"
    ],
    "wof:name":"Jefferson Hills Bible Church",
    "wof:placetype":"venue"
},
  "geometry": {"coordinates":[-79.95628000000001,40.322755],"type":"Point"}
}