{
  "type": "Feature",
  "properties": {
    "iso:country":"US",
    "sg:address":"143 Ronald St",
    "sg:city":"Johnstown",
    "sg:classifiers":[
        {
            "category":"Building & Trades",
            "subcategory":"Landscaping Services",
            "type":"Services"
        }
    ],
    "sg:phone":"+1 814 536 1618",
    "sg:postcode":"15902",
    "sg:province":"PA",
    "sg:tags":[
        "tree"
    ],
    "wof:name":"Tree Expert Tree Svc",
    "wof:placetype":"venue"
},
  "geometry": {"coordinates":[-78.884812,40.327628],"type":"Point"}
}