{
  "type": "Feature",
  "properties": {
    "iso:country":"US",
    "sg:address":"112 7th St",
    "sg:city":"Monessen",
    "sg:classifiers":[
        {
            "category":"Organizations",
            "subcategory":"Community Association",
            "type":"Services"
        }
    ],
    "sg:phone":"+1 724 684 3710",
    "sg:postcode":"15062",
    "sg:province":"PA",
    "sg:tags":[
        "club",
        "venue",
        "event",
        "space"
    ],
    "wof:name":"Italian Hall",
    "wof:placetype":"venue"
},
  "geometry": {"coordinates":[-79.888729,40.162067],"type":"Point"}
}