{
  "type": "Feature",
  "properties": {
    "addr:full":"21 8th Ave Carbondale PA 18407",
    "addr:housenumber":"21",
    "addr:postcode":"18407",
    "addr:street":"8Th Ave",
    "iso:country":"US",
    "sg:address":"21 8th Ave",
    "sg:city":"Carbondale",
    "sg:classifiers":[
        {
            "category":"Food & Beverages",
            "subcategory":"Groceries & Convenience Stores",
            "type":"Retail Goods"
        }
    ],
    "sg:phone":"+1 570 282 7531",
    "sg:postcode":"18407",
    "sg:province":"PA",
    "wof:name":"Turkey Hill Minit Market",
    "wof:placetype":"venue"
},
  "geometry": {"coordinates":[-75.504519,41.569807],"type":"Point"}
}