{
  "type": "Feature",
  "properties": {
    "iso:country":"US",
    "sg:address":"318 Morgantown St",
    "sg:city":"Uniontown",
    "sg:classifiers":[
        {
            "category":"Food & Beverages",
            "subcategory":"Bakery",
            "type":"Retail Goods"
        }
    ],
    "sg:phone":"+1 724 430 9999",
    "sg:postcode":"15401",
    "sg:province":"PA",
    "sg:tags":[
        "bagel"
    ],
    "wof:name":"Yum Yum's Bagel Cafe",
    "wof:placetype":"venue"
},
  "geometry": {"coordinates":[-79.73311,39.892774],"type":"Point"}
}