{
  "type": "Feature",
  "properties": {
    "iso:country":"US",
    "sg:address":"40 E Philadelphia St",
    "sg:city":"York",
    "sg:classifiers":[
        {
            "category":"Professional",
            "subcategory":"Lawyer & Legal Services",
            "type":"Services"
        }
    ],
    "sg:phone":"+1 717 846 4722",
    "sg:postcode":"17401",
    "sg:province":"PA",
    "sg:tags":[
        "attorney"
    ],
    "wof:name":"Mooney & Associates",
    "wof:placetype":"venue"
},
  "geometry": {"coordinates":[-76.72651399999999,39.96447],"type":"Point"}
}