{
  "type": "Feature",
  "properties": {
    "iso:country":"US",
    "sg:address":"888 Church St",
    "sg:city":"Indiana",
    "sg:classifiers":[
        {
            "category":"Health Services",
            "subcategory":"Doctor",
            "type":"Services"
        }
    ],
    "sg:phone":"+1   ",
    "sg:postcode":"15701",
    "sg:province":"PA",
    "wof:name":"Scott Dills DDS",
    "wof:placetype":"venue"
},
  "geometry": {"coordinates":[-79.155362,40.62156],"type":"Point"}
}