{
  "type": "Feature",
  "properties": {
    "addr:full":"226 E College Ave York PA 17403",
    "addr:housenumber":"226",
    "addr:postcode":"17403",
    "addr:street":"E College Ave",
    "iso:country":"US",
    "sg:address":"226 E College Ave",
    "sg:city":"York",
    "sg:classifiers":[
        {
            "category":"Organizations",
            "subcategory":"Non-profit Organization",
            "type":"Services"
        }
    ],
    "sg:phone":"+1 717 846 4600",
    "sg:postcode":"17403",
    "sg:province":"PA",
    "wof:name":"Head Start",
    "wof:placetype":"venue"
},
  "geometry": {"coordinates":[-76.72089699999999,39.959627],"type":"Point"}
}