{
  "type": "Feature",
  "properties": {
    "addr:full":"1500 Windrim Ave Philadelphia PA 19141",
    "addr:housenumber":"1500",
    "addr:postcode":"19141",
    "addr:street":"Windrim Ave",
    "iso:country":"US",
    "sg:address":"1500 Windrim Ave",
    "sg:city":"Philadelphia",
    "sg:classifiers":[
        {
            "category":"Shopping",
            "subcategory":"Discount & Variety Stores",
            "type":"Retail Goods"
        }
    ],
    "sg:phone":"+1   ",
    "sg:postcode":"19141",
    "sg:province":"PA",
    "wof:name":"Neiboerhood Dollar Store",
    "wof:placetype":"venue"
},
  "geometry": {"coordinates":[-75.14966,40.027999],"type":"Point"}
}