{
  "type": "Feature",
  "properties": {
    "iso:country":"US",
    "sg:address":"725 Street Rd",
    "sg:city":"West Grove",
    "sg:classifiers":[
        {
            "category":"Shopping",
            "subcategory":"Clothing, Apparel, & Fashions",
            "type":"Retail Goods"
        }
    ],
    "sg:phone":"+1   ",
    "sg:postcode":"19390",
    "sg:province":"PA",
    "sg:tags":[
        "jewelry"
    ],
    "wof:name":"Dinas Designs",
    "wof:placetype":"venue"
},
  "geometry": {"coordinates":[-75.813327,39.869952],"type":"Point"}
}