{
  "type": "Feature",
  "properties": {
    "iso:country":"US",
    "sg:address":"7 Michele Dr",
    "sg:city":"Media",
    "sg:classifiers":[
        {
            "category":"Manufacturing",
            "subcategory":"Tools & Machinery",
            "type":"Manufacturing & Wholesale Goods"
        }
    ],
    "sg:phone":"+1 610 359 1727",
    "sg:postcode":"19063",
    "sg:province":"PA",
    "sg:tags":[
        "consulting",
        "computer",
        "peripheral",
        "business",
        "mfg"
    ],
    "wof:name":"Power & Control Systems Inc",
    "wof:placetype":"venue"
},
  "geometry": {"coordinates":[-75.386526,39.959623],"type":"Point"}
}