{
  "type": "Feature",
  "properties": {
    "addr:full":"9 N Morgantown St Fairchance PA 15436",
    "addr:housenumber":"9",
    "addr:postcode":"15436",
    "addr:street":"N Morgantown St",
    "iso:country":"US",
    "sg:address":"9 N Morgantown St",
    "sg:city":"Fairchance",
    "sg:classifiers":[
        {
            "category":"Professional",
            "subcategory":"Management & Consulting",
            "type":"Services"
        }
    ],
    "sg:phone":"+1 724 564 4770",
    "sg:postcode":"15436",
    "sg:province":"PA",
    "sg:tags":[
        "consultant",
        "resource",
        "human"
    ],
    "wof:name":"Hugh & Assoc",
    "wof:placetype":"venue"
},
  "geometry": {"coordinates":[-79.75802299999999,39.820884],"type":"Point"}
}