{
  "type": "Feature",
  "properties": {
    "addr:full":"4203 Lilac Ct Upper Gwynedd PA 19446",
    "addr:housenumber":"4203",
    "addr:postcode":"19446",
    "addr:street":"Lilac Ct Upper Gwynedd",
    "iso:country":"US",
    "sg:address":"4203 Lilac Ct",
    "sg:city":"Upper Gwynedd",
    "sg:classifiers":[
        {
            "category":"Health Services",
            "subcategory":"Doctor",
            "type":"Services"
        }
    ],
    "sg:phone":"+1 215 699 3064",
    "sg:postcode":"19446",
    "sg:province":"PA",
    "wof:name":"Yun Daniel MD",
    "wof:placetype":"venue"
},
  "geometry": {"coordinates":[-75.301463,40.200976],"type":"Point"}
}