{
  "type": "Feature",
  "properties": {
    "addr:full":"1080 John Brady Dr Muncy PA 17756",
    "addr:housenumber":"1080",
    "addr:postcode":"17756",
    "addr:street":"John Brady Dr Muncy",
    "iso:country":"US",
    "sg:address":"1080 John Brady Dr",
    "sg:city":"Muncy",
    "sg:classifiers":[
        {
            "category":"Social Services",
            "subcategory":"Child Care",
            "type":"Services"
        }
    ],
    "sg:phone":"+1 570 546 2849",
    "sg:postcode":"17756",
    "sg:province":"PA",
    "sg:tags":[
        "day"
    ],
    "wof:name":"Little Tykes Day Care",
    "wof:placetype":"venue"
},
  "geometry": {"coordinates":[-76.80354199999999,41.22628],"type":"Point"}
}