{
  "type": "Feature",
  "properties": {
    "iso:country":"US",
    "sg:address":"378 S Bellevue Ave",
    "sg:city":"Langhorne",
    "sg:classifiers":[
        {
            "category":"Retail",
            "subcategory":"Funeral Services",
            "type":"Services"
        }
    ],
    "sg:phone":"+1 215 757 3331",
    "sg:postcode":"19047",
    "sg:province":"PA",
    "wof:name":"Dunn-Givnish Funeral Home Inc",
    "wof:placetype":"venue"
},
  "geometry": {"coordinates":[-74.91834,40.171901],"type":"Point"}
}