{
  "type": "Feature",
  "properties": {
    "iso:country":"US",
    "sg:address":"5092 Jonestown Rd",
    "sg:city":"Harrisburg",
    "sg:classifiers":[
        {
            "category":"Home & Garden",
            "subcategory":"Home Furnishings",
            "type":"Retail Goods"
        }
    ],
    "sg:phone":"+1 717 540 5156",
    "sg:postcode":"17112",
    "sg:province":"PA",
    "sg:tags":[
        "furniture"
    ],
    "wof:name":"Four Seasons Fireplace & Patio",
    "wof:placetype":"venue"
},
  "geometry": {"coordinates":[-76.803027,40.309737],"type":"Point"}
}