{
  "type": "Feature",
  "properties": {
    "iso:country":"US",
    "sg:address":"184 Plank Rd",
    "sg:city":"Somerset",
    "sg:classifiers":[
        {
            "category":"Professional",
            "subcategory":"Business Services",
            "type":"Services"
        }
    ],
    "sg:phone":"+1 814 443 3960",
    "sg:postcode":"15501",
    "sg:province":"PA",
    "sg:tags":[
        "interior",
        "consultant",
        "designer",
        "design",
        "decorator"
    ],
    "wof:name":"Hearth & Home Of Somerset",
    "wof:placetype":"venue"
},
  "geometry": {"coordinates":[-79.06605399999999,40.004566],"type":"Point"}
}