{
  "type": "Feature",
  "properties": {
    "iso:country":"US",
    "sg:address":"6275 Maxheimer Rd",
    "sg:city":"Saint Thomas",
    "sg:classifiers":[
        {
            "category":"Farming",
            "subcategory":"Dairy Farm",
            "type":"Manufacturing & Wholesale Goods"
        }
    ],
    "sg:phone":"+1   ",
    "sg:postcode":"17252",
    "sg:province":"PA",
    "wof:name":"Samuel Yoder",
    "wof:placetype":"venue"
},
  "geometry": {"coordinates":[-77.77714,39.93423],"type":"Point"}
}