{
  "type": "Feature",
  "properties": {
    "addr:full":"3109 N Front St Harrisburg PA 17110",
    "addr:housenumber":"3109",
    "addr:postcode":"17110",
    "addr:street":"N Front St",
    "iso:country":"US",
    "sg:address":"3109 N Front St",
    "sg:city":"Harrisburg",
    "sg:classifiers":[
        {
            "category":"Professional",
            "subcategory":"Lawyer & Legal Services",
            "type":"Services"
        }
    ],
    "sg:phone":"+1 717 920 5402",
    "sg:postcode":"17110",
    "sg:province":"PA",
    "sg:tags":[
        "attorney"
    ],
    "wof:name":"Harold E Dunbar Atty At Law",
    "wof:placetype":"venue"
},
  "geometry": {"coordinates":[-76.904532,40.298377],"type":"Point"}
}