{
  "type": "Feature",
  "properties": {
    "addr:full":"118 Dickerson Rd Ste C North Wales PA 19454",
    "addr:housenumber":"118",
    "addr:postcode":"19454",
    "addr:street":"Dickerson Rd Ste C",
    "iso:country":"US",
    "sg:address":"118 Dickerson Rd Ste C",
    "sg:city":"North Wales",
    "sg:classifiers":[
        {
            "category":"Health Services",
            "subcategory":"Chiropractor",
            "type":"Services"
        }
    ],
    "sg:phone":"+1 215 661 8533",
    "sg:postcode":"19454",
    "sg:province":"PA",
    "wof:name":"Portolese Tammy L DC",
    "wof:placetype":"venue"
},
  "geometry": {"coordinates":[-75.28830499999999,40.215552],"type":"Point"}
}