{
  "type": "Feature",
  "properties": {
    "iso:country":"US",
    "sg:address":"3890 Barachel Dr",
    "sg:city":"York",
    "sg:classifiers":[
        {
            "category":"Building & Trades",
            "subcategory":"Construction",
            "type":"Services"
        },
        {
            "category":"Manufacturing",
            "subcategory":"Building Materials",
            "type":"Manufacturing & Wholesale Goods"
        }
    ],
    "sg:phone":"+1 717 755 9248",
    "sg:postcode":"17402",
    "sg:province":"PA",
    "sg:tags":[
        "roofing",
        "sheet",
        "work",
        "metal",
        "contractor",
        "siding"
    ],
    "wof:name":"Stough Contracting, Inc.",
    "wof:placetype":"venue"
},
  "geometry": {"coordinates":[-76.641678,39.966179],"type":"Point"}
}