{
  "type": "Feature",
  "properties": {
    "addr:full":"100 Industrial Way Scottdale PA 15683",
    "addr:housenumber":"100",
    "addr:postcode":"15683",
    "addr:street":"Industrial Way",
    "iso:country":"US",
    "sg:address":"100 Industrial Way",
    "sg:city":"Scottdale",
    "sg:classifiers":[
        {
            "category":"Local Transit",
            "type":"Transportation"
        }
    ],
    "sg:phone":"+1 724 887 6822",
    "sg:postcode":"15683",
    "sg:province":"PA",
    "sg:tags":[
        "passenger"
    ],
    "sg:website":"www.speclin.net",
    "wof:name":"Speclin Inc",
    "wof:placetype":"venue"
},
  "geometry": {"coordinates":[-79.586708,40.099935],"type":"Point"}
}