{
  "type": "Feature",
  "properties": {
    "iso:country":"US",
    "sg:address":"555 S 2nd St",
    "sg:city":"Chambersburg",
    "sg:classifiers":[
        {
            "category":"Professional",
            "type":"Services"
        }
    ],
    "sg:phone":"+1   ",
    "sg:postcode":"17201",
    "sg:province":"PA",
    "wof:name":"Herman G Wishard",
    "wof:placetype":"venue"
},
  "geometry": {"coordinates":[-77.661057,39.928902],"type":"Point"}
}