{
  "type": "Feature",
  "properties": {
    "iso:country":"US",
    "sg:address":"439 Hollars Ext",
    "sg:city":"Everett",
    "sg:classifiers":[
        {
            "category":"Transit Center",
            "subcategory":"Freight",
            "type":"Transportation"
        },
        {
            "category":"Freight",
            "type":"Transportation"
        }
    ],
    "sg:phone":"+1 814 652 0071",
    "sg:postcode":"15537",
    "sg:province":"PA",
    "sg:tags":[
        "local",
        "trucking-motor",
        "trucking"
    ],
    "wof:name":"Mw Hillegas Trucking",
    "wof:placetype":"venue"
},
  "geometry": {"coordinates":[-78.378471,40.0045],"type":"Point"}
}