{
  "type": "Feature",
  "properties": {
    "iso:country":"US",
    "sg:address":"350 Brooke Dr",
    "sg:city":"Royersford",
    "sg:classifiers":[
        {
            "category":"Real Estate",
            "subcategory":"Real Estate Operator",
            "type":"Services"
        }
    ],
    "sg:phone":"+1 610 948 6850",
    "sg:postcode":"19468",
    "sg:province":"PA",
    "sg:tags":[
        "apartment"
    ],
    "sg:website":"www.walnutcrossing.com",
    "wof:name":"Walnut Crossing Apartments",
    "wof:placetype":"venue"
},
  "geometry": {"coordinates":[-75.522209,40.19871],"type":"Point"}
}