{
  "type": "Feature",
  "properties": {
    "iso:country":"US",
    "sg:address":"174 Cowpath Rd",
    "sg:city":"Souderton",
    "sg:classifiers":[
        {
            "category":"Utilities",
            "subcategory":"Sewage",
            "type":"Services"
        }
    ],
    "sg:phone":"+1   ",
    "sg:postcode":"18964",
    "sg:province":"PA",
    "sg:tags":[
        "executive",
        "system",
        "sewerage"
    ],
    "wof:name":"Souderton Waste Water Treatmnt",
    "wof:placetype":"venue"
},
  "geometry": {"coordinates":[-75.33083499999999,40.296225],"type":"Point"}
}