{
  "type": "Feature",
  "properties": {
    "addr:full":"211 E Euclid Ave New Castle PA 16105",
    "addr:housenumber":"211",
    "addr:postcode":"16105",
    "addr:street":"E Euclid Ave",
    "iso:country":"US",
    "sg:address":"211 E Euclid Ave",
    "sg:city":"New Castle",
    "sg:classifiers":[
        {
            "category":"Building & Trades",
            "subcategory":"Construction",
            "type":"Services"
        }
    ],
    "sg:phone":"+1   ",
    "sg:postcode":"16105",
    "sg:province":"PA",
    "sg:tags":[
        "house"
    ],
    "wof:name":"Modular Homes Accessories Corp",
    "wof:placetype":"venue"
},
  "geometry": {"coordinates":[-80.34112,41.016253],"type":"Point"}
}