{
  "type": "Feature",
  "properties": {
    "iso:country":"US",
    "sg:address":"1095 Park Ave",
    "sg:city":"Waynesburg",
    "sg:classifiers":[
        {
            "category":"Professional",
            "subcategory":"Computer Services",
            "type":"Services"
        }
    ],
    "sg:phone":"+1 724 852 4041",
    "sg:postcode":"15370",
    "sg:province":"PA",
    "sg:tags":[
        "repair"
    ],
    "wof:name":"Burns Computer Repair",
    "wof:placetype":"venue"
},
  "geometry": {"coordinates":[-80.155416,39.895043],"type":"Point"}
}