{
  "type": "Feature",
  "properties": {
    "iso:country":"US",
    "sg:address":"257 Main St",
    "sg:city":"Roaring Spring",
    "sg:classifiers":[
        {
            "category":"Shopping",
            "subcategory":"Used Merchandise",
            "type":"Retail Goods"
        }
    ],
    "sg:phone":"+1 814 224 4804",
    "sg:postcode":"16673",
    "sg:province":"PA",
    "sg:tags":[
        "shop",
        "consignment"
    ],
    "wof:name":"B & G Resale & Consignment",
    "wof:placetype":"venue"
},
  "geometry": {"coordinates":[-78.40465500000001,40.337331],"type":"Point"}
}