{
  "type": "Feature",
  "properties": {
    "iso:country":"US",
    "sg:address":"407 Clay Ave",
    "sg:city":"Jeannette",
    "sg:classifiers":[
        {
            "category":"Restaurant",
            "type":"Food & Drink"
        }
    ],
    "sg:menulink":"http://www.allmenus.com/pa/jeannette/286667-the-nest/menu/",
    "sg:phone":"+1 724 527 9880",
    "sg:postcode":"15644",
    "sg:province":"PA",
    "sg:tags":[
        "seafood",
        "steakhouse",
        "american"
    ],
    "wof:name":"The Nest",
    "wof:placetype":"venue"
},
  "geometry": {"coordinates":[-79.61771299999999,40.327181],"type":"Point"}
}