{
  "type": "Feature",
  "properties": {
    "iso:country":"US",
    "sg:address":"1604 State Rte 8",
    "sg:city":"Oil City",
    "sg:classifiers":[
        {
            "category":"Bars & Pubs",
            "type":"Food & Drink"
        }
    ],
    "sg:phone":"+1 814 677 0809",
    "sg:postcode":"16301",
    "sg:province":"PA",
    "wof:name":"Sportsman's Tavern",
    "wof:placetype":"venue"
},
  "geometry": {"coordinates":[-79.701639,41.501194],"type":"Point"}
}