{
  "type": "Feature",
  "properties": {
    "iso:country":"US",
    "sg:address":"1660 S Market St",
    "sg:city":"Elizabethtown",
    "sg:classifiers":[
        {
            "category":"Restaurant",
            "type":"Food & Drink"
        }
    ],
    "sg:phone":"+1   ",
    "sg:postcode":"17022",
    "sg:province":"PA",
    "sg:tags":[
        "eating"
    ],
    "wof:name":"Wendys",
    "wof:placetype":"venue"
},
  "geometry": {"coordinates":[-76.581678,40.136926],"type":"Point"}
}