{
  "type": "Feature",
  "properties": {
    "iso:country":"US",
    "sg:address":"450 Philadelphia Ave",
    "sg:city":"Reading",
    "sg:classifiers":[
        {
            "category":"Social Services",
            "subcategory":"Job Training",
            "type":"Services"
        }
    ],
    "sg:phone":"+1 610 796 8630",
    "sg:postcode":"19607",
    "sg:province":"PA",
    "sg:tags":[
        "rehabilitation"
    ],
    "wof:name":"Genesis Elder Care Rehab",
    "wof:placetype":"venue"
},
  "geometry": {"coordinates":[-75.96225699999999,40.301166],"type":"Point"}
}