{
  "type": "Feature",
  "properties": {
    "addr:full":"1216 E Hunting Park Ave Philadelphia PA 19124",
    "addr:housenumber":"1216",
    "addr:postcode":"19124",
    "addr:street":"E Hunting Park Ave",
    "iso:country":"US",
    "sg:address":"1216 E Hunting Park Ave",
    "sg:city":"Philadelphia",
    "sg:classifiers":[
        {
            "category":"Health Services",
            "subcategory":"Doctor",
            "type":"Services"
        }
    ],
    "sg:phone":"+1 215 533 1333",
    "sg:postcode":"19124",
    "sg:province":"PA",
    "sg:tags":[
        "family"
    ],
    "wof:name":"Complete Physicians Services Ltd",
    "wof:placetype":"venue"
},
  "geometry": {"coordinates":[-75.1035,40.010799],"type":"Point"}
}