{
  "type": "Feature",
  "properties": {
    "iso:country":"US",
    "sg:address":"501 E Baltimore Pike",
    "sg:city":"West Grove",
    "sg:classifiers":[
        {
            "category":"Professional",
            "subcategory":"Lawyer & Legal Services",
            "type":"Services"
        }
    ],
    "sg:phone":"+1 610 869 6283",
    "sg:postcode":"19390",
    "sg:province":"PA",
    "wof:name":"D'onofrio Anthony W Attorney",
    "wof:placetype":"venue"
},
  "geometry": {"coordinates":[-75.799301,39.8339],"type":"Point"}
}