{
  "type": "Feature",
  "properties": {
    "addr:full":"135 N Ridge Rd Reinholds PA 17569",
    "addr:housenumber":"135",
    "addr:postcode":"17569",
    "addr:street":"N Ridge Rd",
    "iso:country":"US",
    "sg:address":"135 N Ridge Rd",
    "sg:city":"Reinholds",
    "sg:classifiers":[
        {
            "category":"Professional",
            "subcategory":"Business Services",
            "type":"Services"
        }
    ],
    "sg:phone":"+1   ",
    "sg:postcode":"17569",
    "sg:province":"PA",
    "wof:name":"Critical Design Associates",
    "wof:placetype":"venue"
},
  "geometry": {"coordinates":[-76.105923,40.267801],"type":"Point"}
}