{
  "type": "Feature",
  "properties": {
    "iso:country":"US",
    "sg:address":"43 Cadwalader Ct",
    "sg:city":"Ambler",
    "sg:classifiers":[
        {
            "category":"Shopping",
            "subcategory":"Jewelry",
            "type":"Retail Goods"
        }
    ],
    "sg:phone":"+1   ",
    "sg:postcode":"19002",
    "sg:province":"PA",
    "wof:name":"Jen Rothbard Jewelry",
    "wof:placetype":"venue"
},
  "geometry": {"coordinates":[-75.238472,40.189685],"type":"Point"}
}