{
  "type": "Feature",
  "properties": {
    "addr:full":"501 Grant St Pittsburgh PA 15219",
    "addr:housenumber":"501",
    "addr:postcode":"15219",
    "addr:street":"Grant St",
    "iso:country":"US",
    "sg:address":"501 Grant St",
    "sg:city":"Pittsburgh",
    "sg:classifiers":[
        {
            "category":"Health Services",
            "subcategory":"Doctor",
            "type":"Services"
        }
    ],
    "sg:phone":"+1 412 577 2980",
    "sg:postcode":"15219",
    "sg:province":"PA",
    "sg:tags":[
        "physician",
        "surgeon"
    ],
    "wof:name":"Medical Legal Reproductions",
    "wof:placetype":"venue"
},
  "geometry": {"coordinates":[-79.99638899999999,40.440124],"type":"Point"}
}