{
  "type": "Feature",
  "properties": {
    "iso:country":"US",
    "sg:address":"720 Red Oak Ter",
    "sg:city":"Wayne",
    "sg:classifiers":[
        {
            "category":"Banks & Credit Unions",
            "subcategory":"Bank",
            "type":"Services"
        }
    ],
    "sg:phone":"+1   ",
    "sg:postcode":"19087",
    "sg:province":"PA",
    "sg:tags":[
        "mortgage"
    ],
    "wof:name":"Alternative Funding Associates",
    "wof:placetype":"venue"
},
  "geometry": {"coordinates":[-75.378454,40.070733],"type":"Point"}
}