{
  "type": "Feature",
  "properties": {
    "iso:country":"US",
    "sg:address":"121 Domorah Dr",
    "sg:city":"Montgomeryville",
    "sg:classifiers":[
        {
            "category":"Manufacturing",
            "subcategory":"Metals",
            "type":"Manufacturing & Wholesale Goods"
        }
    ],
    "sg:phone":"+1 215 540 9797",
    "sg:postcode":"18936",
    "sg:province":"PA",
    "sg:tags":[
        "wire"
    ],
    "sg:website":"www.deltadpa.com",
    "wof:name":"Delta Precision Alloys",
    "wof:placetype":"venue"
},
  "geometry": {"coordinates":[-75.22708799999999,40.224617],"type":"Point"}
}