{
  "type": "Feature",
  "properties": {
    "iso:country":"US",
    "sg:address":"1685 McFarland Rd",
    "sg:city":"Pittsburgh",
    "sg:classifiers":[
        {
            "category":"Home & Garden",
            "subcategory":"Garden Supply",
            "type":"Retail Goods"
        },
        {
            "category":"Shopping",
            "subcategory":"Florist",
            "type":"Retail Goods"
        }
    ],
    "sg:phone":"+1 412 563 7008",
    "sg:postcode":"15216",
    "sg:province":"PA",
    "sg:tags":[
        "nursery",
        "gardening"
    ],
    "sg:website":"www.thebotanicalemporium.com/",
    "wof:name":"The Botanical Emporium Florist & Greenhouse",
    "wof:placetype":"venue"
},
  "geometry": {"coordinates":[-80.0466,40.395802],"type":"Point"}
}