{
  "type": "Feature",
  "properties": {
    "addr:full":"1119 Walnut St Philadelphia PA 19107",
    "addr:housenumber":"1119",
    "addr:postcode":"19107",
    "addr:street":"Walnut St",
    "iso:country":"US",
    "sg:address":"1119 Walnut St",
    "sg:city":"Philadelphia",
    "sg:classifiers":[
        {
            "category":"Restaurant",
            "type":"Food & Drink"
        }
    ],
    "sg:menulink":"http://www.allmenus.com/pa/philadelphia/261813-new-heaven/menu/",
    "sg:phone":"+1 215 940 8855",
    "sg:postcode":"19107",
    "sg:province":"PA",
    "wof:name":"New Heaven",
    "wof:placetype":"venue"
},
  "geometry": {"coordinates":[-75.15986100000001,39.948874],"type":"Point"}
}