{
  "type": "Feature",
  "properties": {
    "addr:full":"851 Mifflin St West Mifflin PA 15122",
    "addr:housenumber":"851",
    "addr:postcode":"15122",
    "addr:street":"Mifflin St",
    "iso:country":"US",
    "sg:address":"851 Mifflin St",
    "sg:city":"West Mifflin",
    "sg:classifiers":[
        {
            "category":"Organizations",
            "subcategory":"Religious Organization",
            "type":"Services"
        }
    ],
    "sg:phone":"+1 412 461 1133",
    "sg:postcode":"15122",
    "sg:province":"PA",
    "sg:tags":[
        "church"
    ],
    "wof:name":"Lincoln Park Nazarene Church",
    "wof:placetype":"venue"
},
  "geometry": {"coordinates":[-79.85451999999999,40.36135],"type":"Point"}
}