{
  "type": "Feature",
  "properties": {
    "addr:full":"2759 Scullton Rd Rockwood PA 15557",
    "addr:housenumber":"2759",
    "addr:postcode":"15557",
    "addr:street":"Scullton Rd",
    "iso:country":"US",
    "sg:address":"2759 Scullton Rd",
    "sg:city":"Rockwood",
    "sg:classifiers":[
        {
            "category":"Autos & Motor Vehicles",
            "subcategory":"Fuel & Gas Station",
            "type":"Retail Goods"
        }
    ],
    "sg:phone":"+1 814 926 3080",
    "sg:postcode":"15557",
    "sg:province":"PA",
    "sg:tags":[
        "station",
        "gasoline"
    ],
    "wof:name":"New Lexington Market",
    "wof:placetype":"venue"
},
  "geometry": {"coordinates":[-79.237837,39.937454],"type":"Point"}
}