{
  "type": "Feature",
  "properties": {
    "iso:country":"US",
    "sg:address":"2104 Foxmeadow Dr",
    "sg:city":"Royersford",
    "sg:classifiers":[
        {
            "category":"Professional",
            "type":"Services"
        }
    ],
    "sg:phone":"+1 610 792 3392",
    "sg:postcode":"19468",
    "sg:province":"PA",
    "sg:tags":[
        "establishment"
    ],
    "wof:name":"Crown Network Systems Inc",
    "wof:placetype":"venue"
},
  "geometry": {"coordinates":[-75.534919,40.200967],"type":"Point"}
}