{
  "type": "Feature",
  "properties": {
    "iso:country":"US",
    "sg:address":"300 S Hanson St",
    "sg:city":"Philadelphia",
    "sg:classifiers":[
        {
            "category":"Sports & Exercise",
            "subcategory":"Swimming Pool",
            "type":"Entertainment"
        }
    ],
    "sg:phone":"+1 215 471 7665",
    "sg:postcode":"19143",
    "sg:province":"PA",
    "sg:tags":[
        "diving"
    ],
    "sg:website":"www.ucswimc.org/",
    "wof:name":"University City Swim Club",
    "wof:placetype":"venue"
},
  "geometry": {"coordinates":[-75.21946199999999,39.953241],"type":"Point"}
}