{
  "type": "Feature",
  "properties": {
    "addr:full":"1124 Kenebec Dr Chambersburg PA 17201",
    "addr:housenumber":"1124",
    "addr:postcode":"17201",
    "addr:street":"Kenebec Dr",
    "iso:country":"US",
    "sg:address":"1124 Kenebec Dr",
    "sg:city":"Chambersburg",
    "sg:classifiers":[
        {
            "category":"Health Services",
            "subcategory":"Chiropractor",
            "type":"Services"
        }
    ],
    "sg:phone":"+1 717 263 8919",
    "sg:postcode":"17201",
    "sg:province":"PA",
    "wof:name":"Madeira Chiropractic Office",
    "wof:placetype":"venue"
},
  "geometry": {"coordinates":[-77.6407,39.92628],"type":"Point"}
}