{
  "type": "Feature",
  "properties": {
    "iso:country":"US",
    "sg:address":"1301 Walnut St",
    "sg:city":"Philadelphia",
    "sg:classifiers":[
        {
            "category":"Organizations",
            "subcategory":"Membership Organization",
            "type":"Services"
        }
    ],
    "sg:phone":"+1 215 735 5924",
    "sg:postcode":"19107",
    "sg:province":"PA",
    "sg:tags":[
        "club",
        "private"
    ],
    "wof:name":"The Philadelphia Club",
    "wof:placetype":"venue"
},
  "geometry": {"coordinates":[-75.162102,39.949089],"type":"Point"}
}