{
  "type": "Feature",
  "properties": {
    "iso:country":"US",
    "sg:address":"5875 Stoneberry Way",
    "sg:city":"Riegelsville",
    "sg:classifiers":[
        {
            "category":"Farming",
            "subcategory":"Livestock Farm",
            "type":"Manufacturing & Wholesale Goods"
        }
    ],
    "sg:phone":"+1   ",
    "sg:postcode":"18077",
    "sg:province":"PA",
    "sg:tags":[
        "specialty",
        "animal"
    ],
    "wof:name":"King Apiaries Inc",
    "wof:placetype":"venue"
},
  "geometry": {"coordinates":[-75.25055399999999,40.542938],"type":"Point"}
}