{
  "type": "Feature",
  "properties": {
    "addr:full":"1601 Easton Rd Willow Grove PA 19090",
    "addr:housenumber":"1601",
    "addr:postcode":"19090",
    "addr:street":"Easton Rd",
    "iso:country":"US",
    "sg:address":"1601 Easton Rd",
    "sg:city":"Willow Grove",
    "sg:classifiers":[
        {
            "category":"Autos & Motor Vehicles",
            "subcategory":"Automobile Sales",
            "type":"Retail Goods"
        }
    ],
    "sg:phone":"+1 215 887 1800",
    "sg:postcode":"19090",
    "sg:province":"PA",
    "sg:tags":[
        "car",
        "dealer"
    ],
    "wof:name":"Sussman Acura",
    "wof:placetype":"venue"
},
  "geometry": {"coordinates":[-75.12444499999999,40.133815],"type":"Point"}
}