{
  "type": "Feature",
  "properties": {
    "addr:full":"476 New Elm St Conshohocken PA 19428",
    "addr:housenumber":"476",
    "addr:postcode":"19428",
    "addr:street":"New Elm St",
    "iso:country":"US",
    "sg:address":"476 New Elm St",
    "sg:city":"Conshohocken",
    "sg:classifiers":[
        {
            "category":"Building & Trades",
            "subcategory":"Pest Control",
            "type":"Services"
        }
    ],
    "sg:phone":"+1 610 828 2059",
    "sg:postcode":"19428",
    "sg:province":"PA",
    "sg:tags":[
        "industrial",
        "services-commercial",
        "termite"
    ],
    "sg:website":"http://www.chemicalexter.com",
    "wof:name":"z`The Chemical Exterminating Co Inc",
    "wof:placetype":"venue"
},
  "geometry": {"coordinates":[-75.314847,40.077915],"type":"Point"}
}