{
  "type": "Feature",
  "properties": {
    "iso:country":"US",
    "sg:address":"150 Monument Rd Ste 404",
    "sg:city":"Bala Cynwyd",
    "sg:classifiers":[
        {
            "category":"Professional",
            "subcategory":"Lawyer & Legal Services",
            "type":"Services"
        }
    ],
    "sg:phone":"+1 610 668 0255",
    "sg:postcode":"19004",
    "sg:province":"PA",
    "wof:name":"Verlin Mark A Attorney",
    "wof:placetype":"venue"
},
  "geometry": {"coordinates":[-75.216499,40.010399],"type":"Point"}
}