{
  "type": "Feature",
  "properties": {
    "addr:full":"8933 Krewstown Rd Philadelphia PA 19115",
    "addr:housenumber":"8933",
    "addr:postcode":"19115",
    "addr:street":"Krewstown Rd",
    "iso:country":"US",
    "sg:address":"8933 Krewstown Rd",
    "sg:city":"Philadelphia",
    "sg:classifiers":[
        {
            "category":"Wholesale",
            "subcategory":"Furniture",
            "type":"Manufacturing & Wholesale Goods"
        }
    ],
    "sg:phone":"+1   ",
    "sg:postcode":"19115",
    "sg:province":"PA",
    "wof:name":"Modern Expressions Inc",
    "wof:placetype":"venue"
},
  "geometry": {"coordinates":[-75.046164,40.086054],"type":"Point"}
}