{
  "type": "Feature",
  "properties": {
    "iso:country":"US",
    "sg:address":"5 Brookhill Sq S",
    "sg:city":"Sugarloaf",
    "sg:classifiers":[
        {
            "category":"Health Services",
            "subcategory":"Clinic",
            "type":"Services"
        }
    ],
    "sg:phone":"+1 570 788 0786",
    "sg:postcode":"18249",
    "sg:province":"PA",
    "sg:tags":[
        "home"
    ],
    "wof:name":"Visting Nurse Assn Home-Health",
    "wof:placetype":"venue"
},
  "geometry": {"coordinates":[-76.072215,40.995397],"type":"Point"}
}