{
  "type": "Feature",
  "properties": {
    "addr:full":"218 Beade St Plymouth PA 18651",
    "addr:housenumber":"218",
    "addr:postcode":"18651",
    "addr:street":"Beade St",
    "iso:country":"US",
    "sg:address":"218 Beade St",
    "sg:city":"Plymouth",
    "sg:classifiers":[
        {
            "category":"Utilities",
            "subcategory":"Fuel Oil & Lpg",
            "type":"Services"
        }
    ],
    "sg:phone":"+1 570 779 4605",
    "sg:postcode":"18651",
    "sg:province":"PA",
    "sg:tags":[
        "coal",
        "bottled",
        "gas",
        "anthracite"
    ],
    "wof:name":"Dundee Fuel Sales",
    "wof:placetype":"venue"
},
  "geometry": {"coordinates":[-75.93905700000001,41.240836],"type":"Point"}
}