{
  "type": "Feature",
  "properties": {
    "iso:country":"US",
    "sg:address":"120 Carol Ave",
    "sg:city":"Bridgeville",
    "sg:classifiers":[
        {
            "category":"Building & Trades",
            "subcategory":"Plumbing",
            "type":"Services"
        }
    ],
    "sg:phone":"+1 724 941 0902",
    "sg:postcode":"15017",
    "sg:province":"PA",
    "wof:name":"Yoest Plumbing Services",
    "wof:placetype":"venue"
},
  "geometry": {"coordinates":[-80.109854,40.361043],"type":"Point"}
}