{
  "type": "Feature",
  "properties": {
    "iso:country":"US",
    "sg:address":"2205 Oregon Pike",
    "sg:city":"Lancaster",
    "sg:classifiers":[
        {
            "category":"Government",
            "subcategory":"Office",
            "type":"Public Place"
        }
    ],
    "sg:phone":"+1 717 569 8774",
    "sg:postcode":"17601",
    "sg:province":"PA",
    "wof:name":"Honorable David P Miller",
    "wof:placetype":"venue"
},
  "geometry": {"coordinates":[-76.29279699999999,40.081532],"type":"Point"}
}