{
  "type": "Feature",
  "properties": {
    "iso:country":"US",
    "sg:address":"14 Big Spring Ter",
    "sg:city":"Newville",
    "sg:classifiers":[
        {
            "category":"Real Estate",
            "subcategory":"Real Estate Operator",
            "type":"Services"
        }
    ],
    "sg:phone":"+1 717 776 4862",
    "sg:postcode":"17241",
    "sg:province":"PA",
    "sg:tags":[
        "mobile",
        "home",
        "community"
    ],
    "wof:name":"Big Spring Terrace Mobile Home",
    "wof:placetype":"venue"
},
  "geometry": {"coordinates":[-77.394311,40.150958],"type":"Point"}
}