{
  "type": "Feature",
  "properties": {
    "addr:full":"210 E Main St Ligonier PA 15658",
    "addr:housenumber":"210",
    "addr:postcode":"15658",
    "addr:street":"E Main St",
    "iso:country":"US",
    "sg:address":"210 E Main St",
    "sg:city":"Ligonier",
    "sg:classifiers":[
        {
            "category":"Freight",
            "type":"Transportation"
        }
    ],
    "sg:phone":"+1 724 238 5672",
    "sg:postcode":"15658",
    "sg:province":"PA",
    "sg:tags":[
        "trucking"
    ],
    "wof:name":"Cougar Trucking Inc",
    "wof:placetype":"venue"
},
  "geometry": {"coordinates":[-79.236276,40.242129],"type":"Point"}
}