{
  "type": "Feature",
  "properties": {
    "iso:country":"US",
    "sg:address":"3572 Frankford Ave",
    "sg:city":"Philadelphia",
    "sg:classifiers":[
        {
            "category":"Banks & Credit Unions",
            "subcategory":"Bank",
            "type":"Services"
        }
    ],
    "sg:phone":"+1 215 744 7215",
    "sg:postcode":"19134",
    "sg:province":"PA",
    "sg:tags":[
        "cashing",
        "check"
    ],
    "wof:name":"Don's Check Cashing",
    "wof:placetype":"venue"
},
  "geometry": {"coordinates":[-75.101342,39.998196],"type":"Point"}
}