{
  "type": "Feature",
  "properties": {
    "addr:full":"909 Concord Ave Drexel Hill PA 19026",
    "addr:housenumber":"909",
    "addr:postcode":"19026",
    "addr:street":"Concord Ave",
    "iso:country":"US",
    "sg:address":"909 Concord Ave",
    "sg:city":"Drexel Hill",
    "sg:classifiers":[
        {
            "category":"Building & Trades",
            "subcategory":"Electrical",
            "type":"Services"
        }
    ],
    "sg:phone":"+1   ",
    "sg:postcode":"19026",
    "sg:province":"PA",
    "sg:tags":[
        "electrical",
        "contractor"
    ],
    "wof:name":"Bianco Electric",
    "wof:placetype":"venue"
},
  "geometry": {"coordinates":[-75.306742,39.956186],"type":"Point"}
}