{
  "type": "Feature",
  "properties": {
    "iso:country":"US",
    "sg:address":"805 Walnut St",
    "sg:city":"Monongahela",
    "sg:classifiers":[
        {
            "category":"Manufacturing",
            "subcategory":"Building Materials",
            "type":"Manufacturing & Wholesale Goods"
        }
    ],
    "sg:phone":"+1   ",
    "sg:postcode":"15063",
    "sg:province":"PA",
    "sg:tags":[
        "mfg"
    ],
    "wof:name":"PC Woodworking",
    "wof:placetype":"venue"
},
  "geometry": {"coordinates":[-79.918874,40.190549],"type":"Point"}
}