{
  "type": "Feature",
  "properties": {
    "iso:country":"US",
    "sg:address":"615 W Mauch Chunk St",
    "sg:city":"Nazareth",
    "sg:classifiers":[
        {
            "category":"Building & Trades",
            "subcategory":"Landscaping Services",
            "type":"Services"
        }
    ],
    "sg:phone":"+1 610 759 7497",
    "sg:postcode":"18064",
    "sg:province":"PA",
    "sg:tags":[
        "landscape"
    ],
    "wof:name":"Prolific Landscape",
    "wof:placetype":"venue"
},
  "geometry": {"coordinates":[-75.323538,40.741077],"type":"Point"}
}