{
  "type": "Feature",
  "properties": {
    "iso:country":"US",
    "sg:address":"166 Horner Rd",
    "sg:city":"Somerset",
    "sg:classifiers":[
        {
            "category":"Home & Garden",
            "subcategory":"Building Materials",
            "type":"Retail Goods"
        }
    ],
    "sg:phone":"+1 814 443 2442",
    "sg:postcode":"15501",
    "sg:province":"PA",
    "sg:tags":[
        "glass",
        "window",
        "plate"
    ],
    "wof:name":"Diamond Auto Glass",
    "wof:placetype":"venue"
},
  "geometry": {"coordinates":[-79.153094,40.094429],"type":"Point"}
}