{
  "type": "Feature",
  "properties": {
    "iso:country":"US",
    "sg:address":"1040 Chestnut St",
    "sg:city":"Emmaus",
    "sg:classifiers":[
        {
            "category":"Health Services",
            "subcategory":"Health Practitioner",
            "type":"Services"
        },
        {
            "category":"Social Services",
            "type":"Services"
        }
    ],
    "sg:phone":"+1 610 966 5188",
    "sg:postcode":"18049",
    "sg:province":"PA",
    "sg:tags":[
        "psychologist"
    ],
    "wof:name":"Lehigh Psychological Services",
    "wof:placetype":"venue"
},
  "geometry": {"coordinates":[-75.505296,40.529203],"type":"Point"}
}