{
  "type": "Feature",
  "properties": {
    "addr:full":"6795 Honey Ln Erie PA 16509",
    "addr:housenumber":"6795",
    "addr:postcode":"16509",
    "addr:street":"Honey Ln",
    "iso:country":"US",
    "sg:address":"6795 Honey Ln",
    "sg:city":"Erie",
    "sg:classifiers":[
        {
            "category":"Wholesale",
            "subcategory":"Vending Machines",
            "type":"Manufacturing & Wholesale Goods"
        }
    ],
    "sg:phone":"+1 814 866 5556",
    "sg:postcode":"16509",
    "sg:province":"PA",
    "sg:tags":[
        "merchandise"
    ],
    "wof:name":"Big Handful Vending",
    "wof:placetype":"venue"
},
  "geometry": {"coordinates":[-80.06932,42.065632],"type":"Point"}
}