{
  "type": "Feature",
  "properties": {
    "iso:country":"US",
    "sg:address":"912 Almond St",
    "sg:city":"Williamsport",
    "sg:classifiers":[
        {
            "category":"Organizations",
            "subcategory":"Religious Organization",
            "type":"Services"
        }
    ],
    "sg:phone":"+1   ",
    "sg:postcode":"17701",
    "sg:province":"PA",
    "wof:name":"Saint Marys Episcopal Church",
    "wof:placetype":"venue"
},
  "geometry": {"coordinates":[-76.98732699999999,41.249165],"type":"Point"}
}