{
  "type": "Feature",
  "properties": {
    "iso:country":"US",
    "sg:address":"150 Green Valley Rd",
    "sg:city":"Reading",
    "sg:classifiers":[
        {
            "category":"Organizations",
            "subcategory":"Membership Organization",
            "type":"Services"
        }
    ],
    "sg:phone":"+1 610 678 8811",
    "sg:postcode":"19608",
    "sg:province":"PA",
    "sg:tags":[
        "club",
        "private"
    ],
    "wof:name":"Green Valley Country Club",
    "wof:placetype":"venue"
},
  "geometry": {"coordinates":[-76.038966,40.330795],"type":"Point"}
}