{
  "type": "Feature",
  "properties": {
    "addr:full":"329 S Main St Doylestown PA 18901",
    "addr:housenumber":"329",
    "addr:postcode":"18901",
    "addr:street":"S Main St",
    "iso:country":"US",
    "sg:address":"329 S Main St",
    "sg:city":"Doylestown",
    "sg:classifiers":[
        {
            "category":"Communications",
            "subcategory":"Newspaper",
            "type":"Services"
        }
    ],
    "sg:phone":"+1 215 340 9811",
    "sg:postcode":"18901",
    "sg:province":"PA",
    "sg:tags":[
        "print",
        "medium"
    ],
    "wof:name":"Doylestown Patriot",
    "wof:placetype":"venue"
},
  "geometry": {"coordinates":[-75.12850299999999,40.302136],"type":"Point"}
}