{
  "type": "Feature",
  "properties": {
    "iso:country":"US",
    "sg:address":"601 Dettmer Ln",
    "sg:city":"Northampton",
    "sg:classifiers":[
        {
            "category":"Building & Trades",
            "subcategory":"Electrical",
            "type":"Services"
        }
    ],
    "sg:phone":"+1 610 767 6540",
    "sg:postcode":"18067",
    "sg:province":"PA",
    "sg:tags":[
        "contractor",
        "electrical",
        "electric",
        "general"
    ],
    "wof:name":"ACS Electric Co",
    "wof:placetype":"venue"
},
  "geometry": {"coordinates":[-75.480784,40.76063],"type":"Point"}
}