{
  "type": "Feature",
  "properties": {
    "addr:full":"539 Fox Chase Rd Jenkintown PA 19046",
    "addr:housenumber":"539",
    "addr:postcode":"19046",
    "addr:street":"Fox Chase Rd",
    "iso:country":"US",
    "sg:address":"539 Fox Chase Rd",
    "sg:city":"Jenkintown",
    "sg:classifiers":[
        {
            "category":"Social Services",
            "subcategory":"Child Care",
            "type":"Services"
        }
    ],
    "sg:phone":"+1   ",
    "sg:postcode":"19046",
    "sg:province":"PA",
    "sg:tags":[
        "day"
    ],
    "wof:name":"Childrens Hour Day Care Center",
    "wof:placetype":"venue"
},
  "geometry": {"coordinates":[-75.094202,40.084495],"type":"Point"}
}