{
  "type": "Feature",
  "properties": {
    "iso:country":"US",
    "sg:address":"845 Main St",
    "sg:city":"Darby",
    "sg:classifiers":[
        {
            "category":"Government",
            "subcategory":"Office",
            "type":"Public Place"
        }
    ],
    "sg:phone":"+1 610 461 3800",
    "sg:postcode":"19023",
    "sg:province":"PA",
    "sg:tags":[
        "state",
        "resource"
    ],
    "wof:name":"Public Welfare Dept",
    "wof:placetype":"venue"
},
  "geometry": {"coordinates":[-75.260198,39.918239],"type":"Point"}
}