{
  "type": "Feature",
  "properties": {
    "iso:country":"US",
    "sg:address":"580 Oneida Valley Rd",
    "sg:city":"Butler",
    "sg:classifiers":[
        {
            "category":"Freight",
            "type":"Transportation"
        }
    ],
    "sg:phone":"+1 724 283 5585",
    "sg:postcode":"16001",
    "sg:province":"PA",
    "sg:tags":[
        "commercial",
        "storage"
    ],
    "wof:name":"Oneida Heights Storage",
    "wof:placetype":"venue"
},
  "geometry": {"coordinates":[-79.879127,40.921277],"type":"Point"}
}