{
  "type": "Feature",
  "properties": {
    "addr:full":"1541 Alta Dr Whitehall PA 18052",
    "addr:housenumber":"1541",
    "addr:postcode":"18052",
    "addr:street":"Alta Dr",
    "iso:country":"US",
    "sg:address":"1541 Alta Dr",
    "sg:city":"Whitehall",
    "sg:classifiers":[
        {
            "category":"Cinema",
            "subcategory":"Movie Rental",
            "type":"Entertainment"
        }
    ],
    "sg:phone":"+1   ",
    "sg:postcode":"18052",
    "sg:province":"PA",
    "sg:tags":[
        "video",
        "tape"
    ],
    "wof:name":"Blockbuster",
    "wof:placetype":"venue"
},
  "geometry": {"coordinates":[-75.48641499999999,40.627621],"type":"Point"}
}