{
  "type": "Feature",
  "properties": {
    "addr:full":"2724 E Allegheny Ave Philadelphia PA 19134",
    "addr:housenumber":"2724",
    "addr:postcode":"19134",
    "addr:street":"E Allegheny Ave",
    "iso:country":"US",
    "sg:address":"2724 E Allegheny Ave",
    "sg:city":"Philadelphia",
    "sg:classifiers":[
        {
            "category":"Retail",
            "subcategory":"Funeral Services",
            "type":"Services"
        }
    ],
    "sg:phone":"+1 215 739 6624",
    "sg:postcode":"19134",
    "sg:province":"PA",
    "sg:tags":[
        "cemetery"
    ],
    "wof:name":"Tomaszewski Edw C Inc",
    "wof:placetype":"venue"
},
  "geometry": {"coordinates":[-75.102097,39.983501],"type":"Point"}
}