{
  "type": "Feature",
  "properties": {
    "addr:full":"220 W Hamilton St Allentown PA 18101",
    "addr:housenumber":"220",
    "addr:postcode":"18101",
    "addr:street":"W Hamilton St",
    "iso:country":"US",
    "sg:address":"220 W Hamilton St",
    "sg:city":"Allentown",
    "sg:classifiers":[
        {
            "category":"Health Services",
            "subcategory":"Doctor",
            "type":"Services"
        }
    ],
    "sg:phone":"+1 610 433 7481",
    "sg:postcode":"18101",
    "sg:province":"PA",
    "sg:tags":[
        "medicine",
        "internal",
        "cardiologist"
    ],
    "wof:name":"Wilson Richd C Phys",
    "wof:placetype":"venue"
},
  "geometry": {"coordinates":[-75.460503,40.6054],"type":"Point"}
}