{
  "type": "Feature",
  "properties": {
    "iso:country":"US",
    "sg:address":"521 Wickshire Cir",
    "sg:city":"Lititz",
    "sg:classifiers":[
        {
            "category":"Personal",
            "subcategory":"Beauty Salon",
            "type":"Services"
        }
    ],
    "sg:phone":"+1 717 626 2403",
    "sg:postcode":"17543",
    "sg:province":"PA",
    "wof:name":"Bea's Beauty Patch",
    "wof:placetype":"venue"
},
  "geometry": {"coordinates":[-76.30758400000001,40.136161],"type":"Point"}
}