{
  "type": "Feature",
  "properties": {
    "iso:country":"US",
    "sg:address":"154 S Potomac St",
    "sg:city":"Waynesboro",
    "sg:classifiers":[
        {
            "category":"Professional",
            "subcategory":"Lawyer & Legal Services",
            "type":"Services"
        }
    ],
    "sg:phone":"+1 717 762 8689",
    "sg:postcode":"17268",
    "sg:province":"PA",
    "sg:tags":[
        "attorney"
    ],
    "wof:name":"Evelyn W Bradford",
    "wof:placetype":"venue"
},
  "geometry": {"coordinates":[-77.582042,39.754893],"type":"Point"}
}