{
  "type": "Feature",
  "properties": {
    "iso:country":"US",
    "sg:address":"448 Strayer St",
    "sg:city":"Johnstown",
    "sg:classifiers":[
        {
            "category":"Insurance",
            "subcategory":"Insurance Agent",
            "type":"Services"
        }
    ],
    "sg:phone":"+1 814 536 1500",
    "sg:postcode":"15906",
    "sg:province":"PA",
    "wof:name":"Dudek Insurance Agency",
    "wof:placetype":"venue"
},
  "geometry": {"coordinates":[-78.94860799999999,40.354431],"type":"Point"}
}