{
  "type": "Feature",
  "properties": {
    "iso:country":"US",
    "sg:address":"2822 W 10th St",
    "sg:city":"Chester",
    "sg:classifiers":[
        {
            "category":"Food & Beverages",
            "subcategory":"Liquor & Beverages",
            "type":"Retail Goods"
        },
        {
            "category":"Wholesale",
            "subcategory":"Beer",
            "type":"Manufacturing & Wholesale Goods"
        }
    ],
    "sg:phone":"+1   ",
    "sg:postcode":"19013",
    "sg:province":"PA",
    "sg:tags":[
        "alcoholic"
    ],
    "wof:name":"Mc Ginn Beer Distributors",
    "wof:placetype":"venue"
},
  "geometry": {"coordinates":[-75.397657,39.83625],"type":"Point"}
}