{
  "type": "Feature",
  "properties": {
    "iso:country":"US",
    "sg:address":"4029 William Penn Hwy",
    "sg:city":"Monroeville",
    "sg:classifiers":[
        {
            "category":"Travel",
            "subcategory":"Travel Agent",
            "type":"Entertainment"
        }
    ],
    "sg:phone":"+1 412 372 2900",
    "sg:postcode":"15146",
    "sg:province":"PA",
    "sg:tags":[
        "agency",
        "bureau"
    ],
    "wof:name":"Fairwind Travel Agency",
    "wof:placetype":"venue"
},
  "geometry": {"coordinates":[-79.773702,40.438264],"type":"Point"}
}