{
  "type": "Feature",
  "properties": {
    "addr:full":"104 S Market St Carmichaels PA 15320",
    "addr:housenumber":"104",
    "addr:postcode":"15320",
    "addr:street":"S Market St",
    "iso:country":"US",
    "sg:address":"104 S Market St",
    "sg:city":"Carmichaels",
    "sg:classifiers":[
        {
            "category":"Professional",
            "subcategory":"Business Services",
            "type":"Services"
        }
    ],
    "sg:phone":"+1 724 966 8653",
    "sg:postcode":"15320",
    "sg:province":"PA",
    "sg:tags":[
        "interior",
        "consultant",
        "design",
        "decorator"
    ],
    "wof:name":"Gideon's 300 Interior Dcrtn",
    "wof:placetype":"venue"
},
  "geometry": {"coordinates":[-79.974036,39.895755],"type":"Point"}
}