{
  "type": "Feature",
  "properties": {
    "addr:full":"247 W Long Ave Du Bois PA 15801",
    "addr:housenumber":"247",
    "addr:postcode":"15801",
    "addr:street":"W Long Ave Du Bois",
    "iso:country":"US",
    "sg:address":"247 W Long Ave",
    "sg:city":"Du Bois",
    "sg:classifiers":[
        {
            "category":"Insurance",
            "subcategory":"Insurance Agent",
            "type":"Services"
        }
    ],
    "sg:phone":"+1 814 375 0542",
    "sg:postcode":"15801",
    "sg:province":"PA",
    "wof:name":"Seniorcare Insurance",
    "wof:placetype":"venue"
},
  "geometry": {"coordinates":[-78.76511499999999,41.120934],"type":"Point"}
}