{
  "type": "Feature",
  "properties": {
    "iso:country":"US",
    "sg:address":"200 Airport Dr",
    "sg:city":"New Cumberland",
    "sg:classifiers":[
        {
            "category":"Professional",
            "subcategory":"Computer Services",
            "type":"Services"
        }
    ],
    "sg:phone":"+1 717 774 0709",
    "sg:postcode":"17070",
    "sg:province":"PA",
    "sg:tags":[
        "consultant",
        "designer"
    ],
    "sg:website":"www.isg4results.com",
    "wof:name":"Information Services Group Inc",
    "wof:placetype":"venue"
},
  "geometry": {"coordinates":[-76.85332699999999,40.211621],"type":"Point"}
}