{
  "type": "Feature",
  "properties": {
    "iso:country":"US",
    "sg:address":"833 Kennedy Dr",
    "sg:city":"Ambridge",
    "sg:classifiers":[
        {
            "category":"Shopping",
            "type":"Retail Goods"
        }
    ],
    "sg:phone":"+1 724 266 2885",
    "sg:postcode":"15003",
    "sg:province":"PA",
    "sg:tags":[
        "merchandise"
    ],
    "wof:name":"Distinctive Design Memorials",
    "wof:placetype":"venue"
},
  "geometry": {"coordinates":[-80.231483,40.589546],"type":"Point"}
}