{
  "type": "Feature",
  "properties": {
    "addr:full":"424 E Ridge St Nanticoke PA 18634",
    "addr:housenumber":"424",
    "addr:postcode":"18634",
    "addr:street":"E Ridge St",
    "iso:country":"US",
    "sg:address":"424 E Ridge St",
    "sg:city":"Nanticoke",
    "sg:classifiers":[
        {
            "category":"Building & Trades",
            "subcategory":"Cleaning & Sanitation",
            "type":"Services"
        }
    ],
    "sg:phone":"+1   ",
    "sg:postcode":"18634",
    "sg:province":"PA",
    "sg:tags":[
        "floor",
        "carpet"
    ],
    "wof:name":"Tri-City Floor Cleaning",
    "wof:placetype":"venue"
},
  "geometry": {"coordinates":[-75.993179,41.201961],"type":"Point"}
}