{
  "type": "Feature",
  "properties": {
    "iso:country":"US",
    "sg:address":"311 Elm St",
    "sg:city":"Pittston",
    "sg:classifiers":[
        {
            "category":"Manufacturing",
            "subcategory":"Tools & Machinery",
            "type":"Manufacturing & Wholesale Goods"
        }
    ],
    "sg:phone":"+1   ",
    "sg:postcode":"18641",
    "sg:province":"PA",
    "sg:tags":[
        "mfg",
        "repair",
        "industrial",
        "welding"
    ],
    "wof:name":"Valley Grinding & Mfg",
    "wof:placetype":"venue"
},
  "geometry": {"coordinates":[-75.740892,41.318763],"type":"Point"}
}