{
  "type": "Feature",
  "properties": {
    "iso:country":"US",
    "sg:address":"263 Brentwood Dr",
    "sg:city":"Cogan Station",
    "sg:classifiers":[
        {
            "category":"Building & Trades",
            "subcategory":"Construction",
            "type":"Services"
        }
    ],
    "sg:phone":"+1   ",
    "sg:postcode":"17728",
    "sg:province":"PA",
    "sg:tags":[
        "housing"
    ],
    "wof:name":"Hch Contractors",
    "wof:placetype":"venue"
},
  "geometry": {"coordinates":[-77.056584,41.309962],"type":"Point"}
}