{
  "type": "Feature",
  "properties": {
    "addr:full":"434 Columbus St Wernersville PA 19565",
    "addr:housenumber":"434",
    "addr:postcode":"19565",
    "addr:street":"Columbus St",
    "iso:country":"US",
    "sg:address":"434 Columbus St",
    "sg:city":"Wernersville",
    "sg:classifiers":[
        {
            "category":"Shopping",
            "type":"Retail Goods"
        }
    ],
    "sg:phone":"+1 610 927 0223",
    "sg:postcode":"19565",
    "sg:province":"PA",
    "sg:tags":[
        "merchandise"
    ],
    "wof:name":"Picture It Here Framery",
    "wof:placetype":"venue"
},
  "geometry": {"coordinates":[-76.08779699999999,40.325651],"type":"Point"}
}