{
  "type": "Feature",
  "properties": {
    "addr:full":"406 Lutz School Rd Indiana PA 15701",
    "addr:housenumber":"406",
    "addr:postcode":"15701",
    "addr:street":"School Rd",
    "iso:country":"US",
    "sg:address":"406 Lutz School Rd",
    "sg:city":"Indiana",
    "sg:classifiers":[
        {
            "category":"Home & Garden",
            "subcategory":"Mobile Homes",
            "type":"Retail Goods"
        }
    ],
    "sg:phone":"+1 724 463 3409",
    "sg:postcode":"15701",
    "sg:province":"PA",
    "sg:website":"www.longshomes.com",
    "wof:name":"Long's Homes & Rv Sales",
    "wof:placetype":"venue"
},
  "geometry": {"coordinates":[-79.107097,40.650423],"type":"Point"}
}