{
  "type": "Feature",
  "properties": {
    "addr:full":"230 N High St Duncannon PA 17020",
    "addr:housenumber":"230",
    "addr:postcode":"17020",
    "addr:street":"N High St",
    "iso:country":"US",
    "sg:address":"230 N High St",
    "sg:city":"Duncannon",
    "sg:classifiers":[
        {
            "category":"Retail",
            "subcategory":"Funeral Services",
            "type":"Services"
        }
    ],
    "sg:phone":"+1 717 834 9091",
    "sg:postcode":"17020",
    "sg:province":"PA",
    "sg:tags":[
        "director"
    ],
    "wof:name":"Boyer Funeral Home",
    "wof:placetype":"venue"
},
  "geometry": {"coordinates":[-77.029546,40.393763],"type":"Point"}
}