{
  "type": "Feature",
  "properties": {
    "addr:full":"365 6th Ave New Kensington PA 15068",
    "addr:housenumber":"365",
    "addr:postcode":"15068",
    "addr:street":"6Th Ave",
    "iso:country":"US",
    "sg:address":"365 6th Ave",
    "sg:city":"New Kensington",
    "sg:classifiers":[
        {
            "category":"Manufacturing",
            "subcategory":"Food",
            "type":"Manufacturing & Wholesale Goods"
        }
    ],
    "sg:phone":"+1   ",
    "sg:postcode":"15068",
    "sg:province":"PA",
    "sg:tags":[
        "beverage",
        "syrup",
        "mfg"
    ],
    "wof:name":"Pittsburgh Flavor Company",
    "wof:placetype":"venue"
},
  "geometry": {"coordinates":[-79.76154,40.55504],"type":"Point"}
}