{
  "type": "Feature",
  "properties": {
    "iso:country":"US",
    "sg:address":"3377 Aramingo Ave",
    "sg:city":"Philadelphia",
    "sg:classifiers":[
        {
            "category":"Restaurant",
            "type":"Food & Drink"
        },
        {
            "category":"Food & Beverages",
            "subcategory":"Groceries & Convenience Stores",
            "type":"Retail Goods"
        }
    ],
    "sg:phone":"+1 215 203 3100",
    "sg:postcode":"19134",
    "sg:province":"PA",
    "sg:tags":[
        "pretzel"
    ],
    "wof:name":"Philly Soft Pretzel Factory",
    "wof:placetype":"venue"
},
  "geometry": {"coordinates":[-75.10212199999999,39.990746],"type":"Point"}
}