{
  "type": "Feature",
  "properties": {
    "iso:country":"US",
    "sg:address":"148 Cricket Ave",
    "sg:city":"Ardmore",
    "sg:classifiers":[
        {
            "category":"Building & Trades",
            "subcategory":"Pest Control",
            "type":"Services"
        }
    ],
    "sg:phone":"+1 610 649 2999",
    "sg:postcode":"19003",
    "sg:province":"PA",
    "wof:name":"Main Line Exterminating Co",
    "wof:placetype":"venue"
},
  "geometry": {"coordinates":[-75.295905,40.005462],"type":"Point"}
}