{
  "type": "Feature",
  "properties": {
    "iso:country":"US",
    "sg:address":"1030 Pine St",
    "sg:city":"Philadelphia",
    "sg:classifiers":[
        {
            "category":"Shopping",
            "subcategory":"Antiques",
            "type":"Retail Goods"
        }
    ],
    "sg:phone":"+1 215 574 3633",
    "sg:postcode":"19107",
    "sg:province":"PA",
    "wof:name":"Biber Jeffery L",
    "wof:placetype":"venue"
},
  "geometry": {"coordinates":[-75.158997,39.945],"type":"Point"}
}