{
  "type": "Feature",
  "properties": {
    "iso:country":"US",
    "sg:address":"6425 Eastwood St",
    "sg:city":"Philadelphia",
    "sg:classifiers":[
        {
            "category":"Building & Trades",
            "subcategory":"Plumbing",
            "type":"Services"
        }
    ],
    "sg:phone":"+1 215 743 6293",
    "sg:postcode":"19149",
    "sg:province":"PA",
    "sg:tags":[
        "contractor"
    ],
    "wof:name":"Vargas Heating & Cooling",
    "wof:placetype":"venue"
},
  "geometry": {"coordinates":[-75.070764,40.0372],"type":"Point"}
}