{
  "type": "Feature",
  "properties": {
    "addr:full":"425 Cochran Rd Mt Lebanon PA 15228",
    "addr:housenumber":"425",
    "addr:postcode":"15228",
    "addr:street":"Cochran Rd",
    "iso:country":"US",
    "sg:address":"425 Cochran Rd",
    "sg:city":"Mt Lebanon",
    "sg:classifiers":[
        {
            "category":"Professional",
            "subcategory":"Lawyer & Legal Services",
            "type":"Services"
        }
    ],
    "sg:phone":"+1 412 531 7004",
    "sg:postcode":"15228",
    "sg:province":"PA",
    "sg:tags":[
        "attorney"
    ],
    "wof:name":"William Winschel",
    "wof:placetype":"venue"
},
  "geometry": {"coordinates":[-80.052548,40.382945],"type":"Point"}
}