{
  "type": "Feature",
  "properties": {
    "addr:full":"624 Library Ave Carnegie PA 15106",
    "addr:housenumber":"624",
    "addr:postcode":"15106",
    "addr:street":"Library Ave",
    "iso:country":"US",
    "sg:address":"624 Library Ave",
    "sg:city":"Carnegie",
    "sg:classifiers":[
        {
            "category":"Arts & Performance",
            "subcategory":"Theater",
            "type":"Entertainment"
        }
    ],
    "sg:phone":"+1 412 276 7464",
    "sg:postcode":"15106",
    "sg:province":"PA",
    "sg:tags":[
        "karaoke"
    ],
    "wof:name":"Diamond Head Kareoke Special",
    "wof:placetype":"venue"
},
  "geometry": {"coordinates":[-80.086173,40.402874],"type":"Point"}
}