{
  "type": "Feature",
  "properties": {
    "iso:country":"US",
    "sg:address":"424 Pike Rd",
    "sg:city":"Huntingdon Vly",
    "sg:classifiers":[
        {
            "category":"Professional",
            "subcategory":"Management & Consulting",
            "type":"Services"
        }
    ],
    "sg:phone":"+1 215 942 0501",
    "sg:postcode":"19006",
    "sg:province":"PA",
    "sg:tags":[
        "marketing",
        "program"
    ],
    "wof:name":"Delaware Valley Mktng Assoc",
    "wof:placetype":"venue"
},
  "geometry": {"coordinates":[-75.02238,40.146203],"type":"Point"}
}