{
  "type": "Feature",
  "properties": {
    "iso:country":"US",
    "sg:address":"1157 Eichelberger St",
    "sg:city":"Hanover",
    "sg:classifiers":[
        {
            "category":"Social Services",
            "type":"Services"
        }
    ],
    "sg:phone":"+1 717 637 6100",
    "sg:postcode":"17331",
    "sg:province":"PA",
    "sg:tags":[
        "organization",
        "welfare"
    ],
    "wof:name":"Life Skills Unlimited",
    "wof:placetype":"venue"
},
  "geometry": {"coordinates":[-76.99261300000001,39.823221],"type":"Point"}
}