{
  "type": "Feature",
  "properties": {
    "iso:country":"US",
    "sg:address":"449 N 3rd St",
    "sg:city":"Oxford",
    "sg:classifiers":[
        {
            "category":"Personal",
            "subcategory":"Tanning Parlor",
            "type":"Services"
        }
    ],
    "sg:phone":"+1 610 932 0166",
    "sg:postcode":"19363",
    "sg:province":"PA",
    "sg:tags":[
        "salon"
    ],
    "wof:name":"Leisure Tanz",
    "wof:placetype":"venue"
},
  "geometry": {"coordinates":[-75.976902,39.79417],"type":"Point"}
}