{
  "type": "Feature",
  "properties": {
    "addr:full":"2900 S 61st St Philadelphia PA 19142",
    "addr:housenumber":"2900",
    "addr:postcode":"19142",
    "addr:street":"S 61St St",
    "iso:country":"US",
    "sg:address":"2900 S 61st St",
    "sg:city":"Philadelphia",
    "sg:classifiers":[
        {
            "category":"Deli",
            "type":"Food & Drink"
        }
    ],
    "sg:phone":"+1 215 727 6654",
    "sg:postcode":"19142",
    "sg:province":"PA",
    "wof:name":"Jim's Food Market",
    "wof:placetype":"venue"
},
  "geometry": {"coordinates":[-75.221497,39.9235],"type":"Point"}
}