{
  "type": "Feature",
  "properties": {
    "iso:country":"US",
    "sg:address":"2298 W Harrisburg Pike",
    "sg:city":"Middletown",
    "sg:classifiers":[
        {
            "category":"Restaurant",
            "type":"Food & Drink"
        }
    ],
    "sg:menulink":"http://www.allmenus.com/pa/lower-swatara/71983-pizza-hut/menu/",
    "sg:phone":"+1 717 944 1437",
    "sg:postcode":"17057",
    "sg:province":"PA",
    "sg:tags":[
        "american",
        "pizza"
    ],
    "wof:name":"Pizza Hut",
    "wof:placetype":"venue"
},
  "geometry": {"coordinates":[-76.77118900000001,40.202002],"type":"Point"}
}