{
  "type": "Feature",
  "properties": {
    "iso:country":"US",
    "sg:address":"2925 Hamilton Ct",
    "sg:city":"Bensalem",
    "sg:classifiers":[
        {
            "category":"Recreation",
            "type":"Entertainment"
        }
    ],
    "sg:phone":"+1   ",
    "sg:postcode":"19020",
    "sg:province":"PA",
    "wof:name":"Q Ball Billiards Inc",
    "wof:placetype":"venue"
},
  "geometry": {"coordinates":[-74.93077700000001,40.149543],"type":"Point"}
}