{
  "type": "Feature",
  "properties": {
    "iso:country":"US",
    "sg:address":"510 Silk St",
    "sg:city":"Jim Thorpe",
    "sg:classifiers":[
        {
            "category":"Utilities",
            "subcategory":"Natural Gas",
            "type":"Services"
        }
    ],
    "sg:phone":"+1   ",
    "sg:postcode":"18229",
    "sg:province":"PA",
    "sg:tags":[
        "distribution"
    ],
    "wof:name":"Reabold Oil Inc",
    "wof:placetype":"venue"
},
  "geometry": {"coordinates":[-75.731826,40.867588],"type":"Point"}
}