{
  "type": "Feature",
  "properties": {
    "iso:country":"US",
    "sg:address":"3308 Recker Dr",
    "sg:city":"Pittsburgh",
    "sg:classifiers":[
        {
            "category":"Building & Trades",
            "subcategory":"Electrical",
            "type":"Services"
        }
    ],
    "sg:phone":"+1   ",
    "sg:postcode":"15227",
    "sg:province":"PA",
    "sg:tags":[
        "electrical",
        "contractor"
    ],
    "wof:name":"Zimmerman Ls Electric",
    "wof:placetype":"venue"
},
  "geometry": {"coordinates":[-79.962473,40.381367],"type":"Point"}
}