{
  "type": "Feature",
  "properties": {
    "iso:country":"US",
    "sg:address":"293 Levan St",
    "sg:city":"Reading",
    "sg:classifiers":[
        {
            "category":"Place Of Worship",
            "subcategory":"Church",
            "type":"Public Place"
        },
        {
            "category":"Place Of Worship",
            "type":"Public Place"
        }
    ],
    "sg:phone":"+1 610 779 8831",
    "sg:postcode":"19606",
    "sg:province":"PA",
    "sg:tags":[
        "churches-episcopal-anglican",
        "churches-episcopal"
    ],
    "wof:name":"St Thomas Episcopal Church",
    "wof:placetype":"venue"
},
  "geometry": {"coordinates":[-75.852476,40.327089],"type":"Point"}
}