{
  "type": "Feature",
  "properties": {
    "iso:country":"US",
    "sg:address":"19 Willow Rd",
    "sg:city":"Reading",
    "sg:classifiers":[
        {
            "category":"Retail",
            "subcategory":"Car Wash",
            "type":"Services"
        }
    ],
    "sg:phone":"+1 610 926 5494",
    "sg:postcode":"19608",
    "sg:province":"PA",
    "sg:tags":[
        "carwash"
    ],
    "wof:name":"I G & S Inc",
    "wof:placetype":"venue"
},
  "geometry": {"coordinates":[-76.043001,40.305849],"type":"Point"}
}