{
  "type": "Feature",
  "properties": {
    "iso:country":"US",
    "sg:address":"301 Elizabeth St",
    "sg:city":"North Versailles",
    "sg:classifiers":[
        {
            "category":"Professional",
            "subcategory":"Accounting & Tax Preparation",
            "type":"Services"
        }
    ],
    "sg:phone":"+1   ",
    "sg:postcode":"15137",
    "sg:province":"PA",
    "wof:name":"Ralph G Powell Jr",
    "wof:placetype":"venue"
},
  "geometry": {"coordinates":[-79.804767,40.380947],"type":"Point"}
}