{
  "type": "Feature",
  "properties": {
    "addr:full":"6542 Lower York Rd New Hope PA 18938",
    "addr:housenumber":"6542",
    "addr:postcode":"18938",
    "addr:street":"Lower York Rd New",
    "iso:country":"US",
    "sg:address":"6542 Lower York Rd",
    "sg:city":"New Hope",
    "sg:classifiers":[
        {
            "category":"Retail",
            "subcategory":"Laundry & Dry Cleaning",
            "type":"Services"
        }
    ],
    "sg:phone":"+1 215 862 0200",
    "sg:postcode":"18938",
    "sg:province":"PA",
    "wof:name":"Logan Square Cleaners",
    "wof:placetype":"venue"
},
  "geometry": {"coordinates":[-74.976744,40.359343],"type":"Point"}
}