{
  "type": "Feature",
  "properties": {
    "iso:country":"US",
    "sg:address":"1312 Osbourne Ave",
    "sg:city":"Abington",
    "sg:classifiers":[
        {
            "category":"Sports & Exercise",
            "subcategory":"Gym",
            "type":"Entertainment"
        }
    ],
    "sg:phone":"+1   ",
    "sg:postcode":"19001",
    "sg:province":"PA",
    "sg:tags":[
        "fitness",
        "physical",
        "facility"
    ],
    "wof:name":"Spirit Aerobic Fitnes Program",
    "wof:placetype":"venue"
},
  "geometry": {"coordinates":[-75.143078,40.133179],"type":"Point"}
}