{
  "type": "Feature",
  "properties": {
    "addr:full":"100 Wilson St Middletown PA 17057",
    "addr:housenumber":"100",
    "addr:postcode":"17057",
    "addr:street":"Wilson St",
    "iso:country":"US",
    "sg:address":"100 Wilson St",
    "sg:city":"Middletown",
    "sg:classifiers":[
        {
            "category":"Real Estate",
            "subcategory":"Real Estate Operator",
            "type":"Services"
        }
    ],
    "sg:phone":"+1   ",
    "sg:postcode":"17057",
    "sg:province":"PA",
    "sg:tags":[
        "building",
        "apartment"
    ],
    "wof:name":"Fenbow LLC",
    "wof:placetype":"venue"
},
  "geometry": {"coordinates":[-76.73424799999999,40.193967],"type":"Point"}
}