{
  "type": "Feature",
  "properties": {
    "addr:full":"7517 W Ridge Rd Fairview PA 16415",
    "addr:housenumber":"7517",
    "addr:postcode":"16415",
    "addr:street":"W Ridge Rd",
    "iso:country":"US",
    "sg:address":"7517 W Ridge Rd",
    "sg:city":"Fairview",
    "sg:classifiers":[
        {
            "category":"Restaurant",
            "type":"Food & Drink"
        }
    ],
    "sg:menulink":"http://www.allmenus.com/pa/fairview/170668-burger-king/menu/",
    "sg:phone":"+1 814 474 1908",
    "sg:postcode":"16415",
    "sg:province":"PA",
    "sg:tags":[
        "burger",
        "american"
    ],
    "wof:name":"Burger King",
    "wof:placetype":"venue"
},
  "geometry": {"coordinates":[-80.255505,42.030904],"type":"Point"}
}