{
  "type": "Feature",
  "properties": {
    "addr:full":"200 Foster Ave Havertown PA 19083",
    "addr:housenumber":"200",
    "addr:postcode":"19083",
    "addr:street":"Foster Ave",
    "iso:country":"US",
    "sg:address":"200 Foster Ave",
    "sg:city":"Havertown",
    "sg:classifiers":[
        {
            "category":"Manufacturing",
            "subcategory":"Printing",
            "type":"Manufacturing & Wholesale Goods"
        }
    ],
    "sg:phone":"+1 610 853 9062",
    "sg:postcode":"19083",
    "sg:province":"PA",
    "sg:tags":[
        "printer"
    ],
    "wof:name":"Nitescan Graphic",
    "wof:placetype":"venue"
},
  "geometry": {"coordinates":[-75.29254299999999,39.973348],"type":"Point"}
}