{
  "type": "Feature",
  "properties": {
    "iso:country":"US",
    "sg:address":"6520 Woodland Ave",
    "sg:city":"Philadelphia",
    "sg:classifiers":[
        {
            "category":"Health Services",
            "subcategory":"Doctor",
            "type":"Services"
        }
    ],
    "sg:phone":"+1 215 727 6080",
    "sg:postcode":"19142",
    "sg:province":"PA",
    "wof:name":"Che Khanh MD",
    "wof:placetype":"venue"
},
  "geometry": {"coordinates":[-75.234703,39.925499],"type":"Point"}
}