{
  "type": "Feature",
  "properties": {
    "addr:full":"450 Highland Ave Pittsburgh PA 15229",
    "addr:housenumber":"450",
    "addr:postcode":"15229",
    "addr:street":"Highland Ave",
    "iso:country":"US",
    "sg:address":"450 Highland Ave",
    "sg:city":"Pittsburgh",
    "sg:classifiers":[
        {
            "category":"Recreation",
            "type":"Entertainment"
        }
    ],
    "sg:phone":"+1 412 761 3556",
    "sg:postcode":"15229",
    "sg:province":"PA",
    "sg:tags":[
        "club",
        "membership"
    ],
    "sg:website":"www.highlandcc.net",
    "wof:name":"Highland Country Club",
    "wof:placetype":"venue"
},
  "geometry": {"coordinates":[-80.04366899999999,40.521715],"type":"Point"}
}