{
  "type": "Feature",
  "properties": {
    "addr:full":"232 Carters Grove Dr Gibsonia PA 15044",
    "addr:housenumber":"232",
    "addr:postcode":"15044",
    "addr:street":"Carters Grove Dr",
    "iso:country":"US",
    "sg:address":"232 Carters Grove Dr",
    "sg:city":"Gibsonia",
    "sg:classifiers":[
        {
            "category":"Building & Trades",
            "subcategory":"Construction",
            "type":"Services"
        }
    ],
    "sg:phone":"+1 724 443 6178",
    "sg:postcode":"15044",
    "sg:province":"PA",
    "sg:tags":[
        "painter"
    ],
    "wof:name":"Your Home Handyman",
    "wof:placetype":"venue"
},
  "geometry": {"coordinates":[-79.92685400000001,40.61687],"type":"Point"}
}