{
  "type": "Feature",
  "properties": {
    "iso:country":"US",
    "sg:address":"698 Harleysville Pike",
    "sg:city":"Harleysville",
    "sg:classifiers":[
        {
            "category":"Real Estate",
            "subcategory":"Architect",
            "type":"Services"
        }
    ],
    "sg:phone":"+1 215 256 6871",
    "sg:postcode":"19438",
    "sg:province":"PA",
    "wof:name":"Lederach Associates Architects & Engineers",
    "wof:placetype":"venue"
},
  "geometry": {"coordinates":[-75.402901,40.266499],"type":"Point"}
}