{
  "type": "Feature",
  "properties": {
    "addr:full":"266 S 21st St Philadelphia PA 19103",
    "addr:housenumber":"266",
    "addr:postcode":"19103",
    "addr:street":"S 21St St",
    "iso:country":"US",
    "sg:address":"266 S 21st St",
    "sg:city":"Philadelphia",
    "sg:classifiers":[
        {
            "category":"Health Services",
            "subcategory":"Dentist",
            "type":"Services"
        }
    ],
    "sg:phone":"+1 215 546 9813",
    "sg:postcode":"19103",
    "sg:province":"PA",
    "wof:name":"Hunt Peter Dentist",
    "wof:placetype":"venue"
},
  "geometry": {"coordinates":[-75.17620100000001,39.9491],"type":"Point"}
}