{
  "type": "Feature",
  "properties": {
    "iso:country":"US",
    "sg:address":"1009 W Chester Rd",
    "sg:city":"West Chester",
    "sg:classifiers":[
        {
            "category":"Building & Trades",
            "subcategory":"Construction",
            "type":"Services"
        }
    ],
    "sg:phone":"+1   ",
    "sg:postcode":"19382",
    "sg:province":"PA",
    "sg:tags":[
        "house"
    ],
    "wof:name":"Thiel Construction",
    "wof:placetype":"venue"
},
  "geometry": {"coordinates":[-75.546162,39.9111],"type":"Point"}
}