{
  "type": "Feature",
  "properties": {
    "iso:country":"US",
    "sg:address":"158 Lafayette Ave",
    "sg:city":"Palmerton",
    "sg:classifiers":[
        {
            "category":"Building & Trades",
            "subcategory":"Electrical",
            "type":"Services"
        }
    ],
    "sg:phone":"+1   ",
    "sg:postcode":"18071",
    "sg:province":"PA",
    "sg:tags":[
        "electrical",
        "contractor"
    ],
    "wof:name":"Merkel Robert W Jr Electric C",
    "wof:placetype":"venue"
},
  "geometry": {"coordinates":[-75.614642,40.802299],"type":"Point"}
}