{
  "type": "Feature",
  "properties": {
    "addr:full":"144 Alpine Rd Bridgeville PA 15017",
    "addr:housenumber":"144",
    "addr:postcode":"15017",
    "addr:street":"Alpine Rd",
    "iso:country":"US",
    "sg:address":"144 Alpine Rd",
    "sg:city":"Bridgeville",
    "sg:classifiers":[
        {
            "category":"Wholesale",
            "subcategory":"Scrap",
            "type":"Manufacturing & Wholesale Goods"
        }
    ],
    "sg:phone":"+1   ",
    "sg:postcode":"15017",
    "sg:province":"PA",
    "sg:tags":[
        "material"
    ],
    "wof:name":"Deblander Assoc",
    "wof:placetype":"venue"
},
  "geometry": {"coordinates":[-80.147623,40.342602],"type":"Point"}
}