{
  "type": "Feature",
  "properties": {
    "iso:country":"US",
    "sg:address":"351 River Ave",
    "sg:city":"Masontown",
    "sg:classifiers":[
        {
            "category":"Home & Garden",
            "subcategory":"Household Appliances",
            "type":"Retail Goods"
        }
    ],
    "sg:phone":"+1 724 583 2811",
    "sg:postcode":"15461",
    "sg:province":"PA",
    "wof:name":"Carmine Appliance Co",
    "wof:placetype":"venue"
},
  "geometry": {"coordinates":[-79.91934999999999,39.850182],"type":"Point"}
}