{
  "type": "Feature",
  "properties": {
    "addr:full":"271 Main St Exton PA 19341",
    "addr:housenumber":"271",
    "addr:postcode":"19341",
    "addr:street":"Main St",
    "iso:country":"US",
    "sg:address":"271 Main St",
    "sg:city":"Exton",
    "sg:classifiers":[
        {
            "category":"Shopping",
            "subcategory":"Gifts & Souvenirs",
            "type":"Retail Goods"
        }
    ],
    "sg:phone":"+1 610 594 2370",
    "sg:postcode":"19341",
    "sg:province":"PA",
    "sg:tags":[
        "shop"
    ],
    "wof:name":"Ten Thousand Villages",
    "wof:placetype":"venue"
},
  "geometry": {"coordinates":[-75.628885,40.024802],"type":"Point"}
}