{
  "type": "Feature",
  "properties": {
    "iso:country":"US",
    "sg:address":"627 Meadowbrook Dr",
    "sg:city":"Huntingdon Vly",
    "sg:classifiers":[
        {
            "category":"Professional",
            "subcategory":"Management & Consulting",
            "type":"Services"
        }
    ],
    "sg:phone":"+1 215 576 5823",
    "sg:postcode":"19006",
    "sg:province":"PA",
    "sg:tags":[
        "consultant",
        "business"
    ],
    "sg:website":"www.keidel.org",
    "wof:name":"Robert Keidel Assoc",
    "wof:placetype":"venue"
},
  "geometry": {"coordinates":[-75.079273,40.111581],"type":"Point"}
}