{
  "type": "Feature",
  "properties": {
    "iso:country":"US",
    "sg:address":"425 5th Ave",
    "sg:city":"Pittsburgh",
    "sg:classifiers":[
        {
            "category":"Professional",
            "subcategory":"Computer Services",
            "type":"Services"
        }
    ],
    "sg:phone":"+1 412 471 7500",
    "sg:postcode":"15219",
    "sg:province":"PA",
    "sg:tags":[
        "consultant",
        "designer"
    ],
    "wof:name":"Commission Junction",
    "wof:placetype":"venue"
},
  "geometry": {"coordinates":[-79.997275,40.440069],"type":"Point"}
}