{
  "type": "Feature",
  "properties": {
    "addr:full":"233 Market St St Marys PA 15857",
    "addr:housenumber":"233",
    "addr:postcode":"15857",
    "addr:street":"Market St",
    "iso:country":"US",
    "sg:address":"233 Market St",
    "sg:city":"St Marys",
    "sg:classifiers":[
        {
            "category":"Bars & Pubs",
            "type":"Food & Drink"
        }
    ],
    "sg:phone":"+1 814 834 6770",
    "sg:postcode":"15857",
    "sg:province":"PA",
    "wof:name":"Dino's Place Inc",
    "wof:placetype":"venue"
},
  "geometry": {"coordinates":[-78.560225,41.426403],"type":"Point"}
}