{
  "type": "Feature",
  "properties": {
    "iso:country":"US",
    "sg:address":"20 Dairyland Sq",
    "sg:city":"Red Lion",
    "sg:classifiers":[
        {
            "category":"Restaurant",
            "type":"Food & Drink"
        }
    ],
    "sg:phone":"+1 717 244 0434",
    "sg:postcode":"17356",
    "sg:province":"PA",
    "wof:name":"Aurora Club",
    "wof:placetype":"venue"
},
  "geometry": {"coordinates":[-76.624377,39.894994],"type":"Point"}
}