{
  "type": "Feature",
  "properties": {
    "addr:full":"1546 E State St Hermitage PA 16148",
    "addr:housenumber":"1546",
    "addr:postcode":"16148",
    "addr:street":"E State St",
    "iso:country":"US",
    "sg:address":"1546 E State St",
    "sg:city":"Hermitage",
    "sg:classifiers":[
        {
            "category":"Manufacturing",
            "subcategory":"Food",
            "type":"Manufacturing & Wholesale Goods"
        }
    ],
    "sg:phone":"+1 724 981 6341",
    "sg:postcode":"16148",
    "sg:province":"PA",
    "sg:tags":[
        "product",
        "confectionery",
        "candy",
        "mfg"
    ],
    "sg:website":"www.phillyc.com",
    "wof:name":"Philadelphia Candies Inc",
    "wof:placetype":"venue"
},
  "geometry": {"coordinates":[-80.48117499999999,41.233127],"type":"Point"}
}