{
  "type": "Feature",
  "properties": {
    "addr:full":"2354 Beaver Valley Pike New Providence PA 17560",
    "addr:housenumber":"2354",
    "addr:postcode":"17560",
    "addr:street":"Beaver Valley Pike",
    "iso:country":"US",
    "sg:address":"2354 Beaver Valley Pike",
    "sg:city":"New Providence",
    "sg:classifiers":[
        {
            "category":"Retail",
            "subcategory":"Auto Rental",
            "type":"Services"
        }
    ],
    "sg:phone":"+1 717 786 0342",
    "sg:postcode":"17560",
    "sg:province":"PA",
    "sg:tags":[
        "renting",
        "truck",
        "leasing"
    ],
    "wof:name":"U-Haul Co",
    "wof:placetype":"venue"
},
  "geometry": {"coordinates":[-76.18346099999999,39.905456],"type":"Point"}
}