{
  "type": "Feature",
  "properties": {
    "iso:country":"US",
    "sg:address":"206 N Main St",
    "sg:city":"Port Allegany",
    "sg:classifiers":[
        {
            "category":"Restaurant",
            "type":"Food & Drink"
        }
    ],
    "sg:phone":"+1 814 642 9353",
    "sg:postcode":"16743",
    "sg:province":"PA",
    "sg:tags":[
        "eating"
    ],
    "wof:name":"Ron's Place",
    "wof:placetype":"venue"
},
  "geometry": {"coordinates":[-78.283551,41.815265],"type":"Point"}
}