{
  "type": "Feature",
  "properties": {
    "addr:full":"1000 Market St Meadville PA 16335",
    "addr:housenumber":"1000",
    "addr:postcode":"16335",
    "addr:street":"Market St",
    "iso:country":"US",
    "sg:address":"1000 Market St",
    "sg:city":"Meadville",
    "sg:classifiers":[
        {
            "category":"Real Estate",
            "subcategory":"Real Estate Agent",
            "type":"Services"
        }
    ],
    "sg:phone":"+1 814 336 2500",
    "sg:postcode":"16335",
    "sg:province":"PA",
    "sg:tags":[
        "agency",
        "rental"
    ],
    "wof:name":"Rent A Wreck",
    "wof:placetype":"venue"
},
  "geometry": {"coordinates":[-80.154321,41.636393],"type":"Point"}
}