{
  "type": "Feature",
  "properties": {
    "iso:country":"US",
    "sg:address":"831 Woodlawn St",
    "sg:city":"Moosic",
    "sg:classifiers":[
        {
            "category":"Health Services",
            "subcategory":"Clinic",
            "type":"Services"
        }
    ],
    "sg:phone":"+1 570 451 1069",
    "sg:postcode":"18507",
    "sg:province":"PA",
    "sg:tags":[
        "organization",
        "medical",
        "surgical"
    ],
    "wof:name":"Paperless Practice",
    "wof:placetype":"venue"
},
  "geometry": {"coordinates":[-75.728679,41.352205],"type":"Point"}
}