{
  "type": "Feature",
  "properties": {
    "iso:country":"US",
    "sg:address":"930 Maple St",
    "sg:city":"Shavertown",
    "sg:classifiers":[
        {
            "category":"Professional",
            "subcategory":"Lawyer & Legal Services",
            "type":"Services"
        }
    ],
    "sg:phone":"+1 570 674 2933",
    "sg:postcode":"18708",
    "sg:province":"PA",
    "sg:tags":[
        "attorney",
        "practice"
    ],
    "wof:name":"Susan Kaufer",
    "wof:placetype":"venue"
},
  "geometry": {"coordinates":[-75.966983,41.281041],"type":"Point"}
}