{
  "type": "Feature",
  "properties": {
    "iso:country":"US",
    "sg:address":"481 John Young Way",
    "sg:city":"Exton",
    "sg:classifiers":[
        {
            "category":"Health Services",
            "subcategory":"Clinic",
            "type":"Services"
        },
        {
            "category":"Health Services",
            "subcategory":"Hospital",
            "type":"Services"
        }
    ],
    "sg:phone":"+1 610 594 9008",
    "sg:postcode":"19341",
    "sg:province":"PA",
    "sg:tags":[
        "children's",
        "medical"
    ],
    "wof:name":"The Childrens Hospital of Philadelphia",
    "wof:placetype":"venue"
},
  "geometry": {"coordinates":[-75.65011800000001,40.022996],"type":"Point"}
}