{
  "type": "Feature",
  "properties": {
    "iso:country":"US",
    "sg:address":"6750 Essington Ave",
    "sg:city":"Philadelphia",
    "sg:classifiers":[
        {
            "category":"Wholesale",
            "subcategory":"Auto Parts",
            "type":"Manufacturing & Wholesale Goods"
        }
    ],
    "sg:phone":"+1   ",
    "sg:postcode":"19153",
    "sg:province":"PA",
    "sg:tags":[
        "used"
    ],
    "wof:name":"Reuben Waller",
    "wof:placetype":"venue"
},
  "geometry": {"coordinates":[-75.221896,39.913062],"type":"Point"}
}