{
  "type": "Feature",
  "properties": {
    "addr:full":"5727 Centre Ave Pittsburgh PA 15206",
    "addr:housenumber":"5727",
    "addr:postcode":"15206",
    "addr:street":"Centre Ave",
    "iso:country":"US",
    "sg:address":"5727 Centre Ave",
    "sg:city":"Pittsburgh",
    "sg:classifiers":[
        {
            "category":"Health Services",
            "subcategory":"Doctor",
            "type":"Services"
        }
    ],
    "sg:phone":"+1 412 363 6626",
    "sg:postcode":"15206",
    "sg:province":"PA",
    "sg:tags":[
        "physician",
        "surgeon"
    ],
    "sg:website":"www.drcapone.com",
    "wof:name":"Shadyside Surgi-Ctr",
    "wof:placetype":"venue"
},
  "geometry": {"coordinates":[-79.934057,40.457262],"type":"Point"}
}