{
  "type": "Feature",
  "properties": {
    "iso:country":"US",
    "sg:address":"100 Clark Aly",
    "sg:city":"Pittsburgh",
    "sg:classifiers":[
        {
            "category":"Wholesale",
            "subcategory":"Painting Supplies",
            "type":"Manufacturing & Wholesale Goods"
        }
    ],
    "sg:phone":"+1 412 782 3030",
    "sg:postcode":"15223",
    "sg:province":"PA",
    "sg:tags":[
        "equipment",
        "painter"
    ],
    "wof:name":"H B Parke Corp",
    "wof:placetype":"venue"
},
  "geometry": {"coordinates":[-79.94677799999999,40.493636],"type":"Point"}
}