{
  "type": "Feature",
  "properties": {
    "iso:country":"US",
    "sg:address":"5907 Hobart St",
    "sg:city":"Pittsburgh",
    "sg:classifiers":[
        {
            "category":"Education",
            "subcategory":"Special Training",
            "type":"Public Place"
        }
    ],
    "sg:phone":"+1   ",
    "sg:postcode":"15217",
    "sg:province":"PA",
    "wof:name":"L Langer",
    "wof:placetype":"venue"
},
  "geometry": {"coordinates":[-79.921254,40.433977],"type":"Point"}
}