{
  "type": "Feature",
  "properties": {
    "addr:full":"1760 Bear Creek Blvd Wilkes Barre PA 18702",
    "addr:housenumber":"1760",
    "addr:postcode":"18702",
    "addr:street":"Bear Creek Blvd",
    "iso:country":"US",
    "sg:address":"1760 Bear Creek Blvd",
    "sg:city":"Wilkes Barre",
    "sg:classifiers":[
        {
            "category":"Building & Trades",
            "subcategory":"Construction",
            "type":"Services"
        }
    ],
    "sg:phone":"+1   ",
    "sg:postcode":"18702",
    "sg:province":"PA",
    "sg:tags":[
        "excavation",
        "contractor"
    ],
    "wof:name":"George Sapp Excavating Co",
    "wof:placetype":"venue"
},
  "geometry": {"coordinates":[-75.80054699999999,41.222539],"type":"Point"}
}