{
  "type": "Feature",
  "properties": {
    "iso:country":"US",
    "sg:address":"1306 Whitfield Blvd",
    "sg:city":"Reading",
    "sg:classifiers":[
        {
            "category":"Manufacturing",
            "subcategory":"Metals",
            "type":"Manufacturing & Wholesale Goods"
        }
    ],
    "sg:phone":"+1 610 678 1832",
    "sg:postcode":"19609",
    "sg:province":"PA",
    "sg:tags":[
        "engraver"
    ],
    "wof:name":"Sundance Engraving",
    "wof:placetype":"venue"
},
  "geometry": {"coordinates":[-76.009379,40.338549],"type":"Point"}
}