{
  "type": "Feature",
  "properties": {
    "iso:country":"US",
    "sg:address":"109 Zeta Dr",
    "sg:city":"Pittsburgh",
    "sg:classifiers":[
        {
            "category":"Building & Trades",
            "subcategory":"Construction",
            "type":"Services"
        }
    ],
    "sg:phone":"+1 412 967 0756",
    "sg:postcode":"15238",
    "sg:province":"PA",
    "sg:tags":[
        "industrial",
        "contractors-commercial"
    ],
    "sg:website":"http://www.studio109designs.com",
    "wof:name":"Studio 109 Designs",
    "wof:placetype":"venue"
},
  "geometry": {"coordinates":[-79.865554,40.500297],"type":"Point"}
}