{
  "type": "Feature",
  "properties": {
    "iso:country":"US",
    "sg:address":"2000 Valley Forge Cir",
    "sg:city":"King Of Prussia",
    "sg:classifiers":[
        {
            "category":"Real Estate",
            "subcategory":"Real Estate Agent",
            "type":"Services"
        }
    ],
    "sg:phone":"+1 610 783 7600",
    "sg:postcode":"19406",
    "sg:province":"PA",
    "wof:name":"Great Enterprises Inc",
    "wof:placetype":"venue"
},
  "geometry": {"coordinates":[-75.412693,40.104634],"type":"Point"}
}