{
  "type": "Feature",
  "properties": {
    "iso:country":"US",
    "sg:address":"2301 Walnut St",
    "sg:city":"Mckeesport",
    "sg:classifiers":[
        {
            "category":"Professional",
            "subcategory":"Advertising",
            "type":"Services"
        },
        {
            "category":"Wholesale",
            "subcategory":"Auto Parts",
            "type":"Manufacturing & Wholesale Goods"
        }
    ],
    "sg:phone":"+1 412 672 1111",
    "sg:postcode":"15132",
    "sg:province":"PA",
    "sg:tags":[
        "distribution"
    ],
    "wof:name":"Total Distributors",
    "wof:placetype":"venue"
},
  "geometry": {"coordinates":[-79.850354,40.335],"type":"Point"}
}