{
  "type": "Feature",
  "properties": {
    "iso:country":"US",
    "sg:address":"625 Old Quaker Rd",
    "sg:city":"Lewisberry",
    "sg:classifiers":[
        {
            "category":"Professional",
            "subcategory":"Business Services",
            "type":"Services"
        },
        {
            "category":"Manufacturing",
            "subcategory":"Apparel",
            "type":"Manufacturing & Wholesale Goods"
        }
    ],
    "sg:phone":"+1 717 932 5771",
    "sg:postcode":"17339",
    "sg:province":"PA",
    "sg:tags":[
        "embroidery"
    ],
    "wof:name":"Marilyn's Creations",
    "wof:placetype":"venue"
},
  "geometry": {"coordinates":[-76.875612,40.154064],"type":"Point"}
}