{
  "type": "Feature",
  "properties": {
    "addr:full":"280 Wotring Rd Washington PA 15301",
    "addr:housenumber":"280",
    "addr:postcode":"15301",
    "addr:street":"Wotring Rd",
    "iso:country":"US",
    "sg:address":"280 Wotring Rd",
    "sg:city":"Washington",
    "sg:classifiers":[
        {
            "category":"Professional",
            "subcategory":"Employment Agencies",
            "type":"Services"
        }
    ],
    "sg:phone":"+1   ",
    "sg:postcode":"15301",
    "sg:province":"PA",
    "sg:tags":[
        "help",
        "supply"
    ],
    "wof:name":"Walker Enterprises",
    "wof:placetype":"venue"
},
  "geometry": {"coordinates":[-80.34854199999999,40.234482],"type":"Point"}
}