{
  "type": "Feature",
  "properties": {
    "addr:full":"165 W Ontario St Philadelphia PA 19140",
    "addr:housenumber":"165",
    "addr:postcode":"19140",
    "addr:street":"W Ontario St",
    "iso:country":"US",
    "sg:address":"165 W Ontario St",
    "sg:city":"Philadelphia",
    "sg:classifiers":[
        {
            "category":"Wholesale",
            "subcategory":"Home Furnishings",
            "type":"Manufacturing & Wholesale Goods"
        }
    ],
    "sg:phone":"+1 215 739 8844",
    "sg:postcode":"19140",
    "sg:province":"PA",
    "sg:tags":[
        "fusion",
        "rug",
        "bonded",
        "carpet"
    ],
    "sg:website":"www.tretfordusa.com",
    "wof:name":"Eurotex Inc",
    "wof:placetype":"venue"
},
  "geometry": {"coordinates":[-75.13105,40.001949],"type":"Point"}
}