{
  "type": "Feature",
  "properties": {
    "iso:country":"US",
    "sg:address":"3085 Washington Pike",
    "sg:city":"Bridgeville",
    "sg:classifiers":[
        {
            "category":"Banks & Credit Unions",
            "subcategory":"Bank",
            "type":"Services"
        }
    ],
    "sg:phone":"+1 412 221 5400",
    "sg:postcode":"15017",
    "sg:province":"PA",
    "wof:name":"Pnc Bank",
    "wof:placetype":"venue"
},
  "geometry": {"coordinates":[-80.112297,40.348598],"type":"Point"}
}