{
  "type": "Feature",
  "properties": {
    "iso:country":"US",
    "sg:address":"126 N Main Ave",
    "sg:city":"Scranton",
    "sg:classifiers":[
        {
            "category":"Professional",
            "type":"Services"
        }
    ],
    "sg:phone":"+1 570 341 0779",
    "sg:postcode":"18504",
    "sg:province":"PA",
    "sg:tags":[
        "establishment"
    ],
    "wof:name":"Ridgeway's",
    "wof:placetype":"venue"
},
  "geometry": {"coordinates":[-75.679906,41.412616],"type":"Point"}
}