{
  "type": "Feature",
  "properties": {
    "iso:country":"US",
    "sg:address":"115 Marbeth Ave",
    "sg:city":"Carlisle",
    "sg:classifiers":[
        {
            "category":"Education",
            "subcategory":"Music School",
            "type":"Public Place"
        }
    ],
    "sg:phone":"+1 717 258 1177",
    "sg:postcode":"17013",
    "sg:province":"PA",
    "sg:tags":[
        "instrument",
        "teacher",
        "musical"
    ],
    "wof:name":"King Louie Music",
    "wof:placetype":"venue"
},
  "geometry": {"coordinates":[-77.172501,40.2187],"type":"Point"}
}