{
  "type": "Feature",
  "properties": {
    "iso:country":"US",
    "sg:address":"6339 Pigeon Hill Rd",
    "sg:city":"Hanover",
    "sg:phone":"+1   ",
    "sg:postcode":"17331",
    "sg:province":"PA",
    "sg:tags":[
        "farm"
    ],
    "wof:name":"Woodland Road Produce Patch",
    "wof:placetype":"venue"
},
  "geometry": {"coordinates":[-76.927122,39.872621],"type":"Point"}
}