{
  "type": "Feature",
  "properties": {
    "addr:full":"5601 Spruce St Philadelphia PA 19139",
    "addr:housenumber":"5601",
    "addr:postcode":"19139",
    "addr:street":"Spruce St",
    "iso:country":"US",
    "sg:address":"5601 Spruce St",
    "sg:city":"Philadelphia",
    "sg:classifiers":[
        {
            "category":"Banks & Credit Unions",
            "subcategory":"Bank",
            "type":"Services"
        }
    ],
    "sg:phone":"+1 215 747 3008",
    "sg:postcode":"19139",
    "sg:province":"PA",
    "sg:tags":[
        "cashing",
        "check"
    ],
    "wof:name":"Currency One",
    "wof:placetype":"venue"
},
  "geometry": {"coordinates":[-75.23467599999999,39.955666],"type":"Point"}
}