{
  "type": "Feature",
  "properties": {
    "iso:country":"US",
    "sg:address":"2301 Market St",
    "sg:city":"Philadelphia",
    "sg:classifiers":[
        {
            "category":"Museum",
            "type":"Entertainment"
        }
    ],
    "sg:phone":"+1 215 405 8719",
    "sg:postcode":"19103",
    "sg:province":"PA",
    "sg:website":"http://www.cwurmuseum.org",
    "wof:name":"Civil War Museum of Philadelphia",
    "wof:placetype":"venue"
},
  "geometry": {"coordinates":[-75.17781100000001,39.954151],"type":"Point"}
}