{
  "type": "Feature",
  "properties": {
    "iso:country":"US",
    "sg:address":"156 Reistville Rd",
    "sg:city":"Myerstown",
    "sg:classifiers":[
        {
            "category":"Manufacturing",
            "subcategory":"Food",
            "type":"Manufacturing & Wholesale Goods"
        }
    ],
    "sg:phone":"+1   ",
    "sg:postcode":"17067",
    "sg:province":"PA",
    "sg:tags":[
        "preparation",
        "mfg"
    ],
    "wof:name":"Chestnut Acres Specialty",
    "wof:placetype":"venue"
},
  "geometry": {"coordinates":[-76.277303,40.328916],"type":"Point"}
}