{
  "type": "Feature",
  "properties": {
    "iso:country":"US",
    "sg:address":"3117 Chestnut St",
    "sg:city":"Camp Hill",
    "sg:classifiers":[
        {
            "category":"Professional",
            "subcategory":"Lawyer & Legal Services",
            "type":"Services"
        }
    ],
    "sg:phone":"+1 717 761 5800",
    "sg:postcode":"17011",
    "sg:province":"PA",
    "wof:name":"Dinner Scott M",
    "wof:placetype":"venue"
},
  "geometry": {"coordinates":[-76.934097,40.238499],"type":"Point"}
}