{
  "type": "Feature",
  "properties": {
    "iso:country":"US",
    "sg:address":"1222 Linden Ave",
    "sg:city":"Erie",
    "sg:classifiers":[
        {
            "category":"Manufacturing",
            "subcategory":"Metals",
            "type":"Manufacturing & Wholesale Goods"
        }
    ],
    "sg:phone":"+1 814 838 2028",
    "sg:postcode":"16505",
    "sg:province":"PA",
    "sg:tags":[
        "pipe",
        "fitting",
        "valve"
    ],
    "sg:website":"www.highpressure.com",
    "wof:name":"High Pressure Equipment Co",
    "wof:placetype":"venue"
},
  "geometry": {"coordinates":[-80.16187600000001,42.092519],"type":"Point"}
}