{
  "type": "Feature",
  "properties": {
    "iso:country":"US",
    "sg:address":"50 W Clearview Dr",
    "sg:city":"Shrewsbury",
    "sg:classifiers":[
        {
            "category":"Manufacturing",
            "subcategory":"Tools & Machinery",
            "type":"Manufacturing & Wholesale Goods"
        }
    ],
    "sg:phone":"+1   ",
    "sg:postcode":"17361",
    "sg:province":"PA",
    "sg:tags":[
        "conductive",
        "wiring",
        "devices",
        "mfg"
    ],
    "wof:name":"Tyco Electronics Corporation",
    "wof:placetype":"venue"
},
  "geometry": {"coordinates":[-76.685678,39.777379],"type":"Point"}
}