{
  "type": "Feature",
  "properties": {
    "iso:country":"US",
    "sg:address":"3713 Birney Ave",
    "sg:city":"Moosic",
    "sg:classifiers":[
        {
            "category":"Professional",
            "subcategory":"Advertising",
            "type":"Services"
        },
        {
            "category":"Professional",
            "subcategory":"Business Services",
            "type":"Services"
        }
    ],
    "sg:phone":"+1 570 558 4941",
    "sg:postcode":"18507",
    "sg:province":"PA",
    "sg:tags":[
        "mail",
        "direct",
        "shipping"
    ],
    "wof:name":"North East Mail Outsourcing",
    "wof:placetype":"venue"
},
  "geometry": {"coordinates":[-75.70542500000001,41.371968],"type":"Point"}
}