{
  "type": "Feature",
  "properties": {
    "iso:country":"US",
    "sg:address":"700 E Broad St",
    "sg:city":"Hazleton",
    "sg:classifiers":[
        {
            "category":"Organizations",
            "subcategory":"Non-profit Organization",
            "type":"Services"
        }
    ],
    "sg:phone":"+1 570 450 4357",
    "sg:postcode":"18201",
    "sg:province":"PA",
    "wof:name":"Hazleton Health Alliance",
    "wof:placetype":"venue"
},
  "geometry": {"coordinates":[-75.963005,40.950188],"type":"Point"}
}