{
  "type": "Feature",
  "properties": {
    "iso:country":"US",
    "sg:address":"522 W Main St",
    "sg:city":"Mount Pleasant",
    "sg:classifiers":[
        {
            "category":"Shopping",
            "subcategory":"Florist",
            "type":"Retail Goods"
        }
    ],
    "sg:phone":"+1   ",
    "sg:postcode":"15666",
    "sg:province":"PA",
    "wof:name":"Ehrlichs Jeffrey Bloom Florl",
    "wof:placetype":"venue"
},
  "geometry": {"coordinates":[-79.542316,40.149085],"type":"Point"}
}