{
  "type": "Feature",
  "properties": {
    "addr:full":"434 S Muddy Creek Rd Denver PA 17517",
    "addr:housenumber":"434",
    "addr:postcode":"17517",
    "addr:street":"S Muddy Creek Rd",
    "iso:country":"US",
    "sg:address":"434 S Muddy Creek Rd",
    "sg:city":"Denver",
    "sg:classifiers":[
        {
            "category":"Manufacturing",
            "subcategory":"Textiles",
            "type":"Manufacturing & Wholesale Goods"
        }
    ],
    "sg:phone":"+1   ",
    "sg:postcode":"17517",
    "sg:province":"PA",
    "sg:tags":[
        "mill",
        "thread"
    ],
    "wof:name":"Coats American",
    "wof:placetype":"venue"
},
  "geometry": {"coordinates":[-76.080607,40.213772],"type":"Point"}
}