{
  "type": "Feature",
  "properties": {
    "iso:country":"US",
    "sg:address":"238 Arch St",
    "sg:city":"Philadelphia",
    "sg:classifiers":[
        {
            "category":"Shopping",
            "type":"Retail Goods"
        }
    ],
    "sg:phone":"+1 215 922 0510",
    "sg:postcode":"19106",
    "sg:province":"PA",
    "wof:name":"Humphrys Flag Company, Inc",
    "wof:placetype":"venue"
},
  "geometry": {"coordinates":[-75.144408,39.952074],"type":"Point"}
}