{
  "type": "Feature",
  "properties": {
    "addr:full":"302 N Empire Ct Wilkes Barre PA 18702",
    "addr:housenumber":"302",
    "addr:postcode":"18702",
    "addr:street":"N Empire Ct",
    "iso:country":"US",
    "sg:address":"302 N Empire Ct",
    "sg:city":"Wilkes Barre",
    "sg:classifiers":[
        {
            "category":"Retail",
            "subcategory":"Repair Shop",
            "type":"Services"
        }
    ],
    "sg:phone":"+1 570 824 9636",
    "sg:postcode":"18702",
    "sg:province":"PA",
    "sg:tags":[
        "repairing",
        "piano",
        "refinishing"
    ],
    "sg:website":"www.robertmsides.com",
    "wof:name":"Robert M Sides Family Music",
    "wof:placetype":"venue"
},
  "geometry": {"coordinates":[-75.865922,41.238331],"type":"Point"}
}