{
  "type": "Feature",
  "properties": {
    "iso:country":"US",
    "sg:address":"981 Bristol Pike",
    "sg:city":"Bensalem",
    "sg:classifiers":[
        {
            "category":"Professional",
            "subcategory":"Business Services",
            "type":"Services"
        }
    ],
    "sg:phone":"+1 215 961 4800",
    "sg:postcode":"19020",
    "sg:province":"PA",
    "sg:tags":[
        "paging",
        "answering"
    ],
    "wof:name":"AAA Answering Svc",
    "wof:placetype":"venue"
},
  "geometry": {"coordinates":[-74.971363,40.067088],"type":"Point"}
}