{
  "type": "Feature",
  "properties": {
    "addr:full":"296 Stormfield Dr Harleysville PA 19438",
    "addr:housenumber":"296",
    "addr:postcode":"19438",
    "addr:street":"Stormfield Dr",
    "iso:country":"US",
    "sg:address":"296 Stormfield Dr",
    "sg:city":"Harleysville",
    "sg:classifiers":[
        {
            "category":"Restaurant",
            "type":"Food & Drink"
        }
    ],
    "sg:phone":"+1 215 513 7573",
    "sg:postcode":"19438",
    "sg:province":"PA",
    "sg:tags":[
        "caterer"
    ],
    "wof:name":"All About Catering",
    "wof:placetype":"venue"
},
  "geometry": {"coordinates":[-75.38287200000001,40.272009],"type":"Point"}
}