{
  "type": "Feature",
  "properties": {
    "iso:country":"US",
    "sg:address":"1343 Baltimore Pike",
    "sg:city":"Media",
    "sg:classifiers":[
        {
            "category":"Health Services",
            "subcategory":"Nursing And Care Facility",
            "type":"Services"
        }
    ],
    "sg:phone":"+1 610 361 8221",
    "sg:postcode":"19063",
    "sg:province":"PA",
    "sg:tags":[
        "home",
        "retirement",
        "community"
    ],
    "sg:website":"www.acts-retirement.org",
    "wof:name":"Granite Farms Estates",
    "wof:placetype":"venue"
},
  "geometry": {"coordinates":[-75.406406,39.917111],"type":"Point"}
}