{
  "type": "Feature",
  "properties": {
    "iso:country":"US",
    "sg:address":"602 W Shawnee Ave",
    "sg:city":"Plymouth",
    "sg:classifiers":[
        {
            "category":"Building & Trades",
            "subcategory":"Construction",
            "type":"Services"
        }
    ],
    "sg:phone":"+1 570 779 9925",
    "sg:postcode":"18651",
    "sg:province":"PA",
    "sg:tags":[
        "house",
        "general",
        "contractor"
    ],
    "wof:name":"Construction By Sincavage",
    "wof:placetype":"venue"
},
  "geometry": {"coordinates":[-75.958806,41.238387],"type":"Point"}
}