{
  "type": "Feature",
  "properties": {
    "iso:country":"US",
    "sg:address":"413 W Amosland Rd",
    "sg:city":"Norwood",
    "sg:classifiers":[
        {
            "category":"Building & Trades",
            "subcategory":"Electrical",
            "type":"Services"
        }
    ],
    "sg:phone":"+1 610 532 7204",
    "sg:postcode":"19074",
    "sg:province":"PA",
    "sg:tags":[
        "electrical",
        "electric",
        "contractor"
    ],
    "wof:name":"Ford Brothers Electric Co Inc",
    "wof:placetype":"venue"
},
  "geometry": {"coordinates":[-75.30588,39.89532],"type":"Point"}
}