{
  "type": "Feature",
  "properties": {
    "iso:country":"US",
    "sg:address":"2400 Cassady Ave",
    "sg:city":"Huntingdon",
    "sg:classifiers":[
        {
            "category":"Professional",
            "type":"Services"
        }
    ],
    "sg:phone":"+1   ",
    "sg:postcode":"16652",
    "sg:province":"PA",
    "wof:name":"Leonard S Fiore Inc",
    "wof:placetype":"venue"
},
  "geometry": {"coordinates":[-78.010825,40.503759],"type":"Point"}
}