{
  "type": "Feature",
  "properties": {
    "addr:full":"217 N Wade Ave Washington PA 15301",
    "addr:housenumber":"217",
    "addr:postcode":"15301",
    "addr:street":"N Wade Ave",
    "iso:country":"US",
    "sg:address":"217 N Wade Ave",
    "sg:city":"Washington",
    "sg:classifiers":[
        {
            "category":"Social Services",
            "type":"Services"
        }
    ],
    "sg:phone":"+1 724 222 1766",
    "sg:postcode":"15301",
    "sg:province":"PA",
    "sg:tags":[
        "agency",
        "adoption"
    ],
    "sg:website":"www.pnpic.org",
    "wof:name":"Parent Network For Post I",
    "wof:placetype":"venue"
},
  "geometry": {"coordinates":[-80.235237,40.175357],"type":"Point"}
}