{
  "type": "Feature",
  "properties": {
    "iso:country":"US",
    "sg:address":"910 Boroline St",
    "sg:city":"New Castle",
    "sg:classifiers":[
        {
            "category":"Building & Trades",
            "subcategory":"Construction",
            "type":"Services"
        }
    ],
    "sg:phone":"+1   ",
    "sg:postcode":"16101",
    "sg:province":"PA",
    "sg:tags":[
        "house"
    ],
    "wof:name":"Jack Gibson Construction",
    "wof:placetype":"venue"
},
  "geometry": {"coordinates":[-80.359239,40.995783],"type":"Point"}
}