{
  "type": "Feature",
  "properties": {
    "iso:country":"US",
    "sg:address":"5800 Elwood Ave",
    "sg:city":"Bristol",
    "sg:classifiers":[
        {
            "category":"Building & Trades",
            "subcategory":"Construction",
            "type":"Services"
        }
    ],
    "sg:phone":"+1 215 785 3006",
    "sg:postcode":"19007",
    "sg:province":"PA",
    "sg:tags":[
        "cabinet",
        "carpentry",
        "maker",
        "contractor"
    ],
    "wof:name":"P & P Custom Fixtures Inc",
    "wof:placetype":"venue"
},
  "geometry": {"coordinates":[-74.84602099999999,40.119319],"type":"Point"}
}