{
  "type": "Feature",
  "properties": {
    "addr:full":"448 Penn Ave Reading PA 19611",
    "addr:housenumber":"448",
    "addr:postcode":"19611",
    "addr:street":"Penn Ave",
    "iso:country":"US",
    "sg:address":"448 Penn Ave",
    "sg:city":"Reading",
    "sg:classifiers":[
        {
            "category":"Shopping",
            "type":"Retail Goods"
        }
    ],
    "sg:phone":"+1 610 685 7256",
    "sg:postcode":"19611",
    "sg:province":"PA",
    "sg:tags":[
        "ice"
    ],
    "wof:name":"F Ire & Ice Cafe",
    "wof:placetype":"venue"
},
  "geometry": {"coordinates":[-75.945638,40.335536],"type":"Point"}
}