{
  "type": "Feature",
  "properties": {
    "iso:country":"US",
    "sg:address":"4240 Greensburg Pike",
    "sg:city":"Pittsburgh",
    "sg:classifiers":[
        {
            "category":"Health Services",
            "subcategory":"Doctor",
            "type":"Services"
        },
        {
            "category":"Health Services",
            "subcategory":"Clinic",
            "type":"Services"
        }
    ],
    "sg:phone":"+1 412 351 1121",
    "sg:postcode":"15221",
    "sg:province":"PA",
    "sg:tags":[
        "psychological",
        "psychologist"
    ],
    "wof:name":"Nelken Andrea Psy D",
    "wof:placetype":"venue"
},
  "geometry": {"coordinates":[-79.841367,40.420068],"type":"Point"}
}