{
  "type": "Feature",
  "properties": {
    "addr:full":"514 E Main St Bath PA 18014",
    "addr:housenumber":"514",
    "addr:postcode":"18014",
    "addr:street":"E Main St",
    "iso:country":"US",
    "sg:address":"514 E Main St",
    "sg:city":"Bath",
    "sg:classifiers":[
        {
            "category":"Wholesale",
            "subcategory":"Toys & Hobbies",
            "type":"Manufacturing & Wholesale Goods"
        },
        {
            "category":"Shopping",
            "subcategory":"Hobbies, Toys, & Games",
            "type":"Retail Goods"
        }
    ],
    "sg:phone":"+1 610 837 6681",
    "sg:postcode":"18014",
    "sg:province":"PA",
    "sg:tags":[
        "model",
        "trade",
        "store",
        "supply"
    ],
    "wof:name":"Dick Wetzel's Hobbies",
    "wof:placetype":"venue"
},
  "geometry": {"coordinates":[-75.38215099999999,40.722536],"type":"Point"}
}