{
  "type": "Feature",
  "properties": {
    "addr:full":"1698 Temple Ave Lancaster PA 17603",
    "addr:housenumber":"1698",
    "addr:postcode":"17603",
    "addr:street":"Temple Ave",
    "iso:country":"US",
    "sg:address":"1698 Temple Ave",
    "sg:city":"Lancaster",
    "sg:classifiers":[
        {
            "category":"Insurance",
            "subcategory":"Hazard Insurance",
            "type":"Services"
        },
        {
            "category":"Insurance",
            "subcategory":"Insurance Agent",
            "type":"Services"
        },
        {
            "category":"Insurance",
            "subcategory":"Life Insurance",
            "type":"Services"
        },
        {
            "category":"Insurance",
            "subcategory":"Title Insurance",
            "type":"Services"
        }
    ],
    "sg:phone":"+1 717 394 1052",
    "sg:postcode":"17603",
    "sg:province":"PA",
    "sg:tags":[
        "auto",
        "homeowner"
    ],
    "sg:website":"http://www.nationwide.com/agent/Lancaster-PENNSYLVANIA-insurance-agent/anthony-harnish/office.html",
    "wof:name":"Anthony R. Harnish - Nationwide Insurance",
    "wof:placetype":"venue"
},
  "geometry": {"coordinates":[-76.349709,40.03614],"type":"Point"}
}