{
  "type": "Feature",
  "properties": {
    "iso:country":"US",
    "sg:address":"2170 Washington Rd",
    "sg:city":"Canonsburg",
    "sg:classifiers":[
        {
            "category":"Real Estate",
            "subcategory":"Real Estate Agent",
            "type":"Services"
        }
    ],
    "sg:phone":"+1   ",
    "sg:postcode":"15317",
    "sg:province":"PA",
    "sg:tags":[
        "property",
        "e",
        "broker"
    ],
    "wof:name":"Prologi",
    "wof:placetype":"venue"
},
  "geometry": {"coordinates":[-80.178271,40.24127],"type":"Point"}
}