{
  "type": "Feature",
  "properties": {
    "iso:country":"US",
    "sg:address":"1034 E Chelten Ave ",
    "sg:city":"Philadelphia",
    "sg:classifiers":[
        {
            "category":"Restaurant",
            "type":"Food & Drink"
        }
    ],
    "sg:menulink":"http://www.allmenus.com/pa/philadelphia/289697-italianos-pizza/menu/",
    "sg:phone":"+1 215 849 5090",
    "sg:postcode":"19138",
    "sg:province":"PA",
    "sg:tags":[
        "american",
        "pizza"
    ],
    "wof:name":"Italiano's Pizza",
    "wof:placetype":"venue"
},
  "geometry": {"coordinates":[-75.160803,40.049295],"type":"Point"}
}