{
  "type": "Feature",
  "properties": {
    "iso:country":"US",
    "sg:address":"200 S Spring Garden St",
    "sg:city":"Carlisle",
    "sg:classifiers":[
        {
            "category":"Shopping",
            "subcategory":"Beauty & Cosmetics",
            "type":"Retail Goods"
        },
        {
            "category":"Personal",
            "subcategory":"Hair Removal",
            "type":"Services"
        },
        {
            "category":"Personal",
            "subcategory":"Nail Salon",
            "type":"Services"
        },
        {
            "category":"Personal",
            "subcategory":"Tanning Parlor",
            "type":"Services"
        },
        {
            "category":"Personal",
            "subcategory":"Skin Care",
            "type":"Services"
        },
        {
            "category":"Manufacturing",
            "subcategory":"Chemicals & Compounds",
            "type":"Manufacturing & Wholesale Goods"
        },
        {
            "category":"Personal",
            "subcategory":"Beauty Salon",
            "type":"Services"
        }
    ],
    "sg:phone":"+1 717 609 4852",
    "sg:postcode":"17013",
    "sg:province":"PA",
    "sg:tags":[
        "permanent",
        "electrolysis",
        "make-up"
    ],
    "sg:website":"http://www.faceforwardclinic.com",
    "wof:name":"Face Forward",
    "wof:placetype":"venue"
},
  "geometry": {"coordinates":[-77.181183,40.198551],"type":"Point"}
}