{
  "type": "Feature",
  "properties": {
    "iso:country":"US",
    "sg:address":"4800 Orchard St",
    "sg:city":"Harrisburg",
    "sg:classifiers":[
        {
            "category":"Health Services",
            "subcategory":"Doctor",
            "type":"Services"
        }
    ],
    "sg:phone":"+1 717 657 7995",
    "sg:postcode":"17109",
    "sg:province":"PA",
    "sg:tags":[
        "medicine",
        "physician",
        "addiction",
        "surgeons"
    ],
    "sg:website":"http://www.last-homestudy.com",
    "wof:name":"Laban's Trainings",
    "wof:placetype":"venue"
},
  "geometry": {"coordinates":[-76.80998200000001,40.304562],"type":"Point"}
}