{
  "type": "Feature",
  "properties": {
    "iso:country":"US",
    "sg:address":"1380 Million Dollar Hwy",
    "sg:city":"Kersey",
    "sg:classifiers":[
        {
            "category":"Building & Trades",
            "subcategory":"Plumbing",
            "type":"Services"
        }
    ],
    "sg:phone":"+1 814 834 1135",
    "sg:postcode":"15846",
    "sg:province":"PA",
    "sg:tags":[
        "pipe",
        "fitter",
        "industrial"
    ],
    "wof:name":"Bon Fabricating & Construction",
    "wof:placetype":"venue"
},
  "geometry": {"coordinates":[-78.55326100000001,41.362012],"type":"Point"}
}