{
  "type": "Feature",
  "properties": {
    "iso:country":"US",
    "sg:address":"302 Red Well Rd",
    "sg:city":"New Holland",
    "sg:classifiers":[
        {
            "category":"Restaurant",
            "type":"Food & Drink"
        }
    ],
    "sg:phone":"+1   ",
    "sg:postcode":"17557",
    "sg:province":"PA",
    "sg:tags":[
        "eating"
    ],
    "wof:name":"Craig M Sheaffer",
    "wof:placetype":"venue"
},
  "geometry": {"coordinates":[-76.05459999999999,40.065914],"type":"Point"}
}