{
  "type": "Feature",
  "properties": {
    "addr:full":"807 Pleasant Hills Rd Williamsport PA 17701",
    "addr:housenumber":"807",
    "addr:postcode":"17701",
    "addr:street":"Pleasant Hills Rd",
    "iso:country":"US",
    "sg:address":"807 Pleasant Hills Rd",
    "sg:city":"Williamsport",
    "sg:classifiers":[
        {
            "category":"Home & Garden",
            "subcategory":"Building Materials",
            "type":"Retail Goods"
        }
    ],
    "sg:phone":"+1   ",
    "sg:postcode":"17701",
    "sg:province":"PA",
    "wof:name":"Ray of Light Stained Glass",
    "wof:placetype":"venue"
},
  "geometry": {"coordinates":[-76.992812,41.291827],"type":"Point"}
}