{
  "type": "Feature",
  "properties": {
    "iso:country":"US",
    "sg:address":"810 3rd St",
    "sg:city":"Beaver",
    "sg:classifiers":[
        {
            "category":"Government",
            "subcategory":"Police Station",
            "type":"Public Place"
        }
    ],
    "sg:phone":"+1 724 728 5700",
    "sg:postcode":"15009",
    "sg:province":"PA",
    "sg:tags":[
        "protection",
        "sheriff"
    ],
    "sg:website":"www.co.beaver.pa.us",
    "wof:name":"Beaver County Sheriff's Office",
    "wof:placetype":"venue"
},
  "geometry": {"coordinates":[-80.30845600000001,40.693819],"type":"Point"}
}