{
  "type": "Feature",
  "properties": {
    "addr:full":"20 Barrel Run Rd Quakertown PA 18951",
    "addr:housenumber":"20",
    "addr:postcode":"18951",
    "addr:street":"Barrel Run Rd",
    "iso:country":"US",
    "sg:address":"20 Barrel Run Rd",
    "sg:city":"Quakertown",
    "sg:classifiers":[
        {
            "category":"Insurance",
            "subcategory":"Insurance Agent",
            "type":"Services"
        }
    ],
    "sg:phone":"+1 215 538 1865",
    "sg:postcode":"18951",
    "sg:province":"PA",
    "wof:name":"Warren S Weiss Insurance",
    "wof:placetype":"venue"
},
  "geometry": {"coordinates":[-75.382576,40.420554],"type":"Point"}
}