{
  "type": "Feature",
  "properties": {
    "iso:country":"US",
    "sg:address":"6106 Lansdowne Ave",
    "sg:city":"Philadelphia",
    "sg:classifiers":[
        {
            "category":"Social Services",
            "subcategory":"Child Care",
            "type":"Services"
        }
    ],
    "sg:phone":"+1 215 452 5519",
    "sg:postcode":"19151",
    "sg:province":"PA",
    "sg:tags":[
        "day"
    ],
    "wof:name":"Mecca Daycare & Learning Center",
    "wof:placetype":"venue"
},
  "geometry": {"coordinates":[-75.24199,39.975579],"type":"Point"}
}