{
  "type": "Feature",
  "properties": {
    "addr:full":"200 W Washington Sq # 3102 Philadelphia PA 19106",
    "addr:housenumber":"200",
    "addr:postcode":"19106",
    "addr:street":"W Washington Sq # 3102",
    "iso:country":"US",
    "sg:address":"200 W Washington Sq # 3102",
    "sg:city":"Philadelphia",
    "sg:classifiers":[
        {
            "category":"Professional",
            "subcategory":"Art Services",
            "type":"Services"
        }
    ],
    "sg:phone":"+1 215 301 4800",
    "sg:postcode":"19106",
    "sg:province":"PA",
    "sg:tags":[
        "commercial",
        "artist"
    ],
    "wof:name":"The Lipski Group Inc",
    "wof:placetype":"venue"
},
  "geometry": {"coordinates":[-75.153198,39.947781],"type":"Point"}
}