{
  "type": "Feature",
  "properties": {
    "iso:country":"US",
    "sg:address":"1701 Hempstead Rd",
    "sg:city":"Lancaster",
    "sg:classifiers":[
        {
            "category":"Manufacturing",
            "subcategory":"Paper Products",
            "type":"Manufacturing & Wholesale Goods"
        }
    ],
    "sg:phone":"+1   ",
    "sg:postcode":"17601",
    "sg:province":"PA",
    "sg:tags":[
        "converted",
        "mfg"
    ],
    "wof:name":"Ris Converting",
    "wof:placetype":"venue"
},
  "geometry": {"coordinates":[-76.258139,40.051422],"type":"Point"}
}