{
  "type": "Feature",
  "properties": {
    "iso:country":"US",
    "sg:address":"513 Washington St",
    "sg:city":"Huntingdon",
    "sg:classifiers":[
        {
            "category":"Shopping",
            "subcategory":"Crafts & Fabrics",
            "type":"Retail Goods"
        }
    ],
    "sg:phone":"+1 814 644 6560",
    "sg:postcode":"16652",
    "sg:province":"PA",
    "sg:tags":[
        "shop"
    ],
    "wof:name":"Taylor's Notions",
    "wof:placetype":"venue"
},
  "geometry": {"coordinates":[-78.01308299999999,40.486053],"type":"Point"}
}