{
  "type": "Feature",
  "properties": {
    "iso:country":"US",
    "sg:address":"274 Pamela Cir",
    "sg:city":"Harleysville",
    "sg:classifiers":[
        {
            "category":"Structure",
            "subcategory":"Office Building",
            "type":"Public Place"
        }
    ],
    "sg:phone":"+1 215 513 1743",
    "sg:postcode":"19438",
    "sg:province":"PA",
    "sg:tags":[
        "park"
    ],
    "wof:name":"Chicago Properties",
    "wof:placetype":"venue"
},
  "geometry": {"coordinates":[-75.37706799999999,40.2697],"type":"Point"}
}