{
  "type": "Feature",
  "properties": {
    "addr:full":"3045 Market St # 2 Camp Hill PA 17011",
    "addr:housenumber":"3045",
    "addr:postcode":"17011",
    "addr:street":"Market St # 2",
    "iso:country":"US",
    "sg:address":"3045 Market St # 2",
    "sg:city":"Camp Hill",
    "sg:classifiers":[
        {
            "category":"Professional",
            "subcategory":"Lawyer & Legal Services",
            "type":"Services"
        }
    ],
    "sg:phone":"+1 717 731 8600",
    "sg:postcode":"17011",
    "sg:province":"PA",
    "wof:name":"Clark Law Office",
    "wof:placetype":"venue"
},
  "geometry": {"coordinates":[-76.93319700000001,40.239799],"type":"Point"}
}