{
  "type": "Feature",
  "properties": {
    "addr:full":"65 S Main St Doylestown PA 18901",
    "addr:housenumber":"65",
    "addr:postcode":"18901",
    "addr:street":"S Main St",
    "iso:country":"US",
    "sg:address":"65 S Main St",
    "sg:city":"Doylestown",
    "sg:classifiers":[
        {
            "category":"Shopping",
            "subcategory":"Clothing, Apparel, & Fashions",
            "type":"Retail Goods"
        }
    ],
    "sg:phone":"+1 215 348 8250",
    "sg:postcode":"18901",
    "sg:province":"PA",
    "sg:tags":[
        "accessory"
    ],
    "wof:name":"Shop Clothes",
    "wof:placetype":"venue"
},
  "geometry": {"coordinates":[-75.12960099999999,40.308601],"type":"Point"}
}