{
  "type": "Feature",
  "properties": {
    "iso:country":"US",
    "sg:address":"707 Exeter Ave",
    "sg:city":"Pittston",
    "sg:classifiers":[
        {
            "category":"Autos & Motor Vehicles",
            "subcategory":"Auto Supplies",
            "type":"Retail Goods"
        },
        {
            "category":"Wholesale",
            "subcategory":"Auto Parts",
            "type":"Manufacturing & Wholesale Goods"
        }
    ],
    "sg:phone":"+1 570 654 1909",
    "sg:postcode":"18643",
    "sg:province":"PA",
    "sg:tags":[
        "automotive",
        "automobile"
    ],
    "wof:name":"Cenera Auto Parts Inc",
    "wof:placetype":"venue"
},
  "geometry": {"coordinates":[-75.80135,41.335568],"type":"Point"}
}