{
  "type": "Feature",
  "properties": {
    "iso:country":"US",
    "sg:address":"840 Walnut St",
    "sg:city":"Philadelphia",
    "sg:classifiers":[
        {
            "category":"Health Services",
            "subcategory":"Doctor",
            "type":"Services"
        }
    ],
    "sg:phone":"+1 215 772 0900",
    "sg:postcode":"19107",
    "sg:province":"PA",
    "sg:tags":[
        "physician",
        "surgeon"
    ],
    "wof:name":"Marc C Cohen MD",
    "wof:placetype":"venue"
},
  "geometry": {"coordinates":[-75.154247,39.948094],"type":"Point"}
}