{
  "type": "Feature",
  "properties": {
    "iso:country":"US",
    "sg:address":"728 Market St",
    "sg:city":"Sunbury",
    "sg:classifiers":[
        {
            "category":"Restaurant",
            "type":"Food & Drink"
        }
    ],
    "sg:phone":"+1 570 286 6182",
    "sg:postcode":"17801",
    "sg:province":"PA",
    "sg:tags":[
        "sandwich",
        "eating"
    ],
    "wof:name":"Marlin's Sub Shop",
    "wof:placetype":"venue"
},
  "geometry": {"coordinates":[-76.787584,40.860181],"type":"Point"}
}