{
  "type": "Feature",
  "properties": {
    "iso:country":"US",
    "sg:address":"1180 Canal Rd Exd",
    "sg:city":"Manchester",
    "sg:classifiers":[
        {
            "category":"Retail",
            "subcategory":"Repair Shop",
            "type":"Services"
        }
    ],
    "sg:phone":"+1 717 266 3328",
    "sg:postcode":"17345",
    "sg:province":"PA",
    "sg:tags":[
        "taxidermist"
    ],
    "wof:name":"Shelley's Pine Hill Taxidermy",
    "wof:placetype":"venue"
},
  "geometry": {"coordinates":[-76.73183899999999,40.06841],"type":"Point"}
}