{
  "type": "Feature",
  "properties": {
    "iso:country":"US",
    "sg:address":"1376 Freeport Rd",
    "sg:city":"Pittsburgh",
    "sg:classifiers":[
        {
            "category":"Real Estate",
            "subcategory":"Real Estate Agent",
            "type":"Services"
        }
    ],
    "sg:phone":"+1 412 782 3700",
    "sg:postcode":"15238",
    "sg:province":"PA",
    "sg:website":"www.prudentialpreferred.com",
    "wof:name":"Prudential Preferred Realty",
    "wof:placetype":"venue"
},
  "geometry": {"coordinates":[-79.870958,40.489945],"type":"Point"}
}