{
  "type": "Feature",
  "properties": {
    "iso:country":"US",
    "sg:address":"3401 Market St",
    "sg:city":"Philadelphia",
    "sg:classifiers":[
        {
            "category":"Food & Beverages",
            "subcategory":"Specialty",
            "type":"Retail Goods"
        }
    ],
    "sg:phone":"+1 215 222 3301",
    "sg:postcode":"19104",
    "sg:province":"PA",
    "sg:tags":[
        "vitamin"
    ],
    "wof:name":"Acumin Corp",
    "wof:placetype":"venue"
},
  "geometry": {"coordinates":[-75.194152,39.956179],"type":"Point"}
}