{
  "type": "Feature",
  "properties": {
    "iso:country":"US",
    "sg:address":"1065 Lakemont Dr",
    "sg:city":"Bridgeville",
    "sg:classifiers":[
        {
            "category":"Personal",
            "subcategory":"Beauty Salon",
            "type":"Services"
        }
    ],
    "sg:phone":"+1 412 257 2373",
    "sg:postcode":"15017",
    "sg:province":"PA",
    "sg:tags":[
        "shop"
    ],
    "wof:name":"Dr Regis P Englert",
    "wof:placetype":"venue"
},
  "geometry": {"coordinates":[-80.117783,40.33688],"type":"Point"}
}