{
  "type": "Feature",
  "properties": {
    "iso:country":"US",
    "sg:address":"1403 Trindle Rd",
    "sg:city":"Carlisle",
    "sg:classifiers":[
        {
            "category":"Shopping",
            "subcategory":"Used Merchandise",
            "type":"Retail Goods"
        }
    ],
    "sg:phone":"+1 717 243 7389",
    "sg:postcode":"17015",
    "sg:province":"PA",
    "sg:tags":[
        "shop",
        "consignment"
    ],
    "wof:name":"Heavenly Children Consignments",
    "wof:placetype":"venue"
},
  "geometry": {"coordinates":[-77.153358,40.199045],"type":"Point"}
}