{
  "type": "Feature",
  "properties": {
    "iso:country":"US",
    "sg:address":"1039 Barnswallow Ln",
    "sg:city":"Huntingdon Valley",
    "sg:classifiers":[
        {
            "category":"Shopping",
            "subcategory":"Gifts & Souvenirs",
            "type":"Retail Goods"
        }
    ],
    "sg:phone":"+1   ",
    "sg:postcode":"19006",
    "sg:province":"PA",
    "wof:name":"For The Children Inc",
    "wof:placetype":"venue"
},
  "geometry": {"coordinates":[-75.048277,40.154999],"type":"Point"}
}