{
  "type": "Feature",
  "properties": {
    "addr:full":"641 Linden Ave East Pittsburgh PA 15112",
    "addr:housenumber":"641",
    "addr:postcode":"15112",
    "addr:street":"Linden Ave East",
    "iso:country":"US",
    "sg:address":"641 Linden Ave",
    "sg:city":"East Pittsburgh",
    "sg:classifiers":[
        {
            "category":"Organizations",
            "subcategory":"Religious Organization",
            "type":"Services"
        }
    ],
    "sg:phone":"+1 412 824 7652",
    "sg:postcode":"15112",
    "sg:province":"PA",
    "sg:tags":[
        "church"
    ],
    "wof:name":"Emmanuel Lutheran Church",
    "wof:placetype":"venue"
},
  "geometry": {"coordinates":[-79.835184,40.400155],"type":"Point"}
}