{
  "type": "Feature",
  "properties": {
    "iso:country":"US",
    "sg:address":"563 South St",
    "sg:city":"Lykens",
    "sg:classifiers":[
        {
            "category":"Home & Garden",
            "subcategory":"Furniture",
            "type":"Retail Goods"
        }
    ],
    "sg:phone":"+1 717 453 9879",
    "sg:postcode":"17048",
    "sg:province":"PA",
    "wof:name":"Fry's Discount Furniture",
    "wof:placetype":"venue"
},
  "geometry": {"coordinates":[-76.701837,40.565233],"type":"Point"}
}