{
  "type": "Feature",
  "properties": {
    "iso:country":"US",
    "sg:address":"200 S Broad St Ste Fc3",
    "sg:city":"Philadelphia",
    "sg:classifiers":[
        {
            "category":"Deli",
            "type":"Food & Drink"
        },
        {
            "category":"Food & Beverages",
            "subcategory":"Bakery",
            "type":"Retail Goods"
        }
    ],
    "sg:phone":"+1 215 545 1910",
    "sg:postcode":"19102",
    "sg:province":"PA",
    "sg:tags":[
        "sandwich"
    ],
    "wof:name":"Bain's Deli Corporate Office",
    "wof:placetype":"venue"
},
  "geometry": {"coordinates":[-75.164536,39.949374],"type":"Point"}
}