{
  "type": "Feature",
  "properties": {
    "iso:country":"US",
    "sg:address":"254 Wyoming Ave",
    "sg:city":"Scranton",
    "sg:classifiers":[
        {
            "category":"Shopping",
            "subcategory":"Florist",
            "type":"Retail Goods"
        }
    ],
    "sg:phone":"+1 570 343 3563",
    "sg:postcode":"18503",
    "sg:province":"PA",
    "wof:name":"Creedon's Flower Shop",
    "wof:placetype":"venue"
},
  "geometry": {"coordinates":[-75.664233,41.40928],"type":"Point"}
}