{
  "type": "Feature",
  "properties": {
    "iso:country":"US",
    "sg:address":"428 W Mount Airy Ave",
    "sg:city":"Philadelphia",
    "sg:classifiers":[
        {
            "category":"Wholesale",
            "subcategory":"Durable Goods & Equipment",
            "type":"Manufacturing & Wholesale Goods"
        }
    ],
    "sg:phone":"+1   ",
    "sg:postcode":"19119",
    "sg:province":"PA",
    "wof:name":"Noya Business Network Inc",
    "wof:placetype":"venue"
},
  "geometry": {"coordinates":[-75.198421,40.053012],"type":"Point"}
}