{
  "type": "Feature",
  "properties": {
    "iso:country":"US",
    "sg:address":"210 E Siddonsburg Rd",
    "sg:city":"Dillsburg",
    "sg:classifiers":[
        {
            "category":"Real Estate",
            "subcategory":"Real Estate Operator",
            "type":"Services"
        }
    ],
    "sg:phone":"+1 717 796 0877",
    "sg:postcode":"17019",
    "sg:province":"PA",
    "sg:tags":[
        "apartment"
    ],
    "wof:name":"Spring Trindle Apartments",
    "wof:placetype":"venue"
},
  "geometry": {"coordinates":[-76.954926,40.150936],"type":"Point"}
}