{
  "type": "Feature",
  "properties": {
    "iso:country":"US",
    "sg:address":"208 S 45th St",
    "sg:city":"Philadelphia",
    "sg:classifiers":[
        {
            "category":"Shopping",
            "subcategory":"Beauty & Cosmetics",
            "type":"Retail Goods"
        }
    ],
    "sg:phone":"+1   ",
    "sg:postcode":"19104",
    "sg:province":"PA",
    "sg:tags":[
        "merchandise"
    ],
    "wof:name":"Harbins",
    "wof:placetype":"venue"
},
  "geometry": {"coordinates":[-75.211944,39.954394],"type":"Point"}
}