{
  "type": "Feature",
  "properties": {
    "iso:country":"US",
    "sg:address":"2 Northern Ave",
    "sg:city":"Nanticoke",
    "sg:classifiers":[
        {
            "category":"Utilities",
            "subcategory":"Fuel Oil & Lpg",
            "type":"Services"
        }
    ],
    "sg:phone":"+1   ",
    "sg:postcode":"18634",
    "sg:province":"PA",
    "sg:tags":[
        "dealer"
    ],
    "wof:name":"Eastern Fuel Oil",
    "wof:placetype":"venue"
},
  "geometry": {"coordinates":[-76.02542099999999,41.192493],"type":"Point"}
}