{
  "type": "Feature",
  "properties": {
    "iso:country":"US",
    "sg:address":"7163 Torresdale Ave",
    "sg:city":"Philadelphia",
    "sg:classifiers":[
        {
            "category":"Restaurant",
            "type":"Food & Drink"
        }
    ],
    "sg:phone":"+1 215 708 0427",
    "sg:postcode":"19135",
    "sg:province":"PA",
    "sg:tags":[
        "shop",
        "coffee"
    ],
    "wof:name":"Cafe Palermo",
    "wof:placetype":"venue"
},
  "geometry": {"coordinates":[-75.037025,40.029016],"type":"Point"}
}