{
  "type": "Feature",
  "properties": {
    "iso:country":"US",
    "sg:address":"2349 Market St",
    "sg:city":"Philadelphia",
    "sg:classifiers":[
        {
            "category":"Autos & Motor Vehicles",
            "subcategory":"Automobile Sales",
            "type":"Retail Goods"
        }
    ],
    "sg:phone":"+1 215 600 2653",
    "sg:postcode":"19103",
    "sg:province":"PA",
    "sg:tags":[
        "limo"
    ],
    "sg:website":"www.philadelphia-limousine.net",
    "wof:name":"Opex Limousine",
    "wof:placetype":"venue"
},
  "geometry": {"coordinates":[-75.178695,39.954284],"type":"Point"}
}