{
  "type": "Feature",
  "properties": {
    "iso:country":"US",
    "sg:address":"2425 Craley Rd",
    "sg:city":"Wrightsville",
    "sg:classifiers":[
        {
            "category":"Government",
            "subcategory":"Police Station",
            "type":"Public Place"
        }
    ],
    "sg:phone":"+1 717 244 8055",
    "sg:postcode":"17368",
    "sg:province":"PA",
    "sg:tags":[
        "department"
    ],
    "wof:name":"Lower Windsor Twp Police",
    "wof:placetype":"venue"
},
  "geometry": {"coordinates":[-76.52324299999999,39.941189],"type":"Point"}
}