{
  "type": "Feature",
  "properties": {
    "iso:country":"US",
    "sg:address":"615 Apache Ln",
    "sg:city":"Plymouth Meeting",
    "sg:classifiers":[
        {
            "category":"Freight",
            "type":"Transportation"
        }
    ],
    "sg:phone":"+1   ",
    "sg:postcode":"19462",
    "sg:province":"PA",
    "sg:tags":[
        "arrangement"
    ],
    "wof:name":"Michael D Bryan",
    "wof:placetype":"venue"
},
  "geometry": {"coordinates":[-75.280258,40.130095],"type":"Point"}
}