{
  "type": "Feature",
  "properties": {
    "iso:country":"US",
    "sg:address":"3229 Davison Rd",
    "sg:city":"Harborcreek",
    "sg:classifiers":[
        {
            "category":"Shopping",
            "subcategory":"Crafts & Fabrics",
            "type":"Retail Goods"
        }
    ],
    "sg:phone":"+1   ",
    "sg:postcode":"16421",
    "sg:province":"PA",
    "sg:tags":[
        "sewing"
    ],
    "wof:name":"Calico Patch",
    "wof:placetype":"venue"
},
  "geometry": {"coordinates":[-79.92292500000001,42.159332],"type":"Point"}
}