{
  "type": "Feature",
  "properties": {
    "iso:country":"US",
    "sg:address":"2236 Frankford Ave",
    "sg:city":"Philadelphia",
    "sg:classifiers":[
        {
            "category":"Shopping",
            "subcategory":"Pets & Pet Supplies",
            "type":"Retail Goods"
        },
        {
            "category":"Retail",
            "subcategory":"Animal Services",
            "type":"Services"
        }
    ],
    "sg:phone":"+1 267 909 9162",
    "sg:postcode":"19125",
    "sg:province":"PA",
    "sg:tags":[
        "grooming",
        "dog",
        "cat"
    ],
    "wof:name":"Groove Hound",
    "wof:placetype":"venue"
},
  "geometry": {"coordinates":[-75.128818,39.980524],"type":"Point"}
}