{
  "type": "Feature",
  "properties": {
    "iso:country":"US",
    "sg:address":"2003 Lincoln Way",
    "sg:city":"White Oak",
    "sg:classifiers":[
        {
            "category":"Banks & Credit Unions",
            "subcategory":"Bank",
            "type":"Services"
        }
    ],
    "sg:phone":"+1 412 678 3000",
    "sg:postcode":"15131",
    "sg:province":"PA",
    "wof:name":"Irwin Bank & Trust Co",
    "wof:placetype":"venue"
},
  "geometry": {"coordinates":[-79.808454,40.337247],"type":"Point"}
}