{
  "type": "Feature",
  "properties": {
    "iso:country":"US",
    "sg:address":"248 N Hobart St",
    "sg:city":"Philadelphia",
    "sg:classifiers":[
        {
            "category":"Health Services",
            "subcategory":"Medical Lab",
            "type":"Services"
        }
    ],
    "sg:phone":"+1 215 747 1299",
    "sg:postcode":"19139",
    "sg:province":"PA",
    "sg:tags":[
        "laboratory"
    ],
    "wof:name":"Ralph Williams Dental Lab",
    "wof:placetype":"venue"
},
  "geometry": {"coordinates":[-75.237354,39.965517],"type":"Point"}
}