{
  "type": "Feature",
  "properties": {
    "iso:country":"US",
    "sg:address":"17 Brenneman Cir",
    "sg:city":"Mechanicsburg",
    "sg:classifiers":[
        {
            "category":"Autos & Motor Vehicles",
            "subcategory":"Auto Supplies",
            "type":"Retail Goods"
        },
        {
            "category":"Retail",
            "subcategory":"Auto Repair",
            "type":"Services"
        },
        {
            "category":"Sports & Exercise",
            "subcategory":"Race Track",
            "type":"Entertainment"
        }
    ],
    "sg:phone":"+1 717 697 9733",
    "sg:postcode":"17050",
    "sg:province":"PA",
    "sg:tags":[
        "engine",
        "rebuilding",
        "exchange",
        "automobile",
        "equipment",
        "car",
        "performance",
        "racing",
        "engines-rebuild"
    ],
    "wof:name":"Performance Fuel Systems",
    "wof:placetype":"venue"
},
  "geometry": {"coordinates":[-77.05485,40.218796],"type":"Point"}
}