{
  "type": "Feature",
  "properties": {
    "iso:country":"US",
    "sg:address":"24 S Main St",
    "sg:city":"Port Allegany",
    "sg:classifiers":[
        {
            "category":"Autos & Motor Vehicles",
            "subcategory":"Automobile Sales",
            "type":"Retail Goods"
        }
    ],
    "sg:phone":"+1 814 642 9544",
    "sg:postcode":"16743",
    "sg:province":"PA",
    "sg:tags":[
        "car",
        "dealer"
    ],
    "wof:name":"Kightlinger Chevrolet",
    "wof:placetype":"venue"
},
  "geometry": {"coordinates":[-78.27978899999999,41.809733],"type":"Point"}
}