{
  "type": "Feature",
  "properties": {
    "iso:country":"US",
    "sg:address":"12 Oak Wood Ln",
    "sg:city":"Lititz",
    "sg:classifiers":[
        {
            "category":"Professional",
            "type":"Services"
        }
    ],
    "sg:phone":"+1   ",
    "sg:postcode":"17543",
    "sg:province":"PA",
    "wof:name":"Susan L Kohlmaier",
    "wof:placetype":"venue"
},
  "geometry": {"coordinates":[-76.32330899999999,40.135558],"type":"Point"}
}