{
  "type": "Feature",
  "properties": {
    "iso:country":"US",
    "sg:address":"1223 W Chester Pike",
    "sg:city":"Havertown",
    "sg:classifiers":[
        {
            "category":"Manufacturing",
            "subcategory":"Paper Products",
            "type":"Manufacturing & Wholesale Goods"
        }
    ],
    "sg:phone":"+1 610 789 2255",
    "sg:postcode":"19083",
    "sg:province":"PA",
    "sg:tags":[
        "converted",
        "mfg"
    ],
    "wof:name":"Eagle Auto Tags",
    "wof:placetype":"venue"
},
  "geometry": {"coordinates":[-75.319091,39.972974],"type":"Point"}
}