{
  "type": "Feature",
  "properties": {
    "iso:country":"US",
    "sg:address":"570 N Pike Rd",
    "sg:city":"Sarver",
    "sg:classifiers":[
        {
            "category":"Building & Trades",
            "subcategory":"Equipment Rental",
            "type":"Services"
        }
    ],
    "sg:phone":"+1 724 360 0900",
    "sg:postcode":"16055",
    "sg:province":"PA",
    "sg:tags":[
        "yard"
    ],
    "wof:name":"356 Rental Ctr",
    "wof:placetype":"venue"
},
  "geometry": {"coordinates":[-79.78641,40.767756],"type":"Point"}
}