{
  "type": "Feature",
  "properties": {
    "iso:country":"US",
    "sg:address":"181 Windover Turn",
    "sg:city":"Lancaster",
    "sg:classifiers":[
        {
            "category":"Professional",
            "subcategory":"Employment Agencies",
            "type":"Services"
        }
    ],
    "sg:phone":"+1 717 299 9242",
    "sg:postcode":"17601",
    "sg:province":"PA",
    "sg:tags":[
        "consultant",
        "search",
        "executive"
    ],
    "wof:name":"Stewart Associates",
    "wof:placetype":"venue"
},
  "geometry": {"coordinates":[-76.26237399999999,40.089599],"type":"Point"}
}