{
  "type": "Feature",
  "properties": {
    "iso:country":"US",
    "sg:address":"600 N 4th St",
    "sg:city":"Philadelphia",
    "sg:classifiers":[
        {
            "category":"Building & Trades",
            "subcategory":"Cleaning & Sanitation",
            "type":"Services"
        },
        {
            "category":"Wholesale",
            "subcategory":"Electrical",
            "type":"Manufacturing & Wholesale Goods"
        }
    ],
    "sg:phone":"+1 215 928 9761",
    "sg:postcode":"19123",
    "sg:province":"PA",
    "sg:tags":[
        "operated",
        "coin",
        "installation",
        "telephone",
        "card"
    ],
    "wof:name":"National Telecoin Corporation",
    "wof:placetype":"venue"
},
  "geometry": {"coordinates":[-75.14472499999999,39.962213],"type":"Point"}
}