{
  "type": "Feature",
  "properties": {
    "iso:country":"US",
    "sg:address":"226 Rocklawn Ln",
    "sg:city":"Lancaster",
    "sg:classifiers":[
        {
            "category":"Professional",
            "subcategory":"Secretarial Services",
            "type":"Services"
        }
    ],
    "sg:phone":"+1 717 290 7960",
    "sg:postcode":"17601",
    "sg:province":"PA",
    "sg:tags":[
        "reporting",
        "court"
    ],
    "wof:name":"Action Resume Svc",
    "wof:placetype":"venue"
},
  "geometry": {"coordinates":[-76.355215,40.056906],"type":"Point"}
}