{
  "type": "Feature",
  "properties": {
    "addr:full":"101 N 6th St Allentown PA 18102",
    "addr:housenumber":"101",
    "addr:postcode":"18102",
    "addr:street":"N 6Th St",
    "iso:country":"US",
    "sg:address":"101 N 6th St",
    "sg:city":"Allentown",
    "sg:classifiers":[
        {
            "category":"Professional",
            "subcategory":"Advertising",
            "type":"Services"
        }
    ],
    "sg:phone":"+1   ",
    "sg:postcode":"18102",
    "sg:province":"PA",
    "sg:tags":[
        "agency"
    ],
    "wof:name":"Display Advertising",
    "wof:placetype":"venue"
},
  "geometry": {"coordinates":[-75.47078500000001,40.60487],"type":"Point"}
}