{
  "type": "Feature",
  "properties": {
    "addr:full":"667 Grant St Hazleton PA 18201",
    "addr:housenumber":"667",
    "addr:postcode":"18201",
    "addr:street":"Grant St",
    "iso:country":"US",
    "sg:address":"667 Grant St",
    "sg:city":"Hazleton",
    "sg:classifiers":[
        {
            "category":"Personal",
            "subcategory":"Beauty Salon",
            "type":"Services"
        }
    ],
    "sg:phone":"+1 570 455 6688",
    "sg:postcode":"18201",
    "sg:province":"PA",
    "wof:name":"S Stacey Stelea Salon",
    "wof:placetype":"venue"
},
  "geometry": {"coordinates":[-75.985608,40.962894],"type":"Point"}
}