{
  "type": "Feature",
  "properties": {
    "addr:full":"1612 W Main St Uniontown PA 15401",
    "addr:housenumber":"1612",
    "addr:postcode":"15401",
    "addr:street":"W Main St",
    "iso:country":"US",
    "sg:address":"1612 W Main St",
    "sg:city":"Uniontown",
    "sg:classifiers":[
        {
            "category":"Shopping",
            "subcategory":"Computers & Home Electronics",
            "type":"Retail Goods"
        }
    ],
    "sg:phone":"+1   ",
    "sg:postcode":"15401",
    "sg:province":"PA",
    "wof:name":"Radio Shack",
    "wof:placetype":"venue"
},
  "geometry": {"coordinates":[-79.753766,39.918508],"type":"Point"}
}