{
  "type": "Feature",
  "properties": {
    "addr:full":"1243 Park City Center Lancaster PA 17601",
    "addr:housenumber":"1243",
    "addr:postcode":"17601",
    "addr:street":"Park",
    "iso:country":"US",
    "sg:address":"1243 Park City Center",
    "sg:city":"Lancaster",
    "sg:classifiers":[
        {
            "category":"Restaurant",
            "type":"Food & Drink"
        }
    ],
    "sg:phone":"+1 717 299 0885",
    "sg:postcode":"17601",
    "sg:province":"PA",
    "wof:name":"Chinese Gourmet Express",
    "wof:placetype":"venue"
},
  "geometry": {"coordinates":[-76.33841099999999,40.069766],"type":"Point"}
}