{
  "type": "Feature",
  "properties": {
    "addr:full":"1660 Valley Center Pkwy Bethlehem PA 18017",
    "addr:housenumber":"1660",
    "addr:postcode":"18017",
    "addr:street":"Valley Center Pkwy",
    "iso:country":"US",
    "sg:address":"1660 Valley Center Pkwy",
    "sg:city":"Bethlehem",
    "sg:classifiers":[
        {
            "category":"Real Estate",
            "subcategory":"Real Estate Agent",
            "type":"Services"
        }
    ],
    "sg:phone":"+1 610 866 1234",
    "sg:postcode":"18017",
    "sg:province":"PA",
    "sg:tags":[
        "brokerage"
    ],
    "wof:name":"Gelcor Realty Inc",
    "wof:placetype":"venue"
},
  "geometry": {"coordinates":[-75.40389399999999,40.654506],"type":"Point"}
}