{
  "type": "Feature",
  "properties": {
    "iso:country":"US",
    "sg:address":"1495 Valley Center Pkwy Ste 350",
    "sg:city":"Bethlehem",
    "sg:classifiers":[
        {
            "category":"Professional",
            "subcategory":"Lawyer & Legal Services",
            "type":"Services"
        }
    ],
    "sg:phone":"+1 484 895 2300",
    "sg:postcode":"18017",
    "sg:province":"PA",
    "wof:name":"Marshall Dennehey Warner Coleman & Goggin",
    "wof:placetype":"venue"
},
  "geometry": {"coordinates":[-75.4044,40.6536],"type":"Point"}
}