{
  "type": "Feature",
  "properties": {
    "iso:country":"US",
    "sg:address":"121 Meadow Ln",
    "sg:city":"Richboro",
    "sg:classifiers":[
        {
            "category":"Building & Trades",
            "subcategory":"Construction",
            "type":"Services"
        }
    ],
    "sg:phone":"+1   ",
    "sg:postcode":"18954",
    "sg:province":"PA",
    "sg:tags":[
        "contractor"
    ],
    "wof:name":"Robert Denito General Contr",
    "wof:placetype":"venue"
},
  "geometry": {"coordinates":[-75.007132,40.222398],"type":"Point"}
}