{
  "type": "Feature",
  "properties": {
    "iso:country":"US",
    "sg:address":"1 Penn St",
    "sg:city":"Marcus Hook",
    "sg:classifiers":[
        {
            "category":"Health Services",
            "subcategory":"Clinic",
            "type":"Services"
        }
    ],
    "sg:phone":"+1 610 485 9580",
    "sg:postcode":"19061",
    "sg:province":"PA",
    "wof:name":"Healthcare Environmental",
    "wof:placetype":"venue"
},
  "geometry": {"coordinates":[-75.414084,39.82146],"type":"Point"}
}