{
  "type": "Feature",
  "properties": {
    "addr:full":"1250 Bethlehem Pike Hatfield PA 19440",
    "addr:housenumber":"1250",
    "addr:postcode":"19440",
    "addr:street":"Bethlehem Pike",
    "iso:country":"US",
    "sg:address":"1250 Bethlehem Pike",
    "sg:city":"Hatfield",
    "sg:classifiers":[
        {
            "category":"Donuts",
            "subcategory":"None",
            "type":"Food & Drink"
        }
    ],
    "sg:phone":"+1 215 822 7800",
    "sg:postcode":"19440",
    "sg:province":"PA",
    "wof:name":"Baskin Robbins Ice Cream",
    "wof:placetype":"venue"
},
  "geometry": {"coordinates":[-75.281502,40.297001],"type":"Point"}
}