{
  "type": "Feature",
  "properties": {
    "addr:full":"2 N Main St Red Lion PA 17356",
    "addr:housenumber":"2",
    "addr:postcode":"17356",
    "addr:street":"N Main St",
    "iso:country":"US",
    "sg:address":"2 N Main St",
    "sg:city":"Red Lion",
    "sg:classifiers":[
        {
            "category":"Food & Beverages",
            "subcategory":"Groceries & Convenience Stores",
            "type":"Retail Goods"
        }
    ],
    "sg:phone":"+1   ",
    "sg:postcode":"17356",
    "sg:province":"PA",
    "wof:name":"Turkey Hill",
    "wof:placetype":"venue"
},
  "geometry": {"coordinates":[-76.60767800000001,39.901838],"type":"Point"}
}