{
  "type": "Feature",
  "properties": {
    "addr:full":"395 Bishop Hollow Rd Newtown Square PA 19073",
    "addr:housenumber":"395",
    "addr:postcode":"19073",
    "addr:street":"Bishop Hollow Rd",
    "iso:country":"US",
    "sg:address":"395 Bishop Hollow Rd",
    "sg:city":"Newtown Square",
    "sg:classifiers":[
        {
            "category":"Social Services",
            "subcategory":"Child Care",
            "type":"Services"
        }
    ],
    "sg:phone":"+1   ",
    "sg:postcode":"19073",
    "sg:province":"PA",
    "sg:tags":[
        "day"
    ],
    "wof:name":"Garret-Williamson Foundation",
    "wof:placetype":"venue"
},
  "geometry": {"coordinates":[-75.41600699999999,39.97453],"type":"Point"}
}