{
  "type": "Feature",
  "properties": {
    "addr:full":"129 Fayette St Conshohocken PA 19428",
    "addr:housenumber":"129",
    "addr:postcode":"19428",
    "addr:street":"Fayette St",
    "iso:country":"US",
    "sg:address":"129 Fayette St",
    "sg:city":"Conshohocken",
    "sg:classifiers":[
        {
            "category":"Arts & Performance",
            "subcategory":"Theater",
            "type":"Entertainment"
        }
    ],
    "sg:phone":"+1 610 825 1011",
    "sg:postcode":"19428",
    "sg:province":"PA",
    "sg:tags":[
        "bureau"
    ],
    "wof:name":"Plum Entertainment",
    "wof:placetype":"venue"
},
  "geometry": {"coordinates":[-75.305594,40.074434],"type":"Point"}
}