{
  "type": "Feature",
  "properties": {
    "addr:full":"39 Porter Rd Tower City PA 17980",
    "addr:housenumber":"39",
    "addr:postcode":"17980",
    "addr:street":"Porter Rd",
    "iso:country":"US",
    "sg:address":"39 Porter Rd",
    "sg:city":"Tower City",
    "sg:classifiers":[
        {
            "category":"Shopping",
            "type":"Retail Goods"
        }
    ],
    "sg:phone":"+1   ",
    "sg:postcode":"17980",
    "sg:province":"PA",
    "sg:tags":[
        "merchandise"
    ],
    "wof:name":"Evans Cemetary Memorial",
    "wof:placetype":"venue"
},
  "geometry": {"coordinates":[-76.577681,40.585153],"type":"Point"}
}