{
  "type": "Feature",
  "properties": {
    "iso:country":"US",
    "sg:address":"350 Northgate Dr",
    "sg:city":"Warrendale",
    "sg:classifiers":[
        {
            "category":"Building & Trades",
            "subcategory":"Plumbing",
            "type":"Services"
        }
    ],
    "sg:phone":"+1 724 934 5385",
    "sg:postcode":"15086",
    "sg:province":"PA",
    "sg:tags":[
        "sheet",
        "work",
        "metal",
        "contractor"
    ],
    "wof:name":"Duct Works Inc",
    "wof:placetype":"venue"
},
  "geometry": {"coordinates":[-80.08124599999999,40.65553],"type":"Point"}
}