{
  "type": "Feature",
  "properties": {
    "iso:country":"US",
    "sg:address":"1819 Sarah St",
    "sg:city":"Pittsburgh",
    "sg:classifiers":[
        {
            "category":"Real Estate",
            "subcategory":"Developer",
            "type":"Services"
        }
    ],
    "sg:phone":"+1 412 481 1600",
    "sg:postcode":"15203",
    "sg:province":"PA",
    "wof:name":"Healey Co",
    "wof:placetype":"venue"
},
  "geometry": {"coordinates":[-79.979421,40.427844],"type":"Point"}
}