{
  "type": "Feature",
  "properties": {
    "addr:full":"801 S Eisenhower Blvd Middletown PA 17057",
    "addr:housenumber":"801",
    "addr:postcode":"17057",
    "addr:street":"S Eisenhower Blvd",
    "iso:country":"US",
    "sg:address":"801 S Eisenhower Blvd",
    "sg:city":"Middletown",
    "sg:phone":"+1 717 939 5568",
    "sg:postcode":"17057",
    "sg:province":"PA",
    "sg:website":"http://www.wendys.com",
    "wof:name":"Wendy's",
    "wof:placetype":"venue"
},
  "geometry": {"coordinates":[-76.79084,40.21677],"type":"Point"}
}