{
  "type": "Feature",
  "properties": {
    "iso:country":"US",
    "sg:address":"8385 S Ridge Dr",
    "sg:city":"Macungie",
    "sg:classifiers":[
        {
            "category":"Shopping",
            "subcategory":"Clothing, Apparel, & Fashions",
            "type":"Retail Goods"
        }
    ],
    "sg:phone":"+1   ",
    "sg:postcode":"18062",
    "sg:province":"PA",
    "wof:name":"Uniform Factory Inc",
    "wof:placetype":"venue"
},
  "geometry": {"coordinates":[-75.596272,40.491984],"type":"Point"}
}