{
  "type": "Feature",
  "properties": {
    "iso:country":"US",
    "sg:address":"2101 Oregon Pike",
    "sg:city":"Lancaster",
    "sg:classifiers":[
        {
            "category":"Banks & Credit Unions",
            "subcategory":"Investment Brokerage",
            "type":"Services"
        }
    ],
    "sg:phone":"+1   ",
    "sg:postcode":"17601",
    "sg:province":"PA",
    "sg:tags":[
        "security"
    ],
    "wof:name":"Rbc Dain Rauscher Corporation",
    "wof:placetype":"venue"
},
  "geometry": {"coordinates":[-76.28594699999999,40.086392],"type":"Point"}
}