{
  "type": "Feature",
  "properties": {
    "iso:country":"US",
    "sg:address":"1630 Petunia St",
    "sg:city":"Pittsburgh",
    "sg:classifiers":[
        {
            "category":"Wholesale",
            "subcategory":"Hardware",
            "type":"Manufacturing & Wholesale Goods"
        }
    ],
    "sg:phone":"+1 412 882 5509",
    "sg:postcode":"15210",
    "sg:province":"PA",
    "sg:tags":[
        "equipment",
        "heating",
        "system"
    ],
    "wof:name":"Claytor Dance Co",
    "wof:placetype":"venue"
},
  "geometry": {"coordinates":[-80.00341899999999,40.399968],"type":"Point"}
}