{
  "type": "Feature",
  "properties": {
    "iso:country":"US",
    "sg:address":"106 E State St",
    "sg:city":"Doylestown",
    "sg:classifiers":[
        {
            "category":"Health Services",
            "subcategory":"Chiropractor",
            "type":"Services"
        }
    ],
    "sg:phone":"+1 215 348 3681",
    "sg:postcode":"18901",
    "sg:province":"PA",
    "wof:name":"Gewanter Alan B",
    "wof:placetype":"venue"
},
  "geometry": {"coordinates":[-75.128197,40.3111],"type":"Point"}
}