{
  "type": "Feature",
  "properties": {
    "iso:country":"US",
    "sg:address":"1175 Old York Rd",
    "sg:city":"Abington",
    "sg:classifiers":[
        {
            "category":"Government",
            "subcategory":"Office",
            "type":"Public Place"
        }
    ],
    "sg:phone":"+1 215 517 6572",
    "sg:postcode":"19001",
    "sg:province":"PA",
    "sg:tags":[
        "government-united",
        "state"
    ],
    "wof:name":"U S Government Of Congress Schwartz Allison Y",
    "wof:placetype":"venue"
},
  "geometry": {"coordinates":[-75.120496,40.116828],"type":"Point"}
}