{
  "type": "Feature",
  "properties": {
    "addr:full":"100 Quarry Rd Leola PA 17540",
    "addr:housenumber":"100",
    "addr:postcode":"17540",
    "addr:street":"Quarry Rd",
    "iso:country":"US",
    "sg:address":"100 Quarry Rd",
    "sg:city":"Leola",
    "sg:classifiers":[
        {
            "category":"Organizations",
            "subcategory":"Religious Organization",
            "type":"Services"
        }
    ],
    "sg:phone":"+1 717 656 6227",
    "sg:postcode":"17540",
    "sg:province":"PA",
    "sg:tags":[
        "church"
    ],
    "sg:website":"www.foresthillschurch.org",
    "wof:name":"Forest Hills Mennonite Church",
    "wof:placetype":"venue"
},
  "geometry": {"coordinates":[-76.21257199999999,40.092679],"type":"Point"}
}