{
  "type": "Feature",
  "properties": {
    "iso:country":"US",
    "sg:address":"1444 Village Rd",
    "sg:city":"Strasburg",
    "sg:classifiers":[
        {
            "category":"Recreation",
            "type":"Entertainment"
        }
    ],
    "sg:phone":"+1   ",
    "sg:postcode":"17579",
    "sg:province":"PA",
    "wof:name":"Village Green Golf Inc",
    "wof:placetype":"venue"
},
  "geometry": {"coordinates":[-76.210111,39.984228],"type":"Point"}
}