{
  "type": "Feature",
  "properties": {
    "iso:country":"US",
    "sg:address":"6 Cricket Grn",
    "sg:city":"Lancaster",
    "sg:classifiers":[
        {
            "category":"Personal",
            "type":"Services"
        },
        {
            "category":"Professional",
            "subcategory":"Art Services",
            "type":"Services"
        }
    ],
    "sg:phone":"+1 717 327 6042",
    "sg:postcode":"17602",
    "sg:province":"PA",
    "sg:tags":[
        "photography",
        "videography",
        "wedding"
    ],
    "wof:name":"Julie Davis Photography",
    "wof:placetype":"venue"
},
  "geometry": {"coordinates":[-76.24690699999999,40.016263],"type":"Point"}
}