{
  "type": "Feature",
  "properties": {
    "addr:full":"400 Grant Ave Millvale PA 15209",
    "addr:housenumber":"400",
    "addr:postcode":"15209",
    "addr:street":"Grant Ave",
    "iso:country":"US",
    "sg:address":"400 Grant Ave",
    "sg:city":"Millvale",
    "sg:classifiers":[
        {
            "category":"Banks & Credit Unions",
            "subcategory":"Bank",
            "type":"Services"
        }
    ],
    "sg:phone":"+1 412 821 6600",
    "sg:postcode":"15209",
    "sg:province":"PA",
    "sg:tags":[
        "state"
    ],
    "wof:name":"National City Bank",
    "wof:placetype":"venue"
},
  "geometry": {"coordinates":[-79.973957,40.480356],"type":"Point"}
}