{
  "type": "Feature",
  "properties": {
    "iso:country":"US",
    "sg:address":"541 Royal Ave",
    "sg:city":"Havertown",
    "sg:classifiers":[
        {
            "category":"Organizations",
            "subcategory":"Non-profit Organization",
            "type":"Services"
        }
    ],
    "sg:phone":"+1 610 446 6008",
    "sg:postcode":"19083",
    "sg:province":"PA",
    "wof:name":"Bon Air Fire Co",
    "wof:placetype":"venue"
},
  "geometry": {"coordinates":[-75.322643,39.964237],"type":"Point"}
}