{
  "type": "Feature",
  "properties": {
    "addr:full":"3525 Welsh Rd Willow Grove PA 19090",
    "addr:housenumber":"3525",
    "addr:postcode":"19090",
    "addr:street":"Welsh Rd",
    "iso:country":"US",
    "sg:address":"3525 Welsh Rd",
    "sg:city":"Willow Grove",
    "sg:classifiers":[
        {
            "category":"Health Services",
            "subcategory":"Doctor",
            "type":"Services"
        }
    ],
    "sg:phone":"+1 215 659 6301",
    "sg:postcode":"19090",
    "sg:province":"PA",
    "sg:tags":[
        "medical"
    ],
    "wof:name":"Willow Grove Internal Medicine",
    "wof:placetype":"venue"
},
  "geometry": {"coordinates":[-75.13544899999999,40.152423],"type":"Point"}
}