{
  "type": "Feature",
  "properties": {
    "iso:country":"US",
    "sg:address":"1040 Benner Pike",
    "sg:city":"State College",
    "sg:classifiers":[
        {
            "category":"Real Estate",
            "subcategory":"Architect",
            "type":"Services"
        }
    ],
    "sg:phone":"+1 814 867 4193",
    "sg:postcode":"16801",
    "sg:province":"PA",
    "sg:tags":[
        "building",
        "management",
        "engineering",
        "s",
        "construction",
        "architectural"
    ],
    "wof:name":"Maguire Group Inc",
    "wof:placetype":"venue"
},
  "geometry": {"coordinates":[-77.797102,40.840763],"type":"Point"}
}