{
  "type": "Feature",
  "properties": {
    "iso:country":"US",
    "sg:address":"778 Lebanon Ave",
    "sg:city":"Mt Lebanon",
    "sg:classifiers":[
        {
            "category":"Building & Trades",
            "subcategory":"Landscaping Services",
            "type":"Services"
        }
    ],
    "sg:phone":"+1 412 344 6219",
    "sg:postcode":"15228",
    "sg:province":"PA",
    "sg:tags":[
        "tree"
    ],
    "wof:name":"Thanksgiving Tree Co",
    "wof:placetype":"venue"
},
  "geometry": {"coordinates":[-80.05373899999999,40.376417],"type":"Point"}
}