{
  "type": "Feature",
  "properties": {
    "addr:full":"115 Sunset Dr Mc Knight PA 15237",
    "addr:housenumber":"115",
    "addr:postcode":"15237",
    "addr:street":"Sunset Dr",
    "iso:country":"US",
    "sg:address":"115 Sunset Dr",
    "sg:city":"Mc Knight",
    "sg:classifiers":[
        {
            "category":"Professional",
            "subcategory":"Art Services",
            "type":"Services"
        }
    ],
    "sg:phone":"+1 412 684 1094",
    "sg:postcode":"15237",
    "sg:province":"PA",
    "sg:tags":[
        "photographer"
    ],
    "wof:name":"Image Point Pittsburgh",
    "wof:placetype":"venue"
},
  "geometry": {"coordinates":[-79.994001,40.531729],"type":"Point"}
}