{
  "type": "Feature",
  "properties": {
    "iso:country":"US",
    "sg:address":"301 Country Club Rd",
    "sg:city":"Dallas",
    "sg:classifiers":[
        {
            "category":"Retail",
            "subcategory":"Repair Shop",
            "type":"Services"
        }
    ],
    "sg:phone":"+1 570 674 3188",
    "sg:postcode":"18612",
    "sg:province":"PA",
    "sg:tags":[
        "water",
        "pressure",
        "cleaning"
    ],
    "wof:name":"Clean Shot Of Nepa",
    "wof:placetype":"venue"
},
  "geometry": {"coordinates":[-75.976298,41.354789],"type":"Point"}
}