{
  "type": "Feature",
  "properties": {
    "iso:country":"US",
    "sg:address":"329 E Baltimore Ave ",
    "sg:city":"Clifton Heights",
    "sg:classifiers":[
        {
            "category":"Restaurant",
            "type":"Food & Drink"
        }
    ],
    "sg:menulink":"http://www.allmenus.com/pa/clifton-heights/291555-walks-steak/menu/",
    "sg:phone":"+1 610 623 3355",
    "sg:postcode":"19018",
    "sg:province":"PA",
    "sg:tags":[
        "sandwich",
        "hoagy",
        "salad",
        "pizza"
    ],
    "wof:name":"Walk's Steak",
    "wof:placetype":"venue"
},
  "geometry": {"coordinates":[-75.291567,39.931806],"type":"Point"}
}