{
  "type": "Feature",
  "properties": {
    "iso:country":"US",
    "sg:address":"6700 Tulip St",
    "sg:city":"Philadelphia",
    "sg:classifiers":[
        {
            "category":"Social Services",
            "type":"Services"
        }
    ],
    "sg:phone":"+1 215 333 7775",
    "sg:postcode":"19135",
    "sg:province":"PA",
    "sg:tags":[
        "organization",
        "welfare"
    ],
    "wof:name":"Co-Dependents Anonymous",
    "wof:placetype":"venue"
},
  "geometry": {"coordinates":[-75.04388,40.022681],"type":"Point"}
}