{
  "type": "Feature",
  "properties": {
    "iso:country":"US",
    "sg:address":"88 Rose Ln",
    "sg:city":"Belleville",
    "sg:classifiers":[
        {
            "category":"Farming",
            "subcategory":"Dairy Farm",
            "type":"Manufacturing & Wholesale Goods"
        }
    ],
    "sg:phone":"+1 717 483 6673",
    "sg:postcode":"17004",
    "sg:province":"PA",
    "wof:name":"Joseph L Glick",
    "wof:placetype":"venue"
},
  "geometry": {"coordinates":[-77.789957,40.560805],"type":"Point"}
}