{
  "type": "Feature",
  "properties": {
    "addr:full":"3596 Penns Valley Pike Spring Mills PA 16875",
    "addr:housenumber":"3596",
    "addr:postcode":"16875",
    "addr:street":"Penns Valley Pike",
    "iso:country":"US",
    "sg:address":"3596 Penns Valley Pike",
    "sg:city":"Spring Mills",
    "sg:classifiers":[
        {
            "category":"Manufacturing",
            "subcategory":"Metals",
            "type":"Manufacturing & Wholesale Goods"
        }
    ],
    "sg:phone":"+1 814 422 0262",
    "sg:postcode":"16875",
    "sg:province":"PA",
    "sg:tags":[
        "fence"
    ],
    "sg:website":"www.qsfvinylproducts.com",
    "wof:name":"Quality Swings & Fencing",
    "wof:placetype":"venue"
},
  "geometry": {"coordinates":[-77.581209,40.855511],"type":"Point"}
}