{
  "type": "Feature",
  "properties": {
    "iso:country":"US",
    "sg:address":"726 N 4th Ave",
    "sg:city":"Altoona",
    "sg:classifiers":[
        {
            "category":"Social Services",
            "subcategory":"Child Care",
            "type":"Services"
        }
    ],
    "sg:phone":"+1   ",
    "sg:postcode":"16601",
    "sg:province":"PA",
    "sg:tags":[
        "day"
    ],
    "wof:name":"1 To Grow On",
    "wof:placetype":"venue"
},
  "geometry": {"coordinates":[-78.380594,40.539141],"type":"Point"}
}