{
  "type": "Feature",
  "properties": {
    "iso:country":"US",
    "sg:address":"1636 Union Blvd",
    "sg:city":"Allentown",
    "sg:classifiers":[
        {
            "category":"Banks & Credit Unions",
            "subcategory":"Bank",
            "type":"Services"
        }
    ],
    "sg:phone":"+1 610 820 3717",
    "sg:postcode":"18109",
    "sg:province":"PA",
    "sg:tags":[
        "loan"
    ],
    "wof:name":"Equity One",
    "wof:placetype":"venue"
},
  "geometry": {"coordinates":[-75.431296,40.625087],"type":"Point"}
}