{
  "type": "Feature",
  "properties": {
    "iso:country":"US",
    "sg:address":"3865 Ridge Pike",
    "sg:city":"Collegeville",
    "sg:classifiers":[
        {
            "category":"Retail",
            "subcategory":"Auto Repair",
            "type":"Services"
        }
    ],
    "sg:phone":"+1 610 489 6142",
    "sg:postcode":"19426",
    "sg:province":"PA",
    "sg:tags":[
        "body",
        "automobile",
        "painting"
    ],
    "wof:name":"Grand Sport Auto Body Inc",
    "wof:placetype":"venue"
},
  "geometry": {"coordinates":[-75.43732799999999,40.177122],"type":"Point"}
}