{
  "type": "Feature",
  "properties": {
    "iso:country":"US",
    "sg:address":"212 S 40th St",
    "sg:city":"Philadelphia",
    "sg:classifiers":[
        {
            "category":"Shopping",
            "subcategory":"Mobile Phones",
            "type":"Retail Goods"
        }
    ],
    "sg:phone":"+1 215 662 5949",
    "sg:postcode":"19104",
    "sg:province":"PA",
    "sg:website":"www.radioshack.com",
    "wof:name":"Radioshack",
    "wof:placetype":"venue"
},
  "geometry": {"coordinates":[-75.202797,39.953701],"type":"Point"}
}