{
  "type": "Feature",
  "properties": {
    "iso:country":"US",
    "sg:address":"151 S 60th St",
    "sg:city":"Philadelphia",
    "sg:classifiers":[
        {
            "category":"Shopping",
            "subcategory":"Used Merchandise",
            "type":"Retail Goods"
        }
    ],
    "sg:phone":"+1 215 747 7005",
    "sg:postcode":"19139",
    "sg:province":"PA",
    "sg:tags":[
        "furniture"
    ],
    "wof:name":"Ikes Used Furniture Store",
    "wof:placetype":"venue"
},
  "geometry": {"coordinates":[-75.24128399999999,39.959428],"type":"Point"}
}