{
  "type": "Feature",
  "properties": {
    "iso:country":"US",
    "sg:address":"6632 Akron St",
    "sg:city":"Philadelphia",
    "sg:classifiers":[
        {
            "category":"Wholesale",
            "subcategory":"Non-durable Goods",
            "type":"Manufacturing & Wholesale Goods"
        }
    ],
    "sg:phone":"+1   ",
    "sg:postcode":"19149",
    "sg:province":"PA",
    "wof:name":"Simco Sportswear Advg Special",
    "wof:placetype":"venue"
},
  "geometry": {"coordinates":[-75.06795,40.039315],"type":"Point"}
}