{
  "type": "Feature",
  "properties": {
    "iso:country":"US",
    "sg:address":"2405 Federal St",
    "sg:city":"Philadelphia",
    "sg:classifiers":[
        {
            "category":"Manufacturing",
            "subcategory":"Glass & Minerals",
            "type":"Manufacturing & Wholesale Goods"
        }
    ],
    "sg:phone":"+1 215 546 5777",
    "sg:postcode":"19146",
    "sg:province":"PA",
    "sg:tags":[
        "product",
        "marble"
    ],
    "wof:name":"Angelo's Marble & Granite",
    "wof:placetype":"venue"
},
  "geometry": {"coordinates":[-75.185232,39.938578],"type":"Point"}
}