{
  "type": "Feature",
  "properties": {
    "iso:country":"US",
    "sg:address":"5150 Liberty Ave",
    "sg:city":"Pittsburgh",
    "sg:classifiers":[
        {
            "category":"Personal",
            "subcategory":"Beauty Salon",
            "type":"Services"
        }
    ],
    "sg:phone":"+1 412 682 3436",
    "sg:postcode":"15224",
    "sg:province":"PA",
    "wof:name":"Russell Kopf's Hair Care Ctr",
    "wof:placetype":"venue"
},
  "geometry": {"coordinates":[-79.93972599999999,40.456596],"type":"Point"}
}