{
  "type": "Feature",
  "properties": {
    "iso:country":"US",
    "sg:address":"561 S Dock St",
    "sg:city":"Sharon",
    "sg:classifiers":[
        {
            "category":"Professional",
            "subcategory":"Accounting & Tax Preparation",
            "type":"Services"
        }
    ],
    "sg:phone":"+1 724 347 7138",
    "sg:postcode":"16146",
    "sg:province":"PA",
    "sg:tags":[
        "return",
        "filing"
    ],
    "wof:name":"Jackson Hewitt Tax Svc",
    "wof:placetype":"venue"
},
  "geometry": {"coordinates":[-80.50704399999999,41.227119],"type":"Point"}
}