{
  "type": "Feature",
  "properties": {
    "addr:full":"1420 Locust St Ste 210 Philadelphia PA 19102",
    "addr:housenumber":"1420",
    "addr:postcode":"19102",
    "addr:street":"Locust St Ste 210",
    "iso:country":"US",
    "sg:address":"1420 Locust St Ste 210",
    "sg:city":"Philadelphia",
    "sg:classifiers":[
        {
            "category":"Arts & Performance",
            "subcategory":"Arts Center",
            "type":"Entertainment"
        },
        {
            "category":"Cinema",
            "subcategory":"Movie Theater",
            "type":"Entertainment"
        }
    ],
    "sg:phone":"+1 215 893 3600",
    "sg:postcode":"19102",
    "sg:province":"PA",
    "sg:tags":[
        "performing"
    ],
    "sg:website":"www.operaphilly.com",
    "wof:name":"Opera Co of Philadelphia",
    "wof:placetype":"venue"
},
  "geometry": {"coordinates":[-75.164902,39.9482],"type":"Point"}
}