{
  "type": "Feature",
  "properties": {
    "iso:country":"US",
    "sg:address":"4021 W 12th St",
    "sg:city":"Erie",
    "sg:classifiers":[
        {
            "category":"Professional",
            "subcategory":"Lawyer & Legal Services",
            "type":"Services"
        }
    ],
    "sg:phone":"+1   ",
    "sg:postcode":"16505",
    "sg:province":"PA",
    "wof:name":"Harold J Bender Attorney",
    "wof:placetype":"venue"
},
  "geometry": {"coordinates":[-80.172579,42.089756],"type":"Point"}
}