{
  "type": "Feature",
  "properties": {
    "addr:full":"1419 Alverado Ave Pittsburgh PA 15216",
    "addr:housenumber":"1419",
    "addr:postcode":"15216",
    "addr:street":"Alverado Ave",
    "iso:country":"US",
    "sg:address":"1419 Alverado Ave",
    "sg:city":"Pittsburgh",
    "sg:classifiers":[
        {
            "category":"Building & Trades",
            "subcategory":"Electrical",
            "type":"Services"
        }
    ],
    "sg:phone":"+1 412 531 8576",
    "sg:postcode":"15216",
    "sg:province":"PA",
    "sg:tags":[
        "electric",
        "industrial",
        "contractors-commercial",
        "contractor"
    ],
    "wof:name":"Tumicki, A C Electric Co",
    "wof:placetype":"venue"
},
  "geometry": {"coordinates":[-80.02857,40.414145],"type":"Point"}
}