{
  "type": "Feature",
  "properties": {
    "iso:country":"US",
    "sg:address":"3731 Carlisle Rd",
    "sg:city":"Dover",
    "sg:classifiers":[
        {
            "category":"Health Services",
            "subcategory":"Podiatrist",
            "type":"Services"
        }
    ],
    "sg:phone":"+1 717 292 1455",
    "sg:postcode":"17315",
    "sg:province":"PA",
    "wof:name":"Kenneth D Dunlap Jr DPM",
    "wof:placetype":"venue"
},
  "geometry": {"coordinates":[-76.838776,39.990277],"type":"Point"}
}