{
  "type": "Feature",
  "properties": {
    "iso:country":"US",
    "sg:address":"4750 Centre Ave",
    "sg:city":"Pittsburgh",
    "sg:classifiers":[
        {
            "category":"Real Estate",
            "subcategory":"Real Estate Operator",
            "type":"Services"
        }
    ],
    "sg:phone":"+1 412 681 4750",
    "sg:postcode":"15213",
    "sg:province":"PA",
    "sg:tags":[
        "apartment"
    ],
    "wof:name":"4750 Center Avenue Inc",
    "wof:placetype":"venue"
},
  "geometry": {"coordinates":[-79.94638999999999,40.453498],"type":"Point"}
}