{
  "type": "Feature",
  "properties": {
    "iso:country":"US",
    "sg:address":"4236 Neilson St",
    "sg:city":"Philadelphia",
    "sg:classifiers":[
        {
            "category":"Wholesale",
            "subcategory":"Electrical",
            "type":"Manufacturing & Wholesale Goods"
        }
    ],
    "sg:phone":"+1 215 739 5929",
    "sg:postcode":"19124",
    "sg:province":"PA",
    "sg:tags":[
        "electronic"
    ],
    "wof:name":"Electronic Heaven",
    "wof:placetype":"venue"
},
  "geometry": {"coordinates":[-75.097212,40.011171],"type":"Point"}
}