{
  "type": "Feature",
  "properties": {
    "iso:country":"US",
    "sg:address":"516 Grandview Ave",
    "sg:city":"Pittsburgh",
    "sg:classifiers":[
        {
            "category":"Building & Trades",
            "subcategory":"Construction",
            "type":"Services"
        }
    ],
    "sg:phone":"+1   ",
    "sg:postcode":"15211",
    "sg:province":"PA",
    "sg:tags":[
        "house"
    ],
    "wof:name":"Berry & Stufft Inc",
    "wof:placetype":"venue"
},
  "geometry": {"coordinates":[-80.012716,40.435385],"type":"Point"}
}