{
  "type": "Feature",
  "properties": {
    "addr:full":"25 Sandy Cir Manchester PA 17345",
    "addr:housenumber":"25",
    "addr:postcode":"17345",
    "addr:street":"Sandy Cir",
    "iso:country":"US",
    "sg:address":"25 Sandy Cir",
    "sg:city":"Manchester",
    "sg:classifiers":[
        {
            "category":"Building & Trades",
            "subcategory":"Construction",
            "type":"Services"
        }
    ],
    "sg:phone":"+1   ",
    "sg:postcode":"17345",
    "sg:province":"PA",
    "sg:tags":[
        "contractor"
    ],
    "wof:name":"Silk - Artist com",
    "wof:placetype":"venue"
},
  "geometry": {"coordinates":[-76.722064,40.070388],"type":"Point"}
}