{
  "type": "Feature",
  "properties": {
    "addr:full":"1831 Chestnut Street Suite 502 Philadelphia PA 19103 ",
    "addr:housenumber":"1831",
    "addr:postcode":"19103",
    "addr:street":"Chestnut Street Suite 502",
    "iso:country":"US",
    "sg:address":"1831 Chestnut Street Suite 502",
    "sg:city":"Philadelphia",
    "sg:classifiers":[
        {
            "category":"Professional",
            "subcategory":"Computer Services",
            "type":"Services"
        }
    ],
    "sg:phone":"+1 215 564 4002",
    "sg:postcode":"19103 ",
    "sg:province":"PA",
    "sg:website":"http://www.ideapartnerships.com/",
    "wof:name":"Idea Partnership",
    "wof:placetype":"venue"
},
  "geometry": {"coordinates":[-75.171533,39.95187],"type":"Point"}
}