{
  "type": "Feature",
  "properties": {
    "addr:full":"1412 Patterson St Mckeesport PA 15132",
    "addr:housenumber":"1412",
    "addr:postcode":"15132",
    "addr:street":"Patterson St",
    "iso:country":"US",
    "sg:address":"1412 Patterson St",
    "sg:city":"Mckeesport",
    "sg:classifiers":[
        {
            "category":"Professional",
            "subcategory":"Accounting & Tax Preparation",
            "type":"Services"
        }
    ],
    "sg:phone":"+1 412 673 8297",
    "sg:postcode":"15132",
    "sg:province":"PA",
    "sg:tags":[
        "accountant"
    ],
    "wof:name":"Brooks' Bookkeeping & Accntng",
    "wof:placetype":"venue"
},
  "geometry": {"coordinates":[-79.837768,40.343047],"type":"Point"}
}