{
  "type": "Feature",
  "properties": {
    "iso:country":"US",
    "sg:address":"817 N Chester Rd",
    "sg:city":"West Chester",
    "sg:classifiers":[
        {
            "category":"Manufacturing",
            "subcategory":"Rubber & Plastics",
            "type":"Manufacturing & Wholesale Goods"
        }
    ],
    "sg:phone":"+1 610 429 9449",
    "sg:postcode":"19380",
    "sg:province":"PA",
    "sg:tags":[
        "gasket"
    ],
    "sg:website":"www.effshield.com",
    "wof:name":"Effective Shielding Co",
    "wof:placetype":"venue"
},
  "geometry": {"coordinates":[-75.544252,39.994591],"type":"Point"}
}