{
  "type": "Feature",
  "properties": {
    "iso:country":"US",
    "sg:address":"207 S Main St",
    "sg:city":"Pittsburgh",
    "sg:classifiers":[
        {
            "category":"Arts & Performance",
            "subcategory":"Theater",
            "type":"Entertainment"
        }
    ],
    "sg:phone":"+1   ",
    "sg:postcode":"15220",
    "sg:province":"PA",
    "sg:tags":[
        "theatrical"
    ],
    "wof:name":"Richard E Rauh Conservatory",
    "wof:placetype":"venue"
},
  "geometry": {"coordinates":[-80.031451,40.442105],"type":"Point"}
}