{
  "type": "Feature",
  "properties": {
    "iso:country":"US",
    "sg:address":"2520 Lititz Pike",
    "sg:city":"Lancaster",
    "sg:classifiers":[
        {
            "category":"Wholesale",
            "subcategory":"Petroleum",
            "type":"Manufacturing & Wholesale Goods"
        }
    ],
    "sg:phone":"+1 717 519 0590",
    "sg:postcode":"17601",
    "sg:province":"PA",
    "sg:tags":[
        "bulk",
        "product",
        "station"
    ],
    "wof:name":"Power Test",
    "wof:placetype":"venue"
},
  "geometry": {"coordinates":[-76.304742,40.094553],"type":"Point"}
}