{
  "type": "Feature",
  "properties": {
    "iso:country":"US",
    "sg:address":"434 Centreville Pike",
    "sg:city":"Slippery Rock",
    "sg:classifiers":[
        {
            "category":"Building & Trades",
            "subcategory":"Construction",
            "type":"Services"
        }
    ],
    "sg:phone":"+1   ",
    "sg:postcode":"16057",
    "sg:province":"PA",
    "sg:tags":[
        "contractor"
    ],
    "wof:name":"Jay Troy Construction",
    "wof:placetype":"venue"
},
  "geometry": {"coordinates":[-80.028704,41.034292],"type":"Point"}
}