{
  "type": "Feature",
  "properties": {
    "iso:country":"US",
    "sg:address":"342 N Pine St",
    "sg:city":"Middletown",
    "sg:classifiers":[
        {
            "category":"Organizations",
            "subcategory":"Membership Organization",
            "type":"Services"
        }
    ],
    "sg:phone":"+1   ",
    "sg:postcode":"17057",
    "sg:province":"PA",
    "wof:name":"Daughter American Revolution",
    "wof:placetype":"venue"
},
  "geometry": {"coordinates":[-76.729457,40.199916],"type":"Point"}
}