{
  "type": "Feature",
  "properties": {
    "iso:country":"US",
    "sg:address":"2723 Pottsville Minersville Hwy",
    "sg:city":"Pottsville",
    "sg:classifiers":[
        {
            "category":"Building & Trades",
            "subcategory":"Construction",
            "type":"Services"
        }
    ],
    "sg:phone":"+1   ",
    "sg:postcode":"17901",
    "sg:province":"PA",
    "sg:tags":[
        "installation",
        "carpet"
    ],
    "wof:name":"Jims Carpet Service",
    "wof:placetype":"venue"
},
  "geometry": {"coordinates":[-76.24705299999999,40.67721],"type":"Point"}
}