{
  "type": "Feature",
  "properties": {
    "iso:country":"US",
    "sg:address":"274 Lovedale Rd",
    "sg:city":"Elizabeth",
    "sg:classifiers":[
        {
            "category":"Retail",
            "subcategory":"Auto Repair",
            "type":"Services"
        }
    ],
    "sg:phone":"+1 412 384 7700",
    "sg:postcode":"15037",
    "sg:province":"PA",
    "sg:website":"www.elizabethautocare.com",
    "wof:name":"Elizabeth AutoCare",
    "wof:placetype":"venue"
},
  "geometry": {"coordinates":[-79.868599,40.277151],"type":"Point"}
}