{
  "type": "Feature",
  "properties": {
    "iso:country":"US",
    "sg:address":"371 E Street Rd",
    "sg:city":"Southampton",
    "sg:classifiers":[
        {
            "category":"Professional",
            "subcategory":"Computer Services",
            "type":"Services"
        }
    ],
    "sg:phone":"+1 215 357 3579",
    "sg:postcode":"18966",
    "sg:province":"PA",
    "sg:tags":[
        "website",
        "design"
    ],
    "sg:website":"www.custommediagroup.com",
    "wof:name":"Custom Media Group Inc",
    "wof:placetype":"venue"
},
  "geometry": {"coordinates":[-75.052097,40.179584],"type":"Point"}
}