{
  "type": "Feature",
  "properties": {
    "iso:country":"US",
    "sg:address":"40 Behrens Rd",
    "sg:city":"Jim Thorpe",
    "sg:classifiers":[
        {
            "category":"Freight",
            "type":"Transportation"
        }
    ],
    "sg:phone":"+1 570 325 9470",
    "sg:postcode":"18229",
    "sg:province":"PA",
    "sg:tags":[
        "trucking"
    ],
    "wof:name":"Eurologistics",
    "wof:placetype":"venue"
},
  "geometry": {"coordinates":[-75.67429,40.919553],"type":"Point"}
}