{
  "type": "Feature",
  "properties": {
    "addr:full":"175 Strafford Ave Wayne PA 19087",
    "addr:housenumber":"175",
    "addr:postcode":"19087",
    "addr:street":"Strafford Ave",
    "iso:country":"US",
    "sg:address":"175 Strafford Ave",
    "sg:city":"Wayne",
    "sg:classifiers":[
        {
            "category":"Insurance",
            "subcategory":"Insurance Agent",
            "type":"Services"
        }
    ],
    "sg:phone":"+1 610 254 0895",
    "sg:postcode":"19087",
    "sg:province":"PA",
    "sg:tags":[
        "consultant"
    ],
    "wof:name":"CMS Inc-Financial Planners",
    "wof:placetype":"venue"
},
  "geometry": {"coordinates":[-75.398426,40.045541],"type":"Point"}
}