{
  "type": "Feature",
  "properties": {
    "addr:full":"302 Main St Great Bend PA 18821",
    "addr:housenumber":"302",
    "addr:postcode":"18821",
    "addr:street":"Main St",
    "iso:country":"US",
    "sg:address":"302 Main St",
    "sg:city":"Great Bend",
    "sg:classifiers":[
        {
            "category":"Professional",
            "subcategory":"Accounting & Tax Preparation",
            "type":"Services"
        }
    ],
    "sg:phone":"+1 570 879 5500",
    "sg:postcode":"18821",
    "sg:province":"PA",
    "sg:tags":[
        "return",
        "filing"
    ],
    "wof:name":"Jackson Hewitt Tax Svc",
    "wof:placetype":"venue"
},
  "geometry": {"coordinates":[-75.744314,41.97273],"type":"Point"}
}