{
  "type": "Feature",
  "properties": {
    "addr:full":"100 W 3rd Ave Conshohocken PA 19428",
    "addr:housenumber":"100",
    "addr:postcode":"19428",
    "addr:street":"W 3Rd Ave",
    "iso:country":"US",
    "sg:address":"100 W 3rd Ave",
    "sg:city":"Conshohocken",
    "sg:classifiers":[
        {
            "category":"Professional",
            "subcategory":"Accounting & Tax Preparation",
            "type":"Services"
        }
    ],
    "sg:phone":"+1 610 940 3939",
    "sg:postcode":"19428",
    "sg:province":"PA",
    "sg:tags":[
        "accountant",
        "auditing",
        "bookkeeping"
    ],
    "wof:name":"Charles N Finder CPA",
    "wof:placetype":"venue"
},
  "geometry": {"coordinates":[-75.307011,40.076957],"type":"Point"}
}