{
  "type": "Feature",
  "properties": {
    "iso:country":"US",
    "sg:address":"5 Lycoming Mall",
    "sg:city":"Muncy",
    "sg:classifiers":[
        {
            "category":"Food & Beverages",
            "subcategory":"Bakery",
            "type":"Retail Goods"
        }
    ],
    "sg:phone":"+1   ",
    "sg:postcode":"17756",
    "sg:province":"PA",
    "sg:tags":[
        "eating"
    ],
    "wof:name":"Bavarian Pretzel Bakery 39",
    "wof:placetype":"venue"
},
  "geometry": {"coordinates":[-76.832145,41.245529],"type":"Point"}
}