{
  "type": "Feature",
  "properties": {
    "iso:country":"US",
    "sg:address":"617 Magee Ave",
    "sg:city":"Patton",
    "sg:classifiers":[
        {
            "category":"Organizations",
            "subcategory":"Religious Organization",
            "type":"Services"
        }
    ],
    "sg:phone":"+1 814 674 5324",
    "sg:postcode":"16668",
    "sg:province":"PA",
    "sg:tags":[
        "church"
    ],
    "wof:name":"Church Of God",
    "wof:placetype":"venue"
},
  "geometry": {"coordinates":[-78.65363000000001,40.633875],"type":"Point"}
}