{
  "type": "Feature",
  "properties": {
    "iso:country":"US",
    "sg:address":"216 Springhouse Ln",
    "sg:city":"Pittsburgh",
    "sg:classifiers":[
        {
            "category":"Retail",
            "subcategory":"Auto Repair",
            "type":"Services"
        }
    ],
    "sg:phone":"+1 412 967 9181",
    "sg:postcode":"15238",
    "sg:province":"PA",
    "sg:tags":[
        "repairing",
        "automobile",
        "service-equipment",
        "supply"
    ],
    "sg:website":"http://www.incastinc.com",
    "wof:name":"Incast, Inc.",
    "wof:placetype":"venue"
},
  "geometry": {"coordinates":[-79.871213,40.513772],"type":"Point"}
}