{
  "type": "Feature",
  "properties": {
    "addr:full":"555 Keswick Dr Morrisville PA 19067",
    "addr:housenumber":"555",
    "addr:postcode":"19067",
    "addr:street":"Keswick Dr",
    "iso:country":"US",
    "sg:address":"555 Keswick Dr",
    "sg:city":"Morrisville",
    "sg:classifiers":[
        {
            "category":"Building & Trades",
            "subcategory":"Plumbing",
            "type":"Services"
        }
    ],
    "sg:phone":"+1 215 295 8350",
    "sg:postcode":"19067",
    "sg:province":"PA",
    "sg:tags":[
        "conditioning",
        "air",
        "system",
        "contractor"
    ],
    "wof:name":"Ronald A Corey Heating & AC",
    "wof:placetype":"venue"
},
  "geometry": {"coordinates":[-74.81617799999999,40.233177],"type":"Point"}
}