{
  "type": "Feature",
  "properties": {
    "iso:country":"US",
    "sg:address":"2098 Butler Pike",
    "sg:city":"Plymouth Meeting",
    "sg:classifiers":[
        {
            "category":"Real Estate",
            "subcategory":"Real Estate Operator",
            "type":"Services"
        }
    ],
    "sg:phone":"+1 610 834 2064",
    "sg:postcode":"19462",
    "sg:province":"PA",
    "sg:tags":[
        "apartment"
    ],
    "wof:name":"Carriage Hill Apartments",
    "wof:placetype":"venue"
},
  "geometry": {"coordinates":[-75.28378600000001,40.097226],"type":"Point"}
}