{
  "type": "Feature",
  "properties": {
    "addr:full":"797 Baltimore St Hanover PA 17331",
    "addr:housenumber":"797",
    "addr:postcode":"17331",
    "addr:street":"Baltimore St",
    "iso:country":"US",
    "sg:address":"797 Baltimore St",
    "sg:city":"Hanover",
    "sg:classifiers":[
        {
            "category":"Building & Trades",
            "subcategory":"Equipment Rental",
            "type":"Services"
        }
    ],
    "sg:phone":"+1   ",
    "sg:postcode":"17331",
    "sg:province":"PA",
    "wof:name":"Rent-Way",
    "wof:placetype":"venue"
},
  "geometry": {"coordinates":[-76.969533,39.787723],"type":"Point"}
}