{
  "type": "Feature",
  "properties": {
    "iso:country":"US",
    "sg:address":"106 N 6th St",
    "sg:city":"Coplay",
    "sg:classifiers":[
        {
            "category":"Wholesale",
            "subcategory":"Non-durable Goods",
            "type":"Manufacturing & Wholesale Goods"
        }
    ],
    "sg:phone":"+1   ",
    "sg:postcode":"18037",
    "sg:province":"PA",
    "sg:tags":[
        "advertising",
        "specialty"
    ],
    "wof:name":"Coupon Madness",
    "wof:placetype":"venue"
},
  "geometry": {"coordinates":[-75.497629,40.671963],"type":"Point"}
}