{
  "type": "Feature",
  "properties": {
    "addr:full":"3715 Hempland Rd Mountville PA 17554",
    "addr:housenumber":"3715",
    "addr:postcode":"17554",
    "addr:street":"Hempland Rd",
    "iso:country":"US",
    "sg:address":"3715 Hempland Rd",
    "sg:city":"Mountville",
    "sg:classifiers":[
        {
            "category":"Retail",
            "subcategory":"Auto Rental",
            "type":"Services"
        }
    ],
    "sg:phone":"+1   ",
    "sg:postcode":"17554",
    "sg:province":"PA",
    "sg:tags":[
        "trailer",
        "utility"
    ],
    "wof:name":"T I P-Transport Intl Pool",
    "wof:placetype":"venue"
},
  "geometry": {"coordinates":[-76.41670999999999,40.044045],"type":"Point"}
}