{
  "type": "Feature",
  "properties": {
    "iso:country":"US",
    "sg:address":"123 State St",
    "sg:city":"Harrisburg",
    "sg:classifiers":[
        {
            "category":"Banks & Credit Unions",
            "subcategory":"Atm",
            "type":"Services"
        }
    ],
    "sg:phone":"+1 717 232 5551",
    "sg:postcode":"17101",
    "sg:province":"PA",
    "sg:tags":[
        "bankruptcy"
    ],
    "wof:name":"Sheppard James P ESQ",
    "wof:placetype":"venue"
},
  "geometry": {"coordinates":[-76.888298,40.2626],"type":"Point"}
}