{
  "type": "Feature",
  "properties": {
    "addr:full":"12 E Butler Ave Ambler PA 19002",
    "addr:housenumber":"12",
    "addr:postcode":"19002",
    "addr:street":"E Butler Ave",
    "iso:country":"US",
    "sg:address":"12 E Butler Ave",
    "sg:city":"Ambler",
    "sg:classifiers":[
        {
            "category":"Professional",
            "subcategory":"Accounting & Tax Preparation",
            "type":"Services"
        }
    ],
    "sg:phone":"+1   ",
    "sg:postcode":"19002",
    "sg:province":"PA",
    "sg:tags":[
        "return"
    ],
    "wof:name":"H & R Block",
    "wof:placetype":"venue"
},
  "geometry": {"coordinates":[-75.22323799999999,40.1539],"type":"Point"}
}