{
  "type": "Feature",
  "properties": {
    "addr:full":"550 N 56th St Philadelphia PA 19131",
    "addr:housenumber":"550",
    "addr:postcode":"19131",
    "addr:street":"N 56Th St",
    "iso:country":"US",
    "sg:address":"550 N 56th St",
    "sg:city":"Philadelphia",
    "sg:classifiers":[
        {
            "category":"Shopping",
            "subcategory":"Discount & Variety Stores",
            "type":"Retail Goods"
        }
    ],
    "sg:phone":"+1   ",
    "sg:postcode":"19131",
    "sg:province":"PA",
    "wof:name":"Barbaras Variety",
    "wof:placetype":"venue"
},
  "geometry": {"coordinates":[-75.23217099999999,39.968138],"type":"Point"}
}