{
  "type": "Feature",
  "properties": {
    "iso:country":"US",
    "sg:address":"3421 W Marshall Rd",
    "sg:city":"Drexel Hill",
    "sg:classifiers":[
        {
            "category":"Building & Trades",
            "subcategory":"Electrical",
            "type":"Services"
        }
    ],
    "sg:phone":"+1   ",
    "sg:postcode":"19026",
    "sg:province":"PA",
    "sg:tags":[
        "electrical",
        "contractor"
    ],
    "wof:name":"Act Security & Electric Inc",
    "wof:placetype":"venue"
},
  "geometry": {"coordinates":[-75.29306800000001,39.941647],"type":"Point"}
}