{
  "type": "Feature",
  "properties": {
    "iso:country":"US",
    "sg:address":"3170 Windgate Dr",
    "sg:city":"Murrysville",
    "sg:classifiers":[
        {
            "category":"Professional",
            "type":"Services"
        }
    ],
    "sg:phone":"+1   ",
    "sg:postcode":"15668",
    "sg:province":"PA",
    "wof:name":"House of Praise",
    "wof:placetype":"venue"
},
  "geometry": {"coordinates":[-79.676074,40.428616],"type":"Point"}
}