{
  "type": "Feature",
  "properties": {
    "addr:full":"502 W Tilghman St Allentown PA 18102",
    "addr:housenumber":"502",
    "addr:postcode":"18102",
    "addr:street":"W Tilghman St",
    "iso:country":"US",
    "sg:address":"502 W Tilghman St",
    "sg:city":"Allentown",
    "sg:classifiers":[
        {
            "category":"Food & Beverages",
            "subcategory":"Groceries & Convenience Stores",
            "type":"Retail Goods"
        }
    ],
    "sg:phone":"+1 610 435 7430",
    "sg:postcode":"18102",
    "sg:province":"PA",
    "wof:name":"A T Grocery",
    "wof:placetype":"venue"
},
  "geometry": {"coordinates":[-75.47260300000001,40.612801],"type":"Point"}
}