{
  "type": "Feature",
  "properties": {
    "iso:country":"US",
    "sg:address":"443 Prospect Ave",
    "sg:city":"Horsham",
    "sg:classifiers":[
        {
            "category":"Building & Trades",
            "subcategory":"Electrical",
            "type":"Services"
        }
    ],
    "sg:phone":"+1   ",
    "sg:postcode":"19044",
    "sg:province":"PA",
    "sg:tags":[
        "home",
        "for",
        "system",
        "install",
        "new"
    ],
    "wof:name":"Michael C Witkowski",
    "wof:placetype":"venue"
},
  "geometry": {"coordinates":[-75.145026,40.182338],"type":"Point"}
}