{
  "type": "Feature",
  "properties": {
    "iso:country":"US",
    "sg:address":"217 E Market St",
    "sg:city":"Orwigsburg",
    "sg:classifiers":[
        {
            "category":"Real Estate",
            "subcategory":"Developer",
            "type":"Services"
        }
    ],
    "sg:phone":"+1   ",
    "sg:postcode":"17961",
    "sg:province":"PA",
    "wof:name":"Penn Alliance",
    "wof:placetype":"venue"
},
  "geometry": {"coordinates":[-76.099543,40.654458],"type":"Point"}
}