{
  "type": "Feature",
  "properties": {
    "iso:country":"US",
    "sg:address":"23 Goodrich St",
    "sg:city":"Ripley",
    "sg:classifiers":[
        {
            "category":"Shopping",
            "subcategory":"Hobbies, Toys, & Games",
            "type":"Retail Goods"
        }
    ],
    "sg:phone":"+1 716 736 3282",
    "sg:postcode":"14775",
    "sg:province":"NY",
    "sg:tags":[
        "equipment",
        "ceramic",
        "supply"
    ],
    "wof:name":"Wendy's House-Crafty Ceramic",
    "wof:placetype":"venue"
},
  "geometry": {"coordinates":[-79.710724,42.262749],"type":"Point"}
}