{
  "type": "Feature",
  "properties": {
    "iso:country":"US",
    "sg:address":"4919 3rd St",
    "sg:city":"Mckeesport",
    "sg:classifiers":[
        {
            "category":"Government",
            "subcategory":"Fire Station",
            "type":"Public Place"
        }
    ],
    "sg:phone":"+1 412 751 3603",
    "sg:postcode":"15132",
    "sg:province":"PA",
    "sg:tags":[
        "department"
    ],
    "wof:name":"Versailles Boro Volunteer Fire",
    "wof:placetype":"venue"
},
  "geometry": {"coordinates":[-79.83276600000001,40.315684],"type":"Point"}
}