{
  "type": "Feature",
  "properties": {
    "iso:country":"US",
    "sg:address":"252 South St",
    "sg:city":"Philadelphia",
    "sg:classifiers":[
        {
            "category":"Retail",
            "subcategory":"Portrait Studio",
            "type":"Services"
        }
    ],
    "sg:phone":"+1 215 923 4727",
    "sg:postcode":"19147",
    "sg:province":"PA",
    "sg:tags":[
        "photographer"
    ],
    "wof:name":"Gisone's Photo Studio",
    "wof:placetype":"venue"
},
  "geometry": {"coordinates":[-75.14739,39.941309],"type":"Point"}
}