{
  "type": "Feature",
  "properties": {
    "addr:full":"800 S Albemarle St York PA 17403",
    "addr:housenumber":"800",
    "addr:postcode":"17403",
    "addr:street":"S Albemarle St",
    "iso:country":"US",
    "sg:address":"800 S Albemarle St",
    "sg:city":"York",
    "sg:classifiers":[
        {
            "category":"Social Services",
            "type":"Services"
        },
        {
            "category":"Personal",
            "type":"Services"
        }
    ],
    "sg:phone":"+1 717 848 8313",
    "sg:postcode":"17403",
    "sg:province":"PA",
    "sg:tags":[
        "individual",
        "family",
        "counselors-licensed",
        "therapist",
        "marriage",
        "child",
        "professional",
        "counselor"
    ],
    "wof:name":"Christian Counseling Assoc",
    "wof:placetype":"venue"
},
  "geometry": {"coordinates":[-76.70208700000001,39.95797],"type":"Point"}
}