{
  "type": "Feature",
  "properties": {
    "iso:country":"US",
    "sg:address":"4905 N 5th St",
    "sg:city":"Philadelphia",
    "sg:classifiers":[
        {
            "category":"Restaurant",
            "type":"Food & Drink"
        }
    ],
    "sg:phone":"+1 215 329 8600",
    "sg:postcode":"19120",
    "sg:province":"PA",
    "sg:tags":[
        "pizza"
    ],
    "wof:name":"Pizza Masters",
    "wof:placetype":"venue"
},
  "geometry": {"coordinates":[-75.132622,40.025821],"type":"Point"}
}