{
  "type": "Feature",
  "properties": {
    "addr:full":"3526 Pine Rd Huntingdon Vly PA 19006",
    "addr:housenumber":"3526",
    "addr:postcode":"19006",
    "addr:street":"Pine Rd",
    "iso:country":"US",
    "sg:address":"3526 Pine Rd",
    "sg:city":"Huntingdon Vly",
    "sg:classifiers":[
        {
            "category":"Real Estate",
            "subcategory":"Real Estate Agent",
            "type":"Services"
        }
    ],
    "sg:phone":"+1 215 947 5188",
    "sg:postcode":"19006",
    "sg:province":"PA",
    "wof:name":"J B Taylor Real Estate Group",
    "wof:placetype":"venue"
},
  "geometry": {"coordinates":[-75.03266600000001,40.134383],"type":"Point"}
}