{
  "type": "Feature",
  "properties": {
    "iso:country":"US",
    "sg:address":"200 Oak Ave",
    "sg:city":"Kittanning",
    "sg:classifiers":[
        {
            "category":"Government",
            "subcategory":"Office",
            "type":"Public Place"
        }
    ],
    "sg:phone":"+1 724 548 1961",
    "sg:postcode":"16201",
    "sg:province":"PA",
    "sg:tags":[
        "state",
        "resource"
    ],
    "wof:name":"Vocational Rehabilitation",
    "wof:placetype":"venue"
},
  "geometry": {"coordinates":[-79.51858199999999,40.819778],"type":"Point"}
}