{
  "type": "Feature",
  "properties": {
    "iso:country":"US",
    "sg:address":"124 Old York Rd",
    "sg:city":"New Cumberland",
    "sg:classifiers":[
        {
            "category":"Personal",
            "subcategory":"Barber",
            "type":"Services"
        }
    ],
    "sg:phone":"+1 717 774 9911",
    "sg:postcode":"17070",
    "sg:province":"PA",
    "wof:name":"Holiday Hair",
    "wof:placetype":"venue"
},
  "geometry": {"coordinates":[-76.859852,40.221265],"type":"Point"}
}