{
  "type": "Feature",
  "properties": {
    "addr:full":"1425 Walnut St Philadelphia PA 19102",
    "addr:housenumber":"1425",
    "addr:postcode":"19102",
    "addr:street":"Walnut St",
    "iso:country":"US",
    "sg:address":"1425 Walnut St",
    "sg:city":"Philadelphia",
    "sg:classifiers":[
        {
            "category":"Wholesale",
            "subcategory":"Non-durable Goods",
            "type":"Manufacturing & Wholesale Goods"
        }
    ],
    "sg:phone":"+1   ",
    "sg:postcode":"19102",
    "sg:province":"PA",
    "wof:name":"Hourglass Trading",
    "wof:placetype":"venue"
},
  "geometry": {"coordinates":[-75.165626,39.949576],"type":"Point"}
}