{
  "type": "Feature",
  "properties": {
    "addr:full":"1123 Forest Hills Dr Salix PA 15952",
    "addr:housenumber":"1123",
    "addr:postcode":"15952",
    "addr:street":"Forest Hills Dr",
    "iso:country":"US",
    "sg:address":"1123 Forest Hills Dr",
    "sg:city":"Salix",
    "sg:classifiers":[
        {
            "category":"Building & Trades",
            "subcategory":"Electrical",
            "type":"Services"
        }
    ],
    "sg:phone":"+1 814 269 4975",
    "sg:postcode":"15952",
    "sg:province":"PA",
    "sg:tags":[
        "electric",
        "contractor"
    ],
    "wof:name":"Barclay Electric Inc",
    "wof:placetype":"venue"
},
  "geometry": {"coordinates":[-78.765349,40.299985],"type":"Point"}
}