{
  "type": "Feature",
  "properties": {
    "iso:country":"US",
    "sg:address":"5715 Roselawn Ave",
    "sg:city":"Altoona",
    "sg:classifiers":[
        {
            "category":"Social Services",
            "subcategory":"Child Care",
            "type":"Services"
        }
    ],
    "sg:phone":"+1 814 942 5643",
    "sg:postcode":"16602",
    "sg:province":"PA",
    "sg:tags":[
        "kindergarten",
        "academic",
        "school"
    ],
    "wof:name":"Stay & Play Pre-School",
    "wof:placetype":"venue"
},
  "geometry": {"coordinates":[-78.42355499999999,40.471563],"type":"Point"}
}