{
  "type": "Feature",
  "properties": {
    "addr:full":"1732 Rodgers Ave Cresson PA 16630",
    "addr:housenumber":"1732",
    "addr:postcode":"16630",
    "addr:street":"Rodgers Ave",
    "iso:country":"US",
    "sg:address":"1732 Rodgers Ave",
    "sg:city":"Cresson",
    "sg:classifiers":[
        {
            "category":"Organizations",
            "subcategory":"Religious Organization",
            "type":"Services"
        }
    ],
    "sg:phone":"+1   ",
    "sg:postcode":"16630",
    "sg:province":"PA",
    "wof:name":"Catholic Daughters of Americas",
    "wof:placetype":"venue"
},
  "geometry": {"coordinates":[-78.59717499999999,40.450289],"type":"Point"}
}