{
  "type": "Feature",
  "properties": {
    "addr:full":"119 Township Line Rd Jenkintown PA 19046",
    "addr:housenumber":"119",
    "addr:postcode":"19046",
    "addr:street":"Township Line Rd",
    "iso:country":"US",
    "sg:address":"119 Township Line Rd",
    "sg:city":"Jenkintown",
    "sg:classifiers":[
        {
            "category":"Retail",
            "subcategory":"Auto Repair",
            "type":"Services"
        }
    ],
    "sg:phone":"+1 215 379 1300",
    "sg:postcode":"19046",
    "sg:province":"PA",
    "sg:tags":[
        "repairing",
        "automobile"
    ],
    "wof:name":"Preferred Automotive Spclst",
    "wof:placetype":"venue"
},
  "geometry": {"coordinates":[-75.130996,40.088751],"type":"Point"}
}