{
  "type": "Feature",
  "properties": {
    "iso:country":"US",
    "sg:address":"104 S Foster Rd",
    "sg:city":"Mercer",
    "sg:classifiers":[
        {
            "category":"Travel",
            "subcategory":"Hotels & Motels",
            "type":"Entertainment"
        }
    ],
    "sg:phone":"+1 724 301 3273",
    "sg:postcode":"16137",
    "sg:province":"PA",
    "sg:tags":[
        "breakfast",
        "accommodation",
        "bed"
    ],
    "wof:name":"Plant's Herb Farm",
    "wof:placetype":"venue"
},
  "geometry": {"coordinates":[-80.150223,41.238649],"type":"Point"}
}