{
  "type": "Feature",
  "properties": {
    "iso:country":"US",
    "sg:address":"1404 Wheatfield Dr",
    "sg:city":"York",
    "sg:classifiers":[
        {
            "category":"Professional",
            "subcategory":"Engineering",
            "type":"Services"
        }
    ],
    "sg:phone":"+1 717 764 2016",
    "sg:postcode":"17408",
    "sg:province":"PA",
    "sg:tags":[
        "consultant",
        "energy",
        "conservation"
    ],
    "wof:name":"Global Energy Conservation Sys",
    "wof:placetype":"venue"
},
  "geometry": {"coordinates":[-76.798115,39.998317],"type":"Point"}
}