{
  "type": "Feature",
  "properties": {
    "iso:country":"US",
    "sg:address":"196 Pittsburgh Rd",
    "sg:city":"Butler",
    "sg:classifiers":[
        {
            "category":"Autos & Motor Vehicles",
            "subcategory":"Automobile Sales",
            "type":"Retail Goods"
        }
    ],
    "sg:phone":"+1   ",
    "sg:postcode":"16045",
    "sg:province":"PA",
    "sg:tags":[
        "car",
        "recreational",
        "used"
    ],
    "wof:name":"Butler Rv Center",
    "wof:placetype":"venue"
},
  "geometry": {"coordinates":[-79.91847799999999,40.839912],"type":"Point"}
}