{
  "type": "Feature",
  "properties": {
    "iso:country":"US",
    "sg:address":"1223 S Irving Ave",
    "sg:city":"Scranton",
    "sg:classifiers":[
        {
            "category":"Building & Trades",
            "subcategory":"Construction",
            "type":"Services"
        }
    ],
    "sg:phone":"+1 570 969 0576",
    "sg:postcode":"18505",
    "sg:province":"PA",
    "sg:tags":[
        "house"
    ],
    "wof:name":"All Surface Pressure Cleaning",
    "wof:placetype":"venue"
},
  "geometry": {"coordinates":[-75.666006,41.390098],"type":"Point"}
}