{
  "type": "Feature",
  "properties": {
    "iso:country":"US",
    "sg:address":"50 S 14th St",
    "sg:city":"Pittsburgh",
    "sg:classifiers":[
        {
            "category":"Organizations",
            "subcategory":"Non-profit Organization",
            "type":"Services"
        }
    ],
    "sg:phone":"+1   ",
    "sg:postcode":"15203",
    "sg:province":"PA",
    "sg:tags":[
        "social"
    ],
    "wof:name":"S S L D C",
    "wof:placetype":"venue"
},
  "geometry": {"coordinates":[-79.98414099999999,40.427743],"type":"Point"}
}