{
  "type": "Feature",
  "properties": {
    "addr:full":"7707 Mccallum St B Philadelphia PA 19118",
    "addr:housenumber":"7707",
    "addr:postcode":"19118",
    "addr:street":"Mccallum St",
    "iso:country":"US",
    "sg:address":"7707 Mccallum St B",
    "sg:city":"Philadelphia",
    "sg:classifiers":[
        {
            "category":"Shopping",
            "subcategory":"Books",
            "type":"Retail Goods"
        },
        {
            "category":"Wholesale",
            "subcategory":"Books, Periodicals, & Newspapers",
            "type":"Manufacturing & Wholesale Goods"
        }
    ],
    "sg:phone":"+1 215 587 9190",
    "sg:postcode":"19118",
    "sg:province":"PA",
    "sg:tags":[
        "books-wholesale",
        "store",
        "manufacturer"
    ],
    "wof:name":"Book Heaven, Inc",
    "wof:placetype":"venue"
},
  "geometry": {"coordinates":[-75.208446,40.057573],"type":"Point"}
}