{
  "type": "Feature",
  "properties": {
    "iso:country":"US",
    "sg:address":"973 Wilamit Dr",
    "sg:city":"Bethel Park",
    "sg:classifiers":[
        {
            "category":"Building & Trades",
            "subcategory":"Construction",
            "type":"Services"
        }
    ],
    "sg:phone":"+1   ",
    "sg:postcode":"15102",
    "sg:province":"PA",
    "sg:tags":[
        "house",
        "br",
        "hanging"
    ],
    "wof:name":"Bastolla Custom Painting",
    "wof:placetype":"venue"
},
  "geometry": {"coordinates":[-80.043679,40.317619],"type":"Point"}
}