{
  "type": "Feature",
  "properties": {
    "iso:country":"US",
    "sg:address":"11 N Main St",
    "sg:city":"Greensburg",
    "sg:classifiers":[
        {
            "category":"Real Estate",
            "subcategory":"Real Estate Services",
            "type":"Services"
        }
    ],
    "sg:phone":"+1   ",
    "sg:postcode":"15601",
    "sg:province":"PA",
    "sg:tags":[
        "abstract",
        "title"
    ],
    "wof:name":"Lawyers Abstract Westmoreland",
    "wof:placetype":"venue"
},
  "geometry": {"coordinates":[-79.544568,40.303596],"type":"Point"}
}