{
  "type": "Feature",
  "properties": {
    "addr:full":"380 Eisenhower Dr Hanover PA 17331",
    "addr:housenumber":"380",
    "addr:postcode":"17331",
    "addr:street":"Eisenhower Dr",
    "iso:country":"US",
    "sg:address":"380 Eisenhower Dr",
    "sg:city":"Hanover",
    "sg:classifiers":[
        {
            "category":"Cinema",
            "subcategory":"Movie Theater",
            "type":"Entertainment"
        }
    ],
    "sg:phone":"+1 717 646 1111",
    "sg:postcode":"17331",
    "sg:province":"PA",
    "sg:tags":[
        "motion",
        "picture"
    ],
    "wof:name":"R C Theatres",
    "wof:placetype":"venue"
},
  "geometry": {"coordinates":[-76.98221700000001,39.824982],"type":"Point"}
}