{
  "type": "Feature",
  "properties": {
    "iso:country":"US",
    "sg:address":"619 Pittston Ave",
    "sg:city":"Scranton",
    "sg:classifiers":[
        {
            "category":"Restaurant",
            "type":"Food & Drink"
        }
    ],
    "sg:phone":"+1   ",
    "sg:postcode":"18505",
    "sg:province":"PA",
    "sg:tags":[
        "eating"
    ],
    "wof:name":"Royal Pizza Inc",
    "wof:placetype":"venue"
},
  "geometry": {"coordinates":[-75.66558000000001,41.398726],"type":"Point"}
}