{
  "type": "Feature",
  "properties": {
    "iso:country":"US",
    "sg:address":"669 Park Hill Dr",
    "sg:city":"Manheim",
    "sg:classifiers":[
        {
            "category":"Professional",
            "subcategory":"Detective & Security Services",
            "type":"Services"
        }
    ],
    "sg:phone":"+1 717 664 0090",
    "sg:postcode":"17545",
    "sg:province":"PA",
    "sg:tags":[
        "system"
    ],
    "wof:name":"3 T Security LLC",
    "wof:placetype":"venue"
},
  "geometry": {"coordinates":[-76.383972,40.151481],"type":"Point"}
}