{
  "type": "Feature",
  "properties": {
    "iso:country":"US",
    "sg:address":"992 Park Estates Rd",
    "sg:city":"Wind Gap",
    "sg:classifiers":[
        {
            "category":"Home & Garden",
            "subcategory":"Carpets & Floor Coverings",
            "type":"Retail Goods"
        }
    ],
    "sg:phone":"+1 610 759 5264",
    "sg:postcode":"18091",
    "sg:province":"PA",
    "sg:tags":[
        "installs",
        "rug",
        "dealer"
    ],
    "wof:name":"John Tanzos Floor Coverings",
    "wof:placetype":"venue"
},
  "geometry": {"coordinates":[-75.300861,40.800105],"type":"Point"}
}