{
  "type": "Feature",
  "properties": {
    "iso:country":"US",
    "sg:address":"10273 S Eagle Valley Rd",
    "sg:city":"Port Matilda",
    "sg:classifiers":[
        {
            "category":"Farming",
            "subcategory":"Dairy Farm",
            "type":"Manufacturing & Wholesale Goods"
        }
    ],
    "sg:phone":"+1   ",
    "sg:postcode":"16870",
    "sg:province":"PA",
    "wof:name":"Liner Valley Dairy Farm",
    "wof:placetype":"venue"
},
  "geometry": {"coordinates":[-78.10477899999999,40.763202],"type":"Point"}
}