{
  "type": "Feature",
  "properties": {
    "addr:full":"1180 Zeager Rd Elizabethtown PA 17022",
    "addr:housenumber":"1180",
    "addr:postcode":"17022",
    "addr:street":"Zeager Rd",
    "iso:country":"US",
    "sg:address":"1180 Zeager Rd",
    "sg:city":"Elizabethtown",
    "sg:classifiers":[
        {
            "category":"Retail",
            "subcategory":"Auto Rental",
            "type":"Services"
        }
    ],
    "sg:phone":"+1 717 361 7759",
    "sg:postcode":"17022",
    "sg:province":"PA",
    "sg:tags":[
        "renting",
        "truck",
        "leasing"
    ],
    "wof:name":"Budget Truck Rental",
    "wof:placetype":"venue"
},
  "geometry": {"coordinates":[-76.64341899999999,40.159649],"type":"Point"}
}