{
  "type": "Feature",
  "properties": {
    "addr:full":"231 W Mount Pleasant Ave Philadelphia PA 19119",
    "addr:housenumber":"231",
    "addr:postcode":"19119",
    "addr:street":"W Mount Pleasant Ave",
    "iso:country":"US",
    "sg:address":"231 W Mount Pleasant Ave",
    "sg:city":"Philadelphia",
    "sg:classifiers":[
        {
            "category":"Wholesale",
            "subcategory":"Home Furnishings",
            "type":"Manufacturing & Wholesale Goods"
        }
    ],
    "sg:phone":"+1   ",
    "sg:postcode":"19119",
    "sg:province":"PA",
    "sg:tags":[
        "oriental",
        "rug"
    ],
    "wof:name":"TPC Corporation",
    "wof:placetype":"venue"
},
  "geometry": {"coordinates":[-75.19218100000001,40.056315],"type":"Point"}
}