{
  "type": "Feature",
  "properties": {
    "iso:country":"US",
    "sg:address":"156 Cedar Ave 401",
    "sg:city":"Scranton",
    "sg:classifiers":[
        {
            "category":"Recreation",
            "subcategory":"Gun Range",
            "type":"Entertainment"
        }
    ],
    "sg:phone":"+1 570 340 1168",
    "sg:postcode":"18505",
    "sg:province":"PA",
    "sg:tags":[
        "ammunition"
    ],
    "wof:name":"Scranton Army Ammunition Plant",
    "wof:placetype":"venue"
},
  "geometry": {"coordinates":[-75.66388999999999,41.404552],"type":"Point"}
}