{
  "type": "Feature",
  "properties": {
    "addr:full":"159 Creek Rd Glen Mills PA 19342",
    "addr:housenumber":"159",
    "addr:postcode":"19342",
    "addr:street":"Creek Rd",
    "iso:country":"US",
    "sg:address":"159 Creek Rd",
    "sg:city":"Glen Mills",
    "sg:classifiers":[
        {
            "category":"Wholesale",
            "subcategory":"Furniture",
            "type":"Manufacturing & Wholesale Goods"
        }
    ],
    "sg:phone":"+1 610 455 0533",
    "sg:postcode":"19342",
    "sg:province":"PA",
    "wof:name":"Facilities 4 Inc",
    "wof:placetype":"venue"
},
  "geometry": {"coordinates":[-75.50707800000001,39.931828],"type":"Point"}
}