{
  "type": "Feature",
  "properties": {
    "iso:country":"US",
    "sg:address":"250 Green St",
    "sg:city":"California",
    "sg:classifiers":[
        {
            "category":"Personal",
            "subcategory":"Beauty Salon",
            "type":"Services"
        }
    ],
    "sg:phone":"+1 724 938 7966",
    "sg:postcode":"15419",
    "sg:province":"PA",
    "sg:tags":[
        "shop"
    ],
    "wof:name":"L Richey",
    "wof:placetype":"venue"
},
  "geometry": {"coordinates":[-79.888525,40.066832],"type":"Point"}
}