{
  "type": "Feature",
  "properties": {
    "iso:country":"US",
    "sg:address":"8501 W Chester Pike",
    "sg:city":"Upper Darby",
    "sg:classifiers":[
        {
            "category":"Education",
            "subcategory":"Special Training",
            "type":"Public Place"
        }
    ],
    "sg:phone":"+1 610 924 9020",
    "sg:postcode":"19082",
    "sg:province":"PA",
    "sg:tags":[
        "instruction",
        "music"
    ],
    "wof:name":"J C Music Studio",
    "wof:placetype":"venue"
},
  "geometry": {"coordinates":[-75.28488299999999,39.966626],"type":"Point"}
}