{
  "type": "Feature",
  "properties": {
    "iso:country":"US",
    "sg:address":"114 Washington St",
    "sg:city":"East Stroudsburg",
    "sg:classifiers":[
        {
            "category":"Shopping",
            "subcategory":"Clothing, Apparel, & Fashions",
            "type":"Retail Goods"
        }
    ],
    "sg:phone":"+1 570 476 0820",
    "sg:postcode":"18301",
    "sg:province":"PA",
    "wof:name":"Possibilities",
    "wof:placetype":"venue"
},
  "geometry": {"coordinates":[-75.18361,40.996526],"type":"Point"}
}