{
  "type": "Feature",
  "properties": {
    "iso:country":"US",
    "sg:address":"32 Steubenville Pike",
    "sg:city":"Paris",
    "sg:classifiers":[
        {
            "category":"Health Services",
            "subcategory":"Doctor",
            "type":"Services"
        }
    ],
    "sg:phone":"+1 724 729 3350",
    "sg:postcode":"15021",
    "sg:province":"PA",
    "sg:tags":[
        "clinic"
    ],
    "sg:website":"www.gambro.com",
    "wof:name":"Gambro Healthcare",
    "wof:placetype":"venue"
},
  "geometry": {"coordinates":[-80.514453,40.403918],"type":"Point"}
}