{
  "type": "Feature",
  "properties": {
    "iso:country":"US",
    "sg:address":"315 Saint Charles St",
    "sg:city":"Schuylkill Haven",
    "sg:classifiers":[
        {
            "category":"Retail",
            "subcategory":"Auto Repair",
            "type":"Services"
        }
    ],
    "sg:phone":"+1 570 385 5712",
    "sg:postcode":"17972",
    "sg:province":"PA",
    "sg:tags":[
        "muffler",
        "exhaust",
        "system"
    ],
    "wof:name":"Manbeck Alignment Svc",
    "wof:placetype":"venue"
},
  "geometry": {"coordinates":[-76.169726,40.623473],"type":"Point"}
}