{
  "type": "Feature",
  "properties": {
    "iso:country":"US",
    "sg:address":"527 S 60th St",
    "sg:city":"Philadelphia",
    "sg:classifiers":[
        {
            "category":"Personal",
            "subcategory":"Beauty Salon",
            "type":"Services"
        }
    ],
    "sg:phone":"+1   ",
    "sg:postcode":"19143",
    "sg:province":"PA",
    "sg:tags":[
        "shop"
    ],
    "wof:name":"Who Did Dat",
    "wof:placetype":"venue"
},
  "geometry": {"coordinates":[-75.24267500000001,39.952441],"type":"Point"}
}