{
  "type": "Feature",
  "properties": {
    "addr:full":"3824 State Rte 309 Orefield PA 18069",
    "addr:housenumber":"3824",
    "addr:postcode":"18069",
    "addr:street":"State Rte 309",
    "iso:country":"US",
    "sg:address":"3824 State Rte 309",
    "sg:city":"Orefield",
    "sg:classifiers":[
        {
            "category":"Shopping",
            "type":"Retail Goods"
        }
    ],
    "sg:phone":"+1   ",
    "sg:postcode":"18069",
    "sg:province":"PA",
    "sg:tags":[
        "merchandise"
    ],
    "wof:name":"Distribution Center",
    "wof:placetype":"venue"
},
  "geometry": {"coordinates":[-75.599675,40.653358],"type":"Point"}
}