{
  "type": "Feature",
  "properties": {
    "iso:country":"US",
    "sg:address":"1519 Babcock Blvd",
    "sg:city":"Pittsburgh",
    "sg:classifiers":[
        {
            "category":"Autos & Motor Vehicles",
            "subcategory":"Automobile Sales",
            "type":"Retail Goods"
        }
    ],
    "sg:phone":"+1 412 821 7630",
    "sg:postcode":"15209",
    "sg:province":"PA",
    "sg:tags":[
        "car",
        "dealer"
    ],
    "wof:name":"Frenchy's Auto",
    "wof:placetype":"venue"
},
  "geometry": {"coordinates":[-79.978933,40.498164],"type":"Point"}
}