{
  "type": "Feature",
  "properties": {
    "iso:country":"US",
    "sg:address":"17 N Hess St",
    "sg:city":"Quarryville",
    "sg:classifiers":[
        {
            "category":"Professional",
            "subcategory":"Computer Services",
            "type":"Services"
        },
        {
            "category":"Internet Cafe",
            "subcategory":"None",
            "type":"Food & Drink"
        }
    ],
    "sg:phone":"+1 717 786 4742",
    "sg:postcode":"17566",
    "sg:province":"PA",
    "sg:tags":[
        "product",
        "software"
    ],
    "wof:name":"Mankin Consulting",
    "wof:placetype":"venue"
},
  "geometry": {"coordinates":[-76.16166800000001,39.897816],"type":"Point"}
}