{
  "type": "Feature",
  "properties": {
    "addr:full":"610 Baltimore Pike Media PA 19063",
    "addr:housenumber":"610",
    "addr:postcode":"19063",
    "addr:street":"Baltimore Pike",
    "iso:country":"US",
    "sg:address":"610 Baltimore Pike",
    "sg:city":"Media",
    "sg:classifiers":[
        {
            "category":"Real Estate",
            "subcategory":"Real Estate Agent",
            "type":"Services"
        }
    ],
    "sg:phone":"+1 610 566 1100",
    "sg:postcode":"19063",
    "sg:province":"PA",
    "wof:name":"Coldwell Banker",
    "wof:placetype":"venue"
},
  "geometry": {"coordinates":[-75.39896,39.917075],"type":"Point"}
}