{
  "type": "Feature",
  "properties": {
    "iso:country":"US",
    "sg:address":"1101 Greenock Buena Vista Rd",
    "sg:city":"Mckeesport",
    "sg:classifiers":[
        {
            "category":"Education",
            "subcategory":"School",
            "type":"Public Place"
        }
    ],
    "sg:phone":"+1 412 751 6769",
    "sg:postcode":"15135",
    "sg:province":"PA",
    "wof:name":"Greenock School",
    "wof:placetype":"venue"
},
  "geometry": {"coordinates":[-79.802921,40.31227],"type":"Point"}
}