{
  "type": "Feature",
  "properties": {
    "iso:country":"US",
    "sg:address":"3539 Oakmont St",
    "sg:city":"Philadelphia",
    "sg:classifiers":[
        {
            "category":"Organizations",
            "subcategory":"Religious Organization",
            "type":"Services"
        }
    ],
    "sg:phone":"+1 215 338 5603",
    "sg:postcode":"19136",
    "sg:province":"PA",
    "sg:tags":[
        "clergy"
    ],
    "wof:name":"Dennis Frantz",
    "wof:placetype":"venue"
},
  "geometry": {"coordinates":[-75.03565500000001,40.039474],"type":"Point"}
}