{
  "type": "Feature",
  "properties": {
    "addr:full":"600 Park Ave Quakertown PA 18951",
    "addr:housenumber":"600",
    "addr:postcode":"18951",
    "addr:street":"Park Ave",
    "iso:country":"US",
    "sg:address":"600 Park Ave",
    "sg:city":"Quakertown",
    "sg:classifiers":[
        {
            "category":"Education",
            "subcategory":"School",
            "type":"Public Place"
        }
    ],
    "sg:phone":"+1 215 529 2000",
    "sg:postcode":"18951",
    "sg:province":"PA",
    "sg:tags":[
        "district"
    ],
    "wof:name":"Quakertown Community Schl Dist",
    "wof:placetype":"venue"
},
  "geometry": {"coordinates":[-75.340732,40.437295],"type":"Point"}
}