{
  "type": "Feature",
  "properties": {
    "addr:full":"2560 Metropolitan Dr Feasterville Trevose PA 19053",
    "addr:housenumber":"2560",
    "addr:postcode":"19053",
    "addr:street":"Metropolitan Dr",
    "iso:country":"US",
    "sg:address":"2560 Metropolitan Dr",
    "sg:city":"Feasterville Trevose",
    "sg:classifiers":[
        {
            "category":"Utilities",
            "subcategory":"Mobile Phone",
            "type":"Services"
        }
    ],
    "sg:phone":"+1   ",
    "sg:postcode":"19053",
    "sg:province":"PA",
    "sg:tags":[
        "communication",
        "radiotelephone"
    ],
    "wof:name":"Nextel",
    "wof:placetype":"venue"
},
  "geometry": {"coordinates":[-74.985367,40.131811],"type":"Point"}
}