{
  "type": "Feature",
  "properties": {
    "iso:country":"US",
    "sg:address":"1445 Willow St",
    "sg:city":"Norristown",
    "sg:classifiers":[
        {
            "category":"Shopping",
            "subcategory":"Jewelry",
            "type":"Retail Goods"
        },
        {
            "category":"Manufacturing",
            "subcategory":"Jewelry",
            "type":"Manufacturing & Wholesale Goods"
        }
    ],
    "sg:phone":"+1 610 277 6457",
    "sg:postcode":"19401",
    "sg:province":"PA",
    "sg:tags":[
        "designer",
        "jeweler"
    ],
    "wof:name":"Laurice, Everlina",
    "wof:placetype":"venue"
},
  "geometry": {"coordinates":[-75.333724,40.124298],"type":"Point"}
}