{
  "type": "Feature",
  "properties": {
    "addr:full":"5020 N 8th St Philadelphia PA 19120",
    "addr:housenumber":"5020",
    "addr:postcode":"19120",
    "addr:street":"N 8Th St",
    "iso:country":"US",
    "sg:address":"5020 N 8th St",
    "sg:city":"Philadelphia",
    "sg:classifiers":[
        {
            "category":"Organizations",
            "subcategory":"Religious Organization",
            "type":"Services"
        }
    ],
    "sg:phone":"+1 215 329 4010",
    "sg:postcode":"19120",
    "sg:province":"PA",
    "wof:name":"Allan Kardec Educational Soc",
    "wof:placetype":"venue"
},
  "geometry": {"coordinates":[-75.137199,40.0284],"type":"Point"}
}