{
  "type": "Feature",
  "properties": {
    "iso:country":"US",
    "sg:address":"114 E Center Ave",
    "sg:city":"Newtown",
    "sg:classifiers":[
        {
            "category":"Education",
            "subcategory":"Library",
            "type":"Public Place"
        }
    ],
    "sg:phone":"+1 215 968 7659",
    "sg:postcode":"18940",
    "sg:province":"PA",
    "wof:name":"Newtown Library Co",
    "wof:placetype":"venue"
},
  "geometry": {"coordinates":[-74.934614,40.227664],"type":"Point"}
}