{
  "type": "Feature",
  "properties": {
    "iso:country":"US",
    "sg:address":"214 Luzerne Ave",
    "sg:city":"West Pittston",
    "sg:classifiers":[
        {
            "category":"Social Services",
            "type":"Services"
        }
    ],
    "sg:phone":"+1 570 655 5947",
    "sg:postcode":"18643",
    "sg:province":"PA",
    "sg:tags":[
        "organization",
        "welfare"
    ],
    "wof:name":"Salvation Army",
    "wof:placetype":"venue"
},
  "geometry": {"coordinates":[-75.79831799999999,41.329661],"type":"Point"}
}