{
  "type": "Feature",
  "properties": {
    "iso:country":"US",
    "sg:address":"280 N Park St",
    "sg:city":"Dallastown",
    "sg:classifiers":[
        {
            "category":"Manufacturing",
            "subcategory":"Signs",
            "type":"Manufacturing & Wholesale Goods"
        }
    ],
    "sg:phone":"+1 717 246 2376",
    "sg:postcode":"17313",
    "sg:province":"PA",
    "wof:name":"Alpine Sign & Lighting",
    "wof:placetype":"venue"
},
  "geometry": {"coordinates":[-76.635668,39.901992],"type":"Point"}
}