{
  "type": "Feature",
  "properties": {
    "addr:full":"442 Lake Rd Hadley PA 16130",
    "addr:housenumber":"442",
    "addr:postcode":"16130",
    "addr:street":"Lake Rd",
    "iso:country":"US",
    "sg:address":"442 Lake Rd",
    "sg:city":"Hadley",
    "sg:classifiers":[
        {
            "category":"Government",
            "subcategory":"Office",
            "type":"Public Place"
        }
    ],
    "sg:phone":"+1 724 253 3376",
    "sg:postcode":"16130",
    "sg:province":"PA",
    "sg:tags":[
        "city",
        "taxation"
    ],
    "wof:name":"Sandy Creek Twp Auditor",
    "wof:placetype":"venue"
},
  "geometry": {"coordinates":[-80.229601,41.463789],"type":"Point"}
}