{
  "type": "Feature",
  "properties": {
    "iso:country":"US",
    "sg:address":"1371 Wilmington Pike",
    "sg:city":"Westtown",
    "sg:classifiers":[
        {
            "category":"Restaurant",
            "type":"Food & Drink"
        }
    ],
    "sg:phone":"+1 610 455 0900",
    "sg:postcode":"19395",
    "sg:province":"PA",
    "wof:name":"The Red Sombrero",
    "wof:placetype":"venue"
},
  "geometry": {"coordinates":[-75.551697,39.931099],"type":"Point"}
}