{
  "type": "Feature",
  "properties": {
    "iso:country":"US",
    "sg:address":"511 W Lemon St",
    "sg:city":"Lancaster",
    "sg:classifiers":[
        {
            "category":"Shopping",
            "type":"Retail Goods"
        }
    ],
    "sg:phone":"+1   ",
    "sg:postcode":"17603",
    "sg:province":"PA",
    "sg:tags":[
        "durable",
        "merchandise",
        "business"
    ],
    "wof:name":"Grahams Fyr-Fyter",
    "wof:placetype":"venue"
},
  "geometry": {"coordinates":[-76.31667899999999,40.04343],"type":"Point"}
}