{
  "type": "Feature",
  "properties": {
    "iso:country":"US",
    "sg:address":"2515 S 72nd St",
    "sg:city":"Philadelphia",
    "sg:classifiers":[
        {
            "category":"Retail",
            "subcategory":"Auto Repair",
            "type":"Services"
        }
    ],
    "sg:phone":"+1 215 492 6698",
    "sg:postcode":"19142",
    "sg:province":"PA",
    "sg:tags":[
        "body",
        "automobile",
        "painting"
    ],
    "wof:name":"Nelson's Auto Body",
    "wof:placetype":"venue"
},
  "geometry": {"coordinates":[-75.23976399999999,39.914826],"type":"Point"}
}