{
  "type": "Feature",
  "properties": {
    "addr:full":"106 Jamison Ave Greensburg PA 15601",
    "addr:housenumber":"106",
    "addr:postcode":"15601",
    "addr:street":"Jamison Ave",
    "iso:country":"US",
    "sg:address":"106 Jamison Ave",
    "sg:city":"Greensburg",
    "sg:classifiers":[
        {
            "category":"Manufacturing",
            "subcategory":"Tools & Machinery",
            "type":"Manufacturing & Wholesale Goods"
        }
    ],
    "sg:phone":"+1   ",
    "sg:postcode":"15601",
    "sg:province":"PA",
    "sg:tags":[
        "shop",
        "distributor",
        "electronic"
    ],
    "wof:name":"Ameritech Manufacturing Co",
    "wof:placetype":"venue"
},
  "geometry": {"coordinates":[-79.548396,40.277967],"type":"Point"}
}