{
  "type": "Feature",
  "properties": {
    "addr:full":"525 Main St E Girard PA 16417",
    "addr:housenumber":"525",
    "addr:postcode":"16417",
    "addr:street":"Main St E",
    "iso:country":"US",
    "sg:address":"525 Main St E",
    "sg:city":"Girard",
    "sg:classifiers":[
        {
            "category":"Retail",
            "subcategory":"Funeral Services",
            "type":"Services"
        }
    ],
    "sg:phone":"+1 814 774 3603",
    "sg:postcode":"16417",
    "sg:province":"PA",
    "sg:tags":[
        "director"
    ],
    "wof:name":"Burton Funeral Homes Inc",
    "wof:placetype":"venue"
},
  "geometry": {"coordinates":[-80.308494,42.005812],"type":"Point"}
}