{
  "type": "Feature",
  "properties": {
    "addr:full":"752 Tory Hollow Rd Berwyn PA 19312",
    "addr:housenumber":"752",
    "addr:postcode":"19312",
    "addr:street":"Tory Hollow Rd",
    "iso:country":"US",
    "sg:address":"752 Tory Hollow Rd",
    "sg:city":"Berwyn",
    "sg:classifiers":[
        {
            "category":"Building & Trades",
            "subcategory":"Landscaping Services",
            "type":"Services"
        }
    ],
    "sg:phone":"+1 610 251 0412",
    "sg:postcode":"19312",
    "sg:province":"PA",
    "sg:tags":[
        "landscape",
        "contractor"
    ],
    "wof:name":"Pelli Landscape Svc",
    "wof:placetype":"venue"
},
  "geometry": {"coordinates":[-75.45415,40.064178],"type":"Point"}
}