{
  "type": "Feature",
  "properties": {
    "iso:country":"US",
    "sg:address":"2100 Turkey Hill Rd",
    "sg:city":"Narvon",
    "sg:classifiers":[
        {
            "category":"Manufacturing",
            "subcategory":"Metals",
            "type":"Manufacturing & Wholesale Goods"
        }
    ],
    "sg:phone":"+1   ",
    "sg:postcode":"17555",
    "sg:province":"PA",
    "sg:tags":[
        "steel"
    ],
    "wof:name":"Shirk Manufacturing",
    "wof:placetype":"venue"
},
  "geometry": {"coordinates":[-75.96826,40.148841],"type":"Point"}
}