{
  "type": "Feature",
  "properties": {
    "addr:full":"620 Main St Shanksville PA 15560",
    "addr:housenumber":"620",
    "addr:postcode":"15560",
    "addr:street":"Main St",
    "iso:country":"US",
    "sg:address":"620 Main St",
    "sg:city":"Shanksville",
    "sg:classifiers":[
        {
            "category":"Autos & Motor Vehicles",
            "subcategory":"Fuel & Gas Station",
            "type":"Retail Goods"
        }
    ],
    "sg:phone":"+1 814 267 3302",
    "sg:postcode":"15560",
    "sg:province":"PA",
    "sg:tags":[
        "oil"
    ],
    "wof:name":"Grine's Service Ctr",
    "wof:placetype":"venue"
},
  "geometry": {"coordinates":[-78.90715400000001,40.017228],"type":"Point"}
}