{
  "type": "Feature",
  "properties": {
    "iso:country":"US",
    "sg:address":"2229 Macdade Blvd",
    "sg:city":"Holmes",
    "sg:classifiers":[
        {
            "category":"Arts & Performance",
            "subcategory":"Music",
            "type":"Entertainment"
        },
        {
            "category":"Bars & Pubs",
            "subcategory":"Lounge",
            "type":"Food & Drink"
        },
        {
            "category":"Shopping",
            "subcategory":"Music",
            "type":"Retail Goods"
        },
        {
            "category":"Recreation",
            "type":"Entertainment"
        }
    ],
    "sg:phone":"+1 610 586 0142",
    "sg:postcode":"19043",
    "sg:province":"PA",
    "sg:tags":[
        "jockey",
        "business",
        "disc",
        "entertainers-family",
        "karaoke",
        "store"
    ],
    "sg:website":"http://WWW.DJPARTYTIME.COM",
    "wof:name":"Party Time DJ'S",
    "wof:placetype":"venue"
},
  "geometry": {"coordinates":[-75.308959,39.898162],"type":"Point"}
}