{
  "type": "Feature",
  "properties": {
    "iso:country":"US",
    "sg:address":"1795 Maplewood Ln",
    "sg:city":"Allentown",
    "sg:classifiers":[
        {
            "category":"Professional",
            "subcategory":"Business Services",
            "type":"Services"
        }
    ],
    "sg:phone":"+1 610 398 6939",
    "sg:postcode":"18103",
    "sg:province":"PA",
    "sg:tags":[
        "consultant",
        "coach"
    ],
    "wof:name":"Bellmarconi Consulting",
    "wof:placetype":"venue"
},
  "geometry": {"coordinates":[-75.534868,40.55463],"type":"Point"}
}