{
  "type": "Feature",
  "properties": {
    "addr:full":"2412 Division Hwy Ephrata PA 17522",
    "addr:housenumber":"2412",
    "addr:postcode":"17522",
    "addr:street":"Division Hwy",
    "iso:country":"US",
    "sg:address":"2412 Division Hwy",
    "sg:city":"Ephrata",
    "sg:classifiers":[
        {
            "category":"Organizations",
            "subcategory":"Non-profit Organization",
            "type":"Services"
        }
    ],
    "sg:phone":"+1 717 354 2434",
    "sg:postcode":"17522",
    "sg:province":"PA",
    "sg:tags":[
        "social"
    ],
    "wof:name":"Christian Aid Ministries",
    "wof:placetype":"venue"
},
  "geometry": {"coordinates":[-76.100776,40.138563],"type":"Point"}
}