{
  "type": "Feature",
  "properties": {
    "iso:country":"US",
    "sg:address":"619 S High St",
    "sg:city":"West Chester",
    "sg:classifiers":[
        {
            "category":"Health Services",
            "subcategory":"Doctor",
            "type":"Services"
        }
    ],
    "sg:phone":"+1 610 696 0416",
    "sg:postcode":"19382",
    "sg:province":"PA",
    "sg:tags":[
        "dentist"
    ],
    "wof:name":"Richard C Nelson DDS PC",
    "wof:placetype":"venue"
},
  "geometry": {"coordinates":[-75.597453,39.953335],"type":"Point"}
}