{
  "type": "Feature",
  "properties": {
    "addr:full":"225 Washington St Conshohocken PA 19428",
    "addr:housenumber":"225",
    "addr:postcode":"19428",
    "addr:street":"Washington St",
    "iso:country":"US",
    "sg:address":"225 Washington St",
    "sg:city":"Conshohocken",
    "sg:classifiers":[
        {
            "category":"Organizations",
            "subcategory":"Professional Association",
            "type":"Services"
        }
    ],
    "sg:phone":"+1   ",
    "sg:postcode":"19428",
    "sg:province":"PA",
    "sg:tags":[
        "computer",
        "business",
        "programing",
        "custom"
    ],
    "wof:name":"Answerthink Consulting Group",
    "wof:placetype":"venue"
},
  "geometry": {"coordinates":[-75.30412200000001,40.071267],"type":"Point"}
}