{
  "type": "Feature",
  "properties": {
    "addr:full":"45 N Bailey Rd Thorndale PA 19372",
    "addr:housenumber":"45",
    "addr:postcode":"19372",
    "addr:street":"N Bailey Rd",
    "iso:country":"US",
    "sg:address":"45 N Bailey Rd",
    "sg:city":"Thorndale",
    "sg:classifiers":[
        {
            "category":"Retail",
            "subcategory":"Animal Services",
            "type":"Services"
        }
    ],
    "sg:phone":"+1 610 384 3702",
    "sg:postcode":"19372",
    "sg:province":"PA",
    "sg:tags":[
        "pet",
        "grooming",
        "washing"
    ],
    "wof:name":"Dog House",
    "wof:placetype":"venue"
},
  "geometry": {"coordinates":[-75.761122,39.994608],"type":"Point"}
}