{
  "type": "Feature",
  "properties": {
    "iso:country":"US",
    "sg:address":"226 S 16th St",
    "sg:city":"Philadelphia",
    "sg:classifiers":[
        {
            "category":"Health Services",
            "subcategory":"Nursing And Care Facility",
            "type":"Services"
        }
    ],
    "sg:phone":"+1 215 832 0688",
    "sg:postcode":"19102",
    "sg:province":"PA",
    "sg:tags":[
        "hospice"
    ],
    "wof:name":"Jewish Hospice Svc",
    "wof:placetype":"venue"
},
  "geometry": {"coordinates":[-75.167829,39.948699],"type":"Point"}
}