{
  "type": "Feature",
  "properties": {
    "addr:full":"243 E Main St Millheim PA 16820",
    "addr:housenumber":"243",
    "addr:postcode":"16820",
    "addr:street":"E Main St",
    "iso:country":"US",
    "sg:address":"243 E Main St",
    "sg:city":"Millheim",
    "sg:classifiers":[
        {
            "category":"Insurance",
            "subcategory":"Insurance Agent",
            "type":"Services"
        }
    ],
    "sg:phone":"+1   ",
    "sg:postcode":"16820",
    "sg:province":"PA",
    "wof:name":"Lutheran Brotherhood Insurance",
    "wof:placetype":"venue"
},
  "geometry": {"coordinates":[-77.467721,40.894154],"type":"Point"}
}