{
  "type": "Feature",
  "properties": {
    "iso:country":"US",
    "sg:address":"1309 Powder Mill Hollow Rd",
    "sg:city":"Boyertown",
    "sg:classifiers":[
        {
            "category":"Professional",
            "subcategory":"Business Services",
            "type":"Services"
        }
    ],
    "sg:phone":"+1 610 689 8309",
    "sg:postcode":"19512",
    "sg:province":"PA",
    "sg:tags":[
        "recording",
        "studio"
    ],
    "sg:website":"www.pmcomp.net",
    "wof:name":"Promediacomp",
    "wof:placetype":"venue"
},
  "geometry": {"coordinates":[-75.728437,40.317692],"type":"Point"}
}