{
  "type": "Feature",
  "properties": {
    "iso:country":"US",
    "sg:address":"7060 Essington Ave",
    "sg:city":"Philadelphia",
    "sg:classifiers":[
        {
            "category":"Parking",
            "type":"Transportation"
        },
        {
            "category":"Airline",
            "type":"Transportation"
        }
    ],
    "sg:phone":"+1 215 492 1161",
    "sg:postcode":"19153",
    "sg:province":"PA",
    "sg:tags":[
        "airport"
    ],
    "sg:website":"www.avistarparking.com/fasttrack",
    "wof:name":"FastTrack Airport Parking",
    "wof:placetype":"venue"
},
  "geometry": {"coordinates":[-75.22516899999999,39.901232],"type":"Point"}
}