{
  "type": "Feature",
  "properties": {
    "iso:country":"US",
    "sg:address":"345 Riverview Ave",
    "sg:city":"Bellevue",
    "sg:classifiers":[
        {
            "category":"Professional",
            "subcategory":"Computer Services",
            "type":"Services"
        }
    ],
    "sg:phone":"+1 412 766 5580",
    "sg:postcode":"15202",
    "sg:province":"PA",
    "sg:tags":[
        "consultant",
        "designer",
        "programing",
        "custom"
    ],
    "wof:name":"Chieffe Enterprises Inc",
    "wof:placetype":"venue"
},
  "geometry": {"coordinates":[-80.062162,40.49336],"type":"Point"}
}