{
  "type": "Feature",
  "properties": {
    "iso:country":"US",
    "sg:address":"1201 New Ford Mill Rd",
    "sg:city":"Morrisville",
    "sg:classifiers":[
        {
            "category":"Utilities",
            "subcategory":"Refuse",
            "type":"Services"
        }
    ],
    "sg:phone":"+1   ",
    "sg:postcode":"19067",
    "sg:province":"PA",
    "sg:tags":[
        "disposal",
        "waste",
        "municipal",
        "facility"
    ],
    "wof:name":"A Waste Management Company Wmi",
    "wof:placetype":"venue"
},
  "geometry": {"coordinates":[-74.76956,40.161489],"type":"Point"}
}