{
  "type": "Feature",
  "properties": {
    "addr:full":"2416 Patton Rd Harrisburg PA 17112",
    "addr:housenumber":"2416",
    "addr:postcode":"17112",
    "addr:street":"Patton Rd",
    "iso:country":"US",
    "sg:address":"2416 Patton Rd",
    "sg:city":"Harrisburg",
    "sg:classifiers":[
        {
            "category":"Real Estate",
            "subcategory":"Real Estate Agent",
            "type":"Services"
        }
    ],
    "sg:phone":"+1 717 657 3497",
    "sg:postcode":"17112",
    "sg:province":"PA",
    "wof:name":"Dave Walker Realtor",
    "wof:placetype":"venue"
},
  "geometry": {"coordinates":[-76.820663,40.341259],"type":"Point"}
}