{
  "type": "Feature",
  "properties": {
    "iso:country":"US",
    "sg:address":"136 N McKean St",
    "sg:city":"Kittanning",
    "sg:classifiers":[
        {
            "category":"Food & Beverages",
            "subcategory":"Bakery",
            "type":"Retail Goods"
        }
    ],
    "sg:phone":"+1 724 543 7437",
    "sg:postcode":"16201",
    "sg:province":"PA",
    "sg:tags":[
        "baker"
    ],
    "wof:name":"Pontious Bakery",
    "wof:placetype":"venue"
},
  "geometry": {"coordinates":[-79.51986100000001,40.816257],"type":"Point"}
}