{
  "type": "Feature",
  "properties": {
    "iso:country":"US",
    "sg:address":"800 E High St Ste 2",
    "sg:city":"Pottstown",
    "sg:classifiers":[
        {
            "category":"Professional",
            "subcategory":"Advertising",
            "type":"Services"
        }
    ],
    "sg:phone":"+1 610 326 8177",
    "sg:postcode":"19464",
    "sg:province":"PA",
    "sg:tags":[
        "agency",
        "specialty"
    ],
    "sg:website":"http://www.skadv.com",
    "wof:name":"Sk Advertising",
    "wof:placetype":"venue"
},
  "geometry": {"coordinates":[-75.634773,40.243729],"type":"Point"}
}