{
  "type": "Feature",
  "properties": {
    "iso:country":"US",
    "sg:address":"656 Morgantown Rd",
    "sg:city":"Uniontown",
    "sg:classifiers":[
        {
            "category":"Retail",
            "subcategory":"Auto Repair",
            "type":"Services"
        }
    ],
    "sg:phone":"+1 724 438 9367",
    "sg:postcode":"15401",
    "sg:province":"PA",
    "sg:tags":[
        "repairing",
        "automobile",
        "general"
    ],
    "wof:name":"Murray's Auto Repair",
    "wof:placetype":"venue"
},
  "geometry": {"coordinates":[-79.739338,39.877511],"type":"Point"}
}