{
  "type": "Feature",
  "properties": {
    "addr:full":"1021 Crystal Cave Rd Kutztown PA 19530",
    "addr:housenumber":"1021",
    "addr:postcode":"19530",
    "addr:street":"Crystal Cave Rd",
    "iso:country":"US",
    "sg:address":"1021 Crystal Cave Rd",
    "sg:city":"Kutztown",
    "sg:classifiers":[
        {
            "category":"Farming",
            "subcategory":"Livestock Farm",
            "type":"Manufacturing & Wholesale Goods"
        }
    ],
    "sg:phone":"+1   ",
    "sg:postcode":"19530",
    "sg:province":"PA",
    "sg:tags":[
        "wheat",
        "beef",
        "corn",
        "soybean",
        "cattle",
        "feedlot"
    ],
    "wof:name":"Leroy Sunday",
    "wof:placetype":"venue"
},
  "geometry": {"coordinates":[-75.857766,40.528748],"type":"Point"}
}