{
  "type": "Feature",
  "properties": {
    "iso:country":"US",
    "sg:address":"4332 Lycoming Creek Rd",
    "sg:city":"Cogan Station",
    "sg:classifiers":[
        {
            "category":"Building & Trades",
            "subcategory":"Plumbing",
            "type":"Services"
        }
    ],
    "sg:phone":"+1 570 494 1300",
    "sg:postcode":"17728",
    "sg:province":"PA",
    "sg:tags":[
        "heating",
        "contractor"
    ],
    "wof:name":"Suburban Agway",
    "wof:placetype":"venue"
},
  "geometry": {"coordinates":[-77.06959500000001,41.308481],"type":"Point"}
}