{
  "type": "Feature",
  "properties": {
    "iso:country":"US",
    "sg:address":"1355 E Lehman St",
    "sg:city":"Lebanon",
    "sg:classifiers":[
        {
            "category":"Personal",
            "subcategory":"Beauty Salon",
            "type":"Services"
        }
    ],
    "sg:phone":"+1 717 306 4222",
    "sg:postcode":"17046",
    "sg:province":"PA",
    "sg:tags":[
        "shop"
    ],
    "wof:name":"Regal Nails",
    "wof:placetype":"venue"
},
  "geometry": {"coordinates":[-76.38723899999999,40.349306],"type":"Point"}
}