{
  "type": "Feature",
  "properties": {
    "addr:full":"969 Butternut Rd Coopersburg PA 18036",
    "addr:housenumber":"969",
    "addr:postcode":"18036",
    "addr:street":"Butternut Rd",
    "iso:country":"US",
    "sg:address":"969 Butternut Rd",
    "sg:city":"Coopersburg",
    "sg:classifiers":[
        {
            "category":"Organizations",
            "subcategory":"Religious Organization",
            "type":"Services"
        }
    ],
    "sg:phone":"+1 610 282 3580",
    "sg:postcode":"18036",
    "sg:province":"PA",
    "wof:name":"Shorb Thos P Rev",
    "wof:placetype":"venue"
},
  "geometry": {"coordinates":[-75.40129899999999,40.502701],"type":"Point"}
}