{
  "type": "Feature",
  "properties": {
    "addr:full":"820 5th Ave Patton PA 16668",
    "addr:housenumber":"820",
    "addr:postcode":"16668",
    "addr:street":"5Th Ave",
    "iso:country":"US",
    "sg:address":"820 5th Ave",
    "sg:city":"Patton",
    "sg:classifiers":[
        {
            "category":"Health Services",
            "subcategory":"Doctor",
            "type":"Services"
        }
    ],
    "sg:phone":"+1 814 674 5806",
    "sg:postcode":"16668",
    "sg:province":"PA",
    "sg:tags":[
        "dentist"
    ],
    "wof:name":"Richard W Larkin DMD",
    "wof:placetype":"venue"
},
  "geometry": {"coordinates":[-78.650047,40.634693],"type":"Point"}
}