{
  "type": "Feature",
  "properties": {
    "addr:full":"303 Golf Club Ave Dillsburg PA 17019",
    "addr:housenumber":"303",
    "addr:postcode":"17019",
    "addr:street":"Golf Club Ave",
    "iso:country":"US",
    "sg:address":"303 Golf Club Ave",
    "sg:city":"Dillsburg",
    "sg:classifiers":[
        {
            "category":"Restaurant",
            "type":"Food & Drink"
        }
    ],
    "sg:phone":"+1 717 432 4812",
    "sg:postcode":"17019",
    "sg:province":"PA",
    "sg:website":"www.rangeendgolfclub.com",
    "wof:name":"Mulligan's Steak House",
    "wof:placetype":"venue"
},
  "geometry": {"coordinates":[-77.050213,40.106921],"type":"Point"}
}