{
  "type": "Feature",
  "properties": {
    "iso:country":"US",
    "sg:address":"3333 Rodgers Ave",
    "sg:city":"Aston",
    "sg:classifiers":[
        {
            "category":"Building & Trades",
            "subcategory":"Landscaping Services",
            "type":"Services"
        }
    ],
    "sg:phone":"+1   ",
    "sg:postcode":"19014",
    "sg:province":"PA",
    "wof:name":"Cardiles Lawn & Garden",
    "wof:placetype":"venue"
},
  "geometry": {"coordinates":[-75.43204799999999,39.842302],"type":"Point"}
}