{
  "type": "Feature",
  "properties": {
    "iso:country":"US",
    "sg:address":"400 W North St",
    "sg:city":"Butler",
    "sg:classifiers":[
        {
            "category":"Insurance",
            "subcategory":"Insurance Agent",
            "type":"Services"
        }
    ],
    "sg:phone":"+1   ",
    "sg:postcode":"16001",
    "sg:province":"PA",
    "sg:tags":[
        "broker"
    ],
    "wof:name":"Thrivent Fincl For Lutherans",
    "wof:placetype":"venue"
},
  "geometry": {"coordinates":[-79.90129,40.862379],"type":"Point"}
}