{
  "type": "Feature",
  "properties": {
    "addr:full":"3503 N B St Philadelphia PA 19134",
    "addr:housenumber":"3503",
    "addr:postcode":"19134",
    "addr:street":"N B St",
    "iso:country":"US",
    "sg:address":"3503 N B St",
    "sg:city":"Philadelphia",
    "sg:classifiers":[
        {
            "category":"Retail",
            "subcategory":"Storage",
            "type":"Services"
        }
    ],
    "sg:phone":"+1 215 423 4000",
    "sg:postcode":"19134",
    "sg:province":"PA",
    "sg:tags":[
        "self"
    ],
    "sg:website":"www.21css.com/en/philadelphia.html",
    "wof:name":"21st Century Self Storage",
    "wof:placetype":"venue"
},
  "geometry": {"coordinates":[-75.124394,40.002684],"type":"Point"}
}