{
  "type": "Feature",
  "properties": {
    "iso:country":"US",
    "sg:address":"5256 Meadow Ln",
    "sg:city":"Gap",
    "sg:classifiers":[
        {
            "category":"Shopping",
            "subcategory":"Catalog Store",
            "type":"Retail Goods"
        }
    ],
    "sg:phone":"+1 717 442 8545",
    "sg:postcode":"17527",
    "sg:province":"PA",
    "sg:tags":[
        "mail",
        "order",
        "online"
    ],
    "wof:name":"Martin, Linda Avon Representative",
    "wof:placetype":"venue"
},
  "geometry": {"coordinates":[-76.028029,39.990547],"type":"Point"}
}