{
  "type": "Feature",
  "properties": {
    "addr:full":"285 Greenville Rd Denver PA 17517",
    "addr:housenumber":"285",
    "addr:postcode":"17517",
    "addr:street":"Greenville Rd",
    "iso:country":"US",
    "sg:address":"285 Greenville Rd",
    "sg:city":"Denver",
    "sg:classifiers":[
        {
            "category":"Travel",
            "subcategory":"Campground",
            "type":"Entertainment"
        }
    ],
    "sg:phone":"+1 717 336 5564",
    "sg:postcode":"17517",
    "sg:province":"PA",
    "sg:website":"www.pacampgrounds.com",
    "wof:name":"Hickory Run Family Campground",
    "wof:placetype":"venue"
},
  "geometry": {"coordinates":[-76.15728799999999,40.263651],"type":"Point"}
}