{
  "type": "Feature",
  "properties": {
    "iso:country":"US",
    "sg:address":"1604 E High St",
    "sg:city":"Waynesburg",
    "sg:classifiers":[
        {
            "category":"Personal",
            "subcategory":"Beauty Salon",
            "type":"Services"
        }
    ],
    "sg:phone":"+1 724 627 5971",
    "sg:postcode":"15370",
    "sg:province":"PA",
    "sg:tags":[
        "shop"
    ],
    "wof:name":"Nails Down Under Inc",
    "wof:placetype":"venue"
},
  "geometry": {"coordinates":[-80.167422,39.896198],"type":"Point"}
}