{
  "type": "Feature",
  "properties": {
    "iso:country":"US",
    "sg:address":"5217 Kemmerer St",
    "sg:city":"Whitehall",
    "sg:classifiers":[
        {
            "category":"Manufacturing",
            "subcategory":"Paper Products",
            "type":"Manufacturing & Wholesale Goods"
        }
    ],
    "sg:phone":"+1 610 262 8860",
    "sg:postcode":"18052",
    "sg:province":"PA",
    "sg:tags":[
        "box",
        "packaging",
        "fiber",
        "mfg"
    ],
    "wof:name":"Century Packaging Inc",
    "wof:placetype":"venue"
},
  "geometry": {"coordinates":[-75.510437,40.691361],"type":"Point"}
}