{
  "type": "Feature",
  "properties": {
    "iso:country":"US",
    "sg:address":"490 Fisher Ave",
    "sg:city":"Catawissa",
    "sg:classifiers":[
        {
            "category":"Social Services",
            "subcategory":"Child Care",
            "type":"Services"
        }
    ],
    "sg:phone":"+1 570 356 7933",
    "sg:postcode":"17820",
    "sg:province":"PA",
    "wof:name":"Academy Of Little Learners",
    "wof:placetype":"venue"
},
  "geometry": {"coordinates":[-76.45735000000001,40.952113],"type":"Point"}
}