{
  "type": "Feature",
  "properties": {
    "iso:country":"US",
    "sg:address":"801 E Hill Dr",
    "sg:city":"New Kensington",
    "sg:classifiers":[
        {
            "category":"Manufacturing",
            "subcategory":"Metals",
            "type":"Manufacturing & Wholesale Goods"
        }
    ],
    "sg:phone":"+1 724 337 8000",
    "sg:postcode":"15068",
    "sg:province":"PA",
    "sg:tags":[
        "ornamental",
        "fabricates",
        "ironwork"
    ],
    "wof:name":"Alfred E Cecchetti Fabricating",
    "wof:placetype":"venue"
},
  "geometry": {"coordinates":[-79.73572,40.56914],"type":"Point"}
}