{
  "type": "Feature",
  "properties": {
    "iso:country":"US",
    "sg:address":"61 Evergreen Ave",
    "sg:city":"Media",
    "sg:classifiers":[
        {
            "category":"Health Services",
            "subcategory":"Hospital",
            "type":"Services"
        }
    ],
    "sg:phone":"+1 610 325 4072",
    "sg:postcode":"19063",
    "sg:province":"PA",
    "sg:tags":[
        "mental"
    ],
    "wof:name":"Life Guidance Svc Inc",
    "wof:placetype":"venue"
},
  "geometry": {"coordinates":[-75.38947,39.934891],"type":"Point"}
}