{
  "type": "Feature",
  "properties": {
    "addr:full":"780 Seem Dr Kutztown PA 19530",
    "addr:housenumber":"780",
    "addr:postcode":"19530",
    "addr:street":"Seem Dr",
    "iso:country":"US",
    "sg:address":"780 Seem Dr",
    "sg:city":"Kutztown",
    "sg:classifiers":[
        {
            "category":"Building & Trades",
            "subcategory":"Landscaping Services",
            "type":"Services"
        }
    ],
    "sg:phone":"+1 610 683 7211",
    "sg:postcode":"19530",
    "sg:province":"PA",
    "sg:tags":[
        "consultant",
        "lawn",
        "designer",
        "landscape",
        "contractor"
    ],
    "sg:website":"http://www.TGSlandscaping.com",
    "wof:name":"The Greener Side",
    "wof:placetype":"venue"
},
  "geometry": {"coordinates":[-75.76785599999999,40.532263],"type":"Point"}
}