{
  "type": "Feature",
  "properties": {
    "iso:country":"US",
    "sg:address":"601 Broad St",
    "sg:city":"Sewickley",
    "sg:classifiers":[
        {
            "category":"Social Services",
            "subcategory":"Child Care",
            "type":"Services"
        }
    ],
    "sg:phone":"+1 412 749 1000",
    "sg:postcode":"15143",
    "sg:province":"PA",
    "sg:tags":[
        "day"
    ],
    "wof:name":"Damian Amato & Start",
    "wof:placetype":"venue"
},
  "geometry": {"coordinates":[-80.178572,40.541368],"type":"Point"}
}