{
  "type": "Feature",
  "properties": {
    "iso:country":"US",
    "sg:address":"397 Cove St",
    "sg:city":"Everett",
    "sg:classifiers":[
        {
            "category":"Retail",
            "subcategory":"Auto Repair",
            "type":"Services"
        }
    ],
    "sg:phone":"+1 814 735 2256",
    "sg:postcode":"15537",
    "sg:province":"PA",
    "sg:tags":[
        "body",
        "automobile",
        "painting",
        "repairing"
    ],
    "wof:name":"Conways Auto Body",
    "wof:placetype":"venue"
},
  "geometry": {"coordinates":[-78.32638900000001,40.038589],"type":"Point"}
}