{
  "type": "Feature",
  "properties": {
    "iso:country":"US",
    "sg:address":"133 Oakwood Ln",
    "sg:city":"Shippenville",
    "sg:classifiers":[
        {
            "category":"Personal",
            "subcategory":"Beauty Salon",
            "type":"Services"
        }
    ],
    "sg:phone":"+1 814 226 4180",
    "sg:postcode":"16254",
    "sg:province":"PA",
    "wof:name":"Barbara Mc Means Beauty Ctr",
    "wof:placetype":"venue"
},
  "geometry": {"coordinates":[-79.422561,41.245121],"type":"Point"}
}