{
  "type": "Feature",
  "properties": {
    "iso:country":"US",
    "sg:address":"100 CONTINENTAL DR",
    "sg:city":"ELIZABETHTOWN",
    "sg:classifiers":[
        {
            "category":"Health Services",
            "subcategory":"Dentist",
            "type":"Services"
        }
    ],
    "sg:phone":"+1 717 367 1336",
    "sg:postcode":"17022",
    "sg:province":"PA",
    "sg:website":"http://www.etowndental.com",
    "wof:name":"Elizabethtown Dental Associates",
    "wof:placetype":"venue"
},
  "geometry": {"coordinates":[-76.595472,40.152215],"type":"Point"}
}