{
  "type": "Feature",
  "properties": {
    "iso:country":"US",
    "sg:address":"610 Painter St",
    "sg:city":"Media",
    "sg:classifiers":[
        {
            "category":"Wholesale",
            "subcategory":"Auto Parts",
            "type":"Manufacturing & Wholesale Goods"
        }
    ],
    "sg:phone":"+1   ",
    "sg:postcode":"19063",
    "sg:province":"PA",
    "wof:name":"Peter Jensen",
    "wof:placetype":"venue"
},
  "geometry": {"coordinates":[-75.398822,39.915886],"type":"Point"}
}