{
  "type": "Feature",
  "properties": {
    "addr:full":"521 Greenfield Ave Pittsburgh PA 15207",
    "addr:housenumber":"521",
    "addr:postcode":"15207",
    "addr:street":"Greenfield Ave",
    "iso:country":"US",
    "sg:address":"521 Greenfield Ave",
    "sg:city":"Pittsburgh",
    "sg:classifiers":[
        {
            "category":"Health Services",
            "subcategory":"Doctor",
            "type":"Services"
        }
    ],
    "sg:phone":"+1 412 422 6500",
    "sg:postcode":"15207",
    "sg:province":"PA",
    "sg:tags":[
        "physician",
        "surgeon"
    ],
    "wof:name":"Bernard J Bernacki & Assoc",
    "wof:placetype":"venue"
},
  "geometry": {"coordinates":[-79.940963,40.425965],"type":"Point"}
}