{
  "type": "Feature",
  "properties": {
    "iso:country":"US",
    "sg:address":"308 31st Ave",
    "sg:city":"Altoona",
    "sg:classifiers":[
        {
            "category":"Real Estate",
            "subcategory":"Architect",
            "type":"Services"
        }
    ],
    "sg:phone":"+1 814 943 5035",
    "sg:postcode":"16601",
    "sg:province":"PA",
    "wof:name":"Robert R Refner",
    "wof:placetype":"venue"
},
  "geometry": {"coordinates":[-78.41228700000001,40.532481],"type":"Point"}
}