{
  "type": "Feature",
  "properties": {
    "iso:country":"US",
    "sg:address":"16098 Sawmill Rd",
    "sg:city":"Stewartstown",
    "sg:classifiers":[
        {
            "category":"Home & Garden",
            "subcategory":"Mobile Homes",
            "type":"Retail Goods"
        }
    ],
    "sg:phone":"+1 717 993 6456",
    "sg:postcode":"17363",
    "sg:province":"PA",
    "wof:name":"Paul K Miller Home Sales",
    "wof:placetype":"venue"
},
  "geometry": {"coordinates":[-76.63300099999999,39.776769],"type":"Point"}
}