{
  "type": "Feature",
  "properties": {
    "addr:full":"232 Orchard Ln Norristown PA 19401",
    "addr:housenumber":"232",
    "addr:postcode":"19401",
    "addr:street":"Orchard Ln",
    "iso:country":"US",
    "sg:address":"232 Orchard Ln",
    "sg:city":"Norristown",
    "sg:classifiers":[
        {
            "category":"Professional",
            "type":"Services"
        }
    ],
    "sg:phone":"+1 610 279 8969",
    "sg:postcode":"19401",
    "sg:province":"PA",
    "sg:tags":[
        "establishment"
    ],
    "wof:name":"Ensurstat",
    "wof:placetype":"venue"
},
  "geometry": {"coordinates":[-75.32209899999999,40.148577],"type":"Point"}
}