{
  "type": "Feature",
  "properties": {
    "iso:country":"US",
    "sg:address":"15 State St",
    "sg:city":"Baden",
    "sg:classifiers":[
        {
            "category":"Freight",
            "type":"Transportation"
        }
    ],
    "sg:phone":"+1 724 869 2177",
    "sg:postcode":"15005",
    "sg:province":"PA",
    "sg:tags":[
        "terminal",
        "operation",
        "river"
    ],
    "wof:name":"General Materials Terminals",
    "wof:placetype":"venue"
},
  "geometry": {"coordinates":[-80.226201,40.626476],"type":"Point"}
}