{
  "type": "Feature",
  "properties": {
    "iso:country":"US",
    "sg:address":"1224 Arch St 5th Floor",
    "sg:city":"Philadelphia",
    "sg:classifiers":[
        {
            "category":"Banks & Credit Unions",
            "subcategory":"Financial Services",
            "type":"Services"
        }
    ],
    "sg:phone":"+1 786 255 2055",
    "sg:postcode":"19107",
    "sg:province":"PA",
    "wof:name":"Capital Funding Partners.com SMALL BUSINESS LOANS No Application Fees",
    "wof:placetype":"venue"
},
  "geometry": {"coordinates":[-75.15979,39.954016],"type":"Point"}
}