{
  "type": "Feature",
  "properties": {
    "iso:country":"US",
    "sg:address":"1660 Columbia Ave",
    "sg:city":"Lancaster",
    "sg:classifiers":[
        {
            "category":"Personal",
            "subcategory":"Beauty Salon",
            "type":"Services"
        }
    ],
    "sg:phone":"+1 717 394 0747",
    "sg:postcode":"17603",
    "sg:province":"PA",
    "wof:name":"Phase II Hair Design",
    "wof:placetype":"venue"
},
  "geometry": {"coordinates":[-76.348152,40.037964],"type":"Point"}
}