{
  "type": "Feature",
  "properties": {
    "addr:full":"525 E Side Dr Lancaster PA 17601",
    "addr:housenumber":"525",
    "addr:postcode":"17601",
    "addr:street":"E Side Dr",
    "iso:country":"US",
    "sg:address":"525 E Side Dr",
    "sg:city":"Lancaster",
    "sg:classifiers":[
        {
            "category":"Health Services",
            "subcategory":"Doctor",
            "type":"Services"
        }
    ],
    "sg:phone":"+1 717 295 1204",
    "sg:postcode":"17601",
    "sg:province":"PA",
    "sg:tags":[
        "psychologist"
    ],
    "wof:name":"Rmd Associates",
    "wof:placetype":"venue"
},
  "geometry": {"coordinates":[-76.25278400000001,40.062693],"type":"Point"}
}