{
  "type": "Feature",
  "properties": {
    "iso:country":"US",
    "sg:address":"1069 Pottsville Pike",
    "sg:city":"Shoemakersville",
    "sg:classifiers":[
        {
            "category":"Wholesale",
            "subcategory":"Painting Supplies",
            "type":"Manufacturing & Wholesale Goods"
        },
        {
            "category":"Home & Garden",
            "subcategory":"Garden Supply",
            "type":"Retail Goods"
        },
        {
            "category":"Wholesale",
            "subcategory":"Construction Materials",
            "type":"Manufacturing & Wholesale Goods"
        },
        {
            "category":"Home & Garden",
            "subcategory":"Hardware",
            "type":"Retail Goods"
        }
    ],
    "sg:phone":"+1 610 562 7186",
    "sg:postcode":"19555",
    "sg:province":"PA",
    "sg:tags":[
        "lawn",
        "paint",
        "equipment",
        "part",
        "plumbing",
        "fixtures",
        "store"
    ],
    "sg:website":"http://www.kuzanshardware.com",
    "wof:name":"Kuzans True Value Hardware",
    "wof:placetype":"venue"
},
  "geometry": {"coordinates":[-75.966618,40.511876],"type":"Point"}
}