{
  "type": "Feature",
  "properties": {
    "iso:country":"US",
    "sg:address":"4294 Mill Rd",
    "sg:city":"Coopersburg",
    "sg:classifiers":[
        {
            "category":"Retail",
            "subcategory":"Portrait Studio",
            "type":"Services"
        },
        {
            "category":"Professional",
            "subcategory":"Art Services",
            "type":"Services"
        }
    ],
    "sg:phone":"+1 610 282 1575",
    "sg:postcode":"18036",
    "sg:province":"PA",
    "sg:tags":[
        "rental",
        "photographers-portrait",
        "photographic",
        "darkroom"
    ],
    "wof:name":"Sweet Peas Studio",
    "wof:placetype":"venue"
},
  "geometry": {"coordinates":[-75.395111,40.51902],"type":"Point"}
}