{
  "type": "Feature",
  "properties": {
    "addr:full":"11616 Keleket Dr Penn Hills PA 15235",
    "addr:housenumber":"11616",
    "addr:postcode":"15235",
    "addr:street":"Keleket Dr",
    "iso:country":"US",
    "sg:address":"11616 Keleket Dr",
    "sg:city":"Penn Hills",
    "sg:classifiers":[
        {
            "category":"Shopping",
            "subcategory":"Clothing, Apparel, & Fashions",
            "type":"Retail Goods"
        }
    ],
    "sg:phone":"+1 412 242 7557",
    "sg:postcode":"15235",
    "sg:province":"PA",
    "wof:name":"Fashion Bug",
    "wof:placetype":"venue"
},
  "geometry": {"coordinates":[-79.826877,40.464109],"type":"Point"}
}