{
  "type": "Feature",
  "properties": {
    "addr:full":"2207 E Ontario St Philadelphia PA 19134",
    "addr:housenumber":"2207",
    "addr:postcode":"19134",
    "addr:street":"E Ontario St",
    "iso:country":"US",
    "sg:address":"2207 E Ontario St",
    "sg:city":"Philadelphia",
    "sg:classifiers":[
        {
            "category":"Retail",
            "subcategory":"Repair Shop",
            "type":"Services"
        }
    ],
    "sg:phone":"+1 215 533 8060",
    "sg:postcode":"19134",
    "sg:province":"PA",
    "sg:tags":[
        "flo",
        "compactors",
        "hydraulic",
        "equipment",
        "maintenance",
        "balers"
    ],
    "wof:name":"Tramrail Baler & Compactor Service Inc",
    "wof:placetype":"venue"
},
  "geometry": {"coordinates":[-75.103984,39.993676],"type":"Point"}
}