{
  "type": "Feature",
  "properties": {
    "iso:country":"US",
    "sg:address":"99 Lorson Rd",
    "sg:city":"Williamsport",
    "sg:classifiers":[
        {
            "category":"Building & Trades",
            "subcategory":"Plumbing",
            "type":"Services"
        }
    ],
    "sg:phone":"+1   ",
    "sg:postcode":"17702",
    "sg:province":"PA",
    "sg:tags":[
        "plumbing",
        "heating",
        "air"
    ],
    "wof:name":"Paul J Lorson Plumbing and Htg",
    "wof:placetype":"venue"
},
  "geometry": {"coordinates":[-77.12423200000001,41.141521],"type":"Point"}
}