{
  "type": "Feature",
  "properties": {
    "iso:country":"US",
    "sg:address":"1883 Painters Run Rd",
    "sg:city":"Pittsburgh",
    "sg:classifiers":[
        {
            "category":"Food & Beverages",
            "subcategory":"Groceries & Convenience Stores",
            "type":"Retail Goods"
        }
    ],
    "sg:phone":"+1 412 914 0878",
    "sg:postcode":"15241",
    "sg:province":"PA",
    "sg:tags":[
        "grocer"
    ],
    "wof:name":"Carlena's Italian Mkt & Deli",
    "wof:placetype":"venue"
},
  "geometry": {"coordinates":[-80.081459,40.361916],"type":"Point"}
}