{
  "type": "Feature",
  "properties": {
    "iso:country":"US",
    "sg:address":"817 N Whitford Rd",
    "sg:city":"Exton",
    "sg:classifiers":[
        {
            "category":"Building & Trades",
            "subcategory":"Construction",
            "type":"Services"
        }
    ],
    "sg:phone":"+1 610 524 7847",
    "sg:postcode":"19341",
    "sg:province":"PA",
    "sg:tags":[
        "painter"
    ],
    "wof:name":"Paper Doll",
    "wof:placetype":"venue"
},
  "geometry": {"coordinates":[-75.65808,40.051521],"type":"Point"}
}