{
  "type": "Feature",
  "properties": {
    "iso:country":"US",
    "sg:address":"3105 Expresso Way",
    "sg:city":"York",
    "sg:classifiers":[
        {
            "category":"Wholesale",
            "subcategory":"Scrap",
            "type":"Manufacturing & Wholesale Goods"
        }
    ],
    "sg:phone":"+1   ",
    "sg:postcode":"17402",
    "sg:province":"PA",
    "sg:tags":[
        "material"
    ],
    "wof:name":"Gordon Waste Co",
    "wof:placetype":"venue"
},
  "geometry": {"coordinates":[-76.74055,40.050104],"type":"Point"}
}