{
  "type": "Feature",
  "properties": {
    "addr:full":"2191 Macdade Blvd Holmes PA 19043",
    "addr:housenumber":"2191",
    "addr:postcode":"19043",
    "addr:street":"Macdade Blvd",
    "iso:country":"US",
    "sg:address":"2191 Macdade Blvd",
    "sg:city":"Holmes",
    "sg:classifiers":[
        {
            "category":"Government",
            "subcategory":"Office",
            "type":"Public Place"
        }
    ],
    "sg:phone":"+1 610 237 1060",
    "sg:postcode":"19043",
    "sg:province":"PA",
    "sg:tags":[
        "armed",
        "force",
        "recruiting"
    ],
    "wof:name":"US Army Recruiting",
    "wof:placetype":"venue"
},
  "geometry": {"coordinates":[-75.310714,39.897546],"type":"Point"}
}