{
  "type": "Feature",
  "properties": {
    "iso:country":"US",
    "sg:address":"1624 Spruce St",
    "sg:city":"Philadelphia",
    "sg:classifiers":[
        {
            "category":"Professional",
            "subcategory":"Advertising",
            "type":"Services"
        }
    ],
    "sg:phone":"+1   ",
    "sg:postcode":"19103",
    "sg:province":"PA",
    "sg:tags":[
        "as",
        "agency",
        "operates",
        "an"
    ],
    "wof:name":"Bear Advertising Inc",
    "wof:placetype":"venue"
},
  "geometry": {"coordinates":[-75.169517,39.947488],"type":"Point"}
}