{
  "type": "Feature",
  "properties": {
    "iso:country":"US",
    "sg:address":"9 Lacrue Ave Ste 7",
    "sg:city":"Glen Mills",
    "sg:classifiers":[
        {
            "category":"Building & Trades",
            "subcategory":"Construction",
            "type":"Services"
        }
    ],
    "sg:phone":"+1 610 459 8147",
    "sg:postcode":"19342",
    "sg:province":"PA",
    "sg:tags":[
        "contractor"
    ],
    "wof:name":"Construction Services Group Llc",
    "wof:placetype":"venue"
},
  "geometry": {"coordinates":[-75.528547,39.888364],"type":"Point"}
}