{
  "type": "Feature",
  "properties": {
    "iso:country":"US",
    "sg:address":"100 Sandy Creek Rd",
    "sg:city":"Verona",
    "sg:classifiers":[
        {
            "category":"Manufacturing",
            "subcategory":"Metals",
            "type":"Manufacturing & Wholesale Goods"
        },
        {
            "category":"Manufacturing",
            "subcategory":"Building Materials",
            "type":"Manufacturing & Wholesale Goods"
        }
    ],
    "sg:phone":"+1 412 793 1180",
    "sg:postcode":"15147",
    "sg:province":"PA",
    "sg:tags":[
        "fabricator",
        "work",
        "sheet"
    ],
    "wof:name":"Reiter Sheet Metal Inc",
    "wof:placetype":"venue"
},
  "geometry": {"coordinates":[-79.851744,40.482952],"type":"Point"}
}