{
  "type": "Feature",
  "properties": {
    "addr:full":"503 W Lancaster Ave Wayne PA 19087",
    "addr:housenumber":"503",
    "addr:postcode":"19087",
    "addr:street":"W Lancaster Ave",
    "iso:country":"US",
    "sg:address":"503 W Lancaster Ave",
    "sg:city":"Wayne",
    "sg:classifiers":[
        {
            "category":"Insurance",
            "subcategory":"Hazard Insurance",
            "type":"Services"
        }
    ],
    "sg:phone":"+1 610 688 5013",
    "sg:postcode":"19087",
    "sg:province":"PA",
    "sg:tags":[
        "commercial",
        "business"
    ],
    "wof:name":"Lillian Williams Insurance",
    "wof:placetype":"venue"
},
  "geometry": {"coordinates":[-75.401993,40.044781],"type":"Point"}
}