{
  "type": "Feature",
  "properties": {
    "iso:country":"US",
    "sg:address":"1900 Halfmoon Valley Rd",
    "sg:city":"Port Matilda",
    "sg:classifiers":[
        {
            "category":"Farming",
            "subcategory":"Dairy Farm",
            "type":"Manufacturing & Wholesale Goods"
        }
    ],
    "sg:phone":"+1   ",
    "sg:postcode":"16870",
    "sg:province":"PA",
    "wof:name":"Grahams Farm",
    "wof:placetype":"venue"
},
  "geometry": {"coordinates":[-77.99764999999999,40.806928],"type":"Point"}
}