{
  "type": "Feature",
  "properties": {
    "iso:country":"US",
    "sg:address":"1460 Wyoming Ave",
    "sg:city":"Kingston",
    "sg:classifiers":[
        {
            "category":"Professional",
            "subcategory":"Lawyer & Legal Services",
            "type":"Services"
        }
    ],
    "sg:phone":"+1 570 288 6441",
    "sg:postcode":"18704",
    "sg:province":"PA",
    "sg:tags":[
        "attorney",
        "accident",
        "estate",
        "business",
        "corporation",
        "partnership",
        "damage",
        "planning",
        "property",
        "law"
    ],
    "sg:website":"http://www.bvrrlaw.com",
    "wof:name":"Burke Vullo Reilly Roberts Attorneys at Law",
    "wof:placetype":"venue"
},
  "geometry": {"coordinates":[-75.87003199999999,41.288983],"type":"Point"}
}