{
  "type": "Feature",
  "properties": {
    "iso:country":"US",
    "sg:address":"141 E Wheeling St",
    "sg:city":"Washington",
    "sg:classifiers":[
        {
            "category":"Education",
            "subcategory":"Library",
            "type":"Public Place"
        }
    ],
    "sg:phone":"+1 724 223 6070",
    "sg:postcode":"15301",
    "sg:province":"PA",
    "wof:name":"Washington & Jefferson Clg Lib",
    "wof:placetype":"venue"
},
  "geometry": {"coordinates":[-80.241433,40.169962],"type":"Point"}
}