{
  "type": "Feature",
  "properties": {
    "addr:full":"3865 William Penn Hwy Murrysville PA 15668",
    "addr:housenumber":"3865",
    "addr:postcode":"15668",
    "addr:street":"William Penn Hwy",
    "iso:country":"US",
    "sg:address":"3865 William Penn Hwy",
    "sg:city":"Murrysville",
    "sg:classifiers":[
        {
            "category":"Real Estate",
            "subcategory":"Real Estate Agent",
            "type":"Services"
        }
    ],
    "sg:phone":"+1   ",
    "sg:postcode":"15668",
    "sg:province":"PA",
    "wof:name":"Coldwell Bnkr RE E Rgional Off",
    "wof:placetype":"venue"
},
  "geometry": {"coordinates":[-79.697834,40.427126],"type":"Point"}
}