{
  "type": "Feature",
  "properties": {
    "iso:country":"US",
    "sg:address":"3560 Old Mill Rd",
    "sg:city":"Slatington",
    "sg:classifiers":[
        {
            "category":"Building & Trades",
            "subcategory":"Construction",
            "type":"Services"
        }
    ],
    "sg:phone":"+1 610 767 4992",
    "sg:postcode":"18080",
    "sg:province":"PA",
    "sg:tags":[
        "home",
        "improvement",
        "general",
        "contracting"
    ],
    "wof:name":"Ed's Building & Remodeling",
    "wof:placetype":"venue"
},
  "geometry": {"coordinates":[-75.637452,40.739665],"type":"Point"}
}