{
  "type": "Feature",
  "properties": {
    "addr:full":"401 Park Dr Pittston PA 18641",
    "addr:housenumber":"401",
    "addr:postcode":"18641",
    "addr:street":"Park Dr",
    "iso:country":"US",
    "sg:address":"401 Park Dr",
    "sg:city":"Pittston",
    "sg:classifiers":[
        {
            "category":"Building & Trades",
            "subcategory":"Construction",
            "type":"Services"
        }
    ],
    "sg:phone":"+1   ",
    "sg:postcode":"18641",
    "sg:province":"PA",
    "sg:tags":[
        "house"
    ],
    "wof:name":"Lucine Development",
    "wof:placetype":"venue"
},
  "geometry": {"coordinates":[-75.754284,41.333014],"type":"Point"}
}