{
  "type": "Feature",
  "properties": {
    "iso:country":"US",
    "sg:address":"185 Margaret St",
    "sg:city":"Palmerton",
    "sg:classifiers":[
        {
            "category":"Professional",
            "subcategory":"Art Services",
            "type":"Services"
        }
    ],
    "sg:phone":"+1 610 377 0693",
    "sg:postcode":"18071",
    "sg:province":"PA",
    "sg:tags":[
        "designer",
        "display",
        "producer"
    ],
    "wof:name":"John Wiesner Cabinet Design Solutions",
    "wof:placetype":"venue"
},
  "geometry": {"coordinates":[-75.592789,40.850044],"type":"Point"}
}