{
  "type": "Feature",
  "properties": {
    "iso:country":"US",
    "sg:address":"8701 Torresdale Ave",
    "sg:city":"Philadelphia",
    "sg:classifiers":[
        {
            "category":"Retail",
            "subcategory":"Repair Shop",
            "type":"Services"
        }
    ],
    "sg:phone":"+1 215 624 5035",
    "sg:postcode":"19136",
    "sg:province":"PA",
    "sg:tags":[
        "lock",
        "locksmith"
    ],
    "sg:website":"http://www.brunellsecurity.com",
    "wof:name":"Brunell & Sons",
    "wof:placetype":"venue"
},
  "geometry": {"coordinates":[-75.00882,40.044441],"type":"Point"}
}