{
  "type": "Feature",
  "properties": {
    "iso:country":"US",
    "sg:address":"435 Bus Park Ln",
    "sg:city":"Allentown",
    "sg:classifiers":[
        {
            "category":"Manufacturing",
            "subcategory":"Glass & Minerals",
            "type":"Manufacturing & Wholesale Goods"
        }
    ],
    "sg:phone":"+1   ",
    "sg:postcode":"18109",
    "sg:province":"PA",
    "sg:tags":[
        "concrete",
        "product",
        "mfg"
    ],
    "wof:name":"Ka-MI Precast Concrete Pdts",
    "wof:placetype":"venue"
},
  "geometry": {"coordinates":[-75.457233,40.628542],"type":"Point"}
}