{
  "type": "Feature",
  "properties": {
    "iso:country":"US",
    "sg:address":"2372 Ardmore Blvd",
    "sg:city":"Pittsburgh",
    "sg:classifiers":[
        {
            "category":"Health Services",
            "subcategory":"Clinic",
            "type":"Services"
        },
        {
            "category":"Health Services",
            "subcategory":"Health Practitioner",
            "type":"Services"
        }
    ],
    "sg:phone":"+1 412 271 5000",
    "sg:postcode":"15221",
    "sg:province":"PA",
    "sg:tags":[
        "therapist",
        "therapy",
        "physical"
    ],
    "wof:name":"Core Network",
    "wof:placetype":"venue"
},
  "geometry": {"coordinates":[-79.847875,40.416132],"type":"Point"}
}