{
  "type": "Feature",
  "properties": {
    "iso:country":"US",
    "sg:address":"1304 Woodside Ave",
    "sg:city":"Ellwood City",
    "sg:classifiers":[
        {
            "category":"Retail",
            "subcategory":"Auto Repair",
            "type":"Services"
        }
    ],
    "sg:phone":"+1 724 752 1458",
    "sg:postcode":"16117",
    "sg:province":"PA",
    "sg:tags":[
        "automobile",
        "electric"
    ],
    "wof:name":"Harold Auto Electric Service",
    "wof:placetype":"venue"
},
  "geometry": {"coordinates":[-80.265458,40.872141],"type":"Point"}
}