{
  "type": "Feature",
  "properties": {
    "addr:full":"4125 3rd Ave Altoona PA 16602",
    "addr:housenumber":"4125",
    "addr:postcode":"16602",
    "addr:street":"3Rd Ave",
    "iso:country":"US",
    "sg:address":"4125 3rd Ave",
    "sg:city":"Altoona",
    "sg:classifiers":[
        {
            "category":"Organizations",
            "subcategory":"Non-profit Organization",
            "type":"Services"
        }
    ],
    "sg:phone":"+1   ",
    "sg:postcode":"16602",
    "sg:province":"PA",
    "sg:tags":[
        "social"
    ],
    "wof:name":"Epilepsy Society Blair County",
    "wof:placetype":"venue"
},
  "geometry": {"coordinates":[-78.414017,40.482925],"type":"Point"}
}