{
  "type": "Feature",
  "properties": {
    "iso:country":"US",
    "sg:address":"1405 N Cedar Crest Blvd",
    "sg:city":"Allentown",
    "sg:classifiers":[
        {
            "category":"Health Services",
            "subcategory":"Clinic",
            "type":"Services"
        }
    ],
    "sg:phone":"+1 610 437 7187",
    "sg:postcode":"18104",
    "sg:province":"PA",
    "sg:tags":[
        "medical",
        "examination"
    ],
    "wof:name":"Portamedic",
    "wof:placetype":"venue"
},
  "geometry": {"coordinates":[-75.532037,40.610438],"type":"Point"}
}