{
  "type": "Feature",
  "properties": {
    "addr:full":"1201 N Church St Hazleton PA 18202",
    "addr:housenumber":"1201",
    "addr:postcode":"18202",
    "addr:street":"N Church St",
    "iso:country":"US",
    "sg:address":"1201 N Church St",
    "sg:city":"Hazleton",
    "sg:classifiers":[
        {
            "category":"Professional",
            "subcategory":"Business Services",
            "type":"Services"
        }
    ],
    "sg:phone":"+1 570 459 2091",
    "sg:postcode":"18202",
    "sg:province":"PA",
    "sg:tags":[
        "inventory"
    ],
    "wof:name":"RGIS Inventory Specialist",
    "wof:placetype":"venue"
},
  "geometry": {"coordinates":[-75.97985799999999,40.979805],"type":"Point"}
}