{
  "type": "Feature",
  "properties": {
    "iso:country":"US",
    "sg:address":"226 E Lancaster Ave",
    "sg:city":"Wayne",
    "sg:classifiers":[
        {
            "category":"Autos & Motor Vehicles",
            "subcategory":"Fuel & Gas Station",
            "type":"Retail Goods"
        },
        {
            "category":"Retail",
            "subcategory":"Auto Repair",
            "type":"Services"
        }
    ],
    "sg:phone":"+1 610 989 0828",
    "sg:postcode":"19087",
    "sg:province":"PA",
    "sg:tags":[
        "automobile",
        "inspection",
        "diagnostic"
    ],
    "sg:website":"http://www.garttmeyerauto.net",
    "wof:name":"Garttmeyer James Automotive Services",
    "wof:placetype":"venue"
},
  "geometry": {"coordinates":[-75.383568,40.04384],"type":"Point"}
}