{
  "type": "Feature",
  "properties": {
    "iso:country":"US",
    "sg:address":"64 N Main St",
    "sg:city":"Union City",
    "sg:classifiers":[
        {
            "category":"Personal",
            "subcategory":"Beauty Salon",
            "type":"Services"
        }
    ],
    "sg:phone":"+1   ",
    "sg:postcode":"16438",
    "sg:province":"PA",
    "sg:tags":[
        "shop"
    ],
    "wof:name":"Jane Watts Beauty Salon",
    "wof:placetype":"venue"
},
  "geometry": {"coordinates":[-79.84551500000001,41.900129],"type":"Point"}
}