{
  "type": "Feature",
  "properties": {
    "iso:country":"US",
    "sg:address":"21 E Glenside Ave",
    "sg:city":"Glenside",
    "sg:classifiers":[
        {
            "category":"Restaurant",
            "type":"Food & Drink"
        }
    ],
    "sg:phone":"+1 215 887 2909",
    "sg:postcode":"19038",
    "sg:province":"PA",
    "wof:name":"Rizzo's Restaurant & Pizzeria",
    "wof:placetype":"venue"
},
  "geometry": {"coordinates":[-75.15328,40.100466],"type":"Point"}
}