{
  "type": "Feature",
  "properties": {
    "addr:full":"7259 Hasbrook Ave Philadelphia PA 19111",
    "addr:housenumber":"7259",
    "addr:postcode":"19111",
    "addr:street":"Hasbrook Ave",
    "iso:country":"US",
    "sg:address":"7259 Hasbrook Ave",
    "sg:city":"Philadelphia",
    "sg:classifiers":[
        {
            "category":"Retail",
            "subcategory":"Auto Repair",
            "type":"Services"
        }
    ],
    "sg:phone":"+1 215 745 1044",
    "sg:postcode":"19111",
    "sg:province":"PA",
    "sg:tags":[
        "recap",
        "retread",
        "tire"
    ],
    "wof:name":"Tire Net Usa",
    "wof:placetype":"venue"
},
  "geometry": {"coordinates":[-75.08811300000001,40.062937],"type":"Point"}
}