{
  "type": "Feature",
  "properties": {
    "iso:country":"US",
    "sg:address":"109 Chestnut St",
    "sg:city":"Natrona",
    "sg:classifiers":[
        {
            "category":"Recreation",
            "type":"Entertainment"
        }
    ],
    "sg:phone":"+1 724 224 5474",
    "sg:postcode":"15065",
    "sg:province":"PA",
    "sg:tags":[
        "skateboard",
        "parks",
        "rink"
    ],
    "wof:name":"Skatepark Of Natrona",
    "wof:placetype":"venue"
},
  "geometry": {"coordinates":[-79.723246,40.614022],"type":"Point"}
}