{
  "type": "Feature",
  "properties": {
    "addr:full":"512 Hughes St Bellefonte PA 16823",
    "addr:housenumber":"512",
    "addr:postcode":"16823",
    "addr:street":"Hughes St",
    "iso:country":"US",
    "sg:address":"512 Hughes St",
    "sg:city":"Bellefonte",
    "sg:classifiers":[
        {
            "category":"Organizations",
            "subcategory":"Religious Organization",
            "type":"Services"
        }
    ],
    "sg:phone":"+1 814 355 3358",
    "sg:postcode":"16823",
    "sg:province":"PA",
    "sg:website":"www.umc.org",
    "wof:name":"Faith United Methodist Church",
    "wof:placetype":"venue"
},
  "geometry": {"coordinates":[-77.76509900000001,40.91],"type":"Point"}
}