{
  "type": "Feature",
  "properties": {
    "iso:country":"US",
    "sg:address":"8015 Mcknight Rd",
    "sg:city":"Pittsburgh",
    "sg:classifiers":[
        {
            "category":"Personal",
            "subcategory":"Beauty Salon",
            "type":"Services"
        }
    ],
    "sg:phone":"+1 412 364 6008",
    "sg:postcode":"15237",
    "sg:province":"PA",
    "wof:name":"Styles",
    "wof:placetype":"venue"
},
  "geometry": {"coordinates":[-80.019577,40.550911],"type":"Point"}
}