{
  "type": "Feature",
  "properties": {
    "addr:full":"8906 W Chester Pike Upper Darby PA 19082",
    "addr:housenumber":"8906",
    "addr:postcode":"19082",
    "addr:street":"W Chester Pike",
    "iso:country":"US",
    "sg:address":"8906 W Chester Pike",
    "sg:city":"Upper Darby",
    "sg:classifiers":[
        {
            "category":"Professional",
            "subcategory":"Business Services",
            "type":"Services"
        }
    ],
    "sg:phone":"+1 610 789 5701",
    "sg:postcode":"19082",
    "sg:province":"PA",
    "sg:tags":[
        "equipment",
        "product",
        "processing",
        "microfilming",
        "microfilm"
    ],
    "wof:name":"C & C Source Inc",
    "wof:placetype":"venue"
},
  "geometry": {"coordinates":[-75.290046,39.967525],"type":"Point"}
}