{
  "type": "Feature",
  "properties": {
    "addr:full":"7001 State Rte 309 Coopersburg PA 18036",
    "addr:housenumber":"7001",
    "addr:postcode":"18036",
    "addr:street":"State Rte 309",
    "iso:country":"US",
    "sg:address":"7001 State Rte 309",
    "sg:city":"Coopersburg",
    "sg:classifiers":[
        {
            "category":"Insurance",
            "subcategory":"Insurance Agent",
            "type":"Services"
        }
    ],
    "sg:phone":"+1   ",
    "sg:postcode":"18036",
    "sg:province":"PA",
    "wof:name":"Prudential",
    "wof:placetype":"venue"
},
  "geometry": {"coordinates":[-75.38549999999999,40.515956],"type":"Point"}
}