{
  "type": "Feature",
  "properties": {
    "iso:country":"US",
    "sg:address":"1121 Wayfield Dr",
    "sg:city":"Norristown",
    "sg:classifiers":[
        {
            "category":"Professional",
            "subcategory":"Management & Consulting",
            "type":"Services"
        },
        {
            "category":"Professional",
            "subcategory":"Business Services",
            "type":"Services"
        }
    ],
    "sg:phone":"+1 610 666 6075",
    "sg:postcode":"19403",
    "sg:province":"PA",
    "sg:tags":[
        "consultant",
        "coach"
    ],
    "sg:website":"http://www.knarf.de",
    "wof:name":"Knarfs Inc",
    "wof:placetype":"venue"
},
  "geometry": {"coordinates":[-75.415109,40.115727],"type":"Point"}
}