{
  "type": "Feature",
  "properties": {
    "iso:country":"US",
    "sg:address":"237 E Market St",
    "sg:city":"York",
    "sg:classifiers":[
        {
            "category":"Professional",
            "subcategory":"Business Services",
            "type":"Services"
        }
    ],
    "sg:phone":"+1   ",
    "sg:postcode":"17403",
    "sg:province":"PA",
    "sg:tags":[
        "interior",
        "design"
    ],
    "wof:name":"Heritage Intr Design & Dctn",
    "wof:placetype":"venue"
},
  "geometry": {"coordinates":[-76.72248999999999,39.964122],"type":"Point"}
}