{
  "type": "Feature",
  "properties": {
    "iso:country":"US",
    "sg:address":"4493 Ashville Rd",
    "sg:city":"Quarryville",
    "sg:phone":"+1   ",
    "sg:postcode":"17566",
    "sg:province":"PA",
    "sg:tags":[
        "farm",
        "corn"
    ],
    "wof:name":"William Fuller",
    "wof:placetype":"venue"
},
  "geometry": {"coordinates":[-76.113035,39.804829],"type":"Point"}
}