{
  "type": "Feature",
  "properties": {
    "addr:full":"750 E Park Dr Harrisburg PA 17111",
    "addr:housenumber":"750",
    "addr:postcode":"17111",
    "addr:street":"E Park Dr",
    "iso:country":"US",
    "sg:address":"750 E Park Dr",
    "sg:city":"Harrisburg",
    "sg:classifiers":[
        {
            "category":"Education",
            "subcategory":"College",
            "type":"Public Place"
        },
        {
            "category":"Education",
            "subcategory":"School",
            "type":"Public Place"
        }
    ],
    "sg:phone":"+1 717 565 1950",
    "sg:postcode":"17111",
    "sg:province":"PA",
    "sg:tags":[
        "university"
    ],
    "wof:name":"Eastern University",
    "wof:placetype":"venue"
},
  "geometry": {"coordinates":[-76.810104,40.263198],"type":"Point"}
}