{
  "type": "Feature",
  "properties": {
    "addr:full":"14 Dunkin Dr Washington Crossing PA 18977",
    "addr:housenumber":"14",
    "addr:postcode":"18977",
    "addr:street":"Dunkin Dr;Crossing",
    "iso:country":"US",
    "sg:address":"14 Dunkin Dr",
    "sg:city":"Washington Crossing",
    "sg:classifiers":[
        {
            "category":"Real Estate",
            "subcategory":"Developer",
            "type":"Services"
        }
    ],
    "sg:phone":"+1   ",
    "sg:postcode":"18977",
    "sg:province":"PA",
    "wof:name":"Syncro Development Corp",
    "wof:placetype":"venue"
},
  "geometry": {"coordinates":[-74.896531,40.307922],"type":"Point"}
}