{
  "type": "Feature",
  "properties": {
    "addr:full":"1 Dock St Du Bois PA 15801",
    "addr:housenumber":"1",
    "addr:postcode":"15801",
    "addr:street":"Dock St Du Bois",
    "iso:country":"US",
    "sg:address":"1 Dock St",
    "sg:city":"Du Bois",
    "sg:classifiers":[
        {
            "category":"Manufacturing",
            "subcategory":"Tools & Machinery",
            "type":"Manufacturing & Wholesale Goods"
        }
    ],
    "sg:phone":"+1   ",
    "sg:postcode":"15801",
    "sg:province":"PA",
    "sg:tags":[
        "gas",
        "meter",
        "mfg"
    ],
    "wof:name":"Invensys Energy Metering Corp",
    "wof:placetype":"venue"
},
  "geometry": {"coordinates":[-78.769577,41.11504],"type":"Point"}
}