{
  "type": "Feature",
  "properties": {
    "addr:full":"32 Mchugh Ave Punxsutawney PA 15767",
    "addr:housenumber":"32",
    "addr:postcode":"15767",
    "addr:street":"Mchugh Ave",
    "iso:country":"US",
    "sg:address":"32 Mchugh Ave",
    "sg:city":"Punxsutawney",
    "sg:classifiers":[
        {
            "category":"Home & Garden",
            "subcategory":"Building Materials",
            "type":"Retail Goods"
        },
        {
            "category":"Home & Garden",
            "subcategory":"Hardware",
            "type":"Retail Goods"
        }
    ],
    "sg:phone":"+1 814 938 6810",
    "sg:postcode":"15767",
    "sg:province":"PA",
    "sg:tags":[
        "bathroom",
        "accessory",
        "fixtures",
        "store",
        "cabinet"
    ],
    "wof:name":"Blose M & Sons",
    "wof:placetype":"venue"
},
  "geometry": {"coordinates":[-78.98434,40.950431],"type":"Point"}
}