{
  "type": "Feature",
  "properties": {
    "addr:full":"1826 Monongahela Ave Pittsburgh PA 15218",
    "addr:housenumber":"1826",
    "addr:postcode":"15218",
    "addr:street":"Monongahela Ave",
    "iso:country":"US",
    "sg:address":"1826 Monongahela Ave",
    "sg:city":"Pittsburgh",
    "sg:classifiers":[
        {
            "category":"Real Estate",
            "subcategory":"Real Estate Operator",
            "type":"Services"
        }
    ],
    "sg:phone":"+1 412 351 6031",
    "sg:postcode":"15218",
    "sg:province":"PA",
    "sg:tags":[
        "apartment"
    ],
    "wof:name":"Swissvale Towers",
    "wof:placetype":"venue"
},
  "geometry": {"coordinates":[-79.890635,40.422141],"type":"Point"}
}