{
  "type": "Feature",
  "properties": {
    "addr:full":"2113 Twin Bridge Rd Chambersburg PA 17202",
    "addr:housenumber":"2113",
    "addr:postcode":"17202",
    "addr:street":"Twin Bridge Rd",
    "iso:country":"US",
    "sg:address":"2113 Twin Bridge Rd",
    "sg:city":"Chambersburg",
    "sg:classifiers":[
        {
            "category":"Farming",
            "subcategory":"Dairy Farm",
            "type":"Manufacturing & Wholesale Goods"
        }
    ],
    "sg:phone":"+1 717 264 6486",
    "sg:postcode":"17202",
    "sg:province":"PA",
    "wof:name":"Creekside Dairy",
    "wof:placetype":"venue"
},
  "geometry": {"coordinates":[-80.33005199999999,40.106642],"type":"Point"}
}