{
  "type": "Feature",
  "properties": {
    "addr:full":"3222 Henrich Farm Ln Allison Park PA 15101",
    "addr:housenumber":"3222",
    "addr:postcode":"15101",
    "addr:street":"Henrich Farm Ln;Park",
    "iso:country":"US",
    "sg:address":"3222 Henrich Farm Ln",
    "sg:city":"Allison Park",
    "sg:classifiers":[
        {
            "category":"Professional",
            "subcategory":"Management & Consulting",
            "type":"Services"
        }
    ],
    "sg:phone":"+1 412 486 9282",
    "sg:postcode":"15101",
    "sg:province":"PA",
    "sg:tags":[
        "consultant",
        "industrial"
    ],
    "wof:name":"Employee Health Guard",
    "wof:placetype":"venue"
},
  "geometry": {"coordinates":[-79.929052,40.574488],"type":"Point"}
}