{
  "type": "Feature",
  "properties": {
    "addr:full":"822 North Ave Beaver PA 15009",
    "addr:housenumber":"822",
    "addr:postcode":"15009",
    "addr:street":"North Ave",
    "iso:country":"US",
    "sg:address":"822 North Ave",
    "sg:city":"Beaver",
    "sg:classifiers":[
        {
            "category":"Wholesale",
            "subcategory":"Groceries",
            "type":"Manufacturing & Wholesale Goods"
        }
    ],
    "sg:phone":"+1 724 774 2443",
    "sg:postcode":"15009",
    "sg:province":"PA",
    "sg:tags":[
        "pretzel"
    ],
    "wof:name":"Simmons's Food Inc",
    "wof:placetype":"venue"
},
  "geometry": {"coordinates":[-80.31366800000001,40.707094],"type":"Point"}
}