{
  "type": "Feature",
  "properties": {
    "iso:country":"US",
    "sg:address":"129 Long Ave",
    "sg:city":"Orwigsburg",
    "sg:classifiers":[
        {
            "category":"Building & Trades",
            "subcategory":"Construction",
            "type":"Services"
        }
    ],
    "sg:phone":"+1 570 366 2324",
    "sg:postcode":"17961",
    "sg:province":"PA",
    "sg:tags":[
        "roofing",
        "contractor"
    ],
    "wof:name":"D H Moore & Co",
    "wof:placetype":"venue"
},
  "geometry": {"coordinates":[-76.10606799999999,40.65692],"type":"Point"}
}