{
  "type": "Feature",
  "properties": {
    "addr:full":"1301 E Butler Pike Ambler PA 19002",
    "addr:housenumber":"1301",
    "addr:postcode":"19002",
    "addr:street":"E Butler Pike",
    "iso:country":"US",
    "sg:address":"1301 E Butler Pike",
    "sg:city":"Ambler",
    "sg:classifiers":[
        {
            "category":"Professional",
            "subcategory":"Business Services",
            "type":"Services"
        }
    ],
    "sg:phone":"+1   ",
    "sg:postcode":"19002",
    "sg:province":"PA",
    "wof:name":"1821 House Interiors",
    "wof:placetype":"venue"
},
  "geometry": {"coordinates":[-75.205473,40.166057],"type":"Point"}
}