{
  "type": "Feature",
  "properties": {
    "addr:full":"12 Cleveland Ave Narberth PA 19072",
    "addr:housenumber":"12",
    "addr:postcode":"19072",
    "addr:street":"Cleveland Ave",
    "iso:country":"US",
    "sg:address":"12 Cleveland Ave",
    "sg:city":"Narberth",
    "sg:classifiers":[
        {
            "category":"Professional",
            "subcategory":"Advertising",
            "type":"Services"
        }
    ],
    "sg:phone":"+1 610 617 7360",
    "sg:postcode":"19072",
    "sg:province":"PA",
    "sg:tags":[
        "guide"
    ],
    "wof:name":"ACT Co",
    "wof:placetype":"venue"
},
  "geometry": {"coordinates":[-75.25736499999999,40.012845],"type":"Point"}
}