{
  "type": "Feature",
  "properties": {
    "addr:full":"154 Fairview Ave Quakertown PA 18951",
    "addr:housenumber":"154",
    "addr:postcode":"18951",
    "addr:street":"Fairview Ave",
    "iso:country":"US",
    "sg:address":"154 Fairview Ave",
    "sg:city":"Quakertown",
    "sg:classifiers":[
        {
            "category":"Wholesale",
            "subcategory":"Non-durable Goods",
            "type":"Manufacturing & Wholesale Goods"
        }
    ],
    "sg:phone":"+1 215 249 3333",
    "sg:postcode":"18951",
    "sg:province":"PA",
    "sg:tags":[
        "canvas"
    ],
    "wof:name":"Canvas Shack",
    "wof:placetype":"venue"
},
  "geometry": {"coordinates":[-75.329998,40.436565],"type":"Point"}
}