{
  "type": "Feature",
  "properties": {
    "iso:country":"US",
    "sg:address":"330 Main St",
    "sg:city":"Leechburg",
    "sg:classifiers":[
        {
            "category":"Government",
            "subcategory":"Office",
            "type":"Public Place"
        }
    ],
    "sg:phone":"+1 724 845 6386",
    "sg:postcode":"15656",
    "sg:province":"PA",
    "wof:name":"Friendship Apartments",
    "wof:placetype":"venue"
},
  "geometry": {"coordinates":[-79.602763,40.626742],"type":"Point"}
}