{
  "type": "Feature",
  "properties": {
    "iso:country":"US",
    "sg:address":"434 Market St Ste 300",
    "sg:city":"Lewisburg",
    "sg:classifiers":[
        {
            "category":"Home & Garden",
            "subcategory":"Carpets & Floor Coverings",
            "type":"Retail Goods"
        }
    ],
    "sg:phone":"+1 570 522 7444",
    "sg:postcode":"17837",
    "sg:province":"PA",
    "sg:tags":[
        "material"
    ],
    "wof:name":"Top Floor Studio",
    "wof:placetype":"venue"
},
  "geometry": {"coordinates":[-76.886352,40.963556],"type":"Point"}
}