{
  "type": "Feature",
  "properties": {
    "addr:full":"1300 Hartranft Ave Fort Washington PA 19034",
    "addr:housenumber":"1300",
    "addr:postcode":"19034",
    "addr:street":"Hartranft Ave",
    "iso:country":"US",
    "sg:address":"1300 Hartranft Ave",
    "sg:city":"Fort Washington",
    "sg:classifiers":[
        {
            "category":"Building & Trades",
            "subcategory":"Construction",
            "type":"Services"
        }
    ],
    "sg:phone":"+1 215 646 9630",
    "sg:postcode":"19034",
    "sg:province":"PA",
    "sg:tags":[
        "contractor"
    ],
    "wof:name":"Brier Inc",
    "wof:placetype":"venue"
},
  "geometry": {"coordinates":[-75.199217,40.142555],"type":"Point"}
}