{
  "type": "Feature",
  "properties": {
    "iso:country":"US",
    "sg:address":"1285 Stonegate Cir",
    "sg:city":"Lansdale",
    "sg:classifiers":[
        {
            "category":"Food & Beverages",
            "subcategory":"Groceries & Convenience Stores",
            "type":"Retail Goods"
        }
    ],
    "sg:phone":"+1   ",
    "sg:postcode":"19446",
    "sg:province":"PA",
    "wof:name":"Quick Mart",
    "wof:placetype":"venue"
},
  "geometry": {"coordinates":[-75.301905,40.230993],"type":"Point"}
}