{
  "type": "Feature",
  "properties": {
    "addr:full":"3273 Ventoura Dr Erie PA 16510",
    "addr:housenumber":"3273",
    "addr:postcode":"16510",
    "addr:street":"Ventoura Dr",
    "iso:country":"US",
    "sg:address":"3273 Ventoura Dr",
    "sg:city":"Erie",
    "sg:classifiers":[
        {
            "category":"Real Estate",
            "subcategory":"Developer",
            "type":"Services"
        }
    ],
    "sg:phone":"+1 814 899 6761",
    "sg:postcode":"16510",
    "sg:province":"PA",
    "sg:tags":[
        "mobile",
        "home"
    ],
    "wof:name":"Wesleyville Mobile Home Park",
    "wof:placetype":"venue"
},
  "geometry": {"coordinates":[-80.015643,42.142174],"type":"Point"}
}