{
  "type": "Feature",
  "properties": {
    "iso:country":"US",
    "sg:address":"537 W 18th St",
    "sg:city":"Erie",
    "sg:classifiers":[
        {
            "category":"Health Services",
            "subcategory":"Doctor",
            "type":"Services"
        }
    ],
    "sg:phone":"+1 814 456 1009",
    "sg:postcode":"16502",
    "sg:province":"PA",
    "sg:tags":[
        "physician",
        "surgeon"
    ],
    "wof:name":"Plaza 18 Medical Ctr",
    "wof:placetype":"venue"
},
  "geometry": {"coordinates":[-80.09031899999999,42.113876],"type":"Point"}
}