{
  "type": "Feature",
  "properties": {
    "iso:country":"US",
    "sg:address":"900 Mancill Mill Rd",
    "sg:city":"King Of Prussia",
    "sg:classifiers":[
        {
            "category":"Government",
            "subcategory":"Office",
            "type":"Public Place"
        }
    ],
    "sg:phone":"+1 610 783 0848",
    "sg:postcode":"19406",
    "sg:province":"PA",
    "sg:tags":[
        "management"
    ],
    "wof:name":"Upper Merion Wastewater Plants",
    "wof:placetype":"venue"
},
  "geometry": {"coordinates":[-75.409767,40.106163],"type":"Point"}
}