{
  "type": "Feature",
  "properties": {
    "addr:full":"56 Ash Cir Warminster PA 18974",
    "addr:housenumber":"56",
    "addr:postcode":"18974",
    "addr:street":"Ash Cir",
    "iso:country":"US",
    "sg:address":"56 Ash Cir",
    "sg:city":"Warminster",
    "sg:classifiers":[
        {
            "category":"Home & Garden",
            "subcategory":"Building Materials",
            "type":"Retail Goods"
        }
    ],
    "sg:phone":"+1 215 672 5700",
    "sg:postcode":"18974",
    "sg:province":"PA",
    "sg:tags":[
        "siding"
    ],
    "wof:name":"Alside Supply Ctr",
    "wof:placetype":"venue"
},
  "geometry": {"coordinates":[-75.09293,40.189544],"type":"Point"}
}