{
  "type": "Feature",
  "properties": {
    "iso:country":"US",
    "sg:address":"2163 N 4th St",
    "sg:city":"Harrisburg",
    "sg:classifiers":[
        {
            "category":"Food & Beverages",
            "subcategory":"Groceries & Convenience Stores",
            "type":"Retail Goods"
        }
    ],
    "sg:phone":"+1   ",
    "sg:postcode":"17110",
    "sg:province":"PA",
    "wof:name":"My Store",
    "wof:placetype":"venue"
},
  "geometry": {"coordinates":[-76.894305,40.280123],"type":"Point"}
}