{
  "type": "Feature",
  "properties": {
    "iso:country":"US",
    "sg:address":"330 Scott St",
    "sg:city":"Wilkes Barre",
    "sg:classifiers":[
        {
            "category":"Home & Garden",
            "subcategory":"Furniture",
            "type":"Retail Goods"
        }
    ],
    "sg:phone":"+1 570 822 4093",
    "sg:postcode":"18702",
    "sg:province":"PA",
    "sg:tags":[
        "builder",
        "custom"
    ],
    "wof:name":"Granpa's Workshop",
    "wof:placetype":"venue"
},
  "geometry": {"coordinates":[-75.860343,41.247842],"type":"Point"}
}