{
  "type": "Feature",
  "properties": {
    "iso:country":"US",
    "sg:address":"105 River Rd",
    "sg:city":"Mc Kees Rocks",
    "sg:classifiers":[
        {
            "category":"Building & Trades",
            "subcategory":"Construction",
            "type":"Services"
        }
    ],
    "sg:phone":"+1   ",
    "sg:postcode":"15136",
    "sg:province":"PA",
    "sg:tags":[
        "home",
        "general",
        "contractor"
    ],
    "wof:name":"J D Gales Contracting",
    "wof:placetype":"venue"
},
  "geometry": {"coordinates":[-80.061453,40.483809],"type":"Point"}
}