{
  "type": "Feature",
  "properties": {
    "iso:country":"US",
    "sg:address":"2710 Penn Ave",
    "sg:city":"Pittsburgh",
    "sg:classifiers":[
        {
            "category":"Professional",
            "subcategory":"Business Services",
            "type":"Services"
        }
    ],
    "sg:phone":"+1 412 281 3377",
    "sg:postcode":"15222",
    "sg:province":"PA",
    "sg:tags":[
        "appraiser"
    ],
    "wof:name":"Steel City Appraisals",
    "wof:placetype":"venue"
},
  "geometry": {"coordinates":[-79.975673,40.456703],"type":"Point"}
}