{
  "type": "Feature",
  "properties": {
    "iso:country":"US",
    "sg:address":"3434 Garrett Rd",
    "sg:city":"Drexel Hill",
    "sg:classifiers":[
        {
            "category":"Health Services",
            "subcategory":"Chiropractor",
            "type":"Services"
        }
    ],
    "sg:phone":"+1 610 622 7140",
    "sg:postcode":"19026",
    "sg:province":"PA",
    "wof:name":"Pandolso Chiropractic",
    "wof:placetype":"venue"
},
  "geometry": {"coordinates":[-75.29389500000001,39.945795],"type":"Point"}
}