{
  "type": "Feature",
  "properties": {
    "addr:full":"926 Shoemaker Ave Wyoming PA 18644",
    "addr:housenumber":"926",
    "addr:postcode":"18644",
    "addr:street":"Shoemaker Ave",
    "iso:country":"US",
    "sg:address":"926 Shoemaker Ave",
    "sg:city":"Wyoming",
    "sg:classifiers":[
        {
            "category":"Government",
            "subcategory":"Office",
            "type":"Public Place"
        },
        {
            "category":"Government",
            "subcategory":"Fire Station",
            "type":"Public Place"
        }
    ],
    "sg:phone":"+1 570 693 1811",
    "sg:postcode":"18644",
    "sg:province":"PA",
    "sg:tags":[
        "protection",
        "village"
    ],
    "wof:name":"West Wyoming Hose Company",
    "wof:placetype":"venue"
},
  "geometry": {"coordinates":[-75.850274,41.317223],"type":"Point"}
}