{
  "type": "Feature",
  "properties": {
    "addr:full":"4912 N 5th St Philadelphia PA 19120",
    "addr:housenumber":"4912",
    "addr:postcode":"19120",
    "addr:street":"N 5Th St",
    "iso:country":"US",
    "sg:address":"4912 N 5th St",
    "sg:city":"Philadelphia",
    "sg:classifiers":[
        {
            "category":"Fast Food",
            "type":"Food & Drink"
        },
        {
            "category":"Restaurant",
            "type":"Food & Drink"
        }
    ],
    "sg:phone":"+1 215 324 7427",
    "sg:postcode":"19120",
    "sg:province":"PA",
    "sg:tags":[
        "house",
        "steakhouse",
        "take",
        "barbecue",
        "steak"
    ],
    "wof:name":"Ribs-R-US",
    "wof:placetype":"venue"
},
  "geometry": {"coordinates":[-75.132946,40.026],"type":"Point"}
}