{
  "type": "Feature",
  "properties": {
    "addr:full":"671 Noble Dr West Mifflin PA 15122",
    "addr:housenumber":"671",
    "addr:postcode":"15122",
    "addr:street":"Noble Dr",
    "iso:country":"US",
    "sg:address":"671 Noble Dr",
    "sg:city":"West Mifflin",
    "sg:classifiers":[
        {
            "category":"Professional",
            "subcategory":"Computer Services",
            "type":"Services"
        }
    ],
    "sg:phone":"+1 412 462 2800",
    "sg:postcode":"15122",
    "sg:province":"PA",
    "sg:tags":[
        "internet"
    ],
    "wof:name":"Libcom Internet Svc Inc",
    "wof:placetype":"venue"
},
  "geometry": {"coordinates":[-79.931727,40.362083],"type":"Point"}
}