{
  "type": "Feature",
  "properties": {
    "iso:country":"US",
    "sg:address":"6 Creekside Dr",
    "sg:city":"Warminster",
    "sg:classifiers":[
        {
            "category":"Building & Trades",
            "subcategory":"Landscaping Services",
            "type":"Services"
        }
    ],
    "sg:phone":"+1   ",
    "sg:postcode":"18974",
    "sg:province":"PA",
    "wof:name":"Hollyberry Inc",
    "wof:placetype":"venue"
},
  "geometry": {"coordinates":[-75.038005,40.222485],"type":"Point"}
}