{
  "type": "Feature",
  "properties": {
    "iso:country":"US",
    "sg:address":"42 N 3rd St",
    "sg:city":"Easton",
    "sg:classifiers":[
        {
            "category":"Health Services",
            "subcategory":"Podiatrist",
            "type":"Services"
        }
    ],
    "sg:phone":"+1   ",
    "sg:postcode":"18042",
    "sg:province":"PA",
    "wof:name":"Lee N Orowitz DPM",
    "wof:placetype":"venue"
},
  "geometry": {"coordinates":[-75.20933100000001,40.692826],"type":"Point"}
}