{
  "type": "Feature",
  "properties": {
    "iso:country":"US",
    "sg:address":"1345 Fairview Ln",
    "sg:city":"Lebanon",
    "sg:classifiers":[
        {
            "category":"Health Services",
            "subcategory":"Clinic",
            "type":"Services"
        }
    ],
    "sg:phone":"+1 717 274 8328",
    "sg:postcode":"17042",
    "sg:province":"PA",
    "sg:tags":[
        "information",
        "alcoholism",
        "treatment"
    ],
    "wof:name":"Assiel Therapy",
    "wof:placetype":"venue"
},
  "geometry": {"coordinates":[-76.384578,40.340998],"type":"Point"}
}