{
  "type": "Feature",
  "properties": {
    "iso:country":"US",
    "sg:address":"112 Brimmer Ave",
    "sg:city":"New Holland",
    "sg:classifiers":[
        {
            "category":"Home & Garden",
            "subcategory":"Building Materials",
            "type":"Retail Goods"
        }
    ],
    "sg:phone":"+1 717 354 2963",
    "sg:postcode":"17557",
    "sg:province":"PA",
    "wof:name":"Lucky Paint Store",
    "wof:placetype":"venue"
},
  "geometry": {"coordinates":[-76.083619,40.10274],"type":"Point"}
}