{
  "type": "Feature",
  "properties": {
    "iso:country":"US",
    "sg:address":"713 Bethlehem Pike",
    "sg:city":"Flourtown",
    "sg:classifiers":[
        {
            "category":"Real Estate",
            "subcategory":"Real Estate Operator",
            "type":"Services"
        }
    ],
    "sg:phone":"+1   ",
    "sg:postcode":"19031",
    "sg:province":"PA",
    "sg:tags":[
        "residential",
        "manages",
        "commercial",
        "owns"
    ],
    "wof:name":"Bushu Associates Inc",
    "wof:placetype":"venue"
},
  "geometry": {"coordinates":[-75.214696,40.115086],"type":"Point"}
}