{
  "type": "Feature",
  "properties": {
    "addr:full":"422 E Lexington Rd Lititz PA 17543",
    "addr:housenumber":"422",
    "addr:postcode":"17543",
    "addr:street":"E Lexington Rd",
    "iso:country":"US",
    "sg:address":"422 E Lexington Rd",
    "sg:city":"Lititz",
    "sg:classifiers":[
        {
            "category":"Freight",
            "type":"Transportation"
        }
    ],
    "sg:phone":"+1   ",
    "sg:postcode":"17543",
    "sg:province":"PA",
    "sg:tags":[
        "operator",
        "local",
        "trucking"
    ],
    "wof:name":"Daryl Kreider",
    "wof:placetype":"venue"
},
  "geometry": {"coordinates":[-76.28921200000001,40.187455],"type":"Point"}
}