{
  "type": "Feature",
  "properties": {
    "iso:country":"US",
    "sg:address":"2110 Sturbridge Cmn",
    "sg:city":"Southampton",
    "sg:classifiers":[
        {
            "category":"Wholesale",
            "subcategory":"Construction Materials",
            "type":"Manufacturing & Wholesale Goods"
        }
    ],
    "sg:phone":"+1   ",
    "sg:postcode":"18966",
    "sg:province":"PA",
    "sg:tags":[
        "lumber",
        "plywood"
    ],
    "wof:name":"Artistic Kitchen and Bathrooms",
    "wof:placetype":"venue"
},
  "geometry": {"coordinates":[-74.945201,40.209489],"type":"Point"}
}