{
  "type": "Feature",
  "properties": {
    "addr:full":"2308 W Oregon Ave Ste D Philadelphia PA 19145",
    "addr:housenumber":"2308",
    "addr:postcode":"19145",
    "addr:street":"W Oregon Ave Ste D",
    "iso:country":"US",
    "sg:address":"2308 W Oregon Ave Ste D",
    "sg:city":"Philadelphia",
    "sg:classifiers":[
        {
            "category":"Shopping",
            "subcategory":"Shoes",
            "type":"Retail Goods"
        }
    ],
    "sg:phone":"+1 215 463 4523",
    "sg:postcode":"19145",
    "sg:province":"PA",
    "sg:tags":[
        "store"
    ],
    "sg:website":"www.footlocker.com",
    "wof:name":"Foot Locker",
    "wof:placetype":"venue"
},
  "geometry": {"coordinates":[-75.186317,39.918557],"type":"Point"}
}