{
  "type": "Feature",
  "properties": {
    "iso:country":"US",
    "sg:address":"110 E Butler Ave",
    "sg:city":"Ambler",
    "sg:classifiers":[
        {
            "category":"Restaurant",
            "type":"Food & Drink"
        }
    ],
    "sg:phone":"+1 215 619 4550",
    "sg:postcode":"19002",
    "sg:province":"PA",
    "sg:tags":[
        "eating"
    ],
    "wof:name":"Jimmy Rubino Ralphs",
    "wof:placetype":"venue"
},
  "geometry": {"coordinates":[-75.221048,40.154814],"type":"Point"}
}