{
  "type": "Feature",
  "properties": {
    "iso:country":"US",
    "sg:address":"55 Pierce Ln",
    "sg:city":"Montoursville",
    "sg:classifiers":[
        {
            "category":"Professional",
            "subcategory":"Employment Agencies",
            "type":"Services"
        }
    ],
    "sg:phone":"+1 570 368 2277",
    "sg:postcode":"17754",
    "sg:province":"PA",
    "sg:tags":[
        "opportunity"
    ],
    "wof:name":"Management Recruiters",
    "wof:placetype":"venue"
},
  "geometry": {"coordinates":[-76.893996,41.246218],"type":"Point"}
}