{
  "type": "Feature",
  "properties": {
    "addr:full":"332 Mc Cully St Pittsburgh PA 15216",
    "addr:housenumber":"332",
    "addr:postcode":"15216",
    "addr:street":"Mc Cully St",
    "iso:country":"US",
    "sg:address":"332 Mc Cully St",
    "sg:city":"Pittsburgh",
    "sg:classifiers":[
        {
            "category":"Wholesale",
            "subcategory":"Groceries",
            "type":"Manufacturing & Wholesale Goods"
        }
    ],
    "sg:phone":"+1   ",
    "sg:postcode":"15216",
    "sg:province":"PA",
    "wof:name":"Snapple Beverage Group Inc",
    "wof:placetype":"venue"
},
  "geometry": {"coordinates":[-80.04964699999999,40.386861],"type":"Point"}
}