{
  "type": "Feature",
  "properties": {
    "iso:country":"US",
    "sg:address":"24 Coulter Ave",
    "sg:city":"Ardmore",
    "sg:classifiers":[
        {
            "category":"Shopping",
            "subcategory":"Clothing, Apparel, & Fashions",
            "type":"Retail Goods"
        }
    ],
    "sg:phone":"+1 610 896 0550",
    "sg:postcode":"19003",
    "sg:province":"PA",
    "wof:name":"Asta De Blue",
    "wof:placetype":"venue"
},
  "geometry": {"coordinates":[-75.290216,40.008832],"type":"Point"}
}