{
  "type": "Feature",
  "properties": {
    "addr:full":"455 Dunksferry Rd Bensalem PA 19020",
    "addr:housenumber":"455",
    "addr:postcode":"19020",
    "addr:street":"Dunksferry Rd",
    "iso:country":"US",
    "sg:address":"455 Dunksferry Rd",
    "sg:city":"Bensalem",
    "sg:classifiers":[
        {
            "category":"Wholesale",
            "subcategory":"Stationery",
            "type":"Manufacturing & Wholesale Goods"
        }
    ],
    "sg:phone":"+1   ",
    "sg:postcode":"19020",
    "sg:province":"PA",
    "sg:tags":[
        "pap",
        "paper"
    ],
    "wof:name":"International Paper",
    "wof:placetype":"venue"
},
  "geometry": {"coordinates":[-74.92399899999999,40.078695],"type":"Point"}
}