{
  "type": "Feature",
  "properties": {
    "iso:country":"US",
    "sg:address":"618 E Main St",
    "sg:city":"Lansdale",
    "sg:classifiers":[
        {
            "category":"Wholesale",
            "subcategory":"Medical Equipment & Supplies",
            "type":"Manufacturing & Wholesale Goods"
        }
    ],
    "sg:phone":"+1 215 412 9991",
    "sg:postcode":"19446",
    "sg:province":"PA",
    "sg:tags":[
        "physician",
        "surgeon"
    ],
    "wof:name":"RHCLLC",
    "wof:placetype":"venue"
},
  "geometry": {"coordinates":[-75.26988900000001,40.233273],"type":"Point"}
}