{
  "type": "Feature",
  "properties": {
    "iso:country":"US",
    "sg:address":"1 Campus Ave",
    "sg:city":"Spring Grove",
    "sg:classifiers":[
        {
            "category":"Government",
            "subcategory":"Office",
            "type":"Public Place"
        }
    ],
    "sg:phone":"+1 717 225 5791",
    "sg:postcode":"17362",
    "sg:province":"PA",
    "sg:tags":[
        "executive",
        "association",
        "village"
    ],
    "wof:name":"Spring Grove Borough Office",
    "wof:placetype":"venue"
},
  "geometry": {"coordinates":[-76.86689699999999,39.883379],"type":"Point"}
}