{
  "type": "Feature",
  "properties": {
    "iso:country":"US",
    "sg:address":"387 Mountain View Rd",
    "sg:city":"Reading",
    "sg:classifiers":[
        {
            "category":"Autos & Motor Vehicles",
            "subcategory":"Automobile Sales",
            "type":"Retail Goods"
        }
    ],
    "sg:phone":"+1   ",
    "sg:postcode":"19607",
    "sg:province":"PA",
    "sg:tags":[
        "used"
    ],
    "wof:name":"Anthonys Automotive",
    "wof:placetype":"venue"
},
  "geometry": {"coordinates":[-75.933543,40.304727],"type":"Point"}
}