{
  "type": "Feature",
  "properties": {
    "iso:country":"US",
    "sg:address":"513 Schoonmaker Ave",
    "sg:city":"Monessen",
    "sg:classifiers":[
        {
            "category":"Professional",
            "subcategory":"Lawyer & Legal Services",
            "type":"Services"
        }
    ],
    "sg:phone":"+1 724 684 6400",
    "sg:postcode":"15062",
    "sg:province":"PA",
    "wof:name":"Gaudio Albert C Attorney",
    "wof:placetype":"venue"
},
  "geometry": {"coordinates":[-79.8862,40.160999],"type":"Point"}
}