{
  "type": "Feature",
  "properties": {
    "iso:country":"US",
    "sg:address":"2835 W Chester Pike",
    "sg:city":"Broomall",
    "sg:classifiers":[
        {
            "category":"Professional",
            "subcategory":"Accounting & Tax Preparation",
            "type":"Services"
        }
    ],
    "sg:phone":"+1 610 356 5800",
    "sg:postcode":"19008",
    "sg:province":"PA",
    "sg:tags":[
        "accountant"
    ],
    "wof:name":"Doyle & Mcdonnell PC CPA",
    "wof:placetype":"venue"
},
  "geometry": {"coordinates":[-75.367548,39.98269],"type":"Point"}
}