{
  "type": "Feature",
  "properties": {
    "iso:country":"US",
    "sg:address":"337 W Girard Ave",
    "sg:city":"Philadelphia",
    "sg:classifiers":[
        {
            "category":"Personal",
            "subcategory":"Beauty Salon",
            "type":"Services"
        }
    ],
    "sg:phone":"+1 215 235 8344",
    "sg:postcode":"19123",
    "sg:province":"PA",
    "wof:name":"Anta Africian Hair Braiding",
    "wof:placetype":"venue"
},
  "geometry": {"coordinates":[-75.14176999999999,39.969843],"type":"Point"}
}