{
  "type": "Feature",
  "properties": {
    "iso:country":"US",
    "sg:address":"901 S 16th St",
    "sg:city":"Harrisburg",
    "sg:classifiers":[
        {
            "category":"Retail",
            "subcategory":"Auto Rental",
            "type":"Services"
        }
    ],
    "sg:phone":"+1 717 234 8500",
    "sg:postcode":"17104",
    "sg:province":"PA",
    "sg:tags":[
        "car"
    ],
    "wof:name":"All In the Family Used Auto Sales",
    "wof:placetype":"venue"
},
  "geometry": {"coordinates":[-76.86019899999999,40.254398],"type":"Point"}
}