{
  "type": "Feature",
  "properties": {
    "iso:country":"US",
    "sg:address":"120 Fayetteville Rd",
    "sg:city":"Oakdale",
    "sg:classifiers":[
        {
            "category":"Retail",
            "subcategory":"Repair Shop",
            "type":"Services"
        }
    ],
    "sg:phone":"+1 412 788 4075",
    "sg:postcode":"15071",
    "sg:province":"PA",
    "sg:tags":[
        "repairing",
        "lawn",
        "mower"
    ],
    "wof:name":"Bob's Mower Repair",
    "wof:placetype":"venue"
},
  "geometry": {"coordinates":[-80.214153,40.438535],"type":"Point"}
}