{
  "type": "Feature",
  "properties": {
    "addr:full":"415 Springville Rd Quarryville PA 17566",
    "addr:housenumber":"415",
    "addr:postcode":"17566",
    "addr:street":"Springville Rd",
    "iso:country":"US",
    "sg:address":"415 Springville Rd",
    "sg:city":"Quarryville",
    "sg:classifiers":[
        {
            "category":"Farming",
            "subcategory":"Poultry Farm",
            "type":"Manufacturing & Wholesale Goods"
        }
    ],
    "sg:phone":"+1   ",
    "sg:postcode":"17566",
    "sg:province":"PA",
    "sg:tags":[
        "chicken"
    ],
    "wof:name":"Robert Landis",
    "wof:placetype":"venue"
},
  "geometry": {"coordinates":[-76.115027,39.938683],"type":"Point"}
}