{
  "type": "Feature",
  "properties": {
    "iso:country":"US",
    "sg:address":"1405 S 58th St",
    "sg:city":"Philadelphia",
    "sg:classifiers":[
        {
            "category":"Utilities",
            "subcategory":"Fuel Oil & Lpg",
            "type":"Services"
        }
    ],
    "sg:phone":"+1 215 921 2078",
    "sg:postcode":"19143",
    "sg:province":"PA",
    "sg:tags":[
        "oils-fuel",
        "burner"
    ],
    "wof:name":"Mamas Boy Heating Oil",
    "wof:placetype":"venue"
},
  "geometry": {"coordinates":[-75.23484500000001,39.941344],"type":"Point"}
}