{
  "type": "Feature",
  "properties": {
    "addr:full":"760 Woodbourne Rd Langhorne PA 19047",
    "addr:housenumber":"760",
    "addr:postcode":"19047",
    "addr:street":"Woodbourne Rd",
    "iso:country":"US",
    "sg:address":"760 Woodbourne Rd",
    "sg:city":"Langhorne",
    "sg:classifiers":[
        {
            "category":"Wholesale",
            "subcategory":"Non-durable Goods",
            "type":"Manufacturing & Wholesale Goods"
        }
    ],
    "sg:phone":"+1 215 757 8788",
    "sg:postcode":"19047",
    "sg:province":"PA",
    "sg:tags":[
        "advertising",
        "specialty"
    ],
    "sg:website":"www.jetspec.com",
    "wof:name":"Jet Specialties Company",
    "wof:placetype":"venue"
},
  "geometry": {"coordinates":[-74.890112,40.19021],"type":"Point"}
}