{
  "type": "Feature",
  "properties": {
    "iso:country":"US",
    "sg:address":"200 Cedarbrook Rd",
    "sg:city":"Ardmore",
    "sg:classifiers":[
        {
            "category":"Organizations",
            "subcategory":"Community Association",
            "type":"Services"
        }
    ],
    "sg:phone":"+1   ",
    "sg:postcode":"19003",
    "sg:province":"PA",
    "wof:name":"PHI Sigma Kappa",
    "wof:placetype":"venue"
},
  "geometry": {"coordinates":[-75.30930499999999,39.99544],"type":"Point"}
}