{
  "type": "Feature",
  "properties": {
    "addr:full":"327 Woodlawn Ave Bethlehem PA 18018",
    "addr:housenumber":"327",
    "addr:postcode":"18018",
    "addr:street":"Woodlawn Ave",
    "iso:country":"US",
    "sg:address":"327 Woodlawn Ave",
    "sg:city":"Bethlehem",
    "sg:classifiers":[
        {
            "category":"Shopping",
            "subcategory":"Pharmacy",
            "type":"Retail Goods"
        }
    ],
    "sg:phone":"+1 610 691 4463",
    "sg:postcode":"18018",
    "sg:province":"PA",
    "wof:name":"CVS Pharmacy",
    "wof:placetype":"venue"
},
  "geometry": {"coordinates":[-75.36802,40.633373],"type":"Point"}
}