{
  "type": "Feature",
  "properties": {
    "iso:country":"US",
    "sg:address":"206 Main St",
    "sg:city":"Imperial",
    "sg:classifiers":[
        {
            "category":"Real Estate",
            "subcategory":"Real Estate Agent",
            "type":"Services"
        }
    ],
    "sg:phone":"+1 724 695 8600",
    "sg:postcode":"15126",
    "sg:province":"PA",
    "sg:tags":[
        "appraiser"
    ],
    "wof:name":"Apex Appraisal Svc",
    "wof:placetype":"venue"
},
  "geometry": {"coordinates":[-80.248194,40.450138],"type":"Point"}
}