{
  "type": "Feature",
  "properties": {
    "iso:country":"US",
    "sg:address":"2702 Zuck Rd",
    "sg:city":"Erie",
    "sg:classifiers":[
        {
            "category":"Health Services",
            "subcategory":"Doctor",
            "type":"Services"
        }
    ],
    "sg:phone":"+1 814 833 3535",
    "sg:postcode":"16506",
    "sg:province":"PA",
    "sg:tags":[
        "dentist"
    ],
    "wof:name":"Comprehensive Family Dentistry",
    "wof:placetype":"venue"
},
  "geometry": {"coordinates":[-80.131254,42.088492],"type":"Point"}
}