{
  "type": "Feature",
  "properties": {
    "iso:country":"US",
    "sg:address":"1200 McKean Ave",
    "sg:city":"Charleroi",
    "sg:classifiers":[
        {
            "category":"Health Services",
            "subcategory":"Health Practitioner",
            "type":"Services"
        }
    ],
    "sg:phone":"+1   ",
    "sg:postcode":"15022",
    "sg:province":"PA",
    "wof:name":"Novacare Otptent Rhabilitation",
    "wof:placetype":"venue"
},
  "geometry": {"coordinates":[-79.904917,40.145163],"type":"Point"}
}