{
  "type": "Feature",
  "properties": {
    "iso:country":"US",
    "sg:address":"699 W Rosedale Ave",
    "sg:city":"West Chester",
    "sg:classifiers":[
        {
            "category":"Travel",
            "subcategory":"Hotels & Motels",
            "type":"Entertainment"
        },
        {
            "category":"Travel",
            "subcategory":"Bed & Breakfast",
            "type":"Entertainment"
        }
    ],
    "sg:phone":"+1 610 436 5788",
    "sg:postcode":"19382",
    "sg:province":"PA",
    "wof:name":"Faunbrook Bed & Breakfast",
    "wof:placetype":"venue"
},
  "geometry": {"coordinates":[-75.607101,39.9454],"type":"Point"}
}