{
  "type": "Feature",
  "properties": {
    "iso:country":"US",
    "sg:address":"911 W Chester Rd",
    "sg:city":"West Chester",
    "sg:classifiers":[
        {
            "category":"Building & Trades",
            "subcategory":"Construction",
            "type":"Services"
        }
    ],
    "sg:phone":"+1 610 429 5859",
    "sg:postcode":"19382",
    "sg:province":"PA",
    "sg:tags":[
        "contractor"
    ],
    "wof:name":"Scovi Contracting LLC",
    "wof:placetype":"venue"
},
  "geometry": {"coordinates":[-75.54597,39.911069],"type":"Point"}
}