{
  "type": "Feature",
  "properties": {
    "addr:full":"1535 Pratt St Philadelphia PA 19124",
    "addr:housenumber":"1535",
    "addr:postcode":"19124",
    "addr:street":"Pratt St",
    "iso:country":"US",
    "sg:address":"1535 Pratt St",
    "sg:city":"Philadelphia",
    "sg:classifiers":[
        {
            "category":"Banks & Credit Unions",
            "subcategory":"Bank",
            "type":"Services"
        }
    ],
    "sg:phone":"+1   ",
    "sg:postcode":"19124",
    "sg:province":"PA",
    "sg:tags":[
        "depository",
        "banking"
    ],
    "wof:name":"A & W Cut Rate",
    "wof:placetype":"venue"
},
  "geometry": {"coordinates":[-75.07818399999999,40.022476],"type":"Point"}
}