{
  "type": "Feature",
  "properties": {
    "addr:full":"1617 Cascade St Erie PA 16502",
    "addr:housenumber":"1617",
    "addr:postcode":"16502",
    "addr:street":"Cascade St",
    "iso:country":"US",
    "sg:address":"1617 Cascade St",
    "sg:city":"Erie",
    "sg:classifiers":[
        {
            "category":"Wholesale",
            "subcategory":"Computers",
            "type":"Manufacturing & Wholesale Goods"
        },
        {
            "category":"Shopping",
            "subcategory":"Computers & Home Electronics",
            "type":"Retail Goods"
        }
    ],
    "sg:phone":"+1 814 459 1030",
    "sg:postcode":"16502",
    "sg:province":"PA",
    "sg:tags":[
        "equipment",
        "dealer",
        "repair"
    ],
    "wof:name":"North East Micro",
    "wof:placetype":"venue"
},
  "geometry": {"coordinates":[-80.099227,42.111827],"type":"Point"}
}