{
  "type": "Feature",
  "properties": {
    "iso:country":"US",
    "sg:address":"119 Maurus St",
    "sg:city":"St Marys",
    "sg:classifiers":[
        {
            "category":"Wholesale",
            "subcategory":"Durable Goods & Equipment",
            "type":"Manufacturing & Wholesale Goods"
        }
    ],
    "sg:phone":"+1 814 834 6401",
    "sg:postcode":"15857",
    "sg:province":"PA",
    "sg:tags":[
        "fire",
        "extinguisher"
    ],
    "wof:name":"General Fire Protection Sales",
    "wof:placetype":"venue"
},
  "geometry": {"coordinates":[-78.562974,41.429512],"type":"Point"}
}