{
  "type": "Feature",
  "properties": {
    "iso:country":"US",
    "sg:address":"4100 W Lincoln Hwy ",
    "sg:city":"Downingtown",
    "sg:classifiers":[
        {
            "category":"Restaurant",
            "type":"Food & Drink"
        }
    ],
    "sg:menulink":"http://www.allmenus.com/pa/caln/289582-coppa-82/menu/",
    "sg:phone":"+1 610 873 1060",
    "sg:postcode":"19335",
    "sg:province":"PA",
    "sg:tags":[
        "italian"
    ],
    "wof:name":"Coppa 82",
    "wof:placetype":"venue"
},
  "geometry": {"coordinates":[-75.738989,39.997012],"type":"Point"}
}