{
  "type": "Feature",
  "properties": {
    "iso:country":"US",
    "sg:address":"848 Stambaugh Ave",
    "sg:city":"Sharon",
    "sg:classifiers":[
        {
            "category":"Social Services",
            "subcategory":"Child Care",
            "type":"Services"
        }
    ],
    "sg:phone":"+1   ",
    "sg:postcode":"16146",
    "sg:province":"PA",
    "sg:tags":[
        "day"
    ],
    "wof:name":"Little Dreams Daycare",
    "wof:placetype":"venue"
},
  "geometry": {"coordinates":[-80.493449,41.222615],"type":"Point"}
}