{
  "type": "Feature",
  "properties": {
    "iso:country":"US",
    "sg:address":"169 Chile Rd",
    "sg:city":"Bedford",
    "sg:classifiers":[
        {
            "category":"Building & Trades",
            "subcategory":"Plumbing",
            "type":"Services"
        }
    ],
    "sg:phone":"+1   ",
    "sg:postcode":"15522",
    "sg:province":"PA",
    "sg:tags":[
        "contractor"
    ],
    "wof:name":"Mike Mortimore Mech Contg",
    "wof:placetype":"venue"
},
  "geometry": {"coordinates":[-78.462414,40.021069],"type":"Point"}
}