{
  "type": "Feature",
  "properties": {
    "iso:country":"US",
    "sg:address":"17 N 6th St",
    "sg:city":"Stroudsburg",
    "sg:classifiers":[
        {
            "category":"Manufacturing",
            "subcategory":"Printing",
            "type":"Manufacturing & Wholesale Goods"
        }
    ],
    "sg:phone":"+1   ",
    "sg:postcode":"18360",
    "sg:province":"PA",
    "sg:tags":[
        "publishing"
    ],
    "wof:name":"Allpocono Publishing Corp",
    "wof:placetype":"venue"
},
  "geometry": {"coordinates":[-75.193376,40.986097],"type":"Point"}
}