{
  "type": "Feature",
  "properties": {
    "iso:country":"US",
    "sg:address":"144 Union St",
    "sg:city":"Uniontown",
    "sg:classifiers":[
        {
            "category":"Professional",
            "type":"Services"
        }
    ],
    "sg:phone":"+1   ",
    "sg:postcode":"15401",
    "sg:province":"PA",
    "wof:name":"P & J Creative Products",
    "wof:placetype":"venue"
},
  "geometry": {"coordinates":[-79.730192,39.894819],"type":"Point"}
}