{
  "type": "Feature",
  "properties": {
    "iso:country":"US",
    "sg:address":"950 Wooded Pond Rd",
    "sg:city":"Ambler",
    "sg:classifiers":[
        {
            "category":"Manufacturing",
            "subcategory":"Electronics",
            "type":"Manufacturing & Wholesale Goods"
        }
    ],
    "sg:phone":"+1   ",
    "sg:postcode":"19002",
    "sg:province":"PA",
    "sg:tags":[
        "semiconductor",
        "integrated",
        "mfg",
        "system",
        "level"
    ],
    "wof:name":"Broadcom Corporation",
    "wof:placetype":"venue"
},
  "geometry": {"coordinates":[-75.21592699999999,40.19566],"type":"Point"}
}