{
  "type": "Feature",
  "properties": {
    "addr:full":"1221 Wyoming Ave Kingston PA 18704",
    "addr:housenumber":"1221",
    "addr:postcode":"18704",
    "addr:street":"Wyoming Ave",
    "iso:country":"US",
    "sg:address":"1221 Wyoming Ave",
    "sg:city":"Kingston",
    "sg:classifiers":[
        {
            "category":"Professional",
            "subcategory":"Advertising",
            "type":"Services"
        }
    ],
    "sg:phone":"+1 570 288 5313",
    "sg:postcode":"18704",
    "sg:province":"PA",
    "sg:tags":[
        "agency"
    ],
    "sg:website":"www.cdscreative.com",
    "wof:name":"CDS Creative",
    "wof:placetype":"venue"
},
  "geometry": {"coordinates":[-75.873881,41.28452],"type":"Point"}
}