{
  "type": "Feature",
  "properties": {
    "iso:country":"US",
    "sg:address":"1326 N Keyser Ave",
    "sg:city":"Scranton",
    "sg:classifiers":[
        {
            "category":"Autos & Motor Vehicles",
            "subcategory":"Automobile Sales",
            "type":"Retail Goods"
        }
    ],
    "sg:phone":"+1 570 347 0272",
    "sg:postcode":"18504",
    "sg:province":"PA",
    "sg:tags":[
        "car",
        "dealer"
    ],
    "wof:name":"John J Cronin Auto Sales",
    "wof:placetype":"venue"
},
  "geometry": {"coordinates":[-75.68722699999999,41.433229],"type":"Point"}
}