{
  "type": "Feature",
  "properties": {
    "iso:country":"US",
    "sg:address":"109 E Phillips St",
    "sg:city":"Coaldale",
    "sg:classifiers":[
        {
            "category":"Restaurant",
            "type":"Food & Drink"
        }
    ],
    "sg:phone":"+1   ",
    "sg:postcode":"18218",
    "sg:province":"PA",
    "sg:tags":[
        "eating"
    ],
    "wof:name":"Tommys Itln Specialty Shoppe",
    "wof:placetype":"venue"
},
  "geometry": {"coordinates":[-75.90355,40.823999],"type":"Point"}
}