{
  "type": "Feature",
  "properties": {
    "iso:country":"US",
    "sg:address":"1321 Upper State Rd",
    "sg:city":"Chalfont",
    "sg:classifiers":[
        {
            "category":"Education",
            "subcategory":"School",
            "type":"Public Place"
        }
    ],
    "sg:phone":"+1 215 412 7101",
    "sg:postcode":"18914",
    "sg:province":"PA",
    "wof:name":"Mary Mother-The Redeemer Sch",
    "wof:placetype":"venue"
},
  "geometry": {"coordinates":[-75.192323,40.278514],"type":"Point"}
}