{
  "type": "Feature",
  "properties": {
    "iso:country":"US",
    "sg:address":"784 Pequea Ave",
    "sg:city":"Gap",
    "sg:classifiers":[
        {
            "category":"Professional",
            "subcategory":"Accounting & Tax Preparation",
            "type":"Services"
        }
    ],
    "sg:phone":"+1 717 442 8804",
    "sg:postcode":"17527",
    "sg:province":"PA",
    "sg:tags":[
        "accountant"
    ],
    "wof:name":"Jeffrey S Hogg CPA",
    "wof:placetype":"venue"
},
  "geometry": {"coordinates":[-76.022436,39.990233],"type":"Point"}
}