{
  "type": "Feature",
  "properties": {
    "iso:country":"US",
    "sg:address":"1937 Broadview Place",
    "sg:city":"Aliquippa",
    "sg:classifiers":[
        {
            "category":"Building & Trades",
            "subcategory":"Landscaping Services",
            "type":"Services"
        },
        {
            "category":"Shopping",
            "subcategory":"Party Supplies",
            "type":"Retail Goods"
        },
        {
            "category":"Shopping",
            "subcategory":"Crafts & Fabrics",
            "type":"Retail Goods"
        },
        {
            "category":"Shopping",
            "subcategory":"Florist",
            "type":"Retail Goods"
        }
    ],
    "sg:phone":"+1 724 513 1686",
    "sg:postcode":"15001",
    "sg:province":"PA",
    "sg:tags":[
        "plant",
        "designer",
        "etc-retail",
        "consultant",
        "dried",
        "wedding",
        "trees-silk",
        "flowers",
        "landscape",
        "gardener"
    ],
    "sg:website":"http://www.magnoliagardensllc.com",
    "wof:name":"Magnolia Gardens, LLC.",
    "wof:placetype":"venue"
},
  "geometry": {"coordinates":[-80.27416700000001,40.601712],"type":"Point"}
}