{
  "type": "Feature",
  "properties": {
    "addr:full":"5924 Chestnut St Philadelphia PA 19139",
    "addr:housenumber":"5924",
    "addr:postcode":"19139",
    "addr:street":"Chestnut St",
    "iso:country":"US",
    "sg:address":"5924 Chestnut St",
    "sg:city":"Philadelphia",
    "sg:classifiers":[
        {
            "category":"Social Services",
            "subcategory":"Child Care",
            "type":"Services"
        }
    ],
    "sg:phone":"+1 215 747 0900",
    "sg:postcode":"19139",
    "sg:province":"PA",
    "sg:tags":[
        "elementary",
        "consultant",
        "school"
    ],
    "sg:website":"http://www.somethingtogrowon.net",
    "wof:name":"Something To Grow On Learning Center Inc",
    "wof:placetype":"venue"
},
  "geometry": {"coordinates":[-75.24009700000001,39.9604],"type":"Point"}
}