{
  "type": "Feature",
  "properties": {
    "iso:country":"US",
    "sg:address":"327 Mingo St",
    "sg:city":"Pittsburgh",
    "sg:classifiers":[
        {
            "category":"Organizations",
            "subcategory":"Community Association",
            "type":"Services"
        }
    ],
    "sg:phone":"+1   ",
    "sg:postcode":"15206",
    "sg:province":"PA",
    "sg:tags":[
        "civic",
        "social"
    ],
    "wof:name":"Circle L Lupus Club",
    "wof:placetype":"venue"
},
  "geometry": {"coordinates":[-79.890862,40.464715],"type":"Point"}
}