{
  "type": "Feature",
  "properties": {
    "iso:country":"US",
    "sg:address":"970 Durham Rd",
    "sg:city":"Langhorne",
    "sg:classifiers":[
        {
            "category":"Professional",
            "subcategory":"Computer Services",
            "type":"Services"
        }
    ],
    "sg:phone":"+1 215 891 9501",
    "sg:postcode":"19047",
    "sg:province":"PA",
    "sg:tags":[
        "developer",
        "publisher",
        "software",
        "designer",
        "consultant"
    ],
    "sg:website":"http://www.jobecca.com",
    "wof:name":"Jobecca Technology Group",
    "wof:placetype":"venue"
},
  "geometry": {"coordinates":[-74.89696600000001,40.154259],"type":"Point"}
}