{
  "type": "Feature",
  "properties": {
    "iso:country":"US",
    "sg:address":"2551 Brindle Dr",
    "sg:city":"Harrisburg",
    "sg:classifiers":[
        {
            "category":"Shopping",
            "subcategory":"Clothing, Apparel, & Fashions",
            "type":"Retail Goods"
        }
    ],
    "sg:phone":"+1 717 635 9535",
    "sg:postcode":"17109",
    "sg:province":"PA",
    "sg:tags":[
        "clothing",
        "women's"
    ],
    "sg:website":"www.facebook.com/lavishPA",
    "wof:name":"Lavish",
    "wof:placetype":"venue"
},
  "geometry": {"coordinates":[-76.84661199999999,40.302843],"type":"Point"}
}