{
  "type": "Feature",
  "properties": {
    "iso:country":"US",
    "sg:address":"1011 S 27th St",
    "sg:city":"Easton",
    "sg:classifiers":[
        {
            "category":"Real Estate",
            "subcategory":"Real Estate Agent",
            "type":"Services"
        }
    ],
    "sg:phone":"+1   ",
    "sg:postcode":"18045",
    "sg:province":"PA",
    "wof:name":"48 Enterprises",
    "wof:placetype":"venue"
},
  "geometry": {"coordinates":[-75.249758,40.675256],"type":"Point"}
}