{
  "type": "Feature",
  "properties": {
    "iso:country":"US",
    "sg:address":"5500 Old Carlisle Rd",
    "sg:city":"Dover",
    "sg:classifiers":[
        {
            "category":"Freight",
            "type":"Transportation"
        }
    ],
    "sg:phone":"+1 717 292 0106",
    "sg:postcode":"17315",
    "sg:province":"PA",
    "sg:tags":[
        "car",
        "pilot"
    ],
    "wof:name":"Guardian Angel",
    "wof:placetype":"venue"
},
  "geometry": {"coordinates":[-76.868539,40.021967],"type":"Point"}
}