{
  "type": "Feature",
  "properties": {
    "addr:full":"586 Main St Stroudsburg PA 18360",
    "addr:housenumber":"586",
    "addr:postcode":"18360",
    "addr:street":"Main St",
    "iso:country":"US",
    "sg:address":"586 Main St",
    "sg:city":"Stroudsburg",
    "sg:classifiers":[
        {
            "category":"Banks & Credit Unions",
            "subcategory":"Bank",
            "type":"Services"
        }
    ],
    "sg:phone":"+1   ",
    "sg:postcode":"18360",
    "sg:province":"PA",
    "sg:tags":[
        "mortgage"
    ],
    "wof:name":"American Heritage Mrtg Corp",
    "wof:placetype":"venue"
},
  "geometry": {"coordinates":[-75.192725,40.985803],"type":"Point"}
}