{
  "type": "Feature",
  "properties": {
    "iso:country":"US",
    "sg:address":"55 Old Clairton Rd # 101",
    "sg:city":"Pittsburgh",
    "sg:classifiers":[
        {
            "category":"Health Services",
            "subcategory":"Chiropractor",
            "type":"Services"
        }
    ],
    "sg:phone":"+1 412 653 5333",
    "sg:postcode":"15236",
    "sg:province":"PA",
    "sg:tags":[
        "chiropractic"
    ],
    "wof:name":"Joseph A Mele Jr Dc Pc",
    "wof:placetype":"venue"
},
  "geometry": {"coordinates":[-79.964073,40.338996],"type":"Point"}
}