{
  "type": "Feature",
  "properties": {
    "iso:country":"US",
    "sg:address":"131 Timber Ln",
    "sg:city":"New Castle",
    "sg:classifiers":[
        {
            "category":"Building & Trades",
            "subcategory":"Construction",
            "type":"Services"
        }
    ],
    "sg:phone":"+1 724 654 4400",
    "sg:postcode":"16116",
    "sg:province":"PA",
    "sg:tags":[
        "contractor",
        "paving",
        "surfacing"
    ],
    "wof:name":"White Oak Paving Inc",
    "wof:placetype":"venue"
},
  "geometry": {"coordinates":[-80.488946,41.059012],"type":"Point"}
}