{
  "type": "Feature",
  "properties": {
    "iso:country":"US",
    "sg:address":"150 Domorah Dr",
    "sg:city":"Montgomeryville",
    "sg:classifiers":[
        {
            "category":"Wholesale",
            "subcategory":"Groceries",
            "type":"Manufacturing & Wholesale Goods"
        }
    ],
    "sg:phone":"+1 215 469 1950",
    "sg:postcode":"18936",
    "sg:province":"PA",
    "sg:tags":[
        "extract",
        "flavoring"
    ],
    "wof:name":"Zink & Triest",
    "wof:placetype":"venue"
},
  "geometry": {"coordinates":[-75.22589000000001,40.223879],"type":"Point"}
}