{
  "type": "Feature",
  "properties": {
    "iso:country":"US",
    "sg:address":"732 Filbert St",
    "sg:city":"Pittsburgh",
    "sg:classifiers":[
        {
            "category":"Restaurant",
            "type":"Food & Drink"
        }
    ],
    "sg:phone":"+1 412 683 2333",
    "sg:postcode":"15232",
    "sg:province":"PA",
    "sg:tags":[
        "eating"
    ],
    "wof:name":"Crepes Parisiennes",
    "wof:placetype":"venue"
},
  "geometry": {"coordinates":[-79.93307,40.451413],"type":"Point"}
}