{
  "type": "Feature",
  "properties": {
    "iso:country":"US",
    "sg:address":"118 Diamond St",
    "sg:city":"Titusville",
    "sg:classifiers":[
        {
            "category":"Shopping",
            "subcategory":"Bicycles & Sporting Goods",
            "type":"Retail Goods"
        }
    ],
    "sg:phone":"+1 814 827 1299",
    "sg:postcode":"16354",
    "sg:province":"PA",
    "wof:name":"Hopkins Sporting Goods Inc",
    "wof:placetype":"venue"
},
  "geometry": {"coordinates":[-79.672107,41.626746],"type":"Point"}
}