{
  "type": "Feature",
  "properties": {
    "addr:full":"3681 Mountain Shadow Dr Fayetteville PA 17222",
    "addr:housenumber":"3681",
    "addr:postcode":"17222",
    "addr:street":"Mountain Shadow Dr",
    "iso:country":"US",
    "sg:address":"3681 Mountain Shadow Dr",
    "sg:city":"Fayetteville",
    "sg:classifiers":[
        {
            "category":"Building & Trades",
            "subcategory":"Construction",
            "type":"Services"
        }
    ],
    "sg:phone":"+1 717 352 4800",
    "sg:postcode":"17222",
    "sg:province":"PA",
    "sg:tags":[
        "home",
        "builder"
    ],
    "wof:name":"S & A Custom Built Homes Inc",
    "wof:placetype":"venue"
},
  "geometry": {"coordinates":[-77.556346,39.931221],"type":"Point"}
}