{
  "type": "Feature",
  "properties": {
    "iso:country":"US",
    "sg:address":"1400 Charles St",
    "sg:city":"State College",
    "sg:classifiers":[
        {
            "category":"Personal",
            "subcategory":"Beauty Salon",
            "type":"Services"
        }
    ],
    "sg:phone":"+1 814 237 5151",
    "sg:postcode":"16801",
    "sg:province":"PA",
    "wof:name":"His & Her Cuts By Rhonda",
    "wof:placetype":"venue"
},
  "geometry": {"coordinates":[-77.827747,40.801277],"type":"Point"}
}