{
  "type": "Feature",
  "properties": {
    "addr:full":"3963 Washington Rd Canonsburg PA 15317",
    "addr:housenumber":"3963",
    "addr:postcode":"15317",
    "addr:street":"Washington Rd",
    "iso:country":"US",
    "sg:address":"3963 Washington Rd",
    "sg:city":"Canonsburg",
    "sg:classifiers":[
        {
            "category":"Shopping",
            "subcategory":"Gifts & Souvenirs",
            "type":"Retail Goods"
        }
    ],
    "sg:phone":"+1   ",
    "sg:postcode":"15317",
    "sg:province":"PA",
    "wof:name":"Card Shop",
    "wof:placetype":"venue"
},
  "geometry": {"coordinates":[-80.12791199999999,40.271091],"type":"Point"}
}