{
  "type": "Feature",
  "properties": {
    "iso:country":"US",
    "sg:address":"555 S Henderson Rd",
    "sg:city":"King Of Prussia",
    "sg:classifiers":[
        {
            "category":"Home & Garden",
            "subcategory":"Home Furnishings",
            "type":"Retail Goods"
        }
    ],
    "sg:phone":"+1 610 992 1790",
    "sg:postcode":"19406",
    "sg:province":"PA",
    "sg:tags":[
        "lighting",
        "fixture"
    ],
    "wof:name":"Bright Light Design Ctr",
    "wof:placetype":"venue"
},
  "geometry": {"coordinates":[-75.35351900000001,40.076779],"type":"Point"}
}