{
  "type": "Feature",
  "properties": {
    "iso:country":"US",
    "sg:address":"637 N 13th St",
    "sg:city":"Philadelphia",
    "sg:classifiers":[
        {
            "category":"Real Estate",
            "subcategory":"Real Estate Operator",
            "type":"Services"
        }
    ],
    "sg:phone":"+1 215 763 9689",
    "sg:postcode":"19123",
    "sg:province":"PA",
    "sg:tags":[
        "apartment"
    ],
    "wof:name":"West Poplar Apts",
    "wof:placetype":"venue"
},
  "geometry": {"coordinates":[-75.158897,39.964699],"type":"Point"}
}