{
  "type": "Feature",
  "properties": {
    "addr:full":"701 Stewart Dr Apollo PA 15613",
    "addr:housenumber":"701",
    "addr:postcode":"15613",
    "addr:street":"Stewart Dr",
    "iso:country":"US",
    "sg:address":"701 Stewart Dr",
    "sg:city":"Apollo",
    "sg:classifiers":[
        {
            "category":"Building & Trades",
            "subcategory":"Construction",
            "type":"Services"
        }
    ],
    "sg:phone":"+1 724 727 2136",
    "sg:postcode":"15613",
    "sg:province":"PA",
    "sg:tags":[
        "road",
        "contractor"
    ],
    "wof:name":"American Carbide Restoration",
    "wof:placetype":"venue"
},
  "geometry": {"coordinates":[-79.59064499999999,40.53327],"type":"Point"}
}