{
  "type": "Feature",
  "properties": {
    "iso:country":"US",
    "sg:address":"45 Bulka Rd",
    "sg:city":"Houtzdale",
    "sg:classifiers":[
        {
            "category":"Organizations",
            "subcategory":"Religious Organization",
            "type":"Services"
        }
    ],
    "sg:phone":"+1 814 378 8025",
    "sg:postcode":"16651",
    "sg:province":"PA",
    "sg:tags":[
        "church"
    ],
    "wof:name":"Carsonville Assembly Of God",
    "wof:placetype":"venue"
},
  "geometry": {"coordinates":[-78.338373,40.846611],"type":"Point"}
}