{
  "type": "Feature",
  "properties": {
    "addr:full":"200 S 40th St Philadelphia PA 19104",
    "addr:housenumber":"200",
    "addr:postcode":"19104",
    "addr:street":"S 40Th St",
    "iso:country":"US",
    "sg:address":"200 S 40th St",
    "sg:city":"Philadelphia",
    "sg:classifiers":[
        {
            "category":"Education",
            "subcategory":"Special Training",
            "type":"Public Place"
        }
    ],
    "sg:phone":"+1 215 243 1711",
    "sg:postcode":"19104",
    "sg:province":"PA",
    "sg:tags":[
        "tutoring"
    ],
    "wof:name":"Kaplan Test Preparation",
    "wof:placetype":"venue"
},
  "geometry": {"coordinates":[-75.202646,39.953835],"type":"Point"}
}