{
  "type": "Feature",
  "properties": {
    "iso:country":"US",
    "sg:address":"1141 Clay Ave",
    "sg:city":"Dunmore",
    "sg:classifiers":[
        {
            "category":"Health Services",
            "subcategory":"Chiropractor",
            "type":"Services"
        },
        {
            "category":"Social Services",
            "subcategory":"Job Training",
            "type":"Services"
        }
    ],
    "sg:phone":"+1 570 343 6531",
    "sg:postcode":"18510",
    "sg:province":"PA",
    "sg:tags":[
        "rehabilitation"
    ],
    "wof:name":"Bessoir Chiropractic",
    "wof:placetype":"venue"
},
  "geometry": {"coordinates":[-75.64434300000001,41.414934],"type":"Point"}
}