{
  "type": "Feature",
  "properties": {
    "addr:full":"6345 Lewisville Ave Bensalem PA 19020",
    "addr:postcode":"6345;19020",
    "addr:street":"Lewisville Ave",
    "iso:country":"US",
    "sg:address":"6345 Lewisville Ave",
    "sg:city":"Bensalem",
    "sg:classifiers":[
        {
            "category":"Building & Trades",
            "subcategory":"Locksmith",
            "type":"Services"
        }
    ],
    "sg:phone":"+1 215 757 6824",
    "sg:postcode":"19020",
    "sg:province":"PA",
    "sg:tags":[
        "key"
    ],
    "wof:name":"P J Lock & Safe",
    "wof:placetype":"venue"
},
  "geometry": {"coordinates":[-74.902259,40.130331],"type":"Point"}
}