{
  "type": "Feature",
  "properties": {
    "iso:country":"US",
    "sg:address":"881 Abbottstown Pike",
    "sg:city":"Hanover",
    "sg:classifiers":[
        {
            "category":"Retail",
            "subcategory":"Animal Services",
            "type":"Services"
        }
    ],
    "sg:phone":"+1 717 637 7979",
    "sg:postcode":"17331",
    "sg:province":"PA",
    "sg:tags":[
        "pet",
        "boarding",
        "sitting"
    ],
    "wof:name":"Kirton Kennel",
    "wof:placetype":"venue"
},
  "geometry": {"coordinates":[-76.975252,39.817164],"type":"Point"}
}