{
  "type": "Feature",
  "properties": {
    "addr:full":"1718 Heilmandale Rd # 100 Lebanon PA 17046",
    "addr:housenumber":"1718",
    "addr:postcode":"17046",
    "addr:street":"Heilmandale Rd # 100",
    "iso:country":"US",
    "sg:address":"1718 Heilmandale Rd # 100",
    "sg:city":"Lebanon",
    "sg:classifiers":[
        {
            "category":"Building & Trades",
            "subcategory":"Construction",
            "type":"Services"
        }
    ],
    "sg:phone":"+1 717 273 3600",
    "sg:postcode":"17046",
    "sg:province":"PA",
    "sg:tags":[
        "carpenter"
    ],
    "wof:name":"Greater Pa Regional Council",
    "wof:placetype":"venue"
},
  "geometry": {"coordinates":[-76.48214299999999,40.370149],"type":"Point"}
}