{
  "type": "Feature",
  "properties": {
    "iso:country":"US",
    "sg:address":"26 S Baltimore St",
    "sg:city":"Dillsburg",
    "sg:classifiers":[
        {
            "category":"Restaurant",
            "type":"Food & Drink"
        }
    ],
    "sg:phone":"+1 717 502 1999",
    "sg:postcode":"17019",
    "sg:province":"PA",
    "sg:tags":[
        "pizza",
        "italian"
    ],
    "wof:name":"Millenium Pizzeria & Italian",
    "wof:placetype":"venue"
},
  "geometry": {"coordinates":[-77.028221,40.075321],"type":"Point"}
}