{
  "type": "Feature",
  "properties": {
    "addr:full":"3739 William Penn Hwy Monroeville PA 15146",
    "addr:housenumber":"3739",
    "addr:postcode":"15146",
    "addr:street":"William Penn Hwy",
    "iso:country":"US",
    "sg:address":"3739 William Penn Hwy",
    "sg:city":"Monroeville",
    "sg:classifiers":[
        {
            "category":"Home & Garden",
            "subcategory":"Home Furnishings",
            "type":"Retail Goods"
        }
    ],
    "sg:phone":"+1 412 372 7226",
    "sg:postcode":"15146",
    "sg:province":"PA",
    "sg:tags":[
        "linen"
    ],
    "wof:name":"Bed Bath & Beyond",
    "wof:placetype":"venue"
},
  "geometry": {"coordinates":[-79.78666699999999,40.435839],"type":"Point"}
}