{
  "type": "Feature",
  "properties": {
    "iso:country":"US",
    "sg:address":"1700 Wilmington Rd",
    "sg:city":"New Castle",
    "sg:classifiers":[
        {
            "category":"Food & Beverages",
            "subcategory":"Groceries & Convenience Stores",
            "type":"Retail Goods"
        }
    ],
    "sg:phone":"+1 724 654 1631",
    "sg:postcode":"16105",
    "sg:province":"PA",
    "sg:tags":[
        "grocer"
    ],
    "wof:name":"Ralph's Golden Dawn",
    "wof:placetype":"venue"
},
  "geometry": {"coordinates":[-80.354643,41.021753],"type":"Point"}
}