{
  "type": "Feature",
  "properties": {
    "addr:full":"2083 Forry Rd Lancaster PA 17601",
    "addr:housenumber":"2083",
    "addr:postcode":"17601",
    "addr:street":"Forry Rd",
    "iso:country":"US",
    "sg:address":"2083 Forry Rd",
    "sg:city":"Lancaster",
    "sg:classifiers":[
        {
            "category":"Building & Trades",
            "subcategory":"Construction",
            "type":"Services"
        }
    ],
    "sg:phone":"+1 717 293 0304",
    "sg:postcode":"17601",
    "sg:province":"PA",
    "sg:tags":[
        "agriculture"
    ],
    "wof:name":"E & F Ag Systems",
    "wof:placetype":"venue"
},
  "geometry": {"coordinates":[-76.23021900000001,40.066787],"type":"Point"}
}