{
  "type": "Feature",
  "properties": {
    "addr:full":"2278 E Street Rd Bensalem PA 19020",
    "addr:housenumber":"2278",
    "addr:postcode":"19020",
    "addr:street":"E Street Rd",
    "iso:country":"US",
    "sg:address":"2278 E Street Rd",
    "sg:city":"Bensalem",
    "sg:classifiers":[
        {
            "category":"Building & Trades",
            "subcategory":"Pest Control",
            "type":"Services"
        }
    ],
    "sg:phone":"+1 215 245 1005",
    "sg:postcode":"19020",
    "sg:province":"PA",
    "wof:name":"Home & Business Svc",
    "wof:placetype":"venue"
},
  "geometry": {"coordinates":[-74.94959900000001,40.102112],"type":"Point"}
}