{
  "type": "Feature",
  "properties": {
    "iso:country":"US",
    "sg:address":"578 US Hwy 209",
    "sg:city":"Milford",
    "sg:classifiers":[
        {
            "category":"Wholesale",
            "subcategory":"Scrap",
            "type":"Manufacturing & Wholesale Goods"
        }
    ],
    "sg:phone":"+1   ",
    "sg:postcode":"18337",
    "sg:province":"PA",
    "sg:tags":[
        "material"
    ],
    "wof:name":"Powertec Inc",
    "wof:placetype":"venue"
},
  "geometry": {"coordinates":[-74.79981100000001,41.32514],"type":"Point"}
}