{
  "type": "Feature",
  "properties": {
    "addr:full":"1700 Market St Philadelphia PA 19103",
    "addr:housenumber":"1700",
    "addr:postcode":"19103",
    "addr:street":"Market St",
    "iso:country":"US",
    "sg:address":"1700 Market St",
    "sg:city":"Philadelphia",
    "sg:classifiers":[
        {
            "category":"Food & Beverages",
            "subcategory":"Groceries & Convenience Stores",
            "type":"Retail Goods"
        }
    ],
    "sg:phone":"+1 215 861 9994",
    "sg:postcode":"19103",
    "sg:province":"PA",
    "wof:name":"Jams",
    "wof:placetype":"venue"
},
  "geometry": {"coordinates":[-75.168421,39.952864],"type":"Point"}
}