{
  "type": "Feature",
  "properties": {
    "iso:country":"US",
    "sg:address":"6595 W Lake Rd",
    "sg:city":"Fairview",
    "sg:classifiers":[
        {
            "category":"Manufacturing",
            "subcategory":"Tools & Machinery",
            "type":"Manufacturing & Wholesale Goods"
        }
    ],
    "sg:phone":"+1 814 474 3611",
    "sg:postcode":"16415",
    "sg:province":"PA",
    "sg:tags":[
        "pattern",
        "industrial",
        "mfg"
    ],
    "wof:name":"Anderson Pattern Works",
    "wof:placetype":"venue"
},
  "geometry": {"coordinates":[-80.229873,42.065301],"type":"Point"}
}