{
  "type": "Feature",
  "properties": {
    "iso:country":"US",
    "sg:address":"395 Easton Rd",
    "sg:city":"Warrington",
    "sg:classifiers":[
        {
            "category":"Shopping",
            "type":"Retail Goods"
        }
    ],
    "sg:phone":"+1 215 734 4000",
    "sg:postcode":"18976",
    "sg:province":"PA",
    "sg:tags":[
        "equipment",
        "merchandise",
        "telephone",
        "cellular",
        "supply"
    ],
    "sg:website":"http://www.upiwireless.com",
    "wof:name":"Upi Wireless",
    "wof:placetype":"venue"
},
  "geometry": {"coordinates":[-75.139957,40.222916],"type":"Point"}
}