{
  "type": "Feature",
  "properties": {
    "addr:full":"7 Woodland Dr Coraopolis PA 15108",
    "addr:housenumber":"7",
    "addr:postcode":"15108",
    "addr:street":"Woodland Dr",
    "iso:country":"US",
    "sg:address":"7 Woodland Dr",
    "sg:city":"Coraopolis",
    "sg:classifiers":[
        {
            "category":"Building & Trades",
            "subcategory":"Construction",
            "type":"Services"
        }
    ],
    "sg:phone":"+1   ",
    "sg:postcode":"15108",
    "sg:province":"PA",
    "wof:name":"Robert H Macek Constructi",
    "wof:placetype":"venue"
},
  "geometry": {"coordinates":[-80.110467,40.481329],"type":"Point"}
}