{
  "type": "Feature",
  "properties": {
    "iso:country":"US",
    "sg:address":"2543 N Patton St",
    "sg:city":"Philadelphia",
    "sg:classifiers":[
        {
            "category":"Insurance",
            "subcategory":"Insurance Agent",
            "type":"Services"
        },
        {
            "category":"Insurance",
            "subcategory":"Hazard Insurance",
            "type":"Services"
        }
    ],
    "sg:phone":"+1 215 221 5774",
    "sg:postcode":"19132",
    "sg:province":"PA",
    "sg:tags":[
        "fire",
        "property",
        "casualty"
    ],
    "wof:name":"Cna Corp",
    "wof:placetype":"venue"
},
  "geometry": {"coordinates":[-75.183322,39.995142],"type":"Point"}
}