{
  "type": "Feature",
  "properties": {
    "addr:full":"256 Logan Valley Mall Altoona PA 16602",
    "addr:housenumber":"256",
    "addr:postcode":"16602",
    "addr:street":"Logan Valley Mall",
    "iso:country":"US",
    "sg:address":"256 Logan Valley Mall",
    "sg:city":"Altoona",
    "sg:classifiers":[
        {
            "category":"Recreation",
            "subcategory":"Amusement Park",
            "type":"Entertainment"
        }
    ],
    "sg:phone":"+1 814 943 0990",
    "sg:postcode":"16602",
    "sg:province":"PA",
    "wof:name":"Pocket Change",
    "wof:placetype":"venue"
},
  "geometry": {"coordinates":[-78.40939,40.472036],"type":"Point"}
}