{
  "type": "Feature",
  "properties": {
    "addr:full":"3220 W Liberty Ave Pittsburgh PA 15216",
    "addr:housenumber":"3220",
    "addr:postcode":"15216",
    "addr:street":"W Liberty Ave",
    "iso:country":"US",
    "sg:address":"3220 W Liberty Ave",
    "sg:city":"Pittsburgh",
    "sg:classifiers":[
        {
            "category":"Restaurant",
            "type":"Food & Drink"
        }
    ],
    "sg:phone":"+1 412 561 0450",
    "sg:postcode":"15216",
    "sg:province":"PA",
    "wof:name":"Jamie's",
    "wof:placetype":"venue"
},
  "geometry": {"coordinates":[-80.028862,40.397316],"type":"Point"}
}