{
  "type": "Feature",
  "properties": {
    "addr:full":"32 E Street Rd Feasterville Trevose PA 19053",
    "addr:housenumber":"32",
    "addr:postcode":"19053",
    "addr:street":"E Street Rd",
    "iso:country":"US",
    "sg:address":"32 E Street Rd",
    "sg:city":"Feasterville Trevose",
    "sg:classifiers":[
        {
            "category":"Retail",
            "subcategory":"Auto Repair",
            "type":"Services"
        }
    ],
    "sg:phone":"+1   ",
    "sg:postcode":"19053",
    "sg:province":"PA",
    "sg:tags":[
        "general"
    ],
    "wof:name":"Stop & Go Transmission Inc",
    "wof:placetype":"venue"
},
  "geometry": {"coordinates":[-75.004409,40.151801],"type":"Point"}
}