{
  "type": "Feature",
  "properties": {
    "iso:country":"US",
    "sg:address":"751 High St",
    "sg:city":"Brownsville",
    "sg:classifiers":[
        {
            "category":"Restaurant",
            "type":"Food & Drink"
        }
    ],
    "sg:phone":"+1 724 785 3500",
    "sg:postcode":"15417",
    "sg:province":"PA",
    "sg:tags":[
        "pizza"
    ],
    "wof:name":"Georgio's Subs & Pizzas",
    "wof:placetype":"venue"
},
  "geometry": {"coordinates":[-79.898493,40.012544],"type":"Point"}
}