{
  "type": "Feature",
  "properties": {
    "iso:country":"US",
    "sg:address":"269 Quaker Dr",
    "sg:city":"Seneca",
    "sg:classifiers":[
        {
            "category":"Shopping",
            "subcategory":"Musical Instruments",
            "type":"Retail Goods"
        }
    ],
    "sg:phone":"+1 814 676 6683",
    "sg:postcode":"16346",
    "sg:province":"PA",
    "sg:tags":[
        "piano",
        "organ"
    ],
    "sg:website":"http://www.qrsmusic.com",
    "wof:name":"Story & Clark Piano Co",
    "wof:placetype":"venue"
},
  "geometry": {"coordinates":[-79.707037,41.375695],"type":"Point"}
}