{
  "type": "Feature",
  "properties": {
    "addr:full":"318 E 2nd St Hummelstown PA 17036",
    "addr:housenumber":"318",
    "addr:postcode":"17036",
    "addr:street":"E 2Nd St",
    "iso:country":"US",
    "sg:address":"318 E 2nd St",
    "sg:city":"Hummelstown",
    "sg:classifiers":[
        {
            "category":"Personal",
            "subcategory":"Beauty Salon",
            "type":"Services"
        }
    ],
    "sg:phone":"+1 717 566 0623",
    "sg:postcode":"17036",
    "sg:province":"PA",
    "sg:tags":[
        "shop"
    ],
    "wof:name":"Head Quarters",
    "wof:placetype":"venue"
},
  "geometry": {"coordinates":[-76.700491,40.267062],"type":"Point"}
}