{
  "type": "Feature",
  "properties": {
    "iso:country":"US",
    "sg:address":"6218 Edgeware Rd",
    "sg:city":"Mechanicsburg",
    "sg:classifiers":[
        {
            "category":"Building & Trades",
            "subcategory":"Construction",
            "type":"Services"
        }
    ],
    "sg:phone":"+1 717 766 6887",
    "sg:postcode":"17050",
    "sg:province":"PA",
    "sg:tags":[
        "concrete",
        "contractor"
    ],
    "wof:name":"A Wells Paving",
    "wof:placetype":"venue"
},
  "geometry": {"coordinates":[-76.997586,40.248846],"type":"Point"}
}