{
  "type": "Feature",
  "properties": {
    "addr:full":"161 Grove Ave Pittsburgh PA 15229",
    "addr:housenumber":"161",
    "addr:postcode":"15229",
    "addr:street":"Grove Ave",
    "iso:country":"US",
    "sg:address":"161 Grove Ave",
    "sg:city":"Pittsburgh",
    "sg:classifiers":[
        {
            "category":"Building & Trades",
            "subcategory":"Construction",
            "type":"Services"
        }
    ],
    "sg:phone":"+1 412 931 5755",
    "sg:postcode":"15229",
    "sg:province":"PA",
    "sg:tags":[
        "wood",
        "refinishing",
        "floor"
    ],
    "wof:name":"A Satin Finish",
    "wof:placetype":"venue"
},
  "geometry": {"coordinates":[-80.016403,40.515913],"type":"Point"}
}