{
  "type": "Feature",
  "properties": {
    "addr:full":"604 Park City Ctr Lancaster PA 17601",
    "addr:housenumber":"604",
    "addr:postcode":"17601",
    "addr:street":"Park",
    "iso:country":"US",
    "sg:address":"604 Park City Ctr",
    "sg:city":"Lancaster",
    "sg:classifiers":[
        {
            "category":"Bakery",
            "type":"Food & Drink"
        }
    ],
    "sg:menulink":"http://www.allmenus.com/pa/lancaster/224018-cinnabon/menu/",
    "sg:phone":"+1 717 399 9855",
    "sg:postcode":"17601",
    "sg:province":"PA",
    "sg:tags":[
        "american",
        "pastry"
    ],
    "wof:name":"Cinnabon",
    "wof:placetype":"venue"
},
  "geometry": {"coordinates":[-76.33562000000001,40.06573],"type":"Point"}
}