{
  "type": "Feature",
  "properties": {
    "iso:country":"US",
    "sg:address":"8 Union Hill Rd",
    "sg:city":"Conshohocken",
    "sg:classifiers":[
        {
            "category":"Wholesale",
            "subcategory":"Construction Materials",
            "type":"Manufacturing & Wholesale Goods"
        },
        {
            "category":"Home & Garden",
            "subcategory":"Building Materials",
            "type":"Retail Goods"
        },
        {
            "category":"Utilities",
            "type":"Services"
        }
    ],
    "sg:phone":"+1 610 941 9550",
    "sg:postcode":"19428",
    "sg:province":"PA",
    "sg:tags":[
        "units-manufacturers",
        "heating",
        "system",
        "systems-wholesale",
        "equipment",
        "distributor"
    ],
    "wof:name":"Tri State Parts Company",
    "wof:placetype":"venue"
},
  "geometry": {"coordinates":[-75.322678,40.069271],"type":"Point"}
}