{
  "type": "Feature",
  "properties": {
    "addr:full":"9432 Roosevelt Blvd Philadelphia PA 19115",
    "addr:housenumber":"9432",
    "addr:postcode":"19115",
    "addr:street":"Roosevelt Blvd",
    "iso:country":"US",
    "sg:address":"9432 Roosevelt Blvd",
    "sg:city":"Philadelphia",
    "sg:classifiers":[
        {
            "category":"Health Services",
            "subcategory":"Doctor",
            "type":"Services"
        }
    ],
    "sg:phone":"+1 215 464 8050",
    "sg:postcode":"19115",
    "sg:province":"PA",
    "sg:tags":[
        "medical"
    ],
    "wof:name":"Medical Imaging Assoc",
    "wof:placetype":"venue"
},
  "geometry": {"coordinates":[-75.02907500000001,40.080925],"type":"Point"}
}