{
  "type": "Feature",
  "properties": {
    "iso:country":"US",
    "sg:address":"202 Main St",
    "sg:city":"Winfield",
    "sg:classifiers":[
        {
            "category":"Building & Trades",
            "subcategory":"Construction",
            "type":"Services"
        }
    ],
    "sg:phone":"+1   ",
    "sg:postcode":"17820",
    "sg:province":"PA",
    "sg:tags":[
        "house"
    ],
    "wof:name":"Poppel Construction",
    "wof:placetype":"venue"
},
  "geometry": {"coordinates":[-76.463335,40.953016],"type":"Point"}
}