{
  "type": "Feature",
  "properties": {
    "iso:country":"US",
    "sg:address":"9892 Bustleton Ave",
    "sg:city":"Philadelphia",
    "sg:classifiers":[
        {
            "category":"Health Services",
            "subcategory":"Doctor",
            "type":"Services"
        }
    ],
    "sg:phone":"+1 610 649 1970",
    "sg:postcode":"19115",
    "sg:province":"PA",
    "sg:tags":[
        "physician",
        "surgeon"
    ],
    "wof:name":"Northeast Retina Consultants",
    "wof:placetype":"venue"
},
  "geometry": {"coordinates":[-75.030765,40.095679],"type":"Point"}
}