{
  "type": "Feature",
  "properties": {
    "iso:country":"US",
    "sg:address":"10030 Jonestown Rd",
    "sg:city":"Grantville",
    "sg:classifiers":[
        {
            "category":"Professional",
            "subcategory":"Business Services",
            "type":"Services"
        }
    ],
    "sg:phone":"+1 717 469 0070",
    "sg:postcode":"17028",
    "sg:province":"PA",
    "sg:tags":[
        "notary"
    ],
    "wof:name":"Curt's Auto Co",
    "wof:placetype":"venue"
},
  "geometry": {"coordinates":[-76.646646,40.37804],"type":"Point"}
}