{
  "type": "Feature",
  "properties": {
    "addr:full":"101 Ridge Rd Chadds Ford PA 19317",
    "addr:housenumber":"101",
    "addr:postcode":"19317",
    "addr:street":"Ridge Rd",
    "iso:country":"US",
    "sg:address":"101 Ridge Rd",
    "sg:city":"Chadds Ford",
    "sg:classifiers":[
        {
            "category":"Shopping",
            "subcategory":"Crafts & Fabrics",
            "type":"Retail Goods"
        }
    ],
    "sg:phone":"+1   ",
    "sg:postcode":"19317",
    "sg:province":"PA",
    "sg:tags":[
        "sewing"
    ],
    "wof:name":"Strawberry Sampler Counted",
    "wof:placetype":"venue"
},
  "geometry": {"coordinates":[-75.57582600000001,39.845425],"type":"Point"}
}