{
  "type": "Feature",
  "properties": {
    "addr:full":"245 Summerlawn Dr Sewickley PA 15143",
    "addr:housenumber":"245",
    "addr:postcode":"15143",
    "addr:street":"Summerlawn Dr",
    "iso:country":"US",
    "sg:address":"245 Summerlawn Dr",
    "sg:city":"Sewickley",
    "sg:classifiers":[
        {
            "category":"Real Estate",
            "subcategory":"Developer",
            "type":"Services"
        }
    ],
    "sg:phone":"+1   ",
    "sg:postcode":"15143",
    "sg:province":"PA",
    "wof:name":"Southersby Development Corp",
    "wof:placetype":"venue"
},
  "geometry": {"coordinates":[-80.196923,40.58431],"type":"Point"}
}