{
  "type": "Feature",
  "properties": {
    "iso:country":"US",
    "sg:address":"928 Brookline Blvd",
    "sg:city":"Pittsburgh",
    "sg:classifiers":[
        {
            "category":"Professional",
            "subcategory":"Accounting & Tax Preparation",
            "type":"Services"
        }
    ],
    "sg:phone":"+1 412 882 8002",
    "sg:postcode":"15226",
    "sg:province":"PA",
    "sg:tags":[
        "accountant"
    ],
    "wof:name":"Dudding Mark D CPA",
    "wof:placetype":"venue"
},
  "geometry": {"coordinates":[-80.01856600000001,40.392318],"type":"Point"}
}