{
  "type": "Feature",
  "properties": {
    "addr:full":"50 E 4th Ave Collegeville PA 19426",
    "addr:housenumber":"50",
    "addr:postcode":"19426",
    "addr:street":"E 4Th Ave",
    "iso:country":"US",
    "sg:address":"50 E 4th Ave",
    "sg:city":"Collegeville",
    "sg:classifiers":[
        {
            "category":"Insurance",
            "subcategory":"Insurance Agent",
            "type":"Services"
        }
    ],
    "sg:phone":"+1   ",
    "sg:postcode":"19426",
    "sg:province":"PA",
    "wof:name":"Arnao A Jr Agency",
    "wof:placetype":"venue"
},
  "geometry": {"coordinates":[-75.452088,40.188652],"type":"Point"}
}