{
  "type": "Feature",
  "properties": {
    "iso:country":"US",
    "sg:address":"617 S Braddock Ave",
    "sg:city":"Wilkinsburg",
    "sg:classifiers":[
        {
            "category":"Wholesale",
            "subcategory":"Machinery & Supplies",
            "type":"Manufacturing & Wholesale Goods"
        }
    ],
    "sg:phone":"+1 412 243 4564",
    "sg:postcode":"15221",
    "sg:province":"PA",
    "sg:tags":[
        "industrial",
        "miscellaneous"
    ],
    "wof:name":"Lincoln Supply & Equipment",
    "wof:placetype":"venue"
},
  "geometry": {"coordinates":[-79.89705499999999,40.438547],"type":"Point"}
}