{
  "type": "Feature",
  "properties": {
    "iso:country":"US",
    "sg:address":"1356 S Corlies St",
    "sg:city":"Philadelphia",
    "sg:classifiers":[
        {
            "category":"Restaurant",
            "type":"Food & Drink"
        }
    ],
    "sg:phone":"+1   ",
    "sg:postcode":"19146",
    "sg:province":"PA",
    "sg:tags":[
        "eating"
    ],
    "wof:name":"Poor Boy",
    "wof:placetype":"venue"
},
  "geometry": {"coordinates":[-75.19436899999999,39.937045],"type":"Point"}
}