{
  "type": "Feature",
  "properties": {
    "addr:full":"3325 E Street Rd Bensalem PA 19020",
    "addr:housenumber":"3325",
    "addr:postcode":"19020",
    "addr:street":"E Street Rd",
    "iso:country":"US",
    "sg:address":"3325 E Street Rd",
    "sg:city":"Bensalem",
    "sg:classifiers":[
        {
            "category":"Professional",
            "subcategory":"Lawyer & Legal Services",
            "type":"Services"
        }
    ],
    "sg:phone":"+1 215 244 1045",
    "sg:postcode":"19020",
    "sg:province":"PA",
    "sg:tags":[
        "attorney"
    ],
    "sg:website":"www.kellisandsoffer.com",
    "wof:name":"Kellis & Soffer LLP",
    "wof:placetype":"venue"
},
  "geometry": {"coordinates":[-74.96022600000001,40.11883],"type":"Point"}
}