{
  "type": "Feature",
  "properties": {
    "addr:full":"100 Center Ave Aspinwall PA 15215",
    "addr:housenumber":"100",
    "addr:postcode":"15215",
    "addr:street":"Center Ave",
    "iso:country":"US",
    "sg:address":"100 Center Ave",
    "sg:city":"Aspinwall",
    "sg:classifiers":[
        {
            "category":"Retail",
            "subcategory":"Funeral Services",
            "type":"Services"
        }
    ],
    "sg:phone":"+1 412 781 1897",
    "sg:postcode":"15215",
    "sg:province":"PA",
    "sg:tags":[
        "director"
    ],
    "wof:name":"Weddell-Ajak Funeral Home",
    "wof:placetype":"venue"
},
  "geometry": {"coordinates":[-79.90473299999999,40.491513],"type":"Point"}
}