{
  "type": "Feature",
  "properties": {
    "addr:full":"7229 Rising Sun Ave Philadelphia PA 19111",
    "addr:housenumber":"7229",
    "addr:postcode":"19111",
    "addr:street":"Rising Sun Ave",
    "iso:country":"US",
    "sg:address":"7229 Rising Sun Ave",
    "sg:city":"Philadelphia",
    "sg:classifiers":[
        {
            "category":"Manufacturing",
            "subcategory":"Textiles",
            "type":"Manufacturing & Wholesale Goods"
        }
    ],
    "sg:phone":"+1 215 928 9969",
    "sg:postcode":"19111",
    "sg:province":"PA",
    "wof:name":"Hofferman B Textiles",
    "wof:placetype":"venue"
},
  "geometry": {"coordinates":[-75.083865,40.061309],"type":"Point"}
}