{
  "type": "Feature",
  "properties": {
    "iso:country":"US",
    "sg:address":"925 Chestnut St",
    "sg:city":"Emmaus",
    "sg:classifiers":[
        {
            "category":"Professional",
            "subcategory":"Business Services",
            "type":"Services"
        },
        {
            "category":"Government",
            "subcategory":"Department Of Motor Vehicles",
            "type":"Public Place"
        }
    ],
    "sg:phone":"+1 610 967 2289",
    "sg:postcode":"18049",
    "sg:province":"PA",
    "sg:tags":[
        "tags-vehicle",
        "notary",
        "license"
    ],
    "sg:website":"http://eg-notary.com",
    "wof:name":"E G Notary Service LLC",
    "wof:placetype":"venue"
},
  "geometry": {"coordinates":[-75.50277800000001,40.530321],"type":"Point"}
}