{
  "type": "Feature",
  "properties": {
    "iso:country":"US",
    "sg:address":"706 Center St",
    "sg:city":"Pittsburgh",
    "sg:classifiers":[
        {
            "category":"Wholesale",
            "subcategory":"Home Furnishings",
            "type":"Manufacturing & Wholesale Goods"
        }
    ],
    "sg:phone":"+1   ",
    "sg:postcode":"15221",
    "sg:province":"PA",
    "sg:tags":[
        "hardware",
        "drapery"
    ],
    "wof:name":"Munkittrick Inc",
    "wof:placetype":"venue"
},
  "geometry": {"coordinates":[-79.88300599999999,40.440676],"type":"Point"}
}