{
  "type": "Feature",
  "properties": {
    "addr:full":"4160 Monument Rd Philadelphia PA 19131",
    "addr:housenumber":"4160",
    "addr:postcode":"19131",
    "addr:street":"Monument Rd",
    "iso:country":"US",
    "sg:address":"4160 Monument Rd",
    "sg:city":"Philadelphia",
    "sg:classifiers":[
        {
            "category":"Building & Trades",
            "subcategory":"Locksmith",
            "type":"Services"
        }
    ],
    "sg:phone":"+1 267 448 7113",
    "sg:postcode":"19131",
    "sg:province":"PA",
    "sg:tags":[
        "key"
    ],
    "wof:name":"Emergency Locksmith Fast Service Philadelphia",
    "wof:placetype":"venue"
},
  "geometry": {"coordinates":[-75.215048,40.002624],"type":"Point"}
}