{
  "type": "Feature",
  "properties": {
    "addr:full":"67 York St Wellsville PA 17365",
    "addr:housenumber":"67",
    "addr:postcode":"17365",
    "addr:street":"York St",
    "iso:country":"US",
    "sg:address":"67 York St",
    "sg:city":"Wellsville",
    "sg:classifiers":[
        {
            "category":"Retail",
            "subcategory":"Repair Shop",
            "type":"Services"
        }
    ],
    "sg:phone":"+1 717 432 4198",
    "sg:postcode":"17365",
    "sg:province":"PA",
    "sg:tags":[
        "television",
        "radio"
    ],
    "wof:name":"Gary E Rodgers TV Svc",
    "wof:placetype":"venue"
},
  "geometry": {"coordinates":[-76.937089,40.051173],"type":"Point"}
}