{
  "type": "Feature",
  "properties": {
    "addr:full":"107 Clay St North East PA 16428",
    "addr:housenumber":"107",
    "addr:postcode":"16428",
    "addr:street":"Clay St North",
    "iso:country":"US",
    "sg:address":"107 Clay St",
    "sg:city":"North East",
    "sg:classifiers":[
        {
            "category":"Health Services",
            "subcategory":"Health Practitioner",
            "type":"Services"
        }
    ],
    "sg:phone":"+1 814 725 3200",
    "sg:postcode":"16428",
    "sg:province":"PA",
    "sg:tags":[
        "therapist",
        "physical"
    ],
    "wof:name":"Keystone Rehabilitation Systs",
    "wof:placetype":"venue"
},
  "geometry": {"coordinates":[-79.82885,42.213834],"type":"Point"}
}