{
  "type": "Feature",
  "properties": {
    "addr:full":"1675 Washington Rd Pittsburgh PA 15228",
    "addr:housenumber":"1675",
    "addr:postcode":"15228",
    "addr:street":"Washington Rd",
    "iso:country":"US",
    "sg:address":"1675 Washington Rd",
    "sg:city":"Pittsburgh",
    "sg:classifiers":[
        {
            "category":"Home & Garden",
            "subcategory":"Carpets & Floor Coverings",
            "type":"Retail Goods"
        }
    ],
    "sg:phone":"+1 412 563 1000",
    "sg:postcode":"15228",
    "sg:province":"PA",
    "sg:tags":[
        "mattress"
    ],
    "wof:name":"Mattress World",
    "wof:placetype":"venue"
},
  "geometry": {"coordinates":[-80.050797,40.351398],"type":"Point"}
}