{
  "type": "Feature",
  "properties": {
    "addr:full":"6107 W Mill Rd Flourtown PA 19031",
    "addr:housenumber":"6107",
    "addr:postcode":"19031",
    "addr:street":"W Mill Rd",
    "iso:country":"US",
    "sg:address":"6107 W Mill Rd",
    "sg:city":"Flourtown",
    "sg:classifiers":[
        {
            "category":"Professional",
            "subcategory":"Computer Services",
            "type":"Services"
        }
    ],
    "sg:phone":"+1   ",
    "sg:postcode":"19031",
    "sg:province":"PA",
    "sg:tags":[
        "photographic",
        "software"
    ],
    "wof:name":"The Candid Image",
    "wof:placetype":"venue"
},
  "geometry": {"coordinates":[-75.220499,40.104143],"type":"Point"}
}