{
  "type": "Feature",
  "properties": {
    "iso:country":"US",
    "sg:address":"701 Laughlin Ave",
    "sg:city":"Aliquippa",
    "sg:classifiers":[
        {
            "category":"Building & Trades",
            "subcategory":"Landscaping Services",
            "type":"Services"
        },
        {
            "category":"Home & Garden",
            "subcategory":"Building Materials",
            "type":"Retail Goods"
        },
        {
            "category":"Home & Garden",
            "subcategory":"Carpets & Floor Coverings",
            "type":"Retail Goods"
        }
    ],
    "sg:phone":"+1 412 208 4260",
    "sg:postcode":"15001",
    "sg:province":"PA",
    "sg:tags":[
        "flooring",
        "wall",
        "contractor",
        "concrete",
        "retaining",
        "landscape"
    ],
    "wof:name":"Ketchel Contracting",
    "wof:placetype":"venue"
},
  "geometry": {"coordinates":[-80.24897,40.61108],"type":"Point"}
}