{
  "type": "Feature",
  "properties": {
    "addr:full":"1356 E Lycoming St Philadelphia PA 19124",
    "addr:housenumber":"1356",
    "addr:postcode":"19124",
    "addr:street":"E Lycoming St",
    "iso:country":"US",
    "sg:address":"1356 E Lycoming St",
    "sg:city":"Philadelphia",
    "sg:classifiers":[
        {
            "category":"Building & Trades",
            "subcategory":"Locksmith",
            "type":"Services"
        }
    ],
    "sg:phone":"+1 267 350 8838",
    "sg:postcode":"19124",
    "sg:province":"PA",
    "sg:tags":[
        "key"
    ],
    "wof:name":"1 Hour Emergency Locksmith",
    "wof:placetype":"venue"
},
  "geometry": {"coordinates":[-75.10096299999999,40.00887],"type":"Point"}
}