{
  "type": "Feature",
  "properties": {
    "iso:country":"US",
    "sg:address":"1 Brandywine",
    "sg:city":"Chadds Ford",
    "sg:classifiers":[
        {
            "category":"Building & Trades",
            "subcategory":"Construction",
            "type":"Services"
        }
    ],
    "sg:phone":"+1 610 429 2900",
    "sg:postcode":"19317",
    "sg:province":"PA",
    "sg:tags":[
        "contractor"
    ],
    "wof:name":"Raab R D & Co",
    "wof:placetype":"venue"
},
  "geometry": {"coordinates":[-75.551804,39.874802],"type":"Point"}
}