{
  "type": "Feature",
  "properties": {
    "iso:country":"US",
    "sg:address":"1509 Bethlehem Pike",
    "sg:city":"Flourtown",
    "sg:classifiers":[
        {
            "category":"Shopping",
            "subcategory":"Clothing, Apparel, & Fashions",
            "type":"Retail Goods"
        }
    ],
    "sg:phone":"+1 215 233 0787",
    "sg:postcode":"19031",
    "sg:province":"PA",
    "sg:tags":[
        "tailor"
    ],
    "wof:name":"Flourtown Tailors",
    "wof:placetype":"venue"
},
  "geometry": {"coordinates":[-75.21338799999999,40.10545],"type":"Point"}
}