{
  "type": "Feature",
  "properties": {
    "addr:full":"600 Murray St Bangor PA 18013",
    "addr:housenumber":"600",
    "addr:postcode":"18013",
    "addr:street":"Murray St",
    "iso:country":"US",
    "sg:address":"600 Murray St",
    "sg:city":"Bangor",
    "sg:classifiers":[
        {
            "category":"Retail",
            "subcategory":"Laundry & Dry Cleaning",
            "type":"Services"
        }
    ],
    "sg:phone":"+1   ",
    "sg:postcode":"18013",
    "sg:province":"PA",
    "sg:tags":[
        "personal",
        "linen",
        "supply",
        "mfg"
    ],
    "wof:name":"Merry Maids",
    "wof:placetype":"venue"
},
  "geometry": {"coordinates":[-75.20474299999999,40.859809],"type":"Point"}
}