{
  "type": "Feature",
  "properties": {
    "addr:full":"120 Horseshoe Ln Horsham PA 19044",
    "addr:housenumber":"120",
    "addr:postcode":"19044",
    "addr:street":"Horseshoe Ln",
    "iso:country":"US",
    "sg:address":"120 Horseshoe Ln",
    "sg:city":"Horsham",
    "sg:classifiers":[
        {
            "category":"Retail",
            "subcategory":"Repair Shop",
            "type":"Services"
        }
    ],
    "sg:phone":"+1 215 442 0659",
    "sg:postcode":"19044",
    "sg:province":"PA",
    "sg:tags":[
        "lighting",
        "fixture"
    ],
    "wof:name":"Mark Burns Electric",
    "wof:placetype":"venue"
},
  "geometry": {"coordinates":[-75.152342,40.173204],"type":"Point"}
}