{
  "type": "Feature",
  "properties": {
    "addr:full":"150 N Queen St Lancaster PA 17603",
    "addr:housenumber":"150",
    "addr:postcode":"17603",
    "addr:street":"N Queen St",
    "iso:country":"US",
    "sg:address":"150 N Queen St",
    "sg:city":"Lancaster",
    "sg:classifiers":[
        {
            "category":"Banks & Credit Unions",
            "subcategory":"Investment Brokerage",
            "type":"Services"
        }
    ],
    "sg:phone":"+1 717 295 8900",
    "sg:postcode":"17603",
    "sg:province":"PA",
    "sg:tags":[
        "stock",
        "bond"
    ],
    "sg:website":"www.smithbarney.com",
    "wof:name":"Smith Barney",
    "wof:placetype":"venue"
},
  "geometry": {"coordinates":[-76.30624299999999,40.0403],"type":"Point"}
}