{
  "type": "Feature",
  "properties": {
    "addr:full":"210 North St Harrisburg PA 17101",
    "addr:housenumber":"210",
    "addr:postcode":"17101",
    "addr:street":"North St",
    "iso:country":"US",
    "sg:address":"210 North St",
    "sg:city":"Harrisburg",
    "sg:classifiers":[
        {
            "category":"Personal",
            "type":"Services"
        }
    ],
    "sg:phone":"+1 717 236 4939",
    "sg:postcode":"17101",
    "sg:province":"PA",
    "sg:tags":[
        "therapist",
        "massage"
    ],
    "wof:name":"Massage At Your Residence",
    "wof:placetype":"venue"
},
  "geometry": {"coordinates":[-76.887388,40.264422],"type":"Point"}
}