{
  "type": "Feature",
  "properties": {
    "iso:country":"US",
    "sg:address":"2511 Rising Sun Rd",
    "sg:city":"Slatington",
    "sg:classifiers":[
        {
            "category":"Professional",
            "subcategory":"Business Services",
            "type":"Services"
        }
    ],
    "sg:phone":"+1 610 262 0423",
    "sg:postcode":"18080",
    "sg:province":"PA",
    "sg:tags":[
        "auctioneer"
    ],
    "wof:name":"John Pfeiffer Auctioneer",
    "wof:placetype":"venue"
},
  "geometry": {"coordinates":[-75.576311,40.705333],"type":"Point"}
}