{
  "type": "Feature",
  "properties": {
    "iso:country":"US",
    "sg:address":"3316 Perry Hwy",
    "sg:city":"Hadley",
    "sg:classifiers":[
        {
            "category":"Manufacturing",
            "subcategory":"Retail Goods",
            "type":"Manufacturing & Wholesale Goods"
        }
    ],
    "sg:phone":"+1   ",
    "sg:postcode":"16130",
    "sg:province":"PA",
    "sg:tags":[
        "marking",
        "devices",
        "mfg"
    ],
    "wof:name":"Paiges Primitives",
    "wof:placetype":"venue"
},
  "geometry": {"coordinates":[-80.20608799999999,41.44822],"type":"Point"}
}