{
  "type": "Feature",
  "properties": {
    "addr:full":"1003 Easton Rd Willow Grove PA 19090",
    "addr:housenumber":"1003",
    "addr:postcode":"19090",
    "addr:street":"Easton Rd",
    "iso:country":"US",
    "sg:address":"1003 Easton Rd",
    "sg:city":"Willow Grove",
    "sg:classifiers":[
        {
            "category":"Health Services",
            "subcategory":"Doctor",
            "type":"Services"
        }
    ],
    "sg:phone":"+1 215 657 2424",
    "sg:postcode":"19090",
    "sg:province":"PA",
    "sg:tags":[
        "dentist"
    ],
    "wof:name":"John P Epright DMD",
    "wof:placetype":"venue"
},
  "geometry": {"coordinates":[-75.12158599999999,40.154511],"type":"Point"}
}