{
  "type": "Feature",
  "properties": {
    "addr:full":"1275 Carolyn Dr Southampton PA 18966",
    "addr:housenumber":"1275",
    "addr:postcode":"18966",
    "addr:street":"Carolyn Dr",
    "iso:country":"US",
    "sg:address":"1275 Carolyn Dr",
    "sg:city":"Southampton",
    "sg:classifiers":[
        {
            "category":"Professional",
            "subcategory":"Detective & Security Services",
            "type":"Services"
        }
    ],
    "sg:phone":"+1 215 942 4806",
    "sg:postcode":"18966",
    "sg:province":"PA",
    "sg:tags":[
        "guard",
        "patrol"
    ],
    "wof:name":"Falcon Security Alarm Systems",
    "wof:placetype":"venue"
},
  "geometry": {"coordinates":[-75.017532,40.180675],"type":"Point"}
}