{
  "type": "Feature",
  "properties": {
    "iso:country":"US",
    "sg:address":"506 S George St",
    "sg:city":"York",
    "sg:classifiers":[
        {
            "category":"Organizations",
            "subcategory":"Non-profit Organization",
            "type":"Services"
        }
    ],
    "sg:phone":"+1 717 854 8742",
    "sg:postcode":"17403",
    "sg:province":"PA",
    "sg:tags":[
        "human"
    ],
    "sg:website":"www.yorkcan.org",
    "wof:name":"South George St Community",
    "wof:placetype":"venue"
},
  "geometry": {"coordinates":[-76.72363300000001,39.954566],"type":"Point"}
}