{
  "type": "Feature",
  "properties": {
    "iso:country":"US",
    "sg:address":"6 Cinder Ln",
    "sg:city":"Levittown",
    "sg:classifiers":[
        {
            "category":"Retail",
            "subcategory":"Car Wash",
            "type":"Services"
        }
    ],
    "sg:phone":"+1 215 547 6205",
    "sg:postcode":"19057",
    "sg:province":"PA",
    "wof:name":"Magic Touch Car Wash",
    "wof:placetype":"venue"
},
  "geometry": {"coordinates":[-74.870993,40.136516],"type":"Point"}
}