{
  "type": "Feature",
  "properties": {
    "iso:country":"US",
    "sg:address":"4 Colonial Ridge Dr",
    "sg:city":"Morrisville",
    "sg:classifiers":[
        {
            "category":"Professional",
            "type":"Services"
        }
    ],
    "sg:phone":"+1   ",
    "sg:postcode":"19067",
    "sg:province":"PA",
    "wof:name":"Stan Lantz Corp",
    "wof:placetype":"venue"
},
  "geometry": {"coordinates":[-74.823033,40.224516],"type":"Point"}
}