{
  "type": "Feature",
  "properties": {
    "addr:full":"3540 Concord Rd York PA 17402",
    "addr:housenumber":"3540",
    "addr:postcode":"17402",
    "addr:street":"Concord Rd",
    "iso:country":"US",
    "sg:address":"3540 Concord Rd",
    "sg:city":"York",
    "sg:classifiers":[
        {
            "category":"Professional",
            "subcategory":"Management & Consulting",
            "type":"Services"
        },
        {
            "category":"Professional",
            "subcategory":"Engineering",
            "type":"Services"
        }
    ],
    "sg:phone":"+1 717 840 4112",
    "sg:postcode":"17402",
    "sg:province":"PA",
    "sg:tags":[
        "environmental",
        "ecological",
        "engineer",
        "consultant"
    ],
    "sg:website":"http://www.atcassociates.com",
    "wof:name":"A T C Associates",
    "wof:placetype":"venue"
},
  "geometry": {"coordinates":[-76.658568,39.98903],"type":"Point"}
}