{
  "type": "Feature",
  "properties": {
    "iso:country":"US",
    "sg:address":"68 E Main St",
    "sg:city":"Waynesboro",
    "sg:classifiers":[
        {
            "category":"Building & Trades",
            "subcategory":"Construction",
            "type":"Services"
        }
    ],
    "sg:phone":"+1 717 762 1155",
    "sg:postcode":"17268",
    "sg:province":"PA",
    "sg:tags":[
        "roofing",
        "contractor"
    ],
    "wof:name":"Bonded Applicators Inc",
    "wof:placetype":"venue"
},
  "geometry": {"coordinates":[-77.57726,39.755322],"type":"Point"}
}