{
  "type": "Feature",
  "properties": {
    "iso:country":"US",
    "sg:address":"512 Township Line Rd",
    "sg:city":"Plymouth Meeting",
    "sg:classifiers":[
        {
            "category":"Insurance",
            "subcategory":"Insurance Agent",
            "type":"Services"
        }
    ],
    "sg:phone":"+1 215 591 2900",
    "sg:postcode":"19462",
    "sg:province":"PA",
    "sg:website":"www.thezenith.com",
    "wof:name":"Zenith Insurance Co",
    "wof:placetype":"venue"
},
  "geometry": {"coordinates":[-75.27295700000001,40.128792],"type":"Point"}
}