{
  "type": "Feature",
  "properties": {
    "iso:country":"US",
    "sg:address":"450 W Walnut St",
    "sg:city":"Lancaster",
    "sg:classifiers":[
        {
            "category":"Shopping",
            "subcategory":"Clothing, Apparel, & Fashions",
            "type":"Retail Goods"
        }
    ],
    "sg:phone":"+1   ",
    "sg:postcode":"17603",
    "sg:province":"PA",
    "wof:name":"Mens Studio",
    "wof:placetype":"venue"
},
  "geometry": {"coordinates":[-76.315207,40.041806],"type":"Point"}
}