{
  "type": "Feature",
  "properties": {
    "iso:country":"US",
    "sg:address":"3157 Lincoln Hwy E",
    "sg:city":"Paradise",
    "sg:classifiers":[
        {
            "category":"Building & Trades",
            "subcategory":"Plumbing",
            "type":"Services"
        }
    ],
    "sg:phone":"+1   ",
    "sg:postcode":"17562",
    "sg:province":"PA",
    "sg:tags":[
        "contractor"
    ],
    "wof:name":"Snader Company Inc",
    "wof:placetype":"venue"
},
  "geometry": {"coordinates":[-76.126885,40.009516],"type":"Point"}
}