{
  "type": "Feature",
  "properties": {
    "addr:full":"608 New St Roaring Spring PA 16673",
    "addr:housenumber":"608",
    "addr:postcode":"16673",
    "addr:street":"New St",
    "iso:country":"US",
    "sg:address":"608 New St",
    "sg:city":"Roaring Spring",
    "sg:classifiers":[
        {
            "category":"Autos & Motor Vehicles",
            "subcategory":"Automobile Sales",
            "type":"Retail Goods"
        }
    ],
    "sg:phone":"+1 814 224 4248",
    "sg:postcode":"16673",
    "sg:province":"PA",
    "sg:tags":[
        "performance",
        "race",
        "dealer"
    ],
    "wof:name":"Corle Enterprise",
    "wof:placetype":"venue"
},
  "geometry": {"coordinates":[-78.39618900000001,40.33427],"type":"Point"}
}