{
  "type": "Feature",
  "properties": {
    "iso:country":"US",
    "sg:address":"2416 Trewigtown Rd",
    "sg:city":"Colmar",
    "sg:classifiers":[
        {
            "category":"Arts & Performance",
            "subcategory":"Music",
            "type":"Entertainment"
        }
    ],
    "sg:phone":"+1 866 997 7688",
    "sg:postcode":"18915",
    "sg:province":"PA",
    "sg:tags":[
        "dj"
    ],
    "wof:name":"Marlin Disc Jockeys",
    "wof:placetype":"venue"
},
  "geometry": {"coordinates":[-75.268045,40.270444],"type":"Point"}
}