{
  "type": "Feature",
  "properties": {
    "addr:full":"15 Enterprise St Dickson City PA 18519",
    "addr:housenumber":"15",
    "addr:postcode":"18519",
    "addr:street":"Enterprise St",
    "iso:country":"US",
    "sg:address":"15 Enterprise St",
    "sg:city":"Dickson City",
    "sg:classifiers":[
        {
            "category":"Wholesale",
            "subcategory":"Machinery & Supplies",
            "type":"Manufacturing & Wholesale Goods"
        }
    ],
    "sg:phone":"+1 570 489 8211",
    "sg:postcode":"18519",
    "sg:province":"PA",
    "sg:tags":[
        "equipment",
        "excavating"
    ],
    "wof:name":"Jackson Crushed Stone Inc",
    "wof:placetype":"venue"
},
  "geometry": {"coordinates":[-75.623045,41.45795],"type":"Point"}
}