{
  "type": "Feature",
  "properties": {
    "addr:full":"293 Beaver St Hastings PA 16646",
    "addr:housenumber":"293",
    "addr:postcode":"16646",
    "addr:street":"Beaver St",
    "iso:country":"US",
    "sg:address":"293 Beaver St",
    "sg:city":"Hastings",
    "sg:classifiers":[
        {
            "category":"Organizations",
            "subcategory":"Community Association",
            "type":"Services"
        }
    ],
    "sg:phone":"+1 814 247 6666",
    "sg:postcode":"16646",
    "sg:province":"PA",
    "sg:tags":[
        "club"
    ],
    "wof:name":"Veterans Of Foreign Wars",
    "wof:placetype":"venue"
},
  "geometry": {"coordinates":[-78.7137,40.663852],"type":"Point"}
}