{
  "type": "Feature",
  "properties": {
    "iso:country":"US",
    "sg:address":"113 Winchester Ln",
    "sg:city":"Newtown",
    "sg:classifiers":[
        {
            "category":"Communications",
            "subcategory":"Film & Video Production",
            "type":"Services"
        }
    ],
    "sg:phone":"+1   ",
    "sg:postcode":"18940",
    "sg:province":"PA",
    "sg:tags":[
        "multimedia"
    ],
    "wof:name":"Living Room Productions Inc",
    "wof:placetype":"venue"
},
  "geometry": {"coordinates":[-74.943034,40.222918],"type":"Point"}
}