{
  "type": "Feature",
  "properties": {
    "iso:country":"US",
    "sg:address":"4464 Franklin Pike",
    "sg:city":"Cochranton",
    "sg:classifiers":[
        {
            "category":"Travel",
            "subcategory":"Hotels & Motels",
            "type":"Entertainment"
        }
    ],
    "sg:phone":"+1 814 425 2377",
    "sg:postcode":"16314",
    "sg:province":"PA",
    "sg:tags":[
        "breakfast",
        "accommodation",
        "bed"
    ],
    "wof:name":"Smith Mills Coach Stop",
    "wof:placetype":"venue"
},
  "geometry": {"coordinates":[-80.032714,41.526192],"type":"Point"}
}