{
  "type": "Feature",
  "properties": {
    "iso:country":"US",
    "sg:address":"1001 Drexel Hills Blvd",
    "sg:city":"New Cumberland",
    "sg:classifiers":[
        {
            "category":"Wholesale",
            "subcategory":"Stationery",
            "type":"Manufacturing & Wholesale Goods"
        }
    ],
    "sg:phone":"+1 717 774 6611",
    "sg:postcode":"17070",
    "sg:province":"PA",
    "sg:tags":[
        "business",
        "form",
        "system"
    ],
    "wof:name":"Taylor Data Systems",
    "wof:placetype":"venue"
},
  "geometry": {"coordinates":[-76.88436799999999,40.227],"type":"Point"}
}