{
  "type": "Feature",
  "properties": {
    "iso:country":"US",
    "sg:address":"140 Woodlyn Ln N",
    "sg:city":"Honesdale",
    "sg:classifiers":[
        {
            "category":"Recreation",
            "type":"Entertainment"
        }
    ],
    "sg:phone":"+1   ",
    "sg:postcode":"18431",
    "sg:province":"PA",
    "sg:tags":[
        "club",
        "membership"
    ],
    "wof:name":"Royal Arch Chapter",
    "wof:placetype":"venue"
},
  "geometry": {"coordinates":[-75.266036,41.527787],"type":"Point"}
}