{
  "type": "Feature",
  "properties": {
    "iso:country":"US",
    "sg:address":"1660 S Cameron St",
    "sg:city":"Harrisburg",
    "sg:classifiers":[
        {
            "category":"Professional",
            "subcategory":"Business Services",
            "type":"Services"
        }
    ],
    "sg:phone":"+1 717 234 3274",
    "sg:postcode":"17104",
    "sg:province":"PA",
    "sg:tags":[
        "delivery",
        "courier"
    ],
    "sg:website":"www.dasherinc.com",
    "wof:name":"Dasher Inc",
    "wof:placetype":"venue"
},
  "geometry": {"coordinates":[-76.857697,40.242802],"type":"Point"}
}