{
  "type": "Feature",
  "properties": {
    "iso:country":"US",
    "sg:address":"10472 Clay Lick Rd",
    "sg:city":"Mercersburg",
    "sg:classifiers":[
        {
            "category":"Building & Trades",
            "subcategory":"Construction",
            "type":"Services"
        }
    ],
    "sg:phone":"+1   ",
    "sg:postcode":"17236",
    "sg:province":"PA",
    "sg:tags":[
        "contractor"
    ],
    "wof:name":"Dean A Heinbaugh",
    "wof:placetype":"venue"
},
  "geometry": {"coordinates":[-77.90099600000001,39.767693],"type":"Point"}
}