{
  "type": "Feature",
  "properties": {
    "addr:full":"2964 Lycoming Creek Rd Williamsport PA 17701",
    "addr:housenumber":"2964",
    "addr:postcode":"17701",
    "addr:street":"Lycoming Creek Rd",
    "iso:country":"US",
    "sg:address":"2964 Lycoming Creek Rd",
    "sg:city":"Williamsport",
    "sg:classifiers":[
        {
            "category":"Autos & Motor Vehicles",
            "subcategory":"Auto Supplies",
            "type":"Retail Goods"
        }
    ],
    "sg:phone":"+1 570 494 1318",
    "sg:postcode":"17701",
    "sg:province":"PA",
    "sg:tags":[
        "automotive",
        "r",
        "tire"
    ],
    "wof:name":"K & W Tire Company Inc",
    "wof:placetype":"venue"
},
  "geometry": {"coordinates":[-77.054225,41.283873],"type":"Point"}
}