{
  "type": "Feature",
  "properties": {
    "iso:country":"US",
    "sg:address":"1510 Ligonier St",
    "sg:city":"Latrobe",
    "sg:classifiers":[
        {
            "category":"Shopping",
            "subcategory":"Clothing, Apparel, & Fashions",
            "type":"Retail Goods"
        }
    ],
    "sg:phone":"+1 724 539 9285",
    "sg:postcode":"15650",
    "sg:province":"PA",
    "sg:tags":[
        "tailor"
    ],
    "wof:name":"Kim's Sewing",
    "wof:placetype":"venue"
},
  "geometry": {"coordinates":[-79.380126,40.312765],"type":"Point"}
}