{
  "type": "Feature",
  "properties": {
    "iso:country":"US",
    "sg:address":"112 Koser Rd",
    "sg:city":"Lititz",
    "sg:classifiers":[
        {
            "category":"Wholesale",
            "subcategory":"Machinery & Supplies",
            "type":"Manufacturing & Wholesale Goods"
        }
    ],
    "sg:phone":"+1   ",
    "sg:postcode":"17543",
    "sg:province":"PA",
    "sg:tags":[
        "equipment"
    ],
    "wof:name":"Bobcat Showroom",
    "wof:placetype":"venue"
},
  "geometry": {"coordinates":[-76.312006,40.121448],"type":"Point"}
}