{
  "type": "Feature",
  "properties": {
    "addr:full":"101 Beechwood Ln Greentown PA 18426",
    "addr:housenumber":"101",
    "addr:postcode":"18426",
    "addr:street":"Beechwood Ln",
    "iso:country":"US",
    "sg:address":"101 Beechwood Ln",
    "sg:city":"Greentown",
    "sg:classifiers":[
        {
            "category":"Professional",
            "subcategory":"Accounting & Tax Preparation",
            "type":"Services"
        }
    ],
    "sg:phone":"+1 570 857 1572",
    "sg:postcode":"18426",
    "sg:province":"PA",
    "sg:tags":[
        "public",
        "accountants-certified"
    ],
    "wof:name":"Carl S Forcheskie Cpa",
    "wof:placetype":"venue"
},
  "geometry": {"coordinates":[-75.235283,41.367229],"type":"Point"}
}