{
  "type": "Feature",
  "properties": {
    "iso:country":"US",
    "sg:address":"52 Washington Ave",
    "sg:city":"Selinsgrove",
    "sg:phone":"+1 570 374 4601",
    "sg:postcode":"17870",
    "sg:province":"PA",
    "wof:name":"Berger' S Auto Repair",
    "wof:placetype":"venue"
},
  "geometry": {"coordinates":[-76.854151,40.814766],"type":"Point"}
}