{
  "type": "Feature",
  "properties": {
    "iso:country":"US",
    "sg:address":"333 W High St",
    "sg:city":"Carlisle",
    "sg:classifiers":[
        {
            "category":"Education",
            "subcategory":"Library",
            "type":"Public Place"
        }
    ],
    "sg:phone":"+1 717 243 5121",
    "sg:postcode":"17013",
    "sg:province":"PA",
    "wof:name":"Boyd Lee Spahr Library",
    "wof:placetype":"venue"
},
  "geometry": {"coordinates":[-77.198171,40.202296],"type":"Point"}
}