{
  "type": "Feature",
  "properties": {
    "iso:country":"US",
    "sg:address":"2413 Yellow Springs Rd",
    "sg:city":"Malvern",
    "sg:classifiers":[
        {
            "category":"Utilities",
            "subcategory":"Fuel Oil & Lpg",
            "type":"Services"
        }
    ],
    "sg:phone":"+1   ",
    "sg:postcode":"19355",
    "sg:province":"PA",
    "sg:tags":[
        "plumbing",
        "dealer",
        "pl"
    ],
    "wof:name":"Haly Oil Co Inc",
    "wof:placetype":"venue"
},
  "geometry": {"coordinates":[-75.522777,40.072718],"type":"Point"}
}