{
  "type": "Feature",
  "properties": {
    "iso:country":"US",
    "sg:address":"131 E Main St",
    "sg:city":"Bath",
    "sg:classifiers":[
        {
            "category":"Shopping",
            "subcategory":"Gifts & Souvenirs",
            "type":"Retail Goods"
        }
    ],
    "sg:phone":"+1 610 837 8230",
    "sg:postcode":"18014",
    "sg:province":"PA",
    "wof:name":"K T S Racing Store",
    "wof:placetype":"venue"
},
  "geometry": {"coordinates":[-75.39228199999999,40.725292],"type":"Point"}
}