{
  "type": "Feature",
  "properties": {
    "addr:full":"751 Pittsburgh McKeesport Blvd Dravosburg PA 15122",
    "addr:housenumber":"751",
    "addr:postcode":"15122",
    "addr:street":"Pittsburgh Mckeesport Blvd",
    "iso:country":"US",
    "sg:address":"751 Pittsburgh McKeesport Blvd",
    "sg:city":"Dravosburg",
    "sg:classifiers":[
        {
            "category":"Restaurant",
            "type":"Food & Drink"
        }
    ],
    "sg:phone":"+1 412 466 8774",
    "sg:postcode":"15122",
    "sg:province":"PA",
    "wof:name":"Subway Sandwiches & Salads",
    "wof:placetype":"venue"
},
  "geometry": {"coordinates":[-79.89707,40.354485],"type":"Point"}
}