{
  "type": "Feature",
  "properties": {
    "iso:country":"US",
    "sg:address":"4450 Oakhurst Blvd",
    "sg:city":"Harrisburg",
    "sg:classifiers":[
        {
            "category":"Food & Beverages",
            "subcategory":"Groceries & Convenience Stores",
            "type":"Retail Goods"
        }
    ],
    "sg:phone":"+1 717 652 7795",
    "sg:postcode":"17110",
    "sg:province":"PA",
    "sg:website":"http://www.giantfoodstores.com",
    "wof:name":"Giant Food",
    "wof:placetype":"venue"
},
  "geometry": {"coordinates":[-76.84895400000001,40.333441],"type":"Point"}
}