{
  "type": "Feature",
  "properties": {
    "iso:country":"US",
    "sg:address":"15 Linden St",
    "sg:city":"Leola",
    "sg:classifiers":[
        {
            "category":"Freight",
            "type":"Transportation"
        }
    ],
    "sg:phone":"+1   ",
    "sg:postcode":"17540",
    "sg:province":"PA",
    "sg:tags":[
        "special"
    ],
    "wof:name":"Linden Street Storage",
    "wof:placetype":"venue"
},
  "geometry": {"coordinates":[-76.20376899999999,40.087028],"type":"Point"}
}