{
  "type": "Feature",
  "properties": {
    "addr:full":"3001 Stokley St Philadelphia PA 19129",
    "addr:housenumber":"3001",
    "addr:postcode":"19129",
    "addr:street":"Stokley St",
    "iso:country":"US",
    "sg:address":"3001 Stokley St",
    "sg:city":"Philadelphia",
    "sg:classifiers":[
        {
            "category":"Professional",
            "type":"Services"
        }
    ],
    "sg:phone":"+1 215 843 4481",
    "sg:postcode":"19129",
    "sg:province":"PA",
    "sg:tags":[
        "establishment"
    ],
    "wof:name":"Cars R Us Intl Inc",
    "wof:placetype":"venue"
},
  "geometry": {"coordinates":[-75.17440999999999,40.012834],"type":"Point"}
}