{
  "type": "Feature",
  "properties": {
    "addr:full":"1520 Green St Philadelphia PA 19130",
    "addr:housenumber":"1520",
    "addr:postcode":"19130",
    "addr:street":"Green St",
    "iso:country":"US",
    "sg:address":"1520 Green St",
    "sg:city":"Philadelphia",
    "sg:classifiers":[
        {
            "category":"Organizations",
            "subcategory":"Religious Organization",
            "type":"Services"
        }
    ],
    "sg:phone":"+1 215 567 4332",
    "sg:postcode":"19130",
    "sg:province":"PA",
    "sg:tags":[
        "church"
    ],
    "wof:name":"Christ Evangelical & Reformed",
    "wof:placetype":"venue"
},
  "geometry": {"coordinates":[-75.16414,39.964082],"type":"Point"}
}