{
  "type": "Feature",
  "properties": {
    "addr:full":"320 Opre Ave Grove City PA 16127",
    "addr:housenumber":"320",
    "addr:postcode":"16127",
    "addr:street":"Opre Ave",
    "iso:country":"US",
    "sg:address":"320 Opre Ave",
    "sg:city":"Grove City",
    "sg:classifiers":[
        {
            "category":"Personal",
            "subcategory":"Beauty Salon",
            "type":"Services"
        }
    ],
    "sg:phone":"+1 724 458 7151",
    "sg:postcode":"16127",
    "sg:province":"PA",
    "sg:tags":[
        "shop"
    ],
    "wof:name":"Hair Emporium",
    "wof:placetype":"venue"
},
  "geometry": {"coordinates":[-80.07844,41.165255],"type":"Point"}
}