{
  "type": "Feature",
  "properties": {
    "iso:country":"US",
    "sg:address":"16069 Lynn Rd",
    "sg:city":"Saegertown",
    "sg:classifiers":[
        {
            "category":"Wholesale",
            "subcategory":"Machinery & Supplies",
            "type":"Manufacturing & Wholesale Goods"
        }
    ],
    "sg:phone":"+1 814 573 6514",
    "sg:postcode":"16433",
    "sg:province":"PA",
    "sg:tags":[
        "designed",
        "specially"
    ],
    "wof:name":"Jones Machine & Assembly",
    "wof:placetype":"venue"
},
  "geometry": {"coordinates":[-80.1858,41.688308],"type":"Point"}
}