{
  "type": "Feature",
  "properties": {
    "iso:country":"US",
    "sg:address":"30 North St",
    "sg:city":"Mc Sherrystown",
    "sg:classifiers":[
        {
            "category":"Home & Garden",
            "subcategory":"Building Materials",
            "type":"Retail Goods"
        }
    ],
    "sg:phone":"+1 717 637 6237",
    "sg:postcode":"17344",
    "sg:province":"PA",
    "sg:tags":[
        "paint"
    ],
    "wof:name":"Shirk's Paint & Glass",
    "wof:placetype":"venue"
},
  "geometry": {"coordinates":[-77.028431,39.800964],"type":"Point"}
}