{
  "type": "Feature",
  "properties": {
    "addr:full":"1865 Easton Rd Willow Grove PA 19090",
    "addr:housenumber":"1865",
    "addr:postcode":"19090",
    "addr:street":"Easton Rd",
    "iso:country":"US",
    "sg:address":"1865 Easton Rd",
    "sg:city":"Willow Grove",
    "sg:classifiers":[
        {
            "category":"Restaurant",
            "type":"Food & Drink"
        }
    ],
    "sg:menulink":"http://www.allmenus.com/pa/abington/211262-kfc---kentucky-fried-chicken/menu/",
    "sg:phone":"+1 215 658 1000",
    "sg:postcode":"19090",
    "sg:province":"PA",
    "sg:tags":[
        "american",
        "chicken"
    ],
    "wof:name":"KFC - Kentucky Fried Chicken",
    "wof:placetype":"venue"
},
  "geometry": {"coordinates":[-75.11937399999999,40.138872],"type":"Point"}
}