{
  "type": "Feature",
  "properties": {
    "addr:full":"294 W College Ave Pleasant Gap PA 16823",
    "addr:housenumber":"294",
    "addr:postcode":"16823",
    "addr:street":"W College Ave Pleasant",
    "iso:country":"US",
    "sg:address":"294 W College Ave",
    "sg:city":"Pleasant Gap",
    "sg:classifiers":[
        {
            "category":"Building & Trades",
            "subcategory":"Cleaning & Sanitation",
            "type":"Services"
        }
    ],
    "sg:phone":"+1 814 364 1379",
    "sg:postcode":"16823",
    "sg:province":"PA",
    "sg:tags":[
        "fireplace",
        "chimney"
    ],
    "wof:name":"Sootslayer Chimney Sweeps",
    "wof:placetype":"venue"
},
  "geometry": {"coordinates":[-77.750906,40.864646],"type":"Point"}
}