{
  "type": "Feature",
  "properties": {
    "addr:full":"2300 Bald Mountain Rd Bear Creek Twp PA 18702",
    "addr:housenumber":"2300",
    "addr:postcode":"18702",
    "addr:street":"Bald Mountain Rd",
    "iso:country":"US",
    "sg:address":"2300 Bald Mountain Rd",
    "sg:city":"Bear Creek Twp",
    "sg:classifiers":[
        {
            "category":"Building & Trades",
            "subcategory":"Construction",
            "type":"Services"
        }
    ],
    "sg:phone":"+1 570 822 3552",
    "sg:postcode":"18702",
    "sg:province":"PA",
    "sg:tags":[
        "house",
        "contractor",
        "roofing"
    ],
    "wof:name":"George Oko Construction",
    "wof:placetype":"venue"
},
  "geometry": {"coordinates":[-75.72730799999999,41.246262],"type":"Point"}
}