{
  "type": "Feature",
  "properties": {
    "addr:full":"318 E Market St Danville PA 17821",
    "addr:housenumber":"318",
    "addr:postcode":"17821",
    "addr:street":"E Market St",
    "iso:country":"US",
    "sg:address":"318 E Market St",
    "sg:city":"Danville",
    "sg:classifiers":[
        {
            "category":"Professional",
            "subcategory":"Advertising",
            "type":"Services"
        }
    ],
    "sg:phone":"+1 570 275 4812",
    "sg:postcode":"17821",
    "sg:province":"PA",
    "wof:name":"John Hagenbuch",
    "wof:placetype":"venue"
},
  "geometry": {"coordinates":[-76.615003,40.958786],"type":"Point"}
}