{
  "type": "Feature",
  "properties": {
    "addr:full":"2101 Pine St Philadelphia PA 19103",
    "addr:housenumber":"2101",
    "addr:postcode":"19103",
    "addr:street":"Pine St",
    "iso:country":"US",
    "sg:address":"2101 Pine St",
    "sg:city":"Philadelphia",
    "sg:classifiers":[
        {
            "category":"Professional",
            "subcategory":"Lawyer & Legal Services",
            "type":"Services"
        }
    ],
    "sg:phone":"+1 215 731 0600",
    "sg:postcode":"19103",
    "sg:province":"PA",
    "wof:name":"Meyers Lincoln & Assoc",
    "wof:placetype":"venue"
},
  "geometry": {"coordinates":[-75.176517,39.947116],"type":"Point"}
}