{
  "type": "Feature",
  "properties": {
    "iso:country":"US",
    "sg:address":"6924 Market St",
    "sg:city":"Upper Darby",
    "sg:classifiers":[
        {
            "category":"Shopping",
            "subcategory":"Bicycles & Sporting Goods",
            "type":"Retail Goods"
        }
    ],
    "sg:phone":"+1 610 352 9422",
    "sg:postcode":"19082",
    "sg:province":"PA",
    "wof:name":"Samsun Sportswear",
    "wof:placetype":"venue"
},
  "geometry": {"coordinates":[-75.259697,39.961899],"type":"Point"}
}