{
  "type": "Feature",
  "properties": {
    "addr:full":"1585 Upper Bermudian Rd Gardners PA 17324",
    "addr:housenumber":"1585",
    "addr:postcode":"17324",
    "addr:street":"Upper Bermudian Rd",
    "iso:country":"US",
    "sg:address":"1585 Upper Bermudian Rd",
    "sg:city":"Gardners",
    "sg:classifiers":[
        {
            "category":"Building & Trades",
            "subcategory":"Construction",
            "type":"Services"
        }
    ],
    "sg:phone":"+1 717 528 4363",
    "sg:postcode":"17324",
    "sg:province":"PA",
    "sg:tags":[
        "general",
        "contractor"
    ],
    "wof:name":"Mentzer's Trim Co",
    "wof:placetype":"venue"
},
  "geometry": {"coordinates":[-77.176365,39.989141],"type":"Point"}
}