{
  "type": "Feature",
  "properties": {
    "addr:full":"1087 2nd Street Pike Richboro PA 18954",
    "addr:housenumber":"1087",
    "addr:postcode":"18954",
    "addr:street":"2Nd Street Pike",
    "iso:country":"US",
    "sg:address":"1087 2nd Street Pike",
    "sg:city":"Richboro",
    "sg:classifiers":[
        {
            "category":"Banks & Credit Unions",
            "subcategory":"Investment Brokerage",
            "type":"Services"
        },
        {
            "category":"Banks & Credit Unions",
            "subcategory":"Financial Services",
            "type":"Services"
        }
    ],
    "sg:phone":"+1 215 281 6311",
    "sg:postcode":"18954",
    "sg:province":"PA",
    "sg:tags":[
        "advisory",
        "planner"
    ],
    "wof:name":"Jmf Investments",
    "wof:placetype":"venue"
},
  "geometry": {"coordinates":[-75.01037100000001,40.218042],"type":"Point"}
}