{
  "type": "Feature",
  "properties": {
    "addr:full":"315 Bailey Ave Uniontown PA 15401",
    "addr:housenumber":"315",
    "addr:postcode":"15401",
    "addr:street":"Bailey Ave",
    "iso:country":"US",
    "sg:address":"315 Bailey Ave",
    "sg:city":"Uniontown",
    "sg:classifiers":[
        {
            "category":"Freight",
            "type":"Transportation"
        }
    ],
    "sg:phone":"+1 724 832 3766",
    "sg:postcode":"15401",
    "sg:province":"PA",
    "sg:tags":[
        "distance",
        "hauling",
        "long"
    ],
    "wof:name":"Parks Moving & Storage Inc",
    "wof:placetype":"venue"
},
  "geometry": {"coordinates":[-79.712853,39.91068],"type":"Point"}
}