{
  "type": "Feature",
  "properties": {
    "addr:full":"234 Mill St Bristol PA 19007",
    "addr:housenumber":"234",
    "addr:postcode":"19007",
    "addr:street":"Mill St",
    "iso:country":"US",
    "sg:address":"234 Mill St",
    "sg:city":"Bristol",
    "sg:classifiers":[
        {
            "category":"Professional",
            "subcategory":"Lawyer & Legal Services",
            "type":"Services"
        }
    ],
    "sg:phone":"+1   ",
    "sg:postcode":"19007",
    "sg:province":"PA",
    "wof:name":"Sowerbutts David J & Assoc PC",
    "wof:placetype":"venue"
},
  "geometry": {"coordinates":[-74.857707,40.095262],"type":"Point"}
}