{
  "type": "Feature",
  "properties": {
    "addr:full":"47 W Church St Uniontown PA 15401",
    "addr:housenumber":"47",
    "addr:postcode":"15401",
    "addr:street":"W Church St",
    "iso:country":"US",
    "sg:address":"47 W Church St",
    "sg:city":"Uniontown",
    "sg:classifiers":[
        {
            "category":"Shopping",
            "type":"Retail Goods"
        }
    ],
    "sg:phone":"+1 724 437 1440",
    "sg:postcode":"15401",
    "sg:province":"PA",
    "sg:tags":[
        "trophy",
        "medal",
        "award"
    ],
    "wof:name":"Lash Sporting Goods Awards Co",
    "wof:placetype":"venue"
},
  "geometry": {"coordinates":[-79.725784,39.900065],"type":"Point"}
}