{
  "type": "Feature",
  "properties": {
    "addr:full":"7012 Rising Sun Ave Philadelphia PA 19111",
    "addr:housenumber":"7012",
    "addr:postcode":"19111",
    "addr:street":"Rising Sun Ave",
    "iso:country":"US",
    "sg:address":"7012 Rising Sun Ave",
    "sg:city":"Philadelphia",
    "sg:classifiers":[
        {
            "category":"Real Estate",
            "subcategory":"Real Estate Operator",
            "type":"Services"
        }
    ],
    "sg:phone":"+1   ",
    "sg:postcode":"19111",
    "sg:province":"PA",
    "sg:tags":[
        "building",
        "apartment"
    ],
    "wof:name":"Austin Manor",
    "wof:placetype":"venue"
},
  "geometry": {"coordinates":[-75.08733599999999,40.058094],"type":"Point"}
}