{
  "type": "Feature",
  "properties": {
    "iso:country":"US",
    "sg:address":"511 N Broad St",
    "sg:city":"Philadelphia",
    "sg:classifiers":[
        {
            "category":"Social Services",
            "type":"Services"
        }
    ],
    "sg:phone":"+1 215 238 5800",
    "sg:postcode":"19123",
    "sg:province":"PA",
    "sg:tags":[
        "organization",
        "welfare"
    ],
    "wof:name":"ACS",
    "wof:placetype":"venue"
},
  "geometry": {"coordinates":[-75.16144199999999,39.962171],"type":"Point"}
}