{
  "type": "Feature",
  "properties": {
    "addr:full":"895 Swamp Rd Rushland PA 18925",
    "addr:housenumber":"895",
    "addr:postcode":"18925",
    "addr:street":"Swamp Rd",
    "iso:country":"US",
    "sg:address":"895 Swamp Rd",
    "sg:city":"Rushland",
    "sg:classifiers":[
        {
            "category":"School Buses",
            "type":"Transportation"
        }
    ],
    "sg:phone":"+1   ",
    "sg:postcode":"18925",
    "sg:province":"PA",
    "sg:tags":[
        "contracting"
    ],
    "wof:name":"First Student Inc",
    "wof:placetype":"venue"
},
  "geometry": {"coordinates":[-75.039247,40.269676],"type":"Point"}
}