{
  "type": "Feature",
  "properties": {
    "addr:full":"109 Industrial Dr Warminster PA 18974",
    "addr:housenumber":"109",
    "addr:postcode":"18974",
    "addr:street":"Industrial Dr",
    "iso:country":"US",
    "sg:address":"109 Industrial Dr",
    "sg:city":"Warminster",
    "sg:classifiers":[
        {
            "category":"Manufacturing",
            "subcategory":"Tools & Machinery",
            "type":"Manufacturing & Wholesale Goods"
        }
    ],
    "sg:phone":"+1 215 357 5333",
    "sg:postcode":"18974",
    "sg:province":"PA",
    "sg:tags":[
        "built",
        "mfg",
        "industry",
        "packaging",
        "designed",
        "mach",
        "electric"
    ],
    "sg:website":"www.empindustries.com",
    "wof:name":"Emp Industries Inc",
    "wof:placetype":"venue"
},
  "geometry": {"coordinates":[-75.059855,40.226242],"type":"Point"}
}