{
  "type": "Feature",
  "properties": {
    "addr:full":"5242 Broadlea Dr Pittsburgh PA 15236",
    "addr:housenumber":"5242",
    "addr:postcode":"15236",
    "addr:street":"Broadlea Dr",
    "iso:country":"US",
    "sg:address":"5242 Broadlea Dr",
    "sg:city":"Pittsburgh",
    "sg:classifiers":[
        {
            "category":"Professional",
            "subcategory":"Accounting & Tax Preparation",
            "type":"Services"
        }
    ],
    "sg:phone":"+1 412 953 0496",
    "sg:postcode":"15236",
    "sg:province":"PA",
    "sg:tags":[
        "accountant"
    ],
    "wof:name":"Monica L Rockwell CPA",
    "wof:placetype":"venue"
},
  "geometry": {"coordinates":[-79.987077,40.342807],"type":"Point"}
}