{
  "type": "Feature",
  "properties": {
    "iso:country":"US",
    "sg:address":"999 8th Ave",
    "sg:city":"Glenshaw",
    "sg:classifiers":[
        {
            "category":"Wholesale",
            "subcategory":"Machinery & Supplies",
            "type":"Manufacturing & Wholesale Goods"
        }
    ],
    "sg:phone":"+1   ",
    "sg:postcode":"15116",
    "sg:province":"PA",
    "sg:tags":[
        "industrial"
    ],
    "wof:name":"Anixter",
    "wof:placetype":"venue"
},
  "geometry": {"coordinates":[-79.964409,40.543897],"type":"Point"}
}