{
  "type": "Feature",
  "properties": {
    "iso:country":"US",
    "sg:address":"525 S Front St",
    "sg:city":"Harrisburg",
    "sg:classifiers":[
        {
            "category":"Restaurant",
            "type":"Food & Drink"
        }
    ],
    "sg:phone":"+1 717 233 1202",
    "sg:postcode":"17104",
    "sg:province":"PA",
    "sg:tags":[
        "pakistani",
        "indian",
        "buffet"
    ],
    "wof:name":"Passage To India",
    "wof:placetype":"venue"
},
  "geometry": {"coordinates":[-76.876701,40.254398],"type":"Point"}
}