{
  "type": "Feature",
  "properties": {
    "iso:country":"US",
    "sg:address":"10 3rd St",
    "sg:city":"Lansdowne",
    "sg:classifiers":[
        {
            "category":"Manufacturing",
            "subcategory":"Printing",
            "type":"Manufacturing & Wholesale Goods"
        }
    ],
    "sg:phone":"+1 610 626 7430",
    "sg:postcode":"19050",
    "sg:province":"PA",
    "sg:tags":[
        "commercial"
    ],
    "wof:name":"Kennedy Printing Co",
    "wof:placetype":"venue"
},
  "geometry": {"coordinates":[-75.25879500000001,39.939723],"type":"Point"}
}