{
  "type": "Feature",
  "properties": {
    "addr:full":"431 Brashears Run Rd Avella PA 15312",
    "addr:housenumber":"431",
    "addr:postcode":"15312",
    "addr:street":"Brashears Run Rd",
    "iso:country":"US",
    "sg:address":"431 Brashears Run Rd",
    "sg:city":"Avella",
    "sg:classifiers":[
        {
            "category":"Freight",
            "type":"Transportation"
        }
    ],
    "sg:phone":"+1 724 587 0218",
    "sg:postcode":"15312",
    "sg:province":"PA",
    "sg:tags":[
        "operator",
        "local",
        "trucking"
    ],
    "wof:name":"Rush Trucking",
    "wof:placetype":"venue"
},
  "geometry": {"coordinates":[-80.509646,40.239827],"type":"Point"}
}