{
  "type": "Feature",
  "properties": {
    "iso:country":"US",
    "sg:address":"300 Pennsylvania Ave",
    "sg:city":"Matamoras",
    "sg:classifiers":[
        {
            "category":"Personal",
            "subcategory":"Beauty Salon",
            "type":"Services"
        }
    ],
    "sg:phone":"+1 570 491 4204",
    "sg:postcode":"18336",
    "sg:province":"PA",
    "wof:name":"Heads Up Hair Salon",
    "wof:placetype":"venue"
},
  "geometry": {"coordinates":[-74.700226,41.368807],"type":"Point"}
}