{
  "type": "Feature",
  "properties": {
    "iso:country":"US",
    "sg:address":"3610 New Rodgers Rd",
    "sg:city":"Levittown",
    "sg:classifiers":[
        {
            "category":"Organizations",
            "subcategory":"Religious Organization",
            "type":"Services"
        }
    ],
    "sg:phone":"+1 215 946 4928",
    "sg:postcode":"19056",
    "sg:province":"PA",
    "sg:tags":[
        "church"
    ],
    "wof:name":"First Baptist Church-Bristol",
    "wof:placetype":"venue"
},
  "geometry": {"coordinates":[-74.883661,40.131657],"type":"Point"}
}