{
  "type": "Feature",
  "properties": {
    "iso:country":"US",
    "sg:address":"4238 Verona Rd",
    "sg:city":"Verona",
    "sg:classifiers":[
        {
            "category":"Professional",
            "type":"Services"
        }
    ],
    "sg:phone":"+1   ",
    "sg:postcode":"15147",
    "sg:province":"PA",
    "wof:name":"Madeline Mc Caskill",
    "wof:placetype":"venue"
},
  "geometry": {"coordinates":[-79.86218100000001,40.467549],"type":"Point"}
}