{
  "type": "Feature",
  "properties": {
    "iso:country":"US",
    "sg:address":"67 Stephania Dr",
    "sg:city":"Middletown",
    "sg:classifiers":[
        {
            "category":"Building & Trades",
            "subcategory":"Cleaning & Sanitation",
            "type":"Services"
        }
    ],
    "sg:phone":"+1 717 944 2820",
    "sg:postcode":"17057",
    "sg:province":"PA",
    "sg:tags":[
        "janitorial"
    ],
    "wof:name":"Clean Technologies",
    "wof:placetype":"venue"
},
  "geometry": {"coordinates":[-76.696686,40.18784],"type":"Point"}
}