{
  "type": "Feature",
  "properties": {
    "addr:full":"310 N 3rd St Harrisburg PA 17101",
    "addr:housenumber":"310",
    "addr:postcode":"17101",
    "addr:street":"N 3Rd St",
    "iso:country":"US",
    "sg:address":"310 N 3rd St",
    "sg:city":"Harrisburg",
    "sg:classifiers":[
        {
            "category":"Manufacturing",
            "subcategory":"Printing",
            "type":"Manufacturing & Wholesale Goods"
        }
    ],
    "sg:phone":"+1 717 238 4717",
    "sg:postcode":"17101",
    "sg:province":"PA",
    "sg:tags":[
        "newspaper"
    ],
    "wof:name":"Downtown Daily Bread",
    "wof:placetype":"venue"
},
  "geometry": {"coordinates":[-76.884417,40.263158],"type":"Point"}
}