{
  "type": "Feature",
  "properties": {
    "iso:country":"US",
    "sg:address":"3520 Saint Lawrence Rd",
    "sg:city":"Flinton",
    "sg:classifiers":[
        {
            "category":"Building & Trades",
            "subcategory":"Construction",
            "type":"Services"
        }
    ],
    "sg:phone":"+1 814 687 3343",
    "sg:postcode":"16640",
    "sg:province":"PA",
    "sg:tags":[
        "welder"
    ],
    "wof:name":"Baum Welding And Auto Repair",
    "wof:placetype":"venue"
},
  "geometry": {"coordinates":[-78.573881,40.718238],"type":"Point"}
}