{
  "type": "Feature",
  "properties": {
    "addr:full":"20 S Valley Rd Paoli PA 19301",
    "addr:housenumber":"20",
    "addr:postcode":"19301",
    "addr:street":"S Valley Rd",
    "iso:country":"US",
    "sg:address":"20 S Valley Rd",
    "sg:city":"Paoli",
    "sg:classifiers":[
        {
            "category":"Building & Trades",
            "subcategory":"Cleaning & Sanitation",
            "type":"Services"
        }
    ],
    "sg:phone":"+1 610 240 9740",
    "sg:postcode":"19301",
    "sg:province":"PA",
    "sg:tags":[
        "janitor",
        "maintenance"
    ],
    "wof:name":"Facility Service Solutions Inc",
    "wof:placetype":"venue"
},
  "geometry": {"coordinates":[-75.483341,40.039835],"type":"Point"}
}