{
  "type": "Feature",
  "properties": {
    "iso:country":"US",
    "sg:address":"338 Walnut St",
    "sg:city":"Danville",
    "sg:classifiers":[
        {
            "category":"Restaurant",
            "type":"Food & Drink"
        }
    ],
    "sg:phone":"+1   ",
    "sg:postcode":"17821",
    "sg:province":"PA",
    "sg:tags":[
        "eating"
    ],
    "wof:name":"L T Evans Place",
    "wof:placetype":"venue"
},
  "geometry": {"coordinates":[-76.61078500000001,40.96258],"type":"Point"}
}