{
  "type": "Feature",
  "properties": {
    "iso:country":"US",
    "sg:address":"740 W Front St Ste A",
    "sg:city":"Berwick",
    "sg:classifiers":[
        {
            "category":"Professional",
            "subcategory":"Business Services",
            "type":"Services"
        }
    ],
    "sg:phone":"+1 570 204 1390",
    "sg:postcode":"18603",
    "sg:province":"PA",
    "sg:tags":[
        "consultant",
        "coach"
    ],
    "wof:name":"Nd Accounting Consulting",
    "wof:placetype":"venue"
},
  "geometry": {"coordinates":[-76.24510100000001,41.050686],"type":"Point"}
}