{
  "type": "Feature",
  "properties": {
    "iso:country":"US",
    "sg:address":"126 Main St",
    "sg:city":"Wellsboro",
    "sg:classifiers":[
        {
            "category":"Professional",
            "subcategory":"Lawyer & Legal Services",
            "type":"Services"
        }
    ],
    "sg:phone":"+1 570 724 4148",
    "sg:postcode":"16901",
    "sg:province":"PA",
    "sg:tags":[
        "attorney",
        "practice"
    ],
    "wof:name":"Walrath, Thomas A Jr Attorney At Law",
    "wof:placetype":"venue"
},
  "geometry": {"coordinates":[-77.303596,41.746269],"type":"Point"}
}