{
  "type": "Feature",
  "properties": {
    "iso:country":"US",
    "sg:address":"127 S State St",
    "sg:city":"Newtown",
    "sg:classifiers":[
        {
            "category":"Insurance",
            "subcategory":"Hazard Insurance",
            "type":"Services"
        },
        {
            "category":"Insurance",
            "subcategory":"Insurance Agent",
            "type":"Services"
        }
    ],
    "sg:phone":"+1 215 860 4811",
    "sg:postcode":"18940",
    "sg:province":"PA",
    "sg:tags":[
        "advisory",
        "sharing",
        "profit",
        "plan",
        "investment",
        "pension"
    ],
    "sg:website":"www.resourcesforretirement.com",
    "wof:name":"Resources For Retirement Plans",
    "wof:placetype":"venue"
},
  "geometry": {"coordinates":[-74.936982,40.22673],"type":"Point"}
}