{
  "type": "Feature",
  "properties": {
    "iso:country":"US",
    "sg:address":"9808 Clark St",
    "sg:city":"Philadelphia",
    "sg:classifiers":[
        {
            "category":"Professional",
            "subcategory":"Detective & Security Services",
            "type":"Services"
        },
        {
            "category":"Utilities",
            "subcategory":"Telephone",
            "type":"Services"
        },
        {
            "category":"Communications",
            "type":"Services"
        },
        {
            "category":"Professional",
            "subcategory":"Computer Services",
            "type":"Services"
        }
    ],
    "sg:phone":"+1 215 525 3223",
    "sg:postcode":"19115",
    "sg:province":"PA",
    "sg:tags":[
        "wire",
        "installation",
        "network",
        "cable",
        "consultant",
        "system",
        "equipment",
        "design"
    ],
    "sg:website":"http://www.nexela.com",
    "wof:name":"Nexela Inc",
    "wof:placetype":"venue"
},
  "geometry": {"coordinates":[-75.02593299999999,40.090977],"type":"Point"}
}