{
  "type": "Feature",
  "properties": {
    "iso:country":"US",
    "sg:address":"2520 Renaissance Blvd",
    "sg:city":"King Of Prussia",
    "sg:classifiers":[
        {
            "category":"Real Estate",
            "subcategory":"Architect",
            "type":"Services"
        }
    ],
    "sg:phone":"+1 610 270 0509",
    "sg:postcode":"19406",
    "sg:province":"PA",
    "wof:name":"B L M C R A Architects",
    "wof:placetype":"venue"
},
  "geometry": {"coordinates":[-75.340272,40.084228],"type":"Point"}
}