{
  "type": "Feature",
  "properties": {
    "iso:country":"US",
    "sg:address":"114 E Diamond St",
    "sg:city":"Butler",
    "sg:classifiers":[
        {
            "category":"Health Services",
            "subcategory":"Doctor",
            "type":"Services"
        },
        {
            "category":"Health Services",
            "subcategory":"Dentist",
            "type":"Services"
        }
    ],
    "sg:phone":"+1 724 282 6100",
    "sg:postcode":"16001",
    "sg:province":"PA",
    "sg:tags":[
        "dentists-oral",
        "physician",
        "maxillofacial",
        "surgeons",
        "surgery",
        "oral"
    ],
    "wof:name":"Kiselica Lawrence D DDS",
    "wof:placetype":"venue"
},
  "geometry": {"coordinates":[-79.894531,40.858601],"type":"Point"}
}