{
  "type": "Feature",
  "properties": {
    "iso:country":"US",
    "sg:address":"2250 N 29th St",
    "sg:city":"Philadelphia",
    "sg:classifiers":[
        {
            "category":"Restaurant",
            "type":"Food & Drink"
        }
    ],
    "sg:phone":"+1 215 236 9955",
    "sg:postcode":"19132",
    "sg:province":"PA",
    "sg:tags":[
        "eating"
    ],
    "wof:name":"Kingstone Restaurant",
    "wof:placetype":"venue"
},
  "geometry": {"coordinates":[-75.179802,39.990799],"type":"Point"}
}