{
  "type": "Feature",
  "properties": {
    "iso:country":"US",
    "sg:address":"1525 Valley Center Pkwy",
    "sg:city":"Bethlehem",
    "sg:classifiers":[
        {
            "category":"Professional",
            "subcategory":"Computer Services",
            "type":"Services"
        }
    ],
    "sg:phone":"+1   ",
    "sg:postcode":"18017",
    "sg:province":"PA",
    "sg:tags":[
        "consulting",
        "programming",
        "custom"
    ],
    "wof:name":"Vertek Corporation",
    "wof:placetype":"venue"
},
  "geometry": {"coordinates":[-75.408283,40.653317],"type":"Point"}
}