{
  "type": "Feature",
  "properties": {
    "iso:country":"US",
    "sg:address":"603 E Dubois Ave",
    "sg:city":"Du Bois",
    "sg:classifiers":[
        {
            "category":"Food & Beverages",
            "subcategory":"Groceries & Convenience Stores",
            "type":"Retail Goods"
        }
    ],
    "sg:phone":"+1   ",
    "sg:postcode":"15801",
    "sg:province":"PA",
    "sg:tags":[
        "station"
    ],
    "wof:name":"Sheetz 63",
    "wof:placetype":"venue"
},
  "geometry": {"coordinates":[-78.74668699999999,41.125375],"type":"Point"}
}