{
  "type": "Feature",
  "properties": {
    "iso:country":"US",
    "sg:address":"32 Brooke St",
    "sg:city":"Uniontown",
    "sg:classifiers":[
        {
            "category":"Retail",
            "subcategory":"Laundry & Dry Cleaning",
            "type":"Services"
        }
    ],
    "sg:phone":"+1 724 438 3394",
    "sg:postcode":"15401",
    "sg:province":"PA",
    "sg:tags":[
        "cleaners",
        "rug",
        "carpet"
    ],
    "wof:name":"Botti Cleaning Svc",
    "wof:placetype":"venue"
},
  "geometry": {"coordinates":[-79.738947,39.891649],"type":"Point"}
}