{
  "type": "Feature",
  "properties": {
    "iso:country":"US",
    "sg:address":"508 W Southern Ave",
    "sg:city":"S Williamsport",
    "sg:classifiers":[
        {
            "category":"Health Services",
            "subcategory":"Chiropractor",
            "type":"Services"
        }
    ],
    "sg:phone":"+1 570 327 0212",
    "sg:postcode":"17702",
    "sg:province":"PA",
    "wof:name":"Morrone Chiropractic Ctr",
    "wof:placetype":"venue"
},
  "geometry": {"coordinates":[-77.001182,41.231156],"type":"Point"}
}