{
  "type": "Feature",
  "properties": {
    "iso:country":"US",
    "sg:address":"169 Boro Line Rd",
    "sg:city":"King Of Prussia",
    "sg:classifiers":[
        {
            "category":"Manufacturing",
            "subcategory":"Tools & Machinery",
            "type":"Manufacturing & Wholesale Goods"
        }
    ],
    "sg:phone":"+1 610 992 9490",
    "sg:postcode":"19406",
    "sg:province":"PA",
    "sg:tags":[
        "distribution",
        "industrial"
    ],
    "sg:website":"www.ftinc.net",
    "wof:name":"Filter Technology",
    "wof:placetype":"venue"
},
  "geometry": {"coordinates":[-75.354882,40.101307],"type":"Point"}
}