{
  "type": "Feature",
  "properties": {
    "addr:full":"30 Cold Springs Dr Manchester PA 17345",
    "addr:housenumber":"30",
    "addr:postcode":"17345",
    "addr:street":"Cold Springs Dr",
    "iso:country":"US",
    "sg:address":"30 Cold Springs Dr",
    "sg:city":"Manchester",
    "sg:classifiers":[
        {
            "category":"Retail",
            "subcategory":"Portrait Studio",
            "type":"Services"
        }
    ],
    "sg:phone":"+1 717 266 0965",
    "sg:postcode":"17345",
    "sg:province":"PA",
    "sg:tags":[
        "photographer"
    ],
    "wof:name":"In The Loupe",
    "wof:placetype":"venue"
},
  "geometry": {"coordinates":[-76.721358,40.065742],"type":"Point"}
}