{
  "type": "Feature",
  "properties": {
    "iso:country":"US",
    "sg:address":"12 Nassau Cir",
    "sg:city":"Reading",
    "sg:classifiers":[
        {
            "category":"Banks & Credit Unions",
            "subcategory":"Bank",
            "type":"Services"
        }
    ],
    "sg:phone":"+1 610 796 2510",
    "sg:postcode":"19607",
    "sg:province":"PA",
    "sg:tags":[
        "loan",
        "real estate"
    ],
    "wof:name":"Swan Mortgage Inc",
    "wof:placetype":"venue"
},
  "geometry": {"coordinates":[-75.914579,40.276976],"type":"Point"}
}