{
  "type": "Feature",
  "properties": {
    "addr:full":"390 Mountain Rd Uniontown PA 15401",
    "addr:housenumber":"390",
    "addr:postcode":"15401",
    "addr:street":"Mountain Rd",
    "iso:country":"US",
    "sg:address":"390 Mountain Rd",
    "sg:city":"Uniontown",
    "sg:classifiers":[
        {
            "category":"Health Services",
            "subcategory":"Nursing And Care Facility",
            "type":"Services"
        }
    ],
    "sg:phone":"+1   ",
    "sg:postcode":"15401",
    "sg:province":"PA",
    "sg:tags":[
        "intermediate"
    ],
    "wof:name":"Kings Personal Care Home",
    "wof:placetype":"venue"
},
  "geometry": {"coordinates":[-79.723207,39.844836],"type":"Point"}
}