{
  "type": "Feature",
  "properties": {
    "iso:country":"US",
    "sg:address":"2270 Hockley Hill Rd",
    "sg:city":"Muncy",
    "sg:classifiers":[
        {
            "category":"Manufacturing",
            "subcategory":"Food",
            "type":"Manufacturing & Wholesale Goods"
        },
        {
            "category":"Farming",
            "subcategory":"Farm",
            "type":"Manufacturing & Wholesale Goods"
        }
    ],
    "sg:phone":"+1 570 649 5832",
    "sg:postcode":"17756",
    "sg:province":"PA",
    "sg:tags":[
        "corn",
        "product"
    ],
    "wof:name":"Miller Luther",
    "wof:placetype":"venue"
},
  "geometry": {"coordinates":[-76.76384,41.131435],"type":"Point"}
}