{
  "type": "Feature",
  "properties": {
    "addr:full":"515 S Ridge Rd Denver PA 17517",
    "addr:housenumber":"515",
    "addr:postcode":"17517",
    "addr:street":"S Ridge Rd",
    "iso:country":"US",
    "sg:address":"515 S Ridge Rd",
    "sg:city":"Denver",
    "sg:classifiers":[
        {
            "category":"Retail",
            "subcategory":"Animal Services",
            "type":"Services"
        }
    ],
    "sg:phone":"+1 717 336 4884",
    "sg:postcode":"17517",
    "sg:province":"PA",
    "sg:tags":[
        "pet",
        "grooming",
        "washing"
    ],
    "wof:name":"Happy Tails Pet Grooming",
    "wof:placetype":"venue"
},
  "geometry": {"coordinates":[-76.118043,40.257985],"type":"Point"}
}