{
  "type": "Feature",
  "properties": {
    "iso:country":"US",
    "sg:address":"2760 Pine Grove Rd",
    "sg:city":"York",
    "sg:classifiers":[
        {
            "category":"Social Services",
            "subcategory":"Adult Care",
            "type":"Services"
        },
        {
            "category":"Health Services",
            "subcategory":"Nursing And Care Facility",
            "type":"Services"
        }
    ],
    "sg:phone":"+1 717 741 1668",
    "sg:postcode":"17403",
    "sg:province":"PA",
    "sg:tags":[
        "home",
        "retirement",
        "community",
        "residential"
    ],
    "wof:name":"Country Meadows Leader Heights",
    "wof:placetype":"venue"
},
  "geometry": {"coordinates":[-76.70860999999999,39.907101],"type":"Point"}
}