{
  "type": "Feature",
  "properties": {
    "addr:full":"50 N 7th St Bangor PA 18013",
    "addr:housenumber":"50",
    "addr:postcode":"18013",
    "addr:street":"N 7Th St",
    "iso:country":"US",
    "sg:address":"50 N 7th St",
    "sg:city":"Bangor",
    "sg:classifiers":[
        {
            "category":"Professional",
            "type":"Services"
        }
    ],
    "sg:phone":"+1 570 588 0965",
    "sg:postcode":"18013",
    "sg:province":"PA",
    "sg:tags":[
        "establishment"
    ],
    "wof:name":"Sean-David Assocs",
    "wof:placetype":"venue"
},
  "geometry": {"coordinates":[-75.213931,40.868304],"type":"Point"}
}