{
  "type": "Feature",
  "properties": {
    "iso:country":"US",
    "sg:address":"4602 Peach St Ste D",
    "sg:city":"Erie",
    "sg:classifiers":[
        {
            "category":"Banks & Credit Unions",
            "subcategory":"Investment Brokerage",
            "type":"Services"
        },
        {
            "category":"Insurance",
            "subcategory":"Hazard Insurance",
            "type":"Services"
        },
        {
            "category":"Professional",
            "subcategory":"Business Services",
            "type":"Services"
        }
    ],
    "sg:phone":"+1 814 868 0858",
    "sg:postcode":"16509",
    "sg:province":"PA",
    "sg:tags":[
        "notary",
        "commercial",
        "public",
        "agent",
        "resume"
    ],
    "sg:website":"http://www.loboins.com",
    "wof:name":"Locastro Bonini Insurance Agency Inc",
    "wof:placetype":"venue"
},
  "geometry": {"coordinates":[-80.087845,42.085592],"type":"Point"}
}