{
  "type": "Feature",
  "properties": {
    "iso:country":"US",
    "sg:address":"2230 W 23rd St",
    "sg:city":"Erie",
    "sg:classifiers":[
        {
            "category":"Home & Garden",
            "subcategory":"Hardware",
            "type":"Retail Goods"
        }
    ],
    "sg:phone":"+1 814 456 2781",
    "sg:postcode":"16506",
    "sg:province":"PA",
    "sg:tags":[
        "tool",
        "used"
    ],
    "wof:name":"Stanley Tool Co",
    "wof:placetype":"venue"
},
  "geometry": {"coordinates":[-80.132471,42.093409],"type":"Point"}
}