{
  "type": "Feature",
  "properties": {
    "addr:full":"619 Otillia St Pittsburgh PA 15210",
    "addr:housenumber":"619",
    "addr:postcode":"15210",
    "addr:street":"Otillia St",
    "iso:country":"US",
    "sg:address":"619 Otillia St",
    "sg:city":"Pittsburgh",
    "sg:classifiers":[
        {
            "category":"Building & Trades",
            "subcategory":"Landscaping Services",
            "type":"Services"
        }
    ],
    "sg:phone":"+1   ",
    "sg:postcode":"15210",
    "sg:province":"PA",
    "wof:name":"Urban Lawn Care",
    "wof:placetype":"venue"
},
  "geometry": {"coordinates":[-79.98079199999999,40.408978],"type":"Point"}
}