{
  "type": "Feature",
  "properties": {
    "iso:country":"US",
    "sg:address":"85 Claremont Ave",
    "sg:city":"Tamaqua",
    "sg:classifiers":[
        {
            "category":"Professional",
            "subcategory":"Business Services",
            "type":"Services"
        }
    ],
    "sg:phone":"+1 570 668 1303",
    "sg:postcode":"18252",
    "sg:province":"PA",
    "sg:tags":[
        "notary"
    ],
    "wof:name":"Kostin's Notary Svc",
    "wof:placetype":"venue"
},
  "geometry": {"coordinates":[-75.97882199999999,40.820224],"type":"Point"}
}