{
  "type": "Feature",
  "properties": {
    "iso:country":"US",
    "sg:address":"2101 Tyson Ave",
    "sg:city":"Philadelphia",
    "sg:classifiers":[
        {
            "category":"Real Estate",
            "subcategory":"Real Estate Services",
            "type":"Services"
        },
        {
            "category":"Banks & Credit Unions",
            "subcategory":"Financial Services",
            "type":"Services"
        }
    ],
    "sg:phone":"+1 215 332 4400",
    "sg:postcode":"19149",
    "sg:province":"PA",
    "sg:tags":[
        "loan",
        "processing"
    ],
    "wof:name":"Concord Mortgage Services",
    "wof:placetype":"venue"
},
  "geometry": {"coordinates":[-75.063187,40.042858],"type":"Point"}
}