{
  "type": "Feature",
  "properties": {
    "addr:full":"3401 Saw Mill Run Blvd Pittsburgh PA 15227",
    "addr:housenumber":"3401",
    "addr:postcode":"15227",
    "addr:street":"Saw Mill Run Blvd",
    "iso:country":"US",
    "sg:address":"3401 Saw Mill Run Blvd",
    "sg:city":"Pittsburgh",
    "sg:classifiers":[
        {
            "category":"Building & Trades",
            "subcategory":"Construction",
            "type":"Services"
        }
    ],
    "sg:phone":"+1   ",
    "sg:postcode":"15227",
    "sg:province":"PA",
    "sg:tags":[
        "bathtub",
        "remodeling",
        "refinishing",
        "contractor"
    ],
    "wof:name":"Dream Maker Bath and Kitchen",
    "wof:placetype":"venue"
},
  "geometry": {"coordinates":[-79.982578,40.374532],"type":"Point"}
}