{
  "type": "Feature",
  "properties": {
    "addr:full":"58 Queen Rd Gordonville PA 17529",
    "addr:housenumber":"58",
    "addr:postcode":"17529",
    "addr:street":"Queen Rd",
    "iso:country":"US",
    "sg:address":"58 Queen Rd",
    "sg:city":"Gordonville",
    "sg:classifiers":[
        {
            "category":"Manufacturing",
            "subcategory":"Wood Products",
            "type":"Manufacturing & Wholesale Goods"
        }
    ],
    "sg:phone":"+1   ",
    "sg:postcode":"17529",
    "sg:province":"PA",
    "sg:tags":[
        "shop"
    ],
    "wof:name":"Mannies Woodshop",
    "wof:placetype":"venue"
},
  "geometry": {"coordinates":[-76.106318,40.034272],"type":"Point"}
}