{
  "type": "Feature",
  "properties": {
    "iso:country":"US",
    "sg:address":"74 Old Ashley Rd",
    "sg:city":"Wilkes Barre",
    "sg:classifiers":[
        {
            "category":"Manufacturing",
            "subcategory":"Signs",
            "type":"Manufacturing & Wholesale Goods"
        }
    ],
    "sg:phone":"+1   ",
    "sg:postcode":"18706",
    "sg:province":"PA",
    "sg:tags":[
        "specialty",
        "mfg"
    ],
    "wof:name":"Razzs Signs",
    "wof:placetype":"venue"
},
  "geometry": {"coordinates":[-75.88703099999999,41.218972],"type":"Point"}
}