{
  "type": "Feature",
  "properties": {
    "addr:full":"7824 Frankford Ave Philadelphia PA 19136",
    "addr:housenumber":"7824",
    "addr:postcode":"19136",
    "addr:street":"Frankford Ave",
    "iso:country":"US",
    "sg:address":"7824 Frankford Ave",
    "sg:city":"Philadelphia",
    "sg:classifiers":[
        {
            "category":"Building & Trades",
            "subcategory":"Construction",
            "type":"Services"
        }
    ],
    "sg:phone":"+1 215 332 0660",
    "sg:postcode":"19136",
    "sg:province":"PA",
    "sg:tags":[
        "contractor"
    ],
    "wof:name":"Joe Friedman Construction Corp",
    "wof:placetype":"venue"
},
  "geometry": {"coordinates":[-75.03116,40.040349],"type":"Point"}
}