{
  "type": "Feature",
  "properties": {
    "iso:country":"US",
    "sg:address":"1546 N 55th St",
    "sg:city":"Philadelphia",
    "sg:classifiers":[
        {
            "category":"Building & Trades",
            "subcategory":"Electrical",
            "type":"Services"
        }
    ],
    "sg:phone":"+1 215 477 4029",
    "sg:postcode":"19131",
    "sg:province":"PA",
    "sg:tags":[
        "electrician",
        "contractor"
    ],
    "wof:name":"Surge Electric",
    "wof:placetype":"venue"
},
  "geometry": {"coordinates":[-75.23161500000001,39.976026],"type":"Point"}
}