{
  "type": "Feature",
  "properties": {
    "iso:country":"US",
    "sg:address":"120 Pennsylvania Ave",
    "sg:city":"Malvern",
    "sg:classifiers":[
        {
            "category":"Building & Trades",
            "subcategory":"Construction",
            "type":"Services"
        }
    ],
    "sg:phone":"+1 610 644 6350",
    "sg:postcode":"19355",
    "sg:province":"PA",
    "sg:tags":[
        "residential",
        "custom",
        "commercial",
        "installation",
        "glass"
    ],
    "wof:name":"Malvern Glass Inc",
    "wof:placetype":"venue"
},
  "geometry": {"coordinates":[-75.51879700000001,40.036817],"type":"Point"}
}