{
  "type": "Feature",
  "properties": {
    "iso:country":"US",
    "sg:address":"316 Ashwood Rd",
    "sg:city":"Springfield",
    "sg:classifiers":[
        {
            "category":"Utilities",
            "type":"Services"
        }
    ],
    "sg:phone":"+1 610 328 4968",
    "sg:postcode":"19064",
    "sg:province":"PA",
    "sg:tags":[
        "management"
    ],
    "wof:name":"Utility Reduction Associates",
    "wof:placetype":"venue"
},
  "geometry": {"coordinates":[-75.342057,39.91823],"type":"Point"}
}