{
  "type": "Feature",
  "properties": {
    "iso:country":"US",
    "sg:address":"39 E Forrest Ave",
    "sg:city":"Shrewsbury",
    "sg:classifiers":[
        {
            "category":"Recreation",
            "type":"Entertainment"
        }
    ],
    "sg:phone":"+1 717 235 6685",
    "sg:postcode":"17361",
    "sg:province":"PA",
    "sg:tags":[
        "martial",
        "arts",
        "instruction"
    ],
    "wof:name":"Kim's Karate",
    "wof:placetype":"venue"
},
  "geometry": {"coordinates":[-76.677874,39.769199],"type":"Point"}
}