{
  "type": "Feature",
  "properties": {
    "iso:country":"US",
    "sg:address":"3500 Extension Ave",
    "sg:city":"Finleyville",
    "sg:classifiers":[
        {
            "category":"Banks & Credit Unions",
            "subcategory":"Bank",
            "type":"Services"
        }
    ],
    "sg:phone":"+1 724 348 7176",
    "sg:postcode":"15332",
    "sg:province":"PA",
    "wof:name":"National City",
    "wof:placetype":"venue"
},
  "geometry": {"coordinates":[-80.0056,40.2533],"type":"Point"}
}