{
  "type": "Feature",
  "properties": {
    "iso:country":"US",
    "sg:address":"124 S 5th St Ste 1",
    "sg:city":"Reading",
    "sg:classifiers":[
        {
            "category":"Professional",
            "subcategory":"Business Services",
            "type":"Services"
        }
    ],
    "sg:phone":"+1 610 376 3566",
    "sg:postcode":"19602",
    "sg:province":"PA",
    "sg:tags":[
        "notary",
        "public"
    ],
    "wof:name":"Downtown Notary Professionals",
    "wof:placetype":"venue"
},
  "geometry": {"coordinates":[-75.927978,40.332682],"type":"Point"}
}