{
  "type": "Feature",
  "properties": {
    "addr:full":"250 Shagbark Dr Cheswick PA 15024",
    "addr:housenumber":"250",
    "addr:postcode":"15024",
    "addr:street":"Shagbark Dr",
    "iso:country":"US",
    "sg:address":"250 Shagbark Dr",
    "sg:city":"Cheswick",
    "sg:classifiers":[
        {
            "category":"Education",
            "subcategory":"College",
            "type":"Public Place"
        }
    ],
    "sg:phone":"+1 724 265 4444",
    "sg:postcode":"15024",
    "sg:province":"PA",
    "wof:name":"AVNC",
    "wof:placetype":"venue"
},
  "geometry": {"coordinates":[-79.850436,40.61459],"type":"Point"}
}