{
  "type": "Feature",
  "properties": {
    "iso:country":"US",
    "sg:address":"596 Devonshire Dr",
    "sg:city":"State College",
    "sg:classifiers":[
        {
            "category":"Banks & Credit Unions",
            "subcategory":"Investment Brokerage",
            "type":"Services"
        }
    ],
    "sg:phone":"+1 814 237 3767",
    "sg:postcode":"16803",
    "sg:province":"PA",
    "sg:tags":[
        "consultant",
        "planning",
        "financial"
    ],
    "wof:name":"Fenchak Financial Svc",
    "wof:placetype":"venue"
},
  "geometry": {"coordinates":[-77.91299600000001,40.796035],"type":"Point"}
}