{
  "type": "Feature",
  "properties": {
    "iso:country":"US",
    "sg:address":"234 W Main St",
    "sg:city":"Leola",
    "sg:classifiers":[
        {
            "category":"Wholesale",
            "subcategory":"Construction Materials",
            "type":"Manufacturing & Wholesale Goods"
        },
        {
            "category":"Building & Trades",
            "subcategory":"Construction",
            "type":"Services"
        }
    ],
    "sg:phone":"+1 717 445 5523",
    "sg:postcode":"17540",
    "sg:province":"PA",
    "sg:tags":[
        "fence",
        "contractor"
    ],
    "wof:name":"Abel Fence",
    "wof:placetype":"venue"
},
  "geometry": {"coordinates":[-76.19923300000001,40.086427],"type":"Point"}
}