{
  "type": "Feature",
  "properties": {
    "iso:country":"US",
    "sg:address":"204 W Chestnut St",
    "sg:city":"Souderton",
    "sg:classifiers":[
        {
            "category":"Building & Trades",
            "subcategory":"Cleaning & Sanitation",
            "type":"Services"
        },
        {
            "category":"Retail",
            "subcategory":"Laundry & Dry Cleaning",
            "type":"Services"
        }
    ],
    "sg:phone":"+1 215 892 6466",
    "sg:postcode":"18964",
    "sg:province":"PA",
    "sg:tags":[
        "cleaner",
        "janitorial",
        "house"
    ],
    "wof:name":"Inspirational Cleaning Services",
    "wof:placetype":"venue"
},
  "geometry": {"coordinates":[-75.326302,40.307331],"type":"Point"}
}