{
  "type": "Feature",
  "properties": {
    "addr:full":"807 Lawnton Ter Glenolden PA 19036",
    "addr:housenumber":"807",
    "addr:postcode":"19036",
    "addr:street":"Lawnton Ter",
    "iso:country":"US",
    "sg:address":"807 Lawnton Ter",
    "sg:city":"Glenolden",
    "sg:classifiers":[
        {
            "category":"Professional",
            "type":"Services"
        }
    ],
    "sg:phone":"+1   ",
    "sg:postcode":"19036",
    "sg:province":"PA",
    "wof:name":"N Thomas Keyon",
    "wof:placetype":"venue"
},
  "geometry": {"coordinates":[-75.29782400000001,39.914595],"type":"Point"}
}