{
  "type": "Feature",
  "properties": {
    "addr:full":"14 Swamp Rd Newtown PA 18940",
    "addr:housenumber":"14",
    "addr:postcode":"18940",
    "addr:street":"Swamp Rd",
    "iso:country":"US",
    "sg:address":"14 Swamp Rd",
    "sg:city":"Newtown",
    "sg:classifiers":[
        {
            "category":"Ice Cream",
            "type":"Food & Drink"
        }
    ],
    "sg:menulink":"http://www.allmenus.com/pa/newtown/234896-ritas-ice-custard-happiness/menu/",
    "sg:phone":"+1 215 968 8668",
    "sg:postcode":"18940",
    "sg:province":"PA",
    "sg:tags":[
        "american"
    ],
    "wof:name":"Rita's Ice Custard Happiness",
    "wof:placetype":"venue"
},
  "geometry": {"coordinates":[-74.93933,40.229413],"type":"Point"}
}