{
  "type": "Feature",
  "properties": {
    "addr:full":"125 Old Route 51 Rd Smock PA 15480",
    "addr:housenumber":"125",
    "addr:postcode":"15480",
    "addr:street":"Old Route 51 Rd",
    "iso:country":"US",
    "sg:address":"125 Old Route 51 Rd",
    "sg:city":"Smock",
    "sg:classifiers":[
        {
            "category":"Restaurant",
            "type":"Food & Drink"
        }
    ],
    "sg:menulink":"http://www.allmenus.com/pa/menallen/133330-subway/menu/",
    "sg:phone":"+1 724 736 0910",
    "sg:postcode":"15480",
    "sg:province":"PA",
    "sg:tags":[
        "american",
        "sandwich"
    ],
    "wof:name":"Subway",
    "wof:placetype":"venue"
},
  "geometry": {"coordinates":[-79.74904600000001,39.956171],"type":"Point"}
}