{
  "type": "Feature",
  "properties": {
    "iso:country":"US",
    "sg:address":"239 N Wales Rd",
    "sg:city":"North Wales",
    "sg:classifiers":[
        {
            "category":"Shopping",
            "subcategory":"Shoes",
            "type":"Retail Goods"
        }
    ],
    "sg:phone":"+1 215 412 8775",
    "sg:postcode":"19446",
    "sg:province":"PA",
    "wof:name":"Journeys",
    "wof:placetype":"venue"
},
  "geometry": {"coordinates":[-75.259462,40.231356],"type":"Point"}
}