{
  "type": "Feature",
  "properties": {
    "addr:full":"12595 Mallick Rd North East PA 16428",
    "addr:housenumber":"12595",
    "addr:postcode":"16428",
    "addr:street":"Mallick Rd",
    "iso:country":"US",
    "sg:address":"12595 Mallick Rd",
    "sg:city":"North East",
    "sg:classifiers":[
        {
            "category":"Organizations",
            "subcategory":"Membership Organization",
            "type":"Services"
        }
    ],
    "sg:phone":"+1   ",
    "sg:postcode":"16428",
    "sg:province":"PA",
    "wof:name":"McGuire Run Association Inc",
    "wof:placetype":"venue"
},
  "geometry": {"coordinates":[-79.761978,42.18372],"type":"Point"}
}