{
  "type": "Feature",
  "properties": {
    "addr:full":"80 Baumbaugh Rd Halifax PA 17032",
    "addr:housenumber":"80",
    "addr:postcode":"17032",
    "addr:street":"Baumbaugh Rd",
    "iso:country":"US",
    "sg:address":"80 Baumbaugh Rd",
    "sg:city":"Halifax",
    "sg:classifiers":[
        {
            "category":"Building & Trades",
            "subcategory":"Construction",
            "type":"Services"
        }
    ],
    "sg:phone":"+1   ",
    "sg:postcode":"17032",
    "sg:province":"PA",
    "sg:tags":[
        "house"
    ],
    "wof:name":"Sheldon L Crum Home Imprvmnts",
    "wof:placetype":"venue"
},
  "geometry": {"coordinates":[-76.868224,40.487279],"type":"Point"}
}