{
  "type": "Feature",
  "properties": {
    "iso:country":"US",
    "sg:address":"19 State St",
    "sg:city":"Belle Vernon",
    "sg:classifiers":[
        {
            "category":"Wholesale",
            "subcategory":"Machinery & Supplies",
            "type":"Manufacturing & Wholesale Goods"
        }
    ],
    "sg:phone":"+1 724 483 0251",
    "sg:postcode":"15012",
    "sg:province":"PA",
    "sg:tags":[
        "equipment",
        "industrial"
    ],
    "sg:website":"www.ellisonic.com",
    "wof:name":"Ellison Industrial Controls",
    "wof:placetype":"venue"
},
  "geometry": {"coordinates":[-79.87259,40.12778],"type":"Point"}
}