{
  "type": "Feature",
  "properties": {
    "iso:country":"US",
    "sg:address":"100 Caruthers Ln",
    "sg:city":"Irwin",
    "sg:classifiers":[
        {
            "category":"Education",
            "subcategory":"Library",
            "type":"Public Place"
        }
    ],
    "sg:phone":"+1 724 863 4700",
    "sg:postcode":"15642",
    "sg:province":"PA",
    "wof:name":"Norwin Public Library",
    "wof:placetype":"venue"
},
  "geometry": {"coordinates":[-79.69906,40.321899],"type":"Point"}
}