{
  "type": "Feature",
  "properties": {
    "addr:full":"4524 Quarry St Whitehall PA 18052",
    "addr:housenumber":"4524",
    "addr:postcode":"18052",
    "addr:street":"Quarry St",
    "iso:country":"US",
    "sg:address":"4524 Quarry St",
    "sg:city":"Whitehall",
    "sg:classifiers":[
        {
            "category":"Retail",
            "subcategory":"Auto Repair",
            "type":"Services"
        }
    ],
    "sg:phone":"+1 610 262 8344",
    "sg:postcode":"18052",
    "sg:province":"PA",
    "sg:tags":[
        "towing"
    ],
    "wof:name":"Precision Auto & Truck Repair Inc",
    "wof:placetype":"venue"
},
  "geometry": {"coordinates":[-75.540199,40.678902],"type":"Point"}
}