{
  "type": "Feature",
  "properties": {
    "iso:country":"US",
    "sg:address":"2 Jackson St",
    "sg:city":"Wellsboro",
    "sg:classifiers":[
        {
            "category":"Food & Beverages",
            "subcategory":"Liquor & Beverages",
            "type":"Retail Goods"
        }
    ],
    "sg:phone":"+1 570 724 1133",
    "sg:postcode":"16901",
    "sg:province":"PA",
    "sg:tags":[
        "alcoholic"
    ],
    "wof:name":"Wells Distributing Co",
    "wof:placetype":"venue"
},
  "geometry": {"coordinates":[-77.28791099999999,41.748408],"type":"Point"}
}