{
  "type": "Feature",
  "properties": {
    "iso:country":"US",
    "sg:address":"121 Hartranft St",
    "sg:city":"Norristown",
    "sg:classifiers":[
        {
            "category":"Professional",
            "subcategory":"Management & Consulting",
            "type":"Services"
        }
    ],
    "sg:phone":"+1   ",
    "sg:postcode":"19401",
    "sg:province":"PA",
    "wof:name":"Fiorini & Co",
    "wof:placetype":"venue"
},
  "geometry": {"coordinates":[-75.363906,40.120233],"type":"Point"}
}