{
  "type": "Feature",
  "properties": {
    "iso:country":"US",
    "sg:address":"202 Miller St",
    "sg:city":"Sayre",
    "sg:classifiers":[
        {
            "category":"Manufacturing",
            "subcategory":"Lumber",
            "type":"Manufacturing & Wholesale Goods"
        }
    ],
    "sg:phone":"+1   ",
    "sg:postcode":"18840",
    "sg:province":"PA",
    "sg:tags":[
        "logging"
    ],
    "wof:name":"Kaminski Logging",
    "wof:placetype":"venue"
},
  "geometry": {"coordinates":[-76.521136,41.976714],"type":"Point"}
}