{
  "type": "Feature",
  "properties": {
    "iso:country":"US",
    "sg:address":"2418 Wilmington Rd",
    "sg:city":"New Castle",
    "sg:classifiers":[
        {
            "category":"Professional",
            "subcategory":"Lawyer & Legal Services",
            "type":"Services"
        }
    ],
    "sg:phone":"+1 724 654 5211",
    "sg:postcode":"16105",
    "sg:province":"PA",
    "sg:tags":[
        "attorney"
    ],
    "wof:name":"Bartholomew & Wish",
    "wof:placetype":"venue"
},
  "geometry": {"coordinates":[-80.353981,41.027912],"type":"Point"}
}