{
  "type": "Feature",
  "properties": {
    "iso:country":"US",
    "sg:address":"1061 Main Street",
    "sg:city":"North Huntigdon",
    "sg:classifiers":[
        {
            "category":"Professional",
            "subcategory":"Research",
            "type":"Services"
        }
    ],
    "sg:phone":"+1 724 861 5510",
    "sg:postcode":"15642",
    "sg:province":"PA",
    "sg:website":"http://www.inspiredtechnologiesinc.com",
    "wof:name":"Inspired Technologies",
    "wof:placetype":"venue"
},
  "geometry": {"coordinates":[-79.71937,40.3178],"type":"Point"}
}