{
  "type": "Feature",
  "properties": {
    "iso:country":"US",
    "sg:address":"102 Denny Rd",
    "sg:city":"Valencia",
    "sg:classifiers":[
        {
            "category":"Retail",
            "subcategory":"Auto Repair",
            "type":"Services"
        }
    ],
    "sg:phone":"+1 724 898 3155",
    "sg:postcode":"16059",
    "sg:province":"PA",
    "wof:name":"Robick's Auto Sales & Service",
    "wof:placetype":"venue"
},
  "geometry": {"coordinates":[-79.936302,40.683399],"type":"Point"}
}