{
  "type": "Feature",
  "properties": {
    "iso:country":"US",
    "sg:address":"304 Anthracite St",
    "sg:city":"Pittston",
    "sg:classifiers":[
        {
            "category":"Banks & Credit Unions",
            "subcategory":"Bank",
            "type":"Services"
        }
    ],
    "sg:phone":"+1   ",
    "sg:postcode":"18643",
    "sg:province":"PA",
    "sg:tags":[
        "broker",
        "mortgage"
    ],
    "wof:name":"Kelex Financial Services",
    "wof:placetype":"venue"
},
  "geometry": {"coordinates":[-75.83629500000001,41.322687],"type":"Point"}
}