{
  "type": "Feature",
  "properties": {
    "iso:country":"US",
    "sg:address":"2243 Darlington Rd",
    "sg:city":"Beaver Falls",
    "sg:classifiers":[
        {
            "category":"Food & Beverages",
            "subcategory":"Fruits & Vegetables",
            "type":"Retail Goods"
        },
        {
            "category":"Wholesale",
            "subcategory":"Fruits & Vegetables",
            "type":"Manufacturing & Wholesale Goods"
        }
    ],
    "sg:phone":"+1 724 846 9717",
    "sg:postcode":"15010",
    "sg:province":"PA",
    "wof:name":"Panellas Chippewa Fruit Market",
    "wof:placetype":"venue"
},
  "geometry": {"coordinates":[-80.35670399999999,40.76678],"type":"Point"}
}