{
  "type": "Feature",
  "properties": {
    "iso:country":"US",
    "sg:address":"6000 Steubenville Pike",
    "sg:city":"Mc Kees Rocks",
    "sg:classifiers":[
        {
            "category":"Health Services",
            "subcategory":"Doctor",
            "type":"Services"
        }
    ],
    "sg:phone":"+1 412 787 7766",
    "sg:postcode":"15136",
    "sg:province":"PA",
    "wof:name":"Chen Anne Pediatrician",
    "wof:placetype":"venue"
},
  "geometry": {"coordinates":[-80.14479799999999,40.444801],"type":"Point"}
}