{
  "type": "Feature",
  "properties": {
    "iso:country":"US",
    "sg:address":"11001 Anthony Hwy",
    "sg:city":"Waynesboro",
    "sg:classifiers":[
        {
            "category":"Insurance",
            "subcategory":"Insurance Agent",
            "type":"Services"
        }
    ],
    "sg:phone":"+1 717 762 5780",
    "sg:postcode":"17268",
    "sg:province":"PA",
    "wof:name":"Advanced Financial Security",
    "wof:placetype":"venue"
},
  "geometry": {"coordinates":[-77.56891,39.772265],"type":"Point"}
}