{
  "type": "Feature",
  "properties": {
    "iso:country":"US",
    "sg:address":"11 Roadway Dr",
    "sg:city":"Carlisle",
    "sg:classifiers":[
        {
            "category":"Professional",
            "subcategory":"Lawyer & Legal Services",
            "type":"Services"
        }
    ],
    "sg:phone":"+1 717 249 5373",
    "sg:postcode":"17015",
    "sg:province":"PA",
    "sg:tags":[
        "attorney"
    ],
    "wof:name":"Hanft & Knight",
    "wof:placetype":"venue"
},
  "geometry": {"coordinates":[-77.11211,40.230613],"type":"Point"}
}