{
  "type": "Feature",
  "properties": {
    "addr:full":"38 S 19th St Philadelphia PA 19103",
    "addr:housenumber":"38",
    "addr:postcode":"19103",
    "addr:street":"S 19Th St",
    "iso:country":"US",
    "sg:address":"38 S 19th St",
    "sg:city":"Philadelphia",
    "sg:classifiers":[
        {
            "category":"Deli",
            "type":"Food & Drink"
        },
        {
            "category":"Food & Beverages",
            "subcategory":"Bakery",
            "type":"Retail Goods"
        }
    ],
    "sg:phone":"+1 215 568 3271",
    "sg:postcode":"19103",
    "sg:province":"PA",
    "sg:tags":[
        "sandwich"
    ],
    "sg:website":"www.famous4thstreetdelicatessen.com",
    "wof:name":"Famous 4th Street Delicatessen",
    "wof:placetype":"venue"
},
  "geometry": {"coordinates":[-75.17205300000001,39.952385],"type":"Point"}
}