{
  "type": "Feature",
  "properties": {
    "addr:full":"309 Main St E Girard PA 16417",
    "addr:housenumber":"309",
    "addr:postcode":"16417",
    "addr:street":"Main St E",
    "iso:country":"US",
    "sg:address":"309 Main St E",
    "sg:city":"Girard",
    "sg:classifiers":[
        {
            "category":"Retail",
            "subcategory":"Funeral Services",
            "type":"Services"
        }
    ],
    "sg:phone":"+1 814 774 4306",
    "sg:postcode":"16417",
    "sg:province":"PA",
    "wof:name":"Daniel R Edder Funeral Home",
    "wof:placetype":"venue"
},
  "geometry": {"coordinates":[-80.311791,42.003754],"type":"Point"}
}