{
  "type": "Feature",
  "properties": {
    "iso:country":"US",
    "sg:address":"422 Washington St",
    "sg:city":"Huntingdon",
    "sg:classifiers":[
        {
            "category":"Restaurant",
            "type":"Food & Drink"
        }
    ],
    "sg:phone":"+1 814 643 5551",
    "sg:postcode":"16652",
    "sg:province":"PA",
    "sg:tags":[
        "eating"
    ],
    "wof:name":"Walt's Cafe",
    "wof:placetype":"venue"
},
  "geometry": {"coordinates":[-78.011456,40.485367],"type":"Point"}
}