{
  "type": "Feature",
  "properties": {
    "iso:country":"US",
    "sg:address":"1233 Claremont Rd",
    "sg:city":"Carlisle",
    "sg:classifiers":[
        {
            "category":"Transit Center",
            "subcategory":"Freight",
            "type":"Transportation"
        },
        {
            "category":"Professional",
            "subcategory":"Business Services",
            "type":"Services"
        }
    ],
    "sg:phone":"+1 717 620 9329",
    "sg:postcode":"17015",
    "sg:province":"PA",
    "sg:tags":[
        "broker",
        "shipping"
    ],
    "wof:name":"4 Freight Solutions",
    "wof:placetype":"venue"
},
  "geometry": {"coordinates":[-77.141597,40.220022],"type":"Point"}
}