{
  "type": "Feature",
  "properties": {
    "iso:country":"US",
    "sg:address":"41 Wagner Dr",
    "sg:city":"Bloomsburg",
    "sg:classifiers":[
        {
            "category":"Farming",
            "subcategory":"Orchard",
            "type":"Manufacturing & Wholesale Goods"
        }
    ],
    "sg:phone":"+1   ",
    "sg:postcode":"17815",
    "sg:province":"PA",
    "sg:tags":[
        "fruit",
        "tree"
    ],
    "wof:name":"Wagner Fruit Farm Inc",
    "wof:placetype":"venue"
},
  "geometry": {"coordinates":[-76.536044,41.017816],"type":"Point"}
}