{
  "type": "Feature",
  "properties": {
    "iso:country":"US",
    "sg:address":"607 Beaver St",
    "sg:city":"Bristol",
    "sg:classifiers":[
        {
            "category":"Professional",
            "subcategory":"Computer Services",
            "type":"Services"
        }
    ],
    "sg:phone":"+1 215 781 1869",
    "sg:postcode":"19007",
    "sg:province":"PA",
    "sg:tags":[
        "website",
        "design"
    ],
    "wof:name":"All The Rave Creative Solutons",
    "wof:placetype":"venue"
},
  "geometry": {"coordinates":[-74.855628,40.103603],"type":"Point"}
}