{
  "type": "Feature",
  "properties": {
    "iso:country":"US",
    "sg:address":"2500 Highland Rd",
    "sg:city":"Hermitage",
    "sg:classifiers":[
        {
            "category":"Government",
            "subcategory":"Office",
            "type":"Public Place"
        }
    ],
    "sg:phone":"+1   ",
    "sg:postcode":"16148",
    "sg:province":"PA",
    "sg:tags":[
        "department",
        "labor"
    ],
    "wof:name":"Vocatnal Rehabilitation Office",
    "wof:placetype":"venue"
},
  "geometry": {"coordinates":[-80.46328699999999,41.239376],"type":"Point"}
}