{
  "type": "Feature",
  "properties": {
    "iso:country":"US",
    "sg:address":"1039 W Trindle Rd",
    "sg:city":"Mechanicsburg",
    "sg:classifiers":[
        {
            "category":"Building & Trades",
            "subcategory":"Landscaping Services",
            "type":"Services"
        },
        {
            "category":"Manufacturing",
            "subcategory":"Paper Products",
            "type":"Manufacturing & Wholesale Goods"
        },
        {
            "category":"Manufacturing",
            "subcategory":"Building Materials",
            "type":"Manufacturing & Wholesale Goods"
        }
    ],
    "sg:phone":"+1 717 766 6751",
    "sg:postcode":"17055",
    "sg:province":"PA",
    "sg:tags":[
        "ponds",
        "designer",
        "garden",
        "consultant",
        "lake",
        "contractor",
        "water",
        "construction",
        "pond",
        "bamboo",
        "landscape"
    ],
    "wof:name":"Burdge's Water Gardens",
    "wof:placetype":"venue"
},
  "geometry": {"coordinates":[-77.05609699999999,40.199508],"type":"Point"}
}