{
  "type": "Feature",
  "properties": {
    "iso:country":"US",
    "sg:address":"7310 Ogontz Ave",
    "sg:city":"Philadelphia",
    "sg:classifiers":[
        {
            "category":"Social Services",
            "subcategory":"Child Care",
            "type":"Services"
        }
    ],
    "sg:phone":"+1 215 224 5805",
    "sg:postcode":"19138",
    "sg:province":"PA",
    "sg:tags":[
        "kindergarten",
        "academic",
        "school"
    ],
    "wof:name":"NIA Learning Ctr",
    "wof:placetype":"venue"
},
  "geometry": {"coordinates":[-75.15536,40.065302],"type":"Point"}
}