{
  "type": "Feature",
  "properties": {
    "addr:full":"335 10th St Saltsburg PA 15681",
    "addr:housenumber":"335",
    "addr:postcode":"15681",
    "addr:street":"10Th St",
    "iso:country":"US",
    "sg:address":"335 10th St",
    "sg:city":"Saltsburg",
    "sg:classifiers":[
        {
            "category":"Building & Trades",
            "subcategory":"Construction",
            "type":"Services"
        }
    ],
    "sg:phone":"+1   ",
    "sg:postcode":"15681",
    "sg:province":"PA",
    "sg:tags":[
        "new",
        "remodeling",
        "home"
    ],
    "wof:name":"A D Construction",
    "wof:placetype":"venue"
},
  "geometry": {"coordinates":[-79.44432999999999,40.491919],"type":"Point"}
}