{
  "type": "Feature",
  "properties": {
    "addr:full":"102 Estate Rd Boyertown PA 19512",
    "addr:housenumber":"102",
    "addr:postcode":"19512",
    "addr:street":"Estate Rd",
    "iso:country":"US",
    "sg:address":"102 Estate Rd",
    "sg:city":"Boyertown",
    "sg:classifiers":[
        {
            "category":"Professional",
            "subcategory":"Computer Services",
            "type":"Services"
        }
    ],
    "sg:phone":"+1 610 473 8730",
    "sg:postcode":"19512",
    "sg:province":"PA",
    "sg:tags":[
        "consultant",
        "designer"
    ],
    "wof:name":"MRO Softare Inc",
    "wof:placetype":"venue"
},
  "geometry": {"coordinates":[-75.62828399999999,40.322924],"type":"Point"}
}