{
  "type": "Feature",
  "properties": {
    "iso:country":"US",
    "sg:address":"2709 16th St",
    "sg:city":"Altoona",
    "sg:classifiers":[
        {
            "category":"Organizations",
            "subcategory":"Religious Organization",
            "type":"Services"
        }
    ],
    "sg:phone":"+1   ",
    "sg:postcode":"16601",
    "sg:province":"PA",
    "wof:name":"Aglow International",
    "wof:placetype":"venue"
},
  "geometry": {"coordinates":[-78.418425,40.521985],"type":"Point"}
}