{
  "type": "Feature",
  "properties": {
    "addr:full":"436 Worthington Dr Mars PA 16046",
    "addr:housenumber":"436",
    "addr:postcode":"16046",
    "addr:street":"Worthington Dr",
    "iso:country":"US",
    "sg:address":"436 Worthington Dr",
    "sg:city":"Mars",
    "sg:classifiers":[
        {
            "category":"Autos & Motor Vehicles",
            "subcategory":"Automobile Sales",
            "type":"Retail Goods"
        }
    ],
    "sg:phone":"+1   ",
    "sg:postcode":"16046",
    "sg:province":"PA",
    "wof:name":"Trostle Oldsmobile",
    "wof:placetype":"venue"
},
  "geometry": {"coordinates":[-80.120322,40.667508],"type":"Point"}
}