{
  "type": "Feature",
  "properties": {
    "iso:country":"US",
    "sg:address":"2901 N Broad St",
    "sg:city":"Philadelphia",
    "sg:classifiers":[
        {
            "category":"Autos & Motor Vehicles",
            "subcategory":"Fuel & Gas Station",
            "type":"Retail Goods"
        }
    ],
    "sg:phone":"+1   ",
    "sg:postcode":"19132",
    "sg:province":"PA",
    "sg:tags":[
        "station",
        "gasoline"
    ],
    "wof:name":"Amerada Hess Corporation",
    "wof:placetype":"venue"
},
  "geometry": {"coordinates":[-75.153781,39.997718],"type":"Point"}
}