{
  "type": "Feature",
  "properties": {
    "addr:full":"2381 Neshaminy Blvd Bensalem PA 19020",
    "addr:housenumber":"2381",
    "addr:postcode":"19020",
    "addr:street":"Neshaminy Blvd",
    "iso:country":"US",
    "sg:address":"2381 Neshaminy Blvd",
    "sg:city":"Bensalem",
    "sg:classifiers":[
        {
            "category":"Personal",
            "type":"Services"
        },
        {
            "category":"Shopping",
            "subcategory":"Bicycles & Sporting Goods",
            "type":"Retail Goods"
        }
    ],
    "sg:phone":"+1 215 752 3223",
    "sg:postcode":"19020",
    "sg:province":"PA",
    "sg:tags":[
        "sewing",
        "alteration"
    ],
    "wof:name":"Dan-El Sporting Goods",
    "wof:placetype":"venue"
},
  "geometry": {"coordinates":[-74.92440000000001,40.132301],"type":"Point"}
}