{
  "type": "Feature",
  "properties": {
    "iso:country":"US",
    "sg:address":"300 N Hanover St",
    "sg:city":"Hershey",
    "sg:classifiers":[
        {
            "category":"Professional",
            "subcategory":"Lawyer & Legal Services",
            "type":"Services"
        }
    ],
    "sg:phone":"+1 717 566 1201",
    "sg:postcode":"17033",
    "sg:province":"PA",
    "sg:tags":[
        "attorney"
    ],
    "wof:name":"Edward J Mimnagh",
    "wof:placetype":"venue"
},
  "geometry": {"coordinates":[-76.682011,40.291326],"type":"Point"}
}