{
  "type": "Feature",
  "properties": {
    "addr:full":"15340 Church Rd Conneaut Lake PA 16316",
    "addr:housenumber":"15340",
    "addr:postcode":"16316",
    "addr:street":"Church Rd",
    "iso:country":"US",
    "sg:address":"15340 Church Rd",
    "sg:city":"Conneaut Lake",
    "sg:classifiers":[
        {
            "category":"Government",
            "subcategory":"Office",
            "type":"Public Place"
        }
    ],
    "sg:phone":"+1 814 382 6959",
    "sg:postcode":"16316",
    "sg:province":"PA",
    "sg:tags":[
        "village"
    ],
    "wof:name":"Greenwood Twp Supervisors",
    "wof:placetype":"venue"
},
  "geometry": {"coordinates":[-80.225882,41.562516],"type":"Point"}
}