{
  "type": "Feature",
  "properties": {
    "addr:full":"5143 William Flynn Hwy Gibsonia PA 15044",
    "addr:housenumber":"5143",
    "addr:postcode":"15044",
    "addr:street":"William Flynn Hwy",
    "iso:country":"US",
    "sg:address":"5143 William Flynn Hwy",
    "sg:city":"Gibsonia",
    "sg:classifiers":[
        {
            "category":"Restaurant",
            "type":"Food & Drink"
        }
    ],
    "sg:menulink":"http://www.allmenus.com/pa/richland/27622-eat-n-park/menu/",
    "sg:phone":"+1 724 443 7280",
    "sg:postcode":"15044",
    "sg:province":"PA",
    "sg:tags":[
        "american",
        "diner"
    ],
    "wof:name":"Eat N' Park",
    "wof:placetype":"venue"
},
  "geometry": {"coordinates":[-79.942296,40.624098],"type":"Point"}
}