{
  "type": "Feature",
  "properties": {
    "addr:full":"389 Tulip Dr New Brighton PA 15066",
    "addr:housenumber":"389",
    "addr:postcode":"15066",
    "addr:street":"Tulip Dr",
    "iso:country":"US",
    "sg:address":"389 Tulip Dr",
    "sg:city":"New Brighton",
    "sg:classifiers":[
        {
            "category":"Wholesale",
            "subcategory":"Auto Parts",
            "type":"Manufacturing & Wholesale Goods"
        }
    ],
    "sg:phone":"+1   ",
    "sg:postcode":"15066",
    "sg:province":"PA",
    "sg:tags":[
        "repair",
        "used",
        "general"
    ],
    "wof:name":"Bumper Mart",
    "wof:placetype":"venue"
},
  "geometry": {"coordinates":[-80.23645399999999,40.757209],"type":"Point"}
}