{
  "type": "Feature",
  "properties": {
    "addr:full":"940 Schoeneck Rd Ephrata PA 17522",
    "addr:housenumber":"940",
    "addr:postcode":"17522",
    "addr:street":"Schoeneck Rd",
    "iso:country":"US",
    "sg:address":"940 Schoeneck Rd",
    "sg:city":"Ephrata",
    "sg:classifiers":[
        {
            "category":"Retail",
            "subcategory":"Animal Services",
            "type":"Services"
        }
    ],
    "sg:phone":"+1 717 733 4544",
    "sg:postcode":"17522",
    "sg:province":"PA",
    "sg:tags":[
        "pet",
        "grooming",
        "washing"
    ],
    "wof:name":"Horton's Boarding Kennels",
    "wof:placetype":"venue"
},
  "geometry": {"coordinates":[-76.17832799999999,40.210387],"type":"Point"}
}