{
  "type": "Feature",
  "properties": {
    "addr:full":"2426 Peach St Erie PA 16502",
    "addr:housenumber":"2426",
    "addr:postcode":"16502",
    "addr:street":"Peach St",
    "iso:country":"US",
    "sg:address":"2426 Peach St",
    "sg:city":"Erie",
    "sg:classifiers":[
        {
            "category":"Bars & Pubs",
            "type":"Food & Drink"
        }
    ],
    "sg:phone":"+1   ",
    "sg:postcode":"16502",
    "sg:province":"PA",
    "sg:tags":[
        "drinking"
    ],
    "wof:name":"Norbs Bar",
    "wof:placetype":"venue"
},
  "geometry": {"coordinates":[-80.0757,42.112485],"type":"Point"}
}