{
  "type": "Feature",
  "properties": {
    "iso:country":"US",
    "sg:address":"328 Fulton St",
    "sg:city":"Sayre",
    "sg:classifiers":[
        {
            "category":"Restaurant",
            "type":"Food & Drink"
        }
    ],
    "sg:phone":"+1   ",
    "sg:postcode":"18840",
    "sg:province":"PA",
    "sg:tags":[
        "eating"
    ],
    "wof:name":"Nocchis Hoagie Stand",
    "wof:placetype":"venue"
},
  "geometry": {"coordinates":[-76.540578,41.992197],"type":"Point"}
}