{
  "type": "Feature",
  "properties": {
    "iso:country":"US",
    "sg:address":"1827 Sanderson Ave",
    "sg:city":"Scranton",
    "sg:classifiers":[
        {
            "category":"Shopping",
            "subcategory":"Bicycles & Sporting Goods",
            "type":"Retail Goods"
        }
    ],
    "sg:phone":"+1 570 963 9377",
    "sg:postcode":"18509",
    "sg:province":"PA",
    "sg:tags":[
        "team"
    ],
    "wof:name":"Tim Wagner's Sports Corner Inc",
    "wof:placetype":"venue"
},
  "geometry": {"coordinates":[-75.648201,41.433028],"type":"Point"}
}