{
  "type": "Feature",
  "properties": {
    "iso:country":"US",
    "sg:address":"1643 Pembrook Rd",
    "sg:city":"Ambler",
    "sg:classifiers":[
        {
            "category":"Professional",
            "type":"Services"
        }
    ],
    "sg:phone":"+1 215 643 2525",
    "sg:postcode":"19002",
    "sg:province":"PA",
    "sg:tags":[
        "establishment"
    ],
    "wof:name":"Miller & Harnick Assoc",
    "wof:placetype":"venue"
},
  "geometry": {"coordinates":[-75.16609099999999,40.159543],"type":"Point"}
}