{
  "type": "Feature",
  "properties": {
    "iso:country":"US",
    "sg:address":"630 Lincoln Hwy",
    "sg:city":"Coatesville",
    "sg:classifiers":[
        {
            "category":"Personal",
            "subcategory":"Barber",
            "type":"Services"
        }
    ],
    "sg:phone":"+1 610 384 3029",
    "sg:postcode":"19320",
    "sg:province":"PA",
    "sg:tags":[
        "shop"
    ],
    "wof:name":"Laurento's Barber Shop",
    "wof:placetype":"venue"
},
  "geometry": {"coordinates":[-75.838491,39.98083],"type":"Point"}
}