{
  "type": "Feature",
  "properties": {
    "iso:country":"US",
    "sg:address":"317 E South Ave",
    "sg:city":"Glenolden",
    "sg:classifiers":[
        {
            "category":"Shopping",
            "subcategory":"Gifts & Souvenirs",
            "type":"Retail Goods"
        },
        {
            "category":"Manufacturing",
            "subcategory":"Jewelry",
            "type":"Manufacturing & Wholesale Goods"
        }
    ],
    "sg:phone":"+1 484 494 3385",
    "sg:postcode":"19036",
    "sg:province":"PA",
    "sg:tags":[
        "shop",
        "novelty"
    ],
    "wof:name":"Airport Magic Shop",
    "wof:placetype":"venue"
},
  "geometry": {"coordinates":[-75.291183,39.890369],"type":"Point"}
}