{
  "type": "Feature",
  "properties": {
    "iso:country":"US",
    "sg:address":"12381 Lincoln Hwy",
    "sg:city":"Irwin",
    "sg:classifiers":[
        {
            "category":"Health Services",
            "subcategory":"Chiropractor",
            "type":"Services"
        }
    ],
    "sg:phone":"+1   ",
    "sg:postcode":"15642",
    "sg:province":"PA",
    "wof:name":"Hummert Chiropractic Hlth Ctr",
    "wof:placetype":"venue"
},
  "geometry": {"coordinates":[-79.744671,40.3354],"type":"Point"}
}