{
  "type": "Feature",
  "properties": {
    "addr:full":"5 Homestead Ln Robesonia PA 19551",
    "addr:housenumber":"5",
    "addr:postcode":"19551",
    "addr:street":"Homestead Ln",
    "iso:country":"US",
    "sg:address":"5 Homestead Ln",
    "sg:city":"Robesonia",
    "sg:classifiers":[
        {
            "category":"Shopping",
            "subcategory":"Gifts & Souvenirs",
            "type":"Retail Goods"
        }
    ],
    "sg:phone":"+1   ",
    "sg:postcode":"19551",
    "sg:province":"PA",
    "wof:name":"Morgans Sports Cards",
    "wof:placetype":"venue"
},
  "geometry": {"coordinates":[-76.146697,40.315936],"type":"Point"}
}