{
  "type": "Feature",
  "properties": {
    "addr:full":"40 Huff Ave Greensburg PA 15601",
    "addr:housenumber":"40",
    "addr:postcode":"15601",
    "addr:street":"Huff Ave",
    "iso:country":"US",
    "sg:address":"40 Huff Ave",
    "sg:city":"Greensburg",
    "sg:classifiers":[
        {
            "category":"Health Services",
            "subcategory":"Health Practitioner",
            "type":"Services"
        },
        {
            "category":"Social Services",
            "type":"Services"
        }
    ],
    "sg:phone":"+1 724 836 2380",
    "sg:postcode":"15601",
    "sg:province":"PA",
    "sg:tags":[
        "psychologist"
    ],
    "wof:name":"Margaret F Mc Kinley PHD",
    "wof:placetype":"venue"
},
  "geometry": {"coordinates":[-79.55134700000001,40.282501],"type":"Point"}
}