{
  "type": "Feature",
  "properties": {
    "addr:full":"1259 Franklin Mills Cir Philadelphia PA 19154",
    "addr:housenumber":"1259",
    "addr:postcode":"19154",
    "addr:street":"Franklin Mills Cir",
    "iso:country":"US",
    "sg:address":"1259 Franklin Mills Cir",
    "sg:city":"Philadelphia",
    "sg:classifiers":[
        {
            "category":"Shopping",
            "subcategory":"Clothing, Apparel, & Fashions",
            "type":"Retail Goods"
        }
    ],
    "sg:phone":"+1 215 281 0925",
    "sg:postcode":"19154",
    "sg:province":"PA",
    "sg:tags":[
        "accessory",
        "clothing",
        "women's"
    ],
    "wof:name":"Rue 21",
    "wof:placetype":"venue"
},
  "geometry": {"coordinates":[-74.958969,40.088415],"type":"Point"}
}