{
  "type": "Feature",
  "properties": {
    "iso:country":"US",
    "sg:address":"1271 E Grandview Blvd",
    "sg:city":"Erie",
    "sg:classifiers":[
        {
            "category":"Retail",
            "subcategory":"Laundry & Dry Cleaning",
            "type":"Services"
        }
    ],
    "sg:phone":"+1 814 825 7611",
    "sg:postcode":"16504",
    "sg:province":"PA",
    "sg:tags":[
        "drycleaning",
        "plant",
        "cleaners"
    ],
    "wof:name":"Thrifty Dry Cleaners Inc",
    "wof:placetype":"venue"
},
  "geometry": {"coordinates":[-80.02895100000001,42.10807],"type":"Point"}
}