{
  "type": "Feature",
  "properties": {
    "iso:country":"US",
    "sg:address":"222 W Main St",
    "sg:city":"Kutztown",
    "sg:classifiers":[
        {
            "category":"Shopping",
            "subcategory":"Pharmacy",
            "type":"Retail Goods"
        }
    ],
    "sg:phone":"+1   ",
    "sg:postcode":"19530",
    "sg:province":"PA",
    "sg:tags":[
        "drug",
        "store"
    ],
    "wof:name":"Eckerd",
    "wof:placetype":"venue"
},
  "geometry": {"coordinates":[-75.777451,40.516982],"type":"Point"}
}