{
  "type": "Feature",
  "properties": {
    "iso:country":"US",
    "sg:address":"323 Main St",
    "sg:city":"Towanda",
    "sg:classifiers":[
        {
            "category":"Professional",
            "subcategory":"Lawyer & Legal Services",
            "type":"Services"
        }
    ],
    "sg:phone":"+1 570 265 7921",
    "sg:postcode":"18848",
    "sg:province":"PA",
    "sg:tags":[
        "attorney"
    ],
    "wof:name":"Northern Tier Abstract Agency",
    "wof:placetype":"venue"
},
  "geometry": {"coordinates":[-76.44303499999999,41.767069],"type":"Point"}
}