{
  "type": "Feature",
  "properties": {
    "iso:country":"US",
    "sg:address":"101 Sycamore Ave",
    "sg:city":"Folsom",
    "sg:classifiers":[
        {
            "category":"Manufacturing",
            "subcategory":"Tools & Machinery",
            "type":"Manufacturing & Wholesale Goods"
        }
    ],
    "sg:phone":"+1 610 532 1850",
    "sg:postcode":"19033",
    "sg:province":"PA",
    "sg:tags":[
        "shop",
        "repair",
        "industrial",
        "mfg",
        "machine",
        "welding"
    ],
    "wof:name":"R G S Machine Inc",
    "wof:placetype":"venue"
},
  "geometry": {"coordinates":[-75.32148599999999,39.890437],"type":"Point"}
}