{
  "type": "Feature",
  "properties": {
    "iso:country":"US",
    "sg:address":"18 N 4th St",
    "sg:city":"Easton",
    "sg:classifiers":[
        {
            "category":"Manufacturing",
            "subcategory":"Tools & Machinery",
            "type":"Manufacturing & Wholesale Goods"
        }
    ],
    "sg:phone":"+1   ",
    "sg:postcode":"18042",
    "sg:province":"PA",
    "sg:tags":[
        "equipment",
        "peripheral",
        "computer",
        "mfg"
    ],
    "wof:name":"W Graphics",
    "wof:placetype":"venue"
},
  "geometry": {"coordinates":[-75.21122099999999,40.691414],"type":"Point"}
}