{
  "type": "Feature",
  "properties": {
    "iso:country":"US",
    "sg:address":"4764 Liberty Ave",
    "sg:city":"Pittsburgh",
    "sg:classifiers":[
        {
            "category":"Government",
            "subcategory":"Office",
            "type":"Public Place"
        }
    ],
    "sg:phone":"+1 412 781 5100",
    "sg:postcode":"15224",
    "sg:province":"PA",
    "wof:name":"Honorable Ronald N Costa Sr",
    "wof:placetype":"venue"
},
  "geometry": {"coordinates":[-79.947214,40.460606],"type":"Point"}
}