{
  "type": "Feature",
  "properties": {
    "addr:full":"2083 Quaker Pointe Dr Quakertown PA 18951",
    "addr:housenumber":"2083",
    "addr:postcode":"18951",
    "addr:street":"Quaker Pointe Dr",
    "iso:country":"US",
    "sg:address":"2083 Quaker Pointe Dr",
    "sg:city":"Quakertown",
    "sg:classifiers":[
        {
            "category":"Manufacturing",
            "subcategory":"Metals",
            "type":"Manufacturing & Wholesale Goods"
        }
    ],
    "sg:phone":"+1 215 538 1600",
    "sg:postcode":"18951",
    "sg:province":"PA",
    "sg:tags":[
        "tower"
    ],
    "wof:name":"Celerity Integrated Svc Inc",
    "wof:placetype":"venue"
},
  "geometry": {"coordinates":[-75.41296,40.433638],"type":"Point"}
}