{
  "type": "Feature",
  "properties": {
    "iso:country":"US",
    "sg:address":"6750 Iroquois Trl Ste 4",
    "sg:city":"Allentown",
    "sg:classifiers":[
        {
            "category":"Personal",
            "subcategory":"Beauty Salon",
            "type":"Services"
        }
    ],
    "sg:phone":"+1 610 395 4448",
    "sg:postcode":"18104",
    "sg:province":"PA",
    "sg:tags":[
        "hair",
        "stylist"
    ],
    "wof:name":"The Hair Connection",
    "wof:placetype":"venue"
},
  "geometry": {"coordinates":[-75.596694,40.576242],"type":"Point"}
}