{
  "type": "Feature",
  "properties": {
    "iso:country":"US",
    "sg:address":"23 Rain Lily Rd",
    "sg:city":"Levittown",
    "sg:classifiers":[
        {
            "category":"Building & Trades",
            "subcategory":"Construction",
            "type":"Services"
        }
    ],
    "sg:phone":"+1   ",
    "sg:postcode":"19056",
    "sg:province":"PA",
    "sg:tags":[
        "house"
    ],
    "wof:name":"Bucks County Home Rmdlg L L C",
    "wof:placetype":"venue"
},
  "geometry": {"coordinates":[-74.877748,40.1561],"type":"Point"}
}