{
  "type": "Feature",
  "properties": {
    "iso:country":"US",
    "sg:address":"2034 Middle Rd",
    "sg:city":"Glenshaw",
    "sg:classifiers":[
        {
            "category":"Government",
            "subcategory":"Fire Station",
            "type":"Public Place"
        }
    ],
    "sg:phone":"+1 412 486 6365",
    "sg:postcode":"15116",
    "sg:province":"PA",
    "sg:tags":[
        "department"
    ],
    "wof:name":"Indiana Twp Fire Dept",
    "wof:placetype":"venue"
},
  "geometry": {"coordinates":[-79.933448,40.54391],"type":"Point"}
}