{
  "type": "Feature",
  "properties": {
    "iso:country":"US",
    "sg:address":"80 N Roland St Fl 1",
    "sg:city":"Pottstown",
    "sg:classifiers":[
        {
            "category":"Home & Garden",
            "subcategory":"Hardware",
            "type":"Retail Goods"
        }
    ],
    "sg:phone":"+1 610 970 0927",
    "sg:postcode":"19464",
    "sg:province":"PA",
    "sg:tags":[
        "water",
        "equipment",
        "filtration",
        "purification"
    ],
    "wof:name":"Action Air And Water Purification",
    "wof:placetype":"venue"
},
  "geometry": {"coordinates":[-75.62179,40.245364],"type":"Point"}
}