{
  "type": "Feature",
  "properties": {
    "addr:full":"216 N Beaver St New Castle PA 16101",
    "addr:housenumber":"216",
    "addr:postcode":"16101",
    "addr:street":"N Beaver St",
    "iso:country":"US",
    "sg:address":"216 N Beaver St",
    "sg:city":"New Castle",
    "sg:classifiers":[
        {
            "category":"Wholesale",
            "subcategory":"Tobacco Products",
            "type":"Manufacturing & Wholesale Goods"
        }
    ],
    "sg:phone":"+1 724 658 6561",
    "sg:postcode":"16101",
    "sg:province":"PA",
    "sg:tags":[
        "cigarette",
        "cigar",
        "dealer"
    ],
    "sg:website":"www.cigarexpress.com",
    "wof:name":"Klafter's Inc",
    "wof:placetype":"venue"
},
  "geometry": {"coordinates":[-80.34865000000001,41.002168],"type":"Point"}
}