{
  "type": "Feature",
  "properties": {
    "iso:country":"US",
    "sg:address":"441 New Grove St",
    "sg:city":"Wilkes Barre",
    "sg:classifiers":[
        {
            "category":"Building & Trades",
            "subcategory":"Plumbing",
            "type":"Services"
        }
    ],
    "sg:phone":"+1 570 820 7133",
    "sg:postcode":"18702",
    "sg:province":"PA",
    "sg:tags":[
        "conditioning",
        "air",
        "system",
        "contractor"
    ],
    "wof:name":"Cdt Enterprises Inc",
    "wof:placetype":"venue"
},
  "geometry": {"coordinates":[-75.90113700000001,41.227211],"type":"Point"}
}