{
  "type": "Feature",
  "properties": {
    "iso:country":"US",
    "sg:address":"4008 Gibsonia Rd",
    "sg:city":"Gibsonia",
    "sg:classifiers":[
        {
            "category":"Utilities",
            "subcategory":"Telephone",
            "type":"Services"
        }
    ],
    "sg:phone":"+1   ",
    "sg:postcode":"15044",
    "sg:province":"PA",
    "sg:tags":[
        "communications"
    ],
    "wof:name":"N W Barthlow Office",
    "wof:placetype":"venue"
},
  "geometry": {"coordinates":[-79.91697000000001,40.620845],"type":"Point"}
}