{
  "type": "Feature",
  "properties": {
    "addr:full":"2190 E High St Pottstown PA 19464",
    "addr:housenumber":"2190",
    "addr:postcode":"19464",
    "addr:street":"E High St",
    "iso:country":"US",
    "sg:address":"2190 E High St",
    "sg:city":"Pottstown",
    "sg:classifiers":[
        {
            "category":"Banks & Credit Unions",
            "subcategory":"Bank",
            "type":"Services"
        }
    ],
    "sg:phone":"+1   ",
    "sg:postcode":"19464",
    "sg:province":"PA",
    "sg:tags":[
        "state",
        "commercial"
    ],
    "wof:name":"M&T",
    "wof:placetype":"venue"
},
  "geometry": {"coordinates":[-75.59905000000001,40.244625],"type":"Point"}
}