{
  "type": "Feature",
  "properties": {
    "addr:full":"1232 Leishman Ave New Kensington PA 15068",
    "addr:housenumber":"1232",
    "addr:postcode":"15068",
    "addr:street":"Leishman Ave",
    "iso:country":"US",
    "sg:address":"1232 Leishman Ave",
    "sg:city":"New Kensington",
    "sg:classifiers":[
        {
            "category":"Organizations",
            "subcategory":"Community Association",
            "type":"Services"
        }
    ],
    "sg:phone":"+1 724 339 7850",
    "sg:postcode":"15068",
    "sg:province":"PA",
    "sg:tags":[
        "fraternal"
    ],
    "wof:name":"Knights Of Columbus",
    "wof:placetype":"venue"
},
  "geometry": {"coordinates":[-79.762733,40.570521],"type":"Point"}
}