{
  "type": "Feature",
  "properties": {
    "addr:full":"70 S 3rd St Chambersburg PA 17201",
    "addr:housenumber":"70",
    "addr:postcode":"17201",
    "addr:street":"S 3Rd St",
    "iso:country":"US",
    "sg:address":"70 S 3rd St",
    "sg:city":"Chambersburg",
    "sg:classifiers":[
        {
            "category":"Personal",
            "subcategory":"Beauty Salon",
            "type":"Services"
        }
    ],
    "sg:phone":"+1 717 264 8211",
    "sg:postcode":"17201",
    "sg:province":"PA",
    "sg:tags":[
        "shop"
    ],
    "wof:name":"Mane Designs Hair Salon",
    "wof:placetype":"venue"
},
  "geometry": {"coordinates":[-77.657331,39.935523],"type":"Point"}
}