{
  "type": "Feature",
  "properties": {
    "iso:country":"US",
    "sg:address":"910 Mountain Home Rd",
    "sg:city":"Reading",
    "sg:classifiers":[
        {
            "category":"Autos & Motor Vehicles",
            "subcategory":"Fuel & Gas Station",
            "type":"Retail Goods"
        },
        {
            "category":"Utilities",
            "subcategory":"Fuel Oil & Lpg",
            "type":"Services"
        }
    ],
    "sg:phone":"+1 610 678 3421",
    "sg:postcode":"19608",
    "sg:province":"PA",
    "sg:tags":[
        "bulk",
        "oils-fuel",
        "petroleum-bottled",
        "gas-liquefied"
    ],
    "sg:website":"http://www.asifuels.com",
    "wof:name":"Palmer & Haller Partnership",
    "wof:placetype":"venue"
},
  "geometry": {"coordinates":[-76.033995,40.319154],"type":"Point"}
}