{
  "type": "Feature",
  "properties": {
    "iso:country":"US",
    "sg:address":"555 N Main St",
    "sg:city":"Bangor",
    "sg:classifiers":[
        {
            "category":"Shopping",
            "subcategory":"Clothing, Apparel, & Fashions",
            "type":"Retail Goods"
        }
    ],
    "sg:phone":"+1 610 588 1415",
    "sg:postcode":"18013",
    "sg:province":"PA",
    "sg:tags":[
        "t-shirt"
    ],
    "wof:name":"Jaurice Inc",
    "wof:placetype":"venue"
},
  "geometry": {"coordinates":[-75.208428,40.873023],"type":"Point"}
}