{
  "type": "Feature",
  "properties": {
    "addr:full":"141 Lehigh Valley Mall Whitehall PA 18052",
    "addr:housenumber":"141",
    "addr:postcode":"18052",
    "addr:street":"Lehigh Valley Mall",
    "iso:country":"US",
    "sg:address":"141 Lehigh Valley Mall",
    "sg:city":"Whitehall",
    "sg:classifiers":[
        {
            "category":"Building & Trades",
            "subcategory":"Construction",
            "type":"Services"
        }
    ],
    "sg:phone":"+1 610 264 1283",
    "sg:postcode":"18052",
    "sg:province":"PA",
    "sg:tags":[
        "general",
        "contractor"
    ],
    "wof:name":"Commercial Contractors Inc",
    "wof:placetype":"venue"
},
  "geometry": {"coordinates":[-75.484245,40.62882],"type":"Point"}
}