{
  "type": "Feature",
  "properties": {
    "iso:country":"US",
    "sg:address":"196 Fischer Rd",
    "sg:city":"Washington",
    "sg:classifiers":[
        {
            "category":"Personal",
            "subcategory":"Barber",
            "type":"Services"
        }
    ],
    "sg:phone":"+1 724 745 7262",
    "sg:postcode":"15301",
    "sg:province":"PA",
    "wof:name":"Janet Fords Mane Street Salon",
    "wof:placetype":"venue"
},
  "geometry": {"coordinates":[-80.210216,40.206511],"type":"Point"}
}