{
  "type": "Feature",
  "properties": {
    "iso:country":"US",
    "sg:address":"641 Frederick St",
    "sg:city":"Hanover",
    "sg:classifiers":[
        {
            "category":"Education",
            "subcategory":"Dance Studio",
            "type":"Public Place"
        }
    ],
    "sg:phone":"+1 717 633 5128",
    "sg:postcode":"17331",
    "sg:province":"PA",
    "sg:tags":[
        "instruction",
        "dancing"
    ],
    "wof:name":"Dance Works",
    "wof:placetype":"venue"
},
  "geometry": {"coordinates":[-76.994383,39.791419],"type":"Point"}
}