{
  "type": "Feature",
  "properties": {
    "iso:country":"US",
    "sg:address":"295 W 10th St",
    "sg:city":"Jim Thorpe",
    "sg:classifiers":[
        {
            "category":"Building & Trades",
            "subcategory":"Construction",
            "type":"Services"
        }
    ],
    "sg:phone":"+1 570 325 8522",
    "sg:postcode":"18229",
    "sg:province":"PA",
    "sg:tags":[
        "contractor"
    ],
    "wof:name":"Al Sibbach Building",
    "wof:placetype":"venue"
},
  "geometry": {"coordinates":[-75.731199,40.881182],"type":"Point"}
}