{
  "type": "Feature",
  "properties": {
    "addr:full":"108 Pine St Darby PA 19023",
    "addr:housenumber":"108",
    "addr:postcode":"19023",
    "addr:street":"Pine St",
    "iso:country":"US",
    "sg:address":"108 Pine St",
    "sg:city":"Darby",
    "sg:classifiers":[
        {
            "category":"Shopping",
            "subcategory":"Hobbies, Toys, & Games",
            "type":"Retail Goods"
        }
    ],
    "sg:phone":"+1   ",
    "sg:postcode":"19023",
    "sg:province":"PA",
    "wof:name":"Auto Toys & Security",
    "wof:placetype":"venue"
},
  "geometry": {"coordinates":[-75.26612900000001,39.91672],"type":"Point"}
}