{
  "type": "Feature",
  "properties": {
    "iso:country":"US",
    "sg:address":"2006 S 7th St",
    "sg:city":"Philadelphia",
    "sg:classifiers":[
        {
            "category":"Retail",
            "subcategory":"Laundry & Dry Cleaning",
            "type":"Services"
        }
    ],
    "sg:phone":"+1 215 389 1183",
    "sg:postcode":"19148",
    "sg:province":"PA",
    "sg:tags":[
        "cleaners"
    ],
    "wof:name":"Seventh Street One Hour Martin",
    "wof:placetype":"venue"
},
  "geometry": {"coordinates":[-75.15806499999999,39.923869],"type":"Point"}
}