{
  "type": "Feature",
  "properties": {
    "iso:country":"US",
    "sg:address":"511 Easton Rd",
    "sg:city":"Warrington",
    "sg:classifiers":[
        {
            "category":"Autos & Motor Vehicles",
            "subcategory":"Motorcycle Sales",
            "type":"Retail Goods"
        }
    ],
    "sg:phone":"+1 215 343 5459",
    "sg:postcode":"18976",
    "sg:province":"PA",
    "sg:tags":[
        "scooter"
    ],
    "wof:name":"Tricked Out Cycles & Power",
    "wof:placetype":"venue"
},
  "geometry": {"coordinates":[-75.139956,40.225977],"type":"Point"}
}