{
  "type": "Feature",
  "properties": {
    "addr:full":"1115 Dogwood Ct Pottstown PA 19465",
    "addr:housenumber":"1115",
    "addr:postcode":"19465",
    "addr:street":"Dogwood Ct",
    "iso:country":"US",
    "sg:address":"1115 Dogwood Ct",
    "sg:city":"Pottstown",
    "sg:classifiers":[
        {
            "category":"Professional",
            "subcategory":"Engineering",
            "type":"Services"
        }
    ],
    "sg:phone":"+1   ",
    "sg:postcode":"19465",
    "sg:province":"PA",
    "sg:tags":[
        "procurement",
        "structural",
        "for",
        "materiel"
    ],
    "wof:name":"Trident E&P",
    "wof:placetype":"venue"
},
  "geometry": {"coordinates":[-75.67550199999999,40.225103],"type":"Point"}
}