{
  "type": "Feature",
  "properties": {
    "iso:country":"US",
    "sg:address":"2201 Industrial Hwy",
    "sg:city":"York",
    "sg:classifiers":[
        {
            "category":"Manufacturing",
            "subcategory":"Tools & Machinery",
            "type":"Manufacturing & Wholesale Goods"
        }
    ],
    "sg:phone":"+1 717 755 3441",
    "sg:postcode":"17402",
    "sg:province":"PA",
    "sg:tags":[
        "tools-electric"
    ],
    "wof:name":"Black & Decker (U.S.) Inc.",
    "wof:placetype":"venue"
},
  "geometry": {"coordinates":[-76.687562,39.977634],"type":"Point"}
}