{
  "type": "Feature",
  "properties": {
    "iso:country":"US",
    "sg:address":"1538 Robertson Dr",
    "sg:city":"Pittsburgh",
    "sg:classifiers":[
        {
            "category":"Professional",
            "subcategory":"Art Services",
            "type":"Services"
        }
    ],
    "sg:phone":"+1   ",
    "sg:postcode":"15237",
    "sg:province":"PA",
    "sg:tags":[
        "commercial",
        "design"
    ],
    "wof:name":"Kostilnik & Assoc Graphics",
    "wof:placetype":"venue"
},
  "geometry": {"coordinates":[-80.07338799999999,40.583535],"type":"Point"}
}