{
  "type": "Feature",
  "properties": {
    "addr:full":"2384 Golden Mile Hwy Pittsburgh PA 15239",
    "addr:housenumber":"2384",
    "addr:postcode":"15239",
    "addr:street":"Golden Mile Hwy",
    "iso:country":"US",
    "sg:address":"2384 Golden Mile Hwy",
    "sg:city":"Pittsburgh",
    "sg:classifiers":[
        {
            "category":"Restaurant",
            "type":"Food & Drink"
        }
    ],
    "sg:menulink":"http://www.allmenus.com/pa/plum/123186-quiznos-sub/menu/",
    "sg:phone":"+1 724 325 2859",
    "sg:postcode":"15239",
    "sg:province":"PA",
    "sg:tags":[
        "wrap",
        "american",
        "sandwich"
    ],
    "wof:name":"Quiznos Sub",
    "wof:placetype":"venue"
},
  "geometry": {"coordinates":[-79.705324,40.464508],"type":"Point"}
}