{
  "type": "Feature",
  "properties": {
    "iso:country":"US",
    "sg:address":"1512 Powells Valley Rd",
    "sg:city":"Halifax",
    "sg:classifiers":[
        {
            "category":"Wholesale",
            "subcategory":"Non-durable Goods",
            "type":"Manufacturing & Wholesale Goods"
        }
    ],
    "sg:phone":"+1   ",
    "sg:postcode":"17032",
    "sg:province":"PA",
    "wof:name":"Printed Balloon",
    "wof:placetype":"venue"
},
  "geometry": {"coordinates":[-76.85158800000001,40.461387],"type":"Point"}
}