{
  "type": "Feature",
  "properties": {
    "addr:full":"120 N Pine St Langhorne PA 19047",
    "addr:housenumber":"120",
    "addr:postcode":"19047",
    "addr:street":"N Pine St",
    "iso:country":"US",
    "sg:address":"120 N Pine St",
    "sg:city":"Langhorne",
    "sg:classifiers":[
        {
            "category":"Shopping",
            "subcategory":"Discount & Variety Stores",
            "type":"Retail Goods"
        }
    ],
    "sg:phone":"+1   ",
    "sg:postcode":"19047",
    "sg:province":"PA",
    "wof:name":"Dollar General",
    "wof:placetype":"venue"
},
  "geometry": {"coordinates":[-74.91808399999999,40.178367],"type":"Point"}
}