{
  "type": "Feature",
  "properties": {
    "iso:country":"US",
    "sg:address":"4636 N 5th St",
    "sg:city":"Philadelphia",
    "sg:classifiers":[
        {
            "category":"Restaurant",
            "type":"Food & Drink"
        }
    ],
    "sg:phone":"+1 215 455 2204",
    "sg:postcode":"19140",
    "sg:province":"PA",
    "wof:name":"LA Pacna",
    "wof:placetype":"venue"
},
  "geometry": {"coordinates":[-75.1336,40.022661],"type":"Point"}
}