{
  "type": "Feature",
  "properties": {
    "addr:full":"101 Timothy Ln Butler PA 16001",
    "addr:housenumber":"101",
    "addr:postcode":"16001",
    "addr:street":"Timothy Ln",
    "iso:country":"US",
    "sg:address":"101 Timothy Ln",
    "sg:city":"Butler",
    "sg:classifiers":[
        {
            "category":"Professional",
            "subcategory":"Computer Services",
            "type":"Services"
        }
    ],
    "sg:phone":"+1   ",
    "sg:postcode":"16001",
    "sg:province":"PA",
    "sg:tags":[
        "programing",
        "custom"
    ],
    "wof:name":"Cutting Edge Solutions Inc",
    "wof:placetype":"venue"
},
  "geometry": {"coordinates":[-79.93273499999999,40.894794],"type":"Point"}
}