{
  "type": "Feature",
  "properties": {
    "iso:country":"US",
    "sg:address":"432 Maryland Ave",
    "sg:city":"Erie",
    "sg:classifiers":[
        {
            "category":"Insurance",
            "subcategory":"Hazard Insurance",
            "type":"Services"
        }
    ],
    "sg:phone":"+1   ",
    "sg:postcode":"16505",
    "sg:province":"PA",
    "sg:tags":[
        "carrier"
    ],
    "wof:name":"Infinity Insurance",
    "wof:placetype":"venue"
},
  "geometry": {"coordinates":[-80.129536,42.113507],"type":"Point"}
}