{
  "type": "Feature",
  "properties": {
    "addr:full":"1319 N 5th St Stroudsburg PA 18360",
    "addr:housenumber":"1319",
    "addr:postcode":"18360",
    "addr:street":"N 5Th St",
    "iso:country":"US",
    "sg:address":"1319 N 5th St",
    "sg:city":"Stroudsburg",
    "sg:classifiers":[
        {
            "category":"Ice Cream",
            "type":"Food & Drink"
        }
    ],
    "sg:menulink":"http://www.allmenus.com/pa/stroud/234978-ritas-ice-custard-happiness/menu/",
    "sg:phone":"+1 570 420 8099",
    "sg:postcode":"18360",
    "sg:province":"PA",
    "sg:tags":[
        "american"
    ],
    "wof:name":"Rita's Ice Custard Happiness",
    "wof:placetype":"venue"
},
  "geometry": {"coordinates":[-75.198015,41.001513],"type":"Point"}
}