{
  "type": "Feature",
  "properties": {
    "iso:country":"US",
    "sg:address":"422 1st Ave",
    "sg:city":"Pittsburgh",
    "sg:classifiers":[
        {
            "category":"Manufacturing",
            "subcategory":"Printing",
            "type":"Manufacturing & Wholesale Goods"
        }
    ],
    "sg:phone":"+1 412 391 4350",
    "sg:postcode":"15219",
    "sg:province":"PA",
    "sg:tags":[
        "printer"
    ],
    "sg:website":"www.gaccpgh.com",
    "wof:name":"Graphic Arts Color Corp",
    "wof:placetype":"venue"
},
  "geometry": {"coordinates":[-80.000546,40.437235],"type":"Point"}
}