{
  "type": "Feature",
  "properties": {
    "addr:full":"519 Greenville Rd Mercer PA 16137",
    "addr:housenumber":"519",
    "addr:postcode":"16137",
    "addr:street":"Greenville Rd",
    "iso:country":"US",
    "sg:address":"519 Greenville Rd",
    "sg:city":"Mercer",
    "sg:classifiers":[
        {
            "category":"Government",
            "subcategory":"Office",
            "type":"Public Place"
        }
    ],
    "sg:phone":"+1 724 662 0526",
    "sg:postcode":"16137",
    "sg:province":"PA",
    "sg:tags":[
        "state",
        "program",
        "transportation"
    ],
    "wof:name":"Driver License Center",
    "wof:placetype":"venue"
},
  "geometry": {"coordinates":[-80.241139,41.232742],"type":"Point"}
}