{
  "type": "Feature",
  "properties": {
    "addr:full":"2969 Industrial Blvd Bethel Park PA 15102",
    "addr:housenumber":"2969",
    "addr:postcode":"15102",
    "addr:street":"Industrial Blvd",
    "iso:country":"US",
    "sg:address":"2969 Industrial Blvd",
    "sg:city":"Bethel Park",
    "sg:classifiers":[
        {
            "category":"Manufacturing",
            "subcategory":"Rubber & Plastics",
            "type":"Manufacturing & Wholesale Goods"
        }
    ],
    "sg:phone":"+1 412 787 0655",
    "sg:postcode":"15102",
    "sg:province":"PA",
    "sg:tags":[
        "product"
    ],
    "sg:website":"www.nationalrubber.com",
    "wof:name":"National Rubber Corp",
    "wof:placetype":"venue"
},
  "geometry": {"coordinates":[-80.040705,40.326584],"type":"Point"}
}