{
  "type": "Feature",
  "properties": {
    "addr:full":"53 E Main St Lititz PA 17543",
    "addr:housenumber":"53",
    "addr:postcode":"17543",
    "addr:street":"E Main St",
    "iso:country":"US",
    "sg:address":"53 E Main St",
    "sg:city":"Lititz",
    "sg:classifiers":[
        {
            "category":"Restaurant",
            "type":"Food & Drink"
        }
    ],
    "sg:phone":"+1   ",
    "sg:postcode":"17543",
    "sg:province":"PA",
    "sg:tags":[
        "eating"
    ],
    "wof:name":"Danners Deli",
    "wof:placetype":"venue"
},
  "geometry": {"coordinates":[-76.30447700000001,40.156841],"type":"Point"}
}