{
  "type": "Feature",
  "properties": {
    "iso:country":"US",
    "sg:address":"318 Pike Rd",
    "sg:city":"Howard",
    "sg:classifiers":[
        {
            "category":"Home & Garden",
            "subcategory":"Building Materials",
            "type":"Retail Goods"
        }
    ],
    "sg:phone":"+1   ",
    "sg:postcode":"16841",
    "sg:province":"PA",
    "wof:name":"Stovers Lumber Company",
    "wof:placetype":"venue"
},
  "geometry": {"coordinates":[-77.55516799999999,40.996212],"type":"Point"}
}