{
  "type": "Feature",
  "properties": {
    "iso:country":"US",
    "sg:address":"24 W Cleveland Ave",
    "sg:city":"Norwood",
    "sg:classifiers":[
        {
            "category":"Home & Garden",
            "subcategory":"Carpets & Floor Coverings",
            "type":"Retail Goods"
        }
    ],
    "sg:phone":"+1 484 494 4304",
    "sg:postcode":"19074",
    "sg:province":"PA",
    "sg:tags":[
        "distributor",
        "rug",
        "manufacturer"
    ],
    "wof:name":"Zagame Carpet",
    "wof:placetype":"venue"
},
  "geometry": {"coordinates":[-75.297141,39.891652],"type":"Point"}
}