{
  "type": "Feature",
  "properties": {
    "iso:country":"US",
    "sg:address":"65 W State St",
    "sg:city":"Doylestown",
    "sg:classifiers":[
        {
            "category":"Social Services",
            "type":"Services"
        }
    ],
    "sg:phone":"+1 215 348 8073",
    "sg:postcode":"18901",
    "sg:province":"PA",
    "sg:tags":[
        "counselor",
        "marriage",
        "family"
    ],
    "wof:name":"Doylestown Counseling Collectn",
    "wof:placetype":"venue"
},
  "geometry": {"coordinates":[-75.13143599999999,40.309639],"type":"Point"}
}