{
  "type": "Feature",
  "properties": {
    "addr:full":"707 E Columbus Ave Corry PA 16407",
    "addr:housenumber":"707",
    "addr:postcode":"16407",
    "addr:street":"E Columbus Ave",
    "iso:country":"US",
    "sg:address":"707 E Columbus Ave",
    "sg:city":"Corry",
    "sg:classifiers":[
        {
            "category":"Professional",
            "type":"Services"
        }
    ],
    "sg:phone":"+1   ",
    "sg:postcode":"16407",
    "sg:province":"PA",
    "wof:name":"Thomass TS & Things",
    "wof:placetype":"venue"
},
  "geometry": {"coordinates":[-79.619957,41.932934],"type":"Point"}
}