{
  "type": "Feature",
  "properties": {
    "iso:country":"US",
    "sg:address":"339 E Wister St",
    "sg:city":"Philadelphia",
    "sg:classifiers":[
        {
            "category":"Home & Garden",
            "subcategory":"Household Appliances",
            "type":"Retail Goods"
        },
        {
            "category":"Building & Trades",
            "subcategory":"Construction",
            "type":"Services"
        },
        {
            "category":"Building & Trades",
            "subcategory":"Electrical",
            "type":"Services"
        }
    ],
    "sg:phone":"+1 215 843 5830",
    "sg:postcode":"19144",
    "sg:province":"PA",
    "sg:tags":[
        "industrial",
        "electrician",
        "electric",
        "system",
        "machine",
        "dishwashing",
        "contractor",
        "air conditioning",
        "contractors-commercial"
    ],
    "wof:name":"Lowry Electric Inc",
    "wof:placetype":"venue"
},
  "geometry": {"coordinates":[-75.161034,40.033718],"type":"Point"}
}