{
  "type": "Feature",
  "properties": {
    "addr:full":"2 E 2nd St Boyertown PA 19512",
    "addr:housenumber":"2",
    "addr:postcode":"19512",
    "addr:street":"E 2Nd St",
    "iso:country":"US",
    "sg:address":"2 E 2nd St",
    "sg:city":"Boyertown",
    "sg:classifiers":[
        {
            "category":"Local Transit",
            "type":"Transportation"
        }
    ],
    "sg:phone":"+1   ",
    "sg:postcode":"19512",
    "sg:province":"PA",
    "sg:tags":[
        "passenger"
    ],
    "wof:name":"Boyertown Amblnce Drivers Assn",
    "wof:placetype":"venue"
},
  "geometry": {"coordinates":[-75.639561,40.330646],"type":"Point"}
}