{
  "type": "Feature",
  "properties": {
    "addr:full":"5620 Peach St Erie PA 16509",
    "addr:housenumber":"5620",
    "addr:postcode":"16509",
    "addr:street":"Peach St",
    "iso:country":"US",
    "sg:address":"5620 Peach St",
    "sg:city":"Erie",
    "sg:classifiers":[
        {
            "category":"Real Estate",
            "subcategory":"Real Estate Agent",
            "type":"Services"
        }
    ],
    "sg:phone":"+1 814 864 3200",
    "sg:postcode":"16509",
    "sg:province":"PA",
    "sg:tags":[
        "broker"
    ],
    "wof:name":"Hanna Howard Real Estate",
    "wof:placetype":"venue"
},
  "geometry": {"coordinates":[-80.093255,42.071642],"type":"Point"}
}