{
  "type": "Feature",
  "properties": {
    "iso:country":"US",
    "sg:address":"2911 Wood Pipe Ln",
    "sg:city":"Philadelphia",
    "sg:classifiers":[
        {
            "category":"Manufacturing",
            "subcategory":"Tools & Machinery",
            "type":"Manufacturing & Wholesale Goods"
        }
    ],
    "sg:phone":"+1   ",
    "sg:postcode":"19129",
    "sg:province":"PA",
    "sg:tags":[
        "analytical",
        "instrument",
        "mfg"
    ],
    "wof:name":"Brian C Tryon MD",
    "wof:placetype":"venue"
},
  "geometry": {"coordinates":[-75.18138999999999,40.020867],"type":"Point"}
}