{
  "type": "Feature",
  "properties": {
    "addr:full":"1629 Randow Rd York PA 17403",
    "addr:housenumber":"1629",
    "addr:postcode":"17403",
    "addr:street":"Randow Rd",
    "iso:country":"US",
    "sg:address":"1629 Randow Rd",
    "sg:city":"York",
    "sg:classifiers":[
        {
            "category":"Manufacturing",
            "subcategory":"Retail Goods",
            "type":"Manufacturing & Wholesale Goods"
        }
    ],
    "sg:phone":"+1   ",
    "sg:postcode":"17403",
    "sg:province":"PA",
    "sg:tags":[
        "product",
        "mfg"
    ],
    "wof:name":"Creative Touch",
    "wof:placetype":"venue"
},
  "geometry": {"coordinates":[-76.684151,39.949049],"type":"Point"}
}