{
  "type": "Feature",
  "properties": {
    "addr:full":"1818 Market St Philadelphia PA 19103",
    "addr:housenumber":"1818",
    "addr:postcode":"19103",
    "addr:street":"Market St",
    "iso:country":"US",
    "sg:address":"1818 Market St",
    "sg:city":"Philadelphia",
    "sg:classifiers":[
        {
            "category":"Health Services",
            "subcategory":"Dentist",
            "type":"Services"
        }
    ],
    "sg:phone":"+1 215 253 4647",
    "sg:postcode":"19103",
    "sg:province":"PA",
    "sg:tags":[
        "product",
        "dentists-cosmetic",
        "teeth",
        "whitening",
        "dentistry",
        "dentists-orthodontists"
    ],
    "sg:website":"http://philadelphia.citysearch.com/profile/external/47350353/philadelphia_pa/maurry_leas_dentistry.html?publisher=yellowpages&reference_id=7&placement=ypwebsitemip",
    "wof:name":"Maurry Leas Dentistry",
    "wof:placetype":"venue"
},
  "geometry": {"coordinates":[-75.170276,39.953225],"type":"Point"}
}