{
  "type": "Feature",
  "properties": {
    "iso:country":"US",
    "sg:address":"137 6th St",
    "sg:city":"Pittsburgh",
    "sg:classifiers":[
        {
            "category":"Restaurant",
            "type":"Food & Drink"
        }
    ],
    "sg:phone":"+1 412 471 0660",
    "sg:postcode":"15222",
    "sg:province":"PA",
    "sg:tags":[
        "indian"
    ],
    "wof:name":"India Palace Cuisine",
    "wof:placetype":"venue"
},
  "geometry": {"coordinates":[-80.00272200000001,40.444019],"type":"Point"}
}