{
  "type": "Feature",
  "properties": {
    "iso:country":"US",
    "sg:address":"242 Amity Rd",
    "sg:city":"Glenshaw",
    "sg:classifiers":[
        {
            "category":"Home & Garden",
            "subcategory":"Carpets & Floor Coverings",
            "type":"Retail Goods"
        }
    ],
    "sg:phone":"+1 412 487 7303",
    "sg:postcode":"15116",
    "sg:province":"PA",
    "sg:tags":[
        "material"
    ],
    "wof:name":"Kelly Flooring",
    "wof:placetype":"venue"
},
  "geometry": {"coordinates":[-79.996261,40.548831],"type":"Point"}
}