{
  "type": "Feature",
  "properties": {
    "iso:country":"US",
    "sg:address":"655 Freeport Rd",
    "sg:city":"Butler",
    "sg:classifiers":[
        {
            "category":"Insurance",
            "subcategory":"Insurance Agent",
            "type":"Services"
        }
    ],
    "sg:phone":"+1   ",
    "sg:postcode":"16002",
    "sg:province":"PA",
    "wof:name":"David Sinz Agent",
    "wof:placetype":"venue"
},
  "geometry": {"coordinates":[-79.82321,40.799856],"type":"Point"}
}