{
  "type": "Feature",
  "properties": {
    "iso:country":"US",
    "sg:address":"507 N York St",
    "sg:city":"Mechanicsburg",
    "sg:classifiers":[
        {
            "category":"Building & Trades",
            "subcategory":"Plumbing",
            "type":"Services"
        }
    ],
    "sg:phone":"+1 717 766 8559",
    "sg:postcode":"17055",
    "sg:province":"PA",
    "sg:tags":[
        "plumbing",
        "contractor"
    ],
    "wof:name":"Tim Wilbur Mechanical Contrg",
    "wof:placetype":"venue"
},
  "geometry": {"coordinates":[-77.01361300000001,40.217101],"type":"Point"}
}