{
  "type": "Feature",
  "properties": {
    "iso:country":"US",
    "sg:address":"511 Main St",
    "sg:city":"Honesdale",
    "sg:classifiers":[
        {
            "category":"Personal",
            "subcategory":"Barber",
            "type":"Services"
        }
    ],
    "sg:phone":"+1 570 253 2910",
    "sg:postcode":"18431",
    "sg:province":"PA",
    "wof:name":"Mick's Barber Shop",
    "wof:placetype":"venue"
},
  "geometry": {"coordinates":[-75.254178,41.569565],"type":"Point"}
}