{
  "type": "Feature",
  "properties": {
    "iso:country":"US",
    "sg:address":"15 Rock Springs Rd",
    "sg:city":"Delmont",
    "sg:classifiers":[
        {
            "category":"Building & Trades",
            "subcategory":"Construction",
            "type":"Services"
        }
    ],
    "sg:phone":"+1   ",
    "sg:postcode":"15626",
    "sg:province":"PA",
    "sg:tags":[
        "water",
        "line",
        "sewer",
        "contractor"
    ],
    "wof:name":"Ricon Inc",
    "wof:placetype":"venue"
},
  "geometry": {"coordinates":[-79.559208,40.417055],"type":"Point"}
}