{
  "type": "Feature",
  "properties": {
    "iso:country":"US",
    "sg:address":"14 Elliott Ave",
    "sg:city":"Bryn Mawr",
    "sg:classifiers":[
        {
            "category":"Social Services",
            "type":"Services"
        }
    ],
    "sg:phone":"+1   ",
    "sg:postcode":"19010",
    "sg:province":"PA",
    "wof:name":"Bryn Mawr Center",
    "wof:placetype":"venue"
},
  "geometry": {"coordinates":[-75.317655,40.019224],"type":"Point"}
}