{
  "type": "Feature",
  "properties": {
    "iso:country":"US",
    "sg:address":"9 E Athens Ave",
    "sg:city":"Ardmore",
    "sg:classifiers":[
        {
            "category":"Professional",
            "subcategory":"Business Services",
            "type":"Services"
        }
    ],
    "sg:phone":"+1   ",
    "sg:postcode":"19003",
    "sg:province":"PA",
    "wof:name":"Midlantic Pool Management",
    "wof:placetype":"venue"
},
  "geometry": {"coordinates":[-75.292936,40.006812],"type":"Point"}
}