{
  "type": "Feature",
  "properties": {
    "iso:country":"US",
    "sg:address":"519 58th St",
    "sg:city":"Altoona",
    "sg:classifiers":[
        {
            "category":"Organizations",
            "subcategory":"Religious Organization",
            "type":"Services"
        }
    ],
    "sg:phone":"+1 814 944 7187",
    "sg:postcode":"16602",
    "sg:province":"PA",
    "wof:name":"St George Orthodox Church",
    "wof:placetype":"venue"
},
  "geometry": {"coordinates":[-78.423171,40.471033],"type":"Point"}
}