{
  "type": "Feature",
  "properties": {
    "iso:country":"US",
    "sg:address":"1101 E Main St",
    "sg:city":"Norristown",
    "sg:classifiers":[
        {
            "category":"Autos & Motor Vehicles",
            "subcategory":"Automobile Sales",
            "type":"Retail Goods"
        }
    ],
    "sg:phone":"+1 610 272 7711",
    "sg:postcode":"19401",
    "sg:province":"PA",
    "sg:tags":[
        "car",
        "dealer"
    ],
    "wof:name":"Conicelli Mitsubishi",
    "wof:placetype":"venue"
},
  "geometry": {"coordinates":[-75.324046,40.108554],"type":"Point"}
}