{
  "type": "Feature",
  "properties": {
    "addr:full":"259 Lincoln Hwy W Coatesville PA 19320",
    "addr:housenumber":"259",
    "addr:postcode":"19320",
    "addr:street":"Lincoln Hwy W",
    "iso:country":"US",
    "sg:address":"259 Lincoln Hwy W",
    "sg:city":"Coatesville",
    "sg:classifiers":[
        {
            "category":"Shopping",
            "subcategory":"Florist",
            "type":"Retail Goods"
        }
    ],
    "sg:phone":"+1   ",
    "sg:postcode":"19320",
    "sg:province":"PA",
    "wof:name":"Coatesville Flower Shop",
    "wof:placetype":"venue"
},
  "geometry": {"coordinates":[-75.829528,39.981729],"type":"Point"}
}