{
  "type": "Feature",
  "properties": {
    "iso:country":"US",
    "sg:address":"1 Tyler Ct",
    "sg:city":"Carlisle",
    "sg:classifiers":[
        {
            "category":"Health Services",
            "subcategory":"Doctor",
            "type":"Services"
        }
    ],
    "sg:phone":"+1 717 218 7471",
    "sg:postcode":"17015",
    "sg:province":"PA",
    "sg:tags":[
        "physician",
        "surgeon"
    ],
    "wof:name":"Hanger Orthopedics Group",
    "wof:placetype":"venue"
},
  "geometry": {"coordinates":[-77.22085199999999,40.185385],"type":"Point"}
}