{
  "type": "Feature",
  "properties": {
    "iso:country":"US",
    "sg:address":"8916 Prindle Rd",
    "sg:city":"North East",
    "sg:classifiers":[
        {
            "category":"Building & Trades",
            "subcategory":"Construction",
            "type":"Services"
        }
    ],
    "sg:phone":"+1 814 899 3383",
    "sg:postcode":"16428",
    "sg:province":"PA",
    "sg:tags":[
        "concrete",
        "contractor"
    ],
    "wof:name":"Lonyo Brothers Concrete Inc",
    "wof:placetype":"venue"
},
  "geometry": {"coordinates":[-79.903273,42.137936],"type":"Point"}
}