{
  "type": "Feature",
  "properties": {
    "addr:full":"1219 Manheim Pike Lancaster PA 17601",
    "addr:housenumber":"1219",
    "addr:postcode":"17601",
    "addr:street":"Manheim Pike",
    "iso:country":"US",
    "sg:address":"1219 Manheim Pike",
    "sg:city":"Lancaster",
    "sg:classifiers":[
        {
            "category":"Building & Trades",
            "subcategory":"Construction",
            "type":"Services"
        }
    ],
    "sg:phone":"+1 717 393 0859",
    "sg:postcode":"17601",
    "sg:province":"PA",
    "sg:tags":[
        "home",
        "improvement"
    ],
    "wof:name":"George J Grove & Son Inc",
    "wof:placetype":"venue"
},
  "geometry": {"coordinates":[-76.32080999999999,40.06074],"type":"Point"}
}