{
  "type": "Feature",
  "properties": {
    "iso:country":"US",
    "sg:address":"355 Carter Moir Dr",
    "sg:city":"Lancaster",
    "sg:classifiers":[
        {
            "category":"Shopping",
            "subcategory":"Jewelry",
            "type":"Retail Goods"
        }
    ],
    "sg:phone":"+1   ",
    "sg:postcode":"17601",
    "sg:province":"PA",
    "wof:name":"Trace Jewelers",
    "wof:placetype":"venue"
},
  "geometry": {"coordinates":[-76.32607899999999,40.104734],"type":"Point"}
}