{
  "type": "Feature",
  "properties": {
    "iso:country":"US",
    "sg:address":"509 Wilshire Cir",
    "sg:city":"Mars",
    "sg:classifiers":[
        {
            "category":"Manufacturing",
            "subcategory":"Printing",
            "type":"Manufacturing & Wholesale Goods"
        }
    ],
    "sg:phone":"+1   ",
    "sg:postcode":"16046",
    "sg:province":"PA",
    "sg:tags":[
        "book"
    ],
    "wof:name":"Walsworth Publishing Co Inc",
    "wof:placetype":"venue"
},
  "geometry": {"coordinates":[-80.06550300000001,40.682438],"type":"Point"}
}