{
  "type": "Feature",
  "properties": {
    "iso:country":"US",
    "sg:address":"611 S Chester Rd",
    "sg:city":"Swarthmore",
    "sg:classifiers":[
        {
            "category":"Retail",
            "subcategory":"Laundry & Dry Cleaning",
            "type":"Services"
        }
    ],
    "sg:phone":"+1 610 690 1291",
    "sg:postcode":"19081",
    "sg:province":"PA",
    "sg:tags":[
        "drycleaning",
        "plant"
    ],
    "wof:name":"Venus Dry Cleaners",
    "wof:placetype":"venue"
},
  "geometry": {"coordinates":[-75.35372700000001,39.890344],"type":"Point"}
}