{
  "type": "Feature",
  "properties": {
    "iso:country":"US",
    "sg:address":"3036 Brodhead Rd",
    "sg:city":"Aliquippa",
    "sg:classifiers":[
        {
            "category":"Recreation",
            "type":"Entertainment"
        }
    ],
    "sg:phone":"+1   ",
    "sg:postcode":"15001",
    "sg:province":"PA",
    "sg:tags":[
        "equipment",
        "range",
        "golf",
        "driving"
    ],
    "wof:name":"Ironwood Golf Center",
    "wof:placetype":"venue"
},
  "geometry": {"coordinates":[-80.255695,40.577817],"type":"Point"}
}