{
  "type": "Feature",
  "properties": {
    "addr:full":"11 S Strawberry St Philadelphia PA 19106",
    "addr:housenumber":"11",
    "addr:postcode":"19106",
    "addr:street":"S Strawberry St",
    "iso:country":"US",
    "sg:address":"11 S Strawberry St",
    "sg:city":"Philadelphia",
    "sg:classifiers":[
        {
            "category":"Arts & Performance",
            "subcategory":"Theater",
            "type":"Entertainment"
        }
    ],
    "sg:phone":"+1 215 925 3805",
    "sg:postcode":"19106",
    "sg:province":"PA",
    "sg:tags":[
        "bureau"
    ],
    "wof:name":"Bash Entertainment",
    "wof:placetype":"venue"
},
  "geometry": {"coordinates":[-75.14439,39.949454],"type":"Point"}
}