{
  "type": "Feature",
  "properties": {
    "iso:country":"US",
    "sg:address":"1601 Walnut St. Ste 1514",
    "sg:city":"Philadelphia",
    "sg:classifiers":[
        {
            "category":"Professional",
            "type":"Services"
        },
        {
            "category":"Professional",
            "subcategory":"Computer Services",
            "type":"Services"
        }
    ],
    "sg:phone":"+1 215 825 5143",
    "sg:postcode":"19102",
    "sg:province":"PA",
    "sg:tags":[
        "repair"
    ],
    "sg:website":"www.voree.net",
    "wof:name":"Laptop Repair Philadelphia By Voree It Solutions",
    "wof:placetype":"venue"
},
  "geometry": {"coordinates":[-75.16752700000001,39.949779],"type":"Point"}
}