{
  "type": "Feature",
  "properties": {
    "iso:country":"US",
    "sg:address":"8 W Butler Ave",
    "sg:city":"Ambler",
    "sg:classifiers":[
        {
            "category":"Restaurant",
            "type":"Food & Drink"
        }
    ],
    "sg:menulink":"http://www.allmenus.com/pa/ambler/267447-bridgets-at-8-west/menu/",
    "sg:phone":"+1 267 465 2000",
    "sg:postcode":"19002",
    "sg:province":"PA",
    "wof:name":"Bridget's at 8 West",
    "wof:placetype":"venue"
},
  "geometry": {"coordinates":[-75.22408299999999,40.153668],"type":"Point"}
}