{
  "type": "Feature",
  "properties": {
    "addr:full":"830 N Broad St Philadelphia PA 19130",
    "addr:housenumber":"830",
    "addr:postcode":"19130",
    "addr:street":"N Broad St",
    "iso:country":"US",
    "sg:address":"830 N Broad St",
    "sg:city":"Philadelphia",
    "sg:classifiers":[
        {
            "category":"Health Services",
            "subcategory":"Doctor",
            "type":"Services"
        }
    ],
    "sg:phone":"+1 215 765 6600",
    "sg:postcode":"19130",
    "sg:province":"PA",
    "sg:tags":[
        "physician",
        "surgeon"
    ],
    "wof:name":"Center City Medical Ctr",
    "wof:placetype":"venue"
},
  "geometry": {"coordinates":[-75.16010199999999,39.968731],"type":"Point"}
}