{
  "type": "Feature",
  "properties": {
    "iso:country":"US",
    "sg:address":"136 W High St Apt 6",
    "sg:city":"Bellefonte",
    "sg:classifiers":[
        {
            "category":"Health Services",
            "subcategory":"Doctor",
            "type":"Services"
        }
    ],
    "sg:phone":"+1 814 355 4082",
    "sg:postcode":"16823",
    "sg:province":"PA",
    "sg:tags":[
        "podiatrist"
    ],
    "wof:name":"Assalita Larry J Podiatrist",
    "wof:placetype":"venue"
},
  "geometry": {"coordinates":[-77.778503,40.9119],"type":"Point"}
}