{
  "type": "Feature",
  "properties": {
    "addr:full":"538 High St Bethlehem PA 18018",
    "addr:housenumber":"538",
    "addr:postcode":"18018",
    "addr:street":"High St",
    "iso:country":"US",
    "sg:address":"538 High St",
    "sg:city":"Bethlehem",
    "sg:classifiers":[
        {
            "category":"Shopping",
            "subcategory":"Florist",
            "type":"Retail Goods"
        }
    ],
    "sg:phone":"+1   ",
    "sg:postcode":"18018",
    "sg:province":"PA",
    "wof:name":"Elysian Flds Specialty Florals",
    "wof:placetype":"venue"
},
  "geometry": {"coordinates":[-75.373244,40.6222],"type":"Point"}
}