{
  "type": "Feature",
  "properties": {
    "addr:full":"370 Saint Charles Way York PA 17402",
    "addr:housenumber":"370",
    "addr:postcode":"17402",
    "addr:street":"Saint Charles Way",
    "iso:country":"US",
    "sg:address":"370 Saint Charles Way",
    "sg:city":"York",
    "sg:classifiers":[
        {
            "category":"Health Services",
            "subcategory":"Doctor",
            "type":"Services"
        }
    ],
    "sg:phone":"+1   ",
    "sg:postcode":"17402",
    "sg:province":"PA",
    "sg:tags":[
        "medical"
    ],
    "wof:name":"York Health Center Mind & Body",
    "wof:placetype":"venue"
},
  "geometry": {"coordinates":[-76.688586,39.930386],"type":"Point"}
}