{
  "type": "Feature",
  "properties": {
    "iso:country":"US",
    "sg:address":"152 Autumn Dr",
    "sg:city":"Johnstown",
    "sg:classifiers":[
        {
            "category":"Shopping",
            "type":"Retail Goods"
        }
    ],
    "sg:phone":"+1   ",
    "sg:postcode":"15904",
    "sg:province":"PA",
    "sg:tags":[
        "merchandise"
    ],
    "wof:name":"Pleasure Pools Inc",
    "wof:placetype":"venue"
},
  "geometry": {"coordinates":[-78.892067,40.27181],"type":"Point"}
}