{
  "type": "Feature",
  "properties": {
    "iso:country":"US",
    "sg:address":"181 Denny Rd",
    "sg:city":"Valencia",
    "sg:classifiers":[
        {
            "category":"Building & Trades",
            "subcategory":"Construction",
            "type":"Services"
        }
    ],
    "sg:phone":"+1 724 898 3366",
    "sg:postcode":"16059",
    "sg:province":"PA",
    "sg:tags":[
        "house",
        "improvement",
        "home"
    ],
    "wof:name":"Sowers Building and Remodeling",
    "wof:placetype":"venue"
},
  "geometry": {"coordinates":[-79.951166,40.682435],"type":"Point"}
}