{
  "type": "Feature",
  "properties": {
    "iso:country":"US",
    "sg:address":"204 Main St",
    "sg:city":"Monroeton",
    "sg:classifiers":[
        {
            "category":"Shopping",
            "subcategory":"Gifts & Souvenirs",
            "type":"Retail Goods"
        }
    ],
    "sg:phone":"+1 570 265 6511",
    "sg:postcode":"18832",
    "sg:province":"PA",
    "sg:tags":[
        "shop"
    ],
    "wof:name":"Just The Place",
    "wof:placetype":"venue"
},
  "geometry": {"coordinates":[-76.473938,41.714592],"type":"Point"}
}