{
  "type": "Feature",
  "properties": {
    "iso:country":"US",
    "sg:address":"120 Brennen Ln",
    "sg:city":"Evans City",
    "sg:classifiers":[
        {
            "category":"Building & Trades",
            "subcategory":"Construction",
            "type":"Services"
        }
    ],
    "sg:phone":"+1 724 865 2929",
    "sg:postcode":"16033",
    "sg:province":"PA",
    "sg:tags":[
        "home",
        "general",
        "contractor"
    ],
    "wof:name":"Brennan Builders Inc",
    "wof:placetype":"venue"
},
  "geometry": {"coordinates":[-80.068361,40.848668],"type":"Point"}
}