{
  "type": "Feature",
  "properties": {
    "iso:country":"US",
    "sg:address":"1420 Belfield Ave",
    "sg:city":"Philadelphia",
    "sg:classifiers":[
        {
            "category":"Autos & Motor Vehicles",
            "subcategory":"Auto Supplies",
            "type":"Retail Goods"
        }
    ],
    "sg:phone":"+1 215 457 4002",
    "sg:postcode":"19140",
    "sg:province":"PA",
    "sg:tags":[
        "automobile",
        "part",
        "accessory"
    ],
    "wof:name":"Heo Enterprises Inc",
    "wof:placetype":"venue"
},
  "geometry": {"coordinates":[-75.14856,40.023332],"type":"Point"}
}