{
  "type": "Feature",
  "properties": {
    "iso:country":"US",
    "sg:address":"506 Carey Ave",
    "sg:city":"Wilkes Barre",
    "sg:classifiers":[
        {
            "category":"Health Services",
            "subcategory":"Chiropractor",
            "type":"Services"
        }
    ],
    "sg:phone":"+1 570 829 0470",
    "sg:postcode":"18702",
    "sg:province":"PA",
    "wof:name":"William Ermisch DC",
    "wof:placetype":"venue"
},
  "geometry": {"coordinates":[-75.913504,41.237673],"type":"Point"}
}