{
  "type": "Feature",
  "properties": {
    "addr:full":"5045 Buffalo Rd Erie PA 16510",
    "addr:housenumber":"5045",
    "addr:postcode":"16510",
    "addr:street":"Buffalo Rd",
    "iso:country":"US",
    "sg:address":"5045 Buffalo Rd",
    "sg:city":"Erie",
    "sg:classifiers":[
        {
            "category":"Building & Trades",
            "subcategory":"Equipment Rental",
            "type":"Services"
        }
    ],
    "sg:phone":"+1 814 899 5870",
    "sg:postcode":"16510",
    "sg:province":"PA",
    "sg:tags":[
        "yard",
        "contractors'"
    ],
    "sg:website":"http://www.grandrental.com",
    "wof:name":"Grand Rental Station",
    "wof:placetype":"venue"
},
  "geometry": {"coordinates":[-79.987747,42.153461],"type":"Point"}
}