{
  "type": "Feature",
  "properties": {
    "iso:country":"US",
    "sg:address":"804 Pennsylvania Ave",
    "sg:city":"Mckeesport",
    "sg:classifiers":[
        {
            "category":"Health Services",
            "subcategory":"Chiropractor",
            "type":"Services"
        }
    ],
    "sg:phone":"+1 412 673 2214",
    "sg:postcode":"15131",
    "sg:province":"PA",
    "wof:name":"Robert Miller DC",
    "wof:placetype":"venue"
},
  "geometry": {"coordinates":[-79.82656900000001,40.356082],"type":"Point"}
}