{
  "type": "Feature",
  "properties": {
    "iso:country":"US",
    "sg:address":"340 W 7th Ave",
    "sg:city":"Tarentum",
    "sg:classifiers":[
        {
            "category":"Building & Trades",
            "subcategory":"Cleaning & Sanitation",
            "type":"Services"
        }
    ],
    "sg:phone":"+1 724 224 2711",
    "sg:postcode":"15084",
    "sg:province":"PA",
    "sg:tags":[
        "window",
        "maintenance"
    ],
    "wof:name":"Apex Maintenance Inc",
    "wof:placetype":"venue"
},
  "geometry": {"coordinates":[-79.763948,40.59867],"type":"Point"}
}