{
  "type": "Feature",
  "properties": {
    "addr:full":"152 N 52nd St Philadelphia PA 19139",
    "addr:housenumber":"152",
    "addr:postcode":"19139",
    "addr:street":"N 52Nd St",
    "iso:country":"US",
    "sg:address":"152 N 52nd St",
    "sg:city":"Philadelphia",
    "sg:classifiers":[
        {
            "category":"Shopping",
            "subcategory":"Discount & Variety Stores",
            "type":"Retail Goods"
        }
    ],
    "sg:phone":"+1   ",
    "sg:postcode":"19139",
    "sg:province":"PA",
    "wof:name":"Trevor Bain",
    "wof:placetype":"venue"
},
  "geometry": {"coordinates":[-75.224425,39.962291],"type":"Point"}
}