{
  "type": "Feature",
  "properties": {
    "iso:country":"US",
    "sg:address":"13 Creek Rd",
    "sg:city":"Mc Kees Rocks",
    "sg:classifiers":[
        {
            "category":"Wholesale",
            "subcategory":"Scrap",
            "type":"Manufacturing & Wholesale Goods"
        }
    ],
    "sg:phone":"+1   ",
    "sg:postcode":"15136",
    "sg:province":"PA",
    "sg:tags":[
        "auto",
        "material",
        "parts",
        "used"
    ],
    "wof:name":"McKees Rocks Auto Wrecking",
    "wof:placetype":"venue"
},
  "geometry": {"coordinates":[-80.095252,40.454353],"type":"Point"}
}