{
  "type": "Feature",
  "properties": {
    "iso:country":"US",
    "sg:address":"900 Sleepy Hollow Rd",
    "sg:city":"Pittsburgh",
    "sg:classifiers":[
        {
            "category":"Retail",
            "subcategory":"Laundry & Dry Cleaning",
            "type":"Services"
        }
    ],
    "sg:phone":"+1 412 341 5888",
    "sg:postcode":"15234",
    "sg:province":"PA",
    "wof:name":"Wash Works Laundryhouse",
    "wof:placetype":"venue"
},
  "geometry": {"coordinates":[-80.01795199999999,40.371991],"type":"Point"}
}