{
  "type": "Feature",
  "properties": {
    "addr:full":"227 E King St Malvern PA 19355",
    "addr:housenumber":"227",
    "addr:postcode":"19355",
    "addr:street":"E King St",
    "iso:country":"US",
    "sg:address":"227 E King St",
    "sg:city":"Malvern",
    "sg:classifiers":[
        {
            "category":"Real Estate",
            "subcategory":"Real Estate Operator",
            "type":"Services"
        }
    ],
    "sg:phone":"+1 610 240 9016",
    "sg:postcode":"19355",
    "sg:province":"PA",
    "sg:tags":[
        "building",
        "commercial"
    ],
    "wof:name":"Brentwood Management Corp",
    "wof:placetype":"venue"
},
  "geometry": {"coordinates":[-75.509073,40.037584],"type":"Point"}
}