{
  "type": "Feature",
  "properties": {
    "iso:country":"US",
    "sg:address":"228 W Main St",
    "sg:city":"New Holland",
    "sg:classifiers":[
        {
            "category":"Building & Trades",
            "subcategory":"Construction",
            "type":"Services"
        }
    ],
    "sg:phone":"+1   ",
    "sg:postcode":"17557",
    "sg:province":"PA",
    "sg:tags":[
        "hanging",
        "contractor"
    ],
    "wof:name":"D Smith Painting",
    "wof:placetype":"venue"
},
  "geometry": {"coordinates":[-76.093,40.101212],"type":"Point"}
}