{
  "type": "Feature",
  "properties": {
    "addr:full":"214 W Broad St Bethlehem PA 18018",
    "addr:housenumber":"214",
    "addr:postcode":"18018",
    "addr:street":"W Broad St",
    "iso:country":"US",
    "sg:address":"214 W Broad St",
    "sg:city":"Bethlehem",
    "sg:classifiers":[
        {
            "category":"Personal",
            "subcategory":"Massage",
            "type":"Services"
        }
    ],
    "sg:phone":"+1 610 865 6800",
    "sg:postcode":"18018",
    "sg:province":"PA",
    "wof:name":"Albanese Krisann J Cmt",
    "wof:placetype":"venue"
},
  "geometry": {"coordinates":[-75.386002,40.622501],"type":"Point"}
}