{
  "type": "Feature",
  "properties": {
    "iso:country":"US",
    "sg:address":"130 Clara Ln",
    "sg:city":"Library",
    "sg:classifiers":[
        {
            "category":"Building & Trades",
            "subcategory":"Plumbing",
            "type":"Services"
        }
    ],
    "sg:phone":"+1   ",
    "sg:postcode":"15129",
    "sg:province":"PA",
    "sg:tags":[
        "contractor"
    ],
    "wof:name":"M & G Heating & Cooling Inc",
    "wof:placetype":"venue"
},
  "geometry": {"coordinates":[-80.05096399999999,40.29039],"type":"Point"}
}