{
  "type": "Feature",
  "properties": {
    "iso:country":"US",
    "sg:address":"1230 Garloch Dr",
    "sg:city":"Erie",
    "sg:classifiers":[
        {
            "category":"Professional",
            "type":"Services"
        }
    ],
    "sg:phone":"+1   ",
    "sg:postcode":"16505",
    "sg:province":"PA",
    "wof:name":"Louis P Dreisbach",
    "wof:placetype":"venue"
},
  "geometry": {"coordinates":[-80.20769300000001,42.081743],"type":"Point"}
}