{
  "type": "Feature",
  "properties": {
    "iso:country":"US",
    "sg:address":"5817 Wattsburg Rd",
    "sg:city":"Erie",
    "sg:classifiers":[
        {
            "category":"Home & Garden",
            "subcategory":"Furniture",
            "type":"Retail Goods"
        },
        {
            "category":"Home & Garden",
            "subcategory":"Home Furnishings",
            "type":"Retail Goods"
        }
    ],
    "sg:phone":"+1 814 825 1098",
    "sg:postcode":"16509",
    "sg:province":"PA",
    "sg:tags":[
        "stove",
        "wood",
        "burning"
    ],
    "wof:name":"Weavers Harmans Stoves",
    "wof:placetype":"venue"
},
  "geometry": {"coordinates":[-80.008967,42.096045],"type":"Point"}
}