{
  "type": "Feature",
  "properties": {
    "iso:country":"US",
    "sg:address":"931 W Washington St",
    "sg:city":"Allentown",
    "sg:classifiers":[
        {
            "category":"Manufacturing",
            "subcategory":"Glass & Minerals",
            "type":"Manufacturing & Wholesale Goods"
        }
    ],
    "sg:phone":"+1 610 434 5485",
    "sg:postcode":"18102",
    "sg:province":"PA",
    "sg:tags":[
        "product",
        "mfg"
    ],
    "wof:name":"Neff-Chattoe Co",
    "wof:placetype":"venue"
},
  "geometry": {"coordinates":[-75.482635,40.611998],"type":"Point"}
}