{
  "type": "Feature",
  "properties": {
    "iso:country":"US",
    "sg:address":"283 Schuylkill Rd",
    "sg:city":"Phoenixville",
    "sg:classifiers":[
        {
            "category":"Food & Beverages",
            "subcategory":"Groceries & Convenience Stores",
            "type":"Retail Goods"
        }
    ],
    "sg:phone":"+1   ",
    "sg:postcode":"19460",
    "sg:province":"PA",
    "wof:name":"Cris Oriental Store",
    "wof:placetype":"venue"
},
  "geometry": {"coordinates":[-75.542647,40.136082],"type":"Point"}
}