{
  "type": "Feature",
  "properties": {
    "iso:country":"US",
    "sg:address":"2621 W Girard Ave",
    "sg:city":"Philadelphia",
    "sg:classifiers":[
        {
            "category":"Real Estate",
            "subcategory":"Real Estate Services",
            "type":"Services"
        }
    ],
    "sg:phone":"+1 267 519 0895",
    "sg:postcode":"19130",
    "sg:province":"PA",
    "sg:website":"mmpartnersllc.com",
    "wof:name":"MMPartners LLC",
    "wof:placetype":"venue"
},
  "geometry": {"coordinates":[-75.179699,39.974297],"type":"Point"}
}