{
  "type": "Feature",
  "properties": {
    "iso:country":"US",
    "sg:address":"124 Mahoning Dr E",
    "sg:city":"Lehighton",
    "sg:classifiers":[
        {
            "category":"Food & Beverages",
            "subcategory":"Meat & Fish",
            "type":"Retail Goods"
        }
    ],
    "sg:phone":"+1 610 377 5233",
    "sg:postcode":"18235",
    "sg:province":"PA",
    "wof:name":"Heintzelman's Meat Market",
    "wof:placetype":"venue"
},
  "geometry": {"coordinates":[-75.730118,40.828009],"type":"Point"}
}