{
  "type": "Feature",
  "properties": {
    "iso:country":"US",
    "sg:address":"49 E 5th St",
    "sg:city":"Wind Gap",
    "sg:classifiers":[
        {
            "category":"Building & Trades",
            "subcategory":"Construction",
            "type":"Services"
        }
    ],
    "sg:phone":"+1 610 863 6755",
    "sg:postcode":"18091",
    "sg:province":"PA",
    "sg:tags":[
        "painter"
    ],
    "wof:name":"Michael J Dovyak Jr Painting",
    "wof:placetype":"venue"
},
  "geometry": {"coordinates":[-75.29315200000001,40.842524],"type":"Point"}
}