{
  "type": "Feature",
  "properties": {
    "iso:country":"US",
    "sg:address":"1212 Millersville Pike",
    "sg:city":"Lancaster",
    "sg:classifiers":[
        {
            "category":"Shopping",
            "subcategory":"Jewelry",
            "type":"Retail Goods"
        }
    ],
    "sg:phone":"+1 717 393 4300",
    "sg:postcode":"17603",
    "sg:province":"PA",
    "wof:name":"Oletowne Jewelers",
    "wof:placetype":"venue"
},
  "geometry": {"coordinates":[-76.324619,40.028683],"type":"Point"}
}