{
  "type": "Feature",
  "properties": {
    "iso:country":"US",
    "sg:address":"120 S 3rd St",
    "sg:city":"Connellsville",
    "sg:classifiers":[
        {
            "category":"Professional",
            "subcategory":"Lawyer & Legal Services",
            "type":"Services"
        }
    ],
    "sg:phone":"+1 724 628 7955",
    "sg:postcode":"15425",
    "sg:province":"PA",
    "sg:tags":[
        "attorney"
    ],
    "wof:name":"Horewitz Cordaro Bowlen Miele",
    "wof:placetype":"venue"
},
  "geometry": {"coordinates":[-79.59478,40.01567],"type":"Point"}
}