{
  "type": "Feature",
  "properties": {
    "addr:full":"3545 Marietta Ave Lancaster PA 17601",
    "addr:housenumber":"3545",
    "addr:postcode":"17601",
    "addr:street":"Marietta Ave",
    "iso:country":"US",
    "sg:address":"3545 Marietta Ave",
    "sg:city":"Lancaster",
    "sg:classifiers":[
        {
            "category":"Wholesale",
            "subcategory":"Machinery & Supplies",
            "type":"Manufacturing & Wholesale Goods"
        }
    ],
    "sg:phone":"+1 717 285 0091",
    "sg:postcode":"17601",
    "sg:province":"PA",
    "sg:tags":[
        "equipment",
        "system",
        "vacuum"
    ],
    "wof:name":"T R Technology",
    "wof:placetype":"venue"
},
  "geometry": {"coordinates":[-76.430369,40.063067],"type":"Point"}
}