{
  "type": "Feature",
  "properties": {
    "iso:country":"US",
    "sg:address":"635 W Main St",
    "sg:city":"Grove City",
    "sg:classifiers":[
        {
            "category":"Building & Trades",
            "subcategory":"Equipment Rental",
            "type":"Services"
        }
    ],
    "sg:phone":"+1   ",
    "sg:postcode":"16127",
    "sg:province":"PA",
    "sg:tags":[
        "field",
        "oil",
        "rent",
        "lease"
    ],
    "wof:name":"Halliburton Resource MGT",
    "wof:placetype":"venue"
},
  "geometry": {"coordinates":[-80.095162,41.162177],"type":"Point"}
}