{
  "type": "Feature",
  "properties": {
    "iso:country":"US",
    "sg:address":"5020 Louise Dr",
    "sg:city":"Mechanicsburg",
    "sg:classifiers":[
        {
            "category":"Professional",
            "subcategory":"Advertising",
            "type":"Services"
        }
    ],
    "sg:phone":"+1   ",
    "sg:postcode":"17055",
    "sg:province":"PA",
    "sg:tags":[
        "mail",
        "direct",
        "marketing"
    ],
    "wof:name":"American Mint LLC",
    "wof:placetype":"venue"
},
  "geometry": {"coordinates":[-76.956554,40.204058],"type":"Point"}
}