{
  "type": "Feature",
  "properties": {
    "iso:country":"US",
    "sg:address":"1921 Edwards Rd",
    "sg:city":"Folcroft",
    "sg:classifiers":[
        {
            "category":"Building & Trades",
            "subcategory":"Construction",
            "type":"Services"
        }
    ],
    "sg:phone":"+1 610 461 1419",
    "sg:postcode":"19032",
    "sg:province":"PA",
    "sg:tags":[
        "house"
    ],
    "wof:name":"L Brink Construction",
    "wof:placetype":"venue"
},
  "geometry": {"coordinates":[-75.282392,39.887072],"type":"Point"}
}