{
  "type": "Feature",
  "properties": {
    "addr:full":"337 Wharton St Philadelphia PA 19147",
    "addr:housenumber":"337",
    "addr:postcode":"19147",
    "addr:street":"Wharton St",
    "iso:country":"US",
    "sg:address":"337 Wharton St",
    "sg:city":"Philadelphia",
    "sg:classifiers":[
        {
            "category":"Professional",
            "subcategory":"Employment Agencies",
            "type":"Services"
        }
    ],
    "sg:phone":"+1   ",
    "sg:postcode":"19147",
    "sg:province":"PA",
    "wof:name":"Lenore Terway Rn",
    "wof:placetype":"venue"
},
  "geometry": {"coordinates":[-75.150851,39.932002],"type":"Point"}
}