{
  "type": "Feature",
  "properties": {
    "addr:full":"1011 E Erie Ave Philadelphia PA 19124",
    "addr:housenumber":"1011",
    "addr:postcode":"19124",
    "addr:street":"E Erie Ave",
    "iso:country":"US",
    "sg:address":"1011 E Erie Ave",
    "sg:city":"Philadelphia",
    "sg:classifiers":[
        {
            "category":"Utilities",
            "subcategory":"Telephone",
            "type":"Services"
        }
    ],
    "sg:phone":"+1   ",
    "sg:postcode":"19124",
    "sg:province":"PA",
    "sg:tags":[
        "owner",
        "pay"
    ],
    "wof:name":"Tri-County",
    "wof:placetype":"venue"
},
  "geometry": {"coordinates":[-75.108036,40.005431],"type":"Point"}
}