{
  "type": "Feature",
  "properties": {
    "iso:country":"US",
    "sg:address":"4 Irvine Row",
    "sg:city":"Carlisle",
    "sg:classifiers":[
        {
            "category":"Professional",
            "subcategory":"Lawyer & Legal Services",
            "type":"Services"
        }
    ],
    "sg:phone":"+1 717 701 8412",
    "sg:postcode":"17013",
    "sg:province":"PA",
    "sg:tags":[
        "plan"
    ],
    "wof:name":"Law Office Of Sean M. Shultz P.C.",
    "wof:placetype":"venue"
},
  "geometry": {"coordinates":[-77.18841999999999,40.201449],"type":"Point"}
}