{
  "type": "Feature",
  "properties": {
    "iso:country":"US",
    "sg:address":"1408 State Rte 309",
    "sg:city":"Sellersville",
    "sg:classifiers":[
        {
            "category":"Restaurant",
            "type":"Food & Drink"
        }
    ],
    "sg:phone":"+1   ",
    "sg:postcode":"18951",
    "sg:province":"PA",
    "sg:tags":[
        "eating"
    ],
    "wof:name":"A C & L Food Service",
    "wof:placetype":"venue"
},
  "geometry": {"coordinates":[-75.37523299999999,40.481248],"type":"Point"}
}