{
  "type": "Feature",
  "properties": {
    "addr:full":"25 Northgate Plz Zelienople PA 16063",
    "addr:housenumber":"25",
    "addr:postcode":"16063",
    "addr:street":"Northgate Plz",
    "iso:country":"US",
    "sg:address":"25 Northgate Plz",
    "sg:city":"Zelienople",
    "sg:classifiers":[
        {
            "category":"Shopping",
            "subcategory":"Pharmacy",
            "type":"Retail Goods"
        }
    ],
    "sg:phone":"+1 724 452 6851",
    "sg:postcode":"16063",
    "sg:province":"PA",
    "sg:tags":[
        "drugstore"
    ],
    "wof:name":"Eckerd Drugs",
    "wof:placetype":"venue"
},
  "geometry": {"coordinates":[-80.137497,40.772301],"type":"Point"}
}