{
  "type": "Feature",
  "properties": {
    "iso:country":"US",
    "sg:address":"672 Horning Rd",
    "sg:city":"Pittsburgh",
    "sg:classifiers":[
        {
            "category":"Building & Trades",
            "subcategory":"Landscaping Services",
            "type":"Services"
        }
    ],
    "sg:phone":"+1 412 833 1444",
    "sg:postcode":"15102",
    "sg:province":"PA",
    "sg:tags":[
        "lawn",
        "maintenance",
        "grounds"
    ],
    "wof:name":"Metro Lawn Landscape Supply",
    "wof:placetype":"venue"
},
  "geometry": {"coordinates":[-80.008805,40.340685],"type":"Point"}
}