{
  "type": "Feature",
  "properties": {
    "iso:country":"US",
    "sg:address":"915 W Maple St",
    "sg:city":"Valley View",
    "sg:classifiers":[
        {
            "category":"Government",
            "subcategory":"Office",
            "type":"Public Place"
        }
    ],
    "sg:phone":"+1 570 682 3228",
    "sg:postcode":"17983",
    "sg:province":"PA",
    "sg:tags":[
        "govt",
        "city"
    ],
    "wof:name":"Hegins Township Water Auth",
    "wof:placetype":"venue"
},
  "geometry": {"coordinates":[-76.53569,40.645244],"type":"Point"}
}