{
  "type": "Feature",
  "properties": {
    "iso:country":"US",
    "sg:address":"121 Mccabe Dr",
    "sg:city":"Greensburg",
    "sg:classifiers":[
        {
            "category":"Professional",
            "subcategory":"Lawyer & Legal Services",
            "type":"Services"
        }
    ],
    "sg:phone":"+1 724 837 9320",
    "sg:postcode":"15601",
    "sg:province":"PA",
    "sg:tags":[
        "plan"
    ],
    "wof:name":"Shortgoughenour Cyndia",
    "wof:placetype":"venue"
},
  "geometry": {"coordinates":[-79.54800299999999,40.329917],"type":"Point"}
}