{
  "type": "Feature",
  "properties": {
    "iso:country":"US",
    "sg:address":"501 Old York Rd",
    "sg:city":"Jenkintown",
    "sg:classifiers":[
        {
            "category":"Retail",
            "subcategory":"Laundry & Dry Cleaning",
            "type":"Services"
        }
    ],
    "sg:phone":"+1 215 885 4731",
    "sg:postcode":"19046",
    "sg:province":"PA",
    "sg:tags":[
        "cleaners",
        "pressing",
        "garment"
    ],
    "wof:name":"Michael's Cleaners",
    "wof:placetype":"venue"
},
  "geometry": {"coordinates":[-75.125835,40.098941],"type":"Point"}
}