{
  "type": "Feature",
  "properties": {
    "iso:country":"US",
    "sg:address":"1900 Kennedy St",
    "sg:city":"Philadelphia",
    "sg:classifiers":[
        {
            "category":"Parking",
            "type":"Transportation"
        }
    ],
    "sg:phone":"+1   ",
    "sg:postcode":"19124",
    "sg:province":"PA",
    "sg:tags":[
        "automobile"
    ],
    "wof:name":"Square Kennedy Corp",
    "wof:placetype":"venue"
},
  "geometry": {"coordinates":[-75.069068,40.01701],"type":"Point"}
}