{
  "type": "Feature",
  "properties": {
    "addr:full":"805 Rozel Ave Southampton PA 18966",
    "addr:housenumber":"805",
    "addr:postcode":"18966",
    "addr:street":"Rozel Ave",
    "iso:country":"US",
    "sg:address":"805 Rozel Ave",
    "sg:city":"Southampton",
    "sg:classifiers":[
        {
            "category":"Retail",
            "subcategory":"Repair Shop",
            "type":"Services"
        }
    ],
    "sg:phone":"+1 215 322 4499",
    "sg:postcode":"18966",
    "sg:province":"PA",
    "sg:tags":[
        "radio",
        "television",
        "electrical"
    ],
    "wof:name":"A & M Electronics Inc",
    "wof:placetype":"venue"
},
  "geometry": {"coordinates":[-75.044088,40.168561],"type":"Point"}
}