{
  "type": "Feature",
  "properties": {
    "iso:country":"US",
    "sg:address":"38 Quail Hill Rd",
    "sg:city":"Pittsburgh",
    "sg:classifiers":[
        {
            "category":"Restaurant",
            "type":"Food & Drink"
        }
    ],
    "sg:phone":"+1   ",
    "sg:postcode":"15214",
    "sg:province":"PA",
    "sg:tags":[
        "eating"
    ],
    "wof:name":"Colleens Kettle Corn",
    "wof:placetype":"venue"
},
  "geometry": {"coordinates":[-79.99909700000001,40.488556],"type":"Point"}
}