{
  "type": "Feature",
  "properties": {
    "iso:country":"US",
    "sg:address":"659 3rd St",
    "sg:city":"Beaver",
    "sg:classifiers":[
        {
            "category":"Shopping",
            "subcategory":"Clothing, Apparel, & Fashions",
            "type":"Retail Goods"
        }
    ],
    "sg:phone":"+1 724 774 5340",
    "sg:postcode":"15009",
    "sg:province":"PA",
    "sg:tags":[
        "ready"
    ],
    "wof:name":"Shirley Shoppe",
    "wof:placetype":"venue"
},
  "geometry": {"coordinates":[-80.305164,40.695064],"type":"Point"}
}