{
  "type": "Feature",
  "properties": {
    "iso:country":"US",
    "sg:address":"4524 10th Ave",
    "sg:city":"Temple",
    "sg:classifiers":[
        {
            "category":"Wholesale",
            "subcategory":"Durable Goods & Equipment",
            "type":"Manufacturing & Wholesale Goods"
        }
    ],
    "sg:phone":"+1   ",
    "sg:postcode":"19560",
    "sg:province":"PA",
    "wof:name":"Inhome Oxygen & Medical Suppli",
    "wof:placetype":"venue"
},
  "geometry": {"coordinates":[-75.918899,40.404001],"type":"Point"}
}