{
  "type": "Feature",
  "properties": {
    "addr:full":"4020 Holly Dr Columbia PA 17512",
    "addr:housenumber":"4020",
    "addr:postcode":"17512",
    "addr:street":"Holly Dr",
    "iso:country":"US",
    "sg:address":"4020 Holly Dr",
    "sg:city":"Columbia",
    "sg:classifiers":[
        {
            "category":"Organizations",
            "subcategory":"Religious Organization",
            "type":"Services"
        }
    ],
    "sg:phone":"+1 717 684 8072",
    "sg:postcode":"17512",
    "sg:province":"PA",
    "sg:tags":[
        "church"
    ],
    "wof:name":"Ironville United Methodist Chr",
    "wof:placetype":"venue"
},
  "geometry": {"coordinates":[-76.46407499999999,40.055148],"type":"Point"}
}