{
  "type": "Feature",
  "properties": {
    "iso:country":"US",
    "sg:address":"830 Tremont Dr",
    "sg:city":"Downingtown",
    "sg:classifiers":[
        {
            "category":"Professional",
            "type":"Services"
        }
    ],
    "sg:phone":"+1   ",
    "sg:postcode":"19335",
    "sg:province":"PA",
    "wof:name":"H & L Creations Inc",
    "wof:placetype":"venue"
},
  "geometry": {"coordinates":[-75.70255299999999,40.036228],"type":"Point"}
}