{
  "type": "Feature",
  "properties": {
    "iso:country":"US",
    "sg:address":"3609 Chestnut St",
    "sg:city":"Philadelphia",
    "sg:classifiers":[
        {
            "category":"Shopping",
            "subcategory":"Pharmacy",
            "type":"Retail Goods"
        }
    ],
    "sg:phone":"+1 215 387 1752",
    "sg:postcode":"19104",
    "sg:province":"PA",
    "sg:tags":[
        "drugstore"
    ],
    "wof:name":"Millennium Pharmacy Systems",
    "wof:placetype":"venue"
},
  "geometry": {"coordinates":[-75.19458400000001,39.954834],"type":"Point"}
}