{
  "type": "Feature",
  "properties": {
    "iso:country":"US",
    "sg:address":"1589 Old Lairdsville Rd",
    "sg:city":"Muncy",
    "sg:phone":"+1   ",
    "sg:postcode":"17756",
    "sg:province":"PA",
    "sg:tags":[
        "wheat",
        "farm",
        "corn",
        "crop",
        "field",
        "berry"
    ],
    "wof:name":"Jay Nickels",
    "wof:placetype":"venue"
},
  "geometry": {"coordinates":[-76.66206099999999,41.21874],"type":"Point"}
}