{
  "type": "Feature",
  "properties": {
    "addr:full":"29 Connellsville St Uniontown PA 15401",
    "addr:housenumber":"29",
    "addr:postcode":"15401",
    "addr:street":"Connellsville St",
    "iso:country":"US",
    "sg:address":"29 Connellsville St",
    "sg:city":"Uniontown",
    "sg:classifiers":[
        {
            "category":"Professional",
            "type":"Services"
        }
    ],
    "sg:phone":"+1 724 438 0200",
    "sg:postcode":"15401",
    "sg:province":"PA",
    "sg:tags":[
        "establishment"
    ],
    "wof:name":"CEM Co",
    "wof:placetype":"venue"
},
  "geometry": {"coordinates":[-79.716311,39.898953],"type":"Point"}
}