{
  "type": "Feature",
  "properties": {
    "addr:full":"116 W End Dr Manheim PA 17545",
    "addr:housenumber":"116",
    "addr:postcode":"17545",
    "addr:street":"W End Dr",
    "iso:country":"US",
    "sg:address":"116 W End Dr",
    "sg:city":"Manheim",
    "sg:classifiers":[
        {
            "category":"Utilities",
            "subcategory":"Refuse",
            "type":"Services"
        }
    ],
    "sg:phone":"+1 717 665 4212",
    "sg:postcode":"17545",
    "sg:province":"PA",
    "sg:tags":[
        "disposal",
        "waste"
    ],
    "wof:name":"County Waste Inc",
    "wof:placetype":"venue"
},
  "geometry": {"coordinates":[-76.381739,40.168352],"type":"Point"}
}