{
  "type": "Feature",
  "properties": {
    "iso:country":"US",
    "sg:address":"38 Sweitzer Rd",
    "sg:city":"Mohnton",
    "sg:classifiers":[
        {
            "category":"Building & Trades",
            "subcategory":"Electrical",
            "type":"Services"
        }
    ],
    "sg:phone":"+1 610 796 8511",
    "sg:postcode":"19540",
    "sg:province":"PA",
    "sg:tags":[
        "electric",
        "contractor"
    ],
    "wof:name":"All-Tek Electric Inc",
    "wof:placetype":"venue"
},
  "geometry": {"coordinates":[-75.978492,40.238987],"type":"Point"}
}