{
  "type": "Feature",
  "properties": {
    "iso:country":"US",
    "sg:address":"113 Hollywood Ave",
    "sg:city":"Norristown",
    "sg:classifiers":[
        {
            "category":"Building & Trades",
            "subcategory":"Construction",
            "type":"Services"
        }
    ],
    "sg:phone":"+1   ",
    "sg:postcode":"19403",
    "sg:province":"PA",
    "sg:tags":[
        "house"
    ],
    "wof:name":"Cubbler Remodeling",
    "wof:placetype":"venue"
},
  "geometry": {"coordinates":[-75.40143,40.1435],"type":"Point"}
}