{
  "type": "Feature",
  "properties": {
    "iso:country":"US",
    "sg:address":"11695 Rte 56 E",
    "sg:city":"Armagh",
    "sg:classifiers":[
        {
            "category":"Health Services",
            "subcategory":"Chiropractor",
            "type":"Services"
        }
    ],
    "sg:phone":"+1 814 446 5555",
    "sg:postcode":"15920",
    "sg:province":"PA",
    "wof:name":"Laurel Chiropractic Assoc",
    "wof:placetype":"venue"
},
  "geometry": {"coordinates":[-79.032327,40.456086],"type":"Point"}
}