{
  "type": "Feature",
  "properties": {
    "addr:full":"3244 Brighton Rd Pittsburgh PA 15212",
    "addr:housenumber":"3244",
    "addr:postcode":"15212",
    "addr:street":"Brighton Rd",
    "iso:country":"US",
    "sg:address":"3244 Brighton Rd",
    "sg:city":"Pittsburgh",
    "sg:classifiers":[
        {
            "category":"Retail",
            "subcategory":"Laundry & Dry Cleaning",
            "type":"Services"
        }
    ],
    "sg:phone":"+1 412 761 2600",
    "sg:postcode":"15212",
    "sg:province":"PA",
    "sg:tags":[
        "drycleaning",
        "plant",
        "power"
    ],
    "wof:name":"Brighton Cleaners",
    "wof:placetype":"venue"
},
  "geometry": {"coordinates":[-80.03163000000001,40.476412],"type":"Point"}
}