{
  "type": "Feature",
  "properties": {
    "iso:country":"US",
    "sg:address":"600 Donaldson Rd",
    "sg:city":"Oakdale",
    "sg:classifiers":[
        {
            "category":"Education",
            "subcategory":"School",
            "type":"Public Place"
        }
    ],
    "sg:phone":"+1 724 695 8270",
    "sg:postcode":"15071",
    "sg:province":"PA",
    "wof:name":"Donaldson Elementary School",
    "wof:placetype":"venue"
},
  "geometry": {"coordinates":[-80.23321199999999,40.421779],"type":"Point"}
}