{
  "type": "Feature",
  "properties": {
    "addr:full":"3225 N 5th Street Hwy Reading PA 19605",
    "addr:housenumber":"3225",
    "addr:postcode":"19605",
    "addr:street":"N 5Th Street Hwy",
    "iso:country":"US",
    "sg:address":"3225 N 5th Street Hwy",
    "sg:city":"Reading",
    "sg:classifiers":[
        {
            "category":"Restaurant",
            "type":"Food & Drink"
        }
    ],
    "sg:phone":"+1 610 939 9288",
    "sg:postcode":"19605",
    "sg:province":"PA",
    "sg:tags":[
        "grill",
        "bar",
        "mexican"
    ],
    "wof:name":"Alebrije Mexican Restaurant",
    "wof:placetype":"venue"
},
  "geometry": {"coordinates":[-75.92744399999999,40.38254],"type":"Point"}
}