{
  "type": "Feature",
  "properties": {
    "iso:country":"US",
    "sg:address":"530 Pottsville Park Plz",
    "sg:city":"Pottsville",
    "sg:classifiers":[
        {
            "category":"Professional",
            "subcategory":"Management & Consulting",
            "type":"Services"
        },
        {
            "category":"Food & Beverages",
            "subcategory":"Liquor & Beverages",
            "type":"Retail Goods"
        },
        {
            "category":"Government",
            "subcategory":"Office",
            "type":"Public Place"
        }
    ],
    "sg:phone":"+1 570 621 3117",
    "sg:postcode":"17901",
    "sg:province":"PA",
    "sg:tags":[
        "government-state",
        "store",
        "consultant"
    ],
    "wof:name":"Wine & Spirits Shoppe",
    "wof:placetype":"venue"
},
  "geometry": {"coordinates":[-76.187692,40.698241],"type":"Point"}
}