{
  "type": "Feature",
  "properties": {
    "iso:country":"US",
    "sg:address":"1709 Renzie Rd",
    "sg:city":"Mc Keesport",
    "sg:classifiers":[
        {
            "category":"Building & Trades",
            "subcategory":"Electrical",
            "type":"Services"
        }
    ],
    "sg:phone":"+1   ",
    "sg:postcode":"15135",
    "sg:province":"PA",
    "sg:tags":[
        "electrical",
        "contractor"
    ],
    "wof:name":"Howell Electric",
    "wof:placetype":"venue"
},
  "geometry": {"coordinates":[-79.82109699999999,40.304542],"type":"Point"}
}