{
  "type": "Feature",
  "properties": {
    "addr:full":"1945 5th Ave Pittsburgh PA 15219",
    "addr:housenumber":"1945",
    "addr:postcode":"15219",
    "addr:street":"5Th Ave",
    "iso:country":"US",
    "sg:address":"1945 5th Ave",
    "sg:city":"Pittsburgh",
    "sg:classifiers":[
        {
            "category":"Social Services",
            "subcategory":"Job Training",
            "type":"Services"
        }
    ],
    "sg:phone":"+1   ",
    "sg:postcode":"15219",
    "sg:province":"PA",
    "sg:tags":[
        "rehabilitation",
        "hearing"
    ],
    "wof:name":"Westmoreland Cnty Deaf Svcs",
    "wof:placetype":"venue"
},
  "geometry": {"coordinates":[-79.97854599999999,40.438344],"type":"Point"}
}