{
  "type": "Feature",
  "properties": {
    "addr:full":"3459 5th Ave Pittsburgh PA 15213",
    "addr:housenumber":"3459",
    "addr:postcode":"15213",
    "addr:street":"5Th Ave",
    "iso:country":"US",
    "sg:address":"3459 5th Ave",
    "sg:city":"Pittsburgh",
    "sg:classifiers":[
        {
            "category":"Health Services",
            "subcategory":"Doctor",
            "type":"Services"
        }
    ],
    "sg:phone":"+1 412 648 6161",
    "sg:postcode":"15213",
    "sg:province":"PA",
    "sg:tags":[
        "physician",
        "pulmonary",
        "surgeons",
        "disease",
        "medical"
    ],
    "wof:name":"Robert Hoffman Md",
    "wof:placetype":"venue"
},
  "geometry": {"coordinates":[-79.960712,40.440159],"type":"Point"}
}