{
  "type": "Feature",
  "properties": {
    "addr:full":"241 N 61st St Philadelphia PA 19139",
    "addr:housenumber":"241",
    "addr:postcode":"19139",
    "addr:street":"N 61St St",
    "iso:country":"US",
    "sg:address":"241 N 61st St",
    "sg:city":"Philadelphia",
    "sg:classifiers":[
        {
            "category":"Retail",
            "subcategory":"Auto Repair",
            "type":"Services"
        }
    ],
    "sg:phone":"+1 215 472 6280",
    "sg:postcode":"19139",
    "sg:province":"PA",
    "wof:name":"Ty's Auto Repair",
    "wof:placetype":"venue"
},
  "geometry": {"coordinates":[-75.242302,39.965199],"type":"Point"}
}