{
  "type": "Feature",
  "properties": {
    "iso:country":"US",
    "sg:address":"12 E 18th St",
    "sg:city":"Selinsgrove",
    "sg:classifiers":[
        {
            "category":"Shopping",
            "subcategory":"Musical Instruments",
            "type":"Retail Goods"
        }
    ],
    "sg:phone":"+1 570 374 2263",
    "sg:postcode":"17870",
    "sg:province":"PA",
    "sg:tags":[
        "rent"
    ],
    "wof:name":"Haines Music",
    "wof:placetype":"venue"
},
  "geometry": {"coordinates":[-76.84225600000001,40.82804],"type":"Point"}
}