{
  "type": "Feature",
  "properties": {
    "addr:full":"500 S Main St Spring City PA 19475",
    "addr:housenumber":"500",
    "addr:postcode":"19475",
    "addr:street":"S Main St",
    "iso:country":"US",
    "sg:address":"500 S Main St",
    "sg:city":"Spring City",
    "sg:classifiers":[
        {
            "category":"Professional",
            "subcategory":"Lawyer & Legal Services",
            "type":"Services"
        }
    ],
    "sg:phone":"+1 610 948 3770",
    "sg:postcode":"19475",
    "sg:province":"PA",
    "sg:tags":[
        "attorney"
    ],
    "wof:name":"Murphy Oliver Caiola & Gowen",
    "wof:placetype":"venue"
},
  "geometry": {"coordinates":[-75.539264,40.171543],"type":"Point"}
}