{
  "type": "Feature",
  "properties": {
    "iso:country":"US",
    "sg:address":"363 Vanadium Rd",
    "sg:city":"Pittsburgh",
    "sg:phone":"+1 412 429 0880",
    "sg:postcode":"15243",
    "sg:province":"PA",
    "sg:website":"http://www.southhillsortho.com",
    "wof:name":"South Hills Orthopaedic Surgery Associates",
    "wof:placetype":"venue"
},
  "geometry": {"coordinates":[-80.085579,40.369308],"type":"Point"}
}