{
  "type": "Feature",
  "properties": {
    "iso:country":"US",
    "sg:address":"53 Victory Ln",
    "sg:city":"Nazareth",
    "sg:classifiers":[
        {
            "category":"Building & Trades",
            "subcategory":"Construction",
            "type":"Services"
        }
    ],
    "sg:phone":"+1 610 250 0693",
    "sg:postcode":"18064",
    "sg:province":"PA",
    "sg:tags":[
        "house",
        "contractor",
        "nonresidential",
        "roofing"
    ],
    "wof:name":"Kardelis E C Construction Co",
    "wof:placetype":"venue"
},
  "geometry": {"coordinates":[-75.30014199999999,40.740174],"type":"Point"}
}