{
  "type": "Feature",
  "properties": {
    "iso:country":"US",
    "sg:address":"147 Airport Rd",
    "sg:city":"Hazleton",
    "sg:classifiers":[
        {
            "category":"Shopping",
            "subcategory":"Clothing, Apparel, & Fashions",
            "type":"Retail Goods"
        }
    ],
    "sg:phone":"+1 570 453 4367",
    "sg:postcode":"18202",
    "sg:province":"PA",
    "wof:name":"PGL Designs",
    "wof:placetype":"venue"
},
  "geometry": {"coordinates":[-75.998592,40.992023],"type":"Point"}
}