{
  "type": "Feature",
  "properties": {
    "addr:full":"514 E Pleasant Valley Blvd Altoona PA 16602",
    "addr:housenumber":"514",
    "addr:postcode":"16602",
    "addr:street":"E Pleasant Valley Blvd",
    "iso:country":"US",
    "sg:address":"514 E Pleasant Valley Blvd",
    "sg:city":"Altoona",
    "sg:classifiers":[
        {
            "category":"Building & Trades",
            "subcategory":"Pest Control",
            "type":"Services"
        }
    ],
    "sg:phone":"+1   ",
    "sg:postcode":"16602",
    "sg:province":"PA",
    "wof:name":"Terminix",
    "wof:placetype":"venue"
},
  "geometry": {"coordinates":[-78.367542,40.522981],"type":"Point"}
}