{
  "type": "Feature",
  "properties": {
    "iso:country":"US",
    "sg:address":"252 W Swamp Rd Ste 2",
    "sg:city":"Doylestown",
    "sg:classifiers":[
        {
            "category":"Wholesale",
            "subcategory":"Apparel",
            "type":"Manufacturing & Wholesale Goods"
        },
        {
            "category":"Shopping",
            "subcategory":"Shoes",
            "type":"Retail Goods"
        }
    ],
    "sg:phone":"+1 215 230 9707",
    "sg:postcode":"18901",
    "sg:province":"PA",
    "sg:tags":[
        "shoes-wholesale",
        "store",
        "manufacturer"
    ],
    "sg:website":"http://www.qualityfootcare.com",
    "wof:name":"Quality Foot Care-Doylestown",
    "wof:placetype":"venue"
},
  "geometry": {"coordinates":[-75.137685,40.333143],"type":"Point"}
}