{
  "type": "Feature",
  "properties": {
    "iso:country":"US",
    "sg:address":"8301 Torresdale Ave",
    "sg:city":"Philadelphia",
    "sg:classifiers":[
        {
            "category":"Retail",
            "subcategory":"Car Wash",
            "type":"Services"
        }
    ],
    "sg:phone":"+1   ",
    "sg:postcode":"19136",
    "sg:province":"PA",
    "sg:tags":[
        "carwash"
    ],
    "wof:name":"All Star Car Detailing",
    "wof:placetype":"venue"
},
  "geometry": {"coordinates":[-75.016378,40.039712],"type":"Point"}
}