{
  "type": "Feature",
  "properties": {
    "addr:full":"108 N Main Ave Scranton PA 18504",
    "addr:housenumber":"108",
    "addr:postcode":"18504",
    "addr:street":"N Main Ave",
    "iso:country":"US",
    "sg:address":"108 N Main Ave",
    "sg:city":"Scranton",
    "sg:classifiers":[
        {
            "category":"Shopping",
            "type":"Retail Goods"
        }
    ],
    "sg:phone":"+1 570 346 6891",
    "sg:postcode":"18504",
    "sg:province":"PA",
    "sg:tags":[
        "merchandise"
    ],
    "wof:name":"Mace Coin & Card Mart",
    "wof:placetype":"venue"
},
  "geometry": {"coordinates":[-75.67973000000001,41.412776],"type":"Point"}
}