{
  "type": "Feature",
  "properties": {
    "iso:country":"US",
    "sg:address":"1223 5th St",
    "sg:city":"Catasauqua",
    "sg:classifiers":[
        {
            "category":"Restaurant",
            "type":"Food & Drink"
        }
    ],
    "sg:phone":"+1 610 264 0740",
    "sg:postcode":"18032",
    "sg:province":"PA",
    "sg:tags":[
        "caterer"
    ],
    "wof:name":"St Andrews Jednota",
    "wof:placetype":"venue"
},
  "geometry": {"coordinates":[-75.478089,40.662444],"type":"Point"}
}