{
  "type": "Feature",
  "properties": {
    "iso:country":"US",
    "sg:address":"2125 28th St SW",
    "sg:city":"Allentown",
    "sg:classifiers":[
        {
            "category":"Wholesale",
            "subcategory":"Machinery & Supplies",
            "type":"Manufacturing & Wholesale Goods"
        }
    ],
    "sg:phone":"+1   ",
    "sg:postcode":"18103",
    "sg:province":"PA",
    "sg:tags":[
        "equipment",
        "industrial"
    ],
    "wof:name":"RG Group",
    "wof:placetype":"venue"
},
  "geometry": {"coordinates":[-75.485169,40.562825],"type":"Point"}
}