{
  "type": "Feature",
  "properties": {
    "iso:country":"US",
    "sg:address":"510 Greenbriar Rd",
    "sg:city":"York",
    "sg:classifiers":[
        {
            "category":"Health Services",
            "subcategory":"Doctor",
            "type":"Services"
        }
    ],
    "sg:phone":"+1 717 764 3373",
    "sg:postcode":"17404",
    "sg:province":"PA",
    "sg:tags":[
        "physician",
        "surgeon"
    ],
    "wof:name":"Gary A Lease DO",
    "wof:placetype":"venue"
},
  "geometry": {"coordinates":[-76.76098399999999,39.983276],"type":"Point"}
}