{
  "type": "Feature",
  "properties": {
    "addr:full":"5185 Library Rd Bethel Park PA 15102",
    "addr:housenumber":"5185",
    "addr:postcode":"15102",
    "addr:street":"Library Rd",
    "iso:country":"US",
    "sg:address":"5185 Library Rd",
    "sg:city":"Bethel Park",
    "sg:classifiers":[
        {
            "category":"Retail",
            "subcategory":"Auto Repair",
            "type":"Services"
        }
    ],
    "sg:phone":"+1 412 831 5521",
    "sg:postcode":"15102",
    "sg:province":"PA",
    "sg:tags":[
        "automotive",
        "agency"
    ],
    "wof:name":"Jiffy Lube",
    "wof:placetype":"venue"
},
  "geometry": {"coordinates":[-80.02416700000001,40.335464],"type":"Point"}
}