{
  "type": "Feature",
  "properties": {
    "iso:country":"US",
    "sg:address":"3885 Brookside Ln",
    "sg:city":"Murrysville",
    "sg:classifiers":[
        {
            "category":"Professional",
            "type":"Services"
        }
    ],
    "sg:phone":"+1   ",
    "sg:postcode":"15668",
    "sg:province":"PA",
    "wof:name":"Robert C Eazor",
    "wof:placetype":"venue"
},
  "geometry": {"coordinates":[-79.66785400000001,40.449723],"type":"Point"}
}