{
  "type": "Feature",
  "properties": {
    "iso:country":"US",
    "sg:address":"444 N 3rd St",
    "sg:city":"Philadelphia",
    "sg:classifiers":[
        {
            "category":"Banks & Credit Unions",
            "subcategory":"Bank",
            "type":"Services"
        }
    ],
    "sg:phone":"+1 215 568 3333",
    "sg:postcode":"19123",
    "sg:province":"PA",
    "wof:name":"ILGWU Federal Credit Union",
    "wof:placetype":"venue"
},
  "geometry": {"coordinates":[-75.143818,39.959181],"type":"Point"}
}