{
  "type": "Feature",
  "properties": {
    "iso:country":"US",
    "sg:address":"3161 Sunnyside Ave",
    "sg:city":"Harrisburg",
    "sg:classifiers":[
        {
            "category":"Building & Trades",
            "subcategory":"Landscaping Services",
            "type":"Services"
        }
    ],
    "sg:phone":"+1   ",
    "sg:postcode":"17109",
    "sg:province":"PA",
    "wof:name":"Hemlock Landscaping",
    "wof:placetype":"venue"
},
  "geometry": {"coordinates":[-76.843283,40.287619],"type":"Point"}
}