{
  "type": "Feature",
  "properties": {
    "iso:country":"US",
    "sg:address":"270 Curry Hollow Rd",
    "sg:city":"Pittsburgh",
    "sg:classifiers":[
        {
            "category":"Food & Beverages",
            "subcategory":"Specialty",
            "type":"Retail Goods"
        }
    ],
    "sg:phone":"+1 412 655 3633",
    "sg:postcode":"15236",
    "sg:province":"PA",
    "sg:tags":[
        "product",
        "health",
        "diet"
    ],
    "wof:name":"American Bodybuilding Pa West, Inc.",
    "wof:placetype":"venue"
},
  "geometry": {"coordinates":[-79.97209599999999,40.336292],"type":"Point"}
}