{
  "type": "Feature",
  "properties": {
    "addr:full":"3202 Willett Rd Pittsburgh PA 15227",
    "addr:housenumber":"3202",
    "addr:postcode":"15227",
    "addr:street":"Willett Rd",
    "iso:country":"US",
    "sg:address":"3202 Willett Rd",
    "sg:city":"Pittsburgh",
    "sg:classifiers":[
        {
            "category":"Restaurant",
            "type":"Food & Drink"
        }
    ],
    "sg:phone":"+1 412 882 3227",
    "sg:postcode":"15227",
    "sg:province":"PA",
    "sg:tags":[
        "catering",
        "caterer"
    ],
    "sg:website":"www.ches-anthony.com",
    "wof:name":"Ches Anthony's Catering",
    "wof:placetype":"venue"
},
  "geometry": {"coordinates":[-79.96686200000001,40.380556],"type":"Point"}
}