{
  "type": "Feature",
  "properties": {
    "addr:full":"24484 N Mosiertown Rd Edinboro PA 16412",
    "addr:housenumber":"24484",
    "addr:postcode":"16412",
    "addr:street":"N Mosiertown Rd",
    "iso:country":"US",
    "sg:address":"24484 N Mosiertown Rd",
    "sg:city":"Edinboro",
    "sg:classifiers":[
        {
            "category":"Manufacturing",
            "subcategory":"Rubber & Plastics",
            "type":"Manufacturing & Wholesale Goods"
        }
    ],
    "sg:phone":"+1 814 763 3770",
    "sg:postcode":"16412",
    "sg:province":"PA",
    "sg:tags":[
        "injection",
        "molding"
    ],
    "wof:name":"Edinboro Molding Inc",
    "wof:placetype":"venue"
},
  "geometry": {"coordinates":[-80.23379,41.823337],"type":"Point"}
}