{
  "type": "Feature",
  "properties": {
    "iso:country":"US",
    "sg:address":"660 2nd Street Pike Ste 3",
    "sg:city":"Southampton",
    "sg:classifiers":[
        {
            "category":"Real Estate",
            "subcategory":"Real Estate Services",
            "type":"Services"
        },
        {
            "category":"Real Estate",
            "subcategory":"Real Estate Agent",
            "type":"Services"
        }
    ],
    "sg:phone":"+1 215 364 6661",
    "sg:postcode":"18966",
    "sg:province":"PA",
    "sg:tags":[
        "management"
    ],
    "wof:name":"Jerry L Berman Appraisers, Inc",
    "wof:placetype":"venue"
},
  "geometry": {"coordinates":[-75.04419,40.173205],"type":"Point"}
}