{
  "type": "Feature",
  "properties": {
    "iso:country":"US",
    "sg:address":"218 Egbert St",
    "sg:city":"Franklin",
    "sg:classifiers":[
        {
            "category":"Retail",
            "subcategory":"Auto Repair",
            "type":"Services"
        }
    ],
    "sg:phone":"+1 814 437 9300",
    "sg:postcode":"16323",
    "sg:province":"PA",
    "sg:tags":[
        "truck"
    ],
    "wof:name":"T & M Diesel Svc",
    "wof:placetype":"venue"
},
  "geometry": {"coordinates":[-79.823058,41.405672],"type":"Point"}
}