{
  "type": "Feature",
  "properties": {
    "iso:country":"US",
    "sg:address":"251 Dickson Ave",
    "sg:city":"Watsontown",
    "sg:classifiers":[
        {
            "category":"Retail",
            "subcategory":"Auto Repair",
            "type":"Services"
        }
    ],
    "sg:phone":"+1 570 538 1559",
    "sg:postcode":"17777",
    "sg:province":"PA",
    "sg:tags":[
        "body",
        "automobile",
        "painting"
    ],
    "wof:name":"Heater's Garage & Body Shop",
    "wof:placetype":"venue"
},
  "geometry": {"coordinates":[-76.85735099999999,41.078161],"type":"Point"}
}