{
  "type": "Feature",
  "properties": {
    "iso:country":"US",
    "sg:address":"1257 S Church St",
    "sg:city":"Hazleton",
    "sg:classifiers":[
        {
            "category":"Retail",
            "subcategory":"Auto Repair",
            "type":"Services"
        }
    ],
    "sg:phone":"+1 570 454 4230",
    "sg:postcode":"18201",
    "sg:province":"PA",
    "sg:tags":[
        "body",
        "automobile",
        "painting"
    ],
    "wof:name":"Frame-Up Auto",
    "wof:placetype":"venue"
},
  "geometry": {"coordinates":[-75.993961,40.927697],"type":"Point"}
}