{
  "type": "Feature",
  "properties": {
    "addr:full":"237 S 48th St Ste 11A Philadelphia PA 19139",
    "addr:housenumber":"237;11a",
    "addr:postcode":"19139",
    "addr:street":"S 48Th St Ste",
    "iso:country":"US",
    "sg:address":"237 S 48th St Ste 11A",
    "sg:city":"Philadelphia",
    "sg:classifiers":[
        {
            "category":"Real Estate",
            "subcategory":"Real Estate Operator",
            "type":"Services"
        }
    ],
    "sg:phone":"+1 215 747 4332",
    "sg:postcode":"19139",
    "sg:province":"PA",
    "sg:tags":[
        "apartment"
    ],
    "wof:name":"Sbg Management Svc Inc",
    "wof:placetype":"venue"
},
  "geometry": {"coordinates":[-75.217713,39.954763],"type":"Point"}
}