{
  "type": "Feature",
  "properties": {
    "iso:country":"US",
    "sg:address":"225 Walker Rd",
    "sg:city":"Chambersburg",
    "sg:classifiers":[
        {
            "category":"Health Services",
            "subcategory":"Doctor",
            "type":"Services"
        }
    ],
    "sg:phone":"+1 717 264 2011",
    "sg:postcode":"17201",
    "sg:province":"PA",
    "sg:tags":[
        "dentist"
    ],
    "wof:name":"Chambersburg Dental Assoc LTD",
    "wof:placetype":"venue"
},
  "geometry": {"coordinates":[-77.633298,39.932869],"type":"Point"}
}