{
  "type": "Feature",
  "properties": {
    "iso:country":"US",
    "sg:address":"2250 E Ontario St",
    "sg:city":"Philadelphia",
    "sg:classifiers":[
        {
            "category":"Manufacturing",
            "subcategory":"Textiles",
            "type":"Manufacturing & Wholesale Goods"
        }
    ],
    "sg:phone":"+1 215 744 5770",
    "sg:postcode":"19134",
    "sg:province":"PA",
    "sg:tags":[
        "fabric"
    ],
    "wof:name":"Pioneer Leathertouch Inc",
    "wof:placetype":"venue"
},
  "geometry": {"coordinates":[-75.103005,39.992574],"type":"Point"}
}