{
  "type": "Feature",
  "properties": {
    "iso:country":"US",
    "sg:address":"4249 Ridge Ave Fl 2",
    "sg:city":"Philadelphia",
    "sg:classifiers":[
        {
            "category":"Retail",
            "subcategory":"Auto Rental",
            "type":"Services"
        }
    ],
    "sg:phone":"+1 215 843 0146",
    "sg:postcode":"19129",
    "sg:province":"PA",
    "sg:tags":[
        "limousine"
    ],
    "wof:name":"Kfr Limo",
    "wof:placetype":"venue"
},
  "geometry": {"coordinates":[-75.195621,40.009554],"type":"Point"}
}