{
  "type": "Feature",
  "properties": {
    "addr:full":"2060 Webster Ave Pittsburgh PA 15219",
    "addr:housenumber":"2060",
    "addr:postcode":"15219",
    "addr:street":"Webster Ave",
    "iso:country":"US",
    "sg:address":"2060 Webster Ave",
    "sg:city":"Pittsburgh",
    "sg:classifiers":[
        {
            "category":"Real Estate",
            "subcategory":"Real Estate Operator",
            "type":"Services"
        }
    ],
    "sg:phone":"+1   ",
    "sg:postcode":"15219",
    "sg:province":"PA",
    "sg:tags":[
        "building",
        "apartment"
    ],
    "wof:name":"Bedford Apts",
    "wof:placetype":"venue"
},
  "geometry": {"coordinates":[-79.980408,40.446188],"type":"Point"}
}