{
  "type": "Feature",
  "properties": {
    "addr:full":"955 N State St Ephrata PA 17522",
    "addr:housenumber":"955",
    "addr:postcode":"17522",
    "addr:street":"N State St",
    "iso:country":"US",
    "sg:address":"955 N State St",
    "sg:city":"Ephrata",
    "sg:classifiers":[
        {
            "category":"Shopping",
            "subcategory":"Gifts & Souvenirs",
            "type":"Retail Goods"
        }
    ],
    "sg:phone":"+1   ",
    "sg:postcode":"17522",
    "sg:province":"PA",
    "wof:name":"Lil Bit Country",
    "wof:placetype":"venue"
},
  "geometry": {"coordinates":[-76.152652,40.193995],"type":"Point"}
}