{
  "type": "Feature",
  "properties": {
    "iso:country":"US",
    "sg:address":"203 W Union St",
    "sg:city":"Somerset",
    "sg:classifiers":[
        {
            "category":"Professional",
            "subcategory":"Lawyer & Legal Services",
            "type":"Services"
        }
    ],
    "sg:phone":"+1   ",
    "sg:postcode":"15501",
    "sg:province":"PA",
    "wof:name":"Robert I Boose II Esquire",
    "wof:placetype":"venue"
},
  "geometry": {"coordinates":[-79.08178100000001,40.00928],"type":"Point"}
}