{
  "type": "Feature",
  "properties": {
    "iso:country":"US",
    "sg:address":"614 Gregg Ave",
    "sg:city":"Reading",
    "sg:classifiers":[
        {
            "category":"Manufacturing",
            "subcategory":"Furniture",
            "type":"Manufacturing & Wholesale Goods"
        },
        {
            "category":"Manufacturing",
            "subcategory":"Building Materials",
            "type":"Manufacturing & Wholesale Goods"
        }
    ],
    "sg:phone":"+1 610 375 9602",
    "sg:postcode":"19611",
    "sg:province":"PA",
    "sg:tags":[
        "mfg",
        "top",
        "counter",
        "cabinet",
        "wood",
        "kitchen"
    ],
    "wof:name":"Wenrich's Cabinet Shop",
    "wof:placetype":"venue"
},
  "geometry": {"coordinates":[-75.93891499999999,40.318514],"type":"Point"}
}