{
  "type": "Feature",
  "properties": {
    "addr:full":"1011 Lincoln Ave Prospect Park PA 19076",
    "addr:housenumber":"1011",
    "addr:postcode":"19076",
    "addr:street":"Lincoln Ave;Park",
    "iso:country":"US",
    "sg:address":"1011 Lincoln Ave",
    "sg:city":"Prospect Park",
    "sg:classifiers":[
        {
            "category":"Building & Trades",
            "subcategory":"Construction",
            "type":"Services"
        }
    ],
    "sg:phone":"+1 610 876 3822",
    "sg:postcode":"19076",
    "sg:province":"PA",
    "sg:tags":[
        "home",
        "improvement"
    ],
    "wof:name":"Good News Home Improvements",
    "wof:placetype":"venue"
},
  "geometry": {"coordinates":[-75.30927800000001,39.886851],"type":"Point"}
}