{
  "type": "Feature",
  "properties": {
    "iso:country":"US",
    "sg:address":"1741 Five Forks Rd",
    "sg:city":"Clearville",
    "sg:classifiers":[
        {
            "category":"Farming",
            "subcategory":"Dairy Farm",
            "type":"Manufacturing & Wholesale Goods"
        },
        {
            "category":"Farming",
            "subcategory":"Farm",
            "type":"Manufacturing & Wholesale Goods"
        }
    ],
    "sg:phone":"+1 814 784 3242",
    "sg:postcode":"15535",
    "sg:province":"PA",
    "wof:name":"Five Forks Farm",
    "wof:placetype":"venue"
},
  "geometry": {"coordinates":[-78.40833600000001,39.860178],"type":"Point"}
}