{
  "type": "Feature",
  "properties": {
    "iso:country":"US",
    "sg:address":"321 South Ave",
    "sg:city":"Verona",
    "sg:classifiers":[
        {
            "category":"Restaurant",
            "type":"Food & Drink"
        }
    ],
    "sg:menulink":"http://www.allmenus.com/pa/verona/286592-nickys-thai-kitchen/menu/",
    "sg:phone":"+1 412 828 0339",
    "sg:postcode":"15147",
    "sg:province":"PA",
    "sg:tags":[
        "thai",
        "asian"
    ],
    "wof:name":"Nicky's Thai Kitchen",
    "wof:placetype":"venue"
},
  "geometry": {"coordinates":[-79.843643,40.504961],"type":"Point"}
}