{
  "type": "Feature",
  "properties": {
    "iso:country":"US",
    "sg:address":"220 Hewett Rd",
    "sg:city":"Wyncote",
    "sg:classifiers":[
        {
            "category":"Health Services",
            "subcategory":"Doctor",
            "type":"Services"
        }
    ],
    "sg:phone":"+1 215 884 4095",
    "sg:postcode":"19095",
    "sg:province":"PA",
    "sg:tags":[
        "physician",
        "surgeon"
    ],
    "wof:name":"J P Brantner Phd",
    "wof:placetype":"venue"
},
  "geometry": {"coordinates":[-75.146749,40.094527],"type":"Point"}
}