{
  "type": "Feature",
  "properties": {
    "iso:country":"US",
    "sg:address":"2099 Cobbs Creek Pkwy",
    "sg:city":"Philadelphia",
    "sg:classifiers":[
        {
            "category":"Building & Trades",
            "subcategory":"Locksmith",
            "type":"Services"
        }
    ],
    "sg:phone":"+1 267 295 2445",
    "sg:postcode":"19142",
    "sg:province":"PA",
    "sg:tags":[
        "key"
    ],
    "wof:name":"Emergency Locksmith",
    "wof:placetype":"venue"
},
  "geometry": {"coordinates":[-75.24669299999999,39.918823],"type":"Point"}
}