{
  "type": "Feature",
  "properties": {
    "iso:country":"US",
    "sg:address":"700 New Rodgers Rd",
    "sg:city":"Levittown",
    "sg:classifiers":[
        {
            "category":"Government",
            "subcategory":"Office",
            "type":"Public Place"
        }
    ],
    "sg:phone":"+1   ",
    "sg:postcode":"19056",
    "sg:province":"PA",
    "sg:tags":[
        "executive"
    ],
    "wof:name":"Middletown Township Hwy Dept",
    "wof:placetype":"venue"
},
  "geometry": {"coordinates":[-74.89684099999999,40.16159],"type":"Point"}
}