{
  "type": "Feature",
  "properties": {
    "addr:full":"111 Freedom Ave New Freedom PA 17349",
    "addr:housenumber":"111",
    "addr:postcode":"17349",
    "addr:street":"Freedom Ave",
    "iso:country":"US",
    "sg:address":"111 Freedom Ave",
    "sg:city":"New Freedom",
    "sg:classifiers":[
        {
            "category":"Manufacturing",
            "subcategory":"Tools & Machinery",
            "type":"Manufacturing & Wholesale Goods"
        }
    ],
    "sg:phone":"+1 717 235 2506",
    "sg:postcode":"17349",
    "sg:province":"PA",
    "sg:tags":[
        "mold"
    ],
    "wof:name":"Tecni Die Mfg Co",
    "wof:placetype":"venue"
},
  "geometry": {"coordinates":[-76.697166,39.734534],"type":"Point"}
}