{
  "type": "Feature",
  "properties": {
    "addr:full":"5617 W Ridge Rd Erie PA 16506",
    "addr:housenumber":"5617",
    "addr:postcode":"16506",
    "addr:street":"W Ridge Rd",
    "iso:country":"US",
    "sg:address":"5617 W Ridge Rd",
    "sg:city":"Erie",
    "sg:classifiers":[
        {
            "category":"Wholesale",
            "subcategory":"Machinery & Supplies",
            "type":"Manufacturing & Wholesale Goods"
        }
    ],
    "sg:phone":"+1   ",
    "sg:postcode":"16506",
    "sg:province":"PA",
    "sg:tags":[
        "equipment",
        "industrial"
    ],
    "wof:name":"Toledo Scales & Systems",
    "wof:placetype":"venue"
},
  "geometry": {"coordinates":[-80.214111,42.057431],"type":"Point"}
}