{
  "type": "Feature",
  "properties": {
    "iso:country":"US",
    "sg:address":"481 Krause Rd",
    "sg:city":"Fleetwood",
    "sg:classifiers":[
        {
            "category":"Building & Trades",
            "subcategory":"Construction",
            "type":"Services"
        }
    ],
    "sg:phone":"+1   ",
    "sg:postcode":"19522",
    "sg:province":"PA",
    "sg:tags":[
        "carpentry",
        "contractor"
    ],
    "wof:name":"Ziegler Robert C Carpentry",
    "wof:placetype":"venue"
},
  "geometry": {"coordinates":[-75.833049,40.500526],"type":"Point"}
}