{
  "type": "Feature",
  "properties": {
    "iso:country":"US",
    "sg:address":"1010 W 8th Ave",
    "sg:city":"King Of Prussia",
    "sg:classifiers":[
        {
            "category":"Real Estate",
            "subcategory":"Real Estate Agent",
            "type":"Services"
        }
    ],
    "sg:phone":"+1   ",
    "sg:postcode":"19406",
    "sg:province":"PA",
    "wof:name":"BR Management",
    "wof:placetype":"venue"
},
  "geometry": {"coordinates":[-75.415572,40.098711],"type":"Point"}
}