{
  "type": "Feature",
  "properties": {
    "iso:country":"US",
    "sg:address":"230 Route 313",
    "sg:city":"Perkasie",
    "sg:classifiers":[
        {
            "category":"Ice Cream",
            "type":"Food & Drink"
        }
    ],
    "sg:menulink":"http://www.allmenus.com/pa/east-rockhill/243681-baskin-robbins/menu/",
    "sg:phone":"+1 215 249 1922",
    "sg:postcode":"18944",
    "sg:province":"PA",
    "sg:tags":[
        "american"
    ],
    "wof:name":"Baskin-Robbins",
    "wof:placetype":"venue"
},
  "geometry": {"coordinates":[-75.248271,40.400093],"type":"Point"}
}