{
  "type": "Feature",
  "properties": {
    "iso:country":"US",
    "sg:address":"625 Community Way",
    "sg:city":"Lancaster",
    "sg:classifiers":[
        {
            "category":"Health Services",
            "subcategory":"Clinic",
            "type":"Services"
        }
    ],
    "sg:phone":"+1   ",
    "sg:postcode":"17603",
    "sg:province":"PA",
    "sg:tags":[
        "specialty",
        "outpatient"
    ],
    "wof:name":"Schreber Pdtric Rehab Ctr Lanc",
    "wof:placetype":"venue"
},
  "geometry": {"coordinates":[-76.353663,40.05097],"type":"Point"}
}