{
  "type": "Feature",
  "properties": {
    "iso:country":"US",
    "sg:address":"79 Hill Rd",
    "sg:city":"Bloomsburg",
    "sg:classifiers":[
        {
            "category":"Restaurant",
            "type":"Food & Drink"
        }
    ],
    "sg:phone":"+1   ",
    "sg:postcode":"17815",
    "sg:province":"PA",
    "sg:tags":[
        "eating"
    ],
    "wof:name":"Frannis Dairy Bar",
    "wof:placetype":"venue"
},
  "geometry": {"coordinates":[-76.445038,41.014047],"type":"Point"}
}