{
  "type": "Feature",
  "properties": {
    "iso:country":"US",
    "sg:address":"700 Quincy Ave",
    "sg:city":"Scranton",
    "sg:classifiers":[
        {
            "category":"Social Services",
            "subcategory":"Job Training",
            "type":"Services"
        }
    ],
    "sg:phone":"+1   ",
    "sg:postcode":"18510",
    "sg:province":"PA",
    "wof:name":"Employee Assistance Program",
    "wof:placetype":"venue"
},
  "geometry": {"coordinates":[-75.65004999999999,41.411387],"type":"Point"}
}