{
  "type": "Feature",
  "properties": {
    "iso:country":"US",
    "sg:address":"3545 Germantown Ave",
    "sg:city":"Philadelphia",
    "sg:classifiers":[
        {
            "category":"Shopping",
            "subcategory":"Jewelry",
            "type":"Retail Goods"
        }
    ],
    "sg:phone":"+1 215 225 1830",
    "sg:postcode":"19140",
    "sg:province":"PA",
    "sg:tags":[
        "jeweler"
    ],
    "wof:name":"Golden Eagle Jewelry",
    "wof:placetype":"venue"
},
  "geometry": {"coordinates":[-75.1502,40.007198],"type":"Point"}
}