{
  "type": "Feature",
  "properties": {
    "iso:country":"US",
    "sg:address":"31 Donora Rd",
    "sg:city":"Monongahela",
    "sg:classifiers":[
        {
            "category":"Building & Trades",
            "subcategory":"Landscaping Services",
            "type":"Services"
        }
    ],
    "sg:phone":"+1   ",
    "sg:postcode":"15063",
    "sg:province":"PA",
    "wof:name":"Taylor Lawn Care",
    "wof:placetype":"venue"
},
  "geometry": {"coordinates":[-79.880869,40.171493],"type":"Point"}
}