{
  "type": "Feature",
  "properties": {
    "iso:country":"US",
    "sg:address":"1075 Woodland Rd",
    "sg:city":"Reading",
    "sg:classifiers":[
        {
            "category":"Coffee & Tea",
            "type":"Food & Drink"
        },
        {
            "category":"Bakery",
            "type":"Food & Drink"
        }
    ],
    "sg:menulink":"http://www.allmenus.com/pa/wyomissing/137085-seattles-best-coffee/menu/",
    "sg:phone":"+1 610 737 0377",
    "sg:postcode":"19610",
    "sg:province":"PA",
    "sg:tags":[
        "american",
        "diner",
        "pastry"
    ],
    "wof:name":"Seattle's Best Coffee",
    "wof:placetype":"venue"
},
  "geometry": {"coordinates":[-75.971665,40.345116],"type":"Point"}
}