{
  "type": "Feature",
  "properties": {
    "iso:country":"US",
    "sg:address":"20 N 9th St",
    "sg:city":"Reading",
    "sg:classifiers":[
        {
            "category":"Building & Trades",
            "subcategory":"Construction",
            "type":"Services"
        }
    ],
    "sg:phone":"+1 610 376 6437",
    "sg:postcode":"19601",
    "sg:province":"PA",
    "sg:tags":[
        "designer",
        "dealer",
        "pool",
        "swimming"
    ],
    "wof:name":"Tropical Pools-The Northeast",
    "wof:placetype":"venue"
},
  "geometry": {"coordinates":[-75.92014899999999,40.335299],"type":"Point"}
}