{
  "type": "Feature",
  "properties": {
    "addr:full":"125 Cocalico Creek Rd Stevens PA 17578",
    "addr:housenumber":"125",
    "addr:postcode":"17578",
    "addr:street":"Cocalico Creek Rd",
    "iso:country":"US",
    "sg:address":"125 Cocalico Creek Rd",
    "sg:city":"Stevens",
    "sg:classifiers":[
        {
            "category":"Shopping",
            "subcategory":"Hobbies, Toys, & Games",
            "type":"Retail Goods"
        }
    ],
    "sg:phone":"+1 717 336 6660",
    "sg:postcode":"17578",
    "sg:province":"PA",
    "wof:name":"Cocalico Creek Ceramics",
    "wof:placetype":"venue"
},
  "geometry": {"coordinates":[-76.139549,40.207449],"type":"Point"}
}