{
  "type": "Feature",
  "properties": {
    "addr:full":"112 Center St Oil City PA 16301",
    "addr:housenumber":"112",
    "addr:postcode":"16301",
    "addr:street":"Center St",
    "iso:country":"US",
    "sg:address":"112 Center St",
    "sg:city":"Oil City",
    "sg:classifiers":[
        {
            "category":"Health Services",
            "subcategory":"Optometrist",
            "type":"Services"
        }
    ],
    "sg:phone":"+1 814 677 3022",
    "sg:postcode":"16301",
    "sg:province":"PA",
    "wof:name":"Eye Care Ctr",
    "wof:placetype":"venue"
},
  "geometry": {"coordinates":[-79.707891,41.434234],"type":"Point"}
}