{
  "type": "Feature",
  "properties": {
    "iso:country":"US",
    "sg:address":"5029 Summit Dr",
    "sg:city":"Allison Park",
    "sg:classifiers":[
        {
            "category":"Health Services",
            "subcategory":"Doctor",
            "type":"Services"
        }
    ],
    "sg:phone":"+1   ",
    "sg:postcode":"15101",
    "sg:province":"PA",
    "wof:name":"Karen M Shulman DMD PC",
    "wof:placetype":"venue"
},
  "geometry": {"coordinates":[-79.922042,40.602851],"type":"Point"}
}