{
  "type": "Feature",
  "properties": {
    "addr:full":"2166 S 12th St Allentown PA 18103",
    "addr:housenumber":"2166",
    "addr:postcode":"18103",
    "addr:street":"S 12Th St",
    "iso:country":"US",
    "sg:address":"2166 S 12th St",
    "sg:city":"Allentown",
    "sg:classifiers":[
        {
            "category":"Insurance",
            "subcategory":"Health Insurance",
            "type":"Services"
        }
    ],
    "sg:phone":"+1   ",
    "sg:postcode":"18103",
    "sg:province":"PA",
    "sg:tags":[
        "administrator",
        "third",
        "benefit",
        "plan",
        "employee",
        "party"
    ],
    "wof:name":"Spectrum Administrators",
    "wof:placetype":"venue"
},
  "geometry": {"coordinates":[-75.476034,40.575414],"type":"Point"}
}