{
  "type": "Feature",
  "properties": {
    "addr:full":"2507 Willow Park Rd Bethlehem PA 18020",
    "addr:housenumber":"2507",
    "addr:postcode":"18020",
    "addr:street":"Willow Park Rd",
    "iso:country":"US",
    "sg:address":"2507 Willow Park Rd",
    "sg:city":"Bethlehem",
    "sg:classifiers":[
        {
            "category":"Personal",
            "subcategory":"Beauty Salon",
            "type":"Services"
        }
    ],
    "sg:phone":"+1 610 691 8226",
    "sg:postcode":"18020",
    "sg:province":"PA",
    "sg:tags":[
        "hair",
        "stylist"
    ],
    "wof:name":"The Hair Depot",
    "wof:placetype":"venue"
},
  "geometry": {"coordinates":[-75.33289499999999,40.652056],"type":"Point"}
}