{
  "type": "Feature",
  "properties": {
    "addr:full":"203 E Walnut St Perkasie PA 18944",
    "addr:housenumber":"203",
    "addr:postcode":"18944",
    "addr:street":"E Walnut St",
    "iso:country":"US",
    "sg:address":"203 E Walnut St",
    "sg:city":"Perkasie",
    "sg:classifiers":[
        {
            "category":"Shopping",
            "subcategory":"Hobbies, Toys, & Games",
            "type":"Retail Goods"
        }
    ],
    "sg:phone":"+1   ",
    "sg:postcode":"18944",
    "sg:province":"PA",
    "wof:name":"Margaret Ann Craft Creations",
    "wof:placetype":"venue"
},
  "geometry": {"coordinates":[-75.29351699999999,40.367349],"type":"Point"}
}