{
  "type": "Feature",
  "properties": {
    "addr:full":"1301 Cranberry St Erie PA 16502",
    "addr:housenumber":"1301",
    "addr:postcode":"16502",
    "addr:street":"Cranberry St",
    "iso:country":"US",
    "sg:address":"1301 Cranberry St",
    "sg:city":"Erie",
    "sg:classifiers":[
        {
            "category":"Wholesale",
            "subcategory":"Metals & Minerals",
            "type":"Manufacturing & Wholesale Goods"
        }
    ],
    "sg:phone":"+1 814 453 4969",
    "sg:postcode":"16502",
    "sg:province":"PA",
    "sg:tags":[
        "steel",
        "warehouse"
    ],
    "sg:website":"www.econsteel.com",
    "wof:name":"Erie Concrete & Steel Supply",
    "wof:placetype":"venue"
},
  "geometry": {"coordinates":[-80.105829,42.112861],"type":"Point"}
}