{
  "type": "Feature",
  "properties": {
    "iso:country":"US",
    "sg:address":"27 State Rd",
    "sg:city":"Media",
    "sg:classifiers":[
        {
            "category":"Personal",
            "subcategory":"Beauty Salon",
            "type":"Services"
        }
    ],
    "sg:phone":"+1 610 891 9020",
    "sg:postcode":"19063",
    "sg:province":"PA",
    "wof:name":"Chameleon",
    "wof:placetype":"venue"
},
  "geometry": {"coordinates":[-75.38475699999999,39.927426],"type":"Point"}
}