{
  "type": "Feature",
  "properties": {
    "addr:full":"1515 Locust St Fl 10 Philadelphia PA 19102",
    "addr:housenumber":"1515;10",
    "addr:postcode":"19102",
    "addr:street":"Locust St Fl",
    "iso:country":"US",
    "sg:address":"1515 Locust St Fl 10",
    "sg:city":"Philadelphia",
    "sg:classifiers":[
        {
            "category":"Professional",
            "subcategory":"Detective & Security Services",
            "type":"Services"
        }
    ],
    "sg:phone":"+1 215 732 7877",
    "sg:postcode":"19102",
    "sg:province":"PA",
    "sg:tags":[
        "private",
        "investigator"
    ],
    "sg:website":"http://www.kolins.info",
    "wof:name":"Russell Kolins Pl",
    "wof:placetype":"venue"
},
  "geometry": {"coordinates":[-75.166881,39.948507],"type":"Point"}
}