{
  "type": "Feature",
  "properties": {
    "addr:full":"112 Pennsylvania Ave Avondale PA 19311",
    "addr:housenumber":"112",
    "addr:postcode":"19311",
    "addr:street":"Pennsylvania Ave",
    "iso:country":"US",
    "sg:address":"112 Pennsylvania Ave",
    "sg:city":"Avondale",
    "sg:classifiers":[
        {
            "category":"Government",
            "subcategory":"Post Office",
            "type":"Public Place"
        }
    ],
    "sg:phone":"+1 610 268 0873",
    "sg:postcode":"19311",
    "sg:province":"PA",
    "wof:name":"US Post Office",
    "wof:placetype":"venue"
},
  "geometry": {"coordinates":[-75.783473,39.824973],"type":"Point"}
}