{
  "type": "Feature",
  "properties": {
    "addr:full":"821 Aubrey Ave Ste B Ardmore PA 19003",
    "addr:housenumber":"821",
    "addr:postcode":"19003",
    "addr:street":"Aubrey Ave Ste B",
    "iso:country":"US",
    "sg:address":"821 Aubrey Ave Ste B",
    "sg:city":"Ardmore",
    "sg:classifiers":[
        {
            "category":"Shopping",
            "subcategory":"Jewelry",
            "type":"Retail Goods"
        },
        {
            "category":"Manufacturing",
            "subcategory":"Soap",
            "type":"Manufacturing & Wholesale Goods"
        }
    ],
    "sg:phone":"+1 610 642 5921",
    "sg:postcode":"19003",
    "sg:province":"PA",
    "sg:tags":[
        "watches-wholesale",
        "watch",
        "manufacturer"
    ],
    "sg:website":"http://www.timezoneus.com",
    "wof:name":"Time Zone",
    "wof:placetype":"venue"
},
  "geometry": {"coordinates":[-75.299547,40.002355],"type":"Point"}
}