{
  "type": "Feature",
  "properties": {
    "iso:country":"US",
    "sg:address":"405 E 5th St",
    "sg:city":"Northampton",
    "sg:classifiers":[
        {
            "category":"Professional",
            "subcategory":"Art Services",
            "type":"Services"
        }
    ],
    "sg:phone":"+1 610 502 9644",
    "sg:postcode":"18067",
    "sg:province":"PA",
    "sg:tags":[
        "photographer"
    ],
    "wof:name":"Pooch Smooch Photography",
    "wof:placetype":"venue"
},
  "geometry": {"coordinates":[-75.476567,40.674859],"type":"Point"}
}