{
  "type": "Feature",
  "properties": {
    "iso:country":"US",
    "sg:address":"1004 Arch St Fl 2",
    "sg:city":"Philadelphia",
    "sg:classifiers":[
        {
            "category":"Wholesale",
            "subcategory":"Non-durable Goods",
            "type":"Manufacturing & Wholesale Goods"
        }
    ],
    "sg:phone":"+1 215 829 0816",
    "sg:postcode":"19107",
    "sg:province":"PA",
    "sg:tags":[
        "merchandise-wholesale"
    ],
    "wof:name":"Tyler International Trade",
    "wof:placetype":"venue"
},
  "geometry": {"coordinates":[-75.156344,39.953557],"type":"Point"}
}