{
  "type": "Feature",
  "properties": {
    "iso:country":"US",
    "sg:address":"41 Conshohocken State Rd",
    "sg:city":"Bala Cynwyd",
    "sg:classifiers":[
        {
            "category":"Professional",
            "subcategory":"Lawyer & Legal Services",
            "type":"Services"
        }
    ],
    "sg:phone":"+1 610 664 2413",
    "sg:postcode":"19004",
    "sg:province":"PA",
    "wof:name":"Taylor Jerome Attorney",
    "wof:placetype":"venue"
},
  "geometry": {"coordinates":[-75.22821999999999,40.003555],"type":"Point"}
}