{
  "type": "Feature",
  "properties": {
    "iso:country":"US",
    "sg:address":"210 E 28th Division Hwy",
    "sg:city":"Lititz",
    "sg:classifiers":[
        {
            "category":"Freight",
            "type":"Transportation"
        }
    ],
    "sg:phone":"+1 717 626 6910",
    "sg:postcode":"17543",
    "sg:province":"PA",
    "sg:tags":[
        "operator",
        "local",
        "trucking"
    ],
    "wof:name":"L G Eckert Trucking",
    "wof:placetype":"venue"
},
  "geometry": {"coordinates":[-76.292614,40.223743],"type":"Point"}
}