{
  "type": "Feature",
  "properties": {
    "addr:full":"2187 Pennsylvania Ave York PA 17404",
    "addr:housenumber":"2187",
    "addr:postcode":"17404",
    "addr:street":"Pennsylvania Ave",
    "iso:country":"US",
    "sg:address":"2187 Pennsylvania Ave",
    "sg:city":"York",
    "sg:classifiers":[
        {
            "category":"Bars & Pubs",
            "type":"Food & Drink"
        }
    ],
    "sg:phone":"+1   ",
    "sg:postcode":"17404",
    "sg:province":"PA",
    "sg:tags":[
        "lounge",
        "cocktail"
    ],
    "wof:name":"Plaza Lounge",
    "wof:placetype":"venue"
},
  "geometry": {"coordinates":[-76.74711600000001,39.989226],"type":"Point"}
}