{
  "type": "Feature",
  "properties": {
    "iso:country":"US",
    "sg:address":"975 Hidden Hollow Dr",
    "sg:city":"Gap",
    "sg:classifiers":[
        {
            "category":"Building & Trades",
            "subcategory":"Construction",
            "type":"Services"
        }
    ],
    "sg:phone":"+1 610 202 6191",
    "sg:postcode":"17527",
    "sg:province":"PA",
    "sg:tags":[
        "home",
        "improvement"
    ],
    "wof:name":"Leave It To Me",
    "wof:placetype":"venue"
},
  "geometry": {"coordinates":[-76.009488,39.981629],"type":"Point"}
}