{
  "type": "Feature",
  "properties": {
    "addr:full":"18875 Main St Dry Run PA 17220",
    "addr:housenumber":"18875",
    "addr:postcode":"17220",
    "addr:street":"Main St",
    "iso:country":"US",
    "sg:address":"18875 Main St",
    "sg:city":"Dry Run",
    "sg:classifiers":[
        {
            "category":"Retail",
            "subcategory":"Funeral Services",
            "type":"Services"
        }
    ],
    "sg:phone":"+1 717 349 2820",
    "sg:postcode":"17220",
    "sg:province":"PA",
    "sg:tags":[
        "director"
    ],
    "wof:name":"John L Agett Funeral Home",
    "wof:placetype":"venue"
},
  "geometry": {"coordinates":[-77.75317200000001,40.171185],"type":"Point"}
}