{
  "type": "Feature",
  "properties": {
    "addr:full":"112 Washington Pl Pittsburgh PA 15219",
    "addr:housenumber":"112",
    "addr:postcode":"15219",
    "addr:street":"Washington Pl",
    "iso:country":"US",
    "sg:address":"112 Washington Pl",
    "sg:city":"Pittsburgh",
    "sg:classifiers":[
        {
            "category":"Personal",
            "subcategory":"Beauty Salon",
            "type":"Services"
        }
    ],
    "sg:phone":"+1 412 281 5400",
    "sg:postcode":"15219",
    "sg:province":"PA",
    "sg:tags":[
        "spa",
        "day"
    ],
    "wof:name":"Spa Uptown",
    "wof:placetype":"venue"
},
  "geometry": {"coordinates":[-79.99132,40.440423],"type":"Point"}
}