{
  "type": "Feature",
  "properties": {
    "addr:full":"114 S Queen St Lancaster PA 17603",
    "addr:housenumber":"114",
    "addr:postcode":"17603",
    "addr:street":"S Queen St",
    "iso:country":"US",
    "sg:address":"114 S Queen St",
    "sg:city":"Lancaster",
    "sg:classifiers":[
        {
            "category":"Home & Garden",
            "subcategory":"Building Materials",
            "type":"Retail Goods"
        }
    ],
    "sg:phone":"+1 717 397 3734",
    "sg:postcode":"17603",
    "sg:province":"PA",
    "sg:tags":[
        "glass",
        "window",
        "plate"
    ],
    "wof:name":"Howells Glass Co Inc",
    "wof:placetype":"venue"
},
  "geometry": {"coordinates":[-76.30543299999999,40.036245],"type":"Point"}
}