{
  "type": "Feature",
  "properties": {
    "iso:country":"US",
    "sg:address":"1608 Walnut St",
    "sg:city":"Erie",
    "sg:classifiers":[
        {
            "category":"Health Services",
            "subcategory":"Doctor",
            "type":"Services"
        }
    ],
    "sg:phone":"+1 814 454 8755",
    "sg:postcode":"16502",
    "sg:province":"PA",
    "sg:tags":[
        "clinic"
    ],
    "sg:website":"www.stpaulsfreeclinic.org",
    "wof:name":"St Paul's Neighborhood Free",
    "wof:placetype":"venue"
},
  "geometry": {"coordinates":[-80.089465,42.115333],"type":"Point"}
}