{
  "type": "Feature",
  "properties": {
    "iso:country":"US",
    "sg:address":"203 Lytton Ave",
    "sg:city":"Pittsburgh",
    "sg:classifiers":[
        {
            "category":"Professional",
            "subcategory":"Lawyer & Legal Services",
            "type":"Services"
        }
    ],
    "sg:phone":"+1   ",
    "sg:postcode":"15213",
    "sg:province":"PA",
    "wof:name":"Mc Kenzie M Ursula",
    "wof:placetype":"venue"
},
  "geometry": {"coordinates":[-79.95747799999999,40.447792],"type":"Point"}
}