{
  "type": "Feature",
  "properties": {
    "iso:country":"US",
    "sg:address":"1028 Applejack Dr",
    "sg:city":"Gibsonia",
    "sg:classifiers":[
        {
            "category":"Communications",
            "type":"Services"
        }
    ],
    "sg:phone":"+1 724 449 8859",
    "sg:postcode":"15044",
    "sg:province":"PA",
    "wof:name":"Db3 Media",
    "wof:placetype":"venue"
},
  "geometry": {"coordinates":[-79.931722,40.619695],"type":"Point"}
}