{
  "type": "Feature",
  "properties": {
    "iso:country":"US",
    "sg:address":"558 W Uwchlan Ave",
    "sg:city":"Exton",
    "sg:classifiers":[
        {
            "category":"Building & Trades",
            "subcategory":"Construction",
            "type":"Services"
        }
    ],
    "sg:phone":"+1 610 524 5334",
    "sg:postcode":"19341",
    "sg:province":"PA",
    "sg:tags":[
        "home",
        "builder"
    ],
    "wof:name":"Home Helpers",
    "wof:placetype":"venue"
},
  "geometry": {"coordinates":[-75.66126,40.051004],"type":"Point"}
}