{
  "type": "Feature",
  "properties": {
    "iso:country":"US",
    "sg:address":"2275 N Reading Rd",
    "sg:city":"Denver",
    "sg:classifiers":[
        {
            "category":"Travel",
            "subcategory":"Hotels & Motels",
            "type":"Entertainment"
        }
    ],
    "sg:phone":"+1 717 336 3553",
    "sg:postcode":"17517",
    "sg:province":"PA",
    "wof:name":"Pa Dutch Motel",
    "wof:placetype":"venue"
},
  "geometry": {"coordinates":[-76.091095,40.226532],"type":"Point"}
}