{
  "type": "Feature",
  "properties": {
    "iso:country":"US",
    "sg:address":"32878 US Hwy 322",
    "sg:city":"Cochranton",
    "sg:classifiers":[
        {
            "category":"Freight",
            "type":"Transportation"
        }
    ],
    "sg:phone":"+1   ",
    "sg:postcode":"16314",
    "sg:province":"PA",
    "sg:tags":[
        "operator",
        "local",
        "trucking"
    ],
    "wof:name":"Rons Trucking",
    "wof:placetype":"venue"
},
  "geometry": {"coordinates":[-80.023233,41.50069],"type":"Point"}
}