{
  "type": "Feature",
  "properties": {
    "addr:full":"20012 Rte 19 Cranberry Twp PA 16066",
    "addr:postcode":"20012;16066",
    "addr:street":"Rte 19",
    "iso:country":"US",
    "sg:address":"20012 Rte 19",
    "sg:city":"Cranberry Twp",
    "sg:classifiers":[
        {
            "category":"Travel",
            "subcategory":"Hotels & Motels",
            "type":"Entertainment"
        }
    ],
    "sg:phone":"+1 724 776 1551",
    "sg:postcode":"16066",
    "sg:province":"PA",
    "wof:name":"Oak Leaf Motel",
    "wof:placetype":"venue"
},
  "geometry": {"coordinates":[-80.098675,40.674512],"type":"Point"}
}