{
  "type": "Feature",
  "properties": {
    "iso:country":"US",
    "sg:address":"19990 Highway 198",
    "sg:city":"Saegertown",
    "sg:classifiers":[
        {
            "category":"Manufacturing",
            "subcategory":"Tools & Machinery",
            "type":"Manufacturing & Wholesale Goods"
        },
        {
            "category":"Manufacturing",
            "subcategory":"Rubber & Plastics",
            "type":"Manufacturing & Wholesale Goods"
        },
        {
            "category":"Building & Trades",
            "subcategory":"Plumbing",
            "type":"Services"
        },
        {
            "category":"Manufacturing",
            "subcategory":"Building Materials",
            "type":"Manufacturing & Wholesale Goods"
        }
    ],
    "sg:phone":"+1 814 763 6076",
    "sg:postcode":"16433",
    "sg:province":"PA",
    "sg:tags":[
        "tools-electric",
        "plastics-vacuum",
        "jig",
        "solid",
        "die",
        "fixture",
        "surface",
        "pressure",
        "forming-manufacturers",
        "maker"
    ],
    "wof:name":"Haemer/Wright Tool & Die Inc",
    "wof:placetype":"venue"
},
  "geometry": {"coordinates":[-80.151775,41.724637],"type":"Point"}
}