{
  "type": "Feature",
  "properties": {
    "iso:country":"US",
    "sg:address":"430 S 61st St",
    "sg:city":"Philadelphia",
    "sg:classifiers":[
        {
            "category":"Retail",
            "subcategory":"Auto Repair",
            "type":"Services"
        }
    ],
    "sg:phone":"+1 215 747 5430",
    "sg:postcode":"19143",
    "sg:province":"PA",
    "wof:name":"Fanatic Mechanics",
    "wof:placetype":"venue"
},
  "geometry": {"coordinates":[-75.244418,39.954938],"type":"Point"}
}