{
  "type": "Feature",
  "properties": {
    "iso:country":"US",
    "sg:address":"901 Pike St",
    "sg:city":"State College",
    "sg:classifiers":[
        {
            "category":"Bars & Pubs",
            "type":"Food & Drink"
        }
    ],
    "sg:menulink":"http://www.allmenus.com/pa/college/245592-alto-italian-restaurant--and-bar/menu/",
    "sg:phone":"+1 814 238 5534",
    "sg:postcode":"16827",
    "sg:province":"PA",
    "sg:tags":[
        "italian"
    ],
    "wof:name":"Alto Italian Restaurant  And Bar",
    "wof:placetype":"venue"
},
  "geometry": {"coordinates":[-77.81877900000001,40.809568],"type":"Point"}
}