{
  "type": "Feature",
  "properties": {
    "iso:country":"US",
    "sg:address":"642 Washington Rd",
    "sg:city":"Pittsburgh",
    "sg:classifiers":[
        {
            "category":"Shopping",
            "subcategory":"Clothing, Apparel, & Fashions",
            "type":"Retail Goods"
        }
    ],
    "sg:phone":"+1 412 343 9917",
    "sg:postcode":"15228",
    "sg:province":"PA",
    "wof:name":"Moda Donnatella",
    "wof:placetype":"venue"
},
  "geometry": {"coordinates":[-80.044197,40.382173],"type":"Point"}
}