{
  "type": "Feature",
  "properties": {
    "addr:full":"4383 Hecktown Rd Suite Ga4 Bethlehem PA 18020",
    "addr:housenumber":"4383",
    "addr:postcode":"18020",
    "addr:street":"Hecktown Rd Suite Ga4",
    "iso:country":"US",
    "sg:address":"4383 Hecktown Rd Suite Ga4",
    "sg:city":"Bethlehem",
    "sg:classifiers":[
        {
            "category":"Utilities",
            "subcategory":"Sewage",
            "type":"Services"
        },
        {
            "category":"Building & Trades",
            "subcategory":"Plumbing",
            "type":"Services"
        },
        {
            "category":"Home & Garden",
            "subcategory":"Building Materials",
            "type":"Retail Goods"
        },
        {
            "category":"Building & Trades",
            "subcategory":"Construction",
            "type":"Services"
        },
        {
            "category":"Building & Trades",
            "subcategory":"Cleaning & Sanitation",
            "type":"Services"
        }
    ],
    "sg:phone":"+1 610 433 8201",
    "sg:postcode":"18020",
    "sg:province":"PA",
    "sg:tags":[
        "cleaner",
        "plumber",
        "heater",
        "excavation",
        "repairer",
        "contractor",
        "water",
        "sewer",
        "plumbing-drain"
    ],
    "sg:website":"http://www.rotorooter.com",
    "wof:name":"Roto-Rooter Plumbing & Drain Service",
    "wof:placetype":"venue"
},
  "geometry": {"coordinates":[-75.33018,40.685268],"type":"Point"}
}