{
  "type": "Feature",
  "properties": {
    "iso:country":"US",
    "sg:address":"45 Highland Ave",
    "sg:city":"Factoryville",
    "sg:classifiers":[
        {
            "category":"Building & Trades",
            "subcategory":"Equipment Rental",
            "type":"Services"
        }
    ],
    "sg:phone":"+1   ",
    "sg:postcode":"18419",
    "sg:province":"PA",
    "sg:tags":[
        "heavy",
        "construction"
    ],
    "wof:name":"Frank Summa Excavating",
    "wof:placetype":"venue"
},
  "geometry": {"coordinates":[-75.783008,41.55818],"type":"Point"}
}