{
  "type": "Feature",
  "properties": {
    "iso:country":"US",
    "sg:address":"2447 S Queen St",
    "sg:city":"York",
    "sg:classifiers":[
        {
            "category":"Health Services",
            "subcategory":"Chiropractor",
            "type":"Services"
        }
    ],
    "sg:phone":"+1 717 505 4050",
    "sg:postcode":"17402",
    "sg:province":"PA",
    "sg:tags":[
        "chiropractic"
    ],
    "wof:name":"Lipsitz Edwin",
    "wof:placetype":"venue"
},
  "geometry": {"coordinates":[-76.68526300000001,39.919305],"type":"Point"}
}