{
  "type": "Feature",
  "properties": {
    "addr:full":"619 Main St Forest City PA 18421",
    "addr:housenumber":"619",
    "addr:postcode":"18421",
    "addr:street":"Main St",
    "iso:country":"US",
    "sg:address":"619 Main St",
    "sg:city":"Forest City",
    "sg:classifiers":[
        {
            "category":"Banks & Credit Unions",
            "subcategory":"Bank",
            "type":"Services"
        }
    ],
    "sg:phone":"+1   ",
    "sg:postcode":"18421",
    "sg:province":"PA",
    "sg:tags":[
        "national",
        "commercial"
    ],
    "wof:name":"PNC",
    "wof:placetype":"venue"
},
  "geometry": {"coordinates":[-75.466307,41.650475],"type":"Point"}
}