{
  "type": "Feature",
  "properties": {
    "iso:country":"US",
    "sg:address":"2046 E Birch St",
    "sg:city":"Philadelphia",
    "sg:classifiers":[
        {
            "category":"Building & Trades",
            "subcategory":"Construction",
            "type":"Services"
        }
    ],
    "sg:phone":"+1   ",
    "sg:postcode":"19134",
    "sg:province":"PA",
    "sg:tags":[
        "hanging",
        "contractor"
    ],
    "wof:name":"Verns Painting",
    "wof:placetype":"venue"
},
  "geometry": {"coordinates":[-75.115925,39.989169],"type":"Point"}
}