{
  "type": "Feature",
  "properties": {
    "iso:country":"US",
    "sg:address":"527 Hollow Rd",
    "sg:city":"Catawissa",
    "sg:classifiers":[
        {
            "category":"Farming",
            "subcategory":"Farm",
            "type":"Manufacturing & Wholesale Goods"
        }
    ],
    "sg:phone":"+1   ",
    "sg:postcode":"17820",
    "sg:province":"PA",
    "sg:tags":[
        "crop",
        "general"
    ],
    "wof:name":"Robert Campbell",
    "wof:placetype":"venue"
},
  "geometry": {"coordinates":[-76.460926,40.960471],"type":"Point"}
}