{
  "type": "Feature",
  "properties": {
    "addr:full":"75 Washington Ave Plymouth PA 18651",
    "addr:housenumber":"75",
    "addr:postcode":"18651",
    "addr:street":"Washington Ave",
    "iso:country":"US",
    "sg:address":"75 Washington Ave",
    "sg:city":"Plymouth",
    "sg:classifiers":[
        {
            "category":"Health Services",
            "subcategory":"Podiatrist",
            "type":"Services"
        }
    ],
    "sg:phone":"+1 570 779 9557",
    "sg:postcode":"18651",
    "sg:province":"PA",
    "wof:name":"Peter Kaminski DPM",
    "wof:placetype":"venue"
},
  "geometry": {"coordinates":[-75.940434,41.244642],"type":"Point"}
}