{
  "type": "Feature",
  "properties": {
    "addr:full":"119 Greenside Ave Canonsburg PA 15317",
    "addr:housenumber":"119",
    "addr:postcode":"15317",
    "addr:street":"Greenside Ave",
    "iso:country":"US",
    "sg:address":"119 Greenside Ave",
    "sg:city":"Canonsburg",
    "sg:classifiers":[
        {
            "category":"Travel",
            "subcategory":"Bed & Breakfast",
            "type":"Entertainment"
        }
    ],
    "sg:phone":"+1   ",
    "sg:postcode":"15317",
    "sg:province":"PA",
    "sg:tags":[
        "house"
    ],
    "wof:name":"Greenside Manor",
    "wof:placetype":"venue"
},
  "geometry": {"coordinates":[-80.184737,40.259635],"type":"Point"}
}