{
  "type": "Feature",
  "properties": {
    "iso:country":"US",
    "sg:address":"190 Alameda Rd",
    "sg:city":"Butler",
    "sg:classifiers":[
        {
            "category":"Shopping",
            "subcategory":"Discount & Variety Stores",
            "type":"Retail Goods"
        }
    ],
    "sg:phone":"+1 724 287 4860",
    "sg:postcode":"16001",
    "sg:province":"PA",
    "sg:website":"www.biglots.com",
    "wof:name":"Big Lots",
    "wof:placetype":"venue"
},
  "geometry": {"coordinates":[-79.93228499999999,40.87114],"type":"Point"}
}