{
  "type": "Feature",
  "properties": {
    "addr:full":"405 Short Dr New Eagle PA 15067",
    "addr:housenumber":"405",
    "addr:postcode":"15067",
    "addr:street":"Short Dr New",
    "iso:country":"US",
    "sg:address":"405 Short Dr",
    "sg:city":"New Eagle",
    "sg:classifiers":[
        {
            "category":"Retail",
            "subcategory":"Auto Repair",
            "type":"Services"
        }
    ],
    "sg:phone":"+1 724 258 8313",
    "sg:postcode":"15067",
    "sg:province":"PA",
    "sg:tags":[
        "automotive"
    ],
    "wof:name":"Crookham Towing & Recovery",
    "wof:placetype":"venue"
},
  "geometry": {"coordinates":[-79.95410099999999,40.209978],"type":"Point"}
}