{
  "type": "Feature",
  "properties": {
    "addr:full":"133 Heather Rd Bala Cynwyd PA 19004",
    "addr:housenumber":"133",
    "addr:postcode":"19004",
    "addr:street":"Heather Rd",
    "iso:country":"US",
    "sg:address":"133 Heather Rd",
    "sg:city":"Bala Cynwyd",
    "sg:classifiers":[
        {
            "category":"Professional",
            "subcategory":"Business Services",
            "type":"Services"
        }
    ],
    "sg:phone":"+1 610 660 9611",
    "sg:postcode":"19004",
    "sg:province":"PA",
    "sg:tags":[
        "interior",
        "consultant",
        "design",
        "decorator"
    ],
    "wof:name":"Pedro Rodriguez Interiors",
    "wof:placetype":"venue"
},
  "geometry": {"coordinates":[-75.232597,40.004501],"type":"Point"}
}