{
  "type": "Feature",
  "properties": {
    "iso:country":"US",
    "sg:address":"411 Center St",
    "sg:city":"Mt Wolf",
    "sg:classifiers":[
        {
            "category":"Shopping",
            "subcategory":"Clothing, Apparel, & Fashions",
            "type":"Retail Goods"
        }
    ],
    "sg:phone":"+1 717 266 4353",
    "sg:postcode":"17347",
    "sg:province":"PA",
    "sg:tags":[
        "t"
    ],
    "wof:name":"Flo's T-Shirt Shop",
    "wof:placetype":"venue"
},
  "geometry": {"coordinates":[-76.704132,40.06294],"type":"Point"}
}