{
  "type": "Feature",
  "properties": {
    "iso:country":"US",
    "sg:address":"129 Doe Run Rd",
    "sg:city":"Manheim",
    "sg:classifiers":[
        {
            "category":"Retail",
            "subcategory":"Photofinishing",
            "type":"Services"
        },
        {
            "category":"Shopping",
            "subcategory":"Pharmacy",
            "type":"Retail Goods"
        }
    ],
    "sg:phone":"+1 717 665 7171",
    "sg:postcode":"17545",
    "sg:province":"PA",
    "sg:tags":[
        "photo",
        "finishing",
        "first",
        "aid",
        "supply"
    ],
    "sg:website":"http://www.cvs.com",
    "wof:name":"CVS/pharmacy",
    "wof:placetype":"venue"
},
  "geometry": {"coordinates":[-76.381948,40.17184],"type":"Point"}
}