{
  "type": "Feature",
  "properties": {
    "addr:full":"715 Electric Ave Lewistown PA 17044",
    "addr:housenumber":"715",
    "addr:postcode":"17044",
    "addr:street":"Electric Ave",
    "iso:country":"US",
    "sg:address":"715 Electric Ave",
    "sg:city":"Lewistown",
    "sg:classifiers":[
        {
            "category":"Restaurant",
            "type":"Food & Drink"
        }
    ],
    "sg:phone":"+1   ",
    "sg:postcode":"17044",
    "sg:province":"PA",
    "sg:tags":[
        "eating"
    ],
    "wof:name":"Papa Johns",
    "wof:placetype":"venue"
},
  "geometry": {"coordinates":[-77.561801,40.620404],"type":"Point"}
}