{
  "type": "Feature",
  "properties": {
    "iso:country":"US",
    "sg:address":"3613 S Partridge Dr",
    "sg:city":"Dover",
    "sg:classifiers":[
        {
            "category":"Building & Trades",
            "subcategory":"Electrical",
            "type":"Services"
        }
    ],
    "sg:phone":"+1 717 792 4449",
    "sg:postcode":"17315",
    "sg:province":"PA",
    "sg:tags":[
        "electrical",
        "contractor"
    ],
    "wof:name":"Mort Electric",
    "wof:placetype":"venue"
},
  "geometry": {"coordinates":[-76.83214599999999,39.964941],"type":"Point"}
}