{
  "type": "Feature",
  "properties": {
    "iso:country":"US",
    "sg:address":"4303 Main Street",
    "sg:city":"Philadelphia",
    "sg:classifiers":[
        {
            "category":"Home & Garden",
            "subcategory":"Home Furnishings",
            "type":"Retail Goods"
        },
        {
            "category":"Shopping",
            "subcategory":"Antiques",
            "type":"Retail Goods"
        },
        {
            "category":"Home & Garden",
            "subcategory":"Furniture",
            "type":"Retail Goods"
        }
    ],
    "sg:phone":"+1 215 483 1269",
    "sg:postcode":"19127",
    "sg:province":"PA",
    "sg:tags":[
        "decor",
        "store"
    ],
    "sg:website":"antiquesprovencal.com/",
    "wof:name":"Antiques Provencal",
    "wof:placetype":"venue"
},
  "geometry": {"coordinates":[-75.22197799999999,40.024829],"type":"Point"}
}