{
  "type": "Feature",
  "properties": {
    "iso:country":"US",
    "sg:address":"280 Higgins Rd",
    "sg:city":"Hilliards",
    "sg:classifiers":[
        {
            "category":"Building & Trades",
            "subcategory":"Plumbing",
            "type":"Services"
        }
    ],
    "sg:phone":"+1   ",
    "sg:postcode":"16040",
    "sg:province":"PA",
    "sg:tags":[
        "contractor"
    ],
    "wof:name":"Hughes Heating Refridge",
    "wof:placetype":"venue"
},
  "geometry": {"coordinates":[-79.84232799999999,41.10228],"type":"Point"}
}