{
  "type": "Feature",
  "properties": {
    "addr:full":"1424 Orthodox St Philadelphia PA 19124",
    "addr:housenumber":"1424",
    "addr:postcode":"19124",
    "addr:street":"Orthodox St",
    "iso:country":"US",
    "sg:address":"1424 Orthodox St",
    "sg:city":"Philadelphia",
    "sg:classifiers":[
        {
            "category":"Place Of Worship",
            "subcategory":"Church",
            "type":"Public Place"
        },
        {
            "category":"Place Of Worship",
            "type":"Public Place"
        },
        {
            "category":"Organizations",
            "subcategory":"Religious Organization",
            "type":"Services"
        }
    ],
    "sg:phone":"+1 215 289 4822",
    "sg:postcode":"19124",
    "sg:province":"PA",
    "sg:tags":[
        "churches-interdenominational",
        "churches-orthodox",
        "churches-various",
        "denomination"
    ],
    "sg:website":"http://www.stmaryscathedral.net",
    "wof:name":"St. Mary's Malankara Orthodox Syrian Cathedral",
    "wof:placetype":"venue"
},
  "geometry": {"coordinates":[-75.087822,40.01603],"type":"Point"}
}