{
  "type": "Feature",
  "properties": {
    "iso:country":"US",
    "sg:address":"1150 N 4th St",
    "sg:city":"Philadelphia",
    "sg:classifiers":[
        {
            "category":"Organizations",
            "subcategory":"Religious Organization",
            "type":"Services"
        }
    ],
    "sg:phone":"+1 215 592 9054",
    "sg:postcode":"19123",
    "sg:province":"PA",
    "sg:tags":[
        "church"
    ],
    "wof:name":"Second Christian Missionary",
    "wof:placetype":"venue"
},
  "geometry": {"coordinates":[-75.143514,39.968055],"type":"Point"}
}