{
  "type": "Feature",
  "properties": {
    "iso:country":"US",
    "sg:address":"1103 S Braddock Ave",
    "sg:city":"Pittsburgh",
    "sg:classifiers":[
        {
            "category":"Restaurant",
            "type":"Food & Drink"
        }
    ],
    "sg:menulink":"http://www.allmenus.com/pa/swissvale/292235-deflavios-on-the-square-pizzeria/menu/",
    "sg:phone":"+1 412 871 8923",
    "sg:postcode":"15218",
    "sg:province":"PA",
    "sg:tags":[
        "pizza"
    ],
    "wof:name":"DeFlavio's On The Square Pizzeria",
    "wof:placetype":"venue"
},
  "geometry": {"coordinates":[-79.893823,40.432794],"type":"Point"}
}