{
  "type": "Feature",
  "properties": {
    "addr:full":"1116 Pine St Philadelphia PA 19107",
    "addr:housenumber":"1116",
    "addr:postcode":"19107",
    "addr:street":"Pine St",
    "iso:country":"US",
    "sg:address":"1116 Pine St",
    "sg:city":"Philadelphia",
    "sg:classifiers":[
        {
            "category":"Shopping",
            "subcategory":"Used Merchandise",
            "type":"Retail Goods"
        }
    ],
    "sg:phone":"+1 215 336 2034",
    "sg:postcode":"19107",
    "sg:province":"PA",
    "sg:tags":[
        "antique"
    ],
    "wof:name":"Charles F Montgomery Jr",
    "wof:placetype":"venue"
},
  "geometry": {"coordinates":[-75.16005,39.944846],"type":"Point"}
}