{
  "type": "Feature",
  "properties": {
    "iso:country":"US",
    "sg:address":"16064 Airport Dr",
    "sg:city":"Dalton",
    "sg:classifiers":[
        {
            "category":"Building & Trades",
            "subcategory":"Construction",
            "type":"Services"
        }
    ],
    "sg:phone":"+1 570 586 8342",
    "sg:postcode":"18414",
    "sg:province":"PA",
    "sg:tags":[
        "house"
    ],
    "wof:name":"Yuscavage Construction",
    "wof:placetype":"venue"
},
  "geometry": {"coordinates":[-75.778464,41.489578],"type":"Point"}
}