{
  "type": "Feature",
  "properties": {
    "addr:full":"1116 Oneida Valley Rd Chicora PA 16025",
    "addr:housenumber":"1116",
    "addr:postcode":"16025",
    "addr:street":"Oneida Valley Rd",
    "iso:country":"US",
    "sg:address":"1116 Oneida Valley Rd",
    "sg:city":"Chicora",
    "sg:classifiers":[
        {
            "category":"Home & Garden",
            "subcategory":"Garden Supply",
            "type":"Retail Goods"
        }
    ],
    "sg:phone":"+1 724 287 3294",
    "sg:postcode":"16025",
    "sg:province":"PA",
    "sg:tags":[
        "lawn",
        "tractor",
        "mower"
    ],
    "wof:name":"Butler Power Equipment Inc",
    "wof:placetype":"venue"
},
  "geometry": {"coordinates":[-79.840907,40.945149],"type":"Point"}
}