{
  "type": "Feature",
  "properties": {
    "iso:country":"US",
    "sg:address":"3706 Calumet St",
    "sg:city":"Philadelphia",
    "sg:classifiers":[
        {
            "category":"Transit Center",
            "subcategory":"Freight",
            "type":"Transportation"
        }
    ],
    "sg:phone":"+1 215 849 7210",
    "sg:postcode":"19129",
    "sg:province":"PA",
    "sg:tags":[
        "trucking-light",
        "hauling"
    ],
    "wof:name":"James E Grier Sr",
    "wof:placetype":"venue"
},
  "geometry": {"coordinates":[-75.19519,40.010844],"type":"Point"}
}