{
  "type": "Feature",
  "properties": {
    "addr:full":"150 Water St Conneaut Lake PA 16316",
    "addr:housenumber":"150",
    "addr:postcode":"16316",
    "addr:street":"Water St",
    "iso:country":"US",
    "sg:address":"150 Water St",
    "sg:city":"Conneaut Lake",
    "sg:classifiers":[
        {
            "category":"Cinema",
            "subcategory":"Movie Rental",
            "type":"Entertainment"
        }
    ],
    "sg:phone":"+1 814 382 3508",
    "sg:postcode":"16316",
    "sg:province":"PA",
    "sg:tags":[
        "leasing",
        "video",
        "disc",
        "tape"
    ],
    "wof:name":"Hollywood Video",
    "wof:placetype":"venue"
},
  "geometry": {"coordinates":[-80.30226500000001,41.603326],"type":"Point"}
}