{
  "type": "Feature",
  "properties": {
    "addr:full":"317 Akron Ave Pittsburgh PA 15216",
    "addr:housenumber":"317",
    "addr:postcode":"15216",
    "addr:street":"Akron Ave",
    "iso:country":"US",
    "sg:address":"317 Akron Ave",
    "sg:city":"Pittsburgh",
    "sg:classifiers":[
        {
            "category":"Building & Trades",
            "subcategory":"Construction",
            "type":"Services"
        }
    ],
    "sg:phone":"+1   ",
    "sg:postcode":"15216",
    "sg:province":"PA",
    "sg:tags":[
        "house"
    ],
    "wof:name":"Brody Remodeling",
    "wof:placetype":"venue"
},
  "geometry": {"coordinates":[-80.04865599999999,40.387809],"type":"Point"}
}