{
  "type": "Feature",
  "properties": {
    "addr:full":"2005 Linglestown Rd Harrisburg PA 17110",
    "addr:housenumber":"2005",
    "addr:postcode":"17110",
    "addr:street":"Linglestown Rd",
    "iso:country":"US",
    "sg:address":"2005 Linglestown Rd",
    "sg:city":"Harrisburg",
    "sg:classifiers":[
        {
            "category":"Banks & Credit Unions",
            "subcategory":"Bank",
            "type":"Services"
        }
    ],
    "sg:phone":"+1 717 540 7317",
    "sg:postcode":"17110",
    "sg:province":"PA",
    "sg:website":"http://www.melloninvestor.com",
    "wof:name":"Mellon",
    "wof:placetype":"venue"
},
  "geometry": {"coordinates":[-76.868657,40.328348],"type":"Point"}
}