{
  "type": "Feature",
  "properties": {
    "iso:country":"US",
    "sg:address":"2611 Elk St",
    "sg:city":"Lake City",
    "sg:classifiers":[
        {
            "category":"Freight",
            "type":"Transportation"
        }
    ],
    "sg:phone":"+1   ",
    "sg:postcode":"16423",
    "sg:province":"PA",
    "sg:tags":[
        "operator",
        "trucking"
    ],
    "wof:name":"Buckner Trucking",
    "wof:placetype":"venue"
},
  "geometry": {"coordinates":[-80.34710200000001,42.010549],"type":"Point"}
}