{
  "type": "Feature",
  "properties": {
    "addr:full":"1653 The Fairway Jenkintown PA 19046",
    "addr:housenumber":"1653",
    "addr:postcode":"19046",
    "addr:street":"The Fairway",
    "iso:country":"US",
    "sg:address":"1653 The Fairway",
    "sg:city":"Jenkintown",
    "sg:classifiers":[
        {
            "category":"Professional",
            "subcategory":"Lawyer & Legal Services",
            "type":"Services"
        }
    ],
    "sg:phone":"+1   ",
    "sg:postcode":"19046",
    "sg:province":"PA",
    "wof:name":"Ellen S Fisher Esq",
    "wof:placetype":"venue"
},
  "geometry": {"coordinates":[-75.11762899999999,40.106643],"type":"Point"}
}