{
  "type": "Feature",
  "properties": {
    "addr:full":"1621 S 56th St Philadelphia PA 19143",
    "addr:housenumber":"1621",
    "addr:postcode":"19143",
    "addr:street":"S 56Th St",
    "iso:country":"US",
    "sg:address":"1621 S 56th St",
    "sg:city":"Philadelphia",
    "sg:classifiers":[
        {
            "category":"Retail",
            "subcategory":"Repair Shop",
            "type":"Services"
        }
    ],
    "sg:phone":"+1   ",
    "sg:postcode":"19143",
    "sg:province":"PA",
    "wof:name":"Handymans Master Lock Smith",
    "wof:placetype":"venue"
},
  "geometry": {"coordinates":[-75.225792,39.938018],"type":"Point"}
}