{
  "type": "Feature",
  "properties": {
    "addr:full":"109 Mercia Dr Pittsburgh PA 15237",
    "addr:housenumber":"109",
    "addr:postcode":"15237",
    "addr:street":"Mercia Dr",
    "iso:country":"US",
    "sg:address":"109 Mercia Dr",
    "sg:city":"Pittsburgh",
    "sg:classifiers":[
        {
            "category":"Professional",
            "subcategory":"Business Services",
            "type":"Services"
        }
    ],
    "sg:phone":"+1 412 213 0361",
    "sg:postcode":"15237",
    "sg:province":"PA",
    "sg:tags":[
        "development",
        "plan"
    ],
    "wof:name":"Reliant Financial Resources",
    "wof:placetype":"venue"
},
  "geometry": {"coordinates":[-79.995062,40.534901],"type":"Point"}
}