{
  "type": "Feature",
  "properties": {
    "addr:full":"606 Pine St Williamsport PA 17701",
    "addr:housenumber":"606",
    "addr:postcode":"17701",
    "addr:street":"Pine St",
    "iso:country":"US",
    "sg:address":"606 Pine St",
    "sg:city":"Williamsport",
    "sg:classifiers":[
        {
            "category":"Retail",
            "subcategory":"Animal Services",
            "type":"Services"
        }
    ],
    "sg:phone":"+1   ",
    "sg:postcode":"17701",
    "sg:province":"PA",
    "wof:name":"Poodle Parlor",
    "wof:placetype":"venue"
},
  "geometry": {"coordinates":[-77.006289,41.244832],"type":"Point"}
}