{
  "type": "Feature",
  "properties": {
    "addr:full":"7315 Brentwood Rd Philadelphia PA 19151",
    "addr:housenumber":"7315",
    "addr:postcode":"19151",
    "addr:street":"Brentwood Rd",
    "iso:country":"US",
    "sg:address":"7315 Brentwood Rd",
    "sg:city":"Philadelphia",
    "sg:classifiers":[
        {
            "category":"Professional",
            "subcategory":"Art Services",
            "type":"Services"
        }
    ],
    "sg:phone":"+1 267 738 5732",
    "sg:postcode":"19151",
    "sg:province":"PA",
    "sg:tags":[
        "photographer"
    ],
    "wof:name":"P L Digital Photo Specialists",
    "wof:placetype":"venue"
},
  "geometry": {"coordinates":[-75.26631399999999,39.977915],"type":"Point"}
}