{
  "type": "Feature",
  "properties": {
    "addr:full":"628 W Luzerne St Philadelphia PA 19140",
    "addr:housenumber":"628",
    "addr:postcode":"19140",
    "addr:street":"W Luzerne St",
    "iso:country":"US",
    "sg:address":"628 W Luzerne St",
    "sg:city":"Philadelphia",
    "sg:classifiers":[
        {
            "category":"Food & Beverages",
            "subcategory":"Groceries & Convenience Stores",
            "type":"Retail Goods"
        }
    ],
    "sg:phone":"+1 215 223 3827",
    "sg:postcode":"19140",
    "sg:province":"PA",
    "wof:name":"Ramirez Grocery Corp",
    "wof:placetype":"venue"
},
  "geometry": {"coordinates":[-75.13866400000001,40.012194],"type":"Point"}
}