{
  "type": "Feature",
  "properties": {
    "addr:full":"304 S 52nd St Philadelphia PA 19143",
    "addr:housenumber":"304",
    "addr:postcode":"19143",
    "addr:street":"S 52Nd St",
    "iso:country":"US",
    "sg:address":"304 S 52nd St",
    "sg:city":"Philadelphia",
    "sg:classifiers":[
        {
            "category":"Banks & Credit Unions",
            "subcategory":"Bank",
            "type":"Services"
        }
    ],
    "sg:phone":"+1 215 476 0656",
    "sg:postcode":"19143",
    "sg:province":"PA",
    "sg:tags":[
        "cashing",
        "check"
    ],
    "wof:name":"Fast Cash Inc",
    "wof:placetype":"venue"
},
  "geometry": {"coordinates":[-75.226163,39.954215],"type":"Point"}
}