{
  "type": "Feature",
  "properties": {
    "iso:country":"US",
    "sg:address":"6464 Ruch Rd",
    "sg:city":"Bethlehem",
    "sg:classifiers":[
        {
            "category":"Manufacturing",
            "subcategory":"Apparel",
            "type":"Manufacturing & Wholesale Goods"
        }
    ],
    "sg:phone":"+1 610 837 9890",
    "sg:postcode":"18017",
    "sg:province":"PA",
    "sg:tags":[
        "clothes",
        "accessory"
    ],
    "wof:name":"Bellante Properties",
    "wof:placetype":"venue"
},
  "geometry": {"coordinates":[-75.423163,40.681759],"type":"Point"}
}