{
  "type": "Feature",
  "properties": {
    "iso:country":"US",
    "sg:address":"100 Dilley St",
    "sg:city":"Kingston",
    "sg:classifiers":[
        {
            "category":"Local Transit",
            "type":"Transportation"
        }
    ],
    "sg:phone":"+1 570 822 5587",
    "sg:postcode":"18704",
    "sg:province":"PA",
    "sg:tags":[
        "ambulance"
    ],
    "sg:website":"www.transmedambulance.com",
    "wof:name":"Trans-Med Ambulance Inc",
    "wof:placetype":"venue"
},
  "geometry": {"coordinates":[-75.88222500000001,41.278835],"type":"Point"}
}