{
  "type": "Feature",
  "properties": {
    "addr:full":"933 Oak Hill Rd Lewisberry PA 17339",
    "addr:housenumber":"933",
    "addr:postcode":"17339",
    "addr:street":"Oak Hill Rd",
    "iso:country":"US",
    "sg:address":"933 Oak Hill Rd",
    "sg:city":"Lewisberry",
    "sg:classifiers":[
        {
            "category":"Farming",
            "subcategory":"Farm",
            "type":"Manufacturing & Wholesale Goods"
        }
    ],
    "sg:phone":"+1   ",
    "sg:postcode":"17339",
    "sg:province":"PA",
    "sg:tags":[
        "crop",
        "general"
    ],
    "wof:name":"Herbert Myers",
    "wof:placetype":"venue"
},
  "geometry": {"coordinates":[-76.900643,40.178091],"type":"Point"}
}