{
  "type": "Feature",
  "properties": {
    "iso:country":"US",
    "sg:address":"202 Fremont Rd",
    "sg:city":"Nottingham",
    "sg:classifiers":[
        {
            "category":"Autos & Motor Vehicles",
            "subcategory":"Automobile Sales",
            "type":"Retail Goods"
        }
    ],
    "sg:phone":"+1   ",
    "sg:postcode":"19362",
    "sg:province":"PA",
    "sg:tags":[
        "used"
    ],
    "wof:name":"James E Wells & Sons",
    "wof:placetype":"venue"
},
  "geometry": {"coordinates":[-76.079341,39.753431],"type":"Point"}
}