{
  "type": "Feature",
  "properties": {
    "iso:country":"US",
    "sg:address":"1200 W Penn Grant Rd",
    "sg:city":"Lancaster",
    "sg:classifiers":[
        {
            "category":"Farming",
            "subcategory":"Farm",
            "type":"Manufacturing & Wholesale Goods"
        }
    ],
    "sg:phone":"+1 717 871 0100",
    "sg:postcode":"17603",
    "sg:province":"PA",
    "sg:website":"www.trevelyanfarm.com",
    "wof:name":"Trevelyan Farm",
    "wof:placetype":"venue"
},
  "geometry": {"coordinates":[-76.305639,39.963664],"type":"Point"}
}