{
  "type": "Feature",
  "properties": {
    "iso:country":"US",
    "sg:address":"7249 Frankstown Ave",
    "sg:city":"Pittsburgh",
    "sg:classifiers":[
        {
            "category":"Professional",
            "subcategory":"Management & Consulting",
            "type":"Services"
        }
    ],
    "sg:phone":"+1   ",
    "sg:postcode":"15208",
    "sg:province":"PA",
    "sg:tags":[
        "construction"
    ],
    "wof:name":"Oakley",
    "wof:placetype":"venue"
},
  "geometry": {"coordinates":[-79.895027,40.457219],"type":"Point"}
}