{
  "type": "Feature",
  "properties": {
    "addr:full":"7190 S State Rte 44 Williamsport PA 17702",
    "addr:housenumber":"7190",
    "addr:postcode":"17702",
    "addr:street":"S State Rte 44",
    "iso:country":"US",
    "sg:address":"7190 S State Rte 44",
    "sg:city":"Williamsport",
    "sg:classifiers":[
        {
            "category":"Education",
            "subcategory":"School",
            "type":"Public Place"
        }
    ],
    "sg:phone":"+1 570 745 7111",
    "sg:postcode":"17702",
    "sg:province":"PA",
    "wof:name":"Nippenose Valley Elem School",
    "wof:placetype":"venue"
},
  "geometry": {"coordinates":[-77.152773,41.148819],"type":"Point"}
}