{
  "type": "Feature",
  "properties": {
    "addr:full":"822 Old Rd Strasburg PA 17579",
    "addr:housenumber":"822",
    "addr:postcode":"17579",
    "addr:street":"Old Rd",
    "iso:country":"US",
    "sg:address":"822 Old Rd",
    "sg:city":"Strasburg",
    "sg:classifiers":[
        {
            "category":"Manufacturing",
            "subcategory":"Textiles",
            "type":"Manufacturing & Wholesale Goods"
        }
    ],
    "sg:phone":"+1   ",
    "sg:postcode":"17579",
    "sg:province":"PA",
    "sg:tags":[
        "tire",
        "mfg"
    ],
    "wof:name":"Sales Office",
    "wof:placetype":"venue"
},
  "geometry": {"coordinates":[-76.200923,39.933952],"type":"Point"}
}