{
  "type": "Feature",
  "properties": {
    "addr:full":"231 E Main St Shiremanstown PA 17011",
    "addr:housenumber":"231",
    "addr:postcode":"17011",
    "addr:street":"E Main St",
    "iso:country":"US",
    "sg:address":"231 E Main St",
    "sg:city":"Shiremanstown",
    "sg:classifiers":[
        {
            "category":"Wholesale",
            "subcategory":"Machinery & Supplies",
            "type":"Manufacturing & Wholesale Goods"
        }
    ],
    "sg:phone":"+1 717 761 3617",
    "sg:postcode":"17011",
    "sg:province":"PA",
    "sg:tags":[
        "equipment",
        "laundry"
    ],
    "wof:name":"Ramco",
    "wof:placetype":"venue"
},
  "geometry": {"coordinates":[-76.950255,40.22421],"type":"Point"}
}