{
  "type": "Feature",
  "properties": {
    "iso:country":"US",
    "sg:address":"911 Ligonier St",
    "sg:city":"Latrobe",
    "sg:classifiers":[
        {
            "category":"Real Estate",
            "subcategory":"Real Estate Agent",
            "type":"Services"
        }
    ],
    "sg:phone":"+1 724 539 8800",
    "sg:postcode":"15650",
    "sg:province":"PA",
    "sg:tags":[
        "appraiser"
    ],
    "wof:name":"Certified Appraisal Svc",
    "wof:placetype":"venue"
},
  "geometry": {"coordinates":[-79.384575,40.31627],"type":"Point"}
}