{
  "type": "Feature",
  "properties": {
    "iso:country":"US",
    "sg:address":"864 E High St",
    "sg:city":"Pottstown",
    "sg:classifiers":[
        {
            "category":"Restaurant",
            "type":"Food & Drink"
        }
    ],
    "sg:phone":"+1 610 705 1833",
    "sg:postcode":"19464",
    "sg:province":"PA",
    "sg:tags":[
        "caterer"
    ],
    "wof:name":"Angelina's Italian Kitchen",
    "wof:placetype":"venue"
},
  "geometry": {"coordinates":[-75.632549,40.243908],"type":"Point"}
}