{
  "type": "Feature",
  "properties": {
    "addr:full":"4272 Township Line Rd Skippack PA 19474",
    "addr:housenumber":"4272",
    "addr:postcode":"19474",
    "addr:street":"Township Line Rd",
    "iso:country":"US",
    "sg:address":"4272 Township Line Rd",
    "sg:city":"Skippack",
    "sg:classifiers":[
        {
            "category":"Personal",
            "subcategory":"Nail Salon",
            "type":"Services"
        }
    ],
    "sg:phone":"+1 610 222 3800",
    "sg:postcode":"19474",
    "sg:province":"PA",
    "wof:name":"Nail Express",
    "wof:placetype":"venue"
},
  "geometry": {"coordinates":[-75.39160200000001,40.221802],"type":"Point"}
}