{
  "type": "Feature",
  "properties": {
    "iso:country":"US",
    "sg:address":"664 2nd Ave",
    "sg:city":"Croydon",
    "sg:classifiers":[
        {
            "category":"Banks & Credit Unions",
            "subcategory":"Bank",
            "type":"Services"
        }
    ],
    "sg:phone":"+1 215 364 0339",
    "sg:postcode":"19021",
    "sg:province":"PA",
    "sg:tags":[
        "loan",
        "real estate"
    ],
    "wof:name":"Summit Lending",
    "wof:placetype":"venue"
},
  "geometry": {"coordinates":[-74.907242,40.088871],"type":"Point"}
}