{
  "type": "Feature",
  "properties": {
    "addr:full":"243 W Main St Kutztown PA 19530",
    "addr:housenumber":"243",
    "addr:postcode":"19530",
    "addr:street":"W Main St",
    "iso:country":"US",
    "sg:address":"243 W Main St",
    "sg:city":"Kutztown",
    "sg:classifiers":[
        {
            "category":"Manufacturing",
            "subcategory":"Printing",
            "type":"Manufacturing & Wholesale Goods"
        }
    ],
    "sg:phone":"+1 610 683 6721",
    "sg:postcode":"19530",
    "sg:province":"PA",
    "sg:tags":[
        "printer"
    ],
    "sg:website":"www.transportationskills.com",
    "wof:name":"Transportation Skills Program",
    "wof:placetype":"venue"
},
  "geometry": {"coordinates":[-75.777928,40.516753],"type":"Point"}
}