{
  "type": "Feature",
  "properties": {
    "addr:full":"4029 Market St Philadelphia PA 19104",
    "addr:housenumber":"4029",
    "addr:postcode":"19104",
    "addr:street":"Market St",
    "iso:country":"US",
    "sg:address":"4029 Market St",
    "sg:city":"Philadelphia",
    "sg:classifiers":[
        {
            "category":"Home & Garden",
            "subcategory":"Furniture",
            "type":"Retail Goods"
        }
    ],
    "sg:phone":"+1 215 382 2288",
    "sg:postcode":"19104",
    "sg:province":"PA",
    "wof:name":"Mr Sleepy Head Discount Mttrss",
    "wof:placetype":"venue"
},
  "geometry": {"coordinates":[-75.202476,39.957255],"type":"Point"}
}