{
  "type": "Feature",
  "properties": {
    "addr:full":"333 N 20th St Philadelphia PA 19103",
    "addr:housenumber":"333",
    "addr:postcode":"19103",
    "addr:street":"N 20Th St",
    "iso:country":"US",
    "sg:address":"333 N 20th St",
    "sg:city":"Philadelphia",
    "sg:classifiers":[
        {
            "category":"Professional",
            "subcategory":"Lawyer & Legal Services",
            "type":"Services"
        }
    ],
    "sg:phone":"+1 215 564 5520",
    "sg:postcode":"19103",
    "sg:province":"PA",
    "sg:tags":[
        "divorce",
        "law",
        "family"
    ],
    "wof:name":"Dewalt",
    "wof:placetype":"venue"
},
  "geometry": {"coordinates":[-75.171898,39.9603],"type":"Point"}
}