{
  "type": "Feature",
  "properties": {
    "iso:country":"US",
    "sg:address":"882 W Chester Rd",
    "sg:city":"West Chester",
    "sg:classifiers":[
        {
            "category":"Wholesale",
            "subcategory":"Machinery & Supplies",
            "type":"Manufacturing & Wholesale Goods"
        }
    ],
    "sg:phone":"+1   ",
    "sg:postcode":"19382",
    "sg:province":"PA",
    "sg:tags":[
        "machine",
        "tool"
    ],
    "wof:name":"Asi",
    "wof:placetype":"venue"
},
  "geometry": {"coordinates":[-75.54594,39.910912],"type":"Point"}
}