{
  "type": "Feature",
  "properties": {
    "iso:country":"US",
    "sg:address":"4 Roberts Ave",
    "sg:city":"Glenside",
    "sg:classifiers":[
        {
            "category":"Professional",
            "subcategory":"Business Services",
            "type":"Services"
        }
    ],
    "sg:phone":"+1 215 887 1009",
    "sg:postcode":"19038",
    "sg:province":"PA",
    "sg:tags":[
        "appraiser"
    ],
    "wof:name":"Station Appraisals Inc",
    "wof:placetype":"venue"
},
  "geometry": {"coordinates":[-75.15389,40.10465],"type":"Point"}
}