{
  "type": "Feature",
  "properties": {
    "iso:country":"US",
    "sg:address":"1024 New Holland Ave",
    "sg:city":"Lancaster",
    "sg:classifiers":[
        {
            "category":"Manufacturing",
            "subcategory":"Paper Products",
            "type":"Manufacturing & Wholesale Goods"
        }
    ],
    "sg:phone":"+1   ",
    "sg:postcode":"17601",
    "sg:province":"PA",
    "sg:tags":[
        "mill",
        "paperboard"
    ],
    "wof:name":"Phoenix Packaging Inc",
    "wof:placetype":"venue"
},
  "geometry": {"coordinates":[-76.283058,40.056227],"type":"Point"}
}