{
  "type": "Feature",
  "properties": {
    "iso:country":"US",
    "sg:address":"1901 E Moyamensing Ave",
    "sg:city":"Philadelphia",
    "sg:classifiers":[
        {
            "category":"Building & Trades",
            "subcategory":"Equipment Rental",
            "type":"Services"
        }
    ],
    "sg:phone":"+1   ",
    "sg:postcode":"19148",
    "sg:province":"PA",
    "sg:tags":[
        "medical"
    ],
    "wof:name":"Ar-Jay Medcare Center",
    "wof:placetype":"venue"
},
  "geometry": {"coordinates":[-75.15258799999999,39.923392],"type":"Point"}
}