{
  "type": "Feature",
  "properties": {
    "iso:country":"US",
    "sg:address":"24 Salina St",
    "sg:city":"Moosic",
    "sg:classifiers":[
        {
            "category":"Shopping",
            "type":"Retail Goods"
        }
    ],
    "sg:phone":"+1 570 457 5469",
    "sg:postcode":"18507",
    "sg:province":"PA",
    "sg:tags":[
        "outdoor",
        "lighting",
        "specialty"
    ],
    "wof:name":"Glenwood Products Inc",
    "wof:placetype":"venue"
},
  "geometry": {"coordinates":[-75.729147,41.351699],"type":"Point"}
}