{
  "type": "Feature",
  "properties": {
    "iso:country":"US",
    "sg:address":"364 Robinson Dr",
    "sg:city":"Broomall",
    "sg:classifiers":[
        {
            "category":"Shopping",
            "subcategory":"Pharmacy",
            "type":"Retail Goods"
        }
    ],
    "sg:phone":"+1   ",
    "sg:postcode":"19008",
    "sg:province":"PA",
    "wof:name":"Balwynne Pharmacy",
    "wof:placetype":"venue"
},
  "geometry": {"coordinates":[-75.350424,39.961624],"type":"Point"}
}