{
  "type": "Feature",
  "properties": {
    "iso:country":"US",
    "sg:address":"3399 Brodhead Rd",
    "sg:city":"Aliquippa",
    "sg:classifiers":[
        {
            "category":"Health Services",
            "subcategory":"Podiatrist",
            "type":"Services"
        }
    ],
    "sg:phone":"+1 724 775 4288",
    "sg:postcode":"15001",
    "sg:province":"PA",
    "wof:name":"Cinzia V Newman DPM",
    "wof:placetype":"venue"
},
  "geometry": {"coordinates":[-80.255291,40.57442],"type":"Point"}
}