{
  "type": "Feature",
  "properties": {
    "iso:country":"US",
    "sg:address":"3200 Horizon Dr",
    "sg:city":"King Of Prussia",
    "sg:classifiers":[
        {
            "category":"Professional",
            "subcategory":"Computer Services",
            "type":"Services"
        }
    ],
    "sg:phone":"+1 610 313 2330",
    "sg:postcode":"19406",
    "sg:province":"PA",
    "sg:tags":[
        "processing",
        "datum"
    ],
    "wof:name":"First Data Corp",
    "wof:placetype":"venue"
},
  "geometry": {"coordinates":[-75.342383,40.090564],"type":"Point"}
}