{
  "type": "Feature",
  "properties": {
    "iso:country":"US",
    "sg:address":"1026 E Lisburn Rd",
    "sg:city":"Mechanicsburg",
    "sg:classifiers":[
        {
            "category":"Manufacturing",
            "subcategory":"Glass & Minerals",
            "type":"Manufacturing & Wholesale Goods"
        }
    ],
    "sg:phone":"+1 717 766 2534",
    "sg:postcode":"17055",
    "sg:province":"PA",
    "sg:tags":[
        "leaded-commercial",
        "glass-stained",
        "leaded",
        "stained"
    ],
    "wof:name":"Carolyn Jones",
    "wof:placetype":"venue"
},
  "geometry": {"coordinates":[-76.93937699999999,40.17244],"type":"Point"}
}