{
  "type": "Feature",
  "properties": {
    "iso:country":"US",
    "sg:address":"311 Hoernerstown Rd",
    "sg:city":"Hummelstown",
    "sg:classifiers":[
        {
            "category":"Manufacturing",
            "subcategory":"Food",
            "type":"Manufacturing & Wholesale Goods"
        },
        {
            "category":"Autos & Motor Vehicles",
            "subcategory":"Auto Supplies",
            "type":"Retail Goods"
        },
        {
            "category":"Farming",
            "subcategory":"Farm",
            "type":"Manufacturing & Wholesale Goods"
        }
    ],
    "sg:phone":"+1 717 566 3284",
    "sg:postcode":"17036",
    "sg:province":"PA",
    "sg:tags":[
        "alfalfa",
        "corn",
        "product"
    ],
    "wof:name":"John D Cassel And Sons Inc",
    "wof:placetype":"venue"
},
  "geometry": {"coordinates":[-76.724197,40.303104],"type":"Point"}
}