{
  "type": "Feature",
  "properties": {
    "iso:country":"US",
    "sg:address":"2004 Charwood Dr",
    "sg:city":"Uniontown",
    "sg:classifiers":[
        {
            "category":"Personal",
            "type":"Services"
        }
    ],
    "sg:phone":"+1 724 437 0464",
    "sg:postcode":"15401",
    "sg:province":"PA",
    "sg:tags":[
        "assistant"
    ],
    "wof:name":"Radcliffe Court",
    "wof:placetype":"venue"
},
  "geometry": {"coordinates":[-79.755357,39.886771],"type":"Point"}
}