{
  "type": "Feature",
  "properties": {
    "addr:full":"524 Penn Ave Scranton PA 18503",
    "addr:housenumber":"524",
    "addr:postcode":"18503",
    "addr:street":"Penn Ave",
    "iso:country":"US",
    "sg:address":"524 Penn Ave",
    "sg:city":"Scranton",
    "sg:classifiers":[
        {
            "category":"Autos & Motor Vehicles",
            "subcategory":"Automobile Sales",
            "type":"Retail Goods"
        }
    ],
    "sg:phone":"+1 570 344 2892",
    "sg:postcode":"18503",
    "sg:province":"PA",
    "sg:tags":[
        "car",
        "dealer"
    ],
    "wof:name":"Brian's Auto Body",
    "wof:placetype":"venue"
},
  "geometry": {"coordinates":[-75.661277,41.413917],"type":"Point"}
}