{
  "type": "Feature",
  "properties": {
    "addr:full":"141 Conyngham Crest Dr Sugarloaf PA 18249",
    "addr:housenumber":"141",
    "addr:postcode":"18249",
    "addr:street":"Conyngham Crest Dr",
    "iso:country":"US",
    "sg:address":"141 Conyngham Crest Dr",
    "sg:city":"Sugarloaf",
    "sg:phone":"+1   ",
    "sg:postcode":"18249",
    "sg:province":"PA",
    "sg:tags":[
        "farm",
        "field",
        "crop"
    ],
    "wof:name":"Earl T Miller",
    "wof:placetype":"venue"
},
  "geometry": {"coordinates":[-76.06072,40.977511],"type":"Point"}
}