{
  "type": "Feature",
  "properties": {
    "iso:country":"US",
    "sg:address":"657 Rte 519",
    "sg:city":"Eighty Four",
    "sg:classifiers":[
        {
            "category":"Retail",
            "subcategory":"Auto Repair",
            "type":"Services"
        }
    ],
    "sg:phone":"+1 724 222 7757",
    "sg:postcode":"15330",
    "sg:province":"PA",
    "sg:tags":[
        "automotive"
    ],
    "wof:name":"Phixt Automotive Repair",
    "wof:placetype":"venue"
},
  "geometry": {"coordinates":[-80.134659,40.168795],"type":"Point"}
}