{
  "type": "Feature",
  "properties": {
    "addr:full":"752 Rebecca St North Huntingdon PA 15642",
    "addr:housenumber":"752",
    "addr:postcode":"15642",
    "addr:street":"Rebecca St",
    "iso:country":"US",
    "sg:address":"752 Rebecca St",
    "sg:city":"North Huntingdon",
    "sg:classifiers":[
        {
            "category":"Retail",
            "subcategory":"Repair Shop",
            "type":"Services"
        }
    ],
    "sg:phone":"+1 724 864 3593",
    "sg:postcode":"15642",
    "sg:province":"PA",
    "sg:tags":[
        "appliance"
    ],
    "wof:name":"Larry's All Appliance Repair",
    "wof:placetype":"venue"
},
  "geometry": {"coordinates":[-79.740225,40.317347],"type":"Point"}
}