{
  "type": "Feature",
  "properties": {
    "iso:country":"US",
    "sg:address":"1326 Hope Hollow Rd",
    "sg:city":"Carnegie",
    "sg:classifiers":[
        {
            "category":"Personal",
            "subcategory":"Beauty Salon",
            "type":"Services"
        }
    ],
    "sg:phone":"+1 412 279 2713",
    "sg:postcode":"15106",
    "sg:province":"PA",
    "sg:tags":[
        "manicuring"
    ],
    "wof:name":"Heavenly Nails",
    "wof:placetype":"venue"
},
  "geometry": {"coordinates":[-80.075171,40.390961],"type":"Point"}
}