{
  "type": "Feature",
  "properties": {
    "iso:country":"US",
    "sg:address":"5101 Carnoustie Ct",
    "sg:city":"Presto",
    "sg:classifiers":[
        {
            "category":"Freight",
            "type":"Transportation"
        }
    ],
    "sg:phone":"+1   ",
    "sg:postcode":"15142",
    "sg:province":"PA",
    "wof:name":"Co-Op Mesca Freight",
    "wof:placetype":"venue"
},
  "geometry": {"coordinates":[-80.12566099999999,40.390524],"type":"Point"}
}