{
  "type": "Feature",
  "properties": {
    "iso:country":"US",
    "sg:address":"22 E Springfield Ave",
    "sg:city":"Philadelphia",
    "sg:classifiers":[
        {
            "category":"Manufacturing",
            "subcategory":"Printing",
            "type":"Manufacturing & Wholesale Goods"
        }
    ],
    "sg:phone":"+1 610 520 1592",
    "sg:postcode":"19118",
    "sg:province":"PA",
    "sg:tags":[
        "periodical"
    ],
    "wof:name":"Forbes Magazine",
    "wof:placetype":"venue"
},
  "geometry": {"coordinates":[-75.19880499999999,40.07052],"type":"Point"}
}