{
  "type": "Feature",
  "properties": {
    "iso:country":"US",
    "sg:address":"31 S Commerce Way",
    "sg:city":"Bethlehem",
    "sg:classifiers":[
        {
            "category":"Education",
            "subcategory":"Special Training",
            "type":"Public Place"
        },
        {
            "category":"Education",
            "subcategory":"School",
            "type":"Public Place"
        }
    ],
    "sg:phone":"+1 610 691 1300",
    "sg:postcode":"18017",
    "sg:province":"PA",
    "sg:tags":[
        "high",
        "middle",
        "specialty",
        "elementary"
    ],
    "sg:website":"www.triangle-tech.edu",
    "wof:name":"Triangle Tech",
    "wof:placetype":"venue"
},
  "geometry": {"coordinates":[-75.37581299999999,40.673024],"type":"Point"}
}