{
  "type": "Feature",
  "properties": {
    "iso:country":"US",
    "sg:address":"2717 W Main St",
    "sg:city":"Norristown",
    "sg:classifiers":[
        {
            "category":"Restaurant",
            "type":"Food & Drink"
        }
    ],
    "sg:phone":"+1 610 726 1558",
    "sg:postcode":"19403",
    "sg:province":"PA",
    "sg:tags":[
        "pizza"
    ],
    "wof:name":"Big Daddy's Brick Oven Pizza",
    "wof:placetype":"venue"
},
  "geometry": {"coordinates":[-75.393771,40.145485],"type":"Point"}
}