{
  "type": "Feature",
  "properties": {
    "iso:country":"US",
    "sg:address":"118 Urick Ln",
    "sg:city":"Monroeville",
    "sg:classifiers":[
        {
            "category":"Professional",
            "subcategory":"Business Services",
            "type":"Services"
        }
    ],
    "sg:phone":"+1   ",
    "sg:postcode":"15146",
    "sg:province":"PA",
    "wof:name":"Auroville",
    "wof:placetype":"venue"
},
  "geometry": {"coordinates":[-79.737678,40.407705],"type":"Point"}
}