{
  "type": "Feature",
  "properties": {
    "addr:full":"258 Frysville Rd Ephrata PA 17522",
    "addr:housenumber":"258",
    "addr:postcode":"17522",
    "addr:street":"Frysville Rd",
    "iso:country":"US",
    "sg:address":"258 Frysville Rd",
    "sg:city":"Ephrata",
    "sg:classifiers":[
        {
            "category":"Farming",
            "subcategory":"Livestock Farm",
            "type":"Manufacturing & Wholesale Goods"
        }
    ],
    "sg:phone":"+1   ",
    "sg:postcode":"17522",
    "sg:province":"PA",
    "sg:tags":[
        "corn",
        "wheat",
        "feedlot",
        "beef",
        "cattle"
    ],
    "wof:name":"Nelson Martin",
    "wof:placetype":"venue"
},
  "geometry": {"coordinates":[-76.11384200000001,40.167782],"type":"Point"}
}