{
  "type": "Feature",
  "properties": {
    "iso:country":"US",
    "sg:address":"230 S Broad St",
    "sg:city":"Grove City",
    "sg:classifiers":[
        {
            "category":"Insurance",
            "subcategory":"Insurance Agent",
            "type":"Services"
        }
    ],
    "sg:phone":"+1 724 458 5231",
    "sg:postcode":"16127",
    "sg:province":"PA",
    "wof:name":"Primerica Financial Svc",
    "wof:placetype":"venue"
},
  "geometry": {"coordinates":[-80.08653099999999,41.159141],"type":"Point"}
}