{
  "type": "Feature",
  "properties": {
    "addr:full":"4853 Campbells Run Rd Pittsburgh PA 15205",
    "addr:housenumber":"4853",
    "addr:postcode":"15205",
    "addr:street":"Campbells Run Rd",
    "iso:country":"US",
    "sg:address":"4853 Campbells Run Rd",
    "sg:city":"Pittsburgh",
    "sg:classifiers":[
        {
            "category":"Manufacturing",
            "subcategory":"Tools & Machinery",
            "type":"Manufacturing & Wholesale Goods"
        }
    ],
    "sg:phone":"+1 412 787 2832",
    "sg:postcode":"15205",
    "sg:province":"PA",
    "sg:tags":[
        "steel",
        "rolling",
        "mfr"
    ],
    "wof:name":"Gega Corp",
    "wof:placetype":"venue"
},
  "geometry": {"coordinates":[-80.141656,40.434225],"type":"Point"}
}