{
  "type": "Feature",
  "properties": {
    "addr:full":"108 Bower Dr Sewickley PA 15143",
    "addr:housenumber":"108",
    "addr:postcode":"15143",
    "addr:street":"Bower Dr",
    "iso:country":"US",
    "sg:address":"108 Bower Dr",
    "sg:city":"Sewickley",
    "sg:classifiers":[
        {
            "category":"Professional",
            "subcategory":"Business Services",
            "type":"Services"
        }
    ],
    "sg:phone":"+1   ",
    "sg:postcode":"15143",
    "sg:province":"PA",
    "wof:name":"Electronic Systems Services",
    "wof:placetype":"venue"
},
  "geometry": {"coordinates":[-80.14797299999999,40.588517],"type":"Point"}
}