{
  "type": "Feature",
  "properties": {
    "addr:full":"218 Stuart Ave Downingtown PA 19335",
    "addr:housenumber":"218",
    "addr:postcode":"19335",
    "addr:street":"Stuart Ave",
    "iso:country":"US",
    "sg:address":"218 Stuart Ave",
    "sg:city":"Downingtown",
    "sg:classifiers":[
        {
            "category":"Building & Trades",
            "subcategory":"Landscaping Services",
            "type":"Services"
        }
    ],
    "sg:phone":"+1   ",
    "sg:postcode":"19335",
    "sg:province":"PA",
    "wof:name":"Environmental Ldscp MGT Servi",
    "wof:placetype":"venue"
},
  "geometry": {"coordinates":[-75.71114300000001,40.004913],"type":"Point"}
}