{
  "type": "Feature",
  "properties": {
    "addr:full":"152 Kittanning Pike Pittsburgh PA 15215",
    "addr:housenumber":"152",
    "addr:postcode":"15215",
    "addr:street":"Kittanning Pike",
    "iso:country":"US",
    "sg:address":"152 Kittanning Pike",
    "sg:city":"Pittsburgh",
    "sg:classifiers":[
        {
            "category":"Government",
            "subcategory":"Fire Station",
            "type":"Public Place"
        }
    ],
    "sg:phone":"+1   ",
    "sg:postcode":"15215",
    "sg:province":"PA",
    "sg:tags":[
        "protection"
    ],
    "wof:name":"Pleasant Vly Vlntr Fire Co N",
    "wof:placetype":"venue"
},
  "geometry": {"coordinates":[-79.92005899999999,40.503503],"type":"Point"}
}