{
  "type": "Feature",
  "properties": {
    "iso:country":"US",
    "sg:address":"7980 W Ridge Rd",
    "sg:city":"Fairview",
    "sg:classifiers":[
        {
            "category":"Manufacturing",
            "subcategory":"Tools & Machinery",
            "type":"Manufacturing & Wholesale Goods"
        }
    ],
    "sg:phone":"+1 814 474 1543",
    "sg:postcode":"16415",
    "sg:province":"PA",
    "sg:tags":[
        "die",
        "maker"
    ],
    "wof:name":"Darr Industries Inc",
    "wof:placetype":"venue"
},
  "geometry": {"coordinates":[-80.264335,42.024302],"type":"Point"}
}