{
  "type": "Feature",
  "properties": {
    "iso:country":"US",
    "sg:address":"434 Fallowfield Ave",
    "sg:city":"Charleroi",
    "sg:classifiers":[
        {
            "category":"Organizations",
            "subcategory":"Membership Organization",
            "type":"Services"
        },
        {
            "category":"Organizations",
            "subcategory":"Non-profit Organization",
            "type":"Services"
        }
    ],
    "sg:phone":"+1 724 483 2399",
    "sg:postcode":"15022",
    "sg:province":"PA",
    "sg:tags":[
        "charity"
    ],
    "sg:website":"http://www.actionhousing.com",
    "wof:name":"Action Housing",
    "wof:placetype":"venue"
},
  "geometry": {"coordinates":[-79.897486,40.137323],"type":"Point"}
}