{
  "type": "Feature",
  "properties": {
    "iso:country":"US",
    "sg:address":"1717 E Main St",
    "sg:city":"Waynesboro",
    "sg:classifiers":[
        {
            "category":"Personal",
            "subcategory":"Nail Salon",
            "type":"Services"
        }
    ],
    "sg:phone":"+1 717 765 4443",
    "sg:postcode":"17268",
    "sg:province":"PA",
    "wof:name":"Pro Nails",
    "wof:placetype":"venue"
},
  "geometry": {"coordinates":[-77.564939,39.74968],"type":"Point"}
}