{
  "type": "Feature",
  "properties": {
    "iso:country":"US",
    "sg:address":"806 N Chester Rd",
    "sg:city":"West Chester",
    "sg:classifiers":[
        {
            "category":"Professional",
            "type":"Services"
        }
    ],
    "sg:phone":"+1   ",
    "sg:postcode":"19380",
    "sg:province":"PA",
    "wof:name":"Rich Pruchnik",
    "wof:placetype":"venue"
},
  "geometry": {"coordinates":[-75.543965,39.993779],"type":"Point"}
}