{
  "type": "Feature",
  "properties": {
    "iso:country":"US",
    "sg:address":"1430 Dartmouth St",
    "sg:city":"Scranton",
    "sg:classifiers":[
        {
            "category":"Building & Trades",
            "subcategory":"Construction",
            "type":"Services"
        }
    ],
    "sg:phone":"+1   ",
    "sg:postcode":"18504",
    "sg:province":"PA",
    "sg:tags":[
        "contractor"
    ],
    "wof:name":"Kitchen Man",
    "wof:placetype":"venue"
},
  "geometry": {"coordinates":[-75.69349099999999,41.406105],"type":"Point"}
}