{
  "type": "Feature",
  "properties": {
    "iso:country":"US",
    "sg:address":"469 Broad St",
    "sg:city":"New Bethlehem",
    "sg:classifiers":[
        {
            "category":"Organizations",
            "subcategory":"Community Association",
            "type":"Services"
        }
    ],
    "sg:phone":"+1 814 275 1243",
    "sg:postcode":"16242",
    "sg:province":"PA",
    "sg:tags":[
        "fraternal"
    ],
    "wof:name":"Fraternal Order Of Eagles",
    "wof:placetype":"venue"
},
  "geometry": {"coordinates":[-79.330482,41.001641],"type":"Point"}
}