{
  "type": "Feature",
  "properties": {
    "iso:country":"US",
    "sg:address":"28 W Market St",
    "sg:city":"Mount Union",
    "sg:classifiers":[
        {
            "category":"Education",
            "subcategory":"School",
            "type":"Public Place"
        }
    ],
    "sg:phone":"+1   ",
    "sg:postcode":"17066",
    "sg:province":"PA",
    "sg:tags":[
        "district"
    ],
    "wof:name":"Mount Union Area School Dst",
    "wof:placetype":"venue"
},
  "geometry": {"coordinates":[-77.884783,40.384199],"type":"Point"}
}