{
  "type": "Feature",
  "properties": {
    "iso:country":"US",
    "sg:address":"1432 Obey Ave",
    "sg:city":"Pittsburgh",
    "sg:classifiers":[
        {
            "category":"Building & Trades",
            "subcategory":"Construction",
            "type":"Services"
        }
    ],
    "sg:phone":"+1   ",
    "sg:postcode":"15205",
    "sg:province":"PA",
    "sg:tags":[
        "painting",
        "contractor"
    ],
    "wof:name":"D William Westfall",
    "wof:placetype":"venue"
},
  "geometry": {"coordinates":[-80.049588,40.438357],"type":"Point"}
}