{
  "type": "Feature",
  "properties": {
    "iso:country":"US",
    "sg:address":"1629 N Main St",
    "sg:city":"Butler",
    "sg:classifiers":[
        {
            "category":"Real Estate",
            "subcategory":"Real Estate Agent",
            "type":"Services"
        }
    ],
    "sg:phone":"+1   ",
    "sg:postcode":"16001",
    "sg:province":"PA",
    "wof:name":"Everest Consulting Group LP",
    "wof:placetype":"venue"
},
  "geometry": {"coordinates":[-79.912041,40.901502],"type":"Point"}
}