{
  "type": "Feature",
  "properties": {
    "iso:country":"US",
    "sg:address":"777 Rural Ave",
    "sg:city":"Williamsport",
    "sg:classifiers":[
        {
            "category":"Social Services",
            "subcategory":"Job Training",
            "type":"Services"
        }
    ],
    "sg:phone":"+1 570 321 2600",
    "sg:postcode":"17701",
    "sg:province":"PA",
    "sg:tags":[
        "rehabilitation"
    ],
    "wof:name":"Rehabilitation Center Gibson",
    "wof:placetype":"venue"
},
  "geometry": {"coordinates":[-77.016947,41.247742],"type":"Point"}
}