{
  "type": "Feature",
  "properties": {
    "iso:country":"US",
    "sg:address":"150 Maple Dr",
    "sg:city":"New Kensington",
    "sg:classifiers":[
        {
            "category":"Building & Trades",
            "subcategory":"Electrical",
            "type":"Services"
        }
    ],
    "sg:phone":"+1 724 339 8777",
    "sg:postcode":"15068",
    "sg:province":"PA",
    "sg:tags":[
        "electrician"
    ],
    "wof:name":"Potts Electric",
    "wof:placetype":"venue"
},
  "geometry": {"coordinates":[-79.67401700000001,40.557918],"type":"Point"}
}