{
  "type": "Feature",
  "properties": {
    "iso:country":"US",
    "sg:address":"100 Schuylkill Medical Plz",
    "sg:city":"Pottsville",
    "sg:classifiers":[
        {
            "category":"Health Services",
            "subcategory":"Doctor",
            "type":"Services"
        }
    ],
    "sg:phone":"+1   ",
    "sg:postcode":"17901",
    "sg:province":"PA",
    "sg:tags":[
        "medical"
    ],
    "wof:name":"Adam J Altman MD",
    "wof:placetype":"venue"
},
  "geometry": {"coordinates":[-76.189859,40.681964],"type":"Point"}
}