{
  "type": "Feature",
  "properties": {
    "iso:country":"US",
    "sg:address":"537 Venard Rd",
    "sg:city":"Clarks Summit",
    "sg:classifiers":[
        {
            "category":"Social Services",
            "type":"Services"
        }
    ],
    "sg:phone":"+1 570 587 4741",
    "sg:postcode":"18411",
    "sg:province":"PA",
    "sg:tags":[
        "residential",
        "special",
        "care"
    ],
    "wof:name":"Lourdesmont",
    "wof:placetype":"venue"
},
  "geometry": {"coordinates":[-75.68498,41.497506],"type":"Point"}
}