{
  "type": "Feature",
  "properties": {
    "addr:full":"7301 N 20th St Philadelphia PA 19138",
    "addr:housenumber":"7301",
    "addr:postcode":"19138",
    "addr:street":"N 20Th St",
    "iso:country":"US",
    "sg:address":"7301 N 20th St",
    "sg:city":"Philadelphia",
    "sg:classifiers":[
        {
            "category":"Banks & Credit Unions",
            "subcategory":"Bank",
            "type":"Services"
        }
    ],
    "sg:phone":"+1 215 276 1052",
    "sg:postcode":"19138",
    "sg:province":"PA",
    "sg:tags":[
        "cashing",
        "check"
    ],
    "wof:name":"Fast Cash Atm",
    "wof:placetype":"venue"
},
  "geometry": {"coordinates":[-75.150719,40.066367],"type":"Point"}
}