{
  "type": "Feature",
  "properties": {
    "iso:country":"US",
    "sg:address":"10 Buckthorn Dr",
    "sg:city":"Carlisle",
    "sg:classifiers":[
        {
            "category":"Arts & Performance",
            "subcategory":"Theater",
            "type":"Entertainment"
        }
    ],
    "sg:phone":"+1 717 249 8322",
    "sg:postcode":"17013",
    "sg:province":"PA",
    "sg:tags":[
        "dj",
        "live",
        "music"
    ],
    "wof:name":"Thomas Ray Dj Entertainment",
    "wof:placetype":"venue"
},
  "geometry": {"coordinates":[-77.15830200000001,40.184399],"type":"Point"}
}