{
  "type": "Feature",
  "properties": {
    "iso:country":"US",
    "sg:address":"941 Longs Gap Rd",
    "sg:city":"Carlisle",
    "sg:classifiers":[
        {
            "category":"Wholesale",
            "subcategory":"Farm Supplies",
            "type":"Manufacturing & Wholesale Goods"
        }
    ],
    "sg:phone":"+1   ",
    "sg:postcode":"17013",
    "sg:province":"PA",
    "wof:name":"G Rich Sales",
    "wof:placetype":"venue"
},
  "geometry": {"coordinates":[-77.209175,40.24573],"type":"Point"}
}