{
  "type": "Feature",
  "properties": {
    "iso:country":"US",
    "sg:address":"463 Zions Church Rd",
    "sg:city":"Shoemakersville",
    "sg:classifiers":[
        {
            "category":"Building & Trades",
            "subcategory":"Construction",
            "type":"Services"
        }
    ],
    "sg:phone":"+1 610 562 2118",
    "sg:postcode":"19555",
    "sg:province":"PA",
    "sg:tags":[
        "wallcoverings-installation",
        "wallpaper",
        "painting",
        "contractor"
    ],
    "wof:name":"Donald Smith",
    "wof:placetype":"venue"
},
  "geometry": {"coordinates":[-75.95537299999999,40.524712],"type":"Point"}
}