{
  "type": "Feature",
  "properties": {
    "addr:full":"276 N Wales Rd North Wales PA 19454",
    "addr:housenumber":"276",
    "addr:postcode":"19454",
    "addr:street":"N Wales Rd",
    "iso:country":"US",
    "sg:address":"276 N Wales Rd",
    "sg:city":"North Wales",
    "sg:classifiers":[
        {
            "category":"Shopping",
            "subcategory":"Clothing, Apparel, & Fashions",
            "type":"Retail Goods"
        }
    ],
    "sg:phone":"+1 215 362 7510",
    "sg:postcode":"19454",
    "sg:province":"PA",
    "sg:tags":[
        "leather"
    ],
    "sg:website":"www.wilsonsleather.com",
    "wof:name":"Wilson's Suede & Leather",
    "wof:placetype":"venue"
},
  "geometry": {"coordinates":[-75.260177,40.230923],"type":"Point"}
}