{
  "type": "Feature",
  "properties": {
    "iso:country":"US",
    "sg:address":"1760 Baltimore Pike",
    "sg:city":"Avondale",
    "sg:classifiers":[
        {
            "category":"Farming",
            "subcategory":"Farm",
            "type":"Manufacturing & Wholesale Goods"
        }
    ],
    "sg:phone":"+1 610 268 2557",
    "sg:postcode":"19311",
    "sg:province":"PA",
    "sg:tags":[
        "mushroom"
    ],
    "wof:name":"Remo Toto's Mushroom Svc",
    "wof:placetype":"venue"
},
  "geometry": {"coordinates":[-75.774492,39.825534],"type":"Point"}
}