{
  "type": "Feature",
  "properties": {
    "iso:country":"US",
    "sg:address":"175 N Henderson Rd",
    "sg:city":"King Of Prussia",
    "sg:classifiers":[
        {
            "category":"Food & Beverages",
            "subcategory":"Liquor & Beverages",
            "type":"Retail Goods"
        },
        {
            "category":"Wholesale",
            "subcategory":"Beer",
            "type":"Manufacturing & Wholesale Goods"
        }
    ],
    "sg:phone":"+1 610 265 2828",
    "sg:postcode":"19406",
    "sg:province":"PA",
    "sg:tags":[
        "distributor",
        "ale"
    ],
    "wof:name":"Valley Forge Beverage Center",
    "wof:placetype":"venue"
},
  "geometry": {"coordinates":[-75.366361,40.097346],"type":"Point"}
}