{
  "type": "Feature",
  "properties": {
    "iso:country":"US",
    "sg:address":"167 Upper Claar Rd",
    "sg:city":"Claysburg",
    "sg:classifiers":[
        {
            "category":"Retail",
            "subcategory":"Auto Repair",
            "type":"Services"
        }
    ],
    "sg:phone":"+1 814 239 5711",
    "sg:postcode":"16625",
    "sg:province":"PA",
    "sg:tags":[
        "repairing",
        "automobile"
    ],
    "wof:name":"Medasia's Garage",
    "wof:placetype":"venue"
},
  "geometry": {"coordinates":[-78.522971,40.289453],"type":"Point"}
}