{
  "type": "Feature",
  "properties": {
    "iso:country":"US",
    "sg:address":"100 W Logan St",
    "sg:city":"Philadelphia",
    "sg:classifiers":[
        {
            "category":"Professional",
            "type":"Services"
        }
    ],
    "sg:phone":"+1 215 563 5468",
    "sg:postcode":"19144",
    "sg:province":"PA",
    "wof:name":"Land Services USA",
    "wof:placetype":"venue"
},
  "geometry": {"coordinates":[-75.16431300000001,40.02638],"type":"Point"}
}