{
  "type": "Feature",
  "properties": {
    "iso:country":"US",
    "sg:address":"238 Jackson St",
    "sg:city":"Rochester",
    "sg:classifiers":[
        {
            "category":"Health Services",
            "subcategory":"Health Practitioner",
            "type":"Services"
        }
    ],
    "sg:phone":"+1 724 773 9727",
    "sg:postcode":"16141",
    "sg:province":"PA",
    "sg:tags":[
        "nurse",
        "registry"
    ],
    "wof:name":"PRN Health Svc",
    "wof:placetype":"venue"
},
  "geometry": {"coordinates":[-80.40014499999999,40.834061],"type":"Point"}
}