{
  "type": "Feature",
  "properties": {
    "iso:country":"US",
    "sg:address":"219 W Afton Ave",
    "sg:city":"Morrisville",
    "sg:classifiers":[
        {
            "category":"Building & Trades",
            "subcategory":"Construction",
            "type":"Services"
        }
    ],
    "sg:phone":"+1 215 369 8648",
    "sg:postcode":"19067",
    "sg:province":"PA",
    "sg:tags":[
        "home",
        "improvement",
        "contractor"
    ],
    "wof:name":"Tub Toppers",
    "wof:placetype":"venue"
},
  "geometry": {"coordinates":[-74.849891,40.238054],"type":"Point"}
}