{
  "type": "Feature",
  "properties": {
    "iso:country":"US",
    "sg:address":"31 Larson Rd",
    "sg:city":"Muncy",
    "sg:classifiers":[
        {
            "category":"Shopping",
            "subcategory":"Luggage & Leather Goods",
            "type":"Retail Goods"
        }
    ],
    "sg:phone":"+1   ",
    "sg:postcode":"17756",
    "sg:province":"PA",
    "wof:name":"Black Cat Leather",
    "wof:placetype":"venue"
},
  "geometry": {"coordinates":[-76.707109,41.135014],"type":"Point"}
}