{
  "type": "Feature",
  "properties": {
    "iso:country":"US",
    "sg:address":"210 Kindig Rd",
    "sg:city":"Littlestown",
    "sg:classifiers":[
        {
            "category":"Personal",
            "subcategory":"Beauty Salon",
            "type":"Services"
        }
    ],
    "sg:phone":"+1 717 359 9546",
    "sg:postcode":"17340",
    "sg:province":"PA",
    "wof:name":"Jacque's Hair & Tanning",
    "wof:placetype":"venue"
},
  "geometry": {"coordinates":[-77.064894,39.738694],"type":"Point"}
}