{
  "type": "Feature",
  "properties": {
    "iso:country":"US",
    "sg:address":"912 Howard St",
    "sg:city":"Brownsville",
    "sg:classifiers":[
        {
            "category":"Organizations",
            "subcategory":"Community Association",
            "type":"Services"
        }
    ],
    "sg:phone":"+1   ",
    "sg:postcode":"15417",
    "sg:province":"PA",
    "wof:name":"Free & Accepted Masons of",
    "wof:placetype":"venue"
},
  "geometry": {"coordinates":[-79.898027,40.009569],"type":"Point"}
}