{
  "type": "Feature",
  "properties": {
    "addr:full":"2597 Schoenersville Rd Ste 101 Bethlehem PA 18017",
    "addr:housenumber":"2597",
    "addr:postcode":"18017",
    "addr:street":"Schoenersville Rd Ste 101",
    "iso:country":"US",
    "sg:address":"2597 Schoenersville Rd Ste 101",
    "sg:city":"Bethlehem",
    "sg:classifiers":[
        {
            "category":"Health Services",
            "subcategory":"Doctor",
            "type":"Services"
        }
    ],
    "sg:phone":"+1 610 691 0973",
    "sg:postcode":"18017",
    "sg:province":"PA",
    "sg:tags":[
        "podiatrist",
        "orthopedist"
    ],
    "wof:name":"Sauer Thomas S MD Orthopedic Assocts of Bthlhm Inc",
    "wof:placetype":"venue"
},
  "geometry": {"coordinates":[-75.37979900000001,40.654301],"type":"Point"}
}