{
  "type": "Feature",
  "properties": {
    "addr:full":"534 Diamond St Slatington PA 18080",
    "addr:housenumber":"534",
    "addr:postcode":"18080",
    "addr:street":"Diamond St",
    "iso:country":"US",
    "sg:address":"534 Diamond St",
    "sg:city":"Slatington",
    "sg:classifiers":[
        {
            "category":"Shopping",
            "subcategory":"Crafts & Fabrics",
            "type":"Retail Goods"
        }
    ],
    "sg:phone":"+1   ",
    "sg:postcode":"18080",
    "sg:province":"PA",
    "sg:tags":[
        "sewing"
    ],
    "wof:name":"Sew Unusual",
    "wof:placetype":"venue"
},
  "geometry": {"coordinates":[-75.60976700000001,40.758574],"type":"Point"}
}