{
  "type": "Feature",
  "properties": {
    "iso:country":"US",
    "sg:address":"9964 Haldeman Ave",
    "sg:city":"Philadelphia",
    "sg:classifiers":[
        {
            "category":"Building & Trades",
            "subcategory":"Electrical",
            "type":"Services"
        }
    ],
    "sg:phone":"+1 215 677 6667",
    "sg:postcode":"19115",
    "sg:province":"PA",
    "sg:tags":[
        "electrical",
        "contractor"
    ],
    "wof:name":"Bright Lights Electrical Contr",
    "wof:placetype":"venue"
},
  "geometry": {"coordinates":[-75.025002,40.095938],"type":"Point"}
}