{
  "type": "Feature",
  "properties": {
    "addr:full":"710 E Johnson Hwy Norristown PA 19401",
    "addr:housenumber":"710",
    "addr:postcode":"19401",
    "addr:street":"E Johnson Hwy",
    "iso:country":"US",
    "sg:address":"710 E Johnson Hwy",
    "sg:city":"Norristown",
    "sg:classifiers":[
        {
            "category":"Health Services",
            "subcategory":"Doctor",
            "type":"Services"
        }
    ],
    "sg:phone":"+1   ",
    "sg:postcode":"19401",
    "sg:province":"PA",
    "sg:tags":[
        "medical"
    ],
    "wof:name":"Zal Alice J D O Fmly Med Care",
    "wof:placetype":"venue"
},
  "geometry": {"coordinates":[-75.317638,40.125378],"type":"Point"}
}