{
  "type": "Feature",
  "properties": {
    "iso:country":"US",
    "sg:address":"718 E McMurray Rd",
    "sg:city":"Canonsburg",
    "sg:classifiers":[
        {
            "category":"Bars & Pubs",
            "subcategory":"Lounge",
            "type":"Food & Drink"
        },
        {
            "category":"Arts & Performance",
            "subcategory":"Music",
            "type":"Entertainment"
        }
    ],
    "sg:phone":"+1 724 942 1277",
    "sg:postcode":"15317",
    "sg:province":"PA",
    "sg:tags":[
        "dj",
        "karaoke"
    ],
    "sg:website":"www.totalentertainment.8m.com",
    "wof:name":"Total Entertainment",
    "wof:placetype":"venue"
},
  "geometry": {"coordinates":[-80.0774,40.285801],"type":"Point"}
}