{
  "type": "Feature",
  "properties": {
    "addr:full":"194 Parfitt Ln Blairsville PA 15765",
    "addr:housenumber":"194",
    "addr:postcode":"15765",
    "addr:street":"Parfitt Ln",
    "iso:country":"US",
    "sg:address":"194 Parfitt Ln",
    "sg:city":"Blairsville",
    "sg:classifiers":[
        {
            "category":"Professional",
            "subcategory":"Engineering",
            "type":"Services"
        }
    ],
    "sg:phone":"+1 724 459 5280",
    "sg:postcode":"15765",
    "sg:province":"PA",
    "sg:tags":[
        "engineer"
    ],
    "wof:name":"Line-Star Maintenance & Repair",
    "wof:placetype":"venue"
},
  "geometry": {"coordinates":[-78.922284,40.599986],"type":"Point"}
}