{
  "type": "Feature",
  "properties": {
    "iso:country":"US",
    "sg:address":"14 Woodland Dr",
    "sg:city":"Pittsburgh",
    "sg:classifiers":[
        {
            "category":"Banks & Credit Unions",
            "subcategory":"Bank",
            "type":"Services"
        }
    ],
    "sg:phone":"+1   ",
    "sg:postcode":"15228",
    "sg:province":"PA",
    "sg:tags":[
        "mortgage"
    ],
    "wof:name":"Heritage Mortgage Corp",
    "wof:placetype":"venue"
},
  "geometry": {"coordinates":[-80.043994,40.359096],"type":"Point"}
}