{
  "type": "Feature",
  "properties": {
    "iso:country":"US",
    "sg:address":"109 Main St",
    "sg:city":"Susquehanna",
    "sg:classifiers":[
        {
            "category":"Shopping",
            "subcategory":"Gifts & Souvenirs",
            "type":"Retail Goods"
        }
    ],
    "sg:phone":"+1   ",
    "sg:postcode":"18847",
    "sg:province":"PA",
    "wof:name":"Gift Shop & More The",
    "wof:placetype":"venue"
},
  "geometry": {"coordinates":[-75.58626099999999,41.953611],"type":"Point"}
}