{
  "type": "Feature",
  "properties": {
    "addr:full":"1038 W Walnut St Coal Township PA 17866",
    "addr:housenumber":"1038",
    "addr:postcode":"17866",
    "addr:street":"W Walnut St",
    "iso:country":"US",
    "sg:address":"1038 W Walnut St",
    "sg:city":"Coal Township",
    "sg:classifiers":[
        {
            "category":"Wholesale",
            "subcategory":"Machinery & Supplies",
            "type":"Manufacturing & Wholesale Goods"
        },
        {
            "category":"Professional",
            "type":"Services"
        }
    ],
    "sg:phone":"+1 570 644 1108",
    "sg:postcode":"17866",
    "sg:province":"PA",
    "sg:tags":[
        "industrial",
        "establishment"
    ],
    "wof:name":"Penndel Containers Inc",
    "wof:placetype":"venue"
},
  "geometry": {"coordinates":[-76.56868799999999,40.789488],"type":"Point"}
}