{
  "type": "Feature",
  "properties": {
    "addr:full":"14 E Court St Doylestown PA 18901",
    "addr:housenumber":"14",
    "addr:postcode":"18901",
    "addr:street":"E Court St",
    "iso:country":"US",
    "sg:address":"14 E Court St",
    "sg:city":"Doylestown",
    "sg:classifiers":[
        {
            "category":"Banks & Credit Unions",
            "subcategory":"Investment Brokerage",
            "type":"Services"
        }
    ],
    "sg:phone":"+1 267 880 2200",
    "sg:postcode":"18901",
    "sg:province":"PA",
    "sg:tags":[
        "security"
    ],
    "wof:name":"Smith Barney",
    "wof:placetype":"venue"
},
  "geometry": {"coordinates":[-75.13032699999999,40.311211],"type":"Point"}
}