{
  "type": "Feature",
  "properties": {
    "addr:full":"300 6th Ave Pittsburgh PA 15222",
    "addr:housenumber":"300",
    "addr:postcode":"15222",
    "addr:street":"6Th Ave",
    "iso:country":"US",
    "sg:address":"300 6th Ave",
    "sg:city":"Pittsburgh",
    "sg:classifiers":[
        {
            "category":"Shopping",
            "subcategory":"Pharmacy",
            "type":"Retail Goods"
        }
    ],
    "sg:phone":"+1 717 214 8556",
    "sg:postcode":"15222",
    "sg:province":"PA",
    "wof:name":"Rite Aid Pharmacy",
    "wof:placetype":"venue"
},
  "geometry": {"coordinates":[-79.998919,40.441888],"type":"Point"}
}