{
  "type": "Feature",
  "properties": {
    "addr:full":"126 Hartford Ln Newtown PA 18940",
    "addr:housenumber":"126",
    "addr:postcode":"18940",
    "addr:street":"Hartford Ln",
    "iso:country":"US",
    "sg:address":"126 Hartford Ln",
    "sg:city":"Newtown",
    "sg:classifiers":[
        {
            "category":"Professional",
            "type":"Services"
        }
    ],
    "sg:phone":"+1   ",
    "sg:postcode":"18940",
    "sg:province":"PA",
    "wof:name":"Hartford Gardens",
    "wof:placetype":"venue"
},
  "geometry": {"coordinates":[-74.919723,40.245461],"type":"Point"}
}