{
  "type": "Feature",
  "properties": {
    "addr:full":"243 Wood St Bristol PA 19007",
    "addr:housenumber":"243",
    "addr:postcode":"19007",
    "addr:street":"Wood St",
    "iso:country":"US",
    "sg:address":"243 Wood St",
    "sg:city":"Bristol",
    "sg:classifiers":[
        {
            "category":"Building & Trades",
            "subcategory":"Plumbing",
            "type":"Services"
        }
    ],
    "sg:phone":"+1 215 788 7856",
    "sg:postcode":"19007",
    "sg:province":"PA",
    "sg:tags":[
        "contractor",
        "mechanical"
    ],
    "wof:name":"Szekely, D Mechanical Contract",
    "wof:placetype":"venue"
},
  "geometry": {"coordinates":[-74.856933,40.096627],"type":"Point"}
}