{
  "type": "Feature",
  "properties": {
    "iso:country":"US",
    "sg:address":"1 W Olney Ave",
    "sg:city":"Philadelphia",
    "sg:classifiers":[
        {
            "category":"Shopping",
            "subcategory":"Clothing, Apparel, & Fashions",
            "type":"Retail Goods"
        }
    ],
    "sg:phone":"+1   ",
    "sg:postcode":"19120",
    "sg:province":"PA",
    "sg:tags":[
        "store"
    ],
    "wof:name":"G G Retail 287",
    "wof:placetype":"venue"
},
  "geometry": {"coordinates":[-75.12385999999999,40.035562],"type":"Point"}
}