{
  "type": "Feature",
  "properties": {
    "iso:country":"US",
    "sg:address":"22 Gay St",
    "sg:city":"Phoenixville",
    "sg:classifiers":[
        {
            "category":"Wholesale",
            "subcategory":"Groceries",
            "type":"Manufacturing & Wholesale Goods"
        }
    ],
    "sg:phone":"+1   ",
    "sg:postcode":"19460",
    "sg:province":"PA",
    "sg:tags":[
        "food"
    ],
    "wof:name":"Matts Discount Vitamins",
    "wof:placetype":"venue"
},
  "geometry": {"coordinates":[-75.518354,40.132613],"type":"Point"}
}