{
  "type": "Feature",
  "properties": {
    "addr:full":"357 Marian Ave Tamaqua PA 18252",
    "addr:housenumber":"357",
    "addr:postcode":"18252",
    "addr:street":"Marian Ave",
    "iso:country":"US",
    "sg:address":"357 Marian Ave",
    "sg:city":"Tamaqua",
    "sg:classifiers":[
        {
            "category":"Manufacturing",
            "subcategory":"Chemicals & Compounds",
            "type":"Manufacturing & Wholesale Goods"
        }
    ],
    "sg:phone":"+1 570 467 2981",
    "sg:postcode":"18252",
    "sg:province":"PA",
    "sg:tags":[
        "gas"
    ],
    "wof:name":"Air Products & Chemicals Inc",
    "wof:placetype":"venue"
},
  "geometry": {"coordinates":[-76.032354,40.838087],"type":"Point"}
}