{
  "type": "Feature",
  "properties": {
    "iso:country":"US",
    "sg:address":"45 Haverford Rd",
    "sg:city":"Wynnewood",
    "sg:classifiers":[
        {
            "category":"Organizations",
            "subcategory":"Religious Organization",
            "type":"Services"
        }
    ],
    "sg:phone":"+1 610 896 2400",
    "sg:postcode":"19096",
    "sg:province":"PA",
    "sg:tags":[
        "synagogue"
    ],
    "wof:name":"Aish Hatora-Metro Philadelphia",
    "wof:placetype":"venue"
},
  "geometry": {"coordinates":[-75.270627,39.982053],"type":"Point"}
}