{
  "type": "Feature",
  "properties": {
    "iso:country":"US",
    "sg:address":"600 Saint Francis Cabrini Ave",
    "sg:city":"Scranton",
    "sg:classifiers":[
        {
            "category":"Manufacturing",
            "subcategory":"Textiles",
            "type":"Manufacturing & Wholesale Goods"
        }
    ],
    "sg:phone":"+1 570 346 4661",
    "sg:postcode":"18504",
    "sg:province":"PA",
    "sg:tags":[
        "textiles-manufacturers"
    ],
    "wof:name":"Advanced Auto Interiors",
    "wof:placetype":"venue"
},
  "geometry": {"coordinates":[-75.67441599999999,41.41608],"type":"Point"}
}