{
  "type": "Feature",
  "properties": {
    "iso:country":"US",
    "sg:address":"456 Montgomery Ave",
    "sg:city":"Bridgeville",
    "sg:classifiers":[
        {
            "category":"Retail",
            "subcategory":"Car Wash",
            "type":"Services"
        }
    ],
    "sg:phone":"+1   ",
    "sg:postcode":"15017",
    "sg:province":"PA",
    "sg:tags":[
        "carwash"
    ],
    "wof:name":"Trim Line In Western PA",
    "wof:placetype":"venue"
},
  "geometry": {"coordinates":[-80.09615599999999,40.370996],"type":"Point"}
}