{
  "type": "Feature",
  "properties": {
    "addr:full":"444 Old Latrobe Derry Rd Loyalhanna PA 15661",
    "addr:housenumber":"444",
    "addr:postcode":"15661",
    "addr:street":"Old Latrobe Derry Rd",
    "iso:country":"US",
    "sg:address":"444 Old Latrobe Derry Rd",
    "sg:city":"Loyalhanna",
    "sg:classifiers":[
        {
            "category":"Manufacturing",
            "subcategory":"Rubber & Plastics",
            "type":"Manufacturing & Wholesale Goods"
        }
    ],
    "sg:phone":"+1 724 532 2890",
    "sg:postcode":"15661",
    "sg:province":"PA",
    "wof:name":"Antal Plastics",
    "wof:placetype":"venue"
},
  "geometry": {"coordinates":[-79.348991,40.31994],"type":"Point"}
}