{
  "type": "Feature",
  "properties": {
    "iso:country":"US",
    "sg:address":"2660 W 8th St",
    "sg:city":"Erie",
    "sg:classifiers":[
        {
            "category":"Travel",
            "subcategory":"Travel Agent",
            "type":"Entertainment"
        }
    ],
    "sg:phone":"+1 814 838 7669",
    "sg:postcode":"16505",
    "sg:province":"PA",
    "sg:tags":[
        "agency",
        "bureau"
    ],
    "sg:website":"www.carlsonerie.com",
    "wof:name":"Carlson Wagonlit Travel",
    "wof:placetype":"venue"
},
  "geometry": {"coordinates":[-80.14362800000001,42.10553],"type":"Point"}
}