{
  "type": "Feature",
  "properties": {
    "addr:full":"840 N 7th St Lebanon PA 17046",
    "addr:housenumber":"840",
    "addr:postcode":"17046",
    "addr:street":"N 7Th St",
    "iso:country":"US",
    "sg:address":"840 N 7th St",
    "sg:city":"Lebanon",
    "sg:classifiers":[
        {
            "category":"Government",
            "subcategory":"Office",
            "type":"Public Place"
        }
    ],
    "sg:phone":"+1 717 272 2072",
    "sg:postcode":"17046",
    "sg:province":"PA",
    "sg:tags":[
        "township",
        "government-city",
        "village"
    ],
    "wof:name":"Direct Response Solutions",
    "wof:placetype":"venue"
},
  "geometry": {"coordinates":[-76.423541,40.352922],"type":"Point"}
}