{
  "type": "Feature",
  "properties": {
    "addr:full":"816 Linden Ave East Pittsburgh PA 15112",
    "addr:housenumber":"816",
    "addr:postcode":"15112",
    "addr:street":"Linden Ave East",
    "iso:country":"US",
    "sg:address":"816 Linden Ave",
    "sg:city":"East Pittsburgh",
    "sg:classifiers":[
        {
            "category":"Recreation",
            "type":"Entertainment"
        }
    ],
    "sg:phone":"+1 412 824 0314",
    "sg:postcode":"15112",
    "sg:province":"PA",
    "sg:tags":[
        "karate",
        "judo",
        "instr"
    ],
    "wof:name":"Chontas Tang Soo Do Karate Std",
    "wof:placetype":"venue"
},
  "geometry": {"coordinates":[-79.834541,40.400808],"type":"Point"}
}