{
  "type": "Feature",
  "properties": {
    "addr:full":"43 Circle Dr Delmont PA 15626",
    "addr:housenumber":"43",
    "addr:postcode":"15626",
    "addr:street":"Circle Dr",
    "iso:country":"US",
    "sg:address":"43 Circle Dr",
    "sg:city":"Delmont",
    "sg:classifiers":[
        {
            "category":"Banks & Credit Unions",
            "subcategory":"Bank",
            "type":"Services"
        }
    ],
    "sg:phone":"+1   ",
    "sg:postcode":"15626",
    "sg:province":"PA",
    "sg:tags":[
        "national",
        "commercial"
    ],
    "wof:name":"Mellon",
    "wof:placetype":"venue"
},
  "geometry": {"coordinates":[-79.565843,40.418116],"type":"Point"}
}