{
  "type": "Feature",
  "properties": {
    "addr:full":"6937 Ludlow St Upper Darby PA 19082",
    "addr:housenumber":"6937",
    "addr:postcode":"19082",
    "addr:street":"Ludlow St",
    "iso:country":"US",
    "sg:address":"6937 Ludlow St",
    "sg:city":"Upper Darby",
    "sg:classifiers":[
        {
            "category":"Restaurant",
            "type":"Food & Drink"
        }
    ],
    "sg:phone":"+1 610 352 5855",
    "sg:postcode":"19082",
    "sg:province":"PA",
    "sg:tags":[
        "eating",
        "pizza"
    ],
    "wof:name":"Penn Famous Pizza & Deli",
    "wof:placetype":"venue"
},
  "geometry": {"coordinates":[-75.260597,39.961201],"type":"Point"}
}