{
  "type": "Feature",
  "properties": {
    "iso:country":"US",
    "sg:address":"252 Main Street ",
    "sg:city":"Slippery Rock",
    "sg:classifiers":[
        {
            "category":"Restaurant",
            "type":"Food & Drink"
        }
    ],
    "sg:menulink":"http://www.allmenus.com/pa/slippery-rock/291498-bobs-sub-and-sandwich-shop/menu/",
    "sg:phone":"+1 724 794 6799",
    "sg:postcode":"16057",
    "sg:province":"PA",
    "sg:tags":[
        "american",
        "sandwich"
    ],
    "wof:name":"Bob's Sub and Sandwich Shop",
    "wof:placetype":"venue"
},
  "geometry": {"coordinates":[-80.061403,41.068252],"type":"Point"}
}