{
  "type": "Feature",
  "properties": {
    "iso:country":"US",
    "sg:address":"20630 Route 19 Unit 102",
    "sg:city":"Cranberry Twp",
    "sg:classifiers":[
        {
            "category":"Health Services",
            "subcategory":"Health Practitioner",
            "type":"Services"
        }
    ],
    "sg:phone":"+1 724 779 1277",
    "sg:postcode":"16066",
    "sg:province":"PA",
    "sg:tags":[
        "therapy",
        "physical"
    ],
    "wof:name":"Freedom Rehabilitation Centers",
    "wof:placetype":"venue"
},
  "geometry": {"coordinates":[-80.103874,40.70594],"type":"Point"}
}