{
  "type": "Feature",
  "properties": {
    "addr:full":"113 N Maple Ave Greensburg PA 15601",
    "addr:housenumber":"113",
    "addr:postcode":"15601",
    "addr:street":"N Maple Ave",
    "iso:country":"US",
    "sg:address":"113 N Maple Ave",
    "sg:city":"Greensburg",
    "sg:classifiers":[
        {
            "category":"Building & Trades",
            "subcategory":"Construction",
            "type":"Services"
        }
    ],
    "sg:phone":"+1 724 853 4363",
    "sg:postcode":"15601",
    "sg:province":"PA",
    "sg:tags":[
        "general",
        "contractor"
    ],
    "wof:name":"Champion Design Contractors",
    "wof:placetype":"venue"
},
  "geometry": {"coordinates":[-79.543711,40.304325],"type":"Point"}
}