{
  "type": "Feature",
  "properties": {
    "addr:full":"1801 S 12th St Allentown PA 18103",
    "addr:housenumber":"1801",
    "addr:postcode":"18103",
    "addr:street":"S 12Th St",
    "iso:country":"US",
    "sg:address":"1801 S 12th St",
    "sg:city":"Allentown",
    "sg:classifiers":[
        {
            "category":"Real Estate",
            "subcategory":"Real Estate Services",
            "type":"Services"
        }
    ],
    "sg:phone":"+1 610 797 5585",
    "sg:postcode":"18103",
    "sg:province":"PA",
    "sg:tags":[
        "management",
        "property"
    ],
    "wof:name":"Queen City Properties Lp",
    "wof:placetype":"venue"
},
  "geometry": {"coordinates":[-75.476799,40.580101],"type":"Point"}
}