{
  "type": "Feature",
  "properties": {
    "iso:country":"US",
    "sg:address":"3426 Fissels Church Rd",
    "sg:city":"Glen Rock",
    "sg:classifiers":[
        {
            "category":"Organizations",
            "subcategory":"Religious Organization",
            "type":"Services"
        }
    ],
    "sg:phone":"+1 717 235 2033",
    "sg:postcode":"17327",
    "sg:province":"PA",
    "sg:tags":[
        "church"
    ],
    "wof:name":"New Hope Fissel's United Chr",
    "wof:placetype":"venue"
},
  "geometry": {"coordinates":[-76.737425,39.766896],"type":"Point"}
}