{
  "type": "Feature",
  "properties": {
    "addr:full":"3653 Sheramy Dr Fairview PA 16415",
    "addr:housenumber":"3653",
    "addr:postcode":"16415",
    "addr:street":"Sheramy Dr",
    "iso:country":"US",
    "sg:address":"3653 Sheramy Dr",
    "sg:city":"Fairview",
    "sg:classifiers":[
        {
            "category":"Professional",
            "subcategory":"Management & Consulting",
            "type":"Services"
        }
    ],
    "sg:phone":"+1 814 474 9045",
    "sg:postcode":"16415",
    "sg:province":"PA",
    "sg:tags":[
        "manufacturing",
        "contract"
    ],
    "wof:name":"Nixons' Technical Service",
    "wof:placetype":"venue"
},
  "geometry": {"coordinates":[-80.26310700000001,42.031303],"type":"Point"}
}