{
  "type": "Feature",
  "properties": {
    "iso:country":"US",
    "sg:address":"1568 Carlton Rd",
    "sg:city":"Carlton",
    "sg:classifiers":[
        {
            "category":"Government",
            "subcategory":"Office",
            "type":"Public Place"
        }
    ],
    "sg:phone":"+1 814 425 3409",
    "sg:postcode":"16311",
    "sg:province":"PA",
    "sg:tags":[
        "village"
    ],
    "wof:name":"Township Supervisor",
    "wof:placetype":"venue"
},
  "geometry": {"coordinates":[-80.047718,41.469231],"type":"Point"}
}