{
  "type": "Feature",
  "properties": {
    "iso:country":"US",
    "sg:address":"322 Carsonia Ave",
    "sg:city":"Reading",
    "sg:classifiers":[
        {
            "category":"Retail",
            "subcategory":"Laundry & Dry Cleaning",
            "type":"Services"
        }
    ],
    "sg:phone":"+1 610 370 0784",
    "sg:postcode":"19606",
    "sg:province":"PA",
    "sg:tags":[
        "cleaners",
        "rug",
        "carpet"
    ],
    "wof:name":"Quality Carpet Care",
    "wof:placetype":"venue"
},
  "geometry": {"coordinates":[-75.888204,40.333068],"type":"Point"}
}