{
  "type": "Feature",
  "properties": {
    "addr:full":"197 Albertson Rd Orangeville PA 17859",
    "addr:housenumber":"197",
    "addr:postcode":"17859",
    "addr:street":"Albertson Rd",
    "iso:country":"US",
    "sg:address":"197 Albertson Rd",
    "sg:city":"Orangeville",
    "sg:classifiers":[
        {
            "category":"Utilities",
            "subcategory":"Refuse",
            "type":"Services"
        }
    ],
    "sg:phone":"+1   ",
    "sg:postcode":"17859",
    "sg:province":"PA",
    "sg:tags":[
        "system"
    ],
    "wof:name":"Foughts Disposal Service",
    "wof:placetype":"venue"
},
  "geometry": {"coordinates":[-76.389163,41.109574],"type":"Point"}
}