{
  "type": "Feature",
  "properties": {
    "iso:country":"US",
    "sg:address":"300 E Street Rd",
    "sg:city":"Feasterville Trevose",
    "sg:classifiers":[
        {
            "category":"Autos & Motor Vehicles",
            "subcategory":"Fuel & Gas Station",
            "type":"Retail Goods"
        }
    ],
    "sg:phone":"+1   ",
    "sg:postcode":"19053",
    "sg:province":"PA",
    "sg:tags":[
        "station",
        "gasoline"
    ],
    "wof:name":"Hansbury Sunoco",
    "wof:placetype":"venue"
},
  "geometry": {"coordinates":[-75.011211,40.155876],"type":"Point"}
}