{
  "type": "Feature",
  "properties": {
    "iso:country":"US",
    "sg:address":"404 Sawyers Ln",
    "sg:city":"Newtown",
    "sg:classifiers":[
        {
            "category":"Education",
            "subcategory":"Special Training",
            "type":"Public Place"
        }
    ],
    "sg:phone":"+1 215 504 2677",
    "sg:postcode":"18940",
    "sg:province":"PA",
    "sg:tags":[
        "tutoring"
    ],
    "wof:name":"Educational Excellence Center Inc",
    "wof:placetype":"venue"
},
  "geometry": {"coordinates":[-74.918295,40.285326],"type":"Point"}
}