{
  "type": "Feature",
  "properties": {
    "iso:country":"US",
    "sg:address":"290 State Rte 22",
    "sg:city":"Delmont",
    "sg:classifiers":[
        {
            "category":"Health Services",
            "subcategory":"Health Practitioner",
            "type":"Services"
        }
    ],
    "sg:phone":"+1   ",
    "sg:postcode":"15626",
    "sg:province":"PA",
    "wof:name":"Centers For Rehab Services",
    "wof:placetype":"venue"
},
  "geometry": {"coordinates":[-79.57624300000001,40.398362],"type":"Point"}
}