{
  "type": "Feature",
  "properties": {
    "iso:country":"US",
    "sg:address":"1 Sentry Pkwy",
    "sg:city":"Blue Bell",
    "sg:classifiers":[
        {
            "category":"Professional",
            "subcategory":"Employment Agencies",
            "type":"Services"
        }
    ],
    "sg:phone":"+1 610 834 7774",
    "sg:postcode":"19422",
    "sg:province":"PA",
    "sg:tags":[
        "consultant",
        "search",
        "executive"
    ],
    "wof:name":"Search Concept",
    "wof:placetype":"venue"
},
  "geometry": {"coordinates":[-75.27038,40.130838],"type":"Point"}
}