{
  "type": "Feature",
  "properties": {
    "addr:full":"914 Lehigh Lifestyle Ctr Whitehall PA 18052",
    "addr:housenumber":"914",
    "addr:postcode":"18052",
    "addr:street":"Lehigh Lifestyle Ctr",
    "iso:country":"US",
    "sg:address":"914 Lehigh Lifestyle Ctr",
    "sg:city":"Whitehall",
    "sg:classifiers":[
        {
            "category":"Home & Garden",
            "subcategory":"Furniture",
            "type":"Retail Goods"
        }
    ],
    "sg:phone":"+1 610 264 0381",
    "sg:postcode":"18052",
    "sg:province":"PA",
    "sg:tags":[
        "store"
    ],
    "sg:website":"www.potterybarn.com",
    "wof:name":"Pottery Barn",
    "wof:placetype":"venue"
},
  "geometry": {"coordinates":[-75.48113499999999,40.629874],"type":"Point"}
}