{
  "type": "Feature",
  "properties": {
    "addr:full":"3008 Settlers Ct Murrysville PA 15668",
    "addr:housenumber":"3008",
    "addr:postcode":"15668",
    "addr:street":"Settlers Ct",
    "iso:country":"US",
    "sg:address":"3008 Settlers Ct",
    "sg:city":"Murrysville",
    "sg:classifiers":[
        {
            "category":"Building & Trades",
            "subcategory":"Construction",
            "type":"Services"
        }
    ],
    "sg:phone":"+1   ",
    "sg:postcode":"15668",
    "sg:province":"PA",
    "sg:tags":[
        "heavy"
    ],
    "wof:name":"Ashland Inc",
    "wof:placetype":"venue"
},
  "geometry": {"coordinates":[-79.702358,40.478824],"type":"Point"}
}