{
  "type": "Feature",
  "properties": {
    "addr:full":"42 S Main St Apt A Coopersburg PA 18036",
    "addr:housenumber":"42",
    "addr:postcode":"18036",
    "addr:street":"S Main St Apt A Coopersburg",
    "iso:country":"US",
    "sg:address":"42 S Main St Apt A",
    "sg:city":"Coopersburg",
    "sg:classifiers":[
        {
            "category":"Personal",
            "subcategory":"Beauty Salon",
            "type":"Services"
        }
    ],
    "sg:phone":"+1 610 282 2142",
    "sg:postcode":"18036",
    "sg:province":"PA",
    "wof:name":"Hair Court",
    "wof:placetype":"venue"
},
  "geometry": {"coordinates":[-75.391378,40.510644],"type":"Point"}
}