{
  "type": "Feature",
  "properties": {
    "iso:country":"US",
    "sg:address":"1502 Plymouth Meeting Mall",
    "sg:city":"Plymouth Meeting",
    "sg:classifiers":[
        {
            "category":"Shopping",
            "type":"Retail Goods"
        }
    ],
    "sg:phone":"+1   ",
    "sg:postcode":"19462",
    "sg:province":"PA",
    "sg:tags":[
        "sunglasses",
        "accessory"
    ],
    "wof:name":"Sunglass Hut International",
    "wof:placetype":"venue"
},
  "geometry": {"coordinates":[-75.284187,40.117306],"type":"Point"}
}