{
  "type": "Feature",
  "properties": {
    "iso:country":"US",
    "sg:address":"27 Bachman Ln",
    "sg:city":"Fredericksburg",
    "sg:classifiers":[
        {
            "category":"Farming",
            "subcategory":"Farm & Veterinary Services",
            "type":"Manufacturing & Wholesale Goods"
        },
        {
            "category":"Farming",
            "subcategory":"Farm",
            "type":"Manufacturing & Wholesale Goods"
        }
    ],
    "sg:phone":"+1 717 933 9211",
    "sg:postcode":"17026",
    "sg:province":"PA",
    "sg:tags":[
        "breeder",
        "livestock"
    ],
    "wof:name":"Ribeye Ranch",
    "wof:placetype":"venue"
},
  "geometry": {"coordinates":[-76.376813,40.453315],"type":"Point"}
}