{
  "type": "Feature",
  "properties": {
    "addr:full":"150 Municipal Rd Berwick PA 18612",
    "addr:housenumber":"150",
    "addr:postcode":"18612",
    "addr:street":"Municipal Rd",
    "iso:country":"US",
    "sg:address":"150 Municipal Rd",
    "sg:city":"Berwick",
    "sg:classifiers":[
        {
            "category":"Government",
            "subcategory":"Office",
            "type":"Public Place"
        }
    ],
    "sg:phone":"+1 570 752 8262",
    "sg:postcode":"18612",
    "sg:province":"PA",
    "sg:tags":[
        "village"
    ],
    "wof:name":"Briar Creek Twp Office",
    "wof:placetype":"venue"
},
  "geometry": {"coordinates":[-75.891053,41.383778],"type":"Point"}
}