{
  "type": "Feature",
  "properties": {
    "iso:country":"US",
    "sg:address":"320 Main St",
    "sg:city":"Johnstown",
    "sg:classifiers":[
        {
            "category":"Health Services",
            "subcategory":"Doctor",
            "type":"Services"
        }
    ],
    "sg:phone":"+1 814 533 0102",
    "sg:postcode":"15901",
    "sg:province":"PA",
    "sg:tags":[
        "physician",
        "surgeon"
    ],
    "wof:name":"UPMC Regional Radiology",
    "wof:placetype":"venue"
},
  "geometry": {"coordinates":[-78.92035199999999,40.3261],"type":"Point"}
}