{
  "type": "Feature",
  "properties": {
    "addr:full":"121 Rock N Roll Ln Sarver PA 16055",
    "addr:housenumber":"121",
    "addr:postcode":"16055",
    "addr:street":"Rock N Roll Ln",
    "iso:country":"US",
    "sg:address":"121 Rock N Roll Ln",
    "sg:city":"Sarver",
    "sg:classifiers":[
        {
            "category":"Recreation",
            "type":"Entertainment"
        }
    ],
    "sg:phone":"+1 724 353 2821",
    "sg:postcode":"16055",
    "sg:province":"PA",
    "sg:tags":[
        "martial",
        "arts",
        "instruction"
    ],
    "wof:name":"Makowski's Ata Martial Arts",
    "wof:placetype":"venue"
},
  "geometry": {"coordinates":[-79.778066,40.713074],"type":"Point"}
}