{
  "type": "Feature",
  "properties": {
    "addr:full":"17 N Hill Ter Mansfield PA 16933",
    "addr:housenumber":"17",
    "addr:postcode":"16933",
    "addr:street":"N Hill Ter",
    "iso:country":"US",
    "sg:address":"17 N Hill Ter",
    "sg:city":"Mansfield",
    "sg:classifiers":[
        {
            "category":"Organizations",
            "subcategory":"Religious Organization",
            "type":"Services"
        }
    ],
    "sg:phone":"+1   ",
    "sg:postcode":"16933",
    "sg:province":"PA",
    "wof:name":"United Methodist Church",
    "wof:placetype":"venue"
},
  "geometry": {"coordinates":[-77.08031699999999,41.814394],"type":"Point"}
}