{
  "type": "Feature",
  "properties": {
    "iso:country":"US",
    "sg:address":"85 S 8th St",
    "sg:city":"Philadelphia",
    "sg:classifiers":[
        {
            "category":"Shopping",
            "subcategory":"Jewelry",
            "type":"Retail Goods"
        }
    ],
    "sg:phone":"+1 215 922 1699",
    "sg:postcode":"19106",
    "sg:province":"PA",
    "sg:tags":[
        "jeweler"
    ],
    "wof:name":"R & M Jewelry",
    "wof:placetype":"venue"
},
  "geometry": {"coordinates":[-75.15376500000001,39.950062],"type":"Point"}
}