{
  "type": "Feature",
  "properties": {
    "iso:country":"US",
    "sg:address":"301 W Susquehanna St",
    "sg:city":"Allentown",
    "sg:classifiers":[
        {
            "category":"Restaurant",
            "type":"Food & Drink"
        }
    ],
    "sg:phone":"+1 610 791 3332",
    "sg:postcode":"18103",
    "sg:province":"PA",
    "sg:tags":[
        "pizza"
    ],
    "wof:name":"Big Woody's Pizza & Beer Inc",
    "wof:placetype":"venue"
},
  "geometry": {"coordinates":[-75.45700100000001,40.590199],"type":"Point"}
}