{
  "type": "Feature",
  "properties": {
    "iso:country":"US",
    "sg:address":"214 W Manheim St",
    "sg:city":"Philadelphia",
    "sg:classifiers":[
        {
            "category":"Food & Beverages",
            "subcategory":"Groceries & Convenience Stores",
            "type":"Retail Goods"
        }
    ],
    "sg:phone":"+1 215 438 3570",
    "sg:postcode":"19144",
    "sg:province":"PA",
    "wof:name":"Rosario Food Market",
    "wof:placetype":"venue"
},
  "geometry": {"coordinates":[-75.169938,40.025386],"type":"Point"}
}