{
  "type": "Feature",
  "properties": {
    "addr:full":"1660 Greengarden Rd Erie PA 16502",
    "addr:housenumber":"1660",
    "addr:postcode":"16502",
    "addr:street":"Greengarden Rd",
    "iso:country":"US",
    "sg:address":"1660 Greengarden Rd",
    "sg:city":"Erie",
    "sg:classifiers":[
        {
            "category":"Professional",
            "type":"Services"
        }
    ],
    "sg:phone":"+1 814 871 5900",
    "sg:postcode":"16502",
    "sg:province":"PA",
    "sg:tags":[
        "establishment"
    ],
    "sg:website":"www.blair.com",
    "wof:name":"Blair Corp",
    "wof:placetype":"venue"
},
  "geometry": {"coordinates":[-80.112758,42.10553],"type":"Point"}
}