{
  "type": "Feature",
  "properties": {
    "iso:country":"US",
    "sg:address":"18 Battle Ave",
    "sg:city":"Carbondale",
    "sg:classifiers":[
        {
            "category":"Retail",
            "subcategory":"Repair Shop",
            "type":"Services"
        }
    ],
    "sg:phone":"+1   ",
    "sg:postcode":"18407",
    "sg:province":"PA",
    "sg:tags":[
        "electrical",
        "contractor"
    ],
    "wof:name":"Repair World",
    "wof:placetype":"venue"
},
  "geometry": {"coordinates":[-75.51088900000001,41.564979],"type":"Point"}
}