{
  "type": "Feature",
  "properties": {
    "iso:country":"US",
    "sg:address":"74 Loggers Mill Rd",
    "sg:city":"Horsham",
    "sg:classifiers":[
        {
            "category":"Health Services",
            "subcategory":"Health Practitioner",
            "type":"Services"
        },
        {
            "category":"Communications",
            "type":"Services"
        }
    ],
    "sg:phone":"+1 215 956 9905",
    "sg:postcode":"19044",
    "sg:province":"PA",
    "sg:tags":[
        "pathologist",
        "speech-language",
        "myofunctional",
        "therapy"
    ],
    "wof:name":"Auditory Verbal Concepts Inc",
    "wof:placetype":"venue"
},
  "geometry": {"coordinates":[-75.148505,40.184395],"type":"Point"}
}