{
  "type": "Feature",
  "properties": {
    "addr:full":"99 Bridge St Phoenixville PA 19460",
    "addr:housenumber":"99",
    "addr:postcode":"19460",
    "addr:street":"Bridge St",
    "iso:country":"US",
    "sg:address":"99 Bridge St",
    "sg:city":"Phoenixville",
    "sg:classifiers":[
        {
            "category":"Real Estate",
            "subcategory":"Developer",
            "type":"Services"
        },
        {
            "category":"Building & Trades",
            "subcategory":"Construction",
            "type":"Services"
        }
    ],
    "sg:phone":"+1 610 917 8900",
    "sg:postcode":"19460",
    "sg:province":"PA",
    "sg:tags":[
        "management"
    ],
    "sg:website":"http://www.deltaorg.com",
    "wof:name":"The Delta Organization Inc",
    "wof:placetype":"venue"
},
  "geometry": {"coordinates":[-75.512299,40.134411],"type":"Point"}
}