{
  "type": "Feature",
  "properties": {
    "addr:full":"361 E Lancaster Ave Downingtown PA 19335",
    "addr:housenumber":"361",
    "addr:postcode":"19335",
    "addr:street":"E Lancaster Ave",
    "iso:country":"US",
    "sg:address":"361 E Lancaster Ave",
    "sg:city":"Downingtown",
    "sg:classifiers":[
        {
            "category":"Health Services",
            "subcategory":"Health Practitioner",
            "type":"Services"
        }
    ],
    "sg:phone":"+1 610 873 8202",
    "sg:postcode":"19335",
    "sg:province":"PA",
    "sg:tags":[
        "nurse",
        "registry"
    ],
    "wof:name":"Bayada Nurses",
    "wof:placetype":"venue"
},
  "geometry": {"coordinates":[-75.69882800000001,40.008327],"type":"Point"}
}