{
  "type": "Feature",
  "properties": {
    "iso:country":"US",
    "sg:address":"2101 Creek Rd",
    "sg:city":"Glenmoore",
    "sg:classifiers":[
        {
            "category":"Manufacturing",
            "subcategory":"Tools & Machinery",
            "type":"Manufacturing & Wholesale Goods"
        }
    ],
    "sg:phone":"+1 610 942 2888",
    "sg:postcode":"19343",
    "sg:province":"PA",
    "sg:tags":[
        "industrial",
        "instr"
    ],
    "sg:website":"www.foxcroft.com",
    "wof:name":"Foxcroft Equipment & Svc Co",
    "wof:placetype":"venue"
},
  "geometry": {"coordinates":[-75.77538699999999,40.092071],"type":"Point"}
}