{
  "type": "Feature",
  "properties": {
    "addr:full":"421 S Carlisle St Allentown PA 18103",
    "addr:housenumber":"421",
    "addr:postcode":"18103",
    "addr:street":"S Carlisle St",
    "iso:country":"US",
    "sg:address":"421 S Carlisle St",
    "sg:city":"Allentown",
    "sg:classifiers":[
        {
            "category":"Manufacturing",
            "subcategory":"Tools & Machinery",
            "type":"Manufacturing & Wholesale Goods"
        }
    ],
    "sg:phone":"+1 610 820 6225",
    "sg:postcode":"18103",
    "sg:province":"PA",
    "sg:tags":[
        "mold"
    ],
    "wof:name":"GHT Inc",
    "wof:placetype":"venue"
},
  "geometry": {"coordinates":[-75.44511199999999,40.605486],"type":"Point"}
}