{
  "type": "Feature",
  "properties": {
    "iso:country":"US",
    "sg:address":"26 Jacqueline Dr",
    "sg:city":"Paoli",
    "sg:classifiers":[
        {
            "category":"Building & Trades",
            "subcategory":"Electrical",
            "type":"Services"
        }
    ],
    "sg:phone":"+1 610 296 8741",
    "sg:postcode":"19301",
    "sg:province":"PA",
    "sg:tags":[
        "electrical",
        "electric",
        "contractor"
    ],
    "wof:name":"Paoli Power & Lighting Inc",
    "wof:placetype":"venue"
},
  "geometry": {"coordinates":[-75.49660900000001,40.049102],"type":"Point"}
}