{
  "type": "Feature",
  "properties": {
    "iso:country":"US",
    "sg:address":"546 Richlandtown Pike",
    "sg:city":"Richlandtown",
    "sg:classifiers":[
        {
            "category":"Professional",
            "type":"Services"
        },
        {
            "category":"Restaurant",
            "type":"Food & Drink"
        }
    ],
    "sg:phone":"+1 215 804 4769",
    "sg:postcode":"18955",
    "sg:province":"PA",
    "sg:tags":[
        "pizza",
        "caterer"
    ],
    "wof:name":"Alcamo Restaurant & Brick Oven Pizza",
    "wof:placetype":"venue"
},
  "geometry": {"coordinates":[-75.323292,40.464141],"type":"Point"}
}