{
  "type": "Feature",
  "properties": {
    "iso:country":"US",
    "sg:address":"1332 Kennedy Blvd",
    "sg:city":"Aliquippa",
    "sg:classifiers":[
        {
            "category":"Wholesale",
            "subcategory":"Meat",
            "type":"Manufacturing & Wholesale Goods"
        },
        {
            "category":"Food & Beverages",
            "subcategory":"Meat & Fish",
            "type":"Retail Goods"
        }
    ],
    "sg:phone":"+1 724 375 2450",
    "sg:postcode":"15001",
    "sg:province":"PA",
    "sg:tags":[
        "sausage",
        "prod",
        "prepared"
    ],
    "wof:name":"Cesina's Sausage Co",
    "wof:placetype":"venue"
},
  "geometry": {"coordinates":[-80.260643,40.614163],"type":"Point"}
}