{
  "type": "Feature",
  "properties": {
    "addr:full":"6500 Beaver Dam Rd Levittown PA 19057",
    "addr:housenumber":"6500",
    "addr:postcode":"19057",
    "addr:street":"Beaver Dam Rd Levittown",
    "iso:country":"US",
    "sg:address":"6500 Beaver Dam Rd",
    "sg:city":"Levittown",
    "sg:classifiers":[
        {
            "category":"Building & Trades",
            "subcategory":"Electrical",
            "type":"Services"
        }
    ],
    "sg:phone":"+1 215 949 9758",
    "sg:postcode":"19057",
    "sg:province":"PA",
    "sg:tags":[
        "electric",
        "contractor"
    ],
    "wof:name":"MJK Electrical Corp",
    "wof:placetype":"venue"
},
  "geometry": {"coordinates":[-74.83333399999999,40.127401],"type":"Point"}
}