{
  "type": "Feature",
  "properties": {
    "iso:country":"US",
    "sg:address":"119 Hidden Valley Rd",
    "sg:city":"Canonsburg",
    "sg:classifiers":[
        {
            "category":"Social Services",
            "subcategory":"Child Care",
            "type":"Services"
        },
        {
            "category":"Education",
            "subcategory":"Preschool",
            "type":"Public Place"
        },
        {
            "category":"Education",
            "subcategory":"School",
            "type":"Public Place"
        }
    ],
    "sg:phone":"+1 724 941 5569",
    "sg:postcode":"15317",
    "sg:province":"PA",
    "sg:tags":[
        "elementary",
        "day"
    ],
    "wof:name":"Magic Years Child Care & Learning Centers Inc",
    "wof:placetype":"venue"
},
  "geometry": {"coordinates":[-80.118202,40.288601],"type":"Point"}
}