{
  "type": "Feature",
  "properties": {
    "iso:country":"US",
    "sg:address":"10 Hendricks Rd",
    "sg:city":"Perkiomenville",
    "sg:classifiers":[
        {
            "category":"Retail",
            "subcategory":"Auto Repair",
            "type":"Services"
        }
    ],
    "sg:phone":"+1 610 287 8050",
    "sg:postcode":"18074",
    "sg:province":"PA",
    "sg:tags":[
        "body"
    ],
    "wof:name":"George A Greeby Jr Auto Repair",
    "wof:placetype":"venue"
},
  "geometry": {"coordinates":[-75.479455,40.296309],"type":"Point"}
}