{
  "type": "Feature",
  "properties": {
    "iso:country":"US",
    "sg:address":"368 Hopper Rd",
    "sg:city":"Transfer",
    "sg:classifiers":[
        {
            "category":"Professional",
            "subcategory":"Accounting & Tax Preparation",
            "type":"Services"
        }
    ],
    "sg:phone":"+1   ",
    "sg:postcode":"16154",
    "sg:province":"PA",
    "sg:tags":[
        "billings",
        "medical"
    ],
    "wof:name":"Overlook Billing Services LLC",
    "wof:placetype":"venue"
},
  "geometry": {"coordinates":[-80.37629200000001,41.298935],"type":"Point"}
}