{
  "type": "Feature",
  "properties": {
    "iso:country":"US",
    "sg:address":"1064 Beckford St",
    "sg:city":"New Castle",
    "sg:classifiers":[
        {
            "category":"Real Estate",
            "subcategory":"Real Estate Agent",
            "type":"Services"
        }
    ],
    "sg:phone":"+1   ",
    "sg:postcode":"16101",
    "sg:province":"PA",
    "sg:tags":[
        "building",
        "operator",
        "commercial"
    ],
    "wof:name":"M A M Realty Company",
    "wof:placetype":"venue"
},
  "geometry": {"coordinates":[-80.32271,40.988583],"type":"Point"}
}