{
  "type": "Feature",
  "properties": {
    "iso:country":"US",
    "sg:address":"1000 N Chester Rd",
    "sg:city":"West Chester",
    "sg:classifiers":[
        {
            "category":"Education",
            "subcategory":"School",
            "type":"Public Place"
        }
    ],
    "sg:phone":"+1   ",
    "sg:postcode":"19380",
    "sg:province":"PA",
    "sg:tags":[
        "elementary",
        "secondary"
    ],
    "wof:name":"Israel Kesher Congretation Kin",
    "wof:placetype":"venue"
},
  "geometry": {"coordinates":[-75.54605599999999,40.004628],"type":"Point"}
}