{
  "type": "Feature",
  "properties": {
    "iso:country":"US",
    "sg:address":"1862 W Maple Ave",
    "sg:city":"Langhorne",
    "sg:classifiers":[
        {
            "category":"Cafe",
            "type":"Food & Drink"
        },
        {
            "category":"Restaurant",
            "type":"Food & Drink"
        }
    ],
    "sg:menulink":"http://www.allmenus.com/pa/woodbourne/229689-chinatown-cafe/menu/",
    "sg:phone":"+1 215 757 3353",
    "sg:postcode":"19047",
    "sg:province":"PA",
    "sg:tags":[
        "asian",
        "chinese"
    ],
    "wof:name":"Chinatown Cafe",
    "wof:placetype":"venue"
},
  "geometry": {"coordinates":[-74.95388800000001,40.174297],"type":"Point"}
}