{
  "type": "Feature",
  "properties": {
    "iso:country":"US",
    "sg:address":"3042 Butler Pike",
    "sg:city":"Conshohocken",
    "sg:classifiers":[
        {
            "category":"Retail",
            "subcategory":"Auto Repair",
            "type":"Services"
        }
    ],
    "sg:phone":"+1 610 828 2136",
    "sg:postcode":"19428",
    "sg:province":"PA",
    "sg:tags":[
        "repairing",
        "automobile",
        "general"
    ],
    "wof:name":"Foster's General Auto Repair",
    "wof:placetype":"venue"
},
  "geometry": {"coordinates":[-75.28072899999999,40.100548],"type":"Point"}
}