{
  "type": "Feature",
  "properties": {
    "addr:full":"316 Weaver Rd Strasburg PA 17579",
    "addr:housenumber":"316",
    "addr:postcode":"17579",
    "addr:street":"Weaver Rd",
    "iso:country":"US",
    "sg:address":"316 Weaver Rd",
    "sg:city":"Strasburg",
    "sg:classifiers":[
        {
            "category":"Recreation",
            "type":"Entertainment"
        }
    ],
    "sg:phone":"+1 717 687 6921",
    "sg:postcode":"17579",
    "sg:province":"PA",
    "sg:tags":[
        "club",
        "membership"
    ],
    "wof:name":"Strasburg Sportsmen",
    "wof:placetype":"venue"
},
  "geometry": {"coordinates":[-76.15924,39.948598],"type":"Point"}
}