{
  "type": "Feature",
  "properties": {
    "addr:full":"3600 William Penn Hwy Monroeville PA 15146",
    "addr:housenumber":"3600",
    "addr:postcode":"15146",
    "addr:street":"William Penn Hwy",
    "iso:country":"US",
    "sg:address":"3600 William Penn Hwy",
    "sg:city":"Monroeville",
    "sg:classifiers":[
        {
            "category":"Bakery",
            "type":"Food & Drink"
        }
    ],
    "sg:menulink":"http://www.allmenus.com/pa/monroeville/28670-panera-bread/menu/",
    "sg:phone":"+1 412 816 5820",
    "sg:postcode":"15146",
    "sg:province":"PA",
    "sg:tags":[
        "american",
        "sandwich",
        "pastry"
    ],
    "wof:name":"Panera Bread",
    "wof:placetype":"venue"
},
  "geometry": {"coordinates":[-79.801602,40.432118],"type":"Point"}
}