{
  "type": "Feature",
  "properties": {
    "addr:full":"- Route 611 Bartonsville PA 18321",
    "addr:postcode":"18321",
    "addr:street":"Route 611",
    "iso:country":"US",
    "sg:address":"- Route 611",
    "sg:city":"Bartonsville",
    "sg:classifiers":[
        {
            "category":"Building & Trades",
            "subcategory":"Construction",
            "type":"Services"
        },
        {
            "category":"Home & Garden",
            "subcategory":"Carpets & Floor Coverings",
            "type":"Retail Goods"
        }
    ],
    "sg:phone":"+1 800 394 3064",
    "sg:postcode":"18321",
    "sg:province":"PA",
    "sg:tags":[
        "flooring",
        "material",
        "rug",
        "contractor",
        "tile-contractors"
    ],
    "sg:website":"http://www.filitrac.com/Click.aspx?tid=BDEDC5D5EF8BAE3541B5938870DA3DDECE60F60FEE115906&FiliAff=15016&sid=99202&utm_source=YellowPages&utm_medium=ppc&utm_campaign=national&utm_term=18321",
    "wof:name":"Giant Carpet One Floor & Home",
    "wof:placetype":"venue"
},
  "geometry": {"coordinates":[-75.29847700000001,41.024263],"type":"Point"}
}