{
  "type": "Feature",
  "properties": {
    "addr:full":"121 Penn Ave Scranton PA 18503",
    "addr:housenumber":"121",
    "addr:postcode":"18503",
    "addr:street":"Penn Ave",
    "iso:country":"US",
    "sg:address":"121 Penn Ave",
    "sg:city":"Scranton",
    "sg:classifiers":[
        {
            "category":"Real Estate",
            "subcategory":"Real Estate Operator",
            "type":"Services"
        }
    ],
    "sg:phone":"+1 570 348 1007",
    "sg:postcode":"18503",
    "sg:province":"PA",
    "sg:tags":[
        "building",
        "nonresidential"
    ],
    "wof:name":"Legion Hall",
    "wof:placetype":"venue"
},
  "geometry": {"coordinates":[-75.666405,41.409578],"type":"Point"}
}