{
  "type": "Feature",
  "properties": {
    "iso:country":"US",
    "sg:address":"22791 Shreve Ridge Rd",
    "sg:city":"Union City",
    "sg:classifiers":[
        {
            "category":"Professional",
            "subcategory":"Business Services",
            "type":"Services"
        }
    ],
    "sg:phone":"+1   ",
    "sg:postcode":"16438",
    "sg:province":"PA",
    "wof:name":"Bloomfield Twnshp Sewag",
    "wof:placetype":"venue"
},
  "geometry": {"coordinates":[-79.838274,41.79367],"type":"Point"}
}