{
  "type": "Feature",
  "properties": {
    "iso:country":"US",
    "sg:address":"121 N 57th St",
    "sg:city":"Philadelphia",
    "sg:classifiers":[
        {
            "category":"Professional",
            "subcategory":"Detective & Security Services",
            "type":"Services"
        }
    ],
    "sg:phone":"+1 215 747 3634",
    "sg:postcode":"19139",
    "sg:province":"PA",
    "sg:tags":[
        "information",
        "bureau"
    ],
    "wof:name":"Ave, Inc.",
    "wof:placetype":"venue"
},
  "geometry": {"coordinates":[-75.234409,39.963369],"type":"Point"}
}