{
  "type": "Feature",
  "properties": {
    "iso:country":"US",
    "sg:address":"1125 E Vernon Rd",
    "sg:city":"Philadelphia",
    "sg:classifiers":[
        {
            "category":"Building & Trades",
            "subcategory":"Construction",
            "type":"Services"
        }
    ],
    "sg:phone":"+1   ",
    "sg:postcode":"19150",
    "sg:province":"PA",
    "sg:tags":[
        "house"
    ],
    "wof:name":"Davis General Contractor",
    "wof:placetype":"venue"
},
  "geometry": {"coordinates":[-75.171935,40.068629],"type":"Point"}
}