{
  "type": "Feature",
  "properties": {
    "iso:country":"US",
    "sg:address":"354 E Main St",
    "sg:city":"Somerset",
    "sg:classifiers":[
        {
            "category":"Autos & Motor Vehicles",
            "subcategory":"Motorcycle Sales",
            "type":"Retail Goods"
        }
    ],
    "sg:phone":"+1 814 445 9825",
    "sg:postcode":"15501",
    "sg:province":"PA",
    "sg:tags":[
        "scooter"
    ],
    "wof:name":"M T Chrome & Leather",
    "wof:placetype":"venue"
},
  "geometry": {"coordinates":[-79.07351199999999,40.008005],"type":"Point"}
}