{
  "type": "Feature",
  "properties": {
    "addr:full":"635 Rosewood Ave Feastervl Trvs PA 19053",
    "addr:housenumber":"635",
    "addr:postcode":"19053",
    "addr:street":"Rosewood Ave",
    "iso:country":"US",
    "sg:address":"635 Rosewood Ave",
    "sg:city":"Feastervl Trvs",
    "sg:classifiers":[
        {
            "category":"Home & Garden",
            "subcategory":"Carpets & Floor Coverings",
            "type":"Retail Goods"
        }
    ],
    "sg:phone":"+1 215 357 6270",
    "sg:postcode":"19053",
    "sg:province":"PA",
    "sg:tags":[
        "dealer",
        "rug"
    ],
    "wof:name":"Collins Carpets & Cleaning",
    "wof:placetype":"venue"
},
  "geometry": {"coordinates":[-74.97784799999999,40.149954],"type":"Point"}
}