{
  "type": "Feature",
  "properties": {
    "addr:full":"600 Penn St Linesville PA 16424",
    "addr:housenumber":"600",
    "addr:postcode":"16424",
    "addr:street":"Penn St",
    "iso:country":"US",
    "sg:address":"600 Penn St",
    "sg:city":"Linesville",
    "sg:classifiers":[
        {
            "category":"Manufacturing",
            "subcategory":"Rubber & Plastics",
            "type":"Manufacturing & Wholesale Goods"
        }
    ],
    "sg:phone":"+1 814 683 2161",
    "sg:postcode":"16424",
    "sg:province":"PA",
    "sg:tags":[
        "plastics-molders",
        "pressure",
        "plastics-vacuum",
        "forming-manufacturers"
    ],
    "wof:name":"R-G-T Plastics Company (Inc)",
    "wof:placetype":"venue"
},
  "geometry": {"coordinates":[-80.431031,41.660721],"type":"Point"}
}