{
  "type": "Feature",
  "properties": {
    "addr:full":"28 Reiber Rd West Middlesex PA 16159",
    "addr:housenumber":"28",
    "addr:postcode":"16159",
    "addr:street":"Reiber Rd",
    "iso:country":"US",
    "sg:address":"28 Reiber Rd",
    "sg:city":"West Middlesex",
    "sg:classifiers":[
        {
            "category":"Retail",
            "subcategory":"Auto Repair",
            "type":"Services"
        }
    ],
    "sg:phone":"+1 724 346 0719",
    "sg:postcode":"16159",
    "sg:province":"PA",
    "sg:tags":[
        "repairing",
        "automobile",
        "general"
    ],
    "wof:name":"J & B's Garage",
    "wof:placetype":"venue"
},
  "geometry": {"coordinates":[-80.377758,41.198999],"type":"Point"}
}