{
  "type": "Feature",
  "properties": {
    "iso:country":"US",
    "sg:address":"322 E Lancaster Ave",
    "sg:city":"Wynnewood",
    "sg:classifiers":[
        {
            "category":"Real Estate",
            "subcategory":"Real Estate Agent",
            "type":"Services"
        }
    ],
    "sg:phone":"+1   ",
    "sg:postcode":"19096",
    "sg:province":"PA",
    "wof:name":"Connie Williams",
    "wof:placetype":"venue"
},
  "geometry": {"coordinates":[-75.26374,39.992205],"type":"Point"}
}