{
  "type": "Feature",
  "properties": {
    "iso:country":"US",
    "sg:address":"324 Limerick Center Rd",
    "sg:city":"Pottstown",
    "sg:classifiers":[
        {
            "category":"Building & Trades",
            "subcategory":"Construction",
            "type":"Services"
        }
    ],
    "sg:phone":"+1   ",
    "sg:postcode":"19464",
    "sg:province":"PA",
    "sg:tags":[
        "general",
        "industrial",
        "commercial",
        "contractor"
    ],
    "wof:name":"Near Contracting Company",
    "wof:placetype":"venue"
},
  "geometry": {"coordinates":[-75.55820199999999,40.226511],"type":"Point"}
}