{
  "type": "Feature",
  "properties": {
    "iso:country":"US",
    "sg:address":"12 Kauffman Ln",
    "sg:city":"Belleville",
    "sg:classifiers":[
        {
            "category":"Farming",
            "subcategory":"Dairy Farm",
            "type":"Manufacturing & Wholesale Goods"
        },
        {
            "category":"Farming",
            "subcategory":"Farm",
            "type":"Manufacturing & Wholesale Goods"
        }
    ],
    "sg:phone":"+1 717 667 2345",
    "sg:postcode":"17004",
    "sg:province":"PA",
    "wof:name":"Kauffman Dairy Farm",
    "wof:placetype":"venue"
},
  "geometry": {"coordinates":[-77.667218,40.63471],"type":"Point"}
}