{
  "type": "Feature",
  "properties": {
    "iso:country":"US",
    "sg:address":"50 Pocono Rd",
    "sg:city":"Mt Pocono",
    "sg:classifiers":[
        {
            "category":"Retail",
            "subcategory":"Repair Shop",
            "type":"Services"
        }
    ],
    "sg:phone":"+1 570 839 5881",
    "sg:postcode":"18344",
    "sg:province":"PA",
    "sg:tags":[
        "television",
        "radio"
    ],
    "wof:name":"Active Electronics Repair Co",
    "wof:placetype":"venue"
},
  "geometry": {"coordinates":[-75.361694,41.120061],"type":"Point"}
}