{
  "type": "Feature",
  "properties": {
    "addr:full":"72 E High St Waynesburg PA 15370",
    "addr:housenumber":"72",
    "addr:postcode":"15370",
    "addr:street":"E High St",
    "iso:country":"US",
    "sg:address":"72 E High St",
    "sg:city":"Waynesburg",
    "sg:classifiers":[
        {
            "category":"Social Services",
            "type":"Services"
        }
    ],
    "sg:phone":"+1 724 627 6410",
    "sg:postcode":"15370",
    "sg:province":"PA",
    "sg:tags":[
        "organization",
        "welfare"
    ],
    "wof:name":"Catholic Charities Of Diocese",
    "wof:placetype":"venue"
},
  "geometry": {"coordinates":[-80.185931,39.896367],"type":"Point"}
}