{
  "type": "Feature",
  "properties": {
    "iso:country":"US",
    "sg:address":"1201 W Branch Rd",
    "sg:city":"State College",
    "sg:classifiers":[
        {
            "category":"Utilities",
            "subcategory":"Water",
            "type":"Services"
        }
    ],
    "sg:phone":"+1 814 238 6766",
    "sg:postcode":"16801",
    "sg:province":"PA",
    "sg:tags":[
        "company",
        "sewage"
    ],
    "sg:website":"www.scwa.org",
    "wof:name":"State College Water Authority",
    "wof:placetype":"venue"
},
  "geometry": {"coordinates":[-77.833078,40.772829],"type":"Point"}
}