{
  "type": "Feature",
  "properties": {
    "addr:full":"43 N 7th St Columbia PA 17512",
    "addr:housenumber":"43",
    "addr:postcode":"17512",
    "addr:street":"N 7Th St",
    "iso:country":"US",
    "sg:address":"43 N 7th St",
    "sg:city":"Columbia",
    "sg:classifiers":[
        {
            "category":"Organizations",
            "subcategory":"Religious Organization",
            "type":"Services"
        }
    ],
    "sg:phone":"+1 717 684 8834",
    "sg:postcode":"17512",
    "sg:province":"PA",
    "sg:tags":[
        "god",
        "churches-pentecostal",
        "church"
    ],
    "wof:name":"Columbia First Church Of God",
    "wof:placetype":"venue"
},
  "geometry": {"coordinates":[-76.497089,40.036539],"type":"Point"}
}