{
  "type": "Feature",
  "properties": {
    "iso:country":"US",
    "sg:address":"4845 N 13th St",
    "sg:city":"Philadelphia",
    "sg:classifiers":[
        {
            "category":"Organizations",
            "subcategory":"Religious Organization",
            "type":"Services"
        }
    ],
    "sg:phone":"+1 215 455 8060",
    "sg:postcode":"19141",
    "sg:province":"PA",
    "sg:tags":[
        "church"
    ],
    "wof:name":"New Way Missionary Baptist Chr",
    "wof:placetype":"venue"
},
  "geometry": {"coordinates":[-75.145245,40.025913],"type":"Point"}
}