{
  "type": "Feature",
  "properties": {
    "iso:country":"US",
    "sg:address":"514 Ridge Rd",
    "sg:city":"Spring City",
    "sg:classifiers":[
        {
            "category":"Wholesale",
            "subcategory":"Books, Periodicals, & Newspapers",
            "type":"Manufacturing & Wholesale Goods"
        }
    ],
    "sg:phone":"+1 610 495 3001",
    "sg:postcode":"19475",
    "sg:province":"PA",
    "sg:tags":[
        "used",
        "merchandise"
    ],
    "wof:name":"Indian Path Books",
    "wof:placetype":"venue"
},
  "geometry": {"coordinates":[-75.61917800000001,40.175241],"type":"Point"}
}