{
  "type": "Feature",
  "properties": {
    "addr:full":"410 S 12th St Philadelphia PA 19147",
    "addr:housenumber":"410",
    "addr:postcode":"19147",
    "addr:street":"S 12Th St",
    "iso:country":"US",
    "sg:address":"410 S 12th St",
    "sg:city":"Philadelphia",
    "sg:classifiers":[
        {
            "category":"Restaurant",
            "type":"Food & Drink"
        }
    ],
    "sg:phone":"+1   ",
    "sg:postcode":"19147",
    "sg:province":"PA",
    "sg:tags":[
        "delicatessen"
    ],
    "wof:name":"Phila-Deli",
    "wof:placetype":"venue"
},
  "geometry": {"coordinates":[-75.161466,39.945019],"type":"Point"}
}