{
  "type": "Feature",
  "properties": {
    "addr:full":"517 Logan Blvd Altoona PA 16602",
    "addr:housenumber":"517",
    "addr:postcode":"16602",
    "addr:street":"Logan Blvd",
    "iso:country":"US",
    "sg:address":"517 Logan Blvd",
    "sg:city":"Altoona",
    "sg:classifiers":[
        {
            "category":"Banks & Credit Unions",
            "subcategory":"Investment Brokerage",
            "type":"Services"
        }
    ],
    "sg:phone":"+1 814 941 4800",
    "sg:postcode":"16602",
    "sg:province":"PA",
    "sg:tags":[
        "planner",
        "financial"
    ],
    "sg:website":"www.kooman.com",
    "wof:name":"Kooman & Assoc Inc",
    "wof:placetype":"venue"
},
  "geometry": {"coordinates":[-78.403839,40.478982],"type":"Point"}
}