{
  "type": "Feature",
  "properties": {
    "iso:country":"US",
    "sg:address":"156 Main Ave",
    "sg:city":"New Brighton",
    "sg:classifiers":[
        {
            "category":"Shopping",
            "type":"Retail Goods"
        }
    ],
    "sg:phone":"+1   ",
    "sg:postcode":"15066",
    "sg:province":"PA",
    "sg:tags":[
        "merchandise"
    ],
    "wof:name":"Steven E Romanchak",
    "wof:placetype":"venue"
},
  "geometry": {"coordinates":[-80.295529,40.748803],"type":"Point"}
}