{
  "type": "Feature",
  "properties": {
    "iso:country":"US",
    "sg:address":"4231 Country Club Rd",
    "sg:city":"Easton",
    "sg:classifiers":[
        {
            "category":"Farming",
            "subcategory":"Farm",
            "type":"Manufacturing & Wholesale Goods"
        }
    ],
    "sg:phone":"+1   ",
    "sg:postcode":"18045",
    "sg:province":"PA",
    "sg:tags":[
        "crop",
        "general"
    ],
    "wof:name":"Hopelock Farm",
    "wof:placetype":"venue"
},
  "geometry": {"coordinates":[-75.292581,40.687728],"type":"Point"}
}