{
  "type": "Feature",
  "properties": {
    "addr:full":"306 Commerce Park Dr Cranberry Twp PA 16066",
    "addr:housenumber":"306",
    "addr:postcode":"16066",
    "addr:street":"Commerce Park Dr",
    "iso:country":"US",
    "sg:address":"306 Commerce Park Dr",
    "sg:city":"Cranberry Twp",
    "sg:classifiers":[
        {
            "category":"Wholesale",
            "subcategory":"Home Furnishings",
            "type":"Manufacturing & Wholesale Goods"
        }
    ],
    "sg:phone":"+1 724 742 1800",
    "sg:postcode":"16066",
    "sg:province":"PA",
    "sg:tags":[
        "rug",
        "carpet"
    ],
    "wof:name":"Bayard Sales Corp",
    "wof:placetype":"venue"
},
  "geometry": {"coordinates":[-80.11203399999999,40.694715],"type":"Point"}
}