{
  "type": "Feature",
  "properties": {
    "addr:full":"9 Mahanoy Ave Tamaqua PA 18252",
    "addr:housenumber":"9",
    "addr:postcode":"18252",
    "addr:street":"Mahanoy Ave",
    "iso:country":"US",
    "sg:address":"9 Mahanoy Ave",
    "sg:city":"Tamaqua",
    "sg:classifiers":[
        {
            "category":"Restaurant",
            "type":"Food & Drink"
        }
    ],
    "sg:phone":"+1 570 668 5511",
    "sg:postcode":"18252",
    "sg:province":"PA",
    "wof:name":"Arby's",
    "wof:placetype":"venue"
},
  "geometry": {"coordinates":[-75.981196,40.823025],"type":"Point"}
}