{
  "type": "Feature",
  "properties": {
    "iso:country":"US",
    "sg:address":"5060 William Penn Hwy",
    "sg:city":"Monroeville",
    "sg:classifiers":[
        {
            "category":"Restaurant",
            "type":"Food & Drink"
        }
    ],
    "sg:phone":"+1 412 373 4497",
    "sg:postcode":"15146",
    "sg:province":"PA",
    "wof:name":"Potato Sack",
    "wof:placetype":"venue"
},
  "geometry": {"coordinates":[-79.71016899999999,40.430249],"type":"Point"}
}