{
  "type": "Feature",
  "properties": {
    "iso:country":"US",
    "sg:address":"130 Redwood Rd",
    "sg:city":"Acme",
    "sg:classifiers":[
        {
            "category":"Manufacturing",
            "subcategory":"Metals",
            "type":"Manufacturing & Wholesale Goods"
        }
    ],
    "sg:phone":"+1   ",
    "sg:postcode":"15666",
    "sg:province":"PA",
    "sg:tags":[
        "tool",
        "cutting",
        "maker",
        "carbide"
    ],
    "wof:name":"Brown Tool & Die Inc",
    "wof:placetype":"venue"
},
  "geometry": {"coordinates":[-79.476933,40.131776],"type":"Point"}
}