{
  "type": "Feature",
  "properties": {
    "iso:country":"US",
    "sg:address":"7959 Roosevelt Blvd",
    "sg:city":"Philadelphia",
    "sg:classifiers":[
        {
            "category":"Autos & Motor Vehicles",
            "subcategory":"Fuel & Gas Station",
            "type":"Retail Goods"
        }
    ],
    "sg:phone":"+1 215 624 9529",
    "sg:postcode":"19152",
    "sg:province":"PA",
    "wof:name":"Mobil Gas Station",
    "wof:placetype":"venue"
},
  "geometry": {"coordinates":[-75.04702,40.05587],"type":"Point"}
}