{
  "type": "Feature",
  "properties": {
    "iso:country":"US",
    "sg:address":"65 Toth Ave",
    "sg:city":"Coatesville",
    "sg:classifiers":[
        {
            "category":"Organizations",
            "subcategory":"Religious Organization",
            "type":"Services"
        }
    ],
    "sg:phone":"+1 610 384 5150",
    "sg:postcode":"19320",
    "sg:province":"PA",
    "sg:tags":[
        "church"
    ],
    "wof:name":"Bell Chapel Church",
    "wof:placetype":"venue"
},
  "geometry": {"coordinates":[-75.790098,39.992284],"type":"Point"}
}