{
  "type": "Feature",
  "properties": {
    "iso:country":"US",
    "sg:address":"436 Creamery Way",
    "sg:city":"Exton",
    "sg:classifiers":[
        {
            "category":"Retail",
            "subcategory":"Repair Shop",
            "type":"Services"
        }
    ],
    "sg:phone":"+1 610 594 9901",
    "sg:postcode":"19341",
    "sg:province":"PA",
    "sg:tags":[
        "equipment",
        "medical"
    ],
    "wof:name":"Ultratouch Corp",
    "wof:placetype":"venue"
},
  "geometry": {"coordinates":[-75.648022,40.01988],"type":"Point"}
}