{
  "type": "Feature",
  "properties": {
    "iso:country":"US",
    "sg:address":"2 N Pennell Rd",
    "sg:city":"Media",
    "sg:classifiers":[
        {
            "category":"Personal",
            "subcategory":"Beauty Salon",
            "type":"Services"
        }
    ],
    "sg:phone":"+1 610 565 2898",
    "sg:postcode":"19063",
    "sg:province":"PA",
    "wof:name":"Biordi Hair Styling",
    "wof:placetype":"venue"
},
  "geometry": {"coordinates":[-75.439947,39.914718],"type":"Point"}
}