{
  "type": "Feature",
  "properties": {
    "iso:country":"US",
    "sg:address":"840 W Street Rd",
    "sg:city":"West Chester",
    "sg:classifiers":[
        {
            "category":"Recreation",
            "type":"Entertainment"
        }
    ],
    "sg:phone":"+1 610 399 9200",
    "sg:postcode":"19382",
    "sg:province":"PA",
    "sg:tags":[
        "martial",
        "arts",
        "instruction"
    ],
    "wof:name":"Mccormick Karate Academy Inc",
    "wof:placetype":"venue"
},
  "geometry": {"coordinates":[-75.59368499999999,39.912296],"type":"Point"}
}