{
  "type": "Feature",
  "properties": {
    "iso:country":"US",
    "sg:address":"6029 Carlisle Pike",
    "sg:city":"Mechanicsburg",
    "sg:classifiers":[
        {
            "category":"Building & Trades",
            "subcategory":"Cleaning & Sanitation",
            "type":"Services"
        },
        {
            "category":"Home & Garden",
            "subcategory":"Carpets & Floor Coverings",
            "type":"Retail Goods"
        }
    ],
    "sg:phone":"+1 717 766 0288",
    "sg:postcode":"17050",
    "sg:province":"PA",
    "sg:tags":[
        "carpeting"
    ],
    "sg:website":"www.mzcarpet.com",
    "wof:name":"M & Z Carpets Inc",
    "wof:placetype":"venue"
},
  "geometry": {"coordinates":[-76.988602,40.241798],"type":"Point"}
}