{
  "type": "Feature",
  "properties": {
    "iso:country":"US",
    "sg:address":"8433 Germantown Ave",
    "sg:city":"Philadelphia",
    "sg:classifiers":[
        {
            "category":"Shopping",
            "subcategory":"Tobacco",
            "type":"Retail Goods"
        }
    ],
    "sg:phone":"+1   ",
    "sg:postcode":"19118",
    "sg:province":"PA",
    "sg:tags":[
        "product"
    ],
    "wof:name":"Pipe Rack The",
    "wof:placetype":"venue"
},
  "geometry": {"coordinates":[-75.20599300000001,40.07578],"type":"Point"}
}