{
  "type": "Feature",
  "properties": {
    "addr:full":"1464 Martin St State College PA 16803",
    "addr:housenumber":"1464",
    "addr:postcode":"16803",
    "addr:street":"Martin St",
    "iso:country":"US",
    "sg:address":"1464 Martin St",
    "sg:city":"State College",
    "sg:classifiers":[
        {
            "category":"Home & Garden",
            "subcategory":"Building Materials",
            "type":"Retail Goods"
        }
    ],
    "sg:phone":"+1 814 867 4787",
    "sg:postcode":"16803",
    "sg:province":"PA",
    "wof:name":"Blaylock Paint",
    "wof:placetype":"venue"
},
  "geometry": {"coordinates":[-77.88669,40.801473],"type":"Point"}
}