{
  "type": "Feature",
  "properties": {
    "addr:full":"530 College Park Dr Coraopolis PA 15108",
    "addr:housenumber":"530",
    "addr:postcode":"15108",
    "addr:street":"College Park Dr",
    "iso:country":"US",
    "sg:address":"530 College Park Dr",
    "sg:city":"Coraopolis",
    "sg:classifiers":[
        {
            "category":"Professional",
            "type":"Services"
        }
    ],
    "sg:phone":"+1   ",
    "sg:postcode":"15108",
    "sg:province":"PA",
    "wof:name":"Wendy Schafer",
    "wof:placetype":"venue"
},
  "geometry": {"coordinates":[-80.222739,40.519094],"type":"Point"}
}