{
  "type": "Feature",
  "properties": {
    "iso:country":"US",
    "sg:address":"The Marketplace At East Falls 3747 Ridge Ave",
    "sg:city":"Philadelphia",
    "sg:classifiers":[
        {
            "category":"Deli",
            "type":"Food & Drink"
        }
    ],
    "sg:phone":"+1 215 226 2322",
    "sg:postcode":"19132",
    "sg:province":"PA",
    "wof:name":"Plenti Grand Cafe",
    "wof:placetype":"venue"
},
  "geometry": {"coordinates":[-75.187014,40.002101],"type":"Point"}
}