{
  "type": "Feature",
  "properties": {
    "iso:country":"US",
    "sg:address":"20 S 10th St",
    "sg:city":"Pittsburgh",
    "sg:classifiers":[
        {
            "category":"Restaurant",
            "type":"Food & Drink"
        }
    ],
    "sg:postcode":"15203",
    "sg:province":"PA",
    "sg:tags":[
        "italian"
    ],
    "wof:name":"Amalfi's",
    "wof:placetype":"venue"
},
  "geometry": {"coordinates":[-79.988924,40.429885],"type":"Point"}
}