{
  "type": "Feature",
  "properties": {
    "addr:full":"401 Jefferson Ave Bristol PA 19007",
    "addr:housenumber":"401",
    "addr:postcode":"19007",
    "addr:street":"Jefferson Ave",
    "iso:country":"US",
    "sg:address":"401 Jefferson Ave",
    "sg:city":"Bristol",
    "sg:classifiers":[
        {
            "category":"Professional",
            "subcategory":"Printing & Photocopies",
            "type":"Services"
        }
    ],
    "sg:phone":"+1 215 788 2877",
    "sg:postcode":"19007",
    "sg:province":"PA",
    "sg:tags":[
        "photocopying",
        "duplicating",
        "copying"
    ],
    "wof:name":"Blue Chip Copy Center",
    "wof:placetype":"venue"
},
  "geometry": {"coordinates":[-74.849867,40.102857],"type":"Point"}
}