{
  "type": "Feature",
  "properties": {
    "iso:country":"US",
    "sg:address":"235 Quaker Plain Rd",
    "sg:city":"Bangor",
    "sg:classifiers":[
        {
            "category":"Retail",
            "subcategory":"Animal Services",
            "type":"Services"
        }
    ],
    "sg:phone":"+1 610 588 7825",
    "sg:postcode":"18013",
    "sg:province":"PA",
    "sg:tags":[
        "pet",
        "grooming"
    ],
    "wof:name":"Candys Critter Cuts",
    "wof:placetype":"venue"
},
  "geometry": {"coordinates":[-75.196094,40.924772],"type":"Point"}
}