{
  "type": "Feature",
  "properties": {
    "iso:country":"US",
    "sg:address":"212 Locust St",
    "sg:city":"Annville",
    "sg:classifiers":[
        {
            "category":"Professional",
            "subcategory":"Business Services",
            "type":"Services"
        },
        {
            "category":"Manufacturing",
            "subcategory":"Apparel",
            "type":"Manufacturing & Wholesale Goods"
        }
    ],
    "sg:phone":"+1 717 867 4003",
    "sg:postcode":"17003",
    "sg:province":"PA",
    "sg:tags":[
        "embroidery"
    ],
    "wof:name":"Unique Designs Custom Digit",
    "wof:placetype":"venue"
},
  "geometry": {"coordinates":[-76.51212200000001,40.327547],"type":"Point"}
}