{
  "type": "Feature",
  "properties": {
    "iso:country":"US",
    "sg:address":"48 Green Briar Cir",
    "sg:city":"Russell",
    "sg:classifiers":[
        {
            "category":"Real Estate",
            "subcategory":"Surveying",
            "type":"Services"
        }
    ],
    "sg:phone":"+1   ",
    "sg:postcode":"16345",
    "sg:province":"PA",
    "wof:name":"Wareham Surveying",
    "wof:placetype":"venue"
},
  "geometry": {"coordinates":[-79.143342,41.927961],"type":"Point"}
}