{
  "type": "Feature",
  "properties": {
    "iso:country":"US",
    "sg:address":"826 2nd St",
    "sg:city":"Blue Bell",
    "sg:classifiers":[
        {
            "category":"Wholesale",
            "subcategory":"Electrical",
            "type":"Manufacturing & Wholesale Goods"
        }
    ],
    "sg:phone":"+1 215 654 5200",
    "sg:postcode":"19422",
    "sg:province":"PA",
    "sg:tags":[
        "lighting",
        "fixture"
    ],
    "wof:name":"Intek Industries Inc",
    "wof:placetype":"venue"
},
  "geometry": {"coordinates":[-75.29119,40.167573],"type":"Point"}
}