{
  "type": "Feature",
  "properties": {
    "addr:full":"30 Bedford Sq Everett PA 15537",
    "addr:housenumber":"30",
    "addr:postcode":"15537",
    "addr:street":"Bedford Sq",
    "iso:country":"US",
    "sg:address":"30 Bedford Sq",
    "sg:city":"Everett",
    "sg:classifiers":[
        {
            "category":"Restaurant",
            "type":"Food & Drink"
        }
    ],
    "sg:phone":"+1 814 623 3400",
    "sg:postcode":"15537",
    "sg:province":"PA",
    "wof:name":"Original Italian Pizza",
    "wof:placetype":"venue"
},
  "geometry": {"coordinates":[-78.462345,40.018387],"type":"Point"}
}