{
  "type": "Feature",
  "properties": {
    "iso:country":"US",
    "sg:address":"2760 Neville Rd",
    "sg:city":"Pittsburgh",
    "sg:classifiers":[
        {
            "category":"Manufacturing",
            "subcategory":"Petroleum Products",
            "type":"Manufacturing & Wholesale Goods"
        }
    ],
    "sg:phone":"+1 412 778 3554",
    "sg:postcode":"15225",
    "sg:province":"PA",
    "wof:name":"Petroleum Products",
    "wof:placetype":"venue"
},
  "geometry": {"coordinates":[-80.109422,40.50466],"type":"Point"}
}