{
  "type": "Feature",
  "properties": {
    "iso:country":"US",
    "sg:address":"821 N 24th St",
    "sg:city":"Philadelphia",
    "sg:classifiers":[
        {
            "category":"Professional",
            "type":"Services"
        }
    ],
    "sg:phone":"+1   ",
    "sg:postcode":"19130",
    "sg:province":"PA",
    "wof:name":"Sonoco Gas",
    "wof:placetype":"venue"
},
  "geometry": {"coordinates":[-75.17624000000001,39.970417],"type":"Point"}
}