{
  "type": "Feature",
  "properties": {
    "iso:country":"US",
    "sg:address":"200 N Park Rd",
    "sg:city":"Reading",
    "sg:classifiers":[
        {
            "category":"Wholesale",
            "subcategory":"Vending Machines",
            "type":"Manufacturing & Wholesale Goods"
        }
    ],
    "sg:phone":"+1 610 655 8866",
    "sg:postcode":"19610",
    "sg:province":"PA",
    "wof:name":"High Food Svc LTD",
    "wof:placetype":"venue"
},
  "geometry": {"coordinates":[-75.956869,40.338941],"type":"Point"}
}