{
  "type": "Feature",
  "properties": {
    "addr:full":"395 Industrial Dr Easton PA 18042",
    "addr:housenumber":"395",
    "addr:postcode":"18042",
    "addr:street":"Industrial Dr",
    "iso:country":"US",
    "sg:address":"395 Industrial Dr",
    "sg:city":"Easton",
    "sg:classifiers":[
        {
            "category":"Recreation",
            "type":"Entertainment"
        }
    ],
    "sg:phone":"+1 610 559 1763",
    "sg:postcode":"18042",
    "sg:province":"PA",
    "sg:tags":[
        "range",
        "pistol",
        "rifle"
    ],
    "wof:name":"Easton Fish & Game",
    "wof:placetype":"venue"
},
  "geometry": {"coordinates":[-75.218003,40.669197],"type":"Point"}
}