{
  "type": "Feature",
  "properties": {
    "iso:country":"US",
    "sg:address":"2454 State Rte 655",
    "sg:city":"Belleville",
    "sg:classifiers":[
        {
            "category":"Building & Trades",
            "subcategory":"Construction",
            "type":"Services"
        }
    ],
    "sg:phone":"+1   ",
    "sg:postcode":"17004",
    "sg:province":"PA",
    "sg:tags":[
        "contractor"
    ],
    "wof:name":"Homestead Builders",
    "wof:placetype":"venue"
},
  "geometry": {"coordinates":[-77.764568,40.582682],"type":"Point"}
}