{
  "type": "Feature",
  "properties": {
    "addr:full":"943 N Church St Hazleton PA 18201",
    "addr:housenumber":"943",
    "addr:postcode":"18201",
    "addr:street":"N Church St",
    "iso:country":"US",
    "sg:address":"943 N Church St",
    "sg:city":"Hazleton",
    "sg:classifiers":[
        {
            "category":"Health Services",
            "subcategory":"Doctor",
            "type":"Services"
        }
    ],
    "sg:phone":"+1 570 453 1882",
    "sg:postcode":"18201",
    "sg:province":"PA",
    "sg:tags":[
        "physician",
        "surgeon"
    ],
    "wof:name":"Family Practice Assoc",
    "wof:placetype":"venue"
},
  "geometry": {"coordinates":[-75.977699,40.972193],"type":"Point"}
}