{
  "type": "Feature",
  "properties": {
    "iso:country":"US",
    "sg:address":"19 Highland Dr",
    "sg:city":"Wilkes Barre",
    "sg:classifiers":[
        {
            "category":"Organizations",
            "subcategory":"Membership Organization",
            "type":"Services"
        }
    ],
    "sg:phone":"+1   ",
    "sg:postcode":"18705",
    "sg:province":"PA",
    "wof:name":"North End Basbal Organization",
    "wof:placetype":"venue"
},
  "geometry": {"coordinates":[-75.86205,41.254991],"type":"Point"}
}