{
  "type": "Feature",
  "properties": {
    "iso:country":"US",
    "sg:address":"116 S Broadway",
    "sg:city":"Wind Gap",
    "sg:classifiers":[
        {
            "category":"Professional",
            "subcategory":"Lawyer & Legal Services",
            "type":"Services"
        }
    ],
    "sg:phone":"+1 610 863 6640",
    "sg:postcode":"18091",
    "sg:province":"PA",
    "sg:tags":[
        "attorney"
    ],
    "wof:name":"Michael A Filingo",
    "wof:placetype":"venue"
},
  "geometry": {"coordinates":[-75.29230099999999,40.8468],"type":"Point"}
}