{
  "type": "Feature",
  "properties": {
    "iso:country":"US",
    "sg:address":"836 S George St",
    "sg:city":"York",
    "sg:classifiers":[
        {
            "category":"Social Services",
            "type":"Services"
        }
    ],
    "sg:phone":"+1 717 845 9113",
    "sg:postcode":"17403",
    "sg:province":"PA",
    "sg:tags":[
        "agency",
        "adoption"
    ],
    "wof:name":"Diakon Adoption Svc",
    "wof:placetype":"venue"
},
  "geometry": {"coordinates":[-76.722399,39.950799],"type":"Point"}
}