{
  "type": "Feature",
  "properties": {
    "addr:full":"716 Adams Ave Philadelphia PA 19124",
    "addr:housenumber":"716",
    "addr:postcode":"19124",
    "addr:street":"Adams Ave",
    "iso:country":"US",
    "sg:address":"716 Adams Ave",
    "sg:city":"Philadelphia",
    "sg:classifiers":[
        {
            "category":"Restaurant",
            "type":"Food & Drink"
        }
    ],
    "sg:menulink":"http://www.allmenus.com/pa/philadelphia/211349-kfc---kentucky-fried-chicken/menu/",
    "sg:phone":"+1 215 533 1110",
    "sg:postcode":"19124",
    "sg:province":"PA",
    "sg:tags":[
        "american",
        "chicken"
    ],
    "wof:name":"KFC - Kentucky Fried Chicken",
    "wof:placetype":"venue"
},
  "geometry": {"coordinates":[-75.106461,40.032694],"type":"Point"}
}