{
  "type": "Feature",
  "properties": {
    "iso:country":"US",
    "sg:address":"47 Windmill Dr",
    "sg:city":"Southampton",
    "sg:classifiers":[
        {
            "category":"Building & Trades",
            "subcategory":"Electrical",
            "type":"Services"
        }
    ],
    "sg:phone":"+1   ",
    "sg:postcode":"18966",
    "sg:province":"PA",
    "sg:tags":[
        "electrical",
        "contractor"
    ],
    "wof:name":"Richard Kohn Electric",
    "wof:placetype":"venue"
},
  "geometry": {"coordinates":[-74.969615,40.199976],"type":"Point"}
}