{
  "type": "Feature",
  "properties": {
    "addr:full":"219 Fisher St Jonestown PA 17038",
    "addr:housenumber":"219",
    "addr:postcode":"17038",
    "addr:street":"Fisher St",
    "iso:country":"US",
    "sg:address":"219 Fisher St",
    "sg:city":"Jonestown",
    "sg:classifiers":[
        {
            "category":"Real Estate",
            "subcategory":"Real Estate Operator",
            "type":"Services"
        }
    ],
    "sg:phone":"+1 717 865 7345",
    "sg:postcode":"17038",
    "sg:province":"PA",
    "sg:tags":[
        "building",
        "apartment"
    ],
    "wof:name":"Walnut Manor",
    "wof:placetype":"venue"
},
  "geometry": {"coordinates":[-76.48459699999999,40.413572],"type":"Point"}
}