{
  "type": "Feature",
  "properties": {
    "addr:full":"106 Whitetail Dr Bellefonte PA 16823",
    "addr:housenumber":"106",
    "addr:postcode":"16823",
    "addr:street":"Whitetail Dr",
    "iso:country":"US",
    "sg:address":"106 Whitetail Dr",
    "sg:city":"Bellefonte",
    "sg:classifiers":[
        {
            "category":"Building & Trades",
            "subcategory":"Construction",
            "type":"Services"
        }
    ],
    "sg:phone":"+1 814 355 0911",
    "sg:postcode":"16823",
    "sg:province":"PA",
    "sg:tags":[
        "house"
    ],
    "wof:name":"Gilmore Construction",
    "wof:placetype":"venue"
},
  "geometry": {"coordinates":[-77.72753,40.903122],"type":"Point"}
}