{
  "type": "Feature",
  "properties": {
    "iso:country":"US",
    "sg:address":"411 Mitchell Ave",
    "sg:city":"Clairton",
    "sg:classifiers":[
        {
            "category":"Organizations",
            "subcategory":"Religious Organization",
            "type":"Services"
        }
    ],
    "sg:phone":"+1 412 233 0671",
    "sg:postcode":"15025",
    "sg:province":"PA",
    "wof:name":"Robinson Jonathan H Rev",
    "wof:placetype":"venue"
},
  "geometry": {"coordinates":[-79.884598,40.290901],"type":"Point"}
}