{
  "type": "Feature",
  "properties": {
    "addr:full":"2033 N 33rd St Philadelphia PA 19121",
    "addr:housenumber":"2033",
    "addr:postcode":"19121",
    "addr:street":"N 33Rd St",
    "iso:country":"US",
    "sg:address":"2033 N 33rd St",
    "sg:city":"Philadelphia",
    "sg:classifiers":[
        {
            "category":"Organizations",
            "subcategory":"Community Association",
            "type":"Services"
        }
    ],
    "sg:phone":"+1 215 232 7486",
    "sg:postcode":"19121",
    "sg:province":"PA",
    "sg:tags":[
        "military"
    ],
    "wof:name":"Veterans Of Foreign Wars",
    "wof:placetype":"venue"
},
  "geometry": {"coordinates":[-75.18727199999999,39.987641],"type":"Point"}
}