{
  "type": "Feature",
  "properties": {
    "iso:country":"US",
    "sg:address":"4 Saddleview Dr",
    "sg:city":"Doylestown",
    "sg:classifiers":[
        {
            "category":"Shopping",
            "subcategory":"Hobbies, Toys, & Games",
            "type":"Retail Goods"
        }
    ],
    "sg:phone":"+1   ",
    "sg:postcode":"18901",
    "sg:province":"PA",
    "wof:name":"Toy With ME",
    "wof:placetype":"venue"
},
  "geometry": {"coordinates":[-75.07257199999999,40.375829],"type":"Point"}
}