{
  "type": "Feature",
  "properties": {
    "addr:full":"634 Stefko Blvd Bethlehem PA 18017",
    "addr:housenumber":"634",
    "addr:postcode":"18017",
    "addr:street":"Stefko Blvd",
    "iso:country":"US",
    "sg:address":"634 Stefko Blvd",
    "sg:city":"Bethlehem",
    "sg:classifiers":[
        {
            "category":"Building & Trades",
            "subcategory":"Construction",
            "type":"Services"
        }
    ],
    "sg:phone":"+1 610 419 1588",
    "sg:postcode":"18017",
    "sg:province":"PA",
    "sg:tags":[
        "house",
        "remodeling"
    ],
    "wof:name":"Custom Craft Remodelers Inc",
    "wof:placetype":"venue"
},
  "geometry": {"coordinates":[-75.359943,40.620983],"type":"Point"}
}