{
  "type": "Feature",
  "properties": {
    "iso:country":"US",
    "sg:address":"76 Pennsylvania Ave",
    "sg:city":"Mill Hall",
    "sg:classifiers":[
        {
            "category":"Wholesale",
            "subcategory":"Farm Supplies",
            "type":"Manufacturing & Wholesale Goods"
        }
    ],
    "sg:phone":"+1 570 726 3080",
    "sg:postcode":"17751",
    "sg:province":"PA",
    "sg:tags":[
        "fertilizer"
    ],
    "wof:name":"Agway Mill Hall",
    "wof:placetype":"venue"
},
  "geometry": {"coordinates":[-77.48465,41.10892],"type":"Point"}
}