{
  "type": "Feature",
  "properties": {
    "addr:full":"88 Scott Rd Dublin PA 18901",
    "addr:housenumber":"88",
    "addr:postcode":"18901",
    "addr:street":"Scott Rd",
    "iso:country":"US",
    "sg:address":"88 Scott Rd",
    "sg:city":"Dublin",
    "sg:classifiers":[
        {
            "category":"Organizations",
            "subcategory":"Community Association",
            "type":"Services"
        }
    ],
    "sg:phone":"+1 215 249 3673",
    "sg:postcode":"18901",
    "sg:province":"PA",
    "sg:tags":[
        "fraternal"
    ],
    "wof:name":"Fraternal Order Of Police",
    "wof:placetype":"venue"
},
  "geometry": {"coordinates":[-75.12576199999999,40.300275],"type":"Point"}
}