{
  "type": "Feature",
  "properties": {
    "addr:full":"800 Race St Williamsport PA 17701",
    "addr:housenumber":"800",
    "addr:postcode":"17701",
    "addr:street":"Race St",
    "iso:country":"US",
    "sg:address":"800 Race St",
    "sg:city":"Williamsport",
    "sg:classifiers":[
        {
            "category":"Recreation",
            "type":"Entertainment"
        }
    ],
    "sg:phone":"+1 570 329 1111",
    "sg:postcode":"17701",
    "sg:province":"PA",
    "sg:tags":[
        "amusement"
    ],
    "wof:name":"3 D Creative Svc",
    "wof:placetype":"venue"
},
  "geometry": {"coordinates":[-77.05120700000001,41.238873],"type":"Point"}
}