{
  "type": "Feature",
  "properties": {
    "iso:country":"US",
    "sg:address":"119 Aster Dr",
    "sg:city":"Harrisburg",
    "sg:classifiers":[
        {
            "category":"Manufacturing",
            "subcategory":"Tools & Machinery",
            "type":"Manufacturing & Wholesale Goods"
        }
    ],
    "sg:phone":"+1   ",
    "sg:postcode":"17112",
    "sg:province":"PA",
    "sg:tags":[
        "machine",
        "mfg"
    ],
    "wof:name":"Pitney Bowes",
    "wof:placetype":"venue"
},
  "geometry": {"coordinates":[-76.780992,40.327221],"type":"Point"}
}