{
  "type": "Feature",
  "properties": {
    "addr:full":"380 Oxford Valley Rd Langhorne PA 19047",
    "addr:housenumber":"380",
    "addr:postcode":"19047",
    "addr:street":"Oxford Valley Rd",
    "iso:country":"US",
    "sg:address":"380 Oxford Valley Rd",
    "sg:city":"Langhorne",
    "sg:classifiers":[
        {
            "category":"Health Services",
            "subcategory":"Hospital",
            "type":"Services"
        },
        {
            "category":"Health Services",
            "subcategory":"Clinic",
            "type":"Services"
        },
        {
            "category":"Community Center",
            "type":"Public Place"
        },
        {
            "category":"Social Services",
            "subcategory":"Job Training",
            "type":"Services"
        }
    ],
    "sg:phone":"+1 215 949 5180",
    "sg:postcode":"19047",
    "sg:province":"PA",
    "sg:tags":[
        "nursing",
        "medical",
        "surgery",
        "homes-skilled",
        "facility"
    ],
    "wof:name":"Aria Health-Bucks County Campus",
    "wof:placetype":"venue"
},
  "geometry": {"coordinates":[-74.870028,40.18481],"type":"Point"}
}