{
  "type": "Feature",
  "properties": {
    "iso:country":"US",
    "sg:address":"1830 Union Ave",
    "sg:city":"Natrona Heights",
    "sg:classifiers":[
        {
            "category":"Shopping",
            "type":"Retail Goods"
        },
        {
            "category":"Shopping",
            "subcategory":"Beauty & Cosmetics",
            "type":"Retail Goods"
        }
    ],
    "sg:phone":"+1 724 224 1417",
    "sg:postcode":"15065",
    "sg:province":"PA",
    "sg:tags":[
        "merchandise",
        "perfume"
    ],
    "sg:website":"www.bathandbodyworks.com",
    "wof:name":"Bath & Body Works Inc",
    "wof:placetype":"venue"
},
  "geometry": {"coordinates":[-79.724571,40.622042],"type":"Point"}
}