{
  "type": "Feature",
  "properties": {
    "addr:full":"1 Center St Doylestown PA 18901",
    "addr:housenumber":"1",
    "addr:postcode":"18901",
    "addr:street":"Center St",
    "iso:country":"US",
    "sg:address":"1 Center St",
    "sg:city":"Doylestown",
    "sg:classifiers":[
        {
            "category":"Health Services",
            "subcategory":"Doctor",
            "type":"Services"
        }
    ],
    "sg:phone":"+1 215 345 8702",
    "sg:postcode":"18901",
    "sg:province":"PA",
    "sg:tags":[
        "surgeon",
        "oral"
    ],
    "wof:name":"Cunning Stephen C DDS",
    "wof:placetype":"venue"
},
  "geometry": {"coordinates":[-75.12809799999999,40.324699],"type":"Point"}
}