{
  "type": "Feature",
  "properties": {
    "iso:country":"US",
    "sg:address":"910 New Market St",
    "sg:city":"Philadelphia",
    "sg:classifiers":[
        {
            "category":"Food & Beverages",
            "subcategory":"Bakery",
            "type":"Retail Goods"
        }
    ],
    "sg:phone":"+1   ",
    "sg:postcode":"19123",
    "sg:province":"PA",
    "wof:name":"L & F Donuts Inc",
    "wof:placetype":"venue"
},
  "geometry": {"coordinates":[-75.139129,39.964265],"type":"Point"}
}