{
  "type": "Feature",
  "properties": {
    "iso:country":"US",
    "sg:address":"155 Herbst Rd",
    "sg:city":"Coraopolis",
    "sg:classifiers":[
        {
            "category":"Building & Trades",
            "subcategory":"Construction",
            "type":"Services"
        }
    ],
    "sg:phone":"+1   ",
    "sg:postcode":"15108",
    "sg:province":"PA",
    "sg:tags":[
        "brick",
        "layer"
    ],
    "wof:name":"Vince Cercone",
    "wof:placetype":"venue"
},
  "geometry": {"coordinates":[-80.116272,40.486543],"type":"Point"}
}