{
  "type": "Feature",
  "properties": {
    "iso:country":"US",
    "sg:address":"2026 Pemberton St",
    "sg:city":"Philadelphia",
    "sg:classifiers":[
        {
            "category":"Shopping",
            "subcategory":"Books",
            "type":"Retail Goods"
        }
    ],
    "sg:phone":"+1 215 731 0460",
    "sg:postcode":"19146",
    "sg:province":"PA",
    "sg:tags":[
        "store"
    ],
    "wof:name":"Words & Whimsy",
    "wof:placetype":"venue"
},
  "geometry": {"coordinates":[-75.17585099999999,39.943525],"type":"Point"}
}