{
  "type": "Feature",
  "properties": {
    "addr:full":"618 Welsh Rd Huntingdon Valley PA 19006",
    "addr:housenumber":"618",
    "addr:postcode":"19006",
    "addr:street":"Welsh Rd",
    "iso:country":"US",
    "sg:address":"618 Welsh Rd",
    "sg:city":"Huntingdon Valley",
    "sg:classifiers":[
        {
            "category":"Banks & Credit Unions",
            "subcategory":"Bank",
            "type":"Services"
        }
    ],
    "sg:phone":"+1   ",
    "sg:postcode":"19006",
    "sg:province":"PA",
    "sg:tags":[
        "national",
        "commercial"
    ],
    "wof:name":"Fleet",
    "wof:placetype":"venue"
},
  "geometry": {"coordinates":[-75.06828400000001,40.120222],"type":"Point"}
}