{
  "type": "Feature",
  "properties": {
    "iso:country":"US",
    "sg:address":"550 E Lancaster Ave",
    "sg:city":"Wayne",
    "sg:classifiers":[
        {
            "category":"Coffee & Tea",
            "type":"Food & Drink"
        }
    ],
    "sg:menulink":"http://www.allmenus.com/pa/radnor/125268-starbucks-coffee/menu/",
    "sg:phone":"+1 610 989 0781",
    "sg:postcode":"19087",
    "sg:province":"PA",
    "sg:tags":[
        "american"
    ],
    "wof:name":"Starbucks Coffee",
    "wof:placetype":"venue"
},
  "geometry": {"coordinates":[-75.36903100000001,40.041109],"type":"Point"}
}