{
  "type": "Feature",
  "properties": {
    "iso:country":"US",
    "sg:address":"2531 Wildwood Rd",
    "sg:city":"Allison Park",
    "sg:classifiers":[
        {
            "category":"Personal",
            "subcategory":"Beauty Salon",
            "type":"Services"
        }
    ],
    "sg:phone":"+1 412 486 7257",
    "sg:postcode":"15101",
    "sg:province":"PA",
    "sg:tags":[
        "manicuring"
    ],
    "wof:name":"All Ten Nails",
    "wof:placetype":"venue"
},
  "geometry": {"coordinates":[-79.968104,40.593859],"type":"Point"}
}