{
  "type": "Feature",
  "properties": {
    "iso:country":"US",
    "sg:address":"2120 Farmington Ave",
    "sg:city":"Boyertown",
    "sg:classifiers":[
        {
            "category":"Building & Trades",
            "subcategory":"Construction",
            "type":"Services"
        }
    ],
    "sg:phone":"+1 610 367 6232",
    "sg:postcode":"19512",
    "sg:province":"PA",
    "sg:tags":[
        "wallcoverings-installation",
        "wallpaper",
        "painting",
        "contractor"
    ],
    "wof:name":"Stauffer Painting",
    "wof:placetype":"venue"
},
  "geometry": {"coordinates":[-75.652687,40.308708],"type":"Point"}
}