{
  "type": "Feature",
  "properties": {
    "addr:full":"1415 Peninsula Dr Erie PA 16505",
    "addr:housenumber":"1415",
    "addr:postcode":"16505",
    "addr:street":"Peninsula Dr",
    "iso:country":"US",
    "sg:address":"1415 Peninsula Dr",
    "sg:city":"Erie",
    "sg:classifiers":[
        {
            "category":"Structure",
            "subcategory":"Warehouse",
            "type":"Public Place"
        },
        {
            "category":"Retail",
            "subcategory":"Storage",
            "type":"Services"
        }
    ],
    "sg:phone":"+1 814 464 8898",
    "sg:postcode":"16505",
    "sg:province":"PA",
    "sg:tags":[
        "self",
        "warehouses-merchandise"
    ],
    "wof:name":"Prosource Erie-Warehouse",
    "wof:placetype":"venue"
},
  "geometry": {"coordinates":[-80.14392100000001,42.097172],"type":"Point"}
}