{
  "type": "Feature",
  "properties": {
    "iso:country":"US",
    "sg:address":"142 Forsythia Ct",
    "sg:city":"Quakertown",
    "sg:classifiers":[
        {
            "category":"Building & Trades",
            "subcategory":"Cleaning & Sanitation",
            "type":"Services"
        }
    ],
    "sg:phone":"+1 215 538 1037",
    "sg:postcode":"18951",
    "sg:province":"PA",
    "sg:tags":[
        "janitor"
    ],
    "wof:name":"Morning Star Cleaning Svc",
    "wof:placetype":"venue"
},
  "geometry": {"coordinates":[-75.34362900000001,40.42456],"type":"Point"}
}