{
  "type": "Feature",
  "properties": {
    "iso:country":"US",
    "sg:address":"5120 E Trindle Rd",
    "sg:city":"Mechanicsburg",
    "sg:classifiers":[
        {
            "category":"Building & Trades",
            "subcategory":"Equipment Rental",
            "type":"Services"
        }
    ],
    "sg:phone":"+1   ",
    "sg:postcode":"17050",
    "sg:province":"PA",
    "wof:name":"West Shore Gas",
    "wof:placetype":"venue"
},
  "geometry": {"coordinates":[-76.975824,40.22369],"type":"Point"}
}