{
  "type": "Feature",
  "properties": {
    "addr:full":"1406 W 21st St Erie PA 16502",
    "addr:housenumber":"1406",
    "addr:postcode":"16502",
    "addr:street":"W 21St St",
    "iso:country":"US",
    "sg:address":"1406 W 21st St",
    "sg:city":"Erie",
    "sg:classifiers":[
        {
            "category":"Building & Trades",
            "subcategory":"Landscaping Services",
            "type":"Services"
        }
    ],
    "sg:phone":"+1 814 455 1752",
    "sg:postcode":"16502",
    "sg:province":"PA",
    "sg:tags":[
        "landscape",
        "contractor"
    ],
    "sg:website":"www.allinco.com",
    "wof:name":"Allin Co",
    "wof:placetype":"venue"
},
  "geometry": {"coordinates":[-80.108716,42.104213],"type":"Point"}
}