{
  "type": "Feature",
  "properties": {
    "addr:full":"4108 Chandler Dr Brookhaven PA 19015",
    "addr:housenumber":"4108",
    "addr:postcode":"19015",
    "addr:street":"Chandler Dr",
    "iso:country":"US",
    "sg:address":"4108 Chandler Dr",
    "sg:city":"Brookhaven",
    "sg:classifiers":[
        {
            "category":"Place Of Worship",
            "type":"Public Place"
        }
    ],
    "sg:phone":"+1 610 306 2946",
    "sg:postcode":"19015",
    "sg:province":"PA",
    "sg:tags":[
        "church"
    ],
    "wof:name":"Media Church Of Christ",
    "wof:placetype":"venue"
},
  "geometry": {"coordinates":[-75.392512,39.869297],"type":"Point"}
}