{
  "type": "Feature",
  "properties": {
    "addr:full":"1320 Price St Marcus Hook PA 19061",
    "addr:housenumber":"1320",
    "addr:postcode":"19061",
    "addr:street":"Price St",
    "iso:country":"US",
    "sg:address":"1320 Price St",
    "sg:city":"Marcus Hook",
    "sg:classifiers":[
        {
            "category":"Building & Trades",
            "subcategory":"Plumbing",
            "type":"Services"
        }
    ],
    "sg:phone":"+1   ",
    "sg:postcode":"19061",
    "sg:province":"PA",
    "sg:tags":[
        "contractor"
    ],
    "wof:name":"Franks Heating & AC Co",
    "wof:placetype":"venue"
},
  "geometry": {"coordinates":[-75.40682200000001,39.836322],"type":"Point"}
}