{
  "type": "Feature",
  "properties": {
    "iso:country":"US",
    "sg:address":"3308 South St",
    "sg:city":"Erie",
    "sg:classifiers":[
        {
            "category":"Organizations",
            "subcategory":"Religious Organization",
            "type":"Services"
        }
    ],
    "sg:phone":"+1 814 899 3302",
    "sg:postcode":"16510",
    "sg:province":"PA",
    "sg:tags":[
        "church"
    ],
    "sg:website":"www.ewesley.com",
    "wof:name":"Wesley United Methodist Church",
    "wof:placetype":"venue"
},
  "geometry": {"coordinates":[-80.01291500000001,42.140196],"type":"Point"}
}