{
  "type": "Feature",
  "properties": {
    "iso:country":"US",
    "sg:address":"3 Sonesta Ct",
    "sg:city":"Landenberg",
    "sg:classifiers":[
        {
            "category":"Shopping",
            "subcategory":"Shoes",
            "type":"Retail Goods"
        }
    ],
    "sg:phone":"+1   ",
    "sg:postcode":"19350",
    "sg:province":"PA",
    "wof:name":"Sarah Maling",
    "wof:placetype":"venue"
},
  "geometry": {"coordinates":[-75.734848,39.789154],"type":"Point"}
}