{
  "type": "Feature",
  "properties": {
    "iso:country":"US",
    "sg:address":"4393 Ramer Rd",
    "sg:city":"Emmaus",
    "sg:classifiers":[
        {
            "category":"Retail",
            "subcategory":"Auto Repair",
            "type":"Services"
        }
    ],
    "sg:phone":"+1 610 967 6634",
    "sg:postcode":"18049",
    "sg:province":"PA",
    "sg:tags":[
        "automobile",
        "used",
        "truck",
        "general"
    ],
    "sg:website":"www.sellstruck.com",
    "wof:name":"Sell's Truck Repair",
    "wof:placetype":"venue"
},
  "geometry": {"coordinates":[-75.515355,40.52354],"type":"Point"}
}