{
  "type": "Feature",
  "properties": {
    "iso:country":"US",
    "sg:address":"317 Bennett St",
    "sg:city":"Luzerne",
    "sg:classifiers":[
        {
            "category":"Building & Trades",
            "subcategory":"Construction",
            "type":"Services"
        }
    ],
    "sg:phone":"+1 570 287 2701",
    "sg:postcode":"18709",
    "sg:province":"PA",
    "sg:tags":[
        "masonry",
        "contractor"
    ],
    "wof:name":"S & S Svc",
    "wof:placetype":"venue"
},
  "geometry": {"coordinates":[-75.88914699999999,41.280398],"type":"Point"}
}