{
  "type": "Feature",
  "properties": {
    "iso:country":"US",
    "sg:address":"649 E Main St",
    "sg:city":"Annville",
    "sg:classifiers":[
        {
            "category":"Autos & Motor Vehicles",
            "subcategory":"Automobile Sales",
            "type":"Retail Goods"
        }
    ],
    "sg:phone":"+1 717 867 2690",
    "sg:postcode":"17003",
    "sg:province":"PA",
    "sg:tags":[
        "car",
        "used",
        "dealer"
    ],
    "wof:name":"Risser Auto Stan Sales",
    "wof:placetype":"venue"
},
  "geometry": {"coordinates":[-76.503891,40.331573],"type":"Point"}
}