{
  "type": "Feature",
  "properties": {
    "addr:full":"875 Greentree Rd Pittsburgh PA 15220",
    "addr:housenumber":"875",
    "addr:postcode":"15220",
    "addr:street":"Greentree Rd",
    "iso:country":"US",
    "sg:address":"875 Greentree Rd",
    "sg:city":"Pittsburgh",
    "sg:classifiers":[
        {
            "category":"Banks & Credit Unions",
            "subcategory":"Bank",
            "type":"Services"
        }
    ],
    "sg:phone":"+1 412 920 0999",
    "sg:postcode":"15220",
    "sg:province":"PA",
    "sg:tags":[
        "federal"
    ],
    "wof:name":"Corning Credit Union",
    "wof:placetype":"venue"
},
  "geometry": {"coordinates":[-80.04122,40.428354],"type":"Point"}
}