{
  "type": "Feature",
  "properties": {
    "iso:country":"US",
    "sg:address":"112 S Main St",
    "sg:city":"Spring Grove",
    "sg:classifiers":[
        {
            "category":"Organizations",
            "subcategory":"Labor Organization",
            "type":"Services"
        }
    ],
    "sg:phone":"+1 717 225 1710",
    "sg:postcode":"17362",
    "sg:province":"PA",
    "wof:name":"Local 1303",
    "wof:placetype":"venue"
},
  "geometry": {"coordinates":[-76.865454,39.872926],"type":"Point"}
}