{
  "type": "Feature",
  "properties": {
    "iso:country":"US",
    "sg:address":"9044 Tomstown Rd",
    "sg:city":"Waynesboro",
    "sg:classifiers":[
        {
            "category":"Retail",
            "subcategory":"Auto Repair",
            "type":"Services"
        }
    ],
    "sg:phone":"+1   ",
    "sg:postcode":"17268",
    "sg:province":"PA",
    "sg:tags":[
        "grade",
        "equipment",
        "construction",
        "power"
    ],
    "wof:name":"D&M Outdoor Power",
    "wof:placetype":"venue"
},
  "geometry": {"coordinates":[-77.558705,39.804419],"type":"Point"}
}