{
  "type": "Feature",
  "properties": {
    "iso:country":"US",
    "sg:address":"4778 US Hwy 19",
    "sg:city":"Cochranton",
    "sg:classifiers":[
        {
            "category":"Retail",
            "subcategory":"Auto Repair",
            "type":"Services"
        }
    ],
    "sg:phone":"+1 814 425 1675",
    "sg:postcode":"16314",
    "sg:province":"PA",
    "sg:tags":[
        "automobile",
        "inspection"
    ],
    "wof:name":"Wright's Hill Top Auto",
    "wof:placetype":"venue"
},
  "geometry": {"coordinates":[-80.1849,41.530144],"type":"Point"}
}