{
  "type": "Feature",
  "properties": {
    "iso:country":"US",
    "sg:address":"107 Bair Blvd",
    "sg:city":"New Stanton",
    "sg:classifiers":[
        {
            "category":"Travel",
            "subcategory":"Hotels & Motels",
            "type":"Entertainment"
        }
    ],
    "sg:phone":"+1 724 755 0800",
    "sg:postcode":"15672",
    "sg:province":"PA",
    "sg:tags":[
        "operation"
    ],
    "wof:name":"Fairfield Inn",
    "wof:placetype":"venue"
},
  "geometry": {"coordinates":[-79.61081799999999,40.219916],"type":"Point"}
}