{
  "type": "Feature",
  "properties": {
    "iso:country":"US",
    "sg:address":"151 W Lancaster Ave",
    "sg:city":"Downingtown",
    "sg:classifiers":[
        {
            "category":"Personal",
            "subcategory":"Beauty Salon",
            "type":"Services"
        }
    ],
    "sg:phone":"+1 610 269 4200",
    "sg:postcode":"19335",
    "sg:province":"PA",
    "wof:name":"Trevoh's Hair Salon LTD",
    "wof:placetype":"venue"
},
  "geometry": {"coordinates":[-75.709452,40.003195],"type":"Point"}
}