{
  "type": "Feature",
  "properties": {
    "iso:country":"US",
    "sg:address":"1309 Decatur Ct",
    "sg:city":"Downingtown",
    "sg:classifiers":[
        {
            "category":"Building & Trades",
            "subcategory":"Cleaning & Sanitation",
            "type":"Services"
        }
    ],
    "sg:phone":"+1 610 269 3100",
    "sg:postcode":"19335",
    "sg:province":"PA",
    "sg:tags":[
        "window"
    ],
    "wof:name":"Residential Window & Glass",
    "wof:placetype":"venue"
},
  "geometry": {"coordinates":[-75.730266,39.974043],"type":"Point"}
}