{
  "type": "Feature",
  "properties": {
    "iso:country":"US",
    "sg:address":"836 Evans City Rd",
    "sg:city":"Renfrew",
    "sg:classifiers":[
        {
            "category":"Retail",
            "subcategory":"Auto Repair",
            "type":"Services"
        }
    ],
    "sg:phone":"+1 724 789 1111",
    "sg:postcode":"16053",
    "sg:province":"PA",
    "sg:tags":[
        "body"
    ],
    "wof:name":"Judson Auto Body",
    "wof:placetype":"venue"
},
  "geometry": {"coordinates":[-79.98491199999999,40.850622],"type":"Point"}
}