{
  "type": "Feature",
  "properties": {
    "addr:full":"9 Lawson Pl Conyngham PA 18219",
    "addr:housenumber":"9",
    "addr:postcode":"18219",
    "addr:street":"Lawson Pl",
    "iso:country":"US",
    "sg:address":"9 Lawson Pl",
    "sg:city":"Conyngham",
    "sg:classifiers":[
        {
            "category":"Professional",
            "subcategory":"Management & Consulting",
            "type":"Services"
        }
    ],
    "sg:phone":"+1 570 788 1976",
    "sg:postcode":"18219",
    "sg:province":"PA",
    "sg:tags":[
        "selling",
        "establishment",
        "direct"
    ],
    "wof:name":"Shaklee Products",
    "wof:placetype":"venue"
},
  "geometry": {"coordinates":[-76.061441,40.993212],"type":"Point"}
}