{
  "type": "Feature",
  "properties": {
    "iso:country":"US",
    "sg:address":"704 W Emaus Ave",
    "sg:city":"Allentown",
    "sg:classifiers":[
        {
            "category":"Food & Beverages",
            "subcategory":"Liquor & Beverages",
            "type":"Retail Goods"
        }
    ],
    "sg:phone":"+1 610 797 3511",
    "sg:postcode":"18103",
    "sg:province":"PA",
    "sg:tags":[
        "beer",
        "spirit",
        "wine"
    ],
    "wof:name":"G Cruz Inc",
    "wof:placetype":"venue"
},
  "geometry": {"coordinates":[-75.46165000000001,40.57432],"type":"Point"}
}