{
  "type": "Feature",
  "properties": {
    "iso:country":"US",
    "sg:address":"1829 Stefko Blvd",
    "sg:city":"Bethlehem",
    "sg:classifiers":[
        {
            "category":"Restaurant",
            "type":"Food & Drink"
        }
    ],
    "sg:menulink":"http://www.allmenus.com/pa/bethlehem/133594-subway/menu/",
    "sg:phone":"+1 610 882 1220",
    "sg:postcode":"18017",
    "sg:province":"PA",
    "sg:tags":[
        "american",
        "sandwich"
    ],
    "wof:name":"Subway",
    "wof:placetype":"venue"
},
  "geometry": {"coordinates":[-75.348916,40.638281],"type":"Point"}
}