{
  "type": "Feature",
  "properties": {
    "iso:country":"US",
    "sg:address":"1004 Ligonier St",
    "sg:city":"Latrobe",
    "sg:classifiers":[
        {
            "category":"Health Services",
            "subcategory":"Clinic",
            "type":"Services"
        }
    ],
    "sg:phone":"+1   ",
    "sg:postcode":"15650",
    "sg:province":"PA",
    "sg:tags":[
        "consulting",
        "management",
        "specialty",
        "outpatient"
    ],
    "wof:name":"Westmrland Csmnagement Support",
    "wof:placetype":"venue"
},
  "geometry": {"coordinates":[-79.38381200000001,40.315874],"type":"Point"}
}