{
  "type": "Feature",
  "properties": {
    "addr:full":"324 W Chelten Ave Philadelphia PA 19144",
    "addr:housenumber":"324",
    "addr:postcode":"19144",
    "addr:street":"W Chelten Ave",
    "iso:country":"US",
    "sg:address":"324 W Chelten Ave",
    "sg:city":"Philadelphia",
    "sg:classifiers":[
        {
            "category":"Restaurant",
            "type":"Food & Drink"
        }
    ],
    "sg:phone":"+1 215 843 3313",
    "sg:postcode":"19144",
    "sg:province":"PA",
    "sg:tags":[
        "eating",
        "pizza"
    ],
    "wof:name":"Germantown Style Pizza",
    "wof:placetype":"venue"
},
  "geometry": {"coordinates":[-75.180801,40.030102],"type":"Point"}
}