{
  "type": "Feature",
  "properties": {
    "iso:country":"US",
    "sg:address":"7229 Passyunk Ave",
    "sg:city":"Philadelphia",
    "sg:classifiers":[
        {
            "category":"Restaurant",
            "type":"Food & Drink"
        }
    ],
    "sg:phone":"+1 215 365 3775",
    "sg:postcode":"19142",
    "sg:province":"PA",
    "sg:tags":[
        "eating",
        "pizza"
    ],
    "wof:name":"Pete's Pizza",
    "wof:placetype":"venue"
},
  "geometry": {"coordinates":[-75.24009700000001,39.9133],"type":"Point"}
}