{
  "type": "Feature",
  "properties": {
    "iso:country":"US",
    "sg:address":"753 E Main St",
    "sg:city":"Annville",
    "sg:classifiers":[
        {
            "category":"Shopping",
            "subcategory":"Clothing, Apparel, & Fashions",
            "type":"Retail Goods"
        }
    ],
    "sg:phone":"+1 717 867 5406",
    "sg:postcode":"17003",
    "sg:province":"PA",
    "sg:tags":[
        "alteration"
    ],
    "wof:name":"Sew What By Mabel",
    "wof:placetype":"venue"
},
  "geometry": {"coordinates":[-76.500472,40.332427],"type":"Point"}
}