{
  "type": "Feature",
  "properties": {
    "addr:full":"110 Unity St Latrobe PA 15650",
    "addr:housenumber":"110",
    "addr:postcode":"15650",
    "addr:street":"Unity St",
    "iso:country":"US",
    "sg:address":"110 Unity St",
    "sg:city":"Latrobe",
    "sg:classifiers":[
        {
            "category":"Restaurant",
            "type":"Food & Drink"
        }
    ],
    "sg:phone":"+1   ",
    "sg:postcode":"15650",
    "sg:province":"PA",
    "sg:tags":[
        "eating"
    ],
    "wof:name":"Wong China",
    "wof:placetype":"venue"
},
  "geometry": {"coordinates":[-79.38851099999999,40.312645],"type":"Point"}
}