{
  "type": "Feature",
  "properties": {
    "iso:country":"US",
    "sg:address":"5136 Applebutter Rd",
    "sg:city":"Plumsteadville",
    "sg:classifiers":[
        {
            "category":"Manufacturing",
            "subcategory":"Tools & Machinery",
            "type":"Manufacturing & Wholesale Goods"
        }
    ],
    "sg:phone":"+1   ",
    "sg:postcode":"18947",
    "sg:province":"PA",
    "sg:tags":[
        "industrial",
        "mfg"
    ],
    "wof:name":"Fluid Energy Aljet",
    "wof:placetype":"venue"
},
  "geometry": {"coordinates":[-75.15372000000001,40.393806],"type":"Point"}
}