{
  "type": "Feature",
  "properties": {
    "addr:full":"532 N 63rd St Philadelphia PA 19151",
    "addr:housenumber":"532",
    "addr:postcode":"19151",
    "addr:street":"N 63Rd St",
    "iso:country":"US",
    "sg:address":"532 N 63rd St",
    "sg:city":"Philadelphia",
    "sg:classifiers":[
        {
            "category":"Shopping",
            "subcategory":"Used Merchandise",
            "type":"Retail Goods"
        }
    ],
    "sg:phone":"+1 215 474 4288",
    "sg:postcode":"19151",
    "sg:province":"PA",
    "sg:tags":[
        "shop",
        "thrift"
    ],
    "wof:name":"Sam's Thrift Shop",
    "wof:placetype":"venue"
},
  "geometry": {"coordinates":[-75.24505600000001,39.971041],"type":"Point"}
}