{
  "type": "Feature",
  "properties": {
    "iso:country":"US",
    "sg:address":"8771 Lemar Rd",
    "sg:city":"Greencastle",
    "sg:classifiers":[
        {
            "category":"Building & Trades",
            "subcategory":"Construction",
            "type":"Services"
        }
    ],
    "sg:phone":"+1 717 597 3770",
    "sg:postcode":"17225",
    "sg:province":"PA",
    "sg:tags":[
        "general",
        "contractor"
    ],
    "wof:name":"Egolf Construction",
    "wof:placetype":"venue"
},
  "geometry": {"coordinates":[-77.81102300000001,39.808714],"type":"Point"}
}