{
  "type": "Feature",
  "properties": {
    "addr:full":"13015 Ferguson Valley Rd Burnham PA 17044",
    "addr:housenumber":"13015",
    "addr:postcode":"17044",
    "addr:street":"Ferguson Valley Rd",
    "iso:country":"US",
    "sg:address":"13015 Ferguson Valley Rd",
    "sg:city":"Burnham",
    "sg:classifiers":[
        {
            "category":"Travel",
            "subcategory":"Hotels & Motels",
            "type":"Entertainment"
        }
    ],
    "sg:phone":"+1   ",
    "sg:postcode":"17044",
    "sg:province":"PA",
    "sg:tags":[
        "operation",
        "eating",
        "real estate"
    ],
    "wof:name":"Clarion Hotel",
    "wof:placetype":"venue"
},
  "geometry": {"coordinates":[-77.587447,40.626442],"type":"Point"}
}