{
  "type": "Feature",
  "properties": {
    "iso:country":"US",
    "sg:address":"263 E Main St",
    "sg:city":"Millheim",
    "sg:classifiers":[
        {
            "category":"Arts & Performance",
            "subcategory":"Theater",
            "type":"Entertainment"
        }
    ],
    "sg:phone":"+1 814 349 5114",
    "sg:postcode":"16820",
    "sg:province":"PA",
    "sg:tags":[
        "live",
        "music"
    ],
    "wof:name":"Mr Nice Guy",
    "wof:placetype":"venue"
},
  "geometry": {"coordinates":[-77.45996100000001,40.898742],"type":"Point"}
}