{
  "type": "Feature",
  "properties": {
    "iso:country":"US",
    "sg:address":"2720 S Old Stage Rd",
    "sg:city":"Lewistown",
    "sg:classifiers":[
        {
            "category":"Building & Trades",
            "subcategory":"Construction",
            "type":"Services"
        }
    ],
    "sg:phone":"+1 717 543 5234",
    "sg:postcode":"17044",
    "sg:province":"PA",
    "sg:tags":[
        "clearing",
        "land",
        "leveling"
    ],
    "wof:name":"John H Goss & Son Construction",
    "wof:placetype":"venue"
},
  "geometry": {"coordinates":[-77.48905999999999,40.6768],"type":"Point"}
}