{
  "type": "Feature",
  "properties": {
    "addr:full":"8000 Mcknight Rd Ste 1124 Pittsburgh PA 15237",
    "addr:housenumber":"8000",
    "addr:postcode":"15237",
    "addr:street":"Mcknight Rd Ste 1124",
    "iso:country":"US",
    "sg:address":"8000 Mcknight Rd Ste 1124",
    "sg:city":"Pittsburgh",
    "sg:classifiers":[
        {
            "category":"Personal",
            "subcategory":"Shoe Repair & Shine",
            "type":"Services"
        }
    ],
    "sg:phone":"+1 412 367 7977",
    "sg:postcode":"15237",
    "sg:province":"PA",
    "wof:name":"Northway Shoe & Repair",
    "wof:placetype":"venue"
},
  "geometry": {"coordinates":[-80.019249,40.550541],"type":"Point"}
}