{
  "type": "Feature",
  "properties": {
    "iso:country":"US",
    "sg:address":"5018 Buchanan Trl E",
    "sg:city":"Waynesboro",
    "sg:classifiers":[
        {
            "category":"Retail",
            "subcategory":"Auto Repair",
            "type":"Services"
        }
    ],
    "sg:phone":"+1 717 762 4521",
    "sg:postcode":"17268",
    "sg:province":"PA",
    "sg:tags":[
        "repairing",
        "automobile"
    ],
    "wof:name":"Veteran Car Care",
    "wof:placetype":"venue"
},
  "geometry": {"coordinates":[-77.625269,39.768794],"type":"Point"}
}