{
  "type": "Feature",
  "properties": {
    "addr:full":"1018 W Broad St Quakertown PA 18951",
    "addr:housenumber":"1018",
    "addr:postcode":"18951",
    "addr:street":"W Broad St",
    "iso:country":"US",
    "sg:address":"1018 W Broad St",
    "sg:city":"Quakertown",
    "sg:classifiers":[
        {
            "category":"Insurance",
            "subcategory":"Insurance Agent",
            "type":"Services"
        }
    ],
    "sg:phone":"+1 610 346 8523",
    "sg:postcode":"18951",
    "sg:province":"PA",
    "wof:name":"Hartman Insurance Agency",
    "wof:placetype":"venue"
},
  "geometry": {"coordinates":[-75.347787,40.442212],"type":"Point"}
}