{
  "type": "Feature",
  "properties": {
    "iso:country":"US",
    "sg:address":"1545 Brotherton Rd",
    "sg:city":"Berlin",
    "sg:classifiers":[
        {
            "category":"Farming",
            "subcategory":"Dairy Farm",
            "type":"Manufacturing & Wholesale Goods"
        }
    ],
    "sg:phone":"+1   ",
    "sg:postcode":"15530",
    "sg:province":"PA",
    "wof:name":"Upper Glade Farm",
    "wof:placetype":"venue"
},
  "geometry": {"coordinates":[-78.942131,39.977081],"type":"Point"}
}