{
  "type": "Feature",
  "properties": {
    "addr:full":"913 Main St Honesdale PA 18431",
    "addr:housenumber":"913",
    "addr:postcode":"18431",
    "addr:street":"Main St",
    "iso:country":"US",
    "sg:address":"913 Main St",
    "sg:city":"Honesdale",
    "sg:classifiers":[
        {
            "category":"Bars & Pubs",
            "type":"Food & Drink"
        }
    ],
    "sg:phone":"+1 570 253 9962",
    "sg:postcode":"18431",
    "sg:province":"PA",
    "sg:tags":[
        "drinking"
    ],
    "wof:name":"Leunes Tavern",
    "wof:placetype":"venue"
},
  "geometry": {"coordinates":[-75.25675200000001,41.574484],"type":"Point"}
}