{
  "type": "Feature",
  "properties": {
    "iso:country":"US",
    "sg:address":"19769 Camp Dr",
    "sg:city":"Saegertown",
    "sg:classifiers":[
        {
            "category":"Building & Trades",
            "subcategory":"Cleaning & Sanitation",
            "type":"Services"
        }
    ],
    "sg:phone":"+1 814 763 5646",
    "sg:postcode":"16433",
    "sg:province":"PA",
    "sg:tags":[
        "repair",
        "janitor",
        "maintenance"
    ],
    "wof:name":"Tri City Mobile Clean",
    "wof:placetype":"venue"
},
  "geometry": {"coordinates":[-80.146863,41.730058],"type":"Point"}
}