{
  "type": "Feature",
  "properties": {
    "addr:full":"500 E Luzerne St Philadelphia PA 19124",
    "addr:housenumber":"500",
    "addr:postcode":"19124",
    "addr:street":"E Luzerne St",
    "iso:country":"US",
    "sg:address":"500 E Luzerne St",
    "sg:city":"Philadelphia",
    "sg:classifiers":[
        {
            "category":"Manufacturing",
            "subcategory":"Apparel",
            "type":"Manufacturing & Wholesale Goods"
        }
    ],
    "sg:phone":"+1 215 425 6136",
    "sg:postcode":"19124",
    "sg:province":"PA",
    "sg:tags":[
        "clothing"
    ],
    "wof:name":"M Manufacturing Inc",
    "wof:placetype":"venue"
},
  "geometry": {"coordinates":[-75.112821,40.009007],"type":"Point"}
}