{
  "type": "Feature",
  "properties": {
    "addr:full":"14 Main St Wellsboro PA 16901",
    "addr:housenumber":"14",
    "addr:postcode":"16901",
    "addr:street":"Main St",
    "iso:country":"US",
    "sg:address":"14 Main St",
    "sg:city":"Wellsboro",
    "sg:classifiers":[
        {
            "category":"Government",
            "subcategory":"Post Office",
            "type":"Public Place"
        }
    ],
    "sg:phone":"+1 570 724 1690",
    "sg:postcode":"16901",
    "sg:province":"PA",
    "wof:name":"US Post Office",
    "wof:placetype":"venue"
},
  "geometry": {"coordinates":[-77.29924200000001,41.749682],"type":"Point"}
}