{
  "type": "Feature",
  "properties": {
    "iso:country":"US",
    "sg:address":"1831 Kenneth Ave",
    "sg:city":"New Kensington",
    "sg:classifiers":[
        {
            "category":"Health Services",
            "subcategory":"Chiropractor",
            "type":"Services"
        }
    ],
    "sg:phone":"+1   ",
    "sg:postcode":"15068",
    "sg:province":"PA",
    "wof:name":"Iozzi Lisa",
    "wof:placetype":"venue"
},
  "geometry": {"coordinates":[-79.76565600000001,40.579197],"type":"Point"}
}