{
  "type": "Feature",
  "properties": {
    "addr:full":"1 Williamsburg Pl Warrendale PA 15086",
    "addr:housenumber":"1",
    "addr:postcode":"15086",
    "addr:street":"Williamsburg Pl",
    "iso:country":"US",
    "sg:address":"1 Williamsburg Pl",
    "sg:city":"Warrendale",
    "sg:classifiers":[
        {
            "category":"Manufacturing",
            "subcategory":"Tools & Machinery",
            "type":"Manufacturing & Wholesale Goods"
        }
    ],
    "sg:phone":"+1   ",
    "sg:postcode":"15086",
    "sg:province":"PA",
    "sg:tags":[
        "carbon",
        "product",
        "mfg"
    ],
    "wof:name":"P A C C O International",
    "wof:placetype":"venue"
},
  "geometry": {"coordinates":[-80.087108,40.653589],"type":"Point"}
}