{
  "type": "Feature",
  "properties": {
    "iso:country":"US",
    "sg:address":"116 Kalmia Rd",
    "sg:city":"Tower City",
    "sg:classifiers":[
        {
            "category":"Food & Beverages",
            "subcategory":"Specialty",
            "type":"Retail Goods"
        }
    ],
    "sg:phone":"+1 717 647 2418",
    "sg:postcode":"17980",
    "sg:province":"PA",
    "sg:tags":[
        "water",
        "bulk",
        "company"
    ],
    "wof:name":"Stoney Mountain Springs",
    "wof:placetype":"venue"
},
  "geometry": {"coordinates":[-76.518558,40.578627],"type":"Point"}
}