{
  "type": "Feature",
  "properties": {
    "addr:full":"96 S George St York PA 17401",
    "addr:housenumber":"96",
    "addr:postcode":"17401",
    "addr:street":"S George St",
    "iso:country":"US",
    "sg:address":"96 S George St",
    "sg:city":"York",
    "sg:classifiers":[
        {
            "category":"Real Estate",
            "subcategory":"Developer",
            "type":"Services"
        }
    ],
    "sg:phone":"+1   ",
    "sg:postcode":"17401",
    "sg:province":"PA",
    "wof:name":"Gcw Properties Inc",
    "wof:placetype":"venue"
},
  "geometry": {"coordinates":[-76.727716,39.962466],"type":"Point"}
}