{
  "type": "Feature",
  "properties": {
    "iso:country":"US",
    "sg:address":"3310 N 9th St",
    "sg:city":"Philadelphia",
    "sg:classifiers":[
        {
            "category":"Professional",
            "type":"Services"
        }
    ],
    "sg:phone":"+1 215 228 2992",
    "sg:postcode":"19140",
    "sg:province":"PA",
    "sg:tags":[
        "establishment"
    ],
    "wof:name":"Korman Brothers Inc",
    "wof:placetype":"venue"
},
  "geometry": {"coordinates":[-75.14384,40.003452],"type":"Point"}
}