{
  "type": "Feature",
  "properties": {
    "addr:full":"9 N 2nd St Easton PA 18042",
    "addr:housenumber":"9",
    "addr:postcode":"18042",
    "addr:street":"N 2Nd St",
    "iso:country":"US",
    "sg:address":"9 N 2nd St",
    "sg:city":"Easton",
    "sg:classifiers":[
        {
            "category":"Manufacturing",
            "subcategory":"Printing",
            "type":"Manufacturing & Wholesale Goods"
        }
    ],
    "sg:phone":"+1   ",
    "sg:postcode":"18042",
    "sg:province":"PA",
    "sg:tags":[
        "commercial"
    ],
    "wof:name":"Write Touch",
    "wof:placetype":"venue"
},
  "geometry": {"coordinates":[-75.207097,40.691838],"type":"Point"}
}