{
  "type": "Feature",
  "properties": {
    "iso:country":"US",
    "sg:address":"145 Rector Street Manayunk",
    "sg:city":"Philadelphia",
    "sg:classifiers":[
        {
            "category":"Organizations",
            "subcategory":"Religious Organization",
            "type":"Services"
        }
    ],
    "sg:phone":"+1 215 482 4600",
    "sg:postcode":"19127",
    "sg:province":"PA",
    "sg:website":"www.stjohnmanayunk.org/",
    "wof:name":"St. John the Baptist RC church",
    "wof:placetype":"venue"
},
  "geometry": {"coordinates":[-75.220279,40.025089],"type":"Point"}
}