{
  "type": "Feature",
  "properties": {
    "iso:country":"US",
    "sg:address":"303 Main St",
    "sg:city":"Fayette City",
    "sg:classifiers":[
        {
            "category":"Organizations",
            "subcategory":"Labor Organization",
            "type":"Services"
        }
    ],
    "sg:phone":"+1 724 326 8248",
    "sg:postcode":"15438",
    "sg:province":"PA",
    "wof:name":"Local Union 3403",
    "wof:placetype":"venue"
},
  "geometry": {"coordinates":[-79.83906,40.098759],"type":"Point"}
}