{
  "type": "Feature",
  "properties": {
    "addr:full":"1524 Newport Rd Manheim PA 17545",
    "addr:housenumber":"1524",
    "addr:postcode":"17545",
    "addr:street":"Newport Rd",
    "iso:country":"US",
    "sg:address":"1524 Newport Rd",
    "sg:city":"Manheim",
    "sg:classifiers":[
        {
            "category":"Building & Trades",
            "subcategory":"Construction",
            "type":"Services"
        }
    ],
    "sg:phone":"+1 717 665 2727",
    "sg:postcode":"17545",
    "sg:province":"PA",
    "sg:tags":[
        "house"
    ],
    "wof:name":"Groff Custom Construction",
    "wof:placetype":"venue"
},
  "geometry": {"coordinates":[-76.37631500000001,40.207766],"type":"Point"}
}