{
  "type": "Feature",
  "properties": {
    "iso:country":"US",
    "sg:address":"4000 N Marshall St",
    "sg:city":"Philadelphia",
    "sg:classifiers":[
        {
            "category":"Health Services",
            "subcategory":"Doctor",
            "type":"Services"
        }
    ],
    "sg:phone":"+1 215 221 6545",
    "sg:postcode":"19140",
    "sg:province":"PA",
    "sg:tags":[
        "physician",
        "surgeon"
    ],
    "wof:name":"Chaudhry Ariz MD",
    "wof:placetype":"venue"
},
  "geometry": {"coordinates":[-75.138329,40.013822],"type":"Point"}
}