{
  "type": "Feature",
  "properties": {
    "addr:full":"275 Vincent Dr Honey Brook PA 19344",
    "addr:housenumber":"275",
    "addr:postcode":"19344",
    "addr:street":"Vincent Dr Honey Brook",
    "iso:country":"US",
    "sg:address":"275 Vincent Dr",
    "sg:city":"Honey Brook",
    "sg:classifiers":[
        {
            "category":"Professional",
            "type":"Services"
        }
    ],
    "sg:phone":"+1   ",
    "sg:postcode":"19344",
    "sg:province":"PA",
    "wof:name":"Scott Stilson Co",
    "wof:placetype":"venue"
},
  "geometry": {"coordinates":[-75.857709,40.109532],"type":"Point"}
}