{
  "type": "Feature",
  "properties": {
    "iso:country":"US",
    "sg:address":"100 Carson Ave",
    "sg:city":"Du Bois",
    "sg:classifiers":[
        {
            "category":"Retail",
            "subcategory":"Auto Repair",
            "type":"Services"
        }
    ],
    "sg:phone":"+1 814 371 4302",
    "sg:postcode":"15801",
    "sg:province":"PA",
    "sg:tags":[
        "body",
        "automobile",
        "painting"
    ],
    "wof:name":"Murray Ford Body Shop",
    "wof:placetype":"venue"
},
  "geometry": {"coordinates":[-78.77413799999999,41.111065],"type":"Point"}
}