{
  "type": "Feature",
  "properties": {
    "iso:country":"US",
    "sg:address":"1390 Mahoning St",
    "sg:city":"Lehighton",
    "sg:classifiers":[
        {
            "category":"Travel",
            "subcategory":"Travel Agent",
            "type":"Entertainment"
        }
    ],
    "sg:phone":"+1   ",
    "sg:postcode":"18235",
    "sg:province":"PA",
    "sg:tags":[
        "agency"
    ],
    "wof:name":"R/S Travel",
    "wof:placetype":"venue"
},
  "geometry": {"coordinates":[-75.72856299999999,40.829061],"type":"Point"}
}