{
  "type": "Feature",
  "properties": {
    "addr:full":"826 Bustleton Pike Feasterville Trevose PA 19053",
    "addr:housenumber":"826",
    "addr:postcode":"19053",
    "addr:street":"Bustleton Pike",
    "iso:country":"US",
    "sg:address":"826 Bustleton Pike",
    "sg:city":"Feasterville Trevose",
    "sg:classifiers":[
        {
            "category":"Professional",
            "subcategory":"Lawyer & Legal Services",
            "type":"Services"
        }
    ],
    "sg:phone":"+1   ",
    "sg:postcode":"19053",
    "sg:province":"PA",
    "wof:name":"Eisenberg Susan Levy Esq",
    "wof:placetype":"venue"
},
  "geometry": {"coordinates":[-75.003266,40.149115],"type":"Point"}
}