{
  "type": "Feature",
  "properties": {
    "iso:country":"US",
    "sg:address":"234 Main St",
    "sg:city":"Slatington",
    "sg:classifiers":[
        {
            "category":"Food & Beverages",
            "subcategory":"Liquor & Beverages",
            "type":"Retail Goods"
        }
    ],
    "sg:phone":"+1   ",
    "sg:postcode":"18080",
    "sg:province":"PA",
    "sg:tags":[
        "alcoholic"
    ],
    "wof:name":"Pops Beverage",
    "wof:placetype":"venue"
},
  "geometry": {"coordinates":[-75.606701,40.75263],"type":"Point"}
}