{
  "type": "Feature",
  "properties": {
    "addr:full":"214 Beaver Philipsburg PA 16866",
    "addr:housenumber":"214",
    "addr:postcode":"16866",
    "addr:street":"Beaver",
    "iso:country":"US",
    "sg:address":"214 Beaver",
    "sg:city":"Philipsburg",
    "sg:classifiers":[
        {
            "category":"Organizations",
            "subcategory":"Religious Organization",
            "type":"Services"
        }
    ],
    "sg:phone":"+1 814 342 3103",
    "sg:postcode":"16866",
    "sg:province":"PA",
    "wof:name":"First Baptist Church",
    "wof:placetype":"venue"
},
  "geometry": {"coordinates":[-78.220467,40.895515],"type":"Point"}
}