{
  "type": "Feature",
  "properties": {
    "iso:country":"US",
    "sg:address":"18 W Main St",
    "sg:city":"Ephrata",
    "sg:classifiers":[
        {
            "category":"Shopping",
            "subcategory":"Gifts & Souvenirs",
            "type":"Retail Goods"
        }
    ],
    "sg:phone":"+1 717 738 9023",
    "sg:postcode":"17522",
    "sg:province":"PA",
    "sg:tags":[
        "shop"
    ],
    "wof:name":"Christmas & More At Sheldons",
    "wof:placetype":"venue"
},
  "geometry": {"coordinates":[-76.178456,40.179374],"type":"Point"}
}