{
  "type": "Feature",
  "properties": {
    "iso:country":"US",
    "sg:address":"228 Desmond St",
    "sg:city":"Sayre",
    "sg:classifiers":[
        {
            "category":"Professional",
            "type":"Services"
        }
    ],
    "sg:phone":"+1   ",
    "sg:postcode":"18840",
    "sg:province":"PA",
    "wof:name":"Bradford County Indus Dev A",
    "wof:placetype":"venue"
},
  "geometry": {"coordinates":[-76.51549799999999,41.980106],"type":"Point"}
}