{
  "type": "Feature",
  "properties": {
    "iso:country":"US",
    "sg:address":"20 East General Robinson St",
    "sg:city":"Pittsburgh",
    "sg:classifiers":[
        {
            "category":"Bars & Pubs",
            "type":"Food & Drink"
        }
    ],
    "sg:phone":"+1 412 325 2601",
    "sg:postcode":"15222",
    "sg:province":"PA",
    "sg:website":"www.finniganspittsburgh.com",
    "wof:name":"Finnegan's Wake",
    "wof:placetype":"venue"
},
  "geometry": {"coordinates":[-80.003502,40.448601],"type":"Point"}
}