{
  "type": "Feature",
  "properties": {
    "iso:country":"US",
    "sg:address":"93 Village Ln",
    "sg:city":"Levittown",
    "sg:classifiers":[
        {
            "category":"Manufacturing",
            "subcategory":"Signs",
            "type":"Manufacturing & Wholesale Goods"
        }
    ],
    "sg:phone":"+1   ",
    "sg:postcode":"19054",
    "sg:province":"PA",
    "sg:tags":[
        "specialty",
        "mfg"
    ],
    "wof:name":"KMC Lttring Pin Striping Signs",
    "wof:placetype":"venue"
},
  "geometry": {"coordinates":[-74.832881,40.179363],"type":"Point"}
}