{
  "type": "Feature",
  "properties": {
    "iso:country":"US",
    "sg:address":"5884 Ellsworth Ave",
    "sg:city":"Pittsburgh",
    "sg:classifiers":[
        {
            "category":"Shopping",
            "type":"Retail Goods"
        }
    ],
    "sg:phone":"+1 412 661 5800",
    "sg:postcode":"15232",
    "sg:province":"PA",
    "sg:tags":[
        "art",
        "gallery",
        "dealer"
    ],
    "wof:name":"Photo Forum",
    "wof:placetype":"venue"
},
  "geometry": {"coordinates":[-79.928676,40.457407],"type":"Point"}
}