{
  "type": "Feature",
  "properties": {
    "addr:full":"254 Green St Mifflinburg PA 17844",
    "addr:housenumber":"254",
    "addr:postcode":"17844",
    "addr:street":"Green St",
    "iso:country":"US",
    "sg:address":"254 Green St",
    "sg:city":"Mifflinburg",
    "sg:classifiers":[
        {
            "category":"Building & Trades",
            "subcategory":"Construction",
            "type":"Services"
        }
    ],
    "sg:phone":"+1 570 966 7967",
    "sg:postcode":"17844",
    "sg:province":"PA",
    "sg:tags":[
        "siding",
        "contractor"
    ],
    "wof:name":"Raymer & Sons Vinyl Siding",
    "wof:placetype":"venue"
},
  "geometry": {"coordinates":[-77.044478,40.916988],"type":"Point"}
}