{
  "type": "Feature",
  "properties": {
    "iso:country":"US",
    "sg:address":"1813 W State St",
    "sg:city":"New Castle",
    "sg:classifiers":[
        {
            "category":"Manufacturing",
            "subcategory":"Metals",
            "type":"Manufacturing & Wholesale Goods"
        }
    ],
    "sg:phone":"+1 724 652 8715",
    "sg:postcode":"16101",
    "sg:province":"PA",
    "wof:name":"J D Franklin & Assoc",
    "wof:placetype":"venue"
},
  "geometry": {"coordinates":[-80.37541899999999,41.006162],"type":"Point"}
}