{
  "type": "Feature",
  "properties": {
    "addr:full":"301 W Lancaster Ave Shillington PA 19607",
    "addr:housenumber":"301",
    "addr:postcode":"19607",
    "addr:street":"W Lancaster Ave",
    "iso:country":"US",
    "sg:address":"301 W Lancaster Ave",
    "sg:city":"Shillington",
    "sg:classifiers":[
        {
            "category":"Government",
            "subcategory":"Office",
            "type":"Public Place"
        }
    ],
    "sg:phone":"+1 610 373 8310",
    "sg:postcode":"19607",
    "sg:province":"PA",
    "sg:tags":[
        "county"
    ],
    "wof:name":"Berks County YAP",
    "wof:placetype":"venue"
},
  "geometry": {"coordinates":[-75.972983,40.304976],"type":"Point"}
}