{
  "type": "Feature",
  "properties": {
    "iso:country":"US",
    "sg:address":"1563 Bend Rd",
    "sg:city":"Mercer",
    "sg:classifiers":[
        {
            "category":"Farming",
            "subcategory":"Livestock Farm",
            "type":"Manufacturing & Wholesale Goods"
        }
    ],
    "sg:phone":"+1   ",
    "sg:postcode":"16137",
    "sg:province":"PA",
    "sg:tags":[
        "beef",
        "feedlot",
        "cattle"
    ],
    "wof:name":"John Jewell",
    "wof:placetype":"venue"
},
  "geometry": {"coordinates":[-80.33506800000001,41.245084],"type":"Point"}
}