{
  "type": "Feature",
  "properties": {
    "addr:full":"1097 North Ave Millvale PA 15209",
    "addr:housenumber":"1097",
    "addr:postcode":"15209",
    "addr:street":"North Ave",
    "iso:country":"US",
    "sg:address":"1097 North Ave",
    "sg:city":"Millvale",
    "sg:classifiers":[
        {
            "category":"Health Services",
            "subcategory":"Doctor",
            "type":"Services"
        }
    ],
    "sg:phone":"+1 412 821 1333",
    "sg:postcode":"15209",
    "sg:province":"PA",
    "sg:tags":[
        "dentist"
    ],
    "wof:name":"Joseph Horne DMD",
    "wof:placetype":"venue"
},
  "geometry": {"coordinates":[-79.972774,40.491071],"type":"Point"}
}