{
  "type": "Feature",
  "properties": {
    "iso:country":"US",
    "sg:address":"105 Cedar Ln",
    "sg:city":"Chester Springs",
    "sg:classifiers":[
        {
            "category":"Building & Trades",
            "subcategory":"Construction",
            "type":"Services"
        }
    ],
    "sg:phone":"+1 610 458 8520",
    "sg:postcode":"19425",
    "sg:province":"PA",
    "sg:tags":[
        "general",
        "contractor"
    ],
    "sg:website":"www.tlcremodeling.com",
    "wof:name":"TLC Remodeling",
    "wof:placetype":"venue"
},
  "geometry": {"coordinates":[-75.695629,40.107869],"type":"Point"}
}