{
  "type": "Feature",
  "properties": {
    "addr:full":"2000 Bennett Rd Philadelphia PA 19116",
    "addr:housenumber":"2000",
    "addr:postcode":"19116",
    "addr:street":"Bennett Rd",
    "iso:country":"US",
    "sg:address":"2000 Bennett Rd",
    "sg:city":"Philadelphia",
    "sg:classifiers":[
        {
            "category":"Utilities",
            "subcategory":"Telephone",
            "type":"Services"
        }
    ],
    "sg:phone":"+1 215 934 7500",
    "sg:postcode":"19116",
    "sg:province":"PA",
    "sg:tags":[
        "systems-wholesale",
        "manufacturer",
        "system",
        "equipment"
    ],
    "sg:website":"http://www.nationalofficeequipment.com",
    "wof:name":"National Office Equipment Company",
    "wof:placetype":"venue"
},
  "geometry": {"coordinates":[-75.010406,40.108391],"type":"Point"}
}