{
  "type": "Feature",
  "properties": {
    "addr:full":"1090 Macarthur Rd Whitehall PA 18052",
    "addr:housenumber":"1090",
    "addr:postcode":"18052",
    "addr:street":"Macarthur Rd",
    "iso:country":"US",
    "sg:address":"1090 Macarthur Rd",
    "sg:city":"Whitehall",
    "sg:classifiers":[
        {
            "category":"Retail",
            "subcategory":"Auto Rental",
            "type":"Services"
        }
    ],
    "sg:phone":"+1 610 434 7601",
    "sg:postcode":"18052",
    "sg:province":"PA",
    "sg:tags":[
        "renting",
        "truck",
        "leasing"
    ],
    "wof:name":"U-Haul Co",
    "wof:placetype":"venue"
},
  "geometry": {"coordinates":[-75.47883299999999,40.617044],"type":"Point"}
}