{
  "type": "Feature",
  "properties": {
    "iso:country":"US",
    "sg:address":"330 Schantz Rd",
    "sg:city":"Allentown",
    "sg:classifiers":[
        {
            "category":"Building & Trades",
            "subcategory":"Construction",
            "type":"Services"
        }
    ],
    "sg:phone":"+1   ",
    "sg:postcode":"18104",
    "sg:province":"PA",
    "sg:tags":[
        "contractor"
    ],
    "wof:name":"Revahs",
    "wof:placetype":"venue"
},
  "geometry": {"coordinates":[-75.552196,40.569277],"type":"Point"}
}