{
  "type": "Feature",
  "properties": {
    "addr:full":"500 Penn St Reading PA 19602",
    "addr:housenumber":"500",
    "addr:postcode":"19602",
    "addr:street":"Penn St",
    "iso:country":"US",
    "sg:address":"500 Penn St",
    "sg:city":"Reading",
    "sg:classifiers":[
        {
            "category":"Restaurant",
            "type":"Food & Drink"
        }
    ],
    "sg:phone":"+1 610 376 5191",
    "sg:postcode":"19602",
    "sg:province":"PA",
    "wof:name":"Mc Donald's",
    "wof:placetype":"venue"
},
  "geometry": {"coordinates":[-75.927876,40.335315],"type":"Point"}
}