{
  "type": "Feature",
  "properties": {
    "addr:full":"1856 Old York Rd Abington PA 19001",
    "addr:housenumber":"1856",
    "addr:postcode":"19001",
    "addr:street":"Old York Rd",
    "iso:country":"US",
    "sg:address":"1856 Old York Rd",
    "sg:city":"Abington",
    "sg:classifiers":[
        {
            "category":"Building & Trades",
            "subcategory":"Construction",
            "type":"Services"
        }
    ],
    "sg:phone":"+1   ",
    "sg:postcode":"19001",
    "sg:province":"PA",
    "sg:tags":[
        "carpentry",
        "contractor"
    ],
    "wof:name":"Hayes Gmzik Cstm Crpntry Rnova",
    "wof:placetype":"venue"
},
  "geometry": {"coordinates":[-75.113738,40.137026],"type":"Point"}
}