{
  "type": "Feature",
  "properties": {
    "iso:country":"US",
    "sg:address":"1220 Industrial Dr",
    "sg:city":"Erie",
    "sg:classifiers":[
        {
            "category":"Manufacturing",
            "subcategory":"Metals",
            "type":"Manufacturing & Wholesale Goods"
        }
    ],
    "sg:phone":"+1 814 833 9045",
    "sg:postcode":"16505",
    "sg:province":"PA",
    "sg:tags":[
        "electroplating"
    ],
    "sg:website":"www.mcmetal.com",
    "wof:name":"Millcreek Metal Finishing Inc",
    "wof:placetype":"venue"
},
  "geometry": {"coordinates":[-80.138378,42.100463],"type":"Point"}
}