{
  "type": "Feature",
  "properties": {
    "iso:country":"US",
    "sg:address":"157 Easton Rd",
    "sg:city":"Horsham",
    "sg:classifiers":[
        {
            "category":"Retail",
            "subcategory":"Auto Repair",
            "type":"Services"
        }
    ],
    "sg:phone":"+1 215 957 7958",
    "sg:postcode":"19044",
    "sg:province":"PA",
    "sg:tags":[
        "transmission"
    ],
    "wof:name":"Transco Transmission Ctrs",
    "wof:placetype":"venue"
},
  "geometry": {"coordinates":[-75.12791300000001,40.171763],"type":"Point"}
}