{
  "type": "Feature",
  "properties": {
    "addr:full":"740 Hillview Ave Latrobe PA 15650",
    "addr:housenumber":"740",
    "addr:postcode":"15650",
    "addr:street":"Hillview Ave",
    "iso:country":"US",
    "sg:address":"740 Hillview Ave",
    "sg:city":"Latrobe",
    "sg:classifiers":[
        {
            "category":"Autos & Motor Vehicles",
            "subcategory":"Automobile Sales",
            "type":"Retail Goods"
        }
    ],
    "sg:phone":"+1 724 537 9209",
    "sg:postcode":"15650",
    "sg:province":"PA",
    "sg:tags":[
        "car",
        "dealer"
    ],
    "wof:name":"Howard Johnson Auto",
    "wof:placetype":"venue"
},
  "geometry": {"coordinates":[-79.360668,40.310838],"type":"Point"}
}