{
  "type": "Feature",
  "properties": {
    "iso:country":"US",
    "sg:address":"1515 Lititz Rd",
    "sg:city":"Manheim",
    "sg:classifiers":[
        {
            "category":"Building & Trades",
            "subcategory":"Construction",
            "type":"Services"
        }
    ],
    "sg:phone":"+1 717 397 8818",
    "sg:postcode":"17545",
    "sg:province":"PA",
    "sg:tags":[
        "general",
        "contractor"
    ],
    "wof:name":"A C Moore Custom Framing",
    "wof:placetype":"venue"
},
  "geometry": {"coordinates":[-76.376017,40.120222],"type":"Point"}
}