{
  "type": "Feature",
  "properties": {
    "addr:full":"835 N Chatham Rd West Grove PA 19390",
    "addr:housenumber":"835",
    "addr:postcode":"19390",
    "addr:street":"N Chatham Rd",
    "iso:country":"US",
    "sg:address":"835 N Chatham Rd",
    "sg:city":"West Grove",
    "sg:classifiers":[
        {
            "category":"Museum",
            "type":"Entertainment"
        }
    ],
    "sg:phone":"+1   ",
    "sg:postcode":"19390",
    "sg:province":"PA",
    "sg:tags":[
        "art",
        "gallery"
    ],
    "wof:name":"Primitive Hall Museum",
    "wof:placetype":"venue"
},
  "geometry": {"coordinates":[-75.831075,39.873376],"type":"Point"}
}