{
  "type": "Feature",
  "properties": {
    "addr:full":"121 Virginia Ln Meyersdale PA 15552",
    "addr:housenumber":"121",
    "addr:postcode":"15552",
    "addr:street":"Virginia Ln",
    "iso:country":"US",
    "sg:address":"121 Virginia Ln",
    "sg:city":"Meyersdale",
    "sg:classifiers":[
        {
            "category":"Building & Trades",
            "subcategory":"Plumbing",
            "type":"Services"
        }
    ],
    "sg:phone":"+1   ",
    "sg:postcode":"15552",
    "sg:province":"PA",
    "sg:tags":[
        "contractor"
    ],
    "wof:name":"Hersch Heating Refrig",
    "wof:placetype":"venue"
},
  "geometry": {"coordinates":[-78.96158699999999,39.798264],"type":"Point"}
}