{
  "type": "Feature",
  "properties": {
    "addr:full":"132 E 2nd St Mt Carmel PA 17851",
    "addr:housenumber":"132",
    "addr:postcode":"17851",
    "addr:street":"E 2Nd St",
    "iso:country":"US",
    "sg:address":"132 E 2nd St",
    "sg:city":"Mt Carmel",
    "sg:classifiers":[
        {
            "category":"Building & Trades",
            "subcategory":"Construction",
            "type":"Services"
        }
    ],
    "sg:phone":"+1 570 339 3330",
    "sg:postcode":"17851",
    "sg:province":"PA",
    "sg:tags":[
        "general",
        "contractor"
    ],
    "wof:name":"D A Kessler Construction Co",
    "wof:placetype":"venue"
},
  "geometry": {"coordinates":[-76.41155999999999,40.798195],"type":"Point"}
}