{
  "type": "Feature",
  "properties": {
    "iso:country":"US",
    "sg:address":"60 N Bacton Hill Rd",
    "sg:city":"Malvern",
    "sg:classifiers":[
        {
            "category":"Utilities",
            "subcategory":"Natural Gas",
            "type":"Services"
        }
    ],
    "sg:phone":"+1   ",
    "sg:postcode":"19355",
    "sg:province":"PA",
    "sg:tags":[
        "transmission"
    ],
    "wof:name":"Transco",
    "wof:placetype":"venue"
},
  "geometry": {"coordinates":[-75.58139799999999,40.045241],"type":"Point"}
}