{
  "type": "Feature",
  "properties": {
    "addr:full":"5 Ferry St Leetsdale PA 15056",
    "addr:housenumber":"5",
    "addr:postcode":"15056",
    "addr:street":"Ferry St",
    "iso:country":"US",
    "sg:address":"5 Ferry St",
    "sg:city":"Leetsdale",
    "sg:classifiers":[
        {
            "category":"Freight",
            "type":"Transportation"
        }
    ],
    "sg:phone":"+1 724 266 2450",
    "sg:postcode":"15056",
    "sg:province":"PA",
    "sg:tags":[
        "warehouse",
        "self",
        "storage"
    ],
    "sg:website":"www.buncher.com",
    "wof:name":"Buncher Co",
    "wof:placetype":"venue"
},
  "geometry": {"coordinates":[-80.206418,40.564363],"type":"Point"}
}