{
  "type": "Feature",
  "properties": {
    "addr:full":"836 W 8th St Lansdale PA 19446",
    "addr:housenumber":"836",
    "addr:postcode":"19446",
    "addr:street":"W 8Th St",
    "iso:country":"US",
    "sg:address":"836 W 8th St",
    "sg:city":"Lansdale",
    "sg:classifiers":[
        {
            "category":"Manufacturing",
            "subcategory":"Tools & Machinery",
            "type":"Manufacturing & Wholesale Goods"
        }
    ],
    "sg:phone":"+1   ",
    "sg:postcode":"19446",
    "sg:province":"PA",
    "sg:tags":[
        "environmental",
        "mfg",
        "devices",
        "con"
    ],
    "wof:name":"Probes Unlimited Inc",
    "wof:placetype":"venue"
},
  "geometry": {"coordinates":[-75.292176,40.256377],"type":"Point"}
}