{
  "type": "Feature",
  "properties": {
    "addr:full":"3749 Zimmerly Rd Erie PA 16506",
    "addr:housenumber":"3749",
    "addr:postcode":"16506",
    "addr:street":"Zimmerly Rd",
    "iso:country":"US",
    "sg:address":"3749 Zimmerly Rd",
    "sg:city":"Erie",
    "sg:classifiers":[
        {
            "category":"Travel",
            "subcategory":"Campground",
            "type":"Entertainment"
        }
    ],
    "sg:phone":"+1 814 833 6035",
    "sg:postcode":"16506",
    "sg:province":"PA",
    "wof:name":"Cassidy's Presque Isle Trailer",
    "wof:placetype":"venue"
},
  "geometry": {"coordinates":[-80.143068,42.056405],"type":"Point"}
}