{
  "type": "Feature",
  "properties": {
    "addr:full":"5727 Villa Haven Dr Pittsburgh PA 15236",
    "addr:housenumber":"5727",
    "addr:postcode":"15236",
    "addr:street":"Villa Haven Dr",
    "iso:country":"US",
    "sg:address":"5727 Villa Haven Dr",
    "sg:city":"Pittsburgh",
    "sg:classifiers":[
        {
            "category":"Structure",
            "subcategory":"Office Building",
            "type":"Public Place"
        }
    ],
    "sg:phone":"+1 412 952 6000",
    "sg:postcode":"15236",
    "sg:province":"PA",
    "sg:tags":[
        "park"
    ],
    "wof:name":"Lanial Properties",
    "wof:placetype":"venue"
},
  "geometry": {"coordinates":[-80.012207,40.348103],"type":"Point"}
}