{
  "type": "Feature",
  "properties": {
    "iso:country":"US",
    "sg:address":"28 Baird Ave",
    "sg:city":"Slovan",
    "sg:classifiers":[
        {
            "category":"Manufacturing",
            "subcategory":"Tools & Machinery",
            "type":"Manufacturing & Wholesale Goods"
        }
    ],
    "sg:phone":"+1 724 947 9397",
    "sg:postcode":"15078",
    "sg:province":"PA",
    "sg:tags":[
        "machine",
        "shop"
    ],
    "sg:website":"www.testa-machine.com",
    "wof:name":"Testa Machine Co",
    "wof:placetype":"venue"
},
  "geometry": {"coordinates":[-80.388249,40.360053],"type":"Point"}
}