{
  "type": "Feature",
  "properties": {
    "iso:country":"US",
    "sg:address":"618 Sheffield Ave",
    "sg:city":"Aliquippa",
    "sg:classifiers":[
        {
            "category":"Wholesale",
            "subcategory":"Beer",
            "type":"Manufacturing & Wholesale Goods"
        }
    ],
    "sg:phone":"+1 724 375 7743",
    "sg:postcode":"15001",
    "sg:province":"PA",
    "sg:tags":[
        "ale",
        "alcoholic",
        "beverage"
    ],
    "wof:name":"Aliquippa Beer Distributor",
    "wof:placetype":"venue"
},
  "geometry": {"coordinates":[-80.251892,40.613955],"type":"Point"}
}