{
  "type": "Feature",
  "properties": {
    "iso:country":"US",
    "sg:address":"342 Montgomery Ave ",
    "sg:city":"Merion Station",
    "sg:classifiers":[
        {
            "category":"Restaurant",
            "type":"Food & Drink"
        }
    ],
    "sg:menulink":"http://www.allmenus.com/pa/lower-merion/291306-hymies-merion/menu/",
    "sg:phone":"+1 610 664 3544",
    "sg:postcode":"19066",
    "sg:province":"PA",
    "sg:tags":[
        "soup",
        "american",
        "sandwich",
        "salad"
    ],
    "wof:name":"Hymie's Merion",
    "wof:placetype":"venue"
},
  "geometry": {"coordinates":[-75.243871,40.005664],"type":"Point"}
}