{
  "type": "Feature",
  "properties": {
    "iso:country":"US",
    "sg:address":"10040 Timbarra Ct",
    "sg:city":"Wexford",
    "sg:classifiers":[
        {
            "category":"Professional",
            "subcategory":"Business Services",
            "type":"Services"
        }
    ],
    "sg:phone":"+1 724 335 2059",
    "sg:postcode":"15090",
    "sg:province":"PA",
    "sg:tags":[
        "holding"
    ],
    "wof:name":"Armada Group Ltd",
    "wof:placetype":"venue"
},
  "geometry": {"coordinates":[-80.05155999999999,40.595818],"type":"Point"}
}