{
  "type": "Feature",
  "properties": {
    "iso:country":"US",
    "sg:address":"62 Pitney Rd",
    "sg:city":"Lancaster",
    "sg:classifiers":[
        {
            "category":"Professional",
            "subcategory":"Management & Consulting",
            "type":"Services"
        }
    ],
    "sg:phone":"+1 717 299 2199",
    "sg:postcode":"17602",
    "sg:province":"PA",
    "sg:tags":[
        "communications",
        "consultant"
    ],
    "wof:name":"Scheid Technology",
    "wof:placetype":"venue"
},
  "geometry": {"coordinates":[-76.271953,40.038108],"type":"Point"}
}