{
  "type": "Feature",
  "properties": {
    "iso:country":"US",
    "sg:address":"1919 W Chestnut St",
    "sg:city":"Washington",
    "sg:classifiers":[
        {
            "category":"Health Services",
            "subcategory":"Chiropractor",
            "type":"Services"
        }
    ],
    "sg:phone":"+1 724 223 1441",
    "sg:postcode":"15301",
    "sg:province":"PA",
    "wof:name":"Giles Chiropractic Ctr",
    "wof:placetype":"venue"
},
  "geometry": {"coordinates":[-80.280278,40.162057],"type":"Point"}
}