{
  "type": "Feature",
  "properties": {
    "iso:country":"US",
    "sg:address":"103 N Mansard St",
    "sg:city":"Martinsburg",
    "sg:classifiers":[
        {
            "category":"Autos & Motor Vehicles",
            "subcategory":"Automobile Sales",
            "type":"Retail Goods"
        }
    ],
    "sg:phone":"+1 814 793 2951",
    "sg:postcode":"16662",
    "sg:province":"PA",
    "sg:tags":[
        "car",
        "dealer"
    ],
    "wof:name":"Smith's Used Cars",
    "wof:placetype":"venue"
},
  "geometry": {"coordinates":[-78.33130800000001,40.315516],"type":"Point"}
}