{
  "type": "Feature",
  "properties": {
    "iso:country":"US",
    "sg:address":"101 Jolly School Rd",
    "sg:city":"Washington",
    "sg:classifiers":[
        {
            "category":"Manufacturing",
            "subcategory":"Retail Goods",
            "type":"Manufacturing & Wholesale Goods"
        }
    ],
    "sg:phone":"+1   ",
    "sg:postcode":"15301",
    "sg:province":"PA",
    "sg:tags":[
        "product",
        "mfg"
    ],
    "wof:name":"Appalachian Industries Inc",
    "wof:placetype":"venue"
},
  "geometry": {"coordinates":[-80.30978399999999,40.127334],"type":"Point"}
}