{
  "type": "Feature",
  "properties": {
    "iso:country":"US",
    "sg:address":"108 Clover Rd",
    "sg:city":"State College",
    "sg:classifiers":[
        {
            "category":"Restaurant",
            "type":"Food & Drink"
        }
    ],
    "sg:phone":"+1 814 238 7710",
    "sg:postcode":"16801",
    "sg:province":"PA",
    "sg:tags":[
        "delivery"
    ],
    "wof:name":"Food Express",
    "wof:placetype":"venue"
},
  "geometry": {"coordinates":[-77.82683400000001,40.812463],"type":"Point"}
}