{
  "type": "Feature",
  "properties": {
    "addr:full":"731 Copeland St Pittsburgh PA 15232",
    "addr:housenumber":"731",
    "addr:postcode":"15232",
    "addr:street":"Copeland St",
    "iso:country":"US",
    "sg:address":"731 Copeland St",
    "sg:city":"Pittsburgh",
    "sg:classifiers":[
        {
            "category":"Organizations",
            "subcategory":"Non-profit Organization",
            "type":"Services"
        }
    ],
    "sg:phone":"+1   ",
    "sg:postcode":"15232",
    "sg:province":"PA",
    "sg:tags":[
        "gallery",
        "social"
    ],
    "wof:name":"Shadyside Summer Arts Festival",
    "wof:placetype":"venue"
},
  "geometry": {"coordinates":[-79.934669,40.450879],"type":"Point"}
}