{
  "type": "Feature",
  "properties": {
    "iso:country":"US",
    "sg:address":"216 Whitmore St",
    "sg:city":"Jermyn",
    "sg:classifiers":[
        {
            "category":"Shopping",
            "type":"Retail Goods"
        },
        {
            "category":"Manufacturing",
            "subcategory":"Apparel",
            "type":"Manufacturing & Wholesale Goods"
        }
    ],
    "sg:phone":"+1 570 876 0350",
    "sg:postcode":"18433",
    "sg:province":"PA",
    "sg:tags":[
        "awning",
        "product",
        "canopy",
        "mfg"
    ],
    "wof:name":"John Reeves & Sons Awning",
    "wof:placetype":"venue"
},
  "geometry": {"coordinates":[-75.545365,41.536587],"type":"Point"}
}