{
  "type": "Feature",
  "properties": {
    "addr:full":"500 Hospital Way Monroeville PA 15132",
    "addr:housenumber":"500",
    "addr:postcode":"15132",
    "addr:street":"Hospital Way",
    "iso:country":"US",
    "sg:address":"500 Hospital Way",
    "sg:city":"Monroeville",
    "sg:classifiers":[
        {
            "category":"Health Services",
            "subcategory":"Health Practitioner",
            "type":"Services"
        }
    ],
    "sg:phone":"+1   ",
    "sg:postcode":"15132",
    "sg:province":"PA",
    "wof:name":"Bondi Hnlon Fnash Srgcal Assoc",
    "wof:placetype":"venue"
},
  "geometry": {"coordinates":[-79.84952,40.350072],"type":"Point"}
}