{
  "type": "Feature",
  "properties": {
    "addr:full":"1143 Harrisburg Pike Carlisle PA 17013",
    "addr:housenumber":"1143",
    "addr:postcode":"17013",
    "addr:street":"Harrisburg Pike",
    "iso:country":"US",
    "sg:address":"1143 Harrisburg Pike",
    "sg:city":"Carlisle",
    "sg:classifiers":[
        {
            "category":"Autos & Motor Vehicles",
            "subcategory":"Automobile Sales",
            "type":"Retail Goods"
        }
    ],
    "sg:phone":"+1 215 243 7485",
    "sg:postcode":"17013",
    "sg:province":"PA",
    "sg:tags":[
        "new",
        "car"
    ],
    "wof:name":"Varsity Volkswagen, Inc",
    "wof:placetype":"venue"
},
  "geometry": {"coordinates":[-77.154867,40.225476],"type":"Point"}
}