{
  "type": "Feature",
  "properties": {
    "iso:country":"US",
    "sg:address":"822 N Oswego St",
    "sg:city":"Allentown",
    "sg:classifiers":[
        {
            "category":"Personal",
            "subcategory":"Beauty Salon",
            "type":"Services"
        }
    ],
    "sg:phone":"+1 610 776 7877",
    "sg:postcode":"18109",
    "sg:province":"PA",
    "wof:name":"Beauti Techniques",
    "wof:placetype":"venue"
},
  "geometry": {"coordinates":[-75.433319,40.622276],"type":"Point"}
}