{
  "type": "Feature",
  "properties": {
    "addr:full":"208 Lycoming Mall Dr Muncy PA 17756",
    "addr:housenumber":"208",
    "addr:postcode":"17756",
    "addr:street":"Lycoming Mall Dr Muncy",
    "iso:country":"US",
    "sg:address":"208 Lycoming Mall Dr",
    "sg:city":"Muncy",
    "sg:classifiers":[
        {
            "category":"Shopping",
            "subcategory":"Jewelry",
            "type":"Retail Goods"
        }
    ],
    "sg:phone":"+1   ",
    "sg:postcode":"17756",
    "sg:province":"PA",
    "wof:name":"Marshall Arts",
    "wof:placetype":"venue"
},
  "geometry": {"coordinates":[-76.813107,41.236841],"type":"Point"}
}