{
  "type": "Feature",
  "properties": {
    "addr:full":"607 Harrison Ave Jeannette PA 15644",
    "addr:housenumber":"607",
    "addr:postcode":"15644",
    "addr:street":"Harrison Ave",
    "iso:country":"US",
    "sg:address":"607 Harrison Ave",
    "sg:city":"Jeannette",
    "sg:classifiers":[
        {
            "category":"Personal",
            "type":"Services"
        }
    ],
    "sg:phone":"+1   ",
    "sg:postcode":"15644",
    "sg:province":"PA",
    "wof:name":"Janets Sun Paradise",
    "wof:placetype":"venue"
},
  "geometry": {"coordinates":[-79.60656899999999,40.333159],"type":"Point"}
}