{
  "type": "Feature",
  "properties": {
    "iso:country":"US",
    "sg:address":"39 N Washington St",
    "sg:city":"Gettysburg",
    "sg:classifiers":[
        {
            "category":"Banks & Credit Unions",
            "subcategory":"Bank",
            "type":"Services"
        }
    ],
    "sg:phone":"+1 717 337 3474",
    "sg:postcode":"17325",
    "sg:province":"PA",
    "sg:tags":[
        "state"
    ],
    "wof:name":"Bellco Community Credit Union",
    "wof:placetype":"venue"
},
  "geometry": {"coordinates":[-77.233249,39.831057],"type":"Point"}
}