{
  "type": "Feature",
  "properties": {
    "addr:full":"2735 N Broad St Philadelphia PA 19132",
    "addr:housenumber":"2735",
    "addr:postcode":"19132",
    "addr:street":"N Broad St",
    "iso:country":"US",
    "sg:address":"2735 N Broad St",
    "sg:city":"Philadelphia",
    "sg:classifiers":[
        {
            "category":"Personal",
            "subcategory":"Barber",
            "type":"Services"
        }
    ],
    "sg:phone":"+1 215 226 3349",
    "sg:postcode":"19132",
    "sg:province":"PA",
    "wof:name":"Spruill Ida",
    "wof:placetype":"venue"
},
  "geometry": {"coordinates":[-75.154404,39.995098],"type":"Point"}
}