{
  "type": "Feature",
  "properties": {
    "iso:country":"US",
    "sg:address":"2919 Saw Mill Run Blvd",
    "sg:city":"Pittsburgh",
    "sg:classifiers":[
        {
            "category":"Cinema",
            "subcategory":"Movie Rental",
            "type":"Entertainment"
        }
    ],
    "sg:phone":"+1 412 884 5682",
    "sg:postcode":"15227",
    "sg:province":"PA",
    "sg:tags":[
        "game",
        "video"
    ],
    "sg:website":"www.familyvideo.com",
    "wof:name":"Family Video",
    "wof:placetype":"venue"
},
  "geometry": {"coordinates":[-79.98649899999999,40.377416],"type":"Point"}
}