{
  "type": "Feature",
  "properties": {
    "iso:country":"US",
    "sg:address":"50 Wood Corner Rd",
    "sg:city":"Lititz",
    "sg:classifiers":[
        {
            "category":"Home & Garden",
            "subcategory":"Hardware",
            "type":"Retail Goods"
        }
    ],
    "sg:phone":"+1 717 738 7350",
    "sg:postcode":"17543",
    "sg:province":"PA",
    "sg:website":"www.pbzinc.com",
    "wof:name":"Paul B Zimmerman Inc",
    "wof:placetype":"venue"
},
  "geometry": {"coordinates":[-76.21986,40.205017],"type":"Point"}
}