{
  "type": "Feature",
  "properties": {
    "iso:country":"US",
    "sg:address":"2044 Karen Dr",
    "sg:city":"Pittsburgh",
    "sg:classifiers":[
        {
            "category":"Professional",
            "subcategory":"Computer Services",
            "type":"Services"
        }
    ],
    "sg:phone":"+1   ",
    "sg:postcode":"15237",
    "sg:province":"PA",
    "sg:tags":[
        "related",
        "business"
    ],
    "wof:name":"Solutions4networks Inc",
    "wof:placetype":"venue"
},
  "geometry": {"coordinates":[-80.068592,40.544745],"type":"Point"}
}