{
  "type": "Feature",
  "properties": {
    "iso:country":"US",
    "sg:address":"118 Grape St",
    "sg:city":"Philadelphia",
    "sg:classifiers":[
        {
            "category":"Retail",
            "subcategory":"Funeral Services",
            "type":"Services"
        }
    ],
    "sg:phone":"+1 215 483 1916",
    "sg:postcode":"19127",
    "sg:province":"PA",
    "sg:tags":[
        "cemetery"
    ],
    "wof:name":"Modzianowski Jj Funeral Home",
    "wof:placetype":"venue"
},
  "geometry": {"coordinates":[-75.2229,40.026001],"type":"Point"}
}