{
  "type": "Feature",
  "properties": {
    "addr:full":"208 S Main St Coudersport PA 16915",
    "addr:housenumber":"208",
    "addr:postcode":"16915",
    "addr:street":"S Main St",
    "iso:country":"US",
    "sg:address":"208 S Main St",
    "sg:city":"Coudersport",
    "sg:classifiers":[
        {
            "category":"Food & Beverages",
            "subcategory":"Groceries & Convenience Stores",
            "type":"Retail Goods"
        }
    ],
    "sg:phone":"+1   ",
    "sg:postcode":"16915",
    "sg:province":"PA",
    "sg:tags":[
        "station"
    ],
    "wof:name":"Sheetz 165",
    "wof:placetype":"venue"
},
  "geometry": {"coordinates":[-78.021269,41.77047],"type":"Point"}
}