{
  "type": "Feature",
  "properties": {
    "iso:country":"US",
    "sg:address":"2304 Chicora Rd",
    "sg:city":"Chicora",
    "sg:classifiers":[
        {
            "category":"Restaurant",
            "type":"Food & Drink"
        }
    ],
    "sg:phone":"+1 724 445 3773",
    "sg:postcode":"16025",
    "sg:province":"PA",
    "sg:tags":[
        "eating"
    ],
    "wof:name":"B S Rockers",
    "wof:placetype":"venue"
},
  "geometry": {"coordinates":[-79.706548,40.965027],"type":"Point"}
}