{
  "type": "Feature",
  "properties": {
    "iso:country":"US",
    "sg:address":"1205 Chartiers Ave",
    "sg:city":"Mc Kees Rocks",
    "sg:classifiers":[
        {
            "category":"Social Services",
            "subcategory":"Child Care",
            "type":"Services"
        }
    ],
    "sg:phone":"+1 412 331 5233",
    "sg:postcode":"15136",
    "sg:province":"PA",
    "sg:tags":[
        "day"
    ],
    "wof:name":"Train Up A Child Daycare & Learning Center",
    "wof:placetype":"venue"
},
  "geometry": {"coordinates":[-80.071899,40.464901],"type":"Point"}
}