{
  "type": "Feature",
  "properties": {
    "addr:full":"808 Conchester Hwy Boothwyn PA 19061",
    "addr:housenumber":"808",
    "addr:postcode":"19061",
    "addr:street":"Conchester Hwy",
    "iso:country":"US",
    "sg:address":"808 Conchester Hwy",
    "sg:city":"Boothwyn",
    "sg:classifiers":[
        {
            "category":"Real Estate",
            "subcategory":"Real Estate Operator",
            "type":"Services"
        }
    ],
    "sg:phone":"+1 610 485 8050",
    "sg:postcode":"19061",
    "sg:province":"PA",
    "sg:tags":[
        "building",
        "apartment"
    ],
    "wof:name":"Park View At Naaman's Creek",
    "wof:placetype":"venue"
},
  "geometry": {"coordinates":[-75.458429,39.851772],"type":"Point"}
}