{
  "type": "Feature",
  "properties": {
    "addr:full":"3992 Locust Grove Rd Columbia PA 17512",
    "addr:housenumber":"3992",
    "addr:postcode":"17512",
    "addr:street":"Locust Grove Rd",
    "iso:country":"US",
    "sg:address":"3992 Locust Grove Rd",
    "sg:city":"Columbia",
    "sg:classifiers":[
        {
            "category":"Home & Garden",
            "subcategory":"Building Materials",
            "type":"Retail Goods"
        },
        {
            "category":"Home & Garden",
            "subcategory":"Garden Supply",
            "type":"Retail Goods"
        }
    ],
    "sg:phone":"+1 717 684 2019",
    "sg:postcode":"17512",
    "sg:province":"PA",
    "sg:tags":[
        "lawnmowers",
        "lawn",
        "formica",
        "mower"
    ],
    "wof:name":"R P Williams & Sons Inc",
    "wof:placetype":"venue"
},
  "geometry": {"coordinates":[-76.468388,40.031588],"type":"Point"}
}