{
  "type": "Feature",
  "properties": {
    "iso:country":"US",
    "sg:address":"426 S 44th St",
    "sg:city":"Philadelphia",
    "sg:classifiers":[
        {
            "category":"Real Estate",
            "subcategory":"Real Estate Operator",
            "type":"Services"
        }
    ],
    "sg:phone":"+1   ",
    "sg:postcode":"19104",
    "sg:province":"PA",
    "sg:tags":[
        "dwelling"
    ],
    "wof:name":"4041 Corporation",
    "wof:placetype":"venue"
},
  "geometry": {"coordinates":[-75.21115,39.950158],"type":"Point"}
}