{
  "type": "Feature",
  "properties": {
    "addr:full":"590 E Market St Mercer PA 16137",
    "addr:housenumber":"590",
    "addr:postcode":"16137",
    "addr:street":"E Market St",
    "iso:country":"US",
    "sg:address":"590 E Market St",
    "sg:city":"Mercer",
    "sg:classifiers":[
        {
            "category":"Building & Trades",
            "subcategory":"Construction",
            "type":"Services"
        }
    ],
    "sg:phone":"+1 724 662 3291",
    "sg:postcode":"16137",
    "sg:province":"PA",
    "sg:tags":[
        "marking",
        "maintenance",
        "parking"
    ],
    "wof:name":"Mercer Street Dept",
    "wof:placetype":"venue"
},
  "geometry": {"coordinates":[-80.22654300000001,41.22586],"type":"Point"}
}