{
  "type": "Feature",
  "properties": {
    "addr:full":"920 E Lycoming St Philadelphia PA 19124",
    "addr:housenumber":"920",
    "addr:postcode":"19124",
    "addr:street":"E Lycoming St",
    "iso:country":"US",
    "sg:address":"920 E Lycoming St",
    "sg:city":"Philadelphia",
    "sg:classifiers":[
        {
            "category":"Shopping",
            "subcategory":"Clothing, Apparel, & Fashions",
            "type":"Retail Goods"
        }
    ],
    "sg:phone":"+1 215 743 0400",
    "sg:postcode":"19124",
    "sg:province":"PA",
    "sg:tags":[
        "suits-custom",
        "men's",
        "made"
    ],
    "wof:name":"W Seitchik & Sons Inc",
    "wof:placetype":"venue"
},
  "geometry": {"coordinates":[-75.109903,40.010145],"type":"Point"}
}