{
  "type": "Feature",
  "properties": {
    "iso:country":"US",
    "sg:address":"133 Hunters Trl",
    "sg:city":"Gettysburg",
    "sg:classifiers":[
        {
            "category":"Education",
            "subcategory":"College",
            "type":"Public Place"
        }
    ],
    "sg:phone":"+1   ",
    "sg:postcode":"17325",
    "sg:province":"PA",
    "wof:name":"Jean S Legros",
    "wof:placetype":"venue"
},
  "geometry": {"coordinates":[-77.261625,39.838866],"type":"Point"}
}