{
  "type": "Feature",
  "properties": {
    "iso:country":"US",
    "sg:address":"1415 S 49th St # 17",
    "sg:city":"Philadelphia",
    "sg:classifiers":[
        {
            "category":"Organizations",
            "subcategory":"Religious Organization",
            "type":"Services"
        }
    ],
    "sg:phone":"+1 215 729 2581",
    "sg:postcode":"19143",
    "sg:province":"PA",
    "wof:name":"Evangel Temple",
    "wof:placetype":"venue"
},
  "geometry": {"coordinates":[-75.21192600000001,39.940483],"type":"Point"}
}