{
  "type": "Feature",
  "properties": {
    "iso:country":"US",
    "sg:address":"1616 Vance Ave",
    "sg:city":"Coraopolis",
    "sg:classifiers":[
        {
            "category":"Shopping",
            "subcategory":"Musical Instruments",
            "type":"Retail Goods"
        }
    ],
    "sg:phone":"+1 412 269 0846",
    "sg:postcode":"15108",
    "sg:province":"PA",
    "wof:name":"Hearing Ear Music",
    "wof:placetype":"venue"
},
  "geometry": {"coordinates":[-80.154709,40.511063],"type":"Point"}
}