{
  "type": "Feature",
  "properties": {
    "iso:country":"US",
    "sg:address":"600 Spring Garden St",
    "sg:city":"Philadelphia",
    "sg:classifiers":[
        {
            "category":"Recreation",
            "type":"Entertainment"
        }
    ],
    "sg:phone":"+1 215 925 8878",
    "sg:postcode":"19123",
    "sg:province":"PA",
    "sg:tags":[
        "club",
        "membership"
    ],
    "wof:name":"Transit Nightclub",
    "wof:placetype":"venue"
},
  "geometry": {"coordinates":[-75.149841,39.961361],"type":"Point"}
}