{
  "type": "Feature",
  "properties": {
    "addr:full":"895 3rd St Whitehall PA 18052",
    "addr:housenumber":"895",
    "addr:postcode":"18052",
    "addr:street":"3Rd St",
    "iso:country":"US",
    "sg:address":"895 3rd St",
    "sg:city":"Whitehall",
    "sg:classifiers":[
        {
            "category":"Manufacturing",
            "subcategory":"Tools & Machinery",
            "type":"Manufacturing & Wholesale Goods"
        }
    ],
    "sg:phone":"+1 610 266 0847",
    "sg:postcode":"18052",
    "sg:province":"PA",
    "sg:tags":[
        "equipment",
        "refrigeration"
    ],
    "wof:name":"S J Schmoyer Co",
    "wof:placetype":"venue"
},
  "geometry": {"coordinates":[-75.47077400000001,40.636241],"type":"Point"}
}