{
  "type": "Feature",
  "properties": {
    "iso:country":"US",
    "sg:address":"516 N Irving Ave",
    "sg:city":"Scranton",
    "sg:classifiers":[
        {
            "category":"Professional",
            "type":"Services"
        }
    ],
    "sg:phone":"+1   ",
    "sg:postcode":"18510",
    "sg:province":"PA",
    "wof:name":"Stacys Jam Delight",
    "wof:placetype":"venue"
},
  "geometry": {"coordinates":[-75.64837799999999,41.405974],"type":"Point"}
}