{
  "type": "Feature",
  "properties": {
    "addr:full":"429 N Main Ave Scranton PA 18504",
    "addr:housenumber":"429",
    "addr:postcode":"18504",
    "addr:street":"N Main Ave",
    "iso:country":"US",
    "sg:address":"429 N Main Ave",
    "sg:city":"Scranton",
    "sg:classifiers":[
        {
            "category":"Restaurant",
            "type":"Food & Drink"
        }
    ],
    "sg:phone":"+1   ",
    "sg:postcode":"18504",
    "sg:province":"PA",
    "sg:tags":[
        "eating"
    ],
    "wof:name":"Wendys",
    "wof:placetype":"venue"
},
  "geometry": {"coordinates":[-75.676941,41.415316],"type":"Point"}
}