{
  "type": "Feature",
  "properties": {
    "iso:country":"US",
    "sg:address":"2385 Blakeslee Boulevard Dr W",
    "sg:city":"Lehighton",
    "sg:classifiers":[
        {
            "category":"Food & Beverages",
            "subcategory":"Groceries & Convenience Stores",
            "type":"Retail Goods"
        }
    ],
    "sg:phone":"+1   ",
    "sg:postcode":"18235",
    "sg:province":"PA",
    "wof:name":"AS Shortstop",
    "wof:placetype":"venue"
},
  "geometry": {"coordinates":[-75.811843,40.785829],"type":"Point"}
}