{
  "type": "Feature",
  "properties": {
    "iso:country":"US",
    "sg:address":"1152 Midland Ave",
    "sg:city":"Midland",
    "sg:classifiers":[
        {
            "category":"Restaurant",
            "type":"Food & Drink"
        }
    ],
    "sg:phone":"+1 724 643 0801",
    "sg:postcode":"15059",
    "sg:province":"PA",
    "wof:name":"Midland Subway",
    "wof:placetype":"venue"
},
  "geometry": {"coordinates":[-80.447502,40.633057],"type":"Point"}
}