{
  "type": "Feature",
  "properties": {
    "iso:country":"US",
    "sg:address":"353 Ridge Ave",
    "sg:city":"Pittsburgh",
    "sg:classifiers":[
        {
            "category":"Organizations",
            "subcategory":"Religious Organization",
            "type":"Services"
        }
    ],
    "sg:phone":"+1   ",
    "sg:postcode":"15221",
    "sg:province":"PA",
    "wof:name":"Hope Lutheran Church Forest Hl",
    "wof:placetype":"venue"
},
  "geometry": {"coordinates":[-79.854777,40.42806],"type":"Point"}
}