{
  "type": "Feature",
  "properties": {
    "addr:full":"423 Highland Rd Nazareth PA 18064",
    "addr:housenumber":"423",
    "addr:postcode":"18064",
    "addr:street":"Highland Rd",
    "iso:country":"US",
    "sg:address":"423 Highland Rd",
    "sg:city":"Nazareth",
    "sg:classifiers":[
        {
            "category":"Organizations",
            "subcategory":"Religious Organization",
            "type":"Services"
        }
    ],
    "sg:phone":"+1 610 759 0433",
    "sg:postcode":"18064",
    "sg:province":"PA",
    "sg:tags":[
        "clergy"
    ],
    "wof:name":"Gordon R Furbay",
    "wof:placetype":"venue"
},
  "geometry": {"coordinates":[-75.337366,40.764054],"type":"Point"}
}