{
  "type": "Feature",
  "properties": {
    "iso:country":"US",
    "sg:address":"1718 Clay Hill Rd",
    "sg:city":"Chambersburg",
    "sg:classifiers":[
        {
            "category":"Farming",
            "subcategory":"Livestock Farm",
            "type":"Manufacturing & Wholesale Goods"
        },
        {
            "category":"Farming",
            "subcategory":"Farm",
            "type":"Manufacturing & Wholesale Goods"
        }
    ],
    "sg:phone":"+1 717 597 3047",
    "sg:postcode":"17202",
    "sg:province":"PA",
    "wof:name":"Ralph Gee",
    "wof:placetype":"venue"
},
  "geometry": {"coordinates":[-77.665346,39.814817],"type":"Point"}
}