{
  "type": "Feature",
  "properties": {
    "iso:country":"US",
    "sg:address":"2008 Lycoming Creek Rd",
    "sg:city":"Williamsport",
    "sg:classifiers":[
        {
            "category":"Insurance",
            "subcategory":"Insurance Agent",
            "type":"Services"
        }
    ],
    "sg:phone":"+1 570 326 7697",
    "sg:postcode":"17701",
    "sg:province":"PA",
    "wof:name":"Cohick Financial Svc",
    "wof:placetype":"venue"
},
  "geometry": {"coordinates":[-77.043437,41.258438],"type":"Point"}
}