{
  "type": "Feature",
  "properties": {
    "iso:country":"US",
    "sg:address":"3036 Lois Ave",
    "sg:city":"Bristol",
    "sg:classifiers":[
        {
            "category":"Building & Trades",
            "subcategory":"Plumbing",
            "type":"Services"
        }
    ],
    "sg:phone":"+1   ",
    "sg:postcode":"19007",
    "sg:province":"PA",
    "sg:tags":[
        "contractor"
    ],
    "wof:name":"Shippee Mechanical Inc",
    "wof:placetype":"venue"
},
  "geometry": {"coordinates":[-74.875867,40.120963],"type":"Point"}
}