{
  "type": "Feature",
  "properties": {
    "addr:full":"219 Millway Rd Ephrata PA 17522",
    "addr:housenumber":"219",
    "addr:postcode":"17522",
    "addr:street":"Millway Rd",
    "iso:country":"US",
    "sg:address":"219 Millway Rd",
    "sg:city":"Ephrata",
    "sg:classifiers":[
        {
            "category":"Building & Trades",
            "subcategory":"Plumbing",
            "type":"Services"
        }
    ],
    "sg:phone":"+1 717 859 2914",
    "sg:postcode":"17522",
    "sg:province":"PA",
    "sg:tags":[
        "conditioning",
        "air",
        "system",
        "contractor"
    ],
    "wof:name":"Ray Youndt & Son",
    "wof:placetype":"venue"
},
  "geometry": {"coordinates":[-76.218856,40.1539],"type":"Point"}
}