{
  "type": "Feature",
  "properties": {
    "iso:country":"US",
    "sg:address":"217 S 8th St",
    "sg:city":"Lebanon",
    "sg:classifiers":[
        {
            "category":"Personal",
            "subcategory":"Beauty Salon",
            "type":"Services"
        }
    ],
    "sg:phone":"+1 717 272 2029",
    "sg:postcode":"17042",
    "sg:province":"PA",
    "sg:tags":[
        "shop"
    ],
    "wof:name":"Classic Designs Inc",
    "wof:placetype":"venue"
},
  "geometry": {"coordinates":[-76.42420300000001,40.336082],"type":"Point"}
}