{
  "type": "Feature",
  "properties": {
    "addr:full":"521 W Baltimore Ave Clifton Heights PA 19018",
    "addr:housenumber":"521",
    "addr:postcode":"19018",
    "addr:street":"W Baltimore Ave",
    "iso:country":"US",
    "sg:address":"521 W Baltimore Ave",
    "sg:city":"Clifton Heights",
    "sg:classifiers":[
        {
            "category":"Restaurant",
            "type":"Food & Drink"
        }
    ],
    "sg:menulink":"http://www.allmenus.com/pa/clifton-heights/170635-burger-king/menu/",
    "sg:phone":"+1 610 394 9004",
    "sg:postcode":"19018",
    "sg:province":"PA",
    "sg:tags":[
        "burger",
        "american"
    ],
    "wof:name":"Burger King",
    "wof:placetype":"venue"
},
  "geometry": {"coordinates":[-75.304723,39.926628],"type":"Point"}
}