{
  "type": "Feature",
  "properties": {
    "addr:full":"140 Sandune Dr Plum PA 15239",
    "addr:housenumber":"140",
    "addr:postcode":"15239",
    "addr:street":"Sandune Dr",
    "iso:country":"US",
    "sg:address":"140 Sandune Dr",
    "sg:city":"Plum",
    "sg:classifiers":[
        {
            "category":"Education",
            "subcategory":"Special Training",
            "type":"Public Place"
        }
    ],
    "sg:phone":"+1 724 327 2777",
    "sg:postcode":"15239",
    "sg:province":"PA",
    "sg:tags":[
        "instruction",
        "music"
    ],
    "wof:name":"Plum Boro Music Ctr",
    "wof:placetype":"venue"
},
  "geometry": {"coordinates":[-79.70323,40.463618],"type":"Point"}
}