{
  "type": "Feature",
  "properties": {
    "iso:country":"US",
    "sg:address":"403 Main St",
    "sg:city":"Harleysville",
    "sg:classifiers":[
        {
            "category":"Home & Garden",
            "subcategory":"Garden Supply",
            "type":"Retail Goods"
        }
    ],
    "sg:phone":"+1 215 256 6163",
    "sg:postcode":"19438",
    "sg:province":"PA",
    "sg:tags":[
        "repair",
        "lawn",
        "lawnmowers",
        "mower"
    ],
    "wof:name":"Moyers Outdoor Power Equipment",
    "wof:placetype":"venue"
},
  "geometry": {"coordinates":[-75.382284,40.276345],"type":"Point"}
}