{
  "type": "Feature",
  "properties": {
    "iso:country":"US",
    "sg:address":"450 W Shamokin St",
    "sg:city":"Trevorton",
    "sg:classifiers":[
        {
            "category":"Banks & Credit Unions",
            "subcategory":"Bank",
            "type":"Services"
        }
    ],
    "sg:phone":"+1   ",
    "sg:postcode":"17881",
    "sg:province":"PA",
    "sg:tags":[
        "national",
        "commercial"
    ],
    "wof:name":"Union Bank & Trust Co Inc",
    "wof:placetype":"venue"
},
  "geometry": {"coordinates":[-76.672316,40.780971],"type":"Point"}
}