{
  "type": "Feature",
  "properties": {
    "iso:country":"US",
    "sg:address":"164 Butternut Ct",
    "sg:city":"Reading",
    "sg:classifiers":[
        {
            "category":"Personal",
            "subcategory":"Hair Removal",
            "type":"Services"
        }
    ],
    "sg:phone":"+1   ",
    "sg:postcode":"19608",
    "sg:province":"PA",
    "sg:tags":[
        "consulting",
        "management"
    ],
    "wof:name":"T S P Financial and Est Svcs",
    "wof:placetype":"venue"
},
  "geometry": {"coordinates":[-76.04257200000001,40.323969],"type":"Point"}
}