{
  "type": "Feature",
  "properties": {
    "addr:full":"435 6th Ave Pittsburgh PA 15219",
    "addr:housenumber":"435",
    "addr:postcode":"15219",
    "addr:street":"6Th Ave",
    "iso:country":"US",
    "sg:address":"435 6th Ave",
    "sg:city":"Pittsburgh",
    "sg:classifiers":[
        {
            "category":"Professional",
            "subcategory":"Lawyer & Legal Services",
            "type":"Services"
        }
    ],
    "sg:phone":"+1 412 288 4053",
    "sg:postcode":"15219",
    "sg:province":"PA",
    "wof:name":"Jones Tracey D Atty",
    "wof:placetype":"venue"
},
  "geometry": {"coordinates":[-79.996696,40.441101],"type":"Point"}
}