{
  "type": "Feature",
  "properties": {
    "iso:country":"US",
    "sg:address":"1000 Commerce Park Dr",
    "sg:city":"Williamsport",
    "sg:phone":"+1 570 326 2628",
    "sg:postcode":"17701",
    "sg:province":"PA",
    "sg:website":"http://www.centurabp.com",
    "wof:name":"Centura Building Products",
    "wof:placetype":"venue"
},
  "geometry": {"coordinates":[-76.984337,41.246574],"type":"Point"}
}