{
  "type": "Feature",
  "properties": {
    "addr:full":"1758 Oregon Pike Lancaster PA 17601",
    "addr:housenumber":"1758",
    "addr:postcode":"17601",
    "addr:street":"Oregon Pike",
    "iso:country":"US",
    "sg:address":"1758 Oregon Pike",
    "sg:city":"Lancaster",
    "sg:classifiers":[
        {
            "category":"Banks & Credit Unions",
            "subcategory":"Bank",
            "type":"Services"
        }
    ],
    "sg:phone":"+1   ",
    "sg:postcode":"17601",
    "sg:province":"PA",
    "sg:tags":[
        "federal",
        "savings",
        "loan"
    ],
    "wof:name":"York Federal Sav & Ln Str 13",
    "wof:placetype":"venue"
},
  "geometry": {"coordinates":[-76.297442,40.074923],"type":"Point"}
}