{
  "type": "Feature",
  "properties": {
    "addr:full":"10 Ebner Dr Bloomsburg PA 17815",
    "addr:housenumber":"10",
    "addr:postcode":"17815",
    "addr:street":"Ebner Dr",
    "iso:country":"US",
    "sg:address":"10 Ebner Dr",
    "sg:city":"Bloomsburg",
    "sg:classifiers":[
        {
            "category":"Health Services",
            "subcategory":"Medical Lab",
            "type":"Services"
        }
    ],
    "sg:phone":"+1   ",
    "sg:postcode":"17815",
    "sg:province":"PA",
    "sg:tags":[
        "laboratory"
    ],
    "wof:name":"H R I",
    "wof:placetype":"venue"
},
  "geometry": {"coordinates":[-76.49418300000001,41.060665],"type":"Point"}
}