{
  "type": "Feature",
  "properties": {
    "iso:country":"US",
    "sg:address":"913 Silver Spring Rd",
    "sg:city":"Lancaster",
    "sg:classifiers":[
        {
            "category":"Building & Trades",
            "subcategory":"Construction",
            "type":"Services"
        }
    ],
    "sg:phone":"+1   ",
    "sg:postcode":"17601",
    "sg:province":"PA",
    "sg:tags":[
        "contractor"
    ],
    "wof:name":"S Albright Contracting",
    "wof:placetype":"venue"
},
  "geometry": {"coordinates":[-76.437067,40.068146],"type":"Point"}
}