{
  "type": "Feature",
  "properties": {
    "addr:full":"109 Plaza Dr Johnstown PA 15905",
    "addr:housenumber":"109",
    "addr:postcode":"15905",
    "addr:street":"Plaza Dr",
    "iso:country":"US",
    "sg:address":"109 Plaza Dr",
    "sg:city":"Johnstown",
    "sg:classifiers":[
        {
            "category":"Professional",
            "type":"Services"
        }
    ],
    "sg:phone":"+1 814 255 9650",
    "sg:postcode":"15905",
    "sg:province":"PA",
    "sg:tags":[
        "establishment"
    ],
    "wof:name":"WMTZ Request Line",
    "wof:placetype":"venue"
},
  "geometry": {"coordinates":[-78.95611599999999,40.323193],"type":"Point"}
}