{
  "type": "Feature",
  "properties": {
    "addr:full":"1829 E Washington St New Castle PA 16101",
    "addr:housenumber":"1829",
    "addr:postcode":"16101",
    "addr:street":"E Washington St",
    "iso:country":"US",
    "sg:address":"1829 E Washington St",
    "sg:city":"New Castle",
    "sg:classifiers":[
        {
            "category":"Restaurant",
            "type":"Food & Drink"
        }
    ],
    "sg:phone":"+1   ",
    "sg:postcode":"16101",
    "sg:province":"PA",
    "sg:tags":[
        "eating"
    ],
    "wof:name":"Bills Sandwich Shop Inc",
    "wof:placetype":"venue"
},
  "geometry": {"coordinates":[-80.321702,40.980933],"type":"Point"}
}