{
  "type": "Feature",
  "properties": {
    "iso:country":"US",
    "sg:address":"241 Front St",
    "sg:city":"Catasauqua",
    "sg:classifiers":[
        {
            "category":"Building & Trades",
            "subcategory":"Construction",
            "type":"Services"
        }
    ],
    "sg:phone":"+1 610 443 5022",
    "sg:postcode":"18032",
    "sg:province":"PA",
    "sg:tags":[
        "contractor"
    ],
    "wof:name":"Home Improvement J&e",
    "wof:placetype":"venue"
},
  "geometry": {"coordinates":[-75.471493,40.651394],"type":"Point"}
}