{
  "type": "Feature",
  "properties": {
    "iso:country":"US",
    "sg:address":"2872 Rte 338",
    "sg:city":"Knox",
    "sg:classifiers":[
        {
            "category":"Retail",
            "subcategory":"Repair Shop",
            "type":"Services"
        }
    ],
    "sg:phone":"+1 814 797 0280",
    "sg:postcode":"16232",
    "sg:province":"PA",
    "sg:tags":[
        "welding"
    ],
    "wof:name":"Swartfager Welding Inc",
    "wof:placetype":"venue"
},
  "geometry": {"coordinates":[-79.59511000000001,41.19501],"type":"Point"}
}