{
  "type": "Feature",
  "properties": {
    "iso:country":"US",
    "sg:address":"1420 Easton Ave",
    "sg:city":"Bethlehem",
    "sg:classifiers":[
        {
            "category":"Real Estate",
            "subcategory":"Real Estate Services",
            "type":"Services"
        },
        {
            "category":"Real Estate",
            "subcategory":"Real Estate Agent",
            "type":"Services"
        }
    ],
    "sg:phone":"+1 610 882 3135",
    "sg:postcode":"18018",
    "sg:province":"PA",
    "sg:tags":[
        "buyer",
        "broker"
    ],
    "wof:name":"Cassidon Real Estate Corp",
    "wof:placetype":"venue"
},
  "geometry": {"coordinates":[-75.368382,40.632072],"type":"Point"}
}