{
  "type": "Feature",
  "properties": {
    "addr:full":"350 Kennedy Blvd Pittston PA 18640",
    "addr:housenumber":"350",
    "addr:postcode":"18640",
    "addr:street":"Kennedy Blvd",
    "iso:country":"US",
    "sg:address":"350 Kennedy Blvd",
    "sg:city":"Pittston",
    "sg:classifiers":[
        {
            "category":"Professional",
            "type":"Services"
        }
    ],
    "sg:phone":"+1 570 602 8309",
    "sg:postcode":"18640",
    "sg:province":"PA",
    "sg:tags":[
        "holding"
    ],
    "wof:name":"Fhb Development Co",
    "wof:placetype":"venue"
},
  "geometry": {"coordinates":[-75.792991,41.321306],"type":"Point"}
}