{
  "type": "Feature",
  "properties": {
    "iso:country":"US",
    "sg:address":"10725 Fry Rd",
    "sg:city":"Edinboro",
    "sg:classifiers":[
        {
            "category":"Farming",
            "subcategory":"Livestock Farm",
            "type":"Manufacturing & Wholesale Goods"
        }
    ],
    "sg:phone":"+1 814 734 5464",
    "sg:postcode":"16412",
    "sg:province":"PA",
    "wof:name":"Weil & Son",
    "wof:placetype":"venue"
},
  "geometry": {"coordinates":[-80.16440299999999,41.933716],"type":"Point"}
}