{
  "type": "Feature",
  "properties": {
    "iso:country":"US",
    "sg:address":"130 S Front St",
    "sg:city":"Milton",
    "sg:classifiers":[
        {
            "category":"Health Services",
            "subcategory":"Doctor",
            "type":"Services"
        }
    ],
    "sg:phone":"+1 570 742 8511",
    "sg:postcode":"17847",
    "sg:province":"PA",
    "sg:tags":[
        "physician",
        "family",
        "practice",
        "surgeons",
        "medicine",
        "surgeon"
    ],
    "wof:name":"Wilson Barclay M DO",
    "wof:placetype":"venue"
},
  "geometry": {"coordinates":[-76.856089,41.018059],"type":"Point"}
}