{
  "type": "Feature",
  "properties": {
    "iso:country":"US",
    "sg:address":"21 E Garfield St",
    "sg:city":"Philadelphia",
    "sg:classifiers":[
        {
            "category":"Retail",
            "subcategory":"Auto Repair",
            "type":"Services"
        }
    ],
    "sg:phone":"+1 215 848 4776",
    "sg:postcode":"19144",
    "sg:province":"PA",
    "wof:name":"Chisolm's Garage",
    "wof:placetype":"venue"
},
  "geometry": {"coordinates":[-75.163803,40.030102],"type":"Point"}
}