{
  "type": "Feature",
  "properties": {
    "iso:country":"US",
    "sg:address":"655 Rodi Rd",
    "sg:city":"Pittsburgh",
    "sg:classifiers":[
        {
            "category":"Professional",
            "subcategory":"Management & Consulting",
            "type":"Services"
        }
    ],
    "sg:phone":"+1   ",
    "sg:postcode":"15235",
    "sg:province":"PA",
    "sg:tags":[
        "business"
    ],
    "wof:name":"SCI Tek Environmental",
    "wof:placetype":"venue"
},
  "geometry": {"coordinates":[-79.827467,40.447981],"type":"Point"}
}