{
  "type": "Feature",
  "properties": {
    "iso:country":"US",
    "sg:address":"209 Poplar St",
    "sg:city":"Archbald",
    "sg:classifiers":[
        {
            "category":"Building & Trades",
            "subcategory":"Construction",
            "type":"Services"
        }
    ],
    "sg:phone":"+1   ",
    "sg:postcode":"18403",
    "sg:province":"PA",
    "sg:tags":[
        "contractor"
    ],
    "wof:name":"Dave Romanski Construction",
    "wof:placetype":"venue"
},
  "geometry": {"coordinates":[-75.53273299999999,41.495166],"type":"Point"}
}