{
  "type": "Feature",
  "properties": {
    "iso:country":"US",
    "sg:address":"114 W Mahoning St",
    "sg:city":"Punxsutawney",
    "sg:classifiers":[
        {
            "category":"Personal",
            "subcategory":"Beauty Salon",
            "type":"Services"
        }
    ],
    "sg:phone":"+1 814 938 4247",
    "sg:postcode":"15767",
    "sg:province":"PA",
    "wof:name":"Hair Trends",
    "wof:placetype":"venue"
},
  "geometry": {"coordinates":[-78.97129200000001,40.943545],"type":"Point"}
}