{
  "type": "Feature",
  "properties": {
    "iso:country":"US",
    "sg:address":"704 Haldane Dr",
    "sg:city":"Kennett Square",
    "sg:classifiers":[
        {
            "category":"Building & Trades",
            "subcategory":"Construction",
            "type":"Services"
        }
    ],
    "sg:phone":"+1   ",
    "sg:postcode":"19348",
    "sg:province":"PA",
    "sg:tags":[
        "house"
    ],
    "wof:name":"J March Builders Inc",
    "wof:placetype":"venue"
},
  "geometry": {"coordinates":[-75.669616,39.883085],"type":"Point"}
}