{
  "type": "Feature",
  "properties": {
    "iso:country":"US",
    "sg:address":"10820 N Delaware Dr",
    "sg:city":"Bangor",
    "sg:classifiers":[
        {
            "category":"Home & Garden",
            "subcategory":"Home Furnishings",
            "type":"Retail Goods"
        }
    ],
    "sg:phone":"+1 610 588 6775",
    "sg:postcode":"18013",
    "sg:province":"PA",
    "sg:tags":[
        "window",
        "casual",
        "furniture"
    ],
    "wof:name":"Blind Spot",
    "wof:placetype":"venue"
},
  "geometry": {"coordinates":[-75.15107500000001,40.823237],"type":"Point"}
}