{
  "type": "Feature",
  "properties": {
    "addr:full":"101 Fox Rd Lebanon PA 17042",
    "addr:housenumber":"101",
    "addr:postcode":"17042",
    "addr:street":"Fox Rd",
    "iso:country":"US",
    "sg:address":"101 Fox Rd",
    "sg:city":"Lebanon",
    "sg:classifiers":[
        {
            "category":"Farming",
            "subcategory":"Farm",
            "type":"Manufacturing & Wholesale Goods"
        }
    ],
    "sg:phone":"+1   ",
    "sg:postcode":"17042",
    "sg:province":"PA",
    "sg:tags":[
        "crop",
        "general"
    ],
    "wof:name":"Jere Brubaker",
    "wof:placetype":"venue"
},
  "geometry": {"coordinates":[-76.36263700000001,40.325431],"type":"Point"}
}