{
  "type": "Feature",
  "properties": {
    "iso:country":"US",
    "sg:address":"6 Wyoming Valley Mall",
    "sg:city":"Wilkes Barre",
    "sg:classifiers":[
        {
            "category":"Shopping",
            "subcategory":"Computers & Home Electronics",
            "type":"Retail Goods"
        }
    ],
    "sg:phone":"+1 570 824 1744",
    "sg:postcode":"18702",
    "sg:province":"PA",
    "sg:tags":[
        "game",
        "video",
        "software"
    ],
    "wof:name":"Electronics Boutique",
    "wof:placetype":"venue"
},
  "geometry": {"coordinates":[-75.842625,41.249431],"type":"Point"}
}