{
  "type": "Feature",
  "properties": {
    "addr:full":"4035 Lancaster Ave Philadelphia PA 19104",
    "addr:housenumber":"4035",
    "addr:postcode":"19104",
    "addr:street":"Lancaster Ave",
    "iso:country":"US",
    "sg:address":"4035 Lancaster Ave",
    "sg:city":"Philadelphia",
    "sg:classifiers":[
        {
            "category":"Farming",
            "subcategory":"Poultry Farm",
            "type":"Manufacturing & Wholesale Goods"
        }
    ],
    "sg:phone":"+1   ",
    "sg:postcode":"19104",
    "sg:province":"PA",
    "sg:tags":[
        "hatchery",
        "chicken",
        "egg"
    ],
    "wof:name":"Pilgrims Pride Chicken Operat",
    "wof:placetype":"venue"
},
  "geometry": {"coordinates":[-75.203754,39.964091],"type":"Point"}
}