{
  "type": "Feature",
  "properties": {
    "iso:country":"US",
    "sg:address":"40 Eldred St",
    "sg:city":"Williamsport",
    "sg:classifiers":[
        {
            "category":"Building & Trades",
            "subcategory":"Construction",
            "type":"Services"
        }
    ],
    "sg:phone":"+1 570 326 1806",
    "sg:postcode":"17701",
    "sg:province":"PA",
    "sg:tags":[
        "resurfacing",
        "floor",
        "laying",
        "refinishing",
        "contractor"
    ],
    "wof:name":"Havrillas Floor Sanding & Fini",
    "wof:placetype":"venue"
},
  "geometry": {"coordinates":[-77.005802,41.251459],"type":"Point"}
}