{
  "type": "Feature",
  "properties": {
    "iso:country":"US",
    "sg:address":"2856 W 33rd St",
    "sg:city":"Erie",
    "sg:classifiers":[
        {
            "category":"Science Facility",
            "type":"Public Place"
        }
    ],
    "sg:phone":"+1 814 833 3318",
    "sg:postcode":"16506",
    "sg:province":"PA",
    "sg:tags":[
        "development",
        "laboratories-research"
    ],
    "wof:name":"Stereogenic Solutions",
    "wof:placetype":"venue"
},
  "geometry": {"coordinates":[-80.133376,42.082674],"type":"Point"}
}