{
  "type": "Feature",
  "properties": {
    "addr:full":"612 Penn Ave Pittsburgh PA 15221",
    "addr:housenumber":"612",
    "addr:postcode":"15221",
    "addr:street":"Penn Ave",
    "iso:country":"US",
    "sg:address":"612 Penn Ave",
    "sg:city":"Pittsburgh",
    "sg:classifiers":[
        {
            "category":"Restaurant",
            "type":"Food & Drink"
        }
    ],
    "sg:menulink":"http://www.allmenus.com/pa/wilkinsburg/286556-salvatores-pizza-house/menu/",
    "sg:phone":"+1 412 247 4848",
    "sg:postcode":"15221",
    "sg:province":"PA",
    "sg:tags":[
        "american",
        "pizza"
    ],
    "wof:name":"Salvatore's Pizza House",
    "wof:placetype":"venue"
},
  "geometry": {"coordinates":[-79.885566,40.443656],"type":"Point"}
}