{
  "type": "Feature",
  "properties": {
    "addr:full":"3 Hulme Ave Langhorne PA 19047",
    "addr:housenumber":"3",
    "addr:postcode":"19047",
    "addr:street":"Hulme Ave Langhorne Pa",
    "iso:country":"US",
    "sg:address":"3 Hulme Ave",
    "sg:city":"Langhorne",
    "sg:classifiers":[
        {
            "category":"Building & Trades",
            "subcategory":"Locksmith",
            "type":"Services"
        }
    ],
    "sg:phone":"+1 267 569 3656",
    "sg:postcode":"19047",
    "sg:province":"PA",
    "sg:tags":[
        "key"
    ],
    "wof:name":"Locksmith Available",
    "wof:placetype":"venue"
},
  "geometry": {"coordinates":[-74.911475,40.142564],"type":"Point"}
}