{
  "type": "Feature",
  "properties": {
    "iso:country":"US",
    "sg:address":"110 Urick Ln",
    "sg:city":"Monroeville",
    "sg:classifiers":[
        {
            "category":"Organizations",
            "subcategory":"Community Association",
            "type":"Services"
        }
    ],
    "sg:phone":"+1   ",
    "sg:postcode":"15146",
    "sg:province":"PA",
    "wof:name":"Alpha Alpha Omega Chapter",
    "wof:placetype":"venue"
},
  "geometry": {"coordinates":[-79.737522,40.407555],"type":"Point"}
}