{
  "type": "Feature",
  "properties": {
    "addr:full":"152 Mathers Rd Ambler PA 19002",
    "addr:housenumber":"152",
    "addr:postcode":"19002",
    "addr:street":"Mathers Rd",
    "iso:country":"US",
    "sg:address":"152 Mathers Rd",
    "sg:city":"Ambler",
    "sg:classifiers":[
        {
            "category":"Building & Trades",
            "subcategory":"Construction",
            "type":"Services"
        }
    ],
    "sg:phone":"+1 215 646 1699",
    "sg:postcode":"19002",
    "sg:province":"PA",
    "sg:tags":[
        "painter"
    ],
    "sg:website":"www.vanhawk.com",
    "wof:name":"Van Hawk Painting",
    "wof:placetype":"venue"
},
  "geometry": {"coordinates":[-75.23845799999999,40.16231],"type":"Point"}
}