{
  "type": "Feature",
  "properties": {
    "iso:country":"US",
    "sg:address":"50 Oak Rd",
    "sg:city":"Northumberland",
    "sg:classifiers":[
        {
            "category":"Wholesale",
            "subcategory":"Groceries",
            "type":"Manufacturing & Wholesale Goods"
        }
    ],
    "sg:phone":"+1   ",
    "sg:postcode":"17857",
    "sg:province":"PA",
    "sg:tags":[
        "general"
    ],
    "wof:name":"Foodswing Inc",
    "wof:placetype":"venue"
},
  "geometry": {"coordinates":[-76.819028,40.900589],"type":"Point"}
}