{
  "type": "Feature",
  "properties": {
    "iso:country":"US",
    "sg:address":"33 Elm Ave",
    "sg:city":"Hershey",
    "sg:classifiers":[
        {
            "category":"Travel",
            "subcategory":"Hotels & Motels",
            "type":"Entertainment"
        }
    ],
    "sg:phone":"+1   ",
    "sg:postcode":"17033",
    "sg:province":"PA",
    "sg:tags":[
        "operation"
    ],
    "wof:name":"Blue Knob Mountain Top Chalet",
    "wof:placetype":"venue"
},
  "geometry": {"coordinates":[-76.64738199999999,40.281178],"type":"Point"}
}