{
  "type": "Feature",
  "properties": {
    "addr:full":"3828 Grace St Homestead PA 15120",
    "addr:housenumber":"3828",
    "addr:postcode":"15120",
    "addr:street":"Grace St",
    "iso:country":"US",
    "sg:address":"3828 Grace St",
    "sg:city":"Homestead",
    "sg:classifiers":[
        {
            "category":"Building & Trades",
            "subcategory":"Landscaping Services",
            "type":"Services"
        }
    ],
    "sg:phone":"+1 412 462 0552",
    "sg:postcode":"15120",
    "sg:province":"PA",
    "sg:tags":[
        "tree"
    ],
    "wof:name":"Sonny's Tree Svc",
    "wof:placetype":"venue"
},
  "geometry": {"coordinates":[-79.904697,40.383268],"type":"Point"}
}