{
  "type": "Feature",
  "properties": {
    "iso:country":"US",
    "sg:address":"4337 Old William Penn Hwy",
    "sg:city":"Monroeville",
    "sg:classifiers":[
        {
            "category":"Personal",
            "subcategory":"Beauty Salon",
            "type":"Services"
        }
    ],
    "sg:phone":"+1 412 856 1290",
    "sg:postcode":"15146",
    "sg:province":"PA",
    "sg:tags":[
        "shop"
    ],
    "wof:name":"Le Shoppe",
    "wof:placetype":"venue"
},
  "geometry": {"coordinates":[-79.774395,40.442542],"type":"Point"}
}