{
  "type": "Feature",
  "properties": {
    "addr:full":"255 S 17th St Philadelphia PA 19103",
    "addr:housenumber":"255",
    "addr:postcode":"19103",
    "addr:street":"S 17Th St",
    "iso:country":"US",
    "sg:address":"255 S 17th St",
    "sg:city":"Philadelphia",
    "sg:classifiers":[
        {
            "category":"Professional",
            "subcategory":"Lawyer & Legal Services",
            "type":"Services"
        }
    ],
    "sg:phone":"+1 215 985 4050",
    "sg:postcode":"19103",
    "sg:province":"PA",
    "wof:name":"Einhorn Edgar R Atty",
    "wof:placetype":"venue"
},
  "geometry": {"coordinates":[-75.169403,39.948299],"type":"Point"}
}