{
  "type": "Feature",
  "properties": {
    "iso:country":"US",
    "sg:address":"3000 Locust St",
    "sg:city":"Pittsburgh",
    "sg:classifiers":[
        {
            "category":"Real Estate",
            "subcategory":"Real Estate Operator",
            "type":"Services"
        }
    ],
    "sg:phone":"+1 412 824 9000",
    "sg:postcode":"15221",
    "sg:province":"PA",
    "sg:tags":[
        "building",
        "apartment"
    ],
    "wof:name":"Brinton Towers",
    "wof:placetype":"venue"
},
  "geometry": {"coordinates":[-79.85188599999999,40.409756],"type":"Point"}
}