{
  "type": "Feature",
  "properties": {
    "iso:country":"US",
    "sg:address":"389 Green Ridge Rd",
    "sg:city":"Orrtanna",
    "sg:classifiers":[
        {
            "category":"Retail",
            "subcategory":"Auto Repair",
            "type":"Services"
        }
    ],
    "sg:phone":"+1 717 334 7684",
    "sg:postcode":"17353",
    "sg:province":"PA",
    "sg:tags":[
        "repairing",
        "automobile"
    ],
    "wof:name":"Wayne & Deb's Auto Repair",
    "wof:placetype":"venue"
},
  "geometry": {"coordinates":[-77.395381,39.881413],"type":"Point"}
}