{
  "type": "Feature",
  "properties": {
    "iso:country":"US",
    "sg:address":"2143 White St",
    "sg:city":"York",
    "sg:classifiers":[
        {
            "category":"Government",
            "subcategory":"Office",
            "type":"Public Place"
        }
    ],
    "sg:phone":"+1 717 771 4435",
    "sg:postcode":"17404",
    "sg:province":"PA",
    "sg:tags":[
        "state",
        "inspection"
    ],
    "wof:name":"Liquor Control Board",
    "wof:placetype":"venue"
},
  "geometry": {"coordinates":[-76.770883,39.962931],"type":"Point"}
}