{
  "type": "Feature",
  "properties": {
    "iso:country":"US",
    "sg:address":"32 Highview Ln",
    "sg:city":"Mertztown",
    "sg:classifiers":[
        {
            "category":"Wholesale",
            "subcategory":"Drugs",
            "type":"Manufacturing & Wholesale Goods"
        }
    ],
    "sg:phone":"+1   ",
    "sg:postcode":"19539",
    "sg:province":"PA",
    "wof:name":"Ireland Health Products",
    "wof:placetype":"venue"
},
  "geometry": {"coordinates":[-75.727279,40.454384],"type":"Point"}
}