{
  "type": "Feature",
  "properties": {
    "iso:country":"US",
    "sg:address":"2270 Scotland Rd",
    "sg:city":"Chambersburg",
    "sg:classifiers":[
        {
            "category":"Personal",
            "subcategory":"Beauty Salon",
            "type":"Services"
        }
    ],
    "sg:phone":"+1 717 263 4542",
    "sg:postcode":"17201",
    "sg:province":"PA",
    "wof:name":"Sharyle Goshen's Beauty Btq",
    "wof:placetype":"venue"
},
  "geometry": {"coordinates":[-77.62927000000001,39.960089],"type":"Point"}
}