{
  "type": "Feature",
  "properties": {
    "iso:country":"US",
    "sg:address":"33 S Duke St",
    "sg:city":"York",
    "sg:classifiers":[
        {
            "category":"Organizations",
            "subcategory":"Professional Association",
            "type":"Services"
        }
    ],
    "sg:phone":"+1 717 854 7610",
    "sg:postcode":"17401",
    "sg:province":"PA",
    "wof:name":"American Collectors Assn",
    "wof:placetype":"venue"
},
  "geometry": {"coordinates":[-76.725015,39.96173],"type":"Point"}
}