{
  "type": "Feature",
  "properties": {
    "iso:country":"US",
    "sg:address":"5827 Mertz Dr",
    "sg:city":"Allentown",
    "sg:classifiers":[
        {
            "category":"Building & Trades",
            "subcategory":"Landscaping Services",
            "type":"Services"
        }
    ],
    "sg:phone":"+1 610 398 2168",
    "sg:postcode":"18104",
    "sg:province":"PA",
    "sg:tags":[
        "tree"
    ],
    "wof:name":"Leibach Herb Tree & Shrub Care",
    "wof:placetype":"venue"
},
  "geometry": {"coordinates":[-75.578979,40.578732],"type":"Point"}
}