{
  "type": "Feature",
  "properties": {
    "iso:country":"US",
    "sg:address":"508 High St",
    "sg:city":"Monongahela",
    "sg:classifiers":[
        {
            "category":"Organizations",
            "subcategory":"Religious Organization",
            "type":"Services"
        }
    ],
    "sg:phone":"+1 724 258 5621",
    "sg:postcode":"15063",
    "sg:province":"PA",
    "sg:tags":[
        "church"
    ],
    "wof:name":"Nativity Blessed Virgin Mary Church",
    "wof:placetype":"venue"
},
  "geometry": {"coordinates":[-79.92939800000001,40.2024],"type":"Point"}
}