{
  "type": "Feature",
  "properties": {
    "addr:full":"1400 N Broad St Philadelphia PA 19121",
    "addr:housenumber":"1400",
    "addr:postcode":"19121",
    "addr:street":"N Broad St",
    "iso:country":"US",
    "sg:address":"1400 N Broad St",
    "sg:city":"Philadelphia",
    "sg:classifiers":[
        {
            "category":"Organizations",
            "subcategory":"Community Association",
            "type":"Services"
        }
    ],
    "sg:phone":"+1   ",
    "sg:postcode":"19121",
    "sg:province":"PA",
    "wof:name":"Columbia",
    "wof:placetype":"venue"
},
  "geometry": {"coordinates":[-75.15852599999999,39.97585],"type":"Point"}
}