{
  "type": "Feature",
  "properties": {
    "iso:country":"US",
    "sg:address":"307 11th St",
    "sg:city":"Honesdale",
    "sg:classifiers":[
        {
            "category":"Professional",
            "subcategory":"Lawyer & Legal Services",
            "type":"Services"
        }
    ],
    "sg:phone":"+1 570 251 9708",
    "sg:postcode":"18431",
    "sg:province":"PA",
    "sg:tags":[
        "attorney"
    ],
    "wof:name":"Patrick L Robinson",
    "wof:placetype":"venue"
},
  "geometry": {"coordinates":[-75.255263,41.576153],"type":"Point"}
}