{
  "type": "Feature",
  "properties": {
    "addr:full":"426 W Lancaster Ave Devon PA 19333",
    "addr:housenumber":"426",
    "addr:postcode":"19333",
    "addr:street":"W Lancaster Ave",
    "iso:country":"US",
    "sg:address":"426 W Lancaster Ave",
    "sg:city":"Devon",
    "sg:classifiers":[
        {
            "category":"Professional",
            "subcategory":"Computer Services",
            "type":"Services"
        }
    ],
    "sg:phone":"+1 610 296 6000",
    "sg:postcode":"19333",
    "sg:province":"PA",
    "sg:tags":[
        "repair",
        "equipment-service"
    ],
    "sg:website":"http://www.decisionone.com",
    "wof:name":"Decisionone",
    "wof:placetype":"venue"
},
  "geometry": {"coordinates":[-75.429059,40.044558],"type":"Point"}
}