{
  "type": "Feature",
  "properties": {
    "addr:full":"329 Church Rd Kutztown PA 19530",
    "addr:housenumber":"329",
    "addr:postcode":"19530",
    "addr:street":"Church Rd",
    "iso:country":"US",
    "sg:address":"329 Church Rd",
    "sg:city":"Kutztown",
    "sg:classifiers":[
        {
            "category":"Place Of Worship",
            "subcategory":"Church",
            "type":"Public Place"
        },
        {
            "category":"Place Of Worship",
            "type":"Public Place"
        }
    ],
    "sg:phone":"+1 610 683 7485",
    "sg:postcode":"19530",
    "sg:province":"PA",
    "sg:tags":[
        "lutheran",
        "america",
        "churches-lutheran",
        "churches-lutheran-evangelical"
    ],
    "wof:name":"Zion Evangelical Lutheran Ch",
    "wof:placetype":"venue"
},
  "geometry": {"coordinates":[-75.71022600000001,40.539299],"type":"Point"}
}