{
  "type": "Feature",
  "properties": {
    "addr:full":"124 S Highland Ave Pittsburgh PA 15206",
    "addr:housenumber":"124",
    "addr:postcode":"15206",
    "addr:street":"S Highland Ave",
    "iso:country":"US",
    "sg:address":"124 S Highland Ave",
    "sg:city":"Pittsburgh",
    "sg:classifiers":[
        {
            "category":"Arts & Performance",
            "subcategory":"Theater",
            "type":"Entertainment"
        }
    ],
    "sg:phone":"+1 412 363 5550",
    "sg:postcode":"15206",
    "sg:province":"PA",
    "sg:tags":[
        "bureau"
    ],
    "wof:name":"Infrared Entertainment",
    "wof:placetype":"venue"
},
  "geometry": {"coordinates":[-79.925043,40.459953],"type":"Point"}
}