{
  "type": "Feature",
  "properties": {
    "iso:country":"US",
    "sg:address":"527 Baltimore Pike",
    "sg:city":"Media",
    "sg:classifiers":[
        {
            "category":"Food & Beverages",
            "subcategory":"Groceries & Convenience Stores",
            "type":"Retail Goods"
        }
    ],
    "sg:phone":"+1 610 565 5072",
    "sg:postcode":"19063",
    "sg:province":"PA",
    "sg:tags":[
        "grocer"
    ],
    "wof:name":"Acme Markets Inc",
    "wof:placetype":"venue"
},
  "geometry": {"coordinates":[-75.46195899999999,39.900478],"type":"Point"}
}