{
  "type": "Feature",
  "properties": {
    "iso:country":"US",
    "sg:address":"155 W Main St",
    "sg:city":"Westfield",
    "sg:classifiers":[
        {
            "category":"Sports & Exercise",
            "subcategory":"Bowling",
            "type":"Entertainment"
        }
    ],
    "sg:phone":"+1 814 367 2232",
    "sg:postcode":"16950",
    "sg:province":"PA",
    "sg:tags":[
        "center"
    ],
    "wof:name":"Valley Bowling Ctr",
    "wof:placetype":"venue"
},
  "geometry": {"coordinates":[-77.54065300000001,41.919108],"type":"Point"}
}