{
  "type": "Feature",
  "properties": {
    "iso:country":"US",
    "sg:address":"400 Farm Ln",
    "sg:city":"Doylestown",
    "sg:classifiers":[
        {
            "category":"Professional",
            "subcategory":"Accounting & Tax Preparation",
            "type":"Services"
        }
    ],
    "sg:phone":"+1 215 345 7221",
    "sg:postcode":"18901",
    "sg:province":"PA",
    "sg:tags":[
        "accountant"
    ],
    "wof:name":"Piper Certified Public Acct PC",
    "wof:placetype":"venue"
},
  "geometry": {"coordinates":[-75.114041,40.310499],"type":"Point"}
}