{
  "type": "Feature",
  "properties": {
    "iso:country":"US",
    "sg:address":"3065 Lincoln Hwy E",
    "sg:city":"Paradise",
    "sg:classifiers":[
        {
            "category":"Arts & Performance",
            "subcategory":"Theater",
            "type":"Entertainment"
        }
    ],
    "sg:phone":"+1 717 687 4300",
    "sg:postcode":"17562",
    "sg:province":"PA",
    "sg:website":"www.rainbowdinnertheatre.com",
    "wof:name":"Rainbow Dinner Theatre",
    "wof:placetype":"venue"
},
  "geometry": {"coordinates":[-76.13412099999999,40.010872],"type":"Point"}
}