{
  "type": "Feature",
  "properties": {
    "iso:country":"US",
    "sg:address":"52 Campbell Ave",
    "sg:city":"Clarion",
    "sg:classifiers":[
        {
            "category":"Shopping",
            "subcategory":"Computers & Home Electronics",
            "type":"Retail Goods"
        }
    ],
    "sg:phone":"+1 814 226 5327",
    "sg:postcode":"16214",
    "sg:province":"PA",
    "sg:tags":[
        "software"
    ],
    "sg:website":"www.pcdatasheet.com",
    "wof:name":"P C Datasheet",
    "wof:placetype":"venue"
},
  "geometry": {"coordinates":[-79.384529,41.207668],"type":"Point"}
}