{
  "type": "Feature",
  "properties": {
    "addr:full":"375 Jefferson Ave Washington PA 15301",
    "addr:housenumber":"375",
    "addr:postcode":"15301",
    "addr:street":"Jefferson Ave",
    "iso:country":"US",
    "sg:address":"375 Jefferson Ave",
    "sg:city":"Washington",
    "sg:classifiers":[
        {
            "category":"Recreation",
            "type":"Entertainment"
        }
    ],
    "sg:phone":"+1 724 229 5477",
    "sg:postcode":"15301",
    "sg:province":"PA",
    "sg:tags":[
        "karate",
        "judo",
        "instr"
    ],
    "wof:name":"Dojo",
    "wof:placetype":"venue"
},
  "geometry": {"coordinates":[-80.255285,40.17482],"type":"Point"}
}