{
  "type": "Feature",
  "properties": {
    "iso:country":"US",
    "sg:address":"34 E Market St",
    "sg:city":"Blairsville",
    "sg:classifiers":[
        {
            "category":"Banks & Credit Unions",
            "subcategory":"Bank",
            "type":"Services"
        }
    ],
    "sg:phone":"+1 724 459 6500",
    "sg:postcode":"15717",
    "sg:province":"PA",
    "wof:name":"Pnc Bank",
    "wof:placetype":"venue"
},
  "geometry": {"coordinates":[-79.263425,40.430824],"type":"Point"}
}