{
  "type": "Feature",
  "properties": {
    "addr:full":"3745 N 6th St Harrisburg PA 17110",
    "addr:housenumber":"3745",
    "addr:postcode":"17110",
    "addr:street":"N 6Th St",
    "iso:country":"US",
    "sg:address":"3745 N 6th St",
    "sg:city":"Harrisburg",
    "sg:classifiers":[
        {
            "category":"Bars & Pubs",
            "type":"Food & Drink"
        }
    ],
    "sg:phone":"+1 717 233 0456",
    "sg:postcode":"17110",
    "sg:province":"PA",
    "sg:tags":[
        "restaurant"
    ],
    "wof:name":"Mr G's Place",
    "wof:placetype":"venue"
},
  "geometry": {"coordinates":[-76.894402,40.309799],"type":"Point"}
}