{
  "type": "Feature",
  "properties": {
    "iso:country":"US",
    "sg:address":"423 Plum St Ste 8",
    "sg:city":"Oakmont",
    "sg:classifiers":[
        {
            "category":"Manufacturing",
            "subcategory":"Tools & Machinery",
            "type":"Manufacturing & Wholesale Goods"
        }
    ],
    "sg:phone":"+1 412 826 8486",
    "sg:postcode":"15139",
    "sg:province":"PA",
    "sg:tags":[
        "fasteners-industrial"
    ],
    "wof:name":"Metric Stainless And Standard",
    "wof:placetype":"venue"
},
  "geometry": {"coordinates":[-79.84145599999999,40.512171],"type":"Point"}
}