{
  "type": "Feature",
  "properties": {
    "iso:country":"US",
    "sg:address":"395 Bethlehem Church Rd",
    "sg:city":"Red Lion",
    "sg:classifiers":[
        {
            "category":"Building & Trades",
            "subcategory":"Construction",
            "type":"Services"
        }
    ],
    "sg:phone":"+1 717 246 5874",
    "sg:postcode":"17356",
    "sg:province":"PA",
    "sg:tags":[
        "repairing",
        "remodeling",
        "contractor"
    ],
    "wof:name":"Mardon Builders Inc",
    "wof:placetype":"venue"
},
  "geometry": {"coordinates":[-76.56769199999999,39.891821],"type":"Point"}
}