{
  "type": "Feature",
  "properties": {
    "iso:country":"US",
    "sg:address":"122 S 17th St",
    "sg:city":"Pittsburgh",
    "sg:classifiers":[
        {
            "category":"Health Services",
            "subcategory":"Health Practitioner",
            "type":"Services"
        }
    ],
    "sg:phone":"+1   ",
    "sg:postcode":"15203",
    "sg:province":"PA",
    "wof:name":"Forensic Consulting Services",
    "wof:placetype":"venue"
},
  "geometry": {"coordinates":[-79.982097,40.42838],"type":"Point"}
}