{
  "type": "Feature",
  "properties": {
    "iso:country":"US",
    "sg:address":"234 S 8th St",
    "sg:city":"Philadelphia",
    "sg:classifiers":[
        {
            "category":"Wholesale",
            "subcategory":"Home Furnishings",
            "type":"Manufacturing & Wholesale Goods"
        }
    ],
    "sg:phone":"+1 215 413 5844",
    "sg:postcode":"19107",
    "sg:province":"PA",
    "sg:tags":[
        "lamp"
    ],
    "wof:name":"Norman Manufacturing Co Inc",
    "wof:placetype":"venue"
},
  "geometry": {"coordinates":[-75.154366,39.947525],"type":"Point"}
}