{
  "type": "Feature",
  "properties": {
    "iso:country":"US",
    "sg:address":"3050 Pennell Rd",
    "sg:city":"Media",
    "sg:classifiers":[
        {
            "category":"Restaurant",
            "type":"Food & Drink"
        }
    ],
    "sg:phone":"+1   ",
    "sg:postcode":"19063",
    "sg:province":"PA",
    "sg:tags":[
        "eating"
    ],
    "wof:name":"Hennesseys Tavern & Restauran",
    "wof:placetype":"venue"
},
  "geometry": {"coordinates":[-75.42874399999999,39.870599],"type":"Point"}
}