{
  "type": "Feature",
  "properties": {
    "iso:country":"US",
    "sg:address":"1309 Bridge St",
    "sg:city":"New Cumberland",
    "sg:classifiers":[
        {
            "category":"Professional",
            "subcategory":"Lawyer & Legal Services",
            "type":"Services"
        }
    ],
    "sg:phone":"+1 717 770 0292",
    "sg:postcode":"17070",
    "sg:province":"PA",
    "wof:name":"Feld Arthur M Attorney",
    "wof:placetype":"venue"
},
  "geometry": {"coordinates":[-76.875298,40.234001],"type":"Point"}
}