{
  "type": "Feature",
  "properties": {
    "iso:country":"US",
    "sg:address":"6904 Torresdale Ave",
    "sg:city":"Philadelphia",
    "sg:classifiers":[
        {
            "category":"Restaurant",
            "type":"Food & Drink"
        }
    ],
    "sg:menulink":"http://www.allmenus.com/pa/philadelphia/55240-new-station-pizza-ii/menu/",
    "sg:phone":"+1 215 331 2222",
    "sg:postcode":"19135",
    "sg:province":"PA",
    "sg:tags":[
        "sandwich",
        "salad",
        "burger",
        "cheesesteaks",
        "soup",
        "american",
        "wrap",
        "wing",
        "pizza"
    ],
    "wof:name":"New Station Pizza Ii",
    "wof:placetype":"venue"
},
  "geometry": {"coordinates":[-75.04294,40.02606],"type":"Point"}
}