{
  "type": "Feature",
  "properties": {
    "iso:country":"US",
    "sg:address":"11412 Williamsport Pike",
    "sg:city":"Greencastle",
    "sg:classifiers":[
        {
            "category":"Professional",
            "subcategory":"Art Services",
            "type":"Services"
        }
    ],
    "sg:phone":"+1 717 597 4994",
    "sg:postcode":"17225",
    "sg:province":"PA",
    "sg:tags":[
        "commercial",
        "photography",
        "aerial"
    ],
    "wof:name":"National Airviews Inc",
    "wof:placetype":"venue"
},
  "geometry": {"coordinates":[-77.736552,39.778753],"type":"Point"}
}