{
  "type": "Feature",
  "properties": {
    "iso:country":"US",
    "sg:address":"1639 S 24th St",
    "sg:city":"Philadelphia",
    "sg:classifiers":[
        {
            "category":"Food & Beverages",
            "subcategory":"Groceries & Convenience Stores",
            "type":"Retail Goods"
        }
    ],
    "sg:phone":"+1 215 463 8319",
    "sg:postcode":"19145",
    "sg:province":"PA",
    "sg:tags":[
        "grocer",
        "sandwich"
    ],
    "wof:name":"Morris Super Deli",
    "wof:placetype":"venue"
},
  "geometry": {"coordinates":[-75.18472,39.931691],"type":"Point"}
}