{
  "type": "Feature",
  "properties": {
    "iso:country":"US",
    "sg:address":"930 Red Rose Ct",
    "sg:city":"Lancaster",
    "sg:classifiers":[
        {
            "category":"Personal",
            "subcategory":"Hair Removal",
            "type":"Services"
        }
    ],
    "sg:phone":"+1   ",
    "sg:postcode":"17601",
    "sg:province":"PA",
    "wof:name":"Harry E Radcliffe",
    "wof:placetype":"venue"
},
  "geometry": {"coordinates":[-76.360603,40.059452],"type":"Point"}
}