{
  "type": "Feature",
  "properties": {
    "addr:full":"237 Centerville Rd Lancaster PA 17603",
    "addr:housenumber":"237",
    "addr:postcode":"17603",
    "addr:street":"Centerville Rd",
    "iso:country":"US",
    "sg:address":"237 Centerville Rd",
    "sg:city":"Lancaster",
    "sg:phone":"+1 717 299 5691",
    "sg:postcode":"17603",
    "sg:province":"PA",
    "sg:website":"http://www.thatfishplace.com",
    "wof:name":"That Fish Place-That Pet Place",
    "wof:placetype":"venue"
},
  "geometry": {"coordinates":[-76.392961,40.047836],"type":"Point"}
}