{
  "type": "Feature",
  "properties": {
    "iso:country":"US",
    "sg:address":"300 Mount Lebanon Blvd Ste 220",
    "sg:city":"Pittsburgh",
    "sg:classifiers":[
        {
            "category":"Shopping",
            "subcategory":"Jewelry",
            "type":"Retail Goods"
        }
    ],
    "sg:phone":"+1 412 343 3354",
    "sg:postcode":"15234",
    "sg:province":"PA",
    "wof:name":"Koinz Collector Shop",
    "wof:placetype":"venue"
},
  "geometry": {"coordinates":[-80.035971,40.368768],"type":"Point"}
}