{
  "type": "Feature",
  "properties": {
    "iso:country":"US",
    "sg:address":"750 Washington Rd",
    "sg:city":"Pittsburgh",
    "sg:classifiers":[
        {
            "category":"Real Estate",
            "subcategory":"Real Estate Agent",
            "type":"Services"
        }
    ],
    "sg:phone":"+1 412 531 1656",
    "sg:postcode":"15228",
    "sg:province":"PA",
    "wof:name":"Point View Properties",
    "wof:placetype":"venue"
},
  "geometry": {"coordinates":[-80.046212,40.377993],"type":"Point"}
}