{
  "type": "Feature",
  "properties": {
    "addr:full":"117 S Hamilton Ave  Greensburg PA 15601",
    "addr:housenumber":"117",
    "addr:postcode":"15601",
    "addr:street":"S Hamilton Ave",
    "iso:country":"US",
    "sg:address":"117 S Hamilton Ave ",
    "sg:city":"Greensburg",
    "sg:classifiers":[
        {
            "category":"Restaurant",
            "type":"Food & Drink"
        }
    ],
    "sg:menulink":"http://www.allmenus.com/pa/greensburg/286894-royal-pizza-house--six-pack/menu/",
    "sg:phone":"+1 724 837 7474",
    "sg:postcode":"15601",
    "sg:province":"PA",
    "sg:tags":[
        "wing",
        "american",
        "sandwich",
        "chicken",
        "pizza"
    ],
    "wof:name":"Royal Pizza House & Six Pack",
    "wof:placetype":"venue"
},
  "geometry": {"coordinates":[-79.55752200000001,40.298566],"type":"Point"}
}