{
  "type": "Feature",
  "properties": {
    "iso:country":"US",
    "sg:address":"1409 State St",
    "sg:city":"Pottstown",
    "sg:classifiers":[
        {
            "category":"Professional",
            "type":"Services"
        }
    ],
    "sg:phone":"+1   ",
    "sg:postcode":"19464",
    "sg:province":"PA",
    "sg:tags":[
        "me"
    ],
    "wof:name":"Upworth Art At The Anvl Stdio",
    "wof:placetype":"venue"
},
  "geometry": {"coordinates":[-75.645116,40.278203],"type":"Point"}
}