{
  "type": "Feature",
  "properties": {
    "iso:country":"US",
    "sg:address":"1548 S 13th St",
    "sg:city":"Philadelphia",
    "sg:classifiers":[
        {
            "category":"Restaurant",
            "type":"Food & Drink"
        }
    ],
    "sg:phone":"+1 215 463 2762",
    "sg:postcode":"19147",
    "sg:province":"PA",
    "sg:tags":[
        "sandwich"
    ],
    "wof:name":"888 Cafe",
    "wof:placetype":"venue"
},
  "geometry": {"coordinates":[-75.16621499999999,39.930817],"type":"Point"}
}