{
  "type": "Feature",
  "properties": {
    "iso:country":"US",
    "sg:address":"345 Main St",
    "sg:city":"New Kensington",
    "sg:classifiers":[
        {
            "category":"Autos & Motor Vehicles",
            "subcategory":"Auto Supplies",
            "type":"Retail Goods"
        }
    ],
    "sg:phone":"+1 724 335 9801",
    "sg:postcode":"15068",
    "sg:province":"PA",
    "wof:name":"Mar-Mac Tire Co Inc",
    "wof:placetype":"venue"
},
  "geometry": {"coordinates":[-79.761105,40.556051],"type":"Point"}
}