{
  "type": "Feature",
  "properties": {
    "iso:country":"US",
    "sg:address":"23 W Seminary St",
    "sg:city":"Mercersburg",
    "sg:classifiers":[
        {
            "category":"Professional",
            "type":"Services"
        }
    ],
    "sg:phone":"+1   ",
    "sg:postcode":"17236",
    "sg:province":"PA",
    "wof:name":"Star Theatre",
    "wof:placetype":"venue"
},
  "geometry": {"coordinates":[-77.90524000000001,39.828209],"type":"Point"}
}