{
  "type": "Feature",
  "properties": {
    "iso:country":"US",
    "sg:address":"26 Cotton Rd",
    "sg:city":"Levittown",
    "sg:classifiers":[
        {
            "category":"Wholesale",
            "subcategory":"Vending Machines",
            "type":"Manufacturing & Wholesale Goods"
        }
    ],
    "sg:phone":"+1   ",
    "sg:postcode":"19057",
    "sg:province":"PA",
    "sg:tags":[
        "operator"
    ],
    "wof:name":"Cindy Riedel",
    "wof:placetype":"venue"
},
  "geometry": {"coordinates":[-74.871788,40.155364],"type":"Point"}
}