{
  "type": "Feature",
  "properties": {
    "addr:full":"5727 Schultz Rd Erie PA 16509",
    "addr:housenumber":"5727",
    "addr:postcode":"16509",
    "addr:street":"Schultz Rd",
    "iso:country":"US",
    "sg:address":"5727 Schultz Rd",
    "sg:city":"Erie",
    "sg:classifiers":[
        {
            "category":"Professional",
            "subcategory":"Management & Consulting",
            "type":"Services"
        },
        {
            "category":"Insurance",
            "subcategory":"Insurance Agent",
            "type":"Services"
        }
    ],
    "sg:phone":"+1 814 824 5315",
    "sg:postcode":"16509",
    "sg:province":"PA",
    "sg:tags":[
        "consultant",
        "financial"
    ],
    "wof:name":"R P Wittuck & Associates Inc",
    "wof:placetype":"venue"
},
  "geometry": {"coordinates":[-80.047766,42.085876],"type":"Point"}
}