{
  "type": "Feature",
  "properties": {
    "addr:full":"1813 Girard Ave Allentown PA 18104",
    "addr:housenumber":"1813",
    "addr:postcode":"18104",
    "addr:street":"Girard Ave",
    "iso:country":"US",
    "sg:address":"1813 Girard Ave",
    "sg:city":"Allentown",
    "sg:classifiers":[
        {
            "category":"Building & Trades",
            "subcategory":"Construction",
            "type":"Services"
        }
    ],
    "sg:phone":"+1 610 799 3329",
    "sg:postcode":"18104",
    "sg:province":"PA",
    "sg:tags":[
        "excavating",
        "contractor"
    ],
    "wof:name":"Robertson Excavating Inc",
    "wof:placetype":"venue"
},
  "geometry": {"coordinates":[-75.51024099999999,40.626614],"type":"Point"}
}