{
  "type": "Feature",
  "properties": {
    "addr:full":"172 Taft Ave Reading PA 19606",
    "addr:housenumber":"172",
    "addr:postcode":"19606",
    "addr:street":"Taft Ave",
    "iso:country":"US",
    "sg:address":"172 Taft Ave",
    "sg:city":"Reading",
    "sg:classifiers":[
        {
            "category":"Wholesale",
            "subcategory":"Home Furnishings",
            "type":"Manufacturing & Wholesale Goods"
        }
    ],
    "sg:phone":"+1   ",
    "sg:postcode":"19606",
    "sg:province":"PA",
    "wof:name":"Master Floor Cvg Specialists",
    "wof:placetype":"venue"
},
  "geometry": {"coordinates":[-75.87009999999999,40.347204],"type":"Point"}
}