{
  "type": "Feature",
  "properties": {
    "iso:country":"US",
    "sg:address":"4905 Frankford Ave",
    "sg:city":"Philadelphia",
    "sg:classifiers":[
        {
            "category":"Real Estate",
            "subcategory":"Real Estate Agent",
            "type":"Services"
        }
    ],
    "sg:phone":"+1 215 643 3375",
    "sg:postcode":"19124",
    "sg:province":"PA",
    "wof:name":"Idler Perkarski Agency",
    "wof:placetype":"venue"
},
  "geometry": {"coordinates":[-75.08093599999999,40.019608],"type":"Point"}
}