{
  "type": "Feature",
  "properties": {
    "iso:country":"US",
    "sg:address":"2005 S Easton Rd",
    "sg:city":"Doylestown",
    "sg:classifiers":[
        {
            "category":"Professional",
            "subcategory":"Employment Agencies",
            "type":"Services"
        }
    ],
    "sg:phone":"+1 215 230 7227",
    "sg:postcode":"18901",
    "sg:province":"PA",
    "sg:tags":[
        "consultant",
        "search",
        "executive"
    ],
    "wof:name":"C Berke & Assoc",
    "wof:placetype":"venue"
},
  "geometry": {"coordinates":[-75.127652,40.294109],"type":"Point"}
}