{
  "type": "Feature",
  "properties": {
    "addr:full":"960 W Wyoming St Allentown PA 18103",
    "addr:housenumber":"960",
    "addr:postcode":"18103",
    "addr:street":"W Wyoming St",
    "iso:country":"US",
    "sg:address":"960 W Wyoming St",
    "sg:city":"Allentown",
    "sg:classifiers":[
        {
            "category":"Professional",
            "subcategory":"Lawyer & Legal Services",
            "type":"Services"
        }
    ],
    "sg:phone":"+1 610 437 1101",
    "sg:postcode":"18103",
    "sg:province":"PA",
    "wof:name":"Cappy's",
    "wof:placetype":"venue"
},
  "geometry": {"coordinates":[-75.47350299999999,40.589199],"type":"Point"}
}