{
  "type": "Feature",
  "properties": {
    "iso:country":"US",
    "sg:address":"3565 Hulmeville Rd",
    "sg:city":"Bensalem",
    "sg:classifiers":[
        {
            "category":"Retail",
            "subcategory":"Self-service Laundry",
            "type":"Services"
        }
    ],
    "sg:phone":"+1 215 245 7558",
    "sg:postcode":"19020",
    "sg:province":"PA",
    "sg:tags":[
        "dry",
        "cleaning"
    ],
    "wof:name":"Mayflower Cleaners",
    "wof:placetype":"venue"
},
  "geometry": {"coordinates":[-74.94000200000001,40.104],"type":"Point"}
}