{
  "type": "Feature",
  "properties": {
    "iso:country":"US",
    "sg:address":"1701 Cottman Ave",
    "sg:city":"Philadelphia",
    "sg:classifiers":[
        {
            "category":"Food & Beverages",
            "subcategory":"Groceries & Convenience Stores",
            "type":"Retail Goods"
        }
    ],
    "sg:phone":"+1 215 728 7998",
    "sg:postcode":"19111",
    "sg:province":"PA",
    "wof:name":"Cottman EZ Gas",
    "wof:placetype":"venue"
},
  "geometry": {"coordinates":[-75.071462,40.054289],"type":"Point"}
}