{
  "type": "Feature",
  "properties": {
    "addr:full":"409 Arden Dr Monroeville PA 15146",
    "addr:housenumber":"409",
    "addr:postcode":"15146",
    "addr:street":"Arden Dr",
    "iso:country":"US",
    "sg:address":"409 Arden Dr",
    "sg:city":"Monroeville",
    "sg:classifiers":[
        {
            "category":"Organizations",
            "subcategory":"Religious Organization",
            "type":"Services"
        }
    ],
    "sg:phone":"+1 412 374 6221",
    "sg:postcode":"15146",
    "sg:province":"PA",
    "sg:tags":[
        "clergy"
    ],
    "wof:name":"Joseph L Garlington",
    "wof:placetype":"venue"
},
  "geometry": {"coordinates":[-79.73787,40.403032],"type":"Point"}
}