{
  "type": "Feature",
  "properties": {
    "iso:country":"US",
    "sg:address":"2155 State Rte 119",
    "sg:city":"Greensburg",
    "sg:classifiers":[
        {
            "category":"Restaurant",
            "type":"Food & Drink"
        }
    ],
    "sg:phone":"+1 724 838 9200",
    "sg:postcode":"15601",
    "sg:province":"PA",
    "wof:name":"Juicy Lucy's",
    "wof:placetype":"venue"
},
  "geometry": {"coordinates":[-79.555567,40.272175],"type":"Point"}
}