{
  "type": "Feature",
  "properties": {
    "iso:country":"US",
    "sg:address":"43 Ocelot Dr",
    "sg:city":"Hanover",
    "sg:classifiers":[
        {
            "category":"Professional",
            "type":"Services"
        }
    ],
    "sg:phone":"+1 717 630 9345",
    "sg:postcode":"17331",
    "sg:province":"PA",
    "sg:tags":[
        "establishment"
    ],
    "wof:name":"Genlyte",
    "wof:placetype":"venue"
},
  "geometry": {"coordinates":[-77.014234,39.800062],"type":"Point"}
}