{
  "type": "Feature",
  "properties": {
    "iso:country":"US",
    "sg:address":"100 A St",
    "sg:city":"Penn Hills",
    "sg:classifiers":[
        {
            "category":"Freight",
            "type":"Transportation"
        }
    ],
    "sg:phone":"+1 412 243 8777",
    "sg:postcode":"15235",
    "sg:province":"PA",
    "sg:tags":[
        "trucking"
    ],
    "wof:name":"Harcheload Trucking Co",
    "wof:placetype":"venue"
},
  "geometry": {"coordinates":[-79.794833,40.467231],"type":"Point"}
}