{
  "type": "Feature",
  "properties": {
    "iso:country":"US",
    "sg:address":"550 Chauvet Dr",
    "sg:city":"Pittsburgh",
    "sg:classifiers":[
        {
            "category":"Professional",
            "subcategory":"Printing & Photocopies",
            "type":"Services"
        }
    ],
    "sg:phone":"+1 412 446 2788",
    "sg:postcode":"15275",
    "sg:province":"PA",
    "sg:website":"www.alphagraphics.com/centers/pi...",
    "wof:name":"Alphagraphics",
    "wof:placetype":"venue"
},
  "geometry": {"coordinates":[-80.18354,40.447542],"type":"Point"}
}