{
  "type": "Feature",
  "properties": {
    "iso:country":"US",
    "sg:address":"98 Miner St",
    "sg:city":"Hudson",
    "sg:classifiers":[
        {
            "category":"Professional",
            "subcategory":"Computer Services",
            "type":"Services"
        }
    ],
    "sg:phone":"+1 570 822 0789",
    "sg:postcode":"18705",
    "sg:province":"PA",
    "wof:name":"Certified Solutions",
    "wof:placetype":"venue"
},
  "geometry": {"coordinates":[-75.831638,41.275091],"type":"Point"}
}