{
  "type": "Feature",
  "properties": {
    "iso:country":"US",
    "sg:address":"375 S 7th St",
    "sg:city":"Harrisburg",
    "sg:classifiers":[
        {
            "category":"Wholesale",
            "subcategory":"Photographic Equipment",
            "type":"Manufacturing & Wholesale Goods"
        }
    ],
    "sg:phone":"+1   ",
    "sg:postcode":"17113",
    "sg:province":"PA",
    "sg:tags":[
        "photo"
    ],
    "wof:name":"Capital X Ray Solutions Svc",
    "wof:placetype":"venue"
},
  "geometry": {"coordinates":[-76.830274,40.235758],"type":"Point"}
}