{
  "type": "Feature",
  "properties": {
    "iso:country":"US",
    "sg:address":"1126 W Market St",
    "sg:city":"Perkasie",
    "sg:phone":"+1 215 257 7864",
    "sg:postcode":"18944",
    "sg:province":"PA",
    "wof:name":"Edward's Service & Supply",
    "wof:placetype":"venue"
},
  "geometry": {"coordinates":[-75.30171,40.376738],"type":"Point"}
}