{
  "type": "Feature",
  "properties": {
    "addr:full":"1400 Martin St State College PA 16803",
    "addr:housenumber":"1400",
    "addr:postcode":"16803",
    "addr:street":"Martin St",
    "iso:country":"US",
    "sg:address":"1400 Martin St",
    "sg:city":"State College",
    "sg:classifiers":[
        {
            "category":"Professional",
            "subcategory":"Management & Consulting",
            "type":"Services"
        }
    ],
    "sg:phone":"+1   ",
    "sg:postcode":"16803",
    "sg:province":"PA",
    "sg:tags":[
        "retail",
        "direct",
        "sales"
    ],
    "wof:name":"P & P Calzones Inc",
    "wof:placetype":"venue"
},
  "geometry": {"coordinates":[-77.88654200000001,40.801377],"type":"Point"}
}