{
  "type": "Feature",
  "properties": {
    "iso:country":"US",
    "sg:address":"934 New Castle Rd",
    "sg:city":"Butler",
    "sg:classifiers":[
        {
            "category":"Autos & Motor Vehicles",
            "subcategory":"Automobile Sales",
            "type":"Retail Goods"
        }
    ],
    "sg:phone":"+1 724 865 3033",
    "sg:postcode":"16001",
    "sg:province":"PA",
    "sg:tags":[
        "car",
        "dealer"
    ],
    "wof:name":"Gerald P Rumburg Notary Public",
    "wof:placetype":"venue"
},
  "geometry": {"coordinates":[-80.011737,40.900516],"type":"Point"}
}