{
  "type": "Feature",
  "properties": {
    "iso:country":"US",
    "sg:address":"3040 Windsor Rd",
    "sg:city":"Red Lion",
    "sg:classifiers":[
        {
            "category":"Shopping",
            "subcategory":"Clothing, Apparel, & Fashions",
            "type":"Retail Goods"
        }
    ],
    "sg:phone":"+1 717 244 6425",
    "sg:postcode":"17356",
    "sg:province":"PA",
    "wof:name":"Cape Horn Western Wear",
    "wof:placetype":"venue"
},
  "geometry": {"coordinates":[-76.580168,39.902226],"type":"Point"}
}