{
  "type": "Feature",
  "properties": {
    "iso:country":"US",
    "sg:address":"1301 Virginia Dr",
    "sg:city":"Fort Washington",
    "sg:classifiers":[
        {
            "category":"Real Estate",
            "subcategory":"Real Estate Agent",
            "type":"Services"
        }
    ],
    "sg:phone":"+1 215 892 8300",
    "sg:postcode":"19034",
    "sg:province":"PA",
    "wof:name":"Long & Foster Realtors",
    "wof:placetype":"venue"
},
  "geometry": {"coordinates":[-75.168792,40.142054],"type":"Point"}
}