{
  "type": "Feature",
  "properties": {
    "iso:country":"US",
    "sg:address":"8140 Verree Rd",
    "sg:city":"Philadelphia",
    "sg:classifiers":[
        {
            "category":"Health Services",
            "subcategory":"Doctor",
            "type":"Services"
        }
    ],
    "sg:phone":"+1 215 725 9350",
    "sg:postcode":"19111",
    "sg:province":"PA",
    "wof:name":"Harvey M Edelman DDS",
    "wof:placetype":"venue"
},
  "geometry": {"coordinates":[-75.073925,40.074812],"type":"Point"}
}