{
  "type": "Feature",
  "properties": {
    "iso:country":"US",
    "sg:address":"589 Bethlehem Pike # 100",
    "sg:city":"Montgomeryville",
    "sg:classifiers":[
        {
            "category":"Professional",
            "subcategory":"Business Services",
            "type":"Services"
        }
    ],
    "sg:phone":"+1 215 997 5700",
    "sg:postcode":"18936",
    "sg:province":"PA",
    "sg:tags":[
        "holding"
    ],
    "wof:name":"Krepps Holdings",
    "wof:placetype":"venue"
},
  "geometry": {"coordinates":[-75.243816,40.247114],"type":"Point"}
}