{
  "type": "Feature",
  "properties": {
    "iso:country":"US",
    "sg:address":"14 S Pennell Rd",
    "sg:city":"Media",
    "sg:classifiers":[
        {
            "category":"Wholesale",
            "subcategory":"Groceries",
            "type":"Manufacturing & Wholesale Goods"
        }
    ],
    "sg:phone":"+1 610 565 2739",
    "sg:postcode":"19063",
    "sg:province":"PA",
    "sg:tags":[
        "beverage"
    ],
    "wof:name":"Lima Beverage",
    "wof:placetype":"venue"
},
  "geometry": {"coordinates":[-75.44001,39.91016],"type":"Point"}
}