{
  "type": "Feature",
  "properties": {
    "addr:full":"2206 Market St Philadelphia PA 19103",
    "addr:housenumber":"2206",
    "addr:postcode":"19103",
    "addr:street":"Market St",
    "iso:country":"US",
    "sg:address":"2206 Market St",
    "sg:city":"Philadelphia",
    "sg:classifiers":[
        {
            "category":"Restaurant",
            "type":"Food & Drink"
        }
    ],
    "sg:menulink":"http://www.allmenus.com/pa/philadelphia/261914-golden-lake/menu/",
    "sg:phone":"+1 215 568 7727",
    "sg:postcode":"19103",
    "sg:province":"PA",
    "sg:tags":[
        "asian",
        "chinese"
    ],
    "wof:name":"Golden Lake",
    "wof:placetype":"venue"
},
  "geometry": {"coordinates":[-75.176863,39.953913],"type":"Point"}
}