{
  "type": "Feature",
  "properties": {
    "iso:country":"US",
    "sg:address":"599 Lincoln Hwy",
    "sg:city":"North Versailles",
    "sg:classifiers":[
        {
            "category":"Shopping",
            "subcategory":"Pharmacy",
            "type":"Retail Goods"
        }
    ],
    "sg:phone":"+1   ",
    "sg:postcode":"15137",
    "sg:province":"PA",
    "sg:tags":[
        "drug",
        "store"
    ],
    "wof:name":"Eckerd",
    "wof:placetype":"venue"
},
  "geometry": {"coordinates":[-79.82474499999999,40.384997],"type":"Point"}
}