{
  "type": "Feature",
  "properties": {
    "iso:country":"US",
    "sg:address":"4604 E Prospect Rd",
    "sg:city":"York",
    "sg:classifiers":[
        {
            "category":"Building & Trades",
            "subcategory":"Pest Control",
            "type":"Services"
        }
    ],
    "sg:phone":"+1   ",
    "sg:postcode":"17406",
    "sg:province":"PA",
    "wof:name":"Morans Elite Trmt & Pest Ctrl",
    "wof:placetype":"venue"
},
  "geometry": {"coordinates":[-76.575868,39.970909],"type":"Point"}
}