{
  "type": "Feature",
  "properties": {
    "addr:full":"6434 Woodland Ave Philadelphia PA 19142",
    "addr:housenumber":"6434",
    "addr:postcode":"19142",
    "addr:street":"Woodland Ave",
    "iso:country":"US",
    "sg:address":"6434 Woodland Ave",
    "sg:city":"Philadelphia",
    "sg:classifiers":[
        {
            "category":"Health Services",
            "subcategory":"Clinic",
            "type":"Services"
        }
    ],
    "sg:phone":"+1 215 729 2340",
    "sg:postcode":"19142",
    "sg:province":"PA",
    "sg:tags":[
        "specialty",
        "outpatient"
    ],
    "wof:name":"One Day At A Time",
    "wof:placetype":"venue"
},
  "geometry": {"coordinates":[-75.23332600000001,39.926271],"type":"Point"}
}