{
  "type": "Feature",
  "properties": {
    "addr:full":"9th at Hamilton Street Allentown PA 18101",
    "addr:postcode":"18101",
    "addr:street":"Street",
    "iso:country":"US",
    "sg:address":"9th at Hamilton Street",
    "sg:city":"Allentown",
    "sg:classifiers":[
        {
            "category":"Food & Beverages",
            "subcategory":"Bakery",
            "type":"Retail Goods"
        }
    ],
    "sg:postcode":"18101",
    "sg:province":"PA",
    "sg:tags":[
        "sandwich"
    ],
    "wof:name":"Badda Bing",
    "wof:placetype":"venue"
},
  "geometry": {"coordinates":[-75.475431,40.601141],"type":"Point"}
}