{
  "type": "Feature",
  "properties": {
    "iso:country":"US",
    "sg:address":"214 6th St",
    "sg:city":"Honesdale",
    "sg:classifiers":[
        {
            "category":"Manufacturing",
            "subcategory":"Wood Products",
            "type":"Manufacturing & Wholesale Goods"
        },
        {
            "category":"Home & Garden",
            "subcategory":"Furniture",
            "type":"Retail Goods"
        }
    ],
    "sg:phone":"+1 570 251 8218",
    "sg:postcode":"18431",
    "sg:province":"PA",
    "sg:tags":[
        "builder",
        "custom",
        "mfg"
    ],
    "sg:website":"www.newwaveframes.com",
    "wof:name":"New Wave Custom Woodwork Inc",
    "wof:placetype":"venue"
},
  "geometry": {"coordinates":[-75.25267700000001,41.571002],"type":"Point"}
}