{
  "type": "Feature",
  "properties": {
    "iso:country":"US",
    "sg:address":"3813 W 9th St",
    "sg:city":"Marcus Hook",
    "sg:classifiers":[
        {
            "category":"Building & Trades",
            "subcategory":"Landscaping Services",
            "type":"Services"
        }
    ],
    "sg:phone":"+1   ",
    "sg:postcode":"19061",
    "sg:province":"PA",
    "sg:tags":[
        "landscape",
        "contractor"
    ],
    "wof:name":"Burke Landscape Supply",
    "wof:placetype":"venue"
},
  "geometry": {"coordinates":[-75.40506999999999,39.831235],"type":"Point"}
}