{
  "type": "Feature",
  "properties": {
    "iso:country":"US",
    "sg:address":"579 W Lancaster Ave",
    "sg:city":"Bryn Mawr",
    "sg:classifiers":[
        {
            "category":"Home & Garden",
            "subcategory":"Building Materials",
            "type":"Retail Goods"
        }
    ],
    "sg:phone":"+1 610 647 0357",
    "sg:postcode":"19101",
    "sg:province":"PA",
    "sg:tags":[
        "shower",
        "door",
        "enclosure"
    ],
    "wof:name":"Bryn Mawr Shower Door",
    "wof:placetype":"venue"
},
  "geometry": {"coordinates":[-75.310429,40.017592],"type":"Point"}
}