{
  "type": "Feature",
  "properties": {
    "iso:country":"US",
    "sg:address":"2365 E York St",
    "sg:city":"Philadelphia",
    "sg:classifiers":[
        {
            "category":"Retail",
            "subcategory":"Car Wash",
            "type":"Services"
        }
    ],
    "sg:phone":"+1 215 634 4017",
    "sg:postcode":"19125",
    "sg:province":"PA",
    "sg:tags":[
        "automobile",
        "detail",
        "clean"
    ],
    "wof:name":"Clean Intentions",
    "wof:placetype":"venue"
},
  "geometry": {"coordinates":[-75.125032,39.978715],"type":"Point"}
}