{
  "type": "Feature",
  "properties": {
    "addr:full":"3548 Washington Ave Finleyville PA 15332",
    "addr:housenumber":"3548",
    "addr:postcode":"15332",
    "addr:street":"Washington Ave",
    "iso:country":"US",
    "sg:address":"3548 Washington Ave",
    "sg:city":"Finleyville",
    "sg:classifiers":[
        {
            "category":"Professional",
            "subcategory":"Lawyer & Legal Services",
            "type":"Services"
        }
    ],
    "sg:phone":"+1 724 348 6990",
    "sg:postcode":"15332",
    "sg:province":"PA",
    "wof:name":"Timothy R Berggren Attorney",
    "wof:placetype":"venue"
},
  "geometry": {"coordinates":[-80.003304,40.252399],"type":"Point"}
}