{
  "type": "Feature",
  "properties": {
    "iso:country":"US",
    "sg:address":"901 Alison Ave",
    "sg:city":"Mechanicsburg",
    "sg:classifiers":[
        {
            "category":"Professional",
            "subcategory":"Lawyer & Legal Services",
            "type":"Services"
        }
    ],
    "sg:phone":"+1 717 691 1074",
    "sg:postcode":"17055",
    "sg:province":"PA",
    "wof:name":"Niesen Thomas T Atty",
    "wof:placetype":"venue"
},
  "geometry": {"coordinates":[-76.9879,40.211601],"type":"Point"}
}