{
  "type": "Feature",
  "properties": {
    "iso:country":"US",
    "sg:address":"900 E 8th Ave",
    "sg:city":"King Of Prussia",
    "sg:classifiers":[
        {
            "category":"Professional",
            "subcategory":"Computer Services",
            "type":"Services"
        }
    ],
    "sg:phone":"+1 610 768 8995",
    "sg:postcode":"19406",
    "sg:province":"PA",
    "sg:tags":[
        "software"
    ],
    "wof:name":"Tektronix Inc",
    "wof:placetype":"venue"
},
  "geometry": {"coordinates":[-75.408203,40.099869],"type":"Point"}
}