{
  "type": "Feature",
  "properties": {
    "iso:country":"US",
    "sg:address":"105 Anderson Rd",
    "sg:city":"Butler",
    "sg:classifiers":[
        {
            "category":"Personal",
            "subcategory":"Beauty Salon",
            "type":"Services"
        }
    ],
    "sg:phone":"+1 724 352 0149",
    "sg:postcode":"16002",
    "sg:province":"PA",
    "wof:name":"Judy Regis Jr",
    "wof:placetype":"venue"
},
  "geometry": {"coordinates":[-79.905776,40.757121],"type":"Point"}
}