{
  "type": "Feature",
  "properties": {
    "addr:full":"322 E High St Pottstown PA 19464",
    "addr:housenumber":"322",
    "addr:postcode":"19464",
    "addr:street":"E High St",
    "iso:country":"US",
    "sg:address":"322 E High St",
    "sg:city":"Pottstown",
    "sg:classifiers":[
        {
            "category":"Food & Beverages",
            "subcategory":"Bakery",
            "type":"Retail Goods"
        }
    ],
    "sg:phone":"+1 610 323 2020",
    "sg:postcode":"19464",
    "sg:province":"PA",
    "sg:tags":[
        "baker"
    ],
    "wof:name":"Beverly's Pastry Shop",
    "wof:placetype":"venue"
},
  "geometry": {"coordinates":[-75.64675,40.245151],"type":"Point"}
}