{
  "type": "Feature",
  "properties": {
    "addr:full":"700 Nutt Rd Phoenixville PA 19460",
    "addr:housenumber":"700",
    "addr:postcode":"19460",
    "addr:street":"Nutt Rd",
    "iso:country":"US",
    "sg:address":"700 Nutt Rd",
    "sg:city":"Phoenixville",
    "sg:classifiers":[
        {
            "category":"Restaurant",
            "type":"Food & Drink"
        }
    ],
    "sg:menulink":"http://www.allmenus.com/pa/phoenixville/123176-quiznos-sub/menu/",
    "sg:phone":"+1 610 933 6919",
    "sg:postcode":"19460",
    "sg:province":"PA",
    "sg:tags":[
        "wrap",
        "american",
        "sandwich"
    ],
    "wof:name":"Quiznos Sub",
    "wof:placetype":"venue"
},
  "geometry": {"coordinates":[-75.534762,40.132083],"type":"Point"}
}