{
  "type": "Feature",
  "properties": {
    "iso:country":"US",
    "sg:address":"194 Oak St",
    "sg:city":"Pittston",
    "sg:classifiers":[
        {
            "category":"Restaurant",
            "type":"Food & Drink"
        }
    ],
    "sg:phone":"+1 570 883 7557",
    "sg:postcode":"18640",
    "sg:province":"PA",
    "sg:tags":[
        "parlor",
        "eating",
        "ice",
        "cream"
    ],
    "wof:name":"Ben & George's Inc",
    "wof:placetype":"venue"
},
  "geometry": {"coordinates":[-75.780013,41.310923],"type":"Point"}
}