{
  "type": "Feature",
  "properties": {
    "addr:full":"306 W Penn Ave Stoystown PA 15563",
    "addr:housenumber":"306",
    "addr:postcode":"15563",
    "addr:street":"W Penn Ave",
    "iso:country":"US",
    "sg:address":"306 W Penn Ave",
    "sg:city":"Stoystown",
    "sg:classifiers":[
        {
            "category":"Personal",
            "subcategory":"Beauty Salon",
            "type":"Services"
        }
    ],
    "sg:phone":"+1 814 893 6171",
    "sg:postcode":"15563",
    "sg:province":"PA",
    "wof:name":"Dimensions Hair Styling Ctr",
    "wof:placetype":"venue"
},
  "geometry": {"coordinates":[-78.956638,40.10363],"type":"Point"}
}