{
  "type": "Feature",
  "properties": {
    "addr:full":"22 Brown St # & Philadelphia PA 19123",
    "addr:housenumber":"22;#",
    "addr:postcode":"19123",
    "addr:street":"Brown St",
    "iso:country":"US",
    "sg:address":"22 Brown St # &",
    "sg:city":"Philadelphia",
    "sg:classifiers":[
        {
            "category":"Social Services",
            "subcategory":"Child Care",
            "type":"Services"
        },
        {
            "category":"Education",
            "subcategory":"School",
            "type":"Public Place"
        }
    ],
    "sg:phone":"+1 215 684 5098",
    "sg:postcode":"19123",
    "sg:province":"PA",
    "sg:tags":[
        "day"
    ],
    "wof:name":"Comprehensive Day Care Centers",
    "wof:placetype":"venue"
},
  "geometry": {"coordinates":[-75.148697,39.962898],"type":"Point"}
}