{
  "type": "Feature",
  "properties": {
    "iso:country":"US",
    "sg:address":"1615 S Market St",
    "sg:city":"Elizabethtown",
    "sg:classifiers":[
        {
            "category":"Shopping",
            "subcategory":"Gifts & Souvenirs",
            "type":"Retail Goods"
        }
    ],
    "sg:phone":"+1   ",
    "sg:postcode":"17022",
    "sg:province":"PA",
    "wof:name":"Matthews Hallmark Inc",
    "wof:placetype":"venue"
},
  "geometry": {"coordinates":[-76.584813,40.138154],"type":"Point"}
}