{
  "type": "Feature",
  "properties": {
    "iso:country":"US",
    "sg:address":"2082 W Market St",
    "sg:city":"Pottsville",
    "sg:classifiers":[
        {
            "category":"Restaurant",
            "type":"Food & Drink"
        }
    ],
    "sg:phone":"+1   ",
    "sg:postcode":"17901",
    "sg:province":"PA",
    "sg:tags":[
        "eating"
    ],
    "wof:name":"Grammas Family Dining",
    "wof:placetype":"venue"
},
  "geometry": {"coordinates":[-76.222397,40.676379],"type":"Point"}
}