{
  "type": "Feature",
  "properties": {
    "iso:country":"US",
    "sg:address":"2323 Main St",
    "sg:city":"Pittsburgh",
    "sg:classifiers":[
        {
            "category":"Building & Trades",
            "subcategory":"Construction",
            "type":"Services"
        }
    ],
    "sg:phone":"+1   ",
    "sg:postcode":"15215",
    "sg:province":"PA",
    "sg:tags":[
        "underground",
        "utility",
        "contractor"
    ],
    "wof:name":"Nicassio Corporation",
    "wof:placetype":"venue"
},
  "geometry": {"coordinates":[-79.911732,40.493149],"type":"Point"}
}