{
  "type": "Feature",
  "properties": {
    "iso:country":"US",
    "sg:address":"61 Greenwood Rd",
    "sg:city":"Altoona",
    "sg:classifiers":[
        {
            "category":"Retail",
            "subcategory":"Auto Repair",
            "type":"Services"
        }
    ],
    "sg:phone":"+1 814 941 4560",
    "sg:postcode":"16602",
    "sg:province":"PA",
    "sg:tags":[
        "repairing",
        "engine"
    ],
    "wof:name":"Steele's Small Engine",
    "wof:placetype":"venue"
},
  "geometry": {"coordinates":[-78.36703300000001,40.530476],"type":"Point"}
}