{
  "type": "Feature",
  "properties": {
    "addr:full":"1137 W Sunbury Rd West Sunbury PA 16061",
    "addr:housenumber":"1137",
    "addr:postcode":"16061",
    "addr:street":"W Sunbury Rd",
    "iso:country":"US",
    "sg:address":"1137 W Sunbury Rd",
    "sg:city":"West Sunbury",
    "sg:classifiers":[
        {
            "category":"Government",
            "subcategory":"Office",
            "type":"Public Place"
        }
    ],
    "sg:phone":"+1 724 794 2005",
    "sg:postcode":"16061",
    "sg:province":"PA",
    "sg:tags":[
        "federal"
    ],
    "wof:name":"Us Office Of Personnel Mgmt",
    "wof:placetype":"venue"
},
  "geometry": {"coordinates":[-79.90567900000001,40.980596],"type":"Point"}
}