{
  "type": "Feature",
  "properties": {
    "addr:full":"108 Pine St Hallstead PA 18822",
    "addr:housenumber":"108",
    "addr:postcode":"18822",
    "addr:street":"Pine St",
    "iso:country":"US",
    "sg:address":"108 Pine St",
    "sg:city":"Hallstead",
    "sg:classifiers":[
        {
            "category":"Organizations",
            "subcategory":"Religious Organization",
            "type":"Services"
        }
    ],
    "sg:phone":"+1 570 879 4676",
    "sg:postcode":"18822",
    "sg:province":"PA",
    "sg:tags":[
        "church"
    ],
    "sg:website":"www.fbchallstead.org",
    "wof:name":"First Baptist Church",
    "wof:placetype":"venue"
},
  "geometry": {"coordinates":[-75.74637,41.963159],"type":"Point"}
}