{
  "type": "Feature",
  "properties": {
    "iso:country":"US",
    "sg:address":"230 Kaolin Rd",
    "sg:city":"Wagontown",
    "sg:classifiers":[
        {
            "category":"Building & Trades",
            "subcategory":"Landscaping Services",
            "type":"Services"
        }
    ],
    "sg:phone":"+1 610 466 0142",
    "sg:postcode":"19320",
    "sg:province":"PA",
    "sg:tags":[
        "landscape",
        "contractor"
    ],
    "wof:name":"KJM Landscape & Tree Svc",
    "wof:placetype":"venue"
},
  "geometry": {"coordinates":[-75.838977,40.040613],"type":"Point"}
}