{
  "type": "Feature",
  "properties": {
    "iso:country":"US",
    "sg:address":"436 E College Ave",
    "sg:city":"State College",
    "sg:classifiers":[
        {
            "category":"Professional",
            "subcategory":"Printing & Photocopies",
            "type":"Services"
        }
    ],
    "sg:phone":"+1   ",
    "sg:postcode":"16801",
    "sg:province":"PA",
    "sg:tags":[
        "photocopying"
    ],
    "wof:name":"Copy Centre",
    "wof:placetype":"venue"
},
  "geometry": {"coordinates":[-77.85667599999999,40.797945],"type":"Point"}
}