{
  "type": "Feature",
  "properties": {
    "iso:country":"US",
    "sg:address":"508 Green St",
    "sg:city":"Mifflinburg",
    "sg:classifiers":[
        {
            "category":"Professional",
            "subcategory":"Business Services",
            "type":"Services"
        }
    ],
    "sg:phone":"+1 570 966 5777",
    "sg:postcode":"17844",
    "sg:province":"PA",
    "sg:tags":[
        "inspection"
    ],
    "wof:name":"Domestic Radon Testing &",
    "wof:placetype":"venue"
},
  "geometry": {"coordinates":[-77.04800899999999,40.915402],"type":"Point"}
}