{
  "type": "Feature",
  "properties": {
    "iso:country":"US",
    "sg:address":"5159 Library Rd",
    "sg:city":"Bethel Park",
    "sg:classifiers":[
        {
            "category":"Restaurant",
            "type":"Food & Drink"
        }
    ],
    "sg:phone":"+1 412 833 7788",
    "sg:postcode":"15102",
    "sg:province":"PA",
    "sg:tags":[
        "pizza"
    ],
    "wof:name":"Danny's Parkview Pizza",
    "wof:placetype":"venue"
},
  "geometry": {"coordinates":[-80.02419999999999,40.336201],"type":"Point"}
}