{
  "type": "Feature",
  "properties": {
    "iso:country":"US",
    "sg:address":"3200 Orchard St",
    "sg:city":"Mc Keesport",
    "sg:classifiers":[
        {
            "category":"Building & Trades",
            "subcategory":"Cleaning & Sanitation",
            "type":"Services"
        }
    ],
    "sg:phone":"+1   ",
    "sg:postcode":"15132",
    "sg:province":"PA",
    "sg:tags":[
        "maintenance"
    ],
    "wof:name":"Dynamic Cleaning",
    "wof:placetype":"venue"
},
  "geometry": {"coordinates":[-79.838651,40.334976],"type":"Point"}
}