{
  "type": "Feature",
  "properties": {
    "iso:country":"US",
    "sg:address":"731 Orchard Rd",
    "sg:city":"Orrtanna",
    "sg:classifiers":[
        {
            "category":"Farming",
            "subcategory":"Orchard",
            "type":"Manufacturing & Wholesale Goods"
        }
    ],
    "sg:phone":"+1   ",
    "sg:postcode":"17353",
    "sg:province":"PA",
    "sg:tags":[
        "fruit",
        "tree"
    ],
    "wof:name":"Lowell Pepple",
    "wof:placetype":"venue"
},
  "geometry": {"coordinates":[-77.378837,39.862012],"type":"Point"}
}