{
  "type": "Feature",
  "properties": {
    "addr:full":"1215 N Canal St Sharpsburg PA 15215",
    "addr:housenumber":"1215",
    "addr:postcode":"15215",
    "addr:street":"N Canal St",
    "iso:country":"US",
    "sg:address":"1215 N Canal St",
    "sg:city":"Sharpsburg",
    "sg:classifiers":[
        {
            "category":"Education",
            "subcategory":"Dance Studio",
            "type":"Public Place"
        }
    ],
    "sg:phone":"+1 412 782 6877",
    "sg:postcode":"15215",
    "sg:province":"PA",
    "sg:tags":[
        "instruction",
        "dancing"
    ],
    "wof:name":"B & B Performing Arts Ctr",
    "wof:placetype":"venue"
},
  "geometry": {"coordinates":[-79.929618,40.495326],"type":"Point"}
}