{
  "type": "Feature",
  "properties": {
    "addr:full":"4150 Washington Rd Mc Murray PA 15317",
    "addr:housenumber":"4150",
    "addr:postcode":"15317",
    "addr:street":"Washington Rd",
    "iso:country":"US",
    "sg:address":"4150 Washington Rd",
    "sg:city":"Mc Murray",
    "sg:classifiers":[
        {
            "category":"Professional",
            "subcategory":"Management & Consulting",
            "type":"Services"
        }
    ],
    "sg:phone":"+1 724 969 5800",
    "sg:postcode":"15317",
    "sg:province":"PA",
    "sg:tags":[
        "employee",
        "consultant",
        "benefit"
    ],
    "wof:name":"Lavery Benefits",
    "wof:placetype":"venue"
},
  "geometry": {"coordinates":[-80.13365400000001,40.262782],"type":"Point"}
}