{
  "type": "Feature",
  "properties": {
    "iso:country":"US",
    "sg:address":"4906 Richmond St",
    "sg:city":"Erie",
    "sg:classifiers":[
        {
            "category":"Health Services",
            "subcategory":"Doctor",
            "type":"Services"
        }
    ],
    "sg:phone":"+1 814 864 2949",
    "sg:postcode":"16509",
    "sg:province":"PA",
    "sg:tags":[
        "physician",
        "surgeon"
    ],
    "wof:name":"Pathways To Health Inc",
    "wof:placetype":"venue"
},
  "geometry": {"coordinates":[-80.0921,42.080816],"type":"Point"}
}