{
  "type": "Feature",
  "properties": {
    "iso:country":"US",
    "sg:address":"2016 E Carson St",
    "sg:city":"Pittsburgh",
    "sg:classifiers":[
        {
            "category":"Retail",
            "subcategory":"Laundry & Dry Cleaning",
            "type":"Services"
        }
    ],
    "sg:phone":"+1 412 431 1303",
    "sg:postcode":"15203",
    "sg:province":"PA",
    "sg:tags":[
        "cleaners"
    ],
    "wof:name":"Gerson Brothers",
    "wof:placetype":"venue"
},
  "geometry": {"coordinates":[-79.97644099999999,40.428444],"type":"Point"}
}