{
  "type": "Feature",
  "properties": {
    "iso:country":"US",
    "sg:address":"1171 Freedom Rd",
    "sg:city":"Cranberry Twp",
    "sg:classifiers":[
        {
            "category":"Restaurant",
            "type":"Food & Drink"
        }
    ],
    "sg:phone":"+1 724 772 5622",
    "sg:postcode":"16066",
    "sg:province":"PA",
    "sg:tags":[
        "chinese"
    ],
    "wof:name":"China Garden",
    "wof:placetype":"venue"
},
  "geometry": {"coordinates":[-80.125099,40.682098],"type":"Point"}
}