{
  "type": "Feature",
  "properties": {
    "addr:full":"1230 Devereaux Ave Philadelphia PA 19111",
    "addr:housenumber":"1230",
    "addr:postcode":"19111",
    "addr:street":"Devereaux Ave",
    "iso:country":"US",
    "sg:address":"1230 Devereaux Ave",
    "sg:city":"Philadelphia",
    "sg:classifiers":[
        {
            "category":"Manufacturing",
            "subcategory":"Signs",
            "type":"Manufacturing & Wholesale Goods"
        }
    ],
    "sg:phone":"+1 215 537 0915",
    "sg:postcode":"19111",
    "sg:province":"PA",
    "wof:name":"Exel Sign Inc",
    "wof:placetype":"venue"
},
  "geometry": {"coordinates":[-75.08135299999999,40.037742],"type":"Point"}
}