{
  "type": "Feature",
  "properties": {
    "iso:country":"US",
    "sg:address":"327 Thomson Park Dr",
    "sg:city":"Cranberry Twp",
    "sg:classifiers":[
        {
            "category":"Professional",
            "subcategory":"Employment Agencies",
            "type":"Services"
        }
    ],
    "sg:phone":"+1 724 772 9900",
    "sg:postcode":"16066",
    "sg:province":"PA",
    "wof:name":"Convergent Search Group Inc",
    "wof:placetype":"venue"
},
  "geometry": {"coordinates":[-80.11350299999999,40.697701],"type":"Point"}
}