{
  "type": "Feature",
  "properties": {
    "addr:full":"249 York St Hanover PA 17331",
    "addr:housenumber":"249",
    "addr:postcode":"17331",
    "addr:street":"York St",
    "iso:country":"US",
    "sg:address":"249 York St",
    "sg:city":"Hanover",
    "sg:classifiers":[
        {
            "category":"Professional",
            "subcategory":"Lawyer & Legal Services",
            "type":"Services"
        }
    ],
    "sg:phone":"+1 717 630 8282",
    "sg:postcode":"17331",
    "sg:province":"PA",
    "sg:tags":[
        "attorney",
        "law",
        "bankruptcy"
    ],
    "sg:website":"http://www.millerandshultis.com",
    "wof:name":"Miller & Shultis",
    "wof:placetype":"venue"
},
  "geometry": {"coordinates":[-76.97784,39.799824],"type":"Point"}
}