{
  "type": "Feature",
  "properties": {
    "iso:country":"US",
    "sg:address":"15 N Village Ave",
    "sg:city":"Lionville",
    "sg:classifiers":[
        {
            "category":"Organizations",
            "subcategory":"Religious Organization",
            "type":"Services"
        }
    ],
    "sg:phone":"+1 610 265 8463",
    "sg:postcode":"19341",
    "sg:province":"PA",
    "sg:tags":[
        "church"
    ],
    "sg:website":"www.philly-vcf.org",
    "wof:name":"Vineyard Community Church",
    "wof:placetype":"venue"
},
  "geometry": {"coordinates":[-75.661154,40.055652],"type":"Point"}
}