{
  "type": "Feature",
  "properties": {
    "addr:full":"36 N Elm St Wernersville PA 19565",
    "addr:housenumber":"36",
    "addr:postcode":"19565",
    "addr:street":"N Elm St",
    "iso:country":"US",
    "sg:address":"36 N Elm St",
    "sg:city":"Wernersville",
    "sg:classifiers":[
        {
            "category":"Wholesale",
            "subcategory":"Construction Materials",
            "type":"Manufacturing & Wholesale Goods"
        }
    ],
    "sg:phone":"+1   ",
    "sg:postcode":"19565",
    "sg:province":"PA",
    "sg:tags":[
        "lumber"
    ],
    "wof:name":"De Gol Organization LP",
    "wof:placetype":"venue"
},
  "geometry": {"coordinates":[-76.08380099999999,40.330815],"type":"Point"}
}