{
  "type": "Feature",
  "properties": {
    "iso:country":"US",
    "sg:address":"13639 W Smith St Exd",
    "sg:city":"Corry",
    "sg:classifiers":[
        {
            "category":"School Buses",
            "type":"Transportation"
        }
    ],
    "sg:phone":"+1 814 664 8088",
    "sg:postcode":"16407",
    "sg:province":"PA",
    "wof:name":"William W Mercer Inc",
    "wof:placetype":"venue"
},
  "geometry": {"coordinates":[-79.660894,41.927101],"type":"Point"}
}