{
  "type": "Feature",
  "properties": {
    "iso:country":"US",
    "sg:address":"1211 Chestnut St",
    "sg:city":"Philadelphia",
    "sg:classifiers":[
        {
            "category":"Social Services",
            "type":"Services"
        }
    ],
    "sg:phone":"+1 215 751 1810",
    "sg:postcode":"19107",
    "sg:province":"PA",
    "sg:tags":[
        "organization",
        "welfare"
    ],
    "sg:website":"www.mhselfhelp.org",
    "wof:name":"Clearinghouse",
    "wof:placetype":"venue"
},
  "geometry": {"coordinates":[-75.161648,39.950647],"type":"Point"}
}