{
  "type": "Feature",
  "properties": {
    "iso:country":"US",
    "sg:address":"736 11th St",
    "sg:city":"Pitcairn",
    "sg:classifiers":[
        {
            "category":"Manufacturing",
            "subcategory":"Buildings",
            "type":"Manufacturing & Wholesale Goods"
        },
        {
            "category":"Building & Trades",
            "subcategory":"Construction",
            "type":"Services"
        }
    ],
    "sg:phone":"+1 412 856 8548",
    "sg:postcode":"15140",
    "sg:province":"PA",
    "sg:tags":[
        "home",
        "builder",
        "contractor"
    ],
    "wof:name":"Sarber Construction Ken",
    "wof:placetype":"venue"
},
  "geometry": {"coordinates":[-79.771866,40.40735],"type":"Point"}
}