{
  "type": "Feature",
  "properties": {
    "iso:country":"US",
    "sg:address":"222 S Kemp Rd",
    "sg:city":"Kutztown",
    "sg:classifiers":[
        {
            "category":"Personal",
            "subcategory":"Beauty Salon",
            "type":"Services"
        }
    ],
    "sg:phone":"+1 610 894 9757",
    "sg:postcode":"19530",
    "sg:province":"PA",
    "wof:name":"20 Minute Haircut",
    "wof:placetype":"venue"
},
  "geometry": {"coordinates":[-75.76038699999999,40.525121],"type":"Point"}
}