{
  "type": "Feature",
  "properties": {
    "iso:country":"US",
    "sg:address":"38 E Main St",
    "sg:city":"Bloomsburg",
    "sg:classifiers":[
        {
            "category":"Building & Trades",
            "subcategory":"Equipment Rental",
            "type":"Services"
        }
    ],
    "sg:phone":"+1 570 784 5722",
    "sg:postcode":"17815",
    "sg:province":"PA",
    "sg:tags":[
        "yard"
    ],
    "wof:name":"Rent-A-Center",
    "wof:placetype":"venue"
},
  "geometry": {"coordinates":[-76.455153,41.003679],"type":"Point"}
}