{
  "type": "Feature",
  "properties": {
    "addr:full":"340 Poplar St Hanover PA 17331",
    "addr:housenumber":"340",
    "addr:postcode":"17331",
    "addr:street":"Poplar St",
    "iso:country":"US",
    "sg:address":"340 Poplar St",
    "sg:city":"Hanover",
    "sg:classifiers":[
        {
            "category":"Shopping",
            "subcategory":"Catalog Store",
            "type":"Retail Goods"
        }
    ],
    "sg:phone":"+1 717 633 3327",
    "sg:postcode":"17331",
    "sg:province":"PA",
    "sg:tags":[
        "mail",
        "order"
    ],
    "wof:name":"Simply Tops",
    "wof:placetype":"venue"
},
  "geometry": {"coordinates":[-76.99392,39.798596],"type":"Point"}
}