{
  "type": "Feature",
  "properties": {
    "iso:country":"US",
    "sg:address":"3755 E Market St",
    "sg:city":"York",
    "sg:classifiers":[
        {
            "category":"Health Services",
            "subcategory":"Medical Lab",
            "type":"Services"
        }
    ],
    "sg:phone":"+1 717 757 5992",
    "sg:postcode":"17402",
    "sg:province":"PA",
    "sg:tags":[
        "laboratory",
        "dental"
    ],
    "wof:name":"Regional Crown & Bridge",
    "wof:placetype":"venue"
},
  "geometry": {"coordinates":[-76.644141,39.987077],"type":"Point"}
}