{
  "type": "Feature",
  "properties": {
    "iso:country":"US",
    "sg:address":"925 E Butter Rd",
    "sg:city":"York",
    "sg:classifiers":[
        {
            "category":"Shopping",
            "type":"Retail Goods"
        }
    ],
    "sg:phone":"+1   ",
    "sg:postcode":"17406",
    "sg:province":"PA",
    "sg:tags":[
        "merchandise"
    ],
    "wof:name":"Bonsai Collectables",
    "wof:placetype":"venue"
},
  "geometry": {"coordinates":[-76.77363800000001,40.088273],"type":"Point"}
}