{
  "type": "Feature",
  "properties": {
    "addr:full":"1800 Callowhill St Philadelphia PA 19130",
    "addr:housenumber":"1800",
    "addr:postcode":"19130",
    "addr:street":"Callowhill St",
    "iso:country":"US",
    "sg:address":"1800 Callowhill St",
    "sg:city":"Philadelphia",
    "sg:classifiers":[
        {
            "category":"Professional",
            "subcategory":"Lawyer & Legal Services",
            "type":"Services"
        }
    ],
    "sg:phone":"+1 215 988 9320",
    "sg:postcode":"19130",
    "sg:province":"PA",
    "wof:name":"Wheeler Wm J Esquire & Assoc PC",
    "wof:placetype":"venue"
},
  "geometry": {"coordinates":[-75.168503,39.960602],"type":"Point"}
}