{
  "type": "Feature",
  "properties": {
    "iso:country":"US",
    "sg:address":"100 Woodlawn Ave Ste 300",
    "sg:city":"Uniontown",
    "sg:classifiers":[
        {
            "category":"Social Services",
            "subcategory":"Adult Care",
            "type":"Services"
        }
    ],
    "sg:phone":"+1 724 439 1610",
    "sg:postcode":"15401",
    "sg:province":"PA",
    "sg:tags":[
        "nurses-home"
    ],
    "sg:website":"http://www.fayettehomecare.com",
    "wof:name":"Fayette Homecare Inc",
    "wof:placetype":"venue"
},
  "geometry": {"coordinates":[-79.738416,39.901173],"type":"Point"}
}