{
  "type": "Feature",
  "properties": {
    "iso:country":"US",
    "sg:address":"103 E Butler Ave",
    "sg:city":"Ambler",
    "sg:classifiers":[
        {
            "category":"Science Facility",
            "type":"Public Place"
        }
    ],
    "sg:phone":"+1 215 542 0122",
    "sg:postcode":"19002",
    "sg:province":"PA",
    "sg:tags":[
        "development",
        "laboratories-research"
    ],
    "wof:name":"A-Z Video",
    "wof:placetype":"venue"
},
  "geometry": {"coordinates":[-75.221475,40.154699],"type":"Point"}
}