{
  "type": "Feature",
  "properties": {
    "iso:country":"US",
    "sg:address":"3904 Trindle Rd",
    "sg:city":"Camp Hill",
    "sg:classifiers":[
        {
            "category":"Banks & Credit Unions",
            "subcategory":"Atm",
            "type":"Services"
        }
    ],
    "sg:phone":"+1 717 731 9502",
    "sg:postcode":"17011",
    "sg:province":"PA",
    "sg:tags":[
        "bankruptcy"
    ],
    "sg:website":"www.mtravislaw.com",
    "wof:name":"Travis Michael S Attorney At Law",
    "wof:placetype":"venue"
},
  "geometry": {"coordinates":[-76.9476,40.234167],"type":"Point"}
}