{
  "type": "Feature",
  "properties": {
    "iso:country":"US",
    "sg:address":"2063 Woodley Hollow Rd",
    "sg:city":"Montoursville",
    "sg:classifiers":[
        {
            "category":"Recreation",
            "type":"Entertainment"
        }
    ],
    "sg:phone":"+1 570 435 0255",
    "sg:postcode":"17754",
    "sg:province":"PA",
    "sg:tags":[
        "hall",
        "auditorium"
    ],
    "wof:name":"Mill Creek Twp Hall",
    "wof:placetype":"venue"
},
  "geometry": {"coordinates":[-76.804317,41.300941],"type":"Point"}
}