{
  "type": "Feature",
  "properties": {
    "addr:full":"3200 Horizon Dr King Of Prussia PA 19406",
    "addr:housenumber":"3200",
    "addr:postcode":"19406",
    "addr:street":"Horizon Dr",
    "iso:country":"US",
    "sg:address":"3200 Horizon Dr",
    "sg:city":"King Of Prussia",
    "sg:classifiers":[
        {
            "category":"Banks & Credit Unions",
            "subcategory":"Investment Brokerage",
            "type":"Services"
        }
    ],
    "sg:phone":"+1   ",
    "sg:postcode":"19406",
    "sg:province":"PA",
    "sg:tags":[
        "security"
    ],
    "wof:name":"Pfpc Globalfunds Services",
    "wof:placetype":"venue"
},
  "geometry": {"coordinates":[-75.342383,40.090564],"type":"Point"}
}