{
  "type": "Feature",
  "properties": {
    "iso:country":"US",
    "sg:address":"1200 Walton St",
    "sg:city":"Philipsburg",
    "sg:classifiers":[
        {
            "category":"Wholesale",
            "subcategory":"Groceries",
            "type":"Manufacturing & Wholesale Goods"
        }
    ],
    "sg:phone":"+1   ",
    "sg:postcode":"16866",
    "sg:province":"PA",
    "wof:name":"Wholesome",
    "wof:placetype":"venue"
},
  "geometry": {"coordinates":[-78.23281799999999,40.887074],"type":"Point"}
}