{
  "type": "Feature",
  "properties": {
    "iso:country":"US",
    "sg:address":"825 25th St",
    "sg:city":"Altoona",
    "sg:classifiers":[
        {
            "category":"Professional",
            "subcategory":"Testing Lab",
            "type":"Services"
        }
    ],
    "sg:phone":"+1 814 949 2034",
    "sg:postcode":"16601",
    "sg:province":"PA",
    "sg:tags":[
        "laboratory",
        "consulting",
        "engineering",
        "business"
    ],
    "sg:website":"www.mountainresearch.com",
    "wof:name":"Mountain Research Inc",
    "wof:placetype":"venue"
},
  "geometry": {"coordinates":[-78.409565,40.502961],"type":"Point"}
}