{
  "type": "Feature",
  "properties": {
    "addr:full":"3344 Crestview Dr Bethel Park PA 15102",
    "addr:housenumber":"3344",
    "addr:postcode":"15102",
    "addr:street":"Crestview Dr",
    "iso:country":"US",
    "sg:address":"3344 Crestview Dr",
    "sg:city":"Bethel Park",
    "sg:classifiers":[
        {
            "category":"Professional",
            "subcategory":"Secretarial Services",
            "type":"Services"
        }
    ],
    "sg:phone":"+1 412 833 3313",
    "sg:postcode":"15102",
    "sg:province":"PA",
    "sg:tags":[
        "reporting",
        "court"
    ],
    "wof:name":"At Your Svc",
    "wof:placetype":"venue"
},
  "geometry": {"coordinates":[-80.059265,40.325246],"type":"Point"}
}