{
  "type": "Feature",
  "properties": {
    "iso:country":"US",
    "sg:address":"1191 Eichelberger St",
    "sg:city":"Hanover",
    "sg:classifiers":[
        {
            "category":"Banks & Credit Unions",
            "subcategory":"Bank",
            "type":"Services"
        }
    ],
    "sg:phone":"+1 717 633 6555",
    "sg:postcode":"17331",
    "sg:province":"PA",
    "sg:tags":[
        "state",
        "commercial"
    ],
    "wof:name":"Community Banks",
    "wof:placetype":"venue"
},
  "geometry": {"coordinates":[-76.991383,39.821117],"type":"Point"}
}