{
  "type": "Feature",
  "properties": {
    "iso:country":"US",
    "sg:address":"1603 Old York Rd",
    "sg:city":"Abington",
    "sg:classifiers":[
        {
            "category":"Communications",
            "subcategory":"Film & Video Production",
            "type":"Services"
        }
    ],
    "sg:phone":"+1   ",
    "sg:postcode":"19001",
    "sg:province":"PA",
    "sg:tags":[
        "motion"
    ],
    "wof:name":"Sigma Animation Inc",
    "wof:placetype":"venue"
},
  "geometry": {"coordinates":[-75.11648,40.129627],"type":"Point"}
}