{
  "type": "Feature",
  "properties": {
    "iso:country":"US",
    "sg:address":"18 Roseville Rd",
    "sg:city":"Williamsport",
    "sg:classifiers":[
        {
            "category":"Professional",
            "type":"Services"
        }
    ],
    "sg:phone":"+1   ",
    "sg:postcode":"17701",
    "sg:province":"PA",
    "wof:name":"Comfort Apparel Inc",
    "wof:placetype":"venue"
},
  "geometry": {"coordinates":[-77.06319499999999,41.247698],"type":"Point"}
}