{
  "type": "Feature",
  "properties": {
    "iso:country":"US",
    "sg:address":"746 Chester Pike",
    "sg:city":"Prospect Park",
    "sg:classifiers":[
        {
            "category":"Retail",
            "subcategory":"Auto Rental",
            "type":"Services"
        }
    ],
    "sg:phone":"+1 610 586 7301",
    "sg:postcode":"19076",
    "sg:province":"PA",
    "sg:tags":[
        "renting",
        "automobile"
    ],
    "wof:name":"Action Auto Rental",
    "wof:placetype":"venue"
},
  "geometry": {"coordinates":[-75.30461699999999,39.88332],"type":"Point"}
}