{
  "type": "Feature",
  "properties": {
    "iso:country":"US",
    "sg:address":"1490 S Valley Forge Rd",
    "sg:city":"Lansdale",
    "sg:classifiers":[
        {
            "category":"Banks & Credit Unions",
            "subcategory":"Bank",
            "type":"Services"
        }
    ],
    "sg:phone":"+1 215 361 9300",
    "sg:postcode":"19446",
    "sg:province":"PA",
    "sg:tags":[
        "state",
        "commercial"
    ],
    "wof:name":"Commerce Bank NA",
    "wof:placetype":"venue"
},
  "geometry": {"coordinates":[-75.315085,40.228943],"type":"Point"}
}