{
  "type": "Feature",
  "properties": {
    "iso:country":"US",
    "sg:address":"307 Shenango St",
    "sg:city":"Jamestown",
    "sg:classifiers":[
        {
            "category":"Retail",
            "subcategory":"Laundry & Dry Cleaning",
            "type":"Services"
        }
    ],
    "sg:phone":"+1 724 932 5383",
    "sg:postcode":"16134",
    "sg:province":"PA",
    "sg:tags":[
        "cleaners",
        "rug",
        "carpet"
    ],
    "wof:name":"Mighty Clean",
    "wof:placetype":"venue"
},
  "geometry": {"coordinates":[-80.43384500000001,41.48702],"type":"Point"}
}