{
  "type": "Feature",
  "properties": {
    "iso:country":"US",
    "sg:address":"3197 Shelly Dr",
    "sg:city":"Library",
    "sg:classifiers":[
        {
            "category":"Food & Beverages",
            "subcategory":"Candy",
            "type":"Retail Goods"
        }
    ],
    "sg:phone":"+1   ",
    "sg:postcode":"15129",
    "sg:province":"PA",
    "wof:name":"Chocolates By Design",
    "wof:placetype":"venue"
},
  "geometry": {"coordinates":[-79.999916,40.292084],"type":"Point"}
}