{
  "type": "Feature",
  "properties": {
    "addr:full":"100 Village Club Dr Wexford PA 15090",
    "addr:housenumber":"100",
    "addr:postcode":"15090",
    "addr:street":"Village Club Dr",
    "iso:country":"US",
    "sg:address":"100 Village Club Dr",
    "sg:city":"Wexford",
    "sg:classifiers":[
        {
            "category":"Bars & Pubs",
            "subcategory":"Lounge",
            "type":"Food & Drink"
        }
    ],
    "sg:phone":"+1 724 934 7876",
    "sg:postcode":"15090",
    "sg:province":"PA",
    "sg:website":"www.thecabanabar.com/",
    "wof:name":"The Cabana Bar",
    "wof:placetype":"venue"
},
  "geometry": {"coordinates":[-80.05050900000001,40.633819],"type":"Point"}
}