{
  "type": "Feature",
  "properties": {
    "iso:country":"US",
    "sg:address":"148 Homestead Dr",
    "sg:city":"Doylestown",
    "sg:classifiers":[
        {
            "category":"Professional",
            "subcategory":"Business Services",
            "type":"Services"
        }
    ],
    "sg:phone":"+1   ",
    "sg:postcode":"18901",
    "sg:province":"PA",
    "wof:name":"Ltc Management Group LLC",
    "wof:placetype":"venue"
},
  "geometry": {"coordinates":[-75.12285799999999,40.302673],"type":"Point"}
}