{
  "type": "Feature",
  "properties": {
    "iso:country":"US",
    "sg:address":"4775 Hikey St",
    "sg:city":"Dover",
    "sg:classifiers":[
        {
            "category":"Professional",
            "type":"Services"
        }
    ],
    "sg:phone":"+1 717 467 5732",
    "sg:postcode":"17315",
    "sg:province":"PA",
    "sg:tags":[
        "caterer"
    ],
    "wof:name":"Fireside Caterers",
    "wof:placetype":"venue"
},
  "geometry": {"coordinates":[-76.855853,39.987488],"type":"Point"}
}