{
  "type": "Feature",
  "properties": {
    "addr:full":"76 11th St Ambridge PA 15003",
    "addr:housenumber":"76",
    "addr:postcode":"15003",
    "addr:street":"11Th St",
    "iso:country":"US",
    "sg:address":"76 11th St",
    "sg:city":"Ambridge",
    "sg:classifiers":[
        {
            "category":"Building & Trades",
            "subcategory":"Equipment Rental",
            "type":"Services"
        }
    ],
    "sg:phone":"+1   ",
    "sg:postcode":"15003",
    "sg:province":"PA",
    "sg:tags":[
        "party"
    ],
    "wof:name":"Promo Works",
    "wof:placetype":"venue"
},
  "geometry": {"coordinates":[-80.232636,40.592534],"type":"Point"}
}