{
  "type": "Feature",
  "properties": {
    "iso:country":"US",
    "sg:address":"256 Downieville Rd",
    "sg:city":"Valencia",
    "sg:classifiers":[
        {
            "category":"Wholesale",
            "subcategory":"Machinery & Supplies",
            "type":"Manufacturing & Wholesale Goods"
        }
    ],
    "sg:phone":"+1   ",
    "sg:postcode":"16059",
    "sg:province":"PA",
    "sg:tags":[
        "pump",
        "industrial"
    ],
    "wof:name":"Flowtech Systems",
    "wof:placetype":"venue"
},
  "geometry": {"coordinates":[-79.98652,40.684836],"type":"Point"}
}