{
  "type": "Feature",
  "properties": {
    "iso:country":"US",
    "sg:address":"4198 Washington Rd",
    "sg:city":"Canonsburg",
    "sg:classifiers":[
        {
            "category":"Health Services",
            "subcategory":"Chiropractor",
            "type":"Services"
        }
    ],
    "sg:phone":"+1 724 942 7660",
    "sg:postcode":"15317",
    "sg:province":"PA",
    "sg:website":"www.apmhealth.com",
    "wof:name":"Todaro Brad DC",
    "wof:placetype":"venue"
},
  "geometry": {"coordinates":[-80.133809,40.262867],"type":"Point"}
}