{
  "type": "Feature",
  "properties": {
    "iso:country":"US",
    "sg:address":"4120 Baltimore Pike",
    "sg:city":"Littlestown",
    "sg:classifiers":[
        {
            "category":"Manufacturing",
            "subcategory":"Tools & Machinery",
            "type":"Manufacturing & Wholesale Goods"
        }
    ],
    "sg:phone":"+1 717 359 4998",
    "sg:postcode":"17340",
    "sg:province":"PA",
    "sg:tags":[
        "machine",
        "shop"
    ],
    "wof:name":"Hands-On Machine Shop",
    "wof:placetype":"venue"
},
  "geometry": {"coordinates":[-77.136937,39.763577],"type":"Point"}
}