{
  "type": "Feature",
  "properties": {
    "iso:country":"US",
    "sg:address":"1422 Big Run Rd",
    "sg:city":"Everett",
    "sg:classifiers":[
        {
            "category":"Building & Trades",
            "subcategory":"Landscaping Services",
            "type":"Services"
        }
    ],
    "sg:phone":"+1   ",
    "sg:postcode":"15537",
    "sg:province":"PA",
    "sg:tags":[
        "landscape"
    ],
    "wof:name":"Scuderi Landscaping",
    "wof:placetype":"venue"
},
  "geometry": {"coordinates":[-78.309893,39.948463],"type":"Point"}
}