{
  "type": "Feature",
  "properties": {
    "iso:country":"US",
    "sg:address":"1890 W Market St",
    "sg:city":"York",
    "sg:classifiers":[
        {
            "category":"Manufacturing",
            "subcategory":"Printing",
            "type":"Manufacturing & Wholesale Goods"
        },
        {
            "category":"Manufacturing",
            "subcategory":"Motor Vehicles & Parts",
            "type":"Manufacturing & Wholesale Goods"
        }
    ],
    "sg:phone":"+1 717 846 6114",
    "sg:postcode":"17404",
    "sg:province":"PA",
    "sg:tags":[
        "mfg",
        "screen",
        "silk",
        "sign"
    ],
    "wof:name":"Imagineered Signs & Displays",
    "wof:placetype":"venue"
},
  "geometry": {"coordinates":[-76.767585,39.95295],"type":"Point"}
}