{
  "type": "Feature",
  "properties": {
    "iso:country":"US",
    "sg:address":"3305 Broad Ave",
    "sg:city":"Altoona",
    "sg:classifiers":[
        {
            "category":"Freight",
            "type":"Transportation"
        }
    ],
    "sg:phone":"+1   ",
    "sg:postcode":"16601",
    "sg:province":"PA",
    "sg:tags":[
        "operator",
        "business",
        "trucking"
    ],
    "wof:name":"Truck Trailor Parts",
    "wof:placetype":"venue"
},
  "geometry": {"coordinates":[-78.418944,40.493318],"type":"Point"}
}