{
  "type": "Feature",
  "properties": {
    "addr:full":"137 Roosevelt St Kingston PA 18704",
    "addr:housenumber":"137",
    "addr:postcode":"18704",
    "addr:street":"Roosevelt St",
    "iso:country":"US",
    "sg:address":"137 Roosevelt St",
    "sg:city":"Kingston",
    "sg:classifiers":[
        {
            "category":"Building & Trades",
            "subcategory":"Plumbing",
            "type":"Services"
        }
    ],
    "sg:phone":"+1   ",
    "sg:postcode":"18704",
    "sg:province":"PA",
    "sg:tags":[
        "contractor"
    ],
    "wof:name":"Harbaugh Curtis M Plmbng Htn",
    "wof:placetype":"venue"
},
  "geometry": {"coordinates":[-75.903874,41.269182],"type":"Point"}
}