{
  "type": "Feature",
  "properties": {
    "iso:country":"US",
    "sg:address":"245 E Main St",
    "sg:city":"Mechanicsburg",
    "sg:classifiers":[
        {
            "category":"Personal",
            "subcategory":"Beauty Salon",
            "type":"Services"
        }
    ],
    "sg:phone":"+1 717 691 5440",
    "sg:postcode":"17055",
    "sg:province":"PA",
    "sg:tags":[
        "hair",
        "stylist"
    ],
    "wof:name":"Casablanca Hair Salon",
    "wof:placetype":"venue"
},
  "geometry": {"coordinates":[-77.00369000000001,40.214534],"type":"Point"}
}