{
  "type": "Feature",
  "properties": {
    "iso:country":"US",
    "sg:address":"1431 Ivy Hill Rd",
    "sg:city":"Philadelphia",
    "sg:classifiers":[
        {
            "category":"Freight",
            "type":"Transportation"
        }
    ],
    "sg:phone":"+1 877 258 8230",
    "sg:postcode":"19150",
    "sg:province":"PA",
    "sg:tags":[
        "storage",
        "household",
        "commercial"
    ],
    "sg:website":"http://www.publicstorage.com/?pid=ypcomCPCingenio",
    "wof:name":"Public Storage",
    "wof:placetype":"venue"
},
  "geometry": {"coordinates":[-75.178119,40.082964],"type":"Point"}
}