{
  "type": "Feature",
  "properties": {
    "iso:country":"US",
    "sg:address":"7090 Dumbarton Pl",
    "sg:city":"Bethel Park",
    "sg:classifiers":[
        {
            "category":"Retail",
            "subcategory":"Auto Repair",
            "type":"Services"
        }
    ],
    "sg:phone":"+1   ",
    "sg:postcode":"15102",
    "sg:province":"PA",
    "sg:tags":[
        "automotive"
    ],
    "wof:name":"Action Framers Inc",
    "wof:placetype":"venue"
},
  "geometry": {"coordinates":[-80.013727,40.339135],"type":"Point"}
}