{
  "type": "Feature",
  "properties": {
    "iso:country":"US",
    "sg:address":"340 Royal Manor Rd",
    "sg:city":"Easton",
    "sg:classifiers":[
        {
            "category":"Professional",
            "type":"Services"
        }
    ],
    "sg:phone":"+1   ",
    "sg:postcode":"18042",
    "sg:province":"PA",
    "wof:name":"Senderling Wildlife Control",
    "wof:placetype":"venue"
},
  "geometry": {"coordinates":[-75.197057,40.624504],"type":"Point"}
}