{
  "type": "Feature",
  "properties": {
    "addr:full":"105 S 22nd St Philadelphia PA 19103",
    "addr:housenumber":"105",
    "addr:postcode":"19103",
    "addr:street":"S 22Nd St",
    "iso:country":"US",
    "sg:address":"105 S 22nd St",
    "sg:city":"Philadelphia",
    "sg:classifiers":[
        {
            "category":"Building & Trades",
            "subcategory":"Locksmith",
            "type":"Services"
        }
    ],
    "sg:phone":"+1 267 519 4159",
    "sg:postcode":"19103",
    "sg:province":"PA",
    "sg:tags":[
        "key"
    ],
    "wof:name":"24 Hour A Locksmith",
    "wof:placetype":"venue"
},
  "geometry": {"coordinates":[-75.176847,39.95231],"type":"Point"}
}