{
  "type": "Feature",
  "properties": {
    "addr:full":"344 Stanford Rd Prospect PA 16052",
    "addr:housenumber":"344",
    "addr:postcode":"16052",
    "addr:street":"Stanford Rd",
    "iso:country":"US",
    "sg:address":"344 Stanford Rd",
    "sg:city":"Prospect",
    "sg:classifiers":[
        {
            "category":"Retail",
            "subcategory":"Repair Shop",
            "type":"Services"
        }
    ],
    "sg:phone":"+1 724 368 3381",
    "sg:postcode":"16052",
    "sg:province":"PA",
    "sg:tags":[
        "related"
    ],
    "wof:name":"Ron Mc Cormick Repair",
    "wof:placetype":"venue"
},
  "geometry": {"coordinates":[-80.117817,40.906054],"type":"Point"}
}