{
  "type": "Feature",
  "properties": {
    "iso:country":"US",
    "sg:address":"4099 William Penn Hwy # 905",
    "sg:city":"Monroeville",
    "sg:classifiers":[
        {
            "category":"Industrial Area",
            "type":"Public Place"
        }
    ],
    "sg:phone":"+1 412 372 9300",
    "sg:postcode":"15146",
    "sg:province":"PA",
    "sg:tags":[
        "development"
    ],
    "wof:name":"Clairton Corporation",
    "wof:placetype":"venue"
},
  "geometry": {"coordinates":[-79.768959,40.438709],"type":"Point"}
}