{
  "type": "Feature",
  "properties": {
    "iso:country":"US",
    "sg:address":"365 S Courtland St",
    "sg:city":"East Stroudsburg",
    "sg:phone":"+1 570 421 4389",
    "sg:postcode":"18301",
    "sg:province":"PA",
    "sg:tags":[
        "oil",
        "gasoline"
    ],
    "wof:name":"Square One Markets",
    "wof:placetype":"venue"
},
  "geometry": {"coordinates":[-75.182754,40.994462],"type":"Point"}
}