{
  "type": "Feature",
  "properties": {
    "addr:full":"355 Lincoln Ave Pittsburgh PA 15202",
    "addr:housenumber":"355",
    "addr:postcode":"15202",
    "addr:street":"Lincoln Ave",
    "iso:country":"US",
    "sg:address":"355 Lincoln Ave",
    "sg:city":"Pittsburgh",
    "sg:classifiers":[
        {
            "category":"Shopping",
            "subcategory":"Pharmacy",
            "type":"Retail Goods"
        }
    ],
    "sg:phone":"+1   ",
    "sg:postcode":"15202",
    "sg:province":"PA",
    "sg:tags":[
        "drug",
        "store"
    ],
    "wof:name":"CVS",
    "wof:placetype":"venue"
},
  "geometry": {"coordinates":[-80.05222999999999,40.493831],"type":"Point"}
}