{
  "type": "Feature",
  "properties": {
    "addr:full":"1296 E High St Pottstown PA 19464",
    "addr:housenumber":"1296",
    "addr:postcode":"19464",
    "addr:street":"E High St",
    "iso:country":"US",
    "sg:address":"1296 E High St",
    "sg:city":"Pottstown",
    "sg:classifiers":[
        {
            "category":"Professional",
            "subcategory":"Management & Consulting",
            "type":"Services"
        }
    ],
    "sg:phone":"+1 610 323 7150",
    "sg:postcode":"19464",
    "sg:province":"PA",
    "sg:tags":[
        "consultant",
        "business"
    ],
    "wof:name":"ECES",
    "wof:placetype":"venue"
},
  "geometry": {"coordinates":[-75.622235,40.243494],"type":"Point"}
}