{
  "type": "Feature",
  "properties": {
    "iso:country":"US",
    "sg:address":"163 W Lincoln Hwy ",
    "sg:city":"Exton",
    "sg:classifiers":[
        {
            "category":"Bars & Pubs",
            "type":"Food & Drink"
        }
    ],
    "sg:menulink":"http://www.allmenus.com/pa/west-whiteland/291859-zwei-asian-cuisine--sushi-bar/menu/",
    "sg:phone":"+1 610 363 1850",
    "sg:postcode":"19341",
    "sg:province":"PA",
    "sg:tags":[
        "soup",
        "seafood",
        "chicken"
    ],
    "wof:name":"Z.Wei Asian Cuisine & Sushi Bar",
    "wof:placetype":"venue"
},
  "geometry": {"coordinates":[-75.630933,40.027764],"type":"Point"}
}