{
  "type": "Feature",
  "properties": {
    "iso:country":"US",
    "sg:address":"214 E Drinker St",
    "sg:city":"Dunmore",
    "sg:classifiers":[
        {
            "category":"Professional",
            "subcategory":"Lawyer & Legal Services",
            "type":"Services"
        }
    ],
    "sg:phone":"+1 570 343 1067",
    "sg:postcode":"18512",
    "sg:province":"PA",
    "sg:tags":[
        "attorney"
    ],
    "wof:name":"Lori Bolick Esq",
    "wof:placetype":"venue"
},
  "geometry": {"coordinates":[-75.628648,41.421579],"type":"Point"}
}