{
  "type": "Feature",
  "properties": {
    "iso:country":"US",
    "sg:address":"212 Bucky Dr",
    "sg:city":"Lititz",
    "sg:classifiers":[
        {
            "category":"Professional",
            "subcategory":"Engineering",
            "type":"Services"
        },
        {
            "category":"Home & Garden",
            "subcategory":"Building Materials",
            "type":"Retail Goods"
        },
        {
            "category":"Building & Trades",
            "subcategory":"Construction",
            "type":"Services"
        }
    ],
    "sg:phone":"+1 717 625 1500",
    "sg:postcode":"17543",
    "sg:province":"PA",
    "sg:tags":[
        "system",
        "specialty",
        "heating",
        "equipment",
        "contractor",
        "air conditioning"
    ],
    "sg:website":"http://find.trane.com/tcs-dealer-407404?utm_source=YP&utm_medium=banner&utm_campaign=TL",
    "wof:name":"Haller Enterprises, Inc.",
    "wof:placetype":"venue"
},
  "geometry": {"coordinates":[-76.310113,40.121982],"type":"Point"}
}