{
  "type": "Feature",
  "properties": {
    "iso:country":"US",
    "sg:address":"148 N 10th St",
    "sg:city":"Philadelphia",
    "sg:classifiers":[
        {
            "category":"Food & Beverages",
            "subcategory":"Ethnic Foods",
            "type":"Retail Goods"
        }
    ],
    "sg:phone":"+1 215 625 9555",
    "sg:postcode":"19107",
    "sg:province":"PA",
    "wof:name":"Ming River Side Walk House",
    "wof:placetype":"venue"
},
  "geometry": {"coordinates":[-75.156217,39.955046],"type":"Point"}
}