{
  "type": "Feature",
  "properties": {
    "addr:full":"25 Camp Letterman Dr Gettysburg PA 17325",
    "addr:housenumber":"25",
    "addr:postcode":"17325",
    "addr:street":"Camp Letterman Dr",
    "iso:country":"US",
    "sg:address":"25 Camp Letterman Dr",
    "sg:city":"Gettysburg",
    "sg:classifiers":[
        {
            "category":"Restaurant",
            "type":"Food & Drink"
        }
    ],
    "sg:menulink":"http://www.allmenus.com/pa/straban/103938-ruby-tuesdays/menu/",
    "sg:phone":"+1 717 334 6127",
    "sg:postcode":"17325",
    "sg:province":"PA",
    "sg:tags":[
        "burger",
        "american"
    ],
    "wof:name":"Ruby Tuesdays",
    "wof:placetype":"venue"
},
  "geometry": {"coordinates":[-77.205264,39.837547],"type":"Point"}
}