{
  "type": "Feature",
  "properties": {
    "addr:full":"2237 2nd Street Pike Newtown PA 18940",
    "addr:housenumber":"2237",
    "addr:postcode":"18940",
    "addr:street":"2Nd Street Pike",
    "iso:country":"US",
    "sg:address":"2237 2nd Street Pike",
    "sg:city":"Newtown",
    "sg:classifiers":[
        {
            "category":"Manufacturing",
            "subcategory":"Buildings",
            "type":"Manufacturing & Wholesale Goods"
        },
        {
            "category":"Building & Trades",
            "subcategory":"Construction",
            "type":"Services"
        }
    ],
    "sg:phone":"+1 215 598 7001",
    "sg:postcode":"18940",
    "sg:province":"PA",
    "sg:tags":[
        "home",
        "builder",
        "contractor"
    ],
    "wof:name":"Damato Construction Co Inc",
    "wof:placetype":"venue"
},
  "geometry": {"coordinates":[-74.999259,40.261283],"type":"Point"}
}