{
  "type": "Feature",
  "properties": {
    "iso:country":"US",
    "sg:address":"356 Olivia St",
    "sg:city":"Mc Kees Rocks",
    "sg:classifiers":[
        {
            "category":"Building & Trades",
            "subcategory":"Construction",
            "type":"Services"
        }
    ],
    "sg:phone":"+1 412 331 6050",
    "sg:postcode":"15136",
    "sg:province":"PA",
    "sg:tags":[
        "house",
        "improvement",
        "home"
    ],
    "wof:name":"Bilak A Roofing & Remodeling",
    "wof:placetype":"venue"
},
  "geometry": {"coordinates":[-80.05699199999999,40.474803],"type":"Point"}
}