{
  "type": "Feature",
  "properties": {
    "addr:full":"435 W 15th St Tyrone PA 16686",
    "addr:housenumber":"435",
    "addr:postcode":"16686",
    "addr:street":"W 15Th St",
    "iso:country":"US",
    "sg:address":"435 W 15th St",
    "sg:city":"Tyrone",
    "sg:classifiers":[
        {
            "category":"Building & Trades",
            "subcategory":"Construction",
            "type":"Services"
        }
    ],
    "sg:phone":"+1 814 684 4296",
    "sg:postcode":"16686",
    "sg:province":"PA",
    "sg:tags":[
        "general",
        "contractor"
    ],
    "wof:name":"Thomas Yon Construction",
    "wof:placetype":"venue"
},
  "geometry": {"coordinates":[-78.242677,40.678231],"type":"Point"}
}