{
  "type": "Feature",
  "properties": {
    "addr:full":"325 Sharon Dr New Cumberland PA 17070",
    "addr:housenumber":"325",
    "addr:postcode":"17070",
    "addr:street":"Sharon Dr",
    "iso:country":"US",
    "sg:address":"325 Sharon Dr",
    "sg:city":"New Cumberland",
    "sg:classifiers":[
        {
            "category":"Wholesale",
            "subcategory":"Non-durable Goods",
            "type":"Manufacturing & Wholesale Goods"
        }
    ],
    "sg:phone":"+1   ",
    "sg:postcode":"17070",
    "sg:province":"PA",
    "sg:tags":[
        "lecturing",
        "merchandise",
        "general"
    ],
    "wof:name":"Wadley & Assocaties",
    "wof:placetype":"venue"
},
  "geometry": {"coordinates":[-76.850252,40.18419],"type":"Point"}
}