{
  "type": "Feature",
  "properties": {
    "addr:full":"1700 Loretta Ave Feasterville Trevose PA 19053",
    "addr:housenumber":"1700",
    "addr:postcode":"19053",
    "addr:street":"Loretta Ave",
    "iso:country":"US",
    "sg:address":"1700 Loretta Ave",
    "sg:city":"Feasterville Trevose",
    "sg:classifiers":[
        {
            "category":"Autos & Motor Vehicles",
            "subcategory":"Auto Supplies",
            "type":"Retail Goods"
        }
    ],
    "sg:phone":"+1   ",
    "sg:postcode":"19053",
    "sg:province":"PA",
    "sg:tags":[
        "installs",
        "automobile",
        "conditioning",
        "air"
    ],
    "wof:name":"Dealer Accessory Service Inc",
    "wof:placetype":"venue"
},
  "geometry": {"coordinates":[-75.007268,40.165959],"type":"Point"}
}