{
  "type": "Feature",
  "properties": {
    "iso:country":"US",
    "sg:address":"340 Union St",
    "sg:city":"Luzerne",
    "sg:classifiers":[
        {
            "category":"Wholesale",
            "subcategory":"Machinery & Supplies",
            "type":"Manufacturing & Wholesale Goods"
        }
    ],
    "sg:phone":"+1 570 288 8676",
    "sg:postcode":"18709",
    "sg:province":"PA",
    "sg:tags":[
        "household",
        "industrial",
        "appliance"
    ],
    "wof:name":"A P Wagner Inc",
    "wof:placetype":"venue"
},
  "geometry": {"coordinates":[-75.894407,41.27942],"type":"Point"}
}