{
  "type": "Feature",
  "properties": {
    "iso:country":"US",
    "sg:address":"19 Penn Charter Dr",
    "sg:city":"Media",
    "sg:classifiers":[
        {
            "category":"Wholesale",
            "subcategory":"Electrical",
            "type":"Manufacturing & Wholesale Goods"
        }
    ],
    "sg:phone":"+1   ",
    "sg:postcode":"19063",
    "sg:province":"PA",
    "sg:tags":[
        "electronic"
    ],
    "wof:name":"American Wireless",
    "wof:placetype":"venue"
},
  "geometry": {"coordinates":[-75.421155,39.916857],"type":"Point"}
}