{
  "type": "Feature",
  "properties": {
    "iso:country":"US",
    "sg:address":"971 Felton Rd",
    "sg:city":"Red Lion",
    "sg:classifiers":[
        {
            "category":"Food & Beverages",
            "subcategory":"Groceries & Convenience Stores",
            "type":"Retail Goods"
        }
    ],
    "sg:phone":"+1 717 244 2311",
    "sg:postcode":"17356",
    "sg:province":"PA",
    "sg:tags":[
        "grocer"
    ],
    "wof:name":"Howard S Bowles Grocery",
    "wof:placetype":"venue"
},
  "geometry": {"coordinates":[-76.588662,39.883781],"type":"Point"}
}