{
  "type": "Feature",
  "properties": {
    "addr:full":"1637 Main St Mechanicsburg PA 17055",
    "addr:housenumber":"1637",
    "addr:postcode":"17055",
    "addr:street":"Main St",
    "iso:country":"US",
    "sg:address":"1637 Main St",
    "sg:city":"Mechanicsburg",
    "sg:classifiers":[
        {
            "category":"Professional",
            "type":"Services"
        }
    ],
    "sg:phone":"+1   ",
    "sg:postcode":"17055",
    "sg:province":"PA",
    "wof:name":"J C Stefanic",
    "wof:placetype":"venue"
},
  "geometry": {"coordinates":[-76.91568100000001,40.167756],"type":"Point"}
}