{
  "type": "Feature",
  "properties": {
    "iso:country":"US",
    "sg:address":"2600 B St",
    "sg:city":"Philadelphia",
    "sg:classifiers":[
        {
            "category":"Social Services",
            "type":"Services"
        }
    ],
    "sg:phone":"+1   ",
    "sg:postcode":"19125",
    "sg:province":"PA",
    "wof:name":"Early Intervention Headstart",
    "wof:placetype":"venue"
},
  "geometry": {"coordinates":[-75.12723200000001,39.989402],"type":"Point"}
}