{
  "type": "Feature",
  "properties": {
    "iso:country":"US",
    "sg:address":"4229 N Broad St",
    "sg:city":"Philadelphia",
    "sg:classifiers":[
        {
            "category":"Building & Trades",
            "subcategory":"Equipment Rental",
            "type":"Services"
        }
    ],
    "sg:phone":"+1 215 329 4000",
    "sg:postcode":"19140",
    "sg:province":"PA",
    "sg:tags":[
        "yard"
    ],
    "wof:name":"Rent A Ctr",
    "wof:placetype":"venue"
},
  "geometry": {"coordinates":[-75.149415,40.017146],"type":"Point"}
}