{
  "type": "Feature",
  "properties": {
    "addr:full":"116 Brookfield Way Mountain Top PA 18707",
    "addr:housenumber":"116",
    "addr:postcode":"18707",
    "addr:street":"Brookfield Way",
    "iso:country":"US",
    "sg:address":"116 Brookfield Way",
    "sg:city":"Mountain Top",
    "sg:classifiers":[
        {
            "category":"Professional",
            "subcategory":"Management & Consulting",
            "type":"Services"
        }
    ],
    "sg:phone":"+1 570 474 2252",
    "sg:postcode":"18707",
    "sg:province":"PA",
    "sg:tags":[
        "fire",
        "consultant",
        "protection"
    ],
    "wof:name":"O'Brien Assoc",
    "wof:placetype":"venue"
},
  "geometry": {"coordinates":[-75.913821,41.117733],"type":"Point"}
}