{
  "type": "Feature",
  "properties": {
    "iso:country":"US",
    "sg:address":"1084 Dutch Hollow Rd",
    "sg:city":"Jeannette",
    "sg:classifiers":[
        {
            "category":"Building & Trades",
            "subcategory":"Plumbing",
            "type":"Services"
        }
    ],
    "sg:phone":"+1   ",
    "sg:postcode":"15644",
    "sg:province":"PA",
    "sg:tags":[
        "contractor"
    ],
    "wof:name":"Cherep Heating & Cooling Inc",
    "wof:placetype":"venue"
},
  "geometry": {"coordinates":[-79.595855,40.375863],"type":"Point"}
}