{
  "type": "Feature",
  "properties": {
    "iso:country":"US",
    "sg:address":"56 N Queen St",
    "sg:city":"Dover",
    "sg:classifiers":[
        {
            "category":"Wholesale",
            "subcategory":"Electrical",
            "type":"Manufacturing & Wholesale Goods"
        }
    ],
    "sg:phone":"+1 717 843 9955",
    "sg:postcode":"17315",
    "sg:province":"PA",
    "sg:tags":[
        "fire",
        "alarm",
        "system"
    ],
    "wof:name":"ESI Inc/Mark Nardontonia",
    "wof:placetype":"venue"
},
  "geometry": {"coordinates":[-76.849266,40.002379],"type":"Point"}
}