{
  "type": "Feature",
  "properties": {
    "addr:full":"15 Walnut St Lebanon PA 17042",
    "addr:housenumber":"15",
    "addr:postcode":"17042",
    "addr:street":"Walnut St",
    "iso:country":"US",
    "sg:address":"15 Walnut St",
    "sg:city":"Lebanon",
    "sg:classifiers":[
        {
            "category":"Professional",
            "type":"Services"
        }
    ],
    "sg:phone":"+1   ",
    "sg:postcode":"17042",
    "sg:province":"PA",
    "wof:name":"Thomas Hinks",
    "wof:placetype":"venue"
},
  "geometry": {"coordinates":[-76.411968,40.337646],"type":"Point"}
}