{
  "type": "Feature",
  "properties": {
    "iso:country":"US",
    "sg:address":"3621 N Sydenham St",
    "sg:city":"Philadelphia",
    "sg:classifiers":[
        {
            "category":"Professional",
            "type":"Services"
        }
    ],
    "sg:phone":"+1   ",
    "sg:postcode":"19140",
    "sg:province":"PA",
    "wof:name":"Baidy Niangane",
    "wof:placetype":"venue"
},
  "geometry": {"coordinates":[-75.153649,40.009218],"type":"Point"}
}