{
  "type": "Feature",
  "properties": {
    "iso:country":"US",
    "sg:address":"117 Badger Hill Rd",
    "sg:city":"Portersville",
    "sg:classifiers":[
        {
            "category":"Wholesale",
            "subcategory":"Auto Parts",
            "type":"Manufacturing & Wholesale Goods"
        }
    ],
    "sg:phone":"+1 724 368 8006",
    "sg:postcode":"16051",
    "sg:province":"PA",
    "wof:name":"Deless Auto Body & Towing",
    "wof:placetype":"venue"
},
  "geometry": {"coordinates":[-80.128811,40.928062],"type":"Point"}
}