{
  "type": "Feature",
  "properties": {
    "addr:full":"2151 Linglestown Rd Harrisburg PA 17110",
    "addr:housenumber":"2151",
    "addr:postcode":"17110",
    "addr:street":"Linglestown Rd",
    "iso:country":"US",
    "sg:address":"2151 Linglestown Rd",
    "sg:city":"Harrisburg",
    "sg:classifiers":[
        {
            "category":"Shopping",
            "subcategory":"Discount & Variety Stores",
            "type":"Retail Goods"
        }
    ],
    "sg:phone":"+1   ",
    "sg:postcode":"17110",
    "sg:province":"PA",
    "sg:tags":[
        "miscellaneous",
        "merchandise",
        "general"
    ],
    "wof:name":"Dollar Only",
    "wof:placetype":"venue"
},
  "geometry": {"coordinates":[-76.865725,40.328483],"type":"Point"}
}