{
  "type": "Feature",
  "properties": {
    "iso:country":"US",
    "sg:address":"2727 Philmont Ave",
    "sg:city":"Huntingdon Vly",
    "sg:classifiers":[
        {
            "category":"Wholesale",
            "subcategory":"Metals & Minerals",
            "type":"Manufacturing & Wholesale Goods"
        }
    ],
    "sg:phone":"+1 215 938 0810",
    "sg:postcode":"19006",
    "sg:province":"PA",
    "sg:tags":[
        "steel",
        "warehouse"
    ],
    "wof:name":"Commonwealth Metal",
    "wof:placetype":"venue"
},
  "geometry": {"coordinates":[-75.046221,40.122724],"type":"Point"}
}