{
  "type": "Feature",
  "properties": {
    "iso:country":"US",
    "sg:address":"361 Towanda St",
    "sg:city":"White Haven",
    "sg:phone":"+1 570 443 9981",
    "sg:postcode":"18661",
    "sg:province":"PA",
    "sg:tags":[
        "gas"
    ],
    "wof:name":"Albee's Fuel Svc",
    "wof:placetype":"venue"
},
  "geometry": {"coordinates":[-75.77412699999999,41.061241],"type":"Point"}
}