{
  "type": "Feature",
  "properties": {
    "iso:country":"US",
    "sg:address":"1404 S 3rd St",
    "sg:city":"Philadelphia",
    "sg:classifiers":[
        {
            "category":"Place Of Worship",
            "subcategory":"Church",
            "type":"Public Place"
        },
        {
            "category":"Place Of Worship",
            "type":"Public Place"
        },
        {
            "category":"Organizations",
            "subcategory":"Religious Organization",
            "type":"Services"
        }
    ],
    "sg:phone":"+1 215 465 4050",
    "sg:postcode":"19147",
    "sg:province":"PA",
    "sg:tags":[
        "churches-catholic-traditional",
        "churches-catholic"
    ],
    "sg:website":"http://www.archbishopryan.com",
    "wof:name":"Sacred Heart Of Jesus Parish",
    "wof:placetype":"venue"
},
  "geometry": {"coordinates":[-75.14782,39.94042],"type":"Point"}
}