{
  "type": "Feature",
  "properties": {
    "iso:country":"US",
    "sg:address":"201 King of Prussia Rd",
    "sg:city":"Radnor",
    "sg:classifiers":[
        {
            "category":"Professional",
            "type":"Services"
        }
    ],
    "sg:phone":"+1 610 902 4020",
    "sg:postcode":"19087",
    "sg:province":"PA",
    "sg:tags":[
        "establishment"
    ],
    "wof:name":"Franks M E Inc",
    "wof:placetype":"venue"
},
  "geometry": {"coordinates":[-75.35684999999999,40.042925],"type":"Point"}
}