{
  "type": "Feature",
  "properties": {
    "iso:country":"US",
    "sg:address":"33 E Center St",
    "sg:city":"Lititz",
    "sg:classifiers":[
        {
            "category":"Organizations",
            "subcategory":"Religious Organization",
            "type":"Services"
        }
    ],
    "sg:phone":"+1 717 626 0900",
    "sg:postcode":"17543",
    "sg:province":"PA",
    "sg:tags":[
        "church"
    ],
    "wof:name":"First Church Of God",
    "wof:placetype":"venue"
},
  "geometry": {"coordinates":[-76.3069,40.154297],"type":"Point"}
}