{
  "type": "Feature",
  "properties": {
    "iso:country":"US",
    "sg:address":"737 Store Rd",
    "sg:city":"Harleysville",
    "sg:classifiers":[
        {
            "category":"Professional",
            "subcategory":"Management & Consulting",
            "type":"Services"
        }
    ],
    "sg:phone":"+1 610 584 6924",
    "sg:postcode":"19438",
    "sg:province":"PA",
    "sg:tags":[
        "consultant",
        "business"
    ],
    "wof:name":"Schettone Brown & Brown",
    "wof:placetype":"venue"
},
  "geometry": {"coordinates":[-75.376122,40.238794],"type":"Point"}
}