{
  "type": "Feature",
  "properties": {
    "iso:country":"US",
    "sg:address":"200 Red Rd",
    "sg:city":"Coatesville",
    "sg:classifiers":[
        {
            "category":"Manufacturing",
            "subcategory":"Glass & Minerals",
            "type":"Manufacturing & Wholesale Goods"
        }
    ],
    "sg:phone":"+1 610 383 4200",
    "sg:postcode":"19320",
    "sg:province":"PA",
    "sg:tags":[
        "wheel",
        "abrasive",
        "grinding",
        "mfg"
    ],
    "sg:website":"www.pacerindustries.com",
    "wof:name":"Pacer Industries Inc",
    "wof:placetype":"venue"
},
  "geometry": {"coordinates":[-75.865222,39.967682],"type":"Point"}
}