{
  "type": "Feature",
  "properties": {
    "addr:full":"799 W Trenton Ave Morrisville PA 19067",
    "addr:housenumber":"799",
    "addr:postcode":"19067",
    "addr:street":"W Trenton Ave",
    "iso:country":"US",
    "sg:address":"799 W Trenton Ave",
    "sg:city":"Morrisville",
    "sg:classifiers":[
        {
            "category":"Real Estate",
            "subcategory":"Real Estate Agent",
            "type":"Services"
        }
    ],
    "sg:phone":"+1 215 295 1181",
    "sg:postcode":"19067",
    "sg:province":"PA",
    "wof:name":"Bacs Realty Inc",
    "wof:placetype":"venue"
},
  "geometry": {"coordinates":[-74.807491,40.203556],"type":"Point"}
}