{
  "type": "Feature",
  "properties": {
    "addr:full":"1034 Montgomery Ave Narberth PA 19072",
    "addr:housenumber":"1034",
    "addr:postcode":"19072",
    "addr:street":"Montgomery Ave",
    "iso:country":"US",
    "sg:address":"1034 Montgomery Ave",
    "sg:city":"Narberth",
    "sg:classifiers":[
        {
            "category":"Education",
            "subcategory":"Special Training",
            "type":"Public Place"
        }
    ],
    "sg:phone":"+1 610 664 0363",
    "sg:postcode":"19072",
    "sg:province":"PA",
    "sg:tags":[
        "instruction",
        "driving"
    ],
    "wof:name":"Ace Driving School",
    "wof:placetype":"venue"
},
  "geometry": {"coordinates":[-75.264218,40.012832],"type":"Point"}
}