{
  "type": "Feature",
  "properties": {
    "iso:country":"US",
    "sg:address":"1303 S Broad St",
    "sg:city":"Philadelphia",
    "sg:classifiers":[
        {
            "category":"Real Estate",
            "subcategory":"Architect",
            "type":"Services"
        }
    ],
    "sg:phone":"+1 215 755 9050",
    "sg:postcode":"19147",
    "sg:province":"PA",
    "wof:name":"Landmark Prof Design",
    "wof:placetype":"venue"
},
  "geometry": {"coordinates":[-75.16738100000001,39.934084],"type":"Point"}
}