{
  "type": "Feature",
  "properties": {
    "iso:country":"US",
    "sg:address":"6323 Woodland Ave",
    "sg:city":"Philadelphia",
    "sg:classifiers":[
        {
            "category":"Shopping",
            "subcategory":"Clothing, Apparel, & Fashions",
            "type":"Retail Goods"
        }
    ],
    "sg:phone":"+1 215 724 9520",
    "sg:postcode":"19142",
    "sg:province":"PA",
    "sg:tags":[
        "item",
        "boutique"
    ],
    "wof:name":"Inbodia",
    "wof:placetype":"venue"
},
  "geometry": {"coordinates":[-75.232911,39.926721],"type":"Point"}
}