{
  "type": "Feature",
  "properties": {
    "iso:country":"US",
    "sg:address":"1605 E 3rd St",
    "sg:city":"Williamsport",
    "sg:classifiers":[
        {
            "category":"Shopping",
            "subcategory":"Clothing, Apparel, & Fashions",
            "type":"Retail Goods"
        }
    ],
    "sg:phone":"+1 570 327 1989",
    "sg:postcode":"17701",
    "sg:province":"PA",
    "sg:tags":[
        "tuxedo",
        "rental"
    ],
    "wof:name":"Colony Classics",
    "wof:placetype":"venue"
},
  "geometry": {"coordinates":[-76.973343,41.251109],"type":"Point"}
}