{
  "type": "Feature",
  "properties": {
    "iso:country":"US",
    "sg:address":"120 W State St",
    "sg:city":"Kennett Square",
    "sg:classifiers":[
        {
            "category":"Building & Trades",
            "subcategory":"Construction",
            "type":"Services"
        }
    ],
    "sg:phone":"+1 484 576 7393",
    "sg:postcode":"19348",
    "sg:province":"PA",
    "sg:tags":[
        "general",
        "contractor"
    ],
    "wof:name":"Shoreboard Construction",
    "wof:placetype":"venue"
},
  "geometry": {"coordinates":[-75.71192499999999,39.846569],"type":"Point"}
}