{
  "type": "Feature",
  "properties": {
    "addr:full":"731 Main St Dickson City PA 18519",
    "addr:housenumber":"731",
    "addr:postcode":"18519",
    "addr:street":"Main St",
    "iso:country":"US",
    "sg:address":"731 Main St",
    "sg:city":"Dickson City",
    "sg:classifiers":[
        {
            "category":"Professional",
            "subcategory":"Detective & Security Services",
            "type":"Services"
        }
    ],
    "sg:phone":"+1   ",
    "sg:postcode":"18519",
    "sg:province":"PA",
    "sg:tags":[
        "system"
    ],
    "wof:name":"Security Solutions",
    "wof:placetype":"venue"
},
  "geometry": {"coordinates":[-75.625146,41.459395],"type":"Point"}
}