{
  "type": "Feature",
  "properties": {
    "iso:country":"US",
    "sg:address":"11020 Parker Dr",
    "sg:city":"Irwin",
    "sg:classifiers":[
        {
            "category":"Manufacturing",
            "subcategory":"Electronics",
            "type":"Manufacturing & Wholesale Goods"
        },
        {
            "category":"Manufacturing",
            "subcategory":"Tools & Machinery",
            "type":"Manufacturing & Wholesale Goods"
        }
    ],
    "sg:phone":"+1 412 754 3000",
    "sg:postcode":"15642",
    "sg:province":"PA",
    "sg:tags":[
        "power",
        "system",
        "devices",
        "mfr",
        "protection",
        "electronic"
    ],
    "wof:name":"Mesta Electronics Inc",
    "wof:placetype":"venue"
},
  "geometry": {"coordinates":[-79.773844,40.334277],"type":"Point"}
}