{
  "type": "Feature",
  "properties": {
    "addr:full":"548 Hahnstown Rd Ephrata PA 17522",
    "addr:housenumber":"548",
    "addr:postcode":"17522",
    "addr:street":"Hahnstown Rd",
    "iso:country":"US",
    "sg:address":"548 Hahnstown Rd",
    "sg:city":"Ephrata",
    "sg:classifiers":[
        {
            "category":"Education",
            "subcategory":"School",
            "type":"Public Place"
        }
    ],
    "sg:phone":"+1   ",
    "sg:postcode":"17522",
    "sg:province":"PA",
    "wof:name":"Napierville Mennonite School",
    "wof:placetype":"venue"
},
  "geometry": {"coordinates":[-76.113215,40.180194],"type":"Point"}
}