{
  "type": "Feature",
  "properties": {
    "addr:full":"777 Wayne Ave Chambersburg PA 17201",
    "addr:housenumber":"777",
    "addr:postcode":"17201",
    "addr:street":"Wayne Ave",
    "iso:country":"US",
    "sg:address":"777 Wayne Ave",
    "sg:city":"Chambersburg",
    "sg:classifiers":[
        {
            "category":"Banks & Credit Unions",
            "subcategory":"Bank",
            "type":"Services"
        }
    ],
    "sg:phone":"+1 717 263 8493",
    "sg:postcode":"17201",
    "sg:province":"PA",
    "sg:tags":[
        "loan",
        "mortgage",
        "real estate"
    ],
    "wof:name":"American General Finance Inc",
    "wof:placetype":"venue"
},
  "geometry": {"coordinates":[-77.655232,39.916337],"type":"Point"}
}