{
  "type": "Feature",
  "properties": {
    "iso:country":"US",
    "sg:address":"2205 Oregon Pike",
    "sg:city":"Lancaster",
    "sg:classifiers":[
        {
            "category":"Insurance",
            "subcategory":"Insurance Agent",
            "type":"Services"
        }
    ],
    "sg:phone":"+1 717 569 5363",
    "sg:postcode":"17601",
    "sg:province":"PA",
    "wof:name":"Giorgio Assoc",
    "wof:placetype":"venue"
},
  "geometry": {"coordinates":[-76.29279699999999,40.081532],"type":"Point"}
}