{
  "type": "Feature",
  "properties": {
    "iso:country":"US",
    "sg:address":"7302 Rising Sun Ave",
    "sg:city":"Philadelphia",
    "sg:classifiers":[
        {
            "category":"Restaurant",
            "type":"Food & Drink"
        }
    ],
    "sg:phone":"+1 215 745 8066",
    "sg:postcode":"19111",
    "sg:province":"PA",
    "sg:tags":[
        "parlor",
        "eating",
        "ice",
        "cream"
    ],
    "wof:name":"Custard's Last Stand",
    "wof:placetype":"venue"
},
  "geometry": {"coordinates":[-75.083564,40.061966],"type":"Point"}
}