{
  "type": "Feature",
  "properties": {
    "addr:full":"25 W Otterman St Greensburg PA 15601",
    "addr:housenumber":"25",
    "addr:postcode":"15601",
    "addr:street":"W Otterman St",
    "iso:country":"US",
    "sg:address":"25 W Otterman St",
    "sg:city":"Greensburg",
    "sg:classifiers":[
        {
            "category":"Restaurant",
            "type":"Food & Drink"
        }
    ],
    "sg:phone":"+1   ",
    "sg:postcode":"15601",
    "sg:province":"PA",
    "sg:tags":[
        "eating"
    ],
    "wof:name":"Baldys Orginal Pizza",
    "wof:placetype":"venue"
},
  "geometry": {"coordinates":[-79.54470999999999,40.303559],"type":"Point"}
}