{
  "type": "Feature",
  "properties": {
    "addr:full":"107 S High St Zelienople PA 16063",
    "addr:housenumber":"107",
    "addr:postcode":"16063",
    "addr:street":"S High St",
    "iso:country":"US",
    "sg:address":"107 S High St",
    "sg:city":"Zelienople",
    "sg:classifiers":[
        {
            "category":"Real Estate",
            "subcategory":"Real Estate Services",
            "type":"Services"
        }
    ],
    "sg:phone":"+1 724 452 4020",
    "sg:postcode":"16063",
    "sg:province":"PA",
    "wof:name":"Gallagher Real Estate",
    "wof:placetype":"venue"
},
  "geometry": {"coordinates":[-80.13539900000001,40.795502],"type":"Point"}
}