{
  "type": "Feature",
  "properties": {
    "iso:country":"US",
    "sg:address":"1181 E 4th St",
    "sg:city":"Bethlehem",
    "sg:classifiers":[
        {
            "category":"Building & Trades",
            "subcategory":"Construction",
            "type":"Services"
        }
    ],
    "sg:phone":"+1   ",
    "sg:postcode":"18015",
    "sg:province":"PA",
    "sg:tags":[
        "general",
        "commercial",
        "family",
        "contractor"
    ],
    "wof:name":"Gonzales Brothers Inc",
    "wof:placetype":"venue"
},
  "geometry": {"coordinates":[-75.360293,40.611215],"type":"Point"}
}