{
  "type": "Feature",
  "properties": {
    "iso:country":"US",
    "sg:address":"RR 113",
    "sg:city":"Silverdale",
    "sg:classifiers":[
        {
            "category":"Personal",
            "subcategory":"Barber",
            "type":"Services"
        }
    ],
    "sg:phone":"+1 215 257 3172",
    "sg:postcode":"18962",
    "sg:province":"PA",
    "wof:name":"Shirley Ann Schmell",
    "wof:placetype":"venue"
},
  "geometry": {"coordinates":[-75.26950100000001,40.3498],"type":"Point"}
}