{
  "type": "Feature",
  "properties": {
    "iso:country":"US",
    "sg:address":"701 S Chester Rd",
    "sg:city":"Swarthmore",
    "sg:classifiers":[
        {
            "category":"Health Services",
            "subcategory":"Doctor",
            "type":"Services"
        }
    ],
    "sg:phone":"+1 610 541 0468",
    "sg:postcode":"19081",
    "sg:province":"PA",
    "sg:tags":[
        "clinic"
    ],
    "wof:name":"Swarthmore Dialysis Ctr",
    "wof:placetype":"venue"
},
  "geometry": {"coordinates":[-75.355508,39.887616],"type":"Point"}
}