{
  "type": "Feature",
  "properties": {
    "addr:full":"1606 Manning Blvd Levittown PA 19057",
    "addr:housenumber":"1606",
    "addr:postcode":"19057",
    "addr:street":"Manning Blvd",
    "iso:country":"US",
    "sg:address":"1606 Manning Blvd",
    "sg:city":"Levittown",
    "sg:classifiers":[
        {
            "category":"Manufacturing",
            "subcategory":"Metals",
            "type":"Manufacturing & Wholesale Goods"
        },
        {
            "category":"Building & Trades",
            "subcategory":"Plumbing",
            "type":"Services"
        }
    ],
    "sg:phone":"+1 215 945 5221",
    "sg:postcode":"19057",
    "sg:province":"PA",
    "sg:tags":[
        "work",
        "sheet",
        "metalwork",
        "contractor"
    ],
    "wof:name":"Eastern Sheet Metal",
    "wof:placetype":"venue"
},
  "geometry": {"coordinates":[-74.842653,40.125562],"type":"Point"}
}