{
  "type": "Feature",
  "properties": {
    "iso:country":"US",
    "sg:address":"11 Grammes Rd",
    "sg:city":"Allentown",
    "sg:classifiers":[
        {
            "category":"Shopping",
            "subcategory":"Stationery & Office Supplies",
            "type":"Retail Goods"
        }
    ],
    "sg:phone":"+1 610 797 6600",
    "sg:postcode":"18103",
    "sg:province":"PA",
    "sg:tags":[
        "equipment"
    ],
    "sg:website":"www.stanleyvidmar.com",
    "wof:name":"Stanley Vidmar Industrial Storage",
    "wof:placetype":"venue"
},
  "geometry": {"coordinates":[-75.4897,40.577202],"type":"Point"}
}