{
  "type": "Feature",
  "properties": {
    "iso:country":"US",
    "sg:address":"1269 E Philadelphia Ave",
    "sg:city":"Gilbertsville",
    "sg:phone":"+1 610 367 2266",
    "sg:postcode":"19525",
    "sg:province":"PA",
    "wof:name":"Brauns Auto Sales",
    "wof:placetype":"venue"
},
  "geometry": {"coordinates":[-75.612343,40.321281],"type":"Point"}
}