{
  "type": "Feature",
  "properties": {
    "iso:country":"US",
    "sg:address":"807 E Lawrence Ave",
    "sg:city":"Ellwood City",
    "sg:classifiers":[
        {
            "category":"Autos & Motor Vehicles",
            "subcategory":"Fuel & Gas Station",
            "type":"Retail Goods"
        }
    ],
    "sg:phone":"+1 724 752 9772",
    "sg:postcode":"16117",
    "sg:province":"PA",
    "sg:tags":[
        "oil"
    ],
    "wof:name":"Ellwood City Boron",
    "wof:placetype":"venue"
},
  "geometry": {"coordinates":[-80.292315,40.858353],"type":"Point"}
}