{
  "type": "Feature",
  "properties": {
    "iso:country":"US",
    "sg:address":"1002 Anna Ave",
    "sg:city":"West Mifflin",
    "sg:classifiers":[
        {
            "category":"Wholesale",
            "subcategory":"Machinery & Supplies",
            "type":"Manufacturing & Wholesale Goods"
        }
    ],
    "sg:phone":"+1   ",
    "sg:postcode":"15122",
    "sg:province":"PA",
    "sg:tags":[
        "equipment",
        "industrial"
    ],
    "wof:name":"Hecka Tech Co Inc",
    "wof:placetype":"venue"
},
  "geometry": {"coordinates":[-79.866705,40.368004],"type":"Point"}
}