{
  "type": "Feature",
  "properties": {
    "iso:country":"US",
    "sg:address":"801 County Line Rd",
    "sg:city":"Horsham",
    "sg:classifiers":[
        {
            "category":"Shopping",
            "type":"Retail Goods"
        }
    ],
    "sg:phone":"+1 215 343 0346",
    "sg:postcode":"19044",
    "sg:province":"PA",
    "sg:tags":[
        "awning",
        "canopy"
    ],
    "wof:name":"MLH Awnings Windows",
    "wof:placetype":"venue"
},
  "geometry": {"coordinates":[-75.143322,40.21429],"type":"Point"}
}