{
  "type": "Feature",
  "properties": {
    "iso:country":"US",
    "sg:address":"2528 Smallman St",
    "sg:city":"Pittsburgh",
    "sg:classifiers":[
        {
            "category":"Autos & Motor Vehicles",
            "subcategory":"Automobile Sales",
            "type":"Retail Goods"
        }
    ],
    "sg:phone":"+1 412 281 7999",
    "sg:postcode":"15222",
    "sg:province":"PA",
    "sg:tags":[
        "car",
        "dealer"
    ],
    "wof:name":"Northeast Auto Exchange Inc",
    "wof:placetype":"venue"
},
  "geometry": {"coordinates":[-79.979591,40.455264],"type":"Point"}
}