{
  "type": "Feature",
  "properties": {
    "iso:country":"US",
    "sg:address":"490 E North Ave",
    "sg:city":"Pittsburgh",
    "sg:classifiers":[
        {
            "category":"Health Services",
            "subcategory":"Doctor",
            "type":"Services"
        }
    ],
    "sg:phone":"+1 412 323 2882",
    "sg:postcode":"15212",
    "sg:province":"PA",
    "sg:tags":[
        "cardiologist"
    ],
    "wof:name":"Schuster Allan H MD",
    "wof:placetype":"venue"
},
  "geometry": {"coordinates":[-80.00160200000001,40.456402],"type":"Point"}
}