{
  "type": "Feature",
  "properties": {
    "iso:country":"US",
    "sg:address":"19 Independence Ct",
    "sg:city":"Folcroft",
    "sg:classifiers":[
        {
            "category":"Manufacturing",
            "subcategory":"Chemicals & Compounds",
            "type":"Manufacturing & Wholesale Goods"
        }
    ],
    "sg:phone":"+1 610 532 2248",
    "sg:postcode":"19032",
    "sg:province":"PA",
    "sg:tags":[
        "preparation",
        "pharmaceutical",
        "mfg"
    ],
    "wof:name":"Mallinckrodt Inc",
    "wof:placetype":"venue"
},
  "geometry": {"coordinates":[-75.276962,39.891989],"type":"Point"}
}