{
  "type": "Feature",
  "properties": {
    "iso:country":"US",
    "sg:address":"700 Markley St",
    "sg:city":"Norristown",
    "sg:classifiers":[
        {
            "category":"Autos & Motor Vehicles",
            "subcategory":"Auto Supplies",
            "type":"Retail Goods"
        }
    ],
    "sg:phone":"+1 610 275 5740",
    "sg:postcode":"19401",
    "sg:province":"PA",
    "sg:tags":[
        "automobile",
        "parts"
    ],
    "wof:name":"ITW Tire Stores",
    "wof:placetype":"venue"
},
  "geometry": {"coordinates":[-75.34425299999999,40.121072],"type":"Point"}
}