{
  "type": "Feature",
  "properties": {
    "iso:country":"US",
    "sg:address":"305 W Uwchlan Ave",
    "sg:city":"Downingtown",
    "sg:classifiers":[
        {
            "category":"Real Estate",
            "subcategory":"Real Estate Operator",
            "type":"Services"
        }
    ],
    "sg:phone":"+1 610 269 0801",
    "sg:postcode":"19335",
    "sg:province":"PA",
    "sg:tags":[
        "mobile",
        "home",
        "community"
    ],
    "wof:name":"Loretta's Mobile Home Park",
    "wof:placetype":"venue"
},
  "geometry": {"coordinates":[-75.681316,40.030848],"type":"Point"}
}