{
  "type": "Feature",
  "properties": {
    "iso:country":"US",
    "sg:address":"418 E Township Line Rd",
    "sg:city":"Havertown",
    "sg:classifiers":[
        {
            "category":"Autos & Motor Vehicles",
            "subcategory":"Auto Supplies",
            "type":"Retail Goods"
        },
        {
            "category":"Retail",
            "subcategory":"Auto Repair",
            "type":"Services"
        }
    ],
    "sg:phone":"+1 610 671 4805",
    "sg:postcode":"19083",
    "sg:province":"PA",
    "sg:tags":[
        "wheel",
        "oil",
        "axle",
        "electric",
        "clutch",
        "automobile",
        "referral",
        "servicing-automotive",
        "diagnostic",
        "lube",
        "brake",
        "automotive",
        "equipment-service",
        "alignment-frame",
        "air conditioning",
        "tune"
    ],
    "sg:website":"http://www.goodyeartires.com/",
    "wof:name":"Havertown Tire & Svc Inc",
    "wof:placetype":"venue"
},
  "geometry": {"coordinates":[-75.287987,39.971409],"type":"Point"}
}