{
  "type": "Feature",
  "properties": {
    "iso:country":"US",
    "sg:address":"2311 Easton Rd",
    "sg:city":"Bethlehem",
    "sg:classifiers":[
        {
            "category":"Building & Trades",
            "subcategory":"Construction",
            "type":"Services"
        }
    ],
    "sg:phone":"+1 610 866 2935",
    "sg:postcode":"18015",
    "sg:province":"PA",
    "sg:tags":[
        "general",
        "contractor"
    ],
    "wof:name":"Nauman Construction Inc",
    "wof:placetype":"venue"
},
  "geometry": {"coordinates":[-75.302312,40.606506],"type":"Point"}
}