{
  "type": "Feature",
  "properties": {
    "addr:full":"104 Bible Rd Spring Mills PA 16875",
    "addr:housenumber":"104",
    "addr:postcode":"16875",
    "addr:street":"Bible Rd",
    "iso:country":"US",
    "sg:address":"104 Bible Rd",
    "sg:city":"Spring Mills",
    "sg:classifiers":[
        {
            "category":"Real Estate",
            "subcategory":"Real Estate Operator",
            "type":"Services"
        }
    ],
    "sg:phone":"+1   ",
    "sg:postcode":"16875",
    "sg:province":"PA",
    "sg:tags":[
        "property",
        "lessor"
    ],
    "wof:name":"Theodore Coulter",
    "wof:placetype":"venue"
},
  "geometry": {"coordinates":[-77.636841,40.812241],"type":"Point"}
}