{
  "type": "Feature",
  "properties": {
    "addr:full":"10 Allegheny Sq Glassport PA 15045",
    "addr:housenumber":"10",
    "addr:postcode":"15045",
    "addr:street":"Allegheny Sq",
    "iso:country":"US",
    "sg:address":"10 Allegheny Sq",
    "sg:city":"Glassport",
    "sg:classifiers":[
        {
            "category":"Manufacturing",
            "subcategory":"Metals",
            "type":"Manufacturing & Wholesale Goods"
        }
    ],
    "sg:phone":"+1 412 664 1000",
    "sg:postcode":"15045",
    "sg:province":"PA",
    "sg:tags":[
        "steel",
        "mill",
        "ruling"
    ],
    "wof:name":"Allegheny Rebar Inc",
    "wof:placetype":"venue"
},
  "geometry": {"coordinates":[-79.892366,40.320869],"type":"Point"}
}