{
  "type": "Feature",
  "properties": {
    "iso:country":"US",
    "sg:address":"718 S 52nd St",
    "sg:city":"Philadelphia",
    "sg:classifiers":[
        {
            "category":"Food & Beverages",
            "subcategory":"Liquor & Beverages",
            "type":"Retail Goods"
        }
    ],
    "sg:phone":"+1 215 747 4667",
    "sg:postcode":"19143",
    "sg:province":"PA",
    "sg:tags":[
        "beer",
        "spirit",
        "wine"
    ],
    "wof:name":"Russell Willie",
    "wof:placetype":"venue"
},
  "geometry": {"coordinates":[-75.227402,39.948399],"type":"Point"}
}