{
  "type": "Feature",
  "properties": {
    "addr:full":"2700 S Front St Philadelphia PA 19148",
    "addr:housenumber":"2700",
    "addr:postcode":"19148",
    "addr:street":"S Front St",
    "iso:country":"US",
    "sg:address":"2700 S Front St",
    "sg:city":"Philadelphia",
    "sg:classifiers":[
        {
            "category":"Autos & Motor Vehicles",
            "subcategory":"Auto Supplies",
            "type":"Retail Goods"
        }
    ],
    "sg:phone":"+1   ",
    "sg:postcode":"19148",
    "sg:province":"PA",
    "wof:name":"R & S Parts and Service Inc",
    "wof:placetype":"venue"
},
  "geometry": {"coordinates":[-75.15040399999999,39.912431],"type":"Point"}
}