{
  "type": "Feature",
  "properties": {
    "iso:country":"US",
    "sg:address":"100 Candlelight Dr",
    "sg:city":"Ebensburg",
    "sg:classifiers":[
        {
            "category":"Real Estate",
            "subcategory":"Real Estate Operator",
            "type":"Services"
        }
    ],
    "sg:phone":"+1 814 471 6865",
    "sg:postcode":"15931",
    "sg:province":"PA",
    "sg:tags":[
        "apartment"
    ],
    "wof:name":"Graystone Court",
    "wof:placetype":"venue"
},
  "geometry": {"coordinates":[-78.724091,40.478458],"type":"Point"}
}