{
  "type": "Feature",
  "properties": {
    "iso:country":"US",
    "sg:address":"3627 Hulmeville Rd",
    "sg:city":"Bensalem",
    "sg:classifiers":[
        {
            "category":"Food & Beverages",
            "subcategory":"Groceries & Convenience Stores",
            "type":"Retail Goods"
        }
    ],
    "sg:phone":"+1 215 245 5676",
    "sg:postcode":"19020",
    "sg:province":"PA",
    "sg:website":"www.7-eleven.com",
    "wof:name":"7-Eleven Stores Inc",
    "wof:placetype":"venue"
},
  "geometry": {"coordinates":[-74.938742,40.105326],"type":"Point"}
}