{
  "type": "Feature",
  "properties": {
    "iso:country":"US",
    "sg:address":"81 Lancaster Ave",
    "sg:city":"Malvern",
    "sg:phone":"+1 610 644 4550",
    "sg:postcode":"19355",
    "sg:province":"PA",
    "wof:name":"Himalyan",
    "wof:placetype":"venue"
},
  "geometry": {"coordinates":[-75.527901,40.0433],"type":"Point"}
}