{
  "type": "Feature",
  "properties": {
    "iso:country":"US",
    "sg:address":"109 E Main St",
    "sg:city":"Dallastown",
    "sg:classifiers":[
        {
            "category":"Organizations",
            "subcategory":"Religious Organization",
            "type":"Services"
        }
    ],
    "sg:phone":"+1   ",
    "sg:postcode":"17313",
    "sg:province":"PA",
    "wof:name":"Pre School",
    "wof:placetype":"venue"
},
  "geometry": {"coordinates":[-76.64015499999999,39.900309],"type":"Point"}
}