{
  "type": "Feature",
  "properties": {
    "iso:country":"US",
    "sg:address":"840 Walnut St",
    "sg:city":"Philadelphia",
    "sg:classifiers":[
        {
            "category":"Health Services",
            "subcategory":"Doctor",
            "type":"Services"
        }
    ],
    "sg:phone":"+1 215 928 3280",
    "sg:postcode":"19107",
    "sg:province":"PA",
    "wof:name":"Eagle Ralph MD",
    "wof:placetype":"venue"
},
  "geometry": {"coordinates":[-75.155197,39.948399],"type":"Point"}
}