{
  "type": "Feature",
  "properties": {
    "addr:full":"920 Wyoming Ave Scranton PA 18509",
    "addr:housenumber":"920",
    "addr:postcode":"18509",
    "addr:street":"Wyoming Ave",
    "iso:country":"US",
    "sg:address":"920 Wyoming Ave",
    "sg:city":"Scranton",
    "sg:classifiers":[
        {
            "category":"Shopping",
            "subcategory":"Clothing, Apparel, & Fashions",
            "type":"Retail Goods"
        }
    ],
    "sg:phone":"+1   ",
    "sg:postcode":"18509",
    "sg:province":"PA",
    "wof:name":"Alans",
    "wof:placetype":"venue"
},
  "geometry": {"coordinates":[-75.65601100000001,41.416712],"type":"Point"}
}