{
  "type": "Feature",
  "properties": {
    "iso:country":"US",
    "sg:address":"400 Stanwix St",
    "sg:city":"Pittsburgh",
    "sg:classifiers":[
        {
            "category":"Professional",
            "type":"Services"
        }
    ],
    "sg:phone":"+1 412 281 1140",
    "sg:postcode":"15222",
    "sg:province":"PA",
    "sg:tags":[
        "actuary"
    ],
    "wof:name":"R H Herchenroether & Assoc",
    "wof:placetype":"venue"
},
  "geometry": {"coordinates":[-80.00414499999999,40.441056],"type":"Point"}
}