{
  "type": "Feature",
  "properties": {
    "iso:country":"US",
    "sg:address":"8230 Frankford Ave",
    "sg:city":"Philadelphia",
    "sg:classifiers":[
        {
            "category":"Health Services",
            "subcategory":"Health Practitioner",
            "type":"Services"
        }
    ],
    "sg:phone":"+1 215 333 8372",
    "sg:postcode":"19136",
    "sg:province":"PA",
    "sg:tags":[
        "therapist",
        "physical"
    ],
    "wof:name":"Allied Medical Assocs",
    "wof:placetype":"venue"
},
  "geometry": {"coordinates":[-75.023884,40.04295],"type":"Point"}
}