{
  "type": "Feature",
  "properties": {
    "iso:country":"US",
    "sg:address":"1139 State Rte 136",
    "sg:city":"Belle Vernon",
    "sg:classifiers":[
        {
            "category":"Manufacturing",
            "subcategory":"Building Materials",
            "type":"Manufacturing & Wholesale Goods"
        }
    ],
    "sg:phone":"+1   ",
    "sg:postcode":"15012",
    "sg:province":"PA",
    "sg:tags":[
        "mfg",
        "wood",
        "kitchen",
        "cabinet"
    ],
    "wof:name":"Shupes Custom Cabinetry",
    "wof:placetype":"venue"
},
  "geometry": {"coordinates":[-79.79629,40.213599],"type":"Point"}
}