{
  "type": "Feature",
  "properties": {
    "iso:country":"US",
    "sg:address":"1090 E Springettsbury Ave",
    "sg:city":"York",
    "sg:classifiers":[
        {
            "category":"Freight",
            "type":"Transportation"
        }
    ],
    "sg:phone":"+1 717 843 0995",
    "sg:postcode":"17403",
    "sg:province":"PA",
    "sg:tags":[
        "hauling",
        "trucking"
    ],
    "wof:name":"Eckert Trucking Inc",
    "wof:placetype":"venue"
},
  "geometry": {"coordinates":[-76.70232799999999,39.956397],"type":"Point"}
}