{
  "type": "Feature",
  "properties": {
    "addr:full":"3708 Rosemont Ave Camp Hill PA 17011",
    "addr:housenumber":"3708",
    "addr:postcode":"17011",
    "addr:street":"Rosemont Ave",
    "iso:country":"US",
    "sg:address":"3708 Rosemont Ave",
    "sg:city":"Camp Hill",
    "sg:classifiers":[
        {
            "category":"Education",
            "subcategory":"Preschool",
            "type":"Public Place"
        },
        {
            "category":"Education",
            "subcategory":"School",
            "type":"Public Place"
        }
    ],
    "sg:phone":"+1 717 737 9517",
    "sg:postcode":"17011",
    "sg:province":"PA",
    "sg:tags":[
        "elementary"
    ],
    "sg:website":"www.brooksidemontessori.com",
    "wof:name":"Brookside Montessori School",
    "wof:placetype":"venue"
},
  "geometry": {"coordinates":[-76.939201,40.222301],"type":"Point"}
}