{
  "type": "Feature",
  "properties": {
    "iso:country":"US",
    "sg:address":"201 S 13th St",
    "sg:city":"Philadelphia",
    "sg:classifiers":[
        {
            "category":"Real Estate",
            "subcategory":"Real Estate Operator",
            "type":"Services"
        }
    ],
    "sg:phone":"+1 215 732 6300",
    "sg:postcode":"19107",
    "sg:province":"PA",
    "sg:tags":[
        "apartment"
    ],
    "wof:name":"Walnut Square Apartment",
    "wof:placetype":"venue"
},
  "geometry": {"coordinates":[-75.162272,39.948329],"type":"Point"}
}