{
  "type": "Feature",
  "properties": {
    "addr:full":"2 Balsam Ct Newtown PA 18940",
    "addr:housenumber":"2",
    "addr:postcode":"18940",
    "addr:street":"Balsam Ct",
    "iso:country":"US",
    "sg:address":"2 Balsam Ct",
    "sg:city":"Newtown",
    "sg:classifiers":[
        {
            "category":"Professional",
            "subcategory":"Management & Consulting",
            "type":"Services"
        }
    ],
    "sg:phone":"+1 215 860 8123",
    "sg:postcode":"18940",
    "sg:province":"PA",
    "sg:tags":[
        "party",
        "planning"
    ],
    "wof:name":"Black Tie Optional",
    "wof:placetype":"venue"
},
  "geometry": {"coordinates":[-74.94620399999999,40.259098],"type":"Point"}
}