{
  "type": "Feature",
  "properties": {
    "iso:country":"US",
    "sg:address":"240 Berwick Hazleton Hwy",
    "sg:city":"Nescopeck",
    "sg:classifiers":[
        {
            "category":"Autos & Motor Vehicles",
            "subcategory":"Fuel & Gas Station",
            "type":"Retail Goods"
        }
    ],
    "sg:phone":"+1   ",
    "sg:postcode":"18635",
    "sg:province":"PA",
    "sg:tags":[
        "automobile",
        "station",
        "gasoline",
        "used"
    ],
    "wof:name":"Johns Garage",
    "wof:placetype":"venue"
},
  "geometry": {"coordinates":[-76.11839500000001,41.033532],"type":"Point"}
}