{
  "type": "Feature",
  "properties": {
    "addr:full":"2301 Lombard St Philadelphia PA 19146",
    "addr:housenumber":"2301",
    "addr:postcode":"19146",
    "addr:street":"Lombard St",
    "iso:country":"US",
    "sg:address":"2301 Lombard St",
    "sg:city":"Philadelphia",
    "sg:classifiers":[
        {
            "category":"Restaurant",
            "type":"Food & Drink"
        }
    ],
    "sg:phone":"+1 215 790 9557",
    "sg:postcode":"19146",
    "sg:province":"PA",
    "sg:tags":[
        "french"
    ],
    "wof:name":"Caf? Lutecia",
    "wof:placetype":"venue"
},
  "geometry": {"coordinates":[-75.17958400000001,39.946515],"type":"Point"}
}