{
  "type": "Feature",
  "properties": {
    "iso:country":"US",
    "sg:address":"1324 S 21st St",
    "sg:city":"Philadelphia",
    "sg:classifiers":[
        {
            "category":"Food & Beverages",
            "subcategory":"Meat & Fish",
            "type":"Retail Goods"
        }
    ],
    "sg:phone":"+1 215 336 7262",
    "sg:postcode":"19146",
    "sg:province":"PA",
    "sg:tags":[
        "seafood",
        "market"
    ],
    "wof:name":"Point Crab's & Seafood",
    "wof:placetype":"venue"
},
  "geometry": {"coordinates":[-75.179365,39.934838],"type":"Point"}
}