{
  "type": "Feature",
  "properties": {
    "addr:full":"7249 Frankstown Ave Pittsburgh PA 15208",
    "addr:housenumber":"7249",
    "addr:postcode":"15208",
    "addr:street":"Frankstown Ave",
    "iso:country":"US",
    "sg:address":"7249 Frankstown Ave",
    "sg:city":"Pittsburgh",
    "sg:classifiers":[
        {
            "category":"Organizations",
            "subcategory":"Professional Association",
            "type":"Services"
        }
    ],
    "sg:phone":"+1 412 247 4822",
    "sg:postcode":"15208",
    "sg:province":"PA",
    "wof:name":"National Assn-Minority Contrs",
    "wof:placetype":"venue"
},
  "geometry": {"coordinates":[-79.895027,40.457219],"type":"Point"}
}