{
  "type": "Feature",
  "properties": {
    "iso:country":"US",
    "sg:address":"40 S Newtown Street Rd",
    "sg:city":"Newtown Square",
    "sg:classifiers":[
        {
            "category":"Food & Beverages",
            "subcategory":"Fruits & Vegetables",
            "type":"Retail Goods"
        }
    ],
    "sg:phone":"+1 610 356 9755",
    "sg:postcode":"19073",
    "sg:province":"PA",
    "sg:tags":[
        "produce"
    ],
    "wof:name":"Gentile's Fruit Market",
    "wof:placetype":"venue"
},
  "geometry": {"coordinates":[-75.39793299999999,39.982576],"type":"Point"}
}