{
  "type": "Feature",
  "properties": {
    "iso:country":"US",
    "sg:address":"2304 Terwood Rd",
    "sg:city":"Huntingdon Vly",
    "sg:classifiers":[
        {
            "category":"Building & Trades",
            "subcategory":"Construction",
            "type":"Services"
        }
    ],
    "sg:phone":"+1 215 659 4438",
    "sg:postcode":"19006",
    "sg:province":"PA",
    "sg:tags":[
        "contractor",
        "general"
    ],
    "wof:name":"Gary Lorenzon Contractor Inc",
    "wof:placetype":"venue"
},
  "geometry": {"coordinates":[-75.099318,40.149406],"type":"Point"}
}