{
  "type": "Feature",
  "properties": {
    "addr:full":"815 S 4th St Philadelphia PA 19147",
    "addr:housenumber":"815",
    "addr:postcode":"19147",
    "addr:street":"S 4Th St",
    "iso:country":"US",
    "sg:address":"815 S 4th St",
    "sg:city":"Philadelphia",
    "sg:classifiers":[
        {
            "category":"Manufacturing",
            "subcategory":"Buildings",
            "type":"Manufacturing & Wholesale Goods"
        },
        {
            "category":"Real Estate",
            "subcategory":"Real Estate Services",
            "type":"Services"
        },
        {
            "category":"Building & Trades",
            "subcategory":"Construction",
            "type":"Services"
        }
    ],
    "sg:phone":"+1 215 279 7915",
    "sg:postcode":"19147",
    "sg:province":"PA",
    "sg:tags":[
        "builder",
        "broker",
        "contractor",
        "buyer",
        "home"
    ],
    "wof:name":"Philly New Homes Com",
    "wof:placetype":"venue"
},
  "geometry": {"coordinates":[-75.15003,39.937746],"type":"Point"}
}