{
  "type": "Feature",
  "properties": {
    "iso:country":"US",
    "sg:address":"170 Freeport Rd",
    "sg:city":"Blawnox",
    "sg:classifiers":[
        {
            "category":"Retail",
            "subcategory":"Auto Repair",
            "type":"Services"
        }
    ],
    "sg:phone":"+1 412 828 5114",
    "sg:postcode":"15238",
    "sg:province":"PA",
    "sg:tags":[
        "repairing",
        "automobile",
        "automotive"
    ],
    "wof:name":"Hi Tech Auto Care",
    "wof:placetype":"venue"
},
  "geometry": {"coordinates":[-79.865404,40.491574],"type":"Point"}
}