{
  "type": "Feature",
  "properties": {
    "iso:country":"US",
    "sg:address":"226 Grant Ave",
    "sg:city":"Pittsburgh",
    "sg:classifiers":[
        {
            "category":"Communications",
            "subcategory":"Film & Video Production",
            "type":"Services"
        }
    ],
    "sg:phone":"+1   ",
    "sg:postcode":"15209",
    "sg:province":"PA",
    "sg:tags":[
        "motion"
    ],
    "wof:name":"Outlook Productions",
    "wof:placetype":"venue"
},
  "geometry": {"coordinates":[-79.971722,40.479193],"type":"Point"}
}