{
  "type": "Feature",
  "properties": {
    "addr:full":"91 Pleasant St Bradford PA 16701",
    "addr:housenumber":"91",
    "addr:postcode":"16701",
    "addr:street":"Pleasant St",
    "iso:country":"US",
    "sg:address":"91 Pleasant St",
    "sg:city":"Bradford",
    "sg:classifiers":[
        {
            "category":"Building & Trades",
            "subcategory":"Construction",
            "type":"Services"
        }
    ],
    "sg:phone":"+1   ",
    "sg:postcode":"16701",
    "sg:province":"PA",
    "sg:tags":[
        "nonresidential"
    ],
    "wof:name":"Daryls Home Improvement",
    "wof:placetype":"venue"
},
  "geometry": {"coordinates":[-78.653488,41.960511],"type":"Point"}
}