{
  "type": "Feature",
  "properties": {
    "iso:country":"US",
    "sg:address":"8150 Perry Hwy",
    "sg:city":"Pittsburgh",
    "sg:classifiers":[
        {
            "category":"Professional",
            "subcategory":"Business Services",
            "type":"Services"
        }
    ],
    "sg:phone":"+1 412 366 7071",
    "sg:postcode":"15237",
    "sg:province":"PA",
    "sg:tags":[
        "interior",
        "consultant",
        "decorating",
        "design",
        "decorator"
    ],
    "wof:name":"Design Group North",
    "wof:placetype":"venue"
},
  "geometry": {"coordinates":[-80.038737,40.555387],"type":"Point"}
}