{
  "type": "Feature",
  "properties": {
    "addr:full":"12480 Game Club Rd Brogue PA 17309",
    "addr:housenumber":"12480",
    "addr:postcode":"17309",
    "addr:street":"Game Club Rd",
    "iso:country":"US",
    "sg:address":"12480 Game Club Rd",
    "sg:city":"Brogue",
    "sg:phone":"+1   ",
    "sg:postcode":"17309",
    "sg:province":"PA",
    "sg:tags":[
        "farm",
        "corn"
    ],
    "wof:name":"Dougherty Brothers",
    "wof:placetype":"venue"
},
  "geometry": {"coordinates":[-76.44983499999999,39.861207],"type":"Point"}
}