{
  "type": "Feature",
  "properties": {
    "iso:country":"US",
    "sg:address":"1 Frederick St",
    "sg:city":"Hanover",
    "sg:classifiers":[
        {
            "category":"Retail",
            "subcategory":"Laundry & Dry Cleaning",
            "type":"Services"
        }
    ],
    "sg:phone":"+1 717 632 2268",
    "sg:postcode":"17331",
    "sg:province":"PA",
    "sg:tags":[
        "cleaners",
        "rug",
        "carpet"
    ],
    "wof:name":"J W Myers Flooring & Carpet Cr",
    "wof:placetype":"venue"
},
  "geometry": {"coordinates":[-76.98327399999999,39.800478],"type":"Point"}
}