{
  "type": "Feature",
  "properties": {
    "addr:full":"10810 Orton Rd Wattsburg PA 16442",
    "addr:housenumber":"10810",
    "addr:postcode":"16442",
    "addr:street":"Orton Rd",
    "iso:country":"US",
    "sg:address":"10810 Orton Rd",
    "sg:city":"Wattsburg",
    "sg:classifiers":[
        {
            "category":"Building & Trades",
            "subcategory":"Construction",
            "type":"Services"
        }
    ],
    "sg:phone":"+1 814 739 9955",
    "sg:postcode":"16442",
    "sg:province":"PA",
    "sg:tags":[
        "general",
        "contractor"
    ],
    "wof:name":"Jim Fletcher Construction Inc",
    "wof:placetype":"venue"
},
  "geometry": {"coordinates":[-79.88320299999999,42.062757],"type":"Point"}
}