{
  "type": "Feature",
  "properties": {
    "iso:country":"US",
    "sg:address":"1717 Arch St Ste 3730",
    "sg:city":"Philadelphia",
    "sg:classifiers":[
        {
            "category":"Real Estate",
            "subcategory":"Architect",
            "type":"Services"
        }
    ],
    "sg:phone":"+1 215 569 1006",
    "sg:postcode":"19103",
    "sg:province":"PA",
    "sg:tags":[
        "architects'",
        "specification",
        "builders'",
        "construction",
        "architectural"
    ],
    "wof:name":"H L M Design",
    "wof:placetype":"venue"
},
  "geometry": {"coordinates":[-75.16828700000001,39.955012],"type":"Point"}
}