{
  "type": "Feature",
  "properties": {
    "iso:country":"US",
    "sg:address":"371 Cedar Blvd",
    "sg:city":"Pittsburgh",
    "sg:classifiers":[
        {
            "category":"Education",
            "subcategory":"Special Training",
            "type":"Public Place"
        }
    ],
    "sg:phone":"+1 412 531 3004",
    "sg:postcode":"15228",
    "sg:province":"PA",
    "sg:tags":[
        "reading",
        "instruction",
        "improvement"
    ],
    "wof:name":"Greater Pittsburgh Literacy",
    "wof:placetype":"venue"
},
  "geometry": {"coordinates":[-80.05499399999999,40.377992],"type":"Point"}
}