{
  "type": "Feature",
  "properties": {
    "iso:country":"US",
    "sg:address":"1542 Packer Ave",
    "sg:city":"Philadelphia",
    "sg:classifiers":[
        {
            "category":"Social Services",
            "subcategory":"Child Care",
            "type":"Services"
        }
    ],
    "sg:phone":"+1 215 334 2836",
    "sg:postcode":"19145",
    "sg:province":"PA",
    "sg:tags":[
        "day"
    ],
    "wof:name":"A Whole New World",
    "wof:placetype":"venue"
},
  "geometry": {"coordinates":[-75.174797,39.912201],"type":"Point"}
}