{
  "type": "Feature",
  "properties": {
    "addr:full":"43 N 9th St Allentown PA 18101",
    "addr:housenumber":"43",
    "addr:postcode":"18101",
    "addr:street":"N 9Th St",
    "iso:country":"US",
    "sg:address":"43 N 9th St",
    "sg:city":"Allentown",
    "sg:classifiers":[
        {
            "category":"Shopping",
            "subcategory":"Used Merchandise",
            "type":"Retail Goods"
        }
    ],
    "sg:phone":"+1   ",
    "sg:postcode":"18101",
    "sg:province":"PA",
    "wof:name":"Duvalls Antq Nice Collectibles",
    "wof:placetype":"venue"
},
  "geometry": {"coordinates":[-75.47605799999999,40.602592],"type":"Point"}
}