{
  "type": "Feature",
  "properties": {
    "addr:full":"44 Oriole Ave Media PA 19063",
    "addr:housenumber":"44",
    "addr:postcode":"19063",
    "addr:street":"Oriole Ave",
    "iso:country":"US",
    "sg:address":"44 Oriole Ave",
    "sg:city":"Media",
    "sg:classifiers":[
        {
            "category":"Building & Trades",
            "subcategory":"Construction",
            "type":"Services"
        }
    ],
    "sg:phone":"+1   ",
    "sg:postcode":"19063",
    "sg:province":"PA",
    "sg:tags":[
        "specializing",
        "remodeling",
        "installation",
        "contractor"
    ],
    "wof:name":"Innovations",
    "wof:placetype":"venue"
},
  "geometry": {"coordinates":[-75.436277,39.915825],"type":"Point"}
}