{
  "type": "Feature",
  "properties": {
    "iso:country":"US",
    "sg:address":"276 Chestnut St",
    "sg:city":"Mertztown",
    "sg:classifiers":[
        {
            "category":"Building & Trades",
            "subcategory":"Construction",
            "type":"Services"
        }
    ],
    "sg:phone":"+1 610 682 7697",
    "sg:postcode":"19539",
    "sg:province":"PA",
    "sg:tags":[
        "pavement",
        "marking"
    ],
    "wof:name":"Martelli Pavement Marking",
    "wof:placetype":"venue"
},
  "geometry": {"coordinates":[-75.67968999999999,40.507279],"type":"Point"}
}