{
  "type": "Feature",
  "properties": {
    "iso:country":"US",
    "sg:address":"720 E Lehman St",
    "sg:city":"Lebanon",
    "sg:classifiers":[
        {
            "category":"Retail",
            "subcategory":"Auto Repair",
            "type":"Services"
        }
    ],
    "sg:phone":"+1 717 866 4486",
    "sg:postcode":"17046",
    "sg:province":"PA",
    "sg:tags":[
        "installs",
        "automotive",
        "glass"
    ],
    "wof:name":"Diamond Auto Glass",
    "wof:placetype":"venue"
},
  "geometry": {"coordinates":[-76.399895,40.346679],"type":"Point"}
}