{
  "type": "Feature",
  "properties": {
    "iso:country":"US",
    "sg:address":"24 United Dr",
    "sg:city":"Clarion",
    "sg:classifiers":[
        {
            "category":"Bars & Pubs",
            "type":"Food & Drink"
        }
    ],
    "sg:phone":"+1 800 424 6423",
    "sg:postcode":"16214",
    "sg:province":"PA",
    "sg:tags":[
        "lounge",
        "hotel",
        "cocktail"
    ],
    "sg:website":"http://www.qualityinn.com/hotel-clarion-pennsylvania-PA385?promo=yplocal",
    "wof:name":"Quality Inn & Suites Clarion",
    "wof:placetype":"venue"
},
  "geometry": {"coordinates":[-79.39272,41.189394],"type":"Point"}
}