{
  "type": "Feature",
  "properties": {
    "addr:full":"783 Diehl Rd Bedford PA 15522",
    "addr:housenumber":"783",
    "addr:postcode":"15522",
    "addr:street":"Diehl Rd",
    "iso:country":"US",
    "sg:address":"783 Diehl Rd",
    "sg:city":"Bedford",
    "sg:classifiers":[
        {
            "category":"Organizations",
            "subcategory":"Religious Organization",
            "type":"Services"
        }
    ],
    "sg:phone":"+1 814 847 2593",
    "sg:postcode":"15522",
    "sg:province":"PA",
    "sg:tags":[
        "church"
    ],
    "wof:name":"Friends Cove United Chr-Christ",
    "wof:placetype":"venue"
},
  "geometry": {"coordinates":[-78.496483,39.928685],"type":"Point"}
}