{
  "type": "Feature",
  "properties": {
    "iso:country":"US",
    "sg:address":"1559 Georgetown Rd",
    "sg:city":"Christiana",
    "sg:classifiers":[
        {
            "category":"Wholesale",
            "subcategory":"Construction Materials",
            "type":"Manufacturing & Wholesale Goods"
        }
    ],
    "sg:phone":"+1 717 529 1012",
    "sg:postcode":"17509",
    "sg:province":"PA",
    "sg:tags":[
        "cupola"
    ],
    "wof:name":"Zook Polycraft",
    "wof:placetype":"venue"
},
  "geometry": {"coordinates":[-76.03711800000001,39.907909],"type":"Point"}
}