{
  "type": "Feature",
  "properties": {
    "addr:full":"198 Hill Rd Bloomsburg PA 17815",
    "addr:housenumber":"198",
    "addr:postcode":"17815",
    "addr:street":"Hill Rd",
    "iso:country":"US",
    "sg:address":"198 Hill Rd",
    "sg:city":"Bloomsburg",
    "sg:classifiers":[
        {
            "category":"Building & Trades",
            "subcategory":"Landscaping Services",
            "type":"Services"
        }
    ],
    "sg:phone":"+1 570 784 8166",
    "sg:postcode":"17815",
    "sg:province":"PA",
    "sg:tags":[
        "landscape",
        "contractor"
    ],
    "wof:name":"Ruckle's Landscaping",
    "wof:placetype":"venue"
},
  "geometry": {"coordinates":[-76.44485299999999,41.014054],"type":"Point"}
}