{
  "type": "Feature",
  "properties": {
    "addr:full":"2525 Hallowell Rd Huntingdon Vly PA 19006",
    "addr:housenumber":"2525",
    "addr:postcode":"19006",
    "addr:street":"Hallowell Rd",
    "iso:country":"US",
    "sg:address":"2525 Hallowell Rd",
    "sg:city":"Huntingdon Vly",
    "sg:classifiers":[
        {
            "category":"Professional",
            "subcategory":"Management & Consulting",
            "type":"Services"
        }
    ],
    "sg:phone":"+1 215 938 1229",
    "sg:postcode":"19006",
    "sg:province":"PA",
    "sg:tags":[
        "counselor",
        "public",
        "relations"
    ],
    "wof:name":"Susan Matthews",
    "wof:placetype":"venue"
},
  "geometry": {"coordinates":[-75.06791200000001,40.125088],"type":"Point"}
}