{
  "type": "Feature",
  "properties": {
    "iso:country":"US",
    "sg:address":"614 Baldwin St",
    "sg:city":"Meadville",
    "sg:classifiers":[
        {
            "category":"Retail",
            "subcategory":"Funeral Services",
            "type":"Services"
        }
    ],
    "sg:phone":"+1 814 724 7860",
    "sg:postcode":"16335",
    "sg:province":"PA",
    "sg:tags":[
        "director"
    ],
    "wof:name":"Hatheway-Tedesco Funeral Home",
    "wof:placetype":"venue"
},
  "geometry": {"coordinates":[-80.150784,41.647848],"type":"Point"}
}