{
  "type": "Feature",
  "properties": {
    "iso:country":"US",
    "sg:address":"7860 Lake Pleasant Rd",
    "sg:city":"Erie",
    "sg:classifiers":[
        {
            "category":"Building & Trades",
            "subcategory":"Landscaping Services",
            "type":"Services"
        }
    ],
    "sg:phone":"+1   ",
    "sg:postcode":"16509",
    "sg:province":"PA",
    "sg:tags":[
        "lawn",
        "design",
        "garden"
    ],
    "wof:name":"Wards Landscape Service Inc",
    "wof:placetype":"venue"
},
  "geometry": {"coordinates":[-80.02207,42.082412],"type":"Point"}
}