{
  "type": "Feature",
  "properties": {
    "iso:country":"US",
    "sg:address":"132 Conoy Ave",
    "sg:city":"Elizabethtown",
    "sg:classifiers":[
        {
            "category":"Manufacturing",
            "subcategory":"Buildings",
            "type":"Manufacturing & Wholesale Goods"
        },
        {
            "category":"Building & Trades",
            "subcategory":"Construction",
            "type":"Services"
        }
    ],
    "sg:phone":"+1 717 419 7717",
    "sg:postcode":"17022",
    "sg:province":"PA",
    "sg:tags":[
        "home",
        "builder",
        "contractor"
    ],
    "wof:name":"Jeremy Snyder Home Improvement",
    "wof:placetype":"venue"
},
  "geometry": {"coordinates":[-76.59358,40.163929],"type":"Point"}
}