{
  "type": "Feature",
  "properties": {
    "addr:full":"522 N Gallatin Ave Uniontown PA 15401",
    "addr:housenumber":"522",
    "addr:postcode":"15401",
    "addr:street":"N Gallatin Ave",
    "iso:country":"US",
    "sg:address":"522 N Gallatin Ave",
    "sg:city":"Uniontown",
    "sg:classifiers":[
        {
            "category":"Personal",
            "subcategory":"Beauty Salon",
            "type":"Services"
        }
    ],
    "sg:phone":"+1 724 437 5480",
    "sg:postcode":"15401",
    "sg:province":"PA",
    "wof:name":"Northside Beauty Salon",
    "wof:placetype":"venue"
},
  "geometry": {"coordinates":[-79.713807,39.912113],"type":"Point"}
}