{
  "type": "Feature",
  "properties": {
    "iso:country":"US",
    "sg:address":"244 Bowers Rd",
    "sg:city":"Punxsutawney",
    "sg:classifiers":[
        {
            "category":"Autos & Motor Vehicles",
            "subcategory":"Fuel & Gas Station",
            "type":"Retail Goods"
        },
        {
            "category":"Retail",
            "subcategory":"Auto Repair",
            "type":"Services"
        }
    ],
    "sg:phone":"+1 610 682 2713",
    "sg:postcode":"15767",
    "sg:province":"PA",
    "sg:tags":[
        "automobile",
        "inspection",
        "diagnostic"
    ],
    "wof:name":"Luckenbills Auto Service",
    "wof:placetype":"venue"
},
  "geometry": {"coordinates":[-78.862808,40.947218],"type":"Point"}
}