{
  "type": "Feature",
  "properties": {
    "iso:country":"US",
    "sg:address":"252 S 16th St",
    "sg:city":"Philadelphia",
    "sg:classifiers":[
        {
            "category":"Arts & Performance",
            "subcategory":"Theater",
            "type":"Entertainment"
        }
    ],
    "sg:phone":"+1   ",
    "sg:postcode":"19102",
    "sg:province":"PA",
    "sg:tags":[
        "organization"
    ],
    "wof:name":"Encore Series Inc",
    "wof:placetype":"venue"
},
  "geometry": {"coordinates":[-75.168094,39.947459],"type":"Point"}
}