{
  "type": "Feature",
  "properties": {
    "iso:country":"US",
    "sg:address":"55 N 3rd St",
    "sg:city":"Philadelphia",
    "sg:classifiers":[
        {
            "category":"Personal",
            "subcategory":"Beauty Salon",
            "type":"Services"
        },
        {
            "category":"Shopping",
            "subcategory":"Beauty & Cosmetics",
            "type":"Retail Goods"
        }
    ],
    "sg:phone":"+1 215 922 6656",
    "sg:postcode":"19176",
    "sg:province":"PA",
    "sg:tags":[
        "hair",
        "supply"
    ],
    "sg:website":"www.mokobeauty.com",
    "wof:name":"MOKO",
    "wof:placetype":"venue"
},
  "geometry": {"coordinates":[-75.14537199999999,39.951455],"type":"Point"}
}