{
  "type": "Feature",
  "properties": {
    "addr:full":"3853 Peach St Erie PA 16509",
    "addr:housenumber":"3853",
    "addr:postcode":"16509",
    "addr:street":"Peach St",
    "iso:country":"US",
    "sg:address":"3853 Peach St",
    "sg:city":"Erie",
    "sg:classifiers":[
        {
            "category":"Retail",
            "subcategory":"Veterinary Services",
            "type":"Services"
        }
    ],
    "sg:phone":"+1 814 864 3019",
    "sg:postcode":"16509",
    "sg:province":"PA",
    "sg:tags":[
        "hospital",
        "animal"
    ],
    "wof:name":"Glenwood Pet Hospital",
    "wof:placetype":"venue"
},
  "geometry": {"coordinates":[-80.081971,42.096469],"type":"Point"}
}