{
  "type": "Feature",
  "properties": {
    "addr:full":"209 Spring St Meadville PA 16335",
    "addr:housenumber":"209",
    "addr:postcode":"16335",
    "addr:street":"Spring St",
    "iso:country":"US",
    "sg:address":"209 Spring St",
    "sg:city":"Meadville",
    "sg:classifiers":[
        {
            "category":"Health Services",
            "subcategory":"Nursing And Care Facility",
            "type":"Services"
        }
    ],
    "sg:phone":"+1 814 724 7883",
    "sg:postcode":"16335",
    "sg:province":"PA",
    "sg:tags":[
        "home",
        "convalescent"
    ],
    "wof:name":"Carousel House Personal Care",
    "wof:placetype":"venue"
},
  "geometry": {"coordinates":[-80.151512,41.647999],"type":"Point"}
}