{
  "type": "Feature",
  "properties": {
    "addr:full":"303 Park City Center Lancaster PA 17601",
    "addr:housenumber":"303",
    "addr:postcode":"17601",
    "addr:street":"Park",
    "iso:country":"US",
    "sg:address":"303 Park City Center",
    "sg:city":"Lancaster",
    "sg:classifiers":[
        {
            "category":"Shopping",
            "subcategory":"Optical Goods",
            "type":"Retail Goods"
        }
    ],
    "sg:phone":"+1 717 394 5768",
    "sg:postcode":"17601",
    "sg:province":"PA",
    "sg:tags":[
        "sun",
        "goggles",
        "sunglasses"
    ],
    "wof:name":"Sunglass Hut",
    "wof:placetype":"venue"
},
  "geometry": {"coordinates":[-76.33879399999999,40.0646],"type":"Point"}
}