{
  "type": "Feature",
  "properties": {
    "iso:country":"US",
    "sg:address":"69 E Main St",
    "sg:city":"Lititz",
    "sg:classifiers":[
        {
            "category":"Professional",
            "subcategory":"Lawyer & Legal Services",
            "type":"Services"
        }
    ],
    "sg:phone":"+1 717 626 6728",
    "sg:postcode":"17543",
    "sg:province":"PA",
    "sg:tags":[
        "attorney"
    ],
    "wof:name":"Morgan Hallgren Crosswell KANE",
    "wof:placetype":"venue"
},
  "geometry": {"coordinates":[-76.304942,40.156902],"type":"Point"}
}