{
  "type": "Feature",
  "properties": {
    "iso:country":"US",
    "sg:address":"799 Water St",
    "sg:city":"Meadville",
    "sg:classifiers":[
        {
            "category":"Building & Trades",
            "subcategory":"Electrical",
            "type":"Services"
        },
        {
            "category":"Retail",
            "subcategory":"Auto Repair",
            "type":"Services"
        }
    ],
    "sg:phone":"+1 814 282 6332",
    "sg:postcode":"16335",
    "sg:province":"PA",
    "sg:tags":[
        "automobile",
        "electrician",
        "electric"
    ],
    "wof:name":"Massung Electric",
    "wof:placetype":"venue"
},
  "geometry": {"coordinates":[-80.153519,41.64156],"type":"Point"}
}