{
  "type": "Feature",
  "properties": {
    "iso:country":"US",
    "sg:address":"190 Konhaus Rd",
    "sg:city":"Mechanicsburg",
    "sg:classifiers":[
        {
            "category":"Building & Trades",
            "subcategory":"Equipment Rental",
            "type":"Services"
        }
    ],
    "sg:phone":"+1   ",
    "sg:postcode":"17050",
    "sg:province":"PA",
    "sg:tags":[
        "sales"
    ],
    "wof:name":"Brubaker Equipment Inc",
    "wof:placetype":"venue"
},
  "geometry": {"coordinates":[-77.064153,40.214081],"type":"Point"}
}