{
  "type": "Feature",
  "properties": {
    "addr:full":"520 Star Grille Rd Butler PA 16002",
    "addr:housenumber":"520",
    "addr:postcode":"16002",
    "addr:street":"Star Grille Rd",
    "iso:country":"US",
    "sg:address":"520 Star Grille Rd",
    "sg:city":"Butler",
    "sg:classifiers":[
        {
            "category":"Freight",
            "type":"Transportation"
        }
    ],
    "sg:phone":"+1   ",
    "sg:postcode":"16002",
    "sg:province":"PA",
    "sg:tags":[
        "haul",
        "local",
        "long",
        "trucking"
    ],
    "wof:name":"Crider Truck Leasing Inc",
    "wof:placetype":"venue"
},
  "geometry": {"coordinates":[-79.78509,40.818084],"type":"Point"}
}