{
  "type": "Feature",
  "properties": {
    "addr:full":"831 Swamp Rd Penns Park PA 18925",
    "addr:housenumber":"831",
    "addr:postcode":"18925",
    "addr:street":"Swamp Rd",
    "iso:country":"US",
    "sg:address":"831 Swamp Rd",
    "sg:city":"Penns Park",
    "sg:classifiers":[
        {
            "category":"Building & Trades",
            "subcategory":"Landscaping Services",
            "type":"Services"
        }
    ],
    "sg:phone":"+1 215 598 7880",
    "sg:postcode":"18925",
    "sg:province":"PA",
    "sg:tags":[
        "topsoil"
    ],
    "wof:name":"Tershon Landscaping & Supplies",
    "wof:placetype":"venue"
},
  "geometry": {"coordinates":[-75.037661,40.26858],"type":"Point"}
}