{
  "type": "Feature",
  "properties": {
    "iso:country":"US",
    "sg:address":"150 S Independence Mall W # 101",
    "sg:city":"Philadelphia",
    "sg:classifiers":[
        {
            "category":"Health Services",
            "subcategory":"Hospital",
            "type":"Services"
        }
    ],
    "sg:phone":"+1 215 922 2801",
    "sg:postcode":"19106",
    "sg:province":"PA",
    "sg:tags":[
        "dialysis"
    ],
    "sg:website":"http://www.davita.com/",
    "wof:name":"Franklin Dialysis Center",
    "wof:placetype":"venue"
},
  "geometry": {"coordinates":[-75.15089399999999,39.948467],"type":"Point"}
}