{
  "type": "Feature",
  "properties": {
    "iso:country":"US",
    "sg:address":"6085 Delta Rd",
    "sg:city":"Delta",
    "sg:classifiers":[
        {
            "category":"Restaurant",
            "type":"Food & Drink"
        }
    ],
    "sg:phone":"+1   ",
    "sg:postcode":"17314",
    "sg:province":"PA",
    "sg:tags":[
        "eating"
    ],
    "wof:name":"Sk Part 2 Ltd",
    "wof:placetype":"venue"
},
  "geometry": {"coordinates":[-76.34872799999999,39.776099],"type":"Point"}
}