{
  "type": "Feature",
  "properties": {
    "iso:country":"US",
    "sg:address":"1259 Derry St",
    "sg:city":"Harrisburg",
    "sg:classifiers":[
        {
            "category":"Restaurant",
            "type":"Food & Drink"
        }
    ],
    "sg:phone":"+1 717 238 6611",
    "sg:postcode":"17104",
    "sg:province":"PA",
    "wof:name":"Kiwi's Bar & Grill",
    "wof:placetype":"venue"
},
  "geometry": {"coordinates":[-76.869499,40.263302],"type":"Point"}
}