{
  "type": "Feature",
  "properties": {
    "iso:country":"US",
    "sg:address":"5340 Old Berwick Rd",
    "sg:city":"Bloomsburg",
    "sg:classifiers":[
        {
            "category":"Professional",
            "subcategory":"Art Services",
            "type":"Services"
        }
    ],
    "sg:phone":"+1 570 784 7933",
    "sg:postcode":"17815",
    "sg:province":"PA",
    "sg:tags":[
        "photographer"
    ],
    "wof:name":"American Views Photography",
    "wof:placetype":"venue"
},
  "geometry": {"coordinates":[-76.35404,41.021873],"type":"Point"}
}