{
  "type": "Feature",
  "properties": {
    "addr:full":"2604 Cecil B Moore Ave Philadelphia PA 19121",
    "addr:housenumber":"2604",
    "addr:postcode":"19121",
    "addr:street":"Cecil B Moore Ave",
    "iso:country":"US",
    "sg:address":"2604 Cecil B Moore Ave",
    "sg:city":"Philadelphia",
    "sg:classifiers":[
        {
            "category":"Food & Beverages",
            "subcategory":"Groceries & Convenience Stores",
            "type":"Retail Goods"
        }
    ],
    "sg:phone":"+1 215 684 1721",
    "sg:postcode":"19121",
    "sg:province":"PA",
    "wof:name":"Cecilbmoore Grocery",
    "wof:placetype":"venue"
},
  "geometry": {"coordinates":[-75.177588,39.981089],"type":"Point"}
}