{
  "type": "Feature",
  "properties": {
    "iso:country":"US",
    "sg:address":"5356 Chew Ave",
    "sg:city":"Philadelphia",
    "sg:classifiers":[
        {
            "category":"Professional",
            "subcategory":"Business Services",
            "type":"Services"
        }
    ],
    "sg:phone":"+1 215 843 5413",
    "sg:postcode":"19138",
    "sg:province":"PA",
    "sg:tags":[
        "arbitration"
    ],
    "wof:name":"Good Shepherd Mediation Prgrm",
    "wof:placetype":"venue"
},
  "geometry": {"coordinates":[-75.160203,40.042325],"type":"Point"}
}