{
  "type": "Feature",
  "properties": {
    "iso:country":"US",
    "sg:address":"1440 Russell Rd",
    "sg:city":"Paoli",
    "sg:classifiers":[
        {
            "category":"Social Services",
            "type":"Services"
        }
    ],
    "sg:phone":"+1   ",
    "sg:postcode":"19301",
    "sg:province":"PA",
    "sg:tags":[
        "rehabilitation"
    ],
    "wof:name":"Rehab After Work",
    "wof:placetype":"venue"
},
  "geometry": {"coordinates":[-75.463544,40.04316],"type":"Point"}
}