{
  "type": "Feature",
  "properties": {
    "iso:country":"US",
    "sg:address":"38 Old Forest Rd",
    "sg:city":"Newtown Square",
    "sg:classifiers":[
        {
            "category":"Wholesale",
            "subcategory":"Electrical",
            "type":"Manufacturing & Wholesale Goods"
        }
    ],
    "sg:phone":"+1 610 359 1002",
    "sg:postcode":"19073",
    "sg:province":"PA",
    "sg:tags":[
        "equipment",
        "electronic",
        "supply"
    ],
    "sg:website":"www.precisionsales.com",
    "wof:name":"Precision Sales & Equipment",
    "wof:placetype":"venue"
},
  "geometry": {"coordinates":[-75.409195,39.970052],"type":"Point"}
}