{
  "type": "Feature",
  "properties": {
    "addr:full":"139 W Broad St Tamaqua PA 18252",
    "addr:housenumber":"139",
    "addr:postcode":"18252",
    "addr:street":"W Broad St",
    "iso:country":"US",
    "sg:address":"139 W Broad St",
    "sg:city":"Tamaqua",
    "sg:classifiers":[
        {
            "category":"Health Services",
            "subcategory":"Doctor",
            "type":"Services"
        }
    ],
    "sg:phone":"+1 570 668 1211",
    "sg:postcode":"18252",
    "sg:province":"PA",
    "sg:tags":[
        "dentist"
    ],
    "wof:name":"Gerald A Brazzo DDS",
    "wof:placetype":"venue"
},
  "geometry": {"coordinates":[-75.97198899999999,40.797216],"type":"Point"}
}