{
  "type": "Feature",
  "properties": {
    "addr:full":"531 Fallowfield Ave Charleroi PA 15022",
    "addr:housenumber":"531",
    "addr:postcode":"15022",
    "addr:street":"Fallowfield Ave",
    "iso:country":"US",
    "sg:address":"531 Fallowfield Ave",
    "sg:city":"Charleroi",
    "sg:classifiers":[
        {
            "category":"Personal",
            "subcategory":"Beauty Salon",
            "type":"Services"
        }
    ],
    "sg:phone":"+1   ",
    "sg:postcode":"15022",
    "sg:province":"PA",
    "sg:tags":[
        "shop"
    ],
    "wof:name":"Landrin Pattie Uniq Your Hair",
    "wof:placetype":"venue"
},
  "geometry": {"coordinates":[-79.89914,40.138669],"type":"Point"}
}