{
  "type": "Feature",
  "properties": {
    "iso:country":"US",
    "sg:address":"24 W Main St Unit Frnt",
    "sg:city":"Waynesboro",
    "sg:classifiers":[
        {
            "category":"Insurance",
            "subcategory":"Insurance Agent",
            "type":"Services"
        },
        {
            "category":"Insurance",
            "subcategory":"Hazard Insurance",
            "type":"Services"
        }
    ],
    "sg:phone":"+1 717 267 1328",
    "sg:postcode":"17268",
    "sg:province":"PA",
    "sg:tags":[
        "auto",
        "commercial",
        "business"
    ],
    "sg:website":"http://www.key-pa.com",
    "wof:name":"Key Insurance Group",
    "wof:placetype":"venue"
},
  "geometry": {"coordinates":[-77.578456,39.75615],"type":"Point"}
}