{
  "type": "Feature",
  "properties": {
    "iso:country":"US",
    "sg:address":"710 Horseshoe Pike",
    "sg:city":"Lebanon",
    "sg:classifiers":[
        {
            "category":"Wholesale",
            "subcategory":"Durable Goods & Equipment",
            "type":"Manufacturing & Wholesale Goods"
        }
    ],
    "sg:phone":"+1 717 867 4495",
    "sg:postcode":"17042",
    "sg:province":"PA",
    "sg:tags":[
        "sawdust",
        "shaving"
    ],
    "wof:name":"Abram Hoover Farm",
    "wof:placetype":"venue"
},
  "geometry": {"coordinates":[-76.485427,40.28498],"type":"Point"}
}