{
  "type": "Feature",
  "properties": {
    "iso:country":"US",
    "sg:address":"251 S 16th St",
    "sg:city":"Philadelphia",
    "sg:classifiers":[
        {
            "category":"Retail",
            "subcategory":"Laundry & Dry Cleaning",
            "type":"Services"
        }
    ],
    "sg:phone":"+1 215 546 3667",
    "sg:postcode":"19102",
    "sg:province":"PA",
    "wof:name":"British Imperial Dry Cleaners",
    "wof:placetype":"venue"
},
  "geometry": {"coordinates":[-75.167801,39.9482],"type":"Point"}
}