{
  "type": "Feature",
  "properties": {
    "iso:country":"US",
    "sg:address":"1073 Church Rd",
    "sg:city":"East Greenville",
    "sg:classifiers":[
        {
            "category":"Manufacturing",
            "subcategory":"Printing",
            "type":"Manufacturing & Wholesale Goods"
        }
    ],
    "sg:phone":"+1   ",
    "sg:postcode":"18041",
    "sg:province":"PA",
    "sg:tags":[
        "publishing"
    ],
    "wof:name":"Grace Wild",
    "wof:placetype":"venue"
},
  "geometry": {"coordinates":[-75.513167,40.399028],"type":"Point"}
}