{
  "type": "Feature",
  "properties": {
    "addr:full":"1401 Wilmington Rd New Castle PA 16105",
    "addr:housenumber":"1401",
    "addr:postcode":"16105",
    "addr:street":"Wilmington Rd New",
    "iso:country":"US",
    "sg:address":"1401 Wilmington Rd",
    "sg:city":"New Castle",
    "sg:classifiers":[
        {
            "category":"Health Services",
            "subcategory":"Doctor",
            "type":"Services"
        }
    ],
    "sg:phone":"+1   ",
    "sg:postcode":"16105",
    "sg:province":"PA",
    "sg:tags":[
        "medical"
    ],
    "wof:name":"Surish P Amina MD",
    "wof:placetype":"venue"
},
  "geometry": {"coordinates":[-80.352198,41.015315],"type":"Point"}
}