{
  "type": "Feature",
  "properties": {
    "iso:country":"US",
    "sg:address":"524 Layton Rd",
    "sg:city":"Clarks Summit",
    "sg:classifiers":[
        {
            "category":"Personal",
            "subcategory":"Beauty Salon",
            "type":"Services"
        }
    ],
    "sg:phone":"+1 570 587 5393",
    "sg:postcode":"18411",
    "sg:province":"PA",
    "wof:name":"That Hair Affair",
    "wof:placetype":"venue"
},
  "geometry": {"coordinates":[-75.674451,41.480441],"type":"Point"}
}