{
  "type": "Feature",
  "properties": {
    "addr:full":"3064 N 7th St Philadelphia PA 19133",
    "addr:housenumber":"3064",
    "addr:postcode":"19133",
    "addr:street":"N 7Th St",
    "iso:country":"US",
    "sg:address":"3064 N 7th St",
    "sg:city":"Philadelphia",
    "sg:classifiers":[
        {
            "category":"Food & Beverages",
            "subcategory":"Groceries & Convenience Stores",
            "type":"Retail Goods"
        }
    ],
    "sg:phone":"+1 215 225 5008",
    "sg:postcode":"19133",
    "sg:province":"PA",
    "sg:tags":[
        "grocer"
    ],
    "wof:name":"Juan's Grocery",
    "wof:placetype":"venue"
},
  "geometry": {"coordinates":[-75.142403,39.998501],"type":"Point"}
}