{
  "type": "Feature",
  "properties": {
    "addr:full":"47 Race St Manor PA 15665",
    "addr:housenumber":"47",
    "addr:postcode":"15665",
    "addr:street":"Race St Manor",
    "iso:country":"US",
    "sg:address":"47 Race St",
    "sg:city":"Manor",
    "sg:classifiers":[
        {
            "category":"Government",
            "subcategory":"Office",
            "type":"Public Place"
        }
    ],
    "sg:phone":"+1   ",
    "sg:postcode":"15665",
    "sg:province":"PA",
    "sg:tags":[
        "development"
    ],
    "wof:name":"Zoning Officer",
    "wof:placetype":"venue"
},
  "geometry": {"coordinates":[-79.67055999999999,40.334839],"type":"Point"}
}