{
  "type": "Feature",
  "properties": {
    "iso:country":"US",
    "sg:address":"4 General Steuben Dr",
    "sg:city":"Media",
    "sg:classifiers":[
        {
            "category":"Professional",
            "subcategory":"Accounting & Tax Preparation",
            "type":"Services"
        }
    ],
    "sg:phone":"+1 610 891 0206",
    "sg:postcode":"19063",
    "sg:province":"PA",
    "wof:name":"Stokes Mickey & Luke",
    "wof:placetype":"venue"
},
  "geometry": {"coordinates":[-75.408339,39.902262],"type":"Point"}
}