{
  "type": "Feature",
  "properties": {
    "addr:full":"274 Main St Harleysville PA 19438",
    "addr:housenumber":"274",
    "addr:postcode":"19438",
    "addr:street":"Main St",
    "iso:country":"US",
    "sg:address":"274 Main St",
    "sg:city":"Harleysville",
    "sg:classifiers":[
        {
            "category":"Restaurant",
            "type":"Food & Drink"
        }
    ],
    "sg:menulink":"http://www.allmenus.com/pa/lower-salford/206084-mcdonalds/menu/",
    "sg:phone":"+1 215 256 1140",
    "sg:postcode":"19438",
    "sg:province":"PA",
    "sg:tags":[
        "burger",
        "american"
    ],
    "wof:name":"McDonald's",
    "wof:placetype":"venue"
},
  "geometry": {"coordinates":[-75.376648,40.267585],"type":"Point"}
}