{
  "type": "Feature",
  "properties": {
    "iso:country":"US",
    "sg:address":"1501 Harrisburg Pike",
    "sg:city":"Carlisle",
    "sg:classifiers":[
        {
            "category":"Food & Beverages",
            "subcategory":"Groceries & Convenience Stores",
            "type":"Retail Goods"
        }
    ],
    "sg:phone":"+1 717 243 8850",
    "sg:postcode":"17013",
    "sg:province":"PA",
    "wof:name":"Flying J Travel Plaza",
    "wof:placetype":"venue"
},
  "geometry": {"coordinates":[-77.125397,40.234299],"type":"Point"}
}