{
  "type": "Feature",
  "properties": {
    "iso:country":"US",
    "sg:address":"1351 Creek Rd",
    "sg:city":"Glenmoore",
    "sg:classifiers":[
        {
            "category":"Autos & Motor Vehicles",
            "subcategory":"Automobile Sales",
            "type":"Retail Goods"
        }
    ],
    "sg:phone":"+1 610 942 4411",
    "sg:postcode":"19343",
    "sg:province":"PA",
    "wof:name":"Marsh Creek Grand Prix",
    "wof:placetype":"venue"
},
  "geometry": {"coordinates":[-75.75266999999999,40.07605],"type":"Point"}
}