{
  "type": "Feature",
  "properties": {
    "iso:country":"US",
    "sg:address":"1722 Scalp Ave",
    "sg:city":"Johnstown",
    "sg:classifiers":[
        {
            "category":"Autos & Motor Vehicles",
            "subcategory":"Auto Supplies",
            "type":"Retail Goods"
        }
    ],
    "sg:phone":"+1   ",
    "sg:postcode":"15904",
    "sg:province":"PA",
    "wof:name":"B & D Off Road/Vehicle Spc",
    "wof:placetype":"venue"
},
  "geometry": {"coordinates":[-78.84997799999999,40.260084],"type":"Point"}
}