{
  "type": "Feature",
  "properties": {
    "iso:country":"US",
    "sg:address":"1514 Yerkes St",
    "sg:city":"Philadelphia",
    "sg:classifiers":[
        {
            "category":"Building & Trades",
            "subcategory":"Pest Control",
            "type":"Services"
        }
    ],
    "sg:phone":"+1 215 224 1488",
    "sg:postcode":"19150",
    "sg:province":"PA",
    "wof:name":"Quality Pest Control Co",
    "wof:placetype":"venue"
},
  "geometry": {"coordinates":[-75.168267,40.063816],"type":"Point"}
}