{
  "type": "Feature",
  "properties": {
    "iso:country":"US",
    "sg:address":"915 Pittsburgh St",
    "sg:city":"Springdale",
    "sg:classifiers":[
        {
            "category":"Professional",
            "subcategory":"Lawyer & Legal Services",
            "type":"Services"
        }
    ],
    "sg:phone":"+1 724 274 7337",
    "sg:postcode":"15144",
    "sg:province":"PA",
    "sg:tags":[
        "attorney"
    ],
    "wof:name":"Mears & Smith",
    "wof:placetype":"venue"
},
  "geometry": {"coordinates":[-79.777107,40.541655],"type":"Point"}
}