{
  "type": "Feature",
  "properties": {
    "iso:country":"US",
    "sg:address":"4259 Nantucket Dr",
    "sg:city":"Mechanicsburg",
    "sg:classifiers":[
        {
            "category":"Government",
            "subcategory":"Office",
            "type":"Public Place"
        }
    ],
    "sg:phone":"+1   ",
    "sg:postcode":"17050",
    "sg:province":"PA",
    "sg:tags":[
        "educational",
        "program",
        "administrative"
    ],
    "wof:name":"Nikken Independant Distributor",
    "wof:placetype":"venue"
},
  "geometry": {"coordinates":[-76.96911299999999,40.270072],"type":"Point"}
}