{
  "type": "Feature",
  "properties": {
    "iso:country":"US",
    "sg:address":"2455 Park Ave",
    "sg:city":"Easton",
    "sg:classifiers":[
        {
            "category":"Shopping",
            "subcategory":"Music",
            "type":"Retail Goods"
        }
    ],
    "sg:phone":"+1 610 253 0677",
    "sg:postcode":"18045",
    "sg:province":"PA",
    "sg:tags":[
        "video",
        "disc",
        "tape",
        "cassette"
    ],
    "wof:name":"Suncoast Motion Picture Co",
    "wof:placetype":"venue"
},
  "geometry": {"coordinates":[-75.260468,40.694664],"type":"Point"}
}