{
  "type": "Feature",
  "properties": {
    "addr:full":"2 Scott Way Essington PA 19029",
    "addr:housenumber":"2",
    "addr:postcode":"19029",
    "addr:street":"Scott Way",
    "iso:country":"US",
    "sg:address":"2 Scott Way",
    "sg:city":"Essington",
    "sg:classifiers":[
        {
            "category":"Social Services",
            "subcategory":"Child Care",
            "type":"Services"
        }
    ],
    "sg:phone":"+1 610 521 2667",
    "sg:postcode":"19029",
    "sg:province":"PA",
    "sg:tags":[
        "day"
    ],
    "wof:name":"Childrens Choice",
    "wof:placetype":"venue"
},
  "geometry": {"coordinates":[-75.261692,39.874896],"type":"Point"}
}