{
  "type": "Feature",
  "properties": {
    "iso:country":"US",
    "sg:address":"Allegheny General Hospital",
    "sg:city":"Pittsburgh",
    "sg:classifiers":[
        {
            "category":"Health Services",
            "subcategory":"Doctor",
            "type":"Services"
        }
    ],
    "sg:phone":"+1 412 359 3682",
    "sg:postcode":"15212",
    "sg:province":"PA",
    "wof:name":"Brown Frank MD",
    "wof:placetype":"venue"
},
  "geometry": {"coordinates":[-80.003346,40.457031],"type":"Point"}
}