{
  "type": "Feature",
  "properties": {
    "iso:country":"US",
    "sg:address":"561 Freeport Rd",
    "sg:city":"Freeport",
    "sg:classifiers":[
        {
            "category":"Health Services",
            "subcategory":"Chiropractor",
            "type":"Services"
        }
    ],
    "sg:phone":"+1 724 295 4400",
    "sg:postcode":"16229",
    "sg:province":"PA",
    "wof:name":"Patriot Wellness Ctr",
    "wof:placetype":"venue"
},
  "geometry": {"coordinates":[-79.66933299999999,40.705638],"type":"Point"}
}