{
  "type": "Feature",
  "properties": {
    "iso:country":"US",
    "sg:address":"910 Gall Rd",
    "sg:city":"Easton",
    "sg:classifiers":[
        {
            "category":"Organizations",
            "subcategory":"Religious Organization",
            "type":"Services"
        }
    ],
    "sg:phone":"+1 610 253 1364",
    "sg:postcode":"18040",
    "sg:province":"PA",
    "sg:tags":[
        "clergy"
    ],
    "wof:name":"Allen Schaarschmidt",
    "wof:placetype":"venue"
},
  "geometry": {"coordinates":[-75.25988099999999,40.773333],"type":"Point"}
}