{
  "type": "Feature",
  "properties": {
    "addr:full":"1517 Piketown Rd Harrisburg PA 17112",
    "addr:housenumber":"1517",
    "addr:postcode":"17112",
    "addr:street":"Piketown Rd",
    "iso:country":"US",
    "sg:address":"1517 Piketown Rd",
    "sg:city":"Harrisburg",
    "sg:classifiers":[
        {
            "category":"Manufacturing",
            "subcategory":"Leather Goods",
            "type":"Manufacturing & Wholesale Goods"
        }
    ],
    "sg:phone":"+1   ",
    "sg:postcode":"17112",
    "sg:province":"PA",
    "sg:tags":[
        "mfg"
    ],
    "wof:name":"Felsburg Leathercraft",
    "wof:placetype":"venue"
},
  "geometry": {"coordinates":[-76.755633,40.391649],"type":"Point"}
}