{
  "type": "Feature",
  "properties": {
    "iso:country":"US",
    "sg:address":"521 W 7th St",
    "sg:city":"Erie",
    "sg:classifiers":[
        {
            "category":"Social Services",
            "subcategory":"Adult Care",
            "type":"Services"
        }
    ],
    "sg:phone":"+1 814 459 5853",
    "sg:postcode":"16502",
    "sg:province":"PA",
    "sg:tags":[
        "residential"
    ],
    "wof:name":"Gaudenzia Erie Community House",
    "wof:placetype":"venue"
},
  "geometry": {"coordinates":[-80.097391,42.123652],"type":"Point"}
}