{
  "type": "Feature",
  "properties": {
    "iso:country":"US",
    "sg:address":"203 N Potomac St",
    "sg:city":"Waynesboro",
    "sg:classifiers":[
        {
            "category":"Health Services",
            "subcategory":"Chiropractor",
            "type":"Services"
        }
    ],
    "sg:phone":"+1 717 762 3820",
    "sg:postcode":"17268",
    "sg:province":"PA",
    "wof:name":"March Dr Sharon K Chirprctr",
    "wof:placetype":"venue"
},
  "geometry": {"coordinates":[-77.577499,39.759899],"type":"Point"}
}