{
  "type": "Feature",
  "properties": {
    "iso:country":"US",
    "sg:address":"509 Carlisle St",
    "sg:city":"Hanover",
    "sg:classifiers":[
        {
            "category":"Personal",
            "subcategory":"Beauty Salon",
            "type":"Services"
        }
    ],
    "sg:phone":"+1   ",
    "sg:postcode":"17325",
    "sg:province":"PA",
    "sg:tags":[
        "shop"
    ],
    "wof:name":"Pampered Lady & Gent Inc",
    "wof:placetype":"venue"
},
  "geometry": {"coordinates":[-77.231054,39.838522],"type":"Point"}
}