{
  "type": "Feature",
  "properties": {
    "addr:full":"10884 Carlson Dr Irwin PA 15642",
    "addr:housenumber":"10884",
    "addr:postcode":"15642",
    "addr:street":"Carlson Dr",
    "iso:country":"US",
    "sg:address":"10884 Carlson Dr",
    "sg:city":"Irwin",
    "sg:classifiers":[
        {
            "category":"Professional",
            "type":"Services"
        }
    ],
    "sg:phone":"+1   ",
    "sg:postcode":"15642",
    "sg:province":"PA",
    "wof:name":"Fertile Fields",
    "wof:placetype":"venue"
},
  "geometry": {"coordinates":[-79.72400500000001,40.329399],"type":"Point"}
}