{
  "type": "Feature",
  "properties": {
    "iso:country":"US",
    "sg:address":"497 E Lehman St",
    "sg:city":"Lebanon",
    "sg:classifiers":[
        {
            "category":"Sports & Exercise",
            "subcategory":"Race Track",
            "type":"Entertainment"
        }
    ],
    "sg:phone":"+1 717 279 7004",
    "sg:postcode":"17046",
    "sg:province":"PA",
    "sg:tags":[
        "equipment",
        "supply"
    ],
    "wof:name":"Speed & Sports",
    "wof:placetype":"venue"
},
  "geometry": {"coordinates":[-76.404388,40.346602],"type":"Point"}
}