{
  "type": "Feature",
  "properties": {
    "iso:country":"US",
    "sg:address":"12 Market St",
    "sg:city":"Mifflinburg",
    "sg:classifiers":[
        {
            "category":"Organizations",
            "subcategory":"Religious Organization",
            "type":"Services"
        }
    ],
    "sg:phone":"+1   ",
    "sg:postcode":"17844",
    "sg:province":"PA",
    "wof:name":"First Church of Nazarene Inc",
    "wof:placetype":"venue"
},
  "geometry": {"coordinates":[-77.037131,40.920443],"type":"Point"}
}