{
  "type": "Feature",
  "properties": {
    "iso:country":"US",
    "sg:address":"611 3rd St",
    "sg:city":"Beaver",
    "sg:classifiers":[
        {
            "category":"Home & Garden",
            "subcategory":"Hardware",
            "type":"Retail Goods"
        }
    ],
    "sg:phone":"+1 724 774 4930",
    "sg:postcode":"15009",
    "sg:province":"PA",
    "wof:name":"Fischer Hardware Co Inc",
    "wof:placetype":"venue"
},
  "geometry": {"coordinates":[-80.305747,40.694772],"type":"Point"}
}