{
  "type": "Feature",
  "properties": {
    "iso:country":"US",
    "sg:address":"2552 N 29th St",
    "sg:city":"Philadelphia",
    "sg:classifiers":[
        {
            "category":"Building & Trades",
            "subcategory":"Cleaning & Sanitation",
            "type":"Services"
        }
    ],
    "sg:phone":"+1 267 977 4047",
    "sg:postcode":"19132",
    "sg:province":"PA",
    "sg:tags":[
        "house"
    ],
    "wof:name":"Elite Janitorial & Maid Svc",
    "wof:placetype":"venue"
},
  "geometry": {"coordinates":[-75.179129,39.994675],"type":"Point"}
}