{
  "type": "Feature",
  "properties": {
    "iso:country":"US",
    "sg:address":"6904 Emilie Rd",
    "sg:city":"Levittown",
    "sg:classifiers":[
        {
            "category":"Shopping",
            "type":"Retail Goods"
        }
    ],
    "sg:phone":"+1 267 914 0500",
    "sg:postcode":"19057",
    "sg:province":"PA",
    "sg:tags":[
        "telephone",
        "cellular"
    ],
    "wof:name":"Wireless Technology",
    "wof:placetype":"venue"
},
  "geometry": {"coordinates":[-74.855473,40.154097],"type":"Point"}
}