{
  "type": "Feature",
  "properties": {
    "addr:full":"6574 W Ridge Rd Erie PA 16506",
    "addr:housenumber":"6574",
    "addr:postcode":"16506",
    "addr:street":"W Ridge Rd",
    "iso:country":"US",
    "sg:address":"6574 W Ridge Rd",
    "sg:city":"Erie",
    "sg:classifiers":[
        {
            "category":"Building & Trades",
            "subcategory":"Construction",
            "type":"Services"
        }
    ],
    "sg:phone":"+1   ",
    "sg:postcode":"16506",
    "sg:province":"PA",
    "sg:tags":[
        "house"
    ],
    "wof:name":"Pyramid Services",
    "wof:placetype":"venue"
},
  "geometry": {"coordinates":[-80.22149,42.051373],"type":"Point"}
}