{
  "type": "Feature",
  "properties": {
    "addr:full":"44 Roth Ave Mertztown PA 19539",
    "addr:housenumber":"44",
    "addr:postcode":"19539",
    "addr:street":"Roth Ave",
    "iso:country":"US",
    "sg:address":"44 Roth Ave",
    "sg:city":"Mertztown",
    "sg:classifiers":[
        {
            "category":"Building & Trades",
            "subcategory":"Construction",
            "type":"Services"
        }
    ],
    "sg:phone":"+1   ",
    "sg:postcode":"19539",
    "sg:province":"PA",
    "sg:tags":[
        "house"
    ],
    "wof:name":"T R Davis Construction",
    "wof:placetype":"venue"
},
  "geometry": {"coordinates":[-75.667042,40.514657],"type":"Point"}
}