{
  "type": "Feature",
  "properties": {
    "iso:country":"US",
    "sg:address":"1005 Broad St",
    "sg:city":"Perkasie",
    "sg:classifiers":[
        {
            "category":"Building & Trades",
            "subcategory":"Landscaping Services",
            "type":"Services"
        }
    ],
    "sg:phone":"+1 215 249 1819",
    "sg:postcode":"18944",
    "sg:province":"PA",
    "sg:tags":[
        "landscape",
        "contractor"
    ],
    "wof:name":"Bartlett Tree Experts",
    "wof:placetype":"venue"
},
  "geometry": {"coordinates":[-75.215558,40.339887],"type":"Point"}
}