{
  "type": "Feature",
  "properties": {
    "addr:full":"63 Whitewood Dr Levittown PA 19057",
    "addr:housenumber":"63",
    "addr:postcode":"19057",
    "addr:street":"Whitewood Dr",
    "iso:country":"US",
    "sg:address":"63 Whitewood Dr",
    "sg:city":"Levittown",
    "sg:classifiers":[
        {
            "category":"Building & Trades",
            "subcategory":"Construction",
            "type":"Services"
        }
    ],
    "sg:phone":"+1   ",
    "sg:postcode":"19057",
    "sg:province":"PA",
    "sg:tags":[
        "remodeling",
        "kitchen"
    ],
    "wof:name":"Renovative Creation Inc",
    "wof:placetype":"venue"
},
  "geometry": {"coordinates":[-74.861228,40.139574],"type":"Point"}
}