{
  "type": "Feature",
  "properties": {
    "addr:full":"411 Glen Arbor Ct King Of Prussia PA 19406",
    "addr:housenumber":"411",
    "addr:postcode":"19406",
    "addr:street":"Glen Arbor Ct",
    "iso:country":"US",
    "sg:address":"411 Glen Arbor Ct",
    "sg:city":"King Of Prussia",
    "sg:classifiers":[
        {
            "category":"Professional",
            "type":"Services"
        }
    ],
    "sg:phone":"+1   ",
    "sg:postcode":"19406",
    "sg:province":"PA",
    "wof:name":"Bs Motorsports LLC",
    "wof:placetype":"venue"
},
  "geometry": {"coordinates":[-75.369353,40.080252],"type":"Point"}
}