{
  "type": "Feature",
  "properties": {
    "iso:country":"US",
    "sg:address":"140 N 12th St",
    "sg:city":"Connellsville",
    "sg:classifiers":[
        {
            "category":"Utilities",
            "subcategory":"Fuel Oil & Lpg",
            "type":"Services"
        }
    ],
    "sg:phone":"+1   ",
    "sg:postcode":"15425",
    "sg:province":"PA",
    "sg:tags":[
        "dealer"
    ],
    "wof:name":"B C M Fuel Co",
    "wof:placetype":"venue"
},
  "geometry": {"coordinates":[-79.605677,40.014509],"type":"Point"}
}