{
  "type": "Feature",
  "properties": {
    "addr:full":"100 Plaza Dr Blandon PA 19510",
    "addr:housenumber":"100",
    "addr:postcode":"19510",
    "addr:street":"Plaza Dr Blandon",
    "iso:country":"US",
    "sg:address":"100 Plaza Dr",
    "sg:city":"Blandon",
    "sg:classifiers":[
        {
            "category":"Banks & Credit Unions",
            "subcategory":"Bank",
            "type":"Services"
        }
    ],
    "sg:phone":"+1 610 926 2111",
    "sg:postcode":"19510",
    "sg:province":"PA",
    "wof:name":"Leesport Bank",
    "wof:placetype":"venue"
},
  "geometry": {"coordinates":[-75.89141100000001,40.452888],"type":"Point"}
}