{
  "type": "Feature",
  "properties": {
    "iso:country":"US",
    "sg:address":"4936 Meadow Crest Dr",
    "sg:city":"Allison Park",
    "sg:classifiers":[
        {
            "category":"Building & Trades",
            "subcategory":"Construction",
            "type":"Services"
        }
    ],
    "sg:phone":"+1   ",
    "sg:postcode":"15101",
    "sg:province":"PA",
    "sg:tags":[
        "house"
    ],
    "wof:name":"Eric Gerber Construction",
    "wof:placetype":"venue"
},
  "geometry": {"coordinates":[-79.92063400000001,40.601966],"type":"Point"}
}