{
  "type": "Feature",
  "properties": {
    "addr:full":"272 S Main St Chambersburg PA 17201",
    "addr:housenumber":"272",
    "addr:postcode":"17201",
    "addr:street":"S Main St",
    "iso:country":"US",
    "sg:address":"272 S Main St",
    "sg:city":"Chambersburg",
    "sg:classifiers":[
        {
            "category":"Health Services",
            "subcategory":"Doctor",
            "type":"Services"
        }
    ],
    "sg:phone":"+1 717 264 5125",
    "sg:postcode":"17201",
    "sg:province":"PA",
    "sg:tags":[
        "clinic"
    ],
    "wof:name":"Adams Hanover Counseling Svc",
    "wof:placetype":"venue"
},
  "geometry": {"coordinates":[-77.662054,39.933348],"type":"Point"}
}