{
  "type": "Feature",
  "properties": {
    "iso:country":"US",
    "sg:address":"129 Kyle Dr",
    "sg:city":"Stroudsburg",
    "sg:classifiers":[
        {
            "category":"Professional",
            "subcategory":"Management & Consulting",
            "type":"Services"
        }
    ],
    "sg:phone":"+1   ",
    "sg:postcode":"18360",
    "sg:province":"PA",
    "wof:name":"Vistar Corporation",
    "wof:placetype":"venue"
},
  "geometry": {"coordinates":[-75.283484,40.968868],"type":"Point"}
}