{
  "type": "Feature",
  "properties": {
    "iso:country":"US",
    "sg:address":"107 W Main St",
    "sg:city":"Glen Lyon",
    "sg:classifiers":[
        {
            "category":"Professional",
            "subcategory":"Business Services",
            "type":"Services"
        }
    ],
    "sg:phone":"+1 570 736 6389",
    "sg:postcode":"18617",
    "sg:province":"PA",
    "sg:tags":[
        "paralegal"
    ],
    "wof:name":"Annee's Paralegal & Notary Svc",
    "wof:placetype":"venue"
},
  "geometry": {"coordinates":[-76.07628699999999,41.173685],"type":"Point"}
}