{
  "type": "Feature",
  "properties": {
    "addr:full":"298 Cashtown Rd Biglerville PA 17307",
    "addr:housenumber":"298",
    "addr:postcode":"17307",
    "addr:street":"Cashtown Rd",
    "iso:country":"US",
    "sg:address":"298 Cashtown Rd",
    "sg:city":"Biglerville",
    "sg:classifiers":[
        {
            "category":"Professional",
            "subcategory":"Business Services",
            "type":"Services"
        }
    ],
    "sg:phone":"+1 717 334 4486",
    "sg:postcode":"17307",
    "sg:province":"PA",
    "sg:tags":[
        "interior",
        "consultant",
        "design",
        "decorator"
    ],
    "wof:name":"Cindy Knouse",
    "wof:placetype":"venue"
},
  "geometry": {"coordinates":[-77.351252,39.900695],"type":"Point"}
}