{
  "type": "Feature",
  "properties": {
    "addr:full":"116 N Bonsall Ave Glenolden PA 19036",
    "addr:housenumber":"116",
    "addr:postcode":"19036",
    "addr:street":"N Bonsall Ave",
    "iso:country":"US",
    "sg:address":"116 N Bonsall Ave",
    "sg:city":"Glenolden",
    "sg:classifiers":[
        {
            "category":"Professional",
            "subcategory":"Management & Consulting",
            "type":"Services"
        }
    ],
    "sg:phone":"+1 610 745 4925",
    "sg:postcode":"19036",
    "sg:province":"PA",
    "sg:tags":[
        "consultant"
    ],
    "wof:name":"Johnson, M Multi Media Services Inc.",
    "wof:placetype":"venue"
},
  "geometry": {"coordinates":[-75.287898,39.904799],"type":"Point"}
}