{
  "type": "Feature",
  "properties": {
    "addr:full":"901 S 2nd St Sunbury PA 17801",
    "addr:housenumber":"901",
    "addr:postcode":"17801",
    "addr:street":"S 2Nd St",
    "iso:country":"US",
    "sg:address":"901 S 2nd St",
    "sg:city":"Sunbury",
    "sg:classifiers":[
        {
            "category":"Food & Beverages",
            "subcategory":"Bakery",
            "type":"Retail Goods"
        }
    ],
    "sg:phone":"+1 570 286 6400",
    "sg:postcode":"17801",
    "sg:province":"PA",
    "sg:tags":[
        "baker"
    ],
    "wof:name":"Grandma's Bakery",
    "wof:placetype":"venue"
},
  "geometry": {"coordinates":[-76.80034999999999,40.851634],"type":"Point"}
}