{
  "type": "Feature",
  "properties": {
    "iso:country":"US",
    "sg:address":"100 Leverington Ave",
    "sg:city":"Philadelphia",
    "sg:classifiers":[
        {
            "category":"Retail",
            "subcategory":"Veterinary Services",
            "type":"Services"
        }
    ],
    "sg:phone":"+1 215 509 6060",
    "sg:postcode":"19127",
    "sg:province":"PA",
    "sg:tags":[
        "clinic",
        "hospital",
        "veterinarian",
        "specialty"
    ],
    "sg:website":"http://www.caringforcatsphilly.com",
    "wof:name":"Caring For Cats",
    "wof:placetype":"venue"
},
  "geometry": {"coordinates":[-75.229156,40.029629],"type":"Point"}
}