{
  "type": "Feature",
  "properties": {
    "iso:country":"US",
    "sg:address":"1655 State Rte 130",
    "sg:city":"Greensburg",
    "sg:classifiers":[
        {
            "category":"Retail",
            "subcategory":"Auto Repair",
            "type":"Services"
        }
    ],
    "sg:phone":"+1 724 834 6670",
    "sg:postcode":"15601",
    "sg:province":"PA",
    "sg:tags":[
        "repairing",
        "automobile"
    ],
    "wof:name":"Danser's Auto Repair & Salvage",
    "wof:placetype":"venue"
},
  "geometry": {"coordinates":[-79.478453,40.258102],"type":"Point"}
}