{
  "type": "Feature",
  "properties": {
    "addr:full":"221 Electric Ave Lewistown PA 17044",
    "addr:housenumber":"221",
    "addr:postcode":"17044",
    "addr:street":"Electric Ave",
    "iso:country":"US",
    "sg:address":"221 Electric Ave",
    "sg:city":"Lewistown",
    "sg:classifiers":[
        {
            "category":"Restaurant",
            "type":"Food & Drink"
        }
    ],
    "sg:menulink":"http://www.allmenus.com/pa/derry/211270-kfc---kentucky-fried-chicken/menu/",
    "sg:phone":"+1 570 248 1391",
    "sg:postcode":"17044",
    "sg:province":"PA",
    "sg:tags":[
        "american",
        "chicken"
    ],
    "wof:name":"KFC - Kentucky Fried Chicken",
    "wof:placetype":"venue"
},
  "geometry": {"coordinates":[-77.568428,40.615518],"type":"Point"}
}