{
  "type": "Feature",
  "properties": {
    "iso:country":"US",
    "sg:address":"115 Rocks Rd",
    "sg:city":"Parker",
    "sg:classifiers":[
        {
            "category":"Wholesale",
            "subcategory":"Machinery & Supplies",
            "type":"Manufacturing & Wholesale Goods"
        }
    ],
    "sg:phone":"+1 724 753 2444",
    "sg:postcode":"16049",
    "sg:province":"PA",
    "sg:tags":[
        "down",
        "tie"
    ],
    "wof:name":"Master-Cord Corp",
    "wof:placetype":"venue"
},
  "geometry": {"coordinates":[-79.709896,41.059413],"type":"Point"}
}