{
  "type": "Feature",
  "properties": {
    "iso:country":"US",
    "sg:address":"29 Linden Ave",
    "sg:city":"Morton",
    "sg:classifiers":[
        {
            "category":"Building & Trades",
            "subcategory":"Landscaping Services",
            "type":"Services"
        }
    ],
    "sg:phone":"+1   ",
    "sg:postcode":"19070",
    "sg:province":"PA",
    "wof:name":"Hopson Landscapes",
    "wof:placetype":"venue"
},
  "geometry": {"coordinates":[-75.32745,39.903459],"type":"Point"}
}