{
  "type": "Feature",
  "properties": {
    "iso:country":"US",
    "sg:address":"4289 Middle Rd",
    "sg:city":"Allison Park",
    "sg:classifiers":[
        {
            "category":"Building & Trades",
            "subcategory":"Landscaping Services",
            "type":"Services"
        }
    ],
    "sg:phone":"+1 412 487 4103",
    "sg:postcode":"15101",
    "sg:province":"PA",
    "sg:tags":[
        "landscape",
        "contractor"
    ],
    "wof:name":"Gaskill Plantscaping",
    "wof:placetype":"venue"
},
  "geometry": {"coordinates":[-79.922179,40.583631],"type":"Point"}
}