{
  "type": "Feature",
  "properties": {
    "iso:country":"US",
    "sg:address":"4214 Fell Rd",
    "sg:city":"Doylestown",
    "sg:classifiers":[
        {
            "category":"Building & Trades",
            "subcategory":"Landscaping Services",
            "type":"Services"
        }
    ],
    "sg:phone":"+1 215 345 1693",
    "sg:postcode":"18902",
    "sg:province":"PA",
    "sg:tags":[
        "consultant",
        "designer",
        "landscape",
        "contractor"
    ],
    "wof:name":"Cipriano Landscaping Inc",
    "wof:placetype":"venue"
},
  "geometry": {"coordinates":[-75.101417,40.336321],"type":"Point"}
}