{
  "type": "Feature",
  "properties": {
    "iso:country":"US",
    "sg:address":"220 7th Ave",
    "sg:city":"Valencia",
    "sg:classifiers":[
        {
            "category":"Manufacturing",
            "subcategory":"Printing",
            "type":"Manufacturing & Wholesale Goods"
        }
    ],
    "sg:phone":"+1   ",
    "sg:postcode":"16059",
    "sg:province":"PA",
    "sg:tags":[
        "business",
        "form",
        "mfg"
    ],
    "wof:name":"Moore Business Comm Svcs",
    "wof:placetype":"venue"
},
  "geometry": {"coordinates":[-79.998351,40.681128],"type":"Point"}
}