{
  "type": "Feature",
  "properties": {
    "iso:country":"US",
    "sg:address":"3313 Gaul St",
    "sg:city":"Philadelphia",
    "sg:classifiers":[
        {
            "category":"Building & Trades",
            "subcategory":"Plumbing",
            "type":"Services"
        }
    ],
    "sg:phone":"+1 215 423 9780",
    "sg:postcode":"19134",
    "sg:province":"PA",
    "wof:name":"Hellas Co",
    "wof:placetype":"venue"
},
  "geometry": {"coordinates":[-75.101997,39.9888],"type":"Point"}
}