{
  "type": "Feature",
  "properties": {
    "addr:full":"28 N 3rd St Philadelphia PA 19106",
    "addr:housenumber":"28",
    "addr:postcode":"19106",
    "addr:street":"N 3Rd St",
    "iso:country":"US",
    "sg:address":"28 N 3rd St",
    "sg:city":"Philadelphia",
    "sg:classifiers":[
        {
            "category":"Recreation",
            "type":"Entertainment"
        }
    ],
    "sg:phone":"+1 215 627 3221",
    "sg:postcode":"19106",
    "sg:province":"PA",
    "sg:tags":[
        "carnival"
    ],
    "wof:name":"Fair Skies Sportswear",
    "wof:placetype":"venue"
},
  "geometry": {"coordinates":[-75.145713,39.950233],"type":"Point"}
}