{
  "type": "Feature",
  "properties": {
    "iso:country":"US",
    "sg:address":"Linden Rd",
    "sg:city":"Canonsburg",
    "sg:classifiers":[
        {
            "category":"Sports & Exercise",
            "subcategory":"Sports Center",
            "type":"Entertainment"
        },
        {
            "category":"Arena",
            "subcategory":"Sports Club",
            "type":"Entertainment"
        }
    ],
    "sg:phone":"+1 724 745 9794",
    "sg:postcode":"15317",
    "sg:province":"PA",
    "sg:tags":[
        "professional",
        "amateur",
        "team"
    ],
    "wof:name":"Dormont Mount Lebanon Sportsman Clup",
    "wof:placetype":"venue"
},
  "geometry": {"coordinates":[-80.160896,40.270802],"type":"Point"}
}