{
  "type": "Feature",
  "properties": {
    "iso:country":"US",
    "sg:address":"1430 Dekalb St",
    "sg:city":"Norristown",
    "sg:classifiers":[
        {
            "category":"Social Services",
            "type":"Services"
        }
    ],
    "sg:phone":"+1 610 270 0567",
    "sg:postcode":"19401",
    "sg:province":"PA",
    "sg:tags":[
        "counselor",
        "marriage",
        "family"
    ],
    "wof:name":"Family Center Norristown",
    "wof:placetype":"venue"
},
  "geometry": {"coordinates":[-75.332499,40.123919],"type":"Point"}
}