{
  "type": "Feature",
  "properties": {
    "iso:country":"US",
    "sg:address":"644 W 7th Ave",
    "sg:city":"Homestead",
    "sg:classifiers":[
        {
            "category":"Travel",
            "subcategory":"Hotels & Motels",
            "type":"Entertainment"
        }
    ],
    "sg:phone":"+1   ",
    "sg:postcode":"15120",
    "sg:province":"PA",
    "sg:tags":[
        "operation"
    ],
    "wof:name":"Hotel Parry",
    "wof:placetype":"venue"
},
  "geometry": {"coordinates":[-79.92210300000001,40.398881],"type":"Point"}
}