{
  "type": "Feature",
  "properties": {
    "iso:country":"US",
    "sg:address":"677 Heacock Rd",
    "sg:city":"Yardley",
    "sg:classifiers":[
        {
            "category":"Restaurant",
            "type":"Food & Drink"
        }
    ],
    "sg:phone":"+1 215 493 1818",
    "sg:postcode":"19067",
    "sg:province":"PA",
    "sg:tags":[
        "asian",
        "chinese",
        "pan"
    ],
    "wof:name":"Gold Fountain Chinese",
    "wof:placetype":"venue"
},
  "geometry": {"coordinates":[-74.87051200000001,40.220437],"type":"Point"}
}