{
  "type": "Feature",
  "properties": {
    "addr:full":"526 E Bruceton Rd Pittsburgh PA 15236",
    "addr:housenumber":"526",
    "addr:postcode":"15236",
    "addr:street":"E Bruceton Rd",
    "iso:country":"US",
    "sg:address":"526 E Bruceton Rd",
    "sg:city":"Pittsburgh",
    "sg:classifiers":[
        {
            "category":"Personal",
            "subcategory":"Beauty Salon",
            "type":"Services"
        }
    ],
    "sg:phone":"+1 412 650 9940",
    "sg:postcode":"15236",
    "sg:province":"PA",
    "sg:tags":[
        "shop"
    ],
    "wof:name":"Expressions",
    "wof:placetype":"venue"
},
  "geometry": {"coordinates":[-79.947761,40.328791],"type":"Point"}
}