{
  "type": "Feature",
  "properties": {
    "iso:country":"US",
    "sg:address":"6341 Rising Sun Ave",
    "sg:city":"Philadelphia",
    "sg:classifiers":[
        {
            "category":"Wholesale",
            "subcategory":"Medical Equipment & Supplies",
            "type":"Manufacturing & Wholesale Goods"
        }
    ],
    "sg:phone":"+1 215 725 8861",
    "sg:postcode":"19111",
    "sg:province":"PA",
    "sg:tags":[
        "hospital"
    ],
    "wof:name":"Medical Equipment Svc Unltd",
    "wof:placetype":"venue"
},
  "geometry": {"coordinates":[-75.095938,40.049033],"type":"Point"}
}