{
  "type": "Feature",
  "properties": {
    "iso:country":"US",
    "sg:address":"1207 Ridge Ave",
    "sg:city":"Ephrata",
    "sg:classifiers":[
        {
            "category":"Building & Trades",
            "subcategory":"Plumbing",
            "type":"Services"
        }
    ],
    "sg:phone":"+1 717 335 3130",
    "sg:postcode":"17522",
    "sg:province":"PA",
    "sg:tags":[
        "plumbing",
        "contractor"
    ],
    "wof:name":"Bosley Plumbing Inc",
    "wof:placetype":"venue"
},
  "geometry": {"coordinates":[-76.119893,40.204346],"type":"Point"}
}