{
  "type": "Feature",
  "properties": {
    "addr:full":"1012 Evans St Mckeesport PA 15132",
    "addr:housenumber":"1012",
    "addr:postcode":"15132",
    "addr:street":"Evans St",
    "iso:country":"US",
    "sg:address":"1012 Evans St",
    "sg:city":"Mckeesport",
    "sg:classifiers":[
        {
            "category":"Bars & Pubs",
            "type":"Food & Drink"
        }
    ],
    "sg:phone":"+1 412 664 0257",
    "sg:postcode":"15132",
    "sg:province":"PA",
    "wof:name":"Stanko's Evans Ave Grill",
    "wof:placetype":"venue"
},
  "geometry": {"coordinates":[-79.84944299999999,40.346714],"type":"Point"}
}