{
  "type": "Feature",
  "properties": {
    "iso:country":"US",
    "sg:address":"6000 Monongahela Ave",
    "sg:city":"Bethel Park",
    "sg:classifiers":[
        {
            "category":"Manufacturing",
            "subcategory":"Retail Goods",
            "type":"Manufacturing & Wholesale Goods"
        }
    ],
    "sg:phone":"+1   ",
    "sg:postcode":"15102",
    "sg:province":"PA",
    "sg:tags":[
        "product",
        "mfg"
    ],
    "wof:name":"Candles By Amy V",
    "wof:placetype":"venue"
},
  "geometry": {"coordinates":[-80.045207,40.313445],"type":"Point"}
}