{
  "type": "Feature",
  "properties": {
    "iso:country":"US",
    "sg:address":"938 S 11th St",
    "sg:city":"Allentown",
    "sg:classifiers":[
        {
            "category":"Organizations",
            "subcategory":"Religious Organization",
            "type":"Services"
        }
    ],
    "sg:phone":"+1 610 434 1380",
    "sg:postcode":"18103",
    "sg:province":"PA",
    "sg:tags":[
        "church"
    ],
    "sg:website":"www.allentownnazarene.org",
    "wof:name":"First Church Of The Nazarene",
    "wof:placetype":"venue"
},
  "geometry": {"coordinates":[-75.476168,40.589508],"type":"Point"}
}