{
  "type": "Feature",
  "properties": {
    "iso:country":"US",
    "sg:address":"247 River St",
    "sg:city":"Kingston",
    "sg:classifiers":[
        {
            "category":"Building & Trades",
            "subcategory":"Electrical",
            "type":"Services"
        }
    ],
    "sg:phone":"+1 570 331 2039",
    "sg:postcode":"18704",
    "sg:province":"PA",
    "sg:tags":[
        "electric",
        "contractor"
    ],
    "wof:name":"Vally Industries Inc",
    "wof:placetype":"venue"
},
  "geometry": {"coordinates":[-75.87206399999999,41.277415],"type":"Point"}
}