{
  "type": "Feature",
  "properties": {
    "iso:country":"US",
    "sg:address":"127 S Main St",
    "sg:city":"Dublin",
    "sg:classifiers":[
        {
            "category":"Farming",
            "subcategory":"Farm",
            "type":"Manufacturing & Wholesale Goods"
        }
    ],
    "sg:phone":"+1   ",
    "sg:postcode":"18917",
    "sg:province":"PA",
    "sg:tags":[
        "crop",
        "general"
    ],
    "wof:name":"Dennis Derstine",
    "wof:placetype":"venue"
},
  "geometry": {"coordinates":[-75.20092699999999,40.37068],"type":"Point"}
}