{
  "type": "Feature",
  "properties": {
    "addr:full":"700 Park Way Broomall PA 19008",
    "addr:housenumber":"700",
    "addr:postcode":"19008",
    "addr:street":"Park Way",
    "iso:country":"US",
    "sg:address":"700 Park Way",
    "sg:city":"Broomall",
    "sg:classifiers":[
        {
            "category":"Retail",
            "subcategory":"Repair Shop",
            "type":"Services"
        }
    ],
    "sg:phone":"+1 610 353 2400",
    "sg:postcode":"19008",
    "sg:province":"PA",
    "sg:tags":[
        "equipment",
        "consumer",
        "instrument",
        "professional",
        "audio",
        "electronic",
        "musical"
    ],
    "sg:website":"www.prodigitalinc.com",
    "wof:name":"Pro Digital Inc",
    "wof:placetype":"venue"
},
  "geometry": {"coordinates":[-75.336561,39.96167],"type":"Point"}
}