{
  "type": "Feature",
  "properties": {
    "addr:full":"723 Glenwood St Emmaus PA 18049",
    "addr:housenumber":"723",
    "addr:postcode":"18049",
    "addr:street":"Glenwood St",
    "iso:country":"US",
    "sg:address":"723 Glenwood St",
    "sg:city":"Emmaus",
    "sg:classifiers":[
        {
            "category":"Professional",
            "subcategory":"Computer Services",
            "type":"Services"
        }
    ],
    "sg:phone":"+1   ",
    "sg:postcode":"18049",
    "sg:province":"PA",
    "sg:tags":[
        "production",
        "software"
    ],
    "wof:name":"Star-Byte Inc",
    "wof:placetype":"venue"
},
  "geometry": {"coordinates":[-75.481398,40.552316],"type":"Point"}
}