{
  "type": "Feature",
  "properties": {
    "iso:country":"US",
    "sg:address":"3217 Willits Rd",
    "sg:city":"Philadelphia",
    "sg:classifiers":[
        {
            "category":"Restaurant",
            "type":"Food & Drink"
        }
    ],
    "sg:phone":"+1   ",
    "sg:postcode":"19114",
    "sg:province":"PA",
    "sg:tags":[
        "eating"
    ],
    "wof:name":"Chens Chinese Restaurant",
    "wof:placetype":"venue"
},
  "geometry": {"coordinates":[-75.013138,40.056628],"type":"Point"}
}