{
  "type": "Feature",
  "properties": {
    "addr:full":"201 W Allegheny Ave Philadelphia PA 19133",
    "addr:housenumber":"201",
    "addr:postcode":"19133",
    "addr:street":"W Allegheny Ave",
    "iso:country":"US",
    "sg:address":"201 W Allegheny Ave",
    "sg:city":"Philadelphia",
    "sg:classifiers":[
        {
            "category":"Restaurant",
            "type":"Food & Drink"
        }
    ],
    "sg:phone":"+1 215 634 3889",
    "sg:postcode":"19133",
    "sg:province":"PA",
    "sg:tags":[
        "specializing",
        "cuisine",
        "spanish"
    ],
    "wof:name":"Freddy & Tony's Restaurant",
    "wof:placetype":"venue"
},
  "geometry": {"coordinates":[-75.13325500000001,39.999258],"type":"Point"}
}