{
  "type": "Feature",
  "properties": {
    "iso:country":"US",
    "sg:address":"931 Loucks Rd",
    "sg:city":"York",
    "sg:classifiers":[
        {
            "category":"Restaurant",
            "type":"Food & Drink"
        }
    ],
    "sg:phone":"+1 717 845 8138",
    "sg:postcode":"17404",
    "sg:province":"PA",
    "sg:tags":[
        "buffet",
        "asian",
        "chinese",
        "pan"
    ],
    "wof:name":"A Won China Buffet",
    "wof:placetype":"venue"
},
  "geometry": {"coordinates":[-76.754124,39.979645],"type":"Point"}
}