{
  "type": "Feature",
  "properties": {
    "iso:country":"US",
    "sg:address":"972 Newswanger Rd",
    "sg:city":"Ephrata",
    "sg:classifiers":[
        {
            "category":"Retail",
            "subcategory":"Auto Repair",
            "type":"Services"
        }
    ],
    "sg:phone":"+1 717 354 2732",
    "sg:postcode":"17522",
    "sg:province":"PA",
    "wof:name":"Nolt Wagon Works",
    "wof:placetype":"venue"
},
  "geometry": {"coordinates":[-76.116921,40.158055],"type":"Point"}
}