{
  "type": "Feature",
  "properties": {
    "iso:country":"US",
    "sg:address":"2198 S Main St",
    "sg:city":"Mansfield",
    "sg:classifiers":[
        {
            "category":"Retail",
            "subcategory":"Repair Shop",
            "type":"Services"
        }
    ],
    "sg:phone":"+1 570 662 1083",
    "sg:postcode":"16933",
    "sg:province":"PA",
    "sg:tags":[
        "scooter",
        "motorcycle",
        "motor"
    ],
    "wof:name":"S & K Motorsports",
    "wof:placetype":"venue"
},
  "geometry": {"coordinates":[-77.080055,41.762132],"type":"Point"}
}