{
  "type": "Feature",
  "properties": {
    "iso:country":"US",
    "sg:address":"32 W King St",
    "sg:city":"Malvern",
    "sg:classifiers":[
        {
            "category":"Health Services",
            "subcategory":"Doctor",
            "type":"Services"
        },
        {
            "category":"Health Services",
            "subcategory":"Health Practitioner",
            "type":"Services"
        }
    ],
    "sg:phone":"+1 610 644 1879",
    "sg:postcode":"19355",
    "sg:province":"PA",
    "sg:tags":[
        "physician",
        "ophthalmology",
        "surgeons",
        "surgeon"
    ],
    "wof:name":"Eugene L Kane Dr Od",
    "wof:placetype":"venue"
},
  "geometry": {"coordinates":[-75.515005,40.035775],"type":"Point"}
}