{
  "type": "Feature",
  "properties": {
    "addr:full":"5100 Liberty Ave Pittsburgh PA 15224",
    "addr:housenumber":"5100",
    "addr:postcode":"15224",
    "addr:street":"Liberty Ave",
    "iso:country":"US",
    "sg:address":"5100 Liberty Ave",
    "sg:city":"Pittsburgh",
    "sg:classifiers":[
        {
            "category":"Recreation",
            "type":"Entertainment"
        }
    ],
    "sg:phone":"+1 412 621 9111",
    "sg:postcode":"15224",
    "sg:province":"PA",
    "sg:tags":[
        "karate",
        "judo",
        "instr"
    ],
    "wof:name":"C S Kim Karate Inc",
    "wof:placetype":"venue"
},
  "geometry": {"coordinates":[-79.942792,40.45831],"type":"Point"}
}