{
  "type": "Feature",
  "properties": {
    "iso:country":"US",
    "sg:address":"156 Turgeon Rd",
    "sg:city":"Sidman",
    "sg:classifiers":[
        {
            "category":"Social Services",
            "subcategory":"Child Care",
            "type":"Services"
        }
    ],
    "sg:phone":"+1 814 495 7383",
    "sg:postcode":"15955",
    "sg:province":"PA",
    "wof:name":"Owl Watchem Daycare",
    "wof:placetype":"venue"
},
  "geometry": {"coordinates":[-78.74100199999999,40.347117],"type":"Point"}
}