{
  "type": "Feature",
  "properties": {
    "iso:country":"US",
    "sg:address":"126 Queen Junction Rd",
    "sg:city":"Butler",
    "sg:classifiers":[
        {
            "category":"Building & Trades",
            "subcategory":"Construction",
            "type":"Services"
        }
    ],
    "sg:phone":"+1   ",
    "sg:postcode":"16001",
    "sg:province":"PA",
    "wof:name":"Complete Custom Contracti",
    "wof:placetype":"venue"
},
  "geometry": {"coordinates":[-79.927218,40.971359],"type":"Point"}
}