{
  "type": "Feature",
  "properties": {
    "iso:country":"US",
    "sg:address":"1353 N Chester Rd",
    "sg:city":"West Chester",
    "sg:classifiers":[
        {
            "category":"Retail",
            "subcategory":"Veterinary Services",
            "type":"Services"
        }
    ],
    "sg:phone":"+1 610 692 7560",
    "sg:postcode":"19355",
    "sg:province":"PA",
    "sg:tags":[
        "veterinarian"
    ],
    "wof:name":"Animal Hospital-Chester County",
    "wof:placetype":"venue"
},
  "geometry": {"coordinates":[-75.547973,40.020354],"type":"Point"}
}