{
  "type": "Feature",
  "properties": {
    "iso:country":"US",
    "sg:address":"420 US Hwy 6",
    "sg:city":"Coudersport",
    "sg:classifiers":[
        {
            "category":"Education",
            "subcategory":"School",
            "type":"Public Place"
        }
    ],
    "sg:phone":"+1 814 274 1104",
    "sg:postcode":"16915",
    "sg:province":"PA",
    "sg:website":"www.iu9.org",
    "wof:name":"Seneca Highlands Intermediate",
    "wof:placetype":"venue"
},
  "geometry": {"coordinates":[-78.003956,41.774947],"type":"Point"}
}