{
  "type": "Feature",
  "properties": {
    "addr:full":"8 Entrance Dr Johnstown PA 15905",
    "addr:postcode":"15905",
    "addr:street":"Entrance Dr",
    "iso:country":"US",
    "sg:address":"8 Entrance Dr",
    "sg:city":"Johnstown",
    "sg:classifiers":[
        {
            "category":"Professional",
            "subcategory":"Accounting & Tax Preparation",
            "type":"Services"
        }
    ],
    "sg:phone":"+1 814 255 6512",
    "sg:postcode":"15905",
    "sg:province":"PA",
    "sg:tags":[
        "accountant"
    ],
    "wof:name":"Hamonko Stasko & Co CPA",
    "wof:placetype":"venue"
},
  "geometry": {"coordinates":[-78.956052,40.321537],"type":"Point"}
}