{
  "type": "Feature",
  "properties": {
    "iso:country":"US",
    "sg:address":"1439 Wyoming Ave",
    "sg:city":"Scranton",
    "sg:classifiers":[
        {
            "category":"Health Services",
            "subcategory":"Doctor",
            "type":"Services"
        }
    ],
    "sg:phone":"+1   ",
    "sg:postcode":"18509",
    "sg:province":"PA",
    "wof:name":"Howard Wimmer DDS",
    "wof:placetype":"venue"
},
  "geometry": {"coordinates":[-75.648106,41.424448],"type":"Point"}
}