{
  "type": "Feature",
  "properties": {
    "iso:country":"US",
    "sg:address":"430 N Enola Dr",
    "sg:city":"Enola",
    "sg:classifiers":[
        {
            "category":"Professional",
            "subcategory":"Accounting & Tax Preparation",
            "type":"Services"
        }
    ],
    "sg:phone":"+1 717 732 2331",
    "sg:postcode":"17025",
    "sg:province":"PA",
    "sg:tags":[
        "accountant"
    ],
    "wof:name":"Flannery Martin J Acctnt",
    "wof:placetype":"venue"
},
  "geometry": {"coordinates":[-76.9366,40.298599],"type":"Point"}
}