{
  "type": "Feature",
  "properties": {
    "addr:full":"2832 Lititz Pike Lancaster PA 17601",
    "addr:housenumber":"2832",
    "addr:postcode":"17601",
    "addr:street":"Lititz Pike",
    "iso:country":"US",
    "sg:address":"2832 Lititz Pike",
    "sg:city":"Lancaster",
    "sg:classifiers":[
        {
            "category":"Personal",
            "subcategory":"Beauty Salon",
            "type":"Services"
        }
    ],
    "sg:phone":"+1   ",
    "sg:postcode":"17601",
    "sg:province":"PA",
    "sg:tags":[
        "shop"
    ],
    "wof:name":"Pamela Js Hair Nail Tan Salon",
    "wof:placetype":"venue"
},
  "geometry": {"coordinates":[-76.30549600000001,40.104649],"type":"Point"}
}