{
  "type": "Feature",
  "properties": {
    "iso:country":"US",
    "sg:address":"1120 Wisteria Dr",
    "sg:city":"Malvern",
    "sg:classifiers":[
        {
            "category":"Professional",
            "subcategory":"Employment Agencies",
            "type":"Services"
        }
    ],
    "sg:phone":"+1   ",
    "sg:postcode":"19355",
    "sg:province":"PA",
    "sg:tags":[
        "executive",
        "coaching",
        "management",
        "placement",
        "consulting"
    ],
    "wof:name":"Professional Search Associates",
    "wof:placetype":"venue"
},
  "geometry": {"coordinates":[-75.503927,40.065754],"type":"Point"}
}