{
  "type": "Feature",
  "properties": {
    "iso:country":"US",
    "sg:address":"7059 Linglestown Rd",
    "sg:city":"Harrisburg",
    "sg:classifiers":[
        {
            "category":"Building & Trades",
            "subcategory":"Plumbing",
            "type":"Services"
        }
    ],
    "sg:phone":"+1 717 545 9387",
    "sg:postcode":"17112",
    "sg:province":"PA",
    "sg:tags":[
        "conditioning",
        "air",
        "system",
        "contractor"
    ],
    "wof:name":"Moad Services",
    "wof:placetype":"venue"
},
  "geometry": {"coordinates":[-76.760259,40.35264],"type":"Point"}
}