{
  "type": "Feature",
  "properties": {
    "iso:country":"US",
    "sg:address":"2100 Corporate Dr",
    "sg:city":"Wexford",
    "sg:classifiers":[
        {
            "category":"Banks & Credit Unions",
            "subcategory":"Bank",
            "type":"Services"
        }
    ],
    "sg:phone":"+1   ",
    "sg:postcode":"15090",
    "sg:province":"PA",
    "sg:tags":[
        "broker",
        "mortgage"
    ],
    "wof:name":"Uft Mortgage",
    "wof:placetype":"venue"
},
  "geometry": {"coordinates":[-80.088364,40.612805],"type":"Point"}
}