{
  "type": "Feature",
  "properties": {
    "iso:country":"US",
    "sg:address":"17 Montrose St",
    "sg:city":"New Milford",
    "sg:classifiers":[
        {
            "category":"Government",
            "subcategory":"Office",
            "type":"Public Place"
        }
    ],
    "sg:phone":"+1 570 465 3394",
    "sg:postcode":"18834",
    "sg:province":"PA",
    "sg:tags":[
        "village"
    ],
    "wof:name":"New Milford Borough Garage",
    "wof:placetype":"venue"
},
  "geometry": {"coordinates":[-75.72877,41.87216],"type":"Point"}
}