{
  "type": "Feature",
  "properties": {
    "iso:country":"US",
    "sg:address":"3916 Church Rd",
    "sg:city":"Chambersburg",
    "sg:classifiers":[
        {
            "category":"Professional",
            "subcategory":"Management & Consulting",
            "type":"Services"
        }
    ],
    "sg:phone":"+1 717 729 0266",
    "sg:postcode":"17202",
    "sg:province":"PA",
    "sg:tags":[
        "consultant"
    ],
    "wof:name":"Usa Calibrations",
    "wof:placetype":"venue"
},
  "geometry": {"coordinates":[-77.62258799999999,39.86406],"type":"Point"}
}