{
  "type": "Feature",
  "properties": {
    "iso:country":"US",
    "sg:address":"149 Meadow Brook Dr",
    "sg:city":"Montgomery",
    "sg:classifiers":[
        {
            "category":"Building & Trades",
            "subcategory":"Plumbing",
            "type":"Services"
        }
    ],
    "sg:phone":"+1 570 547 1195",
    "sg:postcode":"17752",
    "sg:province":"PA",
    "sg:tags":[
        "plumbing",
        "contractor"
    ],
    "wof:name":"O'Connor Plumbing & Heating",
    "wof:placetype":"venue"
},
  "geometry": {"coordinates":[-76.97709,41.164188],"type":"Point"}
}