{
  "type": "Feature",
  "properties": {
    "iso:country":"US",
    "sg:address":"4174 Mallory Rd",
    "sg:city":"Cochranton",
    "sg:classifiers":[
        {
            "category":"Building & Trades",
            "subcategory":"Construction",
            "type":"Services"
        }
    ],
    "sg:phone":"+1   ",
    "sg:postcode":"16314",
    "sg:province":"PA",
    "sg:tags":[
        "house"
    ],
    "wof:name":"Whitlock Construction",
    "wof:placetype":"venue"
},
  "geometry": {"coordinates":[-80.138054,41.514797],"type":"Point"}
}