{
  "type": "Feature",
  "properties": {
    "iso:country":"US",
    "sg:address":"1059 Columbus Ave",
    "sg:city":"Lemoyne",
    "sg:classifiers":[
        {
            "category":"Building & Trades",
            "subcategory":"Construction",
            "type":"Services"
        }
    ],
    "sg:phone":"+1 717 737 4821",
    "sg:postcode":"17043",
    "sg:province":"PA",
    "sg:tags":[
        "refinishing",
        "floor",
        "covering",
        "laying",
        "contractor",
        "resurfacing"
    ],
    "wof:name":"Scheller Hardwood Floors Inc",
    "wof:placetype":"venue"
},
  "geometry": {"coordinates":[-76.89756300000001,40.235582],"type":"Point"}
}