{
  "type": "Feature",
  "properties": {
    "iso:country":"US",
    "sg:address":"357 Regis Ave",
    "sg:city":"Pleasant Hills",
    "sg:classifiers":[
        {
            "category":"Health Services",
            "subcategory":"Doctor",
            "type":"Services"
        }
    ],
    "sg:phone":"+1 412 655 4114",
    "sg:postcode":"15236",
    "sg:province":"PA",
    "sg:tags":[
        "dentist"
    ],
    "wof:name":"Lester F Qualk DDS",
    "wof:placetype":"venue"
},
  "geometry": {"coordinates":[-79.955834,40.340542],"type":"Point"}
}