{
  "type": "Feature",
  "properties": {
    "iso:country":"US",
    "sg:address":"621 Valley Forge Rd",
    "sg:city":"Phoenixville",
    "sg:classifiers":[
        {
            "category":"Health Services",
            "subcategory":"Optometrist",
            "type":"Services"
        }
    ],
    "sg:phone":"+1   ",
    "sg:postcode":"19460",
    "sg:province":"PA",
    "wof:name":"Rawdin Martin",
    "wof:placetype":"venue"
},
  "geometry": {"coordinates":[-75.50561,40.120852],"type":"Point"}
}