{
  "type": "Feature",
  "properties": {
    "iso:country":"US",
    "sg:address":"18 S 4th St",
    "sg:city":"Reading",
    "sg:classifiers":[
        {
            "category":"Personal",
            "subcategory":"Barber",
            "type":"Services"
        }
    ],
    "sg:phone":"+1 610 376 1813",
    "sg:postcode":"19602",
    "sg:province":"PA",
    "wof:name":"Gentlemen's Quarters Barber",
    "wof:placetype":"venue"
},
  "geometry": {"coordinates":[-75.929928,40.335099],"type":"Point"}
}