{
  "type": "Feature",
  "properties": {
    "addr:full":"104 S Blakely St Dunmore PA 18512",
    "addr:housenumber":"104",
    "addr:postcode":"18512",
    "addr:street":"S Blakely St",
    "iso:country":"US",
    "sg:address":"104 S Blakely St",
    "sg:city":"Dunmore",
    "sg:classifiers":[
        {
            "category":"Professional",
            "subcategory":"Accounting & Tax Preparation",
            "type":"Services"
        }
    ],
    "sg:phone":"+1 570 341 9131",
    "sg:postcode":"18512",
    "sg:province":"PA",
    "sg:tags":[
        "return",
        "filing"
    ],
    "wof:name":"Jackson Hewitt Tax Svc",
    "wof:placetype":"venue"
},
  "geometry": {"coordinates":[-75.63127299999999,41.421062],"type":"Point"}
}