{
  "type": "Feature",
  "properties": {
    "iso:country":"US",
    "sg:address":"710 Washington Rd",
    "sg:city":"Pittsburgh",
    "sg:classifiers":[
        {
            "category":"Government",
            "subcategory":"Office",
            "type":"Public Place"
        }
    ],
    "sg:phone":"+1 412 343 7889",
    "sg:postcode":"15228",
    "sg:province":"PA",
    "sg:tags":[
        "village"
    ],
    "wof:name":"Dormont Boro Ambulance",
    "wof:placetype":"venue"
},
  "geometry": {"coordinates":[-80.045345,40.379345],"type":"Point"}
}