{
  "type": "Feature",
  "properties": {
    "iso:country":"US",
    "sg:address":"4700 Wissahickon Ave",
    "sg:city":"Philadelphia",
    "sg:classifiers":[
        {
            "category":"Local Transit",
            "type":"Transportation"
        }
    ],
    "sg:phone":"+1 215 844 3390",
    "sg:postcode":"19144",
    "sg:province":"PA",
    "sg:tags":[
        "ambulance"
    ],
    "wof:name":"East Falls Ambulance Svc",
    "wof:placetype":"venue"
},
  "geometry": {"coordinates":[-75.17124800000001,40.016415],"type":"Point"}
}