{
  "type": "Feature",
  "properties": {
    "addr:full":"1116 Bell Ave Braddock PA 15104",
    "addr:housenumber":"1116",
    "addr:postcode":"15104",
    "addr:street":"Bell Ave",
    "iso:country":"US",
    "sg:address":"1116 Bell Ave",
    "sg:city":"Braddock",
    "sg:classifiers":[
        {
            "category":"Food & Beverages",
            "subcategory":"Groceries & Convenience Stores",
            "type":"Retail Goods"
        }
    ],
    "sg:phone":"+1 412 271 4883",
    "sg:postcode":"15104",
    "sg:province":"PA",
    "sg:tags":[
        "grocer"
    ],
    "wof:name":"Dee's Market",
    "wof:placetype":"venue"
},
  "geometry": {"coordinates":[-79.86001,40.401271],"type":"Point"}
}