{
  "type": "Feature",
  "properties": {
    "addr:full":"1900 Washington Rd Ste 369 Pittsburgh PA 15241",
    "addr:housenumber":"1900",
    "addr:postcode":"15241",
    "addr:street":"Washington Rd Ste 369",
    "iso:country":"US",
    "sg:address":"1900 Washington Rd Ste 369",
    "sg:city":"Pittsburgh",
    "sg:classifiers":[
        {
            "category":"Shopping",
            "subcategory":"Clothing, Apparel, & Fashions",
            "type":"Retail Goods"
        }
    ],
    "sg:phone":"+1 412 851 7201",
    "sg:postcode":"15241",
    "sg:province":"PA",
    "sg:tags":[
        "accessory",
        "clothing",
        "women's"
    ],
    "sg:website":"www.christopherandbanks.com",
    "wof:name":"Christopher & Banks",
    "wof:placetype":"venue"
},
  "geometry": {"coordinates":[-80.059905,40.343965],"type":"Point"}
}