{
  "type": "Feature",
  "properties": {
    "addr:full":"2511 S Broad St Philadelphia PA 19148",
    "addr:housenumber":"2511",
    "addr:postcode":"19148",
    "addr:street":"S Broad St",
    "iso:country":"US",
    "sg:address":"2511 S Broad St",
    "sg:city":"Philadelphia",
    "sg:classifiers":[
        {
            "category":"Health Services",
            "subcategory":"Doctor",
            "type":"Services"
        }
    ],
    "sg:phone":"+1 215 467 3883",
    "sg:postcode":"19148",
    "sg:province":"PA",
    "wof:name":"Codario Ronald A MD",
    "wof:placetype":"venue"
},
  "geometry": {"coordinates":[-75.1707,39.919102],"type":"Point"}
}