{
  "type": "Feature",
  "properties": {
    "addr:full":"1511 Filmore Ave Erie PA 16505",
    "addr:housenumber":"1511",
    "addr:postcode":"16505",
    "addr:street":"Filmore Ave",
    "iso:country":"US",
    "sg:address":"1511 Filmore Ave",
    "sg:city":"Erie",
    "sg:classifiers":[
        {
            "category":"Building & Trades",
            "subcategory":"Construction",
            "type":"Services"
        }
    ],
    "sg:phone":"+1   ",
    "sg:postcode":"16505",
    "sg:province":"PA",
    "sg:tags":[
        "tile",
        "ceramic",
        "contractor"
    ],
    "wof:name":"Lander John Crmic Tile & Crpt",
    "wof:placetype":"venue"
},
  "geometry": {"coordinates":[-80.140573,42.097525],"type":"Point"}
}