{
  "type": "Feature",
  "properties": {
    "iso:country":"US",
    "sg:address":"407 Rte 940",
    "sg:city":"Mt Pocono",
    "sg:classifiers":[
        {
            "category":"Retail",
            "subcategory":"Auto Repair",
            "type":"Services"
        }
    ],
    "sg:phone":"+1 570 895 4117",
    "sg:postcode":"18344",
    "sg:province":"PA",
    "sg:tags":[
        "automobile",
        "inspection"
    ],
    "wof:name":"Speed Zone",
    "wof:placetype":"venue"
},
  "geometry": {"coordinates":[-75.343665,41.127145],"type":"Point"}
}