{
  "type": "Feature",
  "properties": {
    "iso:country":"US",
    "sg:address":"1721 Sunnyside Hollow Rd",
    "sg:city":"Port Matilda",
    "sg:classifiers":[
        {
            "category":"Shopping",
            "subcategory":"Catalog Store",
            "type":"Retail Goods"
        }
    ],
    "sg:phone":"+1   ",
    "sg:postcode":"16870",
    "sg:province":"PA",
    "sg:tags":[
        "mail",
        "house"
    ],
    "wof:name":"Deitrich Merchandise Warehouse",
    "wof:placetype":"venue"
},
  "geometry": {"coordinates":[-78.05561,40.827935],"type":"Point"}
}