{
  "type": "Feature",
  "properties": {
    "iso:country":"US",
    "sg:address":"1401 Maple Dr",
    "sg:city":"Pittsburgh",
    "sg:classifiers":[
        {
            "category":"Shopping",
            "subcategory":"Musical Instruments",
            "type":"Retail Goods"
        }
    ],
    "sg:phone":"+1   ",
    "sg:postcode":"15227",
    "sg:province":"PA",
    "wof:name":"Guitar Teacher",
    "wof:placetype":"venue"
},
  "geometry": {"coordinates":[-79.96473,40.364529],"type":"Point"}
}