{
  "type": "Feature",
  "properties": {
    "iso:country":"US",
    "sg:address":"3905 State Rd",
    "sg:city":"Drexel Hill",
    "sg:classifiers":[
        {
            "category":"Restaurant",
            "type":"Food & Drink"
        }
    ],
    "sg:phone":"+1   ",
    "sg:postcode":"19026",
    "sg:province":"PA",
    "sg:tags":[
        "deli"
    ],
    "wof:name":"ZS Deli",
    "wof:placetype":"venue"
},
  "geometry": {"coordinates":[-75.305637,39.952768],"type":"Point"}
}