{
  "type": "Feature",
  "properties": {
    "iso:country":"US",
    "sg:address":"4655 Linglestown Rd",
    "sg:city":"Harrisburg",
    "sg:classifiers":[
        {
            "category":"Health Services",
            "subcategory":"Doctor",
            "type":"Services"
        }
    ],
    "sg:phone":"+1   ",
    "sg:postcode":"17112",
    "sg:province":"PA",
    "wof:name":"Aves Wslder Katz Mutschler DDS",
    "wof:placetype":"venue"
},
  "geometry": {"coordinates":[-76.81622299999999,40.336836],"type":"Point"}
}