{
  "type": "Feature",
  "properties": {
    "iso:country":"US",
    "sg:address":"2175 Oregon Pike",
    "sg:city":"Lancaster",
    "sg:classifiers":[
        {
            "category":"Health Services",
            "subcategory":"Doctor",
            "type":"Services"
        }
    ],
    "sg:phone":"+1   ",
    "sg:postcode":"17601",
    "sg:province":"PA",
    "wof:name":"M George PC",
    "wof:placetype":"venue"
},
  "geometry": {"coordinates":[-76.290671,40.082911],"type":"Point"}
}