{
  "type": "Feature",
  "properties": {
    "iso:country":"US",
    "sg:address":"1934 Park Manor Blvd",
    "sg:city":"Pittsburgh",
    "sg:classifiers":[
        {
            "category":"Shopping",
            "type":"Retail Goods"
        }
    ],
    "sg:phone":"+1 412 788 6778",
    "sg:postcode":"15205",
    "sg:province":"PA",
    "sg:tags":[
        "orthopedic",
        "appliance"
    ],
    "wof:name":"Delatorre Orthotics",
    "wof:placetype":"venue"
},
  "geometry": {"coordinates":[-80.16575899999999,40.456295],"type":"Point"}
}