{
  "type": "Feature",
  "properties": {
    "iso:country":"US",
    "sg:address":"2250 Mary St",
    "sg:city":"Pittsburgh",
    "sg:classifiers":[
        {
            "category":"Shopping",
            "subcategory":"Crafts & Fabrics",
            "type":"Retail Goods"
        }
    ],
    "sg:phone":"+1 412 481 1666",
    "sg:postcode":"15203",
    "sg:province":"PA",
    "sg:tags":[
        "material",
        "needlework"
    ],
    "wof:name":"Silkthread",
    "wof:placetype":"venue"
},
  "geometry": {"coordinates":[-79.974012,40.425595],"type":"Point"}
}