{
  "type": "Feature",
  "properties": {
    "addr:full":"111 Dana St Wilkes Barre PA 18702",
    "addr:housenumber":"111",
    "addr:postcode":"18702",
    "addr:street":"Dana St",
    "iso:country":"US",
    "sg:address":"111 Dana St",
    "sg:city":"Wilkes Barre",
    "sg:classifiers":[
        {
            "category":"Organizations",
            "subcategory":"Religious Organization",
            "type":"Services"
        }
    ],
    "sg:phone":"+1   ",
    "sg:postcode":"18702",
    "sg:province":"PA",
    "wof:name":"Albright United Methdst Church",
    "wof:placetype":"venue"
},
  "geometry": {"coordinates":[-75.893895,41.236273],"type":"Point"}
}