{
  "type": "Feature",
  "properties": {
    "iso:country":"US",
    "sg:address":"990 N Main St Ste 2",
    "sg:city":"Greensburg",
    "sg:classifiers":[
        {
            "category":"Bakery",
            "type":"Food & Drink"
        }
    ],
    "sg:phone":"+1 724 834 5714",
    "sg:postcode":"15601",
    "sg:province":"PA",
    "wof:name":"Shop N' Save",
    "wof:placetype":"venue"
},
  "geometry": {"coordinates":[-79.5463,40.326343],"type":"Point"}
}