{
  "type": "Feature",
  "properties": {
    "iso:country":"US",
    "sg:address":"200 N 13th St",
    "sg:city":"Reading",
    "sg:classifiers":[
        {
            "category":"Health Services",
            "subcategory":"Doctor",
            "type":"Services"
        }
    ],
    "sg:phone":"+1   ",
    "sg:postcode":"19604",
    "sg:province":"PA",
    "sg:tags":[
        "medical"
    ],
    "wof:name":"Borneman Health Corperation",
    "wof:placetype":"venue"
},
  "geometry": {"coordinates":[-75.91220199999999,40.338574],"type":"Point"}
}