{
  "type": "Feature",
  "properties": {
    "iso:country":"US",
    "sg:address":"8 Purdue Dr",
    "sg:city":"Richboro",
    "sg:classifiers":[
        {
            "category":"Professional",
            "type":"Services"
        }
    ],
    "sg:phone":"+1   ",
    "sg:postcode":"18954",
    "sg:province":"PA",
    "wof:name":"Intelsoft Inc",
    "wof:placetype":"venue"
},
  "geometry": {"coordinates":[-75.01455,40.229353],"type":"Point"}
}