{
  "type": "Feature",
  "properties": {
    "iso:country":"US",
    "sg:address":"3021 Jacks Run Rd",
    "sg:city":"White Oak",
    "sg:classifiers":[
        {
            "category":"Health Services",
            "subcategory":"Chiropractor",
            "type":"Services"
        }
    ],
    "sg:phone":"+1 412 672 8334",
    "sg:postcode":"15131",
    "sg:province":"PA",
    "wof:name":"White Oak Chiropractic Clinic",
    "wof:placetype":"venue"
},
  "geometry": {"coordinates":[-79.793548,40.345819],"type":"Point"}
}