{
  "type": "Feature",
  "properties": {
    "addr:full":"202 Costco Dr Pittsburgh PA 15205",
    "addr:housenumber":"202",
    "addr:postcode":"15205",
    "addr:street":"Costco Dr",
    "iso:country":"US",
    "sg:address":"202 Costco Dr",
    "sg:city":"Pittsburgh",
    "sg:classifiers":[
        {
            "category":"Utilities",
            "subcategory":"Mobile Phone",
            "type":"Services"
        },
        {
            "category":"Shopping",
            "subcategory":"Mobile Phones",
            "type":"Retail Goods"
        },
        {
            "category":"Utilities",
            "subcategory":"Telephone",
            "type":"Services"
        },
        {
            "category":"Professional",
            "subcategory":"Computer Services",
            "type":"Services"
        }
    ],
    "sg:phone":"+1 412 490 4860",
    "sg:postcode":"15205",
    "sg:province":"PA",
    "sg:tags":[
        "telecommunication",
        "supply",
        "communication",
        "system",
        "wireless",
        "equipment",
        "cellular"
    ],
    "sg:website":"http://clickserve.dartsearch.net/link/click?lid=43000000308049899",
    "wof:name":"T-Mobile",
    "wof:placetype":"venue"
},
  "geometry": {"coordinates":[-80.167281,40.45799],"type":"Point"}
}