{
  "type": "Feature",
  "properties": {
    "addr:full":"2520 E Hagert St Philadelphia PA 19125",
    "addr:housenumber":"2520",
    "addr:postcode":"19125",
    "addr:street":"E Hagert St",
    "iso:country":"US",
    "sg:address":"2520 E Hagert St",
    "sg:city":"Philadelphia",
    "sg:classifiers":[
        {
            "category":"Manufacturing",
            "subcategory":"Metals",
            "type":"Manufacturing & Wholesale Goods"
        }
    ],
    "sg:phone":"+1   ",
    "sg:postcode":"19125",
    "sg:province":"PA",
    "sg:tags":[
        "steel",
        "galvanizing",
        "fabricated",
        "custom",
        "hot",
        "dip"
    ],
    "wof:name":"V and S Phldelphia Galvanizing",
    "wof:placetype":"venue"
},
  "geometry": {"coordinates":[-75.122073,39.977309],"type":"Point"}
}