{
  "type": "Feature",
  "properties": {
    "iso:country":"US",
    "sg:address":"405 Pleasant View Dr",
    "sg:city":"Etters",
    "sg:classifiers":[
        {
            "category":"Professional",
            "type":"Services"
        }
    ],
    "sg:phone":"+1   ",
    "sg:postcode":"17319",
    "sg:province":"PA",
    "wof:name":"Galen Glugston",
    "wof:placetype":"venue"
},
  "geometry": {"coordinates":[-76.809062,40.148678],"type":"Point"}
}