{
  "type": "Feature",
  "properties": {
    "iso:country":"US",
    "sg:address":"4104 Fountain Green Rd",
    "sg:city":"Lafayette Hill",
    "sg:classifiers":[
        {
            "category":"Wholesale",
            "subcategory":"Stationery",
            "type":"Manufacturing & Wholesale Goods"
        }
    ],
    "sg:phone":"+1 610 825 0530",
    "sg:postcode":"19444",
    "sg:province":"PA",
    "sg:tags":[
        "business",
        "form",
        "system"
    ],
    "wof:name":"Basic Business Systems",
    "wof:placetype":"venue"
},
  "geometry": {"coordinates":[-75.249045,40.100075],"type":"Point"}
}