{
  "type": "Feature",
  "properties": {
    "iso:country":"US",
    "sg:address":"1215 Graham Ave",
    "sg:city":"Windber",
    "sg:classifiers":[
        {
            "category":"Professional",
            "subcategory":"Accounting & Tax Preparation",
            "type":"Services"
        }
    ],
    "sg:phone":"+1   ",
    "sg:postcode":"15963",
    "sg:province":"PA",
    "sg:tags":[
        "return"
    ],
    "wof:name":"Orlovsky Tax Service",
    "wof:placetype":"venue"
},
  "geometry": {"coordinates":[-78.83341299999999,40.237335],"type":"Point"}
}