{
  "type": "Feature",
  "properties": {
    "iso:country":"US",
    "sg:address":"3617 Kutztown Rd",
    "sg:city":"Reading",
    "sg:classifiers":[
        {
            "category":"Building & Trades",
            "subcategory":"Construction",
            "type":"Services"
        }
    ],
    "sg:phone":"+1 610 929 2832",
    "sg:postcode":"19605",
    "sg:province":"PA",
    "sg:tags":[
        "builder",
        "deck",
        "contractor"
    ],
    "sg:website":"www.hahnexteriors.com",
    "wof:name":"Hahn Exteriors Inc",
    "wof:placetype":"venue"
},
  "geometry": {"coordinates":[-75.91986900000001,40.391322],"type":"Point"}
}