{
  "type": "Feature",
  "properties": {
    "addr:full":"3101 Centre Ave Reading PA 19605",
    "addr:housenumber":"3101",
    "addr:postcode":"19605",
    "addr:street":"Centre Ave",
    "iso:country":"US",
    "sg:address":"3101 Centre Ave",
    "sg:city":"Reading",
    "sg:classifiers":[
        {
            "category":"Building & Trades",
            "subcategory":"Construction",
            "type":"Services"
        }
    ],
    "sg:phone":"+1   ",
    "sg:postcode":"19605",
    "sg:province":"PA",
    "sg:tags":[
        "contractor"
    ],
    "wof:name":"C Rowes Inc",
    "wof:placetype":"venue"
},
  "geometry": {"coordinates":[-75.933665,40.378888],"type":"Point"}
}