{
  "type": "Feature",
  "properties": {
    "iso:country":"US",
    "sg:address":"1035 Main St",
    "sg:city":"Dickson City",
    "sg:classifiers":[
        {
            "category":"Personal",
            "subcategory":"Beauty Salon",
            "type":"Services"
        }
    ],
    "sg:phone":"+1 570 383 6450",
    "sg:postcode":"18519",
    "sg:province":"PA",
    "wof:name":"Alana's A Full Svc Salon",
    "wof:placetype":"venue"
},
  "geometry": {"coordinates":[-75.61811299999999,41.465138],"type":"Point"}
}