{
  "type": "Feature",
  "properties": {
    "iso:country":"US",
    "sg:address":"368 Petersburg Rd",
    "sg:city":"Allenwood",
    "sg:classifiers":[
        {
            "category":"Farming",
            "subcategory":"Livestock Farm",
            "type":"Manufacturing & Wholesale Goods"
        }
    ],
    "sg:phone":"+1   ",
    "sg:postcode":"17810",
    "sg:province":"PA",
    "sg:tags":[
        "beef",
        "feedlot",
        "cattle"
    ],
    "wof:name":"Ned Farley",
    "wof:placetype":"venue"
},
  "geometry": {"coordinates":[-77.023839,41.126229],"type":"Point"}
}