{
  "type": "Feature",
  "properties": {
    "addr:full":"150 Monument Rd Bala Cynwyd PA 19004",
    "addr:housenumber":"150",
    "addr:postcode":"19004",
    "addr:street":"Monument Rd",
    "iso:country":"US",
    "sg:address":"150 Monument Rd",
    "sg:city":"Bala Cynwyd",
    "sg:classifiers":[
        {
            "category":"Insurance",
            "subcategory":"Insurance Agent",
            "type":"Services"
        }
    ],
    "sg:phone":"+1   ",
    "sg:postcode":"19004",
    "sg:province":"PA",
    "sg:tags":[
        "agency"
    ],
    "wof:name":"Phoenix Home Lf Mutl Insur Co",
    "wof:placetype":"venue"
},
  "geometry": {"coordinates":[-75.21775700000001,40.012276],"type":"Point"}
}