{
  "type": "Feature",
  "properties": {
    "iso:country":"US",
    "sg:address":"1210 S Broad St",
    "sg:city":"Philadelphia",
    "sg:classifiers":[
        {
            "category":"Social Services",
            "type":"Services"
        }
    ],
    "sg:phone":"+1   ",
    "sg:postcode":"19146",
    "sg:province":"PA",
    "sg:tags":[
        "agency"
    ],
    "wof:name":"Diversified Community Services",
    "wof:placetype":"venue"
},
  "geometry": {"coordinates":[-75.167687,39.934319],"type":"Point"}
}