{
  "type": "Feature",
  "properties": {
    "addr:full":"3428 York Rd Furlong PA 18925",
    "addr:housenumber":"3428",
    "addr:postcode":"18925",
    "addr:street":"York Rd",
    "iso:country":"US",
    "sg:address":"3428 York Rd",
    "sg:city":"Furlong",
    "sg:classifiers":[
        {
            "category":"Building & Trades",
            "subcategory":"Landscaping Services",
            "type":"Services"
        }
    ],
    "sg:phone":"+1   ",
    "sg:postcode":"18925",
    "sg:province":"PA",
    "sg:tags":[
        "operation",
        "timber",
        "tract"
    ],
    "wof:name":"Greenwoods Affrdbl Large Trees",
    "wof:placetype":"venue"
},
  "geometry": {"coordinates":[-75.082673,40.293926],"type":"Point"}
}