{
  "type": "Feature",
  "properties": {
    "addr:full":"26 N 2nd St Clearfield PA 16830",
    "addr:housenumber":"26",
    "addr:postcode":"16830",
    "addr:street":"N 2Nd St",
    "iso:country":"US",
    "sg:address":"26 N 2nd St",
    "sg:city":"Clearfield",
    "sg:classifiers":[
        {
            "category":"Communications",
            "subcategory":"Film & Video Production",
            "type":"Services"
        }
    ],
    "sg:phone":"+1   ",
    "sg:postcode":"16830",
    "sg:province":"PA",
    "sg:tags":[
        "motion"
    ],
    "wof:name":"Harmony Multi Media LLC",
    "wof:placetype":"venue"
},
  "geometry": {"coordinates":[-78.43815499999999,41.022371],"type":"Point"}
}