{
  "type": "Feature",
  "properties": {
    "addr:full":"31 S 31st St Harrisburg PA 17111",
    "addr:housenumber":"31",
    "addr:postcode":"17111",
    "addr:street":"S 31St St",
    "iso:country":"US",
    "sg:address":"31 S 31st St",
    "sg:city":"Harrisburg",
    "sg:classifiers":[
        {
            "category":"Personal",
            "type":"Services"
        }
    ],
    "sg:phone":"+1 610 776 6177",
    "sg:postcode":"17111",
    "sg:province":"PA",
    "sg:tags":[
        "mover"
    ],
    "wof:name":"Alpha International Movers Inc",
    "wof:placetype":"venue"
},
  "geometry": {"coordinates":[-76.837324,40.258798],"type":"Point"}
}