{
  "type": "Feature",
  "properties": {
    "addr:full":"6000 Oxford Dr Bethel Park PA 15102",
    "addr:housenumber":"6000",
    "addr:postcode":"15102",
    "addr:street":"Oxford Dr",
    "iso:country":"US",
    "sg:address":"6000 Oxford Dr",
    "sg:city":"Bethel Park",
    "sg:classifiers":[
        {
            "category":"Restaurant",
            "type":"Food & Drink"
        }
    ],
    "sg:menulink":"http://www.allmenus.com/pa/bethel-park/13786-olive-garden-italian-restaurant/menu/",
    "sg:phone":"+1 412 835 6353",
    "sg:postcode":"15102",
    "sg:province":"PA",
    "sg:tags":[
        "italian"
    ],
    "wof:name":"Olive Garden Italian Restaurant",
    "wof:placetype":"venue"
},
  "geometry": {"coordinates":[-80.049809,40.34796],"type":"Point"}
}