{
  "type": "Feature",
  "properties": {
    "addr:full":"723 Chestnut St Fl 4 Philadelphia PA 19106",
    "addr:housenumber":"723;4",
    "addr:postcode":"19106",
    "addr:street":"Chestnut St",
    "iso:country":"US",
    "sg:address":"723 Chestnut St Fl 4",
    "sg:city":"Philadelphia",
    "sg:classifiers":[
        {
            "category":"Arts & Performance",
            "subcategory":"Art Gallery",
            "type":"Entertainment"
        }
    ],
    "sg:phone":"+1 215 923 1242",
    "sg:postcode":"19106",
    "sg:province":"PA",
    "sg:website":"www.jamesolivergallery.com",
    "wof:name":"James Oliver Gallery",
    "wof:placetype":"venue"
},
  "geometry": {"coordinates":[-75.152663,39.949599],"type":"Point"}
}