{
  "type": "Feature",
  "properties": {
    "addr:full":"243 E Mine St Hazleton PA 18201",
    "addr:housenumber":"243",
    "addr:postcode":"18201",
    "addr:street":"E Mine St",
    "iso:country":"US",
    "sg:address":"243 E Mine St",
    "sg:city":"Hazleton",
    "sg:classifiers":[
        {
            "category":"Food & Beverages",
            "subcategory":"Fruits & Vegetables",
            "type":"Retail Goods"
        }
    ],
    "sg:phone":"+1   ",
    "sg:postcode":"18201",
    "sg:province":"PA",
    "wof:name":"Dannys Brother Co",
    "wof:placetype":"venue"
},
  "geometry": {"coordinates":[-75.97037400000001,40.952381],"type":"Point"}
}