{
  "type": "Feature",
  "properties": {
    "iso:country":"US",
    "sg:address":"7116 Rising Sun Ave",
    "sg:city":"Philadelphia",
    "sg:classifiers":[
        {
            "category":"Building & Trades",
            "subcategory":"Cleaning & Sanitation",
            "type":"Services"
        }
    ],
    "sg:phone":"+1 215 342 9500",
    "sg:postcode":"19111",
    "sg:province":"PA",
    "sg:tags":[
        "janitor"
    ],
    "wof:name":"OMEX",
    "wof:placetype":"venue"
},
  "geometry": {"coordinates":[-75.087159,40.058204],"type":"Point"}
}