{
  "type": "Feature",
  "properties": {
    "addr:full":"135 Taylor Rd Etters PA 17319",
    "addr:housenumber":"135",
    "addr:postcode":"17319",
    "addr:street":"Taylor Rd",
    "iso:country":"US",
    "sg:address":"135 Taylor Rd",
    "sg:city":"Etters",
    "sg:classifiers":[
        {
            "category":"Autos & Motor Vehicles",
            "subcategory":"Fuel & Gas Station",
            "type":"Retail Goods"
        }
    ],
    "sg:phone":"+1 717 938 2929",
    "sg:postcode":"17319",
    "sg:province":"PA",
    "sg:tags":[
        "repair",
        "station",
        "gasoline",
        "general"
    ],
    "wof:name":"Hollerbush Garage",
    "wof:placetype":"venue"
},
  "geometry": {"coordinates":[-76.818247,40.138101],"type":"Point"}
}