{
  "type": "Feature",
  "properties": {
    "iso:country":"US",
    "sg:address":"1475 W Allen St",
    "sg:city":"Allentown",
    "sg:classifiers":[
        {
            "category":"Government",
            "subcategory":"Fire Station",
            "type":"Public Place"
        }
    ],
    "sg:phone":"+1   ",
    "sg:postcode":"18102",
    "sg:province":"PA",
    "sg:tags":[
        "department",
        "volunteer"
    ],
    "wof:name":"Allentown Volunteer Fire Dept",
    "wof:placetype":"venue"
},
  "geometry": {"coordinates":[-75.490779,40.606523],"type":"Point"}
}