{
  "type": "Feature",
  "properties": {
    "iso:country":"US",
    "sg:address":"110 Chambersburg St",
    "sg:city":"Gettysburg",
    "sg:classifiers":[
        {
            "category":"Coffee & Tea",
            "type":"Food & Drink"
        },
        {
            "category":"Restaurant",
            "type":"Food & Drink"
        }
    ],
    "sg:phone":"+1 717 334 4464",
    "sg:postcode":"17325",
    "sg:province":"PA",
    "sg:tags":[
        "espresso"
    ],
    "wof:name":"Ragged Edge Coffee House",
    "wof:placetype":"venue"
},
  "geometry": {"coordinates":[-77.233493,39.830873],"type":"Point"}
}