{
  "type": "Feature",
  "properties": {
    "iso:country":"US",
    "sg:address":"301 S Geyers Church Rd",
    "sg:city":"Middletown",
    "sg:classifiers":[
        {
            "category":"Professional",
            "type":"Services"
        },
        {
            "category":"Retail",
            "subcategory":"Auto Rental",
            "type":"Services"
        },
        {
            "category":"Travel",
            "subcategory":"Travel Agent",
            "type":"Entertainment"
        },
        {
            "category":"Airport",
            "type":"Transportation"
        }
    ],
    "sg:phone":"+1 717 388 5883",
    "sg:postcode":"17057",
    "sg:province":"PA",
    "sg:tags":[
        "consultant",
        "limousine"
    ],
    "sg:website":"http://www.yext.com/p/superpages/premiere-1-limousine-service-middletown-pennsylvania.html",
    "wof:name":"Premiere #1 Limousine Service",
    "wof:placetype":"venue"
},
  "geometry": {"coordinates":[-76.693207,40.18885],"type":"Point"}
}