{
  "type": "Feature",
  "properties": {
    "iso:country":"US",
    "sg:address":"801 Yale Ave",
    "sg:city":"Swarthmore",
    "sg:classifiers":[
        {
            "category":"Insurance",
            "subcategory":"Insurance Agent",
            "type":"Services"
        }
    ],
    "sg:phone":"+1 610 328 4666",
    "sg:postcode":"19081",
    "sg:province":"PA",
    "wof:name":"Gene H Martenson",
    "wof:placetype":"venue"
},
  "geometry": {"coordinates":[-75.35709199999999,39.894341],"type":"Point"}
}