{
  "type": "Feature",
  "properties": {
    "iso:country":"US",
    "sg:address":"4590 Broadway Rd",
    "sg:city":"Milton",
    "sg:classifiers":[
        {
            "category":"Retail",
            "subcategory":"Auto Rental",
            "type":"Services"
        },
        {
            "category":"Retail",
            "subcategory":"Storage",
            "type":"Services"
        }
    ],
    "sg:phone":"+1 570 742 8811",
    "sg:postcode":"17847",
    "sg:province":"PA",
    "sg:tags":[
        "moving-self",
        "truck"
    ],
    "wof:name":"H B Fleming Inc",
    "wof:placetype":"venue"
},
  "geometry": {"coordinates":[-76.775452,41.027821],"type":"Point"}
}