{
  "type": "Feature",
  "properties": {
    "addr:full":"3536 Rhoads Ave Newtown Square PA 19073",
    "addr:housenumber":"3536",
    "addr:postcode":"19073",
    "addr:street":"Rhoads Ave",
    "iso:country":"US",
    "sg:address":"3536 Rhoads Ave",
    "sg:city":"Newtown Square",
    "sg:classifiers":[
        {
            "category":"Health Services",
            "subcategory":"Doctor",
            "type":"Services"
        }
    ],
    "sg:phone":"+1   ",
    "sg:postcode":"19073",
    "sg:province":"PA",
    "wof:name":"Berman Hope S DMD",
    "wof:placetype":"venue"
},
  "geometry": {"coordinates":[-75.398595,39.987892],"type":"Point"}
}