{
  "type": "Feature",
  "properties": {
    "iso:country":"US",
    "sg:address":"211 E Mountain Rd",
    "sg:city":"Hegins",
    "sg:classifiers":[
        {
            "category":"Wholesale",
            "subcategory":"Fruits & Vegetables",
            "type":"Manufacturing & Wholesale Goods"
        }
    ],
    "sg:phone":"+1 570 682 3342",
    "sg:postcode":"17938",
    "sg:province":"PA",
    "sg:tags":[
        "shipper"
    ],
    "wof:name":"Huntsinger Farms Inc",
    "wof:placetype":"venue"
},
  "geometry": {"coordinates":[-76.503373,40.658579],"type":"Point"}
}