{
  "type": "Feature",
  "properties": {
    "iso:country":"US",
    "sg:address":"602 New St",
    "sg:city":"Olyphant",
    "sg:classifiers":[
        {
            "category":"Building & Trades",
            "subcategory":"Landscaping Services",
            "type":"Services"
        }
    ],
    "sg:phone":"+1   ",
    "sg:postcode":"18447",
    "sg:province":"PA",
    "wof:name":"Meleskys Lawn & Landscape",
    "wof:placetype":"venue"
},
  "geometry": {"coordinates":[-75.602346,41.46422],"type":"Point"}
}