{
  "type": "Feature",
  "properties": {
    "addr:full":"466 Rosanne Dr Verona PA 15147",
    "addr:housenumber":"466",
    "addr:postcode":"15147",
    "addr:street":"Rosanne Dr",
    "iso:country":"US",
    "sg:address":"466 Rosanne Dr",
    "sg:city":"Verona",
    "sg:classifiers":[
        {
            "category":"Building & Trades",
            "subcategory":"Construction",
            "type":"Services"
        }
    ],
    "sg:phone":"+1   ",
    "sg:postcode":"15147",
    "sg:province":"PA",
    "sg:tags":[
        "home"
    ],
    "wof:name":"RL Cunningham Associates",
    "wof:placetype":"venue"
},
  "geometry": {"coordinates":[-79.81561000000001,40.494767],"type":"Point"}
}