{
  "type": "Feature",
  "properties": {
    "iso:country":"US",
    "sg:address":"67 W Willow Rd",
    "sg:city":"Willow Street",
    "sg:classifiers":[
        {
            "category":"Manufacturing",
            "subcategory":"Tools & Machinery",
            "type":"Manufacturing & Wholesale Goods"
        }
    ],
    "sg:phone":"+1   ",
    "sg:postcode":"17584",
    "sg:province":"PA",
    "sg:tags":[
        "instrument",
        "mfg"
    ],
    "wof:name":"J and J Marketing",
    "wof:placetype":"venue"
},
  "geometry": {"coordinates":[-76.279556,39.974747],"type":"Point"}
}