{
  "type": "Feature",
  "properties": {
    "iso:country":"US",
    "sg:address":"248 Hollow View Rd",
    "sg:city":"Curwensville",
    "sg:classifiers":[
        {
            "category":"Farming",
            "subcategory":"Livestock Farm",
            "type":"Manufacturing & Wholesale Goods"
        },
        {
            "category":"Farming",
            "subcategory":"Farm & Veterinary Services",
            "type":"Manufacturing & Wholesale Goods"
        }
    ],
    "sg:phone":"+1 814 236 3027",
    "sg:postcode":"16833",
    "sg:province":"PA",
    "sg:tags":[
        "breeder"
    ],
    "wof:name":"George Prisk",
    "wof:placetype":"venue"
},
  "geometry": {"coordinates":[-78.621319,40.906296],"type":"Point"}
}