{
  "type": "Feature",
  "properties": {
    "addr:full":"3500 Birney Ave Moosic PA 18507",
    "addr:housenumber":"3500",
    "addr:postcode":"18507",
    "addr:street":"Birney Ave",
    "iso:country":"US",
    "sg:address":"3500 Birney Ave",
    "sg:city":"Moosic",
    "sg:classifiers":[
        {
            "category":"Restaurant",
            "type":"Food & Drink"
        }
    ],
    "sg:menulink":"http://www.allmenus.com/pa/moosic/200192-long-john-silvers/menu/",
    "sg:phone":"+1 570 342 2566",
    "sg:postcode":"18507",
    "sg:province":"PA",
    "sg:tags":[
        "seafood",
        "american"
    ],
    "wof:name":"Long John Silver's",
    "wof:placetype":"venue"
},
  "geometry": {"coordinates":[-75.701672,41.373086],"type":"Point"}
}