{
  "type": "Feature",
  "properties": {
    "iso:country":"US",
    "sg:address":"516 4th St",
    "sg:city":"Sutersville",
    "sg:classifiers":[
        {
            "category":"Building & Trades",
            "subcategory":"Plumbing",
            "type":"Services"
        }
    ],
    "sg:phone":"+1 724 872 7999",
    "sg:postcode":"15083",
    "sg:province":"PA",
    "sg:tags":[
        "plumbing",
        "contractor"
    ],
    "wof:name":"J & M Plumbing & Heating",
    "wof:placetype":"venue"
},
  "geometry": {"coordinates":[-79.803338,40.236308],"type":"Point"}
}