{
  "type": "Feature",
  "properties": {
    "addr:full":"128 Water St East Berlin PA 17316",
    "addr:housenumber":"128",
    "addr:postcode":"17316",
    "addr:street":"Water St",
    "iso:country":"US",
    "sg:address":"128 Water St",
    "sg:city":"East Berlin",
    "sg:classifiers":[
        {
            "category":"Government",
            "subcategory":"Office",
            "type":"Public Place"
        }
    ],
    "sg:phone":"+1 717 259 9224",
    "sg:postcode":"17316",
    "sg:province":"PA",
    "sg:tags":[
        "city",
        "village"
    ],
    "wof:name":"East Berlin Borough Hall",
    "wof:placetype":"venue"
},
  "geometry": {"coordinates":[-76.97814700000001,39.941598],"type":"Point"}
}