{
  "type": "Feature",
  "properties": {
    "iso:country":"US",
    "sg:address":"801 Church St",
    "sg:city":"Jessup",
    "sg:classifiers":[
        {
            "category":"Home & Garden",
            "subcategory":"Furniture",
            "type":"Retail Goods"
        }
    ],
    "sg:phone":"+1 570 489 0977",
    "sg:postcode":"18434",
    "sg:province":"PA",
    "sg:tags":[
        "top",
        "counter"
    ],
    "wof:name":"L & L Designs Inc",
    "wof:placetype":"venue"
},
  "geometry": {"coordinates":[-75.565152,41.471468],"type":"Point"}
}