{
  "type": "Feature",
  "properties": {
    "addr:full":"213 N 14th St Allentown PA 18102",
    "addr:housenumber":"213",
    "addr:postcode":"18102",
    "addr:street":"N 14Th St",
    "iso:country":"US",
    "sg:address":"213 N 14th St",
    "sg:city":"Allentown",
    "sg:classifiers":[
        {
            "category":"Wholesale",
            "subcategory":"Construction Materials",
            "type":"Manufacturing & Wholesale Goods"
        }
    ],
    "sg:phone":"+1 610 437 6114",
    "sg:postcode":"18102",
    "sg:province":"PA",
    "sg:tags":[
        "household",
        "kitchen",
        "appliance",
        "electric",
        "cabinet"
    ],
    "wof:name":"Kitchens By Wipco",
    "wof:placetype":"venue"
},
  "geometry": {"coordinates":[-75.48772700000001,40.602098],"type":"Point"}
}