{
  "type": "Feature",
  "properties": {
    "addr:full":"15142 S Townline Rd Linesville PA 16424",
    "addr:housenumber":"15142",
    "addr:postcode":"16424",
    "addr:street":"S Townline Rd",
    "iso:country":"US",
    "sg:address":"15142 S Townline Rd",
    "sg:city":"Linesville",
    "sg:classifiers":[
        {
            "category":"Farming",
            "subcategory":"Farm",
            "type":"Manufacturing & Wholesale Goods"
        }
    ],
    "sg:phone":"+1 814 683 4485",
    "sg:postcode":"16424",
    "sg:province":"PA",
    "wof:name":"Richard Fry",
    "wof:placetype":"venue"
},
  "geometry": {"coordinates":[-80.391503,41.676629],"type":"Point"}
}