{
  "type": "Feature",
  "properties": {
    "iso:country":"US",
    "sg:address":"16 S Market St",
    "sg:city":"Mechanicsburg",
    "sg:classifiers":[
        {
            "category":"Building & Trades",
            "subcategory":"Construction",
            "type":"Services"
        }
    ],
    "sg:phone":"+1 717 697 8801",
    "sg:postcode":"17055",
    "sg:province":"PA",
    "sg:tags":[
        "residential",
        "remodeling"
    ],
    "wof:name":"Page Brothers Inc",
    "wof:placetype":"venue"
},
  "geometry": {"coordinates":[-77.007835,40.212727],"type":"Point"}
}