{
  "type": "Feature",
  "properties": {
    "iso:country":"US",
    "sg:address":"5942 Germantown Ave",
    "sg:city":"Philadelphia",
    "sg:classifiers":[
        {
            "category":"Restaurant",
            "type":"Food & Drink"
        }
    ],
    "sg:phone":"+1   ",
    "sg:postcode":"19144",
    "sg:province":"PA",
    "sg:tags":[
        "eating"
    ],
    "wof:name":"Joseph Newman Inc",
    "wof:placetype":"venue"
},
  "geometry": {"coordinates":[-75.177577,40.039009],"type":"Point"}
}