{
  "type": "Feature",
  "properties": {
    "iso:country":"US",
    "sg:address":"1425 Schirra Dr",
    "sg:city":"Ambler",
    "sg:classifiers":[
        {
            "category":"Building & Trades",
            "subcategory":"Construction",
            "type":"Services"
        }
    ],
    "sg:phone":"+1 215 537 0100",
    "sg:postcode":"19002",
    "sg:province":"PA",
    "sg:tags":[
        "contractor",
        "mechanical"
    ],
    "wof:name":"R&P Mechanical",
    "wof:placetype":"venue"
},
  "geometry": {"coordinates":[-75.18819999999999,40.156882],"type":"Point"}
}