{
  "type": "Feature",
  "properties": {
    "addr:full":"95 E Street Rd Feastervl Trvs PA 19053",
    "addr:housenumber":"95",
    "addr:postcode":"19053",
    "addr:street":"E Street Rd",
    "iso:country":"US",
    "sg:address":"95 E Street Rd",
    "sg:city":"Feastervl Trvs",
    "sg:classifiers":[
        {
            "category":"Shopping",
            "subcategory":"Clothing, Apparel, & Fashions",
            "type":"Retail Goods"
        }
    ],
    "sg:phone":"+1 215 953 8405",
    "sg:postcode":"19053",
    "sg:province":"PA",
    "sg:website":"www.fashionbug.com",
    "wof:name":"Fashion Bug",
    "wof:placetype":"venue"
},
  "geometry": {"coordinates":[-75.00310399999999,40.151117],"type":"Point"}
}