{
  "type": "Feature",
  "properties": {
    "iso:country":"US",
    "sg:address":"1410 5th Ave",
    "sg:city":"Ford City",
    "sg:classifiers":[
        {
            "category":"Health Services",
            "subcategory":"Clinic",
            "type":"Services"
        }
    ],
    "sg:phone":"+1   ",
    "sg:postcode":"16226",
    "sg:province":"PA",
    "sg:tags":[
        "home",
        "care"
    ],
    "wof:name":"Ford City",
    "wof:placetype":"venue"
},
  "geometry": {"coordinates":[-79.524326,40.776833],"type":"Point"}
}