{
  "type": "Feature",
  "properties": {
    "iso:country":"US",
    "sg:address":"308 Harrison Ave",
    "sg:city":"Glenside",
    "sg:classifiers":[
        {
            "category":"Shopping",
            "subcategory":"Musical Instruments",
            "type":"Retail Goods"
        }
    ],
    "sg:phone":"+1   ",
    "sg:postcode":"19038",
    "sg:province":"PA",
    "wof:name":"Player Piano Workshop",
    "wof:placetype":"venue"
},
  "geometry": {"coordinates":[-75.16194400000001,40.097241],"type":"Point"}
}