{
  "type": "Feature",
  "properties": {
    "iso:country":"US",
    "sg:address":"219 Front St",
    "sg:city":"New Brighton",
    "sg:classifiers":[
        {
            "category":"Organizations",
            "subcategory":"Community Association",
            "type":"Services"
        }
    ],
    "sg:phone":"+1 724 847 4663",
    "sg:postcode":"15066",
    "sg:province":"PA",
    "sg:tags":[
        "club"
    ],
    "wof:name":"Beaver Valley Yacht Club",
    "wof:placetype":"venue"
},
  "geometry": {"coordinates":[-80.309378,40.724461],"type":"Point"}
}