{
  "type": "Feature",
  "properties": {
    "addr:full":"5815 Ellsworth Ave Pittsburgh PA 15232",
    "addr:housenumber":"5815",
    "addr:postcode":"15232",
    "addr:street":"Ellsworth Ave",
    "iso:country":"US",
    "sg:address":"5815 Ellsworth Ave",
    "sg:city":"Pittsburgh",
    "sg:classifiers":[
        {
            "category":"Personal",
            "subcategory":"Beauty Salon",
            "type":"Services"
        }
    ],
    "sg:phone":"+1 412 363 2113",
    "sg:postcode":"15232",
    "sg:province":"PA",
    "sg:tags":[
        "shop"
    ],
    "wof:name":"Sybil",
    "wof:placetype":"venue"
},
  "geometry": {"coordinates":[-79.930769,40.456215],"type":"Point"}
}