{
  "type": "Feature",
  "properties": {
    "iso:country":"US",
    "sg:address":"4683 Bradley Ct",
    "sg:city":"Doylestown",
    "sg:classifiers":[
        {
            "category":"Professional",
            "subcategory":"Employment Agencies",
            "type":"Services"
        }
    ],
    "sg:phone":"+1 215 794 9801",
    "sg:postcode":"18901",
    "sg:province":"PA",
    "wof:name":"Lgf & Associates",
    "wof:placetype":"venue"
},
  "geometry": {"coordinates":[-75.064499,40.325901],"type":"Point"}
}