{
  "type": "Feature",
  "properties": {
    "iso:country":"US",
    "sg:address":"1901 S 12th St",
    "sg:city":"Allentown",
    "sg:classifiers":[
        {
            "category":"Home & Garden",
            "subcategory":"Household Appliances",
            "type":"Retail Goods"
        }
    ],
    "sg:phone":"+1   ",
    "sg:postcode":"18103",
    "sg:province":"PA",
    "sg:tags":[
        "machine",
        "sewing"
    ],
    "wof:name":"Home Sewing Center",
    "wof:placetype":"venue"
},
  "geometry": {"coordinates":[-75.476707,40.580481],"type":"Point"}
}