{
  "type": "Feature",
  "properties": {
    "iso:country":"US",
    "sg:address":"850 Laurelwood Rd",
    "sg:city":"Pottstown",
    "sg:classifiers":[
        {
            "category":"Retail",
            "subcategory":"Repair Shop",
            "type":"Services"
        }
    ],
    "sg:phone":"+1 610 323 6505",
    "sg:postcode":"19465",
    "sg:province":"PA",
    "sg:tags":[
        "clocks",
        "parts"
    ],
    "wof:name":"Liberty Clock Svc",
    "wof:placetype":"venue"
},
  "geometry": {"coordinates":[-75.667861,40.230488],"type":"Point"}
}