{
  "type": "Feature",
  "properties": {
    "addr:full":"619 Horsham Rd Horsham PA 19044",
    "addr:housenumber":"619",
    "addr:postcode":"19044",
    "addr:street":"Horsham Rd",
    "iso:country":"US",
    "sg:address":"619 Horsham Rd",
    "sg:city":"Horsham",
    "sg:classifiers":[
        {
            "category":"Health Services",
            "subcategory":"Doctor",
            "type":"Services"
        }
    ],
    "sg:phone":"+1 215 674 4400",
    "sg:postcode":"19044",
    "sg:province":"PA",
    "sg:tags":[
        "dentist"
    ],
    "sg:website":"www.implantoralsurgeons.com",
    "wof:name":"Oral & Maxillofacial Surgical",
    "wof:placetype":"venue"
},
  "geometry": {"coordinates":[-75.150425,40.190904],"type":"Point"}
}