{
  "type": "Feature",
  "properties": {
    "iso:country":"US",
    "sg:address":"455 Fairview Chapel Rd",
    "sg:city":"Birdsboro",
    "sg:classifiers":[
        {
            "category":"Wholesale",
            "subcategory":"Construction Materials",
            "type":"Manufacturing & Wholesale Goods"
        }
    ],
    "sg:phone":"+1 610 404 0622",
    "sg:postcode":"19508",
    "sg:province":"PA",
    "sg:tags":[
        "fence"
    ],
    "wof:name":"Mid-Atlantic Vinyl Mfg Inc",
    "wof:placetype":"venue"
},
  "geometry": {"coordinates":[-75.828227,40.280764],"type":"Point"}
}