{
  "type": "Feature",
  "properties": {
    "iso:country":"US",
    "sg:address":"5850 Ellsworth Ave",
    "sg:city":"Pittsburgh",
    "sg:classifiers":[
        {
            "category":"Health Services",
            "subcategory":"Doctor",
            "type":"Services"
        }
    ],
    "sg:phone":"+1 412 661 2036",
    "sg:postcode":"15232",
    "sg:province":"PA",
    "sg:tags":[
        "psychologist"
    ],
    "wof:name":"Lydon Judith A",
    "wof:placetype":"venue"
},
  "geometry": {"coordinates":[-79.92929100000001,40.457142],"type":"Point"}
}