{
  "type": "Feature",
  "properties": {
    "iso:country":"US",
    "sg:address":"705 N Chester Rd",
    "sg:city":"West Chester",
    "sg:classifiers":[
        {
            "category":"Professional",
            "subcategory":"Management & Consulting",
            "type":"Services"
        }
    ],
    "sg:phone":"+1   ",
    "sg:postcode":"19380",
    "sg:province":"PA",
    "wof:name":"Alexus Group Ltd",
    "wof:placetype":"venue"
},
  "geometry": {"coordinates":[-75.543476,39.992072],"type":"Point"}
}