{
  "type": "Feature",
  "properties": {
    "addr:full":"1500 Washington Rd Pittsburgh PA 15228",
    "addr:housenumber":"1500",
    "addr:postcode":"15228",
    "addr:street":"Washington Rd",
    "iso:country":"US",
    "sg:address":"1500 Washington Rd",
    "sg:city":"Pittsburgh",
    "sg:classifiers":[
        {
            "category":"Arts & Performance",
            "subcategory":"Art Gallery",
            "type":"Entertainment"
        }
    ],
    "sg:phone":"+1 412 341 3222",
    "sg:postcode":"15228",
    "sg:province":"PA",
    "wof:name":"Renaissance Galleries",
    "wof:placetype":"venue"
},
  "geometry": {"coordinates":[-80.0504,40.357498],"type":"Point"}
}