{
  "type": "Feature",
  "properties": {
    "addr:full":"5625 N 5th St Philadelphia PA 19120",
    "addr:housenumber":"5625",
    "addr:postcode":"19120",
    "addr:street":"N 5Th St",
    "iso:country":"US",
    "sg:address":"5625 N 5th St",
    "sg:city":"Philadelphia",
    "sg:classifiers":[
        {
            "category":"Wholesale",
            "subcategory":"Machinery & Supplies",
            "type":"Manufacturing & Wholesale Goods"
        }
    ],
    "sg:phone":"+1   ",
    "sg:postcode":"19120",
    "sg:province":"PA",
    "sg:tags":[
        "equipment",
        "establishment"
    ],
    "wof:name":"Sensations Hair Plus Buty Sup",
    "wof:placetype":"venue"
},
  "geometry": {"coordinates":[-75.130155,40.037595],"type":"Point"}
}