{
  "type": "Feature",
  "properties": {
    "iso:country":"US",
    "sg:address":"133 W Tioga St",
    "sg:city":"Tunkhannock",
    "sg:classifiers":[
        {
            "category":"Health Services",
            "subcategory":"Health Practitioner",
            "type":"Services"
        }
    ],
    "sg:phone":"+1 570 836 6554",
    "sg:postcode":"18657",
    "sg:province":"PA",
    "sg:tags":[
        "psychologist"
    ],
    "wof:name":"Larry Gehres PHD",
    "wof:placetype":"venue"
},
  "geometry": {"coordinates":[-75.956641,41.541203],"type":"Point"}
}