{
  "type": "Feature",
  "properties": {
    "iso:country":"US",
    "sg:address":"109 W Church St",
    "sg:city":"Centre Hall",
    "sg:classifiers":[
        {
            "category":"Travel",
            "subcategory":"Hotels & Motels",
            "type":"Entertainment"
        }
    ],
    "sg:phone":"+1 814 364 2225",
    "sg:postcode":"16828",
    "sg:province":"PA",
    "sg:tags":[
        "breakfast",
        "accommodation",
        "bed"
    ],
    "wof:name":"Keller House B & B",
    "wof:placetype":"venue"
},
  "geometry": {"coordinates":[-77.688346,40.847668],"type":"Point"}
}