{
  "type": "Feature",
  "properties": {
    "addr:full":"4165 Carlisle Rd Gardners PA 17324",
    "addr:housenumber":"4165",
    "addr:postcode":"17324",
    "addr:street":"Carlisle Rd",
    "iso:country":"US",
    "sg:address":"4165 Carlisle Rd",
    "sg:city":"Gardners",
    "sg:classifiers":[
        {
            "category":"Manufacturing",
            "subcategory":"Electronics",
            "type":"Manufacturing & Wholesale Goods"
        }
    ],
    "sg:phone":"+1 717 486 5904",
    "sg:postcode":"17324",
    "sg:province":"PA",
    "sg:tags":[
        "printers-equipment",
        "supply"
    ],
    "wof:name":"Davis Graphic Supply",
    "wof:placetype":"venue"
},
  "geometry": {"coordinates":[-77.202427,40.03989],"type":"Point"}
}