{
  "type": "Feature",
  "properties": {
    "iso:country":"US",
    "sg:address":"2937 Lime Kiln Rd",
    "sg:city":"Chambersburg",
    "sg:classifiers":[
        {
            "category":"Building & Trades",
            "subcategory":"Electrical",
            "type":"Services"
        }
    ],
    "sg:phone":"+1 717 532 3315",
    "sg:postcode":"17202",
    "sg:province":"PA",
    "sg:tags":[
        "industrial",
        "electrician",
        "contractors-commercial",
        "electric"
    ],
    "wof:name":"Benedict Electric",
    "wof:placetype":"venue"
},
  "geometry": {"coordinates":[-77.612629,40.038533],"type":"Point"}
}