{
  "type": "Feature",
  "properties": {
    "iso:country":"US",
    "sg:address":"1917 Washington Pike",
    "sg:city":"Carnegie",
    "sg:classifiers":[
        {
            "category":"Restaurant",
            "type":"Food & Drink"
        }
    ],
    "sg:phone":"+1 412 279 0999",
    "sg:postcode":"15106",
    "sg:province":"PA",
    "sg:tags":[
        "italian"
    ],
    "sg:website":"bennosrestaurant.com",
    "wof:name":"Benno's",
    "wof:placetype":"venue"
},
  "geometry": {"coordinates":[-80.089592,40.388366],"type":"Point"}
}