{
  "type": "Feature",
  "properties": {
    "iso:country":"US",
    "sg:address":"400 Middletown Blvd",
    "sg:city":"Langhorne",
    "sg:classifiers":[
        {
            "category":"Health Services",
            "subcategory":"Doctor",
            "type":"Services"
        }
    ],
    "sg:phone":"+1 215 750 9411",
    "sg:postcode":"19047",
    "sg:province":"PA",
    "sg:tags":[
        "medical"
    ],
    "wof:name":"Delaware Valley Retina Assoc",
    "wof:placetype":"venue"
},
  "geometry": {"coordinates":[-74.88091799999999,40.186629],"type":"Point"}
}