{
  "type": "Feature",
  "properties": {
    "iso:country":"US",
    "sg:address":"955 N Washington St",
    "sg:city":"Orwigsburg",
    "sg:classifiers":[
        {
            "category":"Personal",
            "subcategory":"Tanning Parlor",
            "type":"Services"
        }
    ],
    "sg:phone":"+1 570 366 5044",
    "sg:postcode":"17961",
    "sg:province":"PA",
    "sg:tags":[
        "salon"
    ],
    "wof:name":"Styles Unlimited Tanning",
    "wof:placetype":"venue"
},
  "geometry": {"coordinates":[-76.09114700000001,40.661824],"type":"Point"}
}