{
  "type": "Feature",
  "properties": {
    "addr:full":"2180 MacArthur Rd Whitehall PA 18052",
    "addr:housenumber":"2180",
    "addr:postcode":"18052",
    "addr:street":"Macarthur Rd",
    "iso:country":"US",
    "sg:address":"2180 MacArthur Rd",
    "sg:city":"Whitehall",
    "sg:classifiers":[
        {
            "category":"Shopping",
            "subcategory":"Stationery & Office Supplies",
            "type":"Retail Goods"
        }
    ],
    "sg:phone":"+1 610 432 0150",
    "sg:postcode":"18052",
    "sg:province":"PA",
    "sg:tags":[
        "equipment"
    ],
    "sg:website":"www.staples.com",
    "wof:name":"Staples",
    "wof:placetype":"venue"
},
  "geometry": {"coordinates":[-75.48845300000001,40.637031],"type":"Point"}
}