{
  "type": "Feature",
  "properties": {
    "addr:full":"10 N Main St Pittston PA 18640",
    "addr:housenumber":"10",
    "addr:postcode":"18640",
    "addr:street":"N Main St",
    "iso:country":"US",
    "sg:address":"10 N Main St",
    "sg:city":"Pittston",
    "sg:classifiers":[
        {
            "category":"Social Services",
            "type":"Services"
        }
    ],
    "sg:phone":"+1 570 655 2255",
    "sg:postcode":"18640",
    "sg:province":"PA",
    "sg:tags":[
        "organization",
        "welfare"
    ],
    "sg:website":"www.greaterpittstonymca.org",
    "wof:name":"YMCA",
    "wof:placetype":"venue"
},
  "geometry": {"coordinates":[-75.79021899999999,41.323231],"type":"Point"}
}