{
  "type": "Feature",
  "properties": {
    "iso:country":"US",
    "sg:address":"10 Ruthland Ave",
    "sg:city":"Malvern",
    "sg:classifiers":[
        {
            "category":"Professional",
            "type":"Services"
        }
    ],
    "sg:phone":"+1 610 407 4472",
    "sg:postcode":"19355",
    "sg:province":"PA",
    "sg:tags":[
        "arts",
        "artist"
    ],
    "wof:name":"Custom Artwork",
    "wof:placetype":"venue"
},
  "geometry": {"coordinates":[-75.508262,40.036515],"type":"Point"}
}