{
  "type": "Feature",
  "properties": {
    "iso:country":"US",
    "sg:address":"1760 Dekalb Pike",
    "sg:city":"Blue Bell",
    "sg:classifiers":[
        {
            "category":"Banks & Credit Unions",
            "subcategory":"Bank",
            "type":"Services"
        }
    ],
    "sg:phone":"+1 610 279 4849",
    "sg:postcode":"19422",
    "sg:province":"PA",
    "wof:name":"Commonwealth Bank",
    "wof:placetype":"venue"
},
  "geometry": {"coordinates":[-75.307053,40.149126],"type":"Point"}
}