{
  "type": "Feature",
  "properties": {
    "addr:full":"11676 Perry Hwy Wexford PA 15090",
    "addr:housenumber":"11676",
    "addr:postcode":"15090",
    "addr:street":"Perry Hwy",
    "iso:country":"US",
    "sg:address":"11676 Perry Hwy",
    "sg:city":"Wexford",
    "sg:classifiers":[
        {
            "category":"Health Services",
            "subcategory":"Doctor",
            "type":"Services"
        }
    ],
    "sg:phone":"+1 724 935 9133",
    "sg:postcode":"15090",
    "sg:province":"PA",
    "sg:tags":[
        "dermatologist"
    ],
    "wof:name":"Abell Debra T MD",
    "wof:placetype":"venue"
},
  "geometry": {"coordinates":[-80.0569,40.629902],"type":"Point"}
}