{
  "type": "Feature",
  "properties": {
    "addr:full":"2026 Ridge Ave Philadelphia PA 19121",
    "addr:housenumber":"2026",
    "addr:postcode":"19121",
    "addr:street":"Ridge Ave",
    "iso:country":"US",
    "sg:address":"2026 Ridge Ave",
    "sg:city":"Philadelphia",
    "sg:classifiers":[
        {
            "category":"Social Services",
            "type":"Services"
        }
    ],
    "sg:phone":"+1 215 236 8070",
    "sg:postcode":"19121",
    "sg:province":"PA",
    "sg:tags":[
        "organization",
        "welfare"
    ],
    "wof:name":"Christ Mission Inc",
    "wof:placetype":"venue"
},
  "geometry": {"coordinates":[-75.169044,39.976386],"type":"Point"}
}