{
  "type": "Feature",
  "properties": {
    "iso:country":"US",
    "sg:address":"2244 Chalfant St",
    "sg:city":"Pittsburgh",
    "sg:classifiers":[
        {
            "category":"Building & Trades",
            "subcategory":"Plumbing",
            "type":"Services"
        }
    ],
    "sg:phone":"+1   ",
    "sg:postcode":"15221",
    "sg:province":"PA",
    "sg:tags":[
        "contractor"
    ],
    "wof:name":"A1 Plmbing Heating",
    "wof:placetype":"venue"
},
  "geometry": {"coordinates":[-79.858644,40.452354],"type":"Point"}
}