{
  "type": "Feature",
  "properties": {
    "iso:country":"US",
    "sg:address":"1436 Lansdowne Ave",
    "sg:city":"Darby",
    "sg:classifiers":[
        {
            "category":"Organizations",
            "subcategory":"Religious Organization",
            "type":"Services"
        }
    ],
    "sg:phone":"+1 610 522 1159",
    "sg:postcode":"19023",
    "sg:province":"PA",
    "wof:name":"Graham Thomas Rev",
    "wof:placetype":"venue"
},
  "geometry": {"coordinates":[-75.266403,39.916],"type":"Point"}
}