{
  "type": "Feature",
  "properties": {
    "addr:full":"547 Pottstown Pike Chester Springs PA 19425",
    "addr:housenumber":"547",
    "addr:postcode":"19425",
    "addr:street":"Pottstown Pike",
    "iso:country":"US",
    "sg:address":"547 Pottstown Pike",
    "sg:city":"Chester Springs",
    "sg:classifiers":[
        {
            "category":"Real Estate",
            "subcategory":"Architect",
            "type":"Services"
        }
    ],
    "sg:phone":"+1   ",
    "sg:postcode":"19425",
    "sg:province":"PA",
    "sg:tags":[
        "architectural"
    ],
    "wof:name":"Donald Work Archetech LLC",
    "wof:placetype":"venue"
},
  "geometry": {"coordinates":[-75.692177,40.088179],"type":"Point"}
}