{
  "type": "Feature",
  "properties": {
    "iso:country":"US",
    "sg:address":"146 N Main St",
    "sg:city":"Butler",
    "sg:classifiers":[
        {
            "category":"Food & Beverages",
            "subcategory":"Candy",
            "type":"Retail Goods"
        },
        {
            "category":"Manufacturing",
            "subcategory":"Food",
            "type":"Manufacturing & Wholesale Goods"
        }
    ],
    "sg:phone":"+1 724 287 3287",
    "sg:postcode":"16001",
    "sg:province":"PA",
    "sg:tags":[
        "confectionery"
    ],
    "wof:name":"Cummings Candy & Coffee House",
    "wof:placetype":"venue"
},
  "geometry": {"coordinates":[-79.89530600000001,40.862138],"type":"Point"}
}