{
  "type": "Feature",
  "properties": {
    "iso:country":"US",
    "sg:address":"210 E Lexington Rd",
    "sg:city":"Lititz",
    "sg:classifiers":[
        {
            "category":"Personal",
            "type":"Services"
        }
    ],
    "sg:phone":"+1 717 627 0401",
    "sg:postcode":"17543",
    "sg:province":"PA",
    "wof:name":"Midway Mennonite Reception Ctr",
    "wof:placetype":"venue"
},
  "geometry": {"coordinates":[-76.29716999999999,40.187527],"type":"Point"}
}