{
  "type": "Feature",
  "properties": {
    "iso:country":"US",
    "sg:address":"134 E Main St",
    "sg:city":"Lock Haven",
    "sg:classifiers":[
        {
            "category":"Building & Trades",
            "subcategory":"Equipment Rental",
            "type":"Services"
        }
    ],
    "sg:phone":"+1   ",
    "sg:postcode":"17745",
    "sg:province":"PA",
    "sg:tags":[
        "medical",
        "drug",
        "store"
    ],
    "wof:name":"American Homepatient",
    "wof:placetype":"venue"
},
  "geometry": {"coordinates":[-77.445404,41.137038],"type":"Point"}
}