{
  "type": "Feature",
  "properties": {
    "iso:country":"US",
    "sg:address":"1 Bethlehem Plz",
    "sg:city":"Bethlehem",
    "sg:classifiers":[
        {
            "category":"Professional",
            "subcategory":"Management & Consulting",
            "type":"Services"
        }
    ],
    "sg:phone":"+1   ",
    "sg:postcode":"18018",
    "sg:province":"PA",
    "wof:name":"Hp3 Inc",
    "wof:placetype":"venue"
},
  "geometry": {"coordinates":[-75.38052399999999,40.622339],"type":"Point"}
}