{
  "type": "Feature",
  "properties": {
    "iso:country":"US",
    "sg:address":"820 Stanton Ave",
    "sg:city":"Pittsburgh",
    "sg:classifiers":[
        {
            "category":"Health Services",
            "subcategory":"Doctor",
            "type":"Services"
        }
    ],
    "sg:phone":"+1 412 821 4025",
    "sg:postcode":"15209",
    "sg:province":"PA",
    "sg:tags":[
        "dentist"
    ],
    "wof:name":"Sitterle George R DDS",
    "wof:placetype":"venue"
},
  "geometry": {"coordinates":[-79.979462,40.480453],"type":"Point"}
}