{
  "type": "Feature",
  "properties": {
    "iso:country":"US",
    "sg:address":"2223 Park Rd",
    "sg:city":"Coal Township",
    "sg:classifiers":[
        {
            "category":"Health Services",
            "subcategory":"Doctor",
            "type":"Services"
        }
    ],
    "sg:phone":"+1   ",
    "sg:postcode":"17866",
    "sg:province":"PA",
    "sg:tags":[
        "medical"
    ],
    "wof:name":"Edward V Twiggar II MD",
    "wof:placetype":"venue"
},
  "geometry": {"coordinates":[-76.58937400000001,40.784457],"type":"Point"}
}