{
  "type": "Feature",
  "properties": {
    "iso:country":"US",
    "sg:address":"1650 Huntingdon Pike",
    "sg:city":"Jenkintown",
    "sg:classifiers":[
        {
            "category":"Health Services",
            "subcategory":"Doctor",
            "type":"Services"
        }
    ],
    "sg:phone":"+1 215 947 6556",
    "sg:postcode":"19046",
    "sg:province":"PA",
    "sg:tags":[
        "physician",
        "medical",
        "surgeon"
    ],
    "wof:name":"Urology Group Inc",
    "wof:placetype":"venue"
},
  "geometry": {"coordinates":[-75.08234899999999,40.108305],"type":"Point"}
}