{
  "type": "Feature",
  "properties": {
    "iso:country":"US",
    "sg:address":"113 N Essex Ave",
    "sg:city":"Narberth",
    "sg:classifiers":[
        {
            "category":"Professional",
            "subcategory":"Management & Consulting",
            "type":"Services"
        }
    ],
    "sg:phone":"+1 610 668 8207",
    "sg:postcode":"19072",
    "sg:province":"PA",
    "sg:tags":[
        "marketing",
        "consultant"
    ],
    "sg:website":"www.usacoin.com",
    "wof:name":"Philadelphia International",
    "wof:placetype":"venue"
},
  "geometry": {"coordinates":[-75.262501,40.006273],"type":"Point"}
}