{
  "type": "Feature",
  "properties": {
    "iso:country":"US",
    "sg:address":"24 Buck Run Rd",
    "sg:city":"Claysville",
    "sg:classifiers":[
        {
            "category":"Manufacturing",
            "subcategory":"Tools & Machinery",
            "type":"Manufacturing & Wholesale Goods"
        }
    ],
    "sg:phone":"+1   ",
    "sg:postcode":"15323",
    "sg:province":"PA",
    "sg:tags":[
        "recording",
        "medium",
        "mfg"
    ],
    "wof:name":"Misc",
    "wof:placetype":"venue"
},
  "geometry": {"coordinates":[-80.424043,40.137453],"type":"Point"}
}