{
  "type": "Feature",
  "properties": {
    "iso:country":"US",
    "sg:address":"501 Knightsbridge Ct",
    "sg:city":"Bensalem",
    "sg:classifiers":[
        {
            "category":"Health Services",
            "subcategory":"Clinic",
            "type":"Services"
        }
    ],
    "sg:phone":"+1 215 245 2616",
    "sg:postcode":"19020",
    "sg:province":"PA",
    "sg:tags":[
        "home"
    ],
    "wof:name":"Home Watch Caregivers",
    "wof:placetype":"venue"
},
  "geometry": {"coordinates":[-74.979359,40.056861],"type":"Point"}
}