{
  "type": "Feature",
  "properties": {
    "iso:country":"US",
    "sg:address":"147 N 10th St",
    "sg:city":"Philadelphia",
    "sg:classifiers":[
        {
            "category":"Banks & Credit Unions",
            "subcategory":"Bank",
            "type":"Services"
        }
    ],
    "sg:phone":"+1 215 627 9200",
    "sg:postcode":"19107",
    "sg:province":"PA",
    "sg:tags":[
        "federal",
        "commercial",
        "saving",
        "institution"
    ],
    "sg:website":"www.abacusbank.com",
    "wof:name":"Abacus Federal Savings Bank",
    "wof:placetype":"venue"
},
  "geometry": {"coordinates":[-75.15619700000001,39.954899],"type":"Point"}
}