{
  "type": "Feature",
  "properties": {
    "iso:country":"US",
    "sg:address":"332 S President Ave",
    "sg:city":"Lancaster",
    "sg:classifiers":[
        {
            "category":"Shopping",
            "type":"Retail Goods"
        }
    ],
    "sg:phone":"+1   ",
    "sg:postcode":"17603",
    "sg:province":"PA",
    "sg:tags":[
        "merchandise"
    ],
    "wof:name":"American Ramp Systems",
    "wof:placetype":"venue"
},
  "geometry": {"coordinates":[-76.331478,40.03296],"type":"Point"}
}