{
  "type": "Feature",
  "properties": {
    "addr:full":"1840 South St Philadelphia PA 19146",
    "addr:housenumber":"1840",
    "addr:postcode":"19146",
    "addr:street":"South St",
    "iso:country":"US",
    "sg:address":"1840 South St",
    "sg:city":"Philadelphia",
    "sg:classifiers":[
        {
            "category":"Health Services",
            "subcategory":"Clinic",
            "type":"Services"
        }
    ],
    "sg:phone":"+1   ",
    "sg:postcode":"19146",
    "sg:province":"PA",
    "sg:tags":[
        "kidney",
        "dialysis",
        "center"
    ],
    "wof:name":"Graduate Dialysis Center 2678",
    "wof:placetype":"venue"
},
  "geometry": {"coordinates":[-75.172999,39.944484],"type":"Point"}
}