{
  "type": "Feature",
  "properties": {
    "iso:country":"US",
    "sg:address":"36 Hillcrest Ave",
    "sg:city":"Leola",
    "sg:classifiers":[
        {
            "category":"Government",
            "subcategory":"City Hall",
            "type":"Public Place"
        },
        {
            "category":"Government",
            "subcategory":"Office",
            "type":"Public Place"
        }
    ],
    "sg:phone":"+1 717 656 9755",
    "sg:postcode":"17540",
    "sg:province":"PA",
    "sg:tags":[
        "town",
        "township",
        "planner",
        "government-city",
        "village"
    ],
    "sg:website":"http://www.ultwp.com",
    "wof:name":"Upper Leacock Township",
    "wof:placetype":"venue"
},
  "geometry": {"coordinates":[-76.18661,40.086512],"type":"Point"}
}