{
  "type": "Feature",
  "properties": {
    "iso:country":"US",
    "sg:address":"1337 3rd St",
    "sg:city":"Beaver",
    "sg:classifiers":[
        {
            "category":"Banks & Credit Unions",
            "subcategory":"Investment Brokerage",
            "type":"Services"
        }
    ],
    "sg:phone":"+1 724 728 0400",
    "sg:postcode":"15009",
    "sg:province":"PA",
    "sg:tags":[
        "security"
    ],
    "wof:name":"Janney Montgomery Scott LLC",
    "wof:placetype":"venue"
},
  "geometry": {"coordinates":[-80.315153,40.690856],"type":"Point"}
}