{
  "type": "Feature",
  "properties": {
    "iso:country":"US",
    "sg:address":"236 N Locust Point Rd",
    "sg:city":"Mechanicsburg",
    "sg:phone":"+1 717 796 2159",
    "sg:postcode":"17050",
    "sg:province":"PA",
    "sg:tags":[
        "oil",
        "gasoline"
    ],
    "wof:name":"Leffler Energy",
    "wof:placetype":"venue"
},
  "geometry": {"coordinates":[-77.07594,40.225874],"type":"Point"}
}