{
  "type": "Feature",
  "properties": {
    "addr:full":"429 Schuylkill Rd Phoenixville PA 19460",
    "addr:housenumber":"429",
    "addr:postcode":"19460",
    "addr:street":"Schuylkill Rd",
    "iso:country":"US",
    "sg:address":"429 Schuylkill Rd",
    "sg:city":"Phoenixville",
    "sg:classifiers":[
        {
            "category":"Real Estate",
            "subcategory":"Real Estate Agent",
            "type":"Services"
        }
    ],
    "sg:phone":"+1 484 921 5200",
    "sg:postcode":"19460",
    "sg:province":"PA",
    "wof:name":"Assist 2 Sell Sellers & Buyers",
    "wof:placetype":"venue"
},
  "geometry": {"coordinates":[-75.547611,40.141568],"type":"Point"}
}