{
  "type": "Feature",
  "properties": {
    "iso:country":"US",
    "sg:address":"1551 McKean St",
    "sg:city":"Philadelphia",
    "sg:classifiers":[
        {
            "category":"Food & Beverages",
            "subcategory":"Groceries & Convenience Stores",
            "type":"Retail Goods"
        }
    ],
    "sg:phone":"+1   ",
    "sg:postcode":"19145",
    "sg:province":"PA",
    "wof:name":"Media Variety",
    "wof:placetype":"venue"
},
  "geometry": {"coordinates":[-75.17253100000001,39.92607],"type":"Point"}
}