{
  "type": "Feature",
  "properties": {
    "addr:full":"1263 Baltimore Pike Media PA 19063",
    "addr:housenumber":"1263",
    "addr:postcode":"19063",
    "addr:street":"Baltimore Pike",
    "iso:country":"US",
    "sg:address":"1263 Baltimore Pike",
    "sg:city":"Media",
    "sg:classifiers":[
        {
            "category":"Autos & Motor Vehicles",
            "subcategory":"Automobile Sales",
            "type":"Retail Goods"
        }
    ],
    "sg:phone":"+1 610 566 8600",
    "sg:postcode":"19063",
    "sg:province":"PA",
    "sg:tags":[
        "car",
        "dealer"
    ],
    "wof:name":"Thomas Chevrolet Inc",
    "wof:placetype":"venue"
},
  "geometry": {"coordinates":[-75.444129,39.910956],"type":"Point"}
}