{
  "type": "Feature",
  "properties": {
    "addr:full":"1302 Commerce Park Dr Williamsport PA 17701",
    "addr:housenumber":"1302",
    "addr:postcode":"17701",
    "addr:street":"Commerce Park Dr",
    "iso:country":"US",
    "sg:address":"1302 Commerce Park Dr",
    "sg:city":"Williamsport",
    "sg:classifiers":[
        {
            "category":"Organizations",
            "subcategory":"Religious Organization",
            "type":"Services"
        }
    ],
    "sg:phone":"+1 570 323 6080",
    "sg:postcode":"17701",
    "sg:province":"PA",
    "sg:tags":[
        "church"
    ],
    "wof:name":"Christ Community Church",
    "wof:placetype":"venue"
},
  "geometry": {"coordinates":[-76.98188,41.247137],"type":"Point"}
}