{
  "type": "Feature",
  "properties": {
    "iso:country":"US",
    "sg:address":"505 Centre St",
    "sg:city":"Freeland",
    "sg:classifiers":[
        {
            "category":"Shopping",
            "subcategory":"Florist",
            "type":"Retail Goods"
        }
    ],
    "sg:phone":"+1 570 636 1768",
    "sg:postcode":"18224",
    "sg:province":"PA",
    "wof:name":"Buds For You",
    "wof:placetype":"venue"
},
  "geometry": {"coordinates":[-75.897396,41.016895],"type":"Point"}
}