{
  "type": "Feature",
  "properties": {
    "addr:full":"18 River Rd Sewickley PA 15143",
    "addr:housenumber":"18",
    "addr:postcode":"15143",
    "addr:street":"River Rd",
    "iso:country":"US",
    "sg:address":"18 River Rd",
    "sg:city":"Sewickley",
    "sg:classifiers":[
        {
            "category":"Government",
            "subcategory":"Office",
            "type":"Public Place"
        }
    ],
    "sg:phone":"+1 412 741 5038",
    "sg:postcode":"15143",
    "sg:province":"PA",
    "sg:tags":[
        "village"
    ],
    "wof:name":"Haysville Boro Office",
    "wof:placetype":"venue"
},
  "geometry": {"coordinates":[-80.15888,40.526807],"type":"Point"}
}