{
  "type": "Feature",
  "properties": {
    "iso:country":"US",
    "sg:address":"1330 Market St",
    "sg:city":"Mc Keesport",
    "sg:classifiers":[
        {
            "category":"Wholesale",
            "subcategory":"Machinery & Supplies",
            "type":"Manufacturing & Wholesale Goods"
        }
    ],
    "sg:phone":"+1   ",
    "sg:postcode":"15132",
    "sg:province":"PA",
    "sg:tags":[
        "treating",
        "heat",
        "industrial",
        "metal",
        "nonferrous"
    ],
    "wof:name":"Wahl Refractories Inc",
    "wof:placetype":"venue"
},
  "geometry": {"coordinates":[-79.862745,40.341156],"type":"Point"}
}