{
  "type": "Feature",
  "properties": {
    "addr:full":"3600 Sheaff Ln Philadelphia PA 19145",
    "addr:housenumber":"3600",
    "addr:postcode":"19145",
    "addr:street":"Sheaff Ln",
    "iso:country":"US",
    "sg:address":"3600 Sheaff Ln",
    "sg:city":"Philadelphia",
    "sg:classifiers":[
        {
            "category":"Health Services",
            "subcategory":"Health Practitioner",
            "type":"Services"
        }
    ],
    "sg:phone":"+1 610 874 4783",
    "sg:postcode":"19145",
    "sg:province":"PA",
    "sg:tags":[
        "nurse",
        "registry"
    ],
    "wof:name":"Sally M Steele",
    "wof:placetype":"venue"
},
  "geometry": {"coordinates":[-75.191901,39.902854],"type":"Point"}
}