{
  "type": "Feature",
  "properties": {
    "iso:country":"US",
    "sg:address":"200 S Sumner St",
    "sg:city":"York",
    "sg:classifiers":[
        {
            "category":"Retail",
            "subcategory":"Auto Rental",
            "type":"Services"
        }
    ],
    "sg:phone":"+1   ",
    "sg:postcode":"17404",
    "sg:province":"PA",
    "sg:tags":[
        "passenger",
        "car"
    ],
    "wof:name":"Big Ugly Warehouse",
    "wof:placetype":"venue"
},
  "geometry": {"coordinates":[-76.764578,39.949713],"type":"Point"}
}