{
  "type": "Feature",
  "properties": {
    "iso:country":"US",
    "sg:address":"1720 Georgetown Rd",
    "sg:city":"Volant",
    "sg:classifiers":[
        {
            "category":"Farming",
            "subcategory":"Dairy Farm",
            "type":"Manufacturing & Wholesale Goods"
        }
    ],
    "sg:phone":"+1   ",
    "sg:postcode":"16156",
    "sg:province":"PA",
    "wof:name":"Hillcrest Jersey Farm",
    "wof:placetype":"venue"
},
  "geometry": {"coordinates":[-80.18067000000001,41.064474],"type":"Point"}
}