{
  "type": "Feature",
  "properties": {
    "addr:full":"240 N 6th St Chambersburg PA 17201",
    "addr:housenumber":"240",
    "addr:postcode":"17201",
    "addr:street":"N 6Th St",
    "iso:country":"US",
    "sg:address":"240 N 6th St",
    "sg:city":"Chambersburg",
    "sg:classifiers":[
        {
            "category":"Real Estate",
            "subcategory":"Real Estate Operator",
            "type":"Services"
        }
    ],
    "sg:phone":"+1   ",
    "sg:postcode":"17201",
    "sg:province":"PA",
    "sg:tags":[
        "building",
        "apartment"
    ],
    "wof:name":"Brandon Arms Apartments",
    "wof:placetype":"venue"
},
  "geometry": {"coordinates":[-77.64706,39.937256],"type":"Point"}
}