{
  "type": "Feature",
  "properties": {
    "addr:full":"1103 Mount Royal Blvd Pittsburgh PA 15223",
    "addr:housenumber":"1103",
    "addr:postcode":"15223",
    "addr:street":"Mount Royal Blvd",
    "iso:country":"US",
    "sg:address":"1103 Mount Royal Blvd",
    "sg:city":"Pittsburgh",
    "sg:classifiers":[
        {
            "category":"Real Estate",
            "subcategory":"Real Estate Operator",
            "type":"Services"
        }
    ],
    "sg:phone":"+1 412 492 0246",
    "sg:postcode":"15223",
    "sg:province":"PA",
    "sg:tags":[
        "apartment"
    ],
    "wof:name":"Villa Royal",
    "wof:placetype":"venue"
},
  "geometry": {"coordinates":[-79.959051,40.517631],"type":"Point"}
}