{
  "type": "Feature",
  "properties": {
    "addr:full":"335 E 10th Ave Homestead PA 15120",
    "addr:housenumber":"335",
    "addr:postcode":"15120",
    "addr:street":"E 10Th Ave",
    "iso:country":"US",
    "sg:address":"335 E 10th Ave",
    "sg:city":"Homestead",
    "sg:classifiers":[
        {
            "category":"Organizations",
            "subcategory":"Religious Organization",
            "type":"Services"
        }
    ],
    "sg:phone":"+1 412 461 5530",
    "sg:postcode":"15120",
    "sg:province":"PA",
    "sg:tags":[
        "church"
    ],
    "wof:name":"Community Of The Crucified One",
    "wof:placetype":"venue"
},
  "geometry": {"coordinates":[-79.906868,40.407123],"type":"Point"}
}