{
  "type": "Feature",
  "properties": {
    "iso:country":"US",
    "sg:address":"606 Greenbriar Ct",
    "sg:city":"Chalfont",
    "sg:classifiers":[
        {
            "category":"Building & Trades",
            "subcategory":"Construction",
            "type":"Services"
        }
    ],
    "sg:phone":"+1   ",
    "sg:postcode":"18914",
    "sg:province":"PA",
    "sg:tags":[
        "concrete",
        "contractor"
    ],
    "wof:name":"Form Tech Construction Co Inc",
    "wof:placetype":"venue"
},
  "geometry": {"coordinates":[-75.189441,40.277941],"type":"Point"}
}