{
  "type": "Feature",
  "properties": {
    "iso:country":"US",
    "sg:address":"1001 Lehigh Ave",
    "sg:city":"Lancaster",
    "sg:classifiers":[
        {
            "category":"Education",
            "subcategory":"School",
            "type":"Public Place"
        }
    ],
    "sg:phone":"+1   ",
    "sg:postcode":"17602",
    "sg:province":"PA",
    "wof:name":"Lincoln Junior High School",
    "wof:placetype":"venue"
},
  "geometry": {"coordinates":[-76.28585099999999,40.04626],"type":"Point"}
}