{
  "type": "Feature",
  "properties": {
    "iso:country":"US",
    "sg:address":"2657 Monroeville Blvd",
    "sg:city":"Monroeville",
    "sg:classifiers":[
        {
            "category":"Professional",
            "subcategory":"Accounting & Tax Preparation",
            "type":"Services"
        }
    ],
    "sg:phone":"+1   ",
    "sg:postcode":"15146",
    "sg:province":"PA",
    "sg:tags":[
        "accountant",
        "public",
        "certified"
    ],
    "wof:name":"Warwick Lewis CPA",
    "wof:placetype":"venue"
},
  "geometry": {"coordinates":[-79.783282,40.434145],"type":"Point"}
}