{
  "type": "Feature",
  "properties": {
    "iso:country":"US",
    "sg:address":"40 Freedom Dr N",
    "sg:city":"Bridgeville",
    "sg:classifiers":[
        {
            "category":"Fast Food",
            "type":"Food & Drink"
        },
        {
            "category":"Restaurant",
            "type":"Food & Drink"
        }
    ],
    "sg:phone":"+1 412 221 5364",
    "sg:postcode":"15017",
    "sg:province":"PA",
    "sg:tags":[
        "take"
    ],
    "wof:name":"Wendy Moore",
    "wof:placetype":"venue"
},
  "geometry": {"coordinates":[-80.114367,40.345652],"type":"Point"}
}