{
  "type": "Feature",
  "properties": {
    "iso:country":"US",
    "sg:address":"48 Woodhill Rd",
    "sg:city":"Newtown",
    "sg:classifiers":[
        {
            "category":"Professional",
            "subcategory":"Management & Consulting",
            "type":"Services"
        }
    ],
    "sg:phone":"+1   ",
    "sg:postcode":"18940",
    "sg:province":"PA",
    "sg:tags":[
        "retail",
        "direct",
        "sales"
    ],
    "wof:name":"Mark P Young",
    "wof:placetype":"venue"
},
  "geometry": {"coordinates":[-74.944688,40.29232],"type":"Point"}
}