{
  "type": "Feature",
  "properties": {
    "iso:country":"US",
    "sg:address":"190 Quinn Dr",
    "sg:city":"Pittsburgh",
    "sg:classifiers":[
        {
            "category":"Shopping",
            "subcategory":"Shoes",
            "type":"Retail Goods"
        }
    ],
    "sg:phone":"+1 412 788 6970",
    "sg:postcode":"15275",
    "sg:province":"PA",
    "sg:tags":[
        "store"
    ],
    "sg:website":"www.shoecarnival.com",
    "wof:name":"Shoe Carnival",
    "wof:placetype":"venue"
},
  "geometry": {"coordinates":[-80.177878,40.446095],"type":"Point"}
}