{
  "type": "Feature",
  "properties": {
    "addr:full":"201 Hansell Rd Newtown Square PA 19073",
    "addr:housenumber":"201",
    "addr:postcode":"19073",
    "addr:street":"Hansell Rd",
    "iso:country":"US",
    "sg:address":"201 Hansell Rd",
    "sg:city":"Newtown Square",
    "sg:classifiers":[
        {
            "category":"Building & Trades",
            "subcategory":"Landscaping Services",
            "type":"Services"
        }
    ],
    "sg:phone":"+1   ",
    "sg:postcode":"19073",
    "sg:province":"PA",
    "sg:tags":[
        "tree",
        "shrub"
    ],
    "wof:name":"Arborway Tree Service",
    "wof:placetype":"venue"
},
  "geometry": {"coordinates":[-75.38767300000001,40.000305],"type":"Point"}
}