{
  "type": "Feature",
  "properties": {
    "iso:country":"US",
    "sg:address":"145 York St",
    "sg:city":"Gettysburg",
    "sg:classifiers":[
        {
            "category":"Social Services",
            "subcategory":"Child Care",
            "type":"Services"
        },
        {
            "category":"Food & Beverages",
            "subcategory":"Bakery",
            "type":"Retail Goods"
        }
    ],
    "sg:phone":"+1 717 334 4580",
    "sg:postcode":"17325",
    "sg:province":"PA",
    "sg:tags":[
        "baker",
        "day"
    ],
    "wof:name":"Flour Child Baking Company",
    "wof:placetype":"venue"
},
  "geometry": {"coordinates":[-77.22749899999999,39.830886],"type":"Point"}
}