{
  "type": "Feature",
  "properties": {
    "addr:full":"1133 E 3rd St Bethlehem PA 18015",
    "addr:housenumber":"1133",
    "addr:postcode":"18015",
    "addr:street":"E 3Rd St",
    "iso:country":"US",
    "sg:address":"1133 E 3rd St",
    "sg:city":"Bethlehem",
    "sg:classifiers":[
        {
            "category":"Building & Trades",
            "subcategory":"Construction",
            "type":"Services"
        }
    ],
    "sg:phone":"+1 610 867 0477",
    "sg:postcode":"18015",
    "sg:province":"PA",
    "sg:tags":[
        "mobile",
        "home"
    ],
    "wof:name":"Manufactured Home Svc",
    "wof:placetype":"venue"
},
  "geometry": {"coordinates":[-75.36230500000001,40.612513],"type":"Point"}
}