{
  "type": "Feature",
  "properties": {
    "iso:country":"US",
    "sg:address":"1309 Bridge St",
    "sg:city":"New Cumberland",
    "sg:classifiers":[
        {
            "category":"Communications",
            "subcategory":"Newspaper",
            "type":"Services"
        }
    ],
    "sg:phone":"+1 717 770 0140",
    "sg:postcode":"17070",
    "sg:province":"PA",
    "sg:tags":[
        "print",
        "medium"
    ],
    "wof:name":"On-Line Publishers",
    "wof:placetype":"venue"
},
  "geometry": {"coordinates":[-76.875227,40.234087],"type":"Point"}
}