{
  "type": "Feature",
  "properties": {
    "iso:country":"US",
    "sg:address":"6 S Main St",
    "sg:city":"Morrisville",
    "sg:classifiers":[
        {
            "category":"Shopping",
            "subcategory":"Used Merchandise",
            "type":"Retail Goods"
        }
    ],
    "sg:phone":"+1   ",
    "sg:postcode":"19067",
    "sg:province":"PA",
    "wof:name":"Antiques In Yardley",
    "wof:placetype":"venue"
},
  "geometry": {"coordinates":[-74.838459,40.242215],"type":"Point"}
}