{
  "type": "Feature",
  "properties": {
    "iso:country":"US",
    "sg:address":"1350 Schuylkill Ave",
    "sg:city":"Philadelphia",
    "sg:classifiers":[
        {
            "category":"Freight",
            "type":"Transportation"
        }
    ],
    "sg:phone":"+1 215 389 0688",
    "sg:postcode":"19146",
    "sg:province":"PA",
    "wof:name":"76 Carriage Co",
    "wof:placetype":"venue"
},
  "geometry": {"coordinates":[-75.20340299999999,39.939166],"type":"Point"}
}