{
  "type": "Feature",
  "properties": {
    "iso:country":"US",
    "sg:address":"2992 Hadley Rd",
    "sg:city":"Hadley",
    "sg:classifiers":[
        {
            "category":"Home & Garden",
            "subcategory":"Carpets & Floor Coverings",
            "type":"Retail Goods"
        }
    ],
    "sg:phone":"+1 724 253 3832",
    "sg:postcode":"16130",
    "sg:province":"PA",
    "sg:tags":[
        "dealer",
        "rug"
    ],
    "wof:name":"Shipton's Carpet Co",
    "wof:placetype":"venue"
},
  "geometry": {"coordinates":[-80.25783300000001,41.413289],"type":"Point"}
}