{
  "type": "Feature",
  "properties": {
    "iso:country":"US",
    "sg:address":"1500 Little Lehigh Dr N",
    "sg:city":"Emmaus",
    "sg:classifiers":[
        {
            "category":"Banks & Credit Unions",
            "subcategory":"Investment Brokerage",
            "type":"Services"
        }
    ],
    "sg:phone":"+1   ",
    "sg:postcode":"18049",
    "sg:province":"PA",
    "sg:tags":[
        "security"
    ],
    "wof:name":"East Penn Investment Services",
    "wof:placetype":"venue"
},
  "geometry": {"coordinates":[-75.516797,40.540351],"type":"Point"}
}