{
  "type": "Feature",
  "properties": {
    "iso:country":"US",
    "sg:address":"151 Rivercrest Dr",
    "sg:city":"Coraopolis",
    "sg:classifiers":[
        {
            "category":"Professional",
            "subcategory":"Engineering",
            "type":"Services"
        }
    ],
    "sg:phone":"+1   ",
    "sg:postcode":"15108",
    "sg:province":"PA",
    "wof:name":"J C Engineering Corp Com",
    "wof:placetype":"venue"
},
  "geometry": {"coordinates":[-80.195261,40.530795],"type":"Point"}
}