{
  "type": "Feature",
  "properties": {
    "addr:full":"820 2nd Ave Altoona PA 16602",
    "addr:housenumber":"820",
    "addr:postcode":"16602",
    "addr:street":"2Nd Ave",
    "iso:country":"US",
    "sg:address":"820 2nd Ave",
    "sg:city":"Altoona",
    "sg:classifiers":[
        {
            "category":"Organizations",
            "subcategory":"Community Association",
            "type":"Services"
        }
    ],
    "sg:phone":"+1 814 943 5727",
    "sg:postcode":"16602",
    "sg:province":"PA",
    "sg:tags":[
        "club",
        "social"
    ],
    "wof:name":"Concordia Society",
    "wof:placetype":"venue"
},
  "geometry": {"coordinates":[-78.390013,40.513495],"type":"Point"}
}