{
  "type": "Feature",
  "properties": {
    "iso:country":"US",
    "sg:address":"3619 Forbes Ave",
    "sg:city":"Pittsburgh",
    "sg:classifiers":[
        {
            "category":"Coffee & Tea",
            "type":"Food & Drink"
        }
    ],
    "sg:menulink":"http://www.allmenus.com/pa/pittsburgh/221298-caribou-coffee/menu/",
    "sg:phone":"+1 412 687 2617",
    "sg:postcode":"15213",
    "sg:province":"PA",
    "sg:tags":[
        "american",
        "diner"
    ],
    "wof:name":"Caribou Coffee",
    "wof:placetype":"venue"
},
  "geometry": {"coordinates":[-79.958252,40.44067],"type":"Point"}
}