{
  "type": "Feature",
  "properties": {
    "addr:full":"1039 W County Line Rd Hatboro PA 19040",
    "addr:housenumber":"1039",
    "addr:postcode":"19040",
    "addr:street":"W County Line Rd",
    "iso:country":"US",
    "sg:address":"1039 W County Line Rd",
    "sg:city":"Hatboro",
    "sg:classifiers":[
        {
            "category":"Wholesale",
            "subcategory":"Painting Supplies",
            "type":"Manufacturing & Wholesale Goods"
        },
        {
            "category":"Manufacturing",
            "subcategory":"Tools & Machinery",
            "type":"Manufacturing & Wholesale Goods"
        },
        {
            "category":"Building & Trades",
            "subcategory":"Construction",
            "type":"Services"
        },
        {
            "category":"Home & Garden",
            "subcategory":"Building Materials",
            "type":"Retail Goods"
        },
        {
            "category":"Manufacturing",
            "subcategory":"Chemicals & Compounds",
            "type":"Manufacturing & Wholesale Goods"
        },
        {
            "category":"Autos & Motor Vehicles",
            "subcategory":"Auto Supplies",
            "type":"Retail Goods"
        },
        {
            "category":"Building & Trades",
            "subcategory":"Equipment Rental",
            "type":"Services"
        },
        {
            "category":"Manufacturing",
            "subcategory":"Building Materials",
            "type":"Manufacturing & Wholesale Goods"
        }
    ],
    "sg:phone":"+1 215 675 7445",
    "sg:postcode":"19040",
    "sg:province":"PA",
    "sg:tags":[
        "shop",
        "body",
        "spraying",
        "wall",
        "automobile",
        "wallpaper",
        "coating",
        "improvement",
        "paint-wholesale",
        "paint",
        "wallcoverings-installation",
        "wallcoverings",
        "contractor",
        "equipment-renting",
        "painter",
        "manufacturer"
    ],
    "sg:website":"http://philadelphia.citysearch.com/profile/external/8921057/hatboro_pa/sherwin_williams.html?publisher=yellowpages&reference_id=1&placement=ypwebsitemip",
    "wof:name":"Sherwin-Williams",
    "wof:placetype":"venue"
},
  "geometry": {"coordinates":[-75.11987499999999,40.20003],"type":"Point"}
}