{
  "type": "Feature",
  "properties": {
    "addr:full":"121 Broad St Montoursville PA 17754",
    "addr:housenumber":"121",
    "addr:postcode":"17754",
    "addr:street":"Broad St",
    "iso:country":"US",
    "sg:address":"121 Broad St",
    "sg:city":"Montoursville",
    "sg:classifiers":[
        {
            "category":"Retail",
            "subcategory":"Auto Repair",
            "type":"Services"
        }
    ],
    "sg:phone":"+1 570 368 3050",
    "sg:postcode":"17754",
    "sg:province":"PA",
    "sg:tags":[
        "repairing",
        "automobile",
        "general"
    ],
    "wof:name":"Catherman's Garage Inc",
    "wof:placetype":"venue"
},
  "geometry": {"coordinates":[-76.932909,41.250513],"type":"Point"}
}