{
  "type": "Feature",
  "properties": {
    "iso:country":"US",
    "sg:address":"7 Old Ridge Village",
    "sg:city":"Chadds Ford",
    "sg:classifiers":[
        {
            "category":"Shopping",
            "subcategory":"Crafts & Fabrics",
            "type":"Retail Goods"
        }
    ],
    "sg:phone":"+1 610 459 8580",
    "sg:postcode":"19317",
    "sg:province":"PA",
    "sg:tags":[
        "material",
        "needlework",
        "sewing"
    ],
    "sg:website":"www.strawberrysampler.com",
    "wof:name":"Strawberry Sampler Inc",
    "wof:placetype":"venue"
},
  "geometry": {"coordinates":[-75.54734500000001,39.865025],"type":"Point"}
}