{
  "type": "Feature",
  "properties": {
    "addr:full":"432 E 1st St Hazleton PA 18201",
    "addr:housenumber":"432",
    "addr:postcode":"18201",
    "addr:street":"E 1St St",
    "iso:country":"US",
    "sg:address":"432 E 1st St",
    "sg:city":"Hazleton",
    "sg:classifiers":[
        {
            "category":"Organizations",
            "subcategory":"Community Association",
            "type":"Services"
        }
    ],
    "sg:phone":"+1 570 454 2923",
    "sg:postcode":"18201",
    "sg:province":"PA",
    "sg:tags":[
        "club"
    ],
    "wof:name":"Swing Club",
    "wof:placetype":"venue"
},
  "geometry": {"coordinates":[-75.96289,40.962429],"type":"Point"}
}