{
  "type": "Feature",
  "properties": {
    "addr:full":"606 Rose St Lansdowne PA 19050",
    "addr:housenumber":"606",
    "addr:postcode":"19050",
    "addr:street":"Rose St",
    "iso:country":"US",
    "sg:address":"606 Rose St",
    "sg:city":"Lansdowne",
    "sg:classifiers":[
        {
            "category":"Health Services",
            "subcategory":"Clinic",
            "type":"Services"
        }
    ],
    "sg:phone":"+1 267 784 0037",
    "sg:postcode":"19050",
    "sg:province":"PA",
    "sg:tags":[
        "information",
        "planning",
        "family"
    ],
    "wof:name":"Planned 2 Perfection",
    "wof:placetype":"venue"
},
  "geometry": {"coordinates":[-75.248639,39.938471],"type":"Point"}
}