{
  "type": "Feature",
  "properties": {
    "addr:full":"706 Broadway St Mc Kees Rocks PA 15136",
    "addr:housenumber":"706",
    "addr:postcode":"15136",
    "addr:street":"Broadway St Mc Kees Rocks",
    "iso:country":"US",
    "sg:address":"706 Broadway St",
    "sg:city":"Mc Kees Rocks",
    "sg:classifiers":[
        {
            "category":"Building & Trades",
            "subcategory":"Construction",
            "type":"Services"
        }
    ],
    "sg:phone":"+1   ",
    "sg:postcode":"15136",
    "sg:province":"PA",
    "sg:tags":[
        "house"
    ],
    "wof:name":"Vision Home Remodeling",
    "wof:placetype":"venue"
},
  "geometry": {"coordinates":[-80.07328,40.472434],"type":"Point"}
}