{
  "type": "Feature",
  "properties": {
    "iso:country":"US",
    "sg:address":"255 Houser Rd",
    "sg:city":"Home",
    "sg:classifiers":[
        {
            "category":"Bars & Pubs",
            "type":"Food & Drink"
        }
    ],
    "sg:phone":"+1 724 349 2530",
    "sg:postcode":"15747",
    "sg:province":"PA",
    "sg:tags":[
        "tavern"
    ],
    "wof:name":"Sam's Tavern Inc",
    "wof:placetype":"venue"
},
  "geometry": {"coordinates":[-79.132683,40.719872],"type":"Point"}
}