{
  "type": "Feature",
  "properties": {
    "iso:country":"US",
    "sg:address":"808 Broad St",
    "sg:city":"Akron",
    "sg:classifiers":[
        {
            "category":"Health Services",
            "subcategory":"Health Practitioner",
            "type":"Services"
        }
    ],
    "sg:phone":"+1   ",
    "sg:postcode":"17501",
    "sg:province":"PA",
    "wof:name":"Darlene M Weller",
    "wof:placetype":"venue"
},
  "geometry": {"coordinates":[-76.20396599999999,40.155453],"type":"Point"}
}