{
  "type": "Feature",
  "properties": {
    "iso:country":"US",
    "sg:address":"1500 W Chestnut St",
    "sg:city":"Washington",
    "sg:classifiers":[
        {
            "category":"Shopping",
            "subcategory":"Shoes",
            "type":"Retail Goods"
        }
    ],
    "sg:phone":"+1   ",
    "sg:postcode":"15301",
    "sg:province":"PA",
    "sg:tags":[
        "athletic",
        "footwear",
        "leisure"
    ],
    "wof:name":"Finish Line Inc",
    "wof:placetype":"venue"
},
  "geometry": {"coordinates":[-80.27434599999999,40.16448],"type":"Point"}
}