{
  "type": "Feature",
  "properties": {
    "iso:country":"US",
    "sg:address":"2809 Safe Harbor Rd",
    "sg:city":"Millersville",
    "sg:classifiers":[
        {
            "category":"Farming",
            "subcategory":"Farm",
            "type":"Manufacturing & Wholesale Goods"
        }
    ],
    "sg:phone":"+1   ",
    "sg:postcode":"17551",
    "sg:province":"PA",
    "sg:tags":[
        "crop",
        "general"
    ],
    "wof:name":"Sue Harnish Farms",
    "wof:placetype":"venue"
},
  "geometry": {"coordinates":[-76.400963,39.966754],"type":"Point"}
}