{
  "type": "Feature",
  "properties": {
    "iso:country":"US",
    "sg:address":"801 Ostrum St",
    "sg:city":"Bethlehem",
    "sg:classifiers":[
        {
            "category":"Health Services",
            "subcategory":"Hospital",
            "type":"Services"
        },
        {
            "category":"Health Services",
            "subcategory":"Health Practitioner",
            "type":"Services"
        }
    ],
    "sg:phone":"+1 610 954 4330",
    "sg:postcode":"18015",
    "sg:province":"PA",
    "sg:tags":[
        "nutritionist"
    ],
    "wof:name":"St Luke's Hospital-Outpatient Nutritional Counslng",
    "wof:placetype":"venue"
},
  "geometry": {"coordinates":[-75.392998,40.6082],"type":"Point"}
}