{
  "type": "Feature",
  "properties": {
    "iso:country":"US",
    "sg:address":"6 E Hinckley Ave",
    "sg:city":"Ridley Park",
    "sg:classifiers":[
        {
            "category":"Real Estate",
            "subcategory":"Architect",
            "type":"Services"
        }
    ],
    "sg:phone":"+1 610 521 5060",
    "sg:postcode":"19078",
    "sg:province":"PA",
    "sg:tags":[
        "building",
        "construction"
    ],
    "wof:name":"Tasc Consulting Svc LLC",
    "wof:placetype":"venue"
},
  "geometry": {"coordinates":[-75.322445,39.879542],"type":"Point"}
}