{
  "type": "Feature",
  "properties": {
    "addr:full":"120 W Erie Ave Philadelphia PA 19140",
    "addr:housenumber":"120",
    "addr:postcode":"19140",
    "addr:street":"W Erie Ave",
    "iso:country":"US",
    "sg:address":"120 W Erie Ave",
    "sg:city":"Philadelphia",
    "sg:classifiers":[
        {
            "category":"Food & Beverages",
            "subcategory":"Liquor & Beverages",
            "type":"Retail Goods"
        },
        {
            "category":"Wholesale",
            "subcategory":"Wine & Distilled Alcoholic Beverages",
            "type":"Manufacturing & Wholesale Goods"
        }
    ],
    "sg:phone":"+1 215 423 6916",
    "sg:postcode":"19140",
    "sg:province":"PA",
    "sg:tags":[
        "bottler",
        "beverages-distributors",
        "broker",
        "beer",
        "spirit",
        "store"
    ],
    "wof:name":"Super Value Beverage",
    "wof:placetype":"venue"
},
  "geometry": {"coordinates":[-75.128197,40.007599],"type":"Point"}
}