{
  "type": "Feature",
  "properties": {
    "iso:country":"US",
    "sg:address":"1129 Old Berwick Rd",
    "sg:city":"Bloomsburg",
    "sg:classifiers":[
        {
            "category":"Social Services",
            "subcategory":"Child Care",
            "type":"Services"
        }
    ],
    "sg:phone":"+1   ",
    "sg:postcode":"17815",
    "sg:province":"PA",
    "sg:tags":[
        "day"
    ],
    "wof:name":"Bethesda Day Treatment Center",
    "wof:placetype":"venue"
},
  "geometry": {"coordinates":[-76.43397899999999,41.001649],"type":"Point"}
}