{
  "type": "Feature",
  "properties": {
    "iso:country":"US",
    "sg:address":"325 12th St",
    "sg:city":"Greenville",
    "sg:classifiers":[
        {
            "category":"Real Estate",
            "subcategory":"Real Estate Operator",
            "type":"Services"
        }
    ],
    "sg:phone":"+1 724 646 1450",
    "sg:postcode":"16125",
    "sg:province":"PA",
    "sg:tags":[
        "building",
        "apartment"
    ],
    "wof:name":"Reynolds West Estates",
    "wof:placetype":"venue"
},
  "geometry": {"coordinates":[-80.407691,41.342428],"type":"Point"}
}