{
  "type": "Feature",
  "properties": {
    "iso:country":"US",
    "sg:address":"2251 Fraley St",
    "sg:city":"Philadelphia",
    "sg:classifiers":[
        {
            "category":"Home & Garden",
            "subcategory":"Building Materials",
            "type":"Retail Goods"
        }
    ],
    "sg:phone":"+1 215 743 1370",
    "sg:postcode":"19137",
    "sg:province":"PA",
    "sg:tags":[
        "windows"
    ],
    "wof:name":"JAS Windows & More",
    "wof:placetype":"venue"
},
  "geometry": {"coordinates":[-75.064649,40.010784],"type":"Point"}
}