{
  "type": "Feature",
  "properties": {
    "iso:country":"US",
    "sg:address":"282 Trenton Rd",
    "sg:city":"Fairless Hills",
    "sg:classifiers":[
        {
            "category":"Social Services",
            "subcategory":"Adult Care",
            "type":"Services"
        }
    ],
    "sg:phone":"+1 215 547 6563",
    "sg:postcode":"19030",
    "sg:province":"PA",
    "sg:tags":[
        "organization",
        "senior",
        "citizen"
    ],
    "wof:name":"Falls Township Senior Citizens",
    "wof:placetype":"venue"
},
  "geometry": {"coordinates":[-74.86300199999999,40.174421],"type":"Point"}
}