{
  "type": "Feature",
  "properties": {
    "addr:full":"340 Andrews Rd Feastervl Trvs PA 19053",
    "addr:housenumber":"340",
    "addr:postcode":"19053",
    "addr:street":"Andrews Rd",
    "iso:country":"US",
    "sg:address":"340 Andrews Rd",
    "sg:city":"Feastervl Trvs",
    "sg:classifiers":[
        {
            "category":"Retail",
            "subcategory":"Repair Shop",
            "type":"Services"
        },
        {
            "category":"Building & Trades",
            "subcategory":"Plumbing",
            "type":"Services"
        }
    ],
    "sg:phone":"+1 215 396 8022",
    "sg:postcode":"19053",
    "sg:province":"PA",
    "sg:tags":[
        "conditioning",
        "air",
        "refrigeration",
        "system",
        "contractor"
    ],
    "sg:website":"www.serviceportrefrigeration.com",
    "wof:name":"Service Port Refrigeration Co",
    "wof:placetype":"venue"
},
  "geometry": {"coordinates":[-74.97741499999999,40.156461],"type":"Point"}
}