{
  "type": "Feature",
  "properties": {
    "iso:country":"US",
    "sg:address":"3549 Chestnut St",
    "sg:city":"Philadelphia",
    "sg:classifiers":[
        {
            "category":"Restaurant",
            "type":"Food & Drink"
        }
    ],
    "sg:menulink":"http://www.allmenus.com/pa/philadelphia/291921-sangkee-noodle-house/menu/",
    "sg:phone":"+1 215 387 8808",
    "sg:postcode":"19104",
    "sg:province":"PA",
    "sg:tags":[
        "chinese"
    ],
    "wof:name":"Sangkee Noodle House",
    "wof:placetype":"venue"
},
  "geometry": {"coordinates":[-75.193662,39.954712],"type":"Point"}
}