{
  "type": "Feature",
  "properties": {
    "iso:country":"US",
    "sg:address":"156 Floral Hill Dr",
    "sg:city":"Washington",
    "sg:classifiers":[
        {
            "category":"Education",
            "subcategory":"Special Training",
            "type":"Public Place"
        }
    ],
    "sg:phone":"+1 724 225 2068",
    "sg:postcode":"15301",
    "sg:province":"PA",
    "sg:tags":[
        "instruction",
        "music"
    ],
    "wof:name":"Manfredi Music Studio",
    "wof:placetype":"venue"
},
  "geometry": {"coordinates":[-80.196286,40.178909],"type":"Point"}
}