{
  "type": "Feature",
  "properties": {
    "iso:country":"US",
    "sg:address":"559 3rd Ave",
    "sg:city":"Freedom",
    "sg:classifiers":[
        {
            "category":"Government",
            "subcategory":"Court House",
            "type":"Public Place"
        }
    ],
    "sg:phone":"+1   ",
    "sg:postcode":"15042",
    "sg:province":"PA",
    "sg:tags":[
        "state"
    ],
    "wof:name":"Magisterial District 36-2-01",
    "wof:placetype":"venue"
},
  "geometry": {"coordinates":[-80.256581,40.68799],"type":"Point"}
}