{
  "type": "Feature",
  "properties": {
    "iso:country":"US",
    "sg:address":"1016 13th St",
    "sg:city":"Conway",
    "sg:classifiers":[
        {
            "category":"Bars & Pubs",
            "type":"Food & Drink"
        }
    ],
    "sg:phone":"+1 724 869 0701",
    "sg:postcode":"15027",
    "sg:province":"PA",
    "sg:tags":[
        "drinking"
    ],
    "wof:name":"Conway Lounge",
    "wof:placetype":"venue"
},
  "geometry": {"coordinates":[-80.231995,40.664624],"type":"Point"}
}