{
  "type": "Feature",
  "properties": {
    "iso:country":"US",
    "sg:address":"225 Church St Apt 2C",
    "sg:city":"Philadelphia",
    "sg:classifiers":[
        {
            "category":"Cinema",
            "subcategory":"Movie Theater",
            "type":"Entertainment"
        }
    ],
    "sg:phone":"+1 267 909 3309",
    "sg:postcode":"19106",
    "sg:province":"PA",
    "wof:name":"Nice People Theatre Company",
    "wof:placetype":"venue"
},
  "geometry": {"coordinates":[-75.144471,39.950639],"type":"Point"}
}