{
  "type": "Feature",
  "properties": {
    "iso:country":"US",
    "sg:address":"6242 Mulberry St",
    "sg:city":"Philadelphia",
    "sg:classifiers":[
        {
            "category":"Home & Garden",
            "subcategory":"Building Materials",
            "type":"Retail Goods"
        },
        {
            "category":"Building & Trades",
            "subcategory":"Construction",
            "type":"Services"
        }
    ],
    "sg:phone":"+1 215 437 3357",
    "sg:postcode":"19135",
    "sg:province":"PA",
    "sg:tags":[
        "downspouts",
        "roofing",
        "siding",
        "gutter",
        "contractor"
    ],
    "sg:website":"http://philadelphia.citysearch.com/profile/external/45208409/philadelphia_pa/gutter_gurus.html?publisher=yellowpages&reference_id=15&placement=ypwebsitemip",
    "wof:name":"Gutter Gurus",
    "wof:placetype":"venue"
},
  "geometry": {"coordinates":[-75.060947,40.026951],"type":"Point"}
}