{
  "type": "Feature",
  "properties": {
    "iso:country":"US",
    "sg:address":"710 N Market St",
    "sg:city":"Selinsgrove",
    "sg:classifiers":[
        {
            "category":"Shopping",
            "subcategory":"Computers & Home Electronics",
            "type":"Retail Goods"
        }
    ],
    "sg:phone":"+1 570 374 8764",
    "sg:postcode":"17870",
    "sg:province":"PA",
    "sg:tags":[
        "high",
        "fidelity",
        "stereophonic"
    ],
    "wof:name":"Triad Stage Production",
    "wof:placetype":"venue"
},
  "geometry": {"coordinates":[-76.857636,40.807655],"type":"Point"}
}