{
  "type": "Feature",
  "properties": {
    "iso:country":"US",
    "sg:address":"135 E Nittany Ave",
    "sg:city":"State College",
    "sg:classifiers":[
        {
            "category":"Government",
            "subcategory":"Police Station",
            "type":"Public Place"
        }
    ],
    "sg:phone":"+1 814 234 0341",
    "sg:postcode":"16801",
    "sg:province":"PA",
    "sg:tags":[
        "federal"
    ],
    "wof:name":"Federal Bureau-Investigation",
    "wof:placetype":"venue"
},
  "geometry": {"coordinates":[-77.857103,40.792127],"type":"Point"}
}