{
  "type": "Feature",
  "properties": {
    "addr:full":"232 5th St Freeport PA 16229",
    "addr:housenumber":"232",
    "addr:postcode":"16229",
    "addr:street":"5Th St",
    "iso:country":"US",
    "sg:address":"232 5th St",
    "sg:city":"Freeport",
    "sg:classifiers":[
        {
            "category":"Personal",
            "subcategory":"Beauty Salon",
            "type":"Services"
        }
    ],
    "sg:phone":"+1 724 295 9190",
    "sg:postcode":"16229",
    "sg:province":"PA",
    "wof:name":"Freeport Family Hair Styles",
    "wof:placetype":"venue"
},
  "geometry": {"coordinates":[-79.68535799999999,40.673709],"type":"Point"}
}