{
  "type": "Feature",
  "properties": {
    "iso:country":"US",
    "sg:address":"2506 S 3rd St",
    "sg:city":"Philadelphia",
    "sg:classifiers":[
        {
            "category":"Building & Trades",
            "subcategory":"Construction",
            "type":"Services"
        }
    ],
    "sg:phone":"+1 215 545 5510",
    "sg:postcode":"19148",
    "sg:province":"PA",
    "sg:tags":[
        "contractor"
    ],
    "wof:name":"Pepe L Contractors",
    "wof:placetype":"venue"
},
  "geometry": {"coordinates":[-75.152761,39.917033],"type":"Point"}
}