{
  "type": "Feature",
  "properties": {
    "iso:country":"US",
    "sg:address":"220 Washington St",
    "sg:city":"Bristol",
    "sg:classifiers":[
        {
            "category":"Professional",
            "subcategory":"Lawyer & Legal Services",
            "type":"Services"
        }
    ],
    "sg:phone":"+1 267 812 0110",
    "sg:postcode":"19007",
    "sg:province":"PA",
    "sg:tags":[
        "notary"
    ],
    "wof:name":"Bergner Robert Notary",
    "wof:placetype":"venue"
},
  "geometry": {"coordinates":[-74.850098,40.099701],"type":"Point"}
}