{
  "type": "Feature",
  "properties": {
    "addr:full":"2801 US Hwy 209 Bus Stroudsburg PA 18360",
    "addr:housenumber":"2801",
    "addr:postcode":"18360",
    "addr:street":"Us Hwy 209 Bus",
    "iso:country":"US",
    "sg:address":"2801 US Hwy 209 Bus",
    "sg:city":"Stroudsburg",
    "sg:classifiers":[
        {
            "category":"Building & Trades",
            "subcategory":"Construction",
            "type":"Services"
        }
    ],
    "sg:phone":"+1   ",
    "sg:postcode":"18360",
    "sg:province":"PA",
    "sg:tags":[
        "house"
    ],
    "wof:name":"Glen Eyre Corp",
    "wof:placetype":"venue"
},
  "geometry": {"coordinates":[-75.25973500000001,40.970586],"type":"Point"}
}