{
  "type": "Feature",
  "properties": {
    "iso:country":"US",
    "sg:address":"770 S West St",
    "sg:city":"Carlisle",
    "sg:classifiers":[
        {
            "category":"Food & Beverages",
            "subcategory":"Liquor & Beverages",
            "type":"Retail Goods"
        }
    ],
    "sg:phone":"+1 717 249 2434",
    "sg:postcode":"17013",
    "sg:province":"PA",
    "sg:tags":[
        "beer",
        "spirit",
        "wine"
    ],
    "wof:name":"Carlisle Beverage Inc",
    "wof:placetype":"venue"
},
  "geometry": {"coordinates":[-77.195198,40.1912],"type":"Point"}
}