{
  "type": "Feature",
  "properties": {
    "iso:country":"US",
    "sg:address":"848 Talbot Ave",
    "sg:city":"Braddock",
    "sg:classifiers":[
        {
            "category":"Organizations",
            "subcategory":"Professional Association",
            "type":"Services"
        }
    ],
    "sg:phone":"+1 412 271 2274",
    "sg:postcode":"15104",
    "sg:province":"PA",
    "sg:tags":[
        "business"
    ],
    "wof:name":"Polish Club Of Braddock",
    "wof:placetype":"venue"
},
  "geometry": {"coordinates":[-79.866799,40.399353],"type":"Point"}
}