{
  "type": "Feature",
  "properties": {
    "iso:country":"US",
    "sg:address":"2935 Byberry Rd",
    "sg:city":"Hatboro",
    "sg:classifiers":[
        {
            "category":"Insurance",
            "subcategory":"Insurance Agent",
            "type":"Services"
        }
    ],
    "sg:phone":"+1 215 675 9511",
    "sg:postcode":"19040",
    "sg:province":"PA",
    "wof:name":"Carpitella & Casile Assoc",
    "wof:placetype":"venue"
},
  "geometry": {"coordinates":[-75.09467100000001,40.170648],"type":"Point"}
}