{
  "type": "Feature",
  "properties": {
    "iso:country":"US",
    "sg:address":"2199 Strahle St",
    "sg:city":"Philadelphia",
    "sg:classifiers":[
        {
            "category":"Social Services",
            "subcategory":"Child Care",
            "type":"Services"
        }
    ],
    "sg:phone":"+1   ",
    "sg:postcode":"19152",
    "sg:province":"PA",
    "sg:tags":[
        "day"
    ],
    "wof:name":"Samuel Paley Day Care",
    "wof:placetype":"venue"
},
  "geometry": {"coordinates":[-75.05122,40.06663],"type":"Point"}
}