{
  "type": "Feature",
  "properties": {
    "addr:full":"4930 Carlisle Pike Mechanicsburg PA 17050",
    "addr:housenumber":"4930",
    "addr:postcode":"17050",
    "addr:street":"Carlisle Pike",
    "iso:country":"US",
    "sg:address":"4930 Carlisle Pike",
    "sg:city":"Mechanicsburg",
    "sg:classifiers":[
        {
            "category":"Restaurant",
            "type":"Food & Drink"
        }
    ],
    "sg:phone":"+1 717 763 7368",
    "sg:postcode":"17050",
    "sg:province":"PA",
    "sg:tags":[
        "eating",
        "pizza"
    ],
    "wof:name":"Palumbo Pizza",
    "wof:placetype":"venue"
},
  "geometry": {"coordinates":[-76.96869,40.237119],"type":"Point"}
}