{
  "type": "Feature",
  "properties": {
    "addr:full":"17 Arentzen Blvd Charleroi PA 15022",
    "addr:housenumber":"17",
    "addr:postcode":"15022",
    "addr:street":"Arentzen Blvd",
    "iso:country":"US",
    "sg:address":"17 Arentzen Blvd",
    "sg:city":"Charleroi",
    "sg:classifiers":[
        {
            "category":"Health Services",
            "subcategory":"Doctor",
            "type":"Services"
        }
    ],
    "sg:phone":"+1   ",
    "sg:postcode":"15022",
    "sg:province":"PA",
    "sg:tags":[
        "medical"
    ],
    "wof:name":"Occupational Health Monongahel",
    "wof:placetype":"venue"
},
  "geometry": {"coordinates":[-79.885521,40.121451],"type":"Point"}
}