{
  "type": "Feature",
  "properties": {
    "addr:full":"100 Hamilton St Washington PA 15301",
    "addr:housenumber":"100",
    "addr:postcode":"15301",
    "addr:street":"Hamilton St",
    "iso:country":"US",
    "sg:address":"100 Hamilton St",
    "sg:city":"Washington",
    "sg:classifiers":[
        {
            "category":"Health Services",
            "subcategory":"Clinic",
            "type":"Services"
        }
    ],
    "sg:phone":"+1 724 228 8100",
    "sg:postcode":"15301",
    "sg:province":"PA",
    "sg:tags":[
        "specialty",
        "outpatient"
    ],
    "wof:name":"Better Health Clinics LTD",
    "wof:placetype":"venue"
},
  "geometry": {"coordinates":[-80.253559,40.166849],"type":"Point"}
}