{
  "type": "Feature",
  "properties": {
    "iso:country":"US",
    "sg:address":"420 Guinter Rd",
    "sg:city":"Jersey Shore",
    "sg:classifiers":[
        {
            "category":"Freight",
            "type":"Transportation"
        }
    ],
    "sg:phone":"+1   ",
    "sg:postcode":"17740",
    "sg:province":"PA",
    "sg:tags":[
        "operator",
        "local",
        "trucking"
    ],
    "wof:name":"Larry E Wolfe Trucking",
    "wof:placetype":"venue"
},
  "geometry": {"coordinates":[-77.21472900000001,41.260774],"type":"Point"}
}