{
  "type": "Feature",
  "properties": {
    "addr:full":"112 Exton Square Mall Exton PA 19341",
    "addr:housenumber":"112",
    "addr:postcode":"19341",
    "addr:street":"Exton Square Mall",
    "iso:country":"US",
    "sg:address":"112 Exton Square Mall",
    "sg:city":"Exton",
    "sg:classifiers":[
        {
            "category":"Shopping",
            "subcategory":"Computers & Home Electronics",
            "type":"Retail Goods"
        }
    ],
    "sg:phone":"+1 610 363 1037",
    "sg:postcode":"19341",
    "sg:province":"PA",
    "sg:tags":[
        "equipment",
        "electronic",
        "supply"
    ],
    "wof:name":"Radio Shack",
    "wof:placetype":"venue"
},
  "geometry": {"coordinates":[-75.627437,40.032789],"type":"Point"}
}