{
  "type": "Feature",
  "properties": {
    "iso:country":"US",
    "sg:address":"1155 Cleveland Ave",
    "sg:city":"Reading",
    "sg:classifiers":[
        {
            "category":"Wholesale",
            "subcategory":"Apparel",
            "type":"Manufacturing & Wholesale Goods"
        }
    ],
    "sg:phone":"+1   ",
    "sg:postcode":"19610",
    "sg:province":"PA",
    "sg:tags":[
        "piece"
    ],
    "wof:name":"North American Fabrics Inc",
    "wof:placetype":"venue"
},
  "geometry": {"coordinates":[-75.96323700000001,40.330972],"type":"Point"}
}