{
  "type": "Feature",
  "properties": {
    "iso:country":"US",
    "sg:address":"2201 Moore St",
    "sg:city":"Philadelphia",
    "sg:classifiers":[
        {
            "category":"Social Services",
            "subcategory":"Child Care",
            "type":"Services"
        }
    ],
    "sg:phone":"+1 215 463 2448",
    "sg:postcode":"19145",
    "sg:province":"PA",
    "wof:name":"SCAN",
    "wof:placetype":"venue"
},
  "geometry": {"coordinates":[-75.183601,39.929928],"type":"Point"}
}