{
  "type": "Feature",
  "properties": {
    "iso:country":"US",
    "sg:address":"738 Peace St",
    "sg:city":"Hazleton",
    "sg:classifiers":[
        {
            "category":"Insurance",
            "subcategory":"Hazard Insurance",
            "type":"Services"
        }
    ],
    "sg:phone":"+1 570 459 7063",
    "sg:postcode":"18201",
    "sg:province":"PA",
    "wof:name":"R Gliem",
    "wof:placetype":"venue"
},
  "geometry": {"coordinates":[-75.98447899999999,40.96513],"type":"Point"}
}