{
  "type": "Feature",
  "properties": {
    "iso:country":"US",
    "sg:address":"6611 N 11th St",
    "sg:city":"Philadelphia",
    "sg:classifiers":[
        {
            "category":"Structure",
            "subcategory":"Building",
            "type":"Public Place"
        },
        {
            "category":"Animal Shelter",
            "type":"Public Place"
        }
    ],
    "sg:phone":"+1 215 729 1640",
    "sg:postcode":"19126",
    "sg:province":"PA",
    "sg:tags":[
        "storm"
    ],
    "wof:name":"Highsmith Pch",
    "wof:placetype":"venue"
},
  "geometry": {"coordinates":[-75.13663699999999,40.053173],"type":"Point"}
}