{
  "type": "Feature",
  "properties": {
    "iso:country":"US",
    "sg:address":"709 Linwood Ave",
    "sg:city":"Pittsburgh",
    "sg:classifiers":[
        {
            "category":"Building & Trades",
            "subcategory":"Construction",
            "type":"Services"
        }
    ],
    "sg:phone":"+1   ",
    "sg:postcode":"15215",
    "sg:province":"PA",
    "sg:tags":[
        "hanging",
        "contractor"
    ],
    "wof:name":"Painting By Szwedko",
    "wof:placetype":"venue"
},
  "geometry": {"coordinates":[-79.929455,40.502541],"type":"Point"}
}