{
  "type": "Feature",
  "properties": {
    "iso:country":"US",
    "sg:address":"113 Cavalry Ct",
    "sg:city":"Chesterbrook",
    "sg:classifiers":[
        {
            "category":"Professional",
            "subcategory":"Management & Consulting",
            "type":"Services"
        }
    ],
    "sg:phone":"+1 610 296 3530",
    "sg:postcode":"19087",
    "sg:province":"PA",
    "sg:tags":[
        "consultant",
        "business"
    ],
    "wof:name":"Corporate Staffing Assn Inc",
    "wof:placetype":"venue"
},
  "geometry": {"coordinates":[-75.46156499999999,40.074304],"type":"Point"}
}