{
  "type": "Feature",
  "properties": {
    "iso:country":"US",
    "sg:address":"9528 Lincoln Hwy Ste 1",
    "sg:city":"Bedford",
    "sg:classifiers":[
        {
            "category":"Social Services",
            "type":"Services"
        },
        {
            "category":"Health Services",
            "subcategory":"Clinic",
            "type":"Services"
        },
        {
            "category":"Personal",
            "type":"Services"
        }
    ],
    "sg:phone":"+1 814 623 5077",
    "sg:postcode":"15522",
    "sg:province":"PA",
    "sg:tags":[
        "information",
        "mental",
        "family",
        "counselors-licensed",
        "individual",
        "marriage",
        "child",
        "professional",
        "counselor"
    ],
    "wof:name":"Family Behavioral Resources",
    "wof:placetype":"venue"
},
  "geometry": {"coordinates":[-78.522961,40.036369],"type":"Point"}
}