{
  "type": "Feature",
  "properties": {
    "iso:country":"US",
    "sg:address":"1510 Cornwall Rd",
    "sg:city":"Lebanon",
    "sg:classifiers":[
        {
            "category":"Health Services",
            "subcategory":"Doctor",
            "type":"Services"
        }
    ],
    "sg:phone":"+1 717 273 0662",
    "sg:postcode":"17042",
    "sg:province":"PA",
    "sg:tags":[
        "physician",
        "surgeon"
    ],
    "wof:name":"Albert A Alley Ophthalmic",
    "wof:placetype":"venue"
},
  "geometry": {"coordinates":[-76.41801599999999,40.319192],"type":"Point"}
}