{
  "type": "Feature",
  "properties": {
    "iso:country":"US",
    "sg:address":"406 Main St",
    "sg:city":"Archbald",
    "sg:classifiers":[
        {
            "category":"Building & Trades",
            "subcategory":"Construction",
            "type":"Services"
        }
    ],
    "sg:phone":"+1 570 341 1500",
    "sg:postcode":"18403",
    "sg:province":"PA",
    "sg:tags":[
        "contractor",
        "restoration",
        "general"
    ],
    "wof:name":"Damage Control Inc",
    "wof:placetype":"venue"
},
  "geometry": {"coordinates":[-75.546582,41.492953],"type":"Point"}
}