{
  "type": "Feature",
  "properties": {
    "addr:full":"47 Palo Ave Fairbank PA 15435",
    "addr:housenumber":"47",
    "addr:postcode":"15435",
    "addr:street":"Palo Ave",
    "iso:country":"US",
    "sg:address":"47 Palo Ave",
    "sg:city":"Fairbank",
    "sg:classifiers":[
        {
            "category":"Manufacturing",
            "subcategory":"Tools & Machinery",
            "type":"Manufacturing & Wholesale Goods"
        }
    ],
    "sg:phone":"+1 724 245 6151",
    "sg:postcode":"15435",
    "sg:province":"PA",
    "sg:tags":[
        "machine",
        "shop"
    ],
    "wof:name":"Tiberi Services",
    "wof:placetype":"venue"
},
  "geometry": {"coordinates":[-79.84896999999999,39.94019],"type":"Point"}
}