{
  "type": "Feature",
  "properties": {
    "iso:country":"US",
    "sg:address":"187 N Wales Rd",
    "sg:city":"North Wales",
    "sg:classifiers":[
        {
            "category":"Building & Trades",
            "subcategory":"Cleaning & Sanitation",
            "type":"Services"
        }
    ],
    "sg:phone":"+1   ",
    "sg:postcode":"19454",
    "sg:province":"PA",
    "sg:tags":[
        "maintenance"
    ],
    "wof:name":"Carter Jonathan Window Clg LLC",
    "wof:placetype":"venue"
},
  "geometry": {"coordinates":[-75.259664,40.231123],"type":"Point"}
}