{
  "type": "Feature",
  "properties": {
    "addr:full":"340 Tri Hill Rd York PA 17403",
    "addr:housenumber":"340",
    "addr:postcode":"17403",
    "addr:street":"Tri Hill Rd",
    "iso:country":"US",
    "sg:address":"340 Tri Hill Rd",
    "sg:city":"York",
    "sg:classifiers":[
        {
            "category":"Government",
            "subcategory":"Police Station",
            "type":"Public Place"
        }
    ],
    "sg:phone":"+1   ",
    "sg:postcode":"17403",
    "sg:province":"PA",
    "sg:tags":[
        "protection"
    ],
    "wof:name":"Police Department",
    "wof:placetype":"venue"
},
  "geometry": {"coordinates":[-76.710335,39.942129],"type":"Point"}
}