{
  "type": "Feature",
  "properties": {
    "addr:full":"980 Valley Rd Coatesville PA 19320",
    "addr:housenumber":"980",
    "addr:postcode":"19320",
    "addr:street":"Valley Rd",
    "iso:country":"US",
    "sg:address":"980 Valley Rd",
    "sg:city":"Coatesville",
    "sg:classifiers":[
        {
            "category":"Building & Trades",
            "subcategory":"Electrical",
            "type":"Services"
        }
    ],
    "sg:phone":"+1   ",
    "sg:postcode":"19320",
    "sg:province":"PA",
    "sg:tags":[
        "electrical",
        "contractor"
    ],
    "wof:name":"Vietris Electric",
    "wof:placetype":"venue"
},
  "geometry": {"coordinates":[-75.84142900000001,39.974641],"type":"Point"}
}