{
  "type": "Feature",
  "properties": {
    "addr:full":"3501 Walnut St Mc Keesport PA 15132",
    "addr:housenumber":"3501",
    "addr:postcode":"15132",
    "addr:street":"Walnut St",
    "iso:country":"US",
    "sg:address":"3501 Walnut St",
    "sg:city":"Mc Keesport",
    "sg:classifiers":[
        {
            "category":"Restaurant",
            "type":"Food & Drink"
        }
    ],
    "sg:phone":"+1   ",
    "sg:postcode":"15132",
    "sg:province":"PA",
    "sg:tags":[
        "eating"
    ],
    "wof:name":"Chiaverinis Family Restaurant",
    "wof:placetype":"venue"
},
  "geometry": {"coordinates":[-79.840718,40.328185],"type":"Point"}
}