{
  "type": "Feature",
  "properties": {
    "addr:full":"2641 Mount Carmel Ave Glenside PA 19038",
    "addr:housenumber":"2641",
    "addr:postcode":"19038",
    "addr:street":"Mount Carmel Ave",
    "iso:country":"US",
    "sg:address":"2641 Mount Carmel Ave",
    "sg:city":"Glenside",
    "sg:classifiers":[
        {
            "category":"Organizations",
            "subcategory":"Religious Organization",
            "type":"Services"
        }
    ],
    "sg:phone":"+1 215 576 5590",
    "sg:postcode":"19038",
    "sg:province":"PA",
    "sg:website":"http://www.larkinestate.com",
    "wof:name":"Clarence Larkin Estate",
    "wof:placetype":"venue"
},
  "geometry": {"coordinates":[-75.16123899999999,40.106554],"type":"Point"}
}