{
  "type": "Feature",
  "properties": {
    "iso:country":"US",
    "sg:address":"1300 Bower Hill Rd",
    "sg:city":"Pittsburgh",
    "sg:classifiers":[
        {
            "category":"Building & Trades",
            "subcategory":"Plumbing",
            "type":"Services"
        }
    ],
    "sg:phone":"+1   ",
    "sg:postcode":"15243",
    "sg:province":"PA",
    "sg:tags":[
        "contractor"
    ],
    "wof:name":"A J Demor & Sons Inc",
    "wof:placetype":"venue"
},
  "geometry": {"coordinates":[-80.075547,40.373339],"type":"Point"}
}