{
  "type": "Feature",
  "properties": {
    "iso:country":"US",
    "sg:address":"2569 E Clearfield St",
    "sg:city":"Philadelphia",
    "sg:classifiers":[
        {
            "category":"Personal",
            "subcategory":"Beauty Salon",
            "type":"Services"
        }
    ],
    "sg:phone":"+1 215 423 3414",
    "sg:postcode":"19134",
    "sg:province":"PA",
    "sg:tags":[
        "shop",
        "spa"
    ],
    "wof:name":"Marie's Beauty Salon",
    "wof:placetype":"venue"
},
  "geometry": {"coordinates":[-75.10610200000001,39.984402],"type":"Point"}
}