{
  "type": "Feature",
  "properties": {
    "iso:country":"US",
    "sg:address":"4906 W Penn Ave",
    "sg:city":"Sinking Spring",
    "sg:classifiers":[
        {
            "category":"Shopping",
            "subcategory":"Books",
            "type":"Retail Goods"
        }
    ],
    "sg:phone":"+1 610 678 7627",
    "sg:postcode":"19608",
    "sg:province":"PA",
    "sg:tags":[
        "dealer"
    ],
    "sg:website":"www.visitjoybookstore.com",
    "wof:name":"Joy Book Store",
    "wof:placetype":"venue"
},
  "geometry": {"coordinates":[-76.05332900000001,40.326657],"type":"Point"}
}