{
  "type": "Feature",
  "properties": {
    "addr:full":"1501 N Myrtlewood St Philadelphia PA 19121",
    "addr:housenumber":"1501",
    "addr:postcode":"19121",
    "addr:street":"N Myrtlewood St",
    "iso:country":"US",
    "sg:address":"1501 N Myrtlewood St",
    "sg:city":"Philadelphia",
    "sg:classifiers":[
        {
            "category":"Building & Trades",
            "subcategory":"Locksmith",
            "type":"Services"
        }
    ],
    "sg:phone":"+1 267 350 8857",
    "sg:postcode":"19121",
    "sg:province":"PA",
    "sg:tags":[
        "key"
    ],
    "wof:name":"Packer Ave Emergency Locksmith",
    "wof:placetype":"venue"
},
  "geometry": {"coordinates":[-75.183385,39.979052],"type":"Point"}
}