{
  "type": "Feature",
  "properties": {
    "iso:country":"US",
    "sg:address":"203 S 3rd St",
    "sg:city":"Oxford",
    "sg:classifiers":[
        {
            "category":"Autos & Motor Vehicles",
            "subcategory":"Fuel & Gas Station",
            "type":"Retail Goods"
        }
    ],
    "sg:phone":"+1 610 932 4636",
    "sg:postcode":"19363",
    "sg:province":"PA",
    "sg:tags":[
        "oil"
    ],
    "wof:name":"Getty Mart",
    "wof:placetype":"venue"
},
  "geometry": {"coordinates":[-75.98051599999999,39.779269],"type":"Point"}
}