{
  "type": "Feature",
  "properties": {
    "iso:country":"US",
    "sg:address":"51 W King St",
    "sg:city":"Lancaster",
    "sg:classifiers":[
        {
            "category":"Shopping",
            "subcategory":"Jewelry",
            "type":"Retail Goods"
        }
    ],
    "sg:phone":"+1 717 299 0707",
    "sg:postcode":"17603",
    "sg:province":"PA",
    "sg:tags":[
        "jeweler"
    ],
    "wof:name":"A & W Jewelers",
    "wof:placetype":"venue"
},
  "geometry": {"coordinates":[-76.307503,40.037843],"type":"Point"}
}