{
  "type": "Feature",
  "properties": {
    "iso:country":"US",
    "sg:address":"2300 W Allegheny Ave # 4",
    "sg:city":"Philadelphia",
    "sg:classifiers":[
        {
            "category":"Social Services",
            "subcategory":"Child Care",
            "type":"Services"
        }
    ],
    "sg:phone":"+1 215 226 0691",
    "sg:postcode":"19132",
    "sg:province":"PA",
    "sg:tags":[
        "day"
    ],
    "wof:name":"Brightside Academy",
    "wof:placetype":"venue"
},
  "geometry": {"coordinates":[-75.16755499999999,40.003334],"type":"Point"}
}