{
  "type": "Feature",
  "properties": {
    "iso:country":"US",
    "sg:address":"1025 Lehman St",
    "sg:city":"Lebanon",
    "sg:classifiers":[
        {
            "category":"Organizations",
            "subcategory":"Religious Organization",
            "type":"Services"
        }
    ],
    "sg:phone":"+1 717 273 5331",
    "sg:postcode":"17046",
    "sg:province":"PA",
    "sg:tags":[
        "church"
    ],
    "wof:name":"New Birth United Methodist Chr",
    "wof:placetype":"venue"
},
  "geometry": {"coordinates":[-76.42961699999999,40.345364],"type":"Point"}
}