{
  "type": "Feature",
  "properties": {
    "iso:country":"US",
    "sg:address":"128 Rockland Ave",
    "sg:city":"Merion Station",
    "sg:classifiers":[
        {
            "category":"Communications",
            "subcategory":"Film & Video Production",
            "type":"Services"
        }
    ],
    "sg:phone":"+1   ",
    "sg:postcode":"19066",
    "sg:province":"PA",
    "sg:tags":[
        "motion"
    ],
    "wof:name":"Capella Productions Inc",
    "wof:placetype":"venue"
},
  "geometry": {"coordinates":[-75.261886,40.000783],"type":"Point"}
}