{
  "type": "Feature",
  "properties": {
    "iso:country":"US",
    "sg:address":"30 Keystone Ct",
    "sg:city":"Leola",
    "sg:classifiers":[
        {
            "category":"Insurance",
            "subcategory":"Insurance Agent",
            "type":"Services"
        }
    ],
    "sg:phone":"+1   ",
    "sg:postcode":"17540",
    "sg:province":"PA",
    "wof:name":"Connecticut Mutual Fincl Assoc",
    "wof:placetype":"venue"
},
  "geometry": {"coordinates":[-76.205342,40.085047],"type":"Point"}
}