{
  "type": "Feature",
  "properties": {
    "iso:country":"US",
    "sg:address":"1601 Federal St",
    "sg:city":"Philadelphia",
    "sg:classifiers":[
        {
            "category":"Real Estate",
            "subcategory":"Real Estate Services",
            "type":"Services"
        },
        {
            "category":"Real Estate",
            "subcategory":"Real Estate Agent",
            "type":"Services"
        }
    ],
    "sg:phone":"+1 215 545 1334",
    "sg:postcode":"19146",
    "sg:province":"PA",
    "sg:tags":[
        "buyer",
        "broker"
    ],
    "wof:name":"Universal Community Homes",
    "wof:placetype":"venue"
},
  "geometry": {"coordinates":[-75.17044799999999,39.936218],"type":"Point"}
}