{
  "type": "Feature",
  "properties": {
    "addr:full":"1405 Williams Rd York PA 17402",
    "addr:housenumber":"1405",
    "addr:postcode":"17402",
    "addr:street":"Williams Rd",
    "iso:country":"US",
    "sg:address":"1405 Williams Rd",
    "sg:city":"York",
    "sg:classifiers":[
        {
            "category":"Education",
            "subcategory":"Junior College",
            "type":"Public Place"
        },
        {
            "category":"Education",
            "subcategory":"Vocational School",
            "type":"Public Place"
        }
    ],
    "sg:phone":"+1 717 757 1100",
    "sg:postcode":"17402",
    "sg:province":"PA",
    "sg:tags":[
        "technical",
        "trade"
    ],
    "sg:website":"www.yorktech.net",
    "wof:name":"York Technical Institute Inc",
    "wof:placetype":"venue"
},
  "geometry": {"coordinates":[-76.664891,39.991062],"type":"Point"}
}