{
  "type": "Feature",
  "properties": {
    "iso:country":"US",
    "sg:address":"2729 Woodsview Dr",
    "sg:city":"Bensalem",
    "sg:classifiers":[
        {
            "category":"Wholesale",
            "subcategory":"Medical Equipment & Supplies",
            "type":"Manufacturing & Wholesale Goods"
        },
        {
            "category":"Wholesale",
            "subcategory":"Durable Goods & Equipment",
            "type":"Manufacturing & Wholesale Goods"
        }
    ],
    "sg:phone":"+1 215 757 1205",
    "sg:postcode":"19020",
    "sg:province":"PA",
    "sg:tags":[
        "professional",
        "optical"
    ],
    "wof:name":"Jerico Optics Inc",
    "wof:placetype":"venue"
},
  "geometry": {"coordinates":[-74.927002,40.129768],"type":"Point"}
}