{
  "type": "Feature",
  "properties": {
    "iso:country":"US",
    "sg:address":"144 S Pitt St",
    "sg:city":"Mercer",
    "sg:classifiers":[
        {
            "category":"Retail",
            "subcategory":"Funeral Services",
            "type":"Services"
        }
    ],
    "sg:phone":"+1 724 662 2720",
    "sg:postcode":"16137",
    "sg:province":"PA",
    "wof:name":"Cunningham Funeral Home Inc",
    "wof:placetype":"venue"
},
  "geometry": {"coordinates":[-80.23789600000001,41.22517],"type":"Point"}
}