{
  "type": "Feature",
  "properties": {
    "addr:full":"1606 Newton Ransom Blvd Clarks Summit PA 18411",
    "addr:housenumber":"1606",
    "addr:postcode":"18411",
    "addr:street":"Newton Ransom Blvd",
    "iso:country":"US",
    "sg:address":"1606 Newton Ransom Blvd",
    "sg:city":"Clarks Summit",
    "sg:classifiers":[
        {
            "category":"Shopping",
            "subcategory":"Clothing, Apparel, & Fashions",
            "type":"Retail Goods"
        }
    ],
    "sg:phone":"+1   ",
    "sg:postcode":"18411",
    "sg:province":"PA",
    "wof:name":"Finger Fashions",
    "wof:placetype":"venue"
},
  "geometry": {"coordinates":[-75.76434500000001,41.47511],"type":"Point"}
}