{
  "type": "Feature",
  "properties": {
    "iso:country":"US",
    "sg:address":"316 Lafayette Ave",
    "sg:city":"Darby",
    "sg:classifiers":[
        {
            "category":"Building & Trades",
            "subcategory":"Construction",
            "type":"Services"
        }
    ],
    "sg:phone":"+1 610 717 7716",
    "sg:postcode":"19023",
    "sg:province":"PA",
    "sg:tags":[
        "wallcoverings-installation",
        "wallpaper",
        "painting",
        "contractor"
    ],
    "wof:name":"R O Neill Painting Inc",
    "wof:placetype":"venue"
},
  "geometry": {"coordinates":[-75.283378,39.911],"type":"Point"}
}