{
  "type": "Feature",
  "properties": {
    "addr:full":"2545 Schoenersville Rd Bethlehem PA 18017",
    "addr:housenumber":"2545",
    "addr:postcode":"18017",
    "addr:street":"Schoenersville Rd",
    "iso:country":"US",
    "sg:address":"2545 Schoenersville Rd",
    "sg:city":"Bethlehem",
    "sg:classifiers":[
        {
            "category":"Health Services",
            "subcategory":"Doctor",
            "type":"Services"
        }
    ],
    "sg:phone":"+1 484 884 6503",
    "sg:postcode":"18017",
    "sg:province":"PA",
    "sg:tags":[
        "psychiatrist"
    ],
    "wof:name":"Kaufmann Michael W MD",
    "wof:placetype":"venue"
},
  "geometry": {"coordinates":[-75.37979900000001,40.654301],"type":"Point"}
}