{
  "type": "Feature",
  "properties": {
    "iso:country":"US",
    "sg:address":"57 Makara Dr",
    "sg:city":"Drums",
    "sg:classifiers":[
        {
            "category":"Shopping",
            "subcategory":"Computers & Home Electronics",
            "type":"Retail Goods"
        }
    ],
    "sg:phone":"+1 570 436 4542",
    "sg:postcode":"18222",
    "sg:province":"PA",
    "sg:tags":[
        "equipment",
        "audio-visual"
    ],
    "wof:name":"E.L.S. Audio",
    "wof:placetype":"venue"
},
  "geometry": {"coordinates":[-75.975021,41.00708],"type":"Point"}
}