{
  "type": "Feature",
  "properties": {
    "iso:country":"US",
    "sg:address":"221 Riverview Dr",
    "sg:city":"Ephrata",
    "sg:classifiers":[
        {
            "category":"Professional",
            "type":"Services"
        }
    ],
    "sg:phone":"+1   ",
    "sg:postcode":"17522",
    "sg:province":"PA",
    "wof:name":"Charles W Ulrich IV",
    "wof:placetype":"venue"
},
  "geometry": {"coordinates":[-76.204055,40.168507],"type":"Point"}
}