{
  "type": "Feature",
  "properties": {
    "addr:full":"130 7th St Pittsburgh PA 15222",
    "addr:housenumber":"130",
    "addr:postcode":"15222",
    "addr:street":"7Th St",
    "iso:country":"US",
    "sg:address":"130 7th St",
    "sg:city":"Pittsburgh",
    "sg:classifiers":[
        {
            "category":"Personal",
            "type":"Services"
        }
    ],
    "sg:phone":"+1 412 765 3355",
    "sg:postcode":"15222",
    "sg:province":"PA",
    "sg:tags":[
        "hair",
        "replacement"
    ],
    "wof:name":"A Technical Hairsystems",
    "wof:placetype":"venue"
},
  "geometry": {"coordinates":[-80.00049799999999,40.443609],"type":"Point"}
}