{
  "type": "Feature",
  "properties": {
    "iso:country":"US",
    "sg:address":"753 Bethlehem Pike",
    "sg:city":"Montgomeryville",
    "sg:classifiers":[
        {
            "category":"Retail",
            "subcategory":"Pet Boarding",
            "type":"Services"
        }
    ],
    "sg:phone":"+1 215 393 5760",
    "sg:postcode":"18936",
    "sg:province":"PA",
    "sg:tags":[
        "boarding/pet",
        "sitting"
    ],
    "sg:website":"www.petco.com",
    "wof:name":"Petco",
    "wof:placetype":"venue"
},
  "geometry": {"coordinates":[-75.2351,40.2271],"type":"Point"}
}