{
  "type": "Feature",
  "properties": {
    "addr:full":"2929 Smallman St Pittsburgh PA 15201",
    "addr:housenumber":"2929",
    "addr:postcode":"15201",
    "addr:street":"Smallman St",
    "iso:country":"US",
    "sg:address":"2929 Smallman St",
    "sg:city":"Pittsburgh",
    "sg:classifiers":[
        {
            "category":"Manufacturing",
            "subcategory":"Chemicals & Compounds",
            "type":"Manufacturing & Wholesale Goods"
        }
    ],
    "sg:phone":"+1 412 261 6642",
    "sg:postcode":"15201",
    "sg:province":"PA",
    "sg:tags":[
        "product",
        "allied",
        "chem",
        "mfg"
    ],
    "wof:name":"Gateway Paint & Chemical Co",
    "wof:placetype":"venue"
},
  "geometry": {"coordinates":[-79.97403300000001,40.459289],"type":"Point"}
}