{
  "type": "Feature",
  "properties": {
    "iso:country":"US",
    "sg:address":"518 Rte 18",
    "sg:city":"Monaca",
    "sg:classifiers":[
        {
            "category":"Shopping",
            "subcategory":"Jewelry",
            "type":"Retail Goods"
        }
    ],
    "sg:phone":"+1 724 775 1929",
    "sg:postcode":"15061",
    "sg:province":"PA",
    "sg:tags":[
        "jeweler"
    ],
    "wof:name":"Italian Jewelry Co",
    "wof:placetype":"venue"
},
  "geometry": {"coordinates":[-80.321129,40.668039],"type":"Point"}
}