{
  "type": "Feature",
  "properties": {
    "iso:country":"US",
    "sg:address":"780 N Chester Rd",
    "sg:city":"West Chester",
    "sg:classifiers":[
        {
            "category":"Restaurant",
            "type":"Food & Drink"
        }
    ],
    "sg:phone":"+1 610 344 0271",
    "sg:postcode":"19380",
    "sg:province":"PA",
    "wof:name":"Express Wok",
    "wof:placetype":"venue"
},
  "geometry": {"coordinates":[-75.544224,39.99421],"type":"Point"}
}