{
  "type": "Feature",
  "properties": {
    "addr:full":"1212 Georgetown Rd Sandy Lake PA 16145",
    "addr:housenumber":"1212",
    "addr:postcode":"16145",
    "addr:street":"Georgetown Rd",
    "iso:country":"US",
    "sg:address":"1212 Georgetown Rd",
    "sg:city":"Sandy Lake",
    "sg:classifiers":[
        {
            "category":"Wholesale",
            "subcategory":"Machinery & Supplies",
            "type":"Manufacturing & Wholesale Goods"
        },
        {
            "category":"Retail",
            "subcategory":"Auto Repair",
            "type":"Services"
        }
    ],
    "sg:phone":"+1 724 253 3450",
    "sg:postcode":"16145",
    "sg:province":"PA",
    "sg:tags":[
        "engine",
        "equipment",
        "industrial",
        "general"
    ],
    "wof:name":"Sandy Lake Diesel",
    "wof:placetype":"venue"
},
  "geometry": {"coordinates":[-80.123147,41.416207],"type":"Point"}
}