{
  "type": "Feature",
  "properties": {
    "iso:country":"US",
    "sg:address":"500 Mall Blvd",
    "sg:city":"King Of Prussia",
    "sg:classifiers":[
        {
            "category":"Restaurant",
            "type":"Food & Drink"
        }
    ],
    "sg:menulink":"http://www.allmenus.com/pa/upper-merion/34988-mortons-steakhouse/menu/",
    "sg:phone":"+1 610 491 1900",
    "sg:postcode":"19406",
    "sg:province":"PA",
    "sg:tags":[
        "american",
        "steakhouse"
    ],
    "wof:name":"Morton's Steakhouse",
    "wof:placetype":"venue"
},
  "geometry": {"coordinates":[-75.386686,40.087023],"type":"Point"}
}