{
  "type": "Feature",
  "properties": {
    "iso:country":"US",
    "sg:address":"18 W Front St",
    "sg:city":"Media",
    "sg:classifiers":[
        {
            "category":"Professional",
            "subcategory":"Lawyer & Legal Services",
            "type":"Services"
        }
    ],
    "sg:phone":"+1 610 892 0400",
    "sg:postcode":"19063",
    "sg:province":"PA",
    "sg:tags":[
        "attorney"
    ],
    "wof:name":"Keller Lisgar & Williams",
    "wof:placetype":"venue"
},
  "geometry": {"coordinates":[-75.389657,39.918818],"type":"Point"}
}