{
  "type": "Feature",
  "properties": {
    "addr:full":"4049 Washington Rd Canonsburg PA 15317",
    "addr:housenumber":"4049",
    "addr:postcode":"15317",
    "addr:street":"Washington Rd",
    "iso:country":"US",
    "sg:address":"4049 Washington Rd",
    "sg:city":"Canonsburg",
    "sg:classifiers":[
        {
            "category":"Building & Trades",
            "subcategory":"Construction",
            "type":"Services"
        }
    ],
    "sg:phone":"+1   ",
    "sg:postcode":"15317",
    "sg:province":"PA",
    "sg:tags":[
        "house"
    ],
    "wof:name":"Mosites Construction Co",
    "wof:placetype":"venue"
},
  "geometry": {"coordinates":[-80.129018,40.266571],"type":"Point"}
}