{
  "type": "Feature",
  "properties": {
    "addr:full":"608 High St Freeport PA 16229",
    "addr:housenumber":"608",
    "addr:postcode":"16229",
    "addr:street":"High St",
    "iso:country":"US",
    "sg:address":"608 High St",
    "sg:city":"Freeport",
    "sg:classifiers":[
        {
            "category":"Organizations",
            "subcategory":"Religious Organization",
            "type":"Services"
        }
    ],
    "sg:phone":"+1 724 295 2281",
    "sg:postcode":"16229",
    "sg:province":"PA",
    "sg:tags":[
        "church"
    ],
    "wof:name":"St Mary's RC Church Rectory",
    "wof:placetype":"venue"
},
  "geometry": {"coordinates":[-79.682413,40.674345],"type":"Point"}
}