{
  "type": "Feature",
  "properties": {
    "addr:full":"32 Norman St Pittston PA 18640",
    "addr:housenumber":"32",
    "addr:postcode":"18640",
    "addr:street":"Norman St",
    "iso:country":"US",
    "sg:address":"32 Norman St",
    "sg:city":"Pittston",
    "sg:classifiers":[
        {
            "category":"Restaurant",
            "type":"Food & Drink"
        }
    ],
    "sg:phone":"+1   ",
    "sg:postcode":"18640",
    "sg:province":"PA",
    "sg:tags":[
        "eating"
    ],
    "wof:name":"Joseph Jr P Skrzysowski",
    "wof:placetype":"venue"
},
  "geometry": {"coordinates":[-75.77687299999999,41.316504],"type":"Point"}
}