{
  "type": "Feature",
  "properties": {
    "iso:country":"US",
    "sg:address":"8120 Old York Rd",
    "sg:city":"Elkins Park",
    "sg:classifiers":[
        {
            "category":"Shopping",
            "subcategory":"Bicycles & Sporting Goods",
            "type":"Retail Goods"
        }
    ],
    "sg:phone":"+1 215 782 3752",
    "sg:postcode":"19027",
    "sg:province":"PA",
    "wof:name":"Igloo Sporting Goods",
    "wof:placetype":"venue"
},
  "geometry": {"coordinates":[-75.126418,40.08061],"type":"Point"}
}