{
  "type": "Feature",
  "properties": {
    "iso:country":"US",
    "sg:address":"553 Michell St",
    "sg:city":"Ridley Park",
    "sg:classifiers":[
        {
            "category":"Cinema",
            "subcategory":"Movie Rental",
            "type":"Entertainment"
        }
    ],
    "sg:phone":"+1   ",
    "sg:postcode":"19078",
    "sg:province":"PA",
    "sg:tags":[
        "video",
        "tape"
    ],
    "wof:name":"Act One Video",
    "wof:placetype":"venue"
},
  "geometry": {"coordinates":[-75.320944,39.888271],"type":"Point"}
}