{
  "type": "Feature",
  "properties": {
    "addr:full":"31 Mingo Circle Dr Finleyville PA 15332",
    "addr:housenumber":"31",
    "addr:postcode":"15332",
    "addr:street":"Mingo Circle Dr Finleyville",
    "iso:country":"US",
    "sg:address":"31 Mingo Circle Dr",
    "sg:city":"Finleyville",
    "sg:classifiers":[
        {
            "category":"Retail",
            "subcategory":"Auto Repair",
            "type":"Services"
        }
    ],
    "sg:phone":"+1   ",
    "sg:postcode":"15332",
    "sg:province":"PA",
    "sg:tags":[
        "body"
    ],
    "wof:name":"Bobs Auto Body",
    "wof:placetype":"venue"
},
  "geometry": {"coordinates":[-80.015524,40.235288],"type":"Point"}
}