{
  "type": "Feature",
  "properties": {
    "addr:full":"1010 N Water St Kittanning PA 16201",
    "addr:housenumber":"1010",
    "addr:postcode":"16201",
    "addr:street":"N Water St",
    "iso:country":"US",
    "sg:address":"1010 N Water St",
    "sg:city":"Kittanning",
    "sg:classifiers":[
        {
            "category":"Communications",
            "subcategory":"Film & Video Production",
            "type":"Services"
        }
    ],
    "sg:phone":"+1   ",
    "sg:postcode":"16201",
    "sg:province":"PA",
    "sg:tags":[
        "security",
        "operational",
        "system",
        "surveillance"
    ],
    "wof:name":"Josler Video Systems",
    "wof:placetype":"venue"
},
  "geometry": {"coordinates":[-79.52734599999999,40.824214],"type":"Point"}
}