{
  "type": "Feature",
  "properties": {
    "iso:country":"US",
    "sg:address":"17 Maple St",
    "sg:city":"Lititz",
    "sg:classifiers":[
        {
            "category":"Arts & Performance",
            "subcategory":"Theater",
            "type":"Entertainment"
        }
    ],
    "sg:phone":"+1 717 626 9187",
    "sg:postcode":"17543",
    "sg:province":"PA",
    "sg:tags":[
        "entertainer",
        "group",
        "family"
    ],
    "wof:name":"Ku'Ulei & Keiki Hawaiian Hula",
    "wof:placetype":"venue"
},
  "geometry": {"coordinates":[-76.309865,40.156535],"type":"Point"}
}