{
  "type": "Feature",
  "properties": {
    "addr:full":"6415 Jacksonville Rd Bath PA 18014",
    "addr:housenumber":"6415",
    "addr:postcode":"18014",
    "addr:street":"Jacksonville Rd",
    "iso:country":"US",
    "sg:address":"6415 Jacksonville Rd",
    "sg:city":"Bath",
    "sg:classifiers":[
        {
            "category":"Building & Trades",
            "subcategory":"Construction",
            "type":"Services"
        }
    ],
    "sg:phone":"+1   ",
    "sg:postcode":"18014",
    "sg:province":"PA",
    "sg:tags":[
        "residential"
    ],
    "wof:name":"Imperial Custom Improvements",
    "wof:placetype":"venue"
},
  "geometry": {"coordinates":[-75.402727,40.706845],"type":"Point"}
}