{
  "type": "Feature",
  "properties": {
    "addr:full":"9 Mill St Uniontown PA 15401",
    "addr:housenumber":"9",
    "addr:postcode":"15401",
    "addr:street":"Mill St",
    "iso:country":"US",
    "sg:address":"9 Mill St",
    "sg:city":"Uniontown",
    "sg:classifiers":[
        {
            "category":"Autos & Motor Vehicles",
            "subcategory":"Auto Supplies",
            "type":"Retail Goods"
        }
    ],
    "sg:phone":"+1   ",
    "sg:postcode":"15401",
    "sg:province":"PA",
    "wof:name":"Firestone",
    "wof:placetype":"venue"
},
  "geometry": {"coordinates":[-79.728911,39.900226],"type":"Point"}
}