{
  "type": "Feature",
  "properties": {
    "addr:full":"1822 Middle Rd Glenshaw PA 15116",
    "addr:housenumber":"1822",
    "addr:postcode":"15116",
    "addr:street":"Middle Rd",
    "iso:country":"US",
    "sg:address":"1822 Middle Rd",
    "sg:city":"Glenshaw",
    "sg:classifiers":[
        {
            "category":"Restaurant",
            "type":"Food & Drink"
        }
    ],
    "sg:menulink":"http://www.allmenus.com/pa/indiana/286443-middle-road-inn/menu/",
    "sg:phone":"+1 412 486 7159",
    "sg:postcode":"15116",
    "sg:province":"PA",
    "sg:tags":[
        "american",
        "italian"
    ],
    "wof:name":"Middle Road Inn",
    "wof:placetype":"venue"
},
  "geometry": {"coordinates":[-79.933257,40.538631],"type":"Point"}
}