{
  "type": "Feature",
  "properties": {
    "iso:country":"US",
    "sg:address":"176 Cumberland Pkwy",
    "sg:city":"Mechanicsburg",
    "sg:classifiers":[
        {
            "category":"Professional",
            "subcategory":"Management & Consulting",
            "type":"Services"
        },
        {
            "category":"Professional",
            "subcategory":"Employment Agencies",
            "type":"Services"
        }
    ],
    "sg:phone":"+1 717 691 1129",
    "sg:postcode":"17055",
    "sg:province":"PA",
    "sg:tags":[
        "consultant",
        "business"
    ],
    "wof:name":"Career Services Group",
    "wof:placetype":"venue"
},
  "geometry": {"coordinates":[-76.98984900000001,40.193887],"type":"Point"}
}