{
  "type": "Feature",
  "properties": {
    "addr:full":"3136 William Flynn Hwy Slippery Rock PA 16057",
    "addr:housenumber":"3136",
    "addr:postcode":"16057",
    "addr:street":"William Flynn Hwy",
    "iso:country":"US",
    "sg:address":"3136 William Flynn Hwy",
    "sg:city":"Slippery Rock",
    "sg:classifiers":[
        {
            "category":"Retail",
            "subcategory":"Repair Shop",
            "type":"Services"
        },
        {
            "category":"Home & Garden",
            "subcategory":"Garden Supply",
            "type":"Retail Goods"
        }
    ],
    "sg:phone":"+1 724 794 5723",
    "sg:postcode":"16057",
    "sg:province":"PA",
    "sg:tags":[
        "engine"
    ],
    "wof:name":"Mulligan's",
    "wof:placetype":"venue"
},
  "geometry": {"coordinates":[-80.009077,41.029002],"type":"Point"}
}