{
  "type": "Feature",
  "properties": {
    "addr:full":"3101 Washington Rd Canonsburg PA 15317",
    "addr:housenumber":"3101",
    "addr:postcode":"15317",
    "addr:street":"Washington Rd",
    "iso:country":"US",
    "sg:address":"3101 Washington Rd",
    "sg:city":"Canonsburg",
    "sg:classifiers":[
        {
            "category":"Shopping",
            "type":"Retail Goods"
        }
    ],
    "sg:phone":"+1   ",
    "sg:postcode":"15317",
    "sg:province":"PA",
    "sg:tags":[
        "merchandise"
    ],
    "wof:name":"Riehl Fine Art Gallery",
    "wof:placetype":"venue"
},
  "geometry": {"coordinates":[-80.102586,40.293936],"type":"Point"}
}