{
  "type": "Feature",
  "properties": {
    "addr:full":"7136 Seaford Ave Upper Darby PA 19082",
    "addr:housenumber":"7136",
    "addr:postcode":"19082",
    "addr:street":"Seaford Ave",
    "iso:country":"US",
    "sg:address":"7136 Seaford Ave",
    "sg:city":"Upper Darby",
    "sg:classifiers":[
        {
            "category":"Building & Trades",
            "subcategory":"Cleaning & Sanitation",
            "type":"Services"
        }
    ],
    "sg:phone":"+1 610 626 6631",
    "sg:postcode":"19082",
    "sg:province":"PA",
    "sg:tags":[
        "fireplace",
        "chimney"
    ],
    "wof:name":"Jim Murray's Chimney Svc",
    "wof:placetype":"venue"
},
  "geometry": {"coordinates":[-75.257774,39.946135],"type":"Point"}
}