{
  "type": "Feature",
  "properties": {
    "iso:country":"US",
    "sg:address":"6 Snapdragon Dr",
    "sg:city":"Newtown",
    "sg:classifiers":[
        {
            "category":"Home & Garden",
            "subcategory":"Carpets & Floor Coverings",
            "type":"Retail Goods"
        }
    ],
    "sg:phone":"+1 215 504 4485",
    "sg:postcode":"18940",
    "sg:province":"PA",
    "sg:tags":[
        "dealer",
        "rug"
    ],
    "wof:name":"Nationwide Floor Window Cover",
    "wof:placetype":"venue"
},
  "geometry": {"coordinates":[-74.950884,40.257899],"type":"Point"}
}