{
  "type": "Feature",
  "properties": {
    "iso:country":"US",
    "sg:address":"3425 Fairchild St",
    "sg:city":"Alburtis",
    "sg:classifiers":[
        {
            "category":"Building & Trades",
            "subcategory":"Construction",
            "type":"Services"
        }
    ],
    "sg:phone":"+1   ",
    "sg:postcode":"18011",
    "sg:province":"PA",
    "sg:tags":[
        "residential",
        "industrial"
    ],
    "wof:name":"Right Angle Builders",
    "wof:placetype":"venue"
},
  "geometry": {"coordinates":[-75.616804,40.498674],"type":"Point"}
}