{
  "type": "Feature",
  "properties": {
    "addr:full":"316 N 3rd St Jeannette PA 15644",
    "addr:housenumber":"316",
    "addr:postcode":"15644",
    "addr:street":"N 3Rd St",
    "iso:country":"US",
    "sg:address":"316 N 3rd St",
    "sg:city":"Jeannette",
    "sg:classifiers":[
        {
            "category":"Shopping",
            "subcategory":"Used Merchandise",
            "type":"Retail Goods"
        }
    ],
    "sg:phone":"+1   ",
    "sg:postcode":"15644",
    "sg:province":"PA",
    "wof:name":"Cramer S Antiques",
    "wof:placetype":"venue"
},
  "geometry": {"coordinates":[-79.612666,40.330741],"type":"Point"}
}