{
  "type": "Feature",
  "properties": {
    "iso:country":"US",
    "sg:address":"240 Liberty Ln",
    "sg:city":"Duncansville",
    "sg:classifiers":[
        {
            "category":"Retail",
            "subcategory":"Repair Shop",
            "type":"Services"
        }
    ],
    "sg:phone":"+1   ",
    "sg:postcode":"16635",
    "sg:province":"PA",
    "wof:name":"Freedom Gun Repair",
    "wof:placetype":"venue"
},
  "geometry": {"coordinates":[-78.45878999999999,40.389273],"type":"Point"}
}