{
  "type": "Feature",
  "properties": {
    "iso:country":"US",
    "sg:address":"2119 Whitaker Way",
    "sg:city":"Homestead",
    "sg:classifiers":[
        {
            "category":"Building & Trades",
            "subcategory":"Construction",
            "type":"Services"
        }
    ],
    "sg:phone":"+1 412 461 6800",
    "sg:postcode":"15120",
    "sg:province":"PA",
    "sg:tags":[
        "roofing",
        "contractor"
    ],
    "wof:name":"Hausler Roofing Inc",
    "wof:placetype":"venue"
},
  "geometry": {"coordinates":[-79.888445,40.401883],"type":"Point"}
}