{
  "type": "Feature",
  "properties": {
    "iso:country":"US",
    "sg:address":"30 Runway Rd",
    "sg:city":"Levittown",
    "sg:classifiers":[
        {
            "category":"Professional",
            "subcategory":"Business Services",
            "type":"Services"
        }
    ],
    "sg:phone":"+1 215 943 9400",
    "sg:postcode":"19057",
    "sg:province":"PA",
    "sg:tags":[
        "packaging",
        "specialty",
        "contract",
        "fulfillment"
    ],
    "wof:name":"Assured Packaging Inc",
    "wof:placetype":"venue"
},
  "geometry": {"coordinates":[-74.847323,40.12618],"type":"Point"}
}