{
  "type": "Feature",
  "properties": {
    "iso:country":"US",
    "sg:address":"350 Eagleview Blvd",
    "sg:city":"Exton",
    "sg:classifiers":[
        {
            "category":"Wholesale",
            "subcategory":"Medical Equipment & Supplies",
            "type":"Manufacturing & Wholesale Goods"
        }
    ],
    "sg:phone":"+1 610 363 9125",
    "sg:postcode":"19341",
    "sg:province":"PA",
    "sg:tags":[
        "optical"
    ],
    "wof:name":"Iport Media",
    "wof:placetype":"venue"
},
  "geometry": {"coordinates":[-75.67027299999999,40.057146],"type":"Point"}
}