{
  "type": "Feature",
  "properties": {
    "iso:country":"US",
    "sg:address":"1121 Boyce Rd",
    "sg:city":"Pittsburgh",
    "sg:classifiers":[
        {
            "category":"Government",
            "subcategory":"Court House",
            "type":"Public Place"
        }
    ],
    "sg:phone":"+1   ",
    "sg:postcode":"15241",
    "sg:province":"PA",
    "wof:name":"Magisterial District 05-3-16",
    "wof:placetype":"venue"
},
  "geometry": {"coordinates":[-80.107339,40.315237],"type":"Point"}
}