{
  "type": "Feature",
  "properties": {
    "addr:full":"502 Market St Lemoyne PA 17043",
    "addr:housenumber":"502",
    "addr:postcode":"17043",
    "addr:street":"Market St",
    "iso:country":"US",
    "sg:address":"502 Market St",
    "sg:city":"Lemoyne",
    "sg:classifiers":[
        {
            "category":"Professional",
            "subcategory":"Lawyer & Legal Services",
            "type":"Services"
        }
    ],
    "sg:phone":"+1 717 737 5255",
    "sg:postcode":"17043",
    "sg:province":"PA",
    "wof:name":"Hugel Christian C Attorney",
    "wof:placetype":"venue"
},
  "geometry": {"coordinates":[-76.896896,40.245701],"type":"Point"}
}