{
  "type": "Feature",
  "properties": {
    "iso:country":"US",
    "sg:address":"Concordville Town Ctr",
    "sg:city":"Concordville",
    "sg:classifiers":[
        {
            "category":"Food & Beverages",
            "subcategory":"Bakery",
            "type":"Retail Goods"
        }
    ],
    "sg:phone":"+1 610 361 0300",
    "sg:postcode":"19331",
    "sg:province":"PA",
    "sg:tags":[
        "sandwich"
    ],
    "wof:name":"Capriotti's Sandwich Shop",
    "wof:placetype":"venue"
},
  "geometry": {"coordinates":[-75.53293499999999,39.888414],"type":"Point"}
}