{
  "type": "Feature",
  "properties": {
    "iso:country":"US",
    "sg:address":"1824 W Girard Ave",
    "sg:city":"Philadelphia",
    "sg:classifiers":[
        {
            "category":"Building & Trades",
            "subcategory":"Plumbing",
            "type":"Services"
        }
    ],
    "sg:phone":"+1 215 765 1600",
    "sg:postcode":"19130",
    "sg:province":"PA",
    "sg:tags":[
        "home",
        "improvement",
        "contractor"
    ],
    "wof:name":"Houston & Smith Inc",
    "wof:placetype":"venue"
},
  "geometry": {"coordinates":[-75.16660299999999,39.9725],"type":"Point"}
}