{
  "type": "Feature",
  "properties": {
    "iso:country":"US",
    "sg:address":"265 Scranton Carbondale Hwy",
    "sg:city":"Scranton",
    "sg:classifiers":[
        {
            "category":"Shopping",
            "subcategory":"Shoes",
            "type":"Retail Goods"
        }
    ],
    "sg:phone":"+1 570 558 6826",
    "sg:postcode":"18508",
    "sg:province":"PA",
    "wof:name":"Shoe String",
    "wof:placetype":"venue"
},
  "geometry": {"coordinates":[-75.656462,41.462672],"type":"Point"}
}