{
  "type": "Feature",
  "properties": {
    "iso:country":"US",
    "sg:address":"2212 E National Pike",
    "sg:city":"Scenery Hill",
    "sg:classifiers":[
        {
            "category":"Shopping",
            "subcategory":"Bicycles & Sporting Goods",
            "type":"Retail Goods"
        }
    ],
    "sg:phone":"+1   ",
    "sg:postcode":"15360",
    "sg:province":"PA",
    "sg:tags":[
        "mfg"
    ],
    "wof:name":"Sport About Sporting",
    "wof:placetype":"venue"
},
  "geometry": {"coordinates":[-80.068977,40.085381],"type":"Point"}
}