{
  "type": "Feature",
  "properties": {
    "addr:full":"1013 Regency Cir Blue Bell PA 19422",
    "addr:housenumber":"1013",
    "addr:postcode":"19422",
    "addr:street":"Regency Cir",
    "iso:country":"US",
    "sg:address":"1013 Regency Cir",
    "sg:city":"Blue Bell",
    "sg:classifiers":[
        {
            "category":"Health Services",
            "subcategory":"Doctor",
            "type":"Services"
        }
    ],
    "sg:phone":"+1   ",
    "sg:postcode":"19422",
    "sg:province":"PA",
    "sg:tags":[
        "medical"
    ],
    "wof:name":"H Philip Strunk MD PC",
    "wof:placetype":"venue"
},
  "geometry": {"coordinates":[-75.244314,40.176483],"type":"Point"}
}