{
  "type": "Feature",
  "properties": {
    "addr:full":"1663 S Atherton St State College PA 16801",
    "addr:housenumber":"1663",
    "addr:postcode":"16801",
    "addr:street":"S Atherton St",
    "iso:country":"US",
    "sg:address":"1663 S Atherton St",
    "sg:city":"State College",
    "sg:classifiers":[
        {
            "category":"Shopping",
            "subcategory":"Computers & Home Electronics",
            "type":"Retail Goods"
        }
    ],
    "sg:phone":"+1 814 237 3001",
    "sg:postcode":"16801",
    "sg:province":"PA",
    "sg:tags":[
        "software"
    ],
    "sg:website":"www.atiinternational.com",
    "wof:name":"ATI",
    "wof:placetype":"venue"
},
  "geometry": {"coordinates":[-77.834799,40.78529],"type":"Point"}
}