{
  "type": "Feature",
  "properties": {
    "iso:country":"US",
    "sg:address":"1167 Forest Hills Dr",
    "sg:city":"Salix",
    "sg:classifiers":[
        {
            "category":"Retail",
            "subcategory":"Auto Repair",
            "type":"Services"
        }
    ],
    "sg:phone":"+1 814 487 5701",
    "sg:postcode":"15952",
    "sg:province":"PA",
    "sg:tags":[
        "repairing",
        "automobile"
    ],
    "wof:name":"Miller Motor Co",
    "wof:placetype":"venue"
},
  "geometry": {"coordinates":[-78.766429,40.297218],"type":"Point"}
}