{
  "type": "Feature",
  "properties": {
    "addr:full":"271 Plank Rd Somerset PA 15501",
    "addr:housenumber":"271",
    "addr:postcode":"15501",
    "addr:street":"Plank Rd",
    "iso:country":"US",
    "sg:address":"271 Plank Rd",
    "sg:city":"Somerset",
    "sg:classifiers":[
        {
            "category":"Shopping",
            "subcategory":"Computers & Home Electronics",
            "type":"Retail Goods"
        }
    ],
    "sg:phone":"+1   ",
    "sg:postcode":"15501",
    "sg:province":"PA",
    "sg:tags":[
        "equipment",
        "stereo",
        "video"
    ],
    "wof:name":"Video Haven",
    "wof:placetype":"venue"
},
  "geometry": {"coordinates":[-79.064252,40.003008],"type":"Point"}
}