{
  "type": "Feature",
  "properties": {
    "iso:country":"US",
    "sg:address":"1353 N Cottonwood Rd",
    "sg:city":"Danielsville",
    "sg:classifiers":[
        {
            "category":"Shopping",
            "type":"Retail Goods"
        }
    ],
    "sg:phone":"+1   ",
    "sg:postcode":"18038",
    "sg:province":"PA",
    "sg:tags":[
        "merchandise"
    ],
    "wof:name":"Dr Machine Shop",
    "wof:placetype":"venue"
},
  "geometry": {"coordinates":[-75.49952999999999,40.799284],"type":"Point"}
}