{
  "type": "Feature",
  "properties": {
    "addr:full":"3 Riverview Dr Liverpool PA 17025",
    "addr:housenumber":"3",
    "addr:postcode":"17025",
    "addr:street":"Riverview Dr",
    "iso:country":"US",
    "sg:address":"3 Riverview Dr",
    "sg:city":"Liverpool",
    "sg:classifiers":[
        {
            "category":"Freight",
            "type":"Transportation"
        }
    ],
    "sg:phone":"+1   ",
    "sg:postcode":"17025",
    "sg:province":"PA",
    "sg:tags":[
        "operator",
        "local",
        "trucking"
    ],
    "wof:name":"Williamson & Son Trucking",
    "wof:placetype":"venue"
},
  "geometry": {"coordinates":[-76.947142,40.280415],"type":"Point"}
}