{
  "type": "Feature",
  "properties": {
    "addr:full":"514 Royalty Dr Uniontown PA 15401",
    "addr:housenumber":"514",
    "addr:postcode":"15401",
    "addr:street":"Royalty Dr",
    "iso:country":"US",
    "sg:address":"514 Royalty Dr",
    "sg:city":"Uniontown",
    "sg:classifiers":[
        {
            "category":"Social Services",
            "subcategory":"Job Training",
            "type":"Services"
        }
    ],
    "sg:phone":"+1   ",
    "sg:postcode":"15401",
    "sg:province":"PA",
    "sg:tags":[
        "school",
        "program",
        "after"
    ],
    "wof:name":"Young Inspiration Inc",
    "wof:placetype":"venue"
},
  "geometry": {"coordinates":[-79.75765800000001,39.892475],"type":"Point"}
}