{
  "type": "Feature",
  "properties": {
    "iso:country":"US",
    "sg:address":"2347 Aetna Dr",
    "sg:city":"Pittsburgh",
    "sg:classifiers":[
        {
            "category":"Shopping",
            "subcategory":"Clothing, Apparel, & Fashions",
            "type":"Retail Goods"
        }
    ],
    "sg:phone":"+1   ",
    "sg:postcode":"15241",
    "sg:province":"PA",
    "wof:name":"Mark Hopkins",
    "wof:placetype":"venue"
},
  "geometry": {"coordinates":[-80.08842300000001,40.337449],"type":"Point"}
}