{
  "type": "Feature",
  "properties": {
    "iso:country":"US",
    "sg:address":"187 City Line Ave",
    "sg:city":"Bala Cynwyd",
    "sg:classifiers":[
        {
            "category":"Health Services",
            "subcategory":"Dentist",
            "type":"Services"
        }
    ],
    "sg:phone":"+1 610 667 9713",
    "sg:postcode":"19004",
    "sg:province":"PA",
    "wof:name":"Korn Gerald DDS",
    "wof:placetype":"venue"
},
  "geometry": {"coordinates":[-75.23477699999999,39.997467],"type":"Point"}
}