{
  "type": "Feature",
  "properties": {
    "iso:country":"US",
    "sg:address":"2275 Swallow Hill Rd",
    "sg:city":"Pittsburgh",
    "sg:classifiers":[
        {
            "category":"Professional",
            "subcategory":"Accounting & Tax Preparation",
            "type":"Services"
        }
    ],
    "sg:phone":"+1   ",
    "sg:postcode":"15220",
    "sg:province":"PA",
    "wof:name":"Hoag R D & Associates",
    "wof:placetype":"venue"
},
  "geometry": {"coordinates":[-80.073773,40.390858],"type":"Point"}
}