{
  "type": "Feature",
  "properties": {
    "addr:full":"1 Ivybrook Blvd Warminster PA 18974",
    "addr:housenumber":"1",
    "addr:postcode":"18974",
    "addr:street":"Ivybrook Blvd",
    "iso:country":"US",
    "sg:address":"1 Ivybrook Blvd",
    "sg:city":"Warminster",
    "sg:classifiers":[
        {
            "category":"Professional",
            "subcategory":"Management & Consulting",
            "type":"Services"
        }
    ],
    "sg:phone":"+1 215 444 0682",
    "sg:postcode":"18974",
    "sg:province":"PA",
    "sg:tags":[
        "fuel"
    ],
    "wof:name":"Corp Claims Mgmt Inc",
    "wof:placetype":"venue"
},
  "geometry": {"coordinates":[-75.07316299999999,40.214447],"type":"Point"}
}