{
  "type": "Feature",
  "properties": {
    "iso:country":"US",
    "sg:address":"267 E Market St",
    "sg:city":"York",
    "sg:classifiers":[
        {
            "category":"Professional",
            "subcategory":"Lawyer & Legal Services",
            "type":"Services"
        }
    ],
    "sg:phone":"+1   ",
    "sg:postcode":"17403",
    "sg:province":"PA",
    "sg:tags":[
        "law"
    ],
    "wof:name":"Wolfson & Associates PC",
    "wof:placetype":"venue"
},
  "geometry": {"coordinates":[-76.72297,39.963929],"type":"Point"}
}