{
  "type": "Feature",
  "properties": {
    "addr:full":"2710 Mercer Rd New Castle PA 16105",
    "addr:housenumber":"2710",
    "addr:postcode":"16105",
    "addr:street":"Mercer Rd New",
    "iso:country":"US",
    "sg:address":"2710 Mercer Rd",
    "sg:city":"New Castle",
    "sg:classifiers":[
        {
            "category":"Restaurant",
            "type":"Food & Drink"
        }
    ],
    "sg:phone":"+1 724 658 8800",
    "sg:postcode":"16105",
    "sg:province":"PA",
    "sg:tags":[
        "eating"
    ],
    "wof:name":"Steamers Coffee & Tea Co",
    "wof:placetype":"venue"
},
  "geometry": {"coordinates":[-80.338413,41.032468],"type":"Point"}
}