{
  "type": "Feature",
  "properties": {
    "iso:country":"US",
    "sg:address":"11232 Mckee Rd",
    "sg:city":"Irwin",
    "sg:classifiers":[
        {
            "category":"Restaurant",
            "type":"Food & Drink"
        }
    ],
    "sg:menulink":"http://www.allmenus.com/pa/north-huntingdon/286664-pizza--gyro-express/menu/",
    "sg:phone":"+1 724 864 9959",
    "sg:postcode":"15642",
    "sg:province":"PA",
    "sg:tags":[
        "gyro",
        "american",
        "pizza"
    ],
    "wof:name":"Pizza & Gyro Express",
    "wof:placetype":"venue"
},
  "geometry": {"coordinates":[-79.731013,40.316962],"type":"Point"}
}