{
  "type": "Feature",
  "properties": {
    "iso:country":"US",
    "sg:address":"714 Philadelphia St",
    "sg:city":"Indiana",
    "sg:classifiers":[
        {
            "category":"Shopping",
            "subcategory":"Stationery & Office Supplies",
            "type":"Retail Goods"
        }
    ],
    "sg:phone":"+1 724 463 9111",
    "sg:postcode":"15701",
    "sg:province":"PA",
    "sg:tags":[
        "machine",
        "fur",
        "business"
    ],
    "wof:name":"Henry Hall Office Products",
    "wof:placetype":"venue"
},
  "geometry": {"coordinates":[-79.15451899999999,40.622899],"type":"Point"}
}