{
  "type": "Feature",
  "properties": {
    "addr:full":"2979 W School House Ln Philadelphia PA 19144",
    "addr:housenumber":"2979",
    "addr:postcode":"19144",
    "addr:street":"W School House Ln",
    "iso:country":"US",
    "sg:address":"2979 W School House Ln",
    "sg:city":"Philadelphia",
    "sg:classifiers":[
        {
            "category":"Personal",
            "type":"Services"
        }
    ],
    "sg:phone":"+1 215 844 1313",
    "sg:postcode":"19144",
    "sg:province":"PA",
    "sg:tags":[
        "therapist",
        "massage"
    ],
    "wof:name":"Barbara Isard",
    "wof:placetype":"venue"
},
  "geometry": {"coordinates":[-75.184608,40.024651],"type":"Point"}
}