{
  "type": "Feature",
  "properties": {
    "addr:full":"888 Town Center Dr Langhorne PA 19047",
    "addr:housenumber":"888",
    "addr:postcode":"19047",
    "addr:street":"Town Center Dr",
    "iso:country":"US",
    "sg:address":"888 Town Center Dr",
    "sg:city":"Langhorne",
    "sg:classifiers":[
        {
            "category":"Professional",
            "subcategory":"Computer Services",
            "type":"Services"
        }
    ],
    "sg:phone":"+1 215 757 7411",
    "sg:postcode":"19047",
    "sg:province":"PA",
    "sg:tags":[
        "leasing"
    ],
    "wof:name":"Rentacom Inc",
    "wof:placetype":"venue"
},
  "geometry": {"coordinates":[-74.880354,40.187912],"type":"Point"}
}