{
  "type": "Feature",
  "properties": {
    "addr:full":"1018 Lake St Lake City PA 16423",
    "addr:housenumber":"1018",
    "addr:postcode":"16423",
    "addr:street":"Lake St",
    "iso:country":"US",
    "sg:address":"1018 Lake St",
    "sg:city":"Lake City",
    "sg:classifiers":[
        {
            "category":"Building & Trades",
            "subcategory":"Construction",
            "type":"Services"
        }
    ],
    "sg:phone":"+1 814 774 2986",
    "sg:postcode":"16423",
    "sg:province":"PA",
    "sg:tags":[
        "general",
        "contractor"
    ],
    "wof:name":"Lake Erie Construction Co",
    "wof:placetype":"venue"
},
  "geometry": {"coordinates":[-80.34523900000001,42.025178],"type":"Point"}
}