{
  "type": "Feature",
  "properties": {
    "addr:full":"942 Randolph Dr Morrisville PA 19067",
    "addr:housenumber":"942",
    "addr:postcode":"19067",
    "addr:street":"Randolph Dr",
    "iso:country":"US",
    "sg:address":"942 Randolph Dr",
    "sg:city":"Morrisville",
    "sg:classifiers":[
        {
            "category":"Building & Trades",
            "subcategory":"Landscaping Services",
            "type":"Services"
        }
    ],
    "sg:phone":"+1   ",
    "sg:postcode":"19067",
    "sg:province":"PA",
    "wof:name":"JPS Landscaping",
    "wof:placetype":"venue"
},
  "geometry": {"coordinates":[-74.85124399999999,40.235093],"type":"Point"}
}