{
  "type": "Feature",
  "properties": {
    "iso:country":"US",
    "sg:address":"204 Congruity Rd",
    "sg:city":"Greensburg",
    "sg:classifiers":[
        {
            "category":"Manufacturing",
            "subcategory":"Printing",
            "type":"Manufacturing & Wholesale Goods"
        }
    ],
    "sg:phone":"+1   ",
    "sg:postcode":"15601",
    "sg:province":"PA",
    "sg:tags":[
        "commercial"
    ],
    "wof:name":"Ickes",
    "wof:placetype":"venue"
},
  "geometry": {"coordinates":[-79.505078,40.405859],"type":"Point"}
}