{
  "type": "Feature",
  "properties": {
    "addr:full":"1175 Macarthur Rd Whitehall PA 18052",
    "addr:housenumber":"1175",
    "addr:postcode":"18052",
    "addr:street":"Macarthur Rd",
    "iso:country":"US",
    "sg:address":"1175 Macarthur Rd",
    "sg:city":"Whitehall",
    "sg:classifiers":[
        {
            "category":"Sports & Exercise",
            "subcategory":"Gym",
            "type":"Entertainment"
        }
    ],
    "sg:phone":"+1 610 439 4111",
    "sg:postcode":"18052",
    "sg:province":"PA",
    "sg:tags":[
        "club",
        "health",
        "studio",
        "gymnasium"
    ],
    "wof:name":"Body Central",
    "wof:placetype":"venue"
},
  "geometry": {"coordinates":[-75.480431,40.620816],"type":"Point"}
}