{
  "type": "Feature",
  "properties": {
    "iso:country":"US",
    "sg:address":"450 Manatawny St",
    "sg:city":"Pottstown",
    "sg:classifiers":[
        {
            "category":"Wholesale",
            "subcategory":"Electrical",
            "type":"Manufacturing & Wholesale Goods"
        }
    ],
    "sg:phone":"+1 610 323 4952",
    "sg:postcode":"19464",
    "sg:province":"PA",
    "sg:tags":[
        "electric",
        "motor"
    ],
    "wof:name":"Barney's Electric Motor Svc",
    "wof:placetype":"venue"
},
  "geometry": {"coordinates":[-75.65591499999999,40.257327],"type":"Point"}
}