{
  "type": "Feature",
  "properties": {
    "addr:full":"5311 Oxford Ave Philadelphia PA 19124",
    "addr:housenumber":"5311",
    "addr:postcode":"19124",
    "addr:street":"Oxford Ave",
    "iso:country":"US",
    "sg:address":"5311 Oxford Ave",
    "sg:city":"Philadelphia",
    "sg:classifiers":[
        {
            "category":"Shopping",
            "subcategory":"Clothing, Apparel, & Fashions",
            "type":"Retail Goods"
        }
    ],
    "sg:phone":"+1 215 288 6228",
    "sg:postcode":"19124",
    "sg:province":"PA",
    "wof:name":"Rah's Fashion Boutique",
    "wof:placetype":"venue"
},
  "geometry": {"coordinates":[-75.085144,40.029339],"type":"Point"}
}