{
  "type": "Feature",
  "properties": {
    "iso:country":"US",
    "sg:address":"20 St & Moyamensing Ave",
    "sg:city":"Philadelphia",
    "sg:classifiers":[
        {
            "category":"Professional",
            "type":"Services"
        }
    ],
    "sg:phone":"+1 215 271 9083",
    "sg:postcode":"19145",
    "sg:province":"PA",
    "sg:tags":[
        "caterer"
    ],
    "wof:name":"Galdo's Catering & Entertainment",
    "wof:placetype":"venue"
},
  "geometry": {"coordinates":[-75.18185800000001,39.91368],"type":"Point"}
}