{
  "type": "Feature",
  "properties": {
    "iso:country":"US",
    "sg:address":"5694 Rising Sun Ave",
    "sg:city":"Philadelphia",
    "sg:classifiers":[
        {
            "category":"Restaurant",
            "type":"Food & Drink"
        }
    ],
    "sg:phone":"+1 215 722 5059",
    "sg:postcode":"19120",
    "sg:province":"PA",
    "wof:name":"Asia Cafe",
    "wof:placetype":"venue"
},
  "geometry": {"coordinates":[-75.109019,40.039539],"type":"Point"}
}