{
  "type": "Feature",
  "properties": {
    "iso:country":"US",
    "sg:address":"656 E Street Rd",
    "sg:city":"Churchville",
    "sg:classifiers":[
        {
            "category":"Real Estate",
            "subcategory":"Real Estate Agent",
            "type":"Services"
        }
    ],
    "sg:phone":"+1 215 953 9229",
    "sg:postcode":"18966",
    "sg:province":"PA",
    "wof:name":"First Access Realty Inc",
    "wof:placetype":"venue"
},
  "geometry": {"coordinates":[-75.044657,40.174981],"type":"Point"}
}