{
  "type": "Feature",
  "properties": {
    "addr:full":"2003 31st St SW Allentown PA 18103",
    "addr:housenumber":"2003",
    "addr:postcode":"18103",
    "addr:street":"31St St Sw",
    "iso:country":"US",
    "sg:address":"2003 31st St SW",
    "sg:city":"Allentown",
    "sg:classifiers":[
        {
            "category":"Professional",
            "subcategory":"Art Services",
            "type":"Services"
        }
    ],
    "sg:phone":"+1 610 797 8253",
    "sg:postcode":"18103",
    "sg:province":"PA",
    "sg:tags":[
        "commercial",
        "design",
        "artist"
    ],
    "sg:website":"www.publicationdesign.com",
    "wof:name":"Publication Design Inc",
    "wof:placetype":"venue"
},
  "geometry": {"coordinates":[-75.48920699999999,40.55878],"type":"Point"}
}