{
  "type": "Feature",
  "properties": {
    "iso:country":"US",
    "sg:address":"724 9th Ave",
    "sg:city":"Prospect Park",
    "sg:classifiers":[
        {
            "category":"Building & Trades",
            "subcategory":"Construction",
            "type":"Services"
        }
    ],
    "sg:phone":"+1   ",
    "sg:postcode":"19076",
    "sg:province":"PA",
    "sg:tags":[
        "contractor"
    ],
    "wof:name":"Robert J Sekel Contracting",
    "wof:placetype":"venue"
},
  "geometry": {"coordinates":[-75.307688,39.885342],"type":"Point"}
}