{
  "type": "Feature",
  "properties": {
    "iso:country":"US",
    "sg:address":"333 Linden Ln",
    "sg:city":"Reading",
    "sg:classifiers":[
        {
            "category":"Shopping",
            "subcategory":"Clothing, Apparel, & Fashions",
            "type":"Retail Goods"
        }
    ],
    "sg:phone":"+1   ",
    "sg:postcode":"19611",
    "sg:province":"PA",
    "wof:name":"Alternatives In Motherhood",
    "wof:placetype":"venue"
},
  "geometry": {"coordinates":[-75.942961,40.330944],"type":"Point"}
}