{
  "type": "Feature",
  "properties": {
    "iso:country":"US",
    "sg:address":"150 School Rd",
    "sg:city":"Womelsdorf",
    "sg:phone":"+1   ",
    "sg:postcode":"19567",
    "sg:province":"PA",
    "sg:tags":[
        "farm",
        "corn"
    ],
    "wof:name":"Mervin Brubaker",
    "wof:placetype":"venue"
},
  "geometry": {"coordinates":[-76.208101,40.391829],"type":"Point"}
}