{
  "type": "Feature",
  "properties": {
    "iso:country":"US",
    "sg:address":"3971 6th Ave",
    "sg:city":"Altoona",
    "sg:classifiers":[
        {
            "category":"Building & Trades",
            "subcategory":"Construction",
            "type":"Services"
        }
    ],
    "sg:phone":"+1   ",
    "sg:postcode":"16602",
    "sg:province":"PA",
    "sg:tags":[
        "painting",
        "contractor"
    ],
    "wof:name":"Longstreth Bros Pntg Decoratin",
    "wof:placetype":"venue"
},
  "geometry": {"coordinates":[-78.41468999999999,40.486962],"type":"Point"}
}