{
  "type": "Feature",
  "properties": {
    "iso:country":"US",
    "sg:address":"732 Pershing St",
    "sg:city":"Ellwood City",
    "sg:classifiers":[
        {
            "category":"Professional",
            "type":"Services"
        }
    ],
    "sg:phone":"+1 724 758 2110",
    "sg:postcode":"16117",
    "sg:province":"PA",
    "sg:tags":[
        "establishment"
    ],
    "wof:name":"Outreach Care Group Contract",
    "wof:placetype":"venue"
},
  "geometry": {"coordinates":[-80.27454899999999,40.869516],"type":"Point"}
}