{
  "type": "Feature",
  "properties": {
    "iso:country":"US",
    "sg:address":"28 S 3rd St",
    "sg:city":"Hamburg",
    "sg:classifiers":[
        {
            "category":"Shopping",
            "subcategory":"Gifts & Souvenirs",
            "type":"Retail Goods"
        }
    ],
    "sg:phone":"+1   ",
    "sg:postcode":"19526",
    "sg:province":"PA",
    "wof:name":"Washpin Pals",
    "wof:placetype":"venue"
},
  "geometry": {"coordinates":[-75.98379199999999,40.554399],"type":"Point"}
}