{
  "type": "Feature",
  "properties": {
    "iso:country":"US",
    "sg:address":"1301 Mazetti Rd",
    "sg:city":"Stroudsburg",
    "sg:classifiers":[
        {
            "category":"Wholesale",
            "subcategory":"Non-durable Goods",
            "type":"Manufacturing & Wholesale Goods"
        }
    ],
    "sg:phone":"+1 570 421 1789",
    "sg:postcode":"18360",
    "sg:province":"PA",
    "sg:tags":[
        "tree",
        "christmas"
    ],
    "wof:name":"Tree Farm",
    "wof:placetype":"venue"
},
  "geometry": {"coordinates":[-75.21634299999999,41.001968],"type":"Point"}
}