{
  "type": "Feature",
  "properties": {
    "iso:country":"US",
    "sg:address":"422 N Main St",
    "sg:city":"Wilkes Barre",
    "sg:classifiers":[
        {
            "category":"Personal",
            "subcategory":"Beauty Salon",
            "type":"Services"
        }
    ],
    "sg:phone":"+1 570 826 1471",
    "sg:postcode":"18702",
    "sg:province":"PA",
    "wof:name":"Edie Sulkoski Beauty Salon",
    "wof:placetype":"venue"
},
  "geometry": {"coordinates":[-75.869508,41.253049],"type":"Point"}
}