{
  "type": "Feature",
  "properties": {
    "iso:country":"US",
    "sg:address":"20 Troy Dr",
    "sg:city":"Lititz",
    "sg:classifiers":[
        {
            "category":"Professional",
            "subcategory":"Art Services",
            "type":"Services"
        }
    ],
    "sg:phone":"+1 717 625 3707",
    "sg:postcode":"17543",
    "sg:province":"PA",
    "sg:tags":[
        "graphic",
        "designer"
    ],
    "wof:name":"Pipe Dream Studio",
    "wof:placetype":"venue"
},
  "geometry": {"coordinates":[-76.32414300000001,40.184443],"type":"Point"}
}