{
  "type": "Feature",
  "properties": {
    "iso:country":"US",
    "sg:address":"3257 W Liberty Ave",
    "sg:city":"Pittsburgh",
    "sg:classifiers":[
        {
            "category":"Wholesale",
            "subcategory":"Auto Parts",
            "type":"Manufacturing & Wholesale Goods"
        }
    ],
    "sg:phone":"+1   ",
    "sg:postcode":"15216",
    "sg:province":"PA",
    "wof:name":"Dormont Accessory and Btry Svc",
    "wof:placetype":"venue"
},
  "geometry": {"coordinates":[-80.02748699999999,40.398127],"type":"Point"}
}