{
  "type": "Feature",
  "properties": {
    "addr:full":"456 3rd St California PA 15419",
    "addr:housenumber":"456",
    "addr:postcode":"15419",
    "addr:street":"3Rd St",
    "iso:country":"US",
    "sg:address":"456 3rd St",
    "sg:city":"California",
    "sg:classifiers":[
        {
            "category":"Professional",
            "subcategory":"Printing & Photocopies",
            "type":"Services"
        }
    ],
    "sg:phone":"+1 724 938 0117",
    "sg:postcode":"15419",
    "sg:province":"PA",
    "sg:tags":[
        "photocopying",
        "electronic",
        "duplicating",
        "copying"
    ],
    "sg:website":"http://www.copycat.net",
    "wof:name":"Copycat",
    "wof:placetype":"venue"
},
  "geometry": {"coordinates":[-79.88906799999999,40.066349],"type":"Point"}
}