{
  "type": "Feature",
  "properties": {
    "addr:full":"1900 S Broad St Philadelphia PA 19145",
    "addr:housenumber":"1900",
    "addr:postcode":"19145",
    "addr:street":"S Broad St",
    "iso:country":"US",
    "sg:address":"1900 S Broad St",
    "sg:city":"Philadelphia",
    "sg:classifiers":[
        {
            "category":"Health Services",
            "subcategory":"Podiatrist",
            "type":"Services"
        }
    ],
    "sg:phone":"+1 215 462 0501",
    "sg:postcode":"19145",
    "sg:province":"PA",
    "wof:name":"Ramon C Lopez DPM",
    "wof:placetype":"venue"
},
  "geometry": {"coordinates":[-75.169494,39.925596],"type":"Point"}
}