{
  "type": "Feature",
  "properties": {
    "iso:country":"US",
    "sg:address":"28 Vanderbilt St",
    "sg:city":"Commodore",
    "sg:classifiers":[
        {
            "category":"Retail",
            "subcategory":"Auto Repair",
            "type":"Services"
        }
    ],
    "sg:phone":"+1 724 254 1044",
    "sg:postcode":"15729",
    "sg:province":"PA",
    "sg:tags":[
        "body",
        "automobile",
        "painting"
    ],
    "wof:name":"Buddy's Auto Body",
    "wof:placetype":"venue"
},
  "geometry": {"coordinates":[-78.943687,40.712489],"type":"Point"}
}