{
  "type": "Feature",
  "properties": {
    "iso:country":"US",
    "sg:address":"305 S 60th St",
    "sg:city":"Philadelphia",
    "sg:classifiers":[
        {
            "category":"Shopping",
            "subcategory":"Optical Goods",
            "type":"Retail Goods"
        }
    ],
    "sg:phone":"+1 215 474 1390",
    "sg:postcode":"19143",
    "sg:province":"PA",
    "sg:tags":[
        "optician",
        "eyewear"
    ],
    "wof:name":"Golden Optical Inc",
    "wof:placetype":"venue"
},
  "geometry": {"coordinates":[-75.241798,39.956299],"type":"Point"}
}