{
  "type": "Feature",
  "properties": {
    "iso:country":"US",
    "sg:address":"8406 Strahle Ter",
    "sg:city":"Philadelphia",
    "sg:classifiers":[
        {
            "category":"Insurance",
            "subcategory":"Insurance Agent",
            "type":"Services"
        }
    ],
    "sg:phone":"+1 215 725 4444",
    "sg:postcode":"19111",
    "sg:province":"PA",
    "sg:tags":[
        "adjuster"
    ],
    "wof:name":"Amjet Insurance Adjusters Inc",
    "wof:placetype":"venue"
},
  "geometry": {"coordinates":[-75.067993,40.076796],"type":"Point"}
}