{
  "type": "Feature",
  "properties": {
    "iso:country":"US",
    "sg:address":"7927 Frankford Ave",
    "sg:city":"Philadelphia",
    "sg:classifiers":[
        {
            "category":"Education",
            "subcategory":"School",
            "type":"Public Place"
        }
    ],
    "sg:phone":"+1 215 335 4323",
    "sg:postcode":"19136",
    "sg:province":"PA",
    "wof:name":"Holmesburg Baptist Chrstn Schl",
    "wof:placetype":"venue"
},
  "geometry": {"coordinates":[-75.028575,40.041129],"type":"Point"}
}