{
  "type": "Feature",
  "properties": {
    "addr:full":"3950 Nebraska Ave Levittown PA 19056",
    "addr:housenumber":"3950",
    "addr:postcode":"19056",
    "addr:street":"Nebraska Ave",
    "iso:country":"US",
    "sg:address":"3950 Nebraska Ave",
    "sg:city":"Levittown",
    "sg:classifiers":[
        {
            "category":"Shopping",
            "subcategory":"Gifts & Souvenirs",
            "type":"Retail Goods"
        },
        {
            "category":"Professional",
            "subcategory":"Business Services",
            "type":"Services"
        }
    ],
    "sg:phone":"+1 215 781 8725",
    "sg:postcode":"19056",
    "sg:province":"PA",
    "sg:tags":[
        "material",
        "wrapping",
        "labeling"
    ],
    "sg:website":"http://www.moellerpkg.com",
    "wof:name":"Moeller Contract Packaging",
    "wof:placetype":"venue"
},
  "geometry": {"coordinates":[-74.889893,40.1254],"type":"Point"}
}