{
  "type": "Feature",
  "properties": {
    "addr:full":"723 E Street Rd Southampton PA 18966",
    "addr:housenumber":"723",
    "addr:postcode":"18966",
    "addr:street":"E Street Rd",
    "iso:country":"US",
    "sg:address":"723 E Street Rd",
    "sg:city":"Southampton",
    "sg:classifiers":[
        {
            "category":"Banks & Credit Unions",
            "subcategory":"Bank",
            "type":"Services"
        }
    ],
    "sg:phone":"+1   ",
    "sg:postcode":"18966",
    "sg:province":"PA",
    "sg:tags":[
        "mortgage"
    ],
    "wof:name":"Summit",
    "wof:placetype":"venue"
},
  "geometry": {"coordinates":[-75.043171,40.174254],"type":"Point"}
}