{
  "type": "Feature",
  "properties": {
    "iso:country":"US",
    "sg:address":"2738 Dickinson St",
    "sg:city":"Philadelphia",
    "sg:classifiers":[
        {
            "category":"Social Services",
            "type":"Services"
        }
    ],
    "sg:phone":"+1 215 336 1158",
    "sg:postcode":"19146",
    "sg:province":"PA",
    "sg:tags":[
        "consulting",
        "geriatric"
    ],
    "wof:name":"William A Barrett Nabuurs Center",
    "wof:placetype":"venue"
},
  "geometry": {"coordinates":[-75.190529,39.934582],"type":"Point"}
}