{
  "type": "Feature",
  "properties": {
    "addr:full":"700 W Master St Philadelphia PA 19122",
    "addr:housenumber":"700",
    "addr:postcode":"19122",
    "addr:street":"W Master St",
    "iso:country":"US",
    "sg:address":"700 W Master St",
    "sg:city":"Philadelphia",
    "sg:classifiers":[
        {
            "category":"Restaurant",
            "type":"Food & Drink"
        }
    ],
    "sg:phone":"+1 215 769 5893",
    "sg:postcode":"19122",
    "sg:province":"PA",
    "sg:tags":[
        "mexican"
    ],
    "wof:name":"El Ranchito",
    "wof:placetype":"venue"
},
  "geometry": {"coordinates":[-75.147694,39.973048],"type":"Point"}
}