{
  "type": "Feature",
  "properties": {
    "iso:country":"US",
    "sg:address":"1065 Hwy 315",
    "sg:city":"Wilkes Barre",
    "sg:classifiers":[
        {
            "category":"Banks & Credit Unions",
            "subcategory":"Bank",
            "type":"Services"
        }
    ],
    "sg:phone":"+1 570 208 6680",
    "sg:postcode":"18702",
    "sg:province":"PA",
    "sg:tags":[
        "loan",
        "mortgage",
        "real estate"
    ],
    "wof:name":"Four Star Mortgage Co",
    "wof:placetype":"venue"
},
  "geometry": {"coordinates":[-75.82796399999999,41.252872],"type":"Point"}
}