{
  "type": "Feature",
  "properties": {
    "addr:full":"1333 Buck Rd Feastervl Trvs PA 19053",
    "addr:housenumber":"1333",
    "addr:postcode":"19053",
    "addr:street":"Buck Rd",
    "iso:country":"US",
    "sg:address":"1333 Buck Rd",
    "sg:city":"Feastervl Trvs",
    "sg:classifiers":[
        {
            "category":"Health Services",
            "subcategory":"Optometrist",
            "type":"Services"
        }
    ],
    "sg:phone":"+1 215 357 1479",
    "sg:postcode":"19053",
    "sg:province":"PA",
    "wof:name":"Milton J Fuchs OD",
    "wof:placetype":"venue"
},
  "geometry": {"coordinates":[-74.998986,40.156605],"type":"Point"}
}