{
  "type": "Feature",
  "properties": {
    "iso:country":"US",
    "sg:address":"245 Harman Rd",
    "sg:city":"Halifax",
    "sg:classifiers":[
        {
            "category":"Freight",
            "type":"Transportation"
        }
    ],
    "sg:phone":"+1   ",
    "sg:postcode":"17032",
    "sg:province":"PA",
    "sg:tags":[
        "operator",
        "local",
        "trucking"
    ],
    "wof:name":"Has A Dump Truck",
    "wof:placetype":"venue"
},
  "geometry": {"coordinates":[-76.801609,40.524812],"type":"Point"}
}