{
  "type": "Feature",
  "properties": {
    "iso:country":"US",
    "sg:address":"701 Bosler Ave",
    "sg:city":"Lemoyne",
    "sg:classifiers":[
        {
            "category":"Health Services",
            "subcategory":"Clinic",
            "type":"Services"
        }
    ],
    "sg:phone":"+1 717 730 6706",
    "sg:postcode":"17043",
    "sg:province":"PA",
    "sg:tags":[
        "organization",
        "medical",
        "surgical"
    ],
    "sg:website":"www.cureinternational.org",
    "wof:name":"Cure International",
    "wof:placetype":"venue"
},
  "geometry": {"coordinates":[-76.89877199999999,40.241516],"type":"Point"}
}