{
  "type": "Feature",
  "properties": {
    "addr:full":"603 E Locust Ave Philadelphia PA 19144",
    "addr:housenumber":"603",
    "addr:postcode":"19144",
    "addr:street":"E Locust Ave",
    "iso:country":"US",
    "sg:address":"603 E Locust Ave",
    "sg:city":"Philadelphia",
    "sg:classifiers":[
        {
            "category":"Personal",
            "type":"Services"
        }
    ],
    "sg:phone":"+1 215 438 7840",
    "sg:postcode":"19144",
    "sg:province":"PA",
    "sg:tags":[
        "therapist",
        "massage"
    ],
    "wof:name":"Nature Place",
    "wof:placetype":"venue"
},
  "geometry": {"coordinates":[-75.164723,40.042286],"type":"Point"}
}