{
  "type": "Feature",
  "properties": {
    "iso:country":"US",
    "sg:address":"3106 Lewis Ln",
    "sg:city":"Norristown",
    "sg:classifiers":[
        {
            "category":"Professional",
            "type":"Services"
        }
    ],
    "sg:phone":"+1   ",
    "sg:postcode":"19403",
    "sg:province":"PA",
    "wof:name":"Commonwealth Comm Tech",
    "wof:placetype":"venue"
},
  "geometry": {"coordinates":[-75.360862,40.167491],"type":"Point"}
}