{
  "type": "Feature",
  "properties": {
    "iso:country":"US",
    "sg:address":"12032 Gearhart Rd",
    "sg:city":"Greencastle",
    "sg:classifiers":[
        {
            "category":"Building & Trades",
            "subcategory":"Construction",
            "type":"Services"
        }
    ],
    "sg:phone":"+1 717 597 0872",
    "sg:postcode":"17225",
    "sg:province":"PA",
    "sg:tags":[
        "builder",
        "deck"
    ],
    "wof:name":"Your Design Drafting & Home",
    "wof:placetype":"venue"
},
  "geometry": {"coordinates":[-77.674288,39.77708],"type":"Point"}
}