{
  "type": "Feature",
  "properties": {
    "iso:country":"US",
    "sg:address":"1905 Wilmington Rd",
    "sg:city":"New Castle",
    "sg:classifiers":[
        {
            "category":"Shopping",
            "subcategory":"Clothing, Apparel, & Fashions",
            "type":"Retail Goods"
        }
    ],
    "sg:phone":"+1 724 654 3355",
    "sg:postcode":"16105",
    "sg:province":"PA",
    "sg:tags":[
        "infant",
        "wear"
    ],
    "wof:name":"All My Children",
    "wof:placetype":"venue"
},
  "geometry": {"coordinates":[-80.353971,41.024784],"type":"Point"}
}