{
  "type": "Feature",
  "properties": {
    "addr:full":"300 Meadow Ave Scranton PA 18505",
    "addr:housenumber":"300",
    "addr:postcode":"18505",
    "addr:street":"Meadow Ave",
    "iso:country":"US",
    "sg:address":"300 Meadow Ave",
    "sg:city":"Scranton",
    "sg:classifiers":[
        {
            "category":"Travel",
            "subcategory":"Hotels & Motels",
            "type":"Entertainment"
        }
    ],
    "sg:phone":"+1 570 344 9811",
    "sg:postcode":"18505",
    "sg:province":"PA",
    "sg:website":"www.clarionhotel.com",
    "wof:name":"Clarion Inn",
    "wof:placetype":"venue"
},
  "geometry": {"coordinates":[-75.651865,41.395083],"type":"Point"}
}