{
  "type": "Feature",
  "properties": {
    "addr:full":"350 Brotherton Rd Friedens PA 15541",
    "addr:housenumber":"350",
    "addr:postcode":"15541",
    "addr:street":"Brotherton Rd",
    "iso:country":"US",
    "sg:address":"350 Brotherton Rd",
    "sg:city":"Friedens",
    "sg:classifiers":[
        {
            "category":"Building & Trades",
            "subcategory":"Plumbing",
            "type":"Services"
        }
    ],
    "sg:phone":"+1 814 629 9210",
    "sg:postcode":"15541",
    "sg:province":"PA",
    "sg:tags":[
        "septic"
    ],
    "wof:name":"Honey Pots",
    "wof:placetype":"venue"
},
  "geometry": {"coordinates":[-78.916252,40.005179],"type":"Point"}
}