{
  "type": "Feature",
  "properties": {
    "addr:full":"2010 Keystone Ave Greensburg PA 15601",
    "addr:housenumber":"2010",
    "addr:postcode":"15601",
    "addr:street":"Keystone Ave",
    "iso:country":"US",
    "sg:address":"2010 Keystone Ave",
    "sg:city":"Greensburg",
    "sg:classifiers":[
        {
            "category":"Personal",
            "subcategory":"Beauty Salon",
            "type":"Services"
        }
    ],
    "sg:phone":"+1 724 850 4247",
    "sg:postcode":"15601",
    "sg:province":"PA",
    "wof:name":"Julie's Full Svc Salon",
    "wof:placetype":"venue"
},
  "geometry": {"coordinates":[-79.55470099999999,40.27463],"type":"Point"}
}