{
  "type": "Feature",
  "properties": {
    "addr:full":"804 Heckler Hollow Ct Doylestown PA 18901",
    "addr:housenumber":"804",
    "addr:postcode":"18901",
    "addr:street":"Heckler Hollow Ct",
    "iso:country":"US",
    "sg:address":"804 Heckler Hollow Ct",
    "sg:city":"Doylestown",
    "sg:classifiers":[
        {
            "category":"Professional",
            "subcategory":"Management & Consulting",
            "type":"Services"
        }
    ],
    "sg:phone":"+1 215 343 7017",
    "sg:postcode":"18901",
    "sg:province":"PA",
    "sg:tags":[
        "consultant"
    ],
    "wof:name":"Strat360",
    "wof:placetype":"venue"
},
  "geometry": {"coordinates":[-75.123875,40.265807],"type":"Point"}
}