{
  "type": "Feature",
  "properties": {
    "iso:country":"US",
    "sg:address":"5742 Pentridge St",
    "sg:city":"Philadelphia",
    "sg:classifiers":[
        {
            "category":"Building & Trades",
            "subcategory":"Construction",
            "type":"Services"
        }
    ],
    "sg:phone":"+1 215 729 2454",
    "sg:postcode":"19143",
    "sg:province":"PA",
    "sg:tags":[
        "home",
        "improvement"
    ],
    "wof:name":"Angela Jones",
    "wof:placetype":"venue"
},
  "geometry": {"coordinates":[-75.23254300000001,39.939976],"type":"Point"}
}