{
  "type": "Feature",
  "properties": {
    "iso:country":"US",
    "sg:address":"530 Brookhurst Ave",
    "sg:city":"Narberth",
    "sg:classifiers":[
        {
            "category":"Manufacturing",
            "subcategory":"Printing",
            "type":"Manufacturing & Wholesale Goods"
        }
    ],
    "sg:phone":"+1   ",
    "sg:postcode":"19072",
    "sg:province":"PA",
    "wof:name":"Kvl Printing",
    "wof:placetype":"venue"
},
  "geometry": {"coordinates":[-75.25884000000001,40.011427],"type":"Point"}
}