{
  "type": "Feature",
  "properties": {
    "addr:full":"811 Easton Rd Willow Grove PA 19090",
    "addr:housenumber":"811",
    "addr:postcode":"19090",
    "addr:street":"Easton Rd",
    "iso:country":"US",
    "sg:address":"811 Easton Rd",
    "sg:city":"Willow Grove",
    "sg:classifiers":[
        {
            "category":"Restaurant",
            "type":"Food & Drink"
        }
    ],
    "sg:phone":"+1 215 657 2793",
    "sg:postcode":"19090",
    "sg:province":"PA",
    "sg:tags":[
        "delicatessen"
    ],
    "wof:name":"All Night Deli",
    "wof:placetype":"venue"
},
  "geometry": {"coordinates":[-75.12127099999999,40.152568],"type":"Point"}
}