{
  "type": "Feature",
  "properties": {
    "addr:full":"232 John St Greensburg PA 15601",
    "addr:housenumber":"232",
    "addr:postcode":"15601",
    "addr:street":"John St",
    "iso:country":"US",
    "sg:address":"232 John St",
    "sg:city":"Greensburg",
    "sg:classifiers":[
        {
            "category":"Cinema",
            "subcategory":"Movie Rental",
            "type":"Entertainment"
        }
    ],
    "sg:phone":"+1   ",
    "sg:postcode":"15601",
    "sg:province":"PA",
    "sg:tags":[
        "video",
        "tape"
    ],
    "wof:name":"J & N Video Connections",
    "wof:placetype":"venue"
},
  "geometry": {"coordinates":[-79.55962,40.294738],"type":"Point"}
}