{
  "type": "Feature",
  "properties": {
    "addr:full":"1217 Denbigh Ln Wayne PA 19087",
    "addr:housenumber":"1217",
    "addr:postcode":"19087",
    "addr:street":"Denbigh Ln",
    "iso:country":"US",
    "sg:address":"1217 Denbigh Ln",
    "sg:city":"Wayne",
    "sg:classifiers":[
        {
            "category":"Professional",
            "subcategory":"Business Services",
            "type":"Services"
        }
    ],
    "sg:phone":"+1 610 688 8090",
    "sg:postcode":"19087",
    "sg:province":"PA",
    "sg:tags":[
        "interior",
        "consultant",
        "design",
        "decorator"
    ],
    "wof:name":"Meadowbank Designs",
    "wof:placetype":"venue"
},
  "geometry": {"coordinates":[-75.348578,40.058621],"type":"Point"}
}