{
  "type": "Feature",
  "properties": {
    "addr:full":"45 Wood St Pittston PA 18640",
    "addr:housenumber":"45",
    "addr:postcode":"18640",
    "addr:street":"Wood St",
    "iso:country":"US",
    "sg:address":"45 Wood St",
    "sg:city":"Pittston",
    "sg:classifiers":[
        {
            "category":"Building & Trades",
            "subcategory":"Construction",
            "type":"Services"
        }
    ],
    "sg:phone":"+1   ",
    "sg:postcode":"18640",
    "sg:province":"PA",
    "sg:tags":[
        "residential"
    ],
    "wof:name":"David J Hoffner",
    "wof:placetype":"venue"
},
  "geometry": {"coordinates":[-75.785417,41.326142],"type":"Point"}
}