{
  "type": "Feature",
  "properties": {
    "iso:country":"US",
    "sg:address":"212 E Main St",
    "sg:city":"Carnegie",
    "sg:classifiers":[
        {
            "category":"Shopping",
            "subcategory":"Music",
            "type":"Retail Goods"
        }
    ],
    "sg:phone":"+1 412 279 8888",
    "sg:postcode":"15106",
    "sg:province":"PA",
    "sg:tags":[
        "compact",
        "record",
        "disc",
        "tape",
        "dvd's"
    ],
    "wof:name":"D & J Records",
    "wof:placetype":"venue"
},
  "geometry": {"coordinates":[-80.08519699999999,40.408298],"type":"Point"}
}