{
  "type": "Feature",
  "properties": {
    "iso:country":"US",
    "sg:address":"1109 W Chester Rd",
    "sg:city":"West Chester",
    "sg:classifiers":[
        {
            "category":"Autos & Motor Vehicles",
            "subcategory":"Fuel & Gas Station",
            "type":"Retail Goods"
        }
    ],
    "sg:phone":"+1 610 696 7390",
    "sg:postcode":"19382",
    "sg:province":"PA",
    "sg:tags":[
        "oil"
    ],
    "wof:name":"West Goshen Automotive & Fleet",
    "wof:placetype":"venue"
},
  "geometry": {"coordinates":[-75.546357,39.911133],"type":"Point"}
}