{
  "type": "Feature",
  "properties": {
    "iso:country":"US",
    "sg:address":"108 Academy Rd",
    "sg:city":"Merrittstown",
    "sg:classifiers":[
        {
            "category":"Health Services",
            "subcategory":"Health Practitioner",
            "type":"Services"
        }
    ],
    "sg:phone":"+1 724 246 0780",
    "sg:postcode":"15417",
    "sg:province":"PA",
    "sg:tags":[
        "physician",
        "assistant"
    ],
    "wof:name":"Graymont Pa Inc",
    "wof:placetype":"venue"
},
  "geometry": {"coordinates":[-79.87743,39.97309],"type":"Point"}
}