{
  "type": "Feature",
  "properties": {
    "iso:country":"US",
    "sg:address":"858 N 4th St",
    "sg:city":"Sunbury",
    "sg:classifiers":[
        {
            "category":"Professional",
            "type":"Services"
        }
    ],
    "sg:phone":"+1   ",
    "sg:postcode":"17801",
    "sg:province":"PA",
    "wof:name":"Earned Income Refund Center",
    "wof:placetype":"venue"
},
  "geometry": {"coordinates":[-76.78621800000001,40.870202],"type":"Point"}
}