{
  "type": "Feature",
  "properties": {
    "iso:country":"US",
    "sg:address":"221 Nibert Rd",
    "sg:city":"Indiana",
    "sg:classifiers":[
        {
            "category":"Manufacturing",
            "subcategory":"Tools & Machinery",
            "type":"Manufacturing & Wholesale Goods"
        }
    ],
    "sg:phone":"+1 724 463 8800",
    "sg:postcode":"15701",
    "sg:province":"PA",
    "sg:tags":[
        "mfg"
    ],
    "wof:name":"Die Sets Inc",
    "wof:placetype":"venue"
},
  "geometry": {"coordinates":[-79.0868,40.649437],"type":"Point"}
}