{
  "type": "Feature",
  "properties": {
    "iso:country":"US",
    "sg:address":"33619 E Freemont St",
    "sg:city":"Townville",
    "sg:classifiers":[
        {
            "category":"Farming",
            "subcategory":"Nursery",
            "type":"Manufacturing & Wholesale Goods"
        }
    ],
    "sg:phone":"+1   ",
    "sg:postcode":"16360",
    "sg:province":"PA",
    "sg:tags":[
        "ornamental"
    ],
    "wof:name":"B & D Industries",
    "wof:placetype":"venue"
},
  "geometry": {"coordinates":[-79.87761,41.678589],"type":"Point"}
}