{
  "type": "Feature",
  "properties": {
    "iso:country":"US",
    "sg:address":"4300 Holmesburg Ave",
    "sg:city":"Philadelphia",
    "sg:classifiers":[
        {
            "category":"Retail",
            "subcategory":"Repair Shop",
            "type":"Services"
        }
    ],
    "sg:phone":"+1 215 333 0931",
    "sg:postcode":"19136",
    "sg:province":"PA",
    "sg:tags":[
        "upholsterer"
    ],
    "wof:name":"Magic Upholstery",
    "wof:placetype":"venue"
},
  "geometry": {"coordinates":[-75.022597,40.040468],"type":"Point"}
}