{
  "type": "Feature",
  "properties": {
    "addr:full":"2371 State Rte 88 Finleyville PA 15332",
    "addr:housenumber":"2371",
    "addr:postcode":"15332",
    "addr:street":"State Rte 88",
    "iso:country":"US",
    "sg:address":"2371 State Rte 88",
    "sg:city":"Finleyville",
    "sg:classifiers":[
        {
            "category":"Food & Beverages",
            "subcategory":"Groceries & Convenience Stores",
            "type":"Retail Goods"
        }
    ],
    "sg:phone":"+1 724 348 8447",
    "sg:postcode":"15332",
    "sg:province":"PA",
    "wof:name":"Finleyville Drive Thru",
    "wof:placetype":"venue"
},
  "geometry": {"coordinates":[-79.99612,40.230764],"type":"Point"}
}