{
  "type": "Feature",
  "properties": {
    "addr:full":"1 Braxton Way Glen Mills PA 19342",
    "addr:housenumber":"1",
    "addr:postcode":"19342",
    "addr:street":"Braxton Way",
    "iso:country":"US",
    "sg:address":"1 Braxton Way",
    "sg:city":"Glen Mills",
    "sg:classifiers":[
        {
            "category":"Professional",
            "subcategory":"Accounting & Tax Preparation",
            "type":"Services"
        }
    ],
    "sg:phone":"+1 610 358 4406",
    "sg:postcode":"19342",
    "sg:province":"PA",
    "sg:tags":[
        "accountant"
    ],
    "wof:name":"Deloitte & Touche",
    "wof:placetype":"venue"
},
  "geometry": {"coordinates":[-75.525002,39.867901],"type":"Point"}
}