{
  "type": "Feature",
  "properties": {
    "iso:country":"US",
    "sg:address":"145 Old Fort Rd",
    "sg:city":"Spring Mills",
    "sg:classifiers":[
        {
            "category":"Shopping",
            "subcategory":"Jewelry",
            "type":"Retail Goods"
        }
    ],
    "sg:phone":"+1 814 364 9620",
    "sg:postcode":"16875",
    "sg:province":"PA",
    "sg:tags":[
        "jeweler"
    ],
    "wof:name":"Confer's Jewelry Store",
    "wof:placetype":"venue"
},
  "geometry": {"coordinates":[-77.625857,40.800954],"type":"Point"}
}