{
  "type": "Feature",
  "properties": {
    "iso:country":"US",
    "sg:address":"3751 Ridge Ave",
    "sg:city":"Philadelphia",
    "sg:classifiers":[
        {
            "category":"Restaurant",
            "type":"Food & Drink"
        }
    ],
    "sg:phone":"+1 215 223 8388",
    "sg:postcode":"19132",
    "sg:province":"PA",
    "sg:tags":[
        "beverage"
    ],
    "wof:name":"Hua Feng",
    "wof:placetype":"venue"
},
  "geometry": {"coordinates":[-75.18687799999999,40.001798],"type":"Point"}
}