{
  "type": "Feature",
  "properties": {
    "addr:full":"46 N Main St Chalfont PA 18914",
    "addr:housenumber":"46",
    "addr:postcode":"18914",
    "addr:street":"N Main St",
    "iso:country":"US",
    "sg:address":"46 N Main St",
    "sg:city":"Chalfont",
    "sg:classifiers":[
        {
            "category":"Health Services",
            "subcategory":"Doctor",
            "type":"Services"
        }
    ],
    "sg:phone":"+1 215 822 3838",
    "sg:postcode":"18914",
    "sg:province":"PA",
    "sg:tags":[
        "surgeon",
        "oral"
    ],
    "wof:name":"Eble Dennis M DDS",
    "wof:placetype":"venue"
},
  "geometry": {"coordinates":[-75.20880099999999,40.2873],"type":"Point"}
}