{
  "type": "Feature",
  "properties": {
    "iso:country":"US",
    "sg:address":"887 Henderson Ave",
    "sg:city":"Washington",
    "sg:classifiers":[
        {
            "category":"Real Estate",
            "subcategory":"Real Estate Services",
            "type":"Services"
        }
    ],
    "sg:phone":"+1   ",
    "sg:postcode":"15301",
    "sg:province":"PA",
    "sg:tags":[
        "abstract",
        "title"
    ],
    "wof:name":"Vision Settlement Services",
    "wof:placetype":"venue"
},
  "geometry": {"coordinates":[-80.269767,40.198465],"type":"Point"}
}