{
  "type": "Feature",
  "properties": {
    "addr:full":"732 Penn Ave West Reading PA 19611",
    "addr:housenumber":"732",
    "addr:postcode":"19611",
    "addr:street":"Penn Ave",
    "iso:country":"US",
    "sg:address":"732 Penn Ave",
    "sg:city":"West Reading",
    "sg:classifiers":[
        {
            "category":"Shopping",
            "subcategory":"Clothing, Apparel, & Fashions",
            "type":"Retail Goods"
        }
    ],
    "sg:phone":"+1 610 375 2609",
    "sg:postcode":"19611",
    "sg:province":"PA",
    "sg:tags":[
        "uniform"
    ],
    "wof:name":"Tots & Doo-Dads",
    "wof:placetype":"venue"
},
  "geometry": {"coordinates":[-75.95317799999999,40.335906],"type":"Point"}
}