{
  "type": "Feature",
  "properties": {
    "iso:country":"US",
    "sg:address":"295 Penn Ave",
    "sg:city":"Turtle Creek",
    "sg:classifiers":[
        {
            "category":"Retail",
            "subcategory":"Auto Repair",
            "type":"Services"
        }
    ],
    "sg:phone":"+1   ",
    "sg:postcode":"15145",
    "sg:province":"PA",
    "sg:tags":[
        "body"
    ],
    "wof:name":"Fiola James",
    "wof:placetype":"venue"
},
  "geometry": {"coordinates":[-79.830595,40.404772],"type":"Point"}
}