{
  "type": "Feature",
  "properties": {
    "iso:country":"US",
    "sg:address":"621 Pine Run Rd",
    "sg:city":"Apollo",
    "sg:classifiers":[
        {
            "category":"Building & Trades",
            "subcategory":"Construction",
            "type":"Services"
        }
    ],
    "sg:phone":"+1   ",
    "sg:postcode":"15613",
    "sg:province":"PA",
    "sg:tags":[
        "home",
        "commercial"
    ],
    "wof:name":"Terra Firm Construction Co",
    "wof:placetype":"venue"
},
  "geometry": {"coordinates":[-79.599765,40.570645],"type":"Point"}
}