{
  "type": "Feature",
  "properties": {
    "addr:full":"135 Marlick Ave Reedsville PA 17084",
    "addr:housenumber":"135",
    "addr:postcode":"17084",
    "addr:street":"Marlick Ave",
    "iso:country":"US",
    "sg:address":"135 Marlick Ave",
    "sg:city":"Reedsville",
    "sg:classifiers":[
        {
            "category":"Banks & Credit Unions",
            "subcategory":"Bank",
            "type":"Services"
        }
    ],
    "sg:phone":"+1 717 667 0300",
    "sg:postcode":"17084",
    "sg:province":"PA",
    "sg:tags":[
        "loan",
        "real estate"
    ],
    "wof:name":"People's Equity Mortgage",
    "wof:placetype":"venue"
},
  "geometry": {"coordinates":[-77.60221900000001,40.679767],"type":"Point"}
}