{
  "type": "Feature",
  "properties": {
    "iso:country":"US",
    "sg:address":"5 Toxony Ave",
    "sg:city":"Glenside",
    "sg:classifiers":[
        {
            "category":"Shopping",
            "subcategory":"Computers & Home Electronics",
            "type":"Retail Goods"
        }
    ],
    "sg:phone":"+1   ",
    "sg:postcode":"19038",
    "sg:province":"PA",
    "wof:name":"ADP Micro",
    "wof:placetype":"venue"
},
  "geometry": {"coordinates":[-75.155631,40.096727],"type":"Point"}
}