{
  "type": "Feature",
  "properties": {
    "iso:country":"US",
    "sg:address":"785 Baltimore St",
    "sg:city":"Gettysburg",
    "sg:classifiers":[
        {
            "category":"Travel",
            "subcategory":"Bed & Breakfast",
            "type":"Entertainment"
        }
    ],
    "sg:phone":"+1 717 334 2037",
    "sg:postcode":"17325",
    "sg:province":"PA",
    "sg:tags":[
        "home",
        "tourist"
    ],
    "wof:name":"Homestead",
    "wof:placetype":"venue"
},
  "geometry": {"coordinates":[-77.22956600000001,39.821113],"type":"Point"}
}