{
  "type": "Feature",
  "properties": {
    "addr:full":"810 Hill Church Rd Boyertown PA 19512",
    "addr:housenumber":"810",
    "addr:postcode":"19512",
    "addr:street":"Hill Church Rd",
    "iso:country":"US",
    "sg:address":"810 Hill Church Rd",
    "sg:city":"Boyertown",
    "sg:classifiers":[
        {
            "category":"Government",
            "subcategory":"Office",
            "type":"Public Place"
        }
    ],
    "sg:phone":"+1 610 987 6023",
    "sg:postcode":"19512",
    "sg:province":"PA",
    "sg:tags":[
        "town",
        "city",
        "executive",
        "planner"
    ],
    "wof:name":"Pike Township Bd Supervisors",
    "wof:placetype":"venue"
},
  "geometry": {"coordinates":[-75.70436100000001,40.393478],"type":"Point"}
}