{
  "type": "Feature",
  "properties": {
    "iso:country":"US",
    "sg:address":"2027 N 18th St",
    "sg:city":"Philadelphia",
    "sg:classifiers":[
        {
            "category":"Banks & Credit Unions",
            "subcategory":"Bank",
            "type":"Services"
        }
    ],
    "sg:phone":"+1 215 232 0230",
    "sg:postcode":"19121",
    "sg:province":"PA",
    "sg:tags":[
        "cashing",
        "check"
    ],
    "wof:name":"Lucky Cash LLC",
    "wof:placetype":"venue"
},
  "geometry": {"coordinates":[-75.163184,39.984471],"type":"Point"}
}