{
  "type": "Feature",
  "properties": {
    "addr:full":"877 Stoystown Rd Somerset PA 15501",
    "addr:housenumber":"877",
    "addr:postcode":"15501",
    "addr:street":"Stoystown Rd",
    "iso:country":"US",
    "sg:address":"877 Stoystown Rd",
    "sg:city":"Somerset",
    "sg:classifiers":[
        {
            "category":"Food & Beverages",
            "subcategory":"Groceries & Convenience Stores",
            "type":"Retail Goods"
        }
    ],
    "sg:phone":"+1 814 445 3820",
    "sg:postcode":"15501",
    "sg:province":"PA",
    "sg:tags":[
        "station"
    ],
    "wof:name":"Mostollers Store Gas & Lottery",
    "wof:placetype":"venue"
},
  "geometry": {"coordinates":[-79.05410000000001,40.024402],"type":"Point"}
}