{
  "type": "Feature",
  "properties": {
    "iso:country":"US",
    "sg:address":"22 S Commerce Way Ste 7",
    "sg:city":"Bethlehem",
    "sg:classifiers":[
        {
            "category":"Real Estate",
            "subcategory":"Real Estate Services",
            "type":"Services"
        },
        {
            "category":"Real Estate",
            "subcategory":"Real Estate Agent",
            "type":"Services"
        }
    ],
    "sg:phone":"+1 610 865 6998",
    "sg:postcode":"18017",
    "sg:province":"PA",
    "sg:tags":[
        "management"
    ],
    "wof:name":"Raj Associates Inc",
    "wof:placetype":"venue"
},
  "geometry": {"coordinates":[-75.373901,40.674042],"type":"Point"}
}