{
  "type": "Feature",
  "properties": {
    "addr:full":"290 Lawndale Ave King Of Prussia PA 19406",
    "addr:housenumber":"290",
    "addr:postcode":"19406",
    "addr:street":"Lawndale Ave",
    "iso:country":"US",
    "sg:address":"290 Lawndale Ave",
    "sg:city":"King Of Prussia",
    "sg:classifiers":[
        {
            "category":"Building & Trades",
            "subcategory":"Construction",
            "type":"Services"
        }
    ],
    "sg:phone":"+1   ",
    "sg:postcode":"19406",
    "sg:province":"PA",
    "sg:tags":[
        "hanging",
        "contractor"
    ],
    "wof:name":"Quality Papaerhanging",
    "wof:placetype":"venue"
},
  "geometry": {"coordinates":[-75.34568,40.083728],"type":"Point"}
}