{
  "type": "Feature",
  "properties": {
    "iso:country":"US",
    "sg:address":"436 Little Elk Creek Rd",
    "sg:city":"Lincoln University",
    "sg:classifiers":[
        {
            "category":"Retail",
            "subcategory":"Auto Repair",
            "type":"Services"
        }
    ],
    "sg:phone":"+1 610 932 8555",
    "sg:postcode":"19352",
    "sg:province":"PA",
    "sg:tags":[
        "repairing",
        "automobile"
    ],
    "wof:name":"Goldie Enterprises Inc",
    "wof:placetype":"venue"
},
  "geometry": {"coordinates":[-75.92089799999999,39.781799],"type":"Point"}
}