{
  "type": "Feature",
  "properties": {
    "iso:country":"US",
    "sg:address":"435 Pembroke Rd",
    "sg:city":"Bethlehem",
    "sg:classifiers":[
        {
            "category":"Autos & Motor Vehicles",
            "subcategory":"Fuel & Gas Station",
            "type":"Retail Goods"
        }
    ],
    "sg:phone":"+1 610 861 0156",
    "sg:postcode":"18018",
    "sg:province":"PA",
    "sg:tags":[
        "oil"
    ],
    "wof:name":"Bold's Mobil",
    "wof:placetype":"venue"
},
  "geometry": {"coordinates":[-75.367075,40.626372],"type":"Point"}
}