{
  "type": "Feature",
  "properties": {
    "iso:country":"US",
    "sg:address":"21 Lakeview Ln",
    "sg:city":"East Stroudsburg",
    "sg:classifiers":[
        {
            "category":"Building & Trades",
            "subcategory":"Construction",
            "type":"Services"
        }
    ],
    "sg:phone":"+1   ",
    "sg:postcode":"18301",
    "sg:province":"PA",
    "sg:tags":[
        "house"
    ],
    "wof:name":"R Szlasa Contra",
    "wof:placetype":"venue"
},
  "geometry": {"coordinates":[-75.103143,41.054715],"type":"Point"}
}