{
  "type": "Feature",
  "properties": {
    "iso:country":"US",
    "sg:address":"249 York St",
    "sg:city":"Gettysburg",
    "sg:classifiers":[
        {
            "category":"Insurance",
            "subcategory":"Insurance Agent",
            "type":"Services"
        }
    ],
    "sg:phone":"+1 717 334 8118",
    "sg:postcode":"17325",
    "sg:province":"PA",
    "sg:tags":[
        "notary",
        "agency",
        "public"
    ],
    "wof:name":"CRS Insurance Inc",
    "wof:placetype":"venue"
},
  "geometry": {"coordinates":[-77.225408,39.8316],"type":"Point"}
}