{
  "type": "Feature",
  "properties": {
    "addr:full":"5617 N 5th St Philadelphia PA 19120",
    "addr:housenumber":"5617",
    "addr:postcode":"19120",
    "addr:street":"N 5Th St",
    "iso:country":"US",
    "sg:address":"5617 N 5th St",
    "sg:city":"Philadelphia",
    "sg:classifiers":[
        {
            "category":"Shopping",
            "subcategory":"Clothing, Apparel, & Fashions",
            "type":"Retail Goods"
        }
    ],
    "sg:phone":"+1   ",
    "sg:postcode":"19120",
    "sg:province":"PA",
    "sg:tags":[
        "boy",
        "woman",
        "accessory"
    ],
    "wof:name":"Urban Gear",
    "wof:placetype":"venue"
},
  "geometry": {"coordinates":[-75.130133,40.037722],"type":"Point"}
}