{
  "type": "Feature",
  "properties": {
    "iso:country":"US",
    "sg:address":"1475 Manheim Pike",
    "sg:city":"Lancaster",
    "sg:classifiers":[
        {
            "category":"Autos & Motor Vehicles",
            "subcategory":"Automobile Sales",
            "type":"Retail Goods"
        }
    ],
    "sg:phone":"+1 717 393 0625",
    "sg:postcode":"17601",
    "sg:province":"PA",
    "sg:tags":[
        "car",
        "dealer"
    ],
    "wof:name":"Lancaster Dodge Inc",
    "wof:placetype":"venue"
},
  "geometry": {"coordinates":[-76.33114999999999,40.069492],"type":"Point"}
}