{
  "type": "Feature",
  "properties": {
    "iso:country":"US",
    "sg:address":"6229 Crescent Ave",
    "sg:city":"Bensalem",
    "sg:classifiers":[
        {
            "category":"Building & Trades",
            "subcategory":"Cleaning & Sanitation",
            "type":"Services"
        }
    ],
    "sg:phone":"+1 215 752 1115",
    "sg:postcode":"19020",
    "sg:province":"PA",
    "sg:tags":[
        "cleaning-industrial",
        "contractor"
    ],
    "wof:name":"Ruth Szasranski",
    "wof:placetype":"venue"
},
  "geometry": {"coordinates":[-74.90514899999999,40.130998],"type":"Point"}
}