{
  "type": "Feature",
  "properties": {
    "iso:country":"US",
    "sg:address":"1221 W Southern Ave",
    "sg:city":"Williamsport",
    "sg:classifiers":[
        {
            "category":"Personal",
            "subcategory":"Tanning Parlor",
            "type":"Services"
        },
        {
            "category":"Personal",
            "type":"Services"
        }
    ],
    "sg:phone":"+1 570 322 0637",
    "sg:postcode":"17702",
    "sg:province":"PA",
    "sg:tags":[
        "salon"
    ],
    "wof:name":"Sunsational Tanning Studio",
    "wof:placetype":"venue"
},
  "geometry": {"coordinates":[-77.008146,41.228514],"type":"Point"}
}