{
  "type": "Feature",
  "properties": {
    "addr:full":"501 Daleville Rd Cochranville PA 19330",
    "addr:housenumber":"501",
    "addr:postcode":"19330",
    "addr:street":"Daleville Rd",
    "iso:country":"US",
    "sg:address":"501 Daleville Rd",
    "sg:city":"Cochranville",
    "sg:classifiers":[
        {
            "category":"Building & Trades",
            "subcategory":"Plumbing",
            "type":"Services"
        }
    ],
    "sg:phone":"+1 610 593 6996",
    "sg:postcode":"19330",
    "sg:province":"PA",
    "wof:name":"Cochranville Plumbing & Heating",
    "wof:placetype":"venue"
},
  "geometry": {"coordinates":[-75.91976200000001,39.889116],"type":"Point"}
}