{
  "type": "Feature",
  "properties": {
    "addr:full":"828 Martha Ave Lancaster PA 17601",
    "addr:housenumber":"828",
    "addr:postcode":"17601",
    "addr:street":"Martha Ave",
    "iso:country":"US",
    "sg:address":"828 Martha Ave",
    "sg:city":"Lancaster",
    "sg:classifiers":[
        {
            "category":"Health Services",
            "subcategory":"Hospital",
            "type":"Services"
        }
    ],
    "sg:phone":"+1   ",
    "sg:postcode":"17601",
    "sg:province":"PA",
    "sg:tags":[
        "general"
    ],
    "wof:name":"Life Enhancement Center",
    "wof:placetype":"venue"
},
  "geometry": {"coordinates":[-76.28961099999999,40.057554],"type":"Point"}
}