{
  "type": "Feature",
  "properties": {
    "addr:full":"27 N 3rd St Philadelphia PA 19106",
    "addr:housenumber":"27",
    "addr:postcode":"19106",
    "addr:street":"N 3Rd St",
    "iso:country":"US",
    "sg:address":"27 N 3rd St",
    "sg:city":"Philadelphia",
    "sg:classifiers":[
        {
            "category":"Manufacturing",
            "subcategory":"Tools & Machinery",
            "type":"Manufacturing & Wholesale Goods"
        }
    ],
    "sg:phone":"+1   ",
    "sg:postcode":"19106",
    "sg:province":"PA",
    "sg:tags":[
        "surgical",
        "mfg"
    ],
    "wof:name":"LNard",
    "wof:placetype":"venue"
},
  "geometry": {"coordinates":[-75.14555300000001,39.950276],"type":"Point"}
}