{
  "type": "Feature",
  "properties": {
    "iso:country":"US",
    "sg:address":"242 E Calder Way",
    "sg:city":"State College",
    "sg:classifiers":[
        {
            "category":"Shopping",
            "subcategory":"Florist",
            "type":"Retail Goods"
        }
    ],
    "sg:phone":"+1 814 231 1212",
    "sg:postcode":"16801",
    "sg:province":"PA",
    "wof:name":"Avant Garden",
    "wof:placetype":"venue"
},
  "geometry": {"coordinates":[-77.858923,40.79564],"type":"Point"}
}