{
  "type": "Feature",
  "properties": {
    "addr:full":"223 Market St Harrisburg PA 17101",
    "addr:housenumber":"223",
    "addr:postcode":"17101",
    "addr:street":"Market St",
    "iso:country":"US",
    "sg:address":"223 Market St",
    "sg:city":"Harrisburg",
    "sg:classifiers":[
        {
            "category":"Shopping",
            "subcategory":"Pharmacy",
            "type":"Retail Goods"
        }
    ],
    "sg:phone":"+1   ",
    "sg:postcode":"17101",
    "sg:province":"PA",
    "wof:name":"CVS",
    "wof:placetype":"venue"
},
  "geometry": {"coordinates":[-76.880714,40.260738],"type":"Point"}
}