{
  "type": "Feature",
  "properties": {
    "addr:full":"263 E Main St Mt Pleasant PA 15666",
    "addr:housenumber":"263",
    "addr:postcode":"15666",
    "addr:street":"E Main St",
    "iso:country":"US",
    "sg:address":"263 E Main St",
    "sg:city":"Mt Pleasant",
    "sg:classifiers":[
        {
            "category":"Health Services",
            "subcategory":"Chiropractor",
            "type":"Services"
        }
    ],
    "sg:phone":"+1 724 547 4373",
    "sg:postcode":"15666",
    "sg:province":"PA",
    "wof:name":"Phillip Herd DC",
    "wof:placetype":"venue"
},
  "geometry": {"coordinates":[-79.526781,40.14663],"type":"Point"}
}