{
  "type": "Feature",
  "properties": {
    "addr:full":"1520 Grant Ave Exd Butler PA 16001",
    "addr:housenumber":"1520",
    "addr:postcode":"16001",
    "addr:street":"Grant Ave Exd",
    "iso:country":"US",
    "sg:address":"1520 Grant Ave Exd",
    "sg:city":"Butler",
    "sg:classifiers":[
        {
            "category":"Professional",
            "type":"Services"
        }
    ],
    "sg:phone":"+1   ",
    "sg:postcode":"16001",
    "sg:province":"PA",
    "wof:name":"Booher Installation",
    "wof:placetype":"venue"
},
  "geometry": {"coordinates":[-79.854742,40.892313],"type":"Point"}
}