{
  "type": "Feature",
  "properties": {
    "iso:country":"US",
    "sg:address":"4040 Liberty Ave",
    "sg:city":"Pittsburgh",
    "sg:classifiers":[
        {
            "category":"Retail",
            "subcategory":"Auto Repair",
            "type":"Services"
        },
        {
            "category":"Wholesale",
            "subcategory":"Auto Parts",
            "type":"Manufacturing & Wholesale Goods"
        }
    ],
    "sg:phone":"+1   ",
    "sg:postcode":"15224",
    "sg:province":"PA",
    "sg:tags":[
        "transmission",
        "manufacturer",
        "supply"
    ],
    "wof:name":"Transmission Magician Corp",
    "wof:placetype":"venue"
},
  "geometry": {"coordinates":[-79.95554,40.463013],"type":"Point"}
}