{
  "type": "Feature",
  "properties": {
    "iso:country":"US",
    "sg:address":"441 W Linden St",
    "sg:city":"Allentown",
    "sg:classifiers":[
        {
            "category":"Professional",
            "subcategory":"Lawyer & Legal Services",
            "type":"Services"
        }
    ],
    "sg:phone":"+1 610 437 7064",
    "sg:postcode":"18102",
    "sg:province":"PA",
    "wof:name":"Charles Dennis G Atty",
    "wof:placetype":"venue"
},
  "geometry": {"coordinates":[-75.467697,40.6049],"type":"Point"}
}