{
  "type": "Feature",
  "properties": {
    "addr:full":"700 Packer Ave Ste 2 Philadelphia PA 19148",
    "addr:housenumber":"700",
    "addr:postcode":"19148",
    "addr:street":"Packer Ave Ste 2",
    "iso:country":"US",
    "sg:address":"700 Packer Ave Ste 2",
    "sg:city":"Philadelphia",
    "sg:classifiers":[
        {
            "category":"Bars & Pubs",
            "type":"Food & Drink"
        },
        {
            "category":"Restaurant",
            "type":"Food & Drink"
        }
    ],
    "sg:phone":"+1 215 246 1556",
    "sg:postcode":"19148",
    "sg:province":"PA",
    "sg:tags":[
        "brew"
    ],
    "wof:name":"Sportsview Bar & Grill",
    "wof:placetype":"venue"
},
  "geometry": {"coordinates":[-75.161102,39.909302],"type":"Point"}
}