{
  "type": "Feature",
  "properties": {
    "iso:country":"US",
    "sg:address":"1720 E Canal Rd",
    "sg:city":"Dover",
    "sg:classifiers":[
        {
            "category":"Autos & Motor Vehicles",
            "subcategory":"Automobile Sales",
            "type":"Retail Goods"
        }
    ],
    "sg:phone":"+1 717 266 4611",
    "sg:postcode":"17315",
    "sg:province":"PA",
    "sg:tags":[
        "car",
        "dealer"
    ],
    "wof:name":"Toomey's Auto Sales & Svc",
    "wof:placetype":"venue"
},
  "geometry": {"coordinates":[-76.83931800000001,40.005191],"type":"Point"}
}