{
  "type": "Feature",
  "properties": {
    "addr:full":"1310 W Lehigh Ave Philadelphia PA 19132",
    "addr:housenumber":"1310",
    "addr:postcode":"19132",
    "addr:street":"W Lehigh Ave",
    "iso:country":"US",
    "sg:address":"1310 W Lehigh Ave",
    "sg:city":"Philadelphia",
    "sg:classifiers":[
        {
            "category":"Real Estate",
            "subcategory":"Real Estate Agent",
            "type":"Services"
        }
    ],
    "sg:phone":"+1 215 225 0151",
    "sg:postcode":"19132",
    "sg:province":"PA",
    "sg:tags":[
        "authorities",
        "housing"
    ],
    "wof:name":"Philadelphia Housing Authority",
    "wof:placetype":"venue"
},
  "geometry": {"coordinates":[-75.15316199999999,39.993675],"type":"Point"}
}