{
  "type": "Feature",
  "properties": {
    "addr:full":"4030 Winchester Rd Allentown PA 18104",
    "addr:housenumber":"4030",
    "addr:postcode":"18104",
    "addr:street":"Winchester Rd",
    "iso:country":"US",
    "sg:address":"4030 Winchester Rd",
    "sg:city":"Allentown",
    "sg:classifiers":[
        {
            "category":"Health Services",
            "subcategory":"Dentist",
            "type":"Services"
        }
    ],
    "sg:phone":"+1 610 398 8243",
    "sg:postcode":"18104",
    "sg:province":"PA",
    "wof:name":"Salines Leonard P III Dntst",
    "wof:placetype":"venue"
},
  "geometry": {"coordinates":[-75.552696,40.6101],"type":"Point"}
}