{
  "type": "Feature",
  "properties": {
    "addr:full":"322 Blvd of the Allies Pittsburgh PA 15222",
    "addr:housenumber":"322",
    "addr:postcode":"15222",
    "addr:street":"Blvd Of The Allies",
    "iso:country":"US",
    "sg:address":"322 Blvd of the Allies",
    "sg:city":"Pittsburgh",
    "sg:classifiers":[
        {
            "category":"Professional",
            "subcategory":"Lawyer & Legal Services",
            "type":"Services"
        }
    ],
    "sg:phone":"+1 412 281 5423",
    "sg:postcode":"15222",
    "sg:province":"PA",
    "wof:name":"Fingeret Ilene H Atty",
    "wof:placetype":"venue"
},
  "geometry": {"coordinates":[-80.001503,40.438301],"type":"Point"}
}