{
  "type": "Feature",
  "properties": {
    "iso:country":"US",
    "sg:address":"801 McNeilly Rd",
    "sg:city":"Pittsburgh",
    "sg:classifiers":[
        {
            "category":"Building & Trades",
            "subcategory":"Construction",
            "type":"Services"
        }
    ],
    "sg:phone":"+1   ",
    "sg:postcode":"15226",
    "sg:province":"PA",
    "sg:tags":[
        "general",
        "contractor"
    ],
    "wof:name":"Manheim Corp Constrs Managers",
    "wof:placetype":"venue"
},
  "geometry": {"coordinates":[-80.01250400000001,40.3834],"type":"Point"}
}