{
  "type": "Feature",
  "properties": {
    "iso:country":"US",
    "sg:address":"2822 Connecticut Ave",
    "sg:city":"Pittsburgh",
    "sg:classifiers":[
        {
            "category":"Building & Trades",
            "subcategory":"Construction",
            "type":"Services"
        }
    ],
    "sg:phone":"+1 412 563 7212",
    "sg:postcode":"15216",
    "sg:province":"PA",
    "sg:tags":[
        "hanging",
        "painter",
        "contractor"
    ],
    "wof:name":"Bristle Brothers Painting Co",
    "wof:placetype":"venue"
},
  "geometry": {"coordinates":[-80.03717,40.398839],"type":"Point"}
}