{
  "type": "Feature",
  "properties": {
    "iso:country":"US",
    "sg:address":"701 Harrison St",
    "sg:city":"Allentown",
    "sg:classifiers":[
        {
            "category":"Professional",
            "type":"Services"
        }
    ],
    "sg:phone":"+1   ",
    "sg:postcode":"18103",
    "sg:province":"PA",
    "wof:name":"Michael Vega",
    "wof:placetype":"venue"
},
  "geometry": {"coordinates":[-75.469948,40.593963],"type":"Point"}
}