{
  "type": "Feature",
  "properties": {
    "iso:country":"US",
    "sg:address":"135 Main St",
    "sg:city":"Johnsonburg",
    "sg:classifiers":[
        {
            "category":"Real Estate",
            "subcategory":"Real Estate Agent",
            "type":"Services"
        }
    ],
    "sg:phone":"+1 814 725 0093",
    "sg:postcode":"15845",
    "sg:province":"PA",
    "sg:tags":[
        "agency",
        "rental"
    ],
    "wof:name":"Enterprise Rent A Car",
    "wof:placetype":"venue"
},
  "geometry": {"coordinates":[-78.683381,41.499508],"type":"Point"}
}