{
  "type": "Feature",
  "properties": {
    "addr:full":"1416 7th Ave Beaver Falls PA 15010",
    "addr:housenumber":"1416",
    "addr:postcode":"15010",
    "addr:street":"7Th Ave",
    "iso:country":"US",
    "sg:address":"1416 7th Ave",
    "sg:city":"Beaver Falls",
    "sg:classifiers":[
        {
            "category":"Shopping",
            "type":"Retail Goods"
        }
    ],
    "sg:phone":"+1 724 843 5250",
    "sg:postcode":"15010",
    "sg:province":"PA",
    "sg:tags":[
        "pet",
        "food",
        "fish",
        "tropical"
    ],
    "wof:name":"Aquatic Gardens",
    "wof:placetype":"venue"
},
  "geometry": {"coordinates":[-80.319354,40.755801],"type":"Point"}
}