{
  "type": "Feature",
  "properties": {
    "addr:full":"6719 Ridge Ave Philadelphia PA 19128",
    "addr:housenumber":"6719",
    "addr:postcode":"19128",
    "addr:street":"Ridge Ave",
    "iso:country":"US",
    "sg:address":"6719 Ridge Ave",
    "sg:city":"Philadelphia",
    "sg:classifiers":[
        {
            "category":"Autos & Motor Vehicles",
            "subcategory":"Automobile Sales",
            "type":"Retail Goods"
        }
    ],
    "sg:phone":"+1 215 508 7278",
    "sg:postcode":"19128",
    "sg:province":"PA",
    "sg:tags":[
        "car",
        "dealer"
    ],
    "sg:website":"www.prowlerland.com",
    "wof:name":"Gary Barbera's Dodgeland",
    "wof:placetype":"venue"
},
  "geometry": {"coordinates":[-75.225275,40.041381],"type":"Point"}
}