{
  "type": "Feature",
  "properties": {
    "addr:full":"7500 Germantown Ave E1 Philadelphia PA 19119",
    "addr:housenumber":"7500;e1",
    "addr:postcode":"19119",
    "addr:street":"Germantown Ave",
    "iso:country":"US",
    "sg:address":"7500 Germantown Ave E1",
    "sg:city":"Philadelphia",
    "sg:classifiers":[
        {
            "category":"Education",
            "subcategory":"School",
            "type":"Public Place"
        }
    ],
    "sg:phone":"+1 215 248 1662",
    "sg:postcode":"19119",
    "sg:province":"PA",
    "sg:tags":[
        "k-",
        "private"
    ],
    "sg:website":"http://www.phillywaldorf.com",
    "wof:name":"Waldorf School Of Philadelphia",
    "wof:placetype":"venue"
},
  "geometry": {"coordinates":[-75.194733,40.064732],"type":"Point"}
}