{
  "type": "Feature",
  "properties": {
    "iso:country":"US",
    "sg:address":"5830 Village Ln",
    "sg:city":"Doylestown",
    "sg:classifiers":[
        {
            "category":"Health Services",
            "subcategory":"Health Practitioner",
            "type":"Services"
        }
    ],
    "sg:phone":"+1   ",
    "sg:postcode":"18901",
    "sg:province":"PA",
    "sg:tags":[
        "occupational",
        "therapy"
    ],
    "wof:name":"Comprehensive Therapy",
    "wof:placetype":"venue"
},
  "geometry": {"coordinates":[-75.07632099999999,40.371601],"type":"Point"}
}