{
  "type": "Feature",
  "properties": {
    "addr:full":"1724 5th Ave Arnold PA 15068",
    "addr:housenumber":"1724",
    "addr:postcode":"15068",
    "addr:street":"5Th Ave",
    "iso:country":"US",
    "sg:address":"1724 5th Ave",
    "sg:city":"Arnold",
    "sg:classifiers":[
        {
            "category":"Recreation",
            "type":"Entertainment"
        }
    ],
    "sg:phone":"+1 724 335 9300",
    "sg:postcode":"15068",
    "sg:province":"PA",
    "sg:tags":[
        "karate",
        "judo",
        "instr"
    ],
    "wof:name":"Academy Of Martial Arts",
    "wof:placetype":"venue"
},
  "geometry": {"coordinates":[-79.76793600000001,40.57854],"type":"Point"}
}