{
  "type": "Feature",
  "properties": {
    "iso:country":"US",
    "sg:address":"244 York Rd",
    "sg:city":"Carlisle",
    "sg:classifiers":[
        {
            "category":"Autos & Motor Vehicles",
            "subcategory":"Fuel & Gas Station",
            "type":"Retail Goods"
        }
    ],
    "sg:phone":"+1 717 249 5367",
    "sg:postcode":"17013",
    "sg:province":"PA",
    "sg:website":"www.kwikfill.com",
    "wof:name":"Kwik-Fill",
    "wof:placetype":"venue"
},
  "geometry": {"coordinates":[-77.1661,40.194099],"type":"Point"}
}