{
  "type": "Feature",
  "properties": {
    "addr:full":"107 Diamond St Titusville PA 16354",
    "addr:housenumber":"107",
    "addr:postcode":"16354",
    "addr:street":"Diamond St",
    "iso:country":"US",
    "sg:address":"107 Diamond St",
    "sg:city":"Titusville",
    "sg:classifiers":[
        {
            "category":"Shopping",
            "subcategory":"Jewelry",
            "type":"Retail Goods"
        }
    ],
    "sg:phone":"+1 814 827 2832",
    "sg:postcode":"16354",
    "sg:province":"PA",
    "wof:name":"J & K Jewelry",
    "wof:placetype":"venue"
},
  "geometry": {"coordinates":[-79.671691,41.626695],"type":"Point"}
}