{
  "type": "Feature",
  "properties": {
    "addr:full":"5374 Library Rd Bethel Park PA 15102",
    "addr:housenumber":"5374",
    "addr:postcode":"15102",
    "addr:street":"Library Rd",
    "iso:country":"US",
    "sg:address":"5374 Library Rd",
    "sg:city":"Bethel Park",
    "sg:classifiers":[
        {
            "category":"Home & Garden",
            "subcategory":"Furniture",
            "type":"Retail Goods"
        }
    ],
    "sg:phone":"+1   ",
    "sg:postcode":"15102",
    "sg:province":"PA",
    "wof:name":"Suburban Furniture Service",
    "wof:placetype":"venue"
},
  "geometry": {"coordinates":[-80.025226,40.327545],"type":"Point"}
}