{
  "type": "Feature",
  "properties": {
    "iso:country":"US",
    "sg:address":"4745 Mercer St",
    "sg:city":"Philadelphia",
    "sg:classifiers":[
        {
            "category":"Professional",
            "type":"Services"
        },
        {
            "category":"Professional",
            "subcategory":"Computer Services",
            "type":"Services"
        }
    ],
    "sg:phone":"+1 215 288 7274",
    "sg:postcode":"19195",
    "sg:province":"PA",
    "sg:tags":[
        "repair"
    ],
    "sg:website":"www.kontech.net",
    "wof:name":"Kontech Computer Services",
    "wof:placetype":"venue"
},
  "geometry": {"coordinates":[-75.06864299999999,40.003226],"type":"Point"}
}