{
  "type": "Feature",
  "properties": {
    "addr:full":"6726 Frankford Ave Philadelphia PA 19135",
    "addr:housenumber":"6726",
    "addr:postcode":"19135",
    "addr:street":"Frankford Ave",
    "iso:country":"US",
    "sg:address":"6726 Frankford Ave",
    "sg:city":"Philadelphia",
    "sg:classifiers":[
        {
            "category":"Retail",
            "subcategory":"Auto Repair",
            "type":"Services"
        }
    ],
    "sg:phone":"+1 215 331 3300",
    "sg:postcode":"19135",
    "sg:province":"PA",
    "sg:tags":[
        "transmission"
    ],
    "wof:name":"Cottman Transmission Ctr",
    "wof:placetype":"venue"
},
  "geometry": {"coordinates":[-75.05145899999999,40.032226],"type":"Point"}
}