{
  "type": "Feature",
  "properties": {
    "iso:country":"US",
    "sg:address":"690 Clover Hill Rd",
    "sg:city":"Somerset",
    "sg:classifiers":[
        {
            "category":"Manufacturing",
            "subcategory":"Lumber",
            "type":"Manufacturing & Wholesale Goods"
        }
    ],
    "sg:phone":"+1   ",
    "sg:postcode":"15501",
    "sg:province":"PA",
    "sg:tags":[
        "operation",
        "timber",
        "tract"
    ],
    "wof:name":"Karl W and Mary Ann Poorb",
    "wof:placetype":"venue"
},
  "geometry": {"coordinates":[-79.092129,40.013404],"type":"Point"}
}