{
  "type": "Feature",
  "properties": {
    "addr:full":"101 W Chester Rd West Chester PA 19382",
    "addr:housenumber":"101",
    "addr:postcode":"19382",
    "addr:street":"W Chester Rd",
    "iso:country":"US",
    "sg:address":"101 W Chester Rd",
    "sg:city":"West Chester",
    "sg:classifiers":[
        {
            "category":"Social Services",
            "type":"Services"
        }
    ],
    "sg:phone":"+1 610 696 8746",
    "sg:postcode":"19382",
    "sg:province":"PA",
    "sg:tags":[
        "organization",
        "welfare"
    ],
    "wof:name":"Salvation Army",
    "wof:placetype":"venue"
},
  "geometry": {"coordinates":[-75.544263,39.910686],"type":"Point"}
}