{
  "type": "Feature",
  "properties": {
    "iso:country":"US",
    "sg:address":"1404 Pleasant Valley Blvd",
    "sg:city":"Altoona",
    "sg:classifiers":[
        {
            "category":"Building & Trades",
            "subcategory":"Construction",
            "type":"Services"
        }
    ],
    "sg:phone":"+1   ",
    "sg:postcode":"16602",
    "sg:province":"PA",
    "sg:tags":[
        "hanging",
        "contractor"
    ],
    "wof:name":"Tim Mosels Painting",
    "wof:placetype":"venue"
},
  "geometry": {"coordinates":[-78.38869099999999,40.504329],"type":"Point"}
}