{
  "type": "Feature",
  "properties": {
    "addr:full":"216 Wahl Ave Evans City PA 16033",
    "addr:housenumber":"216",
    "addr:postcode":"16033",
    "addr:street":"Wahl Ave",
    "iso:country":"US",
    "sg:address":"216 Wahl Ave",
    "sg:city":"Evans City",
    "sg:classifiers":[
        {
            "category":"Manufacturing",
            "subcategory":"Printing",
            "type":"Manufacturing & Wholesale Goods"
        }
    ],
    "sg:phone":"+1 724 772 4911",
    "sg:postcode":"16033",
    "sg:province":"PA",
    "sg:tags":[
        "printer"
    ],
    "wof:name":"Minuteman Press",
    "wof:placetype":"venue"
},
  "geometry": {"coordinates":[-80.06321,40.770169],"type":"Point"}
}