{
  "type": "Feature",
  "properties": {
    "addr:full":"724 Landis St Philadelphia PA 19124",
    "addr:housenumber":"724",
    "addr:postcode":"19124",
    "addr:street":"Landis St",
    "iso:country":"US",
    "sg:address":"724 Landis St",
    "sg:city":"Philadelphia",
    "sg:classifiers":[
        {
            "category":"Health Services",
            "subcategory":"Doctor",
            "type":"Services"
        }
    ],
    "sg:phone":"+1   ",
    "sg:postcode":"19124",
    "sg:province":"PA",
    "sg:tags":[
        "medical"
    ],
    "wof:name":"Hu He Fang",
    "wof:placetype":"venue"
},
  "geometry": {"coordinates":[-75.107354,40.030767],"type":"Point"}
}