{
  "type": "Feature",
  "properties": {
    "addr:full":"5401 Lincoln Hwy Gap PA 17527",
    "addr:housenumber":"5401",
    "addr:postcode":"17527",
    "addr:street":"Lincoln Hwy",
    "iso:country":"US",
    "sg:address":"5401 Lincoln Hwy",
    "sg:city":"Gap",
    "sg:classifiers":[
        {
            "category":"Autos & Motor Vehicles",
            "subcategory":"Fuel & Gas Station",
            "type":"Retail Goods"
        }
    ],
    "sg:phone":"+1 717 442 9573",
    "sg:postcode":"17527",
    "sg:province":"PA",
    "sg:tags":[
        "oil"
    ],
    "wof:name":"Shell's Service Center-Gap",
    "wof:placetype":"venue"
},
  "geometry": {"coordinates":[-76.015259,39.991243],"type":"Point"}
}