{
  "type": "Feature",
  "properties": {
    "iso:country":"US",
    "sg:address":"857 Langstroth Ln",
    "sg:city":"Bensalem",
    "sg:classifiers":[
        {
            "category":"Social Services",
            "subcategory":"Child Care",
            "type":"Services"
        }
    ],
    "sg:phone":"+1   ",
    "sg:postcode":"19020",
    "sg:province":"PA",
    "sg:tags":[
        "day"
    ],
    "wof:name":"St Francis Homes For Boys",
    "wof:placetype":"venue"
},
  "geometry": {"coordinates":[-74.959525,40.074889],"type":"Point"}
}