{
  "type": "Feature",
  "properties": {
    "iso:country":"US",
    "sg:address":"212 Locust St",
    "sg:city":"Harrisburg",
    "sg:classifiers":[
        {
            "category":"Professional",
            "subcategory":"Lawyer & Legal Services",
            "type":"Services"
        }
    ],
    "sg:phone":"+1 717 238 8183",
    "sg:postcode":"17101",
    "sg:province":"PA",
    "sg:tags":[
        "attorney"
    ],
    "wof:name":"David T Kluz",
    "wof:placetype":"venue"
},
  "geometry": {"coordinates":[-76.883752,40.26114],"type":"Point"}
}