{
  "type": "Feature",
  "properties": {
    "iso:country":"US",
    "sg:address":"312 Darby Rd",
    "sg:city":"Havertown",
    "sg:classifiers":[
        {
            "category":"Manufacturing",
            "subcategory":"Tools & Machinery",
            "type":"Manufacturing & Wholesale Goods"
        }
    ],
    "sg:phone":"+1 610 449 9800",
    "sg:postcode":"19083",
    "sg:province":"PA",
    "sg:tags":[
        "automatic"
    ],
    "sg:website":"www.neccdelivers.com",
    "wof:name":"National Energy Control Corp",
    "wof:placetype":"venue"
},
  "geometry": {"coordinates":[-75.29885299999999,39.970663],"type":"Point"}
}