{
  "type": "Feature",
  "properties": {
    "addr:full":"169 Rocky Mountain Dr S Effort PA 18330",
    "addr:housenumber":"169",
    "addr:postcode":"18330",
    "addr:street":"Rocky Mountain Dr S",
    "iso:country":"US",
    "sg:address":"169 Rocky Mountain Dr S",
    "sg:city":"Effort",
    "sg:classifiers":[
        {
            "category":"Building & Trades",
            "subcategory":"Construction",
            "type":"Services"
        }
    ],
    "sg:phone":"+1   ",
    "sg:postcode":"18330",
    "sg:province":"PA",
    "sg:tags":[
        "fireplace",
        "installation"
    ],
    "wof:name":"Peter Kaminski Fireplace Insta",
    "wof:placetype":"venue"
},
  "geometry": {"coordinates":[-75.44519,40.988192],"type":"Point"}
}