{
  "type": "Feature",
  "properties": {
    "iso:country":"US",
    "sg:address":"300 Bellefonte Ave",
    "sg:city":"Lock Haven",
    "sg:classifiers":[
        {
            "category":"Government",
            "subcategory":"Office",
            "type":"Public Place"
        }
    ],
    "sg:phone":"+1 570 893 4410",
    "sg:postcode":"17745",
    "sg:province":"PA",
    "sg:tags":[
        "state",
        "resource"
    ],
    "wof:name":"Public School Employees Rtrmnt",
    "wof:placetype":"venue"
},
  "geometry": {"coordinates":[-77.45198499999999,41.135181],"type":"Point"}
}