{
  "type": "Feature",
  "properties": {
    "iso:country":"US",
    "sg:address":"453 Bodnick St",
    "sg:city":"Peckville",
    "sg:classifiers":[
        {
            "category":"Manufacturing",
            "subcategory":"Metals",
            "type":"Manufacturing & Wholesale Goods"
        }
    ],
    "sg:phone":"+1   ",
    "sg:postcode":"18452",
    "sg:province":"PA",
    "sg:tags":[
        "mfg",
        "contractor",
        "architectural",
        "metalwork",
        "trade"
    ],
    "wof:name":"Lamortes Railing & Fence Comp",
    "wof:placetype":"venue"
},
  "geometry": {"coordinates":[-75.581732,41.484039],"type":"Point"}
}