{
  "type": "Feature",
  "properties": {
    "iso:country":"US",
    "sg:address":"716 N 7th St",
    "sg:city":"Allentown",
    "sg:classifiers":[
        {
            "category":"Home & Garden",
            "subcategory":"Building Materials",
            "type":"Retail Goods"
        }
    ],
    "sg:phone":"+1 610 437 6679",
    "sg:postcode":"18102",
    "sg:province":"PA",
    "sg:tags":[
        "windows"
    ],
    "wof:name":"Whitehall Aluminum Distrs",
    "wof:placetype":"venue"
},
  "geometry": {"coordinates":[-75.476551,40.612136],"type":"Point"}
}