{
  "type": "Feature",
  "properties": {
    "iso:country":"US",
    "sg:address":"11299 Baco Rd",
    "sg:city":"Meadville",
    "sg:classifiers":[
        {
            "category":"Manufacturing",
            "subcategory":"Tools & Machinery",
            "type":"Manufacturing & Wholesale Goods"
        }
    ],
    "sg:phone":"+1 814 336 3881",
    "sg:postcode":"16335",
    "sg:province":"PA",
    "sg:tags":[
        "base",
        "mold",
        "custom"
    ],
    "sg:website":"www.targetprecision.com",
    "wof:name":"Target Precision",
    "wof:placetype":"venue"
},
  "geometry": {"coordinates":[-80.218406,41.620813],"type":"Point"}
}