{
  "type": "Feature",
  "properties": {
    "iso:country":"US",
    "sg:address":"4220 Cottman Ave",
    "sg:city":"Philadelphia",
    "sg:classifiers":[
        {
            "category":"Health Services",
            "subcategory":"Podiatrist",
            "type":"Services"
        }
    ],
    "sg:phone":"+1 215 624 7607",
    "sg:postcode":"19135",
    "sg:province":"PA",
    "wof:name":"Ronald M Renzi DPM",
    "wof:placetype":"venue"
},
  "geometry": {"coordinates":[-75.03936299999999,40.035243],"type":"Point"}
}