{
  "type": "Feature",
  "properties": {
    "addr:full":"320 Crown Ave Scranton PA 18505",
    "addr:housenumber":"320",
    "addr:postcode":"18505",
    "addr:street":"Crown Ave",
    "iso:country":"US",
    "sg:address":"320 Crown Ave",
    "sg:city":"Scranton",
    "sg:classifiers":[
        {
            "category":"Food & Beverages",
            "subcategory":"Bakery",
            "type":"Retail Goods"
        }
    ],
    "sg:phone":"+1 570 346 2440",
    "sg:postcode":"18505",
    "sg:province":"PA",
    "sg:tags":[
        "baker"
    ],
    "wof:name":"Lynn Sandy's Cakes",
    "wof:placetype":"venue"
},
  "geometry": {"coordinates":[-75.656014,41.396633],"type":"Point"}
}