{
  "type": "Feature",
  "properties": {
    "iso:country":"US",
    "sg:address":"561 N Sandy Hill Rd",
    "sg:city":"Coatesville",
    "sg:classifiers":[
        {
            "category":"Professional",
            "subcategory":"Advertising",
            "type":"Services"
        }
    ],
    "sg:phone":"+1 610 857 5730",
    "sg:postcode":"19320",
    "sg:province":"PA",
    "wof:name":"Keiffer Productions Group",
    "wof:placetype":"venue"
},
  "geometry": {"coordinates":[-75.892973,40.039775],"type":"Point"}
}