{
  "type": "Feature",
  "properties": {
    "addr:full":"818 Dutch Hill Rd Oakdale PA 15071",
    "addr:housenumber":"818",
    "addr:postcode":"15071",
    "addr:street":"Dutch Hill Rd",
    "iso:country":"US",
    "sg:address":"818 Dutch Hill Rd",
    "sg:city":"Oakdale",
    "sg:classifiers":[
        {
            "category":"Professional",
            "subcategory":"Computer Services",
            "type":"Services"
        }
    ],
    "sg:phone":"+1 412 831 1219",
    "sg:postcode":"15071",
    "sg:province":"PA",
    "sg:tags":[
        "publisher",
        "developer",
        "software"
    ],
    "sg:website":"http://www.chickengirl.com",
    "wof:name":"Cg Software",
    "wof:placetype":"venue"
},
  "geometry": {"coordinates":[-80.141991,40.376369],"type":"Point"}
}