{
  "type": "Feature",
  "properties": {
    "iso:country":"US",
    "sg:address":"223 Orchard Ln",
    "sg:city":"Norristown",
    "sg:classifiers":[
        {
            "category":"Building & Trades",
            "subcategory":"Construction",
            "type":"Services"
        }
    ],
    "sg:phone":"+1   ",
    "sg:postcode":"19401",
    "sg:province":"PA",
    "sg:tags":[
        "house"
    ],
    "wof:name":"Glenns Hm Improvmnts",
    "wof:placetype":"venue"
},
  "geometry": {"coordinates":[-75.323708,40.148144],"type":"Point"}
}