{
  "type": "Feature",
  "properties": {
    "addr:full":"815 6th Ave Brackenridge PA 15014",
    "addr:housenumber":"815",
    "addr:postcode":"15014",
    "addr:street":"6Th Ave",
    "iso:country":"US",
    "sg:address":"815 6th Ave",
    "sg:city":"Brackenridge",
    "sg:classifiers":[
        {
            "category":"Bars & Pubs",
            "type":"Food & Drink"
        }
    ],
    "sg:phone":"+1 724 224 1999",
    "sg:postcode":"15014",
    "sg:province":"PA",
    "sg:tags":[
        "drinking"
    ],
    "wof:name":"Fat & Sassy Saloon",
    "wof:placetype":"venue"
},
  "geometry": {"coordinates":[-79.74493200000001,40.605628],"type":"Point"}
}