{
  "type": "Feature",
  "properties": {
    "iso:country":"US",
    "sg:address":"2302 Meetinghouse Rd",
    "sg:city":"Boothwyn",
    "sg:classifiers":[
        {
            "category":"Health Services",
            "subcategory":"Chiropractor",
            "type":"Services"
        }
    ],
    "sg:phone":"+1 610 485 6500",
    "sg:postcode":"19061",
    "sg:province":"PA",
    "wof:name":"Stewart Gambrill DC",
    "wof:placetype":"venue"
},
  "geometry": {"coordinates":[-75.452535,39.827514],"type":"Point"}
}