{
  "type": "Feature",
  "properties": {
    "iso:country":"US",
    "sg:address":"560 Mill Rd",
    "sg:city":"Havertown",
    "sg:classifiers":[
        {
            "category":"Social Services",
            "subcategory":"Child Care",
            "type":"Services"
        }
    ],
    "sg:phone":"+1 610 853 2267",
    "sg:postcode":"19083",
    "sg:province":"PA",
    "sg:tags":[
        "kindergarten",
        "academic",
        "school"
    ],
    "wof:name":"Play & Learn LTD",
    "wof:placetype":"venue"
},
  "geometry": {"coordinates":[-75.293385,39.987142],"type":"Point"}
}