{
  "type": "Feature",
  "properties": {
    "addr:full":"307 Clearfield Dr Lincoln Univ PA 19352",
    "addr:housenumber":"307",
    "addr:postcode":"19352",
    "addr:street":"Clearfield Dr",
    "iso:country":"US",
    "sg:address":"307 Clearfield Dr",
    "sg:city":"Lincoln Univ",
    "sg:classifiers":[
        {
            "category":"Organizations",
            "subcategory":"Professional Association",
            "type":"Services"
        }
    ],
    "sg:phone":"+1 610 869 7694",
    "sg:postcode":"19352",
    "sg:province":"PA",
    "sg:website":"www.gvfhra.org",
    "wof:name":"Greater Valley Forge Human",
    "wof:placetype":"venue"
},
  "geometry": {"coordinates":[-75.906019,39.767342],"type":"Point"}
}