{
  "type": "Feature",
  "properties": {
    "iso:country":"US",
    "sg:address":"151 Gateshead Dr",
    "sg:city":"Canonsburg",
    "sg:classifiers":[
        {
            "category":"Shopping",
            "subcategory":"Jewelry",
            "type":"Retail Goods"
        }
    ],
    "sg:phone":"+1 724 941 0748",
    "sg:postcode":"15317",
    "sg:province":"PA",
    "sg:tags":[
        "jeweler"
    ],
    "wof:name":"Fabulous Faux Accessories",
    "wof:placetype":"venue"
},
  "geometry": {"coordinates":[-80.11168000000001,40.284568],"type":"Point"}
}