{
  "type": "Feature",
  "properties": {
    "iso:country":"US",
    "sg:address":"100 Parklane Dr Ste 100",
    "sg:city":"Norristown",
    "sg:classifiers":[
        {
            "category":"Government",
            "subcategory":"City Hall",
            "type":"Public Place"
        },
        {
            "category":"Government",
            "subcategory":"Office",
            "type":"Public Place"
        }
    ],
    "sg:phone":"+1 610 539 6161",
    "sg:postcode":"19403",
    "sg:province":"PA",
    "sg:tags":[
        "town",
        "planner",
        "village",
        "township",
        "government-city"
    ],
    "sg:website":"http://www.lowerprovidence.org",
    "wof:name":"Government Offices City Lower Providence Township",
    "wof:placetype":"venue"
},
  "geometry": {"coordinates":[-75.406997,40.161014],"type":"Point"}
}