{
  "type": "Feature",
  "properties": {
    "addr:full":"2100 Spring St Philadelphia PA 19103",
    "addr:housenumber":"2100",
    "addr:postcode":"19103",
    "addr:street":"Spring St",
    "iso:country":"US",
    "sg:address":"2100 Spring St",
    "sg:city":"Philadelphia",
    "sg:classifiers":[
        {
            "category":"Building & Trades",
            "subcategory":"Locksmith",
            "type":"Services"
        }
    ],
    "sg:phone":"+1 267 773 5694",
    "sg:postcode":"19103",
    "sg:province":"PA",
    "sg:tags":[
        "key"
    ],
    "wof:name":"24 Hour Locksmith Service",
    "wof:placetype":"venue"
},
  "geometry": {"coordinates":[-75.174071,39.958234],"type":"Point"}
}