{
  "type": "Feature",
  "properties": {
    "iso:country":"US",
    "sg:address":"1025 Graham Ave",
    "sg:city":"Monessen",
    "sg:classifiers":[
        {
            "category":"Manufacturing",
            "subcategory":"Printing",
            "type":"Manufacturing & Wholesale Goods"
        }
    ],
    "sg:phone":"+1   ",
    "sg:postcode":"15062",
    "sg:province":"PA",
    "sg:tags":[
        "newspaper"
    ],
    "wof:name":"Mon Valley Newsppr Un Council",
    "wof:placetype":"venue"
},
  "geometry": {"coordinates":[-79.894773,40.152468],"type":"Point"}
}