{
  "type": "Feature",
  "properties": {
    "iso:country":"US",
    "sg:address":"407 Cathedral St",
    "sg:city":"Saltsburg",
    "sg:classifiers":[
        {
            "category":"Personal",
            "subcategory":"Beauty Salon",
            "type":"Services"
        }
    ],
    "sg:phone":"+1 724 639 9914",
    "sg:postcode":"15681",
    "sg:province":"PA",
    "wof:name":"Buell Styling By Charlene",
    "wof:placetype":"venue"
},
  "geometry": {"coordinates":[-79.44812400000001,40.48891],"type":"Point"}
}