{
  "type": "Feature",
  "properties": {
    "iso:country":"US",
    "sg:address":"225 S Maple St",
    "sg:city":"Tremont",
    "sg:classifiers":[
        {
            "category":"Retail",
            "subcategory":"Auto Repair",
            "type":"Services"
        }
    ],
    "sg:phone":"+1   ",
    "sg:postcode":"17981",
    "sg:province":"PA",
    "sg:tags":[
        "general"
    ],
    "wof:name":"Frank Miller Service",
    "wof:placetype":"venue"
},
  "geometry": {"coordinates":[-76.398641,40.636154],"type":"Point"}
}