{
  "type": "Feature",
  "properties": {
    "addr:full":"728 W Wallick Ln Red Lion PA 17356",
    "addr:housenumber":"728",
    "addr:postcode":"17356",
    "addr:street":"W Wallick Ln",
    "iso:country":"US",
    "sg:address":"728 W Wallick Ln",
    "sg:city":"Red Lion",
    "sg:classifiers":[
        {
            "category":"Building & Trades",
            "subcategory":"Plumbing",
            "type":"Services"
        }
    ],
    "sg:phone":"+1 717 244 1767",
    "sg:postcode":"17356",
    "sg:province":"PA",
    "sg:tags":[
        "air",
        "heating",
        "contractor",
        "system",
        "conditioning"
    ],
    "wof:name":"Humbert Heating & Air Cond",
    "wof:placetype":"venue"
},
  "geometry": {"coordinates":[-76.617417,39.896212],"type":"Point"}
}