{
  "type": "Feature",
  "properties": {
    "addr:full":"1400 Main St Peckville PA 18452",
    "addr:housenumber":"1400",
    "addr:postcode":"18452",
    "addr:street":"Main St",
    "iso:country":"US",
    "sg:address":"1400 Main St",
    "sg:city":"Peckville",
    "sg:classifiers":[
        {
            "category":"Health Services",
            "subcategory":"Doctor",
            "type":"Services"
        }
    ],
    "sg:phone":"+1 570 969 2527",
    "sg:postcode":"18452",
    "sg:province":"PA",
    "sg:tags":[
        "physician",
        "surgeon"
    ],
    "sg:website":"www.cutweight.org",
    "wof:name":"William S Peters DO",
    "wof:placetype":"venue"
},
  "geometry": {"coordinates":[-75.59518199999999,41.480713],"type":"Point"}
}