{
  "type": "Feature",
  "properties": {
    "addr:full":"5901 N Broad St Philadelphia PA 19141",
    "addr:housenumber":"5901",
    "addr:postcode":"19141",
    "addr:street":"N Broad St",
    "iso:country":"US",
    "sg:address":"5901 N Broad St",
    "sg:city":"Philadelphia",
    "sg:classifiers":[
        {
            "category":"Personal",
            "subcategory":"Barber",
            "type":"Services"
        }
    ],
    "sg:phone":"+1 215 927 3232",
    "sg:postcode":"19141",
    "sg:province":"PA",
    "sg:tags":[
        "school"
    ],
    "wof:name":"Tri-City Barber School Inc",
    "wof:placetype":"venue"
},
  "geometry": {"coordinates":[-75.143547,40.044426],"type":"Point"}
}