{
  "type": "Feature",
  "properties": {
    "iso:country":"US",
    "sg:address":"105 Greenwood Ave",
    "sg:city":"Wyncote",
    "sg:phone":"+1   ",
    "sg:postcode":"19095",
    "sg:province":"PA",
    "sg:tags":[
        "auto",
        "repair"
    ],
    "wof:name":"Greenwood Auto Care",
    "wof:placetype":"venue"
},
  "geometry": {"coordinates":[-75.14028999999999,40.091962],"type":"Point"}
}