{
  "type": "Feature",
  "properties": {
    "iso:country":"US",
    "sg:address":"951 N 4th St",
    "sg:city":"Allentown",
    "sg:classifiers":[
        {
            "category":"Health Services",
            "subcategory":"Hospital",
            "type":"Services"
        }
    ],
    "sg:phone":"+1   ",
    "sg:postcode":"18102",
    "sg:province":"PA",
    "sg:tags":[
        "general"
    ],
    "wof:name":"Sacred Heart Hosp Allentown",
    "wof:placetype":"venue"
},
  "geometry": {"coordinates":[-75.472364,40.618625],"type":"Point"}
}