{
  "type": "Feature",
  "properties": {
    "addr:full":"135 Beech St Beaver PA 15009",
    "addr:housenumber":"135",
    "addr:postcode":"15009",
    "addr:street":"Beech St",
    "iso:country":"US",
    "sg:address":"135 Beech St",
    "sg:city":"Beaver",
    "sg:classifiers":[
        {
            "category":"Professional",
            "subcategory":"Lawyer & Legal Services",
            "type":"Services"
        }
    ],
    "sg:phone":"+1   ",
    "sg:postcode":"15009",
    "sg:province":"PA",
    "wof:name":"Terry Cottage Cottage Law",
    "wof:placetype":"venue"
},
  "geometry": {"coordinates":[-80.40273500000001,40.703531],"type":"Point"}
}