{
  "type": "Feature",
  "properties": {
    "addr:full":"216 Lincoln Hwy Fairless Hills PA 19030",
    "addr:housenumber":"216",
    "addr:postcode":"19030",
    "addr:street":"Lincoln Hwy",
    "iso:country":"US",
    "sg:address":"216 Lincoln Hwy",
    "sg:city":"Fairless Hills",
    "sg:classifiers":[
        {
            "category":"Travel",
            "subcategory":"Hotels & Motels",
            "type":"Entertainment"
        }
    ],
    "sg:phone":"+1 215 945 9919",
    "sg:postcode":"19030",
    "sg:province":"PA",
    "sg:tags":[
        "operation"
    ],
    "wof:name":"Ace Motel",
    "wof:placetype":"venue"
},
  "geometry": {"coordinates":[-74.85724999999999,40.183709],"type":"Point"}
}