{
  "type": "Feature",
  "properties": {
    "iso:country":"US",
    "sg:address":"4300 Sheffield St",
    "sg:city":"Philadelphia",
    "sg:classifiers":[
        {
            "category":"Personal",
            "subcategory":"Beauty Salon",
            "type":"Services"
        }
    ],
    "sg:phone":"+1 215 331 2366",
    "sg:postcode":"19136",
    "sg:province":"PA",
    "sg:tags":[
        "shop"
    ],
    "wof:name":"Korner Kuts Hair Styling",
    "wof:placetype":"venue"
},
  "geometry": {"coordinates":[-75.031903,40.036992],"type":"Point"}
}