{
  "type": "Feature",
  "properties": {
    "iso:country":"US",
    "sg:address":"55 Curtis Dr",
    "sg:city":"Carlisle",
    "sg:classifiers":[
        {
            "category":"Farming",
            "subcategory":"Dairy Farm",
            "type":"Manufacturing & Wholesale Goods"
        }
    ],
    "sg:phone":"+1   ",
    "sg:postcode":"17013",
    "sg:province":"PA",
    "wof:name":"Lehman View Farms",
    "wof:placetype":"venue"
},
  "geometry": {"coordinates":[-77.217069,40.223828],"type":"Point"}
}