{
  "type": "Feature",
  "properties": {
    "iso:country":"US",
    "sg:address":"540 Old Waynesburg Rd",
    "sg:city":"Carmichaels",
    "sg:classifiers":[
        {
            "category":"Building & Trades",
            "subcategory":"Plumbing",
            "type":"Services"
        }
    ],
    "sg:phone":"+1 724 966 2640",
    "sg:postcode":"15320",
    "sg:province":"PA",
    "sg:tags":[
        "conditioning",
        "air",
        "system",
        "contractor"
    ],
    "wof:name":"Cleaner Air Svc",
    "wof:placetype":"venue"
},
  "geometry": {"coordinates":[-79.98065800000001,39.888229],"type":"Point"}
}