{
  "type": "Feature",
  "properties": {
    "addr:full":"355 Lancaster Ave Haverford PA 19041",
    "addr:housenumber":"355",
    "addr:postcode":"19041",
    "addr:street":"Lancaster Ave",
    "iso:country":"US",
    "sg:address":"355 Lancaster Ave",
    "sg:city":"Haverford",
    "sg:classifiers":[
        {
            "category":"Professional",
            "subcategory":"Employment Agencies",
            "type":"Services"
        }
    ],
    "sg:phone":"+1 610 649 9970",
    "sg:postcode":"19041",
    "sg:province":"PA",
    "sg:tags":[
        "personnel",
        "training"
    ],
    "wof:name":"Shiridon Health Matrix",
    "wof:placetype":"venue"
},
  "geometry": {"coordinates":[-75.298693,40.011804],"type":"Point"}
}