{
  "type": "Feature",
  "properties": {
    "addr:full":"110 E Market St Mercer PA 16137",
    "addr:housenumber":"110",
    "addr:postcode":"16137",
    "addr:street":"E Market St",
    "iso:country":"US",
    "sg:address":"110 E Market St",
    "sg:city":"Mercer",
    "sg:classifiers":[
        {
            "category":"Organizations",
            "subcategory":"Religious Organization",
            "type":"Services"
        }
    ],
    "sg:phone":"+1 724 662 2680",
    "sg:postcode":"16137",
    "sg:province":"PA",
    "sg:tags":[
        "church"
    ],
    "sg:website":"www.trinity4.info",
    "wof:name":"Trinity Presbyterian Church",
    "wof:placetype":"venue"
},
  "geometry": {"coordinates":[-80.237517,41.226808],"type":"Point"}
}