{
  "type": "Feature",
  "properties": {
    "addr:full":"6100 Vine St Philadelphia PA 19139",
    "addr:housenumber":"6100",
    "addr:postcode":"19139",
    "addr:street":"Vine St",
    "iso:country":"US",
    "sg:address":"6100 Vine St",
    "sg:city":"Philadelphia",
    "sg:classifiers":[
        {
            "category":"Restaurant",
            "type":"Food & Drink"
        }
    ],
    "sg:phone":"+1 215 747 8744",
    "sg:postcode":"19139",
    "sg:province":"PA",
    "sg:tags":[
        "eating"
    ],
    "wof:name":"Vine St Noodle House",
    "wof:placetype":"venue"
},
  "geometry": {"coordinates":[-75.24189800000001,39.9669],"type":"Point"}
}