{
  "type": "Feature",
  "properties": {
    "iso:country":"US",
    "sg:address":"454 Shamona Cir",
    "sg:city":"Downingtown",
    "sg:classifiers":[
        {
            "category":"Professional",
            "type":"Services"
        }
    ],
    "sg:phone":"+1   ",
    "sg:postcode":"19335",
    "sg:province":"PA",
    "wof:name":"Clarke R Buzz Inc",
    "wof:placetype":"venue"
},
  "geometry": {"coordinates":[-75.69350300000001,40.045948],"type":"Point"}
}