{
  "type": "Feature",
  "properties": {
    "iso:country":"US",
    "sg:address":"525 N New St",
    "sg:city":"Bethlehem",
    "sg:classifiers":[
        {
            "category":"Health Services",
            "subcategory":"Clinic",
            "type":"Services"
        }
    ],
    "sg:phone":"+1 610 865 4880",
    "sg:postcode":"18018",
    "sg:province":"PA",
    "wof:name":"Coordinated Health",
    "wof:placetype":"venue"
},
  "geometry": {"coordinates":[-75.37854799999999,40.621147],"type":"Point"}
}