{
  "type": "Feature",
  "properties": {
    "iso:country":"US",
    "sg:address":"3602 Horizon Dr",
    "sg:city":"King Of Prussia",
    "sg:classifiers":[
        {
            "category":"Professional",
            "subcategory":"Testing Lab",
            "type":"Services"
        },
        {
            "category":"Professional",
            "subcategory":"Engineering",
            "type":"Services"
        }
    ],
    "sg:phone":"+1 610 277 2402",
    "sg:postcode":"19406",
    "sg:province":"PA",
    "sg:tags":[
        "laboratory"
    ],
    "sg:website":"www.pennoni.com",
    "wof:name":"Pennoni Associates Inc",
    "wof:placetype":"venue"
},
  "geometry": {"coordinates":[-75.33962699999999,40.087677],"type":"Point"}
}