{
  "type": "Feature",
  "properties": {
    "iso:country":"US",
    "sg:address":"505 Vallebrook Rd",
    "sg:city":"McMurray",
    "sg:classifiers":[
        {
            "category":"Insurance",
            "subcategory":"Hazard Insurance",
            "type":"Services"
        }
    ],
    "sg:phone":"+1 724 969 0703",
    "sg:postcode":"15367",
    "sg:province":"PA",
    "sg:website":"www.searchmagnetlocal.com/Allsta...",
    "wof:name":"Russell Ergood McMurray- Allstate Insurance",
    "wof:placetype":"venue"
},
  "geometry": {"coordinates":[-80.08341,40.27885],"type":"Point"}
}