{
  "type": "Feature",
  "properties": {
    "iso:country":"US",
    "sg:address":"1391 Walton Rd",
    "sg:city":"Blue Bell",
    "sg:classifiers":[
        {
            "category":"Professional",
            "subcategory":"Management & Consulting",
            "type":"Services"
        }
    ],
    "sg:phone":"+1 215 628 8670",
    "sg:postcode":"19422",
    "sg:province":"PA",
    "sg:tags":[
        "consultant",
        "business"
    ],
    "wof:name":"Value Quest Inc",
    "wof:placetype":"venue"
},
  "geometry": {"coordinates":[-75.270618,40.139107],"type":"Point"}
}