{
  "type": "Feature",
  "properties": {
    "addr:full":"1100 N Hartley St York PA 17404",
    "addr:housenumber":"1100",
    "addr:postcode":"17404",
    "addr:street":"N Hartley St",
    "iso:country":"US",
    "sg:address":"1100 N Hartley St",
    "sg:city":"York",
    "sg:classifiers":[
        {
            "category":"Building & Trades",
            "subcategory":"Cleaning & Sanitation",
            "type":"Services"
        }
    ],
    "sg:phone":"+1 717 761 4603",
    "sg:postcode":"17404",
    "sg:province":"PA",
    "sg:tags":[
        "janitor"
    ],
    "sg:website":"www.firstqualityservices.com",
    "wof:name":"First Quality Svc Inc",
    "wof:placetype":"venue"
},
  "geometry": {"coordinates":[-76.75027300000001,39.966312],"type":"Point"}
}