{
  "type": "Feature",
  "properties": {
    "iso:country":"US",
    "sg:address":"1601 walnut street suite 1501",
    "sg:city":"Philadelphia",
    "sg:classifiers":[
        {
            "category":"Health Services",
            "subcategory":"Doctor",
            "type":"Services"
        }
    ],
    "sg:phone":"+1 215 563 9769",
    "sg:postcode":"19144",
    "sg:province":"PA",
    "sg:tags":[
        "surgeon",
        "oral"
    ],
    "sg:website":"www.pinerundental.com",
    "wof:name":"Henkel Gary L DDS",
    "wof:placetype":"venue"
},
  "geometry": {"coordinates":[-75.167531,39.949761],"type":"Point"}
}