{
  "type": "Feature",
  "properties": {
    "iso:country":"US",
    "sg:address":"933 5th Ave",
    "sg:city":"New Kensington",
    "sg:classifiers":[
        {
            "category":"Home & Garden",
            "subcategory":"Furniture",
            "type":"Retail Goods"
        }
    ],
    "sg:phone":"+1   ",
    "sg:postcode":"15068",
    "sg:province":"PA",
    "wof:name":"Broyhill Showcase Gallery",
    "wof:placetype":"venue"
},
  "geometry": {"coordinates":[-79.765486,40.566357],"type":"Point"}
}