{
  "type": "Feature",
  "properties": {
    "iso:country":"US",
    "sg:address":"11726 Bustleton Ave",
    "sg:city":"Philadelphia",
    "sg:classifiers":[
        {
            "category":"Food & Beverages",
            "subcategory":"Fruits & Vegetables",
            "type":"Retail Goods"
        }
    ],
    "sg:phone":"+1 215 698 2786",
    "sg:postcode":"19116",
    "sg:province":"PA",
    "sg:tags":[
        "produce"
    ],
    "wof:name":"Green Farmers Market",
    "wof:placetype":"venue"
},
  "geometry": {"coordinates":[-75.01638699999999,40.121705],"type":"Point"}
}