{
  "type": "Feature",
  "properties": {
    "iso:country":"US",
    "sg:address":"801 Ostrum St",
    "sg:city":"Bethlehem",
    "sg:classifiers":[
        {
            "category":"Health Services",
            "subcategory":"Doctor",
            "type":"Services"
        }
    ],
    "sg:phone":"+1 610 954 3399",
    "sg:postcode":"18015",
    "sg:province":"PA",
    "wof:name":"Physician Finder",
    "wof:placetype":"venue"
},
  "geometry": {"coordinates":[-75.392998,40.6082],"type":"Point"}
}