{
  "type": "Feature",
  "properties": {
    "iso:country":"US",
    "sg:address":"2949 Grand Ave",
    "sg:city":"Pittsburgh",
    "sg:classifiers":[
        {
            "category":"Manufacturing",
            "subcategory":"Tools & Machinery",
            "type":"Manufacturing & Wholesale Goods"
        }
    ],
    "sg:phone":"+1 412 331 8869",
    "sg:postcode":"15225",
    "sg:province":"PA",
    "sg:tags":[
        "construction",
        "mfg"
    ],
    "wof:name":"Brauner Equipment Co",
    "wof:placetype":"venue"
},
  "geometry": {"coordinates":[-80.116805,40.508623],"type":"Point"}
}