{
  "type": "Feature",
  "properties": {
    "addr:full":"349 Brighton Rd Plymouth Meeting PA 19462",
    "addr:housenumber":"349",
    "addr:postcode":"19462",
    "addr:street":"Brighton Rd",
    "iso:country":"US",
    "sg:address":"349 Brighton Rd",
    "sg:city":"Plymouth Meeting",
    "sg:classifiers":[
        {
            "category":"Wholesale",
            "subcategory":"Office Equipment",
            "type":"Manufacturing & Wholesale Goods"
        }
    ],
    "sg:phone":"+1 610 275 3173",
    "sg:postcode":"19462",
    "sg:province":"PA",
    "sg:tags":[
        "protection",
        "check",
        "mach"
    ],
    "sg:website":"www.cpcsys.com",
    "wof:name":"CPC Systems Corp",
    "wof:placetype":"venue"
},
  "geometry": {"coordinates":[-75.30122,40.136455],"type":"Point"}
}