{
  "type": "Feature",
  "properties": {
    "iso:country":"US",
    "sg:address":"2 Greenway Cir",
    "sg:city":"Fairless Hills",
    "sg:classifiers":[
        {
            "category":"Mining & Drilling",
            "type":"Manufacturing & Wholesale Goods"
        }
    ],
    "sg:phone":"+1   ",
    "sg:postcode":"19030",
    "sg:province":"PA",
    "sg:tags":[
        "field"
    ],
    "wof:name":"Bristol Synthet6ic Lubric",
    "wof:placetype":"venue"
},
  "geometry": {"coordinates":[-74.86230999999999,40.161479],"type":"Point"}
}