{
  "type": "Feature",
  "properties": {
    "addr:full":"1098 3rd St Beaver PA 15009",
    "addr:housenumber":"1098",
    "addr:postcode":"15009",
    "addr:street":"3Rd St",
    "iso:country":"US",
    "sg:address":"1098 3rd St",
    "sg:city":"Beaver",
    "sg:classifiers":[
        {
            "category":"Organizations",
            "subcategory":"Religious Organization",
            "type":"Services"
        }
    ],
    "sg:phone":"+1   ",
    "sg:postcode":"15009",
    "sg:province":"PA",
    "wof:name":"Holy Trnty Evang Lthran Church",
    "wof:placetype":"venue"
},
  "geometry": {"coordinates":[-80.309938,40.693132],"type":"Point"}
}