{
  "type": "Feature",
  "properties": {
    "iso:country":"US",
    "sg:address":"30 Bantry Ln Ste 100",
    "sg:city":"Phoenixville",
    "sg:classifiers":[
        {
            "category":"Professional",
            "subcategory":"Accounting & Tax Preparation",
            "type":"Services"
        }
    ],
    "sg:phone":"+1 610 935 0592",
    "sg:postcode":"19460",
    "sg:province":"PA",
    "sg:tags":[
        "bookkeeping",
        "billing"
    ],
    "wof:name":"Fcs Management Assoc Inc",
    "wof:placetype":"venue"
},
  "geometry": {"coordinates":[-75.481666,40.109896],"type":"Point"}
}