{
  "type": "Feature",
  "properties": {
    "iso:country":"US",
    "sg:address":"1732 W Fairmont St",
    "sg:city":"Allentown",
    "sg:classifiers":[
        {
            "category":"Building & Trades",
            "subcategory":"Plumbing",
            "type":"Services"
        }
    ],
    "sg:phone":"+1   ",
    "sg:postcode":"18104",
    "sg:province":"PA",
    "sg:tags":[
        "contractor"
    ],
    "wof:name":"Indoor Comfort Specialist",
    "wof:placetype":"venue"
},
  "geometry": {"coordinates":[-75.50344699999999,40.615224],"type":"Point"}
}