{
  "type": "Feature",
  "properties": {
    "addr:full":"1389 Streets Run Rd Pittsburgh PA 15236",
    "addr:housenumber":"1389",
    "addr:postcode":"15236",
    "addr:street":"Streets Run Rd",
    "iso:country":"US",
    "sg:address":"1389 Streets Run Rd",
    "sg:city":"Pittsburgh",
    "sg:classifiers":[
        {
            "category":"Retail",
            "subcategory":"Auto Repair",
            "type":"Services"
        }
    ],
    "sg:phone":"+1   ",
    "sg:postcode":"15236",
    "sg:province":"PA",
    "sg:tags":[
        "automotive",
        "general"
    ],
    "wof:name":"Streets Run Auto Service",
    "wof:placetype":"venue"
},
  "geometry": {"coordinates":[-79.95691600000001,40.354707],"type":"Point"}
}