{
  "type": "Feature",
  "properties": {
    "iso:country":"US",
    "sg:address":"5937 Chestnut St",
    "sg:city":"Philadelphia",
    "sg:classifiers":[
        {
            "category":"Health Services",
            "subcategory":"Doctor",
            "type":"Services"
        }
    ],
    "sg:phone":"+1 215 476 1616",
    "sg:postcode":"19139",
    "sg:province":"PA",
    "sg:tags":[
        "podiatrist"
    ],
    "wof:name":"Pron John A Podiatrist",
    "wof:placetype":"venue"
},
  "geometry": {"coordinates":[-75.2407,39.9603],"type":"Point"}
}