{
  "type": "Feature",
  "properties": {
    "addr:full":"939 Jefferson Ave Norristown PA 19403",
    "addr:housenumber":"939",
    "addr:postcode":"19403",
    "addr:street":"Jefferson Ave",
    "iso:country":"US",
    "sg:address":"939 Jefferson Ave",
    "sg:city":"Norristown",
    "sg:classifiers":[
        {
            "category":"Building & Trades",
            "subcategory":"Construction",
            "type":"Services"
        }
    ],
    "sg:phone":"+1   ",
    "sg:postcode":"19403",
    "sg:province":"PA",
    "sg:tags":[
        "nonresidential"
    ],
    "wof:name":"Lamb Design Inc",
    "wof:placetype":"venue"
},
  "geometry": {"coordinates":[-75.41285999999999,40.124466],"type":"Point"}
}