{
  "type": "Feature",
  "properties": {
    "iso:country":"US",
    "sg:address":"3945 Mimosa Dr",
    "sg:city":"Bethel Park",
    "sg:classifiers":[
        {
            "category":"Retail",
            "subcategory":"Repair Shop",
            "type":"Services"
        }
    ],
    "sg:phone":"+1 412 833 3223",
    "sg:postcode":"15102",
    "sg:province":"PA",
    "sg:tags":[
        "appliance"
    ],
    "wof:name":"Weidner Service",
    "wof:placetype":"venue"
},
  "geometry": {"coordinates":[-80.024315,40.313984],"type":"Point"}
}