{
  "type": "Feature",
  "properties": {
    "iso:country":"US",
    "sg:address":"3515 W Chester Pike",
    "sg:city":"Newtown Square",
    "sg:classifiers":[
        {
            "category":"Banks & Credit Unions",
            "subcategory":"Bank",
            "type":"Services"
        }
    ],
    "sg:phone":"+1 610 356 2265",
    "sg:postcode":"19073",
    "sg:province":"PA",
    "wof:name":"Wachovia Bank",
    "wof:placetype":"venue"
},
  "geometry": {"coordinates":[-75.39526600000001,39.985661],"type":"Point"}
}