{
  "type": "Feature",
  "properties": {
    "iso:country":"US",
    "sg:address":"2113 Green St",
    "sg:city":"Philadelphia",
    "sg:classifiers":[
        {
            "category":"Real Estate",
            "subcategory":"Real Estate Agent",
            "type":"Services"
        }
    ],
    "sg:phone":"+1 215 765 7222",
    "sg:postcode":"19130",
    "sg:province":"PA",
    "wof:name":"DHD Properties",
    "wof:placetype":"venue"
},
  "geometry": {"coordinates":[-75.173998,39.965462],"type":"Point"}
}