{
  "type": "Feature",
  "properties": {
    "addr:full":"1570 Raymond Cir Swarthmore PA 19081",
    "addr:housenumber":"1570",
    "addr:postcode":"19081",
    "addr:street":"Raymond Cir",
    "iso:country":"US",
    "sg:address":"1570 Raymond Cir",
    "sg:city":"Swarthmore",
    "sg:classifiers":[
        {
            "category":"Real Estate",
            "subcategory":"Real Estate Agent",
            "type":"Services"
        }
    ],
    "sg:phone":"+1   ",
    "sg:postcode":"19081",
    "sg:province":"PA",
    "wof:name":"Moran Realty Investments",
    "wof:placetype":"venue"
},
  "geometry": {"coordinates":[-75.349605,39.888957],"type":"Point"}
}