{
  "type": "Feature",
  "properties": {
    "iso:country":"US",
    "sg:address":"296 Bristol Pike",
    "sg:city":"Croydon",
    "sg:classifiers":[
        {
            "category":"Banks & Credit Unions",
            "subcategory":"Bank",
            "type":"Services"
        }
    ],
    "sg:phone":"+1 215 000 1111",
    "sg:postcode":"19021",
    "sg:province":"PA",
    "wof:name":"Bank Of America",
    "wof:placetype":"venue"
},
  "geometry": {"coordinates":[-74.912964,40.093696],"type":"Point"}
}