{
  "type": "Feature",
  "properties": {
    "addr:full":"858 New Castle Rd Butler PA 16001",
    "addr:housenumber":"858",
    "addr:postcode":"16001",
    "addr:street":"New Castle Rd",
    "iso:country":"US",
    "sg:address":"858 New Castle Rd",
    "sg:city":"Butler",
    "sg:classifiers":[
        {
            "category":"Wholesale",
            "subcategory":"Construction Materials",
            "type":"Manufacturing & Wholesale Goods"
        }
    ],
    "sg:phone":"+1 724 865 2592",
    "sg:postcode":"16001",
    "sg:province":"PA",
    "sg:tags":[
        "concrete",
        "product"
    ],
    "wof:name":"Semper Concrete Products",
    "wof:placetype":"venue"
},
  "geometry": {"coordinates":[-80.004457,40.896508],"type":"Point"}
}