{
  "type": "Feature",
  "properties": {
    "iso:country":"US",
    "sg:address":"4237 Main Street",
    "sg:city":"Philadelphia",
    "sg:classifiers":[
        {
            "category":"Personal",
            "subcategory":"Nail Salon",
            "type":"Services"
        }
    ],
    "sg:phone":"+1 215 483 2501",
    "sg:postcode":"19127",
    "sg:province":"PA",
    "wof:name":"Brenda Nails & Spa",
    "wof:placetype":"venue"
},
  "geometry": {"coordinates":[-75.22091,40.02447],"type":"Point"}
}