{
  "type": "Feature",
  "properties": {
    "addr:full":"1960 Bristol Rd Southampton PA 18966",
    "addr:housenumber":"1960",
    "addr:postcode":"18966",
    "addr:street":"Bristol Rd",
    "iso:country":"US",
    "sg:address":"1960 Bristol Rd",
    "sg:city":"Southampton",
    "sg:classifiers":[
        {
            "category":"Building & Trades",
            "subcategory":"Electrical",
            "type":"Services"
        }
    ],
    "sg:phone":"+1   ",
    "sg:postcode":"18966",
    "sg:province":"PA",
    "sg:tags":[
        "electrical",
        "contractor"
    ],
    "wof:name":"Schreiner Electric",
    "wof:placetype":"venue"
},
  "geometry": {"coordinates":[-75.000771,40.172154],"type":"Point"}
}