{
  "type": "Feature",
  "properties": {
    "addr:full":"4625 Ditman St Philadelphia PA 19124",
    "addr:housenumber":"4625",
    "addr:postcode":"19124",
    "addr:street":"Ditman St",
    "iso:country":"US",
    "sg:address":"4625 Ditman St",
    "sg:city":"Philadelphia",
    "sg:classifiers":[
        {
            "category":"Building & Trades",
            "subcategory":"Plumbing",
            "type":"Services"
        }
    ],
    "sg:phone":"+1 215 533 7000",
    "sg:postcode":"19124",
    "sg:province":"PA",
    "sg:website":"www.buzzduzzplumbingheatingandai...",
    "wof:name":"Buzz Duzz Plumbing Heating & Air Conditioning",
    "wof:placetype":"venue"
},
  "geometry": {"coordinates":[-75.07940000000001,40.011706],"type":"Point"}
}