{
  "type": "Feature",
  "properties": {
    "iso:country":"US",
    "sg:address":"620 S Cameron St",
    "sg:city":"Harrisburg",
    "sg:classifiers":[
        {
            "category":"Autos & Motor Vehicles",
            "subcategory":"Fuel & Gas Station",
            "type":"Retail Goods"
        }
    ],
    "sg:phone":"+1 717 233 7855",
    "sg:postcode":"17104",
    "sg:province":"PA",
    "wof:name":"Service Oil Co Station No 11",
    "wof:placetype":"venue"
},
  "geometry": {"coordinates":[-76.8694,40.255402],"type":"Point"}
}