{
  "type": "Feature",
  "properties": {
    "iso:country":"US",
    "sg:address":"305 S Richland Ave",
    "sg:city":"York",
    "sg:classifiers":[
        {
            "category":"Shopping",
            "type":"Retail Goods"
        },
        {
            "category":"Food & Beverages",
            "subcategory":"Bakery",
            "type":"Retail Goods"
        }
    ],
    "sg:phone":"+1 717 848 6141",
    "sg:postcode":"17404",
    "sg:province":"PA",
    "sg:tags":[
        "cake",
        "decorating",
        "instruction",
        "supply"
    ],
    "wof:name":"Campbell's Cake & Candy Supls",
    "wof:placetype":"venue"
},
  "geometry": {"coordinates":[-76.746313,39.949346],"type":"Point"}
}