{
  "type": "Feature",
  "properties": {
    "addr:full":"1423 Dorey St Clearfield PA 16830",
    "addr:housenumber":"1423",
    "addr:postcode":"16830",
    "addr:street":"Dorey St",
    "iso:country":"US",
    "sg:address":"1423 Dorey St",
    "sg:city":"Clearfield",
    "sg:classifiers":[
        {
            "category":"Bars & Pubs",
            "type":"Food & Drink"
        }
    ],
    "sg:phone":"+1 814 765 7190",
    "sg:postcode":"16830",
    "sg:province":"PA",
    "sg:website":"www.dennysbeerbarrelpub.com",
    "wof:name":"Denny's Beer Barrel Pub",
    "wof:placetype":"venue"
},
  "geometry": {"coordinates":[-78.422658,41.024879],"type":"Point"}
}