{
  "type": "Feature",
  "properties": {
    "addr:full":"2800 Comly Rd Philadelphia PA 19154",
    "addr:housenumber":"2800",
    "addr:postcode":"19154",
    "addr:street":"Comly Rd",
    "iso:country":"US",
    "sg:address":"2800 Comly Rd",
    "sg:city":"Philadelphia",
    "sg:classifiers":[
        {
            "category":"Freight",
            "type":"Transportation"
        }
    ],
    "sg:phone":"+1 215 245 8920",
    "sg:postcode":"19154",
    "sg:province":"PA",
    "sg:tags":[
        "mover"
    ],
    "wof:name":"Isaac's Relocation",
    "wof:placetype":"venue"
},
  "geometry": {"coordinates":[-75.000919,40.1043],"type":"Point"}
}