{
  "type": "Feature",
  "properties": {
    "iso:country":"US",
    "sg:address":"35 Penn Am Dr",
    "sg:city":"Quakertown",
    "sg:classifiers":[
        {
            "category":"Wholesale",
            "subcategory":"Stationery",
            "type":"Manufacturing & Wholesale Goods"
        }
    ],
    "sg:phone":"+1   ",
    "sg:postcode":"18951",
    "sg:province":"PA",
    "sg:tags":[
        "paper",
        "mfg"
    ],
    "wof:name":"Fasson",
    "wof:placetype":"venue"
},
  "geometry": {"coordinates":[-75.351561,40.455933],"type":"Point"}
}