{
  "type": "Feature",
  "properties": {
    "addr:full":"1467 Easton Rd Warrington PA 18976",
    "addr:housenumber":"1467",
    "addr:postcode":"18976",
    "addr:street":"Easton Rd",
    "iso:country":"US",
    "sg:address":"1467 Easton Rd",
    "sg:city":"Warrington",
    "sg:classifiers":[
        {
            "category":"Wholesale",
            "subcategory":"Machinery & Supplies",
            "type":"Manufacturing & Wholesale Goods"
        }
    ],
    "sg:phone":"+1 215 343 8700",
    "sg:postcode":"18976",
    "sg:province":"PA",
    "sg:tags":[
        "lift"
    ],
    "wof:name":"Automotive Equipment Svc",
    "wof:placetype":"venue"
},
  "geometry": {"coordinates":[-75.132853,40.252474],"type":"Point"}
}