{
  "type": "Feature",
  "properties": {
    "iso:country":"US",
    "sg:address":"55 Pennypacker Rd",
    "sg:city":"Schwenksville",
    "sg:classifiers":[
        {
            "category":"Recreation",
            "type":"Entertainment"
        }
    ],
    "sg:phone":"+1   ",
    "sg:postcode":"19473",
    "sg:province":"PA",
    "wof:name":"Adventure Diving Inc",
    "wof:placetype":"venue"
},
  "geometry": {"coordinates":[-75.454627,40.259918],"type":"Point"}
}