{
  "type": "Feature",
  "properties": {
    "iso:country":"US",
    "sg:address":"200 N 30th St",
    "sg:city":"Harrisburg",
    "sg:classifiers":[
        {
            "category":"Organizations",
            "subcategory":"Professional Association",
            "type":"Services"
        }
    ],
    "sg:phone":"+1 717 545 1570",
    "sg:postcode":"17109",
    "sg:province":"PA",
    "wof:name":"Carwash Association Of Pa",
    "wof:placetype":"venue"
},
  "geometry": {"coordinates":[-76.845646,40.284387],"type":"Point"}
}