{
  "type": "Feature",
  "properties": {
    "addr:full":"805 New Holland Ave Lancaster PA 17602",
    "addr:housenumber":"805",
    "addr:postcode":"17602",
    "addr:street":"New Holland Ave",
    "iso:country":"US",
    "sg:address":"805 New Holland Ave",
    "sg:city":"Lancaster",
    "sg:classifiers":[
        {
            "category":"Health Services",
            "subcategory":"Health Practitioner",
            "type":"Services"
        }
    ],
    "sg:phone":"+1 717 396 7766",
    "sg:postcode":"17602",
    "sg:province":"PA",
    "sg:tags":[
        "therapist",
        "physical"
    ],
    "wof:name":"Kauffman-Gamber Physical Thrpy",
    "wof:placetype":"venue"
},
  "geometry": {"coordinates":[-76.291487,40.050284],"type":"Point"}
}