{
  "type": "Feature",
  "properties": {
    "addr:full":"153 Doctor Ln Renfrew PA 16053",
    "addr:housenumber":"153",
    "addr:postcode":"16053",
    "addr:street":"Doctor Ln",
    "iso:country":"US",
    "sg:address":"153 Doctor Ln",
    "sg:city":"Renfrew",
    "sg:classifiers":[
        {
            "category":"Manufacturing",
            "subcategory":"Retail Goods",
            "type":"Manufacturing & Wholesale Goods"
        }
    ],
    "sg:phone":"+1   ",
    "sg:postcode":"16053",
    "sg:province":"PA",
    "sg:tags":[
        "product",
        "wood",
        "mfg"
    ],
    "wof:name":"Just Around Block",
    "wof:placetype":"venue"
},
  "geometry": {"coordinates":[-79.992536,40.827287],"type":"Point"}
}