{
  "type": "Feature",
  "properties": {
    "addr:full":"414 Beaver St Lancaster PA 17603",
    "addr:housenumber":"414",
    "addr:postcode":"17603",
    "addr:street":"Beaver St",
    "iso:country":"US",
    "sg:address":"414 Beaver St",
    "sg:city":"Lancaster",
    "sg:classifiers":[
        {
            "category":"Building & Trades",
            "subcategory":"Construction",
            "type":"Services"
        }
    ],
    "sg:phone":"+1 717 399 8274",
    "sg:postcode":"17603",
    "sg:province":"PA",
    "sg:tags":[
        "roofing",
        "industrial",
        "contractors-commercial",
        "contractor"
    ],
    "wof:name":"Pete's Quality Roofing Inc",
    "wof:placetype":"venue"
},
  "geometry": {"coordinates":[-76.305509,40.03119],"type":"Point"}
}