{
  "type": "Feature",
  "properties": {
    "addr:full":"885 Sutton Rd Shavertown PA 18708",
    "addr:housenumber":"885",
    "addr:postcode":"18708",
    "addr:street":"Sutton Rd",
    "iso:country":"US",
    "sg:address":"885 Sutton Rd",
    "sg:city":"Shavertown",
    "sg:classifiers":[
        {
            "category":"Professional",
            "type":"Services"
        }
    ],
    "sg:phone":"+1   ",
    "sg:postcode":"18708",
    "sg:province":"PA",
    "wof:name":"Synectics Systems Inc",
    "wof:placetype":"venue"
},
  "geometry": {"coordinates":[-75.941942,41.299489],"type":"Point"}
}