{
  "type": "Feature",
  "properties": {
    "iso:country":"US",
    "sg:address":"401 W Commons Apt 312",
    "sg:city":"Pittsburgh",
    "sg:classifiers":[
        {
            "category":"Professional",
            "subcategory":"Business Services",
            "type":"Services"
        }
    ],
    "sg:phone":"+1 412 434 7020",
    "sg:postcode":"15212",
    "sg:province":"PA",
    "sg:tags":[
        "management"
    ],
    "wof:name":"Xxi-C Industries",
    "wof:placetype":"venue"
},
  "geometry": {"coordinates":[-80.00685199999999,40.44999],"type":"Point"}
}