{
  "type": "Feature",
  "properties": {
    "iso:country":"US",
    "sg:address":"2203 E Harrisburg Pike",
    "sg:city":"Middletown",
    "sg:classifiers":[
        {
            "category":"Arts & Performance",
            "subcategory":"Theater",
            "type":"Entertainment"
        }
    ],
    "sg:phone":"+1   ",
    "sg:postcode":"17057",
    "sg:province":"PA",
    "sg:tags":[
        "theatrical"
    ],
    "wof:name":"Formula 101",
    "wof:placetype":"venue"
},
  "geometry": {"coordinates":[-76.693592,40.19478],"type":"Point"}
}