{
  "type": "Feature",
  "properties": {
    "addr:full":"1103 Park Ave Meadville PA 16335",
    "addr:housenumber":"1103",
    "addr:postcode":"16335",
    "addr:street":"Park Ave",
    "iso:country":"US",
    "sg:address":"1103 Park Ave",
    "sg:city":"Meadville",
    "sg:classifiers":[
        {
            "category":"Real Estate",
            "subcategory":"Real Estate Agent",
            "type":"Services"
        }
    ],
    "sg:phone":"+1 814 724 1100",
    "sg:postcode":"16335",
    "sg:province":"PA",
    "wof:name":"Bainbridge Kaufman Real Estate",
    "wof:placetype":"venue"
},
  "geometry": {"coordinates":[-80.15431599999999,41.633407],"type":"Point"}
}