{
  "type": "Feature",
  "properties": {
    "iso:country":"US",
    "sg:address":"8436 Germantown Ave",
    "sg:city":"Philadelphia",
    "sg:classifiers":[
        {
            "category":"Shopping",
            "subcategory":"Clothing, Apparel, & Fashions",
            "type":"Retail Goods"
        }
    ],
    "sg:phone":"+1 215 753 1118",
    "sg:postcode":"19118",
    "sg:province":"PA",
    "sg:tags":[
        "accessory"
    ],
    "wof:name":"Stylos Fashion Accessories",
    "wof:placetype":"venue"
},
  "geometry": {"coordinates":[-75.20603699999999,40.075625],"type":"Point"}
}