{
  "type": "Feature",
  "properties": {
    "iso:country":"US",
    "sg:address":"52 High St",
    "sg:city":"Montrose",
    "sg:classifiers":[
        {
            "category":"Shopping",
            "subcategory":"Computers & Home Electronics",
            "type":"Retail Goods"
        }
    ],
    "sg:phone":"+1   ",
    "sg:postcode":"18801",
    "sg:province":"PA",
    "sg:tags":[
        "mail",
        "house"
    ],
    "wof:name":"Elegant Treasure",
    "wof:placetype":"venue"
},
  "geometry": {"coordinates":[-75.871058,41.835769],"type":"Point"}
}