{
  "type": "Feature",
  "properties": {
    "addr:full":"253 W Beaver St York PA 17406",
    "addr:housenumber":"253",
    "addr:postcode":"17406",
    "addr:street":"W Beaver St",
    "iso:country":"US",
    "sg:address":"253 W Beaver St",
    "sg:city":"York",
    "sg:classifiers":[
        {
            "category":"Building & Trades",
            "subcategory":"Equipment Rental",
            "type":"Services"
        }
    ],
    "sg:phone":"+1   ",
    "sg:postcode":"17406",
    "sg:province":"PA",
    "wof:name":"A & H Leasing Co",
    "wof:placetype":"venue"
},
  "geometry": {"coordinates":[-76.609117,40.002646],"type":"Point"}
}