{
  "type": "Feature",
  "properties": {
    "iso:country":"US",
    "sg:address":"670 Cherry Dr",
    "sg:city":"Hershey",
    "sg:classifiers":[
        {
            "category":"Health Services",
            "subcategory":"Doctor",
            "type":"Services"
        }
    ],
    "sg:phone":"+1 717 531 3503",
    "sg:postcode":"17033",
    "sg:province":"PA",
    "wof:name":"Women's Health Center-Penn State Hershey Medcl Ctr",
    "wof:placetype":"venue"
},
  "geometry": {"coordinates":[-76.659103,40.272301],"type":"Point"}
}