{
  "type": "Feature",
  "properties": {
    "iso:country":"US",
    "sg:address":"4134 Birney Ave",
    "sg:city":"Moosic",
    "sg:classifiers":[
        {
            "category":"Restaurant",
            "type":"Food & Drink"
        }
    ],
    "sg:phone":"+1 570 457 5200",
    "sg:postcode":"18507",
    "sg:province":"PA",
    "wof:name":"A V Rest",
    "wof:placetype":"venue"
},
  "geometry": {"coordinates":[-75.71302900000001,41.368983],"type":"Point"}
}