{
  "type": "Feature",
  "properties": {
    "iso:country":"US",
    "sg:address":"210 W Gordon St",
    "sg:city":"Allentown",
    "sg:classifiers":[
        {
            "category":"Retail",
            "subcategory":"Auto Repair",
            "type":"Services"
        }
    ],
    "sg:phone":"+1 610 435 1782",
    "sg:postcode":"18102",
    "sg:province":"PA",
    "sg:tags":[
        "repairing",
        "automobile"
    ],
    "wof:name":"L & M Automotive Specialists",
    "wof:placetype":"venue"
},
  "geometry": {"coordinates":[-75.462997,40.611],"type":"Point"}
}