{
  "type": "Feature",
  "properties": {
    "iso:country":"US",
    "sg:address":"356 Smith Rd",
    "sg:city":"Woodbury",
    "sg:classifiers":[
        {
            "category":"Farming",
            "subcategory":"Dairy Farm",
            "type":"Manufacturing & Wholesale Goods"
        }
    ],
    "sg:phone":"+1   ",
    "sg:postcode":"16695",
    "sg:province":"PA",
    "wof:name":"Peter M Yorke",
    "wof:placetype":"venue"
},
  "geometry": {"coordinates":[-78.365813,40.203378],"type":"Point"}
}