{
  "type": "Feature",
  "properties": {
    "iso:country":"US",
    "sg:address":"1730 W Carson St",
    "sg:city":"Pittsburgh",
    "sg:classifiers":[
        {
            "category":"Wholesale",
            "subcategory":"Auto Parts",
            "type":"Manufacturing & Wholesale Goods"
        }
    ],
    "sg:phone":"+1 412 261 6477",
    "sg:postcode":"15219",
    "sg:province":"PA",
    "sg:tags":[
        "automobile",
        "rebuilt"
    ],
    "wof:name":"Battaglia Auto Recycling",
    "wof:placetype":"venue"
},
  "geometry": {"coordinates":[-80.018705,40.440611],"type":"Point"}
}