{
  "type": "Feature",
  "properties": {
    "addr:full":"2701 Miles Ave Pittsburgh PA 15216",
    "addr:housenumber":"2701",
    "addr:postcode":"15216",
    "addr:street":"Miles Ave",
    "iso:country":"US",
    "sg:address":"2701 Miles Ave",
    "sg:city":"Pittsburgh",
    "sg:classifiers":[
        {
            "category":"Manufacturing",
            "subcategory":"Paper Products",
            "type":"Manufacturing & Wholesale Goods"
        }
    ],
    "sg:phone":"+1   ",
    "sg:postcode":"15216",
    "sg:province":"PA",
    "sg:tags":[
        "refuse",
        "converted",
        "s",
        "business",
        "mfg"
    ],
    "wof:name":"Paper Exchange Inc",
    "wof:placetype":"venue"
},
  "geometry": {"coordinates":[-80.03180399999999,40.397113],"type":"Point"}
}