{
  "type": "Feature",
  "properties": {
    "iso:country":"US",
    "sg:address":"1551 Riverside Dr",
    "sg:city":"Williamsport",
    "sg:classifiers":[
        {
            "category":"Manufacturing",
            "subcategory":"Glass & Minerals",
            "type":"Manufacturing & Wholesale Goods"
        }
    ],
    "sg:phone":"+1   ",
    "sg:postcode":"17702",
    "sg:province":"PA",
    "sg:tags":[
        "product",
        "nonmetallic",
        "mfg"
    ],
    "wof:name":"Campion Ceramics",
    "wof:placetype":"venue"
},
  "geometry": {"coordinates":[-77.015378,41.226734],"type":"Point"}
}