{
  "type": "Feature",
  "properties": {
    "iso:country":"US",
    "sg:address":"1701 E Carson St",
    "sg:city":"Pittsburgh",
    "sg:classifiers":[
        {
            "category":"Restaurant",
            "type":"Food & Drink"
        }
    ],
    "sg:menulink":"http://www.allmenus.com/pa/pittsburgh/274688-taco-loco/menu/",
    "sg:phone":"+1 412 481 6325",
    "sg:postcode":"15203",
    "sg:province":"PA",
    "sg:tags":[
        "mexican"
    ],
    "wof:name":"Taco Loco",
    "wof:placetype":"venue"
},
  "geometry": {"coordinates":[-79.981965,40.428918],"type":"Point"}
}