{
  "type": "Feature",
  "properties": {
    "addr:full":"3544 W Chester Pike Newtown Square PA 19073",
    "addr:housenumber":"3544",
    "addr:postcode":"19073",
    "addr:street":"W Chester Pike",
    "iso:country":"US",
    "sg:address":"3544 W Chester Pike",
    "sg:city":"Newtown Square",
    "sg:classifiers":[
        {
            "category":"Organizations",
            "subcategory":"Membership Organization",
            "type":"Services"
        }
    ],
    "sg:phone":"+1 610 325 8212",
    "sg:postcode":"19073",
    "sg:province":"PA",
    "wof:name":"Mothers Against Drunk Driving",
    "wof:placetype":"venue"
},
  "geometry": {"coordinates":[-75.395644,39.985649],"type":"Point"}
}