{
  "type": "Feature",
  "properties": {
    "iso:country":"US",
    "sg:address":"8236 State Rte 14",
    "sg:city":"Trout Run",
    "sg:classifiers":[
        {
            "category":"Food & Beverages",
            "subcategory":"Groceries & Convenience Stores",
            "type":"Retail Goods"
        },
        {
            "category":"Food & Beverages",
            "subcategory":"Meat & Fish",
            "type":"Retail Goods"
        }
    ],
    "sg:phone":"+1 570 995 5541",
    "sg:postcode":"17771",
    "sg:province":"PA",
    "sg:tags":[
        "station",
        "gasoline"
    ],
    "wof:name":"Marsh Hill Meat Market",
    "wof:placetype":"venue"
},
  "geometry": {"coordinates":[-76.980637,41.475699],"type":"Point"}
}