{
  "type": "Feature",
  "properties": {
    "iso:country":"US",
    "sg:address":"100 3rd St",
    "sg:city":"Dravosburg",
    "sg:classifiers":[
        {
            "category":"Real Estate",
            "subcategory":"Real Estate Operator",
            "type":"Services"
        }
    ],
    "sg:phone":"+1 412 469 3011",
    "sg:postcode":"15034",
    "sg:province":"PA",
    "sg:tags":[
        "apartment"
    ],
    "wof:name":"Dravosburg Apartments",
    "wof:placetype":"venue"
},
  "geometry": {"coordinates":[-79.89143799999999,40.349564],"type":"Point"}
}