{
  "type": "Feature",
  "properties": {
    "iso:country":"US",
    "sg:address":"7728 Tabor Ave",
    "sg:city":"Philadelphia",
    "sg:classifiers":[
        {
            "category":"Professional",
            "subcategory":"Accounting & Tax Preparation",
            "type":"Services"
        }
    ],
    "sg:phone":"+1 215 742 3266",
    "sg:postcode":"19111",
    "sg:province":"PA",
    "sg:tags":[
        "accountant"
    ],
    "wof:name":"Thomas P Kirwin CPA",
    "wof:placetype":"venue"
},
  "geometry": {"coordinates":[-75.07574,40.06463],"type":"Point"}
}