{
  "type": "Feature",
  "properties": {
    "iso:country":"US",
    "sg:address":"121 Parnell St",
    "sg:city":"Pittston",
    "sg:classifiers":[
        {
            "category":"Building & Trades",
            "subcategory":"Construction",
            "type":"Services"
        }
    ],
    "sg:phone":"+1   ",
    "sg:postcode":"18640",
    "sg:province":"PA",
    "sg:tags":[
        "contractor"
    ],
    "wof:name":"Al Dunn Masonry",
    "wof:placetype":"venue"
},
  "geometry": {"coordinates":[-75.786044,41.31028],"type":"Point"}
}