{
  "type": "Feature",
  "properties": {
    "iso:country":"US",
    "sg:address":"100 Leaders Heights Rd",
    "sg:city":"York",
    "sg:classifiers":[
        {
            "category":"Professional",
            "type":"Services"
        }
    ],
    "sg:phone":"+1 717 747 0405",
    "sg:postcode":"17403",
    "sg:province":"PA",
    "sg:tags":[
        "establishment"
    ],
    "wof:name":"Kahn Howard M CPA & Assoc",
    "wof:placetype":"venue"
},
  "geometry": {"coordinates":[-76.70662,39.90979],"type":"Point"}
}