{
  "type": "Feature",
  "properties": {
    "iso:country":"US",
    "sg:address":"1233 Locust St",
    "sg:city":"Philadelphia",
    "sg:classifiers":[
        {
            "category":"Health Services",
            "subcategory":"Doctor",
            "type":"Services"
        }
    ],
    "sg:phone":"+1 215 545 8188",
    "sg:postcode":"19107",
    "sg:province":"PA",
    "wof:name":"Cronley Shea A MD",
    "wof:placetype":"venue"
},
  "geometry": {"coordinates":[-75.161697,39.947899],"type":"Point"}
}