{
  "type": "Feature",
  "properties": {
    "iso:country":"US",
    "sg:address":"2209 Gilham Rd",
    "sg:city":"Broomall",
    "sg:classifiers":[
        {
            "category":"Personal",
            "subcategory":"Beauty Salon",
            "type":"Services"
        }
    ],
    "sg:phone":"+1 610 353 8806",
    "sg:postcode":"19008",
    "sg:province":"PA",
    "wof:name":"Soleil De Salon Inc",
    "wof:placetype":"venue"
},
  "geometry": {"coordinates":[-75.352656,39.976739],"type":"Point"}
}