{
  "type": "Feature",
  "properties": {
    "addr:full":"618 Gregg Ave Reading PA 19611",
    "addr:housenumber":"618",
    "addr:postcode":"19611",
    "addr:street":"Gregg Ave",
    "iso:country":"US",
    "sg:address":"618 Gregg Ave",
    "sg:city":"Reading",
    "sg:classifiers":[
        {
            "category":"Freight",
            "type":"Transportation"
        }
    ],
    "sg:phone":"+1 610 372 4395",
    "sg:postcode":"19611",
    "sg:province":"PA",
    "sg:tags":[
        "warehouse",
        "self",
        "storage"
    ],
    "wof:name":"A W Golden Warehouse",
    "wof:placetype":"venue"
},
  "geometry": {"coordinates":[-75.93883,40.318624],"type":"Point"}
}