{
  "type": "Feature",
  "properties": {
    "iso:country":"US",
    "sg:address":"106 Lincoln Way W",
    "sg:city":"Mc Connellsburg",
    "sg:classifiers":[
        {
            "category":"Food & Beverages",
            "subcategory":"Liquor & Beverages",
            "type":"Retail Goods"
        }
    ],
    "sg:phone":"+1 717 485 3035",
    "sg:postcode":"17233",
    "sg:province":"PA",
    "wof:name":"Wine & Spirits",
    "wof:placetype":"venue"
},
  "geometry": {"coordinates":[-77.999698,39.932851],"type":"Point"}
}