{
  "type": "Feature",
  "properties": {
    "addr:full":"106 Lincoln Way W Mc Connellsburg PA 17233",
    "addr:housenumber":"106",
    "addr:postcode":"17233",
    "addr:street":"Lincoln Way W Mc Connellsburg",
    "iso:country":"US",
    "sg:address":"106 Lincoln Way W",
    "sg:city":"Mc Connellsburg",
    "sg:classifiers":[
        {
            "category":"Food & Beverages",
            "subcategory":"Liquor & Beverages",
            "type":"Retail Goods"
        }
    ],
    "sg:phone":"+1 717 485 3035",
    "sg:postcode":"17233",
    "sg:province":"PA",
    "wof:name":"Wine & Spirits",
    "wof:placetype":"venue"
},
  "geometry": {"coordinates":[-77.999698,39.932851],"type":"Point"}
}