{
  "type": "Feature",
  "properties": {
    "addr:full":"133 E Swedesford Rd Exton PA 19341",
    "addr:housenumber":"133",
    "addr:postcode":"19341",
    "addr:street":"E Swedesford Rd",
    "iso:country":"US",
    "sg:address":"133 E Swedesford Rd",
    "sg:city":"Exton",
    "sg:classifiers":[
        {
            "category":"Shopping",
            "subcategory":"Pharmacy",
            "type":"Retail Goods"
        }
    ],
    "sg:phone":"+1   ",
    "sg:postcode":"19341",
    "sg:province":"PA",
    "wof:name":"JC Penney Corporation Inc",
    "wof:placetype":"venue"
},
  "geometry": {"coordinates":[-75.630467,40.03305],"type":"Point"}
}