{
  "type": "Feature",
  "properties": {
    "addr:full":"301 Manor Rd Manor PA 15626",
    "addr:housenumber":"301",
    "addr:postcode":"15626",
    "addr:street":"Manor Rd",
    "iso:country":"US",
    "sg:address":"301 Manor Rd",
    "sg:city":"Manor",
    "sg:classifiers":[
        {
            "category":"Building & Trades",
            "subcategory":"Construction",
            "type":"Services"
        }
    ],
    "sg:phone":"+1   ",
    "sg:postcode":"15626",
    "sg:province":"PA",
    "sg:tags":[
        "hanging",
        "contractor"
    ],
    "wof:name":"GSM Painting Inc",
    "wof:placetype":"venue"
},
  "geometry": {"coordinates":[-79.581225,40.406731],"type":"Point"}
}