{
  "type": "Feature",
  "properties": {
    "iso:country":"US",
    "sg:address":"5187 Lincoln Hwy W",
    "sg:city":"Thomasville",
    "sg:classifiers":[
        {
            "category":"Government",
            "subcategory":"Fire Station",
            "type":"Public Place"
        }
    ],
    "sg:phone":"+1 717 792 1424",
    "sg:postcode":"17364",
    "sg:province":"PA",
    "sg:tags":[
        "consultant",
        "protection"
    ],
    "wof:name":"Lincoln Fire Deptartment 1 Inc",
    "wof:placetype":"venue"
},
  "geometry": {"coordinates":[-76.848778,39.928841],"type":"Point"}
}