{
  "type": "Feature",
  "properties": {
    "addr:full":"4831 W Chester Pike Newtown Square PA 19073",
    "addr:housenumber":"4831",
    "addr:postcode":"19073",
    "addr:street":"W Chester Pike",
    "iso:country":"US",
    "sg:address":"4831 W Chester Pike",
    "sg:city":"Newtown Square",
    "sg:classifiers":[
        {
            "category":"Shopping",
            "type":"Retail Goods"
        }
    ],
    "sg:phone":"+1 610 353 1186",
    "sg:postcode":"19073",
    "sg:province":"PA",
    "sg:tags":[
        "art",
        "gallery",
        "dealer"
    ],
    "wof:name":"Great Frame Up",
    "wof:placetype":"venue"
},
  "geometry": {"coordinates":[-75.44006899999999,39.975263],"type":"Point"}
}