{
  "type": "Feature",
  "properties": {
    "iso:country":"US",
    "sg:address":"2885 Oneida Valley Rd",
    "sg:city":"Parker",
    "sg:classifiers":[
        {
            "category":"Retail",
            "subcategory":"Repair Shop",
            "type":"Services"
        }
    ],
    "sg:phone":"+1 724 791 1175",
    "sg:postcode":"16049",
    "sg:province":"PA",
    "sg:tags":[
        "refinishing",
        "furniture"
    ],
    "wof:name":"Thompson Refinishing",
    "wof:placetype":"venue"
},
  "geometry": {"coordinates":[-79.78606499999999,41.1014],"type":"Point"}
}