{
  "type": "Feature",
  "properties": {
    "iso:country":"US",
    "sg:address":"5001 Penn Ave",
    "sg:city":"Pittsburgh",
    "sg:classifiers":[
        {
            "category":"Food & Beverages",
            "subcategory":"Groceries & Convenience Stores",
            "type":"Retail Goods"
        }
    ],
    "sg:phone":"+1   ",
    "sg:postcode":"15224",
    "sg:province":"PA",
    "wof:name":"Le Thanh",
    "wof:placetype":"venue"
},
  "geometry": {"coordinates":[-79.942858,40.464968],"type":"Point"}
}