{
  "type": "Feature",
  "properties": {
    "iso:country":"US",
    "sg:address":"2110 Bloom Rd",
    "sg:city":"Danville",
    "sg:classifiers":[
        {
            "category":"Restaurant",
            "type":"Food & Drink"
        }
    ],
    "sg:phone":"+1   ",
    "sg:postcode":"17821",
    "sg:province":"PA",
    "sg:tags":[
        "eating"
    ],
    "wof:name":"Cilantros",
    "wof:placetype":"venue"
},
  "geometry": {"coordinates":[-76.57424399999999,40.967633],"type":"Point"}
}