{
  "type": "Feature",
  "properties": {
    "addr:full":"550 Kimberton Rd  Phoenixville PA 19460",
    "addr:housenumber":"550",
    "addr:postcode":"19460",
    "addr:street":"Kimberton Rd",
    "iso:country":"US",
    "sg:address":"550 Kimberton Rd ",
    "sg:city":"Phoenixville",
    "sg:classifiers":[
        {
            "category":"Restaurant",
            "type":"Food & Drink"
        }
    ],
    "sg:menulink":"http://www.allmenus.com/pa/east-pikeland/289312-bravo-pizza/menu/",
    "sg:phone":"+1 610 935 2744",
    "sg:postcode":"19460",
    "sg:province":"PA",
    "sg:tags":[
        "american",
        "pizza"
    ],
    "wof:name":"Bravo Pizza",
    "wof:placetype":"venue"
},
  "geometry": {"coordinates":[-75.549147,40.129897],"type":"Point"}
}