{
  "type": "Feature",
  "properties": {
    "iso:country":"US",
    "sg:address":"858 W Welsh Rd",
    "sg:city":"Ambler",
    "sg:classifiers":[
        {
            "category":"Health Services",
            "subcategory":"Doctor",
            "type":"Services"
        }
    ],
    "sg:phone":"+1 215 643 3755",
    "sg:postcode":"19002",
    "sg:province":"PA",
    "sg:tags":[
        "dentist"
    ],
    "wof:name":"George E Federici DDS",
    "wof:placetype":"venue"
},
  "geometry": {"coordinates":[-75.211477,40.197934],"type":"Point"}
}