{
  "type": "Feature",
  "properties": {
    "iso:country":"US",
    "sg:address":"1860 Weavertown Rd",
    "sg:city":"Douglassville",
    "sg:classifiers":[
        {
            "category":"Shopping",
            "subcategory":"Used Merchandise",
            "type":"Retail Goods"
        }
    ],
    "sg:phone":"+1 610 689 9541",
    "sg:postcode":"19518",
    "sg:province":"PA",
    "sg:tags":[
        "antique"
    ],
    "wof:name":"Merritt's Antiques Inc",
    "wof:placetype":"venue"
},
  "geometry": {"coordinates":[-75.738198,40.299524],"type":"Point"}
}