{
  "type": "Feature",
  "properties": {
    "iso:country":"US",
    "sg:address":"100 E Lehigh Ave",
    "sg:city":"Philadelphia",
    "sg:classifiers":[
        {
            "category":"Health Services",
            "subcategory":"Hospital",
            "type":"Services"
        }
    ],
    "sg:phone":"+1 215 204 5919",
    "sg:postcode":"19125",
    "sg:province":"PA",
    "wof:name":"Episcopal Campus Temple University Hospital",
    "wof:placetype":"venue"
},
  "geometry": {"coordinates":[-75.130898,39.990898],"type":"Point"}
}