{
  "type": "Feature",
  "properties": {
    "iso:country":"US",
    "sg:address":"2537 Great Cove Rd",
    "sg:city":"Warfordsburg",
    "sg:classifiers":[
        {
            "category":"Shopping",
            "subcategory":"Used Merchandise",
            "type":"Retail Goods"
        }
    ],
    "sg:phone":"+1 717 294 6505",
    "sg:postcode":"17267",
    "sg:province":"PA",
    "sg:tags":[
        "antique"
    ],
    "wof:name":"Ancient Times",
    "wof:placetype":"venue"
},
  "geometry": {"coordinates":[-78.19841,39.788139],"type":"Point"}
}