{
  "type": "Feature",
  "properties": {
    "iso:country":"US",
    "sg:address":"6910 McCallum St",
    "sg:city":"Philadelphia",
    "sg:classifiers":[
        {
            "category":"Professional",
            "subcategory":"Management & Consulting",
            "type":"Services"
        }
    ],
    "sg:phone":"+1 215 849 7555",
    "sg:postcode":"19119",
    "sg:province":"PA",
    "sg:tags":[
        "international",
        "consultant"
    ],
    "wof:name":"Jamanick Enterprises Inc",
    "wof:placetype":"venue"
},
  "geometry": {"coordinates":[-75.19548899999999,40.048436],"type":"Point"}
}