{
  "type": "Feature",
  "properties": {
    "iso:country":"US",
    "sg:address":"5450 Wissahickon Ave",
    "sg:city":"Philadelphia",
    "sg:classifiers":[
        {
            "category":"Bakery",
            "type":"Food & Drink"
        }
    ],
    "sg:phone":"+1 215 232 5248",
    "sg:postcode":"19144",
    "sg:province":"PA",
    "wof:name":"Panaderia La Espiga",
    "wof:placetype":"venue"
},
  "geometry": {"coordinates":[-75.180584,40.024704],"type":"Point"}
}