{
  "type": "Feature",
  "properties": {
    "iso:country":"US",
    "sg:address":"125 Station Square Dr",
    "sg:city":"Pittsburgh",
    "sg:classifiers":[
        {
            "category":"Bars & Pubs",
            "subcategory":"Lounge",
            "type":"Food & Drink"
        }
    ],
    "sg:phone":"+1 412 203 3700",
    "sg:postcode":"15219",
    "sg:province":"PA",
    "wof:name":"5ive Lounge",
    "wof:placetype":"venue"
},
  "geometry": {"coordinates":[-80.004356,40.433194],"type":"Point"}
}