{
  "type": "Feature",
  "properties": {
    "iso:country":"US",
    "sg:address":"801 Sansom St",
    "sg:city":"Philadelphia",
    "sg:classifiers":[
        {
            "category":"Shopping",
            "subcategory":"Jewelry",
            "type":"Retail Goods"
        }
    ],
    "sg:phone":"+1 215 923 7714",
    "sg:postcode":"19107",
    "sg:province":"PA",
    "wof:name":"Marquise Jewelers",
    "wof:placetype":"venue"
},
  "geometry": {"coordinates":[-75.154404,39.948799],"type":"Point"}
}