{
  "type": "Feature",
  "properties": {
    "addr:full":"3560 Beck Rd Butler PA 16002",
    "addr:housenumber":"3560",
    "addr:postcode":"16002",
    "addr:street":"Beck Rd",
    "iso:country":"US",
    "sg:address":"3560 Beck Rd",
    "sg:city":"Butler",
    "sg:classifiers":[
        {
            "category":"Manufacturing",
            "subcategory":"Tools & Machinery",
            "type":"Manufacturing & Wholesale Goods"
        }
    ],
    "sg:phone":"+1   ",
    "sg:postcode":"16002",
    "sg:province":"PA",
    "sg:tags":[
        "equipment",
        "microscope",
        "regulating",
        "temperature",
        "mfg"
    ],
    "wof:name":"Bioptechs Inc",
    "wof:placetype":"venue"
},
  "geometry": {"coordinates":[-79.807481,40.849916],"type":"Point"}
}