{
  "type": "Feature",
  "properties": {
    "iso:country":"US",
    "sg:address":"426 S 3rd St",
    "sg:city":"Lemoyne",
    "sg:classifiers":[
        {
            "category":"Professional",
            "subcategory":"Business Services",
            "type":"Services"
        }
    ],
    "sg:phone":"+1   ",
    "sg:postcode":"17043",
    "sg:province":"PA",
    "wof:name":"Kurt M Oravecz Architect",
    "wof:placetype":"venue"
},
  "geometry": {"coordinates":[-76.88768399999999,40.241295],"type":"Point"}
}