{
  "type": "Feature",
  "properties": {
    "iso:country":"US",
    "sg:address":"300 N Centre St",
    "sg:city":"Pottsville",
    "sg:classifiers":[
        {
            "category":"Shopping",
            "subcategory":"Florist",
            "type":"Retail Goods"
        }
    ],
    "sg:phone":"+1   ",
    "sg:postcode":"17901",
    "sg:province":"PA",
    "wof:name":"R J Miske Florists Inc",
    "wof:placetype":"venue"
},
  "geometry": {"coordinates":[-76.19659299999999,40.68696],"type":"Point"}
}