{
  "type": "Feature",
  "properties": {
    "iso:country":"US",
    "sg:address":"6608 Jackson St",
    "sg:city":"Philadelphia",
    "sg:classifiers":[
        {
            "category":"Building & Trades",
            "subcategory":"Construction",
            "type":"Services"
        }
    ],
    "sg:phone":"+1   ",
    "sg:postcode":"19135",
    "sg:province":"PA",
    "sg:tags":[
        "contractor"
    ],
    "wof:name":"Alex Kolosenko",
    "wof:placetype":"venue"
},
  "geometry": {"coordinates":[-75.048536,40.026308],"type":"Point"}
}