{
  "type": "Feature",
  "properties": {
    "addr:full":"2131 N American St Philadelphia PA 19122",
    "addr:housenumber":"2131",
    "addr:postcode":"19122",
    "addr:street":"N American St",
    "iso:country":"US",
    "sg:address":"2131 N American St",
    "sg:city":"Philadelphia",
    "sg:classifiers":[
        {
            "category":"Freight",
            "type":"Transportation"
        }
    ],
    "sg:phone":"+1 215 426 9661",
    "sg:postcode":"19122",
    "sg:province":"PA",
    "sg:tags":[
        "mail",
        "order"
    ],
    "sg:website":"www.edisonrecordings.com",
    "wof:name":"Very Inc",
    "wof:placetype":"venue"
},
  "geometry": {"coordinates":[-75.137804,39.983406],"type":"Point"}
}