{
  "type": "Feature",
  "properties": {
    "addr:full":"1302 Race St Philadelphia PA 19107",
    "addr:housenumber":"1302",
    "addr:postcode":"19107",
    "addr:street":"Race St",
    "iso:country":"US",
    "sg:address":"1302 Race St",
    "sg:city":"Philadelphia",
    "sg:classifiers":[
        {
            "category":"Organizations",
            "subcategory":"Labor Organization",
            "type":"Services"
        }
    ],
    "sg:phone":"+1 215 568 3001",
    "sg:postcode":"19107",
    "sg:province":"PA",
    "wof:name":"LECET",
    "wof:placetype":"venue"
},
  "geometry": {"coordinates":[-75.16108699999999,39.955951],"type":"Point"}
}