{
  "type": "Feature",
  "properties": {
    "addr:full":"2300 Computer Ave Willow Grove PA 19090",
    "addr:postcode":"19090",
    "addr:street":"Ave",
    "iso:country":"US",
    "sg:address":"2300 Computer Ave",
    "sg:city":"Willow Grove",
    "sg:classifiers":[
        {
            "category":"Professional",
            "subcategory":"Computer Services",
            "type":"Services"
        }
    ],
    "sg:phone":"+1 215 659 7664",
    "sg:postcode":"19090",
    "sg:province":"PA",
    "sg:tags":[
        "consultant",
        "designer"
    ],
    "wof:name":"Internet Data Technologies",
    "wof:placetype":"venue"
},
  "geometry": {"coordinates":[-75.136898,40.155933],"type":"Point"}
}