{
  "type": "Feature",
  "properties": {
    "iso:country":"US",
    "sg:address":"168 Kramer Rd",
    "sg:city":"Aaronsburg",
    "sg:classifiers":[
        {
            "category":"Manufacturing",
            "subcategory":"Metals",
            "type":"Manufacturing & Wholesale Goods"
        }
    ],
    "sg:phone":"+1   ",
    "sg:postcode":"16820",
    "sg:province":"PA",
    "sg:tags":[
        "steel",
        "stainless",
        "fabricated",
        "aluminum",
        "mfg"
    ],
    "wof:name":"Poormans Welding",
    "wof:placetype":"venue"
},
  "geometry": {"coordinates":[-77.428408,40.904653],"type":"Point"}
}