{
  "type": "Feature",
  "properties": {
    "iso:country":"US",
    "sg:address":"1200 Vilsmeier Rd",
    "sg:city":"Lansdale",
    "sg:classifiers":[
        {
            "category":"Professional",
            "subcategory":"Management & Consulting",
            "type":"Services"
        }
    ],
    "sg:phone":"+1   ",
    "sg:postcode":"19446",
    "sg:province":"PA",
    "wof:name":"AZ Marketing Solutions In",
    "wof:placetype":"venue"
},
  "geometry": {"coordinates":[-75.24717699999999,40.245373],"type":"Point"}
}