{
  "type": "Feature",
  "properties": {
    "addr:full":"8400 Old Rte 30 Irwin PA 15642",
    "addr:housenumber":"8400",
    "addr:postcode":"15642",
    "addr:street":"Old Rte 30",
    "iso:country":"US",
    "sg:address":"8400 Old Rte 30",
    "sg:city":"Irwin",
    "sg:classifiers":[
        {
            "category":"Building & Trades",
            "subcategory":"Plumbing",
            "type":"Services"
        },
        {
            "category":"Home & Garden",
            "subcategory":"Garden Supply",
            "type":"Retail Goods"
        }
    ],
    "sg:phone":"+1 724 864 9012",
    "sg:postcode":"15642",
    "sg:province":"PA",
    "sg:tags":[
        "installs",
        "irrigation",
        "system",
        "sprinkler"
    ],
    "wof:name":"Eagle Irrigation Inc",
    "wof:placetype":"venue"
},
  "geometry": {"coordinates":[-79.68124,40.31798],"type":"Point"}
}