{
  "type": "Feature",
  "properties": {
    "iso:country":"US",
    "sg:address":"31 S 18th St ",
    "sg:city":"Philadelphia",
    "sg:classifiers":[
        {
            "category":"Cafe",
            "type":"Food & Drink"
        }
    ],
    "sg:menulink":"http://www.allmenus.com/pa/philadelphia/291771-naked-chocolate-cafe/menu/",
    "sg:phone":"+1 215 564 3860",
    "sg:postcode":"19103",
    "sg:province":"PA",
    "sg:tags":[
        "soup",
        "salad"
    ],
    "wof:name":"Naked Chocolate Cafe",
    "wof:placetype":"venue"
},
  "geometry": {"coordinates":[-75.170096,39.952297],"type":"Point"}
}