{
  "type": "Feature",
  "properties": {
    "addr:full":"1682 Freysville Rd York PA 17406",
    "addr:housenumber":"1682",
    "addr:postcode":"17406",
    "addr:street":"Freysville Rd",
    "iso:country":"US",
    "sg:address":"1682 Freysville Rd",
    "sg:city":"York",
    "sg:classifiers":[
        {
            "category":"Building & Trades",
            "subcategory":"Landscaping Services",
            "type":"Services"
        }
    ],
    "sg:phone":"+1   ",
    "sg:postcode":"17406",
    "sg:province":"PA",
    "sg:tags":[
        "excavation",
        "lawn",
        "garden",
        "contractor"
    ],
    "wof:name":"Bupps Excavating & Ldscp Co",
    "wof:placetype":"venue"
},
  "geometry": {"coordinates":[-76.609939,39.958534],"type":"Point"}
}