{
  "type": "Feature",
  "properties": {
    "iso:country":"US",
    "sg:address":"194 Middle Rd",
    "sg:city":"Catawissa",
    "sg:classifiers":[
        {
            "category":"Building & Trades",
            "subcategory":"Cleaning & Sanitation",
            "type":"Services"
        }
    ],
    "sg:phone":"+1 570 799 5774",
    "sg:postcode":"17820",
    "sg:province":"PA",
    "sg:tags":[
        "janitor"
    ],
    "wof:name":"3 B Floor Care & Housekeeping",
    "wof:placetype":"venue"
},
  "geometry": {"coordinates":[-76.420177,40.871458],"type":"Point"}
}