{
  "type": "Feature",
  "properties": {
    "iso:country":"US",
    "sg:address":"3370 Rothsville Rd",
    "sg:city":"Akron",
    "sg:classifiers":[
        {
            "category":"Government",
            "subcategory":"Office",
            "type":"Public Place"
        }
    ],
    "sg:phone":"+1 717 721 6145",
    "sg:postcode":"17501",
    "sg:province":"PA",
    "sg:tags":[
        "armed",
        "national",
        "force",
        "security",
        "recruiting"
    ],
    "wof:name":"US Army Recruiting Station",
    "wof:placetype":"venue"
},
  "geometry": {"coordinates":[-76.209265,40.165332],"type":"Point"}
}