{
  "type": "Feature",
  "properties": {
    "addr:full":"215 Hickory St Scranton PA 18505",
    "addr:housenumber":"215",
    "addr:postcode":"18505",
    "addr:street":"Hickory St",
    "iso:country":"US",
    "sg:address":"215 Hickory St",
    "sg:city":"Scranton",
    "sg:classifiers":[
        {
            "category":"Manufacturing",
            "subcategory":"Aerospace",
            "type":"Manufacturing & Wholesale Goods"
        }
    ],
    "sg:phone":"+1 570 342 1766",
    "sg:postcode":"18505",
    "sg:province":"PA",
    "sg:tags":[
        "aircraft",
        "parts",
        "mfg"
    ],
    "wof:name":"Colombo Manufacturing",
    "wof:placetype":"venue"
},
  "geometry": {"coordinates":[-75.667525,41.402292],"type":"Point"}
}