{
  "type": "Feature",
  "properties": {
    "addr:full":"1364 Foster Rd Warminster PA 18974",
    "addr:housenumber":"1364",
    "addr:postcode":"18974",
    "addr:street":"Foster Rd",
    "iso:country":"US",
    "sg:address":"1364 Foster Rd",
    "sg:city":"Warminster",
    "sg:classifiers":[
        {
            "category":"Building & Trades",
            "subcategory":"Construction",
            "type":"Services"
        }
    ],
    "sg:phone":"+1   ",
    "sg:postcode":"18974",
    "sg:province":"PA",
    "sg:tags":[
        "carpentry",
        "contractor"
    ],
    "wof:name":"John V Forscht",
    "wof:placetype":"venue"
},
  "geometry": {"coordinates":[-75.122405,40.214833],"type":"Point"}
}