{
  "type": "Feature",
  "properties": {
    "iso:country":"US",
    "sg:address":"120 E Front St",
    "sg:city":"Berwick",
    "sg:classifiers":[
        {
            "category":"Shopping",
            "subcategory":"Used Merchandise",
            "type":"Retail Goods"
        }
    ],
    "sg:phone":"+1 570 752 7714",
    "sg:postcode":"18603",
    "sg:province":"PA",
    "sg:tags":[
        "resale",
        "shop"
    ],
    "wof:name":"Vincent's Kids Junction",
    "wof:placetype":"venue"
},
  "geometry": {"coordinates":[-76.233278,41.054932],"type":"Point"}
}