{
  "type": "Feature",
  "properties": {
    "addr:full":"34 Franklin St Reading PA 19607",
    "addr:housenumber":"34",
    "addr:postcode":"19607",
    "addr:street":"Franklin St",
    "iso:country":"US",
    "sg:address":"34 Franklin St",
    "sg:city":"Reading",
    "sg:classifiers":[
        {
            "category":"Real Estate",
            "subcategory":"Real Estate Agent",
            "type":"Services"
        }
    ],
    "sg:phone":"+1   ",
    "sg:postcode":"19607",
    "sg:province":"PA",
    "wof:name":"Cleaver Real Estate Appraising",
    "wof:placetype":"venue"
},
  "geometry": {"coordinates":[-75.966256,40.301873],"type":"Point"}
}