{
  "type": "Feature",
  "properties": {
    "iso:country":"US",
    "sg:address":"13617 Broadway Dr",
    "sg:city":"Meadville",
    "sg:classifiers":[
        {
            "category":"Manufacturing",
            "subcategory":"Tools & Machinery",
            "type":"Manufacturing & Wholesale Goods"
        }
    ],
    "sg:phone":"+1 814 724 1202",
    "sg:postcode":"16335",
    "sg:province":"PA",
    "sg:tags":[
        "shop",
        "die"
    ],
    "sg:website":"www.standardprecisionmfg.com",
    "wof:name":"Standard Precision Mfg",
    "wof:placetype":"venue"
},
  "geometry": {"coordinates":[-80.171091,41.654774],"type":"Point"}
}