{
  "type": "Feature",
  "properties": {
    "iso:country":"US",
    "sg:address":"1083 N Church St",
    "sg:city":"Hazleton",
    "sg:classifiers":[
        {
            "category":"Shopping",
            "subcategory":"Gifts & Souvenirs",
            "type":"Retail Goods"
        }
    ],
    "sg:phone":"+1 570 455 6774",
    "sg:postcode":"18202",
    "sg:province":"PA",
    "sg:tags":[
        "shop"
    ],
    "wof:name":"Angelique Boutique",
    "wof:placetype":"venue"
},
  "geometry": {"coordinates":[-75.978669,40.97542],"type":"Point"}
}