{
  "type": "Feature",
  "properties": {
    "iso:country":"US",
    "sg:address":"RR 45",
    "sg:city":"Centre Hall",
    "sg:classifiers":[
        {
            "category":"Health Services",
            "subcategory":"Chiropractor",
            "type":"Services"
        }
    ],
    "sg:phone":"+1 814 364 2535",
    "sg:postcode":"16828",
    "sg:province":"PA",
    "wof:name":"Nittany Valley Chiropractic Center",
    "wof:placetype":"venue"
},
  "geometry": {"coordinates":[-77.685402,40.798901],"type":"Point"}
}