{
  "type": "Feature",
  "properties": {
    "iso:country":"US",
    "sg:address":"8170 Rabbit Ln",
    "sg:city":"Harrisburg",
    "sg:classifiers":[
        {
            "category":"Manufacturing",
            "subcategory":"Tools & Machinery",
            "type":"Manufacturing & Wholesale Goods"
        }
    ],
    "sg:phone":"+1   ",
    "sg:postcode":"17112",
    "sg:province":"PA",
    "sg:tags":[
        "industrial",
        "mfg"
    ],
    "wof:name":"C & M Machine Shop",
    "wof:placetype":"venue"
},
  "geometry": {"coordinates":[-76.70984199999999,40.370905],"type":"Point"}
}