{
  "type": "Feature",
  "properties": {
    "iso:country":"US",
    "sg:address":"2571 Municipal Rd",
    "sg:city":"Dover",
    "sg:classifiers":[
        {
            "category":"School Buses",
            "type":"Transportation"
        },
        {
            "category":"Local Transit",
            "type":"Transportation"
        }
    ],
    "sg:phone":"+1 717 292 9539",
    "sg:postcode":"17315",
    "sg:province":"PA",
    "sg:tags":[
        "line"
    ],
    "sg:website":"http://www.wolfsbus.com",
    "wof:name":"E & B Transportation",
    "wof:placetype":"venue"
},
  "geometry": {"coordinates":[-76.85521300000001,39.994096],"type":"Point"}
}