{
  "type": "Feature",
  "properties": {
    "iso:country":"US",
    "sg:address":"56 Tanglewood Ln",
    "sg:city":"Levittown",
    "sg:classifiers":[
        {
            "category":"Building & Trades",
            "subcategory":"Plumbing",
            "type":"Services"
        }
    ],
    "sg:phone":"+1 215 945 8710",
    "sg:postcode":"19054",
    "sg:province":"PA",
    "sg:tags":[
        "plumbing",
        "contractor"
    ],
    "wof:name":"Chic's Plumbing & Heating",
    "wof:placetype":"venue"
},
  "geometry": {"coordinates":[-74.829521,40.172067],"type":"Point"}
}