{
  "type": "Feature",
  "properties": {
    "addr:full":"300 Liberty Ave Pittsburgh PA 15222",
    "addr:housenumber":"300",
    "addr:postcode":"15222",
    "addr:street":"Liberty Ave",
    "iso:country":"US",
    "sg:address":"300 Liberty Ave",
    "sg:city":"Pittsburgh",
    "sg:classifiers":[
        {
            "category":"Government",
            "subcategory":"Office",
            "type":"Public Place"
        }
    ],
    "sg:phone":"+1 412 565 5395",
    "sg:postcode":"15222",
    "sg:province":"PA",
    "wof:name":"Human Relations",
    "wof:placetype":"venue"
},
  "geometry": {"coordinates":[-80.005853,40.441354],"type":"Point"}
}