{
  "type": "Feature",
  "properties": {
    "addr:full":"1155 Carlisle St Hanover PA 17331",
    "addr:housenumber":"1155",
    "addr:postcode":"17331",
    "addr:street":"Carlisle St",
    "iso:country":"US",
    "sg:address":"1155 Carlisle St",
    "sg:city":"Hanover",
    "sg:classifiers":[
        {
            "category":"Shopping",
            "type":"Retail Goods"
        }
    ],
    "sg:phone":"+1   ",
    "sg:postcode":"17331",
    "sg:province":"PA",
    "sg:tags":[
        "aids",
        "hearing"
    ],
    "wof:name":"Miracle Aid Center The",
    "wof:placetype":"venue"
},
  "geometry": {"coordinates":[-76.997248,39.822785],"type":"Point"}
}