{
  "type": "Feature",
  "properties": {
    "iso:country":"US",
    "sg:address":"127 E Main St",
    "sg:city":"Mahaffey",
    "sg:classifiers":[
        {
            "category":"Organizations",
            "subcategory":"Community Association",
            "type":"Services"
        }
    ],
    "sg:phone":"+1 814 277 6689",
    "sg:postcode":"15757",
    "sg:province":"PA",
    "sg:tags":[
        "club"
    ],
    "wof:name":"Veterans Of Foreign Wars",
    "wof:placetype":"venue"
},
  "geometry": {"coordinates":[-78.720664,40.8705],"type":"Point"}
}