{
  "type": "Feature",
  "properties": {
    "iso:country":"US",
    "sg:address":"1801 W 1st St",
    "sg:city":"Oil City",
    "sg:classifiers":[
        {
            "category":"Education",
            "subcategory":"College",
            "type":"Public Place"
        }
    ],
    "sg:phone":"+1 814 676 6591",
    "sg:postcode":"16301",
    "sg:province":"PA",
    "sg:tags":[
        "academic",
        "school"
    ],
    "wof:name":"Clarion University",
    "wof:placetype":"venue"
},
  "geometry": {"coordinates":[-79.728489,41.411065],"type":"Point"}
}