{
  "type": "Feature",
  "properties": {
    "iso:country":"US",
    "sg:address":"1011 Charles St",
    "sg:city":"Baden",
    "sg:classifiers":[
        {
            "category":"Building & Trades",
            "subcategory":"Electrical",
            "type":"Services"
        }
    ],
    "sg:phone":"+1 724 242 0204",
    "sg:postcode":"15005",
    "sg:province":"PA",
    "sg:tags":[
        "industrial",
        "electrician",
        "electric",
        "contractors-commercial"
    ],
    "wof:name":"Barr's Electric Company",
    "wof:placetype":"venue"
},
  "geometry": {"coordinates":[-80.218615,40.640971],"type":"Point"}
}