{
  "type": "Feature",
  "properties": {
    "addr:full":"3735 Saxonburg Blvd Pittsburgh PA 15238",
    "addr:housenumber":"3735",
    "addr:postcode":"15238",
    "addr:street":"Saxonburg Blvd",
    "iso:country":"US",
    "sg:address":"3735 Saxonburg Blvd",
    "sg:city":"Pittsburgh",
    "sg:classifiers":[
        {
            "category":"Professional",
            "type":"Services"
        }
    ],
    "sg:phone":"+1 412 767 5466",
    "sg:postcode":"15238",
    "sg:province":"PA",
    "sg:tags":[
        "establishment"
    ],
    "wof:name":"Why Nmd Institute",
    "wof:placetype":"venue"
},
  "geometry": {"coordinates":[-79.89212999999999,40.573855],"type":"Point"}
}