{
  "type": "Feature",
  "properties": {
    "iso:country":"US",
    "sg:address":"800 Chestnut St",
    "sg:city":"Philadelphia",
    "sg:classifiers":[
        {
            "category":"Shopping",
            "subcategory":"Jewelry",
            "type":"Retail Goods"
        }
    ],
    "sg:phone":"+1 215 925 5111",
    "sg:postcode":"19107",
    "sg:province":"PA",
    "sg:tags":[
        "diamond"
    ],
    "sg:website":"www.thediamondtree.com",
    "wof:name":"G N Diamond",
    "wof:placetype":"venue"
},
  "geometry": {"coordinates":[-75.155491,39.949808],"type":"Point"}
}