{
  "type": "Feature",
  "properties": {
    "addr:full":"307 Lenox Rd Havertown PA 19083",
    "addr:housenumber":"307",
    "addr:postcode":"19083",
    "addr:street":"Lenox Rd",
    "iso:country":"US",
    "sg:address":"307 Lenox Rd",
    "sg:city":"Havertown",
    "sg:classifiers":[
        {
            "category":"Social Services",
            "type":"Services"
        }
    ],
    "sg:phone":"+1   ",
    "sg:postcode":"19083",
    "sg:province":"PA",
    "wof:name":"Special Olympics Delaware Cnty",
    "wof:placetype":"venue"
},
  "geometry": {"coordinates":[-75.29443999999999,39.978968],"type":"Point"}
}