{
  "type": "Feature",
  "properties": {
    "iso:country":"US",
    "sg:address":"709 Woodfield Rd",
    "sg:city":"Villanova",
    "sg:classifiers":[
        {
            "category":"Health Services",
            "subcategory":"Doctor",
            "type":"Services"
        }
    ],
    "sg:phone":"+1 610 384 7711",
    "sg:postcode":"19085",
    "sg:province":"PA",
    "sg:tags":[
        "physician",
        "surgeon"
    ],
    "wof:name":"Patricia Lee MD",
    "wof:placetype":"venue"
},
  "geometry": {"coordinates":[-75.338295,40.056946],"type":"Point"}
}