{
  "type": "Feature",
  "properties": {
    "addr:full":"311 N Sumneytown Pike Ste 1E North Wales PA 19454",
    "addr:housenumber":"311",
    "addr:postcode":"19454",
    "addr:street":"N Sumneytown Pike Ste 1E",
    "iso:country":"US",
    "sg:address":"311 N Sumneytown Pike Ste 1E",
    "sg:city":"North Wales",
    "sg:classifiers":[
        {
            "category":"Health Services",
            "subcategory":"Doctor",
            "type":"Services"
        }
    ],
    "sg:phone":"+1 215 661 0300",
    "sg:postcode":"19454",
    "sg:province":"PA",
    "sg:tags":[
        "dermatologist"
    ],
    "wof:name":"East Penn Dermatology PC",
    "wof:placetype":"venue"
},
  "geometry": {"coordinates":[-75.281502,40.2117],"type":"Point"}
}