{
  "type": "Feature",
  "properties": {
    "iso:country":"US",
    "sg:address":"226 Elmore Rd",
    "sg:city":"Pittsburgh",
    "sg:classifiers":[
        {
            "category":"Professional",
            "subcategory":"Lawyer & Legal Services",
            "type":"Services"
        }
    ],
    "sg:phone":"+1 412 241 4129",
    "sg:postcode":"15221",
    "sg:province":"PA",
    "wof:name":"Michel Enterprises",
    "wof:placetype":"venue"
},
  "geometry": {"coordinates":[-79.859171,40.426703],"type":"Point"}
}