{
  "type": "Feature",
  "properties": {
    "iso:country":"US",
    "sg:address":"575 Davidson Rd",
    "sg:city":"Pittsburgh",
    "sg:classifiers":[
        {
            "category":"Wholesale",
            "subcategory":"Electrical",
            "type":"Manufacturing & Wholesale Goods"
        },
        {
            "category":"Home & Garden",
            "subcategory":"Household Appliances",
            "type":"Retail Goods"
        },
        {
            "category":"Manufacturing",
            "subcategory":"Electronics",
            "type":"Manufacturing & Wholesale Goods"
        },
        {
            "category":"Shopping",
            "subcategory":"Computers & Home Electronics",
            "type":"Retail Goods"
        }
    ],
    "sg:phone":"+1 412 793 3912",
    "sg:postcode":"15239",
    "sg:province":"PA",
    "sg:tags":[
        "major",
        "electric",
        "supply",
        "consumer",
        "appliances-small",
        "equipment",
        "electronic",
        "supplies-wholesale",
        "manufacturer"
    ],
    "sg:website":"http://www.pjelectronics.com",
    "wof:name":"P J Electronics Inc",
    "wof:placetype":"venue"
},
  "geometry": {"coordinates":[-79.768419,40.462811],"type":"Point"}
}