{
  "type": "Feature",
  "properties": {
    "iso:country":"US",
    "sg:address":"1200 E High St",
    "sg:city":"Pottstown",
    "sg:classifiers":[
        {
            "category":"Health Services",
            "subcategory":"Doctor",
            "type":"Services"
        }
    ],
    "sg:phone":"+1 610 970 0999",
    "sg:postcode":"19464",
    "sg:province":"PA",
    "sg:tags":[
        "physician",
        "surgeon"
    ],
    "wof:name":"Robert Anolik MD",
    "wof:placetype":"venue"
},
  "geometry": {"coordinates":[-75.62329099999999,40.243688],"type":"Point"}
}