{
  "type": "Feature",
  "properties": {
    "iso:country":"US",
    "sg:address":"2501 Chestnut Rd",
    "sg:city":"Elizabethtown",
    "sg:classifiers":[
        {
            "category":"Wholesale",
            "subcategory":"Durable Goods & Equipment",
            "type":"Manufacturing & Wholesale Goods"
        }
    ],
    "sg:phone":"+1 717 367 0422",
    "sg:postcode":"17022",
    "sg:province":"PA",
    "sg:tags":[
        "representative",
        "manufacturer"
    ],
    "wof:name":"Donald E Parmer Contracting",
    "wof:placetype":"venue"
},
  "geometry": {"coordinates":[-76.64904799999999,40.222847],"type":"Point"}
}