{
  "type": "Feature",
  "properties": {
    "iso:country":"US",
    "sg:address":"134 Avis Ave",
    "sg:city":"Johnstown",
    "sg:classifiers":[
        {
            "category":"Real Estate",
            "subcategory":"Architect",
            "type":"Services"
        }
    ],
    "sg:phone":"+1 814 536 5299",
    "sg:postcode":"15905",
    "sg:province":"PA",
    "sg:tags":[
        "architectural"
    ],
    "wof:name":"Patrick S Ditko",
    "wof:placetype":"venue"
},
  "geometry": {"coordinates":[-78.949197,40.339759],"type":"Point"}
}