{
  "type": "Feature",
  "properties": {
    "addr:full":"21 Hillcrest Dr Manheim PA 17545",
    "addr:housenumber":"21",
    "addr:postcode":"17545",
    "addr:street":"Hillcrest Dr",
    "iso:country":"US",
    "sg:address":"21 Hillcrest Dr",
    "sg:city":"Manheim",
    "sg:classifiers":[
        {
            "category":"Professional",
            "type":"Services"
        }
    ],
    "sg:phone":"+1   ",
    "sg:postcode":"17545",
    "sg:province":"PA",
    "wof:name":"Tiger White International",
    "wof:placetype":"venue"
},
  "geometry": {"coordinates":[-76.38417099999999,40.145854],"type":"Point"}
}