{
  "type": "Feature",
  "properties": {
    "addr:full":"2213 Brownsville Rd Pittsburgh PA 15210",
    "addr:housenumber":"2213",
    "addr:postcode":"15210",
    "addr:street":"Brownsville Rd",
    "iso:country":"US",
    "sg:address":"2213 Brownsville Rd",
    "sg:city":"Pittsburgh",
    "sg:classifiers":[
        {
            "category":"Health Services",
            "subcategory":"Doctor",
            "type":"Services"
        }
    ],
    "sg:phone":"+1 412 881 3111",
    "sg:postcode":"15210",
    "sg:province":"PA",
    "wof:name":"Baade Eileen MD",
    "wof:placetype":"venue"
},
  "geometry": {"coordinates":[-79.986397,40.390999],"type":"Point"}
}