{
  "type": "Feature",
  "properties": {
    "addr:full":"207 Monroe St Philadelphia PA 19147",
    "addr:housenumber":"207",
    "addr:postcode":"19147",
    "addr:street":"Monroe St",
    "iso:country":"US",
    "sg:address":"207 Monroe St",
    "sg:city":"Philadelphia",
    "sg:classifiers":[
        {
            "category":"Education",
            "subcategory":"College",
            "type":"Public Place"
        }
    ],
    "sg:phone":"+1   ",
    "sg:postcode":"19147",
    "sg:province":"PA",
    "wof:name":"Department of Architecture",
    "wof:placetype":"venue"
},
  "geometry": {"coordinates":[-75.146959,39.939541],"type":"Point"}
}