{
  "type": "Feature",
  "properties": {
    "addr:full":"158 Mc Connell Rd Loretto PA 15940",
    "addr:housenumber":"158",
    "addr:postcode":"15940",
    "addr:street":"Mc Connell Rd",
    "iso:country":"US",
    "sg:address":"158 Mc Connell Rd",
    "sg:city":"Loretto",
    "sg:classifiers":[
        {
            "category":"Shopping",
            "subcategory":"Clothing, Apparel, & Fashions",
            "type":"Retail Goods"
        }
    ],
    "sg:phone":"+1   ",
    "sg:postcode":"15940",
    "sg:province":"PA",
    "sg:tags":[
        "store",
        "accessory"
    ],
    "wof:name":"Aleste Bridal",
    "wof:placetype":"venue"
},
  "geometry": {"coordinates":[-78.616112,40.460776],"type":"Point"}
}