{
  "type": "Feature",
  "properties": {
    "iso:country":"US",
    "sg:address":"224 Deysher Rd",
    "sg:city":"Fleetwood",
    "sg:classifiers":[
        {
            "category":"Professional",
            "subcategory":"Lawyer & Legal Services",
            "type":"Services"
        }
    ],
    "sg:phone":"+1 610 987 8804",
    "sg:postcode":"19522",
    "sg:province":"PA",
    "sg:tags":[
        "attorney"
    ],
    "wof:name":"James A Mc Clean Jr Law Ofcs",
    "wof:placetype":"venue"
},
  "geometry": {"coordinates":[-75.738525,40.417905],"type":"Point"}
}