{
  "type": "Feature",
  "properties": {
    "iso:country":"US",
    "sg:address":"110 S Lake Dr",
    "sg:city":"Lake Harmony",
    "sg:classifiers":[
        {
            "category":"Restaurant",
            "type":"Food & Drink"
        }
    ],
    "sg:phone":"+1 570 722 2500",
    "sg:postcode":"18624",
    "sg:province":"PA",
    "wof:name":"Nick's Lake House",
    "wof:placetype":"venue"
},
  "geometry": {"coordinates":[-75.58835999999999,41.059847],"type":"Point"}
}