{
  "type": "Feature",
  "properties": {
    "addr:full":"408 Depot St Youngwood PA 15697",
    "addr:housenumber":"408",
    "addr:postcode":"15697",
    "addr:street":"Depot St",
    "iso:country":"US",
    "sg:address":"408 Depot St",
    "sg:city":"Youngwood",
    "sg:classifiers":[
        {
            "category":"Retail",
            "subcategory":"Funeral Services",
            "type":"Services"
        }
    ],
    "sg:phone":"+1 724 925 7216",
    "sg:postcode":"15697",
    "sg:province":"PA",
    "sg:tags":[
        "director"
    ],
    "wof:name":"Peterson Funeral Home",
    "wof:placetype":"venue"
},
  "geometry": {"coordinates":[-79.57960799999999,40.240501],"type":"Point"}
}