{
  "type": "Feature",
  "properties": {
    "iso:country":"US",
    "sg:address":"1581 W Branch Rd",
    "sg:city":"State College",
    "sg:classifiers":[
        {
            "category":"Organizations",
            "subcategory":"Membership Organization",
            "type":"Services"
        }
    ],
    "sg:phone":"+1   ",
    "sg:postcode":"16801",
    "sg:province":"PA",
    "wof:name":"Queen Nitt-Nee",
    "wof:placetype":"venue"
},
  "geometry": {"coordinates":[-77.837272,40.769953],"type":"Point"}
}