{
  "type": "Feature",
  "properties": {
    "addr:full":"63 E Main St Mt Jewett PA 16740",
    "addr:housenumber":"63",
    "addr:postcode":"16740",
    "addr:street":"E Main St",
    "iso:country":"US",
    "sg:address":"63 E Main St",
    "sg:city":"Mt Jewett",
    "sg:classifiers":[
        {
            "category":"Organizations",
            "subcategory":"Community Association",
            "type":"Services"
        }
    ],
    "sg:phone":"+1 814 778 5911",
    "sg:postcode":"16740",
    "sg:province":"PA",
    "sg:tags":[
        "military"
    ],
    "wof:name":"American Legion",
    "wof:placetype":"venue"
},
  "geometry": {"coordinates":[-78.634569,41.725671],"type":"Point"}
}