{
  "type": "Feature",
  "properties": {
    "addr:full":"873 W Butler Pike Ambler PA 19002",
    "addr:housenumber":"873",
    "addr:postcode":"19002",
    "addr:street":"W Butler Pike",
    "iso:country":"US",
    "sg:address":"873 W Butler Pike",
    "sg:city":"Ambler",
    "sg:classifiers":[
        {
            "category":"Personal",
            "subcategory":"Beauty Salon",
            "type":"Services"
        }
    ],
    "sg:phone":"+1 215 591 9258",
    "sg:postcode":"19002",
    "sg:province":"PA",
    "sg:tags":[
        "shop"
    ],
    "wof:name":"Paris Cosmetics",
    "wof:placetype":"venue"
},
  "geometry": {"coordinates":[-75.244247,40.138975],"type":"Point"}
}