{
  "type": "Feature",
  "properties": {
    "iso:country":"US",
    "sg:address":"8037 Old York Rd",
    "sg:city":"Elkins Park",
    "sg:classifiers":[
        {
            "category":"Real Estate",
            "subcategory":"Real Estate Agent",
            "type":"Services"
        }
    ],
    "sg:phone":"+1 215 635 2200",
    "sg:postcode":"19027",
    "sg:province":"PA",
    "sg:website":"www.c21ag.com",
    "wof:name":"Advantage Gold",
    "wof:placetype":"venue"
},
  "geometry": {"coordinates":[-75.128153,40.075958],"type":"Point"}
}