{
  "type": "Feature",
  "properties": {
    "addr:full":"30 E Columbia Rd Enola PA 17025",
    "addr:housenumber":"30",
    "addr:postcode":"17025",
    "addr:street":"E Columbia Rd",
    "iso:country":"US",
    "sg:address":"30 E Columbia Rd",
    "sg:city":"Enola",
    "sg:classifiers":[
        {
            "category":"Building & Trades",
            "subcategory":"Construction",
            "type":"Services"
        }
    ],
    "sg:phone":"+1   ",
    "sg:postcode":"17025",
    "sg:province":"PA",
    "sg:tags":[
        "contractor"
    ],
    "wof:name":"M W Golden",
    "wof:placetype":"venue"
},
  "geometry": {"coordinates":[-76.931527,40.296314],"type":"Point"}
}