{
  "type": "Feature",
  "properties": {
    "iso:country":"US",
    "sg:address":"1311 Wilmington Pike",
    "sg:city":"West Chester",
    "sg:classifiers":[
        {
            "category":"Building & Trades",
            "subcategory":"Construction",
            "type":"Services"
        }
    ],
    "sg:phone":"+1 610 399 6585",
    "sg:postcode":"19382",
    "sg:province":"PA",
    "sg:tags":[
        "painter"
    ],
    "wof:name":"Armstrong Painting",
    "wof:placetype":"venue"
},
  "geometry": {"coordinates":[-75.570396,39.9104],"type":"Point"}
}