{
  "type": "Feature",
  "properties": {
    "addr:full":"255 Lancaster Ave Williamstown PA 17064",
    "addr:housenumber":"255",
    "addr:postcode":"17064",
    "addr:street":"Lancaster Ave",
    "iso:country":"US",
    "sg:address":"255 Lancaster Ave",
    "sg:city":"Williamstown",
    "sg:classifiers":[
        {
            "category":"Professional",
            "type":"Services"
        }
    ],
    "sg:phone":"+1 610 251 9433",
    "sg:postcode":"17064",
    "sg:province":"PA",
    "sg:tags":[
        "establishment"
    ],
    "wof:name":"Women For Women PC",
    "wof:placetype":"venue"
},
  "geometry": {"coordinates":[-76.472032,40.245234],"type":"Point"}
}