{
  "type": "Feature",
  "properties": {
    "iso:country":"US",
    "sg:address":"695 Jacobs Rd",
    "sg:city":"Somerset",
    "sg:classifiers":[
        {
            "category":"Farming",
            "subcategory":"Livestock Farm",
            "type":"Manufacturing & Wholesale Goods"
        }
    ],
    "sg:phone":"+1   ",
    "sg:postcode":"15501",
    "sg:province":"PA",
    "sg:tags":[
        "specialty",
        "animal"
    ],
    "wof:name":"James Jacobs",
    "wof:placetype":"venue"
},
  "geometry": {"coordinates":[-79.061235,40.072548],"type":"Point"}
}