{
  "type": "Feature",
  "properties": {
    "iso:country":"US",
    "sg:address":"853 Gravel Pike",
    "sg:city":"Schwenksville",
    "sg:classifiers":[
        {
            "category":"Shopping",
            "subcategory":"Florist",
            "type":"Retail Goods"
        }
    ],
    "sg:phone":"+1 610 287 7878",
    "sg:postcode":"19426",
    "sg:province":"PA",
    "wof:name":"Ott's Exotic Plants",
    "wof:placetype":"venue"
},
  "geometry": {"coordinates":[-75.45569,40.238758],"type":"Point"}
}