{
  "type": "Feature",
  "properties": {
    "addr:full":"79 Montgomery St Montgomery PA 17752",
    "addr:housenumber":"79",
    "addr:postcode":"17752",
    "addr:street":"Montgomery St",
    "iso:country":"US",
    "sg:address":"79 Montgomery St",
    "sg:city":"Montgomery",
    "sg:classifiers":[
        {
            "category":"Manufacturing",
            "subcategory":"Tools & Machinery",
            "type":"Manufacturing & Wholesale Goods"
        }
    ],
    "sg:phone":"+1 570 547 1621",
    "sg:postcode":"17752",
    "sg:province":"PA",
    "sg:tags":[
        "construction"
    ],
    "wof:name":"M B Co",
    "wof:placetype":"venue"
},
  "geometry": {"coordinates":[-76.87236799999999,41.171958],"type":"Point"}
}