{
  "type": "Feature",
  "properties": {
    "iso:country":"US",
    "sg:address":"1603 E High St Ste B",
    "sg:city":"Pottstown",
    "sg:classifiers":[
        {
            "category":"Health Services",
            "subcategory":"Doctor",
            "type":"Services"
        },
        {
            "category":"Health Services",
            "subcategory":"Dentist",
            "type":"Services"
        }
    ],
    "sg:phone":"+1 610 323 6520",
    "sg:postcode":"19464",
    "sg:province":"PA",
    "sg:tags":[
        "dentists-oral",
        "physician",
        "maxillofacial",
        "surgeons",
        "surgery",
        "oral"
    ],
    "wof:name":"Powell Jonathan DMD",
    "wof:placetype":"venue"
},
  "geometry": {"coordinates":[-75.611366,40.243938],"type":"Point"}
}