{
  "type": "Feature",
  "properties": {
    "addr:full":"540 Kenhorst Plz Reading PA 19607",
    "addr:housenumber":"540",
    "addr:postcode":"19607",
    "addr:street":"Kenhorst Plz",
    "iso:country":"US",
    "sg:address":"540 Kenhorst Plz",
    "sg:city":"Reading",
    "sg:classifiers":[
        {
            "category":"Banks & Credit Unions",
            "subcategory":"Bank",
            "type":"Services"
        }
    ],
    "sg:phone":"+1 610 775 8100",
    "sg:postcode":"19607",
    "sg:province":"PA",
    "sg:tags":[
        "cashing",
        "money",
        "order",
        "check"
    ],
    "wof:name":"United Check Cashing",
    "wof:placetype":"venue"
},
  "geometry": {"coordinates":[-75.94719499999999,40.298909],"type":"Point"}
}