{
  "type": "Feature",
  "properties": {
    "iso:country":"US",
    "sg:address":"1822 Union Ave",
    "sg:city":"Natrona Heights",
    "sg:classifiers":[
        {
            "category":"Shopping",
            "type":"Retail Goods"
        }
    ],
    "sg:phone":"+1   ",
    "sg:postcode":"15065",
    "sg:province":"PA",
    "sg:tags":[
        "merchandise"
    ],
    "wof:name":"Unwired",
    "wof:placetype":"venue"
},
  "geometry": {"coordinates":[-79.724526,40.622082],"type":"Point"}
}