{
  "type": "Feature",
  "properties": {
    "iso:country":"US",
    "sg:address":"501 W 3rd St",
    "sg:city":"Birdsboro",
    "sg:classifiers":[
        {
            "category":"Building & Trades",
            "subcategory":"Construction",
            "type":"Services"
        }
    ],
    "sg:phone":"+1   ",
    "sg:postcode":"19508",
    "sg:province":"PA",
    "wof:name":"L Harrison Paving",
    "wof:placetype":"venue"
},
  "geometry": {"coordinates":[-75.815966,40.263256],"type":"Point"}
}