{
  "type": "Feature",
  "properties": {
    "addr:full":"111 Presidential Blvd Ste 214 Bala Cynwyd PA 19004",
    "addr:housenumber":"111",
    "addr:postcode":"19004",
    "addr:street":"Presidential Blvd Ste 214",
    "iso:country":"US",
    "sg:address":"111 Presidential Blvd Ste 214",
    "sg:city":"Bala Cynwyd",
    "sg:classifiers":[
        {
            "category":"Community Center",
            "type":"Public Place"
        }
    ],
    "sg:phone":"+1 484 270 8127",
    "sg:postcode":"19004",
    "sg:province":"PA",
    "sg:tags":[
        "medical"
    ],
    "wof:name":"Presidential Medical Center",
    "wof:placetype":"venue"
},
  "geometry": {"coordinates":[-75.2157,40.01106],"type":"Point"}
}