{
  "type": "Feature",
  "properties": {
    "addr:full":"46 Brookside Rd Tunkhannock PA 18657",
    "addr:housenumber":"46",
    "addr:postcode":"18657",
    "addr:street":"Brookside Rd",
    "iso:country":"US",
    "sg:address":"46 Brookside Rd",
    "sg:city":"Tunkhannock",
    "sg:classifiers":[
        {
            "category":"Freight",
            "type":"Transportation"
        }
    ],
    "sg:phone":"+1   ",
    "sg:postcode":"18657",
    "sg:province":"PA",
    "sg:tags":[
        "operator",
        "local",
        "trucking"
    ],
    "wof:name":"Cashmark Trucking & Contg",
    "wof:placetype":"venue"
},
  "geometry": {"coordinates":[-75.937241,41.563599],"type":"Point"}
}