{
  "type": "Feature",
  "properties": {
    "addr:full":"1 Lockview Ave Charleroi PA 15022",
    "addr:housenumber":"1",
    "addr:postcode":"15022",
    "addr:street":"Lockview Ave",
    "iso:country":"US",
    "sg:address":"1 Lockview Ave",
    "sg:city":"Charleroi",
    "sg:classifiers":[
        {
            "category":"Organizations",
            "subcategory":"Religious Organization",
            "type":"Services"
        }
    ],
    "sg:phone":"+1 724 489 1040",
    "sg:postcode":"15022",
    "sg:province":"PA",
    "sg:tags":[
        "church"
    ],
    "wof:name":"Charleroi Baptist Church",
    "wof:placetype":"venue"
},
  "geometry": {"coordinates":[-79.90984899999999,40.154762],"type":"Point"}
}