{
  "type": "Feature",
  "properties": {
    "addr:full":"5070 Route 219 Brockport PA 15823",
    "addr:housenumber":"5070",
    "addr:postcode":"15823",
    "addr:street":"Route 219",
    "iso:country":"US",
    "sg:address":"5070 Route 219",
    "sg:city":"Brockport",
    "sg:classifiers":[
        {
            "category":"Bars & Pubs",
            "subcategory":"Lounge",
            "type":"Food & Drink"
        },
        {
            "category":"Restaurant",
            "type":"Food & Drink"
        }
    ],
    "sg:phone":"+1 814 435 3485",
    "sg:postcode":"15823",
    "sg:province":"PA",
    "sg:tags":[
        "cocktail"
    ],
    "wof:name":"The Wonder Bar & Grill",
    "wof:placetype":"venue"
},
  "geometry": {"coordinates":[-78.711766,41.27157],"type":"Point"}
}