{
  "type": "Feature",
  "properties": {
    "addr:full":"7998 New Falls Rd Levittown PA 19055",
    "addr:housenumber":"7998",
    "addr:postcode":"19055",
    "addr:street":"New Falls Rd Levittown",
    "iso:country":"US",
    "sg:address":"7998 New Falls Rd",
    "sg:city":"Levittown",
    "sg:classifiers":[
        {
            "category":"Building & Trades",
            "subcategory":"Landscaping Services",
            "type":"Services"
        }
    ],
    "sg:phone":"+1   ",
    "sg:postcode":"19055",
    "sg:province":"PA",
    "wof:name":"Jacks Supreme Landscaping",
    "wof:placetype":"venue"
},
  "geometry": {"coordinates":[-74.84814799999999,40.160258],"type":"Point"}
}