{
  "type": "Feature",
  "properties": {
    "iso:country":"US",
    "sg:address":"2000 N 6th St",
    "sg:city":"Harrisburg",
    "sg:classifiers":[
        {
            "category":"Government",
            "subcategory":"Police Station",
            "type":"Public Place"
        }
    ],
    "sg:phone":"+1   ",
    "sg:postcode":"17102",
    "sg:province":"PA",
    "sg:tags":[
        "protection"
    ],
    "wof:name":"Uptown Police",
    "wof:placetype":"venue"
},
  "geometry": {"coordinates":[-76.890366,40.280494],"type":"Point"}
}