{
  "type": "Feature",
  "properties": {
    "iso:country":"US",
    "sg:address":"6287 Five Points Rd",
    "sg:city":"Creekside",
    "sg:phone":"+1   ",
    "sg:postcode":"15732",
    "sg:province":"PA",
    "sg:tags":[
        "farm",
        "hog",
        "corn",
        "or",
        "feedlot"
    ],
    "wof:name":"Robert L Orr",
    "wof:placetype":"venue"
},
  "geometry": {"coordinates":[-79.217266,40.728098],"type":"Point"}
}