{
  "type": "Feature",
  "properties": {
    "iso:country":"US",
    "sg:address":"2547 Brownsville Rd",
    "sg:city":"Pittsburgh",
    "sg:classifiers":[
        {
            "category":"Personal",
            "type":"Services"
        }
    ],
    "sg:phone":"+1 412 885 8365",
    "sg:postcode":"15210",
    "sg:province":"PA",
    "sg:tags":[
        "tanning"
    ],
    "wof:name":"Seaside Serenity",
    "wof:placetype":"venue"
},
  "geometry": {"coordinates":[-79.980904,40.386902],"type":"Point"}
}