{
  "type": "Feature",
  "properties": {
    "iso:country":"US",
    "sg:address":"38 Macdade Blvd",
    "sg:city":"Glenolden",
    "sg:classifiers":[
        {
            "category":"Manufacturing",
            "subcategory":"Food",
            "type":"Manufacturing & Wholesale Goods"
        },
        {
            "category":"Wholesale",
            "subcategory":"Groceries",
            "type":"Manufacturing & Wholesale Goods"
        }
    ],
    "sg:phone":"+1 610 522 2700",
    "sg:postcode":"19036",
    "sg:province":"PA",
    "sg:tags":[
        "confectionery",
        "candy",
        "mfg"
    ],
    "wof:name":"Sweet Dreams Chocolate Box",
    "wof:placetype":"venue"
},
  "geometry": {"coordinates":[-75.290677,39.905754],"type":"Point"}
}