{
  "type": "Feature",
  "properties": {
    "iso:country":"US",
    "sg:address":"1913 Wakeling St",
    "sg:city":"Philadelphia",
    "sg:classifiers":[
        {
            "category":"Building & Trades",
            "subcategory":"Construction",
            "type":"Services"
        }
    ],
    "sg:phone":"+1   ",
    "sg:postcode":"19124",
    "sg:province":"PA",
    "sg:tags":[
        "residential"
    ],
    "wof:name":"Peniel Development Corporation",
    "wof:placetype":"venue"
},
  "geometry": {"coordinates":[-75.07437299999999,40.015662],"type":"Point"}
}