{
  "type": "Feature",
  "properties": {
    "iso:country":"US",
    "sg:address":"740 Sansom St Ste 201",
    "sg:city":"Philadelphia",
    "sg:classifiers":[
        {
            "category":"Shopping",
            "subcategory":"Jewelry",
            "type":"Retail Goods"
        }
    ],
    "sg:phone":"+1 215 922 4923",
    "sg:postcode":"19106",
    "sg:province":"PA",
    "wof:name":"Neff Louis Inc",
    "wof:placetype":"venue"
},
  "geometry": {"coordinates":[-75.153099,39.9487],"type":"Point"}
}