{
  "type": "Feature",
  "properties": {
    "iso:country":"US",
    "sg:address":"34 Jonathan Way",
    "sg:city":"Washington Crossing",
    "sg:classifiers":[
        {
            "category":"Professional",
            "subcategory":"Research",
            "type":"Services"
        }
    ],
    "sg:phone":"+1   ",
    "sg:postcode":"18977",
    "sg:province":"PA",
    "sg:tags":[
        "nonphysical",
        "commercial"
    ],
    "wof:name":"Mmd Inc",
    "wof:placetype":"venue"
},
  "geometry": {"coordinates":[-74.900628,40.310433],"type":"Point"}
}