{
  "type": "Feature",
  "properties": {
    "iso:country":"US",
    "sg:address":"110 Quarry View Dr",
    "sg:city":"Morgantown",
    "sg:classifiers":[
        {
            "category":"Health Services",
            "subcategory":"Doctor",
            "type":"Services"
        }
    ],
    "sg:phone":"+1 610 913 0269",
    "sg:postcode":"19543",
    "sg:province":"PA",
    "sg:tags":[
        "physician",
        "surgeon"
    ],
    "wof:name":"Le Trang",
    "wof:placetype":"venue"
},
  "geometry": {"coordinates":[-75.869438,40.147079],"type":"Point"}
}