{
  "type": "Feature",
  "properties": {
    "iso:country":"US",
    "sg:address":"414 Olive St",
    "sg:city":"Scranton",
    "sg:classifiers":[
        {
            "category":"Social Services",
            "subcategory":"Child Care",
            "type":"Services"
        }
    ],
    "sg:phone":"+1   ",
    "sg:postcode":"18509",
    "sg:province":"PA",
    "sg:tags":[
        "day"
    ],
    "wof:name":"United Neighborhood Center",
    "wof:placetype":"venue"
},
  "geometry": {"coordinates":[-75.658732,41.412855],"type":"Point"}
}