{
  "type": "Feature",
  "properties": {
    "iso:country":"US",
    "sg:address":"101 Hoffman Blvd",
    "sg:city":"Duquesne",
    "sg:classifiers":[
        {
            "category":"Restaurant",
            "type":"Food & Drink"
        }
    ],
    "sg:menulink":"http://www.allmenus.com/pa/duquesne/206021-mcdonalds/menu/",
    "sg:phone":"+1 412 461 6606",
    "sg:postcode":"15110",
    "sg:province":"PA",
    "sg:tags":[
        "burger",
        "american"
    ],
    "wof:name":"McDonald's",
    "wof:placetype":"venue"
},
  "geometry": {"coordinates":[-79.86301400000001,40.384364],"type":"Point"}
}