{
  "type": "Feature",
  "properties": {
    "iso:country":"US",
    "sg:address":"351 Pequea Ave",
    "sg:city":"Honey Brook",
    "sg:classifiers":[
        {
            "category":"Farming",
            "subcategory":"Livestock Farm",
            "type":"Manufacturing & Wholesale Goods"
        }
    ],
    "sg:phone":"+1   ",
    "sg:postcode":"19344",
    "sg:province":"PA",
    "sg:tags":[
        "animal",
        "general"
    ],
    "wof:name":"Alvin Zook",
    "wof:placetype":"venue"
},
  "geometry": {"coordinates":[-75.916764,40.091659],"type":"Point"}
}