{
  "type": "Feature",
  "properties": {
    "iso:country":"US",
    "sg:address":"314 Verla Dr",
    "sg:city":"Windber",
    "sg:classifiers":[
        {
            "category":"Professional",
            "type":"Services"
        }
    ],
    "sg:phone":"+1 814 467 8998",
    "sg:postcode":"15963",
    "sg:province":"PA",
    "sg:tags":[
        "establishment"
    ],
    "wof:name":"Trabc",
    "wof:placetype":"venue"
},
  "geometry": {"coordinates":[-78.790766,40.212015],"type":"Point"}
}