{
  "type": "Feature",
  "properties": {
    "iso:country":"US",
    "sg:address":"3260 Sunnyside Rd",
    "sg:city":"Manheim",
    "sg:classifiers":[
        {
            "category":"Farming",
            "subcategory":"Poultry Farm",
            "type":"Manufacturing & Wholesale Goods"
        }
    ],
    "sg:phone":"+1 717 361 0411",
    "sg:postcode":"17545",
    "sg:province":"PA",
    "sg:tags":[
        "egg"
    ],
    "wof:name":"Sunny Hill Farm",
    "wof:placetype":"venue"
},
  "geometry": {"coordinates":[-76.512355,40.169808],"type":"Point"}
}