{
  "type": "Feature",
  "properties": {
    "iso:country":"US",
    "sg:address":"744 Red Lion Rd",
    "sg:city":"Philadelphia",
    "sg:classifiers":[
        {
            "category":"Restaurant",
            "type":"Food & Drink"
        }
    ],
    "sg:menulink":"http://www.allmenus.com/pa/philadelphia/258802-szechuan-east/menu/",
    "sg:phone":"+1 215 464 4455",
    "sg:postcode":"19115",
    "sg:province":"PA",
    "sg:tags":[
        "asian",
        "chinese"
    ],
    "wof:name":"Szechuan East",
    "wof:placetype":"venue"
},
  "geometry": {"coordinates":[-75.03383599999999,40.105557],"type":"Point"}
}