{
  "type": "Feature",
  "properties": {
    "addr:full":"11 Briarcrest Sq Hershey PA 17033",
    "addr:housenumber":"11",
    "addr:postcode":"17033",
    "addr:street":"Briarcrest Sq",
    "iso:country":"US",
    "sg:address":"11 Briarcrest Sq",
    "sg:city":"Hershey",
    "sg:classifiers":[
        {
            "category":"Shopping",
            "subcategory":"Clothing, Apparel, & Fashions",
            "type":"Retail Goods"
        }
    ],
    "sg:phone":"+1   ",
    "sg:postcode":"17033",
    "sg:province":"PA",
    "sg:tags":[
        "ready"
    ],
    "wof:name":"Mary Eileens Boutique",
    "wof:placetype":"venue"
},
  "geometry": {"coordinates":[-76.672236,40.270286],"type":"Point"}
}