{
  "type": "Feature",
  "properties": {
    "iso:country":"US",
    "sg:address":"145 Timber Springs Dr",
    "sg:city":"Indiana",
    "sg:classifiers":[
        {
            "category":"Manufacturing",
            "subcategory":"Tools & Machinery",
            "type":"Manufacturing & Wholesale Goods"
        }
    ],
    "sg:phone":"+1   ",
    "sg:postcode":"15701",
    "sg:province":"PA",
    "sg:tags":[
        "mining",
        "mfg"
    ],
    "wof:name":"V King Co",
    "wof:placetype":"venue"
},
  "geometry": {"coordinates":[-79.170412,40.599906],"type":"Point"}
}