{
  "type": "Feature",
  "properties": {
    "iso:country":"US",
    "sg:address":"2948 Leechburg Rd",
    "sg:city":"New Kensington",
    "sg:classifiers":[
        {
            "category":"Manufacturing",
            "subcategory":"Tools & Machinery",
            "type":"Manufacturing & Wholesale Goods"
        }
    ],
    "sg:phone":"+1   ",
    "sg:postcode":"15068",
    "sg:province":"PA",
    "sg:tags":[
        "industrial",
        "cutting",
        "sharpens",
        "mfg"
    ],
    "wof:name":"HI Tech Tl & Cutter Sharpening",
    "wof:placetype":"venue"
},
  "geometry": {"coordinates":[-79.722089,40.588434],"type":"Point"}
}