{
  "type": "Feature",
  "properties": {
    "addr:full":"133 Pittsburgh St Uniontown PA 15401",
    "addr:housenumber":"133",
    "addr:postcode":"15401",
    "addr:street":"Pittsburgh St",
    "iso:country":"US",
    "sg:address":"133 Pittsburgh St",
    "sg:city":"Uniontown",
    "sg:classifiers":[
        {
            "category":"Autos & Motor Vehicles",
            "subcategory":"Fuel & Gas Station",
            "type":"Retail Goods"
        }
    ],
    "sg:phone":"+1   ",
    "sg:postcode":"15401",
    "sg:province":"PA",
    "sg:tags":[
        "station",
        "gasoline"
    ],
    "wof:name":"Kolencik Gulf",
    "wof:placetype":"venue"
},
  "geometry": {"coordinates":[-79.72774,39.907189],"type":"Point"}
}