{
  "type": "Feature",
  "properties": {
    "addr:full":"36 Gettysburg St Biglerville PA 17303",
    "addr:housenumber":"36",
    "addr:postcode":"17303",
    "addr:street":"Gettysburg St",
    "iso:country":"US",
    "sg:address":"36 Gettysburg St",
    "sg:city":"Biglerville",
    "sg:classifiers":[
        {
            "category":"Restaurant",
            "type":"Food & Drink"
        }
    ],
    "sg:phone":"+1 717 677 8448",
    "sg:postcode":"17303",
    "sg:province":"PA",
    "wof:name":"Ventura's Pizza",
    "wof:placetype":"venue"
},
  "geometry": {"coordinates":[-77.29761499999999,39.920298],"type":"Point"}
}