{
  "type": "Feature",
  "properties": {
    "iso:country":"US",
    "sg:address":"935 Thorn Run Rd",
    "sg:city":"Coraopolis",
    "sg:classifiers":[
        {
            "category":"Health Services",
            "subcategory":"Health Practitioner",
            "type":"Services"
        }
    ],
    "sg:phone":"+1   ",
    "sg:postcode":"15108",
    "sg:province":"PA",
    "wof:name":"Swickley Vlly Hospital",
    "wof:placetype":"venue"
},
  "geometry": {"coordinates":[-80.199623,40.512833],"type":"Point"}
}