{
  "type": "Feature",
  "properties": {
    "addr:full":"3592 Cresson St Philadelphia PA 19129",
    "addr:housenumber":"3592",
    "addr:postcode":"19129",
    "addr:street":"Cresson St",
    "iso:country":"US",
    "sg:address":"3592 Cresson St",
    "sg:city":"Philadelphia",
    "sg:classifiers":[
        {
            "category":"Professional",
            "subcategory":"Management & Consulting",
            "type":"Services"
        }
    ],
    "sg:phone":"+1 215 991 1963",
    "sg:postcode":"19129",
    "sg:province":"PA",
    "sg:tags":[
        "construction"
    ],
    "wof:name":"Tony Depaul & Sons",
    "wof:placetype":"venue"
},
  "geometry": {"coordinates":[-75.199173,40.013744],"type":"Point"}
}