{
  "type": "Feature",
  "properties": {
    "iso:country":"US",
    "sg:address":"895 Georges Ln",
    "sg:city":"Warminster",
    "sg:classifiers":[
        {
            "category":"Freight",
            "type":"Transportation"
        }
    ],
    "sg:phone":"+1   ",
    "sg:postcode":"18974",
    "sg:province":"PA",
    "sg:tags":[
        "operator",
        "local",
        "trucking"
    ],
    "wof:name":"R T Delivery Service",
    "wof:placetype":"venue"
},
  "geometry": {"coordinates":[-75.10139599999999,40.219811],"type":"Point"}
}