{
  "type": "Feature",
  "properties": {
    "addr:full":"8625 Station Rd Erie PA 16510",
    "addr:housenumber":"8625",
    "addr:postcode":"16510",
    "addr:street":"Station Rd",
    "iso:country":"US",
    "sg:address":"8625 Station Rd",
    "sg:city":"Erie",
    "sg:classifiers":[
        {
            "category":"Farming",
            "subcategory":"Livestock Farm",
            "type":"Manufacturing & Wholesale Goods"
        }
    ],
    "sg:phone":"+1   ",
    "sg:postcode":"16510",
    "sg:province":"PA",
    "sg:tags":[
        "hog",
        "or",
        "feedlot"
    ],
    "wof:name":"Hacks Hog Farm",
    "wof:placetype":"venue"
},
  "geometry": {"coordinates":[-79.914069,42.116245],"type":"Point"}
}