{
  "type": "Feature",
  "properties": {
    "addr:full":"320 Penn St Huntingdon PA 16652",
    "addr:housenumber":"320",
    "addr:postcode":"16652",
    "addr:street":"Penn St",
    "iso:country":"US",
    "sg:address":"320 Penn St",
    "sg:city":"Huntingdon",
    "sg:classifiers":[
        {
            "category":"Shopping",
            "subcategory":"Music",
            "type":"Retail Goods"
        }
    ],
    "sg:phone":"+1   ",
    "sg:postcode":"16652",
    "sg:province":"PA",
    "wof:name":"Marys Bargains",
    "wof:placetype":"venue"
},
  "geometry": {"coordinates":[-78.010806,40.484268],"type":"Point"}
}