{
  "type": "Feature",
  "properties": {
    "iso:country":"US",
    "sg:address":"2582 Balwynne Park Rd",
    "sg:city":"Philadelphia",
    "sg:classifiers":[
        {
            "category":"Health Services",
            "subcategory":"Nursing And Care Facility",
            "type":"Services"
        }
    ],
    "sg:phone":"+1   ",
    "sg:postcode":"19131",
    "sg:province":"PA",
    "sg:tags":[
        "skilled"
    ],
    "wof:name":"Sbenjay Nursing Services Inc",
    "wof:placetype":"venue"
},
  "geometry": {"coordinates":[-75.209694,39.999425],"type":"Point"}
}