{
  "type": "Feature",
  "properties": {
    "iso:country":"US",
    "sg:address":"371 Avon Dr",
    "sg:city":"Pittsburgh",
    "sg:classifiers":[
        {
            "category":"Real Estate",
            "subcategory":"Architect",
            "type":"Services"
        }
    ],
    "sg:phone":"+1 412 531 3674",
    "sg:postcode":"15228",
    "sg:province":"PA",
    "wof:name":"Luedy Carl A Architect",
    "wof:placetype":"venue"
},
  "geometry": {"coordinates":[-80.037498,40.371601],"type":"Point"}
}