{
  "type": "Feature",
  "properties": {
    "iso:country":"US",
    "sg:address":"536 Witmer Ave",
    "sg:city":"Hanover",
    "sg:classifiers":[
        {
            "category":"Professional",
            "subcategory":"Advertising",
            "type":"Services"
        }
    ],
    "sg:phone":"+1 717 632 5052",
    "sg:postcode":"17331",
    "sg:province":"PA",
    "sg:tags":[
        "counselor"
    ],
    "wof:name":"Wine List-Graphics By D Wine",
    "wof:placetype":"venue"
},
  "geometry": {"coordinates":[-76.9736,39.820021],"type":"Point"}
}