{
  "type": "Feature",
  "properties": {
    "iso:country":"US",
    "sg:address":"534 Chester Ave",
    "sg:city":"Phoenixville",
    "sg:classifiers":[
        {
            "category":"Wholesale",
            "subcategory":"Machinery & Supplies",
            "type":"Manufacturing & Wholesale Goods"
        }
    ],
    "sg:phone":"+1   ",
    "sg:postcode":"19460",
    "sg:province":"PA",
    "sg:tags":[
        "retail",
        "installation",
        "carpet"
    ],
    "wof:name":"Jebb Casrpet Installation",
    "wof:placetype":"venue"
},
  "geometry": {"coordinates":[-75.526763,40.124387],"type":"Point"}
}