{
  "type": "Feature",
  "properties": {
    "addr:full":"1372 Columbia Ave Lancaster PA 17603",
    "addr:housenumber":"1372",
    "addr:postcode":"17603",
    "addr:street":"Columbia Ave",
    "iso:country":"US",
    "sg:address":"1372 Columbia Ave",
    "sg:city":"Lancaster",
    "sg:classifiers":[
        {
            "category":"Wholesale",
            "subcategory":"Machinery & Supplies",
            "type":"Manufacturing & Wholesale Goods"
        }
    ],
    "sg:phone":"+1 717 392 7914",
    "sg:postcode":"17603",
    "sg:province":"PA",
    "sg:tags":[
        "salon",
        "beauty"
    ],
    "wof:name":"Kresge Beauty Supply",
    "wof:placetype":"venue"
},
  "geometry": {"coordinates":[-76.336573,40.03843],"type":"Point"}
}