{
  "type": "Feature",
  "properties": {
    "iso:country":"US",
    "sg:address":"1140 Delene Rd",
    "sg:city":"Jenkintown",
    "sg:classifiers":[
        {
            "category":"Local Transit",
            "type":"Transportation"
        }
    ],
    "sg:phone":"+1 215 886 0770",
    "sg:postcode":"19046",
    "sg:province":"PA",
    "sg:tags":[
        "airport"
    ],
    "wof:name":"Limo 2000",
    "wof:placetype":"venue"
},
  "geometry": {"coordinates":[-75.105904,40.09869],"type":"Point"}
}