{
  "type": "Feature",
  "properties": {
    "iso:country":"US",
    "sg:address":"8630 Ridge Ave",
    "sg:city":"Philadelphia",
    "sg:classifiers":[
        {
            "category":"Organizations",
            "subcategory":"Religious Organization",
            "type":"Services"
        }
    ],
    "sg:phone":"+1 215 483 5756",
    "sg:postcode":"19128",
    "sg:province":"PA",
    "sg:tags":[
        "church"
    ],
    "wof:name":"Christ Catholic Church",
    "wof:placetype":"venue"
},
  "geometry": {"coordinates":[-75.23989400000001,40.064787],"type":"Point"}
}