{
  "type": "Feature",
  "properties": {
    "iso:country":"US",
    "sg:address":"1025 Progress Rd",
    "sg:city":"Chambersburg",
    "sg:classifiers":[
        {
            "category":"Home & Garden",
            "subcategory":"Carpets & Floor Coverings",
            "type":"Retail Goods"
        }
    ],
    "sg:phone":"+1 717 263 0922",
    "sg:postcode":"17201",
    "sg:province":"PA",
    "sg:tags":[
        "material"
    ],
    "wof:name":"G & G Millworks & Flooring",
    "wof:placetype":"venue"
},
  "geometry": {"coordinates":[-77.66992500000001,39.920564],"type":"Point"}
}