{
  "type": "Feature",
  "properties": {
    "iso:country":"US",
    "sg:address":"1301 Lancaster Ave Ste 4",
    "sg:city":"Berwyn",
    "sg:classifiers":[
        {
            "category":"Real Estate",
            "subcategory":"Real Estate Services",
            "type":"Services"
        },
        {
            "category":"Real Estate",
            "subcategory":"Real Estate Agent",
            "type":"Services"
        }
    ],
    "sg:phone":"+1 610 644 7979",
    "sg:postcode":"19312",
    "sg:province":"PA",
    "sg:tags":[
        "buyer",
        "management",
        "broker"
    ],
    "sg:website":"http://www.brandolinicompanies.com",
    "wof:name":"Brandolini Companies, Inc.",
    "wof:placetype":"venue"
},
  "geometry": {"coordinates":[-75.457578,40.042812],"type":"Point"}
}