{
  "type": "Feature",
  "properties": {
    "iso:country":"US",
    "sg:address":"209 Catharine St",
    "sg:city":"Philadelphia",
    "sg:classifiers":[
        {
            "category":"Professional",
            "subcategory":"Employment Agencies",
            "type":"Services"
        }
    ],
    "sg:phone":"+1 215 925 3870",
    "sg:postcode":"19147",
    "sg:province":"PA",
    "sg:tags":[
        "consultants-referral"
    ],
    "wof:name":"Occupational Health Cnsltn Svc",
    "wof:placetype":"venue"
},
  "geometry": {"coordinates":[-75.146957,39.937691],"type":"Point"}
}