{
  "type": "Feature",
  "properties": {
    "addr:full":"6400 Chambers Hill Rd Harrisburg PA 17111",
    "addr:housenumber":"6400",
    "addr:postcode":"17111",
    "addr:street":"Chambers Hill Rd",
    "iso:country":"US",
    "sg:address":"6400 Chambers Hill Rd",
    "sg:city":"Harrisburg",
    "sg:classifiers":[
        {
            "category":"Organizations",
            "subcategory":"Professional Association",
            "type":"Services"
        }
    ],
    "sg:phone":"+1 717 564 8839",
    "sg:postcode":"17111",
    "sg:province":"PA",
    "wof:name":"Chambers Hill Community Assn",
    "wof:placetype":"venue"
},
  "geometry": {"coordinates":[-76.77704,40.255403],"type":"Point"}
}