{
  "type": "Feature",
  "properties": {
    "iso:country":"US",
    "sg:address":"1200 Northampton St",
    "sg:city":"Easton",
    "sg:classifiers":[
        {
            "category":"Restaurant",
            "type":"Food & Drink"
        }
    ],
    "sg:phone":"+1 610 330 6990",
    "sg:postcode":"18042",
    "sg:province":"PA",
    "wof:name":"House Of Chen's",
    "wof:placetype":"venue"
},
  "geometry": {"coordinates":[-75.227232,40.690369],"type":"Point"}
}