{
  "type": "Feature",
  "properties": {
    "addr:full":"211 Scott Dr Monroeville PA 15146",
    "addr:housenumber":"211",
    "addr:postcode":"15146",
    "addr:street":"Scott Dr",
    "iso:country":"US",
    "sg:address":"211 Scott Dr",
    "sg:city":"Monroeville",
    "sg:classifiers":[
        {
            "category":"Manufacturing",
            "subcategory":"Apparel",
            "type":"Manufacturing & Wholesale Goods"
        }
    ],
    "sg:phone":"+1   ",
    "sg:postcode":"15146",
    "sg:province":"PA",
    "sg:tags":[
        "stitching",
        "pleating"
    ],
    "wof:name":"Thread Concepts",
    "wof:placetype":"venue"
},
  "geometry": {"coordinates":[-79.750827,40.440834],"type":"Point"}
}