{
  "type": "Feature",
  "properties": {
    "iso:country":"US",
    "sg:address":"1933 Clearview Ave",
    "sg:city":"Norristown",
    "sg:classifiers":[
        {
            "category":"Education",
            "subcategory":"Music School",
            "type":"Public Place"
        }
    ],
    "sg:phone":"+1 610 986 8379",
    "sg:postcode":"19403",
    "sg:province":"PA",
    "sg:tags":[
        "instrument",
        "teacher",
        "musical"
    ],
    "sg:website":"www.jgammuto.com",
    "wof:name":"Gammuto Stringed Instruments",
    "wof:placetype":"venue"
},
  "geometry": {"coordinates":[-75.369146,40.137131],"type":"Point"}
}