{
  "type": "Feature",
  "properties": {
    "iso:country":"US",
    "sg:address":"662 Main St",
    "sg:city":"Johnstown",
    "sg:classifiers":[
        {
            "category":"Retail",
            "subcategory":"Funeral Services",
            "type":"Services"
        }
    ],
    "sg:phone":"+1   ",
    "sg:postcode":"15901",
    "sg:province":"PA",
    "sg:tags":[
        "home"
    ],
    "wof:name":"Gordon Pauline H L Mortuary",
    "wof:placetype":"venue"
},
  "geometry": {"coordinates":[-78.91393100000001,40.323412],"type":"Point"}
}