{
  "type": "Feature",
  "properties": {
    "addr:full":"387 Ben Franklin Hwy W Douglassville PA 19518",
    "addr:housenumber":"387",
    "addr:postcode":"19518",
    "addr:street":"Ben Franklin Hwy W",
    "iso:country":"US",
    "sg:address":"387 Ben Franklin Hwy W",
    "sg:city":"Douglassville",
    "sg:classifiers":[
        {
            "category":"Travel",
            "subcategory":"Hotels & Motels",
            "type":"Entertainment"
        }
    ],
    "sg:phone":"+1 610 385 3016",
    "sg:postcode":"19518",
    "sg:province":"PA",
    "wof:name":"Econo Lodge",
    "wof:placetype":"venue"
},
  "geometry": {"coordinates":[-75.769882,40.270475],"type":"Point"}
}