{
  "type": "Feature",
  "properties": {
    "iso:country":"US",
    "sg:address":"200 Crest St",
    "sg:city":"Clairton",
    "sg:classifiers":[
        {
            "category":"Organizations",
            "subcategory":"Religious Organization",
            "type":"Services"
        }
    ],
    "sg:phone":"+1   ",
    "sg:postcode":"15025",
    "sg:province":"PA",
    "wof:name":"Gethsemane Church God & Christ",
    "wof:placetype":"venue"
},
  "geometry": {"coordinates":[-79.87786699999999,40.296644],"type":"Point"}
}