{
  "type": "Feature",
  "properties": {
    "addr:full":"115 Wenchoff Rd Fairfield PA 17320",
    "addr:housenumber":"115",
    "addr:postcode":"17320",
    "addr:street":"Wenchoff Rd",
    "iso:country":"US",
    "sg:address":"115 Wenchoff Rd",
    "sg:city":"Fairfield",
    "sg:classifiers":[
        {
            "category":"Professional",
            "type":"Services"
        }
    ],
    "sg:phone":"+1   ",
    "sg:postcode":"17320",
    "sg:province":"PA",
    "wof:name":"Arcade Joe",
    "wof:placetype":"venue"
},
  "geometry": {"coordinates":[-77.31685299999999,39.749104],"type":"Point"}
}