{
  "type": "Feature",
  "properties": {
    "iso:country":"US",
    "sg:address":"1401 Freeport Rd",
    "sg:city":"Creighton",
    "sg:classifiers":[
        {
            "category":"Social Services",
            "type":"Services"
        }
    ],
    "sg:phone":"+1   ",
    "sg:postcode":"15030",
    "sg:province":"PA",
    "wof:name":"Colen Victor Msw",
    "wof:placetype":"venue"
},
  "geometry": {"coordinates":[-79.77687299999999,40.586191],"type":"Point"}
}