{
  "type": "Feature",
  "properties": {
    "addr:full":"230 N Craig St Pittsburgh PA 15213",
    "addr:housenumber":"230",
    "addr:postcode":"15213",
    "addr:street":"N Craig St",
    "iso:country":"US",
    "sg:address":"230 N Craig St",
    "sg:city":"Pittsburgh",
    "sg:classifiers":[
        {
            "category":"Health Services",
            "subcategory":"Doctor",
            "type":"Services"
        }
    ],
    "sg:phone":"+1   ",
    "sg:postcode":"15213",
    "sg:province":"PA",
    "sg:tags":[
        "medical"
    ],
    "wof:name":"Jeremy S Musher",
    "wof:placetype":"venue"
},
  "geometry": {"coordinates":[-79.95159,40.451277],"type":"Point"}
}