{
  "type": "Feature",
  "properties": {
    "iso:country":"US",
    "sg:address":"7553 Hamilton Ave",
    "sg:city":"Pittsburgh",
    "sg:classifiers":[
        {
            "category":"Retail",
            "subcategory":"Car Wash",
            "type":"Services"
        }
    ],
    "sg:phone":"+1 412 241 9316",
    "sg:postcode":"15208",
    "sg:province":"PA",
    "sg:tags":[
        "polishing",
        "washing"
    ],
    "wof:name":"Mac's",
    "wof:placetype":"venue"
},
  "geometry": {"coordinates":[-79.892472,40.453568],"type":"Point"}
}