{
  "type": "Feature",
  "properties": {
    "iso:country":"US",
    "sg:address":"3365 Lycoming Creek Rd",
    "sg:city":"Williamsport",
    "sg:classifiers":[
        {
            "category":"Shopping",
            "subcategory":"Discount & Variety Stores",
            "type":"Retail Goods"
        }
    ],
    "sg:phone":"+1 570 494 4119",
    "sg:postcode":"17701",
    "sg:province":"PA",
    "sg:tags":[
        "merchandise",
        "general"
    ],
    "wof:name":"Surplus City Inc",
    "wof:placetype":"venue"
},
  "geometry": {"coordinates":[-77.057436,41.29239],"type":"Point"}
}