{
  "type": "Feature",
  "properties": {
    "iso:country":"US",
    "sg:address":"138 Churchtown Rd",
    "sg:city":"Narvon",
    "sg:classifiers":[
        {
            "category":"Building & Trades",
            "subcategory":"Landscaping Services",
            "type":"Services"
        }
    ],
    "sg:phone":"+1 717 768 0735",
    "sg:postcode":"17555",
    "sg:province":"PA",
    "wof:name":"Green Care Maintenance",
    "wof:placetype":"venue"
},
  "geometry": {"coordinates":[-75.954865,40.037783],"type":"Point"}
}