{
  "type": "Feature",
  "properties": {
    "iso:country":"US",
    "sg:address":"75 Palmer Industrial Rd",
    "sg:city":"Williamsport",
    "sg:classifiers":[
        {
            "category":"Shopping",
            "type":"Retail Goods"
        }
    ],
    "sg:phone":"+1 570 323 3060",
    "sg:postcode":"17701",
    "sg:province":"PA",
    "sg:tags":[
        "spa",
        "hot",
        "tub"
    ],
    "sg:website":"www.pdcspas.com",
    "wof:name":"PDC Spas",
    "wof:placetype":"venue"
},
  "geometry": {"coordinates":[-77.09324700000001,41.231343],"type":"Point"}
}