{
  "type": "Feature",
  "properties": {
    "addr:full":"354 Pondview Dr Harleysville PA 19438",
    "addr:housenumber":"354",
    "addr:postcode":"19438",
    "addr:street":"Pondview Dr",
    "iso:country":"US",
    "sg:address":"354 Pondview Dr",
    "sg:city":"Harleysville",
    "sg:classifiers":[
        {
            "category":"Food & Beverages",
            "subcategory":"Specialty",
            "type":"Retail Goods"
        }
    ],
    "sg:phone":"+1   ",
    "sg:postcode":"19438",
    "sg:province":"PA",
    "wof:name":"Shaklee Distributor",
    "wof:placetype":"venue"
},
  "geometry": {"coordinates":[-75.384648,40.269506],"type":"Point"}
}