{
  "type": "Feature",
  "properties": {
    "addr:full":"54 Messenger St Johnstown PA 15902",
    "addr:housenumber":"54",
    "addr:postcode":"15902",
    "addr:street":"Messenger St",
    "iso:country":"US",
    "sg:address":"54 Messenger St",
    "sg:city":"Johnstown",
    "sg:classifiers":[
        {
            "category":"Railroad",
            "type":"Transportation"
        }
    ],
    "sg:phone":"+1   ",
    "sg:postcode":"15902",
    "sg:province":"PA",
    "wof:name":"CSX Transportation Inc",
    "wof:placetype":"venue"
},
  "geometry": {"coordinates":[-78.91353100000001,40.309013],"type":"Point"}
}