{
  "type": "Feature",
  "properties": {
    "addr:full":"714 South Ave Pittsburgh PA 15221",
    "addr:housenumber":"714",
    "addr:postcode":"15221",
    "addr:street":"South Ave",
    "iso:country":"US",
    "sg:address":"714 South Ave",
    "sg:city":"Pittsburgh",
    "sg:classifiers":[
        {
            "category":"Health Services",
            "subcategory":"Doctor",
            "type":"Services"
        }
    ],
    "sg:phone":"+1   ",
    "sg:postcode":"15221",
    "sg:province":"PA",
    "wof:name":"Edward Cheppa DMD",
    "wof:placetype":"venue"
},
  "geometry": {"coordinates":[-79.88548900000001,40.441977],"type":"Point"}
}