{
  "type": "Feature",
  "properties": {
    "addr:full":"2020 Boltz Ln Lebanon PA 17046",
    "addr:housenumber":"2020",
    "addr:postcode":"17046",
    "addr:street":"Boltz Ln",
    "iso:country":"US",
    "sg:address":"2020 Boltz Ln",
    "sg:city":"Lebanon",
    "sg:classifiers":[
        {
            "category":"Building & Trades",
            "subcategory":"Electrical",
            "type":"Services"
        }
    ],
    "sg:phone":"+1 717 679 0684",
    "sg:postcode":"17046",
    "sg:province":"PA",
    "sg:tags":[
        "electrical",
        "contractor"
    ],
    "wof:name":"Reager Electric",
    "wof:placetype":"venue"
},
  "geometry": {"coordinates":[-76.493163,40.37969],"type":"Point"}
}