{
  "type": "Feature",
  "properties": {
    "iso:country":"US",
    "sg:address":"1530 Harvey Run Rd",
    "sg:city":"Freedom",
    "sg:classifiers":[
        {
            "category":"Bars & Pubs",
            "type":"Food & Drink"
        }
    ],
    "sg:phone":"+1 724 728 5412",
    "sg:postcode":"15042",
    "sg:province":"PA",
    "sg:tags":[
        "drinking"
    ],
    "wof:name":"Harvey Run Inn",
    "wof:placetype":"venue"
},
  "geometry": {"coordinates":[-80.23653299999999,40.684135],"type":"Point"}
}