{
  "type": "Feature",
  "properties": {
    "iso:country":"US",
    "sg:address":"333 Broad St",
    "sg:city":"Montoursville",
    "sg:classifiers":[
        {
            "category":"Health Services",
            "subcategory":"Chiropractor",
            "type":"Services"
        }
    ],
    "sg:phone":"+1 570 368 2897",
    "sg:postcode":"17754",
    "sg:province":"PA",
    "wof:name":"Chiropractic Center",
    "wof:placetype":"venue"
},
  "geometry": {"coordinates":[-76.92643099999999,41.249651],"type":"Point"}
}