{
  "type": "Feature",
  "properties": {
    "iso:country":"US",
    "sg:address":"500 Grant St Ste 5000",
    "sg:city":"Pittsburgh",
    "sg:classifiers":[
        {
            "category":"Professional",
            "subcategory":"Lawyer & Legal Services",
            "type":"Services"
        }
    ],
    "sg:phone":"+1 412 454 5000",
    "sg:postcode":"15219",
    "sg:province":"PA",
    "wof:name":"Pepper Hamilton Llp",
    "wof:placetype":"venue"
},
  "geometry": {"coordinates":[-79.995955,40.439641],"type":"Point"}
}