{
  "type": "Feature",
  "properties": {
    "addr:full":"43 S Main St Ashley PA 18706",
    "addr:housenumber":"43",
    "addr:postcode":"18706",
    "addr:street":"S Main St",
    "iso:country":"US",
    "sg:address":"43 S Main St",
    "sg:city":"Ashley",
    "sg:classifiers":[
        {
            "category":"Shopping",
            "subcategory":"Department Store",
            "type":"Retail Goods"
        }
    ],
    "sg:phone":"+1 570 821 7052",
    "sg:postcode":"18706",
    "sg:province":"PA",
    "sg:tags":[
        "variety"
    ],
    "sg:website":"http://www.familydollar.com",
    "wof:name":"Family Dollar",
    "wof:placetype":"venue"
},
  "geometry": {"coordinates":[-75.901358,41.211449],"type":"Point"}
}