{
  "type": "Feature",
  "properties": {
    "iso:country":"US",
    "sg:address":"2555 Pottstown Pike",
    "sg:city":"Pottstown",
    "sg:classifiers":[
        {
            "category":"Home & Garden",
            "subcategory":"Household Appliances",
            "type":"Retail Goods"
        }
    ],
    "sg:phone":"+1 610 469 6200",
    "sg:postcode":"19465",
    "sg:province":"PA",
    "sg:tags":[
        "lawn",
        "electric",
        "supply"
    ],
    "sg:website":"www.prizers.com",
    "wof:name":"Prizers Inc",
    "wof:placetype":"venue"
},
  "geometry": {"coordinates":[-75.670204,40.161766],"type":"Point"}
}