{
  "type": "Feature",
  "properties": {
    "addr:full":"1494 N Charlotte St Pottstown PA 19464",
    "addr:housenumber":"1494",
    "addr:postcode":"19464",
    "addr:street":"N Charlotte St",
    "iso:country":"US",
    "sg:address":"1494 N Charlotte St",
    "sg:city":"Pottstown",
    "sg:classifiers":[
        {
            "category":"Professional",
            "subcategory":"Art Services",
            "type":"Services"
        },
        {
            "category":"Manufacturing",
            "subcategory":"Printing",
            "type":"Manufacturing & Wholesale Goods"
        }
    ],
    "sg:phone":"+1 484 941 0975",
    "sg:postcode":"19464",
    "sg:province":"PA",
    "sg:tags":[
        "commercial",
        "screen",
        "design"
    ],
    "wof:name":"Infinite Graphic Imaging",
    "wof:placetype":"venue"
},
  "geometry": {"coordinates":[-75.62475999999999,40.268274],"type":"Point"}
}