{
  "type": "Feature",
  "properties": {
    "iso:country":"US",
    "sg:address":"141 Tiffany Ln",
    "sg:city":"Gettysburg",
    "sg:classifiers":[
        {
            "category":"Professional",
            "subcategory":"Detective & Security Services",
            "type":"Services"
        }
    ],
    "sg:phone":"+1 717 334 4974",
    "sg:postcode":"17325",
    "sg:province":"PA",
    "sg:tags":[
        "information",
        "bureau"
    ],
    "wof:name":"Beauchat Consulting Services",
    "wof:placetype":"venue"
},
  "geometry": {"coordinates":[-77.265456,39.83448],"type":"Point"}
}