{
  "type": "Feature",
  "properties": {
    "iso:country":"US",
    "sg:address":"901 N Meadow St",
    "sg:city":"Allentown",
    "sg:classifiers":[
        {
            "category":"Building & Trades",
            "subcategory":"Construction",
            "type":"Services"
        }
    ],
    "sg:phone":"+1 610 774 0207",
    "sg:postcode":"18102",
    "sg:province":"PA",
    "sg:tags":[
        "contractor"
    ],
    "wof:name":"Coyote Construction",
    "wof:placetype":"venue"
},
  "geometry": {"coordinates":[-75.469902,40.618099],"type":"Point"}
}