{
  "type": "Feature",
  "properties": {
    "iso:country":"US",
    "sg:address":"1207 Chestnut St",
    "sg:city":"Philadelphia",
    "sg:classifiers":[
        {
            "category":"Shopping",
            "subcategory":"Clothing, Apparel, & Fashions",
            "type":"Retail Goods"
        }
    ],
    "sg:phone":"+1 215 751 0013",
    "sg:postcode":"19107",
    "sg:province":"PA",
    "sg:tags":[
        "apparel",
        "accessory",
        "clothing",
        "women's"
    ],
    "wof:name":"Easy Pickins Inc",
    "wof:placetype":"venue"
},
  "geometry": {"coordinates":[-75.160301,39.9505],"type":"Point"}
}