{
  "type": "Feature",
  "properties": {
    "iso:country":"US",
    "sg:address":"6 Ellsworth Dr",
    "sg:city":"Montrose",
    "sg:classifiers":[
        {
            "category":"Manufacturing",
            "subcategory":"Glass & Minerals",
            "type":"Manufacturing & Wholesale Goods"
        }
    ],
    "sg:phone":"+1 570 278 0333",
    "sg:postcode":"18801",
    "sg:province":"PA",
    "sg:tags":[
        "stone",
        "cutter"
    ],
    "wof:name":"Miles Supply Pa",
    "wof:placetype":"venue"
},
  "geometry": {"coordinates":[-75.886154,41.803112],"type":"Point"}
}