{
  "type": "Feature",
  "properties": {
    "iso:country":"US",
    "sg:address":"403 W Main St",
    "sg:city":"Ridgway",
    "sg:classifiers":[
        {
            "category":"Manufacturing",
            "subcategory":"Printing",
            "type":"Manufacturing & Wholesale Goods"
        }
    ],
    "sg:phone":"+1   ",
    "sg:postcode":"15853",
    "sg:province":"PA",
    "sg:tags":[
        "lithographic",
        "commercial"
    ],
    "wof:name":"McKay Printing",
    "wof:placetype":"venue"
},
  "geometry": {"coordinates":[-78.744716,41.420758],"type":"Point"}
}