{
  "type": "Feature",
  "properties": {
    "iso:country":"US",
    "sg:address":"343 Old Babcock Trl",
    "sg:city":"Gibsonia",
    "sg:classifiers":[
        {
            "category":"Real Estate",
            "subcategory":"Real Estate Agent",
            "type":"Services"
        }
    ],
    "sg:phone":"+1 724 444 5757",
    "sg:postcode":"15044",
    "sg:province":"PA",
    "wof:name":"Cornelius Appraisal One",
    "wof:placetype":"venue"
},
  "geometry": {"coordinates":[-79.995465,40.599574],"type":"Point"}
}