{
  "type": "Feature",
  "properties": {
    "addr:full":"209 W Lincoln Ave New Castle PA 16101",
    "addr:housenumber":"209",
    "addr:postcode":"16101",
    "addr:street":"W Lincoln Ave",
    "iso:country":"US",
    "sg:address":"209 W Lincoln Ave",
    "sg:city":"New Castle",
    "sg:classifiers":[
        {
            "category":"Government",
            "subcategory":"Office",
            "type":"Public Place"
        }
    ],
    "sg:phone":"+1   ",
    "sg:postcode":"16101",
    "sg:province":"PA",
    "sg:tags":[
        "housing",
        "program"
    ],
    "wof:name":"Lincoln Terrace",
    "wof:placetype":"venue"
},
  "geometry": {"coordinates":[-80.350988,41.005256],"type":"Point"}
}