{
  "type": "Feature",
  "properties": {
    "iso:country":"US",
    "sg:address":"317 W County Line Rd",
    "sg:city":"Hatboro",
    "sg:classifiers":[
        {
            "category":"Wholesale",
            "subcategory":"Machinery & Supplies",
            "type":"Manufacturing & Wholesale Goods"
        },
        {
            "category":"Personal",
            "subcategory":"Beauty Salon",
            "type":"Services"
        }
    ],
    "sg:phone":"+1 215 674 8422",
    "sg:postcode":"19040",
    "sg:province":"PA",
    "sg:tags":[
        "equipment",
        "establishment"
    ],
    "wof:name":"Kim's Coiffures",
    "wof:placetype":"venue"
},
  "geometry": {"coordinates":[-75.12275,40.201729],"type":"Point"}
}