{
  "type": "Feature",
  "properties": {
    "iso:country":"US",
    "sg:address":"300 E Lancaster Ave",
    "sg:city":"Wynnewood",
    "sg:classifiers":[
        {
            "category":"Health Services",
            "subcategory":"Doctor",
            "type":"Services"
        }
    ],
    "sg:phone":"+1 610 645 0525",
    "sg:postcode":"19096",
    "sg:province":"PA",
    "wof:name":"Lichtman Craig MD",
    "wof:placetype":"venue"
},
  "geometry": {"coordinates":[-75.264297,39.9925],"type":"Point"}
}