{
  "type": "Feature",
  "properties": {
    "iso:country":"US",
    "sg:address":"78 Summit Ave",
    "sg:city":"Ellwood City",
    "sg:classifiers":[
        {
            "category":"Professional",
            "type":"Services"
        }
    ],
    "sg:phone":"+1   ",
    "sg:postcode":"16117",
    "sg:province":"PA",
    "wof:name":"Bucci & Sons",
    "wof:placetype":"venue"
},
  "geometry": {"coordinates":[-80.28001399999999,40.85254],"type":"Point"}
}