{
  "type": "Feature",
  "properties": {
    "addr:full":"2577 Crum Creek Dr Berwyn PA 19312",
    "addr:housenumber":"2577",
    "addr:postcode":"19312",
    "addr:street":"Crum Creek Dr",
    "iso:country":"US",
    "sg:address":"2577 Crum Creek Dr",
    "sg:city":"Berwyn",
    "sg:classifiers":[
        {
            "category":"Professional",
            "type":"Services"
        }
    ],
    "sg:phone":"+1   ",
    "sg:postcode":"19312",
    "sg:province":"PA",
    "wof:name":"Dunham & Alarie Corporation",
    "wof:placetype":"venue"
},
  "geometry": {"coordinates":[-75.447981,39.999716],"type":"Point"}
}