{
  "type": "Feature",
  "properties": {
    "iso:country":"US",
    "sg:address":"78 Grow Ave",
    "sg:city":"Montrose",
    "sg:classifiers":[
        {
            "category":"Health Services",
            "subcategory":"Health Practitioner",
            "type":"Services"
        }
    ],
    "sg:phone":"+1 570 278 4781",
    "sg:postcode":"18801",
    "sg:province":"PA",
    "sg:tags":[
        "therapist",
        "physical"
    ],
    "wof:name":"Endless Mountain Health System",
    "wof:placetype":"venue"
},
  "geometry": {"coordinates":[-75.86612,41.83603],"type":"Point"}
}