{
  "type": "Feature",
  "properties": {
    "addr:full":"22 Memel Dr Thornton PA 19373",
    "addr:housenumber":"22",
    "addr:postcode":"19373",
    "addr:street":"Memel Dr",
    "iso:country":"US",
    "sg:address":"22 Memel Dr",
    "sg:city":"Thornton",
    "sg:classifiers":[
        {
            "category":"Home & Garden",
            "subcategory":"Building Materials",
            "type":"Retail Goods"
        }
    ],
    "sg:phone":"+1 610 399 6100",
    "sg:postcode":"19373",
    "sg:province":"PA",
    "wof:name":"Ennis Windows",
    "wof:placetype":"venue"
},
  "geometry": {"coordinates":[-75.540205,39.921988],"type":"Point"}
}