{
  "type": "Feature",
  "properties": {
    "iso:country":"US",
    "sg:address":"1000 Conroy Pl",
    "sg:city":"Easton",
    "sg:classifiers":[
        {
            "category":"Manufacturing",
            "subcategory":"Building Materials",
            "type":"Manufacturing & Wholesale Goods"
        }
    ],
    "sg:phone":"+1 610 559 2180",
    "sg:postcode":"18040",
    "sg:province":"PA",
    "sg:tags":[
        "frame",
        "door"
    ],
    "wof:name":"Curries Co",
    "wof:placetype":"venue"
},
  "geometry": {"coordinates":[-75.236394,40.75068],"type":"Point"}
}