{
  "type": "Feature",
  "properties": {
    "iso:country":"US",
    "sg:address":"1222 N Hancock St",
    "sg:city":"Philadelphia",
    "sg:classifiers":[
        {
            "category":"Organizations",
            "subcategory":"Membership Organization",
            "type":"Services"
        }
    ],
    "sg:phone":"+1   ",
    "sg:postcode":"19122",
    "sg:province":"PA",
    "wof:name":"Gold Star Wives of America",
    "wof:placetype":"venue"
},
  "geometry": {"coordinates":[-75.13831,39.970464],"type":"Point"}
}