{
  "type": "Feature",
  "properties": {
    "addr:full":"300 S Pugh St State College PA 16801",
    "addr:housenumber":"300",
    "addr:postcode":"16801",
    "addr:street":"S Pugh St",
    "iso:country":"US",
    "sg:address":"300 S Pugh St",
    "sg:city":"State College",
    "sg:classifiers":[
        {
            "category":"Insurance",
            "subcategory":"Life Insurance",
            "type":"Services"
        }
    ],
    "sg:phone":"+1   ",
    "sg:postcode":"16801",
    "sg:province":"PA",
    "sg:tags":[
        "carrier"
    ],
    "wof:name":"Elsie Fairchild",
    "wof:placetype":"venue"
},
  "geometry": {"coordinates":[-77.856847,40.793119],"type":"Point"}
}