{
  "type": "Feature",
  "properties": {
    "iso:country":"US",
    "sg:address":"1239 Providence Rd",
    "sg:city":"Secane",
    "sg:classifiers":[
        {
            "category":"Professional",
            "subcategory":"Business Services",
            "type":"Services"
        }
    ],
    "sg:phone":"+1 610 328 9777",
    "sg:postcode":"19018",
    "sg:province":"PA",
    "sg:tags":[
        "notary"
    ],
    "wof:name":"Stan Park Insurance",
    "wof:placetype":"venue"
},
  "geometry": {"coordinates":[-75.30883300000001,39.915685],"type":"Point"}
}