{
  "type": "Feature",
  "properties": {
    "iso:country":"US",
    "sg:address":"213 Penn St",
    "sg:city":"Point Marion",
    "sg:classifiers":[
        {
            "category":"Insurance",
            "subcategory":"Insurance Agent",
            "type":"Services"
        }
    ],
    "sg:phone":"+1   ",
    "sg:postcode":"15474",
    "sg:province":"PA",
    "wof:name":"Russell Brooks",
    "wof:placetype":"venue"
},
  "geometry": {"coordinates":[-79.90057899999999,39.739426],"type":"Point"}
}