{
  "type": "Feature",
  "properties": {
    "addr:full":"2518 Cedar St Philadelphia PA 19125",
    "addr:housenumber":"2518",
    "addr:postcode":"19125",
    "addr:street":"Cedar St",
    "iso:country":"US",
    "sg:address":"2518 Cedar St",
    "sg:city":"Philadelphia",
    "sg:classifiers":[
        {
            "category":"Real Estate",
            "subcategory":"Real Estate Services",
            "type":"Services"
        },
        {
            "category":"Real Estate",
            "subcategory":"Real Estate Agent",
            "type":"Services"
        }
    ],
    "sg:phone":"+1 215 291 9290",
    "sg:postcode":"19125",
    "sg:province":"PA",
    "sg:tags":[
        "buyer",
        "consultant",
        "broker"
    ],
    "wof:name":"Help U Sell Solutions Real Est",
    "wof:placetype":"venue"
},
  "geometry": {"coordinates":[-75.12181099999999,39.97974],"type":"Point"}
}