{
  "type": "Feature",
  "properties": {
    "addr:full":"531 Hollander Rd New Holland PA 17557",
    "addr:housenumber":"531",
    "addr:postcode":"17557",
    "addr:street":"Hollander Rd",
    "iso:country":"US",
    "sg:address":"531 Hollander Rd",
    "sg:city":"New Holland",
    "sg:classifiers":[
        {
            "category":"Building & Trades",
            "subcategory":"Construction",
            "type":"Services"
        }
    ],
    "sg:phone":"+1   ",
    "sg:postcode":"17557",
    "sg:province":"PA",
    "sg:tags":[
        "foundation",
        "footing",
        "contractor"
    ],
    "wof:name":"Precise Concrete Walls Inc",
    "wof:placetype":"venue"
},
  "geometry": {"coordinates":[-76.09908,40.084828],"type":"Point"}
}