{
  "type": "Feature",
  "properties": {
    "iso:country":"US",
    "sg:address":"445 Fort Pitt Blvd",
    "sg:city":"Pittsburgh",
    "sg:classifiers":[
        {
            "category":"Professional",
            "subcategory":"Lawyer & Legal Services",
            "type":"Services"
        }
    ],
    "sg:phone":"+1 412 471 5707",
    "sg:postcode":"15219",
    "sg:province":"PA",
    "wof:name":"Houston William A Attorney",
    "wof:placetype":"venue"
},
  "geometry": {"coordinates":[-79.999802,40.436298],"type":"Point"}
}