{
  "type": "Feature",
  "properties": {
    "addr:full":"54 N Sheaman Rd White Haven PA 18661",
    "addr:housenumber":"54",
    "addr:postcode":"18661",
    "addr:street":"N Sheaman Rd",
    "iso:country":"US",
    "sg:address":"54 N Sheaman Rd",
    "sg:city":"White Haven",
    "sg:classifiers":[
        {
            "category":"Wholesale",
            "subcategory":"Groceries",
            "type":"Manufacturing & Wholesale Goods"
        }
    ],
    "sg:phone":"+1 570 443 0455",
    "sg:postcode":"18661",
    "sg:province":"PA",
    "sg:tags":[
        "confectionery",
        "candy"
    ],
    "wof:name":"R & K Snacks",
    "wof:placetype":"venue"
},
  "geometry": {"coordinates":[-75.79963600000001,41.043206],"type":"Point"}
}