{
  "type": "Feature",
  "properties": {
    "iso:country":"US",
    "sg:address":"75 E Lancaster Ave",
    "sg:city":"Ardmore",
    "sg:classifiers":[
        {
            "category":"Government",
            "subcategory":"Office",
            "type":"Public Place"
        }
    ],
    "sg:phone":"+1 610 645 6140",
    "sg:postcode":"19003",
    "sg:province":"PA",
    "sg:tags":[
        "city",
        "program"
    ],
    "wof:name":"Lwr Merion Planning & Comm Dev",
    "wof:placetype":"venue"
},
  "geometry": {"coordinates":[-75.256046,39.989384],"type":"Point"}
}