{
  "type": "Feature",
  "properties": {
    "iso:country":"US",
    "sg:address":"82 Industrial Park Dr",
    "sg:city":"Brockway",
    "sg:classifiers":[
        {
            "category":"Manufacturing",
            "subcategory":"Metals",
            "type":"Manufacturing & Wholesale Goods"
        }
    ],
    "sg:phone":"+1 814 265 8771",
    "sg:postcode":"15824",
    "sg:province":"PA",
    "sg:tags":[
        "parts",
        "powder"
    ],
    "sg:website":"www.fallscreekpm.com",
    "wof:name":"Falls Creek Powdered Metal Inc",
    "wof:placetype":"venue"
},
  "geometry": {"coordinates":[-78.802066,41.254752],"type":"Point"}
}