{
  "type": "Feature",
  "properties": {
    "addr:full":"102 Willow Valley Sq Lancaster PA 17602",
    "addr:housenumber":"102",
    "addr:postcode":"17602",
    "addr:street":"Willow Valley Sq",
    "iso:country":"US",
    "sg:address":"102 Willow Valley Sq",
    "sg:city":"Lancaster",
    "sg:classifiers":[
        {
            "category":"Banks & Credit Unions",
            "subcategory":"Bank",
            "type":"Services"
        }
    ],
    "sg:phone":"+1 717 291 2536",
    "sg:postcode":"17602",
    "sg:province":"PA",
    "sg:tags":[
        "state",
        "commercial"
    ],
    "wof:name":"Fulton Bank",
    "wof:placetype":"venue"
},
  "geometry": {"coordinates":[-76.285185,39.997465],"type":"Point"}
}