{
  "type": "Feature",
  "properties": {
    "iso:country":"US",
    "sg:address":"135 W 8th St",
    "sg:city":"Pittsburgh",
    "sg:classifiers":[
        {
            "category":"Banks & Credit Unions",
            "subcategory":"Financial Services",
            "type":"Services"
        }
    ],
    "sg:phone":"+1   ",
    "sg:postcode":"15215",
    "sg:province":"PA",
    "sg:tags":[
        "company",
        "holding"
    ],
    "wof:name":"Campbell Holding Company",
    "wof:placetype":"venue"
},
  "geometry": {"coordinates":[-79.90526300000001,40.495812],"type":"Point"}
}