{
  "type": "Feature",
  "properties": {
    "iso:country":"US",
    "sg:address":"1223 Parks Rd",
    "sg:city":"Irvona",
    "sg:classifiers":[
        {
            "category":"Freight",
            "type":"Transportation"
        }
    ],
    "sg:phone":"+1   ",
    "sg:postcode":"16656",
    "sg:province":"PA",
    "sg:tags":[
        "operator",
        "local",
        "trucking"
    ],
    "wof:name":"L J F Trucking",
    "wof:placetype":"venue"
},
  "geometry": {"coordinates":[-78.572695,40.839298],"type":"Point"}
}