{
  "type": "Feature",
  "properties": {
    "addr:full":"6101 Jacks Hollow Rd Williamsport PA 17702",
    "addr:housenumber":"6101",
    "addr:postcode":"17702",
    "addr:street":"Jacks Hollow Rd",
    "iso:country":"US",
    "sg:address":"6101 Jacks Hollow Rd",
    "sg:city":"Williamsport",
    "sg:classifiers":[
        {
            "category":"Education",
            "subcategory":"School",
            "type":"Public Place"
        }
    ],
    "sg:phone":"+1 570 745 3320",
    "sg:postcode":"17702",
    "sg:province":"PA",
    "sg:tags":[
        "elementary"
    ],
    "wof:name":"Immaculate Conception School",
    "wof:placetype":"venue"
},
  "geometry": {"coordinates":[-77.136646,41.175786],"type":"Point"}
}