{
  "type": "Feature",
  "properties": {
    "addr:full":"300 Meadow Ave Scranton PA 18505",
    "addr:housenumber":"300",
    "addr:postcode":"18505",
    "addr:street":"Meadow Ave",
    "iso:country":"US",
    "sg:address":"300 Meadow Ave",
    "sg:city":"Scranton",
    "sg:classifiers":[
        {
            "category":"Food & Beverages",
            "subcategory":"Groceries & Convenience Stores",
            "type":"Retail Goods"
        }
    ],
    "sg:phone":"+1 570 963 7104",
    "sg:postcode":"18505",
    "sg:province":"PA",
    "sg:tags":[
        "gas"
    ],
    "wof:name":"Meadow Exxon",
    "wof:placetype":"venue"
},
  "geometry": {"coordinates":[-75.652053,41.394683],"type":"Point"}
}