{
  "type": "Feature",
  "properties": {
    "iso:country":"US",
    "sg:address":"1230 Macdade Blvd",
    "sg:city":"Darby",
    "sg:classifiers":[
        {
            "category":"Wholesale",
            "subcategory":"Chemicals & Plastics",
            "type":"Manufacturing & Wholesale Goods"
        }
    ],
    "sg:phone":"+1   ",
    "sg:postcode":"19023",
    "sg:province":"PA",
    "wof:name":"Helium & Balloon Filling Eqp",
    "wof:placetype":"venue"
},
  "geometry": {"coordinates":[-75.285105,39.908146],"type":"Point"}
}