{
  "type": "Feature",
  "properties": {
    "addr:full":"6144 Delancey St Philadelphia PA 19143",
    "addr:housenumber":"6144",
    "addr:postcode":"19143",
    "addr:street":"Delancey St",
    "iso:country":"US",
    "sg:address":"6144 Delancey St",
    "sg:city":"Philadelphia",
    "sg:classifiers":[
        {
            "category":"Professional",
            "subcategory":"Detective & Security Services",
            "type":"Services"
        }
    ],
    "sg:phone":"+1 215 476 4461",
    "sg:postcode":"19143",
    "sg:province":"PA",
    "sg:tags":[
        "guard",
        "patrol"
    ],
    "wof:name":"Eagle Eye Security Svc",
    "wof:placetype":"venue"
},
  "geometry": {"coordinates":[-75.24528100000001,39.956318],"type":"Point"}
}