{
  "type": "Feature",
  "properties": {
    "addr:full":"429 Wiley Ave Franklin PA 16323",
    "addr:housenumber":"429",
    "addr:postcode":"16323",
    "addr:street":"Wiley Ave",
    "iso:country":"US",
    "sg:address":"429 Wiley Ave",
    "sg:city":"Franklin",
    "sg:classifiers":[
        {
            "category":"Education",
            "subcategory":"School",
            "type":"Public Place"
        }
    ],
    "sg:phone":"+1 814 432 4919",
    "sg:postcode":"16323",
    "sg:province":"PA",
    "sg:website":"www.vgsd.org",
    "wof:name":"Valley Grove School District",
    "wof:placetype":"venue"
},
  "geometry": {"coordinates":[-79.820801,41.405294],"type":"Point"}
}