{
  "type": "Feature",
  "properties": {
    "addr:full":"1722 Rte 68 New Brighton PA 15066",
    "addr:housenumber":"1722",
    "addr:postcode":"15066",
    "addr:street":"Rte 68",
    "iso:country":"US",
    "sg:address":"1722 Rte 68",
    "sg:city":"New Brighton",
    "sg:classifiers":[
        {
            "category":"Retail",
            "subcategory":"Veterinary Services",
            "type":"Services"
        }
    ],
    "sg:phone":"+1 724 452 6151",
    "sg:postcode":"15066",
    "sg:province":"PA",
    "sg:tags":[
        "veterinarian"
    ],
    "wof:name":"Kaufman's Veterinary Clinic",
    "wof:placetype":"venue"
},
  "geometry": {"coordinates":[-80.18069,40.768319],"type":"Point"}
}