{
  "type": "Feature",
  "properties": {
    "addr:full":"125 Gateway Dr Mechanicsburg PA 17050",
    "addr:housenumber":"125",
    "addr:postcode":"17050",
    "addr:street":"Gateway Dr",
    "iso:country":"US",
    "sg:address":"125 Gateway Dr",
    "sg:city":"Mechanicsburg",
    "sg:classifiers":[
        {
            "category":"Personal",
            "subcategory":"Beauty Salon",
            "type":"Services"
        }
    ],
    "sg:phone":"+1 717 795 8664",
    "sg:postcode":"17050",
    "sg:province":"PA",
    "sg:tags":[
        "shop",
        "manicuring"
    ],
    "wof:name":"Foxy Nails",
    "wof:placetype":"venue"
},
  "geometry": {"coordinates":[-76.981719,40.237681],"type":"Point"}
}