{
  "type": "Feature",
  "properties": {
    "iso:country":"US",
    "sg:address":"2728 S 73rd St",
    "sg:city":"Philadelphia",
    "sg:classifiers":[
        {
            "category":"Organizations",
            "subcategory":"Religious Organization",
            "type":"Services"
        }
    ],
    "sg:phone":"+1 215 727 8300",
    "sg:postcode":"19153",
    "sg:province":"PA",
    "sg:tags":[
        "church"
    ],
    "wof:name":"Saint Irenaeus Rectory",
    "wof:placetype":"venue"
},
  "geometry": {"coordinates":[-75.237978,39.910923],"type":"Point"}
}