{
  "type": "Feature",
  "properties": {
    "addr:full":"26 Main St Walnutport PA 18088",
    "addr:housenumber":"26",
    "addr:postcode":"18088",
    "addr:street":"Main St",
    "iso:country":"US",
    "sg:address":"26 Main St",
    "sg:city":"Walnutport",
    "sg:classifiers":[
        {
            "category":"Professional",
            "subcategory":"Art Services",
            "type":"Services"
        }
    ],
    "sg:phone":"+1 610 653 4492",
    "sg:postcode":"18088",
    "sg:province":"PA",
    "sg:tags":[
        "designer",
        "display",
        "producer"
    ],
    "wof:name":"Amsar Design",
    "wof:placetype":"venue"
},
  "geometry": {"coordinates":[-75.600151,40.75359],"type":"Point"}
}