{
  "type": "Feature",
  "properties": {
    "iso:country":"US",
    "sg:address":"1006 Wood St",
    "sg:city":"Philadelphia",
    "sg:classifiers":[
        {
            "category":"Professional",
            "subcategory":"Computer Services",
            "type":"Services"
        }
    ],
    "sg:phone":"+1 215 923 0599",
    "sg:postcode":"19107",
    "sg:province":"PA",
    "sg:tags":[
        "stereo",
        "installation"
    ],
    "wof:name":"Max Rpm",
    "wof:placetype":"venue"
},
  "geometry": {"coordinates":[-75.15570099999999,39.958099],"type":"Point"}
}