{
  "type": "Feature",
  "properties": {
    "iso:country":"US",
    "sg:address":"354 N Main St",
    "sg:city":"Doylestown",
    "sg:classifiers":[
        {
            "category":"Health Services",
            "subcategory":"Health Practitioner",
            "type":"Services"
        }
    ],
    "sg:phone":"+1   ",
    "sg:postcode":"18901",
    "sg:province":"PA",
    "wof:name":"Lawrence T McGearty",
    "wof:placetype":"venue"
},
  "geometry": {"coordinates":[-75.130717,40.317393],"type":"Point"}
}