{
  "type": "Feature",
  "properties": {
    "addr:full":"400 Northampton St Easton PA 18042",
    "addr:housenumber":"400",
    "addr:postcode":"18042",
    "addr:street":"Northampton St",
    "iso:country":"US",
    "sg:address":"400 Northampton St",
    "sg:city":"Easton",
    "sg:classifiers":[
        {
            "category":"Banks & Credit Unions",
            "subcategory":"Bank",
            "type":"Services"
        }
    ],
    "sg:phone":"+1 610 252 8900",
    "sg:postcode":"18042",
    "sg:province":"PA",
    "sg:tags":[
        "loan",
        "real estate"
    ],
    "wof:name":"Mortgage Now",
    "wof:placetype":"venue"
},
  "geometry": {"coordinates":[-75.213067,40.691049],"type":"Point"}
}