{
  "type": "Feature",
  "properties": {
    "addr:full":"1365 Metro Dr Lebanon PA 17042",
    "addr:postcode":"1365;17042",
    "addr:street":"Metro Dr",
    "iso:country":"US",
    "sg:address":"1365 Metro Dr",
    "sg:city":"Lebanon",
    "sg:classifiers":[
        {
            "category":"Professional",
            "type":"Services"
        }
    ],
    "sg:phone":"+1   ",
    "sg:postcode":"17042",
    "sg:province":"PA",
    "wof:name":"Dones Pascual Inc",
    "wof:placetype":"venue"
},
  "geometry": {"coordinates":[-76.386387,40.341901],"type":"Point"}
}