{
  "type": "Feature",
  "properties": {
    "iso:country":"US",
    "sg:address":"87 Wyoming St",
    "sg:city":"Wilkes Barre",
    "sg:classifiers":[
        {
            "category":"Building & Trades",
            "subcategory":"Construction",
            "type":"Services"
        }
    ],
    "sg:phone":"+1   ",
    "sg:postcode":"18702",
    "sg:province":"PA",
    "sg:tags":[
        "house"
    ],
    "wof:name":"Halls Construction",
    "wof:placetype":"venue"
},
  "geometry": {"coordinates":[-75.916163,41.231443],"type":"Point"}
}