{
  "type": "Feature",
  "properties": {
    "iso:country":"US",
    "sg:address":"102 Bristol Ln",
    "sg:city":"Irwin",
    "sg:classifiers":[
        {
            "category":"Wholesale",
            "subcategory":"Auto Parts",
            "type":"Manufacturing & Wholesale Goods"
        }
    ],
    "sg:phone":"+1   ",
    "sg:postcode":"15642",
    "sg:province":"PA",
    "wof:name":"Milts Service",
    "wof:placetype":"venue"
},
  "geometry": {"coordinates":[-79.679585,40.295987],"type":"Point"}
}