{
  "type": "Feature",
  "properties": {
    "iso:country":"US",
    "sg:address":"3001 W Berks St",
    "sg:city":"Philadelphia",
    "sg:classifiers":[
        {
            "category":"Education",
            "subcategory":"School",
            "type":"Public Place"
        }
    ],
    "sg:phone":"+1 215 684 5085",
    "sg:postcode":"19121",
    "sg:province":"PA",
    "sg:tags":[
        "high",
        "middle",
        "elementary"
    ],
    "sg:website":"www.phila.k12.pa.us",
    "wof:name":"Philadelphia School District",
    "wof:placetype":"venue"
},
  "geometry": {"coordinates":[-75.182844,39.985136],"type":"Point"}
}