{
  "type": "Feature",
  "properties": {
    "iso:country":"US",
    "sg:address":"99 Main St",
    "sg:city":"Tidioute",
    "sg:classifiers":[
        {
            "category":"Travel",
            "subcategory":"Hotels & Motels",
            "type":"Entertainment"
        }
    ],
    "sg:phone":"+1   ",
    "sg:postcode":"16351",
    "sg:province":"PA",
    "sg:tags":[
        "operation",
        "drinking"
    ],
    "wof:name":"Landmark Hotel",
    "wof:placetype":"venue"
},
  "geometry": {"coordinates":[-79.41390199999999,41.682905],"type":"Point"}
}