{
  "type": "Feature",
  "properties": {
    "iso:country":"US",
    "sg:address":"106 S Front St",
    "sg:city":"New Freedom",
    "sg:classifiers":[
        {
            "category":"Bars & Pubs",
            "type":"Food & Drink"
        }
    ],
    "sg:phone":"+1 717 235 2221",
    "sg:postcode":"17349",
    "sg:province":"PA",
    "wof:name":"Hodle Tavern",
    "wof:placetype":"venue"
},
  "geometry": {"coordinates":[-76.70501,39.730168],"type":"Point"}
}