{
  "type": "Feature",
  "properties": {
    "addr:full":"220 S 16th St Ste 3 Philadelphia PA 19102",
    "addr:housenumber":"220",
    "addr:postcode":"19102",
    "addr:street":"S 16Th St Ste 3",
    "iso:country":"US",
    "sg:address":"220 S 16th St Ste 3",
    "sg:city":"Philadelphia",
    "sg:classifiers":[
        {
            "category":"Health Services",
            "subcategory":"Dentist",
            "type":"Services"
        }
    ],
    "sg:phone":"+1 215 735 3660",
    "sg:postcode":"19102",
    "sg:province":"PA",
    "sg:tags":[
        "denture",
        "dentists-prosthodontists",
        "dentists-cosmetic",
        "dentistry"
    ],
    "wof:name":"Brown Stephen Dds",
    "wof:placetype":"venue"
},
  "geometry": {"coordinates":[-75.167669,39.949037],"type":"Point"}
}