{
  "type": "Feature",
  "properties": {
    "iso:country":"US",
    "sg:address":"1601 Paxton St",
    "sg:city":"Harrisburg",
    "sg:classifiers":[
        {
            "category":"Autos & Motor Vehicles",
            "subcategory":"Automobile Sales",
            "type":"Retail Goods"
        }
    ],
    "sg:phone":"+1 717 230 9490",
    "sg:postcode":"17104",
    "sg:province":"PA",
    "sg:tags":[
        "car",
        "dealer"
    ],
    "wof:name":"Net Mark Enterprises Inc",
    "wof:placetype":"venue"
},
  "geometry": {"coordinates":[-76.860281,40.255393],"type":"Point"}
}