{
  "type": "Feature",
  "properties": {
    "iso:country":"US",
    "sg:address":"1135 S Broad St",
    "sg:city":"Philadelphia",
    "sg:classifiers":[
        {
            "category":"Manufacturing",
            "subcategory":"Printing",
            "type":"Manufacturing & Wholesale Goods"
        }
    ],
    "sg:phone":"+1 215 339 5119",
    "sg:postcode":"19147",
    "sg:province":"PA",
    "sg:tags":[
        "newspaper"
    ],
    "wof:name":"Newspaper Stand",
    "wof:placetype":"venue"
},
  "geometry": {"coordinates":[-75.167075,39.935782],"type":"Point"}
}