{
  "type": "Feature",
  "properties": {
    "iso:country":"US",
    "sg:address":"7200 Woolston Ave",
    "sg:city":"Philadelphia",
    "sg:classifiers":[
        {
            "category":"Recreation",
            "type":"Entertainment"
        }
    ],
    "sg:phone":"+1 215 685 3550",
    "sg:postcode":"19138",
    "sg:province":"PA",
    "sg:tags":[
        "center"
    ],
    "wof:name":"Simons Recreation Ctr",
    "wof:placetype":"venue"
},
  "geometry": {"coordinates":[-75.15695599999999,40.062062],"type":"Point"}
}