{
  "type": "Feature",
  "properties": {
    "addr:full":"20480 Route 19 Cranberry Twp PA 16066",
    "addr:housenumber":"20480",
    "addr:postcode":"16066",
    "addr:street":"Route 19",
    "iso:country":"US",
    "sg:address":"20480 Route 19",
    "sg:city":"Cranberry Twp",
    "sg:classifiers":[
        {
            "category":"Shopping",
            "subcategory":"Pharmacy",
            "type":"Retail Goods"
        }
    ],
    "sg:phone":"+1 724 778 8989",
    "sg:postcode":"16066",
    "sg:province":"PA",
    "sg:tags":[
        "drugstore"
    ],
    "sg:website":"www.riteaid.com",
    "wof:name":"Rite Aid Pharmacies",
    "wof:placetype":"venue"
},
  "geometry": {"coordinates":[-80.104226,40.699326],"type":"Point"}
}