{
  "type": "Feature",
  "properties": {
    "iso:country":"US",
    "sg:address":"4560 Wayne Ave",
    "sg:city":"Philadelphia",
    "sg:classifiers":[
        {
            "category":"Retail",
            "subcategory":"Auto Repair",
            "type":"Services"
        }
    ],
    "sg:phone":"+1   ",
    "sg:postcode":"19144",
    "sg:province":"PA",
    "sg:tags":[
        "exhaust"
    ],
    "wof:name":"Jackson C Muff Produtions",
    "wof:placetype":"venue"
},
  "geometry": {"coordinates":[-75.16313100000001,40.022795],"type":"Point"}
}