{
  "type": "Feature",
  "properties": {
    "iso:country":"US",
    "sg:address":"26 Roth Church Rd",
    "sg:city":"Spring Grove",
    "sg:classifiers":[
        {
            "category":"Health Services",
            "subcategory":"Doctor",
            "type":"Services"
        }
    ],
    "sg:phone":"+1   ",
    "sg:postcode":"17362",
    "sg:province":"PA",
    "sg:tags":[
        "dentist"
    ],
    "wof:name":"Family Dentistry",
    "wof:placetype":"venue"
},
  "geometry": {"coordinates":[-76.87867900000001,39.900513],"type":"Point"}
}