{
  "type": "Feature",
  "properties": {
    "iso:country":"US",
    "sg:address":"8137 Grant Rd",
    "sg:city":"Coopersburg",
    "sg:classifiers":[
        {
            "category":"Retail",
            "subcategory":"Auto Repair",
            "type":"Services"
        }
    ],
    "sg:phone":"+1 610 967 6265",
    "sg:postcode":"18036",
    "sg:province":"PA",
    "sg:tags":[
        "repairing",
        "automobile"
    ],
    "wof:name":"Don's Automotive Repair",
    "wof:placetype":"venue"
},
  "geometry": {"coordinates":[-75.418999,40.4804],"type":"Point"}
}