{
  "type": "Feature",
  "properties": {
    "iso:country":"US",
    "sg:address":"1001 W 6th St",
    "sg:city":"Erie",
    "sg:classifiers":[
        {
            "category":"Food & Beverages",
            "subcategory":"Groceries & Convenience Stores",
            "type":"Retail Goods"
        }
    ],
    "sg:phone":"+1 814 454 6966",
    "sg:postcode":"16507",
    "sg:province":"PA",
    "wof:name":"Upper Crust Bakery",
    "wof:placetype":"venue"
},
  "geometry": {"coordinates":[-80.10836399999999,42.12093],"type":"Point"}
}