{
  "type": "Feature",
  "properties": {
    "iso:country":"US",
    "sg:address":"107 French Ln",
    "sg:city":"Zelienople",
    "sg:classifiers":[
        {
            "category":"Professional",
            "subcategory":"Engineering",
            "type":"Services"
        }
    ],
    "sg:phone":"+1 724 452 8242",
    "sg:postcode":"16063",
    "sg:province":"PA",
    "sg:tags":[
        "engineer"
    ],
    "sg:website":"www.wrallp.com",
    "wof:name":"Whitman Requardt & Assoc",
    "wof:placetype":"venue"
},
  "geometry": {"coordinates":[-80.115528,40.75247],"type":"Point"}
}