{
  "type": "Feature",
  "properties": {
    "addr:full":"609 Ogden Ave Clearfield PA 16830",
    "addr:housenumber":"609",
    "addr:postcode":"16830",
    "addr:street":"Ogden Ave",
    "iso:country":"US",
    "sg:address":"609 Ogden Ave",
    "sg:city":"Clearfield",
    "sg:classifiers":[
        {
            "category":"Professional",
            "subcategory":"Business Services",
            "type":"Services"
        }
    ],
    "sg:phone":"+1 814 765 6560",
    "sg:postcode":"16830",
    "sg:province":"PA",
    "sg:tags":[
        "skip",
        "tracing"
    ],
    "wof:name":"Nationwide Bail Bonds",
    "wof:placetype":"venue"
},
  "geometry": {"coordinates":[-78.433984,41.01212],"type":"Point"}
}