{
  "type": "Feature",
  "properties": {
    "iso:country":"US",
    "sg:address":"305 Bridge St",
    "sg:city":"New Cumberland",
    "sg:classifiers":[
        {
            "category":"Restaurant",
            "type":"Food & Drink"
        }
    ],
    "sg:phone":"+1 717 774 5556",
    "sg:postcode":"17070",
    "sg:province":"PA",
    "sg:tags":[
        "tavern",
        "irish"
    ],
    "sg:website":"www.coakleys.com",
    "wof:name":"Coakley's Restaurant & Pub",
    "wof:placetype":"venue"
},
  "geometry": {"coordinates":[-76.864502,40.226601],"type":"Point"}
}