{
  "type": "Feature",
  "properties": {
    "iso:country":"US",
    "sg:address":"11 Lower Mulberry St",
    "sg:city":"Danville",
    "sg:classifiers":[
        {
            "category":"Personal",
            "subcategory":"Beauty Salon",
            "type":"Services"
        }
    ],
    "sg:phone":"+1 570 275 2481",
    "sg:postcode":"17821",
    "sg:province":"PA",
    "wof:name":"Dorothy Doran Beauty Salon",
    "wof:placetype":"venue"
},
  "geometry": {"coordinates":[-76.616449,40.963698],"type":"Point"}
}