{
  "type": "Feature",
  "properties": {
    "addr:full":"2732 Brodhead Rd Aliquippa PA 15001",
    "addr:housenumber":"2732",
    "addr:postcode":"15001",
    "addr:street":"Brodhead Rd",
    "iso:country":"US",
    "sg:address":"2732 Brodhead Rd",
    "sg:city":"Aliquippa",
    "sg:classifiers":[
        {
            "category":"Real Estate",
            "subcategory":"Real Estate Agent",
            "type":"Services"
        }
    ],
    "sg:phone":"+1 724 378 0899",
    "sg:postcode":"15001",
    "sg:province":"PA",
    "wof:name":"Keller Williams Realty",
    "wof:placetype":"venue"
},
  "geometry": {"coordinates":[-80.255869,40.578332],"type":"Point"}
}