{
  "type": "Feature",
  "properties": {
    "iso:country":"US",
    "sg:address":"7901 Bustleton Ave # 307",
    "sg:city":"Philadelphia",
    "sg:classifiers":[
        {
            "category":"Health Services",
            "subcategory":"Doctor",
            "type":"Services"
        }
    ],
    "sg:phone":"+1 215 333 1776",
    "sg:postcode":"19152",
    "sg:province":"PA",
    "sg:tags":[
        "physician",
        "stomach",
        "gastroenterology",
        "surgeons",
        "surgeon",
        "intestines"
    ],
    "sg:website":"http://www.timelinerecruiting.com",
    "wof:name":"Northeast Gastroenterology Associates Inc",
    "wof:placetype":"venue"
},
  "geometry": {"coordinates":[-75.05336,40.056461],"type":"Point"}
}