{
  "type": "Feature",
  "properties": {
    "iso:country":"US",
    "sg:address":"1601 S Valley Forge Rd",
    "sg:city":"Lansdale",
    "sg:classifiers":[
        {
            "category":"Retail",
            "subcategory":"Laundry & Dry Cleaning",
            "type":"Services"
        }
    ],
    "sg:phone":"+1   ",
    "sg:postcode":"19446",
    "sg:province":"PA",
    "sg:tags":[
        "garment",
        "agent"
    ],
    "wof:name":"Marios Dry Cleaning Inc",
    "wof:placetype":"venue"
},
  "geometry": {"coordinates":[-75.31648300000001,40.227298],"type":"Point"}
}