{
  "type": "Feature",
  "properties": {
    "addr:full":"900 Market St Philadelphia PA 19107",
    "addr:housenumber":"900",
    "addr:postcode":"19107",
    "addr:street":"Market St",
    "iso:country":"US",
    "sg:address":"900 Market St",
    "sg:city":"Philadelphia",
    "sg:classifiers":[
        {
            "category":"Restaurant",
            "type":"Food & Drink"
        }
    ],
    "sg:phone":"+1 215 629 1422",
    "sg:postcode":"19107",
    "sg:province":"PA",
    "sg:tags":[
        "caribbean"
    ],
    "wof:name":"Caribbean Delight",
    "wof:placetype":"venue"
},
  "geometry": {"coordinates":[-75.155151,39.951351],"type":"Point"}
}