{
  "type": "Feature",
  "properties": {
    "addr:full":"2801 Frankford Ave Philadelphia PA 19134",
    "addr:housenumber":"2801",
    "addr:postcode":"19134",
    "addr:street":"Frankford Ave",
    "iso:country":"US",
    "sg:address":"2801 Frankford Ave",
    "sg:city":"Philadelphia",
    "sg:classifiers":[
        {
            "category":"Social Services",
            "subcategory":"Child Care",
            "type":"Services"
        }
    ],
    "sg:phone":"+1 215 423 7733",
    "sg:postcode":"19134",
    "sg:province":"PA",
    "sg:tags":[
        "elementary",
        "kindergarten",
        "school",
        "academic"
    ],
    "wof:name":"New Beginnings Head Start",
    "wof:placetype":"venue"
},
  "geometry": {"coordinates":[-75.12020099999999,39.9888],"type":"Point"}
}