{
  "type": "Feature",
  "properties": {
    "addr:full":"44 Jackson Rd Gilbertsville PA 19525",
    "addr:housenumber":"44",
    "addr:postcode":"19525",
    "addr:street":"Jackson Rd",
    "iso:country":"US",
    "sg:address":"44 Jackson Rd",
    "sg:city":"Gilbertsville",
    "sg:classifiers":[
        {
            "category":"Personal",
            "subcategory":"Beauty Salon",
            "type":"Services"
        }
    ],
    "sg:phone":"+1 610 369 3551",
    "sg:postcode":"19525",
    "sg:province":"PA",
    "wof:name":"Tammy Hoffman Beauty Salon",
    "wof:placetype":"venue"
},
  "geometry": {"coordinates":[-75.615846,40.320368],"type":"Point"}
}