{
  "type": "Feature",
  "properties": {
    "iso:country":"US",
    "sg:address":"2301 Freeport Rd",
    "sg:city":"Kittanning",
    "sg:classifiers":[
        {
            "category":"Personal",
            "subcategory":"Beauty Salon",
            "type":"Services"
        }
    ],
    "sg:phone":"+1 724 543 2804",
    "sg:postcode":"16201",
    "sg:province":"PA",
    "wof:name":"Bennett, Mary Bell",
    "wof:placetype":"venue"
},
  "geometry": {"coordinates":[-79.558708,40.80407],"type":"Point"}
}