{
  "type": "Feature",
  "properties": {
    "iso:country":"US",
    "sg:address":"626 Penn Ave",
    "sg:city":"Reading",
    "sg:classifiers":[
        {
            "category":"Personal",
            "subcategory":"Beauty Salon",
            "type":"Services"
        }
    ],
    "sg:phone":"+1   ",
    "sg:postcode":"19611",
    "sg:province":"PA",
    "sg:tags":[
        "shop"
    ],
    "wof:name":"John Hansbury Hair Care Center",
    "wof:placetype":"venue"
},
  "geometry": {"coordinates":[-75.95126500000001,40.335794],"type":"Point"}
}