{
  "type": "Feature",
  "properties": {
    "iso:country":"US",
    "sg:address":"342 Northgate Dr",
    "sg:city":"Warrendale",
    "sg:classifiers":[
        {
            "category":"Building & Trades",
            "subcategory":"Plumbing",
            "type":"Services"
        }
    ],
    "sg:phone":"+1 724 935 1377",
    "sg:postcode":"15086",
    "sg:province":"PA",
    "sg:tags":[
        "heating",
        "contractor"
    ],
    "wof:name":"Jurecko Heating & Cooling",
    "wof:placetype":"venue"
},
  "geometry": {"coordinates":[-80.080764,40.655285],"type":"Point"}
}