{
  "type": "Feature",
  "properties": {
    "iso:country":"US",
    "sg:address":"225 S Chester Rd",
    "sg:city":"Swarthmore",
    "sg:classifiers":[
        {
            "category":"Professional",
            "subcategory":"Computer Services",
            "type":"Services"
        }
    ],
    "sg:phone":"+1   ",
    "sg:postcode":"19081",
    "sg:province":"PA",
    "sg:tags":[
        "related"
    ],
    "wof:name":"Techguides Inc",
    "wof:placetype":"venue"
},
  "geometry": {"coordinates":[-75.351186,39.8978],"type":"Point"}
}