{
  "type": "Feature",
  "properties": {
    "iso:country":"US",
    "sg:address":"580 Flora Ln",
    "sg:city":"York",
    "sg:classifiers":[
        {
            "category":"Building & Trades",
            "subcategory":"Construction",
            "type":"Services"
        }
    ],
    "sg:phone":"+1 717 741 3689",
    "sg:postcode":"17403",
    "sg:province":"PA",
    "sg:tags":[
        "wallpaper"
    ],
    "wof:name":"Robert B Oberlander",
    "wof:placetype":"venue"
},
  "geometry": {"coordinates":[-76.670106,39.900411],"type":"Point"}
}