{
  "type": "Feature",
  "properties": {
    "iso:country":"US",
    "sg:address":"10730 Mount Zion Rd",
    "sg:city":"Glen Rock",
    "sg:classifiers":[
        {
            "category":"Organizations",
            "subcategory":"Religious Organization",
            "type":"Services"
        }
    ],
    "sg:phone":"+1 717 235 0280",
    "sg:postcode":"17327",
    "sg:province":"PA",
    "sg:tags":[
        "church"
    ],
    "wof:name":"Mt Zion-Potosi United Meth",
    "wof:placetype":"venue"
},
  "geometry": {"coordinates":[-76.67535100000001,39.817914],"type":"Point"}
}