{
  "type": "Feature",
  "properties": {
    "addr:full":"18 E Main St Lock Haven PA 17745",
    "addr:housenumber":"18",
    "addr:postcode":"17745",
    "addr:street":"E Main St",
    "iso:country":"US",
    "sg:address":"18 E Main St",
    "sg:city":"Lock Haven",
    "sg:classifiers":[
        {
            "category":"Education",
            "subcategory":"Dance Studio",
            "type":"Public Place"
        }
    ],
    "sg:phone":"+1 570 748 0540",
    "sg:postcode":"17745",
    "sg:province":"PA",
    "sg:tags":[
        "instruction",
        "dancing"
    ],
    "wof:name":"Phillips Fancy Footwork",
    "wof:placetype":"venue"
},
  "geometry": {"coordinates":[-77.446855,41.137198],"type":"Point"}
}