{
  "type": "Feature",
  "properties": {
    "iso:country":"US",
    "sg:address":"1023 Sanlin Dr",
    "sg:city":"Coraopolis",
    "sg:classifiers":[
        {
            "category":"Building & Trades",
            "subcategory":"Construction",
            "type":"Services"
        }
    ],
    "sg:phone":"+1 412 269 1690",
    "sg:postcode":"15108",
    "sg:province":"PA",
    "sg:tags":[
        "contractor"
    ],
    "wof:name":"JMK Energy Management",
    "wof:placetype":"venue"
},
  "geometry": {"coordinates":[-80.208719,40.508813],"type":"Point"}
}