{
  "type": "Feature",
  "properties": {
    "iso:country":"US",
    "sg:address":"3158 Highland Rd",
    "sg:city":"Orefield",
    "sg:classifiers":[
        {
            "category":"Shopping",
            "type":"Retail Goods"
        }
    ],
    "sg:phone":"+1 610 395 8436",
    "sg:postcode":"18069",
    "sg:province":"PA",
    "sg:tags":[
        "mural"
    ],
    "wof:name":"Melicharek Studio & Art",
    "wof:placetype":"venue"
},
  "geometry": {"coordinates":[-75.634998,40.627141],"type":"Point"}
}