{
  "type": "Feature",
  "properties": {
    "addr:full":"20628 Gospel Hill Rd Venango PA 16440",
    "addr:housenumber":"20628",
    "addr:postcode":"16440",
    "addr:street":"Gospel Hill Rd",
    "iso:country":"US",
    "sg:address":"20628 Gospel Hill Rd",
    "sg:city":"Venango",
    "sg:classifiers":[
        {
            "category":"Organizations",
            "subcategory":"Community Association",
            "type":"Services"
        }
    ],
    "sg:phone":"+1 814 398 8214",
    "sg:postcode":"16440",
    "sg:province":"PA",
    "sg:tags":[
        "club"
    ],
    "wof:name":"Veterans Of Foreign Wars",
    "wof:placetype":"venue"
},
  "geometry": {"coordinates":[-80.119658,41.772957],"type":"Point"}
}