{
  "type": "Feature",
  "properties": {
    "iso:country":"US",
    "sg:address":"620 E Mifflin St",
    "sg:city":"Lancaster",
    "sg:classifiers":[
        {
            "category":"Retail",
            "subcategory":"Auto Repair",
            "type":"Services"
        }
    ],
    "sg:phone":"+1 717 394 8061",
    "sg:postcode":"17602",
    "sg:province":"PA",
    "wof:name":"Mifflin Street Garage",
    "wof:placetype":"venue"
},
  "geometry": {"coordinates":[-76.292536,40.038734],"type":"Point"}
}