{
  "type": "Feature",
  "properties": {
    "iso:country":"US",
    "sg:address":"1109 Daniels St",
    "sg:city":"Reading",
    "sg:classifiers":[
        {
            "category":"Professional",
            "type":"Services"
        }
    ],
    "sg:phone":"+1 610 926 7731",
    "sg:postcode":"19605",
    "sg:province":"PA",
    "sg:tags":[
        "establishment"
    ],
    "wof:name":"Italian Language Ctr",
    "wof:placetype":"venue"
},
  "geometry": {"coordinates":[-75.962058,40.396641],"type":"Point"}
}