{
  "type": "Feature",
  "properties": {
    "addr:full":"2600 Eastern Blvd York PA 17402",
    "addr:housenumber":"2600",
    "addr:postcode":"17402",
    "addr:street":"Eastern Blvd",
    "iso:country":"US",
    "sg:address":"2600 Eastern Blvd",
    "sg:city":"York",
    "sg:classifiers":[
        {
            "category":"Professional",
            "type":"Services"
        }
    ],
    "sg:phone":"+1 717 757 1422",
    "sg:postcode":"17402",
    "sg:province":"PA",
    "sg:tags":[
        "establishment"
    ],
    "wof:name":"M & D Controls Co",
    "wof:placetype":"venue"
},
  "geometry": {"coordinates":[-76.675127,39.973019],"type":"Point"}
}