{
  "type": "Feature",
  "properties": {
    "addr:full":"601 Main St Berlin PA 15530",
    "addr:housenumber":"601",
    "addr:postcode":"15530",
    "addr:street":"Main St",
    "iso:country":"US",
    "sg:address":"601 Main St",
    "sg:city":"Berlin",
    "sg:classifiers":[
        {
            "category":"Autos & Motor Vehicles",
            "subcategory":"Automobile Sales",
            "type":"Retail Goods"
        }
    ],
    "sg:phone":"+1   ",
    "sg:postcode":"15530",
    "sg:province":"PA",
    "sg:tags":[
        "used"
    ],
    "wof:name":"Dively Marlin Car Store",
    "wof:placetype":"venue"
},
  "geometry": {"coordinates":[-78.95699999999999,39.920633],"type":"Point"}
}