{
  "type": "Feature",
  "properties": {
    "iso:country":"US",
    "sg:address":"6304 Roosevelt Blvd",
    "sg:city":"Philadelphia",
    "sg:classifiers":[
        {
            "category":"Manufacturing",
            "subcategory":"Furniture",
            "type":"Manufacturing & Wholesale Goods"
        }
    ],
    "sg:phone":"+1 215 533 0703",
    "sg:postcode":"19149",
    "sg:province":"PA",
    "sg:tags":[
        "upholstered",
        "household",
        "store",
        "mfg"
    ],
    "wof:name":"Route One Furniture",
    "wof:placetype":"venue"
},
  "geometry": {"coordinates":[-75.072622,40.034878],"type":"Point"}
}