{
  "type": "Feature",
  "properties": {
    "iso:country":"US",
    "sg:address":"32 Hertzog Dr",
    "sg:city":"Leola",
    "sg:classifiers":[
        {
            "category":"Building & Trades",
            "subcategory":"Plumbing",
            "type":"Services"
        }
    ],
    "sg:phone":"+1   ",
    "sg:postcode":"17540",
    "sg:province":"PA",
    "sg:tags":[
        "contractor"
    ],
    "wof:name":"Imlers Plumbing",
    "wof:placetype":"venue"
},
  "geometry": {"coordinates":[-76.172319,40.092865],"type":"Point"}
}