{
  "type": "Feature",
  "properties": {
    "iso:country":"US",
    "sg:address":"11 Maple Ter",
    "sg:city":"Douglassville",
    "sg:classifiers":[
        {
            "category":"Retail",
            "subcategory":"Portrait Studio",
            "type":"Services"
        }
    ],
    "sg:phone":"+1   ",
    "sg:postcode":"19518",
    "sg:province":"PA",
    "sg:tags":[
        "photo",
        "photography",
        "commercial"
    ],
    "wof:name":"Gene Koch Photographer",
    "wof:placetype":"venue"
},
  "geometry": {"coordinates":[-75.716038,40.245857],"type":"Point"}
}