{
  "type": "Feature",
  "properties": {
    "addr:full":"2517 State Rte 655 Belleville PA 17004",
    "addr:housenumber":"2517",
    "addr:postcode":"17004",
    "addr:street":"State Rte 655",
    "iso:country":"US",
    "sg:address":"2517 State Rte 655",
    "sg:city":"Belleville",
    "sg:classifiers":[
        {
            "category":"Shopping",
            "subcategory":"Discount & Variety Stores",
            "type":"Retail Goods"
        }
    ],
    "sg:phone":"+1 717 483 6662",
    "sg:postcode":"17004",
    "sg:province":"PA",
    "sg:tags":[
        "merchandise",
        "general"
    ],
    "wof:name":"White Hall Store",
    "wof:placetype":"venue"
},
  "geometry": {"coordinates":[-77.77155,40.577057],"type":"Point"}
}