{
  "type": "Feature",
  "properties": {
    "iso:country":"US",
    "sg:address":"900 Tryens Rd",
    "sg:city":"Aston",
    "sg:classifiers":[
        {
            "category":"Freight",
            "type":"Transportation"
        }
    ],
    "sg:phone":"+1 610 459 5593",
    "sg:postcode":"19014",
    "sg:province":"PA",
    "sg:tags":[
        "mover"
    ],
    "wof:name":"HMS Warehouse",
    "wof:placetype":"venue"
},
  "geometry": {"coordinates":[-75.443443,39.869917],"type":"Point"}
}