{
  "type": "Feature",
  "properties": {
    "addr:full":"2438 Bristol Rd Bensalem PA 19020",
    "addr:housenumber":"2438",
    "addr:postcode":"19020",
    "addr:street":"Bristol Rd",
    "iso:country":"US",
    "sg:address":"2438 Bristol Rd",
    "sg:city":"Bensalem",
    "sg:classifiers":[
        {
            "category":"Professional",
            "subcategory":"Management & Consulting",
            "type":"Services"
        }
    ],
    "sg:phone":"+1 215 432 4455",
    "sg:postcode":"19020",
    "sg:province":"PA",
    "sg:tags":[
        "consultant"
    ],
    "wof:name":"Impact Executive Consulting",
    "wof:placetype":"venue"
},
  "geometry": {"coordinates":[-74.933283,40.133481],"type":"Point"}
}