{
  "type": "Feature",
  "properties": {
    "addr:full":"516 Keely Rd Franklin PA 16323",
    "addr:housenumber":"516",
    "addr:postcode":"16323",
    "addr:street":"Keely Rd",
    "iso:country":"US",
    "sg:address":"516 Keely Rd",
    "sg:city":"Franklin",
    "sg:classifiers":[
        {
            "category":"Wholesale",
            "subcategory":"Painting Supplies",
            "type":"Manufacturing & Wholesale Goods"
        },
        {
            "category":"Building & Trades",
            "subcategory":"Construction",
            "type":"Services"
        }
    ],
    "sg:phone":"+1 814 671 6722",
    "sg:postcode":"16323",
    "sg:province":"PA",
    "sg:tags":[
        "altering",
        "paint",
        "remodeling",
        "drywall",
        "contractor"
    ],
    "wof:name":"Matthews Painting",
    "wof:placetype":"venue"
},
  "geometry": {"coordinates":[-79.874566,41.453043],"type":"Point"}
}