{
  "type": "Feature",
  "properties": {
    "iso:country":"US",
    "sg:address":"22 Adams Dr",
    "sg:city":"Cheswick",
    "sg:classifiers":[
        {
            "category":"Coffee & Tea",
            "type":"Food & Drink"
        },
        {
            "category":"Restaurant",
            "type":"Food & Drink"
        }
    ],
    "sg:phone":"+1 724 826 1845",
    "sg:postcode":"15024",
    "sg:province":"PA",
    "sg:tags":[
        "espresso"
    ],
    "sg:website":"http://www.worldcupcafe.org",
    "wof:name":"World Cup Cafe",
    "wof:placetype":"venue"
},
  "geometry": {"coordinates":[-79.843315,40.56173],"type":"Point"}
}