{
  "type": "Feature",
  "properties": {
    "iso:country":"US",
    "sg:address":"15 Church Rd",
    "sg:city":"Hellertown",
    "sg:classifiers":[
        {
            "category":"Building & Trades",
            "subcategory":"Landscaping Services",
            "type":"Services"
        }
    ],
    "sg:phone":"+1   ",
    "sg:postcode":"18055",
    "sg:province":"PA",
    "sg:tags":[
        "landscape"
    ],
    "wof:name":"Paradigm Landscape Concepts LL",
    "wof:placetype":"venue"
},
  "geometry": {"coordinates":[-75.262381,40.601673],"type":"Point"}
}