{
  "type": "Feature",
  "properties": {
    "iso:country":"US",
    "sg:address":"1801 N Broad St",
    "sg:city":"Philadelphia",
    "sg:classifiers":[
        {
            "category":"Professional",
            "type":"Services"
        }
    ],
    "sg:phone":"+1   ",
    "sg:postcode":"19122",
    "sg:province":"PA",
    "wof:name":"Victor Vazquez",
    "wof:placetype":"venue"
},
  "geometry": {"coordinates":[-75.15725399999999,39.981693],"type":"Point"}
}