{
  "type": "Feature",
  "properties": {
    "addr:full":"2280 Quance Rd Waterford PA 16441",
    "addr:housenumber":"2280",
    "addr:postcode":"16441",
    "addr:street":"Quance Rd",
    "iso:country":"US",
    "sg:address":"2280 Quance Rd",
    "sg:city":"Waterford",
    "sg:classifiers":[
        {
            "category":"Building & Trades",
            "subcategory":"Construction",
            "type":"Services"
        }
    ],
    "sg:phone":"+1   ",
    "sg:postcode":"16441",
    "sg:province":"PA",
    "sg:tags":[
        "house"
    ],
    "wof:name":"John Weaver Construction",
    "wof:placetype":"venue"
},
  "geometry": {"coordinates":[-80.05626700000001,41.968733],"type":"Point"}
}