{
  "type": "Feature",
  "properties": {
    "addr:full":"516 Main St Honesdale PA 18431",
    "addr:housenumber":"516",
    "addr:postcode":"18431",
    "addr:street":"Main St",
    "iso:country":"US",
    "sg:address":"516 Main St",
    "sg:city":"Honesdale",
    "sg:classifiers":[
        {
            "category":"Shopping",
            "type":"Retail Goods"
        }
    ],
    "sg:phone":"+1 570 253 3440",
    "sg:postcode":"18431",
    "sg:province":"PA",
    "sg:tags":[
        "farm",
        "equipment",
        "lawn",
        "machinery",
        "garden"
    ],
    "wof:name":"George W Kinsman Inc",
    "wof:placetype":"venue"
},
  "geometry": {"coordinates":[-75.25468100000001,41.570274],"type":"Point"}
}