{
  "type": "Feature",
  "properties": {
    "iso:country":"US",
    "sg:address":"2001 Mission Dr",
    "sg:city":"New Cumberland",
    "sg:classifiers":[
        {
            "category":"Government",
            "subcategory":"Office",
            "type":"Public Place"
        }
    ],
    "sg:phone":"+1   ",
    "sg:postcode":"17070",
    "sg:province":"PA",
    "sg:tags":[
        "general"
    ],
    "wof:name":"Defense Distribution East Cdc",
    "wof:placetype":"venue"
},
  "geometry": {"coordinates":[-76.851703,40.211137],"type":"Point"}
}