{
  "type": "Feature",
  "properties": {
    "addr:full":"2356 Catasauqua Rd Bethlehem PA 18018",
    "addr:housenumber":"2356",
    "addr:postcode":"18018",
    "addr:street":"Catasauqua Rd",
    "iso:country":"US",
    "sg:address":"2356 Catasauqua Rd",
    "sg:city":"Bethlehem",
    "sg:classifiers":[
        {
            "category":"Banks & Credit Unions",
            "subcategory":"Bank",
            "type":"Services"
        }
    ],
    "sg:phone":"+1 610 865 8405",
    "sg:postcode":"18018",
    "sg:province":"PA",
    "wof:name":"Bank Of America",
    "wof:placetype":"venue"
},
  "geometry": {"coordinates":[-75.42733800000001,40.643007],"type":"Point"}
}