{
  "type": "Feature",
  "properties": {
    "iso:country":"US",
    "sg:address":"6392 Heidler Rd",
    "sg:city":"Fairview",
    "sg:classifiers":[
        {
            "category":"Building & Trades",
            "subcategory":"Construction",
            "type":"Services"
        }
    ],
    "sg:phone":"+1   ",
    "sg:postcode":"16415",
    "sg:province":"PA",
    "sg:tags":[
        "contractor"
    ],
    "wof:name":"Scholtz Mark Plastering",
    "wof:placetype":"venue"
},
  "geometry": {"coordinates":[-80.18931000000001,42.03729],"type":"Point"}
}