{
  "type": "Feature",
  "properties": {
    "iso:country":"US",
    "sg:address":"811 Shaw Ave",
    "sg:city":"Lansdale",
    "sg:classifiers":[
        {
            "category":"Bars & Pubs",
            "type":"Food & Drink"
        }
    ],
    "sg:phone":"+1   ",
    "sg:postcode":"19446",
    "sg:province":"PA",
    "sg:tags":[
        "drinking"
    ],
    "wof:name":"Black Magic",
    "wof:placetype":"venue"
},
  "geometry": {"coordinates":[-75.279004,40.249163],"type":"Point"}
}