{
  "type": "Feature",
  "properties": {
    "iso:country":"US",
    "sg:address":"121 Sara Rd",
    "sg:city":"St Marys",
    "sg:classifiers":[
        {
            "category":"Building & Trades",
            "subcategory":"Construction",
            "type":"Services"
        }
    ],
    "sg:phone":"+1 814 834 1200",
    "sg:postcode":"15857",
    "sg:province":"PA",
    "sg:tags":[
        "general",
        "contractor"
    ],
    "wof:name":"Wehler Construction",
    "wof:placetype":"venue"
},
  "geometry": {"coordinates":[-78.55318,41.414013],"type":"Point"}
}