{
  "type": "Feature",
  "properties": {
    "addr:full":"1000 Main St Pittsburgh PA 15215",
    "addr:housenumber":"1000",
    "addr:postcode":"15215",
    "addr:street":"Main St",
    "iso:country":"US",
    "sg:address":"1000 Main St",
    "sg:city":"Pittsburgh",
    "sg:classifiers":[
        {
            "category":"Professional",
            "subcategory":"Computer Services",
            "type":"Services"
        }
    ],
    "sg:phone":"+1   ",
    "sg:postcode":"15215",
    "sg:province":"PA",
    "sg:tags":[
        "design",
        "wed"
    ],
    "wof:name":"Tellusmore Inc",
    "wof:placetype":"venue"
},
  "geometry": {"coordinates":[-79.931737,40.494414],"type":"Point"}
}