{
  "type": "Feature",
  "properties": {
    "addr:full":"251 7th St Exd New Kensington PA 15068",
    "addr:housenumber":"251",
    "addr:postcode":"15068",
    "addr:street":"7Th St Exd",
    "iso:country":"US",
    "sg:address":"251 7th St Exd",
    "sg:city":"New Kensington",
    "sg:classifiers":[
        {
            "category":"Health Services",
            "subcategory":"Doctor",
            "type":"Services"
        }
    ],
    "sg:phone":"+1 724 339 4638",
    "sg:postcode":"15068",
    "sg:province":"PA",
    "sg:tags":[
        "physician",
        "surgeon"
    ],
    "wof:name":"Dutt Vision & Laser",
    "wof:placetype":"venue"
},
  "geometry": {"coordinates":[-79.74106999999999,40.55957],"type":"Point"}
}