{
  "type": "Feature",
  "properties": {
    "iso:country":"US",
    "sg:address":"1081 Hanover St",
    "sg:city":"Wilkes Barre",
    "sg:classifiers":[
        {
            "category":"Shopping",
            "subcategory":"Bicycles & Sporting Goods",
            "type":"Retail Goods"
        }
    ],
    "sg:phone":"+1   ",
    "sg:postcode":"18706",
    "sg:province":"PA",
    "wof:name":"Fire One Firearms Inc",
    "wof:placetype":"venue"
},
  "geometry": {"coordinates":[-75.966241,41.189937],"type":"Point"}
}