{
  "type": "Feature",
  "properties": {
    "addr:full":"1254 Manheim Pike Lancaster PA 17601",
    "addr:housenumber":"1254",
    "addr:postcode":"17601",
    "addr:street":"Manheim Pike",
    "iso:country":"US",
    "sg:address":"1254 Manheim Pike",
    "sg:city":"Lancaster",
    "sg:classifiers":[
        {
            "category":"Autos & Motor Vehicles",
            "subcategory":"Automobile Sales",
            "type":"Retail Goods"
        }
    ],
    "sg:phone":"+1 717 393 9133",
    "sg:postcode":"17601",
    "sg:province":"PA",
    "sg:tags":[
        "car",
        "dealer"
    ],
    "wof:name":"J D Byrider Auto Sales",
    "wof:placetype":"venue"
},
  "geometry": {"coordinates":[-76.323054,40.06245],"type":"Point"}
}