{
  "type": "Feature",
  "properties": {
    "iso:country":"US",
    "sg:address":"66 Brookline Blvd",
    "sg:city":"Havertown",
    "sg:classifiers":[
        {
            "category":"Building & Trades",
            "subcategory":"Construction",
            "type":"Services"
        }
    ],
    "sg:phone":"+1 610 853 2845",
    "sg:postcode":"19083",
    "sg:province":"PA",
    "sg:tags":[
        "contractor"
    ],
    "wof:name":"J L Creative Builders Inc",
    "wof:placetype":"venue"
},
  "geometry": {"coordinates":[-75.30319799999999,39.979156],"type":"Point"}
}