{
  "type": "Feature",
  "properties": {
    "addr:full":"6233 Market St Philadelphia PA 19139",
    "addr:housenumber":"6233",
    "addr:postcode":"19139",
    "addr:street":"Market St",
    "iso:country":"US",
    "sg:address":"6233 Market St",
    "sg:city":"Philadelphia",
    "sg:classifiers":[
        {
            "category":"Professional",
            "type":"Services"
        }
    ],
    "sg:phone":"+1   ",
    "sg:postcode":"19139",
    "sg:province":"PA",
    "wof:name":"Shakirudeen O Lasisi",
    "wof:placetype":"venue"
},
  "geometry": {"coordinates":[-75.245403,39.962536],"type":"Point"}
}