{
  "type": "Feature",
  "properties": {
    "iso:country":"US",
    "sg:address":"5000 Stonewood Dr Ste 210",
    "sg:city":"Wexford",
    "sg:classifiers":[
        {
            "category":"Insurance",
            "subcategory":"Hazard Insurance",
            "type":"Services"
        },
        {
            "category":"Insurance",
            "subcategory":"Life Insurance",
            "type":"Services"
        }
    ],
    "sg:phone":"+1 724 940 2440",
    "sg:postcode":"15090",
    "sg:province":"PA",
    "sg:tags":[
        "commercial",
        "business"
    ],
    "sg:website":"http://www.prudential.com",
    "wof:name":"Prudential",
    "wof:placetype":"venue"
},
  "geometry": {"coordinates":[-80.064751,40.641762],"type":"Point"}
}