{
  "type": "Feature",
  "properties": {
    "iso:country":"US",
    "sg:address":"729 Park Rd",
    "sg:city":"Fleetwood",
    "sg:classifiers":[
        {
            "category":"Shopping",
            "subcategory":"Bicycles & Sporting Goods",
            "type":"Retail Goods"
        }
    ],
    "sg:phone":"+1 610 944 9565",
    "sg:postcode":"19522",
    "sg:province":"PA",
    "wof:name":"Weaver's Bike Shop",
    "wof:placetype":"venue"
},
  "geometry": {"coordinates":[-75.89816399999999,40.435336],"type":"Point"}
}