{
  "type": "Feature",
  "properties": {
    "iso:country":"US",
    "sg:address":"24 W 21st St",
    "sg:city":"Northampton",
    "sg:classifiers":[
        {
            "category":"Government",
            "subcategory":"Court House",
            "type":"Public Place"
        }
    ],
    "sg:phone":"+1   ",
    "sg:postcode":"18067",
    "sg:province":"PA",
    "sg:tags":[
        "state"
    ],
    "wof:name":"Northampton County Dist Court",
    "wof:placetype":"venue"
},
  "geometry": {"coordinates":[-75.499633,40.690483],"type":"Point"}
}