{
  "type": "Feature",
  "properties": {
    "iso:country":"US",
    "sg:address":"302 S 2nd St",
    "sg:city":"Clearfield",
    "sg:classifiers":[
        {
            "category":"Shopping",
            "subcategory":"Hobbies, Toys, & Games",
            "type":"Retail Goods"
        }
    ],
    "sg:phone":"+1   ",
    "sg:postcode":"16830",
    "sg:province":"PA",
    "wof:name":"Scrapbookers Heaven",
    "wof:placetype":"venue"
},
  "geometry": {"coordinates":[-78.439048,41.016818],"type":"Point"}
}