{
  "type": "Feature",
  "properties": {
    "addr:full":"821 Douglas Dr New Castle PA 16101",
    "addr:housenumber":"821",
    "addr:postcode":"16101",
    "addr:street":"Douglas Dr",
    "iso:country":"US",
    "sg:address":"821 Douglas Dr",
    "sg:city":"New Castle",
    "sg:classifiers":[
        {
            "category":"Building & Trades",
            "subcategory":"Plumbing",
            "type":"Services"
        }
    ],
    "sg:phone":"+1 724 657 1144",
    "sg:postcode":"16101",
    "sg:province":"PA",
    "sg:tags":[
        "plumbing",
        "contractor"
    ],
    "wof:name":"Neely Brother's Plumbing",
    "wof:placetype":"venue"
},
  "geometry": {"coordinates":[-80.284575,40.943981],"type":"Point"}
}