{
  "type": "Feature",
  "properties": {
    "addr:full":"618 W South Ave Glenolden PA 19036",
    "addr:housenumber":"618",
    "addr:postcode":"19036",
    "addr:street":"W South Ave",
    "iso:country":"US",
    "sg:address":"618 W South Ave",
    "sg:city":"Glenolden",
    "sg:classifiers":[
        {
            "category":"Real Estate",
            "subcategory":"Real Estate Agent",
            "type":"Services"
        }
    ],
    "sg:phone":"+1   ",
    "sg:postcode":"19036",
    "sg:province":"PA",
    "wof:name":"Mark A Barone",
    "wof:placetype":"venue"
},
  "geometry": {"coordinates":[-75.30412800000001,39.903225],"type":"Point"}
}