{
  "type": "Feature",
  "properties": {
    "iso:country":"US",
    "sg:address":"2536 Eastern Blvd",
    "sg:city":"York",
    "sg:classifiers":[
        {
            "category":"Shopping",
            "subcategory":"Catalog Store",
            "type":"Retail Goods"
        }
    ],
    "sg:phone":"+1   ",
    "sg:postcode":"17402",
    "sg:province":"PA",
    "sg:tags":[
        "house",
        "mail"
    ],
    "wof:name":"Kraus Press",
    "wof:placetype":"venue"
},
  "geometry": {"coordinates":[-76.673473,39.973035],"type":"Point"}
}