{
  "type": "Feature",
  "properties": {
    "iso:country":"US",
    "sg:address":"5417 Chancellor St",
    "sg:city":"Philadelphia",
    "sg:classifiers":[
        {
            "category":"Building & Trades",
            "subcategory":"Plumbing",
            "type":"Services"
        }
    ],
    "sg:phone":"+1 215 747 4505",
    "sg:postcode":"19139",
    "sg:province":"PA",
    "sg:tags":[
        "plumber",
        "industrial",
        "contractors-commercial"
    ],
    "wof:name":"Rooterman",
    "wof:placetype":"venue"
},
  "geometry": {"coordinates":[-75.229748,39.956899],"type":"Point"}
}