{
  "type": "Feature",
  "properties": {
    "addr:full":"999 Lake Rd Mountain Top PA 18707",
    "addr:housenumber":"999",
    "addr:postcode":"18707",
    "addr:street":"Lake Rd",
    "iso:country":"US",
    "sg:address":"999 Lake Rd",
    "sg:city":"Mountain Top",
    "sg:classifiers":[
        {
            "category":"Shopping",
            "type":"Retail Goods"
        }
    ],
    "sg:phone":"+1   ",
    "sg:postcode":"18707",
    "sg:province":"PA",
    "sg:tags":[
        "merchandise"
    ],
    "wof:name":"Pet Entrprises Bookkeeping Off",
    "wof:placetype":"venue"
},
  "geometry": {"coordinates":[-75.854429,41.138002],"type":"Point"}
}