{
  "type": "Feature",
  "properties": {
    "iso:country":"US",
    "sg:address":"1520 Beechwood Blvd",
    "sg:city":"Pittsburgh",
    "sg:classifiers":[
        {
            "category":"Shopping",
            "subcategory":"Beauty & Cosmetics",
            "type":"Retail Goods"
        }
    ],
    "sg:phone":"+1   ",
    "sg:postcode":"15217",
    "sg:province":"PA",
    "sg:tags":[
        "merchandise"
    ],
    "wof:name":"Martin Ann",
    "wof:placetype":"venue"
},
  "geometry": {"coordinates":[-79.917175,40.442285],"type":"Point"}
}