{
  "type": "Feature",
  "properties": {
    "iso:country":"US",
    "sg:address":"51 N 3rd St",
    "sg:city":"Philadelphia",
    "sg:classifiers":[
        {
            "category":"Professional",
            "subcategory":"Business Services",
            "type":"Services"
        }
    ],
    "sg:phone":"+1   ",
    "sg:postcode":"19106",
    "sg:province":"PA",
    "sg:tags":[
        "handset",
        "sales"
    ],
    "wof:name":"Simvoicecom",
    "wof:placetype":"venue"
},
  "geometry": {"coordinates":[-75.145173,39.952062],"type":"Point"}
}