{
  "type": "Feature",
  "properties": {
    "iso:country":"US",
    "sg:address":"4000 Woodland Ave",
    "sg:city":"Philadelphia",
    "sg:classifiers":[
        {
            "category":"Real Estate",
            "subcategory":"Developer",
            "type":"Services"
        }
    ],
    "sg:phone":"+1 215 386 2181",
    "sg:postcode":"19104",
    "sg:province":"PA",
    "sg:tags":[
        "funeral",
        "cemetery"
    ],
    "wof:name":"Woodlands Cemetery Co",
    "wof:placetype":"venue"
},
  "geometry": {"coordinates":[-75.204002,39.949001],"type":"Point"}
}