{
  "type": "Feature",
  "properties": {
    "iso:country":"US",
    "sg:address":"351 W Main St",
    "sg:city":"Leola",
    "sg:classifiers":[
        {
            "category":"Banks & Credit Unions",
            "subcategory":"Investment Brokerage",
            "type":"Services"
        }
    ],
    "sg:phone":"+1 717 354 2400",
    "sg:postcode":"17540",
    "sg:province":"PA",
    "sg:tags":[
        "consultant",
        "planning",
        "financial"
    ],
    "wof:name":"New Holland Financial Svc LTD",
    "wof:placetype":"venue"
},
  "geometry": {"coordinates":[-76.213356,40.0853],"type":"Point"}
}