{
  "type": "Feature",
  "properties": {
    "addr:full":"3463 Beaver St Springboro PA 16435",
    "addr:housenumber":"3463",
    "addr:postcode":"16435",
    "addr:street":"Beaver St",
    "iso:country":"US",
    "sg:address":"3463 Beaver St",
    "sg:city":"Springboro",
    "sg:classifiers":[
        {
            "category":"Retail",
            "subcategory":"Auto Repair",
            "type":"Services"
        }
    ],
    "sg:phone":"+1   ",
    "sg:postcode":"16435",
    "sg:province":"PA",
    "sg:tags":[
        "tire"
    ],
    "wof:name":"Jds Excavating & Well Drlg",
    "wof:placetype":"venue"
},
  "geometry": {"coordinates":[-80.464849,41.802495],"type":"Point"}
}