{
  "type": "Feature",
  "properties": {
    "iso:country":"US",
    "sg:address":"4622 Clubvue Dr",
    "sg:city":"Pittsburgh",
    "sg:classifiers":[
        {
            "category":"Building & Trades",
            "subcategory":"Construction",
            "type":"Services"
        }
    ],
    "sg:phone":"+1 412 882 9788",
    "sg:postcode":"15236",
    "sg:province":"PA",
    "sg:tags":[
        "painter",
        "contractor"
    ],
    "wof:name":"Inside Out the",
    "wof:placetype":"venue"
},
  "geometry": {"coordinates":[-79.982803,40.355801],"type":"Point"}
}