{
  "type": "Feature",
  "properties": {
    "iso:country":"US",
    "sg:address":"4638 Canton St",
    "sg:city":"Philadelphia",
    "sg:classifiers":[
        {
            "category":"Shopping",
            "subcategory":"Used Merchandise",
            "type":"Retail Goods"
        }
    ],
    "sg:phone":"+1   ",
    "sg:postcode":"19127",
    "sg:province":"PA",
    "wof:name":"Eugene Konopka Antique",
    "wof:placetype":"venue"
},
  "geometry": {"coordinates":[-75.230133,40.02973],"type":"Point"}
}