{
  "type": "Feature",
  "properties": {
    "iso:country":"US",
    "sg:address":"631 Wolf Hole Rd",
    "sg:city":"Halifax",
    "sg:classifiers":[
        {
            "category":"Transit Center",
            "subcategory":"Freight",
            "type":"Transportation"
        }
    ],
    "sg:phone":"+1 717 379 3503",
    "sg:postcode":"17032",
    "sg:province":"PA",
    "sg:tags":[
        "trucking-light",
        "hauling"
    ],
    "wof:name":"C.A.T.'S Hauling",
    "wof:placetype":"venue"
},
  "geometry": {"coordinates":[-76.81398799999999,40.49472],"type":"Point"}
}