{
  "type": "Feature",
  "properties": {
    "iso:country":"US",
    "sg:address":"17 Ridgewood Dr",
    "sg:city":"Mc Donald",
    "sg:classifiers":[
        {
            "category":"Building & Trades",
            "subcategory":"Construction",
            "type":"Services"
        }
    ],
    "sg:phone":"+1   ",
    "sg:postcode":"15057",
    "sg:province":"PA",
    "sg:tags":[
        "home",
        "family",
        "contractor"
    ],
    "wof:name":"Casciola Homes Inc",
    "wof:placetype":"venue"
},
  "geometry": {"coordinates":[-80.202327,40.315536],"type":"Point"}
}