{
  "type": "Feature",
  "properties": {
    "addr:full":"232 Main St Emmaus PA 18049",
    "addr:housenumber":"232",
    "addr:postcode":"18049",
    "addr:street":"Main St",
    "iso:country":"US",
    "sg:address":"232 Main St",
    "sg:city":"Emmaus",
    "sg:classifiers":[
        {
            "category":"Real Estate",
            "subcategory":"Real Estate Services",
            "type":"Services"
        }
    ],
    "sg:phone":"+1 610 867 2113",
    "sg:postcode":"18049",
    "sg:province":"PA",
    "wof:name":"Patt White Company Realtors GMAC Real Estate",
    "wof:placetype":"venue"
},
  "geometry": {"coordinates":[-75.490196,40.536201],"type":"Point"}
}