{
  "type": "Feature",
  "properties": {
    "iso:country":"US",
    "sg:address":"1675 Church Rd",
    "sg:city":"York",
    "sg:classifiers":[
        {
            "category":"Shopping",
            "subcategory":"Hobbies, Toys, & Games",
            "type":"Retail Goods"
        },
        {
            "category":"Shopping",
            "subcategory":"Crafts & Fabrics",
            "type":"Retail Goods"
        }
    ],
    "sg:phone":"+1 717 764 4607",
    "sg:postcode":"17408",
    "sg:province":"PA",
    "sg:tags":[
        "shop",
        "hobby",
        "model",
        "supply"
    ],
    "wof:name":"Jo S Candy Crafts",
    "wof:placetype":"venue"
},
  "geometry": {"coordinates":[-76.790443,39.984693],"type":"Point"}
}