{
  "type": "Feature",
  "properties": {
    "iso:country":"US",
    "sg:address":"332 Cherry St",
    "sg:city":"Reading",
    "sg:classifiers":[
        {
            "category":"Restaurant",
            "type":"Food & Drink"
        }
    ],
    "sg:phone":"+1 610 374 8511",
    "sg:postcode":"19611",
    "sg:province":"PA",
    "sg:website":"www.judysoncherry.com",
    "wof:name":"Judy's On Cherry",
    "wof:placetype":"venue"
},
  "geometry": {"coordinates":[-75.943843,40.334603],"type":"Point"}
}