{
  "type": "Feature",
  "properties": {
    "iso:country":"US",
    "sg:address":"223 Wilmington W Chester Pike",
    "sg:city":"Chadds Ford",
    "sg:classifiers":[
        {
            "category":"Restaurant",
            "type":"Food & Drink"
        }
    ],
    "sg:phone":"+1   ",
    "sg:postcode":"19317",
    "sg:province":"PA",
    "sg:tags":[
        "drinking",
        "eating"
    ],
    "wof:name":"Olive Garden",
    "wof:placetype":"venue"
},
  "geometry": {"coordinates":[-75.538297,39.849806],"type":"Point"}
}