{
  "type": "Feature",
  "properties": {
    "addr:full":"4790 Derry St Harrisburg PA 17111",
    "addr:housenumber":"4790",
    "addr:postcode":"17111",
    "addr:street":"Derry St",
    "iso:country":"US",
    "sg:address":"4790 Derry St",
    "sg:city":"Harrisburg",
    "sg:classifiers":[
        {
            "category":"Manufacturing",
            "subcategory":"Printing",
            "type":"Manufacturing & Wholesale Goods"
        }
    ],
    "sg:phone":"+1 717 564 4143",
    "sg:postcode":"17111",
    "sg:province":"PA",
    "sg:tags":[
        "lithographic",
        "commercial"
    ],
    "wof:name":"PIP Printing",
    "wof:placetype":"venue"
},
  "geometry": {"coordinates":[-76.804998,40.258469],"type":"Point"}
}