{
  "type": "Feature",
  "properties": {
    "iso:country":"US",
    "sg:address":"119 S Burrowes St",
    "sg:city":"State College",
    "sg:classifiers":[
        {
            "category":"Professional",
            "subcategory":"Management & Consulting",
            "type":"Services"
        }
    ],
    "sg:phone":"+1 814 237 2516",
    "sg:postcode":"16801",
    "sg:province":"PA",
    "sg:tags":[
        "consultant",
        "telecommunication"
    ],
    "wof:name":"Star H Corp",
    "wof:placetype":"venue"
},
  "geometry": {"coordinates":[-77.862998,40.792108],"type":"Point"}
}