{
  "type": "Feature",
  "properties": {
    "iso:country":"US",
    "sg:address":"1330 Red Oak Dr",
    "sg:city":"Chalfont",
    "sg:classifiers":[
        {
            "category":"Professional",
            "subcategory":"Business Services",
            "type":"Services"
        }
    ],
    "sg:phone":"+1   ",
    "sg:postcode":"18914",
    "sg:province":"PA",
    "wof:name":"Business Partner of Blue Bell",
    "wof:placetype":"venue"
},
  "geometry": {"coordinates":[-75.17469,40.273016],"type":"Point"}
}