{
  "type": "Feature",
  "properties": {
    "addr:full":"7213 Rising Sun Ave Philadelphia PA 19111",
    "addr:housenumber":"7213",
    "addr:postcode":"19111",
    "addr:street":"Rising Sun Ave",
    "iso:country":"US",
    "sg:address":"7213 Rising Sun Ave",
    "sg:city":"Philadelphia",
    "sg:classifiers":[
        {
            "category":"Shopping",
            "subcategory":"Used Merchandise",
            "type":"Retail Goods"
        },
        {
            "category":"Home & Garden",
            "subcategory":"Furniture",
            "type":"Retail Goods"
        }
    ],
    "sg:phone":"+1 215 745 6000",
    "sg:postcode":"19111",
    "sg:province":"PA",
    "sg:tags":[
        "store"
    ],
    "wof:name":"Furniture Etc Inc",
    "wof:placetype":"venue"
},
  "geometry": {"coordinates":[-75.085526,40.059816],"type":"Point"}
}