{
  "type": "Feature",
  "properties": {
    "iso:country":"US",
    "sg:address":"325 Fox Chapel Rd",
    "sg:city":"Pittsburgh",
    "sg:classifiers":[
        {
            "category":"Government",
            "subcategory":"Police Station",
            "type":"Public Place"
        }
    ],
    "sg:phone":"+1   ",
    "sg:postcode":"15238",
    "sg:province":"PA",
    "sg:tags":[
        "protection"
    ],
    "wof:name":"Police Department",
    "wof:placetype":"venue"
},
  "geometry": {"coordinates":[-79.883371,40.498159],"type":"Point"}
}