{
  "type": "Feature",
  "properties": {
    "addr:full":"1057 Church St Landisville PA 17538",
    "addr:housenumber":"1057",
    "addr:postcode":"17538",
    "addr:street":"Church St",
    "iso:country":"US",
    "sg:address":"1057 Church St",
    "sg:city":"Landisville",
    "sg:classifiers":[
        {
            "category":"Health Services",
            "subcategory":"Doctor",
            "type":"Services"
        }
    ],
    "sg:phone":"+1 717 898 8895",
    "sg:postcode":"17538",
    "sg:province":"PA",
    "sg:tags":[
        "physician",
        "surgeon"
    ],
    "wof:name":"Marie V Kiser PHD",
    "wof:placetype":"venue"
},
  "geometry": {"coordinates":[-76.408773,40.073331],"type":"Point"}
}