{
  "type": "Feature",
  "properties": {
    "addr:full":"439 W Main St Lock Haven PA 17745",
    "addr:housenumber":"439",
    "addr:postcode":"17745",
    "addr:street":"W Main St",
    "iso:country":"US",
    "sg:address":"439 W Main St",
    "sg:city":"Lock Haven",
    "sg:classifiers":[
        {
            "category":"Travel",
            "subcategory":"Hotels & Motels",
            "type":"Entertainment"
        }
    ],
    "sg:phone":"+1 570 748 5799",
    "sg:postcode":"17745",
    "sg:province":"PA",
    "sg:tags":[
        "breakfast",
        "accommodation",
        "bed"
    ],
    "sg:website":"www.carriagebandb.com",
    "wof:name":"Carriage House Bed & Breakfast",
    "wof:placetype":"venue"
},
  "geometry": {"coordinates":[-77.453907,41.139788],"type":"Point"}
}