{
  "type": "Feature",
  "properties": {
    "iso:country":"US",
    "sg:address":"570 Gresock Rd",
    "sg:city":"Punxsutawney",
    "sg:classifiers":[
        {
            "category":"Real Estate",
            "subcategory":"Real Estate Agent",
            "type":"Services"
        }
    ],
    "sg:phone":"+1 814 938 1756",
    "sg:postcode":"15767",
    "sg:province":"PA",
    "wof:name":"Blose Enterprises",
    "wof:placetype":"venue"
},
  "geometry": {"coordinates":[-79.007914,40.928852],"type":"Point"}
}