{
  "type": "Feature",
  "properties": {
    "addr:full":"261 Rosecrest Dr Monroeville PA 15146",
    "addr:housenumber":"261",
    "addr:postcode":"15146",
    "addr:street":"Rosecrest Dr",
    "iso:country":"US",
    "sg:address":"261 Rosecrest Dr",
    "sg:city":"Monroeville",
    "sg:classifiers":[
        {
            "category":"Professional",
            "type":"Services"
        }
    ],
    "sg:phone":"+1 412 823 9382",
    "sg:postcode":"15146",
    "sg:province":"PA",
    "sg:tags":[
        "establishment"
    ],
    "wof:name":"Y M & WHA",
    "wof:placetype":"venue"
},
  "geometry": {"coordinates":[-79.78542299999999,40.420037],"type":"Point"}
}