{
  "type": "Feature",
  "properties": {
    "iso:country":"US",
    "sg:address":"113 Shady Lane Rd",
    "sg:city":"Schuylkill Haven",
    "sg:classifiers":[
        {
            "category":"Shopping",
            "subcategory":"Department Store",
            "type":"Retail Goods"
        }
    ],
    "sg:phone":"+1 570 385 5863",
    "sg:postcode":"17972",
    "sg:province":"PA",
    "sg:tags":[
        "shop"
    ],
    "wof:name":"Northeast GPS Supply",
    "wof:placetype":"venue"
},
  "geometry": {"coordinates":[-76.196862,40.621737],"type":"Point"}
}