{
  "type": "Feature",
  "properties": {
    "iso:country":"US",
    "sg:address":"2800 N Reese St",
    "sg:city":"Philadelphia",
    "sg:classifiers":[
        {
            "category":"Food & Beverages",
            "subcategory":"Groceries & Convenience Stores",
            "type":"Retail Goods"
        }
    ],
    "sg:phone":"+1 215 228 3014",
    "sg:postcode":"19133",
    "sg:province":"PA",
    "wof:name":"Celeste Food Market",
    "wof:placetype":"venue"
},
  "geometry": {"coordinates":[-75.140404,39.993801],"type":"Point"}
}