{
  "type": "Feature",
  "properties": {
    "iso:country":"US",
    "sg:address":"1001 E Wiconisco Ave",
    "sg:city":"Tower City",
    "sg:classifiers":[
        {
            "category":"Health Services",
            "subcategory":"Doctor",
            "type":"Services"
        }
    ],
    "sg:phone":"+1 717 647 2297",
    "sg:postcode":"17980",
    "sg:province":"PA",
    "sg:tags":[
        "physician",
        "surgeon"
    ],
    "wof:name":"Family Medicine Ctr-Tower Cty",
    "wof:placetype":"venue"
},
  "geometry": {"coordinates":[-76.543657,40.58949],"type":"Point"}
}