{
  "type": "Feature",
  "properties": {
    "addr:full":"1 Oak Rd Philadelphia PA 19118",
    "addr:housenumber":"1",
    "addr:postcode":"19118",
    "addr:street":"Oak Rd",
    "iso:country":"US",
    "sg:address":"1 Oak Rd",
    "sg:city":"Philadelphia",
    "sg:classifiers":[
        {
            "category":"Building & Trades",
            "subcategory":"Construction",
            "type":"Services"
        }
    ],
    "sg:phone":"+1 215 233 5380",
    "sg:postcode":"19118",
    "sg:province":"PA",
    "sg:tags":[
        "hanging",
        "contractor"
    ],
    "wof:name":"Lafayette Hill Painters",
    "wof:placetype":"venue"
},
  "geometry": {"coordinates":[-75.23347099999999,40.086023],"type":"Point"}
}