{
  "type": "Feature",
  "properties": {
    "addr:full":"1241 Blakeslee Boulevard Dr E Lehighton PA 18235",
    "addr:housenumber":"1241",
    "addr:postcode":"18235",
    "addr:street":"Blakeslee Boulevard Dr E",
    "iso:country":"US",
    "sg:address":"1241 Blakeslee Boulevard Dr E",
    "sg:city":"Lehighton",
    "sg:classifiers":[
        {
            "category":"Professional",
            "type":"Services"
        },
        {
            "category":"Restaurant",
            "type":"Food & Drink"
        },
        {
            "category":"Fast Food",
            "type":"Food & Drink"
        }
    ],
    "sg:phone":"+1 570 386 3288",
    "sg:postcode":"18235",
    "sg:province":"PA",
    "sg:tags":[
        "take",
        "caterer"
    ],
    "wof:name":"Chiu Kwan Kitchen",
    "wof:placetype":"venue"
},
  "geometry": {"coordinates":[-75.789092,40.792821],"type":"Point"}
}