{
  "type": "Feature",
  "properties": {
    "iso:country":"US",
    "sg:address":"106 W Lauman St",
    "sg:city":"Mount Holly Springs",
    "sg:classifiers":[
        {
            "category":"Professional",
            "subcategory":"Employment Agencies",
            "type":"Services"
        }
    ],
    "sg:phone":"+1   ",
    "sg:postcode":"17065",
    "sg:province":"PA",
    "sg:tags":[
        "help",
        "supply"
    ],
    "wof:name":"Unicom Services Inc",
    "wof:placetype":"venue"
},
  "geometry": {"coordinates":[-77.192098,40.122463],"type":"Point"}
}