{
  "type": "Feature",
  "properties": {
    "iso:country":"US",
    "sg:address":"2600 Ridge Pike",
    "sg:city":"Norristown",
    "sg:classifiers":[
        {
            "category":"Autos & Motor Vehicles",
            "subcategory":"Fuel & Gas Station",
            "type":"Retail Goods"
        }
    ],
    "sg:phone":"+1 610 539 1104",
    "sg:postcode":"19403",
    "sg:province":"PA",
    "sg:tags":[
        "oil"
    ],
    "wof:name":"Trooper Mobil",
    "wof:placetype":"venue"
},
  "geometry": {"coordinates":[-75.390771,40.143028],"type":"Point"}
}