{
  "type": "Feature",
  "properties": {
    "iso:country":"US",
    "sg:address":"43 Steam Whistle Dr",
    "sg:city":"Warminster",
    "sg:classifiers":[
        {
            "category":"Manufacturing",
            "subcategory":"Tools & Machinery",
            "type":"Manufacturing & Wholesale Goods"
        }
    ],
    "sg:phone":"+1 215 322 9883",
    "sg:postcode":"18974",
    "sg:province":"PA",
    "sg:tags":[
        "die",
        "maker"
    ],
    "wof:name":"Pro-Cel Mold",
    "wof:placetype":"venue"
},
  "geometry": {"coordinates":[-75.06432700000001,40.227144],"type":"Point"}
}