{
  "type": "Feature",
  "properties": {
    "addr:full":"826 N Liberty St Shamokin PA 17872",
    "addr:housenumber":"826",
    "addr:postcode":"17872",
    "addr:street":"N Liberty St",
    "iso:country":"US",
    "sg:address":"826 N Liberty St",
    "sg:city":"Shamokin",
    "sg:classifiers":[
        {
            "category":"Organizations",
            "subcategory":"Religious Organization",
            "type":"Services"
        }
    ],
    "sg:phone":"+1 570 648 0201",
    "sg:postcode":"17872",
    "sg:province":"PA",
    "wof:name":"Presbyterian Church",
    "wof:placetype":"venue"
},
  "geometry": {"coordinates":[-76.55374999999999,40.79371],"type":"Point"}
}