{
  "type": "Feature",
  "properties": {
    "addr:full":"1800 John F Kennedy Blvd Ste 300 Philadelphia PA 19103",
    "addr:housenumber":"1800",
    "addr:postcode":"19103",
    "addr:street":"John F Kennedy Blvd Ste 300",
    "iso:country":"US",
    "sg:address":"1800 John F Kennedy Blvd Ste 300",
    "sg:city":"Philadelphia",
    "sg:classifiers":[
        {
            "category":"Professional",
            "subcategory":"Lawyer & Legal Services",
            "type":"Services"
        }
    ],
    "sg:phone":"+1 215 636 0616",
    "sg:postcode":"19103",
    "sg:province":"PA",
    "sg:website":"www.weinsteinfirm.com",
    "wof:name":"Weinstein Deborah ESQ",
    "wof:placetype":"venue"
},
  "geometry": {"coordinates":[-75.169741,39.954064],"type":"Point"}
}