{
  "type": "Feature",
  "properties": {
    "iso:country":"US",
    "sg:address":"100 N Caroline St",
    "sg:city":"Ebensburg",
    "sg:classifiers":[
        {
            "category":"Local Transit",
            "type":"Transportation"
        }
    ],
    "sg:phone":"+1   ",
    "sg:postcode":"15931",
    "sg:province":"PA",
    "sg:tags":[
        "emergency",
        "ambulance"
    ],
    "wof:name":"Ebensburg Area Ems",
    "wof:placetype":"venue"
},
  "geometry": {"coordinates":[-78.72277699999999,40.486036],"type":"Point"}
}