{
  "type": "Feature",
  "properties": {
    "iso:country":"US",
    "sg:address":"1900 Street Rd",
    "sg:city":"Bensalem",
    "sg:classifiers":[
        {
            "category":"Shopping",
            "subcategory":"Jewelry",
            "type":"Retail Goods"
        }
    ],
    "sg:phone":"+1 215 639 2910",
    "sg:postcode":"19020",
    "sg:province":"PA",
    "sg:website":"www.getzowjewelers.com",
    "wof:name":"Getzow Jewelers",
    "wof:placetype":"venue"
},
  "geometry": {"coordinates":[-74.947197,40.098999],"type":"Point"}
}