{
  "type": "Feature",
  "properties": {
    "iso:country":"US",
    "sg:address":"1601 Walnut St Ste 901",
    "sg:city":"Philadelphia",
    "sg:classifiers":[
        {
            "category":"Health Services",
            "subcategory":"Optometrist",
            "type":"Services"
        },
        {
            "category":"Health Services",
            "subcategory":"Clinic",
            "type":"Services"
        }
    ],
    "sg:phone":"+1 215 561 7131",
    "sg:postcode":"19102",
    "sg:province":"PA",
    "sg:tags":[
        "counseling",
        "mental"
    ],
    "wof:name":"Bonner Ann PHD",
    "wof:placetype":"venue"
},
  "geometry": {"coordinates":[-75.167603,39.9496],"type":"Point"}
}