{
  "type": "Feature",
  "properties": {
    "iso:country":"US",
    "sg:address":"5231 Surrey Ct",
    "sg:city":"Allentown",
    "sg:classifiers":[
        {
            "category":"Home & Garden",
            "subcategory":"Garden Supply",
            "type":"Retail Goods"
        }
    ],
    "sg:phone":"+1 610 391 8900",
    "sg:postcode":"18104",
    "sg:province":"PA",
    "sg:tags":[
        "equipment",
        "snow",
        "removal"
    ],
    "wof:name":"Maintenance Monitoring",
    "wof:placetype":"venue"
},
  "geometry": {"coordinates":[-75.568855,40.581007],"type":"Point"}
}