{
  "type": "Feature",
  "properties": {
    "addr:full":"174 Lawrence Ave Washington PA 15301",
    "addr:housenumber":"174",
    "addr:postcode":"15301",
    "addr:street":"Lawrence Ave",
    "iso:country":"US",
    "sg:address":"174 Lawrence Ave",
    "sg:city":"Washington",
    "sg:classifiers":[
        {
            "category":"Building & Trades",
            "subcategory":"Construction",
            "type":"Services"
        }
    ],
    "sg:phone":"+1 724 229 8520",
    "sg:postcode":"15301",
    "sg:province":"PA",
    "sg:tags":[
        "general",
        "contractor"
    ],
    "wof:name":"Delrose Construction Co",
    "wof:placetype":"venue"
},
  "geometry": {"coordinates":[-80.263057,40.185026],"type":"Point"}
}