{
  "type": "Feature",
  "properties": {
    "iso:country":"US",
    "sg:address":"14 Main St",
    "sg:city":"Glen Rock",
    "sg:classifiers":[
        {
            "category":"Restaurant",
            "type":"Food & Drink"
        }
    ],
    "sg:phone":"+1 717 235 6884",
    "sg:postcode":"17327",
    "sg:province":"PA",
    "sg:tags":[
        "eating"
    ],
    "wof:name":"Mignanos Brothers",
    "wof:placetype":"venue"
},
  "geometry": {"coordinates":[-76.733679,39.795145],"type":"Point"}
}