{
  "type": "Feature",
  "properties": {
    "iso:country":"US",
    "sg:address":"1840 County Line Rd",
    "sg:city":"Huntingdon Vly",
    "sg:classifiers":[
        {
            "category":"Manufacturing",
            "subcategory":"Electronics",
            "type":"Manufacturing & Wholesale Goods"
        }
    ],
    "sg:phone":"+1 215 364 2450",
    "sg:postcode":"19006",
    "sg:province":"PA",
    "sg:tags":[
        "equipment",
        "electronic",
        "supply"
    ],
    "wof:name":"R F Circuits Inc",
    "wof:placetype":"venue"
},
  "geometry": {"coordinates":[-75.03005400000001,40.147184],"type":"Point"}
}