{
  "type": "Feature",
  "properties": {
    "iso:country":"US",
    "sg:address":"854 Montgomery Ave",
    "sg:city":"Narberth",
    "sg:classifiers":[
        {
            "category":"Shopping",
            "subcategory":"Gifts & Souvenirs",
            "type":"Retail Goods"
        }
    ],
    "sg:phone":"+1 610 668 1480",
    "sg:postcode":"19072",
    "sg:province":"PA",
    "sg:tags":[
        "shop"
    ],
    "wof:name":"Gifted",
    "wof:placetype":"venue"
},
  "geometry": {"coordinates":[-75.25971699999999,40.011212],"type":"Point"}
}