{
  "type": "Feature",
  "properties": {
    "addr:full":"210 E Broad St Bethlehem PA 18018",
    "addr:housenumber":"210",
    "addr:postcode":"18018",
    "addr:street":"E Broad St",
    "iso:country":"US",
    "sg:address":"210 E Broad St",
    "sg:city":"Bethlehem",
    "sg:classifiers":[
        {
            "category":"Professional",
            "subcategory":"Lawyer & Legal Services",
            "type":"Services"
        }
    ],
    "sg:phone":"+1 610 691 0330",
    "sg:postcode":"18018",
    "sg:province":"PA",
    "wof:name":"Davison Robt M Atty",
    "wof:placetype":"venue"
},
  "geometry": {"coordinates":[-75.372902,40.6222],"type":"Point"}
}