{
  "type": "Feature",
  "properties": {
    "addr:full":"134 Union Rd Frenchtown PA 08825",
    "addr:housenumber":"134",
    "addr:postcode":"08825",
    "addr:street":"Union Rd",
    "iso:country":"US",
    "sg:address":"134 Union Rd",
    "sg:city":"Frenchtown",
    "sg:classifiers":[
        {
            "category":"Professional",
            "subcategory":"Research",
            "type":"Services"
        }
    ],
    "sg:phone":"+1   ",
    "sg:postcode":"08825",
    "sg:province":"PA",
    "sg:tags":[
        "commercial",
        "physical"
    ],
    "wof:name":"Prototype Technology",
    "wof:placetype":"venue"
},
  "geometry": {"coordinates":[-75.000838,40.503396],"type":"Point"}
}