{
  "type": "Feature",
  "properties": {
    "addr:full":"7143 Fleury Way Pittsburgh PA 15208",
    "addr:housenumber":"7143",
    "addr:postcode":"15208",
    "addr:street":"Fleury Way",
    "iso:country":"US",
    "sg:address":"7143 Fleury Way",
    "sg:city":"Pittsburgh",
    "sg:classifiers":[
        {
            "category":"Social Services",
            "type":"Services"
        }
    ],
    "sg:phone":"+1   ",
    "sg:postcode":"15208",
    "sg:province":"PA",
    "sg:tags":[
        "agency"
    ],
    "wof:name":"Homewood Brushtn Fmly Suprt CT",
    "wof:placetype":"venue"
},
  "geometry": {"coordinates":[-79.897903,40.456335],"type":"Point"}
}