{
  "type": "Feature",
  "properties": {
    "addr:full":"508 Corporate Dr W Langhorne PA 19047",
    "addr:housenumber":"508",
    "addr:postcode":"19047",
    "addr:street":"Corporate Dr W Langhorne Pa",
    "iso:country":"US",
    "sg:address":"508 Corporate Dr W",
    "sg:city":"Langhorne",
    "sg:classifiers":[
        {
            "category":"Health Services",
            "subcategory":"Doctor",
            "type":"Services"
        }
    ],
    "sg:phone":"+1 215 860 4380",
    "sg:postcode":"19047",
    "sg:province":"PA",
    "sg:tags":[
        "physician",
        "surgeon"
    ],
    "wof:name":"Schwartz Milton A Doctor of Medicine",
    "wof:placetype":"venue"
},
  "geometry": {"coordinates":[-74.908821,40.22171],"type":"Point"}
}