{
  "type": "Feature",
  "properties": {
    "iso:country":"US",
    "sg:address":"727 Delancey St",
    "sg:city":"Philadelphia",
    "sg:classifiers":[
        {
            "category":"Health Services",
            "subcategory":"Doctor",
            "type":"Services"
        }
    ],
    "sg:phone":"+1 215 829 3523",
    "sg:postcode":"19106",
    "sg:province":"PA",
    "sg:tags":[
        "medical"
    ],
    "wof:name":"Kearney Rosemary A MD",
    "wof:placetype":"venue"
},
  "geometry": {"coordinates":[-75.154319,39.945001],"type":"Point"}
}