{
  "type": "Feature",
  "properties": {
    "addr:full":"85 Old Eagle School Rd Strafford PA 19087",
    "addr:housenumber":"85",
    "addr:postcode":"19087",
    "addr:street":"Old Eagle School Rd",
    "iso:country":"US",
    "sg:address":"85 Old Eagle School Rd",
    "sg:city":"Strafford",
    "sg:classifiers":[
        {
            "category":"Health Services",
            "subcategory":"Doctor",
            "type":"Services"
        }
    ],
    "sg:phone":"+1 610 688 3744",
    "sg:postcode":"19087",
    "sg:province":"PA",
    "sg:tags":[
        "physician",
        "surgeon"
    ],
    "wof:name":"Main Line Ob/Gyn Assoc",
    "wof:placetype":"venue"
},
  "geometry": {"coordinates":[-75.40416500000001,40.049171],"type":"Point"}
}