{
  "type": "Feature",
  "properties": {
    "iso:country":"US",
    "sg:address":"2999 Old Rodgers Rd",
    "sg:city":"Bristol",
    "sg:classifiers":[
        {
            "category":"Wholesale",
            "subcategory":"Metals & Minerals",
            "type":"Manufacturing & Wholesale Goods"
        }
    ],
    "sg:phone":"+1   ",
    "sg:postcode":"19007",
    "sg:province":"PA",
    "sg:tags":[
        "center"
    ],
    "wof:name":"Burlington Foundry Inc",
    "wof:placetype":"venue"
},
  "geometry": {"coordinates":[-74.87723699999999,40.120087],"type":"Point"}
}