{
  "type": "Feature",
  "properties": {
    "iso:country":"US",
    "sg:address":"5055 Library Rd Ste 6",
    "sg:city":"Bethel Park",
    "sg:classifiers":[
        {
            "category":"Banks & Credit Unions",
            "subcategory":"Bank",
            "type":"Services"
        }
    ],
    "sg:phone":"+1 412 854 6322",
    "sg:postcode":"15102",
    "sg:province":"PA",
    "wof:name":"Citizens Bank",
    "wof:placetype":"venue"
},
  "geometry": {"coordinates":[-80.025522,40.340449],"type":"Point"}
}