{
  "type": "Feature",
  "properties": {
    "iso:country":"US",
    "sg:address":"660 E Lehman St",
    "sg:city":"Lebanon",
    "sg:classifiers":[
        {
            "category":"Retail",
            "subcategory":"Auto Repair",
            "type":"Services"
        }
    ],
    "sg:phone":"+1 717 274 6610",
    "sg:postcode":"17046",
    "sg:province":"PA",
    "sg:tags":[
        "automobile",
        "top",
        "upholstery"
    ],
    "wof:name":"Dave's Upholstery",
    "wof:placetype":"venue"
},
  "geometry": {"coordinates":[-76.400463,40.346652],"type":"Point"}
}