{
  "type": "Feature",
  "properties": {
    "iso:country":"US",
    "sg:address":"4760 William Flynn Hwy",
    "sg:city":"Allison Park",
    "sg:classifiers":[
        {
            "category":"Food & Beverages",
            "subcategory":"Liquor & Beverages",
            "type":"Retail Goods"
        }
    ],
    "sg:phone":"+1 412 492 5100",
    "sg:postcode":"15101",
    "sg:province":"PA",
    "wof:name":"State Liquor Store",
    "wof:placetype":"venue"
},
  "geometry": {"coordinates":[-79.949561,40.588135],"type":"Point"}
}