{
  "type": "Feature",
  "properties": {
    "iso:country":"US",
    "sg:address":"4119 Walnut St Ste 100",
    "sg:city":"Philadelphia",
    "sg:classifiers":[
        {
            "category":"Utilities",
            "type":"Services"
        }
    ],
    "sg:phone":"+1 215 243 5100",
    "sg:postcode":"19104",
    "sg:province":"PA",
    "sg:tags":[
        "provider",
        "internet"
    ],
    "sg:website":"phillynet.net/",
    "wof:name":"Phillynet",
    "wof:placetype":"venue"
},
  "geometry": {"coordinates":[-75.206204,39.954774],"type":"Point"}
}