{
  "type": "Feature",
  "properties": {
    "iso:country":"US",
    "sg:address":"4468 Richmond St",
    "sg:city":"Philadelphia",
    "sg:classifiers":[
        {
            "category":"Building & Trades",
            "subcategory":"Electrical",
            "type":"Services"
        }
    ],
    "sg:phone":"+1 215 288 2765",
    "sg:postcode":"19137",
    "sg:province":"PA",
    "sg:tags":[
        "electrician"
    ],
    "wof:name":"Binczewski Ed & Paul Electrical Service",
    "wof:placetype":"venue"
},
  "geometry": {"coordinates":[-75.0718,39.998001],"type":"Point"}
}