{
  "type": "Feature",
  "properties": {
    "iso:country":"US",
    "sg:address":"491 S Keyser Ave",
    "sg:city":"Taylor",
    "sg:classifiers":[
        {
            "category":"Manufacturing",
            "subcategory":"Apparel",
            "type":"Manufacturing & Wholesale Goods"
        }
    ],
    "sg:phone":"+1   ",
    "sg:postcode":"18517",
    "sg:province":"PA",
    "sg:tags":[
        "household",
        "furnishing",
        "mfg"
    ],
    "wof:name":"Slipcovers By Shirly",
    "wof:placetype":"venue"
},
  "geometry": {"coordinates":[-75.714984,41.402476],"type":"Point"}
}