{
  "type": "Feature",
  "properties": {
    "addr:full":"531 Haunted Ln Bensalem PA 19020",
    "addr:housenumber":"531",
    "addr:postcode":"19020",
    "addr:street":"Haunted Ln",
    "iso:country":"US",
    "sg:address":"531 Haunted Ln",
    "sg:city":"Bensalem",
    "sg:classifiers":[
        {
            "category":"Retail",
            "subcategory":"Auto Repair",
            "type":"Services"
        }
    ],
    "sg:phone":"+1 215 638 2272",
    "sg:postcode":"19020",
    "sg:province":"PA",
    "sg:tags":[
        "body",
        "shop"
    ],
    "wof:name":"Schaum's Auto Body",
    "wof:placetype":"venue"
},
  "geometry": {"coordinates":[-74.914497,40.0928],"type":"Point"}
}