{
  "type": "Feature",
  "properties": {
    "iso:country":"US",
    "sg:address":"230 E High St",
    "sg:city":"New Oxford",
    "sg:classifiers":[
        {
            "category":"Building & Trades",
            "subcategory":"Electrical",
            "type":"Services"
        }
    ],
    "sg:phone":"+1 717 624 8685",
    "sg:postcode":"17350",
    "sg:province":"PA",
    "sg:tags":[
        "electric",
        "contractor"
    ],
    "wof:name":"H John Spalding Electric",
    "wof:placetype":"venue"
},
  "geometry": {"coordinates":[-77.049896,39.864283],"type":"Point"}
}