{
  "type": "Feature",
  "properties": {
    "iso:country":"US",
    "sg:address":"1095 6th St",
    "sg:city":"Catasauqua",
    "sg:classifiers":[
        {
            "category":"Retail",
            "subcategory":"Auto Repair",
            "type":"Services"
        }
    ],
    "sg:phone":"+1 610 264 2407",
    "sg:postcode":"18032",
    "sg:province":"PA",
    "sg:tags":[
        "body",
        "automobile",
        "painting"
    ],
    "wof:name":"Roman's Auto Body Shop",
    "wof:placetype":"venue"
},
  "geometry": {"coordinates":[-75.473737,40.660834],"type":"Point"}
}