{
  "type": "Feature",
  "properties": {
    "iso:country":"US",
    "sg:address":"301 Mall Blvd",
    "sg:city":"King Of Prussia",
    "sg:classifiers":[
        {
            "category":"Restaurant",
            "type":"Food & Drink"
        }
    ],
    "sg:phone":"+1 610 992 1809",
    "sg:postcode":"19406",
    "sg:province":"PA",
    "wof:name":"Orange Julius",
    "wof:placetype":"venue"
},
  "geometry": {"coordinates":[-75.388735,40.089357],"type":"Point"}
}