{
  "type": "Feature",
  "properties": {
    "iso:country":"US",
    "sg:address":"502 S Guernsey Rd",
    "sg:city":"West Grove",
    "sg:classifiers":[
        {
            "category":"Home & Garden",
            "subcategory":"Building Materials",
            "type":"Retail Goods"
        }
    ],
    "sg:phone":"+1   ",
    "sg:postcode":"19390",
    "sg:province":"PA",
    "sg:tags":[
        "merchandise"
    ],
    "wof:name":"Allstar Home Improvements",
    "wof:placetype":"venue"
},
  "geometry": {"coordinates":[-75.83423999999999,39.796834],"type":"Point"}
}