{
  "type": "Feature",
  "properties": {
    "iso:country":"US",
    "sg:address":"103 N Broadway",
    "sg:city":"Wind Gap",
    "sg:classifiers":[
        {
            "category":"Shopping",
            "subcategory":"News",
            "type":"Retail Goods"
        }
    ],
    "sg:phone":"+1 610 863 3071",
    "sg:postcode":"18091",
    "sg:province":"PA",
    "sg:tags":[
        "jewelery",
        "store"
    ],
    "wof:name":"Jimmeze Jewelers",
    "wof:placetype":"venue"
},
  "geometry": {"coordinates":[-75.2914,40.851532],"type":"Point"}
}