{
  "type": "Feature",
  "properties": {
    "iso:country":"US",
    "sg:address":"1380 Snydertown Rd",
    "sg:city":"Howard",
    "sg:classifiers":[
        {
            "category":"Building & Trades",
            "subcategory":"Construction",
            "type":"Services"
        }
    ],
    "sg:phone":"+1 814 355 7061",
    "sg:postcode":"16841",
    "sg:province":"PA",
    "sg:tags":[
        "plastering",
        "contractor"
    ],
    "wof:name":"Zimmerman Plastering",
    "wof:placetype":"venue"
},
  "geometry": {"coordinates":[-77.56220399999999,40.993977],"type":"Point"}
}