{
  "type": "Feature",
  "properties": {
    "addr:full":"1597 Washington Rd Pittsburgh PA 15228",
    "addr:housenumber":"1597",
    "addr:postcode":"15228",
    "addr:street":"Washington Rd",
    "iso:country":"US",
    "sg:address":"1597 Washington Rd",
    "sg:city":"Pittsburgh",
    "sg:classifiers":[
        {
            "category":"Retail",
            "subcategory":"Laundry & Dry Cleaning",
            "type":"Services"
        }
    ],
    "sg:phone":"+1 412 276 3182",
    "sg:postcode":"15228",
    "sg:province":"PA",
    "wof:name":"Model Cleaners",
    "wof:placetype":"venue"
},
  "geometry": {"coordinates":[-80.05013,40.355663],"type":"Point"}
}