{
  "type": "Feature",
  "properties": {
    "iso:country":"US",
    "sg:address":"502 Cochran Mill Rd",
    "sg:city":"Clairton",
    "sg:classifiers":[
        {
            "category":"Autos & Motor Vehicles",
            "subcategory":"Automobile Sales",
            "type":"Retail Goods"
        }
    ],
    "sg:phone":"+1 412 655 9090",
    "sg:postcode":"15025",
    "sg:province":"PA",
    "sg:tags":[
        "dealers-used",
        "used",
        "cars-wholesale",
        "car"
    ],
    "wof:name":"Precision Auto Sales Inc",
    "wof:placetype":"venue"
},
  "geometry": {"coordinates":[-79.976043,40.310641],"type":"Point"}
}