{
  "type": "Feature",
  "properties": {
    "iso:country":"US",
    "sg:address":"602 S Main St",
    "sg:city":"Shrewsbury",
    "sg:classifiers":[
        {
            "category":"Restaurant",
            "type":"Food & Drink"
        },
        {
            "category":"Food & Beverages",
            "subcategory":"Groceries & Convenience Stores",
            "type":"Retail Goods"
        }
    ],
    "sg:phone":"+1 717 235 4956",
    "sg:postcode":"17361",
    "sg:province":"PA",
    "sg:tags":[
        "shop",
        "sandwich"
    ],
    "wof:name":"Florentino's",
    "wof:placetype":"venue"
},
  "geometry": {"coordinates":[-76.67748400000001,39.753202],"type":"Point"}
}