{
  "type": "Feature",
  "properties": {
    "addr:full":"2332 Carpenter St Philadelphia PA 19146",
    "addr:housenumber":"2332",
    "addr:postcode":"19146",
    "addr:street":"Carpenter St",
    "iso:country":"US",
    "sg:address":"2332 Carpenter St",
    "sg:city":"Philadelphia",
    "sg:classifiers":[
        {
            "category":"Social Services",
            "subcategory":"Child Care",
            "type":"Services"
        }
    ],
    "sg:phone":"+1 215 735 4416",
    "sg:postcode":"19146",
    "sg:province":"PA",
    "wof:name":"Jane D Kent-St Nicholas Day",
    "wof:placetype":"venue"
},
  "geometry": {"coordinates":[-75.18139600000001,39.940826],"type":"Point"}
}