{
  "type": "Feature",
  "properties": {
    "iso:country":"US",
    "sg:address":"928 Old Bethlehem Pike",
    "sg:city":"Quakertown",
    "sg:classifiers":[
        {
            "category":"Retail",
            "subcategory":"Car Wash",
            "type":"Services"
        }
    ],
    "sg:phone":"+1 215 529 9805",
    "sg:postcode":"18951",
    "sg:province":"PA",
    "sg:tags":[
        "carwash"
    ],
    "wof:name":"Magic Touch Car Care",
    "wof:placetype":"venue"
},
  "geometry": {"coordinates":[-75.34016699999999,40.425548],"type":"Point"}
}