{
  "type": "Feature",
  "properties": {
    "iso:country":"US",
    "sg:address":"250 Pierce St",
    "sg:city":"Kingston",
    "sg:classifiers":[
        {
            "category":"Social Services",
            "subcategory":"Adult Care",
            "type":"Services"
        }
    ],
    "sg:phone":"+1   ",
    "sg:postcode":"18704",
    "sg:province":"PA",
    "sg:tags":[
        "residential"
    ],
    "wof:name":"Institute For Humn Rsrces Svcs",
    "wof:placetype":"venue"
},
  "geometry": {"coordinates":[-75.88898500000001,41.263473],"type":"Point"}
}