{
  "type": "Feature",
  "properties": {
    "iso:country":"US",
    "sg:address":"817 S George St",
    "sg:city":"York",
    "sg:classifiers":[
        {
            "category":"Professional",
            "subcategory":"Lawyer & Legal Services",
            "type":"Services"
        }
    ],
    "sg:phone":"+1 717 846 4481",
    "sg:postcode":"17403",
    "sg:province":"PA",
    "sg:tags":[
        "attorney"
    ],
    "sg:website":"www.flightbrothers.com",
    "wof:name":"Flight Brothers Inc",
    "wof:placetype":"venue"
},
  "geometry": {"coordinates":[-76.722179,39.950599],"type":"Point"}
}