{
  "type": "Feature",
  "properties": {
    "iso:country":"US",
    "sg:address":"380 E Berlin Rd",
    "sg:city":"York",
    "sg:classifiers":[
        {
            "category":"Professional",
            "subcategory":"Business Services",
            "type":"Services"
        }
    ],
    "sg:phone":"+1 717 793 9651",
    "sg:postcode":"17408",
    "sg:province":"PA",
    "wof:name":"Rosemary B Smith",
    "wof:placetype":"venue"
},
  "geometry": {"coordinates":[-76.783732,39.952483],"type":"Point"}
}