{
  "type": "Feature",
  "properties": {
    "iso:country":"US",
    "sg:address":"18 Main St",
    "sg:city":"Hallstead",
    "sg:classifiers":[
        {
            "category":"Banks & Credit Unions",
            "subcategory":"Investment Brokerage",
            "type":"Services"
        },
        {
            "category":"Insurance",
            "subcategory":"Hazard Insurance",
            "type":"Services"
        }
    ],
    "sg:phone":"+1 570 879 2727",
    "sg:postcode":"18822",
    "sg:province":"PA",
    "sg:tags":[
        "commercial",
        "agent",
        "business",
        "resume"
    ],
    "wof:name":"Penn Weber Insurance Associates Inc",
    "wof:placetype":"venue"
},
  "geometry": {"coordinates":[-75.742599,41.962509],"type":"Point"}
}