{
  "type": "Feature",
  "properties": {
    "iso:country":"US",
    "sg:address":"960 Beaver Dam Rd",
    "sg:city":"Honey Brook",
    "sg:classifiers":[
        {
            "category":"Travel",
            "subcategory":"Campground",
            "type":"Entertainment"
        }
    ],
    "sg:phone":"+1 610 273 3068",
    "sg:postcode":"19344",
    "sg:province":"PA",
    "wof:name":"Two Log Campground",
    "wof:placetype":"venue"
},
  "geometry": {"coordinates":[-75.883827,40.060771],"type":"Point"}
}