{
  "type": "Feature",
  "properties": {
    "iso:country":"US",
    "sg:address":"505 Curtis St",
    "sg:city":"Philipsburg",
    "sg:classifiers":[
        {
            "category":"Retail",
            "subcategory":"Portrait Studio",
            "type":"Services"
        }
    ],
    "sg:phone":"+1 814 342 1381",
    "sg:postcode":"16866",
    "sg:province":"PA",
    "sg:tags":[
        "photographer"
    ],
    "wof:name":"Lasting Image Photography",
    "wof:placetype":"venue"
},
  "geometry": {"coordinates":[-78.210977,40.890287],"type":"Point"}
}