{
  "type": "Feature",
  "properties": {
    "iso:country":"US",
    "sg:address":"1213 Middle St",
    "sg:city":"Pittsburgh",
    "sg:classifiers":[
        {
            "category":"Retail",
            "subcategory":"Repair Shop",
            "type":"Services"
        }
    ],
    "sg:phone":"+1   ",
    "sg:postcode":"15212",
    "sg:province":"PA",
    "sg:tags":[
        "specializing",
        "instrument",
        "sharpen"
    ],
    "wof:name":"Johns Sharpening",
    "wof:placetype":"venue"
},
  "geometry": {"coordinates":[-80.00030599999999,40.457084],"type":"Point"}
}