{
  "type": "Feature",
  "properties": {
    "addr:full":"11621 Bustleton Ave Philadelphia PA 19116",
    "addr:housenumber":"11621",
    "addr:postcode":"19116",
    "addr:street":"Bustleton Ave",
    "iso:country":"US",
    "sg:address":"11621 Bustleton Ave",
    "sg:city":"Philadelphia",
    "sg:classifiers":[
        {
            "category":"Health Services",
            "subcategory":"Doctor",
            "type":"Services"
        }
    ],
    "sg:phone":"+1   ",
    "sg:postcode":"19116",
    "sg:province":"PA",
    "sg:tags":[
        "dentist"
    ],
    "wof:name":"Mattucci Louis P DDS",
    "wof:placetype":"venue"
},
  "geometry": {"coordinates":[-75.018156,40.118377],"type":"Point"}
}