{
  "type": "Feature",
  "properties": {
    "iso:country":"US",
    "sg:address":"5306 Carlisle Pike",
    "sg:city":"Mechanicsburg",
    "sg:classifiers":[
        {
            "category":"Restaurant",
            "type":"Food & Drink"
        }
    ],
    "sg:phone":"+1 717 697 5306",
    "sg:postcode":"17050",
    "sg:province":"PA",
    "sg:tags":[
        "bakery",
        "retail",
        "eating"
    ],
    "wof:name":"Dunkin Donuts",
    "wof:placetype":"venue"
},
  "geometry": {"coordinates":[-76.98366,40.240145],"type":"Point"}
}