{
  "type": "Feature",
  "properties": {
    "addr:full":"3527 Pine Ave Reading PA 19606",
    "addr:housenumber":"3527",
    "addr:postcode":"19606",
    "addr:street":"Pine Ave",
    "iso:country":"US",
    "sg:address":"3527 Pine Ave",
    "sg:city":"Reading",
    "sg:classifiers":[
        {
            "category":"Professional",
            "type":"Services"
        }
    ],
    "sg:phone":"+1   ",
    "sg:postcode":"19606",
    "sg:province":"PA",
    "wof:name":"Leslie Leinbach",
    "wof:placetype":"venue"
},
  "geometry": {"coordinates":[-75.863353,40.328654],"type":"Point"}
}