{
  "type": "Feature",
  "properties": {
    "addr:full":"120 Oakland Ave Pittsburgh PA 15213",
    "addr:housenumber":"120",
    "addr:postcode":"15213",
    "addr:street":"Oakland Ave",
    "iso:country":"US",
    "sg:address":"120 Oakland Ave",
    "sg:city":"Pittsburgh",
    "sg:classifiers":[
        {
            "category":"Deli",
            "type":"Food & Drink"
        },
        {
            "category":"Restaurant",
            "type":"Food & Drink"
        }
    ],
    "sg:menulink":"http://www.allmenus.com/pa/pittsburgh/18490-quiznos-sub/menu/",
    "sg:phone":"+1 412 683 1177",
    "sg:postcode":"15213",
    "sg:province":"PA",
    "sg:tags":[
        "deli",
        "soup",
        "american",
        "sandwich",
        "wrap"
    ],
    "wof:name":"Quiznos Sub",
    "wof:placetype":"venue"
},
  "geometry": {"coordinates":[-79.95768700000001,40.442107],"type":"Point"}
}