{
  "type": "Feature",
  "properties": {
    "addr:full":"9 N 3rd St Lewisburg PA 17837",
    "addr:housenumber":"9",
    "addr:postcode":"17837",
    "addr:street":"N 3Rd St",
    "iso:country":"US",
    "sg:address":"9 N 3rd St",
    "sg:city":"Lewisburg",
    "sg:classifiers":[
        {
            "category":"Government",
            "subcategory":"Office",
            "type":"Public Place"
        }
    ],
    "sg:phone":"+1   ",
    "sg:postcode":"17837",
    "sg:province":"PA",
    "sg:tags":[
        "administrative",
        "program",
        "health"
    ],
    "wof:name":"Campaign For Life The",
    "wof:placetype":"venue"
},
  "geometry": {"coordinates":[-76.886049,40.96555],"type":"Point"}
}