{
  "type": "Feature",
  "properties": {
    "addr:full":"74 Harmony Rd Levittown PA 19056",
    "addr:housenumber":"74",
    "addr:postcode":"19056",
    "addr:street":"Harmony Rd Levittown",
    "iso:country":"US",
    "sg:address":"74 Harmony Rd",
    "sg:city":"Levittown",
    "sg:phone":"+1 267 467 8052",
    "sg:postcode":"19056",
    "sg:province":"PA",
    "wof:name":"Tara Dembinski",
    "wof:placetype":"venue"
},
  "geometry": {"coordinates":[-74.883629,40.167093],"type":"Point"}
}