{
  "type": "Feature",
  "properties": {
    "iso:country":"US",
    "sg:address":"6360 Flank Dr",
    "sg:city":"Harrisburg",
    "sg:classifiers":[
        {
            "category":"Utilities",
            "subcategory":"Telephone",
            "type":"Services"
        }
    ],
    "sg:phone":"+1   ",
    "sg:postcode":"17112",
    "sg:province":"PA",
    "sg:tags":[
        "communications"
    ],
    "wof:name":"Commonwealth Telephone Entps",
    "wof:placetype":"venue"
},
  "geometry": {"coordinates":[-76.77375499999999,40.327991],"type":"Point"}
}