{
  "type": "Feature",
  "properties": {
    "addr:full":"95 E Queen St Stevens PA 17578",
    "addr:housenumber":"95",
    "addr:postcode":"stevens;17578",
    "addr:street":"E Queen St",
    "iso:country":"US",
    "sg:address":"95 E Queen St",
    "sg:city":"Stevens",
    "sg:classifiers":[
        {
            "category":"Retail",
            "subcategory":"Repair Shop",
            "type":"Services"
        }
    ],
    "sg:phone":"+1 717 336 3330",
    "sg:postcode":"17578",
    "sg:province":"PA",
    "sg:tags":[
        "repairing",
        "equipment",
        "electric"
    ],
    "wof:name":"Musser's Electric Motor Svc",
    "wof:placetype":"venue"
},
  "geometry": {"coordinates":[-76.171886,40.239531],"type":"Point"}
}