{
  "type": "Feature",
  "properties": {
    "iso:country":"US",
    "sg:address":"305 Forbes Ave",
    "sg:city":"Pittsburgh",
    "sg:classifiers":[
        {
            "category":"Personal",
            "subcategory":"Tanning Parlor",
            "type":"Services"
        },
        {
            "category":"Personal",
            "subcategory":"Barber",
            "type":"Services"
        },
        {
            "category":"Personal",
            "subcategory":"Nail Salon",
            "type":"Services"
        }
    ],
    "sg:phone":"+1 412 281 3155",
    "sg:postcode":"15222",
    "sg:province":"PA",
    "wof:name":"Domeniques Hair Studio",
    "wof:placetype":"venue"
},
  "geometry": {"coordinates":[-80.000702,40.440102],"type":"Point"}
}