{
  "type": "Feature",
  "properties": {
    "addr:full":"14 S York Rd Hatboro PA 19040",
    "addr:housenumber":"14",
    "addr:postcode":"19040",
    "addr:street":"S York Rd",
    "iso:country":"US",
    "sg:address":"14 S York Rd",
    "sg:city":"Hatboro",
    "sg:phone":"+1 215 773 9464",
    "sg:postcode":"19040",
    "sg:province":"PA",
    "wof:name":"Main Street Kitchens & Baths",
    "wof:placetype":"venue"
},
  "geometry": {"coordinates":[-75.106329,40.176747],"type":"Point"}
}