{
  "type": "Feature",
  "properties": {
    "iso:country":"US",
    "sg:address":"215 Fence Row Dr",
    "sg:city":"Nazareth",
    "sg:classifiers":[
        {
            "category":"Sports & Exercise",
            "subcategory":"Race Track",
            "type":"Entertainment"
        }
    ],
    "sg:phone":"+1   ",
    "sg:postcode":"18064",
    "sg:province":"PA",
    "sg:tags":[
        "operation",
        "racing",
        "or"
    ],
    "wof:name":"G&B Racing Inc",
    "wof:placetype":"venue"
},
  "geometry": {"coordinates":[-75.268238,40.782236],"type":"Point"}
}