{
  "type": "Feature",
  "properties": {
    "iso:country":"US",
    "sg:address":"134 W 5th St",
    "sg:city":"Chester",
    "sg:classifiers":[
        {
            "category":"Retail",
            "subcategory":"Auto Repair",
            "type":"Services"
        }
    ],
    "sg:phone":"+1 610 872 1400",
    "sg:postcode":"19013",
    "sg:province":"PA",
    "sg:tags":[
        "repairing",
        "automobile"
    ],
    "wof:name":"Fury's Automotive",
    "wof:placetype":"venue"
},
  "geometry": {"coordinates":[-75.36292299999999,39.847005],"type":"Point"}
}