{
  "type": "Feature",
  "properties": {
    "iso:country":"US",
    "sg:address":"4515 William Penn Hwy",
    "sg:city":"Monroeville",
    "sg:classifiers":[
        {
            "category":"Retail",
            "subcategory":"Auto Repair",
            "type":"Services"
        }
    ],
    "sg:phone":"+1 412 374 1111",
    "sg:postcode":"15146",
    "sg:province":"PA",
    "sg:tags":[
        "general"
    ],
    "wof:name":"Cochran Automotive",
    "wof:placetype":"venue"
},
  "geometry": {"coordinates":[-79.74153200000001,40.438374],"type":"Point"}
}