{
  "type": "Feature",
  "properties": {
    "addr:full":"7550 Rugby St Philadelphia PA 19150",
    "addr:housenumber":"7550",
    "addr:postcode":"19150",
    "addr:street":"Rugby St",
    "iso:country":"US",
    "sg:address":"7550 Rugby St",
    "sg:city":"Philadelphia",
    "sg:classifiers":[
        {
            "category":"Manufacturing",
            "subcategory":"Printing",
            "type":"Manufacturing & Wholesale Goods"
        }
    ],
    "sg:phone":"+1   ",
    "sg:postcode":"19150",
    "sg:province":"PA",
    "sg:tags":[
        "lithographic",
        "commercial"
    ],
    "wof:name":"Gabbies Printing",
    "wof:placetype":"venue"
},
  "geometry": {"coordinates":[-75.162779,40.066261],"type":"Point"}
}