{
  "type": "Feature",
  "properties": {
    "addr:full":"11 Braddock Dr Latrobe PA 15650",
    "addr:housenumber":"11",
    "addr:postcode":"15650",
    "addr:street":"Braddock Dr",
    "iso:country":"US",
    "sg:address":"11 Braddock Dr",
    "sg:city":"Latrobe",
    "sg:classifiers":[
        {
            "category":"Retail",
            "subcategory":"Repair Shop",
            "type":"Services"
        }
    ],
    "sg:phone":"+1 724 537 9370",
    "sg:postcode":"15650",
    "sg:province":"PA",
    "sg:tags":[
        "equipment",
        "conditioning",
        "air"
    ],
    "wof:name":"TLC Heating & Air Cond",
    "wof:placetype":"venue"
},
  "geometry": {"coordinates":[-79.39933499999999,40.319128],"type":"Point"}
}