{
  "type": "Feature",
  "properties": {
    "iso:country":"US",
    "sg:address":"1185 W Chester Rd",
    "sg:city":"West Chester",
    "sg:classifiers":[
        {
            "category":"Retail",
            "subcategory":"Laundry & Dry Cleaning",
            "type":"Services"
        }
    ],
    "sg:phone":"+1   ",
    "sg:postcode":"19382",
    "sg:province":"PA",
    "sg:tags":[
        "drycleaning",
        "plant"
    ],
    "wof:name":"Orth Cleaners Enterprises",
    "wof:placetype":"venue"
},
  "geometry": {"coordinates":[-75.546958,39.911161],"type":"Point"}
}