{
  "type": "Feature",
  "properties": {
    "iso:country":"US",
    "sg:address":"1400 Fleming Ave",
    "sg:city":"Mc Kees Rocks",
    "sg:classifiers":[
        {
            "category":"Manufacturing",
            "subcategory":"Motor Vehicles & Parts",
            "type":"Manufacturing & Wholesale Goods"
        }
    ],
    "sg:phone":"+1   ",
    "sg:postcode":"15136",
    "sg:province":"PA",
    "sg:tags":[
        "durable"
    ],
    "wof:name":"Aceomatic-Recon Llc",
    "wof:placetype":"venue"
},
  "geometry": {"coordinates":[-80.07681599999999,40.48783],"type":"Point"}
}