{
  "type": "Feature",
  "properties": {
    "iso:country":"US",
    "sg:address":"4778 McKnight Rd",
    "sg:city":"Pittsburgh",
    "sg:classifiers":[
        {
            "category":"Home & Garden",
            "subcategory":"Furniture",
            "type":"Retail Goods"
        }
    ],
    "sg:phone":"+1   ",
    "sg:postcode":"15237",
    "sg:province":"PA",
    "wof:name":"Tonys Got It",
    "wof:placetype":"venue"
},
  "geometry": {"coordinates":[-80.012388,40.500062],"type":"Point"}
}