{
  "type": "Feature",
  "properties": {
    "addr:full":"2251 Fraley St Philadelphia PA 19137",
    "addr:housenumber":"2251",
    "addr:postcode":"19137",
    "addr:street":"Fraley St",
    "iso:country":"US",
    "sg:address":"2251 Fraley St",
    "sg:city":"Philadelphia",
    "sg:classifiers":[
        {
            "category":"Manufacturing",
            "subcategory":"Apparel",
            "type":"Manufacturing & Wholesale Goods"
        }
    ],
    "sg:phone":"+1 215 744 1138",
    "sg:postcode":"19137",
    "sg:province":"PA",
    "sg:tags":[
        "cap",
        "hat",
        "millinery"
    ],
    "wof:name":"S & S Hat Co Store",
    "wof:placetype":"venue"
},
  "geometry": {"coordinates":[-75.064649,40.010784],"type":"Point"}
}