{
  "type": "Feature",
  "properties": {
    "iso:country":"US",
    "sg:address":"419 Dinwiddie St",
    "sg:city":"Pittsburgh",
    "sg:classifiers":[
        {
            "category":"Education",
            "subcategory":"Library",
            "type":"Public Place"
        }
    ],
    "sg:phone":"+1 412 281 3753",
    "sg:postcode":"15219",
    "sg:province":"PA",
    "wof:name":"Carnegie Library of Pittsburgh",
    "wof:placetype":"venue"
},
  "geometry": {"coordinates":[-79.98065,40.442604],"type":"Point"}
}