{
  "type": "Feature",
  "properties": {
    "addr:full":"35 Country Ln Honey Brook PA 19344",
    "addr:housenumber":"35",
    "addr:postcode":"19344",
    "addr:street":"Country Ln",
    "iso:country":"US",
    "sg:address":"35 Country Ln",
    "sg:city":"Honey Brook",
    "sg:classifiers":[
        {
            "category":"Freight",
            "type":"Transportation"
        }
    ],
    "sg:phone":"+1   ",
    "sg:postcode":"19344",
    "sg:province":"PA",
    "sg:tags":[
        "operator",
        "local",
        "trucking"
    ],
    "wof:name":"Edward R Beachy",
    "wof:placetype":"venue"
},
  "geometry": {"coordinates":[-75.909533,40.11778],"type":"Point"}
}