{
  "type": "Feature",
  "properties": {
    "iso:country":"US",
    "sg:address":"4240 Locust Ln Ste 1",
    "sg:city":"Harrisburg",
    "sg:classifiers":[
        {
            "category":"Health Services",
            "subcategory":"Dentist",
            "type":"Services"
        }
    ],
    "sg:phone":"+1 717 412 1003",
    "sg:postcode":"17109",
    "sg:province":"PA",
    "sg:website":"www.lrhdentistry.com",
    "wof:name":"Lupinetti Rogliano Hockenberry",
    "wof:placetype":"venue"
},
  "geometry": {"coordinates":[-76.819574,40.291564],"type":"Point"}
}