{
  "type": "Feature",
  "properties": {
    "iso:country":"US",
    "sg:address":"112 Maple St",
    "sg:city":"Hyndman",
    "sg:classifiers":[
        {
            "category":"Organizations",
            "subcategory":"Religious Organization",
            "type":"Services"
        }
    ],
    "sg:phone":"+1 814 842 6366",
    "sg:postcode":"15545",
    "sg:province":"PA",
    "sg:tags":[
        "church"
    ],
    "wof:name":"First United Church Of Christ",
    "wof:placetype":"venue"
},
  "geometry": {"coordinates":[-78.721768,39.818564],"type":"Point"}
}