{
  "type": "Feature",
  "properties": {
    "addr:full":"3608 State Rte 8 Titusville PA 16354",
    "addr:housenumber":"3608",
    "addr:postcode":"16354",
    "addr:street":"State Rte 8",
    "iso:country":"US",
    "sg:address":"3608 State Rte 8",
    "sg:city":"Titusville",
    "sg:classifiers":[
        {
            "category":"Personal",
            "subcategory":"Beauty Salon",
            "type":"Services"
        }
    ],
    "sg:phone":"+1 814 827 1342",
    "sg:postcode":"16354",
    "sg:province":"PA",
    "wof:name":"Yvonne's House Of Beauty",
    "wof:placetype":"venue"
},
  "geometry": {"coordinates":[-79.696911,41.55718],"type":"Point"}
}