{
  "type": "Feature",
  "properties": {
    "iso:country":"US",
    "sg:address":"609 Merion Ave",
    "sg:city":"Havertown",
    "sg:classifiers":[
        {
            "category":"Professional",
            "subcategory":"Employment Agencies",
            "type":"Services"
        }
    ],
    "sg:phone":"+1   ",
    "sg:postcode":"19083",
    "sg:province":"PA",
    "wof:name":"Physicians Resource Management",
    "wof:placetype":"venue"
},
  "geometry": {"coordinates":[-75.287851,39.981366],"type":"Point"}
}