{
  "type": "Feature",
  "properties": {
    "iso:country":"US",
    "sg:address":"745 Willow Ln",
    "sg:city":"Gap",
    "sg:classifiers":[
        {
            "category":"Building & Trades",
            "subcategory":"Construction",
            "type":"Services"
        }
    ],
    "sg:phone":"+1   ",
    "sg:postcode":"17527",
    "sg:province":"PA",
    "sg:tags":[
        "hanging",
        "contractor"
    ],
    "wof:name":"Osborne Painting",
    "wof:placetype":"venue"
},
  "geometry": {"coordinates":[-76.00027900000001,39.99301],"type":"Point"}
}