{
  "type": "Feature",
  "properties": {
    "addr:full":"48 Washington Blvd Williamsport PA 17701",
    "addr:housenumber":"48",
    "addr:postcode":"17701",
    "addr:street":"Washington Blvd",
    "iso:country":"US",
    "sg:address":"48 Washington Blvd",
    "sg:city":"Williamsport",
    "sg:classifiers":[
        {
            "category":"Retail",
            "subcategory":"Car Wash",
            "type":"Services"
        }
    ],
    "sg:phone":"+1   ",
    "sg:postcode":"17701",
    "sg:province":"PA",
    "sg:tags":[
        "carwash"
    ],
    "wof:name":"Davids Car Grooming Inc",
    "wof:placetype":"venue"
},
  "geometry": {"coordinates":[-77.003066,41.24695],"type":"Point"}
}