{
  "type": "Feature",
  "properties": {
    "addr:full":"42 West Ave Albion PA 16401",
    "addr:housenumber":"42",
    "addr:postcode":"16401",
    "addr:street":"West Ave",
    "iso:country":"US",
    "sg:address":"42 West Ave",
    "sg:city":"Albion",
    "sg:classifiers":[
        {
            "category":"Personal",
            "subcategory":"Beauty Salon",
            "type":"Services"
        }
    ],
    "sg:phone":"+1 814 756 5444",
    "sg:postcode":"16401",
    "sg:province":"PA",
    "sg:tags":[
        "shop"
    ],
    "wof:name":"Haircare By Lynne",
    "wof:placetype":"venue"
},
  "geometry": {"coordinates":[-80.370958,41.889747],"type":"Point"}
}