{
  "type": "Feature",
  "properties": {
    "addr:full":"112 E High St Carlisle PA 17013",
    "addr:housenumber":"112",
    "addr:postcode":"17013",
    "addr:street":"E High St",
    "iso:country":"US",
    "sg:address":"112 E High St",
    "sg:city":"Carlisle",
    "sg:classifiers":[
        {
            "category":"Shopping",
            "subcategory":"Crafts & Fabrics",
            "type":"Retail Goods"
        }
    ],
    "sg:phone":"+1   ",
    "sg:postcode":"17013",
    "sg:province":"PA",
    "sg:tags":[
        "sewing"
    ],
    "wof:name":"Jo-Ann Fabrics & Crafts",
    "wof:placetype":"venue"
},
  "geometry": {"coordinates":[-77.18650700000001,40.201172],"type":"Point"}
}