{
  "type": "Feature",
  "properties": {
    "addr:full":"290 Luke Fidler Patch Rd Coal Township PA 17866",
    "addr:housenumber":"290",
    "addr:postcode":"17866",
    "addr:street":"Luke Fidler Patch Rd",
    "iso:country":"US",
    "sg:address":"290 Luke Fidler Patch Rd",
    "sg:city":"Coal Township",
    "sg:classifiers":[
        {
            "category":"Restaurant",
            "type":"Food & Drink"
        }
    ],
    "sg:phone":"+1 570 648 4673",
    "sg:postcode":"17866",
    "sg:province":"PA",
    "sg:tags":[
        "eating"
    ],
    "wof:name":"Pizza Hut",
    "wof:placetype":"venue"
},
  "geometry": {"coordinates":[-76.540955,40.790498],"type":"Point"}
}