{
  "type": "Feature",
  "properties": {
    "iso:country":"US",
    "sg:address":"750 Maple Ave",
    "sg:city":"Washington",
    "sg:classifiers":[
        {
            "category":"Retail",
            "subcategory":"Repair Shop",
            "type":"Services"
        }
    ],
    "sg:phone":"+1 724 229 3000",
    "sg:postcode":"15301",
    "sg:province":"PA",
    "sg:tags":[
        "sharpening"
    ],
    "wof:name":"Shearecon",
    "wof:placetype":"venue"
},
  "geometry": {"coordinates":[-80.260187,40.191143],"type":"Point"}
}