{
  "type": "Feature",
  "properties": {
    "iso:country":"US",
    "sg:address":"107 Mont Alto Rd",
    "sg:city":"Fayetteville",
    "sg:classifiers":[
        {
            "category":"Restaurant",
            "type":"Food & Drink"
        }
    ],
    "sg:phone":"+1 717 352 0199",
    "sg:postcode":"17222",
    "sg:province":"PA",
    "sg:tags":[
        "pizza"
    ],
    "wof:name":"Mama's Ii Pizza & Restaurant",
    "wof:placetype":"venue"
},
  "geometry": {"coordinates":[-77.552486,39.907574],"type":"Point"}
}