{
  "type": "Feature",
  "properties": {
    "iso:country":"US",
    "sg:address":"220 3rd St",
    "sg:city":"Carnegie",
    "sg:classifiers":[
        {
            "category":"Shopping",
            "type":"Retail Goods"
        }
    ],
    "sg:phone":"+1 412 276 5233",
    "sg:postcode":"15106",
    "sg:province":"PA",
    "sg:tags":[
        "picture",
        "frame",
        "art",
        "gallery"
    ],
    "wof:name":"3rd Street Art Gallery & Frmng",
    "wof:placetype":"venue"
},
  "geometry": {"coordinates":[-80.09047700000001,40.403963],"type":"Point"}
}