{
  "type": "Feature",
  "properties": {
    "addr:full":"131 Crandon Cir Beaver PA 15009",
    "addr:housenumber":"131",
    "addr:postcode":"15009",
    "addr:street":"Crandon Cir",
    "iso:country":"US",
    "sg:address":"131 Crandon Cir",
    "sg:city":"Beaver",
    "sg:classifiers":[
        {
            "category":"Professional",
            "subcategory":"Advertising",
            "type":"Services"
        }
    ],
    "sg:phone":"+1   ",
    "sg:postcode":"15009",
    "sg:province":"PA",
    "sg:tags":[
        "agency"
    ],
    "wof:name":"Moogoo Inc",
    "wof:placetype":"venue"
},
  "geometry": {"coordinates":[-80.331501,40.701543],"type":"Point"}
}