{
  "type": "Feature",
  "properties": {
    "iso:country":"US",
    "sg:address":"631 N Pike Rd",
    "sg:city":"Cabot",
    "sg:classifiers":[
        {
            "category":"Retail",
            "subcategory":"Auto Repair",
            "type":"Services"
        }
    ],
    "sg:phone":"+1   ",
    "sg:postcode":"16023",
    "sg:province":"PA",
    "sg:tags":[
        "body"
    ],
    "wof:name":"Moores Auto Center",
    "wof:placetype":"venue"
},
  "geometry": {"coordinates":[-79.79033699999999,40.770109],"type":"Point"}
}