{
  "type": "Feature",
  "properties": {
    "iso:country":"US",
    "sg:address":"24 N Church St",
    "sg:city":"Waynesboro",
    "sg:classifiers":[
        {
            "category":"Building & Trades",
            "subcategory":"Cleaning & Sanitation",
            "type":"Services"
        },
        {
            "category":"Home & Garden",
            "subcategory":"Carpets & Floor Coverings",
            "type":"Retail Goods"
        }
    ],
    "sg:phone":"+1 717 762 8030",
    "sg:postcode":"17268",
    "sg:province":"PA",
    "sg:tags":[
        "carpeting"
    ],
    "wof:name":"Bane-Clene Way",
    "wof:placetype":"venue"
},
  "geometry": {"coordinates":[-77.5774,39.755901],"type":"Point"}
}