{
  "type": "Feature",
  "properties": {
    "iso:country":"US",
    "sg:address":"433 N 21st St",
    "sg:city":"Camp Hill",
    "sg:classifiers":[
        {
            "category":"Restaurant",
            "type":"Food & Drink"
        }
    ],
    "sg:phone":"+1 717 724 2803",
    "sg:postcode":"17011",
    "sg:province":"PA",
    "sg:tags":[
        "new",
        "american"
    ],
    "sg:website":"www.thecellarbyob.com/",
    "wof:name":"Cellar Restaurant",
    "wof:placetype":"venue"
},
  "geometry": {"coordinates":[-76.922905,40.2505],"type":"Point"}
}