{
  "type": "Feature",
  "properties": {
    "iso:country":"US",
    "sg:address":"254 E 10th St",
    "sg:city":"Erie",
    "sg:classifiers":[
        {
            "category":"Place Of Worship",
            "subcategory":"Church",
            "type":"Public Place"
        },
        {
            "category":"Place Of Worship",
            "type":"Public Place"
        }
    ],
    "sg:phone":"+1 814 456 6254",
    "sg:postcode":"16503",
    "sg:province":"PA",
    "sg:tags":[
        "covenant",
        "lutheran",
        "churches-covenant",
        "churches-evangelical",
        "churches-lutheran-evangelical",
        "america",
        "churches-lutheran"
    ],
    "sg:website":"http://www.luthermemorialonline.org",
    "wof:name":"Bethany Evang Lutheran Ch",
    "wof:placetype":"venue"
},
  "geometry": {"coordinates":[-80.077585,42.127366],"type":"Point"}
}