{
  "type": "Feature",
  "properties": {
    "addr:full":"150 Selkirk Rd Williamsport PA 17701",
    "addr:housenumber":"150",
    "addr:postcode":"17701",
    "addr:street":"Selkirk Rd",
    "iso:country":"US",
    "sg:address":"150 Selkirk Rd",
    "sg:city":"Williamsport",
    "sg:classifiers":[
        {
            "category":"Manufacturing",
            "subcategory":"Apparel",
            "type":"Manufacturing & Wholesale Goods"
        }
    ],
    "sg:phone":"+1   ",
    "sg:postcode":"17701",
    "sg:province":"PA",
    "sg:tags":[
        "mfg"
    ],
    "wof:name":"Olinsky Judy Larura Flynn",
    "wof:placetype":"venue"
},
  "geometry": {"coordinates":[-77.003781,41.260296],"type":"Point"}
}