{
  "type": "Feature",
  "properties": {
    "iso:country":"US",
    "sg:address":"12750 Hollins Rd",
    "sg:city":"Philadelphia",
    "sg:classifiers":[
        {
            "category":"Building & Trades",
            "subcategory":"Construction",
            "type":"Services"
        }
    ],
    "sg:phone":"+1 215 824 3775",
    "sg:postcode":"19154",
    "sg:province":"PA",
    "sg:tags":[
        "house",
        "contractor",
        "nonresidential"
    ],
    "wof:name":"Gilchrist Construction Inc",
    "wof:placetype":"venue"
},
  "geometry": {"coordinates":[-74.9636,40.100201],"type":"Point"}
}