{
  "type": "Feature",
  "properties": {
    "addr:full":"628 E Penn St Muncy PA 17756",
    "addr:housenumber":"628",
    "addr:postcode":"17756",
    "addr:street":"E Penn St",
    "iso:country":"US",
    "sg:address":"628 E Penn St",
    "sg:city":"Muncy",
    "sg:classifiers":[
        {
            "category":"Organizations",
            "subcategory":"Religious Organization",
            "type":"Services"
        }
    ],
    "sg:phone":"+1 570 546 7814",
    "sg:postcode":"17756",
    "sg:province":"PA",
    "wof:name":"Evangelical Free Fellowship",
    "wof:placetype":"venue"
},
  "geometry": {"coordinates":[-76.771575,41.206188],"type":"Point"}
}