{
  "type": "Feature",
  "properties": {
    "addr:full":"3119 Pennsylvania Ave Glenside PA 19038",
    "addr:housenumber":"3119",
    "addr:postcode":"19038",
    "addr:street":"Pennsylvania Ave",
    "iso:country":"US",
    "sg:address":"3119 Pennsylvania Ave",
    "sg:city":"Glenside",
    "sg:classifiers":[
        {
            "category":"Building & Trades",
            "subcategory":"Construction",
            "type":"Services"
        }
    ],
    "sg:phone":"+1 215 885 7900",
    "sg:postcode":"19038",
    "sg:province":"PA",
    "sg:tags":[
        "pointing",
        "tuck"
    ],
    "wof:name":"Kevin Mcnamara Masonry Restoration Inc",
    "wof:placetype":"venue"
},
  "geometry": {"coordinates":[-75.17147799999999,40.113434],"type":"Point"}
}