{
  "type": "Feature",
  "properties": {
    "iso:country":"US",
    "sg:address":"5407 Nicholas Ct",
    "sg:city":"Pipersville",
    "sg:classifiers":[
        {
            "category":"Professional",
            "subcategory":"Management & Consulting",
            "type":"Services"
        }
    ],
    "sg:phone":"+1   ",
    "sg:postcode":"18947",
    "sg:province":"PA",
    "sg:tags":[
        "marketing",
        "aircraft",
        "ch",
        "consultant",
        "vehicle"
    ],
    "wof:name":"Sierra Transportation Group",
    "wof:placetype":"venue"
},
  "geometry": {"coordinates":[-75.10770599999999,40.383701],"type":"Point"}
}