{
  "type": "Feature",
  "properties": {
    "iso:country":"US",
    "sg:address":"529 College Dr",
    "sg:city":"Allentown",
    "sg:classifiers":[
        {
            "category":"Professional",
            "subcategory":"Computer Services",
            "type":"Services"
        }
    ],
    "sg:phone":"+1 610 437 1577",
    "sg:postcode":"18104",
    "sg:province":"PA",
    "sg:tags":[
        "system",
        "install"
    ],
    "sg:website":"www.clickonaurora.com",
    "wof:name":"Aurora Computers LLC",
    "wof:placetype":"venue"
},
  "geometry": {"coordinates":[-75.51058999999999,40.583321],"type":"Point"}
}