{
  "type": "Feature",
  "properties": {
    "iso:country":"US",
    "sg:address":"200 Camp Hill Rd",
    "sg:city":"Fort Washington",
    "sg:classifiers":[
        {
            "category":"Organizations",
            "subcategory":"Non-profit Organization",
            "type":"Services"
        }
    ],
    "sg:phone":"+1 215 643 5400",
    "sg:postcode":"19034",
    "sg:province":"PA",
    "sg:website":"www.wordsworth.org",
    "wof:name":"Wordsworth Academy",
    "wof:placetype":"venue"
},
  "geometry": {"coordinates":[-75.191643,40.127571],"type":"Point"}
}