{
  "type": "Feature",
  "properties": {
    "addr:full":"4025 Lincoln Way E Fayetteville PA 17222",
    "addr:housenumber":"4025",
    "addr:postcode":"17222",
    "addr:street":"Lincoln Way E",
    "iso:country":"US",
    "sg:address":"4025 Lincoln Way E",
    "sg:city":"Fayetteville",
    "sg:classifiers":[
        {
            "category":"Government",
            "subcategory":"Post Office",
            "type":"Public Place"
        }
    ],
    "sg:phone":"+1 717 352 2022",
    "sg:postcode":"17222",
    "sg:province":"PA",
    "sg:tags":[
        "postal",
        "us"
    ],
    "wof:name":"US Post Office",
    "wof:placetype":"venue"
},
  "geometry": {"coordinates":[-77.560625,39.910584],"type":"Point"}
}