{
  "type": "Feature",
  "properties": {
    "iso:country":"US",
    "sg:address":"12 Locust Dr",
    "sg:city":"Pittsburgh",
    "sg:classifiers":[
        {
            "category":"Social Services",
            "subcategory":"Child Care",
            "type":"Services"
        }
    ],
    "sg:phone":"+1 412 828 3290",
    "sg:postcode":"15238",
    "sg:province":"PA",
    "sg:tags":[
        "kindergarten",
        "academic",
        "school"
    ],
    "wof:name":"Just For Kids Learning Ctr",
    "wof:placetype":"venue"
},
  "geometry": {"coordinates":[-79.856841,40.513353],"type":"Point"}
}