{
  "type": "Feature",
  "properties": {
    "addr:full":"4518 Union Deposit Rd Harrisburg PA 17111",
    "addr:housenumber":"4518",
    "addr:postcode":"17111",
    "addr:street":"Union Deposit Rd",
    "iso:country":"US",
    "sg:address":"4518 Union Deposit Rd",
    "sg:city":"Harrisburg",
    "sg:classifiers":[
        {
            "category":"Health Services",
            "subcategory":"Doctor",
            "type":"Services"
        }
    ],
    "sg:phone":"+1 717 901 8000",
    "sg:postcode":"17111",
    "sg:province":"PA",
    "sg:tags":[
        "physician",
        "surgeon"
    ],
    "wof:name":"Orthopaedic Surgeons-Central",
    "wof:placetype":"venue"
},
  "geometry": {"coordinates":[-76.80631200000001,40.279914],"type":"Point"}
}