{
  "type": "Feature",
  "properties": {
    "addr:full":"16 Crafton St Wellsboro PA 16901",
    "addr:housenumber":"16",
    "addr:postcode":"16901",
    "addr:street":"Crafton St",
    "iso:country":"US",
    "sg:address":"16 Crafton St",
    "sg:city":"Wellsboro",
    "sg:classifiers":[
        {
            "category":"Professional",
            "subcategory":"Accounting & Tax Preparation",
            "type":"Services"
        }
    ],
    "sg:phone":"+1 570 723 8713",
    "sg:postcode":"16901",
    "sg:province":"PA",
    "sg:tags":[
        "bookkeeping",
        "general"
    ],
    "wof:name":"Three Y's Accounting Svc",
    "wof:placetype":"venue"
},
  "geometry": {"coordinates":[-77.30126,41.748046],"type":"Point"}
}