{
  "type": "Feature",
  "properties": {
    "iso:country":"US",
    "sg:address":"136 Cowpath Rd",
    "sg:city":"Telford",
    "sg:classifiers":[
        {
            "category":"Farming",
            "subcategory":"Livestock Farm",
            "type":"Manufacturing & Wholesale Goods"
        }
    ],
    "sg:phone":"+1   ",
    "sg:postcode":"18969",
    "sg:province":"PA",
    "sg:tags":[
        "hog",
        "or",
        "feedlot"
    ],
    "wof:name":"Kermit Moyer",
    "wof:placetype":"venue"
},
  "geometry": {"coordinates":[-75.357891,40.339706],"type":"Point"}
}