{
  "type": "Feature",
  "properties": {
    "iso:country":"US",
    "sg:address":"2415 Street Rd",
    "sg:city":"Warrington",
    "sg:classifiers":[
        {
            "category":"Building & Trades",
            "subcategory":"Construction",
            "type":"Services"
        }
    ],
    "sg:phone":"+1 215 918 2100",
    "sg:postcode":"18976",
    "sg:province":"PA",
    "sg:tags":[
        "contractor"
    ],
    "sg:website":"www.acsbuildingservices.com",
    "wof:name":"A C S Building Services Inc",
    "wof:placetype":"venue"
},
  "geometry": {"coordinates":[-75.14954899999999,40.236033],"type":"Point"}
}