{
  "type": "Feature",
  "properties": {
    "iso:country":"US",
    "sg:address":"240 State St",
    "sg:city":"St Marys",
    "sg:classifiers":[
        {
            "category":"Retail",
            "subcategory":"Car Wash",
            "type":"Services"
        }
    ],
    "sg:phone":"+1 814 834 1186",
    "sg:postcode":"15857",
    "sg:province":"PA",
    "sg:tags":[
        "polishing",
        "washing"
    ],
    "wof:name":"Windfall Car Wash",
    "wof:placetype":"venue"
},
  "geometry": {"coordinates":[-78.56597600000001,41.42374],"type":"Point"}
}