{
  "type": "Feature",
  "properties": {
    "iso:country":"US",
    "sg:address":"819 N Octorara Trl",
    "sg:city":"Parkesburg",
    "sg:classifiers":[
        {
            "category":"Professional",
            "subcategory":"Art Services",
            "type":"Services"
        }
    ],
    "sg:phone":"+1 610 857 4030",
    "sg:postcode":"19365",
    "sg:province":"PA",
    "sg:tags":[
        "interior",
        "designer",
        "decorator"
    ],
    "wof:name":"Interior Concepts",
    "wof:placetype":"venue"
},
  "geometry": {"coordinates":[-75.93342,39.989075],"type":"Point"}
}