{
  "type": "Feature",
  "properties": {
    "iso:country":"US",
    "sg:address":"300 Rising Sun Rd",
    "sg:city":"Millersburg",
    "sg:classifiers":[
        {
            "category":"Insurance",
            "subcategory":"Insurance Agent",
            "type":"Services"
        }
    ],
    "sg:phone":"+1   ",
    "sg:postcode":"17061",
    "sg:province":"PA",
    "wof:name":"Walter Insurance Agency",
    "wof:placetype":"venue"
},
  "geometry": {"coordinates":[-76.944592,40.541706],"type":"Point"}
}