{
  "type": "Feature",
  "properties": {
    "iso:country":"US",
    "sg:address":"2417 Broad Ave",
    "sg:city":"Altoona",
    "sg:classifiers":[
        {
            "category":"Professional",
            "subcategory":"Business Services",
            "type":"Services"
        }
    ],
    "sg:phone":"+1   ",
    "sg:postcode":"16601",
    "sg:province":"PA",
    "sg:tags":[
        "merchandise"
    ],
    "wof:name":"Broad Ave Coin Exchange",
    "wof:placetype":"venue"
},
  "geometry": {"coordinates":[-78.410872,40.503952],"type":"Point"}
}