{
  "type": "Feature",
  "properties": {
    "addr:full":"190 Angletown Rd Muncy PA 17756",
    "addr:housenumber":"190",
    "addr:postcode":"17756",
    "addr:street":"Angletown Rd",
    "iso:country":"US",
    "sg:address":"190 Angletown Rd",
    "sg:city":"Muncy",
    "sg:classifiers":[
        {
            "category":"Manufacturing",
            "subcategory":"Tools & Machinery",
            "type":"Manufacturing & Wholesale Goods"
        }
    ],
    "sg:phone":"+1   ",
    "sg:postcode":"17756",
    "sg:province":"PA",
    "sg:tags":[
        "timing",
        "equipment",
        "speed",
        "mfg"
    ],
    "wof:name":"Targetron Inc",
    "wof:placetype":"venue"
},
  "geometry": {"coordinates":[-76.798042,41.202436],"type":"Point"}
}