{
  "type": "Feature",
  "properties": {
    "iso:country":"US",
    "sg:address":"528 McKean Ave",
    "sg:city":"Charleroi",
    "sg:classifiers":[
        {
            "category":"Wholesale",
            "subcategory":"Electrical",
            "type":"Manufacturing & Wholesale Goods"
        }
    ],
    "sg:phone":"+1 724 483 2035",
    "sg:postcode":"15022",
    "sg:province":"PA",
    "sg:tags":[
        "alarm",
        "burglar",
        "system"
    ],
    "wof:name":"Alarms Promotion Of Pa Inc",
    "wof:placetype":"venue"
},
  "geometry": {"coordinates":[-79.897758,40.138808],"type":"Point"}
}