{
  "type": "Feature",
  "properties": {
    "iso:country":"US",
    "sg:address":"RR 51 Box Old",
    "sg:city":"Waltersburg",
    "sg:classifiers":[
        {
            "category":"Retail",
            "subcategory":"Auto Repair",
            "type":"Services"
        }
    ],
    "sg:phone":"+1 724 439 6257",
    "sg:postcode":"15488",
    "sg:province":"PA",
    "wof:name":"C J's Video & More",
    "wof:placetype":"venue"
},
  "geometry": {"coordinates":[-79.75700399999999,39.981701],"type":"Point"}
}