{
  "type": "Feature",
  "properties": {
    "addr:full":"1332 W Ritner St Philadelphia PA 19148",
    "addr:housenumber":"1332",
    "addr:postcode":"19148",
    "addr:street":"W Ritner St",
    "iso:country":"US",
    "sg:address":"1332 W Ritner St",
    "sg:city":"Philadelphia",
    "sg:classifiers":[
        {
            "category":"Organizations",
            "subcategory":"Professional Association",
            "type":"Services"
        }
    ],
    "sg:phone":"+1   ",
    "sg:postcode":"19148",
    "sg:province":"PA",
    "wof:name":"Politically Active Physicians",
    "wof:placetype":"venue"
},
  "geometry": {"coordinates":[-75.16961000000001,39.920447],"type":"Point"}
}