{
  "type": "Feature",
  "properties": {
    "iso:country":"US",
    "sg:address":"6101 W Jefferson St",
    "sg:city":"Philadelphia",
    "sg:classifiers":[
        {
            "category":"Wholesale",
            "subcategory":"Toys & Hobbies",
            "type":"Manufacturing & Wholesale Goods"
        }
    ],
    "sg:phone":"+1 215 878 8291",
    "sg:postcode":"19151",
    "sg:province":"PA",
    "sg:tags":[
        "wholesaler"
    ],
    "wof:name":"Sun Wholesale",
    "wof:placetype":"venue"
},
  "geometry": {"coordinates":[-75.243245,39.978609],"type":"Point"}
}