{
  "type": "Feature",
  "properties": {
    "iso:country":"US",
    "sg:address":"336 4th Ave",
    "sg:city":"Pittsburgh",
    "sg:classifiers":[
        {
            "category":"Professional",
            "subcategory":"Lawyer & Legal Services",
            "type":"Services"
        }
    ],
    "sg:phone":"+1 412 391 8600",
    "sg:postcode":"15222",
    "sg:province":"PA",
    "wof:name":"Lynch Victor K Atty",
    "wof:placetype":"venue"
},
  "geometry": {"coordinates":[-80.000702,40.439098],"type":"Point"}
}