{
  "type": "Feature",
  "properties": {
    "addr:full":"1231 11th Ave Altoona PA 16601",
    "addr:housenumber":"1231",
    "addr:postcode":"16601",
    "addr:street":"11Th Ave",
    "iso:country":"US",
    "sg:address":"1231 11th Ave",
    "sg:city":"Altoona",
    "sg:classifiers":[
        {
            "category":"Local Transit",
            "type":"Transportation"
        }
    ],
    "sg:phone":"+1   ",
    "sg:postcode":"16601",
    "sg:province":"PA",
    "sg:tags":[
        "bus",
        "line"
    ],
    "wof:name":"Greyhound Bus Lines",
    "wof:placetype":"venue"
},
  "geometry": {"coordinates":[-78.40169899999999,40.515133],"type":"Point"}
}