{
  "type": "Feature",
  "properties": {
    "addr:full":"607 Bath Rd Bristol PA 19007",
    "addr:housenumber":"607",
    "addr:postcode":"19007",
    "addr:street":"Bath Rd",
    "iso:country":"US",
    "sg:address":"607 Bath Rd",
    "sg:city":"Bristol",
    "sg:classifiers":[
        {
            "category":"Building & Trades",
            "subcategory":"Electrical",
            "type":"Services"
        }
    ],
    "sg:phone":"+1 215 788 6608",
    "sg:postcode":"19007",
    "sg:province":"PA",
    "sg:tags":[
        "electrician",
        "electric",
        "contractor"
    ],
    "wof:name":"Asdc",
    "wof:placetype":"venue"
},
  "geometry": {"coordinates":[-74.864799,40.105801],"type":"Point"}
}