{
  "type": "Feature",
  "properties": {
    "addr:full":"90 E 2nd St Emporium PA 15834",
    "addr:housenumber":"90",
    "addr:postcode":"15834",
    "addr:street":"E 2Nd St",
    "iso:country":"US",
    "sg:address":"90 E 2nd St",
    "sg:city":"Emporium",
    "sg:classifiers":[
        {
            "category":"Health Services",
            "subcategory":"Doctor",
            "type":"Services"
        }
    ],
    "sg:phone":"+1 814 486 1115",
    "sg:postcode":"15834",
    "sg:province":"PA",
    "sg:tags":[
        "physician",
        "surgeon"
    ],
    "wof:name":"Cameron County Health Care Ctr",
    "wof:placetype":"venue"
},
  "geometry": {"coordinates":[-78.236467,41.510152],"type":"Point"}
}