{
  "type": "Feature",
  "properties": {
    "iso:country":"US",
    "sg:address":"50 E Philadelphia Ave",
    "sg:city":"Boyertown",
    "sg:classifiers":[
        {
            "category":"Shopping",
            "subcategory":"Pharmacy",
            "type":"Retail Goods"
        }
    ],
    "sg:phone":"+1   ",
    "sg:postcode":"19512",
    "sg:province":"PA",
    "sg:tags":[
        "drug",
        "store",
        "operates"
    ],
    "wof:name":"Medicine Shoppe The",
    "wof:placetype":"venue"
},
  "geometry": {"coordinates":[-75.63614200000001,40.332623],"type":"Point"}
}