{
  "type": "Feature",
  "properties": {
    "iso:country":"US",
    "sg:address":"162 Egypt Rd",
    "sg:city":"Norristown",
    "sg:classifiers":[
        {
            "category":"Education",
            "subcategory":"School",
            "type":"Public Place"
        }
    ],
    "sg:phone":"+1 610 277 0660",
    "sg:postcode":"19403",
    "sg:province":"PA",
    "sg:tags":[
        "private"
    ],
    "sg:website":"www.pathwayschool.org",
    "wof:name":"The Pathway School",
    "wof:placetype":"venue"
},
  "geometry": {"coordinates":[-75.387654,40.13186],"type":"Point"}
}