{
  "type": "Feature",
  "properties": {
    "iso:country":"US",
    "sg:address":"673 Blue Ridge Rd",
    "sg:city":"Pittsburgh",
    "sg:classifiers":[
        {
            "category":"Shopping",
            "subcategory":"Gifts & Souvenirs",
            "type":"Retail Goods"
        }
    ],
    "sg:phone":"+1 412 561 3131",
    "sg:postcode":"15239",
    "sg:province":"PA",
    "sg:tags":[
        "shop"
    ],
    "wof:name":"Perkin's General Store",
    "wof:placetype":"venue"
},
  "geometry": {"coordinates":[-79.71471200000001,40.46013],"type":"Point"}
}