{
  "type": "Feature",
  "properties": {
    "iso:country":"US",
    "sg:address":"4765 York Rd, PO Box 917 Rte 202 & 263",
    "sg:city":"Buckingham",
    "sg:classifiers":[
        {
            "category":"Shopping",
            "subcategory":"Bicycles & Sporting Goods",
            "type":"Retail Goods"
        },
        {
            "category":"Shopping",
            "subcategory":"Pets & Pet Supplies",
            "type":"Retail Goods"
        }
    ],
    "sg:phone":"+1 215 794 5411",
    "sg:postcode":"18912",
    "sg:province":"PA",
    "sg:website":"www.bcsaddlery.com",
    "wof:name":"Bucks County Saddlery",
    "wof:placetype":"venue"
},
  "geometry": {"coordinates":[-75.060225,40.32384],"type":"Point"}
}