{
  "type": "Feature",
  "properties": {
    "iso:country":"US",
    "sg:address":"101 N Centre St",
    "sg:city":"Pottsville",
    "sg:classifiers":[
        {
            "category":"Government",
            "subcategory":"Office",
            "type":"Public Place"
        }
    ],
    "sg:phone":"+1   ",
    "sg:postcode":"17901",
    "sg:province":"PA",
    "sg:tags":[
        "legislative",
        "body"
    ],
    "wof:name":"Tim Holden Congressman",
    "wof:placetype":"venue"
},
  "geometry": {"coordinates":[-76.195639,40.685773],"type":"Point"}
}