{
  "type": "Feature",
  "properties": {
    "addr:full":"1714 Butler St Easton PA 18042",
    "addr:housenumber":"1714",
    "addr:postcode":"18042",
    "addr:street":"Butler St",
    "iso:country":"US",
    "sg:address":"1714 Butler St",
    "sg:city":"Easton",
    "sg:classifiers":[
        {
            "category":"Restaurant",
            "type":"Food & Drink"
        }
    ],
    "sg:phone":"+1 610 253 9453",
    "sg:postcode":"18042",
    "sg:province":"PA",
    "sg:tags":[
        "eating"
    ],
    "wof:name":"George's Luncheonette",
    "wof:placetype":"venue"
},
  "geometry": {"coordinates":[-75.235975,40.684878],"type":"Point"}
}