{
  "type": "Feature",
  "properties": {
    "iso:country":"US",
    "sg:address":"285 Venetia Rd",
    "sg:city":"Wind Ridge",
    "sg:classifiers":[
        {
            "category":"Professional",
            "subcategory":"Engineering",
            "type":"Services"
        }
    ],
    "sg:phone":"+1 724 428 5268",
    "sg:postcode":"15367",
    "sg:province":"PA",
    "sg:tags":[
        "engineer"
    ],
    "wof:name":"Wind Ridge Engineering Co",
    "wof:placetype":"venue"
},
  "geometry": {"coordinates":[-80.05829900000001,40.244775],"type":"Point"}
}