{
  "type": "Feature",
  "properties": {
    "iso:country":"US",
    "sg:address":"8350 Perry Hwy",
    "sg:city":"Pittsburgh",
    "sg:classifiers":[
        {
            "category":"Restaurant",
            "type":"Food & Drink"
        }
    ],
    "sg:menulink":"http://www.allmenus.com/pa/mccandless/286290-pizza-roma/menu/",
    "sg:phone":"+1 412 367 7677",
    "sg:postcode":"15237",
    "sg:province":"PA",
    "sg:tags":[
        "american",
        "pizza"
    ],
    "wof:name":"Pizza Roma",
    "wof:placetype":"venue"
},
  "geometry": {"coordinates":[-80.039457,40.558354],"type":"Point"}
}