{
  "type": "Feature",
  "properties": {
    "addr:full":"16 Harvey Ln Malvern PA 19355",
    "addr:housenumber":"16",
    "addr:postcode":"19355",
    "addr:street":"Harvey Ln",
    "iso:country":"US",
    "sg:address":"16 Harvey Ln",
    "sg:city":"Malvern",
    "sg:classifiers":[
        {
            "category":"Professional",
            "subcategory":"Research",
            "type":"Services"
        }
    ],
    "sg:phone":"+1   ",
    "sg:postcode":"19355",
    "sg:province":"PA",
    "sg:tags":[
        "development",
        "firm",
        "commercial",
        "specializing"
    ],
    "wof:name":"Enviro-Tek",
    "wof:placetype":"venue"
},
  "geometry": {"coordinates":[-75.518535,40.021318],"type":"Point"}
}