{
  "type": "Feature",
  "properties": {
    "iso:country":"US",
    "sg:address":"602 Berkshire Dr",
    "sg:city":"Pittsburgh",
    "sg:classifiers":[
        {
            "category":"Recreation",
            "type":"Entertainment"
        }
    ],
    "sg:phone":"+1   ",
    "sg:postcode":"15215",
    "sg:province":"PA",
    "sg:tags":[
        "sporting"
    ],
    "wof:name":"Dieffenbach Tennis",
    "wof:placetype":"venue"
},
  "geometry": {"coordinates":[-79.902309,40.508109],"type":"Point"}
}