{
  "type": "Feature",
  "properties": {
    "iso:country":"US",
    "sg:address":"2701 N Fairhill St",
    "sg:city":"Philadelphia",
    "sg:classifiers":[
        {
            "category":"Food & Beverages",
            "subcategory":"Groceries & Convenience Stores",
            "type":"Retail Goods"
        }
    ],
    "sg:phone":"+1 215 634 0074",
    "sg:postcode":"19133",
    "sg:province":"PA",
    "wof:name":"Galen Services",
    "wof:placetype":"venue"
},
  "geometry": {"coordinates":[-75.14160200000001,39.992401],"type":"Point"}
}