{
  "type": "Feature",
  "properties": {
    "addr:full":"221 Simpson St Dupont PA 18641",
    "addr:housenumber":"221",
    "addr:postcode":"18641",
    "addr:street":"Simpson St",
    "iso:country":"US",
    "sg:address":"221 Simpson St",
    "sg:city":"Dupont",
    "sg:classifiers":[
        {
            "category":"Building & Trades",
            "subcategory":"Construction",
            "type":"Services"
        }
    ],
    "sg:phone":"+1 570 654 8085",
    "sg:postcode":"18641",
    "sg:province":"PA",
    "sg:tags":[
        "home",
        "improvement"
    ],
    "wof:name":"Edward Kozak Home Improvement",
    "wof:placetype":"venue"
},
  "geometry": {"coordinates":[-75.754777,41.31836],"type":"Point"}
}