{
  "type": "Feature",
  "properties": {
    "iso:country":"US",
    "sg:address":"6411 Lincoln Way E",
    "sg:city":"Fayetteville",
    "sg:classifiers":[
        {
            "category":"Professional",
            "subcategory":"Business Services",
            "type":"Services"
        }
    ],
    "sg:phone":"+1 717 352 3977",
    "sg:postcode":"17222",
    "sg:province":"PA",
    "sg:tags":[
        "messenger"
    ],
    "wof:name":"Sollenberger's Messenger Svc",
    "wof:placetype":"venue"
},
  "geometry": {"coordinates":[-77.52726800000001,39.906518],"type":"Point"}
}