{
  "type": "Feature",
  "properties": {
    "iso:country":"US",
    "sg:address":"1821 Spera Ln",
    "sg:city":"Norristown",
    "sg:classifiers":[
        {
            "category":"Wholesale",
            "subcategory":"Machinery & Supplies",
            "type":"Manufacturing & Wholesale Goods"
        }
    ],
    "sg:phone":"+1   ",
    "sg:postcode":"19403",
    "sg:province":"PA",
    "sg:tags":[
        "instrumentation",
        "product",
        "representative",
        "tempe",
        "mfg"
    ],
    "wof:name":"Instruments & Thermal Products",
    "wof:placetype":"venue"
},
  "geometry": {"coordinates":[-75.369029,40.137935],"type":"Point"}
}