{
  "type": "Feature",
  "properties": {
    "addr:full":"5096 N Jarrod Ct Erie PA 16506",
    "addr:housenumber":"5096",
    "addr:postcode":"16506",
    "addr:street":"N Jarrod Ct",
    "iso:country":"US",
    "sg:address":"5096 N Jarrod Ct",
    "sg:city":"Erie",
    "sg:classifiers":[
        {
            "category":"Farming",
            "subcategory":"Farm",
            "type":"Manufacturing & Wholesale Goods"
        }
    ],
    "sg:phone":"+1   ",
    "sg:postcode":"16506",
    "sg:province":"PA",
    "sg:tags":[
        "crop",
        "general"
    ],
    "wof:name":"Donald Baroth Sr",
    "wof:placetype":"venue"
},
  "geometry": {"coordinates":[-80.136775,42.064553],"type":"Point"}
}