{
  "type": "Feature",
  "properties": {
    "addr:full":"3401 W 26th St Erie PA 16506",
    "addr:housenumber":"3401",
    "addr:postcode":"16506",
    "addr:street":"W 26Th St",
    "iso:country":"US",
    "sg:address":"3401 W 26th St",
    "sg:city":"Erie",
    "sg:classifiers":[
        {
            "category":"Autos & Motor Vehicles",
            "subcategory":"Automobile Sales",
            "type":"Retail Goods"
        }
    ],
    "sg:phone":"+1 814 835 3318",
    "sg:postcode":"16506",
    "sg:province":"PA",
    "sg:tags":[
        "car",
        "dealer"
    ],
    "wof:name":"Bayfront Automotive Inc",
    "wof:placetype":"venue"
},
  "geometry": {"coordinates":[-80.152455,42.082564],"type":"Point"}
}