{
  "type": "Feature",
  "properties": {
    "iso:country":"US",
    "sg:address":"1935 Center St",
    "sg:city":"Northampton",
    "sg:classifiers":[
        {
            "category":"Health Services",
            "subcategory":"Optometrist",
            "type":"Services"
        }
    ],
    "sg:phone":"+1 610 262 2091",
    "sg:postcode":"18067",
    "sg:province":"PA",
    "wof:name":"Sharkey Shannon OD",
    "wof:placetype":"venue"
},
  "geometry": {"coordinates":[-75.499298,40.688801],"type":"Point"}
}