{
  "type": "Feature",
  "properties": {
    "addr:full":"4701 Jonestown Rd Harrisburg PA 17109",
    "addr:housenumber":"4701",
    "addr:postcode":"17109",
    "addr:street":"Jonestown Rd",
    "iso:country":"US",
    "sg:address":"4701 Jonestown Rd",
    "sg:city":"Harrisburg",
    "sg:classifiers":[
        {
            "category":"Autos & Motor Vehicles",
            "subcategory":"Fuel & Gas Station",
            "type":"Retail Goods"
        }
    ],
    "sg:phone":"+1   ",
    "sg:postcode":"17109",
    "sg:province":"PA",
    "sg:tags":[
        "station",
        "gasoline"
    ],
    "wof:name":"Sunoco",
    "wof:placetype":"venue"
},
  "geometry": {"coordinates":[-76.80938399999999,40.303827],"type":"Point"}
}