{
  "type": "Feature",
  "properties": {
    "addr:full":"270 Feathers Rd Imler PA 16655",
    "addr:housenumber":"270",
    "addr:postcode":"16655",
    "addr:street":"Feathers Rd",
    "iso:country":"US",
    "sg:address":"270 Feathers Rd",
    "sg:city":"Imler",
    "sg:classifiers":[
        {
            "category":"Bars & Pubs",
            "type":"Food & Drink"
        }
    ],
    "sg:phone":"+1   ",
    "sg:postcode":"16655",
    "sg:province":"PA",
    "sg:tags":[
        "drinking"
    ],
    "wof:name":"Fast Track Sports Bar",
    "wof:placetype":"venue"
},
  "geometry": {"coordinates":[-78.537718,40.233746],"type":"Point"}
}