{
  "type": "Feature",
  "properties": {
    "iso:country":"US",
    "sg:address":"250 Royer Rd",
    "sg:city":"Ephrata",
    "sg:classifiers":[
        {
            "category":"Retail",
            "subcategory":"Repair Shop",
            "type":"Services"
        }
    ],
    "sg:phone":"+1 717 738 7227",
    "sg:postcode":"17522",
    "sg:province":"PA",
    "sg:tags":[
        "farm",
        "equipment",
        "parts"
    ],
    "wof:name":"Daryl L Martin",
    "wof:placetype":"venue"
},
  "geometry": {"coordinates":[-76.22341299999999,40.172693],"type":"Point"}
}