{
  "type": "Feature",
  "properties": {
    "iso:country":"US",
    "sg:address":"528 Academy St",
    "sg:city":"Hawley",
    "sg:classifiers":[
        {
            "category":"Travel",
            "subcategory":"Hotels & Motels",
            "type":"Entertainment"
        }
    ],
    "sg:phone":"+1 570 226 3430",
    "sg:postcode":"18428",
    "sg:province":"PA",
    "sg:tags":[
        "breakfast",
        "accommodation",
        "bed"
    ],
    "sg:website":"www.academybb.com",
    "wof:name":"Academy Street Bed & Breakfast",
    "wof:placetype":"venue"
},
  "geometry": {"coordinates":[-75.17441100000001,41.474864],"type":"Point"}
}