{
  "type": "Feature",
  "properties": {
    "iso:country":"US",
    "sg:address":"112 York Rd",
    "sg:city":"Jenkintown",
    "sg:classifiers":[
        {
            "category":"Real Estate",
            "subcategory":"Architect",
            "type":"Services"
        }
    ],
    "sg:phone":"+1 215 576 1580",
    "sg:postcode":"19046",
    "sg:province":"PA",
    "sg:website":"www.klett-arch.com",
    "wof:name":"Klett Organization",
    "wof:placetype":"venue"
},
  "geometry": {"coordinates":[-75.127386,40.08842],"type":"Point"}
}