{
  "type": "Feature",
  "properties": {
    "addr:full":"312 N Washington Ave Scranton PA 18503",
    "addr:housenumber":"312",
    "addr:postcode":"18503",
    "addr:street":"N Washington Ave",
    "iso:country":"US",
    "sg:address":"312 N Washington Ave",
    "sg:city":"Scranton",
    "sg:classifiers":[
        {
            "category":"Professional",
            "subcategory":"Lawyer & Legal Services",
            "type":"Services"
        }
    ],
    "sg:phone":"+1 570 499 2890",
    "sg:postcode":"18503",
    "sg:province":"PA",
    "sg:tags":[
        "attorney"
    ],
    "wof:name":"Joan Guari",
    "wof:placetype":"venue"
},
  "geometry": {"coordinates":[-75.661123,41.410106],"type":"Point"}
}