{
  "type": "Feature",
  "properties": {
    "iso:country":"US",
    "sg:address":"522 E Norwegian St",
    "sg:city":"Pottsville",
    "sg:classifiers":[
        {
            "category":"Personal",
            "subcategory":"Barber",
            "type":"Services"
        }
    ],
    "sg:phone":"+1 570 628 3511",
    "sg:postcode":"17901",
    "sg:province":"PA",
    "wof:name":"Joe's Barber Shop",
    "wof:placetype":"venue"
},
  "geometry": {"coordinates":[-76.19007999999999,40.688213],"type":"Point"}
}