{
  "type": "Feature",
  "properties": {
    "iso:country":"US",
    "sg:address":"47 Cherry Hill Rd",
    "sg:city":"Honesdale",
    "sg:classifiers":[
        {
            "category":"Shopping",
            "subcategory":"Antiques",
            "type":"Retail Goods"
        }
    ],
    "sg:phone":"+1 570 253 7367",
    "sg:postcode":"18431",
    "sg:province":"PA",
    "wof:name":"Springhill Antiques Coggins E",
    "wof:placetype":"venue"
},
  "geometry": {"coordinates":[-75.292475,41.510994],"type":"Point"}
}