{
  "type": "Feature",
  "properties": {
    "addr:full":"2 Charles St Malvern PA 19355",
    "addr:housenumber":"2",
    "addr:postcode":"19355",
    "addr:street":"Charles St",
    "iso:country":"US",
    "sg:address":"2 Charles St",
    "sg:city":"Malvern",
    "sg:classifiers":[
        {
            "category":"Professional",
            "subcategory":"Accounting & Tax Preparation",
            "type":"Services"
        }
    ],
    "sg:phone":"+1   ",
    "sg:postcode":"19355",
    "sg:province":"PA",
    "sg:tags":[
        "bookkeeping",
        "return"
    ],
    "wof:name":"Walsh Accounting Services",
    "wof:placetype":"venue"
},
  "geometry": {"coordinates":[-75.566457,40.036857],"type":"Point"}
}