{
  "type": "Feature",
  "properties": {
    "iso:country":"US",
    "sg:address":"241 York Rd",
    "sg:city":"Carlisle",
    "sg:classifiers":[
        {
            "category":"Professional",
            "subcategory":"Research",
            "type":"Services"
        }
    ],
    "sg:phone":"+1 717 243 4666",
    "sg:postcode":"17013",
    "sg:province":"PA",
    "sg:tags":[
        "foundation",
        "philanthropic"
    ],
    "wof:name":"Michael Lynn Shatto Meml Fndtn",
    "wof:placetype":"venue"
},
  "geometry": {"coordinates":[-77.167169,40.19475],"type":"Point"}
}