{
  "type": "Feature",
  "properties": {
    "iso:country":"US",
    "sg:address":"419 N 4th St",
    "sg:city":"Lewisburg",
    "sg:classifiers":[
        {
            "category":"Wholesale",
            "subcategory":"Electrical",
            "type":"Manufacturing & Wholesale Goods"
        }
    ],
    "sg:phone":"+1 570 523 3787",
    "sg:postcode":"17837",
    "sg:province":"PA",
    "sg:tags":[
        "communication",
        "radio",
        "system"
    ],
    "wof:name":"Checkpoint Of Pennsylvania Inc",
    "wof:placetype":"venue"
},
  "geometry": {"coordinates":[-76.89054,40.967771],"type":"Point"}
}