{
  "type": "Feature",
  "properties": {
    "iso:country":"US",
    "sg:address":"1804 4th St",
    "sg:city":"Beaver Falls",
    "sg:classifiers":[
        {
            "category":"Personal",
            "subcategory":"Beauty Salon",
            "type":"Services"
        }
    ],
    "sg:phone":"+1 724 847 8750",
    "sg:postcode":"15010",
    "sg:province":"PA",
    "wof:name":"Scissor Shack Inc",
    "wof:placetype":"venue"
},
  "geometry": {"coordinates":[-80.33179199999999,40.744215],"type":"Point"}
}