{
  "type": "Feature",
  "properties": {
    "iso:country":"US",
    "sg:address":"136 Wilmington Pike",
    "sg:city":"Glen Mills",
    "sg:classifiers":[
        {
            "category":"Wholesale",
            "subcategory":"Machinery & Supplies",
            "type":"Manufacturing & Wholesale Goods"
        }
    ],
    "sg:phone":"+1   ",
    "sg:postcode":"19342",
    "sg:province":"PA",
    "wof:name":"Family Landscape Center",
    "wof:placetype":"venue"
},
  "geometry": {"coordinates":[-75.54209,39.856574],"type":"Point"}
}