{
  "type": "Feature",
  "properties": {
    "iso:country":"US",
    "sg:address":"107 Long Ln",
    "sg:city":"Upper Darby",
    "sg:classifiers":[
        {
            "category":"Professional",
            "type":"Services"
        }
    ],
    "sg:phone":"+1 610 352 7465",
    "sg:postcode":"19082",
    "sg:province":"PA",
    "wof:name":"Brinson Estates",
    "wof:placetype":"venue"
},
  "geometry": {"coordinates":[-75.26289300000001,39.959371],"type":"Point"}
}