{
  "type": "Feature",
  "properties": {
    "addr:full":"258 Lenora Ln Downingtown PA 19335",
    "addr:housenumber":"258",
    "addr:postcode":"19335",
    "addr:street":"Lenora Ln",
    "iso:country":"US",
    "sg:address":"258 Lenora Ln",
    "sg:city":"Downingtown",
    "sg:classifiers":[
        {
            "category":"Organizations",
            "subcategory":"Community Association",
            "type":"Services"
        }
    ],
    "sg:phone":"+1   ",
    "sg:postcode":"19335",
    "sg:province":"PA",
    "wof:name":"Downingtown Soccer Booster CLB",
    "wof:placetype":"venue"
},
  "geometry": {"coordinates":[-75.770865,40.015893],"type":"Point"}
}