{
  "type": "Feature",
  "properties": {
    "iso:country":"US",
    "sg:address":"608 Mt Joy Rd",
    "sg:city":"Mt Joy",
    "sg:classifiers":[
        {
            "category":"Farming",
            "subcategory":"Poultry Farm",
            "type":"Manufacturing & Wholesale Goods"
        }
    ],
    "sg:phone":"+1 717 492 0123",
    "sg:postcode":"17552",
    "sg:province":"PA",
    "wof:name":"Mainjoy Unlimited Inc",
    "wof:placetype":"venue"
},
  "geometry": {"coordinates":[-76.47725,40.123552],"type":"Point"}
}