{
  "type": "Feature",
  "properties": {
    "addr:full":"130 E Church St Nanticoke PA 18634",
    "addr:housenumber":"130",
    "addr:postcode":"18634",
    "addr:street":"E Church St",
    "iso:country":"US",
    "sg:address":"130 E Church St",
    "sg:city":"Nanticoke",
    "sg:classifiers":[
        {
            "category":"Building & Trades",
            "subcategory":"Pest Control",
            "type":"Services"
        }
    ],
    "sg:phone":"+1 570 735 8757",
    "sg:postcode":"18634",
    "sg:province":"PA",
    "wof:name":"Albanese Exterminating Service",
    "wof:placetype":"venue"
},
  "geometry": {"coordinates":[-75.99997500000001,41.201767],"type":"Point"}
}