{
  "type": "Feature",
  "properties": {
    "addr:full":"323 Mifflin St West Mifflin PA 15110",
    "addr:housenumber":"323",
    "addr:postcode":"15110",
    "addr:street":"Mifflin St",
    "iso:country":"US",
    "sg:address":"323 Mifflin St",
    "sg:city":"West Mifflin",
    "sg:classifiers":[
        {
            "category":"Building & Trades",
            "subcategory":"Construction",
            "type":"Services"
        }
    ],
    "sg:phone":"+1   ",
    "sg:postcode":"15110",
    "sg:province":"PA",
    "sg:tags":[
        "general",
        "contractor"
    ],
    "wof:name":"Steves Home Improvements",
    "wof:placetype":"venue"
},
  "geometry": {"coordinates":[-79.85721100000001,40.365944],"type":"Point"}
}