{
  "type": "Feature",
  "properties": {
    "iso:country":"US",
    "sg:address":"2191 Campmeeting Rd",
    "sg:city":"Sewickley",
    "sg:classifiers":[
        {
            "category":"Professional",
            "subcategory":"Lawyer & Legal Services",
            "type":"Services"
        }
    ],
    "sg:phone":"+1 412 741 4694",
    "sg:postcode":"15143",
    "sg:province":"PA",
    "wof:name":"Rhodes John D Atty",
    "wof:placetype":"venue"
},
  "geometry": {"coordinates":[-80.147425,40.594972],"type":"Point"}
}