{
  "type": "Feature",
  "properties": {
    "addr:full":"153 N Hanover St Carlisle PA 17013",
    "addr:housenumber":"153",
    "addr:postcode":"17013",
    "addr:street":"N Hanover St",
    "iso:country":"US",
    "sg:address":"153 N Hanover St",
    "sg:city":"Carlisle",
    "sg:classifiers":[
        {
            "category":"Shopping",
            "subcategory":"Jewelry",
            "type":"Retail Goods"
        }
    ],
    "sg:phone":"+1 717 763 9525",
    "sg:postcode":"17013",
    "sg:province":"PA",
    "sg:tags":[
        "jeweler"
    ],
    "sg:website":"www.mountzjewelers.com",
    "wof:name":"Mountz Jewelers Co",
    "wof:placetype":"venue"
},
  "geometry": {"coordinates":[-77.18861800000001,40.204295],"type":"Point"}
}