{
  "type": "Feature",
  "properties": {
    "iso:country":"US",
    "sg:address":"6410 W Ridge Rd",
    "sg:city":"Erie",
    "sg:classifiers":[
        {
            "category":"Manufacturing",
            "subcategory":"Signs",
            "type":"Manufacturing & Wholesale Goods"
        }
    ],
    "sg:phone":"+1 814 833 2930",
    "sg:postcode":"16506",
    "sg:province":"PA",
    "sg:website":"www.benchmarksign.com",
    "wof:name":"Simplesignman",
    "wof:placetype":"venue"
},
  "geometry": {"coordinates":[-80.220609,42.052196],"type":"Point"}
}