{
  "type": "Feature",
  "properties": {
    "addr:full":"601 W Erie Ave Philadelphia PA 19140",
    "addr:housenumber":"601",
    "addr:postcode":"19140",
    "addr:street":"W Erie Ave",
    "iso:country":"US",
    "sg:address":"601 W Erie Ave",
    "sg:city":"Philadelphia",
    "sg:classifiers":[
        {
            "category":"Banks & Credit Unions",
            "subcategory":"Bank",
            "type":"Services"
        }
    ],
    "sg:phone":"+1 215 226 4950",
    "sg:postcode":"19140",
    "sg:province":"PA",
    "sg:website":"www.wachovia.com",
    "wof:name":"Wachovia",
    "wof:placetype":"venue"
},
  "geometry": {"coordinates":[-75.139297,40.007599],"type":"Point"}
}