{
  "type": "Feature",
  "properties": {
    "addr:full":"1100 3rd St Beaver PA 15009",
    "addr:housenumber":"1100",
    "addr:postcode":"15009",
    "addr:street":"3Rd St",
    "iso:country":"US",
    "sg:address":"1100 3rd St",
    "sg:city":"Beaver",
    "sg:classifiers":[
        {
            "category":"Travel",
            "subcategory":"Travel Agent",
            "type":"Entertainment"
        }
    ],
    "sg:phone":"+1 724 728 6241",
    "sg:postcode":"15009",
    "sg:province":"PA",
    "sg:tags":[
        "agency",
        "bureau"
    ],
    "wof:name":"Beaver Travel Center",
    "wof:placetype":"venue"
},
  "geometry": {"coordinates":[-80.31260899999999,40.692033],"type":"Point"}
}