{
  "type": "Feature",
  "properties": {
    "addr:full":"151 Summit Ln Bala Cynwyd PA 19004",
    "addr:housenumber":"151",
    "addr:postcode":"19004",
    "addr:street":"Summit Ln",
    "iso:country":"US",
    "sg:address":"151 Summit Ln",
    "sg:city":"Bala Cynwyd",
    "sg:classifiers":[
        {
            "category":"Professional",
            "subcategory":"Management & Consulting",
            "type":"Services"
        }
    ],
    "sg:phone":"+1   ",
    "sg:postcode":"19004",
    "sg:province":"PA",
    "sg:tags":[
        "health",
        "business"
    ],
    "wof:name":"Vision Education Seminars",
    "wof:placetype":"venue"
},
  "geometry": {"coordinates":[-75.240679,40.002966],"type":"Point"}
}