{
  "type": "Feature",
  "properties": {
    "iso:country":"US",
    "sg:address":"2218 E 30th St",
    "sg:city":"Erie",
    "sg:classifiers":[
        {
            "category":"Manufacturing",
            "subcategory":"Buildings",
            "type":"Manufacturing & Wholesale Goods"
        },
        {
            "category":"Building & Trades",
            "subcategory":"Construction",
            "type":"Services"
        }
    ],
    "sg:phone":"+1 814 898 4200",
    "sg:postcode":"16510",
    "sg:province":"PA",
    "sg:tags":[
        "industrial",
        "system",
        "specialty",
        "builder",
        "heating",
        "contractor",
        "contractors-commercial",
        "home",
        "air conditioning"
    ],
    "sg:website":"http://www.eriezconstruction.com",
    "wof:name":"Eriez Construction, Inc.",
    "wof:placetype":"venue"
},
  "geometry": {"coordinates":[-80.02253399999999,42.126742],"type":"Point"}
}