{
  "type": "Feature",
  "properties": {
    "iso:country":"US",
    "sg:address":"7171 Allentown Blvd",
    "sg:city":"Harrisburg",
    "sg:classifiers":[
        {
            "category":"Government",
            "subcategory":"Office",
            "type":"Public Place"
        }
    ],
    "sg:phone":"+1 717 540 6080",
    "sg:postcode":"17112",
    "sg:province":"PA",
    "sg:tags":[
        "village"
    ],
    "wof:name":"West Hanover Code Enforcement",
    "wof:placetype":"venue"
},
  "geometry": {"coordinates":[-76.751969,40.330512],"type":"Point"}
}