{
  "type": "Feature",
  "properties": {
    "iso:country":"US",
    "sg:address":"877 Piscataqua Dr",
    "sg:city":"Leeper",
    "sg:classifiers":[
        {
            "category":"Real Estate",
            "subcategory":"Real Estate Services",
            "type":"Services"
        },
        {
            "category":"Building & Trades",
            "subcategory":"Cleaning & Sanitation",
            "type":"Services"
        }
    ],
    "sg:phone":"+1 814 744 9239",
    "sg:postcode":"16233",
    "sg:province":"PA",
    "sg:tags":[
        "maintenance",
        "cleaners-interior"
    ],
    "wof:name":"C T Ceiling Care",
    "wof:placetype":"venue"
},
  "geometry": {"coordinates":[-79.250327,41.32198],"type":"Point"}
}