{
  "type": "Feature",
  "properties": {
    "iso:country":"US",
    "sg:address":"20 E North St",
    "sg:city":"Carlisle",
    "sg:classifiers":[
        {
            "category":"Social Services",
            "type":"Services"
        }
    ],
    "sg:phone":"+1 717 960 0140",
    "sg:postcode":"17013",
    "sg:province":"PA",
    "wof:name":"UCP Central Pa",
    "wof:placetype":"venue"
},
  "geometry": {"coordinates":[-77.187439,40.204372],"type":"Point"}
}