{
  "type": "Feature",
  "properties": {
    "iso:country":"US",
    "sg:address":"700 Barley Sheaf Rd",
    "sg:city":"Coatesville",
    "sg:classifiers":[
        {
            "category":"Food & Beverages",
            "subcategory":"Groceries & Convenience Stores",
            "type":"Retail Goods"
        }
    ],
    "sg:phone":"+1   ",
    "sg:postcode":"19320",
    "sg:province":"PA",
    "wof:name":"Ichabods News",
    "wof:placetype":"venue"
},
  "geometry": {"coordinates":[-75.773579,39.994702],"type":"Point"}
}