{
  "type": "Feature",
  "properties": {
    "iso:country":"US",
    "sg:address":"386 Iron Bridge Rd",
    "sg:city":"Freeport",
    "sg:classifiers":[
        {
            "category":"Organizations",
            "subcategory":"Religious Organization",
            "type":"Services"
        }
    ],
    "sg:phone":"+1 724 295 2707",
    "sg:postcode":"16229",
    "sg:province":"PA",
    "sg:tags":[
        "church"
    ],
    "wof:name":"Cornerstone Baptist Bible Chr",
    "wof:placetype":"venue"
},
  "geometry": {"coordinates":[-79.66607999999999,40.723867],"type":"Point"}
}