{
  "type": "Feature",
  "properties": {
    "addr:full":"2658 W 8th St Erie PA 16505",
    "addr:housenumber":"2658",
    "addr:postcode":"16505",
    "addr:street":"W 8Th St",
    "iso:country":"US",
    "sg:address":"2658 W 8th St",
    "sg:city":"Erie",
    "sg:classifiers":[
        {
            "category":"Insurance",
            "subcategory":"Insurance Agent",
            "type":"Services"
        }
    ],
    "sg:phone":"+1 814 833 9829",
    "sg:postcode":"16505",
    "sg:province":"PA",
    "wof:name":"State Farm Insurance",
    "wof:placetype":"venue"
},
  "geometry": {"coordinates":[-80.143663,42.105513],"type":"Point"}
}