{
  "type": "Feature",
  "properties": {
    "iso:country":"US",
    "sg:address":"633 Mary St",
    "sg:city":"Warminster",
    "sg:classifiers":[
        {
            "category":"Home & Garden",
            "subcategory":"Building Materials",
            "type":"Retail Goods"
        }
    ],
    "sg:phone":"+1 215 674 9360",
    "sg:postcode":"18974",
    "sg:province":"PA",
    "sg:tags":[
        "lumber-used"
    ],
    "sg:website":"http://www.bradco.com",
    "wof:name":"American Builders & Contractors Supply Co., Inc.",
    "wof:placetype":"venue"
},
  "geometry": {"coordinates":[-75.091728,40.203024],"type":"Point"}
}