{
  "type": "Feature",
  "properties": {
    "iso:country":"US",
    "sg:address":"610 White Birch Rd",
    "sg:city":"Clarks Summit",
    "sg:classifiers":[
        {
            "category":"Social Services",
            "subcategory":"Child Care",
            "type":"Services"
        }
    ],
    "sg:phone":"+1 570 587 3031",
    "sg:postcode":"18411",
    "sg:province":"PA",
    "sg:tags":[
        "day"
    ],
    "wof:name":"Little Additions",
    "wof:placetype":"venue"
},
  "geometry": {"coordinates":[-75.679394,41.499524],"type":"Point"}
}