{
  "type": "Feature",
  "properties": {
    "iso:country":"US",
    "sg:address":"89 Summit Ave",
    "sg:city":"Chadds Ford",
    "sg:classifiers":[
        {
            "category":"Wholesale",
            "subcategory":"Machinery & Supplies",
            "type":"Manufacturing & Wholesale Goods"
        }
    ],
    "sg:phone":"+1 610 558 9480",
    "sg:postcode":"19317",
    "sg:province":"PA",
    "sg:tags":[
        "equipment",
        "transportation"
    ],
    "wof:name":"Eelman Associates",
    "wof:placetype":"venue"
},
  "geometry": {"coordinates":[-75.543268,39.848103],"type":"Point"}
}