{
  "type": "Feature",
  "properties": {
    "addr:full":"337 Pearl St Pittsburgh PA 15224",
    "addr:housenumber":"337",
    "addr:postcode":"15224",
    "addr:street":"Pearl St",
    "iso:country":"US",
    "sg:address":"337 Pearl St",
    "sg:city":"Pittsburgh",
    "sg:classifiers":[
        {
            "category":"Social Services",
            "type":"Services"
        }
    ],
    "sg:phone":"+1 412 621 9841",
    "sg:postcode":"15224",
    "sg:province":"PA",
    "sg:tags":[
        "organization",
        "welfare"
    ],
    "wof:name":"Lower Bloomfield Unity Council",
    "wof:placetype":"venue"
},
  "geometry": {"coordinates":[-79.94977400000001,40.462083],"type":"Point"}
}