{
  "type": "Feature",
  "properties": {
    "addr:full":"419 Ave of the States Chester PA 19013",
    "addr:housenumber":"419",
    "addr:postcode":"19013",
    "addr:street":"Ave Of The",
    "iso:country":"US",
    "sg:address":"419 Ave of the States",
    "sg:city":"Chester",
    "sg:classifiers":[
        {
            "category":"Social Services",
            "type":"Services"
        }
    ],
    "sg:phone":"+1 610 876 7164",
    "sg:postcode":"19013",
    "sg:province":"PA",
    "sg:tags":[
        "worker"
    ],
    "wof:name":"Karl Assoc",
    "wof:placetype":"venue"
},
  "geometry": {"coordinates":[-75.359887,39.848095],"type":"Point"}
}