{
  "type": "Feature",
  "properties": {
    "iso:country":"US",
    "sg:address":"1027 Petersburg Rd",
    "sg:city":"Hadley",
    "sg:classifiers":[
        {
            "category":"Wholesale",
            "subcategory":"Machinery & Supplies",
            "type":"Manufacturing & Wholesale Goods"
        }
    ],
    "sg:phone":"+1   ",
    "sg:postcode":"16130",
    "sg:province":"PA",
    "sg:tags":[
        "industrial"
    ],
    "wof:name":"China Supply Ltd",
    "wof:placetype":"venue"
},
  "geometry": {"coordinates":[-80.25085199999999,41.440099],"type":"Point"}
}