{
  "type": "Feature",
  "properties": {
    "iso:country":"US",
    "sg:address":"231 N Chestnut St",
    "sg:city":"Palmyra",
    "sg:classifiers":[
        {
            "category":"Recreation",
            "type":"Entertainment"
        }
    ],
    "sg:phone":"+1 717 838 3857",
    "sg:postcode":"17078",
    "sg:province":"PA",
    "sg:tags":[
        "yoga",
        "c",
        "instruction",
        "clothing",
        "book"
    ],
    "wof:name":"Carol's Hatha Yoga",
    "wof:placetype":"venue"
},
  "geometry": {"coordinates":[-76.596847,40.310622],"type":"Point"}
}