{
  "type": "Feature",
  "properties": {
    "iso:country":"US",
    "sg:address":"218 W Atherton St",
    "sg:city":"Taylor",
    "sg:classifiers":[
        {
            "category":"Transit Center",
            "subcategory":"Freight",
            "type":"Transportation"
        }
    ],
    "sg:phone":"+1 570 499 0333",
    "sg:postcode":"18517",
    "sg:province":"PA",
    "sg:tags":[
        "trucking-light",
        "hauling"
    ],
    "wof:name":"R.A.M. Hauling",
    "wof:placetype":"venue"
},
  "geometry": {"coordinates":[-75.71522,41.381155],"type":"Point"}
}