{
  "type": "Feature",
  "properties": {
    "iso:country":"US",
    "sg:address":"329 38th St",
    "sg:city":"Pittsburgh",
    "sg:classifiers":[
        {
            "category":"Professional",
            "type":"Services"
        }
    ],
    "sg:phone":"+1   ",
    "sg:postcode":"15201",
    "sg:province":"PA",
    "wof:name":"Wild Education",
    "wof:placetype":"venue"
},
  "geometry": {"coordinates":[-79.96097,40.46302],"type":"Point"}
}