{
  "type": "Feature",
  "properties": {
    "iso:country":"US",
    "sg:address":"439 W Main St",
    "sg:city":"Ridgway",
    "sg:classifiers":[
        {
            "category":"Manufacturing",
            "subcategory":"Metals",
            "type":"Manufacturing & Wholesale Goods"
        }
    ],
    "sg:phone":"+1   ",
    "sg:postcode":"15853",
    "sg:province":"PA",
    "sg:tags":[
        "product"
    ],
    "wof:name":"Northern Powdered Metals Inc",
    "wof:placetype":"venue"
},
  "geometry": {"coordinates":[-78.744298,41.420733],"type":"Point"}
}