{
  "type": "Feature",
  "properties": {
    "iso:country":"US",
    "sg:address":"611 Gravel Pike",
    "sg:city":"Collegeville",
    "sg:classifiers":[
        {
            "category":"Restaurant",
            "type":"Food & Drink"
        }
    ],
    "sg:phone":"+1 610 489 6900",
    "sg:postcode":"19426",
    "sg:province":"PA",
    "sg:tags":[
        "pizza"
    ],
    "wof:name":"Justa Pizza Express",
    "wof:placetype":"venue"
},
  "geometry": {"coordinates":[-75.45349899999999,40.226601],"type":"Point"}
}