{
  "type": "Feature",
  "properties": {
    "addr:full":"157 Sawgrass Dr Blue Bell PA 19422",
    "addr:housenumber":"157",
    "addr:postcode":"19422",
    "addr:street":"Sawgrass Dr",
    "iso:country":"US",
    "sg:address":"157 Sawgrass Dr",
    "sg:city":"Blue Bell",
    "sg:classifiers":[
        {
            "category":"Banks & Credit Unions",
            "subcategory":"Investment Brokerage",
            "type":"Services"
        }
    ],
    "sg:phone":"+1 610 277 9223",
    "sg:postcode":"19422",
    "sg:province":"PA",
    "sg:tags":[
        "advisory"
    ],
    "wof:name":"Wire Fun",
    "wof:placetype":"venue"
},
  "geometry": {"coordinates":[-75.28636899999999,40.182994],"type":"Point"}
}