{
  "type": "Feature",
  "properties": {
    "iso:country":"US",
    "sg:address":"2432 Blue Goose Rd",
    "sg:city":"Ebensburg",
    "sg:classifiers":[
        {
            "category":"Bars & Pubs",
            "type":"Food & Drink"
        }
    ],
    "sg:phone":"+1   ",
    "sg:postcode":"15931",
    "sg:province":"PA",
    "sg:tags":[
        "drinking"
    ],
    "wof:name":"Blue Goose Inn",
    "wof:placetype":"venue"
},
  "geometry": {"coordinates":[-78.818833,40.585725],"type":"Point"}
}