{
  "type": "Feature",
  "properties": {
    "iso:country":"US",
    "sg:address":"7811 Germantown Ave",
    "sg:city":"Philadelphia",
    "sg:classifiers":[
        {
            "category":"Professional",
            "subcategory":"Accounting & Tax Preparation",
            "type":"Services"
        },
        {
            "category":"Banks & Credit Unions",
            "subcategory":"Financial Services",
            "type":"Services"
        }
    ],
    "sg:phone":"+1 267 331 8967",
    "sg:postcode":"19118",
    "sg:province":"PA",
    "sg:tags":[
        "return"
    ],
    "sg:website":"http://www.thorntongroupfinancial.com",
    "wof:name":"Thornton Group Financial Services, Llc",
    "wof:placetype":"venue"
},
  "geometry": {"coordinates":[-75.19890100000001,40.068802],"type":"Point"}
}