{
  "type": "Feature",
  "properties": {
    "iso:country":"US",
    "sg:address":"2801 S Queen St",
    "sg:city":"Dallastown",
    "sg:classifiers":[
        {
            "category":"Building & Trades",
            "subcategory":"Equipment Rental",
            "type":"Services"
        }
    ],
    "sg:phone":"+1 717 741 2666",
    "sg:postcode":"17313",
    "sg:province":"PA",
    "sg:tags":[
        "yard"
    ],
    "wof:name":"Grand Rental Station",
    "wof:placetype":"venue"
},
  "geometry": {"coordinates":[-76.657752,39.90672],"type":"Point"}
}