{
  "type": "Feature",
  "properties": {
    "iso:country":"US",
    "sg:address":"7249 Frankford Ave",
    "sg:city":"Philadelphia",
    "sg:classifiers":[
        {
            "category":"Banks & Credit Unions",
            "subcategory":"Bank",
            "type":"Services"
        }
    ],
    "sg:phone":"+1   ",
    "sg:postcode":"19135",
    "sg:province":"PA",
    "sg:tags":[
        "cashing",
        "check"
    ],
    "wof:name":"Frankford Cttman Check Cashing",
    "wof:placetype":"venue"
},
  "geometry": {"coordinates":[-75.040971,40.036594],"type":"Point"}
}