{
  "type": "Feature",
  "properties": {
    "iso:country":"US",
    "sg:address":"615 Green Valley Rd",
    "sg:city":"York",
    "sg:classifiers":[
        {
            "category":"Professional",
            "type":"Services"
        }
    ],
    "sg:phone":"+1   ",
    "sg:postcode":"17403",
    "sg:province":"PA",
    "wof:name":"Constance R Rae",
    "wof:placetype":"venue"
},
  "geometry": {"coordinates":[-76.673446,39.904273],"type":"Point"}
}