{
  "type": "Feature",
  "properties": {
    "iso:country":"US",
    "sg:address":"124 Yale Ave",
    "sg:city":"Morton",
    "sg:classifiers":[
        {
            "category":"Building & Trades",
            "subcategory":"Construction",
            "type":"Services"
        }
    ],
    "sg:phone":"+1 610 328 7997",
    "sg:postcode":"19070",
    "sg:province":"PA",
    "sg:tags":[
        "painting",
        "painter",
        "contractor"
    ],
    "wof:name":"Harden Painting",
    "wof:placetype":"venue"
},
  "geometry": {"coordinates":[-75.331146,39.906723],"type":"Point"}
}