{
  "type": "Feature",
  "properties": {
    "addr:full":"143 Claremont Dr Lansdale PA 19446",
    "addr:housenumber":"143",
    "addr:postcode":"19446",
    "addr:street":"Claremont Dr",
    "iso:country":"US",
    "sg:address":"143 Claremont Dr",
    "sg:city":"Lansdale",
    "sg:classifiers":[
        {
            "category":"Health Services",
            "subcategory":"Doctor",
            "type":"Services"
        }
    ],
    "sg:phone":"+1 215 368 7313",
    "sg:postcode":"19446",
    "sg:province":"PA",
    "sg:tags":[
        "dentist"
    ],
    "wof:name":"Ronald Strisofskty DDS",
    "wof:placetype":"venue"
},
  "geometry": {"coordinates":[-75.22457199999999,40.26039],"type":"Point"}
}