{
  "type": "Feature",
  "properties": {
    "addr:full":"515 Easton Rd Warrington PA 18976",
    "addr:housenumber":"515",
    "addr:postcode":"18976",
    "addr:street":"Easton Rd",
    "iso:country":"US",
    "sg:address":"515 Easton Rd",
    "sg:city":"Warrington",
    "sg:classifiers":[
        {
            "category":"Food & Beverages",
            "subcategory":"Specialty",
            "type":"Retail Goods"
        }
    ],
    "sg:phone":"+1 215 343 4737",
    "sg:postcode":"18976",
    "sg:province":"PA",
    "sg:tags":[
        "tea",
        "coffee"
    ],
    "wof:name":"Coffee Associates Inc",
    "wof:placetype":"venue"
},
  "geometry": {"coordinates":[-75.139967,40.225908],"type":"Point"}
}