{
  "type": "Feature",
  "properties": {
    "iso:country":"US",
    "sg:address":"1161 Robbins Station Rd",
    "sg:city":"Irwin",
    "sg:classifiers":[
        {
            "category":"Building & Trades",
            "subcategory":"Construction",
            "type":"Services"
        }
    ],
    "sg:phone":"+1   ",
    "sg:postcode":"15642",
    "sg:province":"PA",
    "sg:tags":[
        "hanging",
        "contractor"
    ],
    "wof:name":"Removcik Painting",
    "wof:placetype":"venue"
},
  "geometry": {"coordinates":[-79.74779100000001,40.318993],"type":"Point"}
}