{
  "type": "Feature",
  "properties": {
    "iso:country":"US",
    "sg:address":"83 Buck Rd",
    "sg:city":"Holland",
    "sg:classifiers":[
        {
            "category":"Banks & Credit Unions",
            "subcategory":"Bank",
            "type":"Services"
        }
    ],
    "sg:phone":"+1 215 364 6300",
    "sg:postcode":"18966",
    "sg:province":"PA",
    "wof:name":"Pnc Bank",
    "wof:placetype":"venue"
},
  "geometry": {"coordinates":[-74.987369,40.169803],"type":"Point"}
}