{
  "type": "Feature",
  "properties": {
    "iso:country":"US",
    "sg:address":"4295 S 5th St",
    "sg:city":"Emmaus",
    "sg:classifiers":[
        {
            "category":"Building & Trades",
            "subcategory":"Construction",
            "type":"Services"
        }
    ],
    "sg:phone":"+1 610 967 9712",
    "sg:postcode":"18049",
    "sg:province":"PA",
    "sg:tags":[
        "tile",
        "dealer"
    ],
    "wof:name":"Boehm Ceramic Tile Install",
    "wof:placetype":"venue"
},
  "geometry": {"coordinates":[-75.488444,40.528228],"type":"Point"}
}