{
  "type": "Feature",
  "properties": {
    "addr:full":"295 Schooley Ave Pittston PA 18643",
    "addr:housenumber":"295",
    "addr:postcode":"18643",
    "addr:street":"Schooley Ave",
    "iso:country":"US",
    "sg:address":"295 Schooley Ave",
    "sg:city":"Pittston",
    "sg:classifiers":[
        {
            "category":"Building & Trades",
            "subcategory":"Construction",
            "type":"Services"
        }
    ],
    "sg:phone":"+1   ",
    "sg:postcode":"18643",
    "sg:province":"PA",
    "sg:tags":[
        "house"
    ],
    "wof:name":"Samuel J Marranca Gen Contg C",
    "wof:placetype":"venue"
},
  "geometry": {"coordinates":[-75.823579,41.324734],"type":"Point"}
}