{
  "type": "Feature",
  "properties": {
    "iso:country":"US",
    "sg:address":"200 Maple Ave",
    "sg:city":"Camp Hill",
    "sg:classifiers":[
        {
            "category":"Organizations",
            "subcategory":"Non-profit Organization",
            "type":"Services"
        }
    ],
    "sg:phone":"+1   ",
    "sg:postcode":"17011",
    "sg:province":"PA",
    "sg:tags":[
        "social"
    ],
    "wof:name":"Energy Entertainment Inc",
    "wof:placetype":"venue"
},
  "geometry": {"coordinates":[-76.953391,40.233261],"type":"Point"}
}