{
  "type": "Feature",
  "properties": {
    "iso:country":"US",
    "sg:address":"7791 Essington Ave",
    "sg:city":"Philadelphia",
    "sg:classifiers":[
        {
            "category":"Autos & Motor Vehicles",
            "subcategory":"Auto Supplies",
            "type":"Retail Goods"
        },
        {
            "category":"Retail",
            "subcategory":"Auto Repair",
            "type":"Services"
        }
    ],
    "sg:phone":"+1 215 365 1664",
    "sg:postcode":"19153",
    "sg:province":"PA",
    "sg:tags":[
        "body",
        "shop",
        "automobile",
        "equipment",
        "painting",
        "repairing"
    ],
    "sg:website":"http://www.sterlingautobody.com",
    "wof:name":"Sterling Autobody Centers",
    "wof:placetype":"venue"
},
  "geometry": {"coordinates":[-75.22878799999999,39.895315],"type":"Point"}
}