{
  "type": "Feature",
  "properties": {
    "iso:country":"US",
    "sg:address":"117 S 17th St",
    "sg:city":"Philadelphia",
    "sg:classifiers":[
        {
            "category":"Shopping",
            "subcategory":"Computers & Home Electronics",
            "type":"Retail Goods"
        }
    ],
    "sg:phone":"+1   ",
    "sg:postcode":"19103",
    "sg:province":"PA",
    "sg:tags":[
        "solution",
        "it",
        "provider"
    ],
    "wof:name":"Compu-Base Inc",
    "wof:placetype":"venue"
},
  "geometry": {"coordinates":[-75.168876,39.950958],"type":"Point"}
}