{
  "type": "Feature",
  "properties": {
    "addr:full":"540 Church St Norristown PA 19401",
    "addr:housenumber":"540",
    "addr:postcode":"19401",
    "addr:street":"Church St",
    "iso:country":"US",
    "sg:address":"540 Church St",
    "sg:city":"Norristown",
    "sg:classifiers":[
        {
            "category":"Building & Trades",
            "subcategory":"Construction",
            "type":"Services"
        }
    ],
    "sg:phone":"+1 610 369 8911",
    "sg:postcode":"19401",
    "sg:province":"PA",
    "sg:tags":[
        "contractor"
    ],
    "sg:website":"www.gambinoelectric.com",
    "wof:name":"Gambino Electric",
    "wof:placetype":"venue"
},
  "geometry": {"coordinates":[-75.34255400000001,40.11667],"type":"Point"}
}