{
  "type": "Feature",
  "properties": {
    "addr:full":"1075 Virginia Dr Fort Washington PA 19034",
    "addr:housenumber":"1075",
    "addr:postcode":"19034",
    "addr:street":"Virginia Dr",
    "iso:country":"US",
    "sg:address":"1075 Virginia Dr",
    "sg:city":"Fort Washington",
    "sg:classifiers":[
        {
            "category":"Real Estate",
            "subcategory":"Real Estate Agent",
            "type":"Services"
        }
    ],
    "sg:phone":"+1   ",
    "sg:postcode":"19034",
    "sg:province":"PA",
    "wof:name":"Kahn & Company Inc",
    "wof:placetype":"venue"
},
  "geometry": {"coordinates":[-75.180013,40.136321],"type":"Point"}
}