{
  "type": "Feature",
  "properties": {
    "addr:full":"2441 Aspen St Philadelphia PA 19130",
    "addr:housenumber":"2441",
    "addr:postcode":"19130",
    "addr:street":"Aspen St",
    "iso:country":"US",
    "sg:address":"2441 Aspen St",
    "sg:city":"Philadelphia",
    "sg:classifiers":[
        {
            "category":"Shopping",
            "subcategory":"Florist",
            "type":"Retail Goods"
        }
    ],
    "sg:phone":"+1 267 699 7112",
    "sg:postcode":"19130",
    "sg:province":"PA",
    "sg:website":"www.sunfirefloral.com/",
    "wof:name":"Sunfire Floral Design",
    "wof:placetype":"venue"
},
  "geometry": {"coordinates":[-75.178156,39.96902],"type":"Point"}
}