{
  "type": "Feature",
  "properties": {
    "iso:country":"US",
    "sg:address":"938 E Baltimore Pike",
    "sg:city":"Kennett Square",
    "sg:classifiers":[
        {
            "category":"Restaurant",
            "type":"Food & Drink"
        }
    ],
    "sg:phone":"+1 610 388 1144",
    "sg:postcode":"19348",
    "sg:province":"PA",
    "sg:tags":[
        "traditional",
        "american"
    ],
    "sg:website":"www.longwoodfamilyrestaurant.com/",
    "wof:name":"Longwood Family Restaurant",
    "wof:placetype":"venue"
},
  "geometry": {"coordinates":[-75.693727,39.855744],"type":"Point"}
}