{
  "type": "Feature",
  "properties": {
    "addr:full":"201 E Broad St Tamaqua PA 18252",
    "addr:housenumber":"201",
    "addr:postcode":"18252",
    "addr:street":"E Broad St",
    "iso:country":"US",
    "sg:address":"201 E Broad St",
    "sg:city":"Tamaqua",
    "sg:classifiers":[
        {
            "category":"Real Estate",
            "subcategory":"Real Estate Operator",
            "type":"Services"
        }
    ],
    "sg:phone":"+1 570 668 6372",
    "sg:postcode":"18252",
    "sg:province":"PA",
    "sg:tags":[
        "building",
        "apartment"
    ],
    "wof:name":"Majestic House Apts",
    "wof:placetype":"venue"
},
  "geometry": {"coordinates":[-75.966746,40.797415],"type":"Point"}
}