{
  "type": "Feature",
  "properties": {
    "addr:full":"1613 Noblestown Rd Pittsburgh PA 15205",
    "addr:housenumber":"1613",
    "addr:postcode":"15205",
    "addr:street":"Noblestown Rd",
    "iso:country":"US",
    "sg:address":"1613 Noblestown Rd",
    "sg:city":"Pittsburgh",
    "sg:classifiers":[
        {
            "category":"Retail",
            "subcategory":"Auto Repair",
            "type":"Services"
        }
    ],
    "sg:phone":"+1 412 921 5404",
    "sg:postcode":"15205",
    "sg:province":"PA",
    "wof:name":"Gino's Auto Service",
    "wof:placetype":"venue"
},
  "geometry": {"coordinates":[-80.050797,40.437401],"type":"Point"}
}