{
  "type": "Feature",
  "properties": {
    "iso:country":"US",
    "sg:address":"315 E Northview Ave",
    "sg:city":"New Castle",
    "sg:classifiers":[
        {
            "category":"Building & Trades",
            "subcategory":"Construction",
            "type":"Services"
        }
    ],
    "sg:phone":"+1   ",
    "sg:postcode":"16105",
    "sg:province":"PA",
    "sg:tags":[
        "house"
    ],
    "wof:name":"Home Renovation Workshop",
    "wof:placetype":"venue"
},
  "geometry": {"coordinates":[-80.338446,41.023011],"type":"Point"}
}