{
  "type": "Feature",
  "properties": {
    "iso:country":"US",
    "sg:address":"3466 Old Philadelphia Pike",
    "sg:city":"Intercourse",
    "sg:classifiers":[
        {
            "category":"Home & Garden",
            "subcategory":"Home Furnishings",
            "type":"Retail Goods"
        }
    ],
    "sg:phone":"+1 717 768 8673",
    "sg:postcode":"17572",
    "sg:province":"PA",
    "sg:tags":[
        "blanket"
    ],
    "wof:name":"M & N Hand Made Quilts",
    "wof:placetype":"venue"
},
  "geometry": {"coordinates":[-76.113446,40.039067],"type":"Point"}
}