{
  "type": "Feature",
  "properties": {
    "iso:country":"US",
    "sg:address":"3096 State Rte 100",
    "sg:city":"Macungie",
    "sg:classifiers":[
        {
            "category":"Freight",
            "type":"Transportation"
        }
    ],
    "sg:phone":"+1   ",
    "sg:postcode":"18062",
    "sg:province":"PA",
    "wof:name":"Student Trnsp Solution",
    "wof:placetype":"venue"
},
  "geometry": {"coordinates":[-75.575557,40.520979],"type":"Point"}
}