{
  "type": "Feature",
  "properties": {
    "iso:country":"US",
    "sg:address":"101 Spring St",
    "sg:city":"Langhorne",
    "sg:classifiers":[
        {
            "category":"Manufacturing",
            "subcategory":"Signs",
            "type":"Manufacturing & Wholesale Goods"
        }
    ],
    "sg:phone":"+1   ",
    "sg:postcode":"19047",
    "sg:province":"PA",
    "sg:tags":[
        "mfg"
    ],
    "wof:name":"Connor Sign Group Ltd",
    "wof:placetype":"venue"
},
  "geometry": {"coordinates":[-74.911794,40.153195],"type":"Point"}
}