{
  "type": "Feature",
  "properties": {
    "addr:full":"2578 Kingview Rd Scottdale PA 15683",
    "addr:housenumber":"2578",
    "addr:postcode":"15683",
    "addr:street":"Kingview Rd",
    "iso:country":"US",
    "sg:address":"2578 Kingview Rd",
    "sg:city":"Scottdale",
    "sg:classifiers":[
        {
            "category":"Sports & Exercise",
            "subcategory":"Gym",
            "type":"Entertainment"
        }
    ],
    "sg:phone":"+1 724 887 5662",
    "sg:postcode":"15683",
    "sg:province":"PA",
    "sg:tags":[
        "club",
        "health",
        "studio",
        "gymnasium"
    ],
    "wof:name":"Curves For Women",
    "wof:placetype":"venue"
},
  "geometry": {"coordinates":[-79.56111,40.09062],"type":"Point"}
}