{
  "type": "Feature",
  "properties": {
    "addr:full":"9901 Blue Grass Rd Philadelphia PA 19114",
    "addr:housenumber":"9901",
    "addr:postcode":"19114",
    "addr:street":"Blue Grass Rd",
    "iso:country":"US",
    "sg:address":"9901 Blue Grass Rd",
    "sg:city":"Philadelphia",
    "sg:classifiers":[
        {
            "category":"Manufacturing",
            "subcategory":"Tools & Machinery",
            "type":"Manufacturing & Wholesale Goods"
        }
    ],
    "sg:phone":"+1   ",
    "sg:postcode":"19114",
    "sg:province":"PA",
    "sg:tags":[
        "heat",
        "sensor",
        "mfg"
    ],
    "wof:name":"Heraeus Sensor-Nite Co",
    "wof:placetype":"venue"
},
  "geometry": {"coordinates":[-75.02058,40.085764],"type":"Point"}
}