{
  "type": "Feature",
  "properties": {
    "addr:full":"500 Diller Rd Hanover PA 17331",
    "addr:housenumber":"500",
    "addr:postcode":"17331",
    "addr:street":"Diller Rd",
    "iso:country":"US",
    "sg:address":"500 Diller Rd",
    "sg:city":"Hanover",
    "sg:classifiers":[
        {
            "category":"Banks & Credit Unions",
            "subcategory":"Bank",
            "type":"Services"
        }
    ],
    "sg:phone":"+1 717 630 1294",
    "sg:postcode":"17331",
    "sg:province":"PA",
    "sg:tags":[
        "other",
        "plan",
        "card"
    ],
    "wof:name":"American Express",
    "wof:placetype":"venue"
},
  "geometry": {"coordinates":[-77.00644,39.802816],"type":"Point"}
}