{
  "type": "Feature",
  "properties": {
    "addr:full":"7740 Hamot Rd Erie PA 16509",
    "addr:housenumber":"7740",
    "addr:postcode":"16509",
    "addr:street":"Hamot Rd",
    "iso:country":"US",
    "sg:address":"7740 Hamot Rd",
    "sg:city":"Erie",
    "sg:classifiers":[
        {
            "category":"Manufacturing",
            "subcategory":"Metals",
            "type":"Manufacturing & Wholesale Goods"
        }
    ],
    "sg:phone":"+1 814 864 2459",
    "sg:postcode":"16509",
    "sg:province":"PA",
    "sg:tags":[
        "casting"
    ],
    "wof:name":"Erie Matchplate Co",
    "wof:placetype":"venue"
},
  "geometry": {"coordinates":[-80.102915,42.045827],"type":"Point"}
}