{
  "type": "Feature",
  "properties": {
    "addr:full":"3615 Forbes Ave Pittsburgh PA 15213",
    "addr:housenumber":"3615",
    "addr:postcode":"15213",
    "addr:street":"Forbes Ave",
    "iso:country":"US",
    "sg:address":"3615 Forbes Ave",
    "sg:city":"Pittsburgh",
    "sg:classifiers":[
        {
            "category":"Restaurant",
            "type":"Food & Drink"
        }
    ],
    "sg:phone":"+1 412 687 7700",
    "sg:postcode":"15213",
    "sg:province":"PA",
    "wof:name":"Baja Fresh Mexican Grill",
    "wof:placetype":"venue"
},
  "geometry": {"coordinates":[-79.95775399999999,40.44107],"type":"Point"}
}