{
  "type": "Feature",
  "properties": {
    "addr:full":"333 Susquehanna Ave Wyoming PA 18644",
    "addr:housenumber":"333",
    "addr:postcode":"18644",
    "addr:street":"Susquehanna Ave",
    "iso:country":"US",
    "sg:address":"333 Susquehanna Ave",
    "sg:city":"Wyoming",
    "sg:classifiers":[
        {
            "category":"Retail",
            "subcategory":"Veterinary Services",
            "type":"Services"
        }
    ],
    "sg:phone":"+1 570 693 2941",
    "sg:postcode":"18644",
    "sg:province":"PA",
    "wof:name":"Animal Crackers",
    "wof:placetype":"venue"
},
  "geometry": {"coordinates":[-75.83161,41.308493],"type":"Point"}
}