{
  "type": "Feature",
  "properties": {
    "addr:full":"160 Gallery Dr Canonsburg PA 15317",
    "addr:housenumber":"160",
    "addr:postcode":"15317",
    "addr:street":"Gallery Dr",
    "iso:country":"US",
    "sg:address":"160 Gallery Dr",
    "sg:city":"Canonsburg",
    "sg:classifiers":[
        {
            "category":"Food & Beverages",
            "subcategory":"Groceries & Convenience Stores",
            "type":"Retail Goods"
        }
    ],
    "sg:phone":"+1 724 942 0600",
    "sg:postcode":"15317",
    "sg:province":"PA",
    "wof:name":"Festival Foods",
    "wof:placetype":"venue"
},
  "geometry": {"coordinates":[-80.113366,40.289972],"type":"Point"}
}