{
  "type": "Feature",
  "properties": {
    "iso:country":"US",
    "sg:address":"15244 Centerville Rd",
    "sg:city":"Townville",
    "sg:classifiers":[
        {
            "category":"Government",
            "subcategory":"Office",
            "type":"Public Place"
        }
    ],
    "sg:phone":"+1 814 967 4240",
    "sg:postcode":"16360",
    "sg:province":"PA",
    "sg:tags":[
        "city",
        "taxation"
    ],
    "wof:name":"Townville Tax Collector",
    "wof:placetype":"venue"
},
  "geometry": {"coordinates":[-79.885628,41.684682],"type":"Point"}
}