{
  "type": "Feature",
  "properties": {
    "addr:full":"3475 W Chester Pike Newtown Square PA 19073",
    "addr:housenumber":"3475",
    "addr:postcode":"19073",
    "addr:street":"W Chester Pike",
    "iso:country":"US",
    "sg:address":"3475 W Chester Pike",
    "sg:city":"Newtown Square",
    "sg:classifiers":[
        {
            "category":"Shopping",
            "type":"Retail Goods"
        }
    ],
    "sg:phone":"+1 610 325 3266",
    "sg:postcode":"19073",
    "sg:province":"PA",
    "sg:tags":[
        "store",
        "miscellaneous",
        "merchandise"
    ],
    "wof:name":"Harry J Lawall & Son Inc",
    "wof:placetype":"venue"
},
  "geometry": {"coordinates":[-75.390336,39.984719],"type":"Point"}
}