{
  "type": "Feature",
  "properties": {
    "addr:full":"5816 Morris St Philadelphia PA 19144",
    "addr:housenumber":"5816",
    "addr:postcode":"19144",
    "addr:street":"Morris St",
    "iso:country":"US",
    "sg:address":"5816 Morris St",
    "sg:city":"Philadelphia",
    "sg:classifiers":[
        {
            "category":"Building & Trades",
            "subcategory":"Construction",
            "type":"Services"
        }
    ],
    "sg:phone":"+1 215 844 8340",
    "sg:postcode":"19144",
    "sg:province":"PA",
    "sg:tags":[
        "carpenter"
    ],
    "wof:name":"Joseph T Kane Carpentary",
    "wof:placetype":"venue"
},
  "geometry": {"coordinates":[-75.18299,40.030239],"type":"Point"}
}