{
  "type": "Feature",
  "properties": {
    "iso:country":"US",
    "sg:address":"319 Hoffnagle St",
    "sg:city":"Philadelphia",
    "sg:classifiers":[
        {
            "category":"Professional",
            "subcategory":"Management & Consulting",
            "type":"Services"
        }
    ],
    "sg:phone":"+1   ",
    "sg:postcode":"19111",
    "sg:province":"PA",
    "sg:tags":[
        "business"
    ],
    "wof:name":"Biotreatment News",
    "wof:placetype":"venue"
},
  "geometry": {"coordinates":[-75.080787,40.081501],"type":"Point"}
}