{
  "type": "Feature",
  "properties": {
    "iso:country":"US",
    "sg:address":"331 N Chester Rd",
    "sg:city":"West Chester",
    "sg:classifiers":[
        {
            "category":"Building & Trades",
            "subcategory":"Electrical",
            "type":"Services"
        }
    ],
    "sg:phone":"+1   ",
    "sg:postcode":"19380",
    "sg:province":"PA",
    "sg:tags":[
        "electrical",
        "contractor"
    ],
    "wof:name":"Bradshaw Electric",
    "wof:placetype":"venue"
},
  "geometry": {"coordinates":[-75.535331,39.975731],"type":"Point"}
}