{
  "type": "Feature",
  "properties": {
    "iso:country":"US",
    "sg:address":"858 Scotland Rd",
    "sg:city":"Quarryville",
    "sg:classifiers":[
        {
            "category":"Home & Garden",
            "subcategory":"Building Materials",
            "type":"Retail Goods"
        }
    ],
    "sg:phone":"+1 717 284 0001",
    "sg:postcode":"17566",
    "sg:province":"PA",
    "sg:tags":[
        "lumber"
    ],
    "wof:name":"Groff & Groff Lumber",
    "wof:placetype":"venue"
},
  "geometry": {"coordinates":[-76.217794,39.851115],"type":"Point"}
}