{
  "type": "Feature",
  "properties": {
    "iso:country":"US",
    "sg:address":"1072 Washington Church Rd",
    "sg:city":"Home",
    "sg:phone":"+1   ",
    "sg:postcode":"15747",
    "sg:province":"PA",
    "sg:tags":[
        "vegetable",
        "farm"
    ],
    "wof:name":"Hills of Home Farms",
    "wof:placetype":"venue"
},
  "geometry": {"coordinates":[-79.129063,40.735711],"type":"Point"}
}