{
  "type": "Feature",
  "properties": {
    "iso:country":"US",
    "sg:address":"3292 Saranac Dr",
    "sg:city":"Sharpsville",
    "sg:classifiers":[
        {
            "category":"Shopping",
            "subcategory":"Clothing, Apparel, & Fashions",
            "type":"Retail Goods"
        }
    ],
    "sg:phone":"+1 724 962 2010",
    "sg:postcode":"16150",
    "sg:province":"PA",
    "sg:tags":[
        "alteration"
    ],
    "wof:name":"Martha's Sewing Shop",
    "wof:placetype":"venue"
},
  "geometry": {"coordinates":[-80.484334,41.278005],"type":"Point"}
}