{
  "type": "Feature",
  "properties": {
    "addr:full":"1801 Bridgetown Pike Feastervl Trvs PA 19053",
    "addr:housenumber":"1801",
    "addr:postcode":"19053",
    "addr:street":"Bridgetown Pike",
    "iso:country":"US",
    "sg:address":"1801 Bridgetown Pike",
    "sg:city":"Feastervl Trvs",
    "sg:classifiers":[
        {
            "category":"Professional",
            "type":"Services"
        }
    ],
    "sg:phone":"+1 215 357 3814",
    "sg:postcode":"19053",
    "sg:province":"PA",
    "sg:tags":[
        "establishment"
    ],
    "wof:name":"WOCO Inc",
    "wof:placetype":"venue"
},
  "geometry": {"coordinates":[-74.987667,40.161322],"type":"Point"}
}