{
  "type": "Feature",
  "properties": {
    "iso:country":"US",
    "sg:address":"190 Dorwood Dr",
    "sg:city":"Carlisle",
    "sg:classifiers":[
        {
            "category":"Social Services",
            "type":"Services"
        }
    ],
    "sg:phone":"+1 717 243 7772",
    "sg:postcode":"17013",
    "sg:province":"PA",
    "sg:tags":[
        "organization",
        "welfare"
    ],
    "wof:name":"Violence Intervention Program",
    "wof:placetype":"venue"
},
  "geometry": {"coordinates":[-77.221159,40.223252],"type":"Point"}
}