{
  "type": "Feature",
  "properties": {
    "iso:country":"US",
    "sg:address":"185 Camp Run Rd",
    "sg:city":"Harmony",
    "sg:classifiers":[
        {
            "category":"Shopping",
            "subcategory":"Crafts & Fabrics",
            "type":"Retail Goods"
        }
    ],
    "sg:phone":"+1 724 452 7963",
    "sg:postcode":"16037",
    "sg:province":"PA",
    "sg:tags":[
        "adhesive",
        "glue"
    ],
    "sg:website":"http://www.hexion.com",
    "wof:name":"Borden",
    "wof:placetype":"venue"
},
  "geometry": {"coordinates":[-80.140315,40.825509],"type":"Point"}
}