{
  "type": "Feature",
  "properties": {
    "iso:country":"US",
    "sg:address":"3675 Vartan Way",
    "sg:city":"Harrisburg",
    "sg:classifiers":[
        {
            "category":"Recreation",
            "type":"Entertainment"
        }
    ],
    "sg:phone":"+1 717 652 7700",
    "sg:postcode":"17110",
    "sg:province":"PA",
    "sg:tags":[
        "karate",
        "judo",
        "instr"
    ],
    "wof:name":"Kim Studios Of Karate",
    "wof:placetype":"venue"
},
  "geometry": {"coordinates":[-76.854004,40.320375],"type":"Point"}
}