{
  "type": "Feature",
  "properties": {
    "iso:country":"US",
    "sg:address":"113 Harvey Ave",
    "sg:city":"Westfield",
    "sg:classifiers":[
        {
            "category":"Building & Trades",
            "subcategory":"Construction",
            "type":"Services"
        }
    ],
    "sg:phone":"+1 814 367 5146",
    "sg:postcode":"16950",
    "sg:province":"PA",
    "sg:tags":[
        "water",
        "well",
        "drilling"
    ],
    "wof:name":"McLaughlin Water Well Drilling",
    "wof:placetype":"venue"
},
  "geometry": {"coordinates":[-77.550865,41.91982],"type":"Point"}
}