{
  "type": "Feature",
  "properties": {
    "iso:country":"US",
    "sg:address":"411 Clay Ave",
    "sg:city":"Jeannette",
    "sg:classifiers":[
        {
            "category":"Professional",
            "subcategory":"Management & Consulting",
            "type":"Services"
        }
    ],
    "sg:phone":"+1 724 527 1002",
    "sg:postcode":"15644",
    "sg:province":"PA",
    "sg:tags":[
        "consultant",
        "business"
    ],
    "wof:name":"Professional Community Co",
    "wof:placetype":"venue"
},
  "geometry": {"coordinates":[-79.617616,40.327234],"type":"Point"}
}