{
  "type": "Feature",
  "properties": {
    "iso:country":"US",
    "sg:address":"120 South St",
    "sg:city":"Harrisburg",
    "sg:classifiers":[
        {
            "category":"Shopping",
            "subcategory":"Discount & Variety Stores",
            "type":"Retail Goods"
        }
    ],
    "sg:phone":"+1 717 766 7545",
    "sg:postcode":"17101",
    "sg:province":"PA",
    "sg:tags":[
        "plumbing",
        "merchandise"
    ],
    "sg:website":"www.assocproducts.com",
    "wof:name":"Associated Products",
    "wof:placetype":"venue"
},
  "geometry": {"coordinates":[-76.886703,40.2621],"type":"Point"}
}