{
  "type": "Feature",
  "properties": {
    "addr:full":"50 S 16th St Fl 22 Philadelphia PA 19102",
    "addr:housenumber":"50;22",
    "addr:postcode":"19102",
    "addr:street":"S 16Th St Fl",
    "iso:country":"US",
    "sg:address":"50 S 16th St Fl 22",
    "sg:city":"Philadelphia",
    "sg:classifiers":[
        {
            "category":"Professional",
            "subcategory":"Lawyer & Legal Services",
            "type":"Services"
        }
    ],
    "sg:phone":"+1 215 568 6860",
    "sg:postcode":"19102",
    "sg:province":"PA",
    "sg:website":"www.tinovsky.com",
    "wof:name":"Tinovsky Law Firm",
    "wof:placetype":"venue"
},
  "geometry": {"coordinates":[-75.16723399999999,39.951882],"type":"Point"}
}