{
  "type": "Feature",
  "properties": {
    "iso:country":"US",
    "sg:address":"130 Court St",
    "sg:city":"Williamsport",
    "sg:classifiers":[
        {
            "category":"Banks & Credit Unions",
            "subcategory":"Bank",
            "type":"Services"
        }
    ],
    "sg:phone":"+1 570 601 3019",
    "sg:postcode":"17701",
    "sg:province":"PA",
    "wof:name":"Citizens & Northern Bank",
    "wof:placetype":"venue"
},
  "geometry": {"coordinates":[-77.00070700000001,41.239318],"type":"Point"}
}