{
  "type": "Feature",
  "properties": {
    "addr:full":"1227 Tullamore Cir Chester Springs PA 19425",
    "addr:housenumber":"1227",
    "addr:postcode":"19425",
    "addr:street":"Tullamore Cir",
    "iso:country":"US",
    "sg:address":"1227 Tullamore Cir",
    "sg:city":"Chester Springs",
    "sg:classifiers":[
        {
            "category":"Travel",
            "subcategory":"Campground",
            "type":"Entertainment"
        }
    ],
    "sg:phone":"+1 610 827 7989",
    "sg:postcode":"19425",
    "sg:province":"PA",
    "sg:tags":[
        "camp"
    ],
    "wof:name":"Active Learning Partners LTD",
    "wof:placetype":"venue"
},
  "geometry": {"coordinates":[-75.59258,40.094675],"type":"Point"}
}