{
  "type": "Feature",
  "properties": {
    "iso:country":"US",
    "sg:address":"347 Oliver St",
    "sg:city":"Jersey Shore",
    "sg:classifiers":[
        {
            "category":"Manufacturing",
            "subcategory":"Rubber & Plastics",
            "type":"Manufacturing & Wholesale Goods"
        }
    ],
    "sg:phone":"+1 570 398 1133",
    "sg:postcode":"17740",
    "sg:province":"PA",
    "sg:tags":[
        "packaging",
        "pharmaceutical",
        "product",
        "for",
        "mfg"
    ],
    "sg:website":"www.westpharma.com",
    "wof:name":"West Pharmaceutical Services",
    "wof:placetype":"venue"
},
  "geometry": {"coordinates":[-77.27193,41.198517],"type":"Point"}
}