{
  "type": "Feature",
  "properties": {
    "addr:full":"691 Clairton Blvd Pittsburgh PA 15236",
    "addr:housenumber":"691",
    "addr:postcode":"15236",
    "addr:street":"Clairton Blvd",
    "iso:country":"US",
    "sg:address":"691 Clairton Blvd",
    "sg:city":"Pittsburgh",
    "sg:phone":"+1 412 650 1600",
    "sg:postcode":"15236",
    "sg:province":"PA",
    "wof:name":"Vocelli Pizza",
    "wof:placetype":"venue"
},
  "geometry": {"coordinates":[-79.944996,40.328829],"type":"Point"}
}