{
  "type": "Feature",
  "properties": {
    "iso:country":"US",
    "sg:address":"3111 Banksville Rd",
    "sg:city":"Pittsburgh",
    "sg:classifiers":[
        {
            "category":"Government",
            "subcategory":"Office",
            "type":"Public Place"
        }
    ],
    "sg:phone":"+1 412 343 2326",
    "sg:postcode":"15216",
    "sg:province":"PA",
    "sg:tags":[
        "armed",
        "force",
        "recruiting"
    ],
    "wof:name":"US Army Recruiting",
    "wof:placetype":"venue"
},
  "geometry": {"coordinates":[-80.04435100000001,40.399629],"type":"Point"}
}