{
  "type": "Feature",
  "properties": {
    "addr:full":"925 Harvest Dr Blue Bell PA 19422",
    "addr:housenumber":"925",
    "addr:postcode":"19422",
    "addr:street":"Harvest Dr",
    "iso:country":"US",
    "sg:address":"925 Harvest Dr",
    "sg:city":"Blue Bell",
    "sg:classifiers":[
        {
            "category":"Professional",
            "subcategory":"Lawyer & Legal Services",
            "type":"Services"
        }
    ],
    "sg:phone":"+1 215 977 1011",
    "sg:postcode":"19422",
    "sg:province":"PA",
    "wof:name":"Elliott Thomas J Atty",
    "wof:placetype":"venue"
},
  "geometry": {"coordinates":[-75.28600299999999,40.153],"type":"Point"}
}