{
  "type": "Feature",
  "properties": {
    "iso:country":"US",
    "sg:address":"135 Beil Hill Rd",
    "sg:city":"Greenville",
    "sg:classifiers":[
        {
            "category":"Wholesale",
            "subcategory":"Hardware",
            "type":"Manufacturing & Wholesale Goods"
        }
    ],
    "sg:phone":"+1   ",
    "sg:postcode":"16125",
    "sg:province":"PA",
    "sg:tags":[
        "refrigeration"
    ],
    "wof:name":"Quality Maintenance & Repair",
    "wof:placetype":"venue"
},
  "geometry": {"coordinates":[-80.353206,41.342867],"type":"Point"}
}