{
  "type": "Feature",
  "properties": {
    "iso:country":"US",
    "sg:address":"331 Cochran Rd",
    "sg:city":"Pittsburgh",
    "sg:classifiers":[
        {
            "category":"Autos & Motor Vehicles",
            "subcategory":"Auto Supplies",
            "type":"Retail Goods"
        }
    ],
    "sg:phone":"+1 412 344 5568",
    "sg:postcode":"15228",
    "sg:province":"PA",
    "sg:tags":[
        "tire"
    ],
    "wof:name":"Procare Automotive Service Centers",
    "wof:placetype":"venue"
},
  "geometry": {"coordinates":[-80.052597,40.381599],"type":"Point"}
}