{
  "type": "Feature",
  "properties": {
    "iso:country":"US",
    "sg:address":"15 Robinhood Rd",
    "sg:city":"Pittsburgh",
    "sg:classifiers":[
        {
            "category":"Sports & Exercise",
            "subcategory":"Bicycle Rental",
            "type":"Entertainment"
        }
    ],
    "sg:phone":"+1 412 343 6016",
    "sg:postcode":"15220",
    "sg:province":"PA",
    "sg:tags":[
        "wear"
    ],
    "wof:name":"All American Sweats Inc",
    "wof:placetype":"venue"
},
  "geometry": {"coordinates":[-80.053902,40.405399],"type":"Point"}
}