{
  "type": "Feature",
  "properties": {
    "iso:country":"US",
    "sg:address":"5542 Penn Ave",
    "sg:city":"Pittsburgh",
    "sg:classifiers":[
        {
            "category":"Home & Garden",
            "subcategory":"Furniture",
            "type":"Retail Goods"
        }
    ],
    "sg:phone":"+1 412 362 1222",
    "sg:postcode":"15206",
    "sg:province":"PA",
    "sg:tags":[
        "juvenile"
    ],
    "sg:website":"www.babylandpa.com",
    "wof:name":"Babyland Land Kidsroom",
    "wof:placetype":"venue"
},
  "geometry": {"coordinates":[-79.93147,40.463694],"type":"Point"}
}