{
  "type": "Feature",
  "properties": {
    "addr:full":"59 N Millick St Philadelphia PA 19139",
    "addr:housenumber":"59",
    "addr:postcode":"19139",
    "addr:street":"N Millick St",
    "iso:country":"US",
    "sg:address":"59 N Millick St",
    "sg:city":"Philadelphia",
    "sg:classifiers":[
        {
            "category":"Social Services",
            "subcategory":"Child Care",
            "type":"Services"
        }
    ],
    "sg:phone":"+1 215 474 5653",
    "sg:postcode":"19139",
    "sg:province":"PA",
    "sg:tags":[
        "day"
    ],
    "wof:name":"Waller Group Day Care Home",
    "wof:placetype":"venue"
},
  "geometry": {"coordinates":[-75.24178999999999,39.963064],"type":"Point"}
}