{
  "type": "Feature",
  "properties": {
    "addr:full":"116 S Allen St State College PA 16801",
    "addr:housenumber":"116",
    "addr:postcode":"16801",
    "addr:street":"S Allen St",
    "iso:country":"US",
    "sg:address":"116 S Allen St",
    "sg:city":"State College",
    "sg:classifiers":[
        {
            "category":"Bakery",
            "type":"Food & Drink"
        },
        {
            "category":"Food & Beverages",
            "subcategory":"Groceries & Convenience Stores",
            "type":"Retail Goods"
        }
    ],
    "sg:menulink":"http://www.allmenus.com/pa/state-college/259853-mc-lanahans-downtown-mkt/menu/",
    "sg:phone":"+1 814 861 3530",
    "sg:postcode":"16801",
    "sg:province":"PA",
    "sg:tags":[
        "american",
        "bakery",
        "pastry"
    ],
    "wof:name":"Mc Lanahan's Downtown Mkt",
    "wof:placetype":"venue"
},
  "geometry": {"coordinates":[-77.861076,40.793921],"type":"Point"}
}