{
  "type": "Feature",
  "properties": {
    "iso:country":"US",
    "sg:address":"128 Colonial Ct",
    "sg:city":"State College",
    "sg:classifiers":[
        {
            "category":"Professional",
            "type":"Services"
        }
    ],
    "sg:phone":"+1   ",
    "sg:postcode":"16801",
    "sg:province":"PA",
    "wof:name":"Culturefinder Inc",
    "wof:placetype":"venue"
},
  "geometry": {"coordinates":[-77.83367200000001,40.791769],"type":"Point"}
}