{
  "type": "Feature",
  "properties": {
    "iso:country":"US",
    "sg:address":"700 Ekastown Rd",
    "sg:city":"Sarver",
    "sg:classifiers":[
        {
            "category":"Autos & Motor Vehicles",
            "subcategory":"Automobile Sales",
            "type":"Retail Goods"
        }
    ],
    "sg:phone":"+1 724 353 1555",
    "sg:postcode":"16055",
    "sg:province":"PA",
    "sg:tags":[
        "body",
        "car",
        "dealer"
    ],
    "sg:website":"www.jacksford.com",
    "wof:name":"Jack's Ford Inc",
    "wof:placetype":"venue"
},
  "geometry": {"coordinates":[-79.777136,40.711037],"type":"Point"}
}