{
  "type": "Feature",
  "properties": {
    "iso:country":"US",
    "sg:address":"1815 W Liberty Ave",
    "sg:city":"Pittsburgh",
    "sg:classifiers":[
        {
            "category":"Professional",
            "type":"Services"
        }
    ],
    "sg:phone":"+1   ",
    "sg:postcode":"15226",
    "sg:province":"PA",
    "wof:name":"Social Adam Mins",
    "wof:placetype":"venue"
},
  "geometry": {"coordinates":[-80.0188,40.405355],"type":"Point"}
}