{
  "type": "Feature",
  "properties": {
    "iso:country":"US",
    "sg:address":"68 Carlisle Rd",
    "sg:city":"Newville",
    "sg:classifiers":[
        {
            "category":"Personal",
            "subcategory":"Barber",
            "type":"Services"
        }
    ],
    "sg:phone":"+1 717 776 4141",
    "sg:postcode":"17241",
    "sg:province":"PA",
    "wof:name":"Negley's Barber Shop",
    "wof:placetype":"venue"
},
  "geometry": {"coordinates":[-77.38087299999999,40.18154],"type":"Point"}
}