{
  "type": "Feature",
  "properties": {
    "iso:country":"US",
    "sg:address":"199 W. Girard Ave",
    "sg:city":"Philadelphia",
    "sg:classifiers":[
        {
            "category":"Banks & Credit Unions",
            "subcategory":"Bank",
            "type":"Services"
        }
    ],
    "sg:phone":"+1 215 789 4200",
    "sg:postcode":"19122",
    "sg:province":"PA",
    "sg:website":"hyperionbank.com",
    "wof:name":"Hyperion Bank",
    "wof:placetype":"venue"
},
  "geometry": {"coordinates":[-75.13954200000001,39.969502],"type":"Point"}
}