{
  "type": "Feature",
  "properties": {
    "iso:country":"US",
    "sg:address":"434 Frazier St",
    "sg:city":"Braddock",
    "sg:classifiers":[
        {
            "category":"Social Services",
            "subcategory":"Child Care",
            "type":"Services"
        }
    ],
    "sg:phone":"+1 412 351 6815",
    "sg:postcode":"15104",
    "sg:province":"PA",
    "wof:name":"A Child's World Daycare",
    "wof:placetype":"venue"
},
  "geometry": {"coordinates":[-79.861453,40.399198],"type":"Point"}
}