{
  "type": "Feature",
  "properties": {
    "iso:country":"US",
    "sg:address":"3224 Bethel Church Rd",
    "sg:city":"Bethel Park",
    "sg:classifiers":[
        {
            "category":"Restaurant",
            "type":"Food & Drink"
        }
    ],
    "sg:phone":"+1   ",
    "sg:postcode":"15102",
    "sg:province":"PA",
    "sg:tags":[
        "eating"
    ],
    "wof:name":"John Greek Concessions",
    "wof:placetype":"venue"
},
  "geometry": {"coordinates":[-80.052908,40.331265],"type":"Point"}
}