{
  "type": "Feature",
  "properties": {
    "iso:country":"US",
    "sg:address":"5641 William Flynn Hwy",
    "sg:city":"Gibsonia",
    "sg:classifiers":[
        {
            "category":"Bars & Pubs",
            "type":"Food & Drink"
        }
    ],
    "sg:phone":"+1 724 443 4869",
    "sg:postcode":"15044",
    "sg:province":"PA",
    "wof:name":"Gateway Inn",
    "wof:placetype":"venue"
},
  "geometry": {"coordinates":[-79.93816200000001,40.639776],"type":"Point"}
}