{
  "type": "Feature",
  "properties": {
    "addr:full":"1011 N Broad St Lansdale PA 19446",
    "addr:housenumber":"1011",
    "addr:postcode":"19446",
    "addr:street":"N Broad St",
    "iso:country":"US",
    "sg:address":"1011 N Broad St",
    "sg:city":"Lansdale",
    "sg:classifiers":[
        {
            "category":"Real Estate",
            "subcategory":"Real Estate Services",
            "type":"Services"
        }
    ],
    "sg:phone":"+1 215 855 1169",
    "sg:postcode":"19446",
    "sg:province":"PA",
    "wof:name":"Cassel's Real Estate",
    "wof:placetype":"venue"
},
  "geometry": {"coordinates":[-75.27600099999999,40.249599],"type":"Point"}
}