{
  "type": "Feature",
  "properties": {
    "addr:full":"913 N Chester Rd West Chester PA 19380",
    "addr:housenumber":"913",
    "addr:postcode":"19380",
    "addr:street":"N Chester Rd",
    "iso:country":"US",
    "sg:address":"913 N Chester Rd",
    "sg:city":"West Chester",
    "sg:classifiers":[
        {
            "category":"Personal",
            "subcategory":"Beauty Salon",
            "type":"Services"
        }
    ],
    "sg:phone":"+1 610 696 9907",
    "sg:postcode":"19380",
    "sg:province":"PA",
    "wof:name":"Hair Cuttery",
    "wof:placetype":"venue"
},
  "geometry": {"coordinates":[-75.544543,39.995541],"type":"Point"}
}