{
  "type": "Feature",
  "properties": {
    "addr:full":"449 Baltimore St Gettysburg PA 17325",
    "addr:housenumber":"449",
    "addr:postcode":"17325",
    "addr:street":"Baltimore St",
    "iso:country":"US",
    "sg:address":"449 Baltimore St",
    "sg:city":"Gettysburg",
    "sg:classifiers":[
        {
            "category":"Organizations",
            "subcategory":"Membership Organization",
            "type":"Services"
        }
    ],
    "sg:phone":"+1 717 334 0772",
    "sg:postcode":"17325",
    "sg:province":"PA",
    "wof:name":"Friends Of The National Parks",
    "wof:placetype":"venue"
},
  "geometry": {"coordinates":[-77.231099,39.824691],"type":"Point"}
}