{
  "type": "Feature",
  "properties": {
    "addr:full":"79 Pasture Ln Bryn Mawr PA 19010",
    "addr:housenumber":"79",
    "addr:postcode":"19010",
    "addr:street":"Pasture Ln",
    "iso:country":"US",
    "sg:address":"79 Pasture Ln",
    "sg:city":"Bryn Mawr",
    "sg:classifiers":[
        {
            "category":"Organizations",
            "subcategory":"Professional Association",
            "type":"Services"
        }
    ],
    "sg:phone":"+1 610 527 1818",
    "sg:postcode":"19010",
    "sg:province":"PA",
    "wof:name":"Scotch-Irish Foundation",
    "wof:placetype":"venue"
},
  "geometry": {"coordinates":[-75.31378599999999,40.038444],"type":"Point"}
}