{
  "type": "Feature",
  "properties": {
    "iso:country":"US",
    "sg:address":"204 S Penn St",
    "sg:city":"Pleasant Gap",
    "sg:classifiers":[
        {
            "category":"Professional",
            "subcategory":"Lawyer & Legal Services",
            "type":"Services"
        }
    ],
    "sg:phone":"+1 814 364 1495",
    "sg:postcode":"16823",
    "sg:province":"PA",
    "wof:name":"Young Ledon Attorney",
    "wof:placetype":"venue"
},
  "geometry": {"coordinates":[-77.77600099999999,40.910801],"type":"Point"}
}