{
  "type": "Feature",
  "properties": {
    "iso:country":"US",
    "sg:address":"318 Gudekunst Rd",
    "sg:city":"Zelienople",
    "sg:classifiers":[
        {
            "category":"Manufacturing",
            "subcategory":"Apparel",
            "type":"Manufacturing & Wholesale Goods"
        }
    ],
    "sg:phone":"+1 724 452 8780",
    "sg:postcode":"16063",
    "sg:province":"PA",
    "sg:tags":[
        "fur",
        "mfg",
        "leather",
        "ca",
        "rug",
        "sheepskin",
        "pillow"
    ],
    "wof:name":"Hankey's Sew-A-Hide Inc",
    "wof:placetype":"venue"
},
  "geometry": {"coordinates":[-80.144908,40.760242],"type":"Point"}
}