{
  "type": "Feature",
  "properties": {
    "iso:country":"US",
    "sg:address":"13 Sheridan Dr",
    "sg:city":"Tobyhanna",
    "sg:classifiers":[
        {
            "category":"Building & Trades",
            "subcategory":"Construction",
            "type":"Services"
        }
    ],
    "sg:phone":"+1   ",
    "sg:postcode":"18466",
    "sg:province":"PA",
    "sg:tags":[
        "carpentry",
        "contractor"
    ],
    "wof:name":"B & D Carpentry",
    "wof:placetype":"venue"
},
  "geometry": {"coordinates":[-75.352586,41.144847],"type":"Point"}
}