{
  "type": "Feature",
  "properties": {
    "iso:country":"US",
    "sg:address":"455 S Washington St",
    "sg:city":"Gettysburg",
    "sg:classifiers":[
        {
            "category":"Health Services",
            "subcategory":"Doctor",
            "type":"Services"
        }
    ],
    "sg:phone":"+1   ",
    "sg:postcode":"17325",
    "sg:province":"PA",
    "sg:tags":[
        "medical"
    ],
    "wof:name":"Advanced Foot & Ankle",
    "wof:placetype":"venue"
},
  "geometry": {"coordinates":[-77.23316,39.824228],"type":"Point"}
}