{
  "type": "Feature",
  "properties": {
    "addr:full":"1247 S 47th St # 55 Philadelphia PA 19143",
    "addr:housenumber":"1247;55",
    "addr:postcode":"19143",
    "addr:street":"S 47Th St #",
    "iso:country":"US",
    "sg:address":"1247 S 47th St # 55",
    "sg:city":"Philadelphia",
    "sg:classifiers":[
        {
            "category":"Restaurant",
            "type":"Food & Drink"
        }
    ],
    "sg:phone":"+1 215 386 5553",
    "sg:postcode":"19143",
    "sg:province":"PA",
    "sg:tags":[
        "pizza"
    ],
    "wof:name":"Gold Star Pizza",
    "wof:placetype":"venue"
},
  "geometry": {"coordinates":[-75.210999,39.9436],"type":"Point"}
}