{
  "type": "Feature",
  "properties": {
    "iso:country":"US",
    "sg:address":"2175 Fox Hill Rd",
    "sg:city":"State College",
    "sg:classifiers":[
        {
            "category":"Airline",
            "type":"Transportation"
        }
    ],
    "sg:phone":"+1   ",
    "sg:postcode":"16823",
    "sg:province":"PA",
    "sg:tags":[
        "courier",
        "air"
    ],
    "wof:name":"Fedex",
    "wof:placetype":"venue"
},
  "geometry": {"coordinates":[-77.858959,40.847339],"type":"Point"}
}