{
  "type": "Feature",
  "properties": {
    "iso:country":"US",
    "sg:address":"3403 Echo Valley Rd",
    "sg:city":"Manheim",
    "sg:phone":"+1   ",
    "sg:postcode":"17545",
    "sg:province":"PA",
    "sg:tags":[
        "farm"
    ],
    "wof:name":"Frank Mattos",
    "wof:placetype":"venue"
},
  "geometry": {"coordinates":[-76.516105,40.160173],"type":"Point"}
}