{
  "type": "Feature",
  "properties": {
    "iso:country":"US",
    "sg:address":"8011 US Hwy 13",
    "sg:city":"Levittown",
    "sg:classifiers":[
        {
            "category":"Autos & Motor Vehicles",
            "subcategory":"Automobile Sales",
            "type":"Retail Goods"
        }
    ],
    "sg:phone":"+1   ",
    "sg:postcode":"19057",
    "sg:province":"PA",
    "sg:tags":[
        "used"
    ],
    "wof:name":"Arjay Motors Inc",
    "wof:placetype":"venue"
},
  "geometry": {"coordinates":[-74.822374,40.137417],"type":"Point"}
}