{
  "type": "Feature",
  "properties": {
    "addr:full":"2059 Reservoir Dr Middletown PA 17057",
    "addr:housenumber":"2059",
    "addr:postcode":"17057",
    "addr:street":"Reservoir Dr",
    "iso:country":"US",
    "sg:address":"2059 Reservoir Dr",
    "sg:city":"Middletown",
    "sg:classifiers":[
        {
            "category":"Building & Trades",
            "subcategory":"Construction",
            "type":"Services"
        }
    ],
    "sg:phone":"+1 717 944 1124",
    "sg:postcode":"17057",
    "sg:province":"PA",
    "sg:tags":[
        "excavating",
        "contractor"
    ],
    "wof:name":"Angelo's Hauling & Excavating",
    "wof:placetype":"venue"
},
  "geometry": {"coordinates":[-76.689508,40.213255],"type":"Point"}
}