{
  "type": "Feature",
  "properties": {
    "iso:country":"US",
    "sg:address":"640 Bethlehem Pike",
    "sg:city":"Montgomeryville",
    "sg:classifiers":[
        {
            "category":"Health Services",
            "subcategory":"Nursing And Care Facility",
            "type":"Services"
        }
    ],
    "sg:phone":"+1   ",
    "sg:postcode":"18915",
    "sg:province":"PA",
    "sg:tags":[
        "skilled"
    ],
    "wof:name":"Manorcare Hlth Srvces-Lansdale",
    "wof:placetype":"venue"
},
  "geometry": {"coordinates":[-75.260698,40.278157],"type":"Point"}
}