{
  "type": "Feature",
  "properties": {
    "addr:full":"1000 Church Hill Rd Ste 3 Pittsburgh PA 15205",
    "addr:housenumber":"1000",
    "addr:postcode":"15205",
    "addr:street":"Church Hill Rd Ste 3",
    "iso:country":"US",
    "sg:address":"1000 Church Hill Rd Ste 3",
    "sg:city":"Pittsburgh",
    "sg:classifiers":[
        {
            "category":"Government",
            "subcategory":"Court House",
            "type":"Public Place"
        }
    ],
    "sg:phone":"+1 412 788 8120",
    "sg:postcode":"15205",
    "sg:province":"PA",
    "sg:tags":[
        "legislator"
    ],
    "sg:website":"http://www.townshipofrobinson.com",
    "wof:name":"Township Of Robinson",
    "wof:placetype":"venue"
},
  "geometry": {"coordinates":[-80.144311,40.438033],"type":"Point"}
}