{
  "type": "Feature",
  "properties": {
    "iso:country":"US",
    "sg:address":"548 High St",
    "sg:city":"Bradford",
    "sg:classifiers":[
        {
            "category":"Manufacturing",
            "subcategory":"Rubber & Plastics",
            "type":"Manufacturing & Wholesale Goods"
        }
    ],
    "sg:phone":"+1 814 368 4454",
    "sg:postcode":"16701",
    "sg:province":"PA",
    "sg:tags":[
        "product"
    ],
    "sg:website":"www.pepperell.com",
    "wof:name":"Pepperell Braiding Co",
    "wof:placetype":"venue"
},
  "geometry": {"coordinates":[-78.643891,41.933773],"type":"Point"}
}