{
  "type": "Feature",
  "properties": {
    "iso:country":"US",
    "sg:address":"385 W Butler Dr",
    "sg:city":"Drums",
    "sg:classifiers":[
        {
            "category":"Professional",
            "subcategory":"Business Services",
            "type":"Services"
        }
    ],
    "sg:phone":"+1 570 788 6466",
    "sg:postcode":"18222",
    "sg:province":"PA",
    "sg:tags":[
        "notary"
    ],
    "wof:name":"Sue's Notary",
    "wof:placetype":"venue"
},
  "geometry": {"coordinates":[-76.003407,41.014641],"type":"Point"}
}