{
  "type": "Feature",
  "properties": {
    "iso:country":"US",
    "sg:address":"2222 E College Ave",
    "sg:city":"State College",
    "sg:classifiers":[
        {
            "category":"Food & Beverages",
            "subcategory":"Groceries & Convenience Stores",
            "type":"Retail Goods"
        }
    ],
    "sg:phone":"+1   ",
    "sg:postcode":"16801",
    "sg:province":"PA",
    "sg:tags":[
        "prod",
        "mfg"
    ],
    "wof:name":"Giant",
    "wof:placetype":"venue"
},
  "geometry": {"coordinates":[-77.814144,40.822096],"type":"Point"}
}