{
  "type": "Feature",
  "properties": {
    "iso:country":"US",
    "sg:address":"7306 Columbia Blvd",
    "sg:city":"Bloomsburg",
    "sg:classifiers":[
        {
            "category":"Insurance",
            "subcategory":"Hazard Insurance",
            "type":"Services"
        }
    ],
    "sg:phone":"+1 570 752 8884",
    "sg:postcode":"17815",
    "sg:province":"PA",
    "sg:tags":[
        "commercial",
        "business"
    ],
    "sg:website":"http://www.thrivent.com",
    "wof:name":"Thrivent Financial for Lutherans",
    "wof:placetype":"venue"
},
  "geometry": {"coordinates":[-76.393559,41.01684],"type":"Point"}
}