{
  "type": "Feature",
  "properties": {
    "iso:country":"US",
    "sg:address":"15 Ledum Run Rd",
    "sg:city":"West Grove",
    "sg:classifiers":[
        {
            "category":"Retail",
            "subcategory":"Portrait Studio",
            "type":"Services"
        }
    ],
    "sg:phone":"+1   ",
    "sg:postcode":"19390",
    "sg:province":"PA",
    "sg:tags":[
        "photo"
    ],
    "wof:name":"Shipman John Lewis Photography",
    "wof:placetype":"venue"
},
  "geometry": {"coordinates":[-75.886093,39.80058],"type":"Point"}
}