{
  "type": "Feature",
  "properties": {
    "addr:full":"1701 7th Ave Altoona PA 16602",
    "addr:housenumber":"1701",
    "addr:postcode":"16602",
    "addr:street":"7Th Ave",
    "iso:country":"US",
    "sg:address":"1701 7th Ave",
    "sg:city":"Altoona",
    "sg:classifiers":[
        {
            "category":"Food & Beverages",
            "subcategory":"Groceries & Convenience Stores",
            "type":"Retail Goods"
        }
    ],
    "sg:phone":"+1 814 943 4477",
    "sg:postcode":"16602",
    "sg:province":"PA",
    "sg:tags":[
        "grocer"
    ],
    "sg:website":"www.sheetz.com",
    "wof:name":"Sheetz Inc",
    "wof:placetype":"venue"
},
  "geometry": {"coordinates":[-78.40169400000001,40.50844],"type":"Point"}
}