{
  "type": "Feature",
  "properties": {
    "addr:full":"7 Public Ave Montrose PA 18801",
    "addr:housenumber":"7",
    "addr:postcode":"18801",
    "addr:street":"Public Ave",
    "iso:country":"US",
    "sg:address":"7 Public Ave",
    "sg:city":"Montrose",
    "sg:classifiers":[
        {
            "category":"Professional",
            "subcategory":"Lawyer & Legal Services",
            "type":"Services"
        }
    ],
    "sg:phone":"+1 570 278 4015",
    "sg:postcode":"18801",
    "sg:province":"PA",
    "sg:tags":[
        "attorney"
    ],
    "wof:name":"Marion O'Malley",
    "wof:placetype":"venue"
},
  "geometry": {"coordinates":[-75.877447,41.833934],"type":"Point"}
}