{
  "type": "Feature",
  "properties": {
    "iso:country":"US",
    "sg:address":"121 N Broad St",
    "sg:city":"Grove City",
    "sg:classifiers":[
        {
            "category":"Autos & Motor Vehicles",
            "subcategory":"Automobile Sales",
            "type":"Retail Goods"
        }
    ],
    "sg:phone":"+1   ",
    "sg:postcode":"16127",
    "sg:province":"PA",
    "sg:tags":[
        "used"
    ],
    "wof:name":"Maxwell Motor Sales & Service",
    "wof:placetype":"venue"
},
  "geometry": {"coordinates":[-80.085904,41.161902],"type":"Point"}
}