{
  "type": "Feature",
  "properties": {
    "addr:full":"140 W Walnut St Washington PA 15301",
    "addr:housenumber":"140",
    "addr:postcode":"15301",
    "addr:street":"W Walnut St",
    "iso:country":"US",
    "sg:address":"140 W Walnut St",
    "sg:city":"Washington",
    "sg:classifiers":[
        {
            "category":"Shopping",
            "type":"Retail Goods"
        }
    ],
    "sg:phone":"+1 724 914 6016",
    "sg:postcode":"15301",
    "sg:province":"PA",
    "sg:tags":[
        "product",
        "wood"
    ],
    "wof:name":"Wood Steven",
    "wof:placetype":"venue"
},
  "geometry": {"coordinates":[-80.25136000000001,40.1732],"type":"Point"}
}