{
  "type": "Feature",
  "properties": {
    "iso:country":"US",
    "sg:address":"1023 Gap Rd",
    "sg:city":"Kinzers",
    "sg:classifiers":[
        {
            "category":"Retail",
            "subcategory":"Repair Shop",
            "type":"Services"
        }
    ],
    "sg:phone":"+1   ",
    "sg:postcode":"17535",
    "sg:province":"PA",
    "sg:tags":[
        "welding"
    ],
    "wof:name":"Sunny Hill Welding",
    "wof:placetype":"venue"
},
  "geometry": {"coordinates":[-76.02162199999999,39.97487],"type":"Point"}
}