{
  "type": "Feature",
  "properties": {
    "addr:full":"1105 Westminster Rd Harrisburg PA 17109",
    "addr:housenumber":"1105",
    "addr:postcode":"17109",
    "addr:street":"Westminster Rd",
    "iso:country":"US",
    "sg:address":"1105 Westminster Rd",
    "sg:city":"Harrisburg",
    "sg:classifiers":[
        {
            "category":"Social Services",
            "subcategory":"Child Care",
            "type":"Services"
        }
    ],
    "sg:phone":"+1 717 651 5734",
    "sg:postcode":"17109",
    "sg:province":"PA",
    "sg:tags":[
        "day"
    ],
    "wof:name":"Heaven Sent Learning Center",
    "wof:placetype":"venue"
},
  "geometry": {"coordinates":[-76.8396,40.300301],"type":"Point"}
}