{
  "type": "Feature",
  "properties": {
    "iso:country":"US",
    "sg:address":"1671 Orchard Dr",
    "sg:city":"Chambersburg",
    "sg:classifiers":[
        {
            "category":"Manufacturing",
            "subcategory":"Tools & Machinery",
            "type":"Manufacturing & Wholesale Goods"
        }
    ],
    "sg:phone":"+1 717 261 9700",
    "sg:postcode":"17201",
    "sg:province":"PA",
    "sg:tags":[
        "equipment",
        "mfg",
        "laboratory"
    ],
    "sg:website":"www.tbjinc.com",
    "wof:name":"TBJ Inc",
    "wof:placetype":"venue"
},
  "geometry": {"coordinates":[-77.667624,39.914011],"type":"Point"}
}