{
  "type": "Feature",
  "properties": {
    "addr:full":"1331 E Wyoming Ave Philadelphia PA 19124",
    "addr:housenumber":"1331",
    "addr:postcode":"19124",
    "addr:street":"E Wyoming Ave",
    "iso:country":"US",
    "sg:address":"1331 E Wyoming Ave",
    "sg:city":"Philadelphia",
    "sg:classifiers":[
        {
            "category":"Health Services",
            "subcategory":"Hospital",
            "type":"Services"
        }
    ],
    "sg:phone":"+1 215 537 7400",
    "sg:postcode":"19124",
    "sg:province":"PA",
    "sg:tags":[
        "medical",
        "specialty",
        "hosp"
    ],
    "wof:name":"Parkview Hospital",
    "wof:placetype":"venue"
},
  "geometry": {"coordinates":[-75.099637,40.018459],"type":"Point"}
}