{
  "type": "Feature",
  "properties": {
    "iso:country":"US",
    "sg:address":"2320 Coles Blvd",
    "sg:city":"Norristown",
    "sg:classifiers":[
        {
            "category":"Utilities",
            "type":"Services"
        }
    ],
    "sg:phone":"+1 610 272 0741",
    "sg:postcode":"19401",
    "sg:province":"PA",
    "sg:tags":[
        "locating"
    ],
    "wof:name":"Underground Utilities",
    "wof:placetype":"venue"
},
  "geometry": {"coordinates":[-75.324202,40.138306],"type":"Point"}
}