{
  "type": "Feature",
  "properties": {
    "iso:country":"US",
    "sg:address":"1828 Liberty Way",
    "sg:city":"Valencia",
    "sg:classifiers":[
        {
            "category":"Sports & Exercise",
            "subcategory":"Golf",
            "type":"Entertainment"
        }
    ],
    "sg:phone":"+1   ",
    "sg:postcode":"16059",
    "sg:province":"PA",
    "sg:tags":[
        "course"
    ],
    "wof:name":"Pheasant Ridge Golf Course",
    "wof:placetype":"venue"
},
  "geometry": {"coordinates":[-79.984145,40.690174],"type":"Point"}
}