{
  "type": "Feature",
  "properties": {
    "iso:country":"US",
    "sg:address":"1303 Main St",
    "sg:city":"Pittston",
    "sg:classifiers":[
        {
            "category":"Building & Trades",
            "subcategory":"Landscaping Services",
            "type":"Services"
        }
    ],
    "sg:phone":"+1   ",
    "sg:postcode":"18640",
    "sg:province":"PA",
    "wof:name":"Eds Lawn Care and Land Improv",
    "wof:placetype":"venue"
},
  "geometry": {"coordinates":[-75.812482,41.31105],"type":"Point"}
}