{
  "type": "Feature",
  "properties": {
    "addr:full":"2910 Monticello Pl York PA 17408",
    "addr:housenumber":"2910",
    "addr:postcode":"17408",
    "addr:street":"Monticello Pl",
    "iso:country":"US",
    "sg:address":"2910 Monticello Pl",
    "sg:city":"York",
    "sg:classifiers":[
        {
            "category":"Professional",
            "subcategory":"Management & Consulting",
            "type":"Services"
        }
    ],
    "sg:phone":"+1 717 792 0188",
    "sg:postcode":"17408",
    "sg:province":"PA",
    "sg:tags":[
        "consultant",
        "business"
    ],
    "wof:name":"Relevant Reporting",
    "wof:placetype":"venue"
},
  "geometry": {"coordinates":[-76.828585,39.965177],"type":"Point"}
}