{
  "type": "Feature",
  "properties": {
    "iso:country":"US",
    "sg:address":"3007 Gateway Dr",
    "sg:city":"Royersford",
    "sg:classifiers":[
        {
            "category":"Freight",
            "type":"Transportation"
        }
    ],
    "sg:phone":"+1   ",
    "sg:postcode":"19468",
    "sg:province":"PA",
    "sg:tags":[
        "bulk",
        "company"
    ],
    "wof:name":"Mountain Ridge Transportation",
    "wof:placetype":"venue"
},
  "geometry": {"coordinates":[-75.534888,40.226384],"type":"Point"}
}