{
  "type": "Feature",
  "properties": {
    "iso:country":"US",
    "sg:address":"244 Replogle School Rd",
    "sg:city":"New Enterprise",
    "sg:classifiers":[
        {
            "category":"Wholesale",
            "subcategory":"Farm Supplies",
            "type":"Manufacturing & Wholesale Goods"
        }
    ],
    "sg:phone":"+1   ",
    "sg:postcode":"16664",
    "sg:province":"PA",
    "wof:name":"Dean Grimes",
    "wof:placetype":"venue"
},
  "geometry": {"coordinates":[-78.396303,40.196713],"type":"Point"}
}