{
  "type": "Feature",
  "properties": {
    "addr:full":"6808 Reynolds St Pittsburgh PA 15208",
    "addr:housenumber":"6808",
    "addr:postcode":"15208",
    "addr:street":"Reynolds St",
    "iso:country":"US",
    "sg:address":"6808 Reynolds St",
    "sg:city":"Pittsburgh",
    "sg:classifiers":[
        {
            "category":"Banks & Credit Unions",
            "subcategory":"Investment Brokerage",
            "type":"Services"
        }
    ],
    "sg:phone":"+1   ",
    "sg:postcode":"15208",
    "sg:province":"PA",
    "sg:tags":[
        "advisory"
    ],
    "wof:name":"Chu Investment Counsel In",
    "wof:placetype":"venue"
},
  "geometry": {"coordinates":[-79.913006,40.449723],"type":"Point"}
}