{
  "type": "Feature",
  "properties": {
    "addr:full":"316 Market St Philadelphia PA 19106",
    "addr:housenumber":"316",
    "addr:postcode":"19106",
    "addr:street":"Market St",
    "iso:country":"US",
    "sg:address":"316 Market St",
    "sg:city":"Philadelphia",
    "sg:classifiers":[
        {
            "category":"Government",
            "subcategory":"Post Office",
            "type":"Public Place"
        }
    ],
    "sg:phone":"+1 215 592 9610",
    "sg:postcode":"19106",
    "sg:province":"PA",
    "sg:website":"www.usps.com",
    "wof:name":"US Post Office - B Free Franklin",
    "wof:placetype":"venue"
},
  "geometry": {"coordinates":[-75.146432,39.950253],"type":"Point"}
}