{
  "type": "Feature",
  "properties": {
    "addr:full":"440 W Kings Hwy Wagontown PA 19320",
    "addr:housenumber":"440",
    "addr:postcode":"19320",
    "addr:street":"W Kings Hwy",
    "iso:country":"US",
    "sg:address":"440 W Kings Hwy",
    "sg:city":"Wagontown",
    "sg:classifiers":[
        {
            "category":"Travel",
            "subcategory":"Hotels & Motels",
            "type":"Entertainment"
        }
    ],
    "sg:phone":"+1 610 466 7471",
    "sg:postcode":"19320",
    "sg:province":"PA",
    "sg:tags":[
        "breakfast",
        "accommodation",
        "bed"
    ],
    "wof:name":"Country Angel Antiques",
    "wof:placetype":"venue"
},
  "geometry": {"coordinates":[-75.842715,40.010522],"type":"Point"}
}