{
  "type": "Feature",
  "properties": {
    "addr:full":"2510 Arcona Rd Mechanicsburg PA 17055",
    "addr:housenumber":"2510",
    "addr:postcode":"17055",
    "addr:street":"Arcona Rd",
    "iso:country":"US",
    "sg:address":"2510 Arcona Rd",
    "sg:city":"Mechanicsburg",
    "sg:classifiers":[
        {
            "category":"Restaurant",
            "type":"Food & Drink"
        }
    ],
    "sg:phone":"+1   ",
    "sg:postcode":"17055",
    "sg:province":"PA",
    "sg:tags":[
        "eating"
    ],
    "wof:name":"Freemans Texas Style Barbeque",
    "wof:placetype":"venue"
},
  "geometry": {"coordinates":[-76.94509499999999,40.177822],"type":"Point"}
}