{
  "type": "Feature",
  "properties": {
    "iso:country":"US",
    "sg:address":"248 E Broad St",
    "sg:city":"Tamaqua",
    "sg:classifiers":[
        {
            "category":"Personal",
            "subcategory":"Beauty Salon",
            "type":"Services"
        }
    ],
    "sg:phone":"+1 570 668 0677",
    "sg:postcode":"18252",
    "sg:province":"PA",
    "wof:name":"Regina Hills Coiffures",
    "wof:placetype":"venue"
},
  "geometry": {"coordinates":[-75.96597300000001,40.797381],"type":"Point"}
}