{
  "type": "Feature",
  "properties": {
    "iso:country":"US",
    "sg:address":"1202 Oakridge Dr",
    "sg:city":"Butler",
    "sg:classifiers":[
        {
            "category":"Professional",
            "subcategory":"Lawyer & Legal Services",
            "type":"Services"
        }
    ],
    "sg:phone":"+1 724 285 1352",
    "sg:postcode":"16001",
    "sg:province":"PA",
    "sg:tags":[
        "attorney",
        "practice"
    ],
    "wof:name":"Lynn M Patterson Attorney",
    "wof:placetype":"venue"
},
  "geometry": {"coordinates":[-79.894779,40.840598],"type":"Point"}
}