{
  "type": "Feature",
  "properties": {
    "addr:full":"6 Bailey Ave Pittsburgh PA 15211",
    "addr:housenumber":"6",
    "addr:postcode":"15211",
    "addr:street":"Bailey Ave",
    "iso:country":"US",
    "sg:address":"6 Bailey Ave",
    "sg:city":"Pittsburgh",
    "sg:classifiers":[
        {
            "category":"Restaurant",
            "type":"Food & Drink"
        }
    ],
    "sg:phone":"+1 412 381 9300",
    "sg:postcode":"15211",
    "sg:province":"PA",
    "sg:tags":[
        "pizza"
    ],
    "sg:website":"www.foxspizza.com",
    "wof:name":"Fox's Pizza Den",
    "wof:placetype":"venue"
},
  "geometry": {"coordinates":[-80.005402,40.426899],"type":"Point"}
}