{
  "type": "Feature",
  "properties": {
    "iso:country":"US",
    "sg:address":"3600 Blvd of the Allies",
    "sg:city":"Pittsburgh",
    "sg:classifiers":[
        {
            "category":"Autos & Motor Vehicles",
            "subcategory":"Fuel & Gas Station",
            "type":"Retail Goods"
        }
    ],
    "sg:phone":"+1   ",
    "sg:postcode":"15213",
    "sg:province":"PA",
    "sg:tags":[
        "station",
        "gasoline"
    ],
    "wof:name":"Jims Service Station",
    "wof:placetype":"venue"
},
  "geometry": {"coordinates":[-79.95319000000001,40.434383],"type":"Point"}
}