{
  "type": "Feature",
  "properties": {
    "addr:full":"125 E 3rd Ave Conshohocken PA 19428",
    "addr:housenumber":"125",
    "addr:postcode":"19428",
    "addr:street":"E 3Rd Ave",
    "iso:country":"US",
    "sg:address":"125 E 3rd Ave",
    "sg:city":"Conshohocken",
    "sg:classifiers":[
        {
            "category":"Wholesale",
            "subcategory":"Hardware",
            "type":"Manufacturing & Wholesale Goods"
        }
    ],
    "sg:phone":"+1 610 828 7300",
    "sg:postcode":"19428",
    "sg:province":"PA",
    "sg:tags":[
        "equipment",
        "energy",
        "solar"
    ],
    "wof:name":"Solar Priorities",
    "wof:placetype":"venue"
},
  "geometry": {"coordinates":[-75.30269699999999,40.074341],"type":"Point"}
}