{
  "type": "Feature",
  "properties": {
    "addr:full":"517 E Main St Ephrata PA 17522",
    "addr:housenumber":"517",
    "addr:postcode":"17522",
    "addr:street":"E Main St",
    "iso:country":"US",
    "sg:address":"517 E Main St",
    "sg:city":"Ephrata",
    "sg:classifiers":[
        {
            "category":"Health Services",
            "subcategory":"Clinic",
            "type":"Services"
        }
    ],
    "sg:phone":"+1 717 738 3175",
    "sg:postcode":"17522",
    "sg:province":"PA",
    "sg:tags":[
        "specialty",
        "outpatient"
    ],
    "wof:name":"Shared Supports Concepts Inc",
    "wof:placetype":"venue"
},
  "geometry": {"coordinates":[-76.17096600000001,40.172076],"type":"Point"}
}