{
  "type": "Feature",
  "properties": {
    "iso:country":"US",
    "sg:address":"347 S Market St",
    "sg:city":"Elizabethtown",
    "sg:classifiers":[
        {
            "category":"Professional",
            "subcategory":"Advertising",
            "type":"Services"
        }
    ],
    "sg:phone":"+1 717 367 6458",
    "sg:postcode":"17022",
    "sg:province":"PA",
    "sg:tags":[
        "agency"
    ],
    "wof:name":"Rice & Rice LTD",
    "wof:placetype":"venue"
},
  "geometry": {"coordinates":[-76.603335,40.147495],"type":"Point"}
}