{
  "type": "Feature",
  "properties": {
    "addr:full":"144 Gallery Dr Canonsburg PA 15317",
    "addr:housenumber":"144",
    "addr:postcode":"15317",
    "addr:street":"Gallery Dr",
    "iso:country":"US",
    "sg:address":"144 Gallery Dr",
    "sg:city":"Canonsburg",
    "sg:classifiers":[
        {
            "category":"Shopping",
            "subcategory":"Pharmacy",
            "type":"Retail Goods"
        }
    ],
    "sg:phone":"+1 724 941 3004",
    "sg:postcode":"15317",
    "sg:province":"PA",
    "sg:tags":[
        "drugstore"
    ],
    "wof:name":"Rite Aid Pharmacies",
    "wof:placetype":"venue"
},
  "geometry": {"coordinates":[-80.113392,40.290306],"type":"Point"}
}