{
  "type": "Feature",
  "properties": {
    "addr:full":"8917 W Chester Pike Upper Darby PA 19082",
    "addr:housenumber":"8917",
    "addr:postcode":"19082",
    "addr:street":"W Chester Pike",
    "iso:country":"US",
    "sg:address":"8917 W Chester Pike",
    "sg:city":"Upper Darby",
    "sg:classifiers":[
        {
            "category":"Restaurant",
            "type":"Food & Drink"
        }
    ],
    "sg:menulink":"http://www.allmenus.com/pa/upper-darby/247507-verona-pizza/menu/",
    "sg:phone":"+1 610 789 4454",
    "sg:postcode":"19082",
    "sg:province":"PA",
    "sg:tags":[
        "sandwich",
        "salad",
        "greek",
        "seafood",
        "pasta",
        "burger",
        "american",
        "wrap",
        "chicken",
        "pizza",
        "wing",
        "italian"
    ],
    "wof:name":"Verona Pizza",
    "wof:placetype":"venue"
},
  "geometry": {"coordinates":[-75.289179,39.967639],"type":"Point"}
}