{
  "type": "Feature",
  "properties": {
    "iso:country":"US",
    "sg:address":"1935 Buchanan Ave",
    "sg:city":"Croydon",
    "sg:classifiers":[
        {
            "category":"Utilities",
            "subcategory":"Fuel Oil & Lpg",
            "type":"Services"
        }
    ],
    "sg:phone":"+1   ",
    "sg:postcode":"19021",
    "sg:province":"PA",
    "sg:tags":[
        "dealer"
    ],
    "wof:name":"Wolf Wm W",
    "wof:placetype":"venue"
},
  "geometry": {"coordinates":[-74.89425900000001,40.096445],"type":"Point"}
}