{
  "type": "Feature",
  "properties": {
    "iso:country":"US",
    "sg:address":"200 Adams Ave",
    "sg:city":"Scranton",
    "sg:classifiers":[
        {
            "category":"Government",
            "subcategory":"Court House",
            "type":"Public Place"
        }
    ],
    "sg:phone":"+1   ",
    "sg:postcode":"18503",
    "sg:province":"PA",
    "sg:tags":[
        "legal"
    ],
    "wof:name":"Andy Jarbola",
    "wof:placetype":"venue"
},
  "geometry": {"coordinates":[-75.66103099999999,41.408274],"type":"Point"}
}