{
  "type": "Feature",
  "properties": {
    "iso:country":"US",
    "sg:address":"3611 Nicholas St",
    "sg:city":"Easton",
    "sg:classifiers":[
        {
            "category":"Retail",
            "subcategory":"Veterinary Services",
            "type":"Services"
        }
    ],
    "sg:phone":"+1   ",
    "sg:postcode":"18045",
    "sg:province":"PA",
    "wof:name":"Palmer Pet Place",
    "wof:placetype":"venue"
},
  "geometry": {"coordinates":[-75.263116,40.672313],"type":"Point"}
}