{
  "type": "Feature",
  "properties": {
    "iso:country":"US",
    "sg:address":"1425 Meadowbrook Rd",
    "sg:city":"Jenkintown",
    "sg:classifiers":[
        {
            "category":"Professional",
            "subcategory":"Business Services",
            "type":"Services"
        }
    ],
    "sg:phone":"+1 215 887 4447",
    "sg:postcode":"19046",
    "sg:province":"PA",
    "sg:tags":[
        "lecture",
        "bureau",
        "seminar"
    ],
    "wof:name":"Computer Savvy Dentist",
    "wof:placetype":"venue"
},
  "geometry": {"coordinates":[-75.101169,40.120489],"type":"Point"}
}