{
  "type": "Feature",
  "properties": {
    "addr:full":"464 W King St Abbottstown PA 17301",
    "addr:housenumber":"464",
    "addr:postcode":"17301",
    "addr:street":"W King St",
    "iso:country":"US",
    "sg:address":"464 W King St",
    "sg:city":"Abbottstown",
    "sg:classifiers":[
        {
            "category":"Retail",
            "subcategory":"Repair Shop",
            "type":"Services"
        }
    ],
    "sg:phone":"+1 717 259 7943",
    "sg:postcode":"17301",
    "sg:province":"PA",
    "sg:tags":[
        "taxidermist"
    ],
    "wof:name":"Jerry's Taxidermy",
    "wof:placetype":"venue"
},
  "geometry": {"coordinates":[-76.992784,39.884013],"type":"Point"}
}