{
  "type": "Feature",
  "properties": {
    "iso:country":"US",
    "sg:address":"23 N Chester Rd",
    "sg:city":"West Chester",
    "sg:classifiers":[
        {
            "category":"Shopping",
            "subcategory":"Jewelry",
            "type":"Retail Goods"
        }
    ],
    "sg:phone":"+1   ",
    "sg:postcode":"19380",
    "sg:province":"PA",
    "wof:name":"Sunset Hill Jewelers Ltd",
    "wof:placetype":"venue"
},
  "geometry": {"coordinates":[-75.523421,39.966803],"type":"Point"}
}