{
  "type": "Feature",
  "properties": {
    "iso:country":"US",
    "sg:address":"311 W 24th St",
    "sg:city":"Erie",
    "sg:phone":"+1 814 459 1851",
    "sg:postcode":"16502",
    "sg:province":"PA",
    "wof:name":"Dailey Ellen E MD",
    "wof:placetype":"venue"
},
  "geometry": {"coordinates":[-80.081063,42.111279],"type":"Point"}
}