{
  "type": "Feature",
  "properties": {
    "addr:full":"2245 E Lincoln Hwy Langhorne PA 19047",
    "addr:housenumber":"2245",
    "addr:postcode":"19047",
    "addr:street":"E Lincoln Hwy Langhorne Pa",
    "iso:country":"US",
    "sg:address":"2245 E Lincoln Hwy",
    "sg:city":"Langhorne",
    "sg:classifiers":[
        {
            "category":"Restaurant",
            "type":"Food & Drink"
        }
    ],
    "sg:menulink":"http://www.allmenus.com/pa/woodbourne/13804-olive-garden-italian-restaurant/menu/",
    "sg:phone":"+1 215 943 2112",
    "sg:postcode":"19047",
    "sg:province":"PA",
    "sg:tags":[
        "italian"
    ],
    "wof:name":"Olive Garden Italian Restaurant",
    "wof:placetype":"venue"
},
  "geometry": {"coordinates":[-74.881073,40.178287],"type":"Point"}
}