{
  "type": "Feature",
  "properties": {
    "iso:country":"US",
    "sg:address":"4233 Edgmont Ave",
    "sg:city":"Brookhaven",
    "sg:classifiers":[
        {
            "category":"Utilities",
            "subcategory":"Mobile Phone",
            "type":"Services"
        },
        {
            "category":"Utilities",
            "subcategory":"Telephone",
            "type":"Services"
        },
        {
            "category":"Manufacturing",
            "subcategory":"Electronics",
            "type":"Manufacturing & Wholesale Goods"
        }
    ],
    "sg:phone":"+1 610 499 0270",
    "sg:postcode":"19015",
    "sg:province":"PA",
    "sg:tags":[
        "equipment",
        "telecommunications-equipment",
        "system",
        "cellular",
        "supply"
    ],
    "wof:name":"Cellular Connection",
    "wof:placetype":"venue"
},
  "geometry": {"coordinates":[-75.389619,39.873267],"type":"Point"}
}