{
  "type": "Feature",
  "properties": {
    "addr:full":"1210 N Front St Reading PA 19601",
    "addr:housenumber":"1210",
    "addr:postcode":"19601",
    "addr:street":"N Front St",
    "iso:country":"US",
    "sg:address":"1210 N Front St",
    "sg:city":"Reading",
    "sg:classifiers":[
        {
            "category":"Arts & Performance",
            "subcategory":"Theater",
            "type":"Entertainment"
        }
    ],
    "sg:phone":"+1   ",
    "sg:postcode":"19601",
    "sg:province":"PA",
    "sg:tags":[
        "group"
    ],
    "wof:name":"Winstons Gregg Supersound Dj",
    "wof:placetype":"venue"
},
  "geometry": {"coordinates":[-75.93518400000001,40.354863],"type":"Point"}
}