{
  "type": "Feature",
  "properties": {
    "iso:country":"US",
    "sg:address":"387 York Ave",
    "sg:city":"Towanda",
    "sg:classifiers":[
        {
            "category":"Personal",
            "subcategory":"Beauty Salon",
            "type":"Services"
        }
    ],
    "sg:phone":"+1 570 268 4925",
    "sg:postcode":"18848",
    "sg:province":"PA",
    "sg:tags":[
        "shop"
    ],
    "wof:name":"Stylin' Station",
    "wof:placetype":"venue"
},
  "geometry": {"coordinates":[-76.44923799999999,41.782028],"type":"Point"}
}