{
  "type": "Feature",
  "properties": {
    "addr:full":"131 W Maple St Milton PA 17847",
    "addr:housenumber":"131",
    "addr:postcode":"17847",
    "addr:street":"W Maple St",
    "iso:country":"US",
    "sg:address":"131 W Maple St",
    "sg:city":"Milton",
    "sg:classifiers":[
        {
            "category":"Manufacturing",
            "subcategory":"Food",
            "type":"Manufacturing & Wholesale Goods"
        }
    ],
    "sg:phone":"+1   ",
    "sg:postcode":"17847",
    "sg:province":"PA",
    "sg:tags":[
        "product",
        "mfg"
    ],
    "wof:name":"Specialty Desserts",
    "wof:placetype":"venue"
},
  "geometry": {"coordinates":[-76.84866700000001,41.005623],"type":"Point"}
}