{
  "type": "Feature",
  "properties": {
    "iso:country":"US",
    "sg:address":"5474 Old Mile Hill Rd",
    "sg:city":"Orefield",
    "sg:phone":"+1   ",
    "sg:postcode":"18069",
    "sg:province":"PA",
    "sg:tags":[
        "farm",
        "wheat"
    ],
    "wof:name":"Jeffrey Johnson",
    "wof:placetype":"venue"
},
  "geometry": {"coordinates":[-75.60366999999999,40.632754],"type":"Point"}
}