{
  "type": "Feature",
  "properties": {
    "addr:full":"3560 Gettysburg Rd Camp Hill PA 17011",
    "addr:housenumber":"3560",
    "addr:postcode":"17011",
    "addr:street":"Gettysburg Rd",
    "iso:country":"US",
    "sg:address":"3560 Gettysburg Rd",
    "sg:city":"Camp Hill",
    "sg:classifiers":[
        {
            "category":"Real Estate",
            "subcategory":"Real Estate Agent",
            "type":"Services"
        }
    ],
    "sg:phone":"+1 717 909 3948",
    "sg:postcode":"17011",
    "sg:province":"PA",
    "sg:website":"www.exithomefinder.com",
    "wof:name":"Exit Platinum Plus Realty",
    "wof:placetype":"venue"
},
  "geometry": {"coordinates":[-76.93816,40.223945],"type":"Point"}
}