{
  "type": "Feature",
  "properties": {
    "addr:full":"1500 E Lancaster Ave Paoli PA 19301",
    "addr:housenumber":"1500",
    "addr:postcode":"19301",
    "addr:street":"E Lancaster Ave",
    "iso:country":"US",
    "sg:address":"1500 E Lancaster Ave",
    "sg:city":"Paoli",
    "sg:classifiers":[
        {
            "category":"Health Services",
            "subcategory":"Health Practitioner",
            "type":"Services"
        }
    ],
    "sg:phone":"+1 610 296 9114",
    "sg:postcode":"19301",
    "sg:province":"PA",
    "sg:tags":[
        "psychologist"
    ],
    "wof:name":"Karen Clark Shock",
    "wof:placetype":"venue"
},
  "geometry": {"coordinates":[-75.46296100000001,40.042523],"type":"Point"}
}