{
  "type": "Feature",
  "properties": {
    "addr:full":"507 New Castle St Butler PA 16001",
    "addr:housenumber":"507",
    "addr:postcode":"16001",
    "addr:street":"New Castle St",
    "iso:country":"US",
    "sg:address":"507 New Castle St",
    "sg:city":"Butler",
    "sg:classifiers":[
        {
            "category":"Retail",
            "subcategory":"Auto Repair",
            "type":"Services"
        }
    ],
    "sg:phone":"+1 724 282 8182",
    "sg:postcode":"16001",
    "sg:province":"PA",
    "sg:tags":[
        "repairing",
        "automobile"
    ],
    "wof:name":"Stef & Joe's Auto & Truck Rpr",
    "wof:placetype":"venue"
},
  "geometry": {"coordinates":[-79.90280300000001,40.861945],"type":"Point"}
}