{
  "type": "Feature",
  "properties": {
    "iso:country":"US",
    "sg:address":"114 Lillyville Rd",
    "sg:city":"Ellwood City",
    "sg:classifiers":[
        {
            "category":"Home & Garden",
            "subcategory":"Carpets & Floor Coverings",
            "type":"Retail Goods"
        }
    ],
    "sg:phone":"+1   ",
    "sg:postcode":"16117",
    "sg:province":"PA",
    "wof:name":"Bob Goehring Installation",
    "wof:placetype":"venue"
},
  "geometry": {"coordinates":[-80.227884,40.843957],"type":"Point"}
}