{
  "type": "Feature",
  "properties": {
    "iso:country":"US",
    "sg:address":"33 E Main St",
    "sg:city":"Lititz",
    "sg:classifiers":[
        {
            "category":"Home & Garden",
            "subcategory":"Building Materials",
            "type":"Retail Goods"
        }
    ],
    "sg:phone":"+1 717 627 7278",
    "sg:postcode":"17543",
    "sg:province":"PA",
    "wof:name":"A Colorful Past",
    "wof:placetype":"venue"
},
  "geometry": {"coordinates":[-76.306066,40.157118],"type":"Point"}
}