{
  "type": "Feature",
  "properties": {
    "addr:full":"19 Horseshoe Ln Hatboro PA 19040",
    "addr:housenumber":"19",
    "addr:postcode":"19040",
    "addr:street":"Horseshoe Ln",
    "iso:country":"US",
    "sg:address":"19 Horseshoe Ln",
    "sg:city":"Hatboro",
    "sg:classifiers":[
        {
            "category":"Health Services",
            "subcategory":"Doctor",
            "type":"Services"
        }
    ],
    "sg:phone":"+1   ",
    "sg:postcode":"19040",
    "sg:province":"PA",
    "sg:tags":[
        "medical"
    ],
    "wof:name":"Harry D Snyder MD",
    "wof:placetype":"venue"
},
  "geometry": {"coordinates":[-75.106931,40.165309],"type":"Point"}
}