{
  "type": "Feature",
  "properties": {
    "iso:country":"US",
    "sg:address":"568 Sugar Loaf Ln",
    "sg:city":"Tafton",
    "sg:classifiers":[
        {
            "category":"Professional",
            "subcategory":"Management & Consulting",
            "type":"Services"
        }
    ],
    "sg:phone":"+1   ",
    "sg:postcode":"18464",
    "sg:province":"PA",
    "sg:tags":[
        "computer",
        "technology"
    ],
    "wof:name":"Rct Systems",
    "wof:placetype":"venue"
},
  "geometry": {"coordinates":[-75.167849,41.418577],"type":"Point"}
}