{
  "type": "Feature",
  "properties": {
    "iso:country":"US",
    "sg:address":"1110 Rising Sun Ave",
    "sg:city":"Philadelphia",
    "sg:classifiers":[
        {
            "category":"Professional",
            "type":"Services"
        }
    ],
    "sg:phone":"+1   ",
    "sg:postcode":"19140",
    "sg:province":"PA",
    "wof:name":"Bor Pailinn Inc",
    "wof:placetype":"venue"
},
  "geometry": {"coordinates":[-75.146653,40.005126],"type":"Point"}
}