{
  "type": "Feature",
  "properties": {
    "iso:country":"US",
    "sg:address":"38 E Columbus Ave",
    "sg:city":"Corry",
    "sg:classifiers":[
        {
            "category":"Real Estate",
            "subcategory":"Real Estate Agent",
            "type":"Services"
        }
    ],
    "sg:phone":"+1 814 663 0365",
    "sg:postcode":"16407",
    "sg:province":"PA",
    "wof:name":"Rice Realty",
    "wof:placetype":"venue"
},
  "geometry": {"coordinates":[-79.640636,41.936473],"type":"Point"}
}