{
  "type": "Feature",
  "properties": {
    "iso:country":"US",
    "sg:address":"4029 Robinhood Dr",
    "sg:city":"York",
    "sg:classifiers":[
        {
            "category":"Shopping",
            "subcategory":"Discount & Variety Stores",
            "type":"Retail Goods"
        }
    ],
    "sg:phone":"+1 717 792 0084",
    "sg:postcode":"17408",
    "sg:province":"PA",
    "sg:tags":[
        "merchandise",
        "general"
    ],
    "wof:name":"Princess House Inc",
    "wof:placetype":"venue"
},
  "geometry": {"coordinates":[-76.792497,39.909362],"type":"Point"}
}