{
  "type": "Feature",
  "properties": {
    "iso:country":"US",
    "sg:address":"515 W Linden St",
    "sg:city":"Allentown",
    "sg:classifiers":[
        {
            "category":"Professional",
            "subcategory":"Lawyer & Legal Services",
            "type":"Services"
        }
    ],
    "sg:phone":"+1   ",
    "sg:postcode":"18101",
    "sg:province":"PA",
    "wof:name":"Conrad Erik J",
    "wof:placetype":"venue"
},
  "geometry": {"coordinates":[-75.46910800000001,40.604664],"type":"Point"}
}