{
  "type": "Feature",
  "properties": {
    "iso:country":"US",
    "sg:address":"345 E 5th St",
    "sg:city":"Erie",
    "sg:classifiers":[
        {
            "category":"Government",
            "subcategory":"Office",
            "type":"Public Place"
        }
    ],
    "sg:phone":"+1   ",
    "sg:postcode":"16507",
    "sg:province":"PA",
    "sg:tags":[
        "national",
        "guard"
    ],
    "wof:name":"Organzational Maintenace Sp 5",
    "wof:placetype":"venue"
},
  "geometry": {"coordinates":[-80.077361,42.133535],"type":"Point"}
}