{
  "type": "Feature",
  "properties": {
    "iso:country":"US",
    "sg:address":"2 Taylor Blvd",
    "sg:city":"Harrisburg",
    "sg:classifiers":[
        {
            "category":"Autos & Motor Vehicles",
            "subcategory":"Automobile Sales",
            "type":"Retail Goods"
        }
    ],
    "sg:phone":"+1 717 591 1999",
    "sg:postcode":"17103",
    "sg:province":"PA",
    "sg:tags":[
        "car",
        "dealer"
    ],
    "wof:name":"Pay Point Auto Sales",
    "wof:placetype":"venue"
},
  "geometry": {"coordinates":[-76.85708700000001,40.270537],"type":"Point"}
}