{
  "type": "Feature",
  "properties": {
    "iso:country":"US",
    "sg:address":"2990 N 11th St",
    "sg:city":"Philadelphia",
    "sg:classifiers":[
        {
            "category":"Building & Trades",
            "subcategory":"Electrical",
            "type":"Services"
        }
    ],
    "sg:phone":"+1 215 225 2200",
    "sg:postcode":"19133",
    "sg:province":"PA",
    "sg:tags":[
        "electrician"
    ],
    "wof:name":"Maxicom",
    "wof:placetype":"venue"
},
  "geometry": {"coordinates":[-75.142899,39.9925],"type":"Point"}
}