{
  "type": "Feature",
  "properties": {
    "iso:country":"US",
    "sg:address":"921 N Bethlehem Pike",
    "sg:city":"Ambler",
    "sg:classifiers":[
        {
            "category":"Health Services",
            "subcategory":"Doctor",
            "type":"Services"
        }
    ],
    "sg:phone":"+1 215 646 4767",
    "sg:postcode":"19002",
    "sg:province":"PA",
    "sg:tags":[
        "dentist"
    ],
    "wof:name":"Gwynedd Dental Assoc",
    "wof:placetype":"venue"
},
  "geometry": {"coordinates":[-75.22760599999999,40.184297],"type":"Point"}
}