{
  "type": "Feature",
  "properties": {
    "addr:full":"7520 Morris Ct Allentown PA 18106",
    "addr:housenumber":"7520",
    "addr:postcode":"18106",
    "addr:street":"Morris Ct",
    "iso:country":"US",
    "sg:address":"7520 Morris Ct",
    "sg:city":"Allentown",
    "sg:classifiers":[
        {
            "category":"Wholesale",
            "subcategory":"Hardware",
            "type":"Manufacturing & Wholesale Goods"
        }
    ],
    "sg:phone":"+1 610 530 9832",
    "sg:postcode":"18106",
    "sg:province":"PA",
    "sg:tags":[
        "fastener"
    ],
    "sg:website":"www.ilsonline.com",
    "wof:name":"R B & W Logistics",
    "wof:placetype":"venue"
},
  "geometry": {"coordinates":[-75.609011,40.567467],"type":"Point"}
}