{
  "type": "Feature",
  "properties": {
    "iso:country":"US",
    "sg:address":"124 S Allen St",
    "sg:city":"State College",
    "sg:classifiers":[
        {
            "category":"Restaurant",
            "type":"Food & Drink"
        }
    ],
    "sg:phone":"+1   ",
    "sg:postcode":"16801",
    "sg:province":"PA",
    "sg:tags":[
        "eating"
    ],
    "wof:name":"Grahams Newsstand",
    "wof:placetype":"venue"
},
  "geometry": {"coordinates":[-77.860416,40.793419],"type":"Point"}
}