{
  "type": "Feature",
  "properties": {
    "addr:full":"300 Lycoming Mall Cir Muncy PA 17756",
    "addr:housenumber":"300",
    "addr:postcode":"17756",
    "addr:street":"Lycoming Mall Cir",
    "iso:country":"US",
    "sg:address":"300 Lycoming Mall Cir",
    "sg:city":"Muncy",
    "sg:classifiers":[
        {
            "category":"Shopping",
            "type":"Retail Goods"
        }
    ],
    "sg:phone":"+1 570 546 7741",
    "sg:postcode":"17756",
    "sg:province":"PA",
    "sg:tags":[
        "telephone",
        "cellular"
    ],
    "wof:name":"Precision Wireless Inc",
    "wof:placetype":"venue"
},
  "geometry": {"coordinates":[-76.824792,41.23798],"type":"Point"}
}