{
  "type": "Feature",
  "properties": {
    "iso:country":"US",
    "sg:address":"760 Constitution Dr",
    "sg:city":"Exton",
    "sg:classifiers":[
        {
            "category":"Insurance",
            "subcategory":"Insurance Agent",
            "type":"Services"
        }
    ],
    "sg:phone":"+1   ",
    "sg:postcode":"19341",
    "sg:province":"PA",
    "sg:tags":[
        "agency",
        "financial"
    ],
    "wof:name":"Massachusetts Mutual Lf Insur",
    "wof:placetype":"venue"
},
  "geometry": {"coordinates":[-75.677643,40.067057],"type":"Point"}
}