{
  "type": "Feature",
  "properties": {
    "addr:full":"140 E Richardson Ave Langhorne PA 19047",
    "addr:housenumber":"140",
    "addr:postcode":"19047",
    "addr:street":"E Richardson Ave Langhorne Pa",
    "iso:country":"US",
    "sg:address":"140 E Richardson Ave",
    "sg:city":"Langhorne",
    "sg:classifiers":[
        {
            "category":"Government",
            "subcategory":"Office",
            "type":"Public Place"
        }
    ],
    "sg:phone":"+1   ",
    "sg:postcode":"19047",
    "sg:province":"PA",
    "sg:tags":[
        "housing",
        "program"
    ],
    "wof:name":"Buck County Housing Group",
    "wof:placetype":"venue"
},
  "geometry": {"coordinates":[-74.91815200000001,40.175299],"type":"Point"}
}