{
  "type": "Feature",
  "properties": {
    "iso:country":"US",
    "sg:address":"110 Candleridge Ct",
    "sg:city":"Wexford",
    "sg:classifiers":[
        {
            "category":"Professional",
            "subcategory":"Accounting & Tax Preparation",
            "type":"Services"
        }
    ],
    "sg:phone":"+1 724 935 4864",
    "sg:postcode":"15090",
    "sg:province":"PA",
    "sg:tags":[
        "accountant"
    ],
    "wof:name":"Timothy F Henningson CPA",
    "wof:placetype":"venue"
},
  "geometry": {"coordinates":[-80.05476,40.60583],"type":"Point"}
}