{
  "type": "Feature",
  "properties": {
    "iso:country":"US",
    "sg:address":"1105 W Mountain Ave",
    "sg:city":"S Williamsport",
    "sg:classifiers":[
        {
            "category":"Retail",
            "subcategory":"Repair Shop",
            "type":"Services"
        }
    ],
    "sg:phone":"+1 570 326 3299",
    "sg:postcode":"17702",
    "sg:province":"PA",
    "sg:tags":[
        "door"
    ],
    "wof:name":"T E Klotz",
    "wof:placetype":"venue"
},
  "geometry": {"coordinates":[-77.005444,41.225152],"type":"Point"}
}