{
  "type": "Feature",
  "properties": {
    "iso:country":"US",
    "sg:address":"153 Penn Blvd",
    "sg:city":"Lansdowne",
    "sg:classifiers":[
        {
            "category":"Professional",
            "subcategory":"Lawyer & Legal Services",
            "type":"Services"
        }
    ],
    "sg:phone":"+1 610 259 2949",
    "sg:postcode":"19050",
    "sg:province":"PA",
    "sg:tags":[
        "attorney",
        "law",
        "immigration",
        "naturalization"
    ],
    "wof:name":"Irish Apostolate Usa",
    "wof:placetype":"venue"
},
  "geometry": {"coordinates":[-75.26074699999999,39.944453],"type":"Point"}
}