{
  "type": "Feature",
  "properties": {
    "iso:country":"US",
    "sg:address":"55 Browns Dam Rd",
    "sg:city":"New Oxford",
    "sg:classifiers":[
        {
            "category":"Real Estate",
            "subcategory":"Real Estate Operator",
            "type":"Services"
        }
    ],
    "sg:phone":"+1   ",
    "sg:postcode":"17350",
    "sg:province":"PA",
    "sg:tags":[
        "mobile",
        "home",
        "site"
    ],
    "wof:name":"Stockhams Village Inc",
    "wof:placetype":"venue"
},
  "geometry": {"coordinates":[-77.052758,39.91968],"type":"Point"}
}