{
  "type": "Feature",
  "properties": {
    "iso:country":"US",
    "sg:address":"1825 Rte 422 E",
    "sg:city":"Fenelton",
    "sg:classifiers":[
        {
            "category":"Autos & Motor Vehicles",
            "subcategory":"Fuel & Gas Station",
            "type":"Retail Goods"
        }
    ],
    "sg:phone":"+1 724 283 7825",
    "sg:postcode":"16034",
    "sg:province":"PA",
    "sg:tags":[
        "oil"
    ],
    "wof:name":"Gaiser's Truck Stop",
    "wof:placetype":"venue"
},
  "geometry": {"coordinates":[-79.700221,40.848403],"type":"Point"}
}