{
  "type": "Feature",
  "properties": {
    "iso:country":"US",
    "sg:address":"30 W Prospect Ave",
    "sg:city":"Pittsburgh",
    "sg:classifiers":[
        {
            "category":"Organizations",
            "subcategory":"Religious Organization",
            "type":"Services"
        }
    ],
    "sg:phone":"+1   ",
    "sg:postcode":"15205",
    "sg:province":"PA",
    "wof:name":"United Presbt Church In Ingram",
    "wof:placetype":"venue"
},
  "geometry": {"coordinates":[-80.06647100000001,40.445149],"type":"Point"}
}