{
  "type": "Feature",
  "properties": {
    "addr:full":"17 Krocks Rd Allentown PA 18104",
    "addr:housenumber":"17",
    "addr:postcode":"18104",
    "addr:street":"Krocks Rd",
    "iso:country":"US",
    "sg:address":"17 Krocks Rd",
    "sg:city":"Allentown",
    "sg:classifiers":[
        {
            "category":"Manufacturing",
            "subcategory":"Tools & Machinery",
            "type":"Manufacturing & Wholesale Goods"
        }
    ],
    "sg:phone":"+1   ",
    "sg:postcode":"18104",
    "sg:province":"PA",
    "sg:tags":[
        "packaging",
        "mfg"
    ],
    "wof:name":"Trine Manufacturing Co Inc",
    "wof:placetype":"venue"
},
  "geometry": {"coordinates":[-75.57258400000001,40.579074],"type":"Point"}
}