{
  "type": "Feature",
  "properties": {
    "addr:full":"652 Woodspring Dr Warrington PA 18976",
    "addr:housenumber":"652",
    "addr:postcode":"18976",
    "addr:street":"Woodspring Dr",
    "iso:country":"US",
    "sg:address":"652 Woodspring Dr",
    "sg:city":"Warrington",
    "sg:classifiers":[
        {
            "category":"Professional",
            "subcategory":"Research",
            "type":"Services"
        }
    ],
    "sg:phone":"+1 215 491 0543",
    "sg:postcode":"18976",
    "sg:province":"PA",
    "sg:tags":[
        "environmental",
        "ecological"
    ],
    "sg:website":"www.marineenvironmentalmgmt.com",
    "wof:name":"Marine Environmental Mgmt",
    "wof:placetype":"venue"
},
  "geometry": {"coordinates":[-75.157337,40.243521],"type":"Point"}
}