{
  "type": "Feature",
  "properties": {
    "iso:country":"US",
    "sg:address":"931 Harrisburg Ave",
    "sg:city":"Lancaster",
    "sg:classifiers":[
        {
            "category":"Restaurant",
            "type":"Food & Drink"
        }
    ],
    "sg:phone":"+1   ",
    "sg:postcode":"17603",
    "sg:province":"PA",
    "sg:tags":[
        "operator"
    ],
    "wof:name":"Doc Hollidays / Lancaster",
    "wof:placetype":"venue"
},
  "geometry": {"coordinates":[-76.31771999999999,40.049884],"type":"Point"}
}