{
  "type": "Feature",
  "properties": {
    "addr:full":"32 Hummer Rd Ephrata PA 17522",
    "addr:housenumber":"32",
    "addr:postcode":"17522",
    "addr:street":"Hummer Rd",
    "iso:country":"US",
    "sg:address":"32 Hummer Rd",
    "sg:city":"Ephrata",
    "sg:classifiers":[
        {
            "category":"Health Services",
            "subcategory":"Optometrist",
            "type":"Services"
        }
    ],
    "sg:phone":"+1 717 733 0148",
    "sg:postcode":"17522",
    "sg:province":"PA",
    "wof:name":"Dennis A Reddig Od",
    "wof:placetype":"venue"
},
  "geometry": {"coordinates":[-76.199117,40.193753],"type":"Point"}
}