{
  "type": "Feature",
  "properties": {
    "iso:country":"US",
    "sg:address":"1003 Macdade Blvd",
    "sg:city":"Collingdale",
    "sg:classifiers":[
        {
            "category":"Restaurant",
            "type":"Food & Drink"
        }
    ],
    "sg:phone":"+1 610 237 0767",
    "sg:postcode":"19023",
    "sg:province":"PA",
    "sg:tags":[
        "deli",
        "delicatessen"
    ],
    "wof:name":"Collingdale Deli",
    "wof:placetype":"venue"
},
  "geometry": {"coordinates":[-75.28142099999999,39.910002],"type":"Point"}
}