{
  "type": "Feature",
  "properties": {
    "addr:full":"2401 Reach Rd Williamsport PA 17701",
    "addr:housenumber":"2401",
    "addr:postcode":"17701",
    "addr:street":"Reach Rd",
    "iso:country":"US",
    "sg:address":"2401 Reach Rd",
    "sg:city":"Williamsport",
    "sg:classifiers":[
        {
            "category":"Retail",
            "subcategory":"Repair Shop",
            "type":"Services"
        }
    ],
    "sg:phone":"+1 570 322 1578",
    "sg:postcode":"17701",
    "sg:province":"PA",
    "sg:tags":[
        "related"
    ],
    "wof:name":"Jakyl",
    "wof:placetype":"venue"
},
  "geometry": {"coordinates":[-77.058183,41.227016],"type":"Point"}
}