{
  "type": "Feature",
  "properties": {
    "iso:country":"US",
    "sg:address":"1200 Brooks Ln Ste 130",
    "sg:city":"Clairton",
    "sg:classifiers":[
        {
            "category":"Health Services",
            "subcategory":"Hospital",
            "type":"Services"
        }
    ],
    "sg:phone":"+1 412 469 5000",
    "sg:postcode":"15025",
    "sg:province":"PA",
    "wof:name":"McCormick Medical Associates",
    "wof:placetype":"venue"
},
  "geometry": {"coordinates":[-79.938797,40.315201],"type":"Point"}
}