{
  "type": "Feature",
  "properties": {
    "addr:full":"1035 Market St Warren PA 16365",
    "addr:housenumber":"1035",
    "addr:postcode":"16365",
    "addr:street":"Market St",
    "iso:country":"US",
    "sg:address":"1035 Market St",
    "sg:city":"Warren",
    "sg:classifiers":[
        {
            "category":"Wholesale",
            "subcategory":"Auto Parts",
            "type":"Manufacturing & Wholesale Goods"
        }
    ],
    "sg:phone":"+1   ",
    "sg:postcode":"16365",
    "sg:province":"PA",
    "wof:name":"Car-Go Auto Parts",
    "wof:placetype":"venue"
},
  "geometry": {"coordinates":[-79.15478400000001,41.864433],"type":"Point"}
}