{
  "type": "Feature",
  "properties": {
    "iso:country":"US",
    "sg:address":"700 Stony Hill Rd",
    "sg:city":"Morrisville",
    "sg:classifiers":[
        {
            "category":"Food & Beverages",
            "subcategory":"Groceries & Convenience Stores",
            "type":"Retail Goods"
        }
    ],
    "sg:phone":"+1   ",
    "sg:postcode":"19067",
    "sg:province":"PA",
    "sg:tags":[
        "product",
        "mfg"
    ],
    "wof:name":"Giant Food 62",
    "wof:placetype":"venue"
},
  "geometry": {"coordinates":[-74.86165099999999,40.216556],"type":"Point"}
}