{
  "type": "Feature",
  "properties": {
    "iso:country":"US",
    "sg:address":"120 Industrial Dr",
    "sg:city":"Warminster",
    "sg:classifiers":[
        {
            "category":"Wholesale",
            "subcategory":"Non-durable Goods",
            "type":"Manufacturing & Wholesale Goods"
        }
    ],
    "sg:phone":"+1 215 942 8870",
    "sg:postcode":"18974",
    "sg:province":"PA",
    "sg:tags":[
        "gift"
    ],
    "wof:name":"C & W Imports Inc",
    "wof:placetype":"venue"
},
  "geometry": {"coordinates":[-75.06017199999999,40.226303],"type":"Point"}
}