{
  "type": "Feature",
  "properties": {
    "iso:country":"US",
    "sg:address":"199 Fairview Rd",
    "sg:city":"Shippensburg",
    "sg:classifiers":[
        {
            "category":"Building & Trades",
            "subcategory":"Construction",
            "type":"Services"
        }
    ],
    "sg:phone":"+1 717 729 2141",
    "sg:postcode":"17257",
    "sg:province":"PA",
    "sg:tags":[
        "contractor",
        "fence-sales"
    ],
    "wof:name":"Leid Fence",
    "wof:placetype":"venue"
},
  "geometry": {"coordinates":[-77.498413,40.123323],"type":"Point"}
}