{
  "type": "Feature",
  "properties": {
    "addr:full":"19 Warren St Bethlehem PA 18015",
    "addr:housenumber":"19",
    "addr:postcode":"18015",
    "addr:street":"Warren St",
    "iso:country":"US",
    "sg:address":"19 Warren St",
    "sg:city":"Bethlehem",
    "sg:classifiers":[
        {
            "category":"Insurance",
            "subcategory":"Insurance Agent",
            "type":"Services"
        }
    ],
    "sg:phone":"+1   ",
    "sg:postcode":"18015",
    "sg:province":"PA",
    "wof:name":"Nation Wide Insurance",
    "wof:placetype":"venue"
},
  "geometry": {"coordinates":[-75.395945,40.598368],"type":"Point"}
}