{
  "type": "Feature",
  "properties": {
    "iso:country":"US",
    "sg:address":"30 Spring Meadow Ln",
    "sg:city":"Reading",
    "sg:classifiers":[
        {
            "category":"Professional",
            "subcategory":"Computer Services",
            "type":"Services"
        }
    ],
    "sg:phone":"+1   ",
    "sg:postcode":"19606",
    "sg:province":"PA",
    "sg:tags":[
        "programing",
        "custom"
    ],
    "wof:name":"Jayde Design & Technology",
    "wof:placetype":"venue"
},
  "geometry": {"coordinates":[-75.819042,40.321148],"type":"Point"}
}