{
  "type": "Feature",
  "properties": {
    "addr:full":"4141 Lancaster Ave Philadelphia PA 19104",
    "addr:housenumber":"4141",
    "addr:postcode":"19104",
    "addr:street":"Lancaster Ave",
    "iso:country":"US",
    "sg:address":"4141 Lancaster Ave",
    "sg:city":"Philadelphia",
    "sg:classifiers":[
        {
            "category":"Retail",
            "subcategory":"Laundry & Dry Cleaning",
            "type":"Services"
        }
    ],
    "sg:phone":"+1 215 382 1999",
    "sg:postcode":"19104",
    "sg:province":"PA",
    "wof:name":"Cleaners 99",
    "wof:placetype":"venue"
},
  "geometry": {"coordinates":[-75.20700100000001,39.9659],"type":"Point"}
}