{
  "type": "Feature",
  "properties": {
    "iso:country":"US",
    "sg:address":"4519 Hanoverville Rd",
    "sg:city":"Bethlehem",
    "sg:classifiers":[
        {
            "category":"Local Transit",
            "type":"Transportation"
        }
    ],
    "sg:phone":"+1 610 759 2594",
    "sg:postcode":"18020",
    "sg:province":"PA",
    "sg:tags":[
        "ambulance"
    ],
    "wof:name":"Hecktown Volunteer Ambulance",
    "wof:placetype":"venue"
},
  "geometry": {"coordinates":[-75.341536,40.691293],"type":"Point"}
}