{
  "type": "Feature",
  "properties": {
    "iso:country":"US",
    "sg:address":"1074 Old State Rd",
    "sg:city":"Waterford",
    "sg:classifiers":[
        {
            "category":"Retail",
            "subcategory":"Auto Repair",
            "type":"Services"
        }
    ],
    "sg:phone":"+1 814 796 4857",
    "sg:postcode":"16441",
    "sg:province":"PA",
    "sg:tags":[
        "body",
        "automobile",
        "painting",
        "repairing"
    ],
    "wof:name":"Miller, Kenneth",
    "wof:placetype":"venue"
},
  "geometry": {"coordinates":[-80.010001,41.930993],"type":"Point"}
}