{
  "type": "Feature",
  "properties": {
    "iso:country":"US",
    "sg:address":"106 Simpson Howell Rd",
    "sg:city":"Elizabeth",
    "sg:classifiers":[
        {
            "category":"Professional",
            "subcategory":"Management & Consulting",
            "type":"Services"
        }
    ],
    "sg:phone":"+1   ",
    "sg:postcode":"15037",
    "sg:province":"PA",
    "sg:tags":[
        "retail",
        "direct",
        "sales"
    ],
    "wof:name":"Art Swartz Gaming",
    "wof:placetype":"venue"
},
  "geometry": {"coordinates":[-79.836865,40.271776],"type":"Point"}
}