{
  "type": "Feature",
  "properties": {
    "addr:full":"233 Summit Ave Fort Washington PA 19034",
    "addr:housenumber":"233",
    "addr:postcode":"19034",
    "addr:street":"Summit Ave",
    "iso:country":"US",
    "sg:address":"233 Summit Ave",
    "sg:city":"Fort Washington",
    "sg:classifiers":[
        {
            "category":"Building & Trades",
            "subcategory":"Construction",
            "type":"Services"
        }
    ],
    "sg:phone":"+1 215 646 4340",
    "sg:postcode":"19034",
    "sg:province":"PA",
    "sg:tags":[
        "general",
        "contractor"
    ],
    "wof:name":"Edifice Rex Construction Corp",
    "wof:placetype":"venue"
},
  "geometry": {"coordinates":[-75.207202,40.139695],"type":"Point"}
}