{
  "type": "Feature",
  "properties": {
    "iso:country":"US",
    "sg:address":"2828 US Hwy 30",
    "sg:city":"Georgetown",
    "sg:classifiers":[
        {
            "category":"Autos & Motor Vehicles",
            "subcategory":"Automobile Sales",
            "type":"Retail Goods"
        }
    ],
    "sg:phone":"+1 724 573 1345",
    "sg:postcode":"15043",
    "sg:province":"PA",
    "sg:tags":[
        "used"
    ],
    "wof:name":"Schmidt Auto Sales",
    "wof:placetype":"venue"
},
  "geometry": {"coordinates":[-80.491392,40.582756],"type":"Point"}
}