{
  "type": "Feature",
  "properties": {
    "iso:country":"US",
    "sg:address":"2431 7th Ave",
    "sg:city":"Beaver Falls",
    "sg:classifiers":[
        {
            "category":"Personal",
            "subcategory":"Beauty Salon",
            "type":"Services"
        }
    ],
    "sg:phone":"+1 724 846 1611",
    "sg:postcode":"15010",
    "sg:province":"PA",
    "wof:name":"Lucille Nesmith Beauty Salon",
    "wof:placetype":"venue"
},
  "geometry": {"coordinates":[-80.319277,40.764728],"type":"Point"}
}