{
  "type": "Feature",
  "properties": {
    "iso:country":"US",
    "sg:address":"950 Walnut Bottom Rd",
    "sg:city":"Carlisle",
    "sg:classifiers":[
        {
            "category":"Professional",
            "subcategory":"Printing & Photocopies",
            "type":"Services"
        }
    ],
    "sg:phone":"+1 717 241 5554",
    "sg:postcode":"17013",
    "sg:province":"PA",
    "wof:name":"The Ups Store",
    "wof:placetype":"venue"
},
  "geometry": {"coordinates":[-77.213799,40.183601],"type":"Point"}
}