{
  "type": "Feature",
  "properties": {
    "iso:country":"US",
    "sg:address":"630 Kirtland St",
    "sg:city":"Pittsburgh",
    "sg:classifiers":[
        {
            "category":"Retail",
            "subcategory":"Repair Shop",
            "type":"Services"
        }
    ],
    "sg:phone":"+1   ",
    "sg:postcode":"15208",
    "sg:province":"PA",
    "wof:name":"Huber Cartage and Machine",
    "wof:placetype":"venue"
},
  "geometry": {"coordinates":[-79.908044,40.444899],"type":"Point"}
}