{
  "type": "Feature",
  "properties": {
    "iso:country":"US",
    "sg:address":"704 Main St",
    "sg:city":"Rockwood",
    "sg:classifiers":[
        {
            "category":"Home & Garden",
            "subcategory":"Furniture",
            "type":"Retail Goods"
        }
    ],
    "sg:phone":"+1 814 926 2422",
    "sg:postcode":"15557",
    "sg:province":"PA",
    "wof:name":"Stoner Furniture",
    "wof:placetype":"venue"
},
  "geometry": {"coordinates":[-79.151447,39.916898],"type":"Point"}
}