{
  "type": "Feature",
  "properties": {
    "addr:full":"7967 Oak Hill Dr Cheltenham PA 19012",
    "addr:housenumber":"7967",
    "addr:postcode":"19012",
    "addr:street":"Oak Hill Dr",
    "iso:country":"US",
    "sg:address":"7967 Oak Hill Dr",
    "sg:city":"Cheltenham",
    "sg:classifiers":[
        {
            "category":"Retail",
            "subcategory":"Auto Rental",
            "type":"Services"
        }
    ],
    "sg:phone":"+1 215 663 2350",
    "sg:postcode":"19012",
    "sg:province":"PA",
    "sg:tags":[
        "automobile",
        "leasing"
    ],
    "wof:name":"Montgomery Equipment Leasing",
    "wof:placetype":"venue"
},
  "geometry": {"coordinates":[-75.099898,40.063017],"type":"Point"}
}