{
  "type": "Feature",
  "properties": {
    "iso:country":"US",
    "sg:address":"227 Franklin St",
    "sg:city":"Johnstown",
    "sg:classifiers":[
        {
            "category":"Professional",
            "subcategory":"Lawyer & Legal Services",
            "type":"Services"
        }
    ],
    "sg:phone":"+1   ",
    "sg:postcode":"15901",
    "sg:province":"PA",
    "wof:name":"Laurel Legal Services",
    "wof:placetype":"venue"
},
  "geometry": {"coordinates":[-78.91844399999999,40.324528],"type":"Point"}
}