{
  "type": "Feature",
  "properties": {
    "iso:country":"US",
    "sg:address":"305 S Keystone Ave",
    "sg:city":"Sayre",
    "sg:classifiers":[
        {
            "category":"Retail",
            "subcategory":"Car Wash",
            "type":"Services"
        }
    ],
    "sg:phone":"+1 570 888 6431",
    "sg:postcode":"18840",
    "sg:province":"PA",
    "wof:name":"Sayre Car Wash",
    "wof:placetype":"venue"
},
  "geometry": {"coordinates":[-76.52526,41.978127],"type":"Point"}
}