{
  "type": "Feature",
  "properties": {
    "iso:country":"US",
    "sg:address":"7515 Shaw St",
    "sg:city":"Philadelphia",
    "sg:classifiers":[
        {
            "category":"Building & Trades",
            "subcategory":"Construction",
            "type":"Services"
        }
    ],
    "sg:phone":"+1   ",
    "sg:postcode":"19128",
    "sg:province":"PA",
    "sg:tags":[
        "residential"
    ],
    "wof:name":"Matteo Nick Inc General C",
    "wof:placetype":"venue"
},
  "geometry": {"coordinates":[-75.244826,40.045888],"type":"Point"}
}