{
  "type": "Feature",
  "properties": {
    "iso:country":"US",
    "sg:address":"1132 N Chester Rd",
    "sg:city":"West Chester",
    "sg:classifiers":[
        {
            "category":"Building & Trades",
            "subcategory":"Plumbing",
            "type":"Services"
        }
    ],
    "sg:phone":"+1 610 430 0606",
    "sg:postcode":"19380",
    "sg:province":"PA",
    "sg:tags":[
        "conditioning",
        "air",
        "system",
        "contractor"
    ],
    "wof:name":"Ervin Moser Svc",
    "wof:placetype":"venue"
},
  "geometry": {"coordinates":[-75.547872,40.011342],"type":"Point"}
}