{
  "type": "Feature",
  "properties": {
    "iso:country":"US",
    "sg:address":"2025 Fairmount Ave",
    "sg:city":"Philadelphia",
    "sg:classifiers":[
        {
            "category":"Restaurant",
            "type":"Food & Drink"
        }
    ],
    "sg:phone":"+1 215 769 0316",
    "sg:postcode":"19130",
    "sg:province":"PA",
    "sg:tags":[
        "italian"
    ],
    "sg:website":"www.locabistro.com",
    "wof:name":"L'Oca Italian Bistro",
    "wof:placetype":"venue"
},
  "geometry": {"coordinates":[-75.171166,39.967476],"type":"Point"}
}