{
  "type": "Feature",
  "properties": {
    "addr:full":"816 N New St Bethlehem PA 18018",
    "addr:housenumber":"816",
    "addr:postcode":"18018",
    "addr:street":"N New St",
    "iso:country":"US",
    "sg:address":"816 N New St",
    "sg:city":"Bethlehem",
    "sg:classifiers":[
        {
            "category":"Health Services",
            "subcategory":"Health Practitioner",
            "type":"Services"
        }
    ],
    "sg:phone":"+1 610 997 5626",
    "sg:postcode":"18018",
    "sg:province":"PA",
    "sg:tags":[
        "acupuncture"
    ],
    "wof:name":"Alternative Care Acupuncture",
    "wof:placetype":"venue"
},
  "geometry": {"coordinates":[-75.37824000000001,40.625109],"type":"Point"}
}