{
  "type": "Feature",
  "properties": {
    "iso:country":"US",
    "sg:address":"109 Hulda Rd",
    "sg:city":"Westfield",
    "sg:classifiers":[
        {
            "category":"Manufacturing",
            "subcategory":"Pet Food",
            "type":"Manufacturing & Wholesale Goods"
        },
        {
            "category":"Farming",
            "subcategory":"Farm",
            "type":"Manufacturing & Wholesale Goods"
        }
    ],
    "sg:phone":"+1 814 367 5721",
    "sg:postcode":"16950",
    "sg:province":"PA",
    "sg:tags":[
        "hay"
    ],
    "wof:name":"Linford Parker",
    "wof:placetype":"venue"
},
  "geometry": {"coordinates":[-77.597016,41.973892],"type":"Point"}
}