{
  "type": "Feature",
  "properties": {
    "iso:country":"US",
    "sg:address":"N Main",
    "sg:city":"Doylestown",
    "sg:classifiers":[
        {
            "category":"Real Estate",
            "subcategory":"Real Estate Operator",
            "type":"Services"
        }
    ],
    "sg:phone":"+1 215 348 8371",
    "sg:postcode":"18901",
    "sg:province":"PA",
    "sg:tags":[
        "apartment"
    ],
    "wof:name":"Font Hill Apts",
    "wof:placetype":"venue"
},
  "geometry": {"coordinates":[-75.129501,40.321301],"type":"Point"}
}