{
  "type": "Feature",
  "properties": {
    "iso:country":"US",
    "sg:address":"7920 Perry Hwy",
    "sg:city":"Pittsburgh",
    "sg:classifiers":[
        {
            "category":"Food & Beverages",
            "subcategory":"Liquor & Beverages",
            "type":"Retail Goods"
        }
    ],
    "sg:phone":"+1   ",
    "sg:postcode":"15237",
    "sg:province":"PA",
    "sg:tags":[
        "regulation",
        "commercial",
        "sect",
        "alcoholic"
    ],
    "wof:name":"Wine & Spirits Shoppe 0289",
    "wof:placetype":"venue"
},
  "geometry": {"coordinates":[-80.037685,40.552261],"type":"Point"}
}