{
  "type": "Feature",
  "properties": {
    "iso:country":"US",
    "sg:address":"641 Allendale Rd",
    "sg:city":"King Of Prussia",
    "sg:classifiers":[
        {
            "category":"Wholesale",
            "subcategory":"Construction Materials",
            "type":"Manufacturing & Wholesale Goods"
        }
    ],
    "sg:phone":"+1 610 337 5999",
    "sg:postcode":"19406",
    "sg:province":"PA",
    "sg:tags":[
        "insulation",
        "roofing",
        "siding"
    ],
    "wof:name":"General Insulation Co Inc",
    "wof:placetype":"venue"
},
  "geometry": {"coordinates":[-75.39671,40.10014],"type":"Point"}
}