{
  "type": "Feature",
  "properties": {
    "addr:full":"2600 Lewisville Rd Lewisville PA 19363",
    "addr:housenumber":"2600",
    "addr:postcode":"19363",
    "addr:street":"Lewisville Rd",
    "iso:country":"US",
    "sg:address":"2600 Lewisville Rd",
    "sg:city":"Lewisville",
    "sg:classifiers":[
        {
            "category":"Shopping",
            "type":"Retail Goods"
        }
    ],
    "sg:phone":"+1 610 932 8267",
    "sg:postcode":"19363",
    "sg:province":"PA",
    "sg:tags":[
        "feed"
    ],
    "wof:name":"Crown Stone Feed Store Inc",
    "wof:placetype":"venue"
},
  "geometry": {"coordinates":[-75.882502,39.724466],"type":"Point"}
}