{
  "type": "Feature",
  "properties": {
    "iso:country":"US",
    "sg:address":"412 Susquehanna Ave",
    "sg:city":"Curwensville",
    "sg:classifiers":[
        {
            "category":"Autos & Motor Vehicles",
            "subcategory":"Automobile Sales",
            "type":"Retail Goods"
        }
    ],
    "sg:phone":"+1 814 236 0241",
    "sg:postcode":"16833",
    "sg:province":"PA",
    "sg:tags":[
        "car",
        "used",
        "dealer"
    ],
    "wof:name":"Bumbarger's Used Cars",
    "wof:placetype":"venue"
},
  "geometry": {"coordinates":[-78.52420600000001,40.968307],"type":"Point"}
}