{
  "type": "Feature",
  "properties": {
    "iso:country":"US",
    "sg:address":"102 College Park Plz",
    "sg:city":"Johnstown",
    "sg:classifiers":[
        {
            "category":"Professional",
            "subcategory":"Printing & Photocopies",
            "type":"Services"
        }
    ],
    "sg:phone":"+1 814 269 3088",
    "sg:postcode":"15904",
    "sg:province":"PA",
    "sg:tags":[
        "photocopying",
        "lithographic",
        "commercial"
    ],
    "wof:name":"Richland Print Shop",
    "wof:placetype":"venue"
},
  "geometry": {"coordinates":[-78.84789600000001,40.278715],"type":"Point"}
}