{
  "type": "Feature",
  "properties": {
    "iso:country":"US",
    "sg:address":"306 Main St",
    "sg:city":"Irwin",
    "sg:classifiers":[
        {
            "category":"Shopping",
            "type":"Retail Goods"
        }
    ],
    "sg:phone":"+1 724 861 6646",
    "sg:postcode":"15642",
    "sg:province":"PA",
    "sg:tags":[
        "supply",
        "hearing",
        "equipment",
        "health",
        "impaired",
        "merchandise"
    ],
    "wof:name":"Doerfler L Audiology Associate",
    "wof:placetype":"venue"
},
  "geometry": {"coordinates":[-79.71079899999999,40.332528],"type":"Point"}
}