{
  "type": "Feature",
  "properties": {
    "iso:country":"US",
    "sg:address":"816 Chestnut Ave",
    "sg:city":"Altoona",
    "sg:classifiers":[
        {
            "category":"Shopping",
            "subcategory":"Florist",
            "type":"Retail Goods"
        }
    ],
    "sg:phone":"+1 814 944 8161",
    "sg:postcode":"16601",
    "sg:province":"PA",
    "wof:name":"Myers Brothers Florist",
    "wof:placetype":"venue"
},
  "geometry": {"coordinates":[-78.398545,40.518692],"type":"Point"}
}