{
  "type": "Feature",
  "properties": {
    "iso:country":"US",
    "sg:address":"300 Pine Blvd",
    "sg:city":"Orwigsburg",
    "sg:classifiers":[
        {
            "category":"Banks & Credit Unions",
            "subcategory":"Bank",
            "type":"Services"
        }
    ],
    "sg:phone":"+1 570 366 7790",
    "sg:postcode":"17961",
    "sg:province":"PA",
    "wof:name":"Union Bank & Trust Co",
    "wof:placetype":"venue"
},
  "geometry": {"coordinates":[-76.053595,40.626069],"type":"Point"}
}