{
  "type": "Feature",
  "properties": {
    "iso:country":"US",
    "sg:address":"414 6th St",
    "sg:city":"Franklin",
    "sg:classifiers":[
        {
            "category":"Building & Trades",
            "subcategory":"Construction",
            "type":"Services"
        }
    ],
    "sg:phone":"+1   ",
    "sg:postcode":"16323",
    "sg:province":"PA",
    "sg:tags":[
        "hanging",
        "contractor"
    ],
    "wof:name":"Ds Painting Drywall",
    "wof:placetype":"venue"
},
  "geometry": {"coordinates":[-79.823071,41.385621],"type":"Point"}
}