{
  "type": "Feature",
  "properties": {
    "addr:full":"236 S 48th St Philadelphia PA 19139",
    "addr:housenumber":"236",
    "addr:postcode":"19139",
    "addr:street":"S 48Th St",
    "iso:country":"US",
    "sg:address":"236 S 48th St",
    "sg:city":"Philadelphia",
    "sg:classifiers":[
        {
            "category":"Organizations",
            "subcategory":"Religious Organization",
            "type":"Services"
        }
    ],
    "sg:phone":"+1 215 474 4644",
    "sg:postcode":"19139",
    "sg:province":"PA",
    "sg:tags":[
        "clergy"
    ],
    "wof:name":"Pallathu O Mathew",
    "wof:placetype":"venue"
},
  "geometry": {"coordinates":[-75.21775100000001,39.955923],"type":"Point"}
}