{
  "type": "Feature",
  "properties": {
    "iso:country":"US",
    "sg:address":"724 S Chester Rd",
    "sg:city":"Swarthmore",
    "sg:classifiers":[
        {
            "category":"Retail",
            "subcategory":"Auto Repair",
            "type":"Services"
        }
    ],
    "sg:phone":"+1   ",
    "sg:postcode":"19081",
    "sg:province":"PA",
    "sg:tags":[
        "tire",
        "general"
    ],
    "wof:name":"Clarks Tire & Auto Svc Ctr",
    "wof:placetype":"venue"
},
  "geometry": {"coordinates":[-75.355152,39.888441],"type":"Point"}
}