{
  "type": "Feature",
  "properties": {
    "iso:country":"US",
    "sg:address":"306 Pine Ave",
    "sg:city":"Stroudsburg",
    "sg:classifiers":[
        {
            "category":"Travel",
            "subcategory":"Travel Agent",
            "type":"Entertainment"
        }
    ],
    "sg:phone":"+1   ",
    "sg:postcode":"18360",
    "sg:province":"PA",
    "sg:tags":[
        "operator",
        "tour"
    ],
    "wof:name":"Joe T Hrton Csino Rprsentative",
    "wof:placetype":"venue"
},
  "geometry": {"coordinates":[-75.19543400000001,41.004915],"type":"Point"}
}