{
  "type": "Feature",
  "properties": {
    "addr:full":"4525 Spring Hill Dr Schnecksville PA 18078",
    "addr:housenumber":"4525",
    "addr:postcode":"18078",
    "addr:street":"Spring Hill Dr",
    "iso:country":"US",
    "sg:address":"4525 Spring Hill Dr",
    "sg:city":"Schnecksville",
    "sg:classifiers":[
        {
            "category":"Health Services",
            "subcategory":"Doctor",
            "type":"Services"
        }
    ],
    "sg:phone":"+1   ",
    "sg:postcode":"18078",
    "sg:province":"PA",
    "wof:name":"David D Snyder",
    "wof:placetype":"venue"
},
  "geometry": {"coordinates":[-75.60207200000001,40.667664],"type":"Point"}
}