{
  "type": "Feature",
  "properties": {
    "iso:country":"US",
    "sg:address":"1414 Surrey Ln",
    "sg:city":"Wynnewood",
    "sg:classifiers":[
        {
            "category":"Shopping",
            "type":"Retail Goods"
        }
    ],
    "sg:phone":"+1   ",
    "sg:postcode":"19096",
    "sg:province":"PA",
    "sg:tags":[
        "merchandise"
    ],
    "wof:name":"Wayden Zev",
    "wof:placetype":"venue"
},
  "geometry": {"coordinates":[-75.271531,39.98076],"type":"Point"}
}