{
  "type": "Feature",
  "properties": {
    "addr:full":"3800 Garrett Rd Drexel Hill PA 19026",
    "addr:housenumber":"3800",
    "addr:postcode":"19026",
    "addr:street":"Garrett Rd",
    "iso:country":"US",
    "sg:address":"3800 Garrett Rd",
    "sg:city":"Drexel Hill",
    "sg:classifiers":[
        {
            "category":"Food & Beverages",
            "subcategory":"Groceries & Convenience Stores",
            "type":"Retail Goods"
        }
    ],
    "sg:phone":"+1 610 626 9647",
    "sg:postcode":"19026",
    "sg:province":"PA",
    "sg:website":"www.wawa.com",
    "wof:name":"Wawa Food Market",
    "wof:placetype":"venue"
},
  "geometry": {"coordinates":[-75.29940499999999,39.943267],"type":"Point"}
}