{
  "type": "Feature",
  "properties": {
    "iso:country":"US",
    "sg:address":"RR 191",
    "sg:city":"Bethlehem",
    "sg:classifiers":[
        {
            "category":"Arts & Performance",
            "subcategory":"Art Gallery",
            "type":"Entertainment"
        },
        {
            "category":"Education",
            "subcategory":"Special Training",
            "type":"Public Place"
        }
    ],
    "sg:phone":"+1 610 759 9121",
    "sg:postcode":"18015",
    "sg:province":"PA",
    "sg:tags":[
        "school"
    ],
    "wof:name":"Dominick's Art World",
    "wof:placetype":"venue"
},
  "geometry": {"coordinates":[-75.38069900000001,40.595501],"type":"Point"}
}