{
  "type": "Feature",
  "properties": {
    "iso:country":"US",
    "sg:address":"202 Orlan Rd",
    "sg:city":"New Holland",
    "sg:classifiers":[
        {
            "category":"Real Estate",
            "subcategory":"Real Estate Operator",
            "type":"Services"
        }
    ],
    "sg:phone":"+1   ",
    "sg:postcode":"17557",
    "sg:province":"PA",
    "sg:tags":[
        "building",
        "nonresidential"
    ],
    "wof:name":"Schopf Templeton Pfautz RE",
    "wof:placetype":"venue"
},
  "geometry": {"coordinates":[-76.09765400000001,40.090159],"type":"Point"}
}