{
  "type": "Feature",
  "properties": {
    "iso:country":"US",
    "sg:address":"2425 Blair Mill Rd",
    "sg:city":"Willow Grove",
    "sg:classifiers":[
        {
            "category":"Shopping",
            "subcategory":"Computers & Home Electronics",
            "type":"Retail Goods"
        }
    ],
    "sg:phone":"+1 215 361 3783",
    "sg:postcode":"19090",
    "sg:province":"PA",
    "sg:tags":[
        "equipment",
        "dealer"
    ],
    "sg:website":"www.d2computers.com",
    "wof:name":"DII Computers Inc",
    "wof:placetype":"venue"
},
  "geometry": {"coordinates":[-75.14167399999999,40.158212],"type":"Point"}
}