{
  "type": "Feature",
  "properties": {
    "iso:country":"US",
    "sg:address":"2039 Mountain Rd",
    "sg:city":"Manheim",
    "sg:classifiers":[
        {
            "category":"Building & Trades",
            "subcategory":"Construction",
            "type":"Services"
        }
    ],
    "sg:phone":"+1 717 665 2991",
    "sg:postcode":"17545",
    "sg:province":"PA",
    "sg:tags":[
        "tile",
        "dealer"
    ],
    "wof:name":"Roman Mosaic & Tile Co Inc",
    "wof:placetype":"venue"
},
  "geometry": {"coordinates":[-76.410792,40.21746],"type":"Point"}
}