{
  "type": "Feature",
  "properties": {
    "iso:country":"US",
    "sg:address":"12 Orchard Rd",
    "sg:city":"Barnesville",
    "sg:classifiers":[
        {
            "category":"Farming",
            "subcategory":"Orchard",
            "type":"Manufacturing & Wholesale Goods"
        }
    ],
    "sg:phone":"+1   ",
    "sg:postcode":"18214",
    "sg:province":"PA",
    "sg:tags":[
        "fruit",
        "tree"
    ],
    "wof:name":"Charles Dewire",
    "wof:placetype":"venue"
},
  "geometry": {"coordinates":[-76.06205199999999,40.804352],"type":"Point"}
}