{
  "type": "Feature",
  "properties": {
    "iso:country":"US",
    "sg:address":"13123 Mongul Rd",
    "sg:city":"Newburg",
    "sg:classifiers":[
        {
            "category":"Farming",
            "subcategory":"Dairy Farm",
            "type":"Manufacturing & Wholesale Goods"
        }
    ],
    "sg:phone":"+1   ",
    "sg:postcode":"17240",
    "sg:province":"PA",
    "wof:name":"Jobriden Farms",
    "wof:placetype":"venue"
},
  "geometry": {"coordinates":[-77.60335499999999,40.090576],"type":"Point"}
}