{
  "type": "Feature",
  "properties": {
    "iso:country":"US",
    "sg:address":"1108 N Chester Rd",
    "sg:city":"West Chester",
    "sg:classifiers":[
        {
            "category":"Manufacturing",
            "subcategory":"Glass & Minerals",
            "type":"Manufacturing & Wholesale Goods"
        },
        {
            "category":"Retail",
            "subcategory":"Repair Shop",
            "type":"Services"
        }
    ],
    "sg:phone":"+1 610 696 8070",
    "sg:postcode":"19380",
    "sg:province":"PA",
    "sg:tags":[
        "lamp",
        "parts",
        "electrical"
    ],
    "wof:name":"Campbell Lamps Supply",
    "wof:placetype":"venue"
},
  "geometry": {"coordinates":[-75.545947,40.006746],"type":"Point"}
}