{
  "type": "Feature",
  "properties": {
    "addr:full":"507 S 6th St Philadelphia PA 19147",
    "addr:housenumber":"507",
    "addr:postcode":"19147",
    "addr:street":"S 6Th St",
    "iso:country":"US",
    "sg:address":"507 S 6th St",
    "sg:city":"Philadelphia",
    "sg:classifiers":[
        {
            "category":"Restaurant",
            "type":"Food & Drink"
        }
    ],
    "sg:phone":"+1 215 829 4242",
    "sg:postcode":"19147",
    "sg:province":"PA",
    "wof:name":"Texas Wieners",
    "wof:placetype":"venue"
},
  "geometry": {"coordinates":[-75.15211600000001,39.943024],"type":"Point"}
}