{
  "type": "Feature",
  "properties": {
    "addr:full":"1131 Arkansas Ave Pittsburgh PA 15216",
    "addr:housenumber":"1131",
    "addr:postcode":"15216",
    "addr:street":"Arkansas Ave",
    "iso:country":"US",
    "sg:address":"1131 Arkansas Ave",
    "sg:city":"Pittsburgh",
    "sg:classifiers":[
        {
            "category":"Building & Trades",
            "subcategory":"Construction",
            "type":"Services"
        }
    ],
    "sg:phone":"+1   ",
    "sg:postcode":"15216",
    "sg:province":"PA",
    "sg:tags":[
        "house"
    ],
    "wof:name":"Unique Focus Inc",
    "wof:placetype":"venue"
},
  "geometry": {"coordinates":[-80.03008699999999,40.391832],"type":"Point"}
}