{
  "type": "Feature",
  "properties": {
    "iso:country":"US",
    "sg:address":"359 N 1st St",
    "sg:city":"Jeannette",
    "sg:classifiers":[
        {
            "category":"Home & Garden",
            "subcategory":"Building Materials",
            "type":"Retail Goods"
        },
        {
            "category":"Wholesale",
            "subcategory":"Electrical",
            "type":"Manufacturing & Wholesale Goods"
        }
    ],
    "sg:phone":"+1 724 523 3611",
    "sg:postcode":"15644",
    "sg:province":"PA",
    "sg:tags":[
        "equipment",
        "fixture",
        "electric",
        "supply"
    ],
    "sg:website":"www.hummellbrothers.com",
    "wof:name":"Hummell Brothers Electric Sup",
    "wof:placetype":"venue"
},
  "geometry": {"coordinates":[-79.60730700000001,40.331814],"type":"Point"}
}