{
  "type": "Feature",
  "properties": {
    "addr:full":"460 S Cedar Crest Blvd Allentown PA 18103",
    "addr:housenumber":"460",
    "addr:postcode":"18103",
    "addr:street":"S Cedar Crest Blvd",
    "iso:country":"US",
    "sg:address":"460 S Cedar Crest Blvd",
    "sg:city":"Allentown",
    "sg:classifiers":[
        {
            "category":"Restaurant",
            "type":"Food & Drink"
        }
    ],
    "sg:phone":"+1 610 770 9883",
    "sg:postcode":"18103",
    "sg:province":"PA",
    "wof:name":"Friendly's Restaurant",
    "wof:placetype":"venue"
},
  "geometry": {"coordinates":[-75.5224,40.582199],"type":"Point"}
}