{
  "type": "Feature",
  "properties": {
    "addr:full":"3055 Black Gap Rd Chambersburg PA 17201",
    "addr:housenumber":"3055",
    "addr:postcode":"17201",
    "addr:street":"Black Gap Rd",
    "iso:country":"US",
    "sg:address":"3055 Black Gap Rd",
    "sg:city":"Chambersburg",
    "sg:classifiers":[
        {
            "category":"Shopping",
            "subcategory":"Clothing, Apparel, & Fashions",
            "type":"Retail Goods"
        }
    ],
    "sg:phone":"+1 717 263 6438",
    "sg:postcode":"17201",
    "sg:province":"PA",
    "sg:tags":[
        "sportswear"
    ],
    "wof:name":"American Eagle Outfitters",
    "wof:placetype":"venue"
},
  "geometry": {"coordinates":[-77.579775,39.966453],"type":"Point"}
}