{
  "type": "Feature",
  "properties": {
    "addr:full":"129 Sunbury St Minersville PA 17954",
    "addr:housenumber":"129",
    "addr:postcode":"17954",
    "addr:street":"Sunbury St",
    "iso:country":"US",
    "sg:address":"129 Sunbury St",
    "sg:city":"Minersville",
    "sg:classifiers":[
        {
            "category":"Organizations",
            "subcategory":"Labor Organization",
            "type":"Services"
        }
    ],
    "sg:phone":"+1   ",
    "sg:postcode":"17954",
    "sg:province":"PA",
    "wof:name":"Pace International Union",
    "wof:placetype":"venue"
},
  "geometry": {"coordinates":[-76.260329,40.69083],"type":"Point"}
}