{
  "type": "Feature",
  "properties": {
    "addr:full":"118 N 9th St Lebanon PA 17046",
    "addr:housenumber":"118",
    "addr:postcode":"17046",
    "addr:street":"N 9Th St",
    "iso:country":"US",
    "sg:address":"118 N 9th St",
    "sg:city":"Lebanon",
    "sg:classifiers":[
        {
            "category":"Shopping",
            "subcategory":"Discount & Variety Stores",
            "type":"Retail Goods"
        }
    ],
    "sg:phone":"+1 717 376 0255",
    "sg:postcode":"17046",
    "sg:province":"PA",
    "wof:name":"Eunice Variety Store",
    "wof:placetype":"venue"
},
  "geometry": {"coordinates":[-76.426489,40.341569],"type":"Point"}
}