{
  "type": "Feature",
  "properties": {
    "iso:country":"US",
    "sg:address":"39 Central Ave",
    "sg:city":"Berwyn",
    "sg:classifiers":[
        {
            "category":"Retail",
            "subcategory":"Car Wash",
            "type":"Services"
        }
    ],
    "sg:phone":"+1   ",
    "sg:postcode":"19312",
    "sg:province":"PA",
    "sg:tags":[
        "carwash"
    ],
    "wof:name":"Yellow Rose Detailing",
    "wof:placetype":"venue"
},
  "geometry": {"coordinates":[-75.44388499999999,40.043549],"type":"Point"}
}