{
  "type": "Feature",
  "properties": {
    "iso:country":"US",
    "sg:address":"479 Latrobe Ave",
    "sg:city":"Confluence",
    "sg:classifiers":[
        {
            "category":"Autos & Motor Vehicles",
            "subcategory":"Fuel & Gas Station",
            "type":"Retail Goods"
        }
    ],
    "sg:phone":"+1 814 395 3177",
    "sg:postcode":"15424",
    "sg:province":"PA",
    "sg:tags":[
        "convenience",
        "oil",
        "store"
    ],
    "sg:website":"http://www.hsc.nl",
    "wof:name":"Hartman's Service Center",
    "wof:placetype":"venue"
},
  "geometry": {"coordinates":[-79.35954599999999,39.812564],"type":"Point"}
}