{
  "type": "Feature",
  "properties": {
    "iso:country":"US",
    "sg:address":"407 3rd Ave",
    "sg:city":"Jessup",
    "sg:classifiers":[
        {
            "category":"Health Services",
            "subcategory":"Doctor",
            "type":"Services"
        }
    ],
    "sg:phone":"+1 570 383 7922",
    "sg:postcode":"18434",
    "sg:province":"PA",
    "sg:tags":[
        "medicine",
        "as",
        "internal",
        "operates",
        "an"
    ],
    "wof:name":"Susan Biancarelli MD",
    "wof:placetype":"venue"
},
  "geometry": {"coordinates":[-75.57140099999999,41.47386],"type":"Point"}
}