{
  "type": "Feature",
  "properties": {
    "iso:country":"US",
    "sg:address":"245 Hazleton Apartment",
    "sg:city":"West Hazleton",
    "sg:classifiers":[
        {
            "category":"Building & Trades",
            "subcategory":"Plumbing",
            "type":"Services"
        }
    ],
    "sg:phone":"+1 570 459 0330",
    "sg:postcode":"18202",
    "sg:province":"PA",
    "sg:tags":[
        "plumbing",
        "contractor"
    ],
    "wof:name":"L M Plumbing & Heating",
    "wof:placetype":"venue"
},
  "geometry": {"coordinates":[-75.982846,40.975671],"type":"Point"}
}