{
  "type": "Feature",
  "properties": {
    "addr:full":"201 Market St Lititz PA 17543",
    "addr:housenumber":"201",
    "addr:postcode":"17543",
    "addr:street":"Market St",
    "iso:country":"US",
    "sg:address":"201 Market St",
    "sg:city":"Lititz",
    "sg:classifiers":[
        {
            "category":"Social Services",
            "type":"Services"
        }
    ],
    "sg:phone":"+1   ",
    "sg:postcode":"17543",
    "sg:province":"PA",
    "wof:name":"Littitz Senoir Center",
    "wof:placetype":"venue"
},
  "geometry": {"coordinates":[-76.301796,40.16317],"type":"Point"}
}