{
  "type": "Feature",
  "properties": {
    "iso:country":"US",
    "sg:address":"102 Aspen Dr",
    "sg:city":"Downingtown",
    "sg:classifiers":[
        {
            "category":"Organizations",
            "subcategory":"Membership Organization",
            "type":"Services"
        }
    ],
    "sg:phone":"+1   ",
    "sg:postcode":"19335",
    "sg:province":"PA",
    "sg:tags":[
        "social"
    ],
    "wof:name":"National M P S Society Inc",
    "wof:placetype":"venue"
},
  "geometry": {"coordinates":[-75.76415799999999,40.063632],"type":"Point"}
}