{
  "type": "Feature",
  "properties": {
    "addr:full":"460 Caredean Dr Horsham PA 19044",
    "addr:housenumber":"460",
    "addr:postcode":"19044",
    "addr:street":"Caredean Dr",
    "iso:country":"US",
    "sg:address":"460 Caredean Dr",
    "sg:city":"Horsham",
    "sg:classifiers":[
        {
            "category":"Manufacturing",
            "subcategory":"Tools & Machinery",
            "type":"Manufacturing & Wholesale Goods"
        }
    ],
    "sg:phone":"+1 215 957 5999",
    "sg:postcode":"19044",
    "sg:province":"PA",
    "sg:tags":[
        "cylinder"
    ],
    "wof:name":"Isotech Inc",
    "wof:placetype":"venue"
},
  "geometry": {"coordinates":[-75.17264400000001,40.203986],"type":"Point"}
}