{
  "type": "Feature",
  "properties": {
    "addr:full":"13 McCarthy Ave Langhorne PA 19047",
    "addr:housenumber":"13",
    "addr:postcode":"19047",
    "addr:street":"Mccarthy Ave Langhorne Pa",
    "iso:country":"US",
    "sg:address":"13 McCarthy Ave",
    "sg:city":"Langhorne",
    "sg:classifiers":[
        {
            "category":"Building & Trades",
            "subcategory":"Equipment Rental",
            "type":"Services"
        }
    ],
    "sg:phone":"+1 215 757 7327",
    "sg:postcode":"19047",
    "sg:province":"PA",
    "sg:tags":[
        "heavy",
        "construction"
    ],
    "wof:name":"Plates Inc",
    "wof:placetype":"venue"
},
  "geometry": {"coordinates":[-74.91131900000001,40.146656],"type":"Point"}
}