{
  "type": "Feature",
  "properties": {
    "addr:full":"444 N 3rd St Philadelphia PA 19123",
    "addr:housenumber":"444",
    "addr:postcode":"19123",
    "addr:street":"N 3Rd St",
    "iso:country":"US",
    "sg:address":"444 N 3rd St",
    "sg:city":"Philadelphia",
    "sg:classifiers":[
        {
            "category":"Health Services",
            "subcategory":"Medical Lab",
            "type":"Services"
        }
    ],
    "sg:phone":"+1   ",
    "sg:postcode":"19123",
    "sg:province":"PA",
    "sg:tags":[
        "laboratory",
        "dental"
    ],
    "wof:name":"Dental Images Inc",
    "wof:placetype":"venue"
},
  "geometry": {"coordinates":[-75.143818,39.959181],"type":"Point"}
}