{
  "type": "Feature",
  "properties": {
    "iso:country":"US",
    "sg:address":"35 E 4th St",
    "sg:city":"Emporium",
    "sg:classifiers":[
        {
            "category":"Social Services",
            "subcategory":"Child Care",
            "type":"Services"
        }
    ],
    "sg:phone":"+1   ",
    "sg:postcode":"15834",
    "sg:province":"PA",
    "sg:tags":[
        "union",
        "credit",
        "state",
        "day"
    ],
    "wof:name":"St Marys Area Credit Union",
    "wof:placetype":"venue"
},
  "geometry": {"coordinates":[-78.23578000000001,41.511565],"type":"Point"}
}