{
  "type": "Feature",
  "properties": {
    "iso:country":"US",
    "sg:address":"103 Brooklyn St",
    "sg:city":"Carbondale",
    "sg:classifiers":[
        {
            "category":"Education",
            "subcategory":"School",
            "type":"Public Place"
        }
    ],
    "sg:phone":"+1   ",
    "sg:postcode":"18407",
    "sg:province":"PA",
    "wof:name":"Carbondale Elementary School",
    "wof:placetype":"venue"
},
  "geometry": {"coordinates":[-75.514032,41.566506],"type":"Point"}
}