{
  "type": "Feature",
  "properties": {
    "iso:country":"US",
    "sg:address":"4035 Powelton Ave",
    "sg:city":"Philadelphia",
    "sg:classifiers":[
        {
            "category":"Organizations",
            "subcategory":"Non-profit Organization",
            "type":"Services"
        }
    ],
    "sg:phone":"+1 215 222 1117",
    "sg:postcode":"19104",
    "sg:province":"PA",
    "sg:tags":[
        "service/non-profit",
        "community"
    ],
    "wof:name":"To Our Children's Future With Health",
    "wof:placetype":"venue"
},
  "geometry": {"coordinates":[-75.20360599999999,39.959197],"type":"Point"}
}