{
  "type": "Feature",
  "properties": {
    "iso:country":"US",
    "sg:address":"556 N Centre St",
    "sg:city":"Pottsville",
    "sg:classifiers":[
        {
            "category":"Bars & Pubs",
            "type":"Food & Drink"
        }
    ],
    "sg:phone":"+1   ",
    "sg:postcode":"17901",
    "sg:province":"PA",
    "sg:tags":[
        "drinking"
    ],
    "wof:name":"Maroons Sports Bar & Restauran",
    "wof:placetype":"venue"
},
  "geometry": {"coordinates":[-76.197433,40.688894],"type":"Point"}
}