{
  "type": "Feature",
  "properties": {
    "iso:country":"US",
    "sg:address":"5200 Butler St",
    "sg:city":"Pittsburgh",
    "sg:classifiers":[
        {
            "category":"Banks & Credit Unions",
            "subcategory":"Bank",
            "type":"Services"
        }
    ],
    "sg:phone":"+1 412 781 2000",
    "sg:postcode":"15201",
    "sg:province":"PA",
    "wof:name":"Laurel Savings Bank",
    "wof:placetype":"venue"
},
  "geometry": {"coordinates":[-79.953442,40.48159],"type":"Point"}
}