{
  "type": "Feature",
  "properties": {
    "iso:country":"US",
    "sg:address":"830 N Market St",
    "sg:city":"Selinsgrove",
    "sg:classifiers":[
        {
            "category":"Personal",
            "subcategory":"Barber",
            "type":"Services"
        }
    ],
    "sg:phone":"+1 570 374 1447",
    "sg:postcode":"17870",
    "sg:province":"PA",
    "wof:name":"Village Barber Shop",
    "wof:placetype":"venue"
},
  "geometry": {"coordinates":[-76.85711999999999,40.808577],"type":"Point"}
}