{
  "type": "Feature",
  "properties": {
    "iso:country":"US",
    "sg:address":"1615 N Atherton St",
    "sg:city":"State College",
    "sg:classifiers":[
        {
            "category":"Restaurant",
            "type":"Food & Drink"
        }
    ],
    "sg:menulink":"http://www.allmenus.com/pa/ferguson/206839-mcdonalds/menu/",
    "sg:phone":"+1 814 231 8800",
    "sg:postcode":"16803",
    "sg:province":"PA",
    "sg:tags":[
        "burger",
        "american"
    ],
    "wof:name":"McDonald's",
    "wof:placetype":"venue"
},
  "geometry": {"coordinates":[-77.89239600000001,40.807545],"type":"Point"}
}