{
  "type": "Feature",
  "properties": {
    "addr:full":"476 Salem Dr Pittsburgh PA 15243",
    "addr:housenumber":"476",
    "addr:postcode":"15243",
    "addr:street":"Salem Dr",
    "iso:country":"US",
    "sg:address":"476 Salem Dr",
    "sg:city":"Pittsburgh",
    "sg:classifiers":[
        {
            "category":"Insurance",
            "subcategory":"Insurance Agent",
            "type":"Services"
        }
    ],
    "sg:phone":"+1 412 344 5331",
    "sg:postcode":"15243",
    "sg:province":"PA",
    "wof:name":"Nationwide Insurance",
    "wof:placetype":"venue"
},
  "geometry": {"coordinates":[-80.057157,40.379874],"type":"Point"}
}