{
  "type": "Feature",
  "properties": {
    "iso:country":"US",
    "sg:address":"627 North St",
    "sg:city":"Mc Sherrystown",
    "sg:classifiers":[
        {
            "category":"Building & Trades",
            "subcategory":"Cleaning & Sanitation",
            "type":"Services"
        }
    ],
    "sg:phone":"+1 717 632 4560",
    "sg:postcode":"17344",
    "sg:province":"PA",
    "sg:tags":[
        "maintenance"
    ],
    "wof:name":"T & W Floor Care Specialists",
    "wof:placetype":"venue"
},
  "geometry": {"coordinates":[-77.013701,39.807786],"type":"Point"}
}