{
  "type": "Feature",
  "properties": {
    "iso:country":"US",
    "sg:address":"4857 State Rte 51 N",
    "sg:city":"Belle Vernon",
    "sg:classifiers":[
        {
            "category":"Retail",
            "subcategory":"Auto Repair",
            "type":"Services"
        }
    ],
    "sg:phone":"+1   ",
    "sg:postcode":"15012",
    "sg:province":"PA",
    "sg:tags":[
        "shop",
        "automotive",
        "general"
    ],
    "wof:name":"Truck Doctors Inc",
    "wof:placetype":"venue"
},
  "geometry": {"coordinates":[-79.821051,40.192013],"type":"Point"}
}