{
  "type": "Feature",
  "properties": {
    "iso:country":"US",
    "sg:address":"1241 2nd Ave",
    "sg:city":"Conway",
    "sg:classifiers":[
        {
            "category":"Bars & Pubs",
            "type":"Food & Drink"
        },
        {
            "category":"Restaurant",
            "type":"Food & Drink"
        }
    ],
    "sg:phone":"+1 724 869 2127",
    "sg:postcode":"15027",
    "sg:province":"PA",
    "sg:tags":[
        "drinking"
    ],
    "wof:name":"Haglan's Cafe",
    "wof:placetype":"venue"
},
  "geometry": {"coordinates":[-80.238786,40.661277],"type":"Point"}
}