{
  "type": "Feature",
  "properties": {
    "iso:country":"US",
    "sg:address":"432 Dawson Ave",
    "sg:city":"Carnegie",
    "sg:classifiers":[
        {
            "category":"Building & Trades",
            "subcategory":"Landscaping Services",
            "type":"Services"
        }
    ],
    "sg:phone":"+1   ",
    "sg:postcode":"15106",
    "sg:province":"PA",
    "wof:name":"E Stewart & Sons",
    "wof:placetype":"venue"
},
  "geometry": {"coordinates":[-80.08076199999999,40.407012],"type":"Point"}
}