{
  "type": "Feature",
  "properties": {
    "iso:country":"US",
    "sg:address":"255 Logan Rd",
    "sg:city":"Gibsonia",
    "sg:classifiers":[
        {
            "category":"Building & Trades",
            "subcategory":"Construction",
            "type":"Services"
        }
    ],
    "sg:phone":"+1   ",
    "sg:postcode":"15044",
    "sg:province":"PA",
    "sg:tags":[
        "hanging",
        "contractor"
    ],
    "wof:name":"Ragan Painting Co",
    "wof:placetype":"venue"
},
  "geometry": {"coordinates":[-80.01497999999999,40.654256],"type":"Point"}
}