{
  "type": "Feature",
  "properties": {
    "iso:country":"US",
    "sg:address":"106 Sand Rd",
    "sg:city":"Butler",
    "sg:classifiers":[
        {
            "category":"Sports & Exercise",
            "subcategory":"Golf",
            "type":"Entertainment"
        }
    ],
    "sg:phone":"+1 724 287 9180",
    "sg:postcode":"16050",
    "sg:province":"PA",
    "sg:tags":[
        "course",
        "public"
    ],
    "wof:name":"Hiland Public Golf Course",
    "wof:placetype":"venue"
},
  "geometry": {"coordinates":[-79.773706,41.054893],"type":"Point"}
}