{
  "type": "Feature",
  "properties": {
    "addr:full":"409 19th St Windber PA 15963",
    "addr:housenumber":"409",
    "addr:postcode":"15963",
    "addr:street":"19Th St",
    "iso:country":"US",
    "sg:address":"409 19th St",
    "sg:city":"Windber",
    "sg:classifiers":[
        {
            "category":"Utilities",
            "subcategory":"Fuel Oil & Lpg",
            "type":"Services"
        }
    ],
    "sg:phone":"+1   ",
    "sg:postcode":"15963",
    "sg:province":"PA",
    "wof:name":"SHAFFER OIL",
    "wof:placetype":"venue"
},
  "geometry": {"coordinates":[-78.82766700000001,40.232785],"type":"Point"}
}