{
  "type": "Feature",
  "properties": {
    "iso:country":"US",
    "sg:address":"131 Palmetto Dr",
    "sg:city":"Milford",
    "sg:classifiers":[
        {
            "category":"Building & Trades",
            "subcategory":"Construction",
            "type":"Services"
        }
    ],
    "sg:phone":"+1   ",
    "sg:postcode":"18337",
    "sg:province":"PA",
    "sg:tags":[
        "contractor"
    ],
    "wof:name":"Diversified Masonry",
    "wof:placetype":"venue"
},
  "geometry": {"coordinates":[-74.863399,41.327735],"type":"Point"}
}