{
  "type": "Feature",
  "properties": {
    "iso:country":"US",
    "sg:address":"100 E Queen St",
    "sg:city":"Jonestown",
    "sg:classifiers":[
        {
            "category":"Health Services",
            "subcategory":"Clinic",
            "type":"Services"
        }
    ],
    "sg:phone":"+1 717 865 0739",
    "sg:postcode":"17038",
    "sg:province":"PA",
    "sg:tags":[
        "outpatient"
    ],
    "sg:website":"http://www.tenetclassaction.com",
    "wof:name":"Good Samaritan Jonestown Ctr",
    "wof:placetype":"venue"
},
  "geometry": {"coordinates":[-76.476387,40.412601],"type":"Point"}
}