{
  "type": "Feature",
  "properties": {
    "iso:country":"US",
    "sg:address":"750 Langdon Rd",
    "sg:city":"Erie",
    "sg:classifiers":[
        {
            "category":"Retail",
            "subcategory":"Repair Shop",
            "type":"Services"
        }
    ],
    "sg:phone":"+1 814 825 8038",
    "sg:postcode":"16509",
    "sg:province":"PA",
    "sg:tags":[
        "refinishing",
        "furniture"
    ],
    "wof:name":"John Mattson Wood Renu",
    "wof:placetype":"venue"
},
  "geometry": {"coordinates":[-80.02722199999999,42.077382],"type":"Point"}
}