{
  "type": "Feature",
  "properties": {
    "addr:full":"145 Masonic Temple Rd Somerset PA 15501",
    "addr:housenumber":"145",
    "addr:postcode":"15501",
    "addr:street":"Temple Rd",
    "iso:country":"US",
    "sg:address":"145 Masonic Temple Rd",
    "sg:city":"Somerset",
    "sg:classifiers":[
        {
            "category":"Organizations",
            "subcategory":"Labor Organization",
            "type":"Services"
        }
    ],
    "sg:phone":"+1   ",
    "sg:postcode":"15501",
    "sg:province":"PA",
    "wof:name":"Free & Accepted Masons of PA",
    "wof:placetype":"venue"
},
  "geometry": {"coordinates":[-79.076532,40.035087],"type":"Point"}
}