{
  "type": "Feature",
  "properties": {
    "iso:country":"US",
    "sg:address":"381 Brinton Lake Rd",
    "sg:city":"Thornton",
    "sg:classifiers":[
        {
            "category":"Banks & Credit Unions",
            "subcategory":"Investment Brokerage",
            "type":"Services"
        }
    ],
    "sg:phone":"+1 610 361 1000",
    "sg:postcode":"19373",
    "sg:province":"PA",
    "sg:tags":[
        "investing"
    ],
    "wof:name":"Brandywine Asset Management",
    "wof:placetype":"venue"
},
  "geometry": {"coordinates":[-75.537903,39.894199],"type":"Point"}
}