{
  "type": "Feature",
  "properties": {
    "iso:country":"US",
    "sg:address":"170 Hollars Exd",
    "sg:city":"Everett",
    "sg:classifiers":[
        {
            "category":"Building & Trades",
            "subcategory":"Construction",
            "type":"Services"
        }
    ],
    "sg:phone":"+1   ",
    "sg:postcode":"15537",
    "sg:province":"PA",
    "sg:tags":[
        "house",
        "construct",
        "contractor"
    ],
    "wof:name":"Gary Miller Contractor",
    "wof:placetype":"venue"
},
  "geometry": {"coordinates":[-78.381123,39.996774],"type":"Point"}
}