{
  "type": "Feature",
  "properties": {
    "iso:country":"US",
    "sg:address":"3539 York Rd",
    "sg:city":"Furlong",
    "sg:classifiers":[
        {
            "category":"Professional",
            "subcategory":"Business Services",
            "type":"Services"
        },
        {
            "category":"Home & Garden",
            "subcategory":"Furniture",
            "type":"Retail Goods"
        }
    ],
    "sg:phone":"+1 215 794 7325",
    "sg:postcode":"18925",
    "sg:province":"PA",
    "sg:tags":[
        "interior",
        "consultant",
        "design",
        "decorator"
    ],
    "wof:name":"Hendrixson's Furniture",
    "wof:placetype":"venue"
},
  "geometry": {"coordinates":[-75.082571,40.300238],"type":"Point"}
}