{
  "type": "Feature",
  "properties": {
    "iso:country":"US",
    "sg:address":"305 W Moreland Rd",
    "sg:city":"Willow Grove",
    "sg:classifiers":[
        {
            "category":"Organizations",
            "subcategory":"Professional Association",
            "type":"Services"
        }
    ],
    "sg:phone":"+1 215 659 3782",
    "sg:postcode":"19090",
    "sg:province":"PA",
    "wof:name":"Veterans Of Foreign Wars 3612",
    "wof:placetype":"venue"
},
  "geometry": {"coordinates":[-75.121353,40.144015],"type":"Point"}
}