{
  "type": "Feature",
  "properties": {
    "iso:country":"US",
    "sg:address":"106 River Ave",
    "sg:city":"Pittsburgh",
    "sg:classifiers":[
        {
            "category":"Building & Trades",
            "subcategory":"Construction",
            "type":"Services"
        }
    ],
    "sg:phone":"+1 412 921 9868",
    "sg:postcode":"15212",
    "sg:province":"PA",
    "sg:tags":[
        "insulation",
        "heat",
        "contractor"
    ],
    "wof:name":"Specialty Spray Co Inc",
    "wof:placetype":"venue"
},
  "geometry": {"coordinates":[-80.000529,40.4482],"type":"Point"}
}