{
  "type": "Feature",
  "properties": {
    "iso:country":"US",
    "sg:address":"312 Parkhill Rd",
    "sg:city":"Baden",
    "sg:classifiers":[
        {
            "category":"Building & Trades",
            "subcategory":"Construction",
            "type":"Services"
        }
    ],
    "sg:phone":"+1   ",
    "sg:postcode":"15005",
    "sg:province":"PA",
    "sg:tags":[
        "asphalt",
        "maintenance",
        "contractor"
    ],
    "wof:name":"T J Ackerman Contracting",
    "wof:placetype":"venue"
},
  "geometry": {"coordinates":[-80.16051899999999,40.673262],"type":"Point"}
}