{
  "type": "Feature",
  "properties": {
    "addr:full":"955 Freeport Rd Natrona Heights PA 15065",
    "addr:housenumber":"955",
    "addr:postcode":"15065",
    "addr:street":"Freeport Rd",
    "iso:country":"US",
    "sg:address":"955 Freeport Rd",
    "sg:city":"Natrona Heights",
    "sg:classifiers":[
        {
            "category":"Organizations",
            "subcategory":"Non-profit Organization",
            "type":"Services"
        }
    ],
    "sg:phone":"+1 724 226 0866",
    "sg:postcode":"15065",
    "sg:province":"PA",
    "sg:tags":[
        "fund",
        "counselor",
        "raising"
    ],
    "wof:name":"Joe Clark Fund Raising Candies",
    "wof:placetype":"venue"
},
  "geometry": {"coordinates":[-79.744388,40.613146],"type":"Point"}
}