{
  "type": "Feature",
  "properties": {
    "iso:country":"US",
    "sg:address":"295 N Kerrwood Dr",
    "sg:city":"Hermitage",
    "sg:classifiers":[
        {
            "category":"Health Services",
            "subcategory":"Doctor",
            "type":"Services"
        }
    ],
    "sg:phone":"+1 724 981 1940",
    "sg:postcode":"16148",
    "sg:province":"PA",
    "sg:tags":[
        "physician",
        "surgeon"
    ],
    "wof:name":"Michael P Messina DO",
    "wof:placetype":"venue"
},
  "geometry": {"coordinates":[-80.463189,41.236644],"type":"Point"}
}