{
  "type": "Feature",
  "properties": {
    "iso:country":"US",
    "sg:address":"425 W Broad St",
    "sg:city":"Bethlehem",
    "sg:classifiers":[
        {
            "category":"Professional",
            "subcategory":"Lawyer & Legal Services",
            "type":"Services"
        }
    ],
    "sg:phone":"+1 610 867 8150",
    "sg:postcode":"18018",
    "sg:province":"PA",
    "sg:tags":[
        "attorney",
        "practice"
    ],
    "wof:name":"Law Office Of Karl F Logenbach",
    "wof:placetype":"venue"
},
  "geometry": {"coordinates":[-75.388487,40.622448],"type":"Point"}
}