{
  "type": "Feature",
  "properties": {
    "iso:country":"US",
    "sg:address":"1391 Hill Rd",
    "sg:city":"Blairsville",
    "sg:classifiers":[
        {
            "category":"Farming",
            "subcategory":"Dairy Farm",
            "type":"Manufacturing & Wholesale Goods"
        }
    ],
    "sg:phone":"+1   ",
    "sg:postcode":"15717",
    "sg:province":"PA",
    "wof:name":"James Hill",
    "wof:placetype":"venue"
},
  "geometry": {"coordinates":[-79.257465,40.504814],"type":"Point"}
}