{
  "type": "Feature",
  "properties": {
    "addr:full":"102 York Rd Willow Grove PA 19090",
    "addr:housenumber":"102",
    "addr:postcode":"19090",
    "addr:street":"York Rd",
    "iso:country":"US",
    "sg:address":"102 York Rd",
    "sg:city":"Willow Grove",
    "sg:classifiers":[
        {
            "category":"Social Services",
            "type":"Services"
        }
    ],
    "sg:phone":"+1   ",
    "sg:postcode":"19090",
    "sg:province":"PA",
    "wof:name":"Pennsylvania Family Svcs Montg",
    "wof:placetype":"venue"
},
  "geometry": {"coordinates":[-75.11461199999999,40.143045],"type":"Point"}
}