{
  "type": "Feature",
  "properties": {
    "addr:full":"1345 W 11th St Erie PA 16502",
    "addr:housenumber":"1345",
    "addr:postcode":"16502",
    "addr:street":"W 11Th St",
    "iso:country":"US",
    "sg:address":"1345 W 11th St",
    "sg:city":"Erie",
    "sg:classifiers":[
        {
            "category":"Mining & Drilling",
            "type":"Manufacturing & Wholesale Goods"
        }
    ],
    "sg:phone":"+1 814 459 1896",
    "sg:postcode":"16502",
    "sg:province":"PA",
    "sg:tags":[
        "rigger"
    ],
    "wof:name":"NNN Carting & Storage Inc",
    "wof:placetype":"venue"
},
  "geometry": {"coordinates":[-80.111132,42.113684],"type":"Point"}
}