{
  "type": "Feature",
  "properties": {
    "iso:country":"US",
    "sg:address":"8 Browns Dam Rd",
    "sg:city":"New Oxford",
    "sg:classifiers":[
        {
            "category":"Freight",
            "type":"Transportation"
        }
    ],
    "sg:phone":"+1   ",
    "sg:postcode":"17350",
    "sg:province":"PA",
    "sg:tags":[
        "operator",
        "local",
        "trucking"
    ],
    "wof:name":"Richard Lupo Trucking Inc",
    "wof:placetype":"venue"
},
  "geometry": {"coordinates":[-77.051948,39.920044],"type":"Point"}
}