{
  "type": "Feature",
  "properties": {
    "iso:country":"US",
    "sg:address":"1656 Rte 68",
    "sg:city":"New Brighton",
    "sg:classifiers":[
        {
            "category":"Manufacturing",
            "subcategory":"Signs",
            "type":"Manufacturing & Wholesale Goods"
        }
    ],
    "sg:phone":"+1 724 452 0318",
    "sg:postcode":"15066",
    "sg:province":"PA",
    "sg:tags":[
        "specialty",
        "mfg"
    ],
    "wof:name":"Designer Display Cakes",
    "wof:placetype":"venue"
},
  "geometry": {"coordinates":[-80.185744,40.763971],"type":"Point"}
}