{
  "type": "Feature",
  "properties": {
    "iso:country":"US",
    "sg:address":"53 Shrontz Ln",
    "sg:city":"Washington",
    "sg:classifiers":[
        {
            "category":"Autos & Motor Vehicles",
            "subcategory":"Automobile Sales",
            "type":"Retail Goods"
        }
    ],
    "sg:phone":"+1   ",
    "sg:postcode":"15301",
    "sg:province":"PA",
    "wof:name":"East End Equipment Co",
    "wof:placetype":"venue"
},
  "geometry": {"coordinates":[-80.222759,40.163159],"type":"Point"}
}