{
  "type": "Feature",
  "properties": {
    "iso:country":"US",
    "sg:address":"301 Main St",
    "sg:city":"Claysville",
    "sg:classifiers":[
        {
            "category":"Manufacturing",
            "subcategory":"Tools & Machinery",
            "type":"Manufacturing & Wholesale Goods"
        },
        {
            "category":"Retail",
            "subcategory":"Repair Shop",
            "type":"Services"
        }
    ],
    "sg:phone":"+1 724 663 4433",
    "sg:postcode":"15323",
    "sg:province":"PA",
    "sg:tags":[
        "machine",
        "machinery-rebuild"
    ],
    "wof:name":"Kgy Machining",
    "wof:placetype":"venue"
},
  "geometry": {"coordinates":[-80.41037799999999,40.117859],"type":"Point"}
}