{
  "type": "Feature",
  "properties": {
    "addr:full":"1811 Fitzwater St., #E Philadelphia PA 19146",
    "addr:housenumber":"1811",
    "addr:postcode":"19146",
    "addr:street":"Fitzwater St. # E",
    "iso:country":"US",
    "sg:address":"1811 Fitzwater St., #E",
    "sg:city":"Philadelphia",
    "sg:classifiers":[
        {
            "category":"Professional",
            "type":"Services"
        }
    ],
    "sg:phone":"+1 267 519 0370",
    "sg:postcode":"19146",
    "sg:province":"PA",
    "sg:website":"www.vive-consulting.com",
    "wof:name":"Vive Consulting",
    "wof:placetype":"venue"
},
  "geometry": {"coordinates":[-75.17270600000001,39.942899],"type":"Point"}
}