{
  "type": "Feature",
  "properties": {
    "addr:full":"15 Heckamore Rd Bala Cynwyd PA 19004",
    "addr:housenumber":"15",
    "addr:postcode":"19004",
    "addr:street":"Heckamore Rd",
    "iso:country":"US",
    "sg:address":"15 Heckamore Rd",
    "sg:city":"Bala Cynwyd",
    "sg:classifiers":[
        {
            "category":"Building & Trades",
            "subcategory":"Construction",
            "type":"Services"
        }
    ],
    "sg:phone":"+1 610 660 0700",
    "sg:postcode":"19004",
    "sg:province":"PA",
    "sg:tags":[
        "contractor"
    ],
    "wof:name":"Ash William Construction Services",
    "wof:placetype":"venue"
},
  "geometry": {"coordinates":[-75.230923,39.999763],"type":"Point"}
}