{
  "type": "Feature",
  "properties": {
    "iso:country":"US",
    "sg:address":"687 N Chubb Dr",
    "sg:city":"Doylestown",
    "sg:classifiers":[
        {
            "category":"Building & Trades",
            "subcategory":"Construction",
            "type":"Services"
        }
    ],
    "sg:phone":"+1 215 348 2790",
    "sg:postcode":"18901",
    "sg:province":"PA",
    "sg:tags":[
        "contractor"
    ],
    "wof:name":"Scott T Kyle Masonry",
    "wof:placetype":"venue"
},
  "geometry": {"coordinates":[-75.114976,40.325334],"type":"Point"}
}