{
  "type": "Feature",
  "properties": {
    "iso:country":"US",
    "sg:address":"236 W Finley Rd",
    "sg:city":"West Finley",
    "sg:classifiers":[
        {
            "category":"Shopping",
            "subcategory":"Computers & Home Electronics",
            "type":"Retail Goods"
        }
    ],
    "sg:phone":"+1 724 484 0164",
    "sg:postcode":"15377",
    "sg:province":"PA",
    "sg:tags":[
        "equipment",
        "satellite",
        "system"
    ],
    "wof:name":"B & N Electornics",
    "wof:placetype":"venue"
},
  "geometry": {"coordinates":[-80.454492,39.976657],"type":"Point"}
}