{
  "type": "Feature",
  "properties": {
    "iso:country":"US",
    "sg:address":"1680 Brighton Rd",
    "sg:city":"Ellwood City",
    "sg:classifiers":[
        {
            "category":"Professional",
            "subcategory":"Business Services",
            "type":"Services"
        }
    ],
    "sg:phone":"+1 724 758 8436",
    "sg:postcode":"16117",
    "sg:province":"PA",
    "sg:tags":[
        "notary"
    ],
    "wof:name":"Richard C Gaiser",
    "wof:placetype":"venue"
},
  "geometry": {"coordinates":[-80.289603,40.845388],"type":"Point"}
}