{
  "type": "Feature",
  "properties": {
    "addr:full":"3501 N Front St Harrisburg PA 17110",
    "addr:housenumber":"3501",
    "addr:postcode":"17110",
    "addr:street":"N Front St",
    "iso:country":"US",
    "sg:address":"3501 N Front St",
    "sg:city":"Harrisburg",
    "sg:classifiers":[
        {
            "category":"Insurance",
            "subcategory":"Insurance Agent",
            "type":"Services"
        }
    ],
    "sg:phone":"+1 717 234 6530",
    "sg:postcode":"17110",
    "sg:province":"PA",
    "wof:name":"Pa Dental Assn Insurance Svc",
    "wof:placetype":"venue"
},
  "geometry": {"coordinates":[-76.901635,40.306889],"type":"Point"}
}