{
  "type": "Feature",
  "properties": {
    "iso:country":"US",
    "sg:address":"9200 Roosevelt Blvd",
    "sg:city":"Philadelphia",
    "sg:classifiers":[
        {
            "category":"Building & Trades",
            "subcategory":"Plumbing",
            "type":"Services"
        },
        {
            "category":"Building & Trades",
            "subcategory":"Construction",
            "type":"Services"
        },
        {
            "category":"Building & Trades",
            "subcategory":"Cleaning & Sanitation",
            "type":"Services"
        }
    ],
    "sg:phone":"+1 215 722 1300",
    "sg:postcode":"19115",
    "sg:province":"PA",
    "sg:tags":[
        "house",
        "system",
        "clean",
        "contractor",
        "air conditioning",
        "boilers-repair"
    ],
    "sg:website":"http://www.hvacheatingandcooling.com",
    "wof:name":"Eastern Heating & Cooling",
    "wof:placetype":"venue"
},
  "geometry": {"coordinates":[-75.033012,40.076771],"type":"Point"}
}