{
  "type": "Feature",
  "properties": {
    "iso:country":"US",
    "sg:address":"129 Franklin Ave",
    "sg:city":"Uniontown",
    "sg:classifiers":[
        {
            "category":"Social Services",
            "subcategory":"Job Training",
            "type":"Services"
        }
    ],
    "sg:phone":"+1 724 439 5700",
    "sg:postcode":"15401",
    "sg:province":"PA",
    "sg:tags":[
        "rehabilitation"
    ],
    "sg:website":"www.beverlyhealthcare.com",
    "wof:name":"Beverly Healthcare",
    "wof:placetype":"venue"
},
  "geometry": {"coordinates":[-79.74095,39.880522],"type":"Point"}
}