{
  "type": "Feature",
  "properties": {
    "addr:full":"6516 N Radcliffe St Bristol PA 19007",
    "addr:housenumber":"6516",
    "addr:postcode":"19007",
    "addr:street":"N Radcliffe St",
    "iso:country":"US",
    "sg:address":"6516 N Radcliffe St",
    "sg:city":"Bristol",
    "sg:classifiers":[
        {
            "category":"Wholesale",
            "subcategory":"Non-durable Goods",
            "type":"Manufacturing & Wholesale Goods"
        }
    ],
    "sg:phone":"+1 215 788 6652",
    "sg:postcode":"19007",
    "sg:province":"PA",
    "sg:tags":[
        "dry",
        "goods-wholesale"
    ],
    "wof:name":"Restylane Jason Herbalife Beauty Supply At Jasonvertucio",
    "wof:placetype":"venue"
},
  "geometry": {"coordinates":[-74.835003,40.114587],"type":"Point"}
}