{
  "type": "Feature",
  "properties": {
    "iso:country":"US",
    "sg:address":"300 Logan Blvd",
    "sg:city":"Altoona",
    "sg:classifiers":[
        {
            "category":"Shopping",
            "type":"Retail Goods"
        }
    ],
    "sg:phone":"+1 814 942 1150",
    "sg:postcode":"16602",
    "sg:province":"PA",
    "sg:tags":[
        "art",
        "gallery",
        "dealer"
    ],
    "wof:name":"Artistic Persuasion",
    "wof:placetype":"venue"
},
  "geometry": {"coordinates":[-78.40512,40.481003],"type":"Point"}
}