{
  "type": "Feature",
  "properties": {
    "iso:country":"US",
    "sg:address":"1010 Central Ave",
    "sg:city":"Columbia",
    "sg:classifiers":[
        {
            "category":"Utilities",
            "subcategory":"Refuse",
            "type":"Services"
        }
    ],
    "sg:phone":"+1 717 684 4939",
    "sg:postcode":"17512",
    "sg:province":"PA",
    "sg:tags":[
        "garbage",
        "collection"
    ],
    "wof:name":"Gamby's Disposal Svc",
    "wof:placetype":"venue"
},
  "geometry": {"coordinates":[-76.489341,40.02914],"type":"Point"}
}