{
  "type": "Feature",
  "properties": {
    "iso:country":"US",
    "sg:address":"2616 Memorial Blvd",
    "sg:city":"Connellsville",
    "sg:classifiers":[
        {
            "category":"Professional",
            "subcategory":"Business Services",
            "type":"Services"
        },
        {
            "category":"Health Services",
            "subcategory":"Doctor",
            "type":"Services"
        }
    ],
    "sg:phone":"+1 724 620 2819",
    "sg:postcode":"15425",
    "sg:province":"PA",
    "sg:tags":[
        "record",
        "medical"
    ],
    "wof:name":"Mid Atlantic Transcription Svc",
    "wof:placetype":"venue"
},
  "geometry": {"coordinates":[-79.56173,40.055538],"type":"Point"}
}