{
  "type": "Feature",
  "properties": {
    "iso:country":"US",
    "sg:address":"531 N High St",
    "sg:city":"West Chester",
    "sg:classifiers":[
        {
            "category":"Wholesale",
            "subcategory":"Electrical",
            "type":"Manufacturing & Wholesale Goods"
        }
    ],
    "sg:phone":"+1   ",
    "sg:postcode":"19380",
    "sg:province":"PA",
    "sg:tags":[
        "distribution",
        "kitting"
    ],
    "wof:name":"D-Squared Electronics",
    "wof:placetype":"venue"
},
  "geometry": {"coordinates":[-75.609172,39.96565],"type":"Point"}
}