{
  "type": "Feature",
  "properties": {
    "addr:full":"4908 Wayne Ave Philadelphia PA 19144",
    "addr:housenumber":"4908",
    "addr:postcode":"19144",
    "addr:street":"Wayne Ave",
    "iso:country":"US",
    "sg:address":"4908 Wayne Ave",
    "sg:city":"Philadelphia",
    "sg:classifiers":[
        {
            "category":"Retail",
            "subcategory":"Auto Repair",
            "type":"Services"
        }
    ],
    "sg:phone":"+1 215 843 5554",
    "sg:postcode":"19144",
    "sg:province":"PA",
    "sg:tags":[
        "body",
        "shop"
    ],
    "wof:name":"Progressive Motors Inc",
    "wof:placetype":"venue"
},
  "geometry": {"coordinates":[-75.166298,40.024799],"type":"Point"}
}