{
  "type": "Feature",
  "properties": {
    "iso:country":"US",
    "sg:address":"2 Rosette Ln",
    "sg:city":"Richboro",
    "sg:classifiers":[
        {
            "category":"Banks & Credit Unions",
            "subcategory":"Financial Services",
            "type":"Services"
        }
    ],
    "sg:phone":"+1 215 364 3995",
    "sg:postcode":"18954",
    "sg:province":"PA",
    "sg:tags":[
        "management",
        "investment"
    ],
    "wof:name":"Giannone Investments",
    "wof:placetype":"venue"
},
  "geometry": {"coordinates":[-75.012711,40.204819],"type":"Point"}
}