{
  "type": "Feature",
  "properties": {
    "iso:country":"US",
    "sg:address":"116 Sycamore Ave",
    "sg:city":"Folsom",
    "sg:classifiers":[
        {
            "category":"Manufacturing",
            "subcategory":"Tools & Machinery",
            "type":"Manufacturing & Wholesale Goods"
        }
    ],
    "sg:phone":"+1 610 534 9004",
    "sg:postcode":"19033",
    "sg:province":"PA",
    "sg:tags":[
        "machine",
        "shop",
        "cam",
        "manufacturer"
    ],
    "sg:website":"www.allcams.net",
    "wof:name":"Guzzardo Machine Products Corp",
    "wof:placetype":"venue"
},
  "geometry": {"coordinates":[-75.321343,39.890392],"type":"Point"}
}