{
  "type": "Feature",
  "properties": {
    "addr:full":"740 5th Ave New Kensington PA 15068",
    "addr:housenumber":"740",
    "addr:postcode":"15068",
    "addr:street":"5Th Ave",
    "iso:country":"US",
    "sg:address":"740 5th Ave",
    "sg:city":"New Kensington",
    "sg:classifiers":[
        {
            "category":"Professional",
            "subcategory":"Lawyer & Legal Services",
            "type":"Services"
        }
    ],
    "sg:phone":"+1 724 339 9742",
    "sg:postcode":"15068",
    "sg:province":"PA",
    "sg:tags":[
        "attorney",
        "law"
    ],
    "wof:name":"Nardelli Law Offices PC",
    "wof:placetype":"venue"
},
  "geometry": {"coordinates":[-79.76462600000001,40.563394],"type":"Point"}
}