{
  "type": "Feature",
  "properties": {
    "addr:full":"409 Regina St Philadelphia PA 19116",
    "addr:housenumber":"409",
    "addr:postcode":"19116",
    "addr:street":"Regina St",
    "iso:country":"US",
    "sg:address":"409 Regina St",
    "sg:city":"Philadelphia",
    "sg:classifiers":[
        {
            "category":"Sports & Exercise",
            "subcategory":"Playing Field",
            "type":"Entertainment"
        }
    ],
    "sg:phone":"+1 215 934 5562",
    "sg:postcode":"19116",
    "sg:province":"PA",
    "sg:tags":[
        "boxing",
        "instruction"
    ],
    "wof:name":"Philadelphia Amateur Wres",
    "wof:placetype":"venue"
},
  "geometry": {"coordinates":[-75.02703700000001,40.121568],"type":"Point"}
}