{
  "type": "Feature",
  "properties": {
    "addr:full":"22 Westbury Ct Elizabethtown PA 17022",
    "addr:housenumber":"22",
    "addr:postcode":"17022",
    "addr:street":"Westbury Ct",
    "iso:country":"US",
    "sg:address":"22 Westbury Ct",
    "sg:city":"Elizabethtown",
    "sg:classifiers":[
        {
            "category":"Banks & Credit Unions",
            "subcategory":"Investment Brokerage",
            "type":"Services"
        }
    ],
    "sg:phone":"+1 717 572 0785",
    "sg:postcode":"17022",
    "sg:province":"PA",
    "sg:tags":[
        "advisory"
    ],
    "wof:name":"Toews Property Investments",
    "wof:placetype":"venue"
},
  "geometry": {"coordinates":[-76.58786000000001,40.160058],"type":"Point"}
}