{
  "type": "Feature",
  "properties": {
    "iso:country":"US",
    "sg:address":"310 S Market St",
    "sg:city":"Mechanicsburg",
    "sg:classifiers":[
        {
            "category":"Professional",
            "type":"Services"
        }
    ],
    "sg:phone":"+1   ",
    "sg:postcode":"17055",
    "sg:province":"PA",
    "wof:name":"A Elliott",
    "wof:placetype":"venue"
},
  "geometry": {"coordinates":[-77.00649199999999,40.210109],"type":"Point"}
}