{
  "type": "Feature",
  "properties": {
    "addr:full":"111 E Condot Rd Saint Marys PA 15857",
    "addr:housenumber":"111",
    "addr:postcode":"15857",
    "addr:street":"E Condot Rd",
    "iso:country":"US",
    "sg:address":"111 E Condot Rd",
    "sg:city":"Saint Marys",
    "sg:classifiers":[
        {
            "category":"Professional",
            "subcategory":"Lawyer & Legal Services",
            "type":"Services"
        }
    ],
    "sg:phone":"+1   ",
    "sg:postcode":"15857",
    "sg:province":"PA",
    "wof:name":"Law Offices of John Petruna",
    "wof:placetype":"venue"
},
  "geometry": {"coordinates":[-78.56291299999999,41.439413],"type":"Point"}
}