{
  "type": "Feature",
  "properties": {
    "addr:full":"112 Crestview Dr Barto PA 19504",
    "addr:housenumber":"112",
    "addr:postcode":"19504",
    "addr:street":"Crestview Dr",
    "iso:country":"US",
    "sg:address":"112 Crestview Dr",
    "sg:city":"Barto",
    "sg:classifiers":[
        {
            "category":"Building & Trades",
            "subcategory":"Plumbing",
            "type":"Services"
        }
    ],
    "sg:phone":"+1 610 754 0781",
    "sg:postcode":"19504",
    "sg:province":"PA",
    "sg:tags":[
        "plumbing",
        "contractor"
    ],
    "wof:name":"CKL Plumbing & Drain Clng",
    "wof:placetype":"venue"
},
  "geometry": {"coordinates":[-75.58328,40.374257],"type":"Point"}
}