{
  "type": "Feature",
  "properties": {
    "iso:country":"US",
    "sg:address":"1 Eastern Ave Bldg 79",
    "sg:city":"Greencastle",
    "sg:classifiers":[
        {
            "category":"Real Estate",
            "subcategory":"Real Estate Services",
            "type":"Services"
        },
        {
            "category":"Real Estate",
            "subcategory":"Real Estate Operator",
            "type":"Services"
        }
    ],
    "sg:phone":"+1 717 597 9095",
    "sg:postcode":"17225",
    "sg:province":"PA",
    "sg:tags":[
        "vacancy",
        "apartment",
        "rental",
        "finder",
        "listing"
    ],
    "wof:name":"Strathmeade Square",
    "wof:placetype":"venue"
},
  "geometry": {"coordinates":[-77.714653,39.78698],"type":"Point"}
}