{
  "type": "Feature",
  "properties": {
    "iso:country":"US",
    "sg:address":"735 Port Indian Rd",
    "sg:city":"Norristown",
    "sg:classifiers":[
        {
            "category":"Building & Trades",
            "subcategory":"Construction",
            "type":"Services"
        }
    ],
    "sg:phone":"+1 610 279 2272",
    "sg:postcode":"19403",
    "sg:province":"PA",
    "sg:tags":[
        "contractor"
    ],
    "wof:name":"Becker Roofing Co",
    "wof:placetype":"venue"
},
  "geometry": {"coordinates":[-75.390321,40.131627],"type":"Point"}
}