{
  "type": "Feature",
  "properties": {
    "addr:full":"5349 Oxford Ave Philadelphia PA 19195",
    "addr:housenumber":"5349",
    "addr:postcode":"19195",
    "addr:street":"Oxford Ave",
    "iso:country":"US",
    "sg:address":"5349 Oxford Ave",
    "sg:city":"Philadelphia",
    "sg:classifiers":[
        {
            "category":"Education",
            "subcategory":"Music School",
            "type":"Public Place"
        }
    ],
    "sg:phone":"+1 215 533 2053",
    "sg:postcode":"19195",
    "sg:province":"PA",
    "sg:tags":[
        "instrument",
        "teacher",
        "musical"
    ],
    "sg:website":"www.cintiolimusiconline.com",
    "wof:name":"Cintioli Music",
    "wof:placetype":"venue"
},
  "geometry": {"coordinates":[-75.085196,40.029475],"type":"Point"}
}