{
  "type": "Feature",
  "properties": {
    "iso:country":"US",
    "sg:address":"1820 Bullfrog Rd",
    "sg:city":"Fairfield",
    "sg:classifiers":[
        {
            "category":"Farming",
            "subcategory":"Farm",
            "type":"Manufacturing & Wholesale Goods"
        }
    ],
    "sg:phone":"+1   ",
    "sg:postcode":"17320",
    "sg:province":"PA",
    "sg:tags":[
        "crop",
        "general"
    ],
    "wof:name":"Good Intent Farm",
    "wof:placetype":"venue"
},
  "geometry": {"coordinates":[-77.300388,39.757808],"type":"Point"}
}