{
  "type": "Feature",
  "properties": {
    "iso:country":"US",
    "sg:address":"128 N 4th St",
    "sg:city":"Denver",
    "sg:classifiers":[
        {
            "category":"Building & Trades",
            "subcategory":"Construction",
            "type":"Services"
        }
    ],
    "sg:phone":"+1   ",
    "sg:postcode":"17517",
    "sg:province":"PA",
    "sg:tags":[
        "house"
    ],
    "wof:name":"Gene D Kegerise",
    "wof:placetype":"venue"
},
  "geometry": {"coordinates":[-76.13606900000001,40.234102],"type":"Point"}
}