{
  "type": "Feature",
  "properties": {
    "iso:country":"US",
    "sg:address":"1901 Ritner Hwy",
    "sg:city":"Carlisle",
    "sg:classifiers":[
        {
            "category":"Banks & Credit Unions",
            "subcategory":"Bank",
            "type":"Services"
        }
    ],
    "sg:phone":"+1 717 960 1400",
    "sg:postcode":"17013",
    "sg:province":"PA",
    "wof:name":"F & M Trust",
    "wof:placetype":"venue"
},
  "geometry": {"coordinates":[-77.2432,40.190291],"type":"Point"}
}