{
  "type": "Feature",
  "properties": {
    "iso:country":"US",
    "sg:address":"1195 Wilmington St",
    "sg:city":"Washington",
    "sg:classifiers":[
        {
            "category":"Freight",
            "type":"Transportation"
        }
    ],
    "sg:phone":"+1 724 228 6322",
    "sg:postcode":"15301",
    "sg:province":"PA",
    "sg:tags":[
        "commercial",
        "storage",
        "special"
    ],
    "wof:name":"Tylerdale Self Storage",
    "wof:placetype":"venue"
},
  "geometry": {"coordinates":[-80.271619,40.173682],"type":"Point"}
}