{
  "type": "Feature",
  "properties": {
    "iso:country":"US",
    "sg:address":"9115 Red Lion Rd Ste 18",
    "sg:city":"Philadelphia",
    "sg:classifiers":[
        {
            "category":"Health Services",
            "subcategory":"Optometrist",
            "type":"Services"
        }
    ],
    "sg:phone":"+1 215 856 9810",
    "sg:postcode":"19115",
    "sg:province":"PA",
    "wof:name":"Dr, Victor Brinker",
    "wof:placetype":"venue"
},
  "geometry": {"coordinates":[-75.02849999999999,40.102335],"type":"Point"}
}