{
  "type": "Feature",
  "properties": {
    "iso:country":"US",
    "sg:address":"342 Broad St",
    "sg:city":"Montoursville",
    "sg:classifiers":[
        {
            "category":"Shopping",
            "subcategory":"Crafts & Fabrics",
            "type":"Retail Goods"
        }
    ],
    "sg:phone":"+1 570 368 3998",
    "sg:postcode":"17754",
    "sg:province":"PA",
    "sg:tags":[
        "material",
        "needlework"
    ],
    "wof:name":"Bush Mountain Stitchery & Gfts",
    "wof:placetype":"venue"
},
  "geometry": {"coordinates":[-76.926672,41.24954],"type":"Point"}
}