{
  "type": "Feature",
  "properties": {
    "iso:country":"US",
    "sg:address":"2312 Megann Ct",
    "sg:city":"Norristown",
    "sg:classifiers":[
        {
            "category":"Restaurant",
            "type":"Food & Drink"
        }
    ],
    "sg:phone":"+1   ",
    "sg:postcode":"19401",
    "sg:province":"PA",
    "sg:tags":[
        "eating"
    ],
    "wof:name":"Pepes Pizza",
    "wof:placetype":"venue"
},
  "geometry": {"coordinates":[-75.311998,40.131892],"type":"Point"}
}