{
  "type": "Feature",
  "properties": {
    "iso:country":"US",
    "sg:address":"2045 Westgate Dr",
    "sg:city":"Bethlehem",
    "sg:classifiers":[
        {
            "category":"Health Services",
            "subcategory":"Doctor",
            "type":"Services"
        }
    ],
    "sg:phone":"+1 610 691 7010",
    "sg:postcode":"18017",
    "sg:province":"PA",
    "sg:tags":[
        "physician",
        "surgeon"
    ],
    "wof:name":"Lehigh Valley Retinovitreous",
    "wof:placetype":"venue"
},
  "geometry": {"coordinates":[-75.407394,40.639973],"type":"Point"}
}