{
  "type": "Feature",
  "properties": {
    "iso:country":"US",
    "sg:address":"176 Herman Rd",
    "sg:city":"Fombell",
    "sg:classifiers":[
        {
            "category":"Building & Trades",
            "subcategory":"Construction",
            "type":"Services"
        }
    ],
    "sg:phone":"+1   ",
    "sg:postcode":"16123",
    "sg:province":"PA",
    "sg:tags":[
        "house"
    ],
    "wof:name":"Fox Construction",
    "wof:placetype":"venue"
},
  "geometry": {"coordinates":[-80.214099,40.800556],"type":"Point"}
}