{
  "type": "Feature",
  "properties": {
    "iso:country":"US",
    "sg:address":"100 Oley St",
    "sg:city":"Reading",
    "sg:classifiers":[
        {
            "category":"Personal",
            "subcategory":"Barber",
            "type":"Services"
        }
    ],
    "sg:phone":"+1   ",
    "sg:postcode":"19601",
    "sg:province":"PA",
    "sg:tags":[
        "shop"
    ],
    "wof:name":"Moores Danny Barber Shop",
    "wof:placetype":"venue"
},
  "geometry": {"coordinates":[-75.93440099999999,40.346095],"type":"Point"}
}