{
  "type": "Feature",
  "properties": {
    "iso:country":"US",
    "sg:address":"1035 Barkeyville Rd",
    "sg:city":"Grove City",
    "sg:classifiers":[
        {
            "category":"Building & Trades",
            "subcategory":"Landscaping Services",
            "type":"Services"
        }
    ],
    "sg:phone":"+1   ",
    "sg:postcode":"16127",
    "sg:province":"PA",
    "sg:tags":[
        "landscape"
    ],
    "wof:name":"McClelland Landscaping",
    "wof:placetype":"venue"
},
  "geometry": {"coordinates":[-80.03487,41.176915],"type":"Point"}
}