{
  "type": "Feature",
  "properties": {
    "addr:full":"142 S Easton Rd Glenside PA 19038",
    "addr:housenumber":"142",
    "addr:postcode":"19038",
    "addr:street":"S Easton Rd",
    "iso:country":"US",
    "sg:address":"142 S Easton Rd",
    "sg:city":"Glenside",
    "sg:classifiers":[
        {
            "category":"Shopping",
            "subcategory":"Gifts & Souvenirs",
            "type":"Retail Goods"
        }
    ],
    "sg:phone":"+1 215 884 4477",
    "sg:postcode":"19038",
    "sg:province":"PA",
    "sg:tags":[
        "party",
        "supply"
    ],
    "wof:name":"Great American Party Store",
    "wof:placetype":"venue"
},
  "geometry": {"coordinates":[-75.15348899999999,40.100554],"type":"Point"}
}