{
  "type": "Feature",
  "properties": {
    "iso:country":"US",
    "sg:address":"2820 Newcomer Rd",
    "sg:city":"Chambersburg",
    "sg:phone":"+1 717 263 2975",
    "sg:postcode":"17202",
    "sg:province":"PA",
    "sg:website":"http://www.wiseguypaintball.net",
    "wof:name":"Wiseguy Paintball",
    "wof:placetype":"venue"
},
  "geometry": {"coordinates":[-77.61818599999999,39.88695],"type":"Point"}
}