{
  "type": "Feature",
  "properties": {
    "addr:full":"1409 S Main St Mansfield PA 16933",
    "addr:housenumber":"1409",
    "addr:postcode":"16933",
    "addr:street":"S Main St",
    "iso:country":"US",
    "sg:address":"1409 S Main St",
    "sg:city":"Mansfield",
    "sg:classifiers":[
        {
            "category":"Autos & Motor Vehicles",
            "subcategory":"Auto Supplies",
            "type":"Retail Goods"
        },
        {
            "category":"Retail",
            "subcategory":"Auto Repair",
            "type":"Services"
        }
    ],
    "sg:phone":"+1 570 662 0920",
    "sg:postcode":"16933",
    "sg:province":"PA",
    "sg:tags":[
        "exhaust",
        "oil",
        "tire",
        "automobile",
        "system",
        "lube",
        "part",
        "brake",
        "muffler"
    ],
    "sg:website":"http://www.monro.com",
    "wof:name":"Monro Muffler Brake & Service",
    "wof:placetype":"venue"
},
  "geometry": {"coordinates":[-77.06970099999999,41.779719],"type":"Point"}
}