{
  "type": "Feature",
  "properties": {
    "iso:country":"US",
    "sg:address":"155 E Dauphin St",
    "sg:city":"Enola",
    "sg:classifiers":[
        {
            "category":"Retail",
            "subcategory":"Self-service Laundry",
            "type":"Services"
        }
    ],
    "sg:phone":"+1 717 761 3251",
    "sg:postcode":"17025",
    "sg:province":"PA",
    "wof:name":"Morris Laundromation Svc Inc",
    "wof:placetype":"venue"
},
  "geometry": {"coordinates":[-76.931802,40.294347],"type":"Point"}
}