{
  "type": "Feature",
  "properties": {
    "iso:country":"US",
    "sg:address":"200 Stoops Dr",
    "sg:city":"Monongahela",
    "sg:classifiers":[
        {
            "category":"Professional",
            "type":"Services"
        }
    ],
    "sg:phone":"+1   ",
    "sg:postcode":"15063",
    "sg:province":"PA",
    "wof:name":"Cpsr Acssociates LLC",
    "wof:placetype":"venue"
},
  "geometry": {"coordinates":[-79.92331299999999,40.163623],"type":"Point"}
}