{
  "type": "Feature",
  "properties": {
    "addr:full":"803 Arch St Ashland PA 17921",
    "addr:housenumber":"803",
    "addr:postcode":"17921",
    "addr:street":"Arch St",
    "iso:country":"US",
    "sg:address":"803 Arch St",
    "sg:city":"Ashland",
    "sg:classifiers":[
        {
            "category":"Building & Trades",
            "subcategory":"Construction",
            "type":"Services"
        }
    ],
    "sg:phone":"+1 570 875 1951",
    "sg:postcode":"17921",
    "sg:province":"PA",
    "sg:tags":[
        "restoration",
        "cleaning",
        "patio",
        "deck"
    ],
    "wof:name":"Re Nu High Pressure Cleaning",
    "wof:placetype":"venue"
},
  "geometry": {"coordinates":[-76.342547,40.783702],"type":"Point"}
}