{
  "type": "Feature",
  "properties": {
    "iso:country":"US",
    "sg:address":"738 Dekalb Pike",
    "sg:city":"Blue Bell",
    "sg:classifiers":[
        {
            "category":"Health Services",
            "subcategory":"Optometrist",
            "type":"Services"
        },
        {
            "category":"Shopping",
            "subcategory":"Optician",
            "type":"Retail Goods"
        }
    ],
    "sg:phone":"+1 610 278 9026",
    "sg:postcode":"19422",
    "sg:province":"PA",
    "sg:tags":[
        "eyewear"
    ],
    "wof:name":"Psillos Optique Optmtrst",
    "wof:placetype":"venue"
},
  "geometry": {"coordinates":[-75.288498,40.1688],"type":"Point"}
}