{
  "type": "Feature",
  "properties": {
    "addr:full":"6757 Greene St Ste 100 Philadelphia PA 19119",
    "addr:housenumber":"6757",
    "addr:postcode":"19119",
    "addr:street":"Greene St Ste 100",
    "iso:country":"US",
    "sg:address":"6757 Greene St Ste 100",
    "sg:city":"Philadelphia",
    "sg:classifiers":[
        {
            "category":"Place Of Worship",
            "subcategory":"Church",
            "type":"Public Place"
        },
        {
            "category":"Place Of Worship",
            "type":"Public Place"
        }
    ],
    "sg:phone":"+1 215 438 2825",
    "sg:postcode":"19119",
    "sg:province":"PA",
    "sg:tags":[
        "churches-presbyterian-arp",
        "churches-presbyterian"
    ],
    "sg:website":"http://www.pcwoodbury.com",
    "wof:name":"Summit Presbyterian Church",
    "wof:placetype":"venue"
},
  "geometry": {"coordinates":[-75.194115,40.045222],"type":"Point"}
}