{
  "type": "Feature",
  "properties": {
    "addr:full":"520 Baintree Run Downingtown PA 19335",
    "addr:housenumber":"520",
    "addr:postcode":"19335",
    "addr:street":"Baintree Run",
    "iso:country":"US",
    "sg:address":"520 Baintree Run",
    "sg:city":"Downingtown",
    "sg:classifiers":[
        {
            "category":"Health Services",
            "subcategory":"Doctor",
            "type":"Services"
        }
    ],
    "sg:phone":"+1   ",
    "sg:postcode":"19335",
    "sg:province":"PA",
    "sg:tags":[
        "medical"
    ],
    "wof:name":"Richard Wilford",
    "wof:placetype":"venue"
},
  "geometry": {"coordinates":[-75.691379,40.037614],"type":"Point"}
}