{
  "type": "Feature",
  "properties": {
    "iso:country":"US",
    "sg:address":"3440 Schuylkill Rd",
    "sg:city":"Spring City",
    "sg:classifiers":[
        {
            "category":"Home & Garden",
            "subcategory":"Carpets & Floor Coverings",
            "type":"Retail Goods"
        }
    ],
    "sg:phone":"+1 610 948 3701",
    "sg:postcode":"19475",
    "sg:province":"PA",
    "sg:tags":[
        "material"
    ],
    "wof:name":"Crisman Hardwood Flooring Co",
    "wof:placetype":"venue"
},
  "geometry": {"coordinates":[-75.557241,40.169569],"type":"Point"}
}