{
  "type": "Feature",
  "properties": {
    "addr:full":"24 S McKean Ave Donora PA 15033",
    "addr:housenumber":"24",
    "addr:postcode":"15033",
    "addr:street":"S Mckean Ave",
    "iso:country":"US",
    "sg:address":"24 S McKean Ave",
    "sg:city":"Donora",
    "sg:classifiers":[
        {
            "category":"Personal",
            "type":"Services"
        },
        {
            "category":"Retail",
            "subcategory":"Auto Repair",
            "type":"Services"
        }
    ],
    "sg:phone":"+1 724 379 9441",
    "sg:postcode":"15033",
    "sg:province":"PA",
    "sg:tags":[
        "body",
        "shop",
        "towing"
    ],
    "wof:name":"Fast Eddie's Body Work",
    "wof:placetype":"venue"
},
  "geometry": {"coordinates":[-79.86032400000001,40.169482],"type":"Point"}
}