{
  "type": "Feature",
  "properties": {
    "addr:full":"1064 Country Hill Dr Harrisburg PA 17111",
    "addr:housenumber":"1064",
    "addr:postcode":"17111",
    "addr:street":"Country Hill Dr",
    "iso:country":"US",
    "sg:address":"1064 Country Hill Dr",
    "sg:city":"Harrisburg",
    "sg:classifiers":[
        {
            "category":"Professional",
            "subcategory":"Business Services",
            "type":"Services"
        }
    ],
    "sg:phone":"+1   ",
    "sg:postcode":"17111",
    "sg:province":"PA",
    "wof:name":"Kline Musical Enterprise",
    "wof:placetype":"venue"
},
  "geometry": {"coordinates":[-76.786299,40.28601],"type":"Point"}
}