{
  "type": "Feature",
  "properties": {
    "addr:full":"521 W Main St Lansdale PA 19446",
    "addr:housenumber":"521",
    "addr:postcode":"19446",
    "addr:street":"W Main St",
    "iso:country":"US",
    "sg:address":"521 W Main St",
    "sg:city":"Lansdale",
    "sg:classifiers":[
        {
            "category":"Professional",
            "subcategory":"Computer Services",
            "type":"Services"
        }
    ],
    "sg:phone":"+1 215 368 6403",
    "sg:postcode":"19446",
    "sg:province":"PA",
    "sg:tags":[
        "internet"
    ],
    "wof:name":"Robert D Lowrie",
    "wof:placetype":"venue"
},
  "geometry": {"coordinates":[-75.289507,40.245127],"type":"Point"}
}