{
  "type": "Feature",
  "properties": {
    "addr:full":"109 N Eagle Rd Havertown PA 19083",
    "addr:housenumber":"109",
    "addr:postcode":"19083",
    "addr:street":"N Eagle Rd",
    "iso:country":"US",
    "sg:address":"109 N Eagle Rd",
    "sg:city":"Havertown",
    "sg:classifiers":[
        {
            "category":"Professional",
            "subcategory":"Lawyer & Legal Services",
            "type":"Services"
        }
    ],
    "sg:phone":"+1 610 446 1200",
    "sg:postcode":"19083",
    "sg:province":"PA",
    "sg:tags":[
        "attorney"
    ],
    "wof:name":"Matkoff Shengold Burke London",
    "wof:placetype":"venue"
},
  "geometry": {"coordinates":[-75.319337,39.974079],"type":"Point"}
}