{
  "type": "Feature",
  "properties": {
    "iso:country":"US",
    "sg:address":"124 Parker Ave",
    "sg:city":"Easton",
    "sg:classifiers":[
        {
            "category":"Shopping",
            "subcategory":"Music",
            "type":"Retail Goods"
        }
    ],
    "sg:phone":"+1   ",
    "sg:postcode":"18042",
    "sg:province":"PA",
    "wof:name":"Center Stage Records LLC",
    "wof:placetype":"venue"
},
  "geometry": {"coordinates":[-75.200582,40.711179],"type":"Point"}
}