{
  "type": "Feature",
  "properties": {
    "addr:full":"2275 Swallow Hill Rd # 400 Pittsburgh PA 15220",
    "addr:housenumber":"2275",
    "addr:postcode":"15220",
    "addr:street":"Swallow Hill Rd # 400",
    "iso:country":"US",
    "sg:address":"2275 Swallow Hill Rd # 400",
    "sg:city":"Pittsburgh",
    "sg:classifiers":[
        {
            "category":"Professional",
            "subcategory":"Engineering",
            "type":"Services"
        }
    ],
    "sg:phone":"+1 412 276 7175",
    "sg:postcode":"15220",
    "sg:province":"PA",
    "sg:tags":[
        "consulting",
        "engineer"
    ],
    "sg:website":"http://www.nelsonengineeringsales.com",
    "wof:name":"Nelson Engineering Sales Co",
    "wof:placetype":"venue"
},
  "geometry": {"coordinates":[-80.07411999999999,40.389481],"type":"Point"}
}