{
  "type": "Feature",
  "properties": {
    "iso:country":"US",
    "sg:address":"204 N Main St",
    "sg:city":"Moscow",
    "sg:classifiers":[
        {
            "category":"Education",
            "subcategory":"Dance Studio",
            "type":"Public Place"
        }
    ],
    "sg:phone":"+1 570 842 7795",
    "sg:postcode":"18444",
    "sg:province":"PA",
    "sg:tags":[
        "instruction",
        "dancing"
    ],
    "wof:name":"Ardito School Of Dance",
    "wof:placetype":"venue"
},
  "geometry": {"coordinates":[-75.518598,41.338141],"type":"Point"}
}