{
  "type": "Feature",
  "properties": {
    "iso:country":"US",
    "sg:address":"1201 Heeney Ave",
    "sg:city":"Johnstown",
    "sg:classifiers":[
        {
            "category":"Real Estate",
            "subcategory":"Real Estate Operator",
            "type":"Services"
        }
    ],
    "sg:phone":"+1 814 288 3505",
    "sg:postcode":"15904",
    "sg:province":"PA",
    "sg:tags":[
        "building",
        "apartment"
    ],
    "wof:name":"Belmont Heights Apartments",
    "wof:placetype":"venue"
},
  "geometry": {"coordinates":[-78.901667,40.29058],"type":"Point"}
}