{
  "type": "Feature",
  "properties": {
    "addr:full":"18 Hawthorne Ln Levittown PA 19055",
    "addr:housenumber":"18",
    "addr:postcode":"19055",
    "addr:street":"Hawthorne Ln",
    "iso:country":"US",
    "sg:address":"18 Hawthorne Ln",
    "sg:city":"Levittown",
    "sg:classifiers":[
        {
            "category":"Utilities",
            "subcategory":"Electric",
            "type":"Services"
        }
    ],
    "sg:phone":"+1   ",
    "sg:postcode":"19055",
    "sg:province":"PA",
    "wof:name":"Choice Electric Inc",
    "wof:placetype":"venue"
},
  "geometry": {"coordinates":[-74.83676,40.16046],"type":"Point"}
}