{
  "type": "Feature",
  "properties": {
    "iso:country":"US",
    "sg:address":"3826 Broadway",
    "sg:city":"Allentown",
    "sg:classifiers":[
        {
            "category":"Retail",
            "subcategory":"Auto Repair",
            "type":"Services"
        }
    ],
    "sg:phone":"+1 610 398 3220",
    "sg:postcode":"18104",
    "sg:province":"PA",
    "sg:tags":[
        "repairing",
        "automobile"
    ],
    "wof:name":"Cetronia Auto Repair Service",
    "wof:placetype":"venue"
},
  "geometry": {"coordinates":[-75.537598,40.584099],"type":"Point"}
}