{
  "type": "Feature",
  "properties": {
    "iso:country":"US",
    "sg:address":"2502 Edgemont St",
    "sg:city":"Philadelphia",
    "sg:classifiers":[
        {
            "category":"Manufacturing",
            "subcategory":"Metals",
            "type":"Manufacturing & Wholesale Goods"
        }
    ],
    "sg:phone":"+1 215 426 5225",
    "sg:postcode":"19125",
    "sg:province":"PA",
    "sg:tags":[
        "fire",
        "hydrant"
    ],
    "sg:website":"www.waterwarecorp.com",
    "wof:name":"Waterware",
    "wof:placetype":"venue"
},
  "geometry": {"coordinates":[-75.11801,39.976148],"type":"Point"}
}