{
  "type": "Feature",
  "properties": {
    "addr:full":"61 N Main St Shrewsbury PA 17361",
    "addr:housenumber":"61",
    "addr:postcode":"17361",
    "addr:street":"N Main St",
    "iso:country":"US",
    "sg:address":"61 N Main St",
    "sg:city":"Shrewsbury",
    "sg:classifiers":[
        {
            "category":"Professional",
            "subcategory":"Management & Consulting",
            "type":"Services"
        }
    ],
    "sg:phone":"+1   ",
    "sg:postcode":"17361",
    "sg:province":"PA",
    "sg:tags":[
        "retail",
        "direct",
        "sales"
    ],
    "wof:name":"Global Network Development",
    "wof:placetype":"venue"
},
  "geometry": {"coordinates":[-76.678347,39.759864],"type":"Point"}
}