{
  "type": "Feature",
  "properties": {
    "addr:full":"6451 Oxford Ave Philadelphia PA 19111",
    "addr:housenumber":"6451",
    "addr:postcode":"19111",
    "addr:street":"Oxford Ave",
    "iso:country":"US",
    "sg:address":"6451 Oxford Ave",
    "sg:city":"Philadelphia",
    "sg:classifiers":[
        {
            "category":"Real Estate",
            "subcategory":"Real Estate Operator",
            "type":"Services"
        }
    ],
    "sg:phone":"+1 215 728 6885",
    "sg:postcode":"19111",
    "sg:province":"PA",
    "sg:tags":[
        "apartment"
    ],
    "wof:name":"Oxford House Apartments",
    "wof:placetype":"venue"
},
  "geometry": {"coordinates":[-75.088019,40.045896],"type":"Point"}
}