{
  "type": "Feature",
  "properties": {
    "iso:country":"US",
    "sg:address":"702 N 7th St",
    "sg:city":"Allentown",
    "sg:classifiers":[
        {
            "category":"Banks & Credit Unions",
            "subcategory":"Bank",
            "type":"Services"
        }
    ],
    "sg:phone":"+1   ",
    "sg:postcode":"18102",
    "sg:province":"PA",
    "sg:tags":[
        "national"
    ],
    "wof:name":"Tilghman Street",
    "wof:placetype":"venue"
},
  "geometry": {"coordinates":[-75.47670599999999,40.612572],"type":"Point"}
}