{
  "type": "Feature",
  "properties": {
    "iso:country":"US",
    "sg:address":"528 W James St",
    "sg:city":"Lancaster",
    "sg:classifiers":[
        {
            "category":"Retail",
            "subcategory":"Animal Services",
            "type":"Services"
        }
    ],
    "sg:phone":"+1 717 509 5527",
    "sg:postcode":"17603",
    "sg:province":"PA",
    "sg:tags":[
        "pet",
        "grooming",
        "washing"
    ],
    "wof:name":"Michelle's Dog Grooming",
    "wof:placetype":"venue"
},
  "geometry": {"coordinates":[-76.316327,40.044944],"type":"Point"}
}