{
  "type": "Feature",
  "properties": {
    "iso:country":"US",
    "sg:address":"4059 Washington Rd",
    "sg:city":"Canonsburg",
    "sg:classifiers":[
        {
            "category":"Restaurant",
            "type":"Food & Drink"
        }
    ],
    "sg:menulink":"http://www.allmenus.com/pa/peters/32975-atrias/menu/",
    "sg:phone":"+1 724 942 1108",
    "sg:postcode":"15317",
    "sg:province":"PA",
    "sg:tags":[
        "american"
    ],
    "wof:name":"Atria's",
    "wof:placetype":"venue"
},
  "geometry": {"coordinates":[-80.12884,40.26693],"type":"Point"}
}