{
  "type": "Feature",
  "properties": {
    "iso:country":"US",
    "sg:address":"202 Lone Oak Dr",
    "sg:city":"Bryn Mawr",
    "sg:classifiers":[
        {
            "category":"Professional",
            "type":"Services"
        }
    ],
    "sg:phone":"+1   ",
    "sg:postcode":"19010",
    "sg:province":"PA",
    "wof:name":"Star Foods Inc",
    "wof:placetype":"venue"
},
  "geometry": {"coordinates":[-75.342956,40.004289],"type":"Point"}
}