{
  "type": "Feature",
  "properties": {
    "addr:full":"300 W Trenton Ave Morrisville PA 19067",
    "addr:housenumber":"300",
    "addr:postcode":"19067",
    "addr:street":"W Trenton Ave",
    "iso:country":"US",
    "sg:address":"300 W Trenton Ave",
    "sg:city":"Morrisville",
    "sg:classifiers":[
        {
            "category":"Banks & Credit Unions",
            "subcategory":"Investment Brokerage",
            "type":"Services"
        }
    ],
    "sg:phone":"+1 215 295 4747",
    "sg:postcode":"19067",
    "sg:province":"PA",
    "sg:tags":[
        "consultant",
        "planning",
        "financial"
    ],
    "wof:name":"Associated Planning Group Inc",
    "wof:placetype":"venue"
},
  "geometry": {"coordinates":[-74.79260499999999,40.212025],"type":"Point"}
}