{
  "type": "Feature",
  "properties": {
    "iso:country":"US",
    "sg:address":"3401 Aramingo Ave",
    "sg:city":"Philadelphia",
    "sg:classifiers":[
        {
            "category":"Shopping",
            "subcategory":"Hobbies, Toys, & Games",
            "type":"Retail Goods"
        }
    ],
    "sg:phone":"+1 215 423 2680",
    "sg:postcode":"19134",
    "sg:province":"PA",
    "sg:tags":[
        "toy",
        "store"
    ],
    "sg:website":"www.toysrus.com",
    "wof:name":"Toys R Us",
    "wof:placetype":"venue"
},
  "geometry": {"coordinates":[-75.100317,39.990555],"type":"Point"}
}