{
  "type": "Feature",
  "properties": {
    "addr:full":"7520 Castor Ave Philadelphia PA 19152",
    "addr:housenumber":"7520",
    "addr:postcode":"19152",
    "addr:street":"Castor Ave",
    "iso:country":"US",
    "sg:address":"7520 Castor Ave",
    "sg:city":"Philadelphia",
    "sg:classifiers":[
        {
            "category":"Health Services",
            "subcategory":"Doctor",
            "type":"Services"
        }
    ],
    "sg:phone":"+1 215 745 5757",
    "sg:postcode":"19152",
    "sg:province":"PA",
    "sg:tags":[
        "dentist"
    ],
    "wof:name":"Family Dental Care",
    "wof:placetype":"venue"
},
  "geometry": {"coordinates":[-75.062933,40.054564],"type":"Point"}
}