{
  "type": "Feature",
  "properties": {
    "iso:country":"US",
    "sg:address":"21 Brinker Dr",
    "sg:city":"Doylestown",
    "sg:classifiers":[
        {
            "category":"Building & Trades",
            "subcategory":"Construction",
            "type":"Services"
        }
    ],
    "sg:phone":"+1   ",
    "sg:postcode":"18914",
    "sg:province":"PA",
    "sg:tags":[
        "addition",
        "home",
        "remodeling",
        "family"
    ],
    "wof:name":"Tri County Builders Inc",
    "wof:placetype":"venue"
},
  "geometry": {"coordinates":[-75.154718,40.278876],"type":"Point"}
}