{
  "type": "Feature",
  "properties": {
    "iso:country":"US",
    "sg:address":"541 Germantown Pike",
    "sg:city":"Lafayette Hill",
    "sg:classifiers":[
        {
            "category":"Home & Garden",
            "subcategory":"Building Materials",
            "type":"Retail Goods"
        }
    ],
    "sg:phone":"+1 610 828 5747",
    "sg:postcode":"19444",
    "sg:province":"PA",
    "sg:tags":[
        "paint",
        "floor",
        "covering"
    ],
    "wof:name":"Sherwin-Williams Paints",
    "wof:placetype":"venue"
},
  "geometry": {"coordinates":[-75.25167999999999,40.086334],"type":"Point"}
}