{
  "type": "Feature",
  "properties": {
    "iso:country":"US",
    "sg:address":"3601 N Progress Ave",
    "sg:city":"Harrisburg",
    "sg:classifiers":[
        {
            "category":"Health Services",
            "subcategory":"Doctor",
            "type":"Services"
        }
    ],
    "sg:phone":"+1 717 652 7266",
    "sg:postcode":"17110",
    "sg:province":"PA",
    "sg:tags":[
        "physician",
        "surgeon"
    ],
    "wof:name":"Community Medical Assoc PC",
    "wof:placetype":"venue"
},
  "geometry": {"coordinates":[-76.856892,40.318805],"type":"Point"}
}