{
  "type": "Feature",
  "properties": {
    "iso:country":"US",
    "sg:address":"100 E Pomfret St",
    "sg:city":"Carlisle",
    "sg:classifiers":[
        {
            "category":"Social Services",
            "subcategory":"Child Care",
            "type":"Services"
        }
    ],
    "sg:phone":"+1 717 243 1528",
    "sg:postcode":"17013",
    "sg:province":"PA",
    "sg:tags":[
        "elementary",
        "school",
        "day"
    ],
    "sg:website":"www.carlisleearlyeducationcenter...",
    "wof:name":"Carlisle Early Education Center",
    "wof:placetype":"venue"
},
  "geometry": {"coordinates":[-77.186699,40.1996],"type":"Point"}
}