{
  "type": "Feature",
  "properties": {
    "iso:country":"US",
    "sg:address":"943 Main St",
    "sg:city":"Pennsburg",
    "sg:classifiers":[
        {
            "category":"Building & Trades",
            "subcategory":"Construction",
            "type":"Services"
        }
    ],
    "sg:phone":"+1   ",
    "sg:postcode":"18073",
    "sg:province":"PA",
    "sg:tags":[
        "roofing",
        "siding",
        "work"
    ],
    "wof:name":"Ed Gindlesperger",
    "wof:placetype":"venue"
},
  "geometry": {"coordinates":[-75.48941499999999,40.386876],"type":"Point"}
}