{
  "type": "Feature",
  "properties": {
    "iso:country":"US",
    "sg:address":"773 W Huntingdon St",
    "sg:city":"Philadelphia",
    "sg:classifiers":[
        {
            "category":"Restaurant",
            "type":"Food & Drink"
        }
    ],
    "sg:phone":"+1   ",
    "sg:postcode":"19133",
    "sg:province":"PA",
    "sg:tags":[
        "eating"
    ],
    "wof:name":"China Wok",
    "wof:placetype":"venue"
},
  "geometry": {"coordinates":[-75.145112,39.99115],"type":"Point"}
}