{
  "type": "Feature",
  "properties": {
    "addr:full":"905 Harrison St Allentown PA 18103",
    "addr:housenumber":"905",
    "addr:postcode":"18103",
    "addr:street":"Harrison St",
    "iso:country":"US",
    "sg:address":"905 Harrison St",
    "sg:city":"Allentown",
    "sg:classifiers":[
        {
            "category":"Professional",
            "subcategory":"Management & Consulting",
            "type":"Services"
        }
    ],
    "sg:phone":"+1 610 770 1265",
    "sg:postcode":"18103",
    "sg:province":"PA",
    "sg:tags":[
        "science",
        "consultant",
        "academic"
    ],
    "wof:name":"National Environmental Service",
    "wof:placetype":"venue"
},
  "geometry": {"coordinates":[-75.472431,40.593585],"type":"Point"}
}