{
  "type": "Feature",
  "properties": {
    "iso:country":"US",
    "sg:address":"1000 Corporate Dr",
    "sg:city":"Canonsburg",
    "sg:classifiers":[
        {
            "category":"Travel",
            "subcategory":"Hotels & Motels",
            "type":"Entertainment"
        }
    ],
    "sg:phone":"+1 724 743 5000",
    "sg:postcode":"15317",
    "sg:province":"PA",
    "wof:name":"Hilton Garden Inn Pittsburgh Southpointe",
    "wof:placetype":"venue"
},
  "geometry": {"coordinates":[-80.173203,40.298],"type":"Point"}
}