{
  "type": "Feature",
  "properties": {
    "addr:full":"731 Hedgerow Dr Broomall PA 19008",
    "addr:housenumber":"731",
    "addr:postcode":"19008",
    "addr:street":"Hedgerow Dr",
    "iso:country":"US",
    "sg:address":"731 Hedgerow Dr",
    "sg:city":"Broomall",
    "sg:classifiers":[
        {
            "category":"Building & Trades",
            "subcategory":"Construction",
            "type":"Services"
        }
    ],
    "sg:phone":"+1 610 356 5632",
    "sg:postcode":"19008",
    "sg:province":"PA",
    "sg:tags":[
        "contractor"
    ],
    "wof:name":"Mario Carassai & Son Inc",
    "wof:placetype":"venue"
},
  "geometry": {"coordinates":[-75.36271499999999,39.960164],"type":"Point"}
}