{
  "type": "Feature",
  "properties": {
    "iso:country":"US",
    "sg:address":"127 Myers Rd",
    "sg:city":"Carrolltown",
    "sg:classifiers":[
        {
            "category":"Retail",
            "subcategory":"Auto Repair",
            "type":"Services"
        }
    ],
    "sg:phone":"+1 814 344 8054",
    "sg:postcode":"15722",
    "sg:province":"PA",
    "sg:tags":[
        "automobile",
        "inspection"
    ],
    "wof:name":"C & B Car Care",
    "wof:placetype":"venue"
},
  "geometry": {"coordinates":[-78.726563,40.602863],"type":"Point"}
}