{
  "type": "Feature",
  "properties": {
    "iso:country":"US",
    "sg:address":"7 Spring St",
    "sg:city":"Paoli",
    "sg:classifiers":[
        {
            "category":"Retail",
            "subcategory":"Auto Repair",
            "type":"Services"
        }
    ],
    "sg:phone":"+1 610 644 2060",
    "sg:postcode":"19301",
    "sg:province":"PA",
    "sg:tags":[
        "automotive",
        "general"
    ],
    "sg:website":"www.paoliautorepair.com",
    "wof:name":"Paoli Auto Repair",
    "wof:placetype":"venue"
},
  "geometry": {"coordinates":[-75.48517699999999,40.041771],"type":"Point"}
}