{
  "type": "Feature",
  "properties": {
    "addr:full":"120 Gibraltar Rd Ste 109 Horsham PA 19044",
    "addr:housenumber":"120",
    "addr:postcode":"19044",
    "addr:street":"Gibraltar Rd Ste 109",
    "iso:country":"US",
    "sg:address":"120 Gibraltar Rd Ste 109",
    "sg:city":"Horsham",
    "sg:classifiers":[
        {
            "category":"Building & Trades",
            "subcategory":"Cleaning & Sanitation",
            "type":"Services"
        },
        {
            "category":"Retail",
            "subcategory":"Laundry & Dry Cleaning",
            "type":"Services"
        }
    ],
    "sg:phone":"+1 215 957 5830",
    "sg:postcode":"19044",
    "sg:province":"PA",
    "sg:tags":[
        "cleaner",
        "janitorial",
        "house"
    ],
    "wof:name":"Holdon Building",
    "wof:placetype":"venue"
},
  "geometry": {"coordinates":[-75.13054,40.170507],"type":"Point"}
}