{
  "type": "Feature",
  "properties": {
    "iso:country":"US",
    "sg:address":"1448 Chislett St",
    "sg:city":"Pittsburgh",
    "sg:classifiers":[
        {
            "category":"Building & Trades",
            "subcategory":"Landscaping Services",
            "type":"Services"
        }
    ],
    "sg:phone":"+1   ",
    "sg:postcode":"15206",
    "sg:province":"PA",
    "sg:tags":[
        "landscape"
    ],
    "wof:name":"Tirone Pietropaolo Landscaping",
    "wof:placetype":"venue"
},
  "geometry": {"coordinates":[-79.927915,40.481593],"type":"Point"}
}