{
  "type": "Feature",
  "properties": {
    "iso:country":"US",
    "sg:address":"503 S Main Ave",
    "sg:city":"Scranton",
    "sg:classifiers":[
        {
            "category":"Personal",
            "type":"Services"
        }
    ],
    "sg:phone":"+1 570 342 5976",
    "sg:postcode":"18504",
    "sg:province":"PA",
    "sg:tags":[
        "hair",
        "replacement"
    ],
    "wof:name":"Mileto's Hair Replacement",
    "wof:placetype":"venue"
},
  "geometry": {"coordinates":[-75.685451,41.406291],"type":"Point"}
}