{
  "type": "Feature",
  "properties": {
    "iso:country":"US",
    "sg:address":"2555 Cape Horn Rd",
    "sg:city":"Red Lion",
    "sg:classifiers":[
        {
            "category":"Health Services",
            "subcategory":"Chiropractor",
            "type":"Services"
        }
    ],
    "sg:phone":"+1 717 840 0888",
    "sg:postcode":"17356",
    "sg:province":"PA",
    "sg:tags":[
        "chiropractic"
    ],
    "wof:name":"Red Lion Chiropractic",
    "wof:placetype":"venue"
},
  "geometry": {"coordinates":[-76.621719,39.909946],"type":"Point"}
}