{
  "type": "Feature",
  "properties": {
    "iso:country":"US",
    "sg:address":"550 W Walnut St",
    "sg:city":"Shamokin",
    "sg:classifiers":[
        {
            "category":"Health Services",
            "subcategory":"Doctor",
            "type":"Services"
        }
    ],
    "sg:phone":"+1   ",
    "sg:postcode":"17872",
    "sg:province":"PA",
    "sg:tags":[
        "medical"
    ],
    "wof:name":"Jon D Sten MD",
    "wof:placetype":"venue"
},
  "geometry": {"coordinates":[-76.56326300000001,40.789704],"type":"Point"}
}