{
  "type": "Feature",
  "properties": {
    "iso:country":"US",
    "sg:address":"56 Wyoming Valley Mall",
    "sg:city":"Wilkes Barre",
    "sg:classifiers":[
        {
            "category":"Shopping",
            "subcategory":"Clothing, Apparel, & Fashions",
            "type":"Retail Goods"
        }
    ],
    "sg:phone":"+1 570 820 8340",
    "sg:postcode":"18702",
    "sg:province":"PA",
    "wof:name":"B Moss",
    "wof:placetype":"venue"
},
  "geometry": {"coordinates":[-75.842456,41.249866],"type":"Point"}
}