{
  "type": "Feature",
  "properties": {
    "addr:full":"1835 Market St Fl 14 Philadelphia PA 19103",
    "addr:housenumber":"1835;14",
    "addr:postcode":"19103",
    "addr:street":"Market St Fl",
    "iso:country":"US",
    "sg:address":"1835 Market St Fl 14",
    "sg:city":"Philadelphia",
    "sg:classifiers":[
        {
            "category":"Professional",
            "subcategory":"Lawyer & Legal Services",
            "type":"Services"
        }
    ],
    "sg:phone":"+1 215 563 4470",
    "sg:postcode":"19103",
    "sg:province":"PA",
    "wof:name":"Equi Glenn C",
    "wof:placetype":"venue"
},
  "geometry": {"coordinates":[-75.170601,39.9533],"type":"Point"}
}