{
  "type": "Feature",
  "properties": {
    "addr:full":"311 S Craig St Pittsburgh PA 15213",
    "addr:housenumber":"311",
    "addr:postcode":"15213",
    "addr:street":"S Craig St",
    "iso:country":"US",
    "sg:address":"311 S Craig St",
    "sg:city":"Pittsburgh",
    "sg:classifiers":[
        {
            "category":"Social Services",
            "type":"Services"
        }
    ],
    "sg:phone":"+1 412 687 7180",
    "sg:postcode":"15213",
    "sg:province":"PA",
    "sg:tags":[
        "counseling"
    ],
    "wof:name":"Jill Balagur-Conn",
    "wof:placetype":"venue"
},
  "geometry": {"coordinates":[-79.9487,40.445336],"type":"Point"}
}