{
  "type": "Feature",
  "properties": {
    "addr:full":"777 W County Line Rd Hatboro PA 19040",
    "addr:housenumber":"777",
    "addr:postcode":"19040",
    "addr:street":"W County Line Rd",
    "iso:country":"US",
    "sg:address":"777 W County Line Rd",
    "sg:city":"Hatboro",
    "sg:classifiers":[
        {
            "category":"Health Services",
            "subcategory":"Nursing And Care Facility",
            "type":"Services"
        }
    ],
    "sg:phone":"+1   ",
    "sg:postcode":"19040",
    "sg:province":"PA",
    "sg:tags":[
        "intermediate"
    ],
    "wof:name":"Arden Courts Warminster",
    "wof:placetype":"venue"
},
  "geometry": {"coordinates":[-75.091961,40.183673],"type":"Point"}
}