{
  "type": "Feature",
  "properties": {
    "iso:country":"US",
    "sg:address":"1411 E Carson St",
    "sg:city":"Pittsburgh",
    "sg:classifiers":[
        {
            "category":"Shopping",
            "subcategory":"Gifts & Souvenirs",
            "type":"Retail Goods"
        }
    ],
    "sg:phone":"+1 412 381 5632",
    "sg:postcode":"15203",
    "sg:province":"PA",
    "wof:name":"Treasure Gifts",
    "wof:placetype":"venue"
},
  "geometry": {"coordinates":[-79.98348300000001,40.428887],"type":"Point"}
}