{
  "type": "Feature",
  "properties": {
    "iso:country":"US",
    "sg:address":"406 Fitzwater St Apt A",
    "sg:city":"Philadelphia",
    "sg:classifiers":[
        {
            "category":"Professional",
            "subcategory":"Art Services",
            "type":"Services"
        }
    ],
    "sg:phone":"+1 215 925 3732",
    "sg:postcode":"19147",
    "sg:province":"PA",
    "sg:tags":[
        "photographers-portrait"
    ],
    "wof:name":"Jeffrey Totaro Photographer",
    "wof:placetype":"venue"
},
  "geometry": {"coordinates":[-75.149756,39.939167],"type":"Point"}
}