{
  "type": "Feature",
  "properties": {
    "iso:country":"US",
    "sg:address":"602 Moraine Pointe Plz",
    "sg:city":"Butler",
    "sg:classifiers":[
        {
            "category":"Shopping",
            "subcategory":"Department Store",
            "type":"Retail Goods"
        }
    ],
    "sg:phone":"+1 724 283 8188",
    "sg:postcode":"16001",
    "sg:province":"PA",
    "sg:tags":[
        "shop"
    ],
    "wof:name":"Ollie's Bargain Outlet",
    "wof:placetype":"venue"
},
  "geometry": {"coordinates":[-79.950024,40.875585],"type":"Point"}
}