{
  "type": "Feature",
  "properties": {
    "addr:full":"5 Grant St North East PA 16428",
    "addr:housenumber":"5",
    "addr:postcode":"16428",
    "addr:street":"Grant St North",
    "iso:country":"US",
    "sg:address":"5 Grant St",
    "sg:city":"North East",
    "sg:classifiers":[
        {
            "category":"Banks & Credit Unions",
            "subcategory":"Bank",
            "type":"Services"
        }
    ],
    "sg:phone":"+1 814 725 1724",
    "sg:postcode":"16428",
    "sg:province":"PA",
    "wof:name":"Temco Employees FCU",
    "wof:placetype":"venue"
},
  "geometry": {"coordinates":[-79.83478700000001,42.214267],"type":"Point"}
}