{
  "type": "Feature",
  "properties": {
    "iso:country":"US",
    "sg:address":"655 S 10th St",
    "sg:city":"Allentown",
    "sg:classifiers":[
        {
            "category":"Manufacturing",
            "subcategory":"Textiles",
            "type":"Manufacturing & Wholesale Goods"
        }
    ],
    "sg:phone":"+1 610 435 7988",
    "sg:postcode":"18103",
    "sg:province":"PA",
    "sg:tags":[
        "commissioned",
        "knitter"
    ],
    "wof:name":"American Knitting Corp",
    "wof:placetype":"venue"
},
  "geometry": {"coordinates":[-75.475071,40.594953],"type":"Point"}
}