{
  "type": "Feature",
  "properties": {
    "iso:country":"US",
    "sg:address":"1122 Fillmore St",
    "sg:city":"Philadelphia",
    "sg:classifiers":[
        {
            "category":"Building & Trades",
            "subcategory":"Electrical",
            "type":"Services"
        }
    ],
    "sg:phone":"+1 215 535 0965",
    "sg:postcode":"19124",
    "sg:province":"PA",
    "sg:tags":[
        "electrician"
    ],
    "wof:name":"A.N.Grove Electrical Systems",
    "wof:placetype":"venue"
},
  "geometry": {"coordinates":[-75.08956000000001,40.022513],"type":"Point"}
}