{
  "type": "Feature",
  "properties": {
    "iso:country":"US",
    "sg:address":"2688 Old Philadelphia Pike",
    "sg:city":"Bird In Hand",
    "sg:classifiers":[
        {
            "category":"Organizations",
            "subcategory":"Religious Organization",
            "type":"Services"
        }
    ],
    "sg:phone":"+1 717 293 1233",
    "sg:postcode":"17505",
    "sg:province":"PA",
    "sg:tags":[
        "church"
    ],
    "wof:name":"Stumptown Mennonite",
    "wof:placetype":"venue"
},
  "geometry": {"coordinates":[-76.18092300000001,40.038519],"type":"Point"}
}