{
  "type": "Feature",
  "properties": {
    "addr:full":"550 9th St Pitcairn PA 15140",
    "addr:housenumber":"550",
    "addr:postcode":"15140",
    "addr:street":"9Th St",
    "iso:country":"US",
    "sg:address":"550 9th St",
    "sg:city":"Pitcairn",
    "sg:classifiers":[
        {
            "category":"Freight",
            "type":"Transportation"
        }
    ],
    "sg:phone":"+1   ",
    "sg:postcode":"15140",
    "sg:province":"PA",
    "sg:tags":[
        "operator",
        "trucking"
    ],
    "wof:name":"R W Hauling Services",
    "wof:placetype":"venue"
},
  "geometry": {"coordinates":[-79.775148,40.407526],"type":"Point"}
}