{
  "type": "Feature",
  "properties": {
    "iso:country":"US",
    "sg:address":"5740 Baum Blvd Ste 1",
    "sg:city":"Pittsburgh",
    "sg:classifiers":[
        {
            "category":"Wholesale",
            "subcategory":"Medical Equipment & Supplies",
            "type":"Manufacturing & Wholesale Goods"
        }
    ],
    "sg:phone":"+1 412 361 0544",
    "sg:postcode":"15206",
    "sg:province":"PA",
    "sg:tags":[
        "device",
        "prosthetic"
    ],
    "wof:name":"National Artificial Limb Co Inc",
    "wof:placetype":"venue"
},
  "geometry": {"coordinates":[-79.93228,40.458814],"type":"Point"}
}