{
  "type": "Feature",
  "properties": {
    "iso:country":"US",
    "sg:address":"401 E 4th St",
    "sg:city":"Bridgeport",
    "sg:classifiers":[
        {
            "category":"Building & Trades",
            "subcategory":"Construction",
            "type":"Services"
        }
    ],
    "sg:phone":"+1 610 664 9902",
    "sg:postcode":"19405",
    "sg:province":"PA",
    "sg:tags":[
        "maker",
        "cabinet"
    ],
    "sg:website":"www.pauldowns.com",
    "wof:name":"Paul Downs Cabinetmaker Inc",
    "wof:placetype":"venue"
},
  "geometry": {"coordinates":[-75.332082,40.104245],"type":"Point"}
}