{
  "type": "Feature",
  "properties": {
    "iso:country":"US",
    "sg:address":"2635 Springwood Rd",
    "sg:city":"York",
    "sg:classifiers":[
        {
            "category":"Wholesale",
            "subcategory":"Plants",
            "type":"Manufacturing & Wholesale Goods"
        }
    ],
    "sg:phone":"+1 717 741 4688",
    "sg:postcode":"17402",
    "sg:province":"PA",
    "sg:tags":[
        "florist",
        "fresh",
        "flower"
    ],
    "sg:website":"www.swholesaleflorist.com",
    "wof:name":"Schaefer Wholesale Florist Inc",
    "wof:placetype":"venue"
},
  "geometry": {"coordinates":[-76.660939,39.931047],"type":"Point"}
}