{
  "type": "Feature",
  "properties": {
    "iso:country":"US",
    "sg:address":"2101 W York St",
    "sg:city":"Philadelphia",
    "sg:classifiers":[
        {
            "category":"Food & Beverages",
            "subcategory":"Specialty",
            "type":"Retail Goods"
        },
        {
            "category":"Food & Beverages",
            "subcategory":"Groceries & Convenience Stores",
            "type":"Retail Goods"
        }
    ],
    "sg:phone":"+1 215 227 4181",
    "sg:postcode":"19132",
    "sg:province":"PA",
    "sg:tags":[
        "grocers-specialty"
    ],
    "wof:name":"Juan Caba Dba Bros Food Mart",
    "wof:placetype":"venue"
},
  "geometry": {"coordinates":[-75.166939,39.990898],"type":"Point"}
}