{
  "type": "Feature",
  "properties": {
    "iso:country":"US",
    "sg:address":"2744 Ellwood Rd",
    "sg:city":"New Castle",
    "sg:classifiers":[
        {
            "category":"Shopping",
            "type":"Retail Goods"
        }
    ],
    "sg:phone":"+1 724 652 9861",
    "sg:postcode":"16101",
    "sg:province":"PA",
    "sg:tags":[
        "wa",
        "well",
        "contractor",
        "water",
        "pump",
        "drilling"
    ],
    "wof:name":"Book & Proch Well Drilling",
    "wof:placetype":"venue"
},
  "geometry": {"coordinates":[-80.31105599999999,40.968372],"type":"Point"}
}