{
  "type": "Feature",
  "properties": {
    "iso:country":"US",
    "sg:address":"2588 Cresswell Rd",
    "sg:city":"Indiana",
    "sg:classifiers":[
        {
            "category":"Building & Trades",
            "subcategory":"Plumbing",
            "type":"Services"
        }
    ],
    "sg:phone":"+1 724 479 3808",
    "sg:postcode":"15701",
    "sg:province":"PA",
    "sg:tags":[
        "conditioning",
        "air",
        "system",
        "contractor"
    ],
    "wof:name":"Provias Refrigeration Service",
    "wof:placetype":"venue"
},
  "geometry": {"coordinates":[-79.058915,40.57307],"type":"Point"}
}