{
  "type": "Feature",
  "properties": {
    "iso:country":"US",
    "sg:address":"1850 Friedensville Rd Bldg 2",
    "sg:city":"Bethlehem",
    "sg:classifiers":[
        {
            "category":"Home & Garden",
            "subcategory":"Home Furnishings",
            "type":"Retail Goods"
        },
        {
            "category":"Building & Trades",
            "subcategory":"Construction",
            "type":"Services"
        },
        {
            "category":"Autos & Motor Vehicles",
            "subcategory":"Auto Supplies",
            "type":"Retail Goods"
        },
        {
            "category":"Retail",
            "subcategory":"Auto Repair",
            "type":"Services"
        },
        {
            "category":"Personal",
            "type":"Services"
        },
        {
            "category":"Manufacturing",
            "subcategory":"Glass & Minerals",
            "type":"Manufacturing & Wholesale Goods"
        },
        {
            "category":"Manufacturing",
            "subcategory":"Building Materials",
            "type":"Manufacturing & Wholesale Goods"
        }
    ],
    "sg:phone":"+1 610 838 2411",
    "sg:postcode":"18015",
    "sg:province":"PA",
    "sg:tags":[
        "plate",
        "door",
        "windows-repair",
        "window",
        "shower",
        "glass-auto",
        "mirror",
        "installation",
        "windshield",
        "enclosure",
        "replacement"
    ],
    "sg:website":"www.glassdoctor.com",
    "wof:name":"Glass Doctor of Lehigh Valley",
    "wof:placetype":"venue"
},
  "geometry": {"coordinates":[-75.35027,40.5786],"type":"Point"}
}