{
  "type": "Feature",
  "properties": {
    "iso:country":"US",
    "sg:address":"41 Hemlock St",
    "sg:city":"New Philadelphia",
    "sg:classifiers":[
        {
            "category":"Retail",
            "subcategory":"Auto Repair",
            "type":"Services"
        }
    ],
    "sg:phone":"+1 570 277 0496",
    "sg:postcode":"17959",
    "sg:province":"PA",
    "sg:tags":[
        "body",
        "automobile",
        "painting"
    ],
    "wof:name":"A & K Towing",
    "wof:placetype":"venue"
},
  "geometry": {"coordinates":[-76.106122,40.740569],"type":"Point"}
}