{
  "type": "Feature",
  "properties": {
    "iso:country":"US",
    "sg:address":"1555 E Wadsworth Ave",
    "sg:city":"Philadelphia",
    "sg:classifiers":[
        {
            "category":"Personal",
            "subcategory":"Beauty Salon",
            "type":"Services"
        }
    ],
    "sg:phone":"+1 215 242 2588",
    "sg:postcode":"19150",
    "sg:province":"PA",
    "sg:tags":[
        "nail",
        "manicuring"
    ],
    "wof:name":"Ann's Nail Salon",
    "wof:placetype":"venue"
},
  "geometry": {"coordinates":[-75.17295300000001,40.080125],"type":"Point"}
}