{
  "type": "Feature",
  "properties": {
    "iso:country":"US",
    "sg:address":"135 Kuebler Rd",
    "sg:city":"Easton",
    "sg:classifiers":[
        {
            "category":"Professional",
            "subcategory":"Art Services",
            "type":"Services"
        }
    ],
    "sg:phone":"+1 610 258 1604",
    "sg:postcode":"18040",
    "sg:province":"PA",
    "sg:tags":[
        "graphic",
        "commercial",
        "designer",
        "artist"
    ],
    "wof:name":"Virtual Graphics",
    "wof:placetype":"venue"
},
  "geometry": {"coordinates":[-75.219809,40.739828],"type":"Point"}
}