{
  "type": "Feature",
  "properties": {
    "addr:full":"215 Bridge St Catasauqua PA 18032",
    "addr:housenumber":"215",
    "addr:postcode":"18032",
    "addr:street":"Bridge St",
    "iso:country":"US",
    "sg:address":"215 Bridge St",
    "sg:city":"Catasauqua",
    "sg:classifiers":[
        {
            "category":"Restaurant",
            "type":"Food & Drink"
        }
    ],
    "sg:phone":"+1 610 264 2771",
    "sg:postcode":"18032",
    "sg:province":"PA",
    "sg:tags":[
        "eating",
        "diner"
    ],
    "wof:name":"Hill's Restaurant",
    "wof:placetype":"venue"
},
  "geometry": {"coordinates":[-75.473,40.654598],"type":"Point"}
}