{
  "type": "Feature",
  "properties": {
    "iso:country":"US",
    "sg:address":"3245 N Front St",
    "sg:city":"Philadelphia",
    "sg:classifiers":[
        {
            "category":"Shopping",
            "subcategory":"Jewelry",
            "type":"Retail Goods"
        }
    ],
    "sg:phone":"+1 215 426 7788",
    "sg:postcode":"19140",
    "sg:province":"PA",
    "sg:tags":[
        "shoes",
        "jeweler"
    ],
    "wof:name":"Front Steps",
    "wof:placetype":"venue"
},
  "geometry": {"coordinates":[-75.128963,39.999405],"type":"Point"}
}