{
  "type": "Feature",
  "properties": {
    "addr:full":"2898 Banksville Rd Pittsburgh PA 15216",
    "addr:housenumber":"2898",
    "addr:postcode":"15216",
    "addr:street":"Banksville Rd",
    "iso:country":"US",
    "sg:address":"2898 Banksville Rd",
    "sg:city":"Pittsburgh",
    "sg:classifiers":[
        {
            "category":"Retail",
            "subcategory":"Event Space",
            "type":"Services"
        }
    ],
    "sg:phone":"+1 412 343 3000",
    "sg:postcode":"15216",
    "sg:province":"PA",
    "sg:tags":[
        "venue"
    ],
    "wof:name":"Comfort Inn & Suites by Choice Hotels",
    "wof:placetype":"venue"
},
  "geometry": {"coordinates":[-80.041,40.4034],"type":"Point"}
}