{
  "type": "Feature",
  "properties": {
    "addr:full":"1827 Church St Lebanon PA 17046",
    "addr:housenumber":"1827",
    "addr:postcode":"17046",
    "addr:street":"Church St",
    "iso:country":"US",
    "sg:address":"1827 Church St",
    "sg:city":"Lebanon",
    "sg:classifiers":[
        {
            "category":"Retail",
            "subcategory":"Auto Repair",
            "type":"Services"
        }
    ],
    "sg:phone":"+1 717 228 0363",
    "sg:postcode":"17046",
    "sg:province":"PA",
    "sg:tags":[
        "repairing",
        "automobile"
    ],
    "wof:name":"Xclusive Imports",
    "wof:placetype":"venue"
},
  "geometry": {"coordinates":[-76.44426799999999,40.343504],"type":"Point"}
}