{
  "type": "Feature",
  "properties": {
    "iso:country":"US",
    "sg:address":"235 N Gallatin Ave",
    "sg:city":"Uniontown",
    "sg:classifiers":[
        {
            "category":"Health Services",
            "subcategory":"Nursing And Care Facility",
            "type":"Services"
        }
    ],
    "sg:phone":"+1 724 437 3235",
    "sg:postcode":"15401",
    "sg:province":"PA",
    "sg:tags":[
        "home",
        "retirement",
        "community"
    ],
    "wof:name":"Mc Vey Personal Care Home",
    "wof:placetype":"venue"
},
  "geometry": {"coordinates":[-79.72103,39.908449],"type":"Point"}
}