{
  "type": "Feature",
  "properties": {
    "iso:country":"US",
    "sg:address":"2320 Haverford Rd",
    "sg:city":"Ardmore",
    "sg:classifiers":[
        {
            "category":"Banks & Credit Unions",
            "subcategory":"Bank",
            "type":"Services"
        }
    ],
    "sg:phone":"+1   ",
    "sg:postcode":"19003",
    "sg:province":"PA",
    "sg:tags":[
        "company",
        "commercial",
        "finance"
    ],
    "wof:name":"Mercantile Capital LP",
    "wof:placetype":"venue"
},
  "geometry": {"coordinates":[-75.297967,39.993558],"type":"Point"}
}