{
  "type": "Feature",
  "properties": {
    "addr:full":"17 E Benedict Ave Havertown PA 19083",
    "addr:housenumber":"17",
    "addr:postcode":"19083",
    "addr:street":"E Benedict Ave",
    "iso:country":"US",
    "sg:address":"17 E Benedict Ave",
    "sg:city":"Havertown",
    "sg:classifiers":[
        {
            "category":"Building & Trades",
            "subcategory":"Construction",
            "type":"Services"
        }
    ],
    "sg:phone":"+1 610 789 8521",
    "sg:postcode":"19083",
    "sg:province":"PA",
    "sg:tags":[
        "builder",
        "general",
        "operative",
        "contractor"
    ],
    "wof:name":"B & B Contracting",
    "wof:placetype":"venue"
},
  "geometry": {"coordinates":[-75.30588,39.986417],"type":"Point"}
}