{
  "type": "Feature",
  "properties": {
    "addr:full":"355 William Pitt Way Pittsburgh PA 15238",
    "addr:housenumber":"355",
    "addr:postcode":"15238",
    "addr:street":"William Pitt Way",
    "iso:country":"US",
    "sg:address":"355 William Pitt Way",
    "sg:city":"Pittsburgh",
    "sg:classifiers":[
        {
            "category":"Mining & Drilling",
            "type":"Manufacturing & Wholesale Goods"
        }
    ],
    "sg:phone":"+1   ",
    "sg:postcode":"15238",
    "sg:province":"PA",
    "sg:tags":[
        "coal",
        "company",
        "technology"
    ],
    "wof:name":"Beard Technologies Inc",
    "wof:placetype":"venue"
},
  "geometry": {"coordinates":[-79.83441500000001,40.543101],"type":"Point"}
}