{
  "type": "Feature",
  "properties": {
    "iso:country":"US",
    "sg:address":"1632 Rockwell Rd",
    "sg:city":"Abington",
    "sg:classifiers":[
        {
            "category":"Autos & Motor Vehicles",
            "subcategory":"Motorcycle Sales",
            "type":"Retail Goods"
        }
    ],
    "sg:phone":"+1   ",
    "sg:postcode":"19001",
    "sg:province":"PA",
    "wof:name":"DAMfastsportbikes",
    "wof:placetype":"venue"
},
  "geometry": {"coordinates":[-75.11881,40.129896],"type":"Point"}
}