{
  "type": "Feature",
  "properties": {
    "addr:full":"4 Fern Ln Wallingford PA 19086",
    "addr:housenumber":"4",
    "addr:postcode":"19086",
    "addr:street":"Fern Ln",
    "iso:country":"US",
    "sg:address":"4 Fern Ln",
    "sg:city":"Wallingford",
    "sg:classifiers":[
        {
            "category":"Professional",
            "subcategory":"Engineering",
            "type":"Services"
        }
    ],
    "sg:phone":"+1   ",
    "sg:postcode":"19086",
    "sg:province":"PA",
    "wof:name":"Holt Arve Inc",
    "wof:placetype":"venue"
},
  "geometry": {"coordinates":[-75.380882,39.899074],"type":"Point"}
}