{
  "type": "Feature",
  "properties": {
    "addr:full":"26 Hazelwood Cir Ephrata PA 17522",
    "addr:housenumber":"26",
    "addr:postcode":"17522",
    "addr:street":"Hazelwood Cir",
    "iso:country":"US",
    "sg:address":"26 Hazelwood Cir",
    "sg:city":"Ephrata",
    "sg:classifiers":[
        {
            "category":"Manufacturing",
            "subcategory":"Tools & Machinery",
            "type":"Manufacturing & Wholesale Goods"
        }
    ],
    "sg:phone":"+1   ",
    "sg:postcode":"17522",
    "sg:province":"PA",
    "sg:tags":[
        "equipment",
        "mfg",
        "landscape",
        "light"
    ],
    "wof:name":"Pro-Industries Inc",
    "wof:placetype":"venue"
},
  "geometry": {"coordinates":[-76.155182,40.184323],"type":"Point"}
}