{
  "type": "Feature",
  "properties": {
    "iso:country":"US",
    "sg:address":"107 Main St",
    "sg:city":"Hickory",
    "sg:classifiers":[
        {
            "category":"Professional",
            "type":"Services"
        }
    ],
    "sg:phone":"+1 724 356 4086",
    "sg:postcode":"15340",
    "sg:province":"PA",
    "wof:name":"Haynes Integrity Auto Svc",
    "wof:placetype":"venue"
},
  "geometry": {"coordinates":[-80.31106699999999,40.298277],"type":"Point"}
}