{
  "type": "Feature",
  "properties": {
    "addr:full":"176 Ridge Rd Gettysburg PA 17325",
    "addr:housenumber":"176",
    "addr:postcode":"17325",
    "addr:street":"Ridge Rd",
    "iso:country":"US",
    "sg:address":"176 Ridge Rd",
    "sg:city":"Gettysburg",
    "sg:classifiers":[
        {
            "category":"Professional",
            "subcategory":"Management & Consulting",
            "type":"Services"
        }
    ],
    "sg:phone":"+1 717 337 1427",
    "sg:postcode":"17325",
    "sg:province":"PA",
    "sg:tags":[
        "consultant",
        "educational"
    ],
    "wof:name":"Subjects & Predicates Inc",
    "wof:placetype":"venue"
},
  "geometry": {"coordinates":[-77.254501,39.779633],"type":"Point"}
}