{
  "type": "Feature",
  "properties": {
    "iso:country":"US",
    "sg:address":"110 Central Ave",
    "sg:city":"Fairless Hills",
    "sg:classifiers":[
        {
            "category":"Building & Trades",
            "subcategory":"Construction",
            "type":"Services"
        }
    ],
    "sg:phone":"+1 215 946 4500",
    "sg:postcode":"19030",
    "sg:province":"PA",
    "sg:tags":[
        "utility",
        "contractor"
    ],
    "wof:name":"CVA Inc",
    "wof:placetype":"venue"
},
  "geometry": {"coordinates":[-74.86312700000001,40.183792],"type":"Point"}
}