{
  "type": "Feature",
  "properties": {
    "addr:full":"308 N Main St Ste B400 Chalfont PA 18914",
    "addr:housenumber":"308",
    "addr:postcode":"18914",
    "addr:street":"N Main St Ste B400",
    "iso:country":"US",
    "sg:address":"308 N Main St Ste B400",
    "sg:city":"Chalfont",
    "sg:classifiers":[
        {
            "category":"Professional",
            "subcategory":"Lawyer & Legal Services",
            "type":"Services"
        }
    ],
    "sg:phone":"+1 215 822 4643",
    "sg:postcode":"18914",
    "sg:province":"PA",
    "sg:website":"www.shober-rock.com",
    "wof:name":"Advice About Elderlaw",
    "wof:placetype":"venue"
},
  "geometry": {"coordinates":[-75.213719,40.291422],"type":"Point"}
}