{
  "type": "Feature",
  "properties": {
    "addr:full":"302 E 12th St Erie PA 16503",
    "addr:housenumber":"302",
    "addr:postcode":"16503",
    "addr:street":"E 12Th St",
    "iso:country":"US",
    "sg:address":"302 E 12th St",
    "sg:city":"Erie",
    "sg:classifiers":[
        {
            "category":"Professional",
            "type":"Services"
        }
    ],
    "sg:phone":"+1 814 453 2746",
    "sg:postcode":"16503",
    "sg:province":"PA",
    "wof:name":"Gary's Auto Svc & Sales",
    "wof:placetype":"venue"
},
  "geometry": {"coordinates":[-80.07278700000001,42.126705],"type":"Point"}
}