{
  "type": "Feature",
  "properties": {
    "iso:country":"US",
    "sg:address":"273 E Main St",
    "sg:city":"Brookville",
    "sg:classifiers":[
        {
            "category":"Insurance",
            "subcategory":"Insurance Agent",
            "type":"Services"
        }
    ],
    "sg:phone":"+1 814 849 8309",
    "sg:postcode":"15825",
    "sg:province":"PA",
    "wof:name":"Smail Insurance Inc",
    "wof:placetype":"venue"
},
  "geometry": {"coordinates":[-79.081525,41.160586],"type":"Point"}
}