{
  "type": "Feature",
  "properties": {
    "iso:country":"US",
    "sg:address":"8620 Oliver Rd",
    "sg:city":"Erie",
    "sg:classifiers":[
        {
            "category":"Building & Trades",
            "subcategory":"Landscaping Services",
            "type":"Services"
        }
    ],
    "sg:phone":"+1   ",
    "sg:postcode":"16509",
    "sg:province":"PA",
    "wof:name":"Youngers Lawn Service",
    "wof:placetype":"venue"
},
  "geometry": {"coordinates":[-80.0943,42.022207],"type":"Point"}
}