{
  "type": "Feature",
  "properties": {
    "addr:full":"8018 Navajo St Philadelphia PA 19118",
    "addr:housenumber":"8018",
    "addr:postcode":"19118",
    "addr:street":"Navajo St",
    "iso:country":"US",
    "sg:address":"8018 Navajo St",
    "sg:city":"Philadelphia",
    "sg:classifiers":[
        {
            "category":"Place Of Worship",
            "type":"Public Place"
        }
    ],
    "sg:phone":"+1 215 247 8321",
    "sg:postcode":"19118",
    "sg:province":"PA",
    "sg:tags":[
        "church"
    ],
    "wof:name":"Sarah Heckscher",
    "wof:placetype":"venue"
},
  "geometry": {"coordinates":[-75.204002,40.067939],"type":"Point"}
}