{
  "type": "Feature",
  "properties": {
    "iso:country":"US",
    "sg:address":"246 E Shaffer Rd",
    "sg:city":"Aliquippa",
    "sg:classifiers":[
        {
            "category":"Building & Trades",
            "subcategory":"Construction",
            "type":"Services"
        }
    ],
    "sg:phone":"+1   ",
    "sg:postcode":"15001",
    "sg:province":"PA",
    "sg:tags":[
        "excavation",
        "contractor"
    ],
    "wof:name":"John E Hall",
    "wof:placetype":"venue"
},
  "geometry": {"coordinates":[-80.305919,40.638208],"type":"Point"}
}