{
  "type": "Feature",
  "properties": {
    "iso:country":"US",
    "sg:address":"21 S Groffdale Rd",
    "sg:city":"Leola",
    "sg:classifiers":[
        {
            "category":"Manufacturing",
            "subcategory":"Buildings",
            "type":"Manufacturing & Wholesale Goods"
        }
    ],
    "sg:phone":"+1 717 656 2381",
    "sg:postcode":"17540",
    "sg:province":"PA",
    "sg:tags":[
        "mobile",
        "home"
    ],
    "sg:website":"www.libertyhomesinc.com",
    "wof:name":"Liberty Homes Inc",
    "wof:placetype":"venue"
},
  "geometry": {"coordinates":[-76.139149,40.092296],"type":"Point"}
}