{
  "type": "Feature",
  "properties": {
    "iso:country":"US",
    "sg:address":"3350 Airport Rd",
    "sg:city":"Allentown",
    "sg:classifiers":[
        {
            "category":"Professional",
            "subcategory":"Lawyer & Legal Services",
            "type":"Services"
        }
    ],
    "sg:phone":"+1 610 264 0701",
    "sg:postcode":"18109",
    "sg:province":"PA",
    "sg:tags":[
        "notary"
    ],
    "wof:name":"Miller's Notary and Tags",
    "wof:placetype":"venue"
},
  "geometry": {"coordinates":[-75.428299,40.656101],"type":"Point"}
}