{
  "type": "Feature",
  "properties": {
    "iso:country":"US",
    "sg:address":"101 Homestead Rd",
    "sg:city":"York",
    "sg:classifiers":[
        {
            "category":"Education",
            "subcategory":"Special Training",
            "type":"Public Place"
        }
    ],
    "sg:phone":"+1 717 676 8915",
    "sg:postcode":"17402",
    "sg:province":"PA",
    "sg:website":"http://www.yorkareadownsyndrome.org",
    "wof:name":"York Area Down Syndrome Association",
    "wof:placetype":"venue"
},
  "geometry": {"coordinates":[-76.68448600000001,39.92186],"type":"Point"}
}