{
  "type": "Feature",
  "properties": {
    "iso:country":"US",
    "sg:address":"1032 S 5th St",
    "sg:city":"Allentown",
    "sg:classifiers":[
        {
            "category":"Building & Trades",
            "subcategory":"Construction",
            "type":"Services"
        }
    ],
    "sg:phone":"+1   ",
    "sg:postcode":"18103",
    "sg:province":"PA",
    "sg:tags":[
        "roofing",
        "contractor"
    ],
    "wof:name":"Nutech Roofing Inc",
    "wof:placetype":"venue"
},
  "geometry": {"coordinates":[-75.462667,40.591252],"type":"Point"}
}