{
  "type": "Feature",
  "properties": {
    "iso:country":"US",
    "sg:address":"725 County Line Rd",
    "sg:city":"Huntingdon Vly",
    "sg:classifiers":[
        {
            "category":"Home & Garden",
            "subcategory":"Building Materials",
            "type":"Retail Goods"
        }
    ],
    "sg:phone":"+1 215 722 3128",
    "sg:postcode":"19006",
    "sg:province":"PA",
    "sg:tags":[
        "door",
        "gate",
        "operating",
        "devices"
    ],
    "wof:name":"Apex Overhead Doors Co Inc",
    "wof:placetype":"venue"
},
  "geometry": {"coordinates":[-75.043497,40.154693],"type":"Point"}
}