{
  "type": "Feature",
  "properties": {
    "iso:country":"US",
    "sg:address":"5660 Lincoln Hwy",
    "sg:city":"York",
    "sg:classifiers":[
        {
            "category":"Building & Trades",
            "subcategory":"Construction",
            "type":"Services"
        }
    ],
    "sg:phone":"+1 717 252 0600",
    "sg:postcode":"17406",
    "sg:province":"PA",
    "sg:tags":[
        "repairing",
        "remodeling",
        "contractor"
    ],
    "wof:name":"Lauer's Remodeling Property",
    "wof:placetype":"venue"
},
  "geometry": {"coordinates":[-76.57601699999999,40.014896],"type":"Point"}
}