{
  "type": "Feature",
  "properties": {
    "iso:country":"US",
    "sg:address":"1220 Wood Rd",
    "sg:city":"Hummelstown",
    "sg:classifiers":[
        {
            "category":"Shopping",
            "subcategory":"Hobbies, Toys, & Games",
            "type":"Retail Goods"
        }
    ],
    "sg:phone":"+1   ",
    "sg:postcode":"17036",
    "sg:province":"PA",
    "sg:tags":[
        "via",
        "internet"
    ],
    "wof:name":"Trainshelf",
    "wof:placetype":"venue"
},
  "geometry": {"coordinates":[-76.689205,40.255503],"type":"Point"}
}