{
  "type": "Feature",
  "properties": {
    "iso:country":"US",
    "sg:address":"1604 N 2nd St",
    "sg:city":"Harrisburg",
    "sg:classifiers":[
        {
            "category":"Social Services",
            "type":"Services"
        }
    ],
    "sg:phone":"+1 717 233 4310",
    "sg:postcode":"17102",
    "sg:province":"PA",
    "sg:tags":[
        "organization",
        "welfare"
    ],
    "wof:name":"Pennsylvania Grange Fed CU",
    "wof:placetype":"venue"
},
  "geometry": {"coordinates":[-76.894147,40.272059],"type":"Point"}
}