{
  "type": "Feature",
  "properties": {
    "addr:full":"153 Grant St Ridgway PA 15853",
    "addr:housenumber":"153",
    "addr:postcode":"15853",
    "addr:street":"Grant St",
    "iso:country":"US",
    "sg:address":"153 Grant St",
    "sg:city":"Ridgway",
    "sg:classifiers":[
        {
            "category":"Building & Trades",
            "subcategory":"Construction",
            "type":"Services"
        }
    ],
    "sg:phone":"+1   ",
    "sg:postcode":"15853",
    "sg:province":"PA",
    "sg:tags":[
        "concrete",
        "contractor"
    ],
    "wof:name":"Elk County Concrete & Masonary",
    "wof:placetype":"venue"
},
  "geometry": {"coordinates":[-78.726254,41.423807],"type":"Point"}
}