{
  "type": "Feature",
  "properties": {
    "addr:full":"412 S Main St Zelienople PA 16063",
    "addr:housenumber":"412",
    "addr:postcode":"16063",
    "addr:street":"S Main St",
    "iso:country":"US",
    "sg:address":"412 S Main St",
    "sg:city":"Zelienople",
    "sg:classifiers":[
        {
            "category":"Autos & Motor Vehicles",
            "subcategory":"Auto Supplies",
            "type":"Retail Goods"
        },
        {
            "category":"Retail",
            "subcategory":"Auto Repair",
            "type":"Services"
        }
    ],
    "sg:phone":"+1 724 452 7841",
    "sg:postcode":"16063",
    "sg:province":"PA",
    "sg:tags":[
        "tire"
    ],
    "wof:name":"Meyer's Tire Service Inc",
    "wof:placetype":"venue"
},
  "geometry": {"coordinates":[-80.136002,40.790001],"type":"Point"}
}