{
  "type": "Feature",
  "properties": {
    "iso:country":"US",
    "sg:address":"45 E Pittsburgh St",
    "sg:city":"Greensburg",
    "sg:classifiers":[
        {
            "category":"Manufacturing",
            "subcategory":"Printing",
            "type":"Manufacturing & Wholesale Goods"
        }
    ],
    "sg:phone":"+1 724 837 0530",
    "sg:postcode":"15601",
    "sg:province":"PA",
    "sg:tags":[
        "offset",
        "blueprinting",
        "printer",
        "drafting"
    ],
    "sg:website":"www.fotorecord.com",
    "wof:name":"Fotorecord Print Center",
    "wof:placetype":"venue"
},
  "geometry": {"coordinates":[-79.54256100000001,40.302851],"type":"Point"}
}