{
  "type": "Feature",
  "properties": {
    "iso:country":"US",
    "sg:address":"212 Rosedale Dr",
    "sg:city":"Manchester",
    "sg:classifiers":[
        {
            "category":"Health Services",
            "subcategory":"Doctor",
            "type":"Services"
        }
    ],
    "sg:phone":"+1   ",
    "sg:postcode":"17345",
    "sg:province":"PA",
    "sg:tags":[
        "osteopathic"
    ],
    "wof:name":"Wheatlyn Family Medicine",
    "wof:placetype":"venue"
},
  "geometry": {"coordinates":[-76.726263,40.048475],"type":"Point"}
}