{
  "type": "Feature",
  "properties": {
    "iso:country":"US",
    "sg:address":"859 Nazareth Pike Unit 8",
    "sg:city":"Nazareth",
    "sg:classifiers":[
        {
            "category":"Banks & Credit Unions",
            "subcategory":"Bank",
            "type":"Services"
        },
        {
            "category":"Shopping",
            "subcategory":"Used Merchandise",
            "type":"Retail Goods"
        }
    ],
    "sg:phone":"+1 610 759 8660",
    "sg:postcode":"18064",
    "sg:province":"PA",
    "sg:tags":[
        "shop",
        "second",
        "resale",
        "hand"
    ],
    "wof:name":"Via Thrift Shop Nazareth",
    "wof:placetype":"venue"
},
  "geometry": {"coordinates":[-75.313689,40.730933],"type":"Point"}
}