{
  "type": "Feature",
  "properties": {
    "addr:full":"110 Merritt Ave Douglassville PA 19518",
    "addr:housenumber":"110",
    "addr:postcode":"19518",
    "addr:street":"Merritt Ave",
    "iso:country":"US",
    "sg:address":"110 Merritt Ave",
    "sg:city":"Douglassville",
    "sg:classifiers":[
        {
            "category":"Building & Trades",
            "subcategory":"Plumbing",
            "type":"Services"
        }
    ],
    "sg:phone":"+1   ",
    "sg:postcode":"19518",
    "sg:province":"PA",
    "sg:tags":[
        "plumbing",
        "air",
        "conditioning",
        "heating"
    ],
    "wof:name":"Gregory Ribick",
    "wof:placetype":"venue"
},
  "geometry": {"coordinates":[-75.72737499999999,40.265137],"type":"Point"}
}