{
  "type": "Feature",
  "properties": {
    "iso:country":"US",
    "sg:address":"1694 Rte 228",
    "sg:city":"Cranberry Twp",
    "sg:classifiers":[
        {
            "category":"Fast Food",
            "type":"Food & Drink"
        },
        {
            "category":"Food & Beverages",
            "subcategory":"Bakery",
            "type":"Retail Goods"
        }
    ],
    "sg:phone":"+1 724 772 8088",
    "sg:postcode":"16066",
    "sg:province":"PA",
    "sg:tags":[
        "sandwich"
    ],
    "sg:website":"www.dibellas.com",
    "wof:name":"Dibella's Old Fashioned Submarines",
    "wof:placetype":"venue"
},
  "geometry": {"coordinates":[-80.081623,40.684837],"type":"Point"}
}