{
  "type": "Feature",
  "properties": {
    "addr:full":"105 S Water Ave Sharon PA 16146",
    "addr:housenumber":"105",
    "addr:postcode":"16146",
    "addr:street":"S Water Ave",
    "iso:country":"US",
    "sg:address":"105 S Water Ave",
    "sg:city":"Sharon",
    "sg:classifiers":[
        {
            "category":"Professional",
            "subcategory":"Lawyer & Legal Services",
            "type":"Services"
        }
    ],
    "sg:phone":"+1 724 342 2299",
    "sg:postcode":"16146",
    "sg:province":"PA",
    "sg:tags":[
        "attorney",
        "practice"
    ],
    "wof:name":"Harshman & Gervelis",
    "wof:placetype":"venue"
},
  "geometry": {"coordinates":[-80.51011,41.231979],"type":"Point"}
}