{
  "type": "Feature",
  "properties": {
    "iso:country":"US",
    "sg:address":"915 E Price St",
    "sg:city":"Philadelphia",
    "sg:classifiers":[
        {
            "category":"Professional",
            "type":"Services"
        }
    ],
    "sg:phone":"+1   ",
    "sg:postcode":"19138",
    "sg:province":"PA",
    "wof:name":"Michael A Slade Ent",
    "wof:placetype":"venue"
},
  "geometry": {"coordinates":[-75.16308600000001,40.049121],"type":"Point"}
}