{
  "type": "Feature",
  "properties": {
    "iso:country":"US",
    "sg:address":"6928 Elmwood Ave",
    "sg:city":"Philadelphia",
    "sg:classifiers":[
        {
            "category":"Shopping",
            "subcategory":"Discount & Variety Stores",
            "type":"Retail Goods"
        }
    ],
    "sg:phone":"+1 215 365 5174",
    "sg:postcode":"19142",
    "sg:province":"PA",
    "wof:name":"Dollar Magic",
    "wof:placetype":"venue"
},
  "geometry": {"coordinates":[-75.237073,39.917427],"type":"Point"}
}