{
  "type": "Feature",
  "properties": {
    "addr:full":"100 Anderson St Pittsburgh PA 15212",
    "addr:housenumber":"100",
    "addr:postcode":"15212",
    "addr:street":"Anderson St",
    "iso:country":"US",
    "sg:address":"100 Anderson St",
    "sg:city":"Pittsburgh",
    "sg:classifiers":[
        {
            "category":"Real Estate",
            "subcategory":"Real Estate Operator",
            "type":"Services"
        }
    ],
    "sg:phone":"+1 412 321 2300",
    "sg:postcode":"15212",
    "sg:province":"PA",
    "sg:tags":[
        "apartment"
    ],
    "wof:name":"Lincoln At North Shore Apt",
    "wof:placetype":"venue"
},
  "geometry": {"coordinates":[-80.00040300000001,40.448167],"type":"Point"}
}