{
  "type": "Feature",
  "properties": {
    "iso:country":"US",
    "sg:address":"1568 Sheridan Ln",
    "sg:city":"Norristown",
    "sg:classifiers":[
        {
            "category":"Home & Garden",
            "subcategory":"Building Materials",
            "type":"Retail Goods"
        }
    ],
    "sg:phone":"+1   ",
    "sg:postcode":"19403",
    "sg:province":"PA",
    "sg:tags":[
        "trade",
        "contractor"
    ],
    "wof:name":"Service Station Maintenance",
    "wof:placetype":"venue"
},
  "geometry": {"coordinates":[-75.36596900000001,40.124363],"type":"Point"}
}