{
  "type": "Feature",
  "properties": {
    "iso:country":"US",
    "sg:address":"111 E Church St",
    "sg:city":"Ligonier",
    "sg:classifiers":[
        {
            "category":"Health Services",
            "subcategory":"Health Practitioner",
            "type":"Services"
        }
    ],
    "sg:phone":"+1 724 238 3431",
    "sg:postcode":"15658",
    "sg:province":"PA",
    "sg:tags":[
        "acupuncture"
    ],
    "wof:name":"Michelle Clark Bouchard",
    "wof:placetype":"venue"
},
  "geometry": {"coordinates":[-79.236799,40.243877],"type":"Point"}
}