{
  "type": "Feature",
  "properties": {
    "iso:country":"US",
    "sg:address":"137 Kelly St",
    "sg:city":"Luzerne",
    "sg:classifiers":[
        {
            "category":"Shopping",
            "subcategory":"Gifts & Souvenirs",
            "type":"Retail Goods"
        }
    ],
    "sg:phone":"+1   ",
    "sg:postcode":"18709",
    "sg:province":"PA",
    "sg:tags":[
        "cards",
        "sport",
        "trading"
    ],
    "wof:name":"Mvp Sportscards",
    "wof:placetype":"venue"
},
  "geometry": {"coordinates":[-75.897211,41.286465],"type":"Point"}
}