{
  "type": "Feature",
  "properties": {
    "iso:country":"US",
    "sg:address":"643 E High St",
    "sg:city":"Pottstown",
    "sg:classifiers":[
        {
            "category":"Professional",
            "subcategory":"Accounting & Tax Preparation",
            "type":"Services"
        }
    ],
    "sg:phone":"+1   ",
    "sg:postcode":"19464",
    "sg:province":"PA",
    "wof:name":"Financial Liaisons Inc",
    "wof:placetype":"venue"
},
  "geometry": {"coordinates":[-75.637714,40.244077],"type":"Point"}
}