{
  "type": "Feature",
  "properties": {
    "addr:full":"20 Pond Rd Boyertown PA 19512",
    "addr:housenumber":"20",
    "addr:postcode":"19512",
    "addr:street":"Pond Rd",
    "iso:country":"US",
    "sg:address":"20 Pond Rd",
    "sg:city":"Boyertown",
    "sg:classifiers":[
        {
            "category":"Building & Trades",
            "subcategory":"Electrical",
            "type":"Services"
        }
    ],
    "sg:phone":"+1 610 369 9147",
    "sg:postcode":"19512",
    "sg:province":"PA",
    "sg:tags":[
        "electric",
        "contractor"
    ],
    "wof:name":"Rush Electric Corporation",
    "wof:placetype":"venue"
},
  "geometry": {"coordinates":[-75.67489399999999,40.361313],"type":"Point"}
}