{
  "type": "Feature",
  "properties": {
    "addr:full":"2001 Clinton Ave Coal Township PA 17866",
    "addr:housenumber":"2001",
    "addr:postcode":"17866",
    "addr:street":"Clinton Ave",
    "iso:country":"US",
    "sg:address":"2001 Clinton Ave",
    "sg:city":"Coal Township",
    "sg:classifiers":[
        {
            "category":"Education",
            "subcategory":"School",
            "type":"Public Place"
        }
    ],
    "sg:phone":"+1   ",
    "sg:postcode":"17866",
    "sg:province":"PA",
    "wof:name":"Our Lady Lrdes Rgnal High Schl",
    "wof:placetype":"venue"
},
  "geometry": {"coordinates":[-76.582655,40.786797],"type":"Point"}
}