{
  "type": "Feature",
  "properties": {
    "addr:full":"4006 Berger Ln Monroeville PA 15146",
    "addr:housenumber":"4006",
    "addr:postcode":"15146",
    "addr:street":"Berger Ln",
    "iso:country":"US",
    "sg:address":"4006 Berger Ln",
    "sg:city":"Monroeville",
    "sg:classifiers":[
        {
            "category":"Bars & Pubs",
            "type":"Food & Drink"
        },
        {
            "category":"Restaurant",
            "type":"Food & Drink"
        }
    ],
    "sg:phone":"+1 412 372 8199",
    "sg:postcode":"15146",
    "sg:province":"PA",
    "sg:tags":[
        "tavern"
    ],
    "wof:name":"Parkway Tavern",
    "wof:placetype":"venue"
},
  "geometry": {"coordinates":[-79.772722,40.437988],"type":"Point"}
}