{
  "type": "Feature",
  "properties": {
    "iso:country":"US",
    "sg:address":"6 Tahoe Dr",
    "sg:city":"New Hope",
    "sg:classifiers":[
        {
            "category":"Professional",
            "subcategory":"Management & Consulting",
            "type":"Services"
        }
    ],
    "sg:phone":"+1 215 862 9593",
    "sg:postcode":"18938",
    "sg:province":"PA",
    "sg:tags":[
        "consultant",
        "training"
    ],
    "wof:name":"Bukowski Stanton Assoc",
    "wof:placetype":"venue"
},
  "geometry": {"coordinates":[-74.956936,40.358993],"type":"Point"}
}