{
  "type": "Feature",
  "properties": {
    "iso:country":"US",
    "sg:address":"92 Pheasant Valley Rd",
    "sg:city":"Lewistown",
    "sg:classifiers":[
        {
            "category":"Wholesale",
            "subcategory":"Vending Machines",
            "type":"Manufacturing & Wholesale Goods"
        }
    ],
    "sg:phone":"+1 717 543 5733",
    "sg:postcode":"17044",
    "sg:province":"PA",
    "sg:tags":[
        "merchandise"
    ],
    "wof:name":"J T A Vending",
    "wof:placetype":"venue"
},
  "geometry": {"coordinates":[-77.497389,40.666841],"type":"Point"}
}