{
  "type": "Feature",
  "properties": {
    "addr:full":"576 Horseshoe Dr Easton PA 18040",
    "addr:housenumber":"576",
    "addr:postcode":"18040",
    "addr:street":"Horseshoe Dr",
    "iso:country":"US",
    "sg:address":"576 Horseshoe Dr",
    "sg:city":"Easton",
    "sg:classifiers":[
        {
            "category":"Real Estate",
            "subcategory":"Real Estate Agent",
            "type":"Services"
        }
    ],
    "sg:phone":"+1 610 923 6250",
    "sg:postcode":"18040",
    "sg:province":"PA",
    "sg:tags":[
        "management"
    ],
    "wof:name":"Hyrowich Property Management",
    "wof:placetype":"venue"
},
  "geometry": {"coordinates":[-75.24396900000001,40.772721],"type":"Point"}
}