{
  "type": "Feature",
  "properties": {
    "iso:country":"US",
    "sg:address":"185 Great Valley Pkwy",
    "sg:city":"Malvern",
    "sg:classifiers":[
        {
            "category":"Wholesale",
            "subcategory":"Machinery & Supplies",
            "type":"Manufacturing & Wholesale Goods"
        }
    ],
    "sg:phone":"+1 610 647 9900",
    "sg:postcode":"19355",
    "sg:province":"PA",
    "sg:tags":[
        "equipment",
        "material",
        "handling"
    ],
    "sg:website":"www.a-s-h.com",
    "wof:name":"Allen-Sherman-Hoff",
    "wof:placetype":"venue"
},
  "geometry": {"coordinates":[-75.545655,40.062699],"type":"Point"}
}