{
  "type": "Feature",
  "properties": {
    "iso:country":"US",
    "sg:address":"310 Market St",
    "sg:city":"Kingston",
    "sg:classifiers":[
        {
            "category":"Sports & Exercise",
            "subcategory":"Gym",
            "type":"Entertainment"
        }
    ],
    "sg:phone":"+1 570 283 9750",
    "sg:postcode":"18704",
    "sg:province":"PA",
    "sg:tags":[
        "club",
        "health",
        "studio",
        "gymnasium"
    ],
    "wof:name":"Gold's Gym",
    "wof:placetype":"venue"
},
  "geometry": {"coordinates":[-75.890837,41.254886],"type":"Point"}
}