{
  "type": "Feature",
  "properties": {
    "iso:country":"US",
    "sg:address":"1203 Lycoming Mall Cir",
    "sg:city":"Muncy",
    "sg:classifiers":[
        {
            "category":"Manufacturing",
            "subcategory":"Tools & Machinery",
            "type":"Manufacturing & Wholesale Goods"
        },
        {
            "category":"Home & Garden",
            "subcategory":"Hardware",
            "type":"Retail Goods"
        }
    ],
    "sg:phone":"+1 570 546 9663",
    "sg:postcode":"17756",
    "sg:province":"PA",
    "sg:tags":[
        "store"
    ],
    "sg:website":"http://www.pipeclamps.com",
    "wof:name":"Grizzly Industrial, Inc.",
    "wof:placetype":"venue"
},
  "geometry": {"coordinates":[-76.83022,41.240574],"type":"Point"}
}