{
  "type": "Feature",
  "properties": {
    "iso:country":"US",
    "sg:address":"25 Norristown Rd",
    "sg:city":"Blue Bell",
    "sg:classifiers":[
        {
            "category":"Professional",
            "type":"Services"
        }
    ],
    "sg:phone":"+1 215 646 5939",
    "sg:postcode":"19422",
    "sg:province":"PA",
    "sg:tags":[
        "establishment"
    ],
    "wof:name":"Hal Langerman Co",
    "wof:placetype":"venue"
},
  "geometry": {"coordinates":[-75.250321,40.134355],"type":"Point"}
}