{
  "type": "Feature",
  "properties": {
    "addr:full":"24 Homestead Dr Denver PA 17517",
    "addr:housenumber":"24",
    "addr:postcode":"17517",
    "addr:street":"Homestead Dr",
    "iso:country":"US",
    "sg:address":"24 Homestead Dr",
    "sg:city":"Denver",
    "sg:classifiers":[
        {
            "category":"Shopping",
            "type":"Retail Goods"
        }
    ],
    "sg:phone":"+1   ",
    "sg:postcode":"17517",
    "sg:province":"PA",
    "sg:tags":[
        "merchandise"
    ],
    "wof:name":"Nates Exotic Pets Fish & Suppl",
    "wof:placetype":"venue"
},
  "geometry": {"coordinates":[-76.083399,40.236821],"type":"Point"}
}