{
  "type": "Feature",
  "properties": {
    "addr:full":"300 E Walnut Ave Altoona PA 16601",
    "addr:housenumber":"300",
    "addr:postcode":"16601",
    "addr:street":"E Walnut Ave",
    "iso:country":"US",
    "sg:address":"300 E Walnut Ave",
    "sg:city":"Altoona",
    "sg:classifiers":[
        {
            "category":"Retail",
            "subcategory":"Auto Rental",
            "type":"Services"
        }
    ],
    "sg:phone":"+1 814 949 8939",
    "sg:postcode":"16601",
    "sg:province":"PA",
    "sg:tags":[
        "renting",
        "truck",
        "leasing"
    ],
    "wof:name":"U-Haul Co",
    "wof:placetype":"venue"
},
  "geometry": {"coordinates":[-78.391983,40.529527],"type":"Point"}
}