{
  "type": "Feature",
  "properties": {
    "addr:full":"7975 S Eagle Valley Rd Port Matilda PA 16870",
    "addr:housenumber":"7975",
    "addr:postcode":"16870",
    "addr:street":"S Eagle Valley Rd",
    "iso:country":"US",
    "sg:address":"7975 S Eagle Valley Rd",
    "sg:city":"Port Matilda",
    "sg:classifiers":[
        {
            "category":"Building & Trades",
            "subcategory":"Construction",
            "type":"Services"
        }
    ],
    "sg:phone":"+1   ",
    "sg:postcode":"16870",
    "sg:province":"PA",
    "sg:tags":[
        "residential"
    ],
    "wof:name":"Jeff St Clair",
    "wof:placetype":"venue"
},
  "geometry": {"coordinates":[-78.027309,40.822922],"type":"Point"}
}