{
  "type": "Feature",
  "properties": {
    "iso:country":"US",
    "sg:address":"4441 Cemetery Rd",
    "sg:city":"Parkesburg",
    "sg:classifiers":[
        {
            "category":"Shopping",
            "type":"Retail Goods"
        }
    ],
    "sg:phone":"+1   ",
    "sg:postcode":"19365",
    "sg:province":"PA",
    "sg:tags":[
        "merchandise"
    ],
    "wof:name":"Telrite Communications",
    "wof:placetype":"venue"
},
  "geometry": {"coordinates":[-75.946422,39.95935],"type":"Point"}
}