{
  "type": "Feature",
  "properties": {
    "iso:country":"US",
    "sg:address":"1552 E Pleasant Valley Blvd",
    "sg:city":"Altoona",
    "sg:classifiers":[
        {
            "category":"Food & Beverages",
            "subcategory":"Bakery",
            "type":"Retail Goods"
        }
    ],
    "sg:phone":"+1 814 940 5880",
    "sg:postcode":"16602",
    "sg:province":"PA",
    "sg:tags":[
        "baker"
    ],
    "wof:name":"Bakery Outlet",
    "wof:placetype":"venue"
},
  "geometry": {"coordinates":[-78.358654,40.53498],"type":"Point"}
}