{
  "type": "Feature",
  "properties": {
    "addr:full":"334 Grays Ln Haverford PA 19041",
    "addr:housenumber":"334",
    "addr:postcode":"19041",
    "addr:street":"Grays Ln",
    "iso:country":"US",
    "sg:address":"334 Grays Ln",
    "sg:city":"Haverford",
    "sg:classifiers":[
        {
            "category":"Professional",
            "subcategory":"Management & Consulting",
            "type":"Services"
        },
        {
            "category":"Banks & Credit Unions",
            "subcategory":"Financial Services",
            "type":"Services"
        }
    ],
    "sg:phone":"+1 610 649 9580",
    "sg:postcode":"19041",
    "sg:province":"PA",
    "sg:tags":[
        "consultant",
        "financing",
        "planning"
    ],
    "wof:name":"Petersen Consultants Ltd",
    "wof:placetype":"venue"
},
  "geometry": {"coordinates":[-75.28816399999999,40.02068],"type":"Point"}
}