{
  "type": "Feature",
  "properties": {
    "iso:country":"US",
    "sg:address":"5 Great Valley Pkwy",
    "sg:city":"Malvern",
    "sg:classifiers":[
        {
            "category":"Professional",
            "subcategory":"Research",
            "type":"Services"
        }
    ],
    "sg:phone":"+1 610 296 1744",
    "sg:postcode":"19355",
    "sg:province":"PA",
    "wof:name":"Precision Research Inc",
    "wof:placetype":"venue"
},
  "geometry": {"coordinates":[-75.53584600000001,40.063686],"type":"Point"}
}