{
  "type": "Feature",
  "properties": {
    "iso:country":"US",
    "sg:address":"132 E Nesquehoning St",
    "sg:city":"Easton",
    "sg:classifiers":[
        {
            "category":"Building & Trades",
            "subcategory":"Construction",
            "type":"Services"
        }
    ],
    "sg:phone":"+1   ",
    "sg:postcode":"18042",
    "sg:province":"PA",
    "sg:tags":[
        "contractor"
    ],
    "wof:name":"Tdm Masonry",
    "wof:placetype":"venue"
},
  "geometry": {"coordinates":[-75.206547,40.681953],"type":"Point"}
}