{
  "type": "Feature",
  "properties": {
    "addr:full":"1455 Franklin Mills Cir Philadelphia PA 19154",
    "addr:housenumber":"1455",
    "addr:postcode":"19154",
    "addr:street":"Franklin Mills Cir",
    "iso:country":"US",
    "sg:address":"1455 Franklin Mills Cir",
    "sg:city":"Philadelphia",
    "sg:classifiers":[
        {
            "category":"Retail",
            "subcategory":"Auto Repair",
            "type":"Services"
        }
    ],
    "sg:phone":"+1 215 824 1032",
    "sg:postcode":"19154",
    "sg:province":"PA",
    "sg:tags":[
        "body",
        "automobile",
        "painting"
    ],
    "wof:name":"Desimone Auto Body",
    "wof:placetype":"venue"
},
  "geometry": {"coordinates":[-74.960094,40.083142],"type":"Point"}
}