{
  "type": "Feature",
  "properties": {
    "addr:full":"5429 Philadelphia Ave Chambersburg PA 17201",
    "addr:housenumber":"5429",
    "addr:postcode":"17201",
    "addr:street":"Philadelphia Ave",
    "iso:country":"US",
    "sg:address":"5429 Philadelphia Ave",
    "sg:city":"Chambersburg",
    "sg:classifiers":[
        {
            "category":"Autos & Motor Vehicles",
            "subcategory":"Boat Sales",
            "type":"Retail Goods"
        }
    ],
    "sg:phone":"+1 717 263 6963",
    "sg:postcode":"17201",
    "sg:province":"PA",
    "sg:tags":[
        "dealer",
        "sales"
    ],
    "wof:name":"Brook's Marine Svc",
    "wof:placetype":"venue"
},
  "geometry": {"coordinates":[-77.60500399999999,39.994428],"type":"Point"}
}