{
  "type": "Feature",
  "properties": {
    "iso:country":"US",
    "sg:address":"633 Mayfield Rd",
    "sg:city":"Clarion",
    "sg:classifiers":[
        {
            "category":"Government",
            "subcategory":"Office",
            "type":"Public Place"
        }
    ],
    "sg:phone":"+1 814 226 6911",
    "sg:postcode":"16214",
    "sg:province":"PA",
    "sg:tags":[
        "village"
    ],
    "wof:name":"C & K Coal Co",
    "wof:placetype":"venue"
},
  "geometry": {"coordinates":[-79.383957,41.190966],"type":"Point"}
}