{
  "type": "Feature",
  "properties": {
    "addr:full":"5101 Jonestown Rd Harrisburg PA 17112",
    "addr:housenumber":"5101",
    "addr:postcode":"17112",
    "addr:street":"Jonestown Rd",
    "iso:country":"US",
    "sg:address":"5101 Jonestown Rd",
    "sg:city":"Harrisburg",
    "sg:classifiers":[
        {
            "category":"Real Estate",
            "subcategory":"Real Estate Services",
            "type":"Services"
        },
        {
            "category":"Home & Garden",
            "subcategory":"Building Materials",
            "type":"Retail Goods"
        },
        {
            "category":"Building & Trades",
            "subcategory":"Construction",
            "type":"Services"
        },
        {
            "category":"Manufacturing",
            "subcategory":"Building Materials",
            "type":"Manufacturing & Wholesale Goods"
        }
    ],
    "sg:postcode":"17112",
    "sg:province":"PA",
    "sg:tags":[
        "roofing",
        "supply",
        "shingle",
        "contractor",
        "equipment",
        "maintenance",
        "consultant"
    ],
    "sg:website":"http://www.theloanauthority.com",
    "wof:name":"Home Depot - Free Roofing Estimate",
    "wof:placetype":"venue"
},
  "geometry": {"coordinates":[-76.803589,40.308762],"type":"Point"}
}