{
  "type": "Feature",
  "properties": {
    "iso:country":"US",
    "sg:address":"629 California Ave",
    "sg:city":"Rochester",
    "sg:classifiers":[
        {
            "category":"Building & Trades",
            "subcategory":"Construction",
            "type":"Services"
        }
    ],
    "sg:phone":"+1 724 775 2140",
    "sg:postcode":"15074",
    "sg:province":"PA",
    "sg:tags":[
        "carpentry",
        "contractor"
    ],
    "wof:name":"TLN Construction",
    "wof:placetype":"venue"
},
  "geometry": {"coordinates":[-80.285032,40.713251],"type":"Point"}
}