{
  "type": "Feature",
  "properties": {
    "addr:full":"228 E Main St Monongahela PA 15063",
    "addr:housenumber":"228",
    "addr:postcode":"15063",
    "addr:street":"E Main St",
    "iso:country":"US",
    "sg:address":"228 E Main St",
    "sg:city":"Monongahela",
    "sg:classifiers":[
        {
            "category":"Personal",
            "subcategory":"Beauty Salon",
            "type":"Services"
        }
    ],
    "sg:phone":"+1 724 258 4181",
    "sg:postcode":"15063",
    "sg:province":"PA",
    "wof:name":"Hair Loft",
    "wof:placetype":"venue"
},
  "geometry": {"coordinates":[-79.919111,40.197649],"type":"Point"}
}