{
  "type": "Feature",
  "properties": {
    "iso:country":"US",
    "sg:address":"2865 Leechburg Rd",
    "sg:city":"Lower Burrell",
    "sg:classifiers":[
        {
            "category":"Health Services",
            "subcategory":"Doctor",
            "type":"Services"
        }
    ],
    "sg:phone":"+1 724 335 5255",
    "sg:postcode":"15068",
    "sg:province":"PA",
    "sg:tags":[
        "physician",
        "surgeon"
    ],
    "wof:name":"Anthony N Okobi MD",
    "wof:placetype":"venue"
},
  "geometry": {"coordinates":[-79.725836,40.589989],"type":"Point"}
}