{
  "type": "Feature",
  "properties": {
    "iso:country":"US",
    "sg:address":"186 Vanyo Rd",
    "sg:city":"Berlin",
    "sg:classifiers":[
        {
            "category":"Building & Trades",
            "subcategory":"Construction",
            "type":"Services"
        }
    ],
    "sg:phone":"+1   ",
    "sg:postcode":"15530",
    "sg:province":"PA",
    "sg:tags":[
        "contractor"
    ],
    "wof:name":"Terry Coughenour",
    "wof:placetype":"venue"
},
  "geometry": {"coordinates":[-78.886827,39.984614],"type":"Point"}
}