{
  "type": "Feature",
  "properties": {
    "iso:country":"US",
    "sg:address":"189 Pine Valley Rd",
    "sg:city":"New Ringgold",
    "sg:phone":"+1   ",
    "sg:postcode":"17960",
    "sg:province":"PA",
    "sg:tags":[
        "farm",
        "grain",
        "cash"
    ],
    "wof:name":"Lemoyne V Eckroth",
    "wof:placetype":"venue"
},
  "geometry": {"coordinates":[-75.987149,40.679248],"type":"Point"}
}