{
  "type": "Feature",
  "properties": {
    "addr:full":"3120 Broadlawn Dr Erie PA 16506",
    "addr:housenumber":"3120",
    "addr:postcode":"16506",
    "addr:street":"Broadlawn Dr",
    "iso:country":"US",
    "sg:address":"3120 Broadlawn Dr",
    "sg:city":"Erie",
    "sg:classifiers":[
        {
            "category":"Restaurant",
            "type":"Food & Drink"
        }
    ],
    "sg:phone":"+1   ",
    "sg:postcode":"16506",
    "sg:province":"PA",
    "sg:tags":[
        "eating"
    ],
    "wof:name":"O2 Xtreme",
    "wof:placetype":"venue"
},
  "geometry": {"coordinates":[-80.16487600000001,42.072511],"type":"Point"}
}