{
  "type": "Feature",
  "properties": {
    "addr:full":"428 S Main St Greenville PA 16125",
    "addr:housenumber":"428",
    "addr:postcode":"16125",
    "addr:street":"S Main St",
    "iso:country":"US",
    "sg:address":"428 S Main St",
    "sg:city":"Greenville",
    "sg:classifiers":[
        {
            "category":"Health Services",
            "subcategory":"Doctor",
            "type":"Services"
        }
    ],
    "sg:phone":"+1 724 588 4370",
    "sg:postcode":"16125",
    "sg:province":"PA",
    "sg:tags":[
        "physician",
        "surgeon"
    ],
    "wof:name":"UPMC Neuroscience Ctr",
    "wof:placetype":"venue"
},
  "geometry": {"coordinates":[-80.36984099999999,41.410357],"type":"Point"}
}