{
  "type": "Feature",
  "properties": {
    "iso:country":"US",
    "sg:address":"1665 N Main St",
    "sg:city":"Butler",
    "sg:classifiers":[
        {
            "category":"Insurance",
            "subcategory":"Insurance Agent",
            "type":"Services"
        }
    ],
    "sg:phone":"+1 724 287 3166",
    "sg:postcode":"16001",
    "sg:province":"PA",
    "wof:name":"Bail USA",
    "wof:placetype":"venue"
},
  "geometry": {"coordinates":[-79.91858499999999,40.904969],"type":"Point"}
}