{
  "type": "Feature",
  "properties": {
    "iso:country":"US",
    "sg:address":"5 Long St",
    "sg:city":"Smethport",
    "sg:classifiers":[
        {
            "category":"Manufacturing",
            "subcategory":"Metals",
            "type":"Manufacturing & Wholesale Goods"
        }
    ],
    "sg:phone":"+1   ",
    "sg:postcode":"16749",
    "sg:province":"PA",
    "sg:tags":[
        "brass",
        "rod",
        "stair",
        "mfg"
    ],
    "wof:name":"Heritage Brass Company",
    "wof:placetype":"venue"
},
  "geometry": {"coordinates":[-78.45397699999999,41.808586],"type":"Point"}
}