{
  "type": "Feature",
  "properties": {
    "addr:full":"547 Pelham Rd Philadelphia PA 19119",
    "addr:housenumber":"547",
    "addr:postcode":"19119",
    "addr:street":"Pelham Rd",
    "iso:country":"US",
    "sg:address":"547 Pelham Rd",
    "sg:city":"Philadelphia",
    "sg:classifiers":[
        {
            "category":"Professional",
            "subcategory":"Lawyer & Legal Services",
            "type":"Services"
        }
    ],
    "sg:phone":"+1 215 861 9520",
    "sg:postcode":"19119",
    "sg:province":"PA",
    "sg:tags":[
        "attorney"
    ],
    "wof:name":"Simon Thomas & Carson",
    "wof:placetype":"venue"
},
  "geometry": {"coordinates":[-75.18956,40.043831],"type":"Point"}
}