{
  "type": "Feature",
  "properties": {
    "iso:country":"US",
    "sg:address":"214 Foster St",
    "sg:city":"Greensburg",
    "sg:classifiers":[
        {
            "category":"Restaurant",
            "type":"Food & Drink"
        }
    ],
    "sg:phone":"+1 724 838 1460",
    "sg:postcode":"15601",
    "sg:province":"PA",
    "sg:tags":[
        "lounge",
        "cocktail"
    ],
    "wof:name":"Lonzos Pub",
    "wof:placetype":"venue"
},
  "geometry": {"coordinates":[-79.544031,40.296364],"type":"Point"}
}