{
  "type": "Feature",
  "properties": {
    "iso:country":"US",
    "sg:address":"2727 Philmont Ave",
    "sg:city":"Huntingdon Vly",
    "sg:classifiers":[
        {
            "category":"Wholesale",
            "subcategory":"Medical Equipment & Supplies",
            "type":"Manufacturing & Wholesale Goods"
        },
        {
            "category":"Shopping",
            "type":"Retail Goods"
        }
    ],
    "sg:phone":"+1 215 947 7667",
    "sg:postcode":"19006",
    "sg:province":"PA",
    "sg:tags":[
        "hospital"
    ],
    "wof:name":"Professional Office & Med Sup",
    "wof:placetype":"venue"
},
  "geometry": {"coordinates":[-75.046221,40.122724],"type":"Point"}
}