{
  "type": "Feature",
  "properties": {
    "iso:country":"US",
    "sg:address":"924 4th Ave",
    "sg:city":"Coraopolis",
    "sg:classifiers":[
        {
            "category":"Shopping",
            "subcategory":"Catalog Store",
            "type":"Retail Goods"
        }
    ],
    "sg:phone":"+1   ",
    "sg:postcode":"15108",
    "sg:province":"PA",
    "sg:tags":[
        "mail",
        "house"
    ],
    "wof:name":"Scott T Miller",
    "wof:placetype":"venue"
},
  "geometry": {"coordinates":[-80.164607,40.51866],"type":"Point"}
}