{
  "type": "Feature",
  "properties": {
    "iso:country":"US",
    "sg:address":"2259 Valley Rd",
    "sg:city":"Glen Rock",
    "sg:classifiers":[
        {
            "category":"Autos & Motor Vehicles",
            "subcategory":"Automobile Sales",
            "type":"Retail Goods"
        }
    ],
    "sg:phone":"+1 717 235 1729",
    "sg:postcode":"17327",
    "sg:province":"PA",
    "sg:tags":[
        "used"
    ],
    "wof:name":"Valley Motor Co",
    "wof:placetype":"venue"
},
  "geometry": {"coordinates":[-76.717277,39.798555],"type":"Point"}
}