{
  "type": "Feature",
  "properties": {
    "iso:country":"US",
    "sg:address":"1729 Eckert St",
    "sg:city":"Pittsburgh",
    "sg:classifiers":[
        {
            "category":"Restaurant",
            "type":"Food & Drink"
        }
    ],
    "sg:phone":"+1 412 761 5883",
    "sg:postcode":"15212",
    "sg:province":"PA",
    "sg:tags":[
        "eating"
    ],
    "wof:name":"Don's Diner",
    "wof:placetype":"venue"
},
  "geometry": {"coordinates":[-80.03739899999999,40.471699],"type":"Point"}
}