{
  "type": "Feature",
  "properties": {
    "iso:country":"US",
    "sg:address":"3547 W 26th St",
    "sg:city":"Erie",
    "sg:classifiers":[
        {
            "category":"Health Services",
            "subcategory":"Chiropractor",
            "type":"Services"
        }
    ],
    "sg:phone":"+1 814 833 9399",
    "sg:postcode":"16506",
    "sg:province":"PA",
    "sg:tags":[
        "chiropractic"
    ],
    "wof:name":"Hess Glover Family Chiropractic",
    "wof:placetype":"venue"
},
  "geometry": {"coordinates":[-80.154498,42.081825],"type":"Point"}
}