{
  "type": "Feature",
  "properties": {
    "iso:country":"US",
    "sg:address":"920 Red Lion Rd",
    "sg:city":"Philadelphia",
    "sg:classifiers":[
        {
            "category":"Bakery",
            "type":"Food & Drink"
        },
        {
            "category":"Shopping",
            "subcategory":"Pharmacy",
            "type":"Retail Goods"
        },
        {
            "category":"Food & Beverages",
            "subcategory":"Groceries & Convenience Stores",
            "type":"Retail Goods"
        }
    ],
    "sg:phone":"+1 215 676 6201",
    "sg:postcode":"19115",
    "sg:province":"PA",
    "sg:website":"http://www.albertsons.com/",
    "wof:name":"Albertson's",
    "wof:placetype":"venue"
},
  "geometry": {"coordinates":[-75.030078,40.103287],"type":"Point"}
}