{
  "type": "Feature",
  "properties": {
    "addr:full":"1952 Painters Run Rd Pittsburgh PA 15241",
    "addr:housenumber":"1952",
    "addr:postcode":"15241",
    "addr:street":"Painters Run Rd",
    "iso:country":"US",
    "sg:address":"1952 Painters Run Rd",
    "sg:city":"Pittsburgh",
    "sg:classifiers":[
        {
            "category":"Building & Trades",
            "subcategory":"Construction",
            "type":"Services"
        }
    ],
    "sg:phone":"+1 412 221 2557",
    "sg:postcode":"15241",
    "sg:province":"PA",
    "sg:tags":[
        "business",
        "merchandise",
        "contractor"
    ],
    "wof:name":"Bower Hill Pool & Spa",
    "wof:placetype":"venue"
},
  "geometry": {"coordinates":[-80.08438700000001,40.362986],"type":"Point"}
}