{
  "type": "Feature",
  "properties": {
    "iso:country":"US",
    "sg:address":"143 Hillcroft Way",
    "sg:city":"Newtown",
    "sg:classifiers":[
        {
            "category":"Professional",
            "subcategory":"Computer Services",
            "type":"Services"
        }
    ],
    "sg:phone":"+1 215 968 3332",
    "sg:postcode":"18940",
    "sg:province":"PA",
    "sg:tags":[
        "related",
        "typesetting"
    ],
    "wof:name":"Desktop Associates",
    "wof:placetype":"venue"
},
  "geometry": {"coordinates":[-74.945919,40.21743],"type":"Point"}
}