{
  "type": "Feature",
  "properties": {
    "iso:country":"US",
    "sg:address":"21 Mount Pleasant St",
    "sg:city":"Greensburg",
    "sg:classifiers":[
        {
            "category":"Personal",
            "subcategory":"Beauty Salon",
            "type":"Services"
        }
    ],
    "sg:phone":"+1 724 832 7660",
    "sg:postcode":"15601",
    "sg:province":"PA",
    "wof:name":"Magic Touch Family Styling",
    "wof:placetype":"venue"
},
  "geometry": {"coordinates":[-79.543397,40.296039],"type":"Point"}
}