{
  "type": "Feature",
  "properties": {
    "iso:country":"US",
    "sg:address":"1304 Conshohocken Rd",
    "sg:city":"Conshohocken",
    "sg:classifiers":[
        {
            "category":"Wholesale",
            "subcategory":"Electrical",
            "type":"Manufacturing & Wholesale Goods"
        }
    ],
    "sg:phone":"+1   ",
    "sg:postcode":"19428",
    "sg:province":"PA",
    "sg:tags":[
        "cast",
        "iron",
        "motor"
    ],
    "wof:name":"Charlestown Industries",
    "wof:placetype":"venue"
},
  "geometry": {"coordinates":[-75.318285,40.102425],"type":"Point"}
}