{
  "type": "Feature",
  "properties": {
    "iso:country":"US",
    "sg:address":"415 Saint Clair Ave",
    "sg:city":"Clairton",
    "sg:classifiers":[
        {
            "category":"Coffee & Tea",
            "type":"Food & Drink"
        },
        {
            "category":"Restaurant",
            "type":"Food & Drink"
        }
    ],
    "sg:phone":"+1 412 233 6360",
    "sg:postcode":"15025",
    "sg:province":"PA",
    "sg:tags":[
        "shop",
        "espresso"
    ],
    "wof:name":"Saint Clair Coffee",
    "wof:placetype":"venue"
},
  "geometry": {"coordinates":[-79.88398599999999,40.292744],"type":"Point"}
}