{
  "type": "Feature",
  "properties": {
    "iso:country":"US",
    "sg:address":"1091 Pittsburgh Rd",
    "sg:city":"Valencia",
    "sg:classifiers":[
        {
            "category":"Food & Beverages",
            "subcategory":"Bakery",
            "type":"Retail Goods"
        }
    ],
    "sg:phone":"+1 724 898 0080",
    "sg:postcode":"16059",
    "sg:province":"PA",
    "sg:tags":[
        "bank"
    ],
    "sg:website":"http://www.mowaa.org",
    "wof:name":"Meals On Wheels",
    "wof:placetype":"venue"
},
  "geometry": {"coordinates":[-79.929676,40.714862],"type":"Point"}
}