{
  "type": "Feature",
  "properties": {
    "addr:full":"1 N Broad St West Hazleton PA 18202",
    "addr:housenumber":"1",
    "addr:postcode":"18202",
    "addr:street":"N Broad St",
    "iso:country":"US",
    "sg:address":"1 N Broad St",
    "sg:city":"West Hazleton",
    "sg:classifiers":[
        {
            "category":"Organizations",
            "subcategory":"Labor Organization",
            "type":"Services"
        }
    ],
    "sg:phone":"+1 570 459 8698",
    "sg:postcode":"18202",
    "sg:province":"PA",
    "wof:name":"United Steelworkers Of America",
    "wof:placetype":"venue"
},
  "geometry": {"coordinates":[-75.995682,40.959379],"type":"Point"}
}