{
  "type": "Feature",
  "properties": {
    "iso:country":"US",
    "sg:address":"5112 Umbria St",
    "sg:city":"Philadelphia",
    "sg:classifiers":[
        {
            "category":"Building & Trades",
            "subcategory":"Plumbing",
            "type":"Services"
        }
    ],
    "sg:phone":"+1 215 508 1893",
    "sg:postcode":"19128",
    "sg:province":"PA",
    "sg:tags":[
        "conditioning",
        "air",
        "system",
        "contractor"
    ],
    "wof:name":"Oval Heating & AC",
    "wof:placetype":"venue"
},
  "geometry": {"coordinates":[-75.236642,40.036294],"type":"Point"}
}