{
  "type": "Feature",
  "properties": {
    "iso:country":"US",
    "sg:address":"1619 Union Ave",
    "sg:city":"Natrona Heights",
    "sg:classifiers":[
        {
            "category":"Health Services",
            "subcategory":"Doctor",
            "type":"Services"
        }
    ],
    "sg:phone":"+1 724 224 4000",
    "sg:postcode":"15065",
    "sg:province":"PA",
    "sg:tags":[
        "dentist"
    ],
    "wof:name":"Francis A Mattioli DDS",
    "wof:placetype":"venue"
},
  "geometry": {"coordinates":[-79.72584500000001,40.621507],"type":"Point"}
}