{
  "type": "Feature",
  "properties": {
    "iso:country":"US",
    "sg:address":"100 Superior Ave",
    "sg:city":"Aliquippa",
    "sg:classifiers":[
        {
            "category":"Real Estate",
            "subcategory":"Real Estate Agent",
            "type":"Services"
        }
    ],
    "sg:phone":"+1 724 375 3551",
    "sg:postcode":"15001",
    "sg:province":"PA",
    "sg:tags":[
        "authorities",
        "housing"
    ],
    "wof:name":"Beaver County Housing Auth",
    "wof:placetype":"venue"
},
  "geometry": {"coordinates":[-80.247197,40.619219],"type":"Point"}
}