{
  "type": "Feature",
  "properties": {
    "iso:country":"US",
    "sg:address":"701 E Cumberland St",
    "sg:city":"Lebanon",
    "sg:classifiers":[
        {
            "category":"Professional",
            "subcategory":"Printing & Photocopies",
            "type":"Services"
        }
    ],
    "sg:phone":"+1   ",
    "sg:postcode":"17042",
    "sg:province":"PA",
    "sg:tags":[
        "photocopying"
    ],
    "wof:name":"Copies Now",
    "wof:placetype":"venue"
},
  "geometry": {"coordinates":[-76.398225,40.34253],"type":"Point"}
}