{
  "type": "Feature",
  "properties": {
    "iso:country":"US",
    "sg:address":"1794 Oregon Pike",
    "sg:city":"Lancaster",
    "sg:classifiers":[
        {
            "category":"Organizations",
            "subcategory":"Labor Organization",
            "type":"Services"
        }
    ],
    "sg:phone":"+1   ",
    "sg:postcode":"17601",
    "sg:province":"PA",
    "wof:name":"Building Ind Assoc Lncstr Cnty",
    "wof:placetype":"venue"
},
  "geometry": {"coordinates":[-76.29846499999999,40.073397],"type":"Point"}
}