{
  "type": "Feature",
  "properties": {
    "iso:country":"US",
    "sg:address":"120 Ivy Ct",
    "sg:city":"Upper Darby",
    "sg:classifiers":[
        {
            "category":"Food & Beverages",
            "subcategory":"Groceries & Convenience Stores",
            "type":"Retail Goods"
        }
    ],
    "sg:phone":"+1   ",
    "sg:postcode":"19082",
    "sg:province":"PA",
    "wof:name":"Mansis Luncheonette",
    "wof:placetype":"venue"
},
  "geometry": {"coordinates":[-75.289897,39.96551],"type":"Point"}
}