{
  "type": "Feature",
  "properties": {
    "addr:full":"74 Williams Ln Hatboro PA 19040",
    "addr:housenumber":"74",
    "addr:postcode":"19040",
    "addr:street":"Williams Ln",
    "iso:country":"US",
    "sg:address":"74 Williams Ln",
    "sg:city":"Hatboro",
    "sg:classifiers":[
        {
            "category":"Manufacturing",
            "subcategory":"Metals",
            "type":"Manufacturing & Wholesale Goods"
        }
    ],
    "sg:phone":"+1   ",
    "sg:postcode":"19040",
    "sg:province":"PA",
    "sg:tags":[
        "product",
        "fabricated",
        "mfg"
    ],
    "wof:name":"Forestville Technologies",
    "wof:placetype":"venue"
},
  "geometry": {"coordinates":[-75.109689,40.175189],"type":"Point"}
}