{
  "type": "Feature",
  "properties": {
    "iso:country":"US",
    "sg:address":"600 Bursca Dr",
    "sg:city":"Bridgeville",
    "sg:classifiers":[
        {
            "category":"Wholesale",
            "subcategory":"Non-durable Goods",
            "type":"Manufacturing & Wholesale Goods"
        }
    ],
    "sg:phone":"+1 412 221 3010",
    "sg:postcode":"15017",
    "sg:province":"PA",
    "sg:tags":[
        "dry",
        "goods-wholesale"
    ],
    "wof:name":"Mainline Supply Company",
    "wof:placetype":"venue"
},
  "geometry": {"coordinates":[-80.110229,40.34832],"type":"Point"}
}