{
  "type": "Feature",
  "properties": {
    "addr:full":"604 N Wales Rd North Wales PA 19454",
    "addr:housenumber":"604",
    "addr:postcode":"19454",
    "addr:street":"N Wales Rd",
    "iso:country":"US",
    "sg:address":"604 N Wales Rd",
    "sg:city":"North Wales",
    "sg:classifiers":[
        {
            "category":"Building & Trades",
            "subcategory":"Plumbing",
            "type":"Services"
        }
    ],
    "sg:phone":"+1   ",
    "sg:postcode":"19454",
    "sg:province":"PA",
    "sg:tags":[
        "contractor"
    ],
    "wof:name":"JRS Heating & Cooling",
    "wof:placetype":"venue"
},
  "geometry": {"coordinates":[-75.284871,40.203368],"type":"Point"}
}