{
  "type": "Feature",
  "properties": {
    "iso:country":"US",
    "sg:address":"1700 Peach St",
    "sg:city":"Erie",
    "sg:classifiers":[
        {
            "category":"Shopping",
            "subcategory":"Discount & Variety Stores",
            "type":"Retail Goods"
        },
        {
            "category":"Shopping",
            "subcategory":"Department Store",
            "type":"Retail Goods"
        }
    ],
    "sg:phone":"+1 814 459 0150",
    "sg:postcode":"16501",
    "sg:province":"PA",
    "sg:tags":[
        "shop"
    ],
    "wof:name":"Dollar General",
    "wof:placetype":"venue"
},
  "geometry": {"coordinates":[-80.080185,42.11954],"type":"Point"}
}