{
  "type": "Feature",
  "properties": {
    "addr:full":"427 Main St Stroudsburg PA 18360",
    "addr:housenumber":"427",
    "addr:postcode":"18360",
    "addr:street":"Main St",
    "iso:country":"US",
    "sg:address":"427 Main St",
    "sg:city":"Stroudsburg",
    "sg:classifiers":[
        {
            "category":"Professional",
            "subcategory":"Printing & Photocopies",
            "type":"Services"
        }
    ],
    "sg:phone":"+1 570 420 1530",
    "sg:postcode":"18360",
    "sg:province":"PA",
    "sg:tags":[
        "duplicating",
        "copying"
    ],
    "wof:name":"Local Color",
    "wof:placetype":"venue"
},
  "geometry": {"coordinates":[-75.18997400000001,40.986805],"type":"Point"}
}