{
  "type": "Feature",
  "properties": {
    "iso:country":"US",
    "sg:address":"150 Heisey Rd",
    "sg:city":"Annville",
    "sg:classifiers":[
        {
            "category":"Shopping",
            "subcategory":"Clothing, Apparel, & Fashions",
            "type":"Retail Goods"
        },
        {
            "category":"Utilities",
            "subcategory":"Water",
            "type":"Services"
        },
        {
            "category":"Sports & Exercise",
            "subcategory":"Race Track",
            "type":"Entertainment"
        }
    ],
    "sg:phone":"+1 717 867 1651",
    "sg:postcode":"17003",
    "sg:province":"PA",
    "sg:tags":[
        "apparel",
        "equipment",
        "horse",
        "barn",
        "riding"
    ],
    "sg:website":"http://www.hhtackshop.com",
    "wof:name":"H & H Tack Shop Inc",
    "wof:placetype":"venue"
},
  "geometry": {"coordinates":[-76.515021,40.335994],"type":"Point"}
}