{
  "type": "Feature",
  "properties": {
    "addr:full":"1021 Wellington Rd Jenkintown PA 19046",
    "addr:housenumber":"1021",
    "addr:postcode":"19046",
    "addr:street":"Wellington Rd",
    "iso:country":"US",
    "sg:address":"1021 Wellington Rd",
    "sg:city":"Jenkintown",
    "sg:classifiers":[
        {
            "category":"Professional",
            "type":"Services"
        }
    ],
    "sg:phone":"+1   ",
    "sg:postcode":"19046",
    "sg:province":"PA",
    "wof:name":"Michael J Palazzolo",
    "wof:placetype":"venue"
},
  "geometry": {"coordinates":[-75.11699900000001,40.085169],"type":"Point"}
}