{
  "type": "Feature",
  "properties": {
    "addr:full":"295 Millers Run Rd Bridgeville PA 15017",
    "addr:housenumber":"295",
    "addr:postcode":"15017",
    "addr:street":"Millers Run Rd",
    "iso:country":"US",
    "sg:address":"295 Millers Run Rd",
    "sg:city":"Bridgeville",
    "sg:classifiers":[
        {
            "category":"Government",
            "subcategory":"Office",
            "type":"Public Place"
        }
    ],
    "sg:phone":"+1 412 221 3353",
    "sg:postcode":"15017",
    "sg:province":"PA",
    "wof:name":"Allegheny County Magisterial",
    "wof:placetype":"venue"
},
  "geometry": {"coordinates":[-80.11658300000001,40.355392],"type":"Point"}
}