{
  "type": "Feature",
  "properties": {
    "iso:country":"US",
    "sg:address":"1009 Russellton Rd",
    "sg:city":"Cheswick",
    "sg:classifiers":[
        {
            "category":"Retail",
            "subcategory":"Auto Repair",
            "type":"Services"
        }
    ],
    "sg:phone":"+1 724 274 5755",
    "sg:postcode":"15024",
    "sg:province":"PA",
    "sg:tags":[
        "repairing",
        "automotive",
        "general",
        "automobile"
    ],
    "wof:name":"Bochek Auto Body Inc",
    "wof:placetype":"venue"
},
  "geometry": {"coordinates":[-79.819427,40.55584],"type":"Point"}
}