{
  "type": "Feature",
  "properties": {
    "addr:full":"1560 OLD YORK RD ABINGTON PA 19001",
    "addr:housenumber":"1560",
    "addr:postcode":"19001",
    "addr:street":"Old York Rd",
    "iso:country":"US",
    "sg:address":"1560 OLD YORK RD",
    "sg:city":"ABINGTON",
    "sg:classifiers":[
        {
            "category":"Professional",
            "subcategory":"Business Services",
            "type":"Services"
        }
    ],
    "sg:phone":"+1 215 657 7400",
    "sg:postcode":"19001",
    "sg:province":"PA",
    "sg:tags":[
        "consultant",
        "coach"
    ],
    "sg:website":"http://www.oneilleb.com",
    "wof:name":"Oneill Employee Benefits",
    "wof:placetype":"venue"
},
  "geometry": {"coordinates":[-75.116793,40.128443],"type":"Point"}
}