{
  "type": "Feature",
  "properties": {
    "iso:country":"US",
    "sg:address":"133 Chicora Rd",
    "sg:city":"Chicora",
    "sg:classifiers":[
        {
            "category":"Building & Trades",
            "subcategory":"Electrical",
            "type":"Services"
        }
    ],
    "sg:phone":"+1 724 445 7635",
    "sg:postcode":"16025",
    "sg:province":"PA",
    "sg:tags":[
        "industrial",
        "electrician",
        "contractors-commercial",
        "electric"
    ],
    "wof:name":"Eva Electric",
    "wof:placetype":"venue"
},
  "geometry": {"coordinates":[-79.73542,40.95558],"type":"Point"}
}