{
  "type": "Feature",
  "properties": {
    "iso:country":"US",
    "sg:address":"133 Cambridge Dr",
    "sg:city":"Glen Mills",
    "sg:classifiers":[
        {
            "category":"Professional",
            "type":"Services"
        }
    ],
    "sg:phone":"+1   ",
    "sg:postcode":"19342",
    "sg:province":"PA",
    "wof:name":"Evrserv Inc",
    "wof:placetype":"venue"
},
  "geometry": {"coordinates":[-75.497372,39.864011],"type":"Point"}
}