{
  "type": "Feature",
  "properties": {
    "iso:country":"US",
    "sg:address":"296 Parker Dr",
    "sg:city":"Pittsburgh",
    "sg:classifiers":[
        {
            "category":"Shopping",
            "subcategory":"Clothing, Apparel, & Fashions",
            "type":"Retail Goods"
        }
    ],
    "sg:phone":"+1   ",
    "sg:postcode":"15216",
    "sg:province":"PA",
    "wof:name":"Annies Intimate Boutique",
    "wof:placetype":"venue"
},
  "geometry": {"coordinates":[-80.05169600000001,40.390714],"type":"Point"}
}