{
  "type": "Feature",
  "properties": {
    "iso:country":"US",
    "sg:address":"619 N 11th St",
    "sg:city":"Philadelphia",
    "sg:classifiers":[
        {
            "category":"Wholesale",
            "subcategory":"Non-durable Goods",
            "type":"Manufacturing & Wholesale Goods"
        }
    ],
    "sg:phone":"+1 215 769 1607",
    "sg:postcode":"19123",
    "sg:province":"PA",
    "sg:tags":[
        "dry",
        "goods-wholesale"
    ],
    "wof:name":"Sun Wholesales Inc",
    "wof:placetype":"venue"
},
  "geometry": {"coordinates":[-75.155762,39.963379],"type":"Point"}
}