{
  "type": "Feature",
  "properties": {
    "iso:country":"US",
    "sg:address":"1515 Market St Ste 1508",
    "sg:city":"Philadelphia",
    "sg:classifiers":[
        {
            "category":"Professional",
            "subcategory":"Lawyer & Legal Services",
            "type":"Services"
        }
    ],
    "sg:phone":"+1 215 851 8080",
    "sg:postcode":"19102",
    "sg:province":"PA",
    "wof:name":"Greenfield Stephen J",
    "wof:placetype":"venue"
},
  "geometry": {"coordinates":[-75.16547300000001,39.952773],"type":"Point"}
}