{
  "type": "Feature",
  "properties": {
    "iso:country":"US",
    "sg:address":"236 Windermere Ave",
    "sg:city":"Lansdowne",
    "sg:classifiers":[
        {
            "category":"Professional",
            "type":"Services"
        }
    ],
    "sg:phone":"+1   ",
    "sg:postcode":"19050",
    "sg:province":"PA",
    "wof:name":"Diet Works",
    "wof:placetype":"venue"
},
  "geometry": {"coordinates":[-75.280023,39.944598],"type":"Point"}
}