{
  "type": "Feature",
  "properties": {
    "iso:country":"US",
    "sg:address":"1315 Stark Rd",
    "sg:city":"Bethlehem",
    "sg:classifiers":[
        {
            "category":"Airline",
            "type":"Transportation"
        }
    ],
    "sg:phone":"+1 610 691 2128",
    "sg:postcode":"18017",
    "sg:province":"PA",
    "sg:tags":[
        "aircraft-charter",
        "leasing",
        "rental"
    ],
    "sg:website":"http://www.advancedaircraftcharter.com",
    "wof:name":"Advanced Aircraft Charter Inc",
    "wof:placetype":"venue"
},
  "geometry": {"coordinates":[-75.404669,40.668051],"type":"Point"}
}