{
  "type": "Feature",
  "properties": {
    "iso:country":"US",
    "sg:address":"3649 Market St",
    "sg:city":"Camp Hill",
    "sg:classifiers":[
        {
            "category":"Restaurant",
            "type":"Food & Drink"
        }
    ],
    "sg:phone":"+1 717 731 0995",
    "sg:postcode":"17011",
    "sg:province":"PA",
    "sg:tags":[
        "pizza",
        "italian"
    ],
    "wof:name":"Peppino's Italian Restaurant",
    "wof:placetype":"venue"
},
  "geometry": {"coordinates":[-76.945297,40.2388],"type":"Point"}
}