{
  "type": "Feature",
  "properties": {
    "iso:country":"US",
    "sg:address":"113 Grist Mill Rd",
    "sg:city":"Boyertown",
    "sg:classifiers":[
        {
            "category":"Building & Trades",
            "subcategory":"Plumbing",
            "type":"Services"
        }
    ],
    "sg:phone":"+1 610 367 7824",
    "sg:postcode":"19512",
    "sg:province":"PA",
    "sg:tags":[
        "conditioning",
        "air",
        "system",
        "contractor"
    ],
    "wof:name":"R T Rhoads Co",
    "wof:placetype":"venue"
},
  "geometry": {"coordinates":[-75.68108700000001,40.290032],"type":"Point"}
}