{
  "type": "Feature",
  "properties": {
    "iso:country":"US",
    "sg:address":"1496 Orchard Ln",
    "sg:city":"Boyertown",
    "sg:classifiers":[
        {
            "category":"Farming",
            "subcategory":"Farm",
            "type":"Manufacturing & Wholesale Goods"
        }
    ],
    "sg:phone":"+1 610 473 9939",
    "sg:postcode":"19512",
    "sg:province":"PA",
    "wof:name":"Ranch Services",
    "wof:placetype":"venue"
},
  "geometry": {"coordinates":[-75.65237399999999,40.357938],"type":"Point"}
}