{
  "type": "Feature",
  "properties": {
    "iso:country":"US",
    "sg:address":"Citizens Bank Park",
    "sg:city":"Philadelphia",
    "sg:classifiers":[
        {
            "category":"Arena",
            "subcategory":"Sports Club",
            "type":"Entertainment"
        }
    ],
    "sg:postcode":"19176",
    "sg:province":"PA",
    "sg:tags":[
        "professional",
        "team"
    ],
    "sg:website":"www.phillies.mlb.com",
    "wof:name":"Philadelphia Phillies",
    "wof:placetype":"venue"
},
  "geometry": {"coordinates":[-75.16643000000001,39.90592],"type":"Point"}
}