{
  "type": "Feature",
  "properties": {
    "iso:country":"US",
    "sg:address":"159 E 1st Ave",
    "sg:city":"Derry",
    "sg:classifiers":[
        {
            "category":"Personal",
            "subcategory":"Tanning Parlor",
            "type":"Services"
        }
    ],
    "sg:phone":"+1 724 694 2910",
    "sg:postcode":"15627",
    "sg:province":"PA",
    "sg:tags":[
        "salon"
    ],
    "wof:name":"Sunkissed Tanning",
    "wof:placetype":"venue"
},
  "geometry": {"coordinates":[-79.299494,40.334309],"type":"Point"}
}