{
  "type": "Feature",
  "properties": {
    "addr:full":"540 Hollywell Ave Chambersburg PA 17201",
    "addr:housenumber":"540",
    "addr:postcode":"17201",
    "addr:street":"Hollywell Ave",
    "iso:country":"US",
    "sg:address":"540 Hollywell Ave",
    "sg:city":"Chambersburg",
    "sg:classifiers":[
        {
            "category":"Wholesale",
            "subcategory":"Machinery & Supplies",
            "type":"Manufacturing & Wholesale Goods"
        },
        {
            "category":"Shopping",
            "type":"Retail Goods"
        }
    ],
    "sg:phone":"+1 717 261 0066",
    "sg:postcode":"17201",
    "sg:province":"PA",
    "sg:tags":[
        "house",
        "construction",
        "cleaning",
        "equipment"
    ],
    "wof:name":"Universal Secure Lift Inc",
    "wof:placetype":"venue"
},
  "geometry": {"coordinates":[-77.666061,39.929941],"type":"Point"}
}