{
  "type": "Feature",
  "properties": {
    "iso:country":"US",
    "sg:address":"556 N Reading Rd",
    "sg:city":"Ephrata",
    "sg:classifiers":[
        {
            "category":"Restaurant",
            "type":"Food & Drink"
        }
    ],
    "sg:phone":"+1 717 733 7300",
    "sg:postcode":"17522",
    "sg:province":"PA",
    "wof:name":"Nikis Family Kitchen",
    "wof:placetype":"venue"
},
  "geometry": {"coordinates":[-76.15945000000001,40.202189],"type":"Point"}
}