{
  "type": "Feature",
  "properties": {
    "addr:full":"1570 Oakland Ave Indiana PA 15701",
    "addr:housenumber":"1570",
    "addr:postcode":"15701",
    "addr:street":"Oakland Ave",
    "iso:country":"US",
    "sg:address":"1570 Oakland Ave",
    "sg:city":"Indiana",
    "sg:classifiers":[
        {
            "category":"Banks & Credit Unions",
            "subcategory":"Bank",
            "type":"Services"
        }
    ],
    "sg:phone":"+1 724 465 2693",
    "sg:postcode":"15701",
    "sg:province":"PA",
    "wof:name":"First Commonwealth Bank",
    "wof:placetype":"venue"
},
  "geometry": {"coordinates":[-79.17130299999999,40.615058],"type":"Point"}
}