{
  "type": "Feature",
  "properties": {
    "iso:country":"US",
    "sg:address":"829 N Providence Rd",
    "sg:city":"Media",
    "sg:classifiers":[
        {
            "category":"Wholesale",
            "subcategory":"Construction Materials",
            "type":"Manufacturing & Wholesale Goods"
        }
    ],
    "sg:phone":"+1   ",
    "sg:postcode":"19063",
    "sg:province":"PA",
    "sg:tags":[
        "windows",
        "door"
    ],
    "wof:name":"Newtown Window & Door",
    "wof:placetype":"venue"
},
  "geometry": {"coordinates":[-75.386971,39.929094],"type":"Point"}
}