{
  "type": "Feature",
  "properties": {
    "iso:country":"US",
    "sg:address":"816 Washington St",
    "sg:city":"Bentleyville",
    "sg:classifiers":[
        {
            "category":"Professional",
            "type":"Services"
        }
    ],
    "sg:phone":"+1   ",
    "sg:postcode":"15314",
    "sg:province":"PA",
    "wof:name":"Waynettes Wonders",
    "wof:placetype":"venue"
},
  "geometry": {"coordinates":[-80.01379,40.122465],"type":"Point"}
}