{
  "type": "Feature",
  "properties": {
    "iso:country":"US",
    "sg:address":"1166 W Main St",
    "sg:city":"Ephrata",
    "sg:classifiers":[
        {
            "category":"Building & Trades",
            "subcategory":"Construction",
            "type":"Services"
        }
    ],
    "sg:phone":"+1   ",
    "sg:postcode":"17522",
    "sg:province":"PA",
    "sg:tags":[
        "contractor"
    ],
    "wof:name":"B & H Exteriors",
    "wof:placetype":"venue"
},
  "geometry": {"coordinates":[-76.196805,40.192289],"type":"Point"}
}