{
  "type": "Feature",
  "properties": {
    "addr:full":"5 Pine Tree Rd Mountain Top PA 18707",
    "addr:housenumber":"5",
    "addr:postcode":"18707",
    "addr:street":"Pine Tree Rd",
    "iso:country":"US",
    "sg:address":"5 Pine Tree Rd",
    "sg:city":"Mountain Top",
    "sg:classifiers":[
        {
            "category":"Recreation",
            "type":"Entertainment"
        }
    ],
    "sg:phone":"+1   ",
    "sg:postcode":"18707",
    "sg:province":"PA",
    "wof:name":"Powley Enterprises Inc",
    "wof:placetype":"venue"
},
  "geometry": {"coordinates":[-75.872564,41.151362],"type":"Point"}
}