{
  "type": "Feature",
  "properties": {
    "iso:country":"US",
    "sg:address":"916 N Reading Rd",
    "sg:city":"Ephrata",
    "sg:classifiers":[
        {
            "category":"Health Services",
            "subcategory":"Chiropractor",
            "type":"Services"
        }
    ],
    "sg:phone":"+1 717 336 8110",
    "sg:postcode":"17522",
    "sg:province":"PA",
    "wof:name":"Lausch Community Chiropractic",
    "wof:placetype":"venue"
},
  "geometry": {"coordinates":[-76.146968,40.206653],"type":"Point"}
}