{
  "type": "Feature",
  "properties": {
    "iso:country":"US",
    "sg:address":"5201 Old York Rd",
    "sg:city":"Philadelphia",
    "sg:classifiers":[
        {
            "category":"Social Services",
            "subcategory":"Adult Care",
            "type":"Services"
        }
    ],
    "sg:phone":"+1   ",
    "sg:postcode":"19141",
    "sg:province":"PA",
    "sg:tags":[
        "shelter",
        "residential"
    ],
    "wof:name":"Betty Harris Homes Inc",
    "wof:placetype":"venue"
},
  "geometry": {"coordinates":[-75.14539499999999,40.033651],"type":"Point"}
}