{
  "type": "Feature",
  "properties": {
    "addr:full":"601 Upland Ave Brookhaven PA 19015",
    "addr:housenumber":"601",
    "addr:postcode":"19015",
    "addr:street":"Upland Ave",
    "iso:country":"US",
    "sg:address":"601 Upland Ave",
    "sg:city":"Brookhaven",
    "sg:classifiers":[
        {
            "category":"Professional",
            "subcategory":"Printing & Photocopies",
            "type":"Services"
        }
    ],
    "sg:phone":"+1   ",
    "sg:postcode":"19015",
    "sg:province":"PA",
    "sg:tags":[
        "photocopying"
    ],
    "wof:name":"Jvs Copy Services",
    "wof:placetype":"venue"
},
  "geometry": {"coordinates":[-75.37947699999999,39.854689],"type":"Point"}
}