{
  "type": "Feature",
  "properties": {
    "addr:full":"52 Highland Ave Bethlehem PA 18017",
    "addr:housenumber":"52",
    "addr:postcode":"18017",
    "addr:street":"Highland Ave",
    "iso:country":"US",
    "sg:address":"52 Highland Ave",
    "sg:city":"Bethlehem",
    "sg:classifiers":[
        {
            "category":"Health Services",
            "subcategory":"Doctor",
            "type":"Services"
        }
    ],
    "sg:phone":"+1 610 865 1144",
    "sg:postcode":"18017",
    "sg:province":"PA",
    "wof:name":"Healthsouth Diagnostic Center of Lehigh Valley",
    "wof:placetype":"venue"
},
  "geometry": {"coordinates":[-75.380501,40.668201],"type":"Point"}
}