{
  "type": "Feature",
  "properties": {
    "iso:country":"US",
    "sg:address":"1660 W High St",
    "sg:city":"Pottstown",
    "sg:classifiers":[
        {
            "category":"Autos & Motor Vehicles",
            "subcategory":"Auto Supplies",
            "type":"Retail Goods"
        },
        {
            "category":"Manufacturing",
            "subcategory":"Motor Vehicles & Parts",
            "type":"Manufacturing & Wholesale Goods"
        },
        {
            "category":"Wholesale",
            "subcategory":"Auto Parts",
            "type":"Manufacturing & Wholesale Goods"
        },
        {
            "category":"Retail",
            "subcategory":"Auto Repair",
            "type":"Services"
        }
    ],
    "sg:phone":"+1 610 970 2400",
    "sg:postcode":"19464",
    "sg:province":"PA",
    "sg:tags":[
        "body",
        "shop",
        "automobile",
        "supply-wholesale",
        "accessory",
        "equipment",
        "parts",
        "accessories-wholesale",
        "service-equipment",
        "painting",
        "repairing",
        "manufacturer"
    ],
    "wof:name":"Kayfield Automotive Paints",
    "wof:placetype":"venue"
},
  "geometry": {"coordinates":[-75.68902300000001,40.24654],"type":"Point"}
}