{
  "type": "Feature",
  "properties": {
    "iso:country":"US",
    "sg:address":"313 Urban Ave",
    "sg:city":"Norwood",
    "sg:classifiers":[
        {
            "category":"Professional",
            "type":"Services"
        }
    ],
    "sg:phone":"+1   ",
    "sg:postcode":"19074",
    "sg:province":"PA",
    "wof:name":"Fanelli",
    "wof:placetype":"venue"
},
  "geometry": {"coordinates":[-75.303595,39.896402],"type":"Point"}
}