{
  "type": "Feature",
  "properties": {
    "iso:country":"US",
    "sg:address":"124 N Chester Rd",
    "sg:city":"West Chester",
    "sg:classifiers":[
        {
            "category":"Building & Trades",
            "subcategory":"Construction",
            "type":"Services"
        }
    ],
    "sg:phone":"+1   ",
    "sg:postcode":"19380",
    "sg:province":"PA",
    "sg:tags":[
        "contractor"
    ],
    "wof:name":"Gallagher Cngldi Masnry Contrs",
    "wof:placetype":"venue"
},
  "geometry": {"coordinates":[-75.527322,39.96914],"type":"Point"}
}