{
  "type": "Feature",
  "properties": {
    "addr:full":"11131 Law Rd North East PA 16428",
    "addr:housenumber":"11131",
    "addr:postcode":"16428",
    "addr:street":"Law Rd",
    "iso:country":"US",
    "sg:address":"11131 Law Rd",
    "sg:city":"North East",
    "sg:classifiers":[
        {
            "category":"Insurance",
            "subcategory":"Insurance Agent",
            "type":"Services"
        }
    ],
    "sg:phone":"+1 814 725 4291",
    "sg:postcode":"16428",
    "sg:province":"PA",
    "wof:name":"Thrivent Financial-Lutherans",
    "wof:placetype":"venue"
},
  "geometry": {"coordinates":[-79.83668900000001,42.198856],"type":"Point"}
}