{
  "type": "Feature",
  "properties": {
    "addr:full":"2453 Old Philadelphia Pike Lancaster PA 17602",
    "addr:housenumber":"2453",
    "addr:postcode":"17602",
    "addr:street":"Old Philadelphia Pike",
    "iso:country":"US",
    "sg:address":"2453 Old Philadelphia Pike",
    "sg:city":"Lancaster",
    "sg:classifiers":[
        {
            "category":"Food & Beverages",
            "subcategory":"Groceries & Convenience Stores",
            "type":"Retail Goods"
        }
    ],
    "sg:phone":"+1 717 392 7533",
    "sg:postcode":"17602",
    "sg:province":"PA",
    "wof:name":"Turkey Hill Mini Market",
    "wof:placetype":"venue"
},
  "geometry": {"coordinates":[-76.19962,40.03942],"type":"Point"}
}