{
  "type": "Feature",
  "properties": {
    "addr:full":"301A W 3rd St Berwick PA 18603",
    "addr:housenumber":"301a",
    "addr:postcode":"18603",
    "addr:street":"W 3Rd St",
    "iso:country":"US",
    "sg:address":"301A W 3rd St",
    "sg:city":"Berwick",
    "sg:classifiers":[
        {
            "category":"Health Services",
            "subcategory":"Doctor",
            "type":"Services"
        }
    ],
    "sg:phone":"+1 570 752 5655",
    "sg:postcode":"18603",
    "sg:province":"PA",
    "sg:tags":[
        "physician",
        "surgeon",
        "surgeons",
        "infectious",
        "disease"
    ],
    "wof:name":"Caring Communities for Aids",
    "wof:placetype":"venue"
},
  "geometry": {"coordinates":[-76.23803700000001,41.054218],"type":"Point"}
}