{
  "type": "Feature",
  "properties": {
    "addr:full":"28 Drummond St Pittston PA 18640",
    "addr:housenumber":"28",
    "addr:postcode":"18640",
    "addr:street":"Drummond St",
    "iso:country":"US",
    "sg:address":"28 Drummond St",
    "sg:city":"Pittston",
    "sg:classifiers":[
        {
            "category":"Wholesale",
            "subcategory":"Construction Materials",
            "type":"Manufacturing & Wholesale Goods"
        }
    ],
    "sg:phone":"+1   ",
    "sg:postcode":"18640",
    "sg:province":"PA",
    "wof:name":"Lynch Contracting Company Inc",
    "wof:placetype":"venue"
},
  "geometry": {"coordinates":[-75.780849,41.330327],"type":"Point"}
}