{
  "type": "Feature",
  "properties": {
    "iso:country":"US",
    "sg:address":"3911 Main St",
    "sg:city":"Homestead",
    "sg:classifiers":[
        {
            "category":"Shopping",
            "subcategory":"News",
            "type":"Retail Goods"
        }
    ],
    "sg:phone":"+1 412 464 9613",
    "sg:postcode":"15120",
    "sg:province":"PA",
    "sg:tags":[
        "dealer"
    ],
    "wof:name":"Galaxy News",
    "wof:placetype":"venue"
},
  "geometry": {"coordinates":[-79.90482900000001,40.382373],"type":"Point"}
}