{
  "type": "Feature",
  "properties": {
    "iso:country":"US",
    "sg:address":"19 Woodside Rd Ste 19F",
    "sg:city":"Ardmore",
    "sg:classifiers":[
        {
            "category":"Personal",
            "subcategory":"Beauty Salon",
            "type":"Services"
        },
        {
            "category":"Personal",
            "subcategory":"Barber",
            "type":"Services"
        }
    ],
    "sg:phone":"+1 610 642 1121",
    "sg:postcode":"19003",
    "sg:province":"PA",
    "sg:tags":[
        "hair",
        "accessory",
        "stylist",
        "supply"
    ],
    "sg:website":"http://www.haircuttery.com/",
    "wof:name":"Hair Cuttery",
    "wof:placetype":"venue"
},
  "geometry": {"coordinates":[-75.295903,40.010717],"type":"Point"}
}