{
  "type": "Feature",
  "properties": {
    "iso:country":"US",
    "sg:address":"131 Knobb Rd",
    "sg:city":"Brownsville",
    "sg:classifiers":[
        {
            "category":"Manufacturing",
            "subcategory":"Metals",
            "type":"Manufacturing & Wholesale Goods"
        }
    ],
    "sg:phone":"+1 724 785 8822",
    "sg:postcode":"15417",
    "sg:province":"PA",
    "sg:tags":[
        "secondary",
        "refining",
        "smelting"
    ],
    "wof:name":"Simyak's Scrap Iron & Metal",
    "wof:placetype":"venue"
},
  "geometry": {"coordinates":[-79.907647,40.032202],"type":"Point"}
}