{
  "type": "Feature",
  "properties": {
    "addr:full":"134 Gun Club Rd York Springs PA 17372",
    "addr:housenumber":"134",
    "addr:postcode":"17372",
    "addr:street":"Gun Club Rd",
    "iso:country":"US",
    "sg:address":"134 Gun Club Rd",
    "sg:city":"York Springs",
    "sg:classifiers":[
        {
            "category":"Building & Trades",
            "subcategory":"Construction",
            "type":"Services"
        }
    ],
    "sg:phone":"+1   ",
    "sg:postcode":"17372",
    "sg:province":"PA",
    "sg:tags":[
        "plumbing",
        "electrical",
        "contractor"
    ],
    "wof:name":"PSI Pumping Solutions Inc",
    "wof:placetype":"venue"
},
  "geometry": {"coordinates":[-77.112785,39.966212],"type":"Point"}
}