{
  "type": "Feature",
  "properties": {
    "addr:full":"25 N Duke St Lancaster PA 17602",
    "addr:housenumber":"25",
    "addr:postcode":"17602",
    "addr:street":"N Duke St",
    "iso:country":"US",
    "sg:address":"25 N Duke St",
    "sg:city":"Lancaster",
    "sg:classifiers":[
        {
            "category":"Banks & Credit Unions",
            "subcategory":"Bank",
            "type":"Services"
        }
    ],
    "sg:phone":"+1 717 396 7505",
    "sg:postcode":"17602",
    "sg:province":"PA",
    "sg:website":"www.blcnet.com",
    "wof:name":"Bank Of Lancaster County",
    "wof:placetype":"venue"
},
  "geometry": {"coordinates":[-76.303607,40.038185],"type":"Point"}
}