{
  "type": "Feature",
  "properties": {
    "iso:country":"US",
    "sg:address":"70 Fraley St",
    "sg:city":"Kane",
    "sg:classifiers":[
        {
            "category":"Food & Beverages",
            "subcategory":"Groceries & Convenience Stores",
            "type":"Retail Goods"
        }
    ],
    "sg:phone":"+1 814 837 9181",
    "sg:postcode":"16735",
    "sg:province":"PA",
    "wof:name":"Amish Deli",
    "wof:placetype":"venue"
},
  "geometry": {"coordinates":[-78.81138900000001,41.652493],"type":"Point"}
}