{
  "type": "Feature",
  "properties": {
    "addr:full":"4 E Kendig Rd Willow Street PA 17584",
    "addr:housenumber":"4",
    "addr:postcode":"17584",
    "addr:street":"E Kendig Rd Willow Street",
    "iso:country":"US",
    "sg:address":"4 E Kendig Rd",
    "sg:city":"Willow Street",
    "sg:classifiers":[
        {
            "category":"Shopping",
            "subcategory":"Clothing, Apparel, & Fashions",
            "type":"Retail Goods"
        }
    ],
    "sg:phone":"+1 717 464 9640",
    "sg:postcode":"17584",
    "sg:province":"PA",
    "wof:name":"Fashion Bug",
    "wof:placetype":"venue"
},
  "geometry": {"coordinates":[-76.27516799999999,39.975794],"type":"Point"}
}