{
  "type": "Feature",
  "properties": {
    "addr:full":"224 E Main St Boalsburg PA 16827",
    "addr:housenumber":"224",
    "addr:postcode":"16827",
    "addr:street":"E Main St",
    "iso:country":"US",
    "sg:address":"224 E Main St",
    "sg:city":"Boalsburg",
    "sg:classifiers":[
        {
            "category":"Government",
            "subcategory":"Office",
            "type":"Public Place"
        }
    ],
    "sg:phone":"+1 814 466 6228",
    "sg:postcode":"16827",
    "sg:province":"PA",
    "sg:tags":[
        "village"
    ],
    "wof:name":"Harris Twp Municipal Ofc",
    "wof:placetype":"venue"
},
  "geometry": {"coordinates":[-77.790931,40.776014],"type":"Point"}
}