{
  "type": "Feature",
  "properties": {
    "iso:country":"US",
    "sg:address":"30 Vine St",
    "sg:city":"Lansdale",
    "sg:classifiers":[
        {
            "category":"Shopping",
            "subcategory":"Computers & Home Electronics",
            "type":"Retail Goods"
        }
    ],
    "sg:phone":"+1 215 703 0145",
    "sg:postcode":"19446",
    "sg:province":"PA",
    "sg:tags":[
        "equipment",
        "dealer"
    ],
    "wof:name":"Sparrow Computer Systems Inc",
    "wof:placetype":"venue"
},
  "geometry": {"coordinates":[-75.286109,40.240915],"type":"Point"}
}