{
  "type": "Feature",
  "properties": {
    "iso:country":"US",
    "sg:address":"2711 Long Farm Ln",
    "sg:city":"Lancaster",
    "sg:classifiers":[
        {
            "category":"Manufacturing",
            "subcategory":"Printing",
            "type":"Manufacturing & Wholesale Goods"
        }
    ],
    "sg:phone":"+1   ",
    "sg:postcode":"17601",
    "sg:province":"PA",
    "sg:tags":[
        "publishing"
    ],
    "wof:name":"Mark A Selvaggio",
    "wof:placetype":"venue"
},
  "geometry": {"coordinates":[-76.285343,40.094901],"type":"Point"}
}