{
  "type": "Feature",
  "properties": {
    "iso:country":"US",
    "sg:address":"1007 E Willow Grove Ave",
    "sg:city":"Glenside",
    "sg:classifiers":[
        {
            "category":"Personal",
            "subcategory":"Beauty Salon",
            "type":"Services"
        },
        {
            "category":"Personal",
            "subcategory":"Barber",
            "type":"Services"
        }
    ],
    "sg:phone":"+1 215 836 7477",
    "sg:postcode":"19038",
    "sg:province":"PA",
    "wof:name":"Gentlemens Preference Ha",
    "wof:placetype":"venue"
},
  "geometry": {"coordinates":[-75.18769899999999,40.083494],"type":"Point"}
}