{
  "type": "Feature",
  "properties": {
    "addr:full":"3600 Saint Davids Rd Newtown Square PA 19073",
    "addr:housenumber":"3600",
    "addr:postcode":"19073",
    "addr:street":"Saint Davids Rd",
    "iso:country":"US",
    "sg:address":"3600 Saint Davids Rd",
    "sg:city":"Newtown Square",
    "sg:classifiers":[
        {
            "category":"Shopping",
            "subcategory":"Bicycles & Sporting Goods",
            "type":"Retail Goods"
        }
    ],
    "sg:phone":"+1   ",
    "sg:postcode":"19073",
    "sg:province":"PA",
    "sg:tags":[
        "shop",
        "golf"
    ],
    "wof:name":"Aronimink Golf Shop",
    "wof:placetype":"venue"
},
  "geometry": {"coordinates":[-75.41598399999999,40.009924],"type":"Point"}
}