{
  "type": "Feature",
  "properties": {
    "iso:country":"US",
    "sg:address":"1847 State Rte 405",
    "sg:city":"Muncy",
    "sg:classifiers":[
        {
            "category":"Cinema",
            "subcategory":"Movie Rental",
            "type":"Entertainment"
        }
    ],
    "sg:phone":"+1   ",
    "sg:postcode":"17756",
    "sg:province":"PA",
    "sg:tags":[
        "video",
        "tape"
    ],
    "wof:name":"M G A Inc",
    "wof:placetype":"venue"
},
  "geometry": {"coordinates":[-76.74312999999999,41.222197],"type":"Point"}
}