{
  "type": "Feature",
  "properties": {
    "iso:country":"US",
    "sg:address":"816 N 4th St",
    "sg:city":"Philadelphia",
    "sg:classifiers":[
        {
            "category":"Restaurant",
            "type":"Food & Drink"
        }
    ],
    "sg:phone":"+1 215 629 9808",
    "sg:postcode":"19123",
    "sg:province":"PA",
    "sg:tags":[
        "shop",
        "coffee",
        "eating"
    ],
    "wof:name":"Latte Lounge",
    "wof:placetype":"venue"
},
  "geometry": {"coordinates":[-75.144238,39.964513],"type":"Point"}
}