{
  "type": "Feature",
  "properties": {
    "addr:full":"3302 Derry St Harrisburg PA 17111",
    "addr:housenumber":"3302",
    "addr:postcode":"17111",
    "addr:street":"Derry St",
    "iso:country":"US",
    "sg:address":"3302 Derry St",
    "sg:city":"Harrisburg",
    "sg:classifiers":[
        {
            "category":"Restaurant",
            "type":"Food & Drink"
        }
    ],
    "sg:phone":"+1 717 565 1171",
    "sg:postcode":"17111",
    "sg:province":"PA",
    "sg:tags":[
        "diner"
    ],
    "wof:name":"City Line Diner",
    "wof:placetype":"venue"
},
  "geometry": {"coordinates":[-76.834577,40.259443],"type":"Point"}
}