{
  "type": "Feature",
  "properties": {
    "addr:full":"1991 Northampton St Easton PA 18042",
    "addr:housenumber":"1991",
    "addr:postcode":"18042",
    "addr:street":"Northampton St",
    "iso:country":"US",
    "sg:address":"1991 Northampton St",
    "sg:city":"Easton",
    "sg:classifiers":[
        {
            "category":"Manufacturing",
            "subcategory":"Printing",
            "type":"Manufacturing & Wholesale Goods"
        }
    ],
    "sg:phone":"+1 610 738 9300",
    "sg:postcode":"18042",
    "sg:province":"PA",
    "sg:tags":[
        "printer"
    ],
    "wof:name":"Science Press",
    "wof:placetype":"venue"
},
  "geometry": {"coordinates":[-75.23924599999999,40.689493],"type":"Point"}
}