{
  "type": "Feature",
  "properties": {
    "iso:country":"US",
    "sg:address":"3397 Lincoln Hwy E",
    "sg:city":"Paradise",
    "sg:classifiers":[
        {
            "category":"Health Services",
            "subcategory":"Clinic",
            "type":"Services"
        }
    ],
    "sg:phone":"+1   ",
    "sg:postcode":"17562",
    "sg:province":"PA",
    "sg:tags":[
        "mental",
        "rehabilitation"
    ],
    "wof:name":"Community Services Group",
    "wof:placetype":"venue"
},
  "geometry": {"coordinates":[-76.091587,40.002321],"type":"Point"}
}