{
  "type": "Feature",
  "properties": {
    "addr:full":"8000 High School Rd Elkins Park PA 19027",
    "addr:housenumber":"8000",
    "addr:postcode":"19027",
    "addr:street":"High School Rd",
    "iso:country":"US",
    "sg:address":"8000 High School Rd",
    "sg:city":"Elkins Park",
    "sg:classifiers":[
        {
            "category":"Real Estate",
            "subcategory":"Real Estate Operator",
            "type":"Services"
        }
    ],
    "sg:phone":"+1   ",
    "sg:postcode":"19027",
    "sg:province":"PA",
    "sg:tags":[
        "building",
        "apartment"
    ],
    "wof:name":"Elkins Park Garden Apartments",
    "wof:placetype":"venue"
},
  "geometry": {"coordinates":[-75.12408499999999,40.071992],"type":"Point"}
}