{
  "type": "Feature",
  "properties": {
    "addr:full":"250 W Chester Rd West Chester PA 19382",
    "addr:housenumber":"250",
    "addr:postcode":"19382",
    "addr:street":"W Chester Rd",
    "iso:country":"US",
    "sg:address":"250 W Chester Rd",
    "sg:city":"West Chester",
    "sg:classifiers":[
        {
            "category":"Manufacturing",
            "subcategory":"Printing",
            "type":"Manufacturing & Wholesale Goods"
        }
    ],
    "sg:phone":"+1 610 696 1775",
    "sg:postcode":"19382",
    "sg:province":"PA",
    "sg:tags":[
        "newspaper"
    ],
    "sg:website":"www.dailylocal.com",
    "wof:name":"Daily Local News",
    "wof:placetype":"venue"
},
  "geometry": {"coordinates":[-75.54463,39.9107],"type":"Point"}
}