{
  "type": "Feature",
  "properties": {
    "addr:full":"453 Norland Ave Chambersburg PA 17201",
    "addr:housenumber":"453",
    "addr:postcode":"17201",
    "addr:street":"Norland Ave",
    "iso:country":"US",
    "sg:address":"453 Norland Ave",
    "sg:city":"Chambersburg",
    "sg:classifiers":[
        {
            "category":"Real Estate",
            "subcategory":"Real Estate Agent",
            "type":"Services"
        }
    ],
    "sg:phone":"+1   ",
    "sg:postcode":"17201",
    "sg:province":"PA",
    "wof:name":"Lynn Byers",
    "wof:placetype":"venue"
},
  "geometry": {"coordinates":[-77.645044,39.94923],"type":"Point"}
}