{
  "type": "Feature",
  "properties": {
    "addr:full":"150 Hunterstown Hampton Rd Gettysburg PA 17325",
    "addr:housenumber":"150",
    "addr:postcode":"17325",
    "addr:street":"Hunterstown Hampton Rd",
    "iso:country":"US",
    "sg:address":"150 Hunterstown Hampton Rd",
    "sg:city":"Gettysburg",
    "sg:classifiers":[
        {
            "category":"Social Services",
            "subcategory":"Child Care",
            "type":"Services"
        }
    ],
    "sg:phone":"+1 717 337 2619",
    "sg:postcode":"17325",
    "sg:province":"PA",
    "sg:tags":[
        "day"
    ],
    "wof:name":"Babes In Arms Inc",
    "wof:placetype":"venue"
},
  "geometry": {"coordinates":[-77.15547599999999,39.880886],"type":"Point"}
}