{
  "type": "Feature",
  "properties": {
    "iso:country":"US",
    "sg:address":"35990 Lake Rd",
    "sg:city":"Union City",
    "sg:classifiers":[
        {
            "category":"Personal",
            "subcategory":"Beauty Salon",
            "type":"Services"
        }
    ],
    "sg:phone":"+1 814 694 3179",
    "sg:postcode":"16438",
    "sg:province":"PA",
    "wof:name":"Canadohta Clipper",
    "wof:placetype":"venue"
},
  "geometry": {"coordinates":[-79.832013,41.807419],"type":"Point"}
}