{
  "type": "Feature",
  "properties": {
    "iso:country":"US",
    "sg:address":"692 W Schuylkill Rd",
    "sg:city":"Pottstown",
    "sg:classifiers":[
        {
            "category":"Manufacturing",
            "subcategory":"Building Materials",
            "type":"Manufacturing & Wholesale Goods"
        },
        {
            "category":"Home & Garden",
            "subcategory":"Furniture",
            "type":"Retail Goods"
        }
    ],
    "sg:phone":"+1 610 326 8925",
    "sg:postcode":"19465",
    "sg:province":"PA",
    "sg:tags":[
        "mfg",
        "wood",
        "kitchen",
        "cabinet"
    ],
    "wof:name":"King's Furniture",
    "wof:placetype":"venue"
},
  "geometry": {"coordinates":[-75.66662599999999,40.233359],"type":"Point"}
}