{
  "type": "Feature",
  "properties": {
    "iso:country":"US",
    "sg:address":"1711 Boston Hollow Rd",
    "sg:city":"Mckeesport",
    "sg:classifiers":[
        {
            "category":"Insurance",
            "subcategory":"Insurance Agent",
            "type":"Services"
        }
    ],
    "sg:phone":"+1 412 664 4438",
    "sg:postcode":"15037",
    "sg:province":"PA",
    "wof:name":"Gibbons Agency",
    "wof:placetype":"venue"
},
  "geometry": {"coordinates":[-79.83396399999999,40.291579],"type":"Point"}
}