{
  "type": "Feature",
  "properties": {
    "addr:full":"3120 S 3rd St Philadelphia PA 19148",
    "addr:housenumber":"3120",
    "addr:postcode":"19148",
    "addr:street":"S 3Rd St",
    "iso:country":"US",
    "sg:address":"3120 S 3rd St",
    "sg:city":"Philadelphia",
    "sg:classifiers":[
        {
            "category":"Food & Beverages",
            "subcategory":"Meat & Fish",
            "type":"Retail Goods"
        }
    ],
    "sg:phone":"+1 215 468 8001",
    "sg:postcode":"19148",
    "sg:province":"PA",
    "sg:tags":[
        "seafood",
        "seafood-wholesale",
        "market"
    ],
    "wof:name":"M&M Seafood",
    "wof:placetype":"venue"
},
  "geometry": {"coordinates":[-75.153713,39.907693],"type":"Point"}
}