{
  "type": "Feature",
  "properties": {
    "addr:full":"523 Quigley Ave Willow Grove PA 19090",
    "addr:housenumber":"523",
    "addr:postcode":"19090",
    "addr:street":"Quigley Ave",
    "iso:country":"US",
    "sg:address":"523 Quigley Ave",
    "sg:city":"Willow Grove",
    "sg:classifiers":[
        {
            "category":"Building & Trades",
            "subcategory":"Construction",
            "type":"Services"
        }
    ],
    "sg:phone":"+1   ",
    "sg:postcode":"19090",
    "sg:province":"PA",
    "sg:tags":[
        "house"
    ],
    "wof:name":"Mark Craft Builders",
    "wof:placetype":"venue"
},
  "geometry": {"coordinates":[-75.102769,40.136126],"type":"Point"}
}