{
  "type": "Feature",
  "properties": {
    "iso:country":"US",
    "sg:address":"666 Davisville Rd",
    "sg:city":"Willow Grove",
    "sg:classifiers":[
        {
            "category":"Shopping",
            "type":"Retail Goods"
        }
    ],
    "sg:phone":"+1   ",
    "sg:postcode":"19090",
    "sg:province":"PA",
    "sg:tags":[
        "machine",
        "business"
    ],
    "wof:name":"Excel Document Solutions Inc",
    "wof:placetype":"venue"
},
  "geometry": {"coordinates":[-75.1057,40.151699],"type":"Point"}
}