{
  "type": "Feature",
  "properties": {
    "iso:country":"US",
    "sg:address":"930 Liberty St",
    "sg:city":"Erie",
    "sg:classifiers":[
        {
            "category":"Organizations",
            "subcategory":"Religious Organization",
            "type":"Services"
        }
    ],
    "sg:phone":"+1 814 454 2426",
    "sg:postcode":"16502",
    "sg:province":"PA",
    "sg:tags":[
        "place",
        "worship",
        "church"
    ],
    "wof:name":"Jewish Temple",
    "wof:placetype":"venue"
},
  "geometry": {"coordinates":[-80.100132,42.119935],"type":"Point"}
}