{
  "type": "Feature",
  "properties": {
    "iso:country":"US",
    "sg:address":"3528 Henry Ave",
    "sg:city":"Philadelphia",
    "sg:classifiers":[
        {
            "category":"Building & Trades",
            "subcategory":"Construction",
            "type":"Services"
        }
    ],
    "sg:phone":"+1 267 397 3003",
    "sg:postcode":"19129",
    "sg:province":"PA",
    "sg:tags":[
        "home",
        "maintenance",
        "repair"
    ],
    "sg:website":"http://www.locksmithphiladelphiapa.biz",
    "wof:name":"The City # 1Locksmith",
    "wof:placetype":"venue"
},
  "geometry": {"coordinates":[-75.186376,40.015321],"type":"Point"}
}