{
  "type": "Feature",
  "properties": {
    "iso:country":"US",
    "sg:address":"423 E Reliance Rd",
    "sg:city":"Telford",
    "sg:classifiers":[
        {
            "category":"Restaurant",
            "type":"Food & Drink"
        }
    ],
    "sg:phone":"+1 215 723 1331",
    "sg:postcode":"18969",
    "sg:province":"PA",
    "wof:name":"Brambleberry Inc",
    "wof:placetype":"venue"
},
  "geometry": {"coordinates":[-75.318056,40.32815],"type":"Point"}
}