{
  "type": "Feature",
  "properties": {
    "addr:full":"8 Greenacres Kutztown PA 19530",
    "addr:housenumber":"8",
    "addr:postcode":"19530",
    "addr:street":"Greenacres",
    "iso:country":"US",
    "sg:address":"8 Greenacres",
    "sg:city":"Kutztown",
    "sg:classifiers":[
        {
            "category":"Building & Trades",
            "subcategory":"Construction",
            "type":"Services"
        }
    ],
    "sg:phone":"+1   ",
    "sg:postcode":"19530",
    "sg:province":"PA",
    "sg:tags":[
        "masonry"
    ],
    "wof:name":"Woodland Masonry",
    "wof:placetype":"venue"
},
  "geometry": {"coordinates":[-75.765073,40.579658],"type":"Point"}
}