{
  "type": "Feature",
  "properties": {
    "iso:country":"US",
    "sg:address":"1520 O'Block Rd",
    "sg:city":"Pittsburgh",
    "sg:classifiers":[
        {
            "category":"Building & Trades",
            "subcategory":"Construction",
            "type":"Services"
        }
    ],
    "sg:phone":"+1   ",
    "sg:postcode":"15239",
    "sg:province":"PA",
    "sg:tags":[
        "remodeling",
        "contractor"
    ],
    "wof:name":"Deks Remodeling",
    "wof:placetype":"venue"
},
  "geometry": {"coordinates":[-79.93181,40.470271],"type":"Point"}
}