{
  "type": "Feature",
  "properties": {
    "addr:full":"2 Rittenhouse Rd Frenchtown PA 08825",
    "addr:housenumber":"2",
    "addr:postcode":"08825",
    "addr:street":"Rittenhouse Rd",
    "iso:country":"US",
    "sg:address":"2 Rittenhouse Rd",
    "sg:city":"Frenchtown",
    "sg:classifiers":[
        {
            "category":"Parking",
            "type":"Transportation"
        }
    ],
    "sg:phone":"+1   ",
    "sg:postcode":"08825",
    "sg:province":"PA",
    "sg:tags":[
        "automobile"
    ],
    "wof:name":"Parking Solutions Inc",
    "wof:placetype":"venue"
},
  "geometry": {"coordinates":[-75.019052,40.539995],"type":"Point"}
}