{
  "type": "Feature",
  "properties": {
    "addr:full":"760 Morwood Rd Telford PA 18969",
    "addr:housenumber":"760",
    "addr:postcode":"18969",
    "addr:street":"Morwood Rd",
    "iso:country":"US",
    "sg:address":"760 Morwood Rd",
    "sg:city":"Telford",
    "sg:classifiers":[
        {
            "category":"Farming",
            "subcategory":"Farm",
            "type":"Manufacturing & Wholesale Goods"
        }
    ],
    "sg:phone":"+1 215 723 5604",
    "sg:postcode":"18969",
    "sg:province":"PA",
    "sg:tags":[
        "crop"
    ],
    "wof:name":"Kulp, John",
    "wof:placetype":"venue"
},
  "geometry": {"coordinates":[-75.39569899999999,40.312012],"type":"Point"}
}