{
  "type": "Feature",
  "properties": {
    "addr:full":"64 Bridge St Tunkhannock PA 18657",
    "addr:housenumber":"64",
    "addr:postcode":"18657",
    "addr:street":"Bridge St",
    "iso:country":"US",
    "sg:address":"64 Bridge St",
    "sg:city":"Tunkhannock",
    "sg:classifiers":[
        {
            "category":"Retail",
            "subcategory":"Funeral Services",
            "type":"Services"
        }
    ],
    "sg:phone":"+1 570 836 2294",
    "sg:postcode":"18657",
    "sg:province":"PA",
    "sg:tags":[
        "plan"
    ],
    "wof:name":"Harding's Furniture Store",
    "wof:placetype":"venue"
},
  "geometry": {"coordinates":[-75.94704,41.53805],"type":"Point"}
}