{
  "type": "Feature",
  "properties": {
    "iso:country":"US",
    "sg:address":"733 N Highland Ave",
    "sg:city":"Pittsburgh",
    "sg:classifiers":[
        {
            "category":"Health Services",
            "subcategory":"Health Practitioner",
            "type":"Services"
        }
    ],
    "sg:phone":"+1   ",
    "sg:postcode":"15206",
    "sg:province":"PA",
    "sg:tags":[
        "psychotherapy"
    ],
    "wof:name":"Annette Kolski-Andreaco",
    "wof:placetype":"venue"
},
  "geometry": {"coordinates":[-79.92119599999999,40.469474],"type":"Point"}
}