{
  "type": "Feature",
  "properties": {
    "iso:country":"US",
    "sg:address":"10 Hilloch Ln",
    "sg:city":"Chadds Ford",
    "sg:classifiers":[
        {
            "category":"Professional",
            "subcategory":"Lawyer & Legal Services",
            "type":"Services"
        }
    ],
    "sg:phone":"+1 610 361 1983",
    "sg:postcode":"19317",
    "sg:province":"PA",
    "wof:name":"Wilf Nahid Attorney",
    "wof:placetype":"venue"
},
  "geometry": {"coordinates":[-75.567398,39.8666],"type":"Point"}
}