{
  "type": "Feature",
  "properties": {
    "iso:country":"US",
    "sg:address":"4165 Jasmine Pl",
    "sg:city":"Mount Joy",
    "sg:classifiers":[
        {
            "category":"Freight",
            "type":"Transportation"
        }
    ],
    "sg:phone":"+1   ",
    "sg:postcode":"17552",
    "sg:province":"PA",
    "sg:tags":[
        "local",
        "storage",
        "trucking"
    ],
    "wof:name":"Ressler Transport",
    "wof:placetype":"venue"
},
  "geometry": {"coordinates":[-76.47453400000001,40.066487],"type":"Point"}
}