{
  "type": "Feature",
  "properties": {
    "iso:country":"US",
    "sg:address":"6262 McGuffey Rd",
    "sg:city":"Lowellville",
    "sg:phone":"+1 330 534 1502",
    "sg:postcode":"44436",
    "sg:province":"PA",
    "sg:tags":[
        "wheat",
        "farm",
        "corn",
        "cash",
        "grain",
        "soybean"
    ],
    "wof:name":"MB Farms",
    "wof:placetype":"venue"
},
  "geometry": {"coordinates":[-80.52555,41.119596],"type":"Point"}
}