{
  "type": "Feature",
  "properties": {
    "iso:country":"US",
    "sg:address":"5741 Verona Rd",
    "sg:city":"Verona",
    "sg:classifiers":[
        {
            "category":"Recreation",
            "type":"Entertainment"
        }
    ],
    "sg:phone":"+1 412 793 2000",
    "sg:postcode":"15147",
    "sg:province":"PA",
    "sg:tags":[
        "course",
        "golf"
    ],
    "wof:name":"Green Oaks Country Club",
    "wof:placetype":"venue"
},
  "geometry": {"coordinates":[-79.837504,40.485854],"type":"Point"}
}