{
  "type": "Feature",
  "properties": {
    "iso:country":"US",
    "sg:address":"726 Red Lion Rd",
    "sg:city":"Philadelphia",
    "sg:classifiers":[
        {
            "category":"Home & Garden",
            "subcategory":"Furniture",
            "type":"Retail Goods"
        }
    ],
    "sg:phone":"+1   ",
    "sg:postcode":"19115",
    "sg:province":"PA",
    "wof:name":"Northeast Furniture",
    "wof:placetype":"venue"
},
  "geometry": {"coordinates":[-75.03299699999999,40.105109],"type":"Point"}
}