{
  "type": "Feature",
  "properties": {
    "iso:country":"US",
    "sg:address":"1 Ppg Pl Ste 1500",
    "sg:city":"Pittsburgh",
    "sg:classifiers":[
        {
            "category":"Professional",
            "subcategory":"Lawyer & Legal Services",
            "type":"Services"
        }
    ],
    "sg:phone":"+1 412 594 5552",
    "sg:postcode":"15222",
    "sg:province":"PA",
    "wof:name":"Segarnick Kenneth G Atty",
    "wof:placetype":"venue"
},
  "geometry": {"coordinates":[-80.003562,40.439918],"type":"Point"}
}