{
  "type": "Feature",
  "properties": {
    "iso:country":"US",
    "sg:address":"193 Walters Rd",
    "sg:city":"New Castle",
    "sg:classifiers":[
        {
            "category":"Building & Trades",
            "subcategory":"Construction",
            "type":"Services"
        }
    ],
    "sg:phone":"+1 724 654 1017",
    "sg:postcode":"16127",
    "sg:province":"PA",
    "sg:tags":[
        "excavation",
        "concrete",
        "contractor"
    ],
    "wof:name":"Walter K L Excavating",
    "wof:placetype":"venue"
},
  "geometry": {"coordinates":[-80.01621299999999,41.196191],"type":"Point"}
}