{
  "type": "Feature",
  "properties": {
    "iso:country":"US",
    "sg:address":"4090 New Lancaster Valley Rd",
    "sg:city":"Milroy",
    "sg:classifiers":[
        {
            "category":"Travel",
            "subcategory":"Campground",
            "type":"Entertainment"
        }
    ],
    "sg:phone":"+1   ",
    "sg:postcode":"17063",
    "sg:province":"PA",
    "sg:tags":[
        "camp"
    ],
    "wof:name":"Honey Creek Camp",
    "wof:placetype":"venue"
},
  "geometry": {"coordinates":[-77.384399,40.761494],"type":"Point"}
}