{
  "type": "Feature",
  "properties": {
    "addr:full":"6750 Essington Ave Ste 1 Philadelphia PA 19153",
    "addr:housenumber":"6750",
    "addr:postcode":"19153",
    "addr:street":"Essington Ave Ste 1",
    "iso:country":"US",
    "sg:address":"6750 Essington Ave Ste 1",
    "sg:city":"Philadelphia",
    "sg:classifiers":[
        {
            "category":"Autos & Motor Vehicles",
            "subcategory":"Auto Supplies",
            "type":"Retail Goods"
        },
        {
            "category":"Wholesale",
            "subcategory":"Auto Parts",
            "type":"Manufacturing & Wholesale Goods"
        }
    ],
    "sg:phone":"+1 215 492 1144",
    "sg:postcode":"19153",
    "sg:province":"PA",
    "sg:tags":[
        "rebuilt-wholesale",
        "automobile",
        "accessory",
        "parts",
        "supplies-used",
        "accessories-wholesale",
        "rebuilt",
        "manufacturer"
    ],
    "wof:name":"Freds Auto Parts",
    "wof:placetype":"venue"
},
  "geometry": {"coordinates":[-75.223062,39.908735],"type":"Point"}
}