{
  "type": "Feature",
  "properties": {
    "iso:country":"US",
    "sg:address":"1904 Penn Ave",
    "sg:city":"Pittsburgh",
    "sg:classifiers":[
        {
            "category":"Restaurant",
            "type":"Food & Drink"
        }
    ],
    "sg:phone":"+1   ",
    "sg:postcode":"15222",
    "sg:province":"PA",
    "sg:tags":[
        "eating"
    ],
    "wof:name":"Rolands Catering",
    "wof:placetype":"venue"
},
  "geometry": {"coordinates":[-79.983959,40.451105],"type":"Point"}
}