{
  "type": "Feature",
  "properties": {
    "addr:full":"138 Market St Philadelphia PA 19106",
    "addr:housenumber":"138",
    "addr:postcode":"19106",
    "addr:street":"Market St",
    "iso:country":"US",
    "sg:address":"138 Market St",
    "sg:city":"Philadelphia",
    "sg:classifiers":[
        {
            "category":"Bars & Pubs",
            "type":"Food & Drink"
        }
    ],
    "sg:menulink":"http://www.allmenus.com/pa/philadelphia/262666-continental-restaurant--martini-bar/menu/",
    "sg:phone":"+1 215 923 6069",
    "sg:postcode":"19106",
    "sg:province":"PA",
    "sg:tags":[
        "new",
        "american"
    ],
    "wof:name":"Continental Restaurant & Martini Bar",
    "wof:placetype":"venue"
},
  "geometry": {"coordinates":[-75.143246,39.949695],"type":"Point"}
}