{
  "type": "Feature",
  "properties": {
    "addr:full":"901 6th Ave Patton PA 16668",
    "addr:housenumber":"901",
    "addr:postcode":"16668",
    "addr:street":"6Th Ave",
    "iso:country":"US",
    "sg:address":"901 6th Ave",
    "sg:city":"Patton",
    "sg:classifiers":[
        {
            "category":"Professional",
            "subcategory":"Engineering",
            "type":"Services"
        }
    ],
    "sg:phone":"+1 814 674 2650",
    "sg:postcode":"16668",
    "sg:province":"PA",
    "sg:tags":[
        "engineer"
    ],
    "wof:name":"D W Lasota Engineering",
    "wof:placetype":"venue"
},
  "geometry": {"coordinates":[-78.652535,40.635877],"type":"Point"}
}