{
  "type": "Feature",
  "properties": {
    "iso:country":"US",
    "sg:address":"152 Doe Run Rd",
    "sg:city":"Coatesville",
    "sg:classifiers":[
        {
            "category":"Building & Trades",
            "subcategory":"Plumbing",
            "type":"Services"
        }
    ],
    "sg:phone":"+1   ",
    "sg:postcode":"19320",
    "sg:province":"PA",
    "sg:tags":[
        "plumbing",
        "heating",
        "contractor"
    ],
    "wof:name":"Reynolds Craig D Plbg & Htg",
    "wof:placetype":"venue"
},
  "geometry": {"coordinates":[-75.831627,39.971314],"type":"Point"}
}