{
  "type": "Feature",
  "properties": {
    "iso:country":"US",
    "sg:address":"1416 Bleim Rd",
    "sg:city":"Pottstown",
    "sg:classifiers":[
        {
            "category":"Building & Trades",
            "subcategory":"Construction",
            "type":"Services"
        }
    ],
    "sg:phone":"+1 610 327 4643",
    "sg:postcode":"19464",
    "sg:province":"PA",
    "sg:tags":[
        "general",
        "contractor"
    ],
    "wof:name":"David P Farnsworth",
    "wof:placetype":"venue"
},
  "geometry": {"coordinates":[-75.589809,40.270738],"type":"Point"}
}