{
  "type": "Feature",
  "properties": {
    "addr:full":"740 Anna May St York PA 17404",
    "addr:housenumber":"740",
    "addr:postcode":"17404",
    "addr:street":"Anna May St",
    "iso:country":"US",
    "sg:address":"740 Anna May St",
    "sg:city":"York",
    "sg:classifiers":[
        {
            "category":"Organizations",
            "subcategory":"Labor Organization",
            "type":"Services"
        }
    ],
    "sg:phone":"+1   ",
    "sg:postcode":"17404",
    "sg:province":"PA",
    "wof:name":"IBEW Local 777",
    "wof:placetype":"venue"
},
  "geometry": {"coordinates":[-76.76354499999999,40.006089],"type":"Point"}
}