{
  "type": "Feature",
  "properties": {
    "addr:full":"111 E High St Milford PA 18337",
    "addr:housenumber":"111",
    "addr:postcode":"18337",
    "addr:street":"E High St",
    "iso:country":"US",
    "sg:address":"111 E High St",
    "sg:city":"Milford",
    "sg:classifiers":[
        {
            "category":"Organizations",
            "subcategory":"Religious Organization",
            "type":"Services"
        }
    ],
    "sg:phone":"+1 570 296 7451",
    "sg:postcode":"18337",
    "sg:province":"PA",
    "sg:tags":[
        "church"
    ],
    "wof:name":"St Patricks Church",
    "wof:placetype":"venue"
},
  "geometry": {"coordinates":[-74.799972,41.323982],"type":"Point"}
}