{
  "type": "Feature",
  "properties": {
    "addr:full":"1309 Prentisvale Rd Eldred PA 16745",
    "addr:housenumber":"1309",
    "addr:postcode":"16745",
    "addr:street":"Prentisvale Rd",
    "iso:country":"US",
    "sg:address":"1309 Prentisvale Rd",
    "sg:city":"Eldred",
    "sg:classifiers":[
        {
            "category":"Shopping",
            "subcategory":"Clothing, Apparel, & Fashions",
            "type":"Retail Goods"
        }
    ],
    "sg:phone":"+1 814 966 3840",
    "sg:postcode":"16745",
    "sg:province":"PA",
    "sg:tags":[
        "accessory"
    ],
    "wof:name":"Robbins Reflections",
    "wof:placetype":"venue"
},
  "geometry": {"coordinates":[-78.43900600000001,41.933266],"type":"Point"}
}