{
  "type": "Feature",
  "properties": {
    "iso:country":"US",
    "sg:address":"818 Ann St",
    "sg:city":"Homestead",
    "sg:classifiers":[
        {
            "category":"Shopping",
            "subcategory":"Florist",
            "type":"Retail Goods"
        }
    ],
    "sg:phone":"+1 412 462 3855",
    "sg:postcode":"15120",
    "sg:province":"PA",
    "wof:name":"Dan's Flower Shop",
    "wof:placetype":"venue"
},
  "geometry": {"coordinates":[-79.908739,40.407142],"type":"Point"}
}