{
  "type": "Feature",
  "properties": {
    "iso:country":"US",
    "sg:address":"247 Jefferson Ave",
    "sg:city":"Marianna",
    "sg:classifiers":[
        {
            "category":"Education",
            "subcategory":"Library",
            "type":"Public Place"
        }
    ],
    "sg:phone":"+1 724 267 3888",
    "sg:postcode":"15345",
    "sg:province":"PA",
    "wof:name":"Marianna Community Public",
    "wof:placetype":"venue"
},
  "geometry": {"coordinates":[-80.088703,40.021709],"type":"Point"}
}