{
  "type": "Feature",
  "properties": {
    "iso:country":"US",
    "sg:address":"232 Whitaker Way",
    "sg:city":"Homestead",
    "sg:classifiers":[
        {
            "category":"Insurance",
            "subcategory":"Insurance Agent",
            "type":"Services"
        }
    ],
    "sg:phone":"+1   ",
    "sg:postcode":"15120",
    "sg:province":"PA",
    "sg:tags":[
        "real estate"
    ],
    "wof:name":"David Ackerman Ins",
    "wof:placetype":"venue"
},
  "geometry": {"coordinates":[-79.88567999999999,40.398915],"type":"Point"}
}