{
  "type": "Feature",
  "properties": {
    "iso:country":"US",
    "sg:address":"1029 Quentin Rd",
    "sg:city":"Lebanon",
    "sg:classifiers":[
        {
            "category":"Health Services",
            "subcategory":"Doctor",
            "type":"Services"
        }
    ],
    "sg:phone":"+1 717 272 4486",
    "sg:postcode":"17042",
    "sg:province":"PA",
    "sg:tags":[
        "dentist"
    ],
    "wof:name":"James L Bramble DDS",
    "wof:placetype":"venue"
},
  "geometry": {"coordinates":[-76.425746,40.323843],"type":"Point"}
}