{
  "type": "Feature",
  "properties": {
    "iso:country":"US",
    "sg:address":"270 Mill St",
    "sg:city":"Danville",
    "sg:classifiers":[
        {
            "category":"Shopping",
            "subcategory":"Jewelry",
            "type":"Retail Goods"
        }
    ],
    "sg:phone":"+1 570 275 1611",
    "sg:postcode":"17821",
    "sg:province":"PA",
    "sg:tags":[
        "repair",
        "jeweler"
    ],
    "wof:name":"Wolfs Jewelry",
    "wof:placetype":"venue"
},
  "geometry": {"coordinates":[-76.617485,40.96215],"type":"Point"}
}