{
  "type": "Feature",
  "properties": {
    "iso:country":"US",
    "sg:address":"48 Connellsville St",
    "sg:city":"Uniontown",
    "sg:classifiers":[
        {
            "category":"Autos & Motor Vehicles",
            "subcategory":"Auto Supplies",
            "type":"Retail Goods"
        }
    ],
    "sg:phone":"+1 724 425 9705",
    "sg:postcode":"15401",
    "sg:province":"PA",
    "sg:tags":[
        "automobile",
        "used"
    ],
    "wof:name":"Dawg Pound Designs",
    "wof:placetype":"venue"
},
  "geometry": {"coordinates":[-79.71526,39.89912],"type":"Point"}
}