{
  "type": "Feature",
  "properties": {
    "addr:full":"11 Water St Wellsboro PA 16901",
    "addr:housenumber":"11",
    "addr:postcode":"16901",
    "addr:street":"Water St",
    "iso:country":"US",
    "sg:address":"11 Water St",
    "sg:city":"Wellsboro",
    "sg:classifiers":[
        {
            "category":"Health Services",
            "subcategory":"Health Practitioner",
            "type":"Services"
        }
    ],
    "sg:phone":"+1 570 723 1256",
    "sg:postcode":"16901",
    "sg:province":"PA",
    "sg:tags":[
        "therapist",
        "physical"
    ],
    "sg:website":"www.laurelhs.org",
    "wof:name":"Laurel Health Systems",
    "wof:placetype":"venue"
},
  "geometry": {"coordinates":[-77.30315899999999,41.747785],"type":"Point"}
}