{
  "type": "Feature",
  "properties": {
    "addr:full":"20 E High St Gettysburg PA 17325",
    "addr:housenumber":"20",
    "addr:postcode":"17325",
    "addr:street":"E High St",
    "iso:country":"US",
    "sg:address":"20 E High St",
    "sg:city":"Gettysburg",
    "sg:classifiers":[
        {
            "category":"Museum",
            "type":"Entertainment"
        }
    ],
    "sg:phone":"+1 717 337 9151",
    "sg:postcode":"17325",
    "sg:province":"PA",
    "sg:tags":[
        "gallery"
    ],
    "sg:website":"www.exploreandmore.com",
    "wof:name":"Explore & More Inc",
    "wof:placetype":"venue"
},
  "geometry": {"coordinates":[-77.230648,39.828653],"type":"Point"}
}