{
  "type": "Feature",
  "properties": {
    "addr:full":"188 Fireside Dr Canonsburg PA 15317",
    "addr:housenumber":"188",
    "addr:postcode":"15317",
    "addr:street":"Fireside Dr",
    "iso:country":"US",
    "sg:address":"188 Fireside Dr",
    "sg:city":"Canonsburg",
    "sg:classifiers":[
        {
            "category":"Professional",
            "type":"Services"
        }
    ],
    "sg:phone":"+1   ",
    "sg:postcode":"15317",
    "sg:province":"PA",
    "wof:name":"Daniel M Perlmutter",
    "wof:placetype":"venue"
},
  "geometry": {"coordinates":[-80.09432,40.268724],"type":"Point"}
}