{
  "type": "Feature",
  "properties": {
    "iso:country":"US",
    "sg:address":"320 Zoo Rd",
    "sg:city":"Fairfield",
    "sg:classifiers":[
        {
            "category":"Animal Shelter",
            "type":"Public Place"
        },
        {
            "category":"Shopping",
            "subcategory":"Pets & Pet Supplies",
            "type":"Retail Goods"
        },
        {
            "category":"Museum",
            "subcategory":"Zoo",
            "type":"Entertainment"
        }
    ],
    "sg:phone":"+1 717 642 5229",
    "sg:postcode":"17320",
    "sg:province":"PA",
    "sg:tags":[
        "store"
    ],
    "sg:website":"www.eastcoastrescue.org",
    "wof:name":"East Coast Exotic Animal Rescue",
    "wof:placetype":"venue"
},
  "geometry": {"coordinates":[-77.393997,39.775398],"type":"Point"}
}