{
  "type": "Feature",
  "properties": {
    "iso:country":"US",
    "sg:address":"308 W Park St",
    "sg:city":"Newmanstown",
    "sg:classifiers":[
        {
            "category":"Building & Trades",
            "subcategory":"Construction",
            "type":"Services"
        }
    ],
    "sg:phone":"+1 610 589 9697",
    "sg:postcode":"17073",
    "sg:province":"PA",
    "sg:tags":[
        "system",
        "specialty",
        "heating",
        "contractor",
        "air conditioning"
    ],
    "wof:name":"A&B Hvac Inc",
    "wof:placetype":"venue"
},
  "geometry": {"coordinates":[-76.21835,40.347185],"type":"Point"}
}