{
  "type": "Feature",
  "properties": {
    "iso:country":"US",
    "sg:address":"801 Allegheny St",
    "sg:city":"Hollidaysburg",
    "sg:classifiers":[
        {
            "category":"Organizations",
            "subcategory":"Religious Organization",
            "type":"Services"
        }
    ],
    "sg:phone":"+1 814 695 4411",
    "sg:postcode":"16648",
    "sg:province":"PA",
    "sg:tags":[
        "church"
    ],
    "wof:name":"First Church Of Hollidaysburg",
    "wof:placetype":"venue"
},
  "geometry": {"coordinates":[-78.386748,40.431239],"type":"Point"}
}