{
  "type": "Feature",
  "properties": {
    "iso:country":"US",
    "sg:address":"400 Southpointe Blvd, Ste 210",
    "sg:city":"Canonsburg",
    "sg:classifiers":[
        {
            "category":"Banks & Credit Unions",
            "subcategory":"Investment Brokerage",
            "type":"Services"
        },
        {
            "category":"Banks & Credit Unions",
            "subcategory":"Financial Services",
            "type":"Services"
        }
    ],
    "sg:phone":"+1 724 916 2233",
    "sg:postcode":"15317",
    "sg:province":"PA",
    "sg:tags":[
        "investing",
        "advising"
    ],
    "sg:website":"www.ameripriseadvisors.com/edwar...",
    "wof:name":"Edward Poach - Ameriprise Financial",
    "wof:placetype":"venue"
},
  "geometry": {"coordinates":[-80.174105,40.296549],"type":"Point"}
}