{
  "type": "Feature",
  "properties": {
    "iso:country":"US",
    "sg:address":"507 S 2nd St",
    "sg:city":"Philadelphia",
    "sg:classifiers":[
        {
            "category":"Personal",
            "type":"Services"
        }
    ],
    "sg:phone":"+1 215 574 1099",
    "sg:postcode":"19147",
    "sg:province":"PA",
    "sg:tags":[
        "therapist",
        "massage"
    ],
    "wof:name":"Marie Frisbie",
    "wof:placetype":"venue"
},
  "geometry": {"coordinates":[-75.14558100000001,39.942203],"type":"Point"}
}