{
  "type": "Feature",
  "properties": {
    "iso:country":"US",
    "sg:address":"699 Bristol Rd",
    "sg:city":"Morrisville",
    "sg:classifiers":[
        {
            "category":"Building & Trades",
            "subcategory":"Construction",
            "type":"Services"
        }
    ],
    "sg:phone":"+1 215 265 7300",
    "sg:postcode":"19067",
    "sg:province":"PA",
    "sg:tags":[
        "well",
        "drilling"
    ],
    "wof:name":"Ameridrill Inc",
    "wof:placetype":"venue"
},
  "geometry": {"coordinates":[-74.780619,40.192935],"type":"Point"}
}