{
  "type": "Feature",
  "properties": {
    "iso:country":"US",
    "sg:address":"901 Philadelphia St",
    "sg:city":"Indiana",
    "sg:classifiers":[
        {
            "category":"Food & Beverages",
            "subcategory":"Groceries & Convenience Stores",
            "type":"Retail Goods"
        },
        {
            "category":"Restaurant",
            "type":"Food & Drink"
        }
    ],
    "sg:phone":"+1 724 465 5221",
    "sg:postcode":"15701",
    "sg:province":"PA",
    "sg:tags":[
        "eating"
    ],
    "wof:name":"Ninth Street Deli",
    "wof:placetype":"venue"
},
  "geometry": {"coordinates":[-79.157138,40.622996],"type":"Point"}
}