{
  "type": "Feature",
  "properties": {
    "addr:full":"10 Dolly Ave Jeannette PA 15644",
    "addr:housenumber":"10",
    "addr:postcode":"15644",
    "addr:street":"Dolly Ave",
    "iso:country":"US",
    "sg:address":"10 Dolly Ave",
    "sg:city":"Jeannette",
    "sg:classifiers":[
        {
            "category":"Education",
            "subcategory":"School",
            "type":"Public Place"
        }
    ],
    "sg:phone":"+1   ",
    "sg:postcode":"15644",
    "sg:province":"PA",
    "wof:name":"Harrison Park Elementary Schl",
    "wof:placetype":"venue"
},
  "geometry": {"coordinates":[-79.642589,40.350526],"type":"Point"}
}