{
  "type": "Feature",
  "properties": {
    "addr:full":"608 Franklin St New Bethlehem PA 16242",
    "addr:housenumber":"608",
    "addr:postcode":"16242",
    "addr:street":"Franklin St",
    "iso:country":"US",
    "sg:address":"608 Franklin St",
    "sg:city":"New Bethlehem",
    "sg:classifiers":[
        {
            "category":"Manufacturing",
            "subcategory":"Signs",
            "type":"Manufacturing & Wholesale Goods"
        }
    ],
    "sg:phone":"+1 814 275 3461",
    "sg:postcode":"16242",
    "sg:province":"PA",
    "sg:tags":[
        "specialty",
        "mfg"
    ],
    "wof:name":"Kline Signs",
    "wof:placetype":"venue"
},
  "geometry": {"coordinates":[-79.326734,41.00577],"type":"Point"}
}