{
  "type": "Feature",
  "properties": {
    "iso:country":"US",
    "sg:address":"230 S Broad St Ofc",
    "sg:city":"Philadelphia",
    "sg:classifiers":[
        {
            "category":"Health Services",
            "subcategory":"Doctor",
            "type":"Services"
        },
        {
            "category":"Health Services",
            "subcategory":"Clinic",
            "type":"Services"
        }
    ],
    "sg:phone":"+1 215 545 3340",
    "sg:postcode":"19102",
    "sg:province":"PA",
    "sg:tags":[
        "psychological",
        "psychologist"
    ],
    "wof:name":"Kathy J Segal Psyd",
    "wof:placetype":"venue"
},
  "geometry": {"coordinates":[-75.16449,39.9482],"type":"Point"}
}