{
  "type": "Feature",
  "properties": {
    "addr:full":"262 Zerby Ave Kingston PA 18704",
    "addr:housenumber":"262",
    "addr:postcode":"18704",
    "addr:street":"Zerby Ave",
    "iso:country":"US",
    "sg:address":"262 Zerby Ave",
    "sg:city":"Kingston",
    "sg:classifiers":[
        {
            "category":"Real Estate",
            "subcategory":"Real Estate Agent",
            "type":"Services"
        }
    ],
    "sg:phone":"+1 570 814 6030",
    "sg:postcode":"18704",
    "sg:province":"PA",
    "sg:tags":[
        "inspection"
    ],
    "wof:name":"Eagle Eye Inspection",
    "wof:placetype":"venue"
},
  "geometry": {"coordinates":[-75.899781,41.269436],"type":"Point"}
}