{
  "type": "Feature",
  "properties": {
    "iso:country":"US",
    "sg:address":"258 E Allegheny Ave",
    "sg:city":"Philadelphia",
    "sg:classifiers":[
        {
            "category":"Bars & Pubs",
            "type":"Food & Drink"
        }
    ],
    "sg:phone":"+1 215 426 4040",
    "sg:postcode":"19134",
    "sg:province":"PA",
    "sg:tags":[
        "drinking"
    ],
    "wof:name":"Rebounds Bar & Grill",
    "wof:placetype":"venue"
},
  "geometry": {"coordinates":[-75.126321,39.99809],"type":"Point"}
}