{
  "type": "Feature",
  "properties": {
    "iso:country":"US",
    "sg:address":"531 Conchester Hwy",
    "sg:city":"Marcus Hook",
    "sg:classifiers":[
        {
            "category":"Professional",
            "subcategory":"Business Services",
            "type":"Services"
        }
    ],
    "sg:phone":"+1 610 497 2272",
    "sg:postcode":"19061",
    "sg:province":"PA",
    "sg:tags":[
        "interior",
        "consultant",
        "design",
        "decorator"
    ],
    "wof:name":"Pete's II Customized Interior",
    "wof:placetype":"venue"
},
  "geometry": {"coordinates":[-75.44704400000001,39.849912],"type":"Point"}
}