{
  "type": "Feature",
  "properties": {
    "addr:full":"523 W 2nd St Hummelstown PA 17036",
    "addr:housenumber":"523",
    "addr:postcode":"17036",
    "addr:street":"W 2Nd St",
    "iso:country":"US",
    "sg:address":"523 W 2nd St",
    "sg:city":"Hummelstown",
    "sg:classifiers":[
        {
            "category":"Building & Trades",
            "subcategory":"Construction",
            "type":"Services"
        }
    ],
    "sg:phone":"+1 717 566 1254",
    "sg:postcode":"17036",
    "sg:province":"PA",
    "sg:tags":[
        "concrete",
        "cutting",
        "breaking",
        "sawing"
    ],
    "wof:name":"Walter J Laudermilch Saw Cutng",
    "wof:placetype":"venue"
},
  "geometry": {"coordinates":[-76.719874,40.265485],"type":"Point"}
}