{
  "type": "Feature",
  "properties": {
    "addr:full":"102 S Washington Titusville PA 16354",
    "addr:housenumber":"102",
    "addr:postcode":"16354",
    "addr:street":"S Washington",
    "iso:country":"US",
    "sg:address":"102 S Washington",
    "sg:city":"Titusville",
    "sg:classifiers":[
        {
            "category":"Restaurant",
            "type":"Food & Drink"
        }
    ],
    "sg:phone":"+1 814 827 8354",
    "sg:postcode":"16354",
    "sg:province":"PA",
    "wof:name":"Mr B's Pizza & Subs",
    "wof:placetype":"venue"
},
  "geometry": {"coordinates":[-79.675101,41.625491],"type":"Point"}
}