{
  "type": "Feature",
  "properties": {
    "iso:country":"US",
    "sg:address":"1339 Otter St",
    "sg:city":"Franklin",
    "sg:classifiers":[
        {
            "category":"Local Transit",
            "type":"Transportation"
        }
    ],
    "sg:phone":"+1   ",
    "sg:postcode":"16323",
    "sg:province":"PA",
    "sg:tags":[
        "passenger"
    ],
    "wof:name":"Franklin Livery Service",
    "wof:placetype":"venue"
},
  "geometry": {"coordinates":[-79.83256299999999,41.400035],"type":"Point"}
}