{
  "type": "Feature",
  "properties": {
    "iso:country":"US",
    "sg:address":"344 Lobaugh Rd",
    "sg:city":"Aspers",
    "sg:classifiers":[
        {
            "category":"Farming",
            "subcategory":"Farm",
            "type":"Manufacturing & Wholesale Goods"
        }
    ],
    "sg:phone":"+1 717 677 0800",
    "sg:postcode":"17304",
    "sg:province":"PA",
    "wof:name":"Ber-Cerk Farm",
    "wof:placetype":"venue"
},
  "geometry": {"coordinates":[-77.195412,39.987495],"type":"Point"}
}