{
  "type": "Feature",
  "properties": {
    "iso:country":"US",
    "sg:address":"8235 Crittenden St",
    "sg:city":"Philadelphia",
    "sg:classifiers":[
        {
            "category":"Professional",
            "subcategory":"Business Services",
            "type":"Services"
        }
    ],
    "sg:phone":"+1 215 242 2549",
    "sg:postcode":"19118",
    "sg:province":"PA",
    "sg:tags":[
        "development",
        "product",
        "designers-industrial",
        "marketing",
        "commercial",
        "design"
    ],
    "wof:name":"Phase One Design",
    "wof:placetype":"venue"
},
  "geometry": {"coordinates":[-75.199099,40.077087],"type":"Point"}
}