{
  "type": "Feature",
  "properties": {
    "iso:country":"US",
    "sg:address":"1201 Fulling Mill Rd",
    "sg:city":"Middletown",
    "sg:classifiers":[
        {
            "category":"Banks & Credit Unions",
            "subcategory":"Bank",
            "type":"Services"
        }
    ],
    "sg:phone":"+1 717 985 3301",
    "sg:postcode":"17057",
    "sg:province":"PA",
    "wof:name":"Mid Atlantic Corporate Fed Cu",
    "wof:placetype":"venue"
},
  "geometry": {"coordinates":[-76.759951,40.227598],"type":"Point"}
}