{
  "type": "Feature",
  "properties": {
    "addr:full":"403 Freeport Rd Pittsburgh PA 15238",
    "addr:housenumber":"403",
    "addr:postcode":"15238",
    "addr:street":"Freeport Rd",
    "iso:country":"US",
    "sg:address":"403 Freeport Rd",
    "sg:city":"Pittsburgh",
    "sg:classifiers":[
        {
            "category":"Shopping",
            "subcategory":"Computers & Home Electronics",
            "type":"Retail Goods"
        }
    ],
    "sg:phone":"+1   ",
    "sg:postcode":"15238",
    "sg:province":"PA",
    "sg:tags":[
        "programing",
        "custom"
    ],
    "wof:name":"Questor Technologies Inc",
    "wof:placetype":"venue"
},
  "geometry": {"coordinates":[-79.85924900000001,40.494807],"type":"Point"}
}