{
  "type": "Feature",
  "properties": {
    "addr:full":"3500 Spring Garden Rd Pittsburgh PA 15212",
    "addr:housenumber":"3500",
    "addr:postcode":"15212",
    "addr:street":"Spring Garden Rd",
    "iso:country":"US",
    "sg:address":"3500 Spring Garden Rd",
    "sg:city":"Pittsburgh",
    "sg:classifiers":[
        {
            "category":"Building & Trades",
            "subcategory":"Construction",
            "type":"Services"
        }
    ],
    "sg:phone":"+1 412 231 1446",
    "sg:postcode":"15212",
    "sg:province":"PA",
    "sg:tags":[
        "contractor"
    ],
    "wof:name":"Associated Builders & Contractors",
    "wof:placetype":"venue"
},
  "geometry": {"coordinates":[-79.99661,40.482861],"type":"Point"}
}