{
  "type": "Feature",
  "properties": {
    "iso:country":"US",
    "sg:address":"8124 State Rte 97",
    "sg:city":"Union City",
    "sg:classifiers":[
        {
            "category":"Building & Trades",
            "subcategory":"Construction",
            "type":"Services"
        }
    ],
    "sg:phone":"+1 814 438 2721",
    "sg:postcode":"16438",
    "sg:province":"PA",
    "sg:tags":[
        "paving",
        "contractor"
    ],
    "wof:name":"Russell Standard Corp",
    "wof:placetype":"venue"
},
  "geometry": {"coordinates":[-79.86503500000001,41.903275],"type":"Point"}
}