{
  "type": "Feature",
  "properties": {
    "iso:country":"US",
    "sg:address":"12 Bromley Dr",
    "sg:city":"Blue Bell",
    "sg:classifiers":[
        {
            "category":"Wholesale",
            "subcategory":"Machinery & Supplies",
            "type":"Manufacturing & Wholesale Goods"
        }
    ],
    "sg:phone":"+1   ",
    "sg:postcode":"19422",
    "sg:province":"PA",
    "sg:tags":[
        "industrial"
    ],
    "wof:name":"Leonard H Clark Inc",
    "wof:placetype":"venue"
},
  "geometry": {"coordinates":[-75.266496,40.128297],"type":"Point"}
}