{
  "type": "Feature",
  "properties": {
    "iso:country":"US",
    "sg:address":"7900 Old York Rd",
    "sg:city":"Elkins Park",
    "sg:classifiers":[
        {
            "category":"Health Services",
            "subcategory":"Doctor",
            "type":"Services"
        }
    ],
    "sg:phone":"+1 215 635 1666",
    "sg:postcode":"19027",
    "sg:province":"PA",
    "sg:tags":[
        "physician",
        "surgeon"
    ],
    "wof:name":"Harold Kolansky MD",
    "wof:placetype":"venue"
},
  "geometry": {"coordinates":[-75.12949399999999,40.074684],"type":"Point"}
}