{
  "type": "Feature",
  "properties": {
    "iso:country":"US",
    "sg:address":"7 W Columbus Ave",
    "sg:city":"Corry",
    "sg:classifiers":[
        {
            "category":"Professional",
            "type":"Services"
        }
    ],
    "sg:phone":"+1 814 664 4212",
    "sg:postcode":"16407",
    "sg:province":"PA",
    "wof:name":"Mike's Exxon Svc",
    "wof:placetype":"venue"
},
  "geometry": {"coordinates":[-79.641751,41.936575],"type":"Point"}
}