{
  "type": "Feature",
  "properties": {
    "iso:country":"US",
    "sg:address":"3624 Creamery Rd",
    "sg:city":"Bensalem",
    "sg:classifiers":[
        {
            "category":"Building & Trades",
            "subcategory":"Plumbing",
            "type":"Services"
        }
    ],
    "sg:phone":"+1 215 245 8661",
    "sg:postcode":"19020",
    "sg:province":"PA",
    "sg:tags":[
        "refrigeration",
        "contractor"
    ],
    "wof:name":"Quality Control Refrigeration",
    "wof:placetype":"venue"
},
  "geometry": {"coordinates":[-74.93056199999999,40.097848],"type":"Point"}
}