{
  "type": "Feature",
  "properties": {
    "iso:country":"US",
    "sg:address":"2401 Grandview Ave",
    "sg:city":"Mc Keesport",
    "sg:classifiers":[
        {
            "category":"Building & Trades",
            "subcategory":"Construction",
            "type":"Services"
        }
    ],
    "sg:phone":"+1   ",
    "sg:postcode":"15132",
    "sg:province":"PA",
    "sg:tags":[
        "painting",
        "contractor"
    ],
    "wof:name":"Dicks Painting",
    "wof:placetype":"venue"
},
  "geometry": {"coordinates":[-79.83488199999999,40.33586],"type":"Point"}
}