{
  "type": "Feature",
  "properties": {
    "addr:full":"2030 E College Ave State College PA 16801",
    "addr:housenumber":"2030",
    "addr:postcode":"16801",
    "addr:street":"E College Ave",
    "iso:country":"US",
    "sg:address":"2030 E College Ave",
    "sg:city":"State College",
    "sg:classifiers":[
        {
            "category":"Building & Trades",
            "subcategory":"Pest Control",
            "type":"Services"
        }
    ],
    "sg:phone":"+1 814 231 8998",
    "sg:postcode":"16801",
    "sg:province":"PA",
    "wof:name":"Orkin Exterminating Co",
    "wof:placetype":"venue"
},
  "geometry": {"coordinates":[-77.814727,40.821612],"type":"Point"}
}