{
  "type": "Feature",
  "properties": {
    "addr:full":"5527 Baltimore Ave Philadelphia PA 19143",
    "addr:housenumber":"5527",
    "addr:postcode":"19143",
    "addr:street":"Baltimore Ave",
    "iso:country":"US",
    "sg:address":"5527 Baltimore Ave",
    "sg:city":"Philadelphia",
    "sg:classifiers":[
        {
            "category":"Bars & Pubs",
            "type":"Food & Drink"
        }
    ],
    "sg:phone":"+1 215 748 7240",
    "sg:postcode":"19143",
    "sg:province":"PA",
    "sg:tags":[
        "drinking"
    ],
    "wof:name":"Lark's Blue Bird Lounge",
    "wof:placetype":"venue"
},
  "geometry": {"coordinates":[-75.235049,39.946992],"type":"Point"}
}