{
  "type": "Feature",
  "properties": {
    "iso:country":"US",
    "sg:address":"6832 Clover Ave",
    "sg:city":"Upper Darby",
    "sg:classifiers":[
        {
            "category":"Building & Trades",
            "subcategory":"Cleaning & Sanitation",
            "type":"Services"
        }
    ],
    "sg:phone":"+1 610 284 9307",
    "sg:postcode":"19082",
    "sg:province":"PA",
    "sg:tags":[
        "house"
    ],
    "wof:name":"AM-PM Cleaning Svc Inc",
    "wof:placetype":"venue"
},
  "geometry": {"coordinates":[-75.25425,39.94812],"type":"Point"}
}