{
  "type": "Feature",
  "properties": {
    "iso:country":"US",
    "sg:address":"216 Nazareth Pike",
    "sg:city":"Bethlehem",
    "sg:classifiers":[
        {
            "category":"Health Services",
            "subcategory":"Chiropractor",
            "type":"Services"
        }
    ],
    "sg:phone":"+1 610 746 4332",
    "sg:postcode":"18020",
    "sg:province":"PA",
    "wof:name":"Community Chiropractic",
    "wof:placetype":"venue"
},
  "geometry": {"coordinates":[-75.33521,40.6918],"type":"Point"}
}