{
  "type": "Feature",
  "properties": {
    "addr:full":"124 Reamer Rd Butler PA 16002",
    "addr:housenumber":"124",
    "addr:postcode":"16002",
    "addr:street":"Reamer Rd",
    "iso:country":"US",
    "sg:address":"124 Reamer Rd",
    "sg:city":"Butler",
    "sg:phone":"+1 724 352 3634",
    "sg:postcode":"16002",
    "sg:province":"PA",
    "sg:tags":[
        "product",
        "oil",
        "petroleum"
    ],
    "wof:name":"Ozog Albert R Amsoil Dealer",
    "wof:placetype":"venue"
},
  "geometry": {"coordinates":[-79.88065899999999,40.775806],"type":"Point"}
}