{
  "type": "Feature",
  "properties": {
    "iso:country":"US",
    "sg:address":"145 Laurel Rd",
    "sg:city":"Mountainhome",
    "sg:classifiers":[
        {
            "category":"Building & Trades",
            "subcategory":"Construction",
            "type":"Services"
        }
    ],
    "sg:phone":"+1 570 595 3724",
    "sg:postcode":"18302",
    "sg:province":"PA",
    "sg:tags":[
        "painter"
    ],
    "wof:name":"King's Choice Interior Dcrtng",
    "wof:placetype":"venue"
},
  "geometry": {"coordinates":[-75.20022299999999,41.070712],"type":"Point"}
}