{
  "type": "Feature",
  "properties": {
    "iso:country":"US",
    "sg:address":"108 Market St",
    "sg:city":"Philadelphia",
    "sg:classifiers":[
        {
            "category":"Personal",
            "subcategory":"Beauty Salon",
            "type":"Services"
        }
    ],
    "sg:phone":"+1 215 627 6337",
    "sg:postcode":"19176",
    "sg:province":"PA",
    "sg:tags":[
        "hair"
    ],
    "wof:name":"Chroma Hair Gallery",
    "wof:placetype":"venue"
},
  "geometry": {"coordinates":[-75.14267599999999,39.949527],"type":"Point"}
}