{
  "type": "Feature",
  "properties": {
    "iso:country":"US",
    "sg:address":"100 Red Lion Rd",
    "sg:city":"Philadelphia",
    "sg:classifiers":[
        {
            "category":"Retail",
            "subcategory":"Auto Repair",
            "type":"Services"
        }
    ],
    "sg:phone":"+1   ",
    "sg:postcode":"19115",
    "sg:province":"PA",
    "sg:tags":[
        "automotive"
    ],
    "wof:name":"Daves Auto Care",
    "wof:placetype":"venue"
},
  "geometry": {"coordinates":[-75.047945,40.112263],"type":"Point"}
}