{
  "type": "Feature",
  "properties": {
    "addr:full":"137 E Beaver Ave State College PA 16801",
    "addr:housenumber":"137",
    "addr:postcode":"16801",
    "addr:street":"E Beaver Ave",
    "iso:country":"US",
    "sg:address":"137 E Beaver Ave",
    "sg:city":"State College",
    "sg:classifiers":[
        {
            "category":"Shopping",
            "subcategory":"Gifts & Souvenirs",
            "type":"Retail Goods"
        }
    ],
    "sg:phone":"+1 814 237 8675",
    "sg:postcode":"16801",
    "sg:province":"PA",
    "sg:tags":[
        "shop"
    ],
    "wof:name":"Gift Adventures",
    "wof:placetype":"venue"
},
  "geometry": {"coordinates":[-77.86009799999999,40.793604],"type":"Point"}
}