{
  "type": "Feature",
  "properties": {
    "iso:country":"US",
    "sg:address":"44 Hawthorne Ave",
    "sg:city":"Gilbertsville",
    "sg:classifiers":[
        {
            "category":"Retail",
            "subcategory":"Auto Repair",
            "type":"Services"
        }
    ],
    "sg:phone":"+1   ",
    "sg:postcode":"19525",
    "sg:province":"PA",
    "sg:tags":[
        "transmission"
    ],
    "wof:name":"RR Transmission Service",
    "wof:placetype":"venue"
},
  "geometry": {"coordinates":[-75.623024,40.30733],"type":"Point"}
}