{
  "type": "Feature",
  "properties": {
    "addr:full":"4000 Washington Rd Canonsburg PA 15317",
    "addr:housenumber":"4000",
    "addr:postcode":"15317",
    "addr:street":"Washington Rd",
    "iso:country":"US",
    "sg:address":"4000 Washington Rd",
    "sg:city":"Canonsburg",
    "sg:classifiers":[
        {
            "category":"Building & Trades",
            "subcategory":"Construction",
            "type":"Services"
        }
    ],
    "sg:phone":"+1 724 941 2188",
    "sg:postcode":"15317",
    "sg:province":"PA",
    "sg:tags":[
        "home",
        "builder",
        "family",
        "contractor"
    ],
    "wof:name":"Eddy Homes Inc",
    "wof:placetype":"venue"
},
  "geometry": {"coordinates":[-80.128536,40.269557],"type":"Point"}
}