{
  "type": "Feature",
  "properties": {
    "addr:full":"1223 Juniper St Quakertown PA 18951",
    "addr:housenumber":"1223",
    "addr:postcode":"18951",
    "addr:street":"Juniper St",
    "iso:country":"US",
    "sg:address":"1223 Juniper St",
    "sg:city":"Quakertown",
    "sg:classifiers":[
        {
            "category":"Retail",
            "subcategory":"Auto Repair",
            "type":"Services"
        }
    ],
    "sg:phone":"+1 215 538 5486",
    "sg:postcode":"18951",
    "sg:province":"PA",
    "sg:tags":[
        "automobile",
        "part",
        "supply"
    ],
    "wof:name":"Juniper Auto Care",
    "wof:placetype":"venue"
},
  "geometry": {"coordinates":[-75.350916,40.440255],"type":"Point"}
}