{
  "type": "Feature",
  "properties": {
    "iso:country":"US",
    "sg:address":"80 Zook Ln",
    "sg:city":"Newburg",
    "sg:phone":"+1   ",
    "sg:postcode":"17240",
    "sg:province":"PA",
    "sg:tags":[
        "farm",
        "corn",
        "soybean"
    ],
    "wof:name":"Jerry Zook",
    "wof:placetype":"venue"
},
  "geometry": {"coordinates":[-77.587884,40.159507],"type":"Point"}
}