{
  "type": "Feature",
  "properties": {
    "addr:full":"514 N 7th St Allentown PA 18102",
    "addr:housenumber":"514",
    "addr:postcode":"18102",
    "addr:street":"N 7Th St",
    "iso:country":"US",
    "sg:address":"514 N 7th St",
    "sg:city":"Allentown",
    "sg:classifiers":[
        {
            "category":"Personal",
            "subcategory":"Beauty Salon",
            "type":"Services"
        }
    ],
    "sg:phone":"+1   ",
    "sg:postcode":"18102",
    "sg:province":"PA",
    "sg:tags":[
        "shop"
    ],
    "wof:name":"Susan Kim Beauty Salon",
    "wof:placetype":"venue"
},
  "geometry": {"coordinates":[-75.475252,40.609456],"type":"Point"}
}