{
  "type": "Feature",
  "properties": {
    "iso:country":"US",
    "sg:address":"107 Broadway Ave",
    "sg:city":"Farrell",
    "sg:classifiers":[
        {
            "category":"Organizations",
            "subcategory":"Labor Organization",
            "type":"Services"
        }
    ],
    "sg:phone":"+1 724 346 1212",
    "sg:postcode":"16121",
    "sg:province":"PA",
    "wof:name":"United Steelworkers Local 1016",
    "wof:placetype":"venue"
},
  "geometry": {"coordinates":[-80.503798,41.20529],"type":"Point"}
}