{
  "type": "Feature",
  "properties": {
    "iso:country":"US",
    "sg:address":"202 International Dr",
    "sg:city":"Oakdale",
    "sg:classifiers":[
        {
            "category":"Restaurant",
            "type":"Food & Drink"
        }
    ],
    "sg:phone":"+1 724 695 8429",
    "sg:postcode":"15071",
    "sg:province":"PA",
    "sg:tags":[
        "pizza"
    ],
    "wof:name":"Angelia's Pizza Corp. Ofc.",
    "wof:placetype":"venue"
},
  "geometry": {"coordinates":[-80.230977,40.434562],"type":"Point"}
}