{
  "type": "Feature",
  "properties": {
    "iso:country":"US",
    "sg:address":"1740 S Cameron St",
    "sg:city":"Harrisburg",
    "sg:classifiers":[
        {
            "category":"Retail",
            "subcategory":"Auto Repair",
            "type":"Services"
        }
    ],
    "sg:phone":"+1   ",
    "sg:postcode":"17104",
    "sg:province":"PA",
    "sg:tags":[
        "transmission",
        "general"
    ],
    "wof:name":"Capital Transmission",
    "wof:placetype":"venue"
},
  "geometry": {"coordinates":[-76.854787,40.240865],"type":"Point"}
}