{
  "type": "Feature",
  "properties": {
    "iso:country":"US",
    "sg:address":"528 N Lewis Rd",
    "sg:city":"Limerick",
    "sg:classifiers":[
        {
            "category":"Organizations",
            "subcategory":"Religious Organization",
            "type":"Services"
        }
    ],
    "sg:phone":"+1 610 948 0331",
    "sg:postcode":"19468",
    "sg:province":"PA",
    "sg:tags":[
        "church"
    ],
    "wof:name":"Chapel In The Meadow",
    "wof:placetype":"venue"
},
  "geometry": {"coordinates":[-75.545478,40.214619],"type":"Point"}
}