{
  "type": "Feature",
  "properties": {
    "addr:full":"914 N Reading Rd Ephrata PA 17522",
    "addr:housenumber":"914",
    "addr:postcode":"17522",
    "addr:street":"N Reading Rd",
    "iso:country":"US",
    "sg:address":"914 N Reading Rd",
    "sg:city":"Ephrata",
    "sg:classifiers":[
        {
            "category":"Building & Trades",
            "subcategory":"Construction",
            "type":"Services"
        }
    ],
    "sg:phone":"+1 610 927 7838",
    "sg:postcode":"17522",
    "sg:province":"PA",
    "sg:tags":[
        "consultant"
    ],
    "wof:name":"Balton Construction Inc.",
    "wof:placetype":"venue"
},
  "geometry": {"coordinates":[-76.14368899999999,40.207174],"type":"Point"}
}