{
  "type": "Feature",
  "properties": {
    "iso:country":"US",
    "sg:address":"630 Squaw Run Rd E",
    "sg:city":"Pittsburgh",
    "sg:classifiers":[
        {
            "category":"Organizations",
            "subcategory":"Religious Organization",
            "type":"Services"
        }
    ],
    "sg:phone":"+1 412 963 8938",
    "sg:postcode":"15238",
    "sg:province":"PA",
    "sg:tags":[
        "church"
    ],
    "wof:name":"Fox Chapel Episcopal Church",
    "wof:placetype":"venue"
},
  "geometry": {"coordinates":[-79.89161900000001,40.524306],"type":"Point"}
}