{
  "type": "Feature",
  "properties": {
    "addr:full":"3334 Aldine St Philadelphia PA 19136",
    "addr:housenumber":"3334",
    "addr:postcode":"19136",
    "addr:street":"Aldine St",
    "iso:country":"US",
    "sg:address":"3334 Aldine St",
    "sg:city":"Philadelphia",
    "sg:classifiers":[
        {
            "category":"Home & Garden",
            "subcategory":"Building Materials",
            "type":"Retail Goods"
        }
    ],
    "sg:phone":"+1 215 333 6663",
    "sg:postcode":"19136",
    "sg:province":"PA",
    "sg:tags":[
        "windows"
    ],
    "wof:name":"Patriot Window & Door Co",
    "wof:placetype":"venue"
},
  "geometry": {"coordinates":[-75.04199,40.04004],"type":"Point"}
}