{
  "type": "Feature",
  "properties": {
    "iso:country":"US",
    "sg:address":"120 S Union St",
    "sg:city":"Middletown",
    "sg:classifiers":[
        {
            "category":"Banks & Credit Unions",
            "subcategory":"Bank",
            "type":"Services"
        }
    ],
    "sg:phone":"+1 717 944 1301",
    "sg:postcode":"17057",
    "sg:province":"PA",
    "sg:tags":[
        "commercial",
        "state",
        "saving"
    ],
    "sg:website":"http://www.mandtbank.com",
    "wof:name":"M&T",
    "wof:placetype":"venue"
},
  "geometry": {"coordinates":[-76.73148500000001,40.194065],"type":"Point"}
}