{
  "type": "Feature",
  "properties": {
    "iso:country":"US",
    "sg:address":"Harrisburg Train Sta",
    "sg:city":"Harrisburg",
    "sg:classifiers":[
        {
            "category":"Communications",
            "subcategory":"Newspaper",
            "type":"Services"
        },
        {
            "category":"Food & Beverages",
            "subcategory":"Groceries & Convenience Stores",
            "type":"Retail Goods"
        }
    ],
    "sg:phone":"+1 717 232 7775",
    "sg:postcode":"17101",
    "sg:province":"PA",
    "sg:tags":[
        "magazine"
    ],
    "wof:name":"Transit News",
    "wof:placetype":"venue"
},
  "geometry": {"coordinates":[-76.8843,40.2607],"type":"Point"}
}