{
  "type": "Feature",
  "properties": {
    "iso:country":"US",
    "sg:address":"2710 Old Philadelphia Pike",
    "sg:city":"Bird In Hand",
    "sg:classifiers":[
        {
            "category":"Shopping",
            "subcategory":"Hobbies, Toys, & Games",
            "type":"Retail Goods"
        }
    ],
    "sg:phone":"+1 717 393 1061",
    "sg:postcode":"17505",
    "sg:province":"PA",
    "wof:name":"Country Crafter",
    "wof:placetype":"venue"
},
  "geometry": {"coordinates":[-76.17810900000001,40.038435],"type":"Point"}
}