{
  "type": "Feature",
  "properties": {
    "addr:full":"1002 Waterfront Dr E Munhall PA 15120",
    "addr:housenumber":"1002",
    "addr:postcode":"15120",
    "addr:street":"Waterfront Dr E",
    "iso:country":"US",
    "sg:address":"1002 Waterfront Dr E",
    "sg:city":"Munhall",
    "sg:classifiers":[
        {
            "category":"Retail",
            "subcategory":"Auto Rental",
            "type":"Services"
        }
    ],
    "sg:phone":"+1 412 462 4895",
    "sg:postcode":"15120",
    "sg:province":"PA",
    "sg:tags":[
        "renting",
        "truck",
        "leasing"
    ],
    "wof:name":"U-Haul Co",
    "wof:placetype":"venue"
},
  "geometry": {"coordinates":[-79.89822599999999,40.413611],"type":"Point"}
}