{
  "type": "Feature",
  "properties": {
    "iso:country":"US",
    "sg:address":"2895 Hamilton Blvd Ste 207",
    "sg:city":"Allentown",
    "sg:classifiers":[
        {
            "category":"Health Services",
            "subcategory":"Dentist",
            "type":"Services"
        }
    ],
    "sg:phone":"+1 610 435 0115",
    "sg:postcode":"18104",
    "sg:province":"PA",
    "sg:tags":[
        "orthodontist"
    ],
    "wof:name":"Karabasz Sara Dr DMD",
    "wof:placetype":"venue"
},
  "geometry": {"coordinates":[-75.5158,40.585602],"type":"Point"}
}