{
  "type": "Feature",
  "properties": {
    "addr:full":"233 State Rte 1001 Tunkhannock PA 18657",
    "addr:housenumber":"233",
    "addr:postcode":"18657",
    "addr:street":"State Rte 1001",
    "iso:country":"US",
    "sg:address":"233 State Rte 1001",
    "sg:city":"Tunkhannock",
    "sg:classifiers":[
        {
            "category":"Autos & Motor Vehicles",
            "subcategory":"Automobile Sales",
            "type":"Retail Goods"
        }
    ],
    "sg:phone":"+1 570 836 2629",
    "sg:postcode":"18657",
    "sg:province":"PA",
    "sg:tags":[
        "car",
        "used",
        "dealer"
    ],
    "wof:name":"Griffin's Auto Sales",
    "wof:placetype":"venue"
},
  "geometry": {"coordinates":[-75.917466,41.563293],"type":"Point"}
}