{
  "type": "Feature",
  "properties": {
    "iso:country":"US",
    "sg:address":"551 Thorn Run Rd",
    "sg:city":"Coraopolis",
    "sg:classifiers":[
        {
            "category":"Education",
            "subcategory":"Dance Studio",
            "type":"Public Place"
        }
    ],
    "sg:phone":"+1   ",
    "sg:postcode":"15108",
    "sg:province":"PA",
    "sg:tags":[
        "school",
        "child",
        "gymnastic",
        "care"
    ],
    "wof:name":"Body Shoppe The",
    "wof:placetype":"venue"
},
  "geometry": {"coordinates":[-80.186336,40.520853],"type":"Point"}
}