{
  "type": "Feature",
  "properties": {
    "iso:country":"US",
    "sg:address":"351 Fetsko Rd",
    "sg:city":"West Middlesex",
    "sg:classifiers":[
        {
            "category":"Farming",
            "subcategory":"Dairy Farm",
            "type":"Manufacturing & Wholesale Goods"
        }
    ],
    "sg:phone":"+1   ",
    "sg:postcode":"16159",
    "sg:province":"PA",
    "wof:name":"Canon Dairy Farm",
    "wof:placetype":"venue"
},
  "geometry": {"coordinates":[-80.483026,41.146255],"type":"Point"}
}