{
  "type": "Feature",
  "properties": {
    "addr:full":"4044 Rte 130 Irwin PA 15642",
    "addr:housenumber":"4044",
    "addr:postcode":"15642",
    "addr:street":"Rte 130",
    "iso:country":"US",
    "sg:address":"4044 Rte 130",
    "sg:city":"Irwin",
    "sg:classifiers":[
        {
            "category":"Building & Trades",
            "subcategory":"Landscaping Services",
            "type":"Services"
        }
    ],
    "sg:phone":"+1   ",
    "sg:postcode":"15642",
    "sg:province":"PA",
    "sg:tags":[
        "florist",
        "garden",
        "center"
    ],
    "wof:name":"Hamiltn-Fields At Stoney Ledge",
    "wof:placetype":"venue"
},
  "geometry": {"coordinates":[-79.68408599999999,40.371254],"type":"Point"}
}