{
  "type": "Feature",
  "properties": {
    "iso:country":"US",
    "sg:address":"8158 Perry Hwy",
    "sg:city":"Pittsburgh",
    "sg:classifiers":[
        {
            "category":"Shopping",
            "type":"Retail Goods"
        }
    ],
    "sg:phone":"+1 412 367 3877",
    "sg:postcode":"15237",
    "sg:province":"PA",
    "sg:tags":[
        "art",
        "gallery",
        "merchandise",
        "dealer"
    ],
    "sg:website":"www.borelli-edwardsfineart.com",
    "wof:name":"Borelli-Edwards Art Gallery",
    "wof:placetype":"venue"
},
  "geometry": {"coordinates":[-80.038774,40.555544],"type":"Point"}
}