{
  "type": "Feature",
  "properties": {
    "addr:full":"123 N Wales Rd North Wales PA 19454",
    "addr:housenumber":"123",
    "addr:postcode":"19454",
    "addr:street":"N Wales Rd",
    "iso:country":"US",
    "sg:address":"123 N Wales Rd",
    "sg:city":"North Wales",
    "sg:classifiers":[
        {
            "category":"Education",
            "subcategory":"Vocational School",
            "type":"Public Place"
        }
    ],
    "sg:phone":"+1   ",
    "sg:postcode":"19454",
    "sg:province":"PA",
    "wof:name":"Driver Training Services",
    "wof:placetype":"venue"
},
  "geometry": {"coordinates":[-75.259305,40.231266],"type":"Point"}
}