{
  "type": "Feature",
  "properties": {
    "iso:country":"US",
    "sg:address":"412 Market St",
    "sg:city":"Lewisburg",
    "sg:classifiers":[
        {
            "category":"Restaurant",
            "type":"Food & Drink"
        }
    ],
    "sg:phone":"+1 570 523 8088",
    "sg:postcode":"17837",
    "sg:province":"PA",
    "sg:website":"www.elizabethsbistro.com",
    "wof:name":"Elizabeth's An American Bistro",
    "wof:placetype":"venue"
},
  "geometry": {"coordinates":[-76.88611400000001,40.963736],"type":"Point"}
}