{
  "type": "Feature",
  "properties": {
    "iso:country":"US",
    "sg:address":"208 E Wallace Ave",
    "sg:city":"New Castle",
    "sg:classifiers":[
        {
            "category":"Retail",
            "subcategory":"Laundry & Dry Cleaning",
            "type":"Services"
        }
    ],
    "sg:phone":"+1 724 654 5114",
    "sg:postcode":"16101",
    "sg:province":"PA",
    "sg:tags":[
        "cleaners"
    ],
    "wof:name":"Tony Colia Dry Cleaners",
    "wof:placetype":"venue"
},
  "geometry": {"coordinates":[-80.341729,41.006526],"type":"Point"}
}