{
  "type": "Feature",
  "properties": {
    "iso:country":"US",
    "sg:address":"542 Penn Ave",
    "sg:city":"Reading",
    "sg:classifiers":[
        {
            "category":"Manufacturing",
            "subcategory":"Retail Goods",
            "type":"Manufacturing & Wholesale Goods"
        },
        {
            "category":"Wholesale",
            "subcategory":"Durable Goods & Equipment",
            "type":"Manufacturing & Wholesale Goods"
        }
    ],
    "sg:phone":"+1 610 378 1277",
    "sg:postcode":"19611",
    "sg:province":"PA",
    "sg:tags":[
        "professional",
        "engineering",
        "supply"
    ],
    "wof:name":"Yoas Services Inc",
    "wof:placetype":"venue"
},
  "geometry": {"coordinates":[-75.949016,40.33566],"type":"Point"}
}