{
  "type": "Feature",
  "properties": {
    "addr:full":"601 Lakeside Park Southampton PA 18966",
    "addr:housenumber":"601",
    "addr:postcode":"18966",
    "addr:street":"Lakeside Park",
    "iso:country":"US",
    "sg:address":"601 Lakeside Park",
    "sg:city":"Southampton",
    "sg:classifiers":[
        {
            "category":"Professional",
            "type":"Services"
        }
    ],
    "sg:phone":"+1 215 364 7655",
    "sg:postcode":"18966",
    "sg:province":"PA",
    "sg:tags":[
        "establishment"
    ],
    "wof:name":"Tracorp",
    "wof:placetype":"venue"
},
  "geometry": {"coordinates":[-75.017275,40.159006],"type":"Point"}
}