{
  "type": "Feature",
  "properties": {
    "addr:full":"4037 Pine St Philadelphia PA 19104",
    "addr:housenumber":"4037",
    "addr:postcode":"19104",
    "addr:street":"Pine St",
    "iso:country":"US",
    "sg:address":"4037 Pine St",
    "sg:city":"Philadelphia",
    "sg:classifiers":[
        {
            "category":"Place Of Worship",
            "subcategory":"Synagogue",
            "type":"Public Place"
        }
    ],
    "sg:phone":"+1 215 222 9618",
    "sg:postcode":"19104",
    "sg:province":"PA",
    "wof:name":"Steinhardt Jewish Heritage Program",
    "wof:placetype":"venue"
},
  "geometry": {"coordinates":[-75.205044,39.950906],"type":"Point"}
}