{
  "type": "Feature",
  "properties": {
    "iso:country":"US",
    "sg:address":"411 Baltimore Pike",
    "sg:city":"Morton",
    "sg:classifiers":[
        {
            "category":"Restaurant",
            "type":"Food & Drink"
        }
    ],
    "sg:phone":"+1 610 544 7009",
    "sg:postcode":"19063",
    "sg:province":"PA",
    "sg:tags":[
        "eating"
    ],
    "wof:name":"Burger King",
    "wof:placetype":"venue"
},
  "geometry": {"coordinates":[-75.3969,39.91792],"type":"Point"}
}