{
  "type": "Feature",
  "properties": {
    "iso:country":"US",
    "sg:address":"152 Brown Rd",
    "sg:city":"Pittston",
    "sg:classifiers":[
        {
            "category":"Building & Trades",
            "subcategory":"Construction",
            "type":"Services"
        }
    ],
    "sg:phone":"+1   ",
    "sg:postcode":"18640",
    "sg:province":"PA",
    "sg:tags":[
        "concrete",
        "contractor"
    ],
    "wof:name":"Concrete Ventures Inc",
    "wof:placetype":"venue"
},
  "geometry": {"coordinates":[-75.77637799999999,41.302074],"type":"Point"}
}