{
  "type": "Feature",
  "properties": {
    "iso:country":"US",
    "sg:address":"243 Broad St",
    "sg:city":"New Bethlehem",
    "sg:classifiers":[
        {
            "category":"Health Services",
            "subcategory":"Doctor",
            "type":"Services"
        }
    ],
    "sg:phone":"+1 814 275 4220",
    "sg:postcode":"16242",
    "sg:province":"PA",
    "sg:tags":[
        "dentist"
    ],
    "wof:name":"Stephen J Jaworski DDS",
    "wof:placetype":"venue"
},
  "geometry": {"coordinates":[-79.339927,41.000249],"type":"Point"}
}