{
  "type": "Feature",
  "properties": {
    "addr:full":"3303 E State St Hermitage PA 16148",
    "addr:housenumber":"3303",
    "addr:postcode":"16148",
    "addr:street":"E State St",
    "iso:country":"US",
    "sg:address":"3303 E State St",
    "sg:city":"Hermitage",
    "sg:classifiers":[
        {
            "category":"Shopping",
            "subcategory":"Clothing, Apparel, & Fashions",
            "type":"Retail Goods"
        }
    ],
    "sg:phone":"+1   ",
    "sg:postcode":"16148",
    "sg:province":"PA",
    "sg:tags":[
        "accessory"
    ],
    "wof:name":"Nadenes Trading Post",
    "wof:placetype":"venue"
},
  "geometry": {"coordinates":[-80.448798,41.233476],"type":"Point"}
}