{
  "type": "Feature",
  "properties": {
    "iso:country":"US",
    "sg:address":"1056 S Negley Ave",
    "sg:city":"Pittsburgh",
    "sg:classifiers":[
        {
            "category":"Real Estate",
            "subcategory":"Architect",
            "type":"Services"
        }
    ],
    "sg:phone":"+1 412 362 0768",
    "sg:postcode":"15217",
    "sg:province":"PA",
    "wof:name":"Mary Cerrone Architect",
    "wof:placetype":"venue"
},
  "geometry": {"coordinates":[-79.92914,40.449037],"type":"Point"}
}