{
  "type": "Feature",
  "properties": {
    "iso:country":"US",
    "sg:address":"340 Rocky Rd",
    "sg:city":"Hazleton",
    "sg:classifiers":[
        {
            "category":"Building & Trades",
            "subcategory":"Construction",
            "type":"Services"
        }
    ],
    "sg:phone":"+1   ",
    "sg:postcode":"18201",
    "sg:province":"PA",
    "sg:tags":[
        "aggregate",
        "excavating",
        "site",
        "producer"
    ],
    "wof:name":"Stockton Materials",
    "wof:placetype":"venue"
},
  "geometry": {"coordinates":[-75.9709,40.935685],"type":"Point"}
}