{
  "type": "Feature",
  "properties": {
    "addr:full":"82 Queen St Northumberland PA 17857",
    "addr:housenumber":"82",
    "addr:postcode":"17857",
    "addr:street":"Queen St",
    "iso:country":"US",
    "sg:address":"82 Queen St",
    "sg:city":"Northumberland",
    "sg:classifiers":[
        {
            "category":"Home & Garden",
            "subcategory":"Carpets & Floor Coverings",
            "type":"Retail Goods"
        }
    ],
    "sg:phone":"+1 570 473 8751",
    "sg:postcode":"17857",
    "sg:province":"PA",
    "sg:tags":[
        "dealer",
        "rug"
    ],
    "wof:name":"Frye's Interiors",
    "wof:placetype":"venue"
},
  "geometry": {"coordinates":[-76.79536299999999,40.888368],"type":"Point"}
}