{
  "type": "Feature",
  "properties": {
    "iso:country":"US",
    "sg:address":"88 Canal Rd",
    "sg:city":"Fairless Hills",
    "sg:classifiers":[
        {
            "category":"Wholesale",
            "subcategory":"Machinery & Supplies",
            "type":"Manufacturing & Wholesale Goods"
        }
    ],
    "sg:phone":"+1   ",
    "sg:postcode":"19030",
    "sg:province":"PA",
    "sg:tags":[
        "defense",
        "government",
        "contractor",
        "distributing",
        "pa",
        "aerospace"
    ],
    "wof:name":"Kampi Components Co Inc",
    "wof:placetype":"venue"
},
  "geometry": {"coordinates":[-74.785033,40.191482],"type":"Point"}
}