{
  "type": "Feature",
  "properties": {
    "addr:full":"18 Summit Dr Bryn Mawr PA 19010",
    "addr:housenumber":"18",
    "addr:postcode":"19010",
    "addr:street":"Summit Dr",
    "iso:country":"US",
    "sg:address":"18 Summit Dr",
    "sg:city":"Bryn Mawr",
    "sg:classifiers":[
        {
            "category":"Insurance",
            "subcategory":"Insurance Agent",
            "type":"Services"
        }
    ],
    "sg:phone":"+1 610 581 4100",
    "sg:postcode":"19010",
    "sg:province":"PA",
    "sg:tags":[
        "adjuster"
    ],
    "wof:name":"J B Adjustment Svc Inc",
    "wof:placetype":"venue"
},
  "geometry": {"coordinates":[-75.33918300000001,40.006279],"type":"Point"}
}