{
  "type": "Feature",
  "properties": {
    "iso:country":"US",
    "sg:address":"281 Timber Lake Rd",
    "sg:city":"Claysville",
    "sg:classifiers":[
        {
            "category":"Health Services",
            "subcategory":"Nursing And Care Facility",
            "type":"Services"
        }
    ],
    "sg:phone":"+1 724 948 3333",
    "sg:postcode":"15323",
    "sg:province":"PA",
    "sg:tags":[
        "personal",
        "home"
    ],
    "wof:name":"Breese Rest Home",
    "wof:placetype":"venue"
},
  "geometry": {"coordinates":[-80.391783,40.139757],"type":"Point"}
}