{
  "type": "Feature",
  "properties": {
    "iso:country":"US",
    "sg:address":"11 S 12th St",
    "sg:city":"Philadelphia",
    "sg:classifiers":[
        {
            "category":"Professional",
            "subcategory":"Printing & Photocopies",
            "type":"Services"
        }
    ],
    "sg:phone":"+1 215 568 3330",
    "sg:postcode":"19107",
    "sg:province":"PA",
    "wof:name":"Replica I Copying & Printing",
    "wof:placetype":"venue"
},
  "geometry": {"coordinates":[-75.159924,39.951682],"type":"Point"}
}