{
  "type": "Feature",
  "properties": {
    "iso:country":"US",
    "sg:address":"1681 Wabank Rd",
    "sg:city":"Lancaster",
    "sg:classifiers":[
        {
            "category":"Building & Trades",
            "subcategory":"Construction",
            "type":"Services"
        }
    ],
    "sg:phone":"+1 717 299 3804",
    "sg:postcode":"17603",
    "sg:province":"PA",
    "sg:tags":[
        "excavation",
        "excavating",
        "contractor"
    ],
    "wof:name":"J E Fristch Inc",
    "wof:placetype":"venue"
},
  "geometry": {"coordinates":[-76.324777,40.015972],"type":"Point"}
}