{
  "type": "Feature",
  "properties": {
    "addr:full":"334 Candlewood Rd Broomall PA 19008",
    "addr:housenumber":"334",
    "addr:postcode":"19008",
    "addr:street":"Candlewood Rd",
    "iso:country":"US",
    "sg:address":"334 Candlewood Rd",
    "sg:city":"Broomall",
    "sg:classifiers":[
        {
            "category":"Retail",
            "subcategory":"Auto Repair",
            "type":"Services"
        }
    ],
    "sg:phone":"+1 610 353 8455",
    "sg:postcode":"19008",
    "sg:province":"PA",
    "sg:tags":[
        "repairing",
        "automobile"
    ],
    "wof:name":"Luke's Auto Repair",
    "wof:placetype":"venue"
},
  "geometry": {"coordinates":[-75.369383,39.973187],"type":"Point"}
}