{
  "type": "Feature",
  "properties": {
    "iso:country":"US",
    "sg:address":"21663 Cussewago St",
    "sg:city":"Venango",
    "sg:classifiers":[
        {
            "category":"Government",
            "subcategory":"Post Office",
            "type":"Public Place"
        }
    ],
    "sg:phone":"+1 814 000 1111",
    "sg:postcode":"16440",
    "sg:province":"PA",
    "wof:name":"US Post Office",
    "wof:placetype":"venue"
},
  "geometry": {"coordinates":[-80.111774,41.772716],"type":"Point"}
}