{
  "type": "Feature",
  "properties": {
    "iso:country":"US",
    "sg:address":"5805 Peach St",
    "sg:city":"Erie",
    "sg:classifiers":[
        {
            "category":"Banks & Credit Unions",
            "subcategory":"Bank",
            "type":"Services"
        }
    ],
    "sg:phone":"+1 814 868 9611",
    "sg:postcode":"16509",
    "sg:province":"PA",
    "sg:tags":[
        "state",
        "commercial"
    ],
    "wof:name":"Sky Bank",
    "wof:placetype":"venue"
},
  "geometry": {"coordinates":[-80.092662,42.067872],"type":"Point"}
}