{
  "type": "Feature",
  "properties": {
    "iso:country":"US",
    "sg:address":"2335 Oneida Valley Rd",
    "sg:city":"Petrolia",
    "sg:classifiers":[
        {
            "category":"Farming",
            "subcategory":"Farm",
            "type":"Manufacturing & Wholesale Goods"
        }
    ],
    "sg:phone":"+1 724 894 2430",
    "sg:postcode":"16050",
    "sg:province":"PA",
    "wof:name":"Smith's Farms",
    "wof:placetype":"venue"
},
  "geometry": {"coordinates":[-79.81165300000001,41.055693],"type":"Point"}
}