{
  "type": "Feature",
  "properties": {
    "iso:country":"US",
    "sg:address":"7297 Park Dr",
    "sg:city":"Bath",
    "sg:classifiers":[
        {
            "category":"Retail",
            "subcategory":"Repair Shop",
            "type":"Services"
        }
    ],
    "sg:phone":"+1 610 837 8050",
    "sg:postcode":"18014",
    "sg:province":"PA",
    "sg:tags":[
        "compressor"
    ],
    "wof:name":"Air Power Compressor Co",
    "wof:placetype":"venue"
},
  "geometry": {"coordinates":[-75.41950199999999,40.701185],"type":"Point"}
}