{
  "type": "Feature",
  "properties": {
    "addr:full":"518 Ryers Ave Cheltenham PA 19012",
    "addr:housenumber":"518",
    "addr:postcode":"19012",
    "addr:street":"Ryers Ave",
    "iso:country":"US",
    "sg:address":"518 Ryers Ave",
    "sg:city":"Cheltenham",
    "sg:classifiers":[
        {
            "category":"Professional",
            "type":"Services"
        }
    ],
    "sg:phone":"+1   ",
    "sg:postcode":"19012",
    "sg:province":"PA",
    "wof:name":"Southern Draw LLC",
    "wof:placetype":"venue"
},
  "geometry": {"coordinates":[-75.094791,40.05981],"type":"Point"}
}