{
  "type": "Feature",
  "properties": {
    "iso:country":"US",
    "sg:address":"2616 E Lehigh Ave",
    "sg:city":"Philadelphia",
    "sg:classifiers":[
        {
            "category":"Restaurant",
            "type":"Food & Drink"
        }
    ],
    "sg:phone":"+1 215 291 9310",
    "sg:postcode":"19125",
    "sg:province":"PA",
    "sg:tags":[
        "deli",
        "delicatessen"
    ],
    "wof:name":"Best Deli II",
    "wof:placetype":"venue"
},
  "geometry": {"coordinates":[-75.11509700000001,39.978901],"type":"Point"}
}