{
  "type": "Feature",
  "properties": {
    "addr:full":"477 Rolling Rd Bryn Mawr PA 19010",
    "addr:housenumber":"477",
    "addr:postcode":"19010",
    "addr:street":"Rolling Rd",
    "iso:country":"US",
    "sg:address":"477 Rolling Rd",
    "sg:city":"Bryn Mawr",
    "sg:classifiers":[
        {
            "category":"Real Estate",
            "subcategory":"Real Estate Agent",
            "type":"Services"
        }
    ],
    "sg:phone":"+1   ",
    "sg:postcode":"19010",
    "sg:province":"PA",
    "wof:name":"Marenelle Associates Inc",
    "wof:placetype":"venue"
},
  "geometry": {"coordinates":[-75.35635499999999,40.021308],"type":"Point"}
}