{
  "type": "Feature",
  "properties": {
    "addr:full":"704 E 4th St Boyertown PA 19512",
    "addr:housenumber":"704",
    "addr:postcode":"19512",
    "addr:street":"E 4Th St",
    "iso:country":"US",
    "sg:address":"704 E 4th St",
    "sg:city":"Boyertown",
    "sg:classifiers":[
        {
            "category":"Wholesale",
            "subcategory":"Hardware",
            "type":"Manufacturing & Wholesale Goods"
        }
    ],
    "sg:phone":"+1 610 473 2505",
    "sg:postcode":"19512",
    "sg:province":"PA",
    "sg:tags":[
        "fastener"
    ],
    "wof:name":"System 22 Inc",
    "wof:placetype":"venue"
},
  "geometry": {"coordinates":[-75.62501399999999,40.328666],"type":"Point"}
}