{
  "type": "Feature",
  "properties": {
    "iso:country":"US",
    "sg:address":"901 Oak St",
    "sg:city":"Johnstown",
    "sg:classifiers":[
        {
            "category":"Professional",
            "subcategory":"Accounting & Tax Preparation",
            "type":"Services"
        }
    ],
    "sg:phone":"+1   ",
    "sg:postcode":"15902",
    "sg:province":"PA",
    "wof:name":"Shaffer & Co CPA",
    "wof:placetype":"venue"
},
  "geometry": {"coordinates":[-78.907974,40.305882],"type":"Point"}
}