{
  "type": "Feature",
  "properties": {
    "iso:country":"US",
    "sg:address":"33 Parkway Blvd",
    "sg:city":"York",
    "sg:classifiers":[
        {
            "category":"Retail",
            "subcategory":"Auto Repair",
            "type":"Services"
        }
    ],
    "sg:phone":"+1   ",
    "sg:postcode":"17404",
    "sg:province":"PA",
    "sg:tags":[
        "muffler",
        "brake"
    ],
    "wof:name":"Greens Marc Muffler & Brake Sp",
    "wof:placetype":"venue"
},
  "geometry": {"coordinates":[-76.73305999999999,39.971495],"type":"Point"}
}