{
  "type": "Feature",
  "properties": {
    "iso:country":"US",
    "sg:address":"2056 Saxonburg Blvd",
    "sg:city":"Gibsonia",
    "sg:classifiers":[
        {
            "category":"Restaurant",
            "type":"Food & Drink"
        }
    ],
    "sg:phone":"+1 724 265 1350",
    "sg:postcode":"15044",
    "sg:province":"PA",
    "sg:tags":[
        "pizza"
    ],
    "wof:name":"Sisters Corner Shoppe",
    "wof:placetype":"venue"
},
  "geometry": {"coordinates":[-79.861484,40.625423],"type":"Point"}
}