{
  "type": "Feature",
  "properties": {
    "iso:country":"US",
    "sg:address":"105 Aragon Pl",
    "sg:city":"Finleyville",
    "sg:classifiers":[
        {
            "category":"Professional",
            "subcategory":"Business Services",
            "type":"Services"
        }
    ],
    "sg:phone":"+1 724 348 7711",
    "sg:postcode":"15332",
    "sg:province":"PA",
    "sg:tags":[
        "water",
        "treatment"
    ],
    "wof:name":"Aragaon Industrial Svc",
    "wof:placetype":"venue"
},
  "geometry": {"coordinates":[-80.005207,40.259466],"type":"Point"}
}