{
  "type": "Feature",
  "properties": {
    "addr:full":"401 N 2nd St Pottsville PA 17901",
    "addr:housenumber":"401",
    "addr:postcode":"17901",
    "addr:street":"N 2Nd St",
    "iso:country":"US",
    "sg:address":"401 N 2nd St",
    "sg:city":"Pottsville",
    "sg:classifiers":[
        {
            "category":"Wholesale",
            "subcategory":"Vending Machines",
            "type":"Manufacturing & Wholesale Goods"
        }
    ],
    "sg:phone":"+1   ",
    "sg:postcode":"17901",
    "sg:province":"PA",
    "sg:tags":[
        "operator"
    ],
    "wof:name":"Ucp Canteen",
    "wof:placetype":"venue"
},
  "geometry": {"coordinates":[-76.19869300000001,40.688929],"type":"Point"}
}