{
  "type": "Feature",
  "properties": {
    "iso:country":"US",
    "sg:address":"1500 N 15th St",
    "sg:city":"Reading",
    "sg:classifiers":[
        {
            "category":"Professional",
            "subcategory":"Management & Consulting",
            "type":"Services"
        }
    ],
    "sg:phone":"+1 610 376 0165",
    "sg:postcode":"19604",
    "sg:province":"PA",
    "sg:tags":[
        "consultant",
        "business"
    ],
    "wof:name":"Pennsylvania Police Consultant",
    "wof:placetype":"venue"
},
  "geometry": {"coordinates":[-75.907786,40.357873],"type":"Point"}
}