{
  "type": "Feature",
  "properties": {
    "addr:full":"341 E Lincoln Ave Mc Donald PA 15057",
    "addr:housenumber":"341",
    "addr:postcode":"15057",
    "addr:street":"E Lincoln Ave Mc",
    "iso:country":"US",
    "sg:address":"341 E Lincoln Ave",
    "sg:city":"Mc Donald",
    "sg:classifiers":[
        {
            "category":"Bars & Pubs",
            "type":"Food & Drink"
        }
    ],
    "sg:phone":"+1 724 926 4555",
    "sg:postcode":"15057",
    "sg:province":"PA",
    "wof:name":"Michael's",
    "wof:placetype":"venue"
},
  "geometry": {"coordinates":[-80.230306,40.370997],"type":"Point"}
}