{
  "type": "Feature",
  "properties": {
    "iso:country":"US",
    "sg:address":"413 Garden Ave",
    "sg:city":"Grove City",
    "sg:classifiers":[
        {
            "category":"Personal",
            "type":"Services"
        }
    ],
    "sg:phone":"+1 724 458 8960",
    "sg:postcode":"16127",
    "sg:province":"PA",
    "sg:tags":[
        "hair",
        "replacement"
    ],
    "wof:name":"Camille's Hair Replacement Ctr",
    "wof:placetype":"venue"
},
  "geometry": {"coordinates":[-80.090963,41.151325],"type":"Point"}
}