{
  "type": "Feature",
  "properties": {
    "iso:country":"US",
    "sg:address":"205 N Parkview Blvd",
    "sg:city":"Bellefonte",
    "sg:classifiers":[
        {
            "category":"Restaurant",
            "type":"Food & Drink"
        }
    ],
    "sg:phone":"+1 814 353 3330",
    "sg:postcode":"16823",
    "sg:province":"PA",
    "wof:name":"Bonfatto's",
    "wof:placetype":"venue"
},
  "geometry": {"coordinates":[-77.755719,40.918155],"type":"Point"}
}