{
  "type": "Feature",
  "properties": {
    "iso:country":"US",
    "sg:address":"3100 Bergey Rd",
    "sg:city":"Hatfield",
    "sg:classifiers":[
        {
            "category":"Retail",
            "subcategory":"Auto Repair",
            "type":"Services"
        }
    ],
    "sg:phone":"+1 215 997 8997",
    "sg:postcode":"19440",
    "sg:province":"PA",
    "sg:tags":[
        "transmission"
    ],
    "wof:name":"Mike Cody's Transmissions Inc",
    "wof:placetype":"venue"
},
  "geometry": {"coordinates":[-75.292542,40.301349],"type":"Point"}
}