{
  "type": "Feature",
  "properties": {
    "iso:country":"US",
    "sg:address":"1260 Lindencross Ave",
    "sg:city":"Irwin",
    "sg:classifiers":[
        {
            "category":"Organizations",
            "subcategory":"Non-profit Organization",
            "type":"Services"
        }
    ],
    "sg:phone":"+1 724 864 1543",
    "sg:postcode":"15642",
    "sg:province":"PA",
    "sg:tags":[
        "fund",
        "counselor",
        "raising"
    ],
    "wof:name":"Bressler Enterprise",
    "wof:placetype":"venue"
},
  "geometry": {"coordinates":[-79.724754,40.313599],"type":"Point"}
}