{
  "type": "Feature",
  "properties": {
    "iso:country":"US",
    "sg:address":"213 Brownstown Hill",
    "sg:city":"Stoystown",
    "sg:classifiers":[
        {
            "category":"Building & Trades",
            "subcategory":"Construction",
            "type":"Services"
        }
    ],
    "sg:phone":"+1 814 893 5654",
    "sg:postcode":"15563",
    "sg:province":"PA",
    "sg:tags":[
        "general",
        "contractor"
    ],
    "wof:name":"Mc Clellan Electric",
    "wof:placetype":"venue"
},
  "geometry": {"coordinates":[-78.95322400000001,40.079147],"type":"Point"}
}