{
  "type": "Feature",
  "properties": {
    "iso:country":"US",
    "sg:address":"103 Hunt Club Dr",
    "sg:city":"Greensburg",
    "sg:classifiers":[
        {
            "category":"Health Services",
            "subcategory":"Doctor",
            "type":"Services"
        }
    ],
    "sg:phone":"+1   ",
    "sg:postcode":"15601",
    "sg:province":"PA",
    "wof:name":"Mark T Cirbus DDS",
    "wof:placetype":"venue"
},
  "geometry": {"coordinates":[-79.576075,40.297159],"type":"Point"}
}