{
  "type": "Feature",
  "properties": {
    "addr:full":"205 E Church St Stevens PA 17578",
    "addr:housenumber":"205",
    "addr:postcode":"stevens;17578",
    "addr:street":"E Church St",
    "iso:country":"US",
    "sg:address":"205 E Church St",
    "sg:city":"Stevens",
    "sg:classifiers":[
        {
            "category":"Manufacturing",
            "subcategory":"Printing",
            "type":"Manufacturing & Wholesale Goods"
        }
    ],
    "sg:phone":"+1 717 336 4179",
    "sg:postcode":"17578",
    "sg:province":"PA",
    "sg:tags":[
        "printer"
    ],
    "wof:name":"Cocalico Print Shoppe",
    "wof:placetype":"venue"
},
  "geometry": {"coordinates":[-76.10874099999999,40.196119],"type":"Point"}
}