{
  "type": "Feature",
  "properties": {
    "iso:country":"US",
    "sg:address":"2811 Moyers Ln",
    "sg:city":"Reading",
    "sg:classifiers":[
        {
            "category":"Organizations",
            "subcategory":"Religious Organization",
            "type":"Services"
        }
    ],
    "sg:phone":"+1   ",
    "sg:postcode":"19605",
    "sg:province":"PA",
    "wof:name":"Missionary Sisters Most Scrd",
    "wof:placetype":"venue"
},
  "geometry": {"coordinates":[-75.91753199999999,40.378119],"type":"Point"}
}