{
  "type": "Feature",
  "properties": {
    "iso:country":"US",
    "sg:address":"3583 Rothsville Rd",
    "sg:city":"Ephrata",
    "sg:classifiers":[
        {
            "category":"Restaurant",
            "type":"Food & Drink"
        }
    ],
    "sg:phone":"+1 717 721 6156",
    "sg:postcode":"17522",
    "sg:province":"PA",
    "sg:tags":[
        "eating"
    ],
    "wof:name":"Danny's Wok",
    "wof:placetype":"venue"
},
  "geometry": {"coordinates":[-76.201335,40.168948],"type":"Point"}
}