{
  "type": "Feature",
  "properties": {
    "addr:full":"724 Main St Saxton PA 16678",
    "addr:housenumber":"724",
    "addr:postcode":"16678",
    "addr:street":"Main St",
    "iso:country":"US",
    "sg:address":"724 Main St",
    "sg:city":"Saxton",
    "sg:classifiers":[
        {
            "category":"Shopping",
            "subcategory":"Used Merchandise",
            "type":"Retail Goods"
        }
    ],
    "sg:phone":"+1 814 635 0475",
    "sg:postcode":"16678",
    "sg:province":"PA",
    "sg:tags":[
        "shop",
        "consignment"
    ],
    "wof:name":"April's Resale & Variety",
    "wof:placetype":"venue"
},
  "geometry": {"coordinates":[-78.243318,40.215674],"type":"Point"}
}