{
  "type": "Feature",
  "properties": {
    "iso:country":"US",
    "sg:address":"214 E Lexington Rd",
    "sg:city":"Lititz",
    "sg:classifiers":[
        {
            "category":"Building & Trades",
            "subcategory":"Construction",
            "type":"Services"
        }
    ],
    "sg:phone":"+1 717 627 2702",
    "sg:postcode":"17543",
    "sg:province":"PA",
    "sg:tags":[
        "floor",
        "laying",
        "contractor"
    ],
    "wof:name":"Flooring Installation LTD",
    "wof:placetype":"venue"
},
  "geometry": {"coordinates":[-76.29722599999999,40.187513],"type":"Point"}
}