{
  "type": "Feature",
  "properties": {
    "iso:country":"US",
    "sg:address":"402 Clinton Rd",
    "sg:city":"Harrisburg",
    "sg:classifiers":[
        {
            "category":"Organizations",
            "subcategory":"Professional Association",
            "type":"Services"
        }
    ],
    "sg:phone":"+1   ",
    "sg:postcode":"17109",
    "sg:province":"PA",
    "sg:tags":[
        "business"
    ],
    "wof:name":"AAA Topsoil Service",
    "wof:placetype":"venue"
},
  "geometry": {"coordinates":[-76.840892,40.294279],"type":"Point"}
}