{
  "type": "Feature",
  "properties": {
    "iso:country":"US",
    "sg:address":"545 Green St",
    "sg:city":"Brownsville",
    "sg:classifiers":[
        {
            "category":"Professional",
            "type":"Services"
        }
    ],
    "sg:phone":"+1   ",
    "sg:postcode":"15417",
    "sg:province":"PA",
    "wof:name":"Drakes Roverta Elder",
    "wof:placetype":"venue"
},
  "geometry": {"coordinates":[-79.893996,40.014237],"type":"Point"}
}