{
  "type": "Feature",
  "properties": {
    "iso:country":"US",
    "sg:address":"154 Broadlawn Dr",
    "sg:city":"Elizabeth",
    "sg:classifiers":[
        {
            "category":"Manufacturing",
            "subcategory":"Metals",
            "type":"Manufacturing & Wholesale Goods"
        }
    ],
    "sg:phone":"+1 412 751 9330",
    "sg:postcode":"15037",
    "sg:province":"PA",
    "sg:tags":[
        "machine",
        "shop",
        "sheet",
        "mfg"
    ],
    "wof:name":"Barnes Sheet Metal",
    "wof:placetype":"venue"
},
  "geometry": {"coordinates":[-79.82033699999999,40.284225],"type":"Point"}
}