{
  "type": "Feature",
  "properties": {
    "addr:full":"615 N 9th St Philipsburg PA 16866",
    "addr:housenumber":"615",
    "addr:postcode":"16866",
    "addr:street":"N 9Th St",
    "iso:country":"US",
    "sg:address":"615 N 9th St",
    "sg:city":"Philipsburg",
    "sg:classifiers":[
        {
            "category":"Restaurant",
            "type":"Food & Drink"
        },
        {
            "category":"Bars & Pubs",
            "type":"Food & Drink"
        }
    ],
    "sg:phone":"+1 814 342 5307",
    "sg:postcode":"16866",
    "sg:province":"PA",
    "sg:tags":[
        "drinking"
    ],
    "wof:name":"Alice's Pub",
    "wof:placetype":"venue"
},
  "geometry": {"coordinates":[-78.219543,40.903842],"type":"Point"}
}