{
  "type": "Feature",
  "properties": {
    "iso:country":"US",
    "sg:address":"1741 Hempstead Rd",
    "sg:city":"Lancaster",
    "sg:classifiers":[
        {
            "category":"Ice Cream",
            "type":"Food & Drink"
        }
    ],
    "sg:menulink":"http://www.allmenus.com/pa/east-lampeter/209248-tcby/menu/",
    "sg:phone":"+1 717 291 2020",
    "sg:postcode":"17601",
    "sg:province":"PA",
    "sg:tags":[
        "smoothy",
        "juice",
        "american"
    ],
    "wof:name":"TCBY",
    "wof:placetype":"venue"
},
  "geometry": {"coordinates":[-76.253494,40.049525],"type":"Point"}
}