{
  "type": "Feature",
  "properties": {
    "iso:country":"US",
    "sg:address":"4166 2nd Ave",
    "sg:city":"Pittsburgh",
    "sg:classifiers":[
        {
            "category":"Wholesale",
            "subcategory":"Machinery & Supplies",
            "type":"Manufacturing & Wholesale Goods"
        }
    ],
    "sg:phone":"+1 412 471 5333",
    "sg:postcode":"15207",
    "sg:province":"PA",
    "sg:tags":[
        "equipment",
        "railroad"
    ],
    "sg:website":"www.hantzlocomotive.com",
    "wof:name":"Damian Hantz Locomotive Svc",
    "wof:placetype":"venue"
},
  "geometry": {"coordinates":[-79.952735,40.424602],"type":"Point"}
}