{
  "type": "Feature",
  "properties": {
    "iso:country":"US",
    "sg:address":"4528 Reservoir Hill Rd",
    "sg:city":"Macungie",
    "sg:classifiers":[
        {
            "category":"Building & Trades",
            "subcategory":"Construction",
            "type":"Services"
        }
    ],
    "sg:phone":"+1 610 967 0379",
    "sg:postcode":"18062",
    "sg:province":"PA",
    "sg:tags":[
        "house"
    ],
    "wof:name":"David Schnellman Remodeling",
    "wof:placetype":"venue"
},
  "geometry": {"coordinates":[-75.586406,40.490118],"type":"Point"}
}