{
  "type": "Feature",
  "properties": {
    "addr:full":"39 Parker Ave Franklin PA 16323",
    "addr:housenumber":"39",
    "addr:postcode":"16323",
    "addr:street":"Parker Ave",
    "iso:country":"US",
    "sg:address":"39 Parker Ave",
    "sg:city":"Franklin",
    "sg:classifiers":[
        {
            "category":"Social Services",
            "subcategory":"Child Care",
            "type":"Services"
        }
    ],
    "sg:phone":"+1   ",
    "sg:postcode":"16323",
    "sg:province":"PA",
    "sg:tags":[
        "day"
    ],
    "wof:name":"Young Wns Chrstn Assn Madville",
    "wof:placetype":"venue"
},
  "geometry": {"coordinates":[-79.825051,41.41043],"type":"Point"}
}