{
  "type": "Feature",
  "properties": {
    "addr:full":"3710 Broadway Allentown PA 18104",
    "addr:housenumber":"3710",
    "addr:postcode":"18104",
    "addr:street":"Broadway",
    "iso:country":"US",
    "sg:address":"3710 Broadway",
    "sg:city":"Allentown",
    "sg:classifiers":[
        {
            "category":"Health Services",
            "subcategory":"Dentist",
            "type":"Services"
        }
    ],
    "sg:phone":"+1 610 395 0742",
    "sg:postcode":"18104",
    "sg:province":"PA",
    "sg:website":"www.wasnodental.com",
    "wof:name":"Wasno Michelle M DMD",
    "wof:placetype":"venue"
},
  "geometry": {"coordinates":[-75.534536,40.58474],"type":"Point"}
}