{
  "type": "Feature",
  "properties": {
    "addr:full":"415 Glenville Rd Hanover PA 17331",
    "addr:housenumber":"415",
    "addr:postcode":"17331",
    "addr:street":"Glenville Rd",
    "iso:country":"US",
    "sg:address":"415 Glenville Rd",
    "sg:city":"Hanover",
    "sg:classifiers":[
        {
            "category":"Building & Trades",
            "subcategory":"Plumbing",
            "type":"Services"
        }
    ],
    "sg:phone":"+1   ",
    "sg:postcode":"17331",
    "sg:province":"PA",
    "sg:tags":[
        "contractor"
    ],
    "wof:name":"Mlh Plumbing",
    "wof:placetype":"venue"
},
  "geometry": {"coordinates":[-76.897612,39.727548],"type":"Point"}
}