{
  "type": "Feature",
  "properties": {
    "iso:country":"US",
    "sg:address":"50 Wyncroft Dr",
    "sg:city":"Media",
    "sg:classifiers":[
        {
            "category":"Health Services",
            "subcategory":"Doctor",
            "type":"Services"
        }
    ],
    "sg:phone":"+1   ",
    "sg:postcode":"19063",
    "sg:province":"PA",
    "wof:name":"Bodak-G L Z DMD",
    "wof:placetype":"venue"
},
  "geometry": {"coordinates":[-75.412068,39.902182],"type":"Point"}
}