{
  "type": "Feature",
  "properties": {
    "iso:country":"US",
    "sg:address":"6025 Torresdale Ave",
    "sg:city":"Philadelphia",
    "sg:classifiers":[
        {
            "category":"Manufacturing",
            "subcategory":"Printing",
            "type":"Manufacturing & Wholesale Goods"
        }
    ],
    "sg:phone":"+1 215 288 1799",
    "sg:postcode":"19135",
    "sg:province":"PA",
    "sg:tags":[
        "printer"
    ],
    "wof:name":"Alexander's Printing Svc",
    "wof:placetype":"venue"
},
  "geometry": {"coordinates":[-75.057647,40.018402],"type":"Point"}
}