{
  "type": "Feature",
  "properties": {
    "iso:country":"US",
    "sg:address":"4843 N Broad St",
    "sg:city":"Philadelphia",
    "sg:classifiers":[
        {
            "category":"Wholesale",
            "subcategory":"Hardware",
            "type":"Manufacturing & Wholesale Goods"
        }
    ],
    "sg:phone":"+1 215 457 8211",
    "sg:postcode":"19141",
    "sg:province":"PA",
    "wof:name":"Amy Hairbraiding",
    "wof:placetype":"venue"
},
  "geometry": {"coordinates":[-75.147555,40.026137],"type":"Point"}
}