{
  "type": "Feature",
  "properties": {
    "iso:country":"US",
    "sg:address":"229 Hufnagel Rd",
    "sg:city":"Harmony",
    "sg:classifiers":[
        {
            "category":"Insurance",
            "subcategory":"Insurance Agent",
            "type":"Services"
        }
    ],
    "sg:phone":"+1 724 368 8631",
    "sg:postcode":"16037",
    "sg:province":"PA",
    "wof:name":"Rupp Fiore Waychoff Insurance",
    "wof:placetype":"venue"
},
  "geometry": {"coordinates":[-80.141569,40.90436],"type":"Point"}
}