{
  "type": "Feature",
  "properties": {
    "iso:country":"US",
    "sg:address":"15504 Middle Rd",
    "sg:city":"Meadville",
    "sg:classifiers":[
        {
            "category":"Manufacturing",
            "subcategory":"Tools & Machinery",
            "type":"Manufacturing & Wholesale Goods"
        }
    ],
    "sg:phone":"+1 814 724 5393",
    "sg:postcode":"16335",
    "sg:province":"PA",
    "sg:tags":[
        "cutting",
        "metal",
        "mfg"
    ],
    "wof:name":"Hamilton Tool Co Inc",
    "wof:placetype":"venue"
},
  "geometry": {"coordinates":[-80.224689,41.628168],"type":"Point"}
}