{
  "type": "Feature",
  "properties": {
    "addr:full":"1900 Frost Rd Bristol PA 19007",
    "addr:housenumber":"1900",
    "addr:postcode":"19007",
    "addr:street":"Frost Rd",
    "iso:country":"US",
    "sg:address":"1900 Frost Rd",
    "sg:city":"Bristol",
    "sg:classifiers":[
        {
            "category":"Wholesale",
            "subcategory":"Construction Materials",
            "type":"Manufacturing & Wholesale Goods"
        }
    ],
    "sg:phone":"+1   ",
    "sg:postcode":"19007",
    "sg:province":"PA",
    "wof:name":"Amarr Garage Doors",
    "wof:placetype":"venue"
},
  "geometry": {"coordinates":[-74.897537,40.115338],"type":"Point"}
}