{
  "type": "Feature",
  "properties": {
    "addr:full":"974 Osage Rd Pittsburgh PA 15243",
    "addr:housenumber":"974",
    "addr:postcode":"15243",
    "addr:street":"Osage Rd",
    "iso:country":"US",
    "sg:address":"974 Osage Rd",
    "sg:city":"Pittsburgh",
    "sg:classifiers":[
        {
            "category":"Wholesale",
            "subcategory":"Metals & Minerals",
            "type":"Manufacturing & Wholesale Goods"
        }
    ],
    "sg:phone":"+1   ",
    "sg:postcode":"15243",
    "sg:province":"PA",
    "sg:tags":[
        "steel",
        "export"
    ],
    "wof:name":"Alternative Intl Solutions",
    "wof:placetype":"venue"
},
  "geometry": {"coordinates":[-80.073027,40.387887],"type":"Point"}
}