{
  "type": "Feature",
  "properties": {
    "iso:country":"US",
    "sg:address":"5945 Pilgrim Rd",
    "sg:city":"Erie",
    "sg:classifiers":[
        {
            "category":"Professional",
            "type":"Services"
        }
    ],
    "sg:phone":"+1   ",
    "sg:postcode":"16509",
    "sg:province":"PA",
    "wof:name":"Mosmot Inc",
    "wof:placetype":"venue"
},
  "geometry": {"coordinates":[-80.059856,42.076151],"type":"Point"}
}