{
  "type": "Feature",
  "properties": {
    "addr:full":"102 Cooper Ave Oil City PA 16301",
    "addr:housenumber":"102",
    "addr:postcode":"16301",
    "addr:street":"Cooper Ave",
    "iso:country":"US",
    "sg:address":"102 Cooper Ave",
    "sg:city":"Oil City",
    "sg:classifiers":[
        {
            "category":"Shopping",
            "subcategory":"Bicycles & Sporting Goods",
            "type":"Retail Goods"
        }
    ],
    "sg:phone":"+1   ",
    "sg:postcode":"16301",
    "sg:province":"PA",
    "wof:name":"Palace Hill Mall",
    "wof:placetype":"venue"
},
  "geometry": {"coordinates":[-79.70590199999999,41.439556],"type":"Point"}
}