{
  "type": "Feature",
  "properties": {
    "iso:country":"US",
    "sg:address":"416 Reitnour Rd",
    "sg:city":"Spring City",
    "sg:classifiers":[
        {
            "category":"Building & Trades",
            "subcategory":"Electrical",
            "type":"Services"
        }
    ],
    "sg:phone":"+1   ",
    "sg:postcode":"19475",
    "sg:province":"PA",
    "sg:tags":[
        "electrical",
        "contractor"
    ],
    "wof:name":"Jeffries Electric Inc",
    "wof:placetype":"venue"
},
  "geometry": {"coordinates":[-75.58183,40.185575],"type":"Point"}
}