{
  "type": "Feature",
  "properties": {
    "iso:country":"US",
    "sg:address":"115 E North St",
    "sg:city":"Butler",
    "sg:classifiers":[
        {
            "category":"Insurance",
            "subcategory":"Insurance Agent",
            "type":"Services"
        }
    ],
    "sg:phone":"+1 724 283 4496",
    "sg:postcode":"16001",
    "sg:province":"PA",
    "wof:name":"Alpine Insurance & Financial",
    "wof:placetype":"venue"
},
  "geometry": {"coordinates":[-79.89478,40.862223],"type":"Point"}
}