{
  "type": "Feature",
  "properties": {
    "iso:country":"US",
    "sg:address":"1811 Fox Chase Rd",
    "sg:city":"Philadelphia",
    "sg:classifiers":[
        {
            "category":"Health Services",
            "subcategory":"Health Practitioner",
            "type":"Services"
        }
    ],
    "sg:phone":"+1 215 722 7211",
    "sg:postcode":"19152",
    "sg:province":"PA",
    "sg:tags":[
        "psychotherapist"
    ],
    "wof:name":"Herman L Horowitz",
    "wof:placetype":"venue"
},
  "geometry": {"coordinates":[-75.052887,40.068181],"type":"Point"}
}