{
  "type": "Feature",
  "properties": {
    "iso:country":"US",
    "sg:address":"120 Mill Creek Ave",
    "sg:city":"Pottsville",
    "sg:classifiers":[
        {
            "category":"Shopping",
            "subcategory":"Shoes",
            "type":"Retail Goods"
        }
    ],
    "sg:phone":"+1 570 628 5371",
    "sg:postcode":"17901",
    "sg:province":"PA",
    "wof:name":"Moore's Sneaker Place",
    "wof:placetype":"venue"
},
  "geometry": {"coordinates":[-76.18404099999999,40.697953],"type":"Point"}
}