{
  "type": "Feature",
  "properties": {
    "iso:country":"US",
    "sg:address":"800 W Bridge St",
    "sg:city":"Phoenixville",
    "sg:classifiers":[
        {
            "category":"Restaurant",
            "type":"Food & Drink"
        }
    ],
    "sg:phone":"+1   ",
    "sg:postcode":"19460",
    "sg:province":"PA",
    "sg:tags":[
        "eating"
    ],
    "wof:name":"Tri-Corners Deli",
    "wof:placetype":"venue"
},
  "geometry": {"coordinates":[-75.529893,40.127556],"type":"Point"}
}