{
  "type": "Feature",
  "properties": {
    "iso:country":"US",
    "sg:address":"614 Roseto Ave",
    "sg:city":"Roseto",
    "sg:classifiers":[
        {
            "category":"Personal",
            "subcategory":"Beauty Salon",
            "type":"Services"
        }
    ],
    "sg:phone":"+1 610 588 6625",
    "sg:postcode":"18013",
    "sg:province":"PA",
    "wof:name":"Tommie's Hair Styling",
    "wof:placetype":"venue"
},
  "geometry": {"coordinates":[-75.214276,40.882958],"type":"Point"}
}