{
  "type": "Feature",
  "properties": {
    "iso:country":"US",
    "sg:address":"302 Pine St",
    "sg:city":"Glenolden",
    "sg:classifiers":[
        {
            "category":"Professional",
            "type":"Services"
        }
    ],
    "sg:phone":"+1   ",
    "sg:postcode":"19036",
    "sg:province":"PA",
    "wof:name":"Eastern Sportswear",
    "wof:placetype":"venue"
},
  "geometry": {"coordinates":[-75.28971799999999,39.915854],"type":"Point"}
}