{
  "type": "Feature",
  "properties": {
    "iso:country":"US",
    "sg:address":"50 W Main St",
    "sg:city":"Leola",
    "sg:classifiers":[
        {
            "category":"Government",
            "subcategory":"Fire Station",
            "type":"Public Place"
        }
    ],
    "sg:phone":"+1 717 656 9881",
    "sg:postcode":"17540",
    "sg:province":"PA",
    "sg:tags":[
        "department"
    ],
    "wof:name":"Leola Fire Co",
    "wof:placetype":"venue"
},
  "geometry": {"coordinates":[-76.18901700000001,40.08736],"type":"Point"}
}