{
  "type": "Feature",
  "properties": {
    "addr:full":"424 Rose Hill Rd Ephrata PA 17522",
    "addr:housenumber":"424",
    "addr:postcode":"17522",
    "addr:street":"Rose Hill Rd",
    "iso:country":"US",
    "sg:address":"424 Rose Hill Rd",
    "sg:city":"Ephrata",
    "sg:classifiers":[
        {
            "category":"Professional",
            "subcategory":"Art Services",
            "type":"Services"
        }
    ],
    "sg:phone":"+1 717 859 3200",
    "sg:postcode":"17522",
    "sg:province":"PA",
    "sg:tags":[
        "photographer"
    ],
    "wof:name":"Lori Stahl Photography",
    "wof:placetype":"venue"
},
  "geometry": {"coordinates":[-76.23031,40.131224],"type":"Point"}
}