{
  "type": "Feature",
  "properties": {
    "iso:country":"US",
    "sg:address":"3842 Richlieu Rd",
    "sg:city":"Bensalem",
    "sg:classifiers":[
        {
            "category":"Building & Trades",
            "subcategory":"Construction",
            "type":"Services"
        }
    ],
    "sg:phone":"+1   ",
    "sg:postcode":"19020",
    "sg:province":"PA",
    "sg:tags":[
        "house"
    ],
    "wof:name":"Realen Homes",
    "wof:placetype":"venue"
},
  "geometry": {"coordinates":[-74.949634,40.129534],"type":"Point"}
}