{
  "type": "Feature",
  "properties": {
    "addr:full":"10 Warwick St Boyertown PA 19512",
    "addr:housenumber":"10",
    "addr:postcode":"19512",
    "addr:street":"Warwick St",
    "iso:country":"US",
    "sg:address":"10 Warwick St",
    "sg:city":"Boyertown",
    "sg:classifiers":[
        {
            "category":"Manufacturing",
            "subcategory":"Tools & Machinery",
            "type":"Manufacturing & Wholesale Goods"
        }
    ],
    "sg:phone":"+1 610 367 1533",
    "sg:postcode":"19512",
    "sg:province":"PA",
    "sg:tags":[
        "mfg",
        "industrial",
        "general"
    ],
    "wof:name":"F H & L Apparatus Crew",
    "wof:placetype":"venue"
},
  "geometry": {"coordinates":[-75.638998,40.332044],"type":"Point"}
}