{
  "type": "Feature",
  "properties": {
    "addr:full":"3190 Schuylkill Rd Spring City PA 19475",
    "addr:postcode":"3190;19475",
    "addr:street":"Schuylkill Rd",
    "iso:country":"US",
    "sg:address":"3190 Schuylkill Rd",
    "sg:city":"Spring City",
    "sg:classifiers":[
        {
            "category":"Food & Beverages",
            "subcategory":"Fruits & Vegetables",
            "type":"Retail Goods"
        }
    ],
    "sg:phone":"+1 610 495 4555",
    "sg:postcode":"19475",
    "sg:province":"PA",
    "sg:tags":[
        "farm",
        "market"
    ],
    "wof:name":"Farmer's Daughter",
    "wof:placetype":"venue"
},
  "geometry": {"coordinates":[-75.557146,40.169166],"type":"Point"}
}