{
  "type": "Feature",
  "properties": {
    "iso:country":"US",
    "sg:address":"430 B St",
    "sg:city":"Carlisle",
    "sg:classifiers":[
        {
            "category":"Organizations",
            "subcategory":"Religious Organization",
            "type":"Services"
        }
    ],
    "sg:phone":"+1 717 243 5145",
    "sg:postcode":"17013",
    "sg:province":"PA",
    "sg:tags":[
        "church"
    ],
    "wof:name":"Wesleyan Church Of The Cross",
    "wof:placetype":"venue"
},
  "geometry": {"coordinates":[-77.19716,40.209701],"type":"Point"}
}