{
  "type": "Feature",
  "properties": {
    "addr:full":"2950 Clymer Ave Telford PA 18969",
    "addr:postcode":"2950;18969",
    "addr:street":"Clymer Ave",
    "iso:country":"US",
    "sg:address":"2950 Clymer Ave",
    "sg:city":"Telford",
    "sg:classifiers":[
        {
            "category":"Retail",
            "subcategory":"Repair Shop",
            "type":"Services"
        },
        {
            "category":"Building & Trades",
            "subcategory":"Plumbing",
            "type":"Services"
        }
    ],
    "sg:phone":"+1 215 723 2169",
    "sg:postcode":"18969",
    "sg:province":"PA",
    "sg:tags":[
        "system",
        "contractor",
        "refrigeration",
        "conditioning",
        "conditioner",
        "air"
    ],
    "wof:name":"Walter R Dorn Estate Inc",
    "wof:placetype":"venue"
},
  "geometry": {"coordinates":[-75.329759,40.342411],"type":"Point"}
}