{
  "type": "Feature",
  "properties": {
    "iso:country":"US",
    "sg:address":"104 Baltimore St",
    "sg:city":"Hanover",
    "sg:classifiers":[
        {
            "category":"Personal",
            "subcategory":"Barber",
            "type":"Services"
        }
    ],
    "sg:phone":"+1 717 632 0260",
    "sg:postcode":"17331",
    "sg:province":"PA",
    "sg:tags":[
        "shop"
    ],
    "wof:name":"Rohrbaugh's Barber Shop",
    "wof:placetype":"venue"
},
  "geometry": {"coordinates":[-76.981602,39.798968],"type":"Point"}
}