{
  "type": "Feature",
  "properties": {
    "addr:full":"609 Monongahela Ave Glassport PA 15045",
    "addr:housenumber":"609",
    "addr:postcode":"15045",
    "addr:street":"Monongahela Ave",
    "iso:country":"US",
    "sg:address":"609 Monongahela Ave",
    "sg:city":"Glassport",
    "sg:classifiers":[
        {
            "category":"Health Services",
            "subcategory":"Doctor",
            "type":"Services"
        }
    ],
    "sg:phone":"+1   ",
    "sg:postcode":"15045",
    "sg:province":"PA",
    "wof:name":"Joel A Casar DMD",
    "wof:placetype":"venue"
},
  "geometry": {"coordinates":[-79.892385,40.324484],"type":"Point"}
}