{
  "type": "Feature",
  "properties": {
    "iso:country":"US",
    "sg:address":"11129 Gehr Rd",
    "sg:city":"Waynesboro",
    "sg:phone":"+1   ",
    "sg:postcode":"17268",
    "sg:province":"PA",
    "sg:tags":[
        "farm",
        "dairy"
    ],
    "wof:name":"Reynolds Farm",
    "wof:placetype":"venue"
},
  "geometry": {"coordinates":[-77.53464700000001,39.768944],"type":"Point"}
}