{
  "type": "Feature",
  "properties": {
    "addr:full":"2159 Herblew Rd Warrington PA 18976",
    "addr:housenumber":"2159",
    "addr:postcode":"18976",
    "addr:street":"Herblew Rd",
    "iso:country":"US",
    "sg:address":"2159 Herblew Rd",
    "sg:city":"Warrington",
    "sg:classifiers":[
        {
            "category":"Retail",
            "subcategory":"Portrait Studio",
            "type":"Services"
        }
    ],
    "sg:phone":"+1 215 343 1138",
    "sg:postcode":"18976",
    "sg:province":"PA",
    "sg:tags":[
        "photographer"
    ],
    "wof:name":"John W Fern",
    "wof:placetype":"venue"
},
  "geometry": {"coordinates":[-75.119534,40.250455],"type":"Point"}
}