{
  "type": "Feature",
  "properties": {
    "iso:country":"US",
    "sg:address":"2109 Murray Ave",
    "sg:city":"Pittsburgh",
    "sg:classifiers":[
        {
            "category":"Restaurant",
            "type":"Food & Drink"
        }
    ],
    "sg:phone":"+1 412 521 3250",
    "sg:postcode":"15217",
    "sg:province":"PA",
    "sg:tags":[
        "mexican"
    ],
    "wof:name":"Cuzamill Restaurante Mexicano",
    "wof:placetype":"venue"
},
  "geometry": {"coordinates":[-79.922961,40.433709],"type":"Point"}
}