{
  "type": "Feature",
  "properties": {
    "iso:country":"US",
    "sg:address":"1078 Trinity Ln",
    "sg:city":"Conshohocken",
    "sg:classifiers":[
        {
            "category":"Building & Trades",
            "subcategory":"Landscaping Services",
            "type":"Services"
        }
    ],
    "sg:phone":"+1 610 687 5595",
    "sg:postcode":"19428",
    "sg:province":"PA",
    "sg:tags":[
        "landscape",
        "contractor"
    ],
    "wof:name":"Wandering Weeders",
    "wof:placetype":"venue"
},
  "geometry": {"coordinates":[-75.34208599999999,40.067566],"type":"Point"}
}