{
  "type": "Feature",
  "properties": {
    "iso:country":"US",
    "sg:address":"2528 S Broad St",
    "sg:city":"Philadelphia",
    "sg:classifiers":[
        {
            "category":"Government",
            "subcategory":"Office",
            "type":"Public Place"
        }
    ],
    "sg:phone":"+1 215 468 7152",
    "sg:postcode":"19145",
    "sg:province":"PA",
    "sg:tags":[
        "force",
        "armed",
        "recruiting"
    ],
    "sg:website":"http://www.navy.com",
    "wof:name":"Nrs South Philly",
    "wof:placetype":"venue"
},
  "geometry": {"coordinates":[-75.17084699999999,39.919036],"type":"Point"}
}