{
  "type": "Feature",
  "properties": {
    "iso:country":"US",
    "sg:address":"3130 Richmond St",
    "sg:city":"Philadelphia",
    "sg:classifiers":[
        {
            "category":"Retail",
            "subcategory":"Repair Shop",
            "type":"Services"
        },
        {
            "category":"Manufacturing",
            "subcategory":"Food",
            "type":"Manufacturing & Wholesale Goods"
        }
    ],
    "sg:phone":"+1 215 426 8639",
    "sg:postcode":"19134",
    "sg:province":"PA",
    "sg:tags":[
        "marine",
        "oil",
        "refrigeration",
        "animal",
        "fat"
    ],
    "wof:name":"R T A Electronics",
    "wof:placetype":"venue"
},
  "geometry": {"coordinates":[-75.102395,39.982535],"type":"Point"}
}