{
  "type": "Feature",
  "properties": {
    "iso:country":"US",
    "sg:address":"579 E Lancaster Ave",
    "sg:city":"Berwyn",
    "sg:classifiers":[
        {
            "category":"Building & Trades",
            "subcategory":"Construction",
            "type":"Services"
        }
    ],
    "sg:phone":"+1   ",
    "sg:postcode":"19312",
    "sg:province":"PA",
    "sg:tags":[
        "glass",
        "installation",
        "store"
    ],
    "wof:name":"Berwyn Glass Company",
    "wof:placetype":"venue"
},
  "geometry": {"coordinates":[-75.44128499999999,40.048046],"type":"Point"}
}