{
  "type": "Feature",
  "properties": {
    "addr:full":"121 Main St New Eagle PA 15067",
    "addr:housenumber":"121",
    "addr:postcode":"15067",
    "addr:street":"Main St",
    "iso:country":"US",
    "sg:address":"121 Main St",
    "sg:city":"New Eagle",
    "sg:classifiers":[
        {
            "category":"Shopping",
            "subcategory":"Bicycles & Sporting Goods",
            "type":"Retail Goods"
        }
    ],
    "sg:phone":"+1 724 258 3711",
    "sg:postcode":"15067",
    "sg:province":"PA",
    "wof:name":"Varrone's Hole In the Wall Sport Shop",
    "wof:placetype":"venue"
},
  "geometry": {"coordinates":[-79.946701,40.207901],"type":"Point"}
}