{
  "type": "Feature",
  "properties": {
    "addr:full":"222 S Broad St Grove City PA 16127",
    "addr:housenumber":"222",
    "addr:postcode":"16127",
    "addr:street":"S Broad St",
    "iso:country":"US",
    "sg:address":"222 S Broad St",
    "sg:city":"Grove City",
    "sg:classifiers":[
        {
            "category":"Shopping",
            "subcategory":"Gifts & Souvenirs",
            "type":"Retail Goods"
        }
    ],
    "sg:phone":"+1   ",
    "sg:postcode":"16127",
    "sg:province":"PA",
    "wof:name":"Corban Candle Co & Gift Sp",
    "wof:placetype":"venue"
},
  "geometry": {"coordinates":[-80.086512,41.159274],"type":"Point"}
}