{
  "type": "Feature",
  "properties": {
    "iso:country":"US",
    "sg:address":"1007 N Ridge Rd",
    "sg:city":"Perkasie",
    "sg:classifiers":[
        {
            "category":"Bars & Pubs",
            "type":"Food & Drink"
        },
        {
            "category":"Restaurant",
            "type":"Food & Drink"
        }
    ],
    "sg:phone":"+1 215 257 5994",
    "sg:postcode":"18944",
    "sg:province":"PA",
    "sg:tags":[
        "tavern",
        "style",
        "family"
    ],
    "wof:name":"Country Place",
    "wof:placetype":"venue"
},
  "geometry": {"coordinates":[-75.286524,40.385902],"type":"Point"}
}