{
  "type": "Feature",
  "properties": {
    "iso:country":"US",
    "sg:address":"3131 Millers Run Rd",
    "sg:city":"Cecil",
    "sg:classifiers":[
        {
            "category":"Shopping",
            "subcategory":"Used Merchandise",
            "type":"Retail Goods"
        }
    ],
    "sg:phone":"+1   ",
    "sg:postcode":"15321",
    "sg:province":"PA",
    "sg:tags":[
        "clothing"
    ],
    "wof:name":"Before and More",
    "wof:placetype":"venue"
},
  "geometry": {"coordinates":[-80.18892700000001,40.327536],"type":"Point"}
}