{
  "type": "Feature",
  "properties": {
    "iso:country":"US",
    "sg:address":"6115 Cobbs Creek Pkwy",
    "sg:city":"Philadelphia",
    "sg:classifiers":[
        {
            "category":"Organizations",
            "subcategory":"Religious Organization",
            "type":"Services"
        }
    ],
    "sg:phone":"+1 215 747 6281",
    "sg:postcode":"19143",
    "sg:province":"PA",
    "sg:tags":[
        "clergy"
    ],
    "wof:name":"E K Nichols Jr Rev",
    "wof:placetype":"venue"
},
  "geometry": {"coordinates":[-75.24628300000001,39.946607],"type":"Point"}
}