{
  "type": "Feature",
  "properties": {
    "iso:country":"US",
    "sg:address":"2017 Bernville Rd",
    "sg:city":"Reading",
    "sg:classifiers":[
        {
            "category":"Professional",
            "type":"Services"
        }
    ],
    "sg:phone":"+1 610 371 9012",
    "sg:postcode":"19601",
    "sg:province":"PA",
    "sg:tags":[
        "establishment"
    ],
    "wof:name":"Alternate Postal Direct",
    "wof:placetype":"venue"
},
  "geometry": {"coordinates":[-75.955078,40.364877],"type":"Point"}
}