{
  "type": "Feature",
  "properties": {
    "iso:country":"US",
    "sg:address":"953 E Tioga St",
    "sg:city":"Philadelphia",
    "sg:classifiers":[
        {
            "category":"Restaurant",
            "type":"Food & Drink"
        }
    ],
    "sg:phone":"+1   ",
    "sg:postcode":"19134",
    "sg:province":"PA",
    "sg:tags":[
        "pizzeria"
    ],
    "wof:name":"Tioga Express Pizza",
    "wof:placetype":"venue"
},
  "geometry": {"coordinates":[-75.110648,40.000969],"type":"Point"}
}