{
  "type": "Feature",
  "properties": {
    "iso:country":"US",
    "sg:address":"100 5th Ave",
    "sg:city":"Pittsburgh",
    "sg:classifiers":[
        {
            "category":"Shopping",
            "subcategory":"Crafts & Fabrics",
            "type":"Retail Goods"
        }
    ],
    "sg:phone":"+1 412 281 8345",
    "sg:postcode":"15219",
    "sg:province":"PA",
    "sg:tags":[
        "monogram"
    ],
    "wof:name":"Prosperi's Hand Monogram Shop",
    "wof:placetype":"venue"
},
  "geometry": {"coordinates":[-80.002494,40.44153],"type":"Point"}
}