{
  "type": "Feature",
  "properties": {
    "addr:full":"124 Broadway Hanover PA 17331",
    "addr:housenumber":"124",
    "addr:postcode":"17331",
    "addr:street":"Broadway",
    "iso:country":"US",
    "sg:address":"124 Broadway",
    "sg:city":"Hanover",
    "sg:classifiers":[
        {
            "category":"Organizations",
            "subcategory":"Religious Organization",
            "type":"Services"
        }
    ],
    "sg:phone":"+1 717 632 8281",
    "sg:postcode":"17331",
    "sg:province":"PA",
    "sg:tags":[
        "church"
    ],
    "sg:website":"www.emmanuelucc.org",
    "wof:name":"Emmanuel United Ch of Christ",
    "wof:placetype":"venue"
},
  "geometry": {"coordinates":[-76.982629,39.801121],"type":"Point"}
}