{
  "type": "Feature",
  "properties": {
    "iso:country":"US",
    "sg:address":"315 W High St",
    "sg:city":"New Oxford",
    "sg:classifiers":[
        {
            "category":"Building & Trades",
            "subcategory":"Construction",
            "type":"Services"
        }
    ],
    "sg:phone":"+1 717 624 7417",
    "sg:postcode":"17350",
    "sg:province":"PA",
    "sg:tags":[
        "roofing",
        "contractor"
    ],
    "wof:name":"Raymar Roofing Co",
    "wof:placetype":"venue"
},
  "geometry": {"coordinates":[-77.06084199999999,39.861235],"type":"Point"}
}