{
  "type": "Feature",
  "properties": {
    "addr:full":"714 Dekalb Pike Blue Bell PA 19422",
    "addr:housenumber":"714",
    "addr:postcode":"19422",
    "addr:street":"Dekalb Pike",
    "iso:country":"US",
    "sg:address":"714 Dekalb Pike",
    "sg:city":"Blue Bell",
    "sg:classifiers":[
        {
            "category":"Real Estate",
            "subcategory":"Real Estate Agent",
            "type":"Services"
        }
    ],
    "sg:phone":"+1 215 641 2727",
    "sg:postcode":"19422",
    "sg:province":"PA",
    "sg:website":"www.annadonna.com",
    "wof:name":"Coldwell Banker",
    "wof:placetype":"venue"
},
  "geometry": {"coordinates":[-75.287272,40.169983],"type":"Point"}
}