{
  "type": "Feature",
  "properties": {
    "iso:country":"US",
    "sg:address":"1219 Sylvan Rd",
    "sg:city":"West Chester",
    "sg:classifiers":[
        {
            "category":"Building & Trades",
            "subcategory":"Plumbing",
            "type":"Services"
        }
    ],
    "sg:phone":"+1   ",
    "sg:postcode":"19382",
    "sg:province":"PA",
    "sg:tags":[
        "contractor"
    ],
    "wof:name":"ABC Hvac Inc",
    "wof:placetype":"venue"
},
  "geometry": {"coordinates":[-75.555134,39.96471],"type":"Point"}
}