{
  "type": "Feature",
  "properties": {
    "iso:country":"US",
    "sg:address":"800 W Rte 897",
    "sg:city":"Reinholds",
    "sg:classifiers":[
        {
            "category":"Professional",
            "subcategory":"Computer Services",
            "type":"Services"
        }
    ],
    "sg:phone":"+1 717 336 2707",
    "sg:postcode":"17569",
    "sg:province":"PA",
    "wof:name":"Network Design & Consulting",
    "wof:placetype":"venue"
},
  "geometry": {"coordinates":[-76.140885,40.280044],"type":"Point"}
}