{
  "type": "Feature",
  "properties": {
    "iso:country":"US",
    "sg:address":"1000 N Brodhead Rd",
    "sg:city":"Aliquippa",
    "sg:classifiers":[
        {
            "category":"Restaurant",
            "type":"Food & Drink"
        }
    ],
    "sg:menulink":"http://www.allmenus.com/pa/center/211226-kfc---kentucky-fried-chicken/menu/",
    "sg:phone":"+1 412 375 4960",
    "sg:postcode":"15001",
    "sg:province":"PA",
    "sg:tags":[
        "american",
        "chicken"
    ],
    "wof:name":"KFC - Kentucky Fried Chicken",
    "wof:placetype":"venue"
},
  "geometry": {"coordinates":[-80.310597,40.638992],"type":"Point"}
}