{
  "type": "Feature",
  "properties": {
    "iso:country":"US",
    "sg:address":"320 E State St",
    "sg:city":"Kennett Square",
    "sg:classifiers":[
        {
            "category":"Wholesale",
            "subcategory":"Hardware",
            "type":"Manufacturing & Wholesale Goods"
        }
    ],
    "sg:phone":"+1   ",
    "sg:postcode":"19348",
    "sg:province":"PA",
    "sg:tags":[
        "plumbing"
    ],
    "wof:name":"Hajoca Corporation",
    "wof:placetype":"venue"
},
  "geometry": {"coordinates":[-75.709192,39.847471],"type":"Point"}
}