{
  "type": "Feature",
  "properties": {
    "iso:country":"US",
    "sg:address":"507 S 6th St",
    "sg:city":"Philadelphia",
    "sg:classifiers":[
        {
            "category":"Restaurant",
            "type":"Food & Drink"
        }
    ],
    "sg:menulink":"http://www.allmenus.com/pa/philadelphia/50368-giannas-pizzeria/menu/",
    "sg:phone":"+1 215 829 4448",
    "sg:postcode":"19147",
    "sg:province":"PA",
    "sg:tags":[
        "italian"
    ],
    "wof:name":"Gianna's Pizzeria",
    "wof:placetype":"venue"
},
  "geometry": {"coordinates":[-75.15223,39.942664],"type":"Point"}
}