{
  "type": "Feature",
  "properties": {
    "iso:country":"US",
    "sg:address":"408 Highland Ave",
    "sg:city":"Ambler",
    "sg:classifiers":[
        {
            "category":"Building & Trades",
            "subcategory":"Construction",
            "type":"Services"
        }
    ],
    "sg:phone":"+1   ",
    "sg:postcode":"19002",
    "sg:province":"PA",
    "sg:tags":[
        "nonresidential"
    ],
    "wof:name":"Thomas Lorenzo Construction",
    "wof:placetype":"venue"
},
  "geometry": {"coordinates":[-75.21451500000001,40.15035],"type":"Point"}
}