{
  "type": "Feature",
  "properties": {
    "iso:country":"US",
    "sg:address":"15 Presidential Blvd Ste 300",
    "sg:city":"Bala Cynwyd",
    "sg:classifiers":[
        {
            "category":"Health Services",
            "subcategory":"Doctor",
            "type":"Services"
        }
    ],
    "sg:phone":"+1 610 667 2663",
    "sg:postcode":"19004",
    "sg:province":"PA",
    "wof:name":"Schmidt Richard MD",
    "wof:placetype":"venue"
},
  "geometry": {"coordinates":[-75.211304,40.009602],"type":"Point"}
}