{
  "type": "Feature",
  "properties": {
    "iso:country":"US",
    "sg:address":"2003 Broad Hill Farms Rd",
    "sg:city":"Coraopolis",
    "sg:classifiers":[
        {
            "category":"Bars & Pubs",
            "subcategory":"Lounge",
            "type":"Food & Drink"
        }
    ],
    "sg:phone":"+1 724 457 0211",
    "sg:postcode":"15108",
    "sg:province":"PA",
    "sg:tags":[
        "cocktail"
    ],
    "wof:name":"Butya S Lounge",
    "wof:placetype":"venue"
},
  "geometry": {"coordinates":[-80.23200199999999,40.544135],"type":"Point"}
}