{
  "type": "Feature",
  "properties": {
    "iso:country":"US",
    "sg:address":"130 Mifflin St",
    "sg:city":"Lebanon",
    "sg:classifiers":[
        {
            "category":"Building & Trades",
            "subcategory":"Plumbing",
            "type":"Services"
        }
    ],
    "sg:phone":"+1   ",
    "sg:postcode":"17046",
    "sg:province":"PA",
    "sg:tags":[
        "contractor"
    ],
    "wof:name":"B & M Plumbing & Heating Inc",
    "wof:placetype":"venue"
},
  "geometry": {"coordinates":[-76.414587,40.346917],"type":"Point"}
}