{
  "type": "Feature",
  "properties": {
    "iso:country":"US",
    "sg:address":"603 Washington Rd",
    "sg:city":"Pittsburgh",
    "sg:classifiers":[
        {
            "category":"Health Services",
            "subcategory":"Dentist",
            "type":"Services"
        }
    ],
    "sg:phone":"+1 412 563 2501",
    "sg:postcode":"15228",
    "sg:province":"PA",
    "wof:name":"McFarland Edw M III DMD",
    "wof:placetype":"venue"
},
  "geometry": {"coordinates":[-80.0439,40.3829],"type":"Point"}
}