{
  "type": "Feature",
  "properties": {
    "iso:country":"US",
    "sg:address":"32 S Warner Ave",
    "sg:city":"Bryn Mawr",
    "sg:classifiers":[
        {
            "category":"Shopping",
            "type":"Retail Goods"
        }
    ],
    "sg:phone":"+1   ",
    "sg:postcode":"19010",
    "sg:province":"PA",
    "sg:tags":[
        "equipment",
        "radio",
        "telecommunication"
    ],
    "wof:name":"Eclectik",
    "wof:placetype":"venue"
},
  "geometry": {"coordinates":[-75.324448,40.022231],"type":"Point"}
}