{
  "type": "Feature",
  "properties": {
    "addr:full":"6955 Hillside Dr Bloomsburg PA 17815",
    "addr:housenumber":"6955",
    "addr:postcode":"17815",
    "addr:street":"Hillside Dr",
    "iso:country":"US",
    "sg:address":"6955 Hillside Dr",
    "sg:city":"Bloomsburg",
    "sg:classifiers":[
        {
            "category":"Professional",
            "subcategory":"Management & Consulting",
            "type":"Services"
        },
        {
            "category":"Professional",
            "subcategory":"Advertising",
            "type":"Services"
        }
    ],
    "sg:phone":"+1 570 336 6787",
    "sg:postcode":"17815",
    "sg:province":"PA",
    "sg:tags":[
        "marketing",
        "program",
        "consultant"
    ],
    "wof:name":"Omalley Marketing",
    "wof:placetype":"venue"
},
  "geometry": {"coordinates":[-76.327916,41.038305],"type":"Point"}
}