{
  "type": "Feature",
  "properties": {
    "iso:country":"US",
    "sg:address":"565 Kelly Blvd",
    "sg:city":"Slippery Rock",
    "sg:classifiers":[
        {
            "category":"Professional",
            "subcategory":"Lawyer & Legal Services",
            "type":"Services"
        }
    ],
    "sg:phone":"+1   ",
    "sg:postcode":"16057",
    "sg:province":"PA",
    "wof:name":"Michael A McDonald MD",
    "wof:placetype":"venue"
},
  "geometry": {"coordinates":[-80.05249000000001,41.071698],"type":"Point"}
}