{
  "type": "Feature",
  "properties": {
    "iso:country":"US",
    "sg:address":"4051 Freemansburg Ave",
    "sg:city":"Easton",
    "sg:classifiers":[
        {
            "category":"Health Services",
            "subcategory":"Doctor",
            "type":"Services"
        }
    ],
    "sg:phone":"+1 610 559 7474",
    "sg:postcode":"18045",
    "sg:province":"PA",
    "sg:tags":[
        "physician",
        "surgeon"
    ],
    "wof:name":"Caring For Women",
    "wof:placetype":"venue"
},
  "geometry": {"coordinates":[-75.27486399999999,40.659572],"type":"Point"}
}