{
  "type": "Feature",
  "properties": {
    "iso:country":"US",
    "sg:address":"227 Hathaway St E",
    "sg:city":"Girard",
    "sg:classifiers":[
        {
            "category":"Manufacturing",
            "subcategory":"Tools & Machinery",
            "type":"Manufacturing & Wholesale Goods"
        }
    ],
    "sg:phone":"+1 814 774 2075",
    "sg:postcode":"16417",
    "sg:province":"PA",
    "sg:tags":[
        "machine",
        "shop"
    ],
    "wof:name":"PSS Co",
    "wof:placetype":"venue"
},
  "geometry": {"coordinates":[-80.318951,42.008564],"type":"Point"}
}