{
  "type": "Feature",
  "properties": {
    "iso:country":"US",
    "sg:address":"3016 Chartiers Ave",
    "sg:city":"Pittsburgh",
    "sg:classifiers":[
        {
            "category":"Building & Trades",
            "subcategory":"Construction",
            "type":"Services"
        }
    ],
    "sg:phone":"+1 412 331 0233",
    "sg:postcode":"15204",
    "sg:province":"PA",
    "sg:tags":[
        "woodworker"
    ],
    "wof:name":"Procabinet & Woodworking",
    "wof:placetype":"venue"
},
  "geometry": {"coordinates":[-80.05918,40.454289],"type":"Point"}
}