{
  "type": "Feature",
  "properties": {
    "iso:country":"US",
    "sg:address":"437 Mount Lebanon Blvd",
    "sg:city":"Pittsburgh",
    "sg:classifiers":[
        {
            "category":"Restaurant",
            "type":"Food & Drink"
        }
    ],
    "sg:phone":"+1 412 341 0330",
    "sg:postcode":"15234",
    "sg:province":"PA",
    "sg:website":"www.wendys.com",
    "wof:name":"Wendy's Old Fashioned Hamburgers",
    "wof:placetype":"venue"
},
  "geometry": {"coordinates":[-80.033203,40.369598],"type":"Point"}
}