{
  "type": "Feature",
  "properties": {
    "iso:country":"US",
    "sg:address":"27 W Main St",
    "sg:city":"Reynoldsville",
    "sg:classifiers":[
        {
            "category":"Bars & Pubs",
            "type":"Food & Drink"
        }
    ],
    "sg:phone":"+1   ",
    "sg:postcode":"15851",
    "sg:province":"PA",
    "sg:tags":[
        "drinking"
    ],
    "wof:name":"Take 5",
    "wof:placetype":"venue"
},
  "geometry": {"coordinates":[-78.892786,41.099693],"type":"Point"}
}