{
  "type": "Feature",
  "properties": {
    "iso:country":"US",
    "sg:address":"461 E Wyoming Ave",
    "sg:city":"Philadelphia",
    "sg:classifiers":[
        {
            "category":"Restaurant",
            "type":"Food & Drink"
        }
    ],
    "sg:phone":"+1 215 457 8370",
    "sg:postcode":"19120",
    "sg:province":"PA",
    "sg:website":"http://www.crownfriedchicken.com",
    "wof:name":"Crown Fried Chicken",
    "wof:placetype":"venue"
},
  "geometry": {"coordinates":[-75.116731,40.020615],"type":"Point"}
}