{
  "type": "Feature",
  "properties": {
    "iso:country":"US",
    "sg:address":"10 Sanders Cir",
    "sg:city":"Chambersburg",
    "sg:classifiers":[
        {
            "category":"Building & Trades",
            "subcategory":"Electrical",
            "type":"Services"
        },
        {
            "category":"Building & Trades",
            "subcategory":"Plumbing",
            "type":"Services"
        }
    ],
    "sg:phone":"+1 717 263 1469",
    "sg:postcode":"17202",
    "sg:province":"PA",
    "sg:tags":[
        "air",
        "conditioning",
        "contractor",
        "system",
        "electric"
    ],
    "wof:name":"C V Wenger Inc",
    "wof:placetype":"venue"
},
  "geometry": {"coordinates":[-80.243394,40.099516],"type":"Point"}
}