{
  "type": "Feature",
  "properties": {
    "iso:country":"US",
    "sg:address":"200 S Duke St",
    "sg:city":"York",
    "sg:classifiers":[
        {
            "category":"Professional",
            "type":"Services"
        }
    ],
    "sg:phone":"+1   ",
    "sg:postcode":"17403",
    "sg:province":"PA",
    "wof:name":"E J Carter",
    "wof:placetype":"venue"
},
  "geometry": {"coordinates":[-76.72401000000001,39.959581],"type":"Point"}
}