{
  "type": "Feature",
  "properties": {
    "iso:country":"US",
    "sg:address":"664 Lincoln Ave",
    "sg:city":"Pittsburgh",
    "sg:classifiers":[
        {
            "category":"Professional",
            "subcategory":"Computer Services",
            "type":"Services"
        }
    ],
    "sg:phone":"+1   ",
    "sg:postcode":"15202",
    "sg:province":"PA",
    "sg:tags":[
        "prepackaged",
        "software"
    ],
    "wof:name":"Astrolinx Systems Inc",
    "wof:placetype":"venue"
},
  "geometry": {"coordinates":[-80.059375,40.497527],"type":"Point"}
}