{
  "type": "Feature",
  "properties": {
    "iso:country":"US",
    "sg:address":"24 Main St E",
    "sg:city":"Girard",
    "sg:classifiers":[
        {
            "category":"Professional",
            "subcategory":"Lawyer & Legal Services",
            "type":"Services"
        }
    ],
    "sg:phone":"+1 814 774 2628",
    "sg:postcode":"16417",
    "sg:province":"PA",
    "sg:tags":[
        "attorney"
    ],
    "sg:website":"www.steadmanlaw.com",
    "wof:name":"Steadman Law Offices",
    "wof:placetype":"venue"
},
  "geometry": {"coordinates":[-80.316406,42.001265],"type":"Point"}
}