{
  "type": "Feature",
  "properties": {
    "iso:country":"US",
    "sg:address":"13773 State Rte 36",
    "sg:city":"Punxsutawney",
    "sg:classifiers":[
        {
            "category":"Recreation",
            "subcategory":"Marina",
            "type":"Entertainment"
        }
    ],
    "sg:phone":"+1   ",
    "sg:postcode":"15767",
    "sg:province":"PA",
    "sg:tags":[
        "operation"
    ],
    "wof:name":"All Seasons Boat Repair",
    "wof:placetype":"venue"
},
  "geometry": {"coordinates":[-78.874663,40.924468],"type":"Point"}
}