{
  "type": "Feature",
  "properties": {
    "iso:country":"US",
    "sg:address":"603 Dalton St",
    "sg:city":"Emmaus",
    "sg:classifiers":[
        {
            "category":"Communications",
            "subcategory":"Film & Video Production",
            "type":"Services"
        }
    ],
    "sg:phone":"+1   ",
    "sg:postcode":"18049",
    "sg:province":"PA",
    "sg:tags":[
        "motion"
    ],
    "wof:name":"Enliven Productions",
    "wof:placetype":"venue"
},
  "geometry": {"coordinates":[-75.48639300000001,40.551253],"type":"Point"}
}