{
  "type": "Feature",
  "properties": {
    "iso:country":"US",
    "sg:address":"2222 Webster Ave",
    "sg:city":"Pittsburgh",
    "sg:classifiers":[
        {
            "category":"Restaurant",
            "type":"Food & Drink"
        }
    ],
    "sg:phone":"+1 412 586 7602",
    "sg:postcode":"15219",
    "sg:province":"PA",
    "sg:tags":[
        "grill",
        "bar"
    ],
    "wof:name":"Hill City Grill",
    "wof:placetype":"venue"
},
  "geometry": {"coordinates":[-79.976921,40.44772],"type":"Point"}
}