{
  "type": "Feature",
  "properties": {
    "iso:country":"US",
    "sg:address":"1856 E 10th St",
    "sg:city":"Erie",
    "sg:classifiers":[
        {
            "category":"Freight",
            "type":"Transportation"
        }
    ],
    "sg:phone":"+1 814 452 0148",
    "sg:postcode":"16511",
    "sg:province":"PA",
    "sg:tags":[
        "warehouse"
    ],
    "wof:name":"Meridian Creative Group",
    "wof:placetype":"venue"
},
  "geometry": {"coordinates":[-80.04187,42.140455],"type":"Point"}
}