{
  "type": "Feature",
  "properties": {
    "iso:country":"US",
    "sg:address":"207 Carter Dr",
    "sg:city":"West Chester",
    "sg:classifiers":[
        {
            "category":"Building & Trades",
            "subcategory":"Construction",
            "type":"Services"
        }
    ],
    "sg:phone":"+1   ",
    "sg:postcode":"19382",
    "sg:province":"PA",
    "sg:tags":[
        "hanging",
        "contractor"
    ],
    "wof:name":"Ultraseal Inc",
    "wof:placetype":"venue"
},
  "geometry": {"coordinates":[-75.588528,39.950401],"type":"Point"}
}