{
  "type": "Feature",
  "properties": {
    "iso:country":"US",
    "sg:address":"514 E Penn Ave Ste Rear",
    "sg:city":"Cleona",
    "sg:classifiers":[
        {
            "category":"Autos & Motor Vehicles",
            "subcategory":"Automobile Sales",
            "type":"Retail Goods"
        }
    ],
    "sg:phone":"+1 717 272 3688",
    "sg:postcode":"17042",
    "sg:province":"PA",
    "sg:tags":[
        "dealers-used",
        "used",
        "cars-wholesale",
        "car"
    ],
    "wof:name":"Kevins Car Shop",
    "wof:placetype":"venue"
},
  "geometry": {"coordinates":[-76.465857,40.338842],"type":"Point"}
}