{
  "type": "Feature",
  "properties": {
    "iso:country":"US",
    "sg:address":"1508 Unity St",
    "sg:city":"Philadelphia",
    "sg:classifiers":[
        {
            "category":"Building & Trades",
            "subcategory":"Construction",
            "type":"Services"
        }
    ],
    "sg:phone":"+1 215 288 9600",
    "sg:postcode":"19124",
    "sg:province":"PA",
    "sg:tags":[
        "roofing",
        "contractor"
    ],
    "wof:name":"O'Leary Roofing",
    "wof:placetype":"venue"
},
  "geometry": {"coordinates":[-75.08859099999999,40.013051],"type":"Point"}
}