{
  "type": "Feature",
  "properties": {
    "iso:country":"US",
    "sg:address":"427 W Cheltenham Ave",
    "sg:city":"Elkins Park",
    "sg:classifiers":[
        {
            "category":"Professional",
            "subcategory":"Lawyer & Legal Services",
            "type":"Services"
        }
    ],
    "sg:phone":"+1   ",
    "sg:postcode":"19027",
    "sg:province":"PA",
    "wof:name":"Michael D Sayles",
    "wof:placetype":"venue"
},
  "geometry": {"coordinates":[-75.127027,40.055905],"type":"Point"}
}