{
  "type": "Feature",
  "properties": {
    "addr:full":"1503 Lansdowne Ave Ste 3001 Darby PA 19023",
    "addr:housenumber":"1503",
    "addr:postcode":"19023",
    "addr:street":"Lansdowne Ave Ste 3001",
    "iso:country":"US",
    "sg:address":"1503 Lansdowne Ave Ste 3001",
    "sg:city":"Darby",
    "sg:classifiers":[
        {
            "category":"Health Services",
            "subcategory":"Doctor",
            "type":"Services"
        }
    ],
    "sg:phone":"+1 610 586 4100",
    "sg:postcode":"19023",
    "sg:province":"PA",
    "sg:tags":[
        "physician",
        "surgery",
        "thoracic",
        "surgeons",
        "cardiovascular"
    ],
    "sg:website":"http://www.casep.com",
    "wof:name":"Kelly Cardiovascular Group",
    "wof:placetype":"venue"
},
  "geometry": {"coordinates":[-75.267527,39.925453],"type":"Point"}
}