{
  "type": "Feature",
  "properties": {
    "iso:country":"US",
    "sg:address":"142 N George St",
    "sg:city":"York",
    "sg:classifiers":[
        {
            "category":"Restaurant",
            "type":"Food & Drink"
        }
    ],
    "sg:phone":"+1 717 843 7672",
    "sg:postcode":"17401",
    "sg:province":"PA",
    "sg:tags":[
        "banquet",
        "rooms"
    ],
    "sg:website":"www.altlandhouse.com",
    "wof:name":"Valencia Ballroom",
    "wof:placetype":"venue"
},
  "geometry": {"coordinates":[-76.72838900000001,39.964498],"type":"Point"}
}