{
  "type": "Feature",
  "properties": {
    "addr:full":"8832 Rabbit Rd N Greencastle PA 17225",
    "addr:housenumber":"8832",
    "addr:postcode":"17225",
    "addr:street":"Rabbit Rd N Greencastle",
    "iso:country":"US",
    "sg:address":"8832 Rabbit Rd N",
    "sg:city":"Greencastle",
    "sg:classifiers":[
        {
            "category":"Wholesale",
            "subcategory":"Vending Machines",
            "type":"Manufacturing & Wholesale Goods"
        }
    ],
    "sg:phone":"+1 717 597 8945",
    "sg:postcode":"17225",
    "sg:province":"PA",
    "sg:tags":[
        "operator"
    ],
    "wof:name":"Wetzel's Snacks 'N More",
    "wof:placetype":"venue"
},
  "geometry": {"coordinates":[-77.787296,39.804277],"type":"Point"}
}