{
  "type": "Feature",
  "properties": {
    "iso:country":"US",
    "sg:address":"3423 8th Ave",
    "sg:city":"Beaver Falls",
    "sg:classifiers":[
        {
            "category":"Organizations",
            "subcategory":"Religious Organization",
            "type":"Services"
        }
    ],
    "sg:phone":"+1 724 846 7038",
    "sg:postcode":"15010",
    "sg:province":"PA",
    "sg:tags":[
        "clergy"
    ],
    "wof:name":"Edward A Schoeneck",
    "wof:placetype":"venue"
},
  "geometry": {"coordinates":[-80.328919,40.775547],"type":"Point"}
}