{
  "type": "Feature",
  "properties": {
    "iso:country":"US",
    "sg:address":"1161 Ridge Rd",
    "sg:city":"Pottstown",
    "sg:classifiers":[
        {
            "category":"Personal",
            "subcategory":"Beauty Salon",
            "type":"Services"
        }
    ],
    "sg:phone":"+1   ",
    "sg:postcode":"19465",
    "sg:province":"PA",
    "sg:tags":[
        "shop"
    ],
    "wof:name":"Floyds",
    "wof:placetype":"venue"
},
  "geometry": {"coordinates":[-75.666636,40.174761],"type":"Point"}
}