{
  "type": "Feature",
  "properties": {
    "iso:country":"US",
    "sg:address":"102 Carlton Rd",
    "sg:city":"Wallingford",
    "sg:classifiers":[
        {
            "category":"Organizations",
            "subcategory":"Political Organization",
            "type":"Services"
        }
    ],
    "sg:phone":"+1   ",
    "sg:postcode":"19086",
    "sg:province":"PA",
    "wof:name":"League of Women Voters of",
    "wof:placetype":"venue"
},
  "geometry": {"coordinates":[-75.37846500000001,39.905514],"type":"Point"}
}