{
  "type": "Feature",
  "properties": {
    "addr:full":"3936 Miller Rd Newtown Square PA 19073",
    "addr:housenumber":"3936",
    "addr:postcode":"19073",
    "addr:street":"Miller Rd",
    "iso:country":"US",
    "sg:address":"3936 Miller Rd",
    "sg:city":"Newtown Square",
    "sg:classifiers":[
        {
            "category":"Building & Trades",
            "subcategory":"Cleaning & Sanitation",
            "type":"Services"
        }
    ],
    "sg:phone":"+1 610 355 7666",
    "sg:postcode":"19073",
    "sg:province":"PA",
    "sg:tags":[
        "janitor"
    ],
    "wof:name":"Professional Building Svc Inc",
    "wof:placetype":"venue"
},
  "geometry": {"coordinates":[-75.453502,39.974974],"type":"Point"}
}