{
  "type": "Feature",
  "properties": {
    "iso:country":"US",
    "sg:address":"1309 Tarpan Cir",
    "sg:city":"New Hope",
    "sg:classifiers":[
        {
            "category":"Building & Trades",
            "subcategory":"Construction",
            "type":"Services"
        }
    ],
    "sg:phone":"+1   ",
    "sg:postcode":"18938",
    "sg:province":"PA",
    "sg:tags":[
        "hanging",
        "contractor"
    ],
    "wof:name":"Broad Brush",
    "wof:placetype":"venue"
},
  "geometry": {"coordinates":[-75.02656899999999,40.346938],"type":"Point"}
}