{
  "type": "Feature",
  "properties": {
    "iso:country":"US",
    "sg:address":"230 W Station Square Dr",
    "sg:city":"Pittsburgh",
    "sg:classifiers":[
        {
            "category":"Restaurant",
            "type":"Food & Drink"
        }
    ],
    "sg:phone":"+1 412 481 7625",
    "sg:postcode":"15219",
    "sg:province":"PA",
    "sg:website":"www.hardrock.com",
    "wof:name":"Hard Rock Cafe",
    "wof:placetype":"venue"
},
  "geometry": {"coordinates":[-80.01102899999999,40.436614],"type":"Point"}
}