{
  "type": "Feature",
  "properties": {
    "iso:country":"US",
    "sg:address":"20 S Main St",
    "sg:city":"New Hope",
    "sg:classifiers":[
        {
            "category":"Food & Beverages",
            "subcategory":"Bakery",
            "type":"Retail Goods"
        }
    ],
    "sg:phone":"+1   ",
    "sg:postcode":"18938",
    "sg:province":"PA",
    "wof:name":"CEst La Vie",
    "wof:placetype":"venue"
},
  "geometry": {"coordinates":[-74.951317,40.363982],"type":"Point"}
}