{
  "type": "Feature",
  "properties": {
    "iso:country":"US",
    "sg:address":"4310 N 3rd St",
    "sg:city":"Philadelphia",
    "sg:classifiers":[
        {
            "category":"Autos & Motor Vehicles",
            "subcategory":"Auto Supplies",
            "type":"Retail Goods"
        }
    ],
    "sg:phone":"+1 215 455 1077",
    "sg:postcode":"19140",
    "sg:province":"PA",
    "sg:tags":[
        "tire"
    ],
    "wof:name":"Bristol Auto Sport Inc",
    "wof:placetype":"venue"
},
  "geometry": {"coordinates":[-75.131941,40.016409],"type":"Point"}
}