{
  "type": "Feature",
  "properties": {
    "addr:full":"201 Spy Glass Hill Rd Bath PA 18014",
    "addr:housenumber":"201",
    "addr:postcode":"18014",
    "addr:street":"Spy Glass Hill Rd",
    "iso:country":"US",
    "sg:address":"201 Spy Glass Hill Rd",
    "sg:city":"Bath",
    "sg:classifiers":[
        {
            "category":"Building & Trades",
            "subcategory":"Construction",
            "type":"Services"
        }
    ],
    "sg:phone":"+1   ",
    "sg:postcode":"18014",
    "sg:province":"PA",
    "sg:tags":[
        "contractor"
    ],
    "wof:name":"Ldk Enterprises Inc",
    "wof:placetype":"venue"
},
  "geometry": {"coordinates":[-75.38957499999999,40.729715],"type":"Point"}
}