{
  "type": "Feature",
  "properties": {
    "iso:country":"US",
    "sg:address":"4145 William Penn Hwy",
    "sg:city":"Monroeville",
    "sg:classifiers":[
        {
            "category":"Health Services",
            "subcategory":"Dentist",
            "type":"Services"
        }
    ],
    "sg:phone":"+1 412 372 4800",
    "sg:postcode":"15146",
    "sg:province":"PA",
    "sg:tags":[
        "dentists-cosmetic",
        "denture",
        "dental",
        "clinic",
        "dentistry",
        "dentists-prosthodontists"
    ],
    "sg:website":"http://www.allcare.com",
    "wof:name":"Allcare Dental & Dentures",
    "wof:placetype":"venue"
},
  "geometry": {"coordinates":[-79.766837,40.43882],"type":"Point"}
}