{
  "type": "Feature",
  "properties": {
    "iso:country":"US",
    "sg:address":"325 Central Ave",
    "sg:city":"Malvern",
    "sg:classifiers":[
        {
            "category":"Professional",
            "subcategory":"Accounting & Tax Preparation",
            "type":"Services"
        }
    ],
    "sg:phone":"+1 610 296 2875",
    "sg:postcode":"19355",
    "sg:province":"PA",
    "sg:tags":[
        "billing"
    ],
    "wof:name":"Energy Management Systems",
    "wof:placetype":"venue"
},
  "geometry": {"coordinates":[-75.507739,40.039715],"type":"Point"}
}