{
  "type": "Feature",
  "properties": {
    "iso:country":"US",
    "sg:address":"8 N Queen St",
    "sg:city":"Lancaster",
    "sg:classifiers":[
        {
            "category":"Building & Trades",
            "subcategory":"Construction",
            "type":"Services"
        }
    ],
    "sg:phone":"+1   ",
    "sg:postcode":"17603",
    "sg:province":"PA",
    "sg:tags":[
        "house"
    ],
    "wof:name":"Ecklin Group The",
    "wof:placetype":"venue"
},
  "geometry": {"coordinates":[-76.30584899999999,40.038753],"type":"Point"}
}