{
  "type": "Feature",
  "properties": {
    "addr:full":"665 Main St Schwenksville PA 19473",
    "addr:housenumber":"665",
    "addr:postcode":"19473",
    "addr:street":"Main St",
    "iso:country":"US",
    "sg:address":"665 Main St",
    "sg:city":"Schwenksville",
    "sg:classifiers":[
        {
            "category":"Retail",
            "subcategory":"Auto Repair",
            "type":"Services"
        }
    ],
    "sg:phone":"+1 610 287 6295",
    "sg:postcode":"19473",
    "sg:province":"PA",
    "wof:name":"Weiss Automotive",
    "wof:placetype":"venue"
},
  "geometry": {"coordinates":[-75.463898,40.256802],"type":"Point"}
}