{
  "type": "Feature",
  "properties": {
    "addr:full":"449 E Grand Ave Tower City PA 17980",
    "addr:housenumber":"449",
    "addr:postcode":"17980",
    "addr:street":"E Grand Ave",
    "iso:country":"US",
    "sg:address":"449 E Grand Ave",
    "sg:city":"Tower City",
    "sg:classifiers":[
        {
            "category":"Organizations",
            "subcategory":"Religious Organization",
            "type":"Services"
        }
    ],
    "sg:phone":"+1 717 647 4700",
    "sg:postcode":"17980",
    "sg:province":"PA",
    "sg:tags":[
        "church"
    ],
    "wof:name":"St Paul's Lutheran Church",
    "wof:placetype":"venue"
},
  "geometry": {"coordinates":[-76.553228,40.589154],"type":"Point"}
}