{
  "type": "Feature",
  "properties": {
    "addr:full":"1341 S Atherton St State College PA 16801",
    "addr:housenumber":"1341",
    "addr:postcode":"16801",
    "addr:street":"S Atherton St",
    "iso:country":"US",
    "sg:address":"1341 S Atherton St",
    "sg:city":"State College",
    "sg:classifiers":[
        {
            "category":"Sports & Exercise",
            "subcategory":"Gym",
            "type":"Entertainment"
        }
    ],
    "sg:phone":"+1 814 231 1483",
    "sg:postcode":"16801",
    "sg:province":"PA",
    "sg:tags":[
        "club",
        "health",
        "studio",
        "gymnasium"
    ],
    "wof:name":"Z Bodies Personal Health",
    "wof:placetype":"venue"
},
  "geometry": {"coordinates":[-77.84325699999999,40.784548],"type":"Point"}
}