{
  "type": "Feature",
  "properties": {
    "iso:country":"US",
    "sg:address":"927 Pond St",
    "sg:city":"Bristol",
    "sg:classifiers":[
        {
            "category":"Personal",
            "subcategory":"Barber",
            "type":"Services"
        }
    ],
    "sg:phone":"+1 215 526 1688",
    "sg:postcode":"19007",
    "sg:province":"PA",
    "wof:name":"Al's Uppercuts",
    "wof:placetype":"venue"
},
  "geometry": {"coordinates":[-74.84988,40.102052],"type":"Point"}
}