{
  "type": "Feature",
  "properties": {
    "iso:country":"US",
    "sg:address":"3738 Kings Rd",
    "sg:city":"Pennsburg",
    "sg:classifiers":[
        {
            "category":"Retail",
            "subcategory":"Animal Services",
            "type":"Services"
        }
    ],
    "sg:phone":"+1 215 541 4820",
    "sg:postcode":"18073",
    "sg:province":"PA",
    "sg:tags":[
        "personal"
    ],
    "wof:name":"Precious Pet Sitting",
    "wof:placetype":"venue"
},
  "geometry": {"coordinates":[-75.516471,40.363096],"type":"Point"}
}