{
  "type": "Feature",
  "properties": {
    "addr:full":"62 N Juniper St Philadelphia PA 19107",
    "addr:housenumber":"62",
    "addr:postcode":"19107",
    "addr:street":"N Juniper St",
    "iso:country":"US",
    "sg:address":"62 N Juniper St",
    "sg:city":"Philadelphia",
    "sg:classifiers":[
        {
            "category":"Building & Trades",
            "subcategory":"Construction",
            "type":"Services"
        }
    ],
    "sg:phone":"+1 215 836 5150",
    "sg:postcode":"19107",
    "sg:province":"PA",
    "sg:tags":[
        "contractor"
    ],
    "sg:website":"www.caledoniankitchenbath.com",
    "wof:name":"Caledonian Kitchen & Bath LLC",
    "wof:placetype":"venue"
},
  "geometry": {"coordinates":[-75.16213500000001,39.953868],"type":"Point"}
}