{
  "type": "Feature",
  "properties": {
    "iso:country":"US",
    "sg:address":"108 Wood Ln",
    "sg:city":"Centre Hall",
    "sg:classifiers":[
        {
            "category":"Retail",
            "subcategory":"Repair Shop",
            "type":"Services"
        }
    ],
    "sg:phone":"+1 814 364 9585",
    "sg:postcode":"16836",
    "sg:province":"PA",
    "sg:tags":[
        "antique",
        "restoring"
    ],
    "wof:name":"Stan's Auto Body",
    "wof:placetype":"venue"
},
  "geometry": {"coordinates":[-78.25359,41.126407],"type":"Point"}
}