{
  "type": "Feature",
  "properties": {
    "addr:full":"216 Meade Aly Pittsburgh PA 15209",
    "addr:housenumber":"216",
    "addr:postcode":"15209",
    "addr:street":"Meade Aly",
    "iso:country":"US",
    "sg:address":"216 Meade Aly",
    "sg:city":"Pittsburgh",
    "sg:classifiers":[
        {
            "category":"Building & Trades",
            "subcategory":"Construction",
            "type":"Services"
        }
    ],
    "sg:phone":"+1 412 821 1350",
    "sg:postcode":"15209",
    "sg:province":"PA",
    "sg:tags":[
        "marble",
        "contractor"
    ],
    "wof:name":"J P Paracca Tile & Marble Co",
    "wof:placetype":"venue"
},
  "geometry": {"coordinates":[-79.970809,40.480363],"type":"Point"}
}