{
  "type": "Feature",
  "properties": {
    "iso:country":"US",
    "sg:address":"1216 State Rte 113",
    "sg:city":"Chester Springs",
    "sg:classifiers":[
        {
            "category":"Professional",
            "subcategory":"Accounting & Tax Preparation",
            "type":"Services"
        }
    ],
    "sg:phone":"+1 610 827 1995",
    "sg:postcode":"19425",
    "sg:province":"PA",
    "sg:tags":[
        "bookkeeping",
        "general"
    ],
    "wof:name":"Edgehill Enterprises Inc",
    "wof:placetype":"venue"
},
  "geometry": {"coordinates":[-75.619865,40.094454],"type":"Point"}
}