{
  "type": "Feature",
  "properties": {
    "addr:full":"3204 Pearl Ave Erie PA 16510",
    "addr:housenumber":"3204",
    "addr:postcode":"16510",
    "addr:street":"Pearl Ave",
    "iso:country":"US",
    "sg:address":"3204 Pearl Ave",
    "sg:city":"Erie",
    "sg:classifiers":[
        {
            "category":"Retail",
            "subcategory":"Repair Shop",
            "type":"Services"
        }
    ],
    "sg:phone":"+1   ",
    "sg:postcode":"16510",
    "sg:province":"PA",
    "sg:tags":[
        "metalwork",
        "welding",
        "architectural",
        "mfg"
    ],
    "wof:name":"Noyers Welding Service",
    "wof:placetype":"venue"
},
  "geometry": {"coordinates":[-80.015271,42.143139],"type":"Point"}
}