{
  "type": "Feature",
  "properties": {
    "iso:country":"US",
    "sg:address":"8 Hayes Rd",
    "sg:city":"Malvern",
    "sg:classifiers":[
        {
            "category":"Professional",
            "subcategory":"Accounting & Tax Preparation",
            "type":"Services"
        }
    ],
    "sg:phone":"+1 610 889 2444",
    "sg:postcode":"19355",
    "sg:province":"PA",
    "sg:tags":[
        "accountant"
    ],
    "wof:name":"Kurt A Popp CPA",
    "wof:placetype":"venue"
},
  "geometry": {"coordinates":[-75.562332,40.063745],"type":"Point"}
}