{
  "type": "Feature",
  "properties": {
    "iso:country":"US",
    "sg:address":"1619 Interchange Rd",
    "sg:city":"Lehighton",
    "sg:classifiers":[
        {
            "category":"Travel",
            "subcategory":"Hotels & Motels",
            "type":"Entertainment"
        }
    ],
    "sg:phone":"+1 610 379 5066",
    "sg:postcode":"18235",
    "sg:province":"PA",
    "sg:tags":[
        "lodging"
    ],
    "sg:website":"http://www.countryinns.com/lehightonpa",
    "wof:name":"Country Inn & Suites By Carlson, Lehighton",
    "wof:placetype":"venue"
},
  "geometry": {"coordinates":[-75.673576,40.83858],"type":"Point"}
}