{
  "type": "Feature",
  "properties": {
    "iso:country":"US",
    "sg:address":"5742 Smith Dr",
    "sg:city":"Bethel Park",
    "sg:classifiers":[
        {
            "category":"Professional",
            "type":"Services"
        }
    ],
    "sg:phone":"+1   ",
    "sg:postcode":"15102",
    "sg:province":"PA",
    "wof:name":"Rbs Sports",
    "wof:placetype":"venue"
},
  "geometry": {"coordinates":[-80.030327,40.311951],"type":"Point"}
}