{
  "type": "Feature",
  "properties": {
    "addr:full":"2000 Chestnut St Philadelphia PA 19103",
    "addr:housenumber":"2000",
    "addr:postcode":"19103",
    "addr:street":"Chestnut St",
    "iso:country":"US",
    "sg:address":"2000 Chestnut St",
    "sg:city":"Philadelphia",
    "sg:classifiers":[
        {
            "category":"Food & Beverages",
            "subcategory":"Specialty",
            "type":"Retail Goods"
        },
        {
            "category":"Food & Beverages",
            "subcategory":"Groceries & Convenience Stores",
            "type":"Retail Goods"
        }
    ],
    "sg:phone":"+1 215 568 2468",
    "sg:postcode":"19103",
    "sg:province":"PA",
    "sg:tags":[
        "grocers-specialty"
    ],
    "wof:name":"Old Nelson Food Market",
    "wof:placetype":"venue"
},
  "geometry": {"coordinates":[-75.17346999999999,39.952061],"type":"Point"}
}