{
  "type": "Feature",
  "properties": {
    "addr:full":"920 Linda Ln Camp Hill PA 17011",
    "addr:housenumber":"920",
    "addr:postcode":"17011",
    "addr:street":"Linda Ln",
    "iso:country":"US",
    "sg:address":"920 Linda Ln",
    "sg:city":"Camp Hill",
    "sg:classifiers":[
        {
            "category":"Arts & Performance",
            "subcategory":"Arts Center",
            "type":"Entertainment"
        }
    ],
    "sg:phone":"+1 717 761 3301",
    "sg:postcode":"17011",
    "sg:province":"PA",
    "sg:tags":[
        "performing"
    ],
    "sg:website":"www.wevodaudancecenter.com",
    "wof:name":"Wevodau Dance Center",
    "wof:placetype":"venue"
},
  "geometry": {"coordinates":[-76.93380000000001,40.228401],"type":"Point"}
}