{
  "type": "Feature",
  "properties": {
    "iso:country":"US",
    "sg:address":"504 Ave C",
    "sg:city":"Feasterville Trevose",
    "sg:classifiers":[
        {
            "category":"Building & Trades",
            "subcategory":"Electrical",
            "type":"Services"
        }
    ],
    "sg:phone":"+1   ",
    "sg:postcode":"19053",
    "sg:province":"PA",
    "sg:tags":[
        "electrical",
        "contractor"
    ],
    "wof:name":"Riccardi John",
    "wof:placetype":"venue"
},
  "geometry": {"coordinates":[-74.981971,40.148519],"type":"Point"}
}