{
  "type": "Feature",
  "properties": {
    "addr:full":"1553 W Sunbury Rd West Sunbury PA 16061",
    "addr:housenumber":"1553",
    "addr:postcode":"16061",
    "addr:street":"W Sunbury Rd",
    "iso:country":"US",
    "sg:address":"1553 W Sunbury Rd",
    "sg:city":"West Sunbury",
    "sg:classifiers":[
        {
            "category":"Education",
            "subcategory":"Library",
            "type":"Public Place"
        }
    ],
    "sg:phone":"+1   ",
    "sg:postcode":"16061",
    "sg:province":"PA",
    "wof:name":"Butler Cnty Federated Lib Sys",
    "wof:placetype":"venue"
},
  "geometry": {"coordinates":[-79.90714800000001,41.034814],"type":"Point"}
}