{
  "type": "Feature",
  "properties": {
    "iso:country":"US",
    "sg:address":"1410 Ravena St",
    "sg:city":"Bethlehem",
    "sg:classifiers":[
        {
            "category":"Professional",
            "subcategory":"Business Services",
            "type":"Services"
        }
    ],
    "sg:phone":"+1 610 691 1575",
    "sg:postcode":"18015",
    "sg:province":"PA",
    "sg:tags":[
        "auctioneer"
    ],
    "wof:name":"Walter F Bukowski",
    "wof:placetype":"venue"
},
  "geometry": {"coordinates":[-75.34545300000001,40.593764],"type":"Point"}
}