{
  "type": "Feature",
  "properties": {
    "iso:country":"US",
    "sg:address":"305 S 3rd St",
    "sg:city":"Philadelphia",
    "sg:classifiers":[
        {
            "category":"Wholesale",
            "subcategory":"Dairy",
            "type":"Manufacturing & Wholesale Goods"
        }
    ],
    "sg:phone":"+1   ",
    "sg:postcode":"19106",
    "sg:province":"PA",
    "sg:tags":[
        "wholesaler",
        "milk",
        "chocolate"
    ],
    "wof:name":"Cocio Chocolate Milk",
    "wof:placetype":"venue"
},
  "geometry": {"coordinates":[-75.146877,39.944411],"type":"Point"}
}