{
  "type": "Feature",
  "properties": {
    "addr:full":"8040 Roosevelt Blvd Philadelphia PA 19152",
    "addr:housenumber":"8040",
    "addr:postcode":"19152",
    "addr:street":"Roosevelt Blvd",
    "iso:country":"US",
    "sg:address":"8040 Roosevelt Blvd",
    "sg:city":"Philadelphia",
    "sg:classifiers":[
        {
            "category":"Travel",
            "subcategory":"Travel Agent",
            "type":"Entertainment"
        }
    ],
    "sg:phone":"+1 215 338 6000",
    "sg:postcode":"19152",
    "sg:province":"PA",
    "sg:tags":[
        "agency"
    ],
    "wof:name":"Aldo Travel Agency",
    "wof:placetype":"venue"
},
  "geometry": {"coordinates":[-75.04627600000001,40.057541],"type":"Point"}
}