{
  "type": "Feature",
  "properties": {
    "iso:country":"US",
    "sg:address":"230 N 7th St",
    "sg:city":"Lewisburg",
    "sg:classifiers":[
        {
            "category":"Retail",
            "subcategory":"Self-service Laundry",
            "type":"Services"
        },
        {
            "category":"Retail",
            "subcategory":"Laundry & Dry Cleaning",
            "type":"Services"
        }
    ],
    "sg:phone":"+1 570 524 9650",
    "sg:postcode":"17837",
    "sg:province":"PA",
    "sg:tags":[
        "cleaners",
        "coin"
    ],
    "wof:name":"Steininger's Laundry & Dry",
    "wof:placetype":"venue"
},
  "geometry": {"coordinates":[-76.892335,40.96502],"type":"Point"}
}