{
  "type": "Feature",
  "properties": {
    "iso:country":"US",
    "sg:address":"1176 No 1 Rd",
    "sg:city":"Cairnbrook",
    "sg:classifiers":[
        {
            "category":"Building & Trades",
            "subcategory":"Landfill",
            "type":"Services"
        }
    ],
    "sg:phone":"+1 814 754 4587",
    "sg:postcode":"15924",
    "sg:province":"PA",
    "sg:website":"http://www.wm.com",
    "wof:name":"Shade Landfill Inc",
    "wof:placetype":"venue"
},
  "geometry": {"coordinates":[-78.801835,40.120234],"type":"Point"}
}