{
  "type": "Feature",
  "properties": {
    "iso:country":"US",
    "sg:address":"15 E Lancaster Ave",
    "sg:city":"Ardmore",
    "sg:classifiers":[
        {
            "category":"Shopping",
            "subcategory":"Jewelry",
            "type":"Retail Goods"
        }
    ],
    "sg:phone":"+1 610 642 6388",
    "sg:postcode":"19003",
    "sg:province":"PA",
    "sg:tags":[
        "cards",
        "greeting",
        "gift"
    ],
    "wof:name":"Giannini Jewelers Inc",
    "wof:placetype":"venue"
},
  "geometry": {"coordinates":[-75.289227,40.007077],"type":"Point"}
}