{
  "type": "Feature",
  "properties": {
    "iso:country":"US",
    "sg:address":"126 Red Fox Dr",
    "sg:city":"Duncansville",
    "sg:classifiers":[
        {
            "category":"Health Services",
            "subcategory":"Doctor",
            "type":"Services"
        }
    ],
    "sg:phone":"+1   ",
    "sg:postcode":"16635",
    "sg:province":"PA",
    "sg:tags":[
        "medical"
    ],
    "wof:name":"Todd A Sponsler MD PC",
    "wof:placetype":"venue"
},
  "geometry": {"coordinates":[-78.40548800000001,40.445957],"type":"Point"}
}