{
  "type": "Feature",
  "properties": {
    "iso:country":"US",
    "sg:address":"1999 Sproul Rd",
    "sg:city":"Broomall",
    "sg:classifiers":[
        {
            "category":"Health Services",
            "subcategory":"Health Practitioner",
            "type":"Services"
        }
    ],
    "sg:phone":"+1 610 359 1134",
    "sg:postcode":"19008",
    "sg:province":"PA",
    "sg:tags":[
        "therapist",
        "physical"
    ],
    "wof:name":"Broomall Rehabilitation Svc",
    "wof:placetype":"venue"
},
  "geometry": {"coordinates":[-75.35627100000001,39.960875],"type":"Point"}
}