{
  "type": "Feature",
  "properties": {
    "addr:full":"1425 W 36th St Erie PA 16508",
    "addr:housenumber":"1425",
    "addr:postcode":"16508",
    "addr:street":"W 36Th St",
    "iso:country":"US",
    "sg:address":"1425 W 36th St",
    "sg:city":"Erie",
    "sg:classifiers":[
        {
            "category":"Organizations",
            "subcategory":"Community Association",
            "type":"Services"
        }
    ],
    "sg:phone":"+1 814 864 2451",
    "sg:postcode":"16508",
    "sg:province":"PA",
    "wof:name":"Sommerlllyst Club",
    "wof:placetype":"venue"
},
  "geometry": {"coordinates":[-80.097131,42.093137],"type":"Point"}
}