{
  "type": "Feature",
  "properties": {
    "addr:full":"45 Buck Rd Huntingdon Vly PA 19006",
    "addr:housenumber":"45",
    "addr:postcode":"19006",
    "addr:street":"Buck Rd",
    "iso:country":"US",
    "sg:address":"45 Buck Rd",
    "sg:city":"Huntingdon Vly",
    "sg:classifiers":[
        {
            "category":"Professional",
            "type":"Services"
        }
    ],
    "sg:phone":"+1 215 322 7088",
    "sg:postcode":"19006",
    "sg:province":"PA",
    "sg:tags":[
        "establishment"
    ],
    "wof:name":"Us Federation-Enforcement",
    "wof:placetype":"venue"
},
  "geometry": {"coordinates":[-75.029062,40.146533],"type":"Point"}
}