{
  "type": "Feature",
  "properties": {
    "iso:country":"US",
    "sg:address":"525 Jamestown St",
    "sg:city":"Philadelphia",
    "sg:classifiers":[
        {
            "category":"Health Services",
            "subcategory":"Doctor",
            "type":"Services"
        }
    ],
    "sg:phone":"+1   ",
    "sg:postcode":"19128",
    "sg:province":"PA",
    "sg:tags":[
        "medical"
    ],
    "wof:name":"Alberto J Larrieu MD",
    "wof:placetype":"venue"
},
  "geometry": {"coordinates":[-75.208765,40.02834],"type":"Point"}
}