{
  "type": "Feature",
  "properties": {
    "addr:full":"649 Ridgefield Ave Pittsburgh PA 15216",
    "addr:housenumber":"649",
    "addr:postcode":"15216",
    "addr:street":"Ridgefield Ave",
    "iso:country":"US",
    "sg:address":"649 Ridgefield Ave",
    "sg:city":"Pittsburgh",
    "sg:classifiers":[
        {
            "category":"Health Services",
            "subcategory":"Doctor",
            "type":"Services"
        }
    ],
    "sg:phone":"+1   ",
    "sg:postcode":"15216",
    "sg:province":"PA",
    "sg:tags":[
        "medical"
    ],
    "wof:name":"Ronald L Hrebinko Jr MD",
    "wof:placetype":"venue"
},
  "geometry": {"coordinates":[-80.050096,40.397823],"type":"Point"}
}