{
  "type": "Feature",
  "properties": {
    "addr:full":"1225 Barlow Two Taverns Rd Gettysburg PA 17325",
    "addr:housenumber":"1225",
    "addr:postcode":"17325",
    "addr:street":"Barlow Two Taverns Rd",
    "iso:country":"US",
    "sg:address":"1225 Barlow Two Taverns Rd",
    "sg:city":"Gettysburg",
    "sg:classifiers":[
        {
            "category":"Restaurant",
            "type":"Food & Drink"
        }
    ],
    "sg:phone":"+1 717 359 9897",
    "sg:postcode":"17325",
    "sg:province":"PA",
    "wof:name":"Cedar Ridge Restaurant",
    "wof:placetype":"venue"
},
  "geometry": {"coordinates":[-77.18834200000001,39.767039],"type":"Point"}
}