{
  "type": "Feature",
  "properties": {
    "iso:country":"US",
    "sg:address":"3263 Faronia St",
    "sg:city":"Pittsburgh",
    "sg:classifiers":[
        {
            "category":"Professional",
            "subcategory":"Secretarial Services",
            "type":"Services"
        }
    ],
    "sg:phone":"+1 412 928 0241",
    "sg:postcode":"15204",
    "sg:province":"PA",
    "sg:tags":[
        "processing",
        "word"
    ],
    "wof:name":"Administrative Assistance Plus",
    "wof:placetype":"venue"
},
  "geometry": {"coordinates":[-80.068507,40.451995],"type":"Point"}
}