{
  "type": "Feature",
  "properties": {
    "addr:full":"4839 E Street Rd Feasterville Trevose PA 19053",
    "addr:housenumber":"4839",
    "addr:postcode":"19053",
    "addr:street":"E Street Rd",
    "iso:country":"US",
    "sg:address":"4839 E Street Rd",
    "sg:city":"Feasterville Trevose",
    "sg:classifiers":[
        {
            "category":"Manufacturing",
            "subcategory":"Signs",
            "type":"Manufacturing & Wholesale Goods"
        },
        {
            "category":"Manufacturing",
            "subcategory":"Apparel",
            "type":"Manufacturing & Wholesale Goods"
        }
    ],
    "sg:phone":"+1 215 364 9061",
    "sg:postcode":"19053",
    "sg:province":"PA",
    "sg:tags":[
        "flag",
        "banner",
        "specialty",
        "merchandise",
        "mfg"
    ],
    "wof:name":"Banners and Signs Express",
    "wof:placetype":"venue"
},
  "geometry": {"coordinates":[-74.98290799999999,40.136653],"type":"Point"}
}