{
  "type": "Feature",
  "properties": {
    "iso:country":"US",
    "sg:address":"1 Hurley St",
    "sg:city":"Wilkes Barre",
    "sg:classifiers":[
        {
            "category":"Communications",
            "subcategory":"Television Station",
            "type":"Services"
        }
    ],
    "sg:phone":"+1   ",
    "sg:postcode":"18705",
    "sg:province":"PA",
    "wof:name":"M & M Broadcasting",
    "wof:placetype":"venue"
},
  "geometry": {"coordinates":[-75.83128499999999,41.268239],"type":"Point"}
}