{
  "type": "Feature",
  "properties": {
    "iso:country":"US",
    "sg:address":"3415 Simpson Ferry Rd",
    "sg:city":"Camp Hill",
    "sg:classifiers":[
        {
            "category":"Shopping",
            "subcategory":"Crafts & Fabrics",
            "type":"Retail Goods"
        }
    ],
    "sg:phone":"+1 717 975 0102",
    "sg:postcode":"17011",
    "sg:province":"PA",
    "sg:tags":[
        "art",
        "supply"
    ],
    "sg:website":"www.michaels.com",
    "wof:name":"Michael's Arts & Crafts",
    "wof:placetype":"venue"
},
  "geometry": {"coordinates":[-76.936798,40.226501],"type":"Point"}
}