{
  "type": "Feature",
  "properties": {
    "addr:full":"400 Leverington Ave Philadelphia PA 19128",
    "addr:housenumber":"400",
    "addr:postcode":"19128",
    "addr:street":"Leverington Ave",
    "iso:country":"US",
    "sg:address":"400 Leverington Ave",
    "sg:city":"Philadelphia",
    "sg:classifiers":[
        {
            "category":"Autos & Motor Vehicles",
            "subcategory":"Automobile Sales",
            "type":"Retail Goods"
        }
    ],
    "sg:phone":"+1 215 900 9981",
    "sg:postcode":"19128",
    "sg:province":"PA",
    "sg:tags":[
        "new",
        "car"
    ],
    "wof:name":"Diamond Auto Sales",
    "wof:placetype":"venue"
},
  "geometry": {"coordinates":[-75.220879,40.033871],"type":"Point"}
}