{
  "type": "Feature",
  "properties": {
    "iso:country":"US",
    "sg:address":"417 Elm Ave",
    "sg:city":"North Wales",
    "sg:classifiers":[
        {
            "category":"Home & Garden",
            "subcategory":"Garden Supply",
            "type":"Retail Goods"
        }
    ],
    "sg:phone":"+1 215 699 9586",
    "sg:postcode":"19454",
    "sg:province":"PA",
    "sg:tags":[
        "lawn",
        "mower"
    ],
    "wof:name":"Kellner's Lawn & Leisure",
    "wof:placetype":"venue"
},
  "geometry": {"coordinates":[-75.283389,40.207146],"type":"Point"}
}