{
  "type": "Feature",
  "properties": {
    "iso:country":"US",
    "sg:address":"41 Charleston St",
    "sg:city":"Wellsboro",
    "sg:classifiers":[
        {
            "category":"Home & Garden",
            "subcategory":"Building Materials",
            "type":"Retail Goods"
        }
    ],
    "sg:phone":"+1 570 724 2210",
    "sg:postcode":"16901",
    "sg:province":"PA",
    "sg:website":"www.pattersonhomecenter.com",
    "wof:name":"Patterson's Home Ctr",
    "wof:placetype":"venue"
},
  "geometry": {"coordinates":[-77.29146900000001,41.750247],"type":"Point"}
}