{
  "type": "Feature",
  "properties": {
    "iso:country":"US",
    "sg:address":"5298 Mallard Dr",
    "sg:city":"Bensalem",
    "sg:classifiers":[
        {
            "category":"Home & Garden",
            "subcategory":"Building Materials",
            "type":"Retail Goods"
        },
        {
            "category":"Building & Trades",
            "subcategory":"Construction",
            "type":"Services"
        }
    ],
    "sg:phone":"+1 215 245 7360",
    "sg:postcode":"19020",
    "sg:province":"PA",
    "sg:tags":[
        "concrete",
        "staining",
        "contractor"
    ],
    "wof:name":"Concepts In Concrete Inc",
    "wof:placetype":"venue"
},
  "geometry": {"coordinates":[-74.91583300000001,40.114311],"type":"Point"}
}