{
  "type": "Feature",
  "properties": {
    "addr:full":"1400 Locust St Pittsburgh PA 15219",
    "addr:housenumber":"1400",
    "addr:postcode":"15219",
    "addr:street":"Locust St",
    "iso:country":"US",
    "sg:address":"1400 Locust St",
    "sg:city":"Pittsburgh",
    "sg:classifiers":[
        {
            "category":"Health Services",
            "subcategory":"Doctor",
            "type":"Services"
        }
    ],
    "sg:phone":"+1   ",
    "sg:postcode":"15219",
    "sg:province":"PA",
    "sg:tags":[
        "medical"
    ],
    "wof:name":"John M Stramat MD",
    "wof:placetype":"venue"
},
  "geometry": {"coordinates":[-79.98519899999999,40.43683],"type":"Point"}
}