{
  "type": "Feature",
  "properties": {
    "iso:country":"US",
    "sg:address":"120 N Abington Rd",
    "sg:city":"Clarks Green",
    "sg:classifiers":[
        {
            "category":"Home & Garden",
            "subcategory":"Furniture",
            "type":"Retail Goods"
        }
    ],
    "sg:phone":"+1 570 586 7307",
    "sg:postcode":"18411",
    "sg:province":"PA",
    "sg:tags":[
        "mattress"
    ],
    "wof:name":"S & N Corp",
    "wof:placetype":"venue"
},
  "geometry": {"coordinates":[-75.696299,41.499776],"type":"Point"}
}