{
  "type": "Feature",
  "properties": {
    "addr:full":"3901 Conshohocken Ave Philadelphia PA 19131",
    "addr:housenumber":"3901",
    "addr:postcode":"19131",
    "addr:street":"Conshohocken Ave",
    "iso:country":"US",
    "sg:address":"3901 Conshohocken Ave",
    "sg:city":"Philadelphia",
    "sg:classifiers":[
        {
            "category":"Shopping",
            "subcategory":"Pharmacy",
            "type":"Retail Goods"
        }
    ],
    "sg:phone":"+1 215 879 2520",
    "sg:postcode":"19131",
    "sg:province":"PA",
    "sg:tags":[
        "drugstore"
    ],
    "wof:name":"West Village Pharmacy Inc",
    "wof:placetype":"venue"
},
  "geometry": {"coordinates":[-75.207703,40.002701],"type":"Point"}
}