{
  "type": "Feature",
  "properties": {
    "iso:country":"US",
    "sg:address":"108 N Hanover St",
    "sg:city":"Carlisle",
    "sg:classifiers":[
        {
            "category":"Retail",
            "subcategory":"Portrait Studio",
            "type":"Services"
        },
        {
            "category":"Professional",
            "subcategory":"Art Services",
            "type":"Services"
        }
    ],
    "sg:phone":"+1 717 243 5406",
    "sg:postcode":"17013",
    "sg:province":"PA",
    "sg:tags":[
        "photo",
        "photography",
        "commercial",
        "photographer"
    ],
    "wof:name":"Strine's Photography",
    "wof:placetype":"venue"
},
  "geometry": {"coordinates":[-77.188872,40.20359],"type":"Point"}
}