{
  "type": "Feature",
  "properties": {
    "iso:country":"US",
    "sg:address":"647 Main St Ste 310",
    "sg:city":"Johnstown",
    "sg:classifiers":[
        {
            "category":"Social Services",
            "type":"Services"
        },
        {
            "category":"Organizations",
            "subcategory":"Community Association",
            "type":"Services"
        }
    ],
    "sg:phone":"+1 814 255 1550",
    "sg:postcode":"15901",
    "sg:province":"PA",
    "sg:website":"http://www.midmichiganredcross.org",
    "wof:name":"American Red Cross Keystone Chapter",
    "wof:placetype":"venue"
},
  "geometry": {"coordinates":[-78.914612,40.323761],"type":"Point"}
}