{
  "type": "Feature",
  "properties": {
    "addr:full":"309 Main Ave Hawley PA 18428",
    "addr:housenumber":"309",
    "addr:postcode":"18428",
    "addr:street":"Main Ave",
    "iso:country":"US",
    "sg:address":"309 Main Ave",
    "sg:city":"Hawley",
    "sg:classifiers":[
        {
            "category":"Shopping",
            "subcategory":"Clothing, Apparel, & Fashions",
            "type":"Retail Goods"
        }
    ],
    "sg:phone":"+1   ",
    "sg:postcode":"18428",
    "sg:province":"PA",
    "wof:name":"O P Birdsong",
    "wof:placetype":"venue"
},
  "geometry": {"coordinates":[-75.183173,41.476221],"type":"Point"}
}