{
  "type": "Feature",
  "properties": {
    "addr:full":"1878 Holly Pike Carlisle PA 17013",
    "addr:housenumber":"1878",
    "addr:postcode":"17013",
    "addr:street":"Holly Pike",
    "iso:country":"US",
    "sg:address":"1878 Holly Pike",
    "sg:city":"Carlisle",
    "sg:classifiers":[
        {
            "category":"Farming",
            "subcategory":"Dairy Farm",
            "type":"Manufacturing & Wholesale Goods"
        }
    ],
    "sg:phone":"+1   ",
    "sg:postcode":"17013",
    "sg:province":"PA",
    "wof:name":"Glenn Flohr",
    "wof:placetype":"venue"
},
  "geometry": {"coordinates":[-77.19199999999999,40.181605],"type":"Point"}
}