{
  "type": "Feature",
  "properties": {
    "addr:full":"110 Seltzer Ave Coatesville PA 19320",
    "addr:housenumber":"110",
    "addr:postcode":"19320",
    "addr:street":"Seltzer Ave",
    "iso:country":"US",
    "sg:address":"110 Seltzer Ave",
    "sg:city":"Coatesville",
    "sg:classifiers":[
        {
            "category":"Retail",
            "subcategory":"Auto Repair",
            "type":"Services"
        }
    ],
    "sg:phone":"+1   ",
    "sg:postcode":"19320",
    "sg:province":"PA",
    "sg:tags":[
        "body"
    ],
    "wof:name":"Collex Collision Center",
    "wof:placetype":"venue"
},
  "geometry": {"coordinates":[-75.78033000000001,39.991036],"type":"Point"}
}