{
  "type": "Feature",
  "properties": {
    "iso:country":"US",
    "sg:address":"3446 Englewood St",
    "sg:city":"Philadelphia",
    "sg:classifiers":[
        {
            "category":"Building & Trades",
            "subcategory":"Construction",
            "type":"Services"
        }
    ],
    "sg:phone":"+1 215 338 6834",
    "sg:postcode":"19149",
    "sg:province":"PA",
    "sg:tags":[
        "contractor"
    ],
    "wof:name":"Eastern Roofing Co",
    "wof:placetype":"venue"
},
  "geometry": {"coordinates":[-75.043831,40.037548],"type":"Point"}
}