{
  "type": "Feature",
  "properties": {
    "iso:country":"US",
    "sg:address":"2654 Crestline Dr",
    "sg:city":"Hellertown",
    "sg:classifiers":[
        {
            "category":"Building & Trades",
            "subcategory":"Construction",
            "type":"Services"
        }
    ],
    "sg:phone":"+1   ",
    "sg:postcode":"18055",
    "sg:province":"PA",
    "sg:tags":[
        "excavation",
        "contractor"
    ],
    "wof:name":"Eagle Excavating Co",
    "wof:placetype":"venue"
},
  "geometry": {"coordinates":[-75.27948499999999,40.587082],"type":"Point"}
}