{
  "type": "Feature",
  "properties": {
    "iso:country":"US",
    "sg:address":"52 W Valley Ave",
    "sg:city":"Elysburg",
    "sg:classifiers":[
        {
            "category":"Food & Beverages",
            "subcategory":"Groceries & Convenience Stores",
            "type":"Retail Goods"
        }
    ],
    "sg:phone":"+1   ",
    "sg:postcode":"17824",
    "sg:province":"PA",
    "wof:name":"Radzievich Markets Inc",
    "wof:placetype":"venue"
},
  "geometry": {"coordinates":[-76.557695,40.85728],"type":"Point"}
}