{
  "type": "Feature",
  "properties": {
    "addr:full":"5880 Ellsworth Ave Pittsburgh PA 15232",
    "addr:housenumber":"5880",
    "addr:postcode":"15232",
    "addr:street":"Ellsworth Ave",
    "iso:country":"US",
    "sg:address":"5880 Ellsworth Ave",
    "sg:city":"Pittsburgh",
    "sg:classifiers":[
        {
            "category":"Shopping",
            "type":"Retail Goods"
        }
    ],
    "sg:phone":"+1 412 362 7200",
    "sg:postcode":"15232",
    "sg:province":"PA",
    "sg:tags":[
        "art",
        "gallery",
        "dealer"
    ],
    "wof:name":"Bella Arte Gallery",
    "wof:placetype":"venue"
},
  "geometry": {"coordinates":[-79.928568,40.457499],"type":"Point"}
}