{
  "type": "Feature",
  "properties": {
    "addr:full":"5820 City Ave Philadelphia PA 19131",
    "addr:housenumber":"5820",
    "addr:postcode":"19131",
    "addr:street":"City Ave",
    "iso:country":"US",
    "sg:address":"5820 City Ave",
    "sg:city":"Philadelphia",
    "sg:classifiers":[
        {
            "category":"Education",
            "subcategory":"Special Training",
            "type":"Public Place"
        }
    ],
    "sg:phone":"+1   ",
    "sg:postcode":"19131",
    "sg:province":"PA",
    "sg:tags":[
        "religious",
        "retreat"
    ],
    "wof:name":"Sisters of The Vsttn of Phldlp",
    "wof:placetype":"venue"
},
  "geometry": {"coordinates":[-75.24537599999999,39.992309],"type":"Point"}
}