{
  "type": "Feature",
  "properties": {
    "iso:country":"US",
    "sg:address":"4136 Blanche Rd",
    "sg:city":"Bensalem",
    "sg:classifiers":[
        {
            "category":"Shopping",
            "subcategory":"Used Merchandise",
            "type":"Retail Goods"
        }
    ],
    "sg:phone":"+1 215 639 6930",
    "sg:postcode":"19020",
    "sg:province":"PA",
    "sg:tags":[
        "clothing",
        "toy",
        "appliance",
        "furniture"
    ],
    "wof:name":"Village Thrift Stores Inc",
    "wof:placetype":"venue"
},
  "geometry": {"coordinates":[-74.92859199999999,40.103416],"type":"Point"}
}