{
  "type": "Feature",
  "properties": {
    "iso:country":"US",
    "sg:address":"11 W King St",
    "sg:city":"Lancaster",
    "sg:classifiers":[
        {
            "category":"Shopping",
            "type":"Retail Goods"
        }
    ],
    "sg:phone":"+1 717 392 5345",
    "sg:postcode":"17603",
    "sg:province":"PA",
    "sg:tags":[
        "art",
        "gallery",
        "dealer"
    ],
    "wof:name":"Strawberry & Co",
    "wof:placetype":"venue"
},
  "geometry": {"coordinates":[-76.30578800000001,40.037936],"type":"Point"}
}