{
  "type": "Feature",
  "properties": {
    "iso:country":"US",
    "sg:address":"707 Neshaminy Mall",
    "sg:city":"Bensalem",
    "sg:classifiers":[
        {
            "category":"Shopping",
            "subcategory":"Clothing, Apparel, & Fashions",
            "type":"Retail Goods"
        }
    ],
    "sg:phone":"+1 215 364 9112",
    "sg:postcode":"19020",
    "sg:province":"PA",
    "sg:tags":[
        "accessory",
        "clothing",
        "women's"
    ],
    "sg:website":"www.charlotterusse.com",
    "wof:name":"Charlotte Russe",
    "wof:placetype":"venue"
},
  "geometry": {"coordinates":[-74.956802,40.139198],"type":"Point"}
}