{
  "type": "Feature",
  "properties": {
    "iso:country":"US",
    "sg:address":"3551 Chestnut St",
    "sg:city":"Philadelphia",
    "sg:classifiers":[
        {
            "category":"Shopping",
            "subcategory":"Florist",
            "type":"Retail Goods"
        }
    ],
    "sg:phone":"+1   ",
    "sg:postcode":"19104",
    "sg:province":"PA",
    "wof:name":"Roses Sheraton Florist",
    "wof:placetype":"venue"
},
  "geometry": {"coordinates":[-75.19251,39.954485],"type":"Point"}
}