{
  "type": "Feature",
  "properties": {
    "addr:full":"5110 Umbria St Philadelphia PA 19127",
    "addr:housenumber":"5110",
    "addr:postcode":"19127",
    "addr:street":"Umbria St",
    "iso:country":"US",
    "sg:address":"5110 Umbria St",
    "sg:city":"Philadelphia",
    "sg:classifiers":[
        {
            "category":"Retail",
            "subcategory":"Auto Repair",
            "type":"Services"
        }
    ],
    "sg:phone":"+1 215 482 6888",
    "sg:postcode":"19127",
    "sg:province":"PA",
    "sg:tags":[
        "body",
        "automobile",
        "painting"
    ],
    "wof:name":"E T Automobile Collision Rpr",
    "wof:placetype":"venue"
},
  "geometry": {"coordinates":[-75.240098,40.038565],"type":"Point"}
}