{
  "type": "Feature",
  "properties": {
    "addr:full":"95 Rockey Rd Loganton PA 17747",
    "addr:housenumber":"95",
    "addr:postcode":"17747",
    "addr:street":"Rockey Rd",
    "iso:country":"US",
    "sg:address":"95 Rockey Rd",
    "sg:city":"Loganton",
    "sg:classifiers":[
        {
            "category":"Freight",
            "type":"Transportation"
        }
    ],
    "sg:phone":"+1   ",
    "sg:postcode":"17747",
    "sg:province":"PA",
    "sg:tags":[
        "arrangement"
    ],
    "wof:name":"Darlene Kennedy Trucking",
    "wof:placetype":"venue"
},
  "geometry": {"coordinates":[-77.28745000000001,41.057174],"type":"Point"}
}