{
  "type": "Feature",
  "properties": {
    "iso:country":"US",
    "sg:address":"115 S Juniata St",
    "sg:city":"Hollidaysburg",
    "sg:classifiers":[
        {
            "category":"Food & Beverages",
            "subcategory":"Groceries & Convenience Stores",
            "type":"Retail Goods"
        }
    ],
    "sg:phone":"+1 814 695 1140",
    "sg:postcode":"16648",
    "sg:province":"PA",
    "wof:name":"Choice Cigarette Discount Otlt",
    "wof:placetype":"venue"
},
  "geometry": {"coordinates":[-78.394418,40.42735],"type":"Point"}
}