{
  "type": "Feature",
  "properties": {
    "iso:country":"US",
    "sg:address":"6133 Ridge Ave",
    "sg:city":"Philadelphia",
    "sg:classifiers":[
        {
            "category":"Personal",
            "subcategory":"Beauty Salon",
            "type":"Services"
        },
        {
            "category":"Shopping",
            "subcategory":"Party Supplies",
            "type":"Retail Goods"
        },
        {
            "category":"Personal",
            "subcategory":"Barber",
            "type":"Services"
        },
        {
            "category":"Personal",
            "subcategory":"Nail Salon",
            "type":"Services"
        }
    ],
    "sg:phone":"+1 215 483 7500",
    "sg:postcode":"19128",
    "sg:province":"PA",
    "sg:tags":[
        "hair",
        "stylist",
        "wedding"
    ],
    "sg:website":"http://www.luieleihair.com",
    "wof:name":"Lui E Lei Salon",
    "wof:placetype":"venue"
},
  "geometry": {"coordinates":[-75.21628200000001,40.034479],"type":"Point"}
}