{
  "type": "Feature",
  "properties": {
    "iso:country":"US",
    "sg:address":"411 E Market St",
    "sg:city":"Clearfield",
    "sg:classifiers":[
        {
            "category":"Health Services",
            "subcategory":"Doctor",
            "type":"Services"
        }
    ],
    "sg:phone":"+1 814 765 7333",
    "sg:postcode":"16830",
    "sg:province":"PA",
    "sg:tags":[
        "dentist"
    ],
    "wof:name":"Craig Doerfler & Assoc",
    "wof:placetype":"venue"
},
  "geometry": {"coordinates":[-78.43446400000001,41.022001],"type":"Point"}
}