{
  "type": "Feature",
  "properties": {
    "addr:full":"1038 Lancaster Pike Quarryville PA 17566",
    "addr:housenumber":"1038",
    "addr:postcode":"17566",
    "addr:street":"Lancaster Pike",
    "iso:country":"US",
    "sg:address":"1038 Lancaster Pike",
    "sg:city":"Quarryville",
    "sg:classifiers":[
        {
            "category":"Professional",
            "type":"Services"
        }
    ],
    "sg:phone":"+1   ",
    "sg:postcode":"17566",
    "sg:province":"PA",
    "wof:name":"Elam Fisher",
    "wof:placetype":"venue"
},
  "geometry": {"coordinates":[-76.22708900000001,39.867328],"type":"Point"}
}