{
  "type": "Feature",
  "properties": {
    "iso:country":"US",
    "sg:address":"1508 Saint Paul Rd",
    "sg:city":"Salisbury",
    "sg:classifiers":[
        {
            "category":"Wholesale",
            "subcategory":"Machinery & Supplies",
            "type":"Manufacturing & Wholesale Goods"
        }
    ],
    "sg:phone":"+1 814 662 2266",
    "sg:postcode":"15558",
    "sg:province":"PA",
    "sg:tags":[
        "equipment",
        "industrial",
        "hydraulic"
    ],
    "wof:name":"Yoder's Air & Hydraulics",
    "wof:placetype":"venue"
},
  "geometry": {"coordinates":[-79.09738,39.766102],"type":"Point"}
}