{
  "type": "Feature",
  "properties": {
    "iso:country":"US",
    "sg:address":"216 Martzville Rd",
    "sg:city":"Berwick",
    "sg:classifiers":[
        {
            "category":"Shopping",
            "subcategory":"Bicycles & Sporting Goods",
            "type":"Retail Goods"
        }
    ],
    "sg:phone":"+1 570 759 0157",
    "sg:postcode":"18603",
    "sg:province":"PA",
    "sg:tags":[
        "equipment",
        "archery",
        "supply"
    ],
    "wof:name":"Blue Heron",
    "wof:placetype":"venue"
},
  "geometry": {"coordinates":[-76.248487,41.066738],"type":"Point"}
}