{
  "type": "Feature",
  "properties": {
    "iso:country":"US",
    "sg:address":"179 Kings Nursery Rd",
    "sg:city":"Greensburg",
    "sg:classifiers":[
        {
            "category":"Home & Garden",
            "subcategory":"Garden Supply",
            "type":"Retail Goods"
        }
    ],
    "sg:phone":"+1 724 834 0202",
    "sg:postcode":"15601",
    "sg:province":"PA",
    "sg:tags":[
        "nurseryman"
    ],
    "wof:name":"King Garden Palace",
    "wof:placetype":"venue"
},
  "geometry": {"coordinates":[-79.492104,40.279354],"type":"Point"}
}