{
  "type": "Feature",
  "properties": {
    "iso:country":"US",
    "sg:address":"4288 Green Glade Ct",
    "sg:city":"Allison Park",
    "sg:classifiers":[
        {
            "category":"Professional",
            "subcategory":"Lawyer & Legal Services",
            "type":"Services"
        }
    ],
    "sg:phone":"+1 412 487 5391",
    "sg:postcode":"15101",
    "sg:province":"PA",
    "sg:tags":[
        "attorney"
    ],
    "wof:name":"Edward G O'Connor",
    "wof:placetype":"venue"
},
  "geometry": {"coordinates":[-79.927386,40.575518],"type":"Point"}
}