{
  "type": "Feature",
  "properties": {
    "iso:country":"US",
    "sg:address":"37 Forest Ave",
    "sg:city":"Barnesville",
    "sg:classifiers":[
        {
            "category":"Transit Center",
            "subcategory":"Freight",
            "type":"Transportation"
        },
        {
            "category":"Freight",
            "type":"Transportation"
        }
    ],
    "sg:phone":"+1 570 527 6793",
    "sg:postcode":"18214",
    "sg:province":"PA",
    "sg:tags":[
        "local",
        "trucking-motor",
        "trucking"
    ],
    "wof:name":"Gary W Bettis",
    "wof:placetype":"venue"
},
  "geometry": {"coordinates":[-76.051231,40.819217],"type":"Point"}
}