{
  "type": "Feature",
  "properties": {
    "iso:country":"US",
    "sg:address":"1150 Goodwill Dr",
    "sg:city":"Harrisburg",
    "sg:classifiers":[
        {
            "category":"Social Services",
            "type":"Services"
        }
    ],
    "sg:phone":"+1 717 232 1831",
    "sg:postcode":"17101",
    "sg:province":"PA",
    "sg:tags":[
        "organization",
        "welfare"
    ],
    "sg:website":"www.gwcpa.org",
    "wof:name":"Goodwill Industries",
    "wof:placetype":"venue"
},
  "geometry": {"coordinates":[-76.874848,40.269232],"type":"Point"}
}