{
  "type": "Feature",
  "properties": {
    "addr:full":"18 N Park Row Erie PA 16501",
    "addr:housenumber":"18",
    "addr:postcode":"16501",
    "addr:street":"N Park Row",
    "iso:country":"US",
    "sg:address":"18 N Park Row",
    "sg:city":"Erie",
    "sg:classifiers":[
        {
            "category":"Restaurant",
            "type":"Food & Drink"
        }
    ],
    "sg:menulink":"http://www.allmenus.com/pa/erie/278840-bertrands-bistro/menu/",
    "sg:phone":"+1 814 871 6477",
    "sg:postcode":"16501",
    "sg:province":"PA",
    "sg:tags":[
        "french"
    ],
    "wof:name":"Bertrand's Bistro",
    "wof:placetype":"venue"
},
  "geometry": {"coordinates":[-80.08618,42.129992],"type":"Point"}
}