{
  "type": "Feature",
  "properties": {
    "iso:country":"US",
    "sg:address":"1239 Woodland Ave",
    "sg:city":"Pittsburgh",
    "sg:classifiers":[
        {
            "category":"Manufacturing",
            "subcategory":"Retail Goods",
            "type":"Manufacturing & Wholesale Goods"
        }
    ],
    "sg:phone":"+1   ",
    "sg:postcode":"15212",
    "sg:province":"PA",
    "sg:tags":[
        "carbon",
        "mfg",
        "ribbon",
        "sup"
    ],
    "wof:name":"Ribbon Renu",
    "wof:placetype":"venue"
},
  "geometry": {"coordinates":[-80.028291,40.469381],"type":"Point"}
}