{
  "type": "Feature",
  "properties": {
    "addr:full":"120 Ford St W Conshohocken PA 19428",
    "addr:housenumber":"120",
    "addr:postcode":"19428",
    "addr:street":"Ford St W",
    "iso:country":"US",
    "sg:address":"120 Ford St",
    "sg:city":"W Conshohocken",
    "sg:classifiers":[
        {
            "category":"Banks & Credit Unions",
            "subcategory":"Investment Brokerage",
            "type":"Services"
        }
    ],
    "sg:phone":"+1 610 834 5500",
    "sg:postcode":"19428",
    "sg:province":"PA",
    "sg:tags":[
        "consultant",
        "planning",
        "financial"
    ],
    "wof:name":"American Express Financial Adv",
    "wof:placetype":"venue"
},
  "geometry": {"coordinates":[-75.312837,40.068777],"type":"Point"}
}