{
  "type": "Feature",
  "properties": {
    "iso:country":"US",
    "sg:address":"221 Pleasantview Dr",
    "sg:city":"Midland",
    "sg:classifiers":[
        {
            "category":"Professional",
            "type":"Services"
        }
    ],
    "sg:phone":"+1 724 643 9153",
    "sg:postcode":"15059",
    "sg:province":"PA",
    "sg:tags":[
        "establishment"
    ],
    "wof:name":"Bible Holiness Chapel Prsng",
    "wof:placetype":"venue"
},
  "geometry": {"coordinates":[-80.498302,40.688669],"type":"Point"}
}