{
  "type": "Feature",
  "properties": {
    "addr:full":"3250 Kensington Ave Philadelphia PA 19134",
    "addr:housenumber":"3250",
    "addr:postcode":"19134",
    "addr:street":"Kensington Ave",
    "iso:country":"US",
    "sg:address":"3250 Kensington Ave",
    "sg:city":"Philadelphia",
    "sg:classifiers":[
        {
            "category":"Personal",
            "subcategory":"Beauty Salon",
            "type":"Services"
        }
    ],
    "sg:phone":"+1   ",
    "sg:postcode":"19134",
    "sg:province":"PA",
    "sg:tags":[
        "shop"
    ],
    "wof:name":"Perm Shop",
    "wof:placetype":"venue"
},
  "geometry": {"coordinates":[-75.111642,39.997507],"type":"Point"}
}