{
  "type": "Feature",
  "properties": {
    "iso:country":"US",
    "sg:address":"220 Mt Pleasant Rd",
    "sg:city":"Mt Pleasant",
    "sg:classifiers":[
        {
            "category":"Health Services",
            "subcategory":"Doctor",
            "type":"Services"
        }
    ],
    "sg:phone":"+1 724 547 8020",
    "sg:postcode":"15666",
    "sg:province":"PA",
    "sg:tags":[
        "physician",
        "surgeon"
    ],
    "wof:name":"John Domit Surgical Assoc",
    "wof:placetype":"venue"
},
  "geometry": {"coordinates":[-79.55471,40.097497],"type":"Point"}
}