{
  "type": "Feature",
  "properties": {
    "addr:full":"2066 Colebrook Rd Middletown PA 17057",
    "addr:housenumber":"2066",
    "addr:postcode":"17057",
    "addr:street":"Colebrook Rd",
    "iso:country":"US",
    "sg:address":"2066 Colebrook Rd",
    "sg:city":"Middletown",
    "sg:classifiers":[
        {
            "category":"Professional",
            "type":"Services"
        }
    ],
    "sg:phone":"+1   ",
    "sg:postcode":"17057",
    "sg:province":"PA",
    "wof:name":"Ronald Kopp",
    "wof:placetype":"venue"
},
  "geometry": {"coordinates":[-76.677302,40.201516],"type":"Point"}
}