{
  "type": "Feature",
  "properties": {
    "iso:country":"US",
    "sg:address":"26 Cottage Ln",
    "sg:city":"Glen Mills",
    "sg:classifiers":[
        {
            "category":"Wholesale",
            "subcategory":"Home Furnishings",
            "type":"Manufacturing & Wholesale Goods"
        }
    ],
    "sg:phone":"+1   ",
    "sg:postcode":"19342",
    "sg:province":"PA",
    "wof:name":"Draperies Elite",
    "wof:placetype":"venue"
},
  "geometry": {"coordinates":[-75.486113,39.931734],"type":"Point"}
}