{
  "type": "Feature",
  "properties": {
    "addr:full":"515 W Walnut St Perkasie PA 18944",
    "addr:housenumber":"515",
    "addr:postcode":"18944",
    "addr:street":"W Walnut St",
    "iso:country":"US",
    "sg:address":"515 W Walnut St",
    "sg:city":"Perkasie",
    "sg:classifiers":[
        {
            "category":"Building & Trades",
            "subcategory":"Plumbing",
            "type":"Services"
        }
    ],
    "sg:phone":"+1   ",
    "sg:postcode":"18944",
    "sg:province":"PA",
    "sg:tags":[
        "contractor"
    ],
    "wof:name":"Baskin & Son Plumbing",
    "wof:placetype":"venue"
},
  "geometry": {"coordinates":[-75.296981,40.372343],"type":"Point"}
}