{
  "type": "Feature",
  "properties": {
    "addr:full":"26 S Main St Pittston PA 18640",
    "addr:housenumber":"26",
    "addr:postcode":"18640",
    "addr:street":"S Main St",
    "iso:country":"US",
    "sg:address":"26 S Main St",
    "sg:city":"Pittston",
    "sg:classifiers":[
        {
            "category":"Restaurant",
            "type":"Food & Drink"
        }
    ],
    "sg:phone":"+1   ",
    "sg:postcode":"18640",
    "sg:province":"PA",
    "sg:tags":[
        "eating"
    ],
    "wof:name":"Starz Pizza",
    "wof:placetype":"venue"
},
  "geometry": {"coordinates":[-75.7907,41.322316],"type":"Point"}
}