{
  "type": "Feature",
  "properties": {
    "iso:country":"US",
    "sg:address":"5 S 35th St",
    "sg:city":"Camp Hill",
    "sg:classifiers":[
        {
            "category":"Restaurant",
            "type":"Food & Drink"
        }
    ],
    "sg:phone":"+1 717 737 0238",
    "sg:postcode":"17011",
    "sg:province":"PA",
    "sg:tags":[
        "korean",
        "japanese"
    ],
    "sg:website":"www.koreanspringgarden.net",
    "wof:name":"Spring Garden Restaurant",
    "wof:placetype":"venue"
},
  "geometry": {"coordinates":[-76.941472,40.239108],"type":"Point"}
}