{
  "type": "Feature",
  "properties": {
    "iso:country":"US",
    "sg:address":"6034 N Lambert St",
    "sg:city":"Philadelphia",
    "sg:classifiers":[
        {
            "category":"Building & Trades",
            "subcategory":"Construction",
            "type":"Services"
        }
    ],
    "sg:phone":"+1   ",
    "sg:postcode":"19138",
    "sg:province":"PA",
    "sg:tags":[
        "house"
    ],
    "wof:name":"Home Improvements & Landsc",
    "wof:placetype":"venue"
},
  "geometry": {"coordinates":[-75.154994,40.046958],"type":"Point"}
}