{
  "type": "Feature",
  "properties": {
    "iso:country":"US",
    "sg:address":"1781 Autumnwood Dr",
    "sg:city":"Mechanicsburg",
    "sg:classifiers":[
        {
            "category":"Building & Trades",
            "subcategory":"Construction",
            "type":"Services"
        }
    ],
    "sg:phone":"+1 717 691 1332",
    "sg:postcode":"17055",
    "sg:province":"PA",
    "sg:tags":[
        "contractor"
    ],
    "wof:name":"Sechrist Construction Inc",
    "wof:placetype":"venue"
},
  "geometry": {"coordinates":[-76.997781,40.1775],"type":"Point"}
}