{
  "type": "Feature",
  "properties": {
    "iso:country":"US",
    "sg:address":"820 Mountain View St",
    "sg:city":"Harrisburg",
    "sg:classifiers":[
        {
            "category":"Government",
            "subcategory":"Office",
            "type":"Public Place"
        }
    ],
    "sg:phone":"+1   ",
    "sg:postcode":"17112",
    "sg:province":"PA",
    "sg:tags":[
        "educational",
        "program",
        "administrative"
    ],
    "wof:name":"Justin Wallace Memorial S",
    "wof:placetype":"venue"
},
  "geometry": {"coordinates":[-76.79618600000001,40.335443],"type":"Point"}
}