{
  "type": "Feature",
  "properties": {
    "iso:country":"US",
    "sg:address":"1106 Orange St",
    "sg:city":"Berwick",
    "sg:classifiers":[
        {
            "category":"Organizations",
            "subcategory":"Religious Organization",
            "type":"Services"
        }
    ],
    "sg:phone":"+1 570 759 2622",
    "sg:postcode":"18603",
    "sg:province":"PA",
    "sg:tags":[
        "church"
    ],
    "wof:name":"Seventh Day Adventists Church",
    "wof:placetype":"venue"
},
  "geometry": {"coordinates":[-76.251503,41.051901],"type":"Point"}
}