{
  "type": "Feature",
  "properties": {
    "addr:full":"3401 N Broad St Ste 350 Philadelphia PA 19140",
    "addr:housenumber":"3401",
    "addr:postcode":"19140",
    "addr:street":"N Broad St Ste 350",
    "iso:country":"US",
    "sg:address":"3401 N Broad St Ste 350",
    "sg:city":"Philadelphia",
    "sg:classifiers":[
        {
            "category":"Health Services",
            "subcategory":"Doctor",
            "type":"Services"
        }
    ],
    "sg:phone":"+1 215 707 3375",
    "sg:postcode":"19140",
    "sg:province":"PA",
    "sg:tags":[
        "physician",
        "surgeon",
        "urology",
        "surgeons"
    ],
    "wof:name":"Temple Urology Associates",
    "wof:placetype":"venue"
},
  "geometry": {"coordinates":[-75.152237,40.004681],"type":"Point"}
}