{
  "type": "Feature",
  "properties": {
    "addr:full":"523 Wiconisco St Harrisburg PA 17110",
    "addr:housenumber":"523",
    "addr:postcode":"17110",
    "addr:street":"Wiconisco St",
    "iso:country":"US",
    "sg:address":"523 Wiconisco St",
    "sg:city":"Harrisburg",
    "sg:phone":"+1 717 236 3980",
    "sg:postcode":"17110",
    "sg:province":"PA",
    "wof:name":"Sophia's Seafood Restaurant",
    "wof:placetype":"venue"
},
  "geometry": {"coordinates":[-76.89639699999999,40.289807],"type":"Point"}
}