{
  "type": "Feature",
  "properties": {
    "addr:full":"322 E Park Ave State College PA 16803",
    "addr:housenumber":"322",
    "addr:postcode":"16803",
    "addr:street":"E Park Ave",
    "iso:country":"US",
    "sg:address":"322 E Park Ave",
    "sg:city":"State College",
    "sg:classifiers":[
        {
            "category":"Building & Trades",
            "subcategory":"Plumbing",
            "type":"Services"
        }
    ],
    "sg:phone":"+1 814 231 0970",
    "sg:postcode":"16803",
    "sg:province":"PA",
    "sg:tags":[
        "mechanical",
        "contractor"
    ],
    "wof:name":"S A Communale Co Inc",
    "wof:placetype":"venue"
},
  "geometry": {"coordinates":[-77.86713,40.802888],"type":"Point"}
}