{
  "type": "Feature",
  "properties": {
    "iso:country":"US",
    "sg:address":"1019 Valley Rd",
    "sg:city":"Schellsburg",
    "sg:classifiers":[
        {
            "category":"Professional",
            "subcategory":"Business Services",
            "type":"Services"
        }
    ],
    "sg:phone":"+1 814 733 4523",
    "sg:postcode":"15559",
    "sg:province":"PA",
    "sg:tags":[
        "notary"
    ],
    "wof:name":"Lakeside Notary & Tags",
    "wof:placetype":"venue"
},
  "geometry": {"coordinates":[-78.622923,40.075249],"type":"Point"}
}