{
  "type": "Feature",
  "properties": {
    "iso:country":"US",
    "sg:address":"814 Mifflin St",
    "sg:city":"West Mifflin",
    "sg:classifiers":[
        {
            "category":"Building & Trades",
            "subcategory":"Construction",
            "type":"Services"
        }
    ],
    "sg:phone":"+1   ",
    "sg:postcode":"15122",
    "sg:province":"PA",
    "sg:tags":[
        "special",
        "contractor"
    ],
    "wof:name":"Philotechnics Ltd",
    "wof:placetype":"venue"
},
  "geometry": {"coordinates":[-79.85451,40.36133],"type":"Point"}
}