{
  "type": "Feature",
  "properties": {
    "addr:full":"61 Parade St Union City PA 16438",
    "addr:housenumber":"61",
    "addr:postcode":"16438",
    "addr:street":"Parade St",
    "iso:country":"US",
    "sg:address":"61 Parade St",
    "sg:city":"Union City",
    "sg:classifiers":[
        {
            "category":"Real Estate",
            "subcategory":"Real Estate Operator",
            "type":"Services"
        }
    ],
    "sg:phone":"+1   ",
    "sg:postcode":"16438",
    "sg:province":"PA",
    "sg:tags":[
        "building",
        "apartment"
    ],
    "wof:name":"Union City Estates Parade St",
    "wof:placetype":"venue"
},
  "geometry": {"coordinates":[-79.853371,41.893722],"type":"Point"}
}