{
  "type": "Feature",
  "properties": {
    "iso:country":"US",
    "sg:address":"3260 South St",
    "sg:city":"Philadelphia",
    "sg:phone":"+1 215 898 4000",
    "sg:postcode":"19104",
    "sg:province":"PA",
    "sg:website":"http://www.med.upenn.edu",
    "wof:name":"Penn Museum: University of Penssylvania Museum of Archaeology and Anthropology",
    "wof:placetype":"venue"
},
  "geometry": {"coordinates":[-75.190265,39.949304],"type":"Point"}
}