{
  "type": "Feature",
  "properties": {
    "iso:country":"US",
    "sg:address":"135 N George St",
    "sg:city":"York",
    "sg:classifiers":[
        {
            "category":"Professional",
            "subcategory":"Lawyer & Legal Services",
            "type":"Services"
        }
    ],
    "sg:phone":"+1 717 848 3174",
    "sg:postcode":"17401",
    "sg:province":"PA",
    "sg:tags":[
        "attorney"
    ],
    "wof:name":"Peter J Mangan",
    "wof:placetype":"venue"
},
  "geometry": {"coordinates":[-76.72838900000001,39.964498],"type":"Point"}
}