{
  "type": "Feature",
  "properties": {
    "iso:country":"US",
    "sg:address":"605 Corporate Dr W",
    "sg:city":"Langhorne",
    "sg:classifiers":[
        {
            "category":"Real Estate",
            "subcategory":"Real Estate Services",
            "type":"Services"
        }
    ],
    "sg:phone":"+1 215 579 7122",
    "sg:postcode":"19047",
    "sg:province":"PA",
    "sg:tags":[
        "company",
        "title"
    ],
    "wof:name":"Lincoln Abstract Assoc Inc",
    "wof:placetype":"venue"
},
  "geometry": {"coordinates":[-74.90900999999999,40.220791],"type":"Point"}
}