{
  "type": "Feature",
  "properties": {
    "addr:full":"1102 Thompson St Jersey Shore PA 17740",
    "addr:housenumber":"1102",
    "addr:postcode":"17740",
    "addr:street":"Thompson St",
    "iso:country":"US",
    "sg:address":"1102 Thompson St",
    "sg:city":"Jersey Shore",
    "sg:classifiers":[
        {
            "category":"Personal",
            "subcategory":"Beauty Salon",
            "type":"Services"
        }
    ],
    "sg:phone":"+1 570 398 5970",
    "sg:postcode":"17740",
    "sg:province":"PA",
    "wof:name":"Hair Nails & More",
    "wof:placetype":"venue"
},
  "geometry": {"coordinates":[-77.270706,41.201994],"type":"Point"}
}