{
  "type": "Feature",
  "properties": {
    "addr:full":"3110 Ben Venue Dr Greensburg PA 15601",
    "addr:housenumber":"3110",
    "addr:postcode":"15601",
    "addr:street":"Ben Venue Dr",
    "iso:country":"US",
    "sg:address":"3110 Ben Venue Dr",
    "sg:city":"Greensburg",
    "sg:classifiers":[
        {
            "category":"Professional",
            "type":"Services"
        }
    ],
    "sg:phone":"+1   ",
    "sg:postcode":"15601",
    "sg:province":"PA",
    "wof:name":"Bernie Matthews Sports CA",
    "wof:placetype":"venue"
},
  "geometry": {"coordinates":[-79.47434199999999,40.290231],"type":"Point"}
}