{
  "type": "Feature",
  "properties": {
    "iso:country":"US",
    "sg:address":"1639 Sunshine Ave",
    "sg:city":"Johnstown",
    "sg:classifiers":[
        {
            "category":"Building & Trades",
            "subcategory":"Construction",
            "type":"Services"
        }
    ],
    "sg:phone":"+1 814 536 4493",
    "sg:postcode":"15905",
    "sg:province":"PA",
    "sg:tags":[
        "residential"
    ],
    "wof:name":"Covenant Properties",
    "wof:placetype":"venue"
},
  "geometry": {"coordinates":[-78.95587999999999,40.314507],"type":"Point"}
}