{
  "type": "Feature",
  "properties": {
    "iso:country":"US",
    "sg:address":"327 W Long Ave",
    "sg:city":"Du Bois",
    "sg:classifiers":[
        {
            "category":"Shopping",
            "subcategory":"Used Merchandise",
            "type":"Retail Goods"
        },
        {
            "category":"Shopping",
            "subcategory":"Clothing, Apparel, & Fashions",
            "type":"Retail Goods"
        }
    ],
    "sg:phone":"+1 814 371 6090",
    "sg:postcode":"15801",
    "sg:province":"PA",
    "sg:tags":[
        "antique"
    ],
    "wof:name":"Constatino's Jade Co",
    "wof:placetype":"venue"
},
  "geometry": {"coordinates":[-78.766104,41.121286],"type":"Point"}
}