{
  "type": "Feature",
  "properties": {
    "iso:country":"US",
    "sg:address":"701 Martha Ave",
    "sg:city":"Lancaster",
    "sg:classifiers":[
        {
            "category":"Professional",
            "subcategory":"Business Services",
            "type":"Services"
        }
    ],
    "sg:phone":"+1   ",
    "sg:postcode":"17601",
    "sg:province":"PA",
    "wof:name":"Peter Dettore Associates Inc",
    "wof:placetype":"venue"
},
  "geometry": {"coordinates":[-76.292866,40.056678],"type":"Point"}
}