{
  "type": "Feature",
  "properties": {
    "iso:country":"US",
    "sg:address":"206 S Martin St",
    "sg:city":"Titusville",
    "sg:classifiers":[
        {
            "category":"Railroad",
            "type":"Transportation"
        }
    ],
    "sg:phone":"+1 814 827 2659",
    "sg:postcode":"16354",
    "sg:province":"PA",
    "wof:name":"Oil Creek & Titusville Lines",
    "wof:placetype":"venue"
},
  "geometry": {"coordinates":[-79.67165900000001,41.625498],"type":"Point"}
}