{
  "type": "Feature",
  "properties": {
    "iso:country":"US",
    "sg:address":"2701 Germantown Ave",
    "sg:city":"Philadelphia",
    "sg:classifiers":[
        {
            "category":"Restaurant",
            "type":"Food & Drink"
        }
    ],
    "sg:phone":"+1 215 227 2511",
    "sg:postcode":"19133",
    "sg:province":"PA",
    "wof:name":"Nino Restaurant",
    "wof:placetype":"venue"
},
  "geometry": {"coordinates":[-75.147699,39.993781],"type":"Point"}
}