{
  "type": "Feature",
  "properties": {
    "iso:country":"US",
    "sg:address":"820 Mount Gretna Rd",
    "sg:city":"Mt Gretna",
    "sg:classifiers":[
        {
            "category":"Professional",
            "subcategory":"Computer Services",
            "type":"Services"
        }
    ],
    "sg:phone":"+1 717 964 2206",
    "sg:postcode":"17064",
    "sg:province":"PA",
    "sg:tags":[
        "wiring"
    ],
    "wof:name":"Allied Keystone Technologies",
    "wof:placetype":"venue"
},
  "geometry": {"coordinates":[-76.47616499999999,40.244926],"type":"Point"}
}