{
  "type": "Feature",
  "properties": {
    "iso:country":"US",
    "sg:address":"1321 Green St",
    "sg:city":"Linwood",
    "sg:classifiers":[
        {
            "category":"Organizations",
            "subcategory":"Religious Organization",
            "type":"Services"
        }
    ],
    "sg:phone":"+1 610 859 8545",
    "sg:postcode":"19061",
    "sg:province":"PA",
    "sg:tags":[
        "church"
    ],
    "wof:name":"Mt Hebron AME Church",
    "wof:placetype":"venue"
},
  "geometry": {"coordinates":[-75.420849,39.823494],"type":"Point"}
}