{
  "type": "Feature",
  "properties": {
    "iso:country":"US",
    "sg:address":"825 Walnut St",
    "sg:city":"Philadelphia",
    "sg:classifiers":[
        {
            "category":"Retail",
            "subcategory":"Event Space",
            "type":"Services"
        },
        {
            "category":"Arena",
            "subcategory":"Sports Club",
            "type":"Entertainment"
        }
    ],
    "sg:phone":"+1 215 923 4021",
    "sg:postcode":"19107",
    "sg:province":"PA",
    "sg:tags":[
        "ticket",
        "sale"
    ],
    "wof:name":"Ticketmaster",
    "wof:placetype":"venue"
},
  "geometry": {"coordinates":[-75.154636,39.948136],"type":"Point"}
}