{
  "type": "Feature",
  "properties": {
    "addr:full":"1140 Langdon Rd Erie PA 16509",
    "addr:housenumber":"1140",
    "addr:postcode":"16509",
    "addr:street":"Langdon Rd",
    "iso:country":"US",
    "sg:address":"1140 Langdon Rd",
    "sg:city":"Erie",
    "sg:classifiers":[
        {
            "category":"Building & Trades",
            "subcategory":"Cleaning & Sanitation",
            "type":"Services"
        }
    ],
    "sg:phone":"+1 814 825 2537",
    "sg:postcode":"16509",
    "sg:province":"PA",
    "sg:tags":[
        "janitor"
    ],
    "sg:website":"www.sunshineservice.com",
    "wof:name":"Sunshine Services",
    "wof:placetype":"venue"
},
  "geometry": {"coordinates":[-80.02341199999999,42.080224],"type":"Point"}
}