{
  "type": "Feature",
  "properties": {
    "addr:full":"29 Woodcroft Rd Havertown PA 19083",
    "addr:housenumber":"29",
    "addr:postcode":"19083",
    "addr:street":"Woodcroft Rd",
    "iso:country":"US",
    "sg:address":"29 Woodcroft Rd",
    "sg:city":"Havertown",
    "sg:classifiers":[
        {
            "category":"Professional",
            "subcategory":"Computer Services",
            "type":"Services"
        }
    ],
    "sg:phone":"+1   ",
    "sg:postcode":"19083",
    "sg:province":"PA",
    "sg:tags":[
        "design",
        "system"
    ],
    "wof:name":"Meezer Mania LLC",
    "wof:placetype":"venue"
},
  "geometry": {"coordinates":[-75.32069300000001,39.990131],"type":"Point"}
}