{
  "type": "Feature",
  "properties": {
    "addr:full":"313 W Chester Rd West Chester PA 19382",
    "addr:housenumber":"313",
    "addr:postcode":"19382",
    "addr:street":"W Chester Rd",
    "iso:country":"US",
    "sg:address":"313 W Chester Rd",
    "sg:city":"West Chester",
    "sg:classifiers":[
        {
            "category":"Retail",
            "subcategory":"Repair Shop",
            "type":"Services"
        }
    ],
    "sg:phone":"+1 610 738 9300",
    "sg:postcode":"19382",
    "sg:province":"PA",
    "sg:tags":[
        "motorcycle",
        "accessory"
    ],
    "wof:name":"Cycle Adventure LTD II",
    "wof:placetype":"venue"
},
  "geometry": {"coordinates":[-75.54477300000001,39.910875],"type":"Point"}
}