{
  "type": "Feature",
  "properties": {
    "iso:country":"US",
    "sg:address":"28 Donati Rd",
    "sg:city":"Bethel Park",
    "sg:classifiers":[
        {
            "category":"Restaurant",
            "type":"Food & Drink"
        }
    ],
    "sg:phone":"+1   ",
    "sg:postcode":"15102",
    "sg:province":"PA",
    "sg:tags":[
        "eating"
    ],
    "wof:name":"Pepperonis Pizzeria",
    "wof:placetype":"venue"
},
  "geometry": {"coordinates":[-80.049992,40.338235],"type":"Point"}
}