{
  "type": "Feature",
  "properties": {
    "iso:country":"US",
    "sg:address":"316 Eutaw Ave",
    "sg:city":"New Cumberland",
    "sg:classifiers":[
        {
            "category":"Building & Trades",
            "subcategory":"Construction",
            "type":"Services"
        }
    ],
    "sg:phone":"+1 717 774 6679",
    "sg:postcode":"17070",
    "sg:province":"PA",
    "sg:tags":[
        "contractor"
    ],
    "wof:name":"Ashley Home Improvement",
    "wof:placetype":"venue"
},
  "geometry": {"coordinates":[-76.867499,40.223798],"type":"Point"}
}