{
  "type": "Feature",
  "properties": {
    "addr:full":"5632 Pocusset St Pittsburgh PA 15217",
    "addr:housenumber":"5632",
    "addr:postcode":"15217",
    "addr:street":"Pocusset St",
    "iso:country":"US",
    "sg:address":"5632 Pocusset St",
    "sg:city":"Pittsburgh",
    "sg:classifiers":[
        {
            "category":"Shopping",
            "subcategory":"Clothing, Apparel, & Fashions",
            "type":"Retail Goods"
        }
    ],
    "sg:phone":"+1 412 422 4696",
    "sg:postcode":"15217",
    "sg:province":"PA",
    "wof:name":"Saxon Uniform Network Inc",
    "wof:placetype":"venue"
},
  "geometry": {"coordinates":[-79.924386,40.42956],"type":"Point"}
}