{
  "type": "Feature",
  "properties": {
    "iso:country":"US",
    "sg:address":"18 Gettysburg Pike",
    "sg:city":"Mechanicsburg",
    "sg:classifiers":[
        {
            "category":"Retail",
            "subcategory":"Auto Repair",
            "type":"Services"
        }
    ],
    "sg:phone":"+1 717 697 8157",
    "sg:postcode":"17055",
    "sg:province":"PA",
    "wof:name":"Floyd's Garage",
    "wof:placetype":"venue"
},
  "geometry": {"coordinates":[-76.979897,40.190701],"type":"Point"}
}