{
  "type": "Feature",
  "properties": {
    "addr:full":"117 W Penn St Butler PA 16001",
    "addr:housenumber":"117",
    "addr:postcode":"16001",
    "addr:street":"W Penn St",
    "iso:country":"US",
    "sg:address":"117 W Penn St",
    "sg:city":"Butler",
    "sg:classifiers":[
        {
            "category":"Health Services",
            "subcategory":"Doctor",
            "type":"Services"
        }
    ],
    "sg:phone":"+1   ",
    "sg:postcode":"16001",
    "sg:province":"PA",
    "wof:name":"George C Bilowick DMD",
    "wof:placetype":"venue"
},
  "geometry": {"coordinates":[-79.895898,40.864969],"type":"Point"}
}