{
  "type": "Feature",
  "properties": {
    "iso:country":"US",
    "sg:address":"1201 Grampian Blvd",
    "sg:city":"Williamsport",
    "sg:classifiers":[
        {
            "category":"Organizations",
            "subcategory":"Non-profit Organization",
            "type":"Services"
        },
        {
            "category":"Social Services",
            "type":"Services"
        }
    ],
    "sg:phone":"+1 570 322 4220",
    "sg:postcode":"17701",
    "sg:province":"PA",
    "sg:tags":[
        "alternative",
        "abortion"
    ],
    "wof:name":"Catholic Charities",
    "wof:placetype":"venue"
},
  "geometry": {"coordinates":[-76.985736,41.260754],"type":"Point"}
}