{
  "type": "Feature",
  "properties": {
    "iso:country":"US",
    "sg:address":"1100 Maple Ter",
    "sg:city":"Washington",
    "sg:classifiers":[
        {
            "category":"Real Estate",
            "subcategory":"Real Estate Agent",
            "type":"Services"
        }
    ],
    "sg:phone":"+1 724 228 6071",
    "sg:postcode":"15301",
    "sg:province":"PA",
    "sg:tags":[
        "authorities",
        "housing",
        "manager"
    ],
    "wof:name":"Maple Terrace Housing Auth",
    "wof:placetype":"venue"
},
  "geometry": {"coordinates":[-80.261838,40.19017],"type":"Point"}
}