{
  "type": "Feature",
  "properties": {
    "addr:full":"1100 Main St Hellertown PA 18055",
    "addr:housenumber":"1100",
    "addr:postcode":"18055",
    "addr:street":"Main St",
    "iso:country":"US",
    "sg:address":"1100 Main St",
    "sg:city":"Hellertown",
    "sg:classifiers":[
        {
            "category":"Food & Beverages",
            "subcategory":"Groceries & Convenience Stores",
            "type":"Retail Goods"
        }
    ],
    "sg:phone":"+1 610 838 8566",
    "sg:postcode":"18055",
    "sg:province":"PA",
    "wof:name":"Seven Eleven Stores",
    "wof:placetype":"venue"
},
  "geometry": {"coordinates":[-75.341202,40.585499],"type":"Point"}
}