{
  "type": "Feature",
  "properties": {
    "iso:country":"US",
    "sg:address":"3861 Lancaster Ave",
    "sg:city":"Philadelphia",
    "sg:classifiers":[
        {
            "category":"Organizations",
            "subcategory":"Religious Organization",
            "type":"Services"
        }
    ],
    "sg:phone":"+1 215 386 1918",
    "sg:postcode":"19104",
    "sg:province":"PA",
    "sg:tags":[
        "church"
    ],
    "wof:name":"Truelight Missionary Baptist",
    "wof:placetype":"venue"
},
  "geometry": {"coordinates":[-75.19923900000001,39.96156],"type":"Point"}
}