{
  "type": "Feature",
  "properties": {
    "iso:country":"US",
    "sg:address":"731 Copeland St",
    "sg:city":"Pittsburgh",
    "sg:classifiers":[
        {
            "category":"Professional",
            "subcategory":"Advertising",
            "type":"Services"
        }
    ],
    "sg:phone":"+1 412 683 7050",
    "sg:postcode":"15232",
    "sg:province":"PA",
    "wof:name":"Pittsburgh Agency LLC",
    "wof:placetype":"venue"
},
  "geometry": {"coordinates":[-79.934669,40.450879],"type":"Point"}
}