{
  "type": "Feature",
  "properties": {
    "addr:full":"8896 Frankstown Rd Pittsburgh PA 15235",
    "addr:housenumber":"8896",
    "addr:postcode":"15235",
    "addr:street":"Frankstown Rd",
    "iso:country":"US",
    "sg:address":"8896 Frankstown Rd",
    "sg:city":"Pittsburgh",
    "sg:classifiers":[
        {
            "category":"Banks & Credit Unions",
            "subcategory":"Bank",
            "type":"Services"
        }
    ],
    "sg:phone":"+1   ",
    "sg:postcode":"15235",
    "sg:province":"PA",
    "sg:tags":[
        "drive"
    ],
    "wof:name":"Mellon",
    "wof:placetype":"venue"
},
  "geometry": {"coordinates":[-79.871467,40.461011],"type":"Point"}
}