{
  "type": "Feature",
  "properties": {
    "iso:country":"US",
    "sg:address":"3310 Starlight Dr",
    "sg:city":"York",
    "sg:classifiers":[
        {
            "category":"Building & Trades",
            "subcategory":"Construction",
            "type":"Services"
        }
    ],
    "sg:phone":"+1   ",
    "sg:postcode":"17402",
    "sg:province":"PA",
    "sg:tags":[
        "residential"
    ],
    "wof:name":"Mnd Contracting",
    "wof:placetype":"venue"
},
  "geometry": {"coordinates":[-76.658028,39.957573],"type":"Point"}
}