{
  "type": "Feature",
  "properties": {
    "iso:country":"US",
    "sg:address":"1110 Lombard St Apt 10",
    "sg:city":"Philadelphia",
    "sg:classifiers":[
        {
            "category":"Recreation",
            "type":"Entertainment"
        }
    ],
    "sg:phone":"+1 215 629 1615",
    "sg:postcode":"19147",
    "sg:province":"PA",
    "sg:tags":[
        "entertainers-family",
        "business"
    ],
    "wof:name":"Sharon Geller Entertainment",
    "wof:placetype":"venue"
},
  "geometry": {"coordinates":[-75.160393,39.944031],"type":"Point"}
}