{
  "type": "Feature",
  "properties": {
    "iso:country":"US",
    "sg:address":"326 Longfellow St",
    "sg:city":"Vandergrift",
    "sg:classifiers":[
        {
            "category":"Personal",
            "subcategory":"Beauty Salon",
            "type":"Services"
        }
    ],
    "sg:phone":"+1 724 567 7044",
    "sg:postcode":"15690",
    "sg:province":"PA",
    "sg:tags":[
        "shop"
    ],
    "wof:name":"Trends & Traditions",
    "wof:placetype":"venue"
},
  "geometry": {"coordinates":[-79.57172300000001,40.59708],"type":"Point"}
}