{
  "type": "Feature",
  "properties": {
    "iso:country":"US",
    "sg:address":"447 Sharon Rd",
    "sg:city":"Coraopolis",
    "sg:classifiers":[
        {
            "category":"Real Estate",
            "subcategory":"Real Estate Operator",
            "type":"Services"
        }
    ],
    "sg:phone":"+1 412 262 2476",
    "sg:postcode":"15108",
    "sg:province":"PA",
    "sg:tags":[
        "apartment"
    ],
    "wof:name":"Sharon Park Manor Apts",
    "wof:placetype":"venue"
},
  "geometry": {"coordinates":[-80.210297,40.513344],"type":"Point"}
}