{
  "type": "Feature",
  "properties": {
    "addr:full":"200 Wheatland Dr Gettysburg PA 17325",
    "addr:housenumber":"200",
    "addr:postcode":"17325",
    "addr:street":"Wheatland Dr",
    "iso:country":"US",
    "sg:address":"200 Wheatland Dr",
    "sg:city":"Gettysburg",
    "sg:classifiers":[
        {
            "category":"Building & Trades",
            "subcategory":"Construction",
            "type":"Services"
        }
    ],
    "sg:phone":"+1   ",
    "sg:postcode":"17325",
    "sg:province":"PA",
    "sg:tags":[
        "home",
        "general",
        "contractor"
    ],
    "wof:name":"Thomas P Gebhart",
    "wof:placetype":"venue"
},
  "geometry": {"coordinates":[-77.150341,39.812477],"type":"Point"}
}