{
  "type": "Feature",
  "properties": {
    "addr:full":"3832 Brisban St Harrisburg PA 17111",
    "addr:housenumber":"3832",
    "addr:postcode":"17111",
    "addr:street":"Brisban St",
    "iso:country":"US",
    "sg:address":"3832 Brisban St",
    "sg:city":"Harrisburg",
    "sg:classifiers":[
        {
            "category":"Professional",
            "subcategory":"Engineering",
            "type":"Services"
        }
    ],
    "sg:phone":"+1 717 561 1914",
    "sg:postcode":"17111",
    "sg:province":"PA",
    "sg:tags":[
        "general",
        "contractor"
    ],
    "wof:name":"Enders Engineering",
    "wof:placetype":"venue"
},
  "geometry": {"coordinates":[-76.822028,40.259128],"type":"Point"}
}