{
  "type": "Feature",
  "properties": {
    "iso:country":"US",
    "sg:address":"760 US Hwy 22",
    "sg:city":"Lewistown",
    "sg:classifiers":[
        {
            "category":"Wholesale",
            "subcategory":"Apparel",
            "type":"Manufacturing & Wholesale Goods"
        }
    ],
    "sg:phone":"+1 717 242 6383",
    "sg:postcode":"17044",
    "sg:province":"PA",
    "wof:name":"JDM Mfg Inc",
    "wof:placetype":"venue"
},
  "geometry": {"coordinates":[-77.592806,40.592317],"type":"Point"}
}