{
  "type": "Feature",
  "properties": {
    "addr:full":"4938 Germantown Ave Philadelphia PA 19144",
    "addr:housenumber":"4938",
    "addr:postcode":"19144",
    "addr:street":"Germantown Ave",
    "iso:country":"US",
    "sg:address":"4938 Germantown Ave",
    "sg:city":"Philadelphia",
    "sg:classifiers":[
        {
            "category":"Professional",
            "type":"Services"
        }
    ],
    "sg:phone":"+1   ",
    "sg:postcode":"19144",
    "sg:province":"PA",
    "wof:name":"Pennsylvania United Mason",
    "wof:placetype":"venue"
},
  "geometry": {"coordinates":[-75.16271,40.028406],"type":"Point"}
}