{
  "type": "Feature",
  "properties": {
    "iso:country":"US",
    "sg:address":"6719 Bernville Rd",
    "sg:city":"Bernville",
    "sg:classifiers":[
        {
            "category":"Food & Beverages",
            "subcategory":"Groceries & Convenience Stores",
            "type":"Retail Goods"
        }
    ],
    "sg:phone":"+1 610 488 7866",
    "sg:postcode":"19506",
    "sg:province":"PA",
    "wof:name":"Redner's Quick Shoppe",
    "wof:placetype":"venue"
},
  "geometry": {"coordinates":[-76.11216899999999,40.427865],"type":"Point"}
}