{
  "type": "Feature",
  "properties": {
    "iso:country":"US",
    "sg:address":"191 Palmer St",
    "sg:city":"Woodward",
    "sg:classifiers":[
        {
            "category":"Shopping",
            "subcategory":"Discount & Variety Stores",
            "type":"Retail Goods"
        }
    ],
    "sg:phone":"+1 570 322 6354",
    "sg:postcode":"16830",
    "sg:province":"PA",
    "sg:tags":[
        "merchandise",
        "general"
    ],
    "wof:name":"Lycoming Supply Inc",
    "wof:placetype":"venue"
},
  "geometry": {"coordinates":[-78.425489,41.034878],"type":"Point"}
}