{
  "type": "Feature",
  "properties": {
    "addr:full":"641 Maple St Brockway PA 15824",
    "addr:housenumber":"641",
    "addr:postcode":"15824",
    "addr:street":"Maple St",
    "iso:country":"US",
    "sg:address":"641 Maple St",
    "sg:city":"Brockway",
    "sg:classifiers":[
        {
            "category":"Personal",
            "subcategory":"Beauty Salon",
            "type":"Services"
        }
    ],
    "sg:phone":"+1 814 265 4247",
    "sg:postcode":"15824",
    "sg:province":"PA",
    "sg:tags":[
        "hair",
        "shop",
        "stylist"
    ],
    "wof:name":"The Cutting Edge",
    "wof:placetype":"venue"
},
  "geometry": {"coordinates":[-78.797594,41.243666],"type":"Point"}
}