{
  "type": "Feature",
  "properties": {
    "iso:country":"US",
    "sg:address":"125 N Water Ave",
    "sg:city":"Sharon",
    "sg:classifiers":[
        {
            "category":"Shopping",
            "type":"Retail Goods"
        }
    ],
    "sg:phone":"+1   ",
    "sg:postcode":"16146",
    "sg:province":"PA",
    "sg:tags":[
        "merchandise"
    ],
    "wof:name":"Advanced Lghtwave Cmmnications",
    "wof:placetype":"venue"
},
  "geometry": {"coordinates":[-80.512085,41.234994],"type":"Point"}
}