{
  "type": "Feature",
  "properties": {
    "iso:country":"US",
    "sg:address":"230 State Rte 313",
    "sg:city":"Perkasie",
    "sg:classifiers":[
        {
            "category":"Restaurant",
            "type":"Food & Drink"
        }
    ],
    "sg:phone":"+1 215 249 1206",
    "sg:postcode":"18944",
    "sg:province":"PA",
    "wof:name":"Dominick's Pizza Shoppe",
    "wof:placetype":"venue"
},
  "geometry": {"coordinates":[-75.253157,40.403063],"type":"Point"}
}