{
  "type": "Feature",
  "properties": {
    "iso:country":"US",
    "sg:address":"5519 Old Easton Rd",
    "sg:city":"Doylestown",
    "sg:classifiers":[
        {
            "category":"Sports & Exercise",
            "subcategory":"Bowling",
            "type":"Entertainment"
        }
    ],
    "sg:phone":"+1 215 766 8164",
    "sg:postcode":"18901",
    "sg:province":"PA",
    "wof:name":"Port A Bowl",
    "wof:placetype":"venue"
},
  "geometry": {"coordinates":[-75.143997,40.376301],"type":"Point"}
}