{
  "type": "Feature",
  "properties": {
    "iso:country":"US",
    "sg:address":"26 N 19th St",
    "sg:city":"Harrisburg",
    "sg:classifiers":[
        {
            "category":"Food & Beverages",
            "subcategory":"Groceries & Convenience Stores",
            "type":"Retail Goods"
        }
    ],
    "sg:phone":"+1 717 695 6665",
    "sg:postcode":"17103",
    "sg:province":"PA",
    "wof:name":"Mini Mart",
    "wof:placetype":"venue"
},
  "geometry": {"coordinates":[-76.861783,40.269033],"type":"Point"}
}