{
  "type": "Feature",
  "properties": {
    "iso:country":"US",
    "sg:address":"1000 Painters Dr",
    "sg:city":"Pittsburgh",
    "sg:classifiers":[
        {
            "category":"Building & Trades",
            "subcategory":"Construction",
            "type":"Services"
        }
    ],
    "sg:phone":"+1 412 835 3334",
    "sg:postcode":"15228",
    "sg:province":"PA",
    "sg:tags":[
        "painter"
    ],
    "wof:name":"Trotwood Painting",
    "wof:placetype":"venue"
},
  "geometry": {"coordinates":[-80.066726,40.362521],"type":"Point"}
}