{
  "type": "Feature",
  "properties": {
    "iso:country":"US",
    "sg:address":"6327 Tuscarawas Rd",
    "sg:city":"Industry",
    "sg:classifiers":[
        {
            "category":"Manufacturing",
            "subcategory":"Textiles",
            "type":"Manufacturing & Wholesale Goods"
        }
    ],
    "sg:phone":"+1   ",
    "sg:postcode":"15052",
    "sg:province":"PA",
    "sg:tags":[
        "mill",
        "fabric",
        "cotton"
    ],
    "wof:name":"Vista Alegre Alpaca Farm",
    "wof:placetype":"venue"
},
  "geometry": {"coordinates":[-80.474746,40.687497],"type":"Point"}
}