{
  "type": "Feature",
  "properties": {
    "addr:full":"247 Stahl Rd Harleysville PA 19438",
    "addr:housenumber":"247",
    "addr:postcode":"19438",
    "addr:street":"Stahl Rd",
    "iso:country":"US",
    "sg:address":"247 Stahl Rd",
    "sg:city":"Harleysville",
    "sg:classifiers":[
        {
            "category":"Retail",
            "subcategory":"Car Wash",
            "type":"Services"
        }
    ],
    "sg:phone":"+1   ",
    "sg:postcode":"19438",
    "sg:province":"PA",
    "sg:tags":[
        "carwash",
        "trade",
        "contractor"
    ],
    "wof:name":"New Wave Pressure Washing",
    "wof:placetype":"venue"
},
  "geometry": {"coordinates":[-75.37008,40.270115],"type":"Point"}
}