{
  "type": "Feature",
  "properties": {
    "iso:country":"US",
    "sg:address":"194 Tucker Rd",
    "sg:city":"Spring Mills",
    "sg:classifiers":[
        {
            "category":"Government",
            "subcategory":"Office",
            "type":"Public Place"
        }
    ],
    "sg:phone":"+1 814 364 9176",
    "sg:postcode":"16828",
    "sg:province":"PA",
    "sg:tags":[
        "village"
    ],
    "wof:name":"Potter Twp Adm",
    "wof:placetype":"venue"
},
  "geometry": {"coordinates":[-77.638958,40.811134],"type":"Point"}
}