{
  "type": "Feature",
  "properties": {
    "iso:country":"US",
    "sg:address":"310 N Centre St",
    "sg:city":"Pottsville",
    "sg:classifiers":[
        {
            "category":"Shopping",
            "subcategory":"Books",
            "type":"Retail Goods"
        }
    ],
    "sg:phone":"+1 570 622 2243",
    "sg:postcode":"17901",
    "sg:province":"PA",
    "sg:tags":[
        "dealer"
    ],
    "sg:website":"www.goodwillchristianbookstore.com",
    "wof:name":"Good-Will Book Store",
    "wof:placetype":"venue"
},
  "geometry": {"coordinates":[-76.196585,40.687063],"type":"Point"}
}