{
  "type": "Feature",
  "properties": {
    "addr:full":"608 Maple Ave Southampton PA 18966",
    "addr:housenumber":"608",
    "addr:postcode":"18966",
    "addr:street":"Maple Ave",
    "iso:country":"US",
    "sg:address":"608 Maple Ave",
    "sg:city":"Southampton",
    "sg:classifiers":[
        {
            "category":"Shopping",
            "subcategory":"Music",
            "type":"Retail Goods"
        }
    ],
    "sg:phone":"+1   ",
    "sg:postcode":"18966",
    "sg:province":"PA",
    "wof:name":"Anthem Records",
    "wof:placetype":"venue"
},
  "geometry": {"coordinates":[-75.034904,40.184259],"type":"Point"}
}