{
  "type": "Feature",
  "properties": {
    "addr:full":"1 Parkway Center Dr Pittsburgh PA 15220",
    "addr:housenumber":"1",
    "addr:postcode":"15220",
    "addr:street":"Parkway Center Dr",
    "iso:country":"US",
    "sg:address":"1 Parkway Center Dr",
    "sg:city":"Pittsburgh",
    "sg:classifiers":[
        {
            "category":"Real Estate",
            "subcategory":"Real Estate Services",
            "type":"Services"
        }
    ],
    "sg:phone":"+1   ",
    "sg:postcode":"15220",
    "sg:province":"PA",
    "sg:tags":[
        "abstract",
        "title"
    ],
    "wof:name":"P A Settlement Services Inc",
    "wof:placetype":"venue"
},
  "geometry": {"coordinates":[-80.04153599999999,40.425824],"type":"Point"}
}