{
  "type": "Feature",
  "properties": {
    "iso:country":"US",
    "sg:address":"2545 N 5th Street Hwy",
    "sg:city":"Reading",
    "sg:classifiers":[
        {
            "category":"Restaurant",
            "type":"Food & Drink"
        }
    ],
    "sg:phone":"+1   ",
    "sg:postcode":"19605",
    "sg:province":"PA",
    "sg:tags":[
        "eating"
    ],
    "wof:name":"Legends Inc",
    "wof:placetype":"venue"
},
  "geometry": {"coordinates":[-75.92670099999999,40.370443],"type":"Point"}
}