{
  "type": "Feature",
  "properties": {
    "addr:full":"1130 S Main St Bessemer PA 16112",
    "addr:housenumber":"1130",
    "addr:postcode":"16112",
    "addr:street":"S Main St",
    "iso:country":"US",
    "sg:address":"1130 S Main St",
    "sg:city":"Bessemer",
    "sg:phone":"+1   ",
    "sg:postcode":"16112",
    "sg:province":"PA",
    "sg:tags":[
        "farm",
        "corn",
        "soybean"
    ],
    "wof:name":"Marty Gwin",
    "wof:placetype":"venue"
},
  "geometry": {"coordinates":[-80.489687,40.954615],"type":"Point"}
}