{
  "type": "Feature",
  "properties": {
    "iso:country":"US",
    "sg:address":"237 Jefferson Rd",
    "sg:city":"Penn Hills",
    "sg:classifiers":[
        {
            "category":"Restaurant",
            "type":"Food & Drink"
        }
    ],
    "sg:phone":"+1 412 241 9779",
    "sg:postcode":"15235",
    "sg:province":"PA",
    "sg:tags":[
        "banquet",
        "rooms"
    ],
    "wof:name":"Penn Hebron Garden Club",
    "wof:placetype":"venue"
},
  "geometry": {"coordinates":[-79.82147500000001,40.462887],"type":"Point"}
}