{
  "type": "Feature",
  "properties": {
    "iso:country":"US",
    "sg:address":"1105 Boyce Rd",
    "sg:city":"Pittsburgh",
    "sg:classifiers":[
        {
            "category":"Banks & Credit Unions",
            "subcategory":"Bank",
            "type":"Services"
        }
    ],
    "sg:phone":"+1 412 854 1002",
    "sg:postcode":"15241",
    "sg:province":"PA",
    "sg:tags":[
        "loan"
    ],
    "wof:name":"Capital Alternatives Inc",
    "wof:placetype":"venue"
},
  "geometry": {"coordinates":[-80.107241,40.315231],"type":"Point"}
}