{
  "type": "Feature",
  "properties": {
    "iso:country":"US",
    "sg:address":"6460 Leechburg Rd",
    "sg:city":"Verona",
    "sg:classifiers":[
        {
            "category":"Real Estate",
            "subcategory":"Real Estate Services",
            "type":"Services"
        }
    ],
    "sg:phone":"+1 412 798 5589",
    "sg:postcode":"15147",
    "sg:province":"PA",
    "sg:tags":[
        "management"
    ],
    "wof:name":"Beechtree Commons",
    "wof:placetype":"venue"
},
  "geometry": {"coordinates":[-79.804375,40.486876],"type":"Point"}
}