{
  "type": "Feature",
  "properties": {
    "iso:country":"US",
    "sg:address":"1648 Hulmeville Rd",
    "sg:city":"Bensalem",
    "sg:classifiers":[
        {
            "category":"Shopping",
            "subcategory":"Tobacco",
            "type":"Retail Goods"
        },
        {
            "category":"Recreation",
            "type":"Entertainment"
        }
    ],
    "sg:phone":"+1 215 244 6005",
    "sg:postcode":"19020",
    "sg:province":"PA",
    "sg:tags":[
        "shop",
        "cigarette",
        "cigar"
    ],
    "wof:name":"Smoker's Express",
    "wof:placetype":"venue"
},
  "geometry": {"coordinates":[-74.958702,40.075199],"type":"Point"}
}