{
  "type": "Feature",
  "properties": {
    "addr:full":"2771 Baltimore Pike Gettysburg PA 17325",
    "addr:housenumber":"2771",
    "addr:postcode":"17325",
    "addr:street":"Baltimore Pike",
    "iso:country":"US",
    "sg:address":"2771 Baltimore Pike",
    "sg:city":"Gettysburg",
    "sg:classifiers":[
        {
            "category":"Wholesale",
            "subcategory":"Machinery & Supplies",
            "type":"Manufacturing & Wholesale Goods"
        }
    ],
    "sg:phone":"+1   ",
    "sg:postcode":"17325",
    "sg:province":"PA",
    "wof:name":"Silverado Equipment Sls & Svcs",
    "wof:placetype":"venue"
},
  "geometry": {"coordinates":[-77.17247999999999,39.781659],"type":"Point"}
}