{
  "type": "Feature",
  "properties": {
    "addr:full":"205 9th St Port Royal PA 17082",
    "addr:housenumber":"205",
    "addr:postcode":"17082",
    "addr:street":"9Th St",
    "iso:country":"US",
    "sg:address":"205 9th St",
    "sg:city":"Port Royal",
    "sg:classifiers":[
        {
            "category":"Restaurant",
            "type":"Food & Drink"
        }
    ],
    "sg:phone":"+1   ",
    "sg:postcode":"17082",
    "sg:province":"PA",
    "sg:tags":[
        "eating"
    ],
    "wof:name":"Pizza of Original Italian",
    "wof:placetype":"venue"
},
  "geometry": {"coordinates":[-77.393328,40.532703],"type":"Point"}
}