{
  "type": "Feature",
  "properties": {
    "iso:country":"US",
    "sg:address":"4606 Merchant Square Dr",
    "sg:city":"Lansdale",
    "sg:classifiers":[
        {
            "category":"Professional",
            "subcategory":"Computer Services",
            "type":"Services"
        }
    ],
    "sg:phone":"+1   ",
    "sg:postcode":"19446",
    "sg:province":"PA",
    "sg:tags":[
        "programing",
        "custom"
    ],
    "wof:name":"Voysest Alejandro",
    "wof:placetype":"venue"
},
  "geometry": {"coordinates":[-75.319823,40.260174],"type":"Point"}
}