{
  "type": "Feature",
  "properties": {
    "addr:full":"30 Giffin Dr Canonsburg PA 15317",
    "addr:housenumber":"30",
    "addr:postcode":"15317",
    "addr:street":"Giffin Dr",
    "iso:country":"US",
    "sg:address":"30 Giffin Dr",
    "sg:city":"Canonsburg",
    "sg:classifiers":[
        {
            "category":"Professional",
            "type":"Services"
        }
    ],
    "sg:phone":"+1 724 746 3278",
    "sg:postcode":"15317",
    "sg:province":"PA",
    "sg:tags":[
        "establishment"
    ],
    "wof:name":"Intermediate Unit One",
    "wof:placetype":"venue"
},
  "geometry": {"coordinates":[-80.166186,40.259669],"type":"Point"}
}