{
  "type": "Feature",
  "properties": {
    "iso:country":"US",
    "sg:address":"301 Black Bear Ln",
    "sg:city":"Harrisburg",
    "sg:classifiers":[
        {
            "category":"Building & Trades",
            "subcategory":"Construction",
            "type":"Services"
        }
    ],
    "sg:phone":"+1   ",
    "sg:postcode":"17112",
    "sg:province":"PA",
    "sg:tags":[
        "contractor"
    ],
    "wof:name":"Missy Plasic",
    "wof:placetype":"venue"
},
  "geometry": {"coordinates":[-76.81503499999999,40.382652],"type":"Point"}
}