{
  "type": "Feature",
  "properties": {
    "addr:full":"720 Morwood Rd Telford PA 18969",
    "addr:housenumber":"720",
    "addr:postcode":"18969",
    "addr:street":"Morwood Rd",
    "iso:country":"US",
    "sg:address":"720 Morwood Rd",
    "sg:city":"Telford",
    "sg:classifiers":[
        {
            "category":"Retail",
            "subcategory":"Car Wash",
            "type":"Services"
        }
    ],
    "sg:phone":"+1 215 723 5009",
    "sg:postcode":"18969",
    "sg:province":"PA",
    "wof:name":"Morwood Detailing",
    "wof:placetype":"venue"
},
  "geometry": {"coordinates":[-75.393416,40.314218],"type":"Point"}
}