{
  "type": "Feature",
  "properties": {
    "addr:full":"129 W Chelten Ave  Philadelphia PA 19144",
    "addr:housenumber":"129",
    "addr:postcode":"19144",
    "addr:street":"W Chelten Ave",
    "iso:country":"US",
    "sg:address":"129 W Chelten Ave ",
    "sg:city":"Philadelphia",
    "sg:classifiers":[
        {
            "category":"Restaurant",
            "type":"Food & Drink"
        }
    ],
    "sg:menulink":"http://www.allmenus.com/pa/philadelphia/288020-first-wok/menu/",
    "sg:phone":"+1 215 848 0618",
    "sg:postcode":"19144",
    "sg:province":"PA",
    "sg:tags":[
        "asian",
        "chinese"
    ],
    "wof:name":"First Wok",
    "wof:placetype":"venue"
},
  "geometry": {"coordinates":[-75.177452,40.033346],"type":"Point"}
}