{
  "type": "Feature",
  "properties": {
    "iso:country":"US",
    "sg:address":"103 New Haven Dr",
    "sg:city":"Lititz",
    "sg:classifiers":[
        {
            "category":"Building & Trades",
            "subcategory":"Construction",
            "type":"Services"
        }
    ],
    "sg:phone":"+1   ",
    "sg:postcode":"17543",
    "sg:province":"PA",
    "sg:tags":[
        "house"
    ],
    "wof:name":"Joe Minjock",
    "wof:placetype":"venue"
},
  "geometry": {"coordinates":[-76.29825200000001,40.138432],"type":"Point"}
}