{
  "type": "Feature",
  "properties": {
    "addr:full":"13521 Cambridge Springs Rd Edinboro PA 16412",
    "addr:housenumber":"13521",
    "addr:postcode":"16412",
    "addr:street":"Cambridge Springs Rd",
    "iso:country":"US",
    "sg:address":"13521 Cambridge Springs Rd",
    "sg:city":"Edinboro",
    "sg:classifiers":[
        {
            "category":"Wholesale",
            "subcategory":"Machinery & Supplies",
            "type":"Manufacturing & Wholesale Goods"
        }
    ],
    "sg:phone":"+1 814 734 1552",
    "sg:postcode":"16412",
    "sg:province":"PA",
    "sg:tags":[
        "farm",
        "equipment"
    ],
    "sg:website":"www.zahmandmatson.com",
    "wof:name":"Gallup & Tenhaken",
    "wof:placetype":"venue"
},
  "geometry": {"coordinates":[-80.117479,41.851334],"type":"Point"}
}