{
  "type": "Feature",
  "properties": {
    "iso:country":"US",
    "sg:address":"5907 Smithfield St",
    "sg:city":"Mckeesport",
    "sg:classifiers":[
        {
            "category":"Restaurant",
            "type":"Food & Drink"
        }
    ],
    "sg:phone":"+1 412 896 1637",
    "sg:postcode":"15135",
    "sg:province":"PA",
    "wof:name":"M And M's Diner",
    "wof:placetype":"venue"
},
  "geometry": {"coordinates":[-79.823358,40.312234],"type":"Point"}
}