{
  "type": "Feature",
  "properties": {
    "addr:full":"5110 Mine Rd Paradise PA 17562",
    "addr:housenumber":"5110",
    "addr:postcode":"17562",
    "addr:street":"Mine Rd",
    "iso:country":"US",
    "sg:address":"5110 Mine Rd",
    "sg:city":"Paradise",
    "sg:classifiers":[
        {
            "category":"Professional",
            "subcategory":"Advertising",
            "type":"Services"
        }
    ],
    "sg:phone":"+1 717 442 9895",
    "sg:postcode":"17562",
    "sg:province":"PA",
    "sg:tags":[
        "mailing",
        "shipping"
    ],
    "wof:name":"Paradise Promotional Svc",
    "wof:placetype":"venue"
},
  "geometry": {"coordinates":[-76.04201500000001,39.974933],"type":"Point"}
}