{
  "type": "Feature",
  "properties": {
    "iso:country":"US",
    "sg:address":"7535 Windsor Dr",
    "sg:city":"Allentown",
    "sg:classifiers":[
        {
            "category":"Insurance",
            "subcategory":"Insurance Agent",
            "type":"Services"
        }
    ],
    "sg:phone":"+1 610 706 0712",
    "sg:postcode":"18195",
    "sg:province":"PA",
    "wof:name":"Infinity Insurance Co",
    "wof:placetype":"venue"
},
  "geometry": {"coordinates":[-75.623516,40.584662],"type":"Point"}
}