{
  "type": "Feature",
  "properties": {
    "addr:full":"200 Stevens Dr Philadelphia PA 19113",
    "addr:housenumber":"200",
    "addr:postcode":"19113",
    "addr:street":"Stevens Dr",
    "iso:country":"US",
    "sg:address":"200 Stevens Dr",
    "sg:city":"Philadelphia",
    "sg:classifiers":[
        {
            "category":"Recreation",
            "type":"Entertainment"
        }
    ],
    "sg:phone":"+1   ",
    "sg:postcode":"19113",
    "sg:province":"PA",
    "sg:tags":[
        "ticket",
        "agency"
    ],
    "wof:name":"Ticketmaster",
    "wof:placetype":"venue"
},
  "geometry": {"coordinates":[-75.274942,39.866625],"type":"Point"}
}