{
  "type": "Feature",
  "properties": {
    "iso:country":"US",
    "sg:address":"4015 Gwynedd Dr",
    "sg:city":"Allison Park",
    "sg:classifiers":[
        {
            "category":"Professional",
            "subcategory":"Lawyer & Legal Services",
            "type":"Services"
        }
    ],
    "sg:phone":"+1 412 492 0726",
    "sg:postcode":"15101",
    "sg:province":"PA",
    "sg:tags":[
        "attorney"
    ],
    "wof:name":"Edward F Voelker Jr",
    "wof:placetype":"venue"
},
  "geometry": {"coordinates":[-79.951483,40.56361],"type":"Point"}
}