{
  "type": "Feature",
  "properties": {
    "iso:country":"US",
    "sg:address":"2317 S 5th Ave",
    "sg:city":"Lebanon",
    "sg:classifiers":[
        {
            "category":"Professional",
            "type":"Services"
        }
    ],
    "sg:phone":"+1   ",
    "sg:postcode":"17042",
    "sg:province":"PA",
    "wof:name":"Thomas F Rowe",
    "wof:placetype":"venue"
},
  "geometry": {"coordinates":[-76.34217200000001,40.309696],"type":"Point"}
}