{
  "type": "Feature",
  "properties": {
    "iso:country":"US",
    "sg:address":"116 Sterling Ave",
    "sg:city":"Houtzdale",
    "sg:classifiers":[
        {
            "category":"Government",
            "subcategory":"Office",
            "type":"Public Place"
        }
    ],
    "sg:phone":"+1 814 378 5739",
    "sg:postcode":"16651",
    "sg:province":"PA",
    "sg:tags":[
        "village"
    ],
    "wof:name":"Houtzdale Municipal Sewer Auth",
    "wof:placetype":"venue"
},
  "geometry": {"coordinates":[-78.341804,40.828561],"type":"Point"}
}