{
  "type": "Feature",
  "properties": {
    "iso:country":"US",
    "sg:address":"1854 N Center Ave",
    "sg:city":"Somerset",
    "sg:classifiers":[
        {
            "category":"Autos & Motor Vehicles",
            "subcategory":"Auto Supplies",
            "type":"Retail Goods"
        },
        {
            "category":"Wholesale",
            "subcategory":"Auto Parts",
            "type":"Manufacturing & Wholesale Goods"
        }
    ],
    "sg:phone":"+1 814 444 8240",
    "sg:postcode":"15501",
    "sg:province":"PA",
    "sg:tags":[
        "heavy",
        "automotive",
        "automobile",
        "equipment"
    ],
    "wof:name":"Edge Automotive Inc",
    "wof:placetype":"venue"
},
  "geometry": {"coordinates":[-79.075706,40.046782],"type":"Point"}
}