{
  "type": "Feature",
  "properties": {
    "iso:country":"US",
    "sg:address":"711 Hollow Rd",
    "sg:city":"Phoenixville",
    "sg:classifiers":[
        {
            "category":"Education",
            "subcategory":"School",
            "type":"Public Place"
        }
    ],
    "sg:phone":"+1 610 935 4400",
    "sg:postcode":"19460",
    "sg:province":"PA",
    "wof:name":"Chesterbrook Academy",
    "wof:placetype":"venue"
},
  "geometry": {"coordinates":[-75.488264,40.139937],"type":"Point"}
}