{
  "type": "Feature",
  "properties": {
    "iso:country":"US",
    "sg:address":"301 S Main St",
    "sg:city":"Doylestown",
    "sg:classifiers":[
        {
            "category":"Health Services",
            "subcategory":"Doctor",
            "type":"Services"
        }
    ],
    "sg:phone":"+1 215 348 4478",
    "sg:postcode":"18901",
    "sg:province":"PA",
    "sg:tags":[
        "medicine",
        "internal"
    ],
    "wof:name":"Brislin Donald M DO",
    "wof:placetype":"venue"
},
  "geometry": {"coordinates":[-75.128799,40.303902],"type":"Point"}
}