{
  "type": "Feature",
  "properties": {
    "addr:full":"600 E Broad St Souderton PA 18964",
    "addr:housenumber":"600",
    "addr:postcode":"18964",
    "addr:street":"E Broad St",
    "iso:country":"US",
    "sg:address":"600 E Broad St",
    "sg:city":"Souderton",
    "sg:classifiers":[
        {
            "category":"Real Estate",
            "subcategory":"Real Estate Services",
            "type":"Services"
        },
        {
            "category":"Real Estate",
            "subcategory":"Real Estate Agent",
            "type":"Services"
        }
    ],
    "sg:phone":"+1 215 723 9167",
    "sg:postcode":"18964",
    "sg:province":"PA",
    "sg:tags":[
        "buyer",
        "broker"
    ],
    "wof:name":"Hancock Realty",
    "wof:placetype":"venue"
},
  "geometry": {"coordinates":[-75.31353,40.313129],"type":"Point"}
}