{
  "type": "Feature",
  "properties": {
    "iso:country":"US",
    "sg:address":"837 Newville Rd",
    "sg:city":"Carlisle",
    "sg:classifiers":[
        {
            "category":"Professional",
            "subcategory":"Accounting & Tax Preparation",
            "type":"Services"
        }
    ],
    "sg:phone":"+1 717 245 0799",
    "sg:postcode":"17013",
    "sg:province":"PA",
    "sg:tags":[
        "accountant"
    ],
    "wof:name":"Galbraith's Accounting & Tax Service",
    "wof:placetype":"venue"
},
  "geometry": {"coordinates":[-77.212196,40.2033],"type":"Point"}
}