{
  "type": "Feature",
  "properties": {
    "iso:country":"US",
    "sg:address":"560A Evans City Rd",
    "sg:city":"Butler",
    "sg:classifiers":[
        {
            "category":"Insurance",
            "subcategory":"Insurance Agent",
            "type":"Services"
        },
        {
            "category":"Insurance",
            "subcategory":"Hazard Insurance",
            "type":"Services"
        },
        {
            "category":"Insurance",
            "subcategory":"Title Insurance",
            "type":"Services"
        },
        {
            "category":"Insurance",
            "subcategory":"Life Insurance",
            "type":"Services"
        }
    ],
    "sg:phone":"+1 724 482 2070",
    "sg:postcode":"16001",
    "sg:province":"PA",
    "sg:tags":[
        "business",
        "auto",
        "commercial",
        "homeowner",
        "motorcycle",
        "renter"
    ],
    "wof:name":"Allstate Insurance Company - Gerald Altmire",
    "wof:placetype":"venue"
},
  "geometry": {"coordinates":[-79.971451,40.860249],"type":"Point"}
}