{
  "type": "Feature",
  "properties": {
    "addr:full":"3731 Old York Rd Philadelphia PA 19140",
    "addr:housenumber":"3731",
    "addr:postcode":"19140",
    "addr:street":"Old York Rd",
    "iso:country":"US",
    "sg:address":"3731 Old York Rd",
    "sg:city":"Philadelphia",
    "sg:classifiers":[
        {
            "category":"Home & Garden",
            "subcategory":"Home Furnishings",
            "type":"Retail Goods"
        }
    ],
    "sg:phone":"+1 215 925 1716",
    "sg:postcode":"19140",
    "sg:province":"PA",
    "sg:tags":[
        "cover",
        "enclosure",
        "radiator"
    ],
    "wof:name":"Quaker City Radiator Enclosure",
    "wof:placetype":"venue"
},
  "geometry": {"coordinates":[-75.147603,40.008779],"type":"Point"}
}