{
  "type": "Feature",
  "properties": {
    "iso:country":"US",
    "sg:address":"542 Kimberton Rd",
    "sg:city":"Phoenixville",
    "sg:classifiers":[
        {
            "category":"Food & Beverages",
            "subcategory":"Groceries & Convenience Stores",
            "type":"Retail Goods"
        }
    ],
    "sg:phone":"+1   ",
    "sg:postcode":"19460",
    "sg:province":"PA",
    "wof:name":"Genuardis",
    "wof:placetype":"venue"
},
  "geometry": {"coordinates":[-75.5522,40.130045],"type":"Point"}
}