{
  "type": "Feature",
  "properties": {
    "addr:full":"945 Farelane Ct Harrisburg PA 17112",
    "addr:housenumber":"945",
    "addr:postcode":"17112",
    "addr:street":"Farelane Ct",
    "iso:country":"US",
    "sg:address":"945 Farelane Ct",
    "sg:city":"Harrisburg",
    "sg:classifiers":[
        {
            "category":"Wholesale",
            "subcategory":"Machinery & Supplies",
            "type":"Manufacturing & Wholesale Goods"
        }
    ],
    "sg:phone":"+1   ",
    "sg:postcode":"17112",
    "sg:province":"PA",
    "sg:tags":[
        "commercial",
        "container"
    ],
    "wof:name":"Atlantic Bag Company Inc",
    "wof:placetype":"venue"
},
  "geometry": {"coordinates":[-76.799626,40.336407],"type":"Point"}
}