{
  "type": "Feature",
  "properties": {
    "iso:country":"US",
    "sg:address":"5102 Germantown Ave",
    "sg:city":"Philadelphia",
    "sg:classifiers":[
        {
            "category":"Shopping",
            "subcategory":"Books",
            "type":"Retail Goods"
        }
    ],
    "sg:phone":"+1 215 848 4880",
    "sg:postcode":"19144",
    "sg:province":"PA",
    "sg:tags":[
        "bookstore"
    ],
    "wof:name":"Saadiq Books",
    "wof:placetype":"venue"
},
  "geometry": {"coordinates":[-75.165604,40.030399],"type":"Point"}
}