{
  "type": "Feature",
  "properties": {
    "iso:country":"US",
    "sg:address":"63 Heather Ct",
    "sg:city":"Newtown",
    "sg:classifiers":[
        {
            "category":"Education",
            "subcategory":"Dance Studio",
            "type":"Public Place"
        }
    ],
    "sg:phone":"+1 215 357 7402",
    "sg:postcode":"18940",
    "sg:province":"PA",
    "sg:tags":[
        "instruction",
        "dancing"
    ],
    "wof:name":"B C Discoveries Theater Arts",
    "wof:placetype":"venue"
},
  "geometry": {"coordinates":[-74.942734,40.219352],"type":"Point"}
}