{
  "type": "Feature",
  "properties": {
    "addr:full":"6565 Penn Ave Pittsburgh PA 15206",
    "addr:housenumber":"6565",
    "addr:postcode":"15206",
    "addr:street":"Penn Ave",
    "iso:country":"US",
    "sg:address":"6565 Penn Ave",
    "sg:city":"Pittsburgh",
    "sg:classifiers":[
        {
            "category":"Professional",
            "subcategory":"Computer Services",
            "type":"Services"
        }
    ],
    "sg:phone":"+1   ",
    "sg:postcode":"15206",
    "sg:province":"PA",
    "sg:tags":[
        "system",
        "integration"
    ],
    "wof:name":"MSA Pass",
    "wof:placetype":"venue"
},
  "geometry": {"coordinates":[-79.91325500000001,40.45475],"type":"Point"}
}