{
  "type": "Feature",
  "properties": {
    "iso:country":"US",
    "sg:address":"450 Sunrise Ave",
    "sg:city":"Honesdale",
    "sg:classifiers":[
        {
            "category":"Shopping",
            "subcategory":"Jewelry",
            "type":"Retail Goods"
        }
    ],
    "sg:phone":"+1   ",
    "sg:postcode":"18431",
    "sg:province":"PA",
    "sg:tags":[
        "silverware"
    ],
    "wof:name":"Rothrocks",
    "wof:placetype":"venue"
},
  "geometry": {"coordinates":[-75.249303,41.553481],"type":"Point"}
}