{
  "type": "Feature",
  "properties": {
    "addr:full":"2400 W Main St Norristown PA 19403",
    "addr:housenumber":"2400",
    "addr:postcode":"19403",
    "addr:street":"W Main St",
    "iso:country":"US",
    "sg:address":"2400 W Main St",
    "sg:city":"Norristown",
    "sg:classifiers":[
        {
            "category":"Arena",
            "subcategory":"Sports Club",
            "type":"Entertainment"
        },
        {
            "category":"Sports & Exercise",
            "subcategory":"Sports Center",
            "type":"Entertainment"
        },
        {
            "category":"Sports & Exercise",
            "subcategory":"Golf",
            "type":"Entertainment"
        }
    ],
    "sg:phone":"+1 610 539 0422",
    "sg:postcode":"19403",
    "sg:province":"PA",
    "sg:tags":[
        "course"
    ],
    "sg:website":"http://www.westnorritontwp.org",
    "wof:name":"Jeffersonville Golf Club",
    "wof:placetype":"venue"
},
  "geometry": {"coordinates":[-75.3853,40.139],"type":"Point"}
}