{
  "type": "Feature",
  "properties": {
    "iso:country":"US",
    "sg:address":"1701 S 25th St",
    "sg:city":"Philadelphia",
    "sg:phone":"+1 215 334 2415",
    "sg:postcode":"19145",
    "sg:province":"PA",
    "sg:tags":[
        "oil"
    ],
    "wof:name":"Argentieri Fuels",
    "wof:placetype":"venue"
},
  "geometry": {"coordinates":[-75.187027,39.930381],"type":"Point"}
}