{
  "type": "Feature",
  "properties": {
    "addr:full":"550 Moslem Springs Rd Shoemakersville PA 19555",
    "addr:housenumber":"550",
    "addr:postcode":"19555",
    "addr:street":"Moslem Springs Rd",
    "iso:country":"US",
    "sg:address":"550 Moslem Springs Rd",
    "sg:city":"Shoemakersville",
    "sg:classifiers":[
        {
            "category":"Freight",
            "type":"Transportation"
        }
    ],
    "sg:phone":"+1   ",
    "sg:postcode":"19555",
    "sg:province":"PA",
    "sg:tags":[
        "operator",
        "local",
        "trucking"
    ],
    "wof:name":"Balatgek Jf Trucking Inc",
    "wof:placetype":"venue"
},
  "geometry": {"coordinates":[-75.94722,40.507552],"type":"Point"}
}