{
  "type": "Feature",
  "properties": {
    "iso:country":"US",
    "sg:address":"1075 Union Meeting Rd",
    "sg:city":"Blue Bell",
    "sg:classifiers":[
        {
            "category":"Professional",
            "type":"Services"
        }
    ],
    "sg:phone":"+1   ",
    "sg:postcode":"19422",
    "sg:province":"PA",
    "wof:name":"Jack Family Inc",
    "wof:placetype":"venue"
},
  "geometry": {"coordinates":[-75.278965,40.15552],"type":"Point"}
}