{
  "type": "Feature",
  "properties": {
    "iso:country":"US",
    "sg:address":"825 Western Ave",
    "sg:city":"Jeannette",
    "sg:classifiers":[
        {
            "category":"Building & Trades",
            "subcategory":"Construction",
            "type":"Services"
        }
    ],
    "sg:phone":"+1   ",
    "sg:postcode":"15644",
    "sg:province":"PA",
    "sg:tags":[
        "remodeling",
        "contractor"
    ],
    "wof:name":"Pilkington Construction",
    "wof:placetype":"venue"
},
  "geometry": {"coordinates":[-79.624529,40.322463],"type":"Point"}
}