{
  "type": "Feature",
  "properties": {
    "iso:country":"US",
    "sg:address":"325 Gribbell Rd",
    "sg:city":"Wyncote",
    "sg:classifiers":[
        {
            "category":"Health Services",
            "subcategory":"Doctor",
            "type":"Services"
        }
    ],
    "sg:phone":"+1   ",
    "sg:postcode":"19095",
    "sg:province":"PA",
    "sg:tags":[
        "medical"
    ],
    "wof:name":"Leonard F Greenburg MD PC",
    "wof:placetype":"venue"
},
  "geometry": {"coordinates":[-75.15611199999999,40.090626],"type":"Point"}
}