{
  "type": "Feature",
  "properties": {
    "iso:country":"US",
    "sg:address":"2835 Eagleville Rd",
    "sg:city":"Norristown",
    "sg:classifiers":[
        {
            "category":"Retail",
            "subcategory":"Portrait Studio",
            "type":"Services"
        }
    ],
    "sg:phone":"+1 610 650 0521",
    "sg:postcode":"19403",
    "sg:province":"PA",
    "sg:tags":[
        "photo"
    ],
    "wof:name":"Christopher Kimble Photography",
    "wof:placetype":"venue"
},
  "geometry": {"coordinates":[-75.427015,40.135143],"type":"Point"}
}