{
  "type": "Feature",
  "properties": {
    "addr:full":"1080 Edgewood Rd Morrisville PA 19067",
    "addr:housenumber":"1080",
    "addr:postcode":"19067",
    "addr:street":"Edgewood Rd",
    "iso:country":"US",
    "sg:address":"1080 Edgewood Rd",
    "sg:city":"Morrisville",
    "sg:classifiers":[
        {
            "category":"Education",
            "subcategory":"Library",
            "type":"Public Place"
        }
    ],
    "sg:phone":"+1   ",
    "sg:postcode":"19067",
    "sg:province":"PA",
    "sg:tags":[
        "executive"
    ],
    "wof:name":"Yardley Makefield Branch Lib",
    "wof:placetype":"venue"
},
  "geometry": {"coordinates":[-74.836128,40.224287],"type":"Point"}
}