{
  "type": "Feature",
  "properties": {
    "addr:full":"1530 N 11th St Philadelphia PA 19122",
    "addr:housenumber":"1530",
    "addr:postcode":"19122",
    "addr:street":"N 11Th St",
    "iso:country":"US",
    "sg:address":"1530 N 11th St",
    "sg:city":"Philadelphia",
    "sg:classifiers":[
        {
            "category":"Social Services",
            "subcategory":"Child Care",
            "type":"Services"
        }
    ],
    "sg:phone":"+1 215 684 2198",
    "sg:postcode":"19122",
    "sg:province":"PA",
    "sg:tags":[
        "day"
    ],
    "wof:name":"Mt Zion United Methodist Church",
    "wof:placetype":"venue"
},
  "geometry": {"coordinates":[-75.152901,39.975601],"type":"Point"}
}