{
  "type": "Feature",
  "properties": {
    "addr:full":"138 York Rd Warminster PA 18974",
    "addr:housenumber":"138",
    "addr:postcode":"18974",
    "addr:street":"York Rd",
    "iso:country":"US",
    "sg:address":"138 York Rd",
    "sg:city":"Warminster",
    "sg:classifiers":[
        {
            "category":"Personal",
            "subcategory":"Barber",
            "type":"Services"
        }
    ],
    "sg:phone":"+1 215 675 0167",
    "sg:postcode":"18974",
    "sg:province":"PA",
    "wof:name":"Dan's Barber Shop",
    "wof:placetype":"venue"
},
  "geometry": {"coordinates":[-75.10271,40.192094],"type":"Point"}
}