{
  "type": "Feature",
  "properties": {
    "addr:full":"2305 State Rte 29 Tunkhannock PA 18657",
    "addr:housenumber":"2305",
    "addr:postcode":"18657",
    "addr:street":"State Rte 29",
    "iso:country":"US",
    "sg:address":"2305 State Rte 29",
    "sg:city":"Tunkhannock",
    "sg:classifiers":[
        {
            "category":"Farming",
            "subcategory":"Dairy Farm",
            "type":"Manufacturing & Wholesale Goods"
        }
    ],
    "sg:phone":"+1   ",
    "sg:postcode":"18657",
    "sg:province":"PA",
    "wof:name":"Travers Dairy Farm",
    "wof:placetype":"venue"
},
  "geometry": {"coordinates":[-76.0424,41.421739],"type":"Point"}
}