{
  "type": "Feature",
  "properties": {
    "addr:full":"1652 Walton St Philipsburg PA 16866",
    "addr:housenumber":"1652",
    "addr:postcode":"16866",
    "addr:street":"Walton St",
    "iso:country":"US",
    "sg:address":"1652 Walton St",
    "sg:city":"Philipsburg",
    "sg:classifiers":[
        {
            "category":"Manufacturing",
            "subcategory":"Tools & Machinery",
            "type":"Manufacturing & Wholesale Goods"
        }
    ],
    "sg:phone":"+1   ",
    "sg:postcode":"16866",
    "sg:province":"PA",
    "sg:tags":[
        "field",
        "mfg"
    ],
    "wof:name":"Walter Ondrizek",
    "wof:placetype":"venue"
},
  "geometry": {"coordinates":[-78.238699,40.884225],"type":"Point"}
}