{
  "type": "Feature",
  "properties": {
    "addr:full":"417 Wingate Rd Huntingdon Valley PA 19006",
    "addr:housenumber":"417",
    "addr:postcode":"19006",
    "addr:street":"Wingate Rd",
    "iso:country":"US",
    "sg:address":"417 Wingate Rd",
    "sg:city":"Huntingdon Valley",
    "sg:classifiers":[
        {
            "category":"Shopping",
            "type":"Retail Goods"
        }
    ],
    "sg:phone":"+1   ",
    "sg:postcode":"19006",
    "sg:province":"PA",
    "sg:tags":[
        "equipment",
        "telephone",
        "cellular"
    ],
    "wof:name":"Priority Wireless Products LLC",
    "wof:placetype":"venue"
},
  "geometry": {"coordinates":[-75.08463399999999,40.095724],"type":"Point"}
}