{
  "type": "Feature",
  "properties": {
    "addr:full":"7 S Main St Wilkes Barre PA 18701",
    "addr:housenumber":"7",
    "addr:postcode":"18701",
    "addr:street":"S Main St",
    "iso:country":"US",
    "sg:address":"7 S Main St",
    "sg:city":"Wilkes Barre",
    "sg:classifiers":[
        {
            "category":"Banks & Credit Unions",
            "subcategory":"Financial Services",
            "type":"Services"
        }
    ],
    "sg:phone":"+1 570 408 9861",
    "sg:postcode":"18701",
    "sg:province":"PA",
    "sg:tags":[
        "company",
        "holding"
    ],
    "wof:name":"KBJ Holdings LLC",
    "wof:placetype":"venue"
},
  "geometry": {"coordinates":[-75.8848,41.244362],"type":"Point"}
}