{
  "type": "Feature",
  "properties": {
    "iso:country":"US",
    "sg:address":"3049 Sussex Ave",
    "sg:city":"Pittsburgh",
    "sg:classifiers":[
        {
            "category":"Retail",
            "subcategory":"Auto Rental",
            "type":"Services"
        }
    ],
    "sg:phone":"+1   ",
    "sg:postcode":"15226",
    "sg:province":"PA",
    "sg:tags":[
        "automobile"
    ],
    "wof:name":"Enterprise Rent-A-Car",
    "wof:placetype":"venue"
},
  "geometry": {"coordinates":[-80.0158,40.384434],"type":"Point"}
}