{
  "type": "Feature",
  "properties": {
    "iso:country":"US",
    "sg:address":"4910 Shasta Way",
    "sg:city":"Mechanicsburg",
    "sg:classifiers":[
        {
            "category":"Arts & Performance",
            "subcategory":"Theater",
            "type":"Entertainment"
        }
    ],
    "sg:phone":"+1 717 566 6669",
    "sg:postcode":"17050",
    "sg:province":"PA",
    "sg:tags":[
        "magician"
    ],
    "wof:name":"Clown Hotline",
    "wof:placetype":"venue"
},
  "geometry": {"coordinates":[-76.967615,40.245689],"type":"Point"}
}