{
  "type": "Feature",
  "properties": {
    "iso:country":"US",
    "sg:address":"157 W Turner St",
    "sg:city":"Allentown",
    "sg:classifiers":[
        {
            "category":"Organizations",
            "subcategory":"Religious Organization",
            "type":"Services"
        }
    ],
    "sg:phone":"+1 610 439 4995",
    "sg:postcode":"18102",
    "sg:province":"PA",
    "sg:tags":[
        "church"
    ],
    "wof:name":"First Spanish Free Methodist",
    "wof:placetype":"venue"
},
  "geometry": {"coordinates":[-75.46035999999999,40.608621],"type":"Point"}
}