{
  "type": "Feature",
  "properties": {
    "iso:country":"US",
    "sg:address":"216 Crescent Gardens Dr",
    "sg:city":"Pittsburgh",
    "sg:classifiers":[
        {
            "category":"Professional",
            "subcategory":"Management & Consulting",
            "type":"Services"
        }
    ],
    "sg:phone":"+1   ",
    "sg:postcode":"15235",
    "sg:province":"PA",
    "wof:name":"To Envision Inc",
    "wof:placetype":"venue"
},
  "geometry": {"coordinates":[-79.805817,40.471386],"type":"Point"}
}