{
  "type": "Feature",
  "properties": {
    "iso:country":"US",
    "sg:address":"52 S 9th St",
    "sg:city":"Indiana",
    "sg:classifiers":[
        {
            "category":"Professional",
            "subcategory":"Lawyer & Legal Services",
            "type":"Services"
        }
    ],
    "sg:phone":"+1 724 357 9990",
    "sg:postcode":"15701",
    "sg:province":"PA",
    "wof:name":"Tomb Mack & Kauffman",
    "wof:placetype":"venue"
},
  "geometry": {"coordinates":[-79.155968,40.622044],"type":"Point"}
}