{
  "type": "Feature",
  "properties": {
    "iso:country":"US",
    "sg:address":"2403 Rutledge Rd",
    "sg:city":"Transfer",
    "sg:classifiers":[
        {
            "category":"Manufacturing",
            "subcategory":"Tools & Machinery",
            "type":"Manufacturing & Wholesale Goods"
        }
    ],
    "sg:phone":"+1 724 646 4023",
    "sg:postcode":"16154",
    "sg:province":"PA",
    "sg:tags":[
        "mfg"
    ],
    "wof:name":"21st Century Crane Control",
    "wof:placetype":"venue"
},
  "geometry": {"coordinates":[-80.469554,41.341249],"type":"Point"}
}