{
  "type": "Feature",
  "properties": {
    "addr:full":"15 Public Sq Wilkes Barre PA 18701",
    "addr:housenumber":"15",
    "addr:postcode":"18701",
    "addr:street":"Public Sq",
    "iso:country":"US",
    "sg:address":"15 Public Sq",
    "sg:city":"Wilkes Barre",
    "sg:classifiers":[
        {
            "category":"Professional",
            "subcategory":"Lawyer & Legal Services",
            "type":"Services"
        }
    ],
    "sg:phone":"+1 570 820 9800",
    "sg:postcode":"18701",
    "sg:province":"PA",
    "sg:tags":[
        "attorney"
    ],
    "wof:name":"Silverblatt & Assoc",
    "wof:placetype":"venue"
},
  "geometry": {"coordinates":[-75.88251099999999,41.245878],"type":"Point"}
}