{
  "type": "Feature",
  "properties": {
    "addr:full":"900 Spruce St Reading PA 19602",
    "addr:housenumber":"900",
    "addr:postcode":"19602",
    "addr:street":"Spruce St",
    "iso:country":"US",
    "sg:address":"900 Spruce St",
    "sg:city":"Reading",
    "sg:classifiers":[
        {
            "category":"Organizations",
            "subcategory":"Professional Association",
            "type":"Services"
        }
    ],
    "sg:phone":"+1 610 373 8713",
    "sg:postcode":"19602",
    "sg:province":"PA",
    "wof:name":"Polish American Citizens Assn",
    "wof:placetype":"venue"
},
  "geometry": {"coordinates":[-75.919715,40.330565],"type":"Point"}
}