{
  "type": "Feature",
  "properties": {
    "iso:country":"US",
    "sg:address":"25 Water St",
    "sg:city":"Oley",
    "sg:classifiers":[
        {
            "category":"Professional",
            "subcategory":"Business Services",
            "type":"Services"
        }
    ],
    "sg:phone":"+1 610 987 6446",
    "sg:postcode":"19547",
    "sg:province":"PA",
    "sg:tags":[
        "auctioneer"
    ],
    "wof:name":"Hauseman's Auctions",
    "wof:placetype":"venue"
},
  "geometry": {"coordinates":[-75.792868,40.390753],"type":"Point"}
}