{
  "type": "Feature",
  "properties": {
    "iso:country":"US",
    "sg:address":"250 Freeport Rd",
    "sg:city":"New Kensington",
    "sg:classifiers":[
        {
            "category":"Social Services",
            "subcategory":"Child Care",
            "type":"Services"
        }
    ],
    "sg:phone":"+1   ",
    "sg:postcode":"15068",
    "sg:province":"PA",
    "sg:tags":[
        "day"
    ],
    "wof:name":"Tiny Town",
    "wof:placetype":"venue"
},
  "geometry": {"coordinates":[-79.760221,40.566169],"type":"Point"}
}