{
  "type": "Feature",
  "properties": {
    "iso:country":"US",
    "sg:address":"107 Joyce Dr",
    "sg:city":"Moosic",
    "sg:classifiers":[
        {
            "category":"Health Services",
            "subcategory":"Doctor",
            "type":"Services"
        }
    ],
    "sg:phone":"+1 570 496 6457",
    "sg:postcode":"18507",
    "sg:province":"PA",
    "sg:tags":[
        "physician",
        "surgeon"
    ],
    "wof:name":"Michael J Rainey Do Physician",
    "wof:placetype":"venue"
},
  "geometry": {"coordinates":[-75.698261,41.350517],"type":"Point"}
}