{
  "type": "Feature",
  "properties": {
    "iso:country":"US",
    "sg:address":"16953 Linesville Rd",
    "sg:city":"Linesville",
    "sg:classifiers":[
        {
            "category":"Building & Trades",
            "subcategory":"Construction",
            "type":"Services"
        }
    ],
    "sg:phone":"+1   ",
    "sg:postcode":"16424",
    "sg:province":"PA",
    "sg:tags":[
        "house"
    ],
    "wof:name":"Albert I Moss Contracting",
    "wof:placetype":"venue"
},
  "geometry": {"coordinates":[-80.411267,41.71074],"type":"Point"}
}