{
  "type": "Feature",
  "properties": {
    "addr:full":"9435 Lincoln Hwy Irwin PA 15642",
    "addr:housenumber":"9435",
    "addr:postcode":"15642",
    "addr:street":"Lincoln Hwy",
    "iso:country":"US",
    "sg:address":"9435 Lincoln Hwy",
    "sg:city":"Irwin",
    "sg:classifiers":[
        {
            "category":"Retail",
            "subcategory":"Auto Repair",
            "type":"Services"
        }
    ],
    "sg:phone":"+1   ",
    "sg:postcode":"15642",
    "sg:province":"PA",
    "sg:tags":[
        "exhaust"
    ],
    "wof:name":"Monro Muffler Brake",
    "wof:placetype":"venue"
},
  "geometry": {"coordinates":[-79.695958,40.322099],"type":"Point"}
}