{
  "type": "Feature",
  "properties": {
    "iso:country":"US",
    "sg:address":"82 Long Pond Rd",
    "sg:city":"Long Pond",
    "sg:classifiers":[
        {
            "category":"Building & Trades",
            "subcategory":"Construction",
            "type":"Services"
        }
    ],
    "sg:phone":"+1   ",
    "sg:postcode":"18334",
    "sg:province":"PA",
    "sg:tags":[
        "house"
    ],
    "wof:name":"Holywood Remodeling",
    "wof:placetype":"venue"
},
  "geometry": {"coordinates":[-75.43202700000001,41.076005],"type":"Point"}
}