{
  "type": "Feature",
  "properties": {
    "iso:country":"US",
    "sg:address":"246 N Courtland St",
    "sg:city":"East Stroudsburg",
    "sg:classifiers":[
        {
            "category":"Personal",
            "subcategory":"Beauty Salon",
            "type":"Services"
        }
    ],
    "sg:phone":"+1   ",
    "sg:postcode":"18301",
    "sg:province":"PA",
    "sg:tags":[
        "shop"
    ],
    "wof:name":"Hair Hair Hair Minded",
    "wof:placetype":"venue"
},
  "geometry": {"coordinates":[-75.183982,41.005524],"type":"Point"}
}