{
  "type": "Feature",
  "properties": {
    "iso:country":"US",
    "sg:address":"12 Allegheny Sq",
    "sg:city":"Glassport",
    "sg:classifiers":[
        {
            "category":"Manufacturing",
            "subcategory":"Metals",
            "type":"Manufacturing & Wholesale Goods"
        }
    ],
    "sg:phone":"+1 412 673 4700",
    "sg:postcode":"15045",
    "sg:province":"PA",
    "sg:tags":[
        "foundry"
    ],
    "wof:name":"Laurel Aluminum Castings",
    "wof:placetype":"venue"
},
  "geometry": {"coordinates":[-79.892366,40.320873],"type":"Point"}
}