{
  "type": "Feature",
  "properties": {
    "iso:country":"US",
    "sg:address":"1000 Ross Park Mall Dr",
    "sg:city":"Pittsburgh",
    "sg:classifiers":[
        {
            "category":"Shopping",
            "subcategory":"Clothing, Apparel, & Fashions",
            "type":"Retail Goods"
        }
    ],
    "sg:phone":"+1 412 369 4951",
    "sg:postcode":"15237",
    "sg:province":"PA",
    "sg:tags":[
        "high",
        "dress",
        "sportswear"
    ],
    "wof:name":"Cache",
    "wof:placetype":"venue"
},
  "geometry": {"coordinates":[-80.00662,40.54071],"type":"Point"}
}