{
  "type": "Feature",
  "properties": {
    "addr:full":"12 Gold Star Hwy Shenandoah PA 17976",
    "addr:housenumber":"12",
    "addr:postcode":"17976",
    "addr:street":"Gold Star Hwy",
    "iso:country":"US",
    "sg:address":"12 Gold Star Hwy",
    "sg:city":"Shenandoah",
    "sg:classifiers":[
        {
            "category":"Shopping",
            "subcategory":"Discount & Variety Stores",
            "type":"Retail Goods"
        }
    ],
    "sg:phone":"+1 570 462 3226",
    "sg:postcode":"17976",
    "sg:province":"PA",
    "wof:name":"Dollar General",
    "wof:placetype":"venue"
},
  "geometry": {"coordinates":[-76.20126399999999,40.82037],"type":"Point"}
}