{
  "type": "Feature",
  "properties": {
    "addr:full":"5165 Imperial Pkwy Girard PA 16417",
    "addr:housenumber":"5165",
    "addr:postcode":"16417",
    "addr:street":"Imperial Pkwy",
    "iso:country":"US",
    "sg:address":"5165 Imperial Pkwy",
    "sg:city":"Girard",
    "sg:classifiers":[
        {
            "category":"Health Services",
            "subcategory":"Doctor",
            "type":"Services"
        }
    ],
    "sg:phone":"+1 814 774 3128",
    "sg:postcode":"16417",
    "sg:province":"PA",
    "sg:tags":[
        "physician",
        "family",
        "practice",
        "surgeons",
        "medicine",
        "surgeon"
    ],
    "wof:name":"Hilbert Wes MD",
    "wof:placetype":"venue"
},
  "geometry": {"coordinates":[-80.300364,42.008485],"type":"Point"}
}