{
  "type": "Feature",
  "properties": {
    "iso:country":"US",
    "sg:address":"5550 Belmar Ter",
    "sg:city":"Philadelphia",
    "sg:classifiers":[
        {
            "category":"Professional",
            "subcategory":"Business Services",
            "type":"Services"
        }
    ],
    "sg:phone":"+1 267 992 3054",
    "sg:postcode":"19143",
    "sg:province":"PA",
    "sg:tags":[
        "consultant",
        "coach"
    ],
    "wof:name":"Oasis Global Ventures & Solutions International",
    "wof:placetype":"venue"
},
  "geometry": {"coordinates":[-75.226641,39.939655],"type":"Point"}
}