{
  "type": "Feature",
  "properties": {
    "iso:country":"US",
    "sg:address":"421 N 7th St Fl 3",
    "sg:city":"Philadelphia",
    "sg:classifiers":[
        {
            "category":"Professional",
            "subcategory":"Detective & Security Services",
            "type":"Services"
        }
    ],
    "sg:phone":"+1 215 625 3611",
    "sg:postcode":"19123",
    "sg:province":"PA",
    "sg:tags":[
        "bodyguard",
        "patrol",
        "guard"
    ],
    "sg:website":"http://www.ravsecurity.com",
    "wof:name":"Rav Investigative & Securities Services Ltd",
    "wof:placetype":"venue"
},
  "geometry": {"coordinates":[-75.150306,39.958937],"type":"Point"}
}