{
  "type": "Feature",
  "properties": {
    "addr:full":"970 York St Hanover PA 17331",
    "addr:housenumber":"970",
    "addr:postcode":"17331",
    "addr:street":"York St",
    "iso:country":"US",
    "sg:address":"970 York St",
    "sg:city":"Hanover",
    "sg:classifiers":[
        {
            "category":"Insurance",
            "subcategory":"Insurance Agent",
            "type":"Services"
        }
    ],
    "sg:phone":"+1 717 637 1054",
    "sg:postcode":"17331",
    "sg:province":"PA",
    "wof:name":"Harry Dusman Insurance Agency",
    "wof:placetype":"venue"
},
  "geometry": {"coordinates":[-76.95622899999999,39.800965],"type":"Point"}
}