{
  "type": "Feature",
  "properties": {
    "addr:full":"654 Riverview Ct York PA 17406",
    "addr:housenumber":"654",
    "addr:postcode":"17406",
    "addr:street":"Riverview Ct",
    "iso:country":"US",
    "sg:address":"654 Riverview Ct",
    "sg:city":"York",
    "sg:classifiers":[
        {
            "category":"Manufacturing",
            "subcategory":"Jewelry",
            "type":"Manufacturing & Wholesale Goods"
        }
    ],
    "sg:phone":"+1   ",
    "sg:postcode":"17406",
    "sg:province":"PA",
    "sg:tags":[
        "material",
        "mfg"
    ],
    "wof:name":"Marinak Lapidary & More",
    "wof:placetype":"venue"
},
  "geometry": {"coordinates":[-76.607505,40.018103],"type":"Point"}
}