{
  "type": "Feature",
  "properties": {
    "iso:country":"US",
    "sg:address":"1106 Reedsdale St",
    "sg:city":"Pittsburgh",
    "sg:classifiers":[
        {
            "category":"Shopping",
            "subcategory":"Beauty & Cosmetics",
            "type":"Retail Goods"
        },
        {
            "category":"Personal",
            "subcategory":"Beauty Salon",
            "type":"Services"
        }
    ],
    "sg:phone":"+1 412 325 1030",
    "sg:postcode":"15233",
    "sg:province":"PA",
    "sg:tags":[
        "perfume",
        "cosmetics-wholesale",
        "manufacturer"
    ],
    "wof:name":"Reedsdale Sales Corporation",
    "wof:placetype":"venue"
},
  "geometry": {"coordinates":[-80.018716,40.447863],"type":"Point"}
}