{
  "type": "Feature",
  "properties": {
    "iso:country":"US",
    "sg:address":"503 Washington Ave Fl 1",
    "sg:city":"Newtown",
    "sg:classifiers":[
        {
            "category":"Professional",
            "subcategory":"Management & Consulting",
            "type":"Services"
        },
        {
            "category":"Professional",
            "subcategory":"Advertising",
            "type":"Services"
        }
    ],
    "sg:phone":"+1 215 497 9699",
    "sg:postcode":"18940",
    "sg:province":"PA",
    "sg:tags":[
        "marketing",
        "program",
        "consultant"
    ],
    "sg:website":"http://www.pharmagenesis.com",
    "wof:name":"Pharmagenesis",
    "wof:placetype":"venue"
},
  "geometry": {"coordinates":[-74.92878,40.228931],"type":"Point"}
}