{
  "type": "Feature",
  "properties": {
    "iso:country":"US",
    "sg:address":"408 S Highlander Heights Dr",
    "sg:city":"Glenshaw",
    "sg:classifiers":[
        {
            "category":"Utilities",
            "subcategory":"Telephone",
            "type":"Services"
        }
    ],
    "sg:phone":"+1 412 486 2620",
    "sg:postcode":"15116",
    "sg:province":"PA",
    "sg:tags":[
        "telecommunication"
    ],
    "wof:name":"Corporate Cost Controls Inc",
    "wof:placetype":"venue"
},
  "geometry": {"coordinates":[-79.939334,40.534675],"type":"Point"}
}