{
  "type": "Feature",
  "properties": {
    "iso:country":"US",
    "sg:address":"133 Heather Rd",
    "sg:city":"Bala Cynwyd",
    "sg:classifiers":[
        {
            "category":"Arts & Performance",
            "subcategory":"Arts Center",
            "type":"Entertainment"
        }
    ],
    "sg:phone":"+1 610 667 9230",
    "sg:postcode":"19004",
    "sg:province":"PA",
    "sg:tags":[
        "performing"
    ],
    "sg:website":"www.theatreariel.com",
    "wof:name":"Theatre Ariel",
    "wof:placetype":"venue"
},
  "geometry": {"coordinates":[-75.23269000000001,40.004161],"type":"Point"}
}