{
  "type": "Feature",
  "properties": {
    "iso:country":"US",
    "sg:address":"2200 Murray Ave",
    "sg:city":"Pittsburgh",
    "sg:classifiers":[
        {
            "category":"Professional",
            "subcategory":"Lawyer & Legal Services",
            "type":"Services"
        }
    ],
    "sg:phone":"+1 412 521 2732",
    "sg:postcode":"15217",
    "sg:province":"PA",
    "sg:tags":[
        "attorney"
    ],
    "sg:website":"www.rothira-advisor.com",
    "wof:name":"James Lange Law Offices",
    "wof:placetype":"venue"
},
  "geometry": {"coordinates":[-79.92322900000001,40.431712],"type":"Point"}
}