{
  "type": "Feature",
  "properties": {
    "addr:full":"6092 Thompson Rd Stewartstown PA 17363",
    "addr:housenumber":"6092",
    "addr:postcode":"17363",
    "addr:street":"Thompson Rd",
    "iso:country":"US",
    "sg:address":"6092 Thompson Rd",
    "sg:city":"Stewartstown",
    "sg:phone":"+1   ",
    "sg:postcode":"17363",
    "sg:province":"PA",
    "sg:tags":[
        "farm",
        "corn"
    ],
    "wof:name":"Paul Krick",
    "wof:placetype":"venue"
},
  "geometry": {"coordinates":[-76.58808999999999,39.789156],"type":"Point"}
}