{
  "type": "Feature",
  "properties": {
    "addr:full":"274 Twin Bridges Rd Charleroi PA 15022",
    "addr:housenumber":"274",
    "addr:postcode":"15022",
    "addr:street":"Twin Bridges Rd",
    "iso:country":"US",
    "sg:address":"274 Twin Bridges Rd",
    "sg:city":"Charleroi",
    "sg:classifiers":[
        {
            "category":"Building & Trades",
            "subcategory":"Construction",
            "type":"Services"
        }
    ],
    "sg:phone":"+1   ",
    "sg:postcode":"15022",
    "sg:province":"PA",
    "sg:tags":[
        "general",
        "contractor"
    ],
    "wof:name":"Dan Mosco General Contracting",
    "wof:placetype":"venue"
},
  "geometry": {"coordinates":[-79.93722099999999,40.122848],"type":"Point"}
}