{
  "type": "Feature",
  "properties": {
    "iso:country":"US",
    "sg:address":"991 S Arlington Ave",
    "sg:city":"Harrisburg",
    "sg:classifiers":[
        {
            "category":"Health Services",
            "subcategory":"Health Practitioner",
            "type":"Services"
        }
    ],
    "sg:phone":"+1   ",
    "sg:postcode":"17109",
    "sg:province":"PA",
    "wof:name":"Joana Deleo Dr",
    "wof:placetype":"venue"
},
  "geometry": {"coordinates":[-76.819998,40.285921],"type":"Point"}
}