{
  "type": "Feature",
  "properties": {
    "iso:country":"US",
    "sg:address":"1850 Pottstown Pike",
    "sg:city":"Glenmoore",
    "sg:classifiers":[
        {
            "category":"Manufacturing",
            "subcategory":"Tools & Machinery",
            "type":"Manufacturing & Wholesale Goods"
        },
        {
            "category":"Building & Trades",
            "subcategory":"Landscaping Services",
            "type":"Services"
        }
    ],
    "sg:phone":"+1 610 469 0927",
    "sg:postcode":"19343",
    "sg:province":"PA",
    "sg:tags":[
        "equipment",
        "tree",
        "supply"
    ],
    "wof:name":"Rocky Hill Farm Chainshaw Shop",
    "wof:placetype":"venue"
},
  "geometry": {"coordinates":[-75.69250099999999,40.125543],"type":"Point"}
}