{
  "type": "Feature",
  "properties": {
    "iso:country":"US",
    "sg:address":"1613 S Market St",
    "sg:city":"Elizabethtown",
    "sg:classifiers":[
        {
            "category":"Personal",
            "subcategory":"Beauty Salon",
            "type":"Services"
        }
    ],
    "sg:phone":"+1 717 367 1613",
    "sg:postcode":"17022",
    "sg:province":"PA",
    "sg:tags":[
        "shop",
        "barber"
    ],
    "sg:website":"http://www.holidayhair.com/",
    "wof:name":"Holiday Hair",
    "wof:placetype":"venue"
},
  "geometry": {"coordinates":[-76.583798,40.137679],"type":"Point"}
}