{
  "type": "Feature",
  "properties": {
    "addr:full":"1027 Wood St Pittsburgh PA 15221",
    "addr:housenumber":"1027",
    "addr:postcode":"15221",
    "addr:street":"Wood St",
    "iso:country":"US",
    "sg:address":"1027 Wood St",
    "sg:city":"Pittsburgh",
    "sg:classifiers":[
        {
            "category":"Organizations",
            "subcategory":"Community Association",
            "type":"Services"
        }
    ],
    "sg:phone":"+1   ",
    "sg:postcode":"15221",
    "sg:province":"PA",
    "wof:name":"Black Vietnam ERA Veterans",
    "wof:placetype":"venue"
},
  "geometry": {"coordinates":[-79.884664,40.443922],"type":"Point"}
}