{
  "type": "Feature",
  "properties": {
    "addr:full":"32 Bragg Dr East Berlin PA 17316",
    "addr:housenumber":"32",
    "addr:postcode":"17316",
    "addr:street":"Bragg Dr",
    "iso:country":"US",
    "sg:address":"32 Bragg Dr",
    "sg:city":"East Berlin",
    "sg:classifiers":[
        {
            "category":"Autos & Motor Vehicles",
            "subcategory":"Automobile Sales",
            "type":"Retail Goods"
        }
    ],
    "sg:phone":"+1   ",
    "sg:postcode":"17316",
    "sg:province":"PA",
    "sg:tags":[
        "used"
    ],
    "wof:name":"Auto Connection The Inc",
    "wof:placetype":"venue"
},
  "geometry": {"coordinates":[-77.03609899999999,39.977242],"type":"Point"}
}