{
  "type": "Feature",
  "properties": {
    "addr:full":"6901 Edinboro Rd Erie PA 16509",
    "addr:housenumber":"6901",
    "addr:postcode":"16509",
    "addr:street":"Edinboro Rd",
    "iso:country":"US",
    "sg:address":"6901 Edinboro Rd",
    "sg:city":"Erie",
    "sg:classifiers":[
        {
            "category":"Personal",
            "subcategory":"Beauty Salon",
            "type":"Services"
        }
    ],
    "sg:phone":"+1 814 864 2457",
    "sg:postcode":"16509",
    "sg:province":"PA",
    "wof:name":"Shear Magic Take 2",
    "wof:placetype":"venue"
},
  "geometry": {"coordinates":[-80.104882,42.057254],"type":"Point"}
}