{
  "type": "Feature",
  "properties": {
    "iso:country":"US",
    "sg:address":"628 Logan Valley Mall",
    "sg:city":"Altoona",
    "sg:classifiers":[
        {
            "category":"Shopping",
            "subcategory":"Clothing, Apparel, & Fashions",
            "type":"Retail Goods"
        }
    ],
    "sg:phone":"+1 814 941 0717",
    "sg:postcode":"16602",
    "sg:province":"PA",
    "sg:tags":[
        "shop",
        "specialty"
    ],
    "wof:name":"Icing By Claire's",
    "wof:placetype":"venue"
},
  "geometry": {"coordinates":[-78.40839699999999,40.472327],"type":"Point"}
}