{
  "type": "Feature",
  "properties": {
    "addr:full":"2750 Apple Valley Ln Norristown PA 19403",
    "addr:housenumber":"2750",
    "addr:postcode":"19403",
    "addr:street":"Apple Valley Ln",
    "iso:country":"US",
    "sg:address":"2750 Apple Valley Ln",
    "sg:city":"Norristown",
    "sg:classifiers":[
        {
            "category":"Organizations",
            "subcategory":"Religious Organization",
            "type":"Services"
        }
    ],
    "sg:phone":"+1 610 666 5387",
    "sg:postcode":"19403",
    "sg:province":"PA",
    "sg:tags":[
        "clergy"
    ],
    "wof:name":"John G Huber",
    "wof:placetype":"venue"
},
  "geometry": {"coordinates":[-75.430071,40.122384],"type":"Point"}
}