{
  "type": "Feature",
  "properties": {
    "iso:country":"US",
    "sg:address":"1200 Chestnut St",
    "sg:city":"Kulpmont",
    "sg:classifiers":[
        {
            "category":"Manufacturing",
            "subcategory":"Wood Products",
            "type":"Manufacturing & Wholesale Goods"
        }
    ],
    "sg:phone":"+1 570 373 3504",
    "sg:postcode":"17834",
    "sg:province":"PA",
    "sg:tags":[
        "mfg"
    ],
    "wof:name":"Present Under Glass",
    "wof:placetype":"venue"
},
  "geometry": {"coordinates":[-76.478403,40.793099],"type":"Point"}
}