{
  "type": "Feature",
  "properties": {
    "iso:country":"US",
    "sg:address":"2049 Brodhead Rd ",
    "sg:city":"Aliquippa",
    "sg:classifiers":[
        {
            "category":"Restaurant",
            "type":"Food & Drink"
        }
    ],
    "sg:menulink":"http://www.allmenus.com/pa/hopewell/292511-china-city-/menu/",
    "sg:phone":"+1 724 378 7852",
    "sg:postcode":"15001",
    "sg:province":"PA",
    "sg:tags":[
        "chinese"
    ],
    "wof:name":"China City ",
    "wof:placetype":"venue"
},
  "geometry": {"coordinates":[-80.25781600000001,40.56969],"type":"Point"}
}