{
  "type": "Feature",
  "properties": {
    "iso:country":"US",
    "sg:address":"881 Milton Grove Rd",
    "sg:city":"Mount Joy",
    "sg:classifiers":[
        {
            "category":"Building & Trades",
            "subcategory":"Landscaping Services",
            "type":"Services"
        }
    ],
    "sg:phone":"+1   ",
    "sg:postcode":"17552",
    "sg:province":"PA",
    "wof:name":"Goeke Tree Service",
    "wof:placetype":"venue"
},
  "geometry": {"coordinates":[-76.493962,40.126642],"type":"Point"}
}