{
  "type": "Feature",
  "properties": {
    "addr:full":"1006 Main St Linfield PA 19468",
    "addr:housenumber":"1006",
    "addr:postcode":"19468",
    "addr:street":"Main St",
    "iso:country":"US",
    "sg:address":"1006 Main St",
    "sg:city":"Linfield",
    "sg:classifiers":[
        {
            "category":"Manufacturing",
            "subcategory":"Motor Vehicles & Parts",
            "type":"Manufacturing & Wholesale Goods"
        }
    ],
    "sg:phone":"+1 610 495 5090",
    "sg:postcode":"19468",
    "sg:province":"PA",
    "sg:tags":[
        "body",
        "car",
        "mfg",
        "supply"
    ],
    "wof:name":"Parsons Enterprises Ltd Inc",
    "wof:placetype":"venue"
},
  "geometry": {"coordinates":[-75.570909,40.208983],"type":"Point"}
}