{
  "type": "Feature",
  "properties": {
    "addr:full":"1526 E Passyunk Ave Philadelphia PA 19147",
    "addr:housenumber":"1526",
    "addr:postcode":"19147",
    "addr:street":"E Passyunk Ave",
    "iso:country":"US",
    "sg:address":"1526 E Passyunk Ave",
    "sg:city":"Philadelphia",
    "sg:classifiers":[
        {
            "category":"Home & Garden",
            "subcategory":"Garden Supply",
            "type":"Retail Goods"
        }
    ],
    "sg:phone":"+1 215 952 0811",
    "sg:postcode":"19147",
    "sg:province":"PA",
    "sg:tags":[
        "nursery",
        "gardening"
    ],
    "wof:name":"Urban Jungle",
    "wof:placetype":"venue"
},
  "geometry": {"coordinates":[-75.162932,39.930302],"type":"Point"}
}