{
  "type": "Feature",
  "properties": {
    "iso:country":"US",
    "sg:address":"638 Walnut St",
    "sg:city":"Reading",
    "sg:classifiers":[
        {
            "category":"Local Transit",
            "type":"Transportation"
        }
    ],
    "sg:phone":"+1   ",
    "sg:postcode":"19601",
    "sg:province":"PA",
    "sg:tags":[
        "ambulance"
    ],
    "wof:name":"AMR Mid-Atlantic",
    "wof:placetype":"venue"
},
  "geometry": {"coordinates":[-75.92483199999999,40.338411],"type":"Point"}
}