{
  "type": "Feature",
  "properties": {
    "addr:full":"101W W Elm St Conshohocken PA 19428",
    "addr:housenumber":"101w",
    "addr:postcode":"19428",
    "addr:street":"W Elm St",
    "iso:country":"US",
    "sg:address":"101W W Elm St",
    "sg:city":"Conshohocken",
    "sg:classifiers":[
        {
            "category":"Personal",
            "type":"Services"
        },
        {
            "category":"Retail",
            "subcategory":"Auto Rental",
            "type":"Services"
        },
        {
            "category":"Freight",
            "type":"Transportation"
        }
    ],
    "sg:phone":"+1 610 825 9453",
    "sg:postcode":"19428",
    "sg:province":"PA",
    "sg:tags":[
        "renting",
        "full",
        "leasing",
        "storage",
        "trucking",
        "truck",
        "mover",
        "local",
        "trailer"
    ],
    "sg:website":"http://www.uhaul.com",
    "wof:name":"U-Haul",
    "wof:placetype":"venue"
},
  "geometry": {"coordinates":[-75.30811300000001,40.073311],"type":"Point"}
}