{
  "type": "Feature",
  "properties": {
    "iso:country":"US",
    "sg:address":"580 Harbison Ave",
    "sg:city":"Philadelphia",
    "sg:classifiers":[
        {
            "category":"Autos & Motor Vehicles",
            "subcategory":"Auto Supplies",
            "type":"Retail Goods"
        },
        {
            "category":"Retail",
            "subcategory":"Auto Repair",
            "type":"Services"
        }
    ],
    "sg:phone":"+1 215 744 1122",
    "sg:postcode":"19102",
    "sg:province":"PA",
    "sg:tags":[
        "tire"
    ],
    "wof:name":"Allen Tire & Service",
    "wof:placetype":"venue"
},
  "geometry": {"coordinates":[-75.166901,39.949501],"type":"Point"}
}