{
  "type": "Feature",
  "properties": {
    "addr:full":"1139 O'Block Rd Pittsburgh PA 15239",
    "addr:housenumber":"1139",
    "addr:postcode":"15239",
    "addr:street":"O'Block Rd",
    "iso:country":"US",
    "sg:address":"1139 O'Block Rd",
    "sg:city":"Pittsburgh",
    "sg:classifiers":[
        {
            "category":"Manufacturing",
            "subcategory":"Food",
            "type":"Manufacturing & Wholesale Goods"
        }
    ],
    "sg:phone":"+1   ",
    "sg:postcode":"15239",
    "sg:province":"PA",
    "sg:tags":[
        "product",
        "mfg"
    ],
    "wof:name":"Country Cupboard Cookies",
    "wof:placetype":"venue"
},
  "geometry": {"coordinates":[-79.93181,40.470271],"type":"Point"}
}