{
  "type": "Feature",
  "properties": {
    "iso:country":"US",
    "sg:address":"705 Market St",
    "sg:city":"Sunbury",
    "sg:classifiers":[
        {
            "category":"Government",
            "subcategory":"Office",
            "type":"Public Place"
        }
    ],
    "sg:phone":"+1 570 286 8563",
    "sg:postcode":"17801",
    "sg:province":"PA",
    "sg:tags":[
        "village"
    ],
    "wof:name":"Scott Tower",
    "wof:placetype":"venue"
},
  "geometry": {"coordinates":[-76.787773,40.860093],"type":"Point"}
}