{
  "type": "Feature",
  "properties": {
    "iso:country":"US",
    "sg:address":"5 Broad St",
    "sg:city":"Beaver Meadows",
    "sg:classifiers":[
        {
            "category":"Health Services",
            "subcategory":"Doctor",
            "type":"Services"
        }
    ],
    "sg:phone":"+1 570 454 5424",
    "sg:postcode":"18216",
    "sg:province":"PA",
    "sg:tags":[
        "dentist"
    ],
    "wof:name":"General Dental Care",
    "wof:placetype":"venue"
},
  "geometry": {"coordinates":[-75.91512299999999,40.928409],"type":"Point"}
}