{
  "type": "Feature",
  "properties": {
    "iso:country":"US",
    "sg:address":"1 McCoy Rd",
    "sg:city":"Mc Kees Rocks",
    "sg:classifiers":[
        {
            "category":"Retail",
            "subcategory":"Repair Shop",
            "type":"Services"
        }
    ],
    "sg:phone":"+1 412 331 9777",
    "sg:postcode":"15136",
    "sg:province":"PA",
    "sg:tags":[
        "upholsterer"
    ],
    "wof:name":"Lewicke Furniture Refinishing",
    "wof:placetype":"venue"
},
  "geometry": {"coordinates":[-80.068032,40.476016],"type":"Point"}
}