{
  "type": "Feature",
  "properties": {
    "iso:country":"US",
    "sg:address":"201 N Main St",
    "sg:city":"Doylestown",
    "sg:classifiers":[
        {
            "category":"Real Estate",
            "subcategory":"Real Estate Services",
            "type":"Services"
        },
        {
            "category":"Professional",
            "subcategory":"Research",
            "type":"Services"
        }
    ],
    "sg:phone":"+1 215 345 6606",
    "sg:postcode":"18901",
    "sg:province":"PA",
    "sg:tags":[
        "abstracter",
        "title"
    ],
    "sg:website":"http://www.securitysearchabstract.com",
    "wof:name":"Security Search & Abstract Company Of Phila Inc",
    "wof:placetype":"venue"
},
  "geometry": {"coordinates":[-75.13063699999999,40.314636],"type":"Point"}
}