{
  "type": "Feature",
  "properties": {
    "iso:country":"US",
    "sg:address":"251 Grant St",
    "sg:city":"Chambersburg",
    "sg:classifiers":[
        {
            "category":"Restaurant",
            "type":"Food & Drink"
        }
    ],
    "sg:phone":"+1   ",
    "sg:postcode":"17201",
    "sg:province":"PA",
    "sg:tags":[
        "eating"
    ],
    "wof:name":"Fireside Bbq Pit",
    "wof:placetype":"venue"
},
  "geometry": {"coordinates":[-77.657595,39.941313],"type":"Point"}
}