{
  "type": "Feature",
  "properties": {
    "addr:full":"920 Century Dr Mechanicsburg PA 17055",
    "addr:housenumber":"920",
    "addr:postcode":"17055",
    "addr:street":"Century Dr",
    "iso:country":"US",
    "sg:address":"920 Century Dr",
    "sg:city":"Mechanicsburg",
    "sg:classifiers":[
        {
            "category":"Health Services",
            "subcategory":"Clinic",
            "type":"Services"
        }
    ],
    "sg:phone":"+1   ",
    "sg:postcode":"17055",
    "sg:province":"PA",
    "sg:tags":[
        "inpatient"
    ],
    "wof:name":"HealthSouth",
    "wof:placetype":"venue"
},
  "geometry": {"coordinates":[-76.96355800000001,40.211912],"type":"Point"}
}