{
  "type": "Feature",
  "properties": {
    "addr:full":"142 Evergreen Dr Aliquippa PA 15001",
    "addr:housenumber":"142",
    "addr:postcode":"15001",
    "addr:street":"Evergreen Dr",
    "iso:country":"US",
    "sg:address":"142 Evergreen Dr",
    "sg:city":"Aliquippa",
    "sg:classifiers":[
        {
            "category":"Professional",
            "type":"Services"
        }
    ],
    "sg:phone":"+1   ",
    "sg:postcode":"15001",
    "sg:province":"PA",
    "wof:name":"Stonegate",
    "wof:placetype":"venue"
},
  "geometry": {"coordinates":[-80.302924,40.643911],"type":"Point"}
}