{
  "type": "Feature",
  "properties": {
    "addr:full":"350 Chestnut St Mifflinburg PA 17844",
    "addr:housenumber":"350",
    "addr:postcode":"17844",
    "addr:street":"Chestnut St",
    "iso:country":"US",
    "sg:address":"350 Chestnut St",
    "sg:city":"Mifflinburg",
    "sg:classifiers":[
        {
            "category":"Shopping",
            "subcategory":"Gifts & Souvenirs",
            "type":"Retail Goods"
        }
    ],
    "sg:phone":"+1 570 966 0012",
    "sg:postcode":"17844",
    "sg:province":"PA",
    "sg:tags":[
        "collectible"
    ],
    "wof:name":"Terri's Collectibles",
    "wof:placetype":"venue"
},
  "geometry": {"coordinates":[-77.046828,40.918126],"type":"Point"}
}