{
  "type": "Feature",
  "properties": {
    "addr:full":"6500 Saltsburg Rd Pittsburgh PA 15235",
    "addr:postcode":"6500;15235",
    "addr:street":"Saltsburg Rd",
    "iso:country":"US",
    "sg:address":"6500 Saltsburg Rd",
    "sg:city":"Pittsburgh",
    "sg:classifiers":[
        {
            "category":"Autos & Motor Vehicles",
            "subcategory":"Fuel & Gas Station",
            "type":"Retail Goods"
        },
        {
            "category":"Food & Beverages",
            "subcategory":"Groceries & Convenience Stores",
            "type":"Retail Goods"
        }
    ],
    "sg:phone":"+1 412 798 5690",
    "sg:postcode":"15235",
    "sg:province":"PA",
    "wof:name":"Azhar's Sunoco",
    "wof:placetype":"venue"
},
  "geometry": {"coordinates":[-79.809746,40.482918],"type":"Point"}
}