{
  "type": "Feature",
  "properties": {
    "iso:country":"US",
    "sg:address":"498 E Maiden St",
    "sg:city":"Washington",
    "sg:classifiers":[
        {
            "category":"Retail",
            "subcategory":"Veterinary Services",
            "type":"Services"
        }
    ],
    "sg:phone":"+1 724 225 2312",
    "sg:postcode":"15301",
    "sg:province":"PA",
    "wof:name":"East Maiden Animal Clinic",
    "wof:placetype":"venue"
},
  "geometry": {"coordinates":[-80.233853,40.165867],"type":"Point"}
}