{
  "type": "Feature",
  "properties": {
    "iso:country":"US",
    "sg:address":"215 Franklin St",
    "sg:city":"Dunmore",
    "sg:classifiers":[
        {
            "category":"Organizations",
            "subcategory":"Religious Organization",
            "type":"Services"
        }
    ],
    "sg:phone":"+1 570 343 1422",
    "sg:postcode":"18512",
    "sg:province":"PA",
    "sg:tags":[
        "monastery",
        "convent"
    ],
    "wof:name":"St Anthony Convent",
    "wof:placetype":"venue"
},
  "geometry": {"coordinates":[-75.623942,41.418243],"type":"Point"}
}