{
  "type": "Feature",
  "properties": {
    "iso:country":"US",
    "sg:address":"700 Airport Rd",
    "sg:city":"Montoursville",
    "sg:classifiers":[
        {
            "category":"Professional",
            "subcategory":"Advertising",
            "type":"Services"
        }
    ],
    "sg:phone":"+1 570 368 2035",
    "sg:postcode":"17754",
    "sg:province":"PA",
    "wof:name":"Diggins Advertising",
    "wof:placetype":"venue"
},
  "geometry": {"coordinates":[-76.925972,41.246307],"type":"Point"}
}