{
  "type": "Feature",
  "properties": {
    "addr:full":"3417 Garrett Rd Drexel Hill PA 19026",
    "addr:housenumber":"3417",
    "addr:postcode":"19026",
    "addr:street":"Garrett Rd",
    "iso:country":"US",
    "sg:address":"3417 Garrett Rd",
    "sg:city":"Drexel Hill",
    "sg:classifiers":[
        {
            "category":"Retail",
            "subcategory":"Laundry & Dry Cleaning",
            "type":"Services"
        }
    ],
    "sg:phone":"+1 610 284 9839",
    "sg:postcode":"19026",
    "sg:province":"PA",
    "sg:tags":[
        "cleaners"
    ],
    "wof:name":"Gearys Laundromat",
    "wof:placetype":"venue"
},
  "geometry": {"coordinates":[-75.296233,39.944877],"type":"Point"}
}