{
  "type": "Feature",
  "properties": {
    "addr:full":"291 Maple Hollow Rd Duncansville PA 16635",
    "addr:housenumber":"291",
    "addr:postcode":"16635",
    "addr:street":"Maple Hollow Rd",
    "iso:country":"US",
    "sg:address":"291 Maple Hollow Rd",
    "sg:city":"Duncansville",
    "sg:classifiers":[
        {
            "category":"Health Services",
            "subcategory":"Health Practitioner",
            "type":"Services"
        },
        {
            "category":"Professional",
            "subcategory":"Employment Agencies",
            "type":"Services"
        }
    ],
    "sg:phone":"+1 814 693 1415",
    "sg:postcode":"16635",
    "sg:province":"PA",
    "sg:tags":[
        "nurse",
        "help",
        "registry",
        "supply"
    ],
    "wof:name":"Adara Healthcare Staffing Inc",
    "wof:placetype":"venue"
},
  "geometry": {"coordinates":[-78.460404,40.432054],"type":"Point"}
}