{
  "type": "Feature",
  "properties": {
    "addr:full":"4044 Skippack Pike Skippack PA 19474",
    "addr:postcode":"4044;19474",
    "addr:street":"Skippack Pike",
    "iso:country":"US",
    "sg:address":"4044 Skippack Pike",
    "sg:city":"Skippack",
    "sg:classifiers":[
        {
            "category":"Restaurant",
            "type":"Food & Drink"
        }
    ],
    "sg:phone":"+1 610 222 4777",
    "sg:postcode":"19474",
    "sg:province":"PA",
    "sg:tags":[
        "japanese"
    ],
    "sg:website":"www.tokyosushicuisine.com/",
    "wof:name":"Tokyo Japanese Restaurant",
    "wof:placetype":"venue"
},
  "geometry": {"coordinates":[-75.40088799999999,40.224133],"type":"Point"}
}