{
  "type": "Feature",
  "properties": {
    "addr:full":"2419 Manning St Philadelphia PA 19103",
    "addr:housenumber":"2419",
    "addr:postcode":"19103",
    "addr:street":"Manning St",
    "iso:country":"US",
    "sg:address":"2419 Manning St",
    "sg:city":"Philadelphia",
    "sg:classifiers":[
        {
            "category":"Professional",
            "subcategory":"Management & Consulting",
            "type":"Services"
        }
    ],
    "sg:phone":"+1 215 732 5400",
    "sg:postcode":"19103",
    "sg:province":"PA",
    "sg:tags":[
        "consultant"
    ],
    "wof:name":"Buerkel Consultants",
    "wof:placetype":"venue"
},
  "geometry": {"coordinates":[-75.180891,39.94943],"type":"Point"}
}