{
  "type": "Feature",
  "properties": {
    "addr:full":"509 Pacific Ave York PA 17404",
    "addr:housenumber":"509",
    "addr:postcode":"17404",
    "addr:street":"Pacific Ave",
    "iso:country":"US",
    "sg:address":"509 Pacific Ave",
    "sg:city":"York",
    "sg:classifiers":[
        {
            "category":"Social Services",
            "subcategory":"Adult Care",
            "type":"Services"
        }
    ],
    "sg:phone":"+1 717 854 0693",
    "sg:postcode":"17404",
    "sg:province":"PA",
    "sg:tags":[
        "organization",
        "senior",
        "citizen"
    ],
    "wof:name":"Yorktown Senior Ctr",
    "wof:placetype":"venue"
},
  "geometry": {"coordinates":[-76.749317,39.969232],"type":"Point"}
}