{
  "type": "Feature",
  "properties": {
    "addr:full":"1301 Columbia Blvd Bloomsburg PA 17815",
    "addr:housenumber":"1301",
    "addr:postcode":"17815",
    "addr:street":"Columbia Blvd",
    "iso:country":"US",
    "sg:address":"1301 Columbia Blvd",
    "sg:city":"Bloomsburg",
    "sg:classifiers":[
        {
            "category":"Banks & Credit Unions",
            "subcategory":"Bank",
            "type":"Services"
        }
    ],
    "sg:phone":"+1 570 387 8488",
    "sg:postcode":"17815",
    "sg:province":"PA",
    "sg:tags":[
        "loan"
    ],
    "wof:name":"Regency Finance Co",
    "wof:placetype":"venue"
},
  "geometry": {"coordinates":[-76.433021,41.005663],"type":"Point"}
}