{
  "type": "Feature",
  "properties": {
    "iso:country":"US",
    "sg:address":"22 Grant Ave",
    "sg:city":"Pittsburgh",
    "sg:classifiers":[
        {
            "category":"Food & Beverages",
            "subcategory":"Groceries & Convenience Stores",
            "type":"Retail Goods"
        }
    ],
    "sg:phone":"+1   ",
    "sg:postcode":"15223",
    "sg:province":"PA",
    "wof:name":"7-Eleven",
    "wof:placetype":"venue"
},
  "geometry": {"coordinates":[-79.948995,40.504115],"type":"Point"}
}