{
  "type": "Feature",
  "properties": {
    "iso:country":"US",
    "sg:address":"5211 Brownsville Rd",
    "sg:city":"Pleasant Hills",
    "sg:classifiers":[
        {
            "category":"Manufacturing",
            "subcategory":"Printing",
            "type":"Manufacturing & Wholesale Goods"
        }
    ],
    "sg:phone":"+1 412 751 0400",
    "sg:postcode":"15236",
    "sg:province":"PA",
    "sg:tags":[
        "multimedia"
    ],
    "wof:name":"At&T Media Svc",
    "wof:placetype":"venue"
},
  "geometry": {"coordinates":[-79.985051,40.341804],"type":"Point"}
}