{
  "type": "Feature",
  "properties": {
    "addr:full":"343 E North St Carlisle PA 17013",
    "addr:housenumber":"343",
    "addr:postcode":"17013",
    "addr:street":"E North St",
    "iso:country":"US",
    "sg:address":"343 E North St",
    "sg:city":"Carlisle",
    "sg:classifiers":[
        {
            "category":"Social Services",
            "type":"Services"
        }
    ],
    "sg:phone":"+1   ",
    "sg:postcode":"17013",
    "sg:province":"PA",
    "wof:name":"ARC",
    "wof:placetype":"venue"
},
  "geometry": {"coordinates":[-77.181493,40.20404],"type":"Point"}
}