{
  "type": "Feature",
  "properties": {
    "iso:country":"US",
    "sg:address":"609 N Church St",
    "sg:city":"Hazleton",
    "sg:classifiers":[
        {
            "category":"Autos & Motor Vehicles",
            "subcategory":"Automobile Sales",
            "type":"Retail Goods"
        }
    ],
    "sg:phone":"+1 570 459 2272",
    "sg:postcode":"18201",
    "sg:province":"PA",
    "sg:tags":[
        "car",
        "dealer"
    ],
    "wof:name":"NFR Auto Sales",
    "wof:placetype":"venue"
},
  "geometry": {"coordinates":[-75.975139,40.963078],"type":"Point"}
}