{
  "type": "Feature",
  "properties": {
    "addr:full":"54 W Main St Leola PA 17540",
    "addr:housenumber":"54",
    "addr:postcode":"17540",
    "addr:street":"W Main St",
    "iso:country":"US",
    "sg:address":"54 W Main St",
    "sg:city":"Leola",
    "sg:classifiers":[
        {
            "category":"Building & Trades",
            "subcategory":"Construction",
            "type":"Services"
        }
    ],
    "sg:phone":"+1 717 656 7833",
    "sg:postcode":"17540",
    "sg:province":"PA",
    "sg:tags":[
        "contractor"
    ],
    "wof:name":"Leola War Memorial Building",
    "wof:placetype":"venue"
},
  "geometry": {"coordinates":[-76.18868500000001,40.087356],"type":"Point"}
}