{
  "type": "Feature",
  "properties": {
    "iso:country":"US",
    "sg:address":"867 Main St",
    "sg:city":"Honesdale",
    "sg:classifiers":[
        {
            "category":"Shopping",
            "subcategory":"Jewelry",
            "type":"Retail Goods"
        }
    ],
    "sg:phone":"+1 570 253 4688",
    "sg:postcode":"18431",
    "sg:province":"PA",
    "sg:tags":[
        "repair",
        "clock"
    ],
    "wof:name":"Main Street Jewelers",
    "wof:placetype":"venue"
},
  "geometry": {"coordinates":[-75.256079,41.573063],"type":"Point"}
}