{
  "type": "Feature",
  "properties": {
    "iso:country":"US",
    "sg:address":"1891 Fruitville Pike",
    "sg:city":"Lancaster",
    "sg:classifiers":[
        {
            "category":"Health Services",
            "subcategory":"Medical Lab",
            "type":"Services"
        }
    ],
    "sg:phone":"+1   ",
    "sg:postcode":"17601",
    "sg:province":"PA",
    "sg:tags":[
        "laboratory",
        "dental"
    ],
    "wof:name":"Redrose Dental Lab Inc",
    "wof:placetype":"venue"
},
  "geometry": {"coordinates":[-76.31966799999999,40.073254],"type":"Point"}
}