{
  "type": "Feature",
  "properties": {
    "addr:full":"29 E Moreland Ave Hatboro PA 19040",
    "addr:housenumber":"29",
    "addr:postcode":"19040",
    "addr:street":"E Moreland Ave",
    "iso:country":"US",
    "sg:address":"29 E Moreland Ave",
    "sg:city":"Hatboro",
    "sg:classifiers":[
        {
            "category":"Utilities",
            "subcategory":"Telephone",
            "type":"Services"
        }
    ],
    "sg:phone":"+1   ",
    "sg:postcode":"19040",
    "sg:province":"PA",
    "sg:tags":[
        "telecommunication"
    ],
    "wof:name":"Verizon",
    "wof:placetype":"venue"
},
  "geometry": {"coordinates":[-75.10414400000001,40.176765],"type":"Point"}
}