{
  "type": "Feature",
  "properties": {
    "iso:country":"US",
    "sg:address":"5500 Blakemore St Ste 1",
    "sg:city":"Philadelphia",
    "sg:classifiers":[
        {
            "category":"Professional",
            "subcategory":"Computer Services",
            "type":"Services"
        }
    ],
    "sg:phone":"+1 215 844 5856",
    "sg:postcode":"19138",
    "sg:province":"PA",
    "sg:tags":[
        "isp",
        "provider",
        "internet"
    ],
    "wof:name":"Millinium Shop",
    "wof:placetype":"venue"
},
  "geometry": {"coordinates":[-75.158073,40.047138],"type":"Point"}
}