{
  "type": "Feature",
  "properties": {
    "iso:country":"US",
    "sg:address":"1911 Pennsylvania Ave",
    "sg:city":"Croydon",
    "sg:classifiers":[
        {
            "category":"Wholesale",
            "subcategory":"Construction Materials",
            "type":"Manufacturing & Wholesale Goods"
        },
        {
            "category":"Home & Garden",
            "subcategory":"Building Materials",
            "type":"Retail Goods"
        }
    ],
    "sg:phone":"+1 215 781 1500",
    "sg:postcode":"19021",
    "sg:province":"PA",
    "sg:tags":[
        "door",
        "devices",
        "overhead",
        "install",
        "gate",
        "operating"
    ],
    "wof:name":"Abstract Overhead Door Company",
    "wof:placetype":"venue"
},
  "geometry": {"coordinates":[-74.894012,40.094918],"type":"Point"}
}