{
  "type": "Feature",
  "properties": {
    "addr:full":"223 W Walnut St Lancaster PA 17603",
    "addr:housenumber":"223",
    "addr:postcode":"17603",
    "addr:street":"W Walnut St",
    "iso:country":"US",
    "sg:address":"223 W Walnut St",
    "sg:city":"Lancaster",
    "sg:classifiers":[
        {
            "category":"Manufacturing",
            "subcategory":"Metals",
            "type":"Manufacturing & Wholesale Goods"
        }
    ],
    "sg:phone":"+1 717 397 4297",
    "sg:postcode":"17603",
    "sg:province":"PA",
    "sg:tags":[
        "coating"
    ],
    "wof:name":"Pittsburgh Coating & Supply Co",
    "wof:placetype":"venue"
},
  "geometry": {"coordinates":[-76.309619,40.042505],"type":"Point"}
}