{
  "type": "Feature",
  "properties": {
    "iso:country":"US",
    "sg:address":"132 State St",
    "sg:city":"Harrisburg",
    "sg:classifiers":[
        {
            "category":"Banks & Credit Unions",
            "subcategory":"Bank",
            "type":"Services"
        }
    ],
    "sg:phone":"+1 717 236 2300",
    "sg:postcode":"17101",
    "sg:province":"PA",
    "sg:tags":[
        "financing"
    ],
    "wof:name":"Penn Venture Partners LP",
    "wof:placetype":"venue"
},
  "geometry": {"coordinates":[-76.88700300000001,40.26317],"type":"Point"}
}