{
  "type": "Feature",
  "properties": {
    "iso:country":"US",
    "sg:address":"1788 E 3rd St",
    "sg:city":"Williamsport",
    "sg:classifiers":[
        {
            "category":"Autos & Motor Vehicles",
            "subcategory":"Automobile Sales",
            "type":"Retail Goods"
        }
    ],
    "sg:phone":"+1   ",
    "sg:postcode":"17701",
    "sg:province":"PA",
    "sg:tags":[
        "used"
    ],
    "wof:name":"Bpm Auto Sales & Hobby Shop",
    "wof:placetype":"venue"
},
  "geometry": {"coordinates":[-76.969302,41.249864],"type":"Point"}
}