{
  "type": "Feature",
  "properties": {
    "iso:country":"US",
    "sg:address":"40 N Main St",
    "sg:city":"Chalfont",
    "sg:classifiers":[
        {
            "category":"Government",
            "subcategory":"Office",
            "type":"Public Place"
        }
    ],
    "sg:phone":"+1 215 822 0991",
    "sg:postcode":"18914",
    "sg:province":"PA",
    "sg:tags":[
        "village"
    ],
    "wof:name":"Boro Of Chalfont Water Co",
    "wof:placetype":"venue"
},
  "geometry": {"coordinates":[-75.209154,40.28733],"type":"Point"}
}