{
  "type": "Feature",
  "properties": {
    "iso:country":"US",
    "sg:address":"601 W 3rd St",
    "sg:city":"Williamsport",
    "sg:classifiers":[
        {
            "category":"Autos & Motor Vehicles",
            "subcategory":"Automobile Sales",
            "type":"Retail Goods"
        }
    ],
    "sg:phone":"+1 570 326 0567",
    "sg:postcode":"17701",
    "sg:province":"PA",
    "sg:tags":[
        "car",
        "dealer"
    ],
    "wof:name":"Van Campen Motors Inc",
    "wof:placetype":"venue"
},
  "geometry": {"coordinates":[-77.013684,41.237929],"type":"Point"}
}