{
  "type": "Feature",
  "properties": {
    "iso:country":"US",
    "sg:address":"468 N Middletown Rd",
    "sg:city":"Media",
    "sg:classifiers":[
        {
            "category":"Social Services",
            "type":"Services"
        }
    ],
    "sg:phone":"+1 610 565 2353",
    "sg:postcode":"19063",
    "sg:province":"PA",
    "sg:tags":[
        "organization",
        "welfare"
    ],
    "sg:website":"www.easterseals-sepa.org",
    "wof:name":"Easter Seal Society",
    "wof:placetype":"venue"
},
  "geometry": {"coordinates":[-75.443957,39.92458],"type":"Point"}
}