{
  "type": "Feature",
  "properties": {
    "addr:full":"805 Nesbitt Rd Ambler PA 19002",
    "addr:housenumber":"805",
    "addr:postcode":"19002",
    "addr:street":"Nesbitt Rd",
    "iso:country":"US",
    "sg:address":"805 Nesbitt Rd",
    "sg:city":"Ambler",
    "sg:classifiers":[
        {
            "category":"Professional",
            "type":"Services"
        }
    ],
    "sg:phone":"+1   ",
    "sg:postcode":"19002",
    "sg:province":"PA",
    "wof:name":"Rockfield LLC",
    "wof:placetype":"venue"
},
  "geometry": {"coordinates":[-75.187749,40.189897],"type":"Point"}
}