{
  "type": "Feature",
  "properties": {
    "iso:country":"US",
    "sg:address":"6141 Kellers Church Rd",
    "sg:city":"Pipersville",
    "sg:classifiers":[
        {
            "category":"Building & Trades",
            "subcategory":"Construction",
            "type":"Services"
        }
    ],
    "sg:phone":"+1 215 766 2579",
    "sg:postcode":"18947",
    "sg:province":"PA",
    "sg:tags":[
        "roofing",
        "contractor"
    ],
    "wof:name":"Kraus Specialty Contractors",
    "wof:placetype":"venue"
},
  "geometry": {"coordinates":[-75.15169299999999,40.391518],"type":"Point"}
}