{
  "type": "Feature",
  "properties": {
    "iso:country":"US",
    "sg:address":"2490 Commercial Blvd",
    "sg:city":"State College",
    "sg:classifiers":[
        {
            "category":"Home & Garden",
            "subcategory":"Building Materials",
            "type":"Retail Goods"
        },
        {
            "category":"Retail",
            "subcategory":"Auto Repair",
            "type":"Services"
        }
    ],
    "sg:phone":"+1 814 234 3431",
    "sg:postcode":"16801",
    "sg:province":"PA",
    "sg:tags":[
        "glass",
        "window",
        "automotive",
        "plate",
        "replacement"
    ],
    "wof:name":"Auto Glass Center Inc",
    "wof:placetype":"venue"
},
  "geometry": {"coordinates":[-77.813615,40.824343],"type":"Point"}
}