{
  "type": "Feature",
  "properties": {
    "addr:full":"1104 Blue Valley Dr Pen Argyl PA 18072",
    "addr:housenumber":"1104",
    "addr:postcode":"18072",
    "addr:street":"Blue Valley Dr Pen Argyl",
    "iso:country":"US",
    "sg:address":"1104 Blue Valley Dr",
    "sg:city":"Pen Argyl",
    "sg:classifiers":[
        {
            "category":"Social Services",
            "subcategory":"Child Care",
            "type":"Services"
        }
    ],
    "sg:phone":"+1 610 863 4000",
    "sg:postcode":"18072",
    "sg:province":"PA",
    "sg:tags":[
        "kindergarten",
        "academic",
        "school"
    ],
    "wof:name":"Miss Rose's Pre-School",
    "wof:placetype":"venue"
},
  "geometry": {"coordinates":[-75.242125,40.873763],"type":"Point"}
}