{
  "type": "Feature",
  "properties": {
    "addr:full":"4217 Dom Perignon Ct Allison Park PA 15101",
    "addr:housenumber":"4217",
    "addr:postcode":"15101",
    "addr:street":"Dom Perignon Ct;Park",
    "iso:country":"US",
    "sg:address":"4217 Dom Perignon Ct",
    "sg:city":"Allison Park",
    "sg:classifiers":[
        {
            "category":"Health Services",
            "subcategory":"Doctor",
            "type":"Services"
        }
    ],
    "sg:phone":"+1 412 486 0290",
    "sg:postcode":"15101",
    "sg:province":"PA",
    "sg:tags":[
        "physician",
        "surgeon"
    ],
    "wof:name":"R Wendell Ward MD",
    "wof:placetype":"venue"
},
  "geometry": {"coordinates":[-79.983772,40.570588],"type":"Point"}
}