{
  "type": "Feature",
  "properties": {
    "iso:country":"US",
    "sg:address":"10 Lauber Rd",
    "sg:city":"Akron",
    "sg:classifiers":[
        {
            "category":"Manufacturing",
            "subcategory":"Furniture",
            "type":"Manufacturing & Wholesale Goods"
        },
        {
            "category":"Manufacturing",
            "subcategory":"Wood Products",
            "type":"Manufacturing & Wholesale Goods"
        }
    ],
    "sg:phone":"+1 717 627 2701",
    "sg:postcode":"17501",
    "sg:province":"PA",
    "sg:tags":[
        "wooden",
        "custom",
        "mfg"
    ],
    "wof:name":"Ricks Custom Wood Design Inc",
    "wof:placetype":"venue"
},
  "geometry": {"coordinates":[-76.208449,40.14544],"type":"Point"}
}