{
  "type": "Feature",
  "properties": {
    "iso:country":"US",
    "sg:address":"8142 Henry Ave",
    "sg:city":"Philadelphia",
    "sg:classifiers":[
        {
            "category":"Building & Trades",
            "subcategory":"Construction",
            "type":"Services"
        }
    ],
    "sg:phone":"+1   ",
    "sg:postcode":"19128",
    "sg:province":"PA",
    "sg:tags":[
        "house"
    ],
    "wof:name":"Wayne Kavitsky Construc",
    "wof:placetype":"venue"
},
  "geometry": {"coordinates":[-75.235058,40.059507],"type":"Point"}
}