{
  "type": "Feature",
  "properties": {
    "addr:full":"739 Reading Ave Reading PA 19611",
    "addr:housenumber":"739",
    "addr:postcode":"19611",
    "addr:street":"Reading Ave",
    "iso:country":"US",
    "sg:address":"739 Reading Ave",
    "sg:city":"Reading",
    "sg:classifiers":[
        {
            "category":"Shopping",
            "subcategory":"Clothing, Apparel, & Fashions",
            "type":"Retail Goods"
        }
    ],
    "sg:phone":"+1   ",
    "sg:postcode":"19611",
    "sg:province":"PA",
    "sg:tags":[
        "store"
    ],
    "wof:name":"Evan-Picone 277",
    "wof:placetype":"venue"
},
  "geometry": {"coordinates":[-75.952911,40.337119],"type":"Point"}
}