{
  "type": "Feature",
  "properties": {
    "addr:full":"221 Petersburg Rd Lititz PA 17543",
    "addr:housenumber":"221",
    "addr:postcode":"17543",
    "addr:street":"Petersburg Rd",
    "iso:country":"US",
    "sg:address":"221 Petersburg Rd",
    "sg:city":"Lititz",
    "sg:classifiers":[
        {
            "category":"Professional",
            "subcategory":"Computer Services",
            "type":"Services"
        }
    ],
    "sg:phone":"+1   ",
    "sg:postcode":"17543",
    "sg:province":"PA",
    "sg:tags":[
        "consulting",
        "training"
    ],
    "wof:name":"Impact Business Solutions",
    "wof:placetype":"venue"
},
  "geometry": {"coordinates":[-76.315798,40.104858],"type":"Point"}
}