{
  "type": "Feature",
  "properties": {
    "iso:country":"US",
    "sg:address":"1449 Stevens St",
    "sg:city":"Philadelphia",
    "sg:classifiers":[
        {
            "category":"Building & Trades",
            "subcategory":"Construction",
            "type":"Services"
        }
    ],
    "sg:phone":"+1 215 535 3686",
    "sg:postcode":"19149",
    "sg:province":"PA",
    "sg:tags":[
        "general",
        "contractor"
    ],
    "wof:name":"CMJ Construction Co",
    "wof:placetype":"venue"
},
  "geometry": {"coordinates":[-75.07888800000001,40.035968],"type":"Point"}
}