{
  "type": "Feature",
  "properties": {
    "iso:country":"US",
    "sg:address":"124 Lincoln Way W",
    "sg:city":"Chambersburg",
    "sg:classifiers":[
        {
            "category":"Real Estate",
            "subcategory":"Real Estate Agent",
            "type":"Services"
        }
    ],
    "sg:phone":"+1   ",
    "sg:postcode":"17201",
    "sg:province":"PA",
    "wof:name":"Tg Burkey Associates",
    "wof:placetype":"venue"
},
  "geometry": {"coordinates":[-77.66488,39.937919],"type":"Point"}
}