{
  "type": "Feature",
  "properties": {
    "iso:country":"US",
    "sg:address":"132 Carey Ave",
    "sg:city":"Wilkes Barre",
    "sg:classifiers":[
        {
            "category":"Real Estate",
            "subcategory":"Real Estate Agent",
            "type":"Services"
        }
    ],
    "sg:phone":"+1   ",
    "sg:postcode":"18702",
    "sg:province":"PA",
    "wof:name":"Melone Eileen R",
    "wof:placetype":"venue"
},
  "geometry": {"coordinates":[-75.901617,41.240331],"type":"Point"}
}