{
  "type": "Feature",
  "properties": {
    "iso:country":"US",
    "sg:address":"5944 Germantown Ave",
    "sg:city":"Philadelphia",
    "sg:classifiers":[
        {
            "category":"Personal",
            "subcategory":"Beauty Salon",
            "type":"Services"
        }
    ],
    "sg:phone":"+1 215 844 3622",
    "sg:postcode":"19144",
    "sg:province":"PA",
    "sg:tags":[
        "manicuring"
    ],
    "wof:name":"Royal Nails",
    "wof:placetype":"venue"
},
  "geometry": {"coordinates":[-75.17756300000001,40.038987],"type":"Point"}
}