{
  "type": "Feature",
  "properties": {
    "iso:country":"US",
    "sg:address":"1713 Route 228",
    "sg:city":"Cranberry Twp",
    "sg:classifiers":[
        {
            "category":"Retail",
            "subcategory":"Portrait Studio",
            "type":"Services"
        }
    ],
    "sg:phone":"+1 724 779 9365",
    "sg:postcode":"16066",
    "sg:province":"PA",
    "sg:tags":[
        "photography",
        "store"
    ],
    "sg:website":"www.ritzcamera.com",
    "wof:name":"Ritz Camera Service",
    "wof:placetype":"venue"
},
  "geometry": {"coordinates":[-80.070801,40.685398],"type":"Point"}
}