{
  "type": "Feature",
  "properties": {
    "addr:full":"385 Raymondskill Rd Milford PA 18337",
    "addr:housenumber":"385",
    "addr:postcode":"18337",
    "addr:street":"Raymondskill Rd",
    "iso:country":"US",
    "sg:address":"385 Raymondskill Rd",
    "sg:city":"Milford",
    "sg:classifiers":[
        {
            "category":"Health Services",
            "subcategory":"Doctor",
            "type":"Services"
        }
    ],
    "sg:phone":"+1 570 686 9832",
    "sg:postcode":"18337",
    "sg:province":"PA",
    "sg:tags":[
        "medicine",
        "physician",
        "addiction",
        "surgeons"
    ],
    "wof:name":"Serenity Facility",
    "wof:placetype":"venue"
},
  "geometry": {"coordinates":[-74.899432,41.326383],"type":"Point"}
}