{
  "type": "Feature",
  "properties": {
    "addr:full":"243 W End Rd Hanover Twp PA 18706",
    "addr:housenumber":"243",
    "addr:postcode":"18706",
    "addr:street":"W End Rd",
    "iso:country":"US",
    "sg:address":"243 W End Rd",
    "sg:city":"Hanover Twp",
    "sg:classifiers":[
        {
            "category":"Bars & Pubs",
            "type":"Food & Drink"
        }
    ],
    "sg:phone":"+1 570 823 9837",
    "sg:postcode":"18706",
    "sg:province":"PA",
    "wof:name":"Iona Cafe",
    "wof:placetype":"venue"
},
  "geometry": {"coordinates":[-75.926934,41.235546],"type":"Point"}
}