{
  "type": "Feature",
  "properties": {
    "iso:country":"US",
    "sg:address":"2501 W 12th St",
    "sg:city":"Erie",
    "sg:classifiers":[
        {
            "category":"Food & Beverages",
            "subcategory":"Liquor & Beverages",
            "type":"Retail Goods"
        }
    ],
    "sg:phone":"+1   ",
    "sg:postcode":"16505",
    "sg:province":"PA",
    "sg:tags":[
        "regulation",
        "commercial",
        "sect",
        "alcoholic"
    ],
    "wof:name":"Wine & Spirits Shoppe 2514",
    "wof:placetype":"venue"
},
  "geometry": {"coordinates":[-80.13835899999999,42.102362],"type":"Point"}
}