{
  "type": "Feature",
  "properties": {
    "addr:full":"811 Ivy Hill Rd Philadelphia PA 19150",
    "addr:housenumber":"811",
    "addr:postcode":"19150",
    "addr:street":"Ivy Hill Rd",
    "iso:country":"US",
    "sg:address":"811 Ivy Hill Rd",
    "sg:city":"Philadelphia",
    "sg:classifiers":[
        {
            "category":"Professional",
            "subcategory":"Business Services",
            "type":"Services"
        },
        {
            "category":"Building & Trades",
            "subcategory":"Construction",
            "type":"Services"
        }
    ],
    "sg:phone":"+1 215 836 7470",
    "sg:postcode":"19150",
    "sg:province":"PA",
    "sg:tags":[
        "environmental",
        "contractor",
        "testing",
        "inspection",
        "tank"
    ],
    "wof:name":"Ferrick Construction Co Inc",
    "wof:placetype":"venue"
},
  "geometry": {"coordinates":[-75.18213900000001,40.079101],"type":"Point"}
}