{
  "type": "Feature",
  "properties": {
    "addr:full":"385 Oxford Valley Rd Yardley PA 19067",
    "addr:housenumber":"385",
    "addr:postcode":"19067",
    "addr:street":"Oxford Valley Rd",
    "iso:country":"US",
    "sg:address":"385 Oxford Valley Rd",
    "sg:city":"Yardley",
    "sg:classifiers":[
        {
            "category":"Banks & Credit Unions",
            "subcategory":"Bank",
            "type":"Services"
        }
    ],
    "sg:phone":"+1 215 369 3700",
    "sg:postcode":"19067",
    "sg:province":"PA",
    "wof:name":"First Trust Bank",
    "wof:placetype":"venue"
},
  "geometry": {"coordinates":[-74.866231,40.206685],"type":"Point"}
}