{
  "type": "Feature",
  "properties": {
    "iso:country":"US",
    "sg:address":"1105 Concord Ave",
    "sg:city":"Chester",
    "sg:classifiers":[
        {
            "category":"Professional",
            "type":"Services"
        }
    ],
    "sg:phone":"+1 610 490 1970",
    "sg:postcode":"19013",
    "sg:province":"PA",
    "sg:tags":[
        "establishment"
    ],
    "wof:name":"Insitute Of Islamic Studies",
    "wof:placetype":"venue"
},
  "geometry": {"coordinates":[-75.377602,39.849623],"type":"Point"}
}