{
  "type": "Feature",
  "properties": {
    "addr:full":"1489 Baltimore Pike Springfield PA 19064",
    "addr:housenumber":"1489",
    "addr:postcode":"19064",
    "addr:street":"Baltimore Pike Springfield",
    "iso:country":"US",
    "sg:address":"1489 Baltimore Pike",
    "sg:city":"Springfield",
    "sg:classifiers":[
        {
            "category":"Health Services",
            "subcategory":"Doctor",
            "type":"Services"
        }
    ],
    "sg:phone":"+1   ",
    "sg:postcode":"19064",
    "sg:province":"PA",
    "sg:tags":[
        "osteopathic"
    ],
    "wof:name":"Medical Associates of Del Cnty",
    "wof:placetype":"venue"
},
  "geometry": {"coordinates":[-75.359262,39.9127],"type":"Point"}
}