{
  "type": "Feature",
  "properties": {
    "addr:full":"310 N Vesper St Lock Haven PA 17745",
    "addr:housenumber":"310",
    "addr:postcode":"17745",
    "addr:street":"N Vesper St",
    "iso:country":"US",
    "sg:address":"310 N Vesper St",
    "sg:city":"Lock Haven",
    "sg:classifiers":[
        {
            "category":"Personal",
            "subcategory":"Beauty Salon",
            "type":"Services"
        }
    ],
    "sg:phone":"+1 570 893 1282",
    "sg:postcode":"17745",
    "sg:province":"PA",
    "wof:name":"Donna Mark Unisex Hair Salon",
    "wof:placetype":"venue"
},
  "geometry": {"coordinates":[-77.445769,41.13768],"type":"Point"}
}