{
  "type": "Feature",
  "properties": {
    "iso:country":"US",
    "sg:address":"383 Wyoming Ave",
    "sg:city":"Kingston",
    "sg:classifiers":[
        {
            "category":"Professional",
            "subcategory":"Management & Consulting",
            "type":"Services"
        },
        {
            "category":"Professional",
            "subcategory":"Employment Agencies",
            "type":"Services"
        }
    ],
    "sg:phone":"+1 570 283 2055",
    "sg:postcode":"18704",
    "sg:province":"PA",
    "sg:tags":[
        "science",
        "consultant",
        "opportunity",
        "academic"
    ],
    "wof:name":"A J Consultants",
    "wof:placetype":"venue"
},
  "geometry": {"coordinates":[-75.89296400000001,41.265679],"type":"Point"}
}