{
  "type": "Feature",
  "properties": {
    "addr:full":"3945 Frankford Ave Philadelphia PA 19124",
    "addr:housenumber":"3945",
    "addr:postcode":"19124",
    "addr:street":"Frankford Ave",
    "iso:country":"US",
    "sg:address":"3945 Frankford Ave",
    "sg:city":"Philadelphia",
    "sg:classifiers":[
        {
            "category":"Autos & Motor Vehicles",
            "subcategory":"Automobile Sales",
            "type":"Retail Goods"
        }
    ],
    "sg:phone":"+1 215 743 4111",
    "sg:postcode":"19124",
    "sg:province":"PA",
    "sg:tags":[
        "used",
        "car",
        "dealers-used",
        "new",
        "cars-wholesale"
    ],
    "wof:name":"Frankford Auto Sales",
    "wof:placetype":"venue"
},
  "geometry": {"coordinates":[-75.09360100000001,40.004438],"type":"Point"}
}