{
  "type": "Feature",
  "properties": {
    "addr:full":"2852 Whiteford Rd York PA 17402",
    "addr:housenumber":"2852",
    "addr:postcode":"17402",
    "addr:street":"Whiteford Rd",
    "iso:country":"US",
    "sg:address":"2852 Whiteford Rd",
    "sg:city":"York",
    "sg:classifiers":[
        {
            "category":"Restaurant",
            "type":"Food & Drink"
        }
    ],
    "sg:menulink":"http://www.allmenus.com/pa/springettsbury/72625-sbarro/menu/",
    "sg:phone":"+1 717 755 5758",
    "sg:postcode":"17402",
    "sg:province":"PA",
    "sg:tags":[
        "american",
        "pizza"
    ],
    "wof:name":"Sbarro",
    "wof:placetype":"venue"
},
  "geometry": {"coordinates":[-76.67281199999999,39.987845],"type":"Point"}
}