{
  "type": "Feature",
  "properties": {
    "iso:country":"US",
    "sg:address":"2737 Mountain View Dr",
    "sg:city":"Bath",
    "sg:classifiers":[
        {
            "category":"Building & Trades",
            "subcategory":"Construction",
            "type":"Services"
        }
    ],
    "sg:phone":"+1 610 837 8737",
    "sg:postcode":"18014",
    "sg:province":"PA",
    "sg:tags":[
        "contractor"
    ],
    "wof:name":"Bruce Seamless Gutters",
    "wof:placetype":"venue"
},
  "geometry": {"coordinates":[-75.422854,40.775601],"type":"Point"}
}