{
  "type": "Feature",
  "properties": {
    "addr:full":"711 S Main St Exd Punxsutawney PA 15767",
    "addr:housenumber":"711",
    "addr:postcode":"15767",
    "addr:street":"S Main St Exd",
    "iso:country":"US",
    "sg:address":"711 S Main St Exd",
    "sg:city":"Punxsutawney",
    "sg:classifiers":[
        {
            "category":"Wholesale",
            "subcategory":"Groceries",
            "type":"Manufacturing & Wholesale Goods"
        }
    ],
    "sg:phone":"+1 814 938 5310",
    "sg:postcode":"15767",
    "sg:province":"PA",
    "sg:tags":[
        "food",
        "product"
    ],
    "wof:name":"G & G Food Svc Inc",
    "wof:placetype":"venue"
},
  "geometry": {"coordinates":[-78.98759699999999,40.9315],"type":"Point"}
}