{
  "type": "Feature",
  "properties": {
    "addr:full":"6619 Ditman St Philadelphia PA 19135",
    "addr:housenumber":"6619",
    "addr:postcode":"19135",
    "addr:street":"Ditman St",
    "iso:country":"US",
    "sg:address":"6619 Ditman St",
    "sg:city":"Philadelphia",
    "sg:classifiers":[
        {
            "category":"Government",
            "subcategory":"Fire Station",
            "type":"Public Place"
        }
    ],
    "sg:phone":"+1 215 634 1919",
    "sg:postcode":"19135",
    "sg:province":"PA",
    "sg:tags":[
        "extinguisher",
        "protection",
        "servicing",
        "equipment-repairing"
    ],
    "wof:name":"Mcr Fire Protection Company Inc",
    "wof:placetype":"venue"
},
  "geometry": {"coordinates":[-75.04896599999999,40.024537],"type":"Point"}
}