{
  "type": "Feature",
  "properties": {
    "iso:country":"US",
    "sg:address":"903 Mansion St",
    "sg:city":"Bristol",
    "sg:classifiers":[
        {
            "category":"Shopping",
            "subcategory":"Clothing, Apparel, & Fashions",
            "type":"Retail Goods"
        }
    ],
    "sg:phone":"+1   ",
    "sg:postcode":"19007",
    "sg:province":"PA",
    "wof:name":"Generations Boutique",
    "wof:placetype":"venue"
},
  "geometry": {"coordinates":[-74.854489,40.106482],"type":"Point"}
}