{
  "type": "Feature",
  "properties": {
    "iso:country":"US",
    "sg:address":"236 Highpoint Dr",
    "sg:city":"Somerset",
    "sg:classifiers":[
        {
            "category":"Building & Trades",
            "subcategory":"Construction",
            "type":"Services"
        }
    ],
    "sg:phone":"+1 814 445 8519",
    "sg:postcode":"15501",
    "sg:province":"PA",
    "sg:tags":[
        "new",
        "commercial",
        "renovation"
    ],
    "wof:name":"E & A Contracting Inc",
    "wof:placetype":"venue"
},
  "geometry": {"coordinates":[-79.099677,40.024433],"type":"Point"}
}