{
  "type": "Feature",
  "properties": {
    "iso:country":"US",
    "sg:address":"507 Hand Ave",
    "sg:city":"Lancaster",
    "sg:classifiers":[
        {
            "category":"Professional",
            "type":"Services"
        }
    ],
    "sg:phone":"+1   ",
    "sg:postcode":"17602",
    "sg:province":"PA",
    "wof:name":"Lancaster Dek Hockey Inc",
    "wof:placetype":"venue"
},
  "geometry": {"coordinates":[-76.297842,40.049718],"type":"Point"}
}