{
  "type": "Feature",
  "properties": {
    "iso:country":"US",
    "sg:address":"3368 Chichester Ave ",
    "sg:city":"Marcus Hook",
    "sg:classifiers":[
        {
            "category":"Restaurant",
            "type":"Food & Drink"
        }
    ],
    "sg:menulink":"http://www.allmenus.com/pa/upper-chichester/288941-chi-restaurant/menu/",
    "sg:phone":"+1 610 494 9662",
    "sg:postcode":"19061",
    "sg:province":"PA",
    "sg:tags":[
        "seafood",
        "sandwich",
        "american"
    ],
    "wof:name":"Chi Restaurant",
    "wof:placetype":"venue"
},
  "geometry": {"coordinates":[-75.442605,39.837442],"type":"Point"}
}