{
  "type": "Feature",
  "properties": {
    "iso:country":"US",
    "sg:address":"488 Hyde Park Rd",
    "sg:city":"Leechburg",
    "sg:classifiers":[
        {
            "category":"Food & Beverages",
            "subcategory":"Bakery",
            "type":"Retail Goods"
        }
    ],
    "sg:phone":"+1 724 845 6472",
    "sg:postcode":"15656",
    "sg:province":"PA",
    "sg:tags":[
        "doughnut"
    ],
    "wof:name":"Dunkin Donuts",
    "wof:placetype":"venue"
},
  "geometry": {"coordinates":[-79.603651,40.608738],"type":"Point"}
}