{
  "type": "Feature",
  "properties": {
    "iso:country":"US",
    "sg:address":"5833 Forbes Ave",
    "sg:city":"Pittsburgh",
    "sg:classifiers":[
        {
            "category":"Shopping",
            "subcategory":"Clothing, Apparel, & Fashions",
            "type":"Retail Goods"
        }
    ],
    "sg:phone":"+1 412 421 9600",
    "sg:postcode":"15217",
    "sg:province":"PA",
    "sg:tags":[
        "maternity",
        "clothes"
    ],
    "sg:website":"http://www.becomingmommy.com",
    "wof:name":"Becoming Mommy",
    "wof:placetype":"venue"
},
  "geometry": {"coordinates":[-79.92183199999999,40.438089],"type":"Point"}
}