{
  "type": "Feature",
  "properties": {
    "iso:country":"US",
    "sg:address":"504 S Water St",
    "sg:city":"Kittanning",
    "sg:classifiers":[
        {
            "category":"Government",
            "subcategory":"Office",
            "type":"Public Place"
        }
    ],
    "sg:phone":"+1 724 543 1811",
    "sg:postcode":"16201",
    "sg:province":"PA",
    "sg:tags":[
        "township",
        "government-city",
        "village"
    ],
    "sg:website":"http://www.penndotcrm.org",
    "wof:name":"Maintenance District 10-1",
    "wof:placetype":"venue"
},
  "geometry": {"coordinates":[-79.51599899999999,40.808567],"type":"Point"}
}