{
  "type": "Feature",
  "properties": {
    "iso:country":"US",
    "sg:address":"101 Sycamore Ave",
    "sg:city":"Folsom",
    "sg:classifiers":[
        {
            "category":"Manufacturing",
            "subcategory":"Printing",
            "type":"Manufacturing & Wholesale Goods"
        }
    ],
    "sg:phone":"+1 610 717 4516",
    "sg:postcode":"19033",
    "sg:province":"PA",
    "sg:tags":[
        "printer",
        "business",
        "form",
        "system"
    ],
    "sg:website":"http://local.ingenio.com/Listings/Details.aspx?NUM=a%3a9043413%3a13%3a4859924%3a14%3a0%3a7",
    "wof:name":"A & L Graphics",
    "wof:placetype":"venue"
},
  "geometry": {"coordinates":[-75.320892,39.8899],"type":"Point"}
}