{
  "type": "Feature",
  "properties": {
    "iso:country":"US",
    "sg:address":"692 Burmont Rd",
    "sg:city":"Drexel Hill",
    "sg:classifiers":[
        {
            "category":"Restaurant",
            "type":"Food & Drink"
        }
    ],
    "sg:phone":"+1   ",
    "sg:postcode":"19026",
    "sg:province":"PA",
    "sg:tags":[
        "eating"
    ],
    "wof:name":"Pizza Head Inc",
    "wof:placetype":"venue"
},
  "geometry": {"coordinates":[-75.306091,39.948899],"type":"Point"}
}