{
  "type": "Feature",
  "properties": {
    "iso:country":"US",
    "sg:address":"721 Moore Ave",
    "sg:city":"Bryn Mawr",
    "sg:classifiers":[
        {
            "category":"Manufacturing",
            "subcategory":"Metals",
            "type":"Manufacturing & Wholesale Goods"
        }
    ],
    "sg:phone":"+1   ",
    "sg:postcode":"19010",
    "sg:province":"PA",
    "sg:tags":[
        "ornamental",
        "work",
        "architectural",
        "mfg"
    ],
    "wof:name":"Samuel Yellin Metalworkers Co",
    "wof:placetype":"venue"
},
  "geometry": {"coordinates":[-75.323932,40.016784],"type":"Point"}
}