{
  "type": "Feature",
  "properties": {
    "iso:country":"US",
    "sg:address":"34 E 7th St",
    "sg:city":"Chester",
    "sg:classifiers":[
        {
            "category":"Restaurant",
            "type":"Food & Drink"
        }
    ],
    "sg:phone":"+1   ",
    "sg:postcode":"19013",
    "sg:province":"PA",
    "sg:tags":[
        "eating"
    ],
    "wof:name":"Chester Pizzeria",
    "wof:placetype":"venue"
},
  "geometry": {"coordinates":[-75.361518,39.85049],"type":"Point"}
}