{
  "type": "Feature",
  "properties": {
    "iso:country":"US",
    "sg:address":"625 Allegheny River Blvd",
    "sg:city":"Verona",
    "sg:classifiers":[
        {
            "category":"Shopping",
            "subcategory":"Used Merchandise",
            "type":"Retail Goods"
        }
    ],
    "sg:phone":"+1 412 828 4552",
    "sg:postcode":"15147",
    "sg:province":"PA",
    "sg:tags":[
        "second",
        "store",
        "hand"
    ],
    "wof:name":"Yesterdays Friends Resale Shop",
    "wof:placetype":"venue"
},
  "geometry": {"coordinates":[-79.843041,40.504752],"type":"Point"}
}