{
  "type": "Feature",
  "properties": {
    "iso:country":"US",
    "sg:address":"1111 4th Ave",
    "sg:city":"Patton",
    "sg:classifiers":[
        {
            "category":"Personal",
            "subcategory":"Barber",
            "type":"Services"
        }
    ],
    "sg:phone":"+1 814 674 5222",
    "sg:postcode":"16668",
    "sg:province":"PA",
    "sg:tags":[
        "shop"
    ],
    "wof:name":"Mikes Barber & Styling Shop",
    "wof:placetype":"venue"
},
  "geometry": {"coordinates":[-78.64765199999999,40.637321],"type":"Point"}
}