{
  "type": "Feature",
  "properties": {
    "addr:full":"1722 Wharton St Pittsburgh PA 15203",
    "addr:housenumber":"1722",
    "addr:postcode":"15203",
    "addr:street":"Wharton St",
    "iso:country":"US",
    "sg:address":"1722 Wharton St",
    "sg:city":"Pittsburgh",
    "sg:classifiers":[
        {
            "category":"Arts & Performance",
            "subcategory":"Theater",
            "type":"Entertainment"
        }
    ],
    "sg:phone":"+1 412 488 1542",
    "sg:postcode":"15203",
    "sg:province":"PA",
    "sg:tags":[
        "entertainer"
    ],
    "wof:name":"Disc Jockey Productions",
    "wof:placetype":"venue"
},
  "geometry": {"coordinates":[-79.98070800000001,40.430508],"type":"Point"}
}