{
  "type": "Feature",
  "properties": {
    "addr:full":"219 W Painter St Smithton PA 15425",
    "addr:housenumber":"219",
    "addr:postcode":"15425",
    "addr:street":"W Painter St",
    "iso:country":"US",
    "sg:address":"219 W Painter St",
    "sg:city":"Smithton",
    "sg:classifiers":[
        {
            "category":"Manufacturing",
            "subcategory":"Building Materials",
            "type":"Manufacturing & Wholesale Goods"
        }
    ],
    "sg:phone":"+1   ",
    "sg:postcode":"15425",
    "sg:province":"PA",
    "sg:tags":[
        "member",
        "mfg",
        "wood",
        "structural"
    ],
    "wof:name":"Trusco Inc",
    "wof:placetype":"venue"
},
  "geometry": {"coordinates":[-79.59236,40.001462],"type":"Point"}
}