{
  "type": "Feature",
  "properties": {
    "addr:full":"3 General Wayne Dr Media PA 19063",
    "addr:housenumber":"3",
    "addr:postcode":"19063",
    "addr:street":"General Wayne Dr",
    "iso:country":"US",
    "sg:address":"3 General Wayne Dr",
    "sg:city":"Media",
    "sg:classifiers":[
        {
            "category":"Communications",
            "subcategory":"Film & Video Production",
            "type":"Services"
        }
    ],
    "sg:phone":"+1 610 891 8448",
    "sg:postcode":"19063",
    "sg:province":"PA",
    "sg:tags":[
        "audio"
    ],
    "wof:name":"Invinceable Productions",
    "wof:placetype":"venue"
},
  "geometry": {"coordinates":[-75.409605,39.903692],"type":"Point"}
}