{
  "type": "Feature",
  "properties": {
    "addr:full":"850 S Irvine Ave Sharon PA 16146",
    "addr:housenumber":"850",
    "addr:postcode":"16146",
    "addr:street":"S Irvine Ave",
    "iso:country":"US",
    "sg:address":"850 S Irvine Ave",
    "sg:city":"Sharon",
    "sg:classifiers":[
        {
            "category":"Health Services",
            "subcategory":"Clinic",
            "type":"Services"
        }
    ],
    "sg:phone":"+1 724 346 1509",
    "sg:postcode":"16146",
    "sg:province":"PA",
    "wof:name":"Penn Ohio Health Care Ctr",
    "wof:placetype":"venue"
},
  "geometry": {"coordinates":[-80.51805,41.22179],"type":"Point"}
}