{
  "type": "Feature",
  "properties": {
    "addr:full":"2021 Poplar St Philadelphia PA 19130",
    "addr:housenumber":"2021",
    "addr:postcode":"19130",
    "addr:street":"Poplar St",
    "iso:country":"US",
    "sg:address":"2021 Poplar St",
    "sg:city":"Philadelphia",
    "sg:classifiers":[
        {
            "category":"Building & Trades",
            "subcategory":"Cleaning & Sanitation",
            "type":"Services"
        }
    ],
    "sg:phone":"+1 215 232 5229",
    "sg:postcode":"19130",
    "sg:province":"PA",
    "sg:tags":[
        "house"
    ],
    "wof:name":"Commercial Cleaning Specialist",
    "wof:placetype":"venue"
},
  "geometry": {"coordinates":[-75.169962,39.971547],"type":"Point"}
}