{
  "type": "Feature",
  "properties": {
    "iso:country":"US",
    "sg:address":"6209 Grays Ave",
    "sg:city":"Philadelphia",
    "sg:classifiers":[
        {
            "category":"Food & Beverages",
            "subcategory":"Bakery",
            "type":"Retail Goods"
        }
    ],
    "sg:phone":"+1 215 729 5332",
    "sg:postcode":"19142",
    "sg:province":"PA",
    "sg:tags":[
        "baker"
    ],
    "wof:name":"Matteras Bakery",
    "wof:placetype":"venue"
},
  "geometry": {"coordinates":[-75.22909799999999,39.925324],"type":"Point"}
}