{
  "type": "Feature",
  "properties": {
    "iso:country":"US",
    "sg:address":"6990 Old Harrisburg Rd",
    "sg:city":"York Springs",
    "sg:classifiers":[
        {
            "category":"Wholesale",
            "subcategory":"Machinery & Supplies",
            "type":"Manufacturing & Wholesale Goods"
        }
    ],
    "sg:phone":"+1 717 528 4805",
    "sg:postcode":"17372",
    "sg:province":"PA",
    "sg:tags":[
        "brush"
    ],
    "wof:name":"Robert D Fletcher Fuller Brush",
    "wof:placetype":"venue"
},
  "geometry": {"coordinates":[-77.113677,39.999001],"type":"Point"}
}