{
  "type": "Feature",
  "properties": {
    "iso:country":"US",
    "sg:address":"6169 Torresdale Ave",
    "sg:city":"Philadelphia",
    "sg:classifiers":[
        {
            "category":"Restaurant",
            "type":"Food & Drink"
        }
    ],
    "sg:phone":"+1   ",
    "sg:postcode":"19135",
    "sg:province":"PA",
    "sg:tags":[
        "eating"
    ],
    "wof:name":"Fats Deli and Seafood",
    "wof:placetype":"venue"
},
  "geometry": {"coordinates":[-75.056684,40.018742],"type":"Point"}
}