{
  "type": "Feature",
  "properties": {
    "iso:country":"US",
    "sg:address":"395 Arbor Rd",
    "sg:city":"Lancaster",
    "sg:classifiers":[
        {
            "category":"Building & Trades",
            "subcategory":"Construction",
            "type":"Services"
        }
    ],
    "sg:phone":"+1 717 569 6510",
    "sg:postcode":"17601",
    "sg:province":"PA",
    "sg:tags":[
        "paving",
        "contractor"
    ],
    "wof:name":"Charles A Erisman Inc",
    "wof:placetype":"venue"
},
  "geometry": {"coordinates":[-76.326921,40.091183],"type":"Point"}
}