{
  "type": "Feature",
  "properties": {
    "iso:country":"US",
    "sg:address":"5743 US Hwy 202",
    "sg:city":"Lahaska",
    "sg:classifiers":[
        {
            "category":"Manufacturing",
            "subcategory":"Jewelry",
            "type":"Manufacturing & Wholesale Goods"
        }
    ],
    "sg:phone":"+1 215 794 8138",
    "sg:postcode":"18928",
    "sg:province":"PA",
    "sg:tags":[
        "ware",
        "silverware"
    ],
    "sg:website":"www.scandinavian-touch.com",
    "wof:name":"Scandinavian Touch",
    "wof:placetype":"venue"
},
  "geometry": {"coordinates":[-75.029566,40.347043],"type":"Point"}
}