{
  "type": "Feature",
  "properties": {
    "iso:country":"US",
    "sg:address":"2750 Red Lion Rd",
    "sg:city":"Philadelphia",
    "sg:classifiers":[
        {
            "category":"Restaurant",
            "type":"Food & Drink"
        }
    ],
    "sg:phone":"+1 215 969 7746",
    "sg:postcode":"19114",
    "sg:province":"PA",
    "wof:name":"Flatspin",
    "wof:placetype":"venue"
},
  "geometry": {"coordinates":[-75.012096,40.092207],"type":"Point"}
}