{
  "type": "Feature",
  "properties": {
    "iso:country":"US",
    "sg:address":"310 Big Hills Rd",
    "sg:city":"Lake Ariel",
    "sg:classifiers":[
        {
            "category":"Shopping",
            "subcategory":"Hobbies, Toys, & Games",
            "type":"Retail Goods"
        }
    ],
    "sg:phone":"+1   ",
    "sg:postcode":"18436",
    "sg:province":"PA",
    "sg:tags":[
        "collectible"
    ],
    "wof:name":"Keystone Kollectible Kars",
    "wof:placetype":"venue"
},
  "geometry": {"coordinates":[-75.42468700000001,41.467871],"type":"Point"}
}