{
  "type": "Feature",
  "properties": {
    "addr:full":"833 W King St Shippensburg PA 17257",
    "addr:housenumber":"833",
    "addr:postcode":"17257",
    "addr:street":"W King St",
    "iso:country":"US",
    "sg:address":"833 W King St",
    "sg:city":"Shippensburg",
    "sg:classifiers":[
        {
            "category":"Insurance",
            "subcategory":"Insurance Agent",
            "type":"Services"
        }
    ],
    "sg:phone":"+1 717 530 8600",
    "sg:postcode":"17257",
    "sg:province":"PA",
    "sg:tags":[
        "auto"
    ],
    "sg:website":"http://www.carlcramerinsurance.com?utm_source=yp&utm_medium=cpc&utm_campaign=ck_yp",
    "wof:name":"CARL L CRAMER INSURANCE LLC",
    "wof:placetype":"venue"
},
  "geometry": {"coordinates":[-77.53509699999999,40.042642],"type":"Point"}
}