{
  "type": "Feature",
  "properties": {
    "addr:full":"18 Bridge St Towanda PA 18848",
    "addr:housenumber":"18",
    "addr:postcode":"18848",
    "addr:street":"Bridge St",
    "iso:country":"US",
    "sg:address":"18 Bridge St",
    "sg:city":"Towanda",
    "sg:classifiers":[
        {
            "category":"Real Estate",
            "subcategory":"Real Estate Agent",
            "type":"Services"
        }
    ],
    "sg:phone":"+1 570 265 8184",
    "sg:postcode":"18848",
    "sg:province":"PA",
    "wof:name":"Bradford Sullivan Assn-Rltrs",
    "wof:placetype":"venue"
},
  "geometry": {"coordinates":[-76.44298999999999,41.765448],"type":"Point"}
}