{
  "type": "Feature",
  "properties": {
    "iso:country":"US",
    "sg:address":"101 Spyglass Dr",
    "sg:city":"Blue Bell",
    "sg:classifiers":[
        {
            "category":"Professional",
            "subcategory":"Engineering",
            "type":"Services"
        }
    ],
    "sg:phone":"+1   ",
    "sg:postcode":"19422",
    "sg:province":"PA",
    "wof:name":"Retaqs Inc",
    "wof:placetype":"venue"
},
  "geometry": {"coordinates":[-75.28745000000001,40.173981],"type":"Point"}
}