{
  "type": "Feature",
  "properties": {
    "iso:country":"US",
    "sg:address":"6000 Babcock Blvd",
    "sg:city":"Pittsburgh",
    "sg:classifiers":[
        {
            "category":"Banks & Credit Unions",
            "subcategory":"Bank",
            "type":"Services"
        }
    ],
    "sg:phone":"+1 412 367 9010",
    "sg:postcode":"15237",
    "sg:province":"PA",
    "wof:name":"Fidelity Bank",
    "wof:placetype":"venue"
},
  "geometry": {"coordinates":[-80.023341,40.552091],"type":"Point"}
}