{
  "type": "Feature",
  "properties": {
    "iso:country":"US",
    "sg:address":"606 Mann Rd",
    "sg:city":"Horsham",
    "sg:classifiers":[
        {
            "category":"Restaurant",
            "type":"Food & Drink"
        }
    ],
    "sg:phone":"+1 215 793 0959",
    "sg:postcode":"19044",
    "sg:province":"PA",
    "sg:tags":[
        "parlor",
        "ice",
        "cream"
    ],
    "wof:name":"Joe's Water Ice",
    "wof:placetype":"venue"
},
  "geometry": {"coordinates":[-75.16722900000001,40.17388],"type":"Point"}
}