{
  "type": "Feature",
  "properties": {
    "iso:country":"US",
    "sg:address":"116 Depot St",
    "sg:city":"Clarks Summit",
    "sg:classifiers":[
        {
            "category":"Shopping",
            "subcategory":"Computers & Home Electronics",
            "type":"Retail Goods"
        },
        {
            "category":"Professional",
            "subcategory":"Computer Services",
            "type":"Services"
        }
    ],
    "sg:phone":"+1 570 587 5362",
    "sg:postcode":"18411",
    "sg:province":"PA",
    "sg:tags":[
        "repair"
    ],
    "wof:name":"Reboot",
    "wof:placetype":"venue"
},
  "geometry": {"coordinates":[-75.703665,41.49425],"type":"Point"}
}