{
  "type": "Feature",
  "properties": {
    "iso:country":"US",
    "sg:address":"2428 Brown St",
    "sg:city":"Philadelphia",
    "sg:classifiers":[
        {
            "category":"Health Services",
            "subcategory":"Doctor",
            "type":"Services"
        }
    ],
    "sg:phone":"+1   ",
    "sg:postcode":"19130",
    "sg:province":"PA",
    "sg:tags":[
        "medical"
    ],
    "wof:name":"Gerald Chalal MD",
    "wof:placetype":"venue"
},
  "geometry": {"coordinates":[-75.178056,39.970112],"type":"Point"}
}