{
  "type": "Feature",
  "properties": {
    "iso:country":"US",
    "sg:address":"127 E Gay St",
    "sg:city":"West Chester",
    "sg:classifiers":[
        {
            "category":"Health Services",
            "subcategory":"Doctor",
            "type":"Services"
        }
    ],
    "sg:phone":"+1 610 696 9244",
    "sg:postcode":"19380",
    "sg:province":"PA",
    "sg:tags":[
        "dentist"
    ],
    "wof:name":"William Grohol DDS",
    "wof:placetype":"venue"
},
  "geometry": {"coordinates":[-75.602789,39.9616],"type":"Point"}
}