{
  "type": "Feature",
  "properties": {
    "iso:country":"US",
    "sg:address":"1012 Tuckerton Ct",
    "sg:city":"Reading",
    "sg:classifiers":[
        {
            "category":"Wholesale",
            "subcategory":"Groceries",
            "type":"Manufacturing & Wholesale Goods"
        }
    ],
    "sg:phone":"+1 610 926 3663",
    "sg:postcode":"19605",
    "sg:province":"PA",
    "sg:tags":[
        "food",
        "product"
    ],
    "wof:name":"Karetas Foods Inc",
    "wof:placetype":"venue"
},
  "geometry": {"coordinates":[-75.946641,40.400726],"type":"Point"}
}