{
  "type": "Feature",
  "properties": {
    "iso:country":"US",
    "sg:address":"718 Arch St",
    "sg:city":"Philadelphia",
    "sg:classifiers":[
        {
            "category":"Organizations",
            "subcategory":"Non-profit Organization",
            "type":"Services"
        },
        {
            "category":"Professional",
            "type":"Services"
        }
    ],
    "sg:phone":"+1 215 923 3349",
    "sg:postcode":"19106",
    "sg:province":"PA",
    "sg:tags":[
        "consulting",
        "management",
        "establishment"
    ],
    "sg:website":"www.visionforequality.org",
    "wof:name":"Vision For Equality Inc",
    "wof:placetype":"venue"
},
  "geometry": {"coordinates":[-75.152929,39.953041],"type":"Point"}
}