{
  "type": "Feature",
  "properties": {
    "iso:country":"US",
    "sg:address":"16 N Oak St",
    "sg:city":"Mount Carmel",
    "sg:classifiers":[
        {
            "category":"Shopping",
            "subcategory":"Gifts & Souvenirs",
            "type":"Retail Goods"
        }
    ],
    "sg:phone":"+1   ",
    "sg:postcode":"17851",
    "sg:province":"PA",
    "sg:tags":[
        "flower"
    ],
    "wof:name":"J RS",
    "wof:placetype":"venue"
},
  "geometry": {"coordinates":[-76.41355299999999,40.797784],"type":"Point"}
}