{
  "type": "Feature",
  "properties": {
    "addr:full":"544 W Broad St Hazleton PA 18201",
    "addr:housenumber":"544",
    "addr:postcode":"18201",
    "addr:street":"W Broad St",
    "iso:country":"US",
    "sg:address":"544 W Broad St",
    "sg:city":"Hazleton",
    "sg:classifiers":[
        {
            "category":"Restaurant",
            "type":"Food & Drink"
        }
    ],
    "sg:phone":"+1 570 455 3303",
    "sg:postcode":"18201",
    "sg:province":"PA",
    "sg:tags":[
        "eating"
    ],
    "wof:name":"Peking Chinese Restaurant",
    "wof:placetype":"venue"
},
  "geometry": {"coordinates":[-75.985641,40.956944],"type":"Point"}
}