{
  "type": "Feature",
  "properties": {
    "addr:full":"3711 West Chester Pike  Newtown Square PA 19073",
    "addr:housenumber":"3711",
    "addr:postcode":"19073",
    "addr:street":"West Chester Pike",
    "iso:country":"US",
    "sg:address":"3711 West Chester Pike ",
    "sg:city":"Newtown Square",
    "sg:classifiers":[
        {
            "category":"Restaurant",
            "type":"Food & Drink"
        }
    ],
    "sg:menulink":"http://www.allmenus.com/pa/newtown-square/289236-upper-crust-pizzeria--sandwich-shoppe/menu/",
    "sg:phone":"+1 610 356 2104",
    "sg:postcode":"19073",
    "sg:province":"PA",
    "sg:tags":[
        "american",
        "pizza"
    ],
    "wof:name":"Upper Crust Pizzeria & Sandwich Shoppe",
    "wof:placetype":"venue"
},
  "geometry": {"coordinates":[-75.40181800000001,39.986933],"type":"Point"}
}