{
  "type": "Feature",
  "properties": {
    "addr:full":"8355 Loretto Ave Philadelphia PA 19152",
    "addr:postcode":"8355;19152",
    "addr:street":"Loretto Ave",
    "iso:country":"US",
    "sg:address":"8355 Loretto Ave",
    "sg:city":"Philadelphia",
    "sg:classifiers":[
        {
            "category":"Health Services",
            "subcategory":"Doctor",
            "type":"Services"
        }
    ],
    "sg:phone":"+1 215 725 8960",
    "sg:postcode":"19152",
    "sg:province":"PA",
    "sg:tags":[
        "dentist"
    ],
    "wof:name":"Rachel Salzberg DDS",
    "wof:placetype":"venue"
},
  "geometry": {"coordinates":[-75.053241,40.067499],"type":"Point"}
}