{
  "type": "Feature",
  "properties": {
    "iso:country":"US",
    "sg:address":"401 Coates St",
    "sg:city":"Bridgeport",
    "sg:classifiers":[
        {
            "category":"Shopping",
            "subcategory":"Computers & Home Electronics",
            "type":"Retail Goods"
        }
    ],
    "sg:phone":"+1 610 275 3233",
    "sg:postcode":"19405",
    "sg:province":"PA",
    "sg:tags":[
        "equipment",
        "electronic",
        "supply"
    ],
    "wof:name":"Hanifin Electronics Corp",
    "wof:placetype":"venue"
},
  "geometry": {"coordinates":[-75.337667,40.100827],"type":"Point"}
}