{
  "type": "Feature",
  "properties": {
    "iso:country":"US",
    "sg:address":"3506 Main St",
    "sg:city":"Munhall",
    "sg:classifiers":[
        {
            "category":"Health Services",
            "subcategory":"Chiropractor",
            "type":"Services"
        }
    ],
    "sg:phone":"+1 412 461 1442",
    "sg:postcode":"15120",
    "sg:province":"PA",
    "wof:name":"Munhall Chiropractic Ctr",
    "wof:placetype":"venue"
},
  "geometry": {"coordinates":[-79.90344,40.385214],"type":"Point"}
}