{
  "type": "Feature",
  "properties": {
    "iso:country":"US",
    "sg:address":"1012 Highland Pl",
    "sg:city":"Altoona",
    "sg:classifiers":[
        {
            "category":"Building & Trades",
            "subcategory":"Electrical",
            "type":"Services"
        }
    ],
    "sg:phone":"+1   ",
    "sg:postcode":"16601",
    "sg:province":"PA",
    "sg:tags":[
        "electrical",
        "contractor"
    ],
    "wof:name":"Cover Electric",
    "wof:placetype":"venue"
},
  "geometry": {"coordinates":[-78.403103,40.520041],"type":"Point"}
}