{
  "type": "Feature",
  "properties": {
    "iso:country":"US",
    "sg:address":"2505 S Broad St",
    "sg:city":"Philadelphia",
    "sg:classifiers":[
        {
            "category":"Health Services",
            "subcategory":"Chiropractor",
            "type":"Services"
        }
    ],
    "sg:phone":"+1 215 551 3340",
    "sg:postcode":"19148",
    "sg:province":"PA",
    "wof:name":"Demarino Chiropractic Ctr",
    "wof:placetype":"venue"
},
  "geometry": {"coordinates":[-75.17047599999999,39.919159],"type":"Point"}
}