{
  "type": "Feature",
  "properties": {
    "iso:country":"US",
    "sg:address":"458 Castle St",
    "sg:city":"Johnstown",
    "sg:classifiers":[
        {
            "category":"Utilities",
            "subcategory":"Refuse",
            "type":"Services"
        }
    ],
    "sg:phone":"+1 814 539 0444",
    "sg:postcode":"15906",
    "sg:province":"PA",
    "sg:tags":[
        "garbage",
        "collection",
        "system"
    ],
    "wof:name":"M & F Trucking & Disposal",
    "wof:placetype":"venue"
},
  "geometry": {"coordinates":[-78.91535500000001,40.347775],"type":"Point"}
}