{
  "type": "Feature",
  "properties": {
    "iso:country":"US",
    "sg:address":"100 Pine St",
    "sg:city":"Harrisburg",
    "sg:classifiers":[
        {
            "category":"Banks & Credit Unions",
            "subcategory":"Investment Brokerage",
            "type":"Services"
        }
    ],
    "sg:phone":"+1   ",
    "sg:postcode":"17101",
    "sg:province":"PA",
    "sg:tags":[
        "banker"
    ],
    "wof:name":"Wfg Capital Advisors LP",
    "wof:placetype":"venue"
},
  "geometry": {"coordinates":[-76.88587099999999,40.261358],"type":"Point"}
}