{
  "type": "Feature",
  "properties": {
    "addr:full":"310 Macdade Blvd Folsom PA 19033",
    "addr:housenumber":"310",
    "addr:postcode":"19033",
    "addr:street":"Macdade Blvd",
    "iso:country":"US",
    "sg:address":"310 Macdade Blvd",
    "sg:city":"Folsom",
    "sg:classifiers":[
        {
            "category":"Restaurant",
            "type":"Food & Drink"
        }
    ],
    "sg:phone":"+1   ",
    "sg:postcode":"19033",
    "sg:province":"PA",
    "sg:tags":[
        "eating"
    ],
    "wof:name":"Wendys",
    "wof:placetype":"venue"
},
  "geometry": {"coordinates":[-75.327001,39.888769],"type":"Point"}
}