{
  "type": "Feature",
  "properties": {
    "iso:country":"US",
    "sg:address":"116 W Market St",
    "sg:city":"Mc Connellsburg",
    "sg:classifiers":[
        {
            "category":"Government",
            "subcategory":"Office",
            "type":"Public Place"
        }
    ],
    "sg:phone":"+1 717 485 3201",
    "sg:postcode":"17233",
    "sg:province":"PA",
    "sg:tags":[
        "county",
        "safety",
        "order"
    ],
    "wof:name":"Fulton County Emergency Mgmt",
    "wof:placetype":"venue"
},
  "geometry": {"coordinates":[-77.998728,39.933839],"type":"Point"}
}