{
  "type": "Feature",
  "properties": {
    "addr:full":"1 Bala Plz Bala Cynwyd PA 19004",
    "addr:housenumber":"1",
    "addr:postcode":"19004",
    "addr:street":"Bala Plz",
    "iso:country":"US",
    "sg:address":"1 Bala Plz",
    "sg:city":"Bala Cynwyd",
    "sg:classifiers":[
        {
            "category":"Professional",
            "subcategory":"Research",
            "type":"Services"
        }
    ],
    "sg:phone":"+1 610 667 1110",
    "sg:postcode":"19004",
    "sg:province":"PA",
    "sg:tags":[
        "nonphysical",
        "commercial",
        "market",
        "analysis"
    ],
    "sg:website":"www.focussuites.com",
    "wof:name":"Focus Suites of Philadelphia",
    "wof:placetype":"venue"
},
  "geometry": {"coordinates":[-75.23005999999999,40.001799],"type":"Point"}
}