{
  "type": "Feature",
  "properties": {
    "iso:country":"US",
    "sg:address":"2350 Mount Rose Ave",
    "sg:city":"York",
    "sg:classifiers":[
        {
            "category":"Food & Beverages",
            "subcategory":"Specialty",
            "type":"Retail Goods"
        }
    ],
    "sg:phone":"+1 717 755 5757",
    "sg:postcode":"17402",
    "sg:province":"PA",
    "sg:tags":[
        "water",
        "bulk",
        "company"
    ],
    "wof:name":"Yowza Spring Water",
    "wof:placetype":"venue"
},
  "geometry": {"coordinates":[-76.68253199999999,39.958209],"type":"Point"}
}