{
  "type": "Feature",
  "properties": {
    "iso:country":"US",
    "sg:address":"68 Greenwood Cir",
    "sg:city":"Lemoyne",
    "sg:classifiers":[
        {
            "category":"Organizations",
            "subcategory":"Religious Organization",
            "type":"Services"
        }
    ],
    "sg:phone":"+1 717 761 1255",
    "sg:postcode":"17043",
    "sg:province":"PA",
    "wof:name":"Lynne Diehl",
    "wof:placetype":"venue"
},
  "geometry": {"coordinates":[-76.906124,40.256799],"type":"Point"}
}