{
  "type": "Feature",
  "properties": {
    "iso:country":"US",
    "sg:address":"550 W New Castle St",
    "sg:city":"Zelienople",
    "sg:classifiers":[
        {
            "category":"Manufacturing",
            "subcategory":"Tools & Machinery",
            "type":"Manufacturing & Wholesale Goods"
        }
    ],
    "sg:phone":"+1 724 452 8300",
    "sg:postcode":"16063",
    "sg:province":"PA",
    "sg:tags":[
        "equipment",
        "construction"
    ],
    "sg:website":"www.universalscaffold.com",
    "wof:name":"Universal Manufacturing Corp",
    "wof:placetype":"venue"
},
  "geometry": {"coordinates":[-80.15058999999999,40.794413],"type":"Point"}
}