{
  "type": "Feature",
  "properties": {
    "iso:country":"US",
    "sg:address":"111 Floral Vale Blvd",
    "sg:city":"Morrisville",
    "sg:classifiers":[
        {
            "category":"Sports & Exercise",
            "subcategory":"Gym",
            "type":"Entertainment"
        }
    ],
    "sg:phone":"+1   ",
    "sg:postcode":"19067",
    "sg:province":"PA",
    "sg:tags":[
        "fitness",
        "physical",
        "facility"
    ],
    "wof:name":"Passport Health",
    "wof:placetype":"venue"
},
  "geometry": {"coordinates":[-74.884878,40.218797],"type":"Point"}
}