{
  "type": "Feature",
  "properties": {
    "addr:full":"432 Green St Sewickley PA 15143",
    "addr:housenumber":"432",
    "addr:postcode":"15143",
    "addr:street":"Green St",
    "iso:country":"US",
    "sg:address":"432 Green St",
    "sg:city":"Sewickley",
    "sg:classifiers":[
        {
            "category":"Insurance",
            "subcategory":"Insurance Agent",
            "type":"Services"
        }
    ],
    "sg:phone":"+1 412 741 5599",
    "sg:postcode":"15143",
    "sg:province":"PA",
    "wof:name":"State Farm Insurance",
    "wof:placetype":"venue"
},
  "geometry": {"coordinates":[-80.180843,40.540474],"type":"Point"}
}