{
  "type": "Feature",
  "properties": {
    "addr:full":"6907 Bristol Pike Levittown PA 19057",
    "addr:housenumber":"6907",
    "addr:postcode":"19057",
    "addr:street":"Bristol Pike Levittown",
    "iso:country":"US",
    "sg:address":"6907 Bristol Pike",
    "sg:city":"Levittown",
    "sg:classifiers":[
        {
            "category":"Shopping",
            "subcategory":"Musical Instruments",
            "type":"Retail Goods"
        }
    ],
    "sg:phone":"+1 215 946 1256",
    "sg:postcode":"19057",
    "sg:province":"PA",
    "sg:tags":[
        "guitar",
        "amplifier"
    ],
    "wof:name":"Kingston Sound",
    "wof:placetype":"venue"
},
  "geometry": {"coordinates":[-74.837692,40.12545],"type":"Point"}
}