{
  "type": "Feature",
  "properties": {
    "addr:full":"601 S Broad St Philadelphia PA 19147",
    "addr:housenumber":"601",
    "addr:postcode":"19147",
    "addr:street":"S Broad St",
    "iso:country":"US",
    "sg:address":"601 S Broad St",
    "sg:city":"Philadelphia",
    "sg:classifiers":[
        {
            "category":"Arts & Performance",
            "subcategory":"Arts Center",
            "type":"Entertainment"
        },
        {
            "category":"Cinema",
            "subcategory":"Movie Theater",
            "type":"Entertainment"
        }
    ],
    "sg:phone":"+1 215 545 0590",
    "sg:postcode":"19147",
    "sg:province":"PA",
    "sg:tags":[
        "performing"
    ],
    "wof:name":"Phila Arts Bank At the Univ of the Arts",
    "wof:placetype":"venue"
},
  "geometry": {"coordinates":[-75.165497,39.943699],"type":"Point"}
}