{
  "type": "Feature",
  "properties": {
    "addr:full":"1550 W Princess St York PA 17404",
    "addr:housenumber":"1550",
    "addr:postcode":"17404",
    "addr:street":"W Princess St",
    "iso:country":"US",
    "sg:address":"1550 W Princess St",
    "sg:city":"York",
    "sg:classifiers":[
        {
            "category":"Health Services",
            "subcategory":"Medical Lab",
            "type":"Services"
        }
    ],
    "sg:phone":"+1 717 845 1800",
    "sg:postcode":"17404",
    "sg:province":"PA",
    "sg:tags":[
        "laboratory"
    ],
    "wof:name":"Select Dental Studio",
    "wof:placetype":"venue"
},
  "geometry": {"coordinates":[-76.75967900000001,39.948371],"type":"Point"}
}