{
  "type": "Feature",
  "properties": {
    "iso:country":"US",
    "sg:address":"91 Tomlinson Rd",
    "sg:city":"Airville",
    "sg:classifiers":[
        {
            "category":"Farming",
            "subcategory":"Dairy Farm",
            "type":"Manufacturing & Wholesale Goods"
        }
    ],
    "sg:phone":"+1   ",
    "sg:postcode":"17302",
    "sg:province":"PA",
    "wof:name":"Melvin Glatfelter",
    "wof:placetype":"venue"
},
  "geometry": {"coordinates":[-76.439261,39.839928],"type":"Point"}
}