{
  "type": "Feature",
  "properties": {
    "iso:country":"US",
    "sg:address":"1342 Cottman Ave",
    "sg:city":"Philadelphia",
    "sg:classifiers":[
        {
            "category":"Health Services",
            "subcategory":"Doctor",
            "type":"Services"
        }
    ],
    "sg:phone":"+1 215 745 1612",
    "sg:postcode":"19111",
    "sg:province":"PA",
    "sg:tags":[
        "physician",
        "surgeon"
    ],
    "wof:name":"Urological Associates",
    "wof:placetype":"venue"
},
  "geometry": {"coordinates":[-75.076919,40.057391],"type":"Point"}
}