{
  "type": "Feature",
  "properties": {
    "iso:country":"US",
    "sg:address":"185 Wilmont Ave",
    "sg:city":"Washington",
    "sg:classifiers":[
        {
            "category":"Professional",
            "subcategory":"Management & Consulting",
            "type":"Services"
        }
    ],
    "sg:phone":"+1 724 222 4858",
    "sg:postcode":"15301",
    "sg:province":"PA",
    "sg:tags":[
        "consultant"
    ],
    "wof:name":"Logistics Management Consulting",
    "wof:placetype":"venue"
},
  "geometry": {"coordinates":[-80.23531199999999,40.178518],"type":"Point"}
}