{
  "type": "Feature",
  "properties": {
    "addr:full":"273 Fox Run Exton PA 19341",
    "addr:housenumber":"273",
    "addr:postcode":"19341",
    "addr:street":"Fox Run",
    "iso:country":"US",
    "sg:address":"273 Fox Run",
    "sg:city":"Exton",
    "sg:classifiers":[
        {
            "category":"Building & Trades",
            "subcategory":"Construction",
            "type":"Services"
        }
    ],
    "sg:phone":"+1 610 594 8231",
    "sg:postcode":"19341",
    "sg:province":"PA",
    "sg:tags":[
        "contractor"
    ],
    "wof:name":"Haas Contracting",
    "wof:placetype":"venue"
},
  "geometry": {"coordinates":[-75.63940700000001,40.036091],"type":"Point"}
}