{
  "type": "Feature",
  "properties": {
    "addr:full":"933 S High St West Chester PA 19382",
    "addr:housenumber":"933",
    "addr:postcode":"19382",
    "addr:street":"S High St",
    "iso:country":"US",
    "sg:address":"933 S High St",
    "sg:city":"West Chester",
    "sg:classifiers":[
        {
            "category":"Banks & Credit Unions",
            "subcategory":"Investment Brokerage",
            "type":"Services"
        }
    ],
    "sg:phone":"+1 610 429 4191",
    "sg:postcode":"19382",
    "sg:province":"PA",
    "sg:tags":[
        "consultant",
        "planning",
        "financial"
    ],
    "wof:name":"Brickshire Investments",
    "wof:placetype":"venue"
},
  "geometry": {"coordinates":[-75.592033,39.944111],"type":"Point"}
}