{
  "type": "Feature",
  "properties": {
    "iso:country":"US",
    "sg:address":"944 S Eagle Valley Rd",
    "sg:city":"Bellefonte",
    "sg:classifiers":[
        {
            "category":"Retail",
            "subcategory":"Auto Repair",
            "type":"Services"
        }
    ],
    "sg:phone":"+1 814 357 7978",
    "sg:postcode":"16823",
    "sg:province":"PA",
    "sg:tags":[
        "body",
        "automobile",
        "painting",
        "repairing"
    ],
    "wof:name":"Royal Master Collision",
    "wof:placetype":"venue"
},
  "geometry": {"coordinates":[-77.818695,40.933254],"type":"Point"}
}