{
  "type": "Feature",
  "properties": {
    "addr:full":"580 S Aiken Ave Ste 201 Pittsburgh PA 15232",
    "addr:housenumber":"580",
    "addr:postcode":"15232",
    "addr:street":"S Aiken Ave Ste 201",
    "iso:country":"US",
    "sg:address":"580 S Aiken Ave Ste 201",
    "sg:city":"Pittsburgh",
    "sg:classifiers":[
        {
            "category":"Health Services",
            "subcategory":"Doctor",
            "type":"Services"
        },
        {
            "category":"Health Services",
            "subcategory":"Clinic",
            "type":"Services"
        },
        {
            "category":"Community Center",
            "type":"Public Place"
        }
    ],
    "sg:phone":"+1 412 681 0172",
    "sg:postcode":"15232",
    "sg:province":"PA",
    "sg:tags":[
        "physician",
        "pediatrics",
        "medical",
        "surgeons",
        "dermatology",
        "surgeon",
        "surgery-general"
    ],
    "wof:name":"Upmc Dermatology",
    "wof:placetype":"venue"
},
  "geometry": {"coordinates":[-79.93730600000001,40.45382],"type":"Point"}
}