{
  "type": "Feature",
  "properties": {
    "iso:country":"US",
    "sg:address":"110 Centerville Ln",
    "sg:city":"Cecil",
    "sg:classifiers":[
        {
            "category":"Manufacturing",
            "subcategory":"Metals",
            "type":"Manufacturing & Wholesale Goods"
        }
    ],
    "sg:phone":"+1 724 745 0300",
    "sg:postcode":"15333",
    "sg:province":"PA",
    "sg:tags":[
        "manufacture",
        "casting",
        "nonferrous"
    ],
    "sg:website":"www.millercentrifugal.com",
    "wof:name":"Miller Centrifugal Casting Co",
    "wof:placetype":"venue"
},
  "geometry": {"coordinates":[-79.974912,40.047037],"type":"Point"}
}