{
  "type": "Feature",
  "properties": {
    "iso:country":"US",
    "sg:address":"1040 5th Ave",
    "sg:city":"Pittsburgh",
    "sg:classifiers":[
        {
            "category":"Professional",
            "subcategory":"Lawyer & Legal Services",
            "type":"Services"
        }
    ],
    "sg:phone":"+1 412 391 0818",
    "sg:postcode":"15219",
    "sg:province":"PA",
    "wof:name":"Bua Ronald J Atty",
    "wof:placetype":"venue"
},
  "geometry": {"coordinates":[-79.99050099999999,40.438801],"type":"Point"}
}