{
  "type": "Feature",
  "properties": {
    "iso:country":"US",
    "sg:address":"1043 W County Line Rd",
    "sg:city":"Hatboro",
    "sg:classifiers":[
        {
            "category":"Banks & Credit Unions",
            "subcategory":"Bank",
            "type":"Services"
        },
        {
            "category":"Banks & Credit Unions",
            "subcategory":"Financial Services",
            "type":"Services"
        }
    ],
    "sg:phone":"+1 215 674 1720",
    "sg:postcode":"19040",
    "sg:province":"PA",
    "sg:tags":[
        "commercial",
        "loan",
        "saving"
    ],
    "wof:name":"Beneficial Savings Bank 14",
    "wof:placetype":"venue"
},
  "geometry": {"coordinates":[-75.119907,40.200049],"type":"Point"}
}