{
  "type": "Feature",
  "properties": {
    "addr:full":"1974 Devereaux Ave Philadelphia PA 19149",
    "addr:housenumber":"1974",
    "addr:postcode":"19149",
    "addr:street":"Devereaux Ave",
    "iso:country":"US",
    "sg:address":"1974 Devereaux Ave",
    "sg:city":"Philadelphia",
    "sg:classifiers":[
        {
            "category":"Personal",
            "subcategory":"Beauty Salon",
            "type":"Services"
        }
    ],
    "sg:phone":"+1 215 744 5560",
    "sg:postcode":"19149",
    "sg:province":"PA",
    "sg:tags":[
        "shop"
    ],
    "wof:name":"Sawosko's Hairlines",
    "wof:placetype":"venue"
},
  "geometry": {"coordinates":[-75.07427,40.033885],"type":"Point"}
}