{
  "type": "Feature",
  "properties": {
    "iso:country":"US",
    "sg:address":"4250 Wissahickon Ave",
    "sg:city":"Philadelphia",
    "sg:classifiers":[
        {
            "category":"Professional",
            "type":"Services"
        }
    ],
    "sg:phone":"+1 215 430 0388",
    "sg:postcode":"19129",
    "sg:province":"PA",
    "sg:tags":[
        "casino"
    ],
    "wof:name":"Keystone Gaming",
    "wof:placetype":"venue"
},
  "geometry": {"coordinates":[-75.16972,40.014187],"type":"Point"}
}