{
  "type": "Feature",
  "properties": {
    "addr:full":"71 Circle Dr Hollidaysburg PA 16648",
    "addr:housenumber":"71",
    "addr:postcode":"16648",
    "addr:street":"Circle Dr",
    "iso:country":"US",
    "sg:address":"71 Circle Dr",
    "sg:city":"Hollidaysburg",
    "sg:classifiers":[
        {
            "category":"Home & Garden",
            "subcategory":"Garden Supply",
            "type":"Retail Goods"
        }
    ],
    "sg:phone":"+1   ",
    "sg:postcode":"16648",
    "sg:province":"PA",
    "wof:name":"Auss Irrigation Services LLC",
    "wof:placetype":"venue"
},
  "geometry": {"coordinates":[-78.38257900000001,40.445605],"type":"Point"}
}