{
  "type": "Feature",
  "properties": {
    "iso:country":"US",
    "sg:address":"729 W Broad St",
    "sg:city":"Bethlehem",
    "sg:classifiers":[
        {
            "category":"Shopping",
            "subcategory":"Used Merchandise",
            "type":"Retail Goods"
        }
    ],
    "sg:phone":"+1 610 865 3880",
    "sg:postcode":"18018",
    "sg:province":"PA",
    "sg:tags":[
        "antique"
    ],
    "wof:name":"Valley Antiques Gifts & Import",
    "wof:placetype":"venue"
},
  "geometry": {"coordinates":[-75.39340799999999,40.622452],"type":"Point"}
}