{
  "type": "Feature",
  "properties": {
    "iso:country":"US",
    "sg:address":"927 Evans City Rd",
    "sg:city":"Renfrew",
    "sg:classifiers":[
        {
            "category":"Retail",
            "subcategory":"Portrait Studio",
            "type":"Services"
        }
    ],
    "sg:phone":"+1 724 789 7228",
    "sg:postcode":"16053",
    "sg:province":"PA",
    "sg:tags":[
        "photographer"
    ],
    "wof:name":"Huffman Photographic Studio",
    "wof:placetype":"venue"
},
  "geometry": {"coordinates":[-79.992028,40.844439],"type":"Point"}
}