{
  "type": "Feature",
  "properties": {
    "addr:full":"231 Bailey Rd Creekside PA 15732",
    "addr:housenumber":"231",
    "addr:postcode":"15732",
    "addr:street":"Bailey Rd",
    "iso:country":"US",
    "sg:address":"231 Bailey Rd",
    "sg:city":"Creekside",
    "sg:classifiers":[
        {
            "category":"Wholesale",
            "subcategory":"Machinery & Supplies",
            "type":"Manufacturing & Wholesale Goods"
        }
    ],
    "sg:phone":"+1 724 397 2671",
    "sg:postcode":"15732",
    "sg:province":"PA",
    "sg:tags":[
        "equipment",
        "establishment",
        "repair"
    ],
    "wof:name":"Blystone Taxidermy",
    "wof:placetype":"venue"
},
  "geometry": {"coordinates":[-79.220664,40.751632],"type":"Point"}
}