{
  "type": "Feature",
  "properties": {
    "iso:country":"US",
    "sg:address":"5005 Lindermer Ave",
    "sg:city":"Bethel Park",
    "sg:classifiers":[
        {
            "category":"Autos & Motor Vehicles",
            "subcategory":"Fuel & Gas Station",
            "type":"Retail Goods"
        }
    ],
    "sg:phone":"+1 412 835 8989",
    "sg:postcode":"15102",
    "sg:province":"PA",
    "sg:tags":[
        "oil"
    ],
    "wof:name":"Slaney Service Ctr",
    "wof:placetype":"venue"
},
  "geometry": {"coordinates":[-80.02821,40.341803],"type":"Point"}
}