{
  "type": "Feature",
  "properties": {
    "iso:country":"US",
    "sg:address":"1200 W 9th St",
    "sg:city":"Chester",
    "sg:classifiers":[
        {
            "category":"Personal",
            "subcategory":"Barber",
            "type":"Services"
        }
    ],
    "sg:phone":"+1 610 876 3722",
    "sg:postcode":"19013",
    "sg:province":"PA",
    "sg:tags":[
        "shop"
    ],
    "wof:name":"Mr C's Barber Shop",
    "wof:placetype":"venue"
},
  "geometry": {"coordinates":[-75.378418,39.845362],"type":"Point"}
}