{
  "type": "Feature",
  "properties": {
    "iso:country":"US",
    "sg:address":"4567 Wayne Ave",
    "sg:city":"Philadelphia",
    "sg:classifiers":[
        {
            "category":"Manufacturing",
            "subcategory":"Tools & Machinery",
            "type":"Manufacturing & Wholesale Goods"
        }
    ],
    "sg:phone":"+1 215 843 4567",
    "sg:postcode":"19144",
    "sg:province":"PA",
    "sg:tags":[
        "machine",
        "textile",
        "knitting",
        "mfg"
    ],
    "wof:name":"Bearing Products Company",
    "wof:placetype":"venue"
},
  "geometry": {"coordinates":[-75.162885,40.022779],"type":"Point"}
}