{
  "type": "Feature",
  "properties": {
    "iso:country":"US",
    "sg:address":"223 Wilmington Pike",
    "sg:city":"Glen Mills",
    "sg:classifiers":[
        {
            "category":"Professional",
            "subcategory":"Employment Agencies",
            "type":"Services"
        }
    ],
    "sg:phone":"+1   ",
    "sg:postcode":"19342",
    "sg:province":"PA",
    "sg:tags":[
        "nursing",
        "temp"
    ],
    "wof:name":"Chadds Ford Alternative Care",
    "wof:placetype":"venue"
},
  "geometry": {"coordinates":[-75.54319700000001,39.859271],"type":"Point"}
}