{
  "type": "Feature",
  "properties": {
    "iso:country":"US",
    "sg:address":"1455 N Keel Ridge Rd",
    "sg:city":"Hermitage",
    "sg:classifiers":[
        {
            "category":"Organizations",
            "subcategory":"Religious Organization",
            "type":"Services"
        }
    ],
    "sg:phone":"+1 724 962 8206",
    "sg:postcode":"16148",
    "sg:province":"PA",
    "sg:tags":[
        "church"
    ],
    "wof:name":"First Assembly Of God",
    "wof:placetype":"venue"
},
  "geometry": {"coordinates":[-80.44089700000001,41.25294],"type":"Point"}
}