{
  "type": "Feature",
  "properties": {
    "iso:country":"US",
    "sg:address":"620 Warrendale Rd",
    "sg:city":"Wexford",
    "sg:classifiers":[
        {
            "category":"Health Services",
            "subcategory":"Doctor",
            "type":"Services"
        }
    ],
    "sg:phone":"+1 724 940 3223",
    "sg:postcode":"15090",
    "sg:province":"PA",
    "sg:tags":[
        "medicine",
        "surgeon",
        "internal",
        "cosmetic"
    ],
    "wof:name":"About Face Institute of Cosmetic Surgery",
    "wof:placetype":"venue"
},
  "geometry": {"coordinates":[-80.056702,40.651901],"type":"Point"}
}