{
  "type": "Feature",
  "properties": {
    "iso:country":"US",
    "sg:address":"3007 Grays Ferry Ave",
    "sg:city":"Philadelphia",
    "sg:classifiers":[
        {
            "category":"Cinema",
            "subcategory":"Movie Rental",
            "type":"Entertainment"
        }
    ],
    "sg:phone":"+1 215 462 2670",
    "sg:postcode":"19146",
    "sg:province":"PA",
    "sg:tags":[
        "leasing",
        "video",
        "disc",
        "tape"
    ],
    "wof:name":"Blockbuster Video",
    "wof:placetype":"venue"
},
  "geometry": {"coordinates":[-75.19386299999999,39.939105],"type":"Point"}
}