{
  "type": "Feature",
  "properties": {
    "iso:country":"US",
    "sg:address":"1017 French St",
    "sg:city":"Erie",
    "sg:classifiers":[
        {
            "category":"Social Services",
            "subcategory":"Adult Care",
            "type":"Services"
        }
    ],
    "sg:phone":"+1   ",
    "sg:postcode":"16501",
    "sg:province":"PA",
    "sg:tags":[
        "residential"
    ],
    "wof:name":"Titus House",
    "wof:placetype":"venue"
},
  "geometry": {"coordinates":[-80.08062,42.125191],"type":"Point"}
}