{
  "type": "Feature",
  "properties": {
    "iso:country":"US",
    "sg:address":"1155 Roberts St",
    "sg:city":"Nanty Glo",
    "sg:classifiers":[
        {
            "category":"Organizations",
            "subcategory":"Religious Organization",
            "type":"Services"
        }
    ],
    "sg:phone":"+1 814 749 0181",
    "sg:postcode":"15943",
    "sg:province":"PA",
    "sg:tags":[
        "church"
    ],
    "wof:name":"Alliance Church",
    "wof:placetype":"venue"
},
  "geometry": {"coordinates":[-78.839479,40.471066],"type":"Point"}
}