{
  "type": "Feature",
  "properties": {
    "iso:country":"US",
    "sg:address":"1011 W Baltimore Pike",
    "sg:city":"West Grove",
    "sg:classifiers":[
        {
            "category":"Health Services",
            "subcategory":"Doctor",
            "type":"Services"
        }
    ],
    "sg:phone":"+1 610 869 0234",
    "sg:postcode":"19390",
    "sg:province":"PA",
    "wof:name":"Demuth Brian C MD",
    "wof:placetype":"venue"
},
  "geometry": {"coordinates":[-75.88795,39.8226],"type":"Point"}
}