{
  "type": "Feature",
  "properties": {
    "addr:full":"3611 Fox St Philadelphia PA 19129",
    "addr:housenumber":"3611",
    "addr:postcode":"19129",
    "addr:street":"Fox St",
    "iso:country":"US",
    "sg:address":"3611 Fox St",
    "sg:city":"Philadelphia",
    "sg:classifiers":[
        {
            "category":"Shopping",
            "subcategory":"Books",
            "type":"Retail Goods"
        }
    ],
    "sg:phone":"+1   ",
    "sg:postcode":"19129",
    "sg:province":"PA",
    "wof:name":"American Bible Society",
    "wof:placetype":"venue"
},
  "geometry": {"coordinates":[-75.183573,40.019079],"type":"Point"}
}