{
  "type": "Feature",
  "properties": {
    "iso:country":"US",
    "sg:address":"4110 Whiting Rd",
    "sg:city":"Philadelphia",
    "sg:classifiers":[
        {
            "category":"Landmark",
            "subcategory":"Tourist Information",
            "type":"Public Place"
        },
        {
            "category":"Landmark",
            "subcategory":"Tourist Attraction",
            "type":"Public Place"
        }
    ],
    "sg:phone":"+1 215 824 3623",
    "sg:postcode":"19154",
    "sg:province":"PA",
    "sg:tags":[
        "tour",
        "promoter",
        "tours-operators",
        "sightseeing"
    ],
    "wof:name":"Ray's Guide Service",
    "wof:placetype":"venue"
},
  "geometry": {"coordinates":[-74.971844,40.083955],"type":"Point"}
}