{
  "type": "Feature",
  "properties": {
    "iso:country":"US",
    "sg:address":"313 N Main Ave",
    "sg:city":"Scranton",
    "sg:classifiers":[
        {
            "category":"Personal",
            "subcategory":"Beauty Salon",
            "type":"Services"
        }
    ],
    "sg:phone":"+1 570 347 1009",
    "sg:postcode":"18504",
    "sg:province":"PA",
    "sg:tags":[
        "shop"
    ],
    "wof:name":"Linda Lee's Hair Salon",
    "wof:placetype":"venue"
},
  "geometry": {"coordinates":[-75.677638,41.414742],"type":"Point"}
}