{
  "type": "Feature",
  "properties": {
    "addr:full":"780 Meldon Ave Donora PA 15033",
    "addr:housenumber":"780",
    "addr:postcode":"15033",
    "addr:street":"Meldon Ave",
    "iso:country":"US",
    "sg:address":"780 Meldon Ave",
    "sg:city":"Donora",
    "sg:classifiers":[
        {
            "category":"Social Services",
            "subcategory":"Child Care",
            "type":"Services"
        }
    ],
    "sg:phone":"+1 724 379 9411",
    "sg:postcode":"15033",
    "sg:province":"PA",
    "sg:tags":[
        "day"
    ],
    "wof:name":"Community Action SW Head Start",
    "wof:placetype":"venue"
},
  "geometry": {"coordinates":[-79.854888,40.180391],"type":"Point"}
}