{
  "type": "Feature",
  "properties": {
    "addr:full":"509 13th St Franklin PA 16323",
    "addr:housenumber":"509",
    "addr:postcode":"16323",
    "addr:street":"13Th St",
    "iso:country":"US",
    "sg:address":"509 13th St",
    "sg:city":"Franklin",
    "sg:classifiers":[
        {
            "category":"Professional",
            "subcategory":"Business Services",
            "type":"Services"
        }
    ],
    "sg:phone":"+1   ",
    "sg:postcode":"16323",
    "sg:province":"PA",
    "sg:tags":[
        "agency",
        "tax",
        "collection"
    ],
    "wof:name":"The Central Tax Bureau of PA",
    "wof:placetype":"venue"
},
  "geometry": {"coordinates":[-79.83162,41.396791],"type":"Point"}
}