{
  "type": "Feature",
  "properties": {
    "iso:country":"US",
    "sg:address":"304 State Rte 711",
    "sg:city":"Jones Mills",
    "sg:classifiers":[
        {
            "category":"Travel",
            "subcategory":"Hotels & Motels",
            "type":"Entertainment"
        }
    ],
    "sg:phone":"+1   ",
    "sg:postcode":"15658",
    "sg:province":"PA",
    "sg:tags":[
        "operation"
    ],
    "wof:name":"Log Cabin Motel",
    "wof:placetype":"venue"
},
  "geometry": {"coordinates":[-79.235744,40.244813],"type":"Point"}
}