{
  "type": "Feature",
  "properties": {
    "addr:full":"373 Chaucer Dr Irwin PA 15642",
    "addr:housenumber":"373",
    "addr:postcode":"15642",
    "addr:street":"Chaucer Dr",
    "iso:country":"US",
    "sg:address":"373 Chaucer Dr",
    "sg:city":"Irwin",
    "sg:classifiers":[
        {
            "category":"Retail",
            "subcategory":"Repair Shop",
            "type":"Services"
        }
    ],
    "sg:phone":"+1 724 863 3324",
    "sg:postcode":"15642",
    "sg:province":"PA",
    "sg:tags":[
        "upholsterer"
    ],
    "wof:name":"Bell Upholstering",
    "wof:placetype":"venue"
},
  "geometry": {"coordinates":[-79.698077,40.317264],"type":"Point"}
}