{
  "type": "Feature",
  "properties": {
    "addr:full":"2603 S 7th St Philadelphia PA 19148",
    "addr:housenumber":"2603",
    "addr:postcode":"19148",
    "addr:street":"S 7Th St",
    "iso:country":"US",
    "sg:address":"2603 S 7th St",
    "sg:city":"Philadelphia",
    "sg:classifiers":[
        {
            "category":"Personal",
            "subcategory":"Beauty Salon",
            "type":"Services"
        }
    ],
    "sg:phone":"+1 215 467 3959",
    "sg:postcode":"19148",
    "sg:province":"PA",
    "wof:name":"Short Kuts By Curtis Adams",
    "wof:placetype":"venue"
},
  "geometry": {"coordinates":[-75.159764,39.915301],"type":"Point"}
}