{
  "type": "Feature",
  "properties": {
    "iso:country":"US",
    "sg:address":"3300 Springfield Pike",
    "sg:city":"Normalville",
    "sg:classifiers":[
        {
            "category":"Organizations",
            "subcategory":"Religious Organization",
            "type":"Services"
        }
    ],
    "sg:phone":"+1 724 455 3656",
    "sg:postcode":"15469",
    "sg:province":"PA",
    "wof:name":"Carl D Ritenour",
    "wof:placetype":"venue"
},
  "geometry": {"coordinates":[-79.45437200000001,40.002535],"type":"Point"}
}