{
  "type": "Feature",
  "properties": {
    "iso:country":"US",
    "sg:address":"3580 Progress Dr",
    "sg:city":"Bensalem",
    "sg:classifiers":[
        {
            "category":"Wholesale",
            "subcategory":"Machinery & Supplies",
            "type":"Manufacturing & Wholesale Goods"
        }
    ],
    "sg:phone":"+1   ",
    "sg:postcode":"19020",
    "sg:province":"PA",
    "sg:tags":[
        "distributor",
        "item",
        "janitorial"
    ],
    "wof:name":"P C A Industrial & Paper Sups",
    "wof:placetype":"venue"
},
  "geometry": {"coordinates":[-74.92662300000001,40.085604],"type":"Point"}
}