{
  "type": "Feature",
  "properties": {
    "iso:country":"US",
    "sg:address":"102 Franklin St",
    "sg:city":"Steelton",
    "sg:classifiers":[
        {
            "category":"Retail",
            "subcategory":"Auto Repair",
            "type":"Services"
        }
    ],
    "sg:phone":"+1 717 939 0367",
    "sg:postcode":"17113",
    "sg:province":"PA",
    "sg:tags":[
        "body",
        "automobile",
        "painting"
    ],
    "wof:name":"Kohl's Steelton Auto Collision",
    "wof:placetype":"venue"
},
  "geometry": {"coordinates":[-76.849058,40.239404],"type":"Point"}
}