{
  "type": "Feature",
  "properties": {
    "iso:country":"US",
    "sg:address":"229 Portersville Rd",
    "sg:city":"Ellwood City",
    "sg:classifiers":[
        {
            "category":"Personal",
            "subcategory":"Beauty Salon",
            "type":"Services"
        }
    ],
    "sg:phone":"+1   ",
    "sg:postcode":"16117",
    "sg:province":"PA",
    "sg:tags":[
        "shop"
    ],
    "wof:name":"In Style Salon",
    "wof:placetype":"venue"
},
  "geometry": {"coordinates":[-80.262435,40.858613],"type":"Point"}
}