{
  "type": "Feature",
  "properties": {
    "iso:country":"US",
    "sg:address":"3240 Richey Rd",
    "sg:city":"Connellsville",
    "sg:classifiers":[
        {
            "category":"Building & Trades",
            "subcategory":"Construction",
            "type":"Services"
        }
    ],
    "sg:phone":"+1   ",
    "sg:postcode":"15425",
    "sg:province":"PA",
    "sg:tags":[
        "hanging",
        "paper",
        "painting",
        "contractor"
    ],
    "wof:name":"Wilson & Sons Decorating",
    "wof:placetype":"venue"
},
  "geometry": {"coordinates":[-79.56083,40.07812],"type":"Point"}
}