{
  "type": "Feature",
  "properties": {
    "addr:full":"774 Hartley Dr Lansdale PA 19446",
    "addr:housenumber":"774",
    "addr:postcode":"19446",
    "addr:street":"Hartley Dr",
    "iso:country":"US",
    "sg:address":"774 Hartley Dr",
    "sg:city":"Lansdale",
    "sg:classifiers":[
        {
            "category":"Professional",
            "subcategory":"Advertising",
            "type":"Services"
        }
    ],
    "sg:phone":"+1   ",
    "sg:postcode":"19446",
    "sg:province":"PA",
    "sg:tags":[
        "agency"
    ],
    "wof:name":"C A Wilson",
    "wof:placetype":"venue"
},
  "geometry": {"coordinates":[-75.314369,40.207641],"type":"Point"}
}