{
  "type": "Feature",
  "properties": {
    "iso:country":"US",
    "sg:address":"11993 Rte 66",
    "sg:city":"Clarion",
    "sg:classifiers":[
        {
            "category":"Home & Garden",
            "subcategory":"Carpets & Floor Coverings",
            "type":"Retail Goods"
        }
    ],
    "sg:phone":"+1   ",
    "sg:postcode":"16214",
    "sg:province":"PA",
    "sg:tags":[
        "a",
        "upholstery",
        "furniture"
    ],
    "wof:name":"McMillens Upholstery & Carpet",
    "wof:placetype":"venue"
},
  "geometry": {"coordinates":[-79.33305300000001,41.163135],"type":"Point"}
}