{
  "type": "Feature",
  "properties": {
    "addr:full":"7021 Kelly St Pittsburgh PA 15208",
    "addr:housenumber":"7021",
    "addr:postcode":"15208",
    "addr:street":"Kelly St",
    "iso:country":"US",
    "sg:address":"7021 Kelly St",
    "sg:city":"Pittsburgh",
    "sg:classifiers":[
        {
            "category":"Government",
            "subcategory":"Office",
            "type":"Public Place"
        }
    ],
    "sg:phone":"+1   ",
    "sg:postcode":"15208",
    "sg:province":"PA",
    "sg:tags":[
        "housing",
        "program"
    ],
    "wof:name":"Ahrco",
    "wof:placetype":"venue"
},
  "geometry": {"coordinates":[-79.89976,40.456225],"type":"Point"}
}