{
  "type": "Feature",
  "properties": {
    "iso:country":"US",
    "sg:address":"1500 Chicago St",
    "sg:city":"Pittsburgh",
    "sg:classifiers":[
        {
            "category":"Organizations",
            "subcategory":"Religious Organization",
            "type":"Services"
        }
    ],
    "sg:phone":"+1 412 322 2995",
    "sg:postcode":"15214",
    "sg:province":"PA",
    "wof:name":"Bethany House Ministry",
    "wof:placetype":"venue"
},
  "geometry": {"coordinates":[-79.999464,40.479227],"type":"Point"}
}