{
  "type": "Feature",
  "properties": {
    "iso:country":"US",
    "sg:address":"20 Church St",
    "sg:city":"New Salem",
    "sg:classifiers":[
        {
            "category":"Organizations",
            "subcategory":"Religious Organization",
            "type":"Services"
        }
    ],
    "sg:phone":"+1 724 245 9244",
    "sg:postcode":"15468",
    "sg:province":"PA",
    "sg:tags":[
        "church"
    ],
    "wof:name":"St Procopius Church",
    "wof:placetype":"venue"
},
  "geometry": {"coordinates":[-79.838624,39.922534],"type":"Point"}
}