{
  "type": "Feature",
  "properties": {
    "iso:country":"US",
    "sg:address":"301 S Arch St",
    "sg:city":"Connellsville",
    "sg:classifiers":[
        {
            "category":"Local Transit",
            "type":"Transportation"
        }
    ],
    "sg:phone":"+1 724 628 6811",
    "sg:postcode":"15425",
    "sg:province":"PA",
    "sg:tags":[
        "ambulance"
    ],
    "wof:name":"Fayette Emergency Medical Svc",
    "wof:placetype":"venue"
},
  "geometry": {"coordinates":[-79.59097,40.01585],"type":"Point"}
}