{
  "type": "Feature",
  "properties": {
    "iso:country":"US",
    "sg:address":"159 Harveys Ln",
    "sg:city":"Milton",
    "sg:classifiers":[
        {
            "category":"Retail",
            "subcategory":"Event Space",
            "type":"Services"
        },
        {
            "category":"Arena",
            "subcategory":"Sports Club",
            "type":"Entertainment"
        },
        {
            "category":"Sports & Exercise",
            "subcategory":"Sports Center",
            "type":"Entertainment"
        },
        {
            "category":"Sports & Exercise",
            "subcategory":"Golf",
            "type":"Entertainment"
        }
    ],
    "sg:phone":"+1 570 742 7455",
    "sg:postcode":"17847",
    "sg:province":"PA",
    "sg:tags":[
        "course",
        "hall",
        "banquet",
        "reception",
        "facility"
    ],
    "wof:name":"Turbot Hills Golf Club",
    "wof:placetype":"venue"
},
  "geometry": {"coordinates":[-76.85179,41.039626],"type":"Point"}
}