{
  "type": "Feature",
  "properties": {
    "iso:country":"US",
    "sg:address":"620 2nd Ave",
    "sg:city":"Royersford",
    "sg:classifiers":[
        {
            "category":"Building & Trades",
            "subcategory":"Construction",
            "type":"Services"
        }
    ],
    "sg:phone":"+1 610 948 8960",
    "sg:postcode":"19468",
    "sg:province":"PA",
    "sg:tags":[
        "work",
        "siding",
        "gutter",
        "w",
        "replacement"
    ],
    "wof:name":"Jiffy Products Co",
    "wof:placetype":"venue"
},
  "geometry": {"coordinates":[-75.535691,40.176929],"type":"Point"}
}