{
  "type": "Feature",
  "properties": {
    "iso:country":"US",
    "sg:address":"2100 Walnut St Apt 4E",
    "sg:city":"Philadelphia",
    "sg:classifiers":[
        {
            "category":"Professional",
            "subcategory":"Art Services",
            "type":"Services"
        }
    ],
    "sg:phone":"+1 215 567 6945",
    "sg:postcode":"19103",
    "sg:province":"PA",
    "sg:tags":[
        "designer",
        "display",
        "producer"
    ],
    "wof:name":"Stevens Design Assoc.",
    "wof:placetype":"venue"
},
  "geometry": {"coordinates":[-75.17572,39.95079],"type":"Point"}
}