{
  "type": "Feature",
  "properties": {
    "iso:country":"US",
    "sg:address":"35 Water St",
    "sg:city":"Smithfield",
    "sg:classifiers":[
        {
            "category":"Manufacturing",
            "subcategory":"Tools & Machinery",
            "type":"Manufacturing & Wholesale Goods"
        }
    ],
    "sg:phone":"+1 724 569 5232",
    "sg:postcode":"15478",
    "sg:province":"PA",
    "sg:tags":[
        "building",
        "equipment",
        "construction"
    ],
    "wof:name":"Heavy Equipment Service",
    "wof:placetype":"venue"
},
  "geometry": {"coordinates":[-79.809181,39.79916],"type":"Point"}
}