{
  "type": "Feature",
  "properties": {
    "iso:country":"US",
    "sg:address":"42 Speakman Dr",
    "sg:city":"Elkton",
    "sg:classifiers":[
        {
            "category":"Professional",
            "subcategory":"Business Services",
            "type":"Services"
        }
    ],
    "sg:phone":"+1 410 620 3431",
    "sg:postcode":"21921",
    "sg:province":"MD",
    "wof:name":"Mlr Enterprises",
    "wof:placetype":"venue"
},
  "geometry": {"coordinates":[-75.927419,39.678198],"type":"Point"}
}