{
  "type": "Feature",
  "properties": {
    "addr:full":"3031 Fagleysville Rd Gilbertsville PA 19525",
    "addr:housenumber":"3031",
    "addr:postcode":"19525",
    "addr:street":"Fagleysville Rd",
    "iso:country":"US",
    "sg:address":"3031 Fagleysville Rd",
    "sg:city":"Gilbertsville",
    "sg:classifiers":[
        {
            "category":"Sports & Exercise",
            "subcategory":"Golf",
            "type":"Entertainment"
        }
    ],
    "sg:phone":"+1 610 754 1635",
    "sg:postcode":"19525",
    "sg:province":"PA",
    "sg:tags":[
        "course"
    ],
    "wof:name":"Bella Vista Golf Crse Grounds",
    "wof:placetype":"venue"
},
  "geometry": {"coordinates":[-75.558853,40.279635],"type":"Point"}
}