{
  "type": "Feature",
  "properties": {
    "iso:country":"US",
    "sg:address":"2006 Sansom St # 2",
    "sg:city":"Philadelphia",
    "sg:classifiers":[
        {
            "category":"Real Estate",
            "subcategory":"Architect",
            "type":"Services"
        }
    ],
    "sg:phone":"+1 215 567 4038",
    "sg:postcode":"19103",
    "sg:province":"PA",
    "wof:name":"Ciccone John Architects",
    "wof:placetype":"venue"
},
  "geometry": {"coordinates":[-75.173897,39.9515],"type":"Point"}
}