{
  "type": "Feature",
  "properties": {
    "addr:full":"3 Michele Lynn Dr Lancaster PA 17602",
    "addr:housenumber":"3",
    "addr:postcode":"17602",
    "addr:street":"Michele Lynn Dr",
    "iso:country":"US",
    "sg:address":"3 Michele Lynn Dr",
    "sg:city":"Lancaster",
    "sg:classifiers":[
        {
            "category":"Building & Trades",
            "subcategory":"Electrical",
            "type":"Services"
        }
    ],
    "sg:phone":"+1   ",
    "sg:postcode":"17602",
    "sg:province":"PA",
    "sg:tags":[
        "electrical",
        "contractor"
    ],
    "wof:name":"Schrier Electric Co",
    "wof:placetype":"venue"
},
  "geometry": {"coordinates":[-76.26287499999999,40.040486],"type":"Point"}
}