{
  "type": "Feature",
  "properties": {
    "iso:country":"US",
    "sg:address":"24 Andrew Ln",
    "sg:city":"Lansdale",
    "sg:classifiers":[
        {
            "category":"Professional",
            "type":"Services"
        }
    ],
    "sg:phone":"+1   ",
    "sg:postcode":"19446",
    "sg:province":"PA",
    "wof:name":"AAA Direct",
    "wof:placetype":"venue"
},
  "geometry": {"coordinates":[-75.23398299999999,40.261491],"type":"Point"}
}