{
  "type": "Feature",
  "properties": {
    "addr:full":"6411 Marsden St Philadelphia PA 19135",
    "addr:housenumber":"6411",
    "addr:postcode":"19135",
    "addr:street":"Marsden St",
    "iso:country":"US",
    "sg:address":"6411 Marsden St",
    "sg:city":"Philadelphia",
    "sg:classifiers":[
        {
            "category":"Professional",
            "subcategory":"Computer Services",
            "type":"Services"
        }
    ],
    "sg:phone":"+1 215 333 0691",
    "sg:postcode":"19135",
    "sg:province":"PA",
    "sg:tags":[
        "system",
        "cad"
    ],
    "wof:name":"Jeff Hutt Carpentry",
    "wof:placetype":"venue"
},
  "geometry": {"coordinates":[-75.050584,40.022835],"type":"Point"}
}