{
  "type": "Feature",
  "properties": {
    "addr:full":"4421 Prestwick Dr Reading PA 19606",
    "addr:housenumber":"4421",
    "addr:postcode":"19606",
    "addr:street":"Prestwick Dr",
    "iso:country":"US",
    "sg:address":"4421 Prestwick Dr",
    "sg:city":"Reading",
    "sg:classifiers":[
        {
            "category":"Organizations",
            "subcategory":"Religious Organization",
            "type":"Services"
        }
    ],
    "sg:phone":"+1   ",
    "sg:postcode":"19606",
    "sg:province":"PA",
    "wof:name":"Abundant Life Assembly of God",
    "wof:placetype":"venue"
},
  "geometry": {"coordinates":[-75.867276,40.305683],"type":"Point"}
}