{
  "type": "Feature",
  "properties": {
    "iso:country":"US",
    "sg:address":"3547 Washington Ave",
    "sg:city":"Finleyville",
    "sg:classifiers":[
        {
            "category":"Education",
            "subcategory":"Special Training",
            "type":"Public Place"
        }
    ],
    "sg:phone":"+1 724 348 6699",
    "sg:postcode":"15332",
    "sg:province":"PA",
    "sg:tags":[
        "educational"
    ],
    "wof:name":"Healthy Directions",
    "wof:placetype":"venue"
},
  "geometry": {"coordinates":[-80.003219,40.252573],"type":"Point"}
}