{
  "type": "Feature",
  "properties": {
    "iso:country":"US",
    "sg:address":"401 Carlisle Ave",
    "sg:city":"York",
    "sg:classifiers":[
        {
            "category":"Wholesale",
            "subcategory":"Non-durable Goods",
            "type":"Manufacturing & Wholesale Goods"
        }
    ],
    "sg:phone":"+1   ",
    "sg:postcode":"17404",
    "sg:province":"PA",
    "wof:name":"Mj Whitfield",
    "wof:placetype":"venue"
},
  "geometry": {"coordinates":[-76.753058,39.959205],"type":"Point"}
}