{
  "type": "Feature",
  "properties": {
    "iso:country":"US",
    "sg:address":"1922 Cottman Ave",
    "sg:city":"Philadelphia",
    "sg:classifiers":[
        {
            "category":"Communications",
            "type":"Services"
        }
    ],
    "sg:phone":"+1 215 745 2404",
    "sg:postcode":"19111",
    "sg:province":"PA",
    "wof:name":"African American Law Enforcement Communi",
    "wof:placetype":"venue"
},
  "geometry": {"coordinates":[-75.06733699999999,40.05196],"type":"Point"}
}