{
  "type": "Feature",
  "properties": {
    "iso:country":"US",
    "sg:address":"8164 Perry Hwy",
    "sg:city":"Pittsburgh",
    "sg:classifiers":[
        {
            "category":"Home & Garden",
            "subcategory":"Household Appliances",
            "type":"Retail Goods"
        },
        {
            "category":"Home & Garden",
            "subcategory":"Furniture",
            "type":"Retail Goods"
        }
    ],
    "sg:phone":"+1 412 367 2080",
    "sg:postcode":"15237",
    "sg:province":"PA",
    "sg:tags":[
        "equipment",
        "kitchen",
        "unit",
        "cabinet"
    ],
    "wof:name":"Kitchen Distributors N Hills",
    "wof:placetype":"venue"
},
  "geometry": {"coordinates":[-80.03885200000001,40.555621],"type":"Point"}
}