{
  "type": "Feature",
  "properties": {
    "iso:country":"US",
    "sg:address":"110 Old York Rd # 217",
    "sg:city":"New Cumberland",
    "sg:classifiers":[
        {
            "category":"Restaurant",
            "type":"Food & Drink"
        }
    ],
    "sg:phone":"+1 717 712 8771",
    "sg:postcode":"17070",
    "sg:province":"PA",
    "sg:tags":[
        "chinese"
    ],
    "wof:name":"Aroma Chinese Cuisine",
    "wof:placetype":"venue"
},
  "geometry": {"coordinates":[-76.860313,40.218964],"type":"Point"}
}