{
  "type": "Feature",
  "properties": {
    "addr:full":"105 S Market St Carmichaels PA 15320",
    "addr:housenumber":"105",
    "addr:postcode":"15320",
    "addr:street":"S Market St",
    "iso:country":"US",
    "sg:address":"105 S Market St",
    "sg:city":"Carmichaels",
    "sg:classifiers":[
        {
            "category":"Shopping",
            "type":"Retail Goods"
        }
    ],
    "sg:phone":"+1 724 966 2270",
    "sg:postcode":"15320",
    "sg:province":"PA",
    "sg:tags":[
        "merchandise"
    ],
    "wof:name":"Henry & Stewart Audiology",
    "wof:placetype":"venue"
},
  "geometry": {"coordinates":[-79.97416,39.89567],"type":"Point"}
}