{
  "type": "Feature",
  "properties": {
    "addr:full":"200 N 3rd St Harrisburg PA 17101",
    "addr:housenumber":"200",
    "addr:postcode":"17101",
    "addr:street":"N 3Rd St",
    "iso:country":"US",
    "sg:address":"200 N 3rd St",
    "sg:city":"Harrisburg",
    "sg:classifiers":[
        {
            "category":"Government",
            "subcategory":"Court House",
            "type":"Public Place"
        }
    ],
    "sg:phone":"+1   ",
    "sg:postcode":"17101",
    "sg:province":"PA",
    "wof:name":"Supreme Court of Pennsylvania",
    "wof:placetype":"venue"
},
  "geometry": {"coordinates":[-76.883313,40.262456],"type":"Point"}
}