{
  "type": "Feature",
  "properties": {
    "addr:full":"1821 Memorial Hwy Oley PA 19547",
    "addr:housenumber":"1821",
    "addr:postcode":"19547",
    "addr:street":"Memorial Hwy",
    "iso:country":"US",
    "sg:address":"1821 Memorial Hwy",
    "sg:city":"Oley",
    "sg:classifiers":[
        {
            "category":"Real Estate",
            "subcategory":"Real Estate Operator",
            "type":"Services"
        }
    ],
    "sg:phone":"+1   ",
    "sg:postcode":"19547",
    "sg:province":"PA",
    "sg:tags":[
        "property",
        "lessor"
    ],
    "wof:name":"Rothenberger Century Farm",
    "wof:placetype":"venue"
},
  "geometry": {"coordinates":[-75.756119,40.328359],"type":"Point"}
}