{
  "type": "Feature",
  "properties": {
    "iso:country":"US",
    "sg:address":"3019 W Germantown Pike",
    "sg:city":"Norristown",
    "sg:classifiers":[
        {
            "category":"Personal",
            "subcategory":"Beauty Salon",
            "type":"Services"
        }
    ],
    "sg:phone":"+1 610 539 3313",
    "sg:postcode":"19403",
    "sg:province":"PA",
    "sg:tags":[
        "nail"
    ],
    "wof:name":"Shapes Salon",
    "wof:placetype":"venue"
},
  "geometry": {"coordinates":[-75.38130200000001,40.162399],"type":"Point"}
}