{
  "type": "Feature",
  "properties": {
    "iso:country":"US",
    "sg:address":"75 W Chapel Ridge Rd",
    "sg:city":"Pittsburgh",
    "sg:classifiers":[
        {
            "category":"Professional",
            "subcategory":"Computer Services",
            "type":"Services"
        }
    ],
    "sg:phone":"+1   ",
    "sg:postcode":"15238",
    "sg:province":"PA",
    "sg:tags":[
        "development",
        "software"
    ],
    "wof:name":"Xml For All Inc",
    "wof:placetype":"venue"
},
  "geometry": {"coordinates":[-79.88214499999999,40.543378],"type":"Point"}
}