{
  "type": "Feature",
  "properties": {
    "iso:country":"US",
    "sg:address":"2321 N Penn Rd",
    "sg:city":"Hatfield",
    "sg:classifiers":[
        {
            "category":"Manufacturing",
            "subcategory":"Metals",
            "type":"Manufacturing & Wholesale Goods"
        }
    ],
    "sg:phone":"+1   ",
    "sg:postcode":"19440",
    "sg:province":"PA",
    "sg:tags":[
        "mfg",
        "forging"
    ],
    "wof:name":"Csg Rework Center",
    "wof:placetype":"venue"
},
  "geometry": {"coordinates":[-75.285961,40.291074],"type":"Point"}
}