{
  "type": "Feature",
  "properties": {
    "iso:country":"US",
    "sg:address":"28 Market Sq",
    "sg:city":"Manheim",
    "sg:classifiers":[
        {
            "category":"Insurance",
            "subcategory":"Insurance Agent",
            "type":"Services"
        }
    ],
    "sg:phone":"+1 717 665 2283",
    "sg:postcode":"17545",
    "sg:province":"PA",
    "sg:website":"www.ruhl-insurance.com",
    "wof:name":"Jacob H Ruhl Insurance",
    "wof:placetype":"venue"
},
  "geometry": {"coordinates":[-76.396558,40.163159],"type":"Point"}
}