{
  "type": "Feature",
  "properties": {
    "iso:country":"US",
    "sg:address":"807 Main St",
    "sg:city":"Pittsburgh",
    "sg:classifiers":[
        {
            "category":"Manufacturing",
            "subcategory":"Printing",
            "type":"Manufacturing & Wholesale Goods"
        }
    ],
    "sg:phone":"+1 412 782 0112",
    "sg:postcode":"15215",
    "sg:province":"PA",
    "sg:tags":[
        "commercial",
        "lithographic"
    ],
    "wof:name":"Guyasuta Printing Co",
    "wof:placetype":"venue"
},
  "geometry": {"coordinates":[-79.933724,40.494519],"type":"Point"}
}