{
  "type": "Feature",
  "properties": {
    "iso:country":"US",
    "sg:address":"315 E 2nd St",
    "sg:city":"Boyertown",
    "sg:classifiers":[
        {
            "category":"Professional",
            "subcategory":"Computer Services",
            "type":"Services"
        }
    ],
    "sg:phone":"+1   ",
    "sg:postcode":"19512",
    "sg:province":"PA",
    "sg:tags":[
        "prepackaged",
        "design",
        "system",
        "software"
    ],
    "wof:name":"Gateway Ticketing Systems Inc",
    "wof:placetype":"venue"
},
  "geometry": {"coordinates":[-75.63629899999999,40.328697],"type":"Point"}
}