{
  "type": "Feature",
  "properties": {
    "iso:country":"US",
    "sg:address":"114 Keystone Dr",
    "sg:city":"Montgomeryville",
    "sg:classifiers":[
        {
            "category":"Manufacturing",
            "subcategory":"Printing",
            "type":"Manufacturing & Wholesale Goods"
        }
    ],
    "sg:phone":"+1 215 641 4844",
    "sg:postcode":"18936",
    "sg:province":"PA",
    "sg:tags":[
        "printer",
        "commercial"
    ],
    "sg:website":"www.r-sgraphics.com",
    "wof:name":"R & S Graphics Inc",
    "wof:placetype":"venue"
},
  "geometry": {"coordinates":[-75.236152,40.214171],"type":"Point"}
}