{
  "type": "Feature",
  "properties": {
    "iso:country":"US",
    "sg:address":"746 6th Ave",
    "sg:city":"Patterson Hts",
    "sg:classifiers":[
        {
            "category":"Professional",
            "subcategory":"Accounting & Tax Preparation",
            "type":"Services"
        }
    ],
    "sg:phone":"+1 724 847 0205",
    "sg:postcode":"15010",
    "sg:province":"PA",
    "sg:tags":[
        "accountant"
    ],
    "wof:name":"Diane J Plummer CPA",
    "wof:placetype":"venue"
},
  "geometry": {"coordinates":[-80.32756999999999,40.738088],"type":"Point"}
}