{
  "type": "Feature",
  "properties": {
    "addr:full":"6978 Big Beaver Blvd Beaver Falls PA 15010",
    "addr:housenumber":"6978",
    "addr:postcode":"15010",
    "addr:street":"Big Beaver Blvd",
    "iso:country":"US",
    "sg:address":"6978 Big Beaver Blvd",
    "sg:city":"Beaver Falls",
    "sg:classifiers":[
        {
            "category":"Building & Trades",
            "subcategory":"Plumbing",
            "type":"Services"
        }
    ],
    "sg:phone":"+1 724 846 0070",
    "sg:postcode":"15010",
    "sg:province":"PA",
    "sg:tags":[
        "septic"
    ],
    "wof:name":"Dalton's Sanitary Svc",
    "wof:placetype":"venue"
},
  "geometry": {"coordinates":[-80.330504,40.804934],"type":"Point"}
}