{
  "type": "Feature",
  "properties": {
    "iso:country":"US",
    "sg:address":"602 Blue Gill Rd",
    "sg:city":"Oxford",
    "sg:classifiers":[
        {
            "category":"Farming",
            "subcategory":"Farm",
            "type":"Manufacturing & Wholesale Goods"
        }
    ],
    "sg:phone":"+1   ",
    "sg:postcode":"19363",
    "sg:province":"PA",
    "sg:tags":[
        "crop",
        "general"
    ],
    "wof:name":"Hugh Lesley",
    "wof:placetype":"venue"
},
  "geometry": {"coordinates":[-76.070328,39.809584],"type":"Point"}
}