{
  "type": "Feature",
  "properties": {
    "iso:country":"US",
    "sg:address":"228 Groupe Rd",
    "sg:city":"Jersey Shore",
    "sg:classifiers":[
        {
            "category":"Building & Trades",
            "subcategory":"Construction",
            "type":"Services"
        }
    ],
    "sg:phone":"+1   ",
    "sg:postcode":"17740",
    "sg:province":"PA",
    "sg:tags":[
        "house"
    ],
    "wof:name":"Harvey I Palmatary",
    "wof:placetype":"venue"
},
  "geometry": {"coordinates":[-77.23536799999999,41.122647],"type":"Point"}
}