{
  "type": "Feature",
  "properties": {
    "iso:country":"US",
    "sg:address":"420 W Lincoln Ave",
    "sg:city":"Myerstown",
    "sg:classifiers":[
        {
            "category":"Home & Garden",
            "subcategory":"Garden Supply",
            "type":"Retail Goods"
        }
    ],
    "sg:phone":"+1   ",
    "sg:postcode":"17067",
    "sg:province":"PA",
    "sg:tags":[
        "lawn"
    ],
    "wof:name":"Serviceplus Power Equipment",
    "wof:placetype":"venue"
},
  "geometry": {"coordinates":[-76.319299,40.374599],"type":"Point"}
}