{
  "type": "Feature",
  "properties": {
    "iso:country":"US",
    "sg:address":"2775 Philmont Ave",
    "sg:city":"Huntingdon Vly",
    "sg:classifiers":[
        {
            "category":"Health Services",
            "subcategory":"Doctor",
            "type":"Services"
        }
    ],
    "sg:phone":"+1 215 947 6775",
    "sg:postcode":"19006",
    "sg:province":"PA",
    "sg:tags":[
        "physician",
        "surgeon"
    ],
    "wof:name":"Robert W Mannherz MD",
    "wof:placetype":"venue"
},
  "geometry": {"coordinates":[-75.047764,40.1225],"type":"Point"}
}