{
  "type": "Feature",
  "properties": {
    "addr:full":"3 N Maple Ave Greensburg PA 15601",
    "addr:housenumber":"3",
    "addr:postcode":"15601",
    "addr:street":"N Maple Ave",
    "iso:country":"US",
    "sg:address":"3 N Maple Ave",
    "sg:city":"Greensburg",
    "sg:classifiers":[
        {
            "category":"Professional",
            "subcategory":"Lawyer & Legal Services",
            "type":"Services"
        }
    ],
    "sg:phone":"+1 724 837 7535",
    "sg:postcode":"15601",
    "sg:province":"PA",
    "sg:tags":[
        "attorney"
    ],
    "wof:name":"Francis R Murrman",
    "wof:placetype":"venue"
},
  "geometry": {"coordinates":[-79.54317399999999,40.302674],"type":"Point"}
}