{
  "type": "Feature",
  "properties": {
    "iso:country":"US",
    "sg:address":"480 Pierce St",
    "sg:city":"Kingston",
    "sg:classifiers":[
        {
            "category":"Real Estate",
            "subcategory":"Real Estate Services",
            "type":"Services"
        }
    ],
    "sg:phone":"+1 570 288 2015",
    "sg:postcode":"18704",
    "sg:province":"PA",
    "sg:tags":[
        "company",
        "abstract",
        "title"
    ],
    "wof:name":"Continental Land Abstract Serv",
    "wof:placetype":"venue"
},
  "geometry": {"coordinates":[-75.884017,41.258285],"type":"Point"}
}