{
  "type": "Feature",
  "properties": {
    "iso:country":"US",
    "sg:address":"1250 Point Breeze Ave",
    "sg:city":"Philadelphia",
    "sg:classifiers":[
        {
            "category":"Transit Center",
            "subcategory":"Freight",
            "type":"Transportation"
        }
    ],
    "sg:phone":"+1 267 262 8509",
    "sg:postcode":"19146",
    "sg:province":"PA",
    "sg:tags":[
        "trucking-light",
        "hauling"
    ],
    "wof:name":"Top Of The Line 2010 Inc.",
    "wof:placetype":"venue"
},
  "geometry": {"coordinates":[-75.178107,39.935969],"type":"Point"}
}