{
  "type": "Feature",
  "properties": {
    "iso:country":"US",
    "sg:address":"644 Kimball St",
    "sg:city":"Philadelphia",
    "sg:classifiers":[
        {
            "category":"Personal",
            "type":"Services"
        }
    ],
    "sg:phone":"+1 215 378 3684",
    "sg:postcode":"19147",
    "sg:province":"PA",
    "sg:tags":[
        "chef"
    ],
    "sg:website":"www.chefdavids.com",
    "wof:name":"David Salvatore Private Catering",
    "wof:placetype":"venue"
},
  "geometry": {"coordinates":[-75.155113,39.936176],"type":"Point"}
}