{
  "type": "Feature",
  "properties": {
    "iso:country":"US",
    "sg:address":"24 N State St",
    "sg:city":"Newtown",
    "sg:classifiers":[
        {
            "category":"Health Services",
            "subcategory":"Health Practitioner",
            "type":"Services"
        }
    ],
    "sg:phone":"+1 215 579 7577",
    "sg:postcode":"18940",
    "sg:province":"PA",
    "sg:tags":[
        "therapist",
        "physical"
    ],
    "wof:name":"Atlas Physical Therapy",
    "wof:placetype":"venue"
},
  "geometry": {"coordinates":[-74.936665,40.230208],"type":"Point"}
}