{
  "type": "Feature",
  "properties": {
    "iso:country":"US",
    "sg:address":"207 Tanglewood Way",
    "sg:city":"Harleysville",
    "sg:classifiers":[
        {
            "category":"Professional",
            "type":"Services"
        }
    ],
    "sg:phone":"+1   ",
    "sg:postcode":"19438",
    "sg:province":"PA",
    "wof:name":"Wright Ea Inc",
    "wof:placetype":"venue"
},
  "geometry": {"coordinates":[-75.35696900000001,40.244903],"type":"Point"}
}