{
  "type": "Feature",
  "properties": {
    "iso:country":"US",
    "sg:address":"135 State St",
    "sg:city":"Harrisburg",
    "sg:classifiers":[
        {
            "category":"Manufacturing",
            "subcategory":"Printing",
            "type":"Manufacturing & Wholesale Goods"
        }
    ],
    "sg:phone":"+1 717 232 6684",
    "sg:postcode":"17101",
    "sg:province":"PA",
    "sg:tags":[
        "commercial"
    ],
    "wof:name":"State Street Copy & Press",
    "wof:placetype":"venue"
},
  "geometry": {"coordinates":[-76.8871,40.263],"type":"Point"}
}