{
  "type": "Feature",
  "properties": {
    "iso:country":"US",
    "sg:address":"215 W Main St",
    "sg:city":"Norristown",
    "sg:classifiers":[
        {
            "category":"Utilities",
            "subcategory":"Mobile Phone",
            "type":"Services"
        },
        {
            "category":"Utilities",
            "subcategory":"Telephone",
            "type":"Services"
        }
    ],
    "sg:phone":"+1 610 239 1600",
    "sg:postcode":"19401",
    "sg:province":"PA",
    "sg:tags":[
        "communication",
        "cellular"
    ],
    "wof:name":"Ing Wireless",
    "wof:placetype":"venue"
},
  "geometry": {"coordinates":[-75.34750699999999,40.115706],"type":"Point"}
}