{
  "type": "Feature",
  "properties": {
    "iso:country":"US",
    "sg:address":"1000 Brookwood Dr",
    "sg:city":"Mechanicsburg",
    "sg:classifiers":[
        {
            "category":"Professional",
            "subcategory":"Engineering",
            "type":"Services"
        }
    ],
    "sg:phone":"+1   ",
    "sg:postcode":"17055",
    "sg:province":"PA",
    "wof:name":"Bellanca Family Gaa Partnr",
    "wof:placetype":"venue"
},
  "geometry": {"coordinates":[-76.94388600000001,40.177305],"type":"Point"}
}