{
  "type": "Feature",
  "properties": {
    "iso:country":"US",
    "sg:address":"3601 Paxton St Ste 6",
    "sg:city":"Harrisburg",
    "sg:classifiers":[
        {
            "category":"Education",
            "subcategory":"Special Training",
            "type":"Public Place"
        }
    ],
    "sg:phone":"+1 717 561 2060",
    "sg:postcode":"17111",
    "sg:province":"PA",
    "sg:tags":[
        "educational"
    ],
    "wof:name":"Phase 4 Learning Center",
    "wof:placetype":"venue"
},
  "geometry": {"coordinates":[-76.82701,40.253583],"type":"Point"}
}