{
  "type": "Feature",
  "properties": {
    "addr:full":"1800 John F Kennedy Blvd Philadelphia PA 19103",
    "addr:housenumber":"1800",
    "addr:postcode":"19103",
    "addr:street":"John F Kennedy Blvd",
    "iso:country":"US",
    "sg:address":"1800 John F Kennedy Blvd",
    "sg:city":"Philadelphia",
    "sg:classifiers":[
        {
            "category":"Professional",
            "subcategory":"Lawyer & Legal Services",
            "type":"Services"
        }
    ],
    "sg:phone":"+1 215 564 9700",
    "sg:postcode":"19103",
    "sg:province":"PA",
    "sg:tags":[
        "attorney"
    ],
    "wof:name":"Catherine M Baggiano",
    "wof:placetype":"venue"
},
  "geometry": {"coordinates":[-75.17136499999999,39.95438],"type":"Point"}
}