{
  "type": "Feature",
  "properties": {
    "iso:country":"US",
    "sg:address":"42 Blakeslee Boulevard Dr E",
    "sg:city":"Lehighton",
    "sg:classifiers":[
        {
            "category":"Retail",
            "subcategory":"Self-service Laundry",
            "type":"Services"
        },
        {
            "category":"Retail",
            "subcategory":"Laundry & Dry Cleaning",
            "type":"Services"
        }
    ],
    "sg:phone":"+1 610 377 6711",
    "sg:postcode":"18235",
    "sg:province":"PA",
    "sg:tags":[
        "drycleaning",
        "plant",
        "stone"
    ],
    "wof:name":"Lehighton Coin Laundry & Dry",
    "wof:placetype":"venue"
},
  "geometry": {"coordinates":[-75.706366,40.825204],"type":"Point"}
}