{
  "type": "Feature",
  "properties": {
    "iso:country":"US",
    "sg:address":"332 Jefferson Ave",
    "sg:city":"Scranton",
    "sg:classifiers":[
        {
            "category":"Social Services",
            "type":"Services"
        },
        {
            "category":"Personal",
            "type":"Services"
        }
    ],
    "sg:phone":"+1 570 342 5420",
    "sg:postcode":"18510",
    "sg:province":"PA",
    "sg:tags":[
        "counseling",
        "family",
        "counselors-licensed",
        "individual",
        "marriage",
        "child",
        "professional",
        "counselor"
    ],
    "wof:name":"Frein Robert MS",
    "wof:placetype":"venue"
},
  "geometry": {"coordinates":[-75.659482,41.407969],"type":"Point"}
}