{
  "type": "Feature",
  "properties": {
    "iso:country":"US",
    "sg:address":"1301 E Carey St",
    "sg:city":"Philadelphia",
    "sg:classifiers":[
        {
            "category":"Building & Trades",
            "subcategory":"Construction",
            "type":"Services"
        }
    ],
    "sg:phone":"+1 215 744 3573",
    "sg:postcode":"19124",
    "sg:province":"PA",
    "sg:tags":[
        "contractor"
    ],
    "wof:name":"Alexander Painting & General Contractor",
    "wof:placetype":"venue"
},
  "geometry": {"coordinates":[-75.103481,40.004595],"type":"Point"}
}