{
  "type": "Feature",
  "properties": {
    "addr:full":"1264 Hamilton Rd Castle Shannon PA 15234",
    "addr:housenumber":"1264",
    "addr:postcode":"15234",
    "addr:street":"Hamilton Rd",
    "iso:country":"US",
    "sg:address":"1264 Hamilton Rd",
    "sg:city":"Castle Shannon",
    "sg:classifiers":[
        {
            "category":"Insurance",
            "subcategory":"Insurance Agent",
            "type":"Services"
        }
    ],
    "sg:phone":"+1 412 885 2810",
    "sg:postcode":"15234",
    "sg:province":"PA",
    "wof:name":"Lacek Agency",
    "wof:placetype":"venue"
},
  "geometry": {"coordinates":[-80.01452500000001,40.361815],"type":"Point"}
}