{
  "type": "Feature",
  "properties": {
    "iso:country":"US",
    "sg:address":"3300 State Rd",
    "sg:city":"Bensalem",
    "sg:classifiers":[
        {
            "category":"Shopping",
            "subcategory":"Jewelry",
            "type":"Retail Goods"
        }
    ],
    "sg:phone":"+1 215 633 0708",
    "sg:postcode":"19020",
    "sg:province":"PA",
    "sg:website":"www.swarnajewelers.com",
    "wof:name":"Swarna Jewelers",
    "wof:placetype":"venue"
},
  "geometry": {"coordinates":[-74.92433699999999,40.077914],"type":"Point"}
}