{
  "type": "Feature",
  "properties": {
    "iso:country":"US",
    "sg:address":"759 Stouffer Ave",
    "sg:city":"Chambersburg",
    "sg:classifiers":[
        {
            "category":"Health Services",
            "subcategory":"Doctor",
            "type":"Services"
        }
    ],
    "sg:phone":"+1 717 263 0442",
    "sg:postcode":"17201",
    "sg:province":"PA",
    "sg:tags":[
        "dentist"
    ],
    "wof:name":"David E Drake LTD",
    "wof:placetype":"venue"
},
  "geometry": {"coordinates":[-77.645495,39.921267],"type":"Point"}
}