{
  "type": "Feature",
  "properties": {
    "iso:country":"US",
    "sg:address":"1025 N Duke St",
    "sg:city":"Lancaster",
    "sg:classifiers":[
        {
            "category":"Organizations",
            "subcategory":"Labor Organization",
            "type":"Services"
        }
    ],
    "sg:phone":"+1 717 397 8267",
    "sg:postcode":"17602",
    "sg:province":"PA",
    "wof:name":"Teamsters Chauffeurs Local",
    "wof:placetype":"venue"
},
  "geometry": {"coordinates":[-76.306515,40.053482],"type":"Point"}
}