{
  "type": "Feature",
  "properties": {
    "addr:full":"2941 Felton Rd Norristown PA 19401",
    "addr:housenumber":"2941",
    "addr:postcode":"19401",
    "addr:street":"Felton Rd",
    "iso:country":"US",
    "sg:address":"2941 Felton Rd",
    "sg:city":"Norristown",
    "sg:classifiers":[
        {
            "category":"Building & Trades",
            "subcategory":"Landscaping Services",
            "type":"Services"
        }
    ],
    "sg:phone":"+1 610 239 8191",
    "sg:postcode":"19401",
    "sg:province":"PA",
    "sg:tags":[
        "lawn",
        "landscape",
        "maintenance",
        "contractor"
    ],
    "sg:website":"http://www.trugreen.com",
    "wof:name":"Trugreen Landcare",
    "wof:placetype":"venue"
},
  "geometry": {"coordinates":[-75.328834,40.149668],"type":"Point"}
}