{
  "type": "Feature",
  "properties": {
    "addr:full":"2243 W Bakersville Edie Rd Somerset PA 15501",
    "addr:housenumber":"2243",
    "addr:postcode":"15501",
    "addr:street":"W Bakersville Edie Rd",
    "iso:country":"US",
    "sg:address":"2243 W Bakersville Edie Rd",
    "sg:city":"Somerset",
    "sg:classifiers":[
        {
            "category":"Retail",
            "subcategory":"Repair Shop",
            "type":"Services"
        }
    ],
    "sg:phone":"+1 814 443 3157",
    "sg:postcode":"15501",
    "sg:province":"PA",
    "sg:tags":[
        "antique",
        "restoring"
    ],
    "wof:name":"Groff's Antiques & Refinishing",
    "wof:placetype":"venue"
},
  "geometry": {"coordinates":[-79.215406,40.039838],"type":"Point"}
}