{
  "type": "Feature",
  "properties": {
    "iso:country":"US",
    "sg:address":"2473 Wildwood Rd",
    "sg:city":"Allison Park",
    "sg:classifiers":[
        {
            "category":"Building & Trades",
            "subcategory":"Construction",
            "type":"Services"
        }
    ],
    "sg:phone":"+1 412 487 1595",
    "sg:postcode":"15091",
    "sg:province":"PA",
    "sg:tags":[
        "general",
        "contractor"
    ],
    "wof:name":"Stevey Construction",
    "wof:placetype":"venue"
},
  "geometry": {"coordinates":[-79.970202,40.5939],"type":"Point"}
}