{
  "type": "Feature",
  "properties": {
    "addr:full":"1718 W Main St Stroudsburg PA 18360",
    "addr:housenumber":"1718",
    "addr:postcode":"18360",
    "addr:street":"W Main St",
    "iso:country":"US",
    "sg:address":"1718 W Main St",
    "sg:city":"Stroudsburg",
    "sg:classifiers":[
        {
            "category":"Health Services",
            "subcategory":"Chiropractor",
            "type":"Services"
        }
    ],
    "sg:phone":"+1 570 424 5433",
    "sg:postcode":"18360",
    "sg:province":"PA",
    "sg:tags":[
        "chiropractic"
    ],
    "wof:name":"Herman Family Chiropractic Center",
    "wof:placetype":"venue"
},
  "geometry": {"coordinates":[-75.216281,40.982485],"type":"Point"}
}