{
  "type": "Feature",
  "properties": {
    "iso:country":"US",
    "sg:address":"335 Hancock St",
    "sg:city":"Clymer",
    "sg:classifiers":[
        {
            "category":"Organizations",
            "subcategory":"Religious Organization",
            "type":"Services"
        }
    ],
    "sg:phone":"+1 724 254 1001",
    "sg:postcode":"15728",
    "sg:province":"PA",
    "sg:tags":[
        "clergy"
    ],
    "wof:name":"George Mitchell",
    "wof:placetype":"venue"
},
  "geometry": {"coordinates":[-79.00769,40.668566],"type":"Point"}
}