{
  "type": "Feature",
  "properties": {
    "iso:country":"US",
    "sg:address":"607 Pulaski St",
    "sg:city":"Bethlehem",
    "sg:classifiers":[
        {
            "category":"Building & Trades",
            "subcategory":"Construction",
            "type":"Services"
        }
    ],
    "sg:phone":"+1   ",
    "sg:postcode":"18018",
    "sg:province":"PA",
    "sg:tags":[
        "house"
    ],
    "wof:name":"R&R Home Improvements",
    "wof:placetype":"venue"
},
  "geometry": {"coordinates":[-75.36976900000001,40.622729],"type":"Point"}
}