{
  "type": "Feature",
  "properties": {
    "addr:full":"944 S Edgewood Ave Somerset PA 15501",
    "addr:housenumber":"944",
    "addr:postcode":"15501",
    "addr:street":"S Edgewood Ave",
    "iso:country":"US",
    "sg:address":"944 S Edgewood Ave",
    "sg:city":"Somerset",
    "sg:classifiers":[
        {
            "category":"Personal",
            "subcategory":"Beauty Salon",
            "type":"Services"
        }
    ],
    "sg:phone":"+1 814 444 8200",
    "sg:postcode":"15501",
    "sg:province":"PA",
    "sg:tags":[
        "shop"
    ],
    "wof:name":"Scissors N Sun",
    "wof:placetype":"venue"
},
  "geometry": {"coordinates":[-79.08087999999999,39.9993],"type":"Point"}
}