{
  "type": "Feature",
  "properties": {
    "iso:country":"US",
    "sg:address":"5860 Dashwood Dr",
    "sg:city":"Bethel Park",
    "sg:classifiers":[
        {
            "category":"Shopping",
            "type":"Retail Goods"
        }
    ],
    "sg:phone":"+1 412 833 6730",
    "sg:postcode":"15102",
    "sg:province":"PA",
    "sg:tags":[
        "cosmetic",
        "perfume"
    ],
    "wof:name":"Mary Kay Cosmetics",
    "wof:placetype":"venue"
},
  "geometry": {"coordinates":[-80.052115,40.310857],"type":"Point"}
}