{
  "type": "Feature",
  "properties": {
    "iso:country":"US",
    "sg:address":"1008 Chestnut Ave",
    "sg:city":"Altoona",
    "sg:classifiers":[
        {
            "category":"Building & Trades",
            "subcategory":"Plumbing",
            "type":"Services"
        },
        {
            "category":"Building & Trades",
            "subcategory":"Construction",
            "type":"Services"
        },
        {
            "category":"Building & Trades",
            "subcategory":"Electrical",
            "type":"Services"
        },
        {
            "category":"Building & Trades",
            "subcategory":"Cleaning & Sanitation",
            "type":"Services"
        }
    ],
    "sg:phone":"+1 814 942 7153",
    "sg:postcode":"16601",
    "sg:province":"PA",
    "sg:tags":[
        "plumber",
        "furnaces-repairing",
        "system",
        "specialty",
        "furnaces-heating",
        "heating",
        "ventilating",
        "contractor",
        "air conditioning"
    ],
    "sg:website":"http://www.mcaleersplumbing.com",
    "wof:name":"McAleer's Plumbing, Heating, Air Conditioning Inc.",
    "wof:placetype":"venue"
},
  "geometry": {"coordinates":[-78.399427,40.51806],"type":"Point"}
}