{
  "type": "Feature",
  "properties": {
    "addr:full":"66 Vincent Cir Warminster PA 18974",
    "addr:housenumber":"66",
    "addr:postcode":"18974",
    "addr:street":"Vincent Cir",
    "iso:country":"US",
    "sg:address":"66 Vincent Cir",
    "sg:city":"Warminster",
    "sg:classifiers":[
        {
            "category":"Manufacturing",
            "subcategory":"Paper Products",
            "type":"Manufacturing & Wholesale Goods"
        }
    ],
    "sg:phone":"+1 215 675 9307",
    "sg:postcode":"18974",
    "sg:province":"PA",
    "sg:tags":[
        "process",
        "packaging",
        "plastic"
    ],
    "wof:name":"Eastern Web Handling Inc",
    "wof:placetype":"venue"
},
  "geometry": {"coordinates":[-75.05847,40.220401],"type":"Point"}
}