{
  "type": "Feature",
  "properties": {
    "addr:full":"1 Lakeside Dr Levittown PA 19054",
    "addr:housenumber":"1",
    "addr:postcode":"19054",
    "addr:street":"Lakeside Dr",
    "iso:country":"US",
    "sg:address":"1 Lakeside Dr",
    "sg:city":"Levittown",
    "sg:classifiers":[
        {
            "category":"Health Services",
            "subcategory":"Optometrist",
            "type":"Services"
        }
    ],
    "sg:phone":"+1 215 946 1926",
    "sg:postcode":"19054",
    "sg:province":"PA",
    "wof:name":"Austin James R OD",
    "wof:placetype":"venue"
},
  "geometry": {"coordinates":[-74.82089999999999,40.145901],"type":"Point"}
}