{
  "type": "Feature",
  "properties": {
    "iso:country":"US",
    "sg:address":"72 N Greenview Rd",
    "sg:city":"Schuylkill Haven",
    "sg:classifiers":[
        {
            "category":"Building & Trades",
            "subcategory":"Landscaping Services",
            "type":"Services"
        }
    ],
    "sg:phone":"+1 570 366 5296",
    "sg:postcode":"17972",
    "sg:province":"PA",
    "sg:tags":[
        "landscape"
    ],
    "wof:name":"Growing Dreams Landscape Co",
    "wof:placetype":"venue"
},
  "geometry": {"coordinates":[-76.132869,40.649693],"type":"Point"}
}