{
  "type": "Feature",
  "properties": {
    "iso:country":"US",
    "sg:address":"496 Camp Horne Rd",
    "sg:city":"Pittsburgh",
    "sg:classifiers":[
        {
            "category":"Professional",
            "type":"Services"
        },
        {
            "category":"Building & Trades",
            "subcategory":"Construction",
            "type":"Services"
        }
    ],
    "sg:phone":"+1 412 766 3117",
    "sg:postcode":"15237",
    "sg:province":"PA",
    "sg:tags":[
        "general",
        "contractor"
    ],
    "wof:name":"Modany Falcone Inc",
    "wof:placetype":"venue"
},
  "geometry": {"coordinates":[-80.08805599999999,40.521146],"type":"Point"}
}