{
  "type": "Feature",
  "properties": {
    "iso:country":"US",
    "sg:address":"27 N Lansdowne Ave",
    "sg:city":"Lansdowne",
    "sg:classifiers":[
        {
            "category":"Shopping",
            "type":"Retail Goods"
        }
    ],
    "sg:phone":"+1   ",
    "sg:postcode":"19050",
    "sg:province":"PA",
    "sg:tags":[
        "coin"
    ],
    "wof:name":"Alpigini Coin Shop",
    "wof:placetype":"venue"
},
  "geometry": {"coordinates":[-75.272311,39.938824],"type":"Point"}
}