{
  "type": "Feature",
  "properties": {
    "addr:full":"842 E Ohio St Pittsburgh PA 15212",
    "addr:housenumber":"842",
    "addr:postcode":"15212",
    "addr:street":"E Ohio St",
    "iso:country":"US",
    "sg:address":"842 E Ohio St",
    "sg:city":"Pittsburgh",
    "sg:classifiers":[
        {
            "category":"Building & Trades",
            "subcategory":"Pest Control",
            "type":"Services"
        }
    ],
    "sg:phone":"+1   ",
    "sg:postcode":"15212",
    "sg:province":"PA",
    "sg:tags":[
        "exterminating"
    ],
    "wof:name":"Atlas Exterminating Co",
    "wof:placetype":"venue"
},
  "geometry": {"coordinates":[-79.99457,40.454958],"type":"Point"}
}