{
  "type": "Feature",
  "properties": {
    "iso:country":"US",
    "sg:address":"403 Main St",
    "sg:city":"Irwin",
    "sg:classifiers":[
        {
            "category":"Shopping",
            "type":"Retail Goods"
        }
    ],
    "sg:phone":"+1 724 861 8816",
    "sg:postcode":"15642",
    "sg:province":"PA",
    "sg:tags":[
        "merchandise"
    ],
    "wof:name":"K T Pets",
    "wof:placetype":"venue"
},
  "geometry": {"coordinates":[-79.711275,40.330963],"type":"Point"}
}