{
  "type": "Feature",
  "properties": {
    "addr:full":"202 Lycoming Mall Dr Muncy PA 17756",
    "addr:housenumber":"202",
    "addr:postcode":"17756",
    "addr:street":"Lycoming Mall Dr Muncy",
    "iso:country":"US",
    "sg:address":"202 Lycoming Mall Dr",
    "sg:city":"Muncy",
    "sg:classifiers":[
        {
            "category":"Autos & Motor Vehicles",
            "subcategory":"Automobile Sales",
            "type":"Retail Goods"
        }
    ],
    "sg:phone":"+1 570 546 5594",
    "sg:postcode":"17756",
    "sg:province":"PA",
    "sg:tags":[
        "car",
        "dealer"
    ],
    "wof:name":"Fairfield Honda",
    "wof:placetype":"venue"
},
  "geometry": {"coordinates":[-76.813041,41.236866],"type":"Point"}
}