{
  "type": "Feature",
  "properties": {
    "addr:full":"312 Thorndale Rd Port Matilda PA 16870",
    "addr:housenumber":"312",
    "addr:postcode":"16870",
    "addr:street":"Thorndale Rd",
    "iso:country":"US",
    "sg:address":"312 Thorndale Rd",
    "sg:city":"Port Matilda",
    "sg:classifiers":[
        {
            "category":"Sports & Exercise",
            "subcategory":"Gym",
            "type":"Entertainment"
        }
    ],
    "sg:phone":"+1   ",
    "sg:postcode":"16870",
    "sg:province":"PA",
    "sg:tags":[
        "fitness",
        "physical",
        "facility"
    ],
    "wof:name":"Fitness Coach",
    "wof:placetype":"venue"
},
  "geometry": {"coordinates":[-77.94543299999999,40.809517],"type":"Point"}
}