{
  "type": "Feature",
  "properties": {
    "iso:country":"US",
    "sg:address":"520 S Sydbury Ln",
    "sg:city":"Wynnewood",
    "sg:classifiers":[
        {
            "category":"Professional",
            "type":"Services"
        }
    ],
    "sg:phone":"+1   ",
    "sg:postcode":"19096",
    "sg:province":"PA",
    "wof:name":"US Power & Light Inc",
    "wof:placetype":"venue"
},
  "geometry": {"coordinates":[-75.278373,40.015329],"type":"Point"}
}