{
  "type": "Feature",
  "properties": {
    "addr:full":"1 W Mount Kirk Ave Norristown PA 19403",
    "addr:housenumber":"1",
    "addr:postcode":"19403",
    "addr:street":"W Mount Kirk Ave",
    "iso:country":"US",
    "sg:address":"1 W Mount Kirk Ave",
    "sg:city":"Norristown",
    "sg:classifiers":[
        {
            "category":"Personal",
            "subcategory":"Beauty Salon",
            "type":"Services"
        }
    ],
    "sg:phone":"+1 610 631 0341",
    "sg:postcode":"19403",
    "sg:province":"PA",
    "sg:tags":[
        "shop"
    ],
    "wof:name":"Hair Designs",
    "wof:placetype":"venue"
},
  "geometry": {"coordinates":[-75.40460899999999,40.152436],"type":"Point"}
}