{
  "type": "Feature",
  "properties": {
    "iso:country":"US",
    "sg:address":"757 5th St",
    "sg:city":"Beaver",
    "sg:classifiers":[
        {
            "category":"Real Estate",
            "subcategory":"Real Estate Operator",
            "type":"Services"
        }
    ],
    "sg:phone":"+1 724 775 0773",
    "sg:postcode":"15009",
    "sg:province":"PA",
    "sg:tags":[
        "building",
        "apartment"
    ],
    "wof:name":"Riverview Terrace Apartments",
    "wof:placetype":"venue"
},
  "geometry": {"coordinates":[-80.30904,40.698055],"type":"Point"}
}