{
  "type": "Feature",
  "properties": {
    "addr:full":"592 S Benbrook Rd Butler PA 16001",
    "addr:housenumber":"592",
    "addr:postcode":"16001",
    "addr:street":"S Benbrook Rd",
    "iso:country":"US",
    "sg:address":"592 S Benbrook Rd",
    "sg:city":"Butler",
    "sg:classifiers":[
        {
            "category":"Organizations",
            "subcategory":"Membership Organization",
            "type":"Services"
        }
    ],
    "sg:phone":"+1   ",
    "sg:postcode":"16001",
    "sg:province":"PA",
    "wof:name":"1965 66 Full Size Chevrolet",
    "wof:placetype":"venue"
},
  "geometry": {"coordinates":[-79.968024,40.868382],"type":"Point"}
}