{
  "type": "Feature",
  "properties": {
    "iso:country":"US",
    "sg:address":"93 Table Rock Rd",
    "sg:city":"Gettysburg",
    "sg:classifiers":[
        {
            "category":"Government",
            "subcategory":"Office",
            "type":"Public Place"
        }
    ],
    "sg:phone":"+1 717 334 1849",
    "sg:postcode":"17325",
    "sg:province":"PA",
    "sg:tags":[
        "village"
    ],
    "wof:name":"Cumberland Twp Authority",
    "wof:placetype":"venue"
},
  "geometry": {"coordinates":[-77.22986,39.850599],"type":"Point"}
}