{
  "type": "Feature",
  "properties": {
    "iso:country":"US",
    "sg:address":"1801 W Ontario St",
    "sg:city":"Philadelphia",
    "sg:classifiers":[
        {
            "category":"Food & Beverages",
            "subcategory":"Groceries & Convenience Stores",
            "type":"Retail Goods"
        }
    ],
    "sg:phone":"+1 215 226 4494",
    "sg:postcode":"19140",
    "sg:province":"PA",
    "wof:name":"Garcias Grocery",
    "wof:placetype":"venue"
},
  "geometry": {"coordinates":[-75.158699,40.005402],"type":"Point"}
}