{
  "type": "Feature",
  "properties": {
    "iso:country":"US",
    "sg:address":"664 Centreville Pike",
    "sg:city":"Slippery Rock",
    "sg:classifiers":[
        {
            "category":"Restaurant",
            "type":"Food & Drink"
        }
    ],
    "sg:phone":"+1 724 794 1899",
    "sg:postcode":"16057",
    "sg:province":"PA",
    "wof:name":"Wolf Creek School Cafe",
    "wof:placetype":"venue"
},
  "geometry": {"coordinates":[-80.04709,41.052193],"type":"Point"}
}