{
  "type": "Feature",
  "properties": {
    "iso:country":"US",
    "sg:address":"426 Pennsylvania Ave",
    "sg:city":"Fort Washington",
    "sg:classifiers":[
        {
            "category":"Organizations",
            "subcategory":"Labor Organization",
            "type":"Services"
        }
    ],
    "sg:phone":"+1 215 646 1620",
    "sg:postcode":"19034",
    "sg:province":"PA",
    "wof:name":"Communications Workers-America",
    "wof:placetype":"venue"
},
  "geometry": {"coordinates":[-75.20782,40.135073],"type":"Point"}
}