{
  "type": "Feature",
  "properties": {
    "addr:full":"636 Park City Ctr Lancaster PA 17601",
    "addr:housenumber":"636",
    "addr:postcode":"17601",
    "addr:street":"Park",
    "iso:country":"US",
    "sg:address":"636 Park City Ctr",
    "sg:city":"Lancaster",
    "sg:classifiers":[
        {
            "category":"Shopping",
            "subcategory":"Beauty & Cosmetics",
            "type":"Retail Goods"
        },
        {
            "category":"Home & Garden",
            "subcategory":"Home Furnishings",
            "type":"Retail Goods"
        },
        {
            "category":"Personal",
            "subcategory":"Skin Care",
            "type":"Services"
        }
    ],
    "sg:phone":"+1 717 397 5626",
    "sg:postcode":"17601",
    "sg:province":"PA",
    "sg:tags":[
        "candle",
        "perfume"
    ],
    "sg:website":"http://www.bathandbodyworks.com",
    "wof:name":"Bath and Body Works",
    "wof:placetype":"venue"
},
  "geometry": {"coordinates":[-76.34021300000001,40.065892],"type":"Point"}
}