{
  "type": "Feature",
  "properties": {
    "iso:country":"US",
    "sg:address":"3 E Fifth St",
    "sg:city":"Bloomsburg",
    "sg:classifiers":[
        {
            "category":"Real Estate",
            "subcategory":"Real Estate Services",
            "type":"Services"
        }
    ],
    "sg:phone":"+1   ",
    "sg:postcode":"17815",
    "sg:province":"PA",
    "sg:tags":[
        "abstract",
        "title"
    ],
    "wof:name":"C & M Abstract Co Inc",
    "wof:placetype":"venue"
},
  "geometry": {"coordinates":[-76.453216,41.000157],"type":"Point"}
}