{
  "type": "Feature",
  "properties": {
    "iso:country":"US",
    "sg:address":"7317 Mcknight Rd",
    "sg:city":"Pittsburgh",
    "sg:classifiers":[
        {
            "category":"Restaurant",
            "type":"Food & Drink"
        }
    ],
    "sg:menulink":"http://www.allmenus.com/pa/ross/172981-wendys/menu/",
    "sg:phone":"+1 412 366 7117",
    "sg:postcode":"15237",
    "sg:province":"PA",
    "sg:tags":[
        "burger",
        "american",
        "soup"
    ],
    "wof:name":"Wendy's",
    "wof:placetype":"venue"
},
  "geometry": {"coordinates":[-80.011701,40.537919],"type":"Point"}
}