{
  "type": "Feature",
  "properties": {
    "addr:full":"156 Taft Rd Saint Marys PA 15857",
    "addr:housenumber":"156",
    "addr:postcode":"15857",
    "addr:street":"Taft Rd",
    "iso:country":"US",
    "sg:address":"156 Taft Rd",
    "sg:city":"Saint Marys",
    "sg:classifiers":[
        {
            "category":"Shopping",
            "subcategory":"Jewelry",
            "type":"Retail Goods"
        }
    ],
    "sg:phone":"+1   ",
    "sg:postcode":"15857",
    "sg:province":"PA",
    "wof:name":"Fedders Jewelers",
    "wof:placetype":"venue"
},
  "geometry": {"coordinates":[-78.575005,41.466371],"type":"Point"}
}