{
  "type": "Feature",
  "properties": {
    "iso:country":"US",
    "sg:address":"11 Franklin Church Rd",
    "sg:city":"Dillsburg",
    "sg:classifiers":[
        {
            "category":"Retail",
            "subcategory":"Repair Shop",
            "type":"Services"
        }
    ],
    "sg:phone":"+1 717 432 1585",
    "sg:postcode":"17019",
    "sg:province":"PA",
    "sg:tags":[
        "scooter",
        "motorcycle",
        "motor"
    ],
    "sg:website":"www.pm2powertrainltd.com",
    "wof:name":"Power Train LTD",
    "wof:placetype":"venue"
},
  "geometry": {"coordinates":[-77.056569,40.069565],"type":"Point"}
}