{
  "type": "Feature",
  "properties": {
    "iso:country":"US",
    "sg:address":"2039 Long Run Rd",
    "sg:city":"Schuylkill Haven",
    "sg:classifiers":[
        {
            "category":"Autos & Motor Vehicles",
            "subcategory":"Automobile Sales",
            "type":"Retail Goods"
        }
    ],
    "sg:phone":"+1 570 385 0399",
    "sg:postcode":"17972",
    "sg:province":"PA",
    "sg:tags":[
        "car",
        "dealer"
    ],
    "wof:name":"Smoke's Auto Sales",
    "wof:placetype":"venue"
},
  "geometry": {"coordinates":[-76.18150300000001,40.622948],"type":"Point"}
}