{
  "type": "Feature",
  "properties": {
    "addr:full":"1329 N Mascher St Philadelphia PA 19123",
    "addr:housenumber":"1329",
    "addr:postcode":"19123",
    "addr:street":"N Mascher St",
    "iso:country":"US",
    "sg:address":"1329 N Mascher St",
    "sg:city":"Philadelphia",
    "sg:classifiers":[
        {
            "category":"Retail",
            "subcategory":"Auto Repair",
            "type":"Services"
        }
    ],
    "sg:phone":"+1 215 627 8438",
    "sg:postcode":"19123",
    "sg:province":"PA",
    "wof:name":"Sam's Garage",
    "wof:placetype":"venue"
},
  "geometry": {"coordinates":[-75.13707599999999,39.971391],"type":"Point"}
}