{
  "type": "Feature",
  "properties": {
    "addr:full":"3041 Derry Pl Philadelphia PA 19154",
    "addr:housenumber":"3041",
    "addr:postcode":"19154",
    "addr:street":"Derry Pl",
    "iso:country":"US",
    "sg:address":"3041 Derry Pl",
    "sg:city":"Philadelphia",
    "sg:classifiers":[
        {
            "category":"Building & Trades",
            "subcategory":"Plumbing",
            "type":"Services"
        }
    ],
    "sg:phone":"+1 215 281 0344",
    "sg:postcode":"19154",
    "sg:province":"PA",
    "sg:tags":[
        "conditioning",
        "air",
        "system",
        "contractor"
    ],
    "wof:name":"Mcs Heating & Air Cond",
    "wof:placetype":"venue"
},
  "geometry": {"coordinates":[-74.987182,40.094059],"type":"Point"}
}