{
  "type": "Feature",
  "properties": {
    "iso:country":"US",
    "sg:address":"10867 Spring Ridge Rd",
    "sg:city":"Shippensburg",
    "sg:classifiers":[
        {
            "category":"Farming",
            "subcategory":"Dairy Farm",
            "type":"Manufacturing & Wholesale Goods"
        }
    ],
    "sg:phone":"+1   ",
    "sg:postcode":"17257",
    "sg:province":"PA",
    "wof:name":"Wesley Zimmerman",
    "wof:placetype":"venue"
},
  "geometry": {"coordinates":[-77.565594,40.061596],"type":"Point"}
}