{
  "type": "Feature",
  "properties": {
    "iso:country":"US",
    "sg:address":"3812 Newburg Rd",
    "sg:city":"Easton",
    "sg:phone":"+1 610 252 8307",
    "sg:postcode":"18045",
    "sg:province":"PA",
    "sg:tags":[
        "farm",
        "corn"
    ],
    "wof:name":"Walnut Way Farm",
    "wof:placetype":"venue"
},
  "geometry": {"coordinates":[-75.28967,40.704147],"type":"Point"}
}