{
  "type": "Feature",
  "properties": {
    "addr:full":"759 S 8th St Philadelphia PA 19147",
    "addr:housenumber":"759",
    "addr:postcode":"19147",
    "addr:street":"S 8Th St",
    "iso:country":"US",
    "sg:address":"759 S 8th St",
    "sg:city":"Philadelphia",
    "sg:classifiers":[
        {
            "category":"Personal",
            "subcategory":"Barber",
            "type":"Services"
        }
    ],
    "sg:phone":"+1 215 928 9275",
    "sg:postcode":"19147",
    "sg:province":"PA",
    "wof:name":"Anthony's Barber Shop",
    "wof:placetype":"venue"
},
  "geometry": {"coordinates":[-75.15604999999999,39.939715],"type":"Point"}
}