{
  "type": "Feature",
  "properties": {
    "iso:country":"US",
    "sg:address":"123 Maple Ln",
    "sg:city":"Reading",
    "sg:classifiers":[
        {
            "category":"Building & Trades",
            "subcategory":"Construction",
            "type":"Services"
        }
    ],
    "sg:phone":"+1   ",
    "sg:postcode":"19605",
    "sg:province":"PA",
    "sg:tags":[
        "hanging",
        "contractor"
    ],
    "wof:name":"Barrell & Sweitzer Painting",
    "wof:placetype":"venue"
},
  "geometry": {"coordinates":[-75.991282,40.401768],"type":"Point"}
}