{
  "type": "Feature",
  "properties": {
    "addr:full":"782 Worth Blvd Pottstown PA 19465",
    "addr:housenumber":"782",
    "addr:postcode":"19465",
    "addr:street":"Worth Blvd",
    "iso:country":"US",
    "sg:address":"782 Worth Blvd",
    "sg:city":"Pottstown",
    "sg:classifiers":[
        {
            "category":"Real Estate",
            "subcategory":"Real Estate Operator",
            "type":"Services"
        }
    ],
    "sg:phone":"+1   ",
    "sg:postcode":"19465",
    "sg:province":"PA",
    "sg:tags":[
        "building",
        "apartment"
    ],
    "wof:name":"Ashwood Apts",
    "wof:placetype":"venue"
},
  "geometry": {"coordinates":[-75.634896,40.229646],"type":"Point"}
}