{
  "type": "Feature",
  "properties": {
    "iso:country":"US",
    "sg:address":"299 N Carlisle St",
    "sg:city":"New Bloomfield",
    "sg:phone":"+1 717 582 2949",
    "sg:postcode":"17068",
    "sg:province":"PA",
    "sg:tags":[
        "oil"
    ],
    "wof:name":"Swenson Fuels Inc",
    "wof:placetype":"venue"
},
  "geometry": {"coordinates":[-77.18776099999999,40.420645],"type":"Point"}
}