{
  "type": "Feature",
  "properties": {
    "addr:full":"925 Lincoln Ave Springfield PA 19064",
    "addr:housenumber":"925",
    "addr:postcode":"19064",
    "addr:street":"Lincoln Ave Springfield",
    "iso:country":"US",
    "sg:address":"925 Lincoln Ave",
    "sg:city":"Springfield",
    "sg:classifiers":[
        {
            "category":"Social Services",
            "type":"Services"
        }
    ],
    "sg:phone":"+1 610 604 0116",
    "sg:postcode":"19064",
    "sg:province":"PA",
    "sg:tags":[
        "consulting",
        "geriatric"
    ],
    "wof:name":"Older John",
    "wof:placetype":"venue"
},
  "geometry": {"coordinates":[-75.340766,39.914107],"type":"Point"}
}