{
  "type": "Feature",
  "properties": {
    "iso:country":"US",
    "sg:address":"11 Red Rowan Ln",
    "sg:city":"Plymouth Meeting",
    "sg:classifiers":[
        {
            "category":"Banks & Credit Unions",
            "subcategory":"Financial Services",
            "type":"Services"
        }
    ],
    "sg:phone":"+1   ",
    "sg:postcode":"19462",
    "sg:province":"PA",
    "sg:tags":[
        "co",
        "holding"
    ],
    "wof:name":"Kwait Family LLC",
    "wof:placetype":"venue"
},
  "geometry": {"coordinates":[-75.28977500000001,40.11994],"type":"Point"}
}