{
  "type": "Feature",
  "properties": {
    "iso:country":"US",
    "sg:address":"6816 Jackson St",
    "sg:city":"Philadelphia",
    "sg:classifiers":[
        {
            "category":"Place Of Worship",
            "subcategory":"Church",
            "type":"Public Place"
        },
        {
            "category":"Place Of Worship",
            "type":"Public Place"
        }
    ],
    "sg:phone":"+1 215 333 4103",
    "sg:postcode":"19135",
    "sg:province":"PA",
    "sg:tags":[
        "lutheran",
        "america",
        "churches-lutheran",
        "churches-lutheran-evangelical"
    ],
    "wof:name":"Saint Petri Evang Luth Ch",
    "wof:placetype":"venue"
},
  "geometry": {"coordinates":[-75.04627000000001,40.027445],"type":"Point"}
}