{
  "type": "Feature",
  "properties": {
    "addr:full":"1208 Cottage St Cresson PA 16630",
    "addr:housenumber":"1208",
    "addr:postcode":"16630",
    "addr:street":"Cottage St",
    "iso:country":"US",
    "sg:address":"1208 Cottage St",
    "sg:city":"Cresson",
    "sg:classifiers":[
        {
            "category":"Freight",
            "type":"Transportation"
        }
    ],
    "sg:phone":"+1   ",
    "sg:postcode":"16630",
    "sg:province":"PA",
    "sg:tags":[
        "special"
    ],
    "wof:name":"Cresson Springs Storage Units",
    "wof:placetype":"venue"
},
  "geometry": {"coordinates":[-78.59192400000001,40.458183],"type":"Point"}
}