{
  "type": "Feature",
  "properties": {
    "iso:country":"US",
    "sg:address":"662 Lincoln Hwy",
    "sg:city":"Fairless Hills",
    "sg:classifiers":[
        {
            "category":"Retail",
            "subcategory":"Auto Repair",
            "type":"Services"
        }
    ],
    "sg:phone":"+1 215 428 4010",
    "sg:postcode":"19030",
    "sg:province":"PA",
    "sg:tags":[
        "glass",
        "replacement"
    ],
    "wof:name":"S & L Glass Works",
    "wof:placetype":"venue"
},
  "geometry": {"coordinates":[-74.824468,40.191204],"type":"Point"}
}