{
  "type": "Feature",
  "properties": {
    "addr:full":"120 Bustleton Pike Southampton PA 18966",
    "addr:housenumber":"120",
    "addr:postcode":"18966",
    "addr:street":"Bustleton Pike",
    "iso:country":"US",
    "sg:address":"120 Bustleton Pike",
    "sg:city":"Southampton",
    "sg:classifiers":[
        {
            "category":"Health Services",
            "subcategory":"Chiropractor",
            "type":"Services"
        }
    ],
    "sg:phone":"+1 215 322 1300",
    "sg:postcode":"18966",
    "sg:province":"PA",
    "sg:tags":[
        "chiropractic"
    ],
    "wof:name":"Bloom Chiropractors",
    "wof:placetype":"venue"
},
  "geometry": {"coordinates":[-75.01319100000001,40.184711],"type":"Point"}
}