{
  "type": "Feature",
  "properties": {
    "iso:country":"US",
    "sg:address":"263 Main St",
    "sg:city":"Royersford",
    "sg:classifiers":[
        {
            "category":"Restaurant",
            "type":"Food & Drink"
        }
    ],
    "sg:phone":"+1 610 948 8812",
    "sg:postcode":"19468",
    "sg:province":"PA",
    "sg:tags":[
        "eating"
    ],
    "wof:name":"Best Spot In Town",
    "wof:placetype":"venue"
},
  "geometry": {"coordinates":[-75.54159300000001,40.183573],"type":"Point"}
}