{
  "type": "Feature",
  "properties": {
    "iso:country":"US",
    "sg:address":"2935 Byberry Rd",
    "sg:city":"Hatboro",
    "sg:classifiers":[
        {
            "category":"Wholesale",
            "subcategory":"Drugs",
            "type":"Manufacturing & Wholesale Goods"
        },
        {
            "category":"Professional",
            "subcategory":"Business Services",
            "type":"Services"
        }
    ],
    "sg:phone":"+1 215 443 8550",
    "sg:postcode":"19040",
    "sg:province":"PA",
    "sg:tags":[
        "development",
        "pharmaceutical",
        "product",
        "research"
    ],
    "wof:name":"Pangagenic Inc",
    "wof:placetype":"venue"
},
  "geometry": {"coordinates":[-75.09467100000001,40.170648],"type":"Point"}
}