{
  "type": "Feature",
  "properties": {
    "addr:full":"RR 309 Coopersburg PA 18036",
    "addr:postcode":"18036",
    "addr:street":"Coopersburg",
    "iso:country":"US",
    "sg:address":"RR 309",
    "sg:city":"Coopersburg",
    "sg:classifiers":[
        {
            "category":"Banks & Credit Unions",
            "subcategory":"Bank",
            "type":"Services"
        }
    ],
    "sg:phone":"+1 610 282 2860",
    "sg:postcode":"18036",
    "sg:province":"PA",
    "wof:name":"Keystone Savings Bank",
    "wof:placetype":"venue"
},
  "geometry": {"coordinates":[-75.387901,40.509701],"type":"Point"}
}