{
  "type": "Feature",
  "properties": {
    "iso:country":"US",
    "sg:address":"1307 Richmond Rd",
    "sg:city":"Fleetwood",
    "sg:phone":"+1   ",
    "sg:postcode":"19522",
    "sg:province":"PA",
    "sg:tags":[
        "farm"
    ],
    "wof:name":"Oak Grove Host Beans",
    "wof:placetype":"venue"
},
  "geometry": {"coordinates":[-75.850267,40.477215],"type":"Point"}
}