{
  "type": "Feature",
  "properties": {
    "addr:full":"727 Pin Oak Dr Lancaster PA 17601",
    "addr:housenumber":"727",
    "addr:postcode":"17601",
    "addr:street":"Pin Oak Dr",
    "iso:country":"US",
    "sg:address":"727 Pin Oak Dr",
    "sg:city":"Lancaster",
    "sg:classifiers":[
        {
            "category":"Manufacturing",
            "subcategory":"Metals",
            "type":"Manufacturing & Wholesale Goods"
        }
    ],
    "sg:phone":"+1   ",
    "sg:postcode":"17601",
    "sg:province":"PA",
    "sg:tags":[
        "stampings",
        "mfg"
    ],
    "wof:name":"Daf Associates",
    "wof:placetype":"venue"
},
  "geometry": {"coordinates":[-76.37288100000001,40.055379],"type":"Point"}
}