{
  "type": "Feature",
  "properties": {
    "addr:full":"3805 Vartan Way Harrisburg PA 17110",
    "addr:postcode":"3805;17110",
    "addr:street":"Vartan Way",
    "iso:country":"US",
    "sg:address":"3805 Vartan Way",
    "sg:city":"Harrisburg",
    "sg:classifiers":[
        {
            "category":"Shopping",
            "subcategory":"Books",
            "type":"Retail Goods"
        }
    ],
    "sg:phone":"+1 717 541 3909",
    "sg:postcode":"17110",
    "sg:province":"PA",
    "sg:tags":[
        "store"
    ],
    "sg:website":"http://www.thecampushub.com",
    "wof:name":"Widener University Law School",
    "wof:placetype":"venue"
},
  "geometry": {"coordinates":[-76.85424,40.323481],"type":"Point"}
}