{
  "type": "Feature",
  "properties": {
    "iso:country":"US",
    "sg:address":"1440 Oakland Rd",
    "sg:city":"Chadds Ford",
    "sg:classifiers":[
        {
            "category":"Building & Trades",
            "subcategory":"Landscaping Services",
            "type":"Services"
        }
    ],
    "sg:phone":"+1 610 399 9590",
    "sg:postcode":"19382",
    "sg:province":"PA",
    "wof:name":"D Adams & Co Inc",
    "wof:placetype":"venue"
},
  "geometry": {"coordinates":[-75.562337,39.896065],"type":"Point"}
}