{
  "type": "Feature",
  "properties": {
    "iso:country":"US",
    "sg:address":"50 Lebanon Hills Dr",
    "sg:city":"Pittsburgh",
    "sg:classifiers":[
        {
            "category":"Shopping",
            "subcategory":"Gifts & Souvenirs",
            "type":"Retail Goods"
        }
    ],
    "sg:phone":"+1   ",
    "sg:postcode":"15228",
    "sg:province":"PA",
    "wof:name":"Simply Sign It",
    "wof:placetype":"venue"
},
  "geometry": {"coordinates":[-80.047776,40.371469],"type":"Point"}
}