{
  "type": "Feature",
  "properties": {
    "addr:full":"1947 Franklin Mills Cir Philadelphia PA 19154",
    "addr:housenumber":"1947",
    "addr:postcode":"19154",
    "addr:street":"Franklin Mills Cir",
    "iso:country":"US",
    "sg:address":"1947 Franklin Mills Cir",
    "sg:city":"Philadelphia",
    "sg:phone":"+1 215 637 9208",
    "sg:postcode":"19154",
    "sg:province":"PA",
    "sg:tags":[
        "fixture",
        "store"
    ],
    "wof:name":"Ralph D Cohen Store Fixtures",
    "wof:placetype":"venue"
},
  "geometry": {"coordinates":[-74.964158,40.082296],"type":"Point"}
}