{
  "type": "Feature",
  "properties": {
    "iso:country":"US",
    "sg:address":"310 Biddle Dr",
    "sg:city":"Exton",
    "sg:classifiers":[
        {
            "category":"Professional",
            "type":"Services"
        }
    ],
    "sg:phone":"+1   ",
    "sg:postcode":"19341",
    "sg:province":"PA",
    "wof:name":"Dilorbek Inc",
    "wof:placetype":"venue"
},
  "geometry": {"coordinates":[-75.647233,40.041827],"type":"Point"}
}