{
  "type": "Feature",
  "properties": {
    "iso:country":"US",
    "sg:address":"48 E Center St",
    "sg:city":"Nazareth",
    "sg:classifiers":[
        {
            "category":"Shopping",
            "subcategory":"Jewelry",
            "type":"Retail Goods"
        }
    ],
    "sg:phone":"+1   ",
    "sg:postcode":"18064",
    "sg:province":"PA",
    "wof:name":"Oswald G S",
    "wof:placetype":"venue"
},
  "geometry": {"coordinates":[-75.30965500000001,40.742422],"type":"Point"}
}