{
  "type": "Feature",
  "properties": {
    "iso:country":"US",
    "sg:address":"2961 W Liberty Ave",
    "sg:city":"South Hills",
    "sg:classifiers":[
        {
            "category":"Social Services",
            "type":"Services"
        }
    ],
    "sg:phone":"+1 412 341 8326",
    "sg:postcode":"15216",
    "sg:province":"PA",
    "sg:tags":[
        "counselor",
        "marriage",
        "family"
    ],
    "wof:name":"Julie Pastorius",
    "wof:placetype":"venue"
},
  "geometry": {"coordinates":[-80.034948,40.394531],"type":"Point"}
}