{
  "type": "Feature",
  "properties": {
    "addr:full":"2341 Columbia Blvd Bloomsburg PA 17815",
    "addr:housenumber":"2341",
    "addr:postcode":"17815",
    "addr:street":"Columbia Blvd",
    "iso:country":"US",
    "sg:address":"2341 Columbia Blvd",
    "sg:city":"Bloomsburg",
    "sg:classifiers":[
        {
            "category":"Restaurant",
            "type":"Food & Drink"
        }
    ],
    "sg:menulink":"http://www.allmenus.com/pa/scott/215095-taco-bell/menu/",
    "sg:phone":"+1 570 784 5381",
    "sg:postcode":"17815",
    "sg:province":"PA",
    "sg:tags":[
        "mexican"
    ],
    "wof:name":"Taco Bell",
    "wof:placetype":"venue"
},
  "geometry": {"coordinates":[-76.415059,41.010754],"type":"Point"}
}