{
  "type": "Feature",
  "properties": {
    "addr:full":"513 W Butler Ave Chalfont PA 18914",
    "addr:housenumber":"513",
    "addr:postcode":"18914",
    "addr:street":"W Butler Ave",
    "iso:country":"US",
    "sg:address":"513 W Butler Ave",
    "sg:city":"Chalfont",
    "sg:classifiers":[
        {
            "category":"Personal",
            "subcategory":"Barber",
            "type":"Services"
        }
    ],
    "sg:phone":"+1 215 996 1644",
    "sg:postcode":"18914",
    "sg:province":"PA",
    "wof:name":"Many Men's Hair Stylist",
    "wof:placetype":"venue"
},
  "geometry": {"coordinates":[-75.225601,40.268398],"type":"Point"}
}