{
  "type": "Feature",
  "properties": {
    "addr:full":"499 Center New Texas Rd Pittsburgh PA 15239",
    "addr:housenumber":"499",
    "addr:postcode":"15239",
    "addr:street":"Center New Texas Rd",
    "iso:country":"US",
    "sg:address":"499 Center New Texas Rd",
    "sg:city":"Pittsburgh",
    "sg:classifiers":[
        {
            "category":"Organizations",
            "subcategory":"Non-profit Organization",
            "type":"Services"
        },
        {
            "category":"Social Services",
            "subcategory":"Adult Care",
            "type":"Services"
        },
        {
            "category":"Social Services",
            "type":"Services"
        }
    ],
    "sg:phone":"+1 412 795 2330",
    "sg:postcode":"15239",
    "sg:province":"PA",
    "sg:tags":[
        "senior",
        "center",
        "citizen"
    ],
    "wof:name":"Plum Borough Senior Cmnty Ctr",
    "wof:placetype":"venue"
},
  "geometry": {"coordinates":[-79.75216399999999,40.488313],"type":"Point"}
}