{
  "type": "Feature",
  "properties": {
    "addr:full":"130 Post House Rd Breezewood PA 15533",
    "addr:housenumber":"130",
    "addr:postcode":"15533",
    "addr:street":"Post House Rd",
    "iso:country":"US",
    "sg:address":"130 Post House Rd",
    "sg:city":"Breezewood",
    "sg:classifiers":[
        {
            "category":"Manufacturing",
            "subcategory":"Food",
            "type":"Manufacturing & Wholesale Goods"
        }
    ],
    "sg:phone":"+1   ",
    "sg:postcode":"15533",
    "sg:province":"PA",
    "sg:tags":[
        "product",
        "mfg"
    ],
    "wof:name":"Bedford Donuts",
    "wof:placetype":"venue"
},
  "geometry": {"coordinates":[-78.237956,39.998306],"type":"Point"}
}