{
  "type": "Feature",
  "properties": {
    "iso:country":"US",
    "sg:address":"270 S 20th St",
    "sg:city":"Philadelphia",
    "sg:classifiers":[
        {
            "category":"Restaurant",
            "type":"Food & Drink"
        },
        {
            "category":"Food & Beverages",
            "subcategory":"Meat & Fish",
            "type":"Retail Goods"
        }
    ],
    "sg:menulink":"http://www.allmenus.com/pa/philadelphia/262221-seafood-unlimited/menu/",
    "sg:phone":"+1 215 732 9012",
    "sg:postcode":"19103",
    "sg:province":"PA",
    "sg:tags":[
        "seafood",
        "american"
    ],
    "wof:name":"Seafood Unlimited",
    "wof:placetype":"venue"
},
  "geometry": {"coordinates":[-75.174367,39.948459],"type":"Point"}
}