{
  "type": "Feature",
  "properties": {
    "addr:full":"1220 E Chestnut St Lebanon PA 17042",
    "addr:housenumber":"1220",
    "addr:postcode":"17042",
    "addr:street":"E Chestnut St",
    "iso:country":"US",
    "sg:address":"1220 E Chestnut St",
    "sg:city":"Lebanon",
    "sg:classifiers":[
        {
            "category":"Health Services",
            "subcategory":"Health Practitioner",
            "type":"Services"
        }
    ],
    "sg:phone":"+1 717 270 9465",
    "sg:postcode":"17042",
    "sg:province":"PA",
    "sg:tags":[
        "nurse",
        "registry"
    ],
    "wof:name":"Barbara Garber Rn Legal Nurse",
    "wof:placetype":"venue"
},
  "geometry": {"coordinates":[-76.389343,40.344529],"type":"Point"}
}