{
  "type": "Feature",
  "properties": {
    "iso:country":"US",
    "sg:address":"175 S Warren St",
    "sg:city":"Berwick",
    "sg:classifiers":[
        {
            "category":"Retail",
            "subcategory":"Car Wash",
            "type":"Services"
        }
    ],
    "sg:phone":"+1 570 752 2811",
    "sg:postcode":"18603",
    "sg:province":"PA",
    "sg:tags":[
        "polishing",
        "washing"
    ],
    "wof:name":"Barchik's Car Wash",
    "wof:placetype":"venue"
},
  "geometry": {"coordinates":[-76.25199000000001,41.048867],"type":"Point"}
}