{
  "type": "Feature",
  "properties": {
    "addr:full":"353 Markle Dr Harrisburg PA 17111",
    "addr:housenumber":"353",
    "addr:postcode":"17111",
    "addr:street":"Markle Dr",
    "iso:country":"US",
    "sg:address":"353 Markle Dr",
    "sg:city":"Harrisburg",
    "sg:classifiers":[
        {
            "category":"Professional",
            "subcategory":"Management & Consulting",
            "type":"Services"
        }
    ],
    "sg:phone":"+1 717 561 8030",
    "sg:postcode":"17111",
    "sg:province":"PA",
    "sg:tags":[
        "consultant"
    ],
    "wof:name":"Reynolds Consulting Engr Inc",
    "wof:placetype":"venue"
},
  "geometry": {"coordinates":[-76.810483,40.261967],"type":"Point"}
}