{
  "type": "Feature",
  "properties": {
    "addr:full":"1131 Saucony Rd Kutztown PA 19530",
    "addr:housenumber":"1131",
    "addr:postcode":"19530",
    "addr:street":"Saucony Rd",
    "iso:country":"US",
    "sg:address":"1131 Saucony Rd",
    "sg:city":"Kutztown",
    "sg:classifiers":[
        {
            "category":"Travel",
            "subcategory":"Campground",
            "type":"Entertainment"
        }
    ],
    "sg:phone":"+1   ",
    "sg:postcode":"19530",
    "sg:province":"PA",
    "sg:tags":[
        "trailer"
    ],
    "wof:name":"Kutztown Campground New Dutch",
    "wof:placetype":"venue"
},
  "geometry": {"coordinates":[-75.813576,40.53256],"type":"Point"}
}