{
  "type": "Feature",
  "properties": {
    "iso:country":"US",
    "sg:address":"428 Chickasaw Ave",
    "sg:city":"Pittsburgh",
    "sg:classifiers":[
        {
            "category":"Real Estate",
            "subcategory":"Real Estate Agent",
            "type":"Services"
        }
    ],
    "sg:phone":"+1   ",
    "sg:postcode":"15237",
    "sg:province":"PA",
    "wof:name":"Why USA Homes For U RE",
    "wof:placetype":"venue"
},
  "geometry": {"coordinates":[-80.046915,40.569902],"type":"Point"}
}