{
  "type": "Feature",
  "properties": {
    "addr:full":"5521 Irving St Philadelphia PA 19139",
    "addr:housenumber":"5521",
    "addr:postcode":"19139",
    "addr:street":"Irving St",
    "iso:country":"US",
    "sg:address":"5521 Irving St",
    "sg:city":"Philadelphia",
    "sg:classifiers":[
        {
            "category":"Organizations",
            "subcategory":"Religious Organization",
            "type":"Services"
        }
    ],
    "sg:phone":"+1 215 748 2178",
    "sg:postcode":"19139",
    "sg:province":"PA",
    "sg:tags":[
        "clergy"
    ],
    "wof:name":"Charles R Robinson",
    "wof:placetype":"venue"
},
  "geometry": {"coordinates":[-75.23180000000001,39.955948],"type":"Point"}
}