{
  "type": "Feature",
  "properties": {
    "iso:country":"US",
    "sg:address":"2929 Hazel St",
    "sg:city":"Erie",
    "sg:classifiers":[
        {
            "category":"Professional",
            "subcategory":"Computer Services",
            "type":"Services"
        }
    ],
    "sg:phone":"+1   ",
    "sg:postcode":"16508",
    "sg:province":"PA",
    "sg:tags":[
        "datum"
    ],
    "wof:name":"Page Boys Web Design & Svcs",
    "wof:placetype":"venue"
},
  "geometry": {"coordinates":[-80.085408,42.101808],"type":"Point"}
}