{
  "type": "Feature",
  "properties": {
    "iso:country":"US",
    "sg:address":"225 Latimore Valley Rd",
    "sg:city":"York Springs",
    "sg:classifiers":[
        {
            "category":"Professional",
            "subcategory":"Lawyer & Legal Services",
            "type":"Services"
        }
    ],
    "sg:phone":"+1 717 528 4500",
    "sg:postcode":"17372",
    "sg:province":"PA",
    "sg:tags":[
        "attorney"
    ],
    "wof:name":"Worley & Worley",
    "wof:placetype":"venue"
},
  "geometry": {"coordinates":[-77.080133,40.024428],"type":"Point"}
}