{
  "type": "Feature",
  "properties": {
    "addr:full":"1383 E College Ave State College PA 16801",
    "addr:housenumber":"1383",
    "addr:postcode":"16801",
    "addr:street":"E College Ave",
    "iso:country":"US",
    "sg:address":"1383 E College Ave",
    "sg:city":"State College",
    "sg:classifiers":[
        {
            "category":"Retail",
            "subcategory":"Repair Shop",
            "type":"Services"
        }
    ],
    "sg:phone":"+1 814 237 1398",
    "sg:postcode":"16801",
    "sg:province":"PA",
    "sg:tags":[
        "lock",
        "locksmith"
    ],
    "wof:name":"Auman's Key Shop",
    "wof:placetype":"venue"
},
  "geometry": {"coordinates":[-77.83077,40.810683],"type":"Point"}
}