{
  "type": "Feature",
  "properties": {
    "iso:country":"US",
    "sg:address":"1067 Washington Ave",
    "sg:city":"Carnegie",
    "sg:phone":"+1 412 279 8500",
    "sg:postcode":"15106",
    "sg:province":"PA",
    "wof:name":"Pizza Torino",
    "wof:placetype":"venue"
},
  "geometry": {"coordinates":[-80.083443,40.398024],"type":"Point"}
}