{
  "type": "Feature",
  "properties": {
    "iso:country":"US",
    "sg:address":"50 Pepperell Dr",
    "sg:city":"Feasterville Trevose",
    "sg:classifiers":[
        {
            "category":"Building & Trades",
            "subcategory":"Construction",
            "type":"Services"
        }
    ],
    "sg:phone":"+1   ",
    "sg:postcode":"19053",
    "sg:province":"PA",
    "sg:tags":[
        "house"
    ],
    "wof:name":"Manning William E Jr",
    "wof:placetype":"venue"
},
  "geometry": {"coordinates":[-74.953277,40.186074],"type":"Point"}
}