{
  "type": "Feature",
  "properties": {
    "iso:country":"US",
    "sg:address":"20 Elco Dr",
    "sg:city":"Coraopolis",
    "sg:classifiers":[
        {
            "category":"Home & Garden",
            "subcategory":"Building Materials",
            "type":"Retail Goods"
        }
    ],
    "sg:phone":"+1   ",
    "sg:postcode":"15108",
    "sg:province":"PA",
    "wof:name":"K & B Door Masters",
    "wof:placetype":"venue"
},
  "geometry": {"coordinates":[-80.1337,40.479902],"type":"Point"}
}