{
  "type": "Feature",
  "properties": {
    "addr:full":"235 W 17th St Berwick PA 18603",
    "addr:housenumber":"235",
    "addr:postcode":"18603",
    "addr:street":"W 17Th St",
    "iso:country":"US",
    "sg:address":"235 W 17th St",
    "sg:city":"Berwick",
    "sg:classifiers":[
        {
            "category":"Retail",
            "subcategory":"Veterinary Services",
            "type":"Services"
        }
    ],
    "sg:phone":"+1 570 759 0397",
    "sg:postcode":"18603",
    "sg:province":"PA",
    "sg:tags":[
        "clinic",
        "hospital"
    ],
    "wof:name":"North Berwick Animal Hospital",
    "wof:placetype":"venue"
},
  "geometry": {"coordinates":[-76.246539,41.064842],"type":"Point"}
}