{
  "type": "Feature",
  "properties": {
    "addr:full":"1043 S 59th St Philadelphia PA 19143",
    "addr:housenumber":"1043",
    "addr:postcode":"19143",
    "addr:street":"S 59Th St",
    "iso:country":"US",
    "sg:address":"1043 S 59th St",
    "sg:city":"Philadelphia",
    "sg:classifiers":[
        {
            "category":"Wholesale",
            "subcategory":"Fruits & Vegetables",
            "type":"Manufacturing & Wholesale Goods"
        }
    ],
    "sg:phone":"+1 215 922 7819",
    "sg:postcode":"19143",
    "sg:province":"PA",
    "sg:tags":[
        "veggie"
    ],
    "wof:name":"P & F Giordano",
    "wof:placetype":"venue"
},
  "geometry": {"coordinates":[-75.22580000000001,39.944401],"type":"Point"}
}