{
  "type": "Feature",
  "properties": {
    "addr:full":"1611 Babcock Blvd Pittsburgh PA 15209",
    "addr:housenumber":"1611",
    "addr:postcode":"15209",
    "addr:street":"Babcock Blvd",
    "iso:country":"US",
    "sg:address":"1611 Babcock Blvd",
    "sg:city":"Pittsburgh",
    "sg:classifiers":[
        {
            "category":"Bars & Pubs",
            "type":"Food & Drink"
        }
    ],
    "sg:phone":"+1   ",
    "sg:postcode":"15209",
    "sg:province":"PA",
    "sg:tags":[
        "drinking"
    ],
    "wof:name":"Michaels Inn",
    "wof:placetype":"venue"
},
  "geometry": {"coordinates":[-79.97985799999999,40.499224],"type":"Point"}
}