{
  "type": "Feature",
  "properties": {
    "addr:full":"45 N Market St Lancaster PA 17603",
    "addr:housenumber":"45",
    "addr:postcode":"17603",
    "addr:street":"N Market St",
    "iso:country":"US",
    "sg:address":"45 N Market St",
    "sg:city":"Lancaster",
    "sg:classifiers":[
        {
            "category":"Manufacturing",
            "subcategory":"Jewelry",
            "type":"Manufacturing & Wholesale Goods"
        }
    ],
    "sg:phone":"+1   ",
    "sg:postcode":"17603",
    "sg:province":"PA",
    "sg:tags":[
        "precious",
        "metal",
        "mfg"
    ],
    "wof:name":"Gold Woven Basket Co",
    "wof:placetype":"venue"
},
  "geometry": {"coordinates":[-76.306641,40.037889],"type":"Point"}
}