{
  "type": "Feature",
  "properties": {
    "iso:country":"US",
    "sg:address":"144 W Columbus Ave",
    "sg:city":"Nesquehoning",
    "sg:classifiers":[
        {
            "category":"Building & Trades",
            "subcategory":"Construction",
            "type":"Services"
        }
    ],
    "sg:phone":"+1   ",
    "sg:postcode":"18240",
    "sg:province":"PA",
    "sg:tags":[
        "contractor"
    ],
    "wof:name":"St2 Tile Contractors",
    "wof:placetype":"venue"
},
  "geometry": {"coordinates":[-75.817123,40.866864],"type":"Point"}
}