{
  "type": "Feature",
  "properties": {
    "iso:country":"US",
    "sg:address":"1516 Sansom St",
    "sg:city":"Philadelphia",
    "sg:classifiers":[
        {
            "category":"Restaurant",
            "type":"Food & Drink"
        },
        {
            "category":"Brewery",
            "type":"Food & Drink"
        }
    ],
    "sg:menulink":"http://www.allmenus.com/pa/philadelphia/262207-nodding-head-brewery--rstrnt/menu/",
    "sg:phone":"+1 215 567 9525",
    "sg:postcode":"19102",
    "sg:province":"PA",
    "sg:tags":[
        "new",
        "american"
    ],
    "wof:name":"Nodding Head Brewery & Rstrnt",
    "wof:placetype":"venue"
},
  "geometry": {"coordinates":[-75.16618099999999,39.950222],"type":"Point"}
}