{
  "type": "Feature",
  "properties": {
    "iso:country":"US",
    "sg:address":"750 Commonwealth Dr",
    "sg:city":"Warrendale",
    "sg:classifiers":[
        {
            "category":"Government",
            "subcategory":"Post Office",
            "type":"Public Place"
        }
    ],
    "sg:phone":"+1 724 000 1111",
    "sg:postcode":"15086",
    "sg:province":"PA",
    "wof:name":"US Post Office",
    "wof:placetype":"venue"
},
  "geometry": {"coordinates":[-80.106301,40.675284],"type":"Point"}
}