{
  "type": "Feature",
  "properties": {
    "addr:full":"1708 Chestnut St Philadelphia PA 19103",
    "addr:housenumber":"1708",
    "addr:postcode":"19103",
    "addr:street":"Chestnut St",
    "iso:country":"US",
    "sg:address":"1708 Chestnut St",
    "sg:city":"Philadelphia",
    "sg:classifiers":[
        {
            "category":"Shopping",
            "subcategory":"Clothing, Apparel, & Fashions",
            "type":"Retail Goods"
        }
    ],
    "sg:phone":"+1 215 557 6990",
    "sg:postcode":"19103",
    "sg:province":"PA",
    "sg:tags":[
        "accessory",
        "clothing",
        "women's"
    ],
    "sg:website":"www.dressbarn.com",
    "wof:name":"Dress Barn",
    "wof:placetype":"venue"
},
  "geometry": {"coordinates":[-75.16909800000001,39.951698],"type":"Point"}
}