{
  "type": "Feature",
  "properties": {
    "iso:country":"US",
    "sg:address":"1413 Pittsburgh St",
    "sg:city":"Cheswick",
    "sg:classifiers":[
        {
            "category":"Insurance",
            "subcategory":"Hazard Insurance",
            "type":"Services"
        },
        {
            "category":"Insurance",
            "subcategory":"Insurance Agent",
            "type":"Services"
        }
    ],
    "sg:phone":"+1 724 274 8938",
    "sg:postcode":"15024",
    "sg:province":"PA",
    "sg:tags":[
        "personal",
        "agency",
        "commercial"
    ],
    "sg:website":"www.lanzolutzins.com",
    "wof:name":"Lanzo Lutz & Associates Inc",
    "wof:placetype":"venue"
},
  "geometry": {"coordinates":[-79.799539,40.541632],"type":"Point"}
}