{
  "type": "Feature",
  "properties": {
    "iso:country":"US",
    "sg:address":"243 N Duke St",
    "sg:city":"Lancaster",
    "sg:classifiers":[
        {
            "category":"Professional",
            "subcategory":"Business Services",
            "type":"Services"
        }
    ],
    "sg:phone":"+1   ",
    "sg:postcode":"17602",
    "sg:province":"PA",
    "wof:name":"Burns Larry Interior Design",
    "wof:placetype":"venue"
},
  "geometry": {"coordinates":[-76.304478,40.042815],"type":"Point"}
}