{
  "type": "Feature",
  "properties": {
    "iso:country":"US",
    "sg:address":"802 Sans Souci Pkwy",
    "sg:city":"Hanover Twp",
    "sg:classifiers":[
        {
            "category":"Bars & Pubs",
            "type":"Food & Drink"
        }
    ],
    "sg:phone":"+1 570 208 1096",
    "sg:postcode":"18706",
    "sg:province":"PA",
    "sg:tags":[
        "drinking"
    ],
    "wof:name":"Jimmy's Nite Club & Cafe",
    "wof:placetype":"venue"
},
  "geometry": {"coordinates":[-75.92316599999999,41.231145],"type":"Point"}
}