{
  "type": "Feature",
  "properties": {
    "iso:country":"US",
    "sg:address":"731 Scalp Ave",
    "sg:city":"Johnstown",
    "sg:classifiers":[
        {
            "category":"Shopping",
            "subcategory":"Stationery & Office Supplies",
            "type":"Retail Goods"
        }
    ],
    "sg:phone":"+1 814 266 2221",
    "sg:postcode":"15904",
    "sg:province":"PA",
    "sg:tags":[
        "equipment",
        "filing",
        "system"
    ],
    "sg:website":"www.availbusinesssystems.com",
    "wof:name":"Avail Business Systems",
    "wof:placetype":"venue"
},
  "geometry": {"coordinates":[-78.866812,40.288659],"type":"Point"}
}