{
  "type": "Feature",
  "properties": {
    "iso:country":"US",
    "sg:address":"7644 City Ave",
    "sg:city":"Philadelphia",
    "sg:classifiers":[
        {
            "category":"Restaurant",
            "type":"Food & Drink"
        }
    ],
    "sg:menulink":"http://www.allmenus.com/pa/lower-merion/17157-pizza-al-forno/menu/",
    "sg:phone":"+1 215 879 9184",
    "sg:postcode":"19151",
    "sg:province":"PA",
    "sg:tags":[
        "sandwich",
        "salad",
        "burger",
        "seafood",
        "soup",
        "american",
        "wrap",
        "cheesesteaks",
        "pizza"
    ],
    "wof:name":"Pizza Al Forno",
    "wof:placetype":"venue"
},
  "geometry": {"coordinates":[-75.27234,39.978842],"type":"Point"}
}