{
  "type": "Feature",
  "properties": {
    "addr:full":"1740 11th St Bethlehem PA 18020",
    "addr:housenumber":"1740",
    "addr:postcode":"18020",
    "addr:street":"11Th St",
    "iso:country":"US",
    "sg:address":"1740 11th St",
    "sg:city":"Bethlehem",
    "sg:classifiers":[
        {
            "category":"Building & Trades",
            "subcategory":"Construction",
            "type":"Services"
        }
    ],
    "sg:phone":"+1 610 691 3798",
    "sg:postcode":"18020",
    "sg:province":"PA",
    "sg:tags":[
        "tile",
        "dealer"
    ],
    "wof:name":"James J Mc Shane",
    "wof:placetype":"venue"
},
  "geometry": {"coordinates":[-75.321532,40.641467],"type":"Point"}
}