{
  "type": "Feature",
  "properties": {
    "iso:country":"US",
    "sg:address":"1176 Mickley Rd",
    "sg:city":"Whitehall",
    "sg:classifiers":[
        {
            "category":"Building & Trades",
            "subcategory":"Construction",
            "type":"Services"
        },
        {
            "category":"Retail",
            "subcategory":"Storage",
            "type":"Services"
        },
        {
            "category":"Home & Garden",
            "subcategory":"Furniture",
            "type":"Retail Goods"
        }
    ],
    "sg:phone":"+1 610 439 8959",
    "sg:postcode":"18052",
    "sg:province":"PA",
    "sg:tags":[
        "outdoor",
        "household",
        "commercial",
        "contractor",
        "patio",
        "store"
    ],
    "sg:website":"http://www.greenacreslawnfurniture.com",
    "wof:name":"Green Acres Outdoor Living",
    "wof:placetype":"venue"
},
  "geometry": {"coordinates":[-75.485732,40.637777],"type":"Point"}
}