{
  "type": "Feature",
  "properties": {
    "addr:full":"2158 W Union Blvd Bethlehem PA 18018",
    "addr:housenumber":"2158",
    "addr:postcode":"18018",
    "addr:street":"W Union Blvd",
    "iso:country":"US",
    "sg:address":"2158 W Union Blvd",
    "sg:city":"Bethlehem",
    "sg:classifiers":[
        {
            "category":"Deli",
            "type":"Food & Drink"
        },
        {
            "category":"Food & Beverages",
            "subcategory":"Bakery",
            "type":"Retail Goods"
        }
    ],
    "sg:phone":"+1 610 807 3566",
    "sg:postcode":"18018",
    "sg:province":"PA",
    "sg:tags":[
        "sandwich"
    ],
    "wof:name":"Jerry's Deli",
    "wof:placetype":"venue"
},
  "geometry": {"coordinates":[-75.419532,40.626507],"type":"Point"}
}