{
  "type": "Feature",
  "properties": {
    "addr:full":"100 S Broad St Philadelphia PA 19146",
    "addr:housenumber":"100",
    "addr:postcode":"19146",
    "addr:street":"S Broad St",
    "iso:country":"US",
    "sg:address":"100 S Broad St",
    "sg:city":"Philadelphia",
    "sg:classifiers":[
        {
            "category":"Wholesale",
            "subcategory":"Electrical",
            "type":"Manufacturing & Wholesale Goods"
        }
    ],
    "sg:phone":"+1 215 832 0303",
    "sg:postcode":"19146",
    "sg:province":"PA",
    "sg:tags":[
        "telecommunication"
    ],
    "wof:name":"Tele-Systems Inc",
    "wof:placetype":"venue"
},
  "geometry": {"coordinates":[-75.164174,39.950112],"type":"Point"}
}