{
  "type": "Feature",
  "properties": {
    "addr:full":"547 Saint Davids Ave Wayne PA 19087",
    "addr:housenumber":"547",
    "addr:postcode":"19087",
    "addr:street":"Saint Davids Ave",
    "iso:country":"US",
    "sg:address":"547 Saint Davids Ave",
    "sg:city":"Wayne",
    "sg:classifiers":[
        {
            "category":"Manufacturing",
            "subcategory":"Chemicals & Compounds",
            "type":"Manufacturing & Wholesale Goods"
        }
    ],
    "sg:phone":"+1   ",
    "sg:postcode":"19087",
    "sg:province":"PA",
    "sg:tags":[
        "mfg"
    ],
    "wof:name":"H B Fuller Company",
    "wof:placetype":"venue"
},
  "geometry": {"coordinates":[-75.369173,40.045326],"type":"Point"}
}