{
  "type": "Feature",
  "properties": {
    "iso:country":"US",
    "sg:address":"144 N School House Rd",
    "sg:city":"Thomasville",
    "sg:classifiers":[
        {
            "category":"Retail",
            "subcategory":"Veterinary Services",
            "type":"Services"
        }
    ],
    "sg:phone":"+1 717 259 9276",
    "sg:postcode":"17364",
    "sg:province":"PA",
    "sg:tags":[
        "veterinarian"
    ],
    "wof:name":"Maroche Equine Clinic",
    "wof:placetype":"venue"
},
  "geometry": {"coordinates":[-76.932011,39.900357],"type":"Point"}
}