{
  "type": "Feature",
  "properties": {
    "addr:full":"20 Commerce Dr Pittsburgh PA 15239",
    "addr:housenumber":"20",
    "addr:postcode":"15239",
    "addr:street":"Commerce Dr",
    "iso:country":"US",
    "sg:address":"20 Commerce Dr",
    "sg:city":"Pittsburgh",
    "sg:classifiers":[
        {
            "category":"Home & Garden",
            "subcategory":"Building Materials",
            "type":"Retail Goods"
        }
    ],
    "sg:phone":"+1 412 793 3507",
    "sg:postcode":"15239",
    "sg:province":"PA",
    "sg:tags":[
        "mixed",
        "concrete"
    ],
    "wof:name":"Stone & Co",
    "wof:placetype":"venue"
},
  "geometry": {"coordinates":[-79.772324,40.465727],"type":"Point"}
}