{
  "type": "Feature",
  "properties": {
    "addr:full":"122 S Locust St Ebensburg PA 15931",
    "addr:housenumber":"122",
    "addr:postcode":"15931",
    "addr:street":"S Locust St",
    "iso:country":"US",
    "sg:address":"122 S Locust St",
    "sg:city":"Ebensburg",
    "sg:classifiers":[
        {
            "category":"Manufacturing",
            "subcategory":"Printing",
            "type":"Manufacturing & Wholesale Goods"
        }
    ],
    "sg:phone":"+1 814 472 9530",
    "sg:postcode":"15931",
    "sg:province":"PA",
    "sg:tags":[
        "commercial"
    ],
    "sg:website":"www.daminprinting.com",
    "wof:name":"Damin Printing Co",
    "wof:placetype":"venue"
},
  "geometry": {"coordinates":[-78.72394199999999,40.484965],"type":"Point"}
}