{
  "type": "Feature",
  "properties": {
    "iso:country":"US",
    "sg:address":"4990 State Rd",
    "sg:city":"Drexel Hill",
    "sg:classifiers":[
        {
            "category":"Shopping",
            "subcategory":"Gifts & Souvenirs",
            "type":"Retail Goods"
        }
    ],
    "sg:phone":"+1 610 626 0565",
    "sg:postcode":"19026",
    "sg:province":"PA",
    "wof:name":"Dollar Spot",
    "wof:placetype":"venue"
},
  "geometry": {"coordinates":[-75.325637,39.945833],"type":"Point"}
}