{
  "type": "Feature",
  "properties": {
    "iso:country":"US",
    "sg:address":"233 W 8th St",
    "sg:city":"Waynesboro",
    "sg:classifiers":[
        {
            "category":"Personal",
            "subcategory":"Barber",
            "type":"Services"
        }
    ],
    "sg:phone":"+1 717 762 1821",
    "sg:postcode":"17268",
    "sg:province":"PA",
    "wof:name":"Roffler Family Hair Center",
    "wof:placetype":"venue"
},
  "geometry": {"coordinates":[-77.59050000000001,39.7477],"type":"Point"}
}