{
  "type": "Feature",
  "properties": {
    "addr:full":"228 S Church St Hazleton PA 18201",
    "addr:housenumber":"228",
    "addr:postcode":"18201",
    "addr:street":"S Church St",
    "iso:country":"US",
    "sg:address":"228 S Church St",
    "sg:city":"Hazleton",
    "sg:classifiers":[
        {
            "category":"Banks & Credit Unions",
            "subcategory":"Bank",
            "type":"Services"
        }
    ],
    "sg:phone":"+1   ",
    "sg:postcode":"18201",
    "sg:province":"PA",
    "sg:tags":[
        "federal"
    ],
    "wof:name":"Cred-U-Comp Inc",
    "wof:placetype":"venue"
},
  "geometry": {"coordinates":[-75.980009,40.949043],"type":"Point"}
}