{
  "type": "Feature",
  "properties": {
    "addr:full":"2637 Shillington Rd Reading PA 19608",
    "addr:housenumber":"2637",
    "addr:postcode":"19608",
    "addr:street":"Shillington Rd",
    "iso:country":"US",
    "sg:address":"2637 Shillington Rd",
    "sg:city":"Reading",
    "sg:classifiers":[
        {
            "category":"Home & Garden",
            "subcategory":"Furniture",
            "type":"Retail Goods"
        }
    ],
    "sg:phone":"+1   ",
    "sg:postcode":"19608",
    "sg:province":"PA",
    "sg:tags":[
        "mattress",
        "bed",
        "accessory"
    ],
    "wof:name":"Lemoyne Sleeper",
    "wof:placetype":"venue"
},
  "geometry": {"coordinates":[-76.000232,40.315685],"type":"Point"}
}