{
  "type": "Feature",
  "properties": {
    "iso:country":"US",
    "sg:address":"363 Hard Hill Rd",
    "sg:city":"Hamburg",
    "sg:classifiers":[
        {
            "category":"Utilities",
            "type":"Services"
        }
    ],
    "sg:phone":"+1 610 562 8447",
    "sg:postcode":"19526",
    "sg:province":"PA",
    "sg:tags":[
        "sanitary",
        "construction"
    ],
    "wof:name":"Richard M Wells Paving",
    "wof:placetype":"venue"
},
  "geometry": {"coordinates":[-75.86955,40.519647],"type":"Point"}
}