{
  "type": "Feature",
  "properties": {
    "iso:country":"US",
    "sg:address":"2127 N 6th St",
    "sg:city":"Philadelphia",
    "sg:classifiers":[
        {
            "category":"Professional",
            "type":"Services"
        }
    ],
    "sg:phone":"+1 215 235 8411",
    "sg:postcode":"19122",
    "sg:province":"PA",
    "sg:tags":[
        "establishment"
    ],
    "wof:name":"Safe-Base",
    "wof:placetype":"venue"
},
  "geometry": {"coordinates":[-75.143787,39.984574],"type":"Point"}
}