{
  "type": "Feature",
  "properties": {
    "addr:full":"500 Main St Great Bend PA 18821",
    "addr:housenumber":"500",
    "addr:postcode":"18821",
    "addr:street":"Main St",
    "iso:country":"US",
    "sg:address":"500 Main St",
    "sg:city":"Great Bend",
    "sg:classifiers":[
        {
            "category":"Organizations",
            "subcategory":"Religious Organization",
            "type":"Services"
        }
    ],
    "sg:phone":"+1 570 879 4506",
    "sg:postcode":"18821",
    "sg:province":"PA",
    "sg:tags":[
        "church"
    ],
    "wof:name":"United Methodist Community Chr",
    "wof:placetype":"venue"
},
  "geometry": {"coordinates":[-75.74561,41.97415],"type":"Point"}
}