{
  "type": "Feature",
  "properties": {
    "addr:full":"1473 Collier Ave Carnegie PA 15106",
    "addr:housenumber":"1473",
    "addr:postcode":"15106",
    "addr:street":"Collier Ave",
    "iso:country":"US",
    "sg:address":"1473 Collier Ave",
    "sg:city":"Carnegie",
    "sg:classifiers":[
        {
            "category":"Retail",
            "subcategory":"Auto Repair",
            "type":"Services"
        }
    ],
    "sg:phone":"+1 412 276 1766",
    "sg:postcode":"15106",
    "sg:province":"PA",
    "sg:tags":[
        "automobile",
        "inspection"
    ],
    "wof:name":"Carnegie Motors",
    "wof:placetype":"venue"
},
  "geometry": {"coordinates":[-80.09079699999999,40.3885],"type":"Point"}
}