{
  "type": "Feature",
  "properties": {
    "iso:country":"US",
    "sg:address":"37 E South St",
    "sg:city":"Wilkes Barre",
    "sg:classifiers":[
        {
            "category":"Shopping",
            "subcategory":"Discount & Variety Stores",
            "type":"Retail Goods"
        }
    ],
    "sg:phone":"+1 570 824 3171",
    "sg:postcode":"18701",
    "sg:province":"PA",
    "wof:name":"ANH Closeouts",
    "wof:placetype":"venue"
},
  "geometry": {"coordinates":[-75.88700799999999,41.241529],"type":"Point"}
}