{
  "type": "Feature",
  "properties": {
    "iso:country":"US",
    "sg:address":"198 Main St",
    "sg:city":"Greenville",
    "sg:classifiers":[
        {
            "category":"Wholesale",
            "subcategory":"Medical Equipment & Supplies",
            "type":"Manufacturing & Wholesale Goods"
        }
    ],
    "sg:phone":"+1 724 589 0262",
    "sg:postcode":"16125",
    "sg:province":"PA",
    "sg:tags":[
        "physician",
        "surgeon"
    ],
    "wof:name":"Kathco Medical Supply",
    "wof:placetype":"venue"
},
  "geometry": {"coordinates":[-80.389045,41.405082],"type":"Point"}
}