{
  "type": "Feature",
  "properties": {
    "iso:country":"US",
    "sg:address":"312 N 4th St",
    "sg:city":"Clairton",
    "sg:classifiers":[
        {
            "category":"Professional",
            "subcategory":"Management & Consulting",
            "type":"Services"
        }
    ],
    "sg:phone":"+1   ",
    "sg:postcode":"15025",
    "sg:province":"PA",
    "sg:tags":[
        "business"
    ],
    "wof:name":"Cest",
    "wof:placetype":"venue"
},
  "geometry": {"coordinates":[-79.88966000000001,40.305583],"type":"Point"}
}