{
  "type": "Feature",
  "properties": {
    "iso:country":"US",
    "sg:address":"4811 Winsford Rd",
    "sg:city":"Harrisburg",
    "sg:classifiers":[
        {
            "category":"Banks & Credit Unions",
            "subcategory":"Bank",
            "type":"Services"
        }
    ],
    "sg:phone":"+1   ",
    "sg:postcode":"17109",
    "sg:province":"PA",
    "sg:tags":[
        "broker",
        "mortgage"
    ],
    "wof:name":"Penn Mortgage and Leasing",
    "wof:placetype":"venue"
},
  "geometry": {"coordinates":[-76.808573,40.285924],"type":"Point"}
}