{
  "type": "Feature",
  "properties": {
    "addr:full":"654 Red Lion Rd Huntingdon Vly PA 19006",
    "addr:housenumber":"654",
    "addr:postcode":"19006",
    "addr:street":"Red Lion Rd",
    "iso:country":"US",
    "sg:address":"654 Red Lion Rd",
    "sg:city":"Huntingdon Vly",
    "sg:classifiers":[
        {
            "category":"Banks & Credit Unions",
            "subcategory":"Investment Brokerage",
            "type":"Services"
        }
    ],
    "sg:phone":"+1 215 947 9660",
    "sg:postcode":"19006",
    "sg:province":"PA",
    "sg:tags":[
        "consultant",
        "planning",
        "financial"
    ],
    "wof:name":"Fed Professionals",
    "wof:placetype":"venue"
},
  "geometry": {"coordinates":[-75.062029,40.124551],"type":"Point"}
}