{
  "type": "Feature",
  "properties": {
    "addr:full":"521 Highgate Rd Norristown PA 19403",
    "addr:housenumber":"521",
    "addr:postcode":"19403",
    "addr:street":"Highgate Rd",
    "iso:country":"US",
    "sg:address":"521 Highgate Rd",
    "sg:city":"Norristown",
    "sg:classifiers":[
        {
            "category":"Wholesale",
            "subcategory":"Groceries",
            "type":"Manufacturing & Wholesale Goods"
        }
    ],
    "sg:phone":"+1   ",
    "sg:postcode":"19403",
    "sg:province":"PA",
    "wof:name":"B&B Assoc",
    "wof:placetype":"venue"
},
  "geometry": {"coordinates":[-75.391409,40.158742],"type":"Point"}
}