{
  "type": "Feature",
  "properties": {
    "addr:full":"2340 Warren Rd Indiana PA 15701",
    "addr:housenumber":"2340",
    "addr:postcode":"15701",
    "addr:street":"Warren Rd",
    "iso:country":"US",
    "sg:address":"2340 Warren Rd",
    "sg:city":"Indiana",
    "sg:classifiers":[
        {
            "category":"Health Services",
            "subcategory":"Chiropractor",
            "type":"Services"
        }
    ],
    "sg:phone":"+1 724 464 0400",
    "sg:postcode":"15701",
    "sg:province":"PA",
    "wof:name":"Fanella Chiropractic Clinic",
    "wof:placetype":"venue"
},
  "geometry": {"coordinates":[-79.187253,40.610198],"type":"Point"}
}