{
  "type": "Feature",
  "properties": {
    "iso:country":"US",
    "sg:address":"190 Hawkins Rd",
    "sg:city":"Oxford",
    "sg:phone":"+1   ",
    "sg:postcode":"19363",
    "sg:province":"PA",
    "sg:tags":[
        "farm",
        "corn"
    ],
    "wof:name":"Herrvale",
    "wof:placetype":"venue"
},
  "geometry": {"coordinates":[-75.945168,39.848834],"type":"Point"}
}