{
  "type": "Feature",
  "properties": {
    "iso:country":"US",
    "sg:address":"668 Cochran Mill Rd",
    "sg:city":"Clairton",
    "sg:classifiers":[
        {
            "category":"Manufacturing",
            "subcategory":"Tools & Machinery",
            "type":"Manufacturing & Wholesale Goods"
        }
    ],
    "sg:phone":"+1 412 655 4452",
    "sg:postcode":"15025",
    "sg:province":"PA",
    "sg:tags":[
        "machine",
        "shop"
    ],
    "wof:name":"D & R Machine Co",
    "wof:placetype":"venue"
},
  "geometry": {"coordinates":[-79.973585,40.302329],"type":"Point"}
}