{
  "type": "Feature",
  "properties": {
    "addr:full":"513 Baltimore Pike Media PA 19063",
    "addr:housenumber":"513",
    "addr:postcode":"19063",
    "addr:street":"Baltimore Pike",
    "iso:country":"US",
    "sg:address":"513 Baltimore Pike",
    "sg:city":"Media",
    "sg:classifiers":[
        {
            "category":"Home & Garden",
            "subcategory":"Building Materials",
            "type":"Retail Goods"
        }
    ],
    "sg:phone":"+1 610 627 1464",
    "sg:postcode":"19063",
    "sg:province":"PA",
    "sg:tags":[
        "windows"
    ],
    "wof:name":"Pella Window Store",
    "wof:placetype":"venue"
},
  "geometry": {"coordinates":[-75.398794,39.917343],"type":"Point"}
}