{
  "type": "Feature",
  "properties": {
    "iso:country":"US",
    "sg:address":"5236 Mallard Dr",
    "sg:city":"Gibsonia",
    "sg:classifiers":[
        {
            "category":"Professional",
            "subcategory":"Secretarial Services",
            "type":"Services"
        }
    ],
    "sg:phone":"+1   ",
    "sg:postcode":"15044",
    "sg:province":"PA",
    "sg:tags":[
        "reporting"
    ],
    "wof:name":"Viras Transcription Service",
    "wof:placetype":"venue"
},
  "geometry": {"coordinates":[-79.951432,40.614356],"type":"Point"}
}