{
  "type": "Feature",
  "properties": {
    "iso:country":"US",
    "sg:address":"135 Outlet Sq",
    "sg:city":"Hershey",
    "sg:classifiers":[
        {
            "category":"Shopping",
            "subcategory":"Clothing, Apparel, & Fashions",
            "type":"Retail Goods"
        }
    ],
    "sg:phone":"+1 717 533 1494",
    "sg:postcode":"17033",
    "sg:province":"PA",
    "sg:tags":[
        "designer"
    ],
    "wof:name":"Calvin Klein",
    "wof:placetype":"venue"
},
  "geometry": {"coordinates":[-76.647544,40.294752],"type":"Point"}
}