{
  "type": "Feature",
  "properties": {
    "iso:country":"US",
    "sg:address":"144 W John St",
    "sg:city":"Bedford",
    "sg:classifiers":[
        {
            "category":"Organizations",
            "subcategory":"Religious Organization",
            "type":"Services"
        }
    ],
    "sg:phone":"+1 814 623 8817",
    "sg:postcode":"15522",
    "sg:province":"PA",
    "sg:tags":[
        "church"
    ],
    "wof:name":"St John's United Church-Christ",
    "wof:placetype":"venue"
},
  "geometry": {"coordinates":[-78.505167,40.015716],"type":"Point"}
}