{
  "type": "Feature",
  "properties": {
    "iso:country":"US",
    "sg:address":"1366 East Ave",
    "sg:city":"Abington",
    "sg:classifiers":[
        {
            "category":"Building & Trades",
            "subcategory":"Construction",
            "type":"Services"
        }
    ],
    "sg:phone":"+1   ",
    "sg:postcode":"19001",
    "sg:province":"PA",
    "sg:tags":[
        "hanging",
        "contractor"
    ],
    "wof:name":"Rgh Painting",
    "wof:placetype":"venue"
},
  "geometry": {"coordinates":[-75.128732,40.127829],"type":"Point"}
}