{
  "type": "Feature",
  "properties": {
    "addr:full":"258 Inverness Cir Chalfont PA 18914",
    "addr:housenumber":"258",
    "addr:postcode":"18914",
    "addr:street":"Inverness Cir",
    "iso:country":"US",
    "sg:address":"258 Inverness Cir",
    "sg:city":"Chalfont",
    "sg:classifiers":[
        {
            "category":"Retail",
            "subcategory":"Photofinishing",
            "type":"Services"
        }
    ],
    "sg:phone":"+1   ",
    "sg:postcode":"18914",
    "sg:province":"PA",
    "sg:tags":[
        "laboratory",
        "book"
    ],
    "wof:name":"I Photo Central LLC",
    "wof:placetype":"venue"
},
  "geometry": {"coordinates":[-75.213464,40.268441],"type":"Point"}
}