{
  "type": "Feature",
  "properties": {
    "iso:country":"US",
    "sg:address":"112 N 2nd St",
    "sg:city":"Jeannette",
    "sg:classifiers":[
        {
            "category":"Retail",
            "subcategory":"Funeral Services",
            "type":"Services"
        }
    ],
    "sg:phone":"+1 724 527 2168",
    "sg:postcode":"15644",
    "sg:province":"PA",
    "sg:tags":[
        "director"
    ],
    "wof:name":"Lawrence J Mc Clure Funeral Hm",
    "wof:placetype":"venue"
},
  "geometry": {"coordinates":[-79.61356000000001,40.328649],"type":"Point"}
}