{
  "type": "Feature",
  "properties": {
    "iso:country":"US",
    "sg:address":"63 Perkins Rd",
    "sg:city":"Clarion",
    "sg:classifiers":[
        {
            "category":"Personal",
            "subcategory":"Beauty Salon",
            "type":"Services"
        }
    ],
    "sg:phone":"+1   ",
    "sg:postcode":"16214",
    "sg:province":"PA",
    "sg:tags":[
        "shop"
    ],
    "wof:name":"Smart Styles",
    "wof:placetype":"venue"
},
  "geometry": {"coordinates":[-79.393548,41.189893],"type":"Point"}
}