{
  "type": "Feature",
  "properties": {
    "iso:country":"US",
    "sg:address":"476 Main Rd",
    "sg:city":"Hanover Twp",
    "sg:classifiers":[
        {
            "category":"Personal",
            "subcategory":"Beauty Salon",
            "type":"Services"
        }
    ],
    "sg:phone":"+1 570 825 3655",
    "sg:postcode":"18706",
    "sg:province":"PA",
    "sg:tags":[
        "manicuring"
    ],
    "wof:name":"Larbella",
    "wof:placetype":"venue"
},
  "geometry": {"coordinates":[-75.94493300000001,41.221205],"type":"Point"}
}