{
  "type": "Feature",
  "properties": {
    "iso:country":"US",
    "sg:address":"110 Wilmington W Chester Pike",
    "sg:city":"Chadds Ford",
    "sg:classifiers":[
        {
            "category":"Shopping",
            "subcategory":"Pharmacy",
            "type":"Retail Goods"
        }
    ],
    "sg:phone":"+1 484 785 0030",
    "sg:postcode":"19317",
    "sg:province":"PA",
    "sg:tags":[
        "drugstore"
    ],
    "wof:name":"Walgreen Drug Stores",
    "wof:placetype":"venue"
},
  "geometry": {"coordinates":[-75.538096,39.842293],"type":"Point"}
}