{
  "type": "Feature",
  "properties": {
    "addr:full":"17 E State St Quarryville PA 17566",
    "addr:housenumber":"17",
    "addr:postcode":"17566",
    "addr:street":"E State St",
    "iso:country":"US",
    "sg:address":"17 E State St",
    "sg:city":"Quarryville",
    "sg:classifiers":[
        {
            "category":"Shopping",
            "subcategory":"Discount & Variety Stores",
            "type":"Retail Goods"
        }
    ],
    "sg:phone":"+1   ",
    "sg:postcode":"17566",
    "sg:province":"PA",
    "wof:name":"Dollar General",
    "wof:placetype":"venue"
},
  "geometry": {"coordinates":[-76.162813,39.897328],"type":"Point"}
}