{
  "type": "Feature",
  "properties": {
    "addr:full":"2944 Dekalb Pike Norristown PA 19401",
    "addr:housenumber":"2944",
    "addr:postcode":"19401",
    "addr:street":"Dekalb Pike",
    "iso:country":"US",
    "sg:address":"2944 Dekalb Pike",
    "sg:city":"Norristown",
    "sg:classifiers":[
        {
            "category":"Professional",
            "subcategory":"Accounting & Tax Preparation",
            "type":"Services"
        }
    ],
    "sg:phone":"+1 610 279 8160",
    "sg:postcode":"19401",
    "sg:province":"PA",
    "sg:tags":[
        "accountant"
    ],
    "wof:name":"Gambone George A CPA",
    "wof:placetype":"venue"
},
  "geometry": {"coordinates":[-75.311798,40.142601],"type":"Point"}
}