{
  "type": "Feature",
  "properties": {
    "iso:country":"US",
    "sg:address":"511 S Juniata St",
    "sg:city":"Lewistown",
    "sg:classifiers":[
        {
            "category":"Building & Trades",
            "subcategory":"Plumbing",
            "type":"Services"
        }
    ],
    "sg:phone":"+1 717 242 1794",
    "sg:postcode":"17044",
    "sg:province":"PA",
    "sg:tags":[
        "heating",
        "contractor"
    ],
    "wof:name":"Lenair",
    "wof:placetype":"venue"
},
  "geometry": {"coordinates":[-77.569749,40.589446],"type":"Point"}
}