{
  "type": "Feature",
  "properties": {
    "iso:country":"US",
    "sg:address":"209 E Bellevue Ave",
    "sg:city":"Reading",
    "sg:classifiers":[
        {
            "category":"Retail",
            "subcategory":"Auto Repair",
            "type":"Services"
        }
    ],
    "sg:phone":"+1 610 929 1430",
    "sg:postcode":"19605",
    "sg:province":"PA",
    "sg:tags":[
        "truck"
    ],
    "wof:name":"Austin Fleet Maintenance",
    "wof:placetype":"venue"
},
  "geometry": {"coordinates":[-75.93131099999999,40.385666],"type":"Point"}
}