{
  "type": "Feature",
  "properties": {
    "addr:full":"2810 Larchmont Dr York PA 17404",
    "addr:housenumber":"2810",
    "addr:postcode":"17404",
    "addr:street":"Larchmont Dr",
    "iso:country":"US",
    "sg:address":"2810 Larchmont Dr",
    "sg:city":"York",
    "sg:classifiers":[
        {
            "category":"Professional",
            "type":"Services"
        }
    ],
    "sg:phone":"+1   ",
    "sg:postcode":"17404",
    "sg:province":"PA",
    "wof:name":"Dcu LLC",
    "wof:placetype":"venue"
},
  "geometry": {"coordinates":[-76.78430299999999,40.013701],"type":"Point"}
}