{
  "type": "Feature",
  "properties": {
    "addr:full":"1701 Cochran Rd Pittsburgh PA 15220",
    "addr:housenumber":"1701",
    "addr:postcode":"15220",
    "addr:street":"Cochran Rd",
    "iso:country":"US",
    "sg:address":"1701 Cochran Rd",
    "sg:city":"Pittsburgh",
    "sg:classifiers":[
        {
            "category":"Banks & Credit Unions",
            "subcategory":"Bank",
            "type":"Services"
        }
    ],
    "sg:phone":"+1 412 344 7600",
    "sg:postcode":"15220",
    "sg:province":"PA",
    "sg:website":"www.nationalcity.com",
    "wof:name":"National City",
    "wof:placetype":"venue"
},
  "geometry": {"coordinates":[-80.05940200000001,40.3909],"type":"Point"}
}