{
  "type": "Feature",
  "properties": {
    "iso:country":"US",
    "sg:address":"1580 Orchard Dr",
    "sg:city":"Chambersburg",
    "sg:classifiers":[
        {
            "category":"Restaurant",
            "type":"Food & Drink"
        }
    ],
    "sg:phone":"+1   ",
    "sg:postcode":"17201",
    "sg:province":"PA",
    "sg:tags":[
        "drinking",
        "eating"
    ],
    "wof:name":"Orchards Restaurant Inc",
    "wof:placetype":"venue"
},
  "geometry": {"coordinates":[-77.664292,39.913596],"type":"Point"}
}