{
  "type": "Feature",
  "properties": {
    "iso:country":"US",
    "sg:address":"1823 E Venango St",
    "sg:city":"Philadelphia",
    "sg:classifiers":[
        {
            "category":"Shopping",
            "type":"Retail Goods"
        }
    ],
    "sg:phone":"+1   ",
    "sg:postcode":"19134",
    "sg:province":"PA",
    "sg:tags":[
        "swimming",
        "pool",
        "supply"
    ],
    "wof:name":"Annies Pool Center",
    "wof:placetype":"venue"
},
  "geometry": {"coordinates":[-75.103224,40.000415],"type":"Point"}
}