{
  "type": "Feature",
  "properties": {
    "iso:country":"US",
    "sg:address":"112 Broadway St",
    "sg:city":"Connellsville",
    "sg:classifiers":[
        {
            "category":"Building & Trades",
            "subcategory":"Construction",
            "type":"Services"
        }
    ],
    "sg:phone":"+1   ",
    "sg:postcode":"15425",
    "sg:province":"PA",
    "sg:tags":[
        "excavation",
        "contractor"
    ],
    "wof:name":"Rosensteel Construction",
    "wof:placetype":"venue"
},
  "geometry": {"coordinates":[-79.619592,40.011441],"type":"Point"}
}