{
  "type": "Feature",
  "properties": {
    "iso:country":"US",
    "sg:address":"22 Wabash St",
    "sg:city":"Pittsburgh",
    "sg:classifiers":[
        {
            "category":"Restaurant",
            "type":"Food & Drink"
        }
    ],
    "sg:phone":"+1 412 921 2601",
    "sg:postcode":"15220",
    "sg:province":"PA",
    "wof:name":"Rosie's Cafe",
    "wof:placetype":"venue"
},
  "geometry": {"coordinates":[-80.03435899999999,40.4402],"type":"Point"}
}