{
  "type": "Feature",
  "properties": {
    "iso:country":"US",
    "sg:address":"1344 W Somerset St",
    "sg:city":"Philadelphia",
    "sg:classifiers":[
        {
            "category":"Place Of Worship",
            "subcategory":"Church",
            "type":"Public Place"
        },
        {
            "category":"Place Of Worship",
            "type":"Public Place"
        },
        {
            "category":"Organizations",
            "subcategory":"Non-profit Organization",
            "type":"Services"
        }
    ],
    "sg:phone":"+1 215 227 0222",
    "sg:postcode":"19132",
    "sg:province":"PA",
    "sg:tags":[
        "churches-catholic-traditional",
        "community",
        "churches-catholic",
        "service/non-profit"
    ],
    "wof:name":"Greater Love Temple of Faith Church",
    "wof:placetype":"venue"
},
  "geometry": {"coordinates":[-75.153267,39.99528],"type":"Point"}
}