{
  "type": "Feature",
  "properties": {
    "addr:full":"727 Wood St Wilkinsburg PA 15221",
    "addr:housenumber":"727",
    "addr:postcode":"15221",
    "addr:street":"Wood St",
    "iso:country":"US",
    "sg:address":"727 Wood St",
    "sg:city":"Wilkinsburg",
    "sg:classifiers":[
        {
            "category":"Organizations",
            "subcategory":"Religious Organization",
            "type":"Services"
        }
    ],
    "sg:phone":"+1 412 731 8228",
    "sg:postcode":"15221",
    "sg:province":"PA",
    "sg:tags":[
        "church"
    ],
    "wof:name":"Shalom Apostolic Church",
    "wof:placetype":"venue"
},
  "geometry": {"coordinates":[-79.885746,40.442034],"type":"Point"}
}