{
  "type": "Feature",
  "properties": {
    "iso:country":"US",
    "sg:address":"1270 Herrs Ridge Rd",
    "sg:city":"Gettysburg",
    "sg:classifiers":[
        {
            "category":"Organizations",
            "subcategory":"Religious Organization",
            "type":"Services"
        }
    ],
    "sg:phone":"+1 717 338 2003",
    "sg:postcode":"17325",
    "sg:province":"PA",
    "sg:tags":[
        "church"
    ],
    "wof:name":"Herr's Ridge Mennonite",
    "wof:placetype":"venue"
},
  "geometry": {"coordinates":[-77.263018,39.840516],"type":"Point"}
}