{
  "type": "Feature",
  "properties": {
    "addr:full":"500 Centre St Ashland PA 17921",
    "addr:housenumber":"500",
    "addr:postcode":"17921",
    "addr:street":"Centre St",
    "iso:country":"US",
    "sg:address":"500 Centre St",
    "sg:city":"Ashland",
    "sg:classifiers":[
        {
            "category":"Personal",
            "subcategory":"Beauty Salon",
            "type":"Services"
        }
    ],
    "sg:phone":"+1 570 875 4620",
    "sg:postcode":"17921",
    "sg:province":"PA",
    "wof:name":"Salon Designs",
    "wof:placetype":"venue"
},
  "geometry": {"coordinates":[-76.339164,40.782866],"type":"Point"}
}