{
  "type": "Feature",
  "properties": {
    "addr:full":"226 Hampton Dr Birdsboro PA 19508",
    "addr:housenumber":"226",
    "addr:postcode":"19508",
    "addr:street":"Hampton Dr",
    "iso:country":"US",
    "sg:address":"226 Hampton Dr",
    "sg:city":"Birdsboro",
    "sg:classifiers":[
        {
            "category":"Travel",
            "subcategory":"Travel Agent",
            "type":"Entertainment"
        }
    ],
    "sg:phone":"+1 610 582 1556",
    "sg:postcode":"19508",
    "sg:province":"PA",
    "sg:tags":[
        "agency",
        "bureau"
    ],
    "wof:name":"Going Your Way",
    "wof:placetype":"venue"
},
  "geometry": {"coordinates":[-75.811138,40.257145],"type":"Point"}
}