{
  "type": "Feature",
  "properties": {
    "addr:full":"6306 Chelton Ave Harrisburg PA 17112",
    "addr:housenumber":"6306",
    "addr:postcode":"17112",
    "addr:street":"Chelton Ave",
    "iso:country":"US",
    "sg:address":"6306 Chelton Ave",
    "sg:city":"Harrisburg",
    "sg:classifiers":[
        {
            "category":"Organizations",
            "subcategory":"Religious Organization",
            "type":"Services"
        }
    ],
    "sg:phone":"+1 717 652 0372",
    "sg:postcode":"17112",
    "sg:province":"PA",
    "sg:tags":[
        "church"
    ],
    "wof:name":"Child Evangelism Fellowship",
    "wof:placetype":"venue"
},
  "geometry": {"coordinates":[-76.778526,40.330049],"type":"Point"}
}