{
  "type": "Feature",
  "properties": {
    "iso:country":"US",
    "sg:address":"132 W Germantown Pike",
    "sg:city":"Norristown",
    "sg:classifiers":[
        {
            "category":"Shopping",
            "subcategory":"Hobbies, Toys, & Games",
            "type":"Retail Goods"
        }
    ],
    "sg:phone":"+1 610 277 7707",
    "sg:postcode":"19401",
    "sg:province":"PA",
    "wof:name":"Scrapbooks N Smiles LLC",
    "wof:placetype":"venue"
},
  "geometry": {"coordinates":[-75.320634,40.145635],"type":"Point"}
}