{
  "type": "Feature",
  "properties": {
    "addr:full":"248 Chatham Park Dr Pittsburgh PA 15220",
    "addr:housenumber":"248",
    "addr:postcode":"15220",
    "addr:street":"Chatham Park Dr",
    "iso:country":"US",
    "sg:address":"248 Chatham Park Dr",
    "sg:city":"Pittsburgh",
    "sg:classifiers":[
        {
            "category":"Professional",
            "subcategory":"Computer Services",
            "type":"Services"
        }
    ],
    "sg:phone":"+1   ",
    "sg:postcode":"15220",
    "sg:province":"PA",
    "sg:tags":[
        "development",
        "consulting",
        "retail",
        "business",
        "software"
    ],
    "wof:name":"Syntax Inc",
    "wof:placetype":"venue"
},
  "geometry": {"coordinates":[-80.05762799999999,40.401203],"type":"Point"}
}