{
  "type": "Feature",
  "properties": {
    "iso:country":"US",
    "sg:address":"2511 Tower Dr",
    "sg:city":"Dover",
    "sg:classifiers":[
        {
            "category":"Professional",
            "type":"Services"
        }
    ],
    "sg:phone":"+1   ",
    "sg:postcode":"17315",
    "sg:province":"PA",
    "wof:name":"Brownstone Manor",
    "wof:placetype":"venue"
},
  "geometry": {"coordinates":[-76.839123,39.984642],"type":"Point"}
}