{
  "type": "Feature",
  "properties": {
    "iso:country":"US",
    "sg:address":"1872 Bethlehem Pike",
    "sg:city":"Flourtown",
    "sg:classifiers":[
        {
            "category":"Shopping",
            "type":"Retail Goods"
        }
    ],
    "sg:phone":"+1 215 233 2445",
    "sg:postcode":"19031",
    "sg:province":"PA",
    "sg:tags":[
        "telephone",
        "cellular"
    ],
    "wof:name":"Radio Shack",
    "wof:placetype":"venue"
},
  "geometry": {"coordinates":[-75.213808,40.109304],"type":"Point"}
}