{
  "type": "Feature",
  "properties": {
    "iso:country":"US",
    "sg:address":"516 W Broad St",
    "sg:city":"Bethlehem",
    "sg:classifiers":[
        {
            "category":"Restaurant",
            "type":"Food & Drink"
        }
    ],
    "sg:phone":"+1 610 882 1106",
    "sg:postcode":"18018",
    "sg:province":"PA",
    "sg:tags":[
        "eating"
    ],
    "wof:name":"Italia Mia",
    "wof:placetype":"venue"
},
  "geometry": {"coordinates":[-75.390845,40.622565],"type":"Point"}
}