{
  "type": "Feature",
  "properties": {
    "iso:country":"US",
    "sg:address":"160 E 9th Ave",
    "sg:city":"York",
    "sg:classifiers":[
        {
            "category":"Restaurant",
            "type":"Food & Drink"
        }
    ],
    "sg:phone":"+1 717 246 6300",
    "sg:postcode":"17404",
    "sg:province":"PA",
    "sg:tags":[
        "caterer"
    ],
    "wof:name":"Gingerbabies Catering",
    "wof:placetype":"venue"
},
  "geometry": {"coordinates":[-76.731921,39.980534],"type":"Point"}
}