{
  "type": "Feature",
  "properties": {
    "addr:full":"316 Meadow Ave Scranton PA 18505",
    "addr:housenumber":"316",
    "addr:postcode":"18505",
    "addr:street":"Meadow Ave",
    "iso:country":"US",
    "sg:address":"316 Meadow Ave",
    "sg:city":"Scranton",
    "sg:classifiers":[
        {
            "category":"Personal",
            "subcategory":"Beauty Salon",
            "type":"Services"
        }
    ],
    "sg:phone":"+1   ",
    "sg:postcode":"18505",
    "sg:province":"PA",
    "sg:tags":[
        "shop"
    ],
    "wof:name":"New Owner",
    "wof:placetype":"venue"
},
  "geometry": {"coordinates":[-75.651597,41.395219],"type":"Point"}
}