{
  "type": "Feature",
  "properties": {
    "iso:country":"US",
    "sg:address":"50 3rd Ave Ste 220",
    "sg:city":"Collegeville",
    "sg:classifiers":[
        {
            "category":"Restaurant",
            "type":"Food & Drink"
        }
    ],
    "sg:phone":"+1 610 489 7022",
    "sg:postcode":"19426",
    "sg:province":"PA",
    "sg:tags":[
        "sushi",
        "bar",
        "japanese"
    ],
    "sg:website":"www.bonjungsushi.com",
    "wof:name":"Bonjung Japanese Restaurant",
    "wof:placetype":"venue"
},
  "geometry": {"coordinates":[-75.45272799999999,40.185791],"type":"Point"}
}