{
  "type": "Feature",
  "properties": {
    "addr:full":"3758 L St Philadelphia PA 19124",
    "addr:housenumber":"3758",
    "addr:postcode":"19124",
    "addr:street":"L St",
    "iso:country":"US",
    "sg:address":"3758 L St",
    "sg:city":"Philadelphia",
    "sg:classifiers":[
        {
            "category":"Food & Beverages",
            "subcategory":"Groceries & Convenience Stores",
            "type":"Retail Goods"
        }
    ],
    "sg:phone":"+1   ",
    "sg:postcode":"19124",
    "sg:province":"PA",
    "wof:name":"Save-A-Lot",
    "wof:placetype":"venue"
},
  "geometry": {"coordinates":[-75.103702,40.00391],"type":"Point"}
}