{
  "type": "Feature",
  "properties": {
    "addr:full":"701 Coates St Sharon Hill PA 19079",
    "addr:housenumber":"701",
    "addr:postcode":"19079",
    "addr:street":"Coates St",
    "iso:country":"US",
    "sg:address":"701 Coates St",
    "sg:city":"Sharon Hill",
    "sg:classifiers":[
        {
            "category":"Education",
            "subcategory":"School",
            "type":"Public Place"
        }
    ],
    "sg:phone":"+1 610 522 4355",
    "sg:postcode":"19079",
    "sg:province":"PA",
    "wof:name":"Sharon Hill Elementary School",
    "wof:placetype":"venue"
},
  "geometry": {"coordinates":[-75.269729,39.909219],"type":"Point"}
}