{
  "type": "Feature",
  "properties": {
    "iso:country":"US",
    "sg:address":"5222 York Rd",
    "sg:city":"Holicong",
    "sg:classifiers":[
        {
            "category":"Building & Trades",
            "subcategory":"Construction",
            "type":"Services"
        },
        {
            "category":"Home & Garden",
            "subcategory":"Furniture",
            "type":"Retail Goods"
        }
    ],
    "sg:phone":"+1 215 794 1814",
    "sg:postcode":"18928",
    "sg:province":"PA",
    "sg:tags":[
        "interior",
        "design",
        "store"
    ],
    "wof:name":"European Home Collection",
    "wof:placetype":"venue"
},
  "geometry": {"coordinates":[-75.045799,40.3391],"type":"Point"}
}