{
  "type": "Feature",
  "properties": {
    "addr:full":"1221 W 11th St Erie PA 16502",
    "addr:housenumber":"1221",
    "addr:postcode":"16502",
    "addr:street":"W 11Th St",
    "iso:country":"US",
    "sg:address":"1221 W 11th St",
    "sg:city":"Erie",
    "sg:classifiers":[
        {
            "category":"Retail",
            "subcategory":"Repair Shop",
            "type":"Services"
        }
    ],
    "sg:phone":"+1 814 456 7127",
    "sg:postcode":"16502",
    "sg:province":"PA",
    "sg:tags":[
        "electric",
        "motor"
    ],
    "wof:name":"Lyons Electric",
    "wof:placetype":"venue"
},
  "geometry": {"coordinates":[-80.109424,42.114348],"type":"Point"}
}