{
  "type": "Feature",
  "properties": {
    "iso:country":"US",
    "sg:address":"2134 Federal St",
    "sg:city":"Philadelphia",
    "sg:classifiers":[
        {
            "category":"Wholesale",
            "subcategory":"Hardware",
            "type":"Manufacturing & Wholesale Goods"
        }
    ],
    "sg:phone":"+1 215 334 2281",
    "sg:postcode":"19146",
    "sg:province":"PA",
    "sg:tags":[
        "hardware-wholesale",
        "manufacturer"
    ],
    "wof:name":"Det Headquarters Brady",
    "wof:placetype":"venue"
},
  "geometry": {"coordinates":[-75.179137,39.937663],"type":"Point"}
}