{
  "type": "Feature",
  "properties": {
    "iso:country":"US",
    "sg:address":"3134 Little Rd",
    "sg:city":"Perkiomenville",
    "sg:classifiers":[
        {
            "category":"Building & Trades",
            "subcategory":"Construction",
            "type":"Services"
        }
    ],
    "sg:phone":"+1   ",
    "sg:postcode":"18074",
    "sg:province":"PA",
    "sg:tags":[
        "excavation",
        "contractor"
    ],
    "wof:name":"R & K Excavating",
    "wof:placetype":"venue"
},
  "geometry": {"coordinates":[-75.500849,40.299641],"type":"Point"}
}