{
  "type": "Feature",
  "properties": {
    "iso:country":"US",
    "sg:address":"Reading Terminal Market 51 N 12th St",
    "sg:city":"Philadelphia",
    "sg:classifiers":[
        {
            "category":"Restaurant",
            "type":"Food & Drink"
        }
    ],
    "sg:phone":"+1 215 829 9391",
    "sg:postcode":"19107",
    "sg:province":"PA",
    "sg:tags":[
        "pizza"
    ],
    "sg:website":"www.readingterminalmarket.org/me...",
    "wof:name":"By George! Pizza, Pasta & Cheesesteaks",
    "wof:placetype":"venue"
},
  "geometry": {"coordinates":[-75.159589,39.953109],"type":"Point"}
}