{
  "type": "Feature",
  "properties": {
    "addr:full":"150 Greensburg St Delmont PA 15626",
    "addr:housenumber":"150",
    "addr:postcode":"15626",
    "addr:street":"Greensburg St",
    "iso:country":"US",
    "sg:address":"150 Greensburg St",
    "sg:city":"Delmont",
    "sg:classifiers":[
        {
            "category":"Shopping",
            "subcategory":"Used Merchandise",
            "type":"Retail Goods"
        }
    ],
    "sg:phone":"+1 724 468 8744",
    "sg:postcode":"15626",
    "sg:province":"PA",
    "wof:name":"Attic Antiques",
    "wof:placetype":"venue"
},
  "geometry": {"coordinates":[-79.572475,40.410308],"type":"Point"}
}