{
  "type": "Feature",
  "properties": {
    "addr:full":"1369 Amosite Rd Bainbridge PA 17502",
    "addr:housenumber":"1369",
    "addr:postcode":"17502",
    "addr:street":"Amosite Rd",
    "iso:country":"US",
    "sg:address":"1369 Amosite Rd",
    "sg:city":"Bainbridge",
    "sg:classifiers":[
        {
            "category":"Building & Trades",
            "subcategory":"Construction",
            "type":"Services"
        }
    ],
    "sg:phone":"+1   ",
    "sg:postcode":"17502",
    "sg:province":"PA",
    "sg:tags":[
        "a",
        "as",
        "general",
        "operates",
        "contractor"
    ],
    "wof:name":"F L Shank Construction",
    "wof:placetype":"venue"
},
  "geometry": {"coordinates":[-76.67849699999999,40.116358],"type":"Point"}
}