{
  "type": "Feature",
  "properties": {
    "iso:country":"US",
    "sg:address":"7200 Grand Ave",
    "sg:city":"Pittsburgh",
    "sg:classifiers":[
        {
            "category":"Real Estate",
            "subcategory":"Real Estate Agent",
            "type":"Services"
        }
    ],
    "sg:phone":"+1 412 424 0393",
    "sg:postcode":"15225",
    "sg:province":"PA",
    "wof:name":"Lounder Real Estate",
    "wof:placetype":"venue"
},
  "geometry": {"coordinates":[-80.14689,40.516718],"type":"Point"}
}