{
  "type": "Feature",
  "properties": {
    "iso:country":"US",
    "sg:address":"3017 W York St",
    "sg:city":"Philadelphia",
    "sg:classifiers":[
        {
            "category":"Organizations",
            "subcategory":"Religious Organization",
            "type":"Services"
        }
    ],
    "sg:phone":"+1 215 225 0407",
    "sg:postcode":"19132",
    "sg:province":"PA",
    "sg:tags":[
        "church"
    ],
    "wof:name":"Sanctuary Baptist Church",
    "wof:placetype":"venue"
},
  "geometry": {"coordinates":[-75.182209,39.992813],"type":"Point"}
}