{
  "type": "Feature",
  "properties": {
    "addr:full":"4643 Baum Blvd Pittsburgh PA 15213",
    "addr:housenumber":"4643",
    "addr:postcode":"15213",
    "addr:street":"Baum Blvd",
    "iso:country":"US",
    "sg:address":"4643 Baum Blvd",
    "sg:city":"Pittsburgh",
    "sg:classifiers":[
        {
            "category":"Restaurant",
            "type":"Food & Drink"
        }
    ],
    "sg:phone":"+1 412 682 7272",
    "sg:postcode":"15213",
    "sg:province":"PA",
    "wof:name":"Papa John's Pizza",
    "wof:placetype":"venue"
},
  "geometry": {"coordinates":[-79.952147,40.454101],"type":"Point"}
}