{
  "type": "Feature",
  "properties": {
    "iso:country":"US",
    "sg:address":"119 N 2nd St",
    "sg:city":"Jeannette",
    "sg:classifiers":[
        {
            "category":"Organizations",
            "subcategory":"Religious Organization",
            "type":"Services"
        }
    ],
    "sg:phone":"+1 724 523 3290",
    "sg:postcode":"15644",
    "sg:province":"PA",
    "sg:tags":[
        "testament",
        "churches-church",
        "christ-new"
    ],
    "wof:name":"Grace United Church Of Christ Inc",
    "wof:placetype":"venue"
},
  "geometry": {"coordinates":[-79.61404400000001,40.328126],"type":"Point"}
}