{
  "type": "Feature",
  "properties": {
    "iso:country":"US",
    "sg:address":"406 Blair Mill Rd",
    "sg:city":"Hatboro",
    "sg:classifiers":[
        {
            "category":"Building & Trades",
            "subcategory":"Electrical",
            "type":"Services"
        }
    ],
    "sg:phone":"+1   ",
    "sg:postcode":"19040",
    "sg:province":"PA",
    "sg:tags":[
        "electrical",
        "contractor"
    ],
    "wof:name":"Heinz Electric Inc",
    "wof:placetype":"venue"
},
  "geometry": {"coordinates":[-75.12441699999999,40.174947],"type":"Point"}
}