{
  "type": "Feature",
  "properties": {
    "iso:country":"US",
    "sg:address":"2900 W Hunting Park Ave",
    "sg:city":"Philadelphia",
    "sg:classifiers":[
        {
            "category":"Education",
            "subcategory":"School",
            "type":"Public Place"
        }
    ],
    "sg:phone":"+1 215 226 1225",
    "sg:postcode":"19129",
    "sg:province":"PA",
    "sg:tags":[
        "high",
        "middle",
        "elementary"
    ],
    "wof:name":"Mercy Vocational High School",
    "wof:placetype":"venue"
},
  "geometry": {"coordinates":[-75.175499,40.006699],"type":"Point"}
}