{
  "type": "Feature",
  "properties": {
    "addr:full":"225 State Rte 288 Ellwood City PA 16117",
    "addr:housenumber":"225",
    "addr:postcode":"16117",
    "addr:street":"State Rte 288 Ellwood",
    "iso:country":"US",
    "sg:address":"225 State Rte 288",
    "sg:city":"Ellwood City",
    "sg:classifiers":[
        {
            "category":"Personal",
            "subcategory":"Beauty Salon",
            "type":"Services"
        }
    ],
    "sg:phone":"+1 724 758 5499",
    "sg:postcode":"16117",
    "sg:province":"PA",
    "sg:tags":[
        "shop"
    ],
    "wof:name":"Famous Hair",
    "wof:placetype":"venue"
},
  "geometry": {"coordinates":[-80.270611,40.846913],"type":"Point"}
}