{
  "type": "Feature",
  "properties": {
    "iso:country":"US",
    "sg:address":"800 Randolph St",
    "sg:city":"Hanover",
    "sg:classifiers":[
        {
            "category":"Organizations",
            "subcategory":"Non-profit Organization",
            "type":"Services"
        },
        {
            "category":"Social Services",
            "subcategory":"Adult Care",
            "type":"Services"
        }
    ],
    "sg:phone":"+1 717 632 8081",
    "sg:postcode":"17331",
    "sg:province":"PA",
    "sg:tags":[
        "building",
        "residential",
        "apartment",
        "operator"
    ],
    "wof:name":"Clearview Terrace Apartments",
    "wof:placetype":"venue"
},
  "geometry": {"coordinates":[-76.99479100000001,39.813261],"type":"Point"}
}