{
  "type": "Feature",
  "properties": {
    "iso:country":"US",
    "sg:address":"1422 Chestnut St",
    "sg:city":"Philadelphia",
    "sg:classifiers":[
        {
            "category":"Professional",
            "subcategory":"Computer Services",
            "type":"Services"
        }
    ],
    "sg:phone":"+1 215 567 2299",
    "sg:postcode":"19102",
    "sg:province":"PA",
    "sg:tags":[
        "internet"
    ],
    "wof:name":"Internet Behavioral Care",
    "wof:placetype":"venue"
},
  "geometry": {"coordinates":[-75.165346,39.950952],"type":"Point"}
}