{
  "type": "Feature",
  "properties": {
    "iso:country":"US",
    "sg:address":"616 N Lime St",
    "sg:city":"Lancaster",
    "sg:classifiers":[
        {
            "category":"Personal",
            "subcategory":"Beauty Salon",
            "type":"Services"
        }
    ],
    "sg:phone":"+1   ",
    "sg:postcode":"17602",
    "sg:province":"PA",
    "sg:tags":[
        "shop"
    ],
    "wof:name":"Hair Salon & Day Spa",
    "wof:placetype":"venue"
},
  "geometry": {"coordinates":[-76.303498,40.049104],"type":"Point"}
}