{
  "type": "Feature",
  "properties": {
    "iso:country":"US",
    "sg:address":"300 W Lancaster Ave",
    "sg:city":"Devon",
    "sg:phone":"+1 610 341 8162",
    "sg:postcode":"19333",
    "sg:province":"PA",
    "wof:name":"Mayuree Cafe",
    "wof:placetype":"venue"
},
  "geometry": {"coordinates":[-75.42678100000001,40.044529],"type":"Point"}
}