{
  "type": "Feature",
  "properties": {
    "addr:full":"1251 Highland St Harrisburg PA 17113",
    "addr:housenumber":"1251",
    "addr:postcode":"17113",
    "addr:street":"Highland St",
    "iso:country":"US",
    "sg:address":"1251 Highland St",
    "sg:city":"Harrisburg",
    "sg:classifiers":[
        {
            "category":"Organizations",
            "subcategory":"Religious Organization",
            "type":"Services"
        }
    ],
    "sg:phone":"+1 717 939 6921",
    "sg:postcode":"17113",
    "sg:province":"PA",
    "sg:tags":[
        "church"
    ],
    "wof:name":"Neidig Memorial United Meth",
    "wof:placetype":"venue"
},
  "geometry": {"coordinates":[-76.81369599999999,40.238737],"type":"Point"}
}