{
  "type": "Feature",
  "properties": {
    "addr:full":"7852 Montgomery Ave Elkins Park PA 19027",
    "addr:housenumber":"7852",
    "addr:postcode":"19027",
    "addr:street":"Montgomery Ave",
    "iso:country":"US",
    "sg:address":"7852 Montgomery Ave",
    "sg:city":"Elkins Park",
    "sg:classifiers":[
        {
            "category":"Retail",
            "subcategory":"Animal Services",
            "type":"Services"
        }
    ],
    "sg:phone":"+1 215 635 3647",
    "sg:postcode":"19027",
    "sg:province":"PA",
    "sg:tags":[
        "pet",
        "grooming",
        "washing"
    ],
    "wof:name":"Dogroom",
    "wof:placetype":"venue"
},
  "geometry": {"coordinates":[-75.12659499999999,40.07185],"type":"Point"}
}