{
  "type": "Feature",
  "properties": {
    "iso:country":"US",
    "sg:address":"320 Llewellyn Rd",
    "sg:city":"Chester Heights",
    "sg:classifiers":[
        {
            "category":"Education",
            "subcategory":"School",
            "type":"Public Place"
        }
    ],
    "sg:phone":"+1 610 459 2389",
    "sg:postcode":"19014",
    "sg:province":"PA",
    "wof:name":"Rosehill School",
    "wof:placetype":"venue"
},
  "geometry": {"coordinates":[-75.40378200000001,39.858498],"type":"Point"}
}