{
  "type": "Feature",
  "properties": {
    "iso:country":"US",
    "sg:address":"406 Crabtree Dr",
    "sg:city":"Levittown",
    "sg:classifiers":[
        {
            "category":"Health Services",
            "subcategory":"Podiatrist",
            "type":"Services"
        }
    ],
    "sg:phone":"+1   ",
    "sg:postcode":"19055",
    "sg:province":"PA",
    "wof:name":"Gennaria Charles R",
    "wof:placetype":"venue"
},
  "geometry": {"coordinates":[-74.83310899999999,40.161344],"type":"Point"}
}