{
  "type": "Feature",
  "properties": {
    "iso:country":"US",
    "sg:address":"303 Leedom St",
    "sg:city":"Jenkintown",
    "sg:classifiers":[
        {
            "category":"Shopping",
            "subcategory":"Stationery & Office Supplies",
            "type":"Retail Goods"
        }
    ],
    "sg:phone":"+1 215 886 4227",
    "sg:postcode":"19046",
    "sg:province":"PA",
    "sg:tags":[
        "personal",
        "commercial"
    ],
    "wof:name":"Party Please Inc",
    "wof:placetype":"venue"
},
  "geometry": {"coordinates":[-75.127077,40.096069],"type":"Point"}
}