{
  "type": "Feature",
  "properties": {
    "addr:full":"3020 E Market St York PA 17402",
    "addr:housenumber":"3020",
    "addr:postcode":"17402",
    "addr:street":"E Market St",
    "iso:country":"US",
    "sg:address":"3020 E Market St",
    "sg:city":"York",
    "sg:classifiers":[
        {
            "category":"Ice Cream",
            "type":"Food & Drink"
        }
    ],
    "sg:menulink":"http://www.allmenus.com/pa/springettsbury/175952-dairy-queen/menu/",
    "sg:phone":"+1 717 757 2221",
    "sg:postcode":"17402",
    "sg:province":"PA",
    "sg:tags":[
        "burger",
        "american"
    ],
    "wof:name":"Dairy Queen",
    "wof:placetype":"venue"
},
  "geometry": {"coordinates":[-76.66708,39.976735],"type":"Point"}
}