{
  "type": "Feature",
  "properties": {
    "iso:country":"US",
    "sg:address":"2152 Old Rte 220 N",
    "sg:city":"Duncansville",
    "sg:classifiers":[
        {
            "category":"Home & Garden",
            "subcategory":"Mobile Homes",
            "type":"Retail Goods"
        }
    ],
    "sg:phone":"+1   ",
    "sg:postcode":"16635",
    "sg:province":"PA",
    "wof:name":"Shaw Mobile Homes",
    "wof:placetype":"venue"
},
  "geometry": {"coordinates":[-78.409053,40.44945],"type":"Point"}
}