{
  "type": "Feature",
  "properties": {
    "iso:country":"US",
    "sg:address":"1003 5th Ave",
    "sg:city":"Patton",
    "sg:classifiers":[
        {
            "category":"Building & Trades",
            "subcategory":"Plumbing",
            "type":"Services"
        }
    ],
    "sg:phone":"+1 814 674 5400",
    "sg:postcode":"16668",
    "sg:province":"PA",
    "sg:tags":[
        "plumbing",
        "contractor"
    ],
    "wof:name":"Yeager Alan Jr Plumbing & Htg",
    "wof:placetype":"venue"
},
  "geometry": {"coordinates":[-78.650156,40.636521],"type":"Point"}
}