{
  "type": "Feature",
  "properties": {
    "addr:full":"218 N 13th St Philadelphia PA 19107",
    "addr:housenumber":"218",
    "addr:postcode":"19107",
    "addr:street":"N 13Th St",
    "iso:country":"US",
    "sg:address":"218 N 13th St",
    "sg:city":"Philadelphia",
    "sg:classifiers":[
        {
            "category":"Professional",
            "subcategory":"Art Services",
            "type":"Services"
        }
    ],
    "sg:phone":"+1 215 963 0279",
    "sg:postcode":"19107",
    "sg:province":"PA",
    "sg:tags":[
        "graphic",
        "designer"
    ],
    "sg:website":"www.atg13.com",
    "wof:name":"Advanced Typography & Graphics",
    "wof:placetype":"venue"
},
  "geometry": {"coordinates":[-75.160551,39.956548],"type":"Point"}
}