{
  "type": "Feature",
  "properties": {
    "iso:country":"US",
    "sg:address":"501 E Orange St",
    "sg:city":"Lancaster",
    "sg:classifiers":[
        {
            "category":"Organizations",
            "subcategory":"Religious Organization",
            "type":"Services"
        }
    ],
    "sg:phone":"+1 717 394 0669",
    "sg:postcode":"17602",
    "sg:province":"PA",
    "sg:tags":[
        "church"
    ],
    "wof:name":"Redemptorist Fathers",
    "wof:placetype":"venue"
},
  "geometry": {"coordinates":[-76.29350100000001,40.04083],"type":"Point"}
}