{
  "type": "Feature",
  "properties": {
    "iso:country":"US",
    "sg:address":"503 Gilpin Rd",
    "sg:city":"Willow Grove",
    "sg:classifiers":[
        {
            "category":"Manufacturing",
            "subcategory":"Printing",
            "type":"Manufacturing & Wholesale Goods"
        }
    ],
    "sg:phone":"+1 215 872 8004",
    "sg:postcode":"19090",
    "sg:province":"PA",
    "sg:tags":[
        "multimedia"
    ],
    "sg:website":"www.wdesignhouse.com",
    "wof:name":"W Designhouse Inc",
    "wof:placetype":"venue"
},
  "geometry": {"coordinates":[-75.120097,40.152918],"type":"Point"}
}