{
  "type": "Feature",
  "properties": {
    "iso:country":"US",
    "sg:address":"213 W 8th Ave",
    "sg:city":"Homestead",
    "sg:classifiers":[
        {
            "category":"Restaurant",
            "type":"Food & Drink"
        }
    ],
    "sg:phone":"+1 412 464 1477",
    "sg:postcode":"15120",
    "sg:province":"PA",
    "sg:tags":[
        "out"
    ],
    "wof:name":"Me Lyng Restaurant",
    "wof:placetype":"venue"
},
  "geometry": {"coordinates":[-79.915199,40.404029],"type":"Point"}
}