{
  "type": "Feature",
  "properties": {
    "addr:full":"9713 Glenhope Rd Philadelphia PA 19115",
    "addr:housenumber":"9713",
    "addr:postcode":"19115",
    "addr:street":"Glenhope Rd",
    "iso:country":"US",
    "sg:address":"9713 Glenhope Rd",
    "sg:city":"Philadelphia",
    "sg:classifiers":[
        {
            "category":"Building & Trades",
            "subcategory":"Plumbing",
            "type":"Services"
        }
    ],
    "sg:phone":"+1 215 673 4116",
    "sg:postcode":"19115",
    "sg:province":"PA",
    "sg:tags":[
        "contractor"
    ],
    "wof:name":"Rossi Plumbing & Heating",
    "wof:placetype":"venue"
},
  "geometry": {"coordinates":[-75.041218,40.093997],"type":"Point"}
}