{
  "type": "Feature",
  "properties": {
    "iso:country":"US",
    "sg:address":"8229 Germantown Ave",
    "sg:city":"Philadelphia",
    "sg:classifiers":[
        {
            "category":"Bars & Pubs",
            "type":"Food & Drink"
        },
        {
            "category":"Restaurant",
            "type":"Food & Drink"
        },
        {
            "category":"Food & Beverages",
            "subcategory":"Meat & Fish",
            "type":"Retail Goods"
        }
    ],
    "sg:phone":"+1 215 242 3003",
    "sg:postcode":"19118",
    "sg:province":"PA",
    "sg:tags":[
        "dessert",
        "fondue",
        "fine",
        "french",
        "dining"
    ],
    "sg:website":"http://www.meltingpot.com/",
    "wof:name":"The Melting Pot",
    "wof:placetype":"venue"
},
  "geometry": {"coordinates":[-75.203453,40.074211],"type":"Point"}
}