{
  "type": "Feature",
  "properties": {
    "iso:country":"US",
    "sg:address":"313 E Wister St",
    "sg:city":"Philadelphia",
    "sg:classifiers":[
        {
            "category":"Restaurant",
            "type":"Food & Drink"
        }
    ],
    "sg:phone":"+1   ",
    "sg:postcode":"19144",
    "sg:province":"PA",
    "sg:tags":[
        "eating"
    ],
    "wof:name":"Blue Water Coffee",
    "wof:placetype":"venue"
},
  "geometry": {"coordinates":[-75.16141500000001,40.033169],"type":"Point"}
}