{
  "type": "Feature",
  "properties": {
    "addr:full":"460 Chestnut Ridge Rd Penn Run PA 15765",
    "addr:housenumber":"460",
    "addr:postcode":"15765",
    "addr:street":"Chestnut Ridge Rd",
    "iso:country":"US",
    "sg:address":"460 Chestnut Ridge Rd",
    "sg:city":"Penn Run",
    "sg:classifiers":[
        {
            "category":"Building & Trades",
            "subcategory":"Electrical",
            "type":"Services"
        }
    ],
    "sg:phone":"+1 724 349 0908",
    "sg:postcode":"15765",
    "sg:province":"PA",
    "sg:tags":[
        "electric",
        "contractor"
    ],
    "wof:name":"Paragon Electric",
    "wof:placetype":"venue"
},
  "geometry": {"coordinates":[-79.0765,40.606497],"type":"Point"}
}