{
  "type": "Feature",
  "properties": {
    "addr:full":"1030 N 2nd St Philadelphia PA 19123",
    "addr:housenumber":"1030",
    "addr:postcode":"19123",
    "addr:street":"N 2Nd St",
    "iso:country":"US",
    "sg:address":"1030 N 2nd St",
    "sg:city":"Philadelphia",
    "sg:classifiers":[
        {
            "category":"Bars & Pubs",
            "type":"Food & Drink"
        },
        {
            "category":"Restaurant",
            "type":"Food & Drink"
        }
    ],
    "sg:phone":"+1 215 923 1313",
    "sg:postcode":"19123",
    "sg:province":"PA",
    "sg:tags":[
        "tapa",
        "spanish"
    ],
    "sg:website":"www.barferdinand.com",
    "wof:name":"Bar Ferdinand",
    "wof:placetype":"venue"
},
  "geometry": {"coordinates":[-75.140198,39.967098],"type":"Point"}
}