{
  "type": "Feature",
  "properties": {
    "iso:country":"US",
    "sg:address":"7810 Roosevelt Blvd",
    "sg:city":"Philadelphia",
    "sg:classifiers":[
        {
            "category":"Autos & Motor Vehicles",
            "subcategory":"Automobile Sales",
            "type":"Retail Goods"
        }
    ],
    "sg:phone":"+1   ",
    "sg:postcode":"19152",
    "sg:province":"PA",
    "sg:tags":[
        "new",
        "used"
    ],
    "wof:name":"Gary Barberas 1 Chryjeepland",
    "wof:placetype":"venue"
},
  "geometry": {"coordinates":[-75.04871300000001,40.055179],"type":"Point"}
}