{
  "type": "Feature",
  "properties": {
    "addr:full":"419 Oley Furnace Rd Oley PA 19547",
    "addr:housenumber":"419",
    "addr:postcode":"19547",
    "addr:street":"Oley Furnace Rd",
    "iso:country":"US",
    "sg:address":"419 Oley Furnace Rd",
    "sg:city":"Oley",
    "sg:classifiers":[
        {
            "category":"Building & Trades",
            "subcategory":"Construction",
            "type":"Services"
        }
    ],
    "sg:phone":"+1 610 987 0300",
    "sg:postcode":"19547",
    "sg:province":"PA",
    "sg:tags":[
        "house"
    ],
    "wof:name":"Barnhardt Construction",
    "wof:placetype":"venue"
},
  "geometry": {"coordinates":[-75.791775,40.407691],"type":"Point"}
}