{
  "type": "Feature",
  "properties": {
    "iso:country":"US",
    "sg:address":"411 W Conestoga Rd",
    "sg:city":"Devon",
    "sg:classifiers":[
        {
            "category":"Professional",
            "subcategory":"Advertising",
            "type":"Services"
        }
    ],
    "sg:phone":"+1   ",
    "sg:postcode":"19333",
    "sg:province":"PA",
    "wof:name":"L J Harmon",
    "wof:placetype":"venue"
},
  "geometry": {"coordinates":[-75.42982000000001,40.051225],"type":"Point"}
}