{
  "type": "Feature",
  "properties": {
    "iso:country":"US",
    "sg:address":"2433 Milwaukee Rd",
    "sg:city":"Clarks Summit",
    "sg:classifiers":[
        {
            "category":"Professional",
            "type":"Services"
        }
    ],
    "sg:phone":"+1   ",
    "sg:postcode":"18411",
    "sg:province":"PA",
    "wof:name":"Sunset Lighting",
    "wof:placetype":"venue"
},
  "geometry": {"coordinates":[-75.76928700000001,41.43615],"type":"Point"}
}