{
  "type": "Feature",
  "properties": {
    "iso:country":"US",
    "sg:address":"350 N Best Ave",
    "sg:city":"Walnutport",
    "sg:classifiers":[
        {
            "category":"Restaurant",
            "type":"Food & Drink"
        }
    ],
    "sg:phone":"+1 610 760 0777",
    "sg:postcode":"18088",
    "sg:province":"PA",
    "wof:name":"Subway Sandwiches & Salads",
    "wof:placetype":"venue"
},
  "geometry": {"coordinates":[-75.594545,40.761027],"type":"Point"}
}