{
  "type": "Feature",
  "properties": {
    "iso:country":"US",
    "sg:address":"170 Corporate Dr",
    "sg:city":"Reading",
    "sg:classifiers":[
        {
            "category":"Shopping",
            "subcategory":"Used Merchandise",
            "type":"Retail Goods"
        },
        {
            "category":"Restaurant",
            "type":"Food & Drink"
        }
    ],
    "sg:phone":"+1 610 926 8700",
    "sg:postcode":"19605",
    "sg:province":"PA",
    "sg:tags":[
        "eating",
        "furniture"
    ],
    "wof:name":"Furniture Soup Inc",
    "wof:placetype":"venue"
},
  "geometry": {"coordinates":[-75.940954,40.406532],"type":"Point"}
}