{
  "type": "Feature",
  "properties": {
    "addr:full":"1213 Kittanning Pike Chicora PA 16025",
    "addr:housenumber":"1213",
    "addr:postcode":"16025",
    "addr:street":"Kittanning Pike",
    "iso:country":"US",
    "sg:address":"1213 Kittanning Pike",
    "sg:city":"Chicora",
    "sg:classifiers":[
        {
            "category":"Recreation",
            "type":"Entertainment"
        }
    ],
    "sg:phone":"+1 724 445 3784",
    "sg:postcode":"16025",
    "sg:province":"PA",
    "sg:tags":[
        "course",
        "golf"
    ],
    "wof:name":"St Jude Golf Club",
    "wof:placetype":"venue"
},
  "geometry": {"coordinates":[-79.71357,40.970621],"type":"Point"}
}