{
  "type": "Feature",
  "properties": {
    "iso:country":"US",
    "sg:address":"225 Meeting House Ln",
    "sg:city":"Merion Station",
    "sg:classifiers":[
        {
            "category":"Health Services",
            "subcategory":"Doctor",
            "type":"Services"
        }
    ],
    "sg:phone":"+1 610 667 3883",
    "sg:postcode":"19066",
    "sg:province":"PA",
    "wof:name":"Kefalides Nicholas A MD",
    "wof:placetype":"venue"
},
  "geometry": {"coordinates":[-75.244698,40.012001],"type":"Point"}
}