{
  "type": "Feature",
  "properties": {
    "addr:full":"417 S 16th St Harrisburg PA 17104",
    "addr:housenumber":"417",
    "addr:postcode":"17104",
    "addr:street":"S 16Th St",
    "iso:country":"US",
    "sg:address":"417 S 16th St",
    "sg:city":"Harrisburg",
    "sg:classifiers":[
        {
            "category":"Building & Trades",
            "subcategory":"Cleaning & Sanitation",
            "type":"Services"
        }
    ],
    "sg:phone":"+1 717 713 1656",
    "sg:postcode":"17104",
    "sg:province":"PA",
    "sg:tags":[
        "window",
        "washing"
    ],
    "sg:website":"myradiantwindows.com",
    "wof:name":"Radiant Windows",
    "wof:placetype":"venue"
},
  "geometry": {"coordinates":[-76.86312700000001,40.260878],"type":"Point"}
}