{
  "type": "Feature",
  "properties": {
    "addr:full":"233 W Newton Rd Herminie PA 15637",
    "addr:housenumber":"233",
    "addr:postcode":"15637",
    "addr:street":"W Newton Rd",
    "iso:country":"US",
    "sg:address":"233 W Newton Rd",
    "sg:city":"Herminie",
    "sg:classifiers":[
        {
            "category":"Manufacturing",
            "subcategory":"Tools & Machinery",
            "type":"Manufacturing & Wholesale Goods"
        }
    ],
    "sg:phone":"+1   ",
    "sg:postcode":"15637",
    "sg:province":"PA",
    "sg:tags":[
        "industrial",
        "mfg"
    ],
    "wof:name":"Essay Precision Machining",
    "wof:placetype":"venue"
},
  "geometry": {"coordinates":[-79.72238400000001,40.254612],"type":"Point"}
}