{
  "type": "Feature",
  "properties": {
    "iso:country":"US",
    "sg:address":"408 Crescent Park",
    "sg:city":"Warren",
    "sg:classifiers":[
        {
            "category":"Shopping",
            "subcategory":"Music",
            "type":"Retail Goods"
        }
    ],
    "sg:phone":"+1   ",
    "sg:postcode":"16365",
    "sg:province":"PA",
    "wof:name":"Valspar Corp",
    "wof:placetype":"venue"
},
  "geometry": {"coordinates":[-79.149061,41.84224],"type":"Point"}
}