{
  "type": "Feature",
  "properties": {
    "iso:country":"US",
    "sg:address":"1904 E Lake Rd",
    "sg:city":"Erie",
    "sg:classifiers":[
        {
            "category":"Food & Beverages",
            "subcategory":"Groceries & Convenience Stores",
            "type":"Retail Goods"
        }
    ],
    "sg:phone":"+1 814 455 0138",
    "sg:postcode":"16511",
    "sg:province":"PA",
    "wof:name":"Country Fair 33",
    "wof:placetype":"venue"
},
  "geometry": {"coordinates":[-80.042309,42.145734],"type":"Point"}
}