{
  "type": "Feature",
  "properties": {
    "iso:country":"US",
    "sg:address":"60 Harvest Dr",
    "sg:city":"Gettysburg",
    "sg:classifiers":[
        {
            "category":"Building & Trades",
            "subcategory":"Electrical",
            "type":"Services"
        }
    ],
    "sg:phone":"+1 717 337 2012",
    "sg:postcode":"17325",
    "sg:province":"PA",
    "sg:tags":[
        "industrial",
        "electrician",
        "contractors-commercial",
        "electric"
    ],
    "wof:name":"Bag Shot Row Enterprises",
    "wof:placetype":"venue"
},
  "geometry": {"coordinates":[-77.14880100000001,39.81235],"type":"Point"}
}