{
  "type": "Feature",
  "properties": {
    "iso:country":"US",
    "sg:address":"843 Exeter Ave",
    "sg:city":"Exeter",
    "sg:classifiers":[
        {
            "category":"Wholesale",
            "subcategory":"Construction Materials",
            "type":"Manufacturing & Wholesale Goods"
        },
        {
            "category":"Building & Trades",
            "subcategory":"Construction",
            "type":"Services"
        }
    ],
    "sg:phone":"+1 570 602 0432",
    "sg:postcode":"18643",
    "sg:province":"PA",
    "sg:tags":[
        "fencing",
        "fence",
        "contractor"
    ],
    "wof:name":"Action Fence",
    "wof:placetype":"venue"
},
  "geometry": {"coordinates":[-75.80228700000001,41.336453],"type":"Point"}
}