{
  "type": "Feature",
  "properties": {
    "iso:country":"US",
    "sg:address":"1502 W 26th St",
    "sg:city":"Erie",
    "sg:classifiers":[
        {
            "category":"Banks & Credit Unions",
            "subcategory":"Bank",
            "type":"Services"
        }
    ],
    "sg:phone":"+1   ",
    "sg:postcode":"16508",
    "sg:province":"PA",
    "sg:tags":[
        "national"
    ],
    "wof:name":"Charter One Bank NA",
    "wof:placetype":"venue"
},
  "geometry": {"coordinates":[-80.104799,42.100478],"type":"Point"}
}