{
  "type": "Feature",
  "properties": {
    "iso:country":"US",
    "sg:address":"813 Addingham Ave",
    "sg:city":"Drexel Hill",
    "sg:classifiers":[
        {
            "category":"Manufacturing",
            "subcategory":"Printing",
            "type":"Manufacturing & Wholesale Goods"
        }
    ],
    "sg:phone":"+1   ",
    "sg:postcode":"19026",
    "sg:province":"PA",
    "sg:tags":[
        "commercial"
    ],
    "wof:name":"Jebco Printing Center",
    "wof:placetype":"venue"
},
  "geometry": {"coordinates":[-75.31707400000001,39.950006],"type":"Point"}
}