{
  "type": "Feature",
  "properties": {
    "iso:country":"US",
    "sg:address":"13605 Summit Ave",
    "sg:city":"Blue Ridge Summit",
    "sg:classifiers":[
        {
            "category":"Personal",
            "subcategory":"Barber",
            "type":"Services"
        }
    ],
    "sg:phone":"+1   ",
    "sg:postcode":"17214",
    "sg:province":"PA",
    "sg:tags":[
        "shop",
        "beauty"
    ],
    "wof:name":"Summit Hair Studio",
    "wof:placetype":"venue"
},
  "geometry": {"coordinates":[-77.47052499999999,39.721463],"type":"Point"}
}