{
  "type": "Feature",
  "properties": {
    "iso:country":"US",
    "sg:address":"1112 Oakland Ave",
    "sg:city":"Indiana",
    "sg:classifiers":[
        {
            "category":"Social Services",
            "type":"Services"
        }
    ],
    "sg:phone":"+1 724 349 5307",
    "sg:postcode":"15701",
    "sg:province":"PA",
    "wof:name":"Life-Way Pregnancy Clinic",
    "wof:placetype":"venue"
},
  "geometry": {"coordinates":[-79.16119500000001,40.618226],"type":"Point"}
}