{
  "type": "Feature",
  "properties": {
    "iso:country":"US",
    "sg:address":"2133 Arch St",
    "sg:city":"Philadelphia",
    "sg:classifiers":[
        {
            "category":"Professional",
            "subcategory":"Accounting & Tax Preparation",
            "type":"Services"
        }
    ],
    "sg:phone":"+1 215 765 4600",
    "sg:postcode":"19103",
    "sg:province":"PA",
    "sg:tags":[
        "accountant"
    ],
    "wof:name":"Weisbrot Richd G",
    "wof:placetype":"venue"
},
  "geometry": {"coordinates":[-75.175797,39.956001],"type":"Point"}
}