{
  "type": "Feature",
  "properties": {
    "addr:full":"2412 Spruce Rd Cherry Tree PA 15724",
    "addr:housenumber":"2412",
    "addr:postcode":"15724",
    "addr:street":"Spruce Rd",
    "iso:country":"US",
    "sg:address":"2412 Spruce Rd",
    "sg:city":"Cherry Tree",
    "sg:classifiers":[
        {
            "category":"Travel",
            "subcategory":"Travel Agent",
            "type":"Entertainment"
        }
    ],
    "sg:phone":"+1 814 948 7910",
    "sg:postcode":"15724",
    "sg:province":"PA",
    "sg:tags":[
        "agency"
    ],
    "wof:name":"Repine Travel",
    "wof:placetype":"venue"
},
  "geometry": {"coordinates":[-78.86587,40.673456],"type":"Point"}
}