{
  "type": "Feature",
  "properties": {
    "addr:full":"382 Osceola Ave Kingston PA 18704",
    "addr:housenumber":"382",
    "addr:postcode":"18704",
    "addr:street":"Osceola Ave",
    "iso:country":"US",
    "sg:address":"382 Osceola Ave",
    "sg:city":"Kingston",
    "sg:classifiers":[
        {
            "category":"Home & Garden",
            "subcategory":"Carpets & Floor Coverings",
            "type":"Retail Goods"
        }
    ],
    "sg:phone":"+1 570 287 6515",
    "sg:postcode":"18704",
    "sg:province":"PA",
    "wof:name":"Leader Floor Co",
    "wof:placetype":"venue"
},
  "geometry": {"coordinates":[-75.89028999999999,41.262106],"type":"Point"}
}