{
  "type": "Feature",
  "properties": {
    "iso:country":"US",
    "sg:address":"258 W Market St",
    "sg:city":"York",
    "sg:classifiers":[
        {
            "category":"Professional",
            "type":"Services"
        }
    ],
    "sg:phone":"+1 717 849 5250",
    "sg:postcode":"17401",
    "sg:province":"PA",
    "sg:tags":[
        "establishment"
    ],
    "wof:name":"Brenner John For Mayor",
    "wof:placetype":"venue"
},
  "geometry": {"coordinates":[-76.734517,39.960303],"type":"Point"}
}