{
  "type": "Feature",
  "properties": {
    "iso:country":"US",
    "sg:address":"218 E Calder Way",
    "sg:city":"State College",
    "sg:classifiers":[
        {
            "category":"Restaurant",
            "type":"Food & Drink"
        }
    ],
    "sg:menulink":"http://www.allmenus.com/pa/state-college/17622-the-pita-pit/menu/",
    "sg:phone":"+1 814 234 1228",
    "sg:postcode":"16801",
    "sg:province":"PA",
    "sg:tags":[
        "smoothy",
        "juice",
        "american",
        "sandwich",
        "salad"
    ],
    "wof:name":"The Pita Pit",
    "wof:placetype":"venue"
},
  "geometry": {"coordinates":[-77.859521,40.79528],"type":"Point"}
}