{
  "type": "Feature",
  "properties": {
    "iso:country":"US",
    "sg:address":"165 Crestvue Manor Dr",
    "sg:city":"Pittsburgh",
    "sg:classifiers":[
        {
            "category":"Real Estate",
            "subcategory":"Real Estate Agent",
            "type":"Services"
        }
    ],
    "sg:phone":"+1   ",
    "sg:postcode":"15228",
    "sg:province":"PA",
    "wof:name":"Vjv Properties",
    "wof:placetype":"venue"
},
  "geometry": {"coordinates":[-80.04676499999999,40.366918],"type":"Point"}
}