{
  "type": "Feature",
  "properties": {
    "iso:country":"US",
    "sg:address":"980 Bethlehem Pike",
    "sg:city":"Montgomeryville",
    "sg:classifiers":[
        {
            "category":"Shopping",
            "type":"Retail Goods"
        }
    ],
    "sg:phone":"+1   ",
    "sg:postcode":"18915",
    "sg:province":"PA",
    "sg:tags":[
        "merchandise",
        "furniture"
    ],
    "wof:name":"Babies R U S Baby Supersto",
    "wof:placetype":"venue"
},
  "geometry": {"coordinates":[-75.26211600000001,40.284235],"type":"Point"}
}