{
  "type": "Feature",
  "properties": {
    "addr:full":"839 W Market St York PA 17401",
    "addr:housenumber":"839",
    "addr:postcode":"17401",
    "addr:street":"W Market St",
    "iso:country":"US",
    "sg:address":"839 W Market St",
    "sg:city":"York",
    "sg:classifiers":[
        {
            "category":"Organizations",
            "subcategory":"Religious Organization",
            "type":"Services"
        }
    ],
    "sg:phone":"+1 717 845 2721",
    "sg:postcode":"17401",
    "sg:province":"PA",
    "sg:tags":[
        "church"
    ],
    "sg:website":"www.stmatt.org",
    "wof:name":"St Matthew Lutheran Church",
    "wof:placetype":"venue"
},
  "geometry": {"coordinates":[-76.74943,39.955852],"type":"Point"}
}