{
  "type": "Feature",
  "properties": {
    "iso:country":"US",
    "sg:address":"746 15th St",
    "sg:city":"Oakmont",
    "sg:classifiers":[
        {
            "category":"Manufacturing",
            "subcategory":"Tools & Machinery",
            "type":"Manufacturing & Wholesale Goods"
        }
    ],
    "sg:phone":"+1 412 828 6760",
    "sg:postcode":"15139",
    "sg:province":"PA",
    "sg:tags":[
        "testing",
        "apparatus"
    ],
    "wof:name":"Penn-Anderson Equipment Co",
    "wof:placetype":"venue"
},
  "geometry": {"coordinates":[-79.822722,40.521733],"type":"Point"}
}