{
  "type": "Feature",
  "properties": {
    "iso:country":"US",
    "sg:address":"2900 Veterans Hwy",
    "sg:city":"Bristol",
    "sg:classifiers":[
        {
            "category":"Communications",
            "subcategory":"Newspaper",
            "type":"Services"
        }
    ],
    "sg:phone":"+1 215 788 7315",
    "sg:postcode":"19007",
    "sg:province":"PA",
    "sg:tags":[
        "magazine"
    ],
    "wof:name":"Icn",
    "wof:placetype":"venue"
},
  "geometry": {"coordinates":[-74.881343,40.122076],"type":"Point"}
}