{
  "type": "Feature",
  "properties": {
    "addr:full":"2050 S Eagle Rd Newtown PA 18940",
    "addr:housenumber":"2050",
    "addr:postcode":"18940",
    "addr:street":"S Eagle Rd",
    "iso:country":"US",
    "sg:address":"2050 S Eagle Rd",
    "sg:city":"Newtown",
    "sg:classifiers":[
        {
            "category":"Restaurant",
            "type":"Food & Drink"
        }
    ],
    "sg:phone":"+1   ",
    "sg:postcode":"18940",
    "sg:province":"PA",
    "sg:tags":[
        "eating"
    ],
    "wof:name":"Pizza Hut",
    "wof:placetype":"venue"
},
  "geometry": {"coordinates":[-74.940594,40.22983],"type":"Point"}
}