{
  "type": "Feature",
  "properties": {
    "iso:country":"US",
    "sg:address":"1 S 8th St",
    "sg:city":"Philadelphia",
    "sg:classifiers":[
        {
            "category":"Manufacturing",
            "subcategory":"Jewelry",
            "type":"Manufacturing & Wholesale Goods"
        }
    ],
    "sg:phone":"+1 215 923 5964",
    "sg:postcode":"19106",
    "sg:province":"PA",
    "wof:name":"Milici Jewelers",
    "wof:placetype":"venue"
},
  "geometry": {"coordinates":[-75.153711,39.950534],"type":"Point"}
}