{
  "type": "Feature",
  "properties": {
    "iso:country":"US",
    "sg:address":"1800 W Oxford St",
    "sg:city":"Philadelphia",
    "sg:classifiers":[
        {
            "category":"Education",
            "subcategory":"School",
            "type":"Public Place"
        }
    ],
    "sg:phone":"+1 215 232 6137",
    "sg:postcode":"19121",
    "sg:province":"PA",
    "wof:name":"Meade School Pre-Kindergarten",
    "wof:placetype":"venue"
},
  "geometry": {"coordinates":[-75.165368,39.978201],"type":"Point"}
}