{
  "type": "Feature",
  "properties": {
    "iso:country":"US",
    "sg:address":"822 Old Rd",
    "sg:city":"Strasburg",
    "sg:classifiers":[
        {
            "category":"Manufacturing",
            "subcategory":"Tools & Machinery",
            "type":"Manufacturing & Wholesale Goods"
        }
    ],
    "sg:phone":"+1 717 560 7849",
    "sg:postcode":"17579",
    "sg:province":"PA",
    "sg:tags":[
        "equipment",
        "nurseryman",
        "supply"
    ],
    "wof:name":"NYP Corp",
    "wof:placetype":"venue"
},
  "geometry": {"coordinates":[-76.200923,39.933952],"type":"Point"}
}