{
  "type": "Feature",
  "properties": {
    "iso:country":"US",
    "sg:address":"8052 Steubenville Pike",
    "sg:city":"Oakdale",
    "sg:classifiers":[
        {
            "category":"Government",
            "subcategory":"Court House",
            "type":"Public Place"
        }
    ],
    "sg:phone":"+1   ",
    "sg:postcode":"15071",
    "sg:province":"PA",
    "sg:tags":[
        "state"
    ],
    "wof:name":"Magisterial District 05-3-17",
    "wof:placetype":"venue"
},
  "geometry": {"coordinates":[-80.24926000000001,40.440005],"type":"Point"}
}