{
  "type": "Feature",
  "properties": {
    "iso:country":"US",
    "sg:address":"1012 Commonwealth Blvd",
    "sg:city":"Reading",
    "sg:classifiers":[
        {
            "category":"Organizations",
            "subcategory":"Community Association",
            "type":"Services"
        }
    ],
    "sg:phone":"+1   ",
    "sg:postcode":"19607",
    "sg:province":"PA",
    "wof:name":"First Catholic Slovak Lad",
    "wof:placetype":"venue"
},
  "geometry": {"coordinates":[-75.938846,40.312887],"type":"Point"}
}