{
  "type": "Feature",
  "properties": {
    "addr:full":"8050 Rowan Rd Ste 403 Cranberry Twp PA 16066",
    "addr:housenumber":"8050",
    "addr:postcode":"16066",
    "addr:street":"Rowan Rd Ste 403",
    "iso:country":"US",
    "sg:address":"8050 Rowan Rd Ste 403",
    "sg:city":"Cranberry Twp",
    "sg:classifiers":[
        {
            "category":"Health Services",
            "subcategory":"Doctor",
            "type":"Services"
        }
    ],
    "sg:phone":"+1 724 772 0300",
    "sg:postcode":"16066",
    "sg:province":"PA",
    "wof:name":"Dave' Nikhil MD",
    "wof:placetype":"venue"
},
  "geometry": {"coordinates":[-80.09726499999999,40.704023],"type":"Point"}
}