{
  "type": "Feature",
  "properties": {
    "iso:country":"US",
    "sg:address":"949 Thorn Run Rd",
    "sg:city":"Coraopolis",
    "sg:classifiers":[
        {
            "category":"Professional",
            "subcategory":"Research",
            "type":"Services"
        }
    ],
    "sg:phone":"+1 412 264 1188",
    "sg:postcode":"15108",
    "sg:province":"PA",
    "sg:tags":[
        "environmental",
        "ecological"
    ],
    "wof:name":"Hollow Oak Land Trust",
    "wof:placetype":"venue"
},
  "geometry": {"coordinates":[-80.202077,40.509555],"type":"Point"}
}