{
  "type": "Feature",
  "properties": {
    "addr:full":"2 Hershey Rd Indianola PA 15051",
    "addr:housenumber":"2",
    "addr:postcode":"15051",
    "addr:street":"Hershey Rd",
    "iso:country":"US",
    "sg:address":"2 Hershey Rd",
    "sg:city":"Indianola",
    "sg:classifiers":[
        {
            "category":"Building & Trades",
            "subcategory":"Electrical",
            "type":"Services"
        }
    ],
    "sg:phone":"+1   ",
    "sg:postcode":"15051",
    "sg:province":"PA",
    "sg:tags":[
        "electrical",
        "contractor"
    ],
    "wof:name":"Hoyt Industrial Services",
    "wof:placetype":"venue"
},
  "geometry": {"coordinates":[-79.855435,40.565409],"type":"Point"}
}