{
  "type": "Feature",
  "properties": {
    "addr:full":"244 Great Valley Pkwy Malvern PA 19355",
    "addr:housenumber":"244",
    "addr:postcode":"19355",
    "addr:street":"Great Valley Pkwy",
    "iso:country":"US",
    "sg:address":"244 Great Valley Pkwy",
    "sg:city":"Malvern",
    "sg:classifiers":[
        {
            "category":"Professional",
            "subcategory":"Advertising",
            "type":"Services"
        }
    ],
    "sg:phone":"+1   ",
    "sg:postcode":"19355",
    "sg:province":"PA",
    "sg:tags":[
        "mail",
        "direct"
    ],
    "wof:name":"MCS Group Inc",
    "wof:placetype":"venue"
},
  "geometry": {"coordinates":[-75.54219999999999,40.063538],"type":"Point"}
}