{
  "type": "Feature",
  "properties": {
    "addr:full":"108 Espy St Nanticoke PA 18634",
    "addr:housenumber":"108",
    "addr:postcode":"18634",
    "addr:street":"Espy St",
    "iso:country":"US",
    "sg:address":"108 Espy St",
    "sg:city":"Nanticoke",
    "sg:classifiers":[
        {
            "category":"Government",
            "subcategory":"Fire Station",
            "type":"Public Place"
        }
    ],
    "sg:phone":"+1   ",
    "sg:postcode":"18634",
    "sg:province":"PA",
    "sg:tags":[
        "protection"
    ],
    "wof:name":"City of Nanticoke",
    "wof:placetype":"venue"
},
  "geometry": {"coordinates":[-75.98639900000001,41.185181],"type":"Point"}
}