{
  "type": "Feature",
  "properties": {
    "iso:country":"US",
    "sg:address":"3655 S Galloway St",
    "sg:city":"Philadelphia",
    "sg:classifiers":[
        {
            "category":"Freight",
            "type":"Transportation"
        }
    ],
    "sg:phone":"+1 215 389 2822",
    "sg:postcode":"19148",
    "sg:province":"PA",
    "sg:tags":[
        "warehouse",
        "self",
        "storage"
    ],
    "wof:name":"Hunter Brothers Warehouse",
    "wof:placetype":"venue"
},
  "geometry": {"coordinates":[-75.15648,39.90212],"type":"Point"}
}