{
  "type": "Feature",
  "properties": {
    "addr:full":"1000 Market St Bloomsburg PA 17815",
    "addr:housenumber":"1000",
    "addr:postcode":"17815",
    "addr:street":"Market St",
    "iso:country":"US",
    "sg:address":"1000 Market St",
    "sg:city":"Bloomsburg",
    "sg:classifiers":[
        {
            "category":"Shopping",
            "subcategory":"Books",
            "type":"Retail Goods"
        }
    ],
    "sg:phone":"+1 570 380 8960",
    "sg:postcode":"17815",
    "sg:province":"PA",
    "wof:name":"His House",
    "wof:placetype":"venue"
},
  "geometry": {"coordinates":[-76.45124199999999,40.994008],"type":"Point"}
}