{
  "type": "Feature",
  "properties": {
    "iso:country":"US",
    "sg:address":"768 Slate Hill Dr",
    "sg:city":"Oxford",
    "sg:classifiers":[
        {
            "category":"Professional",
            "type":"Services"
        }
    ],
    "sg:phone":"+1 610 998 9600",
    "sg:postcode":"19363",
    "sg:province":"PA",
    "sg:tags":[
        "establishment"
    ],
    "wof:name":"Nippy L",
    "wof:placetype":"venue"
},
  "geometry": {"coordinates":[-75.96027599999999,39.779448],"type":"Point"}
}