{
  "type": "Feature",
  "properties": {
    "iso:country":"US",
    "sg:address":"10661 Carr Rd",
    "sg:city":"Conneautville",
    "sg:classifiers":[
        {
            "category":"Professional",
            "type":"Services"
        }
    ],
    "sg:phone":"+1   ",
    "sg:postcode":"16406",
    "sg:province":"PA",
    "wof:name":"Oakbridge Timber Framing",
    "wof:placetype":"venue"
},
  "geometry": {"coordinates":[-80.299256,41.744479],"type":"Point"}
}