{
  "type": "Feature",
  "properties": {
    "addr:full":"216 Wells Ave Langhorne PA 19047",
    "addr:housenumber":"216",
    "addr:postcode":"19047",
    "addr:street":"Wells Ave Langhorne Pa",
    "iso:country":"US",
    "sg:address":"216 Wells Ave",
    "sg:city":"Langhorne",
    "sg:classifiers":[
        {
            "category":"Building & Trades",
            "subcategory":"Plumbing",
            "type":"Services"
        }
    ],
    "sg:phone":"+1 215 757 3456",
    "sg:postcode":"19047",
    "sg:province":"PA",
    "sg:tags":[
        "plumbing",
        "contractor"
    ],
    "wof:name":"Hollingsworth Plumbing & Htg",
    "wof:placetype":"venue"
},
  "geometry": {"coordinates":[-74.925749,40.178446],"type":"Point"}
}