{
  "type": "Feature",
  "properties": {
    "addr:full":"1005 Pine Heights St Roaring Spring PA 16673",
    "addr:housenumber":"1005",
    "addr:postcode":"16673",
    "addr:street":"Pine Heights St",
    "iso:country":"US",
    "sg:address":"1005 Pine Heights St",
    "sg:city":"Roaring Spring",
    "sg:classifiers":[
        {
            "category":"Retail",
            "subcategory":"Auto Repair",
            "type":"Services"
        }
    ],
    "sg:phone":"+1 814 224 0113",
    "sg:postcode":"16673",
    "sg:province":"PA",
    "sg:tags":[
        "repairing",
        "automobile"
    ],
    "wof:name":"Mahoney's Service Ctr",
    "wof:placetype":"venue"
},
  "geometry": {"coordinates":[-78.396047,40.331316],"type":"Point"}
}