{
  "type": "Feature",
  "properties": {
    "iso:country":"US",
    "sg:address":"11324 Rte 68",
    "sg:city":"Rimersburg",
    "sg:classifiers":[
        {
            "category":"Freight",
            "type":"Transportation"
        }
    ],
    "sg:phone":"+1 814 745 3739",
    "sg:postcode":"16248",
    "sg:province":"PA",
    "sg:tags":[
        "hauling",
        "trucking"
    ],
    "wof:name":"Tim Best Trucking",
    "wof:placetype":"venue"
},
  "geometry": {"coordinates":[-79.483289,41.079032],"type":"Point"}
}