{
  "type": "Feature",
  "properties": {
    "iso:country":"US",
    "sg:address":"2207 Paxton St",
    "sg:city":"Harrisburg",
    "sg:classifiers":[
        {
            "category":"Home & Garden",
            "subcategory":"Building Materials",
            "type":"Retail Goods"
        }
    ],
    "sg:phone":"+1 717 233 8401",
    "sg:postcode":"17111",
    "sg:province":"PA",
    "sg:tags":[
        "equipment",
        "fixture",
        "lighting"
    ],
    "wof:name":"Yale Electric Supply Co",
    "wof:placetype":"venue"
},
  "geometry": {"coordinates":[-76.84850299999999,40.255001],"type":"Point"}
}