{
  "type": "Feature",
  "properties": {
    "iso:country":"US",
    "sg:address":"115 S Main St",
    "sg:city":"Telford",
    "sg:classifiers":[
        {
            "category":"Manufacturing",
            "subcategory":"Tools & Machinery",
            "type":"Manufacturing & Wholesale Goods"
        }
    ],
    "sg:phone":"+1 215 723 3471",
    "sg:postcode":"18969",
    "sg:province":"PA",
    "sg:tags":[
        "jobbing",
        "shop",
        "machine",
        "special",
        "mfg"
    ],
    "wof:name":"H D Sampey Inc",
    "wof:placetype":"venue"
},
  "geometry": {"coordinates":[-75.325434,40.323568],"type":"Point"}
}