{
  "type": "Feature",
  "properties": {
    "addr:full":"2101 W Liberty St Allentown PA 18104",
    "addr:housenumber":"2101",
    "addr:postcode":"18104",
    "addr:street":"W Liberty St",
    "iso:country":"US",
    "sg:address":"2101 W Liberty St",
    "sg:city":"Allentown",
    "sg:classifiers":[
        {
            "category":"Bars & Pubs",
            "type":"Food & Drink"
        },
        {
            "category":"Restaurant",
            "type":"Food & Drink"
        }
    ],
    "sg:phone":"+1 610 432 7553",
    "sg:postcode":"18104",
    "sg:province":"PA",
    "wof:name":"Stooges Bar & Grille",
    "wof:placetype":"venue"
},
  "geometry": {"coordinates":[-75.503998,40.601101],"type":"Point"}
}