{
  "type": "Feature",
  "properties": {
    "addr:full":"40 W Mount Carmel Ave Mt Carmel PA 17851",
    "addr:housenumber":"40",
    "addr:postcode":"17851",
    "addr:street":"W Mount Carmel Ave Mt",
    "iso:country":"US",
    "sg:address":"40 W Mount Carmel Ave",
    "sg:city":"Mt Carmel",
    "sg:classifiers":[
        {
            "category":"Retail",
            "subcategory":"Funeral Services",
            "type":"Services"
        }
    ],
    "sg:phone":"+1 570 339 4300",
    "sg:postcode":"17851",
    "sg:province":"PA",
    "sg:tags":[
        "director"
    ],
    "sg:website":"www.stutzfuneralhome.com",
    "wof:name":"Joseph J Stutz Funeral Home",
    "wof:placetype":"venue"
},
  "geometry": {"coordinates":[-76.41423,40.798879],"type":"Point"}
}