{
  "type": "Feature",
  "properties": {
    "addr:full":"243 Adams St Johnstown PA 15901",
    "addr:housenumber":"243",
    "addr:postcode":"15901",
    "addr:street":"Adams St",
    "iso:country":"US",
    "sg:address":"243 Adams St",
    "sg:city":"Johnstown",
    "sg:classifiers":[
        {
            "category":"Professional",
            "subcategory":"Management & Consulting",
            "type":"Services"
        }
    ],
    "sg:phone":"+1 814 539 9898",
    "sg:postcode":"15901",
    "sg:province":"PA",
    "wof:name":"Public Affairs Management",
    "wof:placetype":"venue"
},
  "geometry": {"coordinates":[-78.91397600000001,40.323192],"type":"Point"}
}