{
  "type": "Feature",
  "properties": {
    "iso:country":"US",
    "sg:address":"5845 Market St",
    "sg:city":"Philadelphia",
    "sg:classifiers":[
        {
            "category":"Social Services",
            "subcategory":"Child Care",
            "type":"Services"
        }
    ],
    "sg:phone":"+1 215 748 1931",
    "sg:postcode":"19139",
    "sg:province":"PA",
    "sg:tags":[
        "day"
    ],
    "wof:name":"Buttons & Bows Day Care",
    "wof:placetype":"venue"
},
  "geometry": {"coordinates":[-75.237647,39.961818],"type":"Point"}
}