{
  "type": "Feature",
  "properties": {
    "iso:country":"US",
    "sg:address":"4900 Liberty Ave",
    "sg:city":"Pittsburgh",
    "sg:classifiers":[
        {
            "category":"Real Estate",
            "subcategory":"Real Estate Services",
            "type":"Services"
        },
        {
            "category":"Banks & Credit Unions",
            "subcategory":"Bank",
            "type":"Services"
        }
    ],
    "sg:phone":"+1 412 690 2358",
    "sg:postcode":"15224",
    "sg:province":"PA",
    "sg:tags":[
        "commercial",
        "loan",
        "saving"
    ],
    "wof:name":"First Commonwealth Bank",
    "wof:placetype":"venue"
},
  "geometry": {"coordinates":[-79.945938,40.460011],"type":"Point"}
}