{
  "type": "Feature",
  "properties": {
    "addr:full":"508 Floral Vale Blvd Morrisville PA 19067",
    "addr:housenumber":"508",
    "addr:postcode":"19067",
    "addr:street":"Floral Vale Blvd",
    "iso:country":"US",
    "sg:address":"508 Floral Vale Blvd",
    "sg:city":"Morrisville",
    "sg:classifiers":[
        {
            "category":"Health Services",
            "subcategory":"Doctor",
            "type":"Services"
        }
    ],
    "sg:phone":"+1   ",
    "sg:postcode":"19067",
    "sg:province":"PA",
    "wof:name":"Sieczkowski Donald P DDS",
    "wof:placetype":"venue"
},
  "geometry": {"coordinates":[-74.882812,40.219552],"type":"Point"}
}