{
  "type": "Feature",
  "properties": {
    "addr:full":"317 McKinley Ave Norwood PA 19074",
    "addr:housenumber":"317",
    "addr:postcode":"19074",
    "addr:street":"Mckinley Ave",
    "iso:country":"US",
    "sg:address":"317 McKinley Ave",
    "sg:city":"Norwood",
    "sg:classifiers":[
        {
            "category":"Building & Trades",
            "subcategory":"Construction",
            "type":"Services"
        }
    ],
    "sg:phone":"+1 610 532 9202",
    "sg:postcode":"19074",
    "sg:province":"PA",
    "sg:tags":[
        "contractor"
    ],
    "wof:name":"System 1 Contracting",
    "wof:placetype":"venue"
},
  "geometry": {"coordinates":[-75.29123,39.888853],"type":"Point"}
}