{
  "type": "Feature",
  "properties": {
    "addr:full":"122 S Margaretta St Schuylkill Haven PA 17972",
    "addr:housenumber":"122",
    "addr:postcode":"17972",
    "addr:street":"S Margaretta St",
    "iso:country":"US",
    "sg:address":"122 S Margaretta St",
    "sg:city":"Schuylkill Haven",
    "sg:classifiers":[
        {
            "category":"Real Estate",
            "subcategory":"Real Estate Operator",
            "type":"Services"
        }
    ],
    "sg:phone":"+1   ",
    "sg:postcode":"17972",
    "sg:province":"PA",
    "sg:tags":[
        "building",
        "commercial",
        "lessor"
    ],
    "wof:name":"Three Bees Company",
    "wof:placetype":"venue"
},
  "geometry": {"coordinates":[-76.16893399999999,40.630078],"type":"Point"}
}