{
  "type": "Feature",
  "properties": {
    "addr:full":"8818 Lake Dr Kunkletown PA 18058",
    "addr:housenumber":"8818",
    "addr:postcode":"18058",
    "addr:street":"Lake Dr Kunkletown",
    "iso:country":"US",
    "sg:address":"8818 Lake Dr",
    "sg:city":"Kunkletown",
    "sg:classifiers":[
        {
            "category":"Manufacturing",
            "subcategory":"Buildings",
            "type":"Manufacturing & Wholesale Goods"
        },
        {
            "category":"Building & Trades",
            "subcategory":"Construction",
            "type":"Services"
        }
    ],
    "sg:phone":"+1 610 681 2200",
    "sg:postcode":"18058",
    "sg:province":"PA",
    "sg:tags":[
        "home",
        "builder",
        "contractor"
    ],
    "wof:name":"Certified Home Builders",
    "wof:placetype":"venue"
},
  "geometry": {"coordinates":[-75.532596,40.966091],"type":"Point"}
}