{
  "type": "Feature",
  "properties": {
    "addr:full":"2578 Duncan Ave Allison Park PA 15101",
    "addr:housenumber":"2578",
    "addr:postcode":"15101",
    "addr:street":"Duncan Ave",
    "iso:country":"US",
    "sg:address":"2578 Duncan Ave",
    "sg:city":"Allison Park",
    "sg:classifiers":[
        {
            "category":"Personal",
            "subcategory":"Beauty Salon",
            "type":"Services"
        }
    ],
    "sg:phone":"+1 412 486 7444",
    "sg:postcode":"15101",
    "sg:province":"PA",
    "sg:tags":[
        "shop"
    ],
    "wof:name":"Schoolhouse Salon",
    "wof:placetype":"venue"
},
  "geometry": {"coordinates":[-79.964215,40.559866],"type":"Point"}
}