{
  "type": "Feature",
  "properties": {
    "addr:full":"1826 Union Blvd Allentown PA 18109",
    "addr:housenumber":"1826",
    "addr:postcode":"18109",
    "addr:street":"Union Blvd",
    "iso:country":"US",
    "sg:address":"1826 Union Blvd",
    "sg:city":"Allentown",
    "sg:classifiers":[
        {
            "category":"Restaurant",
            "type":"Food & Drink"
        }
    ],
    "sg:menulink":"http://www.allmenus.com/pa/allentown/66274-dominos-pizza/menu/",
    "sg:phone":"+1 610 776 2020",
    "sg:postcode":"18109",
    "sg:province":"PA",
    "sg:tags":[
        "american",
        "wing",
        "pizza"
    ],
    "wof:name":"Domino's Pizza",
    "wof:placetype":"venue"
},
  "geometry": {"coordinates":[-75.428316,40.625428],"type":"Point"}
}