{
  "type": "Feature",
  "properties": {
    "addr:full":"702 Greenlawn Rd Ford City PA 16226",
    "addr:housenumber":"702",
    "addr:postcode":"16226",
    "addr:street":"Greenlawn Rd",
    "iso:country":"US",
    "sg:address":"702 Greenlawn Rd",
    "sg:city":"Ford City",
    "sg:classifiers":[
        {
            "category":"Education",
            "subcategory":"Vocational School",
            "type":"Public Place"
        }
    ],
    "sg:phone":"+1 724 763 4128",
    "sg:postcode":"16226",
    "sg:province":"PA",
    "sg:tags":[
        "processing",
        "datum"
    ],
    "wof:name":"Gradwell Consulting",
    "wof:placetype":"venue"
},
  "geometry": {"coordinates":[-79.54495799999999,40.753151],"type":"Point"}
}