{
  "type": "Feature",
  "properties": {
    "iso:country":"US",
    "sg:address":"2725 Plank Rd",
    "sg:city":"New Castle",
    "sg:classifiers":[
        {
            "category":"Retail",
            "subcategory":"Laundry & Dry Cleaning",
            "type":"Services"
        }
    ],
    "sg:phone":"+1 724 656 1054",
    "sg:postcode":"16105",
    "sg:province":"PA",
    "sg:tags":[
        "cleaners",
        "rug",
        "carpet"
    ],
    "wof:name":"Creative Cleaning Systems",
    "wof:placetype":"venue"
},
  "geometry": {"coordinates":[-80.342539,41.033232],"type":"Point"}
}