{
  "type": "Feature",
  "properties": {
    "iso:country":"US",
    "sg:address":"73 Old Dublin Pike Ste 10 Box 113",
    "sg:city":"Doylestown",
    "sg:classifiers":[
        {
            "category":"Professional",
            "subcategory":"Art Services",
            "type":"Services"
        },
        {
            "category":"Communications",
            "type":"Services"
        }
    ],
    "sg:phone":"+1 215 352 5216",
    "sg:postcode":"18901",
    "sg:province":"PA",
    "sg:tags":[
        "web",
        "graphic",
        "design"
    ],
    "sg:website":"www.goldsteinmedia.com",
    "wof:name":"Goldstein Media LLC",
    "wof:placetype":"venue"
},
  "geometry": {"coordinates":[-75.131314,40.324295],"type":"Point"}
}