{
  "type": "Feature",
  "properties": {
    "iso:country":"US",
    "sg:address":"86 Miller Ln",
    "sg:city":"Mertztown",
    "sg:classifiers":[
        {
            "category":"Building & Trades",
            "subcategory":"Construction",
            "type":"Services"
        }
    ],
    "sg:phone":"+1 610 682 7377",
    "sg:postcode":"19606",
    "sg:province":"PA",
    "sg:tags":[
        "home",
        "remodeling",
        "family",
        "contractor"
    ],
    "wof:name":"Clyde F Miller Contractor",
    "wof:placetype":"venue"
},
  "geometry": {"coordinates":[-75.854849,40.384442],"type":"Point"}
}