{
  "type": "Feature",
  "properties": {
    "addr:full":"420 N Penn St Spring City PA 19475",
    "addr:housenumber":"420",
    "addr:postcode":"19475",
    "addr:street":"N Penn St",
    "iso:country":"US",
    "sg:address":"420 N Penn St",
    "sg:city":"Spring City",
    "sg:classifiers":[
        {
            "category":"Building & Trades",
            "subcategory":"Construction",
            "type":"Services"
        }
    ],
    "sg:phone":"+1 610 948 3441",
    "sg:postcode":"19475",
    "sg:province":"PA",
    "sg:tags":[
        "coping",
        "plastering",
        "tiling",
        "pool",
        "swimming"
    ],
    "wof:name":"Rds Plumbing Co",
    "wof:placetype":"venue"
},
  "geometry": {"coordinates":[-75.55262999999999,40.182637],"type":"Point"}
}