{
  "type": "Feature",
  "properties": {
    "iso:country":"US",
    "sg:address":"230 Executive Dr Ste 1",
    "sg:city":"Cranberry Twp",
    "sg:classifiers":[
        {
            "category":"Education",
            "subcategory":"School",
            "type":"Public Place"
        }
    ],
    "sg:phone":"+1 724 772 3800",
    "sg:postcode":"16066",
    "sg:province":"PA",
    "wof:name":"Simplex Grinel Lp",
    "wof:placetype":"venue"
},
  "geometry": {"coordinates":[-80.108902,40.690601],"type":"Point"}
}