{
  "type": "Feature",
  "properties": {
    "addr:full":"204 Stevenson Rd Greenville PA 16125",
    "addr:housenumber":"204",
    "addr:postcode":"16125",
    "addr:street":"Stevenson Rd",
    "iso:country":"US",
    "sg:address":"204 Stevenson Rd",
    "sg:city":"Greenville",
    "sg:classifiers":[
        {
            "category":"Government",
            "subcategory":"Office",
            "type":"Public Place"
        }
    ],
    "sg:phone":"+1   ",
    "sg:postcode":"16125",
    "sg:province":"PA",
    "sg:tags":[
        "policy"
    ],
    "wof:name":"Tax Office",
    "wof:placetype":"venue"
},
  "geometry": {"coordinates":[-80.287733,41.446231],"type":"Point"}
}