{
  "type": "Feature",
  "properties": {
    "iso:country":"US",
    "sg:address":"6200 Noblestown Rd",
    "sg:city":"Oakdale",
    "sg:classifiers":[
        {
            "category":"Retail",
            "subcategory":"Auto Repair",
            "type":"Services"
        }
    ],
    "sg:phone":"+1 724 693 8411",
    "sg:postcode":"15071",
    "sg:province":"PA",
    "wof:name":"Leininger's Auto Service",
    "wof:placetype":"venue"
},
  "geometry": {"coordinates":[-80.198402,40.391102],"type":"Point"}
}