{
  "type": "Feature",
  "properties": {
    "addr:full":"64 Ferguson Ave Broomall PA 19008",
    "addr:housenumber":"64",
    "addr:postcode":"19008",
    "addr:street":"Ferguson Ave",
    "iso:country":"US",
    "sg:address":"64 Ferguson Ave",
    "sg:city":"Broomall",
    "sg:classifiers":[
        {
            "category":"Building & Trades",
            "subcategory":"Plumbing",
            "type":"Services"
        }
    ],
    "sg:phone":"+1 610 359 9590",
    "sg:postcode":"19008",
    "sg:province":"PA",
    "sg:tags":[
        "plumbing",
        "contractor"
    ],
    "wof:name":"Wynne Penn Plumbing & Heating",
    "wof:placetype":"venue"
},
  "geometry": {"coordinates":[-75.34726999999999,39.981045],"type":"Point"}
}