{
  "type": "Feature",
  "properties": {
    "addr:full":"611 Union St Big Run PA 15715",
    "addr:housenumber":"611",
    "addr:postcode":"15715",
    "addr:street":"Union St",
    "iso:country":"US",
    "sg:address":"611 Union St",
    "sg:city":"Big Run",
    "sg:classifiers":[
        {
            "category":"Manufacturing",
            "subcategory":"Printing",
            "type":"Manufacturing & Wholesale Goods"
        }
    ],
    "sg:phone":"+1   ",
    "sg:postcode":"15715",
    "sg:province":"PA",
    "sg:tags":[
        "lithographic",
        "commercial"
    ],
    "wof:name":"Tee Riffik Screen Prtg Design",
    "wof:placetype":"venue"
},
  "geometry": {"coordinates":[-78.864073,40.971198],"type":"Point"}
}