{
  "type": "Feature",
  "properties": {
    "iso:country":"US",
    "sg:address":"449 W Main St",
    "sg:city":"Elizabethville",
    "sg:classifiers":[
        {
            "category":"Insurance",
            "subcategory":"Insurance Agent",
            "type":"Services"
        }
    ],
    "sg:phone":"+1 717 362 7200",
    "sg:postcode":"17023",
    "sg:province":"PA",
    "sg:website":"www.selfemployedgroup.com",
    "wof:name":"Self Employed Insurance Group",
    "wof:placetype":"venue"
},
  "geometry": {"coordinates":[-76.823283,40.546997],"type":"Point"}
}