{
  "type": "Feature",
  "properties": {
    "iso:country":"US",
    "sg:address":"150 N School Ln",
    "sg:city":"Lancaster",
    "sg:classifiers":[
        {
            "category":"Manufacturing",
            "subcategory":"Toys & Sporting Goods",
            "type":"Manufacturing & Wholesale Goods"
        }
    ],
    "sg:phone":"+1   ",
    "sg:postcode":"17603",
    "sg:province":"PA",
    "sg:tags":[
        "mfg",
        "accessory",
        "clothing",
        "doll"
    ],
    "wof:name":"Hoyer Mary Doll Co Inc",
    "wof:placetype":"venue"
},
  "geometry": {"coordinates":[-76.332318,40.042838],"type":"Point"}
}