{
  "type": "Feature",
  "properties": {
    "iso:country":"US",
    "sg:address":"7308 Castor Ave",
    "sg:city":"Philadelphia",
    "sg:classifiers":[
        {
            "category":"Real Estate",
            "subcategory":"Real Estate Agent",
            "type":"Services"
        }
    ],
    "sg:phone":"+1 215 722 9000",
    "sg:postcode":"19152",
    "sg:province":"PA",
    "wof:name":"Remax Metropolitan Inc",
    "wof:placetype":"venue"
},
  "geometry": {"coordinates":[-75.064511,40.052946],"type":"Point"}
}