{
  "type": "Feature",
  "properties": {
    "iso:country":"US",
    "sg:address":"1007 Waterdam Plaza Dr",
    "sg:city":"Canonsburg",
    "sg:classifiers":[
        {
            "category":"Arena",
            "subcategory":"Sports Club",
            "type":"Entertainment"
        }
    ],
    "sg:phone":"+1 724 942 9522",
    "sg:postcode":"15317",
    "sg:province":"PA",
    "sg:tags":[
        "martial art"
    ],
    "wof:name":"Ata Martial Arts Academy",
    "wof:placetype":"venue"
},
  "geometry": {"coordinates":[-80.133776,40.262776],"type":"Point"}
}