{
  "type": "Feature",
  "properties": {
    "addr:full":"5824 Glenbrook Dr Bethel Park PA 15102",
    "addr:housenumber":"5824",
    "addr:postcode":"15102",
    "addr:street":"Glenbrook Dr",
    "iso:country":"US",
    "sg:address":"5824 Glenbrook Dr",
    "sg:city":"Bethel Park",
    "sg:classifiers":[
        {
            "category":"Professional",
            "subcategory":"Management & Consulting",
            "type":"Services"
        },
        {
            "category":"Insurance",
            "subcategory":"Insurance Agent",
            "type":"Services"
        }
    ],
    "sg:phone":"+1 412 833 5700",
    "sg:postcode":"15102",
    "sg:province":"PA",
    "wof:name":"Sarria Associates",
    "wof:placetype":"venue"
},
  "geometry": {"coordinates":[-80.04298199999999,40.307839],"type":"Point"}
}