{
  "type": "Feature",
  "properties": {
    "iso:country":"US",
    "sg:address":"32 S 12th St",
    "sg:city":"Lebanon",
    "sg:classifiers":[
        {
            "category":"Shopping",
            "type":"Retail Goods"
        },
        {
            "category":"Retail",
            "subcategory":"Animal Services",
            "type":"Services"
        }
    ],
    "sg:phone":"+1 717 228 1998",
    "sg:postcode":"17042",
    "sg:province":"PA",
    "sg:tags":[
        "pet",
        "grooming",
        "washing",
        "merchandise"
    ],
    "wof:name":"Karen's Pet Stop",
    "wof:placetype":"venue"
},
  "geometry": {"coordinates":[-76.43090599999999,40.338018],"type":"Point"}
}