{
  "type": "Feature",
  "properties": {
    "iso:country":"US",
    "sg:address":"302 S York St",
    "sg:city":"Mechanicsburg",
    "sg:classifiers":[
        {
            "category":"Building & Trades",
            "subcategory":"Construction",
            "type":"Services"
        }
    ],
    "sg:phone":"+1   ",
    "sg:postcode":"17055",
    "sg:province":"PA",
    "sg:tags":[
        "new",
        "remodeling",
        "comm",
        "residential"
    ],
    "wof:name":"Michael L Ward Bldg & Rmdlg",
    "wof:placetype":"venue"
},
  "geometry": {"coordinates":[-77.012489,40.20876],"type":"Point"}
}