{
  "type": "Feature",
  "properties": {
    "iso:country":"US",
    "sg:address":"1597 Washington Pike",
    "sg:city":"Bridgeville",
    "sg:classifiers":[
        {
            "category":"Retail",
            "subcategory":"Laundry & Dry Cleaning",
            "type":"Services"
        }
    ],
    "sg:phone":"+1 412 276 3177",
    "sg:postcode":"15017",
    "sg:province":"PA",
    "sg:tags":[
        "cleaners"
    ],
    "wof:name":"Fi Del Cleaners",
    "wof:placetype":"venue"
},
  "geometry": {"coordinates":[-80.08727,40.394369],"type":"Point"}
}