{
  "type": "Feature",
  "properties": {
    "iso:country":"US",
    "sg:address":"1141 Clay Ave",
    "sg:city":"Dunmore",
    "sg:classifiers":[
        {
            "category":"Health Services",
            "subcategory":"Doctor",
            "type":"Services"
        }
    ],
    "sg:phone":"+1 570 341 0555",
    "sg:postcode":"18510",
    "sg:province":"PA",
    "sg:tags":[
        "physician",
        "surgeon"
    ],
    "wof:name":"Development Associates",
    "wof:placetype":"venue"
},
  "geometry": {"coordinates":[-75.64434300000001,41.414934],"type":"Point"}
}