{
  "type": "Feature",
  "properties": {
    "iso:country":"US",
    "sg:address":"305 Corporate Dr E",
    "sg:city":"Langhorne",
    "sg:classifiers":[
        {
            "category":"Insurance",
            "subcategory":"Insurance Agent",
            "type":"Services"
        }
    ],
    "sg:phone":"+1   ",
    "sg:postcode":"19047",
    "sg:province":"PA",
    "wof:name":"American Wholesale Insur Group",
    "wof:placetype":"venue"
},
  "geometry": {"coordinates":[-74.906694,40.220909],"type":"Point"}
}