{
  "type": "Feature",
  "properties": {
    "iso:country":"US",
    "sg:address":"407 Locust St",
    "sg:city":"Pittsburgh",
    "sg:classifiers":[
        {
            "category":"Sports & Exercise",
            "subcategory":"Bowling",
            "type":"Entertainment"
        }
    ],
    "sg:phone":"+1 412 771 2800",
    "sg:postcode":"15218",
    "sg:province":"PA",
    "sg:tags":[
        "center"
    ],
    "wof:name":"Brannan's Bowl",
    "wof:placetype":"venue"
},
  "geometry": {"coordinates":[-79.87539599999999,40.431504],"type":"Point"}
}