{
  "type": "Feature",
  "properties": {
    "addr:full":"318 Dubois St Du Bois PA 15801",
    "addr:housenumber":"318",
    "addr:postcode":"15801",
    "addr:street":"Dubois St Du Bois",
    "iso:country":"US",
    "sg:address":"318 Dubois St",
    "sg:city":"Du Bois",
    "sg:classifiers":[
        {
            "category":"Food & Beverages",
            "subcategory":"Bakery",
            "type":"Retail Goods"
        }
    ],
    "sg:phone":"+1 814 371 4781",
    "sg:postcode":"15801",
    "sg:province":"PA",
    "sg:tags":[
        "baker"
    ],
    "wof:name":"Calliari's Bakery",
    "wof:placetype":"venue"
},
  "geometry": {"coordinates":[-78.765317,41.124863],"type":"Point"}
}