{
  "type": "Feature",
  "properties": {
    "iso:country":"US",
    "sg:address":"1800 Linglestown Rd",
    "sg:city":"Harrisburg",
    "sg:classifiers":[
        {
            "category":"Real Estate",
            "subcategory":"Real Estate Services",
            "type":"Services"
        }
    ],
    "sg:phone":"+1 717 257 5400",
    "sg:postcode":"17110",
    "sg:province":"PA",
    "sg:tags":[
        "company",
        "title"
    ],
    "wof:name":"A 1 Abstract Assoc Inc",
    "wof:placetype":"venue"
},
  "geometry": {"coordinates":[-76.87136,40.327718],"type":"Point"}
}