{
  "type": "Feature",
  "properties": {
    "iso:country":"US",
    "sg:address":"341 Main St",
    "sg:city":"Wampum",
    "sg:classifiers":[
        {
            "category":"Cemetery",
            "type":"Public Place"
        },
        {
            "category":"Retail",
            "subcategory":"Funeral Services",
            "type":"Services"
        }
    ],
    "sg:phone":"+1 724 535 8180",
    "sg:postcode":"16157",
    "sg:province":"PA",
    "sg:tags":[
        "director",
        "crematory",
        "plans-pre-arranged",
        "supply"
    ],
    "wof:name":"Marshall Funeral Home",
    "wof:placetype":"venue"
},
  "geometry": {"coordinates":[-80.340799,40.890199],"type":"Point"}
}