{
  "type": "Feature",
  "properties": {
    "iso:country":"US",
    "sg:address":"10362 Ellis Rd",
    "sg:city":"Conneaut Lake",
    "sg:classifiers":[
        {
            "category":"Manufacturing",
            "subcategory":"Metals",
            "type":"Manufacturing & Wholesale Goods"
        },
        {
            "category":"Home & Garden",
            "subcategory":"Building Materials",
            "type":"Retail Goods"
        }
    ],
    "sg:phone":"+1 814 382 4195",
    "sg:postcode":"16316",
    "sg:province":"PA",
    "sg:tags":[
        "work",
        "merchandise",
        "w",
        "general"
    ],
    "wof:name":"Mailliard Aluminum & Self Stor",
    "wof:placetype":"venue"
},
  "geometry": {"coordinates":[-80.32166599999999,41.634136],"type":"Point"}
}