{
  "type": "Feature",
  "properties": {
    "iso:country":"US",
    "sg:address":"179 Meadowbrook Ln",
    "sg:city":"Brookhaven",
    "sg:classifiers":[
        {
            "category":"Professional",
            "subcategory":"Management & Consulting",
            "type":"Services"
        }
    ],
    "sg:phone":"+1   ",
    "sg:postcode":"19015",
    "sg:province":"PA",
    "wof:name":"Elite Property Mgmt",
    "wof:placetype":"venue"
},
  "geometry": {"coordinates":[-75.380301,39.872003],"type":"Point"}
}