{
  "type": "Feature",
  "properties": {
    "addr:full":"815 N Park Ave Norristown PA 19403",
    "addr:housenumber":"815",
    "addr:postcode":"19403",
    "addr:street":"N Park Ave",
    "iso:country":"US",
    "sg:address":"815 N Park Ave",
    "sg:city":"Norristown",
    "sg:classifiers":[
        {
            "category":"Retail",
            "subcategory":"Auto Repair",
            "type":"Services"
        }
    ],
    "sg:phone":"+1 610 539 9911",
    "sg:postcode":"19403",
    "sg:province":"PA",
    "sg:tags":[
        "repairing",
        "automobile"
    ],
    "wof:name":"Ralph Milner's Auto Repair",
    "wof:placetype":"venue"
},
  "geometry": {"coordinates":[-75.382501,40.15913],"type":"Point"}
}