{
  "type": "Feature",
  "properties": {
    "addr:full":"1540 Sans Souci Pkwy Wilkes Barre PA 18706",
    "addr:housenumber":"1540",
    "addr:postcode":"18706",
    "addr:street":"Sans Souci Pkwy",
    "iso:country":"US",
    "sg:address":"1540 Sans Souci Pkwy",
    "sg:city":"Wilkes Barre",
    "sg:classifiers":[
        {
            "category":"Banks & Credit Unions",
            "subcategory":"Bank",
            "type":"Services"
        }
    ],
    "sg:phone":"+1   ",
    "sg:postcode":"18706",
    "sg:province":"PA",
    "sg:tags":[
        "national"
    ],
    "wof:name":"PNC",
    "wof:placetype":"venue"
},
  "geometry": {"coordinates":[-75.940945,41.221702],"type":"Point"}
}