{
  "type": "Feature",
  "properties": {
    "iso:country":"US",
    "sg:address":"256 S York Rd",
    "sg:city":"Hatboro",
    "sg:classifiers":[
        {
            "category":"Banks & Credit Unions",
            "subcategory":"Bank",
            "type":"Services"
        }
    ],
    "sg:phone":"+1 215 675 0146",
    "sg:postcode":"19040",
    "sg:province":"PA",
    "wof:name":"Commerce Bank",
    "wof:placetype":"venue"
},
  "geometry": {"coordinates":[-75.10760399999999,40.173689],"type":"Point"}
}