{
  "type": "Feature",
  "properties": {
    "iso:country":"US",
    "sg:address":"794 Penllyn Blue Bell Pike",
    "sg:city":"Blue Bell",
    "sg:classifiers":[
        {
            "category":"Real Estate",
            "subcategory":"Architect",
            "type":"Services"
        }
    ],
    "sg:phone":"+1 215 793 6608",
    "sg:postcode":"19422",
    "sg:province":"PA",
    "wof:name":"O'Brien C Architects",
    "wof:placetype":"venue"
},
  "geometry": {"coordinates":[-75.263447,40.15603],"type":"Point"}
}