{
  "type": "Feature",
  "properties": {
    "addr:full":"75 N Mountain Blvd Mountain Top PA 18707",
    "addr:housenumber":"75",
    "addr:postcode":"18707",
    "addr:street":"N Mountain Blvd",
    "iso:country":"US",
    "sg:address":"75 N Mountain Blvd",
    "sg:city":"Mountain Top",
    "sg:classifiers":[
        {
            "category":"Social Services",
            "subcategory":"Child Care",
            "type":"Services"
        }
    ],
    "sg:phone":"+1 570 474 9695",
    "sg:postcode":"18707",
    "sg:province":"PA",
    "sg:tags":[
        "day"
    ],
    "wof:name":"Shining Stars Inc",
    "wof:placetype":"venue"
},
  "geometry": {"coordinates":[-75.87979799999999,41.168928],"type":"Point"}
}