{
  "type": "Feature",
  "properties": {
    "addr:full":"733 S Chester Rd Swarthmore PA 19081",
    "addr:housenumber":"733",
    "addr:postcode":"19081",
    "addr:street":"S Chester Rd",
    "iso:country":"US",
    "sg:address":"733 S Chester Rd",
    "sg:city":"Swarthmore",
    "sg:classifiers":[
        {
            "category":"Food & Beverages",
            "subcategory":"Fruits & Vegetables",
            "type":"Retail Goods"
        }
    ],
    "sg:phone":"+1   ",
    "sg:postcode":"19081",
    "sg:province":"PA",
    "wof:name":"320 Produce Market",
    "wof:placetype":"venue"
},
  "geometry": {"coordinates":[-75.354844,39.888611],"type":"Point"}
}