{
  "type": "Feature",
  "properties": {
    "iso:country":"US",
    "sg:address":"131 Upper Gyp Rd",
    "sg:city":"Bellefonte",
    "sg:classifiers":[
        {
            "category":"Building & Trades",
            "subcategory":"Construction",
            "type":"Services"
        }
    ],
    "sg:phone":"+1 814 355 7906",
    "sg:postcode":"16823",
    "sg:province":"PA",
    "sg:tags":[
        "tile",
        "dealer"
    ],
    "wof:name":"D L Harter Ceramic Tile",
    "wof:placetype":"venue"
},
  "geometry": {"coordinates":[-77.839904,40.886952],"type":"Point"}
}