{
  "type": "Feature",
  "properties": {
    "iso:country":"US",
    "sg:address":"668 Jacobs Ferry Rd",
    "sg:city":"Carmichaels",
    "sg:classifiers":[
        {
            "category":"Building & Trades",
            "subcategory":"Construction",
            "type":"Services"
        }
    ],
    "sg:phone":"+1   ",
    "sg:postcode":"15320",
    "sg:province":"PA",
    "sg:tags":[
        "house"
    ],
    "wof:name":"Gasti Construction Inc",
    "wof:placetype":"venue"
},
  "geometry": {"coordinates":[-79.935737,39.930726],"type":"Point"}
}