{
  "type": "Feature",
  "properties": {
    "addr:full":"540 Easterly Pkwy State College PA 16801",
    "addr:housenumber":"540",
    "addr:postcode":"16801",
    "addr:street":"Easterly Pkwy",
    "iso:country":"US",
    "sg:address":"540 Easterly Pkwy",
    "sg:city":"State College",
    "sg:classifiers":[
        {
            "category":"Personal",
            "subcategory":"Beauty Salon",
            "type":"Services"
        }
    ],
    "sg:phone":"+1 814 237 1643",
    "sg:postcode":"16801",
    "sg:province":"PA",
    "sg:tags":[
        "shop"
    ],
    "wof:name":"Price's Skin Care",
    "wof:placetype":"venue"
},
  "geometry": {"coordinates":[-77.84363399999999,40.795333],"type":"Point"}
}