{
  "type": "Feature",
  "properties": {
    "addr:full":"2206 Walnut St Harrisburg PA 17103",
    "addr:housenumber":"2206",
    "addr:postcode":"17103",
    "addr:street":"Walnut St",
    "iso:country":"US",
    "sg:address":"2206 Walnut St",
    "sg:city":"Harrisburg",
    "sg:classifiers":[
        {
            "category":"Social Services",
            "subcategory":"Child Care",
            "type":"Services"
        },
        {
            "category":"Education",
            "subcategory":"Preschool",
            "type":"Public Place"
        },
        {
            "category":"Education",
            "subcategory":"School",
            "type":"Public Place"
        }
    ],
    "sg:phone":"+1 717 234 3309",
    "sg:postcode":"17103",
    "sg:province":"PA",
    "sg:tags":[
        "elementary",
        "day"
    ],
    "wof:name":"Hansel & Gretel Early Learning Centers Inc",
    "wof:placetype":"venue"
},
  "geometry": {"coordinates":[-76.855598,40.274502],"type":"Point"}
}