{
  "type": "Feature",
  "properties": {
    "addr:full":"15 Main St Wilkes Barre PA 18702",
    "addr:housenumber":"15",
    "addr:postcode":"18702",
    "addr:street":"Main St",
    "iso:country":"US",
    "sg:address":"15 Main St",
    "sg:city":"Wilkes Barre",
    "sg:classifiers":[
        {
            "category":"Manufacturing",
            "subcategory":"Printing",
            "type":"Manufacturing & Wholesale Goods"
        }
    ],
    "sg:phone":"+1 570 829 7224",
    "sg:postcode":"18702",
    "sg:province":"PA",
    "sg:tags":[
        "newspaper",
        "publishing"
    ],
    "sg:website":"www.timesleader.com",
    "wof:name":"Obituraries",
    "wof:placetype":"venue"
},
  "geometry": {"coordinates":[-75.80630600000001,41.28812],"type":"Point"}
}