{
  "type": "Feature",
  "properties": {
    "iso:country":"US",
    "sg:address":"66 W Chelten Ave",
    "sg:city":"Philadelphia",
    "sg:classifiers":[
        {
            "category":"Organizations",
            "subcategory":"Religious Organization",
            "type":"Services"
        }
    ],
    "sg:phone":"+1 215 849 3561",
    "sg:postcode":"19144",
    "sg:province":"PA",
    "sg:tags":[
        "church"
    ],
    "wof:name":"Harvest Time Christian Fllwshp",
    "wof:placetype":"venue"
},
  "geometry": {"coordinates":[-75.175533,40.035199],"type":"Point"}
}