{
  "type": "Feature",
  "properties": {
    "iso:country":"US",
    "sg:address":"4059 Skippack Pike",
    "sg:city":"Skippack",
    "sg:classifiers":[
        {
            "category":"Insurance",
            "subcategory":"Insurance Agent",
            "type":"Services"
        }
    ],
    "sg:phone":"+1 610 584 4400",
    "sg:postcode":"19474",
    "sg:province":"PA",
    "wof:name":"Colonial Supplemental Ins",
    "wof:placetype":"venue"
},
  "geometry": {"coordinates":[-75.40513199999999,40.227928],"type":"Point"}
}