{
  "type": "Feature",
  "properties": {
    "iso:country":"US",
    "sg:address":"2040 Avenue C",
    "sg:city":"Bethlehem",
    "sg:classifiers":[
        {
            "category":"Wholesale",
            "subcategory":"Machinery & Supplies",
            "type":"Manufacturing & Wholesale Goods"
        }
    ],
    "sg:phone":"+1 610 264 6011",
    "sg:postcode":"18017",
    "sg:province":"PA",
    "sg:tags":[
        "designed",
        "specially"
    ],
    "wof:name":"Fls Us Holdings Inc",
    "wof:placetype":"venue"
},
  "geometry": {"coordinates":[-75.419034,40.657206],"type":"Point"}
}