{
  "type": "Feature",
  "properties": {
    "iso:country":"US",
    "sg:address":"2611 Ellwood Rd",
    "sg:city":"New Castle",
    "sg:classifiers":[
        {
            "category":"Shopping",
            "subcategory":"Used Merchandise",
            "type":"Retail Goods"
        }
    ],
    "sg:phone":"+1 724 652 4877",
    "sg:postcode":"16101",
    "sg:province":"PA",
    "sg:tags":[
        "shop",
        "thrift"
    ],
    "wof:name":"Goodwill Industries",
    "wof:placetype":"venue"
},
  "geometry": {"coordinates":[-80.312251,40.969626],"type":"Point"}
}