{
  "type": "Feature",
  "properties": {
    "iso:country":"US",
    "sg:address":"1628 Croatan Pl",
    "sg:city":"Philadelphia",
    "sg:classifiers":[
        {
            "category":"Banks & Credit Unions",
            "subcategory":"Bank",
            "type":"Services"
        }
    ],
    "sg:phone":"+1 215 755 3000",
    "sg:postcode":"19145",
    "sg:province":"PA",
    "sg:tags":[
        "mortgage",
        "loan",
        "broker",
        "real estate"
    ],
    "wof:name":"Paramount Mortgage Services Co",
    "wof:placetype":"venue"
},
  "geometry": {"coordinates":[-75.176498,39.9118],"type":"Point"}
}