{
  "type": "Feature",
  "properties": {
    "iso:country":"US",
    "sg:address":"115 Mill St",
    "sg:city":"Shinglehouse",
    "sg:classifiers":[
        {
            "category":"Food & Beverages",
            "subcategory":"Groceries & Convenience Stores",
            "type":"Retail Goods"
        }
    ],
    "sg:phone":"+1 814 697 7145",
    "sg:postcode":"16748",
    "sg:province":"PA",
    "sg:tags":[
        "grocer"
    ],
    "wof:name":"Shinglehouse IGA",
    "wof:placetype":"venue"
},
  "geometry": {"coordinates":[-78.187847,41.962595],"type":"Point"}
}