{
  "type": "Feature",
  "properties": {
    "addr:full":"21 W Washington Ln Philadelphia PA 19144",
    "addr:housenumber":"21",
    "addr:postcode":"19144",
    "addr:street":"W Washington Ln",
    "iso:country":"US",
    "sg:address":"21 W Washington Ln",
    "sg:city":"Philadelphia",
    "sg:classifiers":[
        {
            "category":"Organizations",
            "subcategory":"Religious Organization",
            "type":"Services"
        }
    ],
    "sg:phone":"+1 215 843 5599",
    "sg:postcode":"19144",
    "sg:province":"PA",
    "sg:tags":[
        "churches-mennonite"
    ],
    "wof:name":"Germantown Mennonite Church",
    "wof:placetype":"venue"
},
  "geometry": {"coordinates":[-75.18129500000001,40.042836],"type":"Point"}
}