{
  "type": "Feature",
  "properties": {
    "addr:full":"3800 N 5th St Philadelphia PA 19140",
    "addr:housenumber":"3800",
    "addr:postcode":"19140",
    "addr:street":"N 5Th St",
    "iso:country":"US",
    "sg:address":"3800 N 5th St",
    "sg:city":"Philadelphia",
    "sg:classifiers":[
        {
            "category":"Personal",
            "type":"Services"
        },
        {
            "category":"Retail",
            "subcategory":"Auto Repair",
            "type":"Services"
        }
    ],
    "sg:phone":"+1 215 228 1909",
    "sg:postcode":"19140",
    "sg:province":"PA",
    "sg:tags":[
        "body",
        "shop",
        "towing"
    ],
    "wof:name":"P & W Auto Body Shop",
    "wof:placetype":"venue"
},
  "geometry": {"coordinates":[-75.13629899999999,40.009201],"type":"Point"}
}