{
  "type": "Feature",
  "properties": {
    "addr:full":"6801 N 16th St Philadelphia PA 19126",
    "addr:housenumber":"6801",
    "addr:postcode":"19126",
    "addr:street":"N 16Th St",
    "iso:country":"US",
    "sg:address":"6801 N 16th St",
    "sg:city":"Philadelphia",
    "sg:classifiers":[
        {
            "category":"Social Services",
            "type":"Services"
        }
    ],
    "sg:phone":"+1 215 424 1144",
    "sg:postcode":"19126",
    "sg:province":"PA",
    "sg:tags":[
        "organization",
        "welfare"
    ],
    "wof:name":"New Foundations-Oaklane Div",
    "wof:placetype":"venue"
},
  "geometry": {"coordinates":[-75.14413999999999,40.058189],"type":"Point"}
}