{
  "type": "Feature",
  "properties": {
    "iso:country":"US",
    "sg:address":"101 Mine Hill Rd",
    "sg:city":"Schwenksville",
    "sg:classifiers":[
        {
            "category":"Government",
            "subcategory":"Office",
            "type":"Public Place"
        }
    ],
    "sg:phone":"+1 610 287 8723",
    "sg:postcode":"19473",
    "sg:province":"PA",
    "sg:tags":[
        "township",
        "government-city",
        "village"
    ],
    "wof:name":"Town James",
    "wof:placetype":"venue"
},
  "geometry": {"coordinates":[-75.47599,40.262001],"type":"Point"}
}