{
  "type": "Feature",
  "properties": {
    "addr:full":"50 N Pennsylvania Ave Wilkes Barre PA 18701",
    "addr:housenumber":"50",
    "addr:postcode":"18701",
    "addr:street":"N Pennsylvania Ave",
    "iso:country":"US",
    "sg:address":"50 N Pennsylvania Ave",
    "sg:city":"Wilkes Barre",
    "sg:classifiers":[
        {
            "category":"Health Services",
            "subcategory":"Nursing And Care Facility",
            "type":"Services"
        }
    ],
    "sg:phone":"+1   ",
    "sg:postcode":"18701",
    "sg:province":"PA",
    "sg:tags":[
        "skilled"
    ],
    "wof:name":"Beverly",
    "wof:placetype":"venue"
},
  "geometry": {"coordinates":[-75.877888,41.24448],"type":"Point"}
}