{
  "type": "Feature",
  "properties": {
    "addr:full":"3400 Red Lion Rd Philadelphia PA 19114",
    "addr:housenumber":"3400",
    "addr:postcode":"19114",
    "addr:street":"Red Lion Rd",
    "iso:country":"US",
    "sg:address":"3400 Red Lion Rd",
    "sg:city":"Philadelphia",
    "sg:classifiers":[
        {
            "category":"Social Services",
            "type":"Services"
        }
    ],
    "sg:phone":"+1 215 632 7872",
    "sg:postcode":"19114",
    "sg:province":"PA",
    "sg:tags":[
        "organization",
        "welfare"
    ],
    "wof:name":"Resources For Human Dev",
    "wof:placetype":"venue"
},
  "geometry": {"coordinates":[-74.98498600000001,40.074526],"type":"Point"}
}