{
  "type": "Feature",
  "properties": {
    "iso:country":"US",
    "sg:address":"601 Buckingham Dr",
    "sg:city":"Greensburg",
    "sg:classifiers":[
        {
            "category":"Real Estate",
            "subcategory":"Real Estate Agent",
            "type":"Services"
        }
    ],
    "sg:phone":"+1   ",
    "sg:postcode":"15601",
    "sg:province":"PA",
    "sg:tags":[
        "lessor"
    ],
    "wof:name":"Showplace Systems Inc",
    "wof:placetype":"venue"
},
  "geometry": {"coordinates":[-79.516189,40.264638],"type":"Point"}
}