{
  "type": "Feature",
  "properties": {
    "addr:full":"7339 State Rd Philadelphia PA 19136",
    "addr:housenumber":"7339",
    "addr:postcode":"19136",
    "addr:street":"State Rd",
    "iso:country":"US",
    "sg:address":"7339 State Rd",
    "sg:city":"Philadelphia",
    "sg:classifiers":[
        {
            "category":"Building & Trades",
            "subcategory":"Construction",
            "type":"Services"
        }
    ],
    "sg:phone":"+1   ",
    "sg:postcode":"19136",
    "sg:province":"PA",
    "sg:tags":[
        "nonresidential"
    ],
    "wof:name":"Delaware Valley Construction",
    "wof:placetype":"venue"
},
  "geometry": {"coordinates":[-75.029608,40.026634],"type":"Point"}
}