{
  "type": "Feature",
  "properties": {
    "iso:country":"US",
    "sg:address":"33 W 3rd St",
    "sg:city":"Williamsport",
    "sg:classifiers":[
        {
            "category":"Professional",
            "subcategory":"Lawyer & Legal Services",
            "type":"Services"
        }
    ],
    "sg:phone":"+1 570 326 7044",
    "sg:postcode":"17701",
    "sg:province":"PA",
    "sg:tags":[
        "attorney"
    ],
    "wof:name":"Casale & Bonner PC",
    "wof:placetype":"venue"
},
  "geometry": {"coordinates":[-77.002101,41.240512],"type":"Point"}
}