{
  "type": "Feature",
  "properties": {
    "addr:full":"629 N Market St Lancaster PA 17603",
    "addr:housenumber":"629",
    "addr:postcode":"17603",
    "addr:street":"N Market St",
    "iso:country":"US",
    "sg:address":"629 N Market St",
    "sg:city":"Lancaster",
    "sg:classifiers":[
        {
            "category":"Organizations",
            "subcategory":"Non-profit Organization",
            "type":"Services"
        }
    ],
    "sg:phone":"+1 717 299 5054",
    "sg:postcode":"17603",
    "sg:province":"PA",
    "sg:tags":[
        "information",
        "alcoholism",
        "treatment"
    ],
    "wof:name":"Therapy Co",
    "wof:placetype":"venue"
},
  "geometry": {"coordinates":[-76.308639,40.04844],"type":"Point"}
}