{
  "type": "Feature",
  "properties": {
    "iso:country":"US",
    "sg:address":"101 E King St",
    "sg:city":"Malvern",
    "sg:classifiers":[
        {
            "category":"Building & Trades",
            "subcategory":"Construction",
            "type":"Services"
        }
    ],
    "sg:phone":"+1 610 647 4996",
    "sg:postcode":"19355",
    "sg:province":"PA",
    "sg:tags":[
        "contractor"
    ],
    "wof:name":"Unefab Structures Inc",
    "wof:placetype":"venue"
},
  "geometry": {"coordinates":[-75.51301100000001,40.036747],"type":"Point"}
}