{
  "type": "Feature",
  "properties": {
    "iso:country":"US",
    "sg:address":"416 S Main St",
    "sg:city":"Greensburg",
    "sg:classifiers":[
        {
            "category":"Building & Trades",
            "subcategory":"Construction",
            "type":"Services"
        }
    ],
    "sg:phone":"+1 724 838 4345",
    "sg:postcode":"15601",
    "sg:province":"PA",
    "sg:tags":[
        "contractor",
        "mechanical"
    ],
    "wof:name":"City Mechanic Garage",
    "wof:placetype":"venue"
},
  "geometry": {"coordinates":[-79.543156,40.299223],"type":"Point"}
}