{
  "type": "Feature",
  "properties": {
    "iso:country":"US",
    "sg:address":"406 Greenville Rd",
    "sg:city":"Denver",
    "sg:classifiers":[
        {
            "category":"Retail",
            "subcategory":"Auto Repair",
            "type":"Services"
        }
    ],
    "sg:phone":"+1 717 335 2206",
    "sg:postcode":"17517",
    "sg:province":"PA",
    "wof:name":"Akron Auto Service",
    "wof:placetype":"venue"
},
  "geometry": {"coordinates":[-76.150606,40.258857],"type":"Point"}
}