{
  "type": "Feature",
  "properties": {
    "iso:country":"US",
    "sg:address":"716 Southwinds Dr",
    "sg:city":"Bryn Mawr",
    "sg:classifiers":[
        {
            "category":"Building & Trades",
            "subcategory":"Landscaping Services",
            "type":"Services"
        }
    ],
    "sg:phone":"+1   ",
    "sg:postcode":"19010",
    "sg:province":"PA",
    "wof:name":"Fran Jungreis Garden Design",
    "wof:placetype":"venue"
},
  "geometry": {"coordinates":[-75.346188,40.005657],"type":"Point"}
}