{
  "type": "Feature",
  "properties": {
    "addr:full":"134 E Franklin St Greencastle PA 17225",
    "addr:housenumber":"134",
    "addr:postcode":"17225",
    "addr:street":"E Franklin St",
    "iso:country":"US",
    "sg:address":"134 E Franklin St",
    "sg:city":"Greencastle",
    "sg:classifiers":[
        {
            "category":"Building & Trades",
            "subcategory":"Construction",
            "type":"Services"
        }
    ],
    "sg:phone":"+1 717 597 1064",
    "sg:postcode":"17225",
    "sg:province":"PA",
    "sg:tags":[
        "equipment",
        "supply",
        "drywall",
        "contractor"
    ],
    "wof:name":"Harnish Drywall",
    "wof:placetype":"venue"
},
  "geometry": {"coordinates":[-77.72573300000001,39.788225],"type":"Point"}
}