{
  "type": "Feature",
  "properties": {
    "addr:full":"1375 Argyle Way Bensalem PA 19020",
    "addr:housenumber":"1375",
    "addr:postcode":"19020",
    "addr:street":"Argyle Way",
    "iso:country":"US",
    "sg:address":"1375 Argyle Way",
    "sg:city":"Bensalem",
    "sg:classifiers":[
        {
            "category":"Taxi",
            "type":"Transportation"
        }
    ],
    "sg:phone":"+1   ",
    "sg:postcode":"19020",
    "sg:province":"PA",
    "sg:tags":[
        "taxicab"
    ],
    "wof:name":"A & I Cab Co",
    "wof:placetype":"venue"
},
  "geometry": {"coordinates":[-74.917366,40.114989],"type":"Point"}
}