{
  "type": "Feature",
  "properties": {
    "iso:country":"US",
    "sg:address":"708 N Blakely St",
    "sg:city":"Scranton",
    "sg:classifiers":[
        {
            "category":"Ice Cream",
            "type":"Food & Drink"
        }
    ],
    "sg:menulink":"http://www.allmenus.com/pa/dunmore/98906-friendlys/menu/",
    "sg:phone":"+1 570 961 1565",
    "sg:postcode":"18512",
    "sg:province":"PA",
    "sg:tags":[
        "burger",
        "american"
    ],
    "wof:name":"Friendly's",
    "wof:placetype":"venue"
},
  "geometry": {"coordinates":[-75.624494,41.427681],"type":"Point"}
}