{
  "type": "Feature",
  "properties": {
    "iso:country":"US",
    "sg:address":"1713 State Rte 228",
    "sg:city":"Cranberry Twp",
    "sg:classifiers":[
        {
            "category":"Shopping",
            "subcategory":"Jewelry",
            "type":"Retail Goods"
        }
    ],
    "sg:phone":"+1 724 772 2300",
    "sg:postcode":"16066",
    "sg:province":"PA",
    "sg:tags":[
        "jeweler"
    ],
    "wof:name":"Allegheny Diamond Mine",
    "wof:placetype":"venue"
},
  "geometry": {"coordinates":[-80.087548,40.685648],"type":"Point"}
}