{
  "type": "Feature",
  "properties": {
    "iso:country":"US",
    "sg:address":"2100 Wharton St",
    "sg:city":"Pittsburgh",
    "sg:classifiers":[
        {
            "category":"Building & Trades",
            "subcategory":"Plumbing",
            "type":"Services"
        }
    ],
    "sg:phone":"+1 412 697 0146",
    "sg:postcode":"15203",
    "sg:province":"PA",
    "sg:tags":[
        "product",
        "management",
        "energy",
        "system"
    ],
    "wof:name":"Global Energy Solutions",
    "wof:placetype":"venue"
},
  "geometry": {"coordinates":[-79.97445999999999,40.430209],"type":"Point"}
}