{
  "type": "Feature",
  "properties": {
    "addr:full":"67 Almshouse Rd Richboro PA 18954",
    "addr:housenumber":"67",
    "addr:postcode":"18954",
    "addr:street":"Almshouse Rd",
    "iso:country":"US",
    "sg:address":"67 Almshouse Rd",
    "sg:city":"Richboro",
    "sg:classifiers":[
        {
            "category":"Personal",
            "subcategory":"Beauty Salon",
            "type":"Services"
        }
    ],
    "sg:phone":"+1 215 357 9622",
    "sg:postcode":"18954",
    "sg:province":"PA",
    "sg:tags":[
        "shop"
    ],
    "wof:name":"Hilights Hair Salon",
    "wof:placetype":"venue"
},
  "geometry": {"coordinates":[-75.01235800000001,40.215866],"type":"Point"}
}