{
  "type": "Feature",
  "properties": {
    "iso:country":"US",
    "sg:address":"2020 Derry St",
    "sg:city":"Harrisburg",
    "sg:classifiers":[
        {
            "category":"Shopping",
            "subcategory":"Gifts & Souvenirs",
            "type":"Retail Goods"
        }
    ],
    "sg:phone":"+1   ",
    "sg:postcode":"17104",
    "sg:province":"PA",
    "wof:name":"J W Ceramics",
    "wof:placetype":"venue"
},
  "geometry": {"coordinates":[-76.855424,40.261098],"type":"Point"}
}