{
  "type": "Feature",
  "properties": {
    "iso:country":"US",
    "sg:address":"9635 Milnor St",
    "sg:city":"Philadelphia",
    "sg:classifiers":[
        {
            "category":"Recreation",
            "type":"Entertainment"
        }
    ],
    "sg:phone":"+1 215 637 9900",
    "sg:postcode":"19114",
    "sg:province":"PA",
    "sg:tags":[
        "marina",
        "club",
        "membership"
    ],
    "wof:name":"Delaware River Yacht Club",
    "wof:placetype":"venue"
},
  "geometry": {"coordinates":[-74.980321,40.050554],"type":"Point"}
}