{
  "type": "Feature",
  "properties": {
    "addr:full":"1606 Glen Willow Rd Avondale PA 19311",
    "addr:housenumber":"1606",
    "addr:postcode":"19311",
    "addr:street":"Glen Willow Rd",
    "iso:country":"US",
    "sg:address":"1606 Glen Willow Rd",
    "sg:city":"Avondale",
    "sg:classifiers":[
        {
            "category":"Place Of Worship",
            "subcategory":"Church",
            "type":"Public Place"
        },
        {
            "category":"Place Of Worship",
            "type":"Public Place"
        }
    ],
    "sg:phone":"+1 610 268 2088",
    "sg:postcode":"19311",
    "sg:province":"PA",
    "sg:tags":[
        "testament",
        "christ-new",
        "christ",
        "churches-church"
    ],
    "sg:website":"http://www.avondalechristians.com",
    "wof:name":"Avondale Church Of Christ Inc",
    "wof:placetype":"venue"
},
  "geometry": {"coordinates":[-75.789412,39.835835],"type":"Point"}
}