{
  "type": "Feature",
  "properties": {
    "addr:full":"1360 W 3rd St Williamsport PA 17701",
    "addr:housenumber":"1360",
    "addr:postcode":"17701",
    "addr:street":"W 3Rd St",
    "iso:country":"US",
    "sg:address":"1360 W 3rd St",
    "sg:city":"Williamsport",
    "sg:classifiers":[
        {
            "category":"Building & Trades",
            "subcategory":"Plumbing",
            "type":"Services"
        }
    ],
    "sg:phone":"+1 570 322 7606",
    "sg:postcode":"17701",
    "sg:province":"PA",
    "sg:tags":[
        "heat",
        "pump"
    ],
    "wof:name":"Sun Spot Heating & Cooling",
    "wof:placetype":"venue"
},
  "geometry": {"coordinates":[-77.033011,41.237321],"type":"Point"}
}