{
  "type": "Feature",
  "properties": {
    "iso:country":"US",
    "sg:address":"11619 Penn Hills Dr",
    "sg:city":"Pittsburgh",
    "sg:classifiers":[
        {
            "category":"Personal",
            "subcategory":"Beauty Salon",
            "type":"Services"
        }
    ],
    "sg:phone":"+1 412 731 0600",
    "sg:postcode":"15235",
    "sg:province":"PA",
    "wof:name":"Sir William Hess Fashions",
    "wof:placetype":"venue"
},
  "geometry": {"coordinates":[-79.82712600000001,40.464971],"type":"Point"}
}