{
  "type": "Feature",
  "properties": {
    "iso:country":"US",
    "sg:address":"559 Hopkins Mill Rd",
    "sg:city":"Quarryville",
    "sg:classifiers":[
        {
            "category":"Health Services",
            "subcategory":"Dentist",
            "type":"Services"
        }
    ],
    "sg:phone":"+1 717 786 1678",
    "sg:postcode":"17566",
    "sg:province":"PA",
    "wof:name":"Thos L Regan Dntst",
    "wof:placetype":"venue"
},
  "geometry": {"coordinates":[-76.20766,39.863942],"type":"Point"}
}