{
  "type": "Feature",
  "properties": {
    "iso:country":"US",
    "sg:address":"901 Conshohocken Rd",
    "sg:city":"Conshohocken",
    "sg:classifiers":[
        {
            "category":"Retail",
            "subcategory":"Auto Rental",
            "type":"Services"
        }
    ],
    "sg:phone":"+1 610 828 7930",
    "sg:postcode":"19428",
    "sg:province":"PA",
    "sg:tags":[
        "truck"
    ],
    "wof:name":"Gordon Truck Leasing",
    "wof:placetype":"venue"
},
  "geometry": {"coordinates":[-75.31676,40.090289],"type":"Point"}
}