{
  "type": "Feature",
  "properties": {
    "addr:full":"4 Bower Hill Rd Pittsburgh PA 15228",
    "addr:housenumber":"4",
    "addr:postcode":"15228",
    "addr:street":"Bower Hill Rd",
    "iso:country":"US",
    "sg:address":"4 Bower Hill Rd",
    "sg:city":"Pittsburgh",
    "sg:classifiers":[
        {
            "category":"Bars & Pubs",
            "type":"Food & Drink"
        }
    ],
    "sg:phone":"+1 412 561 1722",
    "sg:postcode":"15228",
    "sg:province":"PA",
    "sg:tags":[
        "tavern",
        "drinking"
    ],
    "wof:name":"Korner The Pub & Deli",
    "wof:placetype":"venue"
},
  "geometry": {"coordinates":[-80.043938,40.386921],"type":"Point"}
}