{
  "type": "Feature",
  "properties": {
    "addr:full":"104 Edward Dr Bellefonte PA 16823",
    "addr:housenumber":"104",
    "addr:postcode":"16823",
    "addr:street":"Edward Dr",
    "iso:country":"US",
    "sg:address":"104 Edward Dr",
    "sg:city":"Bellefonte",
    "sg:classifiers":[
        {
            "category":"Building & Trades",
            "subcategory":"Electrical",
            "type":"Services"
        }
    ],
    "sg:phone":"+1   ",
    "sg:postcode":"16823",
    "sg:province":"PA",
    "sg:tags":[
        "electrical",
        "contractor"
    ],
    "wof:name":"Riglin Frank Co",
    "wof:placetype":"venue"
},
  "geometry": {"coordinates":[-77.809997,40.898555],"type":"Point"}
}