{
  "type": "Feature",
  "properties": {
    "iso:country":"US",
    "sg:address":"1175 8th Ave",
    "sg:city":"Bethlehem",
    "sg:classifiers":[
        {
            "category":"Communications",
            "type":"Services"
        }
    ],
    "sg:phone":"+1   ",
    "sg:postcode":"18018",
    "sg:province":"PA",
    "sg:tags":[
        "communication"
    ],
    "wof:name":"EDS",
    "wof:placetype":"venue"
},
  "geometry": {"coordinates":[-75.395078,40.629779],"type":"Point"}
}