{
  "type": "Feature",
  "properties": {
    "iso:country":"US",
    "sg:address":"1623 E 38th St",
    "sg:city":"Erie",
    "sg:classifiers":[
        {
            "category":"Banks & Credit Unions",
            "subcategory":"Bank",
            "type":"Services"
        }
    ],
    "sg:phone":"+1   ",
    "sg:postcode":"16510",
    "sg:province":"PA",
    "sg:tags":[
        "state"
    ],
    "wof:name":"Erie Gen Elc Employee F C U",
    "wof:placetype":"venue"
},
  "geometry": {"coordinates":[-80.033118,42.114612],"type":"Point"}
}