{
  "type": "Feature",
  "properties": {
    "iso:country":"US",
    "sg:address":"2541 Haverford Rd",
    "sg:city":"Ardmore",
    "sg:classifiers":[
        {
            "category":"Wholesale",
            "subcategory":"Painting Supplies",
            "type":"Manufacturing & Wholesale Goods"
        },
        {
            "category":"Home & Garden",
            "subcategory":"Hardware",
            "type":"Retail Goods"
        },
        {
            "category":"Home & Garden",
            "subcategory":"Building Materials",
            "type":"Retail Goods"
        },
        {
            "category":"Manufacturing",
            "subcategory":"Tools & Machinery",
            "type":"Manufacturing & Wholesale Goods"
        }
    ],
    "sg:phone":"+1 610 400 3694",
    "sg:postcode":"19003",
    "sg:province":"PA",
    "sg:tags":[
        "paint",
        "store",
        "improvement"
    ],
    "sg:website":"http://philadelphia.citysearch.com/profile/external/8902424/ardmore_pa/dmi_home_supply_rental_center.html?publisher=yellowpages&reference_id=15&placement=ypwebsitemip",
    "wof:name":"DMI Home Supply & Rental Center",
    "wof:placetype":"venue"
},
  "geometry": {"coordinates":[-75.30015299999999,39.995044],"type":"Point"}
}