{
  "type": "Feature",
  "properties": {
    "iso:country":"US",
    "sg:address":"2920 Forrest Ave",
    "sg:city":"Bensalem",
    "sg:classifiers":[
        {
            "category":"Professional",
            "type":"Services"
        }
    ],
    "sg:phone":"+1 215 638 0211",
    "sg:postcode":"19020",
    "sg:province":"PA",
    "sg:tags":[
        "establishment"
    ],
    "wof:name":"ACI",
    "wof:placetype":"venue"
},
  "geometry": {"coordinates":[-74.93862900000001,40.0879],"type":"Point"}
}