{
  "type": "Feature",
  "properties": {
    "iso:country":"US",
    "sg:address":"1446 Auction Rd",
    "sg:city":"Manheim",
    "sg:classifiers":[
        {
            "category":"Science Facility",
            "type":"Public Place"
        }
    ],
    "sg:phone":"+1 717 653 4728",
    "sg:postcode":"17545",
    "sg:province":"PA",
    "sg:tags":[
        "development",
        "laboratories-research"
    ],
    "sg:website":"http://www.an.psu.edu",
    "wof:name":"Southeastern Field Res Lab",
    "wof:placetype":"venue"
},
  "geometry": {"coordinates":[-76.426597,40.1167],"type":"Point"}
}