{
  "type": "Feature",
  "properties": {
    "addr:full":"597 Storm Rd Loretto PA 15940",
    "addr:housenumber":"597",
    "addr:postcode":"15940",
    "addr:street":"Storm Rd",
    "iso:country":"US",
    "sg:address":"597 Storm Rd",
    "sg:city":"Loretto",
    "sg:classifiers":[
        {
            "category":"Farming",
            "subcategory":"Livestock Farm",
            "type":"Manufacturing & Wholesale Goods"
        }
    ],
    "sg:phone":"+1   ",
    "sg:postcode":"15940",
    "sg:province":"PA",
    "sg:tags":[
        "beef",
        "feedlot",
        "cattle"
    ],
    "wof:name":"Robert Storm",
    "wof:placetype":"venue"
},
  "geometry": {"coordinates":[-78.60779599999999,40.543016],"type":"Point"}
}