{
  "type": "Feature",
  "properties": {
    "iso:country":"US",
    "sg:address":"510 US Hwy 209",
    "sg:city":"Milford",
    "sg:classifiers":[
        {
            "category":"Health Services",
            "subcategory":"Doctor",
            "type":"Services"
        }
    ],
    "sg:phone":"+1 570 296 1003",
    "sg:postcode":"18337",
    "sg:province":"PA",
    "sg:tags":[
        "physician",
        "surgeon",
        "medical"
    ],
    "wof:name":"West Orange Medical Inc",
    "wof:placetype":"venue"
},
  "geometry": {"coordinates":[-74.799458,41.317717],"type":"Point"}
}