{
  "type": "Feature",
  "properties": {
    "iso:country":"US",
    "sg:address":"6301 Castor Ave",
    "sg:city":"Philadelphia",
    "sg:classifiers":[
        {
            "category":"Personal",
            "type":"Services"
        },
        {
            "category":"Retail",
            "subcategory":"Auto Rental",
            "type":"Services"
        },
        {
            "category":"Freight",
            "type":"Transportation"
        }
    ],
    "sg:phone":"+1 215 535 0317",
    "sg:postcode":"19149",
    "sg:province":"PA",
    "sg:tags":[
        "renting",
        "full",
        "leasing",
        "storage",
        "trucking",
        "truck",
        "mover",
        "local",
        "trailer"
    ],
    "sg:website":"http://www.uhaul.com",
    "wof:name":"U-Haul Neighborhood Dealer - Frank Liquori Trucking&Rd Svc",
    "wof:placetype":"venue"
},
  "geometry": {"coordinates":[-75.078644,40.038212],"type":"Point"}
}