{
  "type": "Feature",
  "properties": {
    "iso:country":"US",
    "sg:address":"439 Main St",
    "sg:city":"Darby",
    "sg:classifiers":[
        {
            "category":"Manufacturing",
            "subcategory":"Metals",
            "type":"Manufacturing & Wholesale Goods"
        },
        {
            "category":"Manufacturing",
            "subcategory":"Tools & Machinery",
            "type":"Manufacturing & Wholesale Goods"
        }
    ],
    "sg:phone":"+1 610 284 7990",
    "sg:postcode":"19023",
    "sg:province":"PA",
    "sg:tags":[
        "supply",
        "ruler",
        "engraver",
        "mfg",
        "photoengraving",
        "drawing"
    ],
    "wof:name":"Theodore Alteneder & Son Inc",
    "wof:placetype":"venue"
},
  "geometry": {"coordinates":[-75.253856,39.917414],"type":"Point"}
}