{
  "type": "Feature",
  "properties": {
    "iso:country":"US",
    "sg:address":"10409 Washington Ave",
    "sg:city":"Irwin",
    "sg:classifiers":[
        {
            "category":"Personal",
            "subcategory":"Beauty Salon",
            "type":"Services"
        }
    ],
    "sg:phone":"+1 724 863 0397",
    "sg:postcode":"15642",
    "sg:province":"PA",
    "wof:name":"Watson Pamela Beauty Salon",
    "wof:placetype":"venue"
},
  "geometry": {"coordinates":[-79.706444,40.33503],"type":"Point"}
}