{
  "type": "Feature",
  "properties": {
    "iso:country":"US",
    "sg:address":"12777 Washington Township Blvd",
    "sg:city":"Waynesboro",
    "sg:classifiers":[
        {
            "category":"Shopping",
            "subcategory":"Bicycles & Sporting Goods",
            "type":"Retail Goods"
        }
    ],
    "sg:phone":"+1 717 765 6804",
    "sg:postcode":"17268",
    "sg:province":"PA",
    "sg:website":"www.olympiasports.net",
    "wof:name":"Olympia Sports Inc",
    "wof:placetype":"venue"
},
  "geometry": {"coordinates":[-77.526039,39.741522],"type":"Point"}
}