{
  "type": "Feature",
  "properties": {
    "iso:country":"US",
    "sg:address":"2115 Stefko Blvd",
    "sg:city":"Bethlehem",
    "sg:classifiers":[
        {
            "category":"Restaurant",
            "type":"Food & Drink"
        }
    ],
    "sg:phone":"+1 610 419 6333",
    "sg:postcode":"18017",
    "sg:province":"PA",
    "wof:name":"Deli Cafe Sunnys",
    "wof:placetype":"venue"
},
  "geometry": {"coordinates":[-75.346019,40.643048],"type":"Point"}
}