{
  "type": "Feature",
  "properties": {
    "iso:country":"US",
    "sg:address":"541 Flat Rock Rd",
    "sg:city":"Apollo",
    "sg:classifiers":[
        {
            "category":"Retail",
            "subcategory":"Animal Services",
            "type":"Services"
        }
    ],
    "sg:phone":"+1 724 697 4040",
    "sg:postcode":"15613",
    "sg:province":"PA",
    "sg:tags":[
        "pet",
        "grooming",
        "washing"
    ],
    "wof:name":"Amy's Golden Touch Kennels",
    "wof:placetype":"venue"
},
  "geometry": {"coordinates":[-79.46363599999999,40.578762],"type":"Point"}
}