{
  "type": "Feature",
  "properties": {
    "addr:full":"103 Rosewood Dr Aliquippa PA 15001",
    "addr:housenumber":"103",
    "addr:postcode":"15001",
    "addr:street":"Rosewood Dr",
    "iso:country":"US",
    "sg:address":"103 Rosewood Dr",
    "sg:city":"Aliquippa",
    "sg:classifiers":[
        {
            "category":"Building & Trades",
            "subcategory":"Construction",
            "type":"Services"
        }
    ],
    "sg:phone":"+1   ",
    "sg:postcode":"15001",
    "sg:province":"PA",
    "sg:tags":[
        "hanging",
        "contractor"
    ],
    "wof:name":"Ep Painting Inc",
    "wof:placetype":"venue"
},
  "geometry": {"coordinates":[-80.29347799999999,40.640915],"type":"Point"}
}