{
  "type": "Feature",
  "properties": {
    "iso:country":"US",
    "sg:address":"99 November Dr",
    "sg:city":"Camp Hill",
    "sg:classifiers":[
        {
            "category":"Professional",
            "subcategory":"Accounting & Tax Preparation",
            "type":"Services"
        }
    ],
    "sg:phone":"+1   ",
    "sg:postcode":"17011",
    "sg:province":"PA",
    "wof:name":"Robert L Haar CPA",
    "wof:placetype":"venue"
},
  "geometry": {"coordinates":[-76.936958,40.233265],"type":"Point"}
}