{
  "type": "Feature",
  "properties": {
    "addr:full":"7 N River St Plains PA 18705",
    "addr:housenumber":"7",
    "addr:postcode":"18705",
    "addr:street":"N River St",
    "iso:country":"US",
    "sg:address":"7 N River St",
    "sg:city":"Plains",
    "sg:classifiers":[
        {
            "category":"Shopping",
            "subcategory":"Pharmacy",
            "type":"Retail Goods"
        }
    ],
    "sg:phone":"+1 570 824 7242",
    "sg:postcode":"18705",
    "sg:province":"PA",
    "wof:name":"Rite Aid Pharmacy",
    "wof:placetype":"venue"
},
  "geometry": {"coordinates":[-75.85629299999999,41.278817],"type":"Point"}
}