{
  "type": "Feature",
  "properties": {
    "iso:country":"US",
    "sg:address":"25 S Main St",
    "sg:city":"Yardley",
    "sg:classifiers":[
        {
            "category":"Professional",
            "subcategory":"Management & Consulting",
            "type":"Services"
        }
    ],
    "sg:phone":"+1 215 736 0570",
    "sg:postcode":"19067",
    "sg:province":"PA",
    "sg:tags":[
        "personnel",
        "consultant"
    ],
    "wof:name":"Yardley Staffing",
    "wof:placetype":"venue"
},
  "geometry": {"coordinates":[-74.83617,40.240473],"type":"Point"}
}