{
  "type": "Feature",
  "properties": {
    "addr:full":"2299 Brodhead Rd Ste N Bethlehem PA 18020",
    "addr:housenumber":"2299",
    "addr:postcode":"18020",
    "addr:street":"Brodhead Rd Ste N",
    "iso:country":"US",
    "sg:address":"2299 Brodhead Rd Ste N",
    "sg:city":"Bethlehem",
    "sg:classifiers":[
        {
            "category":"Health Services",
            "subcategory":"Doctor",
            "type":"Services"
        }
    ],
    "sg:phone":"+1 610 882 2052",
    "sg:postcode":"18020",
    "sg:province":"PA",
    "wof:name":"Gonzalez Abel A MD",
    "wof:placetype":"venue"
},
  "geometry": {"coordinates":[-75.372035,40.677816],"type":"Point"}
}