{
  "type": "Feature",
  "properties": {
    "iso:country":"US",
    "sg:address":"19 Line Rd",
    "sg:city":"Malvern",
    "sg:classifiers":[
        {
            "category":"Wholesale",
            "subcategory":"Stationery",
            "type":"Manufacturing & Wholesale Goods"
        }
    ],
    "sg:phone":"+1 610 644 3520",
    "sg:postcode":"19355",
    "sg:province":"PA",
    "sg:tags":[
        "packaging",
        "material"
    ],
    "wof:name":"Philips Associates",
    "wof:placetype":"venue"
},
  "geometry": {"coordinates":[-75.54221,40.026117],"type":"Point"}
}