{
  "type": "Feature",
  "properties": {
    "addr:full":"3527 Washington Ln Pittsburgh PA 15237",
    "addr:housenumber":"3527",
    "addr:postcode":"15237",
    "addr:street":"Washington Ln",
    "iso:country":"US",
    "sg:address":"3527 Washington Ln",
    "sg:city":"Pittsburgh",
    "sg:classifiers":[
        {
            "category":"Deli",
            "type":"Food & Drink"
        },
        {
            "category":"Bagels",
            "type":"Food & Drink"
        },
        {
            "category":"Coffee & Tea",
            "type":"Food & Drink"
        }
    ],
    "sg:menulink":"http://www.allmenus.com/pa/ross/6147-brueggers/menu/",
    "sg:phone":"+1 724 941 3725",
    "sg:postcode":"15237",
    "sg:province":"PA",
    "sg:tags":[
        "wrap",
        "soup",
        "american",
        "sandwich",
        "salad"
    ],
    "wof:name":"Bruegger's",
    "wof:placetype":"venue"
},
  "geometry": {"coordinates":[-80.06404499999999,40.546333],"type":"Point"}
}