{
  "type": "Feature",
  "properties": {
    "iso:country":"US",
    "sg:address":"500 Business Center Dr",
    "sg:city":"Pittsburgh",
    "sg:classifiers":[
        {
            "category":"Utilities",
            "subcategory":"Telephone",
            "type":"Services"
        },
        {
            "category":"Communications",
            "type":"Services"
        },
        {
            "category":"Wholesale",
            "subcategory":"Computers",
            "type":"Manufacturing & Wholesale Goods"
        }
    ],
    "sg:phone":"+1 412 788 1945",
    "sg:postcode":"15205",
    "sg:province":"PA",
    "sg:tags":[
        "equipment",
        "data",
        "system"
    ],
    "sg:website":"http://www.perfcomcat.com",
    "wof:name":"Performance Communication",
    "wof:placetype":"venue"
},
  "geometry": {"coordinates":[-80.138802,40.4342],"type":"Point"}
}