{
  "type": "Feature",
  "properties": {
    "addr:full":"13848 Conneaut Lake Rd Conneaut Lake PA 16316",
    "addr:housenumber":"13848",
    "addr:postcode":"16316",
    "addr:street":"Conneaut Lake Rd",
    "iso:country":"US",
    "sg:address":"13848 Conneaut Lake Rd",
    "sg:city":"Conneaut Lake",
    "sg:classifiers":[
        {
            "category":"Health Services",
            "subcategory":"Chiropractor",
            "type":"Services"
        }
    ],
    "sg:phone":"+1 814 382 7500",
    "sg:postcode":"16316",
    "sg:province":"PA",
    "wof:name":"Watson Chiropractic Ctr",
    "wof:placetype":"venue"
},
  "geometry": {"coordinates":[-80.26165899999999,41.613811],"type":"Point"}
}