{
  "type": "Feature",
  "properties": {
    "addr:full":"547 Furry Dr New Enterprise PA 16664",
    "addr:housenumber":"547",
    "addr:postcode":"16664",
    "addr:street":"Furry Dr",
    "iso:country":"US",
    "sg:address":"547 Furry Dr",
    "sg:city":"New Enterprise",
    "sg:phone":"+1   ",
    "sg:postcode":"16664",
    "sg:province":"PA",
    "sg:tags":[
        "farm",
        "field",
        "corn",
        "crop"
    ],
    "wof:name":"Rufus Zimmerman",
    "wof:placetype":"venue"
},
  "geometry": {"coordinates":[-78.417478,40.210783],"type":"Point"}
}