{
  "type": "Feature",
  "properties": {
    "iso:country":"US",
    "sg:address":"211 Desmond St",
    "sg:city":"Sayre",
    "sg:classifiers":[
        {
            "category":"Shopping",
            "subcategory":"Jewelry",
            "type":"Retail Goods"
        }
    ],
    "sg:phone":"+1 570 888 9604",
    "sg:postcode":"18840",
    "sg:province":"PA",
    "sg:tags":[
        "jeweler"
    ],
    "wof:name":"Reagan's Jewelry",
    "wof:placetype":"venue"
},
  "geometry": {"coordinates":[-76.51530099999999,41.980358],"type":"Point"}
}