{
  "type": "Feature",
  "properties": {
    "addr:full":"151 E White Bear Dr Summit Hill PA 18250",
    "addr:housenumber":"151",
    "addr:postcode":"18250",
    "addr:street":"E White Bear Dr",
    "iso:country":"US",
    "sg:address":"151 E White Bear Dr",
    "sg:city":"Summit Hill",
    "sg:classifiers":[
        {
            "category":"Organizations",
            "subcategory":"Community Association",
            "type":"Services"
        }
    ],
    "sg:phone":"+1 570 645 8597",
    "sg:postcode":"18250",
    "sg:province":"PA",
    "sg:tags":[
        "environmental",
        "org"
    ],
    "wof:name":"Carbon County Environmental",
    "wof:placetype":"venue"
},
  "geometry": {"coordinates":[-75.83068,40.833831],"type":"Point"}
}