{
  "type": "Feature",
  "properties": {
    "addr:full":"236 Powell Ln Upper Darby PA 19082",
    "addr:housenumber":"236",
    "addr:postcode":"19082",
    "addr:street":"Powell Ln",
    "iso:country":"US",
    "sg:address":"236 Powell Ln",
    "sg:city":"Upper Darby",
    "sg:classifiers":[
        {
            "category":"Real Estate",
            "subcategory":"Developer",
            "type":"Services"
        }
    ],
    "sg:phone":"+1 610 352 7963",
    "sg:postcode":"19082",
    "sg:province":"PA",
    "sg:tags":[
        "funeral",
        "cemetery"
    ],
    "wof:name":"Friends S W Burial Grounds",
    "wof:placetype":"venue"
},
  "geometry": {"coordinates":[-75.252098,39.9562],"type":"Point"}
}