{
  "type": "Feature",
  "properties": {
    "addr:full":"1350 N 10th St Philadelphia PA 19122",
    "addr:housenumber":"1350",
    "addr:postcode":"19122",
    "addr:street":"N 10Th St",
    "iso:country":"US",
    "sg:address":"1350 N 10th St",
    "sg:city":"Philadelphia",
    "sg:classifiers":[
        {
            "category":"Real Estate",
            "subcategory":"Real Estate Agent",
            "type":"Services"
        }
    ],
    "sg:phone":"+1 215 684 4644",
    "sg:postcode":"19122",
    "sg:province":"PA",
    "sg:tags":[
        "government-united",
        "housing",
        "authority",
        "state"
    ],
    "wof:name":"Philadelphia Housing Authority Harrison Plaza",
    "wof:placetype":"venue"
},
  "geometry": {"coordinates":[-75.152055,39.972972],"type":"Point"}
}