{
  "type": "Feature",
  "properties": {
    "iso:country":"US",
    "sg:address":"813 N 64th St",
    "sg:city":"Philadelphia",
    "sg:classifiers":[
        {
            "category":"Professional",
            "type":"Services"
        }
    ],
    "sg:phone":"+1   ",
    "sg:postcode":"19151",
    "sg:province":"PA",
    "wof:name":"Quadran Estates",
    "wof:placetype":"venue"
},
  "geometry": {"coordinates":[-75.247972,39.976385],"type":"Point"}
}