{
  "type": "Feature",
  "properties": {
    "iso:country":"US",
    "sg:address":"1254 Youngsburg Rd",
    "sg:city":"Coatesville",
    "sg:classifiers":[
        {
            "category":"Building & Trades",
            "subcategory":"Construction",
            "type":"Services"
        }
    ],
    "sg:phone":"+1 610 383 4771",
    "sg:postcode":"19320",
    "sg:province":"PA",
    "sg:tags":[
        "home",
        "builder"
    ],
    "wof:name":"Gemcraft Homes Inc",
    "wof:placetype":"venue"
},
  "geometry": {"coordinates":[-75.82188600000001,39.963957],"type":"Point"}
}