{
  "type": "Feature",
  "properties": {
    "iso:country":"US",
    "sg:address":"235 Marlboro Dr",
    "sg:city":"New Kensington",
    "sg:classifiers":[
        {
            "category":"Shopping",
            "subcategory":"Florist",
            "type":"Retail Goods"
        }
    ],
    "sg:phone":"+1 724 337 7309",
    "sg:postcode":"15068",
    "sg:province":"PA",
    "wof:name":"William C Wise",
    "wof:placetype":"venue"
},
  "geometry": {"coordinates":[-79.746375,40.579548],"type":"Point"}
}