{
  "type": "Feature",
  "properties": {
    "iso:country":"US",
    "sg:address":"8622 New Falls Rd",
    "sg:city":"Levittown",
    "sg:classifiers":[
        {
            "category":"Shopping",
            "subcategory":"Music",
            "type":"Retail Goods"
        }
    ],
    "sg:phone":"+1 215 945 9423",
    "sg:postcode":"19054",
    "sg:province":"PA",
    "sg:tags":[
        "compact",
        "record",
        "disc",
        "tape"
    ],
    "wof:name":"Forever Records",
    "wof:placetype":"venue"
},
  "geometry": {"coordinates":[-74.83128000000001,40.174155],"type":"Point"}
}