{
  "type": "Feature",
  "properties": {
    "addr:full":"1730 Vultee St Allentown PA 18103",
    "addr:housenumber":"1730",
    "addr:postcode":"18103",
    "addr:street":"Vultee St",
    "iso:country":"US",
    "sg:address":"1730 Vultee St",
    "sg:city":"Allentown",
    "sg:classifiers":[
        {
            "category":"Personal",
            "subcategory":"Adult",
            "type":"Services"
        }
    ],
    "sg:phone":"+1 610 791 3111",
    "sg:postcode":"18103",
    "sg:province":"PA",
    "sg:tags":[
        "tour",
        "escort"
    ],
    "sg:website":"www.medescort.com",
    "wof:name":"Medescort International Inc",
    "wof:placetype":"venue"
},
  "geometry": {"coordinates":[-75.487099,40.5741],"type":"Point"}
}