{
  "type": "Feature",
  "properties": {
    "iso:country":"US",
    "sg:address":"3751 Ridge Ave",
    "sg:city":"Philadelphia",
    "sg:classifiers":[
        {
            "category":"Sports & Exercise",
            "subcategory":"Gym",
            "type":"Entertainment"
        }
    ],
    "sg:phone":"+1 215 223 2311",
    "sg:postcode":"19132",
    "sg:province":"PA",
    "sg:website":"www.eastfallsfitness.com",
    "wof:name":"East Falls Fitness",
    "wof:placetype":"venue"
},
  "geometry": {"coordinates":[-75.186481,40.00096],"type":"Point"}
}