{
  "type": "Feature",
  "properties": {
    "addr:full":"18 W Maiden St Washington PA 15301",
    "addr:housenumber":"18",
    "addr:postcode":"15301",
    "addr:street":"W Maiden St",
    "iso:country":"US",
    "sg:address":"18 W Maiden St",
    "sg:city":"Washington",
    "sg:classifiers":[
        {
            "category":"Restaurant",
            "type":"Food & Drink"
        }
    ],
    "sg:menulink":"http://www.allmenus.com/pa/washington/25810-mr-gyros/menu/",
    "sg:phone":"+1 724 229 1060",
    "sg:postcode":"15301",
    "sg:province":"PA",
    "sg:tags":[
        "greek",
        "salad",
        "gyro"
    ],
    "wof:name":"Mr. Gyros",
    "wof:placetype":"venue"
},
  "geometry": {"coordinates":[-80.245059,40.167719],"type":"Point"}
}