{
  "type": "Feature",
  "properties": {
    "iso:country":"US",
    "sg:address":"2116 Berkshire Dr",
    "sg:city":"Monroeville",
    "sg:classifiers":[
        {
            "category":"Real Estate",
            "subcategory":"Architect",
            "type":"Services"
        }
    ],
    "sg:phone":"+1 412 856 0033",
    "sg:postcode":"15146",
    "sg:province":"PA",
    "wof:name":"Mahnaz International Design",
    "wof:placetype":"venue"
},
  "geometry": {"coordinates":[-79.74808,40.406825],"type":"Point"}
}