{
  "type": "Feature",
  "properties": {
    "iso:country":"US",
    "sg:address":"5540 Crawford Dr",
    "sg:city":"Bethlehem",
    "sg:classifiers":[
        {
            "category":"Retail",
            "subcategory":"Portrait Studio",
            "type":"Services"
        },
        {
            "category":"Shopping",
            "subcategory":"Pharmacy",
            "type":"Retail Goods"
        }
    ],
    "sg:phone":"+1 610 868 5991",
    "sg:postcode":"18017",
    "sg:province":"PA",
    "sg:tags":[
        "photography",
        "drugstore",
        "store"
    ],
    "wof:name":"Rite Aid Pharmacies",
    "wof:placetype":"venue"
},
  "geometry": {"coordinates":[-75.38829,40.673729],"type":"Point"}
}