{
  "type": "Feature",
  "properties": {
    "iso:country":"US",
    "sg:address":"521 Fayette St",
    "sg:city":"Conshohocken",
    "sg:classifiers":[
        {
            "category":"Restaurant",
            "type":"Food & Drink"
        }
    ],
    "sg:phone":"+1   ",
    "sg:postcode":"19428",
    "sg:province":"PA",
    "sg:tags":[
        "eating"
    ],
    "wof:name":"Boccellas Lunch Inc",
    "wof:placetype":"venue"
},
  "geometry": {"coordinates":[-75.302249,40.077838],"type":"Point"}
}