{
  "type": "Feature",
  "properties": {
    "addr:full":"2602 W 9th St Chester PA 19013",
    "addr:housenumber":"2602",
    "addr:postcode":"19013",
    "addr:street":"W 9Th St",
    "iso:country":"US",
    "sg:address":"2602 W 9th St",
    "sg:city":"Chester",
    "sg:classifiers":[
        {
            "category":"Health Services",
            "subcategory":"Nursing And Care Facility",
            "type":"Services"
        }
    ],
    "sg:phone":"+1   ",
    "sg:postcode":"19013",
    "sg:province":"PA",
    "wof:name":"Health Access Network",
    "wof:placetype":"venue"
},
  "geometry": {"coordinates":[-75.39390899999999,39.836864],"type":"Point"}
}