{
  "type": "Feature",
  "properties": {
    "addr:full":"522 Walnut St Mc Keesport PA 15132",
    "addr:housenumber":"522",
    "addr:postcode":"15132",
    "addr:street":"Walnut St",
    "iso:country":"US",
    "sg:address":"522 Walnut St",
    "sg:city":"Mc Keesport",
    "sg:classifiers":[
        {
            "category":"Social Services",
            "subcategory":"Child Care",
            "type":"Services"
        }
    ],
    "sg:phone":"+1   ",
    "sg:postcode":"15132",
    "sg:province":"PA",
    "sg:tags":[
        "day"
    ],
    "wof:name":"Allegheny Intermediate Unit",
    "wof:placetype":"venue"
},
  "geometry": {"coordinates":[-79.864831,40.350021],"type":"Point"}
}