{
  "type": "Feature",
  "properties": {
    "addr:full":"517 Saint Clair Ave Clairton PA 15025",
    "addr:housenumber":"517",
    "addr:postcode":"15025",
    "addr:street":"Saint Clair Ave",
    "iso:country":"US",
    "sg:address":"517 Saint Clair Ave",
    "sg:city":"Clairton",
    "sg:classifiers":[
        {
            "category":"Shopping",
            "subcategory":"Bicycles & Sporting Goods",
            "type":"Retail Goods"
        }
    ],
    "sg:phone":"+1 412 233 3555",
    "sg:postcode":"15025",
    "sg:province":"PA",
    "sg:website":"www.speedeeshirts.com",
    "wof:name":"Prince Printing",
    "wof:placetype":"venue"
},
  "geometry": {"coordinates":[-79.88629899999999,40.292999],"type":"Point"}
}