{
  "type": "Feature",
  "properties": {
    "addr:full":"64 Hess Rd Leola PA 17540",
    "addr:housenumber":"64",
    "addr:postcode":"17540",
    "addr:street":"Hess Rd",
    "iso:country":"US",
    "sg:address":"64 Hess Rd",
    "sg:city":"Leola",
    "sg:classifiers":[
        {
            "category":"Manufacturing",
            "subcategory":"Buildings",
            "type":"Manufacturing & Wholesale Goods"
        }
    ],
    "sg:phone":"+1 717 656 2081",
    "sg:postcode":"17540",
    "sg:province":"PA",
    "sg:tags":[
        "prefab"
    ],
    "sg:website":"www.mbsionline.com",
    "wof:name":"Miller Building Systems",
    "wof:placetype":"venue"
},
  "geometry": {"coordinates":[-76.15159,40.081461],"type":"Point"}
}