{
  "type": "Feature",
  "properties": {
    "addr:full":"435 Chestnut St Indiana PA 15701",
    "addr:housenumber":"435",
    "addr:postcode":"15701",
    "addr:street":"Chestnut St",
    "iso:country":"US",
    "sg:address":"435 Chestnut St",
    "sg:city":"Indiana",
    "sg:classifiers":[
        {
            "category":"Professional",
            "type":"Services"
        }
    ],
    "sg:phone":"+1   ",
    "sg:postcode":"15701",
    "sg:province":"PA",
    "wof:name":"Howlock Inc",
    "wof:placetype":"venue"
},
  "geometry": {"coordinates":[-79.146198,40.627179],"type":"Point"}
}