{
  "type": "Feature",
  "properties": {
    "iso:country":"US",
    "sg:address":"190 Bethlehem Pike",
    "sg:city":"Colmar",
    "sg:classifiers":[
        {
            "category":"Professional",
            "subcategory":"Accounting & Tax Preparation",
            "type":"Services"
        }
    ],
    "sg:phone":"+1 215 822 6300",
    "sg:postcode":"18915",
    "sg:province":"PA",
    "sg:tags":[
        "accountant"
    ],
    "sg:website":"www.holmesandmurray.com",
    "wof:name":"Holmes and Murray CPA",
    "wof:placetype":"venue"
},
  "geometry": {"coordinates":[-75.25749999999999,40.272301],"type":"Point"}
}