{
  "type": "Feature",
  "properties": {
    "iso:country":"US",
    "sg:address":"541 Forest Ln",
    "sg:city":"Pottsville",
    "sg:classifiers":[
        {
            "category":"Shopping",
            "subcategory":"Bicycles & Sporting Goods",
            "type":"Retail Goods"
        }
    ],
    "sg:phone":"+1   ",
    "sg:postcode":"17901",
    "sg:province":"PA",
    "wof:name":"Kopinetz Sports",
    "wof:placetype":"venue"
},
  "geometry": {"coordinates":[-76.30371599999999,40.688762],"type":"Point"}
}