{
  "type": "Feature",
  "properties": {
    "iso:country":"US",
    "sg:address":"322 Blackstone Dr",
    "sg:city":"Erie",
    "sg:classifiers":[
        {
            "category":"Building & Trades",
            "subcategory":"Plumbing",
            "type":"Services"
        }
    ],
    "sg:phone":"+1 814 833 9084",
    "sg:postcode":"16505",
    "sg:province":"PA",
    "sg:tags":[
        "plumbing",
        "contractor"
    ],
    "wof:name":"Murray Don Plumbing & Heating",
    "wof:placetype":"venue"
},
  "geometry": {"coordinates":[-80.16898,42.102656],"type":"Point"}
}