{
  "type": "Feature",
  "properties": {
    "addr:full":"754 Sans Souci Pkwy Wilkes Barre PA 18706",
    "addr:housenumber":"754",
    "addr:postcode":"18706",
    "addr:street":"Sans Souci Pkwy",
    "iso:country":"US",
    "sg:address":"754 Sans Souci Pkwy",
    "sg:city":"Wilkes Barre",
    "sg:classifiers":[
        {
            "category":"Manufacturing",
            "subcategory":"Food",
            "type":"Manufacturing & Wholesale Goods"
        }
    ],
    "sg:phone":"+1   ",
    "sg:postcode":"18706",
    "sg:province":"PA",
    "sg:tags":[
        "desert",
        "ice",
        "mfg"
    ],
    "wof:name":"Carvel Ice Cream",
    "wof:placetype":"venue"
},
  "geometry": {"coordinates":[-75.924577,41.230102],"type":"Point"}
}