{
  "type": "Feature",
  "properties": {
    "iso:country":"US",
    "sg:address":"1927 S Main Street Ext",
    "sg:city":"Washington",
    "sg:classifiers":[
        {
            "category":"Retail",
            "subcategory":"Storage",
            "type":"Services"
        }
    ],
    "sg:phone":"+1 724 223 7867",
    "sg:postcode":"15301",
    "sg:province":"PA",
    "sg:tags":[
        "self"
    ],
    "wof:name":"South Main Self Storage",
    "wof:placetype":"venue"
},
  "geometry": {"coordinates":[-80.22824300000001,40.141844],"type":"Point"}
}