{
  "type": "Feature",
  "properties": {
    "iso:country":"US",
    "sg:address":"407 Springhouse Rd",
    "sg:city":"Harrisburg",
    "sg:classifiers":[
        {
            "category":"Professional",
            "type":"Services"
        }
    ],
    "sg:phone":"+1 717 558 8270",
    "sg:postcode":"17111",
    "sg:province":"PA",
    "sg:tags":[
        "establishment"
    ],
    "wof:name":"Baags",
    "wof:placetype":"venue"
},
  "geometry": {"coordinates":[-76.797608,40.265757],"type":"Point"}
}