{
  "type": "Feature",
  "properties": {
    "addr:full":"105 N Main St Mountain Top PA 18707",
    "addr:housenumber":"105",
    "addr:postcode":"18707",
    "addr:street":"N Main St",
    "iso:country":"US",
    "sg:address":"105 N Main St",
    "sg:city":"Mountain Top",
    "sg:classifiers":[
        {
            "category":"Personal",
            "subcategory":"Beauty Salon",
            "type":"Services"
        }
    ],
    "sg:phone":"+1 570 474 6810",
    "sg:postcode":"18707",
    "sg:province":"PA",
    "sg:tags":[
        "shop"
    ],
    "wof:name":"Irene's Unisex Hair Salon",
    "wof:placetype":"venue"
},
  "geometry": {"coordinates":[-75.88125599999999,41.165167],"type":"Point"}
}