{
  "type": "Feature",
  "properties": {
    "addr:full":"1424 Farragut Ave Bristol PA 19007",
    "addr:housenumber":"1424",
    "addr:postcode":"19007",
    "addr:street":"Farragut Ave",
    "iso:country":"US",
    "sg:address":"1424 Farragut Ave",
    "sg:city":"Bristol",
    "sg:classifiers":[
        {
            "category":"Shopping",
            "type":"Retail Goods"
        }
    ],
    "sg:phone":"+1 215 785 0249",
    "sg:postcode":"19007",
    "sg:province":"PA",
    "sg:tags":[
        "make-up",
        "permanent",
        "cosmetic",
        "perfume"
    ],
    "wof:name":"About Face Permanent Make Up",
    "wof:placetype":"venue"
},
  "geometry": {"coordinates":[-74.844376,40.104848],"type":"Point"}
}