{
  "type": "Feature",
  "properties": {
    "iso:country":"US",
    "sg:address":"956 Barn St",
    "sg:city":"Hooversville",
    "sg:classifiers":[
        {
            "category":"Food & Beverages",
            "subcategory":"Groceries & Convenience Stores",
            "type":"Retail Goods"
        }
    ],
    "sg:phone":"+1 814 798 7161",
    "sg:postcode":"15936",
    "sg:province":"PA",
    "sg:tags":[
        "grocer"
    ],
    "wof:name":"Riverside Markets",
    "wof:placetype":"venue"
},
  "geometry": {"coordinates":[-78.91320399999999,40.145432],"type":"Point"}
}