{
  "type": "Feature",
  "properties": {
    "iso:country":"US",
    "sg:address":"3421 Library Rd",
    "sg:city":"Pittsburgh",
    "sg:classifiers":[
        {
            "category":"Retail",
            "subcategory":"Auto Repair",
            "type":"Services"
        }
    ],
    "sg:phone":"+1 412 884 0580",
    "sg:postcode":"15234",
    "sg:province":"PA",
    "sg:tags":[
        "body",
        "shop"
    ],
    "wof:name":"Wolber Frank P",
    "wof:placetype":"venue"
},
  "geometry": {"coordinates":[-80.013397,40.367401],"type":"Point"}
}