{
  "type": "Feature",
  "properties": {
    "iso:country":"US",
    "sg:address":"244 Jefferson St",
    "sg:city":"Meadville",
    "sg:classifiers":[
        {
            "category":"Professional",
            "subcategory":"Management & Consulting",
            "type":"Services"
        }
    ],
    "sg:phone":"+1   ",
    "sg:postcode":"16335",
    "sg:province":"PA",
    "sg:tags":[
        "business"
    ],
    "wof:name":"Strategic Purposes",
    "wof:placetype":"venue"
},
  "geometry": {"coordinates":[-80.14033999999999,41.655324],"type":"Point"}
}