{
  "type": "Feature",
  "properties": {
    "iso:country":"US",
    "sg:address":"2366 Springtown Hill Rd",
    "sg:city":"Hellertown",
    "sg:classifiers":[
        {
            "category":"Food & Beverages",
            "subcategory":"Meat & Fish",
            "type":"Retail Goods"
        }
    ],
    "sg:phone":"+1 610 346 7754",
    "sg:postcode":"18055",
    "sg:province":"PA",
    "sg:tags":[
        "shop"
    ],
    "wof:name":"Mease Donald G",
    "wof:placetype":"venue"
},
  "geometry": {"coordinates":[-75.303802,40.556702],"type":"Point"}
}