{
  "type": "Feature",
  "properties": {
    "iso:country":"US",
    "sg:address":"5 Millbrook Plz",
    "sg:city":"Mill Hall",
    "sg:classifiers":[
        {
            "category":"Shopping",
            "subcategory":"Discount & Variety Stores",
            "type":"Retail Goods"
        }
    ],
    "sg:phone":"+1 570 748 4459",
    "sg:postcode":"17751",
    "sg:province":"PA",
    "wof:name":"Dollar General",
    "wof:placetype":"venue"
},
  "geometry": {"coordinates":[-77.47503,41.118015],"type":"Point"}
}