{
  "type": "Feature",
  "properties": {
    "iso:country":"US",
    "sg:address":"11 Swan Ln",
    "sg:city":"Levittown",
    "sg:classifiers":[
        {
            "category":"Building & Trades",
            "subcategory":"Construction",
            "type":"Services"
        }
    ],
    "sg:phone":"+1   ",
    "sg:postcode":"19055",
    "sg:province":"PA",
    "sg:tags":[
        "contractor"
    ],
    "wof:name":"Quality Family Construction",
    "wof:placetype":"venue"
},
  "geometry": {"coordinates":[-74.825857,40.14717],"type":"Point"}
}