{
  "type": "Feature",
  "properties": {
    "iso:country":"US",
    "sg:address":"46 N Chester Rd",
    "sg:city":"West Chester",
    "sg:classifiers":[
        {
            "category":"Travel",
            "subcategory":"Travel Agent",
            "type":"Entertainment"
        }
    ],
    "sg:phone":"+1 610 429 9922",
    "sg:postcode":"19380",
    "sg:province":"PA",
    "sg:tags":[
        "agency",
        "bureau"
    ],
    "wof:name":"Rainbow Custom Tours",
    "wof:placetype":"venue"
},
  "geometry": {"coordinates":[-75.525682,39.968094],"type":"Point"}
}