{
  "type": "Feature",
  "properties": {
    "addr:full":"1420 Locust St Philadelphia PA 19102",
    "addr:housenumber":"1420",
    "addr:postcode":"19102",
    "addr:street":"Locust St",
    "iso:country":"US",
    "sg:address":"1420 Locust St",
    "sg:city":"Philadelphia",
    "sg:classifiers":[
        {
            "category":"Organizations",
            "subcategory":"Religious Organization",
            "type":"Services"
        }
    ],
    "sg:phone":"+1 215 545 0411",
    "sg:postcode":"19102",
    "sg:province":"PA",
    "sg:tags":[
        "clergy"
    ],
    "wof:name":"Richard F Steinbrink Rabbi",
    "wof:placetype":"venue"
},
  "geometry": {"coordinates":[-75.16484,39.948243],"type":"Point"}
}