{
  "type": "Feature",
  "properties": {
    "iso:country":"US",
    "sg:address":"13 Stroh Ln",
    "sg:city":"Lititz",
    "sg:classifiers":[
        {
            "category":"Arts & Performance",
            "subcategory":"Theater",
            "type":"Entertainment"
        }
    ],
    "sg:phone":"+1 717 627 0269",
    "sg:postcode":"17543",
    "sg:province":"PA",
    "sg:tags":[
        "magician"
    ],
    "wof:name":"Magic By Jonathan",
    "wof:placetype":"venue"
},
  "geometry": {"coordinates":[-76.304596,40.159951],"type":"Point"}
}