{
  "type": "Feature",
  "properties": {
    "addr:full":"364 E Pike St Houston PA 15342",
    "addr:housenumber":"364",
    "addr:postcode":"15342",
    "addr:street":"E Pike St",
    "iso:country":"US",
    "sg:address":"364 E Pike St",
    "sg:city":"Houston",
    "sg:classifiers":[
        {
            "category":"Building & Trades",
            "subcategory":"Construction",
            "type":"Services"
        }
    ],
    "sg:phone":"+1   ",
    "sg:postcode":"15342",
    "sg:province":"PA",
    "sg:tags":[
        "house"
    ],
    "wof:name":"Morrow Construction Power",
    "wof:placetype":"venue"
},
  "geometry": {"coordinates":[-80.206135,40.255257],"type":"Point"}
}