{
  "type": "Feature",
  "properties": {
    "addr:full":"11 Meadowbrook Ln Chalfont PA 18914",
    "addr:housenumber":"11",
    "addr:postcode":"18914",
    "addr:street":"Meadowbrook Ln",
    "iso:country":"US",
    "sg:address":"11 Meadowbrook Ln",
    "sg:city":"Chalfont",
    "sg:classifiers":[
        {
            "category":"Organizations",
            "subcategory":"Religious Organization",
            "type":"Services"
        }
    ],
    "sg:phone":"+1 215 822 2807",
    "sg:postcode":"18914",
    "sg:province":"PA",
    "sg:tags":[
        "church"
    ],
    "wof:name":"Chalfont United Methodist Chr",
    "wof:placetype":"venue"
},
  "geometry": {"coordinates":[-75.214499,40.283518],"type":"Point"}
}