{
  "type": "Feature",
  "properties": {
    "iso:country":"US",
    "sg:address":"537 Easton Rd ",
    "sg:city":"Horsham",
    "sg:classifiers":[
        {
            "category":"Restaurant",
            "type":"Food & Drink"
        }
    ],
    "sg:menulink":"http://www.allmenus.com/pa/horsham/288901-fountainside-seafood--grill/menu/",
    "sg:phone":"+1 215 957 5122",
    "sg:postcode":"19044",
    "sg:province":"PA",
    "sg:tags":[
        "burger",
        "seafood",
        "sandwich",
        "american"
    ],
    "wof:name":"Fountainside Seafood & Grill",
    "wof:placetype":"venue"
},
  "geometry": {"coordinates":[-75.132668,40.184512],"type":"Point"}
}