{
  "type": "Feature",
  "properties": {
    "addr:full":"3601 Paxton St Harrisburg PA 17111",
    "addr:housenumber":"3601",
    "addr:postcode":"17111",
    "addr:street":"Paxton St",
    "iso:country":"US",
    "sg:address":"3601 Paxton St",
    "sg:city":"Harrisburg",
    "sg:classifiers":[
        {
            "category":"Shopping",
            "subcategory":"Clothing, Apparel, & Fashions",
            "type":"Retail Goods"
        }
    ],
    "sg:phone":"+1 717 564 6077",
    "sg:postcode":"17111",
    "sg:province":"PA",
    "sg:tags":[
        "lingerie"
    ],
    "sg:website":"www.victoriasecret.com",
    "wof:name":"Victoria's Secret",
    "wof:placetype":"venue"
},
  "geometry": {"coordinates":[-76.826826,40.253584],"type":"Point"}
}