{
  "type": "Feature",
  "properties": {
    "iso:country":"US",
    "sg:address":"416 Elm St",
    "sg:city":"Clairton",
    "sg:classifiers":[
        {
            "category":"Health Services",
            "subcategory":"Nursing And Care Facility",
            "type":"Services"
        }
    ],
    "sg:phone":"+1   ",
    "sg:postcode":"15025",
    "sg:province":"PA",
    "sg:tags":[
        "personal",
        "home"
    ],
    "wof:name":"Lapensione Personal Home Care",
    "wof:placetype":"venue"
},
  "geometry": {"coordinates":[-79.893637,40.306051],"type":"Point"}
}