{
  "type": "Feature",
  "properties": {
    "iso:country":"US",
    "sg:address":"12134 Frankstown Rd",
    "sg:city":"Pittsburgh",
    "sg:classifiers":[
        {
            "category":"Social Services",
            "type":"Services"
        }
    ],
    "sg:phone":"+1   ",
    "sg:postcode":"15235",
    "sg:province":"PA",
    "wof:name":"Ccis of Alleghany County Child",
    "wof:placetype":"venue"
},
  "geometry": {"coordinates":[-79.81995000000001,40.471224],"type":"Point"}
}