{
  "type": "Feature",
  "properties": {
    "iso:country":"US",
    "sg:address":"180 Elm Ave",
    "sg:city":"Clymer",
    "sg:classifiers":[
        {
            "category":"Building & Trades",
            "subcategory":"Electrical",
            "type":"Services"
        }
    ],
    "sg:phone":"+1 724 254 4048",
    "sg:postcode":"15728",
    "sg:province":"PA",
    "sg:tags":[
        "electric",
        "contractor"
    ],
    "wof:name":"Clymer Electric",
    "wof:placetype":"venue"
},
  "geometry": {"coordinates":[-79.01357899999999,40.666796],"type":"Point"}
}