{
  "type": "Feature",
  "properties": {
    "iso:country":"US",
    "sg:address":"105 Snyder St",
    "sg:city":"Shamokin Dam",
    "sg:classifiers":[
        {
            "category":"Personal",
            "subcategory":"Beauty Salon",
            "type":"Services"
        }
    ],
    "sg:phone":"+1 570 743 0909",
    "sg:postcode":"17876",
    "sg:province":"PA",
    "wof:name":"Brenda's Beauty Shop",
    "wof:placetype":"venue"
},
  "geometry": {"coordinates":[-76.825091,40.845472],"type":"Point"}
}