{
  "type": "Feature",
  "properties": {
    "addr:full":"180 S 1st St Lehighton PA 18235",
    "addr:housenumber":"180",
    "addr:postcode":"18235",
    "addr:street":"S 1St St",
    "iso:country":"US",
    "sg:address":"180 S 1st St",
    "sg:city":"Lehighton",
    "sg:classifiers":[
        {
            "category":"Real Estate",
            "subcategory":"Real Estate Agent",
            "type":"Services"
        }
    ],
    "sg:phone":"+1 610 377 8121",
    "sg:postcode":"18235",
    "sg:province":"PA",
    "wof:name":"Carbon County Assn Realtors",
    "wof:placetype":"venue"
},
  "geometry": {"coordinates":[-75.70851999999999,40.832042],"type":"Point"}
}