{
  "type": "Feature",
  "properties": {
    "iso:country":"US",
    "sg:address":"226 W Rittenhouse Sq",
    "sg:city":"Philadelphia",
    "sg:classifiers":[
        {
            "category":"Professional",
            "subcategory":"Management & Consulting",
            "type":"Services"
        }
    ],
    "sg:phone":"+1 215 772 9900",
    "sg:postcode":"19103",
    "sg:province":"PA",
    "sg:tags":[
        "consultant",
        "business"
    ],
    "sg:website":"www.rittenhousegroup.com",
    "wof:name":"Rittenhouse Group Inc",
    "wof:placetype":"venue"
},
  "geometry": {"coordinates":[-75.172918,39.950195],"type":"Point"}
}