{
  "type": "Feature",
  "properties": {
    "addr:full":"208 W Street Rd Warminster PA 18974",
    "addr:housenumber":"208",
    "addr:postcode":"18974",
    "addr:street":"W Street Rd",
    "iso:country":"US",
    "sg:address":"208 W Street Rd",
    "sg:city":"Warminster",
    "sg:classifiers":[
        {
            "category":"Personal",
            "subcategory":"Beauty Salon",
            "type":"Services"
        },
        {
            "category":"Personal",
            "subcategory":"Nail Salon",
            "type":"Services"
        }
    ],
    "sg:phone":"+1 215 957 9530",
    "sg:postcode":"18974",
    "sg:province":"PA",
    "wof:name":"Vee's Artistic Nails",
    "wof:placetype":"venue"
},
  "geometry": {"coordinates":[-75.086111,40.19887],"type":"Point"}
}