{
  "type": "Feature",
  "properties": {
    "addr:full":"199 Fox Gap Rd Aaronsburg PA 16820",
    "addr:housenumber":"199",
    "addr:postcode":"16820",
    "addr:street":"Fox Gap Rd",
    "iso:country":"US",
    "sg:address":"199 Fox Gap Rd",
    "sg:city":"Aaronsburg",
    "sg:classifiers":[
        {
            "category":"Retail",
            "subcategory":"Portrait Studio",
            "type":"Services"
        }
    ],
    "sg:phone":"+1 814 349 2263",
    "sg:postcode":"16820",
    "sg:province":"PA",
    "sg:tags":[
        "photographer"
    ],
    "wof:name":"Foxes Gap Photography",
    "wof:placetype":"venue"
},
  "geometry": {"coordinates":[-77.380467,40.917331],"type":"Point"}
}