{
  "type": "Feature",
  "properties": {
    "iso:country":"US",
    "sg:address":"2848 N 9th St",
    "sg:city":"Philadelphia",
    "sg:classifiers":[
        {
            "category":"Social Services",
            "type":"Services"
        }
    ],
    "sg:phone":"+1 215 226 4999",
    "sg:postcode":"19133",
    "sg:province":"PA",
    "sg:tags":[
        "welfare"
    ],
    "wof:name":"Women Of Excellence Inc",
    "wof:placetype":"venue"
},
  "geometry": {"coordinates":[-75.14555300000001,39.99527],"type":"Point"}
}