{
  "type": "Feature",
  "properties": {
    "iso:country":"US",
    "sg:address":"734 Long Run Rd",
    "sg:city":"Mckeesport",
    "sg:classifiers":[
        {
            "category":"Retail",
            "subcategory":"Auto Repair",
            "type":"Services"
        }
    ],
    "sg:phone":"+1 412 751 1774",
    "sg:postcode":"15132",
    "sg:province":"PA",
    "sg:tags":[
        "transmission"
    ],
    "wof:name":"Long Run Transmission Ctr",
    "wof:placetype":"venue"
},
  "geometry": {"coordinates":[-79.825356,40.32255],"type":"Point"}
}