{
  "type": "Feature",
  "properties": {
    "addr:full":"818 N Broad St Allentown PA 18104",
    "addr:housenumber":"818",
    "addr:postcode":"18104",
    "addr:street":"N Broad St",
    "iso:country":"US",
    "sg:address":"818 N Broad St",
    "sg:city":"Allentown",
    "sg:classifiers":[
        {
            "category":"Personal",
            "type":"Services"
        }
    ],
    "sg:phone":"+1 610 437 4047",
    "sg:postcode":"18104",
    "sg:province":"PA",
    "sg:tags":[
        "property",
        "maintenance"
    ],
    "wof:name":"H & R Maintenance Services, Inc.",
    "wof:placetype":"venue"
},
  "geometry": {"coordinates":[-75.519846,40.602252],"type":"Point"}
}