{
  "type": "Feature",
  "properties": {
    "addr:full":"2017 Mountain Rd Stroudsburg PA 18360",
    "addr:housenumber":"2017",
    "addr:postcode":"18360",
    "addr:street":"Mountain Rd",
    "iso:country":"US",
    "sg:address":"2017 Mountain Rd",
    "sg:city":"Stroudsburg",
    "sg:classifiers":[
        {
            "category":"Wholesale",
            "subcategory":"Durable Goods & Equipment",
            "type":"Manufacturing & Wholesale Goods"
        }
    ],
    "sg:phone":"+1 570 629 4391",
    "sg:postcode":"18360",
    "sg:province":"PA",
    "sg:tags":[
        "importer"
    ],
    "wof:name":"Rollei USA",
    "wof:placetype":"venue"
},
  "geometry": {"coordinates":[-75.37755199999999,41.001402],"type":"Point"}
}