{
  "type": "Feature",
  "properties": {
    "iso:country":"US",
    "sg:address":"Cranberry Mall",
    "sg:city":"Cranberry Twp",
    "sg:classifiers":[
        {
            "category":"Shopping",
            "subcategory":"Clothing, Apparel, & Fashions",
            "type":"Retail Goods"
        }
    ],
    "sg:phone":"+1 724 779 4955",
    "sg:postcode":"16066",
    "sg:province":"PA",
    "sg:tags":[
        "accessory"
    ],
    "wof:name":"Lane Bryant",
    "wof:placetype":"venue"
},
  "geometry": {"coordinates":[-80.1045,40.697399],"type":"Point"}
}