{
  "type": "Feature",
  "properties": {
    "addr:full":"1459 Buttonwood Ln Warminster PA 18974",
    "addr:housenumber":"1459",
    "addr:postcode":"18974",
    "addr:street":"Buttonwood Ln",
    "iso:country":"US",
    "sg:address":"1459 Buttonwood Ln",
    "sg:city":"Warminster",
    "sg:classifiers":[
        {
            "category":"Building & Trades",
            "subcategory":"Locksmith",
            "type":"Services"
        }
    ],
    "sg:phone":"+1 267 960 5125",
    "sg:postcode":"18974",
    "sg:province":"PA",
    "sg:tags":[
        "key"
    ],
    "wof:name":"A 1 Emergency Locksmith",
    "wof:placetype":"venue"
},
  "geometry": {"coordinates":[-75.115313,40.224238],"type":"Point"}
}