{
  "type": "Feature",
  "properties": {
    "addr:full":"607 W Main St Lansdale PA 19446",
    "addr:housenumber":"607",
    "addr:postcode":"19446",
    "addr:street":"W Main St",
    "iso:country":"US",
    "sg:address":"607 W Main St",
    "sg:city":"Lansdale",
    "sg:classifiers":[
        {
            "category":"Professional",
            "subcategory":"Lawyer & Legal Services",
            "type":"Services"
        }
    ],
    "sg:phone":"+1 215 368 9288",
    "sg:postcode":"19446",
    "sg:province":"PA",
    "sg:tags":[
        "notary"
    ],
    "wof:name":"Lansdale Fastags",
    "wof:placetype":"venue"
},
  "geometry": {"coordinates":[-75.2901,40.2453],"type":"Point"}
}