{
  "type": "Feature",
  "properties": {
    "addr:full":"11134 Hendrix St Philadelphia PA 19116",
    "addr:housenumber":"11134",
    "addr:postcode":"19116",
    "addr:street":"Hendrix St",
    "iso:country":"US",
    "sg:address":"11134 Hendrix St",
    "sg:city":"Philadelphia",
    "sg:classifiers":[
        {
            "category":"Building & Trades",
            "subcategory":"Plumbing",
            "type":"Services"
        }
    ],
    "sg:phone":"+1   ",
    "sg:postcode":"19116",
    "sg:province":"PA",
    "sg:tags":[
        "contractor"
    ],
    "wof:name":"Paul J Senior & Son Inc",
    "wof:placetype":"venue"
},
  "geometry": {"coordinates":[-75.031842,40.123647],"type":"Point"}
}