{
  "type": "Feature",
  "properties": {
    "iso:country":"US",
    "sg:address":"613 Geneva Dr",
    "sg:city":"Mechanicsburg",
    "sg:classifiers":[
        {
            "category":"Real Estate",
            "subcategory":"Real Estate Operator",
            "type":"Services"
        }
    ],
    "sg:phone":"+1 717 697 6009",
    "sg:postcode":"17055",
    "sg:province":"PA",
    "sg:tags":[
        "apartment"
    ],
    "wof:name":"Belle Terre",
    "wof:placetype":"venue"
},
  "geometry": {"coordinates":[-76.9785,40.209099],"type":"Point"}
}