{
  "type": "Feature",
  "properties": {
    "iso:country":"US",
    "sg:address":"70 Old Dublin Pike",
    "sg:city":"Doylestown",
    "sg:classifiers":[
        {
            "category":"Manufacturing",
            "subcategory":"Tools & Machinery",
            "type":"Manufacturing & Wholesale Goods"
        }
    ],
    "sg:phone":"+1   ",
    "sg:postcode":"18901",
    "sg:province":"PA",
    "sg:tags":[
        "mfg"
    ],
    "wof:name":"Apptech Engineered Systems",
    "wof:placetype":"venue"
},
  "geometry": {"coordinates":[-75.134635,40.324325],"type":"Point"}
}