{
  "type": "Feature",
  "properties": {
    "addr:full":"1513 Candor Rd Bulger PA 15019",
    "addr:housenumber":"1513",
    "addr:postcode":"15019",
    "addr:street":"Candor Rd",
    "iso:country":"US",
    "sg:address":"1513 Candor Rd",
    "sg:city":"Bulger",
    "sg:classifiers":[
        {
            "category":"Shopping",
            "subcategory":"Gifts & Souvenirs",
            "type":"Retail Goods"
        }
    ],
    "sg:phone":"+1   ",
    "sg:postcode":"15019",
    "sg:province":"PA",
    "sg:tags":[
        "shop",
        "novelty"
    ],
    "wof:name":"Curtis Tole-N-Wood",
    "wof:placetype":"venue"
},
  "geometry": {"coordinates":[-80.30758,40.402056],"type":"Point"}
}