{
  "type": "Feature",
  "properties": {
    "addr:full":"125 Strafford Ave Wayne PA 19087",
    "addr:housenumber":"125",
    "addr:postcode":"19087",
    "addr:street":"Strafford Ave",
    "iso:country":"US",
    "sg:address":"125 Strafford Ave",
    "sg:city":"Wayne",
    "sg:classifiers":[
        {
            "category":"Professional",
            "subcategory":"Lawyer & Legal Services",
            "type":"Services"
        }
    ],
    "sg:phone":"+1   ",
    "sg:postcode":"19087",
    "sg:province":"PA",
    "wof:name":"Bennett Eliz Esq",
    "wof:placetype":"venue"
},
  "geometry": {"coordinates":[-75.39801199999999,40.044532],"type":"Point"}
}