{
  "type": "Feature",
  "properties": {
    "iso:country":"US",
    "sg:address":"310 Toura Dr",
    "sg:city":"Pleasant Hills",
    "sg:classifiers":[
        {
            "category":"Building & Trades",
            "subcategory":"Construction",
            "type":"Services"
        }
    ],
    "sg:phone":"+1 412 650 9925",
    "sg:postcode":"15236",
    "sg:province":"PA",
    "sg:tags":[
        "general",
        "contractor"
    ],
    "sg:website":"www.deltaconstruction.net",
    "wof:name":"Delta Construction Co",
    "wof:placetype":"venue"
},
  "geometry": {"coordinates":[-79.95343099999999,40.320827],"type":"Point"}
}