{
  "type": "Feature",
  "properties": {
    "addr:full":"501 E 3rd St Williamsport PA 17701",
    "addr:housenumber":"501",
    "addr:postcode":"17701",
    "addr:street":"E 3Rd St",
    "iso:country":"US",
    "sg:address":"501 E 3rd St",
    "sg:city":"Williamsport",
    "sg:classifiers":[
        {
            "category":"Social Services",
            "type":"Services"
        }
    ],
    "sg:phone":"+1 570 323 7535",
    "sg:postcode":"17701",
    "sg:province":"PA",
    "wof:name":"Crossroads Counseling Inc",
    "wof:placetype":"venue"
},
  "geometry": {"coordinates":[-76.99399699999999,41.244333],"type":"Point"}
}