{
  "type": "Feature",
  "properties": {
    "iso:country":"US",
    "sg:address":"33 E Roumfort Rd",
    "sg:city":"Philadelphia",
    "sg:classifiers":[
        {
            "category":"Building & Trades",
            "subcategory":"Construction",
            "type":"Services"
        }
    ],
    "sg:phone":"+1 215 753 8919",
    "sg:postcode":"19119",
    "sg:province":"PA",
    "sg:tags":[
        "contractor"
    ],
    "wof:name":"C & C Building Group LLC",
    "wof:placetype":"venue"
},
  "geometry": {"coordinates":[-75.194627,40.065418],"type":"Point"}
}