{
  "type": "Feature",
  "properties": {
    "iso:country":"US",
    "sg:address":"4119 E Chester Dr",
    "sg:city":"Aston",
    "sg:classifiers":[
        {
            "category":"Retail",
            "subcategory":"Animal Services",
            "type":"Services"
        }
    ],
    "sg:phone":"+1 610 497 5336",
    "sg:postcode":"19014",
    "sg:province":"PA",
    "sg:tags":[
        "pet",
        "grooming",
        "washing"
    ],
    "wof:name":"Pauls Dog Training",
    "wof:placetype":"venue"
},
  "geometry": {"coordinates":[-75.40379299999999,39.859179],"type":"Point"}
}