{
  "type": "Feature",
  "properties": {
    "iso:country":"US",
    "sg:address":"29 S Main St",
    "sg:city":"Bangor",
    "sg:classifiers":[
        {
            "category":"Banks & Credit Unions",
            "subcategory":"Bank",
            "type":"Services"
        }
    ],
    "sg:phone":"+1   ",
    "sg:postcode":"18013",
    "sg:province":"PA",
    "sg:tags":[
        "state",
        "commercial"
    ],
    "wof:name":"Fleet",
    "wof:placetype":"venue"
},
  "geometry": {"coordinates":[-75.204365,40.866352],"type":"Point"}
}