{
  "type": "Feature",
  "properties": {
    "iso:country":"US",
    "sg:address":"322 S Juliana St",
    "sg:city":"Bedford",
    "sg:classifiers":[
        {
            "category":"Professional",
            "subcategory":"Lawyer & Legal Services",
            "type":"Services"
        }
    ],
    "sg:phone":"+1 814 623 9889",
    "sg:postcode":"15522",
    "sg:province":"PA",
    "sg:tags":[
        "attorney"
    ],
    "wof:name":"Douglas Goldhaber Law Office",
    "wof:placetype":"venue"
},
  "geometry": {"coordinates":[-78.50357099999999,40.015784],"type":"Point"}
}