{
  "type": "Feature",
  "properties": {
    "iso:country":"US",
    "sg:address":"204 Hathaway Park",
    "sg:city":"Lebanon",
    "sg:classifiers":[
        {
            "category":"Health Services",
            "subcategory":"Doctor",
            "type":"Services"
        },
        {
            "category":"Health Services",
            "subcategory":"Clinic",
            "type":"Services"
        },
        {
            "category":"Personal",
            "type":"Services"
        }
    ],
    "sg:phone":"+1 717 274 9777",
    "sg:postcode":"17042",
    "sg:province":"PA",
    "sg:tags":[
        "counseling",
        "psychologist",
        "outpatient"
    ],
    "sg:website":"http://www.philhaven.org",
    "wof:name":"Philhaven / Lebanon",
    "wof:placetype":"venue"
},
  "geometry": {"coordinates":[-76.414107,40.336295],"type":"Point"}
}