{
  "type": "Feature",
  "properties": {
    "iso:country":"US",
    "sg:address":"121 Paradise Rd",
    "sg:city":"Punxsutawney",
    "sg:classifiers":[
        {
            "category":"Personal",
            "subcategory":"Beauty Salon",
            "type":"Services"
        }
    ],
    "sg:phone":"+1 814 427 2623",
    "sg:postcode":"15767",
    "sg:province":"PA",
    "wof:name":"Linda Smith's Beauty Salon",
    "wof:placetype":"venue"
},
  "geometry": {"coordinates":[-78.851209,40.978719],"type":"Point"}
}