{
  "type": "Feature",
  "properties": {
    "addr:full":"214 W High St Bellefonte PA 16823",
    "addr:housenumber":"214",
    "addr:postcode":"16823",
    "addr:street":"W High St",
    "iso:country":"US",
    "sg:address":"214 W High St",
    "sg:city":"Bellefonte",
    "sg:classifiers":[
        {
            "category":"Shopping",
            "subcategory":"Hobbies, Toys, & Games",
            "type":"Retail Goods"
        }
    ],
    "sg:phone":"+1 814 355 1134",
    "sg:postcode":"16823",
    "sg:province":"PA",
    "sg:tags":[
        "toy",
        "store"
    ],
    "wof:name":"Pure Imagination",
    "wof:placetype":"venue"
},
  "geometry": {"coordinates":[-77.780098,40.911701],"type":"Point"}
}