{
  "type": "Feature",
  "properties": {
    "iso:country":"US",
    "sg:address":"40 Leigh Dr",
    "sg:city":"York",
    "sg:classifiers":[
        {
            "category":"Building & Trades",
            "subcategory":"Landscaping Services",
            "type":"Services"
        }
    ],
    "sg:phone":"+1 717 632 5317",
    "sg:postcode":"17406",
    "sg:province":"PA",
    "sg:tags":[
        "tree"
    ],
    "sg:website":"www.bartlett.com",
    "wof:name":"Bartlett Tree Experts",
    "wof:placetype":"venue"
},
  "geometry": {"coordinates":[-76.737145,40.042248],"type":"Point"}
}