{
  "type": "Feature",
  "properties": {
    "addr:full":"1711 Prunus Cir Chester PA 19013",
    "addr:housenumber":"1711",
    "addr:postcode":"19013",
    "addr:street":"Prunus Cir",
    "iso:country":"US",
    "sg:address":"1711 Prunus Cir",
    "sg:city":"Chester",
    "sg:classifiers":[
        {
            "category":"Social Services",
            "subcategory":"Child Care",
            "type":"Services"
        }
    ],
    "sg:phone":"+1 610 872 6506",
    "sg:postcode":"19013",
    "sg:province":"PA",
    "wof:name":"Hamm's Learning Tree Day Care",
    "wof:placetype":"venue"
},
  "geometry": {"coordinates":[-75.365087,39.860459],"type":"Point"}
}