{
  "type": "Feature",
  "properties": {
    "addr:full":"1903 Sonora Ln Manheim PA 17545",
    "addr:housenumber":"1903",
    "addr:postcode":"17545",
    "addr:street":"Sonora Ln",
    "iso:country":"US",
    "sg:address":"1903 Sonora Ln",
    "sg:city":"Manheim",
    "sg:classifiers":[
        {
            "category":"Food & Beverages",
            "subcategory":"Groceries & Convenience Stores",
            "type":"Retail Goods"
        }
    ],
    "sg:phone":"+1   ",
    "sg:postcode":"17545",
    "sg:province":"PA",
    "wof:name":"Spring Meadow Farms",
    "wof:placetype":"venue"
},
  "geometry": {"coordinates":[-76.474548,40.161357],"type":"Point"}
}