{
  "type": "Feature",
  "properties": {
    "addr:full":"28 Springhouse Ln Media PA 19063",
    "addr:housenumber":"28",
    "addr:postcode":"19063",
    "addr:street":"Springhouse Ln",
    "iso:country":"US",
    "sg:address":"28 Springhouse Ln",
    "sg:city":"Media",
    "sg:classifiers":[
        {
            "category":"Building & Trades",
            "subcategory":"Construction",
            "type":"Services"
        }
    ],
    "sg:phone":"+1 610 891 1456",
    "sg:postcode":"19063",
    "sg:province":"PA",
    "sg:tags":[
        "concrete",
        "contractor"
    ],
    "wof:name":"John Defelice Masonry",
    "wof:placetype":"venue"
},
  "geometry": {"coordinates":[-75.420591,39.903414],"type":"Point"}
}