{
  "type": "Feature",
  "properties": {
    "addr:full":"104 E Wylie Ave Washington PA 15301",
    "addr:housenumber":"104",
    "addr:postcode":"15301",
    "addr:street":"E Wylie Ave",
    "iso:country":"US",
    "sg:address":"104 E Wylie Ave",
    "sg:city":"Washington",
    "sg:classifiers":[
        {
            "category":"Food & Beverages",
            "subcategory":"Groceries & Convenience Stores",
            "type":"Retail Goods"
        }
    ],
    "sg:phone":"+1 724 228 8401",
    "sg:postcode":"15301",
    "sg:province":"PA",
    "wof:name":"Crossroads Food Mart",
    "wof:placetype":"venue"
},
  "geometry": {"coordinates":[-80.262674,40.182952],"type":"Point"}
}