{
  "type": "Feature",
  "properties": {
    "addr:full":"26 Ridge Ave York PA 17403",
    "addr:housenumber":"26",
    "addr:postcode":"17403",
    "addr:street":"Ridge Ave",
    "iso:country":"US",
    "sg:address":"26 Ridge Ave",
    "sg:city":"York",
    "sg:classifiers":[
        {
            "category":"Organizations",
            "subcategory":"Religious Organization",
            "type":"Services"
        }
    ],
    "sg:phone":"+1 717 854 5154",
    "sg:postcode":"17403",
    "sg:province":"PA",
    "sg:tags":[
        "church"
    ],
    "sg:website":"www.newharvestcc.org",
    "wof:name":"New Harvest Community Church",
    "wof:placetype":"venue"
},
  "geometry": {"coordinates":[-76.71484599999999,39.967577],"type":"Point"}
}