{
  "type": "Feature",
  "properties": {
    "iso:country":"US",
    "sg:address":"243 S Washington St",
    "sg:city":"Wilkes Barre",
    "sg:classifiers":[
        {
            "category":"Professional",
            "subcategory":"Computer Services",
            "type":"Services"
        }
    ],
    "sg:phone":"+1   ",
    "sg:postcode":"18701",
    "sg:province":"PA",
    "sg:tags":[
        "prepackaged",
        "software"
    ],
    "wof:name":"E Z Bookkeeping Solutions",
    "wof:placetype":"venue"
},
  "geometry": {"coordinates":[-75.88858500000001,41.240438],"type":"Point"}
}