{
  "type": "Feature",
  "properties": {
    "iso:country":"US",
    "sg:address":"877 Martin Church Rd",
    "sg:city":"New Holland",
    "sg:classifiers":[
        {
            "category":"Travel",
            "subcategory":"Campground",
            "type":"Entertainment"
        }
    ],
    "sg:phone":"+1 717 445 4526",
    "sg:postcode":"17557",
    "sg:province":"PA",
    "sg:tags":[
        "campsite",
        "trailer",
        "parks"
    ],
    "wof:name":"Red Run Campground",
    "wof:placetype":"venue"
},
  "geometry": {"coordinates":[-76.077671,40.175785],"type":"Point"}
}