{
  "type": "Feature",
  "properties": {
    "iso:country":"US",
    "sg:address":"2216 S Lumber St",
    "sg:city":"Allentown",
    "sg:classifiers":[
        {
            "category":"Shopping",
            "subcategory":"Hobbies, Toys, & Games",
            "type":"Retail Goods"
        }
    ],
    "sg:phone":"+1   ",
    "sg:postcode":"18103",
    "sg:province":"PA",
    "wof:name":"Nabils Woodcrafts",
    "wof:placetype":"venue"
},
  "geometry": {"coordinates":[-75.46484100000001,40.573105],"type":"Point"}
}