{
  "type": "Feature",
  "properties": {
    "addr:full":"1518 Walnut St Philadelphia PA 19102",
    "addr:housenumber":"1518",
    "addr:postcode":"19102",
    "addr:street":"Walnut St",
    "iso:country":"US",
    "sg:address":"1518 Walnut St",
    "sg:city":"Philadelphia",
    "sg:classifiers":[
        {
            "category":"Professional",
            "subcategory":"Business Services",
            "type":"Services"
        }
    ],
    "sg:phone":"+1 215 732 2390",
    "sg:postcode":"19102",
    "sg:province":"PA",
    "sg:tags":[
        "electronics",
        "consumer"
    ],
    "sg:website":"http://www.sharperimage.com",
    "wof:name":"Sharper Image",
    "wof:placetype":"venue"
},
  "geometry": {"coordinates":[-75.166786,39.949655],"type":"Point"}
}