{
  "type": "Feature",
  "properties": {
    "addr:full":"2224 E Carson St Pittsburgh PA 15203",
    "addr:housenumber":"2224",
    "addr:postcode":"15203",
    "addr:street":"E Carson St",
    "iso:country":"US",
    "sg:address":"2224 E Carson St",
    "sg:city":"Pittsburgh",
    "sg:classifiers":[
        {
            "category":"Restaurant",
            "type":"Food & Drink"
        },
        {
            "category":"Bars & Pubs",
            "subcategory":"Wine Bar",
            "type":"Food & Drink"
        }
    ],
    "sg:menulink":"http://www.allmenus.com/pa/pittsburgh/6517-ibiza-tapas--wine-bar/menu/",
    "sg:phone":"+1 412 325 2227",
    "sg:postcode":"15203",
    "sg:province":"PA",
    "sg:tags":[
        "spanish",
        "portuguese",
        "brazilian",
        "argentinean"
    ],
    "wof:name":"Ibiza Tapas & Wine Bar",
    "wof:placetype":"venue"
},
  "geometry": {"coordinates":[-79.97362099999999,40.428384],"type":"Point"}
}