{
  "type": "Feature",
  "properties": {
    "iso:country":"US",
    "sg:address":"400 Drew Ct",
    "sg:city":"King Of Prussia",
    "sg:classifiers":[
        {
            "category":"Wholesale",
            "subcategory":"Meat",
            "type":"Manufacturing & Wholesale Goods"
        }
    ],
    "sg:phone":"+1 610 277 5010",
    "sg:postcode":"19406",
    "sg:province":"PA",
    "sg:tags":[
        "packer",
        "plant",
        "prepared",
        "packing",
        "mfg"
    ],
    "wof:name":"Texas American Foodservice",
    "wof:placetype":"venue"
},
  "geometry": {"coordinates":[-75.350999,40.08667],"type":"Point"}
}