{
  "type": "Feature",
  "properties": {
    "iso:country":"US",
    "sg:address":"207 E Brown St",
    "sg:city":"Blairsville",
    "sg:classifiers":[
        {
            "category":"Manufacturing",
            "subcategory":"Metals",
            "type":"Manufacturing & Wholesale Goods"
        }
    ],
    "sg:phone":"+1 724 459 5601",
    "sg:postcode":"15717",
    "sg:province":"PA",
    "sg:tags":[
        "product",
        "wire"
    ],
    "wof:name":"Precision Wire Products Inc",
    "wof:placetype":"venue"
},
  "geometry": {"coordinates":[-79.259011,40.43002],"type":"Point"}
}