{
  "type": "Feature",
  "properties": {
    "iso:country":"US",
    "sg:address":"3805 Huckleberry Hwy",
    "sg:city":"Berlin",
    "sg:classifiers":[
        {
            "category":"Farming",
            "subcategory":"Dairy Farm",
            "type":"Manufacturing & Wholesale Goods"
        }
    ],
    "sg:phone":"+1   ",
    "sg:postcode":"15530",
    "sg:province":"PA",
    "wof:name":"Ray Carver",
    "wof:placetype":"venue"
},
  "geometry": {"coordinates":[-78.906165,39.945655],"type":"Point"}
}