{
  "type": "Feature",
  "properties": {
    "iso:country":"US",
    "sg:address":"1900 Washington Rd Ste 343",
    "sg:city":"Pittsburgh",
    "sg:classifiers":[
        {
            "category":"Shopping",
            "subcategory":"Clothing, Apparel, & Fashions",
            "type":"Retail Goods"
        },
        {
            "category":"Shopping",
            "subcategory":"Shoes",
            "type":"Retail Goods"
        }
    ],
    "sg:phone":"+1 412 831 1353",
    "sg:postcode":"15241",
    "sg:province":"PA",
    "sg:tags":[
        "sportswear",
        "store"
    ],
    "sg:website":"http://www.easyspirit.com/",
    "wof:name":"Easy Spirit Shoe Store",
    "wof:placetype":"venue"
},
  "geometry": {"coordinates":[-80.060417,40.34333],"type":"Point"}
}