{
  "type": "Feature",
  "properties": {
    "addr:full":"808 Valley Forge Rd Phoenixville PA 19460",
    "addr:housenumber":"808",
    "addr:postcode":"19460",
    "addr:street":"Valley Forge Rd",
    "iso:country":"US",
    "sg:address":"808 Valley Forge Rd",
    "sg:city":"Phoenixville",
    "sg:classifiers":[
        {
            "category":"Insurance",
            "subcategory":"Insurance Agent",
            "type":"Services"
        }
    ],
    "sg:phone":"+1 610 935 9458",
    "sg:postcode":"19460",
    "sg:province":"PA",
    "wof:name":"Allstate Insurance",
    "wof:placetype":"venue"
},
  "geometry": {"coordinates":[-75.50071199999999,40.120096],"type":"Point"}
}