{
  "type": "Feature",
  "properties": {
    "iso:country":"US",
    "sg:address":"617 N Loyalsock Ave",
    "sg:city":"Montoursville",
    "sg:classifiers":[
        {
            "category":"Government",
            "subcategory":"Office",
            "type":"Public Place"
        }
    ],
    "sg:phone":"+1 570 368 8600",
    "sg:postcode":"17754",
    "sg:province":"PA",
    "sg:tags":[
        "village"
    ],
    "wof:name":"Montoursville Boro Building",
    "wof:placetype":"venue"
},
  "geometry": {"coordinates":[-76.92191200000001,41.257578],"type":"Point"}
}