{
  "type": "Feature",
  "properties": {
    "iso:country":"US",
    "sg:address":"25 Brilliant Ave",
    "sg:city":"Pittsburgh",
    "sg:classifiers":[
        {
            "category":"Professional",
            "subcategory":"Business Services",
            "type":"Services"
        }
    ],
    "sg:phone":"+1 412 781 1018",
    "sg:postcode":"15215",
    "sg:province":"PA",
    "sg:tags":[
        "interior",
        "consultant",
        "design",
        "decorator"
    ],
    "wof:name":"Mikell Schenck Assoc Inc",
    "wof:placetype":"venue"
},
  "geometry": {"coordinates":[-79.900988,40.489797],"type":"Point"}
}