{
  "type": "Feature",
  "properties": {
    "addr:full":"952 Mill Rd Bryn Mawr PA 19010",
    "addr:housenumber":"952",
    "addr:postcode":"19010",
    "addr:street":"Mill Rd",
    "iso:country":"US",
    "sg:address":"952 Mill Rd",
    "sg:city":"Bryn Mawr",
    "sg:classifiers":[
        {
            "category":"Food & Beverages",
            "subcategory":"Groceries & Convenience Stores",
            "type":"Retail Goods"
        }
    ],
    "sg:phone":"+1   ",
    "sg:postcode":"19010",
    "sg:province":"PA",
    "sg:tags":[
        "gas"
    ],
    "wof:name":"A Plus Mini Market",
    "wof:placetype":"venue"
},
  "geometry": {"coordinates":[-75.34414599999999,40.00665],"type":"Point"}
}