{
  "type": "Feature",
  "properties": {
    "addr:full":"3222 Richmond St Philadelphia PA 19134",
    "addr:housenumber":"3222",
    "addr:postcode":"19134",
    "addr:street":"Richmond St",
    "iso:country":"US",
    "sg:address":"3222 Richmond St",
    "sg:city":"Philadelphia",
    "sg:classifiers":[
        {
            "category":"Food & Beverages",
            "subcategory":"Groceries & Convenience Stores",
            "type":"Retail Goods"
        }
    ],
    "sg:phone":"+1   ",
    "sg:postcode":"19134",
    "sg:province":"PA",
    "wof:name":"Wawa",
    "wof:placetype":"venue"
},
  "geometry": {"coordinates":[-75.09951599999999,39.983992],"type":"Point"}
}