{
  "type": "Feature",
  "properties": {
    "iso:country":"US",
    "sg:address":"837 High Rock Rd N",
    "sg:city":"Hanover",
    "sg:classifiers":[
        {
            "category":"Building & Trades",
            "subcategory":"Construction",
            "type":"Services"
        }
    ],
    "sg:phone":"+1 717 637 4172",
    "sg:postcode":"17331",
    "sg:province":"PA",
    "sg:tags":[
        "altering",
        "bathroom",
        "remodeling",
        "specialty",
        "contractor"
    ],
    "wof:name":"Kauffman Construction",
    "wof:placetype":"venue"
},
  "geometry": {"coordinates":[-76.947304,39.861695],"type":"Point"}
}