{
  "type": "Feature",
  "properties": {
    "iso:country":"US",
    "sg:address":"7420 Derry St",
    "sg:city":"Swatara",
    "sg:classifiers":[
        {
            "category":"Wholesale",
            "subcategory":"Machinery & Supplies",
            "type":"Manufacturing & Wholesale Goods"
        }
    ],
    "sg:phone":"+1 717 561 8562",
    "sg:postcode":"17111",
    "sg:province":"PA",
    "sg:tags":[
        "hair",
        "dryer"
    ],
    "wof:name":"Noel Enterprises",
    "wof:placetype":"venue"
},
  "geometry": {"coordinates":[-76.757554,40.266416],"type":"Point"}
}