{
  "type": "Feature",
  "properties": {
    "iso:country":"US",
    "sg:address":"680 Hollow Rd",
    "sg:city":"Phoenixville",
    "sg:classifiers":[
        {
            "category":"Manufacturing",
            "subcategory":"Tools & Machinery",
            "type":"Manufacturing & Wholesale Goods"
        }
    ],
    "sg:phone":"+1   ",
    "sg:postcode":"19460",
    "sg:province":"PA",
    "sg:tags":[
        "industrial"
    ],
    "wof:name":"Serail",
    "wof:placetype":"venue"
},
  "geometry": {"coordinates":[-75.49145,40.136409],"type":"Point"}
}