{
  "type": "Feature",
  "properties": {
    "iso:country":"US",
    "sg:address":"1151 Sportsman Rd",
    "sg:city":"Robesonia",
    "sg:classifiers":[
        {
            "category":"Building & Trades",
            "subcategory":"Construction",
            "type":"Services"
        }
    ],
    "sg:phone":"+1 610 693 6368",
    "sg:postcode":"19551",
    "sg:province":"PA",
    "sg:tags":[
        "roofing",
        "contractor"
    ],
    "wof:name":"A & H Roofing",
    "wof:placetype":"venue"
},
  "geometry": {"coordinates":[-76.141048,40.311211],"type":"Point"}
}