{
  "type": "Feature",
  "properties": {
    "addr:full":"316 Allegheny Blvd Franklin PA 16323",
    "addr:housenumber":"316",
    "addr:postcode":"16323",
    "addr:street":"Allegheny Blvd",
    "iso:country":"US",
    "sg:address":"316 Allegheny Blvd",
    "sg:city":"Franklin",
    "sg:classifiers":[
        {
            "category":"Manufacturing",
            "subcategory":"Aerospace",
            "type":"Manufacturing & Wholesale Goods"
        },
        {
            "category":"Autos & Motor Vehicles",
            "subcategory":"Recreational Vehicle Sales",
            "type":"Retail Goods"
        }
    ],
    "sg:phone":"+1 814 437 3074",
    "sg:postcode":"16323",
    "sg:province":"PA",
    "sg:tags":[
        "equipment",
        "aircraft",
        "part",
        "supplies-wholesale",
        "manufacturer"
    ],
    "wof:name":"Penn-Aire Aviation Inc",
    "wof:placetype":"venue"
},
  "geometry": {"coordinates":[-79.81724800000001,41.398178],"type":"Point"}
}