{
  "type": "Feature",
  "properties": {
    "iso:country":"US",
    "sg:address":"19 May Ave",
    "sg:city":"Mc Kees Rocks",
    "sg:classifiers":[
        {
            "category":"Organizations",
            "subcategory":"Non-profit Organization",
            "type":"Services"
        }
    ],
    "sg:phone":"+1 412 331 7712",
    "sg:postcode":"15136",
    "sg:province":"PA",
    "sg:tags":[
        "human"
    ],
    "sg:website":"www.hfi-pgh.org",
    "wof:name":"Holy Family Institute",
    "wof:placetype":"venue"
},
  "geometry": {"coordinates":[-80.064967,40.463882],"type":"Point"}
}