{
  "type": "Feature",
  "properties": {
    "iso:country":"US",
    "sg:address":"110 Tulane Ter",
    "sg:city":"Lancaster",
    "sg:classifiers":[
        {
            "category":"Organizations",
            "subcategory":"Religious Organization",
            "type":"Services"
        }
    ],
    "sg:phone":"+1 717 392 2762",
    "sg:postcode":"17603",
    "sg:province":"PA",
    "sg:tags":[
        "church"
    ],
    "wof:name":"Friends Meeting Quaker",
    "wof:placetype":"venue"
},
  "geometry": {"coordinates":[-76.353008,40.039696],"type":"Point"}
}