{
  "type": "Feature",
  "properties": {
    "iso:country":"US",
    "sg:address":"247 US Hwy 522",
    "sg:city":"Middleburg",
    "sg:classifiers":[
        {
            "category":"Building & Trades",
            "subcategory":"Construction",
            "type":"Services"
        }
    ],
    "sg:phone":"+1 570 837 3775",
    "sg:postcode":"17842",
    "sg:province":"PA",
    "sg:tags":[
        "carpentry",
        "contractor"
    ],
    "wof:name":"Kerstetter Counter Tops",
    "wof:placetype":"venue"
},
  "geometry": {"coordinates":[-77.05304599999999,40.791189],"type":"Point"}
}