{
  "type": "Feature",
  "properties": {
    "addr:full":"381 Brooks Rd King Of Prussia PA 19406",
    "addr:housenumber":"381",
    "addr:postcode":"19406",
    "addr:street":"Brooks Rd",
    "iso:country":"US",
    "sg:address":"381 Brooks Rd",
    "sg:city":"King Of Prussia",
    "sg:classifiers":[
        {
            "category":"Professional",
            "subcategory":"Advertising",
            "type":"Services"
        }
    ],
    "sg:phone":"+1 610 265 5278",
    "sg:postcode":"19406",
    "sg:province":"PA",
    "sg:tags":[
        "counselor"
    ],
    "wof:name":"Printz Advertising",
    "wof:placetype":"venue"
},
  "geometry": {"coordinates":[-75.375496,40.080919],"type":"Point"}
}