{
  "type": "Feature",
  "properties": {
    "iso:country":"US",
    "sg:address":"109 Petrolia St",
    "sg:city":"Petrolia",
    "sg:classifiers":[
        {
            "category":"Organizations",
            "subcategory":"Religious Organization",
            "type":"Services"
        }
    ],
    "sg:phone":"+1 724 756 2633",
    "sg:postcode":"16050",
    "sg:province":"PA",
    "sg:tags":[
        "church"
    ],
    "wof:name":"Fairview United Presbyterian",
    "wof:placetype":"venue"
},
  "geometry": {"coordinates":[-79.74221,41.013382],"type":"Point"}
}