{
  "type": "Feature",
  "properties": {
    "addr:full":"2115 E Berlin Rd East Berlin PA 17316",
    "addr:housenumber":"2115",
    "addr:postcode":"17316",
    "addr:street":"E Berlin Rd",
    "iso:country":"US",
    "sg:address":"2115 E Berlin Rd",
    "sg:city":"East Berlin",
    "sg:classifiers":[
        {
            "category":"Food & Beverages",
            "subcategory":"Groceries & Convenience Stores",
            "type":"Retail Goods"
        }
    ],
    "sg:phone":"+1   ",
    "sg:postcode":"17316",
    "sg:province":"PA",
    "wof:name":"Rutters Farm Store 17",
    "wof:placetype":"venue"
},
  "geometry": {"coordinates":[-77.056701,39.937048],"type":"Point"}
}