{
  "type": "Feature",
  "properties": {
    "addr:full":"128 N 4th St Lewisburg PA 17837",
    "addr:housenumber":"128",
    "addr:postcode":"17837",
    "addr:street":"N 4Th St",
    "iso:country":"US",
    "sg:address":"128 N 4th St",
    "sg:city":"Lewisburg",
    "sg:classifiers":[
        {
            "category":"Banks & Credit Unions",
            "subcategory":"Investment Brokerage",
            "type":"Services"
        }
    ],
    "sg:phone":"+1 570 524 5604",
    "sg:postcode":"17837",
    "sg:province":"PA",
    "sg:tags":[
        "advisory",
        "financial"
    ],
    "wof:name":"Social Insights",
    "wof:placetype":"venue"
},
  "geometry": {"coordinates":[-76.887855,40.96565],"type":"Point"}
}