{
  "type": "Feature",
  "properties": {
    "iso:country":"US",
    "sg:address":"55 Kasi Cir",
    "sg:city":"Warminster",
    "sg:classifiers":[
        {
            "category":"Professional",
            "subcategory":"Engineering",
            "type":"Services"
        }
    ],
    "sg:phone":"+1 267 408 3699",
    "sg:postcode":"18974",
    "sg:province":"PA",
    "sg:tags":[
        "engineer",
        "integration",
        "system"
    ],
    "wof:name":"Nebulent Inc.",
    "wof:placetype":"venue"
},
  "geometry": {"coordinates":[-75.056808,40.21685],"type":"Point"}
}