{
  "type": "Feature",
  "properties": {
    "iso:country":"US",
    "sg:address":"2650 Benshoff Hill Rd",
    "sg:city":"Johnstown",
    "sg:classifiers":[
        {
            "category":"Retail",
            "subcategory":"Repair Shop",
            "type":"Services"
        }
    ],
    "sg:phone":"+1   ",
    "sg:postcode":"15909",
    "sg:province":"PA",
    "wof:name":"Rogers Carpet Upholstery & Clg",
    "wof:placetype":"venue"
},
  "geometry": {"coordinates":[-78.878912,40.41816],"type":"Point"}
}