{
  "type": "Feature",
  "properties": {
    "addr:full":"834 N Bambrey St Philadelphia PA 19130",
    "addr:housenumber":"834",
    "addr:postcode":"19130",
    "addr:street":"N Bambrey St",
    "iso:country":"US",
    "sg:address":"834 N Bambrey St",
    "sg:city":"Philadelphia",
    "sg:classifiers":[
        {
            "category":"Restaurant",
            "type":"Food & Drink"
        }
    ],
    "sg:phone":"+1 215 232 2378",
    "sg:postcode":"19130",
    "sg:province":"PA",
    "sg:tags":[
        "eating"
    ],
    "wof:name":"A Full Plate Catering",
    "wof:placetype":"venue"
},
  "geometry": {"coordinates":[-75.17865500000001,39.972548],"type":"Point"}
}