{
  "type": "Feature",
  "properties": {
    "addr:full":"107 Gibraltar Rd Horsham PA 19044",
    "addr:housenumber":"107",
    "addr:postcode":"19044",
    "addr:street":"Gibraltar Rd",
    "iso:country":"US",
    "sg:address":"107 Gibraltar Rd",
    "sg:city":"Horsham",
    "sg:classifiers":[
        {
            "category":"Food & Beverages",
            "subcategory":"Bakery",
            "type":"Retail Goods"
        }
    ],
    "sg:phone":"+1 215 672 9164",
    "sg:postcode":"19044",
    "sg:province":"PA",
    "sg:tags":[
        "baker"
    ],
    "wof:name":"Pepperidge Farm Inc",
    "wof:placetype":"venue"
},
  "geometry": {"coordinates":[-75.129659,40.169979],"type":"Point"}
}