{
  "type": "Feature",
  "properties": {
    "iso:country":"US",
    "sg:address":"541 N Orianna St",
    "sg:city":"Philadelphia",
    "sg:classifiers":[
        {
            "category":"Wholesale",
            "subcategory":"Electrical",
            "type":"Manufacturing & Wholesale Goods"
        }
    ],
    "sg:phone":"+1   ",
    "sg:postcode":"19123",
    "sg:province":"PA",
    "sg:tags":[
        "farm",
        "equipment",
        "supply"
    ],
    "wof:name":"No Bugs",
    "wof:placetype":"venue"
},
  "geometry": {"coordinates":[-75.144014,39.961329],"type":"Point"}
}