{
  "type": "Feature",
  "properties": {
    "iso:country":"US",
    "sg:address":"3321 Sylvan Dr",
    "sg:city":"Thorndale",
    "sg:classifiers":[
        {
            "category":"Manufacturing",
            "subcategory":"Retail Goods",
            "type":"Manufacturing & Wholesale Goods"
        }
    ],
    "sg:phone":"+1 610 380 1594",
    "sg:postcode":"19372",
    "sg:province":"PA",
    "sg:tags":[
        "assembly",
        "fabricating"
    ],
    "wof:name":"Assemblies Perfected",
    "wof:placetype":"venue"
},
  "geometry": {"coordinates":[-75.760897,40.004359],"type":"Point"}
}