{
  "type": "Feature",
  "properties": {
    "iso:country":"US",
    "sg:address":"620 Reading Terminal Market 1136 Arch Street",
    "sg:city":"Philadelphia",
    "sg:classifiers":[
        {
            "category":"Food & Beverages",
            "subcategory":"Meat & Fish",
            "type":"Retail Goods"
        }
    ],
    "sg:phone":"+1 215 922 0303",
    "sg:postcode":"19107",
    "sg:province":"PA",
    "sg:tags":[
        "shop"
    ],
    "sg:website":"Ochsprimemeats.com",
    "wof:name":"Harry Ochs Prime Meats",
    "wof:placetype":"venue"
},
  "geometry": {"coordinates":[-75.159659,39.953241],"type":"Point"}
}