{
  "type": "Feature",
  "properties": {
    "addr:full":"467 E Beaver Ave State College PA 16801",
    "addr:housenumber":"467",
    "addr:postcode":"16801",
    "addr:street":"E Beaver Ave",
    "iso:country":"US",
    "sg:address":"467 E Beaver Ave",
    "sg:city":"State College",
    "sg:classifiers":[
        {
            "category":"Building & Trades",
            "subcategory":"Construction",
            "type":"Services"
        }
    ],
    "sg:phone":"+1   ",
    "sg:postcode":"16801",
    "sg:province":"PA",
    "sg:tags":[
        "low",
        "housing",
        "build",
        "income"
    ],
    "wof:name":"Sunrise Homes",
    "wof:placetype":"venue"
},
  "geometry": {"coordinates":[-77.854252,40.798011],"type":"Point"}
}