{
  "type": "Feature",
  "properties": {
    "iso:country":"US",
    "sg:address":"6430 Sackett St",
    "sg:city":"Philadelphia",
    "sg:classifiers":[
        {
            "category":"Shopping",
            "subcategory":"Shoes",
            "type":"Retail Goods"
        }
    ],
    "sg:phone":"+1 215 333 5204",
    "sg:postcode":"19149",
    "sg:province":"PA",
    "sg:tags":[
        "sportswear"
    ],
    "sg:website":"http://www.footlocker.com",
    "wof:name":"Foot Locker",
    "wof:placetype":"venue"
},
  "geometry": {"coordinates":[-75.05824800000001,40.029025],"type":"Point"}
}