{
  "type": "Feature",
  "properties": {
    "addr:full":"2838 Woodhaven Rd Philadelphia PA 19154",
    "addr:housenumber":"2838",
    "addr:postcode":"19154",
    "addr:street":"Woodhaven Rd",
    "iso:country":"US",
    "sg:address":"2838 Woodhaven Rd",
    "sg:city":"Philadelphia",
    "sg:classifiers":[
        {
            "category":"Government",
            "subcategory":"Office",
            "type":"Public Place"
        }
    ],
    "sg:phone":"+1   ",
    "sg:postcode":"19154",
    "sg:province":"PA",
    "sg:tags":[
        "national",
        "security"
    ],
    "wof:name":"C Estrella Jr Fidel",
    "wof:placetype":"venue"
},
  "geometry": {"coordinates":[-74.99021500000001,40.101981],"type":"Point"}
}