{
  "type": "Feature",
  "properties": {
    "iso:country":"US",
    "sg:address":"516 Trenton Rd",
    "sg:city":"Fairless Hills",
    "sg:classifiers":[
        {
            "category":"Professional",
            "type":"Services"
        }
    ],
    "sg:phone":"+1   ",
    "sg:postcode":"19030",
    "sg:province":"PA",
    "wof:name":"Galloway Bros",
    "wof:placetype":"venue"
},
  "geometry": {"coordinates":[-74.85049600000001,40.179249],"type":"Point"}
}