{
  "type": "Feature",
  "properties": {
    "iso:country":"US",
    "sg:address":"600 Centerview Ln",
    "sg:city":"Hershey",
    "sg:classifiers":[
        {
            "category":"Professional",
            "subcategory":"Lawyer & Legal Services",
            "type":"Services"
        }
    ],
    "sg:phone":"+1   ",
    "sg:postcode":"17033",
    "sg:province":"PA",
    "wof:name":"Mc Quaide Blaski Schwartz",
    "wof:placetype":"venue"
},
  "geometry": {"coordinates":[-76.673117,40.264058],"type":"Point"}
}