{
  "type": "Feature",
  "properties": {
    "addr:full":"1034 W Richardson Ave Langhorne PA 19047",
    "addr:housenumber":"1034",
    "addr:postcode":"19047",
    "addr:street":"W Richardson Ave Langhorne Pa",
    "iso:country":"US",
    "sg:address":"1034 W Richardson Ave",
    "sg:city":"Langhorne",
    "sg:classifiers":[
        {
            "category":"Building & Trades",
            "subcategory":"Construction",
            "type":"Services"
        }
    ],
    "sg:phone":"+1 215 598 9090",
    "sg:postcode":"19047",
    "sg:province":"PA",
    "sg:tags":[
        "designer",
        "dealer",
        "pool",
        "swimming"
    ],
    "wof:name":"Forchetti Pools & Spa",
    "wof:placetype":"venue"
},
  "geometry": {"coordinates":[-74.93150900000001,40.170352],"type":"Point"}
}