{
  "type": "Feature",
  "properties": {
    "iso:country":"US",
    "sg:address":"3427 Hummingbird Ln",
    "sg:city":"Sharpsville",
    "sg:classifiers":[
        {
            "category":"Shopping",
            "subcategory":"Stationery & Office Supplies",
            "type":"Retail Goods"
        }
    ],
    "sg:phone":"+1 724 962 7207",
    "sg:postcode":"16150",
    "sg:province":"PA",
    "sg:tags":[
        "album",
        "scrapbook"
    ],
    "wof:name":"Creative Memories Director",
    "wof:placetype":"venue"
},
  "geometry": {"coordinates":[-80.441,41.27964],"type":"Point"}
}