{
  "type": "Feature",
  "properties": {
    "iso:country":"US",
    "sg:address":"659 S Main St",
    "sg:city":"Washington",
    "sg:classifiers":[
        {
            "category":"Organizations",
            "subcategory":"Non-profit Organization",
            "type":"Services"
        }
    ],
    "sg:phone":"+1   ",
    "sg:postcode":"15301",
    "sg:province":"PA",
    "sg:tags":[
        "social"
    ],
    "wof:name":"REM PA",
    "wof:placetype":"venue"
},
  "geometry": {"coordinates":[-80.240533,40.162028],"type":"Point"}
}