{
  "type": "Feature",
  "properties": {
    "iso:country":"US",
    "sg:address":"8301 Torresdale Ave",
    "sg:city":"Philadelphia",
    "sg:classifiers":[
        {
            "category":"Professional",
            "subcategory":"Business Services",
            "type":"Services"
        }
    ],
    "sg:phone":"+1 215 333 1100",
    "sg:postcode":"19136",
    "sg:province":"PA",
    "sg:tags":[
        "recording",
        "studio"
    ],
    "wof:name":"Ground Control Recording",
    "wof:placetype":"venue"
},
  "geometry": {"coordinates":[-75.016378,40.039712],"type":"Point"}
}