{
  "type": "Feature",
  "properties": {
    "iso:country":"US",
    "sg:address":"310 Abbey Ln",
    "sg:city":"Lansdale",
    "sg:classifiers":[
        {
            "category":"Professional",
            "type":"Services"
        }
    ],
    "sg:phone":"+1   ",
    "sg:postcode":"19446",
    "sg:province":"PA",
    "wof:name":"Location 2",
    "wof:placetype":"venue"
},
  "geometry": {"coordinates":[-75.230238,40.248988],"type":"Point"}
}