{
  "type": "Feature",
  "properties": {
    "iso:country":"US",
    "sg:address":"3606 Nicholas St",
    "sg:city":"Easton",
    "sg:classifiers":[
        {
            "category":"Personal",
            "subcategory":"Beauty Salon",
            "type":"Services"
        }
    ],
    "sg:phone":"+1 610 258 9288",
    "sg:postcode":"18045",
    "sg:province":"PA",
    "sg:tags":[
        "manicuring"
    ],
    "wof:name":"Nails By Kirri",
    "wof:placetype":"venue"
},
  "geometry": {"coordinates":[-75.26293699999999,40.672198],"type":"Point"}
}