{
  "type": "Feature",
  "properties": {
    "iso:country":"US",
    "sg:address":"60 Federal Dr ",
    "sg:city":"Pittsburgh",
    "sg:classifiers":[
        {
            "category":"Restaurant",
            "type":"Food & Drink"
        }
    ],
    "sg:menulink":"http://www.allmenus.com/pa/penn-hills/286551-sichuan-palace/menu/",
    "sg:phone":"+1 412 241 7110",
    "sg:postcode":"15235",
    "sg:province":"PA",
    "sg:tags":[
        "asian",
        "chinese"
    ],
    "wof:name":"Sichuan Palace",
    "wof:placetype":"venue"
},
  "geometry": {"coordinates":[-79.827063,40.462851],"type":"Point"}
}