{
  "type": "Feature",
  "properties": {
    "addr:full":"4559 Peoples Rd Pittsburgh PA 15237",
    "addr:housenumber":"4559",
    "addr:postcode":"15237",
    "addr:street":"Peoples Rd",
    "iso:country":"US",
    "sg:address":"4559 Peoples Rd",
    "sg:city":"Pittsburgh",
    "sg:classifiers":[
        {
            "category":"Building & Trades",
            "subcategory":"Plumbing",
            "type":"Services"
        }
    ],
    "sg:phone":"+1   ",
    "sg:postcode":"15237",
    "sg:province":"PA",
    "sg:tags":[
        "air",
        "heating",
        "conditioning",
        "contractor"
    ],
    "wof:name":"Sauer J A Heating & AC",
    "wof:placetype":"venue"
},
  "geometry": {"coordinates":[-80.003625,40.501139],"type":"Point"}
}