{
  "type": "Feature",
  "properties": {
    "iso:country":"US",
    "sg:address":"701 Sunflower Dr",
    "sg:city":"Du Bois",
    "sg:classifiers":[
        {
            "category":"Health Services",
            "subcategory":"Doctor",
            "type":"Services"
        }
    ],
    "sg:phone":"+1 814 375 0600",
    "sg:postcode":"15801",
    "sg:province":"PA",
    "sg:tags":[
        "physician",
        "surgeon"
    ],
    "wof:name":"Thomas J Bradley PC",
    "wof:placetype":"venue"
},
  "geometry": {"coordinates":[-78.74831399999999,41.116302],"type":"Point"}
}