{
  "type": "Feature",
  "properties": {
    "addr:full":"436 York Rd Jenkintown PA 19046",
    "addr:housenumber":"436",
    "addr:postcode":"19046",
    "addr:street":"York Rd",
    "iso:country":"US",
    "sg:address":"436 York Rd",
    "sg:city":"Jenkintown",
    "sg:classifiers":[
        {
            "category":"Professional",
            "subcategory":"Lawyer & Legal Services",
            "type":"Services"
        }
    ],
    "sg:phone":"+1 215 885 0900",
    "sg:postcode":"19046",
    "sg:province":"PA",
    "sg:tags":[
        "attorney"
    ],
    "wof:name":"Stephen B Lavner",
    "wof:placetype":"venue"
},
  "geometry": {"coordinates":[-75.126447,40.090431],"type":"Point"}
}