{
  "type": "Feature",
  "properties": {
    "iso:country":"US",
    "sg:address":"215 E Main St",
    "sg:city":"Ligonier",
    "sg:classifiers":[
        {
            "category":"Mining & Drilling",
            "type":"Manufacturing & Wholesale Goods"
        }
    ],
    "sg:phone":"+1 724 238 2239",
    "sg:postcode":"15658",
    "sg:province":"PA",
    "sg:tags":[
        "oil",
        "gas",
        "producer"
    ],
    "wof:name":"Fayette Oil & Gas Inc",
    "wof:placetype":"venue"
},
  "geometry": {"coordinates":[-79.236193,40.241866],"type":"Point"}
}