{
  "type": "Feature",
  "properties": {
    "iso:country":"US",
    "sg:address":"3550 Paxton St",
    "sg:city":"Harrisburg",
    "sg:classifiers":[
        {
            "category":"Restaurant",
            "type":"Food & Drink"
        }
    ],
    "sg:phone":"+1   ",
    "sg:postcode":"17111",
    "sg:province":"PA",
    "sg:tags":[
        "steakhouse",
        "family"
    ],
    "wof:name":"Ponderosa Steakhouse",
    "wof:placetype":"venue"
},
  "geometry": {"coordinates":[-76.829258,40.253836],"type":"Point"}
}