{
  "type": "Feature",
  "properties": {
    "iso:country":"US",
    "sg:address":"1809 Lake St",
    "sg:city":"Lake City",
    "sg:classifiers":[
        {
            "category":"Building & Trades",
            "subcategory":"Cleaning & Sanitation",
            "type":"Services"
        }
    ],
    "sg:phone":"+1 814 774 9110",
    "sg:postcode":"16423",
    "sg:province":"PA",
    "sg:tags":[
        "janitor"
    ],
    "wof:name":"Erie Custom Cleaning Svc",
    "wof:placetype":"venue"
},
  "geometry": {"coordinates":[-80.345218,42.016578],"type":"Point"}
}