{
  "type": "Feature",
  "properties": {
    "iso:country":"US",
    "sg:address":"501 Trenton Rd",
    "sg:city":"Langhorne",
    "sg:classifiers":[
        {
            "category":"Education",
            "subcategory":"School",
            "type":"Public Place"
        }
    ],
    "sg:phone":"+1 215 752 9300",
    "sg:postcode":"19047",
    "sg:province":"PA",
    "wof:name":"Hoover Elementary School",
    "wof:placetype":"venue"
},
  "geometry": {"coordinates":[-74.90421499999999,40.148914],"type":"Point"}
}