{
  "type": "Feature",
  "properties": {
    "iso:country":"US",
    "sg:address":"200 Evergreen Rd",
    "sg:city":"New Cumberland",
    "sg:classifiers":[
        {
            "category":"Real Estate",
            "subcategory":"Real Estate Operator",
            "type":"Services"
        }
    ],
    "sg:phone":"+1   ",
    "sg:postcode":"17070",
    "sg:province":"PA",
    "sg:tags":[
        "mobile",
        "home",
        "site"
    ],
    "wof:name":"Frank W & Elizabeth J Stu",
    "wof:placetype":"venue"
},
  "geometry": {"coordinates":[-76.8665,40.207549],"type":"Point"}
}