{
  "type": "Feature",
  "properties": {
    "iso:country":"US",
    "sg:address":"195 N Wales Rd",
    "sg:city":"North Wales",
    "sg:classifiers":[
        {
            "category":"Real Estate",
            "subcategory":"Real Estate Operator",
            "type":"Services"
        }
    ],
    "sg:phone":"+1 215 368 3663",
    "sg:postcode":"19454",
    "sg:province":"PA",
    "sg:tags":[
        "mobile",
        "home",
        "site"
    ],
    "wof:name":"Village Of Neshaminy Falls",
    "wof:placetype":"venue"
},
  "geometry": {"coordinates":[-75.25970100000001,40.231105],"type":"Point"}
}