{
  "type": "Feature",
  "properties": {
    "iso:country":"US",
    "sg:address":"3006 Kingwood Rd",
    "sg:city":"Rockwood",
    "sg:classifiers":[
        {
            "category":"Home & Garden",
            "subcategory":"Home Furnishings",
            "type":"Retail Goods"
        }
    ],
    "sg:phone":"+1 814 926 9961",
    "sg:postcode":"15557",
    "sg:province":"PA",
    "sg:tags":[
        "stove",
        "wood",
        "burning"
    ],
    "wof:name":"New Centerville Stove",
    "wof:placetype":"venue"
},
  "geometry": {"coordinates":[-79.191986,39.942297],"type":"Point"}
}