{
  "type": "Feature",
  "properties": {
    "addr:full":"320 N Kenhorst Blvd Reading PA 19607",
    "addr:housenumber":"320",
    "addr:postcode":"19607",
    "addr:street":"N Kenhorst Blvd",
    "iso:country":"US",
    "sg:address":"320 N Kenhorst Blvd",
    "sg:city":"Reading",
    "sg:classifiers":[
        {
            "category":"Professional",
            "subcategory":"Management & Consulting",
            "type":"Services"
        }
    ],
    "sg:phone":"+1   ",
    "sg:postcode":"19607",
    "sg:province":"PA",
    "sg:tags":[
        "fund",
        "raising"
    ],
    "wof:name":"Capital Venture",
    "wof:placetype":"venue"
},
  "geometry": {"coordinates":[-75.950442,40.316573],"type":"Point"}
}