{
  "type": "Feature",
  "properties": {
    "addr:full":"50 W Main St Glen Lyon PA 18617",
    "addr:housenumber":"50",
    "addr:postcode":"18617",
    "addr:street":"W Main St Glen",
    "iso:country":"US",
    "sg:address":"50 W Main St",
    "sg:city":"Glen Lyon",
    "sg:classifiers":[
        {
            "category":"Retail",
            "subcategory":"Animal Services",
            "type":"Services"
        }
    ],
    "sg:phone":"+1   ",
    "sg:postcode":"18617",
    "sg:province":"PA",
    "sg:tags":[
        "merchandise"
    ],
    "wof:name":"Whitings Rub A Dub Doggie",
    "wof:placetype":"venue"
},
  "geometry": {"coordinates":[-76.07478999999999,41.174269],"type":"Point"}
}