{
  "type": "Feature",
  "properties": {
    "iso:country":"US",
    "sg:address":"27 S State St",
    "sg:city":"Newtown",
    "sg:classifiers":[
        {
            "category":"Professional",
            "subcategory":"Lawyer & Legal Services",
            "type":"Services"
        }
    ],
    "sg:phone":"+1 215 862 9461",
    "sg:postcode":"18940",
    "sg:province":"PA",
    "sg:tags":[
        "attorney"
    ],
    "wof:name":"Cordes King LLP",
    "wof:placetype":"venue"
},
  "geometry": {"coordinates":[-74.93679400000001,40.228263],"type":"Point"}
}