{
  "type": "Feature",
  "properties": {
    "iso:country":"US",
    "sg:address":"7 Grove St",
    "sg:city":"Washington",
    "sg:classifiers":[
        {
            "category":"Building & Trades",
            "subcategory":"Plumbing",
            "type":"Services"
        }
    ],
    "sg:phone":"+1   ",
    "sg:postcode":"15301",
    "sg:province":"PA",
    "sg:tags":[
        "contractor"
    ],
    "wof:name":"Dague & Salsberry Plbg & Htg",
    "wof:placetype":"venue"
},
  "geometry": {"coordinates":[-80.256947,40.168528],"type":"Point"}
}