{
  "type": "Feature",
  "properties": {
    "iso:country":"US",
    "sg:address":"1322 W Chester Rd",
    "sg:city":"West Chester",
    "sg:classifiers":[
        {
            "category":"Real Estate",
            "subcategory":"Real Estate Operator",
            "type":"Services"
        }
    ],
    "sg:phone":"+1   ",
    "sg:postcode":"19382",
    "sg:province":"PA",
    "sg:tags":[
        "building",
        "nonresidential"
    ],
    "wof:name":"Ridley Creek Plaza",
    "wof:placetype":"venue"
},
  "geometry": {"coordinates":[-75.547256,39.911071],"type":"Point"}
}