{
  "type": "Feature",
  "properties": {
    "addr:full":"1311 W Chester Rd West Chester PA 19382",
    "addr:housenumber":"1311",
    "addr:postcode":"19382",
    "addr:street":"W Chester Rd",
    "iso:country":"US",
    "sg:address":"1311 W Chester Rd",
    "sg:city":"West Chester",
    "sg:classifiers":[
        {
            "category":"Education",
            "subcategory":"Special Training",
            "type":"Public Place"
        }
    ],
    "sg:phone":"+1 610 719 6448",
    "sg:postcode":"19382",
    "sg:province":"PA",
    "sg:tags":[
        "reading",
        "instruction",
        "improvement"
    ],
    "wof:name":"Literacy Empowerment Fndtn",
    "wof:placetype":"venue"
},
  "geometry": {"coordinates":[-75.547202,39.911213],"type":"Point"}
}