{
  "type": "Feature",
  "properties": {
    "addr:full":"330 E Norwegian St Pottsville PA 17901",
    "addr:housenumber":"330",
    "addr:postcode":"17901",
    "addr:street":"E Norwegian St",
    "iso:country":"US",
    "sg:address":"330 E Norwegian St",
    "sg:city":"Pottsville",
    "sg:classifiers":[
        {
            "category":"Manufacturing",
            "subcategory":"Electronics",
            "type":"Manufacturing & Wholesale Goods"
        }
    ],
    "sg:phone":"+1 570 622 7866",
    "sg:postcode":"17901",
    "sg:province":"PA",
    "sg:tags":[
        "equipment",
        "electronic",
        "supply"
    ],
    "wof:name":"Moyer Electronic Supply Co",
    "wof:placetype":"venue"
},
  "geometry": {"coordinates":[-76.19234899999999,40.686746],"type":"Point"}
}