{
  "type": "Feature",
  "properties": {
    "addr:full":"5023 Frew St Pittsburgh PA 15213",
    "addr:housenumber":"5023",
    "addr:postcode":"15213",
    "addr:street":"Frew St",
    "iso:country":"US",
    "sg:address":"5023 Frew St",
    "sg:city":"Pittsburgh",
    "sg:classifiers":[
        {
            "category":"Real Estate",
            "subcategory":"Real Estate Operator",
            "type":"Services"
        }
    ],
    "sg:phone":"+1 412 682 2000",
    "sg:postcode":"15213",
    "sg:province":"PA",
    "sg:tags":[
        "building",
        "apartment"
    ],
    "wof:name":"Park Mansions Inc",
    "wof:placetype":"venue"
},
  "geometry": {"coordinates":[-79.940793,40.440217],"type":"Point"}
}