{
  "type": "Feature",
  "properties": {
    "iso:country":"US",
    "sg:address":"31 E Franklin St",
    "sg:city":"Ephrata",
    "sg:classifiers":[
        {
            "category":"Manufacturing",
            "subcategory":"Rubber & Plastics",
            "type":"Manufacturing & Wholesale Goods"
        }
    ],
    "sg:phone":"+1   ",
    "sg:postcode":"17522",
    "sg:province":"PA",
    "sg:tags":[
        "product",
        "mfg"
    ],
    "wof:name":"Integrity Plastics",
    "wof:placetype":"venue"
},
  "geometry": {"coordinates":[-76.176937,40.17674],"type":"Point"}
}