{
  "type": "Feature",
  "properties": {
    "addr:full":"31 E Franklin St Ephrata PA 17522",
    "addr:housenumber":"31",
    "addr:postcode":"17522",
    "addr:street":"E Franklin St",
    "iso:country":"US",
    "sg:address":"31 E Franklin St",
    "sg:city":"Ephrata",
    "sg:classifiers":[
        {
            "category":"Manufacturing",
            "subcategory":"Rubber & Plastics",
            "type":"Manufacturing & Wholesale Goods"
        }
    ],
    "sg:phone":"+1   ",
    "sg:postcode":"17522",
    "sg:province":"PA",
    "sg:tags":[
        "product",
        "mfg"
    ],
    "wof:name":"Integrity Plastics",
    "wof:placetype":"venue"
},
  "geometry": {"coordinates":[-76.176937,40.17674],"type":"Point"}
}