{
  "type": "Feature",
  "properties": {
    "iso:country":"US",
    "sg:address":"1429 Walnut St",
    "sg:city":"Philadelphia",
    "sg:classifiers":[
        {
            "category":"Professional",
            "subcategory":"Business Services",
            "type":"Services"
        }
    ],
    "sg:phone":"+1 215 496 9975",
    "sg:postcode":"19102",
    "sg:province":"PA",
    "wof:name":"Business Development Group",
    "wof:placetype":"venue"
},
  "geometry": {"coordinates":[-75.165576,39.949568],"type":"Point"}
}