{
  "type": "Feature",
  "properties": {
    "iso:country":"US",
    "sg:address":"12th St & Arch Street Reading Terminal Market",
    "sg:city":"Philadelphia",
    "sg:classifiers":[
        {
            "category":"Restaurant",
            "type":"Food & Drink"
        }
    ],
    "sg:postcode":"19176",
    "sg:province":"PA",
    "wof:name":"AJ Pickle Patch and Salads",
    "wof:placetype":"venue"
},
  "geometry": {"coordinates":[-75.15946599999999,39.953949],"type":"Point"}
}