{
  "type": "Feature",
  "properties": {
    "iso:country":"US",
    "sg:address":"184 Fireside Dr",
    "sg:city":"Canonsburg",
    "sg:classifiers":[
        {
            "category":"Retail",
            "subcategory":"Portrait Studio",
            "type":"Services"
        },
        {
            "category":"Professional",
            "subcategory":"Art Services",
            "type":"Services"
        }
    ],
    "sg:phone":"+1 724 941 2002",
    "sg:postcode":"15317",
    "sg:province":"PA",
    "sg:tags":[
        "photographer",
        "photography",
        "store"
    ],
    "wof:name":"Haritan Michael",
    "wof:placetype":"venue"
},
  "geometry": {"coordinates":[-80.094498,40.268101],"type":"Point"}
}