{
  "type": "Feature",
  "properties": {
    "addr:full":"2305 Duss Ave Ambridge PA 15003",
    "addr:housenumber":"2305",
    "addr:postcode":"15003",
    "addr:street":"Duss Ave",
    "iso:country":"US",
    "sg:address":"2305 Duss Ave",
    "sg:city":"Ambridge",
    "sg:classifiers":[
        {
            "category":"Manufacturing",
            "subcategory":"Rubber & Plastics",
            "type":"Manufacturing & Wholesale Goods"
        }
    ],
    "sg:phone":"+1 724 266 8770",
    "sg:postcode":"15003",
    "sg:province":"PA",
    "wof:name":"Advanced Alloys Div",
    "wof:placetype":"venue"
},
  "geometry": {"coordinates":[-80.226353,40.605162],"type":"Point"}
}