{
  "type": "Feature",
  "properties": {
    "iso:country":"US",
    "sg:address":"7 S Market St",
    "sg:city":"Selinsgrove",
    "sg:classifiers":[
        {
            "category":"Restaurant",
            "type":"Food & Drink"
        }
    ],
    "sg:phone":"+1 570 374 9074",
    "sg:postcode":"17870",
    "sg:province":"PA",
    "wof:name":"Bot's Cafe Inc",
    "wof:placetype":"venue"
},
  "geometry": {"coordinates":[-76.861902,40.799317],"type":"Point"}
}