{
  "type": "Feature",
  "properties": {
    "iso:country":"US",
    "sg:address":"211 N 2nd St",
    "sg:city":"Wrightsville",
    "sg:classifiers":[
        {
            "category":"Organizations",
            "subcategory":"Religious Organization",
            "type":"Services"
        }
    ],
    "sg:phone":"+1 717 252 1302",
    "sg:postcode":"17368",
    "sg:province":"PA",
    "sg:tags":[
        "church"
    ],
    "wof:name":"Wrightsville Presbyterian Chr",
    "wof:placetype":"venue"
},
  "geometry": {"coordinates":[-76.530399,40.026931],"type":"Point"}
}