{
  "type": "Feature",
  "properties": {
    "iso:country":"US",
    "sg:address":"135 North Ave",
    "sg:city":"Sewickley",
    "sg:classifiers":[
        {
            "category":"Professional",
            "subcategory":"Computer Services",
            "type":"Services"
        }
    ],
    "sg:phone":"+1 412 741 9510",
    "sg:postcode":"15143",
    "sg:province":"PA",
    "sg:tags":[
        "programing",
        "custom"
    ],
    "wof:name":"Duro Water Conditioning",
    "wof:placetype":"venue"
},
  "geometry": {"coordinates":[-80.18288,40.581851],"type":"Point"}
}