{
  "type": "Feature",
  "properties": {
    "iso:country":"US",
    "sg:address":"5300 Tabor Ave",
    "sg:city":"Philadelphia",
    "sg:classifiers":[
        {
            "category":"Banks & Credit Unions",
            "subcategory":"Bank",
            "type":"Services"
        }
    ],
    "sg:phone":"+1 215 533 0100",
    "sg:postcode":"19120",
    "sg:province":"PA",
    "sg:tags":[
        "cashing",
        "check"
    ],
    "wof:name":"A & T Check Cashing",
    "wof:placetype":"venue"
},
  "geometry": {"coordinates":[-75.105935,40.0341],"type":"Point"}
}