{
  "type": "Feature",
  "properties": {
    "addr:full":"3558 W 26th St Erie PA 16506",
    "addr:housenumber":"3558",
    "addr:postcode":"16506",
    "addr:street":"W 26Th St",
    "iso:country":"US",
    "sg:address":"3558 W 26th St",
    "sg:city":"Erie",
    "sg:classifiers":[
        {
            "category":"Retail",
            "subcategory":"Laundry & Dry Cleaning",
            "type":"Services"
        }
    ],
    "sg:phone":"+1 814 833 8767",
    "sg:postcode":"16506",
    "sg:province":"PA",
    "sg:tags":[
        "power"
    ],
    "wof:name":"Laundry Express",
    "wof:placetype":"venue"
},
  "geometry": {"coordinates":[-80.152455,42.082564],"type":"Point"}
}