{
  "type": "Feature",
  "properties": {
    "iso:country":"US",
    "sg:address":"551 Keystone Dr",
    "sg:city":"Warrendale",
    "sg:classifiers":[
        {
            "category":"Wholesale",
            "subcategory":"Machinery & Supplies",
            "type":"Manufacturing & Wholesale Goods"
        }
    ],
    "sg:phone":"+1 724 776 1818",
    "sg:postcode":"15086",
    "sg:province":"PA",
    "sg:tags":[
        "equipment",
        "industrial",
        "safety"
    ],
    "sg:website":"www.pro-am.com",
    "wof:name":"Pro-AM Safety Inc",
    "wof:placetype":"venue"
},
  "geometry": {"coordinates":[-80.11403199999999,40.667935],"type":"Point"}
}