{
  "type": "Feature",
  "properties": {
    "iso:country":"US",
    "sg:address":"1000 Pittsburgh St",
    "sg:city":"North Versailles",
    "sg:classifiers":[
        {
            "category":"Shopping",
            "subcategory":"Musical Instruments",
            "type":"Retail Goods"
        }
    ],
    "sg:phone":"+1   ",
    "sg:postcode":"15137",
    "sg:province":"PA",
    "sg:tags":[
        "repair"
    ],
    "wof:name":"Yadco Music",
    "wof:placetype":"venue"
},
  "geometry": {"coordinates":[-79.82835799999999,40.392196],"type":"Point"}
}