{
  "type": "Feature",
  "properties": {
    "iso:country":"US",
    "sg:address":"477 W 7th Ave",
    "sg:city":"Homestead",
    "sg:classifiers":[
        {
            "category":"Manufacturing",
            "subcategory":"Textiles",
            "type":"Manufacturing & Wholesale Goods"
        }
    ],
    "sg:phone":"+1 412 462 3900",
    "sg:postcode":"15120",
    "sg:province":"PA",
    "sg:tags":[
        "upholsterer",
        "supply"
    ],
    "wof:name":"Three Rivers Supply Co",
    "wof:placetype":"venue"
},
  "geometry": {"coordinates":[-79.918269,40.40225],"type":"Point"}
}