{
  "type": "Feature",
  "properties": {
    "addr:full":"415 Brighton St Bethlehem PA 18015",
    "addr:housenumber":"415",
    "addr:postcode":"18015",
    "addr:street":"Brighton St",
    "iso:country":"US",
    "sg:address":"415 Brighton St",
    "sg:city":"Bethlehem",
    "sg:classifiers":[
        {
            "category":"Education",
            "subcategory":"School",
            "type":"Public Place"
        }
    ],
    "sg:phone":"+1 610 868 2637",
    "sg:postcode":"18015",
    "sg:province":"PA",
    "sg:website":"www.amdetective.us",
    "wof:name":"American Detective Agency",
    "wof:placetype":"venue"
},
  "geometry": {"coordinates":[-75.38460000000001,40.6136],"type":"Point"}
}