{
  "type": "Feature",
  "properties": {
    "addr:full":"6609 Mars Rd Cranberry Twp PA 16066",
    "addr:housenumber":"6609",
    "addr:postcode":"16066",
    "addr:street":"Mars Rd",
    "iso:country":"US",
    "sg:address":"6609 Mars Rd",
    "sg:city":"Cranberry Twp",
    "sg:classifiers":[
        {
            "category":"Banks & Credit Unions",
            "subcategory":"Investment Brokerage",
            "type":"Services"
        }
    ],
    "sg:phone":"+1 724 776 6660",
    "sg:postcode":"16066",
    "sg:province":"PA",
    "sg:tags":[
        "investing"
    ],
    "wof:name":"Fisher R L",
    "wof:placetype":"venue"
},
  "geometry": {"coordinates":[-80.086403,40.688999],"type":"Point"}
}