{
  "type": "Feature",
  "properties": {
    "iso:country":"US",
    "sg:address":"2209 Forest Hills Dr",
    "sg:city":"Harrisburg",
    "sg:classifiers":[
        {
            "category":"Professional",
            "type":"Services"
        }
    ],
    "sg:phone":"+1 717 652 4021",
    "sg:postcode":"17112",
    "sg:province":"PA",
    "sg:tags":[
        "establishment"
    ],
    "wof:name":"Martin & Smith Inc",
    "wof:placetype":"venue"
},
  "geometry": {"coordinates":[-76.833641,40.335952],"type":"Point"}
}