{
  "type": "Feature",
  "properties": {
    "iso:country":"US",
    "sg:address":"2220 South St",
    "sg:city":"Philadelphia",
    "sg:classifiers":[
        {
            "category":"Shopping",
            "subcategory":"Discount & Variety Stores",
            "type":"Retail Goods"
        }
    ],
    "sg:phone":"+1 215 545 8010",
    "sg:postcode":"19146",
    "sg:province":"PA",
    "wof:name":"Adrianne's Dollar Store",
    "wof:placetype":"venue"
},
  "geometry": {"coordinates":[-75.179292,39.945281],"type":"Point"}
}