{
  "type": "Feature",
  "properties": {
    "iso:country":"US",
    "sg:address":"2942 Belgrade St",
    "sg:city":"Philadelphia",
    "sg:classifiers":[
        {
            "category":"Education",
            "subcategory":"School",
            "type":"Public Place"
        }
    ],
    "sg:phone":"+1 215 291 6317",
    "sg:postcode":"19134",
    "sg:province":"PA",
    "wof:name":"Schl Dist-Phila Richmond Schl",
    "wof:placetype":"venue"
},
  "geometry": {"coordinates":[-75.110968,39.982869],"type":"Point"}
}