{
  "type": "Feature",
  "properties": {
    "addr:full":"2501 Welsh Rd Philadelphia PA 19114",
    "addr:housenumber":"2501",
    "addr:postcode":"19114",
    "addr:street":"Welsh Rd",
    "iso:country":"US",
    "sg:address":"2501 Welsh Rd",
    "sg:city":"Philadelphia",
    "sg:classifiers":[
        {
            "category":"Banks & Credit Unions",
            "subcategory":"Bank",
            "type":"Services"
        }
    ],
    "sg:phone":"+1   ",
    "sg:postcode":"19114",
    "sg:province":"PA",
    "sg:tags":[
        "state",
        "commercial"
    ],
    "wof:name":"Citizens Bank of Pennsylvania",
    "wof:placetype":"venue"
},
  "geometry": {"coordinates":[-75.03414600000001,40.074072],"type":"Point"}
}