{
  "type": "Feature",
  "properties": {
    "iso:country":"US",
    "sg:address":"1331 S 7th St",
    "sg:city":"Chambersburg",
    "sg:classifiers":[
        {
            "category":"Government",
            "subcategory":"Office",
            "type":"Public Place"
        }
    ],
    "sg:phone":"+1   ",
    "sg:postcode":"17201",
    "sg:province":"PA",
    "sg:tags":[
        "environmental",
        "resource"
    ],
    "wof:name":"Chambersburg District Office",
    "wof:placetype":"venue"
},
  "geometry": {"coordinates":[-77.657279,39.917907],"type":"Point"}
}