{
  "type": "Feature",
  "properties": {
    "addr:full":"2170 Barr Slope Rd Dixonville PA 15728",
    "addr:housenumber":"2170",
    "addr:postcode":"15728",
    "addr:street":"Barr Slope Rd",
    "iso:country":"US",
    "sg:address":"2170 Barr Slope Rd",
    "sg:city":"Dixonville",
    "sg:classifiers":[
        {
            "category":"Manufacturing",
            "subcategory":"Glass & Minerals",
            "type":"Manufacturing & Wholesale Goods"
        }
    ],
    "sg:phone":"+1 724 254 4321",
    "sg:postcode":"15728",
    "sg:province":"PA",
    "sg:tags":[
        "blackboard"
    ],
    "sg:website":"www.polyvision.com",
    "wof:name":"Poly Vision Corp",
    "wof:placetype":"venue"
},
  "geometry": {"coordinates":[-79.012128,40.712468],"type":"Point"}
}