{
  "type": "Feature",
  "properties": {
    "iso:country":"US",
    "sg:address":"1180 Benton Pl",
    "sg:city":"Pittsburgh",
    "sg:classifiers":[
        {
            "category":"Building & Trades",
            "subcategory":"Landscaping Services",
            "type":"Services"
        }
    ],
    "sg:phone":"+1 412 761 6485",
    "sg:postcode":"15212",
    "sg:province":"PA",
    "sg:tags":[
        "landscape",
        "contractor"
    ],
    "wof:name":"Besterman Lawn Care",
    "wof:placetype":"venue"
},
  "geometry": {"coordinates":[-80.034936,40.490057],"type":"Point"}
}