{
  "type": "Feature",
  "properties": {
    "addr:full":"1419 E Boot Rd West Chester PA 19380",
    "addr:housenumber":"1419",
    "addr:postcode":"19380",
    "addr:street":"E Boot Rd",
    "iso:country":"US",
    "sg:address":"1419 E Boot Rd",
    "sg:city":"West Chester",
    "sg:classifiers":[
        {
            "category":"Building & Trades",
            "subcategory":"Plumbing",
            "type":"Services"
        }
    ],
    "sg:phone":"+1 610 344 7234",
    "sg:postcode":"19380",
    "sg:province":"PA",
    "sg:tags":[
        "air",
        "heating",
        "conditioning",
        "contractor"
    ],
    "wof:name":"Chester County Fuel Oil Inc",
    "wof:placetype":"venue"
},
  "geometry": {"coordinates":[-75.56701099999999,39.997574],"type":"Point"}
}