{
  "type": "Feature",
  "properties": {
    "iso:country":"US",
    "sg:address":"457 Heintzelman Ave",
    "sg:city":"Chambersburg",
    "sg:classifiers":[
        {
            "category":"Organizations",
            "subcategory":"Membership Organization",
            "type":"Services"
        }
    ],
    "sg:phone":"+1   ",
    "sg:postcode":"17201",
    "sg:province":"PA",
    "wof:name":"BMW Club",
    "wof:placetype":"venue"
},
  "geometry": {"coordinates":[-77.669174,39.945528],"type":"Point"}
}