{
  "type": "Feature",
  "properties": {
    "addr:full":"5434 Torresdale Ave Philadelphia PA 19124",
    "addr:housenumber":"5434",
    "addr:postcode":"19124",
    "addr:street":"Torresdale Ave",
    "iso:country":"US",
    "sg:address":"5434 Torresdale Ave",
    "sg:city":"Philadelphia",
    "sg:classifiers":[
        {
            "category":"Deli",
            "type":"Food & Drink"
        },
        {
            "category":"Food & Beverages",
            "subcategory":"Bakery",
            "type":"Retail Goods"
        }
    ],
    "sg:phone":"+1 215 288 2108",
    "sg:postcode":"19124",
    "sg:province":"PA",
    "sg:tags":[
        "sandwich"
    ],
    "wof:name":"Torres",
    "wof:placetype":"venue"
},
  "geometry": {"coordinates":[-75.06599900000001,40.014347],"type":"Point"}
}