{
  "type": "Feature",
  "properties": {
    "iso:country":"US",
    "sg:address":"1019 E Carson St",
    "sg:city":"Pittsburgh",
    "sg:classifiers":[
        {
            "category":"Shopping",
            "type":"Retail Goods"
        }
    ],
    "sg:phone":"+1 412 488 9121",
    "sg:postcode":"15203",
    "sg:province":"PA",
    "sg:tags":[
        "merchandise"
    ],
    "wof:name":"Blue Ruin",
    "wof:placetype":"venue"
},
  "geometry": {"coordinates":[-79.987668,40.428795],"type":"Point"}
}