{
  "type": "Feature",
  "properties": {
    "iso:country":"US",
    "sg:address":"339 6th Ave Ste 530",
    "sg:city":"Pittsburgh",
    "sg:classifiers":[
        {
            "category":"Health Services",
            "subcategory":"Doctor",
            "type":"Services"
        }
    ],
    "sg:phone":"+1 412 560 8762",
    "sg:postcode":"15222",
    "sg:province":"PA",
    "wof:name":"Yates Anthony P MD",
    "wof:placetype":"venue"
},
  "geometry": {"coordinates":[-79.99855100000001,40.441826],"type":"Point"}
}