{
  "type": "Feature",
  "properties": {
    "iso:country":"US",
    "sg:address":"131 S Antrim Way",
    "sg:city":"Greencastle",
    "sg:classifiers":[
        {
            "category":"Autos & Motor Vehicles",
            "subcategory":"Automobile Sales",
            "type":"Retail Goods"
        }
    ],
    "sg:phone":"+1 717 597 5257",
    "sg:postcode":"17225",
    "sg:province":"PA",
    "sg:tags":[
        "car",
        "dealer"
    ],
    "wof:name":"Skyline Auto Sales",
    "wof:placetype":"venue"
},
  "geometry": {"coordinates":[-77.731826,39.790106],"type":"Point"}
}