{
  "type": "Feature",
  "properties": {
    "addr:full":"1528 W Front St Berwick PA 18603",
    "addr:housenumber":"1528",
    "addr:postcode":"18603",
    "addr:street":"W Front St",
    "iso:country":"US",
    "sg:address":"1528 W Front St",
    "sg:city":"Berwick",
    "sg:classifiers":[
        {
            "category":"Restaurant",
            "type":"Food & Drink"
        }
    ],
    "sg:phone":"+1 570 752 6968",
    "sg:postcode":"18603",
    "sg:province":"PA",
    "sg:tags":[
        "eating"
    ],
    "wof:name":"Happy Buffet",
    "wof:placetype":"venue"
},
  "geometry": {"coordinates":[-76.258875,41.048804],"type":"Point"}
}