{
  "type": "Feature",
  "properties": {
    "iso:country":"US",
    "sg:address":"1655 Bern Rd",
    "sg:city":"Reading",
    "sg:classifiers":[
        {
            "category":"Shopping",
            "subcategory":"Music",
            "type":"Retail Goods"
        }
    ],
    "sg:phone":"+1   ",
    "sg:postcode":"19610",
    "sg:province":"PA",
    "sg:tags":[
        "record",
        "tape"
    ],
    "wof:name":"Record Town",
    "wof:placetype":"venue"
},
  "geometry": {"coordinates":[-75.972677,40.338377],"type":"Point"}
}