{
  "type": "Feature",
  "properties": {
    "addr:full":"28 N Walnut St Blairsville PA 15717",
    "addr:housenumber":"28",
    "addr:postcode":"15717",
    "addr:street":"N Walnut St",
    "iso:country":"US",
    "sg:address":"28 N Walnut St",
    "sg:city":"Blairsville",
    "sg:classifiers":[
        {
            "category":"Communications",
            "subcategory":"Radio Station",
            "type":"Services"
        }
    ],
    "sg:phone":"+1 724 459 8888",
    "sg:postcode":"15717",
    "sg:province":"PA",
    "sg:tags":[
        "company",
        "broadcasting"
    ],
    "wof:name":"WLCY",
    "wof:placetype":"venue"
},
  "geometry": {"coordinates":[-79.26452999999999,40.431085],"type":"Point"}
}