{
  "type": "Feature",
  "properties": {
    "addr:full":"6338 Ogontz Ave Fl 1 Philadelphia PA 19141",
    "addr:housenumber":"6338;1",
    "addr:postcode":"19141",
    "addr:street":"Ogontz Ave Fl",
    "iso:country":"US",
    "sg:address":"6338 Ogontz Ave Fl 1",
    "sg:city":"Philadelphia",
    "sg:classifiers":[
        {
            "category":"Personal",
            "subcategory":"Beauty Salon",
            "type":"Services"
        }
    ],
    "sg:phone":"+1 215 224 9070",
    "sg:postcode":"19141",
    "sg:province":"PA",
    "wof:name":"Nile Empire",
    "wof:placetype":"venue"
},
  "geometry": {"coordinates":[-75.15034900000001,40.050654],"type":"Point"}
}