{
  "type": "Feature",
  "properties": {
    "iso:country":"US",
    "sg:address":"1823 Foulkrod St",
    "sg:city":"Philadelphia",
    "sg:classifiers":[
        {
            "category":"Building & Trades",
            "subcategory":"Construction",
            "type":"Services"
        }
    ],
    "sg:phone":"+1   ",
    "sg:postcode":"19124",
    "sg:province":"PA",
    "sg:tags":[
        "house"
    ],
    "wof:name":"M J Thomas Construction Co",
    "wof:placetype":"venue"
},
  "geometry": {"coordinates":[-75.077836,40.015406],"type":"Point"}
}