{
  "type": "Feature",
  "properties": {
    "iso:country":"US",
    "sg:address":"14425 Bustleton Ave",
    "sg:city":"Philadelphia",
    "sg:classifiers":[
        {
            "category":"Personal",
            "subcategory":"Beauty Salon",
            "type":"Services"
        }
    ],
    "sg:phone":"+1 215 677 3337",
    "sg:postcode":"19116",
    "sg:province":"PA",
    "sg:tags":[
        "shop"
    ],
    "wof:name":"Barry's Castle Hair Designers",
    "wof:placetype":"venue"
},
  "geometry": {"coordinates":[-75.011804,40.132096],"type":"Point"}
}