{
  "type": "Feature",
  "properties": {
    "iso:country":"US",
    "sg:address":"76 Jefferson Ave",
    "sg:city":"Sharon",
    "sg:classifiers":[
        {
            "category":"Social Services",
            "subcategory":"Child Care",
            "type":"Services"
        },
        {
            "category":"Health Services",
            "subcategory":"Hospital",
            "type":"Services"
        }
    ],
    "sg:phone":"+1 724 346 3988",
    "sg:postcode":"16146",
    "sg:province":"PA",
    "sg:tags":[
        "mental",
        "day"
    ],
    "wof:name":"Associates In Counseling",
    "wof:placetype":"venue"
},
  "geometry": {"coordinates":[-80.49523499999999,41.233388],"type":"Point"}
}