{
  "type": "Feature",
  "properties": {
    "iso:country":"US",
    "sg:address":"212 Old Kennett Rd",
    "sg:city":"Kennett Square",
    "sg:classifiers":[
        {
            "category":"Organizations",
            "subcategory":"Religious Organization",
            "type":"Services"
        }
    ],
    "sg:phone":"+1 610 444 4364",
    "sg:postcode":"19348",
    "sg:province":"PA",
    "sg:tags":[
        "church"
    ],
    "wof:name":"St Patrick's Church",
    "wof:placetype":"venue"
},
  "geometry": {"coordinates":[-75.68802599999999,39.826269],"type":"Point"}
}