{
  "type": "Feature",
  "properties": {
    "addr:full":"200 Front St Millersburg PA 17061",
    "addr:housenumber":"200",
    "addr:postcode":"17061",
    "addr:street":"Front St",
    "iso:country":"US",
    "sg:address":"200 Front St",
    "sg:city":"Millersburg",
    "sg:classifiers":[
        {
            "category":"Wholesale",
            "subcategory":"Machinery & Supplies",
            "type":"Manufacturing & Wholesale Goods"
        }
    ],
    "sg:phone":"+1 717 692 2113",
    "sg:postcode":"17061",
    "sg:province":"PA",
    "sg:tags":[
        "tool"
    ],
    "sg:website":"www.talbotholdings.com",
    "wof:name":"Talbot Holdings",
    "wof:placetype":"venue"
},
  "geometry": {"coordinates":[-76.96374900000001,40.539669],"type":"Point"}
}