{
  "type": "Feature",
  "properties": {
    "iso:country":"US",
    "sg:address":"264 Lehigh Valley Mall",
    "sg:city":"Whitehall",
    "sg:classifiers":[
        {
            "category":"Deli",
            "type":"Food & Drink"
        }
    ],
    "sg:phone":"+1 610 264 5533",
    "sg:postcode":"18052",
    "sg:province":"PA",
    "wof:name":"Bain's Deli",
    "wof:placetype":"venue"
},
  "geometry": {"coordinates":[-75.482697,40.630001],"type":"Point"}
}