{
  "type": "Feature",
  "properties": {
    "iso:country":"US",
    "sg:address":"3001 Market St Fl 1",
    "sg:city":"Philadelphia",
    "sg:classifiers":[
        {
            "category":"Building & Trades",
            "subcategory":"Construction",
            "type":"Services"
        }
    ],
    "sg:phone":"+1 215 243 2000",
    "sg:postcode":"19104",
    "sg:province":"PA",
    "sg:tags":[
        "contractor"
    ],
    "wof:name":"Intech Construction Inc",
    "wof:placetype":"venue"
},
  "geometry": {"coordinates":[-75.202904,39.960098],"type":"Point"}
}