{
  "type": "Feature",
  "properties": {
    "addr:full":"96 Rochester Rd Pittsburgh PA 15229",
    "addr:housenumber":"96",
    "addr:postcode":"15229",
    "addr:street":"Rochester Rd",
    "iso:country":"US",
    "sg:address":"96 Rochester Rd",
    "sg:city":"Pittsburgh",
    "sg:classifiers":[
        {
            "category":"Restaurant",
            "type":"Food & Drink"
        }
    ],
    "sg:menulink":"http://www.allmenus.com/pa/west-view/280953-tymaz/menu/",
    "sg:phone":"+1 412 931 9005",
    "sg:postcode":"15229",
    "sg:province":"PA",
    "sg:tags":[
        "middle",
        "mediterranean",
        "eastern"
    ],
    "wof:name":"Tyma'z",
    "wof:placetype":"venue"
},
  "geometry": {"coordinates":[-80.026343,40.520882],"type":"Point"}
}