{
  "type": "Feature",
  "properties": {
    "iso:country":"US",
    "sg:address":"318 Wyoming Ave",
    "sg:city":"Wyoming",
    "sg:classifiers":[
        {
            "category":"Home & Garden",
            "subcategory":"Carpets & Floor Coverings",
            "type":"Retail Goods"
        }
    ],
    "sg:phone":"+1 570 693 3550",
    "sg:postcode":"18644",
    "sg:province":"PA",
    "sg:tags":[
        "dealer",
        "rug"
    ],
    "wof:name":"Charlie Cupani Your Carpetman",
    "wof:placetype":"venue"
},
  "geometry": {"coordinates":[-75.836519,41.312166],"type":"Point"}
}