{
  "type": "Feature",
  "properties": {
    "addr:full":"45 Lincoln Ave Reinholds PA 17569",
    "addr:housenumber":"45",
    "addr:postcode":"17569",
    "addr:street":"Lincoln Ave",
    "iso:country":"US",
    "sg:address":"45 Lincoln Ave",
    "sg:city":"Reinholds",
    "sg:classifiers":[
        {
            "category":"Home & Garden",
            "subcategory":"Furniture",
            "type":"Retail Goods"
        }
    ],
    "sg:phone":"+1 717 336 0111",
    "sg:postcode":"17569",
    "sg:province":"PA",
    "sg:tags":[
        "cabinet"
    ],
    "wof:name":"Lancaster Maid Cabinets Inc",
    "wof:placetype":"venue"
},
  "geometry": {"coordinates":[-76.11468499999999,40.266054],"type":"Point"}
}