{
  "type": "Feature",
  "properties": {
    "iso:country":"US",
    "sg:address":"201 N Franklin St",
    "sg:city":"Titusville",
    "sg:classifiers":[
        {
            "category":"Social Services",
            "type":"Services"
        }
    ],
    "sg:phone":"+1   ",
    "sg:postcode":"16354",
    "sg:province":"PA",
    "wof:name":"YWCA Hsing Hsing Spportive Svc",
    "wof:placetype":"venue"
},
  "geometry": {"coordinates":[-80.052065,41.524517],"type":"Point"}
}