{
  "type": "Feature",
  "properties": {
    "addr:full":"2018 Hamilton St Philadelphia PA 19130",
    "addr:housenumber":"2018",
    "addr:postcode":"19130",
    "addr:street":"Hamilton St",
    "iso:country":"US",
    "sg:address":"2018 Hamilton St",
    "sg:city":"Philadelphia",
    "sg:classifiers":[
        {
            "category":"Building & Trades",
            "subcategory":"Locksmith",
            "type":"Services"
        }
    ],
    "sg:phone":"+1 267 519 4164",
    "sg:postcode":"19130",
    "sg:province":"PA",
    "sg:tags":[
        "key"
    ],
    "wof:name":"Always Available Locksmith",
    "wof:placetype":"venue"
},
  "geometry": {"coordinates":[-75.171622,39.962176],"type":"Point"}
}