{
  "type": "Feature",
  "properties": {
    "iso:country":"US",
    "sg:address":"2594 Jean Dr",
    "sg:city":"Hatfield",
    "sg:classifiers":[
        {
            "category":"Banks & Credit Unions",
            "subcategory":"Bank",
            "type":"Services"
        }
    ],
    "sg:phone":"+1 215 362 0904",
    "sg:postcode":"19440",
    "sg:province":"PA",
    "sg:tags":[
        "financing"
    ],
    "wof:name":"William Gutshe Pvt Note Invstr",
    "wof:placetype":"venue"
},
  "geometry": {"coordinates":[-75.309398,40.276432],"type":"Point"}
}