{
  "type": "Feature",
  "properties": {
    "iso:country":"US",
    "sg:address":"2610 Hill Rd",
    "sg:city":"Reading",
    "sg:classifiers":[
        {
            "category":"Professional",
            "type":"Services"
        }
    ],
    "sg:phone":"+1   ",
    "sg:postcode":"19606",
    "sg:province":"PA",
    "wof:name":"Martin R Rhoad LLC",
    "wof:placetype":"venue"
},
  "geometry": {"coordinates":[-75.889606,40.344065],"type":"Point"}
}