{
  "type": "Feature",
  "properties": {
    "iso:country":"US",
    "sg:address":"807 Beecherstown Rd",
    "sg:city":"Biglerville",
    "sg:classifiers":[
        {
            "category":"Farming",
            "subcategory":"Dairy Farm",
            "type":"Manufacturing & Wholesale Goods"
        }
    ],
    "sg:phone":"+1   ",
    "sg:postcode":"17307",
    "sg:province":"PA",
    "wof:name":"New Hope Dairy",
    "wof:placetype":"venue"
},
  "geometry": {"coordinates":[-77.276422,39.916465],"type":"Point"}
}