{
  "type": "Feature",
  "properties": {
    "iso:country":"US",
    "sg:address":"1937 Fruitville Pike",
    "sg:city":"Lancaster",
    "sg:classifiers":[
        {
            "category":"Shopping",
            "type":"Retail Goods"
        }
    ],
    "sg:phone":"+1 717 509 3500",
    "sg:postcode":"17601",
    "sg:province":"PA",
    "sg:tags":[
        "wedding",
        "supply"
    ],
    "wof:name":"Ink Spots Inc",
    "wof:placetype":"venue"
},
  "geometry": {"coordinates":[-76.322046,40.075014],"type":"Point"}
}