{
  "type": "Feature",
  "properties": {
    "iso:country":"US",
    "sg:address":"42 Mill St",
    "sg:city":"Dallas",
    "sg:classifiers":[
        {
            "category":"Organizations",
            "subcategory":"Labor Organization",
            "type":"Services"
        }
    ],
    "sg:phone":"+1   ",
    "sg:postcode":"18612",
    "sg:province":"PA",
    "wof:name":"Cwa 13571",
    "wof:placetype":"venue"
},
  "geometry": {"coordinates":[-75.960875,41.336488],"type":"Point"}
}