{
  "type": "Feature",
  "properties": {
    "addr:full":"2218 N Broad St Philadelphia PA 19132",
    "addr:housenumber":"2218",
    "addr:postcode":"19132",
    "addr:street":"N Broad St",
    "iso:country":"US",
    "sg:address":"2218 N Broad St",
    "sg:city":"Philadelphia",
    "sg:classifiers":[
        {
            "category":"Personal",
            "subcategory":"Barber",
            "type":"Services"
        }
    ],
    "sg:phone":"+1 215 232 2591",
    "sg:postcode":"19132",
    "sg:province":"PA",
    "sg:tags":[
        "shop"
    ],
    "wof:name":"Millennium Hair Studio",
    "wof:placetype":"venue"
},
  "geometry": {"coordinates":[-75.15589900000001,39.987],"type":"Point"}
}