{
  "type": "Feature",
  "properties": {
    "iso:country":"US",
    "sg:address":"216 Pennsylvania Ave",
    "sg:city":"Watsontown",
    "sg:classifiers":[
        {
            "category":"Building & Trades",
            "subcategory":"Electrical",
            "type":"Services"
        }
    ],
    "sg:phone":"+1 570 538 2460",
    "sg:postcode":"17777",
    "sg:province":"PA",
    "sg:tags":[
        "industrial",
        "electric",
        "system",
        "contractor",
        "contractors-commercial",
        "security"
    ],
    "wof:name":"Smith Electric & Alarm Service",
    "wof:placetype":"venue"
},
  "geometry": {"coordinates":[-76.860516,41.083535],"type":"Point"}
}