{
  "type": "Feature",
  "properties": {
    "addr:full":"356 Wyndmoor Ln Huntingdon Vly PA 19006",
    "addr:housenumber":"356",
    "addr:postcode":"19006",
    "addr:street":"Wyndmoor Ln",
    "iso:country":"US",
    "sg:address":"356 Wyndmoor Ln",
    "sg:city":"Huntingdon Vly",
    "sg:classifiers":[
        {
            "category":"Real Estate",
            "subcategory":"Real Estate Agent",
            "type":"Services"
        }
    ],
    "sg:phone":"+1 215 938 0426",
    "sg:postcode":"19006",
    "sg:province":"PA",
    "wof:name":"Hassett Service Group",
    "wof:placetype":"venue"
},
  "geometry": {"coordinates":[-75.06950399999999,40.108383],"type":"Point"}
}