{
  "type": "Feature",
  "properties": {
    "addr:full":"449 Cameron St Marysville PA 17053",
    "addr:housenumber":"449",
    "addr:postcode":"17053",
    "addr:street":"Cameron St",
    "iso:country":"US",
    "sg:address":"449 Cameron St",
    "sg:city":"Marysville",
    "sg:classifiers":[
        {
            "category":"Professional",
            "subcategory":"Engineering",
            "type":"Services"
        }
    ],
    "sg:phone":"+1 717 957 3306",
    "sg:postcode":"17053",
    "sg:province":"PA",
    "sg:tags":[
        "engineer"
    ],
    "wof:name":"Kline Engineering PC",
    "wof:placetype":"venue"
},
  "geometry": {"coordinates":[-76.936063,40.340541],"type":"Point"}
}