{
  "type": "Feature",
  "properties": {
    "addr:full":"584 US Hwy 209 Milford PA 18337",
    "addr:housenumber":"584",
    "addr:postcode":"18337",
    "addr:street":"Us Hwy 209",
    "iso:country":"US",
    "sg:address":"584 US Hwy 209",
    "sg:city":"Milford",
    "sg:classifiers":[
        {
            "category":"Health Services",
            "subcategory":"Chiropractor",
            "type":"Services"
        }
    ],
    "sg:phone":"+1 570 296 3000",
    "sg:postcode":"18337",
    "sg:province":"PA",
    "wof:name":"Pike Cnty Chiropractic Clinic",
    "wof:placetype":"venue"
},
  "geometry": {"coordinates":[-74.799936,41.325079],"type":"Point"}
}