{
  "type": "Feature",
  "properties": {
    "addr:full":"315 Buchanan Ave Folsom PA 19033",
    "addr:housenumber":"315",
    "addr:postcode":"19033",
    "addr:street":"Buchanan Ave",
    "iso:country":"US",
    "sg:address":"315 Buchanan Ave",
    "sg:city":"Folsom",
    "sg:classifiers":[
        {
            "category":"Professional",
            "subcategory":"Business Services",
            "type":"Services"
        }
    ],
    "sg:phone":"+1 610 461 7277",
    "sg:postcode":"19033",
    "sg:province":"PA",
    "sg:tags":[
        "event"
    ],
    "wof:name":"Fatula Catered Events",
    "wof:placetype":"venue"
},
  "geometry": {"coordinates":[-75.339643,39.881714],"type":"Point"}
}