{
  "type": "Feature",
  "properties": {
    "iso:country":"US",
    "sg:address":"161 Harvey Rd",
    "sg:city":"Sarver",
    "sg:classifiers":[
        {
            "category":"Farming",
            "subcategory":"Dairy Farm",
            "type":"Manufacturing & Wholesale Goods"
        }
    ],
    "sg:phone":"+1   ",
    "sg:postcode":"16055",
    "sg:province":"PA",
    "wof:name":"Roger Harvey",
    "wof:placetype":"venue"
},
  "geometry": {"coordinates":[-79.763648,40.68302],"type":"Point"}
}