{
  "type": "Feature",
  "properties": {
    "iso:country":"US",
    "sg:address":"325 Manor Dr",
    "sg:city":"Mechanicsburg",
    "sg:classifiers":[
        {
            "category":"Banks & Credit Unions",
            "subcategory":"Bank",
            "type":"Services"
        }
    ],
    "sg:phone":"+1 717 761 6410",
    "sg:postcode":"17050",
    "sg:province":"PA",
    "wof:name":"Dombach Denise M",
    "wof:placetype":"venue"
},
  "geometry": {"coordinates":[-76.964142,40.228384],"type":"Point"}
}