{
  "type": "Feature",
  "properties": {
    "addr:full":"5458 Steubenville Pike Mc Kees Rocks PA 15136",
    "addr:housenumber":"5458",
    "addr:postcode":"15136",
    "addr:street":"Steubenville Pike Mc Kees Rocks",
    "iso:country":"US",
    "sg:address":"5458 Steubenville Pike",
    "sg:city":"Mc Kees Rocks",
    "sg:classifiers":[
        {
            "category":"Professional",
            "subcategory":"Management & Consulting",
            "type":"Services"
        }
    ],
    "sg:phone":"+1   ",
    "sg:postcode":"15136",
    "sg:province":"PA",
    "sg:tags":[
        "public",
        "relations"
    ],
    "wof:name":"Crdillo McMahon Communications",
    "wof:placetype":"venue"
},
  "geometry": {"coordinates":[-80.133563,40.452131],"type":"Point"}
}