{
  "type": "Feature",
  "properties": {
    "iso:country":"US",
    "sg:address":"6915 New Falls Rd",
    "sg:city":"Levittown",
    "sg:classifiers":[
        {
            "category":"Insurance",
            "subcategory":"Insurance Agent",
            "type":"Services"
        }
    ],
    "sg:phone":"+1 215 945 8050",
    "sg:postcode":"19056",
    "sg:province":"PA",
    "wof:name":"A's Insurance & Auto Tags",
    "wof:placetype":"venue"
},
  "geometry": {"coordinates":[-74.855542,40.154153],"type":"Point"}
}