{
  "type": "Feature",
  "properties": {
    "addr:full":"2138 Murray Ave Pittsburgh PA 15217",
    "addr:housenumber":"2138",
    "addr:postcode":"15217",
    "addr:street":"Murray Ave",
    "iso:country":"US",
    "sg:address":"2138 Murray Ave",
    "sg:city":"Pittsburgh",
    "sg:classifiers":[
        {
            "category":"Restaurant",
            "type":"Food & Drink"
        }
    ],
    "sg:menulink":"http://www.allmenus.com/pa/pittsburgh/60101-new-dumpling--sushi-house/menu/",
    "sg:phone":"+1 412 422 4178",
    "sg:postcode":"15217",
    "sg:province":"PA",
    "sg:tags":[
        "asian",
        "chinese"
    ],
    "wof:name":"New Dumpling & Sushi House",
    "wof:placetype":"venue"
},
  "geometry": {"coordinates":[-79.922923,40.433095],"type":"Point"}
}