{
  "type": "Feature",
  "properties": {
    "addr:full":"25 E College St Canonsburg PA 15317",
    "addr:housenumber":"25",
    "addr:postcode":"15317",
    "addr:street":"E College St",
    "iso:country":"US",
    "sg:address":"25 E College St",
    "sg:city":"Canonsburg",
    "sg:classifiers":[
        {
            "category":"Education",
            "subcategory":"School",
            "type":"Public Place"
        }
    ],
    "sg:phone":"+1 724 745 9030",
    "sg:postcode":"15317",
    "sg:province":"PA",
    "sg:website":"www.cmsd.k12.pa.us",
    "wof:name":"Canonsburg Middle School",
    "wof:placetype":"venue"
},
  "geometry": {"coordinates":[-80.18543699999999,40.260607],"type":"Point"}
}