{
  "type": "Feature",
  "properties": {
    "iso:country":"US",
    "sg:address":"215 S 45th St",
    "sg:city":"Philadelphia",
    "sg:classifiers":[
        {
            "category":"Professional",
            "subcategory":"Accounting & Tax Preparation",
            "type":"Services"
        }
    ],
    "sg:phone":"+1   ",
    "sg:postcode":"19104",
    "sg:province":"PA",
    "wof:name":"Statwizard",
    "wof:placetype":"venue"
},
  "geometry": {"coordinates":[-75.21174999999999,39.954656],"type":"Point"}
}