{
  "type": "Feature",
  "properties": {
    "iso:country":"US",
    "sg:address":"340 Stratford Ave",
    "sg:city":"Collegeville",
    "sg:classifiers":[
        {
            "category":"Wholesale",
            "subcategory":"Chemicals & Plastics",
            "type":"Manufacturing & Wholesale Goods"
        }
    ],
    "sg:phone":"+1 610 489 8871",
    "sg:postcode":"19426",
    "sg:province":"PA",
    "sg:tags":[
        "wax"
    ],
    "wof:name":"H P Wax",
    "wof:placetype":"venue"
},
  "geometry": {"coordinates":[-75.465633,40.183469],"type":"Point"}
}