{
  "type": "Feature",
  "properties": {
    "addr:full":"1044 University Dr Connellsville PA 15431",
    "addr:housenumber":"1044",
    "addr:postcode":"15431",
    "addr:street":"University Dr",
    "iso:country":"US",
    "sg:address":"1044 University Dr",
    "sg:city":"Connellsville",
    "sg:classifiers":[
        {
            "category":"Autos & Motor Vehicles",
            "subcategory":"Automobile Sales",
            "type":"Retail Goods"
        }
    ],
    "sg:phone":"+1 724 628 4531",
    "sg:postcode":"15431",
    "sg:province":"PA",
    "sg:tags":[
        "car",
        "dealer"
    ],
    "sg:website":"www.brooksautogroup.com",
    "wof:name":"Brooks Automotive Group",
    "wof:placetype":"venue"
},
  "geometry": {"coordinates":[-79.609599,39.995963],"type":"Point"}
}