{
  "type": "Feature",
  "properties": {
    "iso:country":"US",
    "sg:address":"491 Baltimore Pike",
    "sg:city":"Springfield",
    "sg:classifiers":[
        {
            "category":"Building & Trades",
            "subcategory":"Construction",
            "type":"Services"
        }
    ],
    "sg:phone":"+1 610 626 4570",
    "sg:postcode":"19064",
    "sg:province":"PA",
    "sg:tags":[
        "painter"
    ],
    "wof:name":"J Pollacco Construction",
    "wof:placetype":"venue"
},
  "geometry": {"coordinates":[-75.322664,39.92086],"type":"Point"}
}