{
  "type": "Feature",
  "properties": {
    "iso:country":"US",
    "sg:address":"1032 S 5th Ave",
    "sg:city":"Lebanon",
    "sg:classifiers":[
        {
            "category":"Restaurant",
            "type":"Food & Drink"
        }
    ],
    "sg:phone":"+1 717 273 8579",
    "sg:postcode":"17042",
    "sg:province":"PA",
    "sg:tags":[
        "pizza"
    ],
    "wof:name":"Pucillo's Pizza & Restaurant",
    "wof:placetype":"venue"
},
  "geometry": {"coordinates":[-76.391704,40.328837],"type":"Point"}
}