{
  "type": "Feature",
  "properties": {
    "addr:full":"2121 72nd Ave Philadelphia PA 19138",
    "addr:housenumber":"2121",
    "addr:postcode":"19138",
    "addr:street":"72Nd Ave",
    "iso:country":"US",
    "sg:address":"2121 72nd Ave",
    "sg:city":"Philadelphia",
    "sg:classifiers":[
        {
            "category":"Deli",
            "type":"Food & Drink"
        },
        {
            "category":"Restaurant",
            "type":"Food & Drink"
        },
        {
            "category":"Food & Beverages",
            "subcategory":"Groceries & Convenience Stores",
            "type":"Retail Goods"
        }
    ],
    "sg:phone":"+1 215 424 0350",
    "sg:postcode":"19138",
    "sg:province":"PA",
    "sg:tags":[
        "shop",
        "delicatessen",
        "sandwich"
    ],
    "wof:name":"Hoagie Factory",
    "wof:placetype":"venue"
},
  "geometry": {"coordinates":[-75.152856,40.064308],"type":"Point"}
}