{
  "type": "Feature",
  "properties": {
    "addr:full":"1731 Lafayette Dr Jamison PA 18929",
    "addr:housenumber":"1731",
    "addr:postcode":"18929",
    "addr:street":"Lafayette Dr",
    "iso:country":"US",
    "sg:address":"1731 Lafayette Dr",
    "sg:city":"Jamison",
    "sg:classifiers":[
        {
            "category":"Banks & Credit Unions",
            "subcategory":"Bank",
            "type":"Services"
        }
    ],
    "sg:phone":"+1   ",
    "sg:postcode":"18929",
    "sg:province":"PA",
    "sg:tags":[
        "mortgage"
    ],
    "wof:name":"Citywide Mortgage",
    "wof:placetype":"venue"
},
  "geometry": {"coordinates":[-75.096462,40.252592],"type":"Point"}
}