{
  "type": "Feature",
  "properties": {
    "iso:country":"US",
    "sg:address":"215 Presidential Blvd",
    "sg:city":"Bala Cynwyd",
    "sg:classifiers":[
        {
            "category":"Organizations",
            "subcategory":"Non-profit Organization",
            "type":"Services"
        },
        {
            "category":"Travel",
            "subcategory":"Campground",
            "type":"Entertainment"
        }
    ],
    "sg:phone":"+1 610 660 0520",
    "sg:postcode":"19004",
    "sg:province":"PA",
    "sg:tags":[
        "summer",
        "camp"
    ],
    "sg:website":"www.goldenslippercamp.org",
    "wof:name":"Golden Slipper Camp",
    "wof:placetype":"venue"
},
  "geometry": {"coordinates":[-75.210921,40.008814],"type":"Point"}
}