{
  "type": "Feature",
  "properties": {
    "iso:country":"US",
    "sg:address":"700 Pellis Rd",
    "sg:city":"Greensburg",
    "sg:classifiers":[
        {
            "category":"Banks & Credit Unions",
            "subcategory":"Investment Brokerage",
            "type":"Services"
        }
    ],
    "sg:phone":"+1 724 834 6850",
    "sg:postcode":"15601",
    "sg:province":"PA",
    "sg:tags":[
        "advisory",
        "financial"
    ],
    "wof:name":"Berkshire Financial Group",
    "wof:placetype":"venue"
},
  "geometry": {"coordinates":[-79.524158,40.291738],"type":"Point"}
}