{
  "type": "Feature",
  "properties": {
    "addr:full":"4505 Rhawn St Philadelphia PA 19136",
    "addr:housenumber":"4505",
    "addr:postcode":"19136",
    "addr:street":"Rhawn St",
    "iso:country":"US",
    "sg:address":"4505 Rhawn St",
    "sg:city":"Philadelphia",
    "sg:classifiers":[
        {
            "category":"Food & Beverages",
            "subcategory":"Groceries & Convenience Stores",
            "type":"Retail Goods"
        }
    ],
    "sg:phone":"+1 215 332 9419",
    "sg:postcode":"19136",
    "sg:province":"PA",
    "sg:tags":[
        "grocer"
    ],
    "wof:name":"Pat's Corner Store",
    "wof:placetype":"venue"
},
  "geometry": {"coordinates":[-75.025801,40.036306],"type":"Point"}
}