{
  "type": "Feature",
  "properties": {
    "addr:full":"105 W Brown St Norristown PA 19401",
    "addr:housenumber":"105",
    "addr:postcode":"19401",
    "addr:street":"W Brown St",
    "iso:country":"US",
    "sg:address":"105 W Brown St",
    "sg:city":"Norristown",
    "sg:classifiers":[
        {
            "category":"Bars & Pubs",
            "type":"Food & Drink"
        }
    ],
    "sg:phone":"+1   ",
    "sg:postcode":"19401",
    "sg:province":"PA",
    "sg:tags":[
        "drinking"
    ],
    "wof:name":"Jug Little Brown",
    "wof:placetype":"venue"
},
  "geometry": {"coordinates":[-75.333758,40.128319],"type":"Point"}
}