{
  "type": "Feature",
  "properties": {
    "iso:country":"US",
    "sg:address":"705 Somerset St",
    "sg:city":"Johnstown",
    "sg:classifiers":[
        {
            "category":"Organizations",
            "subcategory":"Religious Organization",
            "type":"Services"
        }
    ],
    "sg:phone":"+1 814 535 1688",
    "sg:postcode":"15901",
    "sg:province":"PA",
    "sg:tags":[
        "church"
    ],
    "wof:name":"First Mennonite Church",
    "wof:placetype":"venue"
},
  "geometry": {"coordinates":[-78.91492,40.31848],"type":"Point"}
}