{
  "type": "Feature",
  "properties": {
    "iso:country":"US",
    "sg:address":"60 S 2nd St",
    "sg:city":"Philadelphia",
    "sg:classifiers":[
        {
            "category":"Restaurant",
            "type":"Food & Drink"
        }
    ],
    "sg:phone":"+1   ",
    "sg:postcode":"19106",
    "sg:province":"PA",
    "sg:tags":[
        "shop",
        "sandwich"
    ],
    "wof:name":"Larrys Steaks and Hoagies",
    "wof:placetype":"venue"
},
  "geometry": {"coordinates":[-75.144114,39.948637],"type":"Point"}
}