{
  "type": "Feature",
  "properties": {
    "addr:full":"3 Buckfield Ln Stroudsburg PA 18360",
    "addr:housenumber":"3",
    "addr:postcode":"18360",
    "addr:street":"Buckfield Ln",
    "iso:country":"US",
    "sg:address":"3 Buckfield Ln",
    "sg:city":"Stroudsburg",
    "sg:classifiers":[
        {
            "category":"Manufacturing",
            "subcategory":"Furniture",
            "type":"Manufacturing & Wholesale Goods"
        }
    ],
    "sg:phone":"+1   ",
    "sg:postcode":"18360",
    "sg:province":"PA",
    "sg:tags":[
        "household",
        "mfg"
    ],
    "wof:name":"Cottonwood Homegear",
    "wof:placetype":"venue"
},
  "geometry": {"coordinates":[-75.25575499999999,40.919574],"type":"Point"}
}