{
  "type": "Feature",
  "properties": {
    "addr:full":"61 Mifflin St West Mifflin PA 15110",
    "addr:housenumber":"61",
    "addr:postcode":"15110",
    "addr:street":"Mifflin St",
    "iso:country":"US",
    "sg:address":"61 Mifflin St",
    "sg:city":"West Mifflin",
    "sg:classifiers":[
        {
            "category":"Airline",
            "type":"Transportation"
        }
    ],
    "sg:phone":"+1   ",
    "sg:postcode":"15110",
    "sg:province":"PA",
    "sg:tags":[
        "nonscheduled",
        "air"
    ],
    "wof:name":"Consolidation Coal Company",
    "wof:placetype":"venue"
},
  "geometry": {"coordinates":[-79.859081,40.366909],"type":"Point"}
}