{
  "type": "Feature",
  "properties": {
    "addr:full":"2102 Main St Northampton PA 18067",
    "addr:housenumber":"2102",
    "addr:postcode":"18067",
    "addr:street":"Main St",
    "iso:country":"US",
    "sg:address":"2102 Main St",
    "sg:city":"Northampton",
    "sg:classifiers":[
        {
            "category":"Banks & Credit Unions",
            "subcategory":"Bank",
            "type":"Services"
        }
    ],
    "sg:phone":"+1 610 261 3100",
    "sg:postcode":"18067",
    "sg:province":"PA",
    "sg:website":"www.pncbank.com",
    "wof:name":"Pnc Bank",
    "wof:placetype":"venue"
},
  "geometry": {"coordinates":[-75.499199,40.6908],"type":"Point"}
}