{
  "type": "Feature",
  "properties": {
    "iso:country":"US",
    "sg:address":"1911 E 3rd St",
    "sg:city":"Williamsport",
    "sg:classifiers":[
        {
            "category":"Shopping",
            "subcategory":"Bicycles & Sporting Goods",
            "type":"Retail Goods"
        }
    ],
    "sg:phone":"+1 570 323 1436",
    "sg:postcode":"17701",
    "sg:province":"PA",
    "wof:name":"Olympia Sports",
    "wof:placetype":"venue"
},
  "geometry": {"coordinates":[-76.961325,41.248398],"type":"Point"}
}