{
  "type": "Feature",
  "properties": {
    "iso:country":"US",
    "sg:address":"2628 Craley Rd",
    "sg:city":"Wrightsville",
    "sg:classifiers":[
        {
            "category":"Restaurant",
            "type":"Food & Drink"
        }
    ],
    "sg:phone":"+1 717 244 5330",
    "sg:postcode":"17368",
    "sg:province":"PA",
    "sg:tags":[
        "beverage"
    ],
    "wof:name":"Craley's Beverage Distributors",
    "wof:placetype":"venue"
},
  "geometry": {"coordinates":[-76.508909,39.948205],"type":"Point"}
}