{
  "type": "Feature",
  "properties": {
    "addr:full":"200 Logan Ave Glenside PA 19038",
    "addr:housenumber":"200",
    "addr:postcode":"19038",
    "addr:street":"Logan Ave",
    "iso:country":"US",
    "sg:address":"200 Logan Ave",
    "sg:city":"Glenside",
    "sg:classifiers":[
        {
            "category":"Organizations",
            "subcategory":"Religious Organization",
            "type":"Services"
        }
    ],
    "sg:phone":"+1 215 884 8560",
    "sg:postcode":"19038",
    "sg:province":"PA",
    "wof:name":"Antioch Baptist Church",
    "wof:placetype":"venue"
},
  "geometry": {"coordinates":[-75.17025700000001,40.117416],"type":"Point"}
}