{
  "type": "Feature",
  "properties": {
    "addr:full":"28 E 5th St Mount Carmel PA 17851",
    "addr:housenumber":"28",
    "addr:postcode":"17851",
    "addr:street":"E 5Th St",
    "iso:country":"US",
    "sg:address":"28 E 5th St",
    "sg:city":"Mount Carmel",
    "sg:classifiers":[
        {
            "category":"Health Services",
            "subcategory":"Doctor",
            "type":"Services"
        }
    ],
    "sg:phone":"+1   ",
    "sg:postcode":"17851",
    "sg:province":"PA",
    "sg:tags":[
        "medical"
    ],
    "wof:name":"Kraynak Raymond J DO",
    "wof:placetype":"venue"
},
  "geometry": {"coordinates":[-76.411177,40.794975],"type":"Point"}
}