{
  "type": "Feature",
  "properties": {
    "addr:full":"68 Dean St Beaver Meadows PA 18216",
    "addr:housenumber":"68",
    "addr:postcode":"18216",
    "addr:street":"Dean St",
    "iso:country":"US",
    "sg:address":"68 Dean St",
    "sg:city":"Beaver Meadows",
    "sg:classifiers":[
        {
            "category":"Building & Trades",
            "subcategory":"Landscaping Services",
            "type":"Services"
        }
    ],
    "sg:phone":"+1 570 455 4074",
    "sg:postcode":"18216",
    "sg:province":"PA",
    "wof:name":"Master Gardening",
    "wof:placetype":"venue"
},
  "geometry": {"coordinates":[-75.910048,40.929322],"type":"Point"}
}