{
  "type": "Feature",
  "properties": {
    "addr:full":"3129 Menoher Blvd Johnstown PA 15905",
    "addr:housenumber":"3129",
    "addr:postcode":"15905",
    "addr:street":"Menoher Blvd",
    "iso:country":"US",
    "sg:address":"3129 Menoher Blvd",
    "sg:city":"Johnstown",
    "sg:classifiers":[
        {
            "category":"Building & Trades",
            "subcategory":"Construction",
            "type":"Services"
        }
    ],
    "sg:phone":"+1 814 255 7240",
    "sg:postcode":"15905",
    "sg:province":"PA",
    "sg:tags":[
        "house",
        "contractor"
    ],
    "wof:name":"Kapcsos & Bowser Construction",
    "wof:placetype":"venue"
},
  "geometry": {"coordinates":[-78.99632200000001,40.302793],"type":"Point"}
}