{
  "type": "Feature",
  "properties": {
    "iso:country":"US",
    "sg:address":"339 W Main Ave",
    "sg:city":"Myerstown",
    "sg:classifiers":[
        {
            "category":"Personal",
            "subcategory":"Beauty Salon",
            "type":"Services"
        }
    ],
    "sg:phone":"+1 717 866 2690",
    "sg:postcode":"17067",
    "sg:province":"PA",
    "wof:name":"Rosalie Beauty Salon",
    "wof:placetype":"venue"
},
  "geometry": {"coordinates":[-76.313766,40.374418],"type":"Point"}
}