{
  "type": "Feature",
  "properties": {
    "iso:country":"US",
    "sg:address":"1304 S Forge Rd",
    "sg:city":"Palmyra",
    "sg:classifiers":[
        {
            "category":"Local Transit",
            "type":"Transportation"
        }
    ],
    "sg:phone":"+1   ",
    "sg:postcode":"17078",
    "sg:province":"PA",
    "sg:tags":[
        "passenger"
    ],
    "wof:name":"Boyo Transportation Service",
    "wof:placetype":"venue"
},
  "geometry": {"coordinates":[-76.57716499999999,40.298549],"type":"Point"}
}