{
  "type": "Feature",
  "properties": {
    "addr:full":"2501 W 12th St Erie PA 16505",
    "addr:housenumber":"2501",
    "addr:postcode":"16505",
    "addr:street":"W 12Th St",
    "iso:country":"US",
    "sg:address":"2501 W 12th St",
    "sg:city":"Erie",
    "sg:classifiers":[
        {
            "category":"Food & Beverages",
            "subcategory":"Groceries & Convenience Stores",
            "type":"Retail Goods"
        }
    ],
    "sg:phone":"+1 814 838 6990",
    "sg:postcode":"16505",
    "sg:province":"PA",
    "sg:tags":[
        "grocer"
    ],
    "wof:name":"Giant Eagle",
    "wof:placetype":"venue"
},
  "geometry": {"coordinates":[-80.13835899999999,42.102362],"type":"Point"}
}