{
  "type": "Feature",
  "properties": {
    "iso:country":"US",
    "sg:address":"5139 Chestnut St",
    "sg:city":"Philadelphia",
    "sg:classifiers":[
        {
            "category":"Health Services",
            "subcategory":"Doctor",
            "type":"Services"
        }
    ],
    "sg:phone":"+1 215 748 4241",
    "sg:postcode":"19139",
    "sg:province":"PA",
    "sg:tags":[
        "medicine",
        "internal"
    ],
    "wof:name":"Wrenn Walter F MD",
    "wof:placetype":"venue"
},
  "geometry": {"coordinates":[-75.22489899999999,39.958302],"type":"Point"}
}