{
  "type": "Feature",
  "properties": {
    "addr:full":"311 Broad St Montoursville PA 17754",
    "addr:housenumber":"311",
    "addr:postcode":"17754",
    "addr:street":"Broad St",
    "iso:country":"US",
    "sg:address":"311 Broad St",
    "sg:city":"Montoursville",
    "sg:classifiers":[
        {
            "category":"Personal",
            "subcategory":"Beauty Salon",
            "type":"Services"
        }
    ],
    "sg:phone":"+1 570 329 5055",
    "sg:postcode":"17754",
    "sg:province":"PA",
    "sg:tags":[
        "shop"
    ],
    "wof:name":"Hairscape 2000 By Bethany",
    "wof:placetype":"venue"
},
  "geometry": {"coordinates":[-76.92720199999999,41.249755],"type":"Point"}
}