{
  "type": "Feature",
  "properties": {
    "iso:country":"US",
    "sg:address":"125 6th St",
    "sg:city":"Monessen",
    "sg:classifiers":[
        {
            "category":"Personal",
            "subcategory":"Beauty Salon",
            "type":"Services"
        }
    ],
    "sg:phone":"+1   ",
    "sg:postcode":"15062",
    "sg:province":"PA",
    "sg:tags":[
        "shop"
    ],
    "wof:name":"Delvermes",
    "wof:placetype":"venue"
},
  "geometry": {"coordinates":[-79.88767900000001,40.161503],"type":"Point"}
}