{
  "type": "Feature",
  "properties": {
    "iso:country":"US",
    "sg:address":"1708 Madeira Ave",
    "sg:city":"Jenkintown",
    "sg:classifiers":[
        {
            "category":"Shopping",
            "subcategory":"Clothing, Apparel, & Fashions",
            "type":"Retail Goods"
        }
    ],
    "sg:phone":"+1 215 885 2594",
    "sg:postcode":"19046",
    "sg:province":"PA",
    "sg:tags":[
        "t"
    ],
    "wof:name":"AIR Conway",
    "wof:placetype":"venue"
},
  "geometry": {"coordinates":[-75.12808099999999,40.102896],"type":"Point"}
}