{
  "type": "Feature",
  "properties": {
    "iso:country":"US",
    "sg:address":"2893 Grays Ferry Ave",
    "sg:city":"Philadelphia",
    "sg:classifiers":[
        {
            "category":"Shopping",
            "subcategory":"Clothing, Apparel, & Fashions",
            "type":"Retail Goods"
        }
    ],
    "sg:phone":"+1 215 389 3722",
    "sg:postcode":"19146",
    "sg:province":"PA",
    "sg:tags":[
        "apparel",
        "women's"
    ],
    "wof:name":"Rainbow 1674",
    "wof:placetype":"venue"
},
  "geometry": {"coordinates":[-75.191582,39.93918],"type":"Point"}
}