{
  "type": "Feature",
  "properties": {
    "iso:country":"US",
    "sg:address":"615 Washington Rd",
    "sg:city":"Pittsburgh",
    "sg:classifiers":[
        {
            "category":"Professional",
            "subcategory":"Accounting & Tax Preparation",
            "type":"Services"
        }
    ],
    "sg:phone":"+1 412 531 7470",
    "sg:postcode":"15228",
    "sg:province":"PA",
    "sg:tags":[
        "return",
        "filing"
    ],
    "wof:name":"Barbara Szefi",
    "wof:placetype":"venue"
},
  "geometry": {"coordinates":[-80.043828,40.383128],"type":"Point"}
}