{
  "type": "Feature",
  "properties": {
    "iso:country":"US",
    "sg:address":"514 North Madison St.",
    "sg:city":"Allentown",
    "sg:classifiers":[
        {
            "category":"Building & Trades",
            "subcategory":"Plumbing",
            "type":"Services"
        },
        {
            "category":"Building & Trades",
            "subcategory":"Construction",
            "type":"Services"
        },
        {
            "category":"Building & Trades",
            "subcategory":"Electrical",
            "type":"Services"
        }
    ],
    "sg:phone":"+1 610 879 7637",
    "sg:postcode":"18102",
    "sg:province":"PA",
    "sg:tags":[
        "conditioning/hvac",
        "electrician",
        "heating",
        "air"
    ],
    "sg:website":"www.bollingerhomeservices.com/",
    "wof:name":"Bollinger Home Services",
    "wof:placetype":"venue"
},
  "geometry": {"coordinates":[-75.488799,40.606158],"type":"Point"}
}