{
  "type": "Feature",
  "properties": {
    "iso:country":"US",
    "sg:address":"42 Mountain Ave",
    "sg:city":"Nesquehoning",
    "sg:classifiers":[
        {
            "category":"Manufacturing",
            "subcategory":"Tools & Machinery",
            "type":"Manufacturing & Wholesale Goods"
        }
    ],
    "sg:phone":"+1 570 645 2191",
    "sg:postcode":"18240",
    "sg:province":"PA",
    "sg:tags":[
        "mfg"
    ],
    "sg:website":"www.ametek.com",
    "wof:name":"Ametek Westchester Plastics",
    "wof:placetype":"venue"
},
  "geometry": {"coordinates":[-75.838112,40.860672],"type":"Point"}
}