{
  "type": "Feature",
  "properties": {
    "addr:full":"3948 Constance Rd Philadelphia PA 19114",
    "addr:housenumber":"3948",
    "addr:postcode":"19114",
    "addr:street":"Constance Rd",
    "iso:country":"US",
    "sg:address":"3948 Constance Rd",
    "sg:city":"Philadelphia",
    "sg:classifiers":[
        {
            "category":"Building & Trades",
            "subcategory":"Construction",
            "type":"Services"
        }
    ],
    "sg:phone":"+1 215 632 6854",
    "sg:postcode":"19114",
    "sg:province":"PA",
    "sg:tags":[
        "carpenter"
    ],
    "wof:name":"Miter-Tight",
    "wof:placetype":"venue"
},
  "geometry": {"coordinates":[-74.989007,40.06303],"type":"Point"}
}