{
  "type": "Feature",
  "properties": {
    "addr:full":"143 Kara Pl Aliquippa PA 15001",
    "addr:housenumber":"143",
    "addr:postcode":"15001",
    "addr:street":"Kara Pl",
    "iso:country":"US",
    "sg:address":"143 Kara Pl",
    "sg:city":"Aliquippa",
    "sg:classifiers":[
        {
            "category":"Building & Trades",
            "subcategory":"Landscaping Services",
            "type":"Services"
        }
    ],
    "sg:phone":"+1 724 857 0233",
    "sg:postcode":"15001",
    "sg:province":"PA",
    "wof:name":"Lawn Tailor",
    "wof:placetype":"venue"
},
  "geometry": {"coordinates":[-80.310619,40.575239],"type":"Point"}
}