{
  "type": "Feature",
  "properties": {
    "iso:country":"US",
    "sg:address":"261 King St",
    "sg:city":"Pottstown",
    "sg:classifiers":[
        {
            "category":"Government",
            "subcategory":"Office",
            "type":"Public Place"
        }
    ],
    "sg:phone":"+1 610 323 1070",
    "sg:postcode":"19464",
    "sg:province":"PA",
    "sg:tags":[
        "state",
        "security"
    ],
    "wof:name":"Army National Guard Recruiter",
    "wof:placetype":"venue"
},
  "geometry": {"coordinates":[-75.647755,40.24651],"type":"Point"}
}