{
  "type": "Feature",
  "properties": {
    "iso:country":"US",
    "sg:address":"78 Tomlinson Rd",
    "sg:city":"Huntingdon Valley",
    "sg:classifiers":[
        {
            "category":"Manufacturing",
            "subcategory":"Printing",
            "type":"Manufacturing & Wholesale Goods"
        }
    ],
    "sg:phone":"+1   ",
    "sg:postcode":"19006",
    "sg:province":"PA",
    "sg:tags":[
        "print",
        "news",
        "magazine",
        "publish"
    ],
    "wof:name":"Eye Communication",
    "wof:placetype":"venue"
},
  "geometry": {"coordinates":[-75.041184,40.122111],"type":"Point"}
}