{
  "type": "Feature",
  "properties": {
    "iso:country":"US",
    "sg:address":"631 Lombard Rd",
    "sg:city":"Red Lion",
    "sg:classifiers":[
        {
            "category":"Shopping",
            "subcategory":"Gifts & Souvenirs",
            "type":"Retail Goods"
        }
    ],
    "sg:phone":"+1 717 244 8559",
    "sg:postcode":"17356",
    "sg:province":"PA",
    "sg:tags":[
        "cards",
        "greeting"
    ],
    "wof:name":"Cards n More",
    "wof:placetype":"venue"
},
  "geometry": {"coordinates":[-76.61763999999999,39.920785],"type":"Point"}
}