{
  "type": "Feature",
  "properties": {
    "iso:country":"US",
    "sg:address":"17 Aspen Dr",
    "sg:city":"Manheim",
    "sg:classifiers":[
        {
            "category":"Professional",
            "subcategory":"Detective & Security Services",
            "type":"Services"
        }
    ],
    "sg:phone":"+1 717 270 9723",
    "sg:postcode":"17545",
    "sg:province":"PA",
    "sg:tags":[
        "information",
        "bureau"
    ],
    "wof:name":"Jennifer S Limousine Service",
    "wof:placetype":"venue"
},
  "geometry": {"coordinates":[-76.44040699999999,40.242119],"type":"Point"}
}