{
  "type": "Feature",
  "properties": {
    "addr:full":"2906 William Penn Hwy Easton PA 18045",
    "addr:housenumber":"2906",
    "addr:postcode":"18045",
    "addr:street":"William Penn Hwy",
    "iso:country":"US",
    "sg:address":"2906 William Penn Hwy",
    "sg:city":"Easton",
    "sg:classifiers":[
        {
            "category":"Building & Trades",
            "subcategory":"Plumbing",
            "type":"Services"
        }
    ],
    "sg:phone":"+1 610 559 8601",
    "sg:postcode":"18045",
    "sg:province":"PA",
    "sg:tags":[
        "plumbing",
        "contractor"
    ],
    "wof:name":"4 R Plumbing Inc",
    "wof:placetype":"venue"
},
  "geometry": {"coordinates":[-75.258261,40.678892],"type":"Point"}
}