{
  "type": "Feature",
  "properties": {
    "addr:full":"7710 Rockwell Ave Philadelphia PA 19111",
    "addr:housenumber":"7710",
    "addr:postcode":"19111",
    "addr:street":"Rockwell Ave",
    "iso:country":"US",
    "sg:address":"7710 Rockwell Ave",
    "sg:city":"Philadelphia",
    "sg:classifiers":[
        {
            "category":"Building & Trades",
            "subcategory":"Construction",
            "type":"Services"
        },
        {
            "category":"Manufacturing",
            "subcategory":"Building Materials",
            "type":"Manufacturing & Wholesale Goods"
        }
    ],
    "sg:phone":"+1 215 289 7321",
    "sg:postcode":"19111",
    "sg:province":"PA",
    "sg:tags":[
        "roofing",
        "sheet",
        "work",
        "metal",
        "contractor",
        "siding"
    ],
    "wof:name":"Reeves Roofing",
    "wof:placetype":"venue"
},
  "geometry": {"coordinates":[-75.083671,40.068463],"type":"Point"}
}