{
  "type": "Feature",
  "properties": {
    "addr:full":"236 Donner Ave Monessen PA 15062",
    "addr:housenumber":"236",
    "addr:postcode":"15062",
    "addr:street":"Donner Ave",
    "iso:country":"US",
    "sg:address":"236 Donner Ave",
    "sg:city":"Monessen",
    "sg:classifiers":[
        {
            "category":"Manufacturing",
            "subcategory":"Signs",
            "type":"Manufacturing & Wholesale Goods"
        }
    ],
    "sg:phone":"+1 724 684 8022",
    "sg:postcode":"15062",
    "sg:province":"PA",
    "wof:name":"Evans Graphics",
    "wof:placetype":"venue"
},
  "geometry": {"coordinates":[-79.879069,40.16063],"type":"Point"}
}