{
  "type": "Feature",
  "properties": {
    "iso:country":"US",
    "sg:address":"601 W Susquehanna Ave",
    "sg:city":"Philadelphia",
    "sg:classifiers":[
        {
            "category":"Health Services",
            "subcategory":"Clinic",
            "type":"Services"
        }
    ],
    "sg:phone":"+1   ",
    "sg:postcode":"19122",
    "sg:province":"PA",
    "sg:tags":[
        "specialty",
        "outpatient"
    ],
    "wof:name":"APM Project Exodus",
    "wof:placetype":"venue"
},
  "geometry": {"coordinates":[-75.144154,39.984724],"type":"Point"}
}