{
  "type": "Feature",
  "properties": {
    "iso:country":"US",
    "sg:address":"29 E Main St",
    "sg:city":"Dallastown",
    "sg:classifiers":[
        {
            "category":"Restaurant",
            "type":"Food & Drink"
        },
        {
            "category":"Food & Beverages",
            "subcategory":"Meat & Fish",
            "type":"Retail Goods"
        }
    ],
    "sg:phone":"+1 717 246 5753",
    "sg:postcode":"17313",
    "sg:province":"PA",
    "sg:tags":[
        "seafood",
        "eating"
    ],
    "wof:name":"Paddy's Seafood",
    "wof:placetype":"venue"
},
  "geometry": {"coordinates":[-76.64352,39.900846],"type":"Point"}
}