{
  "type": "Feature",
  "properties": {
    "iso:country":"US",
    "sg:address":"1697 S Forge Rd",
    "sg:city":"Palmyra",
    "sg:classifiers":[
        {
            "category":"Building & Trades",
            "subcategory":"Electrical",
            "type":"Services"
        }
    ],
    "sg:phone":"+1   ",
    "sg:postcode":"17078",
    "sg:province":"PA",
    "sg:tags":[
        "electrical",
        "contractor"
    ],
    "wof:name":"JL Wagner Electric",
    "wof:placetype":"venue"
},
  "geometry": {"coordinates":[-76.575402,40.291951],"type":"Point"}
}