{
  "type": "Feature",
  "properties": {
    "iso:country":"US",
    "sg:address":"3609 Germantown Ave",
    "sg:city":"Philadelphia",
    "sg:classifiers":[
        {
            "category":"Shopping",
            "subcategory":"Clothing, Apparel, & Fashions",
            "type":"Retail Goods"
        }
    ],
    "sg:phone":"+1   ",
    "sg:postcode":"19140",
    "sg:province":"PA",
    "wof:name":"Mega Sportswear",
    "wof:placetype":"venue"
},
  "geometry": {"coordinates":[-75.150327,40.007829],"type":"Point"}
}