{
  "type": "Feature",
  "properties": {
    "iso:country":"US",
    "sg:address":"2277 Ridge Rd",
    "sg:city":"Library",
    "sg:classifiers":[
        {
            "category":"Recreation",
            "type":"Entertainment"
        },
        {
            "category":"Retail",
            "subcategory":"Animal Services",
            "type":"Services"
        }
    ],
    "sg:phone":"+1 412 655 9793",
    "sg:postcode":"15129",
    "sg:province":"PA",
    "sg:tags":[
        "boarding",
        "stable"
    ],
    "wof:name":"Morning Star Stables",
    "wof:placetype":"venue"
},
  "geometry": {"coordinates":[-79.988174,40.302837],"type":"Point"}
}