{
  "type": "Feature",
  "properties": {
    "iso:country":"US",
    "sg:address":"20344 School Rd",
    "sg:city":"Dry Run",
    "sg:classifiers":[
        {
            "category":"Social Services",
            "type":"Services"
        }
    ],
    "sg:phone":"+1 717 349 7227",
    "sg:postcode":"17220",
    "sg:province":"PA",
    "sg:tags":[
        "organization",
        "welfare"
    ],
    "wof:name":"Franklin County Senior Ctr",
    "wof:placetype":"venue"
},
  "geometry": {"coordinates":[-77.74977800000001,40.170258],"type":"Point"}
}