{
  "type": "Feature",
  "properties": {
    "iso:country":"US",
    "sg:address":"2620 Edgmont Ave",
    "sg:city":"Chester",
    "sg:classifiers":[
        {
            "category":"Shopping",
            "subcategory":"Gifts & Souvenirs",
            "type":"Retail Goods"
        }
    ],
    "sg:phone":"+1 610 876 1000",
    "sg:postcode":"19015",
    "sg:province":"PA",
    "sg:tags":[
        "balloon",
        "artist"
    ],
    "wof:name":"Parkside Florist",
    "wof:placetype":"venue"
},
  "geometry": {"coordinates":[-75.375872,39.866481],"type":"Point"}
}