{
  "type": "Feature",
  "properties": {
    "iso:country":"US",
    "sg:address":"3300 Aramingo Ave",
    "sg:city":"Philadelphia",
    "sg:classifiers":[
        {
            "category":"Shopping",
            "subcategory":"Pets & Pet Supplies",
            "type":"Retail Goods"
        }
    ],
    "sg:phone":"+1 215 423 4414",
    "sg:postcode":"19134",
    "sg:province":"PA",
    "sg:tags":[
        "store"
    ],
    "wof:name":"Petco",
    "wof:placetype":"venue"
},
  "geometry": {"coordinates":[-75.10340100000001,39.989899],"type":"Point"}
}