{
  "type": "Feature",
  "properties": {
    "iso:country":"US",
    "sg:address":"170 State Rte 168",
    "sg:city":"Darlington",
    "sg:classifiers":[
        {
            "category":"Retail",
            "subcategory":"Auto Repair",
            "type":"Services"
        }
    ],
    "sg:phone":"+1 724 827 2660",
    "sg:postcode":"16115",
    "sg:province":"PA",
    "sg:tags":[
        "body",
        "automobile",
        "painting"
    ],
    "wof:name":"Auto Body Works Inc",
    "wof:placetype":"venue"
},
  "geometry": {"coordinates":[-80.42513099999999,40.804693],"type":"Point"}
}