{
  "type": "Feature",
  "properties": {
    "iso:country":"US",
    "sg:address":"4291 Shellbrook Dr",
    "sg:city":"Hesston",
    "sg:classifiers":[
        {
            "category":"Farming",
            "subcategory":"Livestock Farm",
            "type":"Manufacturing & Wholesale Goods"
        },
        {
            "category":"Arena",
            "subcategory":"Horse Racetrack",
            "type":"Entertainment"
        }
    ],
    "sg:phone":"+1 814 658 2788",
    "sg:postcode":"16647",
    "sg:province":"PA",
    "sg:tags":[
        "breeder"
    ],
    "wof:name":"Shellbrook Boarding Stable",
    "wof:placetype":"venue"
},
  "geometry": {"coordinates":[-78.129368,40.435002],"type":"Point"}
}