{
  "type": "Feature",
  "properties": {
    "iso:country":"US",
    "sg:address":"605 Eden Park Blvd",
    "sg:city":"Mckeesport",
    "sg:classifiers":[
        {
            "category":"Retail",
            "subcategory":"Auto Repair",
            "type":"Services"
        }
    ],
    "sg:phone":"+1 412 751 8844",
    "sg:postcode":"15132",
    "sg:province":"PA",
    "sg:tags":[
        "body",
        "automobile",
        "painting"
    ],
    "wof:name":"Simonetta's Carstar Auto Body",
    "wof:placetype":"venue"
},
  "geometry": {"coordinates":[-79.82915800000001,40.33264],"type":"Point"}
}