{
  "type": "Feature",
  "properties": {
    "iso:country":"US",
    "sg:address":"4000 Benner St",
    "sg:city":"Philadelphia",
    "sg:classifiers":[
        {
            "category":"Food & Beverages",
            "subcategory":"Groceries & Convenience Stores",
            "type":"Retail Goods"
        }
    ],
    "sg:phone":"+1 215 533 5340",
    "sg:postcode":"19135",
    "sg:province":"PA",
    "wof:name":"Benner Food Market",
    "wof:placetype":"venue"
},
  "geometry": {"coordinates":[-75.065077,40.026753],"type":"Point"}
}