{
  "type": "Feature",
  "properties": {
    "iso:country":"US",
    "sg:address":"19917 Merritt Rd",
    "sg:city":"Saegertown",
    "sg:classifiers":[
        {
            "category":"Personal",
            "subcategory":"Beauty Salon",
            "type":"Services"
        }
    ],
    "sg:phone":"+1   ",
    "sg:postcode":"16433",
    "sg:province":"PA",
    "sg:tags":[
        "shop"
    ],
    "wof:name":"Angled Expressions",
    "wof:placetype":"venue"
},
  "geometry": {"coordinates":[-80.141443,41.767977],"type":"Point"}
}