{
  "type": "Feature",
  "properties": {
    "iso:country":"US",
    "sg:address":"509 Main St",
    "sg:city":"Forest City",
    "sg:classifiers":[
        {
            "category":"Recreation",
            "type":"Entertainment"
        }
    ],
    "sg:phone":"+1 570 785 3323",
    "sg:postcode":"18421",
    "sg:province":"PA",
    "sg:tags":[
        "lottery",
        "agent"
    ],
    "wof:name":"Rocs Smoke & Deli",
    "wof:placetype":"venue"
},
  "geometry": {"coordinates":[-75.466466,41.649118],"type":"Point"}
}