{
  "type": "Feature",
  "properties": {
    "iso:country":"US",
    "sg:address":"120 Miller St",
    "sg:city":"Allentown",
    "sg:classifiers":[
        {
            "category":"Real Estate",
            "subcategory":"Real Estate Agent",
            "type":"Services"
        }
    ],
    "sg:phone":"+1   ",
    "sg:postcode":"18104",
    "sg:province":"PA",
    "wof:name":"Valuation Resources Inc",
    "wof:placetype":"venue"
},
  "geometry": {"coordinates":[-75.512546,40.587459],"type":"Point"}
}