{
  "type": "Feature",
  "properties": {
    "iso:country":"US",
    "sg:address":"5353 Woodland Ave",
    "sg:city":"Philadelphia",
    "sg:classifiers":[
        {
            "category":"Restaurant",
            "type":"Food & Drink"
        }
    ],
    "sg:phone":"+1 215 729 1074",
    "sg:postcode":"19143",
    "sg:province":"PA",
    "sg:tags":[
        "african"
    ],
    "sg:website":"cittinews.com/baobab",
    "wof:name":"Le Baobab Restaurant",
    "wof:placetype":"venue"
},
  "geometry": {"coordinates":[-75.218479,39.936919],"type":"Point"}
}