{
  "type": "Feature",
  "properties": {
    "iso:country":"US",
    "sg:address":"14578 Hollowell Church Rd",
    "sg:city":"Waynesboro",
    "sg:classifiers":[
        {
            "category":"Farming",
            "subcategory":"Farm",
            "type":"Manufacturing & Wholesale Goods"
        }
    ],
    "sg:phone":"+1   ",
    "sg:postcode":"17268",
    "sg:province":"PA",
    "sg:tags":[
        "crop",
        "general"
    ],
    "wof:name":"Daniel Myers",
    "wof:placetype":"venue"
},
  "geometry": {"coordinates":[-77.673374,39.74534],"type":"Point"}
}