{
  "type": "Feature",
  "properties": {
    "addr:full":"549 Harrison City Rd Trafford PA 15085",
    "addr:housenumber":"549",
    "addr:postcode":"15085",
    "addr:street":"Harrison City Rd",
    "iso:country":"US",
    "sg:address":"549 Harrison City Rd",
    "sg:city":"Trafford",
    "sg:classifiers":[
        {
            "category":"Retail",
            "subcategory":"Auto Repair",
            "type":"Services"
        }
    ],
    "sg:phone":"+1 412 372 3372",
    "sg:postcode":"15085",
    "sg:province":"PA",
    "sg:tags":[
        "repairing",
        "automobile",
        "part",
        "supply"
    ],
    "wof:name":"Jim Locke Automotive",
    "wof:placetype":"venue"
},
  "geometry": {"coordinates":[-79.728844,40.39032],"type":"Point"}
}