{
  "type": "Feature",
  "properties": {
    "iso:country":"US",
    "sg:address":"816 Breakneck Rd",
    "sg:city":"Connellsville",
    "sg:classifiers":[
        {
            "category":"Organizations",
            "subcategory":"Religious Organization",
            "type":"Services"
        }
    ],
    "sg:phone":"+1 724 626 0993",
    "sg:postcode":"15425",
    "sg:province":"PA",
    "sg:tags":[
        "church"
    ],
    "wof:name":"Breakneck Church Fellowship",
    "wof:placetype":"venue"
},
  "geometry": {"coordinates":[-79.536676,40.041074],"type":"Point"}
}