{
  "type": "Feature",
  "properties": {
    "iso:country":"US",
    "sg:address":"115 W Germantown Pike Suite 100",
    "sg:city":"Norristown",
    "sg:classifiers":[
        {
            "category":"Professional",
            "subcategory":"Lawyer & Legal Services",
            "type":"Services"
        }
    ],
    "sg:phone":"+1 610 279 2480",
    "sg:postcode":"19401",
    "sg:province":"PA",
    "sg:tags":[
        "litigation",
        "attorney",
        "business",
        "family",
        "trial",
        "civil",
        "divorce",
        "real estate",
        "practice",
        "tort",
        "governmental",
        "planning",
        "law",
        "administrative"
    ],
    "sg:website":"http://www.mcgrorywentz.com",
    "wof:name":"Wentz, Nancy H - Mc Grory Wentz Law Office",
    "wof:placetype":"venue"
},
  "geometry": {"coordinates":[-75.318663,40.145297],"type":"Point"}
}