{
  "type": "Feature",
  "properties": {
    "iso:country":"US",
    "sg:address":"2 Brubeck Cir",
    "sg:city":"Marysville",
    "sg:classifiers":[
        {
            "category":"Food & Beverages",
            "subcategory":"Bakery",
            "type":"Retail Goods"
        }
    ],
    "sg:phone":"+1 717 957 4563",
    "sg:postcode":"17053",
    "sg:province":"PA",
    "sg:tags":[
        "baker"
    ],
    "wof:name":"Sweets 'N' Things",
    "wof:placetype":"venue"
},
  "geometry": {"coordinates":[-76.965676,40.332961],"type":"Point"}
}