{
  "type": "Feature",
  "properties": {
    "iso:country":"US",
    "sg:address":"3713 Lime-Kiln Rd",
    "sg:city":"Chambersburg",
    "sg:classifiers":[
        {
            "category":"Building & Trades",
            "subcategory":"Construction",
            "type":"Services"
        }
    ],
    "sg:phone":"+1   ",
    "sg:postcode":"17201",
    "sg:province":"PA",
    "sg:tags":[
        "house"
    ],
    "wof:name":"Wayne Forrester",
    "wof:placetype":"venue"
},
  "geometry": {"coordinates":[-77.621843,40.040293],"type":"Point"}
}