{
  "type": "Feature",
  "properties": {
    "iso:country":"US",
    "sg:address":"5974 Nor Bath Blvd",
    "sg:city":"Bath",
    "sg:classifiers":[
        {
            "category":"Shopping",
            "subcategory":"Computers & Home Electronics",
            "type":"Retail Goods"
        }
    ],
    "sg:phone":"+1 610 837 8825",
    "sg:postcode":"18014",
    "sg:province":"PA",
    "wof:name":"Harvey's Tv-Vcr Service Inc",
    "wof:placetype":"venue"
},
  "geometry": {"coordinates":[-75.418404,40.703701],"type":"Point"}
}