{
  "type": "Feature",
  "properties": {
    "iso:country":"US",
    "sg:address":"555 10th St",
    "sg:city":"Clairton",
    "sg:classifiers":[
        {
            "category":"Building & Trades",
            "subcategory":"Construction",
            "type":"Services"
        }
    ],
    "sg:phone":"+1   ",
    "sg:postcode":"15025",
    "sg:province":"PA",
    "sg:tags":[
        "residential"
    ],
    "wof:name":"Lazzaris Construction Co",
    "wof:placetype":"venue"
},
  "geometry": {"coordinates":[-79.89315999999999,40.2952],"type":"Point"}
}