{
  "type": "Feature",
  "properties": {
    "iso:country":"US",
    "sg:address":"1010 Butler Ave",
    "sg:city":"New Castle",
    "sg:classifiers":[
        {
            "category":"Manufacturing",
            "subcategory":"Rubber & Plastics",
            "type":"Manufacturing & Wholesale Goods"
        }
    ],
    "sg:phone":"+1 724 652 5341",
    "sg:postcode":"16101",
    "sg:province":"PA",
    "sg:tags":[
        "devices",
        "mfg"
    ],
    "wof:name":"Senko Manufacturing Co",
    "wof:placetype":"venue"
},
  "geometry": {"coordinates":[-80.327079,40.993551],"type":"Point"}
}