{
  "type": "Feature",
  "properties": {
    "iso:country":"US",
    "sg:address":"7326 Steinsburg Rd",
    "sg:city":"Coopersburg",
    "sg:classifiers":[
        {
            "category":"Banks & Credit Unions",
            "subcategory":"Financial Services",
            "type":"Services"
        }
    ],
    "sg:phone":"+1   ",
    "sg:postcode":"18036",
    "sg:province":"PA",
    "sg:tags":[
        "investor"
    ],
    "wof:name":"Ideal Enterprises",
    "wof:placetype":"venue"
},
  "geometry": {"coordinates":[-75.43266199999999,40.490034],"type":"Point"}
}