{
  "type": "Feature",
  "properties": {
    "iso:country":"US",
    "sg:address":"2651 Monroeville Blvd",
    "sg:city":"Monroeville",
    "sg:classifiers":[
        {
            "category":"Professional",
            "subcategory":"Lawyer & Legal Services",
            "type":"Services"
        }
    ],
    "sg:phone":"+1 412 372 2200",
    "sg:postcode":"15146",
    "sg:province":"PA",
    "sg:tags":[
        "attorney"
    ],
    "wof:name":"Scott P Magnuson",
    "wof:placetype":"venue"
},
  "geometry": {"coordinates":[-79.78312699999999,40.434727],"type":"Point"}
}