{
  "type": "Feature",
  "properties": {
    "iso:country":"US",
    "sg:address":"1905 Hart St",
    "sg:city":"Bethlehem",
    "sg:classifiers":[
        {
            "category":"Professional",
            "type":"Services"
        }
    ],
    "sg:phone":"+1   ",
    "sg:postcode":"18017",
    "sg:province":"PA",
    "wof:name":"Bugman Inc",
    "wof:placetype":"venue"
},
  "geometry": {"coordinates":[-75.351433,40.640369],"type":"Point"}
}