{
  "type": "Feature",
  "properties": {
    "iso:country":"US",
    "sg:address":"1659 Lititz Pike",
    "sg:city":"Lancaster",
    "sg:classifiers":[
        {
            "category":"Retail",
            "subcategory":"Laundry & Dry Cleaning",
            "type":"Services"
        }
    ],
    "sg:phone":"+1 717 397 5422",
    "sg:postcode":"17601",
    "sg:province":"PA",
    "sg:tags":[
        "cleaners"
    ],
    "sg:website":"www.davidwmenswear.com",
    "wof:name":"W David Tuxedos & More",
    "wof:placetype":"venue"
},
  "geometry": {"coordinates":[-76.307529,40.068827],"type":"Point"}
}