{
  "type": "Feature",
  "properties": {
    "addr:full":"115 S Charles St Red Lion PA 17356",
    "addr:housenumber":"115",
    "addr:postcode":"17356",
    "addr:street":"S Charles St",
    "iso:country":"US",
    "sg:address":"115 S Charles St",
    "sg:city":"Red Lion",
    "sg:classifiers":[
        {
            "category":"Home & Garden",
            "subcategory":"Carpets & Floor Coverings",
            "type":"Retail Goods"
        }
    ],
    "sg:phone":"+1 717 244 4460",
    "sg:postcode":"17356",
    "sg:province":"PA",
    "sg:tags":[
        "dealer",
        "rug"
    ],
    "wof:name":"Enfield Carpet Svc",
    "wof:placetype":"venue"
},
  "geometry": {"coordinates":[-76.605864,39.898434],"type":"Point"}
}