{
  "type": "Feature",
  "properties": {
    "iso:country":"US",
    "sg:address":"323 10th St",
    "sg:city":"Honesdale",
    "sg:classifiers":[
        {
            "category":"Social Services",
            "type":"Services"
        }
    ],
    "sg:phone":"+1   ",
    "sg:postcode":"18431",
    "sg:province":"PA",
    "sg:tags":[
        "executive"
    ],
    "wof:name":"Honesdale Senior Citizen Ctr",
    "wof:placetype":"venue"
},
  "geometry": {"coordinates":[-75.254267,41.575394],"type":"Point"}
}