{
  "type": "Feature",
  "properties": {
    "iso:country":"US",
    "sg:address":"2749 E Street Rd",
    "sg:city":"Bensalem",
    "sg:classifiers":[
        {
            "category":"Restaurant",
            "type":"Food & Drink"
        }
    ],
    "sg:phone":"+1 215 638 9902",
    "sg:postcode":"19020",
    "sg:province":"PA",
    "wof:name":"Quiznos Sub",
    "wof:placetype":"venue"
},
  "geometry": {"coordinates":[-74.952626,40.109261],"type":"Point"}
}