{
  "type": "Feature",
  "properties": {
    "iso:country":"US",
    "sg:address":"1316 Fretz Ave",
    "sg:city":"Allentown",
    "sg:classifiers":[
        {
            "category":"Building & Trades",
            "subcategory":"Construction",
            "type":"Services"
        }
    ],
    "sg:phone":"+1   ",
    "sg:postcode":"18103",
    "sg:province":"PA",
    "sg:tags":[
        "floor",
        "laying",
        "contractor"
    ],
    "wof:name":"J J J Flooring",
    "wof:placetype":"venue"
},
  "geometry": {"coordinates":[-75.42472100000001,40.590392],"type":"Point"}
}