{
  "type": "Feature",
  "properties": {
    "iso:country":"US",
    "sg:address":"1126 Walnut St",
    "sg:city":"Philadelphia",
    "sg:classifiers":[
        {
            "category":"Cafe",
            "type":"Food & Drink"
        },
        {
            "category":"Restaurant",
            "type":"Food & Drink"
        }
    ],
    "sg:menulink":"http://www.allmenus.com/pa/philadelphia/261769-caribou-cafe/menu/",
    "sg:phone":"+1 215 625 9535",
    "sg:postcode":"19107",
    "sg:province":"PA",
    "sg:tags":[
        "german",
        "french"
    ],
    "wof:name":"Caribou Cafe",
    "wof:placetype":"venue"
},
  "geometry": {"coordinates":[-75.15994000000001,39.948709],"type":"Point"}
}