{
  "type": "Feature",
  "properties": {
    "iso:country":"US",
    "sg:address":"49 Micahill Rd",
    "sg:city":"Levittown",
    "sg:classifiers":[
        {
            "category":"Building & Trades",
            "subcategory":"Landscaping Services",
            "type":"Services"
        }
    ],
    "sg:phone":"+1 215 949 3610",
    "sg:postcode":"19056",
    "sg:province":"PA",
    "sg:tags":[
        "tree"
    ],
    "wof:name":"Keystone Stump & Tree Svc",
    "wof:placetype":"venue"
},
  "geometry": {"coordinates":[-74.875039,40.132604],"type":"Point"}
}