{
  "type": "Feature",
  "properties": {
    "iso:country":"US",
    "sg:address":"111 Valley Rd",
    "sg:city":"Hamburg",
    "sg:classifiers":[
        {
            "category":"Freight",
            "type":"Transportation"
        }
    ],
    "sg:phone":"+1 610 562 9720",
    "sg:postcode":"19526",
    "sg:province":"PA",
    "sg:tags":[
        "livestock",
        "hauling"
    ],
    "wof:name":"Johnson Horse Transportation",
    "wof:placetype":"venue"
},
  "geometry": {"coordinates":[-75.95642700000001,40.564269],"type":"Point"}
}