{
  "type": "Feature",
  "properties": {
    "iso:country":"US",
    "sg:address":"146 N Bread St",
    "sg:city":"Philadelphia",
    "sg:classifiers":[
        {
            "category":"Professional",
            "subcategory":"Advertising",
            "type":"Services"
        }
    ],
    "sg:phone":"+1   ",
    "sg:postcode":"19106",
    "sg:province":"PA",
    "sg:tags":[
        "agency",
        "public",
        "relations"
    ],
    "wof:name":"Mc Laughlin & Morgan Inc",
    "wof:placetype":"venue"
},
  "geometry": {"coordinates":[-75.143944,39.953855],"type":"Point"}
}