{
  "type": "Feature",
  "properties": {
    "addr:full":"235 N Washington Ave Scranton PA 18503",
    "addr:housenumber":"235",
    "addr:postcode":"18503",
    "addr:street":"N Washington Ave",
    "iso:country":"US",
    "sg:address":"235 N Washington Ave",
    "sg:city":"Scranton",
    "sg:classifiers":[
        {
            "category":"Social Services",
            "type":"Services"
        }
    ],
    "sg:phone":"+1 570 207 5840",
    "sg:postcode":"18503",
    "sg:province":"PA",
    "sg:tags":[
        "probation"
    ],
    "wof:name":"US Probation & Parole Office",
    "wof:placetype":"venue"
},
  "geometry": {"coordinates":[-75.662857,41.408754],"type":"Point"}
}