{
  "type": "Feature",
  "properties": {
    "iso:country":"US",
    "sg:address":"160 Penn Adamsburg Rd",
    "sg:city":"Jeannette",
    "sg:classifiers":[
        {
            "category":"Manufacturing",
            "subcategory":"Apparel",
            "type":"Manufacturing & Wholesale Goods"
        },
        {
            "category":"Home & Garden",
            "subcategory":"Home Furnishings",
            "type":"Retail Goods"
        }
    ],
    "sg:phone":"+1 724 527 3818",
    "sg:postcode":"15644",
    "sg:province":"PA",
    "sg:tags":[
        "household",
        "quilting",
        "mfg"
    ],
    "wof:name":"Priscilla's Quilting",
    "wof:placetype":"venue"
},
  "geometry": {"coordinates":[-79.647161,40.315874],"type":"Point"}
}