{
  "type": "Feature",
  "properties": {
    "addr:full":"3335 Fieldstone Dr Doylestown PA 18902",
    "addr:housenumber":"3335",
    "addr:postcode":"18902",
    "addr:street":"Fieldstone Dr",
    "iso:country":"US",
    "sg:address":"3335 Fieldstone Dr",
    "sg:city":"Doylestown",
    "sg:classifiers":[
        {
            "category":"Building & Trades",
            "subcategory":"Construction",
            "type":"Services"
        }
    ],
    "sg:phone":"+1   ",
    "sg:postcode":"18902",
    "sg:province":"PA",
    "sg:tags":[
        "contractor"
    ],
    "wof:name":"Jwc Contracting LLC",
    "wof:placetype":"venue"
},
  "geometry": {"coordinates":[-76.675562,39.85978],"type":"Point"}
}