{
  "type": "Feature",
  "properties": {
    "addr:full":"300 Grant St South Fork PA 15956",
    "addr:housenumber":"300",
    "addr:postcode":"15956",
    "addr:street":"Grant St",
    "iso:country":"US",
    "sg:address":"300 Grant St",
    "sg:city":"South Fork",
    "sg:classifiers":[
        {
            "category":"Manufacturing",
            "subcategory":"Apparel",
            "type":"Manufacturing & Wholesale Goods"
        }
    ],
    "sg:phone":"+1 814 495 4625",
    "sg:postcode":"15956",
    "sg:province":"PA",
    "sg:tags":[
        "lingerie"
    ],
    "wof:name":"Empire Foundation",
    "wof:placetype":"venue"
},
  "geometry": {"coordinates":[-78.7907,40.365925],"type":"Point"}
}