{
  "type": "Feature",
  "properties": {
    "iso:country":"US",
    "sg:address":"141 McMichael Rd",
    "sg:city":"Carnegie",
    "sg:classifiers":[
        {
            "category":"Retail",
            "subcategory":"Animal Services",
            "type":"Services"
        }
    ],
    "sg:phone":"+1 412 279 2979",
    "sg:postcode":"15106",
    "sg:province":"PA",
    "wof:name":"An-Bert Boarding Kennels",
    "wof:placetype":"venue"
},
  "geometry": {"coordinates":[-80.141113,40.417323],"type":"Point"}
}