{
  "type": "Feature",
  "properties": {
    "iso:country":"US",
    "sg:address":"44 Tunkhannock Ave",
    "sg:city":"Exeter",
    "sg:classifiers":[
        {
            "category":"Health Services",
            "subcategory":"Health Practitioner",
            "type":"Services"
        }
    ],
    "sg:phone":"+1 570 655 8499",
    "sg:postcode":"18643",
    "sg:province":"PA",
    "sg:tags":[
        "nurse",
        "registry"
    ],
    "wof:name":"Nurse One Staffing",
    "wof:placetype":"venue"
},
  "geometry": {"coordinates":[-75.805339,41.337018],"type":"Point"}
}