{
  "type": "Feature",
  "properties": {
    "iso:country":"US",
    "sg:address":"3933 Perkiomen Ave",
    "sg:city":"Reading",
    "sg:classifiers":[
        {
            "category":"Health Services",
            "subcategory":"Chiropractor",
            "type":"Services"
        }
    ],
    "sg:phone":"+1 610 779 4588",
    "sg:postcode":"19606",
    "sg:province":"PA",
    "sg:tags":[
        "chiropractic"
    ],
    "sg:website":"http://www.spineandwellness.org",
    "wof:name":"Spine & Wellness Center of Exeter The",
    "wof:placetype":"venue"
},
  "geometry": {"coordinates":[-75.870791,40.314778],"type":"Point"}
}