{
  "type": "Feature",
  "properties": {
    "addr:full":"2804 Dewberry Rd York PA 17404",
    "addr:housenumber":"2804",
    "addr:postcode":"17404",
    "addr:street":"Dewberry Rd",
    "iso:country":"US",
    "sg:address":"2804 Dewberry Rd",
    "sg:city":"York",
    "sg:classifiers":[
        {
            "category":"Building & Trades",
            "subcategory":"Construction",
            "type":"Services"
        }
    ],
    "sg:phone":"+1   ",
    "sg:postcode":"17404",
    "sg:province":"PA",
    "sg:tags":[
        "house"
    ],
    "wof:name":"Lexington Builders",
    "wof:placetype":"venue"
},
  "geometry": {"coordinates":[-76.765694,40.013507],"type":"Point"}
}