{
  "type": "Feature",
  "properties": {
    "iso:country":"US",
    "sg:address":"11683 Woodlea Dr",
    "sg:city":"Waynesboro",
    "sg:classifiers":[
        {
            "category":"Retail",
            "subcategory":"Pet Boarding",
            "type":"Services"
        }
    ],
    "sg:phone":"+1 717 762 3966",
    "sg:postcode":"17268",
    "sg:province":"PA",
    "sg:tags":[
        "boarding/pet",
        "sitting"
    ],
    "wof:name":"Pets At Home",
    "wof:placetype":"venue"
},
  "geometry": {"coordinates":[-77.516076,39.753923],"type":"Point"}
}