{
  "type": "Feature",
  "properties": {
    "iso:country":"US",
    "sg:address":"60 Keystone Industrial Park",
    "sg:city":"Dunmore",
    "sg:classifiers":[
        {
            "category":"Wholesale",
            "subcategory":"Non-durable Goods",
            "type":"Manufacturing & Wholesale Goods"
        }
    ],
    "sg:phone":"+1 570 342 8245",
    "sg:postcode":"18512",
    "sg:province":"PA",
    "sg:tags":[
        "dry",
        "goods-wholesale"
    ],
    "wof:name":"Lackawanna Distributor Corp",
    "wof:placetype":"venue"
},
  "geometry": {"coordinates":[-75.61814,41.43666],"type":"Point"}
}