{
  "type": "Feature",
  "properties": {
    "iso:country":"US",
    "sg:address":"234 Howard St",
    "sg:city":"Butler",
    "sg:classifiers":[
        {
            "category":"Building & Trades",
            "subcategory":"Construction",
            "type":"Services"
        }
    ],
    "sg:phone":"+1 724 285 7782",
    "sg:postcode":"16001",
    "sg:province":"PA",
    "sg:tags":[
        "hanging",
        "painter",
        "contractor"
    ],
    "wof:name":"All Pro Painting Co",
    "wof:placetype":"venue"
},
  "geometry": {"coordinates":[-79.892465,40.865904],"type":"Point"}
}