{
  "type": "Feature",
  "properties": {
    "iso:country":"US",
    "sg:address":"1000 S Main St",
    "sg:city":"Greensburg",
    "sg:classifiers":[
        {
            "category":"Wholesale",
            "subcategory":"Electrical",
            "type":"Manufacturing & Wholesale Goods"
        }
    ],
    "sg:phone":"+1 724 834 4321",
    "sg:postcode":"15601",
    "sg:province":"PA",
    "sg:tags":[
        "equipment",
        "electric",
        "supply"
    ],
    "sg:website":"www.scottelectricusa.com",
    "wof:name":"Scott Electric Company",
    "wof:placetype":"venue"
},
  "geometry": {"coordinates":[-79.54529599999999,40.289189],"type":"Point"}
}