{
  "type": "Feature",
  "properties": {
    "iso:country":"US",
    "sg:address":"138 W 21st St",
    "sg:city":"Hazleton",
    "sg:classifiers":[
        {
            "category":"Restaurant",
            "type":"Food & Drink"
        }
    ],
    "sg:phone":"+1 570 825 3421",
    "sg:postcode":"18201",
    "sg:province":"PA",
    "wof:name":"Nardone Bakery Pizza Co",
    "wof:placetype":"venue"
},
  "geometry": {"coordinates":[-75.977653,40.972387],"type":"Point"}
}