{
  "type": "Feature",
  "properties": {
    "iso:country":"US",
    "sg:address":"916 13th St",
    "sg:city":"Elizabeth",
    "sg:classifiers":[
        {
            "category":"Shopping",
            "subcategory":"Florist",
            "type":"Retail Goods"
        }
    ],
    "sg:phone":"+1 412 384 8165",
    "sg:postcode":"15037",
    "sg:province":"PA",
    "wof:name":"Flowers By Ann",
    "wof:placetype":"venue"
},
  "geometry": {"coordinates":[-79.88630999999999,40.265219],"type":"Point"}
}