{
  "type": "Feature",
  "properties": {
    "addr:full":"5912 Germantown Ave Fl 1 Philadelphia PA 19144",
    "addr:housenumber":"5912;1",
    "addr:postcode":"19144",
    "addr:street":"Germantown Ave Fl",
    "iso:country":"US",
    "sg:address":"5912 Germantown Ave Fl 1",
    "sg:city":"Philadelphia",
    "sg:classifiers":[
        {
            "category":"Bars & Pubs",
            "type":"Food & Drink"
        },
        {
            "category":"Restaurant",
            "type":"Food & Drink"
        }
    ],
    "sg:phone":"+1 215 848 9902",
    "sg:postcode":"19144",
    "sg:province":"PA",
    "sg:tags":[
        "brew",
        "tavern"
    ],
    "wof:name":"Red Door Tavern",
    "wof:placetype":"venue"
},
  "geometry": {"coordinates":[-75.176635,40.038068],"type":"Point"}
}