{
  "type": "Feature",
  "properties": {
    "addr:full":"117 Heath Ct Chalfont PA 18914",
    "addr:housenumber":"117",
    "addr:postcode":"18914",
    "addr:street":"Heath Ct",
    "iso:country":"US",
    "sg:address":"117 Heath Ct",
    "sg:city":"Chalfont",
    "sg:classifiers":[
        {
            "category":"Professional",
            "type":"Services"
        }
    ],
    "sg:phone":"+1 215 513 1447",
    "sg:postcode":"18914",
    "sg:province":"PA",
    "wof:name":"N G Svc",
    "wof:placetype":"venue"
},
  "geometry": {"coordinates":[-75.211101,40.264683],"type":"Point"}
}