{
  "type": "Feature",
  "properties": {
    "iso:country":"US",
    "sg:address":"25 Locust Dr",
    "sg:city":"Dalton",
    "sg:classifiers":[
        {
            "category":"Banks & Credit Unions",
            "subcategory":"Investment Brokerage",
            "type":"Services"
        },
        {
            "category":"Professional",
            "subcategory":"Management & Consulting",
            "type":"Services"
        }
    ],
    "sg:phone":"+1 570 563 8818",
    "sg:postcode":"18414",
    "sg:province":"PA",
    "sg:tags":[
        "advisory",
        "financial"
    ],
    "wof:name":"Thomas R Lanton Associates",
    "wof:placetype":"venue"
},
  "geometry": {"coordinates":[-75.789056,41.532027],"type":"Point"}
}