{
  "type": "Feature",
  "properties": {
    "addr:full":"1761 Main St Bloomsburg PA 17815",
    "addr:housenumber":"1761",
    "addr:postcode":"17815",
    "addr:street":"Main St",
    "iso:country":"US",
    "sg:address":"1761 Main St",
    "sg:city":"Bloomsburg",
    "sg:classifiers":[
        {
            "category":"Wholesale",
            "subcategory":"Construction Materials",
            "type":"Manufacturing & Wholesale Goods"
        }
    ],
    "sg:phone":"+1   ",
    "sg:postcode":"17815",
    "sg:province":"PA",
    "wof:name":"About Face",
    "wof:placetype":"venue"
},
  "geometry": {"coordinates":[-76.42346999999999,41.037022],"type":"Point"}
}