{
  "type": "Feature",
  "properties": {
    "iso:country":"US",
    "sg:address":"150 W Mount Carmel Ave",
    "sg:city":"Mt Carmel",
    "sg:classifiers":[
        {
            "category":"Government",
            "subcategory":"Office",
            "type":"Public Place"
        }
    ],
    "sg:phone":"+1 570 339 2140",
    "sg:postcode":"17851",
    "sg:province":"PA",
    "wof:name":"Mount Carmel Dist Justice Ofc",
    "wof:placetype":"venue"
},
  "geometry": {"coordinates":[-76.415766,40.798608],"type":"Point"}
}