{
  "type": "Feature",
  "properties": {
    "iso:country":"US",
    "sg:address":"5501 Cedar Ave",
    "sg:city":"Philadelphia",
    "sg:classifiers":[
        {
            "category":"Organizations",
            "subcategory":"Religious Organization",
            "type":"Services"
        }
    ],
    "sg:phone":"+1 215 472 2936",
    "sg:postcode":"19143",
    "sg:province":"PA",
    "wof:name":"Sisters of Ihm",
    "wof:placetype":"venue"
},
  "geometry": {"coordinates":[-75.233101,39.951099],"type":"Point"}
}