{
  "type": "Feature",
  "properties": {
    "iso:country":"US",
    "sg:address":"301 Rolling Ridge Dr",
    "sg:city":"Bellefonte",
    "sg:classifiers":[
        {
            "category":"Personal",
            "type":"Services"
        }
    ],
    "sg:phone":"+1 814 234 7090",
    "sg:postcode":"16823",
    "sg:province":"PA",
    "sg:tags":[
        "mover"
    ],
    "wof:name":"Sullivan's Moving & Storage",
    "wof:placetype":"venue"
},
  "geometry": {"coordinates":[-77.777901,40.885399],"type":"Point"}
}