{
  "type": "Feature",
  "properties": {
    "iso:country":"US",
    "sg:address":"919 Hanover Ave",
    "sg:city":"Allentown",
    "sg:classifiers":[
        {
            "category":"Professional",
            "subcategory":"Accounting & Tax Preparation",
            "type":"Services"
        }
    ],
    "sg:phone":"+1 610 782 9102",
    "sg:postcode":"18109",
    "sg:province":"PA",
    "sg:tags":[
        "bookkeeping",
        "general"
    ],
    "wof:name":"Trexler Business Solutions",
    "wof:placetype":"venue"
},
  "geometry": {"coordinates":[-75.440209,40.617459],"type":"Point"}
}