{
  "type": "Feature",
  "properties": {
    "iso:country":"US",
    "sg:address":"227 Mayfair Dr",
    "sg:city":"Pittsburgh",
    "sg:classifiers":[
        {
            "category":"Wholesale",
            "subcategory":"Hardware",
            "type":"Manufacturing & Wholesale Goods"
        },
        {
            "category":"Wholesale",
            "subcategory":"Durable Goods & Equipment",
            "type":"Manufacturing & Wholesale Goods"
        }
    ],
    "sg:phone":"+1 412 343 0566",
    "sg:postcode":"15228",
    "sg:province":"PA",
    "sg:tags":[
        "plumbing",
        "representative",
        "manufacturer"
    ],
    "wof:name":"R L Eppelsheimer Co Inc",
    "wof:placetype":"venue"
},
  "geometry": {"coordinates":[-80.05985200000001,40.370824],"type":"Point"}
}