{
  "type": "Feature",
  "properties": {
    "iso:country":"US",
    "sg:address":"604 Main St",
    "sg:city":"Irwin",
    "sg:classifiers":[
        {
            "category":"Professional",
            "subcategory":"Business Services",
            "type":"Services"
        }
    ],
    "sg:phone":"+1 724 863 2466",
    "sg:postcode":"15642",
    "sg:province":"PA",
    "sg:tags":[
        "appraiser"
    ],
    "wof:name":"Property Damage Appraisers Inc",
    "wof:placetype":"venue"
},
  "geometry": {"coordinates":[-79.71023700000001,40.328438],"type":"Point"}
}