{
  "type": "Feature",
  "properties": {
    "iso:country":"US",
    "sg:address":"1812 Lincoln Way",
    "sg:city":"White Oak",
    "sg:classifiers":[
        {
            "category":"Insurance",
            "subcategory":"Insurance Agent",
            "type":"Services"
        }
    ],
    "sg:phone":"+1 412 664 4177",
    "sg:postcode":"15131",
    "sg:province":"PA",
    "sg:website":"www.therealtyco.com",
    "wof:name":"Realty Co",
    "wof:placetype":"venue"
},
  "geometry": {"coordinates":[-79.814294,40.343773],"type":"Point"}
}