{
  "type": "Feature",
  "properties": {
    "addr:full":"7657 S State Rte 44 Williamsport PA 17702",
    "addr:housenumber":"7657",
    "addr:postcode":"17702",
    "addr:street":"S State Rte 44",
    "iso:country":"US",
    "sg:address":"7657 S State Rte 44",
    "sg:city":"Williamsport",
    "sg:classifiers":[
        {
            "category":"Retail",
            "subcategory":"Auto Repair",
            "type":"Services"
        }
    ],
    "sg:phone":"+1 570 745 3877",
    "sg:postcode":"17702",
    "sg:province":"PA",
    "sg:tags":[
        "repairing",
        "automobile"
    ],
    "wof:name":"Niles Garage Inc Computer",
    "wof:placetype":"venue"
},
  "geometry": {"coordinates":[-77.14876099999999,41.148591],"type":"Point"}
}