{
  "type": "Feature",
  "properties": {
    "iso:country":"US",
    "sg:address":"265 N Queen St",
    "sg:city":"York",
    "sg:classifiers":[
        {
            "category":"Home & Garden",
            "subcategory":"Building Materials",
            "type":"Retail Goods"
        },
        {
            "category":"Manufacturing",
            "subcategory":"Glass & Minerals",
            "type":"Manufacturing & Wholesale Goods"
        }
    ],
    "sg:phone":"+1 717 846 4466",
    "sg:postcode":"17403",
    "sg:province":"PA",
    "sg:tags":[
        "mfg",
        "porcelain",
        "supply",
        "heat",
        "insulation",
        "wool"
    ],
    "sg:website":"www.allfabrications.com",
    "wof:name":"All Fabrications Inc",
    "wof:placetype":"venue"
},
  "geometry": {"coordinates":[-76.725911,39.967677],"type":"Point"}
}