{
  "type": "Feature",
  "properties": {
    "iso:country":"US",
    "sg:address":"2133 W 37th St",
    "sg:city":"Erie",
    "sg:classifiers":[
        {
            "category":"Manufacturing",
            "subcategory":"Motor Vehicles & Parts",
            "type":"Manufacturing & Wholesale Goods"
        }
    ],
    "sg:phone":"+1   ",
    "sg:postcode":"16508",
    "sg:province":"PA",
    "sg:tags":[
        "equipment",
        "railroad",
        "mfg"
    ],
    "wof:name":"Train Masters",
    "wof:placetype":"venue"
},
  "geometry": {"coordinates":[-80.11438200000001,42.085167],"type":"Point"}
}