{
  "type": "Feature",
  "properties": {
    "addr:full":"40 Becker St Houston PA 15342",
    "addr:housenumber":"40",
    "addr:postcode":"15342",
    "addr:street":"Becker St",
    "iso:country":"US",
    "sg:address":"40 Becker St",
    "sg:city":"Houston",
    "sg:classifiers":[
        {
            "category":"Retail",
            "subcategory":"Auto Repair",
            "type":"Services"
        }
    ],
    "sg:phone":"+1 724 745 5507",
    "sg:postcode":"15342",
    "sg:province":"PA",
    "sg:tags":[
        "glass",
        "replacement"
    ],
    "wof:name":"Dodd Auto Specialty",
    "wof:placetype":"venue"
},
  "geometry": {"coordinates":[-80.204463,40.248459],"type":"Point"}
}