{
  "type": "Feature",
  "properties": {
    "addr:full":"100 Kimble Rd Exton PA 19352",
    "addr:housenumber":"100",
    "addr:postcode":"19352",
    "addr:street":"Kimble Rd",
    "iso:country":"US",
    "sg:address":"100 Kimble Rd",
    "sg:city":"Exton",
    "sg:classifiers":[
        {
            "category":"Professional",
            "subcategory":"Engineering",
            "type":"Services"
        }
    ],
    "sg:phone":"+1   ",
    "sg:postcode":"19352",
    "sg:province":"PA",
    "wof:name":"Figgs Engineering Group",
    "wof:placetype":"venue"
},
  "geometry": {"coordinates":[-75.91630499999999,39.813449],"type":"Point"}
}