{
  "type": "Feature",
  "properties": {
    "iso:country":"US",
    "sg:address":"118 Kendall Ave",
    "sg:city":"Jersey Shore",
    "sg:classifiers":[
        {
            "category":"Professional",
            "type":"Services"
        }
    ],
    "sg:phone":"+1 570 398 2557",
    "sg:postcode":"17740",
    "sg:province":"PA",
    "sg:tags":[
        "establishment"
    ],
    "wof:name":"Rectory St Luke's Catholic Chr",
    "wof:placetype":"venue"
},
  "geometry": {"coordinates":[-77.265878,41.203687],"type":"Point"}
}