{
  "type": "Feature",
  "properties": {
    "iso:country":"US",
    "sg:address":"364 Roberts Ave",
    "sg:city":"Conshohocken",
    "sg:phone":"+1 610 941 7034",
    "sg:postcode":"19428",
    "sg:province":"PA",
    "wof:name":"Perfect Weddings",
    "wof:placetype":"venue"
},
  "geometry": {"coordinates":[-75.289255,40.081713],"type":"Point"}
}