{
  "type": "Feature",
  "properties": {
    "iso:country":"US",
    "sg:address":"748 Quincy Ave",
    "sg:city":"Scranton",
    "sg:classifiers":[
        {
            "category":"Health Services",
            "subcategory":"Doctor",
            "type":"Services"
        }
    ],
    "sg:phone":"+1 570 342 5253",
    "sg:postcode":"18510",
    "sg:province":"PA",
    "sg:tags":[
        "physician",
        "surgeon"
    ],
    "wof:name":"Pancoast Fagerburg & Assoc",
    "wof:placetype":"venue"
},
  "geometry": {"coordinates":[-75.65060699999999,41.410773],"type":"Point"}
}