{
  "type": "Feature",
  "properties": {
    "iso:country":"US",
    "sg:address":"80 Barrick Hill Rd",
    "sg:city":"Shermans Dale",
    "sg:classifiers":[
        {
            "category":"Professional",
            "subcategory":"Computer Services",
            "type":"Services"
        }
    ],
    "sg:phone":"+1 717 582 3450",
    "sg:postcode":"17090",
    "sg:province":"PA",
    "sg:tags":[
        "repair"
    ],
    "wof:name":"Eds Computer Repair",
    "wof:placetype":"venue"
},
  "geometry": {"coordinates":[-77.19283,40.31001],"type":"Point"}
}