{
  "type": "Feature",
  "properties": {
    "iso:country":"US",
    "sg:address":"1079 Victor Ln",
    "sg:city":"Bryn Mawr",
    "sg:classifiers":[
        {
            "category":"Banks & Credit Unions",
            "subcategory":"Financial Services",
            "type":"Services"
        }
    ],
    "sg:phone":"+1   ",
    "sg:postcode":"19010",
    "sg:province":"PA",
    "sg:tags":[
        "trust",
        "nonprofit",
        "management"
    ],
    "wof:name":"Sauer Family Foundation",
    "wof:placetype":"venue"
},
  "geometry": {"coordinates":[-75.314626,40.036029],"type":"Point"}
}