{
  "type": "Feature",
  "properties": {
    "iso:country":"US",
    "sg:address":"185 Bollinger Rd",
    "sg:city":"Littlestown",
    "sg:classifiers":[
        {
            "category":"Shopping",
            "type":"Retail Goods"
        }
    ],
    "sg:phone":"+1 717 359 7292",
    "sg:postcode":"17340",
    "sg:province":"PA",
    "sg:tags":[
        "monument"
    ],
    "wof:name":"Sneeringer Memorials",
    "wof:placetype":"venue"
},
  "geometry": {"coordinates":[-77.068825,39.728401],"type":"Point"}
}