{
  "type": "Feature",
  "properties": {
    "addr:full":"733 Waverly Rd Bryn Mawr PA 19010",
    "addr:housenumber":"733",
    "addr:postcode":"19010",
    "addr:street":"Waverly Rd",
    "iso:country":"US",
    "sg:address":"733 Waverly Rd",
    "sg:city":"Bryn Mawr",
    "sg:classifiers":[
        {
            "category":"Banks & Credit Unions",
            "subcategory":"Financial Services",
            "type":"Services"
        }
    ],
    "sg:phone":"+1   ",
    "sg:postcode":"19010",
    "sg:province":"PA",
    "sg:tags":[
        "company",
        "holding"
    ],
    "wof:name":"P J M Holdings Inc",
    "wof:placetype":"venue"
},
  "geometry": {"coordinates":[-75.29850500000001,40.038097],"type":"Point"}
}