{
  "type": "Feature",
  "properties": {
    "iso:country":"US",
    "sg:address":"4014 S Warner Rd",
    "sg:city":"Lafayette Hill",
    "sg:classifiers":[
        {
            "category":"Manufacturing",
            "subcategory":"Printing",
            "type":"Manufacturing & Wholesale Goods"
        }
    ],
    "sg:phone":"+1 610 828 8966",
    "sg:postcode":"19444",
    "sg:province":"PA",
    "sg:tags":[
        "printer"
    ],
    "wof:name":"D B Printing Svc Printers",
    "wof:placetype":"venue"
},
  "geometry": {"coordinates":[-75.257291,40.091264],"type":"Point"}
}