{
  "type": "Feature",
  "properties": {
    "iso:country":"US",
    "sg:address":"122 Gilligan St",
    "sg:city":"Wilkes Barre",
    "sg:classifiers":[
        {
            "category":"Communications",
            "subcategory":"Film & Video Production",
            "type":"Services"
        },
        {
            "category":"Retail",
            "subcategory":"Portrait Studio",
            "type":"Services"
        }
    ],
    "sg:phone":"+1 570 826 1124",
    "sg:postcode":"18702",
    "sg:province":"PA",
    "sg:tags":[
        "motion",
        "picture",
        "taping",
        "photo"
    ],
    "sg:website":"www.skopekphoto.com",
    "wof:name":"Skopek's Photography",
    "wof:placetype":"venue"
},
  "geometry": {"coordinates":[-75.90087,41.226385],"type":"Point"}
}