{
  "type": "Feature",
  "properties": {
    "iso:country":"US",
    "sg:address":"545 Prospect Rd",
    "sg:city":"Evans City",
    "sg:classifiers":[
        {
            "category":"Travel",
            "subcategory":"Travel Agent",
            "type":"Entertainment"
        }
    ],
    "sg:phone":"+1 724 538 8738",
    "sg:postcode":"16033",
    "sg:province":"PA",
    "sg:tags":[
        "agency"
    ],
    "wof:name":"Smart Start Travel",
    "wof:placetype":"venue"
},
  "geometry": {"coordinates":[-80.05431,40.800032],"type":"Point"}
}