{
  "type": "Feature",
  "properties": {
    "iso:country":"US",
    "sg:address":"943 Walnut St",
    "sg:city":"Royersford",
    "sg:classifiers":[
        {
            "category":"Building & Trades",
            "subcategory":"Construction",
            "type":"Services"
        }
    ],
    "sg:phone":"+1   ",
    "sg:postcode":"19468",
    "sg:province":"PA",
    "sg:tags":[
        "carpentry",
        "contractor"
    ],
    "wof:name":"Frank R Derby Construction",
    "wof:placetype":"venue"
},
  "geometry": {"coordinates":[-75.528994,40.192017],"type":"Point"}
}