{
  "type": "Feature",
  "properties": {
    "iso:country":"US",
    "sg:address":"29 Bala Ave",
    "sg:city":"Bala Cynwyd",
    "sg:classifiers":[
        {
            "category":"Wholesale",
            "subcategory":"Machinery & Supplies",
            "type":"Manufacturing & Wholesale Goods"
        }
    ],
    "sg:phone":"+1 610 664 9500",
    "sg:postcode":"19004",
    "sg:province":"PA",
    "sg:tags":[
        "equipment",
        "dairy"
    ],
    "wof:name":"B T Engineering Inc",
    "wof:placetype":"venue"
},
  "geometry": {"coordinates":[-75.231033,40.003115],"type":"Point"}
}