{
  "type": "Feature",
  "properties": {
    "addr:full":"24 N Main St Shenandoah PA 17976",
    "addr:housenumber":"24",
    "addr:postcode":"17976",
    "addr:street":"N Main St",
    "iso:country":"US",
    "sg:address":"24 N Main St",
    "sg:city":"Shenandoah",
    "sg:classifiers":[
        {
            "category":"Health Services",
            "subcategory":"Doctor",
            "type":"Services"
        }
    ],
    "sg:phone":"+1 570 462 1033",
    "sg:postcode":"17976",
    "sg:province":"PA",
    "sg:tags":[
        "physician",
        "surgeon"
    ],
    "wof:name":"Main Street Medical Ctr Inc",
    "wof:placetype":"venue"
},
  "geometry": {"coordinates":[-76.201471,40.821245],"type":"Point"}
}