{
  "type": "Feature",
  "properties": {
    "iso:country":"US",
    "sg:address":"6202 Elmwood Ave",
    "sg:city":"Philadelphia",
    "sg:classifiers":[
        {
            "category":"Food & Beverages",
            "subcategory":"Groceries & Convenience Stores",
            "type":"Retail Goods"
        }
    ],
    "sg:phone":"+1 215 729 6466",
    "sg:postcode":"19142",
    "sg:province":"PA",
    "wof:name":"Lam Hung",
    "wof:placetype":"venue"
},
  "geometry": {"coordinates":[-75.22669999999999,39.924999],"type":"Point"}
}