{
  "type": "Feature",
  "properties": {
    "iso:country":"US",
    "sg:address":"404 Norfolk Rd",
    "sg:city":"Flourtown",
    "sg:classifiers":[
        {
            "category":"Insurance",
            "subcategory":"Insurance Agent",
            "type":"Services"
        }
    ],
    "sg:phone":"+1 215 233 4476",
    "sg:postcode":"19031",
    "sg:province":"PA",
    "sg:tags":[
        "consultant"
    ],
    "wof:name":"Northshore Intl Insurance Adj",
    "wof:placetype":"venue"
},
  "geometry": {"coordinates":[-75.20251,40.106161],"type":"Point"}
}