{
  "type": "Feature",
  "properties": {
    "addr:full":"4 Progress St East Stroudsburg PA 18301",
    "addr:housenumber":"4",
    "addr:postcode":"18301",
    "addr:street":"Progress St",
    "iso:country":"US",
    "sg:address":"4 Progress St",
    "sg:city":"East Stroudsburg",
    "sg:classifiers":[
        {
            "category":"Banks & Credit Unions",
            "subcategory":"Bank",
            "type":"Services"
        }
    ],
    "sg:phone":"+1   ",
    "sg:postcode":"18301",
    "sg:province":"PA",
    "sg:tags":[
        "federal"
    ],
    "wof:name":"Tobyhnna Army Depo Fdral Cr Un",
    "wof:placetype":"venue"
},
  "geometry": {"coordinates":[-75.192769,41.019499],"type":"Point"}
}