{
  "type": "Feature",
  "properties": {
    "iso:country":"US",
    "sg:address":"79 Skyline Dr",
    "sg:city":"Hickory",
    "sg:classifiers":[
        {
            "category":"Building & Trades",
            "subcategory":"Construction",
            "type":"Services"
        }
    ],
    "sg:phone":"+1   ",
    "sg:postcode":"15340",
    "sg:province":"PA",
    "sg:tags":[
        "concrete",
        "contractor"
    ],
    "wof:name":"K & P Asphalt",
    "wof:placetype":"venue"
},
  "geometry": {"coordinates":[-80.35081700000001,40.305191],"type":"Point"}
}