{
  "type": "Feature",
  "properties": {
    "iso:country":"US",
    "sg:address":"255 Reeceville Rd",
    "sg:city":"Coatesville",
    "sg:classifiers":[
        {
            "category":"Health Services",
            "subcategory":"Clinic",
            "type":"Services"
        }
    ],
    "sg:phone":"+1   ",
    "sg:postcode":"19320",
    "sg:province":"PA",
    "sg:tags":[
        "home",
        "care"
    ],
    "wof:name":"Brandywyne HM Hlth Care Hspice",
    "wof:placetype":"venue"
},
  "geometry": {"coordinates":[-75.79072499999999,40.014114],"type":"Point"}
}