{
  "type": "Feature",
  "properties": {
    "addr:full":"140 N Lansdowne Ave Lansdowne PA 19050",
    "addr:housenumber":"140",
    "addr:postcode":"19050",
    "addr:street":"N Lansdowne Ave",
    "iso:country":"US",
    "sg:address":"140 N Lansdowne Ave",
    "sg:city":"Lansdowne",
    "sg:classifiers":[
        {
            "category":"Social Services",
            "subcategory":"Child Care",
            "type":"Services"
        }
    ],
    "sg:phone":"+1 610 622 0800",
    "sg:postcode":"19050",
    "sg:province":"PA",
    "sg:tags":[
        "kindergarten",
        "academic",
        "school"
    ],
    "sg:website":"www.lansdownechurch.com",
    "wof:name":"Lansdowne Pres Nursey School",
    "wof:placetype":"venue"
},
  "geometry": {"coordinates":[-75.27520199999999,39.944698],"type":"Point"}
}