{
  "type": "Feature",
  "properties": {
    "addr:full":"8 W Market St Wilkes Barre PA 18701",
    "addr:housenumber":"8",
    "addr:postcode":"18701",
    "addr:street":"W Market St",
    "iso:country":"US",
    "sg:address":"8 W Market St",
    "sg:city":"Wilkes Barre",
    "sg:classifiers":[
        {
            "category":"Social Services",
            "type":"Services"
        }
    ],
    "sg:phone":"+1 570 829 6711",
    "sg:postcode":"18701",
    "sg:province":"PA",
    "sg:tags":[
        "organization",
        "welfare"
    ],
    "sg:website":"www.unitedwaywb.org",
    "wof:name":"United Way",
    "wof:placetype":"venue"
},
  "geometry": {"coordinates":[-75.882746,41.246757],"type":"Point"}
}