{
  "type": "Feature",
  "properties": {
    "addr:full":"514 Ash St Scranton PA 18509",
    "addr:housenumber":"514",
    "addr:postcode":"18509",
    "addr:street":"Ash St",
    "iso:country":"US",
    "sg:address":"514 Ash St",
    "sg:city":"Scranton",
    "sg:classifiers":[
        {
            "category":"Restaurant",
            "type":"Food & Drink"
        },
        {
            "category":"Wholesale",
            "subcategory":"Beer",
            "type":"Manufacturing & Wholesale Goods"
        }
    ],
    "sg:phone":"+1 570 207 4718",
    "sg:postcode":"18509",
    "sg:province":"PA",
    "sg:tags":[
        "ale",
        "eating"
    ],
    "wof:name":"Variety Brews II",
    "wof:placetype":"venue"
},
  "geometry": {"coordinates":[-75.652367,41.416826],"type":"Point"}
}