{
  "type": "Feature",
  "properties": {
    "iso:country":"US",
    "sg:address":"550 Days Mill Rd",
    "sg:city":"York",
    "sg:classifiers":[
        {
            "category":"Building & Trades",
            "subcategory":"Construction",
            "type":"Services"
        }
    ],
    "sg:phone":"+1   ",
    "sg:postcode":"17403",
    "sg:province":"PA",
    "sg:tags":[
        "home",
        "remodeling",
        "family",
        "contractor"
    ],
    "wof:name":"Timothy L Yelton Construction",
    "wof:placetype":"venue"
},
  "geometry": {"coordinates":[-76.759224,39.913408],"type":"Point"}
}