{
  "type": "Feature",
  "properties": {
    "iso:country":"US",
    "sg:address":"1 Holly Ct",
    "sg:city":"Lititz",
    "sg:classifiers":[
        {
            "category":"Building & Trades",
            "subcategory":"Construction",
            "type":"Services"
        }
    ],
    "sg:phone":"+1 717 627 0109",
    "sg:postcode":"17543",
    "sg:province":"PA",
    "sg:tags":[
        "painter"
    ],
    "wof:name":"Williams & Williams",
    "wof:placetype":"venue"
},
  "geometry": {"coordinates":[-76.304002,40.170072],"type":"Point"}
}