{
  "type": "Feature",
  "properties": {
    "addr:full":"2029 N Broad St Philadelphia PA 19122",
    "addr:housenumber":"2029",
    "addr:postcode":"19122",
    "addr:street":"N Broad St",
    "iso:country":"US",
    "sg:address":"2029 N Broad St",
    "sg:city":"Philadelphia",
    "sg:classifiers":[
        {
            "category":"Travel",
            "subcategory":"Hotels & Motels",
            "type":"Entertainment"
        }
    ],
    "sg:phone":"+1   ",
    "sg:postcode":"19122",
    "sg:province":"PA",
    "sg:tags":[
        "operation"
    ],
    "wof:name":"Marriott",
    "wof:placetype":"venue"
},
  "geometry": {"coordinates":[-75.156609,39.984249],"type":"Point"}
}