{
  "type": "Feature",
  "properties": {
    "iso:country":"US",
    "sg:address":"131 Mill Grove Dr",
    "sg:city":"Norristown",
    "sg:classifiers":[
        {
            "category":"Real Estate",
            "subcategory":"Real Estate Operator",
            "type":"Services"
        }
    ],
    "sg:phone":"+1   ",
    "sg:postcode":"19403",
    "sg:province":"PA",
    "sg:tags":[
        "building",
        "nonresidential"
    ],
    "wof:name":"Mg Associates L P",
    "wof:placetype":"venue"
},
  "geometry": {"coordinates":[-75.43692799999999,40.130396],"type":"Point"}
}