{
  "type": "Feature",
  "properties": {
    "iso:country":"US",
    "sg:address":"1201 Roosevelt Ave",
    "sg:city":"York",
    "sg:classifiers":[
        {
            "category":"Autos & Motor Vehicles",
            "subcategory":"Automobile Sales",
            "type":"Retail Goods"
        }
    ],
    "sg:phone":"+1 717 843 7926",
    "sg:postcode":"17404",
    "sg:province":"PA",
    "sg:tags":[
        "car",
        "dealer"
    ],
    "wof:name":"Touring Cars",
    "wof:placetype":"venue"
},
  "geometry": {"coordinates":[-76.755281,39.975481],"type":"Point"}
}