{
  "type": "Feature",
  "properties": {
    "iso:country":"US",
    "sg:address":"3 State Rte 405",
    "sg:city":"Milton",
    "sg:classifiers":[
        {
            "category":"Restaurant",
            "type":"Food & Drink"
        }
    ],
    "sg:phone":"+1 570 742 9708",
    "sg:postcode":"17847",
    "sg:province":"PA",
    "wof:name":"Fetter's Family Restaurant",
    "wof:placetype":"venue"
},
  "geometry": {"coordinates":[-76.855208,41.020136],"type":"Point"}
}