{
  "type": "Feature",
  "properties": {
    "iso:country":"US",
    "sg:address":"264 Westmoreland Ave",
    "sg:city":"Greensburg",
    "sg:classifiers":[
        {
            "category":"Shopping",
            "subcategory":"Musical Instruments",
            "type":"Retail Goods"
        }
    ],
    "sg:phone":"+1 724 929 2776",
    "sg:postcode":"15601",
    "sg:province":"PA",
    "sg:tags":[
        "organs"
    ],
    "wof:name":"Trombino Music Ctr",
    "wof:placetype":"venue"
},
  "geometry": {"coordinates":[-79.533861,40.30037],"type":"Point"}
}