{
  "type": "Feature",
  "properties": {
    "iso:country":"US",
    "sg:address":"416 Rebecca Ave",
    "sg:city":"Pittsburgh",
    "sg:classifiers":[
        {
            "category":"Personal",
            "subcategory":"Barber",
            "type":"Services"
        }
    ],
    "sg:phone":"+1   ",
    "sg:postcode":"15221",
    "sg:province":"PA",
    "sg:tags":[
        "shop"
    ],
    "wof:name":"Kenneths Barber Shop",
    "wof:placetype":"venue"
},
  "geometry": {"coordinates":[-79.889399,40.441401],"type":"Point"}
}