{
  "type": "Feature",
  "properties": {
    "iso:country":"US",
    "sg:address":"972 Brookline Blvd",
    "sg:city":"Pittsburgh",
    "sg:classifiers":[
        {
            "category":"Shopping",
            "subcategory":"Gifts & Souvenirs",
            "type":"Retail Goods"
        }
    ],
    "sg:phone":"+1 412 343 4002",
    "sg:postcode":"15226",
    "sg:province":"PA",
    "wof:name":"Ceramic Etcetera",
    "wof:placetype":"venue"
},
  "geometry": {"coordinates":[-80.01907,40.393074],"type":"Point"}
}