{
  "type": "Feature",
  "properties": {
    "iso:country":"US",
    "sg:address":"2208 Gettysburg Rd",
    "sg:city":"Camp Hill",
    "sg:classifiers":[
        {
            "category":"Food & Beverages",
            "subcategory":"Bakery",
            "type":"Retail Goods"
        }
    ],
    "sg:phone":"+1   ",
    "sg:postcode":"17011",
    "sg:province":"PA",
    "wof:name":"Stroehmann Bakeries Outlet",
    "wof:placetype":"venue"
},
  "geometry": {"coordinates":[-76.920298,40.22955],"type":"Point"}
}