{
  "type": "Feature",
  "properties": {
    "iso:country":"US",
    "sg:address":"2771 Paxton St",
    "sg:city":"Harrisburg",
    "sg:classifiers":[
        {
            "category":"Wholesale",
            "subcategory":"Machinery & Supplies",
            "type":"Manufacturing & Wholesale Goods"
        }
    ],
    "sg:phone":"+1 717 234 6432",
    "sg:postcode":"17111",
    "sg:province":"PA",
    "sg:tags":[
        "fitting",
        "hose",
        "coupling"
    ],
    "wof:name":"Hose Help Inc",
    "wof:placetype":"venue"
},
  "geometry": {"coordinates":[-76.850431,40.254714],"type":"Point"}
}