{
  "type": "Feature",
  "properties": {
    "addr:full":"1157 Municipal Dr Duncansville PA 16635",
    "addr:housenumber":"1157",
    "addr:postcode":"16635",
    "addr:street":"Municipal Dr Duncansville",
    "iso:country":"US",
    "sg:address":"1157 Municipal Dr",
    "sg:city":"Duncansville",
    "sg:classifiers":[
        {
            "category":"Personal",
            "subcategory":"Beauty Salon",
            "type":"Services"
        }
    ],
    "sg:phone":"+1 814 693 8799",
    "sg:postcode":"16635",
    "sg:province":"PA",
    "wof:name":"Shear Designs Hair & Nail Sln",
    "wof:placetype":"venue"
},
  "geometry": {"coordinates":[-78.43149099999999,40.445005],"type":"Point"}
}