{
  "type": "Feature",
  "properties": {
    "iso:country":"US",
    "sg:address":"2580 N Reading Rd",
    "sg:city":"Denver",
    "sg:classifiers":[
        {
            "category":"Health Services",
            "subcategory":"Clinic",
            "type":"Services"
        }
    ],
    "sg:phone":"+1 717 484 0526",
    "sg:postcode":"17517",
    "sg:province":"PA",
    "wof:name":"Ephrata Medical Laboratory",
    "wof:placetype":"venue"
},
  "geometry": {"coordinates":[-76.078682,40.232826],"type":"Point"}
}