{
  "type": "Feature",
  "properties": {
    "addr:full":"3054 Fern Ln Allentown PA 18103",
    "addr:housenumber":"3054",
    "addr:postcode":"18103",
    "addr:street":"Fern Ln",
    "iso:country":"US",
    "sg:address":"3054 Fern Ln",
    "sg:city":"Allentown",
    "sg:classifiers":[
        {
            "category":"Professional",
            "subcategory":"Engineering",
            "type":"Services"
        }
    ],
    "sg:phone":"+1 610 791 2113",
    "sg:postcode":"18103",
    "sg:province":"PA",
    "sg:tags":[
        "consultant",
        "energy",
        "conservation"
    ],
    "wof:name":"Keystone Renewable Energy Solutions",
    "wof:placetype":"venue"
},
  "geometry": {"coordinates":[-75.429754,40.567584],"type":"Point"}
}