{
  "type": "Feature",
  "properties": {
    "addr:full":"175 W College Ave Pleasant Gap PA 16823",
    "addr:housenumber":"175",
    "addr:postcode":"16823",
    "addr:street":"W College Ave Pleasant",
    "iso:country":"US",
    "sg:address":"175 W College Ave",
    "sg:city":"Pleasant Gap",
    "sg:classifiers":[
        {
            "category":"Government",
            "subcategory":"Post Office",
            "type":"Public Place"
        }
    ],
    "sg:phone":"+1 814 359 2927",
    "sg:postcode":"16823",
    "sg:province":"PA",
    "wof:name":"US Post Office",
    "wof:placetype":"venue"
},
  "geometry": {"coordinates":[-77.74950200000001,40.865918],"type":"Point"}
}