{
  "type": "Feature",
  "properties": {
    "addr:full":"1200 Haymaker Rd State College PA 16801",
    "addr:housenumber":"1200",
    "addr:postcode":"16801",
    "addr:street":"Haymaker Rd",
    "iso:country":"US",
    "sg:address":"1200 Haymaker Rd",
    "sg:city":"State College",
    "sg:classifiers":[
        {
            "category":"Organizations",
            "subcategory":"Religious Organization",
            "type":"Services"
        }
    ],
    "sg:phone":"+1   ",
    "sg:postcode":"16801",
    "sg:province":"PA",
    "wof:name":"Central PA Conf Untd Meth Chrc",
    "wof:placetype":"venue"
},
  "geometry": {"coordinates":[-77.825891,40.796325],"type":"Point"}
}