{
  "type": "Feature",
  "properties": {
    "iso:country":"US",
    "sg:address":"5610 Tavern Cir",
    "sg:city":"Macungie",
    "sg:classifiers":[
        {
            "category":"Shopping",
            "subcategory":"Books",
            "type":"Retail Goods"
        }
    ],
    "sg:phone":"+1 610 395 0004",
    "sg:postcode":"18062",
    "sg:province":"PA",
    "sg:tags":[
        "dealer"
    ],
    "wof:name":"Reference Rack II Inc",
    "wof:placetype":"venue"
},
  "geometry": {"coordinates":[-75.55714399999999,40.542007],"type":"Point"}
}