{
  "type": "Feature",
  "properties": {
    "iso:country":"US",
    "sg:address":"427 Alexandra Dr",
    "sg:city":"Norristown",
    "sg:classifiers":[
        {
            "category":"Wholesale",
            "subcategory":"Machinery & Supplies",
            "type":"Manufacturing & Wholesale Goods"
        }
    ],
    "sg:phone":"+1   ",
    "sg:postcode":"19403",
    "sg:province":"PA",
    "sg:tags":[
        "equipment",
        "establishment"
    ],
    "wof:name":"Fire Hydrant Services Inc",
    "wof:placetype":"venue"
},
  "geometry": {"coordinates":[-75.387192,40.151324],"type":"Point"}
}