{
  "type": "Feature",
  "properties": {
    "iso:country":"US",
    "sg:address":"17 N Chester Rd",
    "sg:city":"West Chester",
    "sg:classifiers":[
        {
            "category":"Government",
            "subcategory":"Court House",
            "type":"Public Place"
        }
    ],
    "sg:phone":"+1   ",
    "sg:postcode":"19380",
    "sg:province":"PA",
    "sg:tags":[
        "state"
    ],
    "wof:name":"Superior Court of Pennsylvania",
    "wof:placetype":"venue"
},
  "geometry": {"coordinates":[-75.52369400000001,39.967015],"type":"Point"}
}