{
  "type": "Feature",
  "properties": {
    "addr:full":"440 N 3rd St Reading PA 19601",
    "addr:housenumber":"440",
    "addr:postcode":"19601",
    "addr:street":"N 3Rd St",
    "iso:country":"US",
    "sg:address":"440 N 3rd St",
    "sg:city":"Reading",
    "sg:classifiers":[
        {
            "category":"Wholesale",
            "subcategory":"Hardware",
            "type":"Manufacturing & Wholesale Goods"
        }
    ],
    "sg:phone":"+1   ",
    "sg:postcode":"19601",
    "sg:province":"PA",
    "sg:tags":[
        "plumbing"
    ],
    "wof:name":"Hajoca Corporation",
    "wof:placetype":"venue"
},
  "geometry": {"coordinates":[-75.93150199999999,40.344561],"type":"Point"}
}