{
  "type": "Feature",
  "properties": {
    "iso:country":"US",
    "sg:address":"2 Washington Ln",
    "sg:city":"Coatesville",
    "sg:classifiers":[
        {
            "category":"Bars & Pubs",
            "type":"Food & Drink"
        }
    ],
    "sg:phone":"+1 610 384 8450",
    "sg:postcode":"19320",
    "sg:province":"PA",
    "wof:name":"Landing Zone",
    "wof:placetype":"venue"
},
  "geometry": {"coordinates":[-75.883797,39.970929],"type":"Point"}
}