{
  "type": "Feature",
  "properties": {
    "addr:full":"1919 Chestnut St Philadelphia PA 19103",
    "addr:housenumber":"1919",
    "addr:postcode":"19103",
    "addr:street":"Chestnut St",
    "iso:country":"US",
    "sg:address":"1919 Chestnut St",
    "sg:city":"Philadelphia",
    "sg:classifiers":[
        {
            "category":"Professional",
            "subcategory":"Lawyer & Legal Services",
            "type":"Services"
        }
    ],
    "sg:phone":"+1 215 561 2929",
    "sg:postcode":"19103",
    "sg:province":"PA",
    "wof:name":"Barol Daniel H Atty",
    "wof:placetype":"venue"
},
  "geometry": {"coordinates":[-75.172203,39.952],"type":"Point"}
}