{
  "type": "Feature",
  "properties": {
    "iso:country":"US",
    "sg:address":"9619 Eden Hall Ln",
    "sg:city":"Philadelphia",
    "sg:classifiers":[
        {
            "category":"Restaurant",
            "type":"Food & Drink"
        }
    ],
    "sg:phone":"+1   ",
    "sg:postcode":"19114",
    "sg:province":"PA",
    "sg:tags":[
        "eating"
    ],
    "wof:name":"Valenos Pizza",
    "wof:placetype":"venue"
},
  "geometry": {"coordinates":[-74.98759800000001,40.053615],"type":"Point"}
}