{
  "type": "Feature",
  "properties": {
    "iso:country":"US",
    "sg:address":"208 Oakland Ave",
    "sg:city":"Greensburg",
    "sg:classifiers":[
        {
            "category":"Building & Trades",
            "subcategory":"Cleaning & Sanitation",
            "type":"Services"
        }
    ],
    "sg:phone":"+1 724 832 8186",
    "sg:postcode":"15601",
    "sg:province":"PA",
    "sg:tags":[
        "maintenance"
    ],
    "wof:name":"Butler Did It Cleaning Svc",
    "wof:placetype":"venue"
},
  "geometry": {"coordinates":[-79.550242,40.29867],"type":"Point"}
}