{
  "type": "Feature",
  "properties": {
    "iso:country":"US",
    "sg:address":"18031 Grange Center Rd",
    "sg:city":"Saegertown",
    "sg:classifiers":[
        {
            "category":"Manufacturing",
            "subcategory":"Tools & Machinery",
            "type":"Manufacturing & Wholesale Goods"
        }
    ],
    "sg:phone":"+1 814 763 5832",
    "sg:postcode":"16433",
    "sg:province":"PA",
    "sg:tags":[
        "die",
        "maker"
    ],
    "wof:name":"Lenhart Tool",
    "wof:placetype":"venue"
},
  "geometry": {"coordinates":[-80.191113,41.764573],"type":"Point"}
}