{
  "type": "Feature",
  "properties": {
    "iso:country":"US",
    "sg:address":"701 Fayette St",
    "sg:city":"Conshohocken",
    "sg:classifiers":[
        {
            "category":"Autos & Motor Vehicles",
            "subcategory":"Fuel & Gas Station",
            "type":"Retail Goods"
        }
    ],
    "sg:phone":"+1 610 828 9573",
    "sg:postcode":"19428",
    "sg:province":"PA",
    "sg:tags":[
        "oil"
    ],
    "wof:name":"Conshohocken Exxon Servicenter",
    "wof:placetype":"venue"
},
  "geometry": {"coordinates":[-75.300468,40.079706],"type":"Point"}
}