{
  "type": "Feature",
  "properties": {
    "addr:full":"1335 Prospect Rd Columbia PA 17512",
    "addr:housenumber":"1335",
    "addr:postcode":"17512",
    "addr:street":"Prospect Rd",
    "iso:country":"US",
    "sg:address":"1335 Prospect Rd",
    "sg:city":"Columbia",
    "sg:phone":"+1   ",
    "sg:postcode":"17512",
    "sg:province":"PA",
    "sg:tags":[
        "farm",
        "campground"
    ],
    "wof:name":"Prospect Vly Frm Camp Ground",
    "wof:placetype":"venue"
},
  "geometry": {"coordinates":[-76.45651100000001,40.03063],"type":"Point"}
}