{
  "type": "Feature",
  "properties": {
    "addr:full":"414 Haggerty Rd New Galilee PA 16141",
    "addr:housenumber":"414",
    "addr:postcode":"16141",
    "addr:street":"Haggerty Rd",
    "iso:country":"US",
    "sg:address":"414 Haggerty Rd",
    "sg:city":"New Galilee",
    "sg:classifiers":[
        {
            "category":"Building & Trades",
            "subcategory":"Electrical",
            "type":"Services"
        }
    ],
    "sg:phone":"+1   ",
    "sg:postcode":"16141",
    "sg:province":"PA",
    "sg:tags":[
        "electrical",
        "contractor"
    ],
    "wof:name":"Williams Electric",
    "wof:placetype":"venue"
},
  "geometry": {"coordinates":[-80.431684,40.859041],"type":"Point"}
}