{
  "type": "Feature",
  "properties": {
    "iso:country":"US",
    "sg:address":"6521 Frankford Ave",
    "sg:city":"Philadelphia",
    "sg:classifiers":[
        {
            "category":"Health Services",
            "subcategory":"Doctor",
            "type":"Services"
        }
    ],
    "sg:phone":"+1 215 624 2303",
    "sg:postcode":"19135",
    "sg:province":"PA",
    "sg:tags":[
        "physician",
        "surgeon"
    ],
    "wof:name":"Temple Physicians",
    "wof:placetype":"venue"
},
  "geometry": {"coordinates":[-75.055419,40.029959],"type":"Point"}
}