{
  "type": "Feature",
  "properties": {
    "addr:full":"3220 Tillman Dr Bensalem PA 19020",
    "addr:housenumber":"3220",
    "addr:postcode":"19020",
    "addr:street":"Tillman Dr",
    "iso:country":"US",
    "sg:address":"3220 Tillman Dr",
    "sg:city":"Bensalem",
    "sg:classifiers":[
        {
            "category":"Building & Trades",
            "subcategory":"Cleaning & Sanitation",
            "type":"Services"
        }
    ],
    "sg:phone":"+1 215 639 8191",
    "sg:postcode":"19020",
    "sg:province":"PA",
    "sg:website":"www.healthcareservicesgroup.com",
    "wof:name":"Healthcare Services Group Inc",
    "wof:placetype":"venue"
},
  "geometry": {"coordinates":[-74.96182399999999,40.114834],"type":"Point"}
}