{
  "type": "Feature",
  "properties": {
    "iso:country":"US",
    "sg:address":"1018 W 52nd St",
    "sg:city":"Erie",
    "sg:classifiers":[
        {
            "category":"Wholesale",
            "subcategory":"Machinery & Supplies",
            "type":"Manufacturing & Wholesale Goods"
        }
    ],
    "sg:phone":"+1 814 866 0207",
    "sg:postcode":"16509",
    "sg:province":"PA",
    "sg:tags":[
        "distributor",
        "industrial"
    ],
    "wof:name":"King Tool & Supply",
    "wof:placetype":"venue"
},
  "geometry": {"coordinates":[-80.081198,42.081549],"type":"Point"}
}