{
  "type": "Feature",
  "properties": {
    "addr:full":"2080 Biglerville Rd Gettysburg PA 17325",
    "addr:housenumber":"2080",
    "addr:postcode":"17325",
    "addr:street":"Biglerville Rd",
    "iso:country":"US",
    "sg:address":"2080 Biglerville Rd",
    "sg:city":"Gettysburg",
    "sg:classifiers":[
        {
            "category":"Building & Trades",
            "subcategory":"Construction",
            "type":"Services"
        }
    ],
    "sg:phone":"+1 717 337 2922",
    "sg:postcode":"17325",
    "sg:province":"PA",
    "sg:tags":[
        "contractor"
    ],
    "wof:name":"Glenn Construction",
    "wof:placetype":"venue"
},
  "geometry": {"coordinates":[-77.244748,39.88492],"type":"Point"}
}