{
  "type": "Feature",
  "properties": {
    "iso:country":"US",
    "sg:address":"2354 Beaver Valley Pike",
    "sg:city":"New Providence",
    "sg:classifiers":[
        {
            "category":"Retail",
            "subcategory":"Auto Repair",
            "type":"Services"
        }
    ],
    "sg:phone":"+1 717 786 6396",
    "sg:postcode":"17560",
    "sg:province":"PA",
    "sg:tags":[
        "repairing",
        "automobile"
    ],
    "wof:name":"Affordable Automotive",
    "wof:placetype":"venue"
},
  "geometry": {"coordinates":[-76.18346099999999,39.905456],"type":"Point"}
}