{
  "type": "Feature",
  "properties": {
    "iso:country":"US",
    "sg:address":"1324 Oak St",
    "sg:city":"Lebanon",
    "sg:classifiers":[
        {
            "category":"Insurance",
            "subcategory":"Hazard Insurance",
            "type":"Services"
        }
    ],
    "sg:phone":"+1 717 273 4756",
    "sg:postcode":"17042",
    "sg:province":"PA",
    "wof:name":"Ann S Thompson",
    "wof:placetype":"venue"
},
  "geometry": {"coordinates":[-76.43225099999999,40.332023],"type":"Point"}
}