{
  "type": "Feature",
  "properties": {
    "iso:country":"US",
    "sg:address":"1547 Spring Garden St",
    "sg:city":"Philadelphia",
    "sg:classifiers":[
        {
            "category":"Building & Trades",
            "subcategory":"Locksmith",
            "type":"Services"
        }
    ],
    "sg:phone":"+1 215 717 7873",
    "sg:postcode":"19130",
    "sg:province":"PA",
    "sg:tags":[
        "key"
    ],
    "wof:name":"24 Hour Emergency Locksmith",
    "wof:placetype":"venue"
},
  "geometry": {"coordinates":[-75.16381699999999,39.962945],"type":"Point"}
}