{
  "type": "Feature",
  "properties": {
    "addr:full":"206 6th St Renovo PA 17764",
    "addr:housenumber":"206",
    "addr:postcode":"17764",
    "addr:street":"6Th St",
    "iso:country":"US",
    "sg:address":"206 6th St",
    "sg:city":"Renovo",
    "sg:classifiers":[
        {
            "category":"Shopping",
            "subcategory":"Used Merchandise",
            "type":"Retail Goods"
        }
    ],
    "sg:phone":"+1   ",
    "sg:postcode":"17764",
    "sg:province":"PA",
    "wof:name":"Carols Antiques",
    "wof:placetype":"venue"
},
  "geometry": {"coordinates":[-77.75323400000001,41.325858],"type":"Point"}
}