{
  "type": "Feature",
  "properties": {
    "iso:country":"US",
    "sg:address":"990 Buck Rd",
    "sg:city":"Quarryville",
    "sg:phone":"+1   ",
    "sg:postcode":"17566",
    "sg:province":"PA",
    "sg:tags":[
        "farm",
        "corn",
        "cash",
        "crop",
        "field",
        "grain"
    ],
    "wof:name":"Robert Kauffman",
    "wof:placetype":"venue"
},
  "geometry": {"coordinates":[-76.225002,39.874941],"type":"Point"}
}