{
  "type": "Feature",
  "properties": {
    "iso:country":"US",
    "sg:address":"2033 Jenkintown Rd",
    "sg:city":"Glenside",
    "sg:classifiers":[
        {
            "category":"Building & Trades",
            "subcategory":"Pest Control",
            "type":"Services"
        }
    ],
    "sg:phone":"+1   ",
    "sg:postcode":"19038",
    "sg:province":"PA",
    "wof:name":"Modern Exterminating",
    "wof:placetype":"venue"
},
  "geometry": {"coordinates":[-75.139072,40.103249],"type":"Point"}
}