{
  "type": "Feature",
  "properties": {
    "iso:country":"US",
    "sg:address":"605 Strawberry Sq Third Floor",
    "sg:city":"Harrisburg",
    "sg:classifiers":[
        {
            "category":"Arts & Performance",
            "subcategory":"Arts Center",
            "type":"Entertainment"
        }
    ],
    "sg:phone":"+1 717 238 4111",
    "sg:postcode":"17101",
    "sg:province":"PA",
    "sg:tags":[
        "performing"
    ],
    "sg:website":"www.gamutplays.org",
    "wof:name":"Gamut Theatre",
    "wof:placetype":"venue"
},
  "geometry": {"coordinates":[-76.904479,40.260525],"type":"Point"}
}