{
  "type": "Feature",
  "properties": {
    "iso:country":"US",
    "sg:address":"232 E Lancaster Rd",
    "sg:city":"Harmony",
    "sg:classifiers":[
        {
            "category":"Manufacturing",
            "subcategory":"Rubber & Plastics",
            "type":"Manufacturing & Wholesale Goods"
        }
    ],
    "sg:phone":"+1 724 452 4188",
    "sg:postcode":"16037",
    "sg:province":"PA",
    "sg:tags":[
        "products-manufacturers"
    ],
    "wof:name":"Jm Industries Inc",
    "wof:placetype":"venue"
},
  "geometry": {"coordinates":[-80.102463,40.856185],"type":"Point"}
}