{
  "type": "Feature",
  "properties": {
    "addr:full":"3701 Levy Ln Huntingdon Vly PA 19006",
    "addr:housenumber":"3701",
    "addr:postcode":"19006",
    "addr:street":"Levy Ln",
    "iso:country":"US",
    "sg:address":"3701 Levy Ln",
    "sg:city":"Huntingdon Vly",
    "sg:classifiers":[
        {
            "category":"Professional",
            "subcategory":"Business Services",
            "type":"Services"
        },
        {
            "category":"Wholesale",
            "subcategory":"Durable Goods & Equipment",
            "type":"Manufacturing & Wholesale Goods"
        }
    ],
    "sg:phone":"+1 215 947 4458",
    "sg:postcode":"19006",
    "sg:province":"PA",
    "sg:tags":[
        "representative",
        "manufacturer"
    ],
    "wof:name":"Vantage Sales & Marketing",
    "wof:placetype":"venue"
},
  "geometry": {"coordinates":[-75.02683399999999,40.137114],"type":"Point"}
}