{
  "type": "Feature",
  "properties": {
    "iso:country":"US",
    "sg:address":"Langhorne Square Sho",
    "sg:city":"Levittown",
    "sg:classifiers":[
        {
            "category":"Autos & Motor Vehicles",
            "subcategory":"Auto Supplies",
            "type":"Retail Goods"
        }
    ],
    "sg:phone":"+1 215 945 7700",
    "sg:postcode":"19055",
    "sg:province":"PA",
    "sg:tags":[
        "tire"
    ],
    "wof:name":"Goodyear Commercial Tire and Service Center",
    "wof:placetype":"venue"
},
  "geometry": {"coordinates":[-74.835503,40.147202],"type":"Point"}
}