{
  "type": "Feature",
  "properties": {
    "iso:country":"US",
    "sg:address":"1248 Slight Rd",
    "sg:city":"Warminster",
    "sg:classifiers":[
        {
            "category":"Building & Trades",
            "subcategory":"Construction",
            "type":"Services"
        }
    ],
    "sg:phone":"+1   ",
    "sg:postcode":"18974",
    "sg:province":"PA",
    "sg:tags":[
        "concrete",
        "contractor"
    ],
    "wof:name":"Supreme Seal",
    "wof:placetype":"venue"
},
  "geometry": {"coordinates":[-75.099236,40.227427],"type":"Point"}
}