{
  "type": "Feature",
  "properties": {
    "addr:full":"184 W Olney Ave Philadelphia PA 19120",
    "addr:housenumber":"184",
    "addr:postcode":"19120",
    "addr:street":"W Olney Ave",
    "iso:country":"US",
    "sg:address":"184 W Olney Ave",
    "sg:city":"Philadelphia",
    "sg:classifiers":[
        {
            "category":"Organizations",
            "subcategory":"Membership Organization",
            "type":"Services"
        }
    ],
    "sg:phone":"+1   ",
    "sg:postcode":"19120",
    "sg:province":"PA",
    "wof:name":"New Look Cab Inc",
    "wof:placetype":"venue"
},
  "geometry": {"coordinates":[-75.1254,40.035773],"type":"Point"}
}