{
  "type": "Feature",
  "properties": {
    "iso:country":"US",
    "sg:address":"150 Maple Dr",
    "sg:city":"Wexford",
    "sg:classifiers":[
        {
            "category":"Retail",
            "subcategory":"Funeral Services",
            "type":"Services"
        }
    ],
    "sg:phone":"+1 724 935 2911",
    "sg:postcode":"15090",
    "sg:province":"PA",
    "sg:tags":[
        "cemetery"
    ],
    "wof:name":"Mt Pleasant Cemetery Association",
    "wof:placetype":"venue"
},
  "geometry": {"coordinates":[-80.056099,40.622398],"type":"Point"}
}