{
  "type": "Feature",
  "properties": {
    "iso:country":"US",
    "sg:address":"130 Hillymede Dr",
    "sg:city":"Harrisburg",
    "sg:classifiers":[
        {
            "category":"Building & Trades",
            "subcategory":"Plumbing",
            "type":"Services"
        }
    ],
    "sg:phone":"+1   ",
    "sg:postcode":"17111",
    "sg:province":"PA",
    "sg:tags":[
        "plumbing",
        "air",
        "heating",
        "contractor"
    ],
    "wof:name":"La Marco Heating & AC",
    "wof:placetype":"venue"
},
  "geometry": {"coordinates":[-76.74346199999999,40.303319],"type":"Point"}
}