{
  "type": "Feature",
  "properties": {
    "iso:country":"US",
    "sg:address":"1005 Race St",
    "sg:city":"Philadelphia",
    "sg:classifiers":[
        {
            "category":"Shopping",
            "subcategory":"Beauty & Cosmetics",
            "type":"Retail Goods"
        }
    ],
    "sg:phone":"+1 215 574 1768",
    "sg:postcode":"19103",
    "sg:province":"PA",
    "sg:tags":[
        "supply"
    ],
    "sg:website":"www.931skincare.com",
    "wof:name":"931 Skin Care & Beauty Center",
    "wof:placetype":"venue"
},
  "geometry": {"coordinates":[-75.156311,39.955444],"type":"Point"}
}