{
  "type": "Feature",
  "properties": {
    "iso:country":"US",
    "sg:address":"31 N Lake St",
    "sg:city":"North East",
    "sg:classifiers":[
        {
            "category":"Recreation",
            "type":"Entertainment"
        }
    ],
    "sg:phone":"+1 814 725 5616",
    "sg:postcode":"16428",
    "sg:province":"PA",
    "sg:tags":[
        "carnival"
    ],
    "wof:name":"Nefd Cherry Festival",
    "wof:placetype":"venue"
},
  "geometry": {"coordinates":[-79.833749,42.219032],"type":"Point"}
}