{
  "type": "Feature",
  "properties": {
    "iso:country":"US",
    "sg:address":"3205 Denfield Pl",
    "sg:city":"Philadelphia",
    "sg:classifiers":[
        {
            "category":"Building & Trades",
            "subcategory":"Construction",
            "type":"Services"
        }
    ],
    "sg:phone":"+1   ",
    "sg:postcode":"19145",
    "sg:province":"PA",
    "sg:tags":[
        "contractor"
    ],
    "wof:name":"Sigismondi Cement Contrac",
    "wof:placetype":"venue"
},
  "geometry": {"coordinates":[-75.179233,39.909979],"type":"Point"}
}