{
  "type": "Feature",
  "properties": {
    "addr:full":"57 Church St Montrose PA 18801",
    "addr:housenumber":"57",
    "addr:postcode":"18801",
    "addr:street":"Church St",
    "iso:country":"US",
    "sg:address":"57 Church St",
    "sg:city":"Montrose",
    "sg:classifiers":[
        {
            "category":"Real Estate",
            "subcategory":"Real Estate Agent",
            "type":"Services"
        }
    ],
    "sg:phone":"+1 570 278 0505",
    "sg:postcode":"18801",
    "sg:province":"PA",
    "wof:name":"Coldwell Banker",
    "wof:placetype":"venue"
},
  "geometry": {"coordinates":[-75.87738899999999,41.832409],"type":"Point"}
}