{
  "type": "Feature",
  "properties": {
    "iso:country":"US",
    "sg:address":"285 Bellevue Rd",
    "sg:city":"Pittsburgh",
    "sg:classifiers":[
        {
            "category":"Health Services",
            "subcategory":"Clinic",
            "type":"Services"
        }
    ],
    "sg:phone":"+1   ",
    "sg:postcode":"15229",
    "sg:province":"PA",
    "sg:tags":[
        "home",
        "care"
    ],
    "wof:name":"Dynamic Life Concepts",
    "wof:placetype":"venue"
},
  "geometry": {"coordinates":[-80.03955499999999,40.507095],"type":"Point"}
}