{
  "type": "Feature",
  "properties": {
    "iso:country":"US",
    "sg:address":"346 Stonemill Dr",
    "sg:city":"Elizabethtown",
    "sg:phone":"+1   ",
    "sg:postcode":"17022",
    "sg:province":"PA",
    "sg:tags":[
        "farm",
        "corn",
        "soybean"
    ],
    "wof:name":"Jere Rutt",
    "wof:placetype":"venue"
},
  "geometry": {"coordinates":[-76.605468,40.120208],"type":"Point"}
}