{
  "type": "Feature",
  "properties": {
    "addr:full":"3102 Bridlewood Dr Glen Mills PA 19342",
    "addr:housenumber":"3102",
    "addr:postcode":"19342",
    "addr:street":"Bridlewood Dr",
    "iso:country":"US",
    "sg:address":"3102 Bridlewood Dr",
    "sg:city":"Glen Mills",
    "sg:classifiers":[
        {
            "category":"Professional",
            "subcategory":"Employment Agencies",
            "type":"Services"
        }
    ],
    "sg:phone":"+1   ",
    "sg:postcode":"19342",
    "sg:province":"PA",
    "wof:name":"Executive Market Search",
    "wof:placetype":"venue"
},
  "geometry": {"coordinates":[-75.53696100000001,39.866657],"type":"Point"}
}