{
  "type": "Feature",
  "properties": {
    "addr:full":"258 Exton Square Mall Exton PA 19341",
    "addr:housenumber":"258",
    "addr:postcode":"19341",
    "addr:street":"Exton Square Mall",
    "iso:country":"US",
    "sg:address":"258 Exton Square Mall",
    "sg:city":"Exton",
    "sg:classifiers":[
        {
            "category":"Coffee & Tea",
            "type":"Food & Drink"
        }
    ],
    "sg:menulink":"http://www.allmenus.com/pa/west-whiteland/125158-starbucks-coffee/menu/",
    "sg:phone":"+1 610 524 8620",
    "sg:postcode":"19341",
    "sg:province":"PA",
    "sg:tags":[
        "american"
    ],
    "wof:name":"Starbucks Coffee",
    "wof:placetype":"venue"
},
  "geometry": {"coordinates":[-75.62331,40.030084],"type":"Point"}
}