{
  "type": "Feature",
  "properties": {
    "iso:country":"US",
    "sg:address":"1112 3rd Ave",
    "sg:city":"New Brighton",
    "sg:classifiers":[
        {
            "category":"Organizations",
            "subcategory":"Religious Organization",
            "type":"Services"
        }
    ],
    "sg:phone":"+1 724 843 8750",
    "sg:postcode":"15066",
    "sg:province":"PA",
    "sg:tags":[
        "church"
    ],
    "wof:name":"Shiloh Assembly Ministries",
    "wof:placetype":"venue"
},
  "geometry": {"coordinates":[-80.31074700000001,40.73136],"type":"Point"}
}