{
  "type": "Feature",
  "properties": {
    "addr:full":"86 Duncan Station Rd Mc Keesport PA 15135",
    "addr:housenumber":"86",
    "addr:postcode":"15135",
    "addr:street":"Duncan Station Rd",
    "iso:country":"US",
    "sg:address":"86 Duncan Station Rd",
    "sg:city":"Mc Keesport",
    "sg:classifiers":[
        {
            "category":"Professional",
            "subcategory":"Computer Services",
            "type":"Services"
        }
    ],
    "sg:phone":"+1   ",
    "sg:postcode":"15135",
    "sg:province":"PA",
    "sg:tags":[
        "website",
        "product",
        "sales",
        "entertainment"
    ],
    "wof:name":"Devilschick",
    "wof:placetype":"venue"
},
  "geometry": {"coordinates":[-79.813777,40.290486],"type":"Point"}
}