{
  "type": "Feature",
  "properties": {
    "iso:country":"US",
    "sg:address":"519 Main St",
    "sg:city":"Bethlehem",
    "sg:classifiers":[
        {
            "category":"Shopping",
            "subcategory":"Crafts & Fabrics",
            "type":"Retail Goods"
        }
    ],
    "sg:phone":"+1 610 867 0318",
    "sg:postcode":"18018",
    "sg:province":"PA",
    "sg:tags":[
        "sewing"
    ],
    "wof:name":"Tangled Yarns",
    "wof:placetype":"venue"
},
  "geometry": {"coordinates":[-75.382042,40.621003],"type":"Point"}
}