{
  "type": "Feature",
  "properties": {
    "addr:full":"590 N Gulph Rd King Of Prussia PA 19406",
    "addr:housenumber":"590",
    "addr:postcode":"19406",
    "addr:street":"N Gulph Rd",
    "iso:country":"US",
    "sg:address":"590 N Gulph Rd",
    "sg:city":"King Of Prussia",
    "sg:classifiers":[
        {
            "category":"Professional",
            "subcategory":"Research",
            "type":"Services"
        }
    ],
    "sg:phone":"+1   ",
    "sg:postcode":"19406",
    "sg:province":"PA",
    "wof:name":"Highbeam Resarch  LLC",
    "wof:placetype":"venue"
},
  "geometry": {"coordinates":[-75.41256300000001,40.089778],"type":"Point"}
}