{
  "type": "Feature",
  "properties": {
    "addr:full":"108 N Stratton St Gettysburg PA 17325",
    "addr:housenumber":"108",
    "addr:postcode":"17325",
    "addr:street":"N Stratton St",
    "iso:country":"US",
    "sg:address":"108 N Stratton St",
    "sg:city":"Gettysburg",
    "sg:classifiers":[
        {
            "category":"Government",
            "subcategory":"Office",
            "type":"Public Place"
        }
    ],
    "sg:phone":"+1 717 334 1173",
    "sg:postcode":"17325",
    "sg:province":"PA",
    "sg:tags":[
        "state",
        "resource"
    ],
    "wof:name":"Unemployment Compensation",
    "wof:placetype":"venue"
},
  "geometry": {"coordinates":[-77.228888,39.83228],"type":"Point"}
}