{
  "type": "Feature",
  "properties": {
    "addr:full":"3637 Washington Rd Canonsburg PA 15317",
    "addr:housenumber":"3637",
    "addr:postcode":"15317",
    "addr:street":"Washington Rd",
    "iso:country":"US",
    "sg:address":"3637 Washington Rd",
    "sg:city":"Canonsburg",
    "sg:classifiers":[
        {
            "category":"Arena",
            "subcategory":"Sports Club",
            "type":"Entertainment"
        }
    ],
    "sg:phone":"+1 724 942 3444",
    "sg:postcode":"15317",
    "sg:province":"PA",
    "sg:tags":[
        "martial art"
    ],
    "wof:name":"C S Kim Karate Inc",
    "wof:placetype":"venue"
},
  "geometry": {"coordinates":[-80.126503,40.274101],"type":"Point"}
}