{
  "type": "Feature",
  "properties": {
    "iso:country":"US",
    "sg:address":"14 W Green St",
    "sg:city":"Nanticoke",
    "sg:classifiers":[
        {
            "category":"Retail",
            "subcategory":"Funeral Services",
            "type":"Services"
        }
    ],
    "sg:phone":"+1 570 735 5533",
    "sg:postcode":"18634",
    "sg:province":"PA",
    "sg:tags":[
        "director"
    ],
    "wof:name":"Earl W Lohman Funeral Home",
    "wof:placetype":"venue"
},
  "geometry": {"coordinates":[-76.00440399999999,41.201279],"type":"Point"}
}