{
  "type": "Feature",
  "properties": {
    "addr:full":"3613 Germantown Ave Philadelphia PA 19140",
    "addr:housenumber":"3613",
    "addr:postcode":"19140",
    "addr:street":"Germantown Ave",
    "iso:country":"US",
    "sg:address":"3613 Germantown Ave",
    "sg:city":"Philadelphia",
    "sg:classifiers":[
        {
            "category":"Cinema",
            "subcategory":"Movie Rental",
            "type":"Entertainment"
        }
    ],
    "sg:phone":"+1 215 227 2337",
    "sg:postcode":"19140",
    "sg:province":"PA",
    "sg:tags":[
        "game",
        "video"
    ],
    "wof:name":"Page Tech Wireless",
    "wof:placetype":"venue"
},
  "geometry": {"coordinates":[-75.150398,40.007702],"type":"Point"}
}