{
  "type": "Feature",
  "properties": {
    "addr:full":"290 Corner Ketch Lyndell Rd Downingtown PA 19335",
    "addr:housenumber":"290",
    "addr:postcode":"19335",
    "addr:street":"Corner Ketch Lyndell Rd",
    "iso:country":"US",
    "sg:address":"290 Corner Ketch Lyndell Rd",
    "sg:city":"Downingtown",
    "sg:classifiers":[
        {
            "category":"Autos & Motor Vehicles",
            "subcategory":"Recreational Vehicle Sales",
            "type":"Retail Goods"
        }
    ],
    "sg:phone":"+1   ",
    "sg:postcode":"19335",
    "sg:province":"PA",
    "sg:tags":[
        "repair"
    ],
    "wof:name":"R V Hopewell Center Inc",
    "wof:placetype":"venue"
},
  "geometry": {"coordinates":[-75.750061,40.034232],"type":"Point"}
}