{
  "type": "Feature",
  "properties": {
    "addr:full":"222 S Blakely St Scranton PA 18512",
    "addr:housenumber":"222",
    "addr:postcode":"18512",
    "addr:street":"S Blakely St",
    "iso:country":"US",
    "sg:address":"222 S Blakely St",
    "sg:city":"Scranton",
    "sg:classifiers":[
        {
            "category":"Recreation",
            "type":"Entertainment"
        }
    ],
    "sg:phone":"+1   ",
    "sg:postcode":"18512",
    "sg:province":"PA",
    "sg:tags":[
        "club",
        "membership"
    ],
    "wof:name":"Shalom",
    "wof:placetype":"venue"
},
  "geometry": {"coordinates":[-75.632491,41.419838],"type":"Point"}
}