{
  "type": "Feature",
  "properties": {
    "iso:country":"US",
    "sg:address":"260 Schoolhouse Rd",
    "sg:city":"Middletown",
    "sg:classifiers":[
        {
            "category":"Education",
            "subcategory":"School",
            "type":"Public Place"
        }
    ],
    "sg:phone":"+1 717 944 9462",
    "sg:postcode":"17057",
    "sg:province":"PA",
    "sg:website":"www.ldsd.org",
    "wof:name":"Londenderry Elementary School",
    "wof:placetype":"venue"
},
  "geometry": {"coordinates":[-76.679417,40.190711],"type":"Point"}
}