{
  "type": "Feature",
  "properties": {
    "iso:country":"US",
    "sg:address":"112 Washington Ave",
    "sg:city":"Bridgeville",
    "sg:classifiers":[
        {
            "category":"Retail",
            "subcategory":"Auto Repair",
            "type":"Services"
        }
    ],
    "sg:phone":"+1 412 257 1708",
    "sg:postcode":"15017",
    "sg:province":"PA",
    "wof:name":"Bridgeville Auto Specialists",
    "wof:placetype":"venue"
},
  "geometry": {"coordinates":[-80.11019899999999,40.363499],"type":"Point"}
}