{
  "type": "Feature",
  "properties": {
    "iso:country":"US",
    "sg:address":"119 Dymond Ave",
    "sg:city":"Fayetteville",
    "sg:classifiers":[
        {
            "category":"Wholesale",
            "subcategory":"Vending Machines",
            "type":"Manufacturing & Wholesale Goods"
        }
    ],
    "sg:phone":"+1   ",
    "sg:postcode":"17222",
    "sg:province":"PA",
    "sg:tags":[
        "operator"
    ],
    "wof:name":"Koko Candies",
    "wof:placetype":"venue"
},
  "geometry": {"coordinates":[-77.56334,39.910082],"type":"Point"}
}