{
  "type": "Feature",
  "properties": {
    "iso:country":"US",
    "sg:address":"6 Anchor Dr",
    "sg:city":"Pittsburgh",
    "sg:classifiers":[
        {
            "category":"Restaurant",
            "type":"Food & Drink"
        }
    ],
    "sg:menulink":"http://www.allmenus.com/pa/harmar/5974-primanti-bros/menu/",
    "sg:phone":"+1 412 826 9680",
    "sg:postcode":"15238",
    "sg:province":"PA",
    "sg:tags":[
        "american",
        "sandwich"
    ],
    "wof:name":"Primanti Bros.",
    "wof:placetype":"venue"
},
  "geometry": {"coordinates":[-79.83564,40.539401],"type":"Point"}
}