{
  "type": "Feature",
  "properties": {
    "iso:country":"US",
    "sg:address":"418 Mellon Ave",
    "sg:city":"Baden",
    "sg:classifiers":[
        {
            "category":"Professional",
            "type":"Services"
        }
    ],
    "sg:phone":"+1   ",
    "sg:postcode":"15005",
    "sg:province":"PA",
    "wof:name":"Dennis C Baker",
    "wof:placetype":"venue"
},
  "geometry": {"coordinates":[-80.228146,40.636922],"type":"Point"}
}