{
  "type": "Feature",
  "properties": {
    "addr:full":"380 Twolick Dr Indiana PA 15701",
    "addr:housenumber":"380",
    "addr:postcode":"15701",
    "addr:street":"Twolick Dr",
    "iso:country":"US",
    "sg:address":"380 Twolick Dr",
    "sg:city":"Indiana",
    "sg:classifiers":[
        {
            "category":"Organizations",
            "subcategory":"Religious Organization",
            "type":"Services"
        }
    ],
    "sg:phone":"+1 724 463 2219",
    "sg:postcode":"15701",
    "sg:province":"PA",
    "sg:tags":[
        "clergy"
    ],
    "wof:name":"Ronald L Sexton",
    "wof:placetype":"venue"
},
  "geometry": {"coordinates":[-79.133341,40.614559],"type":"Point"}
}