{
  "type": "Feature",
  "properties": {
    "iso:country":"US",
    "sg:address":"150 E Main St",
    "sg:city":"New Freedom",
    "sg:classifiers":[
        {
            "category":"Social Services",
            "type":"Services"
        }
    ],
    "sg:phone":"+1 717 227 2824",
    "sg:postcode":"17349",
    "sg:province":"PA",
    "sg:tags":[
        "organization",
        "welfare"
    ],
    "wof:name":"Hope",
    "wof:placetype":"venue"
},
  "geometry": {"coordinates":[-76.697294,39.737586],"type":"Point"}
}