{
  "type": "Feature",
  "properties": {
    "addr:full":"517 Church St Hawley PA 18428",
    "addr:housenumber":"517",
    "addr:postcode":"18428",
    "addr:street":"Church St",
    "iso:country":"US",
    "sg:address":"517 Church St",
    "sg:city":"Hawley",
    "sg:classifiers":[
        {
            "category":"Shopping",
            "subcategory":"Florist",
            "type":"Retail Goods"
        }
    ],
    "sg:phone":"+1   ",
    "sg:postcode":"18428",
    "sg:province":"PA",
    "wof:name":"Designs By Joan Marie",
    "wof:placetype":"venue"
},
  "geometry": {"coordinates":[-75.181674,41.47573],"type":"Point"}
}