{
  "type": "Feature",
  "properties": {
    "iso:country":"US",
    "sg:address":"1040 Garey Dr",
    "sg:city":"Yardley",
    "sg:classifiers":[
        {
            "category":"Banks & Credit Unions",
            "subcategory":"Investment Brokerage",
            "type":"Services"
        }
    ],
    "sg:phone":"+1 215 245 2250",
    "sg:postcode":"19067",
    "sg:province":"PA",
    "sg:tags":[
        "advisory",
        "financial"
    ],
    "wof:name":"On Sat Financial Svc",
    "wof:placetype":"venue"
},
  "geometry": {"coordinates":[-74.83889000000001,40.212929],"type":"Point"}
}