{
  "type": "Feature",
  "properties": {
    "iso:country":"US",
    "sg:address":"11 Sycamore Ln",
    "sg:city":"Oley",
    "sg:classifiers":[
        {
            "category":"Farming",
            "subcategory":"Dairy Farm",
            "type":"Manufacturing & Wholesale Goods"
        }
    ],
    "sg:phone":"+1   ",
    "sg:postcode":"19547",
    "sg:province":"PA",
    "wof:name":"Guntz Rusell",
    "wof:placetype":"venue"
},
  "geometry": {"coordinates":[-75.744753,40.386177],"type":"Point"}
}