{
  "type": "Feature",
  "properties": {
    "iso:country":"US",
    "sg:address":"100 Oak St",
    "sg:city":"Irwin",
    "sg:classifiers":[
        {
            "category":"Wholesale",
            "subcategory":"Durable Goods & Equipment",
            "type":"Manufacturing & Wholesale Goods"
        }
    ],
    "sg:phone":"+1 724 864 9282",
    "sg:postcode":"15642",
    "sg:province":"PA",
    "sg:tags":[
        "representative",
        "manufacturer"
    ],
    "wof:name":"Burns Electric Co",
    "wof:placetype":"venue"
},
  "geometry": {"coordinates":[-79.70894,40.3335],"type":"Point"}
}