{
  "type": "Feature",
  "properties": {
    "iso:country":"US",
    "sg:address":"3501 Terrace St",
    "sg:city":"Pittsburgh",
    "sg:classifiers":[
        {
            "category":"Education",
            "subcategory":"College",
            "type":"Public Place"
        }
    ],
    "sg:phone":"+1 412 648 8616",
    "sg:postcode":"15213",
    "sg:province":"PA",
    "sg:tags":[
        "dental",
        "school"
    ],
    "wof:name":"Univ Of Pittsburgh Dentistry",
    "wof:placetype":"venue"
},
  "geometry": {"coordinates":[-79.962192,40.442569],"type":"Point"}
}