{
  "type": "Feature",
  "properties": {
    "iso:country":"US",
    "sg:address":"117 S Main St",
    "sg:city":"Manchester",
    "sg:classifiers":[
        {
            "category":"Restaurant",
            "type":"Food & Drink"
        }
    ],
    "sg:phone":"+1   ",
    "sg:postcode":"17345",
    "sg:province":"PA",
    "sg:tags":[
        "eating"
    ],
    "wof:name":"Scotties Kountry Kitcher",
    "wof:placetype":"venue"
},
  "geometry": {"coordinates":[-76.721898,40.055921],"type":"Point"}
}