{
  "type": "Feature",
  "properties": {
    "iso:country":"US",
    "sg:address":"4917 Old William Penn Hwy",
    "sg:city":"Monroeville",
    "sg:classifiers":[
        {
            "category":"Retail",
            "subcategory":"Animal Services",
            "type":"Services"
        }
    ],
    "sg:phone":"+1   ",
    "sg:postcode":"15146",
    "sg:province":"PA",
    "wof:name":"Wigglesnwags",
    "wof:placetype":"venue"
},
  "geometry": {"coordinates":[-79.70884700000001,40.430381],"type":"Point"}
}