{
  "type": "Feature",
  "properties": {
    "iso:country":"US",
    "sg:address":"132 N 1st St",
    "sg:city":"Lehighton",
    "sg:classifiers":[
        {
            "category":"Organizations",
            "subcategory":"Professional Association",
            "type":"Services"
        }
    ],
    "sg:phone":"+1 484 892 3752",
    "sg:postcode":"18235",
    "sg:province":"PA",
    "sg:tags":[
        "agency",
        "bureau",
        "entertainment"
    ],
    "wof:name":"Affiliated Entertainment Group",
    "wof:placetype":"venue"
},
  "geometry": {"coordinates":[-75.70881900000001,40.835112],"type":"Point"}
}