{
  "type": "Feature",
  "properties": {
    "addr:full":"3430 Rte 764 Duncansville PA 16635",
    "addr:housenumber":"3430",
    "addr:postcode":"16635",
    "addr:street":"Rte 764",
    "iso:country":"US",
    "sg:address":"3430 Rte 764",
    "sg:city":"Duncansville",
    "sg:classifiers":[
        {
            "category":"Professional",
            "type":"Services"
        }
    ],
    "sg:phone":"+1 814 943 6100",
    "sg:postcode":"16635",
    "sg:province":"PA",
    "wof:name":"Setz Of Style",
    "wof:placetype":"venue"
},
  "geometry": {"coordinates":[-78.427142,40.462784],"type":"Point"}
}