{
  "type": "Feature",
  "properties": {
    "addr:full":"1396 Rostraver Rd Belle Vernon PA 15012",
    "addr:housenumber":"1396",
    "addr:postcode":"15012",
    "addr:street":"Rostraver Rd",
    "iso:country":"US",
    "sg:address":"1396 Rostraver Rd",
    "sg:city":"Belle Vernon",
    "sg:classifiers":[
        {
            "category":"Building & Trades",
            "subcategory":"Construction",
            "type":"Services"
        }
    ],
    "sg:phone":"+1   ",
    "sg:postcode":"15012",
    "sg:province":"PA",
    "sg:tags":[
        "commercial",
        "industrial",
        "painting"
    ],
    "wof:name":"DW Custom Painting Inc",
    "wof:placetype":"venue"
},
  "geometry": {"coordinates":[-79.82021899999999,40.16149],"type":"Point"}
}