{
  "type": "Feature",
  "properties": {
    "addr:full":"353 Northampton St Easton PA 18042",
    "addr:housenumber":"353",
    "addr:postcode":"18042",
    "addr:street":"Northampton St",
    "iso:country":"US",
    "sg:address":"353 Northampton St",
    "sg:city":"Easton",
    "sg:classifiers":[
        {
            "category":"Shopping",
            "type":"Retail Goods"
        }
    ],
    "sg:phone":"+1 610 923 7313",
    "sg:postcode":"18042",
    "sg:province":"PA",
    "sg:tags":[
        "cosmetic",
        "perfume"
    ],
    "wof:name":"Paris Perfume",
    "wof:placetype":"venue"
},
  "geometry": {"coordinates":[-75.210545,40.691243],"type":"Point"}
}