{
  "type": "Feature",
  "properties": {
    "iso:country":"US",
    "sg:address":"222 S Washington St",
    "sg:city":"Butler",
    "sg:classifiers":[
        {
            "category":"Professional",
            "subcategory":"Lawyer & Legal Services",
            "type":"Services"
        }
    ],
    "sg:phone":"+1 724 287 2793",
    "sg:postcode":"16001",
    "sg:province":"PA",
    "sg:tags":[
        "attorney"
    ],
    "wof:name":"Art Rauschenber , Attorney",
    "wof:placetype":"venue"
},
  "geometry": {"coordinates":[-79.896958,40.859173],"type":"Point"}
}