{
  "type": "Feature",
  "properties": {
    "addr:full":"316 E Hinckley Ave Ridley Park PA 19078",
    "addr:housenumber":"316",
    "addr:postcode":"19078",
    "addr:street":"E Hinckley Ave;Park",
    "iso:country":"US",
    "sg:address":"316 E Hinckley Ave",
    "sg:city":"Ridley Park",
    "sg:classifiers":[
        {
            "category":"Health Services",
            "subcategory":"Nursing And Care Facility",
            "type":"Services"
        }
    ],
    "sg:phone":"+1   ",
    "sg:postcode":"19078",
    "sg:province":"PA",
    "sg:tags":[
        "skilled"
    ],
    "wof:name":"Ross Manor Nursing Home",
    "wof:placetype":"venue"
},
  "geometry": {"coordinates":[-75.317033,39.882847],"type":"Point"}
}