{
  "type": "Feature",
  "properties": {
    "iso:country":"US",
    "sg:address":"1524 E Wadsworth Ave",
    "sg:city":"Philadelphia",
    "sg:classifiers":[
        {
            "category":"Food & Beverages",
            "subcategory":"Meat & Fish",
            "type":"Retail Goods"
        }
    ],
    "sg:phone":"+1 215 248 5005",
    "sg:postcode":"19150",
    "sg:province":"PA",
    "wof:name":"Sam's Wadsworth Meat Market",
    "wof:placetype":"venue"
},
  "geometry": {"coordinates":[-75.17383100000001,40.079001],"type":"Point"}
}