{
  "type": "Feature",
  "properties": {
    "iso:country":"US",
    "sg:address":"697 E Lincoln Ave",
    "sg:city":"Myerstown",
    "sg:classifiers":[
        {
            "category":"Freight",
            "type":"Transportation"
        }
    ],
    "sg:phone":"+1   ",
    "sg:postcode":"17067",
    "sg:province":"PA",
    "wof:name":"Dss Transportation Inc",
    "wof:placetype":"venue"
},
  "geometry": {"coordinates":[-76.283822,40.38391],"type":"Point"}
}