{
  "type": "Feature",
  "properties": {
    "addr:full":"500 Heidelberg Ave Reading PA 19606",
    "addr:housenumber":"500",
    "addr:postcode":"19606",
    "addr:street":"Heidelberg Ave",
    "iso:country":"US",
    "sg:address":"500 Heidelberg Ave",
    "sg:city":"Reading",
    "sg:classifiers":[
        {
            "category":"Personal",
            "subcategory":"Beauty Salon",
            "type":"Services"
        }
    ],
    "sg:phone":"+1 610 779 4592",
    "sg:postcode":"19606",
    "sg:province":"PA",
    "wof:name":"Nancy Whitcraft Beauty Shop",
    "wof:placetype":"venue"
},
  "geometry": {"coordinates":[-75.865815,40.34309],"type":"Point"}
}