{
  "type": "Feature",
  "properties": {
    "iso:country":"US",
    "sg:address":"410 N Main St",
    "sg:city":"Moscow",
    "sg:classifiers":[
        {
            "category":"Personal",
            "subcategory":"Beauty Salon",
            "type":"Services"
        }
    ],
    "sg:phone":"+1 570 842 9264",
    "sg:postcode":"18444",
    "sg:province":"PA",
    "wof:name":"Cut-Outs Hair Co",
    "wof:placetype":"venue"
},
  "geometry": {"coordinates":[-75.518601,41.338557],"type":"Point"}
}