{
  "type": "Feature",
  "properties": {
    "addr:full":"139 Connie Dr Pittsburgh PA 15214",
    "addr:housenumber":"139",
    "addr:postcode":"15214",
    "addr:street":"Connie Dr",
    "iso:country":"US",
    "sg:address":"139 Connie Dr",
    "sg:city":"Pittsburgh",
    "sg:classifiers":[
        {
            "category":"Manufacturing",
            "subcategory":"Printing",
            "type":"Manufacturing & Wholesale Goods"
        }
    ],
    "sg:phone":"+1   ",
    "sg:postcode":"15214",
    "sg:province":"PA",
    "sg:tags":[
        "broker"
    ],
    "wof:name":"Lejeune Litho and Graphic Svcs",
    "wof:placetype":"venue"
},
  "geometry": {"coordinates":[-80.02730699999999,40.500934],"type":"Point"}
}