{
  "type": "Feature",
  "properties": {
    "addr:full":"1243 Liberty St Franklin PA 16323",
    "addr:housenumber":"1243",
    "addr:postcode":"16323",
    "addr:street":"Liberty St",
    "iso:country":"US",
    "sg:address":"1243 Liberty St",
    "sg:city":"Franklin",
    "sg:classifiers":[
        {
            "category":"Social Services",
            "type":"Services"
        }
    ],
    "sg:phone":"+1 814 437 1996",
    "sg:postcode":"16323",
    "sg:province":"PA",
    "sg:tags":[
        "assault",
        "abuse",
        "sexual",
        "crisis"
    ],
    "wof:name":"Victims Resources Ctr Hotline",
    "wof:placetype":"venue"
},
  "geometry": {"coordinates":[-79.82821800000001,41.397424],"type":"Point"}
}