{
  "type": "Feature",
  "properties": {
    "addr:full":"291 Poplar Ln Mount Wolf PA 17347",
    "addr:housenumber":"291",
    "addr:postcode":"17347",
    "addr:street":"Poplar Ln",
    "iso:country":"US",
    "sg:address":"291 Poplar Ln",
    "sg:city":"Mount Wolf",
    "sg:classifiers":[
        {
            "category":"Building & Trades",
            "subcategory":"Construction",
            "type":"Services"
        }
    ],
    "sg:phone":"+1   ",
    "sg:postcode":"17347",
    "sg:province":"PA",
    "sg:tags":[
        "hanging",
        "contractor"
    ],
    "wof:name":"Painters Handy Services",
    "wof:placetype":"venue"
},
  "geometry": {"coordinates":[-76.69229199999999,40.051127],"type":"Point"}
}