{
  "type": "Feature",
  "properties": {
    "iso:country":"US",
    "sg:address":"3607 Perkiomen Ave",
    "sg:city":"Reading",
    "sg:classifiers":[
        {
            "category":"Shopping",
            "subcategory":"Gifts & Souvenirs",
            "type":"Retail Goods"
        },
        {
            "category":"Home & Garden",
            "subcategory":"Home Furnishings",
            "type":"Retail Goods"
        }
    ],
    "sg:phone":"+1 610 779 7432",
    "sg:postcode":"19606",
    "sg:province":"PA",
    "sg:tags":[
        "shop"
    ],
    "wof:name":"Mariah's Accents For The Home",
    "wof:placetype":"venue"
},
  "geometry": {"coordinates":[-75.874415,40.319108],"type":"Point"}
}