{
  "type": "Feature",
  "properties": {
    "addr:full":"110 W Eagle Rd Havertown PA 19083",
    "addr:housenumber":"110",
    "addr:postcode":"19083",
    "addr:street":"W Eagle Rd",
    "iso:country":"US",
    "sg:address":"110 W Eagle Rd",
    "sg:city":"Havertown",
    "sg:classifiers":[
        {
            "category":"Professional",
            "subcategory":"Accounting & Tax Preparation",
            "type":"Services"
        }
    ],
    "sg:phone":"+1   ",
    "sg:postcode":"19083",
    "sg:province":"PA",
    "wof:name":"Steve Clott",
    "wof:placetype":"venue"
},
  "geometry": {"coordinates":[-75.31429300000001,39.985775],"type":"Point"}
}