{
  "type": "Feature",
  "properties": {
    "addr:full":"1602 University Dr State College PA 16801",
    "addr:housenumber":"1602",
    "addr:postcode":"16801",
    "addr:street":"University Dr",
    "iso:country":"US",
    "sg:address":"1602 University Dr",
    "sg:city":"State College",
    "sg:classifiers":[
        {
            "category":"Retail",
            "subcategory":"Veterinary Services",
            "type":"Services"
        }
    ],
    "sg:phone":"+1 814 231 8387",
    "sg:postcode":"16801",
    "sg:province":"PA",
    "sg:tags":[
        "hospital",
        "animal"
    ],
    "wof:name":"University Drive Veterinary",
    "wof:placetype":"venue"
},
  "geometry": {"coordinates":[-77.837245,40.785403],"type":"Point"}
}