{
  "type": "Feature",
  "properties": {
    "iso:country":"US",
    "sg:address":"169 Bills Rd",
    "sg:city":"Millersburg",
    "sg:classifiers":[
        {
            "category":"Insurance",
            "subcategory":"Insurance Agent",
            "type":"Services"
        }
    ],
    "sg:phone":"+1   ",
    "sg:postcode":"17061",
    "sg:province":"PA",
    "wof:name":"Gary E Klinger",
    "wof:placetype":"venue"
},
  "geometry": {"coordinates":[-76.957104,40.557422],"type":"Point"}
}