{
  "type": "Feature",
  "properties": {
    "iso:country":"US",
    "sg:address":"2019 11th Ave",
    "sg:city":"Altoona",
    "sg:classifiers":[
        {
            "category":"Bars & Pubs",
            "type":"Food & Drink"
        }
    ],
    "sg:phone":"+1 814 943 9317",
    "sg:postcode":"16601",
    "sg:province":"PA",
    "sg:tags":[
        "drinking"
    ],
    "wof:name":"Neighborhood Tavern",
    "wof:placetype":"venue"
},
  "geometry": {"coordinates":[-78.411556,40.509769],"type":"Point"}
}