{
  "type": "Feature",
  "properties": {
    "iso:country":"US",
    "sg:address":"204 S Wood Ave",
    "sg:city":"Easton",
    "sg:classifiers":[
        {
            "category":"Fast Food",
            "type":"Food & Drink"
        },
        {
            "category":"Restaurant",
            "type":"Food & Drink"
        }
    ],
    "sg:phone":"+1 610 258 5597",
    "sg:postcode":"18042",
    "sg:province":"PA",
    "sg:tags":[
        "american",
        "hot",
        "hamburger",
        "dog"
    ],
    "sg:website":"http://www.wendys.com",
    "wof:name":"Wendy's",
    "wof:placetype":"venue"
},
  "geometry": {"coordinates":[-75.250595,40.685733],"type":"Point"}
}