{
  "type": "Feature",
  "properties": {
    "iso:country":"US",
    "sg:address":"22 Jericho Run",
    "sg:city":"Washington Crossing",
    "sg:classifiers":[
        {
            "category":"Organizations",
            "subcategory":"Community Association",
            "type":"Services"
        }
    ],
    "sg:phone":"+1   ",
    "sg:postcode":"18977",
    "sg:province":"PA",
    "wof:name":"Alpha Omicron PI Frat Inc",
    "wof:placetype":"venue"
},
  "geometry": {"coordinates":[-74.899216,40.31106],"type":"Point"}
}