{
  "type": "Feature",
  "properties": {
    "iso:country":"US",
    "sg:address":"347 W Farmersville Rd",
    "sg:city":"Leola",
    "sg:classifiers":[
        {
            "category":"Building & Trades",
            "subcategory":"Construction",
            "type":"Services"
        }
    ],
    "sg:phone":"+1   ",
    "sg:postcode":"17540",
    "sg:province":"PA",
    "sg:tags":[
        "farm",
        "house",
        "dairy"
    ],
    "wof:name":"Roy E Hoover",
    "wof:placetype":"venue"
},
  "geometry": {"coordinates":[-76.191405,40.125285],"type":"Point"}
}