{
  "type": "Feature",
  "properties": {
    "addr:full":"1124 W Turner St Allentown PA 18102",
    "addr:housenumber":"1124",
    "addr:postcode":"18102",
    "addr:street":"W Turner St",
    "iso:country":"US",
    "sg:address":"1124 W Turner St",
    "sg:city":"Allentown",
    "sg:classifiers":[
        {
            "category":"Education",
            "subcategory":"School",
            "type":"Public Place"
        }
    ],
    "sg:phone":"+1 484 765 5460",
    "sg:postcode":"18102",
    "sg:province":"PA",
    "sg:tags":[
        "high",
        "middle",
        "elementary"
    ],
    "wof:name":"Allentown City School District",
    "wof:placetype":"venue"
},
  "geometry": {"coordinates":[-75.48211000000001,40.602384],"type":"Point"}
}