{
  "type": "Feature",
  "properties": {
    "iso:country":"US",
    "sg:address":"161 Kenney Dr",
    "sg:city":"Sewickley",
    "sg:classifiers":[
        {
            "category":"Professional",
            "subcategory":"Computer Services",
            "type":"Services"
        }
    ],
    "sg:phone":"+1 412 741 1776",
    "sg:postcode":"15143",
    "sg:province":"PA",
    "sg:tags":[
        "repair"
    ],
    "sg:website":"computerhousecall.biz",
    "wof:name":"Computer House Call",
    "wof:placetype":"venue"
},
  "geometry": {"coordinates":[-80.20661200000001,40.570815],"type":"Point"}
}