{
  "type": "Feature",
  "properties": {
    "iso:country":"US",
    "sg:address":"6470 Durham Rd",
    "sg:city":"Pipersville",
    "sg:classifiers":[
        {
            "category":"Professional",
            "subcategory":"Management & Consulting",
            "type":"Services"
        }
    ],
    "sg:phone":"+1 215 766 9884",
    "sg:postcode":"18947",
    "sg:province":"PA",
    "sg:tags":[
        "marketing",
        "business",
        "consultant"
    ],
    "sg:website":"http://www.corpcatalyst.com",
    "wof:name":"Catalyst Partners Inc",
    "wof:placetype":"venue"
},
  "geometry": {"coordinates":[-75.13854000000001,40.42107],"type":"Point"}
}