{
  "type": "Feature",
  "properties": {
    "iso:country":"US",
    "sg:address":"345 S 16th St",
    "sg:city":"Lebanon",
    "sg:classifiers":[
        {
            "category":"Professional",
            "subcategory":"Art Services",
            "type":"Services"
        }
    ],
    "sg:phone":"+1   ",
    "sg:postcode":"17042",
    "sg:province":"PA",
    "sg:tags":[
        "commercial",
        "design",
        "paint"
    ],
    "wof:name":"Zidiks Art Studio",
    "wof:placetype":"venue"
},
  "geometry": {"coordinates":[-76.438284,40.331756],"type":"Point"}
}