{
  "type": "Feature",
  "properties": {
    "addr:full":"555 E Wyoming Ave Philadelphia PA 19120",
    "addr:housenumber":"555",
    "addr:postcode":"19120",
    "addr:street":"E Wyoming Ave",
    "iso:country":"US",
    "sg:address":"555 E Wyoming Ave",
    "sg:city":"Philadelphia",
    "sg:classifiers":[
        {
            "category":"Autos & Motor Vehicles",
            "subcategory":"Automobile Sales",
            "type":"Retail Goods"
        }
    ],
    "sg:phone":"+1 267 285 0307",
    "sg:postcode":"19120",
    "sg:province":"PA",
    "sg:tags":[
        "car",
        "dealer"
    ],
    "wof:name":"Miriams Auto Tags",
    "wof:placetype":"venue"
},
  "geometry": {"coordinates":[-75.114169,40.020378],"type":"Point"}
}