{
  "type": "Feature",
  "properties": {
    "iso:country":"US",
    "sg:address":"6919 Bristol Pike",
    "sg:city":"Levittown",
    "sg:classifiers":[
        {
            "category":"Home & Garden",
            "subcategory":"Carpets & Floor Coverings",
            "type":"Retail Goods"
        }
    ],
    "sg:phone":"+1 215 269 8453",
    "sg:postcode":"19057",
    "sg:province":"PA",
    "sg:tags":[
        "tile",
        "material",
        "sale"
    ],
    "sg:website":"http://www.carpetspluscolortile.com/",
    "wof:name":"Color Tile Plus Inc",
    "wof:placetype":"venue"
},
  "geometry": {"coordinates":[-74.837209,40.125949],"type":"Point"}
}