{
  "type": "Feature",
  "properties": {
    "iso:country":"US",
    "sg:address":"115 Honeoye St",
    "sg:city":"Shinglehouse",
    "sg:classifiers":[
        {
            "category":"Education",
            "subcategory":"Special Training",
            "type":"Public Place"
        }
    ],
    "sg:phone":"+1 814 697 6487",
    "sg:postcode":"16748",
    "sg:province":"PA",
    "sg:tags":[
        "program"
    ],
    "wof:name":"Dickenson Mental Health",
    "wof:placetype":"venue"
},
  "geometry": {"coordinates":[-78.18409,41.967349],"type":"Point"}
}