{
  "type": "Feature",
  "properties": {
    "iso:country":"US",
    "sg:address":"1111 Church St",
    "sg:city":"Honesdale",
    "sg:classifiers":[
        {
            "category":"Professional",
            "subcategory":"Accounting & Tax Preparation",
            "type":"Services"
        }
    ],
    "sg:phone":"+1 570 253 5333",
    "sg:postcode":"18431",
    "sg:province":"PA",
    "sg:tags":[
        "accountant"
    ],
    "wof:name":"William Wyatt",
    "wof:placetype":"venue"
},
  "geometry": {"coordinates":[-75.256488,41.576116],"type":"Point"}
}