{
  "type": "Feature",
  "properties": {
    "addr:full":"12 W Locust St Fleetwood PA 19522",
    "addr:housenumber":"12",
    "addr:postcode":"19522",
    "addr:street":"W Locust St",
    "iso:country":"US",
    "sg:address":"12 W Locust St",
    "sg:city":"Fleetwood",
    "sg:phone":"+1 610 944 0988",
    "sg:postcode":"19522",
    "sg:province":"PA",
    "sg:tags":[
        "equipment",
        "commercial",
        "supply"
    ],
    "wof:name":"Sterling Products Div 1 Inc",
    "wof:placetype":"venue"
},
  "geometry": {"coordinates":[-75.818613,40.452185],"type":"Point"}
}