{
  "type": "Feature",
  "properties": {
    "iso:country":"US",
    "sg:address":"628 Columbia Ave",
    "sg:city":"Sinking Spring",
    "sg:classifiers":[
        {
            "category":"Manufacturing",
            "subcategory":"Building Materials",
            "type":"Manufacturing & Wholesale Goods"
        }
    ],
    "sg:phone":"+1 610 927 0144",
    "sg:postcode":"19608",
    "sg:province":"PA",
    "wof:name":"Spring Valley Custom",
    "wof:placetype":"venue"
},
  "geometry": {"coordinates":[-76.023349,40.323244],"type":"Point"}
}