{
  "type": "Feature",
  "properties": {
    "iso:country":"US",
    "sg:address":"303 Lauman Ave",
    "sg:city":"Norristown",
    "sg:classifiers":[
        {
            "category":"Retail",
            "subcategory":"Repair Shop",
            "type":"Services"
        }
    ],
    "sg:phone":"+1 610 539 9555",
    "sg:postcode":"19403",
    "sg:province":"PA",
    "sg:tags":[
        "equipment"
    ],
    "wof:name":"Tom Hood Bonded Locksmith",
    "wof:placetype":"venue"
},
  "geometry": {"coordinates":[-75.402739,40.139204],"type":"Point"}
}