{
  "type": "Feature",
  "properties": {
    "iso:country":"US",
    "sg:address":"1063 Hobbs Ln",
    "sg:city":"Waterford",
    "sg:classifiers":[
        {
            "category":"Organizations",
            "subcategory":"Professional Association",
            "type":"Services"
        }
    ],
    "sg:phone":"+1 814 882 9757",
    "sg:postcode":"16441",
    "sg:province":"PA",
    "sg:tags":[
        "referral",
        "business",
        "contractor"
    ],
    "wof:name":"Hoag",
    "wof:placetype":"venue"
},
  "geometry": {"coordinates":[-80.01960200000001,41.9715],"type":"Point"}
}