{
  "type": "Feature",
  "properties": {
    "iso:country":"US",
    "sg:address":"10001 Ferndale St",
    "sg:city":"Philadelphia",
    "sg:classifiers":[
        {
            "category":"Retail",
            "subcategory":"Self-service Laundry",
            "type":"Services"
        }
    ],
    "sg:phone":"+1 215 676 7438",
    "sg:postcode":"19116",
    "sg:province":"PA",
    "sg:tags":[
        "coin"
    ],
    "wof:name":"Red Lion Laundromat",
    "wof:placetype":"venue"
},
  "geometry": {"coordinates":[-75.033238,40.106282],"type":"Point"}
}