{
  "type": "Feature",
  "properties": {
    "iso:country":"US",
    "sg:address":"90 Rock Ridge Rd",
    "sg:city":"Upper Black Eddy",
    "sg:classifiers":[
        {
            "category":"Manufacturing",
            "subcategory":"Apparel",
            "type":"Manufacturing & Wholesale Goods"
        }
    ],
    "sg:phone":"+1   ",
    "sg:postcode":"18972",
    "sg:province":"PA",
    "sg:tags":[
        "household",
        "furnishing",
        "mfg"
    ],
    "wof:name":"905 Studio",
    "wof:placetype":"venue"
},
  "geometry": {"coordinates":[-75.127439,40.507133],"type":"Point"}
}