{
  "type": "Feature",
  "properties": {
    "iso:country":"US",
    "sg:address":"350 Main St",
    "sg:city":"Harleysville",
    "sg:classifiers":[
        {
            "category":"Professional",
            "subcategory":"Computer Services",
            "type":"Services"
        }
    ],
    "sg:phone":"+1   ",
    "sg:postcode":"19438",
    "sg:province":"PA",
    "sg:tags":[
        "prepackaged",
        "software"
    ],
    "wof:name":"Evok Solutions Corp",
    "wof:placetype":"venue"
},
  "geometry": {"coordinates":[-75.37920099999999,40.273182],"type":"Point"}
}