{
  "type": "Feature",
  "properties": {
    "iso:country":"US",
    "sg:address":"934 W Street Rd",
    "sg:city":"Warminster",
    "sg:classifiers":[
        {
            "category":"Shopping",
            "subcategory":"Pets & Pet Supplies",
            "type":"Retail Goods"
        }
    ],
    "sg:phone":"+1 215 773 9016",
    "sg:postcode":"18974",
    "sg:province":"PA",
    "sg:tags":[
        "training"
    ],
    "sg:website":"www.petsmart.com",
    "wof:name":"Petsmart",
    "wof:placetype":"venue"
},
  "geometry": {"coordinates":[-75.106697,40.210701],"type":"Point"}
}