{
  "type": "Feature",
  "properties": {
    "iso:country":"US",
    "sg:address":"528 N New St",
    "sg:city":"Bethlehem",
    "sg:classifiers":[
        {
            "category":"Professional",
            "subcategory":"Engineering",
            "type":"Services"
        }
    ],
    "sg:phone":"+1 610 758 9601",
    "sg:postcode":"18018",
    "sg:province":"PA",
    "sg:tags":[
        "engineer"
    ],
    "sg:website":"www.bearingspecialists.com",
    "wof:name":"J V Poplawski & Associates",
    "wof:placetype":"venue"
},
  "geometry": {"coordinates":[-75.37848700000001,40.620703],"type":"Point"}
}