{
  "type": "Feature",
  "properties": {
    "iso:country":"US",
    "sg:address":"808 State Rte 168",
    "sg:city":"Hookstown",
    "sg:classifiers":[
        {
            "category":"Freight",
            "type":"Transportation"
        }
    ],
    "sg:phone":"+1 724 643 0252",
    "sg:postcode":"15050",
    "sg:province":"PA",
    "sg:tags":[
        "commercial",
        "storage"
    ],
    "wof:name":"Secure Self Storage",
    "wof:placetype":"venue"
},
  "geometry": {"coordinates":[-80.448753,40.603448],"type":"Point"}
}