{
  "type": "Feature",
  "properties": {
    "addr:full":"1377 W Chester Rd West Chester PA 19382",
    "addr:housenumber":"1377",
    "addr:postcode":"19382",
    "addr:street":"W Chester Rd",
    "iso:country":"US",
    "sg:address":"1377 W Chester Rd",
    "sg:city":"West Chester",
    "sg:classifiers":[
        {
            "category":"Shopping",
            "subcategory":"Clothing, Apparel, & Fashions",
            "type":"Retail Goods"
        }
    ],
    "sg:phone":"+1   ",
    "sg:postcode":"19382",
    "sg:province":"PA",
    "wof:name":"Amicci Boutique",
    "wof:placetype":"venue"
},
  "geometry": {"coordinates":[-75.54733,39.91124],"type":"Point"}
}