{
  "type": "Feature",
  "properties": {
    "addr:full":"68 Madison Ave Bala Cynwyd PA 19004",
    "addr:housenumber":"68",
    "addr:postcode":"19004",
    "addr:street":"Madison Ave",
    "iso:country":"US",
    "sg:address":"68 Madison Ave",
    "sg:city":"Bala Cynwyd",
    "sg:classifiers":[
        {
            "category":"Building & Trades",
            "subcategory":"Construction",
            "type":"Services"
        }
    ],
    "sg:phone":"+1   ",
    "sg:postcode":"19004",
    "sg:province":"PA",
    "sg:tags":[
        "house"
    ],
    "wof:name":"Peta Frank Extrior Renovation",
    "wof:placetype":"venue"
},
  "geometry": {"coordinates":[-75.238108,40.023128],"type":"Point"}
}