{
  "type": "Feature",
  "properties": {
    "iso:country":"US",
    "sg:address":"7 Mill St",
    "sg:city":"Mt Holly Springs",
    "sg:classifiers":[
        {
            "category":"Freight",
            "type":"Transportation"
        }
    ],
    "sg:phone":"+1 717 486 7780",
    "sg:postcode":"17065",
    "sg:province":"PA",
    "sg:tags":[
        "commercial",
        "storage",
        "general"
    ],
    "wof:name":"Larry's Storage",
    "wof:placetype":"venue"
},
  "geometry": {"coordinates":[-77.18972599999999,40.121581],"type":"Point"}
}