{
  "type": "Feature",
  "properties": {
    "iso:country":"US",
    "sg:address":"316 W Trenton Ave",
    "sg:city":"Morrisville",
    "sg:classifiers":[
        {
            "category":"Health Services",
            "subcategory":"Chiropractor",
            "type":"Services"
        }
    ],
    "sg:phone":"+1   ",
    "sg:postcode":"19067",
    "sg:province":"PA",
    "wof:name":"Gina Genin DC",
    "wof:placetype":"venue"
},
  "geometry": {"coordinates":[-74.79326500000001,40.211879],"type":"Point"}
}