{
  "type": "Feature",
  "properties": {
    "addr:full":"811 Grand Manor Dr Wrightsville PA 17368",
    "addr:housenumber":"811",
    "addr:postcode":"17368",
    "addr:street":"Grand Manor Dr",
    "iso:country":"US",
    "sg:address":"811 Grand Manor Dr",
    "sg:city":"Wrightsville",
    "sg:classifiers":[
        {
            "category":"Wholesale",
            "subcategory":"Non-durable Goods",
            "type":"Manufacturing & Wholesale Goods"
        }
    ],
    "sg:phone":"+1 717 252 1695",
    "sg:postcode":"17368",
    "sg:province":"PA",
    "sg:tags":[
        "merchandise-wholesale"
    ],
    "wof:name":"First Capital Trading Company",
    "wof:placetype":"venue"
},
  "geometry": {"coordinates":[-76.556084,40.036951],"type":"Point"}
}