{
  "type": "Feature",
  "properties": {
    "iso:country":"US",
    "sg:address":"425 S New Middletown Rd",
    "sg:city":"Media",
    "sg:classifiers":[
        {
            "category":"Government",
            "subcategory":"Fire Station",
            "type":"Public Place"
        }
    ],
    "sg:phone":"+1 610 566 0723",
    "sg:postcode":"19063",
    "sg:province":"PA",
    "sg:tags":[
        "department"
    ],
    "wof:name":"Middletown Fire Co",
    "wof:placetype":"venue"
},
  "geometry": {"coordinates":[-75.406075,39.896393],"type":"Point"}
}