{
  "type": "Feature",
  "properties": {
    "iso:country":"US",
    "sg:address":"680 Andersen Dr",
    "sg:city":"Pittsburgh",
    "sg:classifiers":[
        {
            "category":"Real Estate",
            "subcategory":"Real Estate Services",
            "type":"Services"
        }
    ],
    "sg:phone":"+1 412 921 8900",
    "sg:postcode":"15220",
    "sg:province":"PA",
    "sg:tags":[
        "company",
        "abstract",
        "title"
    ],
    "wof:name":"ATI Abstract Company",
    "wof:placetype":"venue"
},
  "geometry": {"coordinates":[-80.062567,40.421006],"type":"Point"}
}