{
  "type": "Feature",
  "properties": {
    "iso:country":"US",
    "sg:address":"7676 Industrial Blvd",
    "sg:city":"Allentown",
    "sg:classifiers":[
        {
            "category":"Utilities",
            "subcategory":"Water",
            "type":"Services"
        }
    ],
    "sg:phone":"+1   ",
    "sg:postcode":"18106",
    "sg:province":"PA",
    "sg:tags":[
        "waste",
        "facility"
    ],
    "wof:name":"Operations Management Intl Inc",
    "wof:placetype":"venue"
},
  "geometry": {"coordinates":[-75.612623,40.565402],"type":"Point"}
}