{
  "type": "Feature",
  "properties": {
    "iso:country":"US",
    "sg:address":"140 Jarod Dr",
    "sg:city":"Coraopolis",
    "sg:classifiers":[
        {
            "category":"Wholesale",
            "subcategory":"Sporting Goods",
            "type":"Manufacturing & Wholesale Goods"
        }
    ],
    "sg:phone":"+1   ",
    "sg:postcode":"15108",
    "sg:province":"PA",
    "wof:name":"Representative For Kelly Sales",
    "wof:placetype":"venue"
},
  "geometry": {"coordinates":[-80.197553,40.52868],"type":"Point"}
}