{
  "type": "Feature",
  "properties": {
    "addr:full":"23 Centre Ave Topton PA 19562",
    "addr:housenumber":"23",
    "addr:postcode":"19562",
    "addr:street":"Centre Ave",
    "iso:country":"US",
    "sg:address":"23 Centre Ave",
    "sg:city":"Topton",
    "sg:classifiers":[
        {
            "category":"Health Services",
            "subcategory":"Chiropractor",
            "type":"Services"
        }
    ],
    "sg:phone":"+1 610 682 4607",
    "sg:postcode":"19562",
    "sg:province":"PA",
    "wof:name":"Topton Chiropractic Ctr",
    "wof:placetype":"venue"
},
  "geometry": {"coordinates":[-75.699815,40.504551],"type":"Point"}
}