{
  "type": "Feature",
  "properties": {
    "addr:full":"999 N 5th St Philadelphia PA 19123",
    "addr:housenumber":"999",
    "addr:postcode":"19123",
    "addr:street":"N 5Th St",
    "iso:country":"US",
    "sg:address":"999 N 5th St",
    "sg:city":"Philadelphia",
    "sg:classifiers":[
        {
            "category":"Landmark",
            "subcategory":"Monument",
            "type":"Public Place"
        }
    ],
    "sg:phone":"+1 215 333 1222",
    "sg:postcode":"19123",
    "sg:province":"PA",
    "sg:website":"http://www.wertheimermonuments.com",
    "wof:name":"Liberty Monument Company",
    "wof:placetype":"venue"
},
  "geometry": {"coordinates":[-75.14532699999999,39.968994],"type":"Point"}
}