{
  "type": "Feature",
  "properties": {
    "addr:full":"9800 Ashton Rd Philadelphia PA 19114",
    "addr:housenumber":"9800",
    "addr:postcode":"19114",
    "addr:street":"Ashton Rd",
    "iso:country":"US",
    "sg:address":"9800 Ashton Rd",
    "sg:city":"Philadelphia",
    "sg:classifiers":[
        {
            "category":"Professional",
            "type":"Services"
        }
    ],
    "sg:phone":"+1 215 464 4030",
    "sg:postcode":"19114",
    "sg:province":"PA",
    "sg:tags":[
        "establishment"
    ],
    "wof:name":"Chopper Six",
    "wof:placetype":"venue"
},
  "geometry": {"coordinates":[-75.012163,40.072969],"type":"Point"}
}