{
  "type": "Feature",
  "properties": {
    "iso:country":"US",
    "sg:address":"191 Edgewater Dr",
    "sg:city":"Monaca",
    "sg:classifiers":[
        {
            "category":"Building & Trades",
            "subcategory":"Construction",
            "type":"Services"
        }
    ],
    "sg:phone":"+1   ",
    "sg:postcode":"15061",
    "sg:province":"PA",
    "sg:tags":[
        "carpentry",
        "contractor"
    ],
    "wof:name":"John Alvin Elias Carpenter",
    "wof:placetype":"venue"
},
  "geometry": {"coordinates":[-80.30014,40.66812],"type":"Point"}
}