{
  "type": "Feature",
  "properties": {
    "iso:country":"US",
    "sg:address":"1340 Justus Blvd",
    "sg:city":"Clarks Summit",
    "sg:classifiers":[
        {
            "category":"Retail",
            "subcategory":"Auto Repair",
            "type":"Services"
        }
    ],
    "sg:phone":"+1 570 586 8825",
    "sg:postcode":"18411",
    "sg:province":"PA",
    "sg:tags":[
        "general"
    ],
    "wof:name":"Von Storch Repairs",
    "wof:placetype":"venue"
},
  "geometry": {"coordinates":[-75.641398,41.505423],"type":"Point"}
}