{
  "type": "Feature",
  "properties": {
    "iso:country":"US",
    "sg:address":"93 Brooklyn St",
    "sg:city":"Carbondale",
    "sg:classifiers":[
        {
            "category":"Manufacturing",
            "subcategory":"Paper Products",
            "type":"Manufacturing & Wholesale Goods"
        }
    ],
    "sg:phone":"+1 570 282 2900",
    "sg:postcode":"18407",
    "sg:province":"PA",
    "sg:tags":[
        "tag"
    ],
    "wof:name":"Northeast Pack & Send",
    "wof:placetype":"venue"
},
  "geometry": {"coordinates":[-75.51428199999999,41.566356],"type":"Point"}
}