{
  "type": "Feature",
  "properties": {
    "addr:full":"407 Schoolhouse Rd Sellersville PA 18960",
    "addr:housenumber":"407",
    "addr:postcode":"18960",
    "addr:street":"Schoolhouse Rd",
    "iso:country":"US",
    "sg:address":"407 Schoolhouse Rd",
    "sg:city":"Sellersville",
    "sg:classifiers":[
        {
            "category":"Health Services",
            "subcategory":"Doctor",
            "type":"Services"
        }
    ],
    "sg:phone":"+1 215 723 2145",
    "sg:postcode":"18960",
    "sg:province":"PA",
    "wof:name":"Kratz Vernon H Physician",
    "wof:placetype":"venue"
},
  "geometry": {"coordinates":[-75.29084899999999,40.33416],"type":"Point"}
}