{
  "type": "Feature",
  "properties": {
    "iso:country":"US",
    "sg:address":"328 Budfield St",
    "sg:city":"Johnstown",
    "sg:classifiers":[
        {
            "category":"Social Services",
            "subcategory":"Child Care",
            "type":"Services"
        }
    ],
    "sg:phone":"+1   ",
    "sg:postcode":"15904",
    "sg:province":"PA",
    "sg:tags":[
        "day"
    ],
    "wof:name":"Day Dreams Day Care",
    "wof:placetype":"venue"
},
  "geometry": {"coordinates":[-78.847354,40.271036],"type":"Point"}
}