{
  "type": "Feature",
  "properties": {
    "iso:country":"US",
    "sg:address":"1509 Franklin Rd",
    "sg:city":"Jackson Center",
    "sg:classifiers":[
        {
            "category":"Building & Trades",
            "subcategory":"Landscaping Services",
            "type":"Services"
        }
    ],
    "sg:phone":"+1   ",
    "sg:postcode":"16133",
    "sg:province":"PA",
    "sg:tags":[
        "landscape"
    ],
    "wof:name":"John S Schiestle",
    "wof:placetype":"venue"
},
  "geometry": {"coordinates":[-80.125578,41.283316],"type":"Point"}
}