{
  "type": "Feature",
  "properties": {
    "addr:full":"2227 Pine St Philadelphia PA 19103",
    "addr:housenumber":"2227",
    "addr:postcode":"19103",
    "addr:street":"Pine St",
    "iso:country":"US",
    "sg:address":"2227 Pine St",
    "sg:city":"Philadelphia",
    "sg:classifiers":[
        {
            "category":"Building & Trades",
            "subcategory":"Locksmith",
            "type":"Services"
        }
    ],
    "sg:phone":"+1 267 702 1207",
    "sg:postcode":"19103",
    "sg:province":"PA",
    "sg:tags":[
        "key"
    ],
    "wof:name":"Anytime Anywhere Emergency Locksmith",
    "wof:placetype":"venue"
},
  "geometry": {"coordinates":[-75.178754,39.947387],"type":"Point"}
}