{
  "type": "Feature",
  "properties": {
    "addr:full":"351 Kennedy Blvd Pittston PA 18640",
    "addr:housenumber":"351",
    "addr:postcode":"18640",
    "addr:street":"Kennedy Blvd",
    "iso:country":"US",
    "sg:address":"351 Kennedy Blvd",
    "sg:city":"Pittston",
    "sg:classifiers":[
        {
            "category":"Shopping",
            "subcategory":"Pharmacy",
            "type":"Retail Goods"
        }
    ],
    "sg:phone":"+1 570 883 7846",
    "sg:postcode":"18640",
    "sg:province":"PA",
    "wof:name":"CVS Pharmacy",
    "wof:placetype":"venue"
},
  "geometry": {"coordinates":[-75.792914,41.321387],"type":"Point"}
}