{
  "type": "Feature",
  "properties": {
    "iso:country":"US",
    "sg:address":"801 Ostrum St Ste 1",
    "sg:city":"Bethlehem",
    "sg:classifiers":[
        {
            "category":"Professional",
            "subcategory":"Business Services",
            "type":"Services"
        }
    ],
    "sg:phone":"+1 610 954 4210",
    "sg:postcode":"18015",
    "sg:province":"PA",
    "sg:tags":[
        "medical",
        "administration"
    ],
    "wof:name":"Homestar Infusion Services",
    "wof:placetype":"venue"
},
  "geometry": {"coordinates":[-75.392601,40.608601],"type":"Point"}
}