{
  "type": "Feature",
  "properties": {
    "iso:country":"US",
    "sg:address":"722 Chestnut St",
    "sg:city":"Philadelphia",
    "sg:classifiers":[
        {
            "category":"Professional",
            "subcategory":"Art Services",
            "type":"Services"
        }
    ],
    "sg:phone":"+1 215 629 1685",
    "sg:postcode":"19106",
    "sg:province":"PA",
    "sg:tags":[
        "photographer"
    ],
    "wof:name":"Michael Weiss Photography",
    "wof:placetype":"venue"
},
  "geometry": {"coordinates":[-75.153657,39.949497],"type":"Point"}
}