{
  "type": "Feature",
  "properties": {
    "iso:country":"US",
    "sg:address":"2861 Main St",
    "sg:city":"Morgantown",
    "sg:classifiers":[
        {
            "category":"Shopping",
            "subcategory":"Gifts & Souvenirs",
            "type":"Retail Goods"
        }
    ],
    "sg:phone":"+1   ",
    "sg:postcode":"19543",
    "sg:province":"PA",
    "wof:name":"Al McCoy Sports Cards",
    "wof:placetype":"venue"
},
  "geometry": {"coordinates":[-75.900221,40.152453],"type":"Point"}
}