{
  "type": "Feature",
  "properties": {
    "addr:full":"2473 N Center Ave Somerset PA 15501",
    "addr:housenumber":"2473",
    "addr:postcode":"15501",
    "addr:street":"N Center Ave",
    "iso:country":"US",
    "sg:address":"2473 N Center Ave",
    "sg:city":"Somerset",
    "sg:classifiers":[
        {
            "category":"Retail",
            "subcategory":"Auto Repair",
            "type":"Services"
        }
    ],
    "sg:phone":"+1 814 443 2418",
    "sg:postcode":"15501",
    "sg:province":"PA",
    "sg:tags":[
        "engine",
        "automotive",
        "parts",
        "rebuilds"
    ],
    "sg:website":"www.rhodesperf.com",
    "wof:name":"Rhodes Performance Machine",
    "wof:placetype":"venue"
},
  "geometry": {"coordinates":[-79.075592,40.065277],"type":"Point"}
}