{
  "type": "Feature",
  "properties": {
    "iso:country":"US",
    "sg:address":"2799 E Beersville Rd",
    "sg:city":"Bath",
    "sg:classifiers":[
        {
            "category":"Building & Trades",
            "subcategory":"Plumbing",
            "type":"Services"
        }
    ],
    "sg:phone":"+1 610 837 0432",
    "sg:postcode":"18014",
    "sg:province":"PA",
    "sg:tags":[
        "plumbing",
        "contractor",
        "heating",
        "conditioning",
        "air"
    ],
    "wof:name":"Yelsits Plumbing & Heating Inc",
    "wof:placetype":"venue"
},
  "geometry": {"coordinates":[-75.418971,40.762799],"type":"Point"}
}