{
  "type": "Feature",
  "properties": {
    "iso:country":"US",
    "sg:address":"121 Rovenolt Dr",
    "sg:city":"Watsontown",
    "sg:classifiers":[
        {
            "category":"Shopping",
            "subcategory":"Pets & Pet Supplies",
            "type":"Retail Goods"
        },
        {
            "category":"Retail",
            "subcategory":"Veterinary Services",
            "type":"Services"
        }
    ],
    "sg:phone":"+1 570 649 6385",
    "sg:postcode":"17777",
    "sg:province":"PA",
    "sg:tags":[
        "specialty"
    ],
    "wof:name":"Paws Itively Obedient Dog Trai",
    "wof:placetype":"venue"
},
  "geometry": {"coordinates":[-76.805379,41.077732],"type":"Point"}
}