{
  "type": "Feature",
  "properties": {
    "addr:full":"5078 Sardis Rd New Kensington PA 15068",
    "addr:housenumber":"5078",
    "addr:postcode":"15068",
    "addr:street":"Sardis Rd",
    "iso:country":"US",
    "sg:address":"5078 Sardis Rd",
    "sg:city":"New Kensington",
    "sg:classifiers":[
        {
            "category":"Professional",
            "subcategory":"Business Services",
            "type":"Services"
        }
    ],
    "sg:phone":"+1 724 335 8681",
    "sg:postcode":"15068",
    "sg:province":"PA",
    "sg:tags":[
        "paper",
        "lamination"
    ],
    "wof:name":"Looking Ahead Laminating",
    "wof:placetype":"venue"
},
  "geometry": {"coordinates":[-79.753244,40.523969],"type":"Point"}
}