{
  "type": "Feature",
  "properties": {
    "iso:country":"US",
    "sg:address":"607 Market St",
    "sg:city":"Zelienople",
    "sg:classifiers":[
        {
            "category":"Government",
            "subcategory":"Office",
            "type":"Public Place"
        }
    ],
    "sg:phone":"+1 724 452 5501",
    "sg:postcode":"16063",
    "sg:province":"PA",
    "wof:name":"Western Butler County Auth",
    "wof:placetype":"venue"
},
  "geometry": {"coordinates":[-80.146872,40.789516],"type":"Point"}
}