{
  "type": "Feature",
  "properties": {
    "addr:full":"128 Fayette St Conshohocken PA 19428",
    "addr:housenumber":"128",
    "addr:postcode":"19428",
    "addr:street":"Fayette St",
    "iso:country":"US",
    "sg:address":"128 Fayette St",
    "sg:city":"Conshohocken",
    "sg:classifiers":[
        {
            "category":"Home & Garden",
            "subcategory":"Furniture",
            "type":"Retail Goods"
        }
    ],
    "sg:phone":"+1 610 828 7990",
    "sg:postcode":"19428",
    "sg:province":"PA",
    "wof:name":"Light Parker Kids",
    "wof:placetype":"venue"
},
  "geometry": {"coordinates":[-75.30571500000001,40.074523],"type":"Point"}
}