{
  "type": "Feature",
  "properties": {
    "iso:country":"US",
    "sg:address":"410 1st Ave",
    "sg:city":"Pittsburgh",
    "sg:classifiers":[
        {
            "category":"Professional",
            "type":"Services"
        }
    ],
    "sg:phone":"+1 412 922 1400",
    "sg:postcode":"15219",
    "sg:province":"PA",
    "sg:tags":[
        "establishment"
    ],
    "wof:name":"Us Data Capture Pittsburgh",
    "wof:placetype":"venue"
},
  "geometry": {"coordinates":[-80.000034,40.436981],"type":"Point"}
}