{
  "type": "Feature",
  "properties": {
    "iso:country":"US",
    "sg:address":"1645 Merchant St",
    "sg:city":"Ambridge",
    "sg:classifiers":[
        {
            "category":"Health Services",
            "subcategory":"Doctor",
            "type":"Services"
        }
    ],
    "sg:phone":"+1 724 266 1224",
    "sg:postcode":"15003",
    "sg:province":"PA",
    "sg:tags":[
        "dentist"
    ],
    "wof:name":"Robert G Norkus DMD",
    "wof:placetype":"venue"
},
  "geometry": {"coordinates":[-80.230754,40.598685],"type":"Point"}
}