{
  "type": "Feature",
  "properties": {
    "addr:full":"3014 Pleasant Valley Blvd Altoona PA 16602",
    "addr:housenumber":"3014",
    "addr:postcode":"16602",
    "addr:street":"Pleasant Valley Blvd",
    "iso:country":"US",
    "sg:address":"3014 Pleasant Valley Blvd",
    "sg:city":"Altoona",
    "sg:classifiers":[
        {
            "category":"Restaurant",
            "type":"Food & Drink"
        }
    ],
    "sg:menulink":"http://www.allmenus.com/pa/logan/64590-papa-johns-pizza/menu/",
    "sg:phone":"+1 814 944 7171",
    "sg:postcode":"16602",
    "sg:province":"PA",
    "sg:tags":[
        "american",
        "pizza"
    ],
    "wof:name":"Papa John's Pizza",
    "wof:placetype":"venue"
},
  "geometry": {"coordinates":[-78.39914899999999,40.487677],"type":"Point"}
}