{
  "type": "Feature",
  "properties": {
    "iso:country":"US",
    "sg:address":"4535 Veman Ave",
    "sg:city":"Pittsburgh",
    "sg:classifiers":[
        {
            "category":"Shopping",
            "subcategory":"Hobbies, Toys, & Games",
            "type":"Retail Goods"
        }
    ],
    "sg:phone":"+1   ",
    "sg:postcode":"15227",
    "sg:province":"PA",
    "wof:name":"Kelldon Co",
    "wof:placetype":"venue"
},
  "geometry": {"coordinates":[-79.98017,40.358276],"type":"Point"}
}