{
  "type": "Feature",
  "properties": {
    "iso:country":"US",
    "sg:address":"721 Skippack Pike Ste 1",
    "sg:city":"Blue Bell",
    "sg:classifiers":[
        {
            "category":"Banks & Credit Unions",
            "subcategory":"Bank",
            "type":"Services"
        }
    ],
    "sg:phone":"+1 215 654 6860",
    "sg:postcode":"19422",
    "sg:province":"PA",
    "wof:name":"Stonebridge Bank",
    "wof:placetype":"venue"
},
  "geometry": {"coordinates":[-75.269739,40.154727],"type":"Point"}
}