{
  "type": "Feature",
  "properties": {
    "iso:country":"US",
    "sg:address":"7820 Nixon St",
    "sg:city":"Philadelphia",
    "sg:classifiers":[
        {
            "category":"Professional",
            "type":"Services"
        }
    ],
    "sg:phone":"+1   ",
    "sg:postcode":"19128",
    "sg:province":"PA",
    "wof:name":"Linda Delmonte",
    "wof:placetype":"venue"
},
  "geometry": {"coordinates":[-75.252246,40.046867],"type":"Point"}
}