{
  "type": "Feature",
  "properties": {
    "iso:country":"US",
    "sg:address":"351 E Lancaster Ave",
    "sg:city":"Downingtown",
    "sg:classifiers":[
        {
            "category":"Social Services",
            "type":"Services"
        }
    ],
    "sg:phone":"+1 610 873 1280",
    "sg:postcode":"19335",
    "sg:province":"PA",
    "wof:name":"Counseling Network",
    "wof:placetype":"venue"
},
  "geometry": {"coordinates":[-75.69863100000001,40.008504],"type":"Point"}
}