{
  "type": "Feature",
  "properties": {
    "iso:country":"US",
    "sg:address":"5428 Baltimore Ave",
    "sg:city":"Philadelphia",
    "sg:classifiers":[
        {
            "category":"Social Services",
            "subcategory":"Child Care",
            "type":"Services"
        }
    ],
    "sg:phone":"+1   ",
    "sg:postcode":"19143",
    "sg:province":"PA",
    "sg:tags":[
        "day"
    ],
    "wof:name":"Dee Dee After School",
    "wof:placetype":"venue"
},
  "geometry": {"coordinates":[-75.23307,39.947439],"type":"Point"}
}