{
  "type": "Feature",
  "properties": {
    "iso:country":"US",
    "sg:address":"90 S Commerce Way",
    "sg:city":"Bethlehem",
    "sg:classifiers":[
        {
            "category":"Manufacturing",
            "subcategory":"Tools & Machinery",
            "type":"Manufacturing & Wholesale Goods"
        }
    ],
    "sg:phone":"+1 610 758 9680",
    "sg:postcode":"18017",
    "sg:province":"PA",
    "sg:tags":[
        "equipment",
        "hydraulic"
    ],
    "sg:website":"www.digitalpressusa.com",
    "wof:name":"Digital Press Inc",
    "wof:placetype":"venue"
},
  "geometry": {"coordinates":[-75.382301,40.673617],"type":"Point"}
}