{
  "type": "Feature",
  "properties": {
    "iso:country":"US",
    "sg:address":"E Penn Sq",
    "sg:city":"Philadelphia",
    "sg:classifiers":[
        {
            "category":"Professional",
            "subcategory":"Computer Services",
            "type":"Services"
        }
    ],
    "sg:phone":"+1 215 825 7696",
    "sg:postcode":"19107",
    "sg:province":"PA",
    "sg:tags":[
        "publisher",
        "software",
        "developer"
    ],
    "wof:name":"Penn Station Data Recovery Svc",
    "wof:placetype":"venue"
},
  "geometry": {"coordinates":[-75.162964,39.950148],"type":"Point"}
}