{
  "type": "Feature",
  "properties": {
    "iso:country":"US",
    "sg:address":"1326 Freeport Rd",
    "sg:city":"Pittsburgh",
    "sg:classifiers":[
        {
            "category":"Health Services",
            "subcategory":"Health Practitioner",
            "type":"Services"
        },
        {
            "category":"Health Services",
            "subcategory":"Doctor",
            "type":"Services"
        }
    ],
    "sg:phone":"+1 412 784 1333",
    "sg:postcode":"15238",
    "sg:province":"PA",
    "sg:tags":[
        "physician",
        "surgeon"
    ],
    "wof:name":"Orthopedic Surgical Associates",
    "wof:placetype":"venue"
},
  "geometry": {"coordinates":[-79.876848,40.488812],"type":"Point"}
}