{
  "type": "Feature",
  "properties": {
    "addr:full":"2509 Leechburg Rd New Kensington PA 15068",
    "addr:housenumber":"2509",
    "addr:postcode":"15068",
    "addr:street":"Leechburg Rd",
    "iso:country":"US",
    "sg:address":"2509 Leechburg Rd",
    "sg:city":"New Kensington",
    "sg:classifiers":[
        {
            "category":"Food & Beverages",
            "subcategory":"Liquor & Beverages",
            "type":"Retail Goods"
        }
    ],
    "sg:phone":"+1   ",
    "sg:postcode":"15068",
    "sg:province":"PA",
    "sg:tags":[
        "regulation",
        "commercial",
        "sect",
        "alcoholic"
    ],
    "wof:name":"Wine & Spirits Shoppe 6515",
    "wof:placetype":"venue"
},
  "geometry": {"coordinates":[-79.745642,40.587929],"type":"Point"}
}