{
  "type": "Feature",
  "properties": {
    "addr:full":"3817 Ridge Rd Gordonville PA 17529",
    "addr:housenumber":"3817",
    "addr:postcode":"17529",
    "addr:street":"Ridge Rd",
    "iso:country":"US",
    "sg:address":"3817 Ridge Rd",
    "sg:city":"Gordonville",
    "sg:classifiers":[
        {
            "category":"Farming",
            "subcategory":"Nursery",
            "type":"Manufacturing & Wholesale Goods"
        },
        {
            "category":"Building & Trades",
            "subcategory":"Landscaping Services",
            "type":"Services"
        }
    ],
    "sg:phone":"+1 717 768 3544",
    "sg:postcode":"17529",
    "sg:province":"PA",
    "sg:tags":[
        "flower",
        "greenhouse",
        "dried"
    ],
    "wof:name":"Fisher's Greenhouse",
    "wof:placetype":"venue"
},
  "geometry": {"coordinates":[-76.10002799999999,40.052458],"type":"Point"}
}