{
  "type": "Feature",
  "properties": {
    "iso:country":"US",
    "sg:address":"947 Bellefonte Ave",
    "sg:city":"Lock Haven",
    "sg:classifiers":[
        {
            "category":"Health Services",
            "subcategory":"Optometrist",
            "type":"Services"
        }
    ],
    "sg:phone":"+1 570 748 7751",
    "sg:postcode":"17745",
    "sg:province":"PA",
    "wof:name":"Brandt Eyecare",
    "wof:placetype":"venue"
},
  "geometry": {"coordinates":[-77.46463799999999,41.130142],"type":"Point"}
}