{
  "type": "Feature",
  "properties": {
    "iso:country":"US",
    "sg:address":"422 Brown St",
    "sg:city":"Philadelphia",
    "sg:classifiers":[
        {
            "category":"Professional",
            "subcategory":"Computer Services",
            "type":"Services"
        }
    ],
    "sg:phone":"+1 215 873 0318",
    "sg:postcode":"19123",
    "sg:province":"PA",
    "sg:tags":[
        "internet"
    ],
    "sg:website":"www.oneworldbar.com",
    "wof:name":"ONEWORLDBAR.COM",
    "wof:placetype":"venue"
},
  "geometry": {"coordinates":[-75.145054,39.963808],"type":"Point"}
}