{
  "type": "Feature",
  "properties": {
    "iso:country":"US",
    "sg:address":"1612 Randolph St",
    "sg:city":"Harrisburg",
    "sg:classifiers":[
        {
            "category":"Building & Trades",
            "subcategory":"Construction",
            "type":"Services"
        }
    ],
    "sg:phone":"+1   ",
    "sg:postcode":"17104",
    "sg:province":"PA",
    "sg:tags":[
        "house",
        "general",
        "family",
        "contractor"
    ],
    "wof:name":"Rodney Hollabaugh",
    "wof:placetype":"venue"
},
  "geometry": {"coordinates":[-76.859588,40.254679],"type":"Point"}
}