{
  "type": "Feature",
  "properties": {
    "addr:full":"1 Duquesne Blvd Duquesne PA 15110",
    "addr:postcode":"15110",
    "iso:country":"US",
    "sg:address":"1 Duquesne Blvd",
    "sg:city":"Duquesne",
    "sg:classifiers":[
        {
            "category":"Government",
            "subcategory":"Office",
            "type":"Public Place"
        }
    ],
    "sg:phone":"+1 412 466 5699",
    "sg:postcode":"15110",
    "sg:province":"PA",
    "wof:name":"Even Start-Allegheny Intrmdt",
    "wof:placetype":"venue"
},
  "geometry": {"coordinates":[-79.84672399999999,40.375906],"type":"Point"}
}