{
  "type": "Feature",
  "properties": {
    "addr:full":"147 Roys Ln Evans City PA 16033",
    "addr:housenumber":"147",
    "addr:postcode":"16033",
    "addr:street":"Roys Ln",
    "iso:country":"US",
    "sg:address":"147 Roys Ln",
    "sg:city":"Evans City",
    "sg:classifiers":[
        {
            "category":"Freight",
            "type":"Transportation"
        }
    ],
    "sg:phone":"+1   ",
    "sg:postcode":"16033",
    "sg:province":"PA",
    "sg:tags":[
        "operator",
        "local",
        "trucking"
    ],
    "wof:name":"Petry Trucking",
    "wof:placetype":"venue"
},
  "geometry": {"coordinates":[-80.063979,40.802053],"type":"Point"}
}