{
  "type": "Feature",
  "properties": {
    "iso:country":"US",
    "sg:address":"2529 Allequippa St",
    "sg:city":"Pittsburgh",
    "sg:classifiers":[
        {
            "category":"Food & Beverages",
            "subcategory":"Groceries & Convenience Stores",
            "type":"Retail Goods"
        }
    ],
    "sg:phone":"+1   ",
    "sg:postcode":"15213",
    "sg:province":"PA",
    "wof:name":"Glenn Dairy",
    "wof:placetype":"venue"
},
  "geometry": {"coordinates":[-79.96723900000001,40.441717],"type":"Point"}
}