{
  "type": "Feature",
  "properties": {
    "iso:country":"US",
    "sg:address":"107 E 4th Ave",
    "sg:city":"Conshohocken",
    "sg:classifiers":[
        {
            "category":"Personal",
            "type":"Services"
        }
    ],
    "sg:phone":"+1 610 828 6595",
    "sg:postcode":"19428",
    "sg:province":"PA",
    "sg:tags":[
        "food",
        "delivery"
    ],
    "wof:name":"Colonial Neighborhood Council",
    "wof:placetype":"venue"
},
  "geometry": {"coordinates":[-75.30279,40.075753],"type":"Point"}
}