{
  "type": "Feature",
  "properties": {
    "addr:full":"231 Springer Dr Coraopolis PA 15108",
    "addr:housenumber":"231",
    "addr:postcode":"15108",
    "addr:street":"Springer Dr",
    "iso:country":"US",
    "sg:address":"231 Springer Dr",
    "sg:city":"Coraopolis",
    "sg:classifiers":[
        {
            "category":"Real Estate",
            "subcategory":"Real Estate Agent",
            "type":"Services"
        }
    ],
    "sg:phone":"+1   ",
    "sg:postcode":"15108",
    "sg:province":"PA",
    "sg:tags":[
        "consulting",
        "cemetery"
    ],
    "wof:name":"Thomas O Hornstein Consultant",
    "wof:placetype":"venue"
},
  "geometry": {"coordinates":[-80.21740800000001,40.507424],"type":"Point"}
}