{
  "type": "Feature",
  "properties": {
    "addr:full":"3207 Perkiomen Ave Reading PA 19606",
    "addr:housenumber":"3207",
    "addr:postcode":"19606",
    "addr:street":"Perkiomen Ave",
    "iso:country":"US",
    "sg:address":"3207 Perkiomen Ave",
    "sg:city":"Reading",
    "sg:classifiers":[
        {
            "category":"Autos & Motor Vehicles",
            "subcategory":"Fuel & Gas Station",
            "type":"Retail Goods"
        }
    ],
    "sg:phone":"+1   ",
    "sg:postcode":"19606",
    "sg:province":"PA",
    "sg:tags":[
        "station"
    ],
    "wof:name":"Jerrys Reiffton Asso",
    "wof:placetype":"venue"
},
  "geometry": {"coordinates":[-75.876904,40.324758],"type":"Point"}
}