{
  "type": "Feature",
  "properties": {
    "iso:country":"US",
    "sg:address":"1057 Washington Rd",
    "sg:city":"Pittsburgh",
    "sg:classifiers":[
        {
            "category":"Building & Trades",
            "subcategory":"Construction",
            "type":"Services"
        }
    ],
    "sg:phone":"+1   ",
    "sg:postcode":"15228",
    "sg:province":"PA",
    "sg:tags":[
        "concrete",
        "contractor"
    ],
    "wof:name":"Albert Vanzin",
    "wof:placetype":"venue"
},
  "geometry": {"coordinates":[-80.04938,40.371613],"type":"Point"}
}