{
  "type": "Feature",
  "properties": {
    "addr:full":"1381 Sumneytown Pike Lansdale PA 19446",
    "addr:housenumber":"1381",
    "addr:postcode":"19446",
    "addr:street":"Sumneytown Pike",
    "iso:country":"US",
    "sg:address":"1381 Sumneytown Pike",
    "sg:city":"Lansdale",
    "sg:classifiers":[
        {
            "category":"Shopping",
            "type":"Retail Goods"
        }
    ],
    "sg:phone":"+1 215 362 0647",
    "sg:postcode":"19446",
    "sg:province":"PA",
    "sg:tags":[
        "candle"
    ],
    "wof:name":"Sir John's Candles",
    "wof:placetype":"venue"
},
  "geometry": {"coordinates":[-75.32418800000001,40.235341],"type":"Point"}
}