{
  "type": "Feature",
  "properties": {
    "addr:full":"1730 Dekalb Pike Blue Bell PA 19422",
    "addr:housenumber":"1730",
    "addr:postcode":"19422",
    "addr:street":"Dekalb Pike",
    "iso:country":"US",
    "sg:address":"1730 Dekalb Pike",
    "sg:city":"Blue Bell",
    "sg:classifiers":[
        {
            "category":"Personal",
            "subcategory":"Barber",
            "type":"Services"
        }
    ],
    "sg:phone":"+1 610 279 9620",
    "sg:postcode":"19422",
    "sg:province":"PA",
    "sg:website":"www.supercuts.com",
    "wof:name":"Supercuts",
    "wof:placetype":"venue"
},
  "geometry": {"coordinates":[-75.306,40.151001],"type":"Point"}
}