{
  "type": "Feature",
  "properties": {
    "addr:full":"276 Loop Rd Quarryville PA 17566",
    "addr:housenumber":"276",
    "addr:postcode":"17566",
    "addr:street":"Loop Rd",
    "iso:country":"US",
    "sg:address":"276 Loop Rd",
    "sg:city":"Quarryville",
    "sg:classifiers":[
        {
            "category":"Building & Trades",
            "subcategory":"Construction",
            "type":"Services"
        }
    ],
    "sg:phone":"+1 717 786 8293",
    "sg:postcode":"17566",
    "sg:province":"PA",
    "sg:tags":[
        "roofing",
        "contractor"
    ],
    "wof:name":"Beiler's General Construction",
    "wof:placetype":"venue"
},
  "geometry": {"coordinates":[-76.15175499999999,39.921994],"type":"Point"}
}