{
  "type": "Feature",
  "properties": {
    "iso:country":"US",
    "sg:address":"2326 N Broad St",
    "sg:city":"Chalfont",
    "sg:classifiers":[
        {
            "category":"Health Services",
            "subcategory":"Chiropractor",
            "type":"Services"
        }
    ],
    "sg:phone":"+1 215 996 9299",
    "sg:postcode":"18914",
    "sg:province":"PA",
    "wof:name":"Merkel Chiropractic Inc",
    "wof:placetype":"venue"
},
  "geometry": {"coordinates":[-75.21839900000001,40.280201],"type":"Point"}
}