{
  "type": "Feature",
  "properties": {
    "addr:full":"600 E Lincoln Hwy Coatesville PA 19320",
    "addr:housenumber":"600",
    "addr:postcode":"19320",
    "addr:street":"E Lincoln Hwy",
    "iso:country":"US",
    "sg:address":"600 E Lincoln Hwy",
    "sg:city":"Coatesville",
    "sg:classifiers":[
        {
            "category":"Deli",
            "type":"Food & Drink"
        }
    ],
    "sg:phone":"+1 610 383 6770",
    "sg:postcode":"19320",
    "sg:province":"PA",
    "sg:tags":[
        "delicatessen"
    ],
    "wof:name":"David's Corner",
    "wof:placetype":"venue"
},
  "geometry": {"coordinates":[-75.812973,39.98476],"type":"Point"}
}