{
  "type": "Feature",
  "properties": {
    "addr:full":"2854 Banksville Rd Pittsburgh PA 15216",
    "addr:housenumber":"2854",
    "addr:postcode":"15216",
    "addr:street":"Banksville Rd",
    "iso:country":"US",
    "sg:address":"2854 Banksville Rd",
    "sg:city":"Pittsburgh",
    "sg:classifiers":[
        {
            "category":"Retail",
            "subcategory":"Auto Repair",
            "type":"Services"
        }
    ],
    "sg:phone":"+1 412 531 3408",
    "sg:postcode":"15216",
    "sg:province":"PA",
    "sg:tags":[
        "automobile",
        "lubrication"
    ],
    "wof:name":"Jiffy Lube",
    "wof:placetype":"venue"
},
  "geometry": {"coordinates":[-80.03764200000001,40.405377],"type":"Point"}
}