{
  "type": "Feature",
  "properties": {
    "iso:country":"US",
    "sg:address":"23 Boulder Lake Dr",
    "sg:city":"Wernersville",
    "sg:classifiers":[
        {
            "category":"Shopping",
            "subcategory":"Clothing, Apparel, & Fashions",
            "type":"Retail Goods"
        }
    ],
    "sg:phone":"+1   ",
    "sg:postcode":"19565",
    "sg:province":"PA",
    "wof:name":"Marsden S Airbrush Designs",
    "wof:placetype":"venue"
},
  "geometry": {"coordinates":[-76.104387,40.305983],"type":"Point"}
}