{
  "type": "Feature",
  "properties": {
    "iso:country":"US",
    "sg:address":"1237 Cleveland Ave",
    "sg:city":"Reading",
    "sg:classifiers":[
        {
            "category":"Building & Trades",
            "subcategory":"Construction",
            "type":"Services"
        }
    ],
    "sg:phone":"+1   ",
    "sg:postcode":"19610",
    "sg:province":"PA",
    "sg:tags":[
        "carpentry",
        "contractor"
    ],
    "wof:name":"J Douglas Weaver Woodworking",
    "wof:placetype":"venue"
},
  "geometry": {"coordinates":[-75.964782,40.330377],"type":"Point"}
}