{
  "type": "Feature",
  "properties": {
    "iso:country":"US",
    "sg:address":"1501 Lower State Rd",
    "sg:city":"Chalfont",
    "sg:classifiers":[
        {
            "category":"Professional",
            "type":"Services"
        }
    ],
    "sg:phone":"+1 215 822 0464",
    "sg:postcode":"18914",
    "sg:province":"PA",
    "sg:tags":[
        "establishment"
    ],
    "wof:name":"Wal",
    "wof:placetype":"venue"
},
  "geometry": {"coordinates":[-75.159823,40.274569],"type":"Point"}
}