{
  "type": "Feature",
  "properties": {
    "iso:country":"US",
    "sg:address":"205 Linden Grove Rd",
    "sg:city":"New Holland",
    "sg:classifiers":[
        {
            "category":"Home & Garden",
            "subcategory":"Garden Supply",
            "type":"Retail Goods"
        }
    ],
    "sg:phone":"+1 717 354 6288",
    "sg:postcode":"17557",
    "sg:province":"PA",
    "wof:name":"Unique Vinyl Products",
    "wof:placetype":"venue"
},
  "geometry": {"coordinates":[-76.119518,40.128324],"type":"Point"}
}