{
  "type": "Feature",
  "properties": {
    "iso:country":"US",
    "sg:address":"1050 Stony Hill Rd",
    "sg:city":"Morrisville",
    "sg:classifiers":[
        {
            "category":"Restaurant",
            "type":"Food & Drink"
        }
    ],
    "sg:phone":"+1   ",
    "sg:postcode":"19067",
    "sg:province":"PA",
    "sg:tags":[
        "eating"
    ],
    "wof:name":"White Rose Cafe",
    "wof:placetype":"venue"
},
  "geometry": {"coordinates":[-74.885688,40.229602],"type":"Point"}
}