{
  "type": "Feature",
  "properties": {
    "addr:full":"2075 Quaker Pointe Dr Quakertown PA 18951",
    "addr:housenumber":"2075",
    "addr:postcode":"18951",
    "addr:street":"Quaker Pointe Dr",
    "iso:country":"US",
    "sg:address":"2075 Quaker Pointe Dr",
    "sg:city":"Quakertown",
    "sg:classifiers":[
        {
            "category":"Professional",
            "type":"Services"
        }
    ],
    "sg:phone":"+1 215 538 7355",
    "sg:postcode":"18951",
    "sg:province":"PA",
    "sg:tags":[
        "establishment"
    ],
    "sg:website":"www.kellwood.com",
    "wof:name":"Kellwood Co",
    "wof:placetype":"venue"
},
  "geometry": {"coordinates":[-75.4127,40.433603],"type":"Point"}
}