{
  "type": "Feature",
  "properties": {
    "iso:country":"US",
    "sg:address":"654 Park Ave",
    "sg:city":"Meadville",
    "sg:classifiers":[
        {
            "category":"Organizations",
            "subcategory":"Political Organization",
            "type":"Services"
        }
    ],
    "sg:phone":"+1   ",
    "sg:postcode":"16335",
    "sg:province":"PA",
    "wof:name":"Mayor Lords Hse Bed Breakfast",
    "wof:placetype":"venue"
},
  "geometry": {"coordinates":[-80.150021,41.645192],"type":"Point"}
}