{
  "type": "Feature",
  "properties": {
    "iso:country":"US",
    "sg:address":"947 Kurtz Mill Rd",
    "sg:city":"Mohnton",
    "sg:classifiers":[
        {
            "category":"Home & Garden",
            "subcategory":"Carpets & Floor Coverings",
            "type":"Retail Goods"
        }
    ],
    "sg:phone":"+1 610 856 7110",
    "sg:postcode":"19540",
    "sg:province":"PA",
    "sg:tags":[
        "installs",
        "wholesale",
        "material"
    ],
    "wof:name":"Gebhart's Floor Covering",
    "wof:placetype":"venue"
},
  "geometry": {"coordinates":[-75.942277,40.236496],"type":"Point"}
}