{
  "type": "Feature",
  "properties": {
    "iso:country":"US",
    "sg:address":"6998 Crider Rd Ste 100",
    "sg:city":"Mars",
    "sg:classifiers":[
        {
            "category":"Health Services",
            "subcategory":"Doctor",
            "type":"Services"
        }
    ],
    "sg:phone":"+1 724 778 3627",
    "sg:postcode":"16046",
    "sg:province":"PA",
    "sg:website":"www.medexpress.com",
    "wof:name":"Medexpress",
    "wof:placetype":"venue"
},
  "geometry": {"coordinates":[-80.03985,40.697383],"type":"Point"}
}