{
  "type": "Feature",
  "properties": {
    "iso:country":"US",
    "sg:address":"37 W Market St",
    "sg:city":"York",
    "sg:classifiers":[
        {
            "category":"Banks & Credit Unions",
            "subcategory":"Financial Services",
            "type":"Services"
        },
        {
            "category":"Professional",
            "subcategory":"Management & Consulting",
            "type":"Services"
        }
    ],
    "sg:phone":"+1 717 845 4958",
    "sg:postcode":"17401",
    "sg:province":"PA",
    "sg:tags":[
        "international",
        "trade",
        "exporting"
    ],
    "wof:name":"K Services International Inc",
    "wof:placetype":"venue"
},
  "geometry": {"coordinates":[-76.729018,39.962142],"type":"Point"}
}