{
  "type": "Feature",
  "properties": {
    "iso:country":"US",
    "sg:address":"427 Cavitt Ave",
    "sg:city":"Trafford",
    "sg:classifiers":[
        {
            "category":"Restaurant",
            "type":"Food & Drink"
        }
    ],
    "sg:phone":"+1 412 373 3036",
    "sg:postcode":"15085",
    "sg:province":"PA",
    "sg:tags":[
        "banquet",
        "rooms"
    ],
    "wof:name":"Angels Dance Hall",
    "wof:placetype":"venue"
},
  "geometry": {"coordinates":[-79.760034,40.385557],"type":"Point"}
}