{
  "type": "Feature",
  "properties": {
    "iso:country":"US",
    "sg:address":"613 Sandstone Rd",
    "sg:city":"Strasburg",
    "sg:classifiers":[
        {
            "category":"Farming",
            "subcategory":"Dairy Farm",
            "type":"Manufacturing & Wholesale Goods"
        }
    ],
    "sg:phone":"+1   ",
    "sg:postcode":"17579",
    "sg:province":"PA",
    "wof:name":"Martin Farm",
    "wof:placetype":"venue"
},
  "geometry": {"coordinates":[-76.199412,39.943681],"type":"Point"}
}