{
  "type": "Feature",
  "properties": {
    "addr:full":"1 N 9th St Lebanon PA 17046",
    "addr:housenumber":"1",
    "addr:postcode":"17046",
    "addr:street":"N 9Th St",
    "iso:country":"US",
    "sg:address":"1 N 9th St",
    "sg:city":"Lebanon",
    "sg:classifiers":[
        {
            "category":"Personal",
            "subcategory":"Beauty Salon",
            "type":"Services"
        }
    ],
    "sg:phone":"+1 717 272 5781",
    "sg:postcode":"17046",
    "sg:province":"PA",
    "sg:tags":[
        "shop"
    ],
    "wof:name":"Orchid Beauty Salon",
    "wof:placetype":"venue"
},
  "geometry": {"coordinates":[-76.426334,40.339818],"type":"Point"}
}