{
  "type": "Feature",
  "properties": {
    "addr:full":"464 Albert Rd Wind Gap PA 18091",
    "addr:housenumber":"464",
    "addr:postcode":"18091",
    "addr:street":"Albert Rd",
    "iso:country":"US",
    "sg:address":"464 Albert Rd",
    "sg:city":"Wind Gap",
    "sg:classifiers":[
        {
            "category":"Retail",
            "subcategory":"Repair Shop",
            "type":"Services"
        }
    ],
    "sg:phone":"+1 610 863 9458",
    "sg:postcode":"18091",
    "sg:province":"PA",
    "sg:tags":[
        "antique",
        "restoring"
    ],
    "wof:name":"Gerry's Brass & Copper Plshng",
    "wof:placetype":"venue"
},
  "geometry": {"coordinates":[-75.291535,40.815816],"type":"Point"}
}