{
  "type": "Feature",
  "properties": {
    "iso:country":"US",
    "sg:address":"734 Springdale Dr",
    "sg:city":"Exton",
    "sg:classifiers":[
        {
            "category":"Utilities",
            "subcategory":"Water",
            "type":"Services"
        },
        {
            "category":"Utilities",
            "type":"Services"
        }
    ],
    "sg:phone":"+1 610 524 7560",
    "sg:postcode":"19341",
    "sg:province":"PA",
    "sg:tags":[
        "consultant",
        "management",
        "public"
    ],
    "wof:name":"Public Utility Service Corporation",
    "wof:placetype":"venue"
},
  "geometry": {"coordinates":[-75.606415,40.029324],"type":"Point"}
}