{
  "type": "Feature",
  "properties": {
    "iso:country":"US",
    "sg:address":"1375 Chestnut St",
    "sg:city":"Emmaus",
    "sg:classifiers":[
        {
            "category":"Health Services",
            "subcategory":"Doctor",
            "type":"Services"
        }
    ],
    "sg:phone":"+1   ",
    "sg:postcode":"18049",
    "sg:province":"PA",
    "sg:tags":[
        "medical"
    ],
    "wof:name":"John N Heid Do",
    "wof:placetype":"venue"
},
  "geometry": {"coordinates":[-75.508785,40.527888],"type":"Point"}
}