{
  "type": "Feature",
  "properties": {
    "iso:country":"US",
    "sg:address":"145 Foreman Rd",
    "sg:city":"Freeport",
    "sg:classifiers":[
        {
            "category":"Home & Garden",
            "subcategory":"Hardware",
            "type":"Retail Goods"
        }
    ],
    "sg:phone":"+1 724 295 3809",
    "sg:postcode":"16229",
    "sg:province":"PA",
    "sg:tags":[
        "saw"
    ],
    "wof:name":"Bill's Saw & Mower Svc",
    "wof:placetype":"venue"
},
  "geometry": {"coordinates":[-79.64380800000001,40.759598],"type":"Point"}
}