{
  "type": "Feature",
  "properties": {
    "iso:country":"US",
    "sg:address":"112 N Aberdeen Ave",
    "sg:city":"Wayne",
    "sg:classifiers":[
        {
            "category":"Retail",
            "subcategory":"Veterinary Services",
            "type":"Services"
        }
    ],
    "sg:phone":"+1 610 687 1550",
    "sg:postcode":"19087",
    "sg:province":"PA",
    "sg:tags":[
        "hospital",
        "animal"
    ],
    "wof:name":"Radnor Veterinary Hospital",
    "wof:placetype":"venue"
},
  "geometry": {"coordinates":[-75.381334,40.044097],"type":"Point"}
}