{
  "type": "Feature",
  "properties": {
    "addr:full":"525 Hancock Ave Vandergrift PA 15690",
    "addr:housenumber":"525",
    "addr:postcode":"15690",
    "addr:street":"Hancock Ave",
    "iso:country":"US",
    "sg:address":"525 Hancock Ave",
    "sg:city":"Vandergrift",
    "sg:classifiers":[
        {
            "category":"Manufacturing",
            "subcategory":"Metals",
            "type":"Manufacturing & Wholesale Goods"
        }
    ],
    "sg:phone":"+1   ",
    "sg:postcode":"15690",
    "sg:province":"PA",
    "sg:tags":[
        "metalwork",
        "sheet",
        "mfg"
    ],
    "wof:name":"Stewart Machine Co",
    "wof:placetype":"venue"
},
  "geometry": {"coordinates":[-79.568718,40.597371],"type":"Point"}
}