{
  "type": "Feature",
  "properties": {
    "iso:country":"US",
    "sg:address":"650 Wigard Ave",
    "sg:city":"Philadelphia",
    "sg:classifiers":[
        {
            "category":"Health Services",
            "subcategory":"Clinic",
            "type":"Services"
        }
    ],
    "sg:phone":"+1 215 483 7829",
    "sg:postcode":"19128",
    "sg:province":"PA",
    "sg:tags":[
        "hypnotherapy"
    ],
    "wof:name":"Action Institute",
    "wof:placetype":"venue"
},
  "geometry": {"coordinates":[-75.22765099999999,40.05233],"type":"Point"}
}