{
  "type": "Feature",
  "properties": {
    "addr:full":"171 E College St Canonsburg PA 15317",
    "addr:housenumber":"171",
    "addr:postcode":"15317",
    "addr:street":"E College St",
    "iso:country":"US",
    "sg:address":"171 E College St",
    "sg:city":"Canonsburg",
    "sg:classifiers":[
        {
            "category":"Organizations",
            "subcategory":"Religious Organization",
            "type":"Services"
        }
    ],
    "sg:phone":"+1 724 745 2091",
    "sg:postcode":"15317",
    "sg:province":"PA",
    "wof:name":"Sacred Hart Jsus Polish Nat Ca",
    "wof:placetype":"venue"
},
  "geometry": {"coordinates":[-80.183874,40.260814],"type":"Point"}
}