{
  "type": "Feature",
  "properties": {
    "iso:country":"US",
    "sg:address":"1121 W Schuylkill Rd",
    "sg:city":"Pottstown",
    "sg:classifiers":[
        {
            "category":"Professional",
            "type":"Services"
        }
    ],
    "sg:phone":"+1   ",
    "sg:postcode":"19465",
    "sg:province":"PA",
    "wof:name":"James Williams",
    "wof:placetype":"venue"
},
  "geometry": {"coordinates":[-75.67997800000001,40.235558],"type":"Point"}
}