{
  "type": "Feature",
  "properties": {
    "addr:full":"4601 Devonshire Rd Harrisburg PA 17109",
    "addr:housenumber":"4601",
    "addr:postcode":"17109",
    "addr:street":"Devonshire Rd",
    "iso:country":"US",
    "sg:address":"4601 Devonshire Rd",
    "sg:city":"Harrisburg",
    "sg:classifiers":[
        {
            "category":"Social Services",
            "subcategory":"Adult Care",
            "type":"Services"
        },
        {
            "category":"Organizations",
            "subcategory":"Non-profit Organization",
            "type":"Services"
        }
    ],
    "sg:phone":"+1 717 545 0333",
    "sg:postcode":"17109",
    "sg:province":"PA",
    "sg:tags":[
        "residential",
        "human"
    ],
    "wof:name":"Impact Systems Inc",
    "wof:placetype":"venue"
},
  "geometry": {"coordinates":[-76.813236,40.305904],"type":"Point"}
}