{
  "type": "Feature",
  "properties": {
    "iso:country":"US",
    "sg:address":"1881 Brodhead Rd",
    "sg:city":"Aliquippa",
    "sg:classifiers":[
        {
            "category":"Organizations",
            "subcategory":"Religious Organization",
            "type":"Services"
        }
    ],
    "sg:phone":"+1 724 375 2100",
    "sg:postcode":"15001",
    "sg:province":"PA",
    "sg:tags":[
        "church"
    ],
    "sg:website":"www.bcmalliance.org",
    "wof:name":"Broadhead Alliance Church",
    "wof:placetype":"venue"
},
  "geometry": {"coordinates":[-80.26765399999999,40.591702],"type":"Point"}
}