{
  "type": "Feature",
  "properties": {
    "addr:full":"2240 Cumberland St Lebanon PA 17042",
    "addr:housenumber":"2240",
    "addr:postcode":"17042",
    "addr:street":"Cumberland St",
    "iso:country":"US",
    "sg:address":"2240 Cumberland St",
    "sg:city":"Lebanon",
    "sg:classifiers":[
        {
            "category":"Shopping",
            "subcategory":"Jewelry",
            "type":"Retail Goods"
        }
    ],
    "sg:phone":"+1 717 274 2539",
    "sg:postcode":"17042",
    "sg:province":"PA",
    "sg:tags":[
        "jeweler"
    ],
    "wof:name":"Zales Jewelers",
    "wof:placetype":"venue"
},
  "geometry": {"coordinates":[-76.452834,40.339229],"type":"Point"}
}