{
  "type": "Feature",
  "properties": {
    "addr:full":"2324 Holly Dr Gilbertsville PA 19525",
    "addr:housenumber":"2324",
    "addr:postcode":"19525",
    "addr:street":"Holly Dr",
    "iso:country":"US",
    "sg:address":"2324 Holly Dr",
    "sg:city":"Gilbertsville",
    "sg:classifiers":[
        {
            "category":"Personal",
            "subcategory":"Massage",
            "type":"Services"
        },
        {
            "category":"Personal",
            "subcategory":"Beauty Salon",
            "type":"Services"
        }
    ],
    "sg:phone":"+1 610 718 0995",
    "sg:postcode":"19525",
    "sg:province":"PA",
    "sg:tags":[
        "therapist"
    ],
    "wof:name":"Sensational Skin",
    "wof:placetype":"venue"
},
  "geometry": {"coordinates":[-75.572492,40.284206],"type":"Point"}
}