{
  "type": "Feature",
  "properties": {
    "addr:full":"5620 Elliott St Philadelphia PA 19143",
    "addr:housenumber":"5620",
    "addr:postcode":"19143",
    "addr:street":"Elliott St",
    "iso:country":"US",
    "sg:address":"5620 Elliott St",
    "sg:city":"Philadelphia",
    "sg:classifiers":[
        {
            "category":"Building & Trades",
            "subcategory":"Cleaning & Sanitation",
            "type":"Services"
        }
    ],
    "sg:phone":"+1 215 476 1652",
    "sg:postcode":"19143",
    "sg:province":"PA",
    "sg:tags":[
        "janitorial"
    ],
    "wof:name":"Alcar Janitorial Services",
    "wof:placetype":"venue"
},
  "geometry": {"coordinates":[-75.23368499999999,39.94381],"type":"Point"}
}