{
  "type": "Feature",
  "properties": {
    "addr:full":"1264 Smithbridge Rd Chadds Ford PA 19317",
    "addr:housenumber":"1264",
    "addr:postcode":"19317",
    "addr:street":"Smithbridge Rd",
    "iso:country":"US",
    "sg:address":"1264 Smithbridge Rd",
    "sg:city":"Chadds Ford",
    "sg:classifiers":[
        {
            "category":"Building & Trades",
            "subcategory":"Cleaning & Sanitation",
            "type":"Services"
        }
    ],
    "sg:phone":"+1   ",
    "sg:postcode":"19317",
    "sg:province":"PA",
    "sg:tags":[
        "maintenance"
    ],
    "wof:name":"Property Pros",
    "wof:placetype":"venue"
},
  "geometry": {"coordinates":[-75.55437000000001,39.851734],"type":"Point"}
}