{
  "type": "Feature",
  "properties": {
    "addr:full":"1839 E 18th St Erie PA 16510",
    "addr:housenumber":"1839",
    "addr:postcode":"16510",
    "addr:street":"E 18Th St",
    "iso:country":"US",
    "sg:address":"1839 E 18th St",
    "sg:city":"Erie",
    "sg:classifiers":[
        {
            "category":"Real Estate",
            "subcategory":"Real Estate Agent",
            "type":"Services"
        }
    ],
    "sg:phone":"+1 814 899 0678",
    "sg:postcode":"16510",
    "sg:province":"PA",
    "sg:tags":[
        "authorities",
        "housing"
    ],
    "sg:website":"www.hace.org",
    "wof:name":"Housing Authority",
    "wof:placetype":"venue"
},
  "geometry": {"coordinates":[-80.037076,42.133789],"type":"Point"}
}