{
  "type": "Feature",
  "properties": {
    "iso:country":"US",
    "sg:address":"1300 Willow St",
    "sg:city":"Oakdale",
    "sg:classifiers":[
        {
            "category":"Shopping",
            "subcategory":"Florist",
            "type":"Retail Goods"
        }
    ],
    "sg:phone":"+1 724 693 9464",
    "sg:postcode":"15071",
    "sg:province":"PA",
    "wof:name":"Noblestown Florists",
    "wof:placetype":"venue"
},
  "geometry": {"coordinates":[-80.198804,40.390021],"type":"Point"}
}