{
  "type": "Feature",
  "properties": {
    "iso:country":"US",
    "sg:address":"1905 Jackson Ave",
    "sg:city":"New Castle",
    "sg:classifiers":[
        {
            "category":"Real Estate",
            "subcategory":"Real Estate Agent",
            "type":"Services"
        }
    ],
    "sg:phone":"+1 724 657 8649",
    "sg:postcode":"16101",
    "sg:province":"PA",
    "sg:tags":[
        "appraiser"
    ],
    "wof:name":"Bruce E Peterson Appraisals",
    "wof:placetype":"venue"
},
  "geometry": {"coordinates":[-80.32995699999999,40.979218],"type":"Point"}
}