{
  "type": "Feature",
  "properties": {
    "addr:full":"8 Monongahela Ave Dilliner PA 15458",
    "addr:housenumber":"8",
    "addr:postcode":"15458",
    "addr:street":"Monongahela Ave",
    "iso:country":"US",
    "sg:address":"8 Monongahela Ave",
    "sg:city":"Dilliner",
    "sg:classifiers":[
        {
            "category":"Government",
            "subcategory":"Office",
            "type":"Public Place"
        }
    ],
    "sg:phone":"+1 724 725 5289",
    "sg:postcode":"15458",
    "sg:province":"PA",
    "sg:tags":[
        "federal"
    ],
    "wof:name":"US Army Corps Of Engineers",
    "wof:placetype":"venue"
},
  "geometry": {"coordinates":[-79.99461599999999,39.991001],"type":"Point"}
}