{
  "type": "Feature",
  "properties": {
    "iso:country":"US",
    "sg:address":"1633 Big Oak Rd",
    "sg:city":"Yardley",
    "sg:classifiers":[
        {
            "category":"Restaurant",
            "type":"Food & Drink"
        }
    ],
    "sg:phone":"+1 215 321 9010",
    "sg:postcode":"19067",
    "sg:province":"PA",
    "sg:tags":[
        "pizza"
    ],
    "sg:website":"http://www.carluccisitaliangrill.com",
    "wof:name":"Carlucci's Grill",
    "wof:placetype":"venue"
},
  "geometry": {"coordinates":[-74.866647,40.198328],"type":"Point"}
}