{
  "type": "Feature",
  "properties": {
    "iso:country":"US",
    "sg:address":"820 Washington Crossing Rd",
    "sg:city":"Newtown",
    "sg:classifiers":[
        {
            "category":"Building & Trades",
            "subcategory":"Construction",
            "type":"Services"
        },
        {
            "category":"Building & Trades",
            "subcategory":"Landscaping Services",
            "type":"Services"
        }
    ],
    "sg:phone":"+1 215 968 3401",
    "sg:postcode":"18940",
    "sg:province":"PA",
    "sg:tags":[
        "mfg",
        "metalwork",
        "architectural",
        "railing"
    ],
    "wof:name":"Leedom Lester E",
    "wof:placetype":"venue"
},
  "geometry": {"coordinates":[-74.895276,40.266456],"type":"Point"}
}