{
  "type": "Feature",
  "properties": {
    "addr:full":"520 Florence Ave Pittsburgh PA 15202",
    "addr:housenumber":"520",
    "addr:postcode":"15202",
    "addr:street":"Florence Ave",
    "iso:country":"US",
    "sg:address":"520 Florence Ave",
    "sg:city":"Pittsburgh",
    "sg:classifiers":[
        {
            "category":"Building & Trades",
            "subcategory":"Construction",
            "type":"Services"
        }
    ],
    "sg:phone":"+1 412 761 4122",
    "sg:postcode":"15202",
    "sg:province":"PA",
    "sg:tags":[
        "roofing",
        "contractor"
    ],
    "wof:name":"Keynon Roofing",
    "wof:placetype":"venue"
},
  "geometry": {"coordinates":[-80.070111,40.500846],"type":"Point"}
}