{
  "type": "Feature",
  "properties": {
    "iso:country":"US",
    "sg:address":"325 Beaver Creek Rd",
    "sg:city":"Dillsburg",
    "sg:classifiers":[
        {
            "category":"Wholesale",
            "subcategory":"Metals & Minerals",
            "type":"Manufacturing & Wholesale Goods"
        }
    ],
    "sg:phone":"+1 717 432 9241",
    "sg:postcode":"17019",
    "sg:province":"PA",
    "wof:name":"Mariani Metal Fabricators",
    "wof:placetype":"venue"
},
  "geometry": {"coordinates":[-76.932548,40.089948],"type":"Point"}
}