{
  "type": "Feature",
  "properties": {
    "addr:full":"10441 Perry Hwy Wexford PA 15090",
    "addr:housenumber":"10441",
    "addr:postcode":"15090",
    "addr:street":"Perry Hwy",
    "iso:country":"US",
    "sg:address":"10441 Perry Hwy",
    "sg:city":"Wexford",
    "sg:classifiers":[
        {
            "category":"Retail",
            "subcategory":"Laundry & Dry Cleaning",
            "type":"Services"
        }
    ],
    "sg:phone":"+1 724 934 3090",
    "sg:postcode":"15090",
    "sg:province":"PA",
    "sg:tags":[
        "cleaners"
    ],
    "wof:name":"Johnson's Cleaners",
    "wof:placetype":"venue"
},
  "geometry": {"coordinates":[-80.05488699999999,40.613927],"type":"Point"}
}