{
  "type": "Feature",
  "properties": {
    "iso:country":"US",
    "sg:address":"12142 Old 126",
    "sg:city":"Crystal Spring",
    "sg:classifiers":[
        {
            "category":"Wholesale",
            "subcategory":"Construction Materials",
            "type":"Manufacturing & Wholesale Goods"
        }
    ],
    "sg:phone":"+1   ",
    "sg:postcode":"15536",
    "sg:province":"PA",
    "sg:tags":[
        "building",
        "lumber",
        "supply"
    ],
    "wof:name":"Jarr Veneer Inc",
    "wof:placetype":"venue"
},
  "geometry": {"coordinates":[-78.250618,39.914683],"type":"Point"}
}