{
  "type": "Feature",
  "properties": {
    "iso:country":"US",
    "sg:address":"321 N 18th St",
    "sg:city":"Philadelphia",
    "sg:classifiers":[
        {
            "category":"Health Services",
            "subcategory":"Doctor",
            "type":"Services"
        }
    ],
    "sg:phone":"+1 215 564 0623",
    "sg:postcode":"19103",
    "sg:province":"PA",
    "wof:name":"Shangold Mona MD",
    "wof:placetype":"venue"
},
  "geometry": {"coordinates":[-75.168453,39.959425],"type":"Point"}
}