{
  "type": "Feature",
  "properties": {
    "iso:country":"US",
    "sg:address":"1611 N Newkirk St",
    "sg:city":"Philadelphia",
    "sg:classifiers":[
        {
            "category":"Professional",
            "subcategory":"Management & Consulting",
            "type":"Services"
        }
    ],
    "sg:phone":"+1 215 236 3137",
    "sg:postcode":"19121",
    "sg:province":"PA",
    "sg:tags":[
        "science",
        "consultant",
        "academic"
    ],
    "wof:name":"Mtc Consultants",
    "wof:placetype":"venue"
},
  "geometry": {"coordinates":[-75.181104,39.980376],"type":"Point"}
}