{
  "type": "Feature",
  "properties": {
    "iso:country":"US",
    "sg:address":"227 E Main St",
    "sg:city":"Sykesville",
    "sg:classifiers":[
        {
            "category":"Manufacturing",
            "subcategory":"Toys & Sporting Goods",
            "type":"Manufacturing & Wholesale Goods"
        }
    ],
    "sg:phone":"+1 814 894 2444",
    "sg:postcode":"15865",
    "sg:province":"PA",
    "sg:tags":[
        "athletic"
    ],
    "sg:website":"www.idealproductsinc.com",
    "wof:name":"Ideal Products Inc",
    "wof:placetype":"venue"
},
  "geometry": {"coordinates":[-78.817892,41.05192],"type":"Point"}
}