{
  "type": "Feature",
  "properties": {
    "iso:country":"US",
    "sg:address":"4313 Pine Ave",
    "sg:city":"Erie",
    "sg:classifiers":[
        {
            "category":"Building & Trades",
            "subcategory":"Construction",
            "type":"Services"
        }
    ],
    "sg:phone":"+1   ",
    "sg:postcode":"16504",
    "sg:province":"PA",
    "sg:tags":[
        "house"
    ],
    "wof:name":"McFarlands Remodeling Service",
    "wof:placetype":"venue"
},
  "geometry": {"coordinates":[-80.037781,42.106865],"type":"Point"}
}