{
  "type": "Feature",
  "properties": {
    "addr:full":"4110 Brownsville Rd Pittsburgh PA 15227",
    "addr:housenumber":"4110",
    "addr:postcode":"15227",
    "addr:street":"Brownsville Rd",
    "iso:country":"US",
    "sg:address":"4110 Brownsville Rd",
    "sg:city":"Pittsburgh",
    "sg:classifiers":[
        {
            "category":"Shopping",
            "subcategory":"Hobbies, Toys, & Games",
            "type":"Retail Goods"
        }
    ],
    "sg:phone":"+1 412 885 0180",
    "sg:postcode":"15227",
    "sg:province":"PA",
    "sg:tags":[
        "shop",
        "hobby",
        "supply"
    ],
    "sg:website":"www.ebgames.com",
    "wof:name":"Eb Games",
    "wof:placetype":"venue"
},
  "geometry": {"coordinates":[-79.98175999999999,40.366244],"type":"Point"}
}