{
  "type": "Feature",
  "properties": {
    "iso:country":"US",
    "sg:address":"1267 Liberty St",
    "sg:city":"Franklin",
    "sg:classifiers":[
        {
            "category":"Restaurant",
            "type":"Food & Drink"
        }
    ],
    "sg:phone":"+1 814 432 8421",
    "sg:postcode":"16323",
    "sg:province":"PA",
    "wof:name":"Leonardo's Restaurant",
    "wof:placetype":"venue"
},
  "geometry": {"coordinates":[-79.830575,41.397811],"type":"Point"}
}