{
  "type": "Feature",
  "properties": {
    "iso:country":"US",
    "sg:address":"347 2nd Street Pike",
    "sg:city":"Southampton",
    "sg:classifiers":[
        {
            "category":"Health Services",
            "subcategory":"Chiropractor",
            "type":"Services"
        }
    ],
    "sg:phone":"+1 215 322 1880",
    "sg:postcode":"18966",
    "sg:province":"PA",
    "wof:name":"Advanced Back & Neck Care",
    "wof:placetype":"venue"
},
  "geometry": {"coordinates":[-75.045822,40.167108],"type":"Point"}
}