{
  "type": "Feature",
  "properties": {
    "iso:country":"US",
    "sg:address":"8014 Ogontz Ave",
    "sg:city":"Philadelphia",
    "sg:classifiers":[
        {
            "category":"Food & Beverages",
            "subcategory":"Groceries & Convenience Stores",
            "type":"Retail Goods"
        }
    ],
    "sg:phone":"+1   ",
    "sg:postcode":"19150",
    "sg:province":"PA",
    "wof:name":"Chong Ran Im",
    "wof:placetype":"venue"
},
  "geometry": {"coordinates":[-75.15844199999999,40.074097],"type":"Point"}
}