{
  "type": "Feature",
  "properties": {
    "iso:country":"US",
    "sg:address":"410 Clearview Ave",
    "sg:city":"Feasterville Trevose",
    "sg:classifiers":[
        {
            "category":"Manufacturing",
            "subcategory":"Tools & Machinery",
            "type":"Manufacturing & Wholesale Goods"
        }
    ],
    "sg:phone":"+1 215 322 8795",
    "sg:postcode":"19053",
    "sg:province":"PA",
    "sg:tags":[
        "for",
        "mfg",
        "die",
        "machine",
        "parts",
        "maker"
    ],
    "wof:name":"Ampol Tool & Machine Corp",
    "wof:placetype":"venue"
},
  "geometry": {"coordinates":[-74.97925499999999,40.154196],"type":"Point"}
}