{
  "type": "Feature",
  "properties": {
    "addr:full":"1541 S 5th St Philadelphia PA 19147",
    "addr:housenumber":"1541",
    "addr:postcode":"19147",
    "addr:street":"S 5Th St",
    "iso:country":"US",
    "sg:address":"1541 S 5th St",
    "sg:city":"Philadelphia",
    "sg:classifiers":[
        {
            "category":"Shopping",
            "subcategory":"Florist",
            "type":"Retail Goods"
        }
    ],
    "sg:phone":"+1   ",
    "sg:postcode":"19147",
    "sg:province":"PA",
    "wof:name":"James Wallace",
    "wof:placetype":"venue"
},
  "geometry": {"coordinates":[-75.153621,39.928619],"type":"Point"}
}