{
  "type": "Feature",
  "properties": {
    "iso:country":"US",
    "sg:address":"636 Tire Hill Rd",
    "sg:city":"Johnstown",
    "sg:classifiers":[
        {
            "category":"Manufacturing",
            "subcategory":"Signs",
            "type":"Manufacturing & Wholesale Goods"
        }
    ],
    "sg:phone":"+1   ",
    "sg:postcode":"15905",
    "sg:province":"PA",
    "sg:tags":[
        "specialty",
        "mfg"
    ],
    "wof:name":"Minahan Signs",
    "wof:placetype":"venue"
},
  "geometry": {"coordinates":[-78.91778499999999,40.271978],"type":"Point"}
}