{
  "type": "Feature",
  "properties": {
    "iso:country":"US",
    "sg:address":"7243 Thomas Rd",
    "sg:city":"Mc Kean",
    "sg:classifiers":[
        {
            "category":"Wholesale",
            "subcategory":"Auto Parts",
            "type":"Manufacturing & Wholesale Goods"
        }
    ],
    "sg:phone":"+1 814 833 7169",
    "sg:postcode":"16426",
    "sg:province":"PA",
    "sg:tags":[
        "automobile",
        "wrecking"
    ],
    "wof:name":"Denny's Auto Wrecking",
    "wof:placetype":"venue"
},
  "geometry": {"coordinates":[-80.157591,42.034313],"type":"Point"}
}