{
  "type": "Feature",
  "properties": {
    "iso:country":"US",
    "sg:address":"121 2nd Street Pike",
    "sg:city":"Southampton",
    "sg:classifiers":[
        {
            "category":"Sports & Exercise",
            "subcategory":"Bowling",
            "type":"Entertainment"
        }
    ],
    "sg:phone":"+1 215 357 1899",
    "sg:postcode":"18966",
    "sg:province":"PA",
    "wof:name":"Pike Lanes Bowling Inc",
    "wof:placetype":"venue"
},
  "geometry": {"coordinates":[-75.047755,40.160533],"type":"Point"}
}