{
  "type": "Feature",
  "properties": {
    "iso:country":"US",
    "sg:address":"4955 State Rte 873",
    "sg:city":"Schnecksville",
    "sg:classifiers":[
        {
            "category":"Health Services",
            "subcategory":"Chiropractor",
            "type":"Services"
        }
    ],
    "sg:phone":"+1 610 799 0700",
    "sg:postcode":"18078",
    "sg:province":"PA",
    "wof:name":"Siano Family Chiropractic",
    "wof:placetype":"venue"
},
  "geometry": {"coordinates":[-75.61313800000001,40.674924],"type":"Point"}
}