{
  "type": "Feature",
  "properties": {
    "addr:full":"2512 Metropolitan Dr Feasterville Trevose PA 19053",
    "addr:housenumber":"2512",
    "addr:postcode":"19053",
    "addr:street":"Metropolitan Dr",
    "iso:country":"US",
    "sg:address":"2512 Metropolitan Dr",
    "sg:city":"Feasterville Trevose",
    "sg:classifiers":[
        {
            "category":"Manufacturing",
            "subcategory":"Printing",
            "type":"Manufacturing & Wholesale Goods"
        }
    ],
    "sg:phone":"+1   ",
    "sg:postcode":"19053",
    "sg:province":"PA",
    "sg:tags":[
        "newspaper",
        "weekly"
    ],
    "wof:name":"Promedia Publishing Co",
    "wof:placetype":"venue"
},
  "geometry": {"coordinates":[-74.984295,40.132618],"type":"Point"}
}