{
  "type": "Feature",
  "properties": {
    "iso:country":"US",
    "sg:address":"713 N Market St",
    "sg:city":"Selinsgrove",
    "sg:classifiers":[
        {
            "category":"Bars & Pubs",
            "type":"Food & Drink"
        }
    ],
    "sg:phone":"+1 570 374 9727",
    "sg:postcode":"17870",
    "sg:province":"PA",
    "wof:name":"Kelly's Towne Tavern",
    "wof:placetype":"venue"
},
  "geometry": {"coordinates":[-76.857513,40.807562],"type":"Point"}
}