{
  "type": "Feature",
  "properties": {
    "addr:full":"444 Center Rd Monroeville PA 15146",
    "addr:housenumber":"444",
    "addr:postcode":"15146",
    "addr:street":"Center Rd",
    "iso:country":"US",
    "sg:address":"444 Center Rd",
    "sg:city":"Monroeville",
    "sg:classifiers":[
        {
            "category":"Professional",
            "subcategory":"Management & Consulting",
            "type":"Services"
        }
    ],
    "sg:phone":"+1   ",
    "sg:postcode":"15146",
    "sg:province":"PA",
    "sg:tags":[
        "eating"
    ],
    "wof:name":"Taco Bell",
    "wof:placetype":"venue"
},
  "geometry": {"coordinates":[-79.761011,40.452982],"type":"Point"}
}