{
  "type": "Feature",
  "properties": {
    "addr:full":"8 Kennedy St Bradford PA 16701",
    "addr:housenumber":"8",
    "addr:postcode":"16701",
    "addr:street":"Kennedy St",
    "iso:country":"US",
    "sg:address":"8 Kennedy St",
    "sg:city":"Bradford",
    "sg:classifiers":[
        {
            "category":"Real Estate",
            "subcategory":"Real Estate Agent",
            "type":"Services"
        }
    ],
    "sg:phone":"+1 814 368 5770",
    "sg:postcode":"16701",
    "sg:province":"PA",
    "wof:name":"Wright Realty",
    "wof:placetype":"venue"
},
  "geometry": {"coordinates":[-78.647336,41.956905],"type":"Point"}
}