{
  "type": "Feature",
  "properties": {
    "iso:country":"US",
    "sg:address":"270 E Smithfield St",
    "sg:city":"Mount Pleasant",
    "sg:classifiers":[
        {
            "category":"Personal",
            "subcategory":"Beauty Salon",
            "type":"Services"
        }
    ],
    "sg:phone":"+1   ",
    "sg:postcode":"15666",
    "sg:province":"PA",
    "sg:tags":[
        "shop"
    ],
    "wof:name":"Jsrs Hair Space Inc",
    "wof:placetype":"venue"
},
  "geometry": {"coordinates":[-79.53064500000001,40.148315],"type":"Point"}
}