{
  "type": "Feature",
  "properties": {
    "iso:country":"US",
    "sg:address":"566 E Main St",
    "sg:city":"New Holland",
    "sg:classifiers":[
        {
            "category":"Local Transit",
            "type":"Transportation"
        }
    ],
    "sg:phone":"+1 717 355 5520",
    "sg:postcode":"17557",
    "sg:province":"PA",
    "sg:tags":[
        "limousine"
    ],
    "wof:name":"Brenner Coach & Limousine",
    "wof:placetype":"venue"
},
  "geometry": {"coordinates":[-76.073699,40.10633],"type":"Point"}
}