{
  "type": "Feature",
  "properties": {
    "addr:full":"Sugan & Cuttalossa Rds Solebury PA 18963",
    "addr:postcode":"18963",
    "iso:country":"US",
    "sg:address":"Sugan & Cuttalossa Rds",
    "sg:city":"Solebury",
    "sg:classifiers":[
        {
            "category":"Retail",
            "subcategory":"Auto Repair",
            "type":"Services"
        }
    ],
    "sg:phone":"+1 215 297 5174",
    "sg:postcode":"18963",
    "sg:province":"PA",
    "wof:name":"Melson S B",
    "wof:placetype":"venue"
},
  "geometry": {"coordinates":[-75.024939,40.387511],"type":"Point"}
}