{
  "type": "Feature",
  "properties": {
    "iso:country":"US",
    "sg:address":"3075 William Penn Hwy",
    "sg:city":"Easton",
    "sg:classifiers":[
        {
            "category":"Real Estate",
            "subcategory":"Real Estate Services",
            "type":"Services"
        },
        {
            "category":"Banks & Credit Unions",
            "subcategory":"Financial Services",
            "type":"Services"
        }
    ],
    "sg:phone":"+1 610 252 9704",
    "sg:postcode":"18045",
    "sg:province":"PA",
    "sg:tags":[
        "financing",
        "processing",
        "loan"
    ],
    "sg:website":"http://www.loansfast.com",
    "wof:name":"American General Finance Corporation",
    "wof:placetype":"venue"
},
  "geometry": {"coordinates":[-75.26164,40.676531],"type":"Point"}
}