{
  "type": "Feature",
  "properties": {
    "addr:full":"675 Lancaster Rd Manheim PA 17545",
    "addr:housenumber":"675",
    "addr:postcode":"17545",
    "addr:street":"Lancaster Rd",
    "iso:country":"US",
    "sg:address":"675 Lancaster Rd",
    "sg:city":"Manheim",
    "sg:classifiers":[
        {
            "category":"Food & Beverages",
            "subcategory":"Groceries & Convenience Stores",
            "type":"Retail Goods"
        }
    ],
    "sg:phone":"+1 717 664 2300",
    "sg:postcode":"17545",
    "sg:province":"PA",
    "wof:name":"Hess Express",
    "wof:placetype":"venue"
},
  "geometry": {"coordinates":[-76.38319,40.151936],"type":"Point"}
}