{
  "type": "Feature",
  "properties": {
    "iso:country":"US",
    "sg:address":"1231 Warm Springs Ave # 101",
    "sg:city":"Huntingdon",
    "sg:classifiers":[
        {
            "category":"Health Services",
            "subcategory":"Clinic",
            "type":"Services"
        },
        {
            "category":"Social Services",
            "subcategory":"Child Care",
            "type":"Services"
        }
    ],
    "sg:phone":"+1 814 643 5364",
    "sg:postcode":"16652",
    "sg:province":"PA",
    "sg:tags":[
        "control",
        "information",
        "planning",
        "birth",
        "family"
    ],
    "sg:website":"http://www.fhcinc.org",
    "wof:name":"Adagio Health Inc.",
    "wof:placetype":"venue"
},
  "geometry": {"coordinates":[-78.013953,40.493626],"type":"Point"}
}