{
  "type": "Feature",
  "properties": {
    "addr:full":"2 Spring Ave Temple PA 19560",
    "addr:housenumber":"2",
    "addr:postcode":"19560",
    "addr:street":"Spring Ave",
    "iso:country":"US",
    "sg:address":"2 Spring Ave",
    "sg:city":"Temple",
    "sg:classifiers":[
        {
            "category":"Building & Trades",
            "subcategory":"Construction",
            "type":"Services"
        }
    ],
    "sg:phone":"+1   ",
    "sg:postcode":"19560",
    "sg:province":"PA",
    "sg:tags":[
        "sanitary",
        "contractor"
    ],
    "wof:name":"Clarence B Prutzman Jr",
    "wof:placetype":"venue"
},
  "geometry": {"coordinates":[-75.856606,40.398253],"type":"Point"}
}