{
  "type": "Feature",
  "properties": {
    "iso:country":"US",
    "sg:address":"700 S Henderson Rd",
    "sg:city":"King Of Prussia",
    "sg:classifiers":[
        {
            "category":"Health Services",
            "subcategory":"Clinic",
            "type":"Services"
        },
        {
            "category":"Health Services",
            "subcategory":"Doctor",
            "type":"Services"
        }
    ],
    "sg:phone":"+1 610 265 6464",
    "sg:postcode":"19406",
    "sg:province":"PA",
    "sg:tags":[
        "physician",
        "surgeon",
        "specialty",
        "outpatient"
    ],
    "wof:name":"Internet Behavioral Care",
    "wof:placetype":"venue"
},
  "geometry": {"coordinates":[-75.355282,40.079478],"type":"Point"}
}