{
  "type": "Feature",
  "properties": {
    "addr:full":"2550 Brownsville Rd Pittsburgh PA 15210",
    "addr:housenumber":"2550",
    "addr:postcode":"15210",
    "addr:street":"Brownsville Rd",
    "iso:country":"US",
    "sg:address":"2550 Brownsville Rd",
    "sg:city":"Pittsburgh",
    "sg:classifiers":[
        {
            "category":"Banks & Credit Unions",
            "subcategory":"Bank",
            "type":"Services"
        }
    ],
    "sg:phone":"+1 412 831 4800",
    "sg:postcode":"15210",
    "sg:province":"PA",
    "wof:name":"Iron & Glass Bank",
    "wof:placetype":"venue"
},
  "geometry": {"coordinates":[-79.97876599999999,40.38559],"type":"Point"}
}