{
  "type": "Feature",
  "properties": {
    "iso:country":"US",
    "sg:address":"1460 Bethlehem Pike",
    "sg:city":"Flourtown",
    "sg:classifiers":[
        {
            "category":"Shopping",
            "subcategory":"Bicycles & Sporting Goods",
            "type":"Retail Goods"
        }
    ],
    "sg:phone":"+1 267 708 0211",
    "sg:postcode":"19031",
    "sg:province":"PA",
    "wof:name":"Leisure Fitness Equipment Str",
    "wof:placetype":"venue"
},
  "geometry": {"coordinates":[-75.212919,40.102532],"type":"Point"}
}