{
  "type": "Feature",
  "properties": {
    "addr:full":"201 Woodspring Cir Doylestown PA 18901",
    "addr:housenumber":"201",
    "addr:postcode":"18901",
    "addr:street":"Woodspring Cir",
    "iso:country":"US",
    "sg:address":"201 Woodspring Cir",
    "sg:city":"Doylestown",
    "sg:classifiers":[
        {
            "category":"Sports & Exercise",
            "subcategory":"Race Track",
            "type":"Entertainment"
        }
    ],
    "sg:phone":"+1   ",
    "sg:postcode":"18901",
    "sg:province":"PA",
    "sg:tags":[
        "operation",
        "racing",
        "or"
    ],
    "wof:name":"Bk Racing LLC",
    "wof:placetype":"venue"
},
  "geometry": {"coordinates":[-75.13168400000001,40.304324],"type":"Point"}
}