{
  "type": "Feature",
  "properties": {
    "iso:country":"US",
    "sg:address":"643 Woodcrest Dr",
    "sg:city":"Pittsburgh",
    "sg:classifiers":[
        {
            "category":"Health Services",
            "subcategory":"Doctor",
            "type":"Services"
        }
    ],
    "sg:phone":"+1   ",
    "sg:postcode":"15205",
    "sg:province":"PA",
    "wof:name":"J Martin Dattilo DDS",
    "wof:placetype":"venue"
},
  "geometry": {"coordinates":[-80.094488,40.430517],"type":"Point"}
}