{
  "type": "Feature",
  "properties": {
    "addr:full":"355 Washington Trails Rd Washington PA 15301",
    "addr:housenumber":"355",
    "addr:postcode":"15301",
    "addr:street":"Washington Trails Rd",
    "iso:country":"US",
    "sg:address":"355 Washington Trails Rd",
    "sg:city":"Washington",
    "sg:classifiers":[
        {
            "category":"Restaurant",
            "type":"Food & Drink"
        }
    ],
    "sg:phone":"+1 724 229 3595",
    "sg:postcode":"15301",
    "sg:province":"PA",
    "sg:tags":[
        "out"
    ],
    "wof:name":"Dominics Of New York",
    "wof:placetype":"venue"
},
  "geometry": {"coordinates":[-80.24705,40.248538],"type":"Point"}
}