{
  "type": "Feature",
  "properties": {
    "iso:country":"US",
    "sg:address":"100 Snyder Rd",
    "sg:city":"Lansdale",
    "sg:classifiers":[
        {
            "category":"Real Estate",
            "subcategory":"Real Estate Operator",
            "type":"Services"
        }
    ],
    "sg:phone":"+1   ",
    "sg:postcode":"19446",
    "sg:province":"PA",
    "sg:tags":[
        "building",
        "apartment"
    ],
    "wof:name":"Kbf Associates LP",
    "wof:placetype":"venue"
},
  "geometry": {"coordinates":[-75.31241,40.237802],"type":"Point"}
}