{
  "type": "Feature",
  "properties": {
    "addr:full":"810 Tech Dr Hilltown PA 18969",
    "addr:housenumber":"810",
    "addr:postcode":"18969",
    "addr:street":"Tech Dr",
    "iso:country":"US",
    "sg:address":"810 Tech Dr",
    "sg:city":"Hilltown",
    "sg:classifiers":[
        {
            "category":"Building & Trades",
            "subcategory":"Construction",
            "type":"Services"
        }
    ],
    "sg:phone":"+1 215 703 0823",
    "sg:postcode":"18969",
    "sg:province":"PA",
    "sg:tags":[
        "builder",
        "stair"
    ],
    "wof:name":"Stairworks Inc",
    "wof:placetype":"venue"
},
  "geometry": {"coordinates":[-75.303545,40.327134],"type":"Point"}
}