{
  "type": "Feature",
  "properties": {
    "addr:full":"1515 Christian St Philadelphia PA 19146",
    "addr:housenumber":"1515",
    "addr:postcode":"19146",
    "addr:street":"Christian St",
    "iso:country":"US",
    "sg:address":"1515 Christian St",
    "sg:city":"Philadelphia",
    "sg:classifiers":[
        {
            "category":"Social Services",
            "subcategory":"Adult Care",
            "type":"Services"
        }
    ],
    "sg:phone":"+1 215 985 4364",
    "sg:postcode":"19146",
    "sg:province":"PA",
    "sg:tags":[
        "centers-adult",
        "day"
    ],
    "wof:name":"Jackson Personal Care",
    "wof:placetype":"venue"
},
  "geometry": {"coordinates":[-75.168193,39.940266],"type":"Point"}
}