{
  "type": "Feature",
  "properties": {
    "addr:full":"1085 Millcreek Rd York PA 17404",
    "addr:housenumber":"1085",
    "addr:postcode":"17404",
    "addr:street":"Millcreek Rd",
    "iso:country":"US",
    "sg:address":"1085 Millcreek Rd",
    "sg:city":"York",
    "sg:classifiers":[
        {
            "category":"Building & Trades",
            "subcategory":"Construction",
            "type":"Services"
        }
    ],
    "sg:phone":"+1 717 764 0811",
    "sg:postcode":"17404",
    "sg:province":"PA",
    "sg:tags":[
        "fire",
        "restoration",
        "damage"
    ],
    "wof:name":"Servpro",
    "wof:placetype":"venue"
},
  "geometry": {"coordinates":[-76.770483,40.017424],"type":"Point"}
}