{
  "type": "Feature",
  "properties": {
    "iso:country":"US",
    "sg:address":"2500 S Queen St",
    "sg:city":"York",
    "sg:classifiers":[
        {
            "category":"Education",
            "subcategory":"School",
            "type":"Public Place"
        }
    ],
    "sg:phone":"+1 717 741 2281",
    "sg:postcode":"17402",
    "sg:province":"PA",
    "sg:tags":[
        "elementary"
    ],
    "sg:website":"http://www.dallastown.k12.pa.us",
    "wof:name":"York Township Elementary School",
    "wof:placetype":"venue"
},
  "geometry": {"coordinates":[-76.684669,39.916695],"type":"Point"}
}