{
  "type": "Feature",
  "properties": {
    "addr:full":"2309 W Cumberland St Philadelphia PA 19132",
    "addr:housenumber":"2309",
    "addr:postcode":"19132",
    "addr:street":"W Cumberland St",
    "iso:country":"US",
    "sg:address":"2309 W Cumberland St",
    "sg:city":"Philadelphia",
    "sg:classifiers":[
        {
            "category":"Real Estate",
            "subcategory":"Real Estate Services",
            "type":"Services"
        }
    ],
    "sg:phone":"+1 215 223 3242",
    "sg:postcode":"19132",
    "sg:province":"PA",
    "sg:tags":[
        "information",
        "referral"
    ],
    "wof:name":"Jacqueline L Hampton",
    "wof:placetype":"venue"
},
  "geometry": {"coordinates":[-75.169962,39.992786],"type":"Point"}
}