{
  "type": "Feature",
  "properties": {
    "iso:country":"US",
    "sg:address":"4 Glen Hollow Ct",
    "sg:city":"Reading",
    "sg:classifiers":[
        {
            "category":"Professional",
            "type":"Services"
        }
    ],
    "sg:phone":"+1   ",
    "sg:postcode":"19607",
    "sg:province":"PA",
    "wof:name":"Barton L Litvin",
    "wof:placetype":"venue"
},
  "geometry": {"coordinates":[-75.94152200000001,40.268649],"type":"Point"}
}