{
  "type": "Feature",
  "properties": {
    "iso:country":"US",
    "sg:address":"9 Cindy Cir",
    "sg:city":"Enola",
    "sg:classifiers":[
        {
            "category":"Building & Trades",
            "subcategory":"Electrical",
            "type":"Services"
        }
    ],
    "sg:phone":"+1 717 732 1461",
    "sg:postcode":"17025",
    "sg:province":"PA",
    "sg:tags":[
        "electrician"
    ],
    "wof:name":"Ltc Electrical Contractor",
    "wof:placetype":"venue"
},
  "geometry": {"coordinates":[-76.957199,40.2883],"type":"Point"}
}