{
  "type": "Feature",
  "properties": {
    "addr:full":"5200 Penn Ave Pittsburgh PA 15224",
    "addr:housenumber":"5200",
    "addr:postcode":"15224",
    "addr:street":"Penn Ave",
    "iso:country":"US",
    "sg:address":"5200 Penn Ave",
    "sg:city":"Pittsburgh",
    "sg:classifiers":[
        {
            "category":"Wholesale",
            "subcategory":"Electrical",
            "type":"Manufacturing & Wholesale Goods"
        }
    ],
    "sg:phone":"+1 412 363 1800",
    "sg:postcode":"15224",
    "sg:province":"PA",
    "sg:tags":[
        "construction",
        "fitting",
        "material",
        "wire"
    ],
    "wof:name":"Service Electrical Supply Co",
    "wof:placetype":"venue"
},
  "geometry": {"coordinates":[-79.938608,40.464562],"type":"Point"}
}