{
  "type": "Feature",
  "properties": {
    "iso:country":"US",
    "sg:address":"239 Schuyler Ave",
    "sg:city":"Kingston",
    "sg:classifiers":[
        {
            "category":"Education",
            "subcategory":"Dance Studio",
            "type":"Public Place"
        }
    ],
    "sg:phone":"+1 570 287 5802",
    "sg:postcode":"18704",
    "sg:province":"PA",
    "sg:tags":[
        "instruction",
        "dancing"
    ],
    "wof:name":"Degnan Ballet",
    "wof:placetype":"venue"
},
  "geometry": {"coordinates":[-75.89811899999999,41.267468],"type":"Point"}
}