{
  "type": "Feature",
  "properties": {
    "iso:country":"US",
    "sg:address":"1802 Michelle Dr",
    "sg:city":"York",
    "sg:classifiers":[
        {
            "category":"Building & Trades",
            "subcategory":"Construction",
            "type":"Services"
        }
    ],
    "sg:phone":"+1   ",
    "sg:postcode":"17408",
    "sg:province":"PA",
    "sg:tags":[
        "contractor"
    ],
    "wof:name":"Kds Contracting Services Inc",
    "wof:placetype":"venue"
},
  "geometry": {"coordinates":[-76.806421,39.964333],"type":"Point"}
}