{
  "type": "Feature",
  "properties": {
    "addr:full":"1560 Lititz Pike Lancaster PA 17601",
    "addr:postcode":"1560;17601",
    "addr:street":"Lititz Pike",
    "iso:country":"US",
    "sg:address":"1560 Lititz Pike",
    "sg:city":"Lancaster",
    "sg:classifiers":[
        {
            "category":"Health Services",
            "subcategory":"Doctor",
            "type":"Services"
        }
    ],
    "sg:phone":"+1 717 735 7788",
    "sg:postcode":"17601",
    "sg:province":"PA",
    "sg:tags":[
        "physician",
        "surgeon"
    ],
    "wof:name":"Character's Pub",
    "wof:placetype":"venue"
},
  "geometry": {"coordinates":[-76.307321,40.066782],"type":"Point"}
}