{
  "type": "Feature",
  "properties": {
    "iso:country":"US",
    "sg:address":"214 Sensenig Rd",
    "sg:city":"Ephrata",
    "sg:classifiers":[
        {
            "category":"Farming",
            "subcategory":"Dairy Farm",
            "type":"Manufacturing & Wholesale Goods"
        }
    ],
    "sg:phone":"+1   ",
    "sg:postcode":"17522",
    "sg:province":"PA",
    "wof:name":"Evergreen Farm",
    "wof:placetype":"venue"
},
  "geometry": {"coordinates":[-76.08195000000001,40.165735],"type":"Point"}
}