{
  "type": "Feature",
  "properties": {
    "iso:country":"US",
    "sg:address":"51 N Towamencin Ave",
    "sg:city":"Lansdale",
    "sg:classifiers":[
        {
            "category":"Professional",
            "type":"Services"
        }
    ],
    "sg:phone":"+1 215 368 9299",
    "sg:postcode":"19446",
    "sg:province":"PA",
    "sg:tags":[
        "establishment"
    ],
    "wof:name":"Bertels Corp",
    "wof:placetype":"venue"
},
  "geometry": {"coordinates":[-75.28918299999999,40.245791],"type":"Point"}
}