{
  "type": "Feature",
  "properties": {
    "iso:country":"US",
    "sg:address":"113 Hindman Ln",
    "sg:city":"Butler",
    "sg:classifiers":[
        {
            "category":"Building & Trades",
            "subcategory":"Construction",
            "type":"Services"
        }
    ],
    "sg:phone":"+1 724 789 9520",
    "sg:postcode":"16001",
    "sg:province":"PA",
    "sg:tags":[
        "maker",
        "cabinet"
    ],
    "wof:name":"Innovative Custom Cabinetry",
    "wof:placetype":"venue"
},
  "geometry": {"coordinates":[-79.97649699999999,40.853155],"type":"Point"}
}