{
  "type": "Feature",
  "properties": {
    "addr:full":"220 Thomas Bright Ave Easton PA 18042",
    "addr:housenumber":"220",
    "addr:postcode":"18042",
    "addr:street":"Thomas Bright Ave",
    "iso:country":"US",
    "sg:address":"220 Thomas Bright Ave",
    "sg:city":"Easton",
    "sg:classifiers":[
        {
            "category":"Organizations",
            "subcategory":"Religious Organization",
            "type":"Services"
        }
    ],
    "sg:phone":"+1 610 252 5640",
    "sg:postcode":"18042",
    "sg:province":"PA",
    "sg:tags":[
        "church"
    ],
    "wof:name":"Greater Shiloh Baptist Church",
    "wof:placetype":"venue"
},
  "geometry": {"coordinates":[-75.219932,40.681309],"type":"Point"}
}