{
  "type": "Feature",
  "properties": {
    "iso:country":"US",
    "sg:address":"486 Landis Store Rd",
    "sg:city":"Boyertown",
    "sg:phone":"+1   ",
    "sg:postcode":"19512",
    "sg:province":"PA",
    "sg:tags":[
        "farm",
        "field",
        "crop"
    ],
    "wof:name":"Kevin Guldin",
    "wof:placetype":"venue"
},
  "geometry": {"coordinates":[-75.67281800000001,40.390488],"type":"Point"}
}