{
  "type": "Feature",
  "properties": {
    "iso:country":"US",
    "sg:address":"40 Buttermilk Ln",
    "sg:city":"Hopwood",
    "sg:classifiers":[
        {
            "category":"Manufacturing",
            "subcategory":"Lumber",
            "type":"Manufacturing & Wholesale Goods"
        }
    ],
    "sg:phone":"+1 724 438 1911",
    "sg:postcode":"15445",
    "sg:province":"PA",
    "sg:tags":[
        "planing",
        "mills",
        "sawmill"
    ],
    "wof:name":"Curry Lumber Co",
    "wof:placetype":"venue"
},
  "geometry": {"coordinates":[-79.69917,39.867909],"type":"Point"}
}