{
  "type": "Feature",
  "properties": {
    "iso:country":"US",
    "sg:address":"528 Main St",
    "sg:city":"Peckville",
    "sg:classifiers":[
        {
            "category":"Bars & Pubs",
            "type":"Food & Drink"
        },
        {
            "category":"Restaurant",
            "type":"Food & Drink"
        },
        {
            "category":"Bars & Pubs",
            "subcategory":"Lounge",
            "type":"Food & Drink"
        }
    ],
    "sg:phone":"+1 570 489 9238",
    "sg:postcode":"18452",
    "sg:province":"PA",
    "sg:tags":[
        "grill",
        "cocktail",
        "pizza"
    ],
    "wof:name":"Andy's Pizza",
    "wof:placetype":"venue"
},
  "geometry": {"coordinates":[-75.575834,41.4803],"type":"Point"}
}