{
  "type": "Feature",
  "properties": {
    "addr:full":"803 Brighton Ave Reading PA 19606",
    "addr:housenumber":"803",
    "addr:postcode":"19606",
    "addr:street":"Brighton Ave",
    "iso:country":"US",
    "sg:address":"803 Brighton Ave",
    "sg:city":"Reading",
    "sg:classifiers":[
        {
            "category":"Insurance",
            "subcategory":"Insurance Agent",
            "type":"Services"
        }
    ],
    "sg:phone":"+1 610 370 0555",
    "sg:postcode":"19606",
    "sg:province":"PA",
    "wof:name":"William D Rhoads Insurance Svc",
    "wof:placetype":"venue"
},
  "geometry": {"coordinates":[-75.877341,40.338815],"type":"Point"}
}