{
  "type": "Feature",
  "properties": {
    "iso:country":"US",
    "sg:address":"19 S Market St",
    "sg:city":"Elizabethtown",
    "sg:classifiers":[
        {
            "category":"Wholesale",
            "subcategory":"Medical Equipment & Supplies",
            "type":"Manufacturing & Wholesale Goods"
        }
    ],
    "sg:phone":"+1 717 367 1262",
    "sg:postcode":"17022",
    "sg:province":"PA",
    "sg:tags":[
        "physician",
        "surgeon"
    ],
    "wof:name":"Kreamer Medical",
    "wof:placetype":"venue"
},
  "geometry": {"coordinates":[-76.605797,40.151302],"type":"Point"}
}