{
  "type": "Feature",
  "properties": {
    "iso:country":"US",
    "sg:address":"4877 Kutztown Rd",
    "sg:city":"Temple",
    "sg:classifiers":[
        {
            "category":"Personal",
            "type":"Services"
        }
    ],
    "sg:phone":"+1 610 929 8728",
    "sg:postcode":"19560",
    "sg:province":"PA",
    "sg:tags":[
        "therapist",
        "massage"
    ],
    "wof:name":"Healthy Directions",
    "wof:placetype":"venue"
},
  "geometry": {"coordinates":[-75.920186,40.408672],"type":"Point"}
}