{
  "type": "Feature",
  "properties": {
    "iso:country":"US",
    "sg:address":"335 1st St",
    "sg:city":"Pittsburgh",
    "sg:classifiers":[
        {
            "category":"Health Services",
            "subcategory":"Health Practitioner",
            "type":"Services"
        }
    ],
    "sg:phone":"+1   ",
    "sg:postcode":"15215",
    "sg:province":"PA",
    "wof:name":"Ronald G Jalbert PHD",
    "wof:placetype":"venue"
},
  "geometry": {"coordinates":[-79.901672,40.489968],"type":"Point"}
}