{
  "type": "Feature",
  "properties": {
    "addr:full":"600 S Elmwood Ave Glenolden PA 19036",
    "addr:housenumber":"600",
    "addr:postcode":"19036",
    "addr:street":"S Elmwood Ave",
    "iso:country":"US",
    "sg:address":"600 S Elmwood Ave",
    "sg:city":"Glenolden",
    "sg:classifiers":[
        {
            "category":"Wholesale",
            "subcategory":"Auto Parts",
            "type":"Manufacturing & Wholesale Goods"
        }
    ],
    "sg:phone":"+1   ",
    "sg:postcode":"19036",
    "sg:province":"PA",
    "sg:tags":[
        "equipment",
        "tool",
        "automotive"
    ],
    "wof:name":"Matco Tools",
    "wof:placetype":"venue"
},
  "geometry": {"coordinates":[-75.29169899999999,39.89111],"type":"Point"}
}