{
  "type": "Feature",
  "properties": {
    "iso:country":"US",
    "sg:address":"4 Jason Ln",
    "sg:city":"Thorndale",
    "sg:classifiers":[
        {
            "category":"Banks & Credit Unions",
            "subcategory":"Investment Brokerage",
            "type":"Services"
        }
    ],
    "sg:phone":"+1   ",
    "sg:postcode":"19372",
    "sg:province":"PA",
    "sg:tags":[
        "advisory"
    ],
    "wof:name":"General Acceptance Financial",
    "wof:placetype":"venue"
},
  "geometry": {"coordinates":[-75.75778699999999,39.998297],"type":"Point"}
}