{
  "type": "Feature",
  "properties": {
    "iso:country":"US",
    "sg:address":"535 Vernon Rd",
    "sg:city":"Greenville",
    "sg:classifiers":[
        {
            "category":"Mining & Drilling",
            "type":"Manufacturing & Wholesale Goods"
        }
    ],
    "sg:phone":"+1   ",
    "sg:postcode":"16125",
    "sg:province":"PA",
    "sg:tags":[
        "construction"
    ],
    "wof:name":"Kinsman Sand & Gravel Co",
    "wof:placetype":"venue"
},
  "geometry": {"coordinates":[-80.440246,41.403871],"type":"Point"}
}