{
  "type": "Feature",
  "properties": {
    "addr:full":"917 Kochenderfer Rd Lebanon PA 17046",
    "addr:housenumber":"917",
    "addr:postcode":"17046",
    "addr:street":"Kochenderfer Rd",
    "iso:country":"US",
    "sg:address":"917 Kochenderfer Rd",
    "sg:city":"Lebanon",
    "sg:classifiers":[
        {
            "category":"Farming",
            "subcategory":"Livestock Farm",
            "type":"Manufacturing & Wholesale Goods"
        }
    ],
    "sg:phone":"+1   ",
    "sg:postcode":"17046",
    "sg:province":"PA",
    "sg:tags":[
        "beef",
        "feedlot",
        "cattle"
    ],
    "wof:name":"Allen Heagy",
    "wof:placetype":"venue"
},
  "geometry": {"coordinates":[-76.424143,40.368407],"type":"Point"}
}