{
  "type": "Feature",
  "properties": {
    "addr:full":"225 Cemetery Ln Pittsburgh PA 15237",
    "addr:housenumber":"225",
    "addr:postcode":"15237",
    "addr:street":"Cemetery Ln",
    "iso:country":"US",
    "sg:address":"225 Cemetery Ln",
    "sg:city":"Pittsburgh",
    "sg:classifiers":[
        {
            "category":"Building & Trades",
            "subcategory":"Construction",
            "type":"Services"
        }
    ],
    "sg:phone":"+1 412 931 3956",
    "sg:postcode":"15237",
    "sg:province":"PA",
    "sg:tags":[
        "marking",
        "maintenance",
        "parking"
    ],
    "sg:website":"www.ross.pa.us",
    "wof:name":"Ross Twp Public Works Dept",
    "wof:placetype":"venue"
},
  "geometry": {"coordinates":[-80.017923,40.507162],"type":"Point"}
}