{
  "type": "Feature",
  "properties": {
    "iso:country":"US",
    "sg:address":"140 Longvue Dr",
    "sg:city":"Canonsburg",
    "sg:classifiers":[
        {
            "category":"Mining & Drilling",
            "type":"Manufacturing & Wholesale Goods"
        }
    ],
    "sg:phone":"+1 724 941 3201",
    "sg:postcode":"15317",
    "sg:province":"PA",
    "sg:tags":[
        "development",
        "gas",
        "oil",
        "exploration"
    ],
    "wof:name":"Lincoln Energy Inc",
    "wof:placetype":"venue"
},
  "geometry": {"coordinates":[-80.111625,40.282902],"type":"Point"}
}