{
  "type": "Feature",
  "properties": {
    "iso:country":"US",
    "sg:address":"9 Dickinson Ct",
    "sg:city":"New Freedom",
    "sg:phone":"+1   ",
    "sg:postcode":"17349",
    "sg:province":"PA",
    "sg:tags":[
        "product",
        "petroleum"
    ],
    "wof:name":"Alt Bill Exxonmobil",
    "wof:placetype":"venue"
},
  "geometry": {"coordinates":[-76.69167899999999,39.734756],"type":"Point"}
}