{
  "type": "Feature",
  "properties": {
    "iso:country":"US",
    "sg:address":"174 W Budd St",
    "sg:city":"Sharon",
    "sg:classifiers":[
        {
            "category":"Real Estate",
            "subcategory":"Real Estate Operator",
            "type":"Services"
        }
    ],
    "sg:phone":"+1 724 981 8201",
    "sg:postcode":"16146",
    "sg:province":"PA",
    "sg:tags":[
        "apartment"
    ],
    "wof:name":"Shanango",
    "wof:placetype":"venue"
},
  "geometry": {"coordinates":[-80.51264500000001,41.227505],"type":"Point"}
}