{
  "type": "Feature",
  "properties": {
    "addr:full":"2712 Banker St Mc Keesport PA 15132",
    "addr:housenumber":"2712",
    "addr:postcode":"15132",
    "addr:street":"Banker St",
    "iso:country":"US",
    "sg:address":"2712 Banker St",
    "sg:city":"Mc Keesport",
    "sg:classifiers":[
        {
            "category":"Communications",
            "subcategory":"Film & Video Production",
            "type":"Services"
        }
    ],
    "sg:phone":"+1   ",
    "sg:postcode":"15132",
    "sg:province":"PA",
    "sg:tags":[
        "motion",
        "picture"
    ],
    "wof:name":"D L S Productions",
    "wof:placetype":"venue"
},
  "geometry": {"coordinates":[-79.832379,40.333413],"type":"Point"}
}