{
  "type": "Feature",
  "properties": {
    "iso:country":"US",
    "sg:address":"572 Queen St",
    "sg:city":"Northumberland",
    "sg:classifiers":[
        {
            "category":"Building & Trades",
            "subcategory":"Construction",
            "type":"Services"
        }
    ],
    "sg:phone":"+1 570 473 3077",
    "sg:postcode":"17857",
    "sg:province":"PA",
    "sg:tags":[
        "home",
        "general",
        "family",
        "contractor"
    ],
    "wof:name":"R & C Decorating Inc",
    "wof:placetype":"venue"
},
  "geometry": {"coordinates":[-76.803318,40.892948],"type":"Point"}
}