{
  "type": "Feature",
  "properties": {
    "addr:full":"127 Cornwall Dr Pittsburgh PA 15238",
    "addr:housenumber":"127",
    "addr:postcode":"15238",
    "addr:street":"Cornwall Dr",
    "iso:country":"US",
    "sg:address":"127 Cornwall Dr",
    "sg:city":"Pittsburgh",
    "sg:classifiers":[
        {
            "category":"Health Services",
            "subcategory":"Doctor",
            "type":"Services"
        }
    ],
    "sg:phone":"+1   ",
    "sg:postcode":"15238",
    "sg:province":"PA",
    "sg:tags":[
        "clinic",
        "medical"
    ],
    "wof:name":"Eugene Ginchereau",
    "wof:placetype":"venue"
},
  "geometry": {"coordinates":[-79.860452,40.510312],"type":"Point"}
}