{
  "type": "Feature",
  "properties": {
    "iso:country":"US",
    "sg:address":"1616 Walnut St Ste 911",
    "sg:city":"Philadelphia",
    "sg:classifiers":[
        {
            "category":"Professional",
            "subcategory":"Engineering",
            "type":"Services"
        },
        {
            "category":"Building & Trades",
            "subcategory":"Construction",
            "type":"Services"
        },
        {
            "category":"Real Estate",
            "subcategory":"Architect",
            "type":"Services"
        }
    ],
    "sg:phone":"+1 215 732 6883",
    "sg:postcode":"19103",
    "sg:province":"PA",
    "sg:tags":[
        "architects'",
        "consulting",
        "consultant",
        "specification",
        "builders'",
        "architectural",
        "engineer"
    ],
    "wof:name":"Lighthouse Achitecture",
    "wof:placetype":"venue"
},
  "geometry": {"coordinates":[-75.168054,39.949812],"type":"Point"}
}