{
  "type": "Feature",
  "properties": {
    "addr:full":"7161 Torresdale Ave Philadelphia PA 19135",
    "addr:postcode":"7161;19135",
    "addr:street":"Torresdale Ave",
    "iso:country":"US",
    "sg:address":"7161 Torresdale Ave",
    "sg:city":"Philadelphia",
    "sg:classifiers":[
        {
            "category":"Personal",
            "subcategory":"Barber",
            "type":"Services"
        }
    ],
    "sg:phone":"+1 215 331 2707",
    "sg:postcode":"19135",
    "sg:province":"PA",
    "wof:name":"Frank Nicoletti Men's",
    "wof:placetype":"venue"
},
  "geometry": {"coordinates":[-75.037001,40.029032],"type":"Point"}
}