{
  "type": "Feature",
  "properties": {
    "addr:full":"163 Montgomery Mall North Wales PA 19454",
    "addr:housenumber":"163",
    "addr:postcode":"19454",
    "addr:street":"Montgomery Mall",
    "iso:country":"US",
    "sg:address":"163 Montgomery Mall",
    "sg:city":"North Wales",
    "sg:classifiers":[
        {
            "category":"Shopping",
            "subcategory":"Shoes",
            "type":"Retail Goods"
        }
    ],
    "sg:phone":"+1 215 855 9939",
    "sg:postcode":"19454",
    "sg:province":"PA",
    "sg:tags":[
        "store"
    ],
    "sg:website":"www.payless.com",
    "wof:name":"Payless Shoesource",
    "wof:placetype":"venue"
},
  "geometry": {"coordinates":[-75.242484,40.236734],"type":"Point"}
}