{
  "type": "Feature",
  "properties": {
    "iso:country":"US",
    "sg:address":"101 E Olney Ave",
    "sg:city":"Philadelphia",
    "sg:classifiers":[
        {
            "category":"Shopping",
            "subcategory":"Optical Goods",
            "type":"Retail Goods"
        }
    ],
    "sg:phone":"+1 215 927 2020",
    "sg:postcode":"19120",
    "sg:province":"PA",
    "sg:tags":[
        "optician"
    ],
    "wof:name":"Philadelphia Vision Ctr",
    "wof:placetype":"venue"
},
  "geometry": {"coordinates":[-75.11754999999999,40.034793],"type":"Point"}
}