{
  "type": "Feature",
  "properties": {
    "iso:country":"US",
    "sg:address":"1609 Briar Hill Rd",
    "sg:city":"Gladwyne",
    "sg:classifiers":[
        {
            "category":"Manufacturing",
            "subcategory":"Textiles",
            "type":"Manufacturing & Wholesale Goods"
        },
        {
            "category":"Building & Trades",
            "subcategory":"Construction",
            "type":"Services"
        }
    ],
    "sg:phone":"+1 610 667 4441",
    "sg:postcode":"19035",
    "sg:province":"PA",
    "sg:tags":[
        "tile-wholesale",
        "tile-contractors",
        "manufacturer"
    ],
    "wof:name":"Penn Valley Tile Inc",
    "wof:placetype":"venue"
},
  "geometry": {"coordinates":[-75.267853,40.051869],"type":"Point"}
}