{
  "type": "Feature",
  "properties": {
    "iso:country":"US",
    "sg:address":"112 Atlee St",
    "sg:city":"Johnstown",
    "sg:classifiers":[
        {
            "category":"Freight",
            "type":"Transportation"
        }
    ],
    "sg:phone":"+1   ",
    "sg:postcode":"15905",
    "sg:province":"PA",
    "sg:tags":[
        "general",
        "storage",
        "warehousing"
    ],
    "wof:name":"Ferndale Mini Storage",
    "wof:placetype":"venue"
},
  "geometry": {"coordinates":[-78.913269,40.289158],"type":"Point"}
}