{
  "type": "Feature",
  "properties": {
    "addr:full":"1714 S 2nd St Philadelphia PA 19148",
    "addr:housenumber":"1714",
    "addr:postcode":"19148",
    "addr:street":"S 2Nd St",
    "iso:country":"US",
    "sg:address":"1714 S 2nd St",
    "sg:city":"Philadelphia",
    "sg:classifiers":[
        {
            "category":"Home & Garden",
            "subcategory":"Furniture",
            "type":"Retail Goods"
        }
    ],
    "sg:phone":"+1 215 334 0632",
    "sg:postcode":"19148",
    "sg:province":"PA",
    "sg:tags":[
        "store"
    ],
    "sg:website":"http://www.normansjuvenilefurniture.com/",
    "wof:name":"Norman's",
    "wof:placetype":"venue"
},
  "geometry": {"coordinates":[-75.14949799999999,39.9263],"type":"Point"}
}