{
  "type": "Feature",
  "properties": {
    "iso:country":"US",
    "sg:address":"7952 Temple Rd",
    "sg:city":"Philadelphia",
    "sg:classifiers":[
        {
            "category":"Retail",
            "subcategory":"Laundry & Dry Cleaning",
            "type":"Services"
        }
    ],
    "sg:phone":"+1   ",
    "sg:postcode":"19150",
    "sg:province":"PA",
    "sg:tags":[
        "cleaner"
    ],
    "wof:name":"Ralph Hicks",
    "wof:placetype":"venue"
},
  "geometry": {"coordinates":[-75.165745,40.073086],"type":"Point"}
}