{
  "type": "Feature",
  "properties": {
    "iso:country":"US",
    "sg:address":"305 Furnace Rd",
    "sg:city":"Greenville",
    "sg:classifiers":[
        {
            "category":"Government",
            "subcategory":"Office",
            "type":"Public Place"
        }
    ],
    "sg:phone":"+1 724 253 2706",
    "sg:postcode":"16125",
    "sg:province":"PA",
    "sg:tags":[
        "village"
    ],
    "wof:name":"Township Supervisor",
    "wof:placetype":"venue"
},
  "geometry": {"coordinates":[-80.25837900000001,41.371963],"type":"Point"}
}