{
  "type": "Feature",
  "properties": {
    "addr:full":"758 Onyx Cave Rd Hamburg PA 19526",
    "addr:housenumber":"758",
    "addr:postcode":"19526",
    "addr:street":"Onyx Cave Rd",
    "iso:country":"US",
    "sg:address":"758 Onyx Cave Rd",
    "sg:city":"Hamburg",
    "sg:classifiers":[
        {
            "category":"Building & Trades",
            "subcategory":"Construction",
            "type":"Services"
        }
    ],
    "sg:phone":"+1   ",
    "sg:postcode":"19526",
    "sg:province":"PA",
    "sg:tags":[
        "contractor"
    ],
    "wof:name":"Ed Kehs Construction Inc",
    "wof:placetype":"venue"
},
  "geometry": {"coordinates":[-75.89294,40.515945],"type":"Point"}
}