{
  "type": "Feature",
  "properties": {
    "addr:full":"435 S Walnut St Blairsville PA 15717",
    "addr:housenumber":"435",
    "addr:postcode":"15717",
    "addr:street":"S Walnut St",
    "iso:country":"US",
    "sg:address":"435 S Walnut St",
    "sg:city":"Blairsville",
    "sg:classifiers":[
        {
            "category":"Health Services",
            "subcategory":"Doctor",
            "type":"Services"
        }
    ],
    "sg:phone":"+1 724 459 6240",
    "sg:postcode":"15717",
    "sg:province":"PA",
    "sg:tags":[
        "dentist"
    ],
    "wof:name":"Philip J Losco DMD",
    "wof:placetype":"venue"
},
  "geometry": {"coordinates":[-79.264672,40.424427],"type":"Point"}
}