{
  "type": "Feature",
  "properties": {
    "iso:country":"US",
    "sg:address":"7964 Verree Rd",
    "sg:city":"Philadelphia",
    "sg:classifiers":[
        {
            "category":"Food & Beverages",
            "subcategory":"Groceries & Convenience Stores",
            "type":"Retail Goods"
        }
    ],
    "sg:phone":"+1 215 742 2356",
    "sg:postcode":"19111",
    "sg:province":"PA",
    "sg:tags":[
        "grocer"
    ],
    "wof:name":"Keller Market",
    "wof:placetype":"venue"
},
  "geometry": {"coordinates":[-75.07705199999999,40.071773],"type":"Point"}
}