{
  "type": "Feature",
  "properties": {
    "addr:full":"475 Pennsylvania Ave York PA 17404",
    "addr:housenumber":"475",
    "addr:postcode":"17404",
    "addr:street":"Pennsylvania Ave",
    "iso:country":"US",
    "sg:address":"475 Pennsylvania Ave",
    "sg:city":"York",
    "sg:classifiers":[
        {
            "category":"Bars & Pubs",
            "type":"Food & Drink"
        }
    ],
    "sg:phone":"+1   ",
    "sg:postcode":"17404",
    "sg:province":"PA",
    "sg:tags":[
        "bar"
    ],
    "wof:name":"Coombs Bar and Grill",
    "wof:placetype":"venue"
},
  "geometry": {"coordinates":[-76.74614699999999,39.965838],"type":"Point"}
}