{
  "type": "Feature",
  "properties": {
    "addr:full":"1525 S 24th St Philadelphia PA 19146",
    "addr:housenumber":"1525",
    "addr:postcode":"19146",
    "addr:street":"S 24Th St",
    "iso:country":"US",
    "sg:address":"1525 S 24th St",
    "sg:city":"Philadelphia",
    "sg:classifiers":[
        {
            "category":"Professional",
            "subcategory":"Accounting & Tax Preparation",
            "type":"Services"
        }
    ],
    "sg:phone":"+1   ",
    "sg:postcode":"19146",
    "sg:province":"PA",
    "wof:name":"Blacks Accounting & Tax",
    "wof:placetype":"venue"
},
  "geometry": {"coordinates":[-75.184507,39.933237],"type":"Point"}
}