{
  "type": "Feature",
  "properties": {
    "iso:country":"US",
    "sg:address":"868 W Oak St",
    "sg:city":"Old Forge",
    "sg:classifiers":[
        {
            "category":"Autos & Motor Vehicles",
            "subcategory":"Automobile Sales",
            "type":"Retail Goods"
        }
    ],
    "sg:phone":"+1 570 457 3744",
    "sg:postcode":"18518",
    "sg:province":"PA",
    "sg:tags":[
        "used"
    ],
    "wof:name":"Reliable Auto Sales",
    "wof:placetype":"venue"
},
  "geometry": {"coordinates":[-75.740784,41.380155],"type":"Point"}
}