{
  "type": "Feature",
  "properties": {
    "iso:country":"US",
    "sg:address":"205 Weaver Run Rd",
    "sg:city":"Washington",
    "sg:classifiers":[
        {
            "category":"Farming",
            "subcategory":"Farm",
            "type":"Manufacturing & Wholesale Goods"
        }
    ],
    "sg:phone":"+1 724 267 3400",
    "sg:postcode":"15301",
    "sg:province":"PA",
    "sg:tags":[
        "crop",
        "general"
    ],
    "wof:name":"Lone Pine Llamas",
    "wof:placetype":"venue"
},
  "geometry": {"coordinates":[-80.191923,40.080732],"type":"Point"}
}