{
  "type": "Feature",
  "properties": {
    "iso:country":"US",
    "sg:address":"213 W 3rd St",
    "sg:city":"Greensburg",
    "sg:classifiers":[
        {
            "category":"Social Services",
            "type":"Services"
        }
    ],
    "sg:phone":"+1   ",
    "sg:postcode":"15601",
    "sg:province":"PA",
    "wof:name":"Home Settlements",
    "wof:placetype":"venue"
},
  "geometry": {"coordinates":[-79.54660699999999,40.299754],"type":"Point"}
}