{
  "type": "Feature",
  "properties": {
    "addr:full":"777 Freeport Rd Cheswick PA 15024",
    "addr:housenumber":"777",
    "addr:postcode":"15024",
    "addr:street":"Freeport Rd",
    "iso:country":"US",
    "sg:address":"777 Freeport Rd",
    "sg:city":"Cheswick",
    "sg:classifiers":[
        {
            "category":"Retail",
            "subcategory":"Car Wash",
            "type":"Services"
        }
    ],
    "sg:phone":"+1 724 274 5205",
    "sg:postcode":"15024",
    "sg:province":"PA",
    "sg:tags":[
        "carwash"
    ],
    "wof:name":"Harmar Car Wash",
    "wof:placetype":"venue"
},
  "geometry": {"coordinates":[-79.81783299999999,40.540932],"type":"Point"}
}