{
  "type": "Feature",
  "properties": {
    "iso:country":"US",
    "sg:address":"319 State St",
    "sg:city":"Erie",
    "sg:classifiers":[
        {
            "category":"Restaurant",
            "type":"Food & Drink"
        }
    ],
    "sg:phone":"+1   ",
    "sg:postcode":"16501",
    "sg:province":"PA",
    "wof:name":"Grill A Marketplace",
    "wof:placetype":"venue"
},
  "geometry": {"coordinates":[-80.086568,42.131614],"type":"Point"}
}