{
  "type": "Feature",
  "properties": {
    "iso:country":"US",
    "sg:address":"865 Beaver Dr",
    "sg:city":"Du Bois",
    "sg:classifiers":[
        {
            "category":"Health Services",
            "subcategory":"Doctor",
            "type":"Services"
        }
    ],
    "sg:phone":"+1 814 371 4320",
    "sg:postcode":"15801",
    "sg:province":"PA",
    "sg:tags":[
        "clinic"
    ],
    "wof:name":"Wound Center Of DRMC",
    "wof:placetype":"venue"
},
  "geometry": {"coordinates":[-78.741415,41.121283],"type":"Point"}
}