{
  "type": "Feature",
  "properties": {
    "addr:full":"2300 Lincoln Hwy E Lancaster PA 17602",
    "addr:housenumber":"2300",
    "addr:postcode":"17602",
    "addr:street":"Lincoln Hwy E",
    "iso:country":"US",
    "sg:address":"2300 Lincoln Hwy E",
    "sg:city":"Lancaster",
    "sg:classifiers":[
        {
            "category":"Restaurant",
            "type":"Food & Drink"
        }
    ],
    "sg:phone":"+1 717 299 9449",
    "sg:postcode":"17602",
    "sg:province":"PA",
    "wof:name":"Celebrities",
    "wof:placetype":"venue"
},
  "geometry": {"coordinates":[-76.207159,40.025267],"type":"Point"}
}