{
  "type": "Feature",
  "properties": {
    "iso:country":"US",
    "sg:address":"5050 Pine Hill Rd",
    "sg:city":"Dover",
    "sg:classifiers":[
        {
            "category":"Retail",
            "subcategory":"Auto Repair",
            "type":"Services"
        }
    ],
    "sg:phone":"+1 717 292 5651",
    "sg:postcode":"17315",
    "sg:province":"PA",
    "sg:tags":[
        "general"
    ],
    "wof:name":"Economy Transmissions",
    "wof:placetype":"venue"
},
  "geometry": {"coordinates":[-76.93307900000001,39.974376],"type":"Point"}
}