{
  "type": "Feature",
  "properties": {
    "iso:country":"US",
    "sg:address":"680 Andersen Dr",
    "sg:city":"Pittsburgh",
    "sg:classifiers":[
        {
            "category":"Wholesale",
            "subcategory":"Machinery & Supplies",
            "type":"Manufacturing & Wholesale Goods"
        },
        {
            "category":"Wholesale",
            "subcategory":"Durable Goods & Equipment",
            "type":"Manufacturing & Wholesale Goods"
        }
    ],
    "sg:phone":"+1 412 922 8770",
    "sg:postcode":"15220",
    "sg:province":"PA",
    "sg:tags":[
        "importer",
        "industrial",
        "mfg"
    ],
    "sg:website":"www.marubeni-usa.com",
    "wof:name":"Marubeni America Corporation",
    "wof:placetype":"venue"
},
  "geometry": {"coordinates":[-80.062567,40.421006],"type":"Point"}
}