{
  "type": "Feature",
  "properties": {
    "addr:full":"1336 Bristol Pike Bensalem PA 19020",
    "addr:housenumber":"1336",
    "addr:postcode":"19020",
    "addr:street":"Bristol Pike",
    "iso:country":"US",
    "sg:address":"1336 Bristol Pike",
    "sg:city":"Bensalem",
    "sg:classifiers":[
        {
            "category":"Restaurant",
            "type":"Food & Drink"
        }
    ],
    "sg:phone":"+1 215 633 9233",
    "sg:postcode":"19020",
    "sg:province":"PA",
    "wof:name":"Brown Brown Mccaughan",
    "wof:placetype":"venue"
},
  "geometry": {"coordinates":[-74.963775,40.072646],"type":"Point"}
}