{
  "type": "Feature",
  "properties": {
    "iso:country":"US",
    "sg:address":"1513 Main St",
    "sg:city":"Shoemakersville",
    "sg:classifiers":[
        {
            "category":"Banks & Credit Unions",
            "subcategory":"Bank",
            "type":"Services"
        }
    ],
    "sg:phone":"+1   ",
    "sg:postcode":"19555",
    "sg:province":"PA",
    "sg:tags":[
        "institution",
        "business"
    ],
    "wof:name":"Midatlantic Farm Credit Aca",
    "wof:placetype":"venue"
},
  "geometry": {"coordinates":[-75.97085199999999,40.520472],"type":"Point"}
}