{
  "type": "Feature",
  "properties": {
    "addr:full":"196 W Main St Leola PA 17540",
    "addr:housenumber":"196",
    "addr:postcode":"17540",
    "addr:street":"W Main St",
    "iso:country":"US",
    "sg:address":"196 W Main St",
    "sg:city":"Leola",
    "sg:classifiers":[
        {
            "category":"Wholesale",
            "subcategory":"Durable Goods & Equipment",
            "type":"Manufacturing & Wholesale Goods"
        }
    ],
    "sg:phone":"+1 717 656 2172",
    "sg:postcode":"17540",
    "sg:province":"PA",
    "sg:tags":[
        "representative",
        "manufacturer"
    ],
    "wof:name":"Sherwood Logan & Assoc",
    "wof:placetype":"venue"
},
  "geometry": {"coordinates":[-76.202692,40.086068],"type":"Point"}
}