{
  "type": "Feature",
  "properties": {
    "iso:country":"US",
    "sg:address":"3281 W Liberty Ave",
    "sg:city":"Pittsburgh",
    "sg:classifiers":[
        {
            "category":"Manufacturing",
            "subcategory":"Jewelry",
            "type":"Manufacturing & Wholesale Goods"
        },
        {
            "category":"Shopping",
            "subcategory":"Jewelry",
            "type":"Retail Goods"
        }
    ],
    "sg:phone":"+1 412 344 8838",
    "sg:postcode":"15216",
    "sg:province":"PA",
    "sg:tags":[
        "precious",
        "metal",
        "jeweler"
    ],
    "wof:name":"Style Jewelry Mfg",
    "wof:placetype":"venue"
},
  "geometry": {"coordinates":[-80.026163,40.398334],"type":"Point"}
}