{
  "type": "Feature",
  "properties": {
    "addr:full":"17 S 7th St Allentown PA 18101",
    "addr:housenumber":"17",
    "addr:postcode":"18101",
    "addr:street":"S 7Th St",
    "iso:country":"US",
    "sg:address":"17 S 7th St",
    "sg:city":"Allentown",
    "sg:classifiers":[
        {
            "category":"Government",
            "subcategory":"Office",
            "type":"Public Place"
        }
    ],
    "sg:phone":"+1   ",
    "sg:postcode":"18101",
    "sg:province":"PA",
    "sg:tags":[
        "social"
    ],
    "wof:name":"Human Services-Adult Services",
    "wof:placetype":"venue"
},
  "geometry": {"coordinates":[-75.471555,40.602187],"type":"Point"}
}