{
  "type": "Feature",
  "properties": {
    "iso:country":"US",
    "sg:address":"10 N Beaver St",
    "sg:city":"York",
    "sg:classifiers":[
        {
            "category":"Education",
            "subcategory":"Special Training",
            "type":"Public Place"
        }
    ],
    "sg:phone":"+1 717 848 3200",
    "sg:postcode":"17401",
    "sg:province":"PA",
    "sg:tags":[
        "gallery"
    ],
    "sg:website":"www.yorkarts.org",
    "wof:name":"York Arts",
    "wof:placetype":"venue"
},
  "geometry": {"coordinates":[-76.730036,39.962343],"type":"Point"}
}