{
  "type": "Feature",
  "properties": {
    "addr:full":"301 E City Ave Bala Cynwyd PA 19004",
    "addr:housenumber":"301",
    "addr:postcode":"19004",
    "addr:street":"E City Ave",
    "iso:country":"US",
    "sg:address":"301 E City Ave",
    "sg:city":"Bala Cynwyd",
    "sg:classifiers":[
        {
            "category":"Manufacturing",
            "subcategory":"Tools & Machinery",
            "type":"Manufacturing & Wholesale Goods"
        }
    ],
    "sg:phone":"+1   ",
    "sg:postcode":"19004",
    "sg:province":"PA",
    "sg:tags":[
        "devices",
        "legal",
        "mfg"
    ],
    "wof:name":"Fox Rothschild LLP",
    "wof:placetype":"venue"
},
  "geometry": {"coordinates":[-75.218341,40.005029],"type":"Point"}
}