{
  "type": "Feature",
  "properties": {
    "iso:country":"US",
    "sg:address":"516 Market St",
    "sg:city":"Fallentimber",
    "sg:classifiers":[
        {
            "category":"Professional",
            "subcategory":"Accounting & Tax Preparation",
            "type":"Services"
        }
    ],
    "sg:phone":"+1   ",
    "sg:postcode":"16639",
    "sg:province":"PA",
    "wof:name":"Ljs Services",
    "wof:placetype":"venue"
},
  "geometry": {"coordinates":[-78.48453499999999,40.695065],"type":"Point"}
}