{
  "type": "Feature",
  "properties": {
    "iso:country":"US",
    "sg:address":"340 Mansfield Ave",
    "sg:city":"Pittsburgh",
    "sg:classifiers":[
        {
            "category":"Building & Trades",
            "subcategory":"Construction",
            "type":"Services"
        }
    ],
    "sg:phone":"+1 412 919 1900",
    "sg:postcode":"15220",
    "sg:province":"PA",
    "sg:tags":[
        "general",
        "contractor"
    ],
    "wof:name":"NDC Builders Inc",
    "wof:placetype":"venue"
},
  "geometry": {"coordinates":[-80.051968,40.421627],"type":"Point"}
}