{
  "type": "Feature",
  "properties": {
    "iso:country":"US",
    "sg:address":"1836 McDowell St",
    "sg:city":"Sharon",
    "sg:classifiers":[
        {
            "category":"Professional",
            "type":"Services"
        }
    ],
    "sg:phone":"+1   ",
    "sg:postcode":"16146",
    "sg:province":"PA",
    "wof:name":"Subasic",
    "wof:placetype":"venue"
},
  "geometry": {"coordinates":[-80.47601899999999,41.241525],"type":"Point"}
}