{
  "type": "Feature",
  "properties": {
    "addr:full":"1213 Chester St Reading PA 19601",
    "addr:housenumber":"1213",
    "addr:postcode":"19601",
    "addr:street":"Chester St",
    "iso:country":"US",
    "sg:address":"1213 Chester St",
    "sg:city":"Reading",
    "sg:classifiers":[
        {
            "category":"Organizations",
            "subcategory":"Religious Organization",
            "type":"Services"
        }
    ],
    "sg:phone":"+1 610 736 3777",
    "sg:postcode":"19601",
    "sg:province":"PA",
    "sg:tags":[
        "clergy"
    ],
    "wof:name":"Doris Johnson",
    "wof:placetype":"venue"
},
  "geometry": {"coordinates":[-75.952848,40.351577],"type":"Point"}
}