{
  "type": "Feature",
  "properties": {
    "iso:country":"US",
    "sg:address":"54 Spring St",
    "sg:city":"Wilkes Barre",
    "sg:classifiers":[
        {
            "category":"Restaurant",
            "type":"Food & Drink"
        }
    ],
    "sg:phone":"+1   ",
    "sg:postcode":"18702",
    "sg:province":"PA",
    "sg:tags":[
        "eating"
    ],
    "wof:name":"Cjs Pizza & Subs Inc",
    "wof:placetype":"venue"
},
  "geometry": {"coordinates":[-75.860308,41.245731],"type":"Point"}
}