{
  "type": "Feature",
  "properties": {
    "addr:full":"1237 W 21st St Erie PA 16502",
    "addr:housenumber":"1237",
    "addr:postcode":"16502",
    "addr:street":"W 21St St",
    "iso:country":"US",
    "sg:address":"1237 W 21st St",
    "sg:city":"Erie",
    "sg:classifiers":[
        {
            "category":"Organizations",
            "subcategory":"Religious Organization",
            "type":"Services"
        }
    ],
    "sg:phone":"+1 814 459 0543",
    "sg:postcode":"16502",
    "sg:province":"PA",
    "sg:tags":[
        "church"
    ],
    "wof:name":"St Stephens RC Church",
    "wof:placetype":"venue"
},
  "geometry": {"coordinates":[-80.10324900000001,42.106054],"type":"Point"}
}