{
  "type": "Feature",
  "properties": {
    "addr:full":"2300 Hartel Ave Philadelphia PA 19152",
    "addr:postcode":"2300;19152",
    "addr:street":"Hartel Ave",
    "iso:country":"US",
    "sg:address":"2300 Hartel Ave",
    "sg:city":"Philadelphia",
    "sg:classifiers":[
        {
            "category":"Professional",
            "subcategory":"Computer Services",
            "type":"Services"
        }
    ],
    "sg:phone":"+1 215 331 2618",
    "sg:postcode":"19152",
    "sg:province":"PA",
    "sg:tags":[
        "publisher",
        "developer",
        "software"
    ],
    "wof:name":"Pudgy Panda Computer Solutions",
    "wof:placetype":"venue"
},
  "geometry": {"coordinates":[-75.05397000000001,40.054951],"type":"Point"}
}