{
  "type": "Feature",
  "properties": {
    "iso:country":"US",
    "sg:address":"131 Columbia Ave",
    "sg:city":"Vandergrift",
    "sg:classifiers":[
        {
            "category":"Manufacturing",
            "subcategory":"Tools & Machinery",
            "type":"Manufacturing & Wholesale Goods"
        }
    ],
    "sg:phone":"+1 724 568 3263",
    "sg:postcode":"15690",
    "sg:province":"PA",
    "sg:tags":[
        "equipment",
        "janitor",
        "supply"
    ],
    "wof:name":"Magna-KROM Wholesale",
    "wof:placetype":"venue"
},
  "geometry": {"coordinates":[-79.56127499999999,40.603733],"type":"Point"}
}