{
  "type": "Feature",
  "properties": {
    "addr:full":"9528 Lincoln Hwy Bedford PA 15522",
    "addr:housenumber":"9528",
    "addr:postcode":"15522",
    "addr:street":"Lincoln Hwy",
    "iso:country":"US",
    "sg:address":"9528 Lincoln Hwy",
    "sg:city":"Bedford",
    "sg:classifiers":[
        {
            "category":"Personal",
            "subcategory":"Beauty Salon",
            "type":"Services"
        }
    ],
    "sg:phone":"+1 814 623 8312",
    "sg:postcode":"15522",
    "sg:province":"PA",
    "sg:tags":[
        "manicuring"
    ],
    "wof:name":"Best Nails",
    "wof:placetype":"venue"
},
  "geometry": {"coordinates":[-78.463723,40.018968],"type":"Point"}
}