{
  "type": "Feature",
  "properties": {
    "iso:country":"US",
    "sg:address":"720 Fox St",
    "sg:city":"Franklin",
    "sg:classifiers":[
        {
            "category":"Shopping",
            "type":"Retail Goods"
        },
        {
            "category":"Manufacturing",
            "subcategory":"Printing",
            "type":"Manufacturing & Wholesale Goods"
        }
    ],
    "sg:phone":"+1 814 432 4503",
    "sg:postcode":"16323",
    "sg:province":"PA",
    "sg:tags":[
        "commercial",
        "merchandise"
    ],
    "wof:name":"Walters's Rubber Stamp Shop",
    "wof:placetype":"venue"
},
  "geometry": {"coordinates":[-79.82104,41.41173],"type":"Point"}
}