{
  "type": "Feature",
  "properties": {
    "iso:country":"US",
    "sg:address":"1194 E Earl Rd",
    "sg:city":"East Earl",
    "sg:classifiers":[
        {
            "category":"Food & Beverages",
            "subcategory":"Specialty",
            "type":"Retail Goods"
        }
    ],
    "sg:phone":"+1 717 354 0199",
    "sg:postcode":"17519",
    "sg:province":"PA",
    "sg:tags":[
        "herb"
    ],
    "wof:name":"Al's Herbs",
    "wof:placetype":"venue"
},
  "geometry": {"coordinates":[-76.042856,40.109126],"type":"Point"}
}