{
  "type": "Feature",
  "properties": {
    "iso:country":"US",
    "sg:address":"1269 Liberty St",
    "sg:city":"Franklin",
    "sg:classifiers":[
        {
            "category":"Utilities",
            "subcategory":"Refuse",
            "type":"Services"
        }
    ],
    "sg:phone":"+1   ",
    "sg:postcode":"16323",
    "sg:province":"PA",
    "sg:tags":[
        "system"
    ],
    "wof:name":"Ross George W & Sons Recycl",
    "wof:placetype":"venue"
},
  "geometry": {"coordinates":[-79.83014799999999,41.397673],"type":"Point"}
}