{
  "type": "Feature",
  "properties": {
    "addr:full":"121 South 17th Street Philadelphia PA 19103",
    "addr:housenumber":"121",
    "addr:postcode":"19103",
    "addr:street":"South 17Th Street",
    "iso:country":"US",
    "sg:address":"121 South 17th Street",
    "sg:city":"Philadelphia",
    "sg:classifiers":[
        {
            "category":"Restaurant",
            "type":"Food & Drink"
        }
    ],
    "sg:phone":"+1 875 563 5008",
    "sg:postcode":"19103",
    "sg:province":"PA",
    "sg:tags":[
        "new",
        "american"
    ],
    "sg:website":"www.square1682.com",
    "wof:name":"Square 1682",
    "wof:placetype":"venue"
},
  "geometry": {"coordinates":[-75.16892300000001,39.950606],"type":"Point"}
}