{
  "type": "Feature",
  "properties": {
    "iso:country":"US",
    "sg:address":"69 W Main St",
    "sg:city":"Glen Lyon",
    "sg:classifiers":[
        {
            "category":"Restaurant",
            "type":"Food & Drink"
        }
    ],
    "sg:phone":"+1 570 736 6007",
    "sg:postcode":"18617",
    "sg:province":"PA",
    "sg:tags":[
        "eating"
    ],
    "wof:name":"Glen Lyon Deli & Pizza",
    "wof:placetype":"venue"
},
  "geometry": {"coordinates":[-76.07777299999999,41.173352],"type":"Point"}
}