{
  "type": "Feature",
  "properties": {
    "addr:full":"5503 Babcock Blvd Pittsburgh PA 15237",
    "addr:housenumber":"5503",
    "addr:postcode":"15237",
    "addr:street":"Babcock Blvd",
    "iso:country":"US",
    "sg:address":"5503 Babcock Blvd",
    "sg:city":"Pittsburgh",
    "sg:classifiers":[
        {
            "category":"Retail",
            "subcategory":"Car Wash",
            "type":"Services"
        }
    ],
    "sg:phone":"+1 412 364 6343",
    "sg:postcode":"15237",
    "sg:province":"PA",
    "sg:tags":[
        "carwash",
        "station",
        "gasoline"
    ],
    "wof:name":"Northway Car Wash",
    "wof:placetype":"venue"
},
  "geometry": {"coordinates":[-80.030444,40.545544],"type":"Point"}
}