{
  "type": "Feature",
  "properties": {
    "iso:country":"US",
    "sg:address":"4600 Frankford Ave",
    "sg:city":"Philadelphia",
    "sg:classifiers":[
        {
            "category":"Restaurant",
            "type":"Food & Drink"
        },
        {
            "category":"Food Court",
            "type":"Food & Drink"
        }
    ],
    "sg:phone":"+1 215 533 1254",
    "sg:postcode":"19124",
    "sg:province":"PA",
    "sg:tags":[
        "frozen",
        "plant",
        "locker"
    ],
    "wof:name":"Good N Plenty",
    "wof:placetype":"venue"
},
  "geometry": {"coordinates":[-75.08548,40.014729],"type":"Point"}
}