{
  "type": "Feature",
  "properties": {
    "addr:full":"2501 Kensington Ave Philadelphia PA 19125",
    "addr:housenumber":"2501",
    "addr:postcode":"19125",
    "addr:street":"Kensington Ave",
    "iso:country":"US",
    "sg:address":"2501 Kensington Ave",
    "sg:city":"Philadelphia",
    "sg:classifiers":[
        {
            "category":"Shopping",
            "subcategory":"Clothing, Apparel, & Fashions",
            "type":"Retail Goods"
        }
    ],
    "sg:phone":"+1   ",
    "sg:postcode":"19125",
    "sg:province":"PA",
    "wof:name":"Julio Colon",
    "wof:placetype":"venue"
},
  "geometry": {"coordinates":[-75.12850299999999,39.988172],"type":"Point"}
}