{
  "type": "Feature",
  "properties": {
    "addr:full":"1730 5th Ave New Brighton PA 15066",
    "addr:housenumber":"1730",
    "addr:postcode":"15066",
    "addr:street":"5Th Ave",
    "iso:country":"US",
    "sg:address":"1730 5th Ave",
    "sg:city":"New Brighton",
    "sg:classifiers":[
        {
            "category":"Manufacturing",
            "subcategory":"Apparel",
            "type":"Manufacturing & Wholesale Goods"
        }
    ],
    "sg:phone":"+1 724 846 2600",
    "sg:postcode":"15066",
    "sg:province":"PA",
    "sg:tags":[
        "textile",
        "bag"
    ],
    "wof:name":"Strayer Products Inc",
    "wof:placetype":"venue"
},
  "geometry": {"coordinates":[-80.303805,40.724667],"type":"Point"}
}