{
  "type": "Feature",
  "properties": {
    "iso:country":"US",
    "sg:address":"117 Jennie Dr",
    "sg:city":"Harmony",
    "sg:classifiers":[
        {
            "category":"Professional",
            "subcategory":"Detective & Security Services",
            "type":"Services"
        }
    ],
    "sg:phone":"+1 724 321 4095",
    "sg:postcode":"16037",
    "sg:province":"PA",
    "sg:tags":[
        "information",
        "bureau"
    ],
    "wof:name":"Technicolor Entrprise Services",
    "wof:placetype":"venue"
},
  "geometry": {"coordinates":[-80.154211,40.873508],"type":"Point"}
}