{
  "type": "Feature",
  "properties": {
    "iso:country":"US",
    "sg:address":"1702 Cedar Ave",
    "sg:city":"Scranton",
    "sg:classifiers":[
        {
            "category":"Restaurant",
            "type":"Food & Drink"
        }
    ],
    "sg:phone":"+1 570 558 1430",
    "sg:postcode":"18505",
    "sg:province":"PA",
    "sg:tags":[
        "eating"
    ],
    "wof:name":"Cyber Cookie Cafe",
    "wof:placetype":"venue"
},
  "geometry": {"coordinates":[-75.678179,41.390281],"type":"Point"}
}