{
  "type": "Feature",
  "properties": {
    "addr:full":"419 Mckean Ave Charleroi PA 15022",
    "addr:housenumber":"419",
    "addr:postcode":"15022",
    "addr:street":"Mckean Ave",
    "iso:country":"US",
    "sg:address":"419 Mckean Ave",
    "sg:city":"Charleroi",
    "sg:phone":"+1 724 489 9291",
    "sg:postcode":"15022",
    "sg:province":"PA",
    "wof:name":"New Unique China",
    "wof:placetype":"venue"
},
  "geometry": {"coordinates":[-79.89662300000001,40.137643],"type":"Point"}
}