{
  "type": "Feature",
  "properties": {
    "addr:full":"7875 Mill Rd Elkins Park PA 19027",
    "addr:housenumber":"7875",
    "addr:postcode":"19027",
    "addr:street":"Mill Rd",
    "iso:country":"US",
    "sg:address":"7875 Mill Rd",
    "sg:city":"Elkins Park",
    "sg:classifiers":[
        {
            "category":"Wholesale",
            "subcategory":"Auto Parts",
            "type":"Manufacturing & Wholesale Goods"
        }
    ],
    "sg:phone":"+1 215 635 0889",
    "sg:postcode":"19027",
    "sg:province":"PA",
    "sg:tags":[
        "automobile",
        "rebuilt"
    ],
    "wof:name":"Biello Auto Parts",
    "wof:placetype":"venue"
},
  "geometry": {"coordinates":[-75.12162499999999,40.071385],"type":"Point"}
}