{
  "type": "Feature",
  "properties": {
    "iso:country":"US",
    "sg:address":"660 Stutzman Rd",
    "sg:city":"Indiana",
    "sg:classifiers":[
        {
            "category":"Health Services",
            "subcategory":"Health Practitioner",
            "type":"Services"
        },
        {
            "category":"Health Services",
            "subcategory":"Doctor",
            "type":"Services"
        }
    ],
    "sg:phone":"+1 724 465 9000",
    "sg:postcode":"15701",
    "sg:province":"PA",
    "sg:tags":[
        "physician",
        "surgeon"
    ],
    "wof:name":"Edward M Woodle DO",
    "wof:placetype":"venue"
},
  "geometry": {"coordinates":[-79.161568,40.596146],"type":"Point"}
}