{
  "type": "Feature",
  "properties": {
    "iso:country":"US",
    "sg:address":"483 Brinton Lake Rd",
    "sg:city":"Thornton",
    "sg:classifiers":[
        {
            "category":"Real Estate",
            "subcategory":"Architect",
            "type":"Services"
        }
    ],
    "sg:phone":"+1 610 358 2160",
    "sg:postcode":"19373",
    "sg:province":"PA",
    "wof:name":"Dever Thomas James Architect",
    "wof:placetype":"venue"
},
  "geometry": {"coordinates":[-75.54679899999999,39.905899],"type":"Point"}
}