{
  "type": "Feature",
  "properties": {
    "iso:country":"US",
    "sg:address":"1241 Almira St",
    "sg:city":"Johnstown",
    "sg:classifiers":[
        {
            "category":"Professional",
            "subcategory":"Business Services",
            "type":"Services"
        }
    ],
    "sg:phone":"+1   ",
    "sg:postcode":"15905",
    "sg:province":"PA",
    "wof:name":"Wellspring Group LLC",
    "wof:placetype":"venue"
},
  "geometry": {"coordinates":[-78.922619,40.301556],"type":"Point"}
}