{
  "type": "Feature",
  "properties": {
    "iso:country":"US",
    "sg:address":"500 E Centre St",
    "sg:city":"Ashland",
    "sg:classifiers":[
        {
            "category":"Manufacturing",
            "subcategory":"Tools & Machinery",
            "type":"Manufacturing & Wholesale Goods"
        }
    ],
    "sg:phone":"+1   ",
    "sg:postcode":"17921",
    "sg:province":"PA",
    "sg:tags":[
        "equipment",
        "mfg",
        "compressor"
    ],
    "wof:name":"Goulds Slurry Pump",
    "wof:placetype":"venue"
},
  "geometry": {"coordinates":[-76.324158,40.785282],"type":"Point"}
}