{
  "type": "Feature",
  "properties": {
    "addr:full":"22006 Little Cooley Rd Union City PA 16438",
    "addr:housenumber":"22006",
    "addr:postcode":"16438",
    "addr:street":"Little Cooley Rd",
    "iso:country":"US",
    "sg:address":"22006 Little Cooley Rd",
    "sg:city":"Union City",
    "sg:classifiers":[
        {
            "category":"Building & Trades",
            "subcategory":"Construction",
            "type":"Services"
        }
    ],
    "sg:phone":"+1   ",
    "sg:postcode":"16438",
    "sg:province":"PA",
    "sg:tags":[
        "house"
    ],
    "wof:name":"Brown Construction",
    "wof:placetype":"venue"
},
  "geometry": {"coordinates":[-79.855244,41.783709],"type":"Point"}
}