{
  "type": "Feature",
  "properties": {
    "iso:country":"US",
    "sg:address":"44 Ridge Rd",
    "sg:city":"Phoenixville",
    "sg:classifiers":[
        {
            "category":"Retail",
            "subcategory":"Auto Repair",
            "type":"Services"
        }
    ],
    "sg:phone":"+1 610 933 9215",
    "sg:postcode":"19460",
    "sg:province":"PA",
    "sg:tags":[
        "body",
        "automobile",
        "painting",
        "repairing"
    ],
    "wof:name":"Tim's Auto Body",
    "wof:placetype":"venue"
},
  "geometry": {"coordinates":[-75.529617,40.129391],"type":"Point"}
}