{
  "type": "Feature",
  "properties": {
    "iso:country":"US",
    "sg:address":"106 Orchard St",
    "sg:city":"Mechanicsburg",
    "sg:classifiers":[
        {
            "category":"Insurance",
            "subcategory":"Insurance Agent",
            "type":"Services"
        }
    ],
    "sg:phone":"+1   ",
    "sg:postcode":"17055",
    "sg:province":"PA",
    "wof:name":"McClimans Ins Assoc",
    "wof:placetype":"venue"
},
  "geometry": {"coordinates":[-77.02046,40.207008],"type":"Point"}
}