{
  "type": "Feature",
  "properties": {
    "addr:full":"217 N Whitford Rd Exton PA 19341",
    "addr:housenumber":"217",
    "addr:postcode":"19341",
    "addr:street":"N Whitford Rd",
    "iso:country":"US",
    "sg:address":"217 N Whitford Rd",
    "sg:city":"Exton",
    "sg:classifiers":[
        {
            "category":"Place Of Worship",
            "subcategory":"Church",
            "type":"Public Place"
        },
        {
            "category":"Place Of Worship",
            "type":"Public Place"
        }
    ],
    "sg:phone":"+1 610 363 8042",
    "sg:postcode":"19341",
    "sg:province":"PA",
    "sg:tags":[
        "testament",
        "churches-church",
        "christ",
        "christ-new"
    ],
    "wof:name":"Church Of Christ Of Exton",
    "wof:placetype":"venue"
},
  "geometry": {"coordinates":[-75.65492,40.0408],"type":"Point"}
}