{
  "type": "Feature",
  "properties": {
    "iso:country":"US",
    "sg:address":"256 Meade Ave",
    "sg:city":"Hanover",
    "sg:classifiers":[
        {
            "category":"Banks & Credit Unions",
            "subcategory":"Financial Services",
            "type":"Services"
        }
    ],
    "sg:phone":"+1   ",
    "sg:postcode":"17331",
    "sg:province":"PA",
    "sg:tags":[
        "trust",
        "management"
    ],
    "wof:name":"Chapman Family Trust",
    "wof:placetype":"venue"
},
  "geometry": {"coordinates":[-76.98436100000001,39.794808],"type":"Point"}
}