{
  "type": "Feature",
  "properties": {
    "iso:country":"US",
    "sg:address":"3159 New Butler Rd",
    "sg:city":"New Castle",
    "sg:classifiers":[
        {
            "category":"Autos & Motor Vehicles",
            "subcategory":"Auto Supplies",
            "type":"Retail Goods"
        }
    ],
    "sg:phone":"+1   ",
    "sg:postcode":"16101",
    "sg:province":"PA",
    "sg:tags":[
        "automotive"
    ],
    "wof:name":"Harding Tire Service",
    "wof:placetype":"venue"
},
  "geometry": {"coordinates":[-80.27114899999999,40.97492],"type":"Point"}
}