{
  "type": "Feature",
  "properties": {
    "addr:full":"393 Vanadium Road, Suite 300 Pittsburgh PA 15243",
    "addr:housenumber":"393",
    "addr:postcode":"15243",
    "addr:street":"Vanadium Road Suite 300",
    "iso:country":"US",
    "sg:address":"393 Vanadium Road, Suite 300",
    "sg:city":"Pittsburgh",
    "sg:classifiers":[
        {
            "category":"Professional",
            "subcategory":"Lawyer & Legal Services",
            "type":"Services"
        }
    ],
    "sg:phone":"+1 412 489 1400",
    "sg:postcode":"15243",
    "sg:province":"PA",
    "wof:name":"Davis Davis Attorneys P.C.",
    "wof:placetype":"venue"
},
  "geometry": {"coordinates":[-80.08788199999999,40.370927],"type":"Point"}
}