{
  "type": "Feature",
  "properties": {
    "iso:country":"US",
    "sg:address":"1018 W 9th Ave",
    "sg:city":"King Of Prussia",
    "sg:classifiers":[
        {
            "category":"Manufacturing",
            "subcategory":"Printing",
            "type":"Manufacturing & Wholesale Goods"
        }
    ],
    "sg:phone":"+1 610 205 1000",
    "sg:postcode":"19406",
    "sg:province":"PA",
    "sg:tags":[
        "periodical"
    ],
    "sg:website":"www.mroexpress.com",
    "wof:name":"Reed Business Information",
    "wof:placetype":"venue"
},
  "geometry": {"coordinates":[-75.414458,40.100831],"type":"Point"}
}