{
  "type": "Feature",
  "properties": {
    "iso:country":"US",
    "sg:address":"229 Union St",
    "sg:city":"Royersford",
    "sg:classifiers":[
        {
            "category":"Professional",
            "type":"Services"
        }
    ],
    "sg:phone":"+1   ",
    "sg:postcode":"19468",
    "sg:province":"PA",
    "wof:name":"Todd Cauffman",
    "wof:placetype":"venue"
},
  "geometry": {"coordinates":[-75.53343,40.178838],"type":"Point"}
}