{
  "type": "Feature",
  "properties": {
    "iso:country":"US",
    "sg:address":"380 Old National Pike",
    "sg:city":"Brownsville",
    "sg:classifiers":[
        {
            "category":"Building & Trades",
            "subcategory":"Construction",
            "type":"Services"
        }
    ],
    "sg:phone":"+1   ",
    "sg:postcode":"15417",
    "sg:province":"PA",
    "sg:tags":[
        "concrete",
        "masonry",
        "contractor"
    ],
    "wof:name":"RC Enterprises Inc",
    "wof:placetype":"venue"
},
  "geometry": {"coordinates":[-79.940928,40.04166],"type":"Point"}
}