{
  "type": "Feature",
  "properties": {
    "addr:full":"1414 Pennsylvania Ave Bethlehem PA 18018",
    "addr:housenumber":"1414",
    "addr:postcode":"18018",
    "addr:street":"Pennsylvania Ave",
    "iso:country":"US",
    "sg:address":"1414 Pennsylvania Ave",
    "sg:city":"Bethlehem",
    "sg:classifiers":[
        {
            "category":"Social Services",
            "subcategory":"Child Care",
            "type":"Services"
        },
        {
            "category":"Education",
            "subcategory":"School",
            "type":"Public Place"
        }
    ],
    "sg:phone":"+1 610 868 7302",
    "sg:postcode":"18018",
    "sg:province":"PA",
    "sg:tags":[
        "private",
        "nursery",
        "k-",
        "interest",
        "religious",
        "day"
    ],
    "wof:name":"Central Christian Academy",
    "wof:placetype":"venue"
},
  "geometry": {"coordinates":[-75.420659,40.63295],"type":"Point"}
}