{
  "type": "Feature",
  "properties": {
    "iso:country":"US",
    "sg:address":"4501 Scenic View Cir",
    "sg:city":"Doylestown",
    "sg:classifiers":[
        {
            "category":"Ice Cream",
            "type":"Food & Drink"
        }
    ],
    "sg:phone":"+1 215 489 2666",
    "sg:postcode":"18902",
    "sg:province":"PA",
    "sg:tags":[
        "frozen",
        "dessert"
    ],
    "wof:name":"Emy's & Amy's Water Ice",
    "wof:placetype":"venue"
},
  "geometry": {"coordinates":[-75.0998,40.372589],"type":"Point"}
}