{
  "type": "Feature",
  "properties": {
    "iso:country":"US",
    "sg:address":"1035 Old Ford Rd",
    "sg:city":"Huntingdon Valley",
    "sg:classifiers":[
        {
            "category":"Professional",
            "subcategory":"Accounting & Tax Preparation",
            "type":"Services"
        }
    ],
    "sg:phone":"+1   ",
    "sg:postcode":"19006",
    "sg:province":"PA",
    "wof:name":"William B ONeill CPA",
    "wof:placetype":"venue"
},
  "geometry": {"coordinates":[-75.08551799999999,40.092906],"type":"Point"}
}