{
  "type": "Feature",
  "properties": {
    "iso:country":"US",
    "sg:address":"3718 Penn Ave",
    "sg:city":"Pittsburgh",
    "sg:classifiers":[
        {
            "category":"Restaurant",
            "type":"Food & Drink"
        }
    ],
    "sg:phone":"+1   ",
    "sg:postcode":"15201",
    "sg:province":"PA",
    "sg:tags":[
        "eating"
    ],
    "wof:name":"Perfect Event",
    "wof:placetype":"venue"
},
  "geometry": {"coordinates":[-79.961626,40.464486],"type":"Point"}
}