{
  "type": "Feature",
  "properties": {
    "iso:country":"US",
    "sg:address":"1300 Main St",
    "sg:city":"Aliquippa",
    "sg:classifiers":[
        {
            "category":"Retail",
            "subcategory":"Auto Repair",
            "type":"Services"
        }
    ],
    "sg:phone":"+1 724 375 9976",
    "sg:postcode":"15001",
    "sg:province":"PA",
    "sg:tags":[
        "automobile",
        "inspection"
    ],
    "wof:name":"Roland's Penzoil",
    "wof:placetype":"venue"
},
  "geometry": {"coordinates":[-80.266121,40.607162],"type":"Point"}
}