{
  "type": "Feature",
  "properties": {
    "iso:country":"US",
    "sg:address":"325 Southpointe Blvd Ste 500",
    "sg:city":"Canonsburg",
    "sg:classifiers":[
        {
            "category":"Shopping",
            "subcategory":"Jewelry",
            "type":"Retail Goods"
        }
    ],
    "sg:phone":"+1 724 745 4771",
    "sg:postcode":"15317",
    "sg:province":"PA",
    "sg:website":"www.montijewelers.com",
    "wof:name":"Monti Jewelers",
    "wof:placetype":"venue"
},
  "geometry": {"coordinates":[-80.172495,40.287331],"type":"Point"}
}