{
  "type": "Feature",
  "properties": {
    "iso:country":"US",
    "sg:address":"1051 Allegheny Ave",
    "sg:city":"Oakmont",
    "sg:classifiers":[
        {
            "category":"Wholesale",
            "subcategory":"Machinery & Supplies",
            "type":"Manufacturing & Wholesale Goods"
        }
    ],
    "sg:phone":"+1 412 828 7190",
    "sg:postcode":"15139",
    "sg:province":"PA",
    "sg:tags":[
        "equipment",
        "casket",
        "establishment"
    ],
    "wof:name":"Haven Line Casket Company",
    "wof:placetype":"venue"
},
  "geometry": {"coordinates":[-79.840406,40.526741],"type":"Point"}
}