{
  "type": "Feature",
  "properties": {
    "iso:country":"US",
    "sg:address":"700 N Chester Rd",
    "sg:city":"West Chester",
    "sg:classifiers":[
        {
            "category":"Professional",
            "type":"Services"
        }
    ],
    "sg:phone":"+1   ",
    "sg:postcode":"19380",
    "sg:province":"PA",
    "wof:name":"Donna Sontag",
    "wof:placetype":"venue"
},
  "geometry": {"coordinates":[-75.543162,39.987496],"type":"Point"}
}