{
  "type": "Feature",
  "properties": {
    "iso:country":"US",
    "sg:address":"134 Bicknell Rd",
    "sg:city":"Peach Bottom",
    "sg:classifiers":[
        {
            "category":"Building & Trades",
            "subcategory":"Construction",
            "type":"Services"
        }
    ],
    "sg:phone":"+1   ",
    "sg:postcode":"17563",
    "sg:province":"PA",
    "sg:tags":[
        "contractor"
    ],
    "wof:name":"Spotts Kent D",
    "wof:placetype":"venue"
},
  "geometry": {"coordinates":[-76.20194600000001,39.764744],"type":"Point"}
}