{
  "type": "Feature",
  "properties": {
    "addr:full":"8226 Cadwalader Ave Elkins Park PA 19027",
    "addr:housenumber":"8226",
    "addr:postcode":"19027",
    "addr:street":"Cadwalader Ave",
    "iso:country":"US",
    "sg:address":"8226 Cadwalader Ave",
    "sg:city":"Elkins Park",
    "sg:classifiers":[
        {
            "category":"Health Services",
            "subcategory":"Optometrist",
            "type":"Services"
        }
    ],
    "sg:phone":"+1 215 635 1344",
    "sg:postcode":"19027",
    "sg:province":"PA",
    "wof:name":"Yale Optical Co",
    "wof:placetype":"venue"
},
  "geometry": {"coordinates":[-75.119997,40.077821],"type":"Point"}
}