{
  "type": "Feature",
  "properties": {
    "addr:full":"2200 Castor Ave Philadelphia PA 19134",
    "addr:housenumber":"2200",
    "addr:postcode":"19134",
    "addr:street":"Castor Ave",
    "iso:country":"US",
    "sg:address":"2200 Castor Ave",
    "sg:city":"Philadelphia",
    "sg:classifiers":[
        {
            "category":"Retail",
            "subcategory":"Auto Repair",
            "type":"Services"
        }
    ],
    "sg:phone":"+1 215 535 0510",
    "sg:postcode":"19134",
    "sg:province":"PA",
    "sg:tags":[
        "body",
        "shop"
    ],
    "wof:name":"Century Auto Body Inc",
    "wof:placetype":"venue"
},
  "geometry": {"coordinates":[-75.09670300000001,39.996899],"type":"Point"}
}