{
  "type": "Feature",
  "properties": {
    "iso:country":"US",
    "sg:address":"Rt 202 and St Rd",
    "sg:city":"West Chester",
    "sg:classifiers":[
        {
            "category":"Building & Trades",
            "subcategory":"Cleaning & Sanitation",
            "type":"Services"
        }
    ],
    "sg:phone":"+1 610 883 0404",
    "sg:postcode":"19382",
    "sg:province":"PA",
    "sg:tags":[
        "home"
    ],
    "wof:name":"EverGreen Maids",
    "wof:placetype":"venue"
},
  "geometry": {"coordinates":[-75.57698499999999,39.919713],"type":"Point"}
}