{
  "type": "Feature",
  "properties": {
    "addr:full":"4133 Brownsville Rd Brentwood PA 15227",
    "addr:housenumber":"4133",
    "addr:postcode":"15227",
    "addr:street":"Brownsville Rd",
    "iso:country":"US",
    "sg:address":"4133 Brownsville Rd",
    "sg:city":"Brentwood",
    "sg:classifiers":[
        {
            "category":"Wholesale",
            "subcategory":"Vending Machines",
            "type":"Manufacturing & Wholesale Goods"
        }
    ],
    "sg:phone":"+1 412 884 5077",
    "sg:postcode":"15227",
    "sg:province":"PA",
    "wof:name":"Big Dog Vending",
    "wof:placetype":"venue"
},
  "geometry": {"coordinates":[-79.982879,40.365088],"type":"Point"}
}