{
  "type": "Feature",
  "properties": {
    "addr:full":"809 State Rte 29 Tunkhannock PA 18657",
    "addr:housenumber":"809",
    "addr:postcode":"18657",
    "addr:street":"State Rte 29",
    "iso:country":"US",
    "sg:address":"809 State Rte 29",
    "sg:city":"Tunkhannock",
    "sg:classifiers":[
        {
            "category":"Shopping",
            "subcategory":"Department Store",
            "type":"Retail Goods"
        }
    ],
    "sg:phone":"+1 570 836 8064",
    "sg:postcode":"18657",
    "sg:province":"PA",
    "wof:name":"Wal-Mart",
    "wof:placetype":"venue"
},
  "geometry": {"coordinates":[-75.936536,41.571864],"type":"Point"}
}