{
  "type": "Feature",
  "properties": {
    "iso:country":"US",
    "sg:address":"205 S Hills Vlg",
    "sg:city":"Pittsburgh",
    "sg:classifiers":[
        {
            "category":"Health Services",
            "subcategory":"Doctor",
            "type":"Services"
        },
        {
            "category":"Health Services",
            "subcategory":"Dentist",
            "type":"Services"
        }
    ],
    "sg:phone":"+1 412 833 3922",
    "sg:postcode":"15241",
    "sg:province":"PA",
    "sg:tags":[
        "dentists-oral",
        "physician",
        "maxillofacial",
        "surgeons",
        "surgery",
        "oral",
        "dentists-orthodontists"
    ],
    "wof:name":"Jack Sahlaney Dmd",
    "wof:placetype":"venue"
},
  "geometry": {"coordinates":[-80.05294499999999,40.341448],"type":"Point"}
}