{
  "type": "Feature",
  "properties": {
    "addr:full":"854 Cottman Ave Philadelphia PA 19111",
    "addr:housenumber":"854",
    "addr:postcode":"19111",
    "addr:street":"Cottman Ave",
    "iso:country":"US",
    "sg:address":"854 Cottman Ave",
    "sg:city":"Philadelphia",
    "sg:classifiers":[
        {
            "category":"Retail",
            "subcategory":"Auto Repair",
            "type":"Services"
        }
    ],
    "sg:phone":"+1 215 342 0211",
    "sg:postcode":"19111",
    "sg:province":"PA",
    "sg:tags":[
        "muffler",
        "exhaust",
        "system"
    ],
    "wof:name":"Midas Auto Svc Experts",
    "wof:placetype":"venue"
},
  "geometry": {"coordinates":[-75.084885,40.062029],"type":"Point"}
}