{
  "type": "Feature",
  "properties": {
    "addr:full":"4411 W 12th St Erie PA 16505",
    "addr:housenumber":"4411",
    "addr:postcode":"16505",
    "addr:street":"W 12Th St",
    "iso:country":"US",
    "sg:address":"4411 W 12th St",
    "sg:city":"Erie",
    "sg:classifiers":[
        {
            "category":"Government",
            "subcategory":"Office",
            "type":"Public Place"
        }
    ],
    "sg:phone":"+1   ",
    "sg:postcode":"16505",
    "sg:province":"PA",
    "sg:tags":[
        "sector",
        "field",
        "airway",
        "facility"
    ],
    "wof:name":"System Support Center",
    "wof:placetype":"venue"
},
  "geometry": {"coordinates":[-80.18218400000001,42.084611],"type":"Point"}
}