{
  "type": "Feature",
  "properties": {
    "iso:country":"US",
    "sg:address":"350 Mc Govern Ave",
    "sg:city":"Washington",
    "sg:classifiers":[
        {
            "category":"Government",
            "subcategory":"Office",
            "type":"Public Place"
        }
    ],
    "sg:phone":"+1   ",
    "sg:postcode":"15301",
    "sg:province":"PA",
    "sg:tags":[
        "taxation",
        "finance"
    ],
    "wof:name":"Virginias Income Tax Services",
    "wof:placetype":"venue"
},
  "geometry": {"coordinates":[-80.27079000000001,40.168017],"type":"Point"}
}