{
  "type": "Feature",
  "properties": {
    "iso:country":"US",
    "sg:address":"321 Spruce St Ste 525",
    "sg:city":"Scranton",
    "sg:classifiers":[
        {
            "category":"Organizations",
            "subcategory":"Non-profit Organization",
            "type":"Services"
        }
    ],
    "sg:phone":"+1 570 347 3377",
    "sg:postcode":"18503",
    "sg:province":"PA",
    "sg:tags":[
        "charity",
        "foundations-educational",
        "philanthropic",
        "research"
    ],
    "wof:name":"Catt Family Foundation",
    "wof:placetype":"venue"
},
  "geometry": {"coordinates":[-75.665718,41.409222],"type":"Point"}
}