{
  "type": "Feature",
  "properties": {
    "addr:full":"366 Shartlesville Rd Bernville PA 19506",
    "addr:housenumber":"366",
    "addr:postcode":"19506",
    "addr:street":"Shartlesville Rd",
    "iso:country":"US",
    "sg:address":"366 Shartlesville Rd",
    "sg:city":"Bernville",
    "sg:classifiers":[
        {
            "category":"Farming",
            "subcategory":"Dairy Farm",
            "type":"Manufacturing & Wholesale Goods"
        }
    ],
    "sg:phone":"+1   ",
    "sg:postcode":"19506",
    "sg:province":"PA",
    "wof:name":"Luther Wagner",
    "wof:placetype":"venue"
},
  "geometry": {"coordinates":[-76.11761,40.461212],"type":"Point"}
}