{
  "type": "Feature",
  "properties": {
    "addr:full":"434 Walnut St Reading PA 19601",
    "addr:housenumber":"434",
    "addr:postcode":"19601",
    "addr:street":"Walnut St",
    "iso:country":"US",
    "sg:address":"434 Walnut St",
    "sg:city":"Reading",
    "sg:classifiers":[
        {
            "category":"Organizations",
            "subcategory":"Political Organization",
            "type":"Services"
        }
    ],
    "sg:phone":"+1 610 376 2304",
    "sg:postcode":"19601",
    "sg:province":"PA",
    "wof:name":"Democratic County Committee",
    "wof:placetype":"venue"
},
  "geometry": {"coordinates":[-75.927915,40.338381],"type":"Point"}
}