{
  "type": "Feature",
  "properties": {
    "addr:full":"4174 Woodland Rd Butler PA 16002",
    "addr:housenumber":"4174",
    "addr:postcode":"16002",
    "addr:street":"Woodland Rd",
    "iso:country":"US",
    "sg:address":"4174 Woodland Rd",
    "sg:city":"Butler",
    "sg:classifiers":[
        {
            "category":"Building & Trades",
            "subcategory":"Construction",
            "type":"Services"
        }
    ],
    "sg:phone":"+1   ",
    "sg:postcode":"16002",
    "sg:province":"PA",
    "sg:tags":[
        "home",
        "family",
        "contractor"
    ],
    "wof:name":"Carl Leicher Construction Co",
    "wof:placetype":"venue"
},
  "geometry": {"coordinates":[-79.893418,40.780485],"type":"Point"}
}