{
  "type": "Feature",
  "properties": {
    "iso:country":"US",
    "sg:address":"3600 Grays Ferry Ave",
    "sg:city":"Philadelphia",
    "sg:classifiers":[
        {
            "category":"Professional",
            "subcategory":"Lawyer & Legal Services",
            "type":"Services"
        },
        {
            "category":"Professional",
            "subcategory":"Business Services",
            "type":"Services"
        },
        {
            "category":"Professional",
            "subcategory":"Printing & Photocopies",
            "type":"Services"
        }
    ],
    "sg:phone":"+1 800 463 3339",
    "sg:postcode":"19146",
    "sg:province":"PA",
    "sg:tags":[
        "notary",
        "duplicating",
        "shipping",
        "copying"
    ],
    "sg:website":"www.kinkos.com",
    "wof:name":"Fedex Express Ship Center",
    "wof:placetype":"venue"
},
  "geometry": {"coordinates":[-75.201421,39.940116],"type":"Point"}
}