{
  "type": "Feature",
  "properties": {
    "addr:full":"102 Station Rd Orwigsburg PA 17961",
    "addr:housenumber":"102",
    "addr:postcode":"17961",
    "addr:street":"Station Rd",
    "iso:country":"US",
    "sg:address":"102 Station Rd",
    "sg:city":"Orwigsburg",
    "sg:classifiers":[
        {
            "category":"Building & Trades",
            "subcategory":"Electrical",
            "type":"Services"
        }
    ],
    "sg:phone":"+1   ",
    "sg:postcode":"17961",
    "sg:province":"PA",
    "sg:tags":[
        "electrical",
        "contractor"
    ],
    "wof:name":"Darin Brensinger Elec Contr",
    "wof:placetype":"venue"
},
  "geometry": {"coordinates":[-76.102677,40.661159],"type":"Point"}
}