{
  "type": "Feature",
  "properties": {
    "addr:full":"2321 W Chester Pike Broomall PA 19008",
    "addr:housenumber":"2321",
    "addr:postcode":"19008",
    "addr:street":"W Chester Pike",
    "iso:country":"US",
    "sg:address":"2321 W Chester Pike",
    "sg:city":"Broomall",
    "sg:classifiers":[
        {
            "category":"Real Estate",
            "subcategory":"Real Estate Agent",
            "type":"Services"
        }
    ],
    "sg:phone":"+1   ",
    "sg:postcode":"19008",
    "sg:province":"PA",
    "sg:tags":[
        "cemetery"
    ],
    "wof:name":"SCI",
    "wof:placetype":"venue"
},
  "geometry": {"coordinates":[-75.35087,39.980282],"type":"Point"}
}