{
  "type": "Feature",
  "properties": {
    "iso:country":"US",
    "sg:address":"100 Churchill Rd",
    "sg:city":"Turtle Creek",
    "sg:classifiers":[
        {
            "category":"Professional",
            "type":"Services"
        }
    ],
    "sg:phone":"+1 412 829 2005",
    "sg:postcode":"15145",
    "sg:province":"PA",
    "sg:tags":[
        "establishment"
    ],
    "wof:name":"Edgewood Country Club",
    "wof:placetype":"venue"
},
  "geometry": {"coordinates":[-79.82466100000001,40.418247],"type":"Point"}
}