{
  "type": "Feature",
  "properties": {
    "addr:full":"4700 Wissahickon Ave Philadelphia PA 19144",
    "addr:housenumber":"4700",
    "addr:postcode":"19144",
    "addr:street":"Wissahickon Ave",
    "iso:country":"US",
    "sg:address":"4700 Wissahickon Ave",
    "sg:city":"Philadelphia",
    "sg:classifiers":[
        {
            "category":"Organizations",
            "subcategory":"Non-profit Organization",
            "type":"Services"
        },
        {
            "category":"Social Services",
            "type":"Services"
        }
    ],
    "sg:phone":"+1 215 849 7360",
    "sg:postcode":"19144",
    "sg:province":"PA",
    "wof:name":"Resources For Human Develope",
    "wof:placetype":"venue"
},
  "geometry": {"coordinates":[-75.17124800000001,40.016415],"type":"Point"}
}