{
  "type": "Feature",
  "properties": {
    "iso:country":"US",
    "sg:address":"1717 E Street Rd",
    "sg:city":"Southampton",
    "sg:classifiers":[
        {
            "category":"Organizations",
            "subcategory":"Religious Organization",
            "type":"Services"
        }
    ],
    "sg:phone":"+1 215 355 7264",
    "sg:postcode":"18966",
    "sg:province":"PA",
    "sg:tags":[
        "church"
    ],
    "sg:website":"www.bbc.faithweb.com",
    "wof:name":"Bible Baptist Church",
    "wof:placetype":"venue"
},
  "geometry": {"coordinates":[-75.017522,40.159825],"type":"Point"}
}