{
  "type": "Feature",
  "properties": {
    "iso:country":"US",
    "sg:address":"162 Industrial Park Rd",
    "sg:city":"Ebensburg",
    "sg:classifiers":[
        {
            "category":"Sports & Exercise",
            "subcategory":"Gym",
            "type":"Entertainment"
        }
    ],
    "sg:phone":"+1   ",
    "sg:postcode":"15931",
    "sg:province":"PA",
    "sg:tags":[
        "club",
        "health",
        "racquetball"
    ],
    "wof:name":"Ebensburg Hlth CLB Wllness Ctr",
    "wof:placetype":"venue"
},
  "geometry": {"coordinates":[-78.75402099999999,40.464759],"type":"Point"}
}