{
  "type": "Feature",
  "properties": {
    "addr:full":"115 W Chester Rd West Chester PA 19382",
    "addr:housenumber":"115",
    "addr:postcode":"19382",
    "addr:street":"W Chester Rd",
    "iso:country":"US",
    "sg:address":"115 W Chester Rd",
    "sg:city":"West Chester",
    "sg:classifiers":[
        {
            "category":"Building & Trades",
            "subcategory":"Construction",
            "type":"Services"
        }
    ],
    "sg:phone":"+1 610 692 5353",
    "sg:postcode":"19382",
    "sg:province":"PA",
    "sg:tags":[
        "painter"
    ],
    "wof:name":"White Wash Painters",
    "wof:placetype":"venue"
},
  "geometry": {"coordinates":[-75.544264,39.910766],"type":"Point"}
}