{
  "type": "Feature",
  "properties": {
    "addr:full":"1200 Baltimore Pike Springfield PA 19064",
    "addr:housenumber":"1200",
    "addr:postcode":"19064",
    "addr:street":"Baltimore Pike Springfield",
    "iso:country":"US",
    "sg:address":"1200 Baltimore Pike",
    "sg:city":"Springfield",
    "sg:classifiers":[
        {
            "category":"Food & Beverages",
            "subcategory":"Specialty",
            "type":"Retail Goods"
        }
    ],
    "sg:phone":"+1   ",
    "sg:postcode":"19064",
    "sg:province":"PA",
    "wof:name":"GNC",
    "wof:placetype":"venue"
},
  "geometry": {"coordinates":[-75.35196500000001,39.913268],"type":"Point"}
}