{
  "type": "Feature",
  "properties": {
    "iso:country":"US",
    "sg:address":"300 Barr Harbor Dr",
    "sg:city":"Conshohocken",
    "sg:classifiers":[
        {
            "category":"Health Services",
            "subcategory":"Doctor",
            "type":"Services"
        }
    ],
    "sg:phone":"+1 610 299 6365",
    "sg:postcode":"19428",
    "sg:province":"PA",
    "sg:tags":[
        "physician",
        "surgeon",
        "radiology",
        "surgeons",
        "pediatrics-radiology"
    ],
    "wof:name":"Usarad.Com",
    "wof:placetype":"venue"
},
  "geometry": {"coordinates":[-75.30873099999999,40.068682],"type":"Point"}
}