{
  "type": "Feature",
  "properties": {
    "addr:full":"1316 Brownsville Rd Langhorne PA 19047",
    "addr:housenumber":"1316",
    "addr:postcode":"19047",
    "addr:street":"Brownsville Rd",
    "iso:country":"US",
    "sg:address":"1316 Brownsville Rd",
    "sg:city":"Langhorne",
    "sg:classifiers":[
        {
            "category":"Wholesale",
            "subcategory":"Construction Materials",
            "type":"Manufacturing & Wholesale Goods"
        },
        {
            "category":"Building & Trades",
            "subcategory":"Construction",
            "type":"Services"
        }
    ],
    "sg:phone":"+1 215 891 8144",
    "sg:postcode":"19047",
    "sg:province":"PA",
    "sg:tags":[
        "installs",
        "windows",
        "frame",
        "industrial",
        "door"
    ],
    "wof:name":"Fourth Dimension Door Co Inc",
    "wof:placetype":"venue"
},
  "geometry": {"coordinates":[-74.942159,40.170307],"type":"Point"}
}