{
  "type": "Feature",
  "properties": {
    "addr:full":"215 Broad St Philadelphia PA 19102",
    "addr:housenumber":"215",
    "addr:postcode":"19102",
    "addr:street":"Broad St",
    "iso:country":"US",
    "sg:address":"215 Broad St",
    "sg:city":"Philadelphia",
    "sg:classifiers":[
        {
            "category":"Parking",
            "type":"Transportation"
        }
    ],
    "sg:phone":"+1 215 972 9604",
    "sg:postcode":"19102",
    "sg:province":"PA",
    "sg:tags":[
        "garage"
    ],
    "wof:name":"Patriot Parking Inc",
    "wof:placetype":"venue"
},
  "geometry": {"coordinates":[-75.164467,39.949205],"type":"Point"}
}