{
  "type": "Feature",
  "properties": {
    "iso:country":"US",
    "sg:address":"179 Scott Ave",
    "sg:city":"Washington",
    "sg:classifiers":[
        {
            "category":"Organizations",
            "subcategory":"Religious Organization",
            "type":"Services"
        }
    ],
    "sg:phone":"+1 724 222 1960",
    "sg:postcode":"15301",
    "sg:province":"PA",
    "sg:tags":[
        "church"
    ],
    "wof:name":"Apostolic Gospel Church",
    "wof:placetype":"venue"
},
  "geometry": {"coordinates":[-80.27136299999999,40.168835],"type":"Point"}
}