{
  "type": "Feature",
  "properties": {
    "addr:full":"325 Old Lancaster Rd Devon PA 19333",
    "addr:housenumber":"325",
    "addr:postcode":"19333",
    "addr:street":"Old Lancaster Rd",
    "iso:country":"US",
    "sg:address":"325 Old Lancaster Rd",
    "sg:city":"Devon",
    "sg:classifiers":[
        {
            "category":"Place Of Worship",
            "type":"Public Place"
        },
        {
            "category":"Shopping",
            "subcategory":"Books",
            "type":"Retail Goods"
        },
        {
            "category":"Shopping",
            "type":"Retail Goods"
        },
        {
            "category":"Organizations",
            "subcategory":"Religious Organization",
            "type":"Services"
        }
    ],
    "sg:phone":"+1 610 644 2720",
    "sg:postcode":"19333",
    "sg:province":"PA",
    "sg:tags":[
        "bible",
        "bookstore",
        "church"
    ],
    "sg:website":"http://www.gideons.org",
    "wof:name":"The Gideons International Inc",
    "wof:placetype":"venue"
},
  "geometry": {"coordinates":[-75.429997,40.049503],"type":"Point"}
}