{
  "type": "Feature",
  "properties": {
    "iso:country":"US",
    "sg:address":"200 Lincoln Way W",
    "sg:city":"Mc Connellsburg",
    "sg:classifiers":[
        {
            "category":"Professional",
            "type":"Services"
        }
    ],
    "sg:phone":"+1 717 485 3833",
    "sg:postcode":"17233",
    "sg:province":"PA",
    "sg:tags":[
        "establishment"
    ],
    "wof:name":"D A Washabuagh Enterprises",
    "wof:placetype":"venue"
},
  "geometry": {"coordinates":[-78.00153899999999,39.933397],"type":"Point"}
}