{
  "type": "Feature",
  "properties": {
    "iso:country":"US",
    "sg:address":"2546 Faunce St",
    "sg:city":"Philadelphia",
    "sg:classifiers":[
        {
            "category":"Retail",
            "subcategory":"Laundry & Dry Cleaning",
            "type":"Services"
        },
        {
            "category":"Building & Trades",
            "subcategory":"Cleaning & Sanitation",
            "type":"Services"
        }
    ],
    "sg:phone":"+1 267 536 6451",
    "sg:postcode":"19152",
    "sg:province":"PA",
    "sg:tags":[
        "cleaner",
        "house"
    ],
    "wof:name":"Nick Cleaning Services",
    "wof:placetype":"venue"
},
  "geometry": {"coordinates":[-75.05220300000001,40.050472],"type":"Point"}
}