{
  "type": "Feature",
  "properties": {
    "addr:full":"800 Allegheny Ave Pittsburgh PA 15233",
    "addr:housenumber":"800",
    "addr:postcode":"15233",
    "addr:street":"Allegheny Ave",
    "iso:country":"US",
    "sg:address":"800 Allegheny Ave",
    "sg:city":"Pittsburgh",
    "sg:classifiers":[
        {
            "category":"Organizations",
            "subcategory":"Non-profit Organization",
            "type":"Services"
        }
    ],
    "sg:phone":"+1   ",
    "sg:postcode":"15233",
    "sg:province":"PA",
    "sg:tags":[
        "social"
    ],
    "wof:name":"Pittsburgh Cncl Hghr Edu",
    "wof:placetype":"venue"
},
  "geometry": {"coordinates":[-80.018755,40.451083],"type":"Point"}
}