{
  "type": "Feature",
  "properties": {
    "iso:country":"US",
    "sg:address":"15 S 4th St",
    "sg:city":"Harrisburg",
    "sg:classifiers":[
        {
            "category":"Organizations",
            "subcategory":"Religious Organization",
            "type":"Services"
        }
    ],
    "sg:phone":"+1 717 234 4064",
    "sg:postcode":"17101",
    "sg:province":"PA",
    "sg:tags":[
        "churches-lutheran"
    ],
    "wof:name":"Zion Lutheran Church",
    "wof:placetype":"venue"
},
  "geometry": {"coordinates":[-76.879008,40.261628],"type":"Point"}
}