{
  "type": "Feature",
  "properties": {
    "iso:country":"US",
    "sg:address":"3174 Main St",
    "sg:city":"West Middlesex",
    "sg:classifiers":[
        {
            "category":"Restaurant",
            "type":"Food & Drink"
        }
    ],
    "sg:phone":"+1 724 528 1712",
    "sg:postcode":"16159",
    "sg:province":"PA",
    "wof:name":"Joey's Pizza Shop",
    "wof:placetype":"venue"
},
  "geometry": {"coordinates":[-80.457999,41.173002],"type":"Point"}
}