{
  "type": "Feature",
  "properties": {
    "iso:country":"US",
    "sg:address":"114 Polk Ave",
    "sg:city":"Beaver Falls",
    "sg:classifiers":[
        {
            "category":"Freight",
            "type":"Transportation"
        }
    ],
    "sg:phone":"+1   ",
    "sg:postcode":"15010",
    "sg:province":"PA",
    "sg:tags":[
        "rental",
        "driver",
        "truck"
    ],
    "wof:name":"T L Ferguson Company Inc",
    "wof:placetype":"venue"
},
  "geometry": {"coordinates":[-80.380062,40.770649],"type":"Point"}
}