{
  "type": "Feature",
  "properties": {
    "addr:full":"33 W Brandt Blvd Landisville PA 17538",
    "addr:housenumber":"33",
    "addr:postcode":"17538",
    "addr:street":"W Brandt Blvd",
    "iso:country":"US",
    "sg:address":"33 W Brandt Blvd",
    "sg:city":"Landisville",
    "sg:classifiers":[
        {
            "category":"Professional",
            "type":"Services"
        }
    ],
    "sg:phone":"+1   ",
    "sg:postcode":"17538",
    "sg:province":"PA",
    "wof:name":"Gary Bender",
    "wof:placetype":"venue"
},
  "geometry": {"coordinates":[-76.426061,40.099736],"type":"Point"}
}