{
  "type": "Feature",
  "properties": {
    "addr:full":"2425 Broad Ave Altoona PA 16601",
    "addr:housenumber":"2425",
    "addr:postcode":"16601",
    "addr:street":"Broad Ave",
    "iso:country":"US",
    "sg:address":"2425 Broad Ave",
    "sg:city":"Altoona",
    "sg:classifiers":[
        {
            "category":"Personal",
            "subcategory":"Barber",
            "type":"Services"
        }
    ],
    "sg:phone":"+1 814 943 9233",
    "sg:postcode":"16601",
    "sg:province":"PA",
    "wof:name":"Ted's Unisex Barber Shop, Inc",
    "wof:placetype":"venue"
},
  "geometry": {"coordinates":[-78.410264,40.504556],"type":"Point"}
}