{
  "type": "Feature",
  "properties": {
    "iso:country":"US",
    "sg:address":"78 Spring Ln",
    "sg:city":"Bangor",
    "sg:classifiers":[
        {
            "category":"Building & Trades",
            "subcategory":"Construction",
            "type":"Services"
        }
    ],
    "sg:phone":"+1 610 588 7765",
    "sg:postcode":"18013",
    "sg:province":"PA",
    "sg:tags":[
        "home",
        "contractor",
        "general",
        "residential"
    ],
    "wof:name":"Wood Wright Builders",
    "wof:placetype":"venue"
},
  "geometry": {"coordinates":[-75.216976,40.91528],"type":"Point"}
}