{
  "type": "Feature",
  "properties": {
    "addr:full":"1886 State Rte 21 Masontown PA 15461",
    "addr:housenumber":"1886",
    "addr:postcode":"15461",
    "addr:street":"State Rte 21 Masontown",
    "iso:country":"US",
    "sg:address":"1886 State Rte 21",
    "sg:city":"Masontown",
    "sg:classifiers":[
        {
            "category":"Shopping",
            "subcategory":"Department Store",
            "type":"Retail Goods"
        }
    ],
    "sg:phone":"+1 724 583 9346",
    "sg:postcode":"15461",
    "sg:province":"PA",
    "wof:name":"Dollar General",
    "wof:placetype":"venue"
},
  "geometry": {"coordinates":[-79.89338600000001,39.866122],"type":"Point"}
}