{
  "type": "Feature",
  "properties": {
    "iso:country":"US",
    "sg:address":"50 Robinhood Dr",
    "sg:city":"Etters",
    "sg:classifiers":[
        {
            "category":"Bakery",
            "type":"Food & Drink"
        },
        {
            "category":"Donuts",
            "subcategory":"None",
            "type":"Food & Drink"
        }
    ],
    "sg:phone":"+1 717 938 5544",
    "sg:postcode":"17319",
    "sg:province":"PA",
    "sg:tags":[
        "shop"
    ],
    "sg:website":"http://www.mapledonuts.com",
    "wof:name":"Maple Donuts Inc",
    "wof:placetype":"venue"
},
  "geometry": {"coordinates":[-76.817848,40.152843],"type":"Point"}
}