{
  "type": "Feature",
  "properties": {
    "iso:country":"US",
    "sg:address":"507 E Lancaster Ave",
    "sg:city":"Berwyn",
    "sg:classifiers":[
        {
            "category":"Autos & Motor Vehicles",
            "subcategory":"Fuel & Gas Station",
            "type":"Retail Goods"
        }
    ],
    "sg:phone":"+1 610 644 4090",
    "sg:postcode":"19312",
    "sg:province":"PA",
    "sg:tags":[
        "oil"
    ],
    "wof:name":"Jim's Berwyn Sunoco",
    "wof:placetype":"venue"
},
  "geometry": {"coordinates":[-75.43664099999999,40.04753],"type":"Point"}
}