{
  "type": "Feature",
  "properties": {
    "addr:full":"136 W Lancaster Ave Paoli PA 19301",
    "addr:housenumber":"136",
    "addr:postcode":"19301",
    "addr:street":"W Lancaster Ave",
    "iso:country":"US",
    "sg:address":"136 W Lancaster Ave",
    "sg:city":"Paoli",
    "sg:classifiers":[
        {
            "category":"Real Estate",
            "subcategory":"Real Estate Agent",
            "type":"Services"
        }
    ],
    "sg:phone":"+1 610 647 5588",
    "sg:postcode":"19301",
    "sg:province":"PA",
    "wof:name":"David M Gratz",
    "wof:placetype":"venue"
},
  "geometry": {"coordinates":[-75.48760299999999,40.041724],"type":"Point"}
}