{
  "type": "Feature",
  "properties": {
    "addr:full":"7353 N 20th St Philadelphia PA 19138",
    "addr:housenumber":"7353",
    "addr:postcode":"19138",
    "addr:street":"N 20Th St",
    "iso:country":"US",
    "sg:address":"7353 N 20th St",
    "sg:city":"Philadelphia",
    "sg:classifiers":[
        {
            "category":"Banks & Credit Unions",
            "subcategory":"Investment Brokerage",
            "type":"Services"
        },
        {
            "category":"Professional",
            "subcategory":"Business Services",
            "type":"Services"
        }
    ],
    "sg:phone":"+1 215 224 3480",
    "sg:postcode":"19138",
    "sg:province":"PA",
    "sg:tags":[
        "advisory",
        "financial"
    ],
    "wof:name":"West Oaklane Business Center",
    "wof:placetype":"venue"
},
  "geometry": {"coordinates":[-75.150452,40.067231],"type":"Point"}
}