{
  "type": "Feature",
  "properties": {
    "addr:full":"2735 Briarwood Pl Bethlehem PA 18017",
    "addr:housenumber":"2735",
    "addr:postcode":"18017",
    "addr:street":"Briarwood Pl",
    "iso:country":"US",
    "sg:address":"2735 Briarwood Pl",
    "sg:city":"Bethlehem",
    "sg:classifiers":[
        {
            "category":"Professional",
            "subcategory":"Management & Consulting",
            "type":"Services"
        }
    ],
    "sg:phone":"+1 610 868 4616",
    "sg:postcode":"18017",
    "sg:province":"PA",
    "sg:tags":[
        "marketing",
        "consultant"
    ],
    "wof:name":"William J Maier Inc",
    "wof:placetype":"venue"
},
  "geometry": {"coordinates":[-75.37446799999999,40.650673],"type":"Point"}
}