{
  "type": "Feature",
  "properties": {
    "addr:full":"7130 Mount Airy Ter Philadelphia PA 19119",
    "addr:housenumber":"7130",
    "addr:postcode":"19119",
    "addr:street":"Mount Airy Ter",
    "iso:country":"US",
    "sg:address":"7130 Mount Airy Ter",
    "sg:city":"Philadelphia",
    "sg:classifiers":[
        {
            "category":"Building & Trades",
            "subcategory":"Construction",
            "type":"Services"
        }
    ],
    "sg:phone":"+1 215 806 1463",
    "sg:postcode":"19119",
    "sg:province":"PA",
    "sg:tags":[
        "wallcoverings-installation",
        "wallpaper",
        "painting",
        "contractor"
    ],
    "wof:name":"Surratt Painting Inc.",
    "wof:placetype":"venue"
},
  "geometry": {"coordinates":[-75.206993,40.043298],"type":"Point"}
}