{
  "type": "Feature",
  "properties": {
    "iso:country":"US",
    "sg:address":"4033 Chestnut St",
    "sg:city":"Emmaus",
    "sg:classifiers":[
        {
            "category":"Shopping",
            "subcategory":"Gifts & Souvenirs",
            "type":"Retail Goods"
        }
    ],
    "sg:phone":"+1 610 967 4387",
    "sg:postcode":"18049",
    "sg:province":"PA",
    "sg:tags":[
        "shop"
    ],
    "wof:name":"Over The Rainbow",
    "wof:placetype":"venue"
},
  "geometry": {"coordinates":[-75.52042899999999,40.520326],"type":"Point"}
}