{
  "type": "Feature",
  "properties": {
    "iso:country":"US",
    "sg:address":"108 N Mulberry St",
    "sg:city":"Berwick",
    "sg:classifiers":[
        {
            "category":"Utilities",
            "subcategory":"Telephone",
            "type":"Services"
        },
        {
            "category":"Professional",
            "subcategory":"Computer Services",
            "type":"Services"
        }
    ],
    "sg:phone":"+1 570 759 1753",
    "sg:postcode":"18603",
    "sg:province":"PA",
    "sg:tags":[
        "communication",
        "isp",
        "provider",
        "internet"
    ],
    "sg:website":"http://www.internetplace.net",
    "wof:name":"The Internet Place Inc",
    "wof:placetype":"venue"
},
  "geometry": {"coordinates":[-76.23537,41.053967],"type":"Point"}
}