{
  "type": "Feature",
  "properties": {
    "addr:full":"603 N American St Philadelphia PA 19123",
    "addr:housenumber":"603",
    "addr:postcode":"19123",
    "addr:street":"N American St",
    "iso:country":"US",
    "sg:address":"603 N American St",
    "sg:city":"Philadelphia",
    "sg:classifiers":[
        {
            "category":"Real Estate",
            "subcategory":"Real Estate Services",
            "type":"Services"
        },
        {
            "category":"Professional",
            "subcategory":"Business Services",
            "type":"Services"
        }
    ],
    "sg:phone":"+1 267 324 5078",
    "sg:postcode":"19123",
    "sg:province":"PA",
    "sg:tags":[
        "management",
        "property"
    ],
    "wof:name":"Reliance Property Management Group",
    "wof:placetype":"venue"
},
  "geometry": {"coordinates":[-75.142151,39.961162],"type":"Point"}
}