{
  "type": "Feature",
  "properties": {
    "iso:country":"US",
    "sg:address":"101 E City Ave",
    "sg:city":"Bala Cynwyd",
    "sg:classifiers":[
        {
            "category":"Shopping",
            "subcategory":"Shoes",
            "type":"Retail Goods"
        }
    ],
    "sg:phone":"+1   ",
    "sg:postcode":"19004",
    "sg:province":"PA",
    "wof:name":"Bare Feet",
    "wof:placetype":"venue"
},
  "geometry": {"coordinates":[-75.223629,40.002545],"type":"Point"}
}