{
  "type": "Feature",
  "properties": {
    "addr:full":"3000 Market St Philadelphia PA 19104",
    "addr:housenumber":"3000",
    "addr:postcode":"19104",
    "addr:street":"Market St",
    "iso:country":"US",
    "sg:address":"3000 Market St",
    "sg:city":"Philadelphia",
    "sg:classifiers":[
        {
            "category":"Building & Trades",
            "subcategory":"Cleaning & Sanitation",
            "type":"Services"
        }
    ],
    "sg:phone":"+1 215 222 2900",
    "sg:postcode":"19104",
    "sg:province":"PA",
    "sg:tags":[
        "house"
    ],
    "wof:name":"Bayada Nurses",
    "wof:placetype":"venue"
},
  "geometry": {"coordinates":[-75.185163,39.955055],"type":"Point"}
}