{
  "type": "Feature",
  "properties": {
    "iso:country":"US",
    "sg:address":"800 S Market St",
    "sg:city":"Mechanicsburg",
    "sg:classifiers":[
        {
            "category":"Organizations",
            "subcategory":"Religious Organization",
            "type":"Services"
        }
    ],
    "sg:phone":"+1 717 766 4633",
    "sg:postcode":"17055",
    "sg:province":"PA",
    "sg:website":"http://www.immanuelcma.org",
    "wof:name":"Christian & Missionary Alliance Immanuel",
    "wof:placetype":"venue"
},
  "geometry": {"coordinates":[-77.004143,40.205818],"type":"Point"}
}