{
  "type": "Feature",
  "properties": {
    "addr:full":"15457 Bricker Rd Fort Loudon PA 17224",
    "addr:housenumber":"15457",
    "addr:postcode":"17224",
    "addr:street":"Bricker Rd",
    "iso:country":"US",
    "sg:address":"15457 Bricker Rd",
    "sg:city":"Fort Loudon",
    "sg:classifiers":[
        {
            "category":"Professional",
            "subcategory":"Computer Services",
            "type":"Services"
        }
    ],
    "sg:phone":"+1 717 369 5646",
    "sg:postcode":"17224",
    "sg:province":"PA",
    "wof:name":"Precision Laser Recharge",
    "wof:placetype":"venue"
},
  "geometry": {"coordinates":[-77.9051,39.961717],"type":"Point"}
}