{
  "type": "Feature",
  "properties": {
    "iso:country":"US",
    "sg:address":"1842 Colonial Village Ln",
    "sg:city":"Lancaster",
    "sg:classifiers":[
        {
            "category":"Manufacturing",
            "subcategory":"Printing",
            "type":"Manufacturing & Wholesale Goods"
        }
    ],
    "sg:phone":"+1 717 390 7300",
    "sg:postcode":"17601",
    "sg:province":"PA",
    "sg:tags":[
        "printer"
    ],
    "wof:name":"R R Donnelley & Sons Co",
    "wof:placetype":"venue"
},
  "geometry": {"coordinates":[-76.23367,40.054818],"type":"Point"}
}