{
  "type": "Feature",
  "properties": {
    "iso:country":"US",
    "sg:address":"6324 Woodland Ave",
    "sg:city":"Philadelphia",
    "sg:classifiers":[
        {
            "category":"Shopping",
            "subcategory":"Department Store",
            "type":"Retail Goods"
        }
    ],
    "sg:phone":"+1 215 730 0528",
    "sg:postcode":"19142",
    "sg:province":"PA",
    "sg:tags":[
        "shop"
    ],
    "wof:name":"Millennium Co",
    "wof:placetype":"venue"
},
  "geometry": {"coordinates":[-75.232789,39.926629],"type":"Point"}
}