{
  "type": "Feature",
  "properties": {
    "iso:country":"US",
    "sg:address":"1639 Clearview Dr",
    "sg:city":"Latrobe",
    "sg:classifiers":[
        {
            "category":"Building & Trades",
            "subcategory":"Construction",
            "type":"Services"
        }
    ],
    "sg:phone":"+1 724 537 3858",
    "sg:postcode":"15650",
    "sg:province":"PA",
    "sg:tags":[
        "house",
        "ma"
    ],
    "wof:name":"KLA Inc",
    "wof:placetype":"venue"
},
  "geometry": {"coordinates":[-79.39681299999999,40.276478],"type":"Point"}
}