{
  "type": "Feature",
  "properties": {
    "iso:country":"US",
    "sg:address":"707 2nd St",
    "sg:city":"Towanda",
    "sg:classifiers":[
        {
            "category":"Autos & Motor Vehicles",
            "subcategory":"Automobile Sales",
            "type":"Retail Goods"
        }
    ],
    "sg:phone":"+1 570 265 5630",
    "sg:postcode":"18848",
    "sg:province":"PA",
    "sg:tags":[
        "car",
        "dealer"
    ],
    "wof:name":"Flynn Automotive Inc",
    "wof:placetype":"venue"
},
  "geometry": {"coordinates":[-76.444214,41.760473],"type":"Point"}
}