{
  "type": "Feature",
  "properties": {
    "addr:full":"208 Gleniffer Hill Rd Richboro PA 18954",
    "addr:housenumber":"208",
    "addr:postcode":"18954",
    "addr:street":"Gleniffer Hill Rd",
    "iso:country":"US",
    "sg:address":"208 Gleniffer Hill Rd",
    "sg:city":"Richboro",
    "sg:classifiers":[
        {
            "category":"Health Services",
            "subcategory":"Doctor",
            "type":"Services"
        }
    ],
    "sg:phone":"+1 215 953 1773",
    "sg:postcode":"18954",
    "sg:province":"PA",
    "sg:tags":[
        "physician",
        "surgeon"
    ],
    "wof:name":"Kugler Steven MD",
    "wof:placetype":"venue"
},
  "geometry": {"coordinates":[-74.995842,40.208569],"type":"Point"}
}