{
  "type": "Feature",
  "properties": {
    "iso:country":"US",
    "sg:address":"145 N Main St",
    "sg:city":"Souderton",
    "sg:classifiers":[
        {
            "category":"Bars & Pubs",
            "type":"Food & Drink"
        }
    ],
    "sg:phone":"+1 215 721 1777",
    "sg:postcode":"18964",
    "sg:province":"PA",
    "sg:tags":[
        "drinking"
    ],
    "wof:name":"Hillside Tavern Inc",
    "wof:placetype":"venue"
},
  "geometry": {"coordinates":[-75.32370899999999,40.311151],"type":"Point"}
}