{
  "type": "Feature",
  "properties": {
    "iso:country":"US",
    "sg:address":"365 Mercer Rd",
    "sg:city":"Greenville",
    "sg:classifiers":[
        {
            "category":"Organizations",
            "subcategory":"Community Association",
            "type":"Services"
        }
    ],
    "sg:phone":"+1 724 588 5030",
    "sg:postcode":"16125",
    "sg:province":"PA",
    "sg:tags":[
        "club",
        "private"
    ],
    "sg:website":"http://www.greensofgreenville.com",
    "wof:name":"Greenville Country Club Inc",
    "wof:placetype":"venue"
},
  "geometry": {"coordinates":[-80.36663799999999,41.385509],"type":"Point"}
}