{
  "type": "Feature",
  "properties": {
    "addr:full":"145 Rose Dr Lancaster PA 17602",
    "addr:housenumber":"145",
    "addr:postcode":"17602",
    "addr:street":"Rose Dr",
    "iso:country":"US",
    "sg:address":"145 Rose Dr",
    "sg:city":"Lancaster",
    "sg:classifiers":[
        {
            "category":"Social Services",
            "type":"Services"
        }
    ],
    "sg:phone":"+1   ",
    "sg:postcode":"17602",
    "sg:province":"PA",
    "wof:name":"Marvin L Weaver",
    "wof:placetype":"venue"
},
  "geometry": {"coordinates":[-76.233023,40.038481],"type":"Point"}
}