{
  "type": "Feature",
  "properties": {
    "iso:country":"US",
    "sg:address":"3820 Locust Walk",
    "sg:city":"Philadelphia",
    "sg:classifiers":[
        {
            "category":"Professional",
            "subcategory":"Management & Consulting",
            "type":"Services"
        }
    ],
    "sg:phone":"+1   ",
    "sg:postcode":"19104",
    "sg:province":"PA",
    "sg:tags":[
        "support",
        "facility"
    ],
    "wof:name":"Hamilton Village",
    "wof:placetype":"venue"
},
  "geometry": {"coordinates":[-75.199067,39.952447],"type":"Point"}
}