{
  "type": "Feature",
  "properties": {
    "iso:country":"US",
    "sg:address":"410 Mary Joe Way",
    "sg:city":"Warrington",
    "sg:classifiers":[
        {
            "category":"Professional",
            "subcategory":"Business Services",
            "type":"Services"
        }
    ],
    "sg:phone":"+1 215 491 7126",
    "sg:postcode":"18976",
    "sg:province":"PA",
    "wof:name":"LJZ III Svc",
    "wof:placetype":"venue"
},
  "geometry": {"coordinates":[-75.164536,40.25163],"type":"Point"}
}