{
  "type": "Feature",
  "properties": {
    "iso:country":"US",
    "sg:address":"633 Tioga St",
    "sg:city":"Johnstown",
    "sg:classifiers":[
        {
            "category":"Health Services",
            "subcategory":"Doctor",
            "type":"Services"
        }
    ],
    "sg:phone":"+1 814 535 5312",
    "sg:postcode":"15905",
    "sg:province":"PA",
    "sg:tags":[
        "physician",
        "surgeon"
    ],
    "wof:name":"PRH Corp",
    "wof:placetype":"venue"
},
  "geometry": {"coordinates":[-78.935856,40.319336],"type":"Point"}
}