{
  "type": "Feature",
  "properties": {
    "iso:country":"US",
    "sg:address":"16 Woodlake Dr",
    "sg:city":"Southampton",
    "sg:classifiers":[
        {
            "category":"Health Services",
            "subcategory":"Doctor",
            "type":"Services"
        },
        {
            "category":"Health Services",
            "subcategory":"Chiropractor",
            "type":"Services"
        }
    ],
    "sg:phone":"+1 215 355 1144",
    "sg:postcode":"18966",
    "sg:province":"PA",
    "sg:tags":[
        "physician",
        "surgeon",
        "chiropractic"
    ],
    "wof:name":"Crum, Brian Dr",
    "wof:placetype":"venue"
},
  "geometry": {"coordinates":[-74.976006,40.184297],"type":"Point"}
}