{
  "type": "Feature",
  "properties": {
    "iso:country":"US",
    "sg:address":"1340 Liberty St",
    "sg:city":"Franklin",
    "sg:classifiers":[
        {
            "category":"Restaurant",
            "type":"Food & Drink"
        }
    ],
    "sg:phone":"+1 814 432 8425",
    "sg:postcode":"16323",
    "sg:province":"PA",
    "sg:tags":[
        "banquet",
        "rooms"
    ],
    "wof:name":"Franklin Club",
    "wof:placetype":"venue"
},
  "geometry": {"coordinates":[-79.83356499999999,41.398248],"type":"Point"}
}