{
  "type": "Feature",
  "properties": {
    "iso:country":"US",
    "sg:address":"5205 N Broad St",
    "sg:city":"Philadelphia",
    "sg:classifiers":[
        {
            "category":"Retail",
            "subcategory":"Car Wash",
            "type":"Services"
        }
    ],
    "sg:phone":"+1 215 324 2884",
    "sg:postcode":"19141",
    "sg:province":"PA",
    "wof:name":"Harvey's Car Wash",
    "wof:placetype":"venue"
},
  "geometry": {"coordinates":[-75.14619500000001,40.032232],"type":"Point"}
}