{
  "type": "Feature",
  "properties": {
    "iso:country":"US",
    "sg:address":"4801 Peach St",
    "sg:city":"Erie",
    "sg:classifiers":[
        {
            "category":"Shopping",
            "subcategory":"Clothing, Apparel, & Fashions",
            "type":"Retail Goods"
        }
    ],
    "sg:phone":"+1 814 868 9447",
    "sg:postcode":"16509",
    "sg:province":"PA",
    "wof:name":"Wig Fashions By Carrie",
    "wof:placetype":"venue"
},
  "geometry": {"coordinates":[-80.08895099999999,42.083563],"type":"Point"}
}