{
  "type": "Feature",
  "properties": {
    "iso:country":"US",
    "sg:address":"3 Fox Pond Pl",
    "sg:city":"Spring House",
    "sg:classifiers":[
        {
            "category":"Professional",
            "type":"Services"
        }
    ],
    "sg:phone":"+1   ",
    "sg:postcode":"19477",
    "sg:province":"PA",
    "wof:name":"Decouprints LLC",
    "wof:placetype":"venue"
},
  "geometry": {"coordinates":[-75.236335,40.184562],"type":"Point"}
}