{
  "type": "Feature",
  "properties": {
    "addr:full":"402 Jackson St Jamestown PA 16134",
    "addr:housenumber":"402",
    "addr:postcode":"16134",
    "addr:street":"Jackson St",
    "iso:country":"US",
    "sg:address":"402 Jackson St",
    "sg:city":"Jamestown",
    "sg:classifiers":[
        {
            "category":"Health Services",
            "subcategory":"Doctor",
            "type":"Services"
        }
    ],
    "sg:phone":"+1 724 932 3151",
    "sg:postcode":"16134",
    "sg:province":"PA",
    "sg:tags":[
        "physician",
        "surgeon"
    ],
    "wof:name":"Jamestown Family Practice",
    "wof:placetype":"venue"
},
  "geometry": {"coordinates":[-80.437292,41.485885],"type":"Point"}
}