{
  "type": "Feature",
  "properties": {
    "iso:country":"US",
    "sg:address":"528 Calvert Ave",
    "sg:city":"Pittsburgh",
    "sg:classifiers":[
        {
            "category":"Retail",
            "subcategory":"Repair Shop",
            "type":"Services"
        }
    ],
    "sg:phone":"+1   ",
    "sg:postcode":"15227",
    "sg:province":"PA",
    "sg:tags":[
        "contractor"
    ],
    "wof:name":"Adrian Plumbing & Heating Inc",
    "wof:placetype":"venue"
},
  "geometry": {"coordinates":[-79.975317,40.395614],"type":"Point"}
}