{
  "type": "Feature",
  "properties": {
    "iso:country":"US",
    "sg:address":"3 Appenzell Ter",
    "sg:city":"Reeders",
    "sg:classifiers":[
        {
            "category":"Restaurant",
            "type":"Food & Drink"
        }
    ],
    "sg:phone":"+1 570 688 9905",
    "sg:postcode":"18360",
    "sg:province":"PA",
    "wof:name":"Edge Bar & Grill",
    "wof:placetype":"venue"
},
  "geometry": {"coordinates":[-75.36989699999999,41.000961],"type":"Point"}
}