{
  "type": "Feature",
  "properties": {
    "addr:full":"8 E Broad St West Hazleton PA 18202",
    "addr:housenumber":"8",
    "addr:postcode":"18202",
    "addr:street":"E Broad St",
    "iso:country":"US",
    "sg:address":"8 E Broad St",
    "sg:city":"West Hazleton",
    "sg:classifiers":[
        {
            "category":"Health Services",
            "subcategory":"Health Practitioner",
            "type":"Services"
        }
    ],
    "sg:phone":"+1 570 459 9099",
    "sg:postcode":"18202",
    "sg:province":"PA",
    "sg:tags":[
        "nutritionist"
    ],
    "wof:name":"Vitamins & Organic Foods",
    "wof:placetype":"venue"
},
  "geometry": {"coordinates":[-75.972599,40.953518],"type":"Point"}
}