{
  "type": "Feature",
  "properties": {
    "addr:full":"110 Wood St Cochranton PA 16314",
    "addr:housenumber":"110",
    "addr:postcode":"16314",
    "addr:street":"Wood St",
    "iso:country":"US",
    "sg:address":"110 Wood St",
    "sg:city":"Cochranton",
    "sg:classifiers":[
        {
            "category":"Organizations",
            "subcategory":"Religious Organization",
            "type":"Services"
        }
    ],
    "sg:phone":"+1 814 425 8309",
    "sg:postcode":"16314",
    "sg:province":"PA",
    "sg:tags":[
        "clergy"
    ],
    "wof:name":"C Dale Dupont",
    "wof:placetype":"venue"
},
  "geometry": {"coordinates":[-80.04833499999999,41.517642],"type":"Point"}
}