{
  "type": "Feature",
  "properties": {
    "iso:country":"US",
    "sg:address":"6019 Penn Cir S",
    "sg:city":"Pittsburgh",
    "sg:classifiers":[
        {
            "category":"Real Estate",
            "subcategory":"Real Estate Agent",
            "type":"Services"
        }
    ],
    "sg:phone":"+1 412 661 4771",
    "sg:postcode":"15206",
    "sg:province":"PA",
    "sg:tags":[
        "appraiser"
    ],
    "wof:name":"Ghafoor Realty Co",
    "wof:placetype":"venue"
},
  "geometry": {"coordinates":[-79.924571,40.460163],"type":"Point"}
}