{
  "type": "Feature",
  "properties": {
    "iso:country":"US",
    "sg:address":"462 Fulton St",
    "sg:city":"Waverly",
    "sg:classifiers":[
        {
            "category":"Retail",
            "subcategory":"Funeral Services",
            "type":"Services"
        }
    ],
    "sg:phone":"+1 607 565 3134",
    "sg:postcode":"14892",
    "sg:province":"PA",
    "sg:tags":[
        "director"
    ],
    "wof:name":"Mc Kee Memorial Chapel",
    "wof:placetype":"venue"
},
  "geometry": {"coordinates":[-76.54193100000001,42.002297],"type":"Point"}
}