{
  "type": "Feature",
  "properties": {
    "addr:full":"230 N 7th St Allentown PA 18102",
    "addr:housenumber":"230",
    "addr:postcode":"18102",
    "addr:street":"N 7Th St",
    "iso:country":"US",
    "sg:address":"230 N 7th St",
    "sg:city":"Allentown",
    "sg:classifiers":[
        {
            "category":"Building & Trades",
            "subcategory":"Construction",
            "type":"Services"
        }
    ],
    "sg:phone":"+1   ",
    "sg:postcode":"18102",
    "sg:province":"PA",
    "sg:tags":[
        "contractor"
    ],
    "wof:name":"Hausers Genral Contracting",
    "wof:placetype":"venue"
},
  "geometry": {"coordinates":[-75.473619,40.605989],"type":"Point"}
}