{
  "type": "Feature",
  "properties": {
    "iso:country":"US",
    "sg:address":"91 Troxel Rd",
    "sg:city":"Shoemakersville",
    "sg:classifiers":[
        {
            "category":"Freight",
            "type":"Transportation"
        }
    ],
    "sg:phone":"+1   ",
    "sg:postcode":"19555",
    "sg:province":"PA",
    "sg:tags":[
        "operator",
        "trucking"
    ],
    "wof:name":"Francis J Hall",
    "wof:placetype":"venue"
},
  "geometry": {"coordinates":[-75.937394,40.472313],"type":"Point"}
}