{
  "type": "Feature",
  "properties": {
    "iso:country":"US",
    "sg:address":"311 Grant Ave",
    "sg:city":"Croydon",
    "sg:classifiers":[
        {
            "category":"Retail",
            "subcategory":"Repair Shop",
            "type":"Services"
        }
    ],
    "sg:phone":"+1 215 785 1438",
    "sg:postcode":"19021",
    "sg:province":"PA",
    "sg:tags":[
        "repairing",
        "lawn",
        "mower"
    ],
    "wof:name":"Rick's Lawnmower Repair",
    "wof:placetype":"venue"
},
  "geometry": {"coordinates":[-74.893659,40.094238],"type":"Point"}
}