{
  "type": "Feature",
  "properties": {
    "iso:country":"US",
    "sg:address":"19 Chester St",
    "sg:city":"Chester Heights",
    "sg:classifiers":[
        {
            "category":"Building & Trades",
            "subcategory":"Construction",
            "type":"Services"
        }
    ],
    "sg:phone":"+1 610 459 5010",
    "sg:postcode":"19040",
    "sg:province":"PA",
    "sg:tags":[
        "contractor"
    ],
    "wof:name":"S B Conrad Inc",
    "wof:placetype":"venue"
},
  "geometry": {"coordinates":[-75.109751,40.173824],"type":"Point"}
}