{
  "type": "Feature",
  "properties": {
    "iso:country":"US",
    "sg:address":"4919 N 5th St",
    "sg:city":"Philadelphia",
    "sg:classifiers":[
        {
            "category":"Professional",
            "type":"Services"
        },
        {
            "category":"Shopping",
            "subcategory":"Jewelry",
            "type":"Retail Goods"
        },
        {
            "category":"Bakery",
            "type":"Food & Drink"
        }
    ],
    "sg:phone":"+1 215 457 4958",
    "sg:postcode":"19120",
    "sg:province":"PA",
    "sg:tags":[
        "caterer"
    ],
    "wof:name":"Oteri's Italian Pastries",
    "wof:placetype":"venue"
},
  "geometry": {"coordinates":[-75.132896,40.026299],"type":"Point"}
}