{
  "type": "Feature",
  "properties": {
    "iso:country":"US",
    "sg:address":"914 New Holland Ave",
    "sg:city":"Lancaster",
    "sg:classifiers":[
        {
            "category":"Real Estate",
            "subcategory":"Real Estate Operator",
            "type":"Services"
        }
    ],
    "sg:phone":"+1 717 392 7980",
    "sg:postcode":"17601",
    "sg:province":"PA",
    "sg:tags":[
        "apartment"
    ],
    "wof:name":"Mildor Realty Corp",
    "wof:placetype":"venue"
},
  "geometry": {"coordinates":[-76.288917,40.052198],"type":"Point"}
}