{
  "type": "Feature",
  "properties": {
    "iso:country":"US",
    "sg:address":"101 W College Ave",
    "sg:city":"York",
    "sg:classifiers":[
        {
            "category":"Shopping",
            "subcategory":"Clothing, Apparel, & Fashions",
            "type":"Retail Goods"
        },
        {
            "category":"Shopping",
            "subcategory":"Shoes",
            "type":"Retail Goods"
        }
    ],
    "sg:phone":"+1 717 767 4872",
    "sg:postcode":"17401",
    "sg:province":"PA",
    "sg:tags":[
        "accessory",
        "store",
        "women's"
    ],
    "sg:website":"http://www.paylessshoesource.com",
    "wof:name":"Payless ShoeSource",
    "wof:placetype":"venue"
},
  "geometry": {"coordinates":[-76.727592,39.957668],"type":"Point"}
}