{
  "type": "Feature",
  "properties": {
    "addr:full":"236 Standing Stone Ave Huntingdon PA 16652",
    "addr:housenumber":"236",
    "addr:postcode":"16652",
    "addr:street":"Standing Stone Ave",
    "iso:country":"US",
    "sg:address":"236 Standing Stone Ave",
    "sg:city":"Huntingdon",
    "sg:classifiers":[
        {
            "category":"Government",
            "subcategory":"Office",
            "type":"Public Place"
        }
    ],
    "sg:phone":"+1 814 643 6970",
    "sg:postcode":"16652",
    "sg:province":"PA",
    "sg:tags":[
        "state",
        "security"
    ],
    "wof:name":"Army National Guard Recruiter",
    "wof:placetype":"venue"
},
  "geometry": {"coordinates":[-78.000506,40.488025],"type":"Point"}
}