{
  "type": "Feature",
  "properties": {
    "iso:country":"US",
    "sg:address":"20 Merkle Rd",
    "sg:city":"Bechtelsville",
    "sg:classifiers":[
        {
            "category":"Building & Trades",
            "subcategory":"Construction",
            "type":"Services"
        }
    ],
    "sg:phone":"+1 610 845 8933",
    "sg:postcode":"19505",
    "sg:province":"PA",
    "sg:tags":[
        "general",
        "contractor"
    ],
    "wof:name":"Dane K Masonry",
    "wof:placetype":"venue"
},
  "geometry": {"coordinates":[-75.640191,40.410481],"type":"Point"}
}