{
  "type": "Feature",
  "properties": {
    "iso:country":"US",
    "sg:address":"1320 Irwin Dr",
    "sg:city":"Erie",
    "sg:classifiers":[
        {
            "category":"Building & Trades",
            "subcategory":"Plumbing",
            "type":"Services"
        }
    ],
    "sg:phone":"+1 814 459 8238",
    "sg:postcode":"16505",
    "sg:province":"PA",
    "sg:tags":[
        "conditioning",
        "air",
        "system",
        "contractor"
    ],
    "sg:website":"www.unitedairtemp.com",
    "wof:name":"United Air Temp",
    "wof:placetype":"venue"
},
  "geometry": {"coordinates":[-80.122636,42.104555],"type":"Point"}
}