{
  "type": "Feature",
  "properties": {
    "iso:country":"US",
    "sg:address":"607 Bath Rd",
    "sg:city":"Bristol",
    "sg:classifiers":[
        {
            "category":"Building & Trades",
            "subcategory":"Electrical",
            "type":"Services"
        }
    ],
    "sg:phone":"+1   ",
    "sg:postcode":"19007",
    "sg:province":"PA",
    "sg:tags":[
        "electrical",
        "contractor"
    ],
    "wof:name":"Bab Electrical Design Services",
    "wof:placetype":"venue"
},
  "geometry": {"coordinates":[-74.864667,40.106252],"type":"Point"}
}