{
  "type": "Feature",
  "properties": {
    "addr:full":"203 Lincoln Hwy Fairless Hills PA 19030",
    "addr:housenumber":"203",
    "addr:postcode":"19030",
    "addr:street":"Lincoln Hwy",
    "iso:country":"US",
    "sg:address":"203 Lincoln Hwy",
    "sg:city":"Fairless Hills",
    "sg:classifiers":[
        {
            "category":"Restaurant",
            "type":"Food & Drink"
        }
    ],
    "sg:phone":"+1 215 949 9440",
    "sg:postcode":"19030",
    "sg:province":"PA",
    "wof:name":"Steak & Hoagie Factory Falls",
    "wof:placetype":"venue"
},
  "geometry": {"coordinates":[-74.857648,40.183729],"type":"Point"}
}