{
  "type": "Feature",
  "properties": {
    "iso:country":"US",
    "sg:address":"48 S Cedar St",
    "sg:city":"Nazareth",
    "sg:classifiers":[
        {
            "category":"Organizations",
            "subcategory":"Community Association",
            "type":"Services"
        }
    ],
    "sg:phone":"+1 610 759 7978",
    "sg:postcode":"18064",
    "sg:province":"PA",
    "sg:tags":[
        "club"
    ],
    "wof:name":"Vigilance Hose Co",
    "wof:placetype":"venue"
},
  "geometry": {"coordinates":[-75.30865,40.741749],"type":"Point"}
}