{
  "type": "Feature",
  "properties": {
    "iso:country":"US",
    "sg:address":"1619 Creedmoor Ave",
    "sg:city":"Pittsburgh",
    "sg:classifiers":[
        {
            "category":"Building & Trades",
            "subcategory":"Landscaping Services",
            "type":"Services"
        }
    ],
    "sg:phone":"+1 412 341 9840",
    "sg:postcode":"15226",
    "sg:province":"PA",
    "sg:tags":[
        "landscape",
        "contractor"
    ],
    "wof:name":"R J Henke Construction",
    "wof:placetype":"venue"
},
  "geometry": {"coordinates":[-80.00989300000001,40.386162],"type":"Point"}
}