{
  "type": "Feature",
  "properties": {
    "iso:country":"US",
    "sg:address":"8074 Holbens Valley Rd",
    "sg:city":"New Tripoli",
    "sg:classifiers":[
        {
            "category":"Farming",
            "subcategory":"Livestock Farm",
            "type":"Manufacturing & Wholesale Goods"
        },
        {
            "category":"Recreation",
            "type":"Entertainment"
        }
    ],
    "sg:phone":"+1 610 298 2199",
    "sg:postcode":"18066",
    "sg:province":"PA",
    "sg:tags":[
        "equine",
        "stable"
    ],
    "wof:name":"Blue Gate Farm Inc",
    "wof:placetype":"venue"
},
  "geometry": {"coordinates":[-75.71769999999999,40.633923],"type":"Point"}
}