{
  "type": "Feature",
  "properties": {
    "iso:country":"US",
    "sg:address":"318 Goucher St",
    "sg:city":"Johnstown",
    "sg:classifiers":[
        {
            "category":"Health Services",
            "subcategory":"Doctor",
            "type":"Services"
        }
    ],
    "sg:phone":"+1   ",
    "sg:postcode":"15905",
    "sg:province":"PA",
    "sg:tags":[
        "osteopathic"
    ],
    "wof:name":"Warren Roy W Do",
    "wof:placetype":"venue"
},
  "geometry": {"coordinates":[-78.927696,40.2912],"type":"Point"}
}