{
  "type": "Feature",
  "properties": {
    "iso:country":"US",
    "sg:address":"134 New Castle St",
    "sg:city":"Butler",
    "sg:classifiers":[
        {
            "category":"Shopping",
            "subcategory":"Jewelry",
            "type":"Retail Goods"
        }
    ],
    "sg:phone":"+1 724 287 3278",
    "sg:postcode":"16001",
    "sg:province":"PA",
    "sg:tags":[
        "jeweler"
    ],
    "wof:name":"Gino's Jewelers",
    "wof:placetype":"venue"
},
  "geometry": {"coordinates":[-79.89684099999999,40.861784],"type":"Point"}
}