{
  "type": "Feature",
  "properties": {
    "addr:full":"521 Utopia Rd Apollo PA 15613",
    "addr:housenumber":"521",
    "addr:postcode":"15613",
    "addr:street":"Utopia Rd",
    "iso:country":"US",
    "sg:address":"521 Utopia Rd",
    "sg:city":"Apollo",
    "sg:classifiers":[
        {
            "category":"Building & Trades",
            "subcategory":"Construction",
            "type":"Services"
        }
    ],
    "sg:phone":"+1 724 339 0380",
    "sg:postcode":"15613",
    "sg:province":"PA",
    "sg:tags":[
        "house",
        "nonresidential"
    ],
    "wof:name":"Rosselle Enterprises Inc",
    "wof:placetype":"venue"
},
  "geometry": {"coordinates":[-79.634979,40.518415],"type":"Point"}
}