{
  "type": "Feature",
  "properties": {
    "addr:full":"2101 Cecil B Moore Ave Philadelphia PA 19121",
    "addr:housenumber":"2101",
    "addr:postcode":"19121",
    "addr:street":"Cecil B Moore Ave",
    "iso:country":"US",
    "sg:address":"2101 Cecil B Moore Ave",
    "sg:city":"Philadelphia",
    "sg:classifiers":[
        {
            "category":"Government",
            "subcategory":"Office",
            "type":"Public Place"
        }
    ],
    "sg:phone":"+1 215 685 9844",
    "sg:postcode":"19121",
    "sg:province":"PA",
    "sg:tags":[
        "village"
    ],
    "wof:name":"Mann Center",
    "wof:placetype":"venue"
},
  "geometry": {"coordinates":[-75.17089199999999,39.980371],"type":"Point"}
}