{
  "type": "Feature",
  "properties": {
    "iso:country":"US",
    "sg:address":"912 Mount Royal Blvd",
    "sg:city":"Pittsburgh",
    "sg:classifiers":[
        {
            "category":"Autos & Motor Vehicles",
            "subcategory":"Fuel & Gas Station",
            "type":"Retail Goods"
        }
    ],
    "sg:phone":"+1   ",
    "sg:postcode":"15223",
    "sg:province":"PA",
    "sg:tags":[
        "operator",
        "station"
    ],
    "wof:name":"Mobil",
    "wof:placetype":"venue"
},
  "geometry": {"coordinates":[-79.959075,40.516567],"type":"Point"}
}