{
  "type": "Feature",
  "properties": {
    "iso:country":"US",
    "sg:address":"909 15th St",
    "sg:city":"Elizabeth",
    "sg:classifiers":[
        {
            "category":"Building & Trades",
            "subcategory":"Plumbing",
            "type":"Services"
        }
    ],
    "sg:phone":"+1 412 384 6433",
    "sg:postcode":"15037",
    "sg:province":"PA",
    "sg:tags":[
        "conditioning",
        "air",
        "system",
        "contractor"
    ],
    "wof:name":"Bleil Indoor Air-Heating Co",
    "wof:placetype":"venue"
},
  "geometry": {"coordinates":[-79.887959,40.264123],"type":"Point"}
}