{
  "type": "Feature",
  "properties": {
    "iso:country":"US",
    "sg:address":"507 Main St",
    "sg:city":"Carbondale",
    "sg:classifiers":[
        {
            "category":"Shopping",
            "subcategory":"Clothing, Apparel, & Fashions",
            "type":"Retail Goods"
        }
    ],
    "sg:phone":"+1 570 282 4588",
    "sg:postcode":"18407",
    "sg:province":"PA",
    "wof:name":"Classy Tips & Toes",
    "wof:placetype":"venue"
},
  "geometry": {"coordinates":[-75.524671,41.557389],"type":"Point"}
}