{
  "type": "Feature",
  "properties": {
    "addr:full":"125 Bethlehem Pike Colmar PA 18915",
    "addr:housenumber":"125",
    "addr:postcode":"18915",
    "addr:street":"Bethlehem Pike",
    "iso:country":"US",
    "sg:address":"125 Bethlehem Pike",
    "sg:city":"Colmar",
    "sg:classifiers":[
        {
            "category":"Banks & Credit Unions",
            "subcategory":"Investment Brokerage",
            "type":"Services"
        }
    ],
    "sg:phone":"+1   ",
    "sg:postcode":"18915",
    "sg:province":"PA",
    "sg:tags":[
        "security"
    ],
    "wof:name":"Benjamin J Gulinello",
    "wof:placetype":"venue"
},
  "geometry": {"coordinates":[-75.25590099999999,40.269898],"type":"Point"}
}