{
  "type": "Feature",
  "properties": {
    "iso:country":"US",
    "sg:address":"3401 Chestnut Street",
    "sg:city":"Philadelphia",
    "sg:classifiers":[
        {
            "category":"Shopping",
            "subcategory":"Bicycles & Sporting Goods",
            "type":"Retail Goods"
        }
    ],
    "sg:phone":"+1 215 382 0930",
    "sg:postcode":"19104",
    "sg:province":"PA",
    "sg:tags":[
        "bike",
        "outdoor",
        "gear"
    ],
    "sg:website":"www.ems.com",
    "wof:name":"Eastern Mountain Sports",
    "wof:placetype":"venue"
},
  "geometry": {"coordinates":[-75.191801,39.954365],"type":"Point"}
}