{
  "type": "Feature",
  "properties": {
    "addr:full":"2873 Mercer Butler Pike Grove City PA 16127",
    "addr:housenumber":"2873",
    "addr:postcode":"16127",
    "addr:street":"Mercer Butler Pike",
    "iso:country":"US",
    "sg:address":"2873 Mercer Butler Pike",
    "sg:city":"Grove City",
    "sg:classifiers":[
        {
            "category":"Government",
            "subcategory":"Office",
            "type":"Public Place"
        }
    ],
    "sg:phone":"+1   ",
    "sg:postcode":"16127",
    "sg:province":"PA",
    "sg:tags":[
        "executive"
    ],
    "wof:name":"Liberty Twp",
    "wof:placetype":"venue"
},
  "geometry": {"coordinates":[-80.094337,41.092932],"type":"Point"}
}