{
  "type": "Feature",
  "properties": {
    "addr:full":"3855 Dartmouth Dr Bethlehem PA 18020",
    "addr:housenumber":"3855",
    "addr:postcode":"18020",
    "addr:street":"Dartmouth Dr",
    "iso:country":"US",
    "sg:address":"3855 Dartmouth Dr",
    "sg:city":"Bethlehem",
    "sg:classifiers":[
        {
            "category":"Shopping",
            "subcategory":"Optical Goods",
            "type":"Retail Goods"
        }
    ],
    "sg:phone":"+1 610 954 7999",
    "sg:postcode":"18020",
    "sg:province":"PA",
    "wof:name":"G & G Optical",
    "wof:placetype":"venue"
},
  "geometry": {"coordinates":[-75.323104,40.66709],"type":"Point"}
}