{
  "type": "Feature",
  "properties": {
    "iso:country":"US",
    "sg:address":"1218 W Broad St",
    "sg:city":"Quakertown",
    "sg:classifiers":[
        {
            "category":"Building & Trades",
            "subcategory":"Construction",
            "type":"Services"
        }
    ],
    "sg:phone":"+1 215 536 0560",
    "sg:postcode":"18951",
    "sg:province":"PA",
    "sg:tags":[
        "contractor"
    ],
    "wof:name":"Bud Cameron General Contr",
    "wof:placetype":"venue"
},
  "geometry": {"coordinates":[-75.35056899999999,40.442383],"type":"Point"}
}