{
  "type": "Feature",
  "properties": {
    "iso:country":"US",
    "sg:address":"8803 Max Way",
    "sg:city":"Breinigsville",
    "sg:classifiers":[
        {
            "category":"Wholesale",
            "subcategory":"Non-durable Goods",
            "type":"Manufacturing & Wholesale Goods"
        }
    ],
    "sg:phone":"+1   ",
    "sg:postcode":"18031",
    "sg:province":"PA",
    "wof:name":"Affordable Treasurers",
    "wof:placetype":"venue"
},
  "geometry": {"coordinates":[-75.63518999999999,40.546295],"type":"Point"}
}