{
  "type": "Feature",
  "properties": {
    "addr:full":"2109 4th Ave Altoona PA 16602",
    "addr:housenumber":"2109",
    "addr:postcode":"16602",
    "addr:street":"4Th Ave",
    "iso:country":"US",
    "sg:address":"2109 4th Ave",
    "sg:city":"Altoona",
    "sg:classifiers":[
        {
            "category":"Building & Trades",
            "subcategory":"Construction",
            "type":"Services"
        }
    ],
    "sg:phone":"+1   ",
    "sg:postcode":"16602",
    "sg:province":"PA",
    "sg:tags":[
        "house"
    ],
    "wof:name":"Rmd Construction",
    "wof:placetype":"venue"
},
  "geometry": {"coordinates":[-78.402089,40.502755],"type":"Point"}
}