{
  "type": "Feature",
  "properties": {
    "addr:full":"632 Lynes Rd Dillsburg PA 17019",
    "addr:housenumber":"632",
    "addr:postcode":"17019",
    "addr:street":"Lynes Rd",
    "iso:country":"US",
    "sg:address":"632 Lynes Rd",
    "sg:city":"Dillsburg",
    "sg:classifiers":[
        {
            "category":"Shopping",
            "subcategory":"Party Supplies",
            "type":"Retail Goods"
        }
    ],
    "sg:phone":"+1 717 432 5647",
    "sg:postcode":"17019",
    "sg:province":"PA",
    "sg:tags":[
        "tents-rental"
    ],
    "wof:name":"Wonders Ltd",
    "wof:placetype":"venue"
},
  "geometry": {"coordinates":[-77.046331,40.136904],"type":"Point"}
}