{
  "type": "Feature",
  "properties": {
    "addr:full":"109 Reed Rd Hughesville PA 17737",
    "addr:housenumber":"109",
    "addr:postcode":"17737",
    "addr:street":"Reed Rd",
    "iso:country":"US",
    "sg:address":"109 Reed Rd",
    "sg:city":"Hughesville",
    "sg:classifiers":[
        {
            "category":"Marine",
            "type":"Transportation"
        }
    ],
    "sg:phone":"+1   ",
    "sg:postcode":"17737",
    "sg:province":"PA",
    "sg:tags":[
        "rental",
        "boat"
    ],
    "wof:name":"Bubbs Canoe & Ski Rental",
    "wof:placetype":"venue"
},
  "geometry": {"coordinates":[-76.604308,41.251997],"type":"Point"}
}