{
  "type": "Feature",
  "properties": {
    "iso:country":"US",
    "sg:address":"1121 Dreher Ave",
    "sg:city":"Stroudsburg",
    "sg:classifiers":[
        {
            "category":"Wholesale",
            "subcategory":"Electrical",
            "type":"Manufacturing & Wholesale Goods"
        }
    ],
    "sg:phone":"+1   ",
    "sg:postcode":"18360",
    "sg:province":"PA",
    "sg:tags":[
        "supply"
    ],
    "wof:name":"Branch 5a",
    "wof:placetype":"venue"
},
  "geometry": {"coordinates":[-75.20625800000001,40.980442],"type":"Point"}
}