{
  "type": "Feature",
  "properties": {
    "iso:country":"US",
    "sg:address":"138 E Main St",
    "sg:city":"Somerset",
    "sg:classifiers":[
        {
            "category":"Health Services",
            "subcategory":"Nursing And Care Facility",
            "type":"Services"
        }
    ],
    "sg:phone":"+1 814 445 9718",
    "sg:postcode":"15501",
    "sg:province":"PA",
    "sg:tags":[
        "personal",
        "home"
    ],
    "sg:website":"www.easylivingestates.com",
    "wof:name":"Easy Living Estates Inc",
    "wof:placetype":"venue"
},
  "geometry": {"coordinates":[-79.077533,40.008424],"type":"Point"}
}