{
  "type": "Feature",
  "properties": {
    "addr:full":"1010 12th St Altoona PA 16601",
    "addr:housenumber":"1010",
    "addr:postcode":"16601",
    "addr:street":"12Th St",
    "iso:country":"US",
    "sg:address":"1010 12th St",
    "sg:city":"Altoona",
    "sg:classifiers":[
        {
            "category":"Real Estate",
            "subcategory":"Real Estate Operator",
            "type":"Services"
        }
    ],
    "sg:phone":"+1 814 944 4055",
    "sg:postcode":"16601",
    "sg:province":"PA",
    "sg:tags":[
        "management"
    ],
    "wof:name":"Ida Tower",
    "wof:placetype":"venue"
},
  "geometry": {"coordinates":[-78.400684,40.515678],"type":"Point"}
}