{
  "type": "Feature",
  "properties": {
    "iso:country":"US",
    "sg:address":"53 Darby Rd",
    "sg:city":"Paoli",
    "sg:classifiers":[
        {
            "category":"Insurance",
            "subcategory":"Insurance Agent",
            "type":"Services"
        }
    ],
    "sg:phone":"+1 610 993 8383",
    "sg:postcode":"19301",
    "sg:province":"PA",
    "sg:tags":[
        "consultant",
        "analyst"
    ],
    "wof:name":"Joseph Super",
    "wof:placetype":"venue"
},
  "geometry": {"coordinates":[-75.48163,40.040643],"type":"Point"}
}