{
  "type": "Feature",
  "properties": {
    "addr:full":"3353 Gun Club Rd Nazareth PA 18064",
    "addr:housenumber":"3353",
    "addr:postcode":"18064",
    "addr:street":"Gun Club Rd",
    "iso:country":"US",
    "sg:address":"3353 Gun Club Rd",
    "sg:city":"Nazareth",
    "sg:classifiers":[
        {
            "category":"Professional",
            "subcategory":"Research",
            "type":"Services"
        }
    ],
    "sg:phone":"+1 610 759 0200",
    "sg:postcode":"18064",
    "sg:province":"PA",
    "sg:tags":[
        "environmental",
        "ecological"
    ],
    "sg:website":"www.jmtenv.com",
    "wof:name":"JMT Environmental Techs Inc",
    "wof:placetype":"venue"
},
  "geometry": {"coordinates":[-75.36010400000001,40.723491],"type":"Point"}
}