{
  "type": "Feature",
  "properties": {
    "addr:full":"1901 Lincoln Hwy North Versailles PA 15137",
    "addr:housenumber":"1901",
    "addr:postcode":"15137",
    "addr:street":"Lincoln Hwy",
    "iso:country":"US",
    "sg:address":"1901 Lincoln Hwy",
    "sg:city":"North Versailles",
    "sg:classifiers":[
        {
            "category":"Shopping",
            "subcategory":"Pharmacy",
            "type":"Retail Goods"
        }
    ],
    "sg:phone":"+1   ",
    "sg:postcode":"15137",
    "sg:province":"PA",
    "wof:name":"Kmart Pharmacies Inc",
    "wof:placetype":"venue"
},
  "geometry": {"coordinates":[-79.77874,40.367361],"type":"Point"}
}