{
  "type": "Feature",
  "properties": {
    "iso:country":"US",
    "sg:address":"27 3rd Ave",
    "sg:city":"Union City",
    "sg:classifiers":[
        {
            "category":"Travel",
            "subcategory":"Hotels & Motels",
            "type":"Entertainment"
        }
    ],
    "sg:phone":"+1 814 438 3953",
    "sg:postcode":"16438",
    "sg:province":"PA",
    "sg:tags":[
        "operation"
    ],
    "wof:name":"Strawberry Inn",
    "wof:placetype":"venue"
},
  "geometry": {"coordinates":[-79.850762,41.899093],"type":"Point"}
}