{
  "type": "Feature",
  "properties": {
    "iso:country":"US",
    "sg:address":"5909 N 5th St",
    "sg:city":"Philadelphia",
    "sg:classifiers":[
        {
            "category":"Restaurant",
            "type":"Food & Drink"
        }
    ],
    "sg:phone":"+1 215 548 8340",
    "sg:postcode":"19120",
    "sg:province":"PA",
    "sg:tags":[
        "eating"
    ],
    "wof:name":"Canaan Restaurant",
    "wof:placetype":"venue"
},
  "geometry": {"coordinates":[-75.129277,40.041668],"type":"Point"}
}