{
  "type": "Feature",
  "properties": {
    "iso:country":"US",
    "sg:address":"222 N Reading Rd",
    "sg:city":"Ephrata",
    "sg:classifiers":[
        {
            "category":"Travel",
            "subcategory":"Hotels & Motels",
            "type":"Entertainment"
        }
    ],
    "sg:phone":"+1 717 733 1237",
    "sg:postcode":"17522",
    "sg:province":"PA",
    "sg:tags":[
        "operation",
        "drinking"
    ],
    "wof:name":"Dutchmaid Motel Inc",
    "wof:placetype":"venue"
},
  "geometry": {"coordinates":[-76.180403,40.189402],"type":"Point"}
}