{
  "type": "Feature",
  "properties": {
    "addr:full":"1833 Tilton Dr Pittsburgh PA 15241",
    "addr:housenumber":"1833",
    "addr:postcode":"15241",
    "addr:street":"Tilton Dr",
    "iso:country":"US",
    "sg:address":"1833 Tilton Dr",
    "sg:city":"Pittsburgh",
    "sg:classifiers":[
        {
            "category":"Banks & Credit Unions",
            "subcategory":"Bank",
            "type":"Services"
        }
    ],
    "sg:phone":"+1 412 220 0344",
    "sg:postcode":"15241",
    "sg:province":"PA",
    "sg:tags":[
        "loan",
        "real estate"
    ],
    "wof:name":"A & B Mortgage Co",
    "wof:placetype":"venue"
},
  "geometry": {"coordinates":[-80.078211,40.34941],"type":"Point"}
}