{
  "type": "Feature",
  "properties": {
    "iso:country":"US",
    "sg:address":"42 W 5th St",
    "sg:city":"Lansdale",
    "sg:classifiers":[
        {
            "category":"Travel",
            "subcategory":"Travel Agent",
            "type":"Entertainment"
        }
    ],
    "sg:phone":"+1   ",
    "sg:postcode":"19446",
    "sg:province":"PA",
    "sg:tags":[
        "agency"
    ],
    "wof:name":"Travel For You",
    "wof:placetype":"venue"
},
  "geometry": {"coordinates":[-75.28196800000001,40.244973],"type":"Point"}
}