{
  "type": "Feature",
  "properties": {
    "iso:country":"US",
    "sg:address":"3002 Old Clairton Rd",
    "sg:city":"Clairton",
    "sg:classifiers":[
        {
            "category":"Retail",
            "subcategory":"Auto Repair",
            "type":"Services"
        }
    ],
    "sg:phone":"+1 412 384 2024",
    "sg:postcode":"15025",
    "sg:province":"PA",
    "wof:name":"Bill's Automotive",
    "wof:placetype":"venue"
},
  "geometry": {"coordinates":[-79.918297,40.2943],"type":"Point"}
}