{
  "type": "Feature",
  "properties": {
    "addr:full":"733 Walnut St Philadelphia PA 19106",
    "addr:housenumber":"733",
    "addr:postcode":"19106",
    "addr:street":"Walnut St",
    "iso:country":"US",
    "sg:address":"733 Walnut St",
    "sg:city":"Philadelphia",
    "sg:classifiers":[
        {
            "category":"Organizations",
            "subcategory":"Non-profit Organization",
            "type":"Services"
        }
    ],
    "sg:phone":"+1   ",
    "sg:postcode":"19106",
    "sg:province":"PA",
    "sg:tags":[
        "social"
    ],
    "wof:name":"AARP",
    "wof:placetype":"venue"
},
  "geometry": {"coordinates":[-75.15407500000001,39.948142],"type":"Point"}
}