{
  "type": "Feature",
  "properties": {
    "addr:full":"19 Llandaff Rd Havertown PA 19083",
    "addr:housenumber":"19",
    "addr:postcode":"19083",
    "addr:street":"Llandaff Rd",
    "iso:country":"US",
    "sg:address":"19 Llandaff Rd",
    "sg:city":"Havertown",
    "sg:classifiers":[
        {
            "category":"Building & Trades",
            "subcategory":"Electrical",
            "type":"Services"
        }
    ],
    "sg:phone":"+1   ",
    "sg:postcode":"19083",
    "sg:province":"PA",
    "sg:tags":[
        "computer",
        "electrical",
        "contractor"
    ],
    "wof:name":"T E N Company",
    "wof:placetype":"venue"
},
  "geometry": {"coordinates":[-75.294031,39.969731],"type":"Point"}
}