{
  "type": "Feature",
  "properties": {
    "iso:country":"US",
    "sg:address":"7906 Frankstown Ave",
    "sg:city":"Pittsburgh",
    "sg:classifiers":[
        {
            "category":"Bars & Pubs",
            "type":"Food & Drink"
        }
    ],
    "sg:phone":"+1 412 244 6788",
    "sg:postcode":"15221",
    "sg:province":"PA",
    "wof:name":"Gandy's Lounge",
    "wof:placetype":"venue"
},
  "geometry": {"coordinates":[-79.884501,40.455317],"type":"Point"}
}