{
  "type": "Feature",
  "properties": {
    "addr:full":"210 S 3rd St Philadelphia PA 19106",
    "addr:housenumber":"210",
    "addr:postcode":"19106",
    "addr:street":"S 3Rd St",
    "iso:country":"US",
    "sg:address":"210 S 3rd St",
    "sg:city":"Philadelphia",
    "sg:classifiers":[
        {
            "category":"Restaurant",
            "type":"Food & Drink"
        }
    ],
    "sg:phone":"+1 215 925 3637",
    "sg:postcode":"19106",
    "sg:province":"PA",
    "wof:name":"Carousel Shoppe",
    "wof:placetype":"venue"
},
  "geometry": {"coordinates":[-75.146567,39.946927],"type":"Point"}
}