{
  "type": "Feature",
  "properties": {
    "iso:country":"US",
    "sg:address":"2222 N Front St",
    "sg:city":"Philadelphia",
    "sg:classifiers":[
        {
            "category":"Building & Trades",
            "subcategory":"Equipment Rental",
            "type":"Services"
        }
    ],
    "sg:phone":"+1 215 668 8455",
    "sg:postcode":"19133",
    "sg:province":"PA",
    "sg:tags":[
        "yard",
        "leasing",
        "store"
    ],
    "wof:name":"Riosource Rentals",
    "wof:placetype":"venue"
},
  "geometry": {"coordinates":[-75.13246599999999,39.983606],"type":"Point"}
}