{
  "type": "Feature",
  "properties": {
    "addr:full":"290 Northgate Dr Warrendale PA 15086",
    "addr:housenumber":"290",
    "addr:postcode":"15086",
    "addr:street":"Northgate Dr",
    "iso:country":"US",
    "sg:address":"290 Northgate Dr",
    "sg:city":"Warrendale",
    "sg:classifiers":[
        {
            "category":"Recreation",
            "subcategory":"Marina",
            "type":"Entertainment"
        }
    ],
    "sg:phone":"+1 724 935 5552",
    "sg:postcode":"15086",
    "sg:province":"PA",
    "sg:tags":[
        "repairing",
        "boat"
    ],
    "wof:name":"Prop Shop",
    "wof:placetype":"venue"
},
  "geometry": {"coordinates":[-80.08016000000001,40.65482],"type":"Point"}
}