{
  "type": "Feature",
  "properties": {
    "addr:full":"111 Presidential Blvd Bala Cynwyd PA 19004",
    "addr:housenumber":"111",
    "addr:postcode":"19004",
    "addr:street":"Presidential Blvd",
    "iso:country":"US",
    "sg:address":"111 Presidential Blvd",
    "sg:city":"Bala Cynwyd",
    "sg:classifiers":[
        {
            "category":"Professional",
            "subcategory":"Lawyer & Legal Services",
            "type":"Services"
        }
    ],
    "sg:phone":"+1   ",
    "sg:postcode":"19004",
    "sg:province":"PA",
    "wof:name":"Horowitz Sherry L",
    "wof:placetype":"venue"
},
  "geometry": {"coordinates":[-75.21212,40.011347],"type":"Point"}
}