{
  "type": "Feature",
  "properties": {
    "addr:full":"385 State Rte 368 Parker PA 16049",
    "addr:housenumber":"385",
    "addr:postcode":"16049",
    "addr:street":"State Rte 368",
    "iso:country":"US",
    "sg:address":"385 State Rte 368",
    "sg:city":"Parker",
    "sg:classifiers":[
        {
            "category":"Organizations",
            "subcategory":"Religious Organization",
            "type":"Services"
        }
    ],
    "sg:phone":"+1 724 791 2274",
    "sg:postcode":"16049",
    "sg:province":"PA",
    "sg:tags":[
        "church"
    ],
    "wof:name":"Church Of God Of Prophecy",
    "wof:placetype":"venue"
},
  "geometry": {"coordinates":[-79.671115,41.101531],"type":"Point"}
}