{
  "type": "Feature",
  "properties": {
    "addr:full":"265 Mulberry St Mifflinburg PA 17844",
    "addr:housenumber":"265",
    "addr:postcode":"17844",
    "addr:street":"Mulberry St",
    "iso:country":"US",
    "sg:address":"265 Mulberry St",
    "sg:city":"Mifflinburg",
    "sg:classifiers":[
        {
            "category":"Utilities",
            "subcategory":"Fuel Oil & Lpg",
            "type":"Services"
        }
    ],
    "sg:phone":"+1 570 966 3121",
    "sg:postcode":"17844",
    "sg:province":"PA",
    "wof:name":"H L Klose & Sons Inc",
    "wof:placetype":"venue"
},
  "geometry": {"coordinates":[-77.044738,40.920309],"type":"Point"}
}