{
  "type": "Feature",
  "properties": {
    "iso:country":"US",
    "sg:address":"1255 Girl Scout Rd",
    "sg:city":"Stevens",
    "sg:classifiers":[
        {
            "category":"Building & Trades",
            "subcategory":"Construction",
            "type":"Services"
        }
    ],
    "sg:phone":"+1   ",
    "sg:postcode":"17578",
    "sg:province":"PA",
    "sg:tags":[
        "heavy"
    ],
    "wof:name":"K D K Services Inc",
    "wof:placetype":"venue"
},
  "geometry": {"coordinates":[-76.212886,40.250187],"type":"Point"}
}