{
  "type": "Feature",
  "properties": {
    "addr:full":"137 N 4th St Philadelphia PA 19106",
    "addr:housenumber":"137",
    "addr:postcode":"19106",
    "addr:street":"N 4Th St",
    "iso:country":"US",
    "sg:address":"137 N 4th St",
    "sg:city":"Philadelphia",
    "sg:classifiers":[
        {
            "category":"Professional",
            "subcategory":"Lawyer & Legal Services",
            "type":"Services"
        }
    ],
    "sg:phone":"+1 215 923 8833",
    "sg:postcode":"19106",
    "sg:province":"PA",
    "sg:tags":[
        "attorney"
    ],
    "wof:name":"Duane Lassiter & Assoc",
    "wof:placetype":"venue"
},
  "geometry": {"coordinates":[-75.146417,39.954201],"type":"Point"}
}