{
  "type": "Feature",
  "properties": {
    "iso:country":"US",
    "sg:address":"2265 Jericho Dr",
    "sg:city":"Jamison",
    "sg:classifiers":[
        {
            "category":"Building & Trades",
            "subcategory":"Construction",
            "type":"Services"
        }
    ],
    "sg:phone":"+1 215 491 7564",
    "sg:postcode":"18929",
    "sg:province":"PA",
    "sg:tags":[
        "contractor",
        "industrial",
        "painting",
        "contractors-commercial",
        "hanging"
    ],
    "wof:name":"Finish Touch Ptg Inc",
    "wof:placetype":"venue"
},
  "geometry": {"coordinates":[-75.112132,40.26756],"type":"Point"}
}