{
  "type": "Feature",
  "properties": {
    "addr:full":"6703 Germantown Avenue, Suite 200 Philadelphia PA 19119",
    "addr:housenumber":"6703",
    "addr:postcode":"19119",
    "addr:street":"Germantown Avenue Suite 200",
    "iso:country":"US",
    "sg:address":"6703 Germantown Avenue, Suite 200",
    "sg:city":"Philadelphia",
    "sg:classifiers":[
        {
            "category":"Professional",
            "subcategory":"Lawyer & Legal Services",
            "type":"Services"
        }
    ],
    "sg:phone":"+1 267 882 2734",
    "sg:postcode":"19119",
    "sg:province":"PA",
    "sg:tags":[
        "attorney",
        "criminal",
        "estate",
        "family",
        "duo",
        "divorce",
        "wills",
        "planning",
        "trust",
        "dwi",
        "law"
    ],
    "sg:website":"http://crossonlawoffice.com",
    "wof:name":"Crosson Law Office",
    "wof:placetype":"venue"
},
  "geometry": {"coordinates":[-75.18530800000001,40.051793],"type":"Point"}
}