{
  "type": "Feature",
  "properties": {
    "addr:full":"1130 Hwy 315 Wilkes Barre PA 18702",
    "addr:housenumber":"1130",
    "addr:postcode":"18702",
    "addr:street":"Hwy 315",
    "iso:country":"US",
    "sg:address":"1130 Hwy 315",
    "sg:city":"Wilkes Barre",
    "sg:classifiers":[
        {
            "category":"Health Services",
            "subcategory":"Doctor",
            "type":"Services"
        }
    ],
    "sg:phone":"+1   ",
    "sg:postcode":"18702",
    "sg:province":"PA",
    "sg:tags":[
        "medical"
    ],
    "wof:name":"Alfonso Rodriguez MD",
    "wof:placetype":"venue"
},
  "geometry": {"coordinates":[-75.82222899999999,41.257515],"type":"Point"}
}