{
  "type": "Feature",
  "properties": {
    "addr:full":"659 W Kingsley St Philadelphia PA 19144",
    "addr:housenumber":"659",
    "addr:postcode":"19144",
    "addr:street":"W Kingsley St",
    "iso:country":"US",
    "sg:address":"659 W Kingsley St",
    "sg:city":"Philadelphia",
    "sg:classifiers":[
        {
            "category":"Farming",
            "subcategory":"Livestock Farm",
            "type":"Manufacturing & Wholesale Goods"
        }
    ],
    "sg:phone":"+1 215 438 1860",
    "sg:postcode":"19144",
    "sg:province":"PA",
    "sg:tags":[
        "horse"
    ],
    "wof:name":"Philadelphia Saddle Club",
    "wof:placetype":"venue"
},
  "geometry": {"coordinates":[-75.192639,40.032934],"type":"Point"}
}