{
  "type": "Feature",
  "properties": {
    "iso:country":"US",
    "sg:address":"23 Garden Pkwy",
    "sg:city":"Carlisle",
    "sg:classifiers":[
        {
            "category":"Personal",
            "subcategory":"Beauty Salon",
            "type":"Services"
        }
    ],
    "sg:phone":"+1   ",
    "sg:postcode":"17013",
    "sg:province":"PA",
    "sg:tags":[
        "shop"
    ],
    "wof:name":"Jills Beauty Salon",
    "wof:placetype":"venue"
},
  "geometry": {"coordinates":[-77.17974599999999,40.190098],"type":"Point"}
}