{
  "type": "Feature",
  "properties": {
    "iso:country":"US",
    "sg:address":"5948 Market St",
    "sg:city":"Philadelphia",
    "sg:classifiers":[
        {
            "category":"Banks & Credit Unions",
            "subcategory":"Atm",
            "type":"Services"
        }
    ],
    "sg:phone":"+1 215 471 3877",
    "sg:postcode":"19139",
    "sg:province":"PA",
    "sg:tags":[
        "location"
    ],
    "wof:name":"King Cash",
    "wof:placetype":"venue"
},
  "geometry": {"coordinates":[-75.240201,39.961861],"type":"Point"}
}