{
  "type": "Feature",
  "properties": {
    "iso:country":"US",
    "sg:address":"100 S Benner Ave",
    "sg:city":"Bethlehem",
    "sg:classifiers":[
        {
            "category":"Manufacturing",
            "subcategory":"Apparel",
            "type":"Manufacturing & Wholesale Goods"
        }
    ],
    "sg:phone":"+1   ",
    "sg:postcode":"18015",
    "sg:province":"PA",
    "sg:tags":[
        "mfg"
    ],
    "wof:name":"Angelwear",
    "wof:placetype":"venue"
},
  "geometry": {"coordinates":[-75.3922,40.602646],"type":"Point"}
}