{
  "type": "Feature",
  "properties": {
    "addr:full":"1223 Hamilton St Philadelphia PA 19123",
    "addr:housenumber":"1223",
    "addr:postcode":"19123",
    "addr:street":"Hamilton St",
    "iso:country":"US",
    "sg:address":"1223 Hamilton St",
    "sg:city":"Philadelphia",
    "sg:classifiers":[
        {
            "category":"Manufacturing",
            "subcategory":"Furniture",
            "type":"Manufacturing & Wholesale Goods"
        },
        {
            "category":"Wholesale",
            "subcategory":"Home Furnishings",
            "type":"Manufacturing & Wholesale Goods"
        }
    ],
    "sg:phone":"+1 215 592 9455",
    "sg:postcode":"19123",
    "sg:province":"PA",
    "sg:tags":[
        "equipment",
        "supply"
    ],
    "wof:name":"Stanley Kitchen Supply Inc",
    "wof:placetype":"venue"
},
  "geometry": {"coordinates":[-75.159301,39.960703],"type":"Point"}
}