{
  "type": "Feature",
  "properties": {
    "iso:country":"US",
    "sg:address":"1032 3rd Ave",
    "sg:city":"Duncansville",
    "sg:classifiers":[
        {
            "category":"Shopping",
            "subcategory":"Used Merchandise",
            "type":"Retail Goods"
        }
    ],
    "sg:phone":"+1 814 695 5909",
    "sg:postcode":"16635",
    "sg:province":"PA",
    "sg:tags":[
        "antique"
    ],
    "wof:name":"Kermit Black",
    "wof:placetype":"venue"
},
  "geometry": {"coordinates":[-78.42998299999999,40.424451],"type":"Point"}
}