{
  "type": "Feature",
  "properties": {
    "iso:country":"US",
    "sg:address":"385 Mount Vernon Rd",
    "sg:city":"Gap",
    "sg:classifiers":[
        {
            "category":"Professional",
            "type":"Services"
        }
    ],
    "sg:phone":"+1   ",
    "sg:postcode":"17527",
    "sg:province":"PA",
    "wof:name":"Old Country Shed",
    "wof:placetype":"venue"
},
  "geometry": {"coordinates":[-75.979506,40.020328],"type":"Point"}
}