{
  "type": "Feature",
  "properties": {
    "iso:country":"US",
    "sg:address":"113 E 3rd St",
    "sg:city":"Bethlehem",
    "sg:classifiers":[
        {
            "category":"Personal",
            "subcategory":"Massage",
            "type":"Services"
        },
        {
            "category":"Personal",
            "subcategory":"Tanning Parlor",
            "type":"Services"
        },
        {
            "category":"Personal",
            "subcategory":"Day Spa",
            "type":"Services"
        }
    ],
    "sg:phone":"+1 610 865 9000",
    "sg:postcode":"18015",
    "sg:province":"PA",
    "sg:website":"www.spasoleil.biz",
    "wof:name":"Spa Soleil",
    "wof:placetype":"venue"
},
  "geometry": {"coordinates":[-75.376735,40.612017],"type":"Point"}
}