{
  "type": "Feature",
  "properties": {
    "addr:full":"143 W Hansberry St Philadelphia PA 19144",
    "addr:housenumber":"143",
    "addr:postcode":"19144",
    "addr:street":"W Hansberry St",
    "iso:country":"US",
    "sg:address":"143 W Hansberry St",
    "sg:city":"Philadelphia",
    "sg:classifiers":[
        {
            "category":"Health Services",
            "subcategory":"Clinic",
            "type":"Services"
        }
    ],
    "sg:phone":"+1   ",
    "sg:postcode":"19144",
    "sg:province":"PA",
    "sg:tags":[
        "program",
        "abuse",
        "substance"
    ],
    "wof:name":"Carl B Amos Assocs",
    "wof:placetype":"venue"
},
  "geometry": {"coordinates":[-75.170177,40.028234],"type":"Point"}
}