{
  "type": "Feature",
  "properties": {
    "iso:country":"US",
    "sg:address":"2 Main St E",
    "sg:city":"Railroad",
    "sg:classifiers":[
        {
            "category":"Government",
            "subcategory":"Office",
            "type":"Public Place"
        }
    ],
    "sg:phone":"+1 717 235 5042",
    "sg:postcode":"17355",
    "sg:province":"PA",
    "sg:tags":[
        "village"
    ],
    "wof:name":"Railroad Borough Office",
    "wof:placetype":"venue"
},
  "geometry": {"coordinates":[-76.69833199999999,39.760687],"type":"Point"}
}