{
  "type": "Feature",
  "properties": {
    "iso:country":"US",
    "sg:address":"2200 W Chester Pike",
    "sg:city":"Broomall",
    "sg:classifiers":[
        {
            "category":"Arts & Performance",
            "subcategory":"Theater",
            "type":"Entertainment"
        }
    ],
    "sg:phone":"+1 610 325 4540",
    "sg:postcode":"19008",
    "sg:province":"PA",
    "sg:tags":[
        "bureau"
    ],
    "wof:name":"Frank Kielb Entertainment",
    "wof:placetype":"venue"
},
  "geometry": {"coordinates":[-75.34769300000001,39.979782],"type":"Point"}
}