{
  "type": "Feature",
  "properties": {
    "iso:country":"US",
    "sg:address":"1345 Connellsville Rd",
    "sg:city":"Fayette City",
    "sg:classifiers":[
        {
            "category":"Retail",
            "subcategory":"Animal Services",
            "type":"Services"
        }
    ],
    "sg:phone":"+1   ",
    "sg:postcode":"15438",
    "sg:province":"PA",
    "wof:name":"Loving Care Dog Grooming",
    "wof:placetype":"venue"
},
  "geometry": {"coordinates":[-79.82224100000001,40.112192],"type":"Point"}
}