{
  "type": "Feature",
  "properties": {
    "iso:country":"US",
    "sg:address":"1609 Cochran Rd",
    "sg:city":"Pittsburgh",
    "sg:classifiers":[
        {
            "category":"Restaurant",
            "type":"Food & Drink"
        }
    ],
    "sg:phone":"+1 412 563 8226",
    "sg:postcode":"15220",
    "sg:province":"PA",
    "sg:website":"www.tacobell.com",
    "wof:name":"Taco Bell",
    "wof:placetype":"venue"
},
  "geometry": {"coordinates":[-80.04969800000001,40.416698],"type":"Point"}
}