{
  "type": "Feature",
  "properties": {
    "addr:full":"813 35th St Barnesboro PA 15714",
    "addr:housenumber":"813",
    "addr:postcode":"15714",
    "addr:street":"35Th St",
    "iso:country":"US",
    "sg:address":"813 35th St",
    "sg:city":"Barnesboro",
    "sg:classifiers":[
        {
            "category":"Education",
            "subcategory":"School",
            "type":"Public Place"
        }
    ],
    "sg:phone":"+1 814 948 6800",
    "sg:postcode":"15714",
    "sg:province":"PA",
    "wof:name":"Northern Cambria High School",
    "wof:placetype":"venue"
},
  "geometry": {"coordinates":[-78.78044199999999,40.655575],"type":"Point"}
}