{
  "type": "Feature",
  "properties": {
    "iso:country":"US",
    "sg:address":"10 Cherry Ave Ste 100",
    "sg:city":"Houston",
    "sg:classifiers":[
        {
            "category":"Wholesale",
            "subcategory":"Stationery",
            "type":"Manufacturing & Wholesale Goods"
        }
    ],
    "sg:phone":"+1 724 745 1140",
    "sg:postcode":"15342",
    "sg:province":"PA",
    "sg:tags":[
        "card"
    ],
    "wof:name":"See-Line Company",
    "wof:placetype":"venue"
},
  "geometry": {"coordinates":[-80.209234,40.251369],"type":"Point"}
}