{
  "type": "Feature",
  "properties": {
    "addr:full":"504 S 3rd St Lebanon PA 17042",
    "addr:housenumber":"504",
    "addr:postcode":"17042",
    "addr:street":"S 3Rd St",
    "iso:country":"US",
    "sg:address":"504 S 3rd St",
    "sg:city":"Lebanon",
    "sg:classifiers":[
        {
            "category":"Building & Trades",
            "subcategory":"Electrical",
            "type":"Services"
        }
    ],
    "sg:phone":"+1   ",
    "sg:postcode":"17042",
    "sg:province":"PA",
    "sg:tags":[
        "electrical",
        "contractor"
    ],
    "wof:name":"Mike Hollis Electrical",
    "wof:placetype":"venue"
},
  "geometry": {"coordinates":[-76.415175,40.332715],"type":"Point"}
}