{
  "type": "Feature",
  "properties": {
    "addr:full":"336 Bunker Hill Rd Strasburg PA 17579",
    "addr:housenumber":"336",
    "addr:postcode":"17579",
    "addr:street":"Bunker Hill Rd",
    "iso:country":"US",
    "sg:address":"336 Bunker Hill Rd",
    "sg:city":"Strasburg",
    "sg:classifiers":[
        {
            "category":"Farming",
            "subcategory":"Nursery",
            "type":"Manufacturing & Wholesale Goods"
        }
    ],
    "sg:phone":"+1 717 687 0980",
    "sg:postcode":"17579",
    "sg:province":"PA",
    "sg:tags":[
        "greenhouse"
    ],
    "wof:name":"Good Harvest Vegetable Farm",
    "wof:placetype":"venue"
},
  "geometry": {"coordinates":[-76.181257,39.96629],"type":"Point"}
}