{
  "type": "Feature",
  "properties": {
    "addr:full":"702 Eden Rd Lancaster PA 17601",
    "addr:housenumber":"702",
    "addr:postcode":"17601",
    "addr:street":"Eden Rd",
    "iso:country":"US",
    "sg:address":"702 Eden Rd",
    "sg:city":"Lancaster",
    "sg:classifiers":[
        {
            "category":"Health Services",
            "subcategory":"Chiropractor",
            "type":"Services"
        }
    ],
    "sg:phone":"+1 717 560 6820",
    "sg:postcode":"17601",
    "sg:province":"PA",
    "wof:name":"Metz Chiropractic Clinic",
    "wof:placetype":"venue"
},
  "geometry": {"coordinates":[-76.28801799999999,40.071998],"type":"Point"}
}