{
  "type": "Feature",
  "properties": {
    "addr:full":"11000 State Rte 993 Irwin PA 15642",
    "addr:housenumber":"11000",
    "addr:postcode":"15642",
    "addr:street":"State Rte 993",
    "iso:country":"US",
    "sg:address":"11000 State Rte 993",
    "sg:city":"Irwin",
    "sg:classifiers":[
        {
            "category":"Building & Trades",
            "subcategory":"Cleaning & Sanitation",
            "type":"Services"
        }
    ],
    "sg:phone":"+1   ",
    "sg:postcode":"15642",
    "sg:province":"PA",
    "sg:tags":[
        "maintenance"
    ],
    "wof:name":"Warehouse Maintenance",
    "wof:placetype":"venue"
},
  "geometry": {"coordinates":[-79.718362,40.336528],"type":"Point"}
}