{
  "type": "Feature",
  "properties": {
    "addr:full":"10 S Main St Spring Grove PA 17362",
    "addr:housenumber":"10",
    "addr:postcode":"17362",
    "addr:street":"S Main St",
    "iso:country":"US",
    "sg:address":"10 S Main St",
    "sg:city":"Spring Grove",
    "sg:classifiers":[
        {
            "category":"Banks & Credit Unions",
            "subcategory":"Bank",
            "type":"Services"
        }
    ],
    "sg:phone":"+1 717 225 4724",
    "sg:postcode":"17362",
    "sg:province":"PA",
    "sg:website":"www.ffb.com",
    "wof:name":"Susquehanna Bank",
    "wof:placetype":"venue"
},
  "geometry": {"coordinates":[-76.865668,39.874501],"type":"Point"}
}