{
  "type": "Feature",
  "properties": {
    "iso:country":"US",
    "sg:address":"458 Shady Rill Rd",
    "sg:city":"Shavertown",
    "sg:classifiers":[
        {
            "category":"Freight",
            "type":"Transportation"
        }
    ],
    "sg:phone":"+1   ",
    "sg:postcode":"18708",
    "sg:province":"PA",
    "sg:tags":[
        "operator",
        "local",
        "trucking"
    ],
    "wof:name":"Material Transport Inc",
    "wof:placetype":"venue"
},
  "geometry": {"coordinates":[-76.00192199999999,41.266652],"type":"Point"}
}