{
  "type": "Feature",
  "properties": {
    "addr:full":"12 S Main St Masontown PA 15461",
    "addr:housenumber":"12",
    "addr:postcode":"15461",
    "addr:street":"S Main St",
    "iso:country":"US",
    "sg:address":"12 S Main St",
    "sg:city":"Masontown",
    "sg:classifiers":[
        {
            "category":"Insurance",
            "subcategory":"Insurance Agent",
            "type":"Services"
        }
    ],
    "sg:phone":"+1 724 583 7767",
    "sg:postcode":"15461",
    "sg:province":"PA",
    "sg:website":"http://www.berishagency.net",
    "wof:name":"Berish Agency Inc.",
    "wof:placetype":"venue"
},
  "geometry": {"coordinates":[-79.899621,39.84633],"type":"Point"}
}