{
  "type": "Feature",
  "properties": {
    "addr:full":"4826 Canterbury Rd Doylestown PA 18901",
    "addr:housenumber":"4826",
    "addr:postcode":"18901",
    "addr:street":"Canterbury Rd",
    "iso:country":"US",
    "sg:address":"4826 Canterbury Rd",
    "sg:city":"Doylestown",
    "sg:classifiers":[
        {
            "category":"Building & Trades",
            "subcategory":"Electrical",
            "type":"Services"
        }
    ],
    "sg:phone":"+1 412 348 5248",
    "sg:postcode":"18901",
    "sg:province":"PA",
    "sg:tags":[
        "electrician"
    ],
    "wof:name":"Large's Electrical Maintenance",
    "wof:placetype":"venue"
},
  "geometry": {"coordinates":[-75.105797,40.355099],"type":"Point"}
}