{
  "type": "Feature",
  "properties": {
    "addr:full":"160 Wolfe Run Rd Freedom PA 15042",
    "addr:housenumber":"160",
    "addr:postcode":"15042",
    "addr:street":"Wolfe Run Rd",
    "iso:country":"US",
    "sg:address":"160 Wolfe Run Rd",
    "sg:city":"Freedom",
    "sg:classifiers":[
        {
            "category":"Building & Trades",
            "subcategory":"Electrical",
            "type":"Services"
        }
    ],
    "sg:phone":"+1 724 775 8280",
    "sg:postcode":"15042",
    "sg:province":"PA",
    "sg:tags":[
        "electric",
        "contractor"
    ],
    "wof:name":"EMP Svc",
    "wof:placetype":"venue"
},
  "geometry": {"coordinates":[-80.207691,40.693917],"type":"Point"}
}