{
  "type": "Feature",
  "properties": {
    "iso:country":"US",
    "sg:address":"208 Union Rd",
    "sg:city":"Lebanon",
    "sg:classifiers":[
        {
            "category":"Farming",
            "subcategory":"Livestock Farm",
            "type":"Manufacturing & Wholesale Goods"
        }
    ],
    "sg:phone":"+1 717 865 6053",
    "sg:postcode":"17046",
    "sg:province":"PA",
    "sg:tags":[
        "ranch"
    ],
    "wof:name":"Geissingers Farm",
    "wof:placetype":"venue"
},
  "geometry": {"coordinates":[-76.389516,40.405329],"type":"Point"}
}