{
  "type": "Feature",
  "properties": {
    "addr:full":"550 Butler St Pittsburgh PA 15223",
    "addr:housenumber":"550",
    "addr:postcode":"15223",
    "addr:street":"Butler St",
    "iso:country":"US",
    "sg:address":"550 Butler St",
    "sg:city":"Pittsburgh",
    "sg:classifiers":[
        {
            "category":"Restaurant",
            "type":"Food & Drink"
        }
    ],
    "sg:menulink":"http://www.allmenus.com/pa/etna/72056-pizza-hut/menu/",
    "sg:phone":"+1 412 781 1400",
    "sg:postcode":"15223",
    "sg:province":"PA",
    "sg:tags":[
        "american",
        "pizza"
    ],
    "wof:name":"Pizza Hut",
    "wof:placetype":"venue"
},
  "geometry": {"coordinates":[-79.94367699999999,40.500555],"type":"Point"}
}