{
  "type": "Feature",
  "properties": {
    "iso:country":"US",
    "sg:address":"3050 N 5th Street Hwy",
    "sg:city":"Reading",
    "sg:classifiers":[
        {
            "category":"Building & Trades",
            "subcategory":"Construction",
            "type":"Services"
        }
    ],
    "sg:phone":"+1   ",
    "sg:postcode":"19605",
    "sg:province":"PA",
    "sg:tags":[
        "contractor",
        "laying",
        "floor",
        "covering"
    ],
    "wof:name":"Four-Js",
    "wof:placetype":"venue"
},
  "geometry": {"coordinates":[-75.92755,40.383165],"type":"Point"}
}