{
  "type": "Feature",
  "properties": {
    "addr:full":"802 Walnut St Waterford PA 16441",
    "addr:housenumber":"802",
    "addr:postcode":"16441",
    "addr:street":"Walnut St",
    "iso:country":"US",
    "sg:address":"802 Walnut St",
    "sg:city":"Waterford",
    "sg:classifiers":[
        {
            "category":"Professional",
            "subcategory":"Advertising",
            "type":"Services"
        }
    ],
    "sg:phone":"+1   ",
    "sg:postcode":"16441",
    "sg:province":"PA",
    "sg:tags":[
        "agency"
    ],
    "wof:name":"Aesthetic Factory Inc",
    "wof:placetype":"venue"
},
  "geometry": {"coordinates":[-79.990419,41.94967],"type":"Point"}
}