{
  "type": "Feature",
  "properties": {
    "addr:full":"1518 Walnut St Ste 1101 Philadelphia PA 19102",
    "addr:housenumber":"1518",
    "addr:postcode":"19102",
    "addr:street":"Walnut St Ste 1101",
    "iso:country":"US",
    "sg:address":"1518 Walnut St Ste 1101",
    "sg:city":"Philadelphia",
    "sg:classifiers":[
        {
            "category":"Health Services",
            "subcategory":"Dentist",
            "type":"Services"
        }
    ],
    "sg:phone":"+1 215 732 0506",
    "sg:postcode":"19102",
    "sg:province":"PA",
    "wof:name":"Myron B Goldberg Dds",
    "wof:placetype":"venue"
},
  "geometry": {"coordinates":[-75.166786,39.949655],"type":"Point"}
}