{
  "type": "Feature",
  "properties": {
    "iso:country":"US",
    "sg:address":"238 Deems Park Rd",
    "sg:city":"Daisytown",
    "sg:classifiers":[
        {
            "category":"Food & Beverages",
            "subcategory":"Meat & Fish",
            "type":"Retail Goods"
        }
    ],
    "sg:phone":"+1 724 938 0226",
    "sg:postcode":"15427",
    "sg:province":"PA",
    "wof:name":"S & S Meat Packing",
    "wof:placetype":"venue"
},
  "geometry": {"coordinates":[-79.98473,40.0779],"type":"Point"}
}