{
  "type": "Feature",
  "properties": {
    "iso:country":"US",
    "sg:address":"4414 Oakhurst Blvd",
    "sg:city":"Harrisburg",
    "sg:classifiers":[
        {
            "category":"Shopping",
            "subcategory":"Stationery & Office Supplies",
            "type":"Retail Goods"
        }
    ],
    "sg:phone":"+1   ",
    "sg:postcode":"17110",
    "sg:province":"PA",
    "sg:tags":[
        "shop",
        "gift"
    ],
    "wof:name":"Freckled Frog The Inc",
    "wof:placetype":"venue"
},
  "geometry": {"coordinates":[-76.848842,40.333144],"type":"Point"}
}