{
  "type": "Feature",
  "properties": {
    "addr:full":"19 W Chestnut St Lancaster PA 17603",
    "addr:housenumber":"19",
    "addr:postcode":"17603",
    "addr:street":"W Chestnut St",
    "iso:country":"US",
    "sg:address":"19 W Chestnut St",
    "sg:city":"Lancaster",
    "sg:classifiers":[
        {
            "category":"Shopping",
            "subcategory":"News",
            "type":"Retail Goods"
        }
    ],
    "sg:phone":"+1 717 394 5323",
    "sg:postcode":"17603",
    "sg:province":"PA",
    "sg:tags":[
        "dealer"
    ],
    "wof:name":"Teck's News Agency",
    "wof:placetype":"venue"
},
  "geometry": {"coordinates":[-76.30668799999999,40.041179],"type":"Point"}
}