{
  "type": "Feature",
  "properties": {
    "iso:country":"US",
    "sg:address":"4722 Liberty Ave",
    "sg:city":"Pittsburgh",
    "sg:classifiers":[
        {
            "category":"Shopping",
            "subcategory":"Shoes",
            "type":"Retail Goods"
        }
    ],
    "sg:phone":"+1 412 802 8660",
    "sg:postcode":"15224",
    "sg:province":"PA",
    "wof:name":"Foot Menders",
    "wof:placetype":"venue"
},
  "geometry": {"coordinates":[-79.94923799999999,40.461695],"type":"Point"}
}