{
  "type": "Feature",
  "properties": {
    "addr:full":"427 State St Erie PA 16501",
    "addr:housenumber":"427",
    "addr:postcode":"16501",
    "addr:street":"State St",
    "iso:country":"US",
    "sg:address":"427 State St",
    "sg:city":"Erie",
    "sg:classifiers":[
        {
            "category":"Personal",
            "subcategory":"Beauty Salon",
            "type":"Services"
        }
    ],
    "sg:phone":"+1 814 464 1562",
    "sg:postcode":"16501",
    "sg:province":"PA",
    "wof:name":"Illusions Hair & Makeup Studio",
    "wof:placetype":"venue"
},
  "geometry": {"coordinates":[-80.08598600000001,42.130766],"type":"Point"}
}