{
  "type": "Feature",
  "properties": {
    "addr:full":"210 Keystone Rd Chester PA 19013",
    "addr:housenumber":"210",
    "addr:postcode":"19013",
    "addr:street":"Keystone Rd",
    "iso:country":"US",
    "sg:address":"210 Keystone Rd",
    "sg:city":"Chester",
    "sg:classifiers":[
        {
            "category":"Autos & Motor Vehicles",
            "subcategory":"Auto Supplies",
            "type":"Retail Goods"
        }
    ],
    "sg:phone":"+1 610 494 2160",
    "sg:postcode":"19013",
    "sg:province":"PA",
    "sg:tags":[
        "tire"
    ],
    "sg:website":"www.wingfootct.com",
    "wof:name":"Wingfoot Commercial Tire Systs",
    "wof:placetype":"venue"
},
  "geometry": {"coordinates":[-75.40802100000001,39.84371],"type":"Point"}
}