{
  "type": "Feature",
  "properties": {
    "addr:full":"9400 McKnight Rd Ste 207 Pittsburgh PA 15237",
    "addr:housenumber":"9400",
    "addr:postcode":"15237",
    "addr:street":"Mcknight Rd Ste 207",
    "iso:country":"US",
    "sg:address":"9400 McKnight Rd Ste 207",
    "sg:city":"Pittsburgh",
    "sg:classifiers":[
        {
            "category":"Building & Trades",
            "subcategory":"Construction",
            "type":"Services"
        }
    ],
    "sg:phone":"+1 412 364 1146",
    "sg:postcode":"15237",
    "sg:province":"PA",
    "sg:tags":[
        "contractor"
    ],
    "wof:name":"Thomson Properties Inc",
    "wof:placetype":"venue"
},
  "geometry": {"coordinates":[-80.02629899999999,40.577202],"type":"Point"}
}