{
  "type": "Feature",
  "properties": {
    "iso:country":"US",
    "sg:address":"110 W McMurray Rd",
    "sg:city":"Canonsburg",
    "sg:classifiers":[
        {
            "category":"Shopping",
            "type":"Retail Goods"
        }
    ],
    "sg:phone":"+1 724 941 2729",
    "sg:postcode":"15317",
    "sg:province":"PA",
    "sg:tags":[
        "picture",
        "frame"
    ],
    "wof:name":"Fastframe",
    "wof:placetype":"venue"
},
  "geometry": {"coordinates":[-80.127233,40.273206],"type":"Point"}
}