{
  "type": "Feature",
  "properties": {
    "iso:country":"US",
    "sg:address":"220 6th St",
    "sg:city":"Mckeesport",
    "sg:classifiers":[
        {
            "category":"Government",
            "subcategory":"Office",
            "type":"Public Place"
        }
    ],
    "sg:phone":"+1 412 664 6800",
    "sg:postcode":"15132",
    "sg:province":"PA",
    "sg:tags":[
        "state",
        "resource"
    ],
    "wof:name":"Public Welfare Dept",
    "wof:placetype":"venue"
},
  "geometry": {"coordinates":[-79.86479199999999,40.349916],"type":"Point"}
}