{
  "type": "Feature",
  "properties": {
    "addr:full":"378 Main St Edwardsville PA 18704",
    "addr:housenumber":"378",
    "addr:postcode":"18704",
    "addr:street":"Main St",
    "iso:country":"US",
    "sg:address":"378 Main St",
    "sg:city":"Edwardsville",
    "sg:classifiers":[
        {
            "category":"Autos & Motor Vehicles",
            "subcategory":"Motorcycle Sales",
            "type":"Retail Goods"
        }
    ],
    "sg:phone":"+1 570 718 1844",
    "sg:postcode":"18704",
    "sg:province":"PA",
    "sg:tags":[
        "scooter"
    ],
    "sg:website":"www.cbxman.com",
    "wof:name":"CBXMAN.COM",
    "wof:placetype":"venue"
},
  "geometry": {"coordinates":[-75.892161,41.289856],"type":"Point"}
}