{
  "type": "Feature",
  "properties": {
    "iso:country":"US",
    "sg:address":"2630 Kane Rd",
    "sg:city":"Aliquippa",
    "sg:classifiers":[
        {
            "category":"Social Services",
            "type":"Services"
        },
        {
            "category":"Organizations",
            "subcategory":"Community Association",
            "type":"Services"
        }
    ],
    "sg:phone":"+1 724 650 1637",
    "sg:postcode":"15001",
    "sg:province":"PA",
    "wof:name":"Cheer Boosters",
    "wof:placetype":"venue"
},
  "geometry": {"coordinates":[-80.28063,40.598415],"type":"Point"}
}