{
  "type": "Feature",
  "properties": {
    "iso:country":"US",
    "sg:address":"515 Harry St",
    "sg:city":"Conshohocken",
    "sg:classifiers":[
        {
            "category":"Recreation",
            "type":"Entertainment"
        }
    ],
    "sg:phone":"+1 610 828 3266",
    "sg:postcode":"19428",
    "sg:province":"PA",
    "sg:tags":[
        "center"
    ],
    "sg:website":"www.thefellowshiphouse.org",
    "wof:name":"Fellowship House-Conshohocken",
    "wof:placetype":"venue"
},
  "geometry": {"coordinates":[-75.301293,40.077364],"type":"Point"}
}