{
  "type": "Feature",
  "properties": {
    "addr:full":"9906 Roosevelt Blvd Philadelphia PA 19115",
    "addr:housenumber":"9906",
    "addr:postcode":"19115",
    "addr:street":"Roosevelt Blvd",
    "iso:country":"US",
    "sg:address":"9906 Roosevelt Blvd",
    "sg:city":"Philadelphia",
    "sg:classifiers":[
        {
            "category":"Home & Garden",
            "subcategory":"Home Furnishings",
            "type":"Retail Goods"
        },
        {
            "category":"Home & Garden",
            "subcategory":"Carpets & Floor Coverings",
            "type":"Retail Goods"
        }
    ],
    "sg:phone":"+1 215 676 2707",
    "sg:postcode":"19115",
    "sg:province":"PA",
    "sg:tags":[
        "set",
        "house",
        "bedding",
        "bed",
        "mattress",
        "linen",
        "bedroom"
    ],
    "sg:website":"http://www.sleepys.com",
    "wof:name":"Sleepy's The Mattress Pros",
    "wof:placetype":"venue"
},
  "geometry": {"coordinates":[-75.017443,40.092883],"type":"Point"}
}