{
  "type": "Feature",
  "properties": {
    "iso:country":"US",
    "sg:address":"100 Grays Ln",
    "sg:city":"Haverford",
    "sg:classifiers":[
        {
            "category":"Real Estate",
            "subcategory":"Real Estate Operator",
            "type":"Services"
        },
        {
            "category":"Organizations",
            "subcategory":"Community Association",
            "type":"Services"
        }
    ],
    "sg:phone":"+1 610 642 4100",
    "sg:postcode":"19041",
    "sg:province":"PA",
    "sg:tags":[
        "condominium"
    ],
    "wof:name":"Grays Lane House Inc",
    "wof:placetype":"venue"
},
  "geometry": {"coordinates":[-75.299088,40.016154],"type":"Point"}
}