{
  "type": "Feature",
  "properties": {
    "iso:country":"US",
    "sg:address":"105 Layton Rd",
    "sg:city":"Clarks Summit",
    "sg:classifiers":[
        {
            "category":"Health Services",
            "subcategory":"Doctor",
            "type":"Services"
        }
    ],
    "sg:phone":"+1 570 586 3982",
    "sg:postcode":"18411",
    "sg:province":"PA",
    "sg:tags":[
        "physician",
        "surgeon"
    ],
    "wof:name":"Raphael Heart Group",
    "wof:placetype":"venue"
},
  "geometry": {"coordinates":[-75.680403,41.4732],"type":"Point"}
}