{
  "type": "Feature",
  "properties": {
    "addr:full":"145 Pusey Mill Rd Cochranville PA 19330",
    "addr:housenumber":"145",
    "addr:postcode":"19330",
    "addr:street":"Pusey Mill Rd",
    "iso:country":"US",
    "sg:address":"145 Pusey Mill Rd",
    "sg:city":"Cochranville",
    "sg:classifiers":[
        {
            "category":"Farming",
            "subcategory":"Dairy Farm",
            "type":"Manufacturing & Wholesale Goods"
        }
    ],
    "sg:phone":"+1   ",
    "sg:postcode":"19330",
    "sg:province":"PA",
    "wof:name":"Lane Pinta Farm",
    "wof:placetype":"venue"
},
  "geometry": {"coordinates":[-75.92944799999999,39.836651],"type":"Point"}
}