{
  "type": "Feature",
  "properties": {
    "iso:country":"US",
    "sg:address":"7462 Oxford Ave",
    "sg:city":"Philadelphia",
    "sg:classifiers":[
        {
            "category":"Building & Trades",
            "subcategory":"Construction",
            "type":"Services"
        }
    ],
    "sg:phone":"+1 267 246 3358",
    "sg:postcode":"19111",
    "sg:province":"PA",
    "sg:tags":[
        "wallcoverings-installation",
        "wallpaper",
        "painting",
        "contractor"
    ],
    "wof:name":"Pellegrino Brother's Painting",
    "wof:placetype":"venue"
},
  "geometry": {"coordinates":[-75.083574,40.065407],"type":"Point"}
}