{
  "type": "Feature",
  "properties": {
    "addr:full":"2000 Market St 20th Fl Philadelphia PA 19103",
    "addr:housenumber":"2000",
    "addr:postcode":"19103",
    "addr:street":"Market St;Fl",
    "iso:country":"US",
    "sg:address":"2000 Market St 20th Fl",
    "sg:city":"Philadelphia",
    "sg:classifiers":[
        {
            "category":"Professional",
            "subcategory":"Lawyer & Legal Services",
            "type":"Services"
        }
    ],
    "sg:phone":"+1 215 299 2000",
    "sg:postcode":"19103",
    "sg:province":"PA",
    "sg:tags":[
        "attorney",
        "family",
        "practice",
        "worker",
        "compensation",
        "labor",
        "benefit",
        "real estate",
        "employee",
        "law",
        "employment",
        "bankruptcy"
    ],
    "sg:website":"http://www.foxrothschild.com",
    "wof:name":"Fox Rothschild LLP",
    "wof:placetype":"venue"
},
  "geometry": {"coordinates":[-75.17318,39.953571],"type":"Point"}
}