{
  "type": "Feature",
  "properties": {
    "addr:full":"2312 W Irwin St Aliquippa PA 15001",
    "addr:housenumber":"2312",
    "addr:postcode":"15001",
    "addr:street":"W Irwin St",
    "iso:country":"US",
    "sg:address":"2312 W Irwin St",
    "sg:city":"Aliquippa",
    "sg:classifiers":[
        {
            "category":"Shopping",
            "subcategory":"Used Merchandise",
            "type":"Retail Goods"
        }
    ],
    "sg:phone":"+1   ",
    "sg:postcode":"15001",
    "sg:province":"PA",
    "wof:name":"Nellos Taj Mahal",
    "wof:placetype":"venue"
},
  "geometry": {"coordinates":[-80.28097099999999,40.603017],"type":"Point"}
}