{
  "type": "Feature",
  "properties": {
    "iso:country":"US",
    "sg:address":"1814 State Hill Rd",
    "sg:city":"Reading",
    "sg:classifiers":[
        {
            "category":"Restaurant",
            "type":"Food & Drink"
        }
    ],
    "sg:phone":"+1 610 374 9355",
    "sg:postcode":"19610",
    "sg:province":"PA",
    "sg:tags":[
        "eating",
        "pizza"
    ],
    "wof:name":"Fat Daddy's Pizza",
    "wof:placetype":"venue"
},
  "geometry": {"coordinates":[-75.973854,40.338447],"type":"Point"}
}