{
  "type": "Feature",
  "properties": {
    "iso:country":"US",
    "sg:address":"1718 Fairmount Ave",
    "sg:city":"Philadelphia",
    "sg:classifiers":[
        {
            "category":"Recreation",
            "type":"Entertainment"
        }
    ],
    "sg:phone":"+1   ",
    "sg:postcode":"19130",
    "sg:province":"PA",
    "wof:name":"Herbert Zayon",
    "wof:placetype":"venue"
},
  "geometry": {"coordinates":[-75.16595,39.967082],"type":"Point"}
}