{
  "type": "Feature",
  "properties": {
    "iso:country":"US",
    "sg:address":"727 Thompson Ave",
    "sg:city":"Mc Kees Rocks",
    "sg:classifiers":[
        {
            "category":"Arts & Performance",
            "subcategory":"Theater",
            "type":"Entertainment"
        }
    ],
    "sg:phone":"+1 412 771 9881",
    "sg:postcode":"15136",
    "sg:province":"PA",
    "sg:tags":[
        "group"
    ],
    "wof:name":"Lettermen",
    "wof:placetype":"venue"
},
  "geometry": {"coordinates":[-80.06218699999999,40.465074],"type":"Point"}
}