{
  "type": "Feature",
  "properties": {
    "iso:country":"US",
    "sg:address":"2217 N 15th St",
    "sg:city":"Philadelphia",
    "sg:classifiers":[
        {
            "category":"Retail",
            "subcategory":"Repair Shop",
            "type":"Services"
        }
    ],
    "sg:phone":"+1   ",
    "sg:postcode":"19132",
    "sg:province":"PA",
    "wof:name":"Killer Drain",
    "wof:placetype":"venue"
},
  "geometry": {"coordinates":[-75.157521,39.987819],"type":"Point"}
}