{
  "type": "Feature",
  "properties": {
    "addr:full":"115 Black Rd Sidman PA 15955",
    "addr:housenumber":"115",
    "addr:postcode":"15955",
    "addr:street":"Black Rd",
    "iso:country":"US",
    "sg:address":"115 Black Rd",
    "sg:city":"Sidman",
    "sg:classifiers":[
        {
            "category":"Professional",
            "type":"Services"
        }
    ],
    "sg:phone":"+1   ",
    "sg:postcode":"15955",
    "sg:province":"PA",
    "wof:name":"Wilma J Plummer",
    "wof:placetype":"venue"
},
  "geometry": {"coordinates":[-78.742794,40.347044],"type":"Point"}
}