{
  "type": "Feature",
  "properties": {
    "iso:country":"US",
    "sg:address":"2314 Farmington Ave",
    "sg:city":"Boyertown",
    "sg:phone":"+1 610 369 0085",
    "sg:postcode":"19512",
    "sg:province":"PA",
    "sg:tags":[
        "oil"
    ],
    "wof:name":"Penn Petroleum",
    "wof:placetype":"venue"
},
  "geometry": {"coordinates":[-75.652385,40.319858],"type":"Point"}
}