{
  "type": "Feature",
  "properties": {
    "iso:country":"US",
    "sg:address":"356 E 12th St",
    "sg:city":"Erie",
    "sg:classifiers":[
        {
            "category":"Autos & Motor Vehicles",
            "subcategory":"Fuel & Gas Station",
            "type":"Retail Goods"
        }
    ],
    "sg:phone":"+1   ",
    "sg:postcode":"16503",
    "sg:province":"PA",
    "sg:tags":[
        "station",
        "gasoline"
    ],
    "wof:name":"The Standard Oil Company",
    "wof:placetype":"venue"
},
  "geometry": {"coordinates":[-80.07393999999999,42.126206],"type":"Point"}
}