{
  "type": "Feature",
  "properties": {
    "iso:country":"US",
    "sg:address":"10 McCoy Ln",
    "sg:city":"Washington",
    "sg:classifiers":[
        {
            "category":"Recreation",
            "type":"Entertainment"
        }
    ],
    "sg:phone":"+1 724 223 9500",
    "sg:postcode":"15301",
    "sg:province":"PA",
    "sg:tags":[
        "skating",
        "rink"
    ],
    "wof:name":"Pancake Skate N' Whirl",
    "wof:placetype":"venue"
},
  "geometry": {"coordinates":[-80.21674400000001,40.157477],"type":"Point"}
}