{
  "type": "Feature",
  "properties": {
    "iso:country":"US",
    "sg:address":"1804 E Main St",
    "sg:city":"Waynesboro",
    "sg:classifiers":[
        {
            "category":"Personal",
            "subcategory":"Beauty Salon",
            "type":"Services"
        }
    ],
    "sg:phone":"+1 717 765 4655",
    "sg:postcode":"17268",
    "sg:province":"PA",
    "sg:tags":[
        "shop"
    ],
    "wof:name":"Your Hair Affair",
    "wof:placetype":"venue"
},
  "geometry": {"coordinates":[-77.56445600000001,39.749284],"type":"Point"}
}