{
  "type": "Feature",
  "properties": {
    "iso:country":"US",
    "sg:address":"2 Valley Sq",
    "sg:city":"Blue Bell",
    "sg:classifiers":[
        {
            "category":"Insurance",
            "subcategory":"Insurance Agent",
            "type":"Services"
        }
    ],
    "sg:phone":"+1 215 591 2900",
    "sg:postcode":"19422",
    "sg:province":"PA",
    "sg:website":"www.thezenith.com",
    "wof:name":"Zenith Insurance Co",
    "wof:placetype":"venue"
},
  "geometry": {"coordinates":[-75.282687,40.133642],"type":"Point"}
}