{
  "type": "Feature",
  "properties": {
    "iso:country":"US",
    "sg:address":"402 Willowbank St",
    "sg:city":"Bellefonte",
    "sg:classifiers":[
        {
            "category":"Organizations",
            "subcategory":"Religious Organization",
            "type":"Services"
        }
    ],
    "sg:phone":"+1 814 355 5423",
    "sg:postcode":"16823",
    "sg:province":"PA",
    "sg:tags":[
        "church",
        "supply"
    ],
    "wof:name":"Church Of The Good Shepherd",
    "wof:placetype":"venue"
},
  "geometry": {"coordinates":[-77.782419,40.907462],"type":"Point"}
}