{
  "type": "Feature",
  "properties": {
    "addr:full":"541 Pembroke Rd Bethlehem PA 18018",
    "addr:housenumber":"541",
    "addr:postcode":"18018",
    "addr:street":"Pembroke Rd",
    "iso:country":"US",
    "sg:address":"541 Pembroke Rd",
    "sg:city":"Bethlehem",
    "sg:classifiers":[
        {
            "category":"Retail",
            "subcategory":"Auto Repair",
            "type":"Services"
        }
    ],
    "sg:phone":"+1 610 865 2688",
    "sg:postcode":"18018",
    "sg:province":"PA",
    "sg:tags":[
        "automotive"
    ],
    "wof:name":"Winning Finish",
    "wof:placetype":"venue"
},
  "geometry": {"coordinates":[-75.365551,40.626937],"type":"Point"}
}