{
  "type": "Feature",
  "properties": {
    "iso:country":"US",
    "sg:address":"1225 Doylestown Pike",
    "sg:city":"Quakertown",
    "sg:classifiers":[
        {
            "category":"Building & Trades",
            "subcategory":"Construction",
            "type":"Services"
        }
    ],
    "sg:phone":"+1   ",
    "sg:postcode":"18951",
    "sg:province":"PA",
    "sg:tags":[
        "house"
    ],
    "wof:name":"Johnston & Sons Inc",
    "wof:placetype":"venue"
},
  "geometry": {"coordinates":[-75.305869,40.43487],"type":"Point"}
}