{
  "type": "Feature",
  "properties": {
    "iso:country":"US",
    "sg:address":"20 W Hancock St",
    "sg:city":"Lansdale",
    "sg:classifiers":[
        {
            "category":"Retail",
            "subcategory":"Car Wash",
            "type":"Services"
        }
    ],
    "sg:phone":"+1   ",
    "sg:postcode":"19446",
    "sg:province":"PA",
    "sg:tags":[
        "carwash"
    ],
    "wof:name":"Vinsons Auto Detailing",
    "wof:placetype":"venue"
},
  "geometry": {"coordinates":[-75.290524,40.237869],"type":"Point"}
}