{
  "type": "Feature",
  "properties": {
    "addr:full":"2204 Amelia Ave Scranton PA 18509",
    "addr:housenumber":"2204",
    "addr:postcode":"18509",
    "addr:street":"Amelia Ave",
    "iso:country":"US",
    "sg:address":"2204 Amelia Ave",
    "sg:city":"Scranton",
    "sg:classifiers":[
        {
            "category":"Building & Trades",
            "subcategory":"Construction",
            "type":"Services"
        }
    ],
    "sg:phone":"+1   ",
    "sg:postcode":"18509",
    "sg:province":"PA",
    "sg:tags":[
        "concrete",
        "contractor"
    ],
    "wof:name":"Joe Worobey Masonry",
    "wof:placetype":"venue"
},
  "geometry": {"coordinates":[-75.645415,41.439233],"type":"Point"}
}