{
  "type": "Feature",
  "properties": {
    "iso:country":"US",
    "sg:address":"123 Welsh Hill Rd",
    "sg:city":"Clarks Summit",
    "sg:classifiers":[
        {
            "category":"Utilities",
            "subcategory":"Telephone",
            "type":"Services"
        }
    ],
    "sg:phone":"+1   ",
    "sg:postcode":"18411",
    "sg:province":"PA",
    "sg:tags":[
        "distance",
        "long"
    ],
    "wof:name":"Bobco Enterprises",
    "wof:placetype":"venue"
},
  "geometry": {"coordinates":[-75.726787,41.49583],"type":"Point"}
}