{
  "type": "Feature",
  "properties": {
    "iso:country":"US",
    "sg:address":"699 E Lincoln Ave",
    "sg:city":"Myerstown",
    "sg:classifiers":[
        {
            "category":"Freight",
            "type":"Transportation"
        }
    ],
    "sg:phone":"+1 717 866 5234",
    "sg:postcode":"17067",
    "sg:province":"PA",
    "wof:name":"DSS Transportation Inc",
    "wof:placetype":"venue"
},
  "geometry": {"coordinates":[-76.28391999999999,40.383885],"type":"Point"}
}