{
  "type": "Feature",
  "properties": {
    "iso:country":"US",
    "sg:address":"3412 Ainslie St",
    "sg:city":"Philadelphia",
    "sg:classifiers":[
        {
            "category":"Shopping",
            "subcategory":"Clothing, Apparel, & Fashions",
            "type":"Retail Goods"
        }
    ],
    "sg:phone":"+1 215 849 7493",
    "sg:postcode":"19129",
    "sg:province":"PA",
    "sg:tags":[
        "costume"
    ],
    "wof:name":"Dressed For The Part",
    "wof:placetype":"venue"
},
  "geometry": {"coordinates":[-75.188186,40.013621],"type":"Point"}
}