{
  "type": "Feature",
  "properties": {
    "iso:country":"US",
    "sg:address":"3280 W College Ave",
    "sg:city":"State College",
    "sg:classifiers":[
        {
            "category":"Autos & Motor Vehicles",
            "subcategory":"Automobile Sales",
            "type":"Retail Goods"
        }
    ],
    "sg:phone":"+1   ",
    "sg:postcode":"16801",
    "sg:province":"PA",
    "sg:tags":[
        "new",
        "used"
    ],
    "wof:name":"Shields Motor Company",
    "wof:placetype":"venue"
},
  "geometry": {"coordinates":[-77.875007,40.757102],"type":"Point"}
}