{
  "type": "Feature",
  "properties": {
    "iso:country":"US",
    "sg:address":"1 York Galleria",
    "sg:city":"York",
    "sg:classifiers":[
        {
            "category":"Shopping",
            "subcategory":"Discount & Variety Stores",
            "type":"Retail Goods"
        }
    ],
    "sg:phone":"+1 717 840 8220",
    "sg:postcode":"17402",
    "sg:province":"PA",
    "wof:name":"Dollar Village",
    "wof:placetype":"venue"
},
  "geometry": {"coordinates":[-76.67675800000001,39.989549],"type":"Point"}
}