{
  "type": "Feature",
  "properties": {
    "iso:country":"US",
    "sg:address":"132 Shuey Ln",
    "sg:city":"Jeannette",
    "sg:classifiers":[
        {
            "category":"Manufacturing",
            "subcategory":"Buildings",
            "type":"Manufacturing & Wholesale Goods"
        },
        {
            "category":"Building & Trades",
            "subcategory":"Construction",
            "type":"Services"
        }
    ],
    "sg:phone":"+1 724 834 5038",
    "sg:postcode":"15644",
    "sg:province":"PA",
    "sg:tags":[
        "industrial",
        "altering",
        "builder",
        "system",
        "specialty",
        "heating",
        "contractors-commercial",
        "home",
        "contractor",
        "remodeling",
        "air conditioning"
    ],
    "wof:name":"Shively Larry R Cnstr Remodeli",
    "wof:placetype":"venue"
},
  "geometry": {"coordinates":[-79.577674,40.315917],"type":"Point"}
}