{
  "type": "Feature",
  "properties": {
    "iso:country":"US",
    "sg:address":"1068 Syner Rd",
    "sg:city":"Annville",
    "sg:classifiers":[
        {
            "category":"Building & Trades",
            "subcategory":"Construction",
            "type":"Services"
        }
    ],
    "sg:phone":"+1 717 838 2354",
    "sg:postcode":"17003",
    "sg:province":"PA",
    "sg:tags":[
        "contractor"
    ],
    "wof:name":"Old Forge Enterprises",
    "wof:placetype":"venue"
},
  "geometry": {"coordinates":[-76.59699999999999,40.350201],"type":"Point"}
}