{
  "type": "Feature",
  "properties": {
    "iso:country":"US",
    "sg:address":"26 N Main St",
    "sg:city":"Wilkes Barre",
    "sg:classifiers":[
        {
            "category":"Organizations",
            "subcategory":"Religious Organization",
            "type":"Services"
        }
    ],
    "sg:phone":"+1   ",
    "sg:postcode":"18706",
    "sg:province":"PA",
    "wof:name":"Centenary Untd Methdst Church",
    "wof:placetype":"venue"
},
  "geometry": {"coordinates":[-75.899535,41.213791],"type":"Point"}
}