{
  "type": "Feature",
  "properties": {
    "addr:full":"716 W Chew St Allentown PA 18102",
    "addr:housenumber":"716",
    "addr:postcode":"18102",
    "addr:street":"W Chew St",
    "iso:country":"US",
    "sg:address":"716 W Chew St",
    "sg:city":"Allentown",
    "sg:classifiers":[
        {
            "category":"Social Services",
            "type":"Services"
        }
    ],
    "sg:phone":"+1 484 223 1618",
    "sg:postcode":"18102",
    "sg:province":"PA",
    "sg:tags":[
        "organization",
        "welfare"
    ],
    "wof:name":"Latinos For Healthy Comm",
    "wof:placetype":"venue"
},
  "geometry": {"coordinates":[-75.474475,40.606161],"type":"Point"}
}