{
  "type": "Feature",
  "properties": {
    "iso:country":"US",
    "sg:address":"145 S Plaza Dr",
    "sg:city":"Lewistown",
    "sg:classifiers":[
        {
            "category":"Sports & Exercise",
            "subcategory":"Gym",
            "type":"Entertainment"
        }
    ],
    "sg:phone":"+1   ",
    "sg:postcode":"17044",
    "sg:province":"PA",
    "sg:tags":[
        "fitness",
        "physical",
        "facility"
    ],
    "wof:name":"Texas Jmm Inc",
    "wof:placetype":"venue"
},
  "geometry": {"coordinates":[-77.571769,40.598317],"type":"Point"}
}