{
  "type": "Feature",
  "properties": {
    "iso:country":"US",
    "sg:address":"2243 S Lambert St",
    "sg:city":"Philadelphia",
    "sg:classifiers":[
        {
            "category":"Insurance",
            "subcategory":"Hazard Insurance",
            "type":"Services"
        }
    ],
    "sg:phone":"+1 215 389 2080",
    "sg:postcode":"19145",
    "sg:province":"PA",
    "sg:tags":[
        "commercial",
        "business"
    ],
    "wof:name":"Bene Rocco Agency Inc- Nationwide Insurance",
    "wof:placetype":"venue"
},
  "geometry": {"coordinates":[-75.18085600000001,39.923664],"type":"Point"}
}