{
  "type": "Feature",
  "properties": {
    "addr:full":"3477 Washington Pike Bridgeville PA 15017",
    "addr:housenumber":"3477",
    "addr:postcode":"15017",
    "addr:street":"Washington Pike",
    "iso:country":"US",
    "sg:address":"3477 Washington Pike",
    "sg:city":"Bridgeville",
    "sg:classifiers":[
        {
            "category":"Restaurant",
            "type":"Food & Drink"
        }
    ],
    "sg:phone":"+1 412 221 9759",
    "sg:postcode":"15017",
    "sg:province":"PA",
    "sg:tags":[
        "drinking",
        "eating"
    ],
    "wof:name":"Pepe's Fairview Inn",
    "wof:placetype":"venue"
},
  "geometry": {"coordinates":[-80.133797,40.3321],"type":"Point"}
}