{
  "type": "Feature",
  "properties": {
    "iso:country":"US",
    "sg:address":"761 Gap Newport Pike",
    "sg:city":"Atglen",
    "sg:classifiers":[
        {
            "category":"Food & Beverages",
            "subcategory":"Groceries & Convenience Stores",
            "type":"Retail Goods"
        }
    ],
    "sg:phone":"+1 610 268 2984",
    "sg:postcode":"19310",
    "sg:province":"PA",
    "wof:name":"Wawa Food Market",
    "wof:placetype":"venue"
},
  "geometry": {"coordinates":[-75.94873200000001,39.927862],"type":"Point"}
}