{
  "type": "Feature",
  "properties": {
    "addr:full":"100 5th Ave Warrendale PA 15067",
    "addr:housenumber":"100",
    "addr:postcode":"15067",
    "addr:street":"5Th Ave",
    "iso:country":"US",
    "sg:address":"100 5th Ave",
    "sg:city":"Warrendale",
    "sg:classifiers":[
        {
            "category":"Professional",
            "subcategory":"Employment Agencies",
            "type":"Services"
        }
    ],
    "sg:phone":"+1   ",
    "sg:postcode":"15067",
    "sg:province":"PA",
    "sg:tags":[
        "help",
        "supply"
    ],
    "wof:name":"Pancoast Staffing Services",
    "wof:placetype":"venue"
},
  "geometry": {"coordinates":[-79.943572,40.202165],"type":"Point"}
}