{
  "type": "Feature",
  "properties": {
    "addr:full":"1000 Gamma Dr Pittsburgh PA 15238",
    "addr:housenumber":"1000",
    "addr:postcode":"15238",
    "addr:street":"Gamma Dr",
    "iso:country":"US",
    "sg:address":"1000 Gamma Dr",
    "sg:city":"Pittsburgh",
    "sg:classifiers":[
        {
            "category":"Health Services",
            "subcategory":"Health Practitioner",
            "type":"Services"
        }
    ],
    "sg:phone":"+1 412 967 1130",
    "sg:postcode":"15238",
    "sg:province":"PA",
    "sg:tags":[
        "psychologist"
    ],
    "sg:website":"www.pci-pmr.com",
    "wof:name":"PCI",
    "wof:placetype":"venue"
},
  "geometry": {"coordinates":[-79.86143800000001,40.501144],"type":"Point"}
}