{
  "type": "Feature",
  "properties": {
    "addr:full":"1640 Wolf St Philadelphia PA 19145",
    "addr:housenumber":"1640",
    "addr:postcode":"19145",
    "addr:street":"Wolf St",
    "iso:country":"US",
    "sg:address":"1640 Wolf St",
    "sg:city":"Philadelphia",
    "sg:classifiers":[
        {
            "category":"Personal",
            "subcategory":"Beauty Salon",
            "type":"Services"
        }
    ],
    "sg:phone":"+1 215 339 9760",
    "sg:postcode":"19145",
    "sg:province":"PA",
    "sg:tags":[
        "shop"
    ],
    "wof:name":"Studio 17",
    "wof:placetype":"venue"
},
  "geometry": {"coordinates":[-75.174998,39.922423],"type":"Point"}
}