{
  "type": "Feature",
  "properties": {
    "iso:country":"US",
    "sg:address":"28 N 10th St",
    "sg:city":"Allentown",
    "sg:classifiers":[
        {
            "category":"Mining & Drilling",
            "type":"Manufacturing & Wholesale Goods"
        }
    ],
    "sg:phone":"+1 610 740 0263",
    "sg:postcode":"18101",
    "sg:province":"PA",
    "sg:tags":[
        "stone"
    ],
    "wof:name":"Tenth Street Stone Wall Modem",
    "wof:placetype":"venue"
},
  "geometry": {"coordinates":[-75.478662,40.601853],"type":"Point"}
}