{
  "type": "Feature",
  "properties": {
    "iso:country":"US",
    "sg:address":"342 Bryant Dr",
    "sg:city":"Pittsburgh",
    "sg:classifiers":[
        {
            "category":"Professional",
            "type":"Services"
        }
    ],
    "sg:phone":"+1 412 798 8780",
    "sg:postcode":"15235",
    "sg:province":"PA",
    "sg:tags":[
        "establishment"
    ],
    "wof:name":"Dpmcusa",
    "wof:placetype":"venue"
},
  "geometry": {"coordinates":[-79.812085,40.456702],"type":"Point"}
}