{
  "type": "Feature",
  "properties": {
    "addr:full":"4610 N Broad St Philadelphia PA 19140",
    "addr:housenumber":"4610",
    "addr:postcode":"19140",
    "addr:street":"N Broad St",
    "iso:country":"US",
    "sg:address":"4610 N Broad St",
    "sg:city":"Philadelphia",
    "sg:classifiers":[
        {
            "category":"Restaurant",
            "type":"Food & Drink"
        }
    ],
    "sg:phone":"+1 215 324 5552",
    "sg:postcode":"19140",
    "sg:province":"PA",
    "sg:tags":[
        "out"
    ],
    "wof:name":"Bob & Stan Rib House",
    "wof:placetype":"venue"
},
  "geometry": {"coordinates":[-75.14799499999999,40.024403],"type":"Point"}
}