{
  "type": "Feature",
  "properties": {
    "iso:country":"US",
    "sg:address":"325 Maple Ave",
    "sg:city":"Hanover",
    "sg:classifiers":[
        {
            "category":"Freight",
            "type":"Transportation"
        }
    ],
    "sg:phone":"+1 717 630 0700",
    "sg:postcode":"17331",
    "sg:province":"PA",
    "sg:tags":[
        "trucking"
    ],
    "wof:name":"Hanover Intermodal Transport",
    "wof:placetype":"venue"
},
  "geometry": {"coordinates":[-76.99617600000001,39.807787],"type":"Point"}
}