{
  "type": "Feature",
  "properties": {
    "iso:country":"US",
    "sg:address":"702 Homestead St",
    "sg:city":"Carbondale",
    "sg:classifiers":[
        {
            "category":"Government",
            "subcategory":"Fire Station",
            "type":"Public Place"
        }
    ],
    "sg:phone":"+1   ",
    "sg:postcode":"18407",
    "sg:province":"PA",
    "sg:tags":[
        "dept",
        "volunteer"
    ],
    "wof:name":"Grattan Singer Hose Comp 1",
    "wof:placetype":"venue"
},
  "geometry": {"coordinates":[-75.482974,41.594242],"type":"Point"}
}