{
  "type": "Feature",
  "properties": {
    "iso:country":"US",
    "sg:address":"4113 Park Ln",
    "sg:city":"Aston",
    "sg:classifiers":[
        {
            "category":"Autos & Motor Vehicles",
            "subcategory":"Automobile Sales",
            "type":"Retail Goods"
        }
    ],
    "sg:phone":"+1 610 364 0123",
    "sg:postcode":"19014",
    "sg:province":"PA",
    "sg:tags":[
        "new",
        "car"
    ],
    "wof:name":"Diamond Auto Sales",
    "wof:placetype":"venue"
},
  "geometry": {"coordinates":[-75.402629,39.858664],"type":"Point"}
}