{
  "type": "Feature",
  "properties": {
    "iso:country":"US",
    "sg:address":"40 Dallas Village Shopping Ctr",
    "sg:city":"Dallas",
    "sg:classifiers":[
        {
            "category":"Health Services",
            "subcategory":"Doctor",
            "type":"Services"
        },
        {
            "category":"Health Services",
            "subcategory":"Clinic",
            "type":"Services"
        }
    ],
    "sg:phone":"+1 570 675 2000",
    "sg:postcode":"18612",
    "sg:province":"PA",
    "sg:tags":[
        "physician",
        "surgeon",
        "osteopathic"
    ],
    "wof:name":"Kovalick Michael DO",
    "wof:placetype":"venue"
},
  "geometry": {"coordinates":[-75.953182,41.332152],"type":"Point"}
}