{
  "type": "Feature",
  "properties": {
    "iso:country":"US",
    "sg:address":"500 Airport Rd",
    "sg:city":"Lititz",
    "sg:classifiers":[
        {
            "category":"Building & Trades",
            "subcategory":"Equipment Rental",
            "type":"Services"
        },
        {
            "category":"Education",
            "subcategory":"Special Training",
            "type":"Public Place"
        }
    ],
    "sg:phone":"+1 717 569 4775",
    "sg:postcode":"17543",
    "sg:province":"PA",
    "sg:tags":[
        "leasing",
        "charter",
        "flight",
        "aircraft"
    ],
    "wof:name":"Advantage Aero Inc",
    "wof:placetype":"venue"
},
  "geometry": {"coordinates":[-76.294189,40.11586],"type":"Point"}
}