{
  "type": "Feature",
  "properties": {
    "iso:country":"US",
    "sg:address":"23 S 5th St",
    "sg:city":"Emmaus",
    "sg:classifiers":[
        {
            "category":"Recreation",
            "type":"Entertainment"
        }
    ],
    "sg:phone":"+1   ",
    "sg:postcode":"18049",
    "sg:province":"PA",
    "sg:tags":[
        "club",
        "membership"
    ],
    "wof:name":"East Penn Model Railroad Club",
    "wof:placetype":"venue"
},
  "geometry": {"coordinates":[-75.49196499999999,40.532556],"type":"Point"}
}