{
  "type": "Feature",
  "properties": {
    "iso:country":"US",
    "sg:address":"84 Allentown Rd",
    "sg:city":"Souderton",
    "sg:classifiers":[
        {
            "category":"Retail",
            "subcategory":"Repair Shop",
            "type":"Services"
        }
    ],
    "sg:phone":"+1 215 721 9522",
    "sg:postcode":"18964",
    "sg:province":"PA",
    "sg:tags":[
        "fabrication",
        "welding"
    ],
    "sg:website":"www.gouldey.com",
    "wof:name":"Gouldey Welding & Fabrications",
    "wof:placetype":"venue"
},
  "geometry": {"coordinates":[-75.33578199999999,40.280495],"type":"Point"}
}