{
  "type": "Feature",
  "properties": {
    "iso:country":"US",
    "sg:address":"405 6th St",
    "sg:city":"Wendel",
    "sg:classifiers":[
        {
            "category":"Organizations",
            "subcategory":"Religious Organization",
            "type":"Services"
        }
    ],
    "sg:phone":"+1 724 863 7405",
    "sg:postcode":"15642",
    "sg:province":"PA",
    "sg:tags":[
        "church"
    ],
    "wof:name":"West Hempfield Baptist Church",
    "wof:placetype":"venue"
},
  "geometry": {"coordinates":[-79.70780600000001,40.330303],"type":"Point"}
}