{
  "type": "Feature",
  "properties": {
    "addr:full":"326a N Chester Pike  Glenolden PA 19036",
    "addr:housenumber":"326a",
    "addr:postcode":"19036",
    "addr:street":"N Chester Pike",
    "iso:country":"US",
    "sg:address":"326a N Chester Pike ",
    "sg:city":"Glenolden",
    "sg:classifiers":[
        {
            "category":"Restaurant",
            "type":"Food & Drink"
        }
    ],
    "sg:menulink":"http://www.allmenus.com/pa/glenolden/291566-hong-kong-restaurant/menu/",
    "sg:phone":"+1 610 461 5370",
    "sg:postcode":"19036",
    "sg:province":"PA",
    "sg:tags":[
        "soup",
        "seafood",
        "chicken"
    ],
    "wof:name":"Hong Kong Restaurant",
    "wof:placetype":"venue"
},
  "geometry": {"coordinates":[-75.283963,39.903227],"type":"Point"}
}