{
  "type": "Feature",
  "properties": {
    "iso:country":"US",
    "sg:address":"5900 Library Rd",
    "sg:city":"Bethel Park",
    "sg:classifiers":[
        {
            "category":"Professional",
            "type":"Services"
        }
    ],
    "sg:phone":"+1 412 835 6855",
    "sg:postcode":"15102",
    "sg:province":"PA",
    "wof:name":"Kingschool Service",
    "wof:placetype":"venue"
},
  "geometry": {"coordinates":[-80.032088,40.306651],"type":"Point"}
}