{
  "type": "Feature",
  "properties": {
    "iso:country":"US",
    "sg:address":"1000 Banetown Rd",
    "sg:city":"Washington",
    "sg:classifiers":[
        {
            "category":"Farming",
            "subcategory":"Livestock Farm",
            "type":"Manufacturing & Wholesale Goods"
        }
    ],
    "sg:phone":"+1   ",
    "sg:postcode":"15301",
    "sg:province":"PA",
    "wof:name":"Phelan Farms",
    "wof:placetype":"venue"
},
  "geometry": {"coordinates":[-80.23726600000001,40.084614],"type":"Point"}
}