{
  "type": "Feature",
  "properties": {
    "iso:country":"US",
    "sg:address":"100 Fellowship Rd",
    "sg:city":"Chester Springs",
    "sg:classifiers":[
        {
            "category":"Building & Trades",
            "subcategory":"Construction",
            "type":"Services"
        }
    ],
    "sg:phone":"+1 610 458 4200",
    "sg:postcode":"19425",
    "sg:province":"PA",
    "sg:tags":[
        "home",
        "builder"
    ],
    "wof:name":"Pulte Home Corp",
    "wof:placetype":"venue"
},
  "geometry": {"coordinates":[-75.689849,40.092377],"type":"Point"}
}