{
  "type": "Feature",
  "properties": {
    "iso:country":"US",
    "sg:address":"2001 N Front St",
    "sg:city":"Harrisburg",
    "sg:classifiers":[
        {
            "category":"Social Services",
            "type":"Services"
        }
    ],
    "sg:phone":"+1   ",
    "sg:postcode":"17102",
    "sg:province":"PA",
    "sg:tags":[
        "counseling",
        "health",
        "mental",
        "for"
    ],
    "wof:name":"Mosaic Partnership",
    "wof:placetype":"venue"
},
  "geometry": {"coordinates":[-76.898932,40.276614],"type":"Point"}
}