{
  "type": "Feature",
  "properties": {
    "iso:country":"US",
    "sg:address":"543 John Edward Ln",
    "sg:city":"Greensburg",
    "sg:classifiers":[
        {
            "category":"Shopping",
            "subcategory":"Clothing, Apparel, & Fashions",
            "type":"Retail Goods"
        }
    ],
    "sg:phone":"+1   ",
    "sg:postcode":"15601",
    "sg:province":"PA",
    "wof:name":"Burtons Ltd",
    "wof:placetype":"venue"
},
  "geometry": {"coordinates":[-79.517405,40.297026],"type":"Point"}
}