{
  "type": "Feature",
  "properties": {
    "iso:country":"US",
    "sg:address":"130 Carlisle St",
    "sg:city":"Hanover",
    "sg:classifiers":[
        {
            "category":"Manufacturing",
            "subcategory":"Tools & Machinery",
            "type":"Manufacturing & Wholesale Goods"
        }
    ],
    "sg:phone":"+1 717 757 5858",
    "sg:postcode":"17331",
    "sg:province":"PA",
    "sg:tags":[
        "limb",
        "orthopedic",
        "artificial",
        "devices",
        "mfg"
    ],
    "wof:name":"Lloyd-Silber Orthopedic",
    "wof:placetype":"venue"
},
  "geometry": {"coordinates":[-76.985422,39.80231],"type":"Point"}
}