{
  "type": "Feature",
  "properties": {
    "addr:full":"201 Main St Schwenksville PA 19473",
    "addr:housenumber":"201",
    "addr:postcode":"19473",
    "addr:street":"Main St",
    "iso:country":"US",
    "sg:address":"201 Main St",
    "sg:city":"Schwenksville",
    "sg:classifiers":[
        {
            "category":"Landmark",
            "subcategory":"Historic",
            "type":"Public Place"
        }
    ],
    "sg:phone":"+1 610 489 8883",
    "sg:postcode":"19473",
    "sg:province":"PA",
    "sg:tags":[
        "building",
        "historical"
    ],
    "wof:name":"Trappe Historical Society",
    "wof:placetype":"venue"
},
  "geometry": {"coordinates":[-75.463097,40.252102],"type":"Point"}
}