{
  "type": "Feature",
  "properties": {
    "addr:full":"12 Terry Dr Newtown PA 18940",
    "addr:housenumber":"12",
    "addr:postcode":"18940",
    "addr:street":"Terry Dr",
    "iso:country":"US",
    "sg:address":"12 Terry Dr",
    "sg:city":"Newtown",
    "sg:classifiers":[
        {
            "category":"Wholesale",
            "subcategory":"Drugs",
            "type":"Manufacturing & Wholesale Goods"
        }
    ],
    "sg:phone":"+1   ",
    "sg:postcode":"18940",
    "sg:province":"PA",
    "wof:name":"Glaxosmithkline",
    "wof:placetype":"venue"
},
  "geometry": {"coordinates":[-74.917264,40.227071],"type":"Point"}
}