{
  "type": "Feature",
  "properties": {
    "iso:country":"US",
    "sg:address":"203 W King St",
    "sg:city":"Chambersburg",
    "sg:classifiers":[
        {
            "category":"Restaurant",
            "type":"Food & Drink"
        }
    ],
    "sg:phone":"+1   ",
    "sg:postcode":"17201",
    "sg:province":"PA",
    "wof:name":"Frans Inn",
    "wof:placetype":"venue"
},
  "geometry": {"coordinates":[-77.66728000000001,39.940022],"type":"Point"}
}