{
  "type": "Feature",
  "properties": {
    "iso:country":"US",
    "sg:address":"1311 Evergreen Dr",
    "sg:city":"Bethlehem",
    "sg:classifiers":[
        {
            "category":"Personal",
            "type":"Services"
        }
    ],
    "sg:phone":"+1   ",
    "sg:postcode":"18015",
    "sg:province":"PA",
    "wof:name":"Benders Home Maintenance Plus",
    "wof:placetype":"venue"
},
  "geometry": {"coordinates":[-75.39668,40.578471],"type":"Point"}
}