{
  "type": "Feature",
  "properties": {
    "iso:country":"US",
    "sg:address":"512 Northampton St",
    "sg:city":"Easton",
    "sg:classifiers":[
        {
            "category":"Retail",
            "subcategory":"Repair Shop",
            "type":"Services"
        }
    ],
    "sg:phone":"+1   ",
    "sg:postcode":"18042",
    "sg:province":"PA",
    "sg:tags":[
        "wooden",
        "re",
        "upholstered",
        "mfg"
    ],
    "wof:name":"Easton Furn & Upholstery",
    "wof:placetype":"venue"
},
  "geometry": {"coordinates":[-75.21371600000001,40.690941],"type":"Point"}
}