{
  "type": "Feature",
  "properties": {
    "iso:country":"US",
    "sg:address":"147 Main St",
    "sg:city":"Ford City",
    "sg:classifiers":[
        {
            "category":"Personal",
            "subcategory":"Barber",
            "type":"Services"
        }
    ],
    "sg:phone":"+1 724 763 7725",
    "sg:postcode":"16226",
    "sg:province":"PA",
    "wof:name":"Thomas Hromadik Barber Shop",
    "wof:placetype":"venue"
},
  "geometry": {"coordinates":[-79.523073,40.775261],"type":"Point"}
}