{
  "type": "Feature",
  "properties": {
    "iso:country":"US",
    "sg:address":"629 Pawnee St",
    "sg:city":"Bethlehem",
    "sg:classifiers":[
        {
            "category":"Professional",
            "subcategory":"Detective & Security Services",
            "type":"Services"
        }
    ],
    "sg:phone":"+1 610 625 4040",
    "sg:postcode":"18015",
    "sg:province":"PA",
    "sg:tags":[
        "control",
        "monitoring",
        "consultant",
        "system",
        "equipment",
        "guard",
        "patrol"
    ],
    "wof:name":"Patriot Security",
    "wof:placetype":"venue"
},
  "geometry": {"coordinates":[-75.387274,40.6083],"type":"Point"}
}