{
  "type": "Feature",
  "properties": {
    "iso:country":"US",
    "sg:address":"101 Municipal Rd",
    "sg:city":"Orwigsburg",
    "sg:classifiers":[
        {
            "category":"Professional",
            "subcategory":"Management & Consulting",
            "type":"Services"
        }
    ],
    "sg:phone":"+1 570 366 1940",
    "sg:postcode":"17961",
    "sg:province":"PA",
    "sg:tags":[
        "business"
    ],
    "wof:name":"Ludgate Engineering Corp",
    "wof:placetype":"venue"
},
  "geometry": {"coordinates":[-76.055635,40.635701],"type":"Point"}
}