{
  "type": "Feature",
  "properties": {
    "iso:country":"US",
    "sg:address":"55 Pottstown Pike",
    "sg:city":"Chester Springs",
    "sg:classifiers":[
        {
            "category":"Wholesale",
            "subcategory":"Stationery",
            "type":"Manufacturing & Wholesale Goods"
        }
    ],
    "sg:phone":"+1 610 321 1779",
    "sg:postcode":"19425",
    "sg:province":"PA",
    "sg:tags":[
        "business",
        "form",
        "system"
    ],
    "wof:name":"Commonwealth Business Systems",
    "wof:placetype":"venue"
},
  "geometry": {"coordinates":[-75.685641,40.075638],"type":"Point"}
}