{
  "type": "Feature",
  "properties": {
    "iso:country":"US",
    "sg:address":"6795 Keefers Ln",
    "sg:city":"Bloomsburg",
    "sg:classifiers":[
        {
            "category":"Personal",
            "subcategory":"Beauty Salon",
            "type":"Services"
        }
    ],
    "sg:phone":"+1 570 380 1300",
    "sg:postcode":"17815",
    "sg:province":"PA",
    "wof:name":"Eden Spa & Salon",
    "wof:placetype":"venue"
},
  "geometry": {"coordinates":[-76.362019,41.034082],"type":"Point"}
}