{
  "type": "Feature",
  "properties": {
    "iso:country":"US",
    "sg:address":"50 Mark Ave",
    "sg:city":"Washington",
    "sg:classifiers":[
        {
            "category":"Real Estate",
            "subcategory":"Real Estate Operator",
            "type":"Services"
        }
    ],
    "sg:phone":"+1   ",
    "sg:postcode":"15301",
    "sg:province":"PA",
    "sg:tags":[
        "mobile",
        "home",
        "site"
    ],
    "wof:name":"Mark II Mobile Home Park",
    "wof:placetype":"venue"
},
  "geometry": {"coordinates":[-80.29168799999999,40.193412],"type":"Point"}
}