{
  "type": "Feature",
  "properties": {
    "iso:country":"US",
    "sg:address":"208 High St",
    "sg:city":"Williamsburg",
    "sg:classifiers":[
        {
            "category":"Shopping",
            "subcategory":"Clothing, Apparel, & Fashions",
            "type":"Retail Goods"
        }
    ],
    "sg:phone":"+1 814 832 3003",
    "sg:postcode":"16693",
    "sg:province":"PA",
    "sg:tags":[
        "salvage",
        "surplus",
        "merchandise"
    ],
    "wof:name":"Williamsburg Surplus",
    "wof:placetype":"venue"
},
  "geometry": {"coordinates":[-78.20152299999999,40.461116],"type":"Point"}
}