{
  "type": "Feature",
  "properties": {
    "addr:full":"1693 Bradshaw Rd Warfordsburg PA 17267",
    "addr:housenumber":"1693",
    "addr:postcode":"17267",
    "addr:street":"Bradshaw Rd",
    "iso:country":"US",
    "sg:address":"1693 Bradshaw Rd",
    "sg:city":"Warfordsburg",
    "sg:classifiers":[
        {
            "category":"Home & Garden",
            "subcategory":"Hardware",
            "type":"Retail Goods"
        }
    ],
    "sg:phone":"+1   ",
    "sg:postcode":"17267",
    "sg:province":"PA",
    "wof:name":"Mister Hardware",
    "wof:placetype":"venue"
},
  "geometry": {"coordinates":[-78.181653,39.835711],"type":"Point"}
}