{
  "type": "Feature",
  "properties": {
    "iso:country":"US",
    "sg:address":"817 Washington Ave",
    "sg:city":"Charleroi",
    "sg:classifiers":[
        {
            "category":"Organizations",
            "subcategory":"Membership Organization",
            "type":"Services"
        }
    ],
    "sg:phone":"+1 724 483 8448",
    "sg:postcode":"15022",
    "sg:province":"PA",
    "sg:tags":[
        "athletic"
    ],
    "wof:name":"Charleroi Cougar Booster Club",
    "wof:placetype":"venue"
},
  "geometry": {"coordinates":[-79.90263400000001,40.140762],"type":"Point"}
}