{
  "type": "Feature",
  "properties": {
    "addr:full":"1519 Isaacs Ct Ambler PA 19002",
    "addr:housenumber":"1519",
    "addr:postcode":"19002",
    "addr:street":"Isaacs Ct",
    "iso:country":"US",
    "sg:address":"1519 Isaacs Ct",
    "sg:city":"Ambler",
    "sg:classifiers":[
        {
            "category":"Wholesale",
            "subcategory":"Machinery & Supplies",
            "type":"Manufacturing & Wholesale Goods"
        }
    ],
    "sg:phone":"+1   ",
    "sg:postcode":"19002",
    "sg:province":"PA",
    "sg:tags":[
        "construction"
    ],
    "wof:name":"R A McLane Inc",
    "wof:placetype":"venue"
},
  "geometry": {"coordinates":[-75.164338,40.163909],"type":"Point"}
}