{
  "type": "Feature",
  "properties": {
    "iso:country":"US",
    "sg:address":"285 E Fairview Ave",
    "sg:city":"Connellsville",
    "sg:classifiers":[
        {
            "category":"Professional",
            "subcategory":"Lawyer & Legal Services",
            "type":"Services"
        }
    ],
    "sg:phone":"+1 724 628 2060",
    "sg:postcode":"15425",
    "sg:province":"PA",
    "wof:name":"Fairview Aid Society",
    "wof:placetype":"venue"
},
  "geometry": {"coordinates":[-79.58189400000001,40.019913],"type":"Point"}
}