{
  "type": "Feature",
  "properties": {
    "iso:country":"US",
    "sg:address":"2721 Reading Rd",
    "sg:city":"Allentown",
    "sg:classifiers":[
        {
            "category":"Professional",
            "subcategory":"Computer Services",
            "type":"Services"
        }
    ],
    "sg:phone":"+1 484 809 3425",
    "sg:postcode":"18104",
    "sg:province":"PA",
    "sg:tags":[
        "repair"
    ],
    "wof:name":"Thompson's PC Repair",
    "wof:placetype":"venue"
},
  "geometry": {"coordinates":[-75.511775,40.587871],"type":"Point"}
}