{
  "type": "Feature",
  "properties": {
    "iso:country":"US",
    "sg:address":"757 Poplar Church Rd",
    "sg:city":"Camp Hill",
    "sg:classifiers":[
        {
            "category":"Professional",
            "subcategory":"Management & Consulting",
            "type":"Services"
        }
    ],
    "sg:phone":"+1   ",
    "sg:postcode":"17011",
    "sg:province":"PA",
    "sg:tags":[
        "business"
    ],
    "wof:name":"William L Goldfarb Foundation",
    "wof:placetype":"venue"
},
  "geometry": {"coordinates":[-76.919004,40.258265],"type":"Point"}
}