{
  "type": "Feature",
  "properties": {
    "iso:country":"US",
    "sg:address":"1200 Columbia Ave",
    "sg:city":"Sinking Spring",
    "sg:classifiers":[
        {
            "category":"Freight",
            "type":"Transportation"
        }
    ],
    "sg:phone":"+1 610 678 4830",
    "sg:postcode":"19608",
    "sg:province":"PA",
    "sg:tags":[
        "dry",
        "bulk",
        "trucking"
    ],
    "wof:name":"Penn Tank Lines",
    "wof:placetype":"venue"
},
  "geometry": {"coordinates":[-76.030585,40.316585],"type":"Point"}
}