{
  "type": "Feature",
  "properties": {
    "addr:full":"1417 Clayton Rd Lancaster PA 17603",
    "addr:housenumber":"1417",
    "addr:postcode":"17603",
    "addr:street":"Clayton Rd",
    "iso:country":"US",
    "sg:address":"1417 Clayton Rd",
    "sg:city":"Lancaster",
    "sg:classifiers":[
        {
            "category":"Professional",
            "subcategory":"Business Services",
            "type":"Services"
        }
    ],
    "sg:phone":"+1   ",
    "sg:postcode":"17603",
    "sg:province":"PA",
    "wof:name":"Heisler Interior Design",
    "wof:placetype":"venue"
},
  "geometry": {"coordinates":[-76.334869,40.052793],"type":"Point"}
}