{
  "type": "Feature",
  "properties": {
    "iso:country":"US",
    "sg:address":"512 Oakland Ave",
    "sg:city":"Johnstown",
    "sg:classifiers":[
        {
            "category":"Restaurant",
            "type":"Food & Drink"
        }
    ],
    "sg:phone":"+1 814 266 5552",
    "sg:postcode":"15902",
    "sg:province":"PA",
    "wof:name":"J R's Sports Den Restaurant",
    "wof:placetype":"venue"
},
  "geometry": {"coordinates":[-78.890478,40.2997],"type":"Point"}
}