{
  "type": "Feature",
  "properties": {
    "iso:country":"US",
    "sg:address":"1940 E Pacific St",
    "sg:city":"Philadelphia",
    "sg:classifiers":[
        {
            "category":"Professional",
            "type":"Services"
        }
    ],
    "sg:phone":"+1   ",
    "sg:postcode":"19134",
    "sg:province":"PA",
    "wof:name":"PC Based Systems",
    "wof:placetype":"venue"
},
  "geometry": {"coordinates":[-75.100616,40.000352],"type":"Point"}
}