{
  "type": "Feature",
  "properties": {
    "iso:country":"US",
    "sg:address":"22 Fontana Ave",
    "sg:city":"Lebanon",
    "sg:classifiers":[
        {
            "category":"Organizations",
            "subcategory":"Religious Organization",
            "type":"Services"
        }
    ],
    "sg:phone":"+1 717 867 1409",
    "sg:postcode":"17042",
    "sg:province":"PA",
    "sg:tags":[
        "church"
    ],
    "wof:name":"Fontana Union Chapel",
    "wof:placetype":"venue"
},
  "geometry": {"coordinates":[-76.499128,40.285294],"type":"Point"}
}