{
  "type": "Feature",
  "properties": {
    "addr:full":"139 S Main St Doylestown PA 18901",
    "addr:housenumber":"139",
    "addr:postcode":"18901",
    "addr:street":"S Main St",
    "iso:country":"US",
    "sg:address":"139 S Main St",
    "sg:city":"Doylestown",
    "sg:classifiers":[
        {
            "category":"Personal",
            "subcategory":"Beauty Salon",
            "type":"Services"
        }
    ],
    "sg:phone":"+1 215 340 2220",
    "sg:postcode":"18901",
    "sg:province":"PA",
    "sg:website":"www.annodamspa.com",
    "wof:name":"Seedlings Salon",
    "wof:placetype":"venue"
},
  "geometry": {"coordinates":[-75.129328,40.307742],"type":"Point"}
}