{
  "type": "Feature",
  "properties": {
    "iso:country":"US",
    "sg:address":"134 Wirtz Aly",
    "sg:city":"Girard",
    "sg:classifiers":[
        {
            "category":"Freight",
            "type":"Transportation"
        }
    ],
    "sg:phone":"+1 814 774 0808",
    "sg:postcode":"16417",
    "sg:province":"PA",
    "wof:name":"Extra Mile Transportation LLC",
    "wof:placetype":"venue"
},
  "geometry": {"coordinates":[-80.31944,42.000282],"type":"Point"}
}