{
  "type": "Feature",
  "properties": {
    "iso:country":"US",
    "sg:address":"8 East Broad Street",
    "sg:city":"Hatfield",
    "sg:classifiers":[
        {
            "category":"Professional",
            "type":"Services"
        }
    ],
    "sg:phone":"+1 215 368 5806",
    "sg:postcode":"19440",
    "sg:province":"PA",
    "sg:website":"www.kcba-architects.com",
    "wof:name":"KCBA Architects",
    "wof:placetype":"venue"
},
  "geometry": {"coordinates":[-75.299232,40.279793],"type":"Point"}
}