{
  "type": "Feature",
  "properties": {
    "iso:country":"US",
    "sg:address":"226 Greater Butler Mart",
    "sg:city":"Butler",
    "sg:classifiers":[
        {
            "category":"Social Services",
            "type":"Services"
        }
    ],
    "sg:phone":"+1 724 287 8682",
    "sg:postcode":"16001",
    "sg:province":"PA",
    "sg:tags":[
        "organization",
        "welfare"
    ],
    "wof:name":"St Vincent Depaul Society",
    "wof:placetype":"venue"
},
  "geometry": {"coordinates":[-79.91656999999999,40.843141],"type":"Point"}
}