{
  "type": "Feature",
  "properties": {
    "addr:full":"225 Bridge St Catasauqua PA 18032",
    "addr:housenumber":"225",
    "addr:postcode":"18032",
    "addr:street":"Bridge St",
    "iso:country":"US",
    "sg:address":"225 Bridge St",
    "sg:city":"Catasauqua",
    "sg:classifiers":[
        {
            "category":"Manufacturing",
            "subcategory":"Tools & Machinery",
            "type":"Manufacturing & Wholesale Goods"
        }
    ],
    "sg:phone":"+1 610 266 1830",
    "sg:postcode":"18032",
    "sg:province":"PA",
    "sg:tags":[
        "charity",
        "membership",
        "industrial",
        "mfg"
    ],
    "wof:name":"Volunteer Firemens Relief",
    "wof:placetype":"venue"
},
  "geometry": {"coordinates":[-75.472674,40.654677],"type":"Point"}
}