{
  "type": "Feature",
  "properties": {
    "iso:country":"US",
    "sg:address":"548 N Chester Rd",
    "sg:city":"West Chester",
    "sg:classifiers":[
        {
            "category":"Manufacturing",
            "subcategory":"Metals",
            "type":"Manufacturing & Wholesale Goods"
        }
    ],
    "sg:phone":"+1 610 696 3211",
    "sg:postcode":"19380",
    "sg:province":"PA",
    "sg:tags":[
        "engraver"
    ],
    "wof:name":"Bireleys Engraving Inc",
    "wof:placetype":"venue"
},
  "geometry": {"coordinates":[-75.537955,39.979072],"type":"Point"}
}