{
  "type": "Feature",
  "properties": {
    "iso:country":"US",
    "sg:address":"432 E Smith St",
    "sg:city":"Corry",
    "sg:classifiers":[
        {
            "category":"Utilities",
            "subcategory":"Natural Gas",
            "type":"Services"
        }
    ],
    "sg:phone":"+1   ",
    "sg:postcode":"16407",
    "sg:province":"PA",
    "wof:name":"National Fuel Gas Dist Corp",
    "wof:placetype":"venue"
},
  "geometry": {"coordinates":[-79.635926,41.925125],"type":"Point"}
}