{
  "type": "Feature",
  "properties": {
    "iso:country":"US",
    "sg:address":"678 Daisy Ln",
    "sg:city":"Pennsburg",
    "sg:classifiers":[
        {
            "category":"Professional",
            "subcategory":"Detective & Security Services",
            "type":"Services"
        }
    ],
    "sg:phone":"+1 215 679 6783",
    "sg:postcode":"18073",
    "sg:province":"PA",
    "sg:tags":[
        "information",
        "bureau"
    ],
    "wof:name":"Snyder's Ebay Services",
    "wof:placetype":"venue"
},
  "geometry": {"coordinates":[-75.49618,40.391896],"type":"Point"}
}