{
  "type": "Feature",
  "properties": {
    "addr:full":"92 E Main St Uniontown PA 15401",
    "addr:housenumber":"92",
    "addr:postcode":"15401",
    "addr:street":"E Main St",
    "iso:country":"US",
    "sg:address":"92 E Main St",
    "sg:city":"Uniontown",
    "sg:classifiers":[
        {
            "category":"Professional",
            "subcategory":"Lawyer & Legal Services",
            "type":"Services"
        }
    ],
    "sg:phone":"+1 724 438 2544",
    "sg:postcode":"15401",
    "sg:province":"PA",
    "sg:tags":[
        "attorney"
    ],
    "wof:name":"Margolis George & Port",
    "wof:placetype":"venue"
},
  "geometry": {"coordinates":[-79.72192099999999,39.900881],"type":"Point"}
}