{
  "type": "Feature",
  "properties": {
    "iso:country":"US",
    "sg:address":"851 Brandywine Rd",
    "sg:city":"Downingtown",
    "sg:classifiers":[
        {
            "category":"Building & Trades",
            "subcategory":"Construction",
            "type":"Services"
        }
    ],
    "sg:phone":"+1   ",
    "sg:postcode":"19335",
    "sg:province":"PA",
    "sg:tags":[
        "house"
    ],
    "wof:name":"Martin Jim General Contractor",
    "wof:placetype":"venue"
},
  "geometry": {"coordinates":[-75.658135,39.989064],"type":"Point"}
}