{
  "type": "Feature",
  "properties": {
    "addr:full":"2840 Chestnut Rd Elizabethtown PA 17022",
    "addr:housenumber":"2840",
    "addr:postcode":"17022",
    "addr:street":"Chestnut Rd",
    "iso:country":"US",
    "sg:address":"2840 Chestnut Rd",
    "sg:city":"Elizabethtown",
    "sg:classifiers":[
        {
            "category":"Utilities",
            "subcategory":"Refuse",
            "type":"Services"
        }
    ],
    "sg:phone":"+1 717 689 0153",
    "sg:postcode":"17022",
    "sg:province":"PA",
    "sg:tags":[
        "truck",
        "dump"
    ],
    "wof:name":"C.D. & Sons Trucking",
    "wof:placetype":"venue"
},
  "geometry": {"coordinates":[-76.64948200000001,40.229726],"type":"Point"}
}