{
  "type": "Feature",
  "properties": {
    "iso:country":"US",
    "sg:address":"425 6th Ave",
    "sg:city":"Pittsburgh",
    "sg:classifiers":[
        {
            "category":"Professional",
            "type":"Services"
        }
    ],
    "sg:phone":"+1 412 553 8995",
    "sg:postcode":"15219",
    "sg:province":"PA",
    "sg:tags":[
        "establishment"
    ],
    "wof:name":"Pugliese Associates",
    "wof:placetype":"venue"
},
  "geometry": {"coordinates":[-79.99592199999999,40.440799],"type":"Point"}
}