{
  "type": "Feature",
  "properties": {
    "iso:country":"US",
    "sg:address":"649 Lizzie Ln",
    "sg:city":"Royersford",
    "sg:classifiers":[
        {
            "category":"Education",
            "subcategory":"Vocational School",
            "type":"Public Place"
        }
    ],
    "sg:phone":"+1   ",
    "sg:postcode":"19468",
    "sg:province":"PA",
    "sg:tags":[
        "training",
        "apprentice"
    ],
    "wof:name":"Northeastern Joint",
    "wof:placetype":"venue"
},
  "geometry": {"coordinates":[-75.519406,40.182688],"type":"Point"}
}