{
  "type": "Feature",
  "properties": {
    "iso:country":"US",
    "sg:address":"910 E Emmaus Ave",
    "sg:city":"Allentown",
    "sg:classifiers":[
        {
            "category":"Social Services",
            "type":"Services"
        }
    ],
    "sg:phone":"+1 610 791 7878",
    "sg:postcode":"18103",
    "sg:province":"PA",
    "sg:website":"www.salisb.com",
    "wof:name":"Salisbury House Healthcare Inc",
    "wof:placetype":"venue"
},
  "geometry": {"coordinates":[-75.432804,40.583539],"type":"Point"}
}