{
  "type": "Feature",
  "properties": {
    "iso:country":"US",
    "sg:address":"310 W Main St",
    "sg:city":"Lansdale",
    "sg:classifiers":[
        {
            "category":"Shopping",
            "type":"Retail Goods"
        }
    ],
    "sg:phone":"+1 215 362 5009",
    "sg:postcode":"19446",
    "sg:province":"PA",
    "sg:tags":[
        "mobile",
        "memorabilia",
        "phone",
        "baseball",
        "sport",
        "card"
    ],
    "sg:website":"www.vipwireless.com",
    "wof:name":"Vip Wireless",
    "wof:placetype":"venue"
},
  "geometry": {"coordinates":[-75.286697,40.2435],"type":"Point"}
}