{
  "type": "Feature",
  "properties": {
    "iso:country":"US",
    "sg:address":"33 Spring Trl",
    "sg:city":"Fairfield",
    "sg:classifiers":[
        {
            "category":"Professional",
            "subcategory":"Lawyer & Legal Services",
            "type":"Services"
        }
    ],
    "sg:phone":"+1 717 642 8300",
    "sg:postcode":"17320",
    "sg:province":"PA",
    "sg:tags":[
        "plan"
    ],
    "wof:name":"Thomas P & Marian G Wolf",
    "wof:placetype":"venue"
},
  "geometry": {"coordinates":[-77.38495899999999,39.751844],"type":"Point"}
}