{
  "type": "Feature",
  "properties": {
    "iso:country":"US",
    "sg:address":"113 Main Street",
    "sg:city":"Tullytown",
    "sg:classifiers":[
        {
            "category":"Personal",
            "type":"Services"
        }
    ],
    "sg:phone":"+1 215 943 3500",
    "sg:postcode":"19007",
    "sg:province":"PA",
    "sg:tags":[
        "home"
    ],
    "sg:website":"www.meenanlp.com/",
    "wof:name":"Meenan Oil",
    "wof:placetype":"venue"
},
  "geometry": {"coordinates":[-74.81832799999999,40.13593],"type":"Point"}
}