{
  "type": "Feature",
  "properties": {
    "iso:country":"US",
    "sg:address":"2924 4th Ave",
    "sg:city":"Altoona",
    "sg:classifiers":[
        {
            "category":"Retail",
            "subcategory":"Portrait Studio",
            "type":"Services"
        }
    ],
    "sg:phone":"+1 814 944 4468",
    "sg:postcode":"16602",
    "sg:province":"PA",
    "sg:tags":[
        "photographer"
    ],
    "wof:name":"James Warren Photography",
    "wof:placetype":"venue"
},
  "geometry": {"coordinates":[-78.408693,40.495622],"type":"Point"}
}