{
  "type": "Feature",
  "properties": {
    "iso:country":"US",
    "sg:address":"878 Main St",
    "sg:city":"Pennsburg",
    "sg:classifiers":[
        {
            "category":"Manufacturing",
            "subcategory":"Printing",
            "type":"Manufacturing & Wholesale Goods"
        }
    ],
    "sg:phone":"+1 215 679 4133",
    "sg:postcode":"18073",
    "sg:province":"PA",
    "sg:tags":[
        "newspaper"
    ],
    "wof:name":"Upper Perkiomen Shoppers Guide",
    "wof:placetype":"venue"
},
  "geometry": {"coordinates":[-75.491968,40.390868],"type":"Point"}
}