{
  "type": "Feature",
  "properties": {
    "iso:country":"US",
    "sg:address":"423 Water St",
    "sg:city":"Johnsonburg",
    "sg:classifiers":[
        {
            "category":"Building & Trades",
            "subcategory":"Construction",
            "type":"Services"
        }
    ],
    "sg:phone":"+1   ",
    "sg:postcode":"15845",
    "sg:province":"PA",
    "sg:tags":[
        "house"
    ],
    "wof:name":"Gap Home Repair",
    "wof:placetype":"venue"
},
  "geometry": {"coordinates":[-78.686725,41.498357],"type":"Point"}
}