{
  "type": "Feature",
  "properties": {
    "iso:country":"US",
    "sg:address":"5424 William Flynn Hwy",
    "sg:city":"Gibsonia",
    "sg:classifiers":[
        {
            "category":"Home & Garden",
            "subcategory":"Home Furnishings",
            "type":"Retail Goods"
        }
    ],
    "sg:phone":"+1 724 444 0808",
    "sg:postcode":"15044",
    "sg:province":"PA",
    "sg:tags":[
        "beveled",
        "glass",
        "ornamental"
    ],
    "wof:name":"Etched In Glass",
    "wof:placetype":"venue"
},
  "geometry": {"coordinates":[-79.944063,40.620578],"type":"Point"}
}