{
  "type": "Feature",
  "properties": {
    "iso:country":"US",
    "sg:address":"2848 Saint Albans Dr",
    "sg:city":"Reading",
    "sg:classifiers":[
        {
            "category":"Place Of Worship",
            "subcategory":"Church",
            "type":"Public Place"
        },
        {
            "category":"Place Of Worship",
            "type":"Public Place"
        }
    ],
    "sg:phone":"+1 610 678 7001",
    "sg:postcode":"19608",
    "sg:province":"PA",
    "sg:tags":[
        "churches-episcopal-anglican",
        "churches-episcopal"
    ],
    "wof:name":"Saint Alban's Episcopal Church",
    "wof:placetype":"venue"
},
  "geometry": {"coordinates":[-76.007851,40.333523],"type":"Point"}
}