{
  "type": "Feature",
  "properties": {
    "addr:full":"414 Beecher Ave Cheltenham PA 19012",
    "addr:housenumber":"414",
    "addr:postcode":"19012",
    "addr:street":"Beecher Ave",
    "iso:country":"US",
    "sg:address":"414 Beecher Ave",
    "sg:city":"Cheltenham",
    "sg:classifiers":[
        {
            "category":"Organizations",
            "subcategory":"Membership Organization",
            "type":"Services"
        }
    ],
    "sg:phone":"+1   ",
    "sg:postcode":"19012",
    "sg:province":"PA",
    "wof:name":"Assn of Latin America Parents",
    "wof:placetype":"venue"
},
  "geometry": {"coordinates":[-75.09460799999999,40.065306],"type":"Point"}
}