{
  "type": "Feature",
  "properties": {
    "addr:full":"101 W High St Elizabethtown PA 17022",
    "addr:housenumber":"101",
    "addr:postcode":"17022",
    "addr:street":"W High St",
    "iso:country":"US",
    "sg:address":"101 W High St",
    "sg:city":"Elizabethtown",
    "sg:classifiers":[
        {
            "category":"Health Services",
            "subcategory":"Doctor",
            "type":"Services"
        }
    ],
    "sg:phone":"+1   ",
    "sg:postcode":"17022",
    "sg:province":"PA",
    "wof:name":"Anderson Noble D DMD",
    "wof:placetype":"venue"
},
  "geometry": {"coordinates":[-76.607468,40.150924],"type":"Point"}
}