{
  "type": "Feature",
  "properties": {
    "addr:full":"108 Fox Hill Dr Newtown PA 18940",
    "addr:housenumber":"108",
    "addr:postcode":"18940",
    "addr:street":"Fox Hill Dr",
    "iso:country":"US",
    "sg:address":"108 Fox Hill Dr",
    "sg:city":"Newtown",
    "sg:classifiers":[
        {
            "category":"Manufacturing",
            "subcategory":"Chemicals & Compounds",
            "type":"Manufacturing & Wholesale Goods"
        }
    ],
    "sg:phone":"+1 215 598 9822",
    "sg:postcode":"18940",
    "sg:province":"PA",
    "sg:tags":[
        "chemicals-wholesale",
        "manufacturer"
    ],
    "sg:website":"http://www.performanceadditives.com",
    "wof:name":"Michelman, Inc.",
    "wof:placetype":"venue"
},
  "geometry": {"coordinates":[-75.003895,40.287507],"type":"Point"}
}