{
  "type": "Feature",
  "properties": {
    "iso:country":"US",
    "sg:address":"293 Donation Rd",
    "sg:city":"Greenville",
    "sg:classifiers":[
        {
            "category":"Structure",
            "subcategory":"Office Building",
            "type":"Public Place"
        }
    ],
    "sg:phone":"+1 724 588 7011",
    "sg:postcode":"16125",
    "sg:province":"PA",
    "sg:tags":[
        "park"
    ],
    "wof:name":"Sisbro Properties",
    "wof:placetype":"venue"
},
  "geometry": {"coordinates":[-80.332335,41.392295],"type":"Point"}
}