{
  "type": "Feature",
  "properties": {
    "iso:country":"US",
    "sg:address":"7612 Fishing Creek Valley Rd",
    "sg:city":"Harrisburg",
    "sg:classifiers":[
        {
            "category":"Freight",
            "type":"Transportation"
        }
    ],
    "sg:phone":"+1   ",
    "sg:postcode":"17112",
    "sg:province":"PA",
    "sg:tags":[
        "operator",
        "trucking"
    ],
    "wof:name":"Smith Alva Transport",
    "wof:placetype":"venue"
},
  "geometry": {"coordinates":[-76.751206,40.399417],"type":"Point"}
}