{
  "type": "Feature",
  "properties": {
    "iso:country":"US",
    "sg:address":"360 W Main St",
    "sg:city":"Evans City",
    "sg:classifiers":[
        {
            "category":"Building & Trades",
            "subcategory":"Construction",
            "type":"Services"
        }
    ],
    "sg:phone":"+1   ",
    "sg:postcode":"16033",
    "sg:province":"PA",
    "sg:tags":[
        "contractor"
    ],
    "wof:name":"Top It Off Inc",
    "wof:placetype":"venue"
},
  "geometry": {"coordinates":[-80.068485,40.769704],"type":"Point"}
}