{
  "type": "Feature",
  "properties": {
    "addr:full":"16 S Kennedy Dr Mcadoo PA 18237",
    "addr:housenumber":"16",
    "addr:postcode":"18237",
    "addr:street":"S Kennedy Dr",
    "iso:country":"US",
    "sg:address":"16 S Kennedy Dr",
    "sg:city":"Mcadoo",
    "sg:classifiers":[
        {
            "category":"Organizations",
            "subcategory":"Community Association",
            "type":"Services"
        }
    ],
    "sg:phone":"+1 570 929 1740",
    "sg:postcode":"18237",
    "sg:province":"PA",
    "sg:tags":[
        "club"
    ],
    "wof:name":"Veterans Of Foreign Wars",
    "wof:placetype":"venue"
},
  "geometry": {"coordinates":[-75.99376100000001,40.901885],"type":"Point"}
}