{
  "type": "Feature",
  "properties": {
    "addr:full":"1 Evergreen Ter Uniontown PA 15401",
    "addr:housenumber":"1",
    "addr:postcode":"15401",
    "addr:street":"Evergreen Ter",
    "iso:country":"US",
    "sg:address":"1 Evergreen Ter",
    "sg:city":"Uniontown",
    "sg:classifiers":[
        {
            "category":"Organizations",
            "subcategory":"Religious Organization",
            "type":"Services"
        }
    ],
    "sg:phone":"+1 724 439 2519",
    "sg:postcode":"15401",
    "sg:province":"PA",
    "sg:tags":[
        "church"
    ],
    "wof:name":"Bible Baptist Church",
    "wof:placetype":"venue"
},
  "geometry": {"coordinates":[-79.73336999999999,39.899969],"type":"Point"}
}