{
  "type": "Feature",
  "properties": {
    "iso:country":"US",
    "sg:address":"215 E Water St",
    "sg:city":"Muncy",
    "sg:classifiers":[
        {
            "category":"Health Services",
            "subcategory":"Hospital",
            "type":"Services"
        },
        {
            "category":"Social Services",
            "subcategory":"Job Training",
            "type":"Services"
        },
        {
            "category":"Community Center",
            "type":"Public Place"
        },
        {
            "category":"Health Services",
            "subcategory":"Clinic",
            "type":"Services"
        }
    ],
    "sg:phone":"+1 570 327 8137",
    "sg:postcode":"17756",
    "sg:province":"PA",
    "sg:tags":[
        "nursing",
        "homes-skilled",
        "facility",
        "medical",
        "surgery"
    ],
    "sg:website":"http://www.shscares.org",
    "wof:name":"Muncy Valley Hospital",
    "wof:placetype":"venue"
},
  "geometry": {"coordinates":[-76.775558,41.209002],"type":"Point"}
}