{
  "type": "Feature",
  "properties": {
    "iso:country":"US",
    "sg:address":"801 Scranton Carbondale Hwy",
    "sg:city":"Eynon",
    "sg:classifiers":[
        {
            "category":"Shopping",
            "subcategory":"Clothing, Apparel, & Fashions",
            "type":"Retail Goods"
        }
    ],
    "sg:phone":"+1 570 876 4360",
    "sg:postcode":"18403",
    "sg:province":"PA",
    "sg:tags":[
        "shop",
        "bridal"
    ],
    "wof:name":"A Touch-Elegance",
    "wof:placetype":"venue"
},
  "geometry": {"coordinates":[-75.57585899999999,41.513041],"type":"Point"}
}