{
  "type": "Feature",
  "properties": {
    "iso:country":"US",
    "sg:address":"234 Pacific St",
    "sg:city":"Franklin",
    "sg:classifiers":[
        {
            "category":"Professional",
            "type":"Services"
        }
    ],
    "sg:phone":"+1 814 432 7456",
    "sg:postcode":"16323",
    "sg:province":"PA",
    "sg:tags":[
        "establishment"
    ],
    "wof:name":"Integrated Dna Tech Inc",
    "wof:placetype":"venue"
},
  "geometry": {"coordinates":[-79.837278,41.405942],"type":"Point"}
}