{
  "type": "Feature",
  "properties": {
    "iso:country":"US",
    "sg:address":"3211 Deep Creek Rd",
    "sg:city":"Perkiomenville",
    "sg:classifiers":[
        {
            "category":"Professional",
            "subcategory":"Art Services",
            "type":"Services"
        }
    ],
    "sg:phone":"+1 215 234 0821",
    "sg:postcode":"18074",
    "sg:province":"PA",
    "sg:tags":[
        "interior",
        "designer",
        "decorator"
    ],
    "wof:name":"Flabbrgasted Intr Ldscp Design",
    "wof:placetype":"venue"
},
  "geometry": {"coordinates":[-75.482686,40.323285],"type":"Point"}
}