{
  "type": "Feature",
  "properties": {
    "addr:full":"475 McCulloch Rd Shippensburg PA 17257",
    "addr:housenumber":"475",
    "addr:postcode":"17257",
    "addr:street":"Mcculloch Rd",
    "iso:country":"US",
    "sg:address":"475 McCulloch Rd",
    "sg:city":"Shippensburg",
    "sg:classifiers":[
        {
            "category":"Retail",
            "subcategory":"Auto Repair",
            "type":"Services"
        }
    ],
    "sg:phone":"+1   ",
    "sg:postcode":"17257",
    "sg:province":"PA",
    "sg:tags":[
        "general"
    ],
    "wof:name":"Ricks Garage",
    "wof:placetype":"venue"
},
  "geometry": {"coordinates":[-77.499263,40.018353],"type":"Point"}
}