{
  "type": "Feature",
  "properties": {
    "addr:full":"2880 Table Rock Rd Biglerville PA 17307",
    "addr:housenumber":"2880",
    "addr:postcode":"17307",
    "addr:street":"Table Rock Rd",
    "iso:country":"US",
    "sg:address":"2880 Table Rock Rd",
    "sg:city":"Biglerville",
    "sg:classifiers":[
        {
            "category":"Recreation",
            "type":"Entertainment"
        }
    ],
    "sg:phone":"+1 717 677 9413",
    "sg:postcode":"17307",
    "sg:province":"PA",
    "sg:tags":[
        "attraction",
        "tourist"
    ],
    "wof:name":"National Apple Harvest Fstvl",
    "wof:placetype":"venue"
},
  "geometry": {"coordinates":[-77.232371,39.921878],"type":"Point"}
}