{
  "type": "Feature",
  "properties": {
    "addr:full":"44 McGovern Blvd Glenwillard PA 15046",
    "addr:housenumber":"44",
    "addr:postcode":"15046",
    "addr:street":"Mcgovern Blvd",
    "iso:country":"US",
    "sg:address":"44 McGovern Blvd",
    "sg:city":"Glenwillard",
    "sg:classifiers":[
        {
            "category":"Retail",
            "subcategory":"Car Wash",
            "type":"Services"
        }
    ],
    "sg:phone":"+1 724 457 0334",
    "sg:postcode":"15046",
    "sg:province":"PA",
    "sg:tags":[
        "automobile",
        "detail",
        "clean"
    ],
    "wof:name":"Us Ideaz's Inc",
    "wof:placetype":"venue"
},
  "geometry": {"coordinates":[-80.218941,40.546434],"type":"Point"}
}