{
  "type": "Feature",
  "properties": {
    "iso:country":"US",
    "sg:address":"909 Walnut St",
    "sg:city":"Philadelphia",
    "sg:classifiers":[
        {
            "category":"Health Services",
            "subcategory":"Doctor",
            "type":"Services"
        }
    ],
    "sg:phone":"+1 215 955 6822",
    "sg:postcode":"19107",
    "sg:province":"PA",
    "sg:tags":[
        "physician",
        "surgeon"
    ],
    "wof:name":"Kollros Peter R MD",
    "wof:placetype":"venue"
},
  "geometry": {"coordinates":[-75.156403,39.948299],"type":"Point"}
}