{
  "type": "Feature",
  "properties": {
    "addr:full":"61 Cassatt Ave Ste 301 Berwyn PA 19312",
    "addr:housenumber":"61",
    "addr:postcode":"19312",
    "addr:street":"Cassatt Ave Ste 301",
    "iso:country":"US",
    "sg:address":"61 Cassatt Ave Ste 301",
    "sg:city":"Berwyn",
    "sg:classifiers":[
        {
            "category":"Farming",
            "subcategory":"Fish & Marine Products",
            "type":"Manufacturing & Wholesale Goods"
        },
        {
            "category":"Banks & Credit Unions",
            "subcategory":"Financial Services",
            "type":"Services"
        }
    ],
    "sg:phone":"+1 610 722 5780",
    "sg:postcode":"19312",
    "sg:province":"PA",
    "sg:tags":[
        "planning",
        "retirement",
        "profit",
        "actuary",
        "sharing",
        "plan",
        "pension"
    ],
    "wof:name":"Carson Hampson Ehrlich And Callahan",
    "wof:placetype":"venue"
},
  "geometry": {"coordinates":[-75.44341300000001,40.048882],"type":"Point"}
}