{
  "type": "Feature",
  "properties": {
    "iso:country":"US",
    "sg:address":"3617 Midvale Ave",
    "sg:city":"Philadelphia",
    "sg:classifiers":[
        {
            "category":"Banks & Credit Unions",
            "subcategory":"Bank",
            "type":"Services"
        }
    ],
    "sg:phone":"+1 215 848 9607",
    "sg:postcode":"19129",
    "sg:province":"PA",
    "sg:website":"www.nationalpennbank.com",
    "wof:name":"National Penn Bank",
    "wof:placetype":"venue"
},
  "geometry": {"coordinates":[-75.193118,40.011458],"type":"Point"}
}