{
  "type": "Feature",
  "properties": {
    "iso:country":"US",
    "sg:address":"133 6th St",
    "sg:city":"Pittsburgh",
    "sg:classifiers":[
        {
            "category":"Restaurant",
            "type":"Food & Drink"
        }
    ],
    "sg:phone":"+1 412 261 4770",
    "sg:postcode":"15222",
    "sg:province":"PA",
    "wof:name":"Salonika Gyros",
    "wof:placetype":"venue"
},
  "geometry": {"coordinates":[-80.002403,40.4436],"type":"Point"}
}