{
  "type": "Feature",
  "properties": {
    "iso:country":"US",
    "sg:address":"6391 Oxford Ave",
    "sg:city":"Philadelphia",
    "sg:classifiers":[
        {
            "category":"Retail",
            "subcategory":"Self-service Laundry",
            "type":"Services"
        }
    ],
    "sg:phone":"+1 215 743 7088",
    "sg:postcode":"19111",
    "sg:province":"PA",
    "wof:name":"Laundro Max",
    "wof:placetype":"venue"
},
  "geometry": {"coordinates":[-75.088688,40.044446],"type":"Point"}
}