{
  "type": "Feature",
  "properties": {
    "iso:country":"US",
    "sg:address":"29 Garrett Ave",
    "sg:city":"Bryn Mawr",
    "sg:classifiers":[
        {
            "category":"Organizations",
            "subcategory":"Professional Association",
            "type":"Services"
        }
    ],
    "sg:phone":"+1   ",
    "sg:postcode":"19010",
    "sg:province":"PA",
    "wof:name":"Scholarship Soley",
    "wof:placetype":"venue"
},
  "geometry": {"coordinates":[-75.333438,40.029036],"type":"Point"}
}