{
  "type": "Feature",
  "properties": {
    "iso:country":"US",
    "sg:address":"915 Spring Garden St",
    "sg:city":"Philadelphia",
    "sg:classifiers":[
        {
            "category":"Building & Trades",
            "subcategory":"Construction",
            "type":"Services"
        }
    ],
    "sg:phone":"+1 215 923 3746",
    "sg:postcode":"19123",
    "sg:province":"PA",
    "sg:tags":[
        "designer"
    ],
    "wof:name":"Jeanne Adams Designs",
    "wof:placetype":"venue"
},
  "geometry": {"coordinates":[-75.153592,39.961748],"type":"Point"}
}