{
  "type": "Feature",
  "properties": {
    "addr:full":"1550 Latimer St Philadelphia PA 19102",
    "addr:housenumber":"1550",
    "addr:postcode":"19102",
    "addr:street":"Latimer St",
    "iso:country":"US",
    "sg:address":"1550 Latimer St",
    "sg:city":"Philadelphia",
    "sg:classifiers":[
        {
            "category":"Real Estate",
            "subcategory":"Architect",
            "type":"Services"
        }
    ],
    "sg:phone":"+1 215 732 0526",
    "sg:postcode":"19102",
    "sg:province":"PA",
    "wof:name":"Kakos Frank Architects Registered Architect",
    "wof:placetype":"venue"
},
  "geometry": {"coordinates":[-75.167503,39.948299],"type":"Point"}
}