{
  "type": "Feature",
  "properties": {
    "iso:country":"US",
    "sg:address":"308 W George St",
    "sg:city":"Carmichaels",
    "sg:classifiers":[
        {
            "category":"Wholesale",
            "subcategory":"Auto Parts",
            "type":"Manufacturing & Wholesale Goods"
        }
    ],
    "sg:phone":"+1 724 966 9130",
    "sg:postcode":"15320",
    "sg:province":"PA",
    "wof:name":"Tratec Automotive",
    "wof:placetype":"venue"
},
  "geometry": {"coordinates":[-79.978291,39.895219],"type":"Point"}
}