{
  "type": "Feature",
  "properties": {
    "addr:full":"43 Bick Rd Fleetwood PA 19522",
    "addr:housenumber":"43",
    "addr:postcode":"19522",
    "addr:street":"Bick Rd",
    "iso:country":"US",
    "sg:address":"43 Bick Rd",
    "sg:city":"Fleetwood",
    "sg:classifiers":[
        {
            "category":"Recreation",
            "type":"Entertainment"
        }
    ],
    "sg:phone":"+1 610 987 3798",
    "sg:postcode":"19522",
    "sg:province":"PA",
    "sg:tags":[
        "hay",
        "ride"
    ],
    "wof:name":"Dutch Treat Hayrides",
    "wof:placetype":"venue"
},
  "geometry": {"coordinates":[-75.75068899999999,40.441645],"type":"Point"}
}