{
  "type": "Feature",
  "properties": {
    "iso:country":"US",
    "sg:address":"22 Creek Pkwy",
    "sg:city":"Marcus Hook",
    "sg:classifiers":[
        {
            "category":"Wholesale",
            "subcategory":"Stationery",
            "type":"Manufacturing & Wholesale Goods"
        }
    ],
    "sg:phone":"+1   ",
    "sg:postcode":"19061",
    "sg:province":"PA",
    "sg:tags":[
        "product"
    ],
    "wof:name":"Office Basics Inc",
    "wof:placetype":"venue"
},
  "geometry": {"coordinates":[-75.460657,39.854687],"type":"Point"}
}