{
  "type": "Feature",
  "properties": {
    "iso:country":"US",
    "sg:address":"1507 Waimea Dr",
    "sg:city":"Downingtown",
    "sg:classifiers":[
        {
            "category":"Building & Trades",
            "subcategory":"Landscaping Services",
            "type":"Services"
        }
    ],
    "sg:phone":"+1 610 269 6603",
    "sg:postcode":"19335",
    "sg:province":"PA",
    "sg:tags":[
        "lawn",
        "care"
    ],
    "wof:name":"Ltm Enterprises",
    "wof:placetype":"venue"
},
  "geometry": {"coordinates":[-75.720528,39.968493],"type":"Point"}
}