{
  "type": "Feature",
  "properties": {
    "iso:country":"US",
    "sg:address":"417 E Ross St",
    "sg:city":"Lancaster",
    "sg:classifiers":[
        {
            "category":"Shopping",
            "subcategory":"Hobbies, Toys, & Games",
            "type":"Retail Goods"
        }
    ],
    "sg:phone":"+1 717 509 7665",
    "sg:postcode":"17602",
    "sg:province":"PA",
    "sg:tags":[
        "toy",
        "store",
        "supply"
    ],
    "wof:name":"K S Games",
    "wof:placetype":"venue"
},
  "geometry": {"coordinates":[-76.29912400000001,40.051929],"type":"Point"}
}