{
  "type": "Feature",
  "properties": {
    "iso:country":"US",
    "sg:address":"440 Ponderosa Rd",
    "sg:city":"Carlisle",
    "sg:classifiers":[
        {
            "category":"Transit Center",
            "subcategory":"Freight",
            "type":"Transportation"
        },
        {
            "category":"Freight",
            "type":"Transportation"
        }
    ],
    "sg:phone":"+1 717 241 4882",
    "sg:postcode":"17015",
    "sg:province":"PA",
    "sg:tags":[
        "local",
        "trucking-motor",
        "trucking"
    ],
    "wof:name":"Donald L Pereschuk Trucking",
    "wof:placetype":"venue"
},
  "geometry": {"coordinates":[-77.306771,40.254888],"type":"Point"}
}