{
  "type": "Feature",
  "properties": {
    "iso:country":"US",
    "sg:address":"1036 Woodbourne Rd",
    "sg:city":"Langhorne",
    "sg:classifiers":[
        {
            "category":"Retail",
            "subcategory":"Repair Shop",
            "type":"Services"
        },
        {
            "category":"Manufacturing",
            "subcategory":"Tools & Machinery",
            "type":"Manufacturing & Wholesale Goods"
        }
    ],
    "sg:phone":"+1 215 757 1162",
    "sg:postcode":"19047",
    "sg:province":"PA",
    "sg:tags":[
        "handling",
        "supply",
        "mfg",
        "equipment",
        "aircraft",
        "industrial",
        "fuel"
    ],
    "wof:name":"Mike Barta & Sons Inc",
    "wof:placetype":"venue"
},
  "geometry": {"coordinates":[-74.893479,40.194754],"type":"Point"}
}