{
  "type": "Feature",
  "properties": {
    "addr:full":"740 W Berwick St Easton PA 18042",
    "addr:housenumber":"740",
    "addr:postcode":"18042",
    "addr:street":"W Berwick St",
    "iso:country":"US",
    "sg:address":"740 W Berwick St",
    "sg:city":"Easton",
    "sg:classifiers":[
        {
            "category":"Organizations",
            "subcategory":"Community Association",
            "type":"Services"
        },
        {
            "category":"Organizations",
            "subcategory":"Professional Association",
            "type":"Services"
        }
    ],
    "sg:phone":"+1 610 258 9201",
    "sg:postcode":"18042",
    "sg:province":"PA",
    "sg:tags":[
        "workers'",
        "placement",
        "volunteer"
    ],
    "wof:name":"Pioneer Athletic Assoc",
    "wof:placetype":"venue"
},
  "geometry": {"coordinates":[-75.221665,40.678288],"type":"Point"}
}