{
  "type": "Feature",
  "properties": {
    "addr:full":"3117 W Ridge Pike Pottstown PA 19464",
    "addr:housenumber":"3117",
    "addr:postcode":"19464",
    "addr:street":"W Ridge Pike",
    "iso:country":"US",
    "sg:address":"3117 W Ridge Pike",
    "sg:city":"Pottstown",
    "sg:classifiers":[
        {
            "category":"Science Facility",
            "type":"Public Place"
        }
    ],
    "sg:phone":"+1 610 495 6204",
    "sg:postcode":"19464",
    "sg:province":"PA",
    "sg:tags":[
        "development",
        "laboratories-research"
    ],
    "wof:name":"Schultz Technology Solutions",
    "wof:placetype":"venue"
},
  "geometry": {"coordinates":[-75.572205,40.243689],"type":"Point"}
}