{
  "type": "Feature",
  "properties": {
    "addr:full":"51 Stevens Rd Stevens PA 17578",
    "addr:housenumber":"51",
    "addr:postcode":"17578",
    "addr:street":"Stevens Rd",
    "iso:country":"US",
    "sg:address":"51 Stevens Rd",
    "sg:city":"Stevens",
    "sg:classifiers":[
        {
            "category":"Freight",
            "type":"Transportation"
        }
    ],
    "sg:phone":"+1   ",
    "sg:postcode":"17578",
    "sg:province":"PA",
    "sg:tags":[
        "operator",
        "trucking"
    ],
    "wof:name":"Ronald Kreider",
    "wof:placetype":"venue"
},
  "geometry": {"coordinates":[-76.15016900000001,40.213547],"type":"Point"}
}