{
  "type": "Feature",
  "properties": {
    "addr:full":"206 E 9th St Chester PA 19013",
    "addr:housenumber":"206",
    "addr:postcode":"19013",
    "addr:street":"E 9Th St",
    "iso:country":"US",
    "sg:address":"206 E 9th St",
    "sg:city":"Chester",
    "sg:classifiers":[
        {
            "category":"Health Services",
            "subcategory":"Doctor",
            "type":"Services"
        }
    ],
    "sg:phone":"+1 610 874 2460",
    "sg:postcode":"19013",
    "sg:province":"PA",
    "sg:tags":[
        "physician",
        "surgeon"
    ],
    "wof:name":"Lebita Mamerto",
    "wof:placetype":"venue"
},
  "geometry": {"coordinates":[-75.35934399999999,39.853186],"type":"Point"}
}