{
  "type": "Feature",
  "properties": {
    "iso:country":"US",
    "sg:address":"96 E Main St",
    "sg:city":"Uniontown",
    "sg:classifiers":[
        {
            "category":"Real Estate",
            "subcategory":"Real Estate Services",
            "type":"Services"
        },
        {
            "category":"Building & Trades",
            "subcategory":"Construction",
            "type":"Services"
        }
    ],
    "sg:phone":"+1 724 437 7339",
    "sg:postcode":"15401",
    "sg:province":"PA",
    "sg:tags":[
        "excavation",
        "company",
        "title",
        "abstract",
        "contractor"
    ],
    "wof:name":"Rbc Researce",
    "wof:placetype":"venue"
},
  "geometry": {"coordinates":[-79.721801,39.900819],"type":"Point"}
}