{
  "type": "Feature",
  "properties": {
    "iso:country":"US",
    "sg:address":"305 Grant St",
    "sg:city":"Olyphant",
    "sg:classifiers":[
        {
            "category":"Manufacturing",
            "subcategory":"Printing",
            "type":"Manufacturing & Wholesale Goods"
        }
    ],
    "sg:phone":"+1 570 489 0451",
    "sg:postcode":"18447",
    "sg:province":"PA",
    "sg:tags":[
        "commercial",
        "lithographic"
    ],
    "wof:name":"Mid Valley Printing",
    "wof:placetype":"venue"
},
  "geometry": {"coordinates":[-75.602215,41.469774],"type":"Point"}
}