{
  "type": "Feature",
  "properties": {
    "iso:country":"US",
    "sg:address":"2454 Mountain Ln Apt 8",
    "sg:city":"Allentown",
    "sg:classifiers":[
        {
            "category":"Real Estate",
            "subcategory":"Real Estate Services",
            "type":"Services"
        }
    ],
    "sg:phone":"+1 610 798 9877",
    "sg:postcode":"18103",
    "sg:province":"PA",
    "sg:tags":[
        "management",
        "property"
    ],
    "wof:name":"Ingram Real Estate Group",
    "wof:placetype":"venue"
},
  "geometry": {"coordinates":[-75.478801,40.558145],"type":"Point"}
}