{
  "type": "Feature",
  "properties": {
    "addr:full":"1113 Mount Vernon Ave Huntingdon PA 16652",
    "addr:housenumber":"1113",
    "addr:postcode":"16652",
    "addr:street":"Mount Vernon Ave",
    "iso:country":"US",
    "sg:address":"1113 Mount Vernon Ave",
    "sg:city":"Huntingdon",
    "sg:classifiers":[
        {
            "category":"Organizations",
            "subcategory":"Religious Organization",
            "type":"Services"
        }
    ],
    "sg:phone":"+1 814 643 0601",
    "sg:postcode":"16652",
    "sg:province":"PA",
    "sg:website":"www.midpacob.org",
    "wof:name":"Church Of The Brethren",
    "wof:placetype":"venue"
},
  "geometry": {"coordinates":[-78.029759,40.488891],"type":"Point"}
}