{
  "type": "Feature",
  "properties": {
    "addr:full":"90 W Chestnut St Washington PA 15301",
    "addr:housenumber":"90",
    "addr:postcode":"15301",
    "addr:street":"W Chestnut St",
    "iso:country":"US",
    "sg:address":"90 W Chestnut St",
    "sg:city":"Washington",
    "sg:classifiers":[
        {
            "category":"Health Services",
            "subcategory":"Doctor",
            "type":"Services"
        }
    ],
    "sg:phone":"+1 724 229 9370",
    "sg:postcode":"15301",
    "sg:province":"PA",
    "sg:tags":[
        "medical",
        "sleep",
        "treatment",
        "disorders-information"
    ],
    "wof:name":"Natalie Furgiuele Md",
    "wof:placetype":"venue"
},
  "geometry": {"coordinates":[-80.248215,40.172065],"type":"Point"}
}