{
  "type": "Feature",
  "properties": {
    "iso:country":"US",
    "sg:address":"931 N Front St",
    "sg:city":"Harrisburg",
    "sg:classifiers":[
        {
            "category":"Professional",
            "type":"Services"
        }
    ],
    "sg:phone":"+1 717 260 9690",
    "sg:postcode":"17102",
    "sg:province":"PA",
    "sg:tags":[
        "establishment"
    ],
    "wof:name":"Ajax Management",
    "wof:placetype":"venue"
},
  "geometry": {"coordinates":[-76.89098,40.265811],"type":"Point"}
}