{
  "type": "Feature",
  "properties": {
    "iso:country":"US",
    "sg:address":"1626 E Roumfort Rd",
    "sg:city":"Philadelphia",
    "sg:classifiers":[
        {
            "category":"Building & Trades",
            "subcategory":"Construction",
            "type":"Services"
        }
    ],
    "sg:phone":"+1 215 248 2442",
    "sg:postcode":"19150",
    "sg:province":"PA",
    "sg:tags":[
        "house",
        "improvement",
        "home"
    ],
    "wof:name":"Thompson Enterprises",
    "wof:placetype":"venue"
},
  "geometry": {"coordinates":[-75.174971,40.083302],"type":"Point"}
}