{
  "type": "Feature",
  "properties": {
    "addr:full":"231 N Front St Bainbridge PA 17502",
    "addr:housenumber":"231",
    "addr:postcode":"17502",
    "addr:street":"N Front St",
    "iso:country":"US",
    "sg:address":"231 N Front St",
    "sg:city":"Bainbridge",
    "sg:classifiers":[
        {
            "category":"Wholesale",
            "subcategory":"Machinery & Supplies",
            "type":"Manufacturing & Wholesale Goods"
        }
    ],
    "sg:phone":"+1 717 426 4333",
    "sg:postcode":"17502",
    "sg:province":"PA",
    "sg:tags":[
        "hair"
    ],
    "sg:website":"www.hairdirectforher.com",
    "wof:name":"Hair Direct Inc",
    "wof:placetype":"venue"
},
  "geometry": {"coordinates":[-76.670152,40.090019],"type":"Point"}
}