{
  "type": "Feature",
  "properties": {
    "iso:country":"US",
    "sg:address":"1174 Wyoming Ave",
    "sg:city":"Kingston",
    "sg:classifiers":[
        {
            "category":"Insurance",
            "subcategory":"Insurance Agent",
            "type":"Services"
        }
    ],
    "sg:phone":"+1   ",
    "sg:postcode":"18704",
    "sg:province":"PA",
    "wof:name":"Wyoming Valley Insurance Agcy",
    "wof:placetype":"venue"
},
  "geometry": {"coordinates":[-75.875141,41.282921],"type":"Point"}
}