{
  "type": "Feature",
  "properties": {
    "addr:full":"15 Sumner Ave Pittsburgh PA 15221",
    "addr:housenumber":"15",
    "addr:postcode":"15221",
    "addr:street":"Sumner Ave",
    "iso:country":"US",
    "sg:address":"15 Sumner Ave",
    "sg:city":"Pittsburgh",
    "sg:classifiers":[
        {
            "category":"Organizations",
            "subcategory":"Community Association",
            "type":"Services"
        }
    ],
    "sg:phone":"+1   ",
    "sg:postcode":"15221",
    "sg:province":"PA",
    "wof:name":"First Catholc Slovak Union U S",
    "wof:placetype":"venue"
},
  "geometry": {"coordinates":[-79.846817,40.417912],"type":"Point"}
}