{
  "type": "Feature",
  "properties": {
    "addr:full":"301 Dauphin St Lancaster PA 17602",
    "addr:housenumber":"301",
    "addr:postcode":"17602",
    "addr:street":"Dauphin St",
    "iso:country":"US",
    "sg:address":"301 Dauphin St",
    "sg:city":"Lancaster",
    "sg:classifiers":[
        {
            "category":"Social Services",
            "subcategory":"Child Care",
            "type":"Services"
        }
    ],
    "sg:phone":"+1 717 295 3471",
    "sg:postcode":"17602",
    "sg:province":"PA",
    "sg:tags":[
        "homes-children"
    ],
    "wof:name":"Fulton Shelter",
    "wof:placetype":"venue"
},
  "geometry": {"coordinates":[-76.29733299999999,40.033058],"type":"Point"}
}