{
  "type": "Feature",
  "properties": {
    "addr:full":"95 Greble Rd Jonestown PA 17038",
    "addr:housenumber":"95",
    "addr:postcode":"17038",
    "addr:street":"Greble Rd",
    "iso:country":"US",
    "sg:address":"95 Greble Rd",
    "sg:city":"Jonestown",
    "sg:classifiers":[
        {
            "category":"Manufacturing",
            "subcategory":"Buildings",
            "type":"Manufacturing & Wholesale Goods"
        },
        {
            "category":"Building & Trades",
            "subcategory":"Construction",
            "type":"Services"
        }
    ],
    "sg:phone":"+1 717 865 9321",
    "sg:postcode":"17038",
    "sg:province":"PA",
    "sg:tags":[
        "industrial",
        "system",
        "specialty",
        "builder",
        "heating",
        "contractor",
        "contractors-commercial",
        "home",
        "air conditioning"
    ],
    "sg:website":"http://www.landisbuildersinc.com",
    "wof:name":"Landis Builders Inc",
    "wof:placetype":"venue"
},
  "geometry": {"coordinates":[-76.463545,40.41642],"type":"Point"}
}