{
  "type": "Feature",
  "properties": {
    "addr:full":"8540 Bustleton Ave Philadelphia PA 19152",
    "addr:postcode":"8540;19152",
    "addr:street":"Bustleton Ave",
    "iso:country":"US",
    "sg:address":"8540 Bustleton Ave",
    "sg:city":"Philadelphia",
    "sg:classifiers":[
        {
            "category":"Communications",
            "subcategory":"Film & Video Production",
            "type":"Services"
        }
    ],
    "sg:phone":"+1 215 725 0322",
    "sg:postcode":"19152",
    "sg:province":"PA",
    "sg:tags":[
        "repair",
        "equipment-installation"
    ],
    "wof:name":"Tv Vcr Service Center",
    "wof:placetype":"venue"
},
  "geometry": {"coordinates":[-75.048304,40.07232],"type":"Point"}
}