{
  "type": "Feature",
  "properties": {
    "addr:full":"453 S Oxford Valley Rd Fairless Hills PA 19030",
    "addr:housenumber":"453",
    "addr:postcode":"19030",
    "addr:street":"S Oxford Valley Rd",
    "iso:country":"US",
    "sg:address":"453 S Oxford Valley Rd",
    "sg:city":"Fairless Hills",
    "sg:classifiers":[
        {
            "category":"Shopping",
            "subcategory":"Discount & Variety Stores",
            "type":"Retail Goods"
        }
    ],
    "sg:phone":"+1 215 547 9000",
    "sg:postcode":"19030",
    "sg:province":"PA",
    "wof:name":"Dollar Tree",
    "wof:placetype":"venue"
},
  "geometry": {"coordinates":[-74.84907800000001,40.16846],"type":"Point"}
}