{
  "type": "Feature",
  "properties": {
    "addr:full":"480 Pierce St Ste 216 Kingston PA 18704",
    "addr:housenumber":"480",
    "addr:postcode":"18704",
    "addr:street":"Pierce St Ste 216",
    "iso:country":"US",
    "sg:address":"480 Pierce St Ste 216",
    "sg:city":"Kingston",
    "sg:classifiers":[
        {
            "category":"Professional",
            "subcategory":"Lawyer & Legal Services",
            "type":"Services"
        }
    ],
    "sg:phone":"+1 570 331 2483",
    "sg:postcode":"18704",
    "sg:province":"PA",
    "sg:tags":[
        "divorce",
        "attorney",
        "practice",
        "family",
        "law"
    ],
    "wof:name":"Robert V Davison",
    "wof:placetype":"venue"
},
  "geometry": {"coordinates":[-75.883876,41.25797],"type":"Point"}
}