{
  "type": "Feature",
  "properties": {
    "iso:country":"US",
    "sg:address":"3485 W 4th St",
    "sg:city":"Williamsport",
    "sg:classifiers":[
        {
            "category":"Building & Trades",
            "subcategory":"Construction",
            "type":"Services"
        }
    ],
    "sg:phone":"+1 570 322 6737",
    "sg:postcode":"17701",
    "sg:province":"PA",
    "sg:tags":[
        "paving",
        "contractor"
    ],
    "wof:name":"HRI Inc",
    "wof:placetype":"venue"
},
  "geometry": {"coordinates":[-77.08344700000001,41.234113],"type":"Point"}
}