{
  "type": "Feature",
  "properties": {
    "iso:country":"US",
    "sg:address":"510 Lemon St",
    "sg:city":"Mc Keesport",
    "sg:classifiers":[
        {
            "category":"Building & Trades",
            "subcategory":"Construction",
            "type":"Services"
        }
    ],
    "sg:phone":"+1   ",
    "sg:postcode":"15132",
    "sg:province":"PA",
    "sg:tags":[
        "contractor"
    ],
    "wof:name":"Shawn Evans General Contractor",
    "wof:placetype":"venue"
},
  "geometry": {"coordinates":[-79.835032,40.326467],"type":"Point"}
}