{
  "type": "Feature",
  "properties": {
    "addr:full":"309 W Mine St Hazleton PA 18201",
    "addr:housenumber":"309",
    "addr:postcode":"18201",
    "addr:street":"W Mine St",
    "iso:country":"US",
    "sg:address":"309 W Mine St",
    "sg:city":"Hazleton",
    "sg:classifiers":[
        {
            "category":"Home & Garden",
            "subcategory":"Building Materials",
            "type":"Retail Goods"
        }
    ],
    "sg:phone":"+1 570 454 3141",
    "sg:postcode":"18201",
    "sg:province":"PA",
    "sg:tags":[
        "glass",
        "window",
        "plate"
    ],
    "wof:name":"Auto Glass Shop",
    "wof:placetype":"venue"
},
  "geometry": {"coordinates":[-75.98056699999999,40.95527],"type":"Point"}
}