{
  "type": "Feature",
  "properties": {
    "iso:country":"US",
    "sg:address":"153 Allen St",
    "sg:city":"Portage",
    "sg:classifiers":[
        {
            "category":"Food & Beverages",
            "subcategory":"Groceries & Convenience Stores",
            "type":"Retail Goods"
        }
    ],
    "sg:phone":"+1 814 932 4137",
    "sg:postcode":"15946",
    "sg:province":"PA",
    "wof:name":"Great Scott Hunts, Inc.",
    "wof:placetype":"venue"
},
  "geometry": {"coordinates":[-78.666675,40.376612],"type":"Point"}
}