{
  "type": "Feature",
  "properties": {
    "iso:country":"US",
    "sg:address":"636 N Irving Ave",
    "sg:city":"Scranton",
    "sg:classifiers":[
        {
            "category":"Education",
            "subcategory":"Special Training",
            "type":"Public Place"
        }
    ],
    "sg:phone":"+1 570 357 9131",
    "sg:postcode":"18510",
    "sg:province":"PA",
    "sg:tags":[
        "career",
        "counseling",
        "vocational"
    ],
    "wof:name":"Sheryl Youngblood",
    "wof:placetype":"venue"
},
  "geometry": {"coordinates":[-75.647751,41.406676],"type":"Point"}
}