{
  "type": "Feature",
  "properties": {
    "addr:full":"435 E Broad St Hazleton PA 18201",
    "addr:housenumber":"435",
    "addr:postcode":"18201",
    "addr:street":"E Broad St",
    "iso:country":"US",
    "sg:address":"435 E Broad St",
    "sg:city":"Hazleton",
    "sg:classifiers":[
        {
            "category":"Autos & Motor Vehicles",
            "subcategory":"Fuel & Gas Station",
            "type":"Retail Goods"
        }
    ],
    "sg:phone":"+1   ",
    "sg:postcode":"18201",
    "sg:province":"PA",
    "sg:tags":[
        "grocery",
        "station",
        "gasoline"
    ],
    "wof:name":"Stefanicks Mobile",
    "wof:placetype":"venue"
},
  "geometry": {"coordinates":[-75.96674400000001,40.952017],"type":"Point"}
}