{
  "type": "Feature",
  "properties": {
    "iso:country":"US",
    "sg:address":"57 Harristown Rd",
    "sg:city":"Paradise",
    "sg:classifiers":[
        {
            "category":"Professional",
            "subcategory":"Management & Consulting",
            "type":"Services"
        }
    ],
    "sg:phone":"+1   ",
    "sg:postcode":"17562",
    "sg:province":"PA",
    "sg:tags":[
        "public",
        "relations"
    ],
    "wof:name":"Penn Dutch Promotions",
    "wof:placetype":"venue"
},
  "geometry": {"coordinates":[-76.10339999999999,40.006457],"type":"Point"}
}