{
  "type": "Feature",
  "properties": {
    "iso:country":"US",
    "sg:address":"6301 Brous Ave",
    "sg:city":"Philadelphia",
    "sg:classifiers":[
        {
            "category":"Organizations",
            "subcategory":"Religious Organization",
            "type":"Services"
        }
    ],
    "sg:phone":"+1 215 535 6540",
    "sg:postcode":"19149",
    "sg:province":"PA",
    "sg:tags":[
        "church"
    ],
    "wof:name":"Westminster Mayfair Presby Chr",
    "wof:placetype":"venue"
},
  "geometry": {"coordinates":[-75.063188,40.031566],"type":"Point"}
}