{
  "type": "Feature",
  "properties": {
    "iso:country":"US",
    "sg:address":"309 Arandale St",
    "sg:city":"Bedford",
    "sg:classifiers":[
        {
            "category":"Transit Center",
            "subcategory":"Freight",
            "type":"Transportation"
        },
        {
            "category":"Freight",
            "type":"Transportation"
        }
    ],
    "sg:phone":"+1 814 623 1610",
    "sg:postcode":"15522",
    "sg:province":"PA",
    "sg:tags":[
        "local",
        "trucking-motor",
        "trucking"
    ],
    "wof:name":"Morningstar Trucking",
    "wof:placetype":"venue"
},
  "geometry": {"coordinates":[-78.495992,40.011904],"type":"Point"}
}