{
  "type": "Feature",
  "properties": {
    "addr:full":"298 N Chester Rd West Chester PA 19380",
    "addr:housenumber":"298",
    "addr:postcode":"19380",
    "addr:street":"N Chester Rd",
    "iso:country":"US",
    "sg:address":"298 N Chester Rd",
    "sg:city":"West Chester",
    "sg:classifiers":[
        {
            "category":"Shopping",
            "subcategory":"Hobbies, Toys, & Games",
            "type":"Retail Goods"
        }
    ],
    "sg:phone":"+1   ",
    "sg:postcode":"19380",
    "sg:province":"PA",
    "wof:name":"Bryans Toy Box",
    "wof:placetype":"venue"
},
  "geometry": {"coordinates":[-75.529375,39.970453],"type":"Point"}
}