{
  "type": "Feature",
  "properties": {
    "addr:full":"262 Hoffman Rd Folsom PA 19078",
    "addr:housenumber":"262",
    "addr:postcode":"19078",
    "addr:street":"Hoffman Rd",
    "iso:country":"US",
    "sg:address":"262 Hoffman Rd",
    "sg:city":"Folsom",
    "sg:classifiers":[
        {
            "category":"Building & Trades",
            "subcategory":"Plumbing",
            "type":"Services"
        }
    ],
    "sg:phone":"+1 610 237 0656",
    "sg:postcode":"19078",
    "sg:province":"PA",
    "sg:tags":[
        "conditioning",
        "air",
        "system",
        "contractor"
    ],
    "wof:name":"H R Weiss Hvac",
    "wof:placetype":"venue"
},
  "geometry": {"coordinates":[-75.31421,39.872787],"type":"Point"}
}