{
  "type": "Feature",
  "properties": {
    "iso:country":"US",
    "sg:address":"7106 Akron St",
    "sg:city":"Philadelphia",
    "sg:classifiers":[
        {
            "category":"Banks & Credit Unions",
            "subcategory":"Bank",
            "type":"Services"
        }
    ],
    "sg:phone":"+1 215 463 3424",
    "sg:postcode":"19149",
    "sg:province":"PA",
    "sg:tags":[
        "financing"
    ],
    "wof:name":"Express Equity Svc",
    "wof:placetype":"venue"
},
  "geometry": {"coordinates":[-75.062071,40.046027],"type":"Point"}
}