{
  "type": "Feature",
  "properties": {
    "addr:full":"297 E Main St Leola PA 17540",
    "addr:housenumber":"297",
    "addr:postcode":"17540",
    "addr:street":"E Main St",
    "iso:country":"US",
    "sg:address":"297 E Main St",
    "sg:city":"Leola",
    "sg:classifiers":[
        {
            "category":"Manufacturing",
            "subcategory":"Tools & Machinery",
            "type":"Manufacturing & Wholesale Goods"
        }
    ],
    "sg:phone":"+1 717 656 6032",
    "sg:postcode":"17540",
    "sg:province":"PA",
    "sg:tags":[
        "pattern",
        "wood",
        "metal",
        "maker",
        "mfg"
    ],
    "wof:name":"Steffy's Pattern Shop",
    "wof:placetype":"venue"
},
  "geometry": {"coordinates":[-76.155428,40.092208],"type":"Point"}
}