{
  "type": "Feature",
  "properties": {
    "iso:country":"US",
    "sg:address":"93 Zerby Ave",
    "sg:city":"Kingston",
    "sg:classifiers":[
        {
            "category":"Place Of Worship",
            "subcategory":"Church",
            "type":"Public Place"
        },
        {
            "category":"Place Of Worship",
            "type":"Public Place"
        }
    ],
    "sg:phone":"+1 570 283 0146",
    "sg:postcode":"18704",
    "sg:province":"PA",
    "sg:tags":[
        "churches-greek",
        "churches-eastern",
        "orthodox"
    ],
    "wof:name":"Saint John Baptist Orthodox Ch",
    "wof:placetype":"venue"
},
  "geometry": {"coordinates":[-75.903603,41.267231],"type":"Point"}
}