{
  "type": "Feature",
  "properties": {
    "iso:country":"US",
    "sg:address":"112 Glen Arbor Rd",
    "sg:city":"Havertown",
    "sg:classifiers":[
        {
            "category":"Building & Trades",
            "subcategory":"Construction",
            "type":"Services"
        }
    ],
    "sg:phone":"+1 610 789 6047",
    "sg:postcode":"19083",
    "sg:province":"PA",
    "sg:tags":[
        "home",
        "improvement"
    ],
    "wof:name":"Handyman Alliance",
    "wof:placetype":"venue"
},
  "geometry": {"coordinates":[-75.298181,39.977276],"type":"Point"}
}