{
  "type": "Feature",
  "properties": {
    "addr:full":"2941 N Front St Harrisburg PA 17110",
    "addr:housenumber":"2941",
    "addr:postcode":"17110",
    "addr:street":"N Front St",
    "iso:country":"US",
    "sg:address":"2941 N Front St",
    "sg:city":"Harrisburg",
    "sg:classifiers":[
        {
            "category":"Real Estate",
            "subcategory":"Real Estate Agent",
            "type":"Services"
        }
    ],
    "sg:phone":"+1 717 236 3909",
    "sg:postcode":"17110",
    "sg:province":"PA",
    "wof:name":"Central Penn Properties",
    "wof:placetype":"venue"
},
  "geometry": {"coordinates":[-76.905691,40.294854],"type":"Point"}
}