{
  "type": "Feature",
  "properties": {
    "addr:full":"1 School St Brodheadsville PA 18344",
    "addr:housenumber":"1",
    "addr:postcode":"18344",
    "addr:street":"School St",
    "iso:country":"US",
    "sg:address":"1 School St",
    "sg:city":"Brodheadsville",
    "sg:classifiers":[
        {
            "category":"Education",
            "subcategory":"School",
            "type":"Public Place"
        }
    ],
    "sg:phone":"+1   ",
    "sg:postcode":"18344",
    "sg:province":"PA",
    "wof:name":"Pleasant Valley High School",
    "wof:placetype":"venue"
},
  "geometry": {"coordinates":[-75.357665,41.123073],"type":"Point"}
}