{
  "type": "Feature",
  "properties": {
    "addr:full":"PO Box 2398 Cranberry Twp PA 16066",
    "addr:housenumber":"po;2398",
    "addr:postcode":"16066",
    "addr:street":"Box",
    "iso:country":"US",
    "sg:address":"PO Box 2398",
    "sg:city":"Cranberry Twp",
    "sg:classifiers":[
        {
            "category":"Autos & Motor Vehicles",
            "subcategory":"Automobile Sales",
            "type":"Retail Goods"
        },
        {
            "category":"Retail",
            "subcategory":"Auto Repair",
            "type":"Services"
        }
    ],
    "sg:phone":"+1 724 772 1177",
    "sg:postcode":"16066",
    "sg:province":"PA",
    "sg:tags":[
        "body",
        "shop",
        "car"
    ],
    "wof:name":"Premier Lincoln Mercury Inc",
    "wof:placetype":"venue"
},
  "geometry": {"coordinates":[-80.1045,40.697399],"type":"Point"}
}