{
  "type": "Feature",
  "properties": {
    "iso:country":"US",
    "sg:address":"7710 Bustleton Ave",
    "sg:city":"Philadelphia",
    "sg:classifiers":[
        {
            "category":"Health Services",
            "subcategory":"Podiatrist",
            "type":"Services"
        }
    ],
    "sg:phone":"+1 215 728 1788",
    "sg:postcode":"19152",
    "sg:province":"PA",
    "wof:name":"Arthur E Potash DPM",
    "wof:placetype":"venue"
},
  "geometry": {"coordinates":[-75.054635,40.053973],"type":"Point"}
}