{
  "type": "Feature",
  "properties": {
    "iso:country":"US",
    "sg:address":"333 N 27th St",
    "sg:city":"Camp Hill",
    "sg:classifiers":[
        {
            "category":"Professional",
            "subcategory":"Lawyer & Legal Services",
            "type":"Services"
        }
    ],
    "sg:phone":"+1 717 737 0796",
    "sg:postcode":"17011",
    "sg:province":"PA",
    "wof:name":"Beckley Thos A Atty",
    "wof:placetype":"venue"
},
  "geometry": {"coordinates":[-76.929298,40.245899],"type":"Point"}
}