{
  "type": "Feature",
  "properties": {
    "iso:country":"US",
    "sg:address":"100 Presidential Blvd",
    "sg:city":"Bala Cynwyd",
    "sg:classifiers":[
        {
            "category":"Health Services",
            "subcategory":"Doctor",
            "type":"Services"
        }
    ],
    "sg:phone":"+1 610 617 7949",
    "sg:postcode":"19004",
    "sg:province":"PA",
    "sg:website":"www.brandowclinic.com",
    "wof:name":"Brandow Kirk R MD",
    "wof:placetype":"venue"
},
  "geometry": {"coordinates":[-75.21401,40.011696],"type":"Point"}
}