{
  "type": "Feature",
  "properties": {
    "iso:country":"US",
    "sg:address":"2351 Orthodox St",
    "sg:city":"Philadelphia",
    "sg:classifiers":[
        {
            "category":"Banks & Credit Unions",
            "subcategory":"Bank",
            "type":"Services"
        }
    ],
    "sg:phone":"+1 215 288 1919",
    "sg:postcode":"19137",
    "sg:province":"PA",
    "sg:tags":[
        "federal",
        "federally",
        "chartered"
    ],
    "wof:name":"Bridesburg Federal Credit Union",
    "wof:placetype":"venue"
},
  "geometry": {"coordinates":[-75.077797,40.006199],"type":"Point"}
}