{
  "type": "Feature",
  "properties": {
    "iso:country":"US",
    "sg:address":"1679 Lincoln Hwy E",
    "sg:city":"Lancaster",
    "sg:classifiers":[
        {
            "category":"Restaurant",
            "type":"Food & Drink"
        }
    ],
    "sg:phone":"+1 717 299 1694",
    "sg:postcode":"17602",
    "sg:province":"PA",
    "sg:website":"www.lancaster-brasserie.com",
    "wof:name":"Brasserie",
    "wof:placetype":"venue"
},
  "geometry": {"coordinates":[-76.26405099999999,40.037342],"type":"Point"}
}