{
  "type": "Feature",
  "properties": {
    "iso:country":"US",
    "sg:address":"200 W Lincoln Hwy",
    "sg:city":"Coatesville",
    "sg:classifiers":[
        {
            "category":"Place Of Worship",
            "subcategory":"Church",
            "type":"Public Place"
        },
        {
            "category":"Place Of Worship",
            "type":"Public Place"
        }
    ],
    "sg:phone":"+1 610 384 1101",
    "sg:postcode":"19320",
    "sg:province":"PA",
    "sg:tags":[
        "churches-seventh-day",
        "adventist",
        "christian",
        "churches-advent"
    ],
    "sg:website":"http://www.adventist.org",
    "wof:name":"First Seventh Day Adventist Church Of Coatesville",
    "wof:placetype":"venue"
},
  "geometry": {"coordinates":[-75.829239,39.981701],"type":"Point"}
}