{
  "type": "Feature",
  "properties": {
    "iso:country":"US",
    "sg:address":"710 S Broad St",
    "sg:city":"Lititz",
    "sg:classifiers":[
        {
            "category":"Personal",
            "type":"Services"
        }
    ],
    "sg:phone":"+1 717 627 2688",
    "sg:postcode":"17543",
    "sg:province":"PA",
    "sg:tags":[
        "electrolysis"
    ],
    "wof:name":"Professional Electrology",
    "wof:placetype":"venue"
},
  "geometry": {"coordinates":[-76.305769,40.146248],"type":"Point"}
}