{
  "type": "Feature",
  "properties": {
    "iso:country":"US",
    "sg:address":"2261 Sans Souci Pkwy",
    "sg:city":"Wilkes Barre",
    "sg:classifiers":[
        {
            "category":"Utilities",
            "subcategory":"Fuel Oil & Lpg",
            "type":"Services"
        }
    ],
    "sg:phone":"+1   ",
    "sg:postcode":"18706",
    "sg:province":"PA",
    "sg:tags":[
        "dealer"
    ],
    "wof:name":"Suburban Oil Service",
    "wof:placetype":"venue"
},
  "geometry": {"coordinates":[-75.970124,41.209765],"type":"Point"}
}