{
  "type": "Feature",
  "properties": {
    "iso:country":"US",
    "sg:address":"1344 Meadow Ln",
    "sg:city":"Perkasie",
    "sg:classifiers":[
        {
            "category":"Building & Trades",
            "subcategory":"Electrical",
            "type":"Services"
        }
    ],
    "sg:phone":"+1 215 453 8761",
    "sg:postcode":"18944",
    "sg:province":"PA",
    "sg:tags":[
        "electrician"
    ],
    "wof:name":"Robert Foss Electric",
    "wof:placetype":"venue"
},
  "geometry": {"coordinates":[-75.302048,40.381926],"type":"Point"}
}