{
  "type": "Feature",
  "properties": {
    "addr:full":"15 E Butler Ave Ambler PA 19002",
    "addr:housenumber":"15",
    "addr:postcode":"19002",
    "addr:street":"E Butler Ave",
    "iso:country":"US",
    "sg:address":"15 E Butler Ave",
    "sg:city":"Ambler",
    "sg:classifiers":[
        {
            "category":"Shopping",
            "type":"Retail Goods"
        },
        {
            "category":"Education",
            "subcategory":"Special Training",
            "type":"Public Place"
        }
    ],
    "sg:phone":"+1 215 619 4757",
    "sg:postcode":"19002",
    "sg:province":"PA",
    "sg:tags":[
        "school",
        "instruction",
        "art",
        "merchandise"
    ],
    "wof:name":"Mermaid Art Studios",
    "wof:placetype":"venue"
},
  "geometry": {"coordinates":[-75.223393,40.15399],"type":"Point"}
}