{
  "type": "Feature",
  "properties": {
    "iso:country":"US",
    "sg:address":"2069 Upper Bermudian Rd",
    "sg:city":"Gardners",
    "sg:classifiers":[
        {
            "category":"Banks & Credit Unions",
            "subcategory":"Investment Brokerage",
            "type":"Services"
        }
    ],
    "sg:phone":"+1 717 528 4990",
    "sg:postcode":"17324",
    "sg:province":"PA",
    "sg:tags":[
        "consultant",
        "planning",
        "financial"
    ],
    "wof:name":"Kristine J Witherow",
    "wof:placetype":"venue"
},
  "geometry": {"coordinates":[-77.165913,39.978688],"type":"Point"}
}