{
  "type": "Feature",
  "properties": {
    "iso:country":"US",
    "sg:address":"260 N West St",
    "sg:city":"Doylestown",
    "sg:classifiers":[
        {
            "category":"Education",
            "subcategory":"School",
            "type":"Public Place"
        }
    ],
    "sg:phone":"+1 215 345 8845",
    "sg:postcode":"18901",
    "sg:province":"PA",
    "wof:name":"Doyle Elementary School",
    "wof:placetype":"venue"
},
  "geometry": {"coordinates":[-75.139387,40.309446],"type":"Point"}
}