{
  "type": "Feature",
  "properties": {
    "addr:full":"186 Wyoming St Wilkes Barre PA 18705",
    "addr:housenumber":"186",
    "addr:postcode":"18705",
    "addr:street":"Wyoming St",
    "iso:country":"US",
    "sg:address":"186 Wyoming St",
    "sg:city":"Wilkes Barre",
    "sg:classifiers":[
        {
            "category":"Home & Garden",
            "subcategory":"Household Appliances",
            "type":"Retail Goods"
        }
    ],
    "sg:phone":"+1   ",
    "sg:postcode":"18705",
    "sg:province":"PA",
    "wof:name":"Aerus Electrolux",
    "wof:placetype":"venue"
},
  "geometry": {"coordinates":[-75.869849,41.249902],"type":"Point"}
}