{
  "type": "Feature",
  "properties": {
    "iso:country":"US",
    "sg:address":"927 Kerlin St",
    "sg:city":"Chester",
    "sg:classifiers":[
        {
            "category":"Restaurant",
            "type":"Food & Drink"
        }
    ],
    "sg:phone":"+1 610 876 6474",
    "sg:postcode":"19013",
    "sg:province":"PA",
    "sg:tags":[
        "sandwich",
        "eating"
    ],
    "wof:name":"Furillo's Sandwich Shop",
    "wof:placetype":"venue"
},
  "geometry": {"coordinates":[-75.371877,39.849112],"type":"Point"}
}