{
  "type": "Feature",
  "properties": {
    "iso:country":"US",
    "sg:address":"301 South Hills Village",
    "sg:city":"Pittsburgh",
    "sg:classifiers":[
        {
            "category":"Shopping",
            "subcategory":"Beauty & Cosmetics",
            "type":"Retail Goods"
        }
    ],
    "sg:phone":"+1 412 854 1111",
    "sg:postcode":"15241",
    "sg:province":"PA",
    "sg:tags":[
        "supply"
    ],
    "sg:website":"www.sephora.com",
    "wof:name":"Sephora",
    "wof:placetype":"venue"
},
  "geometry": {"coordinates":[-80.05688000000001,40.343731],"type":"Point"}
}