{
  "type": "Feature",
  "properties": {
    "iso:country":"US",
    "sg:address":"517 S Orange St",
    "sg:city":"Media",
    "sg:classifiers":[
        {
            "category":"Health Services",
            "subcategory":"Clinic",
            "type":"Services"
        }
    ],
    "sg:phone":"+1 610 565 4947",
    "sg:postcode":"19063",
    "sg:province":"PA",
    "wof:name":"Pathways To Health Wellness",
    "wof:placetype":"venue"
},
  "geometry": {"coordinates":[-75.394243,39.913686],"type":"Point"}
}