{
  "type": "Feature",
  "properties": {
    "addr:full":"234 Mall Blvd King Of Prussia PA 19406",
    "addr:housenumber":"234",
    "addr:postcode":"19406",
    "addr:street":"Mall Blvd",
    "iso:country":"US",
    "sg:address":"234 Mall Blvd",
    "sg:city":"King Of Prussia",
    "sg:classifiers":[
        {
            "category":"Education",
            "subcategory":"Vocational School",
            "type":"Public Place"
        }
    ],
    "sg:phone":"+1   ",
    "sg:postcode":"19406",
    "sg:province":"PA",
    "sg:tags":[
        "training",
        "computer"
    ],
    "wof:name":"Professional Training Services",
    "wof:placetype":"venue"
},
  "geometry": {"coordinates":[-75.39675200000001,40.089169],"type":"Point"}
}