{
  "type": "Feature",
  "properties": {
    "iso:country":"US",
    "sg:address":"111 Sann St",
    "sg:city":"Johnstown",
    "sg:classifiers":[
        {
            "category":"Building & Trades",
            "subcategory":"Construction",
            "type":"Services"
        }
    ],
    "sg:phone":"+1 814 269 3025",
    "sg:postcode":"15904",
    "sg:province":"PA",
    "sg:tags":[
        "contractor"
    ],
    "wof:name":"M R Murray General Contractors",
    "wof:placetype":"venue"
},
  "geometry": {"coordinates":[-78.900272,40.285553],"type":"Point"}
}