{
  "type": "Feature",
  "properties": {
    "iso:country":"US",
    "sg:address":"34 W Philadelphia St",
    "sg:city":"York",
    "sg:classifiers":[
        {
            "category":"Restaurant",
            "type":"Food & Drink"
        }
    ],
    "sg:phone":"+1 717 332 2502",
    "sg:postcode":"17401",
    "sg:province":"PA",
    "sg:tags":[
        "american"
    ],
    "wof:name":"J R's Fresh Cut French Fries",
    "wof:placetype":"venue"
},
  "geometry": {"coordinates":[-76.729424,39.963579],"type":"Point"}
}