{
  "type": "Feature",
  "properties": {
    "addr:full":"177 Big Mount Rd Thomasville PA 17364",
    "addr:housenumber":"177",
    "addr:postcode":"17364",
    "addr:street":"Big Mount Rd",
    "iso:country":"US",
    "sg:address":"177 Big Mount Rd",
    "sg:city":"Thomasville",
    "sg:classifiers":[
        {
            "category":"Manufacturing",
            "subcategory":"Buildings",
            "type":"Manufacturing & Wholesale Goods"
        },
        {
            "category":"Building & Trades",
            "subcategory":"Construction",
            "type":"Services"
        }
    ],
    "sg:phone":"+1 717 965 0067",
    "sg:postcode":"17364",
    "sg:province":"PA",
    "sg:tags":[
        "home",
        "builder",
        "contractor"
    ],
    "wof:name":"W N S Construction Inc",
    "wof:placetype":"venue"
},
  "geometry": {"coordinates":[-76.89141600000001,39.924192],"type":"Point"}
}