{
  "type": "Feature",
  "properties": {
    "addr:full":"470 Sunrise Ave Honesdale PA 18431",
    "addr:housenumber":"470",
    "addr:postcode":"18431",
    "addr:street":"Sunrise Ave",
    "iso:country":"US",
    "sg:address":"470 Sunrise Ave",
    "sg:city":"Honesdale",
    "sg:classifiers":[
        {
            "category":"Building & Trades",
            "subcategory":"Construction",
            "type":"Services"
        }
    ],
    "sg:phone":"+1   ",
    "sg:postcode":"18431",
    "sg:province":"PA",
    "sg:tags":[
        "general",
        "contractor"
    ],
    "wof:name":"Dakan Enterprises Inc",
    "wof:placetype":"venue"
},
  "geometry": {"coordinates":[-75.24925399999999,41.55234],"type":"Point"}
}