{
  "type": "Feature",
  "properties": {
    "addr:full":"640 W Allegheny Ave Philadelphia PA 19133",
    "addr:housenumber":"640",
    "addr:postcode":"19133",
    "addr:street":"W Allegheny Ave",
    "iso:country":"US",
    "sg:address":"640 W Allegheny Ave",
    "sg:city":"Philadelphia",
    "sg:classifiers":[
        {
            "category":"Food & Beverages",
            "subcategory":"Groceries & Convenience Stores",
            "type":"Retail Goods"
        }
    ],
    "sg:phone":"+1 215 221 0522",
    "sg:postcode":"19133",
    "sg:province":"PA",
    "wof:name":"Vaely Grocery Store",
    "wof:placetype":"venue"
},
  "geometry": {"coordinates":[-75.14171,40.000002],"type":"Point"}
}