{
  "type": "Feature",
  "properties": {
    "iso:country":"US",
    "sg:address":"1000 Stony Battery Rd",
    "sg:city":"Lancaster",
    "sg:classifiers":[
        {
            "category":"Building & Trades",
            "subcategory":"Construction",
            "type":"Services"
        }
    ],
    "sg:phone":"+1   ",
    "sg:postcode":"17601",
    "sg:province":"PA",
    "sg:tags":[
        "nonresidential"
    ],
    "wof:name":"Edwin L Heim Company",
    "wof:placetype":"venue"
},
  "geometry": {"coordinates":[-76.421245,40.074267],"type":"Point"}
}