{
  "type": "Feature",
  "properties": {
    "iso:country":"US",
    "sg:address":"766 Main St",
    "sg:city":"Stroudsburg",
    "sg:classifiers":[
        {
            "category":"Arts & Performance",
            "subcategory":"Theater",
            "type":"Entertainment"
        }
    ],
    "sg:phone":"+1 570 422 9100",
    "sg:postcode":"18360",
    "sg:province":"PA",
    "sg:tags":[
        "live",
        "music"
    ],
    "wof:name":"Mix Master Disc Jockey's",
    "wof:placetype":"venue"
},
  "geometry": {"coordinates":[-75.195312,40.985092],"type":"Point"}
}