{
  "type": "Feature",
  "properties": {
    "iso:country":"US",
    "sg:address":"2933 Mary St",
    "sg:city":"Pittsburgh",
    "sg:classifiers":[
        {
            "category":"Professional",
            "type":"Services"
        }
    ],
    "sg:phone":"+1   ",
    "sg:postcode":"15203",
    "sg:province":"PA",
    "wof:name":"USA Images Inc",
    "wof:placetype":"venue"
},
  "geometry": {"coordinates":[-79.96584799999999,40.423045],"type":"Point"}
}