{
  "type": "Feature",
  "properties": {
    "iso:country":"US",
    "sg:address":"420 W Washington St",
    "sg:city":"New Castle",
    "sg:classifiers":[
        {
            "category":"Organizations",
            "subcategory":"Religious Organization",
            "type":"Services"
        }
    ],
    "sg:phone":"+1 724 654 3125",
    "sg:postcode":"16101",
    "sg:province":"PA",
    "sg:tags":[
        "church"
    ],
    "wof:name":"Preach Jesus Ministries",
    "wof:placetype":"venue"
},
  "geometry": {"coordinates":[-80.354467,40.999837],"type":"Point"}
}