{
  "type": "Feature",
  "properties": {
    "addr:full":"45 W School House Ln Philadelphia PA 19144",
    "addr:housenumber":"45",
    "addr:postcode":"19144",
    "addr:street":"W School House Ln",
    "iso:country":"US",
    "sg:address":"45 W School House Ln",
    "sg:city":"Philadelphia",
    "sg:classifiers":[
        {
            "category":"Organizations",
            "subcategory":"Religious Organization",
            "type":"Services"
        }
    ],
    "sg:phone":"+1 215 844 4924",
    "sg:postcode":"19144",
    "sg:province":"PA",
    "wof:name":"Friends Religious Society",
    "wof:placetype":"venue"
},
  "geometry": {"coordinates":[-75.173863,40.033511],"type":"Point"}
}