{
  "type": "Feature",
  "properties": {
    "iso:country":"US",
    "sg:address":"532 Hazle St",
    "sg:city":"Wilkes Barre",
    "sg:classifiers":[
        {
            "category":"Food & Beverages",
            "subcategory":"Groceries & Convenience Stores",
            "type":"Retail Goods"
        }
    ],
    "sg:phone":"+1 570 826 1126",
    "sg:postcode":"18702",
    "sg:province":"PA",
    "wof:name":"Orloski's Quik Mart",
    "wof:placetype":"venue"
},
  "geometry": {"coordinates":[-75.894125,41.225556],"type":"Point"}
}