{
  "type": "Feature",
  "properties": {
    "iso:country":"US",
    "sg:address":"300 Fulling Mill Rd",
    "sg:city":"Middletown",
    "sg:classifiers":[
        {
            "category":"Freight",
            "type":"Transportation"
        }
    ],
    "sg:phone":"+1 717 944 0123",
    "sg:postcode":"17057",
    "sg:province":"PA",
    "sg:tags":[
        "trucking"
    ],
    "wof:name":"Fed Ex Freight",
    "wof:placetype":"venue"
},
  "geometry": {"coordinates":[-76.734335,40.230026],"type":"Point"}
}