{
  "type": "Feature",
  "properties": {
    "addr:full":"6415 Magnolia St Philadelphia PA 19119",
    "addr:housenumber":"6415",
    "addr:postcode":"19119",
    "addr:street":"Magnolia St",
    "iso:country":"US",
    "sg:address":"6415 Magnolia St",
    "sg:city":"Philadelphia",
    "sg:classifiers":[
        {
            "category":"Organizations",
            "subcategory":"Religious Organization",
            "type":"Services"
        }
    ],
    "sg:phone":"+1   ",
    "sg:postcode":"19119",
    "sg:province":"PA",
    "wof:name":"Germantwn 7th Day Advntst Ch",
    "wof:placetype":"venue"
},
  "geometry": {"coordinates":[-75.179982,40.049394],"type":"Point"}
}