{
  "type": "Feature",
  "properties": {
    "addr:full":"522 Main St South Fork PA 15956",
    "addr:housenumber":"522",
    "addr:postcode":"15956",
    "addr:street":"Main St South",
    "iso:country":"US",
    "sg:address":"522 Main St",
    "sg:city":"South Fork",
    "sg:classifiers":[
        {
            "category":"Personal",
            "subcategory":"Barber",
            "type":"Services"
        }
    ],
    "sg:phone":"+1 814 495 5133",
    "sg:postcode":"15956",
    "sg:province":"PA",
    "sg:tags":[
        "shop"
    ],
    "wof:name":"Crute's Barber Shop",
    "wof:placetype":"venue"
},
  "geometry": {"coordinates":[-78.79011300000001,40.363052],"type":"Point"}
}