{
  "type": "Feature",
  "properties": {
    "iso:country":"US",
    "sg:address":"6331 Waldron St",
    "sg:city":"Pittsburgh",
    "sg:classifiers":[
        {
            "category":"Professional",
            "subcategory":"Computer Services",
            "type":"Services"
        }
    ],
    "sg:phone":"+1 412 422 2200",
    "sg:postcode":"15217",
    "sg:province":"PA",
    "sg:tags":[
        "consultant",
        "designer"
    ],
    "sg:website":"www.logixcomputer.com",
    "wof:name":"Logix Computer Svc",
    "wof:placetype":"venue"
},
  "geometry": {"coordinates":[-79.915997,40.431728],"type":"Point"}
}