{
  "type": "Feature",
  "properties": {
    "iso:country":"US",
    "sg:address":"126 School St",
    "sg:city":"Bedford",
    "sg:classifiers":[
        {
            "category":"Building & Trades",
            "subcategory":"Construction",
            "type":"Services"
        }
    ],
    "sg:phone":"+1 814 662 2710",
    "sg:postcode":"15522",
    "sg:province":"PA",
    "sg:tags":[
        "repairing",
        "remodeling",
        "contractor"
    ],
    "wof:name":"G & R Remodeling",
    "wof:placetype":"venue"
},
  "geometry": {"coordinates":[-78.504914,40.03289],"type":"Point"}
}