{
  "type": "Feature",
  "properties": {
    "iso:country":"US",
    "sg:address":"5151 Cold Spring Creamery Rd",
    "sg:city":"Doylestown",
    "sg:classifiers":[
        {
            "category":"Social Services",
            "subcategory":"Child Care",
            "type":"Services"
        },
        {
            "category":"Education",
            "subcategory":"Preschool",
            "type":"Public Place"
        },
        {
            "category":"Education",
            "subcategory":"School",
            "type":"Public Place"
        }
    ],
    "sg:phone":"+1 215 230 4100",
    "sg:postcode":"18902",
    "sg:province":"PA",
    "sg:tags":[
        "elementary",
        "day"
    ],
    "sg:website":"www.cecschool.com",
    "wof:name":"Community Educational Centers Inc",
    "wof:placetype":"venue"
},
  "geometry": {"coordinates":[-75.088661,40.359098],"type":"Point"}
}