{
  "type": "Feature",
  "properties": {
    "iso:country":"US",
    "sg:address":"31 N 2nd St",
    "sg:city":"Chambersburg",
    "sg:classifiers":[
        {
            "category":"Professional",
            "subcategory":"Engineering",
            "type":"Services"
        }
    ],
    "sg:phone":"+1 717 267 1401",
    "sg:postcode":"17201",
    "sg:province":"PA",
    "sg:tags":[
        "engineer"
    ],
    "wof:name":"Brehm-Lebo Engineering Inc",
    "wof:placetype":"venue"
},
  "geometry": {"coordinates":[-77.659201,39.937456],"type":"Point"}
}