{
  "type": "Feature",
  "properties": {
    "iso:country":"US",
    "sg:address":"107 Urban Ave",
    "sg:city":"Latrobe",
    "sg:classifiers":[
        {
            "category":"Professional",
            "subcategory":"Art Services",
            "type":"Services"
        }
    ],
    "sg:phone":"+1 724 532 2335",
    "sg:postcode":"15650",
    "sg:province":"PA",
    "sg:tags":[
        "interior",
        "designer",
        "decorator"
    ],
    "wof:name":"Carol Walor Design",
    "wof:placetype":"venue"
},
  "geometry": {"coordinates":[-79.3647,40.277409],"type":"Point"}
}