{
  "type": "Feature",
  "properties": {
    "addr:full":"14 Calder St Harrisburg PA 17103",
    "addr:housenumber":"14",
    "addr:postcode":"17103",
    "addr:street":"Calder St",
    "iso:country":"US",
    "sg:address":"14 Calder St",
    "sg:city":"Harrisburg",
    "sg:classifiers":[
        {
            "category":"Government",
            "subcategory":"Office",
            "type":"Public Place"
        }
    ],
    "sg:phone":"+1   ",
    "sg:postcode":"17103",
    "sg:province":"PA",
    "sg:tags":[
        "national",
        "guard"
    ],
    "wof:name":"Army National Guard PA",
    "wof:placetype":"venue"
},
  "geometry": {"coordinates":[-76.877743,40.275869],"type":"Point"}
}