{
  "type": "Feature",
  "properties": {
    "iso:country":"US",
    "sg:address":"1909 Grant Ave",
    "sg:city":"Philadelphia",
    "sg:classifiers":[
        {
            "category":"Retail",
            "subcategory":"Auto Repair",
            "type":"Services"
        }
    ],
    "sg:phone":"+1 215 673 9112",
    "sg:postcode":"19115",
    "sg:province":"PA",
    "sg:tags":[
        "repairing",
        "automotive",
        "general",
        "automobile"
    ],
    "wof:name":"Albert's Automotive Inc",
    "wof:placetype":"venue"
},
  "geometry": {"coordinates":[-75.03389,40.083681],"type":"Point"}
}