{
  "type": "Feature",
  "properties": {
    "iso:country":"US",
    "sg:address":"240 N Arch St",
    "sg:city":"Lancaster",
    "sg:classifiers":[
        {
            "category":"Manufacturing",
            "subcategory":"Printing",
            "type":"Manufacturing & Wholesale Goods"
        }
    ],
    "sg:phone":"+1   ",
    "sg:postcode":"17603",
    "sg:province":"PA",
    "sg:tags":[
        "periodical"
    ],
    "wof:name":"We Magazine Inc",
    "wof:placetype":"venue"
},
  "geometry": {"coordinates":[-76.310373,40.04229],"type":"Point"}
}