{
  "type": "Feature",
  "properties": {
    "iso:country":"US",
    "sg:address":"734 Concord Ave",
    "sg:city":"Drexel Hill",
    "sg:classifiers":[
        {
            "category":"Building & Trades",
            "subcategory":"Landscaping Services",
            "type":"Services"
        }
    ],
    "sg:phone":"+1 610 622 2223",
    "sg:postcode":"19026",
    "sg:province":"PA",
    "sg:tags":[
        "landscape",
        "contractor"
    ],
    "wof:name":"J A Landscaping",
    "wof:placetype":"venue"
},
  "geometry": {"coordinates":[-75.30426900000001,39.952046],"type":"Point"}
}