{
  "type": "Feature",
  "properties": {
    "iso:country":"US",
    "sg:address":"800 Main St",
    "sg:city":"Conneautville",
    "sg:classifiers":[
        {
            "category":"Food & Beverages",
            "subcategory":"Groceries & Convenience Stores",
            "type":"Retail Goods"
        }
    ],
    "sg:phone":"+1 814 587 3055",
    "sg:postcode":"16406",
    "sg:province":"PA",
    "sg:tags":[
        "grocer"
    ],
    "wof:name":"Samuel's Market",
    "wof:placetype":"venue"
},
  "geometry": {"coordinates":[-80.370569,41.759161],"type":"Point"}
}