{
  "type": "Feature",
  "properties": {
    "addr:full":"30 Fairview Ave Lansdowne PA 19050",
    "addr:housenumber":"30",
    "addr:postcode":"19050",
    "addr:street":"Fairview Ave",
    "iso:country":"US",
    "sg:address":"30 Fairview Ave",
    "sg:city":"Lansdowne",
    "sg:classifiers":[
        {
            "category":"Professional",
            "subcategory":"Printing & Photocopies",
            "type":"Services"
        }
    ],
    "sg:phone":"+1   ",
    "sg:postcode":"19050",
    "sg:province":"PA",
    "sg:tags":[
        "photocopying"
    ],
    "wof:name":"Ridgways Ltd",
    "wof:placetype":"venue"
},
  "geometry": {"coordinates":[-75.268253,39.933662],"type":"Point"}
}