{
  "type": "Feature",
  "properties": {
    "addr:full":"2560 Haverford Rd Ardmore PA 19003",
    "addr:housenumber":"2560",
    "addr:postcode":"19003",
    "addr:street":"Haverford Rd",
    "iso:country":"US",
    "sg:address":"2560 Haverford Rd",
    "sg:city":"Ardmore",
    "sg:classifiers":[
        {
            "category":"Retail",
            "subcategory":"Auto Rental",
            "type":"Services"
        }
    ],
    "sg:phone":"+1 610 642 2322",
    "sg:postcode":"19003",
    "sg:province":"PA",
    "sg:tags":[
        "renting",
        "automobile",
        "leasing"
    ],
    "wof:name":"Enterprise Rent-A-Car Company",
    "wof:placetype":"venue"
},
  "geometry": {"coordinates":[-75.29973,39.9946],"type":"Point"}
}