{
  "type": "Feature",
  "properties": {
    "iso:country":"US",
    "sg:address":"4544 Main St",
    "sg:city":"Hartstown",
    "sg:classifiers":[
        {
            "category":"Farming",
            "subcategory":"Dairy Farm",
            "type":"Manufacturing & Wholesale Goods"
        }
    ],
    "sg:phone":"+1   ",
    "sg:postcode":"16131",
    "sg:province":"PA",
    "wof:name":"James McElhaney",
    "wof:placetype":"venue"
},
  "geometry": {"coordinates":[-80.37075,41.516397],"type":"Point"}
}