{
  "type": "Feature",
  "properties": {
    "iso:country":"US",
    "sg:address":"3366 N 2nd St",
    "sg:city":"Philadelphia",
    "sg:classifiers":[
        {
            "category":"Restaurant",
            "type":"Food & Drink"
        }
    ],
    "sg:phone":"+1 215 291 1888",
    "sg:postcode":"19140",
    "sg:province":"PA",
    "sg:tags":[
        "chinese"
    ],
    "wof:name":"Chinese Restaurant",
    "wof:placetype":"venue"
},
  "geometry": {"coordinates":[-75.132839,40.001656],"type":"Point"}
}