{
  "type": "Feature",
  "properties": {
    "iso:country":"US",
    "sg:address":"Clubhouse",
    "sg:city":"Wexford",
    "sg:classifiers":[
        {
            "category":"Park",
            "type":"Public Place"
        }
    ],
    "sg:phone":"+1 724 935 1967",
    "sg:postcode":"15090",
    "sg:province":"PA",
    "wof:name":"North Park",
    "wof:placetype":"venue"
},
  "geometry": {"coordinates":[-80.0634,40.619301],"type":"Point"}
}