{
  "type": "Feature",
  "properties": {
    "addr:full":"5430 Pulaski Ave Philadelphia PA 19144",
    "addr:housenumber":"5430",
    "addr:postcode":"19144",
    "addr:street":"Pulaski Ave",
    "iso:country":"US",
    "sg:address":"5430 Pulaski Ave",
    "sg:city":"Philadelphia",
    "sg:classifiers":[
        {
            "category":"Social Services",
            "subcategory":"Child Care",
            "type":"Services"
        }
    ],
    "sg:phone":"+1 215 848 9017",
    "sg:postcode":"19144",
    "sg:province":"PA",
    "sg:tags":[
        "day"
    ],
    "wof:name":"Canaan Baptist Church Daycare Center",
    "wof:placetype":"venue"
},
  "geometry": {"coordinates":[-75.177002,40.0285],"type":"Point"}
}