{
  "type": "Feature",
  "properties": {
    "iso:country":"US",
    "sg:address":"4812 King Rd",
    "sg:city":"Allison Park",
    "sg:classifiers":[
        {
            "category":"Wholesale",
            "subcategory":"Machinery & Supplies",
            "type":"Manufacturing & Wholesale Goods"
        }
    ],
    "sg:phone":"+1   ",
    "sg:postcode":"15101",
    "sg:province":"PA",
    "sg:tags":[
        "equipment"
    ],
    "wof:name":"Mauldin of Pittsburgh",
    "wof:placetype":"venue"
},
  "geometry": {"coordinates":[-79.949684,40.598394],"type":"Point"}
}