{
  "type": "Feature",
  "properties": {
    "addr:full":"275 Pauline Dr York PA 17402",
    "addr:housenumber":"275",
    "addr:postcode":"17402",
    "addr:street":"Pauline Dr",
    "iso:country":"US",
    "sg:address":"275 Pauline Dr",
    "sg:city":"York",
    "sg:classifiers":[
        {
            "category":"Banks & Credit Unions",
            "subcategory":"Bank",
            "type":"Services"
        }
    ],
    "sg:phone":"+1   ",
    "sg:postcode":"17402",
    "sg:province":"PA",
    "sg:tags":[
        "depository",
        "banking"
    ],
    "wof:name":"Western Union",
    "wof:placetype":"venue"
},
  "geometry": {"coordinates":[-76.68485099999999,39.93159],"type":"Point"}
}