{
  "type": "Feature",
  "properties": {
    "addr:full":"841 Chestnut St Philadelphia PA 19107",
    "addr:housenumber":"841",
    "addr:postcode":"19107",
    "addr:street":"Chestnut St",
    "iso:country":"US",
    "sg:address":"841 Chestnut St",
    "sg:city":"Philadelphia",
    "sg:classifiers":[
        {
            "category":"Health Services",
            "subcategory":"Doctor",
            "type":"Services"
        }
    ],
    "sg:phone":"+1 215 955 1915",
    "sg:postcode":"19107",
    "sg:province":"PA",
    "sg:tags":[
        "physician",
        "surgeon"
    ],
    "wof:name":"University Gastroenterology",
    "wof:placetype":"venue"
},
  "geometry": {"coordinates":[-75.15498700000001,39.949803],"type":"Point"}
}