{
  "type": "Feature",
  "properties": {
    "iso:country":"US",
    "sg:address":"4884 Elmwood Dr",
    "sg:city":"Pittsburgh",
    "sg:classifiers":[
        {
            "category":"Health Services",
            "subcategory":"Health Practitioner",
            "type":"Services"
        }
    ],
    "sg:phone":"+1 412 281 4950",
    "sg:postcode":"15227",
    "sg:province":"PA",
    "sg:tags":[
        "psychologist"
    ],
    "wof:name":"Psychological Assessment",
    "wof:placetype":"venue"
},
  "geometry": {"coordinates":[-79.964277,40.360449],"type":"Point"}
}