{
  "type": "Feature",
  "properties": {
    "iso:country":"US",
    "sg:address":"8600 W Chester Pike",
    "sg:city":"Upper Darby",
    "sg:classifiers":[
        {
            "category":"Health Services",
            "subcategory":"Doctor",
            "type":"Services"
        }
    ],
    "sg:phone":"+1 610 446 5548",
    "sg:postcode":"19082",
    "sg:province":"PA",
    "sg:tags":[
        "physician",
        "surgeon"
    ],
    "wof:name":"M Hall Heather MD",
    "wof:placetype":"venue"
},
  "geometry": {"coordinates":[-75.286608,39.966948],"type":"Point"}
}