{
  "type": "Feature",
  "properties": {
    "iso:country":"US",
    "sg:address":"345 W Mount Airy Rd",
    "sg:city":"Stevens",
    "sg:classifiers":[
        {
            "category":"Professional",
            "subcategory":"Business Services",
            "type":"Services"
        }
    ],
    "sg:phone":"+1   ",
    "sg:postcode":"17578",
    "sg:province":"PA",
    "wof:name":"Kline-Kreider-Good Auctioneers",
    "wof:placetype":"venue"
},
  "geometry": {"coordinates":[-76.245954,40.235817],"type":"Point"}
}