{
  "type": "Feature",
  "properties": {
    "addr:full":"4614 Murray St Bristol PA 19007",
    "addr:housenumber":"4614",
    "addr:postcode":"19007",
    "addr:street":"Murray St",
    "iso:country":"US",
    "sg:address":"4614 Murray St",
    "sg:city":"Bristol",
    "sg:classifiers":[
        {
            "category":"Building & Trades",
            "subcategory":"Construction",
            "type":"Services"
        }
    ],
    "sg:phone":"+1   ",
    "sg:postcode":"19007",
    "sg:province":"PA",
    "sg:tags":[
        "excavating",
        "landscape",
        "contractor"
    ],
    "wof:name":"Finish Graders Inc",
    "wof:placetype":"venue"
},
  "geometry": {"coordinates":[-74.865409,40.11952],"type":"Point"}
}