{
  "type": "Feature",
  "properties": {
    "addr:full":"17307 State Rte 36 Punxsutawney PA 15767",
    "addr:housenumber":"17307",
    "addr:postcode":"15767",
    "addr:street":"State Rte 36",
    "iso:country":"US",
    "sg:address":"17307 State Rte 36",
    "sg:city":"Punxsutawney",
    "sg:classifiers":[
        {
            "category":"Restaurant",
            "type":"Food & Drink"
        }
    ],
    "sg:phone":"+1 814 938 7740",
    "sg:postcode":"15767",
    "sg:province":"PA",
    "sg:tags":[
        "parlor",
        "ice",
        "cream"
    ],
    "wof:name":"D & J's Drive In",
    "wof:placetype":"venue"
},
  "geometry": {"coordinates":[-78.936573,40.935338],"type":"Point"}
}