{
  "type": "Feature",
  "properties": {
    "addr:full":"507 Edgewood Ave Pittsburgh PA 15218",
    "addr:housenumber":"507",
    "addr:postcode":"15218",
    "addr:street":"Edgewood Ave",
    "iso:country":"US",
    "sg:address":"507 Edgewood Ave",
    "sg:city":"Pittsburgh",
    "sg:classifiers":[
        {
            "category":"Building & Trades",
            "subcategory":"Construction",
            "type":"Services"
        }
    ],
    "sg:phone":"+1   ",
    "sg:postcode":"15218",
    "sg:province":"PA",
    "sg:tags":[
        "house"
    ],
    "wof:name":"McHael J Scherbick Dsign Bldrs",
    "wof:placetype":"venue"
},
  "geometry": {"coordinates":[-79.88512299999999,40.426945],"type":"Point"}
}