{
  "type": "Feature",
  "properties": {
    "addr:full":"1039 N Lawrence St Philadelphia PA 19123",
    "addr:housenumber":"1039",
    "addr:postcode":"19123",
    "addr:street":"N Lawrence St",
    "iso:country":"US",
    "sg:address":"1039 N Lawrence St",
    "sg:city":"Philadelphia",
    "sg:classifiers":[
        {
            "category":"Wholesale",
            "subcategory":"Non-durable Goods",
            "type":"Manufacturing & Wholesale Goods"
        }
    ],
    "sg:phone":"+1 215 440 9400",
    "sg:postcode":"19123",
    "sg:province":"PA",
    "sg:tags":[
        "premium"
    ],
    "sg:website":"www.chabyumbrellas.com",
    "wof:name":"George R Chaby Inc",
    "wof:placetype":"venue"
},
  "geometry": {"coordinates":[-75.14405499999999,39.969749],"type":"Point"}
}