{
  "type": "Feature",
  "properties": {
    "iso:country":"US",
    "sg:address":"3125 Princeton Rd",
    "sg:city":"Greensburg",
    "sg:classifiers":[
        {
            "category":"Professional",
            "subcategory":"Art Services",
            "type":"Services"
        }
    ],
    "sg:phone":"+1 724 837 8033",
    "sg:postcode":"15601",
    "sg:province":"PA",
    "sg:tags":[
        "interior",
        "designer",
        "decorator"
    ],
    "wof:name":"Designcare",
    "wof:placetype":"venue"
},
  "geometry": {"coordinates":[-79.475723,40.286518],"type":"Point"}
}