{
  "type": "Feature",
  "properties": {
    "iso:country":"US",
    "sg:address":"203 S Filbert St",
    "sg:city":"Mechanicsburg",
    "sg:classifiers":[
        {
            "category":"Organizations",
            "subcategory":"Religious Organization",
            "type":"Services"
        }
    ],
    "sg:phone":"+1 717 766 4595",
    "sg:postcode":"17055",
    "sg:province":"PA",
    "wof:name":"Spengler Margaret H Rev",
    "wof:placetype":"venue"
},
  "geometry": {"coordinates":[-76.9981,40.213699],"type":"Point"}
}