{
  "type": "Feature",
  "properties": {
    "addr:full":"93 Old York Rd Jenkintown PA 19046",
    "addr:housenumber":"93",
    "addr:postcode":"19046",
    "addr:street":"Old York Rd",
    "iso:country":"US",
    "sg:address":"93 Old York Rd",
    "sg:city":"Jenkintown",
    "sg:classifiers":[
        {
            "category":"Banks & Credit Unions",
            "subcategory":"Financial Services",
            "type":"Services"
        }
    ],
    "sg:phone":"+1   ",
    "sg:postcode":"19046",
    "sg:province":"PA",
    "sg:tags":[
        "investing"
    ],
    "wof:name":"Green House LLC",
    "wof:placetype":"venue"
},
  "geometry": {"coordinates":[-75.12544,40.092632],"type":"Point"}
}