{
  "type": "Feature",
  "properties": {
    "iso:country":"US",
    "sg:address":"405 Cumberland St",
    "sg:city":"Lebanon",
    "sg:classifiers":[
        {
            "category":"Professional",
            "subcategory":"Advertising",
            "type":"Services"
        }
    ],
    "sg:phone":"+1 717 272 2826",
    "sg:postcode":"17042",
    "sg:province":"PA",
    "sg:tags":[
        "counselor"
    ],
    "wof:name":"Rooftop Productions",
    "wof:placetype":"venue"
},
  "geometry": {"coordinates":[-76.418012,40.3399],"type":"Point"}
}