{
  "type": "Feature",
  "properties": {
    "iso:country":"US",
    "sg:address":"1090 Freeport Rd",
    "sg:city":"Pittsburgh",
    "sg:classifiers":[
        {
            "category":"Real Estate",
            "subcategory":"Real Estate Agent",
            "type":"Services"
        }
    ],
    "sg:phone":"+1 412 963 6300",
    "sg:postcode":"15238",
    "sg:province":"PA",
    "sg:website":"www.howardhanna.com",
    "wof:name":"Howard Hanna Co",
    "wof:placetype":"venue"
},
  "geometry": {"coordinates":[-79.85165600000001,40.507049],"type":"Point"}
}