{
  "type": "Feature",
  "properties": {
    "iso:country":"US",
    "sg:address":"452 E Norwegian St",
    "sg:city":"Pottsville",
    "sg:classifiers":[
        {
            "category":"Organizations",
            "subcategory":"Religious Organization",
            "type":"Services"
        }
    ],
    "sg:phone":"+1 570 628 0708",
    "sg:postcode":"17901",
    "sg:province":"PA",
    "sg:tags":[
        "church"
    ],
    "wof:name":"New Hope Christian Fellowship",
    "wof:placetype":"venue"
},
  "geometry": {"coordinates":[-76.191371,40.687308],"type":"Point"}
}