{
  "type": "Feature",
  "properties": {
    "iso:country":"US",
    "sg:address":"46 Walnut Bottom Rd",
    "sg:city":"Shippensburg",
    "sg:classifiers":[
        {
            "category":"Health Services",
            "subcategory":"Doctor",
            "type":"Services"
        }
    ],
    "sg:phone":"+1 717 530 5117",
    "sg:postcode":"17257",
    "sg:province":"PA",
    "sg:tags":[
        "physician",
        "medical",
        "surgeon"
    ],
    "wof:name":"Shippensburgs Family Practice",
    "wof:placetype":"venue"
},
  "geometry": {"coordinates":[-77.469559,40.063486],"type":"Point"}
}