{
  "type": "Feature",
  "properties": {
    "iso:country":"US",
    "sg:address":"746 E Passyunk Ave",
    "sg:city":"Philadelphia",
    "sg:classifiers":[
        {
            "category":"Real Estate",
            "subcategory":"Architect",
            "type":"Services"
        }
    ],
    "sg:phone":"+1   ",
    "sg:postcode":"19147",
    "sg:province":"PA",
    "sg:tags":[
        "architectural"
    ],
    "wof:name":"Pivotal Design",
    "wof:placetype":"venue"
},
  "geometry": {"coordinates":[-75.15173299999999,39.939761],"type":"Point"}
}