{
  "type": "Feature",
  "properties": {
    "addr:full":"305 Crossland Ave Uniontown PA 15401",
    "addr:housenumber":"305",
    "addr:postcode":"15401",
    "addr:street":"Crossland Ave",
    "iso:country":"US",
    "sg:address":"305 Crossland Ave",
    "sg:city":"Uniontown",
    "sg:classifiers":[
        {
            "category":"Wholesale",
            "subcategory":"Durable Goods & Equipment",
            "type":"Manufacturing & Wholesale Goods"
        }
    ],
    "sg:phone":"+1 724 439 8800",
    "sg:postcode":"15401",
    "sg:province":"PA",
    "sg:tags":[
        "exporter"
    ],
    "wof:name":"Conaway Hearse & Limousine",
    "wof:placetype":"venue"
},
  "geometry": {"coordinates":[-79.716176,39.892055],"type":"Point"}
}