{
  "type": "Feature",
  "properties": {
    "iso:country":"US",
    "sg:address":"466 Dailey Rd",
    "sg:city":"Pittsburgh",
    "sg:classifiers":[
        {
            "category":"Professional",
            "type":"Services"
        }
    ],
    "sg:phone":"+1   ",
    "sg:postcode":"15227",
    "sg:province":"PA",
    "wof:name":"Hevco Inc",
    "wof:placetype":"venue"
},
  "geometry": {"coordinates":[-79.96845399999999,40.37415],"type":"Point"}
}