{
  "type": "Feature",
  "properties": {
    "iso:country":"US",
    "sg:address":"7821 Witmer Dr",
    "sg:city":"Harrisburg",
    "sg:classifiers":[
        {
            "category":"Retail",
            "subcategory":"Auto Repair",
            "type":"Services"
        }
    ],
    "sg:phone":"+1 717 564 7004",
    "sg:postcode":"17111",
    "sg:province":"PA",
    "sg:tags":[
        "shop",
        "automobile",
        "machine"
    ],
    "sg:website":"http://www.donsperformancecorner.com",
    "wof:name":"Don's Performance Corner",
    "wof:placetype":"venue"
},
  "geometry": {"coordinates":[-76.753434,40.262865],"type":"Point"}
}