{
  "type": "Feature",
  "properties": {
    "iso:country":"US",
    "sg:address":"18 E Union Blvd",
    "sg:city":"Bethlehem",
    "sg:classifiers":[
        {
            "category":"Building & Trades",
            "subcategory":"Construction",
            "type":"Services"
        }
    ],
    "sg:phone":"+1 610 434 6600",
    "sg:postcode":"18018",
    "sg:province":"PA",
    "sg:tags":[
        "painter"
    ],
    "wof:name":"Charlie's Painting",
    "wof:placetype":"venue"
},
  "geometry": {"coordinates":[-75.377464,40.625028],"type":"Point"}
}