{
  "type": "Feature",
  "properties": {
    "addr:full":"880 Co Rd 519 Frenchtown PA 08825",
    "addr:housenumber":"880",
    "addr:postcode":"08825",
    "addr:street":"Co Rd 519",
    "iso:country":"US",
    "sg:address":"880 Co Rd 519",
    "sg:city":"Frenchtown",
    "sg:classifiers":[
        {
            "category":"Building & Trades",
            "subcategory":"Construction",
            "type":"Services"
        }
    ],
    "sg:phone":"+1 908 996 6963",
    "sg:postcode":"08825",
    "sg:province":"PA",
    "sg:tags":[
        "general",
        "contractor"
    ],
    "wof:name":"De Sapio Management Inc",
    "wof:placetype":"venue"
},
  "geometry": {"coordinates":[-75.012745,40.506721],"type":"Point"}
}