{
  "type": "Feature",
  "properties": {
    "iso:country":"US",
    "sg:address":"718 Washington Ave",
    "sg:city":"Philadelphia",
    "sg:classifiers":[
        {
            "category":"Autos & Motor Vehicles",
            "subcategory":"Auto Supplies",
            "type":"Retail Goods"
        },
        {
            "category":"Sports & Exercise",
            "subcategory":"Race Track",
            "type":"Entertainment"
        },
        {
            "category":"Professional",
            "subcategory":"Computer Services",
            "type":"Services"
        }
    ],
    "sg:phone":"+1 215 627 2258",
    "sg:postcode":"19147",
    "sg:province":"PA",
    "sg:tags":[
        "stereo",
        "installation",
        "automobile",
        "accessory",
        "equipment",
        "part",
        "car",
        "performance",
        "racing"
    ],
    "sg:website":"www.ckautoimage.com",
    "wof:name":"CK Auto Image",
    "wof:placetype":"venue"
},
  "geometry": {"coordinates":[-75.156195,39.935566],"type":"Point"}
}