{
  "type": "Feature",
  "properties": {
    "addr:full":"235 N Columbus Blvd Philadelphia PA 19106",
    "addr:housenumber":"235",
    "addr:postcode":"19106",
    "addr:street":"N Columbus Blvd",
    "iso:country":"US",
    "sg:address":"235 N Columbus Blvd",
    "sg:city":"Philadelphia",
    "sg:classifiers":[
        {
            "category":"Recreation",
            "type":"Entertainment"
        }
    ],
    "sg:phone":"+1 215 923 7245",
    "sg:postcode":"19106",
    "sg:province":"PA",
    "sg:tags":[
        "boating",
        "instruction"
    ],
    "wof:name":"Liberty Sailing School",
    "wof:placetype":"venue"
},
  "geometry": {"coordinates":[-75.139218,39.955342],"type":"Point"}
}