{
  "type": "Feature",
  "properties": {
    "iso:country":"US",
    "sg:address":"3680 W Brandon Way",
    "sg:city":"Doylestown",
    "sg:classifiers":[
        {
            "category":"Health Services",
            "subcategory":"Doctor",
            "type":"Services"
        }
    ],
    "sg:phone":"+1 215 489 0451",
    "sg:postcode":"18902",
    "sg:province":"PA",
    "sg:tags":[
        "physician",
        "surgeon"
    ],
    "wof:name":"Robert Diehl",
    "wof:placetype":"venue"
},
  "geometry": {"coordinates":[-75.088838,40.346429],"type":"Point"}
}