{
  "type": "Feature",
  "properties": {
    "iso:country":"US",
    "sg:address":"7 Grahamville St",
    "sg:city":"North East",
    "sg:classifiers":[
        {
            "category":"Personal",
            "subcategory":"Beauty Salon",
            "type":"Services"
        }
    ],
    "sg:phone":"+1 814 725 4141",
    "sg:postcode":"16428",
    "sg:province":"PA",
    "wof:name":"Beauty By Belson",
    "wof:placetype":"venue"
},
  "geometry": {"coordinates":[-79.833883,42.209898],"type":"Point"}
}