{
  "type": "Feature",
  "properties": {
    "iso:country":"US",
    "sg:address":"5725 US Hwy 220",
    "sg:city":"Hughesville",
    "sg:classifiers":[
        {
            "category":"Cinema",
            "subcategory":"Movie Rental",
            "type":"Entertainment"
        }
    ],
    "sg:phone":"+1 570 584 6387",
    "sg:postcode":"17737",
    "sg:province":"PA",
    "sg:tags":[
        "leasing",
        "video",
        "disc",
        "tape"
    ],
    "wof:name":"Villa Groce Video",
    "wof:placetype":"venue"
},
  "geometry": {"coordinates":[-76.715639,41.258824],"type":"Point"}
}