{
  "type": "Feature",
  "properties": {
    "addr:full":"401 E Burnside St Bellefonte PA 16823",
    "addr:housenumber":"401",
    "addr:postcode":"16823",
    "addr:street":"E Burnside St",
    "iso:country":"US",
    "sg:address":"401 E Burnside St",
    "sg:city":"Bellefonte",
    "sg:classifiers":[
        {
            "category":"Shopping",
            "subcategory":"Books",
            "type":"Retail Goods"
        }
    ],
    "sg:phone":"+1   ",
    "sg:postcode":"16823",
    "sg:province":"PA",
    "wof:name":"Christian Book Store",
    "wof:placetype":"venue"
},
  "geometry": {"coordinates":[-77.77070500000001,40.91016],"type":"Point"}
}