{
  "type": "Feature",
  "properties": {
    "iso:country":"US",
    "sg:address":"935 Beaver Grade Rd",
    "sg:city":"Coraopolis",
    "sg:classifiers":[
        {
            "category":"Shopping",
            "subcategory":"Tobacco",
            "type":"Retail Goods"
        }
    ],
    "sg:phone":"+1 412 474 3275",
    "sg:postcode":"15108",
    "sg:province":"PA",
    "sg:tags":[
        "cigarette",
        "cigar"
    ],
    "wof:name":"Cigar Sensations Inc",
    "wof:placetype":"venue"
},
  "geometry": {"coordinates":[-80.213234,40.510702],"type":"Point"}
}