{
  "type": "Feature",
  "properties": {
    "iso:country":"US",
    "sg:address":"600 Montgomery Mall",
    "sg:city":"North Wales",
    "sg:classifiers":[
        {
            "category":"Shopping",
            "subcategory":"Optician",
            "type":"Retail Goods"
        }
    ],
    "sg:phone":"+1 215 362 4212",
    "sg:postcode":"19454",
    "sg:province":"PA",
    "sg:tags":[
        "eyewear"
    ],
    "wof:name":"Sears Optical",
    "wof:placetype":"venue"
},
  "geometry": {"coordinates":[-75.24250000000001,40.233299],"type":"Point"}
}