{
  "type": "Feature",
  "properties": {
    "addr:full":"29 Delaware Rd Riegelsville PA 18077",
    "addr:housenumber":"29",
    "addr:postcode":"18077",
    "addr:street":"Delaware Rd",
    "iso:country":"US",
    "sg:address":"29 Delaware Rd",
    "sg:city":"Riegelsville",
    "sg:classifiers":[
        {
            "category":"Professional",
            "subcategory":"Business Services",
            "type":"Services"
        }
    ],
    "sg:phone":"+1 610 749 0104",
    "sg:postcode":"18077",
    "sg:province":"PA",
    "sg:tags":[
        "interior",
        "consultant",
        "design",
        "decorator"
    ],
    "wof:name":"River Girl Designs",
    "wof:placetype":"venue"
},
  "geometry": {"coordinates":[-75.193899,40.594455],"type":"Point"}
}