{
  "type": "Feature",
  "properties": {
    "addr:full":"1126 Cocoa Ave Hershey PA 17033",
    "addr:housenumber":"1126",
    "addr:postcode":"17033",
    "addr:street":"Cocoa Ave",
    "iso:country":"US",
    "sg:address":"1126 Cocoa Ave",
    "sg:city":"Hershey",
    "sg:classifiers":[
        {
            "category":"Personal",
            "subcategory":"Hair Removal",
            "type":"Services"
        },
        {
            "category":"Personal",
            "subcategory":"Skin Care",
            "type":"Services"
        },
        {
            "category":"Personal",
            "subcategory":"Day Spa",
            "type":"Services"
        }
    ],
    "sg:phone":"+1 717 508 3526",
    "sg:postcode":"17033",
    "sg:province":"PA",
    "wof:name":"Elan Center For Rejuvenation",
    "wof:placetype":"venue"
},
  "geometry": {"coordinates":[-76.648804,40.2747],"type":"Point"}
}