{
  "type": "Feature",
  "properties": {
    "addr:full":"939 E Street Rd Southampton PA 18966",
    "addr:housenumber":"939",
    "addr:postcode":"18966",
    "addr:street":"E Street Rd",
    "iso:country":"US",
    "sg:address":"939 E Street Rd",
    "sg:city":"Southampton",
    "sg:classifiers":[
        {
            "category":"Professional",
            "subcategory":"Accounting & Tax Preparation",
            "type":"Services"
        }
    ],
    "sg:phone":"+1 215 364 4830",
    "sg:postcode":"18966",
    "sg:province":"PA",
    "sg:tags":[
        "consultant"
    ],
    "wof:name":"William Kerins Tax Collector",
    "wof:placetype":"venue"
},
  "geometry": {"coordinates":[-75.03660000000001,40.170556],"type":"Point"}
}