{
  "type": "Feature",
  "properties": {
    "addr:full":"69 Kremis Rd Greenville PA 16125",
    "addr:housenumber":"69",
    "addr:postcode":"16125",
    "addr:street":"Kremis Rd",
    "iso:country":"US",
    "sg:address":"69 Kremis Rd",
    "sg:city":"Greenville",
    "sg:classifiers":[
        {
            "category":"Farming",
            "subcategory":"Farm",
            "type":"Manufacturing & Wholesale Goods"
        }
    ],
    "sg:phone":"+1 724 475 4620",
    "sg:postcode":"16125",
    "sg:province":"PA",
    "wof:name":"Stony Point Grange",
    "wof:placetype":"venue"
},
  "geometry": {"coordinates":[-80.312729,41.358946],"type":"Point"}
}