{
  "type": "Feature",
  "properties": {
    "iso:country":"US",
    "sg:address":"263 Noll Rd",
    "sg:city":"Loretto",
    "sg:classifiers":[
        {
            "category":"Professional",
            "type":"Services"
        }
    ],
    "sg:phone":"+1   ",
    "sg:postcode":"15940",
    "sg:province":"PA",
    "wof:name":"William F Noll",
    "wof:placetype":"venue"
},
  "geometry": {"coordinates":[-78.61886699999999,40.517257],"type":"Point"}
}