{
  "type": "Feature",
  "properties": {
    "iso:country":"US",
    "sg:address":"1300 Washington Pike",
    "sg:city":"Bridgeville",
    "sg:phone":"+1   ",
    "sg:postcode":"15017",
    "sg:province":"PA",
    "sg:tags":[
        "farm",
        "corn"
    ],
    "wof:name":"Leonard Czarnecki",
    "wof:placetype":"venue"
},
  "geometry": {"coordinates":[-80.095164,40.380618],"type":"Point"}
}