{
  "type": "Feature",
  "properties": {
    "iso:country":"US",
    "sg:address":"609 Mahoning St",
    "sg:city":"Lehighton",
    "sg:classifiers":[
        {
            "category":"Personal",
            "subcategory":"Beauty Salon",
            "type":"Services"
        }
    ],
    "sg:phone":"+1   ",
    "sg:postcode":"18235",
    "sg:province":"PA",
    "sg:tags":[
        "shop"
    ],
    "wof:name":"Donnas Hair Care Center",
    "wof:placetype":"venue"
},
  "geometry": {"coordinates":[-75.717381,40.832836],"type":"Point"}
}