{
  "type": "Feature",
  "properties": {
    "iso:country":"US",
    "sg:address":"137 Millville Rd",
    "sg:city":"Bloomsburg",
    "sg:classifiers":[
        {
            "category":"Retail",
            "subcategory":"Auto Repair",
            "type":"Services"
        }
    ],
    "sg:phone":"+1 570 784 2930",
    "sg:postcode":"17815",
    "sg:province":"PA",
    "sg:tags":[
        "body",
        "automobile",
        "painting"
    ],
    "wof:name":"Kile's Body Shop",
    "wof:placetype":"venue"
},
  "geometry": {"coordinates":[-76.46356,41.009276],"type":"Point"}
}