{
  "type": "Feature",
  "properties": {
    "addr:full":"655 Grove Ave Washington PA 15301",
    "addr:housenumber":"655",
    "addr:postcode":"15301",
    "addr:street":"Grove Ave",
    "iso:country":"US",
    "sg:address":"655 Grove Ave",
    "sg:city":"Washington",
    "sg:classifiers":[
        {
            "category":"Government",
            "subcategory":"Office",
            "type":"Public Place"
        }
    ],
    "sg:phone":"+1   ",
    "sg:postcode":"15301",
    "sg:province":"PA",
    "sg:tags":[
        "executive"
    ],
    "wof:name":"Canton Township",
    "wof:placetype":"venue"
},
  "geometry": {"coordinates":[-80.26381499999999,40.17615],"type":"Point"}
}