{
  "type": "Feature",
  "properties": {
    "iso:country":"US",
    "sg:address":"238 Market St",
    "sg:city":"Philadelphia",
    "sg:classifiers":[
        {
            "category":"Manufacturing",
            "subcategory":"Signs",
            "type":"Manufacturing & Wholesale Goods"
        }
    ],
    "sg:phone":"+1 215 238 9050",
    "sg:postcode":"19106",
    "sg:province":"PA",
    "sg:tags":[
        "printing",
        "specialty",
        "mfg"
    ],
    "sg:website":"www.signaramaccphila.com",
    "wof:name":"SIGN-A-RAMA",
    "wof:placetype":"venue"
},
  "geometry": {"coordinates":[-75.14520400000001,39.949821],"type":"Point"}
}