{
  "type": "Feature",
  "properties": {
    "addr:full":"240 Summit Ave Ligonier PA 15658",
    "addr:housenumber":"240",
    "addr:postcode":"15658",
    "addr:street":"Summit Ave",
    "iso:country":"US",
    "sg:address":"240 Summit Ave",
    "sg:city":"Ligonier",
    "sg:classifiers":[
        {
            "category":"Manufacturing",
            "subcategory":"Printing",
            "type":"Manufacturing & Wholesale Goods"
        }
    ],
    "sg:phone":"+1 724 238 2585",
    "sg:postcode":"15658",
    "sg:province":"PA",
    "sg:tags":[
        "publishing"
    ],
    "wof:name":"Shorok Communications",
    "wof:placetype":"venue"
},
  "geometry": {"coordinates":[-79.234201,40.243738],"type":"Point"}
}