{
  "type": "Feature",
  "properties": {
    "iso:country":"US",
    "sg:address":"1251 S Cedar Crest Blvd",
    "sg:city":"Allentown",
    "sg:classifiers":[
        {
            "category":"Professional",
            "subcategory":"Accounting & Tax Preparation",
            "type":"Services"
        }
    ],
    "sg:phone":"+1 610 770 9236",
    "sg:postcode":"18103",
    "sg:province":"PA",
    "sg:tags":[
        "accountant"
    ],
    "wof:name":"Werner & Co",
    "wof:placetype":"venue"
},
  "geometry": {"coordinates":[-75.518614,40.567309],"type":"Point"}
}