{
  "type": "Feature",
  "properties": {
    "iso:country":"US",
    "sg:address":"6315 Beacon St",
    "sg:city":"Pittsburgh",
    "sg:classifiers":[
        {
            "category":"Professional",
            "subcategory":"Lawyer & Legal Services",
            "type":"Services"
        }
    ],
    "sg:phone":"+1   ",
    "sg:postcode":"15217",
    "sg:province":"PA",
    "wof:name":"Greenfield & Kay",
    "wof:placetype":"venue"
},
  "geometry": {"coordinates":[-79.91663,40.434844],"type":"Point"}
}