{
  "type": "Feature",
  "properties": {
    "addr:full":"190 Matson Ave Wilkes Barre PA 18705",
    "addr:housenumber":"190",
    "addr:postcode":"18705",
    "addr:street":"Matson Ave",
    "iso:country":"US",
    "sg:address":"190 Matson Ave",
    "sg:city":"Wilkes Barre",
    "sg:classifiers":[
        {
            "category":"Professional",
            "subcategory":"Art Services",
            "type":"Services"
        }
    ],
    "sg:phone":"+1 570 822 3827",
    "sg:postcode":"18705",
    "sg:province":"PA",
    "sg:tags":[
        "commercial",
        "design"
    ],
    "wof:name":"Pittston Graphics",
    "wof:placetype":"venue"
},
  "geometry": {"coordinates":[-75.844289,41.259806],"type":"Point"}
}