{
  "type": "Feature",
  "properties": {
    "iso:country":"US",
    "sg:address":"1501 Perkiomen Ave",
    "sg:city":"Reading",
    "sg:classifiers":[
        {
            "category":"Retail",
            "subcategory":"Repair Shop",
            "type":"Services"
        },
        {
            "category":"Professional",
            "subcategory":"Detective & Security Services",
            "type":"Services"
        }
    ],
    "sg:phone":"+1 610 374 0606",
    "sg:postcode":"19602",
    "sg:province":"PA",
    "sg:tags":[
        "skip",
        "tracing",
        "bail",
        "bond"
    ],
    "wof:name":"Gonzales & Gonzales Immigratio",
    "wof:placetype":"venue"
},
  "geometry": {"coordinates":[-75.908524,40.329849],"type":"Point"}
}