{
  "type": "Feature",
  "properties": {
    "iso:country":"US",
    "sg:address":"2902 Aspen Cir",
    "sg:city":"Blue Bell",
    "sg:classifiers":[
        {
            "category":"Real Estate",
            "subcategory":"Real Estate Operator",
            "type":"Services"
        }
    ],
    "sg:phone":"+1 610 279 5497",
    "sg:postcode":"19422",
    "sg:province":"PA",
    "sg:tags":[
        "apartment"
    ],
    "sg:website":"www.townlinetownhomes.com",
    "wof:name":"Townline Assocs",
    "wof:placetype":"venue"
},
  "geometry": {"coordinates":[-75.30439800000001,40.1478],"type":"Point"}
}