{
  "type": "Feature",
  "properties": {
    "iso:country":"US",
    "sg:address":"22 State Rd",
    "sg:city":"Paoli",
    "sg:classifiers":[
        {
            "category":"Health Services",
            "subcategory":"Doctor",
            "type":"Services"
        }
    ],
    "sg:phone":"+1 610 644 5547",
    "sg:postcode":"19301",
    "sg:province":"PA",
    "sg:tags":[
        "dentist"
    ],
    "wof:name":"Lawrence C Miller DDS",
    "wof:placetype":"venue"
},
  "geometry": {"coordinates":[-75.486557,40.041536],"type":"Point"}
}