{
  "type": "Feature",
  "properties": {
    "addr:full":"1125 Virginia Dr Fort Washington PA 19034",
    "addr:housenumber":"1125",
    "addr:postcode":"19034",
    "addr:street":"Virginia Dr",
    "iso:country":"US",
    "sg:address":"1125 Virginia Dr",
    "sg:city":"Fort Washington",
    "sg:classifiers":[
        {
            "category":"Organizations",
            "subcategory":"Professional Association",
            "type":"Services"
        }
    ],
    "sg:phone":"+1 215 542 4792",
    "sg:postcode":"19034",
    "sg:province":"PA",
    "wof:name":"ADP Savings Assn",
    "wof:placetype":"venue"
},
  "geometry": {"coordinates":[-75.181217,40.135985],"type":"Point"}
}