{
  "type": "Feature",
  "properties": {
    "iso:country":"US",
    "sg:address":"201 N Tulpehocken Rd",
    "sg:city":"Reading",
    "sg:classifiers":[
        {
            "category":"Wholesale",
            "subcategory":"Groceries",
            "type":"Manufacturing & Wholesale Goods"
        }
    ],
    "sg:phone":"+1 610 374 4241",
    "sg:postcode":"19601",
    "sg:province":"PA",
    "sg:tags":[
        "confectionery",
        "candy"
    ],
    "wof:name":"SCS Sales",
    "wof:placetype":"venue"
},
  "geometry": {"coordinates":[-75.963229,40.359223],"type":"Point"}
}