{
  "type": "Feature",
  "properties": {
    "iso:country":"US",
    "sg:address":"8150 Perry Hwy",
    "sg:city":"Pittsburgh",
    "sg:classifiers":[
        {
            "category":"Professional",
            "subcategory":"Management & Consulting",
            "type":"Services"
        }
    ],
    "sg:phone":"+1 412 548 1030",
    "sg:postcode":"15237",
    "sg:province":"PA",
    "sg:tags":[
        "marketing",
        "program"
    ],
    "wof:name":"Data Banque LTD",
    "wof:placetype":"venue"
},
  "geometry": {"coordinates":[-80.038737,40.555387],"type":"Point"}
}