{
  "type": "Feature",
  "properties": {
    "addr:full":"1 W Broad St Bethlehem PA 18018",
    "addr:housenumber":"1",
    "addr:postcode":"18018",
    "addr:street":"W Broad St",
    "iso:country":"US",
    "sg:address":"1 W Broad St",
    "sg:city":"Bethlehem",
    "sg:classifiers":[
        {
            "category":"Real Estate",
            "subcategory":"Real Estate Agent",
            "type":"Services"
        }
    ],
    "sg:phone":"+1   ",
    "sg:postcode":"18018",
    "sg:province":"PA",
    "sg:tags":[
        "commercial"
    ],
    "wof:name":"Weichert Realtors",
    "wof:placetype":"venue"
},
  "geometry": {"coordinates":[-75.38191500000001,40.622353],"type":"Point"}
}