{
  "type": "Feature",
  "properties": {
    "iso:country":"US",
    "sg:address":"716 Thomson Park Dr",
    "sg:city":"Cranberry Twp",
    "sg:classifiers":[
        {
            "category":"Retail",
            "subcategory":"Car Wash",
            "type":"Services"
        }
    ],
    "sg:phone":"+1 724 742 9000",
    "sg:postcode":"16066",
    "sg:province":"PA",
    "wof:name":"Car Wash Technologies",
    "wof:placetype":"venue"
},
  "geometry": {"coordinates":[-80.113197,40.696098],"type":"Point"}
}