{
  "type": "Feature",
  "properties": {
    "iso:country":"US",
    "sg:address":"2415 Warwick Rd",
    "sg:city":"York",
    "sg:classifiers":[
        {
            "category":"Building & Trades",
            "subcategory":"Construction",
            "type":"Services"
        }
    ],
    "sg:phone":"+1   ",
    "sg:postcode":"17408",
    "sg:province":"PA",
    "sg:tags":[
        "carpentry",
        "contractor"
    ],
    "wof:name":"Erick E Trish",
    "wof:placetype":"venue"
},
  "geometry": {"coordinates":[-76.789494,39.968001],"type":"Point"}
}