{
  "type": "Feature",
  "properties": {
    "iso:country":"US",
    "sg:address":"130 S Lloyd Ave",
    "sg:city":"Downingtown",
    "sg:classifiers":[
        {
            "category":"Travel",
            "subcategory":"Hotels & Motels",
            "type":"Entertainment"
        }
    ],
    "sg:phone":"+1 610 269 9100",
    "sg:postcode":"19335",
    "sg:province":"PA",
    "sg:tags":[
        "breakfast",
        "accommodation",
        "bed"
    ],
    "wof:name":"Glen Isle Farm",
    "wof:placetype":"venue"
},
  "geometry": {"coordinates":[-75.723848,39.998402],"type":"Point"}
}