{
  "type": "Feature",
  "properties": {
    "addr:full":"79 Hutson St Wilkes Barre PA 18702",
    "addr:housenumber":"79",
    "addr:postcode":"18702",
    "addr:street":"Hutson St",
    "iso:country":"US",
    "sg:address":"79 Hutson St",
    "sg:city":"Wilkes Barre",
    "sg:classifiers":[
        {
            "category":"Professional",
            "subcategory":"Business Services",
            "type":"Services"
        }
    ],
    "sg:phone":"+1 570 823 5660",
    "sg:postcode":"18702",
    "sg:province":"PA",
    "sg:tags":[
        "notary"
    ],
    "wof:name":"Bernadette Holloway",
    "wof:placetype":"venue"
},
  "geometry": {"coordinates":[-75.888644,41.234133],"type":"Point"}
}