{
  "type": "Feature",
  "properties": {
    "iso:country":"US",
    "sg:address":"8100 Colfax St",
    "sg:city":"Philadelphia",
    "sg:classifiers":[
        {
            "category":"Organizations",
            "subcategory":"Religious Organization",
            "type":"Services"
        }
    ],
    "sg:phone":"+1 215 333 0977",
    "sg:postcode":"19136",
    "sg:province":"PA",
    "sg:tags":[
        "church"
    ],
    "wof:name":"St Jerome's Church",
    "wof:placetype":"venue"
},
  "geometry": {"coordinates":[-75.028942,40.054437],"type":"Point"}
}