{
  "type": "Feature",
  "properties": {
    "iso:country":"US",
    "sg:address":"812 Smalls Ferry Rd",
    "sg:city":"Enon Valley",
    "sg:classifiers":[
        {
            "category":"Wholesale",
            "subcategory":"Machinery & Supplies",
            "type":"Manufacturing & Wholesale Goods"
        },
        {
            "category":"Farming",
            "subcategory":"Dairy Farm",
            "type":"Manufacturing & Wholesale Goods"
        }
    ],
    "sg:phone":"+1 724 667 7987",
    "sg:postcode":"16120",
    "sg:province":"PA",
    "sg:tags":[
        "equipment"
    ],
    "wof:name":"Shulacks Farm Equipment",
    "wof:placetype":"venue"
},
  "geometry": {"coordinates":[-80.469803,40.951907],"type":"Point"}
}