{
  "type": "Feature",
  "properties": {
    "addr:full":"73 Pine Glenn Rd Lewistown PA 17044",
    "addr:housenumber":"73",
    "addr:postcode":"17044",
    "addr:street":"Pine Glenn Rd",
    "iso:country":"US",
    "sg:address":"73 Pine Glenn Rd",
    "sg:city":"Lewistown",
    "sg:classifiers":[
        {
            "category":"Retail",
            "subcategory":"Repair Shop",
            "type":"Services"
        }
    ],
    "sg:phone":"+1   ",
    "sg:postcode":"17044",
    "sg:province":"PA",
    "wof:name":"Johnnies Upholstery Shop",
    "wof:placetype":"venue"
},
  "geometry": {"coordinates":[-77.680295,40.498393],"type":"Point"}
}