{
  "type": "Feature",
  "properties": {
    "iso:country":"US",
    "sg:address":"303 Loucks Ave",
    "sg:city":"Scottdale",
    "sg:classifiers":[
        {
            "category":"Personal",
            "subcategory":"Beauty Salon",
            "type":"Services"
        }
    ],
    "sg:phone":"+1 724 887 4440",
    "sg:postcode":"15683",
    "sg:province":"PA",
    "sg:tags":[
        "shop"
    ],
    "wof:name":"Sorrento Styling Salon",
    "wof:placetype":"venue"
},
  "geometry": {"coordinates":[-79.587828,40.103764],"type":"Point"}
}