{
  "type": "Feature",
  "properties": {
    "iso:country":"US",
    "sg:address":"137 Hufford Run Rd",
    "sg:city":"Marianna",
    "sg:classifiers":[
        {
            "category":"Retail",
            "subcategory":"Animal Services",
            "type":"Services"
        }
    ],
    "sg:phone":"+1   ",
    "sg:postcode":"15345",
    "sg:province":"PA",
    "wof:name":"Bar Z Barrel Horses",
    "wof:placetype":"venue"
},
  "geometry": {"coordinates":[-80.144531,40.01153],"type":"Point"}
}