{
  "type": "Feature",
  "properties": {
    "addr:full":"4645 N 5th St Philadelphia PA 19140",
    "addr:housenumber":"4645",
    "addr:postcode":"19140",
    "addr:street":"N 5Th St",
    "iso:country":"US",
    "sg:address":"4645 N 5th St",
    "sg:city":"Philadelphia",
    "sg:classifiers":[
        {
            "category":"Banks & Credit Unions",
            "subcategory":"Bank",
            "type":"Services"
        }
    ],
    "sg:phone":"+1   ",
    "sg:postcode":"19140",
    "sg:province":"PA",
    "sg:tags":[
        "national"
    ],
    "wof:name":"Wachovia Bank National Assn",
    "wof:placetype":"venue"
},
  "geometry": {"coordinates":[-75.13346799999999,40.02254],"type":"Point"}
}