{
  "type": "Feature",
  "properties": {
    "addr:full":"1913 S Broad St Philadelphia PA 19148",
    "addr:housenumber":"1913",
    "addr:postcode":"19148",
    "addr:street":"S Broad St",
    "iso:country":"US",
    "sg:address":"1913 S Broad St",
    "sg:city":"Philadelphia",
    "sg:classifiers":[
        {
            "category":"Personal",
            "subcategory":"Beauty Salon",
            "type":"Services"
        }
    ],
    "sg:phone":"+1   ",
    "sg:postcode":"19148",
    "sg:province":"PA",
    "sg:tags":[
        "shop"
    ],
    "wof:name":"Fashion Nails",
    "wof:placetype":"venue"
},
  "geometry": {"coordinates":[-75.169262,39.925728],"type":"Point"}
}