{
  "type": "Feature",
  "properties": {
    "addr:full":"826 Ann St Stroudsburg PA 18360",
    "addr:housenumber":"826",
    "addr:postcode":"18360",
    "addr:street":"Ann St",
    "iso:country":"US",
    "sg:address":"826 Ann St",
    "sg:city":"Stroudsburg",
    "sg:classifiers":[
        {
            "category":"Retail",
            "subcategory":"Auto Repair",
            "type":"Services"
        }
    ],
    "sg:phone":"+1 570 421 9941",
    "sg:postcode":"18360",
    "sg:province":"PA",
    "sg:tags":[
        "automobile",
        "inspection"
    ],
    "wof:name":"Tony's Auto Repair",
    "wof:placetype":"venue"
},
  "geometry": {"coordinates":[-75.19571999999999,40.983641],"type":"Point"}
}