{
  "type": "Feature",
  "properties": {
    "addr:full":"1395 Lenape Rd West Chester PA 19382",
    "addr:housenumber":"1395",
    "addr:postcode":"19382",
    "addr:street":"Lenape Rd",
    "iso:country":"US",
    "sg:address":"1395 Lenape Rd",
    "sg:city":"West Chester",
    "sg:classifiers":[
        {
            "category":"Building & Trades",
            "subcategory":"Electrical",
            "type":"Services"
        }
    ],
    "sg:phone":"+1 610 793 5183",
    "sg:postcode":"19382",
    "sg:province":"PA",
    "sg:tags":[
        "electric",
        "contractor"
    ],
    "wof:name":"Raff Electric Inc",
    "wof:placetype":"venue"
},
  "geometry": {"coordinates":[-75.638052,39.907577],"type":"Point"}
}