{
  "type": "Feature",
  "properties": {
    "iso:country":"US",
    "sg:address":"1515 Ridge Rd",
    "sg:city":"Lancaster",
    "sg:classifiers":[
        {
            "category":"Health Services",
            "subcategory":"Doctor",
            "type":"Services"
        }
    ],
    "sg:phone":"+1   ",
    "sg:postcode":"17603",
    "sg:province":"PA",
    "sg:tags":[
        "medical"
    ],
    "wof:name":"Justin L Cappiello",
    "wof:placetype":"venue"
},
  "geometry": {"coordinates":[-76.342409,40.045151],"type":"Point"}
}