{
  "type": "Feature",
  "properties": {
    "iso:country":"US",
    "sg:address":"601 S 5th St",
    "sg:city":"Reading",
    "sg:classifiers":[
        {
            "category":"Wholesale",
            "subcategory":"Construction Materials",
            "type":"Manufacturing & Wholesale Goods"
        }
    ],
    "sg:phone":"+1 610 376 5049",
    "sg:postcode":"19602",
    "sg:province":"PA",
    "sg:tags":[
        "building",
        "aluminum"
    ],
    "wof:name":"Aluminum Building Products",
    "wof:placetype":"venue"
},
  "geometry": {"coordinates":[-75.92859199999999,40.325793],"type":"Point"}
}