{
  "type": "Feature",
  "properties": {
    "iso:country":"US",
    "sg:address":"209 Stalman Ln",
    "sg:city":"Kennerdell",
    "sg:classifiers":[
        {
            "category":"Building & Trades",
            "subcategory":"Construction",
            "type":"Services"
        }
    ],
    "sg:phone":"+1   ",
    "sg:postcode":"16374",
    "sg:province":"PA",
    "sg:tags":[
        "specializing",
        "clearing",
        "land",
        "contractor"
    ],
    "wof:name":"Tassone Land Management",
    "wof:placetype":"venue"
},
  "geometry": {"coordinates":[-79.736431,41.257691],"type":"Point"}
}