{
  "type": "Feature",
  "properties": {
    "iso:country":"US",
    "sg:address":"3817 Gettysburg Rd",
    "sg:city":"Camp Hill",
    "sg:classifiers":[
        {
            "category":"Restaurant",
            "type":"Food & Drink"
        }
    ],
    "sg:phone":"+1 717 761 1330",
    "sg:postcode":"17011",
    "sg:province":"PA",
    "wof:name":"Harding's Restaurant & Catering",
    "wof:placetype":"venue"
},
  "geometry": {"coordinates":[-76.9422,40.2215],"type":"Point"}
}