{
  "type": "Feature",
  "properties": {
    "iso:country":"US",
    "sg:address":"928 Vickroy Ave",
    "sg:city":"Johnstown",
    "sg:classifiers":[
        {
            "category":"Personal",
            "subcategory":"Beauty Salon",
            "type":"Services"
        }
    ],
    "sg:phone":"+1   ",
    "sg:postcode":"15905",
    "sg:province":"PA",
    "sg:tags":[
        "shop"
    ],
    "wof:name":"New You By Darlene",
    "wof:placetype":"venue"
},
  "geometry": {"coordinates":[-78.91525300000001,40.28484],"type":"Point"}
}