{
  "type": "Feature",
  "properties": {
    "addr:full":"930 Bellaire Ave Pittsburgh PA 15226",
    "addr:housenumber":"930",
    "addr:postcode":"15226",
    "addr:street":"Bellaire Ave",
    "iso:country":"US",
    "sg:address":"930 Bellaire Ave",
    "sg:city":"Pittsburgh",
    "sg:classifiers":[
        {
            "category":"Banks & Credit Unions",
            "subcategory":"Bank",
            "type":"Services"
        }
    ],
    "sg:phone":"+1   ",
    "sg:postcode":"15226",
    "sg:province":"PA",
    "sg:tags":[
        "mortgage"
    ],
    "wof:name":"NBC Mortgage",
    "wof:placetype":"venue"
},
  "geometry": {"coordinates":[-80.01849300000001,40.393845],"type":"Point"}
}