{
  "type": "Feature",
  "properties": {
    "iso:country":"US",
    "sg:address":"334 Dean St",
    "sg:city":"West Chester",
    "sg:classifiers":[
        {
            "category":"Retail",
            "subcategory":"Photofinishing",
            "type":"Services"
        }
    ],
    "sg:phone":"+1   ",
    "sg:postcode":"19382",
    "sg:province":"PA",
    "sg:tags":[
        "photo",
        "document",
        "restoration",
        "laboratory"
    ],
    "wof:name":"Wwwphotomdnet",
    "wof:placetype":"venue"
},
  "geometry": {"coordinates":[-75.607243,39.953757],"type":"Point"}
}