{
  "type": "Feature",
  "properties": {
    "addr:full":"1610 W River Rd Nichols PA 13812",
    "addr:housenumber":"1610",
    "addr:postcode":"13812",
    "addr:street":"W River Rd",
    "iso:country":"US",
    "sg:address":"1610 W River Rd",
    "sg:city":"Nichols",
    "sg:classifiers":[
        {
            "category":"Retail",
            "subcategory":"Auto Repair",
            "type":"Services"
        }
    ],
    "sg:phone":"+1   ",
    "sg:postcode":"13812",
    "sg:province":"PA",
    "wof:name":"Seeleys Garage",
    "wof:placetype":"venue"
},
  "geometry": {"coordinates":[-76.396011,42.027457],"type":"Point"}
}