{
  "type": "Feature",
  "properties": {
    "addr:full":"101 Bridge St Tionesta PA 16353",
    "addr:housenumber":"101",
    "addr:postcode":"16353",
    "addr:street":"Bridge St",
    "iso:country":"US",
    "sg:address":"101 Bridge St",
    "sg:city":"Tionesta",
    "sg:classifiers":[
        {
            "category":"Real Estate",
            "subcategory":"Real Estate Operator",
            "type":"Services"
        }
    ],
    "sg:phone":"+1 814 755 4540",
    "sg:postcode":"16353",
    "sg:province":"PA",
    "sg:tags":[
        "building",
        "apartment"
    ],
    "wof:name":"Tionesta Manor",
    "wof:placetype":"venue"
},
  "geometry": {"coordinates":[-79.459379,41.493947],"type":"Point"}
}