{
  "type": "Feature",
  "properties": {
    "iso:country":"US",
    "sg:address":"10 Kendel Cir",
    "sg:city":"Coatesville",
    "sg:classifiers":[
        {
            "category":"Professional",
            "subcategory":"Computer Services",
            "type":"Services"
        }
    ],
    "sg:phone":"+1   ",
    "sg:postcode":"19320",
    "sg:province":"PA",
    "sg:tags":[
        "related"
    ],
    "wof:name":"Lamar Logic",
    "wof:placetype":"venue"
},
  "geometry": {"coordinates":[-75.854412,39.996307],"type":"Point"}
}