{
  "type": "Feature",
  "properties": {
    "iso:country":"US",
    "sg:address":"4368 Mercer St",
    "sg:city":"Sandy Lake",
    "sg:classifiers":[
        {
            "category":"Freight",
            "type":"Transportation"
        }
    ],
    "sg:phone":"+1   ",
    "sg:postcode":"16145",
    "sg:province":"PA",
    "sg:tags":[
        "operator",
        "local",
        "trucking"
    ],
    "wof:name":"James T Adams Trucking",
    "wof:placetype":"venue"
},
  "geometry": {"coordinates":[-80.07487,41.421563],"type":"Point"}
}