{
  "type": "Feature",
  "properties": {
    "iso:country":"US",
    "sg:address":"1496 Johns Hill Rd",
    "sg:city":"Brookville",
    "sg:classifiers":[
        {
            "category":"Professional",
            "subcategory":"Accounting & Tax Preparation",
            "type":"Services"
        }
    ],
    "sg:phone":"+1 814 715 0784",
    "sg:postcode":"15825",
    "sg:province":"PA",
    "sg:tags":[
        "bookkeeping"
    ],
    "wof:name":"Riley's Accounting & Computingservices",
    "wof:placetype":"venue"
},
  "geometry": {"coordinates":[-79.068662,41.129945],"type":"Point"}
}