{
  "type": "Feature",
  "properties": {
    "iso:country":"US",
    "sg:address":"1400 Fairview Ave",
    "sg:city":"Berwick",
    "sg:classifiers":[
        {
            "category":"Retail",
            "subcategory":"Auto Repair",
            "type":"Services"
        }
    ],
    "sg:phone":"+1 570 752 6451",
    "sg:postcode":"18603",
    "sg:province":"PA",
    "sg:tags":[
        "body",
        "automobile",
        "painting"
    ],
    "wof:name":"Dave Hargraves Auto Body",
    "wof:placetype":"venue"
},
  "geometry": {"coordinates":[-76.25643100000001,41.051489],"type":"Point"}
}