{
  "type": "Feature",
  "properties": {
    "iso:country":"US",
    "sg:address":"5870 Easton Rd",
    "sg:city":"Pipersville",
    "sg:classifiers":[
        {
            "category":"Arts & Performance",
            "subcategory":"Arts Center",
            "type":"Entertainment"
        }
    ],
    "sg:phone":"+1 215 766 7205",
    "sg:postcode":"18947",
    "sg:province":"PA",
    "sg:tags":[
        "performing"
    ],
    "sg:website":"www.danceartscollaborative.com",
    "wof:name":"Dance Arts Collaborative Llc",
    "wof:placetype":"venue"
},
  "geometry": {"coordinates":[-75.146767,40.38675],"type":"Point"}
}