{
  "type": "Feature",
  "properties": {
    "addr:full":"14425 Main St Wattsburg PA 16442",
    "addr:housenumber":"14425",
    "addr:postcode":"16442",
    "addr:street":"Main St",
    "iso:country":"US",
    "sg:address":"14425 Main St",
    "sg:city":"Wattsburg",
    "sg:classifiers":[
        {
            "category":"Home & Garden",
            "subcategory":"Carpets & Floor Coverings",
            "type":"Retail Goods"
        }
    ],
    "sg:phone":"+1 814 739 2586",
    "sg:postcode":"16442",
    "sg:province":"PA",
    "sg:tags":[
        "dealer",
        "rug"
    ],
    "wof:name":"Wright Carpets",
    "wof:placetype":"venue"
},
  "geometry": {"coordinates":[-79.81083099999999,42.002086],"type":"Point"}
}