{
  "type": "Feature",
  "properties": {
    "iso:country":"US",
    "sg:address":"209 N 9th St",
    "sg:city":"Lebanon",
    "sg:classifiers":[
        {
            "category":"Home & Garden",
            "subcategory":"Home Furnishings",
            "type":"Retail Goods"
        }
    ],
    "sg:phone":"+1 717 272 4080",
    "sg:postcode":"17046",
    "sg:province":"PA",
    "sg:tags":[
        "curtain",
        "made",
        "drapery",
        "furniture"
    ],
    "wof:name":"C E White Enterprises Inc",
    "wof:placetype":"venue"
},
  "geometry": {"coordinates":[-76.426817,40.343026],"type":"Point"}
}