{
  "type": "Feature",
  "properties": {
    "addr:full":"704 Mountain Rd Effort PA 18330",
    "addr:housenumber":"704",
    "addr:postcode":"18330",
    "addr:street":"Mountain Rd",
    "iso:country":"US",
    "sg:address":"704 Mountain Rd",
    "sg:city":"Effort",
    "sg:classifiers":[
        {
            "category":"Building & Trades",
            "subcategory":"Construction",
            "type":"Services"
        }
    ],
    "sg:phone":"+1 570 629 2555",
    "sg:postcode":"18330",
    "sg:province":"PA",
    "sg:tags":[
        "excavating",
        "contractor"
    ],
    "wof:name":"Fischer Construction Co",
    "wof:placetype":"venue"
},
  "geometry": {"coordinates":[-75.47497,40.987552],"type":"Point"}
}