{
  "type": "Feature",
  "properties": {
    "addr:full":"4723 Point Pleasant Pike Doylestown PA 18902",
    "addr:housenumber":"4723",
    "addr:postcode":"18902",
    "addr:street":"Point Pleasant Pike",
    "iso:country":"US",
    "sg:address":"4723 Point Pleasant Pike",
    "sg:city":"Doylestown",
    "sg:classifiers":[
        {
            "category":"Professional",
            "type":"Services"
        }
    ],
    "sg:phone":"+1 215 766 3439",
    "sg:postcode":"18902",
    "sg:province":"PA",
    "sg:tags":[
        "caterer"
    ],
    "sg:website":"www.maxhansencaterer.com",
    "wof:name":"Max Hansen Caterers",
    "wof:placetype":"venue"
},
  "geometry": {"coordinates":[-75.124084,40.362502],"type":"Point"}
}