{
  "type": "Feature",
  "properties": {
    "iso:country":"US",
    "sg:address":"309 Lotz Ave",
    "sg:city":"Altoona",
    "sg:classifiers":[
        {
            "category":"Organizations",
            "subcategory":"Religious Organization",
            "type":"Services"
        }
    ],
    "sg:phone":"+1 814 942 5503",
    "sg:postcode":"16602",
    "sg:province":"PA",
    "sg:tags":[
        "church"
    ],
    "wof:name":"St John The Evangelist Church",
    "wof:placetype":"venue"
},
  "geometry": {"coordinates":[-78.39428700000001,40.463409],"type":"Point"}
}