{
  "type": "Feature",
  "properties": {
    "addr:full":"50 Lititz Run Rd Lititz PA 17543",
    "addr:housenumber":"50",
    "addr:postcode":"17543",
    "addr:street":"Lititz Run Rd",
    "iso:country":"US",
    "sg:address":"50 Lititz Run Rd",
    "sg:city":"Lititz",
    "sg:classifiers":[
        {
            "category":"Professional",
            "subcategory":"Management & Consulting",
            "type":"Services"
        }
    ],
    "sg:phone":"+1   ",
    "sg:postcode":"17543",
    "sg:province":"PA",
    "sg:tags":[
        "water",
        "plant",
        "waste",
        "treatment"
    ],
    "wof:name":"Severn Trent Envmtl Svcs",
    "wof:placetype":"venue"
},
  "geometry": {"coordinates":[-76.285155,40.153149],"type":"Point"}
}