{
  "type": "Feature",
  "properties": {
    "addr:full":"3802 Caughey Rd Erie PA 16506",
    "addr:housenumber":"3802",
    "addr:postcode":"16506",
    "addr:street":"Caughey Rd",
    "iso:country":"US",
    "sg:address":"3802 Caughey Rd",
    "sg:city":"Erie",
    "sg:classifiers":[
        {
            "category":"Home & Garden",
            "subcategory":"Furniture",
            "type":"Retail Goods"
        }
    ],
    "sg:phone":"+1   ",
    "sg:postcode":"16506",
    "sg:province":"PA",
    "wof:name":"Patio Shop The",
    "wof:placetype":"venue"
},
  "geometry": {"coordinates":[-80.144835,42.071541],"type":"Point"}
}