{
  "type": "Feature",
  "properties": {
    "iso:country":"US",
    "sg:address":"4227 Union Deposit Rd",
    "sg:city":"Harrisburg",
    "sg:classifiers":[
        {
            "category":"Food & Beverages",
            "subcategory":"Liquor & Beverages",
            "type":"Retail Goods"
        }
    ],
    "sg:phone":"+1   ",
    "sg:postcode":"17111",
    "sg:province":"PA",
    "sg:tags":[
        "alcoholic"
    ],
    "wof:name":"Wine & Spirits Shoppe 2215",
    "wof:placetype":"venue"
},
  "geometry": {"coordinates":[-76.814768,40.279026],"type":"Point"}
}