{
  "type": "Feature",
  "properties": {
    "iso:country":"US",
    "sg:address":"1226 W Broad St",
    "sg:city":"Quakertown",
    "sg:classifiers":[
        {
            "category":"Professional",
            "subcategory":"Accounting & Tax Preparation",
            "type":"Services"
        }
    ],
    "sg:phone":"+1 215 536 8000",
    "sg:postcode":"18951",
    "sg:province":"PA",
    "sg:tags":[
        "return",
        "accountants-certified",
        "preparation-business",
        "public"
    ],
    "sg:website":"http://www.rrccpa.com",
    "wof:name":"Fox Rotchild O'brien & Frankel Llp",
    "wof:placetype":"venue"
},
  "geometry": {"coordinates":[-75.350471,40.44245],"type":"Point"}
}