{
  "type": "Feature",
  "properties": {
    "iso:country":"US",
    "sg:address":"521 Station Ave",
    "sg:city":"Glenside",
    "sg:classifiers":[
        {
            "category":"Professional",
            "type":"Services"
        }
    ],
    "sg:phone":"+1 215 885 6326",
    "sg:postcode":"19038",
    "sg:province":"PA",
    "sg:tags":[
        "establishment"
    ],
    "wof:name":"Institute For Contextual Growt",
    "wof:placetype":"venue"
},
  "geometry": {"coordinates":[-75.180752,40.10205],"type":"Point"}
}