{
  "type": "Feature",
  "properties": {
    "iso:country":"US",
    "sg:address":"2618 Freeport Rd",
    "sg:city":"Natrona Heights",
    "sg:classifiers":[
        {
            "category":"Shopping",
            "subcategory":"Jewelry",
            "type":"Retail Goods"
        }
    ],
    "sg:phone":"+1 724 226 8767",
    "sg:postcode":"15065",
    "sg:province":"PA",
    "wof:name":"Diamonds & More",
    "wof:placetype":"venue"
},
  "geometry": {"coordinates":[-79.714055,40.633598],"type":"Point"}
}