{
  "type": "Feature",
  "properties": {
    "addr:full":"1953 W Market St Pottsville PA 17901",
    "addr:housenumber":"1953",
    "addr:postcode":"17901",
    "addr:street":"W Market St",
    "iso:country":"US",
    "sg:address":"1953 W Market St",
    "sg:city":"Pottsville",
    "sg:classifiers":[
        {
            "category":"Autos & Motor Vehicles",
            "subcategory":"Fuel & Gas Station",
            "type":"Retail Goods"
        }
    ],
    "sg:phone":"+1 570 622 5685",
    "sg:postcode":"17901",
    "sg:province":"PA",
    "sg:tags":[
        "oil"
    ],
    "wof:name":"Shell",
    "wof:placetype":"venue"
},
  "geometry": {"coordinates":[-76.218518,40.677369],"type":"Point"}
}