{
  "type": "Feature",
  "properties": {
    "addr:full":"347 Patterson Ave Du Bois PA 15801",
    "addr:housenumber":"347",
    "addr:postcode":"15801",
    "addr:street":"Patterson Ave Du Bois",
    "iso:country":"US",
    "sg:address":"347 Patterson Ave",
    "sg:city":"Du Bois",
    "sg:classifiers":[
        {
            "category":"Building & Trades",
            "subcategory":"Construction",
            "type":"Services"
        }
    ],
    "sg:phone":"+1 814 371 2772",
    "sg:postcode":"15801",
    "sg:province":"PA",
    "sg:tags":[
        "downspouts",
        "gutter"
    ],
    "wof:name":"J & D Seamless Gutters",
    "wof:placetype":"venue"
},
  "geometry": {"coordinates":[-78.777085,41.117717],"type":"Point"}
}