{
  "type": "Feature",
  "properties": {
    "iso:country":"US",
    "sg:address":"3126 Oley Turnpike Rd",
    "sg:city":"Reading",
    "sg:classifiers":[
        {
            "category":"Health Services",
            "subcategory":"Doctor",
            "type":"Services"
        }
    ],
    "sg:phone":"+1 610 779 7998",
    "sg:postcode":"19606",
    "sg:province":"PA",
    "wof:name":"Larry R Lewis DDS",
    "wof:placetype":"venue"
},
  "geometry": {"coordinates":[-75.87215399999999,40.32656],"type":"Point"}
}