{
  "type": "Feature",
  "properties": {
    "iso:country":"US",
    "sg:address":"995 Beaver Grade Rd",
    "sg:city":"Coraopolis",
    "sg:classifiers":[
        {
            "category":"Health Services",
            "subcategory":"Doctor",
            "type":"Services"
        },
        {
            "category":"Health Services",
            "subcategory":"Dentist",
            "type":"Services"
        }
    ],
    "sg:phone":"+1 412 262 3707",
    "sg:postcode":"15108",
    "sg:province":"PA",
    "sg:tags":[
        "dentists-oral",
        "physician",
        "maxillofacial",
        "surgeons",
        "surgery",
        "oral"
    ],
    "wof:name":"Fedorchak Rodney N DMD",
    "wof:placetype":"venue"
},
  "geometry": {"coordinates":[-80.207809,40.505699],"type":"Point"}
}