{
  "type": "Feature",
  "properties": {
    "iso:country":"US",
    "sg:address":"219 E Pittsburgh St",
    "sg:city":"Greensburg",
    "sg:classifiers":[
        {
            "category":"Food & Beverages",
            "subcategory":"Groceries & Convenience Stores",
            "type":"Retail Goods"
        }
    ],
    "sg:phone":"+1 724 837 9388",
    "sg:postcode":"15601",
    "sg:province":"PA",
    "wof:name":"Stop N-Go Food Store",
    "wof:placetype":"venue"
},
  "geometry": {"coordinates":[-79.539816,40.303338],"type":"Point"}
}