{
  "type": "Feature",
  "properties": {
    "addr:full":"3557 Manor Rd Glenmoore PA 19343",
    "addr:housenumber":"3557",
    "addr:postcode":"19343",
    "addr:street":"Manor Rd",
    "iso:country":"US",
    "sg:address":"3557 Manor Rd",
    "sg:city":"Glenmoore",
    "sg:classifiers":[
        {
            "category":"Home & Garden",
            "subcategory":"Building Materials",
            "type":"Retail Goods"
        }
    ],
    "sg:phone":"+1 610 942 4526",
    "sg:postcode":"19343",
    "sg:province":"PA",
    "sg:tags":[
        "downspouts",
        "gutter"
    ],
    "wof:name":"Pro Tec Seamless Gutters",
    "wof:placetype":"venue"
},
  "geometry": {"coordinates":[-75.81562099999999,40.059688],"type":"Point"}
}