{
  "type": "Feature",
  "properties": {
    "addr:full":"Cooper Drive & Street Rd Warminster PA 18974",
    "addr:postcode":"18974",
    "addr:street":"Cooper Drive & Street Rd",
    "iso:country":"US",
    "sg:address":"Cooper Drive & Street Rd",
    "sg:city":"Warminster",
    "sg:classifiers":[
        {
            "category":"Health Services",
            "subcategory":"Dentist",
            "type":"Services"
        }
    ],
    "sg:phone":"+1 215 672 5320",
    "sg:postcode":"18974",
    "sg:province":"PA",
    "wof:name":"Forlano Ronald P DDS",
    "wof:placetype":"venue"
},
  "geometry": {"coordinates":[-75.120884,40.218831],"type":"Point"}
}