{
  "type": "Feature",
  "properties": {
    "iso:country":"US",
    "sg:address":"3183 W Market St",
    "sg:city":"York",
    "sg:classifiers":[
        {
            "category":"Wholesale",
            "subcategory":"Electrical",
            "type":"Manufacturing & Wholesale Goods"
        }
    ],
    "sg:phone":"+1 717 792 3343",
    "sg:postcode":"17404",
    "sg:province":"PA",
    "sg:tags":[
        "generator"
    ],
    "wof:name":"Markle Mower",
    "wof:placetype":"venue"
},
  "geometry": {"coordinates":[-76.78630200000001,39.944374],"type":"Point"}
}