{
  "type": "Feature",
  "properties": {
    "addr:full":"2100 Tremont St Philadelphia PA 19115",
    "addr:housenumber":"2100",
    "addr:postcode":"19115",
    "addr:street":"Tremont St",
    "iso:country":"US",
    "sg:address":"2100 Tremont St",
    "sg:city":"Philadelphia",
    "sg:classifiers":[
        {
            "category":"Real Estate",
            "subcategory":"Real Estate Services",
            "type":"Services"
        },
        {
            "category":"Real Estate",
            "subcategory":"Real Estate Operator",
            "type":"Services"
        }
    ],
    "sg:phone":"+1 215 677 6388",
    "sg:postcode":"19115",
    "sg:province":"PA",
    "sg:tags":[
        "vacancy",
        "apartment",
        "rental",
        "finder",
        "listing"
    ],
    "wof:name":"Winmont Apts",
    "wof:placetype":"venue"
},
  "geometry": {"coordinates":[-75.04034799999999,40.075281],"type":"Point"}
}