{
  "type": "Feature",
  "properties": {
    "iso:country":"US",
    "sg:address":"661 Memorial Hwy",
    "sg:city":"Dallas",
    "sg:classifiers":[
        {
            "category":"Restaurant",
            "type":"Food & Drink"
        }
    ],
    "sg:phone":"+1 570 675 9611",
    "sg:postcode":"18612",
    "sg:province":"PA",
    "sg:tags":[
        "pizza"
    ],
    "wof:name":"Bernie's Pizza",
    "wof:placetype":"venue"
},
  "geometry": {"coordinates":[-75.966961,41.337313],"type":"Point"}
}