{
  "type": "Feature",
  "properties": {
    "addr:full":"1327 Wyoming Ave Scranton PA 18509",
    "addr:housenumber":"1327",
    "addr:postcode":"18509",
    "addr:street":"Wyoming Ave",
    "iso:country":"US",
    "sg:address":"1327 Wyoming Ave",
    "sg:city":"Scranton",
    "sg:classifiers":[
        {
            "category":"Personal",
            "type":"Services"
        }
    ],
    "sg:phone":"+1 570 558 7952",
    "sg:postcode":"18509",
    "sg:province":"PA",
    "sg:tags":[
        "control",
        "weight"
    ],
    "wof:name":"Physicians Weight Loss Ctr",
    "wof:placetype":"venue"
},
  "geometry": {"coordinates":[-75.65033,41.421991],"type":"Point"}
}