{
  "type": "Feature",
  "properties": {
    "addr:full":"301 E Philadelphia St York PA 17403",
    "addr:housenumber":"301",
    "addr:postcode":"17403",
    "addr:street":"E Philadelphia St",
    "iso:country":"US",
    "sg:address":"301 E Philadelphia St",
    "sg:city":"York",
    "sg:classifiers":[
        {
            "category":"Education",
            "subcategory":"School",
            "type":"Public Place"
        }
    ],
    "sg:phone":"+1 717 849 1415",
    "sg:postcode":"17403",
    "sg:province":"PA",
    "wof:name":"York Even Start",
    "wof:placetype":"venue"
},
  "geometry": {"coordinates":[-76.720726,39.966246],"type":"Point"}
}