{
  "type": "Feature",
  "properties": {
    "addr:full":"1134 Glenn St Philadelphia PA 19115",
    "addr:housenumber":"1134",
    "addr:postcode":"19115",
    "addr:street":"Glenn St",
    "iso:country":"US",
    "sg:address":"1134 Glenn St",
    "sg:city":"Philadelphia",
    "sg:classifiers":[
        {
            "category":"Professional",
            "subcategory":"Employment Agencies",
            "type":"Services"
        }
    ],
    "sg:phone":"+1 215 783 0179",
    "sg:postcode":"19115",
    "sg:province":"PA",
    "wof:name":"Beacon Career Group",
    "wof:placetype":"venue"
},
  "geometry": {"coordinates":[-75.035831,40.101686],"type":"Point"}
}