{
  "type": "Feature",
  "properties": {
    "iso:country":"US",
    "sg:address":"2115 Stefko Blvd",
    "sg:city":"Bethlehem",
    "sg:classifiers":[
        {
            "category":"Personal",
            "subcategory":"Beauty Salon",
            "type":"Services"
        }
    ],
    "sg:phone":"+1 610 419 6121",
    "sg:postcode":"18017",
    "sg:province":"PA",
    "sg:tags":[
        "shop"
    ],
    "wof:name":"Branches Of True Beauty",
    "wof:placetype":"venue"
},
  "geometry": {"coordinates":[-75.346019,40.643048],"type":"Point"}
}