{
  "type": "Feature",
  "properties": {
    "addr:full":"1159 National Pike Hopwood PA 15401",
    "addr:housenumber":"1159",
    "addr:postcode":"15401",
    "addr:street":"National Pike",
    "iso:country":"US",
    "sg:address":"1159 National Pike",
    "sg:city":"Hopwood",
    "sg:classifiers":[
        {
            "category":"Professional",
            "type":"Services"
        }
    ],
    "sg:phone":"+1 724 439 2333",
    "sg:postcode":"15401",
    "sg:province":"PA",
    "sg:tags":[
        "establishment"
    ],
    "wof:name":"Terre Verte Tech Inc",
    "wof:placetype":"venue"
},
  "geometry": {"coordinates":[-79.74575,39.91097],"type":"Point"}
}