{
  "type": "Feature",
  "properties": {
    "iso:country":"US",
    "sg:address":"210 W Main St",
    "sg:city":"Saxonburg",
    "sg:classifiers":[
        {
            "category":"Shopping",
            "subcategory":"Used Merchandise",
            "type":"Retail Goods"
        }
    ],
    "sg:phone":"+1 724 352 0098",
    "sg:postcode":"16056",
    "sg:province":"PA",
    "sg:tags":[
        "antique"
    ],
    "wof:name":"Antique Coffee Shoppe",
    "wof:placetype":"venue"
},
  "geometry": {"coordinates":[-79.813931,40.750633],"type":"Point"}
}