{
  "type": "Feature",
  "properties": {
    "iso:country":"US",
    "sg:address":"1600 Chestnut St",
    "sg:city":"Philadelphia",
    "sg:classifiers":[
        {
            "category":"Banks & Credit Unions",
            "subcategory":"Bank",
            "type":"Services"
        }
    ],
    "sg:phone":"+1 215 000 1111",
    "sg:postcode":"19103",
    "sg:province":"PA",
    "wof:name":"Beneficial Savings Bank",
    "wof:placetype":"venue"
},
  "geometry": {"coordinates":[-75.168767,39.951468],"type":"Point"}
}