{
  "type": "Feature",
  "properties": {
    "iso:country":"US",
    "sg:address":"475 Creek Rd",
    "sg:city":"Shelocta",
    "sg:classifiers":[
        {
            "category":"Retail",
            "subcategory":"Pet Boarding",
            "type":"Services"
        },
        {
            "category":"Retail",
            "subcategory":"Animal Services",
            "type":"Services"
        }
    ],
    "sg:phone":"+1 724 354 4745",
    "sg:postcode":"15774",
    "sg:province":"PA",
    "sg:tags":[
        "grooming",
        "kennel"
    ],
    "wof:name":"Animal House",
    "wof:placetype":"venue"
},
  "geometry": {"coordinates":[-79.283906,40.657715],"type":"Point"}
}