{
  "type": "Feature",
  "properties": {
    "iso:country":"US",
    "sg:address":"6320 Upper York Rd",
    "sg:city":"New Hope",
    "sg:classifiers":[
        {
            "category":"Wholesale",
            "subcategory":"Fruits & Vegetables",
            "type":"Manufacturing & Wholesale Goods"
        }
    ],
    "sg:phone":"+1 215 869 0076",
    "sg:postcode":"18938",
    "sg:province":"PA",
    "sg:tags":[
        "veggie"
    ],
    "sg:website":"www.tuckamony.com",
    "wof:name":"Tuckamony Farm",
    "wof:placetype":"venue"
},
  "geometry": {"coordinates":[-75.017422,40.371544],"type":"Point"}
}