{
  "type": "Feature",
  "properties": {
    "addr:full":"165 Valley Dr Churchville PA 18966",
    "addr:housenumber":"165",
    "addr:postcode":"18966",
    "addr:street":"Valley Dr",
    "iso:country":"US",
    "sg:address":"165 Valley Dr",
    "sg:city":"Churchville",
    "sg:classifiers":[
        {
            "category":"Health Services",
            "subcategory":"Health Practitioner",
            "type":"Services"
        }
    ],
    "sg:phone":"+1 215 396 1974",
    "sg:postcode":"18966",
    "sg:province":"PA",
    "sg:tags":[
        "acupuncture"
    ],
    "wof:name":"Bucks County Acupuncture",
    "wof:placetype":"venue"
},
  "geometry": {"coordinates":[-75.016481,40.186437],"type":"Point"}
}