{
  "type": "Feature",
  "properties": {
    "iso:country":"US",
    "sg:address":"204 S West St",
    "sg:city":"Williamstown",
    "sg:classifiers":[
        {
            "category":"Local Transit",
            "type":"Transportation"
        }
    ],
    "sg:phone":"+1 717 647 4513",
    "sg:postcode":"17098",
    "sg:province":"PA",
    "sg:tags":[
        "ambulance"
    ],
    "wof:name":"Williamstown Area EMS Inc",
    "wof:placetype":"venue"
},
  "geometry": {"coordinates":[-76.619128,40.579328],"type":"Point"}
}