{
  "type": "Feature",
  "properties": {
    "iso:country":"US",
    "sg:address":"42 Lee Ave",
    "sg:city":"Pittsburgh",
    "sg:classifiers":[
        {
            "category":"Building & Trades",
            "subcategory":"Construction",
            "type":"Services"
        }
    ],
    "sg:phone":"+1   ",
    "sg:postcode":"15221",
    "sg:province":"PA",
    "sg:tags":[
        "house"
    ],
    "wof:name":"Les Potter Construction",
    "wof:placetype":"venue"
},
  "geometry": {"coordinates":[-79.851595,40.416682],"type":"Point"}
}