{
  "type": "Feature",
  "properties": {
    "addr:full":"865 Village Ln Bensalem PA 19020",
    "addr:housenumber":"865",
    "addr:postcode":"19020",
    "addr:street":"Village Ln",
    "iso:country":"US",
    "sg:address":"865 Village Ln",
    "sg:city":"Bensalem",
    "sg:classifiers":[
        {
            "category":"Manufacturing",
            "subcategory":"Tools & Machinery",
            "type":"Manufacturing & Wholesale Goods"
        }
    ],
    "sg:phone":"+1   ",
    "sg:postcode":"19020",
    "sg:province":"PA",
    "sg:tags":[
        "consulting",
        "computer",
        "mfg"
    ],
    "wof:name":"Strategic Business Development",
    "wof:placetype":"venue"
},
  "geometry": {"coordinates":[-74.969222,40.06092],"type":"Point"}
}