{
  "type": "Feature",
  "properties": {
    "iso:country":"US",
    "sg:address":"2614 New Butler Rd",
    "sg:city":"New Castle",
    "sg:classifiers":[
        {
            "category":"Retail",
            "subcategory":"Auto Repair",
            "type":"Services"
        }
    ],
    "sg:phone":"+1 724 658 0998",
    "sg:postcode":"16101",
    "sg:province":"PA",
    "sg:tags":[
        "automobile",
        "starter",
        "electric",
        "generator"
    ],
    "wof:name":"George's Automotive Electric",
    "wof:placetype":"venue"
},
  "geometry": {"coordinates":[-80.29259500000001,40.97677],"type":"Point"}
}