{
  "type": "Feature",
  "properties": {
    "addr:full":"70 Dew Drop Rd York PA 17403",
    "addr:housenumber":"70",
    "addr:postcode":"17403",
    "addr:street":"Dew Drop Rd",
    "iso:country":"US",
    "sg:address":"70 Dew Drop Rd",
    "sg:city":"York",
    "sg:classifiers":[
        {
            "category":"Manufacturing",
            "subcategory":"Buildings",
            "type":"Manufacturing & Wholesale Goods"
        }
    ],
    "sg:phone":"+1   ",
    "sg:postcode":"17403",
    "sg:province":"PA",
    "sg:tags":[
        "prefabricated",
        "wood",
        "mfg"
    ],
    "wof:name":"Art House",
    "wof:placetype":"venue"
},
  "geometry": {"coordinates":[-76.70111900000001,39.919354],"type":"Point"}
}