{
  "type": "Feature",
  "properties": {
    "addr:full":"5097 Bernville Rd Bernville PA 19506",
    "addr:postcode":"5097;19506",
    "addr:street":"Bernville Rd",
    "iso:country":"US",
    "sg:address":"5097 Bernville Rd",
    "sg:city":"Bernville",
    "sg:classifiers":[
        {
            "category":"Autos & Motor Vehicles",
            "subcategory":"Boat Sales",
            "type":"Retail Goods"
        }
    ],
    "sg:phone":"+1 610 488 6251",
    "sg:postcode":"19506",
    "sg:province":"PA",
    "sg:tags":[
        "dealer",
        "sales"
    ],
    "wof:name":"Ric's Marine Inc",
    "wof:placetype":"venue"
},
  "geometry": {"coordinates":[-76.042739,40.404147],"type":"Point"}
}