{
  "type": "Feature",
  "properties": {
    "addr:full":"1144 Street Rd Southampton PA 18966",
    "addr:housenumber":"1144",
    "addr:postcode":"18966",
    "addr:street":"Street Rd",
    "iso:country":"US",
    "sg:address":"1144 Street Rd",
    "sg:city":"Southampton",
    "sg:classifiers":[
        {
            "category":"Personal",
            "subcategory":"Beauty Salon",
            "type":"Services"
        }
    ],
    "sg:phone":"+1 215 322 6677",
    "sg:postcode":"18966",
    "sg:province":"PA",
    "sg:tags":[
        "hair",
        "stylist"
    ],
    "wof:name":"Southampton Hair Design Inc",
    "wof:placetype":"venue"
},
  "geometry": {"coordinates":[-75.033028,40.168571],"type":"Point"}
}