{
  "type": "Feature",
  "properties": {
    "iso:country":"US",
    "sg:address":"400 W Lincoln Ave",
    "sg:city":"Lititz",
    "sg:classifiers":[
        {
            "category":"Banks & Credit Unions",
            "subcategory":"Bank",
            "type":"Services"
        }
    ],
    "sg:phone":"+1 717 627 9329",
    "sg:postcode":"17543",
    "sg:province":"PA",
    "sg:tags":[
        "federal"
    ],
    "wof:name":"Parda Federal Credit Union",
    "wof:placetype":"venue"
},
  "geometry": {"coordinates":[-76.318551,40.166433],"type":"Point"}
}