{
  "type": "Feature",
  "properties": {
    "iso:country":"US",
    "sg:address":"1315 Walnut St Ste 717",
    "sg:city":"Philadelphia",
    "sg:classifiers":[
        {
            "category":"Manufacturing",
            "subcategory":"Chemicals & Compounds",
            "type":"Manufacturing & Wholesale Goods"
        },
        {
            "category":"Personal",
            "subcategory":"Beauty Salon",
            "type":"Services"
        },
        {
            "category":"Personal",
            "subcategory":"Hair Removal",
            "type":"Services"
        }
    ],
    "sg:phone":"+1 215 735 8144",
    "sg:postcode":"19107",
    "sg:province":"PA",
    "sg:tags":[
        "electrolysis"
    ],
    "sg:website":"www.savareseelectrolysis.com",
    "wof:name":"Savarese Electrolysis Salon",
    "wof:placetype":"venue"
},
  "geometry": {"coordinates":[-75.16280399999999,39.949299],"type":"Point"}
}