{
  "type": "Feature",
  "properties": {
    "iso:country":"US",
    "sg:address":"304 W Mountain Rd",
    "sg:city":"Allentown",
    "sg:classifiers":[
        {
            "category":"Wholesale",
            "subcategory":"Dairy",
            "type":"Manufacturing & Wholesale Goods"
        }
    ],
    "sg:phone":"+1 610 797 9375",
    "sg:postcode":"18103",
    "sg:province":"PA",
    "sg:tags":[
        "frozen",
        "dessert",
        "ice",
        "cream"
    ],
    "wof:name":"Charles R Berner",
    "wof:placetype":"venue"
},
  "geometry": {"coordinates":[-75.45176600000001,40.573693],"type":"Point"}
}