{
  "type": "Feature",
  "properties": {
    "addr:full":"157 Bethlehem Pike Colmar PA 18915",
    "addr:housenumber":"157",
    "addr:postcode":"18915",
    "addr:street":"Bethlehem Pike",
    "iso:country":"US",
    "sg:address":"157 Bethlehem Pike",
    "sg:city":"Colmar",
    "sg:classifiers":[
        {
            "category":"Real Estate",
            "subcategory":"Real Estate Agent",
            "type":"Services"
        }
    ],
    "sg:phone":"+1   ",
    "sg:postcode":"18915",
    "sg:province":"PA",
    "sg:tags":[
        "loan",
        "broker"
    ],
    "wof:name":"Homebuyers Advantage Realty",
    "wof:placetype":"venue"
},
  "geometry": {"coordinates":[-75.25682399999999,40.271244],"type":"Point"}
}