{
  "type": "Feature",
  "properties": {
    "addr:full":"6218 Ridge Ave Philadelphia PA 19128",
    "addr:housenumber":"6218",
    "addr:postcode":"19128",
    "addr:street":"Ridge Ave",
    "iso:country":"US",
    "sg:address":"6218 Ridge Ave",
    "sg:city":"Philadelphia",
    "sg:classifiers":[
        {
            "category":"Organizations",
            "subcategory":"Community Association",
            "type":"Services"
        }
    ],
    "sg:phone":"+1 215 483 2689",
    "sg:postcode":"19128",
    "sg:province":"PA",
    "sg:tags":[
        "fraternal"
    ],
    "wof:name":"Knights Of Columbus",
    "wof:placetype":"venue"
},
  "geometry": {"coordinates":[-75.21875799999999,40.036654],"type":"Point"}
}