{
  "type": "Feature",
  "properties": {
    "iso:country":"US",
    "sg:address":"721 W Linden St",
    "sg:city":"Allentown",
    "sg:classifiers":[
        {
            "category":"Bars & Pubs",
            "type":"Food & Drink"
        }
    ],
    "sg:phone":"+1 610 437 6666",
    "sg:postcode":"18101",
    "sg:province":"PA",
    "sg:tags":[
        "drinking"
    ],
    "wof:name":"Hondo's Bar",
    "wof:placetype":"venue"
},
  "geometry": {"coordinates":[-75.47330599999999,40.603366],"type":"Point"}
}