{
  "type": "Feature",
  "properties": {
    "iso:country":"US",
    "sg:address":"301 Oxford Valley Rd",
    "sg:city":"Morrisville",
    "sg:classifiers":[
        {
            "category":"Professional",
            "subcategory":"Accounting & Tax Preparation",
            "type":"Services"
        }
    ],
    "sg:phone":"+1   ",
    "sg:postcode":"19067",
    "sg:province":"PA",
    "wof:name":"Certified Public Accountants",
    "wof:placetype":"venue"
},
  "geometry": {"coordinates":[-74.867306,40.205362],"type":"Point"}
}