{
  "type": "Feature",
  "properties": {
    "iso:country":"US",
    "sg:address":"331 South St",
    "sg:city":"Ridgway",
    "sg:classifiers":[
        {
            "category":"Organizations",
            "subcategory":"Religious Organization",
            "type":"Services"
        }
    ],
    "sg:phone":"+1 814 773 5381",
    "sg:postcode":"15853",
    "sg:province":"PA",
    "sg:tags":[
        "church"
    ],
    "wof:name":"First Evang Lutheran Church",
    "wof:placetype":"venue"
},
  "geometry": {"coordinates":[-78.726629,41.420609],"type":"Point"}
}