{
  "type": "Feature",
  "properties": {
    "addr:full":"80 E Highland Ave Uniontown PA 15401",
    "addr:housenumber":"80",
    "addr:postcode":"15401",
    "addr:street":"E Highland Ave",
    "iso:country":"US",
    "sg:address":"80 E Highland Ave",
    "sg:city":"Uniontown",
    "sg:classifiers":[
        {
            "category":"Building & Trades",
            "subcategory":"Construction",
            "type":"Services"
        }
    ],
    "sg:phone":"+1   ",
    "sg:postcode":"15401",
    "sg:province":"PA",
    "sg:tags":[
        "house"
    ],
    "wof:name":"Edward King Home Remodeling",
    "wof:placetype":"venue"
},
  "geometry": {"coordinates":[-79.727026,39.893135],"type":"Point"}
}