{
  "type": "Feature",
  "properties": {
    "addr:full":"158 Lincoln Hwy Fairless Hills PA 19030",
    "addr:housenumber":"158",
    "addr:postcode":"19030",
    "addr:street":"Lincoln Hwy",
    "iso:country":"US",
    "sg:address":"158 Lincoln Hwy",
    "sg:city":"Fairless Hills",
    "sg:classifiers":[
        {
            "category":"Shopping",
            "subcategory":"Computers & Home Electronics",
            "type":"Retail Goods"
        }
    ],
    "sg:phone":"+1   ",
    "sg:postcode":"19030",
    "sg:province":"PA",
    "wof:name":"Advance Computer Svc Inc",
    "wof:placetype":"venue"
},
  "geometry": {"coordinates":[-74.864026,40.181638],"type":"Point"}
}