{
  "type": "Feature",
  "properties": {
    "addr:full":"1529 E Philadelphia Ave Gilbertsville PA 19525",
    "addr:housenumber":"1529 e",
    "addr:postcode":"19525",
    "addr:street":"Philadelphia Ave",
    "iso:country":"US",
    "sg:address":"1529 E Philadelphia Ave",
    "sg:city":"Gilbertsville",
    "sg:classifiers":[
        {
            "category":"Retail",
            "subcategory":"Auto Repair",
            "type":"Services"
        }
    ],
    "sg:phone":"+1 610 367 7500",
    "sg:postcode":"19525",
    "sg:province":"PA",
    "sg:tags":[
        "repairing",
        "automobile"
    ],
    "wof:name":"Bob's Tire Co",
    "wof:placetype":"venue"
},
  "geometry": {"coordinates":[-75.604558,40.315761],"type":"Point"}
}