{
  "type": "Feature",
  "properties": {
    "addr:full":"618 Tyler Ave Clearfield PA 16830",
    "addr:housenumber":"618",
    "addr:postcode":"16830",
    "addr:street":"Tyler Ave",
    "iso:country":"US",
    "sg:address":"618 Tyler Ave",
    "sg:city":"Clearfield",
    "sg:classifiers":[
        {
            "category":"Professional",
            "subcategory":"Accounting & Tax Preparation",
            "type":"Services"
        }
    ],
    "sg:phone":"+1 814 765 7188",
    "sg:postcode":"16830",
    "sg:province":"PA",
    "sg:tags":[
        "bookkeeping"
    ],
    "wof:name":"Robert L Mitchell Cpa",
    "wof:placetype":"venue"
},
  "geometry": {"coordinates":[-78.44877,41.028288],"type":"Point"}
}