{
  "type": "Feature",
  "properties": {
    "iso:country":"US",
    "sg:address":"4200 Neshaminy Blvd",
    "sg:city":"Bensalem",
    "sg:classifiers":[
        {
            "category":"Shopping",
            "subcategory":"Used Merchandise",
            "type":"Retail Goods"
        }
    ],
    "sg:phone":"+1 215 357 6106",
    "sg:postcode":"19020",
    "sg:province":"PA",
    "sg:tags":[
        "clothing"
    ],
    "wof:name":"Rave",
    "wof:placetype":"venue"
},
  "geometry": {"coordinates":[-74.937003,40.143874],"type":"Point"}
}