{
  "type": "Feature",
  "properties": {
    "iso:country":"US",
    "sg:address":"1551 Moore Dr",
    "sg:city":"Gilbertsville",
    "sg:classifiers":[
        {
            "category":"Professional",
            "subcategory":"Accounting & Tax Preparation",
            "type":"Services"
        }
    ],
    "sg:phone":"+1 610 367 2050",
    "sg:postcode":"19525",
    "sg:province":"PA",
    "sg:tags":[
        "accountant"
    ],
    "wof:name":"Robert A Hoffman CPA",
    "wof:placetype":"venue"
},
  "geometry": {"coordinates":[-75.605976,40.312181],"type":"Point"}
}