{
  "type": "Feature",
  "properties": {
    "iso:country":"US",
    "sg:address":"207 Maple St",
    "sg:city":"Honey Brook",
    "sg:classifiers":[
        {
            "category":"Government",
            "subcategory":"Office",
            "type":"Public Place"
        }
    ],
    "sg:phone":"+1 610 273 4589",
    "sg:postcode":"19344",
    "sg:province":"PA",
    "sg:tags":[
        "govt",
        "city"
    ],
    "wof:name":"Honey Brook Water Authority",
    "wof:placetype":"venue"
},
  "geometry": {"coordinates":[-75.900327,40.102034],"type":"Point"}
}