{
  "type": "Feature",
  "properties": {
    "iso:country":"US",
    "sg:address":"528 Pinkerton Run Rd",
    "sg:city":"Oakdale",
    "sg:classifiers":[
        {
            "category":"Professional",
            "subcategory":"Detective & Security Services",
            "type":"Services"
        }
    ],
    "sg:phone":"+1 412 788 1259",
    "sg:postcode":"15071",
    "sg:province":"PA",
    "sg:tags":[
        "information",
        "bureau"
    ],
    "wof:name":"Rei Services",
    "wof:placetype":"venue"
},
  "geometry": {"coordinates":[-80.18450900000001,40.433891],"type":"Point"}
}