{
  "type": "Feature",
  "properties": {
    "iso:country":"US",
    "sg:address":"100 Matsonford Rd",
    "sg:city":"Radnor",
    "sg:classifiers":[
        {
            "category":"Banks & Credit Unions",
            "subcategory":"Bank",
            "type":"Services"
        }
    ],
    "sg:phone":"+1 610 989 9800",
    "sg:postcode":"19087",
    "sg:province":"PA",
    "wof:name":"Sun Federal Credit Union",
    "wof:placetype":"venue"
},
  "geometry": {"coordinates":[-75.35357999999999,40.048324],"type":"Point"}
}