{
  "type": "Feature",
  "properties": {
    "addr:full":"396 US Hwy 209 Milford PA 18337",
    "addr:housenumber":"396",
    "addr:postcode":"18337",
    "addr:street":"Us Hwy 209",
    "iso:country":"US",
    "sg:address":"396 US Hwy 209",
    "sg:city":"Milford",
    "sg:classifiers":[
        {
            "category":"Health Services",
            "subcategory":"Doctor",
            "type":"Services"
        }
    ],
    "sg:phone":"+1   ",
    "sg:postcode":"18337",
    "sg:province":"PA",
    "wof:name":"Paul M Tanner DMD Ms",
    "wof:placetype":"venue"
},
  "geometry": {"coordinates":[-74.801948,41.323366],"type":"Point"}
}