{
  "type": "Feature",
  "properties": {
    "addr:full":"4713 Unruh Ave Philadelphia PA 19135",
    "addr:housenumber":"4713",
    "addr:postcode":"19135",
    "addr:street":"Unruh Ave",
    "iso:country":"US",
    "sg:address":"4713 Unruh Ave",
    "sg:city":"Philadelphia",
    "sg:classifiers":[
        {
            "category":"Restaurant",
            "type":"Food & Drink"
        }
    ],
    "sg:phone":"+1   ",
    "sg:postcode":"19135",
    "sg:province":"PA",
    "sg:tags":[
        "eating"
    ],
    "wof:name":"Do Dos Pizzeria",
    "wof:placetype":"venue"
},
  "geometry": {"coordinates":[-75.04563899999999,40.023309],"type":"Point"}
}