{
  "type": "Feature",
  "properties": {
    "iso:country":"US",
    "sg:address":"2826 Mount Carmel Ave",
    "sg:city":"Glenside",
    "sg:classifiers":[
        {
            "category":"Professional",
            "type":"Services"
        }
    ],
    "sg:phone":"+1 267 763 0432",
    "sg:postcode":"19038",
    "sg:province":"PA",
    "sg:tags":[
        "establishment"
    ],
    "wof:name":"Charles Harrison & Assoc",
    "wof:placetype":"venue"
},
  "geometry": {"coordinates":[-75.166748,40.110906],"type":"Point"}
}