{
  "type": "Feature",
  "properties": {
    "addr:full":"973 N 7th St Philadelphia PA 19123",
    "addr:housenumber":"973",
    "addr:postcode":"19123",
    "addr:street":"N 7Th St",
    "iso:country":"US",
    "sg:address":"973 N 7th St",
    "sg:city":"Philadelphia",
    "sg:classifiers":[
        {
            "category":"Shopping",
            "subcategory":"Mobile Phones",
            "type":"Retail Goods"
        }
    ],
    "sg:phone":"+1 215 625 0902",
    "sg:postcode":"19123",
    "sg:province":"PA",
    "wof:name":"Mt Tabor Cyber Village",
    "wof:placetype":"venue"
},
  "geometry": {"coordinates":[-75.148088,39.969654],"type":"Point"}
}