{
  "type": "Feature",
  "properties": {
    "iso:country":"US",
    "sg:address":"3323 Washington Rd",
    "sg:city":"Canonsburg",
    "sg:classifiers":[
        {
            "category":"Shopping",
            "subcategory":"Bicycles & Sporting Goods",
            "type":"Retail Goods"
        }
    ],
    "sg:phone":"+1 724 941 0110",
    "sg:postcode":"15317",
    "sg:province":"PA",
    "wof:name":"Golf Clubs and Repairs Inc",
    "wof:placetype":"venue"
},
  "geometry": {"coordinates":[-80.115997,40.2878],"type":"Point"}
}