{
  "type": "Feature",
  "properties": {
    "iso:country":"US",
    "sg:address":"505 Halfway Dr",
    "sg:city":"Myerstown",
    "sg:classifiers":[
        {
            "category":"Food & Beverages",
            "subcategory":"Farmers Market",
            "type":"Retail Goods"
        }
    ],
    "sg:phone":"+1 717 866 7782",
    "sg:postcode":"17067",
    "sg:province":"PA",
    "sg:tags":[
        "vegetable",
        "fruit"
    ],
    "wof:name":"Weaver's Produce",
    "wof:placetype":"venue"
},
  "geometry": {"coordinates":[-76.35857799999999,40.374913],"type":"Point"}
}