{
  "type": "Feature",
  "properties": {
    "iso:country":"US",
    "sg:address":"1102 Mount Gretna Rd",
    "sg:city":"Elizabethtown",
    "sg:classifiers":[
        {
            "category":"Professional",
            "subcategory":"Secretarial Services",
            "type":"Services"
        },
        {
            "category":"Professional",
            "subcategory":"Employment Agencies",
            "type":"Services"
        }
    ],
    "sg:phone":"+1 717 367 8528",
    "sg:postcode":"17022",
    "sg:province":"PA",
    "sg:tags":[
        "typing"
    ],
    "wof:name":"All Types",
    "wof:placetype":"venue"
},
  "geometry": {"coordinates":[-76.596898,40.173401],"type":"Point"}
}