{
  "type": "Feature",
  "properties": {
    "iso:country":"US",
    "sg:address":"902 Macdade Blvd",
    "sg:city":"Folsom",
    "sg:classifiers":[
        {
            "category":"Restaurant",
            "type":"Food & Drink"
        }
    ],
    "sg:phone":"+1 610 237 0200",
    "sg:postcode":"19033",
    "sg:province":"PA",
    "wof:name":"Italian Village Restaurant",
    "wof:placetype":"venue"
},
  "geometry": {"coordinates":[-75.321966,39.891963],"type":"Point"}
}