{
  "type": "Feature",
  "properties": {
    "iso:country":"US",
    "sg:address":"5040 E Trindle Rd",
    "sg:city":"Mechanicsburg",
    "sg:classifiers":[
        {
            "category":"Shopping",
            "subcategory":"Beauty & Cosmetics",
            "type":"Retail Goods"
        },
        {
            "category":"Personal",
            "subcategory":"Beauty Salon",
            "type":"Services"
        }
    ],
    "sg:phone":"+1 717 691 1122",
    "sg:postcode":"17050",
    "sg:province":"PA",
    "sg:tags":[
        "treatment",
        "merchandise",
        "skin"
    ],
    "wof:name":"Ange's Accents",
    "wof:placetype":"venue"
},
  "geometry": {"coordinates":[-76.970771,40.225587],"type":"Point"}
}