{
  "type": "Feature",
  "properties": {
    "iso:country":"US",
    "sg:address":"2301 N Carlisle St",
    "sg:city":"Philadelphia",
    "sg:classifiers":[
        {
            "category":"Organizations",
            "subcategory":"Religious Organization",
            "type":"Services"
        }
    ],
    "sg:phone":"+1 215 223 3955",
    "sg:postcode":"19132",
    "sg:province":"PA",
    "sg:tags":[
        "church"
    ],
    "wof:name":"New Psalmist Baptist Church",
    "wof:placetype":"venue"
},
  "geometry": {"coordinates":[-75.156436,39.989478],"type":"Point"}
}