{
  "type": "Feature",
  "properties": {
    "iso:country":"US",
    "sg:address":"134 Union St",
    "sg:city":"Wilkes Barre",
    "sg:classifiers":[
        {
            "category":"Building & Trades",
            "subcategory":"Construction",
            "type":"Services"
        }
    ],
    "sg:phone":"+1   ",
    "sg:postcode":"18705",
    "sg:province":"PA",
    "sg:tags":[
        "home",
        "remodeling"
    ],
    "wof:name":"Robert J Turner Construction",
    "wof:placetype":"venue"
},
  "geometry": {"coordinates":[-75.81994400000001,41.276945],"type":"Point"}
}