{
  "type": "Feature",
  "properties": {
    "addr:full":"538 Venard Rd Clarks Summit PA 18411",
    "addr:housenumber":"538",
    "addr:postcode":"18411",
    "addr:street":"Venard Rd",
    "iso:country":"US",
    "sg:address":"538 Venard Rd",
    "sg:city":"Clarks Summit",
    "sg:classifiers":[
        {
            "category":"Social Services",
            "type":"Services"
        }
    ],
    "sg:phone":"+1   ",
    "sg:postcode":"18411",
    "sg:province":"PA",
    "sg:tags":[
        "counseling"
    ],
    "wof:name":"Love Life Marraige & Fmly Ctr",
    "wof:placetype":"venue"
},
  "geometry": {"coordinates":[-75.684843,41.497382],"type":"Point"}
}