{
  "type": "Feature",
  "properties": {
    "iso:country":"US",
    "sg:address":"2502 W Main St",
    "sg:city":"Norristown",
    "sg:classifiers":[
        {
            "category":"Professional",
            "subcategory":"Computer Services",
            "type":"Services"
        }
    ],
    "sg:phone":"+1 610 631 0778",
    "sg:postcode":"19403",
    "sg:province":"PA",
    "sg:tags":[
        "repair"
    ],
    "wof:name":"Cablenet Services Unlimited",
    "wof:placetype":"venue"
},
  "geometry": {"coordinates":[-75.38768,40.140574],"type":"Point"}
}