{
  "type": "Feature",
  "properties": {
    "iso:country":"US",
    "sg:address":"13326 Philmont Ave",
    "sg:city":"Philadelphia",
    "sg:classifiers":[
        {
            "category":"Personal",
            "subcategory":"Beauty Salon",
            "type":"Services"
        }
    ],
    "sg:phone":"+1 215 673 9985",
    "sg:postcode":"19116",
    "sg:province":"PA",
    "wof:name":"Spa Jonbet",
    "wof:placetype":"venue"
},
  "geometry": {"coordinates":[-75.02478000000001,40.129174],"type":"Point"}
}