{
  "type": "Feature",
  "properties": {
    "iso:country":"US",
    "sg:address":"508 N St",
    "sg:city":"Doylestown",
    "sg:classifiers":[
        {
            "category":"Manufacturing",
            "subcategory":"Retail Goods",
            "type":"Manufacturing & Wholesale Goods"
        }
    ],
    "sg:phone":"+1   ",
    "sg:postcode":"18901",
    "sg:province":"PA",
    "sg:tags":[
        "product",
        "mfg"
    ],
    "wof:name":"Doylestown Car Company Inc",
    "wof:placetype":"venue"
},
  "geometry": {"coordinates":[-75.126948,40.322369],"type":"Point"}
}