{
  "type": "Feature",
  "properties": {
    "iso:country":"US",
    "sg:address":"680 Andersen Dr",
    "sg:city":"Pittsburgh",
    "sg:classifiers":[
        {
            "category":"Real Estate",
            "subcategory":"Real Estate Services",
            "type":"Services"
        }
    ],
    "sg:phone":"+1 412 921 8500",
    "sg:postcode":"15220",
    "sg:province":"PA",
    "sg:tags":[
        "management",
        "property"
    ],
    "wof:name":"Kennedy-Wilson Properties",
    "wof:placetype":"venue"
},
  "geometry": {"coordinates":[-80.06199599999999,40.421398],"type":"Point"}
}