{
  "type": "Feature",
  "properties": {
    "iso:country":"US",
    "sg:address":"33 Houk Rd",
    "sg:city":"Doylestown",
    "sg:classifiers":[
        {
            "category":"Professional",
            "type":"Services"
        }
    ],
    "sg:phone":"+1   ",
    "sg:postcode":"18901",
    "sg:province":"PA",
    "wof:name":"Stanley W Struble",
    "wof:placetype":"venue"
},
  "geometry": {"coordinates":[-75.10634400000001,40.311866],"type":"Point"}
}