{
  "type": "Feature",
  "properties": {
    "addr:full":"801 Midland Ave Midland PA 15059",
    "addr:housenumber":"801",
    "addr:postcode":"15059",
    "addr:street":"Midland Ave",
    "iso:country":"US",
    "sg:address":"801 Midland Ave",
    "sg:city":"Midland",
    "sg:classifiers":[
        {
            "category":"Professional",
            "subcategory":"Employment Agencies",
            "type":"Services"
        }
    ],
    "sg:phone":"+1 724 643 0200",
    "sg:postcode":"15059",
    "sg:province":"PA",
    "sg:tags":[
        "truck",
        "driver"
    ],
    "wof:name":"TSL LTD",
    "wof:placetype":"venue"
},
  "geometry": {"coordinates":[-80.45129799999999,40.635757],"type":"Point"}
}