{
  "type": "Feature",
  "properties": {
    "addr:full":"48 E Budd St Sharon PA 16146",
    "addr:housenumber":"48",
    "addr:postcode":"16146",
    "addr:street":"E Budd St",
    "iso:country":"US",
    "sg:address":"48 E Budd St",
    "sg:city":"Sharon",
    "sg:classifiers":[
        {
            "category":"Freight",
            "type":"Transportation"
        }
    ],
    "sg:phone":"+1 724 981 0400",
    "sg:postcode":"16146",
    "sg:province":"PA",
    "sg:tags":[
        "trucking"
    ],
    "wof:name":"RSL Trucking & Repairs",
    "wof:placetype":"venue"
},
  "geometry": {"coordinates":[-80.508937,41.225677],"type":"Point"}
}