{
  "type": "Feature",
  "properties": {
    "iso:country":"US",
    "sg:address":"83 Fitzkee Rd",
    "sg:city":"Conestoga",
    "sg:classifiers":[
        {
            "category":"Building & Trades",
            "subcategory":"Electrical",
            "type":"Services"
        }
    ],
    "sg:phone":"+1 717 871 1300",
    "sg:postcode":"17516",
    "sg:province":"PA",
    "sg:tags":[
        "electrical",
        "contractor"
    ],
    "wof:name":"Jason R Brown Electric",
    "wof:placetype":"venue"
},
  "geometry": {"coordinates":[-76.34566,39.903012],"type":"Point"}
}