{
  "type": "Feature",
  "properties": {
    "addr:full":"532 Clever Rd Mc Kees Rocks PA 15136",
    "addr:housenumber":"532",
    "addr:postcode":"15136",
    "addr:street":"Clever Rd;Kees Rocks",
    "iso:country":"US",
    "sg:address":"532 Clever Rd",
    "sg:city":"Mc Kees Rocks",
    "sg:classifiers":[
        {
            "category":"Sports & Exercise",
            "subcategory":"Gym",
            "type":"Entertainment"
        }
    ],
    "sg:phone":"+1 412 788 2727",
    "sg:postcode":"15136",
    "sg:province":"PA",
    "sg:tags":[
        "club",
        "health",
        "studio",
        "gymnasium"
    ],
    "wof:name":"Results",
    "wof:placetype":"venue"
},
  "geometry": {"coordinates":[-80.135469,40.466054],"type":"Point"}
}