{
  "type": "Feature",
  "properties": {
    "iso:country":"US",
    "sg:address":"18 N High St",
    "sg:city":"West Chester",
    "sg:classifiers":[
        {
            "category":"Utilities",
            "subcategory":"Mobile Phone",
            "type":"Services"
        }
    ],
    "sg:phone":"+1 610 719 1590",
    "sg:postcode":"19380",
    "sg:province":"PA",
    "sg:tags":[
        "communication",
        "radiotelephone"
    ],
    "wof:name":"Nu Wave Paging & Cell",
    "wof:placetype":"venue"
},
  "geometry": {"coordinates":[-75.60563999999999,39.960841],"type":"Point"}
}