{
  "type": "Feature",
  "properties": {
    "addr:full":"6709 Castor Ave Philadelphia PA 19149",
    "addr:housenumber":"6709",
    "addr:postcode":"19149",
    "addr:street":"Castor Ave",
    "iso:country":"US",
    "sg:address":"6709 Castor Ave",
    "sg:city":"Philadelphia",
    "sg:classifiers":[
        {
            "category":"Personal",
            "subcategory":"Beauty Salon",
            "type":"Services"
        }
    ],
    "sg:phone":"+1 215 742 5284",
    "sg:postcode":"19149",
    "sg:province":"PA",
    "sg:tags":[
        "shop"
    ],
    "wof:name":"Le Salon",
    "wof:placetype":"venue"
},
  "geometry": {"coordinates":[-75.07326399999999,40.043648],"type":"Point"}
}