{
  "type": "Feature",
  "properties": {
    "addr:full":"1635 N 7th St Harrisburg PA 17102",
    "addr:housenumber":"1635",
    "addr:postcode":"17102",
    "addr:street":"N 7Th St",
    "iso:country":"US",
    "sg:address":"1635 N 7th St",
    "sg:city":"Harrisburg",
    "sg:classifiers":[
        {
            "category":"Home & Garden",
            "subcategory":"Furniture",
            "type":"Retail Goods"
        }
    ],
    "sg:phone":"+1 717 234 2287",
    "sg:postcode":"17102",
    "sg:province":"PA",
    "wof:name":"American Furniture Co",
    "wof:placetype":"venue"
},
  "geometry": {"coordinates":[-76.885563,40.275358],"type":"Point"}
}