{
  "type": "Feature",
  "properties": {
    "iso:country":"US",
    "sg:address":"3590 Anchor Rd",
    "sg:city":"Washington Boro",
    "sg:classifiers":[
        {
            "category":"Farming",
            "subcategory":"Farm",
            "type":"Manufacturing & Wholesale Goods"
        }
    ],
    "sg:phone":"+1   ",
    "sg:postcode":"17582",
    "sg:province":"PA",
    "sg:tags":[
        "crop",
        "general"
    ],
    "wof:name":"James B Murry",
    "wof:placetype":"venue"
},
  "geometry": {"coordinates":[-76.4401,39.977613],"type":"Point"}
}