{
  "type": "Feature",
  "properties": {
    "iso:country":"US",
    "sg:address":"3624 Market St Ste 1SD",
    "sg:city":"Philadelphia",
    "sg:classifiers":[
        {
            "category":"Professional",
            "subcategory":"Management & Consulting",
            "type":"Services"
        }
    ],
    "sg:phone":"+1 215 222 2246",
    "sg:postcode":"19104",
    "sg:province":"PA",
    "sg:tags":[
        "personnel",
        "consultant"
    ],
    "sg:website":"http://www.uniqueadvantage.com",
    "wof:name":"Unique Advantage",
    "wof:placetype":"venue"
},
  "geometry": {"coordinates":[-75.19460599999999,39.956245],"type":"Point"}
}