{
  "type": "Feature",
  "properties": {
    "addr:full":"912 S 21st St Harrisburg PA 17104",
    "addr:housenumber":"912",
    "addr:postcode":"17104",
    "addr:street":"S 21St St",
    "iso:country":"US",
    "sg:address":"912 S 21st St",
    "sg:city":"Harrisburg",
    "sg:classifiers":[
        {
            "category":"Organizations",
            "subcategory":"Religious Organization",
            "type":"Services"
        }
    ],
    "sg:phone":"+1 717 232 4341",
    "sg:postcode":"17104",
    "sg:province":"PA",
    "sg:tags":[
        "church"
    ],
    "wof:name":"Epworth United Methodist Chr",
    "wof:placetype":"venue"
},
  "geometry": {"coordinates":[-76.85288799999999,40.260754],"type":"Point"}
}