{
  "type": "Feature",
  "properties": {
    "iso:country":"US",
    "sg:address":"302 Jefferson Ave",
    "sg:city":"Falls Creek",
    "sg:classifiers":[
        {
            "category":"Home & Garden",
            "subcategory":"Building Materials",
            "type":"Retail Goods"
        }
    ],
    "sg:phone":"+1   ",
    "sg:postcode":"15840",
    "sg:province":"PA",
    "sg:tags":[
        "lumber"
    ],
    "wof:name":"84 Lumber",
    "wof:placetype":"venue"
},
  "geometry": {"coordinates":[-78.79095,41.143718],"type":"Point"}
}