{
  "type": "Feature",
  "properties": {
    "iso:country":"US",
    "sg:address":"501 Gale Rd",
    "sg:city":"Camp Hill",
    "sg:classifiers":[
        {
            "category":"Food & Beverages",
            "subcategory":"Groceries & Convenience Stores",
            "type":"Retail Goods"
        }
    ],
    "sg:phone":"+1   ",
    "sg:postcode":"17011",
    "sg:province":"PA",
    "wof:name":"Market Mate",
    "wof:placetype":"venue"
},
  "geometry": {"coordinates":[-76.94694200000001,40.246631],"type":"Point"}
}