{
  "type": "Feature",
  "properties": {
    "addr:full":"1969 Henderson Ave Washington PA 15301",
    "addr:housenumber":"1969",
    "addr:postcode":"15301",
    "addr:street":"Henderson Ave",
    "iso:country":"US",
    "sg:address":"1969 Henderson Ave",
    "sg:city":"Washington",
    "sg:classifiers":[
        {
            "category":"Travel",
            "subcategory":"Campground",
            "type":"Entertainment"
        }
    ],
    "sg:phone":"+1 724 222 9830",
    "sg:postcode":"15301",
    "sg:province":"PA",
    "wof:name":"Whispering Pines Family",
    "wof:placetype":"venue"
},
  "geometry": {"coordinates":[-80.297827,40.23653],"type":"Point"}
}