{
  "type": "Feature",
  "properties": {
    "addr:full":"234 Strawberry Sq Harrisburg PA 17101",
    "addr:housenumber":"234",
    "addr:postcode":"17101",
    "addr:street":"Strawberry Sq",
    "iso:country":"US",
    "sg:address":"234 Strawberry Sq",
    "sg:city":"Harrisburg",
    "sg:classifiers":[
        {
            "category":"Education",
            "subcategory":"University",
            "type":"Public Place"
        }
    ],
    "sg:phone":"+1 717 232 6400",
    "sg:postcode":"17101",
    "sg:province":"PA",
    "sg:tags":[
        "college"
    ],
    "wof:name":"Temple University",
    "wof:placetype":"venue"
},
  "geometry": {"coordinates":[-76.881798,40.2607],"type":"Point"}
}