{
  "type": "Feature",
  "properties": {
    "iso:country":"US",
    "sg:address":"4175 Washington Rd",
    "sg:city":"Canonsburg",
    "sg:classifiers":[
        {
            "category":"Restaurant",
            "type":"Food & Drink"
        }
    ],
    "sg:phone":"+1   ",
    "sg:postcode":"15317",
    "sg:province":"PA",
    "sg:tags":[
        "eating"
    ],
    "wof:name":"Heavenly Ham",
    "wof:placetype":"venue"
},
  "geometry": {"coordinates":[-80.13334,40.262781],"type":"Point"}
}