{
  "type": "Feature",
  "properties": {
    "addr:full":"660 Boas St Harrisburg PA 17102",
    "addr:housenumber":"660",
    "addr:postcode":"17102",
    "addr:street":"Boas St",
    "iso:country":"US",
    "sg:address":"660 Boas St",
    "sg:city":"Harrisburg",
    "sg:classifiers":[
        {
            "category":"Manufacturing",
            "subcategory":"Printing",
            "type":"Manufacturing & Wholesale Goods"
        }
    ],
    "sg:phone":"+1   ",
    "sg:postcode":"17102",
    "sg:province":"PA",
    "sg:tags":[
        "lithographic",
        "commercial"
    ],
    "wof:name":"Action Printing",
    "wof:placetype":"venue"
},
  "geometry": {"coordinates":[-76.884293,40.268763],"type":"Point"}
}