{
  "type": "Feature",
  "properties": {
    "iso:country":"US",
    "sg:address":"100 Berlin Mnr",
    "sg:city":"Berlin",
    "sg:classifiers":[
        {
            "category":"Real Estate",
            "subcategory":"Real Estate Operator",
            "type":"Services"
        }
    ],
    "sg:phone":"+1 814 267 3644",
    "sg:postcode":"15530",
    "sg:province":"PA",
    "sg:tags":[
        "apartment"
    ],
    "wof:name":"Berlin Manor",
    "wof:placetype":"venue"
},
  "geometry": {"coordinates":[-78.954183,39.918001],"type":"Point"}
}