{
  "type": "Feature",
  "properties": {
    "iso:country":"US",
    "sg:address":"110 W Arch St",
    "sg:city":"Fleetwood",
    "sg:classifiers":[
        {
            "category":"Education",
            "subcategory":"Library",
            "type":"Public Place"
        }
    ],
    "sg:phone":"+1 610 944 0146",
    "sg:postcode":"19522",
    "sg:province":"PA",
    "wof:name":"Fleetwood Area Public Library",
    "wof:placetype":"venue"
},
  "geometry": {"coordinates":[-75.820573,40.455592],"type":"Point"}
}