{
  "type": "Feature",
  "properties": {
    "addr:full":"6004 Market St Philadelphia PA 19139",
    "addr:housenumber":"6004",
    "addr:postcode":"19139",
    "addr:street":"Market St",
    "iso:country":"US",
    "sg:address":"6004 Market St",
    "sg:city":"Philadelphia",
    "sg:classifiers":[
        {
            "category":"Bars & Pubs",
            "type":"Food & Drink"
        }
    ],
    "sg:phone":"+1   ",
    "sg:postcode":"19139",
    "sg:province":"PA",
    "sg:tags":[
        "drinking"
    ],
    "wof:name":"Edmundson Inc",
    "wof:placetype":"venue"
},
  "geometry": {"coordinates":[-75.24135099999999,39.961954],"type":"Point"}
}