{
  "type": "Feature",
  "properties": {
    "addr:full":"6022 Penn Ave Pittsburgh PA 15206",
    "addr:housenumber":"6022",
    "addr:postcode":"15206",
    "addr:street":"Penn Ave",
    "iso:country":"US",
    "sg:address":"6022 Penn Ave",
    "sg:city":"Pittsburgh",
    "sg:classifiers":[
        {
            "category":"Shopping",
            "subcategory":"Clothing, Apparel, & Fashions",
            "type":"Retail Goods"
        }
    ],
    "sg:phone":"+1   ",
    "sg:postcode":"15206",
    "sg:province":"PA",
    "sg:tags":[
        "retailer"
    ],
    "wof:name":"Mo-Gear",
    "wof:placetype":"venue"
},
  "geometry": {"coordinates":[-79.92407300000001,40.461077],"type":"Point"}
}