{
  "type": "Feature",
  "properties": {
    "iso:country":"US",
    "sg:address":"500 Pine Hollow Rd",
    "sg:city":"Mc Kees Rocks",
    "sg:classifiers":[
        {
            "category":"Health Services",
            "subcategory":"Health Practitioner",
            "type":"Services"
        }
    ],
    "sg:phone":"+1 412 771 1055",
    "sg:postcode":"15136",
    "sg:province":"PA",
    "sg:tags":[
        "therapist",
        "therapy",
        "physical"
    ],
    "wof:name":"Hess Physical Therapy Llc",
    "wof:placetype":"venue"
},
  "geometry": {"coordinates":[-80.076508,40.469982],"type":"Point"}
}