{
  "type": "Feature",
  "properties": {
    "addr:full":"350 Main St Felton PA 17322",
    "addr:housenumber":"350",
    "addr:postcode":"17322",
    "addr:street":"Main St",
    "iso:country":"US",
    "sg:address":"350 Main St",
    "sg:city":"Felton",
    "sg:classifiers":[
        {
            "category":"Autos & Motor Vehicles",
            "subcategory":"Automobile Sales",
            "type":"Retail Goods"
        }
    ],
    "sg:phone":"+1 717 244 0669",
    "sg:postcode":"17322",
    "sg:province":"PA",
    "sg:tags":[
        "used"
    ],
    "wof:name":"Octagon Auto Sales",
    "wof:placetype":"venue"
},
  "geometry": {"coordinates":[-76.55313700000001,39.859482],"type":"Point"}
}