{
  "type": "Feature",
  "properties": {
    "iso:country":"US",
    "sg:address":"721 Knight Rd",
    "sg:city":"Blue Bell",
    "sg:classifiers":[
        {
            "category":"Building & Trades",
            "subcategory":"Construction",
            "type":"Services"
        }
    ],
    "sg:phone":"+1   ",
    "sg:postcode":"19422",
    "sg:province":"PA",
    "sg:tags":[
        "carpentry",
        "contractor"
    ],
    "wof:name":"Ellis Company Inc",
    "wof:placetype":"venue"
},
  "geometry": {"coordinates":[-75.23392,40.167708],"type":"Point"}
}