{
  "type": "Feature",
  "properties": {
    "addr:full":"22 N 9th St Darby PA 19023",
    "addr:housenumber":"22",
    "addr:postcode":"19023",
    "addr:street":"N 9Th St",
    "iso:country":"US",
    "sg:address":"22 N 9th St",
    "sg:city":"Darby",
    "sg:classifiers":[
        {
            "category":"Social Services",
            "type":"Services"
        }
    ],
    "sg:phone":"+1 610 583 3720",
    "sg:postcode":"19023",
    "sg:province":"PA",
    "sg:tags":[
        "organization",
        "welfare"
    ],
    "wof:name":"Salvation Army",
    "wof:placetype":"venue"
},
  "geometry": {"coordinates":[-75.26266099999999,39.918312],"type":"Point"}
}