{
  "type": "Feature",
  "properties": {
    "iso:country":"US",
    "sg:address":"444 Arona Rd",
    "sg:city":"New Stanton",
    "sg:classifiers":[
        {
            "category":"Banks & Credit Unions",
            "subcategory":"Bank",
            "type":"Services"
        }
    ],
    "sg:phone":"+1 724 925 9505",
    "sg:postcode":"15672",
    "sg:province":"PA",
    "sg:website":"www.stanwoodareafcu.org",
    "wof:name":"Stanwood Area Federal CU",
    "wof:placetype":"venue"
},
  "geometry": {"coordinates":[-79.618769,40.234047],"type":"Point"}
}