{
  "type": "Feature",
  "properties": {
    "addr:full":"43 N 6th St Stroudsburg PA 18360",
    "addr:housenumber":"43",
    "addr:postcode":"18360",
    "addr:street":"N 6Th St",
    "iso:country":"US",
    "sg:address":"43 N 6th St",
    "sg:city":"Stroudsburg",
    "sg:classifiers":[
        {
            "category":"Banks & Credit Unions",
            "subcategory":"Bank",
            "type":"Services"
        }
    ],
    "sg:phone":"+1 570 476 5016",
    "sg:postcode":"18360",
    "sg:province":"PA",
    "wof:name":"Pnc Bank",
    "wof:placetype":"venue"
},
  "geometry": {"coordinates":[-75.19328400000001,40.985841],"type":"Point"}
}