{
  "type": "Feature",
  "properties": {
    "iso:country":"US",
    "sg:address":"6 S Washington St",
    "sg:city":"Frenchtown",
    "sg:classifiers":[
        {
            "category":"Retail",
            "subcategory":"Auto Repair",
            "type":"Services"
        }
    ],
    "sg:phone":"+1   ",
    "sg:postcode":"08825",
    "sg:province":"PA",
    "sg:tags":[
        "general"
    ],
    "wof:name":"Exoticars U S A",
    "wof:placetype":"venue"
},
  "geometry": {"coordinates":[-75.062563,40.520245],"type":"Point"}
}