{
  "type": "Feature",
  "properties": {
    "iso:country":"US",
    "sg:address":"1009 Rhoades Ave",
    "sg:city":"Clifton Heights",
    "sg:classifiers":[
        {
            "category":"Health Services",
            "subcategory":"Nursing And Care Facility",
            "type":"Services"
        }
    ],
    "sg:phone":"+1 610 623 3624",
    "sg:postcode":"19018",
    "sg:province":"PA",
    "sg:tags":[
        "personal",
        "home",
        "intermediate"
    ],
    "wof:name":"Haskins Personal Care Center",
    "wof:placetype":"venue"
},
  "geometry": {"coordinates":[-75.306442,39.919747],"type":"Point"}
}