{
  "type": "Feature",
  "properties": {
    "addr:full":"335 Wallace Ave Bensalem PA 19020",
    "addr:housenumber":"335",
    "addr:postcode":"19020",
    "addr:street":"Wallace Ave",
    "iso:country":"US",
    "sg:address":"335 Wallace Ave",
    "sg:city":"Bensalem",
    "sg:classifiers":[
        {
            "category":"Recreation",
            "type":"Entertainment"
        }
    ],
    "sg:phone":"+1 215 245 5627",
    "sg:postcode":"19020",
    "sg:province":"PA",
    "sg:tags":[
        "safety",
        "instruction",
        "marksmanship",
        "gun"
    ],
    "wof:name":"Penna Lethal Weapon Institute",
    "wof:placetype":"venue"
},
  "geometry": {"coordinates":[-74.946597,40.067794],"type":"Point"}
}