{
  "type": "Feature",
  "properties": {
    "addr:full":"2739 Spring Garden St Easton PA 18045",
    "addr:housenumber":"2739",
    "addr:postcode":"18045",
    "addr:street":"Spring Garden St",
    "iso:country":"US",
    "sg:address":"2739 Spring Garden St",
    "sg:city":"Easton",
    "sg:classifiers":[
        {
            "category":"Professional",
            "type":"Services"
        }
    ],
    "sg:phone":"+1   ",
    "sg:postcode":"18045",
    "sg:province":"PA",
    "wof:name":"Absolute Angelic Companion",
    "wof:placetype":"venue"
},
  "geometry": {"coordinates":[-75.26118700000001,40.687256],"type":"Point"}
}