{
  "type": "Feature",
  "properties": {
    "iso:country":"US",
    "sg:address":"3272 N 5th Street Hwy",
    "sg:city":"Reading",
    "sg:classifiers":[
        {
            "category":"Banks & Credit Unions",
            "subcategory":"Bank",
            "type":"Services"
        }
    ],
    "sg:phone":"+1 610 921 0870",
    "sg:postcode":"19605",
    "sg:province":"PA",
    "sg:tags":[
        "personal",
        "institution"
    ],
    "wof:name":"Advance America",
    "wof:placetype":"venue"
},
  "geometry": {"coordinates":[-75.927376,40.380249],"type":"Point"}
}