{
  "type": "Feature",
  "properties": {
    "addr:full":"900 1st Ave Conway PA 15027",
    "addr:housenumber":"900",
    "addr:postcode":"15027",
    "addr:street":"1St Ave",
    "iso:country":"US",
    "sg:address":"900 1st Ave",
    "sg:city":"Conway",
    "sg:classifiers":[
        {
            "category":"Restaurant",
            "type":"Food & Drink"
        }
    ],
    "sg:menulink":"http://www.allmenus.com/pa/conway/175369-arbys/menu/",
    "sg:phone":"+1 724 869 3620",
    "sg:postcode":"15027",
    "sg:province":"PA",
    "sg:tags":[
        "burger",
        "american"
    ],
    "wof:name":"Arby's",
    "wof:placetype":"venue"
},
  "geometry": {"coordinates":[-80.238522,40.65826],"type":"Point"}
}