{
  "type": "Feature",
  "properties": {
    "iso:country":"US",
    "sg:address":"435 Main St",
    "sg:city":"Moosic",
    "sg:classifiers":[
        {
            "category":"Professional",
            "subcategory":"Lawyer & Legal Services",
            "type":"Services"
        }
    ],
    "sg:phone":"+1 570 451 0600",
    "sg:postcode":"18507",
    "sg:province":"PA",
    "sg:tags":[
        "attorney"
    ],
    "wof:name":"Kobal & Frederickson",
    "wof:placetype":"venue"
},
  "geometry": {"coordinates":[-75.73418700000001,41.355747],"type":"Point"}
}