{
  "type": "Feature",
  "properties": {
    "addr:full":"4141 W Tilghman St Allentown PA 18104",
    "addr:housenumber":"4141",
    "addr:postcode":"18104",
    "addr:street":"W Tilghman St",
    "iso:country":"US",
    "sg:address":"4141 W Tilghman St",
    "sg:city":"Allentown",
    "sg:classifiers":[
        {
            "category":"Autos & Motor Vehicles",
            "subcategory":"Fuel & Gas Station",
            "type":"Retail Goods"
        }
    ],
    "sg:phone":"+1 610 398 3468",
    "sg:postcode":"18104",
    "sg:province":"PA",
    "wof:name":"Top Star",
    "wof:placetype":"venue"
},
  "geometry": {"coordinates":[-75.548162,40.59218],"type":"Point"}
}