{
  "type": "Feature",
  "properties": {
    "iso:country":"US",
    "sg:address":"1331 Moore St",
    "sg:city":"Huntingdon",
    "sg:classifiers":[
        {
            "category":"Banks & Credit Unions",
            "subcategory":"Bank",
            "type":"Services"
        }
    ],
    "sg:phone":"+1 814 643 5998",
    "sg:postcode":"16652",
    "sg:province":"PA",
    "wof:name":"Omega Bank",
    "wof:placetype":"venue"
},
  "geometry": {"coordinates":[-78.01604399999999,40.494715],"type":"Point"}
}