{
  "type": "Feature",
  "properties": {
    "addr:full":"1015 American St Catasauqua PA 18032",
    "addr:housenumber":"1015",
    "addr:postcode":"18032",
    "addr:street":"American St",
    "iso:country":"US",
    "sg:address":"1015 American St",
    "sg:city":"Catasauqua",
    "sg:classifiers":[
        {
            "category":"Building & Trades",
            "subcategory":"Electrical",
            "type":"Services"
        }
    ],
    "sg:phone":"+1   ",
    "sg:postcode":"18032",
    "sg:province":"PA",
    "sg:tags":[
        "electrical",
        "contractor"
    ],
    "wof:name":"Ironton Electrical",
    "wof:placetype":"venue"
},
  "geometry": {"coordinates":[-75.469785,40.660198],"type":"Point"}
}