{
  "type": "Feature",
  "properties": {
    "iso:country":"US",
    "sg:address":"1040 N Irving St",
    "sg:city":"Allentown",
    "sg:classifiers":[
        {
            "category":"Home & Garden",
            "subcategory":"Building Materials",
            "type":"Retail Goods"
        }
    ],
    "sg:phone":"+1 610 432 0468",
    "sg:postcode":"18109",
    "sg:province":"PA",
    "sg:tags":[
        "door"
    ],
    "sg:website":"www.generalsupplycompany.com",
    "wof:name":"General Supply Co",
    "wof:placetype":"venue"
},
  "geometry": {"coordinates":[-75.444271,40.626101],"type":"Point"}
}