{
  "type": "Feature",
  "properties": {
    "addr:full":"93 Nut Grove Rd Pine Grove PA 17963",
    "addr:housenumber":"93",
    "addr:postcode":"17963",
    "addr:street":"Nut Grove Rd",
    "iso:country":"US",
    "sg:address":"93 Nut Grove Rd",
    "sg:city":"Pine Grove",
    "sg:classifiers":[
        {
            "category":"Professional",
            "subcategory":"Accounting & Tax Preparation",
            "type":"Services"
        }
    ],
    "sg:phone":"+1 570 345 8321",
    "sg:postcode":"17963",
    "sg:province":"PA",
    "sg:tags":[
        "payroll"
    ],
    "wof:name":"Pay Days Plus",
    "wof:placetype":"venue"
},
  "geometry": {"coordinates":[-76.367885,40.525805],"type":"Point"}
}