{
  "type": "Feature",
  "properties": {
    "addr:full":"9 Park Ln Hegins PA 17938",
    "addr:housenumber":"9",
    "addr:postcode":"17938",
    "addr:street":"Park Ln",
    "iso:country":"US",
    "sg:address":"9 Park Ln",
    "sg:city":"Hegins",
    "sg:classifiers":[
        {
            "category":"Government",
            "subcategory":"Office",
            "type":"Public Place"
        }
    ],
    "sg:phone":"+1 570 682 3226",
    "sg:postcode":"17938",
    "sg:province":"PA",
    "wof:name":"Bob Allen",
    "wof:placetype":"venue"
},
  "geometry": {"coordinates":[-76.491815,40.650839],"type":"Point"}
}