{
  "type": "Feature",
  "properties": {
    "addr:full":"492 Jacksonville Rd Hatboro PA 19040",
    "addr:housenumber":"492",
    "addr:postcode":"19040",
    "addr:street":"Jacksonville Rd",
    "iso:country":"US",
    "sg:address":"492 Jacksonville Rd",
    "sg:city":"Hatboro",
    "sg:classifiers":[
        {
            "category":"Autos & Motor Vehicles",
            "subcategory":"Automobile Sales",
            "type":"Retail Goods"
        }
    ],
    "sg:phone":"+1 215 442 9190",
    "sg:postcode":"19040",
    "sg:province":"PA",
    "sg:tags":[
        "car",
        "used",
        "dealer"
    ],
    "wof:name":"Dylan Motor Cars",
    "wof:placetype":"venue"
},
  "geometry": {"coordinates":[-75.094932,40.184531],"type":"Point"}
}