{
  "type": "Feature",
  "properties": {
    "iso:country":"US",
    "sg:address":"43 N Church St",
    "sg:city":"Mohnton",
    "sg:classifiers":[
        {
            "category":"Health Services",
            "subcategory":"Clinic",
            "type":"Services"
        }
    ],
    "sg:phone":"+1 610 796 2614",
    "sg:postcode":"19540",
    "sg:province":"PA",
    "wof:name":"Aetna US Healthcare",
    "wof:placetype":"venue"
},
  "geometry": {"coordinates":[-75.984408,40.28576],"type":"Point"}
}