{
  "type": "Feature",
  "properties": {
    "iso:country":"US",
    "sg:address":"4010 Muirfield Dr",
    "sg:city":"Presto",
    "sg:classifiers":[
        {
            "category":"Sports & Exercise",
            "subcategory":"Golf",
            "type":"Entertainment"
        }
    ],
    "sg:phone":"+1   ",
    "sg:postcode":"15142",
    "sg:province":"PA",
    "sg:tags":[
        "course",
        "public"
    ],
    "wof:name":"CMS Nevillewood",
    "wof:placetype":"venue"
},
  "geometry": {"coordinates":[-80.12254,40.387986],"type":"Point"}
}