{
  "type": "Feature",
  "properties": {
    "addr:full":"820 5th Ave Chambersburg PA 17201",
    "addr:housenumber":"820",
    "addr:postcode":"17201",
    "addr:street":"5Th Ave",
    "iso:country":"US",
    "sg:address":"820 5th Ave",
    "sg:city":"Chambersburg",
    "sg:classifiers":[
        {
            "category":"Health Services",
            "subcategory":"Doctor",
            "type":"Services"
        }
    ],
    "sg:phone":"+1 717 263 4313",
    "sg:postcode":"17201",
    "sg:province":"PA",
    "sg:tags":[
        "physician",
        "surgeon"
    ],
    "wof:name":"Keystone Health Ctr",
    "wof:placetype":"venue"
},
  "geometry": {"coordinates":[-77.646361,39.944165],"type":"Point"}
}