{
  "type": "Feature",
  "properties": {
    "iso:country":"US",
    "sg:address":"8106 Heacock Ln",
    "sg:city":"Wyncote",
    "sg:classifiers":[
        {
            "category":"Shopping",
            "subcategory":"Catalog Store",
            "type":"Retail Goods"
        }
    ],
    "sg:phone":"+1   ",
    "sg:postcode":"19095",
    "sg:province":"PA",
    "sg:tags":[
        "mail",
        "house"
    ],
    "wof:name":"Ron Levin Dist",
    "wof:placetype":"venue"
},
  "geometry": {"coordinates":[-75.14138699999999,40.087012],"type":"Point"}
}