{
  "type": "Feature",
  "properties": {
    "addr:full":"1116 Pheasant Ln Collegeville PA 19426",
    "addr:housenumber":"1116",
    "addr:postcode":"19426",
    "addr:street":"Pheasant Ln",
    "iso:country":"US",
    "sg:address":"1116 Pheasant Ln",
    "sg:city":"Collegeville",
    "sg:classifiers":[
        {
            "category":"Professional",
            "subcategory":"Management & Consulting",
            "type":"Services"
        }
    ],
    "sg:phone":"+1   ",
    "sg:postcode":"19426",
    "sg:province":"PA",
    "sg:tags":[
        "grocery",
        "business"
    ],
    "wof:name":"Markets Edge Inc",
    "wof:placetype":"venue"
},
  "geometry": {"coordinates":[-75.404083,40.214735],"type":"Point"}
}