{
  "type": "Feature",
  "properties": {
    "addr:full":"49 Dean St Drums PA 18222",
    "addr:housenumber":"49",
    "addr:postcode":"18222",
    "addr:street":"Dean St",
    "iso:country":"US",
    "sg:address":"49 Dean St",
    "sg:city":"Drums",
    "sg:classifiers":[
        {
            "category":"Health Services",
            "subcategory":"Dentist",
            "type":"Services"
        }
    ],
    "sg:phone":"+1 570 708 0291",
    "sg:postcode":"18222",
    "sg:province":"PA",
    "wof:name":"E Scott Leonard Assoc",
    "wof:placetype":"venue"
},
  "geometry": {"coordinates":[-75.997393,41.004748],"type":"Point"}
}