{
  "type": "Feature",
  "properties": {
    "iso:country":"US",
    "sg:address":"199 Main St",
    "sg:city":"Greenville",
    "sg:classifiers":[
        {
            "category":"Shopping",
            "subcategory":"Books",
            "type":"Retail Goods"
        }
    ],
    "sg:phone":"+1 724 588 4201",
    "sg:postcode":"16125",
    "sg:province":"PA",
    "sg:tags":[
        "dealer"
    ],
    "wof:name":"News Depot",
    "wof:placetype":"venue"
},
  "geometry": {"coordinates":[-80.389045,41.405082],"type":"Point"}
}