{
  "type": "Feature",
  "properties": {
    "addr:full":"102 S Market St Carmichaels PA 15320",
    "addr:housenumber":"102",
    "addr:postcode":"15320",
    "addr:street":"S Market St",
    "iso:country":"US",
    "sg:address":"102 S Market St",
    "sg:city":"Carmichaels",
    "sg:classifiers":[
        {
            "category":"Restaurant",
            "type":"Food & Drink"
        }
    ],
    "sg:phone":"+1   ",
    "sg:postcode":"15320",
    "sg:province":"PA",
    "sg:tags":[
        "eating"
    ],
    "wof:name":"Romah",
    "wof:placetype":"venue"
},
  "geometry": {"coordinates":[-79.974009,39.895714],"type":"Point"}
}