{
  "type": "Feature",
  "properties": {
    "iso:country":"US",
    "sg:address":"1411 W Erie Ave",
    "sg:city":"Philadelphia",
    "sg:classifiers":[
        {
            "category":"Professional",
            "subcategory":"Accounting & Tax Preparation",
            "type":"Services"
        }
    ],
    "sg:phone":"+1 866 871 1040",
    "sg:postcode":"19140",
    "sg:province":"PA",
    "sg:tags":[
        "return",
        "preparation-business"
    ],
    "sg:website":"http://www.libertytax.com/",
    "wof:name":"Liberty Tax Service",
    "wof:placetype":"venue"
},
  "geometry": {"coordinates":[-75.151793,40.009325],"type":"Point"}
}