{
  "type": "Feature",
  "properties": {
    "iso:country":"US",
    "sg:address":"102 Abard Dr",
    "sg:city":"Pittsburgh",
    "sg:classifiers":[
        {
            "category":"Building & Trades",
            "subcategory":"Construction",
            "type":"Services"
        }
    ],
    "sg:phone":"+1 412 657 0497",
    "sg:postcode":"15237",
    "sg:province":"PA",
    "sg:tags":[
        "brick-fire",
        "brick-clay-common",
        "face"
    ],
    "wof:name":"Lawrence Mcgrath",
    "wof:placetype":"venue"
},
  "geometry": {"coordinates":[-79.988822,40.531818],"type":"Point"}
}