{
  "type": "Feature",
  "properties": {
    "iso:country":"US",
    "sg:address":"3200 Market St",
    "sg:city":"Camp Hill",
    "sg:classifiers":[
        {
            "category":"Shopping",
            "subcategory":"Mobile Phones",
            "type":"Retail Goods"
        }
    ],
    "sg:phone":"+1 717 608 7271",
    "sg:postcode":"17011",
    "sg:province":"PA",
    "wof:name":"Pcs One",
    "wof:placetype":"venue"
},
  "geometry": {"coordinates":[-76.934998,40.239899],"type":"Point"}
}