{
  "type": "Feature",
  "properties": {
    "iso:country":"US",
    "sg:address":"1025 Chestnut St",
    "sg:city":"Emmaus",
    "sg:classifiers":[
        {
            "category":"Retail",
            "subcategory":"Self-service Laundry",
            "type":"Services"
        }
    ],
    "sg:phone":"+1   ",
    "sg:postcode":"18049",
    "sg:province":"PA",
    "sg:tags":[
        "drycleaning",
        "plant",
        "coin"
    ],
    "wof:name":"Blue Plum The",
    "wof:placetype":"venue"
},
  "geometry": {"coordinates":[-75.50559,40.529205],"type":"Point"}
}