{
  "type": "Feature",
  "properties": {
    "iso:country":"US",
    "sg:address":"6 Chestwood Dr",
    "sg:city":"Connellsville",
    "sg:classifiers":[
        {
            "category":"Real Estate",
            "subcategory":"Real Estate Agent",
            "type":"Services"
        }
    ],
    "sg:phone":"+1 724 437 5778",
    "sg:postcode":"15425",
    "sg:province":"PA",
    "sg:tags":[
        "inspection"
    ],
    "sg:website":"www.precisionhomeinspections.com",
    "wof:name":"Precision Home Inspections Inc",
    "wof:placetype":"venue"
},
  "geometry": {"coordinates":[-79.55440400000001,40.066763],"type":"Point"}
}