{
  "type": "Feature",
  "properties": {
    "addr:full":"862 5th Ave New Kensington PA 15068",
    "addr:housenumber":"862",
    "addr:postcode":"15068",
    "addr:street":"5Th Ave",
    "iso:country":"US",
    "sg:address":"862 5th Ave",
    "sg:city":"New Kensington",
    "sg:classifiers":[
        {
            "category":"Shopping",
            "subcategory":"Used Merchandise",
            "type":"Retail Goods"
        }
    ],
    "sg:phone":"+1 724 335 0532",
    "sg:postcode":"15068",
    "sg:province":"PA",
    "sg:tags":[
        "second",
        "store",
        "hand"
    ],
    "wof:name":"Paul's Second Hand Store",
    "wof:placetype":"venue"
},
  "geometry": {"coordinates":[-79.76491799999999,40.564503],"type":"Point"}
}