{
  "type": "Feature",
  "properties": {
    "iso:country":"US",
    "sg:address":"Broad & Chestnut Sts",
    "sg:city":"Philadelphia",
    "sg:classifiers":[
        {
            "category":"Professional",
            "subcategory":"Accounting & Tax Preparation",
            "type":"Services"
        }
    ],
    "sg:phone":"+1 215 563 0276",
    "sg:postcode":"19102",
    "sg:province":"PA",
    "sg:tags":[
        "accountant"
    ],
    "wof:name":"Alloy Silverstein Shapiro Adams Mulford & Co",
    "wof:placetype":"venue"
},
  "geometry": {"coordinates":[-75.166901,39.949501],"type":"Point"}
}