{
  "type": "Feature",
  "properties": {
    "iso:country":"US",
    "sg:address":"3705 W Chester Pike",
    "sg:city":"Newtown Square",
    "sg:classifiers":[
        {
            "category":"Shopping",
            "subcategory":"Jewelry",
            "type":"Retail Goods"
        }
    ],
    "sg:phone":"+1 610 356 3170",
    "sg:postcode":"19073",
    "sg:province":"PA",
    "sg:tags":[
        "jeweler"
    ],
    "wof:name":"Mitchel D Robbins Jewelers",
    "wof:placetype":"venue"
},
  "geometry": {"coordinates":[-75.40210500000001,39.98674],"type":"Point"}
}