{
  "type": "Feature",
  "properties": {
    "iso:country":"US",
    "sg:address":"35 Bellefonte Ave",
    "sg:city":"Lock Haven",
    "sg:classifiers":[
        {
            "category":"Social Services",
            "type":"Services"
        }
    ],
    "sg:phone":"+1   ",
    "sg:postcode":"17745",
    "sg:province":"PA",
    "wof:name":"Clinton Unit",
    "wof:placetype":"venue"
},
  "geometry": {"coordinates":[-77.447766,41.137089],"type":"Point"}
}