{
  "type": "Feature",
  "properties": {
    "addr:full":"398 Otterbein Rd Stoystown PA 15563",
    "addr:housenumber":"398",
    "addr:postcode":"15563",
    "addr:street":"Otterbein Rd",
    "iso:country":"US",
    "sg:address":"398 Otterbein Rd",
    "sg:city":"Stoystown",
    "sg:classifiers":[
        {
            "category":"Mining & Drilling",
            "type":"Manufacturing & Wholesale Goods"
        }
    ],
    "sg:phone":"+1 814 798 6200",
    "sg:postcode":"15563",
    "sg:province":"PA",
    "sg:tags":[
        "company"
    ],
    "wof:name":"Hoffman Mining Inc",
    "wof:placetype":"venue"
},
  "geometry": {"coordinates":[-78.900294,40.121036],"type":"Point"}
}