{
  "type": "Feature",
  "properties": {
    "addr:full":"20 Terrell Dr Washington Crsng PA 18977",
    "addr:housenumber":"20",
    "addr:postcode":"crsng pa 18977",
    "addr:street":"Terrell Dr",
    "iso:country":"US",
    "sg:address":"20 Terrell Dr",
    "sg:city":"Washington Crsng",
    "sg:classifiers":[
        {
            "category":"Insurance",
            "subcategory":"Insurance Agent",
            "type":"Services"
        }
    ],
    "sg:phone":"+1 215 369 0580",
    "sg:postcode":"18977",
    "sg:province":"PA",
    "wof:name":"Long Term Care Insurance Store",
    "wof:placetype":"venue"
},
  "geometry": {"coordinates":[-74.879795,40.294461],"type":"Point"}
}