{
  "type": "Feature",
  "properties": {
    "iso:country":"US",
    "sg:address":"300 Pine Grove Commons",
    "sg:city":"York",
    "sg:classifiers":[
        {
            "category":"Health Services",
            "subcategory":"Doctor",
            "type":"Services"
        }
    ],
    "sg:phone":"+1 717 851 5736",
    "sg:postcode":"17403",
    "sg:province":"PA",
    "sg:tags":[
        "physician",
        "surgeon"
    ],
    "sg:website":"http://www.wellspan.org",
    "wof:name":"Wellspan Center for Aging",
    "wof:placetype":"venue"
},
  "geometry": {"coordinates":[-76.707581,39.912022],"type":"Point"}
}