{
  "type": "Feature",
  "properties": {
    "iso:country":"US",
    "sg:address":"39 Red Maple Ln",
    "sg:city":"Levittown",
    "sg:classifiers":[
        {
            "category":"Building & Trades",
            "subcategory":"Electrical",
            "type":"Services"
        }
    ],
    "sg:phone":"+1 215 949 3424",
    "sg:postcode":"19055",
    "sg:province":"PA",
    "sg:tags":[
        "electric",
        "contractor"
    ],
    "wof:name":"Richard F Clements Electric",
    "wof:placetype":"venue"
},
  "geometry": {"coordinates":[-74.845388,40.152947],"type":"Point"}
}