{
  "type": "Feature",
  "properties": {
    "iso:country":"US",
    "sg:address":"2777 Helen St",
    "sg:city":"Philadelphia",
    "sg:classifiers":[
        {
            "category":"Building & Trades",
            "subcategory":"Construction",
            "type":"Services"
        }
    ],
    "sg:phone":"+1 215 427 9050",
    "sg:postcode":"19134",
    "sg:province":"PA",
    "sg:tags":[
        "home",
        "improvement"
    ],
    "wof:name":"T-A Zavislak Home Improvement",
    "wof:placetype":"venue"
},
  "geometry": {"coordinates":[-75.12125,39.989634],"type":"Point"}
}