{
  "type": "Feature",
  "properties": {
    "addr:full":"800 Carpenters Xing Folcroft PA 19032",
    "addr:housenumber":"800",
    "addr:postcode":"19032",
    "addr:street":"Carpenters Xing",
    "iso:country":"US",
    "sg:address":"800 Carpenters Xing",
    "sg:city":"Folcroft",
    "sg:classifiers":[
        {
            "category":"Freight",
            "type":"Transportation"
        }
    ],
    "sg:phone":"+1   ",
    "sg:postcode":"19032",
    "sg:province":"PA",
    "sg:tags":[
        "record",
        "management",
        "information"
    ],
    "wof:name":"Iron Mountain Information MGT",
    "wof:placetype":"venue"
},
  "geometry": {"coordinates":[-75.27447100000001,39.890164],"type":"Point"}
}