{
  "type": "Feature",
  "properties": {
    "iso:country":"US",
    "sg:address":"524 19th St",
    "sg:city":"Allentown",
    "sg:classifiers":[
        {
            "category":"Shopping",
            "subcategory":"Optician",
            "type":"Retail Goods"
        }
    ],
    "sg:phone":"+1 610 351 4848",
    "sg:postcode":"18104",
    "sg:province":"PA",
    "sg:tags":[
        "eyewear"
    ],
    "sg:website":"www.blinkon19th.com",
    "wof:name":"Blink Optical",
    "wof:placetype":"venue"
},
  "geometry": {"coordinates":[-75.50042000000001,40.60309],"type":"Point"}
}