{
  "type": "Feature",
  "properties": {
    "addr:full":"203 Park City Center Lancaster PA 17601",
    "addr:housenumber":"203",
    "addr:postcode":"17601",
    "addr:street":"Park",
    "iso:country":"US",
    "sg:address":"203 Park City Center",
    "sg:city":"Lancaster",
    "sg:classifiers":[
        {
            "category":"Shopping",
            "subcategory":"Computers & Home Electronics",
            "type":"Retail Goods"
        }
    ],
    "sg:phone":"+1 717 299 9504",
    "sg:postcode":"17601",
    "sg:province":"PA",
    "sg:tags":[
        "game",
        "video",
        "software"
    ],
    "wof:name":"Electronics Boutique",
    "wof:placetype":"venue"
},
  "geometry": {"coordinates":[-76.340175,40.064478],"type":"Point"}
}