{
  "type": "Feature",
  "properties": {
    "iso:country":"US",
    "sg:address":"416 E 8th Ave",
    "sg:city":"Homestead",
    "sg:classifiers":[
        {
            "category":"Shopping",
            "subcategory":"Clothing, Apparel, & Fashions",
            "type":"Retail Goods"
        }
    ],
    "sg:phone":"+1   ",
    "sg:postcode":"15120",
    "sg:province":"PA",
    "sg:tags":[
        "lingerie",
        "novelty",
        "specialty",
        "shoes"
    ],
    "wof:name":"Outer Skin For Inner You",
    "wof:placetype":"venue"
},
  "geometry": {"coordinates":[-79.90658500000001,40.408728],"type":"Point"}
}