{
  "type": "Feature",
  "properties": {
    "iso:country":"US",
    "sg:address":"980 Crestwood Rd",
    "sg:city":"Mountain Top",
    "sg:classifiers":[
        {
            "category":"Manufacturing",
            "subcategory":"Metals",
            "type":"Manufacturing & Wholesale Goods"
        }
    ],
    "sg:phone":"+1 570 474 5600",
    "sg:postcode":"18707",
    "sg:province":"PA",
    "sg:tags":[
        "steel"
    ],
    "wof:name":"S K Sales Co Inc",
    "wof:placetype":"venue"
},
  "geometry": {"coordinates":[-75.884833,41.13938],"type":"Point"}
}