{
  "type": "Feature",
  "properties": {
    "iso:country":"US",
    "sg:address":"6343 Winside Dr",
    "sg:city":"Bethlehem",
    "sg:classifiers":[
        {
            "category":"Retail",
            "subcategory":"Auto Repair",
            "type":"Services"
        }
    ],
    "sg:phone":"+1 484 281 3325",
    "sg:postcode":"18017",
    "sg:province":"PA",
    "wof:name":"Dent Design Hardware Limited",
    "wof:placetype":"venue"
},
  "geometry": {"coordinates":[-75.413803,40.691968],"type":"Point"}
}