{
  "type": "Feature",
  "properties": {
    "iso:country":"US",
    "sg:address":"243 Bank Hill Rd",
    "sg:city":"Wrightsville",
    "sg:classifiers":[
        {
            "category":"Building & Trades",
            "subcategory":"Construction",
            "type":"Services"
        }
    ],
    "sg:phone":"+1 717 252 5808",
    "sg:postcode":"17368",
    "sg:province":"PA",
    "sg:tags":[
        "general",
        "contractor"
    ],
    "wof:name":"Craft Construction",
    "wof:placetype":"venue"
},
  "geometry": {"coordinates":[-76.510216,39.974897],"type":"Point"}
}