{
  "type": "Feature",
  "properties": {
    "addr:full":"603 4th St New Kensington PA 15068",
    "addr:housenumber":"603",
    "addr:postcode":"15068",
    "addr:street":"4Th St",
    "iso:country":"US",
    "sg:address":"603 4th St",
    "sg:city":"New Kensington",
    "sg:classifiers":[
        {
            "category":"Bars & Pubs",
            "type":"Food & Drink"
        }
    ],
    "sg:phone":"+1 724 339 2222",
    "sg:postcode":"15068",
    "sg:province":"PA",
    "wof:name":"Normandy Bar",
    "wof:placetype":"venue"
},
  "geometry": {"coordinates":[-79.761931,40.557032],"type":"Point"}
}