{
  "type": "Feature",
  "properties": {
    "iso:country":"US",
    "sg:address":"2929 Stewart Dr",
    "sg:city":"State College",
    "sg:classifiers":[
        {
            "category":"Autos & Motor Vehicles",
            "subcategory":"Motorcycle Sales",
            "type":"Retail Goods"
        }
    ],
    "sg:phone":"+1 814 234 9433",
    "sg:postcode":"16801",
    "sg:province":"PA",
    "sg:tags":[
        "scooter"
    ],
    "wof:name":"Extreme Custom Cycles LLC",
    "wof:placetype":"venue"
},
  "geometry": {"coordinates":[-77.79652400000001,40.830735],"type":"Point"}
}