{
  "type": "Feature",
  "properties": {
    "iso:country":"US",
    "sg:address":"325 Frederick St",
    "sg:city":"Hanover",
    "sg:classifiers":[
        {
            "category":"Professional",
            "subcategory":"Advertising",
            "type":"Services"
        }
    ],
    "sg:phone":"+1 717 632 8303",
    "sg:postcode":"17331",
    "sg:province":"PA",
    "sg:tags":[
        "agency"
    ],
    "wof:name":"Kapp Advertising Service Incorporated",
    "wof:placetype":"venue"
},
  "geometry": {"coordinates":[-76.989649,39.794954],"type":"Point"}
}