{
  "type": "Feature",
  "properties": {
    "iso:country":"US",
    "sg:address":"138 W Main St",
    "sg:city":"Somerset",
    "sg:classifiers":[
        {
            "category":"Banks & Credit Unions",
            "subcategory":"Investment Brokerage",
            "type":"Services"
        }
    ],
    "sg:phone":"+1   ",
    "sg:postcode":"15501",
    "sg:province":"PA",
    "sg:tags":[
        "security"
    ],
    "wof:name":"Edward Jones 19364",
    "wof:placetype":"venue"
},
  "geometry": {"coordinates":[-79.07872399999999,40.008363],"type":"Point"}
}