{
  "type": "Feature",
  "properties": {
    "iso:country":"US",
    "sg:address":"1743 Blacks Bridge Rd",
    "sg:city":"Annville",
    "sg:classifiers":[
        {
            "category":"Government",
            "subcategory":"Fire Station",
            "type":"Public Place"
        }
    ],
    "sg:phone":"+1   ",
    "sg:postcode":"17003",
    "sg:province":"PA",
    "sg:tags":[
        "department",
        "volunteer"
    ],
    "wof:name":"Bellegrove Fire Company",
    "wof:placetype":"venue"
},
  "geometry": {"coordinates":[-76.567779,40.374857],"type":"Point"}
}