{
  "type": "Feature",
  "properties": {
    "addr:full":"2151 Jennings St Bethlehem PA 18017",
    "addr:housenumber":"2151",
    "addr:postcode":"18017",
    "addr:street":"Jennings St",
    "iso:country":"US",
    "sg:address":"2151 Jennings St",
    "sg:city":"Bethlehem",
    "sg:classifiers":[
        {
            "category":"Building & Trades",
            "subcategory":"Construction",
            "type":"Services"
        }
    ],
    "sg:phone":"+1 610 861 9456",
    "sg:postcode":"18017",
    "sg:province":"PA",
    "sg:tags":[
        "siding",
        "contractor"
    ],
    "wof:name":"Caceres Siding",
    "wof:placetype":"venue"
},
  "geometry": {"coordinates":[-75.361439,40.642457],"type":"Point"}
}