{
  "type": "Feature",
  "properties": {
    "iso:country":"US",
    "sg:address":"468 Kerr Ln",
    "sg:city":"Springfield",
    "sg:classifiers":[
        {
            "category":"Arts & Performance",
            "subcategory":"Theater",
            "type":"Entertainment"
        }
    ],
    "sg:phone":"+1   ",
    "sg:postcode":"19064",
    "sg:province":"PA",
    "sg:tags":[
        "group"
    ],
    "wof:name":"Peppers Ghost",
    "wof:placetype":"venue"
},
  "geometry": {"coordinates":[-75.343694,39.931215],"type":"Point"}
}