{
  "type": "Feature",
  "properties": {
    "iso:country":"US",
    "sg:address":"312 2nd Ave",
    "sg:city":"Carnegie",
    "sg:classifiers":[
        {
            "category":"Health Services",
            "subcategory":"Dentist",
            "type":"Services"
        }
    ],
    "sg:phone":"+1 412 279 6767",
    "sg:postcode":"15106",
    "sg:province":"PA",
    "wof:name":"Affolter John DDS",
    "wof:placetype":"venue"
},
  "geometry": {"coordinates":[-80.089995,40.403394],"type":"Point"}
}