{
  "type": "Feature",
  "properties": {
    "iso:country":"US",
    "sg:address":"800 S Aiken Ave",
    "sg:city":"Pittsburgh",
    "sg:classifiers":[
        {
            "category":"Shopping",
            "subcategory":"Shoes",
            "type":"Retail Goods"
        }
    ],
    "sg:phone":"+1 412 621 2997",
    "sg:postcode":"15232",
    "sg:province":"PA",
    "wof:name":"Athlete's Foot",
    "wof:placetype":"venue"
},
  "geometry": {"coordinates":[-79.935503,40.450635],"type":"Point"}
}