{
  "type": "Feature",
  "properties": {
    "iso:country":"US",
    "sg:address":"2207 Fleetwing Dr",
    "sg:city":"Levittown",
    "sg:classifiers":[
        {
            "category":"Professional",
            "type":"Services"
        }
    ],
    "sg:phone":"+1   ",
    "sg:postcode":"19057",
    "sg:province":"PA",
    "wof:name":"Stacey Oliver",
    "wof:placetype":"venue"
},
  "geometry": {"coordinates":[-74.852485,40.125594],"type":"Point"}
}