{
  "type": "Feature",
  "properties": {
    "iso:country":"US",
    "sg:address":"2219 Pine St",
    "sg:city":"Philadelphia",
    "sg:classifiers":[
        {
            "category":"Real Estate",
            "subcategory":"Architect",
            "type":"Services"
        }
    ],
    "sg:phone":"+1 215 732 0364",
    "sg:postcode":"19103",
    "sg:province":"PA",
    "wof:name":"Hirshorn Paul M Architect",
    "wof:placetype":"venue"
},
  "geometry": {"coordinates":[-75.17849699999999,39.947102],"type":"Point"}
}