{
  "type": "Feature",
  "properties": {
    "iso:country":"US",
    "sg:address":"6866 Dicks Ave",
    "sg:city":"Philadelphia",
    "sg:classifiers":[
        {
            "category":"Health Services",
            "subcategory":"Doctor",
            "type":"Services"
        }
    ],
    "sg:phone":"+1 215 492 8892",
    "sg:postcode":"19142",
    "sg:province":"PA",
    "sg:tags":[
        "dentist"
    ],
    "wof:name":"Southwest Dental",
    "wof:placetype":"venue"
},
  "geometry": {"coordinates":[-75.23319100000001,39.915793],"type":"Point"}
}