{
  "type": "Feature",
  "properties": {
    "iso:country":"US",
    "sg:address":"700 E Passyunk Ave",
    "sg:city":"Philadelphia",
    "sg:classifiers":[
        {
            "category":"Personal",
            "subcategory":"Tanning Parlor",
            "type":"Services"
        }
    ],
    "sg:phone":"+1 215 238 1209",
    "sg:postcode":"19147",
    "sg:province":"PA",
    "sg:tags":[
        "salon"
    ],
    "wof:name":"Tanfasia II",
    "wof:placetype":"venue"
},
  "geometry": {"coordinates":[-75.15155799999999,39.939826],"type":"Point"}
}