{
  "type": "Feature",
  "properties": {
    "iso:country":"US",
    "sg:address":"607 Sackettsford Rd",
    "sg:city":"Warminster",
    "sg:classifiers":[
        {
            "category":"Professional",
            "subcategory":"Management & Consulting",
            "type":"Services"
        }
    ],
    "sg:phone":"+1   ",
    "sg:postcode":"18974",
    "sg:province":"PA",
    "wof:name":"Robt F Rauchut",
    "wof:placetype":"venue"
},
  "geometry": {"coordinates":[-75.021083,40.245571],"type":"Point"}
}