{
  "type": "Feature",
  "properties": {
    "addr:full":"714 West Ave Jenkintown PA 19046",
    "addr:housenumber":"714",
    "addr:postcode":"19046",
    "addr:street":"West Ave",
    "iso:country":"US",
    "sg:address":"714 West Ave",
    "sg:city":"Jenkintown",
    "sg:classifiers":[
        {
            "category":"Wholesale",
            "subcategory":"Stationery",
            "type":"Manufacturing & Wholesale Goods"
        }
    ],
    "sg:phone":"+1 215 884 3343",
    "sg:postcode":"19046",
    "sg:province":"PA",
    "sg:tags":[
        "supply"
    ],
    "wof:name":"Jenkintown Business Graphics",
    "wof:placetype":"venue"
},
  "geometry": {"coordinates":[-75.126769,40.095969],"type":"Point"}
}