{
  "type": "Feature",
  "properties": {
    "iso:country":"US",
    "sg:address":"1399 W Chestnut St",
    "sg:city":"Washington",
    "sg:classifiers":[
        {
            "category":"Restaurant",
            "type":"Food & Drink"
        }
    ],
    "sg:phone":"+1 724 222 7860",
    "sg:postcode":"15301",
    "sg:province":"PA",
    "wof:name":"Wendy's",
    "wof:placetype":"venue"
},
  "geometry": {"coordinates":[-80.27414,40.164563],"type":"Point"}
}