{
  "type": "Feature",
  "properties": {
    "iso:country":"US",
    "sg:address":"130 Hinds St",
    "sg:city":"Rochester",
    "sg:classifiers":[
        {
            "category":"Retail",
            "subcategory":"Portrait Studio",
            "type":"Services"
        },
        {
            "category":"Professional",
            "subcategory":"Art Services",
            "type":"Services"
        }
    ],
    "sg:phone":"+1 724 775 2176",
    "sg:postcode":"15074",
    "sg:province":"PA",
    "sg:tags":[
        "photographer",
        "photo"
    ],
    "sg:website":"www.graule.com",
    "wof:name":"Graule Studios",
    "wof:placetype":"venue"
},
  "geometry": {"coordinates":[-80.28270500000001,40.700601],"type":"Point"}
}