{
  "type": "Feature",
  "properties": {
    "iso:country":"US",
    "sg:address":"1411 Riverview Rd",
    "sg:city":"Dauphin",
    "sg:classifiers":[
        {
            "category":"Wholesale",
            "subcategory":"Construction Materials",
            "type":"Manufacturing & Wholesale Goods"
        }
    ],
    "sg:phone":"+1 717 921 8775",
    "sg:postcode":"17018",
    "sg:province":"PA",
    "sg:tags":[
        "timberland",
        "company",
        "timber"
    ],
    "wof:name":"Tuscarora Hardwoods Inc",
    "wof:placetype":"venue"
},
  "geometry": {"coordinates":[-76.985068,40.370514],"type":"Point"}
}