{
  "type": "Feature",
  "properties": {
    "iso:country":"US",
    "sg:address":"3310 Buffalo Rd",
    "sg:city":"Erie",
    "sg:classifiers":[
        {
            "category":"Shopping",
            "subcategory":"Hobbies, Toys, & Games",
            "type":"Retail Goods"
        }
    ],
    "sg:phone":"+1 814 899 2157",
    "sg:postcode":"16510",
    "sg:province":"PA",
    "wof:name":"Train Shop",
    "wof:placetype":"venue"
},
  "geometry": {"coordinates":[-80.014273,42.140727],"type":"Point"}
}