{
  "type": "Feature",
  "properties": {
    "iso:country":"US",
    "sg:address":"705 Ivy Ln",
    "sg:city":"Aliquippa",
    "sg:classifiers":[
        {
            "category":"Professional",
            "type":"Services"
        }
    ],
    "sg:phone":"+1   ",
    "sg:postcode":"15001",
    "sg:province":"PA",
    "wof:name":"Custom Accents",
    "wof:placetype":"venue"
},
  "geometry": {"coordinates":[-80.306901,40.626513],"type":"Point"}
}