{
  "type": "Feature",
  "properties": {
    "addr:full":"16282 Valley Rd Meadville PA 16335",
    "addr:housenumber":"16282",
    "addr:postcode":"16335",
    "addr:street":"Valley Rd",
    "iso:country":"US",
    "sg:address":"16282 Valley Rd",
    "sg:city":"Meadville",
    "sg:classifiers":[
        {
            "category":"Government",
            "subcategory":"Office",
            "type":"Public Place"
        }
    ],
    "sg:phone":"+1   ",
    "sg:postcode":"16335",
    "sg:province":"PA",
    "sg:tags":[
        "city",
        "tax",
        "collector"
    ],
    "wof:name":"Hayfield Township",
    "wof:placetype":"venue"
},
  "geometry": {"coordinates":[-80.209451,41.708842],"type":"Point"}
}