{
  "type": "Feature",
  "properties": {
    "iso:country":"US",
    "sg:address":"1621 N Cedar Crest Blvd",
    "sg:city":"Allentown",
    "sg:classifiers":[
        {
            "category":"Professional",
            "subcategory":"Accounting & Tax Preparation",
            "type":"Services"
        }
    ],
    "sg:phone":"+1 610 433 3866",
    "sg:postcode":"18104",
    "sg:province":"PA",
    "sg:tags":[
        "accountant"
    ],
    "wof:name":"Accounting & Tax Assoc Inc",
    "wof:placetype":"venue"
},
  "geometry": {"coordinates":[-75.533125,40.613207],"type":"Point"}
}