{
  "type": "Feature",
  "properties": {
    "iso:country":"US",
    "sg:address":"209 S Pittsburgh St",
    "sg:city":"Connellsville",
    "sg:classifiers":[
        {
            "category":"Professional",
            "subcategory":"Accounting & Tax Preparation",
            "type":"Services"
        }
    ],
    "sg:phone":"+1   ",
    "sg:postcode":"15425",
    "sg:province":"PA",
    "sg:tags":[
        "business"
    ],
    "wof:name":"Gismondi Michael J CPA",
    "wof:placetype":"venue"
},
  "geometry": {"coordinates":[-79.58892899999999,40.016606],"type":"Point"}
}