{
  "type": "Feature",
  "properties": {
    "iso:country":"US",
    "sg:address":"1200 Welsh Rd Ste B ",
    "sg:city":"North Wales",
    "sg:classifiers":[
        {
            "category":"Restaurant",
            "type":"Food & Drink"
        }
    ],
    "sg:menulink":"http://www.allmenus.com/pa/montgomery/288446-jims-buffet/menu/",
    "sg:phone":"+1 215 855 6768",
    "sg:postcode":"19454",
    "sg:province":"PA",
    "sg:tags":[
        "american"
    ],
    "wof:name":"Jim's Buffet",
    "wof:placetype":"venue"
},
  "geometry": {"coordinates":[-75.259209,40.227125],"type":"Point"}
}