{
  "type": "Feature",
  "properties": {
    "iso:country":"US",
    "sg:address":"1070 Milnor Rd",
    "sg:city":"Greencastle",
    "sg:classifiers":[
        {
            "category":"Home & Garden",
            "subcategory":"Garden Supply",
            "type":"Retail Goods"
        }
    ],
    "sg:phone":"+1 717 597 4224",
    "sg:postcode":"17225",
    "sg:province":"PA",
    "sg:tags":[
        "mulch"
    ],
    "wof:name":"Mulch Bin",
    "wof:placetype":"venue"
},
  "geometry": {"coordinates":[-77.75300300000001,39.757794],"type":"Point"}
}