{
  "type": "Feature",
  "properties": {
    "iso:country":"US",
    "sg:address":"3021 E Market St",
    "sg:city":"York",
    "sg:classifiers":[
        {
            "category":"Travel",
            "subcategory":"Hotels & Motels",
            "type":"Entertainment"
        }
    ],
    "sg:phone":"+1 717 755 2806",
    "sg:postcode":"17402",
    "sg:province":"PA",
    "wof:name":"Barnharts Hospitality Inn",
    "wof:placetype":"venue"
},
  "geometry": {"coordinates":[-76.665954,39.977212],"type":"Point"}
}