{
  "type": "Feature",
  "properties": {
    "addr:full":"5583 Roosevelt St Whitehall PA 18052",
    "addr:housenumber":"5583",
    "addr:postcode":"18052",
    "addr:street":"Roosevelt St",
    "iso:country":"US",
    "sg:address":"5583 Roosevelt St",
    "sg:city":"Whitehall",
    "sg:classifiers":[
        {
            "category":"Manufacturing",
            "subcategory":"Glass & Minerals",
            "type":"Manufacturing & Wholesale Goods"
        }
    ],
    "sg:phone":"+1 610 262 1535",
    "sg:postcode":"18052",
    "sg:province":"PA",
    "sg:tags":[
        "refractory"
    ],
    "sg:website":"www.lvrinc.com",
    "wof:name":"LVR Inc",
    "wof:placetype":"venue"
},
  "geometry": {"coordinates":[-75.524711,40.698535],"type":"Point"}
}