{
  "type": "Feature",
  "properties": {
    "iso:country":"US",
    "sg:address":"726 Glenwood Ave",
    "sg:city":"Johnstown",
    "sg:classifiers":[
        {
            "category":"Building & Trades",
            "subcategory":"Construction",
            "type":"Services"
        }
    ],
    "sg:phone":"+1 814 288 2380",
    "sg:postcode":"15905",
    "sg:province":"PA",
    "sg:tags":[
        "home",
        "commercial"
    ],
    "wof:name":"Burgo Construction Inc",
    "wof:placetype":"venue"
},
  "geometry": {"coordinates":[-78.916042,40.285273],"type":"Point"}
}