{
  "type": "Feature",
  "properties": {
    "addr:full":"113 Georgian Pl Somerset PA 15501",
    "addr:housenumber":"113",
    "addr:postcode":"15501",
    "addr:street":"Georgian Pl",
    "iso:country":"US",
    "sg:address":"113 Georgian Pl",
    "sg:city":"Somerset",
    "sg:classifiers":[
        {
            "category":"Home & Garden",
            "subcategory":"Home Furnishings",
            "type":"Retail Goods"
        }
    ],
    "sg:phone":"+1 814 445 3449",
    "sg:postcode":"15501",
    "sg:province":"PA",
    "sg:tags":[
        "kitchen",
        "accessory"
    ],
    "sg:website":"www.kitchencollections.com",
    "wof:name":"Kitchen Collection",
    "wof:placetype":"venue"
},
  "geometry": {"coordinates":[-79.075333,40.021277],"type":"Point"}
}