{
  "type": "Feature",
  "properties": {
    "addr:full":"1880 Frankstown Rd Johnstown PA 15902",
    "addr:housenumber":"1880",
    "addr:postcode":"15902",
    "addr:street":"Frankstown Rd",
    "iso:country":"US",
    "sg:address":"1880 Frankstown Rd",
    "sg:city":"Johnstown",
    "sg:classifiers":[
        {
            "category":"Building & Trades",
            "subcategory":"Equipment Rental",
            "type":"Services"
        }
    ],
    "sg:phone":"+1   ",
    "sg:postcode":"15902",
    "sg:province":"PA",
    "wof:name":"Rent A Tent Inc",
    "wof:placetype":"venue"
},
  "geometry": {"coordinates":[-78.83402599999999,40.329045],"type":"Point"}
}