{
  "type": "Feature",
  "properties": {
    "addr:full":"830 Tuck St Lebanon PA 17042",
    "addr:housenumber":"830",
    "addr:postcode":"17042",
    "addr:street":"Tuck St",
    "iso:country":"US",
    "sg:address":"830 Tuck St",
    "sg:city":"Lebanon",
    "sg:classifiers":[
        {
            "category":"Health Services",
            "subcategory":"Doctor",
            "type":"Services"
        }
    ],
    "sg:phone":"+1 717 228 1620",
    "sg:postcode":"17042",
    "sg:province":"PA",
    "sg:tags":[
        "clinic"
    ],
    "wof:name":"Lebanon Outpatient Surgical",
    "wof:placetype":"venue"
},
  "geometry": {"coordinates":[-76.419989,40.318688],"type":"Point"}
}