{
  "type": "Feature",
  "properties": {
    "iso:country":"US",
    "sg:address":"294 State St",
    "sg:city":"Beaver",
    "sg:classifiers":[
        {
            "category":"Autos & Motor Vehicles",
            "subcategory":"Automobile Sales",
            "type":"Retail Goods"
        }
    ],
    "sg:phone":"+1 724 728 4800",
    "sg:postcode":"15009",
    "sg:province":"PA",
    "sg:tags":[
        "new",
        "used"
    ],
    "sg:website":"www.nickcrivelli.com",
    "wof:name":"Nick Crivelli Chevrolet Inc",
    "wof:placetype":"venue"
},
  "geometry": {"coordinates":[-80.32139100000001,40.688217],"type":"Point"}
}