{
  "type": "Feature",
  "properties": {
    "iso:country":"US",
    "sg:address":"1513 Peach Tree Ln",
    "sg:city":"Hatfield",
    "sg:classifiers":[
        {
            "category":"Building & Trades",
            "subcategory":"Construction",
            "type":"Services"
        }
    ],
    "sg:phone":"+1 215 997 6283",
    "sg:postcode":"19440",
    "sg:province":"PA",
    "sg:tags":[
        "contractor"
    ],
    "wof:name":"Ward Construction Services Inc",
    "wof:placetype":"venue"
},
  "geometry": {"coordinates":[-75.278702,40.279701],"type":"Point"}
}