{
  "type": "Feature",
  "properties": {
    "iso:country":"US",
    "sg:address":"311 State Rte 18",
    "sg:city":"New Castle",
    "sg:classifiers":[
        {
            "category":"Manufacturing",
            "subcategory":"Tools & Machinery",
            "type":"Manufacturing & Wholesale Goods"
        }
    ],
    "sg:phone":"+1 724 652 8833",
    "sg:postcode":"16102",
    "sg:province":"PA",
    "wof:name":"K D Machine Inc",
    "wof:placetype":"venue"
},
  "geometry": {"coordinates":[-80.383146,40.959893],"type":"Point"}
}