{
  "type": "Feature",
  "properties": {
    "addr:full":"22 Kern Dr Perkasie PA 18944",
    "addr:housenumber":"22",
    "addr:postcode":"18944",
    "addr:street":"Kern Dr",
    "iso:country":"US",
    "sg:address":"22 Kern Dr",
    "sg:city":"Perkasie",
    "sg:classifiers":[
        {
            "category":"Professional",
            "subcategory":"Business Services",
            "type":"Services"
        }
    ],
    "sg:phone":"+1 215 249 3640",
    "sg:postcode":"18944",
    "sg:province":"PA",
    "sg:tags":[
        "interior",
        "consultant",
        "design",
        "decorator"
    ],
    "wof:name":"Interior Impressions",
    "wof:placetype":"venue"
},
  "geometry": {"coordinates":[-75.203569,40.384129],"type":"Point"}
}