{
  "type": "Feature",
  "properties": {
    "addr:full":"2049 W Oregon Ave Philadelphia PA 19145",
    "addr:housenumber":"2049",
    "addr:postcode":"19145",
    "addr:street":"W Oregon Ave",
    "iso:country":"US",
    "sg:address":"2049 W Oregon Ave",
    "sg:city":"Philadelphia",
    "sg:classifiers":[
        {
            "category":"Building & Trades",
            "subcategory":"Locksmith",
            "type":"Services"
        }
    ],
    "sg:phone":"+1 267 299 1255",
    "sg:postcode":"19145",
    "sg:province":"PA",
    "sg:tags":[
        "key"
    ],
    "wof:name":"Locksmith",
    "wof:placetype":"venue"
},
  "geometry": {"coordinates":[-75.181788,39.918354],"type":"Point"}
}