{
  "type": "Feature",
  "properties": {
    "addr:full":"543 N Wood St Middletown PA 17057",
    "addr:housenumber":"543",
    "addr:postcode":"17057",
    "addr:street":"N Wood St",
    "iso:country":"US",
    "sg:address":"543 N Wood St",
    "sg:city":"Middletown",
    "sg:classifiers":[
        {
            "category":"Building & Trades",
            "subcategory":"Plumbing",
            "type":"Services"
        }
    ],
    "sg:phone":"+1   ",
    "sg:postcode":"17057",
    "sg:province":"PA",
    "sg:tags":[
        "air",
        "heating",
        "conditioning",
        "contractor"
    ],
    "wof:name":"Packard Heating & AC",
    "wof:placetype":"venue"
},
  "geometry": {"coordinates":[-76.73711,40.199161],"type":"Point"}
}