{
  "type": "Feature",
  "properties": {
    "iso:country":"US",
    "sg:address":"2682 Lincoln Hwy E Ste A",
    "sg:city":"Ronks",
    "sg:classifiers":[
        {
            "category":"Shopping",
            "subcategory":"Hobbies, Toys, & Games",
            "type":"Retail Goods"
        },
        {
            "category":"Education",
            "subcategory":"Junior College",
            "type":"Public Place"
        }
    ],
    "sg:phone":"+1 717 687 8118",
    "sg:postcode":"17572",
    "sg:province":"PA",
    "sg:tags":[
        "house",
        "toy",
        "store",
        "accessory",
        "doll"
    ],
    "sg:website":"http://www.dolloutlet.com",
    "wof:name":"Doll Outlet",
    "wof:placetype":"venue"
},
  "geometry": {"coordinates":[-76.174841,40.018909],"type":"Point"}
}