{
  "type": "Feature",
  "properties": {
    "iso:country":"US",
    "sg:address":"500 Galleria Dr",
    "sg:city":"Johnstown",
    "sg:classifiers":[
        {
            "category":"Shopping",
            "type":"Retail Goods"
        }
    ],
    "sg:phone":"+1 814 269 2265",
    "sg:postcode":"15904",
    "sg:province":"PA",
    "sg:tags":[
        "merchandise"
    ],
    "wof:name":"Accent On Communications",
    "wof:placetype":"venue"
},
  "geometry": {"coordinates":[-78.83332299999999,40.302036],"type":"Point"}
}