{
  "type": "Feature",
  "properties": {
    "iso:country":"US",
    "sg:address":"1961 Durham Rd",
    "sg:city":"New Hope",
    "sg:classifiers":[
        {
            "category":"Shopping",
            "subcategory":"Used Merchandise",
            "type":"Retail Goods"
        }
    ],
    "sg:phone":"+1 215 794 7111",
    "sg:postcode":"18938",
    "sg:province":"PA",
    "sg:tags":[
        "antique"
    ],
    "wof:name":"Second Thoughts",
    "wof:placetype":"venue"
},
  "geometry": {"coordinates":[-75.04923599999999,40.310255],"type":"Point"}
}