{
  "type": "Feature",
  "properties": {
    "iso:country":"US",
    "sg:address":"32 E Main St",
    "sg:city":"Dallastown",
    "sg:classifiers":[
        {
            "category":"Wholesale",
            "subcategory":"Meat",
            "type":"Manufacturing & Wholesale Goods"
        }
    ],
    "sg:phone":"+1 717 244 2975",
    "sg:postcode":"17313",
    "sg:province":"PA",
    "sg:tags":[
        "packer"
    ],
    "wof:name":"Sechrist Brothers",
    "wof:placetype":"venue"
},
  "geometry": {"coordinates":[-76.64340300000001,39.900758],"type":"Point"}
}