{
  "type": "Feature",
  "properties": {
    "addr:full":"47 Lakeside Ct Devon PA 19333",
    "addr:housenumber":"47",
    "addr:postcode":"19333",
    "addr:street":"Lakeside Ct",
    "iso:country":"US",
    "sg:address":"47 Lakeside Ct",
    "sg:city":"Devon",
    "sg:classifiers":[
        {
            "category":"Building & Trades",
            "subcategory":"Landscaping Services",
            "type":"Services"
        }
    ],
    "sg:phone":"+1   ",
    "sg:postcode":"19333",
    "sg:province":"PA",
    "wof:name":"Saint Remy Group",
    "wof:placetype":"venue"
},
  "geometry": {"coordinates":[-75.432877,40.044781],"type":"Point"}
}