{
  "type": "Feature",
  "properties": {
    "iso:country":"US",
    "sg:address":"883 Big Mount Rd",
    "sg:city":"Thomasville",
    "sg:classifiers":[
        {
            "category":"Building & Trades",
            "subcategory":"Landscaping Services",
            "type":"Services"
        }
    ],
    "sg:phone":"+1 717 292 1584",
    "sg:postcode":"17364",
    "sg:province":"PA",
    "sg:tags":[
        "landscape",
        "contractor"
    ],
    "wof:name":"T & S Lawn Care Snow Plow",
    "wof:placetype":"venue"
},
  "geometry": {"coordinates":[-76.92997,39.954243],"type":"Point"}
}