{
  "type": "Feature",
  "properties": {
    "iso:country":"US",
    "sg:address":"174 W Allegheny Ave",
    "sg:city":"Philadelphia",
    "sg:classifiers":[
        {
            "category":"Organizations",
            "subcategory":"Non-profit Organization",
            "type":"Services"
        }
    ],
    "sg:phone":"+1 215 425 0599",
    "sg:postcode":"19133",
    "sg:province":"PA",
    "sg:tags":[
        "human"
    ],
    "wof:name":"Impact Service Corp",
    "wof:placetype":"venue"
},
  "geometry": {"coordinates":[-75.13237599999999,39.998851],"type":"Point"}
}