{
  "type": "Feature",
  "properties": {
    "iso:country":"US",
    "sg:address":"4050 Washington Rd",
    "sg:city":"Mc Murray",
    "sg:classifiers":[
        {
            "category":"Retail",
            "subcategory":"Repair Shop",
            "type":"Services"
        }
    ],
    "sg:phone":"+1 724 873 1400",
    "sg:postcode":"15317",
    "sg:province":"PA",
    "sg:tags":[
        "upholsterer"
    ],
    "wof:name":"Decorating South",
    "wof:placetype":"venue"
},
  "geometry": {"coordinates":[-80.128446,40.270132],"type":"Point"}
}