{
  "type": "Feature",
  "properties": {
    "iso:country":"US",
    "sg:address":"1734 Norristown Rd",
    "sg:city":"Ambler",
    "sg:classifiers":[
        {
            "category":"Shopping",
            "subcategory":"Crafts & Fabrics",
            "type":"Retail Goods"
        }
    ],
    "sg:phone":"+1 215 646 7322",
    "sg:postcode":"19002",
    "sg:province":"PA",
    "sg:tags":[
        "florist",
        "supplies-wholesale",
        "manufacturer",
        "florists'",
        "supply"
    ],
    "wof:name":"Cf Wholesale Flowers",
    "wof:placetype":"venue"
},
  "geometry": {"coordinates":[-75.19143699999999,40.178562],"type":"Point"}
}