{
  "type": "Feature",
  "properties": {
    "addr:full":"120 Stump Rd Danville PA 17821",
    "addr:housenumber":"120",
    "addr:postcode":"17821",
    "addr:street":"Stump Rd",
    "iso:country":"US",
    "sg:address":"120 Stump Rd",
    "sg:city":"Danville",
    "sg:classifiers":[
        {
            "category":"Real Estate",
            "subcategory":"Surveying",
            "type":"Services"
        }
    ],
    "sg:phone":"+1 570 275 8524",
    "sg:postcode":"17821",
    "sg:province":"PA",
    "sg:tags":[
        "surveyor"
    ],
    "wof:name":"Wayne Hildebrand",
    "wof:placetype":"venue"
},
  "geometry": {"coordinates":[-76.707555,40.988111],"type":"Point"}
}