{
  "type": "Feature",
  "properties": {
    "iso:country":"US",
    "sg:address":"1083 Finchley Rd",
    "sg:city":"Irwin",
    "sg:classifiers":[
        {
            "category":"Building & Trades",
            "subcategory":"Construction",
            "type":"Services"
        }
    ],
    "sg:phone":"+1 724 863 7243",
    "sg:postcode":"15642",
    "sg:province":"PA",
    "sg:tags":[
        "plastering",
        "contractor"
    ],
    "wof:name":"Tri State Finishing",
    "wof:placetype":"venue"
},
  "geometry": {"coordinates":[-79.74878699999999,40.331569],"type":"Point"}
}