{
  "type": "Feature",
  "properties": {
    "iso:country":"US",
    "sg:address":"1838 Harrisburg Pike",
    "sg:city":"Carlisle",
    "sg:classifiers":[
        {
            "category":"Home & Garden",
            "subcategory":"Building Materials",
            "type":"Retail Goods"
        }
    ],
    "sg:phone":"+1 717 245 2486",
    "sg:postcode":"17013",
    "sg:province":"PA",
    "sg:tags":[
        "supply"
    ],
    "wof:name":"Carter Plumbing Electric & Heating",
    "wof:placetype":"venue"
},
  "geometry": {"coordinates":[-77.121201,40.233898],"type":"Point"}
}