{
  "type": "Feature",
  "properties": {
    "iso:country":"US",
    "sg:address":"7840 Buffalo Rd",
    "sg:city":"Harborcreek",
    "sg:classifiers":[
        {
            "category":"Farming",
            "subcategory":"Vineyard",
            "type":"Manufacturing & Wholesale Goods"
        }
    ],
    "sg:phone":"+1   ",
    "sg:postcode":"16421",
    "sg:province":"PA",
    "sg:tags":[
        "farm",
        "grape"
    ],
    "wof:name":"Finnell Farms",
    "wof:placetype":"venue"
},
  "geometry": {"coordinates":[-79.932551,42.17827],"type":"Point"}
}