{
  "type": "Feature",
  "properties": {
    "iso:country":"US",
    "sg:address":"150 Mundy St",
    "sg:city":"Wilkes Barre",
    "sg:classifiers":[
        {
            "category":"Health Services",
            "subcategory":"Doctor",
            "type":"Services"
        }
    ],
    "sg:phone":"+1 570 824 7117",
    "sg:postcode":"18702",
    "sg:province":"PA",
    "sg:tags":[
        "physician",
        "surgeon",
        "medical"
    ],
    "wof:name":"Arthritis Center The",
    "wof:placetype":"venue"
},
  "geometry": {"coordinates":[-75.85469399999999,41.244507],"type":"Point"}
}