{
  "type": "Feature",
  "properties": {
    "iso:country":"US",
    "sg:address":"1150 Crestwood Rd",
    "sg:city":"Mountain Top",
    "sg:classifiers":[
        {
            "category":"Wholesale",
            "subcategory":"Stationery",
            "type":"Manufacturing & Wholesale Goods"
        }
    ],
    "sg:phone":"+1 570 474 0969",
    "sg:postcode":"18707",
    "sg:province":"PA",
    "sg:tags":[
        "packaging",
        "material"
    ],
    "wof:name":"AEP Industries Inc",
    "wof:placetype":"venue"
},
  "geometry": {"coordinates":[-75.890727,41.141028],"type":"Point"}
}