{
  "type": "Feature",
  "properties": {
    "iso:country":"US",
    "sg:address":"1909 E Washington Ln",
    "sg:city":"Philadelphia",
    "sg:classifiers":[
        {
            "category":"Shopping",
            "subcategory":"Discount & Variety Stores",
            "type":"Retail Goods"
        }
    ],
    "sg:phone":"+1 215 924 2446",
    "sg:postcode":"19138",
    "sg:province":"PA",
    "wof:name":"Dollar Plus Outlet",
    "wof:placetype":"venue"
},
  "geometry": {"coordinates":[-75.159249,40.065987],"type":"Point"}
}