{
  "type": "Feature",
  "properties": {
    "addr:full":"575 Morgantown Rd Uniontown PA 15401",
    "addr:housenumber":"575",
    "addr:postcode":"15401",
    "addr:street":"Morgantown Rd",
    "iso:country":"US",
    "sg:address":"575 Morgantown Rd",
    "sg:city":"Uniontown",
    "sg:classifiers":[
        {
            "category":"Cinema",
            "subcategory":"Movie Rental",
            "type":"Entertainment"
        }
    ],
    "sg:phone":"+1   ",
    "sg:postcode":"15401",
    "sg:province":"PA",
    "sg:tags":[
        "video",
        "store"
    ],
    "wof:name":"M G A Inc",
    "wof:placetype":"venue"
},
  "geometry": {"coordinates":[-79.73519400000001,39.883706],"type":"Point"}
}