{
  "type": "Feature",
  "properties": {
    "iso:country":"US",
    "sg:address":"10099 Lincoln Way E",
    "sg:city":"Fayetteville",
    "sg:classifiers":[
        {
            "category":"Government",
            "subcategory":"Office",
            "type":"Public Place"
        }
    ],
    "sg:phone":"+1   ",
    "sg:postcode":"17222",
    "sg:province":"PA",
    "sg:tags":[
        "forestry",
        "agency"
    ],
    "wof:name":"District 1 Forester",
    "wof:placetype":"venue"
},
  "geometry": {"coordinates":[-77.495401,39.905315],"type":"Point"}
}