{
  "type": "Feature",
  "properties": {
    "addr:full":"1627 Mt Bethel Hwy Mt Bethel PA 18343",
    "addr:housenumber":"1627",
    "addr:postcode":"18343",
    "addr:street":"Mt Bethel Hwy Mt",
    "iso:country":"US",
    "sg:address":"1627 Mt Bethel Hwy",
    "sg:city":"Mt Bethel",
    "sg:classifiers":[
        {
            "category":"Building & Trades",
            "subcategory":"Construction",
            "type":"Services"
        }
    ],
    "sg:phone":"+1 570 897 6814",
    "sg:postcode":"18343",
    "sg:province":"PA",
    "sg:tags":[
        "excavating",
        "contractor"
    ],
    "wof:name":"Joe's Excavation",
    "wof:placetype":"venue"
},
  "geometry": {"coordinates":[-75.13578800000001,40.896431],"type":"Point"}
}