{
  "type": "Feature",
  "properties": {
    "iso:country":"US",
    "sg:address":"187 Portman Rd",
    "sg:city":"Butler",
    "sg:classifiers":[
        {
            "category":"Personal",
            "subcategory":"Beauty Salon",
            "type":"Services"
        }
    ],
    "sg:phone":"+1 724 282 2775",
    "sg:postcode":"16002",
    "sg:province":"PA",
    "sg:tags":[
        "shop"
    ],
    "wof:name":"Classic Cuts By Bev",
    "wof:placetype":"venue"
},
  "geometry": {"coordinates":[-79.869963,40.859017],"type":"Point"}
}