{
  "type": "Feature",
  "properties": {
    "addr:full":"130 E College Ave State College PA 16801",
    "addr:housenumber":"130",
    "addr:postcode":"16801",
    "addr:street":"E College Ave",
    "iso:country":"US",
    "sg:address":"130 E College Ave",
    "sg:city":"State College",
    "sg:classifiers":[
        {
            "category":"Shopping",
            "subcategory":"Shoes",
            "type":"Retail Goods"
        }
    ],
    "sg:phone":"+1 814 234 8080",
    "sg:postcode":"16801",
    "sg:province":"PA",
    "wof:name":"Bare Foot",
    "wof:placetype":"venue"
},
  "geometry": {"coordinates":[-77.860664,40.794982],"type":"Point"}
}