{
  "type": "Feature",
  "properties": {
    "iso:country":"US",
    "sg:address":"309 Mercer Rd",
    "sg:city":"Greenville",
    "sg:classifiers":[
        {
            "category":"Real Estate",
            "subcategory":"Real Estate Agent",
            "type":"Services"
        }
    ],
    "sg:phone":"+1 724 588 1810",
    "sg:postcode":"16125",
    "sg:province":"PA",
    "wof:name":"Northwood Realty Svc",
    "wof:placetype":"venue"
},
  "geometry": {"coordinates":[-80.369705,41.390946],"type":"Point"}
}