{
  "type": "Feature",
  "properties": {
    "iso:country":"US",
    "sg:address":"143 Zanes Ln",
    "sg:city":"Mc Clure",
    "sg:classifiers":[
        {
            "category":"Building & Trades",
            "subcategory":"Plumbing",
            "type":"Services"
        }
    ],
    "sg:phone":"+1 717 543 5605",
    "sg:postcode":"17841",
    "sg:province":"PA",
    "sg:tags":[
        "conditioning",
        "air",
        "system",
        "contractor"
    ],
    "wof:name":"Wrays Heating & Air Condition",
    "wof:placetype":"venue"
},
  "geometry": {"coordinates":[-77.426857,40.698467],"type":"Point"}
}