{
  "type": "Feature",
  "properties": {
    "iso:country":"US",
    "sg:address":"23 Logan St",
    "sg:city":"Carnegie",
    "sg:classifiers":[
        {
            "category":"Education",
            "subcategory":"School",
            "type":"Public Place"
        }
    ],
    "sg:phone":"+1 412 276 7730",
    "sg:postcode":"15106",
    "sg:province":"PA",
    "wof:name":"Tender Loving Care Childrens Center",
    "wof:placetype":"venue"
},
  "geometry": {"coordinates":[-80.0905,40.4062],"type":"Point"}
}