{
  "type": "Feature",
  "properties": {
    "iso:country":"US",
    "sg:address":"5037 Love Rd",
    "sg:city":"Erie",
    "sg:classifiers":[
        {
            "category":"Personal",
            "subcategory":"Beauty Salon",
            "type":"Services"
        }
    ],
    "sg:phone":"+1 814 838 0744",
    "sg:postcode":"16506",
    "sg:province":"PA",
    "wof:name":"Cynthia Skellie Styling Salon",
    "wof:placetype":"venue"
},
  "geometry": {"coordinates":[-80.144846,42.05992],"type":"Point"}
}