{
  "type": "Feature",
  "properties": {
    "iso:country":"US",
    "sg:address":"552 E Washington Ln",
    "sg:city":"Philadelphia",
    "sg:classifiers":[
        {
            "category":"Building & Trades",
            "subcategory":"Electrical",
            "type":"Services"
        }
    ],
    "sg:phone":"+1 215 844 8506",
    "sg:postcode":"19144",
    "sg:province":"PA",
    "sg:tags":[
        "fire",
        "alarm",
        "system",
        "contractor"
    ],
    "wof:name":"Russells Coml Rsidential Wirin",
    "wof:placetype":"venue"
},
  "geometry": {"coordinates":[-75.17393800000001,40.050108],"type":"Point"}
}