{
  "type": "Feature",
  "properties": {
    "iso:country":"US",
    "sg:address":"4526 Liberty Ave",
    "sg:city":"Pittsburgh",
    "sg:classifiers":[
        {
            "category":"Shopping",
            "subcategory":"Music",
            "type":"Retail Goods"
        }
    ],
    "sg:phone":"+1 412 621 3256",
    "sg:postcode":"15224",
    "sg:province":"PA",
    "sg:tags":[
        "compact",
        "record",
        "disc",
        "tape"
    ],
    "sg:website":"www.paulscds.com",
    "wof:name":"Paul's Compact Discs",
    "wof:placetype":"venue"
},
  "geometry": {"coordinates":[-79.950931,40.462694],"type":"Point"}
}