{
  "type": "Feature",
  "properties": {
    "iso:country":"US",
    "sg:address":"116 Hemlock Dr",
    "sg:city":"Canonsburg",
    "sg:classifiers":[
        {
            "category":"Health Services",
            "subcategory":"Doctor",
            "type":"Services"
        }
    ],
    "sg:phone":"+1 724 942 3240",
    "sg:postcode":"15317",
    "sg:province":"PA",
    "sg:tags":[
        "physician",
        "surgeon"
    ],
    "wof:name":"Thomas J Kraczon Dr",
    "wof:placetype":"venue"
},
  "geometry": {"coordinates":[-80.137023,40.280798],"type":"Point"}
}