{
  "type": "Feature",
  "properties": {
    "iso:country":"US",
    "sg:address":"105 1st St",
    "sg:city":"Elkland",
    "sg:classifiers":[
        {
            "category":"Insurance",
            "subcategory":"Life Insurance",
            "type":"Services"
        }
    ],
    "sg:phone":"+1   ",
    "sg:postcode":"16920",
    "sg:province":"NY",
    "sg:tags":[
        "carrier"
    ],
    "wof:name":"Knights of Columbus Elkla",
    "wof:placetype":"venue"
},
  "geometry": {"coordinates":[-77.316468,41.988049],"type":"Point"}
}