{
  "type": "Feature",
  "properties": {
    "iso:country":"US",
    "sg:address":"101 Fox Run Dr",
    "sg:city":"York",
    "sg:classifiers":[
        {
            "category":"Insurance",
            "subcategory":"Insurance Agent",
            "type":"Services"
        }
    ],
    "sg:phone":"+1   ",
    "sg:postcode":"17403",
    "sg:province":"PA",
    "wof:name":"Joseph K Bury",
    "wof:placetype":"venue"
},
  "geometry": {"coordinates":[-76.69807299999999,39.924172],"type":"Point"}
}