{
  "type": "Feature",
  "properties": {
    "addr:full":"1013 Commerce Blvd Dickson City PA 18519",
    "addr:housenumber":"1013",
    "addr:postcode":"18519",
    "addr:street":"Commerce Blvd",
    "iso:country":"US",
    "sg:address":"1013 Commerce Blvd",
    "sg:city":"Dickson City",
    "sg:classifiers":[
        {
            "category":"Restaurant",
            "type":"Food & Drink"
        }
    ],
    "sg:phone":"+1 570 383 2323",
    "sg:postcode":"18519",
    "sg:province":"PA",
    "sg:tags":[
        "eating"
    ],
    "wof:name":"China Palace Inn",
    "wof:placetype":"venue"
},
  "geometry": {"coordinates":[-75.64365599999999,41.463069],"type":"Point"}
}