{
  "type": "Feature",
  "properties": {
    "addr:full":"522 Merchant St Ambridge PA 15003",
    "addr:housenumber":"522",
    "addr:postcode":"15003",
    "addr:street":"Merchant St",
    "iso:country":"US",
    "sg:address":"522 Merchant St",
    "sg:city":"Ambridge",
    "sg:classifiers":[
        {
            "category":"Bars & Pubs",
            "type":"Food & Drink"
        }
    ],
    "sg:phone":"+1 724 266 5340",
    "sg:postcode":"15003",
    "sg:province":"PA",
    "sg:tags":[
        "drinking"
    ],
    "wof:name":"Colonial Grill",
    "wof:placetype":"venue"
},
  "geometry": {"coordinates":[-80.22702,40.586242],"type":"Point"}
}