{
  "type": "Feature",
  "properties": {
    "addr:full":"62 Lancstr Ave Philadelphia PA 19102",
    "addr:housenumber":"62",
    "addr:postcode":"19102",
    "addr:street":"Lancstr Ave",
    "iso:country":"US",
    "sg:address":"62 Lancstr Ave",
    "sg:city":"Philadelphia",
    "sg:classifiers":[
        {
            "category":"Wholesale",
            "subcategory":"Fruits & Vegetables",
            "type":"Manufacturing & Wholesale Goods"
        }
    ],
    "sg:phone":"+1 215 877 4880",
    "sg:postcode":"19102",
    "sg:province":"PA",
    "sg:tags":[
        "veggie"
    ],
    "wof:name":"Giordano Jos Jr Prod",
    "wof:placetype":"venue"
},
  "geometry": {"coordinates":[-75.166901,39.949501],"type":"Point"}
}