{
  "type": "Feature",
  "properties": {
    "iso:country":"US",
    "sg:address":"139 Clinton St",
    "sg:city":"Johnstown",
    "sg:classifiers":[
        {
            "category":"Banks & Credit Unions",
            "subcategory":"Investment Brokerage",
            "type":"Services"
        }
    ],
    "sg:phone":"+1 814 536 1040",
    "sg:postcode":"15901",
    "sg:province":"PA",
    "sg:tags":[
        "consultant",
        "planning",
        "financial"
    ],
    "wof:name":"Asset Planning Group",
    "wof:placetype":"venue"
},
  "geometry": {"coordinates":[-78.915741,40.324901],"type":"Point"}
}