{
  "type": "Feature",
  "properties": {
    "iso:country":"US",
    "sg:address":"2119 Springfield Pike",
    "sg:city":"Connellsville",
    "sg:classifiers":[
        {
            "category":"Food & Beverages",
            "subcategory":"Groceries & Convenience Stores",
            "type":"Retail Goods"
        }
    ],
    "sg:phone":"+1   ",
    "sg:postcode":"15425",
    "sg:province":"PA",
    "wof:name":"Karels Kountry Korner",
    "wof:placetype":"venue"
},
  "geometry": {"coordinates":[-79.54486,40.017669],"type":"Point"}
}