{
  "type": "Feature",
  "properties": {
    "iso:country":"US",
    "sg:address":"70 W Oakland Ave",
    "sg:city":"Doylestown",
    "sg:classifiers":[
        {
            "category":"Professional",
            "subcategory":"Management & Consulting",
            "type":"Services"
        }
    ],
    "sg:phone":"+1   ",
    "sg:postcode":"18901",
    "sg:province":"PA",
    "sg:tags":[
        "business",
        "association"
    ],
    "wof:name":"McHugh Consulting Resourc",
    "wof:placetype":"venue"
},
  "geometry": {"coordinates":[-75.13145299999999,40.308221],"type":"Point"}
}