{
  "type": "Feature",
  "properties": {
    "addr:full":"63 Rutherford Run Bradford PA 16701",
    "addr:housenumber":"63",
    "addr:postcode":"16701",
    "addr:street":"Rutherford Run",
    "iso:country":"US",
    "sg:address":"63 Rutherford Run",
    "sg:city":"Bradford",
    "sg:classifiers":[
        {
            "category":"Farming",
            "subcategory":"Poultry Farm",
            "type":"Manufacturing & Wholesale Goods"
        }
    ],
    "sg:phone":"+1   ",
    "sg:postcode":"16701",
    "sg:province":"PA",
    "sg:tags":[
        "chicken"
    ],
    "wof:name":"Emery Aharrah",
    "wof:placetype":"venue"
},
  "geometry": {"coordinates":[-78.636217,41.931973],"type":"Point"}
}