{
  "type": "Feature",
  "properties": {
    "iso:country":"US",
    "sg:address":"113 Interlachen Ct",
    "sg:city":"Avondale",
    "sg:classifiers":[
        {
            "category":"Health Services",
            "subcategory":"Doctor",
            "type":"Services"
        }
    ],
    "sg:phone":"+1   ",
    "sg:postcode":"19311",
    "sg:province":"PA",
    "sg:tags":[
        "medical"
    ],
    "wof:name":"Dr David Ettinger",
    "wof:placetype":"venue"
},
  "geometry": {"coordinates":[-75.729922,39.802341],"type":"Point"}
}