{
  "type": "Feature",
  "properties": {
    "addr:full":"534 Burmont Rd Drexel Hill PA 19026",
    "addr:housenumber":"534",
    "addr:postcode":"19026",
    "addr:street":"Burmont Rd",
    "iso:country":"US",
    "sg:address":"534 Burmont Rd",
    "sg:city":"Drexel Hill",
    "sg:classifiers":[
        {
            "category":"Arts & Performance",
            "subcategory":"Theater",
            "type":"Entertainment"
        }
    ],
    "sg:phone":"+1 610 460 0993",
    "sg:postcode":"19026",
    "sg:province":"PA",
    "sg:tags":[
        "bureau"
    ],
    "wof:name":"Talent Connection",
    "wof:placetype":"venue"
},
  "geometry": {"coordinates":[-75.301665,39.946584],"type":"Point"}
}