{
  "type": "Feature",
  "properties": {
    "addr:full":"1 Wyoming Valley Mall Wilkes Barre PA 18702",
    "addr:housenumber":"1",
    "addr:postcode":"18702",
    "addr:street":"Wyoming Valley Mall",
    "iso:country":"US",
    "sg:address":"1 Wyoming Valley Mall",
    "sg:city":"Wilkes Barre",
    "sg:classifiers":[
        {
            "category":"Banks & Credit Unions",
            "subcategory":"Bank",
            "type":"Services"
        }
    ],
    "sg:phone":"+1 570 826 4966",
    "sg:postcode":"18702",
    "sg:province":"PA",
    "sg:website":"www.pncbank.com",
    "wof:name":"Pnc Bank",
    "wof:placetype":"venue"
},
  "geometry": {"coordinates":[-75.842569,41.249369],"type":"Point"}
}