{
  "type": "Feature",
  "properties": {
    "iso:country":"US",
    "sg:address":"2383 Neshaminy Blvd",
    "sg:city":"Bensalem",
    "sg:classifiers":[
        {
            "category":"Professional",
            "subcategory":"Accounting & Tax Preparation",
            "type":"Services"
        }
    ],
    "sg:phone":"+1 215 741 1830",
    "sg:postcode":"19020",
    "sg:province":"PA",
    "sg:tags":[
        "return",
        "filing"
    ],
    "wof:name":"William J Sarr",
    "wof:placetype":"venue"
},
  "geometry": {"coordinates":[-74.92486700000001,40.133245],"type":"Point"}
}