{
  "type": "Feature",
  "properties": {
    "iso:country":"US",
    "sg:address":"436 Walnut St",
    "sg:city":"Philadelphia",
    "sg:classifiers":[
        {
            "category":"Personal",
            "type":"Services"
        }
    ],
    "sg:phone":"+1 215 923 5352",
    "sg:postcode":"19106",
    "sg:province":"PA",
    "sg:tags":[
        "property",
        "maintenance"
    ],
    "wof:name":"Ace U S A",
    "wof:placetype":"venue"
},
  "geometry": {"coordinates":[-75.148517,39.947364],"type":"Point"}
}