{
  "type": "Feature",
  "properties": {
    "iso:country":"US",
    "sg:address":"1000 Henderson Ave",
    "sg:city":"Washington",
    "sg:classifiers":[
        {
            "category":"Manufacturing",
            "subcategory":"Buildings",
            "type":"Manufacturing & Wholesale Goods"
        }
    ],
    "sg:phone":"+1 724 229 1400",
    "sg:postcode":"15301",
    "sg:province":"PA",
    "sg:tags":[
        "prefab"
    ],
    "wof:name":"Washington Estates",
    "wof:placetype":"venue"
},
  "geometry": {"coordinates":[-80.271243,40.200207],"type":"Point"}
}