{
  "type": "Feature",
  "properties": {
    "iso:country":"US",
    "sg:address":"3411 Library Rd",
    "sg:city":"Pittsburgh",
    "sg:classifiers":[
        {
            "category":"Building & Trades",
            "subcategory":"Pest Control",
            "type":"Services"
        }
    ],
    "sg:phone":"+1   ",
    "sg:postcode":"15234",
    "sg:province":"PA",
    "wof:name":"Bug Goff Exterminating Co Inc",
    "wof:placetype":"venue"
},
  "geometry": {"coordinates":[-80.013345,40.367526],"type":"Point"}
}