{
  "type": "Feature",
  "properties": {
    "addr:full":"4411 Osage Ave Philadelphia PA 19104",
    "addr:housenumber":"4411",
    "addr:postcode":"19104",
    "addr:street":"Osage Ave",
    "iso:country":"US",
    "sg:address":"4411 Osage Ave",
    "sg:city":"Philadelphia",
    "sg:classifiers":[
        {
            "category":"Building & Trades",
            "subcategory":"Landscaping Services",
            "type":"Services"
        }
    ],
    "sg:phone":"+1   ",
    "sg:postcode":"19104",
    "sg:province":"PA",
    "sg:tags":[
        "counseling",
        "planning",
        "landscape"
    ],
    "wof:name":"Hamerman Conrad Lndscp Arch",
    "wof:placetype":"venue"
},
  "geometry": {"coordinates":[-75.212417,39.951108],"type":"Point"}
}