{
  "type": "Feature",
  "properties": {
    "addr:full":"1 Passan Dr Wilkes Barre PA 18702",
    "addr:housenumber":"1",
    "addr:postcode":"18702",
    "addr:street":"Passan Dr",
    "iso:country":"US",
    "sg:address":"1 Passan Dr",
    "sg:city":"Wilkes Barre",
    "sg:classifiers":[
        {
            "category":"Freight",
            "type":"Transportation"
        }
    ],
    "sg:phone":"+1 570 654 2403",
    "sg:postcode":"18702",
    "sg:province":"PA",
    "sg:tags":[
        "warehouse",
        "storage",
        "warehousing"
    ],
    "sg:website":"www.valleydist.com",
    "wof:name":"Valley Distributing & Stor Co",
    "wof:placetype":"venue"
},
  "geometry": {"coordinates":[-75.797369,41.294359],"type":"Point"}
}