{
  "type": "Feature",
  "properties": {
    "iso:country":"US",
    "sg:address":"3721 William Penn Hwy",
    "sg:city":"Monroeville",
    "sg:classifiers":[
        {
            "category":"Autos & Motor Vehicles",
            "subcategory":"Automobile Sales",
            "type":"Retail Goods"
        }
    ],
    "sg:phone":"+1 412 856 1422",
    "sg:postcode":"15146",
    "sg:province":"PA",
    "sg:tags":[
        "car",
        "dealer"
    ],
    "wof:name":"Monroeville Chrysler Jeep",
    "wof:placetype":"venue"
},
  "geometry": {"coordinates":[-79.790474,40.435034],"type":"Point"}
}