{
  "type": "Feature",
  "properties": {
    "addr:full":"235 Hulton Rd New Kensington PA 15068",
    "addr:housenumber":"235",
    "addr:postcode":"15068",
    "addr:street":"Hulton Rd",
    "iso:country":"US",
    "sg:address":"235 Hulton Rd",
    "sg:city":"New Kensington",
    "sg:classifiers":[
        {
            "category":"Real Estate",
            "subcategory":"Real Estate Agent",
            "type":"Services"
        }
    ],
    "sg:phone":"+1   ",
    "sg:postcode":"15068",
    "sg:province":"PA",
    "sg:tags":[
        "residential",
        "rental"
    ],
    "wof:name":"Elmark Inc",
    "wof:placetype":"venue"
},
  "geometry": {"coordinates":[-79.68338900000001,40.605577],"type":"Point"}
}