{
  "type": "Feature",
  "properties": {
    "iso:country":"US",
    "sg:address":"1805 Berks Rd",
    "sg:city":"Worcester",
    "sg:classifiers":[
        {
            "category":"Building & Trades",
            "subcategory":"Construction",
            "type":"Services"
        }
    ],
    "sg:phone":"+1 610 584 6020",
    "sg:postcode":"19403",
    "sg:province":"PA",
    "sg:tags":[
        "excavating",
        "contractor"
    ],
    "sg:website":"www.americaninfrastructure.com",
    "wof:name":"American Infrastructure",
    "wof:placetype":"venue"
},
  "geometry": {"coordinates":[-75.32708100000001,40.187244],"type":"Point"}
}