{
  "type": "Feature",
  "properties": {
    "iso:country":"US",
    "sg:address":"726 W Ontario St",
    "sg:city":"Philadelphia",
    "sg:classifiers":[
        {
            "category":"Retail",
            "subcategory":"Auto Repair",
            "type":"Services"
        }
    ],
    "sg:phone":"+1 215 228 5014",
    "sg:postcode":"19140",
    "sg:province":"PA",
    "sg:tags":[
        "repairing",
        "automobile"
    ],
    "wof:name":"Compai Auto Repair",
    "wof:placetype":"venue"
},
  "geometry": {"coordinates":[-75.142522,40.003342],"type":"Point"}
}