{
  "type": "Feature",
  "properties": {
    "addr:full":"147 S 18th St Pittsburgh PA 15203",
    "addr:housenumber":"147",
    "addr:postcode":"15203",
    "addr:street":"S 18Th St",
    "iso:country":"US",
    "sg:address":"147 S 18th St",
    "sg:city":"Pittsburgh",
    "sg:classifiers":[
        {
            "category":"Home & Garden",
            "subcategory":"Carpets & Floor Coverings",
            "type":"Retail Goods"
        }
    ],
    "sg:phone":"+1   ",
    "sg:postcode":"15203",
    "sg:province":"PA",
    "sg:tags":[
        "laying",
        "contractor"
    ],
    "wof:name":"George Lancaster Carpets Inc",
    "wof:placetype":"venue"
},
  "geometry": {"coordinates":[-79.980738,40.426239],"type":"Point"}
}