{
  "type": "Feature",
  "properties": {
    "iso:country":"US",
    "sg:address":"244 Neeley School Rd",
    "sg:city":"Wexford",
    "sg:classifiers":[
        {
            "category":"Building & Trades",
            "subcategory":"Construction",
            "type":"Services"
        }
    ],
    "sg:phone":"+1 724 935 0778",
    "sg:postcode":"15090",
    "sg:province":"PA",
    "sg:tags":[
        "woodworker"
    ],
    "wof:name":"Umenhofer Contracting",
    "wof:placetype":"venue"
},
  "geometry": {"coordinates":[-80.09639,40.638991],"type":"Point"}
}