{
  "type": "Feature",
  "properties": {
    "iso:country":"US",
    "sg:address":"4002 Chestnut St",
    "sg:city":"Emmaus",
    "sg:classifiers":[
        {
            "category":"Autos & Motor Vehicles",
            "subcategory":"Fuel & Gas Station",
            "type":"Retail Goods"
        }
    ],
    "sg:phone":"+1   ",
    "sg:postcode":"18049",
    "sg:province":"PA",
    "wof:name":"Hess",
    "wof:placetype":"venue"
},
  "geometry": {"coordinates":[-75.520977,40.519671],"type":"Point"}
}