{
  "type": "Feature",
  "properties": {
    "addr:full":"2900 Grant Ave Philadelphia PA 19114",
    "addr:housenumber":"2900",
    "addr:postcode":"19114",
    "addr:street":"Grant Ave",
    "iso:country":"US",
    "sg:address":"2900 Grant Ave",
    "sg:city":"Philadelphia",
    "sg:classifiers":[
        {
            "category":"Manufacturing",
            "subcategory":"Paper Products",
            "type":"Manufacturing & Wholesale Goods"
        }
    ],
    "sg:phone":"+1 215 676 8888",
    "sg:postcode":"19114",
    "sg:province":"PA",
    "sg:tags":[
        "bag"
    ],
    "sg:website":"www.swalter.com",
    "wof:name":"S Walter Packaging Corp",
    "wof:placetype":"venue"
},
  "geometry": {"coordinates":[-75.015626,40.073496],"type":"Point"}
}