{
  "type": "Feature",
  "properties": {
    "iso:country":"US",
    "sg:address":"7794 W Ridge Rd",
    "sg:city":"Fairview",
    "sg:classifiers":[
        {
            "category":"Shopping",
            "subcategory":"Bicycles & Sporting Goods",
            "type":"Retail Goods"
        }
    ],
    "sg:phone":"+1 814 474 5555",
    "sg:postcode":"16415",
    "sg:province":"PA",
    "sg:tags":[
        "equipment",
        "range",
        "archery",
        "supply"
    ],
    "wof:name":"Outpost Archery",
    "wof:placetype":"venue"
},
  "geometry": {"coordinates":[-80.26279,42.024991],"type":"Point"}
}