{
  "type": "Feature",
  "properties": {
    "addr:full":"1037 Line St Sunbury PA 17801",
    "addr:housenumber":"1037",
    "addr:postcode":"17801",
    "addr:street":"Line St",
    "iso:country":"US",
    "sg:address":"1037 Line St",
    "sg:city":"Sunbury",
    "sg:classifiers":[
        {
            "category":"Shopping",
            "subcategory":"Hobbies, Toys, & Games",
            "type":"Retail Goods"
        }
    ],
    "sg:phone":"+1   ",
    "sg:postcode":"17801",
    "sg:province":"PA",
    "wof:name":"C W & D Model Railroad Sups",
    "wof:placetype":"venue"
},
  "geometry": {"coordinates":[-76.781037,40.862883],"type":"Point"}
}