{
  "type": "Feature",
  "properties": {
    "addr:full":"234 Kathleen Dr Peckville PA 18452",
    "addr:housenumber":"234",
    "addr:postcode":"18452",
    "addr:street":"Kathleen Dr Peckville",
    "iso:country":"US",
    "sg:address":"234 Kathleen Dr",
    "sg:city":"Peckville",
    "sg:classifiers":[
        {
            "category":"Building & Trades",
            "subcategory":"Construction",
            "type":"Services"
        }
    ],
    "sg:phone":"+1   ",
    "sg:postcode":"18452",
    "sg:province":"PA",
    "sg:tags":[
        "house"
    ],
    "wof:name":"Jj Builders James V Galli",
    "wof:placetype":"venue"
},
  "geometry": {"coordinates":[-75.582854,41.482247],"type":"Point"}
}