{
  "type": "Feature",
  "properties": {
    "iso:country":"US",
    "sg:address":"17 Groce Ave",
    "sg:city":"Lansdowne",
    "sg:classifiers":[
        {
            "category":"Organizations",
            "subcategory":"Religious Organization",
            "type":"Services"
        }
    ],
    "sg:phone":"+1 610 626 0637",
    "sg:postcode":"19036",
    "sg:province":"PA",
    "wof:name":"Lansdowne Baptist Church",
    "wof:placetype":"venue"
},
  "geometry": {"coordinates":[-75.29087,39.910712],"type":"Point"}
}