{
  "type": "Feature",
  "properties": {
    "addr:full":"1 Church St Elizabeth PA 15037",
    "addr:housenumber":"1",
    "addr:postcode":"15037",
    "addr:street":"Church St",
    "iso:country":"US",
    "sg:address":"1 Church St",
    "sg:city":"Elizabeth",
    "sg:classifiers":[
        {
            "category":"Mining & Drilling",
            "type":"Manufacturing & Wholesale Goods"
        }
    ],
    "sg:phone":"+1 412 384 6550",
    "sg:postcode":"15037",
    "sg:province":"PA",
    "sg:tags":[
        "coal",
        "shipping"
    ],
    "sg:website":"www.consolenergy.com",
    "wof:name":"Twin Rivers Towing Co",
    "wof:placetype":"venue"
},
  "geometry": {"coordinates":[-79.882845,40.276156],"type":"Point"}
}