{
  "type": "Feature",
  "properties": {
    "addr:full":"2904 Moravian Ave Allentown PA 18103",
    "addr:housenumber":"2904",
    "addr:postcode":"18103",
    "addr:street":"Moravian Ave",
    "iso:country":"US",
    "sg:address":"2904 Moravian Ave",
    "sg:city":"Allentown",
    "sg:classifiers":[
        {
            "category":"Insurance",
            "subcategory":"Insurance Agent",
            "type":"Services"
        }
    ],
    "sg:phone":"+1   ",
    "sg:postcode":"18103",
    "sg:province":"PA",
    "wof:name":"Senior Health Insurance Svcs",
    "wof:placetype":"venue"
},
  "geometry": {"coordinates":[-75.48824500000001,40.560453],"type":"Point"}
}