{
  "type": "Feature",
  "properties": {
    "iso:country":"US",
    "sg:address":"620 Commerce Blvd",
    "sg:city":"Fairless Hills",
    "sg:classifiers":[
        {
            "category":"Home & Garden",
            "subcategory":"Furniture",
            "type":"Retail Goods"
        }
    ],
    "sg:phone":"+1 215 269 4500",
    "sg:postcode":"19030",
    "sg:province":"PA",
    "sg:website":"www.kincaidhome.com",
    "wof:name":"Kincaid Of Oxford Valley",
    "wof:placetype":"venue"
},
  "geometry": {"coordinates":[-74.864711,40.18729],"type":"Point"}
}