{
  "type": "Feature",
  "properties": {
    "iso:country":"US",
    "sg:address":"107 N Front St",
    "sg:city":"Harrisburg",
    "sg:classifiers":[
        {
            "category":"Professional",
            "subcategory":"Lawyer & Legal Services",
            "type":"Services"
        }
    ],
    "sg:phone":"+1 717 237 6022",
    "sg:postcode":"17101",
    "sg:province":"PA",
    "sg:tags":[
        "attorney"
    ],
    "wof:name":"Samuel Cooper III Law Offices",
    "wof:placetype":"venue"
},
  "geometry": {"coordinates":[-76.885116,40.259934],"type":"Point"}
}