{
  "type": "Feature",
  "properties": {
    "addr:full":"18 E Ridge St Lansford PA 18232",
    "addr:housenumber":"18",
    "addr:postcode":"18232",
    "addr:street":"E Ridge St",
    "iso:country":"US",
    "sg:address":"18 E Ridge St",
    "sg:city":"Lansford",
    "sg:classifiers":[
        {
            "category":"Home & Garden",
            "subcategory":"Furniture",
            "type":"Retail Goods"
        }
    ],
    "sg:phone":"+1 570 645 2102",
    "sg:postcode":"18232",
    "sg:province":"PA",
    "wof:name":"Silver Furniture Co Inc",
    "wof:placetype":"venue"
},
  "geometry": {"coordinates":[-75.882929,40.832366],"type":"Point"}
}