{
  "type": "Feature",
  "properties": {
    "iso:country":"US",
    "sg:address":"607 Eby Chiques Rd",
    "sg:city":"Mount Joy",
    "sg:classifiers":[
        {
            "category":"Travel",
            "subcategory":"Hotels & Motels",
            "type":"Entertainment"
        }
    ],
    "sg:phone":"+1   ",
    "sg:postcode":"17552",
    "sg:province":"PA",
    "sg:tags":[
        "operation"
    ],
    "wof:name":"Hillside Farm Bed & Breakfast",
    "wof:placetype":"venue"
},
  "geometry": {"coordinates":[-76.45865499999999,40.107962],"type":"Point"}
}