{
  "type": "Feature",
  "properties": {
    "addr:full":"25 E State St Media PA 19063",
    "addr:housenumber":"25",
    "addr:postcode":"19063",
    "addr:street":"E State St",
    "iso:country":"US",
    "sg:address":"25 E State St",
    "sg:city":"Media",
    "sg:classifiers":[
        {
            "category":"Shopping",
            "subcategory":"Florist",
            "type":"Retail Goods"
        }
    ],
    "sg:phone":"+1 610 565 7470",
    "sg:postcode":"19063",
    "sg:province":"PA",
    "sg:website":"www.mediaflorist.com",
    "wof:name":"Media Florist",
    "wof:placetype":"venue"
},
  "geometry": {"coordinates":[-75.38763400000001,39.91776],"type":"Point"}
}