{
  "type": "Feature",
  "properties": {
    "addr:full":"1006 Neils Dr Exton PA 19341",
    "addr:housenumber":"1006",
    "addr:postcode":"19341",
    "addr:street":"Neils Dr",
    "iso:country":"US",
    "sg:address":"1006 Neils Dr",
    "sg:city":"Exton",
    "sg:classifiers":[
        {
            "category":"Organizations",
            "subcategory":"Professional Association",
            "type":"Services"
        }
    ],
    "sg:phone":"+1 610 594 9920",
    "sg:postcode":"19341",
    "sg:province":"PA",
    "sg:tags":[
        "sales"
    ],
    "wof:name":"Concord Communications",
    "wof:placetype":"venue"
},
  "geometry": {"coordinates":[-75.612801,40.049545],"type":"Point"}
}