{
  "type": "Feature",
  "properties": {
    "iso:country":"US",
    "sg:address":"27 Sunset Ln",
    "sg:city":"Cresco",
    "sg:classifiers":[
        {
            "category":"Building & Trades",
            "subcategory":"Construction",
            "type":"Services"
        }
    ],
    "sg:phone":"+1   ",
    "sg:postcode":"18322",
    "sg:province":"PA",
    "sg:tags":[
        "carpentry",
        "contractor"
    ],
    "wof:name":"Gorilla Overhead Doors Inc",
    "wof:placetype":"venue"
},
  "geometry": {"coordinates":[-75.40032600000001,40.911432],"type":"Point"}
}