{
  "type": "Feature",
  "properties": {
    "iso:country":"US",
    "sg:address":"2810A Paxton Street",
    "sg:city":"Harrisburg",
    "sg:classifiers":[
        {
            "category":"Retail",
            "subcategory":"Auto Repair",
            "type":"Services"
        }
    ],
    "sg:phone":"+1 717 565 2134",
    "sg:postcode":"17111",
    "sg:province":"PA",
    "sg:website":"www.alltunecarepair.com/",
    "wof:name":"All Tune and Lube",
    "wof:placetype":"venue"
},
  "geometry": {"coordinates":[-76.84059600000001,40.25588],"type":"Point"}
}