{
  "type": "Feature",
  "properties": {
    "addr:full":"1052 S Church St Hazleton PA 18201",
    "addr:housenumber":"1052",
    "addr:postcode":"18201",
    "addr:street":"S Church St",
    "iso:country":"US",
    "sg:address":"1052 S Church St",
    "sg:city":"Hazleton",
    "sg:classifiers":[
        {
            "category":"Government",
            "subcategory":"Office",
            "type":"Public Place"
        }
    ],
    "sg:phone":"+1   ",
    "sg:postcode":"18201",
    "sg:province":"PA",
    "sg:tags":[
        "transportation"
    ],
    "wof:name":"Driver License Center",
    "wof:placetype":"venue"
},
  "geometry": {"coordinates":[-75.993529,40.933475],"type":"Point"}
}