{
  "type": "Feature",
  "properties": {
    "iso:country":"US",
    "sg:address":"24 S Market St",
    "sg:city":"Elizabethtown",
    "sg:classifiers":[
        {
            "category":"Organizations",
            "subcategory":"Professional Association",
            "type":"Services"
        }
    ],
    "sg:phone":"+1 717 361 7188",
    "sg:postcode":"17022",
    "sg:province":"PA",
    "sg:tags":[
        "chambers",
        "business",
        "commerce"
    ],
    "sg:website":"www.elizabethtowncoc.com",
    "wof:name":"Elizabethtown Chamber Commerce",
    "wof:placetype":"venue"
},
  "geometry": {"coordinates":[-76.605903,40.151178],"type":"Point"}
}