{
  "type": "Feature",
  "properties": {
    "iso:country":"US",
    "sg:address":"190 E Lauer Ln",
    "sg:city":"Camp Hill",
    "sg:classifiers":[
        {
            "category":"Health Services",
            "subcategory":"Doctor",
            "type":"Services"
        }
    ],
    "sg:phone":"+1 717 761 4257",
    "sg:postcode":"17011",
    "sg:province":"PA",
    "wof:name":"Brock Richard R MD",
    "wof:placetype":"venue"
},
  "geometry": {"coordinates":[-76.961428,40.253793],"type":"Point"}
}