{
  "type": "Feature",
  "properties": {
    "iso:country":"US",
    "sg:address":"375 Malin Rd",
    "sg:city":"Newtown Square",
    "sg:classifiers":[
        {
            "category":"Building & Trades",
            "subcategory":"Electrical",
            "type":"Services"
        }
    ],
    "sg:phone":"+1   ",
    "sg:postcode":"19073",
    "sg:province":"PA",
    "sg:tags":[
        "electrical",
        "contractor"
    ],
    "wof:name":"Console Electric Co Inc",
    "wof:placetype":"venue"
},
  "geometry": {"coordinates":[-75.374678,39.995013],"type":"Point"}
}