{
  "type": "Feature",
  "properties": {
    "iso:country":"US",
    "sg:address":"5680 Munhall Rd",
    "sg:city":"Pittsburgh",
    "sg:classifiers":[
        {
            "category":"Real Estate",
            "subcategory":"Real Estate Operator",
            "type":"Services"
        }
    ],
    "sg:phone":"+1 412 521 2866",
    "sg:postcode":"15217",
    "sg:province":"PA",
    "sg:tags":[
        "building",
        "apartment"
    ],
    "wof:name":"Morris Hall Charles Management",
    "wof:placetype":"venue"
},
  "geometry": {"coordinates":[-79.924941,40.43345],"type":"Point"}
}