{
  "type": "Feature",
  "properties": {
    "iso:country":"US",
    "sg:address":"5901 Castor Ave",
    "sg:city":"Philadelphia",
    "sg:phone":"+1 215 537 1937",
    "sg:postcode":"19149",
    "sg:province":"PA",
    "wof:name":"Rajbhog Restaurant & Sweets",
    "wof:placetype":"venue"
},
  "geometry": {"coordinates":[-75.083359,40.033241],"type":"Point"}
}