{
  "type": "Feature",
  "properties": {
    "addr:full":"200 Lincoln Ave Phoenixville PA 19460",
    "addr:housenumber":"200",
    "addr:postcode":"19460",
    "addr:street":"Lincoln Ave",
    "iso:country":"US",
    "sg:address":"200 Lincoln Ave",
    "sg:city":"Phoenixville",
    "sg:classifiers":[
        {
            "category":"Wholesale",
            "subcategory":"Home Furnishings",
            "type":"Manufacturing & Wholesale Goods"
        }
    ],
    "sg:phone":"+1 610 415 0800",
    "sg:postcode":"19460",
    "sg:province":"PA",
    "sg:tags":[
        "curtain",
        "drapery"
    ],
    "wof:name":"Skotz Manufacturing Inc",
    "wof:placetype":"venue"
},
  "geometry": {"coordinates":[-75.51944899999999,40.129114],"type":"Point"}
}