{
  "type": "Feature",
  "properties": {
    "addr:full":"1185 Washington Pike Bridgeville PA 15017",
    "addr:housenumber":"1185",
    "addr:postcode":"15017",
    "addr:street":"Washington Pike",
    "iso:country":"US",
    "sg:address":"1185 Washington Pike",
    "sg:city":"Bridgeville",
    "sg:classifiers":[
        {
            "category":"Personal",
            "subcategory":"Beauty Salon",
            "type":"Services"
        }
    ],
    "sg:phone":"+1 412 221 7601",
    "sg:postcode":"15017",
    "sg:province":"PA",
    "wof:name":"The Auto Salon",
    "wof:placetype":"venue"
},
  "geometry": {"coordinates":[-80.101209,40.369685],"type":"Point"}
}