{
  "type": "Feature",
  "properties": {
    "addr:full":"606 Rohrerstown Rd Lancaster PA 17603",
    "addr:housenumber":"606",
    "addr:postcode":"17603",
    "addr:street":"Rohrerstown Rd",
    "iso:country":"US",
    "sg:address":"606 Rohrerstown Rd",
    "sg:city":"Lancaster",
    "sg:classifiers":[
        {
            "category":"Manufacturing",
            "subcategory":"Signs",
            "type":"Manufacturing & Wholesale Goods"
        }
    ],
    "sg:phone":"+1 717 290 1112",
    "sg:postcode":"17603",
    "sg:province":"PA",
    "sg:website":"www.redrosesigns.com",
    "wof:name":"Red Rose Sign Co",
    "wof:placetype":"venue"
},
  "geometry": {"coordinates":[-76.360108,40.052896],"type":"Point"}
}