{
  "type": "Feature",
  "properties": {
    "iso:country":"US",
    "sg:address":"Burnt House Hill Rd",
    "sg:city":"Danboro",
    "sg:classifiers":[
        {
            "category":"Building & Trades",
            "subcategory":"Construction",
            "type":"Services"
        },
        {
            "category":"Building & Trades",
            "subcategory":"Electrical",
            "type":"Services"
        }
    ],
    "sg:phone":"+1 215 348 1467",
    "sg:postcode":"18916",
    "sg:province":"PA",
    "sg:tags":[
        "electrician",
        "contractor"
    ],
    "wof:name":"Helsel B - CLOSED",
    "wof:placetype":"venue"
},
  "geometry": {"coordinates":[-75.18499799999999,40.297401],"type":"Point"}
}