{
  "type": "Feature",
  "properties": {
    "iso:country":"US",
    "sg:address":"2820 Mechanicsville Rd",
    "sg:city":"Bensalem",
    "sg:classifiers":[
        {
            "category":"Professional",
            "subcategory":"Management & Consulting",
            "type":"Services"
        }
    ],
    "sg:phone":"+1 215 244 0470",
    "sg:postcode":"19020",
    "sg:province":"PA",
    "sg:tags":[
        "construction"
    ],
    "wof:name":"Alexander Construction Co",
    "wof:placetype":"venue"
},
  "geometry": {"coordinates":[-74.957337,40.107414],"type":"Point"}
}