{
  "type": "Feature",
  "properties": {
    "iso:country":"US",
    "sg:address":"4617 Fernhill Rd",
    "sg:city":"Philadelphia",
    "sg:classifiers":[
        {
            "category":"Home & Garden",
            "subcategory":"Carpets & Floor Coverings",
            "type":"Retail Goods"
        }
    ],
    "sg:phone":"+1 215 681 6563",
    "sg:postcode":"19144",
    "sg:province":"PA",
    "sg:tags":[
        "installation"
    ],
    "wof:name":"Robinson Visual Graphics",
    "wof:placetype":"venue"
},
  "geometry": {"coordinates":[-75.166428,40.021062],"type":"Point"}
}