{
  "type": "Feature",
  "properties": {
    "addr:full":"915 Stoneybrook Dr Springfield PA 19064",
    "addr:housenumber":"915",
    "addr:postcode":"19064",
    "addr:street":"Stoneybrook Dr",
    "iso:country":"US",
    "sg:address":"915 Stoneybrook Dr",
    "sg:city":"Springfield",
    "sg:classifiers":[
        {
            "category":"Wholesale",
            "subcategory":"Non-durable Goods",
            "type":"Manufacturing & Wholesale Goods"
        }
    ],
    "sg:phone":"+1   ",
    "sg:postcode":"19064",
    "sg:province":"PA",
    "wof:name":"Crosseywarehouse",
    "wof:placetype":"venue"
},
  "geometry": {"coordinates":[-75.32216200000001,39.917999],"type":"Point"}
}