{
  "type": "Feature",
  "properties": {
    "iso:country":"US",
    "sg:address":"4810 Old William Penn Hwy",
    "sg:city":"Export",
    "sg:classifiers":[
        {
            "category":"Food & Beverages",
            "subcategory":"Groceries & Convenience Stores",
            "type":"Retail Goods"
        }
    ],
    "sg:phone":"+1   ",
    "sg:postcode":"15632",
    "sg:province":"PA",
    "sg:tags":[
        "supermarket"
    ],
    "wof:name":"Giant Eagle",
    "wof:placetype":"venue"
},
  "geometry": {"coordinates":[-79.66306299999999,40.423849],"type":"Point"}
}