{
  "type": "Feature",
  "properties": {
    "addr:full":"60 W Union St Kingston PA 18704",
    "addr:housenumber":"60",
    "addr:postcode":"18704",
    "addr:street":"W Union St",
    "iso:country":"US",
    "sg:address":"60 W Union St",
    "sg:city":"Kingston",
    "sg:classifiers":[
        {
            "category":"Home & Garden",
            "subcategory":"Building Materials",
            "type":"Retail Goods"
        }
    ],
    "sg:phone":"+1 570 287 1163",
    "sg:postcode":"18704",
    "sg:province":"PA",
    "sg:tags":[
        "plumbing",
        "fixture",
        "supply"
    ],
    "wof:name":"Kingston Plumbing Supply Co",
    "wof:placetype":"venue"
},
  "geometry": {"coordinates":[-75.888989,41.274013],"type":"Point"}
}