{
  "type": "Feature",
  "properties": {
    "iso:country":"US",
    "sg:address":"4 Portland Rd",
    "sg:city":"Conshohocken",
    "sg:classifiers":[
        {
            "category":"Manufacturing",
            "subcategory":"Chemicals & Compounds",
            "type":"Manufacturing & Wholesale Goods"
        }
    ],
    "sg:phone":"+1 610 941 4900",
    "sg:postcode":"19428",
    "sg:province":"PA",
    "sg:tags":[
        "inorganic",
        "industrial"
    ],
    "sg:website":"www.paratherm.com",
    "wof:name":"Paratherm Corp",
    "wof:placetype":"venue"
},
  "geometry": {"coordinates":[-75.32735700000001,40.071106],"type":"Point"}
}