{
  "type": "Feature",
  "properties": {
    "iso:country":"US",
    "sg:address":"601 Seldon Ave",
    "sg:city":"Verona",
    "sg:classifiers":[
        {
            "category":"Manufacturing",
            "subcategory":"Rubber & Plastics",
            "type":"Manufacturing & Wholesale Goods"
        }
    ],
    "sg:phone":"+1 412 828 1111",
    "sg:postcode":"15147",
    "sg:province":"PA",
    "sg:tags":[
        "product",
        "bottle",
        "mfg"
    ],
    "wof:name":"Double R Enterprises",
    "wof:placetype":"venue"
},
  "geometry": {"coordinates":[-79.835708,40.510168],"type":"Point"}
}