{
  "type": "Feature",
  "properties": {
    "iso:country":"US",
    "sg:address":"4919 Jonestown Rd",
    "sg:city":"Harrisburg",
    "sg:classifiers":[
        {
            "category":"Professional",
            "type":"Services"
        }
    ],
    "sg:phone":"+1 717 652 8043",
    "sg:postcode":"17109",
    "sg:province":"PA",
    "sg:tags":[
        "establishment"
    ],
    "wof:name":"Pennsylvania Heavy & Highway",
    "wof:placetype":"venue"
},
  "geometry": {"coordinates":[-76.805468,40.306605],"type":"Point"}
}