{
  "type": "Feature",
  "properties": {
    "iso:country":"US",
    "sg:address":"1160 S Krocks Rd",
    "sg:city":"Wescosville",
    "sg:classifiers":[
        {
            "category":"Restaurant",
            "type":"Food & Drink"
        }
    ],
    "sg:phone":"+1 610 391 0648",
    "sg:postcode":"18106",
    "sg:province":"PA",
    "wof:name":"Krocks Pub",
    "wof:placetype":"venue"
},
  "geometry": {"coordinates":[-75.56817700000001,40.555397],"type":"Point"}
}