{
  "type": "Feature",
  "properties": {
    "addr:full":"3212 Pike St Harrisburg PA 17111",
    "addr:housenumber":"3212",
    "addr:postcode":"17111",
    "addr:street":"Pike St",
    "iso:country":"US",
    "sg:address":"3212 Pike St",
    "sg:city":"Harrisburg",
    "sg:classifiers":[
        {
            "category":"Wholesale",
            "subcategory":"Vending Machines",
            "type":"Manufacturing & Wholesale Goods"
        }
    ],
    "sg:phone":"+1   ",
    "sg:postcode":"17111",
    "sg:province":"PA",
    "sg:tags":[
        "operator"
    ],
    "wof:name":"Greenaway & Keller Vending Svc",
    "wof:placetype":"venue"
},
  "geometry": {"coordinates":[-76.837079,40.258969],"type":"Point"}
}