{
  "type": "Feature",
  "properties": {
    "iso:country":"US",
    "sg:address":"220 W Center St",
    "sg:city":"Meadville",
    "sg:classifiers":[
        {
            "category":"Organizations",
            "subcategory":"Community Association",
            "type":"Services"
        }
    ],
    "sg:phone":"+1 814 724 2128",
    "sg:postcode":"16335",
    "sg:province":"PA",
    "sg:tags":[
        "club",
        "social"
    ],
    "wof:name":"Taylor Hose Co",
    "wof:placetype":"venue"
},
  "geometry": {"coordinates":[-80.153443,41.639627],"type":"Point"}
}