{
  "type": "Feature",
  "properties": {
    "addr:full":"237 W Godfrey Ave Philadelphia PA 19120",
    "addr:housenumber":"237",
    "addr:postcode":"19120",
    "addr:street":"W Godfrey Ave",
    "iso:country":"US",
    "sg:address":"237 W Godfrey Ave",
    "sg:city":"Philadelphia",
    "sg:classifiers":[
        {
            "category":"Professional",
            "type":"Services"
        },
        {
            "category":"Personal",
            "type":"Services"
        },
        {
            "category":"Freight",
            "type":"Transportation"
        },
        {
            "category":"Transit Center",
            "subcategory":"Freight",
            "type":"Transportation"
        }
    ],
    "sg:phone":"+1 215 549 3477",
    "sg:postcode":"19120",
    "sg:province":"PA",
    "sg:tags":[
        "trucking-motor",
        "material",
        "trucking",
        "moving",
        "services-labor",
        "mover"
    ],
    "wof:name":"Gibsons Transport & Hauling Service",
    "wof:placetype":"venue"
},
  "geometry": {"coordinates":[-75.12430500000001,40.045112],"type":"Point"}
}