{
  "type": "Feature",
  "properties": {
    "iso:country":"US",
    "sg:address":"817 E Lawrence Ave",
    "sg:city":"Ellwood City",
    "sg:classifiers":[
        {
            "category":"Education",
            "subcategory":"Dance Studio",
            "type":"Public Place"
        }
    ],
    "sg:phone":"+1 724 758 3865",
    "sg:postcode":"16117",
    "sg:province":"PA",
    "sg:tags":[
        "instruction",
        "dancing"
    ],
    "wof:name":"Bette Baney's Dance Studio",
    "wof:placetype":"venue"
},
  "geometry": {"coordinates":[-80.292441,40.858349],"type":"Point"}
}