{
  "type": "Feature",
  "properties": {
    "addr:full":"750 Nittany Ridge Rd Howard PA 16841",
    "addr:housenumber":"750",
    "addr:postcode":"16841",
    "addr:street":"Nittany Ridge Rd",
    "iso:country":"US",
    "sg:address":"750 Nittany Ridge Rd",
    "sg:city":"Howard",
    "sg:classifiers":[
        {
            "category":"Recreation",
            "type":"Entertainment"
        }
    ],
    "sg:phone":"+1 814 383 4066",
    "sg:postcode":"16841",
    "sg:province":"PA",
    "sg:tags":[
        "archery",
        "range"
    ],
    "wof:name":"Black Eagle Bowmen Inc",
    "wof:placetype":"venue"
},
  "geometry": {"coordinates":[-77.577136,41.011183],"type":"Point"}
}