{
  "type": "Feature",
  "properties": {
    "iso:country":"US",
    "sg:address":"140 Mingo Rd",
    "sg:city":"Wexford",
    "sg:classifiers":[
        {
            "category":"Building & Trades",
            "subcategory":"Plumbing",
            "type":"Services"
        }
    ],
    "sg:phone":"+1 724 933 8011",
    "sg:postcode":"15090",
    "sg:province":"PA",
    "wof:name":"Brolley & Schmitt Plumbing",
    "wof:placetype":"venue"
},
  "geometry": {"coordinates":[-80.090698,40.616798],"type":"Point"}
}