{
  "type": "Feature",
  "properties": {
    "iso:country":"US",
    "sg:address":"226 Market St",
    "sg:city":"Sunbury",
    "sg:classifiers":[
        {
            "category":"Restaurant",
            "type":"Food & Drink"
        }
    ],
    "sg:menulink":"http://www.allmenus.com/pa/sunbury/133573-subway/menu/",
    "sg:phone":"+1 570 955 7827",
    "sg:postcode":"17801",
    "sg:province":"PA",
    "sg:tags":[
        "american",
        "sandwich"
    ],
    "wof:name":"Subway",
    "wof:placetype":"venue"
},
  "geometry": {"coordinates":[-76.79413700000001,40.862235],"type":"Point"}
}