{
  "type": "Feature",
  "properties": {
    "iso:country":"US",
    "sg:address":"1315 Frosty Hollow Rd",
    "sg:city":"Levittown",
    "sg:classifiers":[
        {
            "category":"Health Services",
            "subcategory":"Doctor",
            "type":"Services"
        }
    ],
    "sg:phone":"+1 215 547 3973",
    "sg:postcode":"19056",
    "sg:province":"PA",
    "sg:tags":[
        "surgeon",
        "oral"
    ],
    "wof:name":"Larkin Edward T Jr DDS",
    "wof:placetype":"venue"
},
  "geometry": {"coordinates":[-74.88200399999999,40.1478],"type":"Point"}
}