{
  "type": "Feature",
  "properties": {
    "iso:country":"US",
    "sg:address":"266 Frazier Rd",
    "sg:city":"Buffalo Mills",
    "sg:classifiers":[
        {
            "category":"Farming",
            "subcategory":"Dairy Farm",
            "type":"Manufacturing & Wholesale Goods"
        }
    ],
    "sg:phone":"+1   ",
    "sg:postcode":"15534",
    "sg:province":"PA",
    "wof:name":"Frazier Farms",
    "wof:placetype":"venue"
},
  "geometry": {"coordinates":[-78.75335800000001,39.908946],"type":"Point"}
}