{
  "type": "Feature",
  "properties": {
    "addr:full":"6027 Library Rd Bethel Park PA 15102",
    "addr:housenumber":"6027",
    "addr:postcode":"15102",
    "addr:street":"Library Rd",
    "iso:country":"US",
    "sg:address":"6027 Library Rd",
    "sg:city":"Bethel Park",
    "sg:classifiers":[
        {
            "category":"Social Services",
            "subcategory":"Adult Care",
            "type":"Services"
        }
    ],
    "sg:phone":"+1   ",
    "sg:postcode":"15102",
    "sg:province":"PA",
    "sg:tags":[
        "residential"
    ],
    "wof:name":"Wesley Penn Residence",
    "wof:placetype":"venue"
},
  "geometry": {"coordinates":[-80.030445,40.303004],"type":"Point"}
}