{
  "type": "Feature",
  "properties": {
    "iso:country":"US",
    "sg:address":"401 S Main St",
    "sg:city":"Zelienople",
    "sg:classifiers":[
        {
            "category":"Organizations",
            "subcategory":"Religious Organization",
            "type":"Services"
        }
    ],
    "sg:phone":"+1   ",
    "sg:postcode":"16063",
    "sg:province":"PA",
    "wof:name":"Seaman Mem Evang Lthran Church",
    "wof:placetype":"venue"
},
  "geometry": {"coordinates":[-80.13617000000001,40.791423],"type":"Point"}
}