{
  "type": "Feature",
  "properties": {
    "iso:country":"US",
    "sg:address":"499 Constitution Ave",
    "sg:city":"Perkasie",
    "sg:classifiers":[
        {
            "category":"Manufacturing",
            "subcategory":"Rubber & Plastics",
            "type":"Manufacturing & Wholesale Goods"
        }
    ],
    "sg:phone":"+1 215 257 6581",
    "sg:postcode":"18944",
    "sg:province":"PA",
    "sg:tags":[
        "plastics-vacuum",
        "plastics-fabricating",
        "pressure",
        "forming-manufacturers",
        "decorating",
        "finishing"
    ],
    "wof:name":"Perkasie Industries Corp",
    "wof:placetype":"venue"
},
  "geometry": {"coordinates":[-75.298186,40.364431],"type":"Point"}
}