{
  "type": "Feature",
  "properties": {
    "iso:country":"US",
    "sg:address":"301 Cumberland Hwy",
    "sg:city":"Berlin",
    "sg:classifiers":[
        {
            "category":"Restaurant",
            "type":"Food & Drink"
        }
    ],
    "sg:menulink":"http://www.allmenus.com/pa/berlin/133334-subway/menu/",
    "sg:phone":"+1 814 267 6376",
    "sg:postcode":"15530",
    "sg:province":"PA",
    "sg:tags":[
        "american",
        "sandwich"
    ],
    "wof:name":"Subway",
    "wof:placetype":"venue"
},
  "geometry": {"coordinates":[-78.95280700000001,39.917146],"type":"Point"}
}