{
  "type": "Feature",
  "properties": {
    "addr:full":"81 Old Racetrack Rd Coatesville PA 19320",
    "addr:housenumber":"81",
    "addr:postcode":"19320",
    "addr:street":"Old Racetrack Rd",
    "iso:country":"US",
    "sg:address":"81 Old Racetrack Rd",
    "sg:city":"Coatesville",
    "sg:classifiers":[
        {
            "category":"Farming",
            "subcategory":"Poultry Farm",
            "type":"Manufacturing & Wholesale Goods"
        }
    ],
    "sg:phone":"+1   ",
    "sg:postcode":"19320",
    "sg:province":"PA",
    "sg:tags":[
        "egg"
    ],
    "wof:name":"David Lantz",
    "wof:placetype":"venue"
},
  "geometry": {"coordinates":[-75.89708899999999,39.929708],"type":"Point"}
}