{
  "type": "Feature",
  "properties": {
    "iso:country":"US",
    "sg:address":"110 Old York Rd",
    "sg:city":"New Cumberland",
    "sg:classifiers":[
        {
            "category":"Cinema",
            "subcategory":"Movie Rental",
            "type":"Entertainment"
        }
    ],
    "sg:phone":"+1   ",
    "sg:postcode":"17070",
    "sg:province":"PA",
    "sg:tags":[
        "video",
        "tape"
    ],
    "wof:name":"M G A Inc",
    "wof:placetype":"venue"
},
  "geometry": {"coordinates":[-76.860135,40.219264],"type":"Point"}
}