{
  "type": "Feature",
  "properties": {
    "iso:country":"US",
    "sg:address":"340 Poplar St",
    "sg:city":"Hanover",
    "sg:classifiers":[
        {
            "category":"Shopping",
            "subcategory":"Clothing, Apparel, & Fashions",
            "type":"Retail Goods"
        }
    ],
    "sg:phone":"+1 717 633 3343",
    "sg:postcode":"17331",
    "sg:province":"PA",
    "wof:name":"Fashion Galaxy",
    "wof:placetype":"venue"
},
  "geometry": {"coordinates":[-76.99392,39.798596],"type":"Point"}
}