{
  "type": "Feature",
  "properties": {
    "addr:full":"115 Broadway Hanover PA 17331",
    "addr:housenumber":"115",
    "addr:postcode":"17331",
    "addr:street":"Broadway",
    "iso:country":"US",
    "sg:address":"115 Broadway",
    "sg:city":"Hanover",
    "sg:classifiers":[
        {
            "category":"Shopping",
            "subcategory":"Jewelry",
            "type":"Retail Goods"
        }
    ],
    "sg:phone":"+1 717 632 4244",
    "sg:postcode":"17331",
    "sg:province":"PA",
    "sg:tags":[
        "jeweler"
    ],
    "wof:name":"Smith Jewelers",
    "wof:placetype":"venue"
},
  "geometry": {"coordinates":[-76.982507,39.801],"type":"Point"}
}