{
  "type": "Feature",
  "properties": {
    "iso:country":"US",
    "sg:address":"1513 Ben Franklin Hwy",
    "sg:city":"Douglassville",
    "sg:classifiers":[
        {
            "category":"Manufacturing",
            "subcategory":"Glass & Minerals",
            "type":"Manufacturing & Wholesale Goods"
        }
    ],
    "sg:phone":"+1 610 323 0700",
    "sg:postcode":"19518",
    "sg:province":"PA",
    "sg:tags":[
        "concrete",
        "brick",
        "prod",
        "block"
    ],
    "sg:website":"www.universalconcrete.com",
    "wof:name":"Universal Concrete Prods",
    "wof:placetype":"venue"
},
  "geometry": {"coordinates":[-75.70697199999999,40.251427],"type":"Point"}
}