{
  "type": "Feature",
  "properties": {
    "iso:country":"US",
    "sg:address":"28 Main St",
    "sg:city":"Bradford",
    "sg:classifiers":[
        {
            "category":"Communications",
            "subcategory":"Film & Video Production",
            "type":"Services"
        }
    ],
    "sg:phone":"+1 814 362 4489",
    "sg:postcode":"16701",
    "sg:province":"PA",
    "sg:tags":[
        "motion",
        "picture",
        "taping"
    ],
    "sg:website":"www.apvideo.com",
    "wof:name":"Allegheny Productions",
    "wof:placetype":"venue"
},
  "geometry": {"coordinates":[-78.65001100000001,41.955805],"type":"Point"}
}