{
  "type": "Feature",
  "properties": {
    "addr:full":"2179 Bennett Rd Philadelphia PA 19116",
    "addr:housenumber":"2179",
    "addr:postcode":"19116",
    "addr:street":"Bennett Rd",
    "iso:country":"US",
    "sg:address":"2179 Bennett Rd",
    "sg:city":"Philadelphia",
    "sg:classifiers":[
        {
            "category":"Manufacturing",
            "subcategory":"Tools & Machinery",
            "type":"Manufacturing & Wholesale Goods"
        }
    ],
    "sg:phone":"+1 215 671 0612",
    "sg:postcode":"19116",
    "sg:province":"PA",
    "sg:tags":[
        "optical"
    ],
    "wof:name":"Laser Labs",
    "wof:placetype":"venue"
},
  "geometry": {"coordinates":[-75.00611000000001,40.106005],"type":"Point"}
}