{
  "type": "Feature",
  "properties": {
    "addr:full":"4245 Steubenville Pike Pittsburgh PA 15205",
    "addr:housenumber":"4245",
    "addr:postcode":"15205",
    "addr:street":"Steubenville Pike",
    "iso:country":"US",
    "sg:address":"4245 Steubenville Pike",
    "sg:city":"Pittsburgh",
    "sg:classifiers":[
        {
            "category":"Health Services",
            "subcategory":"Dentist",
            "type":"Services"
        }
    ],
    "sg:phone":"+1 412 922 2171",
    "sg:postcode":"15205",
    "sg:province":"PA",
    "wof:name":"Bott Robert DMD",
    "wof:placetype":"venue"
},
  "geometry": {"coordinates":[-80.0933,40.440701],"type":"Point"}
}