{
  "type": "Feature",
  "properties": {
    "iso:country":"US",
    "sg:address":"900 Waggoners Gap Rd",
    "sg:city":"Carlisle",
    "sg:classifiers":[
        {
            "category":"Education",
            "subcategory":"School",
            "type":"Public Place"
        }
    ],
    "sg:phone":"+1 717 240 6740",
    "sg:postcode":"17013",
    "sg:province":"PA",
    "sg:website":"www.carlisle.org",
    "wof:name":"Wilson Middle School",
    "wof:placetype":"venue"
},
  "geometry": {"coordinates":[-77.20725299999999,40.216184],"type":"Point"}
}