{
  "type": "Feature",
  "properties": {
    "addr:full":"735 Muncpl Pittsburgh PA 15233",
    "addr:housenumber":"735",
    "addr:postcode":"15233",
    "addr:street":"Muncpl",
    "iso:country":"US",
    "sg:address":"735 Muncpl",
    "sg:city":"Pittsburgh",
    "sg:classifiers":[
        {
            "category":"Building & Trades",
            "subcategory":"Construction",
            "type":"Services"
        }
    ],
    "sg:phone":"+1 412 771 7974",
    "sg:postcode":"15233",
    "sg:province":"PA",
    "sg:tags":[
        "contractor"
    ],
    "wof:name":"Ray Rowe Radon Mitigation & Basement De-Watering",
    "wof:placetype":"venue"
},
  "geometry": {"coordinates":[-80.02359800000001,40.452599],"type":"Point"}
}