{
  "type": "Feature",
  "properties": {
    "iso:country":"US",
    "sg:address":"1653 The Fairway",
    "sg:city":"Jenkintown",
    "sg:classifiers":[
        {
            "category":"Professional",
            "subcategory":"Lawyer & Legal Services",
            "type":"Services"
        }
    ],
    "sg:phone":"+1 215 887 7887",
    "sg:postcode":"19046",
    "sg:province":"PA",
    "sg:tags":[
        "attorney"
    ],
    "wof:name":"Marcia B Aronow",
    "wof:placetype":"venue"
},
  "geometry": {"coordinates":[-75.11762899999999,40.106643],"type":"Point"}
}