{
  "type": "Feature",
  "properties": {
    "iso:country":"US",
    "sg:address":"26 Bridge St",
    "sg:city":"Stroudsburg",
    "sg:classifiers":[
        {
            "category":"Real Estate",
            "subcategory":"Real Estate Operator",
            "type":"Services"
        }
    ],
    "sg:phone":"+1   ",
    "sg:postcode":"18360",
    "sg:province":"PA",
    "sg:tags":[
        "building",
        "apartment"
    ],
    "wof:name":"Bridge Street Apartments Inc",
    "wof:placetype":"venue"
},
  "geometry": {"coordinates":[-75.225368,40.985355],"type":"Point"}
}