{
  "type": "Feature",
  "properties": {
    "addr:full":"3901 Pennsgrove St Philadelphia PA 19104",
    "addr:housenumber":"3901",
    "addr:postcode":"19104",
    "addr:street":"Pennsgrove St",
    "iso:country":"US",
    "sg:address":"3901 Pennsgrove St",
    "sg:city":"Philadelphia",
    "sg:classifiers":[
        {
            "category":"Food & Beverages",
            "subcategory":"Groceries & Convenience Stores",
            "type":"Retail Goods"
        }
    ],
    "sg:phone":"+1 215 222 6055",
    "sg:postcode":"19104",
    "sg:province":"PA",
    "wof:name":"Felix Deli & Grocery",
    "wof:placetype":"venue"
},
  "geometry": {"coordinates":[-75.201401,39.971901],"type":"Point"}
}