{
  "type": "Feature",
  "properties": {
    "addr:full":"116 Ruthland Ave Malvern PA 19355",
    "addr:housenumber":"116",
    "addr:postcode":"19355",
    "addr:street":"Ruthland Ave",
    "iso:country":"US",
    "sg:address":"116 Ruthland Ave",
    "sg:city":"Malvern",
    "sg:classifiers":[
        {
            "category":"Government",
            "subcategory":"Office",
            "type":"Public Place"
        }
    ],
    "sg:phone":"+1 610 644 1819",
    "sg:postcode":"19355",
    "sg:province":"PA",
    "sg:tags":[
        "village"
    ],
    "wof:name":"Malvern Pumping Station",
    "wof:placetype":"venue"
},
  "geometry": {"coordinates":[-75.50645799999999,40.035088],"type":"Point"}
}