{
  "type": "Feature",
  "properties": {
    "iso:country":"US",
    "sg:address":"720 W Lackawanna Ave",
    "sg:city":"Olyphant",
    "sg:classifiers":[
        {
            "category":"Building & Trades",
            "subcategory":"Construction",
            "type":"Services"
        }
    ],
    "sg:phone":"+1   ",
    "sg:postcode":"18447",
    "sg:province":"PA",
    "wof:name":"Sheridan Sealing Co",
    "wof:placetype":"venue"
},
  "geometry": {"coordinates":[-75.609099,41.472357],"type":"Point"}
}