{
  "type": "Feature",
  "properties": {
    "iso:country":"US",
    "sg:address":"214 E Park Rd",
    "sg:city":"Havertown",
    "sg:classifiers":[
        {
            "category":"Building & Trades",
            "subcategory":"Plumbing",
            "type":"Services"
        },
        {
            "category":"Building & Trades",
            "subcategory":"Construction",
            "type":"Services"
        }
    ],
    "sg:phone":"+1 610 446 7757",
    "sg:postcode":"19083",
    "sg:province":"PA",
    "sg:tags":[
        "mechanical",
        "plumber",
        "industrial",
        "contractors-commercial",
        "contractor"
    ],
    "wof:name":"Frank X Mccrossin Plumbing &H",
    "wof:placetype":"venue"
},
  "geometry": {"coordinates":[-75.292282,39.970661],"type":"Point"}
}