{
  "type": "Feature",
  "properties": {
    "iso:country":"US",
    "sg:address":"14242 Flatts Rd",
    "sg:city":"Waterford",
    "sg:classifiers":[
        {
            "category":"Mining & Drilling",
            "type":"Manufacturing & Wholesale Goods"
        }
    ],
    "sg:phone":"+1 814 796 6702",
    "sg:postcode":"16441",
    "sg:province":"PA",
    "sg:tags":[
        "development",
        "gas",
        "oil",
        "exploration"
    ],
    "wof:name":"Energy Corp Of America",
    "wof:placetype":"venue"
},
  "geometry": {"coordinates":[-79.97190500000001,41.887469],"type":"Point"}
}