{
  "type": "Feature",
  "properties": {
    "iso:country":"US",
    "sg:address":"1744 Dekalb Pike",
    "sg:city":"Blue Bell",
    "sg:classifiers":[
        {
            "category":"Professional",
            "subcategory":"Management & Consulting",
            "type":"Services"
        }
    ],
    "sg:phone":"+1 215 872 0605",
    "sg:postcode":"19422",
    "sg:province":"PA",
    "sg:tags":[
        "planning",
        "business",
        "strategic"
    ],
    "wof:name":"Fundableplans",
    "wof:placetype":"venue"
},
  "geometry": {"coordinates":[-75.30636800000001,40.150386],"type":"Point"}
}