{
  "type": "Feature",
  "properties": {
    "iso:country":"US",
    "sg:address":"197 Parmer Dr",
    "sg:city":"Halifax",
    "sg:classifiers":[
        {
            "category":"Professional",
            "subcategory":"Detective & Security Services",
            "type":"Services"
        }
    ],
    "sg:phone":"+1 717 896 8641",
    "sg:postcode":"17032",
    "sg:province":"PA",
    "sg:tags":[
        "guard",
        "patrol"
    ],
    "wof:name":"Wirrick Associates",
    "wof:placetype":"venue"
},
  "geometry": {"coordinates":[-76.91995900000001,40.446324],"type":"Point"}
}