{
  "type": "Feature",
  "properties": {
    "iso:country":"US",
    "sg:address":"401 E Main St",
    "sg:city":"Macungie",
    "sg:classifiers":[
        {
            "category":"Manufacturing",
            "subcategory":"Rubber & Plastics",
            "type":"Manufacturing & Wholesale Goods"
        },
        {
            "category":"Autos & Motor Vehicles",
            "subcategory":"Auto Supplies",
            "type":"Retail Goods"
        },
        {
            "category":"Retail",
            "subcategory":"Auto Repair",
            "type":"Services"
        }
    ],
    "sg:phone":"+1 610 967 1900",
    "sg:postcode":"18062",
    "sg:province":"PA",
    "sg:tags":[
        "recap",
        "retread",
        "tires-wholesale",
        "tire",
        "manufacturer"
    ],
    "sg:website":"http://www.coopertire.com/html/",
    "wof:name":"Jeff's Auto Serv Cntr Inc",
    "wof:placetype":"venue"
},
  "geometry": {"coordinates":[-75.549522,40.512699],"type":"Point"}
}