{
  "type": "Feature",
  "properties": {
    "iso:country":"US",
    "sg:address":"1671 Louser Rd",
    "sg:city":"Annville",
    "sg:classifiers":[
        {
            "category":"Retail",
            "subcategory":"Pet Boarding",
            "type":"Services"
        }
    ],
    "sg:phone":"+1 717 867 0742",
    "sg:postcode":"17003",
    "sg:province":"PA",
    "sg:tags":[
        "boarding/pet",
        "sitting"
    ],
    "wof:name":"Limestone Ridge Kennel",
    "wof:placetype":"venue"
},
  "geometry": {"coordinates":[-76.547096,40.289101],"type":"Point"}
}