{
  "type": "Feature",
  "properties": {
    "addr:full":"2729 Germantown Ave Philadelphia PA 19133",
    "addr:housenumber":"2729",
    "addr:postcode":"19133",
    "addr:street":"Germantown Ave",
    "iso:country":"US",
    "sg:address":"2729 Germantown Ave",
    "sg:city":"Philadelphia",
    "sg:classifiers":[
        {
            "category":"Shopping",
            "subcategory":"Jewelry",
            "type":"Retail Goods"
        }
    ],
    "sg:phone":"+1 215 221 0866",
    "sg:postcode":"19133",
    "sg:province":"PA",
    "sg:tags":[
        "jeweler"
    ],
    "wof:name":"Germantown Jewelry",
    "wof:placetype":"venue"
},
  "geometry": {"coordinates":[-75.147797,39.9939],"type":"Point"}
}