{
  "type": "Feature",
  "properties": {
    "iso:country":"US",
    "sg:address":"603 Pennsylvania Ave",
    "sg:city":"Matamoras",
    "sg:classifiers":[
        {
            "category":"Personal",
            "subcategory":"Beauty Salon",
            "type":"Services"
        }
    ],
    "sg:phone":"+1 570 491 4214",
    "sg:postcode":"18336",
    "sg:province":"PA",
    "wof:name":"Beauty Box",
    "wof:placetype":"venue"
},
  "geometry": {"coordinates":[-74.702742,41.36661],"type":"Point"}
}