{
  "type": "Feature",
  "properties": {
    "addr:full":"6238 Ridge Ave Philadelphia PA 19128",
    "addr:housenumber":"6238",
    "addr:postcode":"19128",
    "addr:street":"Ridge Ave",
    "iso:country":"US",
    "sg:address":"6238 Ridge Ave",
    "sg:city":"Philadelphia",
    "sg:phone":"+1 215 483 8000",
    "sg:postcode":"19128",
    "sg:province":"PA",
    "wof:name":"Euphoria Hair Salon",
    "wof:placetype":"venue"
},
  "geometry": {"coordinates":[-75.21803800000001,40.03627],"type":"Point"}
}