{
  "type": "Feature",
  "properties": {
    "iso:country":"US",
    "sg:address":"632 Radnor St",
    "sg:city":"Harrisburg",
    "sg:classifiers":[
        {
            "category":"Building & Trades",
            "subcategory":"Construction",
            "type":"Services"
        }
    ],
    "sg:phone":"+1 717 233 0960",
    "sg:postcode":"17110",
    "sg:province":"PA",
    "sg:tags":[
        "builder",
        "deck"
    ],
    "wof:name":"Brady Enterprises",
    "wof:placetype":"venue"
},
  "geometry": {"coordinates":[-76.89277,40.289039],"type":"Point"}
}