{
  "type": "Feature",
  "properties": {
    "addr:full":"2560 W Chester Pike  Broomall PA 19008",
    "addr:housenumber":"2560",
    "addr:postcode":"19008",
    "addr:street":"W Chester Pike",
    "iso:country":"US",
    "sg:address":"2560 W Chester Pike ",
    "sg:city":"Broomall",
    "sg:classifiers":[
        {
            "category":"Bakery",
            "type":"Food & Drink"
        }
    ],
    "sg:menulink":"http://www.allmenus.com/pa/marple/289256-country-squire-diner/menu/",
    "sg:phone":"+1 610 353 0550",
    "sg:postcode":"19008",
    "sg:province":"PA",
    "sg:tags":[
        "american",
        "pastry"
    ],
    "wof:name":"Country Squire Diner",
    "wof:placetype":"venue"
},
  "geometry": {"coordinates":[-75.35960900000001,39.981427],"type":"Point"}
}