{
  "type": "Feature",
  "properties": {
    "iso:country":"US",
    "sg:address":"3933 Perrysville Ave",
    "sg:city":"Pittsburgh",
    "sg:classifiers":[
        {
            "category":"Professional",
            "subcategory":"Art Services",
            "type":"Services"
        }
    ],
    "sg:phone":"+1 412 321 0879",
    "sg:postcode":"15214",
    "sg:province":"PA",
    "sg:tags":[
        "marketing",
        "graphic",
        "design",
        "solution",
        "designer"
    ],
    "sg:website":"www.spdesign.net",
    "wof:name":"Scott Pipitone Design Ltd",
    "wof:placetype":"venue"
},
  "geometry": {"coordinates":[-80.01978800000001,40.490932],"type":"Point"}
}