{
  "type": "Feature",
  "properties": {
    "iso:country":"US",
    "sg:address":"119 James St",
    "sg:city":"North Versailles",
    "sg:classifiers":[
        {
            "category":"Shopping",
            "type":"Retail Goods"
        }
    ],
    "sg:phone":"+1 412 823 5399",
    "sg:postcode":"15137",
    "sg:province":"PA",
    "sg:tags":[
        "wedding",
        "supply"
    ],
    "wof:name":"Lacko Brothers Disc Jockeys",
    "wof:placetype":"venue"
},
  "geometry": {"coordinates":[-79.812077,40.373144],"type":"Point"}
}