{
  "type": "Feature",
  "properties": {
    "addr:full":"2907 Mannerchor Rd Temple PA 19560",
    "addr:housenumber":"2907",
    "addr:postcode":"19560",
    "addr:street":"Mannerchor Rd",
    "iso:country":"US",
    "sg:address":"2907 Mannerchor Rd",
    "sg:city":"Temple",
    "sg:classifiers":[
        {
            "category":"Home & Garden",
            "subcategory":"Building Materials",
            "type":"Retail Goods"
        },
        {
            "category":"Building & Trades",
            "subcategory":"Construction",
            "type":"Services"
        }
    ],
    "sg:phone":"+1 610 921 2201",
    "sg:postcode":"19560",
    "sg:province":"PA",
    "sg:tags":[
        "installation",
        "windows-repair",
        "builder",
        "window",
        "awning",
        "canopy",
        "gazebo",
        "patio",
        "replacement"
    ],
    "sg:website":"http://www.aluminumassociatessloancorp.com",
    "wof:name":"Aluminum Associates-Sloan Corp",
    "wof:placetype":"venue"
},
  "geometry": {"coordinates":[-75.905604,40.385039],"type":"Point"}
}