{
  "type": "Feature",
  "properties": {
    "addr:full":"1458 Buck Rd Holland PA 18966",
    "addr:housenumber":"1458",
    "addr:postcode":"18966",
    "addr:street":"Buck Rd",
    "iso:country":"US",
    "sg:address":"1458 Buck Rd",
    "sg:city":"Holland",
    "sg:classifiers":[
        {
            "category":"Personal",
            "subcategory":"Beauty Salon",
            "type":"Services"
        }
    ],
    "sg:phone":"+1 215 968 0555",
    "sg:postcode":"18966",
    "sg:province":"PA",
    "sg:tags":[
        "hair"
    ],
    "wof:name":"Stars Hair Salon",
    "wof:placetype":"venue"
},
  "geometry": {"coordinates":[-74.95308900000001,40.205735],"type":"Point"}
}