{
  "type": "Feature",
  "properties": {
    "iso:country":"US",
    "sg:address":"440 Green Ln Apt 2",
    "sg:city":"Philadelphia",
    "sg:classifiers":[
        {
            "category":"Building & Trades",
            "subcategory":"Construction",
            "type":"Services"
        }
    ],
    "sg:phone":"+1 215 880 7952",
    "sg:postcode":"19128",
    "sg:province":"PA",
    "sg:tags":[
        "wallcoverings-installation",
        "wallpaper",
        "painting",
        "contractor"
    ],
    "wof:name":"Bella Painting",
    "wof:placetype":"venue"
},
  "geometry": {"coordinates":[-75.21773,40.032903],"type":"Point"}
}