{
  "type": "Feature",
  "properties": {
    "iso:country":"US",
    "sg:address":"1075 Specktown Rd",
    "sg:city":"Lykens",
    "sg:classifiers":[
        {
            "category":"Retail",
            "subcategory":"Repair Shop",
            "type":"Services"
        }
    ],
    "sg:phone":"+1 717 365 3285",
    "sg:postcode":"17048",
    "sg:province":"PA",
    "sg:tags":[
        "clocks",
        "parts"
    ],
    "wof:name":"Ray Ferster Watch & Clock Rpr",
    "wof:placetype":"venue"
},
  "geometry": {"coordinates":[-76.74195,40.600525],"type":"Point"}
}