{
  "type": "Feature",
  "properties": {
    "addr:full":"101 New St Rockton PA 15801",
    "addr:housenumber":"101",
    "addr:postcode":"15801",
    "addr:street":"New St",
    "iso:country":"US",
    "sg:address":"101 New St",
    "sg:city":"Rockton",
    "sg:classifiers":[
        {
            "category":"Home & Garden",
            "subcategory":"Furniture",
            "type":"Retail Goods"
        }
    ],
    "sg:phone":"+1   ",
    "sg:postcode":"15801",
    "sg:province":"PA",
    "wof:name":"Steeple Furniture",
    "wof:placetype":"venue"
},
  "geometry": {"coordinates":[-78.764107,41.121798],"type":"Point"}
}