{
  "type": "Feature",
  "properties": {
    "iso:country":"US",
    "sg:address":"113 Sheeley Rd",
    "sg:city":"Kersey",
    "sg:classifiers":[
        {
            "category":"Real Estate",
            "subcategory":"Real Estate Agent",
            "type":"Services"
        }
    ],
    "sg:phone":"+1   ",
    "sg:postcode":"15846",
    "sg:province":"PA",
    "wof:name":"Sheeley Real Estate & Excav",
    "wof:placetype":"venue"
},
  "geometry": {"coordinates":[-78.609835,41.364005],"type":"Point"}
}