{
  "type": "Feature",
  "properties": {
    "iso:country":"US",
    "sg:address":"110 E Brookhaven Rd",
    "sg:city":"Wallingford",
    "sg:classifiers":[
        {
            "category":"Place Of Worship",
            "subcategory":"Church",
            "type":"Public Place"
        },
        {
            "category":"Place Of Worship",
            "type":"Public Place"
        }
    ],
    "sg:phone":"+1 610 566 1644",
    "sg:postcode":"19086",
    "sg:province":"PA",
    "sg:tags":[
        "churches-presbyterian-arp",
        "churches-presbyterian"
    ],
    "wof:name":"Wallingford Presbyterian Church",
    "wof:placetype":"venue"
},
  "geometry": {"coordinates":[-75.368347,39.902672],"type":"Point"}
}