{
  "type": "Feature",
  "properties": {
    "iso:country":"US",
    "sg:address":"330 W Bridge St",
    "sg:city":"New Hope",
    "sg:classifiers":[
        {
            "category":"Personal",
            "subcategory":"Beauty Salon",
            "type":"Services"
        }
    ],
    "sg:phone":"+1 215 862 0100",
    "sg:postcode":"18938",
    "sg:province":"PA",
    "sg:tags":[
        "nail",
        "manicuring"
    ],
    "wof:name":"Flemington Nails Three",
    "wof:placetype":"venue"
},
  "geometry": {"coordinates":[-74.965103,40.363602],"type":"Point"}
}