{
  "type": "Feature",
  "properties": {
    "iso:country":"US",
    "sg:address":"1903 W 26th St",
    "sg:city":"Erie",
    "sg:classifiers":[
        {
            "category":"Personal",
            "subcategory":"Beauty Salon",
            "type":"Services"
        }
    ],
    "sg:phone":"+1 814 455 5501",
    "sg:postcode":"16508",
    "sg:province":"PA",
    "sg:tags":[
        "shop"
    ],
    "wof:name":"Simply Red Beauty Salon",
    "wof:placetype":"venue"
},
  "geometry": {"coordinates":[-80.116632,42.095948],"type":"Point"}
}