{
  "type": "Feature",
  "properties": {
    "addr:full":"100 Shoen Rd Exton PA 19341",
    "addr:housenumber":"100",
    "addr:postcode":"19341",
    "addr:street":"Shoen Rd",
    "iso:country":"US",
    "sg:address":"100 Shoen Rd",
    "sg:city":"Exton",
    "sg:classifiers":[
        {
            "category":"Food & Beverages",
            "subcategory":"Meat & Fish",
            "type":"Retail Goods"
        }
    ],
    "sg:phone":"+1   ",
    "sg:postcode":"19341",
    "sg:province":"PA",
    "sg:tags":[
        "market"
    ],
    "wof:name":"Hills Quality Seafood Markets",
    "wof:placetype":"venue"
},
  "geometry": {"coordinates":[-75.63484699999999,40.039778],"type":"Point"}
}