{
  "type": "Feature",
  "properties": {
    "iso:country":"US",
    "sg:address":"447 N Felton St",
    "sg:city":"Philadelphia",
    "sg:classifiers":[
        {
            "category":"Building & Trades",
            "subcategory":"Construction",
            "type":"Services"
        }
    ],
    "sg:phone":"+1 215 471 5990",
    "sg:postcode":"19151",
    "sg:province":"PA",
    "sg:tags":[
        "work",
        "welder",
        "sub",
        "iron",
        "welding"
    ],
    "sg:website":"http://www.fwbwelding.com",
    "wof:name":"F W B & Son's Welding",
    "wof:placetype":"venue"
},
  "geometry": {"coordinates":[-75.244265,39.969424],"type":"Point"}
}