{
  "type": "Feature",
  "properties": {
    "iso:country":"US",
    "sg:address":"550 Township Line Rd",
    "sg:city":"Plymouth Meeting",
    "sg:classifiers":[
        {
            "category":"Shopping",
            "subcategory":"Clothing, Apparel, & Fashions",
            "type":"Retail Goods"
        }
    ],
    "sg:phone":"+1 610 828 7006",
    "sg:postcode":"19462",
    "sg:province":"PA",
    "sg:tags":[
        "accessory"
    ],
    "wof:name":"Happy Name Belt",
    "wof:placetype":"venue"
},
  "geometry": {"coordinates":[-75.27024299999999,40.127452],"type":"Point"}
}