{
  "type": "Feature",
  "properties": {
    "addr:full":"517 Derwyn Rd Drexel Hill PA 19026",
    "addr:housenumber":"517",
    "addr:postcode":"19026",
    "addr:street":"Derwyn Rd",
    "iso:country":"US",
    "sg:address":"517 Derwyn Rd",
    "sg:city":"Drexel Hill",
    "sg:classifiers":[
        {
            "category":"Professional",
            "type":"Services"
        }
    ],
    "sg:phone":"+1   ",
    "sg:postcode":"19026",
    "sg:province":"PA",
    "wof:name":"Pat Goode",
    "wof:placetype":"venue"
},
  "geometry": {"coordinates":[-75.287881,39.953834],"type":"Point"}
}