{
  "type": "Feature",
  "properties": {
    "iso:country":"US",
    "sg:address":"1717 Kuntz Rd",
    "sg:city":"Erie",
    "sg:phone":"+1 814 868 4681",
    "sg:postcode":"16509",
    "sg:province":"PA",
    "wof:name":"Granada Apartments",
    "wof:placetype":"venue"
},
  "geometry": {"coordinates":[-80.08964400000001,42.067471],"type":"Point"}
}