{
  "type": "Feature",
  "properties": {
    "iso:country":"US",
    "sg:address":"829 N 19th St",
    "sg:city":"Allentown",
    "sg:classifiers":[
        {
            "category":"Professional",
            "subcategory":"Accounting & Tax Preparation",
            "type":"Services"
        }
    ],
    "sg:phone":"+1 610 439 1422",
    "sg:postcode":"18104",
    "sg:province":"PA",
    "sg:tags":[
        "accountant"
    ],
    "wof:name":"Sowers & Conway",
    "wof:placetype":"venue"
},
  "geometry": {"coordinates":[-75.502403,40.607601],"type":"Point"}
}