{
  "type": "Feature",
  "properties": {
    "iso:country":"US",
    "sg:address":"15 Mount Lebanon Blvd",
    "sg:city":"Pittsburgh",
    "sg:classifiers":[
        {
            "category":"Real Estate",
            "subcategory":"Real Estate Agent",
            "type":"Services"
        }
    ],
    "sg:phone":"+1   ",
    "sg:postcode":"15228",
    "sg:province":"PA",
    "wof:name":"Mary Dunn Realtor",
    "wof:placetype":"venue"
},
  "geometry": {"coordinates":[-80.046099,40.363466],"type":"Point"}
}