{
  "type": "Feature",
  "properties": {
    "iso:country":"US",
    "sg:address":"5556 Warrensville Rd",
    "sg:city":"Montoursville",
    "sg:classifiers":[
        {
            "category":"Government",
            "subcategory":"Fire Station",
            "type":"Public Place"
        }
    ],
    "sg:phone":"+1   ",
    "sg:postcode":"17754",
    "sg:province":"PA",
    "sg:tags":[
        "protection"
    ],
    "wof:name":"Eldred Twp Vol Fire Co",
    "wof:placetype":"venue"
},
  "geometry": {"coordinates":[-76.945735,41.322153],"type":"Point"}
}