{
  "type": "Feature",
  "properties": {
    "iso:country":"US",
    "sg:address":"36 W Willow Rd",
    "sg:city":"Willow Street",
    "sg:classifiers":[
        {
            "category":"Professional",
            "type":"Services"
        }
    ],
    "sg:phone":"+1   ",
    "sg:postcode":"17584",
    "sg:province":"PA",
    "wof:name":"Carol Pugh Cnm",
    "wof:placetype":"venue"
},
  "geometry": {"coordinates":[-76.28088099999999,39.974376],"type":"Point"}
}