{
  "type": "Feature",
  "properties": {
    "addr:full":"235 Brick Rd Oxford PA 19363",
    "addr:housenumber":"235",
    "addr:postcode":"19363",
    "addr:street":"Brick Rd",
    "iso:country":"US",
    "sg:address":"235 Brick Rd",
    "sg:city":"Oxford",
    "sg:classifiers":[
        {
            "category":"Building & Trades",
            "subcategory":"Electrical",
            "type":"Services"
        }
    ],
    "sg:phone":"+1   ",
    "sg:postcode":"19363",
    "sg:province":"PA",
    "sg:tags":[
        "electrical",
        "contractor"
    ],
    "wof:name":"Oxford Electric",
    "wof:placetype":"venue"
},
  "geometry": {"coordinates":[-75.95964600000001,39.79148],"type":"Point"}
}