{
  "type": "Feature",
  "properties": {
    "addr:full":"715 Meadowview Dr Red Lion PA 17356",
    "addr:housenumber":"715",
    "addr:postcode":"17356",
    "addr:street":"Meadowview Dr",
    "iso:country":"US",
    "sg:address":"715 Meadowview Dr",
    "sg:city":"Red Lion",
    "sg:classifiers":[
        {
            "category":"Building & Trades",
            "subcategory":"Construction",
            "type":"Services"
        }
    ],
    "sg:phone":"+1   ",
    "sg:postcode":"17356",
    "sg:province":"PA",
    "sg:tags":[
        "contractor"
    ],
    "wof:name":"William A Henry",
    "wof:placetype":"venue"
},
  "geometry": {"coordinates":[-76.620475,39.880995],"type":"Point"}
}