{
  "type": "Feature",
  "properties": {
    "iso:country":"US",
    "sg:address":"1318 Lititz Pike",
    "sg:city":"Lancaster",
    "sg:classifiers":[
        {
            "category":"Personal",
            "subcategory":"Beauty Salon",
            "type":"Services"
        }
    ],
    "sg:phone":"+1 717 396 7788",
    "sg:postcode":"17601",
    "sg:province":"PA",
    "sg:tags":[
        "shop"
    ],
    "wof:name":"Nail Place",
    "wof:placetype":"venue"
},
  "geometry": {"coordinates":[-76.306245,40.060185],"type":"Point"}
}