{
  "type": "Feature",
  "properties": {
    "iso:country":"US",
    "sg:address":"9201 Old Bustleton Ave",
    "sg:city":"Philadelphia",
    "sg:classifiers":[
        {
            "category":"Organizations",
            "subcategory":"Religious Organization",
            "type":"Services"
        }
    ],
    "sg:phone":"+1 215 673 2511",
    "sg:postcode":"19115",
    "sg:province":"PA",
    "sg:tags":[
        "synagogue"
    ],
    "wof:name":"Temple Beth Ami",
    "wof:placetype":"venue"
},
  "geometry": {"coordinates":[-75.041422,40.078651],"type":"Point"}
}