{
  "type": "Feature",
  "properties": {
    "iso:country":"US",
    "sg:address":"670 Pleasant Hills Rd",
    "sg:city":"Wexford",
    "sg:classifiers":[
        {
            "category":"Organizations",
            "subcategory":"Religious Organization",
            "type":"Services"
        }
    ],
    "sg:phone":"+1 724 935 3316",
    "sg:postcode":"15090",
    "sg:province":"PA",
    "sg:tags":[
        "church"
    ],
    "sg:website":"www.mtpleasantchurch.org",
    "wof:name":"Mount Pleasant Presbyterian",
    "wof:placetype":"venue"
},
  "geometry": {"coordinates":[-80.123788,40.66059],"type":"Point"}
}