{
  "type": "Feature",
  "properties": {
    "iso:country":"US",
    "sg:address":"135 S 9th St",
    "sg:city":"Lebanon",
    "sg:classifiers":[
        {
            "category":"Social Services",
            "type":"Services"
        }
    ],
    "sg:phone":"+1 717 228 0935",
    "sg:postcode":"17042",
    "sg:province":"PA",
    "sg:tags":[
        "organization",
        "welfare"
    ],
    "sg:website":"www.tapinc.org",
    "wof:name":"Lebanon County YAP",
    "wof:placetype":"venue"
},
  "geometry": {"coordinates":[-76.426072,40.337147],"type":"Point"}
}