{
  "type": "Feature",
  "properties": {
    "addr:full":"3307 Windstream Dr Gibsonia PA 15044",
    "addr:housenumber":"3307",
    "addr:postcode":"15044",
    "addr:street":"Windstream Dr",
    "iso:country":"US",
    "sg:address":"3307 Windstream Dr",
    "sg:city":"Gibsonia",
    "sg:classifiers":[
        {
            "category":"Shopping",
            "subcategory":"Used Merchandise",
            "type":"Retail Goods"
        }
    ],
    "sg:phone":"+1 724 443 4584",
    "sg:postcode":"15044",
    "sg:province":"PA",
    "sg:tags":[
        "antique"
    ],
    "wof:name":"Antique Broker The",
    "wof:placetype":"venue"
},
  "geometry": {"coordinates":[-79.92247999999999,40.606452],"type":"Point"}
}