{
  "type": "Feature",
  "properties": {
    "addr:full":"100 Greenwood Ave Wyncote PA 19095",
    "addr:housenumber":"100",
    "addr:postcode":"19095",
    "addr:street":"Greenwood Ave",
    "iso:country":"US",
    "sg:address":"100 Greenwood Ave",
    "sg:city":"Wyncote",
    "sg:classifiers":[
        {
            "category":"Wholesale",
            "subcategory":"Durable Goods & Equipment",
            "type":"Manufacturing & Wholesale Goods"
        }
    ],
    "sg:phone":"+1 215 886 5353",
    "sg:postcode":"19095",
    "sg:province":"PA",
    "sg:tags":[
        "representative",
        "manufacturer"
    ],
    "wof:name":"Rep-Net",
    "wof:placetype":"venue"
},
  "geometry": {"coordinates":[-75.14042499999999,40.091832],"type":"Point"}
}