{
  "type": "Feature",
  "properties": {
    "iso:country":"US",
    "sg:address":"215 Haag Rd",
    "sg:city":"Reading",
    "sg:classifiers":[
        {
            "category":"Banks & Credit Unions",
            "subcategory":"Bank",
            "type":"Services"
        }
    ],
    "sg:phone":"+1   ",
    "sg:postcode":"19606",
    "sg:province":"PA",
    "sg:tags":[
        "mortgage"
    ],
    "wof:name":"Affinity Mortgage Co Inc",
    "wof:placetype":"venue"
},
  "geometry": {"coordinates":[-75.89372299999999,40.34974],"type":"Point"}
}