{
  "type": "Feature",
  "properties": {
    "addr:full":"194 Paul Ln Warminster PA 18974",
    "addr:housenumber":"194",
    "addr:postcode":"18974",
    "addr:street":"Paul Ln",
    "iso:country":"US",
    "sg:address":"194 Paul Ln",
    "sg:city":"Warminster",
    "sg:classifiers":[
        {
            "category":"Building & Trades",
            "subcategory":"Construction",
            "type":"Services"
        }
    ],
    "sg:phone":"+1 215 674 8508",
    "sg:postcode":"18974",
    "sg:province":"PA",
    "sg:tags":[
        "system",
        "contractor",
        "air conditioning"
    ],
    "wof:name":"Carver, A W Heating & Air Conditioning",
    "wof:placetype":"venue"
},
  "geometry": {"coordinates":[-75.081322,40.189201],"type":"Point"}
}