{
  "type": "Feature",
  "properties": {
    "iso:country":"US",
    "sg:address":"374 W Main St",
    "sg:city":"Somerset",
    "sg:classifiers":[
        {
            "category":"Autos & Motor Vehicles",
            "subcategory":"Automobile Sales",
            "type":"Retail Goods"
        }
    ],
    "sg:phone":"+1 814 443 4824",
    "sg:postcode":"15501",
    "sg:province":"PA",
    "sg:tags":[
        "new",
        "car"
    ],
    "wof:name":"Jim Dolan Chevrolet Cadillac Incorporated",
    "wof:placetype":"venue"
},
  "geometry": {"coordinates":[-79.08513499999999,40.008482],"type":"Point"}
}