{
  "type": "Feature",
  "properties": {
    "iso:country":"US",
    "sg:address":"31 N 12th St",
    "sg:city":"Lebanon",
    "sg:classifiers":[
        {
            "category":"Manufacturing",
            "subcategory":"Chemicals & Compounds",
            "type":"Manufacturing & Wholesale Goods"
        }
    ],
    "sg:phone":"+1   ",
    "sg:postcode":"17046",
    "sg:province":"PA",
    "sg:tags":[
        "product",
        "gas",
        "related",
        "mfg"
    ],
    "wof:name":"Boc Group Inc A Delaware Corp",
    "wof:placetype":"venue"
},
  "geometry": {"coordinates":[-76.431265,40.340703],"type":"Point"}
}