{
  "type": "Feature",
  "properties": {
    "addr:full":"205 Bock Ln University Park PA 16866",
    "addr:housenumber":"205",
    "addr:postcode":"16866",
    "addr:street":"Bock Ln",
    "iso:country":"US",
    "sg:address":"205 Bock Ln",
    "sg:city":"University Park",
    "sg:classifiers":[
        {
            "category":"Education",
            "subcategory":"College",
            "type":"Public Place"
        }
    ],
    "sg:phone":"+1   ",
    "sg:postcode":"16866",
    "sg:province":"PA",
    "wof:name":"Penn State Student Support",
    "wof:placetype":"venue"
},
  "geometry": {"coordinates":[-78.247884,40.898516],"type":"Point"}
}