{
  "type": "Feature",
  "properties": {
    "iso:country":"US",
    "sg:address":"14845 E Main St",
    "sg:city":"Clarion",
    "sg:classifiers":[
        {
            "category":"Home & Garden",
            "subcategory":"Building Materials",
            "type":"Retail Goods"
        }
    ],
    "sg:phone":"+1 814 226 6161",
    "sg:postcode":"16214",
    "sg:province":"PA",
    "sg:tags":[
        "lumber"
    ],
    "wof:name":"Clarion Builders Supply Co",
    "wof:placetype":"venue"
},
  "geometry": {"coordinates":[-79.366015,41.207923],"type":"Point"}
}