{
  "type": "Feature",
  "properties": {
    "addr:full":"176 Rochester Rd West View PA 15229",
    "addr:housenumber":"176",
    "addr:postcode":"15229",
    "addr:street":"Rochester Rd",
    "iso:country":"US",
    "sg:address":"176 Rochester Rd",
    "sg:city":"West View",
    "sg:classifiers":[
        {
            "category":"Home & Garden",
            "subcategory":"Furniture",
            "type":"Retail Goods"
        }
    ],
    "sg:phone":"+1 412 939 3508",
    "sg:postcode":"15229",
    "sg:province":"PA",
    "sg:website":"www.houseworks-furniture.com",
    "wof:name":"Scandinavian Furniture Ctr",
    "wof:placetype":"venue"
},
  "geometry": {"coordinates":[-80.022441,40.520692],"type":"Point"}
}