{
  "type": "Feature",
  "properties": {
    "addr:full":"1648 S 7th St Philadelphia PA 19148",
    "addr:housenumber":"1648",
    "addr:postcode":"19148",
    "addr:street":"S 7Th St",
    "iso:country":"US",
    "sg:address":"1648 S 7th St",
    "sg:city":"Philadelphia",
    "sg:classifiers":[
        {
            "category":"Restaurant",
            "type":"Food & Drink"
        }
    ],
    "sg:phone":"+1 215 755 9900",
    "sg:postcode":"19148",
    "sg:province":"PA",
    "sg:tags":[
        "pizza"
    ],
    "wof:name":"Pizza Place the",
    "wof:placetype":"venue"
},
  "geometry": {"coordinates":[-75.15720399999999,39.927898],"type":"Point"}
}