{
  "type": "Feature",
  "properties": {
    "addr:full":"287 East Ave State Line PA 17263",
    "addr:housenumber":"287",
    "addr:postcode":"17263",
    "addr:street":"East Ave",
    "iso:country":"US",
    "sg:address":"287 East Ave",
    "sg:city":"State Line",
    "sg:classifiers":[
        {
            "category":"Organizations",
            "subcategory":"Religious Organization",
            "type":"Services"
        }
    ],
    "sg:phone":"+1 717 597 4217",
    "sg:postcode":"17263",
    "sg:province":"PA",
    "sg:tags":[
        "church"
    ],
    "wof:name":"State Line United Methodist",
    "wof:placetype":"venue"
},
  "geometry": {"coordinates":[-77.72026,39.723942],"type":"Point"}
}