{
  "type": "Feature",
  "properties": {
    "addr:full":"1009 Three Degree Rd Butler PA 16002",
    "addr:housenumber":"1009",
    "addr:postcode":"16002",
    "addr:street":"Three Degree Rd",
    "iso:country":"US",
    "sg:address":"1009 Three Degree Rd",
    "sg:city":"Butler",
    "sg:classifiers":[
        {
            "category":"Building & Trades",
            "subcategory":"Construction",
            "type":"Services"
        }
    ],
    "sg:phone":"+1 724 586 2456",
    "sg:postcode":"16002",
    "sg:province":"PA",
    "sg:tags":[
        "home",
        "house",
        "carpentry",
        "improvement",
        "contractor"
    ],
    "wof:name":"Mc Coy Construction",
    "wof:placetype":"venue"
},
  "geometry": {"coordinates":[-79.96678199999999,40.757645],"type":"Point"}
}