{
  "type": "Feature",
  "properties": {
    "addr:full":"2245 Lincoln Hwy Boswell PA 15531",
    "addr:housenumber":"2245",
    "addr:postcode":"15531",
    "addr:street":"Lincoln Hwy",
    "iso:country":"US",
    "sg:address":"2245 Lincoln Hwy",
    "sg:city":"Boswell",
    "sg:classifiers":[
        {
            "category":"Food & Beverages",
            "subcategory":"Liquor & Beverages",
            "type":"Retail Goods"
        }
    ],
    "sg:phone":"+1 814 629 6013",
    "sg:postcode":"15531",
    "sg:province":"PA",
    "sg:tags":[
        "beer",
        "ale"
    ],
    "wof:name":"Beer Junction",
    "wof:placetype":"venue"
},
  "geometry": {"coordinates":[-79.042333,40.147499],"type":"Point"}
}