{
  "type": "Feature",
  "properties": {
    "iso:country":"US",
    "sg:address":"151 Discovery Dr",
    "sg:city":"Colmar",
    "sg:classifiers":[
        {
            "category":"Building & Trades",
            "subcategory":"Construction",
            "type":"Services"
        }
    ],
    "sg:phone":"+1 215 491 5191",
    "sg:postcode":"18915",
    "sg:province":"PA",
    "sg:tags":[
        "roofing",
        "contractor"
    ],
    "wof:name":"Mick & Assoc",
    "wof:placetype":"venue"
},
  "geometry": {"coordinates":[-75.25509099999999,40.273154],"type":"Point"}
}