{
  "type": "Feature",
  "properties": {
    "iso:country":"US",
    "sg:address":"910 Church St",
    "sg:city":"Saxton",
    "sg:classifiers":[
        {
            "category":"Building & Trades",
            "subcategory":"Construction",
            "type":"Services"
        }
    ],
    "sg:phone":"+1 814 635 2371",
    "sg:postcode":"16678",
    "sg:province":"PA",
    "sg:tags":[
        "manufactured",
        "housing-communities"
    ],
    "wof:name":"Mountain Manor Park",
    "wof:placetype":"venue"
},
  "geometry": {"coordinates":[-78.246475,40.21665],"type":"Point"}
}