{
  "type": "Feature",
  "properties": {
    "iso:country":"US",
    "sg:address":"705 Broad St",
    "sg:city":"Oxford",
    "sg:classifiers":[
        {
            "category":"Banks & Credit Unions",
            "subcategory":"Bank",
            "type":"Services"
        }
    ],
    "sg:phone":"+1   ",
    "sg:postcode":"19363",
    "sg:province":"PA",
    "sg:tags":[
        "mortgage"
    ],
    "wof:name":"Wilson & Associates",
    "wof:placetype":"venue"
},
  "geometry": {"coordinates":[-75.96799,39.782237],"type":"Point"}
}