{
  "type": "Feature",
  "properties": {
    "iso:country":"US",
    "sg:address":"321 E 4th St",
    "sg:city":"Bethlehem",
    "sg:classifiers":[
        {
            "category":"Arts & Performance",
            "subcategory":"Theater",
            "type":"Entertainment"
        }
    ],
    "sg:phone":"+1 610 867 1689",
    "sg:postcode":"18015",
    "sg:province":"PA",
    "sg:tags":[
        "production",
        "cinema"
    ],
    "sg:website":"www.touchstone.org",
    "wof:name":"Touchstone Theatre",
    "wof:placetype":"venue"
},
  "geometry": {"coordinates":[-75.37339799999999,40.610699],"type":"Point"}
}