{
  "type": "Feature",
  "properties": {
    "addr:full":"4 Erie Ave Saint Marys PA 15857",
    "addr:housenumber":"4",
    "addr:postcode":"15857",
    "addr:street":"Erie Ave",
    "iso:country":"US",
    "sg:address":"4 Erie Ave",
    "sg:city":"Saint Marys",
    "sg:classifiers":[
        {
            "category":"Organizations",
            "subcategory":"Community Association",
            "type":"Services"
        }
    ],
    "sg:phone":"+1   ",
    "sg:postcode":"15857",
    "sg:province":"PA",
    "wof:name":"Keystone Tall Tree Girl Scout",
    "wof:placetype":"venue"
},
  "geometry": {"coordinates":[-78.55765700000001,41.429794],"type":"Point"}
}