{
  "type": "Feature",
  "properties": {
    "addr:full":"3065 Industrial Blvd Bethel Park PA 15102",
    "addr:housenumber":"3065",
    "addr:postcode":"15102",
    "addr:street":"Industrial Blvd",
    "iso:country":"US",
    "sg:address":"3065 Industrial Blvd",
    "sg:city":"Bethel Park",
    "sg:classifiers":[
        {
            "category":"Wholesale",
            "subcategory":"Construction Materials",
            "type":"Manufacturing & Wholesale Goods"
        }
    ],
    "sg:phone":"+1 412 835 2234",
    "sg:postcode":"15102",
    "sg:province":"PA",
    "sg:tags":[
        "distributor",
        "tile",
        "ceramic"
    ],
    "wof:name":"Ceramic Tile Sales",
    "wof:placetype":"venue"
},
  "geometry": {"coordinates":[-80.04357400000001,40.325112],"type":"Point"}
}