{
  "type": "Feature",
  "properties": {
    "iso:country":"US",
    "sg:address":"1411 Limekiln Pike",
    "sg:city":"Dresher",
    "sg:classifiers":[
        {
            "category":"Building & Trades",
            "subcategory":"Landscaping Services",
            "type":"Services"
        }
    ],
    "sg:phone":"+1 215 628 3876",
    "sg:postcode":"19025",
    "sg:province":"PA",
    "sg:tags":[
        "landscape",
        "contractor"
    ],
    "wof:name":"Dominic's Landscaping",
    "wof:placetype":"venue"
},
  "geometry": {"coordinates":[-75.175906,40.155364],"type":"Point"}
}