{
  "type": "Feature",
  "properties": {
    "iso:country":"US",
    "sg:address":"535 Prospect St",
    "sg:city":"York",
    "sg:classifiers":[
        {
            "category":"Retail",
            "subcategory":"Auto Repair",
            "type":"Services"
        }
    ],
    "sg:phone":"+1   ",
    "sg:postcode":"17403",
    "sg:province":"PA",
    "sg:tags":[
        "body",
        "automotive"
    ],
    "wof:name":"Darrahs Automotive and Recycl",
    "wof:placetype":"venue"
},
  "geometry": {"coordinates":[-76.715475,39.960903],"type":"Point"}
}