{
  "type": "Feature",
  "properties": {
    "iso:country":"US",
    "sg:address":"1070 Municipal Rd",
    "sg:city":"Walnutport",
    "sg:classifiers":[
        {
            "category":"Utilities",
            "subcategory":"Water",
            "type":"Services"
        }
    ],
    "sg:phone":"+1 610 767 0621",
    "sg:postcode":"18088",
    "sg:province":"PA",
    "sg:tags":[
        "pump",
        "well",
        "drilling",
        "contractor"
    ],
    "wof:name":"Derau Well Drilling Co",
    "wof:placetype":"venue"
},
  "geometry": {"coordinates":[-75.55153900000001,40.775881],"type":"Point"}
}