{
  "type": "Feature",
  "properties": {
    "addr:full":"7100 Highland Dr Pittsburgh PA 15206",
    "addr:housenumber":"7100",
    "addr:postcode":"15206",
    "addr:street":"Highland Dr",
    "iso:country":"US",
    "sg:address":"7100 Highland Dr",
    "sg:city":"Pittsburgh",
    "sg:classifiers":[
        {
            "category":"Government",
            "subcategory":"Office",
            "type":"Public Place"
        }
    ],
    "sg:phone":"+1 412 362 4123",
    "sg:postcode":"15206",
    "sg:province":"PA",
    "sg:tags":[
        "federal",
        "security"
    ],
    "wof:name":"US Army Reserve",
    "wof:placetype":"venue"
},
  "geometry": {"coordinates":[-79.89961599999999,40.478332],"type":"Point"}
}