{
  "type": "Feature",
  "properties": {
    "addr:full":"115 W Richardson Ave Langhorne PA 19047",
    "addr:housenumber":"115",
    "addr:postcode":"19047",
    "addr:street":"W Richardson Ave Langhorne Pa",
    "iso:country":"US",
    "sg:address":"115 W Richardson Ave",
    "sg:city":"Langhorne",
    "sg:classifiers":[
        {
            "category":"Organizations",
            "subcategory":"Community Association",
            "type":"Services"
        }
    ],
    "sg:phone":"+1 215 757 3056",
    "sg:postcode":"19047",
    "sg:province":"PA",
    "sg:tags":[
        "military"
    ],
    "wof:name":"American Legion",
    "wof:placetype":"venue"
},
  "geometry": {"coordinates":[-74.921029,40.174916],"type":"Point"}
}