{
  "type": "Feature",
  "properties": {
    "iso:country":"US",
    "sg:address":"106 Airport Dr",
    "sg:city":"New Cumberland",
    "sg:classifiers":[
        {
            "category":"Retail",
            "subcategory":"Auto Rental",
            "type":"Services"
        }
    ],
    "sg:phone":"+1   ",
    "sg:postcode":"17070",
    "sg:province":"PA",
    "sg:tags":[
        "passenger",
        "car"
    ],
    "wof:name":"Enterprise Rent-A-Car",
    "wof:placetype":"venue"
},
  "geometry": {"coordinates":[-76.85459899999999,40.209679],"type":"Point"}
}