{
  "type": "Feature",
  "properties": {
    "addr:full":"350 Sunrise Ave Honesdale PA 18431",
    "addr:housenumber":"350",
    "addr:postcode":"18431",
    "addr:street":"Sunrise Ave",
    "iso:country":"US",
    "sg:address":"350 Sunrise Ave",
    "sg:city":"Honesdale",
    "sg:classifiers":[
        {
            "category":"Autos & Motor Vehicles",
            "subcategory":"Auto Supplies",
            "type":"Retail Goods"
        }
    ],
    "sg:phone":"+1 570 253 1610",
    "sg:postcode":"18431",
    "sg:province":"PA",
    "sg:tags":[
        "tire"
    ],
    "wof:name":"Sunrise Service",
    "wof:placetype":"venue"
},
  "geometry": {"coordinates":[-75.24983899999999,41.555702],"type":"Point"}
}