{
  "type": "Feature",
  "properties": {
    "iso:country":"US",
    "sg:address":"111 Golfview Dr",
    "sg:city":"Monaca",
    "sg:classifiers":[
        {
            "category":"Restaurant",
            "type":"Food & Drink"
        }
    ],
    "sg:phone":"+1   ",
    "sg:postcode":"15061",
    "sg:province":"PA",
    "sg:tags":[
        "eating"
    ],
    "wof:name":"Wendys",
    "wof:placetype":"venue"
},
  "geometry": {"coordinates":[-80.31009400000001,40.673843],"type":"Point"}
}