{
  "type": "Feature",
  "properties": {
    "iso:country":"US",
    "sg:address":"2221 Point Rd",
    "sg:city":"Schellsburg",
    "sg:phone":"+1   ",
    "sg:postcode":"15559",
    "sg:province":"PA",
    "sg:tags":[
        "farm",
        "field",
        "crop"
    ],
    "wof:name":"Jay Callihan",
    "wof:placetype":"venue"
},
  "geometry": {"coordinates":[-78.60383400000001,40.09058],"type":"Point"}
}