{
  "type": "Feature",
  "properties": {
    "addr:full":"4 Center Sq Nazareth PA 18064",
    "addr:housenumber":"4",
    "addr:postcode":"18064",
    "addr:street":"Center Sq",
    "iso:country":"US",
    "sg:address":"4 Center Sq",
    "sg:city":"Nazareth",
    "sg:classifiers":[
        {
            "category":"Recreation",
            "type":"Entertainment"
        }
    ],
    "sg:phone":"+1   ",
    "sg:postcode":"18064",
    "sg:province":"PA",
    "sg:tags":[
        "club",
        "membership"
    ],
    "wof:name":"4h Center Northampton County",
    "wof:placetype":"venue"
},
  "geometry": {"coordinates":[-75.312163,40.742489],"type":"Point"}
}