{
  "type": "Feature",
  "properties": {
    "iso:country":"US",
    "sg:address":"100 W Ridge St",
    "sg:city":"Lansford",
    "sg:classifiers":[
        {
            "category":"Professional",
            "subcategory":"Employment Agencies",
            "type":"Services"
        }
    ],
    "sg:phone":"+1 570 645 5000",
    "sg:postcode":"18232",
    "sg:province":"PA",
    "sg:tags":[
        "opportunity"
    ],
    "sg:website":"www.allstaffing.com",
    "wof:name":"All Staffing Inc",
    "wof:placetype":"venue"
},
  "geometry": {"coordinates":[-75.8865,40.831606],"type":"Point"}
}