{
  "type": "Feature",
  "properties": {
    "iso:country":"US",
    "sg:address":"946 Morgantown Rd",
    "sg:city":"Uniontown",
    "sg:classifiers":[
        {
            "category":"Food & Beverages",
            "subcategory":"Liquor & Beverages",
            "type":"Retail Goods"
        }
    ],
    "sg:phone":"+1   ",
    "sg:postcode":"15401",
    "sg:province":"PA",
    "sg:tags":[
        "regulation",
        "commercial",
        "sect",
        "alcoholic"
    ],
    "wof:name":"Wine & Spirits Shoppe 2611",
    "wof:placetype":"venue"
},
  "geometry": {"coordinates":[-79.74386,39.868036],"type":"Point"}
}