{
  "type": "Feature",
  "properties": {
    "iso:country":"US",
    "sg:address":"208 Teaberry Cir",
    "sg:city":"State College",
    "sg:classifiers":[
        {
            "category":"Wholesale",
            "subcategory":"Apparel",
            "type":"Manufacturing & Wholesale Goods"
        }
    ],
    "sg:phone":"+1   ",
    "sg:postcode":"16803",
    "sg:province":"PA",
    "sg:tags":[
        "trim",
        "item",
        "clothing"
    ],
    "wof:name":"Artco Textiles Inc",
    "wof:placetype":"venue"
},
  "geometry": {"coordinates":[-77.917357,40.799699],"type":"Point"}
}