{
  "type": "Feature",
  "properties": {
    "iso:country":"US",
    "sg:address":"753 Pheasant Trail Ln",
    "sg:city":"Mc Connellsburg",
    "sg:classifiers":[
        {
            "category":"Freight",
            "type":"Transportation"
        }
    ],
    "sg:phone":"+1   ",
    "sg:postcode":"17233",
    "sg:province":"PA",
    "sg:tags":[
        "local",
        "hauling",
        "trucking"
    ],
    "wof:name":"Stan Fetters",
    "wof:placetype":"venue"
},
  "geometry": {"coordinates":[-77.989153,39.957504],"type":"Point"}
}