{
  "type": "Feature",
  "properties": {
    "iso:country":"US",
    "sg:address":"1 Agata Dr",
    "sg:city":"Douglassville",
    "sg:classifiers":[
        {
            "category":"Building & Trades",
            "subcategory":"Construction",
            "type":"Services"
        }
    ],
    "sg:phone":"+1 610 476 1969",
    "sg:postcode":"19518",
    "sg:province":"PA",
    "sg:tags":[
        "installation",
        "commercial",
        "sale",
        "carpet"
    ],
    "wof:name":"Mill Direct Carpet",
    "wof:placetype":"venue"
},
  "geometry": {"coordinates":[-75.76185599999999,40.322075],"type":"Point"}
}