{
  "type": "Feature",
  "properties": {
    "iso:country":"US",
    "sg:address":"103 Park Dr",
    "sg:city":"Montgomeryville",
    "sg:classifiers":[
        {
            "category":"Manufacturing",
            "subcategory":"Furniture",
            "type":"Manufacturing & Wholesale Goods"
        }
    ],
    "sg:phone":"+1 215 540 9295",
    "sg:postcode":"18936",
    "sg:province":"PA",
    "wof:name":"Virco Manufacturing Corp",
    "wof:placetype":"venue"
},
  "geometry": {"coordinates":[-75.22616600000001,40.212469],"type":"Point"}
}