{
  "type": "Feature",
  "properties": {
    "iso:country":"US",
    "sg:address":"512 S 8th St",
    "sg:city":"Lebanon",
    "sg:classifiers":[
        {
            "category":"Organizations",
            "subcategory":"Non-profit Organization",
            "type":"Services"
        }
    ],
    "sg:phone":"+1 717 273 7351",
    "sg:postcode":"17042",
    "sg:province":"PA",
    "sg:tags":[
        "human"
    ],
    "wof:name":"Easter Seals South Central Pa",
    "wof:placetype":"venue"
},
  "geometry": {"coordinates":[-76.423536,40.331792],"type":"Point"}
}