{
  "type": "Feature",
  "properties": {
    "addr:full":"121 Bridge St Beaver PA 15009",
    "addr:housenumber":"121",
    "addr:postcode":"15009",
    "addr:street":"Bridge St",
    "iso:country":"US",
    "sg:address":"121 Bridge St",
    "sg:city":"Beaver",
    "sg:classifiers":[
        {
            "category":"Sports & Exercise",
            "subcategory":"Gym",
            "type":"Entertainment"
        }
    ],
    "sg:phone":"+1 724 728 8004",
    "sg:postcode":"15009",
    "sg:province":"PA",
    "sg:tags":[
        "shop",
        "fitness",
        "physical",
        "beauty",
        "facility"
    ],
    "wof:name":"A Sense Of Eden Salon & Spa",
    "wof:placetype":"venue"
},
  "geometry": {"coordinates":[-80.29275,40.700764],"type":"Point"}
}