{
  "type": "Feature",
  "properties": {
    "iso:country":"US",
    "sg:address":"93 York Rd",
    "sg:city":"Jenkintown",
    "sg:classifiers":[
        {
            "category":"Professional",
            "subcategory":"Management & Consulting",
            "type":"Services"
        }
    ],
    "sg:phone":"+1   ",
    "sg:postcode":"19046",
    "sg:province":"PA",
    "sg:tags":[
        "technical",
        "development",
        "material"
    ],
    "wof:name":"Strategic Communications Group",
    "wof:placetype":"venue"
},
  "geometry": {"coordinates":[-75.12544,40.092632],"type":"Point"}
}