{
  "type": "Feature",
  "properties": {
    "iso:country":"US",
    "sg:address":"30 Ohio St",
    "sg:city":"Wheatland",
    "sg:classifiers":[
        {
            "category":"Wholesale",
            "subcategory":"Dairy",
            "type":"Manufacturing & Wholesale Goods"
        }
    ],
    "sg:phone":"+1 724 981 1848",
    "sg:postcode":"16161",
    "sg:province":"PA",
    "sg:tags":[
        "product"
    ],
    "wof:name":"J L Dairy Sales",
    "wof:placetype":"venue"
},
  "geometry": {"coordinates":[-80.499977,41.198716],"type":"Point"}
}