{
  "type": "Feature",
  "properties": {
    "iso:country":"US",
    "sg:address":"1478 State Rd",
    "sg:city":"Oxford",
    "sg:classifiers":[
        {
            "category":"Wholesale",
            "subcategory":"Machinery & Supplies",
            "type":"Manufacturing & Wholesale Goods"
        }
    ],
    "sg:phone":"+1   ",
    "sg:postcode":"19363",
    "sg:province":"PA",
    "wof:name":"M Weaver Enterprises Inc",
    "wof:placetype":"venue"
},
  "geometry": {"coordinates":[-75.933004,39.725405],"type":"Point"}
}