{
  "type": "Feature",
  "properties": {
    "iso:country":"US",
    "sg:address":"4634 N Front St",
    "sg:city":"Philadelphia",
    "sg:classifiers":[
        {
            "category":"Retail",
            "subcategory":"Auto Repair",
            "type":"Services"
        }
    ],
    "sg:phone":"+1   ",
    "sg:postcode":"19140",
    "sg:province":"PA",
    "sg:tags":[
        "general"
    ],
    "wof:name":"Lous Cars",
    "wof:placetype":"venue"
},
  "geometry": {"coordinates":[-75.12442799999999,40.021515],"type":"Point"}
}