{
  "type": "Feature",
  "properties": {
    "addr:full":"1820 S 11th St Philadelphia PA 19148",
    "addr:housenumber":"1820",
    "addr:postcode":"19148",
    "addr:street":"S 11Th St",
    "iso:country":"US",
    "sg:address":"1820 S 11th St",
    "sg:city":"Philadelphia",
    "sg:classifiers":[
        {
            "category":"Shopping",
            "subcategory":"Clothing, Apparel, & Fashions",
            "type":"Retail Goods"
        }
    ],
    "sg:phone":"+1 215 468 1005",
    "sg:postcode":"19148",
    "sg:province":"PA",
    "sg:tags":[
        "tailor"
    ],
    "wof:name":"Zangari Training",
    "wof:placetype":"venue"
},
  "geometry": {"coordinates":[-75.16375499999999,39.927289],"type":"Point"}
}