{
  "type": "Feature",
  "properties": {
    "iso:country":"US",
    "sg:address":"380 Erie St",
    "sg:city":"Honesdale",
    "sg:classifiers":[
        {
            "category":"Retail",
            "subcategory":"Laundry & Dry Cleaning",
            "type":"Services"
        }
    ],
    "sg:phone":"+1 570 253 1670",
    "sg:postcode":"18431",
    "sg:province":"PA",
    "sg:tags":[
        "cleaner",
        "commercial"
    ],
    "wof:name":"Imperial Dry Cleaners",
    "wof:placetype":"venue"
},
  "geometry": {"coordinates":[-75.24901199999999,41.561479],"type":"Point"}
}