{
  "type": "Feature",
  "properties": {
    "iso:country":"US",
    "sg:address":"2028 Mercer Rd",
    "sg:city":"New Brighton",
    "sg:classifiers":[
        {
            "category":"Building & Trades",
            "subcategory":"Construction",
            "type":"Services"
        }
    ],
    "sg:phone":"+1   ",
    "sg:postcode":"15066",
    "sg:province":"PA",
    "sg:tags":[
        "contractor"
    ],
    "wof:name":"Rossi Contracting",
    "wof:placetype":"venue"
},
  "geometry": {"coordinates":[-80.30098,40.749199],"type":"Point"}
}