{
  "type": "Feature",
  "properties": {
    "iso:country":"US",
    "sg:address":"44 E Main St",
    "sg:city":"Waynesboro",
    "sg:classifiers":[
        {
            "category":"Education",
            "subcategory":"Dance Studio",
            "type":"Public Place"
        }
    ],
    "sg:phone":"+1 717 762 4456",
    "sg:postcode":"17268",
    "sg:province":"PA",
    "sg:tags":[
        "art",
        "performing",
        "instruction",
        "dancing"
    ],
    "wof:name":"Beckie Dance Studio",
    "wof:placetype":"venue"
},
  "geometry": {"coordinates":[-77.5774,39.755501],"type":"Point"}
}