{
  "type": "Feature",
  "properties": {
    "iso:country":"US",
    "sg:address":"30 Carverton Rd",
    "sg:city":"Shavertown",
    "sg:classifiers":[
        {
            "category":"Health Services",
            "subcategory":"Clinic",
            "type":"Services"
        }
    ],
    "sg:phone":"+1 570 696 2655",
    "sg:postcode":"18708",
    "sg:province":"PA",
    "sg:tags":[
        "welfare"
    ],
    "wof:name":"Yanik Family Wellness",
    "wof:placetype":"venue"
},
  "geometry": {"coordinates":[-75.928746,41.303382],"type":"Point"}
}