{
  "type": "Feature",
  "properties": {
    "iso:country":"US",
    "sg:address":"Routes 73 & 363",
    "sg:city":"Worcester",
    "sg:classifiers":[
        {
            "category":"Retail",
            "subcategory":"Auto Repair",
            "type":"Services"
        }
    ],
    "sg:phone":"+1 610 584 9251",
    "sg:postcode":"19490",
    "sg:province":"PA",
    "sg:website":"www.exxon.com",
    "wof:name":"Center Point Exxon",
    "wof:placetype":"venue"
},
  "geometry": {"coordinates":[-75.34050000000001,40.205799],"type":"Point"}
}