{
  "type": "Feature",
  "properties": {
    "addr:full":"1417 4th Ave Ford City PA 16226",
    "addr:housenumber":"1417",
    "addr:postcode":"16226",
    "addr:street":"4Th Ave",
    "iso:country":"US",
    "sg:address":"1417 4th Ave",
    "sg:city":"Ford City",
    "sg:classifiers":[
        {
            "category":"Sports & Exercise",
            "subcategory":"Bowling",
            "type":"Entertainment"
        },
        {
            "category":"Shopping",
            "subcategory":"Bicycles & Sporting Goods",
            "type":"Retail Goods"
        }
    ],
    "sg:phone":"+1 724 763 2123",
    "sg:postcode":"16226",
    "sg:province":"PA",
    "sg:tags":[
        "center"
    ],
    "wof:name":"Bower's Pro Shop",
    "wof:placetype":"venue"
},
  "geometry": {"coordinates":[-79.525629,40.777277],"type":"Point"}
}