{
  "type": "Feature",
  "properties": {
    "iso:country":"US",
    "sg:address":"15132 Great Cove Rd",
    "sg:city":"Big Cove Tannery",
    "sg:classifiers":[
        {
            "category":"Food & Beverages",
            "subcategory":"Groceries & Convenience Stores",
            "type":"Retail Goods"
        }
    ],
    "sg:phone":"+1 717 485 3046",
    "sg:postcode":"17212",
    "sg:province":"PA",
    "sg:tags":[
        "grocer"
    ],
    "wof:name":"Harr's Grocery",
    "wof:placetype":"venue"
},
  "geometry": {"coordinates":[-78.04615699999999,39.855601],"type":"Point"}
}