{
  "type": "Feature",
  "properties": {
    "iso:country":"US",
    "sg:address":"1005 S Bee St",
    "sg:city":"Pittsburgh",
    "sg:classifiers":[
        {
            "category":"Wholesale",
            "subcategory":"Hardware",
            "type":"Manufacturing & Wholesale Goods"
        },
        {
            "category":"Wholesale",
            "subcategory":"Electrical",
            "type":"Manufacturing & Wholesale Goods"
        }
    ],
    "sg:phone":"+1 412 928 4200",
    "sg:postcode":"15220",
    "sg:province":"PA",
    "sg:tags":[
        "control",
        "c",
        "system",
        "parts",
        "security",
        "electronic"
    ],
    "wof:name":"Honeywell",
    "wof:placetype":"venue"
},
  "geometry": {"coordinates":[-80.04249299999999,40.428533],"type":"Point"}
}