{
  "type": "Feature",
  "properties": {
    "iso:country":"US",
    "sg:address":"817 W Pike St",
    "sg:city":"Houston",
    "sg:classifiers":[
        {
            "category":"Building & Trades",
            "subcategory":"Pest Control",
            "type":"Services"
        }
    ],
    "sg:phone":"+1 724 746 2847",
    "sg:postcode":"15342",
    "sg:province":"PA",
    "sg:tags":[
        "farm",
        "supply"
    ],
    "wof:name":"All Kontrol Exterminating Co",
    "wof:placetype":"venue"
},
  "geometry": {"coordinates":[-80.213139,40.241145],"type":"Point"}
}