{
  "type": "Feature",
  "properties": {
    "iso:country":"US",
    "sg:address":"913 Center St",
    "sg:city":"Mount Joy",
    "sg:classifiers":[
        {
            "category":"Building & Trades",
            "subcategory":"Landscaping Services",
            "type":"Services"
        }
    ],
    "sg:phone":"+1   ",
    "sg:postcode":"17552",
    "sg:province":"PA",
    "wof:name":"Halt",
    "wof:placetype":"venue"
},
  "geometry": {"coordinates":[-76.464629,40.068113],"type":"Point"}
}