{
  "type": "Feature",
  "properties": {
    "iso:country":"US",
    "sg:address":"1001 Ranck Mill Rd",
    "sg:city":"Lancaster",
    "sg:classifiers":[
        {
            "category":"Manufacturing",
            "subcategory":"Metals",
            "type":"Manufacturing & Wholesale Goods"
        }
    ],
    "sg:phone":"+1 717 431 2316",
    "sg:postcode":"17602",
    "sg:province":"PA",
    "sg:tags":[
        "hardware",
        "tran",
        "mfg"
    ],
    "wof:name":"Schmitt Marine Steering Wheels",
    "wof:placetype":"venue"
},
  "geometry": {"coordinates":[-76.281605,40.044308],"type":"Point"}
}