{
  "type": "Feature",
  "properties": {
    "addr:full":"616 York Rd Jenkintown PA 19046",
    "addr:housenumber":"616",
    "addr:postcode":"19046",
    "addr:street":"York Rd",
    "iso:country":"US",
    "sg:address":"616 York Rd",
    "sg:city":"Jenkintown",
    "sg:classifiers":[
        {
            "category":"Banks & Credit Unions",
            "subcategory":"Bank",
            "type":"Services"
        }
    ],
    "sg:phone":"+1   ",
    "sg:postcode":"19046",
    "sg:province":"PA",
    "sg:tags":[
        "federal",
        "savings",
        "institution"
    ],
    "wof:name":"Fleet",
    "wof:placetype":"venue"
},
  "geometry": {"coordinates":[-75.125911,40.099572],"type":"Point"}
}