{
  "type": "Feature",
  "properties": {
    "iso:country":"US",
    "sg:address":"1495 Hall Rd",
    "sg:city":"Julian",
    "sg:classifiers":[
        {
            "category":"Building & Trades",
            "subcategory":"Construction",
            "type":"Services"
        }
    ],
    "sg:phone":"+1   ",
    "sg:postcode":"16844",
    "sg:province":"PA",
    "sg:tags":[
        "contractor"
    ],
    "wof:name":"Precise Builders",
    "wof:placetype":"venue"
},
  "geometry": {"coordinates":[-77.95528299999999,40.904572],"type":"Point"}
}