{
  "type": "Feature",
  "properties": {
    "iso:country":"US",
    "sg:address":"336 US Hwy 6",
    "sg:city":"Coudersport",
    "sg:classifiers":[
        {
            "category":"Health Services",
            "subcategory":"Clinic",
            "type":"Services"
        }
    ],
    "sg:phone":"+1 814 274 0115",
    "sg:postcode":"16915",
    "sg:province":"PA",
    "sg:tags":[
        "home"
    ],
    "wof:name":"Helpmates Home Health Care Inc",
    "wof:placetype":"venue"
},
  "geometry": {"coordinates":[-78.030798,41.766637],"type":"Point"}
}