{
  "type": "Feature",
  "properties": {
    "addr:full":"3700 Nicholas St Easton PA 18045",
    "addr:housenumber":"3700",
    "addr:postcode":"18045",
    "addr:street":"Nicholas St",
    "iso:country":"US",
    "sg:address":"3700 Nicholas St",
    "sg:city":"Easton",
    "sg:classifiers":[
        {
            "category":"Sports & Exercise",
            "subcategory":"Bowling",
            "type":"Entertainment"
        }
    ],
    "sg:phone":"+1   ",
    "sg:postcode":"18045",
    "sg:province":"PA",
    "sg:tags":[
        "center"
    ],
    "wof:name":"Bardon Lanes LLC",
    "wof:placetype":"venue"
},
  "geometry": {"coordinates":[-75.26514299999999,40.671275],"type":"Point"}
}