{
  "type": "Feature",
  "properties": {
    "addr:full":"1100 Cedar Crest Ave Lebanon PA 17046",
    "addr:housenumber":"1100",
    "addr:postcode":"17046",
    "addr:street":"Cedar Crest Ave",
    "iso:country":"US",
    "sg:address":"1100 Cedar Crest Ave",
    "sg:city":"Lebanon",
    "sg:classifiers":[
        {
            "category":"Real Estate",
            "subcategory":"Real Estate Agent",
            "type":"Services"
        }
    ],
    "sg:phone":"+1 717 274 6661",
    "sg:postcode":"17046",
    "sg:province":"PA",
    "wof:name":"Rauch Appraisals",
    "wof:placetype":"venue"
},
  "geometry": {"coordinates":[-76.390227,40.352731],"type":"Point"}
}