{
  "type": "Feature",
  "properties": {
    "iso:country":"US",
    "sg:address":"2555 Kingston Rd",
    "sg:city":"York",
    "sg:classifiers":[
        {
            "category":"Insurance",
            "subcategory":"Insurance Agent",
            "type":"Services"
        }
    ],
    "sg:phone":"+1 717 600 0417",
    "sg:postcode":"17402",
    "sg:province":"PA",
    "wof:name":"All Risk",
    "wof:placetype":"venue"
},
  "geometry": {"coordinates":[-76.675669,39.970547],"type":"Point"}
}