{
  "type": "Feature",
  "properties": {
    "iso:country":"US",
    "sg:address":"801 Freeport Rd",
    "sg:city":"New Kensington",
    "sg:classifiers":[
        {
            "category":"Professional",
            "subcategory":"Lawyer & Legal Services",
            "type":"Services"
        }
    ],
    "sg:phone":"+1   ",
    "sg:postcode":"15068",
    "sg:province":"PA",
    "wof:name":"Van Horne Terry A Atty",
    "wof:placetype":"venue"
},
  "geometry": {"coordinates":[-79.75612,40.57543],"type":"Point"}
}