{
  "type": "Feature",
  "properties": {
    "addr:full":"128 Oakland Ave Pittsburgh PA 15213",
    "addr:housenumber":"128",
    "addr:postcode":"15213",
    "addr:street":"Oakland Ave",
    "iso:country":"US",
    "sg:address":"128 Oakland Ave",
    "sg:city":"Pittsburgh",
    "sg:classifiers":[
        {
            "category":"Restaurant",
            "type":"Food & Drink"
        }
    ],
    "sg:menulink":"http://www.allmenus.com/pa/pittsburgh/273305-sushi-boat/menu/",
    "sg:phone":"+1 412 681 1818",
    "sg:postcode":"15213",
    "sg:province":"PA",
    "sg:tags":[
        "sushi",
        "asian"
    ],
    "wof:name":"Sushi Boat",
    "wof:placetype":"venue"
},
  "geometry": {"coordinates":[-79.95763100000001,40.441937],"type":"Point"}
}