{
  "type": "Feature",
  "properties": {
    "addr:full":"210 S Tulpehocken St Pine Grove PA 17963",
    "addr:housenumber":"210",
    "addr:postcode":"17963",
    "addr:street":"S Tulpehocken St",
    "iso:country":"US",
    "sg:address":"210 S Tulpehocken St",
    "sg:city":"Pine Grove",
    "sg:classifiers":[
        {
            "category":"Health Services",
            "subcategory":"Doctor",
            "type":"Services"
        }
    ],
    "sg:phone":"+1   ",
    "sg:postcode":"17963",
    "sg:province":"PA",
    "wof:name":"Mangat S Harcharn DMD",
    "wof:placetype":"venue"
},
  "geometry": {"coordinates":[-76.385328,40.545624],"type":"Point"}
}