{
  "type": "Feature",
  "properties": {
    "addr:full":"527 Hoffmansville Rd Bechtelsville PA 19505",
    "addr:housenumber":"527",
    "addr:postcode":"19505",
    "addr:street":"Hoffmansville Rd",
    "iso:country":"US",
    "sg:address":"527 Hoffmansville Rd",
    "sg:city":"Bechtelsville",
    "sg:classifiers":[
        {
            "category":"Organizations",
            "subcategory":"Religious Organization",
            "type":"Services"
        }
    ],
    "sg:phone":"+1   ",
    "sg:postcode":"19505",
    "sg:province":"PA",
    "sg:tags":[
        "church"
    ],
    "wof:name":"Shepherd of The Hlls Un Chrch",
    "wof:placetype":"venue"
},
  "geometry": {"coordinates":[-75.589805,40.355401],"type":"Point"}
}