{
  "type": "Feature",
  "properties": {
    "addr:full":"203 N Main St Punxsutawney PA 15767",
    "addr:housenumber":"203",
    "addr:postcode":"15767",
    "addr:street":"N Main St",
    "iso:country":"US",
    "sg:address":"203 N Main St",
    "sg:city":"Punxsutawney",
    "sg:classifiers":[
        {
            "category":"Government",
            "subcategory":"Office",
            "type":"Public Place"
        }
    ],
    "sg:phone":"+1 814 938 6630",
    "sg:postcode":"15767",
    "sg:province":"PA",
    "wof:name":"Well Baby Clinic",
    "wof:placetype":"venue"
},
  "geometry": {"coordinates":[-78.99212799999999,40.944246],"type":"Point"}
}