{
  "type": "Feature",
  "properties": {
    "addr:city":"Erie",
    "addr:full":"428 Chestnut Street Erie, Pa 16504",
    "addr:house_number":"428",
    "addr:housenumber":"428",
    "addr:phone":"+1 814-456-5969",
    "addr:postcode":"16504",
    "addr:road":"Chestnut Street",
    "addr:state":"PA",
    "addr:street":"Chestnut St",
    "iso:country":"US",
    "sg:address":"428 Chestnut St",
    "sg:city":"Erie",
    "sg:classifiers":[
        {
            "category":"Museum",
            "type":"Entertainment"
        }
    ],
    "sg:phone":"+1 814 456 5969",
    "sg:postcode":"16507",
    "sg:province":"PA",
    "wof:airports":[
        102524857
    ],
    "wof:name":"Firefighters Historical Museum",
    "wof:placetype":"venue"
},
  "geometry": {"coordinates":[-80.09496,42.12798],"type":"Point"}
}