{
  "type": "Feature",
  "properties": {
    "addr:full":"428 Chestnut St Erie PA 16507",
    "addr:housenumber":"428",
    "addr:postcode":"16507",
    "addr:street":"Chestnut St",
    "iso:country":"US",
    "sg:address":"428 Chestnut St",
    "sg:city":"Erie",
    "sg:classifiers":[
        {
            "category":"Museum",
            "type":"Entertainment"
        }
    ],
    "sg:phone":"+1 814 456 5969",
    "sg:postcode":"16507",
    "sg:province":"PA",
    "wof:name":"Firefighters Historical Museum",
    "wof:placetype":"venue"
},
  "geometry": {"coordinates":[-80.094657,42.127557],"type":"Point"}
}