{
  "type": "Feature",
  "properties": {
    "iso:country":"US",
    "sg:address":"5734 Tulip St",
    "sg:city":"Philadelphia",
    "sg:classifiers":[
        {
            "category":"Building & Trades",
            "subcategory":"Electrical",
            "type":"Services"
        }
    ],
    "sg:phone":"+1 215 535 3950",
    "sg:postcode":"19135",
    "sg:province":"PA",
    "sg:tags":[
        "medical",
        "alarm",
        "install",
        "system"
    ],
    "wof:name":"Treasury Alarm Co Inc",
    "wof:placetype":"venue"
},
  "geometry": {"coordinates":[-75.06129199999999,40.013952],"type":"Point"}
}