{
  "type": "Feature",
  "properties": {
    "iso:country":"US",
    "sg:address":"363 6th Ave",
    "sg:city":"New Kensington",
    "sg:classifiers":[
        {
            "category":"Autos & Motor Vehicles",
            "subcategory":"Automobile Sales",
            "type":"Retail Goods"
        }
    ],
    "sg:phone":"+1 724 335 3443",
    "sg:postcode":"15068",
    "sg:province":"PA",
    "sg:tags":[
        "car",
        "dealer"
    ],
    "wof:name":"Custom Auto & Hot Rod",
    "wof:placetype":"venue"
},
  "geometry": {"coordinates":[-79.76154,40.55504],"type":"Point"}
}