{
  "type": "Feature",
  "properties": {
    "iso:country":"US",
    "sg:address":"212 Magee Ave",
    "sg:city":"Patton",
    "sg:classifiers":[
        {
            "category":"Food & Beverages",
            "subcategory":"Groceries & Convenience Stores",
            "type":"Retail Goods"
        }
    ],
    "sg:phone":"+1   ",
    "sg:postcode":"16668",
    "sg:province":"PA",
    "wof:name":"Country Maid",
    "wof:placetype":"venue"
},
  "geometry": {"coordinates":[-78.643001,40.634236],"type":"Point"}
}