{
  "type": "Feature",
  "properties": {
    "iso:country":"US",
    "sg:address":"2555 W Chester Pike",
    "sg:city":"Broomall",
    "sg:classifiers":[
        {
            "category":"Autos & Motor Vehicles",
            "subcategory":"Motorcycle Sales",
            "type":"Retail Goods"
        }
    ],
    "sg:phone":"+1 610 356 2662",
    "sg:postcode":"19008",
    "sg:province":"PA",
    "sg:tags":[
        "scooter"
    ],
    "sg:website":"www.cycle-city.com",
    "wof:name":"Cycle City",
    "wof:placetype":"venue"
},
  "geometry": {"coordinates":[-75.360998,39.981847],"type":"Point"}
}