{
  "type": "Feature",
  "properties": {
    "iso:country":"US",
    "sg:address":"124 S Market St",
    "sg:city":"Mechanicsburg",
    "sg:classifiers":[
        {
            "category":"Retail",
            "subcategory":"Repair Shop",
            "type":"Services"
        },
        {
            "category":"Shopping",
            "subcategory":"Used Merchandise",
            "type":"Retail Goods"
        }
    ],
    "sg:phone":"+1 717 697 4924",
    "sg:postcode":"17055",
    "sg:province":"PA",
    "sg:tags":[
        "antique",
        "restoring"
    ],
    "wof:name":"Veronique's Antiques",
    "wof:placetype":"venue"
},
  "geometry": {"coordinates":[-77.007301,40.211498],"type":"Point"}
}