{
  "type": "Feature",
  "properties": {
    "iso:country":"US",
    "sg:address":"11 S Beaver St",
    "sg:city":"York",
    "sg:classifiers":[
        {
            "category":"Retail",
            "subcategory":"Repair Shop",
            "type":"Services"
        }
    ],
    "sg:phone":"+1 717 846 6043",
    "sg:postcode":"17401",
    "sg:province":"PA",
    "sg:tags":[
        "high",
        "fidelity",
        "stereophonic"
    ],
    "wof:name":"Sound Odyssey",
    "wof:placetype":"venue"
},
  "geometry": {"coordinates":[-76.72936900000001,39.961436],"type":"Point"}
}