{
  "type": "Feature",
  "properties": {
    "iso:country":"US",
    "sg:address":"4211 Union Deposit Rd",
    "sg:city":"Harrisburg",
    "sg:classifiers":[
        {
            "category":"Restaurant",
            "type":"Food & Drink"
        }
    ],
    "sg:phone":"+1 717 564 9446",
    "sg:postcode":"17111",
    "sg:province":"PA",
    "sg:tags":[
        "eating"
    ],
    "wof:name":"Hong Kong Chef",
    "wof:placetype":"venue"
},
  "geometry": {"coordinates":[-76.814021,40.279091],"type":"Point"}
}