{
  "type": "Feature",
  "properties": {
    "iso:country":"US",
    "sg:address":"178 Sollenberger Rd",
    "sg:city":"Everett",
    "sg:phone":"+1   ",
    "sg:postcode":"15537",
    "sg:province":"PA",
    "sg:tags":[
        "farm",
        "corn"
    ],
    "wof:name":"Lloyd Sollenberger",
    "wof:placetype":"venue"
},
  "geometry": {"coordinates":[-78.329374,39.976561],"type":"Point"}
}