{
  "type": "Feature",
  "properties": {
    "addr:full":"2385 W Cheltenham Ave Ste 37 Philadelphia PA 19150",
    "addr:housenumber":"2385;37",
    "addr:postcode":"19150",
    "addr:street":"W Cheltenham Ave Ste",
    "iso:country":"US",
    "sg:address":"2385 W Cheltenham Ave Ste 37",
    "sg:city":"Philadelphia",
    "sg:classifiers":[
        {
            "category":"Shopping",
            "subcategory":"Baby Store",
            "type":"Retail Goods"
        },
        {
            "category":"Shopping",
            "subcategory":"Shoes",
            "type":"Retail Goods"
        }
    ],
    "sg:phone":"+1 215 887 5808",
    "sg:postcode":"19150",
    "sg:province":"PA",
    "sg:tags":[
        "children's",
        "infant",
        "wear"
    ],
    "sg:website":"http://www.kidsfootlocker.com",
    "wof:name":"Kids Foot Locker",
    "wof:placetype":"venue"
},
  "geometry": {"coordinates":[-75.15652300000001,40.07311],"type":"Point"}
}