{
  "type": "Feature",
  "properties": {
    "iso:country":"US",
    "sg:address":"319 W Walnut St",
    "sg:city":"Perkasie",
    "sg:classifiers":[
        {
            "category":"Shopping",
            "type":"Retail Goods"
        }
    ],
    "sg:phone":"+1 215 453 8398",
    "sg:postcode":"18944",
    "sg:province":"PA",
    "sg:tags":[
        "picture",
        "frame"
    ],
    "wof:name":"Walnut Street Gallery",
    "wof:placetype":"venue"
},
  "geometry": {"coordinates":[-75.29569600000001,40.36997],"type":"Point"}
}