{
  "type": "Feature",
  "properties": {
    "addr:full":"1361 Fruitville Pike Lancaster PA 17601",
    "addr:housenumber":"1361",
    "addr:postcode":"17601",
    "addr:street":"Fruitville Pike",
    "iso:country":"US",
    "sg:address":"1361 Fruitville Pike",
    "sg:city":"Lancaster",
    "sg:classifiers":[
        {
            "category":"Health Services",
            "subcategory":"Doctor",
            "type":"Services"
        }
    ],
    "sg:phone":"+1   ",
    "sg:postcode":"17601",
    "sg:province":"PA",
    "sg:tags":[
        "osteopathic"
    ],
    "wof:name":"Michael A Rakosky Do",
    "wof:placetype":"venue"
},
  "geometry": {"coordinates":[-76.311679,40.057825],"type":"Point"}
}