{
  "type": "Feature",
  "properties": {
    "iso:country":"US",
    "sg:address":"544 Harrison St",
    "sg:city":"Hazleton",
    "sg:classifiers":[
        {
            "category":"Shopping",
            "subcategory":"Hobbies, Toys, & Games",
            "type":"Retail Goods"
        }
    ],
    "sg:phone":"+1 570 455 5698",
    "sg:postcode":"18201",
    "sg:province":"PA",
    "sg:tags":[
        "model",
        "supply"
    ],
    "wof:name":"Northeast Hobby Center",
    "wof:placetype":"venue"
},
  "geometry": {"coordinates":[-75.95989400000001,40.96405],"type":"Point"}
}