{
  "type": "Feature",
  "properties": {
    "iso:country":"US",
    "sg:address":"300 Brush Creek Rd",
    "sg:city":"Warrendale",
    "sg:classifiers":[
        {
            "category":"Banks & Credit Unions",
            "subcategory":"Bank",
            "type":"Services"
        }
    ],
    "sg:phone":"+1   ",
    "sg:postcode":"15086",
    "sg:province":"PA",
    "sg:tags":[
        "state"
    ],
    "wof:name":"Allegheny Co PA US Gov CU",
    "wof:placetype":"venue"
},
  "geometry": {"coordinates":[-80.11623299999999,40.673659],"type":"Point"}
}