{
  "type": "Feature",
  "properties": {
    "addr:full":"592 Whitestown Rd Butler PA 16001",
    "addr:housenumber":"592",
    "addr:postcode":"16001",
    "addr:street":"Whitestown Rd",
    "iso:country":"US",
    "sg:address":"592 Whitestown Rd",
    "sg:city":"Butler",
    "sg:classifiers":[
        {
            "category":"Building & Trades",
            "subcategory":"Plumbing",
            "type":"Services"
        }
    ],
    "sg:phone":"+1   ",
    "sg:postcode":"16001",
    "sg:province":"PA",
    "sg:tags":[
        "contractor"
    ],
    "wof:name":"McDonald Rollin Plumbing & Htg",
    "wof:placetype":"venue"
},
  "geometry": {"coordinates":[-79.964984,40.859746],"type":"Point"}
}