{
  "type": "Feature",
  "properties": {
    "addr:full":"309 N Main St Sellersville PA 18960",
    "addr:housenumber":"309",
    "addr:postcode":"18960",
    "addr:street":"N Main St",
    "iso:country":"US",
    "sg:address":"309 N Main St",
    "sg:city":"Sellersville",
    "sg:classifiers":[
        {
            "category":"Restaurant",
            "type":"Food & Drink"
        }
    ],
    "sg:phone":"+1 215 257 9300",
    "sg:postcode":"18960",
    "sg:province":"PA",
    "sg:tags":[
        "eating"
    ],
    "wof:name":"J T Bankers Saloon & Eatery",
    "wof:placetype":"venue"
},
  "geometry": {"coordinates":[-75.311954,40.36247],"type":"Point"}
}