{
  "type": "Feature",
  "properties": {
    "addr:full":"103 White Tail Pl Honesdale PA 18431",
    "addr:housenumber":"103",
    "addr:postcode":"18431",
    "addr:street":"White Tail Pl",
    "iso:country":"US",
    "sg:address":"103 White Tail Pl",
    "sg:city":"Honesdale",
    "sg:classifiers":[
        {
            "category":"Professional",
            "type":"Services"
        }
    ],
    "sg:phone":"+1   ",
    "sg:postcode":"18431",
    "sg:province":"PA",
    "wof:name":"John Fiorelli",
    "wof:placetype":"venue"
},
  "geometry": {"coordinates":[-75.274141,41.522969],"type":"Point"}
}