{
  "type": "Feature",
  "properties": {
    "addr:full":"100 W Main St Troy PA 16947",
    "addr:housenumber":"100",
    "addr:postcode":"16947",
    "addr:street":"W Main St",
    "iso:country":"US",
    "sg:address":"100 W Main St",
    "sg:city":"Troy",
    "sg:classifiers":[
        {
            "category":"Food & Beverages",
            "subcategory":"Bakery",
            "type":"Retail Goods"
        }
    ],
    "sg:phone":"+1 570 297 4800",
    "sg:postcode":"16947",
    "sg:province":"PA",
    "sg:tags":[
        "baker"
    ],
    "wof:name":"Endless Mountain Donut Co",
    "wof:placetype":"venue"
},
  "geometry": {"coordinates":[-76.790235,41.786231],"type":"Point"}
}