{
  "type": "Feature",
  "properties": {
    "iso:country":"US",
    "sg:address":"101 S Groffdale Rd",
    "sg:city":"Leola",
    "sg:classifiers":[
        {
            "category":"Retail",
            "subcategory":"Animal Services",
            "type":"Services"
        }
    ],
    "sg:phone":"+1 717 656 9744",
    "sg:postcode":"17540",
    "sg:province":"PA",
    "wof:name":"Dog Den",
    "wof:placetype":"venue"
},
  "geometry": {"coordinates":[-76.136763,40.085693],"type":"Point"}
}