{
  "type": "Feature",
  "properties": {
    "addr:full":"5426 Hardt Rd Gibsonia PA 15044",
    "addr:housenumber":"5426",
    "addr:postcode":"15044",
    "addr:street":"Hardt Rd",
    "iso:country":"US",
    "sg:address":"5426 Hardt Rd",
    "sg:city":"Gibsonia",
    "sg:classifiers":[
        {
            "category":"Building & Trades",
            "subcategory":"Electrical",
            "type":"Services"
        },
        {
            "category":"Retail",
            "subcategory":"Auto Repair",
            "type":"Services"
        }
    ],
    "sg:phone":"+1 724 502 4055",
    "sg:postcode":"15044",
    "sg:province":"PA",
    "sg:tags":[
        "automobile",
        "electrician",
        "electric"
    ],
    "sg:website":"http://frequencyelectric.com",
    "wof:name":"Frequency Electric, Inc.",
    "wof:placetype":"venue"
},
  "geometry": {"coordinates":[-79.97601299999999,40.628077],"type":"Point"}
}