{
  "type": "Feature",
  "properties": {
    "addr:full":"4956 Fitler St Philadelphia PA 19114",
    "addr:housenumber":"4956",
    "addr:postcode":"19114",
    "addr:street":"Fitler St",
    "iso:country":"US",
    "sg:address":"4956 Fitler St",
    "sg:city":"Philadelphia",
    "sg:classifiers":[
        {
            "category":"Organizations",
            "subcategory":"Community Association",
            "type":"Services"
        }
    ],
    "sg:phone":"+1   ",
    "sg:postcode":"19114",
    "sg:province":"PA",
    "wof:name":"Rivers Bend Condominium Assn",
    "wof:placetype":"venue"
},
  "geometry": {"coordinates":[-74.98500300000001,40.052402],"type":"Point"}
}