{
  "type": "Feature",
  "properties": {
    "addr:full":"918 Town Center Doylestown PA 18901",
    "addr:housenumber":"918",
    "addr:postcode":"18901",
    "addr:street":"Town",
    "iso:country":"US",
    "sg:address":"918 Town Center",
    "sg:city":"Doylestown",
    "sg:classifiers":[
        {
            "category":"Insurance",
            "subcategory":"Hazard Insurance",
            "type":"Services"
        }
    ],
    "sg:phone":"+1   ",
    "sg:postcode":"18901",
    "sg:province":"PA",
    "wof:name":"Liberty Mutual Group",
    "wof:placetype":"venue"
},
  "geometry": {"coordinates":[-75.190162,40.298533],"type":"Point"}
}