{
  "type": "Feature",
  "properties": {
    "iso:country":"US",
    "sg:address":"1501 N Canal St",
    "sg:city":"Pittsburgh",
    "sg:classifiers":[
        {
            "category":"Food & Beverages",
            "subcategory":"Groceries & Convenience Stores",
            "type":"Retail Goods"
        }
    ],
    "sg:phone":"+1 412 781 4426",
    "sg:postcode":"15215",
    "sg:province":"PA",
    "sg:tags":[
        "grocer"
    ],
    "wof:name":"Co Go's Co",
    "wof:placetype":"venue"
},
  "geometry": {"coordinates":[-79.925476,40.497296],"type":"Point"}
}