{
  "type": "Feature",
  "properties": {
    "iso:country":"US",
    "sg:address":"318 Holiday Dr",
    "sg:city":"Pittsburgh",
    "sg:classifiers":[
        {
            "category":"Professional",
            "subcategory":"Engineering",
            "type":"Services"
        }
    ],
    "sg:phone":"+1 412 367 7990",
    "sg:postcode":"15237",
    "sg:province":"PA",
    "sg:tags":[
        "engineer"
    ],
    "wof:name":"Advanced Engineering Svc",
    "wof:placetype":"venue"
},
  "geometry": {"coordinates":[-80.04659100000001,40.548885],"type":"Point"}
}