{
  "type": "Feature",
  "properties": {
    "iso:country":"US",
    "sg:address":"509 Race St",
    "sg:city":"Scranton",
    "sg:classifiers":[
        {
            "category":"Restaurant",
            "type":"Food & Drink"
        }
    ],
    "sg:phone":"+1   ",
    "sg:postcode":"18509",
    "sg:province":"PA",
    "sg:tags":[
        "eating"
    ],
    "wof:name":"Green Ridge Restaurant",
    "wof:placetype":"venue"
},
  "geometry": {"coordinates":[-75.646944,41.436456],"type":"Point"}
}