{
  "type": "Feature",
  "properties": {
    "iso:country":"US",
    "sg:address":"534 Main St",
    "sg:city":"Bethlehem",
    "sg:classifiers":[
        {
            "category":"Shopping",
            "subcategory":"Gifts & Souvenirs",
            "type":"Retail Goods"
        }
    ],
    "sg:phone":"+1 610 866 3244",
    "sg:postcode":"18018",
    "sg:province":"PA",
    "sg:tags":[
        "flower"
    ],
    "sg:website":"www.donegal.com/",
    "wof:name":"Donegal Square",
    "wof:placetype":"venue"
},
  "geometry": {"coordinates":[-75.381934,40.621327],"type":"Point"}
}