{
  "type": "Feature",
  "properties": {
    "addr:full":"415 Upper Demunds Rd Dallas PA 18612",
    "addr:housenumber":"415",
    "addr:postcode":"18612",
    "addr:street":"Upper Demunds Rd",
    "iso:country":"US",
    "sg:address":"415 Upper Demunds Rd",
    "sg:city":"Dallas",
    "sg:classifiers":[
        {
            "category":"Freight",
            "type":"Transportation"
        }
    ],
    "sg:phone":"+1 570 674 4698",
    "sg:postcode":"18612",
    "sg:province":"PA",
    "sg:tags":[
        "trucking"
    ],
    "sg:website":"www.prioritytrans.com",
    "wof:name":"Priority Transportation",
    "wof:placetype":"venue"
},
  "geometry": {"coordinates":[-75.945565,41.376864],"type":"Point"}
}