{
  "type": "Feature",
  "properties": {
    "iso:country":"US",
    "sg:address":"1009 N Lawrence St",
    "sg:city":"Philadelphia",
    "sg:classifiers":[
        {
            "category":"Shopping",
            "subcategory":"Computers & Home Electronics",
            "type":"Retail Goods"
        }
    ],
    "sg:phone":"+1 215 922 6639",
    "sg:postcode":"19123",
    "sg:province":"PA",
    "sg:tags":[
        "software"
    ],
    "wof:name":"Applied Software Strategies",
    "wof:placetype":"venue"
},
  "geometry": {"coordinates":[-75.14424,39.968822],"type":"Point"}
}