{
  "type": "Feature",
  "properties": {
    "addr:full":"520 Twining Rd Dresher PA 19025",
    "addr:housenumber":"520",
    "addr:postcode":"19025",
    "addr:street":"Twining Rd",
    "iso:country":"US",
    "sg:address":"520 Twining Rd",
    "sg:city":"Dresher",
    "sg:classifiers":[
        {
            "category":"Education",
            "subcategory":"School",
            "type":"Public Place"
        }
    ],
    "sg:phone":"+1 215 576 3251",
    "sg:postcode":"19025",
    "sg:province":"PA",
    "wof:name":"Sandy Run Middle School",
    "wof:placetype":"venue"
},
  "geometry": {"coordinates":[-75.167091,40.128623],"type":"Point"}
}