{
  "type": "Feature",
  "properties": {
    "addr:full":"4180 William Penn Hwy Murrysville PA 15668",
    "addr:housenumber":"4180",
    "addr:postcode":"15668",
    "addr:street":"William Penn Hwy",
    "iso:country":"US",
    "sg:address":"4180 William Penn Hwy",
    "sg:city":"Murrysville",
    "sg:classifiers":[
        {
            "category":"Autos & Motor Vehicles",
            "subcategory":"Fuel & Gas Station",
            "type":"Retail Goods"
        }
    ],
    "sg:phone":"+1   ",
    "sg:postcode":"15668",
    "sg:province":"PA",
    "sg:tags":[
        "convenience",
        "store"
    ],
    "wof:name":"Citgo",
    "wof:placetype":"venue"
},
  "geometry": {"coordinates":[-79.68944999999999,40.427691],"type":"Point"}
}