{
  "type": "Feature",
  "properties": {
    "iso:country":"US",
    "sg:address":"1030 W Lancaster Ave",
    "sg:city":"Bryn Mawr",
    "sg:classifiers":[
        {
            "category":"Health Services",
            "subcategory":"Doctor",
            "type":"Services"
        }
    ],
    "sg:phone":"+1 610 525 1113",
    "sg:postcode":"19010",
    "sg:province":"PA",
    "sg:tags":[
        "physician",
        "surgeon"
    ],
    "wof:name":"Christina Herring MD",
    "wof:placetype":"venue"
},
  "geometry": {"coordinates":[-75.324243,40.024274],"type":"Point"}
}