{
  "type": "Feature",
  "properties": {
    "iso:country":"US",
    "sg:address":"105 Winding Hill Dr",
    "sg:city":"Lancaster",
    "sg:classifiers":[
        {
            "category":"Retail",
            "subcategory":"Repair Shop",
            "type":"Services"
        }
    ],
    "sg:phone":"+1   ",
    "sg:postcode":"17601",
    "sg:province":"PA",
    "wof:name":"Furniture Medic of Lancaster",
    "wof:placetype":"venue"
},
  "geometry": {"coordinates":[-76.38140799999999,40.066143],"type":"Point"}
}