{
  "type": "Feature",
  "properties": {
    "addr:full":"4231 Buffalo Rd Erie PA 16510",
    "addr:housenumber":"4231",
    "addr:postcode":"16510",
    "addr:street":"Buffalo Rd",
    "iso:country":"US",
    "sg:address":"4231 Buffalo Rd",
    "sg:city":"Erie",
    "sg:classifiers":[
        {
            "category":"Shopping",
            "subcategory":"Discount & Variety Stores",
            "type":"Retail Goods"
        }
    ],
    "sg:phone":"+1 814 899 0956",
    "sg:postcode":"16510",
    "sg:province":"PA",
    "wof:name":"D & K Store Inc",
    "wof:placetype":"venue"
},
  "geometry": {"coordinates":[-80.00623299999999,42.144301],"type":"Point"}
}