{
  "type": "Feature",
  "properties": {
    "iso:country":"US",
    "sg:address":"360 Riemer Rd",
    "sg:city":"Sarver",
    "sg:classifiers":[
        {
            "category":"Mining & Drilling",
            "type":"Manufacturing & Wholesale Goods"
        }
    ],
    "sg:phone":"+1 724 352 1541",
    "sg:postcode":"16055",
    "sg:province":"PA",
    "sg:tags":[
        "company"
    ],
    "wof:name":"R C Kadyk Corp",
    "wof:placetype":"venue"
},
  "geometry": {"coordinates":[-79.78313,40.742501],"type":"Point"}
}