{
  "type": "Feature",
  "properties": {
    "addr:full":"1321 Freedom Rd Cranberry Twp PA 16066",
    "addr:housenumber":"1321",
    "addr:postcode":"16066",
    "addr:street":"Freedom Rd",
    "iso:country":"US",
    "sg:address":"1321 Freedom Rd",
    "sg:city":"Cranberry Twp",
    "sg:classifiers":[
        {
            "category":"Social Services",
            "subcategory":"Child Care",
            "type":"Services"
        }
    ],
    "sg:phone":"+1 724 776 2122",
    "sg:postcode":"16066",
    "sg:province":"PA",
    "wof:name":"Kinder Care Learning Ctr",
    "wof:placetype":"venue"
},
  "geometry": {"coordinates":[-80.106481,40.685026],"type":"Point"}
}