{
  "type": "Feature",
  "properties": {
    "iso:country":"US",
    "sg:address":"12494 E Troy Rd",
    "sg:city":"Titusville",
    "sg:classifiers":[
        {
            "category":"Health Services",
            "subcategory":"Doctor",
            "type":"Services"
        }
    ],
    "sg:phone":"+1 814 827 4185",
    "sg:postcode":"16354",
    "sg:province":"PA",
    "sg:tags":[
        "physician",
        "surgeon"
    ],
    "wof:name":"Byron Donovan MD",
    "wof:placetype":"venue"
},
  "geometry": {"coordinates":[-79.757718,41.638071],"type":"Point"}
}