{
  "type": "Feature",
  "properties": {
    "iso:country":"US",
    "sg:address":"1869 S 4th St",
    "sg:city":"Allentown",
    "sg:classifiers":[
        {
            "category":"Restaurant",
            "type":"Food & Drink"
        }
    ],
    "sg:phone":"+1 610 797 1924",
    "sg:postcode":"18103",
    "sg:province":"PA",
    "sg:website":"www.shakewells.com",
    "wof:name":"Oliver Shakewell's",
    "wof:placetype":"venue"
},
  "geometry": {"coordinates":[-75.45590199999999,40.580601],"type":"Point"}
}