{
  "type": "Feature",
  "properties": {
    "iso:country":"US",
    "sg:address":"1320 S 21st St",
    "sg:city":"Philadelphia",
    "sg:classifiers":[
        {
            "category":"Restaurant",
            "type":"Food & Drink"
        }
    ],
    "sg:phone":"+1 215 336 4138",
    "sg:postcode":"19146",
    "sg:province":"PA",
    "sg:tags":[
        "eating"
    ],
    "wof:name":"Huyon Sea Food",
    "wof:placetype":"venue"
},
  "geometry": {"coordinates":[-75.17930200000001,39.934394],"type":"Point"}
}