{
  "type": "Feature",
  "properties": {
    "addr:full":"647 Georgetown Rd Nazareth PA 18064",
    "addr:housenumber":"647",
    "addr:postcode":"18064",
    "addr:street":"Georgetown Rd",
    "iso:country":"US",
    "sg:address":"647 Georgetown Rd",
    "sg:city":"Nazareth",
    "sg:classifiers":[
        {
            "category":"Autos & Motor Vehicles",
            "subcategory":"Fuel & Gas Station",
            "type":"Retail Goods"
        }
    ],
    "sg:phone":"+1 610 837 6311",
    "sg:postcode":"18064",
    "sg:province":"PA",
    "sg:tags":[
        "oil"
    ],
    "wof:name":"Northampton County Seed Co",
    "wof:placetype":"venue"
},
  "geometry": {"coordinates":[-75.353112,40.714174],"type":"Point"}
}