{
  "type": "Feature",
  "properties": {
    "iso:country":"US",
    "sg:address":"717 Liberty Ave",
    "sg:city":"Pittsburgh",
    "sg:classifiers":[
        {
            "category":"Health Services",
            "subcategory":"Doctor",
            "type":"Services"
        }
    ],
    "sg:phone":"+1 412 471 2124",
    "sg:postcode":"15222",
    "sg:province":"PA",
    "sg:tags":[
        "podiatrist"
    ],
    "wof:name":"Haubelt Lynne J Podiatrst",
    "wof:placetype":"venue"
},
  "geometry": {"coordinates":[-79.999802,40.442501],"type":"Point"}
}