{
  "type": "Feature",
  "properties": {
    "iso:country":"US",
    "sg:address":"301 S 8th St Ste 2C",
    "sg:city":"Philadelphia",
    "sg:classifiers":[
        {
            "category":"Health Services",
            "subcategory":"Doctor",
            "type":"Services"
        }
    ],
    "sg:phone":"+1 215 829 5022",
    "sg:postcode":"19106",
    "sg:province":"PA",
    "wof:name":"Lackman Richard MD",
    "wof:placetype":"venue"
},
  "geometry": {"coordinates":[-75.154701,39.945801],"type":"Point"}
}