{
  "type": "Feature",
  "properties": {
    "iso:country":"US",
    "sg:address":"8920 Walnut St",
    "sg:city":"Westmoreland Cty",
    "sg:classifiers":[
        {
            "category":"Manufacturing",
            "subcategory":"Printing",
            "type":"Manufacturing & Wholesale Goods"
        }
    ],
    "sg:phone":"+1 724 863 3137",
    "sg:postcode":"15692",
    "sg:province":"PA",
    "sg:tags":[
        "commercial"
    ],
    "wof:name":"Jiffy Print",
    "wof:placetype":"venue"
},
  "geometry": {"coordinates":[-79.680115,40.330997],"type":"Point"}
}