{
  "type": "Feature",
  "properties": {
    "addr:full":"239 Red Bridge Rd Kintnersville PA 18930",
    "addr:housenumber":"239",
    "addr:postcode":"18930",
    "addr:street":"Red Bridge Rd",
    "iso:country":"US",
    "sg:address":"239 Red Bridge Rd",
    "sg:city":"Kintnersville",
    "sg:classifiers":[
        {
            "category":"Retail",
            "subcategory":"Animal Services",
            "type":"Services"
        }
    ],
    "sg:phone":"+1 610 749 2544",
    "sg:postcode":"18930",
    "sg:province":"PA",
    "sg:tags":[
        "pet"
    ],
    "wof:name":"Teddy's Pet Care",
    "wof:placetype":"venue"
},
  "geometry": {"coordinates":[-75.207916,40.586388],"type":"Point"}
}