{
  "type": "Feature",
  "properties": {
    "iso:country":"US",
    "sg:address":"1621 Lincoln Ave",
    "sg:city":"Pittsburgh",
    "sg:classifiers":[
        {
            "category":"Real Estate",
            "subcategory":"Real Estate Services",
            "type":"Services"
        },
        {
            "category":"Real Estate",
            "subcategory":"Real Estate Agent",
            "type":"Services"
        }
    ],
    "sg:phone":"+1 412 363 4169",
    "sg:postcode":"15206",
    "sg:province":"PA",
    "sg:tags":[
        "management"
    ],
    "wof:name":"Eva P. Mitchell Housing Lp",
    "wof:placetype":"venue"
},
  "geometry": {"coordinates":[-79.89254,40.470605],"type":"Point"}
}