{
  "type": "Feature",
  "properties": {
    "iso:country":"US",
    "sg:address":"450 E College Ave",
    "sg:city":"Bellefonte",
    "sg:classifiers":[
        {
            "category":"Building & Trades",
            "subcategory":"Construction",
            "type":"Services"
        },
        {
            "category":"Mining & Drilling",
            "type":"Manufacturing & Wholesale Goods"
        }
    ],
    "sg:phone":"+1 814 359 3411",
    "sg:postcode":"16823",
    "sg:province":"PA",
    "sg:tags":[
        "concrete",
        "stone",
        "contractor",
        "asphalt",
        "mfg"
    ],
    "wof:name":"Central Valley Aggregates",
    "wof:placetype":"venue"
},
  "geometry": {"coordinates":[-77.68022000000001,40.912362],"type":"Point"}
}