{
  "type": "Feature",
  "properties": {
    "iso:country":"US",
    "sg:address":"60 Shearer Dr",
    "sg:city":"Dillsburg",
    "sg:phone":"+1   ",
    "sg:postcode":"17019",
    "sg:province":"PA",
    "sg:tags":[
        "farm",
        "field",
        "crop"
    ],
    "wof:name":"Carl Shearer",
    "wof:placetype":"venue"
},
  "geometry": {"coordinates":[-77.00782700000001,40.083384],"type":"Point"}
}