{
  "type": "Feature",
  "properties": {
    "addr:full":"699 Washington Rd Pittsburgh PA 15228",
    "addr:housenumber":"699",
    "addr:postcode":"15228",
    "addr:street":"Washington Rd",
    "iso:country":"US",
    "sg:address":"699 Washington Rd",
    "sg:city":"Pittsburgh",
    "sg:classifiers":[
        {
            "category":"Shopping",
            "subcategory":"Jewelry",
            "type":"Retail Goods"
        }
    ],
    "sg:phone":"+1   ",
    "sg:postcode":"15228",
    "sg:province":"PA",
    "wof:name":"Jacqueline Rossi",
    "wof:placetype":"venue"
},
  "geometry": {"coordinates":[-80.045024,40.379583],"type":"Point"}
}