{
  "type": "Feature",
  "properties": {
    "iso:country":"US",
    "sg:address":"315 Grant St",
    "sg:city":"Meyersdale",
    "sg:classifiers":[
        {
            "category":"Manufacturing",
            "subcategory":"Apparel",
            "type":"Manufacturing & Wholesale Goods"
        }
    ],
    "sg:phone":"+1 814 634 5924",
    "sg:postcode":"15552",
    "sg:province":"PA",
    "sg:tags":[
        "shirt"
    ],
    "wof:name":"Meyersdale Manufacturing Co",
    "wof:placetype":"venue"
},
  "geometry": {"coordinates":[-79.027956,39.81438],"type":"Point"}
}