{
  "type": "Feature",
  "properties": {
    "addr:full":"899 S Chiques Rd Manheim PA 17545",
    "addr:housenumber":"899",
    "addr:postcode":"17545",
    "addr:street":"S Chiques Rd",
    "iso:country":"US",
    "sg:address":"899 S Chiques Rd",
    "sg:city":"Manheim",
    "sg:classifiers":[
        {
            "category":"Organizations",
            "subcategory":"Religious Organization",
            "type":"Services"
        }
    ],
    "sg:phone":"+1 717 859 3443",
    "sg:postcode":"17545",
    "sg:province":"PA",
    "wof:name":"Associates For Biblical Rsrch",
    "wof:placetype":"venue"
},
  "geometry": {"coordinates":[-76.445426,40.110999],"type":"Point"}
}