{
  "type": "Feature",
  "properties": {
    "iso:country":"US",
    "sg:address":"470 Diablo Dr",
    "sg:city":"Pittsburgh",
    "sg:classifiers":[
        {
            "category":"Building & Trades",
            "subcategory":"Construction",
            "type":"Services"
        }
    ],
    "sg:phone":"+1   ",
    "sg:postcode":"15241",
    "sg:province":"PA",
    "sg:tags":[
        "hanging",
        "contractor"
    ],
    "wof:name":"Custom House Painting",
    "wof:placetype":"venue"
},
  "geometry": {"coordinates":[-80.07249,40.306257],"type":"Point"}
}