{
  "type": "Feature",
  "properties": {
    "iso:country":"US",
    "sg:address":"1523 Spring Garden St",
    "sg:city":"Philadelphia",
    "sg:classifiers":[
        {
            "category":"Arts & Performance",
            "subcategory":"Theater",
            "type":"Entertainment"
        }
    ],
    "sg:phone":"+1   ",
    "sg:postcode":"19130",
    "sg:province":"PA",
    "sg:tags":[
        "psychic",
        "studio"
    ],
    "wof:name":"Daisy George",
    "wof:placetype":"venue"
},
  "geometry": {"coordinates":[-75.164377,39.962941],"type":"Point"}
}