{
  "type": "Feature",
  "properties": {
    "addr:full":"3929 Admiral Peary Hwy Ebensburg PA 15931",
    "addr:housenumber":"3929",
    "addr:postcode":"15931",
    "addr:street":"Admiral Peary Hwy",
    "iso:country":"US",
    "sg:address":"3929 Admiral Peary Hwy",
    "sg:city":"Ebensburg",
    "sg:classifiers":[
        {
            "category":"Autos & Motor Vehicles",
            "subcategory":"Automobile Sales",
            "type":"Retail Goods"
        }
    ],
    "sg:phone":"+1 814 472 9550",
    "sg:postcode":"15931",
    "sg:province":"PA",
    "sg:tags":[
        "new",
        "car"
    ],
    "sg:website":"http://www.gmoutlet.com",
    "wof:name":"James E Black Cadillac",
    "wof:placetype":"venue"
},
  "geometry": {"coordinates":[-78.70208700000001,40.48011],"type":"Point"}
}