{
  "type": "Feature",
  "properties": {
    "iso:country":"US",
    "sg:address":"2001 Park Manor Blvd",
    "sg:city":"Pittsburgh",
    "sg:classifiers":[
        {
            "category":"Shopping",
            "subcategory":"Hobbies, Toys, & Games",
            "type":"Retail Goods"
        }
    ],
    "sg:phone":"+1 412 787 1770",
    "sg:postcode":"15205",
    "sg:province":"PA",
    "sg:tags":[
        "toy",
        "store"
    ],
    "sg:website":"www.toysrus.com",
    "wof:name":"Toys R Us",
    "wof:placetype":"venue"
},
  "geometry": {"coordinates":[-80.167675,40.452223],"type":"Point"}
}