{
  "type": "Feature",
  "properties": {
    "iso:country":"US",
    "sg:address":"109 Alyson Dr",
    "sg:city":"Canonsburg",
    "sg:classifiers":[
        {
            "category":"Professional",
            "subcategory":"Management & Consulting",
            "type":"Services"
        }
    ],
    "sg:phone":"+1 724 296 6500",
    "sg:postcode":"15317",
    "sg:province":"PA",
    "sg:tags":[
        "consultant"
    ],
    "wof:name":"Redpointe",
    "wof:placetype":"venue"
},
  "geometry": {"coordinates":[-80.07668,40.275551],"type":"Point"}
}