{
  "type": "Feature",
  "properties": {
    "iso:country":"US",
    "sg:address":"259 Seaward Ave",
    "sg:city":"Bradford",
    "sg:classifiers":[
        {
            "category":"Retail",
            "subcategory":"Veterinary Services",
            "type":"Services"
        }
    ],
    "sg:phone":"+1   ",
    "sg:postcode":"16701",
    "sg:province":"PA",
    "wof:name":"McKean County Animal Hospital",
    "wof:placetype":"venue"
},
  "geometry": {"coordinates":[-78.62895899999999,41.977724],"type":"Point"}
}