{
  "type": "Feature",
  "properties": {
    "iso:country":"US",
    "sg:address":"3608 Freemansburg Ave",
    "sg:city":"Bethlehem",
    "sg:classifiers":[
        {
            "category":"Retail",
            "subcategory":"Auto Repair",
            "type":"Services"
        }
    ],
    "sg:phone":"+1 610 866 9041",
    "sg:postcode":"18020",
    "sg:province":"PA",
    "sg:tags":[
        "repairing",
        "automobile"
    ],
    "wof:name":"Pagats Auto Svc",
    "wof:placetype":"venue"
},
  "geometry": {"coordinates":[-75.324923,40.641545],"type":"Point"}
}