{
  "type": "Feature",
  "properties": {
    "addr:full":"4034 Lancaster Ave Philadelphia PA 19104",
    "addr:housenumber":"4034",
    "addr:postcode":"19104",
    "addr:street":"Lancaster Ave",
    "iso:country":"US",
    "sg:address":"4034 Lancaster Ave",
    "sg:city":"Philadelphia",
    "sg:classifiers":[
        {
            "category":"Shopping",
            "subcategory":"Shoes",
            "type":"Retail Goods"
        }
    ],
    "sg:phone":"+1 215 387 7229",
    "sg:postcode":"19104",
    "sg:province":"PA",
    "sg:website":"www.giantshoes.com",
    "wof:name":"Giant Shoes & Apparel",
    "wof:placetype":"venue"
},
  "geometry": {"coordinates":[-75.203802,39.963937],"type":"Point"}
}