{
  "type": "Feature",
  "properties": {
    "iso:country":"US",
    "sg:address":"7248 Tilghman St",
    "sg:city":"Allentown",
    "sg:classifiers":[
        {
            "category":"Real Estate",
            "subcategory":"Real Estate Operator",
            "type":"Services"
        }
    ],
    "sg:phone":"+1   ",
    "sg:postcode":"18106",
    "sg:province":"PA",
    "sg:tags":[
        "property",
        "management"
    ],
    "wof:name":"Aimco",
    "wof:placetype":"venue"
},
  "geometry": {"coordinates":[-75.614998,40.58666],"type":"Point"}
}