{
  "type": "Feature",
  "properties": {
    "addr:full":"283 S 52nd St 85S Philadelphia PA 19139",
    "addr:housenumber":"283;85s",
    "addr:postcode":"19139",
    "addr:street":"S 52Nd St",
    "iso:country":"US",
    "sg:address":"283 S 52nd St 85S",
    "sg:city":"Philadelphia",
    "sg:classifiers":[
        {
            "category":"Coffee & Tea",
            "type":"Food & Drink"
        },
        {
            "category":"Restaurant",
            "type":"Food & Drink"
        }
    ],
    "sg:phone":"+1 215 748 1655",
    "sg:postcode":"19139",
    "sg:province":"PA",
    "sg:tags":[
        "espresso"
    ],
    "wof:name":"Georges Southern Cafe",
    "wof:placetype":"venue"
},
  "geometry": {"coordinates":[-75.225948,39.954905],"type":"Point"}
}