{
  "type": "Feature",
  "properties": {
    "iso:country":"US",
    "sg:address":"602 E Mahoning St",
    "sg:city":"Punxsutawney",
    "sg:classifiers":[
        {
            "category":"Social Services",
            "subcategory":"Job Training",
            "type":"Services"
        }
    ],
    "sg:phone":"+1 814 938 1076",
    "sg:postcode":"15767",
    "sg:province":"PA",
    "sg:tags":[
        "employment"
    ],
    "sg:website":"www.pacareerlink.state.pa.us",
    "wof:name":"North Central Pa Regional Ofc",
    "wof:placetype":"venue"
},
  "geometry": {"coordinates":[-78.96266900000001,40.94448],"type":"Point"}
}