{
  "type": "Feature",
  "properties": {
    "iso:country":"US",
    "sg:address":"228 W 7th Ave",
    "sg:city":"Tarentum",
    "sg:classifiers":[
        {
            "category":"Retail",
            "subcategory":"Repair Shop",
            "type":"Services"
        }
    ],
    "sg:phone":"+1   ",
    "sg:postcode":"15084",
    "sg:province":"PA",
    "sg:tags":[
        "appliance",
        "household",
        "electrical"
    ],
    "wof:name":"Babinsacks Repairs & Sales",
    "wof:placetype":"venue"
},
  "geometry": {"coordinates":[-79.762114,40.599633],"type":"Point"}
}