{
  "type": "Feature",
  "properties": {
    "addr:full":"217 Bustleton Pike Feasterville Trevose PA 19053",
    "addr:housenumber":"217",
    "addr:postcode":"19053",
    "addr:street":"Bustleton Pike",
    "iso:country":"US",
    "sg:address":"217 Bustleton Pike",
    "sg:city":"Feasterville Trevose",
    "sg:classifiers":[
        {
            "category":"Building & Trades",
            "subcategory":"Plumbing",
            "type":"Services"
        }
    ],
    "sg:phone":"+1   ",
    "sg:postcode":"19053",
    "sg:province":"PA",
    "sg:tags":[
        "contractor"
    ],
    "wof:name":"Atlas Heating & Cooling",
    "wof:placetype":"venue"
},
  "geometry": {"coordinates":[-75.005994,40.141617],"type":"Point"}
}