{
  "type": "Feature",
  "properties": {
    "iso:country":"US",
    "sg:address":"375 Farview Rd",
    "sg:city":"Hamburg",
    "sg:classifiers":[
        {
            "category":"Sports & Exercise",
            "subcategory":"Golf",
            "type":"Entertainment"
        }
    ],
    "sg:phone":"+1 610 562 0660",
    "sg:postcode":"19526",
    "sg:province":"PA",
    "sg:tags":[
        "course"
    ],
    "wof:name":"Farview Greens Golf Club",
    "wof:placetype":"venue"
},
  "geometry": {"coordinates":[-75.910427,40.527535],"type":"Point"}
}