{
  "type": "Feature",
  "properties": {
    "addr:full":"905 Big Oak Rd Yardley PA 19067",
    "addr:housenumber":"905",
    "addr:postcode":"19067",
    "addr:street":"Big Oak Rd",
    "iso:country":"US",
    "sg:address":"905 Big Oak Rd",
    "sg:city":"Yardley",
    "sg:classifiers":[
        {
            "category":"Organizations",
            "subcategory":"Religious Organization",
            "type":"Services"
        }
    ],
    "sg:phone":"+1 215 295 3613",
    "sg:postcode":"19067",
    "sg:province":"PA",
    "wof:name":"Center For Jewish Life & Learn",
    "wof:placetype":"venue"
},
  "geometry": {"coordinates":[-74.83033399999999,40.207402],"type":"Point"}
}