{
  "type": "Feature",
  "properties": {
    "addr:full":"78 N Pennsylvania Ave Morrisville PA 19067",
    "addr:housenumber":"78",
    "addr:postcode":"19067",
    "addr:street":"N Pennsylvania Ave",
    "iso:country":"US",
    "sg:address":"78 N Pennsylvania Ave",
    "sg:city":"Morrisville",
    "sg:classifiers":[
        {
            "category":"Building & Trades",
            "subcategory":"Plumbing",
            "type":"Services"
        }
    ],
    "sg:phone":"+1   ",
    "sg:postcode":"19067",
    "sg:province":"PA",
    "sg:tags":[
        "plumbing",
        "mechanical",
        "carpentry",
        "contractor"
    ],
    "wof:name":"Rti Mechanical Constructors",
    "wof:placetype":"venue"
},
  "geometry": {"coordinates":[-74.775661,40.208405],"type":"Point"}
}