{
  "type": "Feature",
  "properties": {
    "iso:country":"US",
    "sg:address":"3745 Mc Clelland Ave",
    "sg:city":"Erie",
    "sg:classifiers":[
        {
            "category":"Food & Beverages",
            "subcategory":"Groceries & Convenience Stores",
            "type":"Retail Goods"
        }
    ],
    "sg:phone":"+1   ",
    "sg:postcode":"16510",
    "sg:province":"PA",
    "wof:name":"Pennz Mart",
    "wof:placetype":"venue"
},
  "geometry": {"coordinates":[-80.01683,42.121159],"type":"Point"}
}