{
  "type": "Feature",
  "properties": {
    "addr:full":"3787 William Penn Ave Johnstown PA 15909",
    "addr:housenumber":"3787",
    "addr:postcode":"15909",
    "addr:street":"William Penn Ave",
    "iso:country":"US",
    "sg:address":"3787 William Penn Ave",
    "sg:city":"Johnstown",
    "sg:classifiers":[
        {
            "category":"Autos & Motor Vehicles",
            "subcategory":"Automobile Sales",
            "type":"Retail Goods"
        }
    ],
    "sg:phone":"+1 814 749 6933",
    "sg:postcode":"15909",
    "sg:province":"PA",
    "sg:tags":[
        "car",
        "dealer"
    ],
    "wof:name":"Mundy's Corner Auto Sales",
    "wof:placetype":"venue"
},
  "geometry": {"coordinates":[-78.841605,40.444748],"type":"Point"}
}