{
  "type": "Feature",
  "properties": {
    "iso:country":"US",
    "sg:address":"339 Hidden River Rd",
    "sg:city":"Narberth",
    "sg:classifiers":[
        {
            "category":"Banks & Credit Unions",
            "subcategory":"Investment Brokerage",
            "type":"Services"
        }
    ],
    "sg:phone":"+1   ",
    "sg:postcode":"19072",
    "sg:province":"PA",
    "sg:tags":[
        "security"
    ],
    "wof:name":"Consolidated Mortage Service",
    "wof:placetype":"venue"
},
  "geometry": {"coordinates":[-75.247837,40.034407],"type":"Point"}
}