{
  "type": "Feature",
  "properties": {
    "iso:country":"US",
    "sg:address":"38 S Kirklyn Ave",
    "sg:city":"Upper Darby",
    "sg:classifiers":[
        {
            "category":"Professional",
            "type":"Services"
        }
    ],
    "sg:phone":"+1   ",
    "sg:postcode":"19082",
    "sg:province":"PA",
    "wof:name":"William Deegan",
    "wof:placetype":"venue"
},
  "geometry": {"coordinates":[-75.290733,39.965929],"type":"Point"}
}