{
  "type": "Feature",
  "properties": {
    "addr:full":"835 Old York Rd Jenkintown PA 19046",
    "addr:housenumber":"835",
    "addr:postcode":"19046",
    "addr:street":"Old York Rd",
    "iso:country":"US",
    "sg:address":"835 Old York Rd",
    "sg:city":"Jenkintown",
    "sg:classifiers":[
        {
            "category":"Banks & Credit Unions",
            "subcategory":"Investment Brokerage",
            "type":"Services"
        },
        {
            "category":"Shopping",
            "subcategory":"Music",
            "type":"Retail Goods"
        },
        {
            "category":"Shopping",
            "subcategory":"Computers & Home Electronics",
            "type":"Retail Goods"
        },
        {
            "category":"Shopping",
            "subcategory":"Gifts & Souvenirs",
            "type":"Retail Goods"
        },
        {
            "category":"Utilities",
            "subcategory":"Mobile Phone",
            "type":"Services"
        },
        {
            "category":"Communications",
            "subcategory":"Film & Video Production",
            "type":"Services"
        },
        {
            "category":"Shopping",
            "subcategory":"Books",
            "type":"Retail Goods"
        },
        {
            "category":"Wholesale",
            "subcategory":"Books, Periodicals, & Newspapers",
            "type":"Manufacturing & Wholesale Goods"
        }
    ],
    "sg:phone":"+1 215 886 5366",
    "sg:postcode":"19046",
    "sg:province":"PA",
    "sg:tags":[
        "shop",
        "educational",
        "dvd",
        "material",
        "sale",
        "hotspot",
        "dvds-rental",
        "record",
        "magazine",
        "tapes-wholesale",
        "tape",
        "cd's",
        "wi-fi",
        "store",
        "manufacturer"
    ],
    "sg:website":"http://store-locator.barnesandnoble.com/store/1893",
    "wof:name":"Barnes & Noble Booksellers",
    "wof:placetype":"venue"
},
  "geometry": {"coordinates":[-75.124584,40.105568],"type":"Point"}
}