{
  "type": "Feature",
  "properties": {
    "iso:country":"US",
    "sg:address":"570 Greenridge Rd",
    "sg:city":"Glenmoore",
    "sg:classifiers":[
        {
            "category":"Shopping",
            "subcategory":"Clothing, Apparel, & Fashions",
            "type":"Retail Goods"
        },
        {
            "category":"Manufacturing",
            "subcategory":"Apparel",
            "type":"Manufacturing & Wholesale Goods"
        }
    ],
    "sg:phone":"+1 610 458 0202",
    "sg:postcode":"19343",
    "sg:province":"PA",
    "sg:tags":[
        "dressmaker",
        "made",
        "apparel-wholesale",
        "women's",
        "custom",
        "scarf",
        "manufacturer"
    ],
    "wof:name":"Leni Hoch Designer",
    "wof:placetype":"venue"
},
  "geometry": {"coordinates":[-75.728781,40.097896],"type":"Point"}
}