{
  "type": "Feature",
  "properties": {
    "iso:country":"US",
    "sg:address":"200 Woodlands Rd",
    "sg:city":"Evans City",
    "sg:classifiers":[
        {
            "category":"Freight",
            "type":"Transportation"
        }
    ],
    "sg:phone":"+1   ",
    "sg:postcode":"16033",
    "sg:province":"PA",
    "sg:tags":[
        "excavation",
        "farming",
        "local",
        "trucking"
    ],
    "wof:name":"Jacob Dressler IV",
    "wof:placetype":"venue"
},
  "geometry": {"coordinates":[-80.066962,40.84227],"type":"Point"}
}