{
  "type": "Feature",
  "properties": {
    "iso:country":"US",
    "sg:address":"28 Wilson Ave",
    "sg:city":"Chalfont",
    "sg:classifiers":[
        {
            "category":"Shopping",
            "subcategory":"Gifts & Souvenirs",
            "type":"Retail Goods"
        }
    ],
    "sg:phone":"+1 215 791 7046",
    "sg:postcode":"18914",
    "sg:province":"PA",
    "sg:tags":[
        "shop"
    ],
    "sg:website":"http://www.decoratingwithlace.com",
    "wof:name":"Decorating With Lace",
    "wof:placetype":"venue"
},
  "geometry": {"coordinates":[-75.210403,40.281281],"type":"Point"}
}