{
  "type": "Feature",
  "properties": {
    "addr:full":"101 Brilliant Ave Pittsburgh PA 15215",
    "addr:housenumber":"101",
    "addr:postcode":"15215",
    "addr:street":"Brilliant Ave",
    "iso:country":"US",
    "sg:address":"101 Brilliant Ave",
    "sg:city":"Pittsburgh",
    "sg:classifiers":[
        {
            "category":"Banks & Credit Unions",
            "subcategory":"Bank",
            "type":"Services"
        }
    ],
    "sg:phone":"+1   ",
    "sg:postcode":"15215",
    "sg:province":"PA",
    "sg:tags":[
        "state",
        "commercial"
    ],
    "wof:name":"National City Bank",
    "wof:placetype":"venue"
},
  "geometry": {"coordinates":[-79.90076999999999,40.490573],"type":"Point"}
}