{
  "type": "Feature",
  "properties": {
    "addr:full":"1020 W 8th Ave King Of Prussia PA 19406",
    "addr:housenumber":"1020",
    "addr:postcode":"19406",
    "addr:street":"W 8Th Ave",
    "iso:country":"US",
    "sg:address":"1020 W 8th Ave",
    "sg:city":"King Of Prussia",
    "sg:classifiers":[
        {
            "category":"Wholesale",
            "subcategory":"Medical Equipment & Supplies",
            "type":"Manufacturing & Wholesale Goods"
        }
    ],
    "sg:phone":"+1 610 354 8448",
    "sg:postcode":"19406",
    "sg:province":"PA",
    "sg:tags":[
        "physician",
        "surgeon"
    ],
    "wof:name":"Physician Sales & Svc",
    "wof:placetype":"venue"
},
  "geometry": {"coordinates":[-75.41510700000001,40.09879],"type":"Point"}
}