{
  "type": "Feature",
  "properties": {
    "iso:country":"US",
    "sg:address":"1026 Walnut St",
    "sg:city":"Mckeesport",
    "sg:classifiers":[
        {
            "category":"Health Services",
            "subcategory":"Doctor",
            "type":"Services"
        }
    ],
    "sg:phone":"+1 412 672 2877",
    "sg:postcode":"15132",
    "sg:province":"PA",
    "sg:tags":[
        "physician",
        "surgeon"
    ],
    "wof:name":"Harry E Lanauze MD",
    "wof:placetype":"venue"
},
  "geometry": {"coordinates":[-79.86356499999999,40.34465],"type":"Point"}
}