{
  "type": "Feature",
  "properties": {
    "iso:country":"US",
    "sg:address":"455 Sundale Dr",
    "sg:city":"York",
    "sg:classifiers":[
        {
            "category":"Education",
            "subcategory":"School",
            "type":"Public Place"
        }
    ],
    "sg:phone":"+1 717 755 2841",
    "sg:postcode":"17402",
    "sg:province":"PA",
    "wof:name":"York Suburban Middle School",
    "wof:placetype":"venue"
},
  "geometry": {"coordinates":[-76.671853,39.969434],"type":"Point"}
}