{
  "type": "Feature",
  "properties": {
    "iso:country":"US",
    "sg:address":"2619 Stauffer Rd",
    "sg:city":"Mount Joy",
    "sg:phone":"+1   ",
    "sg:postcode":"17552",
    "sg:province":"PA",
    "sg:tags":[
        "farm",
        "corn"
    ],
    "wof:name":"Robert Schatz",
    "wof:placetype":"venue"
},
  "geometry": {"coordinates":[-76.540077,40.143813],"type":"Point"}
}