{
  "type": "Feature",
  "properties": {
    "iso:country":"US",
    "sg:address":"200 S Broad St Fl 6",
    "sg:city":"Philadelphia",
    "sg:classifiers":[
        {
            "category":"Professional",
            "subcategory":"Lawyer & Legal Services",
            "type":"Services"
        }
    ],
    "sg:phone":"+1 215 732 3500",
    "sg:postcode":"19102",
    "sg:province":"PA",
    "wof:name":"Berg Donald Assocs",
    "wof:placetype":"venue"
},
  "geometry": {"coordinates":[-75.164299,39.949501],"type":"Point"}
}