{
  "type": "Feature",
  "properties": {
    "addr:full":"1651 Buck Hill Dr Huntingdon Valley PA 19006",
    "addr:housenumber":"1651",
    "addr:postcode":"19006",
    "addr:street":"Buck Hill Dr",
    "iso:country":"US",
    "sg:address":"1651 Buck Hill Dr",
    "sg:city":"Huntingdon Valley",
    "sg:classifiers":[
        {
            "category":"Wholesale",
            "subcategory":"Meat",
            "type":"Manufacturing & Wholesale Goods"
        }
    ],
    "sg:phone":"+1   ",
    "sg:postcode":"19006",
    "sg:province":"PA",
    "wof:name":"Jacks Wholesale Meats",
    "wof:placetype":"venue"
},
  "geometry": {"coordinates":[-75.066295,40.100306],"type":"Point"}
}