{
  "type": "Feature",
  "properties": {
    "iso:country":"US",
    "sg:address":"153 N 8th St",
    "sg:city":"Reading",
    "sg:classifiers":[
        {
            "category":"Banks & Credit Unions",
            "subcategory":"Bank",
            "type":"Services"
        }
    ],
    "sg:phone":"+1 610 374 8670",
    "sg:postcode":"19601",
    "sg:province":"PA",
    "sg:tags":[
        "cashing",
        "check"
    ],
    "wof:name":"Eighth Street Check Cashing",
    "wof:placetype":"venue"
},
  "geometry": {"coordinates":[-75.92187699999999,40.337571],"type":"Point"}
}