{
  "type": "Feature",
  "properties": {
    "addr:full":"2005 Regency Dr Reading PA 19610",
    "addr:housenumber":"2005",
    "addr:postcode":"19610",
    "addr:street":"Regency Dr",
    "iso:country":"US",
    "sg:address":"2005 Regency Dr",
    "sg:city":"Reading",
    "sg:classifiers":[
        {
            "category":"Manufacturing",
            "subcategory":"Retail Goods",
            "type":"Manufacturing & Wholesale Goods"
        }
    ],
    "sg:phone":"+1   ",
    "sg:postcode":"19610",
    "sg:province":"PA",
    "sg:tags":[
        "product",
        "mfg"
    ],
    "wof:name":"Anzalone International",
    "wof:placetype":"venue"
},
  "geometry": {"coordinates":[-75.98008799999999,40.316039],"type":"Point"}
}