{
  "type": "Feature",
  "properties": {
    "iso:country":"US",
    "sg:address":"60 Fairview Rd",
    "sg:city":"Gettysburg",
    "sg:classifiers":[
        {
            "category":"Place Of Worship",
            "subcategory":"Church",
            "type":"Public Place"
        },
        {
            "category":"Place Of Worship",
            "type":"Public Place"
        }
    ],
    "sg:phone":"+1 717 334 2601",
    "sg:postcode":"17325",
    "sg:province":"PA",
    "sg:tags":[
        "testament",
        "christ-new",
        "churches-church",
        "christ"
    ],
    "wof:name":"Gettysburg Church Of Christ",
    "wof:placetype":"venue"
},
  "geometry": {"coordinates":[-77.200882,39.85699],"type":"Point"}
}