{
  "type": "Feature",
  "properties": {
    "addr:full":"9994 Susquehanna Trl S Glen Rock PA 17327",
    "addr:housenumber":"9994",
    "addr:postcode":"17327",
    "addr:street":"Susquehanna Trl S Glen",
    "iso:country":"US",
    "sg:address":"9994 Susquehanna Trl S",
    "sg:city":"Glen Rock",
    "sg:classifiers":[
        {
            "category":"Banks & Credit Unions",
            "subcategory":"Bank",
            "type":"Services"
        }
    ],
    "sg:phone":"+1 717 227 2526",
    "sg:postcode":"17327",
    "sg:province":"PA",
    "sg:tags":[
        "loan",
        "real estate"
    ],
    "wof:name":"Affinity Mortgage",
    "wof:placetype":"venue"
},
  "geometry": {"coordinates":[-76.70115199999999,39.828371],"type":"Point"}
}