{
  "type": "Feature",
  "properties": {
    "iso:country":"US",
    "sg:address":"1 Center St",
    "sg:city":"East Stroudsburg",
    "sg:classifiers":[
        {
            "category":"Health Services",
            "subcategory":"Chiropractor",
            "type":"Services"
        }
    ],
    "sg:phone":"+1 570 223 7211",
    "sg:postcode":"18301",
    "sg:province":"PA",
    "sg:tags":[
        "practice",
        "chiropractic"
    ],
    "wof:name":"Marshalls Creek Chiropractic",
    "wof:placetype":"venue"
},
  "geometry": {"coordinates":[-75.178979,40.993515],"type":"Point"}
}