{
  "type": "Feature",
  "properties": {
    "addr:full":"134 W South St Everett PA 15537",
    "addr:housenumber":"134",
    "addr:postcode":"15537",
    "addr:street":"W South St",
    "iso:country":"US",
    "sg:address":"134 W South St",
    "sg:city":"Everett",
    "sg:classifiers":[
        {
            "category":"Freight",
            "type":"Transportation"
        }
    ],
    "sg:phone":"+1 814 652 5742",
    "sg:postcode":"15537",
    "sg:province":"PA",
    "sg:tags":[
        "dry",
        "bulk",
        "trucking"
    ],
    "wof:name":"Tri-County Bulk Haulers",
    "wof:placetype":"venue"
},
  "geometry": {"coordinates":[-78.374323,40.00943],"type":"Point"}
}