{
  "type": "Feature",
  "properties": {
    "iso:country":"US",
    "sg:address":"405 E 6th Ave",
    "sg:city":"Tarentum",
    "sg:classifiers":[
        {
            "category":"Shopping",
            "type":"Retail Goods"
        },
        {
            "category":"Retail",
            "subcategory":"Animal Services",
            "type":"Services"
        }
    ],
    "sg:phone":"+1 724 226 4822",
    "sg:postcode":"15084",
    "sg:province":"PA",
    "sg:tags":[
        "food",
        "pet",
        "supply",
        "foods-wholesale",
        "manufacturer"
    ],
    "sg:website":"http://www.ringerspetdogtraining.com",
    "wof:name":"Ringers Pet Dog Training",
    "wof:placetype":"venue"
},
  "geometry": {"coordinates":[-79.75252399999999,40.60304],"type":"Point"}
}