{
  "type": "Feature",
  "properties": {
    "addr:full":"1752 Lincoln Way E Chambersburg PA 17202",
    "addr:housenumber":"1752",
    "addr:postcode":"17202",
    "addr:street":"Lincoln Way E",
    "iso:country":"US",
    "sg:address":"1752 Lincoln Way E",
    "sg:city":"Chambersburg",
    "sg:classifiers":[
        {
            "category":"Shopping",
            "subcategory":"Hobbies, Toys, & Games",
            "type":"Retail Goods"
        }
    ],
    "sg:phone":"+1 717 267 4367",
    "sg:postcode":"17202",
    "sg:province":"PA",
    "sg:tags":[
        "supply"
    ],
    "wof:name":"EB Games",
    "wof:placetype":"venue"
},
  "geometry": {"coordinates":[-80.242729,40.176128],"type":"Point"}
}