{
  "type": "Feature",
  "properties": {
    "addr:full":"3120 N 17th St Philadelphia PA 19132",
    "addr:housenumber":"3120",
    "addr:postcode":"19132",
    "addr:street":"N 17Th St",
    "iso:country":"US",
    "sg:address":"3120 N 17th St",
    "sg:city":"Philadelphia",
    "sg:classifiers":[
        {
            "category":"Food & Beverages",
            "subcategory":"Chocolate",
            "type":"Retail Goods"
        }
    ],
    "sg:phone":"+1 215 229 4990",
    "sg:postcode":"19132",
    "sg:province":"PA",
    "sg:tags":[
        "shop",
        "chocolatiers"
    ],
    "sg:website":"www.zitners.com/",
    "wof:name":"Zitner Candy Corp",
    "wof:placetype":"venue"
},
  "geometry": {"coordinates":[-75.157898,40.0009],"type":"Point"}
}