{
  "type": "Feature",
  "properties": {
    "iso:country":"US",
    "sg:address":"245 Main St",
    "sg:city":"Emmaus",
    "sg:classifiers":[
        {
            "category":"Professional",
            "subcategory":"Lawyer & Legal Services",
            "type":"Services"
        }
    ],
    "sg:phone":"+1 610 965 9652",
    "sg:postcode":"18049",
    "sg:province":"PA",
    "wof:name":"Weida Bruce Attorney",
    "wof:placetype":"venue"
},
  "geometry": {"coordinates":[-75.489785,40.536578],"type":"Point"}
}