{
  "type": "Feature",
  "properties": {
    "addr:full":"403 E Mountain Rd Scranton PA 18505",
    "addr:housenumber":"403",
    "addr:postcode":"18505",
    "addr:street":"E Mountain Rd",
    "iso:country":"US",
    "sg:address":"403 E Mountain Rd",
    "sg:city":"Scranton",
    "sg:classifiers":[
        {
            "category":"Food & Beverages",
            "subcategory":"Candy",
            "type":"Retail Goods"
        }
    ],
    "sg:phone":"+1   ",
    "sg:postcode":"18505",
    "sg:province":"PA",
    "wof:name":"John R Dandrea Pharmacy",
    "wof:placetype":"venue"
},
  "geometry": {"coordinates":[-75.648978,41.392334],"type":"Point"}
}