{
  "type": "Feature",
  "properties": {
    "iso:country":"US",
    "sg:address":"300 Jacksonville Rd",
    "sg:city":"Warminster",
    "sg:classifiers":[
        {
            "category":"Freight",
            "type":"Transportation"
        }
    ],
    "sg:phone":"+1 215 444 9240",
    "sg:postcode":"18974",
    "sg:province":"PA",
    "sg:tags":[
        "commercial",
        "storage"
    ],
    "wof:name":"Devon Self-Storage",
    "wof:placetype":"venue"
},
  "geometry": {"coordinates":[-75.06005999999999,40.216634],"type":"Point"}
}