{
  "type": "Feature",
  "properties": {
    "addr:full":"2208 S 5th Ave Lebanon PA 17042",
    "addr:housenumber":"2208",
    "addr:postcode":"17042",
    "addr:street":"S 5Th Ave",
    "iso:country":"US",
    "sg:address":"2208 S 5th Ave",
    "sg:city":"Lebanon",
    "sg:classifiers":[
        {
            "category":"Building & Trades",
            "subcategory":"Landscaping Services",
            "type":"Services"
        }
    ],
    "sg:phone":"+1   ",
    "sg:postcode":"17042",
    "sg:province":"PA",
    "sg:tags":[
        "landscape"
    ],
    "wof:name":"Shank Landscaping Co",
    "wof:placetype":"venue"
},
  "geometry": {"coordinates":[-76.342828,40.309937],"type":"Point"}
}