{
  "type": "Feature",
  "properties": {
    "iso:country":"US",
    "sg:address":"824 N Gallatin Ave Exd",
    "sg:city":"Uniontown",
    "sg:classifiers":[
        {
            "category":"Professional",
            "subcategory":"Lawyer & Legal Services",
            "type":"Services"
        }
    ],
    "sg:phone":"+1   ",
    "sg:postcode":"15401",
    "sg:province":"PA",
    "wof:name":"Shelly Snoddy Esq",
    "wof:placetype":"venue"
},
  "geometry": {"coordinates":[-79.696169,39.926417],"type":"Point"}
}