{
  "type": "Feature",
  "properties": {
    "addr:full":"1300 Oxford Dr Bethel Park PA 15102",
    "addr:housenumber":"1300",
    "addr:postcode":"15102",
    "addr:street":"Oxford Dr",
    "iso:country":"US",
    "sg:address":"1300 Oxford Dr",
    "sg:city":"Bethel Park",
    "sg:classifiers":[
        {
            "category":"Health Services",
            "subcategory":"Doctor",
            "type":"Services"
        }
    ],
    "sg:phone":"+1 412 851 8800",
    "sg:postcode":"15102",
    "sg:province":"PA",
    "wof:name":"Crock Frederick W MD",
    "wof:placetype":"venue"
},
  "geometry": {"coordinates":[-80.05167899999999,40.343408],"type":"Point"}
}