{
  "type": "Feature",
  "properties": {
    "iso:country":"US",
    "sg:address":"4548 Market St",
    "sg:city":"Philadelphia",
    "sg:classifiers":[
        {
            "category":"Professional",
            "subcategory":"Business Services",
            "type":"Services"
        }
    ],
    "sg:phone":"+1 215 895 4002",
    "sg:postcode":"19139",
    "sg:province":"PA",
    "sg:tags":[
        "management"
    ],
    "wof:name":"Citylife 2825 N Broad",
    "wof:placetype":"venue"
},
  "geometry": {"coordinates":[-75.212388,39.958435],"type":"Point"}
}