{
  "type": "Feature",
  "properties": {
    "addr:full":"6429 Castor Ave Philadelphia PA 19149",
    "addr:housenumber":"6429",
    "addr:postcode":"19149",
    "addr:street":"Castor Ave",
    "iso:country":"US",
    "sg:address":"6429 Castor Ave",
    "sg:city":"Philadelphia",
    "sg:classifiers":[
        {
            "category":"Organizations",
            "subcategory":"Religious Organization",
            "type":"Services"
        }
    ],
    "sg:phone":"+1 215 535 1072",
    "sg:postcode":"19149",
    "sg:province":"PA",
    "sg:tags":[
        "church"
    ],
    "wof:name":"Bethel International Missions",
    "wof:placetype":"venue"
},
  "geometry": {"coordinates":[-75.076612,40.040183],"type":"Point"}
}