{
  "type": "Feature",
  "properties": {
    "iso:country":"US",
    "sg:address":"3234 Freemansburg Ave",
    "sg:city":"Easton",
    "sg:classifiers":[
        {
            "category":"Retail",
            "subcategory":"Animal Services",
            "type":"Services"
        }
    ],
    "sg:phone":"+1   ",
    "sg:postcode":"18045",
    "sg:province":"PA",
    "sg:tags":[
        "pet",
        "grooming",
        "dog",
        "sitting"
    ],
    "wof:name":"Natural Dogs",
    "wof:placetype":"venue"
},
  "geometry": {"coordinates":[-75.258679,40.668398],"type":"Point"}
}