{
  "type": "Feature",
  "properties": {
    "iso:country":"US",
    "sg:address":"1337 E 5th St",
    "sg:city":"Bethlehem",
    "sg:classifiers":[
        {
            "category":"Social Services",
            "type":"Services"
        }
    ],
    "sg:phone":"+1 610 691 5620",
    "sg:postcode":"18015",
    "sg:province":"PA",
    "sg:tags":[
        "organization",
        "welfare"
    ],
    "sg:website":"www.caclv.org",
    "wof:name":"Community Action Committee",
    "wof:placetype":"venue"
},
  "geometry": {"coordinates":[-75.35635499999999,40.610613],"type":"Point"}
}