{
  "type": "Feature",
  "properties": {
    "addr:full":"1619 Grant Ave Philadelphia PA 19115",
    "addr:housenumber":"1619",
    "addr:postcode":"19115",
    "addr:street":"Grant Ave",
    "iso:country":"US",
    "sg:address":"1619 Grant Ave",
    "sg:city":"Philadelphia",
    "sg:phone":"+1 215 677 8019",
    "sg:postcode":"19115",
    "sg:province":"PA",
    "wof:name":"United Artists Theaters",
    "wof:placetype":"venue"
},
  "geometry": {"coordinates":[-75.04066899999999,40.087047],"type":"Point"}
}