{
  "type": "Feature",
  "properties": {
    "iso:country":"US",
    "sg:address":"424 E Sunbury St",
    "sg:city":"Shamokin",
    "sg:classifiers":[
        {
            "category":"Autos & Motor Vehicles",
            "subcategory":"Fuel & Gas Station",
            "type":"Retail Goods"
        }
    ],
    "sg:phone":"+1 570 648 9395",
    "sg:postcode":"17872",
    "sg:province":"PA",
    "sg:tags":[
        "oil"
    ],
    "wof:name":"Shamokin Exxon Svc Ctr",
    "wof:placetype":"venue"
},
  "geometry": {"coordinates":[-76.551812,40.793064],"type":"Point"}
}