{
  "type": "Feature",
  "properties": {
    "addr:full":"309 S Oak St Mt Carmel PA 17851",
    "addr:housenumber":"309",
    "addr:postcode":"17851",
    "addr:street":"S Oak St",
    "iso:country":"US",
    "sg:address":"309 S Oak St",
    "sg:city":"Mt Carmel",
    "sg:classifiers":[
        {
            "category":"Recreation",
            "type":"Entertainment"
        },
        {
            "category":"Organizations",
            "subcategory":"Community Association",
            "type":"Services"
        }
    ],
    "sg:phone":"+1 570 339 4770",
    "sg:postcode":"17851",
    "sg:province":"PA",
    "sg:tags":[
        "club",
        "membership"
    ],
    "wof:name":"Lithuanian Social Club",
    "wof:placetype":"venue"
},
  "geometry": {"coordinates":[-76.412164,40.793524],"type":"Point"}
}