{
  "type": "Feature",
  "properties": {
    "iso:country":"US",
    "sg:address":"790 Penllyn Blue Bell Pike",
    "sg:city":"Blue Bell",
    "sg:classifiers":[
        {
            "category":"Health Services",
            "subcategory":"Doctor",
            "type":"Services"
        }
    ],
    "sg:phone":"+1 215 542 9700",
    "sg:postcode":"19422",
    "sg:province":"PA",
    "sg:tags":[
        "physician",
        "surgeon"
    ],
    "wof:name":"Blatt Crispino & Faye Ob/Gyn",
    "wof:placetype":"venue"
},
  "geometry": {"coordinates":[-75.263471,40.155997],"type":"Point"}
}