{
  "type": "Feature",
  "properties": {
    "addr:full":"1699 Point Dr Bensalem PA 19020",
    "addr:housenumber":"1699",
    "addr:postcode":"19020",
    "addr:street":"Point Dr",
    "iso:country":"US",
    "sg:address":"1699 Point Dr",
    "sg:city":"Bensalem",
    "sg:classifiers":[
        {
            "category":"Professional",
            "type":"Services"
        }
    ],
    "sg:phone":"+1 215 741 1699",
    "sg:postcode":"19020",
    "sg:province":"PA",
    "sg:website":"www.paytonwoodcraft.com",
    "wof:name":"Payton Woodcraft",
    "wof:placetype":"venue"
},
  "geometry": {"coordinates":[-74.91692500000001,40.130303],"type":"Point"}
}