{
  "type": "Feature",
  "properties": {
    "addr:full":"235 Sunrise Dr Delmont PA 15642",
    "addr:housenumber":"235",
    "addr:postcode":"15642",
    "addr:street":"Sunrise Dr",
    "iso:country":"US",
    "sg:address":"235 Sunrise Dr",
    "sg:city":"Delmont",
    "sg:classifiers":[
        {
            "category":"Building & Trades",
            "subcategory":"Cleaning & Sanitation",
            "type":"Services"
        }
    ],
    "sg:phone":"+1 724 733 2747",
    "sg:postcode":"15642",
    "sg:province":"PA",
    "sg:tags":[
        "fireplace",
        "chimney"
    ],
    "wof:name":"Ash's Chimney Sweep",
    "wof:placetype":"venue"
},
  "geometry": {"coordinates":[-79.69344100000001,40.369924],"type":"Point"}
}