{
  "type": "Feature",
  "properties": {
    "addr:full":"4333 Main St Philadelphia PA 19127",
    "addr:housenumber":"4333",
    "addr:postcode":"19127",
    "addr:street":"Main St",
    "iso:country":"US",
    "sg:address":"4333 Main St",
    "sg:city":"Philadelphia",
    "sg:classifiers":[
        {
            "category":"Communications",
            "subcategory":"Radio Station",
            "type":"Services"
        },
        {
            "category":"Shopping",
            "subcategory":"Shoes",
            "type":"Retail Goods"
        }
    ],
    "sg:phone":"+1 215 483 4620",
    "sg:postcode":"19127",
    "sg:province":"PA",
    "sg:tags":[
        "broadcast",
        "store"
    ],
    "wof:name":"Walk the Talk",
    "wof:placetype":"venue"
},
  "geometry": {"coordinates":[-75.223133,40.02527],"type":"Point"}
}