{
  "type": "Feature",
  "properties": {
    "addr:full":"136 Nicholson St Wilkes Barre PA 18702",
    "addr:housenumber":"136",
    "addr:postcode":"18702",
    "addr:street":"Nicholson St",
    "iso:country":"US",
    "sg:address":"136 Nicholson St",
    "sg:city":"Wilkes Barre",
    "sg:classifiers":[
        {
            "category":"Bars & Pubs",
            "type":"Food & Drink"
        }
    ],
    "sg:phone":"+1 570 822 0772",
    "sg:postcode":"18702",
    "sg:province":"PA",
    "sg:tags":[
        "drinking"
    ],
    "wof:name":"Carl's Bar",
    "wof:placetype":"venue"
},
  "geometry": {"coordinates":[-75.885238,41.219328],"type":"Point"}
}