{
  "type": "Feature",
  "properties": {
    "iso:country":"US",
    "sg:address":"101 Camelot Ln",
    "sg:city":"Jeannette",
    "sg:classifiers":[
        {
            "category":"Building & Trades",
            "subcategory":"Construction",
            "type":"Services"
        }
    ],
    "sg:phone":"+1   ",
    "sg:postcode":"15644",
    "sg:province":"PA",
    "sg:tags":[
        "house"
    ],
    "wof:name":"Braun Homes/Braun Carpentry",
    "wof:placetype":"venue"
},
  "geometry": {"coordinates":[-79.60119899999999,40.3831],"type":"Point"}
}