{
  "type": "Feature",
  "properties": {
    "addr:full":"139 E Centre St Ashland PA 17921",
    "addr:housenumber":"139",
    "addr:postcode":"17921",
    "addr:street":"E Centre St",
    "iso:country":"US",
    "sg:address":"139 E Centre St",
    "sg:city":"Ashland",
    "sg:classifiers":[
        {
            "category":"Retail",
            "subcategory":"Auto Repair",
            "type":"Services"
        }
    ],
    "sg:phone":"+1 570 875 3050",
    "sg:postcode":"17921",
    "sg:province":"PA",
    "sg:tags":[
        "repairing",
        "automobile"
    ],
    "wof:name":"John White Garage",
    "wof:placetype":"venue"
},
  "geometry": {"coordinates":[-76.33058699999999,40.784083],"type":"Point"}
}