{
  "type": "Feature",
  "properties": {
    "addr:full":"207 Exton Square Mall Exton PA 19341",
    "addr:housenumber":"207",
    "addr:postcode":"19341",
    "addr:street":"Exton Square Mall",
    "iso:country":"US",
    "sg:address":"207 Exton Square Mall",
    "sg:city":"Exton",
    "sg:classifiers":[
        {
            "category":"Food & Beverages",
            "subcategory":"Specialty",
            "type":"Retail Goods"
        }
    ],
    "sg:phone":"+1 610 363 9902",
    "sg:postcode":"19341",
    "sg:province":"PA",
    "sg:tags":[
        "health",
        "diet"
    ],
    "wof:name":"General Nutrition Ctr",
    "wof:placetype":"venue"
},
  "geometry": {"coordinates":[-75.62566200000001,40.032968],"type":"Point"}
}