{
  "type": "Feature",
  "properties": {
    "addr:full":"725 Hollywell Ave Chambersburg PA 17201",
    "addr:housenumber":"725",
    "addr:postcode":"17201",
    "addr:street":"Hollywell Ave",
    "iso:country":"US",
    "sg:address":"725 Hollywell Ave",
    "sg:city":"Chambersburg",
    "sg:classifiers":[
        {
            "category":"Government",
            "subcategory":"Office",
            "type":"Public Place"
        }
    ],
    "sg:phone":"+1   ",
    "sg:postcode":"17201",
    "sg:province":"PA",
    "sg:tags":[
        "management",
        "executive"
    ],
    "wof:name":"Chambrsburg Waste Trtmnt Plant",
    "wof:placetype":"venue"
},
  "geometry": {"coordinates":[-77.66945200000001,39.928385],"type":"Point"}
}