{
  "type": "Feature",
  "properties": {
    "iso:country":"US",
    "sg:address":"107 E Drinker St",
    "sg:city":"Dunmore",
    "sg:classifiers":[
        {
            "category":"Restaurant",
            "type":"Food & Drink"
        }
    ],
    "sg:phone":"+1 570 346 7881",
    "sg:postcode":"18512",
    "sg:province":"PA",
    "wof:name":"Cuginos",
    "wof:placetype":"venue"
},
  "geometry": {"coordinates":[-75.63000700000001,41.421812],"type":"Point"}
}