{
  "type": "Feature",
  "properties": {
    "iso:country":"US",
    "sg:address":"432 Blue Valley Dr",
    "sg:city":"Bangor",
    "sg:classifiers":[
        {
            "category":"Shopping",
            "subcategory":"Department Store",
            "type":"Retail Goods"
        }
    ],
    "sg:phone":"+1 610 863 6333",
    "sg:postcode":"18013",
    "sg:province":"PA",
    "sg:tags":[
        "shop"
    ],
    "wof:name":"Dollar General",
    "wof:placetype":"venue"
},
  "geometry": {"coordinates":[-75.234191,40.87207],"type":"Point"}
}