{
  "type": "Feature",
  "properties": {
    "addr:full":"240 Mall Blvd King Of Prussia PA 19406",
    "addr:housenumber":"240",
    "addr:postcode":"19406",
    "addr:street":"Mall Blvd",
    "iso:country":"US",
    "sg:address":"240 Mall Blvd",
    "sg:city":"King Of Prussia",
    "sg:classifiers":[
        {
            "category":"Autos & Motor Vehicles",
            "subcategory":"Automobile Sales",
            "type":"Retail Goods"
        }
    ],
    "sg:phone":"+1 610 337 3100",
    "sg:postcode":"19406",
    "sg:province":"PA",
    "sg:tags":[
        "car",
        "used",
        "truck",
        "dealer",
        "new"
    ],
    "wof:name":"David Penske Chevrolet Inc",
    "wof:placetype":"venue"
},
  "geometry": {"coordinates":[-75.394789,40.090791],"type":"Point"}
}