{
  "type": "Feature",
  "properties": {
    "iso:country":"US",
    "sg:address":"125 Pillow St",
    "sg:city":"Butler",
    "sg:classifiers":[
        {
            "category":"Shopping",
            "subcategory":"Pharmacy",
            "type":"Retail Goods"
        }
    ],
    "sg:phone":"+1 724 282 8446",
    "sg:postcode":"16001",
    "sg:province":"PA",
    "wof:name":"Medicine Shoppe Pharmacy",
    "wof:placetype":"venue"
},
  "geometry": {"coordinates":[-79.904456,40.861092],"type":"Point"}
}