{
  "type": "Feature",
  "properties": {
    "iso:country":"US",
    "sg:address":"2846 Blvd of the Allies",
    "sg:city":"Pittsburgh",
    "sg:classifiers":[
        {
            "category":"Professional",
            "subcategory":"Accounting & Tax Preparation",
            "type":"Services"
        }
    ],
    "sg:phone":"+1 412 621 9201",
    "sg:postcode":"15213",
    "sg:province":"PA",
    "sg:tags":[
        "accountant"
    ],
    "wof:name":"Wittlin Simon & Newman PC",
    "wof:placetype":"venue"
},
  "geometry": {"coordinates":[-79.963117,40.435602],"type":"Point"}
}