{
  "type": "Feature",
  "properties": {
    "addr:full":"70 E Broad St Bethlehem PA 18018",
    "addr:housenumber":"70",
    "addr:postcode":"18018",
    "addr:street":"E Broad St",
    "iso:country":"US",
    "sg:address":"70 E Broad St",
    "sg:city":"Bethlehem",
    "sg:classifiers":[
        {
            "category":"Professional",
            "subcategory":"Lawyer & Legal Services",
            "type":"Services"
        }
    ],
    "sg:phone":"+1 610 867 2538",
    "sg:postcode":"18018",
    "sg:province":"PA",
    "wof:name":"Shearer Gail Weiner",
    "wof:placetype":"venue"
},
  "geometry": {"coordinates":[-75.376251,40.622114],"type":"Point"}
}