{
  "type": "Feature",
  "properties": {
    "iso:country":"US",
    "sg:address":"2330 Crestview Ln",
    "sg:city":"Aston",
    "sg:classifiers":[
        {
            "category":"Insurance",
            "subcategory":"Hazard Insurance",
            "type":"Services"
        }
    ],
    "sg:phone":"+1 610 364 9921",
    "sg:postcode":"19014",
    "sg:province":"PA",
    "wof:name":"A Regotti",
    "wof:placetype":"venue"
},
  "geometry": {"coordinates":[-75.442801,39.864791],"type":"Point"}
}