{
  "type": "Feature",
  "properties": {
    "iso:country":"US",
    "sg:address":"2309 Delancey Pl",
    "sg:city":"Philadelphia",
    "sg:classifiers":[
        {
            "category":"Professional",
            "subcategory":"Lawyer & Legal Services",
            "type":"Services"
        }
    ],
    "sg:phone":"+1 215 735 2384",
    "sg:postcode":"19103",
    "sg:province":"PA",
    "sg:website":"www.gosfield.com",
    "wof:name":"Rodriguez Todd A Atty",
    "wof:placetype":"venue"
},
  "geometry": {"coordinates":[-75.179604,39.948002],"type":"Point"}
}