{
  "type": "Feature",
  "properties": {
    "addr:full":"6405 Grayson Rd Harrisburg PA 17111",
    "addr:housenumber":"6405",
    "addr:postcode":"17111",
    "addr:street":"Grayson Rd",
    "iso:country":"US",
    "sg:address":"6405 Grayson Rd",
    "sg:city":"Harrisburg",
    "sg:classifiers":[
        {
            "category":"Restaurant",
            "type":"Food & Drink"
        }
    ],
    "sg:phone":"+1 717 561 0180",
    "sg:postcode":"17111",
    "sg:province":"PA",
    "sg:website":"www.valentifm.com",
    "wof:name":"Wendy's",
    "wof:placetype":"venue"
},
  "geometry": {"coordinates":[-76.754862,40.263661],"type":"Point"}
}