{
  "type": "Feature",
  "properties": {
    "iso:country":"US",
    "sg:address":"549 Greenhowe Dr",
    "sg:city":"Lititz",
    "sg:classifiers":[
        {
            "category":"Wholesale",
            "subcategory":"Electrical",
            "type":"Manufacturing & Wholesale Goods"
        }
    ],
    "sg:phone":"+1 717 569 8796",
    "sg:postcode":"17543",
    "sg:province":"PA",
    "sg:tags":[
        "control",
        "security",
        "system"
    ],
    "wof:name":"Information Security Systems",
    "wof:placetype":"venue"
},
  "geometry": {"coordinates":[-76.330467,40.109023],"type":"Point"}
}