{
  "type": "Feature",
  "properties": {
    "addr:full":"181 Gibraltar Rd Horsham PA 19044",
    "addr:housenumber":"181",
    "addr:postcode":"19044",
    "addr:street":"Gibraltar Rd",
    "iso:country":"US",
    "sg:address":"181 Gibraltar Rd",
    "sg:city":"Horsham",
    "sg:classifiers":[
        {
            "category":"Professional",
            "subcategory":"Engineering",
            "type":"Services"
        },
        {
            "category":"Professional",
            "type":"Services"
        }
    ],
    "sg:phone":"+1 215 542 8400",
    "sg:postcode":"19044",
    "sg:province":"PA",
    "sg:tags":[
        "engineer"
    ],
    "sg:website":"www.materials-sciences.com",
    "wof:name":"Materials Sciences Corp",
    "wof:placetype":"venue"
},
  "geometry": {"coordinates":[-75.131409,40.171039],"type":"Point"}
}