{
  "type": "Feature",
  "properties": {
    "iso:country":"US",
    "sg:address":"363 Frampton Rd",
    "sg:city":"Harrisville",
    "sg:classifiers":[
        {
            "category":"Retail",
            "subcategory":"Auto Repair",
            "type":"Services"
        }
    ],
    "sg:phone":"+1 724 735 2908",
    "sg:postcode":"16038",
    "sg:province":"PA",
    "sg:tags":[
        "body",
        "automobile",
        "painting"
    ],
    "wof:name":"Frampton Larry C Auto Body",
    "wof:placetype":"venue"
},
  "geometry": {"coordinates":[-79.991426,41.130594],"type":"Point"}
}