{
  "type": "Feature",
  "properties": {
    "iso:country":"US",
    "sg:address":"1429 Houserville Rd",
    "sg:city":"State College",
    "sg:classifiers":[
        {
            "category":"Health Services",
            "subcategory":"Medical Lab",
            "type":"Services"
        }
    ],
    "sg:phone":"+1   ",
    "sg:postcode":"16801",
    "sg:province":"PA",
    "sg:tags":[
        "laboratory",
        "dental"
    ],
    "wof:name":"Nittany Dental Lab",
    "wof:placetype":"venue"
},
  "geometry": {"coordinates":[-77.83148799999999,40.826905],"type":"Point"}
}