{
  "type": "Feature",
  "properties": {
    "iso:country":"US",
    "sg:address":"1223 13th Ave",
    "sg:city":"Altoona",
    "sg:classifiers":[
        {
            "category":"Health Services",
            "subcategory":"Doctor",
            "type":"Services"
        }
    ],
    "sg:phone":"+1 814 942 9081",
    "sg:postcode":"16601",
    "sg:province":"PA",
    "sg:tags":[
        "physician",
        "surgeon"
    ],
    "wof:name":"Capriotti Richard D MD & Assoc",
    "wof:placetype":"venue"
},
  "geometry": {"coordinates":[-78.40306,40.516438],"type":"Point"}
}