{
  "type": "Feature",
  "properties": {
    "iso:country":"US",
    "sg:address":"1285 N 9th St",
    "sg:city":"Stroudsburg",
    "sg:classifiers":[
        {
            "category":"Insurance",
            "subcategory":"Hazard Insurance",
            "type":"Services"
        },
        {
            "category":"Insurance",
            "subcategory":"Insurance Agent",
            "type":"Services"
        },
        {
            "category":"Insurance",
            "subcategory":"Life Insurance",
            "type":"Services"
        },
        {
            "category":"Insurance",
            "subcategory":"Title Insurance",
            "type":"Services"
        }
    ],
    "sg:phone":"+1 570 421 7447",
    "sg:postcode":"18360",
    "sg:province":"PA",
    "sg:tags":[
        "auto",
        "homeowner"
    ],
    "sg:website":"http://www.nationwide.com/agent/Stroudsburg-PENNSYLVANIA-insurance-agent/michaelfrailey/office.html",
    "wof:name":"Michael J. Frailey - Nationwide Insurance",
    "wof:placetype":"venue"
},
  "geometry": {"coordinates":[-75.221723,40.988122],"type":"Point"}
}