{
  "type": "Feature",
  "properties": {
    "iso:country":"US",
    "sg:address":"3 Woodland Dr",
    "sg:city":"Newville",
    "sg:classifiers":[
        {
            "category":"Professional",
            "type":"Services"
        }
    ],
    "sg:phone":"+1   ",
    "sg:postcode":"17241",
    "sg:province":"PA",
    "wof:name":"James I Salisbury",
    "wof:placetype":"venue"
},
  "geometry": {"coordinates":[-77.372066,40.253828],"type":"Point"}
}