{
  "type": "Feature",
  "properties": {
    "addr:full":"2103 Walnut St Philadelphia PA 19103",
    "addr:housenumber":"2103",
    "addr:postcode":"19103",
    "addr:street":"Walnut St",
    "iso:country":"US",
    "sg:address":"2103 Walnut St",
    "sg:city":"Philadelphia",
    "sg:classifiers":[
        {
            "category":"Arts & Performance",
            "subcategory":"Art Gallery",
            "type":"Entertainment"
        }
    ],
    "sg:phone":"+1 215 567 6800",
    "sg:postcode":"19103",
    "sg:province":"PA",
    "wof:name":"F W I Acquistion Corp",
    "wof:placetype":"venue"
},
  "geometry": {"coordinates":[-75.17620100000001,39.9506],"type":"Point"}
}