{
  "type": "Feature",
  "properties": {
    "iso:country":"US",
    "sg:address":"2626 N 3rd St Ste 3B",
    "sg:city":"Harrisburg",
    "sg:classifiers":[
        {
            "category":"Health Services",
            "subcategory":"Doctor",
            "type":"Services"
        },
        {
            "category":"Health Services",
            "subcategory":"Clinic",
            "type":"Services"
        }
    ],
    "sg:phone":"+1 717 238 0885",
    "sg:postcode":"17110",
    "sg:province":"PA",
    "sg:tags":[
        "psychological",
        "counseling",
        "psychologist",
        "mental"
    ],
    "wof:name":"Sleber Richard L MA",
    "wof:placetype":"venue"
},
  "geometry": {"coordinates":[-76.89969600000001,40.287498],"type":"Point"}
}