{
  "type": "Feature",
  "properties": {
    "addr:full":"213 6th St Monongahela PA 15063",
    "addr:housenumber":"213",
    "addr:postcode":"15063",
    "addr:street":"6Th St",
    "iso:country":"US",
    "sg:address":"213 6th St",
    "sg:city":"Monongahela",
    "sg:classifiers":[
        {
            "category":"Professional",
            "type":"Services"
        }
    ],
    "sg:phone":"+1   ",
    "sg:postcode":"15063",
    "sg:province":"PA",
    "wof:name":"A Evans",
    "wof:placetype":"venue"
},
  "geometry": {"coordinates":[-79.92964499999999,40.204603],"type":"Point"}
}