{
  "type": "Feature",
  "properties": {
    "addr:full":"39 Ellis Ave Hermitage PA 16148",
    "addr:housenumber":"39",
    "addr:postcode":"16148",
    "addr:street":"Ellis Ave",
    "iso:country":"US",
    "sg:address":"39 Ellis Ave",
    "sg:city":"Hermitage",
    "sg:classifiers":[
        {
            "category":"Banks & Credit Unions",
            "subcategory":"Bank",
            "type":"Services"
        }
    ],
    "sg:phone":"+1 724 983 0882",
    "sg:postcode":"16148",
    "sg:province":"PA",
    "sg:tags":[
        "loan",
        "broker",
        "mortgage"
    ],
    "sg:website":"www.pleasantmortgage.com",
    "wof:name":"Pleasant Mortgage Inc",
    "wof:placetype":"venue"
},
  "geometry": {"coordinates":[-80.466359,41.23168],"type":"Point"}
}