{
  "type": "Feature",
  "properties": {
    "iso:country":"US",
    "sg:address":"865 Church Rd",
    "sg:city":"Mountain Top",
    "sg:classifiers":[
        {
            "category":"Organizations",
            "subcategory":"Religious Organization",
            "type":"Services"
        }
    ],
    "sg:phone":"+1 570 868 6863",
    "sg:postcode":"18707",
    "sg:province":"PA",
    "sg:tags":[
        "church"
    ],
    "wof:name":"Mountain Top Baptist Church",
    "wof:placetype":"venue"
},
  "geometry": {"coordinates":[-75.93694000000001,41.122857],"type":"Point"}
}