{
  "type": "Feature",
  "properties": {
    "iso:country":"US",
    "sg:address":"1384 Old Freeport Rd",
    "sg:city":"Pittsburgh",
    "sg:classifiers":[
        {
            "category":"Personal",
            "type":"Services"
        }
    ],
    "sg:phone":"+1 412 963 6911",
    "sg:postcode":"15238",
    "sg:province":"PA",
    "sg:tags":[
        "therapist",
        "massage"
    ],
    "wof:name":"Dena M Vrabel Massage Thrpst",
    "wof:placetype":"venue"
},
  "geometry": {"coordinates":[-79.871273,40.489272],"type":"Point"}
}