{
  "type": "Feature",
  "properties": {
    "addr:full":"164 Van Auken Hill Rd Milford PA 18337",
    "addr:housenumber":"164",
    "addr:postcode":"18337",
    "addr:street":"Van Auken Hill Rd",
    "iso:country":"US",
    "sg:address":"164 Van Auken Hill Rd",
    "sg:city":"Milford",
    "sg:classifiers":[
        {
            "category":"Professional",
            "type":"Services"
        }
    ],
    "sg:phone":"+1 570 296 2109",
    "sg:postcode":"18337",
    "sg:province":"PA",
    "sg:tags":[
        "establishment"
    ],
    "wof:name":"South Canaan Celluar",
    "wof:placetype":"venue"
},
  "geometry": {"coordinates":[-74.863095,41.322405],"type":"Point"}
}