{
  "type": "Feature",
  "properties": {
    "addr:full":"45 Main St Mainland PA 19438",
    "addr:housenumber":"45",
    "addr:postcode":"19438",
    "addr:street":"Main St",
    "iso:country":"US",
    "sg:address":"45 Main St",
    "sg:city":"Mainland",
    "sg:classifiers":[
        {
            "category":"Wholesale",
            "subcategory":"Groceries",
            "type":"Manufacturing & Wholesale Goods"
        }
    ],
    "sg:phone":"+1 215 513 0950",
    "sg:postcode":"19438",
    "sg:province":"PA",
    "sg:tags":[
        "food",
        "product"
    ],
    "wof:name":"Salad Bar Tenders",
    "wof:placetype":"venue"
},
  "geometry": {"coordinates":[-75.35899499999999,40.256056],"type":"Point"}
}