{
  "type": "Feature",
  "properties": {
    "iso:country":"US",
    "sg:address":"6395 Carlisle Pike",
    "sg:city":"Mechanicsburg",
    "sg:classifiers":[
        {
            "category":"Shopping",
            "subcategory":"Bridal",
            "type":"Retail Goods"
        }
    ],
    "sg:phone":"+1 717 697 5710",
    "sg:postcode":"17050",
    "sg:province":"PA",
    "sg:website":"www.gownsbydesignbridal.com",
    "wof:name":"Gowns by Design Bridal Salon",
    "wof:placetype":"venue"
},
  "geometry": {"coordinates":[-77.003601,40.246601],"type":"Point"}
}