{
  "type": "Feature",
  "properties": {
    "iso:country":"US",
    "sg:address":"2026 S 7th St",
    "sg:city":"Philadelphia",
    "sg:classifiers":[
        {
            "category":"Shopping",
            "subcategory":"Discount & Variety Stores",
            "type":"Retail Goods"
        }
    ],
    "sg:phone":"+1 215 468 4826",
    "sg:postcode":"19148",
    "sg:province":"PA",
    "sg:tags":[
        "merchandise",
        "general"
    ],
    "wof:name":"Titan Industrial Supply",
    "wof:placetype":"venue"
},
  "geometry": {"coordinates":[-75.158192,39.922891],"type":"Point"}
}