{
  "type": "Feature",
  "properties": {
    "iso:country":"US",
    "sg:address":"9000 Brooktree Rd",
    "sg:city":"Wexford",
    "sg:classifiers":[
        {
            "category":"Health Services",
            "subcategory":"Clinic",
            "type":"Services"
        }
    ],
    "sg:phone":"+1   ",
    "sg:postcode":"15090",
    "sg:province":"PA",
    "sg:tags":[
        "laboratory",
        "medical"
    ],
    "wof:name":"Wexford Womens Imaging",
    "wof:placetype":"venue"
},
  "geometry": {"coordinates":[-80.054928,40.614216],"type":"Point"}
}