{
  "type": "Feature",
  "properties": {
    "iso:country":"US",
    "sg:address":"2545 Schoenersville Rd",
    "sg:city":"Bethlehem",
    "sg:classifiers":[
        {
            "category":"Health Services",
            "subcategory":"Doctor",
            "type":"Services"
        }
    ],
    "sg:phone":"+1 484 884 3333",
    "sg:postcode":"18017",
    "sg:province":"PA",
    "wof:name":"Xu Shu Guang MD",
    "wof:placetype":"venue"
},
  "geometry": {"coordinates":[-75.418685,40.658377],"type":"Point"}
}