{
  "type": "Feature",
  "properties": {
    "iso:country":"US",
    "sg:address":"6600 Bustleton Ave",
    "sg:city":"Philadelphia",
    "sg:classifiers":[
        {
            "category":"Personal",
            "subcategory":"Beauty Salon",
            "type":"Services"
        }
    ],
    "sg:phone":"+1 215 335 9960",
    "sg:postcode":"19149",
    "sg:province":"PA",
    "sg:tags":[
        "shop"
    ],
    "wof:name":"Enzo Unisex Hair Styling",
    "wof:placetype":"venue"
},
  "geometry": {"coordinates":[-75.06743899999999,40.038608],"type":"Point"}
}