{
  "type": "Feature",
  "properties": {
    "iso:country":"US",
    "sg:address":"25 Gateway Dr",
    "sg:city":"Mechanicsburg",
    "sg:classifiers":[
        {
            "category":"Banks & Credit Unions",
            "subcategory":"Bank",
            "type":"Services"
        }
    ],
    "sg:phone":"+1   ",
    "sg:postcode":"17050",
    "sg:province":"PA",
    "sg:tags":[
        "personal",
        "institution"
    ],
    "wof:name":"HFC",
    "wof:placetype":"venue"
},
  "geometry": {"coordinates":[-76.980462,40.238043],"type":"Point"}
}