{
  "type": "Feature",
  "properties": {
    "iso:country":"US",
    "sg:address":"963 Englesville Hill Rd",
    "sg:city":"Boyertown",
    "sg:classifiers":[
        {
            "category":"Wholesale",
            "subcategory":"Hardware",
            "type":"Manufacturing & Wholesale Goods"
        }
    ],
    "sg:phone":"+1   ",
    "sg:postcode":"19512",
    "sg:province":"PA",
    "sg:tags":[
        "supply"
    ],
    "wof:name":"Pipco Inc",
    "wof:placetype":"venue"
},
  "geometry": {"coordinates":[-75.649907,40.310066],"type":"Point"}
}