{
  "type": "Feature",
  "properties": {
    "iso:country":"US",
    "sg:address":"2637 Cumberland St",
    "sg:city":"Lebanon",
    "sg:classifiers":[
        {
            "category":"Personal",
            "subcategory":"Tattoo Parlor",
            "type":"Services"
        },
        {
            "category":"Personal",
            "subcategory":"Piercing",
            "type":"Services"
        }
    ],
    "sg:phone":"+1 717 376 0190",
    "sg:postcode":"17042",
    "sg:province":"PA",
    "sg:tags":[
        "body"
    ],
    "wof:name":"Yi Shen Jing Tattooing",
    "wof:placetype":"venue"
},
  "geometry": {"coordinates":[-76.45939300000001,40.339723],"type":"Point"}
}