{
  "type": "Feature",
  "properties": {
    "addr:full":"104 Carmichaels Rd Carmichaels PA 15320",
    "addr:housenumber":"104",
    "addr:postcode":"15320",
    "addr:street":"Carmichaels Rd",
    "iso:country":"US",
    "sg:address":"104 Carmichaels Rd",
    "sg:city":"Carmichaels",
    "sg:classifiers":[
        {
            "category":"Restaurant",
            "type":"Food & Drink"
        }
    ],
    "sg:phone":"+1 724 966 2430",
    "sg:postcode":"15320",
    "sg:province":"PA",
    "sg:tags":[
        "eating"
    ],
    "wof:name":"Domino's Pizza",
    "wof:placetype":"venue"
},
  "geometry": {"coordinates":[-80.026335,39.818156],"type":"Point"}
}