{
  "type": "Feature",
  "properties": {
    "iso:country":"US",
    "sg:address":"238 York St",
    "sg:city":"Hanover",
    "sg:classifiers":[
        {
            "category":"Food & Beverages",
            "subcategory":"Groceries & Convenience Stores",
            "type":"Retail Goods"
        }
    ],
    "sg:phone":"+1 717 632 0091",
    "sg:postcode":"17331",
    "sg:province":"PA",
    "sg:tags":[
        "product"
    ],
    "wof:name":"Harmony Foods",
    "wof:placetype":"venue"
},
  "geometry": {"coordinates":[-76.97818700000001,39.799953],"type":"Point"}
}