{
  "type": "Feature",
  "properties": {
    "addr:full":"3000 State Rte 18 Hookstown PA 15050",
    "addr:housenumber":"3000",
    "addr:postcode":"15050",
    "addr:street":"State Rte 18",
    "iso:country":"US",
    "sg:address":"3000 State Rte 18",
    "sg:city":"Hookstown",
    "sg:classifiers":[
        {
            "category":"Recreation",
            "type":"Entertainment"
        }
    ],
    "sg:phone":"+1 724 899 2200",
    "sg:postcode":"15050",
    "sg:province":"PA",
    "sg:tags":[
        "parks"
    ],
    "wof:name":"Hillman State Park",
    "wof:placetype":"venue"
},
  "geometry": {"coordinates":[-80.42404999999999,40.502933],"type":"Point"}
}