{
  "type": "Feature",
  "properties": {
    "iso:country":"US",
    "sg:address":"5675 N Front St",
    "sg:city":"Philadelphia",
    "sg:classifiers":[
        {
            "category":"Restaurant",
            "type":"Food & Drink"
        }
    ],
    "sg:menulink":"http://www.allmenus.com/pa/philadelphia/170767-burger-king/menu/",
    "sg:phone":"+1 215 549 9110",
    "sg:postcode":"19120",
    "sg:province":"PA",
    "sg:tags":[
        "burger",
        "american"
    ],
    "wof:name":"Burger King",
    "wof:placetype":"venue"
},
  "geometry": {"coordinates":[-75.120998,40.03641],"type":"Point"}
}