{
  "type": "Feature",
  "properties": {
    "iso:country":"US",
    "sg:address":"2381 Philmont Ave",
    "sg:city":"Huntingdon Vly",
    "sg:classifiers":[
        {
            "category":"Manufacturing",
            "subcategory":"Printing",
            "type":"Manufacturing & Wholesale Goods"
        }
    ],
    "sg:phone":"+1 215 947 9722",
    "sg:postcode":"19006",
    "sg:province":"PA",
    "sg:tags":[
        "printer"
    ],
    "sg:website":"www.bctphiladelphia.com",
    "wof:name":"BCT",
    "wof:placetype":"venue"
},
  "geometry": {"coordinates":[-75.062333,40.119472],"type":"Point"}
}