{
  "type": "Feature",
  "properties": {
    "iso:country":"US",
    "sg:address":"5453 Master St",
    "sg:city":"Philadelphia",
    "sg:classifiers":[
        {
            "category":"Food & Beverages",
            "subcategory":"Groceries & Convenience Stores",
            "type":"Retail Goods"
        }
    ],
    "sg:phone":"+1 215 871 7595",
    "sg:postcode":"19131",
    "sg:province":"PA",
    "wof:name":"Torres Grocery",
    "wof:placetype":"venue"
},
  "geometry": {"coordinates":[-75.23063500000001,39.973901],"type":"Point"}
}