{
  "type": "Feature",
  "properties": {
    "iso:country":"US",
    "sg:address":"3399 Clark Rd",
    "sg:city":"Erie",
    "sg:classifiers":[
        {
            "category":"Freight",
            "type":"Transportation"
        }
    ],
    "sg:phone":"+1   ",
    "sg:postcode":"16510",
    "sg:province":"PA",
    "sg:tags":[
        "operator",
        "local",
        "trucking"
    ],
    "wof:name":"Stiver Trucking",
    "wof:placetype":"venue"
},
  "geometry": {"coordinates":[-79.968633,42.143871],"type":"Point"}
}