{
  "type": "Feature",
  "properties": {
    "iso:country":"US",
    "sg:address":"3790 Morgantown Rd",
    "sg:city":"Mohnton",
    "sg:classifiers":[
        {
            "category":"Restaurant",
            "type":"Food & Drink"
        }
    ],
    "sg:phone":"+1 610 856 7887",
    "sg:postcode":"19540",
    "sg:province":"PA",
    "sg:tags":[
        "eating"
    ],
    "wof:name":"Emily's Pub",
    "wof:placetype":"venue"
},
  "geometry": {"coordinates":[-75.90812099999999,40.233327],"type":"Point"}
}