{
  "type": "Feature",
  "properties": {
    "addr:full":"504 S Bank St Derry PA 15627",
    "addr:housenumber":"504",
    "addr:postcode":"15627",
    "addr:street":"S Bank St",
    "iso:country":"US",
    "sg:address":"504 S Bank St",
    "sg:city":"Derry",
    "sg:classifiers":[
        {
            "category":"Home & Garden",
            "subcategory":"Carpets & Floor Coverings",
            "type":"Retail Goods"
        }
    ],
    "sg:phone":"+1   ",
    "sg:postcode":"15627",
    "sg:province":"PA",
    "wof:name":"Joe Hill Floors",
    "wof:placetype":"venue"
},
  "geometry": {"coordinates":[-79.30714999999999,40.321639],"type":"Point"}
}