{
  "type": "Feature",
  "properties": {
    "addr:full":"21 S 12th St Ste 1040 Philadelphia PA 19107",
    "addr:housenumber":"21",
    "addr:postcode":"19107",
    "addr:street":"S 12Th St Ste 1040",
    "iso:country":"US",
    "sg:address":"21 S 12th St Ste 1040",
    "sg:city":"Philadelphia",
    "sg:classifiers":[
        {
            "category":"Professional",
            "subcategory":"Lawyer & Legal Services",
            "type":"Services"
        }
    ],
    "sg:phone":"+1 215 854 9600",
    "sg:postcode":"19107",
    "sg:province":"PA",
    "wof:name":"Cipparone Rocco C Jr",
    "wof:placetype":"venue"
},
  "geometry": {"coordinates":[-75.159806,39.951522],"type":"Point"}
}