{
  "type": "Feature",
  "properties": {
    "iso:country":"US",
    "sg:address":"145 W High St",
    "sg:city":"Bellefonte",
    "sg:classifiers":[
        {
            "category":"Personal",
            "subcategory":"Beauty Salon",
            "type":"Services"
        },
        {
            "category":"Personal",
            "subcategory":"Barber",
            "type":"Services"
        }
    ],
    "sg:phone":"+1 814 353 3360",
    "sg:postcode":"16823",
    "sg:province":"PA",
    "sg:tags":[
        "shop"
    ],
    "wof:name":"Amy's Fine Cuts",
    "wof:placetype":"venue"
},
  "geometry": {"coordinates":[-77.779297,40.911598],"type":"Point"}
}