{
  "type": "Feature",
  "properties": {
    "iso:country":"US",
    "sg:address":"1593 Gilmar Rd",
    "sg:city":"Apollo",
    "sg:classifiers":[
        {
            "category":"Building & Trades",
            "subcategory":"Construction",
            "type":"Services"
        }
    ],
    "sg:phone":"+1   ",
    "sg:postcode":"15613",
    "sg:province":"PA",
    "sg:tags":[
        "excavation",
        "contractor"
    ],
    "wof:name":"David Kosmach Excavating",
    "wof:placetype":"venue"
},
  "geometry": {"coordinates":[-79.63775699999999,40.504536],"type":"Point"}
}