{
  "type": "Feature",
  "properties": {
    "iso:country":"US",
    "sg:address":"7330 Anthony Hwy",
    "sg:city":"Waynesboro",
    "sg:classifiers":[
        {
            "category":"Building & Trades",
            "subcategory":"Equipment Rental",
            "type":"Services"
        }
    ],
    "sg:phone":"+1 717 749 5727",
    "sg:postcode":"17268",
    "sg:province":"PA",
    "sg:tags":[
        "crane"
    ],
    "wof:name":"Pat Krueger Cranes Inc",
    "wof:placetype":"venue"
},
  "geometry": {"coordinates":[-77.572073,39.822176],"type":"Point"}
}