{
  "type": "Feature",
  "properties": {
    "iso:country":"US",
    "sg:address":"537 Monarch Rd",
    "sg:city":"Dunbar",
    "sg:classifiers":[
        {
            "category":"Personal",
            "type":"Services"
        }
    ],
    "sg:phone":"+1 724 626 1426",
    "sg:postcode":"15431",
    "sg:province":"PA",
    "sg:tags":[
        "towing"
    ],
    "wof:name":"Brown's Auto Service",
    "wof:placetype":"venue"
},
  "geometry": {"coordinates":[-79.665398,39.9818],"type":"Point"}
}