{
  "type": "Feature",
  "properties": {
    "addr:full":"4000 N Front St Philadelphia PA 19140",
    "addr:housenumber":"4000",
    "addr:postcode":"19140",
    "addr:street":"N Front St",
    "iso:country":"US",
    "sg:address":"4000 N Front St",
    "sg:city":"Philadelphia",
    "sg:classifiers":[
        {
            "category":"Government",
            "subcategory":"Fire Station",
            "type":"Public Place"
        }
    ],
    "sg:phone":"+1   ",
    "sg:postcode":"19140",
    "sg:province":"PA",
    "sg:tags":[
        "protection"
    ],
    "wof:name":"Fire Dept",
    "wof:placetype":"venue"
},
  "geometry": {"coordinates":[-75.126296,40.012854],"type":"Point"}
}