{
  "type": "Feature",
  "properties": {
    "iso:country":"US",
    "sg:address":"2264 N 21st St",
    "sg:city":"Philadelphia",
    "sg:classifiers":[
        {
            "category":"Personal",
            "subcategory":"Beauty Salon",
            "type":"Services"
        }
    ],
    "sg:phone":"+1 215 235 1617",
    "sg:postcode":"19132",
    "sg:province":"PA",
    "wof:name":"Sarah Long",
    "wof:placetype":"venue"
},
  "geometry": {"coordinates":[-75.167535,39.988318],"type":"Point"}
}