{
  "type": "Feature",
  "properties": {
    "addr:full":"156 Old Nazareth Pike B Bethlehem PA 18020",
    "addr:housenumber":"156",
    "addr:postcode":"18020",
    "addr:street":"Old Nazareth Pike",
    "iso:country":"US",
    "sg:address":"156 Old Nazareth Pike B",
    "sg:city":"Bethlehem",
    "sg:classifiers":[
        {
            "category":"Communications",
            "subcategory":"Film & Video Production",
            "type":"Services"
        },
        {
            "category":"Professional",
            "subcategory":"Art Services",
            "type":"Services"
        }
    ],
    "sg:phone":"+1 610 746 5056",
    "sg:postcode":"18020",
    "sg:province":"PA",
    "sg:tags":[
        "creative",
        "audio-visual"
    ],
    "wof:name":"J I Penzes Productions",
    "wof:placetype":"venue"
},
  "geometry": {"coordinates":[-75.336173,40.686531],"type":"Point"}
}