{
  "type": "Feature",
  "properties": {
    "iso:country":"US",
    "sg:address":"113 Sandy Creek Rd",
    "sg:city":"Verona",
    "sg:classifiers":[
        {
            "category":"Retail",
            "subcategory":"Auto Repair",
            "type":"Services"
        }
    ],
    "sg:phone":"+1   ",
    "sg:postcode":"15147",
    "sg:province":"PA",
    "sg:tags":[
        "body",
        "automotive"
    ],
    "wof:name":"Conley B T Auto Body",
    "wof:placetype":"venue"
},
  "geometry": {"coordinates":[-79.848308,40.476291],"type":"Point"}
}