{
  "type": "Feature",
  "properties": {
    "addr:full":"102 N Tyson Ave Glenside PA 19038",
    "addr:housenumber":"102",
    "addr:postcode":"19038",
    "addr:street":"N Tyson Ave",
    "iso:country":"US",
    "sg:address":"102 N Tyson Ave",
    "sg:city":"Glenside",
    "sg:classifiers":[
        {
            "category":"Deli",
            "type":"Food & Drink"
        },
        {
            "category":"Restaurant",
            "type":"Food & Drink"
        }
    ],
    "sg:phone":"+1 215 886 1077",
    "sg:postcode":"19038",
    "sg:province":"PA",
    "sg:tags":[
        "delicatessen"
    ],
    "wof:name":"S J Rizzo",
    "wof:placetype":"venue"
},
  "geometry": {"coordinates":[-75.15907900000001,40.105296],"type":"Point"}
}