{
  "type": "Feature",
  "properties": {
    "addr:full":"2 N Chester Rd West Chester PA 19380",
    "addr:housenumber":"2",
    "addr:postcode":"19380",
    "addr:street":"N Chester Rd",
    "iso:country":"US",
    "sg:address":"2 N Chester Rd",
    "sg:city":"West Chester",
    "sg:classifiers":[
        {
            "category":"Government",
            "subcategory":"Office",
            "type":"Public Place"
        }
    ],
    "sg:phone":"+1 610 344 6625",
    "sg:postcode":"19380",
    "sg:province":"PA",
    "wof:name":"Honorable Alexander Endy",
    "wof:placetype":"venue"
},
  "geometry": {"coordinates":[-75.52457099999999,39.967524],"type":"Point"}
}