{
  "type": "Feature",
  "properties": {
    "addr:full":"1331 Oreilly Dr Feasterville Trevose PA 19053",
    "addr:housenumber":"1331",
    "addr:postcode":"19053",
    "addr:street":"Oreilly Dr",
    "iso:country":"US",
    "sg:address":"1331 Oreilly Dr",
    "sg:city":"Feasterville Trevose",
    "sg:classifiers":[
        {
            "category":"Education",
            "subcategory":"School",
            "type":"Public Place"
        }
    ],
    "sg:phone":"+1   ",
    "sg:postcode":"19053",
    "sg:province":"PA",
    "wof:name":"Usta Middle States Sectio",
    "wof:placetype":"venue"
},
  "geometry": {"coordinates":[-75.00373999999999,40.165704],"type":"Point"}
}