{
  "type": "Feature",
  "properties": {
    "addr:full":"853 Penn St Reading PA 19601",
    "addr:housenumber":"853",
    "addr:postcode":"19601",
    "addr:street":"Penn St",
    "iso:country":"US",
    "sg:address":"853 Penn St",
    "sg:city":"Reading",
    "sg:classifiers":[
        {
            "category":"Restaurant",
            "type":"Food & Drink"
        }
    ],
    "sg:phone":"+1 610 374 4860",
    "sg:postcode":"19601",
    "sg:province":"PA",
    "sg:tags":[
        "italian"
    ],
    "wof:name":"Italian Garden",
    "wof:placetype":"venue"
},
  "geometry": {"coordinates":[-75.92098799999999,40.335238],"type":"Point"}
}