{
  "type": "Feature",
  "properties": {
    "iso:country":"US",
    "sg:address":"18 Water St",
    "sg:city":"Reading",
    "sg:classifiers":[
        {
            "category":"Utilities",
            "subcategory":"Refuse",
            "type":"Services"
        }
    ],
    "sg:phone":"+1 610 929 2883",
    "sg:postcode":"19605",
    "sg:province":"PA",
    "sg:tags":[
        "waste",
        "removal"
    ],
    "wof:name":"Environmental Options Group",
    "wof:placetype":"venue"
},
  "geometry": {"coordinates":[-75.93025299999999,40.402444],"type":"Point"}
}