{
  "type": "Feature",
  "properties": {
    "iso:country":"US",
    "sg:address":"7520 City Ave",
    "sg:city":"Philadelphia",
    "sg:classifiers":[
        {
            "category":"Fast Food",
            "type":"Food & Drink"
        },
        {
            "category":"Restaurant",
            "type":"Food & Drink"
        }
    ],
    "sg:phone":"+1 215 878 8035",
    "sg:postcode":"19151",
    "sg:province":"PA",
    "sg:tags":[
        "mexican"
    ],
    "sg:website":"http://www.tacobell.com",
    "wof:name":"Taco Bell",
    "wof:placetype":"venue"
},
  "geometry": {"coordinates":[-75.26970799999999,39.979986],"type":"Point"}
}