{
  "type": "Feature",
  "properties": {
    "iso:country":"US",
    "sg:address":"117 N Eagle Rd",
    "sg:city":"Havertown",
    "sg:classifiers":[
        {
            "category":"Professional",
            "subcategory":"Lawyer & Legal Services",
            "type":"Services"
        }
    ],
    "sg:phone":"+1 610 924 9000",
    "sg:postcode":"19083",
    "sg:province":"PA",
    "sg:tags":[
        "attorney"
    ],
    "wof:name":"John B Alessandroni Attorney",
    "wof:placetype":"venue"
},
  "geometry": {"coordinates":[-75.319242,39.974452],"type":"Point"}
}