{
  "type": "Feature",
  "properties": {
    "iso:country":"US",
    "sg:address":"1295 Donnan Ave",
    "sg:city":"Washington",
    "sg:classifiers":[
        {
            "category":"Food & Beverages",
            "subcategory":"Candy",
            "type":"Retail Goods"
        }
    ],
    "sg:phone":"+1 724 228 7749",
    "sg:postcode":"15301",
    "sg:province":"PA",
    "sg:tags":[
        "store"
    ],
    "sg:website":"paradiseconfectionery.com",
    "wof:name":"Paradise Candy",
    "wof:placetype":"venue"
},
  "geometry": {"coordinates":[-80.256699,40.187199],"type":"Point"}
}