{
  "type": "Feature",
  "properties": {
    "iso:country":"US",
    "sg:address":"13 Coffman Ave",
    "sg:city":"Malvern",
    "sg:classifiers":[
        {
            "category":"Building & Trades",
            "subcategory":"Landscaping Services",
            "type":"Services"
        }
    ],
    "sg:phone":"+1 610 431 2701",
    "sg:postcode":"19355",
    "sg:province":"PA",
    "sg:tags":[
        "landscape",
        "contractor"
    ],
    "wof:name":"Brogan Landscaping Inc",
    "wof:placetype":"venue"
},
  "geometry": {"coordinates":[-75.567347,40.036078],"type":"Point"}
}