{
  "type": "Feature",
  "properties": {
    "iso:country":"US",
    "sg:address":"903 Washington Blvd",
    "sg:city":"Williamsport",
    "sg:classifiers":[
        {
            "category":"Personal",
            "subcategory":"Beauty Salon",
            "type":"Services"
        }
    ],
    "sg:phone":"+1   ",
    "sg:postcode":"17701",
    "sg:province":"PA",
    "sg:tags":[
        "shop"
    ],
    "wof:name":"Anns Beauty Galary",
    "wof:placetype":"venue"
},
  "geometry": {"coordinates":[-76.987193,41.248281],"type":"Point"}
}