{
  "type": "Feature",
  "properties": {
    "addr:full":"735 Beechnut Dr Pittsburgh PA 15205",
    "addr:housenumber":"735",
    "addr:postcode":"15205",
    "addr:street":"Beechnut Dr",
    "iso:country":"US",
    "sg:address":"735 Beechnut Dr",
    "sg:city":"Pittsburgh",
    "sg:classifiers":[
        {
            "category":"Food & Beverages",
            "subcategory":"Groceries & Convenience Stores",
            "type":"Retail Goods"
        },
        {
            "category":"Wholesale",
            "subcategory":"Groceries",
            "type":"Manufacturing & Wholesale Goods"
        }
    ],
    "sg:phone":"+1   ",
    "sg:postcode":"15205",
    "sg:province":"PA",
    "sg:tags":[
        "general"
    ],
    "wof:name":"Giant Eagle",
    "wof:placetype":"venue"
},
  "geometry": {"coordinates":[-80.086527,40.452349],"type":"Point"}
}