{
  "type": "Feature",
  "properties": {
    "iso:country":"US",
    "sg:address":"107 2nd St",
    "sg:city":"Monongahela",
    "sg:classifiers":[
        {
            "category":"Bars & Pubs",
            "type":"Food & Drink"
        }
    ],
    "sg:phone":"+1 724 258 2588",
    "sg:postcode":"15063",
    "sg:province":"PA",
    "sg:tags":[
        "drinking",
        "restaurant"
    ],
    "wof:name":"Blaine Hill Bbq",
    "wof:placetype":"venue"
},
  "geometry": {"coordinates":[-79.924004,40.201599],"type":"Point"}
}