{
  "type": "Feature",
  "properties": {
    "iso:country":"US",
    "sg:address":"410 S Van Pelt St",
    "sg:city":"Philadelphia",
    "sg:classifiers":[
        {
            "category":"Arts & Performance",
            "subcategory":"Art Gallery",
            "type":"Entertainment"
        }
    ],
    "sg:phone":"+1 215 985 1792",
    "sg:postcode":"19146",
    "sg:province":"PA",
    "sg:tags":[
        "fine",
        "artist"
    ],
    "wof:name":"Fox, Patty Art Consultant",
    "wof:placetype":"venue"
},
  "geometry": {"coordinates":[-75.17740999999999,39.946779],"type":"Point"}
}