{
  "type": "Feature",
  "properties": {
    "iso:country":"US",
    "sg:address":"344 Avi Dr",
    "sg:city":"Alburtis",
    "sg:classifiers":[
        {
            "category":"Real Estate",
            "subcategory":"Real Estate Agent",
            "type":"Services"
        }
    ],
    "sg:phone":"+1   ",
    "sg:postcode":"18011",
    "sg:province":"PA",
    "wof:name":"Marisol Quinones",
    "wof:placetype":"venue"
},
  "geometry": {"coordinates":[-75.610325,40.507658],"type":"Point"}
}