{
  "type": "Feature",
  "properties": {
    "iso:country":"US",
    "sg:address":"141 S Jefferson St",
    "sg:city":"Kittanning",
    "sg:classifiers":[
        {
            "category":"Manufacturing",
            "subcategory":"Tools & Machinery",
            "type":"Manufacturing & Wholesale Goods"
        }
    ],
    "sg:phone":"+1 724 548 4801",
    "sg:postcode":"16201",
    "sg:province":"PA",
    "sg:tags":[
        "mfg",
        "aids",
        "hearing",
        "repair"
    ],
    "wof:name":"Professional Hearing Aid Svc",
    "wof:placetype":"venue"
},
  "geometry": {"coordinates":[-79.51643300000001,40.810911],"type":"Point"}
}