{
  "type": "Feature",
  "properties": {
    "addr:full":"1601 E Passyunk Ave Philadelphia PA 19148",
    "addr:housenumber":"1601",
    "addr:postcode":"19148",
    "addr:street":"E Passyunk Ave",
    "iso:country":"US",
    "sg:address":"1601 E Passyunk Ave",
    "sg:city":"Philadelphia",
    "sg:classifiers":[
        {
            "category":"Restaurant",
            "type":"Food & Drink"
        }
    ],
    "sg:phone":"+1 215 271 1222",
    "sg:postcode":"19148",
    "sg:province":"PA",
    "sg:tags":[
        "sushi",
        "bar",
        "japanese"
    ],
    "sg:website":"www.izumiphilly.com",
    "wof:name":"Izumi",
    "wof:placetype":"venue"
},
  "geometry": {"coordinates":[-75.16342,39.929707],"type":"Point"}
}