{
  "type": "Feature",
  "properties": {
    "addr:full":"224 Shellyland Rd Manheim PA 17545",
    "addr:housenumber":"224",
    "addr:postcode":"17545",
    "addr:street":"Shellyland Rd",
    "iso:country":"US",
    "sg:address":"224 Shellyland Rd",
    "sg:city":"Manheim",
    "sg:classifiers":[
        {
            "category":"Freight",
            "type":"Transportation"
        }
    ],
    "sg:phone":"+1 717 657 5424",
    "sg:postcode":"17545",
    "sg:province":"PA",
    "sg:tags":[
        "mover"
    ],
    "wof:name":"Fritz Moving Co Inc",
    "wof:placetype":"venue"
},
  "geometry": {"coordinates":[-76.47141499999999,40.123489],"type":"Point"}
}