{
  "type": "Feature",
  "properties": {
    "addr:full":"8919 Ridge Ave Ste 12 Philadelphia PA 19128",
    "addr:housenumber":"8919;12",
    "addr:postcode":"19128",
    "addr:street":"Ridge Ave Ste",
    "iso:country":"US",
    "sg:address":"8919 Ridge Ave Ste 12",
    "sg:city":"Philadelphia",
    "sg:classifiers":[
        {
            "category":"Personal",
            "subcategory":"Nail Salon",
            "type":"Services"
        }
    ],
    "sg:phone":"+1 215 508 4277",
    "sg:postcode":"19128",
    "sg:province":"PA",
    "wof:name":"Pinki Nails",
    "wof:placetype":"venue"
},
  "geometry": {"coordinates":[-75.240578,40.069191],"type":"Point"}
}