{
  "type": "Feature",
  "properties": {
    "addr:full":"434 Rte 30 Imperial PA 15126",
    "addr:housenumber":"434",
    "addr:postcode":"15126",
    "addr:street":"Rte 30",
    "iso:country":"US",
    "sg:address":"434 Rte 30",
    "sg:city":"Imperial",
    "sg:classifiers":[
        {
            "category":"Shopping",
            "subcategory":"Gifts & Souvenirs",
            "type":"Retail Goods"
        }
    ],
    "sg:phone":"+1 724 695 3551",
    "sg:postcode":"15126",
    "sg:province":"PA",
    "sg:tags":[
        "shop"
    ],
    "wof:name":"Mamone's Bit Of Country",
    "wof:placetype":"venue"
},
  "geometry": {"coordinates":[-80.24119399999999,40.442837],"type":"Point"}
}