{
  "type": "Feature",
  "properties": {
    "iso:country":"US",
    "sg:address":"1200 Rte 422 E",
    "sg:city":"Fenelton",
    "sg:classifiers":[
        {
            "category":"Wholesale",
            "subcategory":"Auto Parts",
            "type":"Manufacturing & Wholesale Goods"
        }
    ],
    "sg:phone":"+1 724 285 4674",
    "sg:postcode":"16034",
    "sg:province":"PA",
    "sg:tags":[
        "automobile",
        "rebuilt",
        "used"
    ],
    "wof:name":"Weichey Auto Wrecking Repair",
    "wof:placetype":"venue"
},
  "geometry": {"coordinates":[-79.76250400000001,40.852398],"type":"Point"}
}