{
  "type": "Feature",
  "properties": {
    "iso:country":"US",
    "sg:address":"13 E Market St",
    "sg:city":"Lewistown",
    "sg:classifiers":[
        {
            "category":"Shopping",
            "subcategory":"Jewelry",
            "type":"Retail Goods"
        }
    ],
    "sg:phone":"+1 717 248 8160",
    "sg:postcode":"17044",
    "sg:province":"PA",
    "sg:tags":[
        "watch",
        "jeweler"
    ],
    "wof:name":"Wilson's Gifts & Jewelry",
    "wof:placetype":"venue"
},
  "geometry": {"coordinates":[-77.57328800000001,40.598304],"type":"Point"}
}