{
  "type": "Feature",
  "properties": {
    "iso:country":"US",
    "sg:address":"2360 Hospital Dr",
    "sg:city":"Aliquippa",
    "sg:classifiers":[
        {
            "category":"Health Services",
            "subcategory":"Doctor",
            "type":"Services"
        }
    ],
    "sg:phone":"+1 724 378 0830",
    "sg:postcode":"15001",
    "sg:province":"PA",
    "sg:tags":[
        "physician",
        "surgeon"
    ],
    "wof:name":"Gandhe Ashwini",
    "wof:placetype":"venue"
},
  "geometry": {"coordinates":[-80.287423,40.611047],"type":"Point"}
}