{
  "type": "Feature",
  "properties": {
    "addr:full":"5451 Rutland St Philadelphia PA 19124",
    "addr:housenumber":"5451",
    "addr:postcode":"19124",
    "addr:street":"Rutland St",
    "iso:country":"US",
    "sg:address":"5451 Rutland St",
    "sg:city":"Philadelphia",
    "sg:classifiers":[
        {
            "category":"Restaurant",
            "type":"Food & Drink"
        }
    ],
    "sg:phone":"+1 215 537 9443",
    "sg:postcode":"19124",
    "sg:province":"PA",
    "sg:tags":[
        "parlor",
        "ice",
        "cream"
    ],
    "wof:name":"Roses Real Italian Water Ice",
    "wof:placetype":"venue"
},
  "geometry": {"coordinates":[-75.083692,40.030388],"type":"Point"}
}