{
  "type": "Feature",
  "properties": {
    "addr:full":"709 Hamilton Mall Allentown PA 18101",
    "addr:housenumber":"709",
    "addr:postcode":"18101",
    "addr:street":"Hamilton Mall",
    "iso:country":"US",
    "sg:address":"709 Hamilton Mall",
    "sg:city":"Allentown",
    "sg:classifiers":[
        {
            "category":"Restaurant",
            "type":"Food & Drink"
        }
    ],
    "sg:phone":"+1   ",
    "sg:postcode":"18101",
    "sg:province":"PA",
    "sg:tags":[
        "franchise"
    ],
    "wof:name":"Wendys",
    "wof:placetype":"venue"
},
  "geometry": {"coordinates":[-75.472245,40.60218],"type":"Point"}
}