{
  "type": "Feature",
  "properties": {
    "iso:country":"US",
    "sg:address":"9 N Main St",
    "sg:city":"Carbondale",
    "sg:classifiers":[
        {
            "category":"Professional",
            "subcategory":"Computer Services",
            "type":"Services"
        }
    ],
    "sg:phone":"+1 570 282 8665",
    "sg:postcode":"18407",
    "sg:province":"PA",
    "sg:tags":[
        "graphics"
    ],
    "wof:name":"Lightcrafter Digital Video",
    "wof:placetype":"venue"
},
  "geometry": {"coordinates":[-75.484111,41.59314],"type":"Point"}
}