{
  "type": "Feature",
  "properties": {
    "iso:country":"US",
    "sg:address":"114 N Market St",
    "sg:city":"Berwick",
    "sg:classifiers":[
        {
            "category":"Professional",
            "subcategory":"Accounting & Tax Preparation",
            "type":"Services"
        }
    ],
    "sg:phone":"+1 570 752 2660",
    "sg:postcode":"18603",
    "sg:province":"PA",
    "sg:tags":[
        "accountant"
    ],
    "wof:name":"J H Williams & Co LLP",
    "wof:placetype":"venue"
},
  "geometry": {"coordinates":[-76.23396200000001,41.055285],"type":"Point"}
}