{
  "type": "Feature",
  "properties": {
    "iso:country":"US",
    "sg:address":"514 Fullerton Ave",
    "sg:city":"Whitehall",
    "sg:classifiers":[
        {
            "category":"Insurance",
            "subcategory":"Insurance Agent",
            "type":"Services"
        }
    ],
    "sg:phone":"+1   ",
    "sg:postcode":"18052",
    "sg:province":"PA",
    "wof:name":"Eastern Institute",
    "wof:placetype":"venue"
},
  "geometry": {"coordinates":[-75.469865,40.627802],"type":"Point"}
}