{
  "type": "Feature",
  "properties": {
    "addr:full":"100 Industrial Dr Delmont PA 15626",
    "addr:housenumber":"100",
    "addr:postcode":"15626",
    "addr:street":"Industrial Dr",
    "iso:country":"US",
    "sg:address":"100 Industrial Dr",
    "sg:city":"Delmont",
    "sg:classifiers":[
        {
            "category":"Real Estate",
            "subcategory":"Real Estate Agent",
            "type":"Services"
        }
    ],
    "sg:phone":"+1   ",
    "sg:postcode":"15626",
    "sg:province":"PA",
    "sg:tags":[
        "architectural",
        "mfg"
    ],
    "wof:name":"Salem Millwork and Truss Inc",
    "wof:placetype":"venue"
},
  "geometry": {"coordinates":[-79.575439,40.425204],"type":"Point"}
}