{
  "type": "Feature",
  "properties": {
    "iso:country":"US",
    "sg:address":"454 Evergreen Ln",
    "sg:city":"Needmore",
    "sg:phone":"+1   ",
    "sg:postcode":"17238",
    "sg:province":"PA",
    "sg:tags":[
        "farm",
        "crop",
        "field",
        "tract",
        "operation",
        "timber"
    ],
    "wof:name":"Miller Ray & Kelly",
    "wof:placetype":"venue"
},
  "geometry": {"coordinates":[-78.161852,39.851919],"type":"Point"}
}