{
  "type": "Feature",
  "properties": {
    "iso:country":"US",
    "sg:address":"275 Mundy St",
    "sg:city":"Wilkes Barre",
    "sg:classifiers":[
        {
            "category":"Insurance",
            "subcategory":"Insurance Agent",
            "type":"Services"
        }
    ],
    "sg:phone":"+1 570 825 6891",
    "sg:postcode":"18702",
    "sg:province":"PA",
    "sg:website":"www.firstinscenter.com",
    "wof:name":"FIRST Insurance Ctr",
    "wof:placetype":"venue"
},
  "geometry": {"coordinates":[-75.842124,41.243019],"type":"Point"}
}