{
  "type": "Feature",
  "properties": {
    "iso:country":"US",
    "sg:address":"5212 Lytle St",
    "sg:city":"Pittsburgh",
    "sg:classifiers":[
        {
            "category":"Manufacturing",
            "subcategory":"Signs",
            "type":"Manufacturing & Wholesale Goods"
        },
        {
            "category":"Manufacturing",
            "subcategory":"Printing",
            "type":"Manufacturing & Wholesale Goods"
        }
    ],
    "sg:phone":"+1 412 422 1125",
    "sg:postcode":"15207",
    "sg:province":"PA",
    "sg:tags":[
        "body",
        "repair",
        "printer",
        "mfg",
        "auto",
        "specialty",
        "advertising"
    ],
    "sg:website":"www.graphics22signs.com",
    "wof:name":"Graphics 22 Signs Inc",
    "wof:placetype":"venue"
},
  "geometry": {"coordinates":[-79.944726,40.403682],"type":"Point"}
}