{
  "type": "Feature",
  "properties": {
    "iso:country":"US",
    "sg:address":"1001 S Saint Marys Rd",
    "sg:city":"Saint Marys",
    "sg:classifiers":[
        {
            "category":"Shopping",
            "type":"Retail Goods"
        }
    ],
    "sg:phone":"+1   ",
    "sg:postcode":"15857",
    "sg:province":"PA",
    "sg:tags":[
        "merchandise"
    ],
    "wof:name":"Verizon",
    "wof:placetype":"venue"
},
  "geometry": {"coordinates":[-78.56030199999999,41.401421],"type":"Point"}
}