{
  "type": "Feature",
  "properties": {
    "iso:country":"US",
    "sg:address":"243 E Main St",
    "sg:city":"Uniontown",
    "sg:classifiers":[
        {
            "category":"Autos & Motor Vehicles",
            "subcategory":"Automobile Sales",
            "type":"Retail Goods"
        }
    ],
    "sg:phone":"+1   ",
    "sg:postcode":"15401",
    "sg:province":"PA",
    "sg:tags":[
        "used",
        "local",
        "hauling"
    ],
    "wof:name":"Fike Brothers Trucking",
    "wof:placetype":"venue"
},
  "geometry": {"coordinates":[-79.71683899999999,39.898391],"type":"Point"}
}