{
  "type": "Feature",
  "properties": {
    "addr:full":"7 Woodsworth Ct Wayne PA 19087",
    "addr:housenumber":"7",
    "addr:postcode":"19087",
    "addr:street":"Woodsworth Ct",
    "iso:country":"US",
    "sg:address":"7 Woodsworth Ct",
    "sg:city":"Wayne",
    "sg:classifiers":[
        {
            "category":"Personal",
            "subcategory":"Beauty Salon",
            "type":"Services"
        }
    ],
    "sg:phone":"+1   ",
    "sg:postcode":"19087",
    "sg:province":"PA",
    "sg:tags":[
        "shop"
    ],
    "wof:name":"Lets Have An Affair",
    "wof:placetype":"venue"
},
  "geometry": {"coordinates":[-75.39064500000001,40.051936],"type":"Point"}
}