{
  "type": "Feature",
  "properties": {
    "iso:country":"US",
    "sg:address":"138 W Market St",
    "sg:city":"Mercer",
    "sg:classifiers":[
        {
            "category":"Health Services",
            "subcategory":"Optometrist",
            "type":"Services"
        }
    ],
    "sg:phone":"+1   ",
    "sg:postcode":"16137",
    "sg:province":"PA",
    "sg:tags":[
        "optical",
        "good"
    ],
    "wof:name":"Optometrist Family Eyecare",
    "wof:placetype":"venue"
},
  "geometry": {"coordinates":[-80.241916,41.226956],"type":"Point"}
}