{
  "type": "Feature",
  "properties": {
    "iso:country":"US",
    "sg:address":"1000 Gamma Dr",
    "sg:city":"Pittsburgh",
    "sg:classifiers":[
        {
            "category":"Professional",
            "subcategory":"Computer Services",
            "type":"Services"
        }
    ],
    "sg:phone":"+1 412 963 7568",
    "sg:postcode":"15238",
    "sg:province":"PA",
    "sg:tags":[
        "consultant",
        "designer"
    ],
    "wof:name":"Computer Aid Inc",
    "wof:placetype":"venue"
},
  "geometry": {"coordinates":[-79.86143800000001,40.501144],"type":"Point"}
}