{
  "type": "Feature",
  "properties": {
    "addr:full":"821 Bridle Path Dr Wexford PA 15090",
    "addr:housenumber":"821",
    "addr:postcode":"15090",
    "addr:street":"Bridle Path Dr",
    "iso:country":"US",
    "sg:address":"821 Bridle Path Dr",
    "sg:city":"Wexford",
    "sg:classifiers":[
        {
            "category":"Professional",
            "subcategory":"Detective & Security Services",
            "type":"Services"
        }
    ],
    "sg:phone":"+1   ",
    "sg:postcode":"15090",
    "sg:province":"PA",
    "sg:tags":[
        "car"
    ],
    "wof:name":"Finley Consulting & Investigat",
    "wof:placetype":"venue"
},
  "geometry": {"coordinates":[-80.092448,40.647489],"type":"Point"}
}