{
  "type": "Feature",
  "properties": {
    "addr:full":"193 Front St Hellertown PA 18055",
    "addr:housenumber":"193",
    "addr:postcode":"18055",
    "addr:street":"Front St",
    "iso:country":"US",
    "sg:address":"193 Front St",
    "sg:city":"Hellertown",
    "sg:classifiers":[
        {
            "category":"Retail",
            "subcategory":"Auto Repair",
            "type":"Services"
        }
    ],
    "sg:phone":"+1   ",
    "sg:postcode":"18055",
    "sg:province":"PA",
    "sg:tags":[
        "body",
        "general"
    ],
    "wof:name":"Kichlines Body Shop",
    "wof:placetype":"venue"
},
  "geometry": {"coordinates":[-75.342044,40.572523],"type":"Point"}
}