{
  "type": "Feature",
  "properties": {
    "iso:country":"US",
    "sg:address":"680 Tennis Ave",
    "sg:city":"Ambler",
    "sg:classifiers":[
        {
            "category":"Recreation",
            "type":"Entertainment"
        }
    ],
    "sg:phone":"+1   ",
    "sg:postcode":"19002",
    "sg:province":"PA",
    "sg:tags":[
        "club",
        "membership",
        "sport"
    ],
    "wof:name":"Upper Dublin Sport Center LLC",
    "wof:placetype":"venue"
},
  "geometry": {"coordinates":[-75.211202,40.172838],"type":"Point"}
}