{
  "type": "Feature",
  "properties": {
    "iso:country":"US",
    "sg:address":"706 Market St",
    "sg:city":"Williamsport",
    "sg:classifiers":[
        {
            "category":"Professional",
            "subcategory":"Business Services",
            "type":"Services"
        },
        {
            "category":"Shopping",
            "subcategory":"Gifts & Souvenirs",
            "type":"Retail Goods"
        }
    ],
    "sg:phone":"+1 570 322 4800",
    "sg:postcode":"17701",
    "sg:province":"PA",
    "sg:tags":[
        "shop",
        "interior",
        "design"
    ],
    "sg:website":"www.interiorsandgifts.com",
    "wof:name":"Smith Rudasill Interiors Gifts",
    "wof:placetype":"venue"
},
  "geometry": {"coordinates":[-77.005775,41.246829],"type":"Point"}
}