{
  "type": "Feature",
  "properties": {
    "iso:country":"US",
    "sg:address":"826 E Bellevue Ave",
    "sg:city":"Reading",
    "sg:classifiers":[
        {
            "category":"Utilities",
            "subcategory":"Telephone",
            "type":"Services"
        }
    ],
    "sg:phone":"+1   ",
    "sg:postcode":"19605",
    "sg:province":"PA",
    "sg:tags":[
        "internet",
        "provider"
    ],
    "wof:name":"Bluetrucknet",
    "wof:placetype":"venue"
},
  "geometry": {"coordinates":[-75.921576,40.388473],"type":"Point"}
}