{
  "type": "Feature",
  "properties": {
    "iso:country":"US",
    "sg:address":"500 Upland Rd",
    "sg:city":"Havertown",
    "sg:classifiers":[
        {
            "category":"Building & Trades",
            "subcategory":"Landscaping Services",
            "type":"Services"
        }
    ],
    "sg:phone":"+1 610 449 7980",
    "sg:postcode":"19083",
    "sg:province":"PA",
    "wof:name":"Landrum Landscaping",
    "wof:placetype":"venue"
},
  "geometry": {"coordinates":[-75.31855299999999,39.979027],"type":"Point"}
}