{
  "type": "Feature",
  "properties": {
    "iso:country":"US",
    "sg:address":"3366 Garnet Mine Rd",
    "sg:city":"Marcus Hook",
    "sg:classifiers":[
        {
            "category":"Building & Trades",
            "subcategory":"Construction",
            "type":"Services"
        }
    ],
    "sg:phone":"+1   ",
    "sg:postcode":"19061",
    "sg:province":"PA",
    "sg:tags":[
        "house"
    ],
    "wof:name":"Suburban Construction Assoc",
    "wof:placetype":"venue"
},
  "geometry": {"coordinates":[-75.50332899999999,39.851833],"type":"Point"}
}