{
  "type": "Feature",
  "properties": {
    "iso:country":"US",
    "sg:address":"2846 Bottle Run Rd",
    "sg:city":"Williamsport",
    "sg:classifiers":[
        {
            "category":"Home & Garden",
            "subcategory":"Home Furnishings",
            "type":"Retail Goods"
        }
    ],
    "sg:phone":"+1 570 322 8029",
    "sg:postcode":"17701",
    "sg:province":"PA",
    "sg:tags":[
        "window",
        "covering"
    ],
    "wof:name":"Impressions Unlimited",
    "wof:placetype":"venue"
},
  "geometry": {"coordinates":[-77.083966,41.267428],"type":"Point"}
}