{
  "type": "Feature",
  "properties": {
    "iso:country":"US",
    "sg:address":"651 E Springfield Rd",
    "sg:city":"Springfield",
    "sg:classifiers":[
        {
            "category":"Place Of Worship",
            "subcategory":"Church",
            "type":"Public Place"
        },
        {
            "category":"Place Of Worship",
            "type":"Public Place"
        }
    ],
    "sg:phone":"+1 610 259 2240",
    "sg:postcode":"19064",
    "sg:province":"PA",
    "sg:tags":[
        "churches-catholic-traditional",
        "churches-catholic"
    ],
    "wof:name":"Korean Catholic Community",
    "wof:placetype":"venue"
},
  "geometry": {"coordinates":[-75.311582,39.930501],"type":"Point"}
}