{
  "type": "Feature",
  "properties": {
    "addr:full":"117 W Frankford St Bethlehem PA 18018",
    "addr:housenumber":"117",
    "addr:postcode":"18018",
    "addr:street":"W Frankford St",
    "iso:country":"US",
    "sg:address":"117 W Frankford St",
    "sg:city":"Bethlehem",
    "sg:classifiers":[
        {
            "category":"Retail",
            "subcategory":"Laundry & Dry Cleaning",
            "type":"Services"
        }
    ],
    "sg:phone":"+1   ",
    "sg:postcode":"18018",
    "sg:province":"PA",
    "wof:name":"Olympic Carpet Cleaners",
    "wof:placetype":"venue"
},
  "geometry": {"coordinates":[-75.382312,40.628279],"type":"Point"}
}