{
  "type": "Feature",
  "properties": {
    "addr:full":"196 Main St Oley PA 19547",
    "addr:housenumber":"196",
    "addr:postcode":"19547",
    "addr:street":"Main St",
    "iso:country":"US",
    "sg:address":"196 Main St",
    "sg:city":"Oley",
    "sg:classifiers":[
        {
            "category":"Manufacturing",
            "subcategory":"Metals",
            "type":"Manufacturing & Wholesale Goods"
        }
    ],
    "sg:phone":"+1 610 987 3733",
    "sg:postcode":"19547",
    "sg:province":"PA",
    "sg:tags":[
        "sheet",
        "installation",
        "fabrication"
    ],
    "wof:name":"Double D Sheet Metal Inc",
    "wof:placetype":"venue"
},
  "geometry": {"coordinates":[-75.793508,40.390377],"type":"Point"}
}