{
  "type": "Feature",
  "properties": {
    "iso:country":"US",
    "sg:address":"3 W Chestnut St",
    "sg:city":"Mt Union",
    "sg:classifiers":[
        {
            "category":"Organizations",
            "subcategory":"Religious Organization",
            "type":"Services"
        }
    ],
    "sg:phone":"+1 814 542 8977",
    "sg:postcode":"17066",
    "sg:province":"PA",
    "sg:tags":[
        "church"
    ],
    "wof:name":"Mt Hope Missionary Baptist Chr",
    "wof:placetype":"venue"
},
  "geometry": {"coordinates":[-77.880539,40.389724],"type":"Point"}
}