{
  "type": "Feature",
  "properties": {
    "addr:full":"22 Essex Ln Langhorne PA 19047",
    "addr:housenumber":"22",
    "addr:postcode":"19047",
    "addr:street":"Essex Ln",
    "iso:country":"US",
    "sg:address":"22 Essex Ln",
    "sg:city":"Langhorne",
    "sg:classifiers":[
        {
            "category":"Banks & Credit Unions",
            "subcategory":"Financial Services",
            "type":"Services"
        }
    ],
    "sg:phone":"+1   ",
    "sg:postcode":"19047",
    "sg:province":"PA",
    "sg:tags":[
        "investor"
    ],
    "wof:name":"No Limit Investors",
    "wof:placetype":"venue"
},
  "geometry": {"coordinates":[-74.94732500000001,40.174555],"type":"Point"}
}