{
  "type": "Feature",
  "properties": {
    "addr:full":"1029 W View Park Dr Pittsburgh PA 15229",
    "addr:housenumber":"1029",
    "addr:postcode":"15229",
    "addr:street":"W View Park Dr",
    "iso:country":"US",
    "sg:address":"1029 W View Park Dr",
    "sg:city":"Pittsburgh",
    "sg:classifiers":[
        {
            "category":"Food & Beverages",
            "subcategory":"Groceries & Convenience Stores",
            "type":"Retail Goods"
        }
    ],
    "sg:phone":"+1 412 931 0148",
    "sg:postcode":"15229",
    "sg:province":"PA",
    "sg:tags":[
        "laboratory",
        "laundry",
        "power"
    ],
    "wof:name":"Giant Eagle",
    "wof:placetype":"venue"
},
  "geometry": {"coordinates":[-80.034282,40.516594],"type":"Point"}
}