{
  "type": "Feature",
  "properties": {
    "iso:country":"US",
    "sg:address":"1500 John F Kennedy Blvd Ste 130",
    "sg:city":"Philadelphia",
    "sg:classifiers":[
        {
            "category":"Banks & Credit Unions",
            "subcategory":"Bank",
            "type":"Services"
        }
    ],
    "sg:phone":"+1 215 564 1685",
    "sg:postcode":"19102",
    "sg:province":"PA",
    "wof:name":"Commerce Bank",
    "wof:placetype":"venue"
},
  "geometry": {"coordinates":[-75.165071,39.953474],"type":"Point"}
}