{
  "type": "Feature",
  "properties": {
    "iso:country":"US",
    "sg:address":"7446 Ogontz Ave",
    "sg:city":"Philadelphia",
    "sg:classifiers":[
        {
            "category":"Retail",
            "subcategory":"Auto Repair",
            "type":"Services"
        }
    ],
    "sg:phone":"+1 215 424 9708",
    "sg:postcode":"19138",
    "sg:province":"PA",
    "sg:tags":[
        "repairing",
        "automobile"
    ],
    "wof:name":"Philadelphia Motorworld Inc",
    "wof:placetype":"venue"
},
  "geometry": {"coordinates":[-75.15660200000001,40.067562],"type":"Point"}
}