{
  "type": "Feature",
  "properties": {
    "addr:full":"2912 Olga Ave Bensalem PA 19020",
    "addr:housenumber":"2912",
    "addr:postcode":"19020",
    "addr:street":"Olga Ave",
    "iso:country":"US",
    "sg:address":"2912 Olga Ave",
    "sg:city":"Bensalem",
    "sg:classifiers":[
        {
            "category":"Shopping",
            "subcategory":"Hobbies, Toys, & Games",
            "type":"Retail Goods"
        }
    ],
    "sg:phone":"+1   ",
    "sg:postcode":"19020",
    "sg:province":"PA",
    "wof:name":"RI Creations",
    "wof:placetype":"venue"
},
  "geometry": {"coordinates":[-74.942324,40.092644],"type":"Point"}
}