{
  "type": "Feature",
  "properties": {
    "iso:country":"US",
    "sg:address":"701 Smithfield St",
    "sg:city":"Pittsburgh",
    "sg:classifiers":[
        {
            "category":"Professional",
            "subcategory":"Employment Agencies",
            "type":"Services"
        }
    ],
    "sg:phone":"+1 412 261 4130",
    "sg:postcode":"15222",
    "sg:province":"PA",
    "sg:tags":[
        "help",
        "contractor"
    ],
    "wof:name":"First Choice Temporary Services",
    "wof:placetype":"venue"
},
  "geometry": {"coordinates":[-79.996803,40.442799],"type":"Point"}
}