{
  "type": "Feature",
  "properties": {
    "addr:full":"620 Little Gap Rd Palmerton PA 18071",
    "addr:housenumber":"620",
    "addr:postcode":"18071",
    "addr:street":"Little Gap Rd",
    "iso:country":"US",
    "sg:address":"620 Little Gap Rd",
    "sg:city":"Palmerton",
    "sg:classifiers":[
        {
            "category":"Retail",
            "subcategory":"Auto Rental",
            "type":"Services"
        }
    ],
    "sg:phone":"+1 610 826 6374",
    "sg:postcode":"18071",
    "sg:province":"PA",
    "sg:tags":[
        "renting",
        "truck",
        "leasing"
    ],
    "wof:name":"U-Haul Co",
    "wof:placetype":"venue"
},
  "geometry": {"coordinates":[-75.58475900000001,40.812997],"type":"Point"}
}