{
  "type": "Feature",
  "properties": {
    "addr:full":"914 N 2nd St Philadelphia PA 19123",
    "addr:housenumber":"914",
    "addr:postcode":"19123",
    "addr:street":"N 2Nd St",
    "iso:country":"US",
    "sg:address":"914 N 2nd St",
    "sg:city":"Philadelphia",
    "sg:classifiers":[
        {
            "category":"Restaurant",
            "type":"Food & Drink"
        }
    ],
    "sg:phone":"+1 800 232 2004",
    "sg:postcode":"19123",
    "sg:province":"PA",
    "sg:tags":[
        "eating",
        "barbeque"
    ],
    "wof:name":"Miss Amelia's Bar-B-Que",
    "wof:placetype":"venue"
},
  "geometry": {"coordinates":[-75.140404,39.9646],"type":"Point"}
}