{
  "type": "Feature",
  "properties": {
    "iso:country":"US",
    "sg:address":"127 Old Plank Rd",
    "sg:city":"Washington",
    "sg:classifiers":[
        {
            "category":"Restaurant",
            "type":"Food & Drink"
        }
    ],
    "sg:phone":"+1   ",
    "sg:postcode":"15301",
    "sg:province":"PA",
    "sg:tags":[
        "eating"
    ],
    "wof:name":"Kandys Kitchen",
    "wof:placetype":"venue"
},
  "geometry": {"coordinates":[-80.288112,40.129433],"type":"Point"}
}