{
  "type": "Feature",
  "properties": {
    "iso:country":"US",
    "sg:address":"636 Collins Ave",
    "sg:city":"Pittsburgh",
    "sg:classifiers":[
        {
            "category":"Recreation",
            "type":"Entertainment"
        }
    ],
    "sg:phone":"+1   ",
    "sg:postcode":"15206",
    "sg:province":"PA",
    "wof:name":"Robinsons Bodywork Inc",
    "wof:placetype":"venue"
},
  "geometry": {"coordinates":[-79.91878199999999,40.466725],"type":"Point"}
}