{
  "type": "Feature",
  "properties": {
    "iso:country":"US",
    "sg:address":"1750 S Easton Rd",
    "sg:city":"Doylestown",
    "sg:classifiers":[
        {
            "category":"Government",
            "subcategory":"Office",
            "type":"Public Place"
        }
    ],
    "sg:phone":"+1 215 340 8300",
    "sg:postcode":"18901",
    "sg:province":"PA",
    "wof:name":"Bucks County Youth Ctr",
    "wof:placetype":"venue"
},
  "geometry": {"coordinates":[-75.127481,40.27667],"type":"Point"}
}