{
  "type": "Feature",
  "properties": {
    "iso:country":"US",
    "sg:address":"1386 Naamans Creek Rd",
    "sg:city":"Marcus Hook",
    "sg:classifiers":[
        {
            "category":"Real Estate",
            "subcategory":"Real Estate Services",
            "type":"Services"
        }
    ],
    "sg:phone":"+1 610 485 5918",
    "sg:postcode":"19061",
    "sg:province":"PA",
    "sg:tags":[
        "company",
        "title"
    ],
    "wof:name":"Garnet Valley Abstract LLC",
    "wof:placetype":"venue"
},
  "geometry": {"coordinates":[-75.4956,39.839464],"type":"Point"}
}