{
  "type": "Feature",
  "properties": {
    "iso:country":"US",
    "sg:address":"221 Hastings Ave",
    "sg:city":"Havertown",
    "sg:classifiers":[
        {
            "category":"Building & Trades",
            "subcategory":"Plumbing",
            "type":"Services"
        }
    ],
    "sg:phone":"+1   ",
    "sg:postcode":"19083",
    "sg:province":"PA",
    "sg:tags":[
        "contractor"
    ],
    "wof:name":"Gorski Mechanical",
    "wof:placetype":"venue"
},
  "geometry": {"coordinates":[-75.302384,39.988935],"type":"Point"}
}