{
  "type": "Feature",
  "properties": {
    "iso:country":"US",
    "sg:address":"10755 Smith Rd",
    "sg:city":"North East",
    "sg:classifiers":[
        {
            "category":"Home & Garden",
            "subcategory":"Carpets & Floor Coverings",
            "type":"Retail Goods"
        }
    ],
    "sg:phone":"+1   ",
    "sg:postcode":"16428",
    "sg:province":"PA",
    "sg:tags":[
        "installs"
    ],
    "wof:name":"Carpet Craftsman",
    "wof:placetype":"venue"
},
  "geometry": {"coordinates":[-79.829005,42.185075],"type":"Point"}
}