{
  "type": "Feature",
  "properties": {
    "iso:country":"US",
    "sg:address":"5775 Baptist Rd",
    "sg:city":"Bethel Park",
    "sg:classifiers":[
        {
            "category":"Home & Garden",
            "subcategory":"Hardware",
            "type":"Retail Goods"
        }
    ],
    "sg:phone":"+1 412 212 2000",
    "sg:postcode":"15102",
    "sg:province":"PA",
    "sg:tags":[
        "store"
    ],
    "wof:name":"Lowe's",
    "wof:placetype":"venue"
},
  "geometry": {"coordinates":[-80.014477,40.348914],"type":"Point"}
}