{
  "type": "Feature",
  "properties": {
    "iso:country":"US",
    "sg:address":"56 Evans St",
    "sg:city":"Warminster",
    "sg:classifiers":[
        {
            "category":"Building & Trades",
            "subcategory":"Construction",
            "type":"Services"
        },
        {
            "category":"Sports & Exercise",
            "subcategory":"Swimming Pool",
            "type":"Entertainment"
        }
    ],
    "sg:phone":"+1 215 674 2829",
    "sg:postcode":"18974",
    "sg:province":"PA",
    "sg:tags":[
        "repair",
        "consulting",
        "designing"
    ],
    "sg:website":"http://www.RigousCustomPools.com",
    "wof:name":"Rigous Custom Pools",
    "wof:placetype":"venue"
},
  "geometry": {"coordinates":[-75.086658,40.187216],"type":"Point"}
}