{
  "type": "Feature",
  "properties": {
    "iso:country":"US",
    "sg:address":"1000 Ross Ave",
    "sg:city":"Pittsburgh",
    "sg:classifiers":[
        {
            "category":"Shopping",
            "subcategory":"Clothing, Apparel, & Fashions",
            "type":"Retail Goods"
        }
    ],
    "sg:phone":"+1   ",
    "sg:postcode":"15221",
    "sg:province":"PA",
    "sg:tags":[
        "mfg"
    ],
    "wof:name":"Bebe",
    "wof:placetype":"venue"
},
  "geometry": {"coordinates":[-79.878175,40.44054],"type":"Point"}
}