{
  "type": "Feature",
  "properties": {
    "iso:country":"US",
    "sg:address":"113 Sandy Flat Rd",
    "sg:city":"Reynoldsville",
    "sg:classifiers":[
        {
            "category":"Organizations",
            "subcategory":"Religious Organization",
            "type":"Services"
        }
    ],
    "sg:phone":"+1 814 653 2344",
    "sg:postcode":"15864",
    "sg:province":"PA",
    "sg:tags":[
        "church"
    ],
    "wof:name":"Sandy Valley Community Church",
    "wof:placetype":"venue"
},
  "geometry": {"coordinates":[-79.255957,41.134432],"type":"Point"}
}