{
  "type": "Feature",
  "properties": {
    "iso:country":"US",
    "sg:address":"35 W High St",
    "sg:city":"Carlisle",
    "sg:classifiers":[
        {
            "category":"Fast Food",
            "type":"Food & Drink"
        },
        {
            "category":"Restaurant",
            "type":"Food & Drink"
        },
        {
            "category":"Food & Beverages",
            "subcategory":"Groceries & Convenience Stores",
            "type":"Retail Goods"
        }
    ],
    "sg:phone":"+1 717 249 7299",
    "sg:postcode":"17013",
    "sg:province":"PA",
    "sg:tags":[
        "shop",
        "american",
        "sandwich",
        "take"
    ],
    "sg:website":"http://www.subway.com",
    "wof:name":"SUBWAY",
    "wof:placetype":"venue"
},
  "geometry": {"coordinates":[-77.19024,40.201578],"type":"Point"}
}