{
  "type": "Feature",
  "properties": {
    "iso:country":"US",
    "sg:address":"372 S Main St",
    "sg:city":"Manheim",
    "sg:classifiers":[
        {
            "category":"Autos & Motor Vehicles",
            "subcategory":"Automobile Sales",
            "type":"Retail Goods"
        }
    ],
    "sg:phone":"+1 717 664 0594",
    "sg:postcode":"17545",
    "sg:province":"PA",
    "sg:tags":[
        "dealers-used",
        "car",
        "used",
        "cars-wholesale"
    ],
    "wof:name":"Quality Car Care Auto Sal",
    "wof:placetype":"venue"
},
  "geometry": {"coordinates":[-76.387297,40.156539],"type":"Point"}
}