{
  "type": "Feature",
  "properties": {
    "addr:full":"1401 Lehigh St Allentown PA 18103",
    "addr:housenumber":"1401",
    "addr:postcode":"18103",
    "addr:street":"Lehigh St",
    "iso:country":"US",
    "sg:address":"1401 Lehigh St",
    "sg:city":"Allentown",
    "sg:classifiers":[
        {
            "category":"Autos & Motor Vehicles",
            "subcategory":"Auto Supplies",
            "type":"Retail Goods"
        },
        {
            "category":"Retail",
            "subcategory":"Auto Repair",
            "type":"Services"
        }
    ],
    "sg:phone":"+1 610 791 4430",
    "sg:postcode":"18103",
    "sg:province":"PA",
    "sg:tags":[
        "exhaust",
        "oil",
        "tire",
        "automobile",
        "system",
        "lube",
        "part",
        "brake",
        "muffler"
    ],
    "sg:website":"http://www.monro.com",
    "wof:name":"Monro Muffler Brake & Service",
    "wof:placetype":"venue"
},
  "geometry": {"coordinates":[-75.477493,40.58234],"type":"Point"}
}