{
  "type": "Feature",
  "properties": {
    "iso:country":"US",
    "sg:address":"204 Shoemaker Rd",
    "sg:city":"Pottstown",
    "sg:classifiers":[
        {
            "category":"Building & Trades",
            "subcategory":"Equipment Rental",
            "type":"Services"
        }
    ],
    "sg:phone":"+1 484 941 0880",
    "sg:postcode":"19464",
    "sg:province":"PA",
    "sg:tags":[
        "leasing",
        "furniture"
    ],
    "wof:name":"Aarons Sales & Lease Ownership",
    "wof:placetype":"venue"
},
  "geometry": {"coordinates":[-75.667186,40.25637],"type":"Point"}
}