{
  "type": "Feature",
  "properties": {
    "iso:country":"US",
    "sg:address":"140 Ridge View Rd",
    "sg:city":"New Kensington",
    "sg:classifiers":[
        {
            "category":"Professional",
            "subcategory":"Business Services",
            "type":"Services"
        }
    ],
    "sg:phone":"+1 412 798 8555",
    "sg:postcode":"15068",
    "sg:province":"PA",
    "sg:tags":[
        "embroidery"
    ],
    "wof:name":"Excel Impressions",
    "wof:placetype":"venue"
},
  "geometry": {"coordinates":[-79.784716,40.516135],"type":"Point"}
}