{
  "type": "Feature",
  "properties": {
    "addr:full":"9760 Grosick Rd Pittsburgh PA 15237",
    "addr:postcode":"9760;15237",
    "addr:street":"Grosick Rd",
    "iso:country":"US",
    "sg:address":"9760 Grosick Rd",
    "sg:city":"Pittsburgh",
    "sg:classifiers":[
        {
            "category":"Retail",
            "subcategory":"Auto Repair",
            "type":"Services"
        },
        {
            "category":"Home & Garden",
            "subcategory":"Garden Supply",
            "type":"Retail Goods"
        }
    ],
    "sg:phone":"+1 412 364 8575",
    "sg:postcode":"15237",
    "sg:province":"PA",
    "sg:tags":[
        "lawn",
        "general",
        "mower"
    ],
    "wof:name":"Cooper's Garage",
    "wof:placetype":"venue"
},
  "geometry": {"coordinates":[-80.05227499999999,40.583793],"type":"Point"}
}