{
  "type": "Feature",
  "properties": {
    "iso:country":"US",
    "sg:address":"4596 Cross Roads Blvd",
    "sg:city":"Coalport",
    "sg:classifiers":[
        {
            "category":"Manufacturing",
            "subcategory":"Metals",
            "type":"Manufacturing & Wholesale Goods"
        }
    ],
    "sg:phone":"+1   ",
    "sg:postcode":"16627",
    "sg:province":"PA",
    "sg:tags":[
        "equipment",
        "heating",
        "mfg"
    ],
    "wof:name":"Control & Recorder Equipment",
    "wof:placetype":"venue"
},
  "geometry": {"coordinates":[-78.448307,40.783202],"type":"Point"}
}