{
  "type": "Feature",
  "properties": {
    "iso:country":"US",
    "sg:address":"511 E Drinker St",
    "sg:city":"Dunmore",
    "sg:classifiers":[
        {
            "category":"Organizations",
            "subcategory":"Religious Organization",
            "type":"Services"
        }
    ],
    "sg:phone":"+1 570 961 9167",
    "sg:postcode":"18512",
    "sg:province":"PA",
    "sg:tags":[
        "church"
    ],
    "wof:name":"St Michael's Byzantine Rite",
    "wof:placetype":"venue"
},
  "geometry": {"coordinates":[-75.622911,41.420409],"type":"Point"}
}