{
  "type": "Feature",
  "properties": {
    "addr:full":"85 Tomlinson Rd Huntingdon Vly PA 19006",
    "addr:housenumber":"85",
    "addr:postcode":"19006",
    "addr:street":"Tomlinson Rd",
    "iso:country":"US",
    "sg:address":"85 Tomlinson Rd",
    "sg:city":"Huntingdon Vly",
    "sg:classifiers":[
        {
            "category":"Shopping",
            "subcategory":"Computers & Home Electronics",
            "type":"Retail Goods"
        }
    ],
    "sg:phone":"+1 215 947 9211",
    "sg:postcode":"19006",
    "sg:province":"PA",
    "sg:tags":[
        "equipment",
        "electronic",
        "supply"
    ],
    "wof:name":"Electronic Recovery",
    "wof:placetype":"venue"
},
  "geometry": {"coordinates":[-75.040522,40.121786],"type":"Point"}
}