{
  "type": "Feature",
  "properties": {
    "iso:country":"US",
    "sg:address":"986 E Governor Rd",
    "sg:city":"Hershey",
    "sg:classifiers":[
        {
            "category":"Organizations",
            "subcategory":"Religious Organization",
            "type":"Services"
        }
    ],
    "sg:phone":"+1 717 534 2010",
    "sg:postcode":"17033",
    "sg:province":"PA",
    "sg:tags":[
        "church"
    ],
    "sg:website":"www.hersheynazarene.org",
    "wof:name":"Hershey Church Of The Nazarene",
    "wof:placetype":"venue"
},
  "geometry": {"coordinates":[-76.602599,40.27718],"type":"Point"}
}