{
  "type": "Feature",
  "properties": {
    "addr:full":"9560 Fox Rd Pittsburgh PA 15237",
    "addr:housenumber":"9560",
    "addr:postcode":"15237",
    "addr:street":"Fox Rd",
    "iso:country":"US",
    "sg:address":"9560 Fox Rd",
    "sg:city":"Pittsburgh",
    "sg:classifiers":[
        {
            "category":"Building & Trades",
            "subcategory":"Construction",
            "type":"Services"
        }
    ],
    "sg:phone":"+1   ",
    "sg:postcode":"15237",
    "sg:province":"PA",
    "sg:tags":[
        "house"
    ],
    "wof:name":"Mullinary Contracting",
    "wof:placetype":"venue"
},
  "geometry": {"coordinates":[-80.050361,40.581434],"type":"Point"}
}