{
  "type": "Feature",
  "properties": {
    "addr:full":"126 Market St Kittanning PA 16201",
    "addr:housenumber":"126",
    "addr:postcode":"16201",
    "addr:street":"Market St",
    "iso:country":"US",
    "sg:address":"126 Market St",
    "sg:city":"Kittanning",
    "sg:classifiers":[
        {
            "category":"Personal",
            "subcategory":"Beauty Salon",
            "type":"Services"
        }
    ],
    "sg:phone":"+1 724 545 7871",
    "sg:postcode":"16201",
    "sg:province":"PA",
    "wof:name":"Head To Toe",
    "wof:placetype":"venue"
},
  "geometry": {"coordinates":[-79.519762,40.814087],"type":"Point"}
}