{
  "type": "Feature",
  "properties": {
    "iso:country":"US",
    "sg:address":"1216 Jacobsburg Rd",
    "sg:city":"Wind Gap",
    "sg:classifiers":[
        {
            "category":"Shopping",
            "subcategory":"Hobbies, Toys, & Games",
            "type":"Retail Goods"
        }
    ],
    "sg:phone":"+1   ",
    "sg:postcode":"18091",
    "sg:province":"PA",
    "wof:name":"Elaines Ceramics",
    "wof:placetype":"venue"
},
  "geometry": {"coordinates":[-75.3027,40.814247],"type":"Point"}
}