{
  "type": "Feature",
  "properties": {
    "iso:country":"US",
    "sg:address":"357 N 60th St",
    "sg:city":"Philadelphia",
    "sg:classifiers":[
        {
            "category":"Travel",
            "subcategory":"Campground",
            "type":"Entertainment"
        }
    ],
    "sg:phone":"+1   ",
    "sg:postcode":"19139",
    "sg:province":"PA",
    "sg:tags":[
        "camp"
    ],
    "wof:name":"Camp Summerlove",
    "wof:placetype":"venue"
},
  "geometry": {"coordinates":[-75.239542,39.967217],"type":"Point"}
}