{
  "type": "Feature",
  "properties": {
    "addr:full":"321 Hunt Valley Rd New Kensington PA 15068",
    "addr:housenumber":"321",
    "addr:postcode":"15068",
    "addr:street":"Hunt Valley Rd",
    "iso:country":"US",
    "sg:address":"321 Hunt Valley Rd",
    "sg:city":"New Kensington",
    "sg:classifiers":[
        {
            "category":"Manufacturing",
            "subcategory":"Tools & Machinery",
            "type":"Manufacturing & Wholesale Goods"
        }
    ],
    "sg:phone":"+1 724 335 9702",
    "sg:postcode":"15068",
    "sg:province":"PA",
    "sg:tags":[
        "machine",
        "shop"
    ],
    "wof:name":"A-F N Machine Technology Inc",
    "wof:placetype":"venue"
},
  "geometry": {"coordinates":[-79.642797,40.535832],"type":"Point"}
}