{
  "type": "Feature",
  "properties": {
    "addr:full":"40 Crest Ave Malvern PA 19355",
    "addr:housenumber":"40",
    "addr:postcode":"19355",
    "addr:street":"Crest Ave",
    "iso:country":"US",
    "sg:address":"40 Crest Ave",
    "sg:city":"Malvern",
    "sg:classifiers":[
        {
            "category":"Professional",
            "type":"Services"
        }
    ],
    "sg:phone":"+1   ",
    "sg:postcode":"19355",
    "sg:province":"PA",
    "wof:name":"Gratus LLC",
    "wof:placetype":"venue"
},
  "geometry": {"coordinates":[-75.52085700000001,40.03167],"type":"Point"}
}