{
  "type": "Feature",
  "properties": {
    "iso:country":"US",
    "sg:address":"20 E State St",
    "sg:city":"Doylestown",
    "sg:classifiers":[
        {
            "category":"Cinema",
            "subcategory":"Movie Theater",
            "type":"Entertainment"
        }
    ],
    "sg:phone":"+1 215 345 6789",
    "sg:postcode":"18901",
    "sg:province":"PA",
    "sg:tags":[
        "motion",
        "picture"
    ],
    "wof:name":"County Theater",
    "wof:placetype":"venue"
},
  "geometry": {"coordinates":[-75.13009599999999,40.310001],"type":"Point"}
}