{
  "type": "Feature",
  "properties": {
    "iso:country":"US",
    "sg:address":"302 E Brown St",
    "sg:city":"East Stroudsburg",
    "sg:classifiers":[
        {
            "category":"Health Services",
            "subcategory":"Health Practitioner",
            "type":"Services"
        }
    ],
    "sg:phone":"+1 570 420 8888",
    "sg:postcode":"18301",
    "sg:province":"PA",
    "sg:tags":[
        "therapist",
        "physical"
    ],
    "wof:name":"Laurie B Samet Physical Thrpy",
    "wof:placetype":"venue"
},
  "geometry": {"coordinates":[-75.168119,40.9952],"type":"Point"}
}