{
  "type": "Feature",
  "properties": {
    "iso:country":"US",
    "sg:address":"102 Meyers Ave",
    "sg:city":"Meyersdale",
    "sg:classifiers":[
        {
            "category":"Professional",
            "subcategory":"Advertising",
            "type":"Services"
        },
        {
            "category":"Professional",
            "subcategory":"Printing & Photocopies",
            "type":"Services"
        }
    ],
    "sg:phone":"+1 814 634 9245",
    "sg:postcode":"15552",
    "sg:province":"PA",
    "sg:tags":[
        "distributing",
        "sample",
        "screen",
        "service-circular"
    ],
    "sg:website":"http://www.apexplasticinc.com",
    "wof:name":"Apex Screen Printing & Embroidery Inc",
    "wof:placetype":"venue"
},
  "geometry": {"coordinates":[-79.025097,39.813451],"type":"Point"}
}