{
  "type": "Feature",
  "properties": {
    "addr:full":"2813 W Diamond St Philadelphia PA 19121",
    "addr:housenumber":"2813",
    "addr:postcode":"19121",
    "addr:street":"W Diamond St",
    "iso:country":"US",
    "sg:address":"2813 W Diamond St",
    "sg:city":"Philadelphia",
    "sg:classifiers":[
        {
            "category":"Health Services",
            "subcategory":"Clinic",
            "type":"Services"
        }
    ],
    "sg:phone":"+1   ",
    "sg:postcode":"19121",
    "sg:province":"PA",
    "sg:tags":[
        "medical",
        "specialty",
        "outpatient"
    ],
    "wof:name":"Family Health Center",
    "wof:placetype":"venue"
},
  "geometry": {"coordinates":[-75.178969,39.987612],"type":"Point"}
}