{
  "type": "Feature",
  "properties": {
    "iso:country":"US",
    "sg:address":"170 Clear Spring Rd",
    "sg:city":"Annville",
    "sg:classifiers":[
        {
            "category":"Home & Garden",
            "subcategory":"Furniture",
            "type":"Retail Goods"
        }
    ],
    "sg:phone":"+1   ",
    "sg:postcode":"17003",
    "sg:province":"PA",
    "sg:tags":[
        "custom",
        "work",
        "cabinet"
    ],
    "wof:name":"Simply Wood Inc",
    "wof:placetype":"venue"
},
  "geometry": {"coordinates":[-76.54438,40.347636],"type":"Point"}
}