{
  "type": "Feature",
  "properties": {
    "iso:country":"US",
    "sg:address":"664 Graham Station Rd",
    "sg:city":"Philipsburg",
    "sg:classifiers":[
        {
            "category":"Manufacturing",
            "subcategory":"Chemicals & Compounds",
            "type":"Manufacturing & Wholesale Goods"
        }
    ],
    "sg:phone":"+1 814 342 0782",
    "sg:postcode":"16866",
    "sg:province":"PA",
    "sg:tags":[
        "explosive"
    ],
    "sg:website":"http://www.douglasdrillservices.com",
    "wof:name":"Douglas Explosives, Inc",
    "wof:placetype":"venue"
},
  "geometry": {"coordinates":[-78.248714,40.921157],"type":"Point"}
}