{
  "type": "Feature",
  "properties": {
    "iso:country":"US",
    "sg:address":"115 S Rebecca Ave",
    "sg:city":"Scranton",
    "sg:classifiers":[
        {
            "category":"Professional",
            "subcategory":"Accounting & Tax Preparation",
            "type":"Services"
        }
    ],
    "sg:phone":"+1 570 346 4045",
    "sg:postcode":"18504",
    "sg:province":"PA",
    "sg:tags":[
        "accountant"
    ],
    "wof:name":"William J Moran CPA",
    "wof:placetype":"venue"
},
  "geometry": {"coordinates":[-75.686977,41.413506],"type":"Point"}
}