{
  "type": "Feature",
  "properties": {
    "iso:country":"US",
    "sg:address":"249 Forsythe Rd",
    "sg:city":"Valencia",
    "sg:classifiers":[
        {
            "category":"Professional",
            "subcategory":"Detective & Security Services",
            "type":"Services"
        }
    ],
    "sg:phone":"+1 724 898 2883",
    "sg:postcode":"16059",
    "sg:province":"PA",
    "sg:tags":[
        "information",
        "bureau"
    ],
    "wof:name":"Boron Specialties",
    "wof:placetype":"venue"
},
  "geometry": {"coordinates":[-79.942267,40.715035],"type":"Point"}
}