{
  "type": "Feature",
  "properties": {
    "iso:country":"US",
    "sg:address":"111 N 49th St",
    "sg:city":"Philadelphia",
    "sg:classifiers":[
        {
            "category":"Health Services",
            "subcategory":"Clinic",
            "type":"Services"
        },
        {
            "category":"Health Services",
            "subcategory":"Health Practitioner",
            "type":"Services"
        }
    ],
    "sg:phone":"+1 215 471 2600",
    "sg:postcode":"19139",
    "sg:province":"PA",
    "sg:tags":[
        "information",
        "drug",
        "abuse",
        "treatment",
        "addiction",
        "alcoholism"
    ],
    "sg:website":"http://www.kirkbridecenter.com",
    "wof:name":"Kickbride Center",
    "wof:placetype":"venue"
},
  "geometry": {"coordinates":[-75.219448,39.961109],"type":"Point"}
}