{
  "type": "Feature",
  "properties": {
    "iso:country":"US",
    "sg:address":"11 Kings Blvd",
    "sg:city":"Reading",
    "sg:classifiers":[
        {
            "category":"Building & Trades",
            "subcategory":"Construction",
            "type":"Services"
        }
    ],
    "sg:phone":"+1 610 777 6644",
    "sg:postcode":"19607",
    "sg:province":"PA",
    "sg:tags":[
        "house"
    ],
    "wof:name":"Remp Construction",
    "wof:placetype":"venue"
},
  "geometry": {"coordinates":[-75.96199,40.300215],"type":"Point"}
}