{
  "type": "Feature",
  "properties": {
    "addr:full":"322 S Hanover St Carlisle PA 17013",
    "addr:housenumber":"322",
    "addr:postcode":"17013",
    "addr:street":"S Hanover St",
    "iso:country":"US",
    "sg:address":"322 S Hanover St",
    "sg:city":"Carlisle",
    "sg:classifiers":[
        {
            "category":"Home & Garden",
            "subcategory":"Mobile Homes",
            "type":"Retail Goods"
        }
    ],
    "sg:phone":"+1   ",
    "sg:postcode":"17013",
    "sg:province":"PA",
    "wof:name":"Carlisle Mobile Homes Inc",
    "wof:placetype":"venue"
},
  "geometry": {"coordinates":[-77.18993,40.196361],"type":"Point"}
}