{
  "type": "Feature",
  "properties": {
    "addr:full":"4146 Glades Pike Somerset PA 15501",
    "addr:housenumber":"4146",
    "addr:postcode":"15501",
    "addr:street":"Glades Pike",
    "iso:country":"US",
    "sg:address":"4146 Glades Pike",
    "sg:city":"Somerset",
    "sg:classifiers":[
        {
            "category":"Home & Garden",
            "subcategory":"Furniture",
            "type":"Retail Goods"
        },
        {
            "category":"Shopping",
            "subcategory":"Clothing, Apparel, & Fashions",
            "type":"Retail Goods"
        }
    ],
    "sg:phone":"+1 814 445 8182",
    "sg:postcode":"15501",
    "sg:province":"PA",
    "sg:tags":[
        "shop",
        "barber",
        "wear",
        "beauty"
    ],
    "wof:name":"Gary's Styling Boutique",
    "wof:placetype":"venue"
},
  "geometry": {"coordinates":[-79.107359,40.010142],"type":"Point"}
}