{
  "type": "Feature",
  "properties": {
    "iso:country":"US",
    "sg:address":"1650 Harlansburg Rd",
    "sg:city":"New Castle",
    "sg:classifiers":[
        {
            "category":"Home & Garden",
            "subcategory":"Mobile Homes",
            "type":"Retail Goods"
        }
    ],
    "sg:phone":"+1 724 658 1000",
    "sg:postcode":"16101",
    "sg:province":"PA",
    "sg:website":"www.gaslighthomesales.com",
    "wof:name":"Gas Light Sales",
    "wof:placetype":"venue"
},
  "geometry": {"coordinates":[-80.30996500000001,41.011066],"type":"Point"}
}