{
  "type": "Feature",
  "properties": {
    "addr:full":"528 Main St Rimersburg PA 16248",
    "addr:housenumber":"528",
    "addr:postcode":"16248",
    "addr:street":"Main St",
    "iso:country":"US",
    "sg:address":"528 Main St",
    "sg:city":"Rimersburg",
    "sg:classifiers":[
        {
            "category":"Restaurant",
            "type":"Food & Drink"
        }
    ],
    "sg:menulink":"http://www.allmenus.com/pa/rimersburg/133427-subway/menu/",
    "sg:phone":"+1 814 473 3166",
    "sg:postcode":"16248",
    "sg:province":"PA",
    "sg:tags":[
        "american",
        "sandwich"
    ],
    "wof:name":"Subway",
    "wof:placetype":"venue"
},
  "geometry": {"coordinates":[-79.50288,41.041202],"type":"Point"}
}