{
  "type": "Feature",
  "properties": {
    "iso:country":"US",
    "sg:address":"5 Vera Ln",
    "sg:city":"Conshohocken",
    "sg:classifiers":[
        {
            "category":"Wholesale",
            "subcategory":"Non-durable Goods",
            "type":"Manufacturing & Wholesale Goods"
        }
    ],
    "sg:phone":"+1   ",
    "sg:postcode":"19428",
    "sg:province":"PA",
    "sg:tags":[
        "advertising",
        "specialty"
    ],
    "wof:name":"Advantage Group",
    "wof:placetype":"venue"
},
  "geometry": {"coordinates":[-75.28319999999999,40.086797],"type":"Point"}
}