{
  "type": "Feature",
  "properties": {
    "iso:country":"US",
    "sg:address":"5731 Canoe Ripple Rd",
    "sg:city":"Knox",
    "sg:classifiers":[
        {
            "category":"Autos & Motor Vehicles",
            "subcategory":"Automobile Sales",
            "type":"Retail Goods"
        },
        {
            "category":"Retail",
            "subcategory":"Auto Repair",
            "type":"Services"
        }
    ],
    "sg:phone":"+1 814 797 2902",
    "sg:postcode":"16232",
    "sg:province":"PA",
    "sg:tags":[
        "car",
        "general",
        "dealer",
        "supply"
    ],
    "wof:name":"G W Dollar Used Auto & Garage",
    "wof:placetype":"venue"
},
  "geometry": {"coordinates":[-79.539576,41.178399],"type":"Point"}
}