{
  "type": "Feature",
  "properties": {
    "iso:country":"US",
    "sg:address":"2629 Brownsville Rd",
    "sg:city":"Pittsburgh",
    "sg:classifiers":[
        {
            "category":"Food & Beverages",
            "subcategory":"Liquor & Beverages",
            "type":"Retail Goods"
        }
    ],
    "sg:phone":"+1 412 886 2003",
    "sg:postcode":"15227",
    "sg:province":"PA",
    "wof:name":"Carrick Liquor Store",
    "wof:placetype":"venue"
},
  "geometry": {"coordinates":[-79.977873,40.384626],"type":"Point"}
}