{
  "type": "Feature",
  "properties": {
    "iso:country":"US",
    "sg:address":"445 E Main St",
    "sg:city":"Birdsboro",
    "sg:classifiers":[
        {
            "category":"Organizations",
            "subcategory":"Community Association",
            "type":"Services"
        }
    ],
    "sg:phone":"+1 610 378 5500",
    "sg:postcode":"19508",
    "sg:province":"PA",
    "sg:tags":[
        "military"
    ],
    "wof:name":"Birdsboro American Legion Comm",
    "wof:placetype":"venue"
},
  "geometry": {"coordinates":[-75.803,40.266532],"type":"Point"}
}