{
  "type": "Feature",
  "properties": {
    "iso:country":"US",
    "sg:address":"865 Berkshire Blvd",
    "sg:city":"Reading",
    "sg:classifiers":[
        {
            "category":"Social Services",
            "subcategory":"Child Care",
            "type":"Services"
        },
        {
            "category":"Education",
            "subcategory":"Preschool",
            "type":"Public Place"
        }
    ],
    "sg:phone":"+1 610 376 6152",
    "sg:postcode":"19610",
    "sg:province":"PA",
    "sg:tags":[
        "kindergarten",
        "nursery",
        "day"
    ],
    "sg:website":"http://www.kindercare.com/our-centers/center-details/303023/?cid=YP_KC303023",
    "wof:name":"KinderCare Learning Center",
    "wof:placetype":"venue"
},
  "geometry": {"coordinates":[-75.96910699999999,40.349606],"type":"Point"}
}