{
  "type": "Feature",
  "properties": {
    "iso:country":"US",
    "sg:address":"2229 Paxton Church Rd",
    "sg:city":"Harrisburg",
    "sg:classifiers":[
        {
            "category":"Professional",
            "subcategory":"Management & Consulting",
            "type":"Services"
        }
    ],
    "sg:phone":"+1   ",
    "sg:postcode":"17110",
    "sg:province":"PA",
    "sg:tags":[
        "medical",
        "specialized"
    ],
    "wof:name":"Vrs",
    "wof:placetype":"venue"
},
  "geometry": {"coordinates":[-76.85593799999999,40.31512],"type":"Point"}
}