{
  "type": "Feature",
  "properties": {
    "iso:country":"US",
    "sg:address":"915 Rockland St",
    "sg:city":"Bethlehem",
    "sg:classifiers":[
        {
            "category":"Professional",
            "type":"Services"
        }
    ],
    "sg:phone":"+1   ",
    "sg:postcode":"18017",
    "sg:province":"PA",
    "wof:name":"KB K9 Care",
    "wof:placetype":"venue"
},
  "geometry": {"coordinates":[-75.35574699999999,40.633879],"type":"Point"}
}