{
  "type": "Feature",
  "properties": {
    "iso:country":"US",
    "sg:address":"1961 E Street Rd",
    "sg:city":"Bensalem",
    "sg:classifiers":[
        {
            "category":"Building & Trades",
            "subcategory":"Equipment Rental",
            "type":"Services"
        }
    ],
    "sg:phone":"+1 215 638 4333",
    "sg:postcode":"19020",
    "sg:province":"PA",
    "wof:name":"Rent-A-Center",
    "wof:placetype":"venue"
},
  "geometry": {"coordinates":[-74.945857,40.097181],"type":"Point"}
}