{
  "type": "Feature",
  "properties": {
    "addr:full":"115 E Main St Mount Joy PA 17552",
    "addr:housenumber":"115",
    "addr:postcode":"17552",
    "addr:street":"E Main St",
    "iso:country":"US",
    "sg:address":"115 E Main St",
    "sg:city":"Mount Joy",
    "sg:classifiers":[
        {
            "category":"Organizations",
            "subcategory":"Professional Association",
            "type":"Services"
        }
    ],
    "sg:phone":"+1   ",
    "sg:postcode":"17552",
    "sg:province":"PA",
    "sg:tags":[
        "business"
    ],
    "wof:name":"Main Street Mount Joy",
    "wof:placetype":"venue"
},
  "geometry": {"coordinates":[-76.49751500000001,40.109264],"type":"Point"}
}