{
  "type": "Feature",
  "properties": {
    "addr:full":"29 Kerry Ln Malvern PA 19355",
    "addr:housenumber":"29",
    "addr:postcode":"19355",
    "addr:street":"Kerry Ln",
    "iso:country":"US",
    "sg:address":"29 Kerry Ln",
    "sg:city":"Malvern",
    "sg:classifiers":[
        {
            "category":"Professional",
            "type":"Services"
        }
    ],
    "sg:phone":"+1 610 651 0346",
    "sg:postcode":"19355",
    "sg:province":"PA",
    "wof:name":"Sirius Satellite Inc",
    "wof:placetype":"venue"
},
  "geometry": {"coordinates":[-75.52992500000001,40.035692],"type":"Point"}
}