{
  "type": "Feature",
  "properties": {
    "iso:country":"US",
    "sg:address":"121 Paper Mill Rd",
    "sg:city":"Bloomsburg",
    "sg:classifiers":[
        {
            "category":"Professional",
            "subcategory":"Business Services",
            "type":"Services"
        }
    ],
    "sg:phone":"+1   ",
    "sg:postcode":"17815",
    "sg:province":"PA",
    "wof:name":"Tourist Information",
    "wof:placetype":"venue"
},
  "geometry": {"coordinates":[-76.425274,41.033457],"type":"Point"}
}