{
  "type": "Feature",
  "properties": {
    "addr:full":"6028 6th Ave Altoona PA 16602",
    "addr:housenumber":"6028",
    "addr:postcode":"16602",
    "addr:street":"6Th Ave",
    "iso:country":"US",
    "sg:address":"6028 6th Ave",
    "sg:city":"Altoona",
    "sg:classifiers":[
        {
            "category":"Autos & Motor Vehicles",
            "subcategory":"Motorcycle Sales",
            "type":"Retail Goods"
        }
    ],
    "sg:phone":"+1   ",
    "sg:postcode":"16602",
    "sg:province":"PA",
    "wof:name":"Saylor Honda Sea Doo",
    "wof:placetype":"venue"
},
  "geometry": {"coordinates":[-78.425893,40.469604],"type":"Point"}
}