{
  "type": "Feature",
  "properties": {
    "addr:full":"150 Wadham St Plymouth PA 18651",
    "addr:housenumber":"150",
    "addr:postcode":"18651",
    "addr:street":"Wadham St",
    "iso:country":"US",
    "sg:address":"150 Wadham St",
    "sg:city":"Plymouth",
    "sg:classifiers":[
        {
            "category":"Professional",
            "subcategory":"Management & Consulting",
            "type":"Services"
        }
    ],
    "sg:phone":"+1 570 779 0735",
    "sg:postcode":"18651",
    "sg:province":"PA",
    "sg:tags":[
        "business"
    ],
    "wof:name":"Aramark",
    "wof:placetype":"venue"
},
  "geometry": {"coordinates":[-75.94828699999999,41.240252],"type":"Point"}
}