{
  "type": "Feature",
  "properties": {
    "addr:full":"107 N 2nd Ave Elizabeth PA 15037",
    "addr:housenumber":"107",
    "addr:postcode":"15037",
    "addr:street":"N 2Nd Ave",
    "iso:country":"US",
    "sg:address":"107 N 2nd Ave",
    "sg:city":"Elizabeth",
    "sg:classifiers":[
        {
            "category":"Utilities",
            "type":"Services"
        },
        {
            "category":"Professional",
            "subcategory":"Computer Services",
            "type":"Services"
        }
    ],
    "sg:phone":"+1 412 384 4993",
    "sg:postcode":"15037",
    "sg:province":"PA",
    "sg:tags":[
        "repair",
        "provider",
        "internet"
    ],
    "wof:name":"Rsr Technical Training & Consulting",
    "wof:placetype":"venue"
},
  "geometry": {"coordinates":[-79.886703,40.2729],"type":"Point"}
}