{
  "type": "Feature",
  "properties": {
    "addr:full":"19 N Main St Greensburg PA 15601",
    "addr:housenumber":"19",
    "addr:postcode":"15601",
    "addr:street":"N Main St",
    "iso:country":"US",
    "sg:address":"19 N Main St",
    "sg:city":"Greensburg",
    "sg:classifiers":[
        {
            "category":"Banks & Credit Unions",
            "subcategory":"Bank",
            "type":"Services"
        }
    ],
    "sg:phone":"+1 724 836 7699",
    "sg:postcode":"15601",
    "sg:province":"PA",
    "sg:tags":[
        "national",
        "commercial"
    ],
    "sg:website":"www.cbthebank.com",
    "wof:name":"Commercial National Bank",
    "wof:placetype":"venue"
},
  "geometry": {"coordinates":[-79.54458700000001,40.30366],"type":"Point"}
}