{
  "type": "Feature",
  "properties": {
    "addr:full":"2049 S Philip St Philadelphia PA 19148",
    "addr:housenumber":"2049",
    "addr:postcode":"19148",
    "addr:street":"S Philip St",
    "iso:country":"US",
    "sg:address":"2049 S Philip St",
    "sg:city":"Philadelphia",
    "sg:classifiers":[
        {
            "category":"Building & Trades",
            "subcategory":"Pest Control",
            "type":"Services"
        }
    ],
    "sg:phone":"+1 215 551 7180",
    "sg:postcode":"19148",
    "sg:province":"PA",
    "wof:name":"Swift Pest Control",
    "wof:placetype":"venue"
},
  "geometry": {"coordinates":[-75.150295,39.922454],"type":"Point"}
}