{
  "type": "Feature",
  "properties": {
    "addr:full":"675 Percy St Williamsport PA 17702",
    "addr:housenumber":"675",
    "addr:postcode":"17702",
    "addr:street":"Percy St",
    "iso:country":"US",
    "sg:address":"675 Percy St",
    "sg:city":"Williamsport",
    "sg:classifiers":[
        {
            "category":"Manufacturing",
            "subcategory":"Tools & Machinery",
            "type":"Manufacturing & Wholesale Goods"
        }
    ],
    "sg:phone":"+1   ",
    "sg:postcode":"17702",
    "sg:province":"PA",
    "sg:tags":[
        "fire",
        "detection",
        "mfg",
        "equipment"
    ],
    "wof:name":"Ansul Incorporated",
    "wof:placetype":"venue"
},
  "geometry": {"coordinates":[-76.995766,41.227374],"type":"Point"}
}