{
  "type": "Feature",
  "properties": {
    "iso:country":"US",
    "sg:address":"4026 Monroeville Blvd",
    "sg:city":"Monroeville",
    "sg:classifiers":[
        {
            "category":"Retail",
            "subcategory":"Laundry & Dry Cleaning",
            "type":"Services"
        }
    ],
    "sg:phone":"+1   ",
    "sg:postcode":"15146",
    "sg:province":"PA",
    "sg:tags":[
        "garment",
        "agent"
    ],
    "wof:name":"Tom Clemens",
    "wof:placetype":"venue"
},
  "geometry": {"coordinates":[-79.770661,40.435557],"type":"Point"}
}