{
  "type": "Feature",
  "properties": {
    "iso:country":"US",
    "sg:address":"1941 Debbie Dr",
    "sg:city":"York",
    "sg:classifiers":[
        {
            "category":"Building & Trades",
            "subcategory":"Construction",
            "type":"Services"
        }
    ],
    "sg:phone":"+1   ",
    "sg:postcode":"17403",
    "sg:province":"PA",
    "sg:tags":[
        "house"
    ],
    "wof:name":"Reed Construction Inc",
    "wof:placetype":"venue"
},
  "geometry": {"coordinates":[-76.686677,39.946198],"type":"Point"}
}