{
  "type": "Feature",
  "properties": {
    "iso:country":"US",
    "sg:address":"111 South St",
    "sg:city":"Lehighton",
    "sg:classifiers":[
        {
            "category":"Restaurant",
            "type":"Food & Drink"
        },
        {
            "category":"Retail",
            "subcategory":"Animal Services",
            "type":"Services"
        }
    ],
    "sg:phone":"+1 610 377 2500",
    "sg:postcode":"18235",
    "sg:province":"PA",
    "sg:tags":[
        "pet",
        "eating",
        "grooming",
        "washing",
        "merchandise"
    ],
    "wof:name":"Trudy's Pooch Parlor",
    "wof:placetype":"venue"
},
  "geometry": {"coordinates":[-75.708961,40.83397],"type":"Point"}
}