{
  "type": "Feature",
  "properties": {
    "iso:country":"US",
    "sg:address":"125 Main St Ste 1",
    "sg:city":"Luzerne",
    "sg:classifiers":[
        {
            "category":"Home & Garden",
            "subcategory":"Home Furnishings",
            "type":"Retail Goods"
        },
        {
            "category":"Home & Garden",
            "subcategory":"Carpets & Floor Coverings",
            "type":"Retail Goods"
        }
    ],
    "sg:phone":"+1 570 283 5667",
    "sg:postcode":"18709",
    "sg:province":"PA",
    "sg:tags":[
        "draperies",
        "flooring",
        "material",
        "contractor",
        "window",
        "treatment",
        "curtain"
    ],
    "wof:name":"Nu-Floors",
    "wof:placetype":"venue"
},
  "geometry": {"coordinates":[-75.89549100000001,41.283598],"type":"Point"}
}