{
  "type": "Feature",
  "properties": {
    "iso:country":"US",
    "sg:address":"5 Natrona St",
    "sg:city":"Natrona Heights",
    "sg:classifiers":[
        {
            "category":"Retail",
            "subcategory":"Repair Shop",
            "type":"Services"
        }
    ],
    "sg:phone":"+1 724 224 1073",
    "sg:postcode":"15065",
    "sg:province":"PA",
    "sg:tags":[
        "welding"
    ],
    "wof:name":"Integrity Welding",
    "wof:placetype":"venue"
},
  "geometry": {"coordinates":[-79.724082,40.61633],"type":"Point"}
}