{
  "type": "Feature",
  "properties": {
    "iso:country":"US",
    "sg:address":"3293 Lincoln Hwy E",
    "sg:city":"Paradise",
    "sg:classifiers":[
        {
            "category":"Education",
            "subcategory":"School",
            "type":"Public Place"
        }
    ],
    "sg:phone":"+1 717 768 5560",
    "sg:postcode":"17562",
    "sg:province":"PA",
    "wof:name":"Paradise Elementary School",
    "wof:placetype":"venue"
},
  "geometry": {"coordinates":[-76.107682,40.005452],"type":"Point"}
}