{
  "type": "Feature",
  "properties": {
    "iso:country":"US",
    "sg:address":"141 Brown Rd",
    "sg:city":"Pittston",
    "sg:classifiers":[
        {
            "category":"Utilities",
            "subcategory":"Refuse",
            "type":"Services"
        }
    ],
    "sg:phone":"+1 570 341 7751",
    "sg:postcode":"18640",
    "sg:province":"PA",
    "sg:tags":[
        "garbage",
        "collection"
    ],
    "sg:website":"www.ert.com",
    "wof:name":"ERT Group",
    "wof:placetype":"venue"
},
  "geometry": {"coordinates":[-75.774531,41.305381],"type":"Point"}
}