{
  "type": "Feature",
  "properties": {
    "iso:country":"US",
    "sg:address":"1194 Collegeville Rd",
    "sg:city":"Collegeville",
    "sg:classifiers":[
        {
            "category":"Retail",
            "subcategory":"Auto Repair",
            "type":"Services"
        }
    ],
    "sg:phone":"+1 610 222 0233",
    "sg:postcode":"19426",
    "sg:province":"PA",
    "wof:name":"Last Chance Auto",
    "wof:placetype":"venue"
},
  "geometry": {"coordinates":[-75.404297,40.218201],"type":"Point"}
}