{
  "type": "Feature",
  "properties": {
    "addr:full":"623 Hannah St Houtzdale PA 16651",
    "addr:housenumber":"623",
    "addr:postcode":"16651",
    "addr:street":"Hannah St",
    "iso:country":"US",
    "sg:address":"623 Hannah St",
    "sg:city":"Houtzdale",
    "sg:classifiers":[
        {
            "category":"Social Services",
            "type":"Services"
        }
    ],
    "sg:phone":"+1 814 378 6217",
    "sg:postcode":"16651",
    "sg:province":"PA",
    "sg:tags":[
        "organization",
        "welfare"
    ],
    "wof:name":"Wic Program",
    "wof:placetype":"venue"
},
  "geometry": {"coordinates":[-78.35138600000001,40.824965],"type":"Point"}
}