{
  "type": "Feature",
  "properties": {
    "iso:country":"US",
    "sg:address":"1405 N Cedar Crest Blvd Ste 104",
    "sg:city":"Allentown",
    "sg:classifiers":[
        {
            "category":"Professional",
            "subcategory":"Employment Agencies",
            "type":"Services"
        }
    ],
    "sg:phone":"+1 610 776 0760",
    "sg:postcode":"18104",
    "sg:province":"PA",
    "wof:name":"Virtual Staffing Inc",
    "wof:placetype":"venue"
},
  "geometry": {"coordinates":[-75.531998,40.6105],"type":"Point"}
}