{
  "type": "Feature",
  "properties": {
    "addr:full":"228 E Street Rd Warminster PA 18974",
    "addr:housenumber":"228",
    "addr:postcode":"18974",
    "addr:street":"E Street Rd",
    "iso:country":"US",
    "sg:address":"228 E Street Rd",
    "sg:city":"Warminster",
    "sg:classifiers":[
        {
            "category":"Autos & Motor Vehicles",
            "subcategory":"Fuel & Gas Station",
            "type":"Retail Goods"
        }
    ],
    "sg:phone":"+1   ",
    "sg:postcode":"18974",
    "sg:province":"PA",
    "sg:tags":[
        "repair",
        "station",
        "gasoline",
        "general"
    ],
    "wof:name":"Sams Atlantic Service",
    "wof:placetype":"venue"
},
  "geometry": {"coordinates":[-75.08631200000001,40.198885],"type":"Point"}
}