{
  "type": "Feature",
  "properties": {
    "iso:country":"US",
    "sg:address":"1110 N Mountain Rd",
    "sg:city":"Harrisburg",
    "sg:classifiers":[
        {
            "category":"Professional",
            "subcategory":"Business Services",
            "type":"Services"
        }
    ],
    "sg:phone":"+1 717 541 1280",
    "sg:postcode":"17112",
    "sg:province":"PA",
    "wof:name":"Focussed Business Solutions",
    "wof:placetype":"venue"
},
  "geometry": {"coordinates":[-76.791566,40.338775],"type":"Point"}
}