{
  "type": "Feature",
  "properties": {
    "iso:country":"US",
    "sg:address":"258 Main St Ste B",
    "sg:city":"Bristol",
    "sg:classifiers":[
        {
            "category":"Personal",
            "subcategory":"Nail Salon",
            "type":"Services"
        }
    ],
    "sg:phone":"+1 215 949 2112",
    "sg:postcode":"19007",
    "sg:province":"PA",
    "wof:name":"Ultra Tech Hair & Nail Design",
    "wof:placetype":"venue"
},
  "geometry": {"coordinates":[-74.81590300000001,40.138302],"type":"Point"}
}