{
  "type": "Feature",
  "properties": {
    "iso:country":"US",
    "sg:address":"89 Schlouch Rd",
    "sg:city":"Mohnton",
    "sg:classifiers":[
        {
            "category":"Professional",
            "subcategory":"Business Services",
            "type":"Services"
        }
    ],
    "sg:phone":"+1   ",
    "sg:postcode":"19540",
    "sg:province":"PA",
    "wof:name":"Ruhl & Asociates",
    "wof:placetype":"venue"
},
  "geometry": {"coordinates":[-75.98021900000001,40.225667],"type":"Point"}
}