{
  "type": "Feature",
  "properties": {
    "iso:country":"US",
    "sg:address":"2186 Butler Logan Rd",
    "sg:city":"Tarentum",
    "sg:classifiers":[
        {
            "category":"Retail",
            "subcategory":"Auto Repair",
            "type":"Services"
        }
    ],
    "sg:phone":"+1 724 224 3170",
    "sg:postcode":"15084",
    "sg:province":"PA",
    "sg:tags":[
        "repairing",
        "automobile"
    ],
    "wof:name":"Casares Auto Repair & Svc",
    "wof:placetype":"venue"
},
  "geometry": {"coordinates":[-79.803658,40.580509],"type":"Point"}
}