{
  "type": "Feature",
  "properties": {
    "iso:country":"US",
    "sg:address":"105 Dorchester Ln",
    "sg:city":"Pottstown",
    "sg:classifiers":[
        {
            "category":"Health Services",
            "subcategory":"Doctor",
            "type":"Services"
        }
    ],
    "sg:phone":"+1 610 323 8346",
    "sg:postcode":"19465",
    "sg:province":"PA",
    "sg:tags":[
        "dentist"
    ],
    "wof:name":"Bernard Copelovitch DDS",
    "wof:placetype":"venue"
},
  "geometry": {"coordinates":[-75.652828,40.23606],"type":"Point"}
}