{
  "type": "Feature",
  "properties": {
    "iso:country":"US",
    "sg:address":"1634 Ashurst Rd",
    "sg:city":"Philadelphia",
    "sg:classifiers":[
        {
            "category":"Social Services",
            "type":"Services"
        }
    ],
    "sg:phone":"+1 215 878 6773",
    "sg:postcode":"19151",
    "sg:province":"PA",
    "sg:tags":[
        "gambling",
        "addiction-information",
        "treatment"
    ],
    "wof:name":"Millennium Foundation Inc",
    "wof:placetype":"venue"
},
  "geometry": {"coordinates":[-75.271536,39.972861],"type":"Point"}
}