{
  "type": "Feature",
  "properties": {
    "iso:country":"US",
    "sg:address":"101 York Rd",
    "sg:city":"Jenkintown",
    "sg:classifiers":[
        {
            "category":"Home & Garden",
            "subcategory":"Furniture",
            "type":"Retail Goods"
        }
    ],
    "sg:phone":"+1 215 886 4260",
    "sg:postcode":"19046",
    "sg:province":"PA",
    "sg:tags":[
        "store"
    ],
    "wof:name":"Bona Bon Furniture, Inc.",
    "wof:placetype":"venue"
},
  "geometry": {"coordinates":[-75.125443,40.092632],"type":"Point"}
}