{
  "type": "Feature",
  "properties": {
    "addr:full":"4256 Neptune St Erie PA 16506",
    "addr:housenumber":"4256",
    "addr:postcode":"16506",
    "addr:street":"Neptune St",
    "iso:country":"US",
    "sg:address":"4256 Neptune St",
    "sg:city":"Erie",
    "sg:classifiers":[
        {
            "category":"Restaurant",
            "type":"Food & Drink"
        }
    ],
    "sg:phone":"+1 814 833 1032",
    "sg:postcode":"16506",
    "sg:province":"PA",
    "sg:tags":[
        "management",
        "eating"
    ],
    "wof:name":"Raymond Management Company",
    "wof:placetype":"venue"
},
  "geometry": {"coordinates":[-80.163203,42.05896],"type":"Point"}
}