{
  "type": "Feature",
  "properties": {
    "addr:full":"205 Bellefonte Ave Lock Haven PA 17745",
    "addr:housenumber":"205",
    "addr:postcode":"17745",
    "addr:street":"Bellefonte Ave",
    "iso:country":"US",
    "sg:address":"205 Bellefonte Ave",
    "sg:city":"Lock Haven",
    "sg:classifiers":[
        {
            "category":"Restaurant",
            "type":"Food & Drink"
        }
    ],
    "sg:phone":"+1 570 748 9260",
    "sg:postcode":"17745",
    "sg:province":"PA",
    "wof:name":"Wendy's",
    "wof:placetype":"venue"
},
  "geometry": {"coordinates":[-77.45143,41.135558],"type":"Point"}
}