{
  "type": "Feature",
  "properties": {
    "iso:country":"US",
    "sg:address":"2637 Durham Rd",
    "sg:city":"Bristol",
    "sg:classifiers":[
        {
            "category":"Personal",
            "subcategory":"Nail Salon",
            "type":"Services"
        }
    ],
    "sg:phone":"+1 215 788 7272",
    "sg:postcode":"19007",
    "sg:province":"PA",
    "wof:name":"DO Nails II",
    "wof:placetype":"venue"
},
  "geometry": {"coordinates":[-74.882912,40.127238],"type":"Point"}
}