{
  "type": "Feature",
  "properties": {
    "iso:country":"US",
    "sg:address":"35 Wilson St",
    "sg:city":"Pittsburgh",
    "sg:classifiers":[
        {
            "category":"Social Services",
            "type":"Services"
        }
    ],
    "sg:phone":"+1   ",
    "sg:postcode":"15223",
    "sg:province":"PA",
    "wof:name":"Autism Advisory Board of",
    "wof:placetype":"venue"
},
  "geometry": {"coordinates":[-79.951769,40.503977],"type":"Point"}
}