{
  "type": "Feature",
  "properties": {
    "iso:country":"US",
    "sg:address":"1011 S 11th St",
    "sg:city":"Philadelphia",
    "sg:classifiers":[
        {
            "category":"Professional",
            "subcategory":"Art Services",
            "type":"Services"
        }
    ],
    "sg:phone":"+1 267 407 7531",
    "sg:postcode":"19147",
    "sg:province":"PA",
    "sg:tags":[
        "photographer"
    ],
    "sg:website":"www.foto-graphy.com/",
    "wof:name":"Evolution Photography",
    "wof:placetype":"venue"
},
  "geometry": {"coordinates":[-75.160983,39.937936],"type":"Point"}
}