{
  "type": "Feature",
  "properties": {
    "addr:full":"1322 Pine St Philadelphia PA 19107",
    "addr:housenumber":"1322",
    "addr:postcode":"19107",
    "addr:street":"Pine St",
    "iso:country":"US",
    "sg:address":"1322 Pine St",
    "sg:city":"Philadelphia",
    "sg:classifiers":[
        {
            "category":"Professional",
            "subcategory":"Accounting & Tax Preparation",
            "type":"Services"
        }
    ],
    "sg:phone":"+1 215 735 2739",
    "sg:postcode":"19107",
    "sg:province":"PA",
    "sg:tags":[
        "accountant"
    ],
    "wof:name":"Edward R Trybala",
    "wof:placetype":"venue"
},
  "geometry": {"coordinates":[-75.163251,39.945235],"type":"Point"}
}