{
  "type": "Feature",
  "properties": {
    "iso:country":"US",
    "sg:address":"12 N 60th St",
    "sg:city":"Philadelphia",
    "sg:classifiers":[
        {
            "category":"Bars & Pubs",
            "type":"Food & Drink"
        }
    ],
    "sg:phone":"+1   ",
    "sg:postcode":"19139",
    "sg:province":"PA",
    "sg:tags":[
        "drinking"
    ],
    "wof:name":"Johnny Dollars Players Lounge",
    "wof:placetype":"venue"
},
  "geometry": {"coordinates":[-75.240529,39.963384],"type":"Point"}
}