{
  "type": "Feature",
  "properties": {
    "iso:country":"US",
    "sg:address":"1111 US Hwy 22",
    "sg:city":"Dauphin",
    "sg:phone":"+1   ",
    "sg:postcode":"17018",
    "sg:province":"PA",
    "sg:tags":[
        "equipment",
        "commercial"
    ],
    "wof:name":"Keystone State Trucking Inc",
    "wof:placetype":"venue"
},
  "geometry": {"coordinates":[-76.973794,40.368249],"type":"Point"}
}