{
  "type": "Feature",
  "properties": {
    "addr:full":"221 E Street Rd Feastervl Trvs PA 19053",
    "addr:housenumber":"221",
    "addr:postcode":"19053",
    "addr:street":"E Street Rd",
    "iso:country":"US",
    "sg:address":"221 E Street Rd",
    "sg:city":"Feastervl Trvs",
    "sg:classifiers":[
        {
            "category":"Professional",
            "subcategory":"Employment Agencies",
            "type":"Services"
        }
    ],
    "sg:phone":"+1 215 355 6440",
    "sg:postcode":"19053",
    "sg:province":"PA",
    "sg:tags":[
        "consultant",
        "search",
        "executive"
    ],
    "wof:name":"Scott KANE Assoc Inc",
    "wof:placetype":"venue"
},
  "geometry": {"coordinates":[-75.00903700000001,40.154595],"type":"Point"}
}