{
  "type": "Feature",
  "properties": {
    "iso:country":"US",
    "sg:address":"2503 Wilmington Rd",
    "sg:city":"New Castle",
    "sg:classifiers":[
        {
            "category":"Bagels",
            "type":"Food & Drink"
        },
        {
            "category":"Coffee & Tea",
            "type":"Food & Drink"
        },
        {
            "category":"Food & Beverages",
            "subcategory":"Bakery",
            "type":"Retail Goods"
        },
        {
            "category":"Bakery",
            "type":"Food & Drink"
        },
        {
            "category":"Donuts",
            "type":"Food & Drink"
        }
    ],
    "sg:menulink":"http://www.allmenus.com/pa/neshannock/143763-dunkin-donuts/menu/",
    "sg:phone":"+1 724 652 2998",
    "sg:postcode":"16105",
    "sg:province":"PA",
    "sg:tags":[
        "coffee",
        "diner",
        "tea",
        "bakery",
        "bagel",
        "american",
        "pastry"
    ],
    "wof:name":"Dunkin' Donuts",
    "wof:placetype":"venue"
},
  "geometry": {"coordinates":[-80.35437,41.02961],"type":"Point"}
}