{
  "type": "Feature",
  "properties": {
    "addr:full":"4605 Irvine St Pittsburgh PA 15207",
    "addr:housenumber":"4605",
    "addr:postcode":"15207",
    "addr:street":"Irvine St",
    "iso:country":"US",
    "sg:address":"4605 Irvine St",
    "sg:city":"Pittsburgh",
    "sg:classifiers":[
        {
            "category":"Professional",
            "subcategory":"Printing & Photocopies",
            "type":"Services"
        }
    ],
    "sg:phone":"+1 412 521 8832",
    "sg:postcode":"15207",
    "sg:province":"PA",
    "sg:tags":[
        "photocopying",
        "commercial"
    ],
    "sg:website":"www.forwardlitho.com",
    "wof:name":"Forward Lithography",
    "wof:placetype":"venue"
},
  "geometry": {"coordinates":[-79.945302,40.41342],"type":"Point"}
}