{
  "type": "Feature",
  "properties": {
    "iso:country":"US",
    "sg:address":"4838 Old York Rd",
    "sg:city":"Philadelphia",
    "sg:classifiers":[
        {
            "category":"Health Services",
            "subcategory":"Medical Lab",
            "type":"Services"
        }
    ],
    "sg:phone":"+1 215 457 8799",
    "sg:postcode":"19141",
    "sg:province":"PA",
    "sg:tags":[
        "laboratory",
        "dental"
    ],
    "wof:name":"United Ceramic Dental Lab Inc",
    "wof:placetype":"venue"
},
  "geometry": {"coordinates":[-75.146716,40.026191],"type":"Point"}
}