{
  "type": "Feature",
  "properties": {
    "addr:full":"333 Maple Ave Pittsburgh PA 15218",
    "addr:housenumber":"333",
    "addr:postcode":"15218",
    "addr:street":"Maple Ave",
    "iso:country":"US",
    "sg:address":"333 Maple Ave",
    "sg:city":"Pittsburgh",
    "sg:classifiers":[
        {
            "category":"Health Services",
            "subcategory":"Doctor",
            "type":"Services"
        }
    ],
    "sg:phone":"+1   ",
    "sg:postcode":"15218",
    "sg:province":"PA",
    "sg:tags":[
        "medical"
    ],
    "wof:name":"Janice L Forster MD",
    "wof:placetype":"venue"
},
  "geometry": {"coordinates":[-79.881016,40.431826],"type":"Point"}
}