{
  "type": "Feature",
  "properties": {
    "iso:country":"US",
    "sg:address":"672 Sheffield Ave",
    "sg:city":"Aliquippa",
    "sg:classifiers":[
        {
            "category":"Home & Garden",
            "subcategory":"Building Materials",
            "type":"Retail Goods"
        }
    ],
    "sg:phone":"+1 724 378 4078",
    "sg:postcode":"15001",
    "sg:province":"PA",
    "sg:tags":[
        "glass",
        "window",
        "plate"
    ],
    "wof:name":"John's Collision Ctr",
    "wof:placetype":"venue"
},
  "geometry": {"coordinates":[-80.250855,40.614599],"type":"Point"}
}