{
  "type": "Feature",
  "properties": {
    "addr:full":"6323 Castor Ave Philadelphia PA 19149",
    "addr:housenumber":"6323",
    "addr:postcode":"19149",
    "addr:street":"Castor Ave",
    "iso:country":"US",
    "sg:address":"6323 Castor Ave",
    "sg:city":"Philadelphia",
    "sg:classifiers":[
        {
            "category":"Food & Beverages",
            "subcategory":"Bakery",
            "type":"Retail Goods"
        }
    ],
    "sg:phone":"+1 215 288 3531",
    "sg:postcode":"19149",
    "sg:province":"PA",
    "sg:tags":[
        "doughnut"
    ],
    "wof:name":"JSC Donuts Inc",
    "wof:placetype":"venue"
},
  "geometry": {"coordinates":[-75.077828,40.039001],"type":"Point"}
}