{
  "type": "Feature",
  "properties": {
    "addr:full":"773 State Rte 168 Darlington PA 16115",
    "addr:housenumber":"773",
    "addr:postcode":"16115",
    "addr:street":"State Rte 168",
    "iso:country":"US",
    "sg:address":"773 State Rte 168",
    "sg:city":"Darlington",
    "sg:classifiers":[
        {
            "category":"Government",
            "subcategory":"Office",
            "type":"Public Place"
        }
    ],
    "sg:phone":"+1   ",
    "sg:postcode":"16115",
    "sg:province":"PA",
    "sg:tags":[
        "executive"
    ],
    "wof:name":"South Beaver Township",
    "wof:placetype":"venue"
},
  "geometry": {"coordinates":[-80.463481,40.773006],"type":"Point"}
}