{
  "type": "Feature",
  "properties": {
    "iso:country":"US",
    "sg:address":"413 Florence Ave",
    "sg:city":"Jenkintown",
    "sg:classifiers":[
        {
            "category":"Professional",
            "type":"Services"
        }
    ],
    "sg:phone":"+1   ",
    "sg:postcode":"19046",
    "sg:province":"PA",
    "wof:name":"Secure Care Systems Inc",
    "wof:placetype":"venue"
},
  "geometry": {"coordinates":[-75.135243,40.095632],"type":"Point"}
}