{
  "type": "Feature",
  "properties": {
    "iso:country":"US",
    "sg:address":"911 Hanover Ave",
    "sg:city":"Allentown",
    "sg:classifiers":[
        {
            "category":"Autos & Motor Vehicles",
            "subcategory":"Automobile Sales",
            "type":"Retail Goods"
        }
    ],
    "sg:phone":"+1   ",
    "sg:postcode":"18109",
    "sg:province":"PA",
    "wof:name":"Albrights Auto Sales",
    "wof:placetype":"venue"
},
  "geometry": {"coordinates":[-75.440094,40.617506],"type":"Point"}
}