{
  "type": "Feature",
  "properties": {
    "iso:country":"US",
    "sg:address":"1075 Hunters Path",
    "sg:city":"Lancaster",
    "sg:classifiers":[
        {
            "category":"Retail",
            "subcategory":"Auto Repair",
            "type":"Services"
        }
    ],
    "sg:phone":"+1   ",
    "sg:postcode":"17601",
    "sg:province":"PA",
    "wof:name":"Dent Fighters Inc",
    "wof:placetype":"venue"
},
  "geometry": {"coordinates":[-76.386118,40.076664],"type":"Point"}
}