{
  "type": "Feature",
  "properties": {
    "addr:full":"38 Jenkins Ave Lansdale PA 19446",
    "addr:housenumber":"38",
    "addr:postcode":"19446",
    "addr:street":"Jenkins Ave",
    "iso:country":"US",
    "sg:address":"38 Jenkins Ave",
    "sg:city":"Lansdale",
    "sg:classifiers":[
        {
            "category":"Real Estate",
            "subcategory":"Real Estate Operator",
            "type":"Services"
        }
    ],
    "sg:phone":"+1 215 368 8689",
    "sg:postcode":"19446",
    "sg:province":"PA",
    "sg:tags":[
        "apartment"
    ],
    "wof:name":"Stanbridge the",
    "wof:placetype":"venue"
},
  "geometry": {"coordinates":[-75.283897,40.240398],"type":"Point"}
}