{
  "type": "Feature",
  "properties": {
    "iso:country":"US",
    "sg:address":"324 Showers Rd",
    "sg:city":"Clarion",
    "sg:classifiers":[
        {
            "category":"Food & Beverages",
            "subcategory":"Groceries & Convenience Stores",
            "type":"Retail Goods"
        }
    ],
    "sg:phone":"+1   ",
    "sg:postcode":"16214",
    "sg:province":"PA",
    "wof:name":"B James Channels II",
    "wof:placetype":"venue"
},
  "geometry": {"coordinates":[-79.304507,41.171386],"type":"Point"}
}