{
  "type": "Feature",
  "properties": {
    "iso:country":"US",
    "sg:address":"338 York Rd",
    "sg:city":"Warminster",
    "sg:classifiers":[
        {
            "category":"Manufacturing",
            "subcategory":"Signs",
            "type":"Manufacturing & Wholesale Goods"
        }
    ],
    "sg:phone":"+1 215 675 3166",
    "sg:postcode":"18974",
    "sg:province":"PA",
    "sg:tags":[
        "specialty",
        "mfg"
    ],
    "wof:name":"Hightech Signs",
    "wof:placetype":"venue"
},
  "geometry": {"coordinates":[-75.101366,40.198727],"type":"Point"}
}