{
  "type": "Feature",
  "properties": {
    "addr:full":"5386 Chestnut St Emmaus PA 18049",
    "addr:housenumber":"5386",
    "addr:postcode":"18049",
    "addr:street":"Chestnut St",
    "iso:country":"US",
    "sg:address":"5386 Chestnut St",
    "sg:city":"Emmaus",
    "sg:classifiers":[
        {
            "category":"Professional",
            "subcategory":"Business Services",
            "type":"Services"
        }
    ],
    "sg:phone":"+1 610 967 0699",
    "sg:postcode":"18049",
    "sg:province":"PA",
    "sg:tags":[
        "interior",
        "consultant",
        "design",
        "decorator"
    ],
    "wof:name":"Hendrixson's Furniture",
    "wof:placetype":"venue"
},
  "geometry": {"coordinates":[-75.52744,40.496036],"type":"Point"}
}