{
  "type": "Feature",
  "properties": {
    "addr:full":"147 Chapel Ave Parkesburg PA 19365",
    "addr:housenumber":"147",
    "addr:postcode":"19365",
    "addr:street":"Chapel Ave",
    "iso:country":"US",
    "sg:address":"147 Chapel Ave",
    "sg:city":"Parkesburg",
    "sg:classifiers":[
        {
            "category":"Professional",
            "subcategory":"Management & Consulting",
            "type":"Services"
        }
    ],
    "sg:phone":"+1   ",
    "sg:postcode":"19365",
    "sg:province":"PA",
    "wof:name":"Kodiak Construction Management",
    "wof:placetype":"venue"
},
  "geometry": {"coordinates":[-75.91542099999999,39.9627],"type":"Point"}
}