{
  "type": "Feature",
  "properties": {
    "iso:country":"US",
    "sg:address":"901 E Brady St Ste 103",
    "sg:city":"Butler",
    "sg:classifiers":[
        {
            "category":"Health Services",
            "subcategory":"Doctor",
            "type":"Services"
        },
        {
            "category":"Health Services",
            "subcategory":"Clinic",
            "type":"Services"
        }
    ],
    "sg:phone":"+1 724 282 1627",
    "sg:postcode":"16001",
    "sg:province":"PA",
    "sg:tags":[
        "psychological",
        "physician",
        "psychologist",
        "surgeons",
        "psychiatry"
    ],
    "wof:name":"Ness, David E Md",
    "wof:placetype":"venue"
},
  "geometry": {"coordinates":[-79.88343,40.86673],"type":"Point"}
}