{
  "type": "Feature",
  "properties": {
    "iso:country":"US",
    "sg:address":"1040 Harrisburg Ave",
    "sg:city":"Lancaster",
    "sg:classifiers":[
        {
            "category":"Restaurant",
            "type":"Food & Drink"
        }
    ],
    "sg:phone":"+1 717 299 9903",
    "sg:postcode":"17603",
    "sg:province":"PA",
    "wof:name":"Rosa Rosa Cafe & Bar",
    "wof:placetype":"venue"
},
  "geometry": {"coordinates":[-76.32196399999999,40.052015],"type":"Point"}
}