{
  "type": "Feature",
  "properties": {
    "addr:full":"2545 Broder St SW Allentown PA 18103",
    "addr:housenumber":"2545",
    "addr:postcode":"18103",
    "addr:street":"Broder St Sw",
    "iso:country":"US",
    "sg:address":"2545 Broder St SW",
    "sg:city":"Allentown",
    "sg:classifiers":[
        {
            "category":"Wholesale",
            "subcategory":"Non-durable Goods",
            "type":"Manufacturing & Wholesale Goods"
        }
    ],
    "sg:phone":"+1 610 791 1467",
    "sg:postcode":"18103",
    "sg:province":"PA",
    "sg:tags":[
        "merchandise-wholesale"
    ],
    "wof:name":"Dunye Import & Export Incorporated",
    "wof:placetype":"venue"
},
  "geometry": {"coordinates":[-75.47515799999999,40.560589],"type":"Point"}
}