{
  "type": "Feature",
  "properties": {
    "addr:full":"1440 Manheim Pike Lancaster PA 17601",
    "addr:housenumber":"1440",
    "addr:postcode":"17601",
    "addr:street":"Manheim Pike",
    "iso:country":"US",
    "sg:address":"1440 Manheim Pike",
    "sg:city":"Lancaster",
    "sg:classifiers":[
        {
            "category":"Professional",
            "type":"Services"
        },
        {
            "category":"Restaurant",
            "type":"Food & Drink"
        },
        {
            "category":"Fast Food",
            "type":"Food & Drink"
        }
    ],
    "sg:phone":"+1 717 392 8457",
    "sg:postcode":"17601",
    "sg:province":"PA",
    "sg:tags":[
        "delivery",
        "style",
        "take",
        "family",
        "pizza"
    ],
    "sg:website":"http://www.pizzahut.com",
    "wof:name":"Pizza Hut",
    "wof:placetype":"venue"
},
  "geometry": {"coordinates":[-76.333151,40.071223],"type":"Point"}
}