{
  "type": "Feature",
  "properties": {
    "iso:country":"US",
    "sg:address":"511 Broad St",
    "sg:city":"Milford",
    "sg:classifiers":[
        {
            "category":"Manufacturing",
            "subcategory":"Printing",
            "type":"Manufacturing & Wholesale Goods"
        }
    ],
    "sg:phone":"+1 570 296 6397",
    "sg:postcode":"18337",
    "sg:province":"PA",
    "sg:tags":[
        "newspaper"
    ],
    "sg:website":"www.pikecountypa.com",
    "wof:name":"Pike County Courier",
    "wof:placetype":"venue"
},
  "geometry": {"coordinates":[-74.800065,41.324765],"type":"Point"}
}