{
  "type": "Feature",
  "properties": {
    "addr:full":"1544 Huntsville Rd Shavertown PA 18708",
    "addr:housenumber":"1544",
    "addr:postcode":"18708",
    "addr:street":"Huntsville Rd",
    "iso:country":"US",
    "sg:address":"1544 Huntsville Rd",
    "sg:city":"Shavertown",
    "sg:classifiers":[
        {
            "category":"Manufacturing",
            "subcategory":"Wood Products",
            "type":"Manufacturing & Wholesale Goods"
        }
    ],
    "sg:phone":"+1 570 675 0890",
    "sg:postcode":"18708",
    "sg:province":"PA",
    "sg:tags":[
        "box",
        "pallet",
        "skid",
        "mfg"
    ],
    "wof:name":"Woodruff Corp",
    "wof:placetype":"venue"
},
  "geometry": {"coordinates":[-75.965445,41.288391],"type":"Point"}
}