{
  "type": "Feature",
  "properties": {
    "iso:country":"US",
    "sg:address":"44 Pennsylvania Ave",
    "sg:city":"Malvern",
    "sg:classifiers":[
        {
            "category":"Manufacturing",
            "subcategory":"Textiles",
            "type":"Manufacturing & Wholesale Goods"
        }
    ],
    "sg:phone":"+1 610 296 7501",
    "sg:postcode":"19355",
    "sg:province":"PA",
    "sg:tags":[
        "textiles-manufacturers"
    ],
    "wof:name":"Skyline Technology Inc",
    "wof:placetype":"venue"
},
  "geometry": {"coordinates":[-75.517527,40.037167],"type":"Point"}
}