{
  "type": "Feature",
  "properties": {
    "iso:country":"US",
    "sg:address":"1011 McKean St",
    "sg:city":"Philadelphia",
    "sg:classifiers":[
        {
            "category":"Building & Trades",
            "subcategory":"Construction",
            "type":"Services"
        }
    ],
    "sg:phone":"+1   ",
    "sg:postcode":"19148",
    "sg:province":"PA",
    "sg:tags":[
        "house"
    ],
    "wof:name":"Le Pore Tom A Construction",
    "wof:placetype":"venue"
},
  "geometry": {"coordinates":[-75.16280500000001,39.924792],"type":"Point"}
}