{
  "type": "Feature",
  "properties": {
    "iso:country":"US",
    "sg:address":"1326 Streets Run Rd",
    "sg:city":"Pittsburgh",
    "sg:classifiers":[
        {
            "category":"Wholesale",
            "subcategory":"Electrical",
            "type":"Manufacturing & Wholesale Goods"
        }
    ],
    "sg:phone":"+1 412 341 3606",
    "sg:postcode":"15236",
    "sg:province":"PA",
    "sg:tags":[
        "lighting"
    ],
    "wof:name":"ADS Lighting & Staging",
    "wof:placetype":"venue"
},
  "geometry": {"coordinates":[-79.956401,40.354326],"type":"Point"}
}