{
  "type": "Feature",
  "properties": {
    "addr:full":"275 Hardin Hollow Rd Smithfield PA 15478",
    "addr:housenumber":"275",
    "addr:postcode":"15478",
    "addr:street":"Hardin Hollow Rd",
    "iso:country":"US",
    "sg:address":"275 Hardin Hollow Rd",
    "sg:city":"Smithfield",
    "sg:classifiers":[
        {
            "category":"Organizations",
            "subcategory":"Religious Organization",
            "type":"Services"
        }
    ],
    "sg:phone":"+1 724 564 1554",
    "sg:postcode":"15478",
    "sg:province":"PA",
    "sg:tags":[
        "clergy"
    ],
    "wof:name":"C L Moser",
    "wof:placetype":"venue"
},
  "geometry": {"coordinates":[-79.757115,39.799526],"type":"Point"}
}