{
  "type": "Feature",
  "properties": {
    "iso:country":"US",
    "sg:address":"400 Oxford Dr",
    "sg:city":"Monroeville",
    "sg:classifiers":[
        {
            "category":"Professional",
            "type":"Services"
        }
    ],
    "sg:phone":"+1 412 373 4600",
    "sg:postcode":"15146",
    "sg:province":"PA",
    "sg:tags":[
        "establishment"
    ],
    "wof:name":"Penn-Del Directory Corp",
    "wof:placetype":"venue"
},
  "geometry": {"coordinates":[-79.788668,40.431709],"type":"Point"}
}