{
  "type": "Feature",
  "properties": {
    "addr:full":"176 Prince St Northumberland PA 17857",
    "addr:housenumber":"176",
    "addr:postcode":"17857",
    "addr:street":"Prince St",
    "iso:country":"US",
    "sg:address":"176 Prince St",
    "sg:city":"Northumberland",
    "sg:classifiers":[
        {
            "category":"Government",
            "subcategory":"Office",
            "type":"Public Place"
        }
    ],
    "sg:phone":"+1 570 473 0150",
    "sg:postcode":"17857",
    "sg:province":"PA",
    "sg:tags":[
        "village"
    ],
    "wof:name":"Northumberland Boro Office",
    "wof:placetype":"venue"
},
  "geometry": {"coordinates":[-76.791656,40.893992],"type":"Point"}
}