{
  "type": "Feature",
  "properties": {
    "iso:country":"US",
    "sg:address":"360 Locust St",
    "sg:city":"Columbia",
    "sg:classifiers":[
        {
            "category":"Organizations",
            "subcategory":"Religious Organization",
            "type":"Services"
        }
    ],
    "sg:phone":"+1 717 684 6271",
    "sg:postcode":"17512",
    "sg:province":"PA",
    "sg:tags":[
        "church"
    ],
    "sg:website":"www.donegalpby.com",
    "wof:name":"Presbyterian Church",
    "wof:placetype":"venue"
},
  "geometry": {"coordinates":[-76.50139,40.032507],"type":"Point"}
}