{
  "type": "Feature",
  "properties": {
    "iso:country":"US",
    "sg:address":"2813 Enola Rd",
    "sg:city":"Carlisle",
    "sg:classifiers":[
        {
            "category":"Building & Trades",
            "subcategory":"Cleaning & Sanitation",
            "type":"Services"
        }
    ],
    "sg:phone":"+1 717 648 9645",
    "sg:postcode":"17013",
    "sg:province":"PA",
    "sg:tags":[
        "carpet"
    ],
    "wof:name":"Capital Area Chemdry",
    "wof:placetype":"venue"
},
  "geometry": {"coordinates":[-77.2714,40.263302],"type":"Point"}
}