{
  "type": "Feature",
  "properties": {
    "iso:country":"US",
    "sg:address":"2460 Commercial Blvd",
    "sg:city":"State College",
    "sg:classifiers":[
        {
            "category":"Wholesale",
            "subcategory":"Hardware",
            "type":"Manufacturing & Wholesale Goods"
        }
    ],
    "sg:phone":"+1 814 234 1897",
    "sg:postcode":"16801",
    "sg:province":"PA",
    "wof:name":"Hardware Specialties",
    "wof:placetype":"venue"
},
  "geometry": {"coordinates":[-77.81268799999999,40.824848],"type":"Point"}
}