{
  "type": "Feature",
  "properties": {
    "addr:full":"20 Canal St Greenville PA 16125",
    "addr:housenumber":"20",
    "addr:postcode":"16125",
    "addr:street":"Canal St",
    "iso:country":"US",
    "sg:address":"20 Canal St",
    "sg:city":"Greenville",
    "sg:classifiers":[
        {
            "category":"Shopping",
            "type":"Retail Goods"
        }
    ],
    "sg:phone":"+1 724 588 4784",
    "sg:postcode":"16125",
    "sg:province":"PA",
    "sg:tags":[
        "hearing",
        "equipment",
        "supply",
        "impaired"
    ],
    "wof:name":"R W Petruso Hearing Ctr",
    "wof:placetype":"venue"
},
  "geometry": {"coordinates":[-80.388559,41.404377],"type":"Point"}
}