{
  "type": "Feature",
  "properties": {
    "iso:country":"US",
    "sg:address":"878 Jonathan Dr",
    "sg:city":"Telford",
    "sg:classifiers":[
        {
            "category":"Travel",
            "subcategory":"Travel Agent",
            "type":"Entertainment"
        }
    ],
    "sg:phone":"+1 215 723 2460",
    "sg:postcode":"18969",
    "sg:province":"PA",
    "sg:tags":[
        "agency",
        "bureau"
    ],
    "wof:name":"Spirit Travel Svc",
    "wof:placetype":"venue"
},
  "geometry": {"coordinates":[-75.370575,40.328222],"type":"Point"}
}