{
  "type": "Feature",
  "properties": {
    "iso:country":"US",
    "sg:address":"244 Windsor Ct",
    "sg:city":"Glen Mills",
    "sg:classifiers":[
        {
            "category":"Bars & Pubs",
            "type":"Food & Drink"
        }
    ],
    "sg:phone":"+1   ",
    "sg:postcode":"19342",
    "sg:province":"PA",
    "sg:tags":[
        "drinking"
    ],
    "wof:name":"Avalon Tavern Corporation",
    "wof:placetype":"venue"
},
  "geometry": {"coordinates":[-75.482195,39.898661],"type":"Point"}
}