{
  "type": "Feature",
  "properties": {
    "iso:country":"US",
    "sg:address":"808 Church St",
    "sg:city":"Moosic",
    "sg:classifiers":[
        {
            "category":"Banks & Credit Unions",
            "subcategory":"Bank",
            "type":"Services"
        }
    ],
    "sg:phone":"+1 570 504 0751",
    "sg:postcode":"18507",
    "sg:province":"PA",
    "sg:tags":[
        "mortgage",
        "loan",
        "broker",
        "real estate"
    ],
    "wof:name":"A & M Mortgage Brokers Inc",
    "wof:placetype":"venue"
},
  "geometry": {"coordinates":[-75.70358400000001,41.369069],"type":"Point"}
}