{
  "type": "Feature",
  "properties": {
    "addr:full":"2121 Market St Philadelphia PA 19103",
    "addr:housenumber":"2121",
    "addr:postcode":"19103",
    "addr:street":"Market St",
    "iso:country":"US",
    "sg:address":"2121 Market St",
    "sg:city":"Philadelphia",
    "sg:classifiers":[
        {
            "category":"Real Estate",
            "subcategory":"Real Estate Agent",
            "type":"Services"
        }
    ],
    "sg:phone":"+1 215 569 2945",
    "sg:postcode":"19103",
    "sg:province":"PA",
    "sg:tags":[
        "management"
    ],
    "wof:name":"Philadelphia Management Corp",
    "wof:placetype":"venue"
},
  "geometry": {"coordinates":[-75.17639699999999,39.954039],"type":"Point"}
}