{
  "type": "Feature",
  "properties": {
    "addr:full":"1600 John F. Kennedy Boulevard Suite 1050 Philadelphia PA 19103",
    "addr:housenumber":"1600",
    "addr:postcode":"19103",
    "addr:street":"John F. Kennedy Boulevard Suite 1050",
    "iso:country":"US",
    "sg:address":"1600 John F. Kennedy Boulevard Suite 1050",
    "sg:city":"Philadelphia",
    "sg:classifiers":[
        {
            "category":"Professional",
            "subcategory":"Lawyer & Legal Services",
            "type":"Services"
        }
    ],
    "sg:phone":"+1 215 568 4500",
    "sg:postcode":"19103",
    "sg:province":"PA",
    "sg:tags":[
        "litigation"
    ],
    "wof:name":"Ominsky Andrew M Atty",
    "wof:placetype":"venue"
},
  "geometry": {"coordinates":[-75.166768,39.953663],"type":"Point"}
}