{
  "type": "Feature",
  "properties": {
    "iso:country":"US",
    "sg:address":"237 E Brown St",
    "sg:city":"East Stroudsburg",
    "sg:classifiers":[
        {
            "category":"Health Services",
            "subcategory":"Health Practitioner",
            "type":"Services"
        }
    ],
    "sg:phone":"+1 570 688 9123",
    "sg:postcode":"18301",
    "sg:province":"PA",
    "sg:tags":[
        "psychologist"
    ],
    "wof:name":"Pocono Psychological Svc",
    "wof:placetype":"venue"
},
  "geometry": {"coordinates":[-75.174038,40.992226],"type":"Point"}
}