{
  "type": "Feature",
  "properties": {
    "iso:country":"US",
    "sg:address":"500 William St",
    "sg:city":"Pen Argyl",
    "sg:classifiers":[
        {
            "category":"Manufacturing",
            "subcategory":"Textiles",
            "type":"Manufacturing & Wholesale Goods"
        },
        {
            "category":"Manufacturing",
            "subcategory":"Apparel",
            "type":"Manufacturing & Wholesale Goods"
        }
    ],
    "sg:phone":"+1 610 863 4176",
    "sg:postcode":"18072",
    "sg:province":"PA",
    "sg:tags":[
        "bathing",
        "mfg",
        "suit"
    ],
    "sg:website":"www.miraclesuit.com",
    "wof:name":"A & H Sportswear Co Inc",
    "wof:placetype":"venue"
},
  "geometry": {"coordinates":[-75.259266,40.866609],"type":"Point"}
}