{
  "type": "Feature",
  "properties": {
    "addr:full":"555 Van Reed Rd Reading PA 19610",
    "addr:housenumber":"555",
    "addr:postcode":"19610",
    "addr:street":"Van Reed Rd",
    "iso:country":"US",
    "sg:address":"555 Van Reed Rd",
    "sg:city":"Reading",
    "sg:classifiers":[
        {
            "category":"Health Services",
            "subcategory":"Optometrist",
            "type":"Services"
        }
    ],
    "sg:phone":"+1   ",
    "sg:postcode":"19610",
    "sg:province":"PA",
    "wof:name":"Berkshire Vision Center",
    "wof:placetype":"venue"
},
  "geometry": {"coordinates":[-75.95851,40.341134],"type":"Point"}
}