{
  "type": "Feature",
  "properties": {
    "addr:full":"183 Limekiln Rd New Cumberland PA 17070",
    "addr:housenumber":"183",
    "addr:postcode":"17070",
    "addr:street":"Limekiln Rd",
    "iso:country":"US",
    "sg:address":"183 Limekiln Rd",
    "sg:city":"New Cumberland",
    "sg:classifiers":[
        {
            "category":"Travel",
            "subcategory":"Hotels & Motels",
            "type":"Entertainment"
        }
    ],
    "sg:phone":"+1 717 774 5990",
    "sg:postcode":"17070",
    "sg:province":"PA",
    "wof:name":"Knights Inn",
    "wof:placetype":"venue"
},
  "geometry": {"coordinates":[-76.87220000000001,40.2145],"type":"Point"}
}