{
  "type": "Feature",
  "properties": {
    "iso:country":"US",
    "sg:address":"6750 Peach St",
    "sg:city":"Erie",
    "sg:classifiers":[
        {
            "category":"Restaurant",
            "type":"Food & Drink"
        }
    ],
    "sg:menulink":"http://www.allmenus.com/pa/summit/98676-longhorn-steakhouse/menu/",
    "sg:phone":"+1 814 866 7003",
    "sg:postcode":"16509",
    "sg:province":"PA",
    "sg:tags":[
        "american",
        "steakhouse"
    ],
    "wof:name":"LongHorn Steakhouse",
    "wof:placetype":"venue"
},
  "geometry": {"coordinates":[-80.089901,42.056881],"type":"Point"}
}