{
  "type": "Feature",
  "properties": {
    "iso:country":"US",
    "sg:address":"26455 Maple Dr",
    "sg:city":"Cambridge Springs",
    "sg:classifiers":[
        {
            "category":"Manufacturing",
            "subcategory":"Rubber & Plastics",
            "type":"Manufacturing & Wholesale Goods"
        }
    ],
    "sg:phone":"+1   ",
    "sg:postcode":"16403",
    "sg:province":"PA",
    "sg:tags":[
        "product",
        "mfg"
    ],
    "wof:name":"Lakeshore Plastics",
    "wof:placetype":"venue"
},
  "geometry": {"coordinates":[-80.06009,41.844031],"type":"Point"}
}