{
  "type": "Feature",
  "properties": {
    "iso:country":"US",
    "sg:address":"354 Walnut St",
    "sg:city":"Phoenixville",
    "sg:classifiers":[
        {
            "category":"Manufacturing",
            "subcategory":"Tools & Machinery",
            "type":"Manufacturing & Wholesale Goods"
        }
    ],
    "sg:phone":"+1   ",
    "sg:postcode":"19460",
    "sg:province":"PA",
    "sg:tags":[
        "c",
        "mfg",
        "die",
        "metal",
        "precision",
        "stampings",
        "electronic"
    ],
    "wof:name":"Danco Precision Inc",
    "wof:placetype":"venue"
},
  "geometry": {"coordinates":[-75.519425,40.131187],"type":"Point"}
}