{
  "type": "Feature",
  "properties": {
    "iso:country":"US",
    "sg:address":"6066 Peach St",
    "sg:city":"Erie",
    "sg:classifiers":[
        {
            "category":"Health Services",
            "subcategory":"Dentist",
            "type":"Services"
        }
    ],
    "sg:phone":"+1 814 868 8679",
    "sg:postcode":"16509",
    "sg:province":"PA",
    "sg:tags":[
        "dentists-orthodontists"
    ],
    "sg:website":"http://www.drwilcko.com",
    "wof:name":"Wilcko William M DMD MS",
    "wof:placetype":"venue"
},
  "geometry": {"coordinates":[-80.093914,42.061734],"type":"Point"}
}