{
  "type": "Feature",
  "properties": {
    "iso:country":"US",
    "sg:address":"2739 Shadyside Rd",
    "sg:city":"Findley Lake",
    "sg:classifiers":[
        {
            "category":"Personal",
            "subcategory":"Beauty Salon",
            "type":"Services"
        }
    ],
    "sg:phone":"+1 716 769 7764",
    "sg:postcode":"14724",
    "sg:province":"NY",
    "wof:name":"Cyndy's Hair Design",
    "wof:placetype":"venue"
},
  "geometry": {"coordinates":[-79.73509,42.115786],"type":"Point"}
}