{
  "type": "Feature",
  "properties": {
    "iso:country":"US",
    "sg:address":"5138 Lower Valley Rd",
    "sg:city":"Atglen",
    "sg:phone":"+1   ",
    "sg:postcode":"19310",
    "sg:province":"PA",
    "sg:tags":[
        "farm",
        "corn",
        "dairy",
        "soybean"
    ],
    "wof:name":"Glen Valley Farm",
    "wof:placetype":"venue"
},
  "geometry": {"coordinates":[-75.96646200000001,39.947509],"type":"Point"}
}