{
  "type": "Feature",
  "properties": {
    "addr:full":"112 S Washington St Eau Claire PA 16030",
    "addr:housenumber":"112",
    "addr:postcode":"16030",
    "addr:street":"S Washington St",
    "iso:country":"US",
    "sg:address":"112 S Washington St",
    "sg:city":"Eau Claire",
    "sg:classifiers":[
        {
            "category":"Organizations",
            "subcategory":"Religious Organization",
            "type":"Services"
        }
    ],
    "sg:phone":"+1 724 791 1123",
    "sg:postcode":"16030",
    "sg:province":"PA",
    "sg:tags":[
        "church"
    ],
    "wof:name":"Bethel Methodist Church",
    "wof:placetype":"venue"
},
  "geometry": {"coordinates":[-79.798376,41.136061],"type":"Point"}
}