{
  "type": "Feature",
  "properties": {
    "iso:country":"US",
    "sg:address":"301 Crisp Ave",
    "sg:city":"Scranton",
    "sg:classifiers":[
        {
            "category":"Building & Trades",
            "subcategory":"Construction",
            "type":"Services"
        }
    ],
    "sg:phone":"+1   ",
    "sg:postcode":"18504",
    "sg:province":"PA",
    "sg:tags":[
        "contractor"
    ],
    "wof:name":"Robert F Ravioli",
    "wof:placetype":"venue"
},
  "geometry": {"coordinates":[-75.70822200000001,41.419961],"type":"Point"}
}