{
  "type": "Feature",
  "properties": {
    "addr:full":"44 Mauch Chunk St Tamaqua PA 18252",
    "addr:housenumber":"44",
    "addr:postcode":"18252",
    "addr:street":"Mauch Chunk St",
    "iso:country":"US",
    "sg:address":"44 Mauch Chunk St",
    "sg:city":"Tamaqua",
    "sg:classifiers":[
        {
            "category":"Personal",
            "type":"Services"
        }
    ],
    "sg:phone":"+1   ",
    "sg:postcode":"18252",
    "sg:province":"PA",
    "wof:name":"Mob Ink",
    "wof:placetype":"venue"
},
  "geometry": {"coordinates":[-75.96871400000001,40.798181],"type":"Point"}
}