{
  "type": "Feature",
  "properties": {
    "iso:country":"US",
    "sg:address":"53 N Monroe St",
    "sg:city":"Boyertown",
    "sg:classifiers":[
        {
            "category":"Recreation",
            "type":"Entertainment"
        }
    ],
    "sg:phone":"+1   ",
    "sg:postcode":"19512",
    "sg:province":"PA",
    "wof:name":"Bear Stadium",
    "wof:placetype":"venue"
},
  "geometry": {"coordinates":[-75.630883,40.330678],"type":"Point"}
}