{
  "type": "Feature",
  "properties": {
    "addr:full":"526 Heath Rd Telford PA 18969",
    "addr:housenumber":"526",
    "addr:postcode":"18969",
    "addr:street":"Heath Rd",
    "iso:country":"US",
    "sg:address":"526 Heath Rd",
    "sg:city":"Telford",
    "sg:classifiers":[
        {
            "category":"Building & Trades",
            "subcategory":"Plumbing",
            "type":"Services"
        }
    ],
    "sg:phone":"+1 215 723 0204",
    "sg:postcode":"18969",
    "sg:province":"PA",
    "sg:tags":[
        "plumbing",
        "contractor"
    ],
    "wof:name":"Harry L Ketterer",
    "wof:placetype":"venue"
},
  "geometry": {"coordinates":[-75.38001199999999,40.315676],"type":"Point"}
}