{
  "type": "Feature",
  "properties": {
    "addr:full":"113 S Front St Frnt Frnt Steelton PA 17113",
    "addr:housenumber":"113",
    "addr:postcode":"17113",
    "addr:street":"S Front St",
    "iso:country":"US",
    "sg:address":"113 S Front St Frnt Frnt",
    "sg:city":"Steelton",
    "sg:classifiers":[
        {
            "category":"Personal",
            "subcategory":"Beauty Salon",
            "type":"Services"
        },
        {
            "category":"Personal",
            "subcategory":"Barber",
            "type":"Services"
        }
    ],
    "sg:phone":"+1 717 939 3848",
    "sg:postcode":"17113",
    "sg:province":"PA",
    "wof:name":"Pizazz Ladies & Mens Salon",
    "wof:placetype":"venue"
},
  "geometry": {"coordinates":[-76.83823099999999,40.233741],"type":"Point"}
}