{
  "type": "Feature",
  "properties": {
    "addr:full":"204 W Spring St Titusville PA 16354",
    "addr:housenumber":"204",
    "addr:postcode":"16354",
    "addr:street":"W Spring St",
    "iso:country":"US",
    "sg:address":"204 W Spring St",
    "sg:city":"Titusville",
    "sg:classifiers":[
        {
            "category":"Professional",
            "type":"Services"
        }
    ],
    "sg:phone":"+1 814 827 6692",
    "sg:postcode":"16354",
    "sg:province":"PA",
    "sg:tags":[
        "establishment"
    ],
    "wof:name":"Weldon Larry & Kelly Bus Ofc",
    "wof:placetype":"venue"
},
  "geometry": {"coordinates":[-79.673923,41.626523],"type":"Point"}
}