{
  "type": "Feature",
  "properties": {
    "addr:full":"301 S Pine St Langhorne PA 19047",
    "addr:housenumber":"301",
    "addr:postcode":"19047",
    "addr:street":"S Pine St",
    "iso:country":"US",
    "sg:address":"301 S Pine St",
    "sg:city":"Langhorne",
    "sg:classifiers":[
        {
            "category":"Education",
            "subcategory":"Library",
            "type":"Public Place"
        }
    ],
    "sg:phone":"+1 215 757 2510",
    "sg:postcode":"19047",
    "sg:province":"PA",
    "wof:name":"Bucks County Free Library",
    "wof:placetype":"venue"
},
  "geometry": {"coordinates":[-74.91629500000001,40.174162],"type":"Point"}
}