{
  "type": "Feature",
  "properties": {
    "addr:full":"214 Market St Scottdale PA 15683",
    "addr:housenumber":"214",
    "addr:postcode":"15683",
    "addr:street":"Market St",
    "iso:country":"US",
    "sg:address":"214 Market St",
    "sg:city":"Scottdale",
    "sg:classifiers":[
        {
            "category":"Professional",
            "subcategory":"Lawyer & Legal Services",
            "type":"Services"
        }
    ],
    "sg:phone":"+1   ",
    "sg:postcode":"15683",
    "sg:province":"PA",
    "wof:name":"Robt P Boyer",
    "wof:placetype":"venue"
},
  "geometry": {"coordinates":[-79.589747,40.101007],"type":"Point"}
}