{
  "type": "Feature",
  "properties": {
    "iso:country":"US",
    "sg:address":"2081 McKees Rocks Rd",
    "sg:city":"Mc Kees Rocks",
    "sg:classifiers":[
        {
            "category":"Building & Trades",
            "subcategory":"Construction",
            "type":"Services"
        }
    ],
    "sg:phone":"+1   ",
    "sg:postcode":"15136",
    "sg:province":"PA",
    "sg:tags":[
        "house"
    ],
    "wof:name":"Rowe Home Improvement",
    "wof:placetype":"venue"
},
  "geometry": {"coordinates":[-80.110024,40.457622],"type":"Point"}
}