{
  "type": "Feature",
  "properties": {
    "addr:full":"1304 Valley Dr Lansdale PA 19446",
    "addr:housenumber":"1304",
    "addr:postcode":"19446",
    "addr:street":"Valley Dr",
    "iso:country":"US",
    "sg:address":"1304 Valley Dr",
    "sg:city":"Lansdale",
    "sg:classifiers":[
        {
            "category":"Shopping",
            "subcategory":"Hobbies, Toys, & Games",
            "type":"Retail Goods"
        }
    ],
    "sg:phone":"+1   ",
    "sg:postcode":"19446",
    "sg:province":"PA",
    "wof:name":"Elkes Dream",
    "wof:placetype":"venue"
},
  "geometry": {"coordinates":[-75.301917,40.230464],"type":"Point"}
}