{
  "type": "Feature",
  "properties": {
    "addr:full":"202 Westview Dr Meadville PA 16335",
    "addr:housenumber":"202",
    "addr:postcode":"16335",
    "addr:street":"Westview Dr",
    "iso:country":"US",
    "sg:address":"202 Westview Dr",
    "sg:city":"Meadville",
    "sg:classifiers":[
        {
            "category":"Professional",
            "subcategory":"Business Services",
            "type":"Services"
        }
    ],
    "sg:phone":"+1 814 337 7753",
    "sg:postcode":"16335",
    "sg:province":"PA",
    "sg:tags":[
        "inspection"
    ],
    "sg:website":"http://www.actcometrology.com",
    "wof:name":"Actco Metrology Services",
    "wof:placetype":"venue"
},
  "geometry": {"coordinates":[-80.15833600000001,41.660159],"type":"Point"}
}