{
  "type": "Feature",
  "properties": {
    "iso:country":"US",
    "sg:address":"30 Fetters Mill Sq",
    "sg:city":"Huntingdon Valley",
    "sg:classifiers":[
        {
            "category":"Shopping",
            "subcategory":"Clothing, Apparel, & Fashions",
            "type":"Retail Goods"
        }
    ],
    "sg:phone":"+1   ",
    "sg:postcode":"19006",
    "sg:province":"PA",
    "sg:tags":[
        "ready"
    ],
    "wof:name":"Curlys Cleaners",
    "wof:placetype":"venue"
},
  "geometry": {"coordinates":[-75.062836,40.126055],"type":"Point"}
}