{
  "type": "Feature",
  "properties": {
    "iso:country":"US",
    "sg:address":"916 Northampton St",
    "sg:city":"Easton",
    "sg:classifiers":[
        {
            "category":"Freight",
            "type":"Transportation"
        }
    ],
    "sg:phone":"+1   ",
    "sg:postcode":"18042",
    "sg:province":"PA",
    "wof:name":"Fast Transportation",
    "wof:placetype":"venue"
},
  "geometry": {"coordinates":[-75.222258,40.690523],"type":"Point"}
}