{
  "type": "Feature",
  "properties": {
    "addr:full":"4433 Lincoln Way W Saint Thomas PA 17252",
    "addr:housenumber":"4433",
    "addr:postcode":"17252",
    "addr:street":"Lincoln Way W",
    "iso:country":"US",
    "sg:address":"4433 Lincoln Way W",
    "sg:city":"Saint Thomas",
    "sg:classifiers":[
        {
            "category":"Manufacturing",
            "subcategory":"Tools & Machinery",
            "type":"Manufacturing & Wholesale Goods"
        }
    ],
    "sg:phone":"+1   ",
    "sg:postcode":"17252",
    "sg:province":"PA",
    "sg:tags":[
        "industrial",
        "mfg"
    ],
    "wof:name":"Lincoln Way Machine & Welding",
    "wof:placetype":"venue"
},
  "geometry": {"coordinates":[-77.750668,39.928719],"type":"Point"}
}