{
  "type": "Feature",
  "properties": {
    "addr:full":"100 Robinson Center Dr Pittsburgh PA 15205",
    "addr:housenumber":"100",
    "addr:postcode":"15205",
    "addr:street":"Robinson Center Dr",
    "iso:country":"US",
    "sg:address":"100 Robinson Center Dr",
    "sg:city":"Pittsburgh",
    "sg:classifiers":[
        {
            "category":"Restaurant",
            "type":"Food & Drink"
        }
    ],
    "sg:phone":"+1 412 494 9794",
    "sg:postcode":"15205",
    "sg:province":"PA",
    "sg:tags":[
        "pizza"
    ],
    "sg:website":"www.villapizza.com",
    "wof:name":"Villa Pizza",
    "wof:placetype":"venue"
},
  "geometry": {"coordinates":[-80.157709,40.454458],"type":"Point"}
}