{
  "type": "Feature",
  "properties": {
    "iso:country":"US",
    "sg:address":"2902 Marvine Ave",
    "sg:city":"Scranton",
    "sg:classifiers":[
        {
            "category":"Bars & Pubs",
            "type":"Food & Drink"
        }
    ],
    "sg:phone":"+1 570 558 9946",
    "sg:postcode":"18508",
    "sg:province":"PA",
    "sg:tags":[
        "lounge",
        "cocktail"
    ],
    "wof:name":"ICU Lounge",
    "wof:placetype":"venue"
},
  "geometry": {"coordinates":[-75.644566,41.445944],"type":"Point"}
}