{
  "type": "Feature",
  "properties": {
    "iso:country":"US",
    "sg:address":"610 Bickmore Dr",
    "sg:city":"Wallingford",
    "sg:classifiers":[
        {
            "category":"Organizations",
            "subcategory":"Religious Organization",
            "type":"Services"
        }
    ],
    "sg:phone":"+1 610 876 0807",
    "sg:postcode":"19086",
    "sg:province":"PA",
    "sg:tags":[
        "clergy"
    ],
    "wof:name":"Harry D Jones",
    "wof:placetype":"venue"
},
  "geometry": {"coordinates":[-75.378049,39.882875],"type":"Point"}
}