{
  "type": "Feature",
  "properties": {
    "iso:country":"US",
    "sg:address":"434 White St",
    "sg:city":"Lehighton",
    "sg:classifiers":[
        {
            "category":"Retail",
            "subcategory":"Auto Repair",
            "type":"Services"
        }
    ],
    "sg:phone":"+1 610 377 5941",
    "sg:postcode":"18235",
    "sg:province":"PA",
    "sg:tags":[
        "body",
        "automobile",
        "painting"
    ],
    "wof:name":"Car Country Inc",
    "wof:placetype":"venue"
},
  "geometry": {"coordinates":[-75.69918699999999,40.826775],"type":"Point"}
}