{
  "type": "Feature",
  "properties": {
    "addr:full":"5618 N 12th St Philadelphia PA 19141",
    "addr:housenumber":"5618",
    "addr:postcode":"19141",
    "addr:street":"N 12Th St",
    "iso:country":"US",
    "sg:address":"5618 N 12th St",
    "sg:city":"Philadelphia",
    "sg:classifiers":[
        {
            "category":"Professional",
            "subcategory":"Business Services",
            "type":"Services"
        }
    ],
    "sg:phone":"+1   ",
    "sg:postcode":"19141",
    "sg:province":"PA",
    "sg:tags":[
        "wholesale",
        "good",
        "broker"
    ],
    "wof:name":"United Gvernment Solutions Inc",
    "wof:placetype":"venue"
},
  "geometry": {"coordinates":[-75.140899,40.03916],"type":"Point"}
}