{
  "type": "Feature",
  "properties": {
    "addr:full":"6519 Lilac St Pittsburgh PA 15217",
    "addr:housenumber":"6519",
    "addr:postcode":"15217",
    "addr:street":"Lilac St",
    "iso:country":"US",
    "sg:address":"6519 Lilac St",
    "sg:city":"Pittsburgh",
    "sg:classifiers":[
        {
            "category":"Building & Trades",
            "subcategory":"Construction",
            "type":"Services"
        }
    ],
    "sg:phone":"+1 412 421 0930",
    "sg:postcode":"15217",
    "sg:province":"PA",
    "sg:tags":[
        "bathroom",
        "remodeling"
    ],
    "wof:name":"Joe Arenson Kitchens & Baths",
    "wof:placetype":"venue"
},
  "geometry": {"coordinates":[-79.922185,40.423386],"type":"Point"}
}