{
  "type": "Feature",
  "properties": {
    "iso:country":"US",
    "sg:address":"11 Aloha St",
    "sg:city":"Port Matilda",
    "sg:classifiers":[
        {
            "category":"Health Services",
            "subcategory":"Doctor",
            "type":"Services"
        }
    ],
    "sg:phone":"+1   ",
    "sg:postcode":"16870",
    "sg:province":"PA",
    "sg:tags":[
        "medical"
    ],
    "wof:name":"D McLane Rogers MD",
    "wof:placetype":"venue"
},
  "geometry": {"coordinates":[-78.00649,40.78276],"type":"Point"}
}