{
  "type": "Feature",
  "properties": {
    "iso:country":"US",
    "sg:address":"5020 Ritter Rd",
    "sg:city":"Mechanicsburg",
    "sg:classifiers":[
        {
            "category":"Professional",
            "subcategory":"Computer Services",
            "type":"Services"
        }
    ],
    "sg:phone":"+1 717 691 8999",
    "sg:postcode":"17055",
    "sg:province":"PA",
    "sg:tags":[
        "consultant",
        "designer"
    ],
    "wof:name":"Computer Task Group Inc",
    "wof:placetype":"venue"
},
  "geometry": {"coordinates":[-76.960494,40.205195],"type":"Point"}
}