{
  "type": "Feature",
  "properties": {
    "iso:country":"US",
    "sg:address":"12 S Hull St",
    "sg:city":"Reading",
    "sg:classifiers":[
        {
            "category":"Building & Trades",
            "subcategory":"Construction",
            "type":"Services"
        }
    ],
    "sg:phone":"+1   ",
    "sg:postcode":"19608",
    "sg:province":"PA",
    "sg:tags":[
        "house"
    ],
    "wof:name":"Dream Home Remodeling Inc",
    "wof:placetype":"venue"
},
  "geometry": {"coordinates":[-76.02432399999999,40.324869],"type":"Point"}
}