{
  "type": "Feature",
  "properties": {
    "addr:full":"341 Chestnut St Columbia PA 17512",
    "addr:housenumber":"341",
    "addr:postcode":"17512",
    "addr:street":"Chestnut St",
    "iso:country":"US",
    "sg:address":"341 Chestnut St",
    "sg:city":"Columbia",
    "sg:classifiers":[
        {
            "category":"Wholesale",
            "subcategory":"Toys & Hobbies",
            "type":"Manufacturing & Wholesale Goods"
        },
        {
            "category":"Banks & Credit Unions",
            "subcategory":"Financial Services",
            "type":"Services"
        }
    ],
    "sg:phone":"+1 717 684 7009",
    "sg:postcode":"17512",
    "sg:province":"PA",
    "sg:tags":[
        "company",
        "firework",
        "holding"
    ],
    "wof:name":"Heartland Associates",
    "wof:placetype":"venue"
},
  "geometry": {"coordinates":[-76.504369,40.034298],"type":"Point"}
}