{
  "type": "Feature",
  "properties": {
    "addr:full":"10109 Raystown Rd Saxton PA 16678",
    "addr:housenumber":"10109",
    "addr:postcode":"16678",
    "addr:street":"Raystown Rd",
    "iso:country":"US",
    "sg:address":"10109 Raystown Rd",
    "sg:city":"Saxton",
    "sg:classifiers":[
        {
            "category":"Personal",
            "subcategory":"Beauty Salon",
            "type":"Services"
        }
    ],
    "sg:phone":"+1 814 635 3512",
    "sg:postcode":"16678",
    "sg:province":"PA",
    "wof:name":"Stacey's Beauty Salon",
    "wof:placetype":"venue"
},
  "geometry": {"coordinates":[-78.275209,40.220304],"type":"Point"}
}