{
  "type": "Feature",
  "properties": {
    "addr:full":"141 W Upsal St Philadelphia PA 19119",
    "addr:housenumber":"141",
    "addr:postcode":"19119",
    "addr:street":"W Upsal St",
    "iso:country":"US",
    "sg:address":"141 W Upsal St",
    "sg:city":"Philadelphia",
    "sg:classifiers":[
        {
            "category":"Communications",
            "subcategory":"Film & Video Production",
            "type":"Services"
        }
    ],
    "sg:phone":"+1 215 849 3737",
    "sg:postcode":"19119",
    "sg:province":"PA",
    "sg:tags":[
        "picture",
        "companies-film",
        "producer",
        "tv",
        "motion",
        "studio",
        "radio"
    ],
    "wof:name":"The Windmill Group Inc",
    "wof:placetype":"venue"
},
  "geometry": {"coordinates":[-75.185847,40.045849],"type":"Point"}
}