{
  "type": "Feature",
  "properties": {
    "addr:full":"2282 Nottingham Rd Allentown PA 18103",
    "addr:housenumber":"2282",
    "addr:postcode":"18103",
    "addr:street":"Nottingham Rd",
    "iso:country":"US",
    "sg:address":"2282 Nottingham Rd",
    "sg:city":"Allentown",
    "sg:classifiers":[
        {
            "category":"Retail",
            "subcategory":"Laundry & Dry Cleaning",
            "type":"Services"
        }
    ],
    "sg:phone":"+1   ",
    "sg:postcode":"18103",
    "sg:province":"PA",
    "wof:name":"Johnnys Carpet Care",
    "wof:placetype":"venue"
},
  "geometry": {"coordinates":[-75.49788700000001,40.581186],"type":"Point"}
}