{
  "type": "Feature",
  "properties": {
    "iso:country":"US",
    "sg:address":"1549 S 13th St",
    "sg:city":"Philadelphia",
    "sg:classifiers":[
        {
            "category":"Restaurant",
            "type":"Food & Drink"
        }
    ],
    "sg:phone":"+1 215 755 8903",
    "sg:postcode":"19147",
    "sg:province":"PA",
    "sg:tags":[
        "eating"
    ],
    "wof:name":"Pastaria Restaurant",
    "wof:placetype":"venue"
},
  "geometry": {"coordinates":[-75.166067,39.930791],"type":"Point"}
}