{
  "type": "Feature",
  "properties": {
    "addr:full":"439 W Market St York PA 17401",
    "addr:housenumber":"439",
    "addr:postcode":"17401",
    "addr:street":"W Market St",
    "iso:country":"US",
    "sg:address":"439 W Market St",
    "sg:city":"York",
    "sg:classifiers":[
        {
            "category":"Real Estate",
            "subcategory":"Real Estate Agent",
            "type":"Services"
        }
    ],
    "sg:phone":"+1 717 843 5104",
    "sg:postcode":"17401",
    "sg:province":"PA",
    "sg:tags":[
        "appraisal",
        "appraiser"
    ],
    "wof:name":"Meagher & Associates",
    "wof:placetype":"venue"
},
  "geometry": {"coordinates":[-76.73917299999999,39.959037],"type":"Point"}
}