{
  "type": "Feature",
  "properties": {
    "iso:country":"US",
    "sg:address":"754 Gettysburg Rd",
    "sg:city":"Mechanicsburg",
    "sg:classifiers":[
        {
            "category":"Building & Trades",
            "subcategory":"Construction",
            "type":"Services"
        }
    ],
    "sg:phone":"+1 717 691 9750",
    "sg:postcode":"17055",
    "sg:province":"PA",
    "sg:tags":[
        "bridge",
        "concrete"
    ],
    "wof:name":"Deblin Inc",
    "wof:placetype":"venue"
},
  "geometry": {"coordinates":[-76.97434199999999,40.198682],"type":"Point"}
}