{
  "type": "Feature",
  "properties": {
    "iso:country":"US",
    "sg:address":"308 Hodgson Rd",
    "sg:city":"Darlington",
    "sg:classifiers":[
        {
            "category":"Retail",
            "subcategory":"Event Space",
            "type":"Services"
        }
    ],
    "sg:phone":"+1 724 847 1667",
    "sg:postcode":"16115",
    "sg:province":"PA",
    "sg:tags":[
        "facility",
        "hall",
        "reception",
        "banquet"
    ],
    "wof:name":"Bershire Banquet Hall",
    "wof:placetype":"venue"
},
  "geometry": {"coordinates":[-80.462696,40.784478],"type":"Point"}
}