{
  "type": "Feature",
  "properties": {
    "addr:full":"62 N Whitehorse Rd Phoenixville PA 19460",
    "addr:housenumber":"62",
    "addr:postcode":"19460",
    "addr:street":"N Whitehorse Rd",
    "iso:country":"US",
    "sg:address":"62 N Whitehorse Rd",
    "sg:city":"Phoenixville",
    "sg:classifiers":[
        {
            "category":"Manufacturing",
            "subcategory":"Building Materials",
            "type":"Manufacturing & Wholesale Goods"
        }
    ],
    "sg:phone":"+1   ",
    "sg:postcode":"19460",
    "sg:province":"PA",
    "sg:tags":[
        "mfg",
        "wood",
        "kitchen",
        "cabinet"
    ],
    "wof:name":"Mack Cabinets",
    "wof:placetype":"venue"
},
  "geometry": {"coordinates":[-75.500866,40.122355],"type":"Point"}
}