{
  "type": "Feature",
  "properties": {
    "iso:country":"US",
    "sg:address":"632 S Main St",
    "sg:city":"Wilkes Barre",
    "sg:classifiers":[
        {
            "category":"Manufacturing",
            "subcategory":"Retail Goods",
            "type":"Manufacturing & Wholesale Goods"
        }
    ],
    "sg:phone":"+1   ",
    "sg:postcode":"18701",
    "sg:province":"PA",
    "sg:tags":[
        "product",
        "mfg"
    ],
    "wof:name":"Nbsc",
    "wof:placetype":"venue"
},
  "geometry": {"coordinates":[-75.90142899999999,41.234886],"type":"Point"}
}