{
  "type": "Feature",
  "properties": {
    "iso:country":"US",
    "sg:address":"178 N 3rd St",
    "sg:city":"Hamburg",
    "sg:classifiers":[
        {
            "category":"Professional",
            "subcategory":"Accounting & Tax Preparation",
            "type":"Services"
        }
    ],
    "sg:phone":"+1 610 562 4142",
    "sg:postcode":"19526",
    "sg:province":"PA",
    "sg:tags":[
        "accountant"
    ],
    "wof:name":"Charles J Hafer",
    "wof:placetype":"venue"
},
  "geometry": {"coordinates":[-75.984908,40.556999],"type":"Point"}
}