{
  "type": "Feature",
  "properties": {
    "iso:country":"US",
    "sg:address":"130 E Main St",
    "sg:city":"Westfield",
    "sg:classifiers":[
        {
            "category":"Restaurant",
            "type":"Food & Drink"
        }
    ],
    "sg:phone":"+1 814 367 2646",
    "sg:postcode":"16950",
    "sg:province":"PA",
    "sg:tags":[
        "eating"
    ],
    "wof:name":"Pizza & Stuff",
    "wof:placetype":"venue"
},
  "geometry": {"coordinates":[-77.536085,41.920362],"type":"Point"}
}