{
  "type": "Feature",
  "properties": {
    "iso:country":"US",
    "sg:address":"5531 Germantown Ave",
    "sg:city":"Philadelphia",
    "sg:classifiers":[
        {
            "category":"Restaurant",
            "type":"Food & Drink"
        }
    ],
    "sg:phone":"+1 215 844 5818",
    "sg:postcode":"19144",
    "sg:province":"PA",
    "sg:tags":[
        "eating"
    ],
    "wof:name":"Larose Club",
    "wof:placetype":"venue"
},
  "geometry": {"coordinates":[-75.173582,40.034964],"type":"Point"}
}