{
  "type": "Feature",
  "properties": {
    "addr:full":"25 Utley Dr Camp Hill PA 17011",
    "addr:housenumber":"25",
    "addr:postcode":"17011",
    "addr:street":"Utley Dr",
    "iso:country":"US",
    "sg:address":"25 Utley Dr",
    "sg:city":"Camp Hill",
    "sg:classifiers":[
        {
            "category":"Freight",
            "type":"Transportation"
        }
    ],
    "sg:phone":"+1   ",
    "sg:postcode":"17011",
    "sg:province":"PA",
    "sg:tags":[
        "food",
        "snack",
        "mfg"
    ],
    "wof:name":"Herrs Potato Chips",
    "wof:placetype":"venue"
},
  "geometry": {"coordinates":[-76.944356,40.215385],"type":"Point"}
}