{
  "type": "Feature",
  "properties": {
    "addr:full":"539 S Main St Nazareth PA 18064",
    "addr:housenumber":"539",
    "addr:postcode":"18064",
    "addr:street":"S Main St",
    "iso:country":"US",
    "sg:address":"539 S Main St",
    "sg:city":"Nazareth",
    "sg:classifiers":[
        {
            "category":"Wholesale",
            "subcategory":"Non-durable Goods",
            "type":"Manufacturing & Wholesale Goods"
        }
    ],
    "sg:phone":"+1   ",
    "sg:postcode":"18064",
    "sg:province":"PA",
    "sg:tags":[
        "packaging",
        "machine",
        "parts",
        "for"
    ],
    "wof:name":"Toss Machine Components Inc",
    "wof:placetype":"venue"
},
  "geometry": {"coordinates":[-75.311792,40.73421],"type":"Point"}
}