{
  "type": "Feature",
  "properties": {
    "addr:full":"667 Davenport St Meadville PA 16335",
    "addr:housenumber":"667",
    "addr:postcode":"16335",
    "addr:street":"Davenport St",
    "iso:country":"US",
    "sg:address":"667 Davenport St",
    "sg:city":"Meadville",
    "sg:classifiers":[
        {
            "category":"Professional",
            "subcategory":"Accounting & Tax Preparation",
            "type":"Services"
        }
    ],
    "sg:phone":"+1 814 337 5998",
    "sg:postcode":"16335",
    "sg:province":"PA",
    "sg:tags":[
        "accountant"
    ],
    "wof:name":"Kreider & Co",
    "wof:placetype":"venue"
},
  "geometry": {"coordinates":[-80.137665,41.639048],"type":"Point"}
}