{
  "type": "Feature",
  "properties": {
    "addr:full":"9702 Chapel Rd Philadelphia PA 19115",
    "addr:housenumber":"9702",
    "addr:postcode":"19115",
    "addr:street":"Chapel Rd",
    "iso:country":"US",
    "sg:address":"9702 Chapel Rd",
    "sg:city":"Philadelphia",
    "sg:classifiers":[
        {
            "category":"Professional",
            "subcategory":"Detective & Security Services",
            "type":"Services"
        }
    ],
    "sg:phone":"+1   ",
    "sg:postcode":"19115",
    "sg:province":"PA",
    "sg:tags":[
        "installation",
        "system"
    ],
    "wof:name":"Edtronics Security Inc",
    "wof:placetype":"venue"
},
  "geometry": {"coordinates":[-75.040278,40.094196],"type":"Point"}
}