{
  "type": "Feature",
  "properties": {
    "iso:country":"US",
    "sg:address":"2251 Blue Mountain Pkwy",
    "sg:city":"Harrisburg",
    "sg:classifiers":[
        {
            "category":"Wholesale",
            "subcategory":"Computers",
            "type":"Manufacturing & Wholesale Goods"
        }
    ],
    "sg:phone":"+1 717 526 4604",
    "sg:postcode":"17112",
    "sg:province":"PA",
    "sg:tags":[
        "computer-wholesale",
        "manufacturer"
    ],
    "wof:name":"Raymond Nattress",
    "wof:placetype":"venue"
},
  "geometry": {"coordinates":[-76.80526,40.359824],"type":"Point"}
}