{
  "type": "Feature",
  "properties": {
    "iso:country":"US",
    "sg:address":"916 Gettysburg Pike",
    "sg:city":"Mechanicsburg",
    "sg:classifiers":[
        {
            "category":"Retail",
            "subcategory":"Veterinary Services",
            "type":"Services"
        }
    ],
    "sg:phone":"+1   ",
    "sg:postcode":"17055",
    "sg:province":"PA",
    "sg:tags":[
        "hospital",
        "animal"
    ],
    "wof:name":"Tri-County Animal Hospital",
    "wof:placetype":"venue"
},
  "geometry": {"coordinates":[-77.00464599999999,40.161379],"type":"Point"}
}