{
  "type": "Feature",
  "properties": {
    "iso:country":"US",
    "sg:address":"659 E Street Rd",
    "sg:city":"Southampton",
    "sg:classifiers":[
        {
            "category":"Retail",
            "subcategory":"Funeral Services",
            "type":"Services"
        }
    ],
    "sg:phone":"+1 215 357 1101",
    "sg:postcode":"18966",
    "sg:province":"PA",
    "sg:tags":[
        "crematory"
    ],
    "wof:name":"Delaware Valley Crematory Co",
    "wof:placetype":"venue"
},
  "geometry": {"coordinates":[-75.04459300000001,40.175121],"type":"Point"}
}