{
  "type": "Feature",
  "properties": {
    "addr:full":"506 N State St Clarks Summit PA 18411",
    "addr:housenumber":"506",
    "addr:postcode":"18411",
    "addr:street":"N State St",
    "iso:country":"US",
    "sg:address":"506 N State St",
    "sg:city":"Clarks Summit",
    "sg:classifiers":[
        {
            "category":"Shopping",
            "subcategory":"Gifts & Souvenirs",
            "type":"Retail Goods"
        }
    ],
    "sg:phone":"+1 570 585 0948",
    "sg:postcode":"18411",
    "sg:province":"PA",
    "sg:tags":[
        "shop"
    ],
    "sg:website":"www.equineimpressions.com",
    "wof:name":"Equine Impressions Inc",
    "wof:placetype":"venue"
},
  "geometry": {"coordinates":[-75.708799,41.499159],"type":"Point"}
}