{
  "type": "Feature",
  "properties": {
    "iso:country":"US",
    "sg:address":"600 Stones Crossing Rd",
    "sg:city":"Easton",
    "sg:classifiers":[
        {
            "category":"Manufacturing",
            "subcategory":"Buildings",
            "type":"Manufacturing & Wholesale Goods"
        },
        {
            "category":"Building & Trades",
            "subcategory":"Construction",
            "type":"Services"
        }
    ],
    "sg:phone":"+1 484 560 1827",
    "sg:postcode":"18045",
    "sg:province":"PA",
    "sg:tags":[
        "home",
        "builder",
        "contractor"
    ],
    "wof:name":"Complete Home Restorations",
    "wof:placetype":"venue"
},
  "geometry": {"coordinates":[-75.26937100000001,40.669479],"type":"Point"}
}