{
  "type": "Feature",
  "properties": {
    "iso:country":"US",
    "sg:address":"39 E 3rd St",
    "sg:city":"Williamsport",
    "sg:classifiers":[
        {
            "category":"Wholesale",
            "subcategory":"Medical Equipment & Supplies",
            "type":"Manufacturing & Wholesale Goods"
        }
    ],
    "sg:phone":"+1 570 322 0656",
    "sg:postcode":"17701",
    "sg:province":"PA",
    "sg:tags":[
        "hospital",
        "surgical"
    ],
    "wof:name":"Dice Surgical",
    "wof:placetype":"venue"
},
  "geometry": {"coordinates":[-76.99958599999999,41.241894],"type":"Point"}
}