{
  "type": "Feature",
  "properties": {
    "iso:country":"US",
    "sg:address":"24564 State Rte 18",
    "sg:city":"Springboro",
    "sg:classifiers":[
        {
            "category":"Retail",
            "subcategory":"Auto Repair",
            "type":"Services"
        }
    ],
    "sg:phone":"+1 814 587 2691",
    "sg:postcode":"16435",
    "sg:province":"PA",
    "sg:tags":[
        "automotive",
        "general"
    ],
    "wof:name":"Eschweilers Automotive",
    "wof:placetype":"venue"
},
  "geometry": {"coordinates":[-80.371578,41.806319],"type":"Point"}
}