{
  "type": "Feature",
  "properties": {
    "iso:country":"US",
    "sg:address":"645 N 24th St",
    "sg:city":"Philadelphia",
    "sg:classifiers":[
        {
            "category":"Health Services",
            "subcategory":"Doctor",
            "type":"Services"
        }
    ],
    "sg:phone":"+1 215 232 1107",
    "sg:postcode":"19130",
    "sg:province":"PA",
    "wof:name":"Edelstein Merle MD",
    "wof:placetype":"venue"
},
  "geometry": {"coordinates":[-75.176912,39.966898],"type":"Point"}
}