{
  "type": "Feature",
  "properties": {
    "iso:country":"US",
    "sg:address":"12 W Green St",
    "sg:city":"Mechanicsburg",
    "sg:classifiers":[
        {
            "category":"Retail",
            "subcategory":"Car Wash",
            "type":"Services"
        },
        {
            "category":"Wholesale",
            "subcategory":"Auto Parts",
            "type":"Manufacturing & Wholesale Goods"
        }
    ],
    "sg:phone":"+1 717 691 8316",
    "sg:postcode":"17055",
    "sg:province":"PA",
    "sg:tags":[
        "automotive",
        "detailing",
        "detail",
        "clean",
        "automobile"
    ],
    "wof:name":"Rick's Clean Car Systems",
    "wof:placetype":"venue"
},
  "geometry": {"coordinates":[-77.009804,40.215401],"type":"Point"}
}