{
  "type": "Feature",
  "properties": {
    "iso:country":"US",
    "sg:address":"363 Main St",
    "sg:city":"Mc Sherrystown",
    "sg:classifiers":[
        {
            "category":"Organizations",
            "subcategory":"Membership Organization",
            "type":"Services"
        }
    ],
    "sg:phone":"+1 717 630 2454",
    "sg:postcode":"17344",
    "sg:province":"PA",
    "wof:name":"John T Reily Historical Socty",
    "wof:placetype":"venue"
},
  "geometry": {"coordinates":[-77.01956300000001,39.803763],"type":"Point"}
}