{
  "type": "Feature",
  "properties": {
    "iso:country":"US",
    "sg:address":"945 Liberty Ave",
    "sg:city":"Pittsburgh",
    "sg:classifiers":[
        {
            "category":"Professional",
            "subcategory":"Computer Services",
            "type":"Services"
        }
    ],
    "sg:phone":"+1 412 391 4333",
    "sg:postcode":"15222",
    "sg:province":"PA",
    "sg:tags":[
        "information",
        "recovery",
        "processing",
        "system",
        "equipment",
        "data",
        "retrieval"
    ],
    "wof:name":"Renovation Information Network",
    "wof:placetype":"venue"
},
  "geometry": {"coordinates":[-79.99640100000001,40.443325],"type":"Point"}
}