{
  "type": "Feature",
  "properties": {
    "iso:country":"US",
    "sg:address":"442 Acosta Rd",
    "sg:city":"Friedens",
    "sg:classifiers":[
        {
            "category":"Retail",
            "subcategory":"Auto Repair",
            "type":"Services"
        }
    ],
    "sg:phone":"+1 814 629 6530",
    "sg:postcode":"15541",
    "sg:province":"PA",
    "sg:tags":[
        "repairing",
        "automobile"
    ],
    "wof:name":"Bailey Auto & Repair",
    "wof:placetype":"venue"
},
  "geometry": {"coordinates":[-79.084552,40.115977],"type":"Point"}
}