{
  "type": "Feature",
  "properties": {
    "iso:country":"US",
    "sg:address":"845 Steel St",
    "sg:city":"Johnstown",
    "sg:classifiers":[
        {
            "category":"Food & Beverages",
            "subcategory":"Fruits & Vegetables",
            "type":"Retail Goods"
        }
    ],
    "sg:phone":"+1 814 535 4817",
    "sg:postcode":"15901",
    "sg:province":"PA",
    "sg:tags":[
        "produce"
    ],
    "wof:name":"Rose's Market",
    "wof:placetype":"venue"
},
  "geometry": {"coordinates":[-78.90767700000001,40.326262],"type":"Point"}
}