{
  "type": "Feature",
  "properties": {
    "addr:full":"65 Penn St Lenhartsville PA 19534",
    "addr:housenumber":"65",
    "addr:postcode":"19534",
    "addr:street":"Penn St",
    "iso:country":"US",
    "sg:address":"65 Penn St",
    "sg:city":"Lenhartsville",
    "sg:classifiers":[
        {
            "category":"Food & Beverages",
            "subcategory":"Meat & Fish",
            "type":"Retail Goods"
        }
    ],
    "sg:phone":"+1 610 562 2231",
    "sg:postcode":"19534",
    "sg:province":"PA",
    "sg:website":"www.petersbrosmeats.com",
    "wof:name":"Peters Brothers Meat Market",
    "wof:placetype":"venue"
},
  "geometry": {"coordinates":[-75.89107799999999,40.573565],"type":"Point"}
}