{
  "type": "Feature",
  "properties": {
    "addr:full":"345 York Rd Warminster PA 18974",
    "addr:housenumber":"345",
    "addr:postcode":"18974",
    "addr:street":"York Rd",
    "iso:country":"US",
    "sg:address":"345 York Rd",
    "sg:city":"Warminster",
    "sg:classifiers":[
        {
            "category":"Autos & Motor Vehicles",
            "subcategory":"Automobile Sales",
            "type":"Retail Goods"
        }
    ],
    "sg:phone":"+1   ",
    "sg:postcode":"18974",
    "sg:province":"PA",
    "sg:tags":[
        "used"
    ],
    "wof:name":"Richard Vogel",
    "wof:placetype":"venue"
},
  "geometry": {"coordinates":[-75.10120999999999,40.198949],"type":"Point"}
}