{
  "type": "Feature",
  "properties": {
    "addr:full":"1708 E Lancaster Ave Paoli PA 19301",
    "addr:housenumber":"1708",
    "addr:postcode":"19301",
    "addr:street":"E Lancaster Ave",
    "iso:country":"US",
    "sg:address":"1708 E Lancaster Ave",
    "sg:city":"Paoli",
    "sg:classifiers":[
        {
            "category":"Professional",
            "subcategory":"Advertising",
            "type":"Services"
        }
    ],
    "sg:phone":"+1 610 296 4180",
    "sg:postcode":"19301",
    "sg:province":"PA",
    "sg:tags":[
        "mailing",
        "shipping"
    ],
    "wof:name":"Mail Boxes Etc",
    "wof:placetype":"venue"
},
  "geometry": {"coordinates":[-75.469523,40.042317],"type":"Point"}
}