{
  "type": "Feature",
  "properties": {
    "iso:country":"US",
    "sg:address":"18 Gay St",
    "sg:city":"Christiana",
    "sg:classifiers":[
        {
            "category":"Personal",
            "subcategory":"Beauty Salon",
            "type":"Services"
        }
    ],
    "sg:phone":"+1 610 593 6287",
    "sg:postcode":"17509",
    "sg:province":"PA",
    "wof:name":"Julia Wonder Beauty Salon",
    "wof:placetype":"venue"
},
  "geometry": {"coordinates":[-75.995515,39.954439],"type":"Point"}
}