{
  "type": "Feature",
  "properties": {
    "iso:country":"US",
    "sg:address":"606 W Oak Ln",
    "sg:city":"Glenolden",
    "sg:classifiers":[
        {
            "category":"Wholesale",
            "subcategory":"Machinery & Supplies",
            "type":"Manufacturing & Wholesale Goods"
        }
    ],
    "sg:phone":"+1 610 583 3055",
    "sg:postcode":"19036",
    "sg:province":"PA",
    "sg:tags":[
        "contractor"
    ],
    "wof:name":"Mac Machine",
    "wof:placetype":"venue"
},
  "geometry": {"coordinates":[-75.289928,39.9114],"type":"Point"}
}