{
  "type": "Feature",
  "properties": {
    "iso:country":"US",
    "sg:address":"6612 Castor Ave",
    "sg:city":"Philadelphia",
    "sg:classifiers":[
        {
            "category":"Restaurant",
            "type":"Food & Drink"
        }
    ],
    "sg:phone":"+1 215 728 0277",
    "sg:postcode":"19149",
    "sg:province":"PA",
    "sg:tags":[
        "eating"
    ],
    "wof:name":"China City Restaurant",
    "wof:placetype":"venue"
},
  "geometry": {"coordinates":[-75.074651,40.042346],"type":"Point"}
}