{
  "type": "Feature",
  "properties": {
    "iso:country":"US",
    "sg:address":"1663 N Forge Mountain Dr",
    "sg:city":"Phoenixville",
    "sg:classifiers":[
        {
            "category":"Wholesale",
            "subcategory":"Furniture",
            "type":"Manufacturing & Wholesale Goods"
        }
    ],
    "sg:phone":"+1 610 783 5500",
    "sg:postcode":"19481",
    "sg:province":"PA",
    "wof:name":"Contrax Group",
    "wof:placetype":"venue"
},
  "geometry": {"coordinates":[-75.47619899999999,40.091015],"type":"Point"}
}