{
  "type": "Feature",
  "properties": {
    "iso:country":"US",
    "sg:address":"324 Pennsylvania Ave W",
    "sg:city":"Warren",
    "sg:classifiers":[
        {
            "category":"Building & Trades",
            "subcategory":"Construction",
            "type":"Services"
        }
    ],
    "sg:phone":"+1   ",
    "sg:postcode":"16365",
    "sg:province":"PA",
    "sg:tags":[
        "concrete",
        "contractor"
    ],
    "wof:name":"John Anderson Construction",
    "wof:placetype":"venue"
},
  "geometry": {"coordinates":[-79.147857,41.844922],"type":"Point"}
}