{
  "type": "Feature",
  "properties": {
    "addr:full":"23 Cowan St Pittsburgh PA 15211",
    "addr:housenumber":"23",
    "addr:postcode":"15211",
    "addr:street":"Cowan St",
    "iso:country":"US",
    "sg:address":"23 Cowan St",
    "sg:city":"Pittsburgh",
    "sg:classifiers":[
        {
            "category":"Building & Trades",
            "subcategory":"Construction",
            "type":"Services"
        }
    ],
    "sg:phone":"+1 412 279 9826",
    "sg:postcode":"15211",
    "sg:province":"PA",
    "sg:tags":[
        "general",
        "contractor"
    ],
    "wof:name":"Colt Building & Maintenance",
    "wof:placetype":"venue"
},
  "geometry": {"coordinates":[-80.00946399999999,40.427558],"type":"Point"}
}