{
  "type": "Feature",
  "properties": {
    "iso:country":"US",
    "sg:address":"104 W Wyoming Ave",
    "sg:city":"Philadelphia",
    "sg:classifiers":[
        {
            "category":"Personal",
            "subcategory":"Beauty Salon",
            "type":"Services"
        }
    ],
    "sg:phone":"+1 215 329 5959",
    "sg:postcode":"19140",
    "sg:province":"PA",
    "sg:tags":[
        "unisex",
        "hair"
    ],
    "wof:name":"Stylistic Unisex Hair Salon",
    "wof:placetype":"venue"
},
  "geometry": {"coordinates":[-75.12545900000001,40.021604],"type":"Point"}
}