{
  "type": "Feature",
  "properties": {
    "iso:country":"US",
    "sg:address":"1428 N Broad St",
    "sg:city":"Philadelphia",
    "sg:classifiers":[
        {
            "category":"Building & Trades",
            "subcategory":"Cleaning & Sanitation",
            "type":"Services"
        }
    ],
    "sg:phone":"+1 215 765 0761",
    "sg:postcode":"19121",
    "sg:province":"PA",
    "sg:tags":[
        "janitorial"
    ],
    "sg:website":"http://www.servicemasterclean.com/",
    "wof:name":"Service Master True Image",
    "wof:placetype":"venue"
},
  "geometry": {"coordinates":[-75.15869600000001,39.974857],"type":"Point"}
}