{
  "type": "Feature",
  "properties": {
    "iso:country":"US",
    "sg:address":"265 S 19th St",
    "sg:city":"Philadelphia",
    "sg:classifiers":[
        {
            "category":"Personal",
            "type":"Services"
        }
    ],
    "sg:phone":"+1 215 735 8132",
    "sg:postcode":"19103",
    "sg:province":"PA",
    "wof:name":"AIM Investments Inc",
    "wof:placetype":"venue"
},
  "geometry": {"coordinates":[-75.17267,39.94798],"type":"Point"}
}