{
  "type": "Feature",
  "properties": {
    "iso:country":"US",
    "sg:address":"50 N Lee St",
    "sg:city":"Hellam",
    "sg:classifiers":[
        {
            "category":"Education",
            "subcategory":"School",
            "type":"Public Place"
        }
    ],
    "sg:phone":"+1 717 757 9682",
    "sg:postcode":"17406",
    "sg:province":"PA",
    "sg:tags":[
        "elementary"
    ],
    "wof:name":"Kreutz Creek Elementary School",
    "wof:placetype":"venue"
},
  "geometry": {"coordinates":[-76.61072900000001,40.004469],"type":"Point"}
}