{
  "type": "Feature",
  "properties": {
    "iso:country":"US",
    "sg:address":"115 North St Apt 105",
    "sg:city":"Harrisburg",
    "sg:classifiers":[
        {
            "category":"Real Estate",
            "subcategory":"Real Estate Operator",
            "type":"Services"
        }
    ],
    "sg:phone":"+1 717 238 2800",
    "sg:postcode":"17101",
    "sg:province":"PA",
    "sg:tags":[
        "apartment"
    ],
    "wof:name":"Grayco Apartments",
    "wof:placetype":"venue"
},
  "geometry": {"coordinates":[-76.889,40.263699],"type":"Point"}
}