{
  "type": "Feature",
  "properties": {
    "iso:country":"US",
    "sg:address":"339 Main St",
    "sg:city":"Royersford",
    "sg:classifiers":[
        {
            "category":"Building & Trades",
            "subcategory":"Construction",
            "type":"Services"
        }
    ],
    "sg:phone":"+1 610 792 4941",
    "sg:postcode":"19468",
    "sg:province":"PA",
    "sg:tags":[
        "house",
        "improvement",
        "home"
    ],
    "wof:name":"C & C Improvements",
    "wof:placetype":"venue"
},
  "geometry": {"coordinates":[-75.539524,40.18496],"type":"Point"}
}