{
  "type": "Feature",
  "properties": {
    "iso:country":"US",
    "sg:address":"129 Logans Ferry Rd",
    "sg:city":"New Kensington",
    "sg:classifiers":[
        {
            "category":"Health Services",
            "subcategory":"Health Practitioner",
            "type":"Services"
        }
    ],
    "sg:phone":"+1 724 339 7725",
    "sg:postcode":"15068",
    "sg:province":"PA",
    "sg:tags":[
        "therapist",
        "physical"
    ],
    "wof:name":"Westarm Therapy Svc",
    "wof:placetype":"venue"
},
  "geometry": {"coordinates":[-79.75991500000001,40.545282],"type":"Point"}
}