{
  "type": "Feature",
  "properties": {
    "iso:country":"US",
    "sg:address":"74 Woodlawn Rd",
    "sg:city":"Warminster",
    "sg:classifiers":[
        {
            "category":"Professional",
            "subcategory":"Computer Services",
            "type":"Services"
        }
    ],
    "sg:phone":"+1   ",
    "sg:postcode":"18974",
    "sg:province":"PA",
    "sg:tags":[
        "prepackaged",
        "school",
        "processing",
        "datum",
        "software"
    ],
    "wof:name":"Solomon III Sftwr-Lyal Bkkping",
    "wof:placetype":"venue"
},
  "geometry": {"coordinates":[-75.084744,40.182279],"type":"Point"}
}