{
  "type": "Feature",
  "properties": {
    "iso:country":"US",
    "sg:address":"104 Airport Rd",
    "sg:city":"Coatesville",
    "sg:classifiers":[
        {
            "category":"Personal",
            "subcategory":"Beauty Salon",
            "type":"Services"
        }
    ],
    "sg:phone":"+1 610 380 9201",
    "sg:postcode":"19320",
    "sg:province":"PA",
    "sg:tags":[
        "shop"
    ],
    "wof:name":"Limited Nail Salon",
    "wof:placetype":"venue"
},
  "geometry": {"coordinates":[-75.866951,39.983611],"type":"Point"}
}