{
  "type": "Feature",
  "properties": {
    "iso:country":"US",
    "sg:address":"155 W Market St",
    "sg:city":"York",
    "sg:classifiers":[
        {
            "category":"Banks & Credit Unions",
            "subcategory":"Investment Brokerage",
            "type":"Services"
        }
    ],
    "sg:phone":"+1 717 812 8380",
    "sg:postcode":"17401",
    "sg:province":"PA",
    "sg:tags":[
        "advisory"
    ],
    "wof:name":"Brynes & Co",
    "wof:placetype":"venue"
},
  "geometry": {"coordinates":[-76.730751,39.961654],"type":"Point"}
}