{
  "type": "Feature",
  "properties": {
    "addr:full":"8600 Cathedral Cir Philadelphia PA 19128",
    "addr:housenumber":"8600",
    "addr:postcode":"19128",
    "addr:street":"Cathedral Cir",
    "iso:country":"US",
    "sg:address":"8600 Cathedral Cir",
    "sg:city":"Philadelphia",
    "sg:classifiers":[
        {
            "category":"Shopping",
            "subcategory":"Photographic Equipment",
            "type":"Retail Goods"
        }
    ],
    "sg:phone":"+1   ",
    "sg:postcode":"19128",
    "sg:province":"PA",
    "sg:tags":[
        "camera",
        "supply"
    ],
    "wof:name":"Ritz Camera Centers Inc",
    "wof:placetype":"venue"
},
  "geometry": {"coordinates":[-75.24342799999999,40.063001],"type":"Point"}
}