{
  "type": "Feature",
  "properties": {
    "addr:full":"2220 Fairmount Ave Philadelphia PA 19130",
    "addr:housenumber":"2220",
    "addr:postcode":"19130",
    "addr:street":"Fairmount Ave",
    "iso:country":"US",
    "sg:address":"2220 Fairmount Ave",
    "sg:city":"Philadelphia",
    "sg:classifiers":[
        {
            "category":"Real Estate",
            "subcategory":"Developer",
            "type":"Services"
        }
    ],
    "sg:phone":"+1   ",
    "sg:postcode":"19130",
    "sg:province":"PA",
    "wof:name":"Rga Research & Development Co",
    "wof:placetype":"venue"
},
  "geometry": {"coordinates":[-75.175172,39.967264],"type":"Point"}
}