{
  "type": "Feature",
  "properties": {
    "iso:country":"US",
    "sg:address":"302 Chestnut St",
    "sg:city":"Marcus Hook",
    "sg:classifiers":[
        {
            "category":"Manufacturing",
            "subcategory":"Metals",
            "type":"Manufacturing & Wholesale Goods"
        }
    ],
    "sg:phone":"+1   ",
    "sg:postcode":"19061",
    "sg:province":"PA",
    "sg:tags":[
        "coating",
        "plastic"
    ],
    "wof:name":"Brumbaugh Industries Inc",
    "wof:placetype":"venue"
},
  "geometry": {"coordinates":[-75.427785,39.834994],"type":"Point"}
}