{
  "type": "Feature",
  "properties": {
    "addr:full":"407 Center St Danville PA 17821",
    "addr:housenumber":"407",
    "addr:postcode":"17821",
    "addr:street":"Center St",
    "iso:country":"US",
    "sg:address":"407 Center St",
    "sg:city":"Danville",
    "sg:classifiers":[
        {
            "category":"Government",
            "subcategory":"Fire Station",
            "type":"Public Place"
        }
    ],
    "sg:phone":"+1   ",
    "sg:postcode":"17821",
    "sg:province":"PA",
    "sg:tags":[
        "protection"
    ],
    "wof:name":"Good Will Fire Co 4",
    "wof:placetype":"venue"
},
  "geometry": {"coordinates":[-76.610924,40.966088],"type":"Point"}
}