{
  "type": "Feature",
  "properties": {
    "iso:country":"US",
    "sg:address":"43 Philadelphia Ave",
    "sg:city":"Waynesboro",
    "sg:classifiers":[
        {
            "category":"Professional",
            "subcategory":"Accounting & Tax Preparation",
            "type":"Services"
        }
    ],
    "sg:phone":"+1 717 762 3285",
    "sg:postcode":"17268",
    "sg:province":"PA",
    "wof:name":"Financial Services Unlimited",
    "wof:placetype":"venue"
},
  "geometry": {"coordinates":[-77.581523,39.753793],"type":"Point"}
}