{
  "type": "Feature",
  "properties": {
    "addr:full":"1009 Davis Rd Ambler PA 19002",
    "addr:housenumber":"1009",
    "addr:postcode":"19002",
    "addr:street":"Davis Rd",
    "iso:country":"US",
    "sg:address":"1009 Davis Rd",
    "sg:city":"Ambler",
    "sg:classifiers":[
        {
            "category":"Building & Trades",
            "subcategory":"Construction",
            "type":"Services"
        }
    ],
    "sg:phone":"+1 215 643 1985",
    "sg:postcode":"19002",
    "sg:province":"PA",
    "sg:tags":[
        "roofing",
        "contractor"
    ],
    "wof:name":"Peter A Nocero",
    "wof:placetype":"venue"
},
  "geometry": {"coordinates":[-75.21425600000001,40.178328],"type":"Point"}
}