{
  "type": "Feature",
  "properties": {
    "iso:country":"US",
    "sg:address":"1449 Beaver Hill Rd",
    "sg:city":"Chester Springs",
    "sg:classifiers":[
        {
            "category":"Building & Trades",
            "subcategory":"Construction",
            "type":"Services"
        }
    ],
    "sg:phone":"+1 610 827 7139",
    "sg:postcode":"19425",
    "sg:province":"PA",
    "sg:tags":[
        "home",
        "builder"
    ],
    "wof:name":"Woodstone Homes",
    "wof:placetype":"venue"
},
  "geometry": {"coordinates":[-75.611313,40.131957],"type":"Point"}
}