{
  "type": "Feature",
  "properties": {
    "iso:country":"US",
    "sg:address":"110 Chestnut St",
    "sg:city":"Dunmore",
    "sg:classifiers":[
        {
            "category":"Organizations",
            "subcategory":"Community Association",
            "type":"Services"
        }
    ],
    "sg:phone":"+1 570 961 1646",
    "sg:postcode":"18512",
    "sg:province":"PA",
    "sg:tags":[
        "club"
    ],
    "wof:name":"Veterans Of Foreign Wars",
    "wof:placetype":"venue"
},
  "geometry": {"coordinates":[-75.62997,41.421051],"type":"Point"}
}