{
  "type": "Feature",
  "properties": {
    "addr:full":"234 Kline Rd Somerset PA 15501",
    "addr:housenumber":"234",
    "addr:postcode":"15501",
    "addr:street":"Kline Rd",
    "iso:country":"US",
    "sg:address":"234 Kline Rd",
    "sg:city":"Somerset",
    "sg:classifiers":[
        {
            "category":"Freight",
            "type":"Transportation"
        }
    ],
    "sg:phone":"+1 814 445 3067",
    "sg:postcode":"15501",
    "sg:province":"PA",
    "sg:tags":[
        "water",
        "delivery",
        "company",
        "oil",
        "for"
    ],
    "wof:name":"Keystone Vacuum Inc",
    "wof:placetype":"venue"
},
  "geometry": {"coordinates":[-79.042907,40.045458],"type":"Point"}
}