{
  "type": "Feature",
  "properties": {
    "iso:country":"US",
    "sg:address":"321 S Lang Ave",
    "sg:city":"Pittsburgh",
    "sg:classifiers":[
        {
            "category":"Health Services",
            "subcategory":"Clinic",
            "type":"Services"
        }
    ],
    "sg:phone":"+1 412 371 7326",
    "sg:postcode":"15208",
    "sg:province":"PA",
    "sg:tags":[
        "specialty",
        "outpatient"
    ],
    "wof:name":"Janice Kelly",
    "wof:placetype":"venue"
},
  "geometry": {"coordinates":[-79.905469,40.447513],"type":"Point"}
}