{
  "type": "Feature",
  "properties": {
    "iso:country":"US",
    "sg:address":"338 Congo-Niantic Rd",
    "sg:city":"Barto",
    "sg:classifiers":[
        {
            "category":"Autos & Motor Vehicles",
            "subcategory":"Auto Supplies",
            "type":"Retail Goods"
        }
    ],
    "sg:phone":"+1 610 845 2357",
    "sg:postcode":"19504",
    "sg:province":"PA",
    "sg:tags":[
        "automobile",
        "parts"
    ],
    "wof:name":"F A Paluba Supply Co",
    "wof:placetype":"venue"
},
  "geometry": {"coordinates":[-75.573144,40.375845],"type":"Point"}
}