{
  "type": "Feature",
  "properties": {
    "iso:country":"US",
    "sg:address":"1528 Walnut St",
    "sg:city":"Philadelphia",
    "sg:classifiers":[
        {
            "category":"Professional",
            "subcategory":"Management & Consulting",
            "type":"Services"
        }
    ],
    "sg:phone":"+1   ",
    "sg:postcode":"19102",
    "sg:province":"PA",
    "sg:tags":[
        "benefit",
        "association"
    ],
    "wof:name":"Peba",
    "wof:placetype":"venue"
},
  "geometry": {"coordinates":[-75.167427,39.949654],"type":"Point"}
}