{
  "type": "Feature",
  "properties": {
    "iso:country":"US",
    "sg:address":"1525 W Dauphin St",
    "sg:city":"Philadelphia",
    "sg:classifiers":[
        {
            "category":"Retail",
            "subcategory":"Funeral Services",
            "type":"Services"
        }
    ],
    "sg:phone":"+1 215 223 3133",
    "sg:postcode":"19132",
    "sg:province":"PA",
    "sg:tags":[
        "cemetery"
    ],
    "wof:name":"Ray George E Funeral Director",
    "wof:placetype":"venue"
},
  "geometry": {"coordinates":[-75.15860000000001,39.988098],"type":"Point"}
}