{
  "type": "Feature",
  "properties": {
    "addr:full":"3512 State Rte 257 Seneca PA 16346",
    "addr:housenumber":"3512",
    "addr:postcode":"16346",
    "addr:street":"State Rte 257",
    "iso:country":"US",
    "sg:address":"3512 State Rte 257",
    "sg:city":"Seneca",
    "sg:classifiers":[
        {
            "category":"Professional",
            "type":"Services"
        },
        {
            "category":"Health Services",
            "subcategory":"Doctor",
            "type":"Services"
        }
    ],
    "sg:phone":"+1 814 677 2262",
    "sg:postcode":"16346",
    "sg:province":"PA",
    "sg:tags":[
        "physician",
        "surgeon"
    ],
    "wof:name":"Chest Medicine",
    "wof:placetype":"venue"
},
  "geometry": {"coordinates":[-79.70299900000001,41.389005],"type":"Point"}
}