{
  "type": "Feature",
  "properties": {
    "iso:country":"US",
    "sg:address":"13015 Ferguson Valley Rd",
    "sg:city":"Burnham",
    "sg:classifiers":[
        {
            "category":"Travel",
            "subcategory":"Hotels & Motels",
            "type":"Entertainment"
        }
    ],
    "sg:phone":"+1 717 248 4961",
    "sg:postcode":"17009",
    "sg:province":"PA",
    "sg:tags":[
        "lodging"
    ],
    "sg:website":"http://www.qualityinn.com/hotel-burnham-pennsylvania-PA234",
    "wof:name":"Quality Inn and Suites Burnham",
    "wof:placetype":"venue"
},
  "geometry": {"coordinates":[-77.581959,40.62981],"type":"Point"}
}