{
  "type": "Feature",
  "properties": {
    "iso:country":"US",
    "sg:address":"101 Old York Rd",
    "sg:city":"Jenkintown",
    "sg:classifiers":[
        {
            "category":"Banks & Credit Unions",
            "subcategory":"Investment Brokerage",
            "type":"Services"
        }
    ],
    "sg:phone":"+1 215 745 1768",
    "sg:postcode":"19046",
    "sg:province":"PA",
    "sg:tags":[
        "advisory",
        "financial"
    ],
    "wof:name":"Kevin Kim",
    "wof:placetype":"venue"
},
  "geometry": {"coordinates":[-75.127354,40.088514],"type":"Point"}
}