{
  "type": "Feature",
  "properties": {
    "addr:full":"383 N Main St Carrolltown PA 15722",
    "addr:housenumber":"383",
    "addr:postcode":"15722",
    "addr:street":"N Main St",
    "iso:country":"US",
    "sg:address":"383 N Main St",
    "sg:city":"Carrolltown",
    "sg:classifiers":[
        {
            "category":"Bars & Pubs",
            "type":"Food & Drink"
        }
    ],
    "sg:phone":"+1 814 344 8201",
    "sg:postcode":"15722",
    "sg:province":"PA",
    "wof:name":"Jerry's Tavern",
    "wof:placetype":"venue"
},
  "geometry": {"coordinates":[-78.7101,40.611894],"type":"Point"}
}