{
  "type": "Feature",
  "properties": {
    "iso:country":"US",
    "sg:address":"4300 N 16th St",
    "sg:city":"Philadelphia",
    "sg:classifiers":[
        {
            "category":"Food & Beverages",
            "subcategory":"Groceries & Convenience Stores",
            "type":"Retail Goods"
        }
    ],
    "sg:phone":"+1 215 324 5010",
    "sg:postcode":"19140",
    "sg:province":"PA",
    "sg:tags":[
        "grocer"
    ],
    "wof:name":"Noeliza Mini Market",
    "wof:placetype":"venue"
},
  "geometry": {"coordinates":[-75.152635,40.018921],"type":"Point"}
}