{
  "type": "Feature",
  "properties": {
    "iso:country":"US",
    "sg:address":"117 E Askren St",
    "sg:city":"Uniontown",
    "sg:classifiers":[
        {
            "category":"Retail",
            "subcategory":"Repair Shop",
            "type":"Services"
        },
        {
            "category":"Manufacturing",
            "subcategory":"Tools & Machinery",
            "type":"Manufacturing & Wholesale Goods"
        }
    ],
    "sg:phone":"+1 724 437 5162",
    "sg:postcode":"15401",
    "sg:province":"PA",
    "sg:tags":[
        "electric",
        "motor"
    ],
    "wof:name":"Bethel Electric Motor Service",
    "wof:placetype":"venue"
},
  "geometry": {"coordinates":[-79.717472,39.909099],"type":"Point"}
}