{
  "type": "Feature",
  "properties": {
    "iso:country":"US",
    "sg:address":"1209 State Rte 885",
    "sg:city":"Clairton",
    "sg:classifiers":[
        {
            "category":"Health Services",
            "subcategory":"Doctor",
            "type":"Services"
        }
    ],
    "sg:phone":"+1   ",
    "sg:postcode":"15025",
    "sg:province":"PA",
    "wof:name":"John E Fallon Jr DMD",
    "wof:placetype":"venue"
},
  "geometry": {"coordinates":[-79.917366,40.315598],"type":"Point"}
}