{
  "type": "Feature",
  "properties": {
    "iso:country":"US",
    "sg:address":"1723 Perry Hwy",
    "sg:city":"Portersville",
    "sg:classifiers":[
        {
            "category":"Manufacturing",
            "subcategory":"Metals",
            "type":"Manufacturing & Wholesale Goods"
        },
        {
            "category":"Retail",
            "subcategory":"Repair Shop",
            "type":"Services"
        }
    ],
    "sg:phone":"+1 724 368 8725",
    "sg:postcode":"16051",
    "sg:province":"PA",
    "sg:tags":[
        "mfg",
        "industrial",
        "valve",
        "supply"
    ],
    "sg:website":"www.portersvillevalve.com",
    "wof:name":"Portersville Valve Company",
    "wof:placetype":"venue"
},
  "geometry": {"coordinates":[-80.156791,40.960143],"type":"Point"}
}