{
  "type": "Feature",
  "properties": {
    "iso:country":"US",
    "sg:address":"3446 Charlotte St",
    "sg:city":"Pittsburgh",
    "sg:classifiers":[
        {
            "category":"Professional",
            "subcategory":"Advertising",
            "type":"Services"
        }
    ],
    "sg:phone":"+1 412 688 0444",
    "sg:postcode":"15201",
    "sg:province":"PA",
    "sg:tags":[
        "distribution"
    ],
    "wof:name":"Apple Books",
    "wof:placetype":"venue"
},
  "geometry": {"coordinates":[-79.96747999999999,40.463673],"type":"Point"}
}