{
  "type": "Feature",
  "properties": {
    "iso:country":"US",
    "sg:address":"1 Boathouse Row",
    "sg:city":"Philadelphia",
    "sg:classifiers":[
        {
            "category":"Restaurant",
            "type":"Food & Drink"
        }
    ],
    "sg:menulink":"http://www.allmenus.com/pa/philadelphia/261742-water-works/menu/",
    "sg:phone":"+1 215 236 9000",
    "sg:postcode":"19130",
    "sg:province":"PA",
    "sg:tags":[
        "american"
    ],
    "wof:name":"Water Works",
    "wof:placetype":"venue"
},
  "geometry": {"coordinates":[-75.186149,39.96946],"type":"Point"}
}