{
  "type": "Feature",
  "properties": {
    "iso:country":"US",
    "sg:address":"1891 Santa Barbara Dr",
    "sg:city":"Lancaster",
    "sg:classifiers":[
        {
            "category":"Professional",
            "subcategory":"Management & Consulting",
            "type":"Services"
        }
    ],
    "sg:phone":"+1 717 519 1780",
    "sg:postcode":"17601",
    "sg:province":"PA",
    "sg:tags":[
        "consultant"
    ],
    "sg:website":"http://www.apexasset.com",
    "wof:name":"Apex Asset Management",
    "wof:placetype":"venue"
},
  "geometry": {"coordinates":[-76.307638,40.076491],"type":"Point"}
}