{
  "type": "Feature",
  "properties": {
    "iso:country":"US",
    "sg:address":"340 Doyle St",
    "sg:city":"Doylestown",
    "sg:classifiers":[
        {
            "category":"Professional",
            "type":"Services"
        }
    ],
    "sg:phone":"+1 215 345 8405",
    "sg:postcode":"18901",
    "sg:province":"PA",
    "sg:tags":[
        "establishment"
    ],
    "wof:name":"PHL Inc",
    "wof:placetype":"venue"
},
  "geometry": {"coordinates":[-75.139183,40.309579],"type":"Point"}
}