{
  "type": "Feature",
  "properties": {
    "iso:country":"US",
    "sg:address":"1030 Plymouth Rd",
    "sg:city":"York",
    "sg:classifiers":[
        {
            "category":"Health Services",
            "subcategory":"Doctor",
            "type":"Services"
        }
    ],
    "sg:phone":"+1   ",
    "sg:postcode":"17402",
    "sg:province":"PA",
    "sg:tags":[
        "medical"
    ],
    "wof:name":"Chen Douglas N MD",
    "wof:placetype":"venue"
},
  "geometry": {"coordinates":[-76.666526,39.959157],"type":"Point"}
}