{
  "type": "Feature",
  "properties": {
    "iso:country":"US",
    "sg:address":"1828 E 3rd St",
    "sg:city":"Williamsport",
    "sg:classifiers":[
        {
            "category":"Retail",
            "subcategory":"Veterinary Services",
            "type":"Services"
        }
    ],
    "sg:phone":"+1 570 323 9431",
    "sg:postcode":"17701",
    "sg:province":"PA",
    "sg:tags":[
        "veterinarian"
    ],
    "wof:name":"Animal & Avian Hospital",
    "wof:placetype":"venue"
},
  "geometry": {"coordinates":[-76.967069,41.249419],"type":"Point"}
}