{
  "type": "Feature",
  "properties": {
    "iso:country":"US",
    "sg:address":"37 Lake Rd",
    "sg:city":"Sandy Lake",
    "sg:phone":"+1   ",
    "sg:postcode":"16145",
    "sg:province":"PA",
    "sg:tags":[
        "farm",
        "corn",
        "cash",
        "crop",
        "field",
        "grain"
    ],
    "wof:name":"Dale Kepner",
    "wof:placetype":"venue"
},
  "geometry": {"coordinates":[-80.07239300000001,41.385961],"type":"Point"}
}