{
  "type": "Feature",
  "properties": {
    "addr:full":"235 W Tannery St Harrison Valley PA 16927",
    "addr:housenumber":"235",
    "addr:postcode":"16927",
    "addr:street":"W Tannery St",
    "iso:country":"US",
    "sg:address":"235 W Tannery St",
    "sg:city":"Harrison Valley",
    "sg:classifiers":[
        {
            "category":"Wholesale",
            "subcategory":"Sporting Goods",
            "type":"Manufacturing & Wholesale Goods"
        }
    ],
    "sg:phone":"+1   ",
    "sg:postcode":"16927",
    "sg:province":"PA",
    "sg:tags":[
        "diving"
    ],
    "wof:name":"Bakers Dive Shop",
    "wof:placetype":"venue"
},
  "geometry": {"coordinates":[-77.647543,41.942316],"type":"Point"}
}