{
  "type": "Feature",
  "properties": {
    "iso:country":"US",
    "sg:address":"336 Stricklerstown Rd",
    "sg:city":"Newmanstown",
    "sg:classifiers":[
        {
            "category":"Freight",
            "type":"Transportation"
        }
    ],
    "sg:phone":"+1   ",
    "sg:postcode":"17073",
    "sg:province":"PA",
    "sg:tags":[
        "operator",
        "trucking"
    ],
    "wof:name":"Kurtz Transport Ltd",
    "wof:placetype":"venue"
},
  "geometry": {"coordinates":[-76.227997,40.320146],"type":"Point"}
}