{
  "type": "Feature",
  "properties": {
    "iso:country":"US",
    "sg:address":"7147 US 322",
    "sg:city":"Cranberry",
    "sg:classifiers":[
        {
            "category":"Insurance",
            "subcategory":"Hazard Insurance",
            "type":"Services"
        }
    ],
    "sg:phone":"+1 814 676 2335",
    "sg:postcode":"16319",
    "sg:province":"PA",
    "sg:tags":[
        "commercial",
        "business"
    ],
    "sg:website":"http://allstate.com",
    "wof:name":"Bowler Ins Agcy Inc",
    "wof:placetype":"venue"
},
  "geometry": {"coordinates":[-79.70936500000001,41.349171],"type":"Point"}
}