{
  "type": "Feature",
  "properties": {
    "addr:full":"1357 W 6th St Erie PA 16505",
    "addr:housenumber":"1357",
    "addr:postcode":"16505",
    "addr:street":"W 6Th St",
    "iso:country":"US",
    "sg:address":"1357 W 6th St",
    "sg:city":"Erie",
    "sg:classifiers":[
        {
            "category":"Personal",
            "type":"Services"
        }
    ],
    "sg:phone":"+1 814 461 1075",
    "sg:postcode":"16505",
    "sg:province":"PA",
    "sg:tags":[
        "counseling"
    ],
    "wof:name":"Siepel, Kathleen E Ma",
    "wof:placetype":"venue"
},
  "geometry": {"coordinates":[-80.115433,42.11961],"type":"Point"}
}