{
  "type": "Feature",
  "properties": {
    "iso:country":"US",
    "sg:address":"1518 N 56th St",
    "sg:city":"Philadelphia",
    "sg:classifiers":[
        {
            "category":"Social Services",
            "subcategory":"Child Care",
            "type":"Services"
        }
    ],
    "sg:phone":"+1 215 473 2610",
    "sg:postcode":"19131",
    "sg:province":"PA",
    "sg:tags":[
        "day"
    ],
    "wof:name":"Mia Luvs Kidz Inc",
    "wof:placetype":"venue"
},
  "geometry": {"coordinates":[-75.23372500000001,39.976347],"type":"Point"}
}