{
  "type": "Feature",
  "properties": {
    "addr:full":"7 Pearl Dr Doylestown PA 18901",
    "addr:housenumber":"7",
    "addr:postcode":"18901",
    "addr:street":"Pearl Dr",
    "iso:country":"US",
    "sg:address":"7 Pearl Dr",
    "sg:city":"Doylestown",
    "sg:classifiers":[
        {
            "category":"Professional",
            "type":"Services"
        }
    ],
    "sg:phone":"+1   ",
    "sg:postcode":"18901",
    "sg:province":"PA",
    "wof:name":"Action Personal Training",
    "wof:placetype":"venue"
},
  "geometry": {"coordinates":[-75.140676,40.322357],"type":"Point"}
}