{
  "type": "Feature",
  "properties": {
    "iso:country":"US",
    "sg:address":"1189 W Main St",
    "sg:city":"Stroudsburg",
    "sg:classifiers":[
        {
            "category":"Building & Trades",
            "subcategory":"Construction",
            "type":"Services"
        }
    ],
    "sg:phone":"+1   ",
    "sg:postcode":"18360",
    "sg:province":"PA",
    "sg:tags":[
        "install",
        "fence"
    ],
    "wof:name":"Sentry Fence Co Inc",
    "wof:placetype":"venue"
},
  "geometry": {"coordinates":[-75.209974,40.982476],"type":"Point"}
}