{
  "type": "Feature",
  "properties": {
    "addr:full":"127 W Street Rd Kennett Square PA 19348",
    "addr:housenumber":"127",
    "addr:postcode":"19348",
    "addr:street":"W Street Rd",
    "iso:country":"US",
    "sg:address":"127 W Street Rd",
    "sg:city":"Kennett Square",
    "sg:classifiers":[
        {
            "category":"Health Services",
            "subcategory":"Dentist",
            "type":"Services"
        }
    ],
    "sg:phone":"+1 610 444 9952",
    "sg:postcode":"19348",
    "sg:province":"PA",
    "sg:tags":[
        "orthodontist"
    ],
    "sg:website":"www.superiorsmiles.com",
    "wof:name":"Hendrix Jeffrey D D S M S",
    "wof:placetype":"venue"
},
  "geometry": {"coordinates":[-75.72152,39.874096],"type":"Point"}
}