{
  "type": "Feature",
  "properties": {
    "addr:full":"20 S 2nd St Newport PA 17074",
    "addr:housenumber":"20",
    "addr:postcode":"17074",
    "addr:street":"S 2Nd St",
    "iso:country":"US",
    "sg:address":"20 S 2nd St",
    "sg:city":"Newport",
    "sg:classifiers":[
        {
            "category":"Shopping",
            "subcategory":"Gifts & Souvenirs",
            "type":"Retail Goods"
        }
    ],
    "sg:phone":"+1 717 567 0155",
    "sg:postcode":"17074",
    "sg:province":"PA",
    "sg:tags":[
        "shop"
    ],
    "wof:name":"Tuscarora Trading Post",
    "wof:placetype":"venue"
},
  "geometry": {"coordinates":[-77.130349,40.477343],"type":"Point"}
}