{
  "type": "Feature",
  "properties": {
    "iso:country":"US",
    "sg:address":"106 Cedarbrook Dr",
    "sg:city":"Pittsburgh",
    "sg:classifiers":[
        {
            "category":"Professional",
            "type":"Services"
        }
    ],
    "sg:phone":"+1   ",
    "sg:postcode":"15220",
    "sg:province":"PA",
    "wof:name":"Dennis F Fingers",
    "wof:placetype":"venue"
},
  "geometry": {"coordinates":[-80.048294,40.441145],"type":"Point"}
}