{
  "type": "Feature",
  "properties": {
    "iso:country":"US",
    "sg:address":"43 Clarence Fry Rd",
    "sg:city":"Montoursville",
    "sg:classifiers":[
        {
            "category":"Building & Trades",
            "subcategory":"Construction",
            "type":"Services"
        }
    ],
    "sg:phone":"+1   ",
    "sg:postcode":"17754",
    "sg:province":"PA",
    "sg:tags":[
        "hanging",
        "contractor"
    ],
    "wof:name":"Renati School of Dance",
    "wof:placetype":"venue"
},
  "geometry": {"coordinates":[-76.863851,41.281295],"type":"Point"}
}