{
  "type": "Feature",
  "properties": {
    "addr:full":"103 Pennsylvania Ave Havertown PA 19083",
    "addr:housenumber":"103",
    "addr:postcode":"19083",
    "addr:street":"Pennsylvania Ave",
    "iso:country":"US",
    "sg:address":"103 Pennsylvania Ave",
    "sg:city":"Havertown",
    "sg:classifiers":[
        {
            "category":"Insurance",
            "subcategory":"Insurance Agent",
            "type":"Services"
        }
    ],
    "sg:phone":"+1 610 853 2668",
    "sg:postcode":"19083",
    "sg:province":"PA",
    "wof:name":"Senior Citizen Insurance Svc",
    "wof:placetype":"venue"
},
  "geometry": {"coordinates":[-75.29946700000001,39.977512],"type":"Point"}
}