{
  "type": "Feature",
  "properties": {
    "addr:full":"4064 William Penn Hwy Murrysville PA 15668",
    "addr:housenumber":"4064",
    "addr:postcode":"15668",
    "addr:street":"William Penn Hwy",
    "iso:country":"US",
    "sg:address":"4064 William Penn Hwy",
    "sg:city":"Murrysville",
    "sg:classifiers":[
        {
            "category":"Insurance",
            "subcategory":"Insurance Agent",
            "type":"Services"
        }
    ],
    "sg:phone":"+1 724 327 8787",
    "sg:postcode":"15668",
    "sg:province":"PA",
    "wof:name":"State Farm Insurance",
    "wof:placetype":"venue"
},
  "geometry": {"coordinates":[-79.69251800000001,40.42753],"type":"Point"}
}