{
  "type": "Feature",
  "properties": {
    "iso:country":"US",
    "sg:address":"204 Miller St",
    "sg:city":"Newell",
    "sg:classifiers":[
        {
            "category":"Organizations",
            "subcategory":"Religious Organization",
            "type":"Services"
        }
    ],
    "sg:phone":"+1 724 938 7510",
    "sg:postcode":"15466",
    "sg:province":"PA",
    "sg:tags":[
        "church"
    ],
    "wof:name":"Newell United Methodist",
    "wof:placetype":"venue"
},
  "geometry": {"coordinates":[-79.898794,40.075113],"type":"Point"}
}