{
  "type": "Feature",
  "properties": {
    "iso:country":"US",
    "sg:address":"134 Madison Ave",
    "sg:city":"Reading",
    "sg:classifiers":[
        {
            "category":"Utilities",
            "subcategory":"Water",
            "type":"Services"
        }
    ],
    "sg:phone":"+1 610 921 0985",
    "sg:postcode":"19605",
    "sg:province":"PA",
    "sg:tags":[
        "bulk",
        "companies-bottled"
    ],
    "wof:name":"Air And Water Filtration",
    "wof:placetype":"venue"
},
  "geometry": {"coordinates":[-75.922505,40.374899],"type":"Point"}
}