{
  "type": "Feature",
  "properties": {
    "iso:country":"US",
    "sg:address":"504 N Broad St",
    "sg:city":"Grove City",
    "sg:classifiers":[
        {
            "category":"Building & Trades",
            "subcategory":"Construction",
            "type":"Services"
        },
        {
            "category":"Building & Trades",
            "subcategory":"Plumbing",
            "type":"Services"
        }
    ],
    "sg:phone":"+1 724 458 5200",
    "sg:postcode":"16127",
    "sg:province":"PA",
    "sg:tags":[
        "plumbing",
        "residential",
        "cooling",
        "heating",
        "contractor"
    ],
    "wof:name":"Filers Plumbing & Heating",
    "wof:placetype":"venue"
},
  "geometry": {"coordinates":[-80.08155499999999,41.167366],"type":"Point"}
}