{
  "type": "Feature",
  "properties": {
    "iso:country":"US",
    "sg:address":"7210 Frankstown Ave",
    "sg:city":"Pittsburgh",
    "sg:classifiers":[
        {
            "category":"Restaurant",
            "type":"Food & Drink"
        }
    ],
    "sg:phone":"+1 412 371 0456",
    "sg:postcode":"15208",
    "sg:province":"PA",
    "sg:tags":[
        "fast"
    ],
    "wof:name":"KFC",
    "wof:placetype":"venue"
},
  "geometry": {"coordinates":[-79.894358,40.456886],"type":"Point"}
}