{
  "type": "Feature",
  "properties": {
    "addr:full":"992 Blockhouse Rd Trout Run PA 17771",
    "addr:housenumber":"992",
    "addr:postcode":"17771",
    "addr:street":"Blockhouse Rd",
    "iso:country":"US",
    "sg:address":"992 Blockhouse Rd",
    "sg:city":"Trout Run",
    "sg:classifiers":[
        {
            "category":"Retail",
            "subcategory":"Auto Repair",
            "type":"Services"
        }
    ],
    "sg:phone":"+1   ",
    "sg:postcode":"17771",
    "sg:province":"PA",
    "sg:tags":[
        "truck",
        "tractor"
    ],
    "wof:name":"Buttonwood Garage Sales & Svc",
    "wof:placetype":"venue"
},
  "geometry": {"coordinates":[-77.133054,41.501796],"type":"Point"}
}