{
  "type": "Feature",
  "properties": {
    "iso:country":"US",
    "sg:address":"1145 W Baltimore Pike",
    "sg:city":"Media",
    "sg:classifiers":[
        {
            "category":"Fast Food",
            "type":"Food & Drink"
        },
        {
            "category":"Restaurant",
            "type":"Food & Drink"
        },
        {
            "category":"Ice Cream",
            "type":"Food & Drink"
        },
        {
            "category":"Food & Beverages",
            "subcategory":"Groceries & Convenience Stores",
            "type":"Retail Goods"
        }
    ],
    "sg:phone":"+1 610 891 0188",
    "sg:postcode":"19063",
    "sg:province":"PA",
    "sg:tags":[
        "shop",
        "style",
        "sandwich",
        "hamburger",
        "family",
        "frozen",
        "dessert",
        "dog",
        "lunch",
        "hot",
        "american",
        "brunch",
        "breakfast"
    ],
    "sg:website":"http://www.friendlys.com",
    "wof:name":"Friendly's",
    "wof:placetype":"venue"
},
  "geometry": {"coordinates":[-75.43584199999999,39.913512],"type":"Point"}
}