{
  "type": "Feature",
  "properties": {
    "iso:country":"US",
    "sg:address":"63 W Point Rd",
    "sg:city":"Washington",
    "sg:classifiers":[
        {
            "category":"Manufacturing",
            "subcategory":"Metals",
            "type":"Manufacturing & Wholesale Goods"
        }
    ],
    "sg:phone":"+1   ",
    "sg:postcode":"15301",
    "sg:province":"PA",
    "sg:tags":[
        "shop",
        "gasket"
    ],
    "wof:name":"Accutrex Products Inc",
    "wof:placetype":"venue"
},
  "geometry": {"coordinates":[-80.273083,40.165709],"type":"Point"}
}