{
  "type": "Feature",
  "properties": {
    "iso:country":"US",
    "sg:address":"160 Bankway St",
    "sg:city":"Lehighton",
    "sg:classifiers":[
        {
            "category":"Organizations",
            "subcategory":"Religious Organization",
            "type":"Services"
        }
    ],
    "sg:phone":"+1 610 379 9591",
    "sg:postcode":"18235",
    "sg:province":"PA",
    "sg:tags":[
        "synagogue"
    ],
    "wof:name":"Temple Israel Of Lehighton",
    "wof:placetype":"venue"
},
  "geometry": {"coordinates":[-75.707667,40.830591],"type":"Point"}
}