{
  "type": "Feature",
  "properties": {
    "addr:full":"300 E Campus Ave Davidsville PA 15928",
    "addr:housenumber":"300",
    "addr:postcode":"15928",
    "addr:street":"E Campus Ave",
    "iso:country":"US",
    "sg:address":"300 E Campus Ave",
    "sg:city":"Davidsville",
    "sg:classifiers":[
        {
            "category":"Building & Trades",
            "subcategory":"Construction",
            "type":"Services"
        }
    ],
    "sg:phone":"+1   ",
    "sg:postcode":"15928",
    "sg:province":"PA",
    "sg:tags":[
        "house"
    ],
    "wof:name":"Wilson Construction Co Inc",
    "wof:placetype":"venue"
},
  "geometry": {"coordinates":[-78.93554399999999,40.22622],"type":"Point"}
}