{
  "type": "Feature",
  "properties": {
    "iso:country":"US",
    "sg:address":"157 Church St",
    "sg:city":"Dallas",
    "sg:classifiers":[
        {
            "category":"Building & Trades",
            "subcategory":"Construction",
            "type":"Services"
        }
    ],
    "sg:phone":"+1   ",
    "sg:postcode":"18612",
    "sg:province":"PA",
    "sg:tags":[
        "installs",
        "equipment",
        "commercial",
        "kitchen"
    ],
    "wof:name":"Barrys Coml Installations",
    "wof:placetype":"venue"
},
  "geometry": {"coordinates":[-75.963082,41.338368],"type":"Point"}
}