{
  "type": "Feature",
  "properties": {
    "iso:country":"US",
    "sg:address":"988 Perry Hwy",
    "sg:city":"Pittsburgh",
    "sg:classifiers":[
        {
            "category":"Insurance",
            "subcategory":"Hazard Insurance",
            "type":"Services"
        }
    ],
    "sg:phone":"+1 412 367 2161",
    "sg:postcode":"15237",
    "sg:province":"PA",
    "sg:website":"http://www.VisitKenMoore.com",
    "wof:name":"State Farm\u00ae Agent Ken Moore",
    "wof:placetype":"venue"
},
  "geometry": {"coordinates":[-80.036343,40.538267],"type":"Point"}
}