{
  "type": "Feature",
  "properties": {
    "iso:country":"US",
    "sg:address":"1232 Horsham Rd",
    "sg:city":"Ambler",
    "sg:classifiers":[
        {
            "category":"Professional",
            "subcategory":"Advertising",
            "type":"Services"
        }
    ],
    "sg:phone":"+1   ",
    "sg:postcode":"19002",
    "sg:province":"PA",
    "sg:tags":[
        "marketing",
        "agency",
        "dealership",
        "for",
        "car"
    ],
    "wof:name":"Knopf Motors Inc",
    "wof:placetype":"venue"
},
  "geometry": {"coordinates":[-75.198036,40.219499],"type":"Point"}
}