{
  "type": "Feature",
  "properties": {
    "iso:country":"US",
    "sg:address":"2543 Riddle Run Rd",
    "sg:city":"Tarentum",
    "sg:classifiers":[
        {
            "category":"Manufacturing",
            "subcategory":"Electronics",
            "type":"Manufacturing & Wholesale Goods"
        },
        {
            "category":"Professional",
            "subcategory":"Printing & Photocopies",
            "type":"Services"
        }
    ],
    "sg:phone":"+1 724 274 0687",
    "sg:postcode":"15084",
    "sg:province":"PA",
    "sg:tags":[
        "printers-equipment",
        "typesetting",
        "supply"
    ],
    "wof:name":"Just Your Type",
    "wof:placetype":"venue"
},
  "geometry": {"coordinates":[-79.78505699999999,40.565836],"type":"Point"}
}