{
  "type": "Feature",
  "properties": {
    "iso:country":"US",
    "sg:address":"5 Short Ln",
    "sg:city":"New Oxford",
    "sg:phone":"+1   ",
    "sg:postcode":"17350",
    "sg:province":"PA",
    "sg:tags":[
        "farm",
        "grain",
        "cash"
    ],
    "wof:name":"Pleasantview Farms",
    "wof:placetype":"venue"
},
  "geometry": {"coordinates":[-77.028459,39.896102],"type":"Point"}
}