{
  "type": "Feature",
  "properties": {
    "iso:country":"US",
    "sg:address":"1015 Green St",
    "sg:city":"Marcus Hook",
    "sg:classifiers":[
        {
            "category":"Social Services",
            "type":"Services"
        }
    ],
    "sg:phone":"+1 610 485 1877",
    "sg:postcode":"19061",
    "sg:province":"PA",
    "sg:tags":[
        "organization",
        "welfare"
    ],
    "wof:name":"Marcus Hook Community Dev Corp",
    "wof:placetype":"venue"
},
  "geometry": {"coordinates":[-75.41945200000001,39.8201],"type":"Point"}
}