{
  "type": "Feature",
  "properties": {
    "iso:country":"US",
    "sg:address":"4035 N Front St",
    "sg:city":"Harrisburg",
    "sg:classifiers":[
        {
            "category":"Retail",
            "subcategory":"Auto Repair",
            "type":"Services"
        }
    ],
    "sg:phone":"+1 717 232 3252",
    "sg:postcode":"17110",
    "sg:province":"PA",
    "sg:tags":[
        "automobile",
        "inspection"
    ],
    "wof:name":"Sadiq's Foreign Car Repair",
    "wof:placetype":"venue"
},
  "geometry": {"coordinates":[-76.89858599999999,40.318339],"type":"Point"}
}