{
  "type": "Feature",
  "properties": {
    "iso:country":"US",
    "sg:address":"180 Fort Couch Rd",
    "sg:city":"Pittsburgh",
    "sg:classifiers":[
        {
            "category":"Health Services",
            "subcategory":"Doctor",
            "type":"Services"
        },
        {
            "category":"Health Services",
            "subcategory":"Podiatrist",
            "type":"Services"
        }
    ],
    "sg:phone":"+1 412 831 2288",
    "sg:postcode":"15241",
    "sg:province":"PA",
    "sg:tags":[
        "physician",
        "surgeon",
        "surgeons"
    ],
    "wof:name":"Jones Sandra MD",
    "wof:placetype":"venue"
},
  "geometry": {"coordinates":[-80.05393599999999,40.345922],"type":"Point"}
}