{
  "type": "Feature",
  "properties": {
    "addr:full":"144 S Morton Ave Morton PA 19070",
    "addr:housenumber":"144",
    "addr:postcode":"19070",
    "addr:street":"S Morton Ave",
    "iso:country":"US",
    "sg:address":"144 S Morton Ave",
    "sg:city":"Morton",
    "sg:classifiers":[
        {
            "category":"Shopping",
            "subcategory":"Hobbies, Toys, & Games",
            "type":"Retail Goods"
        }
    ],
    "sg:phone":"+1   ",
    "sg:postcode":"19070",
    "sg:province":"PA",
    "wof:name":"Woodland Hall Bingo",
    "wof:placetype":"venue"
},
  "geometry": {"coordinates":[-75.329601,39.903399],"type":"Point"}
}