{
  "type": "Feature",
  "properties": {
    "iso:country":"US",
    "sg:address":"4930 Carlisle Pike Ste 112",
    "sg:city":"Mechanicsburg",
    "sg:classifiers":[
        {
            "category":"Personal",
            "subcategory":"Nail Salon",
            "type":"Services"
        }
    ],
    "sg:phone":"+1 717 975 3808",
    "sg:postcode":"17050",
    "sg:province":"PA",
    "wof:name":"Hampden Nails",
    "wof:placetype":"venue"
},
  "geometry": {"coordinates":[-76.96869700000001,40.237202],"type":"Point"}
}