{
  "type": "Feature",
  "properties": {
    "iso:country":"US",
    "sg:address":"2000 Hamilton St Ste 201",
    "sg:city":"Philadelphia",
    "sg:classifiers":[
        {
            "category":"Social Services",
            "type":"Services"
        },
        {
            "category":"Organizations",
            "subcategory":"Non-profit Organization",
            "type":"Services"
        }
    ],
    "sg:phone":"+1 267 386 4600",
    "sg:postcode":"19130",
    "sg:province":"PA",
    "sg:tags":[
        "fund",
        "raising"
    ],
    "sg:website":"http://www.cisphl.org",
    "wof:name":"Communities In Schools Of Philadelphia, Inc.",
    "wof:placetype":"venue"
},
  "geometry": {"coordinates":[-75.171272,39.962261],"type":"Point"}
}