{
  "type": "Feature",
  "properties": {
    "addr:full":"717 N Clear Ridge Rd Hustontown PA 17229",
    "addr:housenumber":"717",
    "addr:postcode":"17229",
    "addr:street":"N Clear Ridge Rd",
    "iso:country":"US",
    "sg:address":"717 N Clear Ridge Rd",
    "sg:city":"Hustontown",
    "sg:classifiers":[
        {
            "category":"Shopping",
            "subcategory":"Bicycles & Sporting Goods",
            "type":"Retail Goods"
        }
    ],
    "sg:phone":"+1   ",
    "sg:postcode":"17229",
    "sg:province":"PA",
    "wof:name":"Als Gun Shop",
    "wof:placetype":"venue"
},
  "geometry": {"coordinates":[-78.015957,40.061523],"type":"Point"}
}