{
  "type": "Feature",
  "properties": {
    "iso:country":"US",
    "sg:address":"4620 Hatfield St",
    "sg:city":"Pittsburgh",
    "sg:classifiers":[
        {
            "category":"Building & Trades",
            "subcategory":"Plumbing",
            "type":"Services"
        }
    ],
    "sg:phone":"+1 412 687 4344",
    "sg:postcode":"15201",
    "sg:province":"PA",
    "sg:tags":[
        "plumbing",
        "contractor"
    ],
    "wof:name":"C & L Mechanical Contracting",
    "wof:placetype":"venue"
},
  "geometry": {"coordinates":[-79.960668,40.475163],"type":"Point"}
}