{
  "type": "Feature",
  "properties": {
    "addr:full":"1900 Market St Philadelphia PA 19103",
    "addr:housenumber":"1900",
    "addr:postcode":"19103",
    "addr:street":"Market St",
    "iso:country":"US",
    "sg:address":"1900 Market St",
    "sg:city":"Philadelphia",
    "sg:classifiers":[
        {
            "category":"Banks & Credit Unions",
            "subcategory":"Investment Brokerage",
            "type":"Services"
        }
    ],
    "sg:phone":"+1 215 563 8605",
    "sg:postcode":"19103",
    "sg:province":"PA",
    "sg:tags":[
        "stock",
        "bond"
    ],
    "wof:name":"Raymond James & Assoc Inc",
    "wof:placetype":"venue"
},
  "geometry": {"coordinates":[-75.173176,39.953571],"type":"Point"}
}