{
  "type": "Feature",
  "properties": {
    "iso:country":"US",
    "sg:address":"772 Mt Bethel Hwy",
    "sg:city":"Mt Bethel",
    "sg:classifiers":[
        {
            "category":"Shopping",
            "subcategory":"Used Merchandise",
            "type":"Retail Goods"
        }
    ],
    "sg:phone":"+1 610 588 8995",
    "sg:postcode":"18343",
    "sg:province":"PA",
    "sg:tags":[
        "antique"
    ],
    "wof:name":"Country Doctor Antiques",
    "wof:placetype":"venue"
},
  "geometry": {"coordinates":[-75.15313999999999,40.888279],"type":"Point"}
}