{
  "type": "Feature",
  "properties": {
    "addr:full":"301 S 3rd St Darby PA 19023",
    "addr:housenumber":"301",
    "addr:postcode":"19023",
    "addr:street":"S 3Rd St",
    "iso:country":"US",
    "sg:address":"301 S 3rd St",
    "sg:city":"Darby",
    "sg:classifiers":[
        {
            "category":"Social Services",
            "subcategory":"Child Care",
            "type":"Services"
        }
    ],
    "sg:phone":"+1 610 522 8310",
    "sg:postcode":"19023",
    "sg:province":"PA",
    "sg:tags":[
        "day"
    ],
    "wof:name":"Childrens Garden",
    "wof:placetype":"venue"
},
  "geometry": {"coordinates":[-75.25279999999999,39.913799],"type":"Point"}
}