{
  "type": "Feature",
  "properties": {
    "iso:country":"US",
    "sg:address":"412 Sentner St",
    "sg:city":"Philadelphia",
    "sg:classifiers":[
        {
            "category":"Place Of Worship",
            "subcategory":"Church",
            "type":"Public Place"
        },
        {
            "category":"Place Of Worship",
            "type":"Public Place"
        },
        {
            "category":"Organizations",
            "subcategory":"Religious Organization",
            "type":"Services"
        }
    ],
    "sg:phone":"+1 215 745 7115",
    "sg:postcode":"19120",
    "sg:province":"PA",
    "sg:tags":[
        "churches-methodist"
    ],
    "wof:name":"Crescentville United Methodist Church Inc",
    "wof:placetype":"venue"
},
  "geometry": {"coordinates":[-75.106748,40.043366],"type":"Point"}
}