{
  "type": "Feature",
  "properties": {
    "iso:country":"US",
    "sg:address":"540 E High St",
    "sg:city":"Pottstown",
    "sg:classifiers":[
        {
            "category":"Real Estate",
            "subcategory":"Real Estate Operator",
            "type":"Services"
        }
    ],
    "sg:phone":"+1 610 326 4778",
    "sg:postcode":"19464",
    "sg:province":"PA",
    "sg:tags":[
        "apartment"
    ],
    "wof:name":"Gatehouse Properties",
    "wof:placetype":"venue"
},
  "geometry": {"coordinates":[-75.64019,40.244317],"type":"Point"}
}