{
  "type": "Feature",
  "properties": {
    "iso:country":"US",
    "sg:address":"8 River Rd",
    "sg:city":"Mc Kees Rocks",
    "sg:classifiers":[
        {
            "category":"Wholesale",
            "subcategory":"Metals & Minerals",
            "type":"Manufacturing & Wholesale Goods"
        }
    ],
    "sg:phone":"+1 412 771 2600",
    "sg:postcode":"15136",
    "sg:province":"PA",
    "sg:tags":[
        "center",
        "aluminum"
    ],
    "sg:website":"www.integrismetals.com",
    "wof:name":"Integris Metals Inc",
    "wof:placetype":"venue"
},
  "geometry": {"coordinates":[-80.061798,40.484031],"type":"Point"}
}