{
  "type": "Feature",
  "properties": {
    "iso:country":"US",
    "sg:address":"180 E Butler Ave",
    "sg:city":"Chalfont",
    "sg:classifiers":[
        {
            "category":"Social Services",
            "subcategory":"Child Care",
            "type":"Services"
        },
        {
            "category":"Education",
            "subcategory":"Preschool",
            "type":"Public Place"
        },
        {
            "category":"Education",
            "subcategory":"School",
            "type":"Public Place"
        }
    ],
    "sg:phone":"+1 215 997 9271",
    "sg:postcode":"18914",
    "sg:province":"PA",
    "sg:tags":[
        "elementary",
        "day"
    ],
    "sg:website":"www.kindercare.com/Our-Centers/C...",
    "wof:name":"Chalfont East Kindercare",
    "wof:placetype":"venue"
},
  "geometry": {"coordinates":[-75.201187,40.288966],"type":"Point"}
}