{
  "type": "Feature",
  "properties": {
    "addr:full":"282 Erie Blvd Susquehanna PA 18847",
    "addr:housenumber":"282",
    "addr:postcode":"18847",
    "addr:street":"Erie Blvd",
    "iso:country":"US",
    "sg:address":"282 Erie Blvd",
    "sg:city":"Susquehanna",
    "sg:classifiers":[
        {
            "category":"Government",
            "subcategory":"Office",
            "type":"Public Place"
        }
    ],
    "sg:phone":"+1 570 853 4719",
    "sg:postcode":"18847",
    "sg:province":"PA",
    "sg:tags":[
        "management",
        "village"
    ],
    "wof:name":"Tri-Boro Municipal Authority",
    "wof:placetype":"venue"
},
  "geometry": {"coordinates":[-75.600313,41.944453],"type":"Point"}
}