{
  "type": "Feature",
  "properties": {
    "addr:full":"893 Parkes Run Ln Villanova PA 19085",
    "addr:housenumber":"893",
    "addr:postcode":"19085",
    "addr:street":"Parkes Run Ln",
    "iso:country":"US",
    "sg:address":"893 Parkes Run Ln",
    "sg:city":"Villanova",
    "sg:classifiers":[
        {
            "category":"Professional",
            "type":"Services"
        }
    ],
    "sg:phone":"+1   ",
    "sg:postcode":"19085",
    "sg:province":"PA",
    "wof:name":"David M & Marjorie D Rose",
    "wof:placetype":"venue"
},
  "geometry": {"coordinates":[-75.378224,40.030623],"type":"Point"}
}