{
  "type": "Feature",
  "properties": {
    "iso:country":"US",
    "sg:address":"84 Mccracken Hill Rd",
    "sg:city":"Burgettstown",
    "sg:classifiers":[
        {
            "category":"Restaurant",
            "type":"Food & Drink"
        }
    ],
    "sg:phone":"+1 724 947 2423",
    "sg:postcode":"15021",
    "sg:province":"PA",
    "sg:tags":[
        "italian"
    ],
    "wof:name":"Tias Retaurant",
    "wof:placetype":"venue"
},
  "geometry": {"coordinates":[-80.490517,40.426063],"type":"Point"}
}