{
  "type": "Feature",
  "properties": {
    "iso:country":"US",
    "sg:address":"100 Lincoln St",
    "sg:city":"Dupont",
    "sg:classifiers":[
        {
            "category":"Personal",
            "subcategory":"Beauty Salon",
            "type":"Services"
        }
    ],
    "sg:phone":"+1 570 603 7175",
    "sg:postcode":"18641",
    "sg:province":"PA",
    "wof:name":"Stella's Beauty Shoppe",
    "wof:placetype":"venue"
},
  "geometry": {"coordinates":[-75.75184299999999,41.320562],"type":"Point"}
}