{
  "type": "Feature",
  "properties": {
    "addr:full":"956 S Matlack St West Chester PA 19382",
    "addr:housenumber":"956",
    "addr:postcode":"19382",
    "addr:street":"S Matlack St",
    "iso:country":"US",
    "sg:address":"956 S Matlack St",
    "sg:city":"West Chester",
    "sg:classifiers":[
        {
            "category":"Home & Garden",
            "subcategory":"Garden Supply",
            "type":"Retail Goods"
        }
    ],
    "sg:phone":"+1 610 696 1700",
    "sg:postcode":"19382",
    "sg:province":"PA",
    "sg:tags":[
        "nursery",
        "gardening"
    ],
    "wof:name":"Agway Inc",
    "wof:placetype":"venue"
},
  "geometry": {"coordinates":[-75.580704,39.942699],"type":"Point"}
}