{
  "type": "Feature",
  "properties": {
    "iso:country":"US",
    "sg:address":"2125 N 63rd St",
    "sg:city":"Philadelphia",
    "sg:classifiers":[
        {
            "category":"Retail",
            "subcategory":"Auto Repair",
            "type":"Services"
        }
    ],
    "sg:phone":"+1 215 877 5010",
    "sg:postcode":"19151",
    "sg:province":"PA",
    "sg:tags":[
        "repairing",
        "automobile"
    ],
    "wof:name":"P C Mechanics",
    "wof:placetype":"venue"
},
  "geometry": {"coordinates":[-75.249982,39.98884],"type":"Point"}
}