{
  "type": "Feature",
  "properties": {
    "iso:country":"US",
    "sg:address":"2346 Pikeside Dr",
    "sg:city":"Greencastle",
    "sg:classifiers":[
        {
            "category":"Professional",
            "type":"Services"
        }
    ],
    "sg:phone":"+1   ",
    "sg:postcode":"17225",
    "sg:province":"PA",
    "wof:name":"Winners Edge Inc",
    "wof:placetype":"venue"
},
  "geometry": {"coordinates":[-77.75995399999999,39.74876],"type":"Point"}
}