{
  "type": "Feature",
  "properties": {
    "iso:country":"US",
    "sg:address":"3584 W Chester Pike",
    "sg:city":"Newtown Square",
    "sg:classifiers":[
        {
            "category":"Retail",
            "subcategory":"Laundry & Dry Cleaning",
            "type":"Services"
        }
    ],
    "sg:phone":"+1   ",
    "sg:postcode":"19073",
    "sg:province":"PA",
    "sg:tags":[
        "garment",
        "agent"
    ],
    "wof:name":"Wagners Original Cstm Dry Clrs",
    "wof:placetype":"venue"
},
  "geometry": {"coordinates":[-75.40066400000001,39.986665],"type":"Point"}
}