{
  "type": "Feature",
  "properties": {
    "iso:country":"US",
    "sg:address":"173 Holly Rd",
    "sg:city":"Gilbertsville",
    "sg:classifiers":[
        {
            "category":"Restaurant",
            "type":"Food & Drink"
        }
    ],
    "sg:phone":"+1 610 369 5566",
    "sg:postcode":"19525",
    "sg:province":"PA",
    "wof:name":"Bonanza Steakhouse",
    "wof:placetype":"venue"
},
  "geometry": {"coordinates":[-75.61839999999999,40.333456],"type":"Point"}
}