{
  "type": "Feature",
  "properties": {
    "addr:full":"865 5th Ave Coraopolis PA 15108",
    "addr:housenumber":"865",
    "addr:postcode":"15108",
    "addr:street":"5Th Ave",
    "iso:country":"US",
    "sg:address":"865 5th Ave",
    "sg:city":"Coraopolis",
    "sg:classifiers":[
        {
            "category":"Personal",
            "subcategory":"Beauty Salon",
            "type":"Services"
        }
    ],
    "sg:phone":"+1 412 269 0930",
    "sg:postcode":"15108",
    "sg:province":"PA",
    "wof:name":"Judy's Hair Studio",
    "wof:placetype":"venue"
},
  "geometry": {"coordinates":[-80.167254,40.518692],"type":"Point"}
}