{
  "type": "Feature",
  "properties": {
    "addr:full":"5000 Market St Philadelphia PA 19139",
    "addr:housenumber":"5000",
    "addr:postcode":"19139",
    "addr:street":"Market St",
    "iso:country":"US",
    "sg:address":"5000 Market St",
    "sg:city":"Philadelphia",
    "sg:classifiers":[
        {
            "category":"Bars & Pubs",
            "type":"Food & Drink"
        }
    ],
    "sg:phone":"+1 215 748 4499",
    "sg:postcode":"19139",
    "sg:province":"PA",
    "sg:tags":[
        "drinking"
    ],
    "wof:name":"Caprice Villa",
    "wof:placetype":"venue"
},
  "geometry": {"coordinates":[-75.221909,39.959626],"type":"Point"}
}