{
  "type": "Feature",
  "properties": {
    "iso:country":"US",
    "sg:address":"4402 Mc Kenzie Dr",
    "sg:city":"Monroeville",
    "sg:classifiers":[
        {
            "category":"Building & Trades",
            "subcategory":"Construction",
            "type":"Services"
        }
    ],
    "sg:phone":"+1   ",
    "sg:postcode":"15146",
    "sg:province":"PA",
    "sg:tags":[
        "contractor"
    ],
    "wof:name":"Perez Roofing",
    "wof:placetype":"venue"
},
  "geometry": {"coordinates":[-79.75806900000001,40.454624],"type":"Point"}
}