{
  "type": "Feature",
  "properties": {
    "addr:full":"1829 McKees Rocks Rd Mc Kees Rocks PA 15136",
    "addr:housenumber":"1829",
    "addr:postcode":"15136",
    "addr:street":"Mckees Rocks Rd;Kees Rocks",
    "iso:country":"US",
    "sg:address":"1829 McKees Rocks Rd",
    "sg:city":"Mc Kees Rocks",
    "sg:classifiers":[
        {
            "category":"Sports & Exercise",
            "subcategory":"Gym",
            "type":"Entertainment"
        }
    ],
    "sg:phone":"+1 412 331 1098",
    "sg:postcode":"15136",
    "sg:province":"PA",
    "sg:tags":[
        "fitness",
        "physical",
        "facility"
    ],
    "wof:name":"Streamline Fitness",
    "wof:placetype":"venue"
},
  "geometry": {"coordinates":[-80.098743,40.467449],"type":"Point"}
}