{
  "type": "Feature",
  "properties": {
    "iso:country":"US",
    "sg:address":"3300 Ridge Rd",
    "sg:city":"Bloomsburg",
    "sg:classifiers":[
        {
            "category":"Organizations",
            "subcategory":"Religious Organization",
            "type":"Services"
        }
    ],
    "sg:phone":"+1   ",
    "sg:postcode":"17815",
    "sg:province":"PA",
    "wof:name":"Calvary Baptist Church Inc",
    "wof:placetype":"venue"
},
  "geometry": {"coordinates":[-76.40719799999999,41.035705],"type":"Point"}
}