{
  "type": "Feature",
  "properties": {
    "addr:full":"5611 Washington Ave Philadelphia PA 19143",
    "addr:housenumber":"5611",
    "addr:postcode":"19143",
    "addr:street":"Washington Ave",
    "iso:country":"US",
    "sg:address":"5611 Washington Ave",
    "sg:city":"Philadelphia",
    "sg:classifiers":[
        {
            "category":"Wholesale",
            "subcategory":"Machinery & Supplies",
            "type":"Manufacturing & Wholesale Goods"
        }
    ],
    "sg:phone":"+1 215 472 0737",
    "sg:postcode":"19143",
    "sg:province":"PA",
    "sg:tags":[
        "janitor"
    ],
    "wof:name":"Black Star Specialty Chemicals",
    "wof:placetype":"venue"
},
  "geometry": {"coordinates":[-75.237157,39.94713],"type":"Point"}
}