{
  "type": "Feature",
  "properties": {
    "iso:country":"US",
    "sg:address":"52 Maple St",
    "sg:city":"Wilkes Barre",
    "sg:classifiers":[
        {
            "category":"Professional",
            "subcategory":"Business Services",
            "type":"Services"
        }
    ],
    "sg:phone":"+1 570 829 5585",
    "sg:postcode":"18702",
    "sg:province":"PA",
    "sg:tags":[
        "license"
    ],
    "wof:name":"Action Notary & Tag Svc",
    "wof:placetype":"venue"
},
  "geometry": {"coordinates":[-75.819157,41.262775],"type":"Point"}
}