{
  "type": "Feature",
  "properties": {
    "addr:full":"595 Bethlehem Pike Montgomeryville PA 18915",
    "addr:housenumber":"595",
    "addr:postcode":"18915",
    "addr:street":"Bethlehem Pike",
    "iso:country":"US",
    "sg:address":"595 Bethlehem Pike",
    "sg:city":"Montgomeryville",
    "sg:classifiers":[
        {
            "category":"Professional",
            "subcategory":"Accounting & Tax Preparation",
            "type":"Services"
        }
    ],
    "sg:phone":"+1 215 822 5229",
    "sg:postcode":"18915",
    "sg:province":"PA",
    "sg:tags":[
        "accountant"
    ],
    "sg:website":"www.seitz-leatherman.com",
    "wof:name":"Seitz & Leatherman",
    "wof:placetype":"venue"
},
  "geometry": {"coordinates":[-75.26030299999999,40.277479],"type":"Point"}
}