{
  "type": "Feature",
  "properties": {
    "addr:full":"132 S 17th St Philadelphia PA 19103",
    "addr:housenumber":"132",
    "addr:postcode":"19103",
    "addr:street":"S 17Th St",
    "iso:country":"US",
    "sg:address":"132 S 17th St",
    "sg:city":"Philadelphia",
    "sg:classifiers":[
        {
            "category":"Personal",
            "subcategory":"Shoe Repair & Shine",
            "type":"Services"
        }
    ],
    "sg:phone":"+1 215 563 8197",
    "sg:postcode":"19103",
    "sg:province":"PA",
    "sg:tags":[
        "repairing",
        "boot"
    ],
    "wof:name":"Fidelity Shoe Repair",
    "wof:placetype":"venue"
},
  "geometry": {"coordinates":[-75.16892799999999,39.950699],"type":"Point"}
}