{
  "type": "Feature",
  "properties": {
    "iso:country":"US",
    "sg:address":"613 Baltimore Dr",
    "sg:city":"Wilkes Barre",
    "sg:classifiers":[
        {
            "category":"Insurance",
            "subcategory":"Insurance Agent",
            "type":"Services"
        }
    ],
    "sg:phone":"+1 570 288 6401",
    "sg:postcode":"18702",
    "sg:province":"PA",
    "wof:name":"Galland Steinhauer & Repa Inc",
    "wof:placetype":"venue"
},
  "geometry": {"coordinates":[-75.807751,41.251911],"type":"Point"}
}