{
  "type": "Feature",
  "properties": {
    "iso:country":"US",
    "sg:address":"112 Port Vue Dr",
    "sg:city":"Coraopolis",
    "sg:classifiers":[
        {
            "category":"Retail",
            "subcategory":"Car Wash",
            "type":"Services"
        }
    ],
    "sg:phone":"+1 724 457 2080",
    "sg:postcode":"15108",
    "sg:province":"PA",
    "sg:tags":[
        "automobile",
        "detail",
        "clean"
    ],
    "wof:name":"Pro Line Auto Detailing",
    "wof:placetype":"venue"
},
  "geometry": {"coordinates":[-80.21795,40.502726],"type":"Point"}
}