{
  "type": "Feature",
  "properties": {
    "iso:country":"US",
    "sg:address":"113 Jeffrey Cir",
    "sg:city":"Coraopolis",
    "sg:classifiers":[
        {
            "category":"Wholesale",
            "subcategory":"Scrap",
            "type":"Manufacturing & Wholesale Goods"
        }
    ],
    "sg:phone":"+1 724 695 8477",
    "sg:postcode":"15108",
    "sg:province":"PA",
    "sg:tags":[
        "waste"
    ],
    "wof:name":"New AGE Environmental Inc",
    "wof:placetype":"venue"
},
  "geometry": {"coordinates":[-80.21944000000001,40.455929],"type":"Point"}
}