{
  "type": "Feature",
  "properties": {
    "addr:full":"1057 W Chester Rd West Chester PA 19382",
    "addr:housenumber":"1057",
    "addr:postcode":"19382",
    "addr:street":"W Chester Rd",
    "iso:country":"US",
    "sg:address":"1057 W Chester Rd",
    "sg:city":"West Chester",
    "sg:classifiers":[
        {
            "category":"Travel",
            "subcategory":"Campground",
            "type":"Entertainment"
        }
    ],
    "sg:phone":"+1   ",
    "sg:postcode":"19382",
    "sg:province":"PA",
    "sg:tags":[
        "camp"
    ],
    "wof:name":"C M Fun World Inc",
    "wof:placetype":"venue"
},
  "geometry": {"coordinates":[-75.546255,39.911116],"type":"Point"}
}