{
  "type": "Feature",
  "properties": {
    "addr:full":"501 Park Rd Leetsdale PA 15010",
    "addr:housenumber":"501",
    "addr:postcode":"15010",
    "addr:street":"Park Rd",
    "iso:country":"US",
    "sg:address":"501 Park Rd",
    "sg:city":"Leetsdale",
    "sg:classifiers":[
        {
            "category":"Manufacturing",
            "subcategory":"Chemicals & Compounds",
            "type":"Manufacturing & Wholesale Goods"
        }
    ],
    "sg:phone":"+1   ",
    "sg:postcode":"15010",
    "sg:province":"PA",
    "sg:tags":[
        "inorganic",
        "industrial",
        "mfg"
    ],
    "wof:name":"Almatis Inc",
    "wof:placetype":"venue"
},
  "geometry": {"coordinates":[-80.38040599999999,40.745658],"type":"Point"}
}