{
  "type": "Feature",
  "properties": {
    "iso:country":"US",
    "sg:address":"205 Mercer Mill Rd",
    "sg:city":"Landenberg",
    "sg:classifiers":[
        {
            "category":"Restaurant",
            "type":"Food & Drink"
        }
    ],
    "sg:phone":"+1 610 274 0560",
    "sg:postcode":"19350",
    "sg:province":"PA",
    "sg:tags":[
        "cake",
        "wedding",
        "pastry",
        "caterer"
    ],
    "sg:website":"http://www.ammermanscatering.com",
    "wof:name":"Ammerman's Catering",
    "wof:placetype":"venue"
},
  "geometry": {"coordinates":[-75.78598,39.773949],"type":"Point"}
}