{
  "type": "Feature",
  "properties": {
    "iso:country":"US",
    "sg:address":"264 W Main St",
    "sg:city":"Leola",
    "sg:classifiers":[
        {
            "category":"Communications",
            "type":"Services"
        }
    ],
    "sg:phone":"+1 717 656 0166",
    "sg:postcode":"17540",
    "sg:province":"PA",
    "wof:name":"Vmi Communications",
    "wof:placetype":"venue"
},
  "geometry": {"coordinates":[-76.206524,40.085737],"type":"Point"}
}