{
  "type": "Feature",
  "properties": {
    "iso:country":"US",
    "sg:address":"720 Plum St",
    "sg:city":"Lemoyne",
    "sg:classifiers":[
        {
            "category":"Wholesale",
            "subcategory":"Auto Parts",
            "type":"Manufacturing & Wholesale Goods"
        }
    ],
    "sg:phone":"+1   ",
    "sg:postcode":"17043",
    "sg:province":"PA",
    "sg:tags":[
        "repair",
        "automotive"
    ],
    "wof:name":"Air Brake and Power Eqp Co",
    "wof:placetype":"venue"
},
  "geometry": {"coordinates":[-76.89414600000001,40.240921],"type":"Point"}
}