{
  "type": "Feature",
  "properties": {
    "iso:country":"US",
    "sg:address":"439 S Hermitage Rd",
    "sg:city":"Hermitage",
    "sg:classifiers":[
        {
            "category":"Organizations",
            "subcategory":"Religious Organization",
            "type":"Services"
        }
    ],
    "sg:phone":"+1 724 981 7777",
    "sg:postcode":"16148",
    "sg:province":"PA",
    "wof:name":"Don Reed Ministry",
    "wof:placetype":"venue"
},
  "geometry": {"coordinates":[-80.451035,41.227493],"type":"Point"}
}