{
  "type": "Feature",
  "properties": {
    "addr:full":"4824 Leeds Ct Center Valley PA 18034",
    "addr:housenumber":"4824",
    "addr:postcode":"18034",
    "addr:street":"Leeds Ct",
    "iso:country":"US",
    "sg:address":"4824 Leeds Ct",
    "sg:city":"Center Valley",
    "sg:classifiers":[
        {
            "category":"Restaurant",
            "type":"Food & Drink"
        }
    ],
    "sg:phone":"+1   ",
    "sg:postcode":"18034",
    "sg:province":"PA",
    "sg:tags":[
        "shop",
        "bakery",
        "sandwich"
    ],
    "wof:name":"Atlanta Bread Company",
    "wof:placetype":"venue"
},
  "geometry": {"coordinates":[-75.403881,40.548568],"type":"Point"}
}