{
  "type": "Feature",
  "properties": {
    "iso:country":"US",
    "sg:address":"201 Penn St",
    "sg:city":"Reading",
    "sg:classifiers":[
        {
            "category":"Government",
            "subcategory":"Office",
            "type":"Public Place"
        }
    ],
    "sg:phone":"+1   ",
    "sg:postcode":"19601",
    "sg:province":"PA",
    "sg:tags":[
        "employment",
        "training",
        "administration",
        "for",
        "local"
    ],
    "wof:name":"Apprenticeship and Training",
    "wof:placetype":"venue"
},
  "geometry": {"coordinates":[-75.93629,40.335501],"type":"Point"}
}