{
  "type": "Feature",
  "properties": {
    "addr:full":"1238 Lititz Pike Lancaster PA 17601",
    "addr:housenumber":"1238",
    "addr:postcode":"17601",
    "addr:street":"Lititz Pike",
    "iso:country":"US",
    "sg:address":"1238 Lititz Pike",
    "sg:city":"Lancaster",
    "sg:classifiers":[
        {
            "category":"Restaurant",
            "type":"Food & Drink"
        }
    ],
    "sg:phone":"+1 717 394 1914",
    "sg:postcode":"17601",
    "sg:province":"PA",
    "sg:tags":[
        "asian",
        "chinese",
        "pan"
    ],
    "wof:name":"China Palace",
    "wof:placetype":"venue"
},
  "geometry": {"coordinates":[-76.305807,40.057507],"type":"Point"}
}