{
  "type": "Feature",
  "properties": {
    "addr:full":"2372 Orthodox St Philadelphia PA 19137",
    "addr:housenumber":"2372",
    "addr:postcode":"19137",
    "addr:street":"Orthodox St",
    "iso:country":"US",
    "sg:address":"2372 Orthodox St",
    "sg:city":"Philadelphia",
    "sg:classifiers":[
        {
            "category":"Building & Trades",
            "subcategory":"Locksmith",
            "type":"Services"
        }
    ],
    "sg:phone":"+1 267 350 8819",
    "sg:postcode":"19137",
    "sg:province":"PA",
    "sg:tags":[
        "key"
    ],
    "wof:name":"Locksmith",
    "wof:placetype":"venue"
},
  "geometry": {"coordinates":[-75.07788499999999,40.00535],"type":"Point"}
}