{
  "type": "Feature",
  "properties": {
    "addr:full":"205 S Blakely St Dunmore PA 18512",
    "addr:housenumber":"205",
    "addr:postcode":"18512",
    "addr:street":"S Blakely St",
    "iso:country":"US",
    "sg:address":"205 S Blakely St",
    "sg:city":"Dunmore",
    "sg:classifiers":[
        {
            "category":"Home & Garden",
            "subcategory":"Household Appliances",
            "type":"Retail Goods"
        }
    ],
    "sg:phone":"+1 570 346 7880",
    "sg:postcode":"18512",
    "sg:province":"PA",
    "wof:name":"Dunmore Appliance Outlet",
    "wof:placetype":"venue"
},
  "geometry": {"coordinates":[-75.632536,41.41962],"type":"Point"}
}