{
  "type": "Feature",
  "properties": {
    "addr:full":"2 E Railroad Ave New Ringgold PA 17960",
    "addr:housenumber":"2",
    "addr:postcode":"17960",
    "addr:street":"E Railroad Ave",
    "iso:country":"US",
    "sg:address":"2 E Railroad Ave",
    "sg:city":"New Ringgold",
    "sg:classifiers":[
        {
            "category":"Retail",
            "subcategory":"Animal Services",
            "type":"Services"
        }
    ],
    "sg:phone":"+1 570 943 2624",
    "sg:postcode":"17960",
    "sg:province":"PA",
    "sg:tags":[
        "pet",
        "boarding",
        "sitting"
    ],
    "wof:name":"Char-Will Kennels",
    "wof:placetype":"venue"
},
  "geometry": {"coordinates":[-75.998588,40.682393],"type":"Point"}
}