{
  "type": "Feature",
  "properties": {
    "iso:country":"US",
    "sg:address":"2649 E Ontario St",
    "sg:city":"Philadelphia",
    "sg:classifiers":[
        {
            "category":"Shopping",
            "subcategory":"Stationery & Office Supplies",
            "type":"Retail Goods"
        },
        {
            "category":"Shopping",
            "subcategory":"Gifts & Souvenirs",
            "type":"Retail Goods"
        }
    ],
    "sg:phone":"+1 215 356 9284",
    "sg:postcode":"19134",
    "sg:province":"PA",
    "sg:tags":[
        "shop",
        "store"
    ],
    "wof:name":"The Gift & Garden Shop",
    "wof:placetype":"venue"
},
  "geometry": {"coordinates":[-75.098,39.986938],"type":"Point"}
}