{
  "type": "Feature",
  "properties": {
    "iso:country":"US",
    "sg:address":"1175 Enterprise Rd",
    "sg:city":"East Petersburg",
    "sg:classifiers":[
        {
            "category":"Utilities",
            "subcategory":"Refuse",
            "type":"Services"
        }
    ],
    "sg:phone":"+1 717 581 8383",
    "sg:postcode":"17520",
    "sg:province":"PA",
    "sg:tags":[
        "operator",
        "local",
        "system",
        "trucking"
    ],
    "wof:name":"York Waste Disposal Inc",
    "wof:placetype":"venue"
},
  "geometry": {"coordinates":[-76.354838,40.088326],"type":"Point"}
}