{
  "type": "Feature",
  "properties": {
    "addr:full":"100 E Union St Meyersdale PA 15501",
    "addr:housenumber":"100",
    "addr:postcode":"15501",
    "addr:street":"E Union St",
    "iso:country":"US",
    "sg:address":"100 E Union St",
    "sg:city":"Meyersdale",
    "sg:classifiers":[
        {
            "category":"Government",
            "subcategory":"Police Station",
            "type":"Public Place"
        }
    ],
    "sg:phone":"+1 814 634 5149",
    "sg:postcode":"15501",
    "sg:province":"PA",
    "sg:tags":[
        "department"
    ],
    "wof:name":"Meyersdale Boro Police Dept",
    "wof:placetype":"venue"
},
  "geometry": {"coordinates":[-79.07862,40.009341],"type":"Point"}
}