{
  "type": "Feature",
  "properties": {
    "addr:full":"427 Vermont Ave Rochester PA 15074",
    "addr:housenumber":"427",
    "addr:postcode":"15074",
    "addr:street":"Vermont Ave",
    "iso:country":"US",
    "sg:address":"427 Vermont Ave",
    "sg:city":"Rochester",
    "sg:classifiers":[
        {
            "category":"Building & Trades",
            "subcategory":"Construction",
            "type":"Services"
        }
    ],
    "sg:phone":"+1   ",
    "sg:postcode":"15074",
    "sg:province":"PA",
    "sg:tags":[
        "house"
    ],
    "wof:name":"Still Stewart Cnstr & Rmdlg",
    "wof:placetype":"venue"
},
  "geometry": {"coordinates":[-80.28455,40.705292],"type":"Point"}
}