{
  "type": "Feature",
  "properties": {
    "addr:full":"310 S 1st St Bellwood PA 16617",
    "addr:housenumber":"310",
    "addr:postcode":"16617",
    "addr:street":"S 1St St",
    "iso:country":"US",
    "sg:address":"310 S 1st St",
    "sg:city":"Bellwood",
    "sg:classifiers":[
        {
            "category":"Building & Trades",
            "subcategory":"Electrical",
            "type":"Services"
        }
    ],
    "sg:phone":"+1 412 264 9400",
    "sg:postcode":"16617",
    "sg:province":"PA",
    "sg:tags":[
        "electric",
        "contractor"
    ],
    "wof:name":"Mr Electric",
    "wof:placetype":"venue"
},
  "geometry": {"coordinates":[-78.333675,40.597184],"type":"Point"}
}