{
  "type": "Feature",
  "properties": {
    "iso:country":"US",
    "sg:address":"45 W Main St",
    "sg:city":"Schuylkill Haven",
    "sg:classifiers":[
        {
            "category":"Banks & Credit Unions",
            "subcategory":"Bank",
            "type":"Services"
        }
    ],
    "sg:phone":"+1 570 385 4058",
    "sg:postcode":"17972",
    "sg:province":"PA",
    "sg:tags":[
        "national",
        "commercial"
    ],
    "wof:name":"First National Bank",
    "wof:placetype":"venue"
},
  "geometry": {"coordinates":[-76.173559,40.628465],"type":"Point"}
}