{
  "type": "Feature",
  "properties": {
    "addr:full":"744 E Chocolate Ave Hershey PA 17033",
    "addr:housenumber":"744",
    "addr:postcode":"17033",
    "addr:street":"E Chocolate Ave",
    "iso:country":"US",
    "sg:address":"744 E Chocolate Ave",
    "sg:city":"Hershey",
    "sg:classifiers":[
        {
            "category":"Home & Garden",
            "subcategory":"Building Materials",
            "type":"Retail Goods"
        }
    ],
    "sg:phone":"+1 717 533 4997",
    "sg:postcode":"17033",
    "sg:province":"PA",
    "sg:tags":[
        "paint",
        "improvement"
    ],
    "sg:website":"http://www.sherwin-williams.com/index.jsp?WT.mc_id=SW_Store5194",
    "wof:name":"Sherwin-Williams",
    "wof:placetype":"venue"
},
  "geometry": {"coordinates":[-76.633236,40.292089],"type":"Point"}
}