{
  "type": "Feature",
  "properties": {
    "addr:full":"8315 Water View Ln Erie PA 16509",
    "addr:housenumber":"8315",
    "addr:postcode":"16509",
    "addr:street":"Water View Ln",
    "iso:country":"US",
    "sg:address":"8315 Water View Ln",
    "sg:city":"Erie",
    "sg:classifiers":[
        {
            "category":"Retail",
            "subcategory":"Auto Repair",
            "type":"Services"
        }
    ],
    "sg:phone":"+1 814 864 0438",
    "sg:postcode":"16509",
    "sg:province":"PA",
    "sg:tags":[
        "automobile",
        "top",
        "upholstery"
    ],
    "wof:name":"Tops Unlimited Car & Truck",
    "wof:placetype":"venue"
},
  "geometry": {"coordinates":[-80.073729,42.040401],"type":"Point"}
}