{
  "type": "Feature",
  "properties": {
    "iso:country":"US",
    "sg:address":"256 N Limerick Rd",
    "sg:city":"Schwenksville",
    "sg:classifiers":[
        {
            "category":"Building & Trades",
            "subcategory":"Construction",
            "type":"Services"
        }
    ],
    "sg:phone":"+1 610 287 6002",
    "sg:postcode":"19473",
    "sg:province":"PA",
    "sg:tags":[
        "contractor",
        "general"
    ],
    "wof:name":"Natale-Onufer Home Remodeling",
    "wof:placetype":"venue"
},
  "geometry": {"coordinates":[-75.507705,40.245912],"type":"Point"}
}