{
  "type": "Feature",
  "properties": {
    "iso:country":"US",
    "sg:address":"641 Baldwin St",
    "sg:city":"Bridgeville",
    "sg:classifiers":[
        {
            "category":"Freight",
            "type":"Transportation"
        }
    ],
    "sg:phone":"+1   ",
    "sg:postcode":"15017",
    "sg:province":"PA",
    "sg:tags":[
        "operator",
        "trucking"
    ],
    "wof:name":"Collier John",
    "wof:placetype":"venue"
},
  "geometry": {"coordinates":[-80.10647299999999,40.357738],"type":"Point"}
}