{
  "type": "Feature",
  "properties": {
    "iso:country":"US",
    "sg:address":"1201 Airport Rd",
    "sg:city":"Allentown",
    "sg:classifiers":[
        {
            "category":"Autos & Motor Vehicles",
            "subcategory":"Auto Supplies",
            "type":"Retail Goods"
        }
    ],
    "sg:phone":"+1   ",
    "sg:postcode":"18109",
    "sg:province":"PA",
    "wof:name":"Parts America",
    "wof:placetype":"venue"
},
  "geometry": {"coordinates":[-75.44140899999999,40.631237],"type":"Point"}
}