{
  "type": "Feature",
  "properties": {
    "iso:country":"US",
    "sg:address":"2652 Hidden Valley Rd",
    "sg:city":"Pittsburgh",
    "sg:classifiers":[
        {
            "category":"Restaurant",
            "type":"Food & Drink"
        }
    ],
    "sg:phone":"+1 724 942 1974",
    "sg:postcode":"15241",
    "sg:province":"PA",
    "wof:name":"Legend's On the Green",
    "wof:placetype":"venue"
},
  "geometry": {"coordinates":[-80.11219800000001,40.3162],"type":"Point"}
}