{
  "type": "Feature",
  "properties": {
    "iso:country":"US",
    "sg:address":"11237 Shaw Ave",
    "sg:city":"Meadville",
    "sg:classifiers":[
        {
            "category":"Travel",
            "subcategory":"Hotels & Motels",
            "type":"Entertainment"
        },
        {
            "category":"Travel",
            "subcategory":"Bed & Breakfast",
            "type":"Entertainment"
        }
    ],
    "sg:phone":"+1 814 724 6366",
    "sg:postcode":"16335",
    "sg:province":"PA",
    "sg:tags":[
        "inn",
        "lodging"
    ],
    "wof:name":"Econo Lodge Meadville",
    "wof:placetype":"venue"
},
  "geometry": {"coordinates":[-80.174032,41.62104],"type":"Point"}
}