{
  "type": "Feature",
  "properties": {
    "addr:full":"1856 Holly Dr Camp Hill PA 17011",
    "addr:housenumber":"1856",
    "addr:postcode":"17011",
    "addr:street":"Holly Dr",
    "iso:country":"US",
    "sg:address":"1856 Holly Dr",
    "sg:city":"Camp Hill",
    "sg:classifiers":[
        {
            "category":"Manufacturing",
            "subcategory":"Signs",
            "type":"Manufacturing & Wholesale Goods"
        }
    ],
    "sg:phone":"+1   ",
    "sg:postcode":"17011",
    "sg:province":"PA",
    "sg:tags":[
        "specialty",
        "mfg"
    ],
    "wof:name":"Coffee Signs",
    "wof:placetype":"venue"
},
  "geometry": {"coordinates":[-76.910567,40.226382],"type":"Point"}
}