{
  "type": "Feature",
  "properties": {
    "addr:full":"36 Jones Ave Flourtown PA 19031",
    "addr:housenumber":"36",
    "addr:postcode":"19031",
    "addr:street":"Jones Ave",
    "iso:country":"US",
    "sg:address":"36 Jones Ave",
    "sg:city":"Flourtown",
    "sg:classifiers":[
        {
            "category":"Manufacturing",
            "subcategory":"Tools & Machinery",
            "type":"Manufacturing & Wholesale Goods"
        }
    ],
    "sg:phone":"+1   ",
    "sg:postcode":"19031",
    "sg:province":"PA",
    "sg:tags":[
        "scale",
        "weighing",
        "mfg",
        "devices",
        "lab",
        "electronic"
    ],
    "wof:name":"Mettler-Toledo Inc",
    "wof:placetype":"venue"
},
  "geometry": {"coordinates":[-75.20952200000001,40.101141],"type":"Point"}
}