{
  "type": "Feature",
  "properties": {
    "iso:country":"US",
    "sg:address":"851 W Chestnut St",
    "sg:city":"Coal Twp",
    "sg:classifiers":[
        {
            "category":"Health Services",
            "subcategory":"Nursing And Care Facility",
            "type":"Services"
        }
    ],
    "sg:phone":"+1 570 644 2782",
    "sg:postcode":"17866",
    "sg:province":"PA",
    "sg:tags":[
        "intermediate",
        "adult"
    ],
    "wof:name":"Chestnut Hill Personal Care Hm",
    "wof:placetype":"venue"
},
  "geometry": {"coordinates":[-76.56590799999999,40.787508],"type":"Point"}
}