{
  "type": "Feature",
  "properties": {
    "addr:full":"2559 State Rte 88 Finleyville PA 15332",
    "addr:housenumber":"2559",
    "addr:postcode":"15332",
    "addr:street":"State Rte 88",
    "iso:country":"US",
    "sg:address":"2559 State Rte 88",
    "sg:city":"Finleyville",
    "sg:classifiers":[
        {
            "category":"Building & Trades",
            "subcategory":"Plumbing",
            "type":"Services"
        }
    ],
    "sg:phone":"+1   ",
    "sg:postcode":"15332",
    "sg:province":"PA",
    "sg:tags":[
        "mechanical",
        "contractor"
    ],
    "wof:name":"W G Tomko Inc",
    "wof:placetype":"venue"
},
  "geometry": {"coordinates":[-79.99944600000001,40.237464],"type":"Point"}
}