{
  "type": "Feature",
  "properties": {
    "addr:full":"116 E Green St Camp Hill PA 17011",
    "addr:housenumber":"116",
    "addr:postcode":"17011",
    "addr:street":"E Green St",
    "iso:country":"US",
    "sg:address":"116 E Green St",
    "sg:city":"Camp Hill",
    "sg:classifiers":[
        {
            "category":"Building & Trades",
            "subcategory":"Construction",
            "type":"Services"
        }
    ],
    "sg:phone":"+1 717 975 9483",
    "sg:postcode":"17011",
    "sg:province":"PA",
    "sg:tags":[
        "builder",
        "repairer",
        "chimney",
        "contractor"
    ],
    "wof:name":"Hertz-A-Crete Construction",
    "wof:placetype":"venue"
},
  "geometry": {"coordinates":[-76.949848,40.222901],"type":"Point"}
}