{
  "type": "Feature",
  "properties": {
    "addr:full":"4246 Rhawn St Philadelphia PA 19136",
    "addr:housenumber":"4246",
    "addr:postcode":"19136",
    "addr:street":"Rhawn St",
    "iso:country":"US",
    "sg:address":"4246 Rhawn St",
    "sg:city":"Philadelphia",
    "sg:classifiers":[
        {
            "category":"Wholesale",
            "subcategory":"Sporting Goods",
            "type":"Manufacturing & Wholesale Goods"
        }
    ],
    "sg:phone":"+1   ",
    "sg:postcode":"19136",
    "sg:province":"PA",
    "wof:name":"Rawlinson LLC",
    "wof:placetype":"venue"
},
  "geometry": {"coordinates":[-75.027579,40.039996],"type":"Point"}
}