{
  "type": "Feature",
  "properties": {
    "iso:country":"US",
    "sg:address":"3 Foxwood Ln",
    "sg:city":"Greensburg",
    "sg:classifiers":[
        {
            "category":"Building & Trades",
            "subcategory":"Landscaping Services",
            "type":"Services"
        }
    ],
    "sg:phone":"+1   ",
    "sg:postcode":"15601",
    "sg:province":"PA",
    "wof:name":"Scotts Lawn Service",
    "wof:placetype":"venue"
},
  "geometry": {"coordinates":[-79.495271,40.275468],"type":"Point"}
}