{
  "type": "Feature",
  "properties": {
    "iso:country":"US",
    "sg:address":"59 Keith St",
    "sg:city":"Hanover Twp",
    "sg:classifiers":[
        {
            "category":"Building & Trades",
            "subcategory":"Cleaning & Sanitation",
            "type":"Services"
        },
        {
            "category":"Retail",
            "subcategory":"Laundry & Dry Cleaning",
            "type":"Services"
        }
    ],
    "sg:phone":"+1 570 819 2252",
    "sg:postcode":"18706",
    "sg:province":"PA",
    "sg:tags":[
        "upholstery",
        "janitor",
        "carpet"
    ],
    "wof:name":"Best Carpet & Upholstery Clg",
    "wof:placetype":"venue"
},
  "geometry": {"coordinates":[-75.919847,41.23113],"type":"Point"}
}