{
  "type": "Feature",
  "properties": {
    "addr:full":"9893 Pettis Rd Meadville PA 16335",
    "addr:housenumber":"9893",
    "addr:postcode":"16335",
    "addr:street":"Pettis Rd",
    "iso:country":"US",
    "sg:address":"9893 Pettis Rd",
    "sg:city":"Meadville",
    "sg:classifiers":[
        {
            "category":"Building & Trades",
            "subcategory":"Construction",
            "type":"Services"
        }
    ],
    "sg:phone":"+1 814 333 1068",
    "sg:postcode":"16335",
    "sg:province":"PA",
    "sg:tags":[
        "general",
        "contractor"
    ],
    "wof:name":"David Beachy",
    "wof:placetype":"venue"
},
  "geometry": {"coordinates":[-80.070082,41.584438],"type":"Point"}
}