{
  "type": "Feature",
  "properties": {
    "iso:country":"US",
    "sg:address":"2173 Embassy Dr",
    "sg:city":"Lancaster",
    "sg:classifiers":[
        {
            "category":"Professional",
            "subcategory":"Accounting & Tax Preparation",
            "type":"Services"
        }
    ],
    "sg:phone":"+1 717 431 3047",
    "sg:postcode":"17603",
    "sg:province":"PA",
    "sg:tags":[
        "accountant"
    ],
    "wof:name":"Faren & Assoc PC",
    "wof:placetype":"venue"
},
  "geometry": {"coordinates":[-76.359419,40.044633],"type":"Point"}
}