{
  "type": "Feature",
  "properties": {
    "iso:country":"US",
    "sg:address":"101 Bentley Ave",
    "sg:city":"Bala Cynwyd",
    "sg:classifiers":[
        {
            "category":"Building & Trades",
            "subcategory":"Construction",
            "type":"Services"
        }
    ],
    "sg:phone":"+1 610 667 0629",
    "sg:postcode":"19004",
    "sg:province":"PA",
    "sg:tags":[
        "repairing",
        "remodeling",
        "contractor"
    ],
    "wof:name":"Ted Goldsborough Svc",
    "wof:placetype":"venue"
},
  "geometry": {"coordinates":[-75.240139,40.006857],"type":"Point"}
}