{
  "type": "Feature",
  "properties": {
    "iso:country":"US",
    "sg:address":"445 Sterling Rd",
    "sg:city":"Tobyhanna",
    "sg:classifiers":[
        {
            "category":"Real Estate",
            "subcategory":"Real Estate Agent",
            "type":"Services"
        }
    ],
    "sg:phone":"+1 570 839 7055",
    "sg:postcode":"18466",
    "sg:province":"PA",
    "sg:tags":[
        "agency"
    ],
    "wof:name":"William Klod Realty",
    "wof:placetype":"venue"
},
  "geometry": {"coordinates":[-75.35759299999999,41.152471],"type":"Point"}
}