{
  "type": "Feature",
  "properties": {
    "iso:country":"US",
    "sg:address":"920 Wildwood Park Drive",
    "sg:city":"Harrisburg",
    "sg:classifiers":[
        {
            "category":"Travel",
            "subcategory":"Hotels & Motels",
            "type":"Entertainment"
        },
        {
            "category":"Retail",
            "subcategory":"Event Space",
            "type":"Services"
        }
    ],
    "sg:phone":"+1 717 233 3304",
    "sg:postcode":"17110",
    "sg:province":"PA",
    "sg:tags":[
        "venue"
    ],
    "sg:website":"www.staybridge.com",
    "wof:name":"Staybridge Suites Harrisburg Hershey",
    "wof:placetype":"venue"
},
  "geometry": {"coordinates":[-76.88647,40.290085],"type":"Point"}
}