{
  "type": "Feature",
  "properties": {
    "iso:country":"US",
    "sg:address":"305 Long Ln",
    "sg:city":"York Springs",
    "sg:classifiers":[
        {
            "category":"Home & Garden",
            "subcategory":"Building Materials",
            "type":"Retail Goods"
        }
    ],
    "sg:phone":"+1 717 528 8152",
    "sg:postcode":"17372",
    "sg:province":"PA",
    "sg:tags":[
        "modular"
    ],
    "wof:name":"York Springs Modular Home Sls",
    "wof:placetype":"venue"
},
  "geometry": {"coordinates":[-77.11434,39.993283],"type":"Point"}
}