{
  "type": "Feature",
  "properties": {
    "iso:country":"US",
    "sg:address":"400 Washington St",
    "sg:city":"Reading",
    "sg:classifiers":[
        {
            "category":"Professional",
            "subcategory":"Management & Consulting",
            "type":"Services"
        }
    ],
    "sg:phone":"+1   ",
    "sg:postcode":"19601",
    "sg:province":"PA",
    "sg:tags":[
        "organization",
        "employer"
    ],
    "wof:name":"Keystone Prof Employers",
    "wof:placetype":"venue"
},
  "geometry": {"coordinates":[-75.928838,40.336985],"type":"Point"}
}