{
  "type": "Feature",
  "properties": {
    "iso:country":"US",
    "sg:address":"132 Mulberry Dr",
    "sg:city":"Everett",
    "sg:classifiers":[
        {
            "category":"Home & Garden",
            "subcategory":"Furniture",
            "type":"Retail Goods"
        }
    ],
    "sg:phone":"+1   ",
    "sg:postcode":"15537",
    "sg:province":"PA",
    "sg:tags":[
        "residential",
        "construction"
    ],
    "wof:name":"Mark Hahns Construction & Bldg",
    "wof:placetype":"venue"
},
  "geometry": {"coordinates":[-78.35113200000001,39.965189],"type":"Point"}
}