{
  "type": "Feature",
  "properties": {
    "iso:country":"US",
    "sg:address":"1604 Settlers Grove Ln",
    "sg:city":"Wexford",
    "sg:classifiers":[
        {
            "category":"Real Estate",
            "subcategory":"Architect",
            "type":"Services"
        }
    ],
    "sg:phone":"+1 724 934 7868",
    "sg:postcode":"15090",
    "sg:province":"PA",
    "sg:website":"www.finalmove.com",
    "wof:name":"Schlueb Architecture",
    "wof:placetype":"venue"
},
  "geometry": {"coordinates":[-80.07906199999999,40.604488],"type":"Point"}
}