{
  "type": "Feature",
  "properties": {
    "addr:full":"420 Hays Ave Pittsburgh PA 15210",
    "addr:housenumber":"420",
    "addr:postcode":"15210",
    "addr:street":"Hays Ave",
    "iso:country":"US",
    "sg:address":"420 Hays Ave",
    "sg:city":"Pittsburgh",
    "sg:classifiers":[
        {
            "category":"Personal",
            "subcategory":"Beauty Salon",
            "type":"Services"
        }
    ],
    "sg:phone":"+1   ",
    "sg:postcode":"15210",
    "sg:province":"PA",
    "sg:tags":[
        "shop"
    ],
    "wof:name":"California",
    "wof:placetype":"venue"
},
  "geometry": {"coordinates":[-79.987391,40.410399],"type":"Point"}
}