{
  "type": "Feature",
  "properties": {
    "iso:country":"US",
    "sg:address":"3738 Birney Ave",
    "sg:city":"Moosic",
    "sg:classifiers":[
        {
            "category":"Professional",
            "subcategory":"Lawyer & Legal Services",
            "type":"Services"
        }
    ],
    "sg:phone":"+1 570 961 0444",
    "sg:postcode":"18507",
    "sg:province":"PA",
    "sg:tags":[
        "attorney"
    ],
    "wof:name":"Peter W Chapla",
    "wof:placetype":"venue"
},
  "geometry": {"coordinates":[-75.706818,41.371688],"type":"Point"}
}