{
  "type": "Feature",
  "properties": {
    "addr:full":"6703 Germantown Ave Philadelphia PA 19119",
    "addr:housenumber":"6703",
    "addr:postcode":"19119",
    "addr:street":"Germantown Ave",
    "iso:country":"US",
    "sg:address":"6703 Germantown Ave",
    "sg:city":"Philadelphia",
    "sg:classifiers":[
        {
            "category":"Professional",
            "subcategory":"Management & Consulting",
            "type":"Services"
        }
    ],
    "sg:phone":"+1 215 848 4380",
    "sg:postcode":"19119",
    "sg:province":"PA",
    "sg:tags":[
        "consultant",
        "business"
    ],
    "wof:name":"Allen Zaklad Assoc",
    "wof:placetype":"venue"
},
  "geometry": {"coordinates":[-75.185585,40.052394],"type":"Point"}
}