{
  "type": "Feature",
  "properties": {
    "iso:country":"US",
    "sg:address":"104 Cedarbrook Ct",
    "sg:city":"Oakdale",
    "sg:classifiers":[
        {
            "category":"Health Services",
            "subcategory":"Doctor",
            "type":"Services"
        }
    ],
    "sg:phone":"+1   ",
    "sg:postcode":"15071",
    "sg:province":"PA",
    "sg:tags":[
        "medical"
    ],
    "wof:name":"Aleksandar Vranjican MD",
    "wof:placetype":"venue"
},
  "geometry": {"coordinates":[-80.217558,40.423722],"type":"Point"}
}