{
  "type": "Feature",
  "properties": {
    "iso:country":"US",
    "sg:address":"27 S 8th St Apt 1",
    "sg:city":"Allentown",
    "sg:classifiers":[
        {
            "category":"Banks & Credit Unions",
            "subcategory":"Financial Services",
            "type":"Services"
        }
    ],
    "sg:phone":"+1 610 776 8283",
    "sg:postcode":"18101",
    "sg:province":"PA",
    "sg:tags":[
        "broker",
        "mortgage"
    ],
    "wof:name":"Affordable Home Funding",
    "wof:placetype":"venue"
},
  "geometry": {"coordinates":[-75.473198,40.601002],"type":"Point"}
}