{
  "type": "Feature",
  "properties": {
    "iso:country":"US",
    "sg:address":"230 W Middlesex Dr",
    "sg:city":"Carlisle",
    "sg:phone":"+1   ",
    "sg:postcode":"17013",
    "sg:province":"PA",
    "sg:tags":[
        "wheat",
        "farm",
        "cash",
        "crop",
        "field",
        "grain"
    ],
    "wof:name":"Sarah Fought",
    "wof:placetype":"venue"
},
  "geometry": {"coordinates":[-77.145791,40.251222],"type":"Point"}
}