{
  "type": "Feature",
  "properties": {
    "iso:country":"US",
    "sg:address":"2772 Valley Woods Rd",
    "sg:city":"Hatfield",
    "sg:classifiers":[
        {
            "category":"Manufacturing",
            "subcategory":"Retail Goods",
            "type":"Manufacturing & Wholesale Goods"
        }
    ],
    "sg:phone":"+1 215 822 5909",
    "sg:postcode":"19440",
    "sg:province":"PA",
    "sg:tags":[
        "product",
        "contract",
        "mfg"
    ],
    "wof:name":"Woltman Industries",
    "wof:placetype":"venue"
},
  "geometry": {"coordinates":[-75.265565,40.276767],"type":"Point"}
}