{
  "type": "Feature",
  "properties": {
    "iso:country":"US",
    "sg:address":"114 Silver Dr",
    "sg:city":"Renfrew",
    "sg:classifiers":[
        {
            "category":"Manufacturing",
            "subcategory":"Lumber",
            "type":"Manufacturing & Wholesale Goods"
        }
    ],
    "sg:phone":"+1   ",
    "sg:postcode":"16053",
    "sg:province":"PA",
    "sg:tags":[
        "mill"
    ],
    "wof:name":"Shedio Logging & Lumber",
    "wof:placetype":"venue"
},
  "geometry": {"coordinates":[-79.96573600000001,40.838518],"type":"Point"}
}