{
  "type": "Feature",
  "properties": {
    "iso:country":"US",
    "sg:address":"1521 Dickson Ave",
    "sg:city":"Scranton",
    "sg:classifiers":[
        {
            "category":"Wholesale",
            "subcategory":"Auto Parts",
            "type":"Manufacturing & Wholesale Goods"
        }
    ],
    "sg:phone":"+1 570 558 3027",
    "sg:postcode":"18509",
    "sg:province":"PA",
    "sg:tags":[
        "automobile"
    ],
    "wof:name":"Clark's Auto Svc",
    "wof:placetype":"venue"
},
  "geometry": {"coordinates":[-75.651723,41.431079],"type":"Point"}
}