{
  "type": "Feature",
  "properties": {
    "addr:full":"92 Riley Rd Gettysburg PA 17325",
    "addr:housenumber":"92",
    "addr:postcode":"17325",
    "addr:street":"Riley Rd",
    "iso:country":"US",
    "sg:address":"92 Riley Rd",
    "sg:city":"Gettysburg",
    "sg:classifiers":[
        {
            "category":"Wholesale",
            "subcategory":"Auto Parts",
            "type":"Manufacturing & Wholesale Goods"
        }
    ],
    "sg:phone":"+1 717 334 6177",
    "sg:postcode":"17325",
    "sg:province":"PA",
    "sg:tags":[
        "automobile",
        "rebuilt",
        "used"
    ],
    "wof:name":"Riley's Used Auto Parts",
    "wof:placetype":"venue"
},
  "geometry": {"coordinates":[-77.183649,39.856827],"type":"Point"}
}