{
  "type": "Feature",
  "properties": {
    "addr:full":"243 W School House Ln Philadelphia PA 19144",
    "addr:housenumber":"243",
    "addr:postcode":"19144",
    "addr:street":"W School House Ln",
    "iso:country":"US",
    "sg:address":"243 W School House Ln",
    "sg:city":"Philadelphia",
    "sg:classifiers":[
        {
            "category":"Health Services",
            "subcategory":"Clinic",
            "type":"Services"
        }
    ],
    "sg:phone":"+1   ",
    "sg:postcode":"19144",
    "sg:province":"PA",
    "sg:tags":[
        "specialty",
        "outpatient"
    ],
    "wof:name":"Community Rhblttion Residences",
    "wof:placetype":"venue"
},
  "geometry": {"coordinates":[-75.177712,40.029724],"type":"Point"}
}