{
  "type": "Feature",
  "properties": {
    "addr:full":"208 Stevenson St Sayre PA 18840",
    "addr:housenumber":"208",
    "addr:postcode":"18840",
    "addr:street":"Stevenson St",
    "iso:country":"US",
    "sg:address":"208 Stevenson St",
    "sg:city":"Sayre",
    "sg:classifiers":[
        {
            "category":"Professional",
            "subcategory":"Advertising",
            "type":"Services"
        }
    ],
    "sg:phone":"+1   ",
    "sg:postcode":"18840",
    "sg:province":"PA",
    "sg:tags":[
        "agency"
    ],
    "wof:name":"Walker Hill Advertising",
    "wof:placetype":"venue"
},
  "geometry": {"coordinates":[-76.51924699999999,41.98537],"type":"Point"}
}