{
  "type": "Feature",
  "properties": {
    "iso:country":"US",
    "sg:address":"155 Quarry Rd",
    "sg:city":"Leola",
    "sg:classifiers":[
        {
            "category":"Retail",
            "subcategory":"Animal Services",
            "type":"Services"
        }
    ],
    "sg:phone":"+1 717 335 7355",
    "sg:postcode":"17540",
    "sg:province":"PA",
    "sg:tags":[
        "horse",
        "training"
    ],
    "wof:name":"Crescendo Training Ctr",
    "wof:placetype":"venue"
},
  "geometry": {"coordinates":[-76.218467,40.096584],"type":"Point"}
}