{
  "type": "Feature",
  "properties": {
    "addr:full":"11600 Roosevelt Blvd Philadelphia PA 19116",
    "addr:housenumber":"11600",
    "addr:postcode":"19116",
    "addr:street":"Roosevelt Blvd",
    "iso:country":"US",
    "sg:address":"11600 Roosevelt Blvd",
    "sg:city":"Philadelphia",
    "sg:classifiers":[
        {
            "category":"Recreation",
            "type":"Entertainment"
        }
    ],
    "sg:phone":"+1   ",
    "sg:postcode":"19116",
    "sg:province":"PA",
    "sg:tags":[
        "skating",
        "roller",
        "rink"
    ],
    "wof:name":"Palace Roller & In-Line",
    "wof:placetype":"venue"
},
  "geometry": {"coordinates":[-75.002623,40.104363],"type":"Point"}
}