{
  "type": "Feature",
  "properties": {
    "addr:full":"5100 Neville Rd Neville Island PA 15225",
    "addr:housenumber":"5100",
    "addr:postcode":"15225",
    "addr:street":"Neville Rd",
    "iso:country":"US",
    "sg:address":"5100 Neville Rd",
    "sg:city":"Neville Island",
    "sg:classifiers":[
        {
            "category":"Manufacturing",
            "subcategory":"Tools & Machinery",
            "type":"Manufacturing & Wholesale Goods"
        }
    ],
    "sg:phone":"+1 412 264 5976",
    "sg:postcode":"15225",
    "sg:province":"PA",
    "sg:tags":[
        "cutting",
        "gear"
    ],
    "wof:name":"Pittsburgh Gear Co",
    "wof:placetype":"venue"
},
  "geometry": {"coordinates":[-80.126631,40.508527],"type":"Point"}
}