{
  "type": "Feature",
  "properties": {
    "iso:country":"US",
    "sg:address":"1650 Metropolitan St",
    "sg:city":"Pittsburgh",
    "sg:classifiers":[
        {
            "category":"Bars & Pubs",
            "type":"Food & Drink"
        },
        {
            "category":"Bars & Pubs",
            "subcategory":"Nightclub",
            "type":"Food & Drink"
        }
    ],
    "sg:phone":"+1 412 224 4404",
    "sg:postcode":"15233",
    "sg:province":"PA",
    "sg:tags":[
        "club",
        "night"
    ],
    "wof:name":"Mansion At Maple Heights",
    "wof:placetype":"venue"
},
  "geometry": {"coordinates":[-80.03131999999999,40.455549],"type":"Point"}
}