{
  "type": "Feature",
  "properties": {
    "addr:full":"253 Schuylkill Rd Phoenixville PA 19460",
    "addr:housenumber":"253",
    "addr:postcode":"19460",
    "addr:street":"Schuylkill Rd",
    "iso:country":"US",
    "sg:address":"253 Schuylkill Rd",
    "sg:city":"Phoenixville",
    "sg:classifiers":[
        {
            "category":"Restaurant",
            "type":"Food & Drink"
        }
    ],
    "sg:menulink":"http://www.allmenus.com/pa/east-pikeland/66236-dominos-pizza/menu/",
    "sg:phone":"+1 610 933 3030",
    "sg:postcode":"19460",
    "sg:province":"PA",
    "sg:tags":[
        "american",
        "wing",
        "pizza"
    ],
    "wof:name":"Domino's Pizza",
    "wof:placetype":"venue"
},
  "geometry": {"coordinates":[-75.54231299999999,40.135701],"type":"Point"}
}