{
  "type": "Feature",
  "properties": {
    "iso:country":"US",
    "sg:address":"1053 Pulinski Rd",
    "sg:city":"Warminster",
    "sg:classifiers":[
        {
            "category":"Health Services",
            "subcategory":"Hospital",
            "type":"Services"
        }
    ],
    "sg:phone":"+1 215 682 7445",
    "sg:postcode":"18974",
    "sg:province":"PA",
    "sg:tags":[
        "equipment",
        "supply"
    ],
    "wof:name":"Philcare Hme Inc",
    "wof:placetype":"venue"
},
  "geometry": {"coordinates":[-75.058672,40.222553],"type":"Point"}
}