{
  "type": "Feature",
  "properties": {
    "iso:country":"US",
    "sg:address":"150 McCracken Run Rd",
    "sg:city":"Du Bois",
    "sg:classifiers":[
        {
            "category":"Restaurant",
            "type":"Food & Drink"
        }
    ],
    "sg:phone":"+1 814 371 9686",
    "sg:postcode":"15801",
    "sg:province":"PA",
    "sg:tags":[
        "pizzeria"
    ],
    "wof:name":"Playtime Pizza Inc",
    "wof:placetype":"venue"
},
  "geometry": {"coordinates":[-78.739087,41.133554],"type":"Point"}
}