{
  "type": "Feature",
  "properties": {
    "iso:country":"US",
    "sg:address":"6453 Martins Mill Rd",
    "sg:city":"Philadelphia",
    "sg:classifiers":[
        {
            "category":"Social Services",
            "subcategory":"Adult Care",
            "type":"Services"
        }
    ],
    "sg:phone":"+1 215 722 4711",
    "sg:postcode":"19111",
    "sg:province":"PA",
    "sg:tags":[
        "home",
        "group"
    ],
    "wof:name":"Kensington Community-Indvdl",
    "wof:placetype":"venue"
},
  "geometry": {"coordinates":[-75.091098,40.047059],"type":"Point"}
}