{
  "type": "Feature",
  "properties": {
    "addr:full":"713 Main St Pittsburgh PA 15215",
    "addr:housenumber":"713",
    "addr:postcode":"15215",
    "addr:street":"Main St",
    "iso:country":"US",
    "sg:address":"713 Main St",
    "sg:city":"Pittsburgh",
    "sg:classifiers":[
        {
            "category":"Restaurant",
            "type":"Food & Drink"
        }
    ],
    "sg:menulink":"http://www.allmenus.com/pa/sharpsburg/286536-club-sandwich/menu/",
    "sg:phone":"+1 412 781 6860",
    "sg:postcode":"15215",
    "sg:province":"PA",
    "sg:tags":[
        "american"
    ],
    "wof:name":"Club Sandwich",
    "wof:placetype":"venue"
},
  "geometry": {"coordinates":[-79.934635,40.494613],"type":"Point"}
}