{
  "type": "Feature",
  "properties": {
    "iso:country":"US",
    "sg:address":"622 Lancaster Ave",
    "sg:city":"Berwyn",
    "sg:classifiers":[
        {
            "category":"Personal",
            "subcategory":"Beauty Salon",
            "type":"Services"
        }
    ],
    "sg:phone":"+1 610 296 4940",
    "sg:postcode":"19312",
    "sg:province":"PA",
    "wof:name":"Above Beyond Skincare",
    "wof:placetype":"venue"
},
  "geometry": {"coordinates":[-75.440839,40.048048],"type":"Point"}
}