{
  "type": "Feature",
  "properties": {
    "iso:country":"US",
    "sg:address":"257 W Uwchlan Ave",
    "sg:city":"Downingtown",
    "sg:classifiers":[
        {
            "category":"Professional",
            "subcategory":"Employment Agencies",
            "type":"Services"
        }
    ],
    "sg:phone":"+1   ",
    "sg:postcode":"19335",
    "sg:province":"PA",
    "wof:name":"Career Mappers",
    "wof:placetype":"venue"
},
  "geometry": {"coordinates":[-75.683684,40.029654],"type":"Point"}
}