{
  "type": "Feature",
  "properties": {
    "iso:country":"US",
    "sg:address":"317 B St",
    "sg:city":"Middletown",
    "sg:classifiers":[
        {
            "category":"Professional",
            "subcategory":"Accounting & Tax Preparation",
            "type":"Services"
        }
    ],
    "sg:phone":"+1 717 774 1930",
    "sg:postcode":"17013",
    "sg:province":"PA",
    "sg:tags":[
        "accountant"
    ],
    "wof:name":"John R Cox CPA",
    "wof:placetype":"venue"
},
  "geometry": {"coordinates":[-77.195713,40.209732],"type":"Point"}
}