{
  "type": "Feature",
  "properties": {
    "iso:country":"US",
    "sg:address":"4596 Clover Hill Cir",
    "sg:city":"Walnutport",
    "sg:classifiers":[
        {
            "category":"Building & Trades",
            "subcategory":"Construction",
            "type":"Services"
        }
    ],
    "sg:phone":"+1   ",
    "sg:postcode":"18088",
    "sg:province":"PA",
    "sg:tags":[
        "house",
        "construct",
        "contractor"
    ],
    "wof:name":"Hausman Aluminum",
    "wof:placetype":"venue"
},
  "geometry": {"coordinates":[-75.568248,40.75357],"type":"Point"}
}