{
  "type": "Feature",
  "properties": {
    "iso:country":"US",
    "sg:address":"200 S 4th St",
    "sg:city":"Reading",
    "sg:classifiers":[
        {
            "category":"Food & Beverages",
            "subcategory":"Groceries & Convenience Stores",
            "type":"Retail Goods"
        }
    ],
    "sg:phone":"+1 610 373 4466",
    "sg:postcode":"19602",
    "sg:province":"PA",
    "sg:tags":[
        "grocer"
    ],
    "wof:name":"Santo Santiesteban Grocery",
    "wof:placetype":"venue"
},
  "geometry": {"coordinates":[-75.930008,40.330718],"type":"Point"}
}