{
  "type": "Feature",
  "properties": {
    "iso:country":"US",
    "sg:address":"460 N Gulph Rd",
    "sg:city":"King Of Prussia",
    "sg:classifiers":[
        {
            "category":"Restaurant",
            "type":"Food & Drink"
        }
    ],
    "sg:phone":"+1 610 265 1113",
    "sg:postcode":"19406",
    "sg:province":"PA",
    "sg:tags":[
        "sandwich"
    ],
    "wof:name":"Mrs C's",
    "wof:placetype":"venue"
},
  "geometry": {"coordinates":[-75.40276900000001,40.086318],"type":"Point"}
}