{
  "type": "Feature",
  "properties": {
    "addr:full":"10778 Jamestown Rd Wattsburg PA 16442",
    "addr:housenumber":"10778",
    "addr:postcode":"16442",
    "addr:street":"Jamestown Rd",
    "iso:country":"US",
    "sg:address":"10778 Jamestown Rd",
    "sg:city":"Wattsburg",
    "sg:classifiers":[
        {
            "category":"Farming",
            "subcategory":"Farm",
            "type":"Manufacturing & Wholesale Goods"
        }
    ],
    "sg:phone":"+1   ",
    "sg:postcode":"16442",
    "sg:province":"PA",
    "sg:tags":[
        "crop",
        "general"
    ],
    "wof:name":"David Bensik",
    "wof:placetype":"venue"
},
  "geometry": {"coordinates":[-79.780192,42.02155],"type":"Point"}
}