{
  "type": "Feature",
  "properties": {
    "iso:country":"US",
    "sg:address":"3671 Old Hershey Rd",
    "sg:city":"Elizabethtown",
    "sg:classifiers":[
        {
            "category":"Shopping",
            "subcategory":"Used Merchandise",
            "type":"Retail Goods"
        }
    ],
    "sg:phone":"+1   ",
    "sg:postcode":"17022",
    "sg:province":"PA",
    "wof:name":"Ponyhill Antiques",
    "wof:placetype":"venue"
},
  "geometry": {"coordinates":[-76.62587600000001,40.238616],"type":"Point"}
}