{
  "type": "Feature",
  "properties": {
    "addr:full":"462 Elmhurst Ave Bethlehem PA 18017",
    "addr:housenumber":"462",
    "addr:postcode":"18017",
    "addr:street":"Elmhurst Ave",
    "iso:country":"US",
    "sg:address":"462 Elmhurst Ave",
    "sg:city":"Bethlehem",
    "sg:classifiers":[
        {
            "category":"Personal",
            "subcategory":"Beauty Salon",
            "type":"Services"
        }
    ],
    "sg:phone":"+1 610 866 8078",
    "sg:postcode":"18017",
    "sg:province":"PA",
    "sg:tags":[
        "make",
        "studio"
    ],
    "wof:name":"Mary Kay Cosmetics",
    "wof:placetype":"venue"
},
  "geometry": {"coordinates":[-75.369671,40.641773],"type":"Point"}
}