{
  "type": "Feature",
  "properties": {
    "iso:country":"US",
    "sg:address":"4700 Union Deposit Rd",
    "sg:city":"Harrisburg",
    "sg:classifiers":[
        {
            "category":"Health Services",
            "subcategory":"Doctor",
            "type":"Services"
        }
    ],
    "sg:phone":"+1 717 652 6605",
    "sg:postcode":"17111",
    "sg:province":"PA",
    "sg:tags":[
        "physician",
        "reproductive",
        "gynecology",
        "endocrinology",
        "surgeons",
        "obstetrics",
        "surgeon",
        "public"
    ],
    "wof:name":"Women First",
    "wof:placetype":"venue"
},
  "geometry": {"coordinates":[-76.804813,40.280037],"type":"Point"}
}