{
  "type": "Feature",
  "properties": {
    "addr:full":"445 Rebecca Ave Wilkinsburg PA 15221",
    "addr:housenumber":"445",
    "addr:postcode":"15221",
    "addr:street":"Rebecca Ave",
    "iso:country":"US",
    "sg:address":"445 Rebecca Ave",
    "sg:city":"Wilkinsburg",
    "sg:classifiers":[
        {
            "category":"Professional",
            "subcategory":"Computer Services",
            "type":"Services"
        }
    ],
    "sg:phone":"+1 412 271 4273",
    "sg:postcode":"15221",
    "sg:province":"PA",
    "sg:tags":[
        "repair"
    ],
    "wof:name":"Tenc Computer Svc Inc",
    "wof:placetype":"venue"
},
  "geometry": {"coordinates":[-79.889914,40.441743],"type":"Point"}
}