{
  "type": "Feature",
  "properties": {
    "addr:full":"312 Newlins Rd E Easton PA 18040",
    "addr:housenumber":"312",
    "addr:postcode":"18040",
    "addr:street":"Newlins Rd E",
    "iso:country":"US",
    "sg:address":"312 Newlins Rd E",
    "sg:city":"Easton",
    "sg:classifiers":[
        {
            "category":"Retail",
            "subcategory":"Animal Services",
            "type":"Services"
        }
    ],
    "sg:phone":"+1 610 253 0048",
    "sg:postcode":"18040",
    "sg:province":"PA",
    "sg:tags":[
        "pet",
        "boarding",
        "sitting"
    ],
    "wof:name":"Mountain View Kennels",
    "wof:placetype":"venue"
},
  "geometry": {"coordinates":[-75.205499,40.735289],"type":"Point"}
}