{
  "type": "Feature",
  "properties": {
    "iso:country":"US",
    "sg:address":"620 Howard Ave",
    "sg:city":"Altoona",
    "sg:classifiers":[
        {
            "category":"Health Services",
            "subcategory":"Doctor",
            "type":"Services"
        }
    ],
    "sg:phone":"+1 814 889 2328",
    "sg:postcode":"16601",
    "sg:province":"PA",
    "sg:tags":[
        "physician",
        "surgeons",
        "otorhinolaryngology",
        "throat",
        "internal",
        "nose",
        "vascular",
        "medicine",
        "surgeon",
        "ear",
        "surgery"
    ],
    "sg:website":"http://cvtsaltoona.com",
    "wof:name":"Cardiovascular & Thoracic Surgery of Altoona Inc",
    "wof:placetype":"venue"
},
  "geometry": {"coordinates":[-78.398133,40.521206],"type":"Point"}
}