{
  "type": "Feature",
  "properties": {
    "iso:country":"US",
    "sg:address":"5634 Baum Blvd",
    "sg:city":"Pittsburgh",
    "sg:classifiers":[
        {
            "category":"Autos & Motor Vehicles",
            "subcategory":"Auto Supplies",
            "type":"Retail Goods"
        }
    ],
    "sg:phone":"+1 412 362 9123",
    "sg:postcode":"15206",
    "sg:province":"PA",
    "sg:tags":[
        "tire"
    ],
    "wof:name":"Bruce Brothers Tires",
    "wof:placetype":"venue"
},
  "geometry": {"coordinates":[-79.93549400000001,40.45777],"type":"Point"}
}