{
  "type": "Feature",
  "properties": {
    "addr:full":"1650 Bobali Dr Harrisburg PA 17104",
    "addr:housenumber":"1650",
    "addr:postcode":"17104",
    "addr:street":"Bobali Dr",
    "iso:country":"US",
    "sg:address":"1650 Bobali Dr",
    "sg:city":"Harrisburg",
    "sg:classifiers":[
        {
            "category":"Wholesale",
            "subcategory":"Books, Periodicals, & Newspapers",
            "type":"Manufacturing & Wholesale Goods"
        }
    ],
    "sg:phone":"+1 717 704 1029",
    "sg:postcode":"17104",
    "sg:province":"PA",
    "sg:tags":[
        "publisher",
        "book"
    ],
    "wof:name":"Dgs-Bureau Of Publications",
    "wof:placetype":"venue"
},
  "geometry": {"coordinates":[-76.84887999999999,40.248207],"type":"Point"}
}