{
  "type": "Feature",
  "properties": {
    "addr:full":"1171 Joann Ave Ephrata PA 17522",
    "addr:housenumber":"1171",
    "addr:postcode":"17522",
    "addr:street":"Joann Ave",
    "iso:country":"US",
    "sg:address":"1171 Joann Ave",
    "sg:city":"Ephrata",
    "sg:classifiers":[
        {
            "category":"Building & Trades",
            "subcategory":"Construction",
            "type":"Services"
        }
    ],
    "sg:phone":"+1   ",
    "sg:postcode":"17522",
    "sg:province":"PA",
    "sg:tags":[
        "contractor"
    ],
    "wof:name":"Carpet Installer",
    "wof:placetype":"venue"
},
  "geometry": {"coordinates":[-76.198928,40.188089],"type":"Point"}
}