{
  "type": "Feature",
  "properties": {
    "iso:country":"US",
    "sg:address":"171 W Crawford Ave",
    "sg:city":"Connellsville",
    "sg:classifiers":[
        {
            "category":"Shopping",
            "type":"Retail Goods"
        }
    ],
    "sg:phone":"+1   ",
    "sg:postcode":"15425",
    "sg:province":"PA",
    "sg:tags":[
        "equipment",
        "medical",
        "durable",
        "rent"
    ],
    "wof:name":"Professional Homecare Eqp",
    "wof:placetype":"venue"
},
  "geometry": {"coordinates":[-79.59402,40.01738],"type":"Point"}
}