{
  "type": "Feature",
  "properties": {
    "addr:full":"1153 N Center Ave Somerset PA 15501",
    "addr:housenumber":"1153",
    "addr:postcode":"15501",
    "addr:street":"N Center Ave",
    "iso:country":"US",
    "sg:address":"1153 N Center Ave",
    "sg:city":"Somerset",
    "sg:classifiers":[
        {
            "category":"Shopping",
            "subcategory":"Used Merchandise",
            "type":"Retail Goods"
        }
    ],
    "sg:phone":"+1 814 443 9111",
    "sg:postcode":"15501",
    "sg:province":"PA",
    "sg:tags":[
        "pawnbroker"
    ],
    "wof:name":"Gary's Steals & Deals",
    "wof:placetype":"venue"
},
  "geometry": {"coordinates":[-79.077561,40.020591],"type":"Point"}
}