{
  "type": "Feature",
  "properties": {
    "iso:country":"US",
    "sg:address":"40 W Germantown Pike",
    "sg:city":"Norristown",
    "sg:classifiers":[
        {
            "category":"Health Services",
            "subcategory":"Doctor",
            "type":"Services"
        }
    ],
    "sg:phone":"+1 610 277 8000",
    "sg:postcode":"19401",
    "sg:province":"PA",
    "wof:name":"Spiro Kassis MD",
    "wof:placetype":"venue"
},
  "geometry": {"coordinates":[-75.315534,40.143462],"type":"Point"}
}