{
  "type": "Feature",
  "properties": {
    "iso:country":"US",
    "sg:address":"2640 Westview Dr",
    "sg:city":"Reading",
    "sg:classifiers":[
        {
            "category":"Professional",
            "subcategory":"Lawyer & Legal Services",
            "type":"Services"
        }
    ],
    "sg:phone":"+1   ",
    "sg:postcode":"19610",
    "sg:province":"PA",
    "wof:name":"Brian F Boland",
    "wof:placetype":"venue"
},
  "geometry": {"coordinates":[-75.989919,40.343235],"type":"Point"}
}