{
  "type": "Feature",
  "properties": {
    "iso:country":"US",
    "sg:address":"304 E Fairview St",
    "sg:city":"Coopersburg",
    "sg:classifiers":[
        {
            "category":"Real Estate",
            "subcategory":"Real Estate Services",
            "type":"Services"
        }
    ],
    "sg:phone":"+1 610 282 4700",
    "sg:postcode":"18036",
    "sg:province":"PA",
    "wof:name":"Katzbeck John K Real Estate",
    "wof:placetype":"venue"
},
  "geometry": {"coordinates":[-75.385201,40.514198],"type":"Point"}
}