{
  "type": "Feature",
  "properties": {
    "iso:country":"US",
    "sg:address":"781 Sumneytown Pike",
    "sg:city":"Lansdale",
    "sg:classifiers":[
        {
            "category":"Health Services",
            "subcategory":"Doctor",
            "type":"Services"
        }
    ],
    "sg:phone":"+1 215 699 6139",
    "sg:postcode":"19446",
    "sg:province":"PA",
    "sg:tags":[
        "dentist"
    ],
    "wof:name":"Deborah Koerner DDS",
    "wof:placetype":"venue"
},
  "geometry": {"coordinates":[-75.301063,40.220442],"type":"Point"}
}