{
  "type": "Feature",
  "properties": {
    "addr:full":"478 Lurgan Rd New Hope PA 18938",
    "addr:housenumber":"478",
    "addr:postcode":"18938",
    "addr:street":"Lurgan Rd New",
    "iso:country":"US",
    "sg:address":"478 Lurgan Rd",
    "sg:city":"New Hope",
    "sg:classifiers":[
        {
            "category":"Professional",
            "subcategory":"Management & Consulting",
            "type":"Services"
        }
    ],
    "sg:phone":"+1 215 862 0809",
    "sg:postcode":"18938",
    "sg:province":"PA",
    "sg:tags":[
        "business"
    ],
    "wof:name":"Baldwin House Publishing",
    "wof:placetype":"venue"
},
  "geometry": {"coordinates":[-74.943365,40.320814],"type":"Point"}
}