{
  "type": "Feature",
  "properties": {
    "iso:country":"US",
    "sg:address":"1810 Northway Rd",
    "sg:city":"Williamsport",
    "sg:classifiers":[
        {
            "category":"Restaurant",
            "type":"Food & Drink"
        }
    ],
    "sg:phone":"+1 570 322 6871",
    "sg:postcode":"17701",
    "sg:province":"PA",
    "sg:tags":[
        "pizza"
    ],
    "wof:name":"Joe's Pizza",
    "wof:placetype":"venue"
},
  "geometry": {"coordinates":[-76.969886,41.260317],"type":"Point"}
}