{
  "type": "Feature",
  "properties": {
    "iso:country":"US",
    "sg:address":"88 S Franklin St",
    "sg:city":"Wilkes Barre",
    "sg:classifiers":[
        {
            "category":"Professional",
            "subcategory":"Lawyer & Legal Services",
            "type":"Services"
        }
    ],
    "sg:phone":"+1   ",
    "sg:postcode":"18701",
    "sg:province":"PA",
    "wof:name":"Polishan Timothy P Esq",
    "wof:placetype":"venue"
},
  "geometry": {"coordinates":[-75.88464999999999,41.246001],"type":"Point"}
}