{
  "type": "Feature",
  "properties": {
    "addr:full":"1320 Storms Store Rd New Oxford PA 17350",
    "addr:housenumber":"1320",
    "addr:postcode":"17350",
    "addr:street":"Storms Store Rd",
    "iso:country":"US",
    "sg:address":"1320 Storms Store Rd",
    "sg:city":"New Oxford",
    "sg:classifiers":[
        {
            "category":"Retail",
            "subcategory":"Veterinary Services",
            "type":"Services"
        }
    ],
    "sg:phone":"+1 717 624 4550",
    "sg:postcode":"17350",
    "sg:province":"PA",
    "sg:tags":[
        "veterinarian"
    ],
    "wof:name":"Adams Animal Hospital",
    "wof:placetype":"venue"
},
  "geometry": {"coordinates":[-77.080834,39.83231],"type":"Point"}
}