{
  "type": "Feature",
  "properties": {
    "addr:full":"1200 Washington Rd Washington PA 15301",
    "addr:housenumber":"1200",
    "addr:postcode":"15301",
    "addr:street":"Washington Rd",
    "iso:country":"US",
    "sg:address":"1200 Washington Rd",
    "sg:city":"Washington",
    "sg:classifiers":[
        {
            "category":"Banks & Credit Unions",
            "subcategory":"Bank",
            "type":"Services"
        }
    ],
    "sg:phone":"+1 724 222 4909",
    "sg:postcode":"15301",
    "sg:province":"PA",
    "sg:tags":[
        "loan"
    ],
    "wof:name":"Equity One Inc",
    "wof:placetype":"venue"
},
  "geometry": {"coordinates":[-80.197592,40.210008],"type":"Point"}
}