{
  "type": "Feature",
  "properties": {
    "addr:full":"6907 Easton Rd Pipersville PA 18947",
    "addr:housenumber":"6907",
    "addr:postcode":"18947",
    "addr:street":"Easton Rd",
    "iso:country":"US",
    "sg:address":"6907 Easton Rd",
    "sg:city":"Pipersville",
    "sg:classifiers":[
        {
            "category":"Organizations",
            "subcategory":"Membership Organization",
            "type":"Services"
        },
        {
            "category":"Personal",
            "type":"Services"
        }
    ],
    "sg:phone":"+1 215 766 8678",
    "sg:postcode":"18947",
    "sg:province":"PA",
    "sg:tags":[
        "therapist",
        "massage"
    ],
    "wof:name":"Cloud Hands Healing Arts Cente",
    "wof:placetype":"venue"
},
  "geometry": {"coordinates":[-75.145453,40.422371],"type":"Point"}
}