{
  "type": "Feature",
  "properties": {
    "iso:country":"US",
    "sg:address":"2201 S 7th St",
    "sg:city":"Philadelphia",
    "sg:classifiers":[
        {
            "category":"Restaurant",
            "type":"Food & Drink"
        }
    ],
    "sg:phone":"+1 215 463 1095",
    "sg:postcode":"19148",
    "sg:province":"PA",
    "sg:tags":[
        "vietnamese"
    ],
    "sg:website":"cafechau.com",
    "wof:name":"Cafe Chau",
    "wof:placetype":"venue"
},
  "geometry": {"coordinates":[-75.158339,39.921543],"type":"Point"}
}