{
  "type": "Feature",
  "properties": {
    "addr:full":"916 Elmwood Ave Sharon Hill PA 19079",
    "addr:housenumber":"916",
    "addr:postcode":"19079",
    "addr:street":"Elmwood Ave",
    "iso:country":"US",
    "sg:address":"916 Elmwood Ave",
    "sg:city":"Sharon Hill",
    "sg:classifiers":[
        {
            "category":"Building & Trades",
            "subcategory":"Cleaning & Sanitation",
            "type":"Services"
        }
    ],
    "sg:phone":"+1 610 237 9255",
    "sg:postcode":"19079",
    "sg:province":"PA",
    "sg:tags":[
        "janitor"
    ],
    "wof:name":"Earl Gaymon Sr",
    "wof:placetype":"venue"
},
  "geometry": {"coordinates":[-75.267793,39.905038],"type":"Point"}
}