{
  "type": "Feature",
  "properties": {
    "iso:country":"US",
    "sg:address":"3195 E Prospect Rd",
    "sg:city":"York",
    "sg:classifiers":[
        {
            "category":"Home & Garden",
            "subcategory":"Building Materials",
            "type":"Retail Goods"
        }
    ],
    "sg:phone":"+1 717 757 1551",
    "sg:postcode":"17402",
    "sg:province":"PA",
    "sg:tags":[
        "glass",
        "window",
        "plate"
    ],
    "sg:website":"www.kemxert.com",
    "wof:name":"Kemxert Windshield Repair",
    "wof:placetype":"venue"
},
  "geometry": {"coordinates":[-76.63174600000001,39.961301],"type":"Point"}
}