{
  "type": "Feature",
  "properties": {
    "addr:full":"130 Buck Rd Southampton PA 18966",
    "addr:housenumber":"130",
    "addr:postcode":"18966",
    "addr:street":"Buck Rd",
    "iso:country":"US",
    "sg:address":"130 Buck Rd",
    "sg:city":"Southampton",
    "sg:classifiers":[
        {
            "category":"Wholesale",
            "subcategory":"Machinery & Supplies",
            "type":"Manufacturing & Wholesale Goods"
        }
    ],
    "sg:phone":"+1   ",
    "sg:postcode":"18966",
    "sg:province":"PA",
    "sg:tags":[
        "equipment",
        "industrial"
    ],
    "wof:name":"Saati",
    "wof:placetype":"venue"
},
  "geometry": {"coordinates":[-74.98810899999999,40.168953],"type":"Point"}
}