{
  "type": "Feature",
  "properties": {
    "addr:full":"1114 Sommerset St Mc Keesport PA 15135",
    "addr:housenumber":"1114",
    "addr:postcode":"15135",
    "addr:street":"Sommerset St",
    "iso:country":"US",
    "sg:address":"1114 Sommerset St",
    "sg:city":"Mc Keesport",
    "sg:classifiers":[
        {
            "category":"Food & Beverages",
            "subcategory":"Groceries & Convenience Stores",
            "type":"Retail Goods"
        }
    ],
    "sg:phone":"+1   ",
    "sg:postcode":"15135",
    "sg:province":"PA",
    "wof:name":"Greenock Deli",
    "wof:placetype":"venue"
},
  "geometry": {"coordinates":[-79.80530299999999,40.314858],"type":"Point"}
}