{
  "type": "Feature",
  "properties": {
    "iso:country":"US",
    "sg:address":"3915 Carlisle Rd",
    "sg:city":"Dover",
    "sg:classifiers":[
        {
            "category":"Building & Trades",
            "subcategory":"Construction",
            "type":"Services"
        }
    ],
    "sg:phone":"+1 717 292 5476",
    "sg:postcode":"17315",
    "sg:province":"PA",
    "sg:tags":[
        "home",
        "improvement"
    ],
    "wof:name":"INH Home Improvement",
    "wof:placetype":"venue"
},
  "geometry": {"coordinates":[-76.842292,39.993094],"type":"Point"}
}