{
  "type": "Feature",
  "properties": {
    "iso:country":"US",
    "sg:address":"260 Ash Stop Rd",
    "sg:city":"Evans City",
    "sg:classifiers":[
        {
            "category":"Food & Beverages",
            "subcategory":"Fruits & Vegetables",
            "type":"Retail Goods"
        }
    ],
    "sg:phone":"+1   ",
    "sg:postcode":"16033",
    "sg:province":"PA",
    "sg:tags":[
        "grocery"
    ],
    "wof:name":"Deeners Farm Market",
    "wof:placetype":"venue"
},
  "geometry": {"coordinates":[-80.026121,40.786332],"type":"Point"}
}