{
  "type": "Feature",
  "properties": {
    "addr:full":"180 Curry Hollow Rd Pittsburgh PA 15236",
    "addr:housenumber":"180",
    "addr:postcode":"15236",
    "addr:street":"Curry Hollow Rd",
    "iso:country":"US",
    "sg:address":"180 Curry Hollow Rd",
    "sg:city":"Pittsburgh",
    "sg:classifiers":[
        {
            "category":"Insurance",
            "subcategory":"Insurance Agent",
            "type":"Services"
        },
        {
            "category":"Insurance",
            "subcategory":"Hazard Insurance",
            "type":"Services"
        },
        {
            "category":"Insurance",
            "subcategory":"Title Insurance",
            "type":"Services"
        },
        {
            "category":"Insurance",
            "subcategory":"Life Insurance",
            "type":"Services"
        }
    ],
    "sg:phone":"+1 412 655 3600",
    "sg:postcode":"15236",
    "sg:province":"PA",
    "sg:tags":[
        "business",
        "auto",
        "commercial",
        "homeowner",
        "motorcycle",
        "renter"
    ],
    "wof:name":"Allstate Insurance Company - Blair Bogdan",
    "wof:placetype":"venue"
},
  "geometry": {"coordinates":[-79.96870800000001,40.338145],"type":"Point"}
}