{
  "type": "Feature",
  "properties": {
    "iso:country":"US",
    "sg:address":"1118 E Philadelphia St",
    "sg:city":"York",
    "sg:classifiers":[
        {
            "category":"Retail",
            "subcategory":"Car Wash",
            "type":"Services"
        }
    ],
    "sg:phone":"+1 717 846 6094",
    "sg:postcode":"17403",
    "sg:province":"PA",
    "sg:tags":[
        "automobile",
        "detail",
        "clean"
    ],
    "wof:name":"Stoner's Detail Shop",
    "wof:placetype":"venue"
},
  "geometry": {"coordinates":[-76.705865,39.972979],"type":"Point"}
}