{
  "type": "Feature",
  "properties": {
    "iso:country":"US",
    "sg:address":"2961 Kanes Rd",
    "sg:city":"Willow Grove",
    "sg:classifiers":[
        {
            "category":"Banks & Credit Unions",
            "subcategory":"Investment Brokerage",
            "type":"Services"
        }
    ],
    "sg:phone":"+1   ",
    "sg:postcode":"19090",
    "sg:province":"PA",
    "sg:tags":[
        "advisory"
    ],
    "wof:name":"Comprehensive Financial Option",
    "wof:placetype":"venue"
},
  "geometry": {"coordinates":[-75.140699,40.143243],"type":"Point"}
}