{
  "type": "Feature",
  "properties": {
    "addr:full":"1002 Jackson St Scranton PA 18504",
    "addr:housenumber":"1002",
    "addr:postcode":"18504",
    "addr:street":"Jackson St",
    "iso:country":"US",
    "sg:address":"1002 Jackson St",
    "sg:city":"Scranton",
    "sg:classifiers":[
        {
            "category":"Building & Trades",
            "subcategory":"Cleaning & Sanitation",
            "type":"Services"
        },
        {
            "category":"Home & Garden",
            "subcategory":"Carpets & Floor Coverings",
            "type":"Retail Goods"
        }
    ],
    "sg:phone":"+1 570 969 4371",
    "sg:postcode":"18504",
    "sg:province":"PA",
    "sg:tags":[
        "dealer",
        "upholstery",
        "rug",
        "janitorial"
    ],
    "wof:name":"Pauls Carpet Cleaning",
    "wof:placetype":"venue"
},
  "geometry": {"coordinates":[-75.67927,41.412148],"type":"Point"}
}