{
  "type": "Feature",
  "properties": {
    "addr:full":"10 6th St Cairnbrook PA 15924",
    "addr:housenumber":"10",
    "addr:postcode":"15924",
    "addr:street":"6Th St",
    "iso:country":"US",
    "sg:address":"10 6th St",
    "sg:city":"Cairnbrook",
    "sg:classifiers":[
        {
            "category":"Retail",
            "subcategory":"Auto Repair",
            "type":"Services"
        }
    ],
    "sg:phone":"+1 814 754 4212",
    "sg:postcode":"15924",
    "sg:province":"PA",
    "sg:tags":[
        "machine",
        "automobile",
        "shop"
    ],
    "wof:name":"Chiappelli Engine Machine",
    "wof:placetype":"venue"
},
  "geometry": {"coordinates":[-78.818417,40.119813],"type":"Point"}
}