{
  "type": "Feature",
  "properties": {
    "iso:country":"US",
    "sg:address":"87 Shepard Rd",
    "sg:city":"Waverly",
    "sg:classifiers":[
        {
            "category":"Real Estate",
            "subcategory":"Real Estate Operator",
            "type":"Services"
        }
    ],
    "sg:phone":"+1 607 565 9977",
    "sg:postcode":"14892",
    "sg:province":"PA",
    "sg:tags":[
        "property",
        "lessor"
    ],
    "wof:name":"John Desisti Rentals",
    "wof:placetype":"venue"
},
  "geometry": {"coordinates":[-76.48975799999999,42.003488],"type":"Point"}
}