{
  "type": "Feature",
  "properties": {
    "addr:full":"21 Tarleton Ave Dallas PA 18612",
    "addr:housenumber":"21",
    "addr:postcode":"18612",
    "addr:street":"Tarleton Ave",
    "iso:country":"US",
    "sg:address":"21 Tarleton Ave",
    "sg:city":"Dallas",
    "sg:classifiers":[
        {
            "category":"Autos & Motor Vehicles",
            "subcategory":"Auto Supplies",
            "type":"Retail Goods"
        },
        {
            "category":"Retail",
            "subcategory":"Auto Repair",
            "type":"Services"
        }
    ],
    "sg:phone":"+1 570 674 6021",
    "sg:postcode":"18612",
    "sg:province":"PA",
    "sg:tags":[
        "exhaust",
        "oil",
        "tire",
        "automobile",
        "system",
        "lube",
        "part",
        "brake",
        "muffler"
    ],
    "sg:website":"http://www.monro.com",
    "wof:name":"Monro Muffler Brake & Service",
    "wof:placetype":"venue"
},
  "geometry": {"coordinates":[-75.95450099999999,41.333106],"type":"Point"}
}