{
  "type": "Feature",
  "properties": {
    "addr:full":"1000 Wister St Harrisburg PA 17104",
    "addr:housenumber":"1000",
    "addr:postcode":"17104",
    "addr:street":"Wister St",
    "iso:country":"US",
    "sg:address":"1000 Wister St",
    "sg:city":"Harrisburg",
    "sg:classifiers":[
        {
            "category":"Home & Garden",
            "subcategory":"Building Materials",
            "type":"Retail Goods"
        }
    ],
    "sg:phone":"+1 717 232 5620",
    "sg:postcode":"17104",
    "sg:province":"PA",
    "sg:tags":[
        "roofing"
    ],
    "wof:name":"ABC Supply Co",
    "wof:placetype":"venue"
},
  "geometry": {"coordinates":[-76.851731,40.255565],"type":"Point"}
}