{
  "type": "Feature",
  "properties": {
    "addr:full":"2240 Butler Pike Plymouth Meeting PA 19462",
    "addr:housenumber":"2240",
    "addr:postcode":"19462",
    "addr:street":"Butler Pike",
    "iso:country":"US",
    "sg:address":"2240 Butler Pike",
    "sg:city":"Plymouth Meeting",
    "sg:classifiers":[
        {
            "category":"Banks & Credit Unions",
            "subcategory":"Bank",
            "type":"Services"
        }
    ],
    "sg:phone":"+1 610 834 2013",
    "sg:postcode":"19462",
    "sg:province":"PA",
    "sg:website":"www.wachovia.com",
    "wof:name":"Wachovia Bank",
    "wof:placetype":"venue"
},
  "geometry": {"coordinates":[-75.275981,40.105416],"type":"Point"}
}