{
  "type": "Feature",
  "properties": {
    "addr:full":"345 Mountain Trails Rd Templeton PA 16259",
    "addr:housenumber":"345",
    "addr:postcode":"16259",
    "addr:street":"Mountain Trails Rd",
    "iso:country":"US",
    "sg:address":"345 Mountain Trails Rd",
    "sg:city":"Templeton",
    "sg:classifiers":[
        {
            "category":"Recreation",
            "type":"Entertainment"
        },
        {
            "category":"Recreation",
            "subcategory":"Campground",
            "type":"Entertainment"
        }
    ],
    "sg:phone":"+1 724 868 2196",
    "sg:postcode":"16259",
    "sg:province":"PA",
    "sg:tags":[
        "recreational",
        "park",
        "camps-recreational",
        "vehicle"
    ],
    "wof:name":"Bear Ridge Camp Ground",
    "wof:placetype":"venue"
},
  "geometry": {"coordinates":[-79.426762,40.890067],"type":"Point"}
}