{
  "type": "Feature",
  "properties": {
    "addr:full":"760 Main St Avoca PA 18641",
    "addr:housenumber":"760",
    "addr:postcode":"18641",
    "addr:street":"Main St",
    "iso:country":"US",
    "sg:address":"760 Main St",
    "sg:city":"Avoca",
    "sg:classifiers":[
        {
            "category":"Wholesale",
            "subcategory":"Plants",
            "type":"Manufacturing & Wholesale Goods"
        },
        {
            "category":"Shopping",
            "subcategory":"Florist",
            "type":"Retail Goods"
        }
    ],
    "sg:phone":"+1 570 457 6225",
    "sg:postcode":"18641",
    "sg:province":"PA",
    "sg:tags":[
        "supply"
    ],
    "wof:name":"Just Because Floral & Gift",
    "wof:placetype":"venue"
},
  "geometry": {"coordinates":[-75.74117099999999,41.338404],"type":"Point"}
}