{
  "type": "Feature",
  "properties": {
    "iso:country":"US",
    "sg:address":"26 E Main St",
    "sg:city":"New Bloomfield",
    "sg:classifiers":[
        {
            "category":"Professional",
            "subcategory":"Lawyer & Legal Services",
            "type":"Services"
        }
    ],
    "sg:phone":"+1 717 582 8883",
    "sg:postcode":"17068",
    "sg:province":"PA",
    "sg:tags":[
        "attorney"
    ],
    "wof:name":"Barbara L Wevodau Law Office",
    "wof:placetype":"venue"
},
  "geometry": {"coordinates":[-77.187034,40.419833],"type":"Point"}
}