{
  "type": "Feature",
  "properties": {
    "addr:full":"1190 Piedmont Rd Somerset PA 15501",
    "addr:housenumber":"1190",
    "addr:postcode":"15501",
    "addr:street":"Piedmont Rd",
    "iso:country":"US",
    "sg:address":"1190 Piedmont Rd",
    "sg:city":"Somerset",
    "sg:classifiers":[
        {
            "category":"Professional",
            "subcategory":"Business Services",
            "type":"Services"
        }
    ],
    "sg:phone":"+1 814 443 6600",
    "sg:postcode":"15501",
    "sg:province":"PA",
    "sg:tags":[
        "drafting"
    ],
    "wof:name":"Warren & Assoc",
    "wof:placetype":"venue"
},
  "geometry": {"coordinates":[-79.119246,39.960958],"type":"Point"}
}