{
  "type": "Feature",
  "properties": {
    "iso:country":"US",
    "sg:address":"1985 Muhlenberg Dr",
    "sg:city":"Lansdale",
    "sg:classifiers":[
        {
            "category":"Personal",
            "subcategory":"Beauty Salon",
            "type":"Services"
        }
    ],
    "sg:phone":"+1   ",
    "sg:postcode":"19446",
    "sg:province":"PA",
    "sg:tags":[
        "shop"
    ],
    "wof:name":"Elements of Beauty",
    "wof:placetype":"venue"
},
  "geometry": {"coordinates":[-75.321338,40.210241],"type":"Point"}
}