{
  "type": "Feature",
  "properties": {
    "iso:country":"US",
    "sg:address":"3800 Trindle Rd",
    "sg:city":"Camp Hill",
    "sg:classifiers":[
        {
            "category":"Food & Beverages",
            "subcategory":"Ethnic Foods",
            "type":"Retail Goods"
        },
        {
            "category":"Insurance",
            "subcategory":"Health Insurance",
            "type":"Services"
        },
        {
            "category":"Food & Beverages",
            "subcategory":"Groceries & Convenience Stores",
            "type":"Retail Goods"
        }
    ],
    "sg:phone":"+1 717 737 5123",
    "sg:postcode":"17011",
    "sg:province":"PA",
    "sg:tags":[
        "market"
    ],
    "sg:website":"www.thehealthygrocer.com",
    "wof:name":"Healthy Grocer",
    "wof:placetype":"venue"
},
  "geometry": {"coordinates":[-76.945396,40.234699],"type":"Point"}
}