{
  "type": "Feature",
  "properties": {
    "iso:country":"US",
    "sg:address":"292 Wild Orchid Ct",
    "sg:city":"Morrisville",
    "sg:classifiers":[
        {
            "category":"Insurance",
            "subcategory":"Insurance Agent",
            "type":"Services"
        }
    ],
    "sg:phone":"+1   ",
    "sg:postcode":"19067",
    "sg:province":"PA",
    "wof:name":"Ortmann Benefit",
    "wof:placetype":"venue"
},
  "geometry": {"coordinates":[-74.85207800000001,40.207618],"type":"Point"}
}