{
  "type": "Feature",
  "properties": {
    "iso:country":"US",
    "sg:address":"209 N 3rd St",
    "sg:city":"Philadelphia",
    "sg:classifiers":[
        {
            "category":"Arts & Performance",
            "subcategory":"Art Gallery",
            "type":"Entertainment"
        }
    ],
    "sg:phone":"+1 267 586 2042",
    "sg:postcode":"19106",
    "sg:province":"PA",
    "wof:name":"Gallery 209",
    "wof:placetype":"venue"
},
  "geometry": {"coordinates":[-75.144543,39.954257],"type":"Point"}
}