{
  "type": "Feature",
  "properties": {
    "iso:country":"US",
    "sg:address":"1846 S 12th St",
    "sg:city":"Philadelphia",
    "sg:classifiers":[
        {
            "category":"Restaurant",
            "type":"Food & Drink"
        }
    ],
    "sg:phone":"+1   ",
    "sg:postcode":"19148",
    "sg:province":"PA",
    "sg:tags":[
        "eating"
    ],
    "wof:name":"Stepanos Haviaras",
    "wof:placetype":"venue"
},
  "geometry": {"coordinates":[-75.165459,39.92692],"type":"Point"}
}