{
  "type": "Feature",
  "properties": {
    "iso:country":"US",
    "sg:address":"101 S Spring Garden St",
    "sg:city":"Carlisle",
    "sg:classifiers":[
        {
            "category":"Wholesale",
            "subcategory":"Medical Equipment & Supplies",
            "type":"Manufacturing & Wholesale Goods"
        },
        {
            "category":"Shopping",
            "type":"Retail Goods"
        },
        {
            "category":"Utilities",
            "subcategory":"Natural Gas",
            "type":"Services"
        },
        {
            "category":"Bars & Pubs",
            "subcategory":"Oxygen Bar",
            "type":"Food & Drink"
        },
        {
            "category":"Wholesale",
            "subcategory":"Machinery & Supplies",
            "type":"Manufacturing & Wholesale Goods"
        },
        {
            "category":"Wholesale",
            "subcategory":"Chemicals & Plastics",
            "type":"Manufacturing & Wholesale Goods"
        },
        {
            "category":"Shopping",
            "subcategory":"Pharmacy",
            "type":"Retail Goods"
        },
        {
            "category":"Food & Beverages",
            "subcategory":"Liquor & Beverages",
            "type":"Retail Goods"
        }
    ],
    "sg:phone":"+1 717 249 9353",
    "sg:postcode":"17013",
    "sg:province":"PA",
    "sg:tags":[
        "dry",
        "plant",
        "gas-industrial",
        "medical-cylinder",
        "helium",
        "ice",
        "bulk",
        "health",
        "safety",
        "home",
        "care",
        "clothing",
        "equipment-renting",
        "welding"
    ],
    "sg:website":"http://www.airgas.com",
    "wof:name":"Airgas",
    "wof:placetype":"venue"
},
  "geometry": {"coordinates":[-77.181023,40.199181],"type":"Point"}
}