{
  "type": "Feature",
  "properties": {
    "addr:full":"4371 Cresson St Philadelphia PA 19127",
    "addr:housenumber":"4371",
    "addr:postcode":"19127",
    "addr:street":"Cresson St",
    "iso:country":"US",
    "sg:address":"4371 Cresson St",
    "sg:city":"Philadelphia",
    "sg:classifiers":[
        {
            "category":"Personal",
            "subcategory":"Tattoo Parlor",
            "type":"Services"
        },
        {
            "category":"Personal",
            "subcategory":"Piercing",
            "type":"Services"
        }
    ],
    "sg:phone":"+1 215 487 0360",
    "sg:postcode":"19127",
    "sg:province":"PA",
    "sg:website":"kadillactattoo.com",
    "wof:name":"Kadillac Tattoo",
    "wof:placetype":"venue"
},
  "geometry": {"coordinates":[-75.22410600000001,40.026734],"type":"Point"}
}