{
  "type": "Feature",
  "properties": {
    "iso:country":"US",
    "sg:address":"47 E Pike St",
    "sg:city":"Canonsburg",
    "sg:classifiers":[
        {
            "category":"Restaurant",
            "type":"Food & Drink"
        }
    ],
    "sg:phone":"+1 724 873 9222",
    "sg:postcode":"15317",
    "sg:province":"PA",
    "sg:tags":[
        "eating",
        "pizza"
    ],
    "wof:name":"Big Fella's Pizza Deli & Wings",
    "wof:placetype":"venue"
},
  "geometry": {"coordinates":[-80.186897,40.2589],"type":"Point"}
}