{
  "type": "Feature",
  "properties": {
    "iso:country":"US",
    "sg:address":"121 N 10th St",
    "sg:city":"Philadelphia",
    "sg:classifiers":[
        {
            "category":"Health Services",
            "subcategory":"Doctor",
            "type":"Services"
        }
    ],
    "sg:phone":"+1 215 955 5279",
    "sg:postcode":"19107",
    "sg:province":"PA",
    "wof:name":"Au Clement C MD",
    "wof:placetype":"venue"
},
  "geometry": {"coordinates":[-75.15630299999999,39.954201],"type":"Point"}
}