{
  "type": "Feature",
  "properties": {
    "addr:full":"3314 Washington Ave Erie PA 16508",
    "addr:housenumber":"3314",
    "addr:postcode":"16508",
    "addr:street":"Washington Ave",
    "iso:country":"US",
    "sg:address":"3314 Washington Ave",
    "sg:city":"Erie",
    "sg:classifiers":[
        {
            "category":"Shopping",
            "subcategory":"Gifts & Souvenirs",
            "type":"Retail Goods"
        }
    ],
    "sg:phone":"+1 814 866 2629",
    "sg:postcode":"16508",
    "sg:province":"PA",
    "sg:tags":[
        "shop"
    ],
    "wof:name":"Washington Ave Florial & Gifts",
    "wof:placetype":"venue"
},
  "geometry": {"coordinates":[-80.10025899999999,42.094003],"type":"Point"}
}