{
  "type": "Feature",
  "properties": {
    "iso:country":"US",
    "sg:address":"6375 Penn Ave",
    "sg:city":"Pittsburgh",
    "sg:classifiers":[
        {
            "category":"Shopping",
            "subcategory":"Shoes",
            "type":"Retail Goods"
        }
    ],
    "sg:phone":"+1   ",
    "sg:postcode":"15206",
    "sg:province":"PA",
    "wof:name":"Payless Shoesource",
    "wof:placetype":"venue"
},
  "geometry": {"coordinates":[-79.918738,40.458581],"type":"Point"}
}