{
  "type": "Feature",
  "properties": {
    "addr:full":"4252 Whitaker Ave Philadelphia PA 19124",
    "addr:housenumber":"4252",
    "addr:postcode":"19124",
    "addr:street":"Whitaker Ave",
    "iso:country":"US",
    "sg:address":"4252 Whitaker Ave",
    "sg:city":"Philadelphia",
    "sg:classifiers":[
        {
            "category":"Retail",
            "subcategory":"Laundry & Dry Cleaning",
            "type":"Services"
        },
        {
            "category":"Building & Trades",
            "subcategory":"Cleaning & Sanitation",
            "type":"Services"
        },
        {
            "category":"Manufacturing",
            "subcategory":"Building Materials",
            "type":"Manufacturing & Wholesale Goods"
        }
    ],
    "sg:phone":"+1 215 239 9283",
    "sg:postcode":"19124",
    "sg:province":"PA",
    "sg:tags":[
        "house",
        "fireplace",
        "chimney"
    ],
    "wof:name":"Pennsylvania Vertical Exteriors dba Super Chimneys",
    "wof:placetype":"venue"
},
  "geometry": {"coordinates":[-75.11808000000001,40.01487],"type":"Point"}
}