{
  "type": "Feature",
  "properties": {
    "iso:country":"US",
    "sg:address":"1015 S Cedar Crest Blvd",
    "sg:city":"Allentown",
    "sg:classifiers":[
        {
            "category":"Real Estate",
            "subcategory":"Real Estate Agent",
            "type":"Services"
        }
    ],
    "sg:phone":"+1 610 434 8300",
    "sg:postcode":"18103",
    "sg:province":"PA",
    "wof:name":"Evans Real Estate",
    "wof:placetype":"venue"
},
  "geometry": {"coordinates":[-75.519565,40.573462],"type":"Point"}
}