{
  "type": "Feature",
  "properties": {
    "iso:country":"US",
    "sg:address":"143 Bustleton Pike",
    "sg:city":"Feastervl Trvs",
    "sg:classifiers":[
        {
            "category":"Professional",
            "subcategory":"Accounting & Tax Preparation",
            "type":"Services"
        }
    ],
    "sg:phone":"+1 215 357 5016",
    "sg:postcode":"19053",
    "sg:province":"PA",
    "sg:tags":[
        "accountant"
    ],
    "wof:name":"Jason M Mc Fadden",
    "wof:placetype":"venue"
},
  "geometry": {"coordinates":[-75.00660499999999,40.140025],"type":"Point"}
}