{
  "type": "Feature",
  "properties": {
    "addr:full":"1985 Lincoln Way Mckeesport PA 15131",
    "addr:housenumber":"1985",
    "addr:postcode":"15131",
    "addr:street":"Lincoln Way",
    "iso:country":"US",
    "sg:address":"1985 Lincoln Way",
    "sg:city":"Mckeesport",
    "sg:classifiers":[
        {
            "category":"Ice Cream",
            "type":"Food & Drink"
        }
    ],
    "sg:menulink":"http://www.allmenus.com/pa/white-oak/234994-ritas-ice-custard-happiness/menu/",
    "sg:phone":"+1 412 673 7482",
    "sg:postcode":"15131",
    "sg:province":"PA",
    "sg:tags":[
        "american"
    ],
    "wof:name":"Rita's Ice Custard Happiness",
    "wof:placetype":"venue"
},
  "geometry": {"coordinates":[-79.809184,40.338267],"type":"Point"}
}