{
  "type": "Feature",
  "properties": {
    "iso:country":"US",
    "sg:address":"57 E Main St",
    "sg:city":"Uniontown",
    "sg:classifiers":[
        {
            "category":"Professional",
            "subcategory":"Lawyer & Legal Services",
            "type":"Services"
        }
    ],
    "sg:phone":"+1 724 430 9800",
    "sg:postcode":"15401",
    "sg:province":"PA",
    "sg:tags":[
        "attorney",
        "injury",
        "personal",
        "worker",
        "disability",
        "compensation",
        "benefit",
        "social",
        "employee",
        "security",
        "law"
    ],
    "sg:website":"http://www.monaghanlawfirm.com",
    "wof:name":"Monaghan & Monaghan L L P Attorneys at Law",
    "wof:placetype":"venue"
},
  "geometry": {"coordinates":[-79.723237,39.901378],"type":"Point"}
}