{
  "type": "Feature",
  "properties": {
    "addr:full":"814 Chatham Rd Fairless Hills PA 19030",
    "addr:housenumber":"814",
    "addr:postcode":"19030",
    "addr:street":"Chatham Rd",
    "iso:country":"US",
    "sg:address":"814 Chatham Rd",
    "sg:city":"Fairless Hills",
    "sg:classifiers":[
        {
            "category":"Building & Trades",
            "subcategory":"Construction",
            "type":"Services"
        }
    ],
    "sg:phone":"+1   ",
    "sg:postcode":"19030",
    "sg:province":"PA",
    "sg:tags":[
        "house"
    ],
    "wof:name":"Link Home Improvements",
    "wof:placetype":"venue"
},
  "geometry": {"coordinates":[-74.835182,40.181046],"type":"Point"}
}