{
  "type": "Feature",
  "properties": {
    "iso:country":"US",
    "sg:address":"3353 Gun Club Rd",
    "sg:city":"Nazareth",
    "sg:classifiers":[
        {
            "category":"Utilities",
            "subcategory":"Mobile Phone",
            "type":"Services"
        }
    ],
    "sg:phone":"+1 610 837 9917",
    "sg:postcode":"18064",
    "sg:province":"PA",
    "sg:tags":[
        "telephone",
        "cellular"
    ],
    "wof:name":"Wireless Solutions",
    "wof:placetype":"venue"
},
  "geometry": {"coordinates":[-75.36010400000001,40.723491],"type":"Point"}
}