{
  "type": "Feature",
  "properties": {
    "addr:full":"220 Main St Watsontown PA 17777",
    "addr:housenumber":"220",
    "addr:postcode":"17777",
    "addr:street":"Main St",
    "iso:country":"US",
    "sg:address":"220 Main St",
    "sg:city":"Watsontown",
    "sg:classifiers":[
        {
            "category":"Shopping",
            "subcategory":"Pharmacy",
            "type":"Retail Goods"
        }
    ],
    "sg:phone":"+1 570 538 9123",
    "sg:postcode":"17777",
    "sg:province":"PA",
    "wof:name":"CVS Pharmacy",
    "wof:placetype":"venue"
},
  "geometry": {"coordinates":[-76.86205,41.083015],"type":"Point"}
}