{
  "type": "Feature",
  "properties": {
    "addr:full":"1824 Boulevard Ave Scranton PA 18509",
    "addr:housenumber":"1824",
    "addr:postcode":"18509",
    "addr:street":"Boulevard Ave",
    "iso:country":"US",
    "sg:address":"1824 Boulevard Ave",
    "sg:city":"Scranton",
    "sg:classifiers":[
        {
            "category":"Education",
            "subcategory":"School",
            "type":"Public Place"
        }
    ],
    "sg:phone":"+1 570 348 3681",
    "sg:postcode":"18509",
    "sg:province":"PA",
    "wof:name":"Robert Morris School",
    "wof:placetype":"venue"
},
  "geometry": {"coordinates":[-75.647694,41.432642],"type":"Point"}
}