{
  "type": "Feature",
  "properties": {
    "iso:country":"US",
    "sg:address":"5217 Simpson Ferry Rd",
    "sg:city":"Mechanicsburg",
    "sg:classifiers":[
        {
            "category":"Manufacturing",
            "subcategory":"Printing",
            "type":"Manufacturing & Wholesale Goods"
        }
    ],
    "sg:phone":"+1 717 691 6880",
    "sg:postcode":"17050",
    "sg:province":"PA",
    "sg:tags":[
        "printer",
        "commercial"
    ],
    "wof:name":"Franklin's Printing",
    "wof:placetype":"venue"
},
  "geometry": {"coordinates":[-76.983208,40.217653],"type":"Point"}
}