{
  "type": "Feature",
  "properties": {
    "addr:full":"5632 Ridge Ave Philadelphia PA 19128",
    "addr:housenumber":"5632",
    "addr:postcode":"19128",
    "addr:street":"Ridge Ave",
    "iso:country":"US",
    "sg:address":"5632 Ridge Ave",
    "sg:city":"Philadelphia",
    "sg:classifiers":[
        {
            "category":"Building & Trades",
            "subcategory":"Locksmith",
            "type":"Services"
        }
    ],
    "sg:phone":"+1 267 297 3431",
    "sg:postcode":"19128",
    "sg:province":"PA",
    "sg:tags":[
        "key"
    ],
    "wof:name":"Locksmith & Locks-24 7 Emergency",
    "wof:placetype":"venue"
},
  "geometry": {"coordinates":[-75.20917799999999,40.026136],"type":"Point"}
}