{
  "type": "Feature",
  "properties": {
    "iso:country":"US",
    "sg:address":"4230 Mechanicsville Rd",
    "sg:city":"Bensalem",
    "sg:classifiers":[
        {
            "category":"Wholesale",
            "subcategory":"Non-durable Goods",
            "type":"Manufacturing & Wholesale Goods"
        }
    ],
    "sg:phone":"+1   ",
    "sg:postcode":"19020",
    "sg:province":"PA",
    "wof:name":"African Breeders",
    "wof:placetype":"venue"
},
  "geometry": {"coordinates":[-74.929912,40.119323],"type":"Point"}
}