{
  "type": "Feature",
  "properties": {
    "iso:country":"US",
    "sg:address":"872 Water St",
    "sg:city":"Meadville",
    "sg:classifiers":[
        {
            "category":"Local Transit",
            "type":"Transportation"
        }
    ],
    "sg:phone":"+1   ",
    "sg:postcode":"16335",
    "sg:province":"PA",
    "sg:tags":[
        "passenger"
    ],
    "wof:name":"Tristate Emergency Systems",
    "wof:placetype":"venue"
},
  "geometry": {"coordinates":[-80.154511,41.640325],"type":"Point"}
}