{
  "type": "Feature",
  "properties": {
    "iso:country":"US",
    "sg:address":"136 N Flowers Mill Rd",
    "sg:city":"Langhorne",
    "sg:classifiers":[
        {
            "category":"Home & Garden",
            "subcategory":"Furniture",
            "type":"Retail Goods"
        }
    ],
    "sg:phone":"+1   ",
    "sg:postcode":"19047",
    "sg:province":"PA",
    "wof:name":"Rockaway Bedding Inc",
    "wof:placetype":"venue"
},
  "geometry": {"coordinates":[-74.90756,40.17965],"type":"Point"}
}