{
  "type": "Feature",
  "properties": {
    "iso:country":"US",
    "sg:address":"6027 Brush Valley Rd",
    "sg:city":"Rebersburg",
    "sg:classifiers":[
        {
            "category":"Farming",
            "subcategory":"Dairy Farm",
            "type":"Manufacturing & Wholesale Goods"
        }
    ],
    "sg:phone":"+1   ",
    "sg:postcode":"16872",
    "sg:province":"PA",
    "wof:name":"Trinca Farms",
    "wof:placetype":"venue"
},
  "geometry": {"coordinates":[-77.43649000000001,40.947122],"type":"Point"}
}