{
  "type": "Feature",
  "properties": {
    "iso:country":"US",
    "sg:address":"263 Westminster Rd",
    "sg:city":"Sarver",
    "sg:classifiers":[
        {
            "category":"Professional",
            "subcategory":"Management & Consulting",
            "type":"Services"
        }
    ],
    "sg:phone":"+1 724 352 8411",
    "sg:postcode":"16055",
    "sg:province":"PA",
    "sg:tags":[
        "party",
        "planning"
    ],
    "wof:name":"Party Makers",
    "wof:placetype":"venue"
},
  "geometry": {"coordinates":[-79.82380499999999,40.705875],"type":"Point"}
}