{
  "type": "Feature",
  "properties": {
    "iso:country":"US",
    "sg:address":"319 Dean St",
    "sg:city":"West Chester",
    "sg:classifiers":[
        {
            "category":"Building & Trades",
            "subcategory":"Construction",
            "type":"Services"
        },
        {
            "category":"Wholesale",
            "subcategory":"Durable Goods & Equipment",
            "type":"Manufacturing & Wholesale Goods"
        }
    ],
    "sg:phone":"+1 610 696 3654",
    "sg:postcode":"19382",
    "sg:province":"PA",
    "sg:tags":[
        "manufacturer",
        "representative",
        "contractor"
    ],
    "wof:name":"Mancini Associates Inc",
    "wof:placetype":"venue"
},
  "geometry": {"coordinates":[-75.607545,39.953754],"type":"Point"}
}