{
  "type": "Feature",
  "properties": {
    "addr:full":"2948 Leechburg Rd Lower Burrell PA 15068",
    "addr:housenumber":"2948",
    "addr:postcode":"15068",
    "addr:street":"Leechburg Rd",
    "iso:country":"US",
    "sg:address":"2948 Leechburg Rd",
    "sg:city":"Lower Burrell",
    "sg:classifiers":[
        {
            "category":"Personal",
            "subcategory":"Barber",
            "type":"Services"
        }
    ],
    "sg:phone":"+1 724 337 8288",
    "sg:postcode":"15068",
    "sg:province":"PA",
    "wof:name":"Doug Milanak Barber Shop",
    "wof:placetype":"venue"
},
  "geometry": {"coordinates":[-79.722089,40.588434],"type":"Point"}
}