{
  "type": "Feature",
  "properties": {
    "addr:full":"122 Limekiln Pike Glenside PA 19038",
    "addr:housenumber":"122",
    "addr:postcode":"19038",
    "addr:street":"Limekiln Pike",
    "iso:country":"US",
    "sg:address":"122 Limekiln Pike",
    "sg:city":"Glenside",
    "sg:classifiers":[
        {
            "category":"Building & Trades",
            "subcategory":"Landscaping Services",
            "type":"Services"
        }
    ],
    "sg:phone":"+1 215 884 2917",
    "sg:postcode":"19038",
    "sg:province":"PA",
    "sg:tags":[
        "landscape",
        "contractor"
    ],
    "wof:name":"Don Dolan Landscape Design Inc",
    "wof:placetype":"venue"
},
  "geometry": {"coordinates":[-75.164283,40.103581],"type":"Point"}
}