{
  "type": "Feature",
  "properties": {
    "iso:country":"US",
    "sg:address":"339 Wyoming Ave",
    "sg:city":"Wyoming",
    "sg:classifiers":[
        {
            "category":"Health Services",
            "subcategory":"Doctor",
            "type":"Services"
        }
    ],
    "sg:phone":"+1   ",
    "sg:postcode":"18644",
    "sg:province":"PA",
    "sg:tags":[
        "orthodontist"
    ],
    "wof:name":"Nahas & Donahue Orthodontist",
    "wof:placetype":"venue"
},
  "geometry": {"coordinates":[-75.83636,41.312376],"type":"Point"}
}