{
  "type": "Feature",
  "properties": {
    "iso:country":"US",
    "sg:address":"85 Makefield Rd",
    "sg:city":"Morrisville",
    "sg:classifiers":[
        {
            "category":"Wholesale",
            "subcategory":"Medical Equipment & Supplies",
            "type":"Manufacturing & Wholesale Goods"
        },
        {
            "category":"Manufacturing",
            "subcategory":"Tools & Machinery",
            "type":"Manufacturing & Wholesale Goods"
        }
    ],
    "sg:phone":"+1 215 295 0444",
    "sg:postcode":"19067",
    "sg:province":"PA",
    "sg:tags":[
        "ophthalmic",
        "optical",
        "mfg"
    ],
    "wof:name":"Normandy Optical Co",
    "wof:placetype":"venue"
},
  "geometry": {"coordinates":[-74.821224,40.200472],"type":"Point"}
}