{
  "type": "Feature",
  "properties": {
    "addr:full":"4535 E Lake Rd Erie PA 16511",
    "addr:housenumber":"4535",
    "addr:postcode":"16511",
    "addr:street":"E Lake Rd",
    "iso:country":"US",
    "sg:address":"4535 E Lake Rd",
    "sg:city":"Erie",
    "sg:classifiers":[
        {
            "category":"Travel",
            "subcategory":"Hotels & Motels",
            "type":"Entertainment"
        }
    ],
    "sg:phone":"+1 814 899 2133",
    "sg:postcode":"16511",
    "sg:province":"PA",
    "wof:name":"Greenwood Inn & Efficiencies",
    "wof:placetype":"venue"
},
  "geometry": {"coordinates":[-80.00905400000001,42.163311],"type":"Point"}
}