{
  "type": "Feature",
  "properties": {
    "iso:country":"US",
    "sg:address":"8001 Castor Ave",
    "sg:city":"Philadelphia",
    "sg:classifiers":[
        {
            "category":"Building & Trades",
            "subcategory":"Construction",
            "type":"Services"
        }
    ],
    "sg:phone":"+1   ",
    "sg:postcode":"19152",
    "sg:province":"PA",
    "sg:tags":[
        "contractor"
    ],
    "wof:name":"Precision Drywall Finishing",
    "wof:placetype":"venue"
},
  "geometry": {"coordinates":[-75.05556199999999,40.062439],"type":"Point"}
}