{
  "type": "Feature",
  "properties": {
    "addr:full":"410 Broadway Hanover PA 17331",
    "addr:housenumber":"410",
    "addr:postcode":"17331",
    "addr:street":"Broadway",
    "iso:country":"US",
    "sg:address":"410 Broadway",
    "sg:city":"Hanover",
    "sg:classifiers":[
        {
            "category":"Retail",
            "subcategory":"Auto Repair",
            "type":"Services"
        }
    ],
    "sg:phone":"+1 717 630 2260",
    "sg:postcode":"17331",
    "sg:province":"PA",
    "sg:tags":[
        "body",
        "automobile",
        "painting"
    ],
    "wof:name":"Broadway Blasting Svc Inc",
    "wof:placetype":"venue"
},
  "geometry": {"coordinates":[-76.979928,39.805737],"type":"Point"}
}