{
  "type": "Feature",
  "properties": {
    "iso:country":"US",
    "sg:address":"901 Canal St",
    "sg:city":"Bristol",
    "sg:classifiers":[
        {
            "category":"Industrial Area",
            "type":"Public Place"
        }
    ],
    "sg:phone":"+1 215 788 4616",
    "sg:postcode":"19007",
    "sg:province":"PA",
    "sg:tags":[
        "development"
    ],
    "wof:name":"Grundy Industrial Complex Inc",
    "wof:placetype":"venue"
},
  "geometry": {"coordinates":[-74.852249,40.103539],"type":"Point"}
}