{
  "type": "Feature",
  "properties": {
    "iso:country":"US",
    "sg:address":"112 Pershing Dr",
    "sg:city":"Connellsville",
    "sg:classifiers":[
        {
            "category":"Autos & Motor Vehicles",
            "subcategory":"Auto Supplies",
            "type":"Retail Goods"
        }
    ],
    "sg:phone":"+1 724 628 1246",
    "sg:postcode":"15425",
    "sg:province":"PA",
    "sg:tags":[
        "tire"
    ],
    "wof:name":"Shaffer Ralph E Tire Service",
    "wof:placetype":"venue"
},
  "geometry": {"coordinates":[-79.62629699999999,40.009201],"type":"Point"}
}