{
  "type": "Feature",
  "properties": {
    "iso:country":"US",
    "sg:address":"6069 Irishtown Rd",
    "sg:city":"Bethel Park",
    "sg:classifiers":[
        {
            "category":"Shopping",
            "subcategory":"Computers & Home Electronics",
            "type":"Retail Goods"
        }
    ],
    "sg:phone":"+1   ",
    "sg:postcode":"15102",
    "sg:province":"PA",
    "sg:tags":[
        "product",
        "compute",
        "related"
    ],
    "wof:name":"Turn-Key Computer and Cons",
    "wof:placetype":"venue"
},
  "geometry": {"coordinates":[-80.04862,40.303422],"type":"Point"}
}