{
  "type": "Feature",
  "properties": {
    "iso:country":"US",
    "sg:address":"1414 N Cameron St",
    "sg:city":"Harrisburg",
    "sg:classifiers":[
        {
            "category":"Organizations",
            "subcategory":"Non-profit Organization",
            "type":"Services"
        }
    ],
    "sg:phone":"+1 717 236 6310",
    "sg:postcode":"17103",
    "sg:province":"PA",
    "sg:tags":[
        "human"
    ],
    "wof:name":"Pa Health Law Project",
    "wof:placetype":"venue"
},
  "geometry": {"coordinates":[-76.87875699999999,40.276385],"type":"Point"}
}