{
  "type": "Feature",
  "properties": {
    "iso:country":"US",
    "sg:address":"4141 Washington Rd",
    "sg:city":"Canonsburg",
    "sg:classifiers":[
        {
            "category":"Health Services",
            "subcategory":"Doctor",
            "type":"Services"
        }
    ],
    "sg:phone":"+1 724 225 0990",
    "sg:postcode":"15317",
    "sg:province":"PA",
    "wof:name":"Urology Triangle Urology Group",
    "wof:placetype":"venue"
},
  "geometry": {"coordinates":[-80.130402,40.264301],"type":"Point"}
}