{
  "type": "Feature",
  "properties": {
    "iso:country":"US",
    "sg:address":"145 Chaps Ln",
    "sg:city":"West Chester",
    "sg:classifiers":[
        {
            "category":"Shopping",
            "subcategory":"Computers & Home Electronics",
            "type":"Retail Goods"
        }
    ],
    "sg:phone":"+1   ",
    "sg:postcode":"19382",
    "sg:province":"PA",
    "sg:tags":[
        "hardware",
        "software"
    ],
    "wof:name":"Quixtarunocom",
    "wof:placetype":"venue"
},
  "geometry": {"coordinates":[-75.577088,39.914392],"type":"Point"}
}