{
  "type": "Feature",
  "properties": {
    "addr:full":"4524 Germantown Ave Philadelphia PA 19144",
    "addr:housenumber":"4524",
    "addr:postcode":"19144",
    "addr:street":"Germantown Ave",
    "iso:country":"US",
    "sg:address":"4524 Germantown Ave",
    "sg:city":"Philadelphia",
    "sg:classifiers":[
        {
            "category":"Banks & Credit Unions",
            "subcategory":"Atm",
            "type":"Services"
        }
    ],
    "sg:phone":"+1 215 848 4960",
    "sg:postcode":"19144",
    "sg:province":"PA",
    "sg:tags":[
        "location"
    ],
    "wof:name":"M B M Atm Group",
    "wof:placetype":"venue"
},
  "geometry": {"coordinates":[-75.159531,40.023891],"type":"Point"}
}