{
  "type": "Feature",
  "properties": {
    "iso:country":"US",
    "sg:address":"690 Fox Hollow Rd",
    "sg:city":"Saint Marys",
    "sg:classifiers":[
        {
            "category":"Health Services",
            "subcategory":"Doctor",
            "type":"Services"
        }
    ],
    "sg:phone":"+1   ",
    "sg:postcode":"15857",
    "sg:province":"PA",
    "wof:name":"Robert J Schmidt",
    "wof:placetype":"venue"
},
  "geometry": {"coordinates":[-78.565088,41.443511],"type":"Point"}
}