{
  "type": "Feature",
  "properties": {
    "iso:country":"US",
    "sg:address":"80 Hilltown Pike",
    "sg:city":"Line Lexington",
    "sg:classifiers":[
        {
            "category":"Organizations",
            "subcategory":"Religious Organization",
            "type":"Services"
        }
    ],
    "sg:phone":"+1 215 822 0446",
    "sg:postcode":"18932",
    "sg:province":"PA",
    "sg:tags":[
        "church"
    ],
    "sg:website":"www.llmc.org",
    "wof:name":"Line Lexington Mennonite Chr",
    "wof:placetype":"venue"
},
  "geometry": {"coordinates":[-75.26115299999999,40.289393],"type":"Point"}
}