{
  "type": "Feature",
  "properties": {
    "addr:full":"902 W Mahoning St Punxsutawney PA 15767",
    "addr:housenumber":"902",
    "addr:postcode":"15767",
    "addr:street":"W Mahoning St",
    "iso:country":"US",
    "sg:address":"902 W Mahoning St",
    "sg:city":"Punxsutawney",
    "sg:classifiers":[
        {
            "category":"Home & Garden",
            "subcategory":"Building Materials",
            "type":"Retail Goods"
        }
    ],
    "sg:phone":"+1 814 938 6230",
    "sg:postcode":"15767",
    "sg:province":"PA",
    "sg:tags":[
        "glass",
        "window",
        "plate"
    ],
    "wof:name":"Fred R Means Steel Co",
    "wof:placetype":"venue"
},
  "geometry": {"coordinates":[-78.988913,40.942863],"type":"Point"}
}