{
  "type": "Feature",
  "properties": {
    "iso:country":"US",
    "sg:address":"5736 Township Line Rd",
    "sg:city":"Pipersville",
    "sg:classifiers":[
        {
            "category":"Retail",
            "subcategory":"Portrait Studio",
            "type":"Services"
        }
    ],
    "sg:phone":"+1 215 766 9386",
    "sg:postcode":"18947",
    "sg:province":"PA",
    "sg:tags":[
        "photographer"
    ],
    "wof:name":"Paul Barton Photography",
    "wof:placetype":"venue"
},
  "geometry": {"coordinates":[-75.138761,40.409711],"type":"Point"}
}