{
  "type": "Feature",
  "properties": {
    "addr:full":"5 Birch Ln East Stroudsburg PA 18301",
    "addr:housenumber":"5",
    "addr:postcode":"18301",
    "addr:street":"Birch Ln",
    "iso:country":"US",
    "sg:address":"5 Birch Ln",
    "sg:city":"East Stroudsburg",
    "sg:classifiers":[
        {
            "category":"Retail",
            "subcategory":"Auto Repair",
            "type":"Services"
        }
    ],
    "sg:phone":"+1   ",
    "sg:postcode":"18301",
    "sg:province":"PA",
    "sg:tags":[
        "general"
    ],
    "wof:name":"Carls Auto Repairs Inc",
    "wof:placetype":"venue"
},
  "geometry": {"coordinates":[-75.272361,41.043406],"type":"Point"}
}