{
  "type": "Feature",
  "properties": {
    "iso:country":"US",
    "sg:address":"6198 Butler Pike",
    "sg:city":"Blue Bell",
    "sg:classifiers":[
        {
            "category":"Professional",
            "subcategory":"Management & Consulting",
            "type":"Services"
        }
    ],
    "sg:phone":"+1 215 641 1400",
    "sg:postcode":"19422",
    "sg:province":"PA",
    "sg:tags":[
        "food"
    ],
    "wof:name":"Williamson Hospitality Svcs",
    "wof:placetype":"venue"
},
  "geometry": {"coordinates":[-75.244247,40.138975],"type":"Point"}
}