{
  "type": "Feature",
  "properties": {
    "iso:country":"US",
    "sg:address":"513 Leech Ave",
    "sg:city":"Saltsburg",
    "sg:classifiers":[
        {
            "category":"Building & Trades",
            "subcategory":"Construction",
            "type":"Services"
        }
    ],
    "sg:phone":"+1   ",
    "sg:postcode":"15681",
    "sg:province":"PA",
    "sg:tags":[
        "finish",
        "carpentry"
    ],
    "wof:name":"Gregs Home Improvement",
    "wof:placetype":"venue"
},
  "geometry": {"coordinates":[-79.45005399999999,40.493077],"type":"Point"}
}