{
  "type": "Feature",
  "properties": {
    "iso:country":"US",
    "sg:address":"223 W Park Rd",
    "sg:city":"Portersville",
    "sg:classifiers":[
        {
            "category":"Autos & Motor Vehicles",
            "subcategory":"Auto Supplies",
            "type":"Retail Goods"
        }
    ],
    "sg:phone":"+1 724 368 3413",
    "sg:postcode":"16051",
    "sg:province":"PA",
    "sg:tags":[
        "tire"
    ],
    "wof:name":"Nicholson Tire & Storage",
    "wof:placetype":"venue"
},
  "geometry": {"coordinates":[-80.14543999999999,40.936763],"type":"Point"}
}