{
  "type": "Feature",
  "properties": {
    "iso:country":"US",
    "sg:address":"4 Parsonage St",
    "sg:city":"Dallas",
    "sg:classifiers":[
        {
            "category":"Organizations",
            "subcategory":"Religious Organization",
            "type":"Services"
        }
    ],
    "sg:phone":"+1 570 675 0122",
    "sg:postcode":"18612",
    "sg:province":"PA",
    "wof:name":"Dallas United Methodist Church",
    "wof:placetype":"venue"
},
  "geometry": {"coordinates":[-75.963914,41.33835],"type":"Point"}
}