{
  "type": "Feature",
  "properties": {
    "addr:full":"146 East Ave Wellsboro PA 16901",
    "addr:housenumber":"146",
    "addr:postcode":"16901",
    "addr:street":"East Ave",
    "iso:country":"US",
    "sg:address":"146 East Ave",
    "sg:city":"Wellsboro",
    "sg:classifiers":[
        {
            "category":"Social Services",
            "subcategory":"Job Training",
            "type":"Services"
        }
    ],
    "sg:phone":"+1 570 723 9949",
    "sg:postcode":"16901",
    "sg:province":"PA",
    "sg:tags":[
        "employment"
    ],
    "wof:name":"Experience Works",
    "wof:placetype":"venue"
},
  "geometry": {"coordinates":[-77.289688,41.747402],"type":"Point"}
}