{
  "type": "Feature",
  "properties": {
    "iso:country":"US",
    "sg:address":"521 E Locust St",
    "sg:city":"Bethlehem",
    "sg:classifiers":[
        {
            "category":"Organizations",
            "subcategory":"Religious Organization",
            "type":"Services"
        }
    ],
    "sg:phone":"+1 610 867 6021",
    "sg:postcode":"18018",
    "sg:province":"PA",
    "sg:tags":[
        "church"
    ],
    "wof:name":"Saint Matthews Lutheran Church",
    "wof:placetype":"venue"
},
  "geometry": {"coordinates":[-75.366287,40.629658],"type":"Point"}
}