{
  "type": "Feature",
  "properties": {
    "iso:country":"US",
    "sg:address":"380 Smith Rd",
    "sg:city":"Bath",
    "sg:classifiers":[
        {
            "category":"Manufacturing",
            "subcategory":"Retail Goods",
            "type":"Manufacturing & Wholesale Goods"
        }
    ],
    "sg:phone":"+1   ",
    "sg:postcode":"18014",
    "sg:province":"PA",
    "sg:tags":[
        "product",
        "mfg"
    ],
    "wof:name":"Maroski Brothers",
    "wof:placetype":"venue"
},
  "geometry": {"coordinates":[-75.440292,40.753143],"type":"Point"}
}