{
  "type": "Feature",
  "properties": {
    "iso:country":"US",
    "sg:address":"825 Lancaster Ave",
    "sg:city":"Columbia",
    "sg:classifiers":[
        {
            "category":"Retail",
            "subcategory":"Auto Repair",
            "type":"Services"
        }
    ],
    "sg:phone":"+1 717 684 5676",
    "sg:postcode":"17512",
    "sg:province":"PA",
    "sg:tags":[
        "body",
        "automobile",
        "painting"
    ],
    "wof:name":"Midway Collision Shop",
    "wof:placetype":"venue"
},
  "geometry": {"coordinates":[-76.49190900000001,40.031992],"type":"Point"}
}