{
  "type": "Feature",
  "properties": {
    "iso:country":"US",
    "sg:address":"1545 Minesite Rd",
    "sg:city":"Allentown",
    "sg:classifiers":[
        {
            "category":"Professional",
            "type":"Services"
        }
    ],
    "sg:phone":"+1   ",
    "sg:postcode":"18103",
    "sg:province":"PA",
    "wof:name":"Leonard Saeger",
    "wof:placetype":"venue"
},
  "geometry": {"coordinates":[-75.537344,40.557333],"type":"Point"}
}