{
  "type": "Feature",
  "properties": {
    "addr:full":"345 S 16th St Lebanon PA 17042",
    "addr:housenumber":"345",
    "addr:postcode":"17042",
    "addr:street":"S 16Th St",
    "iso:country":"US",
    "sg:address":"345 S 16th St",
    "sg:city":"Lebanon",
    "sg:classifiers":[
        {
            "category":"Real Estate",
            "subcategory":"Real Estate Agent",
            "type":"Services"
        }
    ],
    "sg:phone":"+1   ",
    "sg:postcode":"17042",
    "sg:province":"PA",
    "wof:name":"Garden Oaks Assoc",
    "wof:placetype":"venue"
},
  "geometry": {"coordinates":[-76.438284,40.331756],"type":"Point"}
}