{
  "type": "Feature",
  "properties": {
    "iso:country":"US",
    "sg:address":"1801 N 3rd St",
    "sg:city":"Harrisburg",
    "sg:classifiers":[
        {
            "category":"Social Services",
            "type":"Services"
        }
    ],
    "sg:phone":"+1   ",
    "sg:postcode":"17102",
    "sg:province":"PA",
    "sg:tags":[
        "center",
        "community"
    ],
    "wof:name":"Neighborhood Center of United",
    "wof:placetype":"venue"
},
  "geometry": {"coordinates":[-76.893405,40.275824],"type":"Point"}
}