{
  "type": "Feature",
  "properties": {
    "addr:full":"399 Cinnamon Dr Huntingdon Valley PA 19006",
    "addr:housenumber":"399",
    "addr:postcode":"19006",
    "addr:street":"Cinnamon Dr",
    "iso:country":"US",
    "sg:address":"399 Cinnamon Dr",
    "sg:city":"Huntingdon Valley",
    "sg:classifiers":[
        {
            "category":"Organizations",
            "subcategory":"Membership Organization",
            "type":"Services"
        }
    ],
    "sg:phone":"+1   ",
    "sg:postcode":"19006",
    "sg:province":"PA",
    "wof:name":"American Orff Schullwerk Assn",
    "wof:placetype":"venue"
},
  "geometry": {"coordinates":[-75.062291,40.112534],"type":"Point"}
}