{
  "type": "Feature",
  "properties": {
    "addr:full":"2211 Stenton Ave Philadelphia PA 19138",
    "addr:housenumber":"2211",
    "addr:postcode":"19138",
    "addr:street":"Stenton Ave",
    "iso:country":"US",
    "sg:address":"2211 Stenton Ave",
    "sg:city":"Philadelphia",
    "sg:classifiers":[
        {
            "category":"Autos & Motor Vehicles",
            "subcategory":"Fuel & Gas Station",
            "type":"Retail Goods"
        }
    ],
    "sg:phone":"+1   ",
    "sg:postcode":"19138",
    "sg:province":"PA",
    "sg:tags":[
        "station",
        "gasoline"
    ],
    "wof:name":"Amoco",
    "wof:placetype":"venue"
},
  "geometry": {"coordinates":[-75.158174,40.055436],"type":"Point"}
}