{
  "type": "Feature",
  "properties": {
    "iso:country":"US",
    "sg:address":"1760 Market St",
    "sg:city":"Philadelphia",
    "sg:classifiers":[
        {
            "category":"Health Services",
            "subcategory":"Doctor",
            "type":"Services"
        }
    ],
    "sg:phone":"+1 215 563 8333",
    "sg:postcode":"19103",
    "sg:province":"PA",
    "sg:tags":[
        "physician",
        "surgeon",
        "medical"
    ],
    "sg:website":"www.parishdermatology.com",
    "wof:name":"Parish Lawrence Charles MD",
    "wof:placetype":"venue"
},
  "geometry": {"coordinates":[-75.169358,39.952974],"type":"Point"}
}