{
  "type": "Feature",
  "properties": {
    "iso:country":"US",
    "sg:address":"288 Rivercrest Dr",
    "sg:city":"Phoenixville",
    "sg:classifiers":[
        {
            "category":"Utilities",
            "subcategory":"Electric",
            "type":"Services"
        }
    ],
    "sg:phone":"+1 610 917 9399",
    "sg:postcode":"19460",
    "sg:province":"PA",
    "sg:tags":[
        "electrical",
        "power",
        "systems-maintenance"
    ],
    "wof:name":"Nax Power, Inc",
    "wof:placetype":"venue"
},
  "geometry": {"coordinates":[-75.496098,40.155346],"type":"Point"}
}