{
  "type": "Feature",
  "properties": {
    "addr:full":"5970 Cetronia Rd Allentown PA 18106",
    "addr:postcode":"5970;18106",
    "addr:street":"Cetronia Rd",
    "iso:country":"US",
    "sg:address":"5970 Cetronia Rd",
    "sg:city":"Allentown",
    "sg:classifiers":[
        {
            "category":"Real Estate",
            "subcategory":"Developer",
            "type":"Services"
        }
    ],
    "sg:phone":"+1   ",
    "sg:postcode":"18106",
    "sg:province":"PA",
    "sg:tags":[
        "cemetery"
    ],
    "wof:name":"Lehigh Zion Cemetery",
    "wof:placetype":"venue"
},
  "geometry": {"coordinates":[-75.57255499999999,40.571263],"type":"Point"}
}