{
  "type": "Feature",
  "properties": {
    "iso:country":"US",
    "sg:address":"160 N Craig St",
    "sg:city":"Pittsburgh",
    "sg:classifiers":[
        {
            "category":"Health Services",
            "subcategory":"Podiatrist",
            "type":"Services"
        },
        {
            "category":"Health Services",
            "subcategory":"Doctor",
            "type":"Services"
        }
    ],
    "sg:phone":"+1 412 681 5600",
    "sg:postcode":"15213",
    "sg:province":"PA",
    "sg:tags":[
        "physician"
    ],
    "wof:name":"Oakland Podiatry Assoc DPM",
    "wof:placetype":"venue"
},
  "geometry": {"coordinates":[-79.949764,40.448088],"type":"Point"}
}