{
  "type": "Feature",
  "properties": {
    "iso:country":"US",
    "sg:address":"2005 Market St ",
    "sg:city":"Philadelphia",
    "sg:classifiers":[
        {
            "category":"Restaurant",
            "type":"Food & Drink"
        }
    ],
    "sg:menulink":"http://www.allmenus.com/pa/philadelphia/291765-du-jour/menu/",
    "sg:phone":"+1 215 735 8010",
    "sg:postcode":"19103",
    "sg:province":"PA",
    "sg:tags":[
        "burger",
        "salad",
        "soup"
    ],
    "wof:name":"Du Jour",
    "wof:placetype":"venue"
},
  "geometry": {"coordinates":[-75.173293,39.953664],"type":"Point"}
}