{
  "type": "Feature",
  "properties": {
    "iso:country":"US",
    "sg:address":"2601 MacArthur Rd",
    "sg:city":"Whitehall",
    "sg:classifiers":[
        {
            "category":"Shopping",
            "subcategory":"Optician",
            "type":"Retail Goods"
        }
    ],
    "sg:phone":"+1 610 266 8930",
    "sg:postcode":"18052",
    "sg:province":"PA",
    "sg:tags":[
        "eyewear"
    ],
    "wof:name":"Wal-Mart Vision Center & Optometrists",
    "wof:placetype":"venue"
},
  "geometry": {"coordinates":[-75.493599,40.645599],"type":"Point"}
}