{
  "type": "Feature",
  "properties": {
    "iso:country":"US",
    "sg:address":"19 Rockwood Ave",
    "sg:city":"Oil City",
    "sg:classifiers":[
        {
            "category":"Real Estate",
            "subcategory":"Real Estate Agent",
            "type":"Services"
        }
    ],
    "sg:phone":"+1 814 677 5926",
    "sg:postcode":"16301",
    "sg:province":"PA",
    "sg:tags":[
        "authorities",
        "housing"
    ],
    "wof:name":"Housing Authority-County",
    "wof:placetype":"venue"
},
  "geometry": {"coordinates":[-79.678259,41.445475],"type":"Point"}
}