{
  "type": "Feature",
  "properties": {
    "iso:country":"US",
    "sg:address":"4000 Mount Royal Blvd",
    "sg:city":"Allison Park",
    "sg:classifiers":[
        {
            "category":"Health Services",
            "subcategory":"Doctor",
            "type":"Services"
        }
    ],
    "sg:phone":"+1   ",
    "sg:postcode":"15101",
    "sg:province":"PA",
    "wof:name":"Senior Dntl Care Allgheny Cnty",
    "wof:placetype":"venue"
},
  "geometry": {"coordinates":[-79.96632099999999,40.563465],"type":"Point"}
}