{
  "type": "Feature",
  "properties": {
    "iso:country":"US",
    "sg:address":"814 Academy Heights Ave",
    "sg:city":"Ephrata",
    "sg:classifiers":[
        {
            "category":"Utilities",
            "subcategory":"Cable",
            "type":"Services"
        }
    ],
    "sg:phone":"+1 717 733 0011",
    "sg:postcode":"17522",
    "sg:province":"PA",
    "sg:tags":[
        "television"
    ],
    "wof:name":"Cable-11 Studios",
    "wof:placetype":"venue"
},
  "geometry": {"coordinates":[-76.189334,40.185215],"type":"Point"}
}