{
  "type": "Feature",
  "properties": {
    "addr:full":"134 Bell Rd Palmyra PA 17078",
    "addr:housenumber":"134",
    "addr:postcode":"17078",
    "addr:street":"Bell Rd",
    "iso:country":"US",
    "sg:address":"134 Bell Rd",
    "sg:city":"Palmyra",
    "sg:classifiers":[
        {
            "category":"Building & Trades",
            "subcategory":"Landscaping Services",
            "type":"Services"
        }
    ],
    "sg:phone":"+1 717 832 0476",
    "sg:postcode":"17078",
    "sg:province":"PA",
    "sg:tags":[
        "landscape",
        "contractor"
    ],
    "wof:name":"Advantage Lawn & Landscape",
    "wof:placetype":"venue"
},
  "geometry": {"coordinates":[-76.572321,40.261079],"type":"Point"}
}