{
  "type": "Feature",
  "properties": {
    "iso:country":"US",
    "sg:address":"32 Rust Hill Rd",
    "sg:city":"Levittown",
    "sg:classifiers":[
        {
            "category":"Building & Trades",
            "subcategory":"Construction",
            "type":"Services"
        }
    ],
    "sg:phone":"+1 215 741 4834",
    "sg:postcode":"19056",
    "sg:province":"PA",
    "sg:tags":[
        "general",
        "contractor"
    ],
    "wof:name":"Wenderlich Construction",
    "wof:placetype":"venue"
},
  "geometry": {"coordinates":[-74.878713,40.155607],"type":"Point"}
}