{
  "type": "Feature",
  "properties": {
    "addr:full":"20138 Valley Forge Cir King Of Prussia PA 19406",
    "addr:housenumber":"20138",
    "addr:postcode":"19406",
    "addr:street":"Valley Forge Cir",
    "iso:country":"US",
    "sg:address":"20138 Valley Forge Cir",
    "sg:city":"King Of Prussia",
    "sg:classifiers":[
        {
            "category":"Real Estate",
            "subcategory":"Real Estate Agent",
            "type":"Services"
        }
    ],
    "sg:phone":"+1 610 783 0500",
    "sg:postcode":"19406",
    "sg:province":"PA",
    "sg:tags":[
        "appraiser"
    ],
    "wof:name":"Bearoff & Co",
    "wof:placetype":"venue"
},
  "geometry": {"coordinates":[-75.41374399999999,40.104293],"type":"Point"}
}