{
  "type": "Feature",
  "properties": {
    "iso:country":"US",
    "sg:address":"241 Jennie Dr",
    "sg:city":"North Huntingdon",
    "sg:classifiers":[
        {
            "category":"Professional",
            "subcategory":"Computer Services",
            "type":"Services"
        }
    ],
    "sg:phone":"+1 724 864 7750",
    "sg:postcode":"15642",
    "sg:province":"PA",
    "sg:tags":[
        "system",
        "cad"
    ],
    "wof:name":"Wynn H Frick",
    "wof:placetype":"venue"
},
  "geometry": {"coordinates":[-79.741051,40.326835],"type":"Point"}
}