{
  "type": "Feature",
  "properties": {
    "iso:country":"US",
    "sg:address":"5918 William Flynn Hwy",
    "sg:city":"Bakerstown",
    "sg:phone":"+1 724 443 5402",
    "sg:postcode":"15007",
    "sg:province":"PA",
    "sg:tags":[
        "equipment",
        "supply"
    ],
    "wof:name":"North Pittsburgh Showcase",
    "wof:placetype":"venue"
},
  "geometry": {"coordinates":[-79.935264,40.655434],"type":"Point"}
}