{
  "type": "Feature",
  "properties": {
    "iso:country":"US",
    "sg:address":"5648 2nd Ave",
    "sg:city":"Pittsburgh",
    "sg:classifiers":[
        {
            "category":"Building & Trades",
            "subcategory":"Plumbing",
            "type":"Services"
        }
    ],
    "sg:phone":"+1   ",
    "sg:postcode":"15207",
    "sg:province":"PA",
    "sg:tags":[
        "contractor"
    ],
    "wof:name":"Cordero Plumbing",
    "wof:placetype":"venue"
},
  "geometry": {"coordinates":[-79.93788499999999,40.400084],"type":"Point"}
}