{
  "type": "Feature",
  "properties": {
    "addr:full":"2410 Single Tree Ln Norristown PA 19403",
    "addr:housenumber":"2410",
    "addr:postcode":"19403",
    "addr:street":"Single Tree Ln",
    "iso:country":"US",
    "sg:address":"2410 Single Tree Ln",
    "sg:city":"Norristown",
    "sg:classifiers":[
        {
            "category":"Health Services",
            "subcategory":"Clinic",
            "type":"Services"
        }
    ],
    "sg:phone":"+1 610 539 3867",
    "sg:postcode":"19403",
    "sg:province":"PA",
    "sg:tags":[
        "welfare"
    ],
    "wof:name":"Spectrum Healthcare",
    "wof:placetype":"venue"
},
  "geometry": {"coordinates":[-75.378992,40.146672],"type":"Point"}
}