{
  "type": "Feature",
  "properties": {
    "addr:full":"5830 Forbes Ave Pittsburgh PA 15217",
    "addr:housenumber":"5830",
    "addr:postcode":"15217",
    "addr:street":"Forbes Ave",
    "iso:country":"US",
    "sg:address":"5830 Forbes Ave",
    "sg:city":"Pittsburgh",
    "sg:classifiers":[
        {
            "category":"Food & Beverages",
            "subcategory":"Candy",
            "type":"Retail Goods"
        },
        {
            "category":"Shopping",
            "subcategory":"Gifts & Souvenirs",
            "type":"Retail Goods"
        }
    ],
    "sg:phone":"+1 412 422 2208",
    "sg:postcode":"15217",
    "sg:province":"PA",
    "wof:name":"Chocolate Moose Inc",
    "wof:placetype":"venue"
},
  "geometry": {"coordinates":[-79.920377,40.437969],"type":"Point"}
}