{
  "type": "Feature",
  "properties": {
    "iso:country":"US",
    "sg:address":"1830 Midland Beaver Rd",
    "sg:city":"Industry",
    "sg:classifiers":[
        {
            "category":"Restaurant",
            "type":"Food & Drink"
        }
    ],
    "sg:phone":"+1 724 643 4500",
    "sg:postcode":"15052",
    "sg:province":"PA",
    "sg:tags":[
        "banquet",
        "rooms"
    ],
    "wof:name":"Willows Inn",
    "wof:placetype":"venue"
},
  "geometry": {"coordinates":[-80.400149,40.651655],"type":"Point"}
}