{
  "type": "Feature",
  "properties": {
    "addr:full":"642 Hooker Rd West Sunbury PA 16061",
    "addr:housenumber":"642",
    "addr:postcode":"16061",
    "addr:street":"Hooker Rd",
    "iso:country":"US",
    "sg:address":"642 Hooker Rd",
    "sg:city":"West Sunbury",
    "sg:phone":"+1 724 894 2414",
    "sg:postcode":"16061",
    "sg:province":"PA",
    "sg:tags":[
        "gas"
    ],
    "wof:name":"Stewart & Stewart Inc",
    "wof:placetype":"venue"
},
  "geometry": {"coordinates":[-79.843535,40.997606],"type":"Point"}
}