{
  "type": "Feature",
  "properties": {
    "iso:country":"US",
    "sg:address":"61 W King St",
    "sg:city":"Pottstown",
    "sg:classifiers":[
        {
            "category":"Restaurant",
            "type":"Food & Drink"
        }
    ],
    "sg:phone":"+1   ",
    "sg:postcode":"19464",
    "sg:province":"PA",
    "sg:tags":[
        "eating"
    ],
    "wof:name":"Star Wok Restaurant",
    "wof:placetype":"venue"
},
  "geometry": {"coordinates":[-75.657926,40.248092],"type":"Point"}
}