{
  "type": "Feature",
  "properties": {
    "iso:country":"US",
    "sg:address":"7455 Church St",
    "sg:city":"Swissvale",
    "sg:classifiers":[
        {
            "category":"Health Services",
            "subcategory":"Clinic",
            "type":"Services"
        }
    ],
    "sg:phone":"+1 412 683 9938",
    "sg:postcode":"15218",
    "sg:province":"PA",
    "sg:tags":[
        "holistic",
        "practitioner"
    ],
    "wof:name":"Aletheia Center For Holistic",
    "wof:placetype":"venue"
},
  "geometry": {"coordinates":[-79.88967,40.422208],"type":"Point"}
}