{
  "type": "Feature",
  "properties": {
    "iso:country":"US",
    "sg:address":"4514 Princeton Ave",
    "sg:city":"Philadelphia",
    "sg:classifiers":[
        {
            "category":"Professional",
            "type":"Services"
        }
    ],
    "sg:phone":"+1   ",
    "sg:postcode":"19135",
    "sg:province":"PA",
    "wof:name":"Anthony A Naccarato",
    "wof:placetype":"venue"
},
  "geometry": {"coordinates":[-75.039912,40.029215],"type":"Point"}
}