{
  "type": "Feature",
  "properties": {
    "addr:full":"607 Church St Girard PA 16417",
    "addr:housenumber":"607",
    "addr:postcode":"16417",
    "addr:street":"Church St",
    "iso:country":"US",
    "sg:address":"607 Church St",
    "sg:city":"Girard",
    "sg:classifiers":[
        {
            "category":"Manufacturing",
            "subcategory":"Retail Goods",
            "type":"Manufacturing & Wholesale Goods"
        }
    ],
    "sg:phone":"+1 814 774 3137",
    "sg:postcode":"16417",
    "sg:province":"PA",
    "sg:tags":[
        "manufacturer"
    ],
    "sg:website":"www.emscogroup.com",
    "wof:name":"Emsco-Erie Inc",
    "wof:placetype":"venue"
},
  "geometry": {"coordinates":[-80.31798999999999,42.009194],"type":"Point"}
}