{
  "type": "Feature",
  "properties": {
    "iso:country":"US",
    "sg:address":"124 Barnsley Rd",
    "sg:city":"Oxford",
    "sg:classifiers":[
        {
            "category":"Retail",
            "subcategory":"Auto Repair",
            "type":"Services"
        }
    ],
    "sg:phone":"+1 610 932 3977",
    "sg:postcode":"19363",
    "sg:province":"PA",
    "sg:tags":[
        "general"
    ],
    "wof:name":"Scott Adams Tire & Alignment",
    "wof:placetype":"venue"
},
  "geometry": {"coordinates":[-75.98889200000001,39.765938],"type":"Point"}
}