{
  "type": "Feature",
  "properties": {
    "iso:country":"US",
    "sg:address":"524 Burmont Rd",
    "sg:city":"Drexel Hill",
    "sg:classifiers":[
        {
            "category":"Home & Garden",
            "subcategory":"Hardware",
            "type":"Retail Goods"
        }
    ],
    "sg:phone":"+1   ",
    "sg:postcode":"19026",
    "sg:province":"PA",
    "wof:name":"Burhill Hardware",
    "wof:placetype":"venue"
},
  "geometry": {"coordinates":[-75.301925,39.946766],"type":"Point"}
}