{
  "type": "Feature",
  "properties": {
    "iso:country":"US",
    "sg:address":"7630 Fayette St",
    "sg:city":"Philadelphia",
    "sg:classifiers":[
        {
            "category":"Freight",
            "type":"Transportation"
        }
    ],
    "sg:phone":"+1 215 548 1411",
    "sg:postcode":"19150",
    "sg:province":"PA",
    "sg:tags":[
        "operator",
        "trucking-light",
        "local",
        "hauling",
        "trucking"
    ],
    "wof:name":"United Vending Hauling",
    "wof:placetype":"venue"
},
  "geometry": {"coordinates":[-75.161008,40.070039],"type":"Point"}
}