{
  "type": "Feature",
  "properties": {
    "iso:country":"US",
    "sg:address":"295 E Main St",
    "sg:city":"Brookville",
    "sg:classifiers":[
        {
            "category":"Shopping",
            "subcategory":"Bicycles & Sporting Goods",
            "type":"Retail Goods"
        }
    ],
    "sg:phone":"+1 814 220 0010",
    "sg:postcode":"15825",
    "sg:province":"PA",
    "wof:name":"Rich's Outdoor World",
    "wof:placetype":"venue"
},
  "geometry": {"coordinates":[-79.08114399999999,41.160515],"type":"Point"}
}