{
  "type": "Feature",
  "properties": {
    "addr:full":"601 W Marshall St Norristown PA 19401",
    "addr:housenumber":"601",
    "addr:postcode":"19401",
    "addr:street":"W Marshall St",
    "iso:country":"US",
    "sg:address":"601 W Marshall St",
    "sg:city":"Norristown",
    "sg:classifiers":[
        {
            "category":"Retail",
            "subcategory":"Self-service Laundry",
            "type":"Services"
        }
    ],
    "sg:phone":"+1 610 272 8320",
    "sg:postcode":"19401",
    "sg:province":"PA",
    "sg:tags":[
        "coin"
    ],
    "wof:name":"Sno-Flake Laundromat Inc",
    "wof:placetype":"venue"
},
  "geometry": {"coordinates":[-75.350562,40.121016],"type":"Point"}
}