{
  "type": "Feature",
  "properties": {
    "iso:country":"US",
    "sg:address":"6300 Buist Ave",
    "sg:city":"Philadelphia",
    "sg:classifiers":[
        {
            "category":"Place Of Worship",
            "subcategory":"Church",
            "type":"Public Place"
        },
        {
            "category":"Place Of Worship",
            "type":"Public Place"
        }
    ],
    "sg:phone":"+1 215 726 1119",
    "sg:postcode":"19142",
    "sg:province":"PA",
    "sg:tags":[
        "churches-catholic-traditional",
        "churches-salvation",
        "churches-catholic",
        "army"
    ],
    "sg:website":"http://www.archbishopryan.com",
    "wof:name":"St Barnabas Rectory",
    "wof:placetype":"venue"
},
  "geometry": {"coordinates":[-75.226311,39.922871],"type":"Point"}
}