{
  "type": "Feature",
  "properties": {
    "iso:country":"US",
    "sg:address":"429 W 6th St",
    "sg:city":"Erie",
    "sg:classifiers":[
        {
            "category":"Health Services",
            "subcategory":"Clinic",
            "type":"Services"
        }
    ],
    "sg:phone":"+1   ",
    "sg:postcode":"16507",
    "sg:province":"PA",
    "sg:tags":[
        "residential",
        "specialty",
        "outpatient",
        "care"
    ],
    "wof:name":"Abraxas Halfway House",
    "wof:placetype":"venue"
},
  "geometry": {"coordinates":[-80.09611700000001,42.125431],"type":"Point"}
}