{
  "type": "Feature",
  "properties": {
    "addr:full":"2439 Mill St Aliquippa PA 15001",
    "addr:housenumber":"2439",
    "addr:postcode":"15001",
    "addr:street":"Mill St",
    "iso:country":"US",
    "sg:address":"2439 Mill St",
    "sg:city":"Aliquippa",
    "sg:classifiers":[
        {
            "category":"Personal",
            "subcategory":"Beauty Salon",
            "type":"Services"
        }
    ],
    "sg:phone":"+1 724 375 2464",
    "sg:postcode":"15001",
    "sg:province":"PA",
    "wof:name":"Ceccarelli Hair & Tanning",
    "wof:placetype":"venue"
},
  "geometry": {"coordinates":[-80.286765,40.606263],"type":"Point"}
}