{
  "type": "Feature",
  "properties": {
    "iso:country":"US",
    "sg:address":"595 Galiffa Dr",
    "sg:city":"Donora",
    "sg:classifiers":[
        {
            "category":"Food & Beverages",
            "subcategory":"Liquor & Beverages",
            "type":"Retail Goods"
        }
    ],
    "sg:phone":"+1 724 379 1583",
    "sg:postcode":"15033",
    "sg:province":"PA",
    "sg:tags":[
        "beer",
        "spirit",
        "wine"
    ],
    "wof:name":"Wine & Spirits Stores",
    "wof:placetype":"venue"
},
  "geometry": {"coordinates":[-79.855751,40.16752],"type":"Point"}
}