{
  "type": "Feature",
  "properties": {
    "iso:country":"US",
    "sg:address":"4207 Lincoln Hwy",
    "sg:city":"Thorndale",
    "sg:classifiers":[
        {
            "category":"Professional",
            "subcategory":"Business Services",
            "type":"Services"
        }
    ],
    "sg:phone":"+1 610 269 1916",
    "sg:postcode":"19365",
    "sg:province":"PA",
    "sg:tags":[
        "license"
    ],
    "wof:name":"Wiggins Auto Tags",
    "wof:placetype":"venue"
},
  "geometry": {"coordinates":[-75.944534,39.984826],"type":"Point"}
}