{
  "type": "Feature",
  "properties": {
    "addr:full":"201 N Dithridge St Pittsburgh PA 15213",
    "addr:housenumber":"201",
    "addr:postcode":"15213",
    "addr:street":"N Dithridge St",
    "iso:country":"US",
    "sg:address":"201 N Dithridge St",
    "sg:city":"Pittsburgh",
    "sg:classifiers":[
        {
            "category":"Organizations",
            "subcategory":"Religious Organization",
            "type":"Services"
        }
    ],
    "sg:phone":"+1 412 621 5339",
    "sg:postcode":"15213",
    "sg:province":"PA",
    "sg:tags":[
        "church"
    ],
    "wof:name":"First Church-Christ Scientist",
    "wof:placetype":"venue"
},
  "geometry": {"coordinates":[-79.95334699999999,40.451488],"type":"Point"}
}