{
  "type": "Feature",
  "properties": {
    "addr:full":"2015 Palomino Dr Warrington PA 18976",
    "addr:housenumber":"2015",
    "addr:postcode":"18976",
    "addr:street":"Palomino Dr",
    "iso:country":"US",
    "sg:address":"2015 Palomino Dr",
    "sg:city":"Warrington",
    "sg:classifiers":[
        {
            "category":"Education",
            "subcategory":"School",
            "type":"Public Place"
        }
    ],
    "sg:phone":"+1 267 893 4100",
    "sg:postcode":"18976",
    "sg:province":"PA",
    "sg:tags":[
        "elementary"
    ],
    "wof:name":"Barclay Elementary School",
    "wof:placetype":"venue"
},
  "geometry": {"coordinates":[-75.129797,40.236235],"type":"Point"}
}