{
  "type": "Feature",
  "properties": {
    "addr:full":"281 Mill St Danville PA 17821",
    "addr:housenumber":"281",
    "addr:postcode":"17821",
    "addr:street":"Mill St",
    "iso:country":"US",
    "sg:address":"281 Mill St",
    "sg:city":"Danville",
    "sg:classifiers":[
        {
            "category":"Personal",
            "subcategory":"Beauty Salon",
            "type":"Services"
        }
    ],
    "sg:phone":"+1   ",
    "sg:postcode":"17821",
    "sg:province":"PA",
    "sg:tags":[
        "shop"
    ],
    "wof:name":"Cut & Curl",
    "wof:placetype":"venue"
},
  "geometry": {"coordinates":[-76.61751,40.962266],"type":"Point"}
}