{
  "type": "Feature",
  "properties": {
    "iso:country":"US",
    "sg:address":"3884 Union Deposit Rd",
    "sg:city":"Harrisburg",
    "sg:classifiers":[
        {
            "category":"Ice Cream",
            "type":"Food & Drink"
        }
    ],
    "sg:menulink":"http://www.allmenus.com/pa/susquehanna/234845-ritas-ice-custard-happiness/menu/",
    "sg:phone":"+1 717 671 0888",
    "sg:postcode":"17109",
    "sg:province":"PA",
    "sg:tags":[
        "american"
    ],
    "wof:name":"Rita's Ice Custard Happiness",
    "wof:placetype":"venue"
},
  "geometry": {"coordinates":[-76.82399700000001,40.278106],"type":"Point"}
}