{
  "type": "Feature",
  "properties": {
    "addr:full":"20 Union St E Richlandtown PA 18955",
    "addr:housenumber":"20",
    "addr:postcode":"18955",
    "addr:street":"Union St E Richlandtown",
    "iso:country":"US",
    "sg:address":"20 Union St E",
    "sg:city":"Richlandtown",
    "sg:classifiers":[
        {
            "category":"Utilities",
            "subcategory":"Fuel Oil & Lpg",
            "type":"Services"
        }
    ],
    "sg:phone":"+1   ",
    "sg:postcode":"18955",
    "sg:province":"PA",
    "sg:tags":[
        "liquefied",
        "gas",
        "petroleum"
    ],
    "wof:name":"Doylestown Bottled Gas Co",
    "wof:placetype":"venue"
},
  "geometry": {"coordinates":[-75.31956700000001,40.469776],"type":"Point"}
}