{
  "type": "Feature",
  "properties": {
    "iso:country":"US",
    "sg:address":"48 N Hellertown Ave",
    "sg:city":"Quakertown",
    "sg:classifiers":[
        {
            "category":"Education",
            "subcategory":"School",
            "type":"Public Place"
        }
    ],
    "sg:phone":"+1 215 536 4060",
    "sg:postcode":"18951",
    "sg:province":"PA",
    "wof:name":"Tween Tot Nursery",
    "wof:placetype":"venue"
},
  "geometry": {"coordinates":[-75.333157,40.442444],"type":"Point"}
}