{
  "type": "Feature",
  "properties": {
    "addr:full":"6391 Oxford Ave Philadelphia PA 19111",
    "addr:housenumber":"6391",
    "addr:postcode":"19111",
    "addr:street":"Oxford Ave",
    "iso:country":"US",
    "sg:address":"6391 Oxford Ave",
    "sg:city":"Philadelphia",
    "sg:classifiers":[
        {
            "category":"Deli",
            "type":"Food & Drink"
        },
        {
            "category":"Restaurant",
            "type":"Food & Drink"
        }
    ],
    "sg:phone":"+1 215 533 1111",
    "sg:postcode":"19111",
    "sg:province":"PA",
    "sg:tags":[
        "delicatessen"
    ],
    "wof:name":"Christines Deli & Catering",
    "wof:placetype":"venue"
},
  "geometry": {"coordinates":[-75.088459,40.045324],"type":"Point"}
}