{
  "type": "Feature",
  "properties": {
    "iso:country":"US",
    "sg:address":"1690 E Race St",
    "sg:city":"Allentown",
    "sg:classifiers":[
        {
            "category":"Professional",
            "type":"Services"
        }
    ],
    "sg:phone":"+1   ",
    "sg:postcode":"18109",
    "sg:province":"PA",
    "wof:name":"Liqui-Box Corp",
    "wof:placetype":"venue"
},
  "geometry": {"coordinates":[-75.436086,40.661161],"type":"Point"}
}