{
  "type": "Feature",
  "properties": {
    "addr:full":"503 Greenfield Ave Pittsburgh PA 15207",
    "addr:housenumber":"503",
    "addr:postcode":"15207",
    "addr:street":"Greenfield Ave",
    "iso:country":"US",
    "sg:address":"503 Greenfield Ave",
    "sg:city":"Pittsburgh",
    "sg:classifiers":[
        {
            "category":"Banks & Credit Unions",
            "subcategory":"Bank",
            "type":"Services"
        }
    ],
    "sg:phone":"+1 412 421 0040",
    "sg:postcode":"15207",
    "sg:province":"PA",
    "sg:tags":[
        "savings",
        "institution"
    ],
    "wof:name":"Parkvale Savings Bank",
    "wof:placetype":"venue"
},
  "geometry": {"coordinates":[-79.941759,40.425767],"type":"Point"}
}