{
  "type": "Feature",
  "properties": {
    "iso:country":"US",
    "sg:address":"1446 Hollow Rd",
    "sg:city":"Collegeville",
    "sg:classifiers":[
        {
            "category":"Building & Trades",
            "subcategory":"Plumbing",
            "type":"Services"
        }
    ],
    "sg:phone":"+1   ",
    "sg:postcode":"19426",
    "sg:province":"PA",
    "sg:tags":[
        "repair",
        "contractor"
    ],
    "wof:name":"Ferrero Wastewater Management",
    "wof:placetype":"venue"
},
  "geometry": {"coordinates":[-75.37137300000001,40.186387],"type":"Point"}
}