{
  "type": "Feature",
  "properties": {
    "addr:full":"404 Jackson St Dickson City PA 18519",
    "addr:housenumber":"404",
    "addr:postcode":"18519",
    "addr:street":"Jackson St",
    "iso:country":"US",
    "sg:address":"404 Jackson St",
    "sg:city":"Dickson City",
    "sg:classifiers":[
        {
            "category":"Professional",
            "subcategory":"Advertising",
            "type":"Services"
        }
    ],
    "sg:phone":"+1 570 383 2090",
    "sg:postcode":"18519",
    "sg:province":"PA",
    "sg:tags":[
        "counselor"
    ],
    "sg:website":"www.kiwistudios.com",
    "wof:name":"Kiwi Studios",
    "wof:placetype":"venue"
},
  "geometry": {"coordinates":[-75.62214400000001,41.461572],"type":"Point"}
}