{
  "type": "Feature",
  "properties": {
    "iso:country":"US",
    "sg:address":"1735 5th Ave",
    "sg:city":"Freedom",
    "sg:classifiers":[
        {
            "category":"Organizations",
            "subcategory":"Community Association",
            "type":"Services"
        }
    ],
    "sg:phone":"+1 724 728 1497",
    "sg:postcode":"15042",
    "sg:province":"PA",
    "sg:tags":[
        "club",
        "sport",
        "center",
        "entertainment"
    ],
    "wof:name":"Freedom Serbian Club",
    "wof:placetype":"venue"
},
  "geometry": {"coordinates":[-80.246697,40.676779],"type":"Point"}
}