{
  "type": "Feature",
  "properties": {
    "iso:country":"US",
    "sg:address":"1319 N Chester Rd",
    "sg:city":"West Chester",
    "sg:classifiers":[
        {
            "category":"Arts & Performance",
            "subcategory":"Theater",
            "type":"Entertainment"
        }
    ],
    "sg:phone":"+1 610 524 4733",
    "sg:postcode":"19380",
    "sg:province":"PA",
    "sg:tags":[
        "live",
        "music"
    ],
    "wof:name":"Dynamite Audio LLC",
    "wof:placetype":"venue"
},
  "geometry": {"coordinates":[-75.54787899999999,40.021035],"type":"Point"}
}