{
  "type": "Feature",
  "properties": {
    "addr:full":"1520 Locust St Philadelphia PA 19102",
    "addr:housenumber":"1520",
    "addr:postcode":"19102",
    "addr:street":"Locust St",
    "iso:country":"US",
    "sg:address":"1520 Locust St",
    "sg:city":"Philadelphia",
    "sg:classifiers":[
        {
            "category":"Social Services",
            "type":"Services"
        }
    ],
    "sg:phone":"+1 215 599 0253",
    "sg:postcode":"19102",
    "sg:province":"PA",
    "sg:tags":[
        "center",
        "instruction",
        "system",
        "improvement",
        "youth",
        "equipment",
        "reading"
    ],
    "wof:name":"Youth Agricultural Literacy &",
    "wof:placetype":"venue"
},
  "geometry": {"coordinates":[-75.16699699999999,39.948523],"type":"Point"}
}