{
  "type": "Feature",
  "properties": {
    "iso:country":"US",
    "sg:address":"166 Cecil B Moore Ave",
    "sg:city":"Philadelphia",
    "sg:classifiers":[
        {
            "category":"Retail",
            "subcategory":"Auto Repair",
            "type":"Services"
        }
    ],
    "sg:phone":"+1 215 427 1611",
    "sg:postcode":"19122",
    "sg:province":"PA",
    "sg:tags":[
        "repairing",
        "automobile"
    ],
    "wof:name":"Peak Motors Inc",
    "wof:placetype":"venue"
},
  "geometry": {"coordinates":[-75.13751600000001,39.976011],"type":"Point"}
}