{
  "type": "Feature",
  "properties": {
    "iso:country":"US",
    "sg:address":"314 Arborlea Ave",
    "sg:city":"Morrisville",
    "sg:classifiers":[
        {
            "category":"Freight",
            "type":"Transportation"
        }
    ],
    "sg:phone":"+1   ",
    "sg:postcode":"19067",
    "sg:province":"PA",
    "sg:tags":[
        "trucking"
    ],
    "wof:name":"Schulz HP Trucking",
    "wof:placetype":"venue"
},
  "geometry": {"coordinates":[-74.80379600000001,40.213655],"type":"Point"}
}