{
  "type": "Feature",
  "properties": {
    "iso:country":"US",
    "sg:address":"60 E Shenango St",
    "sg:city":"Sharpsville",
    "sg:classifiers":[
        {
            "category":"Real Estate",
            "subcategory":"Real Estate Agent",
            "type":"Services"
        }
    ],
    "sg:phone":"+1   ",
    "sg:postcode":"16150",
    "sg:province":"OH",
    "wof:name":"Jerry Barber",
    "wof:placetype":"venue"
},
  "geometry": {"coordinates":[-80.47462400000001,41.265943],"type":"Point"}
}