{
  "type": "Feature",
  "properties": {
    "iso:country":"US",
    "sg:address":"147 Valley View Dr",
    "sg:city":"Butler",
    "sg:classifiers":[
        {
            "category":"Social Services",
            "subcategory":"Adult Care",
            "type":"Services"
        }
    ],
    "sg:phone":"+1 724 282 8111",
    "sg:postcode":"16002",
    "sg:province":"PA",
    "sg:tags":[
        "home",
        "residential"
    ],
    "wof:name":"Colonial Gardens Guest House",
    "wof:placetype":"venue"
},
  "geometry": {"coordinates":[-79.83585100000001,40.859634],"type":"Point"}
}