{
  "type": "Feature",
  "properties": {
    "iso:country":"US",
    "sg:address":"250 Oxford Valley Rd",
    "sg:city":"Morrisville",
    "sg:classifiers":[
        {
            "category":"Manufacturing",
            "subcategory":"Lumber",
            "type":"Manufacturing & Wholesale Goods"
        }
    ],
    "sg:phone":"+1   ",
    "sg:postcode":"19067",
    "sg:province":"PA",
    "sg:tags":[
        "mill",
        "material"
    ],
    "wof:name":"Quinn M W Hardwood Lbr Sawmill",
    "wof:placetype":"venue"
},
  "geometry": {"coordinates":[-74.86766299999999,40.202807],"type":"Point"}
}