{
  "type": "Feature",
  "properties": {
    "addr:full":"208 Waterford St Edinboro PA 16412",
    "addr:housenumber":"208",
    "addr:postcode":"16412",
    "addr:street":"Waterford St",
    "iso:country":"US",
    "sg:address":"208 Waterford St",
    "sg:city":"Edinboro",
    "sg:classifiers":[
        {
            "category":"Health Services",
            "subcategory":"Medical Lab",
            "type":"Services"
        }
    ],
    "sg:phone":"+1 814 734 5220",
    "sg:postcode":"16412",
    "sg:province":"PA",
    "sg:tags":[
        "x"
    ],
    "wof:name":"Hamot Imaging Ctr",
    "wof:placetype":"venue"
},
  "geometry": {"coordinates":[-80.121244,41.877102],"type":"Point"}
}