{
  "type": "Feature",
  "properties": {
    "iso:country":"US",
    "sg:address":"301 S 12th St",
    "sg:city":"Philadelphia",
    "sg:classifiers":[
        {
            "category":"Travel",
            "subcategory":"Hotels & Motels",
            "type":"Entertainment"
        }
    ],
    "sg:phone":"+1 215 923 3535",
    "sg:postcode":"19107",
    "sg:province":"PA",
    "sg:tags":[
        "breakfast",
        "accommodation",
        "bed"
    ],
    "sg:website":"www.alexanderinn.com",
    "wof:name":"Alexander Inn",
    "wof:placetype":"venue"
},
  "geometry": {"coordinates":[-75.16112099999999,39.946206],"type":"Point"}
}