{
  "type": "Feature",
  "properties": {
    "iso:country":"US",
    "sg:address":"3537 Locust Walk",
    "sg:city":"Philadelphia",
    "sg:classifiers":[
        {
            "category":"Education",
            "subcategory":"School",
            "type":"Public Place"
        }
    ],
    "sg:phone":"+1   ",
    "sg:postcode":"19104",
    "sg:province":"PA",
    "wof:name":"Lead Prgram At Wharton Schools",
    "wof:placetype":"venue"
},
  "geometry": {"coordinates":[-75.194582,39.952101],"type":"Point"}
}