{
  "type": "Feature",
  "properties": {
    "iso:country":"US",
    "sg:address":"4 S 4th St",
    "sg:city":"Reading",
    "sg:classifiers":[
        {
            "category":"Health Services",
            "subcategory":"Doctor",
            "type":"Services"
        }
    ],
    "sg:phone":"+1 610 378 2306",
    "sg:postcode":"19602",
    "sg:province":"PA",
    "sg:tags":[
        "physician",
        "surgeon"
    ],
    "wof:name":"Mark P Stegman MD",
    "wof:placetype":"venue"
},
  "geometry": {"coordinates":[-75.92994299999999,40.334521],"type":"Point"}
}