{
  "type": "Feature",
  "properties": {
    "iso:country":"US",
    "sg:address":"3612 Avalon St",
    "sg:city":"Philadelphia",
    "sg:classifiers":[
        {
            "category":"Home & Garden",
            "subcategory":"Building Materials",
            "type":"Retail Goods"
        },
        {
            "category":"Building & Trades",
            "subcategory":"Construction",
            "type":"Services"
        }
    ],
    "sg:phone":"+1 215 612 2230",
    "sg:postcode":"19114",
    "sg:province":"PA",
    "sg:tags":[
        "installation",
        "windows-repair",
        "siding",
        "contractor",
        "window",
        "replacement"
    ],
    "wof:name":"Adams Siding & Windows",
    "wof:placetype":"venue"
},
  "geometry": {"coordinates":[-74.998865,40.074694],"type":"Point"}
}