{
  "type": "Feature",
  "properties": {
    "addr:full":"108 W Beidler Rd King Of Prussia PA 19406",
    "addr:housenumber":"108",
    "addr:postcode":"19406",
    "addr:street":"W Beidler Rd",
    "iso:country":"US",
    "sg:address":"108 W Beidler Rd",
    "sg:city":"King Of Prussia",
    "sg:classifiers":[
        {
            "category":"Health Services",
            "subcategory":"Chiropractor",
            "type":"Services"
        }
    ],
    "sg:phone":"+1 610 337 2424",
    "sg:postcode":"19406",
    "sg:province":"PA",
    "wof:name":"Henderson Center Chiropractic",
    "wof:placetype":"venue"
},
  "geometry": {"coordinates":[-75.377948,40.112667],"type":"Point"}
}