{
  "type": "Feature",
  "properties": {
    "iso:country":"US",
    "sg:address":"2967 W School House Ln",
    "sg:city":"Philadelphia",
    "sg:classifiers":[
        {
            "category":"Professional",
            "type":"Services"
        }
    ],
    "sg:phone":"+1 215 713 9111",
    "sg:postcode":"19144",
    "sg:province":"PA",
    "sg:tags":[
        "establishment"
    ],
    "wof:name":"M Furman",
    "wof:placetype":"venue"
},
  "geometry": {"coordinates":[-75.18195900000001,40.025613],"type":"Point"}
}