{
  "type": "Feature",
  "properties": {
    "addr:full":"84 S 24th St Pittsburgh PA 15203",
    "addr:housenumber":"84",
    "addr:postcode":"15203",
    "addr:street":"S 24Th St",
    "iso:country":"US",
    "sg:address":"84 S 24th St",
    "sg:city":"Pittsburgh",
    "sg:classifiers":[
        {
            "category":"Building & Trades",
            "subcategory":"Electrical",
            "type":"Services"
        }
    ],
    "sg:phone":"+1   ",
    "sg:postcode":"15203",
    "sg:province":"PA",
    "sg:tags":[
        "engineering",
        "electrical",
        "provides"
    ],
    "wof:name":"B & C Transit Consultants Inc",
    "wof:placetype":"venue"
},
  "geometry": {"coordinates":[-79.970795,40.429559],"type":"Point"}
}