{
  "type": "Feature",
  "properties": {
    "iso:country":"US",
    "sg:address":"130 E Division St",
    "sg:city":"Wilkes Barre",
    "sg:classifiers":[
        {
            "category":"Social Services",
            "type":"Services"
        }
    ],
    "sg:phone":"+1   ",
    "sg:postcode":"18706",
    "sg:province":"PA",
    "sg:tags":[
        "family"
    ],
    "wof:name":"Wilkes-Barre/Scranton Svc Ctr",
    "wof:placetype":"venue"
},
  "geometry": {"coordinates":[-75.905895,41.228481],"type":"Point"}
}