{
  "type": "Feature",
  "properties": {
    "addr:full":"4765 Forest St Lehighton PA 18235",
    "addr:housenumber":"4765",
    "addr:postcode":"18235",
    "addr:street":"Forest St",
    "iso:country":"US",
    "sg:address":"4765 Forest St",
    "sg:city":"Lehighton",
    "sg:classifiers":[
        {
            "category":"Building & Trades",
            "subcategory":"Cleaning & Sanitation",
            "type":"Services"
        }
    ],
    "sg:phone":"+1   ",
    "sg:postcode":"18235",
    "sg:province":"PA",
    "sg:tags":[
        "maintenance"
    ],
    "wof:name":"Nighthawk Maintenance Inc",
    "wof:placetype":"venue"
},
  "geometry": {"coordinates":[-75.593411,40.912679],"type":"Point"}
}