{
  "type": "Feature",
  "properties": {
    "iso:country":"US",
    "sg:address":"622 N Broad St",
    "sg:city":"Allentown",
    "sg:classifiers":[
        {
            "category":"Health Services",
            "subcategory":"Doctor",
            "type":"Services"
        }
    ],
    "sg:phone":"+1 610 866 8076",
    "sg:postcode":"18104",
    "sg:province":"PA",
    "wof:name":"Stein Stanley MD",
    "wof:placetype":"venue"
},
  "geometry": {"coordinates":[-75.51840199999999,40.5994],"type":"Point"}
}