{
  "type": "Feature",
  "properties": {
    "addr:full":"3923 Walnut St Philadelphia PA 19104",
    "addr:housenumber":"3923",
    "addr:postcode":"19104",
    "addr:street":"Walnut St",
    "iso:country":"US",
    "sg:address":"3923 Walnut St",
    "sg:city":"Philadelphia",
    "sg:classifiers":[
        {
            "category":"Professional",
            "subcategory":"Printing & Photocopies",
            "type":"Services"
        }
    ],
    "sg:phone":"+1   ",
    "sg:postcode":"19104",
    "sg:province":"PA",
    "sg:tags":[
        "photocopying",
        "typesetting"
    ],
    "wof:name":"Kinkos",
    "wof:placetype":"venue"
},
  "geometry": {"coordinates":[-75.20217599999999,39.95412],"type":"Point"}
}