{
  "type": "Feature",
  "properties": {
    "iso:country":"US",
    "sg:address":"177 N Lime St",
    "sg:city":"Quarryville",
    "sg:classifiers":[
        {
            "category":"Building & Trades",
            "subcategory":"Construction",
            "type":"Services"
        }
    ],
    "sg:phone":"+1   ",
    "sg:postcode":"17566",
    "sg:province":"PA",
    "sg:tags":[
        "contractor"
    ],
    "wof:name":"Solanco Drywall Corp",
    "wof:placetype":"venue"
},
  "geometry": {"coordinates":[-76.159918,39.902751],"type":"Point"}
}