{
  "type": "Feature",
  "properties": {
    "iso:country":"US",
    "sg:address":"499 Frogtown Rd",
    "sg:city":"Pequea",
    "sg:classifiers":[
        {
            "category":"Building & Trades",
            "subcategory":"Construction",
            "type":"Services"
        }
    ],
    "sg:phone":"+1   ",
    "sg:postcode":"17565",
    "sg:province":"PA",
    "sg:tags":[
        "general",
        "contractor"
    ],
    "wof:name":"Stephen Rineer Builder Inc",
    "wof:placetype":"venue"
},
  "geometry": {"coordinates":[-76.31751,39.931887],"type":"Point"}
}