{
  "type": "Feature",
  "properties": {
    "iso:country":"US",
    "sg:address":"535 Smithfield St",
    "sg:city":"Pittsburgh",
    "sg:classifiers":[
        {
            "category":"Organizations",
            "subcategory":"Religious Organization",
            "type":"Services"
        }
    ],
    "sg:phone":"+1 412 281 6131",
    "sg:postcode":"15222",
    "sg:province":"PA",
    "sg:tags":[
        "church"
    ],
    "sg:website":"www.pgh.anglican.org",
    "wof:name":"Episcopal Diocese Pittsburgh",
    "wof:placetype":"venue"
},
  "geometry": {"coordinates":[-79.997843,40.4414],"type":"Point"}
}