{
  "type": "Feature",
  "properties": {
    "addr:full":"3612 River Rd Mount Bethel PA 18343",
    "addr:housenumber":"3612",
    "addr:postcode":"18343",
    "addr:street":"River Rd",
    "iso:country":"US",
    "sg:address":"3612 River Rd",
    "sg:city":"Mount Bethel",
    "sg:classifiers":[
        {
            "category":"Building & Trades",
            "subcategory":"Construction",
            "type":"Services"
        }
    ],
    "sg:phone":"+1   ",
    "sg:postcode":"18343",
    "sg:province":"PA",
    "sg:tags":[
        "excavating",
        "work",
        "demolition"
    ],
    "wof:name":"R E S Inc",
    "wof:placetype":"venue"
},
  "geometry": {"coordinates":[-75.067277,40.885547],"type":"Point"}
}