{
  "type": "Feature",
  "properties": {
    "addr:full":"417 Mingo Church Rd Finleyville PA 15332",
    "addr:housenumber":"417",
    "addr:postcode":"15332",
    "addr:street":"Mingo Church Rd",
    "iso:country":"US",
    "sg:address":"417 Mingo Church Rd",
    "sg:city":"Finleyville",
    "sg:classifiers":[
        {
            "category":"Building & Trades",
            "subcategory":"Construction",
            "type":"Services"
        }
    ],
    "sg:phone":"+1   ",
    "sg:postcode":"15332",
    "sg:province":"PA",
    "sg:tags":[
        "stone",
        "masonry",
        "work",
        "other"
    ],
    "wof:name":"Miller Brothers Masonry",
    "wof:placetype":"venue"
},
  "geometry": {"coordinates":[-80.007374,40.231546],"type":"Point"}
}