{
  "type": "Feature",
  "properties": {
    "addr:full":"501 Holmes Rd Morton PA 19070",
    "addr:housenumber":"501",
    "addr:postcode":"19070",
    "addr:street":"Holmes Rd",
    "iso:country":"US",
    "sg:address":"501 Holmes Rd",
    "sg:city":"Morton",
    "sg:classifiers":[
        {
            "category":"Real Estate",
            "subcategory":"Surveying",
            "type":"Services"
        }
    ],
    "sg:phone":"+1 610 532 4769",
    "sg:postcode":"19070",
    "sg:province":"PA",
    "sg:tags":[
        "surveyor",
        "land",
        "engineer"
    ],
    "sg:website":"http://www.ps.gen.nz",
    "wof:name":"Design Services",
    "wof:placetype":"venue"
},
  "geometry": {"coordinates":[-75.31242399999999,39.902149],"type":"Point"}
}