{
  "type": "Feature",
  "properties": {
    "iso:country":"US",
    "sg:address":"97 Main St",
    "sg:city":"Montandon",
    "sg:classifiers":[
        {
            "category":"Government",
            "subcategory":"Post Office",
            "type":"Public Place"
        }
    ],
    "sg:phone":"+1 570 524 9464",
    "sg:postcode":"17866",
    "sg:province":"PA",
    "wof:name":"US Post Office",
    "wof:placetype":"venue"
},
  "geometry": {"coordinates":[-76.52102499999999,40.787523],"type":"Point"}
}