{
  "type": "Feature",
  "properties": {
    "iso:country":"US",
    "sg:address":"5140 Arney Rd",
    "sg:city":"Harrisburg",
    "sg:classifiers":[
        {
            "category":"Wholesale",
            "subcategory":"Vending Machines",
            "type":"Manufacturing & Wholesale Goods"
        }
    ],
    "sg:phone":"+1   ",
    "sg:postcode":"17111",
    "sg:province":"PA",
    "sg:tags":[
        "operator"
    ],
    "wof:name":"Snacks 4u Vending",
    "wof:placetype":"venue"
},
  "geometry": {"coordinates":[-76.797495,40.266552],"type":"Point"}
}