{
  "type": "Feature",
  "properties": {
    "addr:full":"3625 Davisville Rd Hatboro PA 19040",
    "addr:housenumber":"3625",
    "addr:postcode":"19040",
    "addr:street":"Davisville Rd",
    "iso:country":"US",
    "sg:address":"3625 Davisville Rd",
    "sg:city":"Hatboro",
    "sg:classifiers":[
        {
            "category":"Autos & Motor Vehicles",
            "subcategory":"Automobile Sales",
            "type":"Retail Goods"
        }
    ],
    "sg:phone":"+1 215 675 6771",
    "sg:postcode":"19040",
    "sg:province":"PA",
    "sg:tags":[
        "car",
        "dealer"
    ],
    "wof:name":"Patanovich Auto Sales & Svc",
    "wof:placetype":"venue"
},
  "geometry": {"coordinates":[-75.090215,40.163167],"type":"Point"}
}