{
  "type": "Feature",
  "properties": {
    "iso:country":"US",
    "sg:address":"235 Jasper Rd",
    "sg:city":"King Of Prussia",
    "sg:classifiers":[
        {
            "category":"Building & Trades",
            "subcategory":"Landscaping Services",
            "type":"Services"
        }
    ],
    "sg:phone":"+1 610 265 8717",
    "sg:postcode":"19406",
    "sg:province":"PA",
    "wof:name":"Green Scene Landscaping",
    "wof:placetype":"venue"
},
  "geometry": {"coordinates":[-75.381626,40.108745],"type":"Point"}
}