{
  "type": "Feature",
  "properties": {
    "iso:country":"US",
    "sg:address":"27 Fraley St",
    "sg:city":"Kane",
    "sg:classifiers":[
        {
            "category":"Home & Garden",
            "subcategory":"Building Materials",
            "type":"Retail Goods"
        }
    ],
    "sg:phone":"+1 814 837 6558",
    "sg:postcode":"16735",
    "sg:province":"PA",
    "sg:tags":[
        "plumbing",
        "fixture",
        "supply"
    ],
    "wof:name":"Incredible Baths & More",
    "wof:placetype":"venue"
},
  "geometry": {"coordinates":[-78.81085400000001,41.653296],"type":"Point"}
}