{
  "type": "Feature",
  "properties": {
    "iso:country":"US",
    "sg:address":"704 Edward Ln",
    "sg:city":"West Chester",
    "sg:classifiers":[
        {
            "category":"Building & Trades",
            "subcategory":"Construction",
            "type":"Services"
        }
    ],
    "sg:phone":"+1   ",
    "sg:postcode":"19382",
    "sg:province":"PA",
    "sg:tags":[
        "residential",
        "general",
        "commercial",
        "contractor"
    ],
    "wof:name":"Stackhouse Construction",
    "wof:placetype":"venue"
},
  "geometry": {"coordinates":[-75.563878,39.957376],"type":"Point"}
}