{
  "type": "Feature",
  "properties": {
    "iso:country":"US",
    "sg:address":"356 N 1st St",
    "sg:city":"Jeannette",
    "sg:classifiers":[
        {
            "category":"Shopping",
            "subcategory":"Gifts & Souvenirs",
            "type":"Retail Goods"
        }
    ],
    "sg:phone":"+1 724 523 9411",
    "sg:postcode":"15644",
    "sg:province":"PA",
    "sg:tags":[
        "announcement",
        "invitation"
    ],
    "wof:name":"A J Press",
    "wof:placetype":"venue"
},
  "geometry": {"coordinates":[-79.607277,40.331659],"type":"Point"}
}