{
  "type": "Feature",
  "properties": {
    "iso:country":"US",
    "sg:address":"554 N Chester Rd",
    "sg:city":"West Chester",
    "sg:classifiers":[
        {
            "category":"Professional",
            "subcategory":"Engineering",
            "type":"Services"
        }
    ],
    "sg:phone":"+1 610 692 7650",
    "sg:postcode":"19380",
    "sg:province":"PA",
    "sg:tags":[
        "engineer"
    ],
    "wof:name":"Integrity Engineering Inc",
    "wof:placetype":"venue"
},
  "geometry": {"coordinates":[-75.54055700000001,39.982645],"type":"Point"}
}