{
  "type": "Feature",
  "properties": {
    "addr:full":"526 Duncan Station Rd Mckeesport PA 15135",
    "addr:housenumber":"526",
    "addr:postcode":"15135",
    "addr:street":"Duncan Station Rd",
    "iso:country":"US",
    "sg:address":"526 Duncan Station Rd",
    "sg:city":"Mckeesport",
    "sg:classifiers":[
        {
            "category":"Building & Trades",
            "subcategory":"Electrical",
            "type":"Services"
        }
    ],
    "sg:phone":"+1 412 754 0883",
    "sg:postcode":"15135",
    "sg:province":"PA",
    "sg:tags":[
        "electrical",
        "electric",
        "contractor"
    ],
    "wof:name":"Cindrich Electric",
    "wof:placetype":"venue"
},
  "geometry": {"coordinates":[-79.80431,40.286343],"type":"Point"}
}