{
  "type": "Feature",
  "properties": {
    "addr:full":"610 Beatty Rd Monroeville PA 15146",
    "addr:housenumber":"610",
    "addr:postcode":"15146",
    "addr:street":"Beatty Rd",
    "iso:country":"US",
    "sg:address":"610 Beatty Rd",
    "sg:city":"Monroeville",
    "sg:classifiers":[
        {
            "category":"Manufacturing",
            "subcategory":"Printing",
            "type":"Manufacturing & Wholesale Goods"
        }
    ],
    "sg:phone":"+1   ",
    "sg:postcode":"15146",
    "sg:province":"PA",
    "sg:tags":[
        "newspaper",
        "commercial",
        "publishing"
    ],
    "wof:name":"Trinity Holdings",
    "wof:placetype":"venue"
},
  "geometry": {"coordinates":[-79.75301,40.452087],"type":"Point"}
}