{
  "type": "Feature",
  "properties": {
    "addr:full":"440 Washington Ave Bridgeville PA 15017",
    "addr:housenumber":"440",
    "addr:postcode":"15017",
    "addr:street":"Washington Ave",
    "iso:country":"US",
    "sg:address":"440 Washington Ave",
    "sg:city":"Bridgeville",
    "sg:classifiers":[
        {
            "category":"Retail",
            "subcategory":"Animal Services",
            "type":"Services"
        }
    ],
    "sg:phone":"+1 412 221 5457",
    "sg:postcode":"15017",
    "sg:province":"PA",
    "sg:tags":[
        "pet",
        "boarding/pet",
        "sitting"
    ],
    "wof:name":"Furry Friends",
    "wof:placetype":"venue"
},
  "geometry": {"coordinates":[-80.11190000000001,40.359501],"type":"Point"}
}