{
  "type": "Feature",
  "properties": {
    "addr:full":"428 Forbes Ave Ste. 220 Pittsburgh PA 15219",
    "addr:housenumber":"428",
    "addr:postcode":"15219",
    "addr:street":"Forbes Ave Ste. 220",
    "iso:country":"US",
    "sg:address":"428 Forbes Ave Ste. 220",
    "sg:city":"Pittsburgh",
    "sg:classifiers":[
        {
            "category":"Professional",
            "subcategory":"Lawyer & Legal Services",
            "type":"Services"
        }
    ],
    "sg:phone":"+1 412 227 0964",
    "sg:postcode":"15219",
    "sg:province":"PA",
    "sg:tags":[
        "attorney",
        "criminal",
        "law"
    ],
    "wof:name":"Making Law Easy-James Brink",
    "wof:placetype":"venue"
},
  "geometry": {"coordinates":[-79.998172,40.438933],"type":"Point"}
}