{
  "type": "Feature",
  "properties": {
    "iso:country":"US",
    "sg:address":"952 Strasburg Rd",
    "sg:city":"Kinzers",
    "sg:classifiers":[
        {
            "category":"Wholesale",
            "subcategory":"Electrical",
            "type":"Manufacturing & Wholesale Goods"
        }
    ],
    "sg:phone":"+1   ",
    "sg:postcode":"17535",
    "sg:province":"PA",
    "sg:tags":[
        "equipment"
    ],
    "wof:name":"Star Lux Illumination",
    "wof:placetype":"venue"
},
  "geometry": {"coordinates":[-76.05668799999999,39.984864],"type":"Point"}
}