{
  "type": "Feature",
  "properties": {
    "iso:country":"US",
    "sg:address":"6520 Senator Ln",
    "sg:city":"Bensalem",
    "sg:classifiers":[
        {
            "category":"Shopping",
            "subcategory":"Discount & Variety Stores",
            "type":"Retail Goods"
        }
    ],
    "sg:phone":"+1 215 741 4243",
    "sg:postcode":"19020",
    "sg:province":"PA",
    "sg:tags":[
        "salvage",
        "surplus",
        "merchandise"
    ],
    "wof:name":"Unlimited Bargains",
    "wof:placetype":"venue"
},
  "geometry": {"coordinates":[-74.925775,40.147638],"type":"Point"}
}