{
  "type": "Feature",
  "properties": {
    "iso:country":"US",
    "sg:address":"20 Berry Ln",
    "sg:city":"Robesonia",
    "sg:classifiers":[
        {
            "category":"Farming",
            "subcategory":"Livestock Farm",
            "type":"Manufacturing & Wholesale Goods"
        }
    ],
    "sg:phone":"+1   ",
    "sg:postcode":"19540",
    "sg:province":"PA",
    "sg:tags":[
        "animal",
        "general"
    ],
    "wof:name":"Daniel M Goodyear",
    "wof:placetype":"venue"
},
  "geometry": {"coordinates":[-75.92413500000001,40.226366],"type":"Point"}
}