{
  "type": "Feature",
  "properties": {
    "iso:country":"US",
    "sg:address":"1481 Spencer Rd",
    "sg:city":"Warminster",
    "sg:phone":"+1   ",
    "sg:postcode":"18974",
    "sg:province":"PA",
    "sg:tags":[
        "farm",
        "corn"
    ],
    "wof:name":"William Rook",
    "wof:placetype":"venue"
},
  "geometry": {"coordinates":[-75.02735800000001,40.241499],"type":"Point"}
}