{
  "type": "Feature",
  "properties": {
    "iso:country":"US",
    "sg:address":"1055 4th St",
    "sg:city":"Catasauqua",
    "sg:classifiers":[
        {
            "category":"Building & Trades",
            "subcategory":"Construction",
            "type":"Services"
        }
    ],
    "sg:phone":"+1 610 264 5520",
    "sg:postcode":"18032",
    "sg:province":"PA",
    "sg:tags":[
        "handyman"
    ],
    "wof:name":"O-Soo-Clean",
    "wof:placetype":"venue"
},
  "geometry": {"coordinates":[-75.47608,40.659331],"type":"Point"}
}