{
  "type": "Feature",
  "properties": {
    "iso:country":"US",
    "sg:address":"75 Camp Rd",
    "sg:city":"Valencia",
    "sg:classifiers":[
        {
            "category":"Travel",
            "subcategory":"Campground",
            "type":"Entertainment"
        }
    ],
    "sg:phone":"+1 724 625 1452",
    "sg:postcode":"16059",
    "sg:province":"PA",
    "sg:tags":[
        "camp"
    ],
    "wof:name":"Lillian Taylor Camp",
    "wof:placetype":"venue"
},
  "geometry": {"coordinates":[-79.989638,40.677365],"type":"Point"}
}