{
  "type": "Feature",
  "properties": {
    "iso:country":"US",
    "sg:address":"120 Ringneck Dr",
    "sg:city":"Harrisburg",
    "sg:classifiers":[
        {
            "category":"Professional",
            "subcategory":"Art Services",
            "type":"Services"
        }
    ],
    "sg:phone":"+1 717 213 9113",
    "sg:postcode":"17112",
    "sg:province":"PA",
    "sg:tags":[
        "graphic",
        "designer"
    ],
    "sg:website":"www.keisling.com",
    "wof:name":"Keisling Image & Design Inc",
    "wof:placetype":"venue"
},
  "geometry": {"coordinates":[-76.832976,40.332536],"type":"Point"}
}