{
  "type": "Feature",
  "properties": {
    "iso:country":"US",
    "sg:address":"715 Cliff Dr",
    "sg:city":"Lake Ariel",
    "sg:classifiers":[
        {
            "category":"Retail",
            "subcategory":"Repair Shop",
            "type":"Services"
        }
    ],
    "sg:phone":"+1 570 689 3237",
    "sg:postcode":"18436",
    "sg:province":"PA",
    "sg:tags":[
        "taxidermist"
    ],
    "sg:website":"www.mistymountainstudios.com",
    "wof:name":"Misty Mountain Taxidermy",
    "wof:placetype":"venue"
},
  "geometry": {"coordinates":[-75.498515,41.413184],"type":"Point"}
}