{
  "type": "Feature",
  "properties": {
    "iso:country":"US",
    "sg:address":"943 N 4th St",
    "sg:city":"Sunbury",
    "sg:classifiers":[
        {
            "category":"Autos & Motor Vehicles",
            "subcategory":"Automobile Sales",
            "type":"Retail Goods"
        }
    ],
    "sg:phone":"+1 570 284 3073",
    "sg:postcode":"17801",
    "sg:province":"PA",
    "sg:tags":[
        "car",
        "used"
    ],
    "sg:website":"http://www.sunburymotors.com",
    "wof:name":"Sunbury Motor Co",
    "wof:placetype":"venue"
},
  "geometry": {"coordinates":[-76.785563,40.871626],"type":"Point"}
}