{
  "type": "Feature",
  "properties": {
    "addr:full":"30 Melon Ln Reading PA 19606",
    "addr:housenumber":"30",
    "addr:postcode":"19606",
    "addr:street":"Melon Ln",
    "iso:country":"US",
    "sg:address":"30 Melon Ln",
    "sg:city":"Reading",
    "sg:classifiers":[
        {
            "category":"Mining & Drilling",
            "type":"Manufacturing & Wholesale Goods"
        }
    ],
    "sg:phone":"+1   ",
    "sg:postcode":"19606",
    "sg:province":"PA",
    "sg:tags":[
        "consulting",
        "management",
        "exploration"
    ],
    "wof:name":"I Need A Profit",
    "wof:placetype":"venue"
},
  "geometry": {"coordinates":[-75.88461,40.371794],"type":"Point"}
}