{
  "type": "Feature",
  "properties": {
    "addr:full":"1837 Chestnut St Lebanon PA 17042",
    "addr:housenumber":"1837",
    "addr:postcode":"17042",
    "addr:street":"Chestnut St",
    "iso:country":"US",
    "sg:address":"1837 Chestnut St",
    "sg:city":"Lebanon",
    "sg:classifiers":[
        {
            "category":"Professional",
            "subcategory":"Business Services",
            "type":"Services"
        }
    ],
    "sg:phone":"+1   ",
    "sg:postcode":"17042",
    "sg:province":"PA",
    "wof:name":"Chestnut Hill Townhouses",
    "wof:placetype":"venue"
},
  "geometry": {"coordinates":[-76.442543,40.336995],"type":"Point"}
}