{
  "type": "Feature",
  "properties": {
    "iso:country":"US",
    "sg:address":"1278 Rigley Rd",
    "sg:city":"Indiana",
    "sg:classifiers":[
        {
            "category":"Building & Trades",
            "subcategory":"Construction",
            "type":"Services"
        }
    ],
    "sg:phone":"+1 724 726 9026",
    "sg:postcode":"15774",
    "sg:province":"PA",
    "sg:tags":[
        "sewer",
        "contractor"
    ],
    "wof:name":"Marshall R Stout",
    "wof:placetype":"venue"
},
  "geometry": {"coordinates":[-79.254679,40.588849],"type":"Point"}
}