{
  "type": "Feature",
  "properties": {
    "iso:country":"US",
    "sg:address":"5976 Dogwood Dr",
    "sg:city":"New Tripoli",
    "sg:classifiers":[
        {
            "category":"Building & Trades",
            "subcategory":"Construction",
            "type":"Services"
        }
    ],
    "sg:phone":"+1   ",
    "sg:postcode":"18066",
    "sg:province":"PA",
    "sg:tags":[
        "general",
        "remodeling",
        "renovation",
        "contractor"
    ],
    "wof:name":"William G Ash Carpentry",
    "wof:placetype":"venue"
},
  "geometry": {"coordinates":[-75.71267,40.672087],"type":"Point"}
}