{
  "type": "Feature",
  "properties": {
    "iso:country":"US",
    "sg:address":"1 Brookhill Rd",
    "sg:city":"Sugarloaf",
    "sg:classifiers":[
        {
            "category":"Food & Beverages",
            "subcategory":"Groceries & Convenience Stores",
            "type":"Retail Goods"
        }
    ],
    "sg:phone":"+1   ",
    "sg:postcode":"18249",
    "sg:province":"PA",
    "sg:tags":[
        "station",
        "gas"
    ],
    "wof:name":"Turkey Hill 179",
    "wof:placetype":"venue"
},
  "geometry": {"coordinates":[-76.07176699999999,40.99384],"type":"Point"}
}