{
  "type": "Feature",
  "properties": {
    "iso:country":"US",
    "sg:address":"5648 Butler St",
    "sg:city":"Pittsburgh",
    "sg:classifiers":[
        {
            "category":"Retail",
            "subcategory":"Auto Repair",
            "type":"Services"
        }
    ],
    "sg:phone":"+1 412 784 9144",
    "sg:postcode":"15201",
    "sg:province":"PA",
    "sg:tags":[
        "repairing",
        "automobile",
        "truck"
    ],
    "wof:name":"T J's Auto & Truck Repair",
    "wof:placetype":"venue"
},
  "geometry": {"coordinates":[-79.94804999999999,40.484398],"type":"Point"}
}