{
  "type": "Feature",
  "properties": {
    "iso:country":"US",
    "sg:address":"415 Mahoning St",
    "sg:city":"Lehighton",
    "sg:classifiers":[
        {
            "category":"Professional",
            "subcategory":"Lawyer & Legal Services",
            "type":"Services"
        }
    ],
    "sg:phone":"+1 610 377 0500",
    "sg:postcode":"18235",
    "sg:province":"PA",
    "sg:tags":[
        "attorney"
    ],
    "wof:name":"Shutack & Lavelle",
    "wof:placetype":"venue"
},
  "geometry": {"coordinates":[-75.71402500000001,40.833833],"type":"Point"}
}