{
  "type": "Feature",
  "properties": {
    "addr:full":"7258 Castor Ave Philadelphia PA 19149",
    "addr:housenumber":"7258",
    "addr:postcode":"19149",
    "addr:street":"Castor Ave",
    "iso:country":"US",
    "sg:address":"7258 Castor Ave",
    "sg:city":"Philadelphia",
    "sg:classifiers":[
        {
            "category":"Health Services",
            "subcategory":"Dentist",
            "type":"Services"
        }
    ],
    "sg:phone":"+1 215 728 1144",
    "sg:postcode":"19149",
    "sg:province":"PA",
    "sg:tags":[
        "clinic",
        "dental",
        "dentists-cosmetic",
        "dentistry"
    ],
    "sg:website":"http://www.drseymourkovnat.com",
    "wof:name":"Kovnat, Seymour, Dds - Seymour Kovnat & Assoc",
    "wof:placetype":"venue"
},
  "geometry": {"coordinates":[-75.066509,40.050794],"type":"Point"}
}