{
  "type": "Feature",
  "properties": {
    "iso:country":"US",
    "sg:address":"1502 W Main St",
    "sg:city":"Collegeville",
    "sg:classifiers":[
        {
            "category":"Manufacturing",
            "subcategory":"Metals",
            "type":"Manufacturing & Wholesale Goods"
        },
        {
            "category":"Manufacturing",
            "subcategory":"Building Materials",
            "type":"Manufacturing & Wholesale Goods"
        }
    ],
    "sg:phone":"+1 610 489 4239",
    "sg:postcode":"19426",
    "sg:province":"PA",
    "sg:tags":[
        "fabricator",
        "work",
        "sheet"
    ],
    "wof:name":"Trappe Sheet Metal",
    "wof:placetype":"venue"
},
  "geometry": {"coordinates":[-75.484808,40.203533],"type":"Point"}
}