{
  "type": "Feature",
  "properties": {
    "iso:country":"US",
    "sg:address":"112 Rye Ct",
    "sg:city":"Mc Kees Rocks",
    "sg:classifiers":[
        {
            "category":"Retail",
            "subcategory":"Repair Shop",
            "type":"Services"
        }
    ],
    "sg:phone":"+1 412 331 1988",
    "sg:postcode":"15136",
    "sg:province":"PA",
    "sg:tags":[
        "contractor"
    ],
    "wof:name":"Tomaino Plumbing",
    "wof:placetype":"venue"
},
  "geometry": {"coordinates":[-80.109629,40.472321],"type":"Point"}
}