{
  "type": "Feature",
  "properties": {
    "iso:country":"US",
    "sg:address":"1227 Smith Township State Rd",
    "sg:city":"Burgettstown",
    "sg:classifiers":[
        {
            "category":"Health Services",
            "subcategory":"Doctor",
            "type":"Services"
        }
    ],
    "sg:phone":"+1   ",
    "sg:postcode":"15021",
    "sg:province":"PA",
    "sg:tags":[
        "dental",
        "clinic",
        "medical"
    ],
    "wof:name":"Community Med Ctr NW Wash Cnty",
    "wof:placetype":"venue"
},
  "geometry": {"coordinates":[-80.355075,40.321857],"type":"Point"}
}