{
  "type": "Feature",
  "properties": {
    "iso:country":"US",
    "sg:address":"766 E Pittsburgh St",
    "sg:city":"Greensburg",
    "sg:classifiers":[
        {
            "category":"Restaurant",
            "type":"Food & Drink"
        }
    ],
    "sg:phone":"+1 724 853 1824",
    "sg:postcode":"15601",
    "sg:province":"PA",
    "wof:name":"Cheyenne Food Svc",
    "wof:placetype":"venue"
},
  "geometry": {"coordinates":[-79.528068,40.302454],"type":"Point"}
}