{
  "type": "Feature",
  "properties": {
    "addr:full":"918 7th Ave Beaver Falls PA 15010",
    "addr:housenumber":"918",
    "addr:postcode":"15010",
    "addr:street":"7Th Ave",
    "iso:country":"US",
    "sg:address":"918 7th Ave",
    "sg:city":"Beaver Falls",
    "sg:classifiers":[
        {
            "category":"Organizations",
            "subcategory":"Religious Organization",
            "type":"Services"
        }
    ],
    "sg:phone":"+1 724 847 4177",
    "sg:postcode":"15010",
    "sg:province":"PA",
    "wof:name":"Prison Fellowship Ministries",
    "wof:placetype":"venue"
},
  "geometry": {"coordinates":[-80.319451,40.750827],"type":"Point"}
}