{
  "type": "Feature",
  "properties": {
    "iso:country":"US",
    "sg:address":"389 Pensinger Rd",
    "sg:city":"Greencastle",
    "sg:classifiers":[
        {
            "category":"Government",
            "subcategory":"Office",
            "type":"Public Place"
        }
    ],
    "sg:phone":"+1   ",
    "sg:postcode":"17225",
    "sg:province":"PA",
    "sg:tags":[
        "general"
    ],
    "wof:name":"Amsa 113",
    "wof:placetype":"venue"
},
  "geometry": {"coordinates":[-77.7239,39.749796],"type":"Point"}
}