{
  "type": "Feature",
  "properties": {
    "iso:country":"US",
    "sg:address":"6830 Sylvester St",
    "sg:city":"Philadelphia",
    "sg:classifiers":[
        {
            "category":"Utilities",
            "subcategory":"Mobile Phone",
            "type":"Services"
        },
        {
            "category":"Communications",
            "type":"Services"
        }
    ],
    "sg:phone":"+1 215 332 3834",
    "sg:postcode":"19149",
    "sg:province":"PA",
    "sg:tags":[
        "telephone",
        "cellular"
    ],
    "wof:name":"Links Communications",
    "wof:placetype":"venue"
},
  "geometry": {"coordinates":[-75.06786200000001,40.042322],"type":"Point"}
}