{
  "type": "Feature",
  "properties": {
    "iso:country":"US",
    "sg:address":"148 Rock Glen Rd",
    "sg:city":"Wynnewood",
    "sg:classifiers":[
        {
            "category":"Communications",
            "type":"Services"
        }
    ],
    "sg:phone":"+1 610 649 3159",
    "sg:postcode":"19096",
    "sg:province":"PA",
    "sg:tags":[
        "translator",
        "interpreter"
    ],
    "wof:name":"Multilingua Company",
    "wof:placetype":"venue"
},
  "geometry": {"coordinates":[-75.275026,39.983309],"type":"Point"}
}