{
  "type": "Feature",
  "properties": {
    "iso:country":"US",
    "sg:address":"727 Race St",
    "sg:city":"Waynesburg",
    "sg:classifiers":[
        {
            "category":"Professional",
            "type":"Services"
        }
    ],
    "sg:phone":"+1 724 852 2781",
    "sg:postcode":"15370",
    "sg:province":"PA",
    "sg:tags":[
        "establishment"
    ],
    "wof:name":"P A Protection & Advocacy",
    "wof:placetype":"venue"
},
  "geometry": {"coordinates":[-80.17775399999999,39.902551],"type":"Point"}
}