{
  "type": "Feature",
  "properties": {
    "iso:country":"US",
    "sg:address":"565 Gralan Dr",
    "sg:city":"Lancaster",
    "sg:classifiers":[
        {
            "category":"Professional",
            "subcategory":"Management & Consulting",
            "type":"Services"
        }
    ],
    "sg:phone":"+1 717 397 9003",
    "sg:postcode":"17601",
    "sg:province":"PA",
    "sg:tags":[
        "consultant",
        "lighting"
    ],
    "wof:name":"Illuminations Inc",
    "wof:placetype":"venue"
},
  "geometry": {"coordinates":[-76.256523,40.063844],"type":"Point"}
}