{
  "type": "Feature",
  "properties": {
    "iso:country":"US",
    "sg:address":"5932 N Broad St",
    "sg:city":"Philadelphia",
    "sg:classifiers":[
        {
            "category":"Government",
            "subcategory":"Court House",
            "type":"Public Place"
        }
    ],
    "sg:phone":"+1 215 686 3350",
    "sg:postcode":"19141",
    "sg:province":"PA",
    "sg:tags":[
        "department",
        "police"
    ],
    "sg:website":"http://www.phila.gov",
    "wof:name":"Police Dept-35th District",
    "wof:placetype":"venue"
},
  "geometry": {"coordinates":[-75.14376,40.043396],"type":"Point"}
}