{
  "type": "Feature",
  "properties": {
    "addr:full":"126 W Chester Pike Havertown PA 19083",
    "addr:housenumber":"126",
    "addr:postcode":"19083",
    "addr:street":"W Chester Pike",
    "iso:country":"US",
    "sg:address":"126 W Chester Pike",
    "sg:city":"Havertown",
    "sg:classifiers":[
        {
            "category":"Building & Trades",
            "subcategory":"Construction",
            "type":"Services"
        }
    ],
    "sg:phone":"+1 610 449 5966",
    "sg:postcode":"19083",
    "sg:province":"PA",
    "sg:tags":[
        "roofing",
        "contractor"
    ],
    "wof:name":"Suburban Roofing & Siding",
    "wof:placetype":"venue"
},
  "geometry": {"coordinates":[-75.29608899999999,39.96863],"type":"Point"}
}