{
  "type": "Feature",
  "properties": {
    "iso:country":"US",
    "sg:address":"333 E City Ave Ste 300",
    "sg:city":"Bala Cynwyd",
    "sg:classifiers":[
        {
            "category":"Professional",
            "subcategory":"Employment Agencies",
            "type":"Services"
        }
    ],
    "sg:phone":"+1 610 667 8288",
    "sg:postcode":"19004",
    "sg:province":"PA",
    "wof:name":"Epstein J & Associates",
    "wof:placetype":"venue"
},
  "geometry": {"coordinates":[-75.220084,40.004382],"type":"Point"}
}