{
  "type": "Feature",
  "properties": {
    "iso:country":"US",
    "sg:address":"131 Wallace Ave",
    "sg:city":"Downingtown",
    "sg:classifiers":[
        {
            "category":"Home & Garden",
            "subcategory":"Carpets & Floor Coverings",
            "type":"Retail Goods"
        }
    ],
    "sg:phone":"+1 610 873 8380",
    "sg:postcode":"19335",
    "sg:province":"PA",
    "sg:tags":[
        "dealer",
        "rug"
    ],
    "wof:name":"Floor Works",
    "wof:placetype":"venue"
},
  "geometry": {"coordinates":[-75.704015,40.012536],"type":"Point"}
}