{
  "type": "Feature",
  "properties": {
    "iso:country":"US",
    "sg:address":"119 Fayette St",
    "sg:city":"Conshohocken",
    "sg:classifiers":[
        {
            "category":"Restaurant",
            "type":"Food & Drink"
        }
    ],
    "sg:phone":"+1 610 832 2114",
    "sg:postcode":"19428",
    "sg:province":"PA",
    "sg:tags":[
        "eating"
    ],
    "wof:name":"Maya Bella Restaurant",
    "wof:placetype":"venue"
},
  "geometry": {"coordinates":[-75.305497,40.074517],"type":"Point"}
}