{
  "type": "Feature",
  "properties": {
    "addr:full":"4397 Twin Oaks Dr Murrysville PA 15668",
    "addr:housenumber":"4397",
    "addr:postcode":"15668",
    "addr:street":"Twin Oaks Dr",
    "iso:country":"US",
    "sg:address":"4397 Twin Oaks Dr",
    "sg:city":"Murrysville",
    "sg:classifiers":[
        {
            "category":"Local Transit",
            "type":"Transportation"
        }
    ],
    "sg:phone":"+1   ",
    "sg:postcode":"15668",
    "sg:province":"PA",
    "sg:tags":[
        "passenger"
    ],
    "wof:name":"Vintage Limo Services Inc",
    "wof:placetype":"venue"
},
  "geometry": {"coordinates":[-79.669465,40.461243],"type":"Point"}
}