{
  "type": "Feature",
  "properties": {
    "addr:full":"1733 Quincy Ave Scranton PA 18509",
    "addr:housenumber":"1733",
    "addr:postcode":"18509",
    "addr:street":"Quincy Ave",
    "iso:country":"US",
    "sg:address":"1733 Quincy Ave",
    "sg:city":"Scranton",
    "sg:classifiers":[
        {
            "category":"Restaurant",
            "type":"Food & Drink"
        }
    ],
    "sg:phone":"+1   ",
    "sg:postcode":"18509",
    "sg:province":"PA",
    "sg:tags":[
        "eating"
    ],
    "wof:name":"Battistas Cafe",
    "wof:placetype":"venue"
},
  "geometry": {"coordinates":[-75.635952,41.426046],"type":"Point"}
}