{
  "type": "Feature",
  "properties": {
    "iso:country":"US",
    "sg:address":"602 Dogwood Dr",
    "sg:city":"Downingtown",
    "sg:classifiers":[
        {
            "category":"Building & Trades",
            "subcategory":"Construction",
            "type":"Services"
        }
    ],
    "sg:phone":"+1 610 594 1605",
    "sg:postcode":"19335",
    "sg:province":"PA",
    "sg:tags":[
        "home",
        "builder"
    ],
    "wof:name":"Community Homes",
    "wof:placetype":"venue"
},
  "geometry": {"coordinates":[-75.64584499999999,40.005508],"type":"Point"}
}