{
  "type": "Feature",
  "properties": {
    "iso:country":"US",
    "sg:address":"41 Joseph St",
    "sg:city":"Dallas",
    "sg:classifiers":[
        {
            "category":"Communications",
            "subcategory":"Film & Video Production",
            "type":"Services"
        }
    ],
    "sg:phone":"+1   ",
    "sg:postcode":"18612",
    "sg:province":"PA",
    "sg:tags":[
        "motion",
        "picture"
    ],
    "wof:name":"Lindas Video Productions",
    "wof:placetype":"venue"
},
  "geometry": {"coordinates":[-75.964573,41.32639],"type":"Point"}
}