{
  "type": "Feature",
  "properties": {
    "iso:country":"US",
    "sg:address":"121 Welliver Dr",
    "sg:city":"Bloomsburg",
    "sg:classifiers":[
        {
            "category":"Freight",
            "type":"Transportation"
        }
    ],
    "sg:phone":"+1   ",
    "sg:postcode":"17815",
    "sg:province":"PA",
    "sg:tags":[
        "operator",
        "local",
        "trucking"
    ],
    "wof:name":"Gww Trucking",
    "wof:placetype":"venue"
},
  "geometry": {"coordinates":[-76.492366,40.982472],"type":"Point"}
}