{
  "type": "Feature",
  "properties": {
    "iso:country":"US",
    "sg:address":"231 Nutt Rd",
    "sg:city":"Phoenixville",
    "sg:classifiers":[
        {
            "category":"Professional",
            "subcategory":"Business Services",
            "type":"Services"
        }
    ],
    "sg:phone":"+1 610 917 8247",
    "sg:postcode":"19460",
    "sg:province":"PA",
    "sg:tags":[
        "license"
    ],
    "wof:name":"American Auto Tags & Notary",
    "wof:placetype":"venue"
},
  "geometry": {"coordinates":[-75.517815,40.125579],"type":"Point"}
}