{
  "type": "Feature",
  "properties": {
    "iso:country":"US",
    "sg:address":"816 Veterans Hwy",
    "sg:city":"Bristol",
    "sg:classifiers":[
        {
            "category":"Place Of Worship",
            "subcategory":"Church",
            "type":"Public Place"
        },
        {
            "category":"Place Of Worship",
            "type":"Public Place"
        }
    ],
    "sg:phone":"+1 215 788 2040",
    "sg:postcode":"19007",
    "sg:province":"PA",
    "sg:tags":[
        "churches-non-denominational",
        "christ",
        "churches-community"
    ],
    "wof:name":"Christ Faith Christn Cmnty Ch",
    "wof:placetype":"venue"
},
  "geometry": {"coordinates":[-74.87633,40.10549],"type":"Point"}
}