{
  "type": "Feature",
  "properties": {
    "iso:country":"US",
    "sg:address":"1009 Mifflin St",
    "sg:city":"Huntingdon",
    "sg:classifiers":[
        {
            "category":"Health Services",
            "subcategory":"Health Practitioner",
            "type":"Services"
        }
    ],
    "sg:phone":"+1   ",
    "sg:postcode":"16652",
    "sg:province":"PA",
    "wof:name":"Relaxation Station",
    "wof:placetype":"venue"
},
  "geometry": {"coordinates":[-78.016437,40.491018],"type":"Point"}
}