{
  "type": "Feature",
  "properties": {
    "iso:country":"US",
    "sg:address":"550 Broadway",
    "sg:city":"Bethlehem",
    "sg:classifiers":[
        {
            "category":"Food & Beverages",
            "subcategory":"Groceries & Convenience Stores",
            "type":"Retail Goods"
        }
    ],
    "sg:phone":"+1   ",
    "sg:postcode":"18015",
    "sg:province":"PA",
    "wof:name":"Rodriguez Mini Mart",
    "wof:placetype":"venue"
},
  "geometry": {"coordinates":[-75.385375,40.608725],"type":"Point"}
}