{
  "type": "Feature",
  "properties": {
    "iso:country":"US",
    "sg:address":"505 Sycamore St",
    "sg:city":"Punxsutawney",
    "sg:classifiers":[
        {
            "category":"Real Estate",
            "subcategory":"Real Estate Operator",
            "type":"Services"
        }
    ],
    "sg:phone":"+1 814 938 9482",
    "sg:postcode":"15767",
    "sg:province":"PA",
    "sg:tags":[
        "apartment"
    ],
    "wof:name":"Sycamore Apartments",
    "wof:placetype":"venue"
},
  "geometry": {"coordinates":[-78.97952600000001,40.950196],"type":"Point"}
}