{
  "type": "Feature",
  "properties": {
    "iso:country":"US",
    "sg:address":"2655 W Sterner St",
    "sg:city":"Philadelphia",
    "sg:classifiers":[
        {
            "category":"Banks & Credit Unions",
            "subcategory":"Bank",
            "type":"Services"
        }
    ],
    "sg:phone":"+1 215 227 1430",
    "sg:postcode":"19132",
    "sg:province":"PA",
    "sg:tags":[
        "machine",
        "teller",
        "automated"
    ],
    "wof:name":"Fast Cash Atm",
    "wof:placetype":"venue"
},
  "geometry": {"coordinates":[-75.174744,39.997085],"type":"Point"}
}