{
  "type": "Feature",
  "properties": {
    "addr:full":"107 W 4th St Williamsport PA 17701",
    "addr:housenumber":"107",
    "addr:postcode":"17701",
    "addr:street":"W 4Th St",
    "iso:country":"US",
    "sg:address":"107 W 4th St",
    "sg:city":"Williamsport",
    "sg:classifiers":[
        {
            "category":"Shopping",
            "subcategory":"Books",
            "type":"Retail Goods"
        }
    ],
    "sg:phone":"+1 570 326 5764",
    "sg:postcode":"17701",
    "sg:province":"PA",
    "sg:tags":[
        "store"
    ],
    "wof:name":"Otto Book Store",
    "wof:placetype":"venue"
},
  "geometry": {"coordinates":[-77.003978,41.24129],"type":"Point"}
}