{
  "type": "Feature",
  "properties": {
    "addr:full":"3113 Main St Conestoga PA 17516",
    "addr:housenumber":"3113",
    "addr:postcode":"17516",
    "addr:street":"Main St",
    "iso:country":"US",
    "sg:address":"3113 Main St",
    "sg:city":"Conestoga",
    "sg:classifiers":[
        {
            "category":"Wholesale",
            "subcategory":"Machinery & Supplies",
            "type":"Manufacturing & Wholesale Goods"
        }
    ],
    "sg:phone":"+1   ",
    "sg:postcode":"17516",
    "sg:province":"PA",
    "sg:tags":[
        "equipment",
        "industrial"
    ],
    "wof:name":"Supreme Screen",
    "wof:placetype":"venue"
},
  "geometry": {"coordinates":[-76.33962699999999,39.943873],"type":"Point"}
}