{
  "type": "Feature",
  "properties": {
    "addr:full":"1600 Locust St Philadelphia PA 19103",
    "addr:housenumber":"1600",
    "addr:postcode":"19103",
    "addr:street":"Locust St",
    "iso:country":"US",
    "sg:address":"1600 Locust St",
    "sg:city":"Philadelphia",
    "sg:classifiers":[
        {
            "category":"Real Estate",
            "subcategory":"Real Estate Operator",
            "type":"Services"
        }
    ],
    "sg:phone":"+1 877 813 8426",
    "sg:postcode":"19103",
    "sg:province":"PA",
    "sg:tags":[
        "apartment"
    ],
    "sg:website":"www.scullycompany.com",
    "wof:name":"Scully Company",
    "wof:placetype":"venue"
},
  "geometry": {"coordinates":[-75.167773,39.948464],"type":"Point"}
}