{
  "type": "Feature",
  "properties": {
    "addr:full":"1726 Spruce St Philadelphia PA 19103",
    "addr:housenumber":"1726",
    "addr:postcode":"19103",
    "addr:street":"Spruce St",
    "iso:country":"US",
    "sg:address":"1726 Spruce St",
    "sg:city":"Philadelphia",
    "sg:classifiers":[
        {
            "category":"Professional",
            "subcategory":"Engineering",
            "type":"Services"
        }
    ],
    "sg:phone":"+1 215 735 8192",
    "sg:postcode":"19103",
    "sg:province":"PA",
    "sg:tags":[
        "consulting",
        "engineer"
    ],
    "wof:name":"Watermation Inc",
    "wof:placetype":"venue"
},
  "geometry": {"coordinates":[-75.17001500000001,39.947637],"type":"Point"}
}