{
  "type": "Feature",
  "properties": {
    "iso:country":"US",
    "sg:address":"603 Lewisville Rd",
    "sg:city":"Oxford",
    "sg:classifiers":[
        {
            "category":"Farming",
            "subcategory":"Farm",
            "type":"Manufacturing & Wholesale Goods"
        }
    ],
    "sg:phone":"+1   ",
    "sg:postcode":"19363",
    "sg:province":"PA",
    "sg:tags":[
        "crop",
        "general"
    ],
    "wof:name":"Farm",
    "wof:placetype":"venue"
},
  "geometry": {"coordinates":[-75.91651400000001,39.747338],"type":"Point"}
}