{
  "type": "Feature",
  "properties": {
    "iso:country":"US",
    "sg:address":"5116 Jonestown Rd",
    "sg:city":"Harrisburg",
    "sg:classifiers":[
        {
            "category":"Restaurant",
            "type":"Food & Drink"
        }
    ],
    "sg:phone":"+1 717 671 6924",
    "sg:postcode":"17112",
    "sg:province":"PA",
    "sg:tags":[
        "shop",
        "coffee",
        "eating"
    ],
    "wof:name":"Starbucks",
    "wof:placetype":"venue"
},
  "geometry": {"coordinates":[-76.799947,40.312995],"type":"Point"}
}