{
  "type": "Feature",
  "properties": {
    "iso:country":"US",
    "sg:address":"817 S 24th St",
    "sg:city":"Easton",
    "sg:classifiers":[
        {
            "category":"Wholesale",
            "subcategory":"Hardware",
            "type":"Manufacturing & Wholesale Goods"
        }
    ],
    "sg:phone":"+1   ",
    "sg:postcode":"18042",
    "sg:province":"PA",
    "wof:name":"M & M Sales Incorporated",
    "wof:placetype":"venue"
},
  "geometry": {"coordinates":[-75.2431,40.678975],"type":"Point"}
}