{
  "type": "Feature",
  "properties": {
    "addr:full":"1770 Lincoln Hwy E Lancaster PA 17602",
    "addr:housenumber":"1770",
    "addr:postcode":"17602",
    "addr:street":"Lincoln Hwy E",
    "iso:country":"US",
    "sg:address":"1770 Lincoln Hwy E",
    "sg:city":"Lancaster",
    "sg:classifiers":[
        {
            "category":"Professional",
            "subcategory":"Engineering",
            "type":"Services"
        }
    ],
    "sg:phone":"+1   ",
    "sg:postcode":"17602",
    "sg:province":"PA",
    "wof:name":"Ats",
    "wof:placetype":"venue"
},
  "geometry": {"coordinates":[-76.25842799999999,40.036604],"type":"Point"}
}