{
  "type": "Feature",
  "properties": {
    "iso:country":"US",
    "sg:address":"243 S Broad St",
    "sg:city":"Lititz",
    "sg:classifiers":[
        {
            "category":"Home & Garden",
            "subcategory":"Furniture",
            "type":"Retail Goods"
        }
    ],
    "sg:phone":"+1 717 625 1616",
    "sg:postcode":"17543",
    "sg:province":"PA",
    "sg:tags":[
        "store"
    ],
    "sg:website":"http://LuxuryLivingAuto.com",
    "wof:name":"Luxury Living Auto",
    "wof:placetype":"venue"
},
  "geometry": {"coordinates":[-76.307169,40.152543],"type":"Point"}
}