{
  "type": "Feature",
  "properties": {
    "iso:country":"US",
    "sg:address":"220 Mc Clelland Rd",
    "sg:city":"Mercer",
    "sg:classifiers":[
        {
            "category":"Building & Trades",
            "subcategory":"Construction",
            "type":"Services"
        }
    ],
    "sg:phone":"+1 724 748 3203",
    "sg:postcode":"16137",
    "sg:province":"PA",
    "sg:tags":[
        "home",
        "general",
        "remodeling",
        "improvement"
    ],
    "wof:name":"Mc Clelland Design & Remodel",
    "wof:placetype":"venue"
},
  "geometry": {"coordinates":[-80.17267099999999,41.185124],"type":"Point"}
}