{
  "type": "Feature",
  "properties": {
    "iso:country":"US",
    "sg:address":"2121 Shelly Dr Ste 3",
    "sg:city":"Indiana",
    "sg:classifiers":[
        {
            "category":"Health Services",
            "subcategory":"Dentist",
            "type":"Services"
        }
    ],
    "sg:phone":"+1 724 463 8050",
    "sg:postcode":"15701",
    "sg:province":"PA",
    "wof:name":"Petras, Brian G",
    "wof:placetype":"venue"
},
  "geometry": {"coordinates":[-79.189317,40.619713],"type":"Point"}
}