{
  "type": "Feature",
  "properties": {
    "iso:country":"US",
    "sg:address":"985 Manifold Rd",
    "sg:city":"Washington",
    "sg:classifiers":[
        {
            "category":"Education",
            "subcategory":"School",
            "type":"Public Place"
        }
    ],
    "sg:phone":"+1 724 250 6262",
    "sg:postcode":"15301",
    "sg:province":"PA",
    "wof:name":"Diabetes Education Management Program",
    "wof:placetype":"venue"
},
  "geometry": {"coordinates":[-80.213667,40.190692],"type":"Point"}
}