{
  "type": "Feature",
  "properties": {
    "iso:country":"US",
    "sg:address":"551 W Walnut Ln",
    "sg:city":"Philadelphia",
    "sg:classifiers":[
        {
            "category":"Social Services",
            "type":"Services"
        }
    ],
    "sg:phone":"+1   ",
    "sg:postcode":"19128",
    "sg:province":"PA",
    "wof:name":"Blind Relief Fund of Phila",
    "wof:placetype":"venue"
},
  "geometry": {"coordinates":[-75.208136,40.027372],"type":"Point"}
}