{
  "type": "Feature",
  "properties": {
    "addr:full":"600 E Manoa Rd Havertown PA 19083",
    "addr:housenumber":"600",
    "addr:postcode":"19083",
    "addr:street":"E Manoa Rd",
    "iso:country":"US",
    "sg:address":"600 E Manoa Rd",
    "sg:city":"Havertown",
    "sg:classifiers":[
        {
            "category":"Wholesale",
            "subcategory":"Machinery & Supplies",
            "type":"Manufacturing & Wholesale Goods"
        }
    ],
    "sg:phone":"+1 610 446 3400",
    "sg:postcode":"19083",
    "sg:province":"PA",
    "sg:tags":[
        "chemical",
        "plant",
        "representative",
        "manufacturer"
    ],
    "wof:name":"H Loeb & Son",
    "wof:placetype":"venue"
},
  "geometry": {"coordinates":[-75.28691499999999,39.980478],"type":"Point"}
}