{
  "type": "Feature",
  "properties": {
    "iso:country":"US",
    "sg:address":"767 W Newton Rd",
    "sg:city":"West Newton",
    "sg:classifiers":[
        {
            "category":"Food & Beverages",
            "subcategory":"Groceries & Convenience Stores",
            "type":"Retail Goods"
        }
    ],
    "sg:phone":"+1   ",
    "sg:postcode":"15089",
    "sg:province":"PA",
    "wof:name":"Marys Lunch & Groceries",
    "wof:placetype":"venue"
},
  "geometry": {"coordinates":[-79.71660900000001,40.230649],"type":"Point"}
}