{
  "type": "Feature",
  "properties": {
    "iso:country":"US",
    "sg:address":"118 Skyline Dr",
    "sg:city":"Mercer",
    "sg:classifiers":[
        {
            "category":"Insurance",
            "subcategory":"Insurance Agent",
            "type":"Services"
        }
    ],
    "sg:phone":"+1 724 662 5879",
    "sg:postcode":"16137",
    "sg:province":"PA",
    "wof:name":"Judith L Warner Insurance",
    "wof:placetype":"venue"
},
  "geometry": {"coordinates":[-80.280592,41.240509],"type":"Point"}
}