{
  "type": "Feature",
  "properties": {
    "iso:country":"US",
    "sg:address":"923 Mary St",
    "sg:city":"Williamsport",
    "sg:classifiers":[
        {
            "category":"Shopping",
            "subcategory":"Bicycles & Sporting Goods",
            "type":"Retail Goods"
        }
    ],
    "sg:phone":"+1   ",
    "sg:postcode":"17701",
    "sg:province":"PA",
    "wof:name":"Kieser Gun Shop & Repair",
    "wof:placetype":"venue"
},
  "geometry": {"coordinates":[-76.99655300000001,41.249823],"type":"Point"}
}