{
  "type": "Feature",
  "properties": {
    "iso:country":"US",
    "sg:address":"5140 Liberty Ave Ste 9",
    "sg:city":"Pittsburgh",
    "sg:classifiers":[
        {
            "category":"Health Services",
            "subcategory":"Doctor",
            "type":"Services"
        }
    ],
    "sg:phone":"+1 412 682 2100",
    "sg:postcode":"15224",
    "sg:province":"PA",
    "sg:tags":[
        "physician",
        "cardiology",
        "thoracic",
        "surgeons",
        "surgery",
        "surgeon",
        "cardiovascular"
    ],
    "sg:website":"http://www.wpcapc.com",
    "wof:name":"West Penn Cardiology Associates Pc",
    "wof:placetype":"venue"
},
  "geometry": {"coordinates":[-79.94227100000001,40.458054],"type":"Point"}
}