{
  "type": "Feature",
  "properties": {
    "iso:country":"US",
    "sg:address":"724 W Chocolate Ave",
    "sg:city":"Hershey",
    "sg:classifiers":[
        {
            "category":"Personal",
            "subcategory":"Beauty Salon",
            "type":"Services"
        }
    ],
    "sg:phone":"+1 717 534 9819",
    "sg:postcode":"17033",
    "sg:province":"PA",
    "sg:tags":[
        "shop"
    ],
    "wof:name":"Holiday Hair",
    "wof:placetype":"venue"
},
  "geometry": {"coordinates":[-76.664438,40.28021],"type":"Point"}
}