{
  "type": "Feature",
  "properties": {
    "iso:country":"US",
    "sg:address":"604 Gault Rd",
    "sg:city":"Gap",
    "sg:classifiers":[
        {
            "category":"Manufacturing",
            "subcategory":"Wood Products",
            "type":"Manufacturing & Wholesale Goods"
        }
    ],
    "sg:phone":"+1   ",
    "sg:postcode":"17527",
    "sg:province":"PA",
    "sg:tags":[
        "woodworking"
    ],
    "wof:name":"Welsh Mountain Woodworking",
    "wof:placetype":"venue"
},
  "geometry": {"coordinates":[-75.986327,40.073951],"type":"Point"}
}