{
  "type": "Feature",
  "properties": {
    "addr:full":"1523 7th Ave Beaver Falls PA 15010",
    "addr:housenumber":"1523",
    "addr:postcode":"15010",
    "addr:street":"7Th Ave",
    "iso:country":"US",
    "sg:address":"1523 7th Ave",
    "sg:city":"Beaver Falls",
    "sg:classifiers":[
        {
            "category":"Bars & Pubs",
            "type":"Food & Drink"
        }
    ],
    "sg:phone":"+1 724 843 5201",
    "sg:postcode":"15010",
    "sg:province":"PA",
    "sg:tags":[
        "drinking"
    ],
    "wof:name":"Corbins Tavern",
    "wof:placetype":"venue"
},
  "geometry": {"coordinates":[-80.31947599999999,40.75673],"type":"Point"}
}