{
  "type": "Feature",
  "properties": {
    "addr:full":"2009 Franklin Rd Washington Boro PA 17582",
    "addr:housenumber":"2009",
    "addr:postcode":"17582",
    "addr:street":"Franklin Rd",
    "iso:country":"US",
    "sg:address":"2009 Franklin Rd",
    "sg:city":"Washington Boro",
    "sg:classifiers":[
        {
            "category":"Building & Trades",
            "subcategory":"Construction",
            "type":"Services"
        }
    ],
    "sg:phone":"+1   ",
    "sg:postcode":"17582",
    "sg:province":"PA",
    "sg:tags":[
        "contractor"
    ],
    "wof:name":"Kautz Construction",
    "wof:placetype":"venue"
},
  "geometry": {"coordinates":[-76.463353,40.015975],"type":"Point"}
}