{
  "type": "Feature",
  "properties": {
    "iso:country":"US",
    "sg:address":"621 Kelly Blvd",
    "sg:city":"Slippery Rock",
    "sg:classifiers":[
        {
            "category":"Health Services",
            "subcategory":"Medical Lab",
            "type":"Services"
        }
    ],
    "sg:phone":"+1 724 794 9662",
    "sg:postcode":"16057",
    "sg:province":"PA",
    "sg:tags":[
        "laboratory"
    ],
    "wof:name":"United Community Outpatient",
    "wof:placetype":"venue"
},
  "geometry": {"coordinates":[-80.054182,41.071803],"type":"Point"}
}