{
  "type": "Feature",
  "properties": {
    "iso:country":"US",
    "sg:address":"1313 W Chester Rd",
    "sg:city":"West Chester",
    "sg:classifiers":[
        {
            "category":"Personal",
            "subcategory":"Beauty Salon",
            "type":"Services"
        }
    ],
    "sg:phone":"+1 610 430 3888",
    "sg:postcode":"19382",
    "sg:province":"PA",
    "sg:tags":[
        "manicuring"
    ],
    "wof:name":"Select Nails",
    "wof:placetype":"venue"
},
  "geometry": {"coordinates":[-75.547206,39.911214],"type":"Point"}
}