{
  "type": "Feature",
  "properties": {
    "iso:country":"US",
    "sg:address":"2345 Castor Ave",
    "sg:city":"Philadelphia",
    "sg:classifiers":[
        {
            "category":"Manufacturing",
            "subcategory":"Paper Products",
            "type":"Manufacturing & Wholesale Goods"
        }
    ],
    "sg:phone":"+1 215 289 8050",
    "sg:postcode":"19134",
    "sg:province":"PA",
    "sg:tags":[
        "box",
        "paperboard",
        "mill",
        "folding",
        "mfg"
    ],
    "wof:name":"Royal Pioneer Industries Inc",
    "wof:placetype":"venue"
},
  "geometry": {"coordinates":[-75.09481599999999,39.99518],"type":"Point"}
}