{
  "type": "Feature",
  "properties": {
    "iso:country":"US",
    "sg:address":"3 Penn Ctr W Ste 229",
    "sg:city":"Pittsburgh",
    "sg:classifiers":[
        {
            "category":"Social Services",
            "type":"Services"
        }
    ],
    "sg:phone":"+1 412 747 2680",
    "sg:postcode":"15276",
    "sg:province":"PA",
    "wof:name":"Variety The Children's Charity",
    "wof:placetype":"venue"
},
  "geometry": {"coordinates":[-80.125252,40.42704],"type":"Point"}
}