{
  "type": "Feature",
  "properties": {
    "iso:country":"US",
    "sg:address":"3344 Byberry Rd",
    "sg:city":"Philadelphia",
    "sg:classifiers":[
        {
            "category":"Real Estate",
            "subcategory":"Real Estate Operator",
            "type":"Services"
        }
    ],
    "sg:phone":"+1 215 824 3325",
    "sg:postcode":"19154",
    "sg:province":"PA",
    "sg:tags":[
        "building",
        "park",
        "nonresidential"
    ],
    "wof:name":"Deonarain Properties",
    "wof:placetype":"venue"
},
  "geometry": {"coordinates":[-74.976015,40.093752],"type":"Point"}
}