{
  "type": "Feature",
  "properties": {
    "addr:full":"128 Pottstown Pike Chester Springs PA 19425",
    "addr:housenumber":"128",
    "addr:postcode":"19425",
    "addr:street":"Pottstown Pike",
    "iso:country":"US",
    "sg:address":"128 Pottstown Pike",
    "sg:city":"Chester Springs",
    "sg:classifiers":[
        {
            "category":"Professional",
            "subcategory":"Management & Consulting",
            "type":"Services"
        }
    ],
    "sg:phone":"+1 610 458 0442",
    "sg:postcode":"19425",
    "sg:province":"PA",
    "sg:tags":[
        "consultant"
    ],
    "wof:name":"EFF Consulting Inc",
    "wof:placetype":"venue"
},
  "geometry": {"coordinates":[-75.68838599999999,40.078683],"type":"Point"}
}