{
  "type": "Feature",
  "properties": {
    "iso:country":"US",
    "sg:address":"5788 York Rd",
    "sg:city":"Buckingham",
    "sg:classifiers":[
        {
            "category":"Shopping",
            "subcategory":"Jewelry",
            "type":"Retail Goods"
        }
    ],
    "sg:phone":"+1 215 794 8950",
    "sg:postcode":"18912",
    "sg:province":"PA",
    "wof:name":"Silver Buyer Inc",
    "wof:placetype":"venue"
},
  "geometry": {"coordinates":[-75.03631,40.345838],"type":"Point"}
}