{
  "type": "Feature",
  "properties": {
    "addr:full":"555 5th St Exd Verona PA 15147",
    "addr:housenumber":"555",
    "addr:postcode":"15147",
    "addr:street":"5Th St Exd",
    "iso:country":"US",
    "sg:address":"555 5th St Exd",
    "sg:city":"Verona",
    "sg:classifiers":[
        {
            "category":"Professional",
            "type":"Services"
        }
    ],
    "sg:phone":"+1   ",
    "sg:postcode":"15147",
    "sg:province":"PA",
    "wof:name":"Jeffrey A Geraci",
    "wof:placetype":"venue"
},
  "geometry": {"coordinates":[-79.832054,40.503567],"type":"Point"}
}