{
  "type": "Feature",
  "properties": {
    "iso:country":"US",
    "sg:address":"850 Cranberry Woods Dr Ste 2241",
    "sg:city":"Cranberry Twp",
    "sg:classifiers":[
        {
            "category":"Education",
            "subcategory":"University",
            "type":"Public Place"
        }
    ],
    "sg:phone":"+1 724 741 2130",
    "sg:postcode":"16066",
    "sg:province":"PA",
    "sg:tags":[
        "college"
    ],
    "sg:website":"find.strayer.edu",
    "wof:name":"Strayer University",
    "wof:placetype":"venue"
},
  "geometry": {"coordinates":[-80.089073,40.674363],"type":"Point"}
}