{
  "type": "Feature",
  "properties": {
    "addr:full":"12 Robinson St Du Bois PA 15801",
    "addr:housenumber":"12",
    "addr:postcode":"15801",
    "addr:street":"Robinson St Du Bois",
    "iso:country":"US",
    "sg:address":"12 Robinson St",
    "sg:city":"Du Bois",
    "sg:classifiers":[
        {
            "category":"Banks & Credit Unions",
            "subcategory":"Bank",
            "type":"Services"
        }
    ],
    "sg:phone":"+1   ",
    "sg:postcode":"15801",
    "sg:province":"PA",
    "wof:name":"Brockway Press Fed Crdt Union",
    "wof:placetype":"venue"
},
  "geometry": {"coordinates":[-78.773527,41.12435],"type":"Point"}
}