{
  "type": "Feature",
  "properties": {
    "addr:full":"714 E Lawrence Ave Ellwood City PA 16117",
    "addr:housenumber":"714",
    "addr:postcode":"16117",
    "addr:street":"E Lawrence Ave",
    "iso:country":"US",
    "sg:address":"714 E Lawrence Ave",
    "sg:city":"Ellwood City",
    "sg:classifiers":[
        {
            "category":"Organizations",
            "subcategory":"Community Association",
            "type":"Services"
        }
    ],
    "sg:phone":"+1 724 758 5941",
    "sg:postcode":"16117",
    "sg:province":"PA",
    "sg:tags":[
        "club"
    ],
    "wof:name":"Eagles Club",
    "wof:placetype":"venue"
},
  "geometry": {"coordinates":[-80.290764,40.858527],"type":"Point"}
}