{
  "type": "Feature",
  "properties": {
    "iso:country":"US",
    "sg:address":"250 S 57th St",
    "sg:city":"Philadelphia",
    "sg:classifiers":[
        {
            "category":"Utilities",
            "subcategory":"Fuel Oil & Lpg",
            "type":"Services"
        }
    ],
    "sg:phone":"+1 215 474 9967",
    "sg:postcode":"19139",
    "sg:province":"PA",
    "sg:tags":[
        "oils-fuel"
    ],
    "wof:name":"Catherine Council",
    "wof:placetype":"venue"
},
  "geometry": {"coordinates":[-75.235776,39.956915],"type":"Point"}
}