{
  "type": "Feature",
  "properties": {
    "iso:country":"US",
    "sg:address":"542 W 20th St",
    "sg:city":"Hazleton",
    "sg:classifiers":[
        {
            "category":"Restaurant",
            "type":"Food & Drink"
        }
    ],
    "sg:phone":"+1 570 454 2361",
    "sg:postcode":"18201",
    "sg:province":"PA",
    "wof:name":"Zola's Italian House",
    "wof:placetype":"venue"
},
  "geometry": {"coordinates":[-75.983977,40.970238],"type":"Point"}
}