{
  "type": "Feature",
  "properties": {
    "iso:country":"US",
    "sg:address":"1630 Constitution Blvd",
    "sg:city":"Arnold",
    "sg:classifiers":[
        {
            "category":"Food & Beverages",
            "subcategory":"Bakery",
            "type":"Retail Goods"
        }
    ],
    "sg:phone":"+1 724 335 9376",
    "sg:postcode":"15068",
    "sg:province":"PA",
    "sg:tags":[
        "baker"
    ],
    "wof:name":"Mazziotti Bakery",
    "wof:placetype":"venue"
},
  "geometry": {"coordinates":[-79.766193,40.5754],"type":"Point"}
}