{
  "type": "Feature",
  "properties": {
    "iso:country":"US",
    "sg:address":"2200 Colorado St",
    "sg:city":"Philadelphia",
    "sg:classifiers":[
        {
            "category":"Building & Trades",
            "subcategory":"Construction",
            "type":"Services"
        }
    ],
    "sg:phone":"+1 215 416 0113",
    "sg:postcode":"19145",
    "sg:province":"PA",
    "sg:tags":[
        "contractor"
    ],
    "sg:website":"guiseppiwhite3.point2agent.com",
    "wof:name":"Elite Professional Painting & Construction",
    "wof:placetype":"venue"
},
  "geometry": {"coordinates":[-75.175299,39.923823],"type":"Point"}
}