{
  "type": "Feature",
  "properties": {
    "iso:country":"US",
    "sg:address":"2120 Freeport Rd",
    "sg:city":"New Kensington",
    "sg:classifiers":[
        {
            "category":"Real Estate",
            "subcategory":"Real Estate Agent",
            "type":"Services"
        }
    ],
    "sg:phone":"+1 724 335 1898",
    "sg:postcode":"15068",
    "sg:province":"PA",
    "wof:name":"Walley Agency Inc",
    "wof:placetype":"venue"
},
  "geometry": {"coordinates":[-79.757831,40.58358],"type":"Point"}
}