{
  "type": "Feature",
  "properties": {
    "addr:full":"152 Forest Hills Rd Pittsburgh PA 15221",
    "addr:housenumber":"152",
    "addr:postcode":"15221",
    "addr:street":"Forest Hills Rd",
    "iso:country":"US",
    "sg:address":"152 Forest Hills Rd",
    "sg:city":"Pittsburgh",
    "sg:classifiers":[
        {
            "category":"Personal",
            "subcategory":"Beauty Salon",
            "type":"Services"
        }
    ],
    "sg:phone":"+1   ",
    "sg:postcode":"15221",
    "sg:province":"PA",
    "sg:tags":[
        "shop"
    ],
    "wof:name":"1st Nail",
    "wof:placetype":"venue"
},
  "geometry": {"coordinates":[-79.86263099999999,40.434598],"type":"Point"}
}