{
  "type": "Feature",
  "properties": {
    "iso:country":"US",
    "sg:address":"1316 Harvard Ave",
    "sg:city":"Natrona Heights",
    "sg:classifiers":[
        {
            "category":"Insurance",
            "subcategory":"Insurance Agent",
            "type":"Services"
        }
    ],
    "sg:phone":"+1 724 224 8908",
    "sg:postcode":"15065",
    "sg:province":"PA",
    "wof:name":"New York Life Insurance Co",
    "wof:placetype":"venue"
},
  "geometry": {"coordinates":[-79.72304200000001,40.626901],"type":"Point"}
}