{
  "type": "Feature",
  "properties": {
    "iso:country":"US",
    "sg:address":"12 Little Swatara Church Rd",
    "sg:city":"Richland",
    "sg:classifiers":[
        {
            "category":"Professional",
            "type":"Services"
        }
    ],
    "sg:phone":"+1 717 933 4059",
    "sg:postcode":"17087",
    "sg:province":"PA",
    "sg:tags":[
        "establishment"
    ],
    "wof:name":"Bray & Bray",
    "wof:placetype":"venue"
},
  "geometry": {"coordinates":[-76.277486,40.449408],"type":"Point"}
}