{
  "type": "Feature",
  "properties": {
    "addr:full":"8 S Lake Dr Jim Thorpe PA 18229",
    "addr:housenumber":"8",
    "addr:postcode":"18229",
    "addr:street":"S Lake Dr Jim Thorpe",
    "iso:country":"US",
    "sg:address":"8 S Lake Dr",
    "sg:city":"Jim Thorpe",
    "sg:classifiers":[
        {
            "category":"Real Estate",
            "subcategory":"Real Estate Agent",
            "type":"Services"
        }
    ],
    "sg:phone":"+1 570 325 2074",
    "sg:postcode":"18229",
    "sg:province":"PA",
    "sg:tags":[
        "rental",
        "vacation"
    ],
    "wof:name":"Vacation Pocono",
    "wof:placetype":"venue"
},
  "geometry": {"coordinates":[-75.676557,40.928663],"type":"Point"}
}