{
  "type": "Feature",
  "properties": {
    "iso:country":"US",
    "sg:address":"1 Technology Park",
    "sg:city":"Harrisburg",
    "sg:classifiers":[
        {
            "category":"Professional",
            "subcategory":"Computer Services",
            "type":"Services"
        }
    ],
    "sg:phone":"+1   ",
    "sg:postcode":"17110",
    "sg:province":"PA",
    "sg:tags":[
        "site"
    ],
    "wof:name":"Commonwealth Technology Center",
    "wof:placetype":"venue"
},
  "geometry": {"coordinates":[-76.875264,40.291018],"type":"Point"}
}