{
  "type": "Feature",
  "properties": {
    "iso:country":"US",
    "sg:address":"1440 Evans City Rd",
    "sg:city":"Evans City",
    "sg:classifiers":[
        {
            "category":"Real Estate",
            "subcategory":"Real Estate Operator",
            "type":"Services"
        }
    ],
    "sg:phone":"+1   ",
    "sg:postcode":"16033",
    "sg:province":"PA",
    "sg:tags":[
        "property",
        "lessor"
    ],
    "wof:name":"Karen Marburger",
    "wof:placetype":"venue"
},
  "geometry": {"coordinates":[-80.02686,40.791893],"type":"Point"}
}