{
  "type": "Feature",
  "properties": {
    "iso:country":"US",
    "sg:address":"4344 Bedford Valley Rd",
    "sg:city":"Bedford",
    "sg:classifiers":[
        {
            "category":"Government",
            "subcategory":"Fire Station",
            "type":"Public Place"
        }
    ],
    "sg:phone":"+1 814 356 3544",
    "sg:postcode":"15522",
    "sg:province":"PA",
    "sg:tags":[
        "department"
    ],
    "wof:name":"Cumberland Valley Twp Fire Dpt",
    "wof:placetype":"venue"
},
  "geometry": {"coordinates":[-78.643941,39.83221],"type":"Point"}
}