{
  "type": "Feature",
  "properties": {
    "iso:country":"US",
    "sg:address":"610 Pittston Ave",
    "sg:city":"Scranton",
    "sg:classifiers":[
        {
            "category":"Wholesale",
            "subcategory":"Vending Machines",
            "type":"Manufacturing & Wholesale Goods"
        }
    ],
    "sg:phone":"+1 570 347 6976",
    "sg:postcode":"18505",
    "sg:province":"PA",
    "wof:name":"J & J Amusements",
    "wof:placetype":"venue"
},
  "geometry": {"coordinates":[-75.665753,41.398753],"type":"Point"}
}