{
  "type": "Feature",
  "properties": {
    "addr:full":"236 S Grandview Ave Pittsburgh PA 15205",
    "addr:housenumber":"236",
    "addr:postcode":"15205",
    "addr:street":"S Grandview Ave",
    "iso:country":"US",
    "sg:address":"236 S Grandview Ave",
    "sg:city":"Pittsburgh",
    "sg:classifiers":[
        {
            "category":"Shopping",
            "subcategory":"Computers & Home Electronics",
            "type":"Retail Goods"
        }
    ],
    "sg:phone":"+1   ",
    "sg:postcode":"15205",
    "sg:province":"PA",
    "wof:name":"Argenco Video Concepts",
    "wof:placetype":"venue"
},
  "geometry": {"coordinates":[-80.079015,40.427125],"type":"Point"}
}