{
  "type": "Feature",
  "properties": {
    "iso:country":"US",
    "sg:address":"4171 Rockdale Rd",
    "sg:city":"Greencastle",
    "sg:classifiers":[
        {
            "category":"Sports & Exercise",
            "subcategory":"Gym",
            "type":"Entertainment"
        }
    ],
    "sg:phone":"+1   ",
    "sg:postcode":"17225",
    "sg:province":"PA",
    "sg:tags":[
        "physical",
        "fitness"
    ],
    "wof:name":"Karen C Douglas",
    "wof:placetype":"venue"
},
  "geometry": {"coordinates":[-77.817505,39.868082],"type":"Point"}
}