{
  "type": "Feature",
  "properties": {
    "iso:country":"US",
    "sg:address":"4250 E Berlin Rd",
    "sg:city":"Thomasville",
    "sg:classifiers":[
        {
            "category":"Farming",
            "subcategory":"Farm",
            "type":"Manufacturing & Wholesale Goods"
        }
    ],
    "sg:phone":"+1 717 792 8832",
    "sg:postcode":"17364",
    "sg:province":"PA",
    "wof:name":"Gruver's Pine Farm",
    "wof:placetype":"venue"
},
  "geometry": {"coordinates":[-76.88456499999999,39.939367],"type":"Point"}
}