{
  "type": "Feature",
  "properties": {
    "iso:country":"US",
    "sg:address":"329 E Godfrey Ave",
    "sg:city":"Philadelphia",
    "sg:classifiers":[
        {
            "category":"Personal",
            "subcategory":"Beauty Salon",
            "type":"Services"
        }
    ],
    "sg:phone":"+1 215 924 9372",
    "sg:postcode":"19120",
    "sg:province":"PA",
    "wof:name":"Elizabeth A Beauty Salon",
    "wof:placetype":"venue"
},
  "geometry": {"coordinates":[-75.108587,40.042554],"type":"Point"}
}