{
  "type": "Feature",
  "properties": {
    "iso:country":"US",
    "sg:address":"620 Whitehall Rd",
    "sg:city":"Emlenton",
    "sg:classifiers":[
        {
            "category":"Manufacturing",
            "subcategory":"Lumber",
            "type":"Manufacturing & Wholesale Goods"
        }
    ],
    "sg:phone":"+1   ",
    "sg:postcode":"16373",
    "sg:province":"PA",
    "sg:tags":[
        "mill"
    ],
    "wof:name":"Hickman Lumber Co Inc",
    "wof:placetype":"venue"
},
  "geometry": {"coordinates":[-79.685064,41.192371],"type":"Point"}
}