{
  "type": "Feature",
  "properties": {
    "iso:country":"US",
    "sg:address":"1842 Delmar Dr",
    "sg:city":"Folcroft",
    "sg:classifiers":[
        {
            "category":"Retail",
            "subcategory":"Auto Rental",
            "type":"Services"
        }
    ],
    "sg:phone":"+1 610 532 9050",
    "sg:postcode":"19032",
    "sg:province":"PA",
    "sg:tags":[
        "renting",
        "automobile"
    ],
    "wof:name":"Hertz Rent A Car",
    "wof:placetype":"venue"
},
  "geometry": {"coordinates":[-75.280924,39.893416],"type":"Point"}
}