{
  "type": "Feature",
  "properties": {
    "addr:full":"810 Rural Ave Williamsport PA 17701",
    "addr:housenumber":"810",
    "addr:postcode":"17701",
    "addr:street":"Rural Ave",
    "iso:country":"US",
    "sg:address":"810 Rural Ave",
    "sg:city":"Williamsport",
    "sg:classifiers":[
        {
            "category":"Organizations",
            "subcategory":"Community Association",
            "type":"Services"
        }
    ],
    "sg:phone":"+1   ",
    "sg:postcode":"17701",
    "sg:province":"PA",
    "wof:name":"Pta Pennsylvania Congress",
    "wof:placetype":"venue"
},
  "geometry": {"coordinates":[-77.019144,41.247771],"type":"Point"}
}