{
  "type": "Feature",
  "properties": {
    "iso:country":"US",
    "sg:address":"770 W Chester Rd",
    "sg:city":"West Chester",
    "sg:classifiers":[
        {
            "category":"Retail",
            "subcategory":"Animal Services",
            "type":"Services"
        }
    ],
    "sg:phone":"+1   ",
    "sg:postcode":"19382",
    "sg:province":"PA",
    "wof:name":"Deerminders",
    "wof:placetype":"venue"
},
  "geometry": {"coordinates":[-75.545722,39.910876],"type":"Point"}
}