{
  "type": "Feature",
  "properties": {
    "iso:country":"US",
    "sg:address":"1873 Ridge Rd",
    "sg:city":"Homer City",
    "sg:classifiers":[
        {
            "category":"Retail",
            "subcategory":"Auto Repair",
            "type":"Services"
        }
    ],
    "sg:phone":"+1 814 446 6849",
    "sg:postcode":"15748",
    "sg:province":"PA",
    "sg:tags":[
        "body",
        "automobile",
        "painting"
    ],
    "wof:name":"Ridge Road Auto Body & Sales",
    "wof:placetype":"venue"
},
  "geometry": {"coordinates":[-78.995407,40.495037],"type":"Point"}
}