{
  "type": "Feature",
  "properties": {
    "iso:country":"US",
    "sg:address":"1443 Center Ave",
    "sg:city":"Feastervl Trvs",
    "sg:classifiers":[
        {
            "category":"Building & Trades",
            "subcategory":"Construction",
            "type":"Services"
        }
    ],
    "sg:phone":"+1 215 364 3704",
    "sg:postcode":"19053",
    "sg:province":"PA",
    "sg:tags":[
        "home",
        "improvement"
    ],
    "wof:name":"Pro Bath Refinishing & Rmdlng",
    "wof:placetype":"venue"
},
  "geometry": {"coordinates":[-74.989608,40.151885],"type":"Point"}
}