{
  "type": "Feature",
  "properties": {
    "addr:full":"3443 William Penn Ave Johnstown PA 15909",
    "addr:housenumber":"3443",
    "addr:postcode":"15909",
    "addr:street":"William Penn Ave",
    "iso:country":"US",
    "sg:address":"3443 William Penn Ave",
    "sg:city":"Johnstown",
    "sg:classifiers":[
        {
            "category":"Personal",
            "subcategory":"Beauty Salon",
            "type":"Services"
        }
    ],
    "sg:phone":"+1 814 322 4604",
    "sg:postcode":"15909",
    "sg:province":"PA",
    "wof:name":"Right Cut",
    "wof:placetype":"venue"
},
  "geometry": {"coordinates":[-78.850739,40.434763],"type":"Point"}
}