{
  "type": "Feature",
  "properties": {
    "iso:country":"US",
    "sg:address":"501 Cypress Ave",
    "sg:city":"Johnstown",
    "sg:classifiers":[
        {
            "category":"Building & Trades",
            "subcategory":"Construction",
            "type":"Services"
        }
    ],
    "sg:phone":"+1 814 539 3140",
    "sg:postcode":"15902",
    "sg:province":"PA",
    "sg:tags":[
        "floor",
        "laying",
        "contractor"
    ],
    "wof:name":"Allen Flooring",
    "wof:placetype":"venue"
},
  "geometry": {"coordinates":[-78.908469,40.296786],"type":"Point"}
}