{
  "type": "Feature",
  "properties": {
    "iso:country":"US",
    "sg:address":"420 S York Rd",
    "sg:city":"Hatboro",
    "sg:classifiers":[
        {
            "category":"Insurance",
            "subcategory":"Hazard Insurance",
            "type":"Services"
        }
    ],
    "sg:phone":"+1   ",
    "sg:postcode":"19040",
    "sg:province":"PA",
    "sg:tags":[
        "carrier",
        "legal"
    ],
    "wof:name":"Pennamerica",
    "wof:placetype":"venue"
},
  "geometry": {"coordinates":[-75.110615,40.169612],"type":"Point"}
}