{
  "type": "Feature",
  "properties": {
    "iso:country":"US",
    "sg:address":"570 S Loyalsock Ave",
    "sg:city":"Montoursville",
    "sg:classifiers":[
        {
            "category":"Government",
            "subcategory":"Police Station",
            "type":"Public Place"
        }
    ],
    "sg:phone":"+1 570 368 5712",
    "sg:postcode":"17754",
    "sg:province":"PA",
    "sg:tags":[
        "state"
    ],
    "wof:name":"Police Dept",
    "wof:placetype":"venue"
},
  "geometry": {"coordinates":[-76.927351,41.245524],"type":"Point"}
}