{
  "type": "Feature",
  "properties": {
    "addr:full":"213 N Main St Spring Grove PA 17362",
    "addr:housenumber":"213",
    "addr:postcode":"17362",
    "addr:street":"N Main St",
    "iso:country":"US",
    "sg:address":"213 N Main St",
    "sg:city":"Spring Grove",
    "sg:classifiers":[
        {
            "category":"Organizations",
            "subcategory":"Religious Organization",
            "type":"Services"
        }
    ],
    "sg:phone":"+1 717 225 0343",
    "sg:postcode":"17362",
    "sg:province":"PA",
    "sg:tags":[
        "church"
    ],
    "sg:website":"www.sgacma.org",
    "wof:name":"Spring Grove C & Ma CHURCH",
    "wof:placetype":"venue"
},
  "geometry": {"coordinates":[-76.865347,39.878273],"type":"Point"}
}