{
  "type": "Feature",
  "properties": {
    "addr:full":"1539 Linden St Cheswick PA 15024",
    "addr:housenumber":"1539",
    "addr:postcode":"15024",
    "addr:street":"Linden St",
    "iso:country":"US",
    "sg:address":"1539 Linden St",
    "sg:city":"Cheswick",
    "sg:classifiers":[
        {
            "category":"Shopping",
            "subcategory":"Computers & Home Electronics",
            "type":"Retail Goods"
        }
    ],
    "sg:phone":"+1 724 274 4460",
    "sg:postcode":"15024",
    "sg:province":"PA",
    "sg:tags":[
        "software"
    ],
    "wof:name":"JJN Technologies",
    "wof:placetype":"venue"
},
  "geometry": {"coordinates":[-79.7967,40.54485],"type":"Point"}
}