{
  "type": "Feature",
  "properties": {
    "addr:full":"4655 Buffalo Rd Erie PA 16510",
    "addr:housenumber":"4655",
    "addr:postcode":"16510",
    "addr:street":"Buffalo Rd",
    "iso:country":"US",
    "sg:address":"4655 Buffalo Rd",
    "sg:city":"Erie",
    "sg:classifiers":[
        {
            "category":"Retail",
            "subcategory":"Auto Repair",
            "type":"Services"
        }
    ],
    "sg:phone":"+1 814 899 2055",
    "sg:postcode":"16510",
    "sg:province":"PA",
    "sg:tags":[
        "wrecker"
    ],
    "wof:name":"Martin's Towing Svc",
    "wof:placetype":"venue"
},
  "geometry": {"coordinates":[-79.995572,42.149554],"type":"Point"}
}