{
  "type": "Feature",
  "properties": {
    "iso:country":"US",
    "sg:address":"77 Mechanics Ln",
    "sg:city":"Plymouth",
    "sg:classifiers":[
        {
            "category":"Insurance",
            "subcategory":"Hazard Insurance",
            "type":"Services"
        }
    ],
    "sg:phone":"+1 570 779 4823",
    "sg:postcode":"18651",
    "sg:province":"PA",
    "wof:name":"Kenneth Jackson",
    "wof:placetype":"venue"
},
  "geometry": {"coordinates":[-75.93961,41.244137],"type":"Point"}
}