{
  "type": "Feature",
  "properties": {
    "iso:country":"US",
    "sg:address":"104 Linden Ave",
    "sg:city":"Mercersburg",
    "sg:classifiers":[
        {
            "category":"Organizations",
            "subcategory":"Membership Organization",
            "type":"Services"
        }
    ],
    "sg:phone":"+1   ",
    "sg:postcode":"17236",
    "sg:province":"PA",
    "wof:name":"Livesay Historical Society",
    "wof:placetype":"venue"
},
  "geometry": {"coordinates":[-77.903639,39.82252],"type":"Point"}
}