{
  "type": "Feature",
  "properties": {
    "iso:country":"US",
    "sg:address":"3735 Nazareth Rd",
    "sg:city":"Easton",
    "sg:classifiers":[
        {
            "category":"Health Services",
            "subcategory":"Doctor",
            "type":"Services"
        }
    ],
    "sg:phone":"+1   ",
    "sg:postcode":"18045",
    "sg:province":"PA",
    "sg:tags":[
        "medical"
    ],
    "wof:name":"Northwood Eye Institute",
    "wof:placetype":"venue"
},
  "geometry": {"coordinates":[-75.282286,40.711994],"type":"Point"}
}