{
  "type": "Feature",
  "properties": {
    "iso:country":"US",
    "sg:address":"1516 Magnolia Dr",
    "sg:city":"Orefield",
    "sg:classifiers":[
        {
            "category":"Health Services",
            "subcategory":"Nursing And Care Facility",
            "type":"Services"
        }
    ],
    "sg:phone":"+1   ",
    "sg:postcode":"18069",
    "sg:province":"PA",
    "sg:tags":[
        "intermediate"
    ],
    "wof:name":"Lifepath Inc",
    "wof:placetype":"venue"
},
  "geometry": {"coordinates":[-75.594212,40.601106],"type":"Point"}
}