{
  "type": "Feature",
  "properties": {
    "addr:full":"49 Tookany Creek Pkwy Cheltenham PA 19012",
    "addr:housenumber":"49",
    "addr:postcode":"19012",
    "addr:street":"Tookany Creek Pkwy",
    "iso:country":"US",
    "sg:address":"49 Tookany Creek Pkwy",
    "sg:city":"Cheltenham",
    "sg:classifiers":[
        {
            "category":"Building & Trades",
            "subcategory":"Construction",
            "type":"Services"
        }
    ],
    "sg:phone":"+1 215 379 4833",
    "sg:postcode":"19012",
    "sg:province":"PA",
    "sg:tags":[
        "house",
        "special",
        "contractor"
    ],
    "wof:name":"Calmar Construction",
    "wof:placetype":"venue"
},
  "geometry": {"coordinates":[-75.101812,40.066355],"type":"Point"}
}