{
  "type": "Feature",
  "properties": {
    "addr:full":"609 Spring St Scottdale PA 15683",
    "addr:housenumber":"609",
    "addr:postcode":"15683",
    "addr:street":"Spring St",
    "iso:country":"US",
    "sg:address":"609 Spring St",
    "sg:city":"Scottdale",
    "sg:classifiers":[
        {
            "category":"Manufacturing",
            "subcategory":"Buildings",
            "type":"Manufacturing & Wholesale Goods"
        },
        {
            "category":"Building & Trades",
            "subcategory":"Construction",
            "type":"Services"
        }
    ],
    "sg:phone":"+1 724 806 0117",
    "sg:postcode":"15683",
    "sg:province":"PA",
    "sg:tags":[
        "home",
        "builder",
        "contractor"
    ],
    "wof:name":"Usborne Books At Home",
    "wof:placetype":"venue"
},
  "geometry": {"coordinates":[-79.58604,40.105825],"type":"Point"}
}