{
  "type": "Feature",
  "properties": {
    "iso:country":"US",
    "sg:address":"208 Hughes St",
    "sg:city":"Williamsport",
    "sg:classifiers":[
        {
            "category":"Manufacturing",
            "subcategory":"Watercraft",
            "type":"Manufacturing & Wholesale Goods"
        }
    ],
    "sg:phone":"+1   ",
    "sg:postcode":"17701",
    "sg:province":"PA",
    "sg:tags":[
        "building",
        "design",
        "sales"
    ],
    "wof:name":"Proof Sales",
    "wof:placetype":"venue"
},
  "geometry": {"coordinates":[-76.999244,41.248515],"type":"Point"}
}