{
  "type": "Feature",
  "properties": {
    "addr:full":"1012 Easton Rd Abington PA 19001",
    "addr:housenumber":"1012",
    "addr:postcode":"19001",
    "addr:street":"Easton Rd",
    "iso:country":"US",
    "sg:address":"1012 Easton Rd",
    "sg:city":"Abington",
    "sg:classifiers":[
        {
            "category":"Shopping",
            "subcategory":"Clothing, Apparel, & Fashions",
            "type":"Retail Goods"
        }
    ],
    "sg:phone":"+1   ",
    "sg:postcode":"19001",
    "sg:province":"PA",
    "wof:name":"Woodrow Cindy",
    "wof:placetype":"venue"
},
  "geometry": {"coordinates":[-75.13531,40.119127],"type":"Point"}
}