{
  "type": "Feature",
  "properties": {
    "iso:country":"US",
    "sg:address":"2956 Carpenters Park Rd",
    "sg:city":"Davidsville",
    "sg:classifiers":[
        {
            "category":"Building & Trades",
            "subcategory":"Landscaping Services",
            "type":"Services"
        }
    ],
    "sg:phone":"+1   ",
    "sg:postcode":"15928",
    "sg:province":"PA",
    "sg:tags":[
        "brokering"
    ],
    "wof:name":"Bxm Inc",
    "wof:placetype":"venue"
},
  "geometry": {"coordinates":[-78.91046900000001,40.252501],"type":"Point"}
}