{
  "type": "Feature",
  "properties": {
    "addr:full":"2366 Eldridge St Pittsburgh PA 15217",
    "addr:housenumber":"2366",
    "addr:postcode":"15217",
    "addr:street":"Eldridge St",
    "iso:country":"US",
    "sg:address":"2366 Eldridge St",
    "sg:city":"Pittsburgh",
    "sg:classifiers":[
        {
            "category":"Retail",
            "subcategory":"Auto Repair",
            "type":"Services"
        }
    ],
    "sg:phone":"+1 412 521 4600",
    "sg:postcode":"15217",
    "sg:province":"PA",
    "sg:tags":[
        "repairing",
        "automobile"
    ],
    "wof:name":"M & G Auto Svc",
    "wof:placetype":"venue"
},
  "geometry": {"coordinates":[-79.92253599999999,40.430851],"type":"Point"}
}