{
  "type": "Feature",
  "properties": {
    "iso:country":"US",
    "sg:address":"533 Ferndale Ave",
    "sg:city":"Johnstown",
    "sg:classifiers":[
        {
            "category":"Insurance",
            "subcategory":"Insurance Agent",
            "type":"Services"
        }
    ],
    "sg:phone":"+1   ",
    "sg:postcode":"15905",
    "sg:province":"PA",
    "wof:name":"Edward L Kavar Insurance Inc",
    "wof:placetype":"venue"
},
  "geometry": {"coordinates":[-78.915752,40.28948],"type":"Point"}
}