{
  "type": "Feature",
  "properties": {
    "iso:country":"US",
    "sg:address":"23 McMichael Rd",
    "sg:city":"Carnegie",
    "sg:classifiers":[
        {
            "category":"Retail",
            "subcategory":"Portrait Studio",
            "type":"Services"
        }
    ],
    "sg:phone":"+1 412 276 7544",
    "sg:postcode":"15106",
    "sg:province":"PA",
    "sg:tags":[
        "photographer"
    ],
    "wof:name":"Richard Guiliani",
    "wof:placetype":"venue"
},
  "geometry": {"coordinates":[-80.139758,40.402191],"type":"Point"}
}