{
  "type": "Feature",
  "properties": {
    "iso:country":"US",
    "sg:address":"102 Bonnybrook Rd",
    "sg:city":"Carlisle",
    "sg:classifiers":[
        {
            "category":"Mining & Drilling",
            "type":"Manufacturing & Wholesale Goods"
        }
    ],
    "sg:phone":"+1 717 249 5012",
    "sg:postcode":"17013",
    "sg:province":"PA",
    "sg:tags":[
        "stone"
    ],
    "sg:website":"www.unionquarries.com",
    "wof:name":"Union Quarries Inc",
    "wof:placetype":"venue"
},
  "geometry": {"coordinates":[-77.187744,40.177512],"type":"Point"}
}