{
  "type": "Feature",
  "properties": {
    "addr:full":"150 Rathton Rd York PA 17403",
    "addr:housenumber":"150",
    "addr:postcode":"17403",
    "addr:street":"Rathton Rd",
    "iso:country":"US",
    "sg:address":"150 Rathton Rd",
    "sg:city":"York",
    "sg:classifiers":[
        {
            "category":"Arena",
            "subcategory":"Sports Club",
            "type":"Entertainment"
        }
    ],
    "sg:phone":"+1 717 885 0195",
    "sg:postcode":"17403",
    "sg:province":"PA",
    "sg:tags":[
        "ticket",
        "sale"
    ],
    "wof:name":"Mycommunitytickets.Com",
    "wof:placetype":"venue"
},
  "geometry": {"coordinates":[-76.71360799999999,39.94754],"type":"Point"}
}