{
  "type": "Feature",
  "properties": {
    "iso:country":"US",
    "sg:address":"150 Rathton Rd",
    "sg:city":"York",
    "sg:classifiers":[
        {
            "category":"Arena",
            "subcategory":"Sports Club",
            "type":"Entertainment"
        }
    ],
    "sg:phone":"+1 717 885 0195",
    "sg:postcode":"17403",
    "sg:province":"PA",
    "sg:tags":[
        "ticket",
        "sale"
    ],
    "wof:name":"Mycommunitytickets.Com",
    "wof:placetype":"venue"
},
  "geometry": {"coordinates":[-76.713608,39.94754],"type":"Point"}
}