{
  "type": "Feature",
  "properties": {
    "iso:country":"US",
    "sg:address":"201 Kirkpatrick St",
    "sg:city":"Pittsburgh",
    "sg:classifiers":[
        {
            "category":"Real Estate",
            "subcategory":"Real Estate Agent",
            "type":"Services"
        }
    ],
    "sg:phone":"+1 412 456 5128",
    "sg:postcode":"15219",
    "sg:province":"PA",
    "sg:tags":[
        "authorities",
        "housing"
    ],
    "wof:name":"Pittsburgh Housing Authority",
    "wof:placetype":"venue"
},
  "geometry": {"coordinates":[-79.97394799999999,40.440854],"type":"Point"}
}