{
  "type": "Feature",
  "properties": {
    "iso:country":"US",
    "sg:address":"327 S Lehigh Ave",
    "sg:city":"Frackville",
    "sg:classifiers":[
        {
            "category":"Bars & Pubs",
            "type":"Food & Drink"
        }
    ],
    "sg:phone":"+1 570 874 2468",
    "sg:postcode":"17931",
    "sg:province":"PA",
    "wof:name":"Black Diamond Bar & Restaurant",
    "wof:placetype":"venue"
},
  "geometry": {"coordinates":[-76.22877699999999,40.780588],"type":"Point"}
}