{
  "type": "Feature",
  "properties": {
    "addr:full":"4777 Old Rte 8 Polk PA 16342",
    "addr:housenumber":"4777",
    "addr:postcode":"16342",
    "addr:street":"Old Rte 8 Polk",
    "iso:country":"US",
    "sg:address":"4777 Old Rte 8",
    "sg:city":"Polk",
    "sg:classifiers":[
        {
            "category":"Organizations",
            "subcategory":"Religious Organization",
            "type":"Services"
        }
    ],
    "sg:phone":"+1 814 437 5618",
    "sg:postcode":"16342",
    "sg:province":"PA",
    "sg:tags":[
        "church"
    ],
    "wof:name":"Baptist Temple Of Franklin",
    "wof:placetype":"venue"
},
  "geometry": {"coordinates":[-79.87291999999999,41.354317],"type":"Point"}
}