{
  "type": "Feature",
  "properties": {
    "addr:full":"901 N Bethlehem Pike Ambler PA 19002",
    "addr:housenumber":"901",
    "addr:postcode":"19002",
    "addr:street":"N Bethlehem Pike",
    "iso:country":"US",
    "sg:address":"901 N Bethlehem Pike",
    "sg:city":"Ambler",
    "sg:classifiers":[
        {
            "category":"Shopping",
            "type":"Retail Goods"
        }
    ],
    "sg:phone":"+1 215 643 4504",
    "sg:postcode":"19002",
    "sg:province":"PA",
    "sg:tags":[
        "craft",
        "gallery",
        "dealer"
    ],
    "wof:name":"Artisans Three Gallery",
    "wof:placetype":"venue"
},
  "geometry": {"coordinates":[-75.226716,40.181086],"type":"Point"}
}