{
  "type": "Feature",
  "properties": {
    "iso:country":"US",
    "sg:address":"1717 W Main St",
    "sg:city":"Stroudsburg",
    "sg:classifiers":[
        {
            "category":"Retail",
            "subcategory":"Auto Repair",
            "type":"Services"
        }
    ],
    "sg:phone":"+1   ",
    "sg:postcode":"18360",
    "sg:province":"PA",
    "sg:tags":[
        "automotive",
        "general"
    ],
    "wof:name":"J M P Unlimited",
    "wof:placetype":"venue"
},
  "geometry": {"coordinates":[-75.218182,40.982475],"type":"Point"}
}