{
  "type": "Feature",
  "properties": {
    "addr:full":"2400 W Master St Philadelphia PA 19121",
    "addr:housenumber":"2400",
    "addr:postcode":"19121",
    "addr:street":"W Master St",
    "iso:country":"US",
    "sg:address":"2400 W Master St",
    "sg:city":"Philadelphia",
    "sg:classifiers":[
        {
            "category":"Place Of Worship",
            "subcategory":"Church",
            "type":"Public Place"
        },
        {
            "category":"Place Of Worship",
            "type":"Public Place"
        }
    ],
    "sg:phone":"+1 215 765 3593",
    "sg:postcode":"19121",
    "sg:province":"PA",
    "sg:tags":[
        "churches-pentecostal-independent",
        "denomination",
        "churches-pentecostal",
        "churches-interdenominational",
        "churches-various"
    ],
    "wof:name":"Holy Bethel Church",
    "wof:placetype":"venue"
},
  "geometry": {"coordinates":[-75.175003,39.976589],"type":"Point"}
}