{
  "type": "Feature",
  "properties": {
    "iso:country":"US",
    "sg:address":"341 Shikellamy Ave",
    "sg:city":"Sunbury",
    "sg:classifiers":[
        {
            "category":"Restaurant",
            "type":"Food & Drink"
        }
    ],
    "sg:phone":"+1 570 286 2165",
    "sg:postcode":"17801",
    "sg:province":"PA",
    "wof:name":"Eat-A-Bite",
    "wof:placetype":"venue"
},
  "geometry": {"coordinates":[-76.78295,40.877822],"type":"Point"}
}