{
  "type": "Feature",
  "properties": {
    "addr:full":"1318 Baltimore St Hanover PA 17331",
    "addr:housenumber":"1318",
    "addr:postcode":"17331",
    "addr:street":"Baltimore St",
    "iso:country":"US",
    "sg:address":"1318 Baltimore St",
    "sg:city":"Hanover",
    "sg:classifiers":[
        {
            "category":"Shopping",
            "subcategory":"Gifts & Souvenirs",
            "type":"Retail Goods"
        }
    ],
    "sg:phone":"+1 717 630 2085",
    "sg:postcode":"17331",
    "sg:province":"PA",
    "sg:tags":[
        "shop"
    ],
    "wof:name":"Grandpa's Old Shanty",
    "wof:placetype":"venue"
},
  "geometry": {"coordinates":[-76.960267,39.774955],"type":"Point"}
}