{
  "type": "Feature",
  "properties": {
    "addr:full":"1 Quaker Village Shoppin Center Leetsdale PA 15056",
    "addr:housenumber":"1",
    "addr:postcode":"15056",
    "addr:street":"Quaker Village",
    "iso:country":"US",
    "sg:address":"1 Quaker Village Shoppin Center",
    "sg:city":"Leetsdale",
    "sg:classifiers":[
        {
            "category":"Personal",
            "subcategory":"Beauty Salon",
            "type":"Services"
        }
    ],
    "sg:phone":"+1 412 749 9939",
    "sg:postcode":"15056",
    "sg:province":"PA",
    "sg:tags":[
        "manicuring"
    ],
    "wof:name":"Nails 2000",
    "wof:placetype":"venue"
},
  "geometry": {"coordinates":[-80.20392,40.561206],"type":"Point"}
}