{
  "type": "Feature",
  "properties": {
    "iso:country":"US",
    "sg:address":"3041 Industry Dr",
    "sg:city":"Lancaster",
    "sg:classifiers":[
        {
            "category":"Freight",
            "type":"Transportation"
        }
    ],
    "sg:phone":"+1 717 393 9809",
    "sg:postcode":"17603",
    "sg:province":"PA",
    "sg:tags":[
        "trucking"
    ],
    "wof:name":"Ryder Integrated Logistics Inc",
    "wof:placetype":"venue"
},
  "geometry": {"coordinates":[-76.39066,40.043815],"type":"Point"}
}