{
  "type": "Feature",
  "properties": {
    "addr:full":"317 E Pleasant Valley Blvd Altoona PA 16602",
    "addr:housenumber":"317",
    "addr:postcode":"16602",
    "addr:street":"E Pleasant Valley Blvd",
    "iso:country":"US",
    "sg:address":"317 E Pleasant Valley Blvd",
    "sg:city":"Altoona",
    "sg:classifiers":[
        {
            "category":"Sports & Exercise",
            "subcategory":"Golf",
            "type":"Entertainment"
        }
    ],
    "sg:phone":"+1 814 941 2585",
    "sg:postcode":"16602",
    "sg:province":"PA",
    "sg:tags":[
        "instruction"
    ],
    "wof:name":"Deadsolid Golf",
    "wof:placetype":"venue"
},
  "geometry": {"coordinates":[-78.378128,40.5141],"type":"Point"}
}