{
  "type": "Feature",
  "properties": {
    "iso:country":"US",
    "sg:address":"451 W 4th St",
    "sg:city":"Mt Carmel",
    "sg:classifiers":[
        {
            "category":"Restaurant",
            "type":"Food & Drink"
        }
    ],
    "sg:phone":"+1 570 339 2310",
    "sg:postcode":"17851",
    "sg:province":"PA",
    "sg:website":"www.mattuccis.com",
    "wof:name":"Mattucci's Willow Cafe",
    "wof:placetype":"venue"
},
  "geometry": {"coordinates":[-76.419087,40.794807],"type":"Point"}
}