{
  "type": "Feature",
  "properties": {
    "iso:country":"US",
    "sg:address":"443 Fulton St",
    "sg:city":"Waverly",
    "sg:classifiers":[
        {
            "category":"Professional",
            "subcategory":"Lawyer & Legal Services",
            "type":"Services"
        }
    ],
    "sg:phone":"+1   ",
    "sg:postcode":"14892",
    "sg:province":"PA",
    "wof:name":"Keene Law Office",
    "wof:placetype":"venue"
},
  "geometry": {"coordinates":[-76.542438,42.003566],"type":"Point"}
}