{
  "type": "Feature",
  "properties": {
    "iso:country":"US",
    "sg:address":"130 Center St",
    "sg:city":"Ridgway",
    "sg:classifiers":[
        {
            "category":"Professional",
            "subcategory":"Management & Consulting",
            "type":"Services"
        },
        {
            "category":"Retail",
            "subcategory":"Funeral Services",
            "type":"Services"
        }
    ],
    "sg:phone":"+1 814 772 1821",
    "sg:postcode":"15853",
    "sg:province":"PA",
    "sg:tags":[
        "director",
        "consultant",
        "plans-pre-arranged",
        "embalmer",
        "supply"
    ],
    "wof:name":"Meehan Shilk Funeral Home Inc",
    "wof:placetype":"venue"
},
  "geometry": {"coordinates":[-78.731455,41.420047],"type":"Point"}
}