{
  "type": "Feature",
  "properties": {
    "iso:country":"US",
    "sg:address":"5961 Ridge Ave",
    "sg:city":"Philadelphia",
    "sg:classifiers":[
        {
            "category":"Autos & Motor Vehicles",
            "subcategory":"Auto Supplies",
            "type":"Retail Goods"
        }
    ],
    "sg:phone":"+1 215 483 3220",
    "sg:postcode":"19128",
    "sg:province":"PA",
    "sg:tags":[
        "tire"
    ],
    "wof:name":"Gabriel John Goodyear",
    "wof:placetype":"venue"
},
  "geometry": {"coordinates":[-75.21230300000001,40.030701],"type":"Point"}
}