{
  "type": "Feature",
  "properties": {
    "iso:country":"US",
    "sg:address":"1401 Lemon Drop Rd",
    "sg:city":"Ebensburg",
    "sg:classifiers":[
        {
            "category":"Manufacturing",
            "subcategory":"Pet Food",
            "type":"Manufacturing & Wholesale Goods"
        }
    ],
    "sg:phone":"+1 814 674 8069",
    "sg:postcode":"15931",
    "sg:province":"PA",
    "sg:tags":[
        "feed"
    ],
    "wof:name":"Western Pennsylvania Fur Farm",
    "wof:placetype":"venue"
},
  "geometry": {"coordinates":[-78.667511,40.551363],"type":"Point"}
}