{
  "type": "Feature",
  "properties": {
    "iso:country":"US",
    "sg:address":"203 W Main St",
    "sg:city":"Walnut Bottom",
    "sg:classifiers":[
        {
            "category":"Utilities",
            "subcategory":"Refuse",
            "type":"Services"
        }
    ],
    "sg:phone":"+1   ",
    "sg:postcode":"17266",
    "sg:province":"PA",
    "sg:tags":[
        "disposal",
        "rubbish",
        "collection"
    ],
    "wof:name":"Oye-Hauling",
    "wof:placetype":"venue"
},
  "geometry": {"coordinates":[-77.41006899999999,40.084727],"type":"Point"}
}