{
  "type": "Feature",
  "properties": {
    "addr:full":"100 Greenwood Ave Collegeville PA 19426",
    "addr:housenumber":"100",
    "addr:postcode":"19426",
    "addr:street":"Greenwood Ave",
    "iso:country":"US",
    "sg:address":"100 Greenwood Ave",
    "sg:city":"Collegeville",
    "sg:classifiers":[
        {
            "category":"Retail",
            "subcategory":"Repair Shop",
            "type":"Services"
        }
    ],
    "sg:phone":"+1 610 489 3900",
    "sg:postcode":"19426",
    "sg:province":"PA",
    "wof:name":"Gallery At Greenwood",
    "wof:placetype":"venue"
},
  "geometry": {"coordinates":[-75.485939,40.207343],"type":"Point"}
}