{
  "type": "Feature",
  "properties": {
    "iso:country":"US",
    "sg:address":"300 W STATION SQUARE DR",
    "sg:city":"PITTSBURGH",
    "sg:classifiers":[
        {
            "category":"Travel",
            "subcategory":"Hotels & Motels",
            "type":"Entertainment"
        },
        {
            "category":"Travel",
            "subcategory":"Resort",
            "type":"Entertainment"
        },
        {
            "category":"Sports & Exercise",
            "subcategory":"Ski Resort",
            "type":"Entertainment"
        }
    ],
    "sg:phone":"+1 651 209 3280",
    "sg:postcode":"15219",
    "sg:province":"PA",
    "sg:tags":[
        "corporate",
        "lodging"
    ],
    "sg:website":"http://clk.atdmt.com/NYC/go/156346466/direct/01/",
    "wof:name":"Sheraton St. Paul Woodbury Hotel",
    "wof:placetype":"venue"
},
  "geometry": {"coordinates":[-92.954246,44.940142],"type":"Point"}
}