{
  "type": "Feature",
  "properties": {
    "iso:country":"US",
    "sg:address":"1841 Buck Rd",
    "sg:city":"Feasterville Trevose",
    "sg:classifiers":[
        {
            "category":"Social Services",
            "type":"Services"
        }
    ],
    "sg:phone":"+1   ",
    "sg:postcode":"19053",
    "sg:province":"PA",
    "wof:name":"Cynthia Urban Thee",
    "wof:placetype":"venue"
},
  "geometry": {"coordinates":[-74.992926,40.163691],"type":"Point"}
}