{
  "type": "Feature",
  "properties": {
    "iso:country":"US",
    "sg:address":"25 Enck Dr",
    "sg:city":"Boiling Springs",
    "sg:classifiers":[
        {
            "category":"Health Services",
            "subcategory":"Clinic",
            "type":"Services"
        }
    ],
    "sg:phone":"+1 717 240 0878",
    "sg:postcode":"17007",
    "sg:province":"PA",
    "sg:tags":[
        "home"
    ],
    "wof:name":"Lakeview Home Health Svc",
    "wof:placetype":"venue"
},
  "geometry": {"coordinates":[-77.13472400000001,40.158743],"type":"Point"}
}