{
  "type": "Feature",
  "properties": {
    "iso:country":"US",
    "sg:address":"2 Fern Ridge Ct",
    "sg:city":"Shavertown",
    "sg:classifiers":[
        {
            "category":"Personal",
            "type":"Services"
        }
    ],
    "sg:phone":"+1   ",
    "sg:postcode":"18708",
    "sg:province":"PA",
    "sg:tags":[
        "party",
        "planning"
    ],
    "wof:name":"An Affair To Remember",
    "wof:placetype":"venue"
},
  "geometry": {"coordinates":[-75.924026,41.31094],"type":"Point"}
}