{
  "type": "Feature",
  "properties": {
    "iso:country":"US",
    "sg:address":"130 N Wales Rd",
    "sg:city":"North Wales",
    "sg:classifiers":[
        {
            "category":"Building & Trades",
            "subcategory":"Landscaping Services",
            "type":"Services"
        }
    ],
    "sg:phone":"+1 215 997 5528",
    "sg:postcode":"19454",
    "sg:province":"PA",
    "wof:name":"Gem Landscaping Inc",
    "wof:placetype":"venue"
},
  "geometry": {"coordinates":[-75.259337,40.231251],"type":"Point"}
}