{
  "type": "Feature",
  "properties": {
    "iso:country":"US",
    "sg:address":"3742 W 12th St",
    "sg:city":"Erie",
    "sg:classifiers":[
        {
            "category":"Shopping",
            "subcategory":"Department Store",
            "type":"Retail Goods"
        }
    ],
    "sg:phone":"+1 814 838 4097",
    "sg:postcode":"16505",
    "sg:province":"PA",
    "sg:tags":[
        "discount"
    ],
    "sg:website":"http://www.dollargeneral.com",
    "wof:name":"Dollar General",
    "wof:placetype":"venue"
},
  "geometry": {"coordinates":[-80.166056,42.092223],"type":"Point"}
}