{
  "type": "Feature",
  "properties": {
    "addr:full":"213 W 3rd Ave Warren PA 16365",
    "addr:housenumber":"213",
    "addr:postcode":"16365",
    "addr:street":"W 3Rd Ave",
    "iso:country":"US",
    "sg:address":"213 W 3rd Ave",
    "sg:city":"Warren",
    "sg:classifiers":[
        {
            "category":"Professional",
            "subcategory":"Lawyer & Legal Services",
            "type":"Services"
        }
    ],
    "sg:phone":"+1   ",
    "sg:postcode":"16365",
    "sg:province":"PA",
    "wof:name":"North Western Legal Services",
    "wof:placetype":"venue"
},
  "geometry": {"coordinates":[-79.145916,41.846537],"type":"Point"}
}