{
  "type": "Feature",
  "properties": {
    "iso:country":"US",
    "sg:address":"3907 Derry St",
    "sg:city":"Harrisburg",
    "sg:classifiers":[
        {
            "category":"Organizations",
            "subcategory":"Religious Organization",
            "type":"Services"
        }
    ],
    "sg:phone":"+1 717 558 8166",
    "sg:postcode":"17111",
    "sg:province":"PA",
    "sg:tags":[
        "church"
    ],
    "wof:name":"Central Penna United Meth Chr",
    "wof:placetype":"venue"
},
  "geometry": {"coordinates":[-76.818123,40.257589],"type":"Point"}
}