{
  "type": "Feature",
  "properties": {
    "iso:country":"US",
    "sg:address":"2020 Chestnut Hill Rd",
    "sg:city":"Mohnton",
    "sg:classifiers":[
        {
            "category":"Organizations",
            "subcategory":"Religious Organization",
            "type":"Services"
        }
    ],
    "sg:phone":"+1   ",
    "sg:postcode":"19540",
    "sg:province":"PA",
    "wof:name":"Saint Bndcts Rman Cthlic Chrch",
    "wof:placetype":"venue"
},
  "geometry": {"coordinates":[-75.91068199999999,40.206724],"type":"Point"}
}