{
  "type": "Feature",
  "properties": {
    "addr:full":"111 W Beaver St Mercer PA 16137",
    "addr:housenumber":"111",
    "addr:postcode":"16137",
    "addr:street":"W Beaver St",
    "iso:country":"US",
    "sg:address":"111 W Beaver St",
    "sg:city":"Mercer",
    "sg:classifiers":[
        {
            "category":"Insurance",
            "subcategory":"Hazard Insurance",
            "type":"Services"
        },
        {
            "category":"Insurance",
            "subcategory":"Insurance Agent",
            "type":"Services"
        },
        {
            "category":"Professional",
            "subcategory":"Lawyer & Legal Services",
            "type":"Services"
        },
        {
            "category":"Insurance",
            "subcategory":"Title Insurance",
            "type":"Services"
        }
    ],
    "sg:phone":"+1 724 662 4130",
    "sg:postcode":"16137",
    "sg:province":"PA",
    "sg:tags":[
        "attorney",
        "consultant",
        "homeowner",
        "motorcycle",
        "renter",
        "auto",
        "analyst"
    ],
    "sg:website":"http://www.Armstronginsurancemercer.com",
    "wof:name":"Armstrong Insurance Agency Inc",
    "wof:placetype":"venue"
},
  "geometry": {"coordinates":[-80.23988300000001,41.223728],"type":"Point"}
}