{
  "type": "Feature",
  "properties": {
    "addr:full":"71 S River St Wilkes Barre PA 18705",
    "addr:housenumber":"71",
    "addr:postcode":"18705",
    "addr:street":"S River St",
    "iso:country":"US",
    "sg:address":"71 S River St",
    "sg:city":"Wilkes Barre",
    "sg:classifiers":[
        {
            "category":"Autos & Motor Vehicles",
            "subcategory":"Automobile Sales",
            "type":"Retail Goods"
        }
    ],
    "sg:phone":"+1   ",
    "sg:postcode":"18705",
    "sg:province":"PA",
    "sg:tags":[
        "used"
    ],
    "wof:name":"Riverside Motors",
    "wof:placetype":"venue"
},
  "geometry": {"coordinates":[-75.85829,41.276088],"type":"Point"}
}