{
  "type": "Feature",
  "properties": {
    "addr:full":"409 Woodhaven Dr Monroeville PA 15146",
    "addr:housenumber":"409",
    "addr:postcode":"15146",
    "addr:street":"Woodhaven Dr",
    "iso:country":"US",
    "sg:address":"409 Woodhaven Dr",
    "sg:city":"Monroeville",
    "sg:classifiers":[
        {
            "category":"Organizations",
            "subcategory":"Community Association",
            "type":"Services"
        }
    ],
    "sg:phone":"+1   ",
    "sg:postcode":"15146",
    "sg:province":"PA",
    "wof:name":"Knights of Columbus",
    "wof:placetype":"venue"
},
  "geometry": {"coordinates":[-79.763412,40.451861],"type":"Point"}
}