{
  "type": "Feature",
  "properties": {
    "addr:full":"1590 N Center Ave Somerset PA 15501",
    "addr:housenumber":"1590",
    "addr:postcode":"15501",
    "addr:street":"N Center Ave",
    "iso:country":"US",
    "sg:address":"1590 N Center Ave",
    "sg:city":"Somerset",
    "sg:classifiers":[
        {
            "category":"Government",
            "subcategory":"Office",
            "type":"Public Place"
        }
    ],
    "sg:phone":"+1   ",
    "sg:postcode":"15501",
    "sg:province":"PA",
    "wof:name":"Natural Rsrces Cnservation Svc",
    "wof:placetype":"venue"
},
  "geometry": {"coordinates":[-79.075187,40.036007],"type":"Point"}
}