{
  "type": "Feature",
  "properties": {
    "addr:full":"45 Kline Village Harrisburg PA 17104",
    "addr:housenumber":"45",
    "addr:postcode":"17104",
    "addr:street":"Kline Village",
    "iso:country":"US",
    "sg:address":"45 Kline Village",
    "sg:city":"Harrisburg",
    "sg:classifiers":[
        {
            "category":"Restaurant",
            "type":"Food & Drink"
        }
    ],
    "sg:phone":"+1 717 233 5445",
    "sg:postcode":"17104",
    "sg:province":"PA",
    "wof:name":"New Plaza Diner",
    "wof:placetype":"venue"
},
  "geometry": {"coordinates":[-76.84452400000001,40.270936],"type":"Point"}
}