{
  "type": "Feature",
  "properties": {
    "iso:country":"US",
    "sg:address":"44 S 2nd St",
    "sg:city":"Philadelphia",
    "sg:classifiers":[
        {
            "category":"Personal",
            "subcategory":"Tattoo Parlor",
            "type":"Services"
        }
    ],
    "sg:phone":"+1 215 627 6271",
    "sg:postcode":"19106",
    "sg:province":"PA",
    "sg:tags":[
        "tattooing"
    ],
    "sg:website":"www.oldecitytattoo.com",
    "wof:name":"Olde City Tattoo",
    "wof:placetype":"venue"
},
  "geometry": {"coordinates":[-75.144096,39.948898],"type":"Point"}
}