{
  "type": "Feature",
  "properties": {
    "iso:country":"US",
    "sg:address":"330 Conestoga Rd",
    "sg:city":"Malvern",
    "sg:classifiers":[
        {
            "category":"Retail",
            "subcategory":"Veterinary Services",
            "type":"Services"
        }
    ],
    "sg:phone":"+1   ",
    "sg:postcode":"19355",
    "sg:province":"PA",
    "wof:name":"Springville Animal Hospital",
    "wof:placetype":"venue"
},
  "geometry": {"coordinates":[-75.570364,40.053683],"type":"Point"}
}