{
  "type": "Feature",
  "properties": {
    "iso:country":"US",
    "sg:address":"230 McWilliams Rd",
    "sg:city":"Bloomsburg",
    "sg:classifiers":[
        {
            "category":"Government",
            "subcategory":"Office",
            "type":"Public Place"
        }
    ],
    "sg:phone":"+1   ",
    "sg:postcode":"17815",
    "sg:province":"PA",
    "sg:tags":[
        "legislative",
        "body"
    ],
    "wof:name":"Mount Pleasant Township of",
    "wof:placetype":"venue"
},
  "geometry": {"coordinates":[-76.466742,41.063539],"type":"Point"}
}