{
  "type": "Feature",
  "properties": {
    "iso:country":"US",
    "sg:address":"1308 Irwin Dr",
    "sg:city":"Erie",
    "sg:classifiers":[
        {
            "category":"Manufacturing",
            "subcategory":"Printing",
            "type":"Manufacturing & Wholesale Goods"
        }
    ],
    "sg:phone":"+1 814 453 3016",
    "sg:postcode":"16505",
    "sg:province":"PA",
    "sg:tags":[
        "engraving",
        "laser"
    ],
    "wof:name":"Laser Engraving Inc",
    "wof:placetype":"venue"
},
  "geometry": {"coordinates":[-80.12253,42.104365],"type":"Point"}
}