{
  "type": "Feature",
  "properties": {
    "addr:full":"610 E Main St Waynesboro PA 17268",
    "addr:housenumber":"610",
    "addr:postcode":"17268",
    "addr:street":"E Main St",
    "iso:country":"US",
    "sg:address":"610 E Main St",
    "sg:city":"Waynesboro",
    "sg:phone":"+1 717 762 9410",
    "sg:postcode":"17268",
    "sg:province":"PA",
    "sg:website":"http://www.blockbuster.com",
    "wof:name":"Blockbuster Video",
    "wof:placetype":"venue"
},
  "geometry": {"coordinates":[-77.58967699999999,39.761009],"type":"Point"}
}