{
  "type": "Feature",
  "properties": {
    "iso:country":"US",
    "sg:address":"2499 Aramingo Ave",
    "sg:city":"Philadelphia",
    "sg:classifiers":[
        {
            "category":"Professional",
            "subcategory":"Lawyer & Legal Services",
            "type":"Services"
        }
    ],
    "sg:phone":"+1 215 425 5555",
    "sg:postcode":"19125",
    "sg:province":"PA",
    "sg:tags":[
        "attorney"
    ],
    "wof:name":"Dorian Goldstein Rochestie",
    "wof:placetype":"venue"
},
  "geometry": {"coordinates":[-75.119969,39.975911],"type":"Point"}
}