{
  "type": "Feature",
  "properties": {
    "iso:country":"US",
    "sg:address":"188 Keystone Dr",
    "sg:city":"Telford",
    "sg:classifiers":[
        {
            "category":"Wholesale",
            "subcategory":"Auto Parts",
            "type":"Manufacturing & Wholesale Goods"
        }
    ],
    "sg:phone":"+1 215 257 4650",
    "sg:postcode":"18969",
    "sg:province":"PA",
    "sg:tags":[
        "tire"
    ],
    "sg:website":"www.performancetireinc.com",
    "wof:name":"Performance Tire Inc",
    "wof:placetype":"venue"
},
  "geometry": {"coordinates":[-75.30740400000001,40.339802],"type":"Point"}
}