{
  "type": "Feature",
  "properties": {
    "iso:country":"US",
    "sg:address":"899 Cassatt Rd",
    "sg:city":"Berwyn",
    "sg:classifiers":[
        {
            "category":"Professional",
            "subcategory":"Management & Consulting",
            "type":"Services"
        }
    ],
    "sg:phone":"+1 484 321 5800",
    "sg:postcode":"19312",
    "sg:province":"PA",
    "sg:tags":[
        "employee",
        "consultant",
        "benefit"
    ],
    "wof:name":"Kistler Tiffany Benefits Co",
    "wof:placetype":"venue"
},
  "geometry": {"coordinates":[-75.460498,40.061893],"type":"Point"}
}