{
  "type": "Feature",
  "properties": {
    "iso:country":"US",
    "sg:address":"501 Centre St",
    "sg:city":"Freeland",
    "sg:classifiers":[
        {
            "category":"Shopping",
            "subcategory":"Discount & Variety Stores",
            "type":"Retail Goods"
        },
        {
            "category":"Shopping",
            "subcategory":"Bicycles & Sporting Goods",
            "type":"Retail Goods"
        }
    ],
    "sg:phone":"+1 570 636 2822",
    "sg:postcode":"18224",
    "sg:province":"PA",
    "wof:name":"Ed's Discount Corner",
    "wof:placetype":"venue"
},
  "geometry": {"coordinates":[-75.89747199999999,41.016934],"type":"Point"}
}