{
  "type": "Feature",
  "properties": {
    "addr:full":"881 2nd Street Pike Richboro PA 18954",
    "addr:housenumber":"881",
    "addr:postcode":"18954",
    "addr:street":"2Nd Street Pike",
    "iso:country":"US",
    "sg:address":"881 2nd Street Pike",
    "sg:city":"Richboro",
    "sg:classifiers":[
        {
            "category":"Retail",
            "subcategory":"Auto Repair",
            "type":"Services"
        }
    ],
    "sg:phone":"+1 215 355 6325",
    "sg:postcode":"18954",
    "sg:province":"PA",
    "sg:tags":[
        "repairing",
        "automobile",
        "general",
        "automotive"
    ],
    "wof:name":"Richboro Imported Car Service",
    "wof:placetype":"venue"
},
  "geometry": {"coordinates":[-75.012407,40.209936],"type":"Point"}
}