{
  "type": "Feature",
  "properties": {
    "iso:country":"US",
    "sg:address":"3400 Spruce St",
    "sg:city":"Philadelphia",
    "sg:classifiers":[
        {
            "category":"Health Services",
            "subcategory":"Doctor",
            "type":"Services"
        }
    ],
    "sg:phone":"+1 215 662 3436",
    "sg:postcode":"19104",
    "sg:province":"PA",
    "wof:name":"Bekeris Leonas G MD",
    "wof:placetype":"venue"
},
  "geometry": {"coordinates":[-75.192593,39.950304],"type":"Point"}
}