{
  "type": "Feature",
  "properties": {
    "iso:country":"US",
    "sg:address":"1300 N 52nd St",
    "sg:city":"Philadelphia",
    "sg:classifiers":[
        {
            "category":"Restaurant",
            "type":"Food & Drink"
        }
    ],
    "sg:phone":"+1 215 878 0146",
    "sg:postcode":"19131",
    "sg:province":"PA",
    "sg:tags":[
        "chinese"
    ],
    "wof:name":"ABC Chinese Food",
    "wof:placetype":"venue"
},
  "geometry": {"coordinates":[-75.225998,39.973099],"type":"Point"}
}