{
  "type": "Feature",
  "properties": {
    "iso:country":"US",
    "sg:address":"252 Plymouth Ave",
    "sg:city":"Wilkes Barre",
    "sg:classifiers":[
        {
            "category":"Organizations",
            "subcategory":"Community Association",
            "type":"Services"
        }
    ],
    "sg:phone":"+1   ",
    "sg:postcode":"18702",
    "sg:province":"PA",
    "wof:name":"Francisco Berucci Club The",
    "wof:placetype":"venue"
},
  "geometry": {"coordinates":[-75.918871,41.238812],"type":"Point"}
}