{
  "type": "Feature",
  "properties": {
    "iso:country":"US",
    "sg:address":"38 N 16th St",
    "sg:city":"Allentown",
    "sg:classifiers":[
        {
            "category":"Professional",
            "subcategory":"Lawyer & Legal Services",
            "type":"Services"
        }
    ],
    "sg:phone":"+1 610 432 6884",
    "sg:postcode":"18102",
    "sg:province":"PA",
    "sg:tags":[
        "attorney"
    ],
    "wof:name":"Richard S Kohn Law Offices",
    "wof:placetype":"venue"
},
  "geometry": {"coordinates":[-75.490813,40.598372],"type":"Point"}
}