{
  "type": "Feature",
  "properties": {
    "iso:country":"US",
    "sg:address":"901 Market St",
    "sg:city":"Philadelphia",
    "sg:classifiers":[
        {
            "category":"Shopping",
            "subcategory":"Gifts & Souvenirs",
            "type":"Retail Goods"
        }
    ],
    "sg:phone":"+1 215 925 9598",
    "sg:postcode":"19107",
    "sg:province":"PA",
    "sg:tags":[
        "shop"
    ],
    "wof:name":"Neils Hallmark Shop",
    "wof:placetype":"venue"
},
  "geometry": {"coordinates":[-75.156735,39.95153],"type":"Point"}
}