{
  "type": "Feature",
  "properties": {
    "iso:country":"US",
    "sg:address":"485 Mansfield Ave",
    "sg:city":"Pittsburgh",
    "sg:classifiers":[
        {
            "category":"Insurance",
            "subcategory":"Insurance Agent",
            "type":"Services"
        }
    ],
    "sg:phone":"+1 412 922 8222",
    "sg:postcode":"15220",
    "sg:province":"PA",
    "sg:website":"www.hurstweiss.com",
    "wof:name":"Hurst-Weiss Insurance",
    "wof:placetype":"venue"
},
  "geometry": {"coordinates":[-80.05418400000001,40.420198],"type":"Point"}
}