{
  "type": "Feature",
  "properties": {
    "iso:country":"US",
    "sg:address":"847 S Custer Ave",
    "sg:city":"New Holland",
    "sg:classifiers":[
        {
            "category":"Retail",
            "subcategory":"Auto Repair",
            "type":"Services"
        }
    ],
    "sg:phone":"+1 717 354 0989",
    "sg:postcode":"17557",
    "sg:province":"PA",
    "sg:tags":[
        "general"
    ],
    "wof:name":"Byers Garage",
    "wof:placetype":"venue"
},
  "geometry": {"coordinates":[-76.085038,40.073916],"type":"Point"}
}