{
  "type": "Feature",
  "properties": {
    "addr:full":"502 Race St Catasauqua PA 18032",
    "addr:housenumber":"502",
    "addr:postcode":"18032",
    "addr:street":"Race St",
    "iso:country":"US",
    "sg:address":"502 Race St",
    "sg:city":"Catasauqua",
    "sg:classifiers":[
        {
            "category":"Personal",
            "subcategory":"Barber",
            "type":"Services"
        }
    ],
    "sg:phone":"+1 610 264 4169",
    "sg:postcode":"18032",
    "sg:province":"PA",
    "wof:name":"Russ & Cathy's Barber Styling",
    "wof:placetype":"venue"
},
  "geometry": {"coordinates":[-75.460503,40.6521],"type":"Point"}
}