{
  "type": "Feature",
  "properties": {
    "addr:full":"452 Columbus St Wernersville PA 19565",
    "addr:housenumber":"452",
    "addr:postcode":"19565",
    "addr:street":"Columbus St",
    "iso:country":"US",
    "sg:address":"452 Columbus St",
    "sg:city":"Wernersville",
    "sg:classifiers":[
        {
            "category":"Professional",
            "type":"Services"
        }
    ],
    "sg:phone":"+1 610 670 2729",
    "sg:postcode":"19565",
    "sg:province":"PA",
    "sg:tags":[
        "writer"
    ],
    "wof:name":"Writers Block Inc",
    "wof:placetype":"venue"
},
  "geometry": {"coordinates":[-76.087671,40.325936],"type":"Point"}
}