{
  "type": "Feature",
  "properties": {
    "iso:country":"US",
    "sg:address":"537 Woodland Ave",
    "sg:city":"Cheltenham",
    "sg:classifiers":[
        {
            "category":"Manufacturing",
            "subcategory":"Tools & Machinery",
            "type":"Manufacturing & Wholesale Goods"
        },
        {
            "category":"Retail",
            "subcategory":"Repair Shop",
            "type":"Services"
        },
        {
            "category":"Retail",
            "subcategory":"Auto Repair",
            "type":"Services"
        }
    ],
    "sg:phone":"+1 215 379 6162",
    "sg:postcode":"19012",
    "sg:province":"PA",
    "sg:tags":[
        "machine",
        "automobile",
        "machinery-rebuild"
    ],
    "sg:website":"http://www.emilius.com",
    "wof:name":"Emilius, J A Sons",
    "wof:placetype":"venue"
},
  "geometry": {"coordinates":[-75.09310000000001,40.058722],"type":"Point"}
}