{
  "type": "Feature",
  "properties": {
    "addr:full":"1685 Route 228 Cranberry PA 16066",
    "addr:housenumber":"1685",
    "addr:postcode":"16066",
    "addr:street":"Route 228",
    "iso:country":"US",
    "sg:address":"1685 Route 228",
    "sg:city":"Cranberry",
    "sg:classifiers":[
        {
            "category":"Restaurant",
            "type":"Food & Drink"
        }
    ],
    "sg:menulink":"http://www.allmenus.com/pa/cranberry/84665-applebees/menu/",
    "sg:phone":"+1 724 742 8668",
    "sg:postcode":"16066",
    "sg:province":"PA",
    "sg:tags":[
        "burger",
        "american",
        "sandwich",
        "soup"
    ],
    "wof:name":"Applebee's",
    "wof:placetype":"venue"
},
  "geometry": {"coordinates":[-80.07185200000001,40.685397],"type":"Point"}
}