{
  "type": "Feature",
  "properties": {
    "iso:country":"US",
    "sg:address":"825 N Croton Ave",
    "sg:city":"New Castle",
    "sg:classifiers":[
        {
            "category":"Wholesale",
            "subcategory":"Machinery & Supplies",
            "type":"Manufacturing & Wholesale Goods"
        }
    ],
    "sg:phone":"+1 724 652 9620",
    "sg:postcode":"16101",
    "sg:province":"PA",
    "sg:tags":[
        "casket"
    ],
    "wof:name":"Milso Industries",
    "wof:placetype":"venue"
},
  "geometry": {"coordinates":[-80.32986099999999,41.006484],"type":"Point"}
}