{
  "type": "Feature",
  "properties": {
    "iso:country":"US",
    "sg:address":"1510 N Juniata St",
    "sg:city":"Hollidaysburg",
    "sg:classifiers":[
        {
            "category":"Government",
            "subcategory":"Police Station",
            "type":"Public Place"
        }
    ],
    "sg:phone":"+1 814 696 6100",
    "sg:postcode":"16648",
    "sg:province":"PA",
    "sg:tags":[
        "department"
    ],
    "wof:name":"State Police Pennsylvania",
    "wof:placetype":"venue"
},
  "geometry": {"coordinates":[-78.405903,40.435053],"type":"Point"}
}