{
  "type": "Feature",
  "properties": {
    "iso:country":"US",
    "sg:address":"364 Wilmington Pike",
    "sg:city":"Glen Mills",
    "sg:classifiers":[
        {
            "category":"Shopping",
            "subcategory":"Books",
            "type":"Retail Goods"
        }
    ],
    "sg:phone":"+1 610 558 2833",
    "sg:postcode":"19342",
    "sg:province":"PA",
    "sg:tags":[
        "bookstore"
    ],
    "wof:name":"Mustard Seed the",
    "wof:placetype":"venue"
},
  "geometry": {"coordinates":[-75.534897,39.8517],"type":"Point"}
}