{
  "type": "Feature",
  "properties": {
    "addr:full":"814 Ulster St # 830 Allentown PA 18109",
    "addr:housenumber":"814",
    "addr:postcode":"18109",
    "addr:street":"Ulster St # 830",
    "iso:country":"US",
    "sg:address":"814 Ulster St # 830",
    "sg:city":"Allentown",
    "sg:classifiers":[
        {
            "category":"Home & Garden",
            "subcategory":"Carpets & Floor Coverings",
            "type":"Retail Goods"
        }
    ],
    "sg:phone":"+1 610 435 1445",
    "sg:postcode":"18109",
    "sg:province":"PA",
    "sg:tags":[
        "carpeting"
    ],
    "wof:name":"Carpet Connection",
    "wof:placetype":"venue"
},
  "geometry": {"coordinates":[-75.424699,40.623145],"type":"Point"}
}