{
  "type": "Feature",
  "properties": {
    "iso:country":"US",
    "sg:address":"6439 Paschall Ave",
    "sg:city":"Philadelphia",
    "sg:classifiers":[
        {
            "category":"Building & Trades",
            "subcategory":"Construction",
            "type":"Services"
        }
    ],
    "sg:phone":"+1 215 729 1355",
    "sg:postcode":"19142",
    "sg:province":"PA",
    "sg:tags":[
        "builder",
        "church"
    ],
    "wof:name":"Guide One Taylor Ball",
    "wof:placetype":"venue"
},
  "geometry": {"coordinates":[-75.23280099999999,39.924953],"type":"Point"}
}