{
  "type": "Feature",
  "properties": {
    "iso:country":"US",
    "sg:address":"51 Wanner Rd",
    "sg:city":"Reading",
    "sg:classifiers":[
        {
            "category":"Building & Trades",
            "subcategory":"Construction",
            "type":"Services"
        }
    ],
    "sg:phone":"+1   ",
    "sg:postcode":"19606",
    "sg:province":"PA",
    "sg:tags":[
        "house"
    ],
    "wof:name":"Lewis R Tomlinson",
    "wof:placetype":"venue"
},
  "geometry": {"coordinates":[-75.87423099999999,40.367982],"type":"Point"}
}