{
  "type": "Feature",
  "properties": {
    "iso:country":"US",
    "sg:address":"150 Allendale Rd",
    "sg:city":"King Of Prussia",
    "sg:classifiers":[
        {
            "category":"Restaurant",
            "type":"Food & Drink"
        }
    ],
    "sg:menulink":"http://www.allmenus.com/pa/upper-merion/35040-melting-pot/menu/",
    "sg:phone":"+1 610 265 7195",
    "sg:postcode":"19406",
    "sg:province":"PA",
    "sg:tags":[
        "new",
        "american"
    ],
    "wof:name":"Melting Pot",
    "wof:placetype":"venue"
},
  "geometry": {"coordinates":[-75.382919,40.089805],"type":"Point"}
}