{
  "type": "Feature",
  "properties": {
    "addr:full":"2381 Oakdale Ave Glenside PA 19038",
    "addr:housenumber":"2381",
    "addr:postcode":"19038",
    "addr:street":"Oakdale Ave",
    "iso:country":"US",
    "sg:address":"2381 Oakdale Ave",
    "sg:city":"Glenside",
    "sg:classifiers":[
        {
            "category":"Wholesale",
            "subcategory":"Electrical",
            "type":"Manufacturing & Wholesale Goods"
        }
    ],
    "sg:phone":"+1 215 572 6220",
    "sg:postcode":"19038",
    "sg:province":"PA",
    "sg:tags":[
        "alarm",
        "burglar",
        "system"
    ],
    "wof:name":"Artuck Inc",
    "wof:placetype":"venue"
},
  "geometry": {"coordinates":[-75.150464,40.106993],"type":"Point"}
}