{
  "type": "Feature",
  "properties": {
    "addr:full":"329 14th St Ambridge PA 15003",
    "addr:housenumber":"329",
    "addr:postcode":"15003",
    "addr:street":"14Th St",
    "iso:country":"US",
    "sg:address":"329 14th St",
    "sg:city":"Ambridge",
    "sg:classifiers":[
        {
            "category":"Bars & Pubs",
            "type":"Food & Drink"
        }
    ],
    "sg:phone":"+1 724 266 6223",
    "sg:postcode":"15003",
    "sg:province":"PA",
    "sg:tags":[
        "drinking"
    ],
    "wof:name":"Metro",
    "wof:placetype":"venue"
},
  "geometry": {"coordinates":[-80.229327,40.596736],"type":"Point"}
}