{
  "type": "Feature",
  "properties": {
    "addr:full":"137 5th St Pittsburgh PA 15215",
    "addr:housenumber":"137",
    "addr:postcode":"15215",
    "addr:street":"5Th St",
    "iso:country":"US",
    "sg:address":"137 5th St",
    "sg:city":"Pittsburgh",
    "sg:classifiers":[
        {
            "category":"Building & Trades",
            "subcategory":"Construction",
            "type":"Services"
        }
    ],
    "sg:phone":"+1   ",
    "sg:postcode":"15215",
    "sg:province":"PA",
    "sg:tags":[
        "house"
    ],
    "wof:name":"We Group Inc",
    "wof:placetype":"venue"
},
  "geometry": {"coordinates":[-79.904455,40.493839],"type":"Point"}
}