{
  "type": "Feature",
  "properties": {
    "iso:country":"US",
    "sg:address":"219 E Beaver Ave",
    "sg:city":"State College",
    "sg:classifiers":[
        {
            "category":"Restaurant",
            "type":"Food & Drink"
        }
    ],
    "sg:menulink":"http://www.allmenus.com/pa/state-college/259865-canyon-wings/menu/",
    "sg:phone":"+1 814 237 6010",
    "sg:postcode":"16801",
    "sg:province":"PA",
    "sg:tags":[
        "american",
        "wing"
    ],
    "wof:name":"Canyon Wings",
    "wof:placetype":"venue"
},
  "geometry": {"coordinates":[-77.85852199999999,40.794906],"type":"Point"}
}