{
  "type": "Feature",
  "properties": {
    "iso:country":"US",
    "sg:address":"256 Bethel Rd",
    "sg:city":"Glen Mills",
    "sg:classifiers":[
        {
            "category":"Organizations",
            "subcategory":"Religious Organization",
            "type":"Services"
        }
    ],
    "sg:phone":"+1 610 358 2105",
    "sg:postcode":"19342",
    "sg:province":"PA",
    "sg:tags":[
        "church"
    ],
    "sg:website":"www.concordliberty.org",
    "wof:name":"Concord Liberty Presbyterian",
    "wof:placetype":"venue"
},
  "geometry": {"coordinates":[-75.507673,39.866907],"type":"Point"}
}