{
  "type": "Feature",
  "properties": {
    "iso:country":"US",
    "sg:address":"4337 Lancaster Ave",
    "sg:city":"Philadelphia",
    "sg:classifiers":[
        {
            "category":"Personal",
            "subcategory":"Barber",
            "type":"Services"
        }
    ],
    "sg:phone":"+1   ",
    "sg:postcode":"19104",
    "sg:province":"PA",
    "sg:tags":[
        "shop"
    ],
    "wof:name":"Als Barber Shop",
    "wof:placetype":"venue"
},
  "geometry": {"coordinates":[-75.210987,39.968568],"type":"Point"}
}