{
  "type": "Feature",
  "properties": {
    "iso:country":"US",
    "sg:address":"2 Mordansville Rd",
    "sg:city":"Bloomsburg",
    "sg:classifiers":[
        {
            "category":"Real Estate",
            "subcategory":"Real Estate Operator",
            "type":"Services"
        }
    ],
    "sg:phone":"+1   ",
    "sg:postcode":"17815",
    "sg:province":"PA",
    "sg:tags":[
        "property",
        "lessor"
    ],
    "wof:name":"Harry James",
    "wof:placetype":"venue"
},
  "geometry": {"coordinates":[-76.50008699999999,41.066962],"type":"Point"}
}