{
  "type": "Feature",
  "properties": {
    "iso:country":"US",
    "sg:address":"671 Youngs Rd",
    "sg:city":"Linden",
    "sg:classifiers":[
        {
            "category":"Manufacturing",
            "subcategory":"Leather Goods",
            "type":"Manufacturing & Wholesale Goods"
        }
    ],
    "sg:phone":"+1   ",
    "sg:postcode":"17744",
    "sg:province":"PA",
    "sg:tags":[
        "mfg"
    ],
    "wof:name":"Kathys Leather & Lace",
    "wof:placetype":"venue"
},
  "geometry": {"coordinates":[-77.17322299999999,41.214783],"type":"Point"}
}