{
  "type": "Feature",
  "properties": {
    "addr:full":"236 N Locust Point Rd Mechanicsburg PA 17050",
    "addr:housenumber":"236",
    "addr:postcode":"17050",
    "addr:street":"N Locust Point Rd",
    "iso:country":"US",
    "sg:address":"236 N Locust Point Rd",
    "sg:city":"Mechanicsburg",
    "sg:classifiers":[
        {
            "category":"Building & Trades",
            "subcategory":"Landscaping Services",
            "type":"Services"
        },
        {
            "category":"Home & Garden",
            "subcategory":"Building Materials",
            "type":"Retail Goods"
        },
        {
            "category":"Building & Trades",
            "subcategory":"Construction",
            "type":"Services"
        }
    ],
    "sg:phone":"+1 717 766 8760",
    "sg:postcode":"17050",
    "sg:province":"PA",
    "sg:tags":[
        "lawn",
        "deck",
        "builder",
        "contractor",
        "landscape",
        "maintenance",
        "gazebo",
        "patio"
    ],
    "sg:website":"http://www.outdoorexpressionslandscape.com",
    "wof:name":"Outdoor Expressions LLC",
    "wof:placetype":"venue"
},
  "geometry": {"coordinates":[-77.075536,40.225024],"type":"Point"}
}