{
  "type": "Feature",
  "properties": {
    "iso:country":"US",
    "sg:address":"5035 Peach St",
    "sg:city":"Erie",
    "sg:classifiers":[
        {
            "category":"Health Services",
            "subcategory":"Chiropractor",
            "type":"Services"
        }
    ],
    "sg:phone":"+1 814 459 1905",
    "sg:postcode":"16509",
    "sg:province":"PA",
    "wof:name":"Lake Erie Spine & Injury Ctr",
    "wof:placetype":"venue"
},
  "geometry": {"coordinates":[-80.09021300000001,42.08107],"type":"Point"}
}