{
  "type": "Feature",
  "properties": {
    "iso:country":"US",
    "sg:address":"16 Central Ave",
    "sg:city":"Oil City",
    "sg:classifiers":[
        {
            "category":"Organizations",
            "subcategory":"Religious Organization",
            "type":"Services"
        }
    ],
    "sg:phone":"+1 814 677 3023",
    "sg:postcode":"16301",
    "sg:province":"PA",
    "sg:tags":[
        "episcopalian",
        "church"
    ],
    "wof:name":"Christ Episcopal Church Inc",
    "wof:placetype":"venue"
},
  "geometry": {"coordinates":[-79.71101400000001,41.428722],"type":"Point"}
}