{
  "type": "Feature",
  "properties": {
    "iso:country":"US",
    "sg:address":"1108 Pennsylvania Ave",
    "sg:city":"Irwin",
    "sg:classifiers":[
        {
            "category":"Home & Garden",
            "subcategory":"Furniture",
            "type":"Retail Goods"
        }
    ],
    "sg:phone":"+1   ",
    "sg:postcode":"15642",
    "sg:province":"PA",
    "wof:name":"Db Furniture Sales",
    "wof:placetype":"venue"
},
  "geometry": {"coordinates":[-79.695947,40.32628],"type":"Point"}
}