{
  "type": "Feature",
  "properties": {
    "iso:country":"US",
    "sg:address":"555 Mercer Rd",
    "sg:city":"Greenville",
    "sg:classifiers":[
        {
            "category":"Restaurant",
            "type":"Food & Drink"
        }
    ],
    "sg:phone":"+1   ",
    "sg:postcode":"16125",
    "sg:province":"PA",
    "sg:tags":[
        "eating"
    ],
    "wof:name":"Lakeway Restaurant",
    "wof:placetype":"venue"
},
  "geometry": {"coordinates":[-80.357798,41.369359],"type":"Point"}
}