{
  "type": "Feature",
  "properties": {
    "addr:full":"1918 Kilmer Rd Manheim PA 17545",
    "addr:housenumber":"1918",
    "addr:postcode":"17545",
    "addr:street":"Kilmer Rd",
    "iso:country":"US",
    "sg:address":"1918 Kilmer Rd",
    "sg:city":"Manheim",
    "sg:classifiers":[
        {
            "category":"Building & Trades",
            "subcategory":"Construction",
            "type":"Services"
        }
    ],
    "sg:phone":"+1 717 665 6983",
    "sg:postcode":"17545",
    "sg:province":"PA",
    "sg:tags":[
        "plastering",
        "contractor"
    ],
    "wof:name":"M J Moyer Plastering & Drywlng",
    "wof:placetype":"venue"
},
  "geometry": {"coordinates":[-76.448958,40.183304],"type":"Point"}
}