{
  "type": "Feature",
  "properties": {
    "iso:country":"US",
    "sg:address":"110 Chestnut St",
    "sg:city":"Berwick",
    "sg:classifiers":[
        {
            "category":"Retail",
            "subcategory":"Funeral Services",
            "type":"Services"
        }
    ],
    "sg:phone":"+1 570 752 2759",
    "sg:postcode":"18603",
    "sg:province":"PA",
    "sg:tags":[
        "director",
        "crematory"
    ],
    "sg:website":"http://www.mayofh.com",
    "wof:name":"Mayo Funeral Home Inc",
    "wof:placetype":"venue"
},
  "geometry": {"coordinates":[-76.230158,41.056538],"type":"Point"}
}