{
  "type": "Feature",
  "properties": {
    "iso:country":"US",
    "sg:address":"81 S Main St",
    "sg:city":"Pittston",
    "sg:classifiers":[
        {
            "category":"Organizations",
            "subcategory":"Political Organization",
            "type":"Services"
        }
    ],
    "sg:phone":"+1 570 823 2711",
    "sg:postcode":"18640",
    "sg:province":"PA",
    "wof:name":"Raphael Musto Senator",
    "wof:placetype":"venue"
},
  "geometry": {"coordinates":[-75.791718,41.321102],"type":"Point"}
}