{
  "type": "Feature",
  "properties": {
    "addr:full":"2233 Royal Ave Williamsport PA 17701",
    "addr:housenumber":"2233",
    "addr:postcode":"17701",
    "addr:street":"Royal Ave",
    "iso:country":"US",
    "sg:address":"2233 Royal Ave",
    "sg:city":"Williamsport",
    "sg:classifiers":[
        {
            "category":"Retail",
            "subcategory":"Auto Repair",
            "type":"Services"
        }
    ],
    "sg:phone":"+1   ",
    "sg:postcode":"17701",
    "sg:province":"PA",
    "sg:tags":[
        "body",
        "general"
    ],
    "wof:name":"Cathermans Garage and Body Sp",
    "wof:placetype":"venue"
},
  "geometry": {"coordinates":[-77.054596,41.229715],"type":"Point"}
}