{
  "type": "Feature",
  "properties": {
    "iso:country":"US",
    "sg:address":"5338 Osage Ave",
    "sg:city":"Philadelphia",
    "sg:classifiers":[
        {
            "category":"Travel",
            "subcategory":"Travel Agent",
            "type":"Entertainment"
        }
    ],
    "sg:phone":"+1 215 260 9574",
    "sg:postcode":"19143",
    "sg:province":"PA",
    "sg:tags":[
        "agency",
        "services-commercial"
    ],
    "wof:name":"Anderson Travel/Triage Inc.",
    "wof:placetype":"venue"
},
  "geometry": {"coordinates":[-75.22900300000001,39.953325],"type":"Point"}
}