{
  "type": "Feature",
  "properties": {
    "addr:full":"901 University Dr State College PA 16801",
    "addr:housenumber":"901",
    "addr:postcode":"16801",
    "addr:street":"University Dr",
    "iso:country":"US",
    "sg:address":"901 University Dr",
    "sg:city":"State College",
    "sg:classifiers":[
        {
            "category":"Government",
            "subcategory":"Office",
            "type":"Public Place"
        }
    ],
    "sg:phone":"+1   ",
    "sg:postcode":"16801",
    "sg:province":"PA",
    "sg:tags":[
        "security",
        "social"
    ],
    "wof:name":"Social Security Administration",
    "wof:placetype":"venue"
},
  "geometry": {"coordinates":[-77.84405599999999,40.797191],"type":"Point"}
}