{
  "type": "Feature",
  "properties": {
    "iso:country":"US",
    "sg:address":"125 E Willow St",
    "sg:city":"Williamsport",
    "sg:classifiers":[
        {
            "category":"Health Services",
            "subcategory":"Nursing And Care Facility",
            "type":"Services"
        }
    ],
    "sg:phone":"+1 570 326 2566",
    "sg:postcode":"17701",
    "sg:province":"PA",
    "sg:tags":[
        "clinic",
        "welfare"
    ],
    "wof:name":"Saint Anthony's Free Medical Clinic",
    "wof:placetype":"venue"
},
  "geometry": {"coordinates":[-76.99935499999999,41.242783],"type":"Point"}
}