{
  "type": "Feature",
  "properties": {
    "iso:country":"US",
    "sg:address":"100 President Ave",
    "sg:city":"Morton",
    "sg:classifiers":[
        {
            "category":"Building & Trades",
            "subcategory":"Cleaning & Sanitation",
            "type":"Services"
        },
        {
            "category":"Professional",
            "subcategory":"Employment Agencies",
            "type":"Services"
        }
    ],
    "sg:phone":"+1 610 544 3073",
    "sg:postcode":"19070",
    "sg:province":"PA",
    "sg:tags":[
        "janitor",
        "help",
        "supply"
    ],
    "wof:name":"Metro Maids Inc",
    "wof:placetype":"venue"
},
  "geometry": {"coordinates":[-75.325867,39.900518],"type":"Point"}
}