{
  "type": "Feature",
  "properties": {
    "addr:full":"220 Biddle Dr Exton PA 19341",
    "addr:housenumber":"220",
    "addr:postcode":"19341",
    "addr:street":"Biddle Dr",
    "iso:country":"US",
    "sg:address":"220 Biddle Dr",
    "sg:city":"Exton",
    "sg:classifiers":[
        {
            "category":"Retail",
            "subcategory":"Repair Shop",
            "type":"Services"
        }
    ],
    "sg:phone":"+1 610 363 6410",
    "sg:postcode":"19341",
    "sg:province":"PA",
    "sg:tags":[
        "taxidermist"
    ],
    "wof:name":"Rumsey Taxidermy Studio",
    "wof:placetype":"venue"
},
  "geometry": {"coordinates":[-75.65272899999999,40.040666],"type":"Point"}
}