{
  "type": "Feature",
  "properties": {
    "addr:full":"1018 S 2nd St Philadelphia PA 19147",
    "addr:housenumber":"1018",
    "addr:postcode":"19147",
    "addr:street":"S 2Nd St",
    "iso:country":"US",
    "sg:address":"1018 S 2nd St",
    "sg:city":"Philadelphia",
    "sg:classifiers":[
        {
            "category":"Retail",
            "subcategory":"Funeral Services",
            "type":"Services"
        }
    ],
    "sg:phone":"+1 215 462 0441",
    "sg:postcode":"19147",
    "sg:province":"PA",
    "sg:tags":[
        "director",
        "cemetery"
    ],
    "wof:name":"Cieplinski Funeral Home",
    "wof:placetype":"venue"
},
  "geometry": {"coordinates":[-75.147301,39.934502],"type":"Point"}
}