{
  "type": "Feature",
  "properties": {
    "addr:full":"110 N Esbenshade Rd Manheim PA 17545",
    "addr:housenumber":"110",
    "addr:postcode":"17545",
    "addr:street":"N Esbenshade Rd",
    "iso:country":"US",
    "sg:address":"110 N Esbenshade Rd",
    "sg:city":"Manheim",
    "sg:classifiers":[
        {
            "category":"Education",
            "subcategory":"School",
            "type":"Public Place"
        }
    ],
    "sg:phone":"+1 717 653 4301",
    "sg:postcode":"17545",
    "sg:province":"PA",
    "wof:name":"Clearview Mennonite School",
    "wof:placetype":"venue"
},
  "geometry": {"coordinates":[-76.45236300000001,40.130664],"type":"Point"}
}