{
  "type": "Feature",
  "properties": {
    "iso:country":"US",
    "sg:address":"526 Main St",
    "sg:city":"Stroudsburg",
    "sg:classifiers":[
        {
            "category":"Coffee & Tea",
            "type":"Food & Drink"
        },
        {
            "category":"Restaurant",
            "type":"Food & Drink"
        }
    ],
    "sg:phone":"+1 570 420 8222",
    "sg:postcode":"18360",
    "sg:province":"PA",
    "sg:tags":[
        "shop",
        "espresso"
    ],
    "wof:name":"Cheeky Monkey Coffee House",
    "wof:placetype":"venue"
},
  "geometry": {"coordinates":[-75.191796,40.985973],"type":"Point"}
}