{
  "type": "Feature",
  "properties": {
    "iso:country":"US",
    "sg:address":"2210 Walnut St",
    "sg:city":"Philadelphia",
    "sg:classifiers":[
        {
            "category":"Professional",
            "subcategory":"Engineering",
            "type":"Services"
        }
    ],
    "sg:phone":"+1   ",
    "sg:postcode":"19103",
    "sg:province":"PA",
    "wof:name":"I TAn Yu and Associates Inc",
    "wof:placetype":"venue"
},
  "geometry": {"coordinates":[-75.1784,39.951016],"type":"Point"}
}