{
  "type": "Feature",
  "properties": {
    "addr:full":"1805 Woodbourne Rd Levittown PA 19057",
    "addr:housenumber":"1805",
    "addr:postcode":"19057",
    "addr:street":"Woodbourne Rd Levittown",
    "iso:country":"US",
    "sg:address":"1805 Woodbourne Rd",
    "sg:city":"Levittown",
    "sg:classifiers":[
        {
            "category":"Building & Trades",
            "subcategory":"Electrical",
            "type":"Services"
        }
    ],
    "sg:phone":"+1   ",
    "sg:postcode":"19057",
    "sg:province":"PA",
    "sg:tags":[
        "specializing",
        "work",
        "electrical",
        "contractor"
    ],
    "wof:name":"Qpi Electrical Co Inc",
    "wof:placetype":"venue"
},
  "geometry": {"coordinates":[-74.868236,40.159561],"type":"Point"}
}