{
  "type": "Feature",
  "properties": {
    "iso:country":"US",
    "sg:address":"12190 Hill Rd",
    "sg:city":"Wattsburg",
    "sg:classifiers":[
        {
            "category":"Manufacturing",
            "subcategory":"Buildings",
            "type":"Manufacturing & Wholesale Goods"
        },
        {
            "category":"Building & Trades",
            "subcategory":"Construction",
            "type":"Services"
        }
    ],
    "sg:phone":"+1 814 440 6704",
    "sg:postcode":"16442",
    "sg:province":"PA",
    "sg:tags":[
        "roofing",
        "builder",
        "carpenter",
        "contractor",
        "siding",
        "home"
    ],
    "sg:website":"http://www.snippertconstruction.com",
    "wof:name":"Snippert Construction",
    "wof:placetype":"venue"
},
  "geometry": {"coordinates":[-79.866439,42.027379],"type":"Point"}
}