{
  "type": "Feature",
  "properties": {
    "iso:country":"US",
    "sg:address":"745 Preston Ave",
    "sg:city":"Bryn Mawr",
    "sg:classifiers":[
        {
            "category":"Building & Trades",
            "subcategory":"Landscaping Services",
            "type":"Services"
        }
    ],
    "sg:phone":"+1 610 520 1872",
    "sg:postcode":"19010",
    "sg:province":"PA",
    "sg:tags":[
        "landscape",
        "contractor"
    ],
    "wof:name":"James K Gibbons Landscaping",
    "wof:placetype":"venue"
},
  "geometry": {"coordinates":[-75.314065,40.012926],"type":"Point"}
}