{
  "type": "Feature",
  "properties": {
    "iso:country":"US",
    "sg:address":"281 Farmland Rd",
    "sg:city":"Leola",
    "sg:classifiers":[
        {
            "category":"Freight",
            "type":"Transportation"
        }
    ],
    "sg:phone":"+1   ",
    "sg:postcode":"17540",
    "sg:province":"PA",
    "sg:tags":[
        "operator",
        "trucking"
    ],
    "wof:name":"D & B Moyer Trucking Inc",
    "wof:placetype":"venue"
},
  "geometry": {"coordinates":[-76.164117,40.083744],"type":"Point"}
}