{
  "type": "Feature",
  "properties": {
    "addr:full":"2900 N 5th St Philadelphia PA 19133",
    "addr:housenumber":"2900",
    "addr:postcode":"19133",
    "addr:street":"N 5Th St",
    "iso:country":"US",
    "sg:address":"2900 N 5th St",
    "sg:city":"Philadelphia",
    "sg:classifiers":[
        {
            "category":"Shopping",
            "subcategory":"Clothing, Apparel, & Fashions",
            "type":"Retail Goods"
        }
    ],
    "sg:phone":"+1 215 223 1404",
    "sg:postcode":"19133",
    "sg:province":"PA",
    "sg:tags":[
        "apparel",
        "accessory",
        "clothing",
        "store",
        "women's"
    ],
    "wof:name":"Jerry's Ladies Fashions",
    "wof:placetype":"venue"
},
  "geometry": {"coordinates":[-75.139397,39.9953],"type":"Point"}
}