{
  "type": "Feature",
  "properties": {
    "addr:full":"139C Colonial Rd Gordonville PA 17529",
    "addr:housenumber":"139c",
    "addr:postcode":"17529",
    "addr:street":"Colonial Rd",
    "iso:country":"US",
    "sg:address":"139C Colonial Rd",
    "sg:city":"Gordonville",
    "sg:classifiers":[
        {
            "category":"Manufacturing",
            "subcategory":"Furniture",
            "type":"Manufacturing & Wholesale Goods"
        }
    ],
    "sg:phone":"+1 717 768 3177",
    "sg:postcode":"17529",
    "sg:province":"PA",
    "sg:tags":[
        "builder",
        "designer",
        "custom"
    ],
    "wof:name":"A K Woodworks",
    "wof:placetype":"venue"
},
  "geometry": {"coordinates":[-76.084489,40.047221],"type":"Point"}
}