{
  "type": "Feature",
  "properties": {
    "iso:country":"US",
    "sg:address":"3858 Pulaski Ave",
    "sg:city":"Philadelphia",
    "sg:classifiers":[
        {
            "category":"Manufacturing",
            "subcategory":"Buildings",
            "type":"Manufacturing & Wholesale Goods"
        },
        {
            "category":"Structure",
            "subcategory":"Warehouse",
            "type":"Public Place"
        },
        {
            "category":"Building & Trades",
            "subcategory":"Construction",
            "type":"Services"
        }
    ],
    "sg:phone":"+1 215 226 2030",
    "sg:postcode":"19140",
    "sg:province":"PA",
    "sg:tags":[
        "industrial",
        "warehouses-merchandise",
        "warehouses-public-commercial",
        "builder",
        "contractor",
        "contractors-commercial",
        "home"
    ],
    "wof:name":"Vernon Burton Construction Company",
    "wof:placetype":"venue"
},
  "geometry": {"coordinates":[-75.15705,40.012862],"type":"Point"}
}