{
  "type": "Feature",
  "properties": {
    "addr:full":"217 Executive Dr Cranberry Twp PA 16066",
    "addr:housenumber":"217",
    "addr:postcode":"16066",
    "addr:street":"Executive Dr",
    "iso:country":"US",
    "sg:address":"217 Executive Dr",
    "sg:city":"Cranberry Twp",
    "sg:classifiers":[
        {
            "category":"Professional",
            "subcategory":"Engineering",
            "type":"Services"
        }
    ],
    "sg:phone":"+1 724 772 9088",
    "sg:postcode":"16066",
    "sg:province":"PA",
    "sg:tags":[
        "engineer"
    ],
    "wof:name":"Sundstrand Service Corp",
    "wof:placetype":"venue"
},
  "geometry": {"coordinates":[-80.108304,40.687442],"type":"Point"}
}