{
  "type": "Feature",
  "properties": {
    "addr:full":"146 W Front St Berwick PA 18603",
    "addr:housenumber":"146",
    "addr:postcode":"18603",
    "addr:street":"W Front St",
    "iso:country":"US",
    "sg:address":"146 W Front St",
    "sg:city":"Berwick",
    "sg:classifiers":[
        {
            "category":"Shopping",
            "subcategory":"Hobbies, Toys, & Games",
            "type":"Retail Goods"
        },
        {
            "category":"Shopping",
            "type":"Retail Goods"
        }
    ],
    "sg:phone":"+1 570 752 9611",
    "sg:postcode":"18603",
    "sg:province":"PA",
    "sg:tags":[
        "craft",
        "gallery",
        "dealer"
    ],
    "wof:name":"Daughters Dream Crafts and Gif",
    "wof:placetype":"venue"
},
  "geometry": {"coordinates":[-76.234178,41.054286],"type":"Point"}
}