{
  "type": "Feature",
  "properties": {
    "addr:full":"2323 Edinboro Rd Ste 501 Erie PA 16509",
    "addr:housenumber":"2323",
    "addr:postcode":"16509",
    "addr:street":"Edinboro Rd Ste 501",
    "iso:country":"US",
    "sg:address":"2323 Edinboro Rd Ste 501",
    "sg:city":"Erie",
    "sg:classifiers":[
        {
            "category":"Health Services",
            "subcategory":"Nursing And Care Facility",
            "type":"Services"
        },
        {
            "category":"Social Services",
            "subcategory":"Retirement Home",
            "type":"Services"
        }
    ],
    "sg:phone":"+1 814 860 7000",
    "sg:postcode":"16509",
    "sg:province":"PA",
    "sg:tags":[
        "personal",
        "convalescent"
    ],
    "wof:name":"Spring Hl Senior Living Cmnty",
    "wof:placetype":"venue"
},
  "geometry": {"coordinates":[-80.103808,42.059477],"type":"Point"}
}