{
  "type": "Feature",
  "properties": {
    "iso:country":"US",
    "sg:address":"629 Norway Rd",
    "sg:city":"Chadds Ford",
    "sg:classifiers":[
        {
            "category":"Professional",
            "subcategory":"Computer Services",
            "type":"Services"
        }
    ],
    "sg:phone":"+1 610 388 7903",
    "sg:postcode":"19317",
    "sg:province":"PA",
    "sg:tags":[
        "repair"
    ],
    "wof:name":"Advantage Computer Systems Inc",
    "wof:placetype":"venue"
},
  "geometry": {"coordinates":[-75.659373,39.836429],"type":"Point"}
}