{
  "type": "Feature",
  "properties": {
    "addr:full":"101 Leverington Ave Philadelphia PA 19127",
    "addr:housenumber":"101",
    "addr:postcode":"19127",
    "addr:street":"Leverington Ave",
    "iso:country":"US",
    "sg:address":"101 Leverington Ave",
    "sg:city":"Philadelphia",
    "sg:classifiers":[
        {
            "category":"Retail",
            "subcategory":"Auto Repair",
            "type":"Services"
        }
    ],
    "sg:phone":"+1 215 482 2850",
    "sg:postcode":"19127",
    "sg:province":"PA",
    "wof:name":"Andorra Auto Repair Inc",
    "wof:placetype":"venue"
},
  "geometry": {"coordinates":[-75.230294,40.02897],"type":"Point"}
}