{
  "type": "Feature",
  "properties": {
    "iso:country":"US",
    "sg:address":"21 Windsor Ln",
    "sg:city":"Red Lion",
    "sg:classifiers":[
        {
            "category":"Real Estate",
            "subcategory":"Real Estate Operator",
            "type":"Services"
        }
    ],
    "sg:phone":"+1 717 244 4777",
    "sg:postcode":"17356",
    "sg:province":"PA",
    "sg:tags":[
        "apartment"
    ],
    "wof:name":"Windsor Commons Townhouses",
    "wof:placetype":"venue"
},
  "geometry": {"coordinates":[-76.607891,39.902328],"type":"Point"}
}