{
  "type": "Feature",
  "properties": {
    "iso:country":"US",
    "sg:address":"22412 Perry Hwy",
    "sg:city":"Zelienople",
    "sg:classifiers":[
        {
            "category":"Building & Trades",
            "subcategory":"Plumbing",
            "type":"Services"
        }
    ],
    "sg:phone":"+1 724 452 6280",
    "sg:postcode":"16063",
    "sg:province":"PA",
    "sg:tags":[
        "conditioning",
        "air",
        "system",
        "contractor"
    ],
    "sg:website":"www.knoechelheating.com",
    "wof:name":"Knoechel Heating Co",
    "wof:placetype":"venue"
},
  "geometry": {"coordinates":[-80.133692,40.780357],"type":"Point"}
}