{
  "type": "Feature",
  "properties": {
    "addr:full":"3063 N Mascher St Philadelphia PA 19133",
    "addr:housenumber":"3063",
    "addr:postcode":"19133",
    "addr:street":"N Mascher St",
    "iso:country":"US",
    "sg:address":"3063 N Mascher St",
    "sg:city":"Philadelphia",
    "sg:classifiers":[
        {
            "category":"Retail",
            "subcategory":"Auto Rental",
            "type":"Services"
        },
        {
            "category":"Retail",
            "subcategory":"Storage",
            "type":"Services"
        }
    ],
    "sg:phone":"+1 215 427 2191",
    "sg:postcode":"19133",
    "sg:province":"PA",
    "sg:tags":[
        "moving-self",
        "truck"
    ],
    "wof:name":"Cruz, L M Truck And Equipment Rental",
    "wof:placetype":"venue"
},
  "geometry": {"coordinates":[-75.131674,39.996881],"type":"Point"}
}