{
  "type": "Feature",
  "properties": {
    "addr:full":"1440 S Main St Wilkes Barre PA 18706",
    "addr:housenumber":"1440",
    "addr:postcode":"18706",
    "addr:street":"S Main St",
    "iso:country":"US",
    "sg:address":"1440 S Main St",
    "sg:city":"Wilkes Barre",
    "sg:classifiers":[
        {
            "category":"Bars & Pubs",
            "type":"Food & Drink"
        }
    ],
    "sg:phone":"+1   ",
    "sg:postcode":"18706",
    "sg:province":"PA",
    "sg:tags":[
        "drinking"
    ],
    "wof:name":"Alexis Frank",
    "wof:placetype":"venue"
},
  "geometry": {"coordinates":[-75.91841100000001,41.224144],"type":"Point"}
}