{
  "type": "Feature",
  "properties": {
    "addr:full":"544 State Rte 93 Conyngham PA 18201",
    "addr:housenumber":"544",
    "addr:postcode":"18201",
    "addr:street":"State Rte 93 Conyngham",
    "iso:country":"US",
    "sg:address":"544 State Rte 93",
    "sg:city":"Conyngham",
    "sg:classifiers":[
        {
            "category":"Food & Beverages",
            "subcategory":"Groceries & Convenience Stores",
            "type":"Retail Goods"
        }
    ],
    "sg:phone":"+1 570 788 1710",
    "sg:postcode":"18201",
    "sg:province":"PA",
    "wof:name":"Uni-Mart",
    "wof:placetype":"venue"
},
  "geometry": {"coordinates":[-75.96504899999999,40.951169],"type":"Point"}
}