{
  "type": "Feature",
  "properties": {
    "iso:country":"US",
    "sg:address":"116 Shurs Ln",
    "sg:city":"Philadelphia",
    "sg:classifiers":[
        {
            "category":"Communications",
            "type":"Services"
        }
    ],
    "sg:phone":"+1 215 487 2997",
    "sg:postcode":"19127",
    "sg:province":"PA",
    "sg:tags":[
        "recording",
        "rehearsal",
        "studio"
    ],
    "wof:name":"Scrunch Recordings Inc",
    "wof:placetype":"venue"
},
  "geometry": {"coordinates":[-75.2174,40.0228],"type":"Point"}
}