{
  "type": "Feature",
  "properties": {
    "iso:country":"US",
    "sg:address":"739 W Main St",
    "sg:city":"Palmyra",
    "sg:classifiers":[
        {
            "category":"Shopping",
            "subcategory":"Computers & Home Electronics",
            "type":"Retail Goods"
        }
    ],
    "sg:phone":"+1 717 832 1300",
    "sg:postcode":"17078",
    "sg:province":"PA",
    "wof:name":"Frye's Wireless Concepts",
    "wof:placetype":"venue"
},
  "geometry": {"coordinates":[-76.607902,40.302015],"type":"Point"}
}