{
  "type": "Feature",
  "properties": {
    "addr:full":"1235 Tatamy Rd Easton PA 18045",
    "addr:housenumber":"1235",
    "addr:postcode":"18045",
    "addr:street":"Tatamy Rd",
    "iso:country":"US",
    "sg:address":"1235 Tatamy Rd",
    "sg:city":"Easton",
    "sg:classifiers":[
        {
            "category":"Shopping",
            "subcategory":"Computers & Home Electronics",
            "type":"Retail Goods"
        }
    ],
    "sg:phone":"+1   ",
    "sg:postcode":"18045",
    "sg:province":"PA",
    "sg:tags":[
        "repair",
        "television"
    ],
    "wof:name":"Pat Wiricks T V & Stereo",
    "wof:placetype":"venue"
},
  "geometry": {"coordinates":[-75.25398199999999,40.714621],"type":"Point"}
}