{
  "type": "Feature",
  "properties": {
    "addr:full":"6900 State Rd Philadelphia PA 19135",
    "addr:housenumber":"6900",
    "addr:postcode":"19135",
    "addr:street":"State Rd",
    "iso:country":"US",
    "sg:address":"6900 State Rd",
    "sg:city":"Philadelphia",
    "sg:classifiers":[
        {
            "category":"Bars & Pubs",
            "type":"Food & Drink"
        },
        {
            "category":"Restaurant",
            "type":"Food & Drink"
        }
    ],
    "sg:phone":"+1 215 331 8628",
    "sg:postcode":"19135",
    "sg:province":"PA",
    "sg:tags":[
        "tavern",
        "grill",
        "brew"
    ],
    "wof:name":"Curran's Irish Inn",
    "wof:placetype":"venue"
},
  "geometry": {"coordinates":[-75.040138,40.021851],"type":"Point"}
}