{
  "type": "Feature",
  "properties": {
    "iso:country":"US",
    "sg:address":"1800 Millport Rd",
    "sg:city":"Lancaster",
    "sg:classifiers":[
        {
            "category":"Building & Trades",
            "subcategory":"Construction",
            "type":"Services"
        }
    ],
    "sg:phone":"+1   ",
    "sg:postcode":"17602",
    "sg:province":"PA",
    "sg:tags":[
        "house"
    ],
    "wof:name":"Trippart Homes Inc",
    "wof:placetype":"venue"
},
  "geometry": {"coordinates":[-76.25645299999999,40.024729],"type":"Point"}
}