{
  "type": "Feature",
  "properties": {
    "iso:country":"US",
    "sg:address":"Penn Ctr # 6W",
    "sg:city":"Pittsburgh",
    "sg:classifiers":[
        {
            "category":"Education",
            "subcategory":"University",
            "type":"Public Place"
        }
    ],
    "sg:phone":"+1 412 747 0793",
    "sg:postcode":"15203",
    "sg:province":"PA",
    "sg:tags":[
        "college"
    ],
    "wof:name":"University of Phoenix Pittsburgh Campus",
    "wof:placetype":"venue"
},
  "geometry": {"coordinates":[-80.124567,40.428771],"type":"Point"}
}