{
  "type": "Feature",
  "properties": {
    "iso:country":"US",
    "sg:address":"698 S Shore Trl",
    "sg:city":"Central City",
    "sg:classifiers":[
        {
            "category":"Professional",
            "subcategory":"Engineering",
            "type":"Services"
        }
    ],
    "sg:phone":"+1   ",
    "sg:postcode":"15926",
    "sg:province":"PA",
    "wof:name":"P S I",
    "wof:placetype":"venue"
},
  "geometry": {"coordinates":[-78.861392,40.036274],"type":"Point"}
}