{
  "type": "Feature",
  "properties": {
    "addr:full":"438 S Mountain Blvd Mountain Top PA 18707",
    "addr:housenumber":"438",
    "addr:postcode":"18707",
    "addr:street":"S Mountain Blvd",
    "iso:country":"US",
    "sg:address":"438 S Mountain Blvd",
    "sg:city":"Mountain Top",
    "sg:classifiers":[
        {
            "category":"Real Estate",
            "subcategory":"Real Estate Agent",
            "type":"Services"
        }
    ],
    "sg:phone":"+1   ",
    "sg:postcode":"18707",
    "sg:province":"PA",
    "wof:name":"CD Mountain Realty Inc",
    "wof:placetype":"venue"
},
  "geometry": {"coordinates":[-75.911145,41.117901],"type":"Point"}
}