{
  "type": "Feature",
  "properties": {
    "addr:full":"121 E Susquehanna St Allentown PA 18103",
    "addr:housenumber":"121",
    "addr:postcode":"18103",
    "addr:street":"E Susquehanna St",
    "iso:country":"US",
    "sg:address":"121 E Susquehanna St",
    "sg:city":"Allentown",
    "sg:classifiers":[
        {
            "category":"Building & Trades",
            "subcategory":"Cleaning & Sanitation",
            "type":"Services"
        }
    ],
    "sg:phone":"+1 484 550 5773",
    "sg:postcode":"18103",
    "sg:province":"PA",
    "sg:tags":[
        "house"
    ],
    "sg:website":"http://www.bbcleaningservice.synthasite.com/",
    "wof:name":"B & B cleaning service",
    "wof:placetype":"venue"
},
  "geometry": {"coordinates":[-75.450005,40.59086],"type":"Point"}
}