{
  "type": "Feature",
  "properties": {
    "addr:full":"756 Woodside Ave Mertztown PA 19539",
    "addr:housenumber":"756",
    "addr:postcode":"19539",
    "addr:street":"Woodside Ave",
    "iso:country":"US",
    "sg:address":"756 Woodside Ave",
    "sg:city":"Mertztown",
    "sg:classifiers":[
        {
            "category":"Building & Trades",
            "subcategory":"Construction",
            "type":"Services"
        }
    ],
    "sg:phone":"+1   ",
    "sg:postcode":"19539",
    "sg:province":"PA",
    "sg:tags":[
        "laying",
        "floor",
        "establishment",
        "contractor"
    ],
    "wof:name":"Schlegels Carpet Install",
    "wof:placetype":"venue"
},
  "geometry": {"coordinates":[-75.701016,40.494332],"type":"Point"}
}