{
  "type": "Feature",
  "properties": {
    "iso:country":"US",
    "sg:address":"1313 Adams Ave",
    "sg:city":"Scranton",
    "sg:classifiers":[
        {
            "category":"Restaurant",
            "type":"Food & Drink"
        }
    ],
    "sg:phone":"+1 570 961 9286",
    "sg:postcode":"18509",
    "sg:province":"PA",
    "sg:tags":[
        "pizza"
    ],
    "wof:name":"Fontana's Pizza",
    "wof:placetype":"venue"
},
  "geometry": {"coordinates":[-75.64770799999999,41.420248],"type":"Point"}
}