{
  "type": "Feature",
  "properties": {
    "iso:country":"US",
    "sg:address":"64 State St",
    "sg:city":"Nicholson",
    "sg:classifiers":[
        {
            "category":"Organizations",
            "subcategory":"Religious Organization",
            "type":"Services"
        }
    ],
    "sg:phone":"+1 570 942 6604",
    "sg:postcode":"18446",
    "sg:province":"PA",
    "sg:tags":[
        "church"
    ],
    "wof:name":"Nicholson United Methodist Chr",
    "wof:placetype":"venue"
},
  "geometry": {"coordinates":[-75.783666,41.624302],"type":"Point"}
}