{
  "type": "Feature",
  "properties": {
    "iso:country":"US",
    "sg:address":"1110 Longshore Ave",
    "sg:city":"Philadelphia",
    "sg:classifiers":[
        {
            "category":"Professional",
            "subcategory":"Management & Consulting",
            "type":"Services"
        }
    ],
    "sg:phone":"+1 215 745 4168",
    "sg:postcode":"19111",
    "sg:province":"PA",
    "sg:tags":[
        "counselor",
        "relation",
        "public"
    ],
    "sg:website":"http://www.buzzunlimited.com",
    "wof:name":"Eisen & Associates",
    "wof:placetype":"venue"
},
  "geometry": {"coordinates":[-75.078446,40.049528],"type":"Point"}
}