{
  "type": "Feature",
  "properties": {
    "addr:full":"1301 Filbert St Philadelphia PA 19107",
    "addr:housenumber":"1301",
    "addr:postcode":"19107",
    "addr:street":"Filbert St",
    "iso:country":"US",
    "sg:address":"1301 Filbert St",
    "sg:city":"Philadelphia",
    "sg:classifiers":[
        {
            "category":"Utilities",
            "subcategory":"Telephone",
            "type":"Services"
        }
    ],
    "sg:phone":"+1 215 972 8340",
    "sg:postcode":"19107",
    "sg:province":"PA",
    "sg:tags":[
        "telecommunication"
    ],
    "wof:name":"Verizon Communications",
    "wof:placetype":"venue"
},
  "geometry": {"coordinates":[-75.16225,39.953244],"type":"Point"}
}