{
  "type": "Feature",
  "properties": {
    "addr:full":"2029 Walnut St Philadelphia PA 19103",
    "addr:housenumber":"2029",
    "addr:postcode":"19103",
    "addr:street":"Walnut St",
    "iso:country":"US",
    "sg:address":"2029 Walnut St",
    "sg:city":"Philadelphia",
    "sg:classifiers":[
        {
            "category":"Bars & Pubs",
            "type":"Food & Drink"
        },
        {
            "category":"Restaurant",
            "type":"Food & Drink"
        },
        {
            "category":"Bars & Pubs",
            "subcategory":"Nightclub",
            "type":"Food & Drink"
        },
        {
            "category":"Bars & Pubs",
            "subcategory":"Lounge",
            "type":"Food & Drink"
        }
    ],
    "sg:phone":"+1 215 557 0296",
    "sg:postcode":"19103",
    "sg:province":"PA",
    "sg:tags":[
        "club",
        "grill",
        "brew",
        "night"
    ],
    "sg:website":"www.monkeybarphilly.com",
    "wof:name":"Monkey Bar",
    "wof:placetype":"venue"
},
  "geometry": {"coordinates":[-75.17441599999999,39.950542],"type":"Point"}
}