{
  "type": "Feature",
  "properties": {
    "addr:full":"1817 Bernville Rd Reading PA 19601",
    "addr:housenumber":"1817",
    "addr:postcode":"19601",
    "addr:street":"Bernville Rd",
    "iso:country":"US",
    "sg:address":"1817 Bernville Rd",
    "sg:city":"Reading",
    "sg:classifiers":[
        {
            "category":"Professional",
            "subcategory":"Management & Consulting",
            "type":"Services"
        }
    ],
    "sg:phone":"+1 610 372 6692",
    "sg:postcode":"19601",
    "sg:province":"PA",
    "sg:tags":[
        "consultant",
        "hygiene",
        "industrial"
    ],
    "sg:website":"www.noisetest.com",
    "wof:name":"Cih Environmental",
    "wof:placetype":"venue"
},
  "geometry": {"coordinates":[-75.95319499999999,40.362639],"type":"Point"}
}