{
  "type": "Feature",
  "properties": {
    "iso:country":"US",
    "sg:address":"6631 Castor Ave",
    "sg:city":"Philadelphia",
    "sg:classifiers":[
        {
            "category":"Home & Garden",
            "subcategory":"Furniture",
            "type":"Retail Goods"
        }
    ],
    "sg:phone":"+1   ",
    "sg:postcode":"19149",
    "sg:province":"PA",
    "wof:name":"Fleishmans Fine Furn Dcorators",
    "wof:placetype":"venue"
},
  "geometry": {"coordinates":[-75.074703,40.042067],"type":"Point"}
}