{
  "type": "Feature",
  "properties": {
    "addr:full":"1747 Adams Ave Tyrone PA 16686",
    "addr:housenumber":"1747",
    "addr:postcode":"16686",
    "addr:street":"Adams Ave",
    "iso:country":"US",
    "sg:address":"1747 Adams Ave",
    "sg:city":"Tyrone",
    "sg:classifiers":[
        {
            "category":"Health Services",
            "subcategory":"Health Practitioner",
            "type":"Services"
        }
    ],
    "sg:phone":"+1 814 946 0105",
    "sg:postcode":"16686",
    "sg:province":"PA",
    "sg:tags":[
        "therapist",
        "physical"
    ],
    "wof:name":"Keystone Rehabilitation Systs",
    "wof:placetype":"venue"
},
  "geometry": {"coordinates":[-78.24215,40.680752],"type":"Point"}
}