{
  "type": "Feature",
  "properties": {
    "iso:country":"US",
    "sg:address":"2821 Island Ave",
    "sg:city":"Philadelphia",
    "sg:classifiers":[
        {
            "category":"Health Services",
            "subcategory":"Doctor",
            "type":"Services"
        }
    ],
    "sg:phone":"+1 215 492 9100",
    "sg:postcode":"19153",
    "sg:province":"PA",
    "sg:tags":[
        "physician",
        "surgeon"
    ],
    "wof:name":"Frank Kern MD",
    "wof:placetype":"venue"
},
  "geometry": {"coordinates":[-75.240251,39.90485],"type":"Point"}
}