{
  "type": "Feature",
  "properties": {
    "iso:country":"US",
    "sg:address":"38 Bierer Ave",
    "sg:city":"Uniontown",
    "sg:classifiers":[
        {
            "category":"Building & Trades",
            "subcategory":"Construction",
            "type":"Services"
        }
    ],
    "sg:phone":"+1 724 438 6768",
    "sg:postcode":"15401",
    "sg:province":"PA",
    "sg:tags":[
        "house"
    ],
    "wof:name":"Hibbs Carpentry",
    "wof:placetype":"venue"
},
  "geometry": {"coordinates":[-79.70600899999999,39.89745],"type":"Point"}
}