{
  "type": "Feature",
  "properties": {
    "iso:country":"US",
    "sg:address":"2 Parkway Ctr Ste 107",
    "sg:city":"Pittsburgh",
    "sg:classifiers":[
        {
            "category":"Professional",
            "subcategory":"Credit Reporting & Collection",
            "type":"Services"
        }
    ],
    "sg:phone":"+1 412 321 4990",
    "sg:postcode":"15220",
    "sg:province":"PA",
    "sg:tags":[
        "agency"
    ],
    "sg:website":"http://www.tulsatsi.com",
    "wof:name":"Transworld Systems Inc",
    "wof:placetype":"venue"
},
  "geometry": {"coordinates":[-80.041588,40.425804],"type":"Point"}
}