{
  "type": "Feature",
  "properties": {
    "iso:country":"US",
    "sg:address":"100 Jack Dr",
    "sg:city":"Indiana",
    "sg:classifiers":[
        {
            "category":"Wholesale",
            "subcategory":"Metals & Minerals",
            "type":"Manufacturing & Wholesale Goods"
        }
    ],
    "sg:phone":"+1 724 349 6823",
    "sg:postcode":"15701",
    "sg:province":"PA",
    "sg:tags":[
        "pipe"
    ],
    "sg:website":"www.mcjunkin.com",
    "wof:name":"Mc Junkin Corp",
    "wof:placetype":"venue"
},
  "geometry": {"coordinates":[-79.116041,40.630924],"type":"Point"}
}