{
  "type": "Feature",
  "properties": {
    "addr:full":"230 S Broad St Philadelphia PA 19102",
    "addr:housenumber":"230",
    "addr:postcode":"19102",
    "addr:street":"S Broad St",
    "iso:country":"US",
    "sg:address":"230 S Broad St",
    "sg:city":"Philadelphia",
    "sg:classifiers":[
        {
            "category":"Professional",
            "subcategory":"Management & Consulting",
            "type":"Services"
        },
        {
            "category":"Professional",
            "subcategory":"Advertising",
            "type":"Services"
        }
    ],
    "sg:phone":"+1 215 569 2262",
    "sg:postcode":"19102",
    "sg:province":"PA",
    "sg:tags":[
        "marketing",
        "program",
        "consultant"
    ],
    "sg:website":"http://www.karpmarketing.com",
    "wof:name":"Karp Marketing",
    "wof:placetype":"venue"
},
  "geometry": {"coordinates":[-75.16449,39.9482],"type":"Point"}
}