{
  "type": "Feature",
  "properties": {
    "iso:country":"US",
    "sg:address":"7306 Ogontz Ave",
    "sg:city":"Philadelphia",
    "sg:classifiers":[
        {
            "category":"Professional",
            "subcategory":"Advertising",
            "type":"Services"
        }
    ],
    "sg:phone":"+1 215 224 7800",
    "sg:postcode":"19138",
    "sg:province":"PA",
    "sg:tags":[
        "distribution"
    ],
    "wof:name":"A L M Distributing Co Inc",
    "wof:placetype":"venue"
},
  "geometry": {"coordinates":[-75.155455,40.065372],"type":"Point"}
}