{
  "type": "Feature",
  "properties": {
    "iso:country":"US",
    "sg:address":"N 2nd & Cherokee",
    "sg:city":"Emmaus",
    "sg:classifiers":[
        {
            "category":"Organizations",
            "subcategory":"Religious Organization",
            "type":"Services"
        }
    ],
    "sg:phone":"+1 610 967 5600",
    "sg:postcode":"18049",
    "sg:province":"PA",
    "sg:website":"www.faithchurchemmaus.org",
    "wof:name":"Faith Presbyterian Church",
    "wof:placetype":"venue"
},
  "geometry": {"coordinates":[-75.495102,40.531101],"type":"Point"}
}