{
  "type": "Feature",
  "properties": {
    "addr:full":"607 S 2nd St Philadelphia PA 19147",
    "addr:housenumber":"607",
    "addr:postcode":"19147",
    "addr:street":"S 2Nd St",
    "iso:country":"US",
    "sg:address":"607 S 2nd St",
    "sg:city":"Philadelphia",
    "sg:classifiers":[
        {
            "category":"Fast Food",
            "type":"Food & Drink"
        },
        {
            "category":"Restaurant",
            "type":"Food & Drink"
        }
    ],
    "sg:phone":"+1 215 627 7110",
    "sg:postcode":"19147",
    "sg:province":"PA",
    "sg:tags":[
        "style",
        "bar",
        "family",
        "sushi",
        "japanese",
        "take",
        "pan",
        "asian"
    ],
    "wof:name":"Hikaru Restaurant",
    "wof:placetype":"venue"
},
  "geometry": {"coordinates":[-75.1455,39.941101],"type":"Point"}
}