{
  "type": "Feature",
  "properties": {
    "iso:country":"US",
    "sg:address":"6633 Dalzell Pl",
    "sg:city":"Pittsburgh",
    "sg:classifiers":[
        {
            "category":"Health Services",
            "subcategory":"Doctor",
            "type":"Services"
        }
    ],
    "sg:phone":"+1   ",
    "sg:postcode":"15217",
    "sg:province":"PA",
    "sg:tags":[
        "medical"
    ],
    "wof:name":"Demian Essam MD",
    "wof:placetype":"venue"
},
  "geometry": {"coordinates":[-79.91310300000001,40.44207],"type":"Point"}
}