{
  "type": "Feature",
  "properties": {
    "iso:country":"US",
    "sg:address":"409 Ohio St",
    "sg:city":"Belle Vernon",
    "sg:classifiers":[
        {
            "category":"Retail",
            "subcategory":"Auto Repair",
            "type":"Services"
        }
    ],
    "sg:phone":"+1   ",
    "sg:postcode":"15012",
    "sg:province":"PA",
    "sg:tags":[
        "general"
    ],
    "wof:name":"Johns Truck & Equipment Repr",
    "wof:placetype":"venue"
},
  "geometry": {"coordinates":[-79.853847,40.135026],"type":"Point"}
}