{
  "type": "Feature",
  "properties": {
    "iso:country":"US",
    "sg:address":"116 S Broad St",
    "sg:city":"Kennett Square",
    "sg:classifiers":[
        {
            "category":"Banks & Credit Unions",
            "subcategory":"Investment Brokerage",
            "type":"Services"
        }
    ],
    "sg:phone":"+1 610 961 0101",
    "sg:postcode":"19348",
    "sg:province":"PA",
    "sg:tags":[
        "advisory",
        "financial"
    ],
    "wof:name":"W L Bechtold Financial Svc",
    "wof:placetype":"venue"
},
  "geometry": {"coordinates":[-75.710172,39.846017],"type":"Point"}
}