{
  "type": "Feature",
  "properties": {
    "addr:full":"6758 Ridge Ave Philadelphia PA 19128",
    "addr:housenumber":"6758",
    "addr:postcode":"19128",
    "addr:street":"Ridge Ave",
    "iso:country":"US",
    "sg:address":"6758 Ridge Ave",
    "sg:city":"Philadelphia",
    "sg:classifiers":[
        {
            "category":"Autos & Motor Vehicles",
            "subcategory":"Auto Supplies",
            "type":"Retail Goods"
        },
        {
            "category":"Wholesale",
            "subcategory":"Electrical",
            "type":"Manufacturing & Wholesale Goods"
        }
    ],
    "sg:phone":"+1 215 487 1274",
    "sg:postcode":"19128",
    "sg:province":"PA",
    "sg:tags":[
        "battery",
        "automobile",
        "part",
        "batteries-storage",
        "accessory"
    ],
    "sg:website":"http://www.autozone.com",
    "wof:name":"Autozone",
    "wof:placetype":"venue"
},
  "geometry": {"coordinates":[-75.225864,40.041996],"type":"Point"}
}