{
  "type": "Feature",
  "properties": {
    "addr:full":"1555 Easton Rd Abington PA 19001",
    "addr:housenumber":"1555",
    "addr:postcode":"19001",
    "addr:street":"Easton Rd",
    "iso:country":"US",
    "sg:address":"1555 Easton Rd",
    "sg:city":"Abington",
    "sg:classifiers":[
        {
            "category":"Food & Beverages",
            "subcategory":"Liquor & Beverages",
            "type":"Retail Goods"
        },
        {
            "category":"Wholesale",
            "subcategory":"Beer",
            "type":"Manufacturing & Wholesale Goods"
        }
    ],
    "sg:phone":"+1 215 659 5445",
    "sg:postcode":"19001",
    "sg:province":"PA",
    "sg:tags":[
        "ale",
        "soda"
    ],
    "wof:name":"Big Top Beverage Mart",
    "wof:placetype":"venue"
},
  "geometry": {"coordinates":[-75.12730999999999,40.130902],"type":"Point"}
}