{
  "type": "Feature",
  "properties": {
    "iso:country":"US",
    "sg:address":"406 S Main St",
    "sg:city":"Wilkes Barre",
    "sg:classifiers":[
        {
            "category":"Banks & Credit Unions",
            "subcategory":"Bank",
            "type":"Services"
        }
    ],
    "sg:phone":"+1   ",
    "sg:postcode":"18701",
    "sg:province":"PA",
    "sg:tags":[
        "national",
        "commercial"
    ],
    "wof:name":"Fleet",
    "wof:placetype":"venue"
},
  "geometry": {"coordinates":[-75.893715,41.239347],"type":"Point"}
}