{
  "type": "Feature",
  "properties": {
    "addr:full":"904 W Mount Airy Ave Philadelphia PA 19119",
    "addr:housenumber":"904",
    "addr:postcode":"19119",
    "addr:street":"W Mount Airy Ave",
    "iso:country":"US",
    "sg:address":"904 W Mount Airy Ave",
    "sg:city":"Philadelphia",
    "sg:classifiers":[
        {
            "category":"Professional",
            "subcategory":"Management & Consulting",
            "type":"Services"
        }
    ],
    "sg:phone":"+1 215 248 1225",
    "sg:postcode":"19119",
    "sg:province":"PA",
    "sg:tags":[
        "consultant",
        "coach",
        "business"
    ],
    "sg:website":"http://www.leadershipconsultinginc.com",
    "wof:name":"Leadership Consulting Group",
    "wof:placetype":"venue"
},
  "geometry": {"coordinates":[-75.207649,40.043839],"type":"Point"}
}