{
  "type": "Feature",
  "properties": {
    "addr:full":"13 Franklin Village Mall Kittanning PA 16201",
    "addr:housenumber":"13",
    "addr:postcode":"16201",
    "addr:street":"Franklin Village Mall",
    "iso:country":"US",
    "sg:address":"13 Franklin Village Mall",
    "sg:city":"Kittanning",
    "sg:classifiers":[
        {
            "category":"Food & Beverages",
            "subcategory":"Liquor & Beverages",
            "type":"Retail Goods"
        }
    ],
    "sg:phone":"+1   ",
    "sg:postcode":"16201",
    "sg:province":"PA",
    "sg:tags":[
        "regulation",
        "commercial",
        "sect",
        "alcoholic"
    ],
    "wof:name":"Wine & Spirits Shoppe 0308",
    "wof:placetype":"venue"
},
  "geometry": {"coordinates":[-79.54858299999999,40.812274],"type":"Point"}
}