{
  "type": "Feature",
  "properties": {
    "iso:country":"US",
    "sg:address":"4740 Library Rd",
    "sg:city":"Bethel Park",
    "sg:classifiers":[
        {
            "category":"Retail",
            "subcategory":"Auto Repair",
            "type":"Services"
        }
    ],
    "sg:phone":"+1 412 831 5500",
    "sg:postcode":"15102",
    "sg:province":"PA",
    "sg:tags":[
        "body",
        "shop"
    ],
    "wof:name":"Premium Collision Carstar",
    "wof:placetype":"venue"
},
  "geometry": {"coordinates":[-80.0242,40.348598],"type":"Point"}
}