{
  "type": "Feature",
  "properties": {
    "iso:country":"US",
    "sg:address":"406 Kettle St",
    "sg:city":"Altoona",
    "sg:classifiers":[
        {
            "category":"Wholesale",
            "subcategory":"Fruits & Vegetables",
            "type":"Manufacturing & Wholesale Goods"
        }
    ],
    "sg:phone":"+1 814 949 9156",
    "sg:postcode":"16602",
    "sg:province":"PA",
    "sg:tags":[
        "fresh",
        "or"
    ],
    "wof:name":"Cartwright Produce Inc",
    "wof:placetype":"venue"
},
  "geometry": {"coordinates":[-78.383664,40.524088],"type":"Point"}
}