{
  "type": "Feature",
  "properties": {
    "addr:full":"811 Victory Dr Allison Park PA 15101",
    "addr:housenumber":"811",
    "addr:postcode":"15101",
    "addr:street":"Victory Dr",
    "iso:country":"US",
    "sg:address":"811 Victory Dr",
    "sg:city":"Allison Park",
    "sg:classifiers":[
        {
            "category":"Building & Trades",
            "subcategory":"Cleaning & Sanitation",
            "type":"Services"
        }
    ],
    "sg:phone":"+1   ",
    "sg:postcode":"15101",
    "sg:province":"PA",
    "sg:tags":[
        "maintenance"
    ],
    "wof:name":"Charley S Window Cleaning",
    "wof:placetype":"venue"
},
  "geometry": {"coordinates":[-79.95997199999999,40.545771],"type":"Point"}
}