{
  "type": "Feature",
  "properties": {
    "addr:full":"131 E Butler Ave Ambler PA 19002",
    "addr:housenumber":"131",
    "addr:postcode":"19002",
    "addr:street":"E Butler Ave",
    "iso:country":"US",
    "sg:address":"131 E Butler Ave",
    "sg:city":"Ambler",
    "sg:classifiers":[
        {
            "category":"Food & Beverages",
            "subcategory":"Liquor & Beverages",
            "type":"Retail Goods"
        }
    ],
    "sg:phone":"+1   ",
    "sg:postcode":"19002",
    "sg:province":"PA",
    "sg:tags":[
        "regulation",
        "commercial",
        "sect",
        "alcoholic"
    ],
    "wof:name":"Wine & Spirits Shoppe 4607",
    "wof:placetype":"venue"
},
  "geometry": {"coordinates":[-75.221169,40.154916],"type":"Point"}
}