{
  "type": "Feature",
  "properties": {
    "addr:full":"504 Park Ave Clearfield PA 16830",
    "addr:housenumber":"504",
    "addr:postcode":"16830",
    "addr:street":"Park Ave",
    "iso:country":"US",
    "sg:address":"504 Park Ave",
    "sg:city":"Clearfield",
    "sg:classifiers":[
        {
            "category":"Health Services",
            "subcategory":"Health Practitioner",
            "type":"Services"
        }
    ],
    "sg:phone":"+1 814 768 3550",
    "sg:postcode":"16830",
    "sg:province":"PA",
    "sg:tags":[
        "therapist",
        "physical"
    ],
    "wof:name":"Joyner Sports Medicine Inst",
    "wof:placetype":"venue"
},
  "geometry": {"coordinates":[-78.436667,41.012737],"type":"Point"}
}