{
  "type": "Feature",
  "properties": {
    "addr:full":"203 W Main St Bloomsburg PA 17815",
    "addr:housenumber":"203",
    "addr:postcode":"17815",
    "addr:street":"W Main St",
    "iso:country":"US",
    "sg:address":"203 W Main St",
    "sg:city":"Bloomsburg",
    "sg:classifiers":[
        {
            "category":"Organizations",
            "subcategory":"Community Association",
            "type":"Services"
        }
    ],
    "sg:phone":"+1 570 784 1440",
    "sg:postcode":"17815",
    "sg:province":"PA",
    "sg:tags":[
        "fraternal"
    ],
    "wof:name":"Moose Lodge",
    "wof:placetype":"venue"
},
  "geometry": {"coordinates":[-76.45956099999999,41.001904],"type":"Point"}
}