{
  "type": "Feature",
  "properties": {
    "iso:country":"US",
    "sg:address":"1129 Treasure Lake",
    "sg:city":"Du Bois",
    "sg:classifiers":[
        {
            "category":"Real Estate",
            "subcategory":"Real Estate Agent",
            "type":"Services"
        }
    ],
    "sg:phone":"+1   ",
    "sg:postcode":"15801",
    "sg:province":"PA",
    "sg:tags":[
        "manages",
        "resort",
        "retirement",
        "vacation",
        "operates"
    ],
    "wof:name":"Treasure Lake",
    "wof:placetype":"venue"
},
  "geometry": {"coordinates":[-78.706594,41.165444],"type":"Point"}
}