{
  "type": "Feature",
  "properties": {
    "iso:country":"US",
    "sg:address":"373 W Susquehanna St",
    "sg:city":"Allentown",
    "sg:classifiers":[
        {
            "category":"Manufacturing",
            "subcategory":"Printing",
            "type":"Manufacturing & Wholesale Goods"
        }
    ],
    "sg:phone":"+1 610 797 2374",
    "sg:postcode":"18103",
    "sg:province":"PA",
    "sg:tags":[
        "commercial"
    ],
    "wof:name":"Best Impressions Printing",
    "wof:placetype":"venue"
},
  "geometry": {"coordinates":[-75.458921,40.590292],"type":"Point"}
}