{
  "type": "Feature",
  "properties": {
    "iso:country":"US",
    "sg:address":"21 Kedron Ave",
    "sg:city":"Morton",
    "sg:classifiers":[
        {
            "category":"Food & Beverages",
            "subcategory":"Groceries & Convenience Stores",
            "type":"Retail Goods"
        }
    ],
    "sg:phone":"+1   ",
    "sg:postcode":"19070",
    "sg:province":"PA",
    "wof:name":"Wawa 178",
    "wof:placetype":"venue"
},
  "geometry": {"coordinates":[-75.327477,39.908146],"type":"Point"}
}