{
  "type": "Feature",
  "properties": {
    "iso:country":"US",
    "sg:address":"3032 N Broad St",
    "sg:city":"Philadelphia",
    "sg:classifiers":[
        {
            "category":"Fast Food",
            "type":"Food & Drink"
        }
    ],
    "sg:phone":"+1 215 225 5553",
    "sg:postcode":"19132",
    "sg:province":"PA",
    "sg:website":"www.kfc.com",
    "wof:name":"KFC/Taco Bell",
    "wof:placetype":"venue"
},
  "geometry": {"coordinates":[-75.153344,39.99955],"type":"Point"}
}