{
  "type": "Feature",
  "properties": {
    "addr:full":"316 Dell Dr Perkasie PA 18944",
    "addr:housenumber":"316",
    "addr:postcode":"18944",
    "addr:street":"Dell Dr",
    "iso:country":"US",
    "sg:address":"316 Dell Dr",
    "sg:city":"Perkasie",
    "sg:classifiers":[
        {
            "category":"Building & Trades",
            "subcategory":"Construction",
            "type":"Services"
        }
    ],
    "sg:phone":"+1 215 453 7772",
    "sg:postcode":"18944",
    "sg:province":"PA",
    "sg:tags":[
        "painting",
        "contractor"
    ],
    "wof:name":"Mike Leven Painting",
    "wof:placetype":"venue"
},
  "geometry": {"coordinates":[-75.30394800000001,40.384502],"type":"Point"}
}