{
  "type": "Feature",
  "properties": {
    "addr:full":"1318 Walnut St Philadelphia PA 19107",
    "addr:housenumber":"1318",
    "addr:postcode":"19107",
    "addr:street":"Walnut St",
    "iso:country":"US",
    "sg:address":"1318 Walnut St",
    "sg:city":"Philadelphia",
    "sg:classifiers":[
        {
            "category":"Food & Beverages",
            "subcategory":"Groceries & Convenience Stores",
            "type":"Retail Goods"
        }
    ],
    "sg:phone":"+1 215 545 4085",
    "sg:postcode":"19107",
    "sg:province":"PA",
    "wof:name":"Citi Marketplace",
    "wof:placetype":"venue"
},
  "geometry": {"coordinates":[-75.162927,39.948869],"type":"Point"}
}