{
  "type": "Feature",
  "properties": {
    "iso:country":"US",
    "sg:address":"810 Larkspur Ln",
    "sg:city":"Narberth",
    "sg:classifiers":[
        {
            "category":"Health Services",
            "subcategory":"Doctor",
            "type":"Services"
        }
    ],
    "sg:phone":"+1 610 667 7752",
    "sg:postcode":"19072",
    "sg:province":"PA",
    "sg:tags":[
        "surgeon",
        "oral"
    ],
    "wof:name":"Korn Gerald DDS",
    "wof:placetype":"venue"
},
  "geometry": {"coordinates":[-75.2612,40.019402],"type":"Point"}
}