{
  "type": "Feature",
  "properties": {
    "iso:country":"US",
    "sg:address":"376 Erie Ave",
    "sg:city":"Telford",
    "sg:classifiers":[
        {
            "category":"Autos & Motor Vehicles",
            "subcategory":"Auto Supplies",
            "type":"Retail Goods"
        }
    ],
    "sg:phone":"+1 215 527 3866",
    "sg:postcode":"18969",
    "sg:province":"PA",
    "sg:tags":[
        "automobile",
        "part"
    ],
    "wof:name":"Bumpers & Body",
    "wof:placetype":"venue"
},
  "geometry": {"coordinates":[-75.33444900000001,40.321013],"type":"Point"}
}