{
  "type": "Feature",
  "properties": {
    "addr:full":"450 W Dauphin St Philadelphia PA 19133",
    "addr:housenumber":"450",
    "addr:postcode":"19133",
    "addr:street":"W Dauphin St",
    "iso:country":"US",
    "sg:address":"450 W Dauphin St",
    "sg:city":"Philadelphia",
    "sg:classifiers":[
        {
            "category":"Health Services",
            "subcategory":"Doctor",
            "type":"Services"
        }
    ],
    "sg:phone":"+1 215 426 1220",
    "sg:postcode":"19133",
    "sg:province":"PA",
    "sg:tags":[
        "physician",
        "surgeon",
        "medical"
    ],
    "wof:name":"450 Medical Center",
    "wof:placetype":"venue"
},
  "geometry": {"coordinates":[-75.14145000000001,39.985929],"type":"Point"}
}