{
  "type": "Feature",
  "properties": {
    "iso:country":"US",
    "sg:address":"440 Monongahela Ave",
    "sg:city":"Glassport",
    "sg:classifiers":[
        {
            "category":"Education",
            "subcategory":"Library",
            "type":"Public Place"
        }
    ],
    "sg:phone":"+1 412 672 7400",
    "sg:postcode":"15045",
    "sg:province":"PA",
    "wof:name":"Samuel A Weiss Community Libr",
    "wof:placetype":"venue"
},
  "geometry": {"coordinates":[-79.892528,40.329149],"type":"Point"}
}