{
  "type": "Feature",
  "properties": {
    "iso:country":"US",
    "sg:address":"5406 W Berks St",
    "sg:city":"Philadelphia",
    "sg:classifiers":[
        {
            "category":"Communications",
            "subcategory":"Radio Station",
            "type":"Services"
        }
    ],
    "sg:phone":"+1   ",
    "sg:postcode":"19131",
    "sg:province":"PA",
    "sg:tags":[
        "arts",
        "medium"
    ],
    "wof:name":"Cme Inc",
    "wof:placetype":"venue"
},
  "geometry": {"coordinates":[-75.234618,39.985252],"type":"Point"}
}