{
  "type": "Feature",
  "properties": {
    "addr:full":"900 Northbrook Dr Ste 310 Feasterville Trevose PA 19053",
    "addr:housenumber":"900",
    "addr:postcode":"19053",
    "addr:street":"Northbrook Dr Ste 310",
    "iso:country":"US",
    "sg:address":"900 Northbrook Dr Ste 310",
    "sg:city":"Feasterville Trevose",
    "sg:classifiers":[
        {
            "category":"Building & Trades",
            "subcategory":"Construction",
            "type":"Services"
        }
    ],
    "sg:phone":"+1 215 357 0630",
    "sg:postcode":"19053",
    "sg:province":"PA",
    "sg:tags":[
        "contractor"
    ],
    "wof:name":"Cetco Contracting Services Co",
    "wof:placetype":"venue"
},
  "geometry": {"coordinates":[-74.96399599999999,40.142932],"type":"Point"}
}