{
  "type": "Feature",
  "properties": {
    "iso:country":"US",
    "sg:address":"11 Meadow Dr",
    "sg:city":"Effort",
    "sg:classifiers":[
        {
            "category":"Communications",
            "subcategory":"Film & Video Production",
            "type":"Services"
        }
    ],
    "sg:phone":"+1   ",
    "sg:postcode":"18330",
    "sg:province":"PA",
    "sg:tags":[
        "motion"
    ],
    "wof:name":"Evermore Productions",
    "wof:placetype":"venue"
},
  "geometry": {"coordinates":[-75.470454,40.944654],"type":"Point"}
}