{
  "type": "Feature",
  "properties": {
    "addr:full":"2011 W Shunk St Philadelphia PA 19145",
    "addr:housenumber":"2011",
    "addr:postcode":"19145",
    "addr:street":"W Shunk St",
    "iso:country":"US",
    "sg:address":"2011 W Shunk St",
    "sg:city":"Philadelphia",
    "sg:classifiers":[
        {
            "category":"Building & Trades",
            "subcategory":"Cleaning & Sanitation",
            "type":"Services"
        }
    ],
    "sg:phone":"+1 215 764 5486",
    "sg:postcode":"19145",
    "sg:province":"PA",
    "sg:tags":[
        "home"
    ],
    "sg:website":"www.philadelphia-carpet-cleaners...",
    "wof:name":"Philadelphia Upholstery Cleaning",
    "wof:placetype":"venue"
},
  "geometry": {"coordinates":[-75.181091,39.919451],"type":"Point"}
}