{
  "type": "Feature",
  "properties": {
    "iso:country":"US",
    "sg:address":"6058 Stanton Ave",
    "sg:city":"Pittsburgh",
    "sg:classifiers":[
        {
            "category":"Professional",
            "subcategory":"Art Services",
            "type":"Services"
        }
    ],
    "sg:phone":"+1 412 362 6580",
    "sg:postcode":"15206",
    "sg:province":"PA",
    "sg:tags":[
        "artist"
    ],
    "wof:name":"John Manders",
    "wof:placetype":"venue"
},
  "geometry": {"coordinates":[-79.91890100000001,40.469034],"type":"Point"}
}