{
  "type": "Feature",
  "properties": {
    "addr:full":"5350 Campbells Run Rd Pittsburgh PA 15205",
    "addr:housenumber":"5350",
    "addr:postcode":"15205",
    "addr:street":"Campbells Run Rd",
    "iso:country":"US",
    "sg:address":"5350 Campbells Run Rd",
    "sg:city":"Pittsburgh",
    "sg:classifiers":[
        {
            "category":"Manufacturing",
            "subcategory":"Metals",
            "type":"Manufacturing & Wholesale Goods"
        }
    ],
    "sg:phone":"+1 412 787 9750",
    "sg:postcode":"15205",
    "sg:province":"PA",
    "sg:tags":[
        "trim",
        "frame",
        "door",
        "sash"
    ],
    "sg:website":"www.bulkpvc.com",
    "wof:name":"Tmi Inc",
    "wof:placetype":"venue"
},
  "geometry": {"coordinates":[-80.158766,40.445484],"type":"Point"}
}