{
  "type": "Feature",
  "properties": {
    "iso:country":"US",
    "sg:address":"71 S Timber Rd",
    "sg:city":"Holland",
    "sg:classifiers":[
        {
            "category":"Education",
            "subcategory":"Special Training",
            "type":"Public Place"
        }
    ],
    "sg:phone":"+1 215 504 5468",
    "sg:postcode":"18966",
    "sg:province":"PA",
    "sg:tags":[
        "instruction",
        "driving"
    ],
    "wof:name":"Accurate Driving School Inc",
    "wof:placetype":"venue"
},
  "geometry": {"coordinates":[-74.95934699999999,40.216821],"type":"Point"}
}