{
  "type": "Feature",
  "properties": {
    "addr:full":"8 Fawn Cir Malvern PA 19355",
    "addr:housenumber":"8",
    "addr:postcode":"19355",
    "addr:street":"Fawn Cir",
    "iso:country":"US",
    "sg:address":"8 Fawn Cir",
    "sg:city":"Malvern",
    "sg:classifiers":[
        {
            "category":"Communications",
            "subcategory":"Radio Station",
            "type":"Services"
        }
    ],
    "sg:phone":"+1   ",
    "sg:postcode":"19355",
    "sg:province":"PA",
    "sg:tags":[
        "broadcast"
    ],
    "wof:name":"Thomas Stecher Associates",
    "wof:placetype":"venue"
},
  "geometry": {"coordinates":[-75.544454,40.048715],"type":"Point"}
}