{
  "type": "Feature",
  "properties": {
    "addr:full":"233 Mill St Coraopolis PA 15108",
    "addr:housenumber":"233",
    "addr:postcode":"15108",
    "addr:street":"Mill St",
    "iso:country":"US",
    "sg:address":"233 Mill St",
    "sg:city":"Coraopolis",
    "sg:classifiers":[
        {
            "category":"Building & Trades",
            "subcategory":"Landscaping Services",
            "type":"Services"
        }
    ],
    "sg:phone":"+1 412 264 3235",
    "sg:postcode":"15108",
    "sg:province":"PA",
    "wof:name":"Zucchero Landscaping",
    "wof:placetype":"venue"
},
  "geometry": {"coordinates":[-80.163082,40.519106],"type":"Point"}
}