{
  "type": "Feature",
  "properties": {
    "addr:full":"68 W High St Waynesburg PA 15370",
    "addr:housenumber":"68",
    "addr:postcode":"15370",
    "addr:street":"W High St",
    "iso:country":"US",
    "sg:address":"68 W High St",
    "sg:city":"Waynesburg",
    "sg:classifiers":[
        {
            "category":"Personal",
            "subcategory":"Beauty Salon",
            "type":"Services"
        }
    ],
    "sg:phone":"+1 724 627 9083",
    "sg:postcode":"15370",
    "sg:province":"PA",
    "wof:name":"Helen's Hair Salon",
    "wof:placetype":"venue"
},
  "geometry": {"coordinates":[-80.188256,39.896422],"type":"Point"}
}