{
  "type": "Feature",
  "properties": {
    "iso:country":"US",
    "sg:address":"5408 Spruce St",
    "sg:city":"Philadelphia",
    "sg:classifiers":[
        {
            "category":"Personal",
            "subcategory":"Beauty Salon",
            "type":"Services"
        }
    ],
    "sg:phone":"+1 215 748 1916",
    "sg:postcode":"19139",
    "sg:province":"PA",
    "wof:name":"Rachael Matthews Beauty Salon",
    "wof:placetype":"venue"
},
  "geometry": {"coordinates":[-75.231813,39.955223],"type":"Point"}
}