{
  "type": "Feature",
  "properties": {
    "iso:country":"US",
    "sg:address":"4001 Lyman Dr",
    "sg:city":"Philadelphia",
    "sg:classifiers":[
        {
            "category":"Health Services",
            "subcategory":"Doctor",
            "type":"Services"
        }
    ],
    "sg:phone":"+1 215 637 6300",
    "sg:postcode":"19114",
    "sg:province":"PA",
    "sg:tags":[
        "dentist"
    ],
    "wof:name":"Pren Gulati DDS",
    "wof:placetype":"venue"
},
  "geometry": {"coordinates":[-74.98325699999999,40.064416],"type":"Point"}
}