{
  "type": "Feature",
  "properties": {
    "iso:country":"US",
    "sg:address":"410 Hazle St",
    "sg:city":"Wilkes Barre",
    "sg:classifiers":[
        {
            "category":"Home & Garden",
            "subcategory":"Household Appliances",
            "type":"Retail Goods"
        },
        {
            "category":"Retail",
            "subcategory":"Repair Shop",
            "type":"Services"
        }
    ],
    "sg:phone":"+1 570 824 3751",
    "sg:postcode":"18702",
    "sg:province":"PA",
    "sg:tags":[
        "stereo",
        "radio",
        "television"
    ],
    "wof:name":"Electron T V & Appliance Ctr",
    "wof:placetype":"venue"
},
  "geometry": {"coordinates":[-75.890958,41.230561],"type":"Point"}
}