{
  "type": "Feature",
  "properties": {
    "addr:full":"2929 S 10th St Philadelphia PA 19148",
    "addr:housenumber":"2929",
    "addr:postcode":"19148",
    "addr:street":"S 10Th St",
    "iso:country":"US",
    "sg:address":"2929 S 10th St",
    "sg:city":"Philadelphia",
    "sg:classifiers":[
        {
            "category":"Organizations",
            "subcategory":"Religious Organization",
            "type":"Services"
        }
    ],
    "sg:phone":"+1 215 462 1111",
    "sg:postcode":"19148",
    "sg:province":"PA",
    "sg:tags":[
        "monastery",
        "convent"
    ],
    "wof:name":"Sisters Of St Joseph",
    "wof:placetype":"venue"
},
  "geometry": {"coordinates":[-75.16528099999999,39.912275],"type":"Point"}
}