{
  "type": "Feature",
  "properties": {
    "addr:full":"5550 Centre Ave Pittsburgh PA 15232",
    "addr:housenumber":"5550",
    "addr:postcode":"15232",
    "addr:street":"Centre Ave",
    "iso:country":"US",
    "sg:address":"5550 Centre Ave",
    "sg:city":"Pittsburgh",
    "sg:classifiers":[
        {
            "category":"Banks & Credit Unions",
            "subcategory":"Bank",
            "type":"Services"
        }
    ],
    "sg:phone":"+1 412 578 7770",
    "sg:postcode":"15232",
    "sg:province":"PA",
    "sg:tags":[
        "saving",
        "commercial"
    ],
    "sg:website":"http://www.usafinancialgroup.net",
    "wof:name":"Citizens Bank",
    "wof:placetype":"venue"
},
  "geometry": {"coordinates":[-79.93523999999999,40.456917],"type":"Point"}
}