{
  "type": "Feature",
  "properties": {
    "iso:country":"US",
    "sg:address":"43 Dougherty Blvd",
    "sg:city":"Glen Mills",
    "sg:classifiers":[
        {
            "category":"Insurance",
            "subcategory":"Insurance Agent",
            "type":"Services"
        }
    ],
    "sg:phone":"+1 610 696 4515",
    "sg:postcode":"19342",
    "sg:province":"PA",
    "wof:name":"Lewis Hopkins & Williamson Inc",
    "wof:placetype":"venue"
},
  "geometry": {"coordinates":[-75.487286,39.89528],"type":"Point"}
}