{
  "type": "Feature",
  "properties": {
    "iso:country":"US",
    "sg:address":"1101 Market St",
    "sg:city":"Philadelphia",
    "sg:classifiers":[
        {
            "category":"Government",
            "subcategory":"Office",
            "type":"Public Place"
        },
        {
            "category":"Utilities",
            "subcategory":"Water",
            "type":"Services"
        }
    ],
    "sg:phone":"+1 215 685 6121",
    "sg:postcode":"19107",
    "sg:province":"PA",
    "sg:tags":[
        "govt",
        "city",
        "supply"
    ],
    "sg:website":"www.phillywater.org",
    "wof:name":"Philadelphia Water Department",
    "wof:placetype":"venue"
},
  "geometry": {"coordinates":[-75.159885,39.951913],"type":"Point"}
}