{
  "type": "Feature",
  "properties": {
    "iso:country":"US",
    "sg:address":"410 Blossom Dr",
    "sg:city":"Mount Wolf",
    "sg:classifiers":[
        {
            "category":"Building & Trades",
            "subcategory":"Plumbing",
            "type":"Services"
        }
    ],
    "sg:phone":"+1   ",
    "sg:postcode":"17347",
    "sg:province":"PA",
    "sg:tags":[
        "contractor"
    ],
    "wof:name":"Klings Heating & A/C",
    "wof:placetype":"venue"
},
  "geometry": {"coordinates":[-76.69069399999999,40.044747],"type":"Point"}
}