{
  "type": "Feature",
  "properties": {
    "addr:full":"50 Tipp St Du Bois PA 15801",
    "addr:housenumber":"50",
    "addr:postcode":"15801",
    "addr:street":"Tipp St Du Bois",
    "iso:country":"US",
    "sg:address":"50 Tipp St",
    "sg:city":"Du Bois",
    "sg:classifiers":[
        {
            "category":"Building & Trades",
            "subcategory":"Electrical",
            "type":"Services"
        }
    ],
    "sg:phone":"+1   ",
    "sg:postcode":"15801",
    "sg:province":"PA",
    "sg:tags":[
        "material",
        "electrical",
        "contractor"
    ],
    "wof:name":"Du Com",
    "wof:placetype":"venue"
},
  "geometry": {"coordinates":[-78.76814299999999,41.109486],"type":"Point"}
}