{
  "type": "Feature",
  "properties": {
    "iso:country":"US",
    "sg:address":"57 Main St",
    "sg:city":"Harleysville",
    "sg:classifiers":[
        {
            "category":"Government",
            "subcategory":"Office",
            "type":"Public Place"
        }
    ],
    "sg:phone":"+1 215 256 8676",
    "sg:postcode":"19438",
    "sg:province":"PA",
    "sg:tags":[
        "village"
    ],
    "wof:name":"Lower Salford Twp Sewer Auth",
    "wof:placetype":"venue"
},
  "geometry": {"coordinates":[-75.36110600000001,40.257215],"type":"Point"}
}