{
  "type": "Feature",
  "properties": {
    "iso:country":"US",
    "sg:address":"100 Nutt Rd",
    "sg:city":"Phoenixville",
    "sg:classifiers":[
        {
            "category":"Retail",
            "subcategory":"Auto Repair",
            "type":"Services"
        }
    ],
    "sg:phone":"+1 610 935 8810",
    "sg:postcode":"19460",
    "sg:province":"PA",
    "sg:tags":[
        "automobile",
        "inspection"
    ],
    "sg:website":"www.cartersautomotive.com",
    "wof:name":"Carters Automotive Inc",
    "wof:placetype":"venue"
},
  "geometry": {"coordinates":[-75.512897,40.123629],"type":"Point"}
}