{
  "type": "Feature",
  "properties": {
    "addr:full":"506 Myrtle Ave Horsham PA 19044",
    "addr:housenumber":"506",
    "addr:postcode":"19044",
    "addr:street":"Myrtle Ave",
    "iso:country":"US",
    "sg:address":"506 Myrtle Ave",
    "sg:city":"Horsham",
    "sg:classifiers":[
        {
            "category":"Building & Trades",
            "subcategory":"Construction",
            "type":"Services"
        }
    ],
    "sg:phone":"+1 215 443 5433",
    "sg:postcode":"19044",
    "sg:province":"PA",
    "sg:tags":[
        "general",
        "contractor"
    ],
    "wof:name":"Craig N Gower Construction",
    "wof:placetype":"venue"
},
  "geometry": {"coordinates":[-75.144053,40.185972],"type":"Point"}
}