{
  "type": "Feature",
  "properties": {
    "addr:full":"6497 Sullivan Trl Pen Argyl PA 18072",
    "addr:housenumber":"6497",
    "addr:postcode":"18072",
    "addr:street":"Sullivan Trl",
    "iso:country":"US",
    "sg:address":"6497 Sullivan Trl",
    "sg:city":"Pen Argyl",
    "sg:classifiers":[
        {
            "category":"Retail",
            "subcategory":"Auto Rental",
            "type":"Services"
        }
    ],
    "sg:phone":"+1   ",
    "sg:postcode":"18072",
    "sg:province":"PA",
    "sg:tags":[
        "truck"
    ],
    "wof:name":"Ryder",
    "wof:placetype":"venue"
},
  "geometry": {"coordinates":[-75.294597,40.826744],"type":"Point"}
}