{
  "type": "Feature",
  "properties": {
    "iso:country":"US",
    "sg:address":"1111 E End Blvd",
    "sg:city":"Wilkes Barre",
    "sg:classifiers":[
        {
            "category":"Health Services",
            "subcategory":"Medical Lab",
            "type":"Services"
        }
    ],
    "sg:phone":"+1 570 821 9806",
    "sg:postcode":"18702",
    "sg:province":"PA",
    "sg:tags":[
        "laboratory"
    ],
    "wof:name":"LCAI",
    "wof:placetype":"venue"
},
  "geometry": {"coordinates":[-75.833917,41.247704],"type":"Point"}
}