{
  "type": "Feature",
  "properties": {
    "addr:full":"201 N Kenhorst Blvd Reading PA 19607",
    "addr:housenumber":"201",
    "addr:postcode":"19607",
    "addr:street":"N Kenhorst Blvd",
    "iso:country":"US",
    "sg:address":"201 N Kenhorst Blvd",
    "sg:city":"Reading",
    "sg:classifiers":[
        {
            "category":"Health Services",
            "subcategory":"Optometrist",
            "type":"Services"
        }
    ],
    "sg:phone":"+1 610 796 1300",
    "sg:postcode":"19607",
    "sg:province":"PA",
    "wof:name":"Lisa M Mc Devitt OD",
    "wof:placetype":"venue"
},
  "geometry": {"coordinates":[-75.94996999999999,40.316103],"type":"Point"}
}