{
  "type": "Feature",
  "properties": {
    "iso:country":"US",
    "sg:address":"2520 Lititz Pike",
    "sg:city":"Lancaster",
    "sg:classifiers":[
        {
            "category":"Bagels",
            "subcategory":"None",
            "type":"Food & Drink"
        }
    ],
    "sg:phone":"+1 717 581 8180",
    "sg:postcode":"17601",
    "sg:province":"PA",
    "wof:name":"Neffsville Bagels, Inc.",
    "wof:placetype":"venue"
},
  "geometry": {"coordinates":[-76.304806,40.094883],"type":"Point"}
}