{
  "type": "Feature",
  "properties": {
    "addr:full":"1618 Poplar St Philadelphia PA 19130",
    "addr:housenumber":"1618",
    "addr:postcode":"19130",
    "addr:street":"Poplar St",
    "iso:country":"US",
    "sg:address":"1618 Poplar St",
    "sg:city":"Philadelphia",
    "sg:classifiers":[
        {
            "category":"Building & Trades",
            "subcategory":"Landscaping Services",
            "type":"Services"
        }
    ],
    "sg:phone":"+1 215 236 4660",
    "sg:postcode":"19130",
    "sg:province":"PA",
    "sg:tags":[
        "aged",
        "homes-institutional"
    ],
    "wof:name":"Trevor's Next Door",
    "wof:placetype":"venue"
},
  "geometry": {"coordinates":[-75.163263,39.970654],"type":"Point"}
}