{
  "type": "Feature",
  "properties": {
    "iso:country":"US",
    "sg:address":"2624 Haworth St",
    "sg:city":"Philadelphia",
    "sg:classifiers":[
        {
            "category":"Arts & Performance",
            "subcategory":"Theater",
            "type":"Entertainment"
        }
    ],
    "sg:phone":"+1 215 537 1959",
    "sg:postcode":"19137",
    "sg:province":"PA",
    "sg:tags":[
        "musician",
        "entertainers-family",
        "business"
    ],
    "wof:name":"Original Trilby String Band",
    "wof:placetype":"venue"
},
  "geometry": {"coordinates":[-75.067998,40.003139],"type":"Point"}
}