{
  "type": "Feature",
  "properties": {
    "addr:full":"4802 Parkside Ave Philadelphia PA 19131",
    "addr:housenumber":"4802",
    "addr:postcode":"19131",
    "addr:street":"Parkside Ave",
    "iso:country":"US",
    "sg:address":"4802 Parkside Ave",
    "sg:city":"Philadelphia",
    "sg:classifiers":[
        {
            "category":"Shopping",
            "subcategory":"Bicycles & Sporting Goods",
            "type":"Retail Goods"
        }
    ],
    "sg:phone":"+1   ",
    "sg:postcode":"19131",
    "sg:province":"PA",
    "wof:name":"Pelzers Horse Supplies",
    "wof:placetype":"venue"
},
  "geometry": {"coordinates":[-75.21681,39.97894],"type":"Point"}
}