{
  "type": "Feature",
  "properties": {
    "iso:country":"US",
    "sg:address":"90 N Ridgeway Ave",
    "sg:city":"Glenolden",
    "sg:classifiers":[
        {
            "category":"Wholesale",
            "subcategory":"Electrical",
            "type":"Manufacturing & Wholesale Goods"
        }
    ],
    "sg:phone":"+1 610 494 0213",
    "sg:postcode":"19036",
    "sg:province":"PA",
    "sg:tags":[
        "alarm",
        "burglar",
        "system"
    ],
    "wof:name":"AMS Security",
    "wof:placetype":"venue"
},
  "geometry": {"coordinates":[-75.28016599999999,39.900035],"type":"Point"}
}