{
  "type": "Feature",
  "properties": {
    "iso:country":"US",
    "sg:address":"1144 Devon Rd",
    "sg:city":"Rydal",
    "sg:classifiers":[
        {
            "category":"Wholesale",
            "subcategory":"Durable Goods & Equipment",
            "type":"Manufacturing & Wholesale Goods"
        }
    ],
    "sg:phone":"+1 215 887 7116",
    "sg:postcode":"19046",
    "sg:province":"PA",
    "sg:tags":[
        "representative",
        "manufacturer"
    ],
    "wof:name":"William B Murray",
    "wof:placetype":"venue"
},
  "geometry": {"coordinates":[-75.109397,40.098885],"type":"Point"}
}