{
  "type": "Feature",
  "properties": {
    "iso:country":"US",
    "sg:address":"1932 E Washington Ln ",
    "sg:city":"Philadelphia",
    "sg:classifiers":[
        {
            "category":"Restaurant",
            "type":"Food & Drink"
        }
    ],
    "sg:menulink":"http://www.allmenus.com/pa/philadelphia/292174-maple-tree-restaurant/menu/",
    "sg:phone":"+1 215 424 3336",
    "sg:postcode":"19138",
    "sg:province":"PA",
    "sg:tags":[
        "sandwich",
        "salad",
        "dessert",
        "seafood",
        "wrap",
        "chicken",
        "hoagy"
    ],
    "wof:name":"Maple Tree Restaurant",
    "wof:placetype":"venue"
},
  "geometry": {"coordinates":[-75.15885400000001,40.066169],"type":"Point"}
}