{
  "type": "Feature",
  "properties": {
    "addr:full":"496 Ben Franklin Rd S Indiana PA 15701",
    "addr:housenumber":"496",
    "addr:postcode":"15701",
    "addr:street":"Ben Franklin Rd",
    "iso:country":"US",
    "sg:address":"496 Ben Franklin Rd S",
    "sg:city":"Indiana",
    "sg:classifiers":[
        {
            "category":"Sports & Exercise",
            "subcategory":"Gym",
            "type":"Entertainment"
        }
    ],
    "sg:phone":"+1 724 463 2287",
    "sg:postcode":"15701",
    "sg:province":"PA",
    "sg:tags":[
        "club",
        "health",
        "studio",
        "gymnasium"
    ],
    "wof:name":"Curves For Women",
    "wof:placetype":"venue"
},
  "geometry": {"coordinates":[-79.18984399999999,40.611802],"type":"Point"}
}