{
  "type": "Feature",
  "properties": {
    "iso:country":"US",
    "sg:address":"800 River Rd",
    "sg:city":"Conshohocken",
    "sg:classifiers":[
        {
            "category":"Manufacturing",
            "subcategory":"Printing",
            "type":"Manufacturing & Wholesale Goods"
        }
    ],
    "sg:phone":"+1 610 292 6200",
    "sg:postcode":"19428",
    "sg:province":"PA",
    "sg:tags":[
        "newspaper"
    ],
    "sg:website":"www.phillynews.com",
    "wof:name":"Philadelphia Inquirer",
    "wof:placetype":"venue"
},
  "geometry": {"coordinates":[-75.27993499999999,40.075464],"type":"Point"}
}