{
  "type": "Feature",
  "properties": {
    "iso:country":"US",
    "sg:address":"4797 York Rd",
    "sg:city":"New Oxford",
    "sg:classifiers":[
        {
            "category":"Restaurant",
            "type":"Food & Drink"
        }
    ],
    "sg:phone":"+1 717 624 8987",
    "sg:postcode":"17350",
    "sg:province":"PA",
    "sg:tags":[
        "bar",
        "italian"
    ],
    "wof:name":"Scozzaros Old Mill Inn Inc",
    "wof:placetype":"venue"
},
  "geometry": {"coordinates":[-77.07079299999999,39.861738],"type":"Point"}
}