{
  "type": "Feature",
  "properties": {
    "iso:country":"US",
    "sg:address":"322 Bristol Pike",
    "sg:city":"Croydon",
    "sg:classifiers":[
        {
            "category":"Personal",
            "subcategory":"Beauty Salon",
            "type":"Services"
        }
    ],
    "sg:phone":"+1 215 788 5855",
    "sg:postcode":"19021",
    "sg:province":"PA",
    "sg:tags":[
        "hair",
        "stylist"
    ],
    "wof:name":"Unique Hair Designs",
    "wof:placetype":"venue"
},
  "geometry": {"coordinates":[-74.911407,40.093715],"type":"Point"}
}