{
  "type": "Feature",
  "properties": {
    "iso:country":"US",
    "sg:address":"106 Throop St",
    "sg:city":"Dunmore",
    "sg:classifiers":[
        {
            "category":"Shopping",
            "subcategory":"Gifts & Souvenirs",
            "type":"Retail Goods"
        }
    ],
    "sg:phone":"+1 570 558 4979",
    "sg:postcode":"18512",
    "sg:province":"PA",
    "sg:tags":[
        "shop"
    ],
    "wof:name":"Carly Indubidibly",
    "wof:placetype":"venue"
},
  "geometry": {"coordinates":[-75.626183,41.425021],"type":"Point"}
}