{
  "type": "Feature",
  "properties": {
    "iso:country":"US",
    "sg:address":"301 E City Ave",
    "sg:city":"Bala Cynwyd",
    "sg:classifiers":[
        {
            "category":"Health Services",
            "subcategory":"Doctor",
            "type":"Services"
        }
    ],
    "sg:phone":"+1 610 667 8708",
    "sg:postcode":"19004",
    "sg:province":"PA",
    "sg:tags":[
        "psychiatrist"
    ],
    "wof:name":"Psychoanalytic Center of Philadelphia",
    "wof:placetype":"venue"
},
  "geometry": {"coordinates":[-75.22020000000001,40.0042],"type":"Point"}
}