{
  "type": "Feature",
  "properties": {
    "iso:country":"US",
    "sg:address":"1208 S 4th St",
    "sg:city":"Allentown",
    "sg:classifiers":[
        {
            "category":"Restaurant",
            "type":"Food & Drink"
        }
    ],
    "sg:menulink":"http://www.allmenus.com/pa/allentown/133622-subway/menu/",
    "sg:phone":"+1 610 798 7878",
    "sg:postcode":"18103",
    "sg:province":"PA",
    "sg:tags":[
        "american",
        "sandwich"
    ],
    "wof:name":"Subway",
    "wof:placetype":"venue"
},
  "geometry": {"coordinates":[-75.460403,40.589835],"type":"Point"}
}