{
  "type": "Feature",
  "properties": {
    "iso:country":"US",
    "sg:address":"671 Hauger Rd",
    "sg:city":"Rockwood",
    "sg:classifiers":[
        {
            "category":"Arts & Performance",
            "subcategory":"Theater",
            "type":"Entertainment"
        }
    ],
    "sg:phone":"+1   ",
    "sg:postcode":"15557",
    "sg:province":"PA",
    "sg:tags":[
        "group"
    ],
    "wof:name":"Twentieth Century Productions",
    "wof:placetype":"venue"
},
  "geometry": {"coordinates":[-79.133518,39.917291],"type":"Point"}
}