{
  "type": "Feature",
  "properties": {
    "iso:country":"US",
    "sg:address":"273 Hemlock Rd",
    "sg:city":"Petrolia",
    "sg:classifiers":[
        {
            "category":"Building & Trades",
            "subcategory":"Landscaping Services",
            "type":"Services"
        }
    ],
    "sg:phone":"+1 724 753 2724",
    "sg:postcode":"16050",
    "sg:province":"PA",
    "wof:name":"Lessner Tree Svc",
    "wof:placetype":"venue"
},
  "geometry": {"coordinates":[-79.736746,41.041954],"type":"Point"}
}