{
  "type": "Feature",
  "properties": {
    "iso:country":"US",
    "sg:address":"8 S Wyoming Ave",
    "sg:city":"Kingston",
    "sg:classifiers":[
        {
            "category":"Shopping",
            "subcategory":"Clothing, Apparel, & Fashions",
            "type":"Retail Goods"
        }
    ],
    "sg:phone":"+1   ",
    "sg:postcode":"18704",
    "sg:province":"PA",
    "wof:name":"Shelby",
    "wof:placetype":"venue"
},
  "geometry": {"coordinates":[-75.89982999999999,41.25948],"type":"Point"}
}