{
  "type": "Feature",
  "properties": {
    "iso:country":"US",
    "sg:address":"1118 Bristol Pike",
    "sg:city":"Bensalem",
    "sg:classifiers":[
        {
            "category":"Building & Trades",
            "subcategory":"Construction",
            "type":"Services"
        }
    ],
    "sg:phone":"+1 215 244 8865",
    "sg:postcode":"19020",
    "sg:province":"PA",
    "sg:tags":[
        "concrete",
        "contractor"
    ],
    "wof:name":"Academy Concrete & Masonry Inc",
    "wof:placetype":"venue"
},
  "geometry": {"coordinates":[-74.968504,40.069431],"type":"Point"}
}