{
  "type": "Feature",
  "properties": {
    "iso:country":"US",
    "sg:address":"1425 Arch St Fl 3",
    "sg:city":"Philadelphia",
    "sg:classifiers":[
        {
            "category":"Professional",
            "subcategory":"Lawyer & Legal Services",
            "type":"Services"
        }
    ],
    "sg:phone":"+1 215 496 9530",
    "sg:postcode":"19102",
    "sg:province":"PA",
    "wof:name":"Self Inc",
    "wof:placetype":"venue"
},
  "geometry": {"coordinates":[-75.163597,39.954605],"type":"Point"}
}