{
  "type": "Feature",
  "properties": {
    "addr:full":"8771 Sipes Mill Rd Needmore PA 17238",
    "addr:housenumber":"8771",
    "addr:postcode":"17238",
    "addr:street":"Sipes Mill Rd",
    "iso:country":"US",
    "sg:address":"8771 Sipes Mill Rd",
    "sg:city":"Needmore",
    "sg:classifiers":[
        {
            "category":"Farming",
            "subcategory":"Livestock Farm",
            "type":"Manufacturing & Wholesale Goods"
        }
    ],
    "sg:phone":"+1   ",
    "sg:postcode":"17238",
    "sg:province":"PA",
    "sg:tags":[
        "beef",
        "corn",
        "crop",
        "general",
        "cattle",
        "feedlot"
    ],
    "wof:name":"Ralph Swope",
    "wof:placetype":"venue"
},
  "geometry": {"coordinates":[-78.138099,39.932751],"type":"Point"}
}