{
  "type": "Feature",
  "properties": {
    "iso:country":"US",
    "sg:address":"4210 Salem St",
    "sg:city":"Philadelphia",
    "sg:classifiers":[
        {
            "category":"Retail",
            "subcategory":"Auto Repair",
            "type":"Services"
        }
    ],
    "sg:phone":"+1 215 533 4112",
    "sg:postcode":"19124",
    "sg:province":"PA",
    "sg:tags":[
        "repairing",
        "automobile"
    ],
    "wof:name":"Motorworks Inc",
    "wof:placetype":"venue"
},
  "geometry": {"coordinates":[-75.088523,40.009778],"type":"Point"}
}