{
  "type": "Feature",
  "properties": {
    "addr:full":"356 E Butler Ave Ambler PA 19002",
    "addr:housenumber":"356",
    "addr:postcode":"19002",
    "addr:street":"E Butler Ave",
    "iso:country":"US",
    "sg:address":"356 E Butler Ave",
    "sg:city":"Ambler",
    "sg:classifiers":[
        {
            "category":"Manufacturing",
            "subcategory":"Metals",
            "type":"Manufacturing & Wholesale Goods"
        }
    ],
    "sg:phone":"+1   ",
    "sg:postcode":"19002",
    "sg:province":"PA",
    "sg:tags":[
        "weapon",
        "parts",
        "spare",
        "for",
        "mfg"
    ],
    "wof:name":"Facilities Inc",
    "wof:placetype":"venue"
},
  "geometry": {"coordinates":[-75.21490900000001,40.159329],"type":"Point"}
}