{
  "type": "Feature",
  "properties": {
    "iso:country":"US",
    "sg:address":"73 E Forrest Ave",
    "sg:city":"Shrewsbury",
    "sg:classifiers":[
        {
            "category":"Social Services",
            "type":"Services"
        }
    ],
    "sg:phone":"+1 717 235 0199",
    "sg:postcode":"17361",
    "sg:province":"PA",
    "sg:tags":[
        "counselor",
        "marriage",
        "family"
    ],
    "wof:name":"Crossroads Counseling & Ed",
    "wof:placetype":"venue"
},
  "geometry": {"coordinates":[-76.674398,39.770209],"type":"Point"}
}