{
  "type": "Feature",
  "properties": {
    "iso:country":"US",
    "sg:address":"2602 Myrtle St",
    "sg:city":"Erie",
    "sg:classifiers":[
        {
            "category":"Shopping",
            "subcategory":"Florist",
            "type":"Retail Goods"
        }
    ],
    "sg:phone":"+1 814 461 0904",
    "sg:postcode":"16508",
    "sg:province":"PA",
    "wof:name":"Larese Floral Design",
    "wof:placetype":"venue"
},
  "geometry": {"coordinates":[-80.07923099999999,42.108835],"type":"Point"}
}