{
  "type": "Feature",
  "properties": {
    "addr:full":"455 High St Brownsville PA 15417",
    "addr:housenumber":"455",
    "addr:postcode":"15417",
    "addr:street":"High St",
    "iso:country":"US",
    "sg:address":"455 High St",
    "sg:city":"Brownsville",
    "sg:classifiers":[
        {
            "category":"Professional",
            "subcategory":"Business Services",
            "type":"Services"
        }
    ],
    "sg:phone":"+1 724 785 2990",
    "sg:postcode":"15417",
    "sg:province":"PA",
    "sg:tags":[
        "notary",
        "public"
    ],
    "wof:name":"Melvin's Notary",
    "wof:placetype":"venue"
},
  "geometry": {"coordinates":[-79.894868,40.015996],"type":"Point"}
}