{
  "type": "Feature",
  "properties": {
    "addr:full":"8850 Lancaster Ave Bethel PA 19507",
    "addr:housenumber":"8850",
    "addr:postcode":"19507",
    "addr:street":"Lancaster Ave",
    "iso:country":"US",
    "sg:address":"8850 Lancaster Ave",
    "sg:city":"Bethel",
    "sg:classifiers":[
        {
            "category":"Manufacturing",
            "subcategory":"Apparel",
            "type":"Manufacturing & Wholesale Goods"
        }
    ],
    "sg:phone":"+1   ",
    "sg:postcode":"19507",
    "sg:province":"PA",
    "wof:name":"Appalachian Quilts",
    "wof:placetype":"venue"
},
  "geometry": {"coordinates":[-76.310518,40.487079],"type":"Point"}
}