{
  "type": "Feature",
  "properties": {
    "iso:country":"US",
    "sg:address":"312 Hemlock Dr",
    "sg:city":"Coraopolis",
    "sg:classifiers":[
        {
            "category":"Organizations",
            "subcategory":"Professional Association",
            "type":"Services"
        }
    ],
    "sg:phone":"+1 412 264 0922",
    "sg:postcode":"15108",
    "sg:province":"PA",
    "wof:name":"Mooncrest Neighborhood Assn",
    "wof:placetype":"venue"
},
  "geometry": {"coordinates":[-80.18719400000001,40.524816],"type":"Point"}
}