{
  "type": "Feature",
  "properties": {
    "iso:country":"US",
    "sg:address":"812 Krayn Rd",
    "sg:city":"Windber",
    "sg:classifiers":[
        {
            "category":"Building & Trades",
            "subcategory":"Construction",
            "type":"Services"
        }
    ],
    "sg:phone":"+1   ",
    "sg:postcode":"15963",
    "sg:province":"PA",
    "sg:tags":[
        "residential"
    ],
    "wof:name":"Young Rj Construction",
    "wof:placetype":"venue"
},
  "geometry": {"coordinates":[-78.74249,40.276071],"type":"Point"}
}