{
  "type": "Feature",
  "properties": {
    "iso:country":"US",
    "sg:address":"684 Stony Hill Rd",
    "sg:city":"Morrisville",
    "sg:classifiers":[
        {
            "category":"Retail",
            "subcategory":"Laundry & Dry Cleaning",
            "type":"Services"
        }
    ],
    "sg:phone":"+1 215 321 4400",
    "sg:postcode":"19067",
    "sg:province":"PA",
    "sg:tags":[
        "garment",
        "agent",
        "cleaners"
    ],
    "wof:name":"Custom Cleaners",
    "wof:placetype":"venue"
},
  "geometry": {"coordinates":[-74.86077899999999,40.216227],"type":"Point"}
}