{
  "type": "Feature",
  "properties": {
    "iso:country":"US",
    "sg:address":"326 Cedarville St",
    "sg:city":"Pittsburgh",
    "sg:classifiers":[
        {
            "category":"Health Services",
            "subcategory":"Nursing And Care Facility",
            "type":"Services"
        }
    ],
    "sg:phone":"+1   ",
    "sg:postcode":"15224",
    "sg:province":"PA",
    "wof:name":"Senior Friends Inc",
    "wof:placetype":"venue"
},
  "geometry": {"coordinates":[-79.950205,40.460202],"type":"Point"}
}