{
  "type": "Feature",
  "properties": {
    "addr:full":"525 Reservoir Rd Honey Brook PA 19344",
    "addr:housenumber":"525",
    "addr:postcode":"19344",
    "addr:street":"Reservoir Rd",
    "iso:country":"US",
    "sg:address":"525 Reservoir Rd",
    "sg:city":"Honey Brook",
    "sg:classifiers":[
        {
            "category":"Wholesale",
            "subcategory":"Home Furnishings",
            "type":"Manufacturing & Wholesale Goods"
        }
    ],
    "sg:phone":"+1   ",
    "sg:postcode":"19344",
    "sg:province":"PA",
    "wof:name":"Zooks Welding",
    "wof:placetype":"venue"
},
  "geometry": {"coordinates":[-75.929092,40.106355],"type":"Point"}
}