{
  "type": "Feature",
  "properties": {
    "iso:country":"US",
    "sg:address":"167 Municipal Rd",
    "sg:city":"Lehighton",
    "sg:classifiers":[
        {
            "category":"Government",
            "subcategory":"Office",
            "type":"Public Place"
        }
    ],
    "sg:phone":"+1 570 386 5735",
    "sg:postcode":"18235",
    "sg:province":"PA",
    "sg:tags":[
        "village"
    ],
    "sg:website":"www.eastpenntownship.tripod.com",
    "wof:name":"East Penn Twp Supervisors",
    "wof:placetype":"venue"
},
  "geometry": {"coordinates":[-75.76689,40.784518],"type":"Point"}
}