{
  "type": "Feature",
  "properties": {
    "addr:full":"1719 Willow Dr Easton PA 18040",
    "addr:housenumber":"1719",
    "addr:postcode":"18040",
    "addr:street":"Willow Dr",
    "iso:country":"US",
    "sg:address":"1719 Willow Dr",
    "sg:city":"Easton",
    "sg:classifiers":[
        {
            "category":"Building & Trades",
            "subcategory":"Construction",
            "type":"Services"
        }
    ],
    "sg:phone":"+1 610 250 9354",
    "sg:postcode":"18040",
    "sg:province":"PA",
    "sg:tags":[
        "carpentry",
        "contractor"
    ],
    "wof:name":"Timberline Construction",
    "wof:placetype":"venue"
},
  "geometry": {"coordinates":[-75.240893,40.714719],"type":"Point"}
}