{
  "type": "Feature",
  "properties": {
    "addr:full":"530 Parlin St Philadelphia PA 19116",
    "addr:housenumber":"530",
    "addr:postcode":"19116",
    "addr:street":"Parlin St",
    "iso:country":"US",
    "sg:address":"530 Parlin St",
    "sg:city":"Philadelphia",
    "sg:classifiers":[
        {
            "category":"Building & Trades",
            "subcategory":"Construction",
            "type":"Services"
        }
    ],
    "sg:phone":"+1 215 330 3391",
    "sg:postcode":"19116",
    "sg:province":"PA",
    "sg:tags":[
        "contractor"
    ],
    "wof:name":"Aklym Roofing & Siding",
    "wof:placetype":"venue"
},
  "geometry": {"coordinates":[-75.031189,40.11342],"type":"Point"}
}