{
  "type": "Feature",
  "properties": {
    "iso:country":"US",
    "sg:address":"401 Main St",
    "sg:city":"Shippenville",
    "sg:classifiers":[
        {
            "category":"Social Services",
            "subcategory":"Child Care",
            "type":"Services"
        }
    ],
    "sg:phone":"+1 814 782 3037",
    "sg:postcode":"16254",
    "sg:province":"PA",
    "sg:tags":[
        "day"
    ],
    "wof:name":"Swartzfager Child Care",
    "wof:placetype":"venue"
},
  "geometry": {"coordinates":[-79.461624,41.250862],"type":"Point"}
}