{
  "type": "Feature",
  "properties": {
    "addr:full":"809 State Rte 288 Fombell PA 16123",
    "addr:housenumber":"809",
    "addr:postcode":"16123",
    "addr:street":"State Rte 288",
    "iso:country":"US",
    "sg:address":"809 State Rte 288",
    "sg:city":"Fombell",
    "sg:classifiers":[
        {
            "category":"Manufacturing",
            "subcategory":"Glass & Minerals",
            "type":"Manufacturing & Wholesale Goods"
        },
        {
            "category":"Manufacturing",
            "subcategory":"Rubber & Plastics",
            "type":"Manufacturing & Wholesale Goods"
        }
    ],
    "sg:phone":"+1 724 752 2268",
    "sg:postcode":"16123",
    "sg:province":"PA",
    "sg:tags":[
        "product",
        "fiber",
        "sheet",
        "mfg",
        "fabricated",
        "fabricator",
        "metalwork"
    ],
    "wof:name":"Formed Fiberglass Co Inc",
    "wof:placetype":"venue"
},
  "geometry": {"coordinates":[-80.211035,40.838999],"type":"Point"}
}