{
  "type": "Feature",
  "properties": {
    "iso:country":"US",
    "sg:address":"2040 Linglestown Rd",
    "sg:city":"Harrisburg",
    "sg:classifiers":[
        {
            "category":"Organizations",
            "subcategory":"Professional Association",
            "type":"Services"
        }
    ],
    "sg:phone":"+1   ",
    "sg:postcode":"17110",
    "sg:province":"PA",
    "sg:tags":[
        "assoc"
    ],
    "wof:name":"American Diabetes Association",
    "wof:placetype":"venue"
},
  "geometry": {"coordinates":[-76.86689699999999,40.328518],"type":"Point"}
}