{
  "type": "Feature",
  "properties": {
    "addr:full":"347 Main St Dickson City PA 18519",
    "addr:housenumber":"347",
    "addr:postcode":"18519",
    "addr:street":"Main St",
    "iso:country":"US",
    "sg:address":"347 Main St",
    "sg:city":"Dickson City",
    "sg:classifiers":[
        {
            "category":"Retail",
            "subcategory":"Auto Repair",
            "type":"Services"
        }
    ],
    "sg:phone":"+1 570 489 9912",
    "sg:postcode":"18519",
    "sg:province":"PA",
    "sg:tags":[
        "trailer"
    ],
    "wof:name":"Red Line Leasing Corp",
    "wof:placetype":"venue"
},
  "geometry": {"coordinates":[-75.634276,41.453],"type":"Point"}
}