{
  "type": "Feature",
  "properties": {
    "iso:country":"US",
    "sg:address":"110 Doyle St",
    "sg:city":"Doylestown",
    "sg:classifiers":[
        {
            "category":"Manufacturing",
            "subcategory":"Metals",
            "type":"Manufacturing & Wholesale Goods"
        }
    ],
    "sg:phone":"+1   ",
    "sg:postcode":"18901",
    "sg:province":"PA",
    "sg:tags":[
        "machine",
        "screw",
        "parts",
        "mfg"
    ],
    "wof:name":"Chris Machine Co Inc",
    "wof:placetype":"venue"
},
  "geometry": {"coordinates":[-75.134072,40.314396],"type":"Point"}
}