{
  "type": "Feature",
  "properties": {
    "iso:country":"US",
    "sg:address":"156 Lancaster Ave",
    "sg:city":"Columbia",
    "sg:classifiers":[
        {
            "category":"Government",
            "subcategory":"Court House",
            "type":"Public Place"
        }
    ],
    "sg:phone":"+1   ",
    "sg:postcode":"17512",
    "sg:province":"PA",
    "wof:name":"Magisterial District 02-1-03",
    "wof:placetype":"venue"
},
  "geometry": {"coordinates":[-76.495806,40.032632],"type":"Point"}
}