{
  "type": "Feature",
  "properties": {
    "addr:full":"2301 Race St Philadelphia PA 19103",
    "addr:housenumber":"2301",
    "addr:postcode":"19103",
    "addr:street":"Race St",
    "iso:country":"US",
    "sg:address":"2301 Race St",
    "sg:city":"Philadelphia",
    "sg:classifiers":[
        {
            "category":"Parking",
            "type":"Transportation"
        }
    ],
    "sg:phone":"+1 215 567 1556",
    "sg:postcode":"19103",
    "sg:province":"PA",
    "wof:name":"Martin's Parking",
    "wof:placetype":"venue"
},
  "geometry": {"coordinates":[-75.1772,39.957901],"type":"Point"}
}