{
  "type": "Feature",
  "properties": {
    "iso:country":"US",
    "sg:address":"655 Penn Green Rd",
    "sg:city":"Landenberg",
    "sg:classifiers":[
        {
            "category":"Retail",
            "subcategory":"Auto Repair",
            "type":"Services"
        }
    ],
    "sg:phone":"+1 610 274 8724",
    "sg:postcode":"19350",
    "sg:province":"PA",
    "wof:name":"Dave's Auto Service",
    "wof:placetype":"venue"
},
  "geometry": {"coordinates":[-75.76979799999999,39.7985],"type":"Point"}
}