{
  "type": "Feature",
  "properties": {
    "iso:country":"US",
    "sg:address":"7552 Ruth Farm Ln",
    "sg:city":"Thomasville",
    "sg:classifiers":[
        {
            "category":"Building & Trades",
            "subcategory":"Electrical",
            "type":"Services"
        }
    ],
    "sg:phone":"+1 717 259 0921",
    "sg:postcode":"17364",
    "sg:province":"PA",
    "sg:tags":[
        "electrical",
        "contractor"
    ],
    "wof:name":"Boyer Electric",
    "wof:placetype":"venue"
},
  "geometry": {"coordinates":[-76.950536,39.926064],"type":"Point"}
}