{
  "type": "Feature",
  "properties": {
    "iso:country":"US",
    "sg:address":"201 Turkey Ridge Rd",
    "sg:city":"Millerstown",
    "sg:classifiers":[
        {
            "category":"Farming",
            "subcategory":"Livestock Farm",
            "type":"Manufacturing & Wholesale Goods"
        }
    ],
    "sg:phone":"+1   ",
    "sg:postcode":"17062",
    "sg:province":"PA",
    "sg:tags":[
        "feedlot",
        "hog",
        "or",
        "beef",
        "cattle"
    ],
    "wof:name":"Glenn Benner",
    "wof:placetype":"venue"
},
  "geometry": {"coordinates":[-77.112432,40.585083],"type":"Point"}
}