{
  "type": "Feature",
  "properties": {
    "iso:country":"US",
    "sg:address":"9600 Perry Hwy",
    "sg:city":"Pittsburgh",
    "sg:classifiers":[
        {
            "category":"Shopping",
            "subcategory":"Musical Instruments",
            "type":"Retail Goods"
        }
    ],
    "sg:phone":"+1 412 366 3631",
    "sg:postcode":"15237",
    "sg:province":"PA",
    "sg:tags":[
        "novelty",
        "gift"
    ],
    "sg:website":"www.musikinnovations.com",
    "wof:name":"Musik Innovations",
    "wof:placetype":"venue"
},
  "geometry": {"coordinates":[-80.037847,40.581043],"type":"Point"}
}