{
  "type": "Feature",
  "properties": {
    "addr:full":"3760 William Penn Hwy Monroeville PA 15146",
    "addr:housenumber":"3760",
    "addr:postcode":"15146",
    "addr:street":"William Penn Hwy",
    "iso:country":"US",
    "sg:address":"3760 William Penn Hwy",
    "sg:city":"Monroeville",
    "sg:classifiers":[
        {
            "category":"Restaurant",
            "type":"Food & Drink"
        }
    ],
    "sg:menulink":"http://www.allmenus.com/pa/monroeville/206663-mcdonalds/menu/",
    "sg:phone":"+1 412 856 0264",
    "sg:postcode":"15146",
    "sg:province":"PA",
    "sg:tags":[
        "burger",
        "american"
    ],
    "wof:name":"McDonald's",
    "wof:placetype":"venue"
},
  "geometry": {"coordinates":[-79.786683,40.435713],"type":"Point"}
}