{
  "type": "Feature",
  "properties": {
    "addr:full":"PO Box 509 Allentown PA 18105",
    "addr:housenumber":"po",
    "addr:postcode":"18105",
    "addr:street":"Box 509",
    "iso:country":"US",
    "sg:address":"PO Box 509",
    "sg:city":"Allentown",
    "sg:classifiers":[
        {
            "category":"Building & Trades",
            "subcategory":"Construction",
            "type":"Services"
        }
    ],
    "sg:phone":"+1 610 395 6871",
    "sg:postcode":"18105",
    "sg:province":"PA",
    "sg:tags":[
        "contractor"
    ],
    "sg:website":"www.butz.com",
    "wof:name":"Butz Alvin H Inc",
    "wof:placetype":"venue"
},
  "geometry": {"coordinates":[-75.472099,40.602001],"type":"Point"}
}