{
  "type": "Feature",
  "properties": {
    "iso:country":"US",
    "sg:address":"935 Jacks Ln",
    "sg:city":"Orwigsburg",
    "sg:classifiers":[
        {
            "category":"Wholesale",
            "subcategory":"Painting Supplies",
            "type":"Manufacturing & Wholesale Goods"
        },
        {
            "category":"Home & Garden",
            "subcategory":"Building Materials",
            "type":"Retail Goods"
        }
    ],
    "sg:phone":"+1 570 366 1005",
    "sg:postcode":"17961",
    "sg:province":"PA",
    "sg:tags":[
        "paint",
        "wallpaper",
        "wallcoverings"
    ],
    "wof:name":"David R Everly Sales",
    "wof:placetype":"venue"
},
  "geometry": {"coordinates":[-76.093156,40.662529],"type":"Point"}
}