{
  "type": "Feature",
  "properties": {
    "iso:country":"US",
    "sg:address":"517 E 12th St",
    "sg:city":"Erie",
    "sg:classifiers":[
        {
            "category":"Organizations",
            "subcategory":"Religious Organization",
            "type":"Services"
        }
    ],
    "sg:phone":"+1   ",
    "sg:postcode":"16503",
    "sg:province":"PA",
    "wof:name":"Saint Stanislaus Convent",
    "wof:placetype":"venue"
},
  "geometry": {"coordinates":[-80.06834000000001,42.12815],"type":"Point"}
}