{
  "type": "Feature",
  "properties": {
    "iso:country":"US",
    "sg:address":"100 E Centre St",
    "sg:city":"Mahanoy City",
    "sg:classifiers":[
        {
            "category":"Professional",
            "subcategory":"Lawyer & Legal Services",
            "type":"Services"
        }
    ],
    "sg:phone":"+1 570 773 3870",
    "sg:postcode":"17948",
    "sg:province":"PA",
    "sg:tags":[
        "attorney"
    ],
    "wof:name":"Noonan Law Offices",
    "wof:placetype":"venue"
},
  "geometry": {"coordinates":[-76.139618,40.813114],"type":"Point"}
}