{
  "type": "Feature",
  "properties": {
    "iso:country":"US",
    "sg:address":"280 E Fayette St",
    "sg:city":"Uniontown",
    "sg:classifiers":[
        {
            "category":"Organizations",
            "subcategory":"Political Organization",
            "type":"Services"
        }
    ],
    "sg:phone":"+1 724 425 2993",
    "sg:postcode":"15401",
    "sg:province":"PA",
    "wof:name":"Larry Roberts Campaign",
    "wof:placetype":"venue"
},
  "geometry": {"coordinates":[-79.71588199999999,39.894949],"type":"Point"}
}