{
  "type": "Feature",
  "properties": {
    "iso:country":"US",
    "sg:address":"118 Pleasant Acres Rd",
    "sg:city":"York",
    "sg:classifiers":[
        {
            "category":"Health Services",
            "subcategory":"Medical Lab",
            "type":"Services"
        }
    ],
    "sg:phone":"+1 717 751 0394",
    "sg:postcode":"17402",
    "sg:province":"PA",
    "sg:tags":[
        "x"
    ],
    "wof:name":"Mobile X-Ray Imaging",
    "wof:placetype":"venue"
},
  "geometry": {"coordinates":[-76.648901,39.989697],"type":"Point"}
}