{
  "type": "Feature",
  "properties": {
    "iso:country":"US",
    "sg:address":"890 Cortleigh Dr",
    "sg:city":"York",
    "sg:classifiers":[
        {
            "category":"Professional",
            "subcategory":"Engineering",
            "type":"Services"
        }
    ],
    "sg:phone":"+1   ",
    "sg:postcode":"17402",
    "sg:province":"PA",
    "sg:tags":[
        "equipment",
        "industrial"
    ],
    "wof:name":"Protosight Inc",
    "wof:placetype":"venue"
},
  "geometry": {"coordinates":[-76.663203,39.961759],"type":"Point"}
}