{
  "type": "Feature",
  "properties": {
    "iso:country":"US",
    "sg:address":"1020 Mount Jackson Rd",
    "sg:city":"New Castle",
    "sg:classifiers":[
        {
            "category":"Building & Trades",
            "subcategory":"Construction",
            "type":"Services"
        }
    ],
    "sg:phone":"+1   ",
    "sg:postcode":"16102",
    "sg:province":"PA",
    "sg:tags":[
        "house"
    ],
    "wof:name":"Jeffrey D Smith Construction",
    "wof:placetype":"venue"
},
  "geometry": {"coordinates":[-80.436466,40.962069],"type":"Point"}
}