{
  "type": "Feature",
  "properties": {
    "iso:country":"US",
    "sg:address":"50 S 25th St",
    "sg:city":"Pittsburgh",
    "sg:classifiers":[
        {
            "category":"Manufacturing",
            "subcategory":"Tools & Machinery",
            "type":"Manufacturing & Wholesale Goods"
        }
    ],
    "sg:phone":"+1 412 381 3322",
    "sg:postcode":"15203",
    "sg:province":"PA",
    "sg:tags":[
        "machine",
        "shop"
    ],
    "wof:name":"M J Machining & Fabricating Co",
    "wof:placetype":"venue"
},
  "geometry": {"coordinates":[-79.969639,40.428379],"type":"Point"}
}