{
  "type": "Feature",
  "properties": {
    "iso:country":"US",
    "sg:address":"205 Berkeley Rd",
    "sg:city":"Glenside",
    "sg:classifiers":[
        {
            "category":"Building & Trades",
            "subcategory":"Landscaping Services",
            "type":"Services"
        }
    ],
    "sg:phone":"+1   ",
    "sg:postcode":"19038",
    "sg:province":"PA",
    "sg:tags":[
        "landscape"
    ],
    "wof:name":"Thinkgreen LLC",
    "wof:placetype":"venue"
},
  "geometry": {"coordinates":[-75.161387,40.10075],"type":"Point"}
}