{
  "type": "Feature",
  "properties": {
    "iso:country":"US",
    "sg:address":"609 Cedar Ave",
    "sg:city":"Lansdowne",
    "sg:classifiers":[
        {
            "category":"Deli",
            "type":"Food & Drink"
        }
    ],
    "sg:phone":"+1 610 622 0228",
    "sg:postcode":"19050",
    "sg:province":"PA",
    "wof:name":"Trio Cold Cuts Yeadon",
    "wof:placetype":"venue"
},
  "geometry": {"coordinates":[-75.25460099999999,39.921001],"type":"Point"}
}