{
  "type": "Feature",
  "properties": {
    "iso:country":"US",
    "sg:address":"234 Hermitage St",
    "sg:city":"Philadelphia",
    "sg:classifiers":[
        {
            "category":"Organizations",
            "subcategory":"Religious Organization",
            "type":"Services"
        }
    ],
    "sg:phone":"+1 215 482 0450",
    "sg:postcode":"19127",
    "sg:province":"PA",
    "sg:tags":[
        "church"
    ],
    "wof:name":"Holy Family Church",
    "wof:placetype":"venue"
},
  "geometry": {"coordinates":[-75.22856400000001,40.032335],"type":"Point"}
}