{
  "type": "Feature",
  "properties": {
    "iso:country":"US",
    "sg:address":"2851 Bedford Ave",
    "sg:city":"Pittsburgh",
    "sg:classifiers":[
        {
            "category":"Social Services",
            "subcategory":"Child Care",
            "type":"Services"
        }
    ],
    "sg:phone":"+1 412 621 9434",
    "sg:postcode":"15219",
    "sg:province":"PA",
    "wof:name":"Heavenly Care Day Care",
    "wof:placetype":"venue"
},
  "geometry": {"coordinates":[-79.968108,40.45263],"type":"Point"}
}