{
  "type": "Feature",
  "properties": {
    "iso:country":"US",
    "sg:address":"637 E Pittsburgh St",
    "sg:city":"Greensburg",
    "sg:classifiers":[
        {
            "category":"Building & Trades",
            "subcategory":"Construction",
            "type":"Services"
        }
    ],
    "sg:phone":"+1   ",
    "sg:postcode":"15601",
    "sg:province":"PA",
    "sg:tags":[
        "roofing",
        "siding",
        "commercial",
        "contractor"
    ],
    "wof:name":"Carlsons Cnstr & Ldscpg Co",
    "wof:placetype":"venue"
},
  "geometry": {"coordinates":[-79.53156199999999,40.303053],"type":"Point"}
}