{
  "type": "Feature",
  "properties": {
    "iso:country":"US",
    "sg:address":"922 W Courtland St",
    "sg:city":"Philadelphia",
    "sg:classifiers":[
        {
            "category":"Health Services",
            "subcategory":"Doctor",
            "type":"Services"
        }
    ],
    "sg:phone":"+1 215 324 8955",
    "sg:postcode":"19140",
    "sg:province":"PA",
    "wof:name":"Turner Donald F DO",
    "wof:placetype":"venue"
},
  "geometry": {"coordinates":[-75.14009900000001,40.021999],"type":"Point"}
}