{
  "type": "Feature",
  "properties": {
    "iso:country":"US",
    "sg:address":"1027 Borbeck Ave",
    "sg:city":"Philadelphia",
    "sg:classifiers":[
        {
            "category":"Professional",
            "type":"Services"
        }
    ],
    "sg:phone":"+1   ",
    "sg:postcode":"19111",
    "sg:province":"PA",
    "wof:name":"John Stenger",
    "wof:placetype":"venue"
},
  "geometry": {"coordinates":[-75.07513899999999,40.068736],"type":"Point"}
}