{
  "type": "Feature",
  "properties": {
    "iso:country":"US",
    "sg:address":"398 E Liberty St",
    "sg:city":"Schuylkill Haven",
    "sg:classifiers":[
        {
            "category":"Wholesale",
            "subcategory":"Fruits & Vegetables",
            "type":"Manufacturing & Wholesale Goods"
        }
    ],
    "sg:phone":"+1   ",
    "sg:postcode":"17972",
    "sg:province":"PA",
    "sg:tags":[
        "fresh"
    ],
    "wof:name":"Bedway Banana Boat Inc",
    "wof:placetype":"venue"
},
  "geometry": {"coordinates":[-76.161804,40.629374],"type":"Point"}
}