{
  "type": "Feature",
  "properties": {
    "addr:full":"751 Wallace Ave Wilkinsburg PA 15221",
    "addr:housenumber":"751",
    "addr:postcode":"15221",
    "addr:street":"Wallace Ave",
    "iso:country":"US",
    "sg:address":"751 Wallace Ave",
    "sg:city":"Wilkinsburg",
    "sg:classifiers":[
        {
            "category":"Education",
            "subcategory":"School",
            "type":"Public Place"
        }
    ],
    "sg:phone":"+1 412 371 0192",
    "sg:postcode":"15221",
    "sg:province":"PA",
    "wof:name":"Wilkinsburg Academy",
    "wof:placetype":"venue"
},
  "geometry": {"coordinates":[-79.881765,40.443732],"type":"Point"}
}