{
  "type": "Feature",
  "properties": {
    "addr:full":"1259 Route 113 Hilltown PA 18927",
    "addr:housenumber":"1259",
    "addr:postcode":"18927",
    "addr:street":"Route 113",
    "iso:country":"US",
    "sg:address":"1259 Route 113",
    "sg:city":"Hilltown",
    "sg:classifiers":[
        {
            "category":"Professional",
            "subcategory":"Lawyer & Legal Services",
            "type":"Services"
        }
    ],
    "sg:phone":"+1 215 453 5801",
    "sg:postcode":"18927",
    "sg:province":"PA",
    "sg:tags":[
        "divorce",
        "law",
        "family"
    ],
    "wof:name":"Link Richard Attorney",
    "wof:placetype":"venue"
},
  "geometry": {"coordinates":[-75.25357700000001,40.366233],"type":"Point"}
}