{
  "type": "Feature",
  "properties": {
    "iso:country":"US",
    "sg:address":"2019 Walnut St",
    "sg:city":"Philadelphia",
    "sg:classifiers":[
        {
            "category":"Professional",
            "subcategory":"Lawyer & Legal Services",
            "type":"Services"
        }
    ],
    "sg:phone":"+1 215 864 9300",
    "sg:postcode":"19103",
    "sg:province":"PA",
    "sg:tags":[
        "attorney"
    ],
    "wof:name":"Stephen C Josel & Assoc",
    "wof:placetype":"venue"
},
  "geometry": {"coordinates":[-75.175455,39.950799],"type":"Point"}
}