{
  "type": "Feature",
  "properties": {
    "addr:full":"738 Highland Ave Latrobe PA 15650",
    "addr:housenumber":"738",
    "addr:postcode":"15650",
    "addr:street":"Highland Ave",
    "iso:country":"US",
    "sg:address":"738 Highland Ave",
    "sg:city":"Latrobe",
    "sg:classifiers":[
        {
            "category":"Real Estate",
            "subcategory":"Real Estate Agent",
            "type":"Services"
        }
    ],
    "sg:phone":"+1 724 537 3910",
    "sg:postcode":"15650",
    "sg:province":"PA",
    "sg:tags":[
        "inspection"
    ],
    "wof:name":"P A One",
    "wof:placetype":"venue"
},
  "geometry": {"coordinates":[-79.377745,40.320502],"type":"Point"}
}