{
  "type": "Feature",
  "properties": {
    "iso:country":"US",
    "sg:address":"101 Jude Dr",
    "sg:city":"Pittsburgh",
    "sg:classifiers":[
        {
            "category":"Restaurant",
            "type":"Food & Drink"
        }
    ],
    "sg:phone":"+1   ",
    "sg:postcode":"15237",
    "sg:province":"PA",
    "wof:name":"Redman Enterprises Inc",
    "wof:placetype":"venue"
},
  "geometry": {"coordinates":[-80.02357499999999,40.548185],"type":"Point"}
}