{
  "type": "Feature",
  "properties": {
    "addr:full":"33 S 4th St Hamburg PA 19526",
    "addr:housenumber":"33",
    "addr:postcode":"19526",
    "addr:street":"S 4Th St",
    "iso:country":"US",
    "sg:address":"33 S 4th St",
    "sg:city":"Hamburg",
    "sg:classifiers":[
        {
            "category":"Banks & Credit Unions",
            "subcategory":"Bank",
            "type":"Services"
        }
    ],
    "sg:phone":"+1 610 562 4466",
    "sg:postcode":"19526",
    "sg:province":"PA",
    "wof:name":"First National Bank In Fltwd",
    "wof:placetype":"venue"
},
  "geometry": {"coordinates":[-75.98215399999999,40.554702],"type":"Point"}
}