{
  "type": "Feature",
  "properties": {
    "addr:full":"906 Kedron Ave Morton PA 19070",
    "addr:housenumber":"906",
    "addr:postcode":"19070",
    "addr:street":"Kedron Ave",
    "iso:country":"US",
    "sg:address":"906 Kedron Ave",
    "sg:city":"Morton",
    "sg:classifiers":[
        {
            "category":"Internet Cafe",
            "subcategory":"None",
            "type":"Food & Drink"
        },
        {
            "category":"Professional",
            "subcategory":"Computer Services",
            "type":"Services"
        }
    ],
    "sg:phone":"+1 610 543 7725",
    "sg:postcode":"19070",
    "sg:province":"PA",
    "sg:tags":[
        "product",
        "designer",
        "network",
        "consultant",
        "system",
        "design",
        "software"
    ],
    "wof:name":"Lucid Tech Inc",
    "wof:placetype":"venue"
},
  "geometry": {"coordinates":[-75.32382200000001,39.904991],"type":"Point"}
}