{
  "type": "Feature",
  "properties": {
    "iso:country":"US",
    "sg:address":"941 Perry Hwy",
    "sg:city":"Pittsburgh",
    "sg:classifiers":[
        {
            "category":"Retail",
            "subcategory":"Auto Repair",
            "type":"Services"
        }
    ],
    "sg:phone":"+1 412 364 4799",
    "sg:postcode":"15237",
    "sg:province":"PA",
    "sg:tags":[
        "repairing",
        "automobile"
    ],
    "wof:name":"Tevis Auto Svc",
    "wof:placetype":"venue"
},
  "geometry": {"coordinates":[-80.03596400000001,40.535582],"type":"Point"}
}