{
  "type": "Feature",
  "properties": {
    "iso:country":"US",
    "sg:address":"95 Wood St",
    "sg:city":"Bristol",
    "sg:classifiers":[
        {
            "category":"Organizations",
            "subcategory":"Community Association",
            "type":"Services"
        }
    ],
    "sg:phone":"+1   ",
    "sg:postcode":"19007",
    "sg:province":"PA",
    "sg:tags":[
        "membership",
        "fraternal",
        "civic"
    ],
    "wof:name":"Bristol Elks Lodge 970",
    "wof:placetype":"venue"
},
  "geometry": {"coordinates":[-74.858807,40.095256],"type":"Point"}
}