{
  "type": "Feature",
  "properties": {
    "addr:full":"995 Greentree Rd Pittsburgh PA 15220",
    "addr:housenumber":"995",
    "addr:postcode":"15220",
    "addr:street":"Greentree Rd",
    "iso:country":"US",
    "sg:address":"995 Greentree Rd",
    "sg:city":"Pittsburgh",
    "sg:classifiers":[
        {
            "category":"Health Services",
            "subcategory":"Hospital",
            "type":"Services"
        }
    ],
    "sg:phone":"+1 412 920 0100",
    "sg:postcode":"15220",
    "sg:province":"PA",
    "sg:website":"www.hfimaging.com",
    "wof:name":"High Field Imaging",
    "wof:placetype":"venue"
},
  "geometry": {"coordinates":[-80.044842,40.416981],"type":"Point"}
}