{
  "type": "Feature",
  "properties": {
    "addr:full":"2750 Egypt Rd Norristown PA 19403",
    "addr:housenumber":"2750",
    "addr:postcode":"19403",
    "addr:street":"Egypt Rd",
    "iso:country":"US",
    "sg:address":"2750 Egypt Rd",
    "sg:city":"Norristown",
    "sg:classifiers":[
        {
            "category":"Sports & Exercise",
            "subcategory":"Golf",
            "type":"Entertainment"
        }
    ],
    "sg:phone":"+1 610 666 7602",
    "sg:postcode":"19403",
    "sg:province":"PA",
    "sg:tags":[
        "course"
    ],
    "wof:name":"The General Washington",
    "wof:placetype":"venue"
},
  "geometry": {"coordinates":[-75.423107,40.129171],"type":"Point"}
}