{
  "type": "Feature",
  "properties": {
    "addr:full":"4444 Buffalo Rd Erie PA 16510",
    "addr:housenumber":"4444",
    "addr:postcode":"16510",
    "addr:street":"Buffalo Rd",
    "iso:country":"US",
    "sg:address":"4444 Buffalo Rd",
    "sg:city":"Erie",
    "sg:classifiers":[
        {
            "category":"Restaurant",
            "type":"Food & Drink"
        }
    ],
    "sg:menulink":"http://www.allmenus.com/pa/harborcreek/214834-ponderosa-steak-house/menu/",
    "sg:phone":"+1 814 899 8856",
    "sg:postcode":"16510",
    "sg:province":"PA",
    "sg:tags":[
        "american",
        "steakhouse"
    ],
    "wof:name":"Ponderosa Steak House",
    "wof:placetype":"venue"
},
  "geometry": {"coordinates":[-80.001668,42.147919],"type":"Point"}
}