{
  "type": "Feature",
  "properties": {
    "iso:country":"US",
    "sg:address":"1123 Vancar Dr",
    "sg:city":"Bethel Park",
    "sg:classifiers":[
        {
            "category":"Professional",
            "subcategory":"Advertising",
            "type":"Services"
        }
    ],
    "sg:phone":"+1   ",
    "sg:postcode":"15102",
    "sg:province":"PA",
    "sg:tags":[
        "agency"
    ],
    "wof:name":"Pittsburgh Advertising Sp",
    "wof:placetype":"venue"
},
  "geometry": {"coordinates":[-80.033518,40.315704],"type":"Point"}
}