{
  "type": "Feature",
  "properties": {
    "iso:country":"US",
    "sg:address":"3615 Burgoon Rd",
    "sg:city":"Altoona",
    "sg:classifiers":[
        {
            "category":"Professional",
            "subcategory":"Lawyer & Legal Services",
            "type":"Services"
        }
    ],
    "sg:phone":"+1   ",
    "sg:postcode":"16602",
    "sg:province":"PA",
    "wof:name":"George Terressa E",
    "wof:placetype":"venue"
},
  "geometry": {"coordinates":[-78.411345,40.48785],"type":"Point"}
}