{
  "type": "Feature",
  "properties": {
    "iso:country":"US",
    "sg:address":"419 W 4th St",
    "sg:city":"Williamsport",
    "sg:classifiers":[
        {
            "category":"Utilities",
            "subcategory":"Mobile Phone",
            "type":"Services"
        }
    ],
    "sg:phone":"+1 570 323 2337",
    "sg:postcode":"17701",
    "sg:province":"PA",
    "sg:tags":[
        "paging",
        "carrier",
        "signaling"
    ],
    "wof:name":"Checkpoint Communications Co",
    "wof:placetype":"venue"
},
  "geometry": {"coordinates":[-77.009944,41.23995],"type":"Point"}
}