{
  "type": "Feature",
  "properties": {
    "addr:full":"1620 New London Rd Landenberg PA 19350",
    "addr:housenumber":"1620",
    "addr:postcode":"19350",
    "addr:street":"New London Rd",
    "iso:country":"US",
    "sg:address":"1620 New London Rd",
    "sg:city":"Landenberg",
    "sg:classifiers":[
        {
            "category":"Building & Trades",
            "subcategory":"Construction",
            "type":"Services"
        }
    ],
    "sg:phone":"+1 610 255 3870",
    "sg:postcode":"19350",
    "sg:province":"PA",
    "sg:tags":[
        "maintenance",
        "contractor"
    ],
    "wof:name":"Chisel Creek Golf Maintenance",
    "wof:placetype":"venue"
},
  "geometry": {"coordinates":[-75.811088,39.746579],"type":"Point"}
}