{
  "type": "Feature",
  "properties": {
    "addr:full":"940 Town Center Dr Langhorne PA 19047",
    "addr:housenumber":"940",
    "addr:postcode":"19047",
    "addr:street":"Town Center Dr",
    "iso:country":"US",
    "sg:address":"940 Town Center Dr",
    "sg:city":"Langhorne",
    "sg:classifiers":[
        {
            "category":"Retail",
            "subcategory":"Animal Services",
            "type":"Services"
        }
    ],
    "sg:phone":"+1 215 891 1630",
    "sg:postcode":"19047",
    "sg:province":"PA",
    "sg:tags":[
        "pet"
    ],
    "wof:name":"Bucks County Partners In Pet",
    "wof:placetype":"venue"
},
  "geometry": {"coordinates":[-74.881591,40.187445],"type":"Point"}
}