{
  "type": "Feature",
  "properties": {
    "iso:country":"US",
    "sg:address":"2733 W Emaus Ave Ste 5",
    "sg:city":"Allentown",
    "sg:classifiers":[
        {
            "category":"Shopping",
            "subcategory":"Clothing, Apparel, & Fashions",
            "type":"Retail Goods"
        }
    ],
    "sg:phone":"+1 610 709 9993",
    "sg:postcode":"18103",
    "sg:province":"PA",
    "wof:name":"The Beauty Bar Specialty Shop",
    "wof:placetype":"venue"
},
  "geometry": {"coordinates":[-75.47788300000001,40.561493],"type":"Point"}
}