{
  "type": "Feature",
  "properties": {
    "iso:country":"US",
    "sg:address":"1776 N Broad St",
    "sg:city":"Philadelphia",
    "sg:classifiers":[
        {
            "category":"Arts & Performance",
            "subcategory":"Art Gallery",
            "type":"Entertainment"
        }
    ],
    "sg:phone":"+1 215 236 0993",
    "sg:postcode":"19121",
    "sg:province":"PA",
    "wof:name":"Barrington Consultants",
    "wof:placetype":"venue"
},
  "geometry": {"coordinates":[-75.157787,39.979892],"type":"Point"}
}