{
  "type": "Feature",
  "properties": {
    "addr:full":"126 S Wyomissing Ave Reading PA 19607",
    "addr:housenumber":"126",
    "addr:postcode":"19607",
    "addr:street":"S Wyomissing Ave",
    "iso:country":"US",
    "sg:address":"126 S Wyomissing Ave",
    "sg:city":"Reading",
    "sg:classifiers":[
        {
            "category":"Manufacturing",
            "subcategory":"Tools & Machinery",
            "type":"Manufacturing & Wholesale Goods"
        },
        {
            "category":"Industrial Area",
            "type":"Public Place"
        }
    ],
    "sg:phone":"+1 610 223 2083",
    "sg:postcode":"19607",
    "sg:province":"PA",
    "sg:tags":[
        "repair",
        "equipment-repairing",
        "machinery-rebuild"
    ],
    "wof:name":"V & G. Sound Mach.",
    "wof:placetype":"venue"
},
  "geometry": {"coordinates":[-75.974101,40.303051],"type":"Point"}
}