{
  "type": "Feature",
  "properties": {
    "iso:country":"US",
    "sg:address":"117 S 17th St Ste 407",
    "sg:city":"Philadelphia",
    "sg:classifiers":[
        {
            "category":"Health Services",
            "subcategory":"Chiropractor",
            "type":"Services"
        }
    ],
    "sg:phone":"+1 215 563 8843",
    "sg:postcode":"19103",
    "sg:province":"PA",
    "wof:name":"Snyman Basil Chiropractic Office",
    "wof:placetype":"venue"
},
  "geometry": {"coordinates":[-75.16889999999999,39.950802],"type":"Point"}
}