{
  "type": "Feature",
  "properties": {
    "addr:full":"2176 Willow Street Pike Lancaster PA 17602",
    "addr:housenumber":"2176",
    "addr:postcode":"17602",
    "addr:street":"Willow Street Pike",
    "iso:country":"US",
    "sg:address":"2176 Willow Street Pike",
    "sg:city":"Lancaster",
    "sg:classifiers":[
        {
            "category":"Retail",
            "subcategory":"Auto Rental",
            "type":"Services"
        }
    ],
    "sg:phone":"+1 717 464 5224",
    "sg:postcode":"17602",
    "sg:province":"PA",
    "sg:tags":[
        "renting",
        "truck",
        "leasing"
    ],
    "wof:name":"U-Haul Co",
    "wof:placetype":"venue"
},
  "geometry": {"coordinates":[-76.290239,39.998198],"type":"Point"}
}