{
  "type": "Feature",
  "properties": {
    "iso:country":"US",
    "sg:address":"67 Cedar Hill Ln",
    "sg:city":"Media",
    "sg:classifiers":[
        {
            "category":"Building & Trades",
            "subcategory":"Construction",
            "type":"Services"
        }
    ],
    "sg:phone":"+1   ",
    "sg:postcode":"19063",
    "sg:province":"PA",
    "sg:tags":[
        "house"
    ],
    "wof:name":"Rose Tree Develo-Pment",
    "wof:placetype":"venue"
},
  "geometry": {"coordinates":[-75.37249,39.93579],"type":"Point"}
}