{
  "type": "Feature",
  "properties": {
    "addr:full":"138 Muffley Dr Apollo PA 15613",
    "addr:housenumber":"138",
    "addr:postcode":"15613",
    "addr:street":"Muffley Dr",
    "iso:country":"US",
    "sg:address":"138 Muffley Dr",
    "sg:city":"Apollo",
    "sg:classifiers":[
        {
            "category":"Professional",
            "type":"Services"
        }
    ],
    "sg:phone":"+1   ",
    "sg:postcode":"15613",
    "sg:province":"PA",
    "wof:name":"J Schwab Theodore",
    "wof:placetype":"venue"
},
  "geometry": {"coordinates":[-79.58026099999999,40.55527],"type":"Point"}
}