{
  "type": "Feature",
  "properties": {
    "addr:full":"718 W Main St Plymouth PA 18651",
    "addr:housenumber":"718",
    "addr:postcode":"18651",
    "addr:street":"W Main St",
    "iso:country":"US",
    "sg:address":"718 W Main St",
    "sg:city":"Plymouth",
    "sg:classifiers":[
        {
            "category":"Autos & Motor Vehicles",
            "subcategory":"Automobile Sales",
            "type":"Retail Goods"
        }
    ],
    "sg:phone":"+1 570 719 1999",
    "sg:postcode":"18651",
    "sg:province":"PA",
    "sg:tags":[
        "car",
        "dealer"
    ],
    "wof:name":"Charley's Auto Sales",
    "wof:placetype":"venue"
},
  "geometry": {"coordinates":[-75.960533,41.235312],"type":"Point"}
}