{
  "type": "Feature",
  "properties": {
    "iso:country":"US",
    "sg:address":"4701 Bath St",
    "sg:city":"Philadelphia",
    "sg:classifiers":[
        {
            "category":"Real Estate",
            "subcategory":"Real Estate Agent",
            "type":"Services"
        },
        {
            "category":"Real Estate",
            "subcategory":"Real Estate Operator",
            "type":"Services"
        }
    ],
    "sg:phone":"+1 215 331 5151",
    "sg:postcode":"19137",
    "sg:province":"PA",
    "sg:tags":[
        "building",
        "industrial",
        "wa",
        "general",
        "manager",
        "owner"
    ],
    "wof:name":"Wolf Investments Corps",
    "wof:placetype":"venue"
},
  "geometry": {"coordinates":[-75.06702300000001,39.998117],"type":"Point"}
}