{
  "type": "Feature",
  "properties": {
    "iso:country":"US",
    "sg:address":"553 E Mahoning St",
    "sg:city":"Punxsutawney",
    "sg:classifiers":[
        {
            "category":"Government",
            "subcategory":"Post Office",
            "type":"Public Place"
        }
    ],
    "sg:phone":"+1 814 938 6120",
    "sg:postcode":"15767",
    "sg:province":"PA",
    "wof:name":"US Post Office",
    "wof:placetype":"venue"
},
  "geometry": {"coordinates":[-78.96315,40.944371],"type":"Point"}
}