{
  "type": "Feature",
  "properties": {
    "iso:country":"US",
    "sg:address":"10 S Wayne St",
    "sg:city":"Lewistown",
    "sg:classifiers":[
        {
            "category":"Professional",
            "subcategory":"Lawyer & Legal Services",
            "type":"Services"
        }
    ],
    "sg:phone":"+1 717 247 3787",
    "sg:postcode":"17044",
    "sg:province":"PA",
    "sg:tags":[
        "attorney",
        "practice"
    ],
    "wof:name":"Knepp & Snook",
    "wof:placetype":"venue"
},
  "geometry": {"coordinates":[-77.575822,40.596564],"type":"Point"}
}