{
  "type": "Feature",
  "properties": {
    "iso:country":"US",
    "sg:address":"85 W Wellsboro St",
    "sg:city":"Mansfield",
    "sg:classifiers":[
        {
            "category":"Farming",
            "subcategory":"Dairy Farm",
            "type":"Manufacturing & Wholesale Goods"
        }
    ],
    "sg:phone":"+1   ",
    "sg:postcode":"16933",
    "sg:province":"PA",
    "wof:name":"Courtney Bernard Dairy Farm",
    "wof:placetype":"venue"
},
  "geometry": {"coordinates":[-77.080202,41.806507],"type":"Point"}
}