{
  "type": "Feature",
  "properties": {
    "iso:country":"US",
    "sg:address":"1831 N Main Ave",
    "sg:city":"Scranton",
    "sg:classifiers":[
        {
            "category":"Restaurant",
            "type":"Food & Drink"
        }
    ],
    "sg:phone":"+1 570 342 4869",
    "sg:postcode":"18508",
    "sg:province":"PA",
    "sg:tags":[
        "sandwich",
        "eating"
    ],
    "wof:name":"Dee Jay's Hoagie Shop",
    "wof:placetype":"venue"
},
  "geometry": {"coordinates":[-75.657731,41.437615],"type":"Point"}
}