{
  "type": "Feature",
  "properties": {
    "iso:country":"US",
    "sg:address":"393 Pone Ln",
    "sg:city":"Franklin",
    "sg:classifiers":[
        {
            "category":"Place Of Worship",
            "subcategory":"Church",
            "type":"Public Place"
        },
        {
            "category":"Place Of Worship",
            "type":"Public Place"
        }
    ],
    "sg:phone":"+1 814 437 2593",
    "sg:postcode":"16323",
    "sg:province":"PA",
    "sg:tags":[
        "nazarene",
        "churches-church",
        "churches-nazarene"
    ],
    "wof:name":"Church Of The Nazarene Of Franklin",
    "wof:placetype":"venue"
},
  "geometry": {"coordinates":[-79.843917,41.367895],"type":"Point"}
}