{
  "type": "Feature",
  "properties": {
    "iso:country":"US",
    "sg:address":"1137 Freeport Rd",
    "sg:city":"Blawnox",
    "sg:classifiers":[
        {
            "category":"Shopping",
            "subcategory":"Clothing, Apparel, & Fashions",
            "type":"Retail Goods"
        }
    ],
    "sg:phone":"+1 412 967 9300",
    "sg:postcode":"15238",
    "sg:province":"PA",
    "sg:tags":[
        "infant",
        "wear"
    ],
    "wof:name":"Lambs & Ivy",
    "wof:placetype":"venue"
},
  "geometry": {"coordinates":[-79.879604,40.488121],"type":"Point"}
}