{
  "type": "Feature",
  "properties": {
    "addr:full":"2345 Oak St Lebanon PA 17042",
    "addr:housenumber":"2345",
    "addr:postcode":"17042",
    "addr:street":"Oak St",
    "iso:country":"US",
    "sg:address":"2345 Oak St",
    "sg:city":"Lebanon",
    "sg:classifiers":[
        {
            "category":"Social Services",
            "subcategory":"Adult Care",
            "type":"Services"
        }
    ],
    "sg:phone":"+1   ",
    "sg:postcode":"17042",
    "sg:province":"PA",
    "sg:tags":[
        "residential"
    ],
    "wof:name":"Phonex Services",
    "wof:placetype":"venue"
},
  "geometry": {"coordinates":[-76.448318,40.32507],"type":"Point"}
}