{
  "type": "Feature",
  "properties": {
    "addr:full":"413 W Moreland Rd Willow Grove PA 19090",
    "addr:housenumber":"413",
    "addr:postcode":"19090",
    "addr:street":"W Moreland Rd",
    "iso:country":"US",
    "sg:address":"413 W Moreland Rd",
    "sg:city":"Willow Grove",
    "sg:classifiers":[
        {
            "category":"Restaurant",
            "type":"Food & Drink"
        }
    ],
    "sg:menulink":"http://www.allmenus.com/pa/abington/229686-wings-to-go/menu/",
    "sg:phone":"+1 215 784 7011",
    "sg:postcode":"19090",
    "sg:province":"PA",
    "sg:tags":[
        "american",
        "wing"
    ],
    "wof:name":"Wings To Go",
    "wof:placetype":"venue"
},
  "geometry": {"coordinates":[-75.121683,40.144165],"type":"Point"}
}