{
  "type": "Feature",
  "properties": {
    "addr:full":"1525 Farmington Ave Pottstown PA 19464",
    "addr:housenumber":"1525",
    "addr:postcode":"19464",
    "addr:street":"Farmington Ave",
    "iso:country":"US",
    "sg:address":"1525 Farmington Ave",
    "sg:city":"Pottstown",
    "sg:phone":"+1 610 327 0046",
    "sg:postcode":"19464",
    "sg:province":"PA",
    "sg:tags":[
        "oil"
    ],
    "wof:name":"Atlas Oil I LTD",
    "wof:placetype":"venue"
},
  "geometry": {"coordinates":[-75.641231,40.286307],"type":"Point"}
}