{
  "type": "Feature",
  "properties": {
    "addr:full":"4710 Business 220 Bedford PA 15522",
    "addr:housenumber":"4710;220",
    "addr:postcode":"15522",
    "addr:street":"Business",
    "iso:country":"US",
    "sg:address":"4710 Business 220",
    "sg:city":"Bedford",
    "sg:phone":"+1 814 623 1174",
    "sg:postcode":"15522",
    "sg:province":"PA",
    "wof:name":"Carriage House Restaurant and Lounge",
    "wof:placetype":"venue"
},
  "geometry": {"coordinates":[-78.511244,40.063393],"type":"Point"}
}