{
  "type": "Feature",
  "properties": {
    "addr:full":"340 Bell Ave Mc Kees Rocks PA 15136",
    "addr:housenumber":"340",
    "addr:postcode":"15136",
    "addr:street":"Bell Ave Mc Kees Rocks",
    "iso:country":"US",
    "sg:address":"340 Bell Ave",
    "sg:city":"Mc Kees Rocks",
    "sg:classifiers":[
        {
            "category":"Government",
            "subcategory":"Office",
            "type":"Public Place"
        }
    ],
    "sg:phone":"+1 412 331 6120",
    "sg:postcode":"15136",
    "sg:province":"PA",
    "sg:tags":[
        "city",
        "taxation"
    ],
    "wof:name":"Tax Collector",
    "wof:placetype":"venue"
},
  "geometry": {"coordinates":[-80.056782,40.46589],"type":"Point"}
}