{
  "type": "Feature",
  "properties": {
    "addr:full":"1732 Tioga St Coal Township PA 17866",
    "addr:housenumber":"1732",
    "addr:postcode":"17866",
    "addr:street":"Tioga St",
    "iso:country":"US",
    "sg:address":"1732 Tioga St",
    "sg:city":"Coal Township",
    "sg:classifiers":[
        {
            "category":"Bars & Pubs",
            "type":"Food & Drink"
        }
    ],
    "sg:phone":"+1 570 648 9333",
    "sg:postcode":"17866",
    "sg:province":"PA",
    "sg:tags":[
        "drinking"
    ],
    "wof:name":"Nolter's Cafe",
    "wof:placetype":"venue"
},
  "geometry": {"coordinates":[-76.53459100000001,40.788329],"type":"Point"}
}