{
  "type": "Feature",
  "properties": {
    "addr:full":"3203 Maryland Ave North Versailles PA 15137",
    "addr:housenumber":"3203",
    "addr:postcode":"15137",
    "addr:street":"Maryland Ave",
    "iso:country":"US",
    "sg:address":"3203 Maryland Ave",
    "sg:city":"North Versailles",
    "sg:classifiers":[
        {
            "category":"Education",
            "subcategory":"School",
            "type":"Public Place"
        }
    ],
    "sg:phone":"+1   ",
    "sg:postcode":"15137",
    "sg:province":"PA",
    "sg:tags":[
        "high",
        "junior"
    ],
    "wof:name":"Regional Education Center",
    "wof:placetype":"venue"
},
  "geometry": {"coordinates":[-79.82846000000001,40.380181],"type":"Point"}
}