{
  "type": "Feature",
  "properties": {
    "iso:country":"US",
    "sg:address":"114 W Black Bass Ln",
    "sg:city":"Media",
    "sg:classifiers":[
        {
            "category":"Building & Trades",
            "subcategory":"Construction",
            "type":"Services"
        }
    ],
    "sg:phone":"+1 610 356 2060",
    "sg:postcode":"19063",
    "sg:province":"PA",
    "sg:tags":[
        "general",
        "contractor"
    ],
    "wof:name":"Vincent P Sposato Homes",
    "wof:placetype":"venue"
},
  "geometry": {"coordinates":[-75.379317,39.949449],"type":"Point"}
}