{
  "type": "Feature",
  "properties": {
    "iso:country":"US",
    "sg:address":"332 N Reading Rd",
    "sg:city":"Ephrata",
    "sg:classifiers":[
        {
            "category":"Organizations",
            "subcategory":"Religious Organization",
            "type":"Services"
        }
    ],
    "sg:phone":"+1 717 733 6372",
    "sg:postcode":"17522",
    "sg:province":"PA",
    "sg:tags":[
        "church"
    ],
    "wof:name":"New Hope Community Church",
    "wof:placetype":"venue"
},
  "geometry": {"coordinates":[-76.17397099999999,40.193566],"type":"Point"}
}