{
  "type": "Feature",
  "properties": {
    "iso:country":"US",
    "sg:address":"125 W Pike St",
    "sg:city":"Canonsburg",
    "sg:classifiers":[
        {
            "category":"Health Services",
            "subcategory":"Clinic",
            "type":"Services"
        },
        {
            "category":"Personal",
            "type":"Services"
        }
    ],
    "sg:phone":"+1 724 745 7766",
    "sg:postcode":"15317",
    "sg:province":"PA",
    "sg:tags":[
        "information",
        "mental",
        "counseling"
    ],
    "wof:name":"Canonsburg Counseling Associates",
    "wof:placetype":"venue"
},
  "geometry": {"coordinates":[-80.18989000000001,40.258291],"type":"Point"}
}