{
  "type": "Feature",
  "properties": {
    "iso:country":"US",
    "sg:address":"142 E Millsboro Rd",
    "sg:city":"East Millsboro",
    "sg:classifiers":[
        {
            "category":"Government",
            "subcategory":"Office",
            "type":"Public Place"
        }
    ],
    "sg:phone":"+1 724 785 5027",
    "sg:postcode":"15433",
    "sg:province":"PA",
    "wof:name":"US Lock & Dam",
    "wof:placetype":"venue"
},
  "geometry": {"coordinates":[-79.99019,39.97604],"type":"Point"}
}