{
  "type": "Feature",
  "properties": {
    "iso:country":"US",
    "sg:address":"535 S Carldon St",
    "sg:city":"Allentown",
    "sg:classifiers":[
        {
            "category":"Bus Station",
            "type":"Transportation"
        }
    ],
    "sg:phone":"+1   ",
    "sg:postcode":"18103",
    "sg:province":"PA",
    "sg:tags":[
        "facility"
    ],
    "wof:name":"Transportion Dept",
    "wof:placetype":"venue"
},
  "geometry": {"coordinates":[-75.457431,40.597166],"type":"Point"}
}