{
  "type": "Feature",
  "properties": {
    "addr:full":"1016 N 9th St Stroudsburg PA 18360",
    "addr:housenumber":"1016",
    "addr:postcode":"18360",
    "addr:street":"N 9Th St",
    "iso:country":"US",
    "sg:address":"1016 N 9th St",
    "sg:city":"Stroudsburg",
    "sg:classifiers":[
        {
            "category":"Autos & Motor Vehicles",
            "subcategory":"Auto Supplies",
            "type":"Retail Goods"
        }
    ],
    "sg:phone":"+1   ",
    "sg:postcode":"18360",
    "sg:province":"PA",
    "sg:tags":[
        "muffler",
        "brake",
        "installation",
        "sales"
    ],
    "wof:name":"Midas Muffler",
    "wof:placetype":"venue"
},
  "geometry": {"coordinates":[-75.215144,40.989876],"type":"Point"}
}