{
  "type": "Feature",
  "properties": {
    "iso:country":"US",
    "sg:address":"133 S 20th St",
    "sg:city":"Philadelphia",
    "sg:classifiers":[
        {
            "category":"Building & Trades",
            "subcategory":"Locksmith",
            "type":"Services"
        }
    ],
    "sg:phone":"+1 267 702 1097",
    "sg:postcode":"19103",
    "sg:province":"PA",
    "sg:tags":[
        "key"
    ],
    "wof:name":"Philadelphia Locksmith",
    "wof:placetype":"venue"
},
  "geometry": {"coordinates":[-75.173464,39.951204],"type":"Point"}
}