{
  "type": "Feature",
  "properties": {
    "iso:country":"US",
    "sg:address":"2358 N Front St",
    "sg:city":"Philadelphia",
    "sg:classifiers":[
        {
            "category":"Deli",
            "type":"Food & Drink"
        }
    ],
    "sg:phone":"+1 215 425 0160",
    "sg:postcode":"19133",
    "sg:province":"PA",
    "wof:name":"Kim Kyu Yong",
    "wof:placetype":"venue"
},
  "geometry": {"coordinates":[-75.131699,39.986099],"type":"Point"}
}