{
  "type": "Feature",
  "properties": {
    "iso:country":"US",
    "sg:address":"901 Western Ave",
    "sg:city":"Pittsburgh",
    "sg:classifiers":[
        {
            "category":"Building & Trades",
            "subcategory":"Cleaning & Sanitation",
            "type":"Services"
        }
    ],
    "sg:phone":"+1 412 231 4033",
    "sg:postcode":"15233",
    "sg:province":"PA",
    "sg:tags":[
        "janitor"
    ],
    "wof:name":"A & J Commercial Cleaning",
    "wof:placetype":"venue"
},
  "geometry": {"coordinates":[-80.018897,40.451518],"type":"Point"}
}