{
  "type": "Feature",
  "properties": {
    "iso:country":"US",
    "sg:address":"225 S Main St",
    "sg:city":"Wilkes Barre",
    "sg:classifiers":[
        {
            "category":"Communications",
            "subcategory":"Film & Video Production",
            "type":"Services"
        }
    ],
    "sg:phone":"+1 570 822 5798",
    "sg:postcode":"18701",
    "sg:province":"PA",
    "sg:tags":[
        "taping"
    ],
    "sg:website":"www.tommustopro.com",
    "wof:name":"Tom Musto Productions",
    "wof:placetype":"venue"
},
  "geometry": {"coordinates":[-75.88985599999999,41.241548],"type":"Point"}
}