{
  "type": "Feature",
  "properties": {
    "addr:full":"349 Nottingham Rd Quarryville PA 17566",
    "addr:housenumber":"349",
    "addr:postcode":"17566",
    "addr:street":"Nottingham Rd",
    "iso:country":"US",
    "sg:address":"349 Nottingham Rd",
    "sg:city":"Quarryville",
    "sg:classifiers":[
        {
            "category":"Retail",
            "subcategory":"Auto Repair",
            "type":"Services"
        }
    ],
    "sg:phone":"+1 717 529 5470",
    "sg:postcode":"17566",
    "sg:province":"PA",
    "sg:tags":[
        "truck"
    ],
    "wof:name":"Phipps & Son",
    "wof:placetype":"venue"
},
  "geometry": {"coordinates":[-76.114431,39.779686],"type":"Point"}
}