{
  "type": "Feature",
  "properties": {
    "iso:country":"US",
    "sg:address":"5501 MacArthur Rd",
    "sg:city":"Whitehall",
    "sg:classifiers":[
        {
            "category":"Health Services",
            "subcategory":"Dentist",
            "type":"Services"
        }
    ],
    "sg:phone":"+1 610 502 1545",
    "sg:postcode":"18052",
    "sg:province":"PA",
    "sg:website":"www.incrediblesmiles.net",
    "wof:name":"Salivonchik S John DMD",
    "wof:placetype":"venue"
},
  "geometry": {"coordinates":[-75.523697,40.692402],"type":"Point"}
}