{
  "type": "Feature",
  "properties": {
    "addr:full":"RR 3 Box 148 Dalton PA 18414",
    "addr:housenumber":"148",
    "addr:postcode":"18414",
    "addr:street":"Rr 3 Box",
    "iso:country":"US",
    "sg:address":"RR 3 Box 148",
    "sg:city":"Dalton",
    "sg:classifiers":[
        {
            "category":"Recreation",
            "type":"Entertainment"
        }
    ],
    "sg:phone":"+1 570 563 1627",
    "sg:postcode":"18414",
    "sg:province":"PA",
    "sg:tags":[
        "entertainers-family",
        "business"
    ],
    "wof:name":"Magical Memories",
    "wof:placetype":"venue"
},
  "geometry": {"coordinates":[-75.721394,41.525703],"type":"Point"}
}