{
  "type": "Feature",
  "properties": {
    "iso:country":"US",
    "sg:address":"305 Skyline Dr N",
    "sg:city":"Clarks Summit",
    "sg:classifiers":[
        {
            "category":"Insurance",
            "subcategory":"Insurance Agent",
            "type":"Services"
        }
    ],
    "sg:phone":"+1   ",
    "sg:postcode":"18411",
    "sg:province":"PA",
    "wof:name":"Hess John",
    "wof:placetype":"venue"
},
  "geometry": {"coordinates":[-75.691732,41.477591],"type":"Point"}
}