{
  "type": "Feature",
  "properties": {
    "iso:country":"US",
    "sg:address":"249 S 52nd St",
    "sg:city":"Philadelphia",
    "sg:classifiers":[
        {
            "category":"Health Services",
            "subcategory":"Doctor",
            "type":"Services"
        }
    ],
    "sg:phone":"+1 215 476 0440",
    "sg:postcode":"19139",
    "sg:province":"PA",
    "sg:tags":[
        "surgeon",
        "oral"
    ],
    "wof:name":"Patel Ramesh G DDS",
    "wof:placetype":"venue"
},
  "geometry": {"coordinates":[-75.2257,39.955502],"type":"Point"}
}