{
  "type": "Feature",
  "properties": {
    "iso:country":"US",
    "sg:address":"4171 Country Club Rd",
    "sg:city":"Easton",
    "sg:classifiers":[
        {
            "category":"Recreation",
            "type":"Entertainment"
        }
    ],
    "sg:phone":"+1 610 258 8643",
    "sg:postcode":"18045",
    "sg:province":"PA",
    "sg:tags":[
        "stable"
    ],
    "wof:name":"Hope Lock Farm",
    "wof:placetype":"venue"
},
  "geometry": {"coordinates":[-75.292799,40.690039],"type":"Point"}
}