{
  "type": "Feature",
  "properties": {
    "iso:country":"US",
    "sg:address":"405 N Main St",
    "sg:city":"Coudersport",
    "sg:classifiers":[
        {
            "category":"Home & Garden",
            "subcategory":"Household Appliances",
            "type":"Retail Goods"
        }
    ],
    "sg:phone":"+1 814 274 9244",
    "sg:postcode":"16915",
    "sg:province":"PA",
    "sg:tags":[
        "repair",
        "electrical",
        "dwelling",
        "ope"
    ],
    "wof:name":"Wilson Appliance Sales & Svc",
    "wof:placetype":"venue"
},
  "geometry": {"coordinates":[-78.020837,41.777276],"type":"Point"}
}