{
  "type": "Feature",
  "properties": {
    "iso:country":"US",
    "sg:address":"713 Bethlehem Pike",
    "sg:city":"Montgomeryville",
    "sg:classifiers":[
        {
            "category":"Home & Garden",
            "subcategory":"Furniture",
            "type":"Retail Goods"
        }
    ],
    "sg:phone":"+1 215 368 8530",
    "sg:postcode":"18915",
    "sg:province":"PA",
    "wof:name":"La-Z-Boy Furniture Galleries",
    "wof:placetype":"venue"
},
  "geometry": {"coordinates":[-75.260955,40.279034],"type":"Point"}
}