{
  "type": "Feature",
  "properties": {
    "iso:country":"US",
    "sg:address":"6343 Race St",
    "sg:city":"Philadelphia",
    "sg:classifiers":[
        {
            "category":"Organizations",
            "subcategory":"Community Association",
            "type":"Services"
        }
    ],
    "sg:phone":"+1   ",
    "sg:postcode":"19139",
    "sg:province":"PA",
    "wof:name":"Eritrean Cmnty of Philadelphia",
    "wof:placetype":"venue"
},
  "geometry": {"coordinates":[-75.248029,39.966106],"type":"Point"}
}