{
  "type": "Feature",
  "properties": {
    "addr:full":"11000 Roosevelt Blvd Philadelphia PA 19116",
    "addr:housenumber":"11000",
    "addr:postcode":"19116",
    "addr:street":"Roosevelt Blvd",
    "iso:country":"US",
    "sg:address":"11000 Roosevelt Blvd",
    "sg:city":"Philadelphia",
    "sg:classifiers":[
        {
            "category":"Bars & Pubs",
            "type":"Food & Drink"
        },
        {
            "category":"Restaurant",
            "type":"Food & Drink"
        }
    ],
    "sg:phone":"+1 215 677 4424",
    "sg:postcode":"19116",
    "sg:province":"PA",
    "sg:tags":[
        "tavern",
        "grill",
        "american"
    ],
    "sg:website":"http://www.bennigans.com",
    "wof:name":"Bennigan's Grill & Tavern",
    "wof:placetype":"venue"
},
  "geometry": {"coordinates":[-75.00138099999999,40.105208],"type":"Point"}
}