{
  "type": "Feature",
  "properties": {
    "iso:country":"US",
    "sg:address":"10479 US Hwy 6n",
    "sg:city":"Albion",
    "sg:classifiers":[
        {
            "category":"Retail",
            "subcategory":"Auto Repair",
            "type":"Services"
        }
    ],
    "sg:phone":"+1   ",
    "sg:postcode":"16401",
    "sg:province":"PA",
    "sg:tags":[
        "performance",
        "car",
        "parts",
        "detailing",
        "automotive"
    ],
    "wof:name":"Speedy KS",
    "wof:placetype":"venue"
},
  "geometry": {"coordinates":[-80.342805,41.890094],"type":"Point"}
}