{
  "type": "Feature",
  "properties": {
    "addr:full":"757 S Front St Philadelphia PA 19147",
    "addr:housenumber":"757",
    "addr:postcode":"19147",
    "addr:street":"S Front St",
    "iso:country":"US",
    "sg:address":"757 S Front St",
    "sg:city":"Philadelphia",
    "sg:classifiers":[
        {
            "category":"Restaurant",
            "type":"Food & Drink"
        }
    ],
    "sg:phone":"+1 215 551 2200",
    "sg:postcode":"19147",
    "sg:province":"PA",
    "sg:website":"www.thevillagebelle.com",
    "wof:name":"Village Belle",
    "wof:placetype":"venue"
},
  "geometry": {"coordinates":[-75.14440500000001,39.938329],"type":"Point"}
}