{
  "type": "Feature",
  "properties": {
    "iso:country":"US",
    "sg:address":"619 W Main St",
    "sg:city":"New Holland",
    "sg:classifiers":[
        {
            "category":"Retail",
            "subcategory":"Repair Shop",
            "type":"Services"
        }
    ],
    "sg:phone":"+1 717 351 0378",
    "sg:postcode":"17557",
    "sg:province":"PA",
    "sg:tags":[
        "refinishing",
        "furniture"
    ],
    "wof:name":"Artistic Touch Furniture",
    "wof:placetype":"venue"
},
  "geometry": {"coordinates":[-76.110952,40.095056],"type":"Point"}
}