{
  "type": "Feature",
  "properties": {
    "iso:country":"US",
    "sg:address":"5504 Interboro Ave",
    "sg:city":"Pittsburgh",
    "sg:classifiers":[
        {
            "category":"Retail",
            "subcategory":"Animal Services",
            "type":"Services"
        },
        {
            "category":"Wholesale",
            "subcategory":"Non-durable Goods",
            "type":"Manufacturing & Wholesale Goods"
        }
    ],
    "sg:phone":"+1 412 464 1138",
    "sg:postcode":"15207",
    "sg:province":"PA",
    "sg:tags":[
        "pet",
        "grooming",
        "washing"
    ],
    "wof:name":"Judy's Pet Parlor",
    "wof:placetype":"venue"
},
  "geometry": {"coordinates":[-79.914361,40.36823],"type":"Point"}
}