{
  "type": "Feature",
  "properties": {
    "addr:full":"912 Main St Stroudsburg PA 18360",
    "addr:housenumber":"912",
    "addr:postcode":"18360",
    "addr:street":"Main St",
    "iso:country":"US",
    "sg:address":"912 Main St",
    "sg:city":"Stroudsburg",
    "sg:classifiers":[
        {
            "category":"Insurance",
            "subcategory":"Insurance Agent",
            "type":"Services"
        }
    ],
    "sg:phone":"+1   ",
    "sg:postcode":"18360",
    "sg:province":"PA",
    "wof:name":"Blue Cross Group Services",
    "wof:placetype":"venue"
},
  "geometry": {"coordinates":[-75.19808,40.984357],"type":"Point"}
}