{
  "type": "Feature",
  "properties": {
    "addr:full":"1201 Dekalb St Norristown PA 19401",
    "addr:housenumber":"1201",
    "addr:postcode":"19401",
    "addr:street":"Dekalb St",
    "iso:country":"US",
    "sg:address":"1201 Dekalb St",
    "sg:city":"Norristown",
    "sg:phone":"+1 610 277 4247",
    "sg:postcode":"19401",
    "sg:province":"PA",
    "sg:website":"http://www.citrussalonspa.com",
    "wof:name":"Citrus Salon & Day Spa",
    "wof:placetype":"venue"
},
  "geometry": {"coordinates":[-75.336029,40.12154],"type":"Point"}
}