{
  "type": "Feature",
  "properties": {
    "iso:country":"US",
    "sg:address":"216 Cambria Ave",
    "sg:city":"Avonmore",
    "sg:classifiers":[
        {
            "category":"Personal",
            "subcategory":"Beauty Salon",
            "type":"Services"
        }
    ],
    "sg:phone":"+1 724 697 4411",
    "sg:postcode":"15618",
    "sg:province":"PA",
    "wof:name":"Antonucci Beauty Salon",
    "wof:placetype":"venue"
},
  "geometry": {"coordinates":[-79.470408,40.527234],"type":"Point"}
}