{
  "type": "Feature",
  "properties": {
    "iso:country":"US",
    "sg:address":"130 S Main St",
    "sg:city":"Butler",
    "sg:classifiers":[
        {
            "category":"Professional",
            "subcategory":"Employment Agencies",
            "type":"Services"
        }
    ],
    "sg:phone":"+1 724 287 8380",
    "sg:postcode":"16001",
    "sg:province":"PA",
    "wof:name":"Specialized Staffing Inc",
    "wof:placetype":"venue"
},
  "geometry": {"coordinates":[-79.895355,40.860337],"type":"Point"}
}