{
  "type": "Feature",
  "properties": {
    "iso:country":"US",
    "sg:address":"106 Westinghouse Ave",
    "sg:city":"Wilmerding",
    "sg:classifiers":[
        {
            "category":"Restaurant",
            "type":"Food & Drink"
        }
    ],
    "sg:phone":"+1 412 823 1232",
    "sg:postcode":"15148",
    "sg:province":"PA",
    "wof:name":"Sports Page",
    "wof:placetype":"venue"
},
  "geometry": {"coordinates":[-79.809792,40.392711],"type":"Point"}
}