{
  "type": "Feature",
  "properties": {
    "iso:country":"US",
    "sg:address":"221 Story Rd",
    "sg:city":"Export",
    "sg:classifiers":[
        {
            "category":"Building & Trades",
            "subcategory":"Cleaning & Sanitation",
            "type":"Services"
        }
    ],
    "sg:phone":"+1 724 468 4326",
    "sg:postcode":"15632",
    "sg:province":"PA",
    "sg:tags":[
        "janitorial"
    ],
    "wof:name":"G And G Cleaning Company Inc",
    "wof:placetype":"venue"
},
  "geometry": {"coordinates":[-79.569245,40.440578],"type":"Point"}
}