{
  "type": "Feature",
  "properties": {
    "iso:country":"US",
    "sg:address":"211 Powder Mill Dr",
    "sg:city":"Phoenixville",
    "sg:classifiers":[
        {
            "category":"Professional",
            "subcategory":"Printing & Photocopies",
            "type":"Services"
        }
    ],
    "sg:phone":"+1 610 935 4446",
    "sg:postcode":"19460",
    "sg:province":"PA",
    "sg:tags":[
        "services-commercial"
    ],
    "wof:name":"Gemini Products & Services",
    "wof:placetype":"venue"
},
  "geometry": {"coordinates":[-75.550811,40.132271],"type":"Point"}
}