{
  "type": "Feature",
  "properties": {
    "iso:country":"US",
    "sg:address":"2609 Northwood Ave",
    "sg:city":"Easton",
    "sg:classifiers":[
        {
            "category":"Real Estate",
            "subcategory":"Developer",
            "type":"Services"
        }
    ],
    "sg:phone":"+1   ",
    "sg:postcode":"18045",
    "sg:province":"PA",
    "sg:tags":[
        "cemetery"
    ],
    "wof:name":"Bloomsbury Cemetery Assn",
    "wof:placetype":"venue"
},
  "geometry": {"coordinates":[-75.262381,40.70833],"type":"Point"}
}