{
  "type": "Feature",
  "properties": {
    "addr:full":"6 S Main St Ste 316 Washington PA 15301",
    "addr:housenumber":"6",
    "addr:postcode":"15301",
    "addr:street":"S Main St Ste 316",
    "iso:country":"US",
    "sg:address":"6 S Main St Ste 316",
    "sg:city":"Washington",
    "sg:classifiers":[
        {
            "category":"Professional",
            "subcategory":"Management & Consulting",
            "type":"Services"
        },
        {
            "category":"Banks & Credit Unions",
            "subcategory":"Investment Brokerage",
            "type":"Services"
        },
        {
            "category":"Insurance",
            "subcategory":"Hazard Insurance",
            "type":"Services"
        },
        {
            "category":"Banks & Credit Unions",
            "subcategory":"Financial Services",
            "type":"Services"
        }
    ],
    "sg:phone":"+1 724 223 8990",
    "sg:postcode":"15301",
    "sg:province":"PA",
    "sg:tags":[
        "financing",
        "business",
        "consultant",
        "commercial",
        "planning",
        "security"
    ],
    "wof:name":"Terry Marynchak",
    "wof:placetype":"venue"
},
  "geometry": {"coordinates":[-80.245436,40.1708],"type":"Point"}
}