{
  "type": "Feature",
  "properties": {
    "iso:country":"US",
    "sg:address":"608 Georgian Pl",
    "sg:city":"Somerset",
    "sg:classifiers":[
        {
            "category":"Shopping",
            "subcategory":"Gifts & Souvenirs",
            "type":"Retail Goods"
        }
    ],
    "sg:phone":"+1 814 443 4084",
    "sg:postcode":"15501",
    "sg:province":"PA",
    "sg:tags":[
        "shop"
    ],
    "wof:name":"Rose Garden Gift Shop",
    "wof:placetype":"venue"
},
  "geometry": {"coordinates":[-79.07434499999999,40.023076],"type":"Point"}
}