{
  "type": "Feature",
  "properties": {
    "iso:country":"US",
    "sg:address":"165 E Broad St",
    "sg:city":"Dallastown",
    "sg:classifiers":[
        {
            "category":"Manufacturing",
            "subcategory":"Metals",
            "type":"Manufacturing & Wholesale Goods"
        }
    ],
    "sg:phone":"+1   ",
    "sg:postcode":"17313",
    "sg:province":"PA",
    "sg:tags":[
        "finishing"
    ],
    "wof:name":"Anodizing of York Inc",
    "wof:placetype":"venue"
},
  "geometry": {"coordinates":[-76.636376,39.901886],"type":"Point"}
}