{
  "type": "Feature",
  "properties": {
    "iso:country":"US",
    "sg:address":"310 Huntingdon Pike",
    "sg:city":"Jenkintown",
    "sg:classifiers":[
        {
            "category":"Health Services",
            "subcategory":"Health Practitioner",
            "type":"Services"
        }
    ],
    "sg:phone":"+1   ",
    "sg:postcode":"19046",
    "sg:province":"PA",
    "wof:name":"John Wesolowich Pt",
    "wof:placetype":"venue"
},
  "geometry": {"coordinates":[-75.089963,40.081261],"type":"Point"}
}