{
  "type": "Feature",
  "properties": {
    "iso:country":"US",
    "sg:address":"4628 Frankford Ave",
    "sg:city":"Philadelphia",
    "sg:classifiers":[
        {
            "category":"Shopping",
            "subcategory":"Discount & Variety Stores",
            "type":"Retail Goods"
        },
        {
            "category":"Shopping",
            "subcategory":"Department Store",
            "type":"Retail Goods"
        }
    ],
    "sg:phone":"+1 215 535 8222",
    "sg:postcode":"19124",
    "sg:province":"PA",
    "sg:tags":[
        "shop"
    ],
    "wof:name":"Valu Plus Inc",
    "wof:placetype":"venue"
},
  "geometry": {"coordinates":[-75.08520300000001,40.015074],"type":"Point"}
}