{
  "type": "Feature",
  "properties": {
    "iso:country":"US",
    "sg:address":"55 W Maiden St",
    "sg:city":"Washington",
    "sg:classifiers":[
        {
            "category":"Government",
            "subcategory":"Office",
            "type":"Public Place"
        }
    ],
    "sg:phone":"+1 724 223 4209",
    "sg:postcode":"15301",
    "sg:province":"PA",
    "sg:tags":[
        "city"
    ],
    "wof:name":"Washington City Clerk",
    "wof:placetype":"venue"
},
  "geometry": {"coordinates":[-80.245902,40.167676],"type":"Point"}
}