{
  "type": "Feature",
  "properties": {
    "iso:country":"US",
    "sg:address":"5201 N Broad St",
    "sg:city":"Philadelphia",
    "sg:classifiers":[
        {
            "category":"Health Services",
            "subcategory":"Doctor",
            "type":"Services"
        }
    ],
    "sg:phone":"+1 215 329 5512",
    "sg:postcode":"19141",
    "sg:province":"PA",
    "sg:tags":[
        "dentist"
    ],
    "wof:name":"Debra V Irvin DDS",
    "wof:placetype":"venue"
},
  "geometry": {"coordinates":[-75.145898,40.033728],"type":"Point"}
}