{
  "type": "Feature",
  "properties": {
    "addr:full":"239 Center St Meyersdale PA 15552",
    "addr:housenumber":"239",
    "addr:postcode":"15552",
    "addr:street":"Center St",
    "iso:country":"US",
    "sg:address":"239 Center St",
    "sg:city":"Meyersdale",
    "sg:classifiers":[
        {
            "category":"Government",
            "subcategory":"Post Office",
            "type":"Public Place"
        }
    ],
    "sg:phone":"+1   ",
    "sg:postcode":"15552",
    "sg:province":"PA",
    "sg:tags":[
        "postal",
        "us"
    ],
    "wof:name":"Meyersdale Post Office",
    "wof:placetype":"venue"
},
  "geometry": {"coordinates":[-79.02625,39.81583],"type":"Point"}
}