{
  "type": "Feature",
  "properties": {
    "iso:country":"US",
    "sg:address":"1133 3rd St",
    "sg:city":"Whitehall",
    "sg:classifiers":[
        {
            "category":"Shopping",
            "subcategory":"Florist",
            "type":"Retail Goods"
        }
    ],
    "sg:phone":"+1 610 264 9376",
    "sg:postcode":"18052",
    "sg:province":"PA",
    "wof:name":"Dick's Florist",
    "wof:placetype":"venue"
},
  "geometry": {"coordinates":[-75.47268,40.640806],"type":"Point"}
}