{
  "type": "Feature",
  "properties": {
    "addr:full":"1993 Grant Rd Coopersburg PA 18036",
    "addr:housenumber":"1993",
    "addr:postcode":"18036",
    "addr:street":"Grant Rd",
    "iso:country":"US",
    "sg:address":"1993 Grant Rd",
    "sg:city":"Coopersburg",
    "sg:classifiers":[
        {
            "category":"Health Services",
            "subcategory":"Nursing And Care Facility",
            "type":"Services"
        }
    ],
    "sg:phone":"+1   ",
    "sg:postcode":"18036",
    "sg:province":"PA",
    "wof:name":"Barc/Star Route",
    "wof:placetype":"venue"
},
  "geometry": {"coordinates":[-75.417164,40.477165],"type":"Point"}
}