{
  "type": "Feature",
  "properties": {
    "iso:country":"US",
    "sg:address":"505 Clark St",
    "sg:city":"Waverly",
    "sg:classifiers":[
        {
            "category":"Social Services",
            "type":"Services"
        }
    ],
    "sg:phone":"+1 607 565 7580",
    "sg:postcode":"14892",
    "sg:province":"PA",
    "sg:tags":[
        "organization",
        "welfare"
    ],
    "wof:name":"Catholic Charities",
    "wof:placetype":"venue"
},
  "geometry": {"coordinates":[-76.54392,42.00541],"type":"Point"}
}