{
  "type": "Feature",
  "properties": {
    "iso:country":"US",
    "sg:address":"952 Elizabeth St",
    "sg:city":"Mckeesport",
    "sg:classifiers":[
        {
            "category":"Insurance",
            "subcategory":"Hazard Insurance",
            "type":"Services"
        }
    ],
    "sg:phone":"+1 412 896 0044",
    "sg:postcode":"15133",
    "sg:province":"PA",
    "sg:tags":[
        "commercial",
        "business"
    ],
    "wof:name":"Cincinnati Insurance Co.",
    "wof:placetype":"venue"
},
  "geometry": {"coordinates":[-79.864423,40.323618],"type":"Point"}
}