{
  "type": "Feature",
  "properties": {
    "addr:full":"229 E Main St Brookville PA 15825",
    "addr:housenumber":"229",
    "addr:postcode":"15825",
    "addr:street":"E Main St",
    "iso:country":"US",
    "sg:address":"229 E Main St",
    "sg:city":"Brookville",
    "sg:classifiers":[
        {
            "category":"Shopping",
            "subcategory":"Pharmacy",
            "type":"Retail Goods"
        }
    ],
    "sg:phone":"+1 814 849 7300",
    "sg:postcode":"15825",
    "sg:province":"PA",
    "sg:tags":[
        "drug",
        "store"
    ],
    "wof:name":"Mc Cabe's Drug Store",
    "wof:placetype":"venue"
},
  "geometry": {"coordinates":[-79.080197,41.160397],"type":"Point"}
}