{
  "type": "Feature",
  "properties": {
    "iso:country":"US",
    "sg:address":"3062 Cement Hollow Rd",
    "sg:city":"Jersey Shore",
    "sg:classifiers":[
        {
            "category":"Autos & Motor Vehicles",
            "subcategory":"Auto Supplies",
            "type":"Retail Goods"
        }
    ],
    "sg:phone":"+1 570 398 2309",
    "sg:postcode":"17740",
    "sg:province":"PA",
    "sg:tags":[
        "tire"
    ],
    "wof:name":"All Round Tire Co",
    "wof:placetype":"venue"
},
  "geometry": {"coordinates":[-77.252489,41.213284],"type":"Point"}
}