{
  "type": "Feature",
  "properties": {
    "iso:country":"US",
    "sg:address":"166 Farmington Ln",
    "sg:city":"Lancaster",
    "sg:classifiers":[
        {
            "category":"Insurance",
            "subcategory":"Insurance Agent",
            "type":"Services"
        }
    ],
    "sg:phone":"+1   ",
    "sg:postcode":"17601",
    "sg:province":"PA",
    "wof:name":"Financial Institution Mar",
    "wof:placetype":"venue"
},
  "geometry": {"coordinates":[-76.318378,40.072878],"type":"Point"}
}