{
  "type": "Feature",
  "properties": {
    "iso:country":"US",
    "sg:address":"589 Musser School Rd",
    "sg:city":"Leola",
    "sg:classifiers":[
        {
            "category":"Home & Garden",
            "subcategory":"Home Furnishings",
            "type":"Retail Goods"
        }
    ],
    "sg:phone":"+1   ",
    "sg:postcode":"17540",
    "sg:province":"PA",
    "sg:tags":[
        "housewares",
        "gift"
    ],
    "wof:name":"Country Housewares",
    "wof:placetype":"venue"
},
  "geometry": {"coordinates":[-76.123891,40.077681],"type":"Point"}
}