{
  "type": "Feature",
  "properties": {
    "addr:full":"2003 Renaissance Blvd King Of Prussia PA 19406",
    "addr:housenumber":"2003",
    "addr:postcode":"19406",
    "addr:street":"Renaissance Blvd",
    "iso:country":"US",
    "sg:address":"2003 Renaissance Blvd",
    "sg:city":"King Of Prussia",
    "sg:classifiers":[
        {
            "category":"Utilities",
            "subcategory":"Electric",
            "type":"Services"
        }
    ],
    "sg:phone":"+1   ",
    "sg:postcode":"19406",
    "sg:province":"PA",
    "sg:tags":[
        "construction",
        "energy",
        "management",
        "engineering",
        "o"
    ],
    "wof:name":"Cogenex Corporation",
    "wof:placetype":"venue"
},
  "geometry": {"coordinates":[-75.333274,40.081239],"type":"Point"}
}