{
  "type": "Feature",
  "properties": {
    "iso:country":"US",
    "sg:address":"204 Pitney Rd",
    "sg:city":"Lancaster",
    "sg:classifiers":[
        {
            "category":"Building & Trades",
            "subcategory":"Construction",
            "type":"Services"
        }
    ],
    "sg:phone":"+1 717 397 4813",
    "sg:postcode":"17601",
    "sg:province":"PA",
    "sg:tags":[
        "contractor"
    ],
    "wof:name":"Broadback Roofing Inc",
    "wof:placetype":"venue"
},
  "geometry": {"coordinates":[-76.26258900000001,40.052081],"type":"Point"}
}