{
  "type": "Feature",
  "properties": {
    "addr:full":"255 S 38th St Philadelphia PA 19104",
    "addr:housenumber":"255",
    "addr:postcode":"19104",
    "addr:street":"S 38Th St",
    "iso:country":"US",
    "sg:address":"255 S 38th St",
    "sg:city":"Philadelphia",
    "sg:classifiers":[
        {
            "category":"Education",
            "subcategory":"School",
            "type":"Public Place"
        }
    ],
    "sg:phone":"+1 215 898 4560",
    "sg:postcode":"19104",
    "sg:province":"PA",
    "wof:name":"Aresty Inst of Executive Education of U of P",
    "wof:placetype":"venue"
},
  "geometry": {"coordinates":[-75.19879899999999,39.952499],"type":"Point"}
}