{
  "type": "Feature",
  "properties": {
    "addr:full":"2070 Saw Mill Run Blvd Pittsburgh PA 15210",
    "addr:postcode":"2070;15210",
    "addr:street":"Saw Mill Run Blvd",
    "iso:country":"US",
    "sg:address":"2070 Saw Mill Run Blvd",
    "sg:city":"Pittsburgh",
    "sg:classifiers":[
        {
            "category":"Autos & Motor Vehicles",
            "subcategory":"Automobile Sales",
            "type":"Retail Goods"
        }
    ],
    "sg:phone":"+1   ",
    "sg:postcode":"15210",
    "sg:province":"PA",
    "sg:tags":[
        "used"
    ],
    "wof:name":"Atlantic Auto Sales",
    "wof:placetype":"venue"
},
  "geometry": {"coordinates":[-79.99678400000001,40.390957],"type":"Point"}
}