{
  "type": "Feature",
  "properties": {
    "iso:country":"US",
    "sg:address":"1913 S Broad St",
    "sg:city":"Philadelphia",
    "sg:classifiers":[
        {
            "category":"Health Services",
            "subcategory":"Doctor",
            "type":"Services"
        }
    ],
    "sg:phone":"+1 215 336 8000",
    "sg:postcode":"19148",
    "sg:province":"PA",
    "wof:name":"Fortino Robert DO",
    "wof:placetype":"venue"
},
  "geometry": {"coordinates":[-75.16887699999999,39.926393],"type":"Point"}
}