{
  "type": "Feature",
  "properties": {
    "addr:full":"100 John Hoff Pl Lancaster PA 17602",
    "addr:housenumber":"100",
    "addr:postcode":"17602",
    "addr:street":"John Hoff Pl",
    "iso:country":"US",
    "sg:address":"100 John Hoff Pl",
    "sg:city":"Lancaster",
    "sg:classifiers":[
        {
            "category":"Health Services",
            "subcategory":"Optometrist",
            "type":"Services"
        }
    ],
    "sg:phone":"+1 717 397 4044",
    "sg:postcode":"17602",
    "sg:province":"PA",
    "wof:name":"Imagicorp",
    "wof:placetype":"venue"
},
  "geometry": {"coordinates":[-76.30323199999999,40.036336],"type":"Point"}
}