{
  "type": "Feature",
  "properties": {
    "addr:full":"21 Landon St Pittston PA 18640",
    "addr:housenumber":"21",
    "addr:postcode":"18640",
    "addr:street":"Landon St",
    "iso:country":"US",
    "sg:address":"21 Landon St",
    "sg:city":"Pittston",
    "sg:classifiers":[
        {
            "category":"Professional",
            "subcategory":"Detective & Security Services",
            "type":"Services"
        }
    ],
    "sg:phone":"+1 570 654 4889",
    "sg:postcode":"18640",
    "sg:province":"PA",
    "sg:tags":[
        "car",
        "private",
        "investigator"
    ],
    "sg:website":"http://www.gotcha-pi.com",
    "wof:name":"Pennsylvania Adjusters Bureau",
    "wof:placetype":"venue"
},
  "geometry": {"coordinates":[-75.79610599999999,41.314726],"type":"Point"}
}