{
  "type": "Feature",
  "properties": {
    "addr:full":"1335 Perkiomen Ave Reading PA 19602",
    "addr:housenumber":"1335",
    "addr:postcode":"19602",
    "addr:street":"Perkiomen Ave",
    "iso:country":"US",
    "sg:address":"1335 Perkiomen Ave",
    "sg:city":"Reading",
    "sg:classifiers":[
        {
            "category":"Real Estate",
            "subcategory":"Real Estate Agent",
            "type":"Services"
        }
    ],
    "sg:phone":"+1 610 376 7111",
    "sg:postcode":"19602",
    "sg:province":"PA",
    "wof:name":"John W Rosselli Sr",
    "wof:placetype":"venue"
},
  "geometry": {"coordinates":[-75.91172,40.331865],"type":"Point"}
}