{
  "type": "Feature",
  "properties": {
    "iso:country":"US",
    "sg:address":"60 Evergreen Dr",
    "sg:city":"Myerstown",
    "sg:classifiers":[
        {
            "category":"Education",
            "subcategory":"School",
            "type":"Public Place"
        }
    ],
    "sg:phone":"+1 717 866 6591",
    "sg:postcode":"17067",
    "sg:province":"PA",
    "wof:name":"Eastern Lebanon County Middle",
    "wof:placetype":"venue"
},
  "geometry": {"coordinates":[-76.29256100000001,40.345136],"type":"Point"}
}