{
  "type": "Feature",
  "properties": {
    "iso:country":"US",
    "sg:address":"1421 Lincoln Ave",
    "sg:city":"Prospect Park",
    "sg:classifiers":[
        {
            "category":"Health Services",
            "subcategory":"Doctor",
            "type":"Services"
        }
    ],
    "sg:phone":"+1   ",
    "sg:postcode":"19076",
    "sg:province":"PA",
    "sg:tags":[
        "medical"
    ],
    "wof:name":"Patel Mukesh MD Facp",
    "wof:placetype":"venue"
},
  "geometry": {"coordinates":[-75.31196199999999,39.890433],"type":"Point"}
}