{
  "type": "Feature",
  "properties": {
    "iso:country":"US",
    "sg:address":"5553 Rising Sun Ave",
    "sg:city":"Philadelphia",
    "sg:classifiers":[
        {
            "category":"Real Estate",
            "subcategory":"Real Estate Agent",
            "type":"Services"
        }
    ],
    "sg:phone":"+1 215 663 2360",
    "sg:postcode":"19120",
    "sg:province":"PA",
    "wof:name":"Richard K O'Donnell Real Est",
    "wof:placetype":"venue"
},
  "geometry": {"coordinates":[-75.11501,40.034139],"type":"Point"}
}