{
  "type": "Feature",
  "properties": {
    "iso:country":"US",
    "sg:address":"177 Springbrook Rd",
    "sg:city":"Shohola",
    "sg:classifiers":[
        {
            "category":"Manufacturing",
            "subcategory":"Buildings",
            "type":"Manufacturing & Wholesale Goods"
        },
        {
            "category":"Building & Trades",
            "subcategory":"Construction",
            "type":"Services"
        }
    ],
    "sg:phone":"+1 570 296 8285",
    "sg:postcode":"18458",
    "sg:province":"PA",
    "sg:tags":[
        "roofing",
        "industrial",
        "altering",
        "builder",
        "specialty",
        "system",
        "heating",
        "contractor",
        "contractors-commercial",
        "home",
        "remodeling",
        "air conditioning"
    ],
    "wof:name":"Busy Bee",
    "wof:placetype":"venue"
},
  "geometry": {"coordinates":[-74.955552,41.371973],"type":"Point"}
}