{
  "type": "Feature",
  "properties": {
    "addr:full":"20 Linden St West Chester PA 19382",
    "addr:housenumber":"20",
    "addr:postcode":"19382",
    "addr:street":"Linden St",
    "iso:country":"US",
    "sg:address":"20 Linden St",
    "sg:city":"West Chester",
    "sg:classifiers":[
        {
            "category":"Shopping",
            "subcategory":"Books",
            "type":"Retail Goods"
        }
    ],
    "sg:phone":"+1 610 692 8030",
    "sg:postcode":"19382",
    "sg:province":"PA",
    "sg:tags":[
        "dealer"
    ],
    "sg:website":"www.dynamicbookstore.com",
    "wof:name":"Dynamic Student Svc",
    "wof:placetype":"venue"
},
  "geometry": {"coordinates":[-75.59701699999999,39.953327],"type":"Point"}
}