{
  "type": "Feature",
  "properties": {
    "addr:full":"1315 Walnut St Ste 1200 Philadelphia PA 19107",
    "addr:housenumber":"1315",
    "addr:postcode":"19107",
    "addr:street":"Walnut St Ste 1200",
    "iso:country":"US",
    "sg:address":"1315 Walnut St Ste 1200",
    "sg:city":"Philadelphia",
    "sg:classifiers":[
        {
            "category":"Professional",
            "subcategory":"Lawyer & Legal Services",
            "type":"Services"
        }
    ],
    "sg:phone":"+1 215 546 0310",
    "sg:postcode":"19107",
    "sg:province":"PA",
    "wof:name":"Klein Howard S",
    "wof:placetype":"venue"
},
  "geometry": {"coordinates":[-75.16255099999999,39.949259],"type":"Point"}
}