{
  "type": "Feature",
  "properties": {
    "iso:country":"US",
    "sg:address":"113 E Beaver Ave",
    "sg:city":"State College",
    "sg:classifiers":[
        {
            "category":"Personal",
            "subcategory":"Beauty Salon",
            "type":"Services"
        }
    ],
    "sg:phone":"+1 814 237 2454",
    "sg:postcode":"16801",
    "sg:province":"PA",
    "sg:tags":[
        "nail"
    ],
    "wof:name":"Downtown Nails",
    "wof:placetype":"venue"
},
  "geometry": {"coordinates":[-77.859882,40.793816],"type":"Point"}
}