{
  "type": "Feature",
  "properties": {
    "addr:full":"25 Shady Ln Carlisle PA 17013",
    "addr:housenumber":"25",
    "addr:postcode":"17013",
    "addr:street":"Shady Ln",
    "iso:country":"US",
    "sg:address":"25 Shady Ln",
    "sg:city":"Carlisle",
    "sg:classifiers":[
        {
            "category":"Retail",
            "subcategory":"Veterinary Services",
            "type":"Services"
        }
    ],
    "sg:phone":"+1 717 766 5535",
    "sg:postcode":"17013",
    "sg:province":"PA",
    "sg:tags":[
        "veterinarian"
    ],
    "wof:name":"Robert Heidecker DVM",
    "wof:placetype":"venue"
},
  "geometry": {"coordinates":[-77.15107500000001,40.226585],"type":"Point"}
}