{
  "type": "Feature",
  "properties": {
    "addr:full":"55 Sugar Run Rd Waynesburg PA 15370",
    "addr:housenumber":"55",
    "addr:postcode":"15370",
    "addr:street":"Sugar Run Rd",
    "iso:country":"US",
    "sg:address":"55 Sugar Run Rd",
    "sg:city":"Waynesburg",
    "sg:classifiers":[
        {
            "category":"Shopping",
            "subcategory":"Discount & Variety Stores",
            "type":"Retail Goods"
        }
    ],
    "sg:phone":"+1 724 852 1224",
    "sg:postcode":"15370",
    "sg:province":"PA",
    "wof:name":"Dollar Tree",
    "wof:placetype":"venue"
},
  "geometry": {"coordinates":[-80.169337,39.895116],"type":"Point"}
}