{
  "type": "Feature",
  "properties": {
    "iso:country":"US",
    "sg:address":"1801 Union Blvd",
    "sg:city":"Allentown",
    "sg:classifiers":[
        {
            "category":"Shopping",
            "subcategory":"Computers & Home Electronics",
            "type":"Retail Goods"
        }
    ],
    "sg:phone":"+1 610 841 3000",
    "sg:postcode":"18109",
    "sg:province":"PA",
    "sg:tags":[
        "equipment",
        "dealer"
    ],
    "wof:name":"Microapex Computer Care Ctr",
    "wof:placetype":"venue"
},
  "geometry": {"coordinates":[-75.427967,40.625484],"type":"Point"}
}