{
  "type": "Feature",
  "properties": {
    "addr:full":"325 W Glenwood Ave Philadelphia PA 19140",
    "addr:housenumber":"325",
    "addr:postcode":"19140",
    "addr:street":"W Glenwood Ave",
    "iso:country":"US",
    "sg:address":"325 W Glenwood Ave",
    "sg:city":"Philadelphia",
    "sg:classifiers":[
        {
            "category":"Professional",
            "type":"Services"
        }
    ],
    "sg:phone":"+1 215 634 9084",
    "sg:postcode":"19140",
    "sg:province":"PA",
    "sg:tags":[
        "establishment"
    ],
    "wof:name":"Charm Statues",
    "wof:placetype":"venue"
},
  "geometry": {"coordinates":[-75.134351,40.004216],"type":"Point"}
}