{
  "type": "Feature",
  "properties": {
    "addr:full":"1520 Locust St Philadelphia PA 19102",
    "addr:housenumber":"1520",
    "addr:postcode":"19102",
    "addr:street":"Locust St",
    "iso:country":"US",
    "sg:address":"1520 Locust St",
    "sg:city":"Philadelphia",
    "sg:classifiers":[
        {
            "category":"Professional",
            "subcategory":"Detective & Security Services",
            "type":"Services"
        }
    ],
    "sg:phone":"+1 215 735 7010",
    "sg:postcode":"19102",
    "sg:province":"PA",
    "sg:tags":[
        "guard",
        "patrol"
    ],
    "wof:name":"1520 Locust Assoc",
    "wof:placetype":"venue"
},
  "geometry": {"coordinates":[-75.16775,39.948678],"type":"Point"}
}