{
  "type": "Feature",
  "properties": {
    "iso:country":"US",
    "sg:address":"392 Roberts Rd",
    "sg:city":"Sandy Lake",
    "sg:classifiers":[
        {
            "category":"Building & Trades",
            "subcategory":"Construction",
            "type":"Services"
        }
    ],
    "sg:phone":"+1 724 376 2229",
    "sg:postcode":"16145",
    "sg:province":"PA",
    "sg:tags":[
        "house",
        "general",
        "contractor"
    ],
    "wof:name":"Miller & Sons Construction",
    "wof:placetype":"venue"
},
  "geometry": {"coordinates":[-80.07616299999999,41.392163],"type":"Point"}
}