{
  "type": "Feature",
  "properties": {
    "iso:country":"US",
    "sg:address":"571 State Rte 212",
    "sg:city":"Quakertown",
    "sg:classifiers":[
        {
            "category":"Home & Garden",
            "subcategory":"Building Materials",
            "type":"Retail Goods"
        }
    ],
    "sg:phone":"+1 215 538 9300",
    "sg:postcode":"18951",
    "sg:province":"PA",
    "sg:tags":[
        "windows"
    ],
    "wof:name":"Marvic Supply Co",
    "wof:placetype":"venue"
},
  "geometry": {"coordinates":[-75.323097,40.464899],"type":"Point"}
}