{
  "type": "Feature",
  "properties": {
    "addr:full":"1330 S Main St Phoenixville PA 19460",
    "addr:housenumber":"1330",
    "addr:postcode":"19460",
    "addr:street":"S Main St",
    "iso:country":"US",
    "sg:address":"1330 S Main St",
    "sg:city":"Phoenixville",
    "sg:classifiers":[
        {
            "category":"Restaurant",
            "type":"Food & Drink"
        }
    ],
    "sg:phone":"+1   ",
    "sg:postcode":"19460",
    "sg:province":"PA",
    "sg:tags":[
        "machine",
        "vending",
        "catering"
    ],
    "wof:name":"Centerplate",
    "wof:placetype":"venue"
},
  "geometry": {"coordinates":[-75.517437,40.118972],"type":"Point"}
}