{
  "type": "Feature",
  "properties": {
    "iso:country":"US",
    "sg:address":"1240 Allegheny St",
    "sg:city":"Jersey Shore",
    "sg:classifiers":[
        {
            "category":"Shopping",
            "subcategory":"Hobbies, Toys, & Games",
            "type":"Retail Goods"
        }
    ],
    "sg:phone":"+1 570 398 8171",
    "sg:postcode":"17740",
    "sg:province":"PA",
    "wof:name":"J & K Hobbies",
    "wof:placetype":"venue"
},
  "geometry": {"coordinates":[-77.271923,41.202383],"type":"Point"}
}