{
  "type": "Feature",
  "properties": {
    "iso:country":"US",
    "sg:address":"2428 9th St",
    "sg:city":"Bethlehem",
    "sg:classifiers":[
        {
            "category":"Wholesale",
            "subcategory":"Stationery",
            "type":"Manufacturing & Wholesale Goods"
        }
    ],
    "sg:phone":"+1   ",
    "sg:postcode":"18020",
    "sg:province":"PA",
    "sg:tags":[
        "supply"
    ],
    "wof:name":"Ronald Zelko",
    "wof:placetype":"venue"
},
  "geometry": {"coordinates":[-75.325529,40.650895],"type":"Point"}
}