{
  "type": "Feature",
  "properties": {
    "iso:country":"US",
    "sg:address":"910 Sensor Dr",
    "sg:city":"Morrisville",
    "sg:classifiers":[
        {
            "category":"Manufacturing",
            "subcategory":"Tools & Machinery",
            "type":"Manufacturing & Wholesale Goods"
        }
    ],
    "sg:phone":"+1   ",
    "sg:postcode":"19067",
    "sg:province":"PA",
    "sg:tags":[
        "electrical",
        "mfg"
    ],
    "wof:name":"Alpha Marketing Inc",
    "wof:placetype":"venue"
},
  "geometry": {"coordinates":[-74.832837,40.224658],"type":"Point"}
}