{
  "type": "Feature",
  "properties": {
    "iso:country":"US",
    "sg:address":"7584 Morris Ct",
    "sg:city":"Allentown",
    "sg:classifiers":[
        {
            "category":"Building & Trades",
            "subcategory":"Electrical",
            "type":"Services"
        }
    ],
    "sg:phone":"+1 610 398 3663",
    "sg:postcode":"18106",
    "sg:province":"PA",
    "sg:tags":[
        "electric",
        "contractor"
    ],
    "sg:website":"www.tri-mllc.com",
    "wof:name":"Encompass Electrical Tech",
    "wof:placetype":"venue"
},
  "geometry": {"coordinates":[-75.604145,40.566112],"type":"Point"}
}