{
  "type": "Feature",
  "properties": {
    "iso:country":"US",
    "sg:address":"63 Charlestown Rd",
    "sg:city":"Washington Boro",
    "sg:classifiers":[
        {
            "category":"Organizations",
            "subcategory":"Religious Organization",
            "type":"Services"
        }
    ],
    "sg:phone":"+1   ",
    "sg:postcode":"17582",
    "sg:province":"PA",
    "wof:name":"Church of God Parsonage",
    "wof:placetype":"venue"
},
  "geometry": {"coordinates":[-76.464642,40.00004],"type":"Point"}
}