{
  "type": "Feature",
  "properties": {
    "iso:country":"US",
    "sg:address":"1329 Bristol Pike",
    "sg:city":"Bensalem",
    "sg:classifiers":[
        {
            "category":"Autos & Motor Vehicles",
            "subcategory":"Automobile Sales",
            "type":"Retail Goods"
        },
        {
            "category":"Retail",
            "subcategory":"Auto Rental",
            "type":"Services"
        }
    ],
    "sg:phone":"+1 800 331 1212",
    "sg:postcode":"19020",
    "sg:province":"PA",
    "sg:tags":[
        "car",
        "limo"
    ],
    "sg:website":"www.avis.com",
    "wof:name":"Avis Rent A Car",
    "wof:placetype":"venue"
},
  "geometry": {"coordinates":[-74.966078,40.071086],"type":"Point"}
}