{
  "type": "Feature",
  "properties": {
    "addr:full":"40 W Pine St Palmyra PA 17078",
    "addr:housenumber":"40",
    "addr:postcode":"17078",
    "addr:street":"W Pine St",
    "iso:country":"US",
    "sg:address":"40 W Pine St",
    "sg:city":"Palmyra",
    "sg:classifiers":[
        {
            "category":"Organizations",
            "subcategory":"Religious Organization",
            "type":"Services"
        }
    ],
    "sg:phone":"+1 717 838 3412",
    "sg:postcode":"17078",
    "sg:province":"PA",
    "sg:tags":[
        "church"
    ],
    "wof:name":"Trinity United Church Christ",
    "wof:placetype":"venue"
},
  "geometry": {"coordinates":[-76.59079699999999,40.303729],"type":"Point"}
}