{
  "type": "Feature",
  "properties": {
    "addr:full":"1239 Mckinley St Philadelphia PA 19111",
    "addr:housenumber":"1239",
    "addr:postcode":"19111",
    "addr:street":"Mckinley St",
    "iso:country":"US",
    "sg:address":"1239 Mckinley St",
    "sg:city":"Philadelphia",
    "sg:classifiers":[
        {
            "category":"Home & Garden",
            "subcategory":"Furniture",
            "type":"Retail Goods"
        }
    ],
    "sg:phone":"+1 215 533 4687",
    "sg:postcode":"19111",
    "sg:province":"PA",
    "sg:tags":[
        "store"
    ],
    "wof:name":"The Comfort Zone Pub",
    "wof:placetype":"venue"
},
  "geometry": {"coordinates":[-75.08207,40.038937],"type":"Point"}
}