{
  "type": "Feature",
  "properties": {
    "iso:country":"US",
    "sg:address":"125 W Lackawanna Ave",
    "sg:city":"Olyphant",
    "sg:classifiers":[
        {
            "category":"Shopping",
            "subcategory":"Gifts & Souvenirs",
            "type":"Retail Goods"
        }
    ],
    "sg:phone":"+1 570 489 6577",
    "sg:postcode":"18447",
    "sg:province":"PA",
    "sg:tags":[
        "collectible"
    ],
    "wof:name":"Rebecca's Auction Gallery",
    "wof:placetype":"venue"
},
  "geometry": {"coordinates":[-75.605659,41.470168],"type":"Point"}
}