{
  "type": "Feature",
  "properties": {
    "addr:full":"1015 Chestnut St Ste 312 Philadelphia PA 19107",
    "addr:housenumber":"1015",
    "addr:postcode":"19107",
    "addr:street":"Chestnut St Ste 312",
    "iso:country":"US",
    "sg:address":"1015 Chestnut St Ste 312",
    "sg:city":"Philadelphia",
    "sg:classifiers":[
        {
            "category":"Health Services",
            "subcategory":"Doctor",
            "type":"Services"
        },
        {
            "category":"Health Services",
            "subcategory":"Clinic",
            "type":"Services"
        }
    ],
    "sg:phone":"+1 215 627 9088",
    "sg:postcode":"19107",
    "sg:province":"PA",
    "sg:tags":[
        "psychological",
        "psychologist"
    ],
    "wof:name":"G L K Health Psychology Association",
    "wof:placetype":"venue"
},
  "geometry": {"coordinates":[-75.15724899999999,39.950047],"type":"Point"}
}