{
  "type": "Feature",
  "properties": {
    "addr:full":"343 South St Philadelphia PA 19147",
    "addr:housenumber":"343",
    "addr:postcode":"19147",
    "addr:street":"South St",
    "iso:country":"US",
    "sg:address":"343 South St",
    "sg:city":"Philadelphia",
    "sg:classifiers":[
        {
            "category":"Shopping",
            "subcategory":"Used Merchandise",
            "type":"Retail Goods"
        }
    ],
    "sg:phone":"+1 215 922 5239",
    "sg:postcode":"19147",
    "sg:province":"PA",
    "sg:tags":[
        "equipment",
        "fixture",
        "lighting"
    ],
    "wof:name":"Tiffany City Lighting",
    "wof:placetype":"venue"
},
  "geometry": {"coordinates":[-75.14830000000001,39.941502],"type":"Point"}
}