{
  "type": "Feature",
  "properties": {
    "iso:country":"US",
    "sg:address":"6721 Oxford Ave",
    "sg:city":"Philadelphia",
    "sg:classifiers":[
        {
            "category":"Professional",
            "type":"Services"
        }
    ],
    "sg:phone":"+1   ",
    "sg:postcode":"19111",
    "sg:province":"PA",
    "wof:name":"Sandz We R",
    "wof:placetype":"venue"
},
  "geometry": {"coordinates":[-75.086493,40.052093],"type":"Point"}
}