{
  "type": "Feature",
  "properties": {
    "addr:full":"14 S Reading Ave Rear Boyertown PA 19512",
    "addr:housenumber":"14",
    "addr:postcode":"boyertown;19512",
    "addr:street":"S Reading Ave",
    "iso:country":"US",
    "sg:address":"14 S Reading Ave Rear",
    "sg:city":"Boyertown",
    "sg:classifiers":[
        {
            "category":"Personal",
            "subcategory":"Beauty Salon",
            "type":"Services"
        },
        {
            "category":"Personal",
            "subcategory":"Barber",
            "type":"Services"
        }
    ],
    "sg:phone":"+1 610 367 5426",
    "sg:postcode":"19512",
    "sg:province":"PA",
    "sg:tags":[
        "hair",
        "stylist"
    ],
    "wof:name":"Hair Symetrics",
    "wof:placetype":"venue"
},
  "geometry": {"coordinates":[-75.63804500000001,40.333041],"type":"Point"}
}