{
  "type": "Feature",
  "properties": {
    "addr:full":"345 Hemlock Rd Reynoldsville PA 15851",
    "addr:housenumber":"345",
    "addr:postcode":"15851",
    "addr:street":"Hemlock Rd",
    "iso:country":"US",
    "sg:address":"345 Hemlock Rd",
    "sg:city":"Reynoldsville",
    "sg:classifiers":[
        {
            "category":"Farming",
            "subcategory":"Dairy Farm",
            "type":"Manufacturing & Wholesale Goods"
        },
        {
            "category":"Farming",
            "subcategory":"Farm",
            "type":"Manufacturing & Wholesale Goods"
        }
    ],
    "sg:phone":"+1 814 427 2828",
    "sg:postcode":"15851",
    "sg:province":"PA",
    "wof:name":"Kuntz Farm",
    "wof:placetype":"venue"
},
  "geometry": {"coordinates":[-78.851433,41.026428],"type":"Point"}
}