{
  "type": "Feature",
  "properties": {
    "iso:country":"US",
    "sg:address":"1 W Broad St",
    "sg:city":"Bethlehem",
    "sg:classifiers":[
        {
            "category":"Insurance",
            "subcategory":"Insurance Agent",
            "type":"Services"
        }
    ],
    "sg:phone":"+1 610 868 1344",
    "sg:postcode":"18018",
    "sg:province":"PA",
    "sg:tags":[
        "consultant"
    ],
    "wof:name":"John E Mc Gorry",
    "wof:placetype":"venue"
},
  "geometry": {"coordinates":[-75.38191500000001,40.622353],"type":"Point"}
}