{
  "type": "Feature",
  "properties": {
    "addr:full":"165 Bedford Plaza Rd Bedford PA 15522",
    "addr:housenumber":"165",
    "addr:postcode":"15522",
    "addr:street":"Bedford Plaza Rd",
    "iso:country":"US",
    "sg:address":"165 Bedford Plaza Rd",
    "sg:city":"Bedford",
    "sg:classifiers":[
        {
            "category":"Sports & Exercise",
            "subcategory":"Gym",
            "type":"Entertainment"
        }
    ],
    "sg:phone":"+1   ",
    "sg:postcode":"15522",
    "sg:province":"PA",
    "sg:tags":[
        "fitness",
        "physical",
        "facility"
    ],
    "wof:name":"Shirley J Brooks",
    "wof:placetype":"venue"
},
  "geometry": {"coordinates":[-78.468096,40.01434],"type":"Point"}
}