{
  "type": "Feature",
  "properties": {
    "iso:country":"US",
    "sg:address":"401 W Walnut Ln",
    "sg:city":"Philadelphia",
    "sg:classifiers":[
        {
            "category":"Real Estate",
            "subcategory":"Real Estate Operator",
            "type":"Services"
        }
    ],
    "sg:phone":"+1   ",
    "sg:postcode":"19144",
    "sg:province":"PA",
    "sg:tags":[
        "building",
        "apartment"
    ],
    "wof:name":"Walnut Terrace",
    "wof:placetype":"venue"
},
  "geometry": {"coordinates":[-75.185677,40.033618],"type":"Point"}
}