{
  "type": "Feature",
  "properties": {
    "addr:full":"144 Glentay Ave Lansdowne PA 19050",
    "addr:housenumber":"144",
    "addr:postcode":"19050",
    "addr:street":"Glentay Ave",
    "iso:country":"US",
    "sg:address":"144 Glentay Ave",
    "sg:city":"Lansdowne",
    "sg:classifiers":[
        {
            "category":"Health Services",
            "subcategory":"Nursing And Care Facility",
            "type":"Services"
        }
    ],
    "sg:phone":"+1   ",
    "sg:postcode":"19050",
    "sg:province":"PA",
    "sg:tags":[
        "skilled"
    ],
    "wof:name":"Oncology Nursing Society",
    "wof:placetype":"venue"
},
  "geometry": {"coordinates":[-75.28317699999999,39.94439],"type":"Point"}
}