{
  "type": "Feature",
  "properties": {
    "iso:country":"US",
    "sg:address":"78 W End Rd",
    "sg:city":"Wilkes Barre",
    "sg:classifiers":[
        {
            "category":"Shopping",
            "type":"Retail Goods"
        }
    ],
    "sg:phone":"+1   ",
    "sg:postcode":"18706",
    "sg:province":"PA",
    "sg:tags":[
        "cemetery",
        "monument"
    ],
    "wof:name":"Grontkowski F Monument",
    "wof:placetype":"venue"
},
  "geometry": {"coordinates":[-75.92657800000001,41.235147],"type":"Point"}
}