{
  "type": "Feature",
  "properties": {
    "addr:full":"221 Stanbridge Rd Holmes PA 19043",
    "addr:housenumber":"221",
    "addr:postcode":"19043",
    "addr:street":"Stanbridge Rd",
    "iso:country":"US",
    "sg:address":"221 Stanbridge Rd",
    "sg:city":"Holmes",
    "sg:classifiers":[
        {
            "category":"Retail",
            "subcategory":"Auto Repair",
            "type":"Services"
        }
    ],
    "sg:phone":"+1   ",
    "sg:postcode":"19043",
    "sg:province":"PA",
    "sg:tags":[
        "automotive"
    ],
    "wof:name":"Israels Towing",
    "wof:placetype":"venue"
},
  "geometry": {"coordinates":[-75.310652,39.897158],"type":"Point"}
}