{
  "type": "Feature",
  "properties": {
    "iso:country":"US",
    "sg:address":"5861 York Rd",
    "sg:city":"Lahaska",
    "sg:classifiers":[
        {
            "category":"Shopping",
            "subcategory":"Shoes",
            "type":"Retail Goods"
        }
    ],
    "sg:phone":"+1 215 794 8006",
    "sg:postcode":"18938",
    "sg:province":"PA",
    "wof:name":"Easy Spirit",
    "wof:placetype":"venue"
},
  "geometry": {"coordinates":[-75.035989,40.346023],"type":"Point"}
}