{
  "type": "Feature",
  "properties": {
    "iso:country":"US",
    "sg:address":"15 Memorial Hwy",
    "sg:city":"Dallas",
    "sg:classifiers":[
        {
            "category":"Shopping",
            "subcategory":"Computers & Home Electronics",
            "type":"Retail Goods"
        }
    ],
    "sg:phone":"+1 570 675 2347",
    "sg:postcode":"18612",
    "sg:province":"PA",
    "sg:tags":[
        "equipment",
        "dealer"
    ],
    "wof:name":"Campbell Business Machines",
    "wof:placetype":"venue"
},
  "geometry": {"coordinates":[-75.945504,41.326164],"type":"Point"}
}