{
  "type": "Feature",
  "properties": {
    "iso:country":"US",
    "sg:address":"25 6th Ave",
    "sg:city":"Indiana",
    "sg:classifiers":[
        {
            "category":"Building & Trades",
            "subcategory":"Plumbing",
            "type":"Services"
        }
    ],
    "sg:phone":"+1 724 463 6284",
    "sg:postcode":"15701",
    "sg:province":"PA",
    "sg:tags":[
        "heating",
        "contractor"
    ],
    "wof:name":"Schultheis Brothers",
    "wof:placetype":"venue"
},
  "geometry": {"coordinates":[-79.050341,40.642965],"type":"Point"}
}