{
  "type": "Feature",
  "properties": {
    "iso:country":"US",
    "sg:address":"2510 Secane Ave",
    "sg:city":"Swarthmore",
    "sg:classifiers":[
        {
            "category":"Building & Trades",
            "subcategory":"Landscaping Services",
            "type":"Services"
        }
    ],
    "sg:phone":"+1 610 328 9230",
    "sg:postcode":"19018",
    "sg:province":"PA",
    "sg:tags":[
        "landscape",
        "contractor"
    ],
    "wof:name":"Amoroso's Lawn Maintenance",
    "wof:placetype":"venue"
},
  "geometry": {"coordinates":[-75.312742,39.913595],"type":"Point"}
}