{
  "type": "Feature",
  "properties": {
    "iso:country":"US",
    "sg:address":"699 Golden Oaks Rd",
    "sg:city":"New Freeport",
    "sg:classifiers":[
        {
            "category":"Retail",
            "subcategory":"Auto Repair",
            "type":"Services"
        }
    ],
    "sg:phone":"+1 724 447 2099",
    "sg:postcode":"15352",
    "sg:province":"PA",
    "sg:tags":[
        "repairing",
        "automobile",
        "general"
    ],
    "wof:name":"Dave's Garage",
    "wof:placetype":"venue"
},
  "geometry": {"coordinates":[-80.418571,39.74972],"type":"Point"}
}