{
  "type": "Feature",
  "properties": {
    "iso:country":"US",
    "sg:address":"4417 Frankford Ave",
    "sg:city":"Philadelphia",
    "sg:classifiers":[
        {
            "category":"Shopping",
            "subcategory":"Clothing, Apparel, & Fashions",
            "type":"Retail Goods"
        }
    ],
    "sg:phone":"+1   ",
    "sg:postcode":"19124",
    "sg:province":"PA",
    "wof:name":"Smalls Formal Wear Rentl & Sls",
    "wof:placetype":"venue"
},
  "geometry": {"coordinates":[-75.08644,40.013604],"type":"Point"}
}