{
  "type": "Feature",
  "properties": {
    "iso:country":"US",
    "sg:address":"4258 E Bristol Rd",
    "sg:city":"Feasterville Trevose",
    "sg:classifiers":[
        {
            "category":"Building & Trades",
            "subcategory":"Locksmith",
            "type":"Services"
        }
    ],
    "sg:phone":"+1 215 494 7169",
    "sg:postcode":"19053",
    "sg:province":"PA",
    "sg:tags":[
        "key"
    ],
    "wof:name":"AAA 24 Hour Emergency Locksmith",
    "wof:placetype":"venue"
},
  "geometry": {"coordinates":[-74.960059,40.147354],"type":"Point"}
}