{
  "type": "Feature",
  "properties": {
    "iso:country":"US",
    "sg:address":"300 Coral St",
    "sg:city":"Lancaster",
    "sg:classifiers":[
        {
            "category":"Food & Beverages",
            "subcategory":"Groceries & Convenience Stores",
            "type":"Retail Goods"
        }
    ],
    "sg:phone":"+1 717 299 7310",
    "sg:postcode":"17603",
    "sg:province":"PA",
    "sg:tags":[
        "grocer"
    ],
    "wof:name":"Latin American Deli Grocery",
    "wof:placetype":"venue"
},
  "geometry": {"coordinates":[-76.31866599999999,40.033597],"type":"Point"}
}