{
  "type": "Feature",
  "properties": {
    "iso:country":"US",
    "sg:address":"1118 Griffith Rd",
    "sg:city":"Ligonier",
    "sg:classifiers":[
        {
            "category":"Professional",
            "subcategory":"Management & Consulting",
            "type":"Services"
        }
    ],
    "sg:phone":"+1   ",
    "sg:postcode":"15658",
    "sg:province":"PA",
    "sg:tags":[
        "planner",
        "financial"
    ],
    "wof:name":"A Dennis Muia Fincl Plg Svc",
    "wof:placetype":"venue"
},
  "geometry": {"coordinates":[-79.176446,40.254608],"type":"Point"}
}