{
  "type": "Feature",
  "properties": {
    "addr:full":"7765 Mountain Rd Macungie PA 18062",
    "addr:housenumber":"7765",
    "addr:postcode":"18062",
    "addr:street":"Mountain Rd",
    "iso:country":"US",
    "sg:address":"7765 Mountain Rd",
    "sg:city":"Macungie",
    "sg:classifiers":[
        {
            "category":"Building & Trades",
            "subcategory":"Construction",
            "type":"Services"
        }
    ],
    "sg:phone":"+1 610 967 3071",
    "sg:postcode":"18062",
    "sg:province":"PA",
    "sg:tags":[
        "excavation",
        "excavating",
        "contractor"
    ],
    "wof:name":"Steven J Krause Excavating",
    "wof:placetype":"venue"
},
  "geometry": {"coordinates":[-75.58927300000001,40.494702],"type":"Point"}
}