{
  "type": "Feature",
  "properties": {
    "iso:country":"US",
    "sg:address":"4734 William Penn Hwy",
    "sg:city":"Monroeville",
    "sg:classifiers":[
        {
            "category":"Home & Garden",
            "subcategory":"Garden Supply",
            "type":"Retail Goods"
        }
    ],
    "sg:phone":"+1   ",
    "sg:postcode":"15146",
    "sg:province":"PA",
    "wof:name":"Tlic",
    "wof:placetype":"venue"
},
  "geometry": {"coordinates":[-79.72807,40.429508],"type":"Point"}
}