{
  "type": "Feature",
  "properties": {
    "iso:country":"US",
    "sg:address":"2066 W Indiana Ave",
    "sg:city":"Philadelphia",
    "sg:classifiers":[
        {
            "category":"Food & Beverages",
            "subcategory":"Groceries & Convenience Stores",
            "type":"Retail Goods"
        }
    ],
    "sg:phone":"+1 215 221 5999",
    "sg:postcode":"19132",
    "sg:province":"PA",
    "wof:name":"Indiana Mini Market",
    "wof:placetype":"venue"
},
  "geometry": {"coordinates":[-75.164637,39.999829],"type":"Point"}
}