{
  "type": "Feature",
  "properties": {
    "addr:full":"106 Steamboat Dr Warminster PA 18974",
    "addr:housenumber":"106",
    "addr:postcode":"18974",
    "addr:street":"Steamboat Dr",
    "iso:country":"US",
    "sg:address":"106 Steamboat Dr",
    "sg:city":"Warminster",
    "sg:classifiers":[
        {
            "category":"Manufacturing",
            "subcategory":"Furniture",
            "type":"Manufacturing & Wholesale Goods"
        }
    ],
    "sg:phone":"+1   ",
    "sg:postcode":"18974",
    "sg:province":"PA",
    "sg:tags":[
        "mfg",
        "wood",
        "furn"
    ],
    "wof:name":"A/S Custom Furniture Company",
    "wof:placetype":"venue"
},
  "geometry": {"coordinates":[-75.082797,40.193318],"type":"Point"}
}