{
  "type": "Feature",
  "properties": {
    "iso:country":"US",
    "sg:address":"1 Isabella St",
    "sg:city":"Pittsburgh",
    "sg:classifiers":[
        {
            "category":"Recreation",
            "type":"Entertainment"
        },
        {
            "category":"Organizations",
            "subcategory":"Community Association",
            "type":"Services"
        }
    ],
    "sg:phone":"+1 412 781 9830",
    "sg:postcode":"15223",
    "sg:province":"PA",
    "sg:tags":[
        "club",
        "membership"
    ],
    "wof:name":"Jockey Club Of Etna",
    "wof:placetype":"venue"
},
  "geometry": {"coordinates":[-79.946268,40.494077],"type":"Point"}
}