{
  "type": "Feature",
  "properties": {
    "iso:country":"US",
    "sg:address":"34 Carlisle St",
    "sg:city":"Hanover",
    "sg:classifiers":[
        {
            "category":"Shopping",
            "type":"Retail Goods"
        }
    ],
    "sg:phone":"+1 717 646 1010",
    "sg:postcode":"17331",
    "sg:province":"PA",
    "sg:tags":[
        "material",
        "artist",
        "supply"
    ],
    "wof:name":"Hanover Art Supplies",
    "wof:placetype":"venue"
},
  "geometry": {"coordinates":[-76.98439999999999,39.801384],"type":"Point"}
}