{
  "type": "Feature",
  "properties": {
    "iso:country":"US",
    "sg:address":"85 W Main St",
    "sg:city":"New Kingstown",
    "sg:classifiers":[
        {
            "category":"Professional",
            "type":"Services"
        }
    ],
    "sg:phone":"+1 717 791 9872",
    "sg:postcode":"17072",
    "sg:province":"PA",
    "sg:tags":[
        "establishment"
    ],
    "wof:name":"Pal Amal",
    "wof:placetype":"venue"
},
  "geometry": {"coordinates":[-77.08587300000001,40.232534],"type":"Point"}
}