{
  "type": "Feature",
  "properties": {
    "iso:country":"US",
    "sg:address":"The Brickyard 350 N Broad St",
    "sg:city":"Doylestown",
    "sg:classifiers":[
        {
            "category":"Personal",
            "subcategory":"Beauty Salon",
            "type":"Services"
        },
        {
            "category":"Shopping",
            "subcategory":"Pets & Pet Supplies",
            "type":"Retail Goods"
        }
    ],
    "sg:phone":"+1 215 340 3647",
    "sg:postcode":"18901",
    "sg:province":"PA",
    "sg:tags":[
        "groomers"
    ],
    "sg:website":"www.dogdazepetgrooming.com/",
    "wof:name":"Dog Daze Canine Hair Salon",
    "wof:placetype":"venue"
},
  "geometry": {"coordinates":[-75.13556,40.316414],"type":"Point"}
}