{
  "type": "Feature",
  "properties": {
    "addr:full":"20 N Park Ave Mercersburg PA 17236",
    "addr:housenumber":"20",
    "addr:postcode":"17236",
    "addr:street":"N Park Ave",
    "iso:country":"US",
    "sg:address":"20 N Park Ave",
    "sg:city":"Mercersburg",
    "sg:classifiers":[
        {
            "category":"Organizations",
            "subcategory":"Religious Organization",
            "type":"Services"
        }
    ],
    "sg:phone":"+1 717 328 5424",
    "sg:postcode":"17236",
    "sg:province":"PA",
    "sg:tags":[
        "church"
    ],
    "wof:name":"Assembly Of God Church",
    "wof:placetype":"venue"
},
  "geometry": {"coordinates":[-77.905433,39.828966],"type":"Point"}
}