{
  "type": "Feature",
  "properties": {
    "iso:country":"US",
    "sg:address":"118 Killinger Rd",
    "sg:city":"Annville",
    "sg:classifiers":[
        {
            "category":"Farming",
            "subcategory":"Poultry Farm",
            "type":"Manufacturing & Wholesale Goods"
        }
    ],
    "sg:phone":"+1 717 867 1269",
    "sg:postcode":"17003",
    "sg:province":"PA",
    "sg:tags":[
        "chicken",
        "eggs"
    ],
    "wof:name":"Providence Egg Producers",
    "wof:placetype":"venue"
},
  "geometry": {"coordinates":[-76.561604,40.306357],"type":"Point"}
}