{
  "type": "Feature",
  "properties": {
    "iso:country":"US",
    "sg:address":"83 S Hamilton St",
    "sg:city":"Doylestown",
    "sg:classifiers":[
        {
            "category":"Home & Garden",
            "subcategory":"Garden Supply",
            "type":"Retail Goods"
        },
        {
            "category":"Shopping",
            "subcategory":"Gifts & Souvenirs",
            "type":"Retail Goods"
        },
        {
            "category":"Shopping",
            "subcategory":"Crafts & Fabrics",
            "type":"Retail Goods"
        },
        {
            "category":"Shopping",
            "subcategory":"Florist",
            "type":"Retail Goods"
        }
    ],
    "sg:phone":"+1 215 230 8410",
    "sg:postcode":"18901",
    "sg:province":"PA",
    "sg:tags":[
        "plant",
        "etc-retail",
        "dried",
        "basket",
        "trees-silk",
        "flowers"
    ],
    "sg:website":"http://www.doylestownfloribunda.com",
    "wof:name":"Doylestown Floribunda",
    "wof:placetype":"venue"
},
  "geometry": {"coordinates":[-75.13029299999999,40.307875],"type":"Point"}
}