{
  "type": "Feature",
  "properties": {
    "addr:full":"2050 State St Harrisburg PA 17103",
    "addr:housenumber":"2050",
    "addr:postcode":"17103",
    "addr:street":"State St",
    "iso:country":"US",
    "sg:address":"2050 State St",
    "sg:city":"Harrisburg",
    "sg:classifiers":[
        {
            "category":"Personal",
            "type":"Services"
        },
        {
            "category":"Retail",
            "subcategory":"Laundry & Dry Cleaning",
            "type":"Services"
        }
    ],
    "sg:phone":"+1 717 238 4881",
    "sg:postcode":"17103",
    "sg:province":"PA",
    "sg:tags":[
        "sewing",
        "alteration"
    ],
    "wof:name":"Georges Cleaners",
    "wof:placetype":"venue"
},
  "geometry": {"coordinates":[-76.859909,40.274734],"type":"Point"}
}