{
  "type": "Feature",
  "properties": {
    "iso:country":"US",
    "sg:address":"534 Eden Park Blvd",
    "sg:city":"Mc Keesport",
    "sg:classifiers":[
        {
            "category":"Retail",
            "subcategory":"Auto Repair",
            "type":"Services"
        }
    ],
    "sg:phone":"+1   ",
    "sg:postcode":"15132",
    "sg:province":"PA",
    "sg:tags":[
        "body",
        "good"
    ],
    "wof:name":"Advertising Ideas",
    "wof:placetype":"venue"
},
  "geometry": {"coordinates":[-79.833855,40.329043],"type":"Point"}
}