{
  "type": "Feature",
  "properties": {
    "addr:full":"2830 Norcross Ln Philadelphia PA 19114",
    "addr:housenumber":"2830",
    "addr:postcode":"19114",
    "addr:street":"Norcross Ln",
    "iso:country":"US",
    "sg:address":"2830 Norcross Ln",
    "sg:city":"Philadelphia",
    "sg:classifiers":[
        {
            "category":"Professional",
            "subcategory":"Art Services",
            "type":"Services"
        }
    ],
    "sg:phone":"+1 215 677 2011",
    "sg:postcode":"19114",
    "sg:province":"PA",
    "sg:tags":[
        "graphic",
        "designer"
    ],
    "wof:name":"Visual Concepts Unlimited Co",
    "wof:placetype":"venue"
},
  "geometry": {"coordinates":[-75.016401,40.068056],"type":"Point"}
}