{
  "type": "Feature",
  "properties": {
    "iso:country":"US",
    "sg:address":"306 Grant St",
    "sg:city":"Olyphant",
    "sg:classifiers":[
        {
            "category":"Professional",
            "subcategory":"Engineering",
            "type":"Services"
        },
        {
            "category":"Retail",
            "subcategory":"Repair Shop",
            "type":"Services"
        },
        {
            "category":"Building & Trades",
            "subcategory":"Construction",
            "type":"Services"
        }
    ],
    "sg:phone":"+1 570 489 8991",
    "sg:postcode":"18447",
    "sg:province":"PA",
    "sg:tags":[
        "system",
        "specialty",
        "heating",
        "refrigeration",
        "air conditioning",
        "contractor",
        "freezers-repair",
        "refrigerator",
        "engineer"
    ],
    "wof:name":"J&F Refrigeration And Conditoning Service, Llc",
    "wof:placetype":"venue"
},
  "geometry": {"coordinates":[-75.602743,41.47028],"type":"Point"}
}