{
  "type": "Feature",
  "properties": {
    "addr:full":"102 N 2nd St Philadelphia PA 19106",
    "addr:housenumber":"102",
    "addr:postcode":"19106",
    "addr:street":"N 2Nd St",
    "iso:country":"US",
    "sg:address":"102 N 2nd St",
    "sg:city":"Philadelphia",
    "sg:classifiers":[
        {
            "category":"Shopping",
            "subcategory":"Tobacco",
            "type":"Retail Goods"
        }
    ],
    "sg:phone":"+1 215 922 3822",
    "sg:postcode":"19106",
    "sg:province":"PA",
    "sg:tags":[
        "shop"
    ],
    "wof:name":"Second Street Wholesalers",
    "wof:placetype":"venue"
},
  "geometry": {"coordinates":[-75.143097,39.952],"type":"Point"}
}