{
  "type": "Feature",
  "properties": {
    "addr:full":"213 Limestone Rd Oxford PA 19363",
    "addr:housenumber":"213",
    "addr:postcode":"19363",
    "addr:street":"Limestone Rd",
    "iso:country":"US",
    "sg:address":"213 Limestone Rd",
    "sg:city":"Oxford",
    "sg:classifiers":[
        {
            "category":"Retail",
            "subcategory":"Animal Services",
            "type":"Services"
        }
    ],
    "sg:phone":"+1 610 998 9429",
    "sg:postcode":"19363",
    "sg:province":"PA",
    "sg:tags":[
        "pet",
        "grooming",
        "washing"
    ],
    "wof:name":"Tails R' Wagging Pet Salon",
    "wof:placetype":"venue"
},
  "geometry": {"coordinates":[-75.973354,39.798496],"type":"Point"}
}