{
  "type": "Feature",
  "properties": {
    "iso:country":"US",
    "sg:address":"63 S Washington St",
    "sg:city":"Waynesburg",
    "sg:classifiers":[
        {
            "category":"Professional",
            "subcategory":"Lawyer & Legal Services",
            "type":"Services"
        }
    ],
    "sg:phone":"+1 724 627 3127",
    "sg:postcode":"15370",
    "sg:province":"PA",
    "sg:tags":[
        "clinic"
    ],
    "wof:name":"Southwestern Pa Legal Aid",
    "wof:placetype":"venue"
},
  "geometry": {"coordinates":[-80.187023,39.8955],"type":"Point"}
}