{
  "type": "Feature",
  "properties": {
    "iso:country":"US",
    "sg:address":"653 E Lancaster Ave",
    "sg:city":"Radnor",
    "sg:classifiers":[
        {
            "category":"Shopping",
            "subcategory":"Crafts & Fabrics",
            "type":"Retail Goods"
        }
    ],
    "sg:phone":"+1 610 688 1505",
    "sg:postcode":"19087",
    "sg:province":"PA",
    "sg:tags":[
        "shop"
    ],
    "sg:website":"www.calicocorners.com",
    "wof:name":"Calico Corners",
    "wof:placetype":"venue"
},
  "geometry": {"coordinates":[-75.405413,40.04616],"type":"Point"}
}