{
  "type": "Feature",
  "properties": {
    "addr:full":"125 Hillvue Ln Pittsburgh PA 15237",
    "addr:housenumber":"125",
    "addr:postcode":"15237",
    "addr:street":"Hillvue Ln",
    "iso:country":"US",
    "sg:address":"125 Hillvue Ln",
    "sg:city":"Pittsburgh",
    "sg:classifiers":[
        {
            "category":"Professional",
            "subcategory":"Management & Consulting",
            "type":"Services"
        },
        {
            "category":"Professional",
            "subcategory":"Advertising",
            "type":"Services"
        }
    ],
    "sg:phone":"+1 412 381 4302",
    "sg:postcode":"15237",
    "sg:province":"PA",
    "sg:tags":[
        "marketing",
        "program",
        "consultant"
    ],
    "wof:name":"Nine 10 Interactive",
    "wof:placetype":"venue"
},
  "geometry": {"coordinates":[-80.03720800000001,40.569335],"type":"Point"}
}