{
  "type": "Feature",
  "properties": {
    "addr:full":"110 Clay Ave Jeannette PA 15644",
    "addr:housenumber":"110",
    "addr:postcode":"15644",
    "addr:street":"Clay Ave",
    "iso:country":"US",
    "sg:address":"110 Clay Ave",
    "sg:city":"Jeannette",
    "sg:classifiers":[
        {
            "category":"Government",
            "subcategory":"Office",
            "type":"Public Place"
        }
    ],
    "sg:phone":"+1   ",
    "sg:postcode":"15644",
    "sg:province":"PA",
    "sg:tags":[
        "general"
    ],
    "wof:name":"Code Enforcement",
    "wof:placetype":"venue"
},
  "geometry": {"coordinates":[-79.615465,40.325852],"type":"Point"}
}