{
  "type": "Feature",
  "properties": {
    "addr:full":"475 Church Rd Avondale PA 19311",
    "addr:housenumber":"475",
    "addr:postcode":"19311",
    "addr:street":"Church Rd",
    "iso:country":"US",
    "sg:address":"475 Church Rd",
    "sg:city":"Avondale",
    "sg:classifiers":[
        {
            "category":"Building & Trades",
            "subcategory":"Landscaping Services",
            "type":"Services"
        }
    ],
    "sg:phone":"+1 610 268 2205",
    "sg:postcode":"19311",
    "sg:province":"PA",
    "sg:tags":[
        "landscape",
        "contractor"
    ],
    "wof:name":"Creative Garden Solutions Inc",
    "wof:placetype":"venue"
},
  "geometry": {"coordinates":[-75.77587800000001,39.836897],"type":"Point"}
}