{
  "type": "Feature",
  "properties": {
    "addr:full":"1800 State Rte 286 Pittsburgh PA 15239",
    "addr:housenumber":"1800",
    "addr:postcode":"15239",
    "addr:street":"State Rte 286",
    "iso:country":"US",
    "sg:address":"1800 State Rte 286",
    "sg:city":"Pittsburgh",
    "sg:classifiers":[
        {
            "category":"Autos & Motor Vehicles",
            "subcategory":"Fuel & Gas Station",
            "type":"Retail Goods"
        }
    ],
    "sg:phone":"+1   ",
    "sg:postcode":"15239",
    "sg:province":"PA",
    "sg:tags":[
        "station",
        "gasoline"
    ],
    "wof:name":"Roberts BP Service",
    "wof:placetype":"venue"
},
  "geometry": {"coordinates":[-79.713571,40.450827],"type":"Point"}
}