{
  "type": "Feature",
  "properties": {
    "iso:country":"US",
    "sg:address":"100 Union St",
    "sg:city":"Bridgeville",
    "sg:classifiers":[
        {
            "category":"Wholesale",
            "subcategory":"Machinery & Supplies",
            "type":"Manufacturing & Wholesale Goods"
        }
    ],
    "sg:phone":"+1   ",
    "sg:postcode":"15017",
    "sg:province":"PA",
    "sg:tags":[
        "distributor",
        "abrasive"
    ],
    "wof:name":"RG Brewton",
    "wof:placetype":"venue"
},
  "geometry": {"coordinates":[-80.105611,40.361765],"type":"Point"}
}