{
  "type": "Feature",
  "properties": {
    "addr:full":"955 N Center St Corry PA 16407",
    "addr:housenumber":"955",
    "addr:postcode":"16407",
    "addr:street":"N Center St",
    "iso:country":"US",
    "sg:address":"955 N Center St",
    "sg:city":"Corry",
    "sg:classifiers":[
        {
            "category":"Wholesale",
            "subcategory":"Auto Parts",
            "type":"Manufacturing & Wholesale Goods"
        }
    ],
    "sg:phone":"+1 814 664 7731",
    "sg:postcode":"16407",
    "sg:province":"PA",
    "sg:tags":[
        "supply"
    ],
    "wof:name":"NAPA Auto Parts",
    "wof:placetype":"venue"
},
  "geometry": {"coordinates":[-79.641418,41.932297],"type":"Point"}
}