{
  "type": "Feature",
  "properties": {
    "iso:country":"US",
    "sg:address":"1928 Carpenter St",
    "sg:city":"Philadelphia",
    "sg:classifiers":[
        {
            "category":"Professional",
            "subcategory":"Management & Consulting",
            "type":"Services"
        }
    ],
    "sg:phone":"+1 215 545 1778",
    "sg:postcode":"19146",
    "sg:province":"PA",
    "sg:tags":[
        "consultant",
        "business"
    ],
    "wof:name":"Imani Star Development Inc",
    "wof:placetype":"venue"
},
  "geometry": {"coordinates":[-75.175721,39.940122],"type":"Point"}
}