{
  "type": "Feature",
  "properties": {
    "iso:country":"US",
    "sg:address":"135 Sherwood Dr",
    "sg:city":"Greensburg",
    "sg:classifiers":[
        {
            "category":"Building & Trades",
            "subcategory":"Electrical",
            "type":"Services"
        }
    ],
    "sg:phone":"+1   ",
    "sg:postcode":"15601",
    "sg:province":"PA",
    "sg:tags":[
        "electrical",
        "contractor"
    ],
    "wof:name":"Thorsen Electric",
    "wof:placetype":"venue"
},
  "geometry": {"coordinates":[-79.50578899999999,40.282619],"type":"Point"}
}