{
  "type": "Feature",
  "properties": {
    "iso:country":"US",
    "sg:address":"20 Industrial Dr",
    "sg:city":"Hamburg",
    "sg:classifiers":[
        {
            "category":"Autos & Motor Vehicles",
            "subcategory":"Recreational Vehicle Sales",
            "type":"Retail Goods"
        }
    ],
    "sg:phone":"+1 610 562 2513",
    "sg:postcode":"19526",
    "sg:province":"PA",
    "wof:name":"Boat & Rv Superstore",
    "wof:placetype":"venue"
},
  "geometry": {"coordinates":[-75.99767900000001,40.559697],"type":"Point"}
}