{
  "type": "Feature",
  "properties": {
    "addr:full":"5802 Master St Philadelphia PA 19131",
    "addr:housenumber":"5802",
    "addr:postcode":"19131",
    "addr:street":"Master St",
    "iso:country":"US",
    "sg:address":"5802 Master St",
    "sg:city":"Philadelphia",
    "sg:classifiers":[
        {
            "category":"Social Services",
            "type":"Services"
        }
    ],
    "sg:phone":"+1 215 477 6260",
    "sg:postcode":"19131",
    "sg:province":"PA",
    "sg:tags":[
        "youth",
        "organization",
        "center"
    ],
    "wof:name":"Neighborhood Youth Achievement",
    "wof:placetype":"venue"
},
  "geometry": {"coordinates":[-75.23675299999999,39.97302],"type":"Point"}
}