{
  "type": "Feature",
  "properties": {
    "iso:country":"US",
    "sg:address":"2601 W 26th St",
    "sg:city":"Erie",
    "sg:classifiers":[
        {
            "category":"Real Estate",
            "subcategory":"Real Estate Operator",
            "type":"Services"
        }
    ],
    "sg:phone":"+1 814 833 8900",
    "sg:postcode":"16506",
    "sg:province":"PA",
    "sg:tags":[
        "housing",
        "student"
    ],
    "sg:website":"www.wpperie.com",
    "wof:name":"Westminster Place Partnership",
    "wof:placetype":"venue"
},
  "geometry": {"coordinates":[-80.132267,42.090111],"type":"Point"}
}