{
  "type": "Feature",
  "properties": {
    "iso:country":"US",
    "sg:address":"1503 N 17th St",
    "sg:city":"Philadelphia",
    "sg:classifiers":[
        {
            "category":"Building & Trades",
            "subcategory":"Construction",
            "type":"Services"
        }
    ],
    "sg:phone":"+1 215 654 5250",
    "sg:postcode":"19121",
    "sg:province":"PA",
    "sg:tags":[
        "general",
        "contractor"
    ],
    "wof:name":"Harlee Corp",
    "wof:placetype":"venue"
},
  "geometry": {"coordinates":[-75.162937,39.977857],"type":"Point"}
}