{
  "type": "Feature",
  "properties": {
    "iso:country":"US",
    "sg:address":"157 Waterdam Rd Ste 280",
    "sg:city":"Canonsburg",
    "sg:classifiers":[
        {
            "category":"Real Estate",
            "subcategory":"Real Estate Services",
            "type":"Services"
        },
        {
            "category":"Banks & Credit Unions",
            "subcategory":"Financial Services",
            "type":"Services"
        }
    ],
    "sg:phone":"+1 724 260 0571",
    "sg:postcode":"15317",
    "sg:province":"PA",
    "sg:tags":[
        "loan",
        "processing",
        "broker",
        "mortgage"
    ],
    "wof:name":"Eagle Nationwide Mortgage",
    "wof:placetype":"venue"
},
  "geometry": {"coordinates":[-80.13207,40.260072],"type":"Point"}
}