{
  "type": "Feature",
  "properties": {
    "iso:country":"US",
    "sg:address":"2533 Leechburg Rd",
    "sg:city":"Lower Burrell",
    "sg:classifiers":[
        {
            "category":"Health Services",
            "subcategory":"Doctor",
            "type":"Services"
        }
    ],
    "sg:phone":"+1 724 339 1143",
    "sg:postcode":"15068",
    "sg:province":"PA",
    "sg:tags":[
        "physician",
        "medical",
        "surgeon"
    ],
    "wof:name":"Center For Behavioral Medicine",
    "wof:placetype":"venue"
},
  "geometry": {"coordinates":[-79.744145,40.58833],"type":"Point"}
}