{
  "type": "Feature",
  "properties": {
    "iso:country":"US",
    "sg:address":"820 N Cherry St",
    "sg:city":"Lancaster",
    "sg:classifiers":[
        {
            "category":"Organizations",
            "subcategory":"Community Association",
            "type":"Services"
        }
    ],
    "sg:phone":"+1 717 396 9311",
    "sg:postcode":"17602",
    "sg:province":"PA",
    "sg:tags":[
        "club"
    ],
    "wof:name":"Lancaster Association Of Deaf",
    "wof:placetype":"venue"
},
  "geometry": {"coordinates":[-76.305171,40.051084],"type":"Point"}
}