{
  "type": "Feature",
  "properties": {
    "iso:country":"US",
    "sg:address":"13 Merion Ter",
    "sg:city":"Upper Darby",
    "sg:classifiers":[
        {
            "category":"Restaurant",
            "type":"Food & Drink"
        }
    ],
    "sg:phone":"+1   ",
    "sg:postcode":"19082",
    "sg:province":"PA",
    "sg:tags":[
        "eating"
    ],
    "wof:name":"One Crazy Greek Pizza",
    "wof:placetype":"venue"
},
  "geometry": {"coordinates":[-75.264495,39.963722],"type":"Point"}
}