{
  "type": "Feature",
  "properties": {
    "addr:full":"66 Station St Bulger PA 15019",
    "addr:housenumber":"66",
    "addr:postcode":"15019",
    "addr:street":"Station St",
    "iso:country":"US",
    "sg:address":"66 Station St",
    "sg:city":"Bulger",
    "sg:classifiers":[
        {
            "category":"Professional",
            "type":"Services"
        }
    ],
    "sg:phone":"+1   ",
    "sg:postcode":"15019",
    "sg:province":"PA",
    "wof:name":"Randy R Curtis",
    "wof:placetype":"venue"
},
  "geometry": {"coordinates":[-80.360322,40.383082],"type":"Point"}
}