{
  "type": "Feature",
  "properties": {
    "addr:full":"160 Jalyn Dr New Holland PA 17557",
    "addr:housenumber":"160",
    "addr:postcode":"17557",
    "addr:street":"Jalyn Dr",
    "iso:country":"US",
    "sg:address":"160 Jalyn Dr",
    "sg:city":"New Holland",
    "sg:classifiers":[
        {
            "category":"Freight",
            "type":"Transportation"
        }
    ],
    "sg:phone":"+1 717 355 9676",
    "sg:postcode":"17557",
    "sg:province":"PA",
    "sg:tags":[
        "special"
    ],
    "wof:name":"Orlan Self Storage",
    "wof:placetype":"venue"
},
  "geometry": {"coordinates":[-76.087858,40.089213],"type":"Point"}
}