{
  "type": "Feature",
  "properties": {
    "iso:country":"US",
    "sg:address":"301 E Pennsylvania Blvd",
    "sg:city":"Feastervl Trvs",
    "sg:classifiers":[
        {
            "category":"Health Services",
            "subcategory":"Medical Lab",
            "type":"Services"
        }
    ],
    "sg:phone":"+1 215 396 9056",
    "sg:postcode":"19053",
    "sg:province":"PA",
    "sg:tags":[
        "laboratory",
        "dental"
    ],
    "wof:name":"Broadway Ceramic Dental Studio",
    "wof:placetype":"venue"
},
  "geometry": {"coordinates":[-75.00991,40.151645],"type":"Point"}
}