{
  "type": "Feature",
  "properties": {
    "iso:country":"US",
    "sg:address":"245 S Main St",
    "sg:city":"Greensburg",
    "sg:classifiers":[
        {
            "category":"Shopping",
            "subcategory":"Florist",
            "type":"Retail Goods"
        }
    ],
    "sg:phone":"+1   ",
    "sg:postcode":"15601",
    "sg:province":"PA",
    "wof:name":"Guffey Brothers Inc",
    "wof:placetype":"venue"
},
  "geometry": {"coordinates":[-79.543603,40.30081],"type":"Point"}
}