{
  "type": "Feature",
  "properties": {
    "addr:full":"4261 Shangri la Rd Stewartstown PA 17363",
    "addr:postcode":"4261;17363",
    "addr:street":"Shangri La Rd",
    "iso:country":"US",
    "sg:address":"4261 Shangri la Rd",
    "sg:city":"Stewartstown",
    "sg:classifiers":[
        {
            "category":"Building & Trades",
            "subcategory":"Construction",
            "type":"Services"
        }
    ],
    "sg:phone":"+1   ",
    "sg:postcode":"17363",
    "sg:province":"PA",
    "sg:tags":[
        "chemical",
        "repair",
        "industrial",
        "commercial",
        "grout"
    ],
    "wof:name":"Mason Dixon Building Maint",
    "wof:placetype":"venue"
},
  "geometry": {"coordinates":[-76.602508,39.81165],"type":"Point"}
}