{
  "type": "Feature",
  "properties": {
    "iso:country":"US",
    "sg:address":"140 Myrtle Ave",
    "sg:city":"Waynesboro",
    "sg:classifiers":[
        {
            "category":"Professional",
            "type":"Services"
        }
    ],
    "sg:phone":"+1   ",
    "sg:postcode":"17268",
    "sg:province":"PA",
    "wof:name":"Woodcrafters",
    "wof:placetype":"venue"
},
  "geometry": {"coordinates":[-77.573351,39.750476],"type":"Point"}
}