{
  "type": "Feature",
  "properties": {
    "iso:country":"US",
    "sg:address":"9 N Chester Rd",
    "sg:city":"West Chester",
    "sg:classifiers":[
        {
            "category":"Health Services",
            "subcategory":"Doctor",
            "type":"Services"
        }
    ],
    "sg:phone":"+1   ",
    "sg:postcode":"19380",
    "sg:province":"PA",
    "wof:name":"Robert S White DDS",
    "wof:placetype":"venue"
},
  "geometry": {"coordinates":[-75.524057,39.967297],"type":"Point"}
}