{
  "type": "Feature",
  "properties": {
    "addr:full":"9000 Perry Hwy Pittsburgh PA 15237",
    "addr:housenumber":"9000",
    "addr:postcode":"15237",
    "addr:street":"Perry Hwy",
    "iso:country":"US",
    "sg:address":"9000 Perry Hwy",
    "sg:city":"Pittsburgh",
    "sg:classifiers":[
        {
            "category":"Health Services",
            "subcategory":"Doctor",
            "type":"Services"
        }
    ],
    "sg:phone":"+1 412 367 4250",
    "sg:postcode":"15237",
    "sg:province":"PA",
    "sg:tags":[
        "physician",
        "surgeon"
    ],
    "wof:name":"Associates In Gastroenterology",
    "wof:placetype":"venue"
},
  "geometry": {"coordinates":[-80.037369,40.569252],"type":"Point"}
}