{
  "type": "Feature",
  "properties": {
    "iso:country":"US",
    "sg:address":"35 Woodland Ave",
    "sg:city":"Morton",
    "sg:classifiers":[
        {
            "category":"Insurance",
            "subcategory":"Hazard Insurance",
            "type":"Services"
        },
        {
            "category":"Insurance",
            "subcategory":"Insurance Agent",
            "type":"Services"
        },
        {
            "category":"Insurance",
            "subcategory":"Life Insurance",
            "type":"Services"
        },
        {
            "category":"Insurance",
            "subcategory":"Title Insurance",
            "type":"Services"
        }
    ],
    "sg:phone":"+1 610 544 8070",
    "sg:postcode":"19070",
    "sg:province":"PA",
    "sg:tags":[
        "auto",
        "homeowner"
    ],
    "sg:website":"http://www.nationwide.com/agent/Morton-PENNSYLVANIA-insurance-agent/chrislamoureux/office.html",
    "wof:name":"Christopher Lamoureux - Nationwide Insurance",
    "wof:placetype":"venue"
},
  "geometry": {"coordinates":[-75.327921,39.908584],"type":"Point"}
}