{
  "type": "Feature",
  "properties": {
    "iso:country":"US",
    "sg:address":"206 Westwood Ave",
    "sg:city":"Masontown",
    "sg:classifiers":[
        {
            "category":"Health Services",
            "subcategory":"Nursing And Care Facility",
            "type":"Services"
        }
    ],
    "sg:phone":"+1 724 583 0620",
    "sg:postcode":"15461",
    "sg:province":"PA",
    "sg:tags":[
        "intermediate"
    ],
    "wof:name":"Cloverdale Personal Care Home",
    "wof:placetype":"venue"
},
  "geometry": {"coordinates":[-79.915008,39.851446],"type":"Point"}
}