{
  "type": "Feature",
  "properties": {
    "addr:full":"410 E Main St Mechanicsburg PA 17055",
    "addr:housenumber":"410",
    "addr:postcode":"17055",
    "addr:street":"E Main St",
    "iso:country":"US",
    "sg:address":"410 E Main St",
    "sg:city":"Mechanicsburg",
    "sg:classifiers":[
        {
            "category":"Health Services",
            "subcategory":"Doctor",
            "type":"Services"
        },
        {
            "category":"Health Services",
            "subcategory":"Clinic",
            "type":"Services"
        }
    ],
    "sg:phone":"+1 717 795 1157",
    "sg:postcode":"17055",
    "sg:province":"PA",
    "sg:tags":[
        "psychological",
        "psychologist"
    ],
    "sg:website":"http://www.intrinsicdevelopment.com",
    "wof:name":"Intrinsic Development",
    "wof:placetype":"venue"
},
  "geometry": {"coordinates":[-77.001212,40.215175],"type":"Point"}
}