{
  "type": "Feature",
  "properties": {
    "iso:country":"US",
    "sg:address":"203 N Redwood St",
    "sg:city":"Masontown",
    "sg:classifiers":[
        {
            "category":"Health Services",
            "subcategory":"Optometrist",
            "type":"Services"
        }
    ],
    "sg:phone":"+1   ",
    "sg:postcode":"15461",
    "sg:province":"PA",
    "wof:name":"Eye Centers",
    "wof:placetype":"venue"
},
  "geometry": {"coordinates":[-79.912155,39.850629],"type":"Point"}
}