{
  "type": "Feature",
  "properties": {
    "addr:full":"301 Duncomb St Oil City PA 16301",
    "addr:housenumber":"301",
    "addr:postcode":"16301",
    "addr:street":"Duncomb St",
    "iso:country":"US",
    "sg:address":"301 Duncomb St",
    "sg:city":"Oil City",
    "sg:classifiers":[
        {
            "category":"Personal",
            "type":"Services"
        }
    ],
    "sg:phone":"+1 814 677 2525",
    "sg:postcode":"16301",
    "sg:province":"PA",
    "wof:name":"Austin Inkorperated",
    "wof:placetype":"venue"
},
  "geometry": {"coordinates":[-79.707095,41.437173],"type":"Point"}
}