{
  "type": "Feature",
  "properties": {
    "addr:full":"165 Rainey Rd Sycamore PA 15330",
    "addr:housenumber":"165",
    "addr:postcode":"15330",
    "addr:street":"Rainey Rd",
    "iso:country":"US",
    "sg:address":"165 Rainey Rd",
    "sg:city":"Sycamore",
    "sg:classifiers":[
        {
            "category":"Recreation",
            "type":"Entertainment"
        }
    ],
    "sg:phone":"+1 724 499 5709",
    "sg:postcode":"15330",
    "sg:province":"PA",
    "sg:tags":[
        "stable"
    ],
    "wof:name":"Save-A-Horse Stable",
    "wof:placetype":"venue"
},
  "geometry": {"coordinates":[-80.115258,40.149501],"type":"Point"}
}