{
  "type": "Feature",
  "properties": {
    "iso:country":"US",
    "sg:address":"2149 E Birch St",
    "sg:city":"Philadelphia",
    "sg:classifiers":[
        {
            "category":"Building & Trades",
            "subcategory":"Cleaning & Sanitation",
            "type":"Services"
        }
    ],
    "sg:phone":"+1 215 739 1050",
    "sg:postcode":"19134",
    "sg:province":"PA",
    "sg:tags":[
        "janitor"
    ],
    "wof:name":"TKO Cleaning Svc",
    "wof:placetype":"venue"
},
  "geometry": {"coordinates":[-75.115257,39.988544],"type":"Point"}
}