{
  "type": "Feature",
  "properties": {
    "addr:full":"434 Comanche Trl Mercer PA 16137",
    "addr:housenumber":"434",
    "addr:postcode":"16137",
    "addr:street":"Comanche Trl",
    "iso:country":"US",
    "sg:address":"434 Comanche Trl",
    "sg:city":"Mercer",
    "sg:classifiers":[
        {
            "category":"Government",
            "subcategory":"Office",
            "type":"Public Place"
        }
    ],
    "sg:phone":"+1 724 475 4931",
    "sg:postcode":"16137",
    "sg:province":"PA",
    "sg:tags":[
        "city",
        "taxation"
    ],
    "wof:name":"Jackson Twp Tax Collector",
    "wof:placetype":"venue"
},
  "geometry": {"coordinates":[-80.175044,41.291214],"type":"Point"}
}