{
  "type": "Feature",
  "properties": {
    "iso:country":"US",
    "sg:address":"8357 Kings Hwy",
    "sg:city":"New Tripoli",
    "sg:classifiers":[
        {
            "category":"Building & Trades",
            "subcategory":"Construction",
            "type":"Services"
        }
    ],
    "sg:phone":"+1   ",
    "sg:postcode":"18066",
    "sg:province":"PA",
    "sg:tags":[
        "house"
    ],
    "wof:name":"Wayne J Greenawalt",
    "wof:placetype":"venue"
},
  "geometry": {"coordinates":[-75.826088,40.672509],"type":"Point"}
}