{
  "type": "Feature",
  "properties": {
    "iso:country":"US",
    "sg:address":"549 New Holland Ave",
    "sg:city":"Lancaster",
    "sg:classifiers":[
        {
            "category":"Restaurant",
            "type":"Food & Drink"
        }
    ],
    "sg:phone":"+1 717 393 6669",
    "sg:postcode":"17602",
    "sg:province":"PA",
    "sg:tags":[
        "drinking",
        "eating"
    ],
    "wof:name":"Friendly Greek Pizza",
    "wof:placetype":"venue"
},
  "geometry": {"coordinates":[-76.29473900000001,40.0479],"type":"Point"}
}