{
  "type": "Feature",
  "properties": {
    "iso:country":"US",
    "sg:address":"1035 Greensburg Rd",
    "sg:city":"New Kensington",
    "sg:classifiers":[
        {
            "category":"Insurance",
            "subcategory":"Insurance Agent",
            "type":"Services"
        }
    ],
    "sg:phone":"+1 724 339 4900",
    "sg:postcode":"15068",
    "sg:province":"PA",
    "wof:name":"Norwin Insurance Svc",
    "wof:placetype":"venue"
},
  "geometry": {"coordinates":[-79.737228,40.549716],"type":"Point"}
}