{
  "type": "Feature",
  "properties": {
    "iso:country":"US",
    "sg:address":"2639 W Chester Pike",
    "sg:city":"Broomall",
    "sg:classifiers":[
        {
            "category":"Manufacturing",
            "subcategory":"Printing",
            "type":"Manufacturing & Wholesale Goods"
        }
    ],
    "sg:phone":"+1   ",
    "sg:postcode":"19008",
    "sg:province":"PA",
    "sg:tags":[
        "commercial"
    ],
    "wof:name":"Promo America",
    "wof:placetype":"venue"
},
  "geometry": {"coordinates":[-75.36472000000001,39.982354],"type":"Point"}
}