{
  "type": "Feature",
  "properties": {
    "iso:country":"US",
    "sg:address":"2618 Siesta Dr",
    "sg:city":"Pittsburgh",
    "sg:classifiers":[
        {
            "category":"Building & Trades",
            "subcategory":"Construction",
            "type":"Services"
        }
    ],
    "sg:phone":"+1 724 942 9133",
    "sg:postcode":"15241",
    "sg:province":"PA",
    "sg:tags":[
        "wallcoverings-installation",
        "wallpaper",
        "painting",
        "contractor"
    ],
    "wof:name":"P P Painting",
    "wof:placetype":"venue"
},
  "geometry": {"coordinates":[-80.079054,40.308163],"type":"Point"}
}