{
  "type": "Feature",
  "properties": {
    "iso:country":"US",
    "sg:address":"152 York Rd",
    "sg:city":"Warminster",
    "sg:classifiers":[
        {
            "category":"Professional",
            "subcategory":"Computer Services",
            "type":"Services"
        }
    ],
    "sg:phone":"+1   ",
    "sg:postcode":"18974",
    "sg:province":"PA",
    "sg:tags":[
        "related",
        "programing",
        "custom"
    ],
    "wof:name":"Business Management Intl",
    "wof:placetype":"venue"
},
  "geometry": {"coordinates":[-75.102284,40.194593],"type":"Point"}
}