{
  "type": "Feature",
  "properties": {
    "iso:country":"US",
    "sg:address":"736 Springdale Dr Ste 100",
    "sg:city":"Exton",
    "sg:classifiers":[
        {
            "category":"Insurance",
            "subcategory":"Hazard Insurance",
            "type":"Services"
        }
    ],
    "sg:phone":"+1 610 363 7999",
    "sg:postcode":"19341",
    "sg:province":"PA",
    "sg:website":"http://www.roehrs.com",
    "wof:name":"Roehrs & Company Inc",
    "wof:placetype":"venue"
},
  "geometry": {"coordinates":[-75.60632099999999,40.029334],"type":"Point"}
}