{
  "type": "Feature",
  "properties": {
    "addr:full":"222 S Highland Ave Pittsburgh PA 15206",
    "addr:housenumber":"222",
    "addr:postcode":"15206",
    "addr:street":"S Highland Ave",
    "iso:country":"US",
    "sg:address":"222 S Highland Ave",
    "sg:city":"Pittsburgh",
    "sg:classifiers":[
        {
            "category":"Home & Garden",
            "subcategory":"Home Furnishings",
            "type":"Retail Goods"
        }
    ],
    "sg:phone":"+1   ",
    "sg:postcode":"15206",
    "sg:province":"PA",
    "sg:tags":[
        "merchandise"
    ],
    "wof:name":"Sopraffino Inc",
    "wof:placetype":"venue"
},
  "geometry": {"coordinates":[-79.925228,40.458261],"type":"Point"}
}