{
  "type": "Feature",
  "properties": {
    "iso:country":"US",
    "sg:address":"4211 Hunters Run Blvd",
    "sg:city":"Reading",
    "sg:classifiers":[
        {
            "category":"Freight",
            "type":"Transportation"
        }
    ],
    "sg:phone":"+1 610 370 1218",
    "sg:postcode":"19606",
    "sg:province":"PA",
    "sg:tags":[
        "operator",
        "local",
        "trucking"
    ],
    "wof:name":"Boyer Trans Service Inc",
    "wof:placetype":"venue"
},
  "geometry": {"coordinates":[-75.85356,40.322279],"type":"Point"}
}