{
  "type": "Feature",
  "properties": {
    "iso:country":"US",
    "sg:address":"559 Rasley Hill Rd",
    "sg:city":"Bangor",
    "sg:classifiers":[
        {
            "category":"Building & Trades",
            "subcategory":"Construction",
            "type":"Services"
        }
    ],
    "sg:phone":"+1 610 588 2232",
    "sg:postcode":"18013",
    "sg:province":"PA",
    "sg:tags":[
        "contractor"
    ],
    "wof:name":"Concrete Jack Pumping Svc",
    "wof:placetype":"venue"
},
  "geometry": {"coordinates":[-75.190146,40.814845],"type":"Point"}
}