{
  "type": "Feature",
  "properties": {
    "addr:full":"1714 Ramich Rd Temple PA 19560",
    "addr:housenumber":"1714",
    "addr:postcode":"19560",
    "addr:street":"Ramich Rd",
    "iso:country":"US",
    "sg:address":"1714 Ramich Rd",
    "sg:city":"Temple",
    "sg:classifiers":[
        {
            "category":"Building & Trades",
            "subcategory":"Construction",
            "type":"Services"
        }
    ],
    "sg:phone":"+1   ",
    "sg:postcode":"19560",
    "sg:province":"PA",
    "sg:tags":[
        "house",
        "carpentry",
        "contractor"
    ],
    "wof:name":"K S Jamison Construction",
    "wof:placetype":"venue"
},
  "geometry": {"coordinates":[-75.89958799999999,40.390989],"type":"Point"}
}