{
  "type": "Feature",
  "properties": {
    "iso:country":"US",
    "sg:address":"407 Turnpike St",
    "sg:city":"Susquehanna",
    "sg:classifiers":[
        {
            "category":"Health Services",
            "subcategory":"Doctor",
            "type":"Services"
        }
    ],
    "sg:phone":"+1   ",
    "sg:postcode":"18847",
    "sg:province":"PA",
    "sg:tags":[
        "medical"
    ],
    "wof:name":"Warren S Dewitt",
    "wof:placetype":"venue"
},
  "geometry": {"coordinates":[-75.593992,41.946602],"type":"Point"}
}