{
  "type": "Feature",
  "properties": {
    "iso:country":"US",
    "sg:address":"430 Harrisburg Ave",
    "sg:city":"Lancaster",
    "sg:classifiers":[
        {
            "category":"Restaurant",
            "type":"Food & Drink"
        }
    ],
    "sg:phone":"+1 717 509 7700",
    "sg:postcode":"17603",
    "sg:province":"PA",
    "sg:tags":[
        "delicatessen"
    ],
    "wof:name":"Thomas' Campus Deli",
    "wof:placetype":"venue"
},
  "geometry": {"coordinates":[-76.315113,40.048416],"type":"Point"}
}