{
  "type": "Feature",
  "properties": {
    "iso:country":"US",
    "sg:address":"517 Taylor Ave",
    "sg:city":"Warrington",
    "sg:classifiers":[
        {
            "category":"Manufacturing",
            "subcategory":"Signs",
            "type":"Manufacturing & Wholesale Goods"
        }
    ],
    "sg:phone":"+1 215 343 6657",
    "sg:postcode":"18976",
    "sg:province":"PA",
    "wof:name":"Sterling Signs",
    "wof:placetype":"venue"
},
  "geometry": {"coordinates":[-75.143615,40.229923],"type":"Point"}
}