{
  "type": "Feature",
  "properties": {
    "iso:country":"US",
    "sg:address":"503 Martindale St",
    "sg:city":"Pittsburgh",
    "sg:classifiers":[
        {
            "category":"Banks & Credit Unions",
            "subcategory":"Investment Brokerage",
            "type":"Services"
        }
    ],
    "sg:phone":"+1 412 788 2700",
    "sg:postcode":"15212",
    "sg:province":"PA",
    "sg:tags":[
        "security"
    ],
    "wof:name":"Ht Capital Markets",
    "wof:placetype":"venue"
},
  "geometry": {"coordinates":[-80.00823,40.448912],"type":"Point"}
}