{
  "type": "Feature",
  "properties": {
    "iso:country":"US",
    "sg:address":"1270 Ridge Rd",
    "sg:city":"Pottstown",
    "sg:classifiers":[
        {
            "category":"Autos & Motor Vehicles",
            "subcategory":"Fuel & Gas Station",
            "type":"Retail Goods"
        }
    ],
    "sg:phone":"+1   ",
    "sg:postcode":"19465",
    "sg:province":"PA",
    "sg:tags":[
        "station",
        "gasoline"
    ],
    "wof:name":"Sonnys Quick Stop",
    "wof:placetype":"venue"
},
  "geometry": {"coordinates":[-75.67491699999999,40.17431],"type":"Point"}
}