{
  "type": "Feature",
  "properties": {
    "iso:country":"US",
    "sg:address":"2200 Michener St",
    "sg:city":"Philadelphia",
    "sg:classifiers":[
        {
            "category":"Wholesale",
            "subcategory":"Medical Equipment & Supplies",
            "type":"Manufacturing & Wholesale Goods"
        }
    ],
    "sg:phone":"+1 215 673 6333",
    "sg:postcode":"19115",
    "sg:province":"PA",
    "sg:tags":[
        "physician",
        "surgeon"
    ],
    "sg:website":"www.nicholemedical.com",
    "wof:name":"Nichole Medical Equipment Inc",
    "wof:placetype":"venue"
},
  "geometry": {"coordinates":[-75.030805,40.079035],"type":"Point"}
}