{
  "type": "Feature",
  "properties": {
    "addr:full":"6501 Market St Upper Darby PA 19082",
    "addr:housenumber":"6501",
    "addr:postcode":"19082",
    "addr:street":"Market St",
    "iso:country":"US",
    "sg:address":"6501 Market St",
    "sg:city":"Upper Darby",
    "sg:classifiers":[
        {
            "category":"Home & Garden",
            "subcategory":"Furniture",
            "type":"Retail Goods"
        }
    ],
    "sg:phone":"+1 610 352 6501",
    "sg:postcode":"19082",
    "sg:province":"PA",
    "wof:name":"Adam's Furniture Gallery",
    "wof:placetype":"venue"
},
  "geometry": {"coordinates":[-75.253524,39.962507],"type":"Point"}
}