{
  "type": "Feature",
  "properties": {
    "iso:country":"US",
    "sg:address":"1004 Lancaster Pike",
    "sg:city":"Quarryville",
    "sg:classifiers":[
        {
            "category":"Wholesale",
            "subcategory":"Beer",
            "type":"Manufacturing & Wholesale Goods"
        }
    ],
    "sg:phone":"+1 717 284 3008",
    "sg:postcode":"17566",
    "sg:province":"PA",
    "sg:tags":[
        "ale"
    ],
    "wof:name":"Buck Beverage Inc",
    "wof:placetype":"venue"
},
  "geometry": {"coordinates":[-76.228641,39.872232],"type":"Point"}
}