{
  "type": "Feature",
  "properties": {
    "iso:country":"US",
    "sg:address":"331 Stonyhill Dr",
    "sg:city":"Chalfont",
    "sg:classifiers":[
        {
            "category":"Personal",
            "type":"Services"
        }
    ],
    "sg:phone":"+1 215 230 0654",
    "sg:postcode":"18914",
    "sg:province":"PA",
    "sg:tags":[
        "therapist",
        "massage"
    ],
    "wof:name":"Pathways Center-Therapeutic",
    "wof:placetype":"venue"
},
  "geometry": {"coordinates":[-75.226826,40.279418],"type":"Point"}
}