{
  "type": "Feature",
  "properties": {
    "addr:full":"7227 Marshall Rd Upper Darby PA 19082",
    "addr:housenumber":"7227",
    "addr:postcode":"19082",
    "addr:street":"Marshall Rd",
    "iso:country":"US",
    "sg:address":"7227 Marshall Rd",
    "sg:city":"Upper Darby",
    "sg:classifiers":[
        {
            "category":"Retail",
            "subcategory":"Laundry & Dry Cleaning",
            "type":"Services"
        }
    ],
    "sg:phone":"+1 610 352 1455",
    "sg:postcode":"19082",
    "sg:province":"PA",
    "sg:tags":[
        "cleaners"
    ],
    "wof:name":"Min Young Som",
    "wof:placetype":"venue"
},
  "geometry": {"coordinates":[-75.26573,39.951735],"type":"Point"}
}