{
  "type": "Feature",
  "properties": {
    "iso:country":"US",
    "sg:address":"54 Fraley St",
    "sg:city":"Kane",
    "sg:classifiers":[
        {
            "category":"Building & Trades",
            "subcategory":"Construction",
            "type":"Services"
        }
    ],
    "sg:phone":"+1   ",
    "sg:postcode":"16735",
    "sg:province":"PA",
    "sg:tags":[
        "business"
    ],
    "wof:name":"Kane Area Revitalication Entp",
    "wof:placetype":"venue"
},
  "geometry": {"coordinates":[-78.811176,41.65278],"type":"Point"}
}