{
  "type": "Feature",
  "properties": {
    "iso:country":"US",
    "sg:address":"404 Long Ln",
    "sg:city":"Upper Darby",
    "sg:classifiers":[
        {
            "category":"Personal",
            "subcategory":"Beauty Salon",
            "type":"Services"
        }
    ],
    "sg:phone":"+1   ",
    "sg:postcode":"19082",
    "sg:province":"PA",
    "sg:tags":[
        "shop"
    ],
    "wof:name":"Hair 2 Gether",
    "wof:placetype":"venue"
},
  "geometry": {"coordinates":[-75.26227799999999,39.95049],"type":"Point"}
}