{
  "type": "Feature",
  "properties": {
    "iso:country":"US",
    "sg:address":"1901 E Clearfield St",
    "sg:city":"Philadelphia",
    "sg:classifiers":[
        {
            "category":"Building & Trades",
            "subcategory":"Plumbing",
            "type":"Services"
        }
    ],
    "sg:phone":"+1   ",
    "sg:postcode":"19134",
    "sg:province":"PA",
    "sg:tags":[
        "system",
        "air",
        "heating",
        "conditioning",
        "plumbing",
        "sprinkling"
    ],
    "wof:name":"Howard V Gadsby & Sons Inc",
    "wof:placetype":"venue"
},
  "geometry": {"coordinates":[-75.11424100000001,39.993407],"type":"Point"}
}