{
  "type": "Feature",
  "properties": {
    "addr:full":"1 Lakeside Dr New Providence PA 17560",
    "addr:housenumber":"1",
    "addr:postcode":"17560",
    "addr:street":"Lakeside Dr",
    "iso:country":"US",
    "sg:address":"1 Lakeside Dr",
    "sg:city":"New Providence",
    "sg:classifiers":[
        {
            "category":"Personal",
            "subcategory":"Beauty Salon",
            "type":"Services"
        }
    ],
    "sg:phone":"+1 717 786 2944",
    "sg:postcode":"17560",
    "sg:province":"PA",
    "sg:tags":[
        "treatment",
        "skin"
    ],
    "sg:website":"www.strongskinsavvy.com",
    "wof:name":"Strong Skin Savvy",
    "wof:placetype":"venue"
},
  "geometry": {"coordinates":[-76.209487,39.911183],"type":"Point"}
}