{
  "type": "Feature",
  "properties": {
    "addr:full":"215 Market St Kittanning PA 16201",
    "addr:housenumber":"215",
    "addr:postcode":"16201",
    "addr:street":"Market St",
    "iso:country":"US",
    "sg:address":"215 Market St",
    "sg:city":"Kittanning",
    "sg:classifiers":[
        {
            "category":"Shopping",
            "subcategory":"Florist",
            "type":"Retail Goods"
        }
    ],
    "sg:phone":"+1 724 548 1528",
    "sg:postcode":"16201",
    "sg:province":"PA",
    "wof:name":"Towne & Country Floral & Brdl",
    "wof:placetype":"venue"
},
  "geometry": {"coordinates":[-79.51936000000001,40.814491],"type":"Point"}
}