{
  "type": "Feature",
  "properties": {
    "iso:country":"US",
    "sg:address":"3404 Walbert Ave",
    "sg:city":"Allentown",
    "sg:classifiers":[
        {
            "category":"Home & Garden",
            "subcategory":"Garden Supply",
            "type":"Retail Goods"
        }
    ],
    "sg:phone":"+1 610 395 3129",
    "sg:postcode":"18104",
    "sg:province":"PA",
    "sg:tags":[
        "nursery",
        "gardening"
    ],
    "wof:name":"Price Landscape Nursery",
    "wof:placetype":"venue"
},
  "geometry": {"coordinates":[-75.53649900000001,40.6152],"type":"Point"}
}