{
  "type": "Feature",
  "properties": {
    "addr:full":"94 N Flowers Mill Rd Langhorne PA 19047",
    "addr:housenumber":"94",
    "addr:postcode":"19047",
    "addr:street":"N Flowers Mill Rd",
    "iso:country":"US",
    "sg:address":"94 N Flowers Mill Rd",
    "sg:city":"Langhorne",
    "sg:classifiers":[
        {
            "category":"Banks & Credit Unions",
            "subcategory":"Bank",
            "type":"Services"
        }
    ],
    "sg:phone":"+1 215 752 5700",
    "sg:postcode":"19047",
    "sg:province":"PA",
    "wof:name":"First Service Bank",
    "wof:placetype":"venue"
},
  "geometry": {"coordinates":[-74.907653,40.178909],"type":"Point"}
}