{
  "type": "Feature",
  "properties": {
    "iso:country":"US",
    "sg:address":"1929 Coolidge Ave",
    "sg:city":"Willow Grove",
    "sg:classifiers":[
        {
            "category":"Building & Trades",
            "subcategory":"Landscaping Services",
            "type":"Services"
        }
    ],
    "sg:phone":"+1   ",
    "sg:postcode":"19090",
    "sg:province":"PA",
    "wof:name":"G&B Landscaping",
    "wof:placetype":"venue"
},
  "geometry": {"coordinates":[-75.125272,40.144325],"type":"Point"}
}