{
  "type": "Feature",
  "properties": {
    "addr:full":"66 Economy Grade Rd Coraopolis PA 15108",
    "addr:housenumber":"66",
    "addr:postcode":"15108",
    "addr:street":"Economy Grade Rd",
    "iso:country":"US",
    "sg:address":"66 Economy Grade Rd",
    "sg:city":"Coraopolis",
    "sg:classifiers":[
        {
            "category":"Animal Shelter",
            "type":"Public Place"
        },
        {
            "category":"Shopping",
            "subcategory":"Pets & Pet Supplies",
            "type":"Retail Goods"
        },
        {
            "category":"Retail",
            "subcategory":"Pet Boarding",
            "type":"Services"
        },
        {
            "category":"Retail",
            "subcategory":"Animal Services",
            "type":"Services"
        }
    ],
    "sg:phone":"+1 724 457 0942",
    "sg:postcode":"15108",
    "sg:province":"PA",
    "sg:tags":[
        "sitting",
        "dog",
        "exercising",
        "grooming",
        "cat",
        "kennel"
    ],
    "sg:website":"http://www.parkwaykennels.com",
    "wof:name":"Parkway Kennels",
    "wof:placetype":"venue"
},
  "geometry": {"coordinates":[-80.272595,40.532484],"type":"Point"}
}