{
  "type": "Feature",
  "properties": {
    "iso:country":"US",
    "sg:address":"100 Sawmill Rd",
    "sg:city":"Belleville",
    "sg:classifiers":[
        {
            "category":"Home & Garden",
            "subcategory":"Building Materials",
            "type":"Retail Goods"
        }
    ],
    "sg:phone":"+1   ",
    "sg:postcode":"17004",
    "sg:province":"PA",
    "sg:tags":[
        "lumber"
    ],
    "wof:name":"J Box & Lumber Inc",
    "wof:placetype":"venue"
},
  "geometry": {"coordinates":[-77.664464,40.656646],"type":"Point"}
}