{
  "type": "Feature",
  "properties": {
    "addr:full":"130 East Ave Wellsboro PA 16901",
    "addr:housenumber":"130",
    "addr:postcode":"16901",
    "addr:street":"East Ave",
    "iso:country":"US",
    "sg:address":"130 East Ave",
    "sg:city":"Wellsboro",
    "sg:classifiers":[
        {
            "category":"Retail",
            "subcategory":"Car Wash",
            "type":"Services"
        }
    ],
    "sg:phone":"+1   ",
    "sg:postcode":"16901",
    "sg:province":"PA",
    "sg:tags":[
        "carwash"
    ],
    "wof:name":"Clean Machine",
    "wof:placetype":"venue"
},
  "geometry": {"coordinates":[-77.281049,41.745915],"type":"Point"}
}