{
  "type": "Feature",
  "properties": {
    "iso:country":"US",
    "sg:address":"123 Good St",
    "sg:city":"Houtzdale",
    "sg:classifiers":[
        {
            "category":"Organizations",
            "subcategory":"Religious Organization",
            "type":"Services"
        }
    ],
    "sg:phone":"+1 814 378 7653",
    "sg:postcode":"16651",
    "sg:province":"PA",
    "wof:name":"Christ The King Church",
    "wof:placetype":"venue"
},
  "geometry": {"coordinates":[-78.35171699999999,40.830656],"type":"Point"}
}