{
  "type": "Feature",
  "properties": {
    "addr:full":"716 Bainbridge St Philadelphia PA 19147",
    "addr:housenumber":"716",
    "addr:postcode":"19147",
    "addr:street":"Bainbridge St",
    "iso:country":"US",
    "sg:address":"716 Bainbridge St",
    "sg:city":"Philadelphia",
    "sg:classifiers":[
        {
            "category":"Wholesale",
            "subcategory":"Furniture",
            "type":"Manufacturing & Wholesale Goods"
        }
    ],
    "sg:phone":"+1 215 574 1922",
    "sg:postcode":"19147",
    "sg:province":"PA",
    "wof:name":"Ethnics Furniture",
    "wof:placetype":"venue"
},
  "geometry": {"coordinates":[-75.15473299999999,39.941328],"type":"Point"}
}