{
  "type": "Feature",
  "properties": {
    "addr:full":"137 Freedom Valley Cir Coatesville PA 19320",
    "addr:housenumber":"137",
    "addr:postcode":"19320",
    "addr:street":"Freedom Valley Cir",
    "iso:country":"US",
    "sg:address":"137 Freedom Valley Cir",
    "sg:city":"Coatesville",
    "sg:classifiers":[
        {
            "category":"Building & Trades",
            "subcategory":"Plumbing",
            "type":"Services"
        }
    ],
    "sg:phone":"+1 610 380 9866",
    "sg:postcode":"19320",
    "sg:province":"PA",
    "sg:tags":[
        "plumbing",
        "contractor"
    ],
    "wof:name":"Ronald C Rissel Plumbing",
    "wof:placetype":"venue"
},
  "geometry": {"coordinates":[-75.834694,40.017133],"type":"Point"}
}