{
  "type": "Feature",
  "properties": {
    "iso:country":"US",
    "sg:address":"100 Art Rooney Avenue",
    "sg:city":"Pittsburgh",
    "sg:classifiers":[
        {
            "category":"Arena",
            "subcategory":"Stadium",
            "type":"Entertainment"
        }
    ],
    "sg:phone":"+1 412 697 7700",
    "sg:postcode":"15289",
    "sg:province":"PA",
    "sg:website":"www.steelers.com/heinzfield",
    "wof:name":"Heinz Field",
    "wof:placetype":"venue"
},
  "geometry": {"coordinates":[-80.01404599999999,40.446838],"type":"Point"}
}