{
  "type": "Feature",
  "properties": {
    "iso:country":"US",
    "sg:address":"1601 Valley Forge Road",
    "sg:city":"Lansdale",
    "sg:classifiers":[
        {
            "category":"Food & Beverages",
            "subcategory":"Groceries & Convenience Stores",
            "type":"Retail Goods"
        }
    ],
    "sg:phone":"+1 215 361 2486",
    "sg:postcode":"19446",
    "sg:province":"PA",
    "sg:website":"www.wawa.com",
    "wof:name":"Wawa",
    "wof:placetype":"venue"
},
  "geometry": {"coordinates":[-75.31545699999999,40.228442],"type":"Point"}
}