{
  "type": "Feature",
  "properties": {
    "iso:country":"US",
    "sg:address":"9524 Lincoln Hwy",
    "sg:city":"Bedford",
    "sg:classifiers":[
        {
            "category":"Professional",
            "subcategory":"Computer Services",
            "type":"Services"
        }
    ],
    "sg:phone":"+1   ",
    "sg:postcode":"15522",
    "sg:province":"PA",
    "sg:tags":[
        "repair",
        "technology",
        "sales",
        "con"
    ],
    "wof:name":"Black Seal Systems Inc",
    "wof:placetype":"venue"
},
  "geometry": {"coordinates":[-78.46364,40.019055],"type":"Point"}
}