{
  "type": "Feature",
  "properties": {
    "addr:full":"2061 Wyngate Dr Newtown PA 18940",
    "addr:housenumber":"2061",
    "addr:postcode":"18940",
    "addr:street":"Wyngate Dr",
    "iso:country":"US",
    "sg:address":"2061 Wyngate Dr",
    "sg:city":"Newtown",
    "sg:classifiers":[
        {
            "category":"Communications",
            "subcategory":"Film & Video Production",
            "type":"Services"
        },
        {
            "category":"Arts & Performance",
            "subcategory":"Theater",
            "type":"Entertainment"
        }
    ],
    "sg:phone":"+1 215 579 7712",
    "sg:postcode":"18940",
    "sg:province":"PA",
    "sg:tags":[
        "motion",
        "television",
        "program",
        "producer"
    ],
    "wof:name":"Cooper Communications Co",
    "wof:placetype":"venue"
},
  "geometry": {"coordinates":[-74.89914,40.241849],"type":"Point"}
}