{
  "type": "Feature",
  "properties": {
    "iso:country":"US",
    "sg:address":"415 Airport Rd",
    "sg:city":"Montoursville",
    "sg:classifiers":[
        {
            "category":"Autos & Motor Vehicles",
            "subcategory":"Automobile Sales",
            "type":"Retail Goods"
        }
    ],
    "sg:phone":"+1 570 368 3970",
    "sg:postcode":"17754",
    "sg:province":"PA",
    "sg:tags":[
        "sport",
        "trailer",
        "utility"
    ],
    "sg:website":"www.worthingtontrailers.com",
    "wof:name":"Worthington Welding Inc",
    "wof:placetype":"venue"
},
  "geometry": {"coordinates":[-76.92228299999999,41.246308],"type":"Point"}
}