{
  "type": "Feature",
  "properties": {
    "iso:country":"US",
    "sg:address":"500 E Providence Rd",
    "sg:city":"Aldan",
    "sg:classifiers":[
        {
            "category":"Wholesale",
            "subcategory":"Sporting Goods",
            "type":"Manufacturing & Wholesale Goods"
        }
    ],
    "sg:phone":"+1 610 623 8384",
    "sg:postcode":"19018",
    "sg:province":"PA",
    "sg:tags":[
        "equipment",
        "pool",
        "swimming"
    ],
    "wof:name":"Delaware Valley Pool Supply",
    "wof:placetype":"venue"
},
  "geometry": {"coordinates":[-75.280079,39.925542],"type":"Point"}
}