{
  "type": "Feature",
  "properties": {
    "addr:full":"612 9th St Beaver Falls PA 15010",
    "addr:housenumber":"612",
    "addr:postcode":"15010",
    "addr:street":"9Th St",
    "iso:country":"US",
    "sg:address":"612 9th St",
    "sg:city":"Beaver Falls",
    "sg:classifiers":[
        {
            "category":"Organizations",
            "subcategory":"Religious Organization",
            "type":"Services"
        }
    ],
    "sg:phone":"+1 724 891 1033",
    "sg:postcode":"15010",
    "sg:province":"PA",
    "sg:tags":[
        "clergy"
    ],
    "wof:name":"Leonard Cleckley",
    "wof:placetype":"venue"
},
  "geometry": {"coordinates":[-80.31816999999999,40.750067],"type":"Point"}
}