{
  "type": "Feature",
  "properties": {
    "addr:full":"1871 Catasauqua Rd Allentown PA 18109",
    "addr:housenumber":"1871",
    "addr:postcode":"18109",
    "addr:street":"Catasauqua Rd",
    "iso:country":"US",
    "sg:address":"1871 Catasauqua Rd",
    "sg:city":"Allentown",
    "sg:classifiers":[
        {
            "category":"Restaurant",
            "type":"Food & Drink"
        }
    ],
    "sg:phone":"+1   ",
    "sg:postcode":"18109",
    "sg:province":"PA",
    "wof:name":"Dennys",
    "wof:placetype":"venue"
},
  "geometry": {"coordinates":[-75.428933,40.642763],"type":"Point"}
}