{
  "type": "Feature",
  "properties": {
    "iso:country":"US",
    "sg:address":"800 Old Pond Rd Ste 701",
    "sg:city":"Bridgeville",
    "sg:classifiers":[
        {
            "category":"Professional",
            "subcategory":"Computer Services",
            "type":"Services"
        }
    ],
    "sg:phone":"+1 412 257 2011",
    "sg:postcode":"15017",
    "sg:province":"PA",
    "sg:tags":[
        "repair"
    ],
    "wof:name":"S M S Systems Maintenance Services Inc",
    "wof:placetype":"venue"
},
  "geometry": {"coordinates":[-80.11962,40.351945],"type":"Point"}
}