{
  "type": "Feature",
  "properties": {
    "iso:country":"US",
    "sg:address":"404 Crum Lynne Rd",
    "sg:city":"Ridley Park",
    "sg:classifiers":[
        {
            "category":"Shopping",
            "subcategory":"Bicycles & Sporting Goods",
            "type":"Retail Goods"
        }
    ],
    "sg:phone":"+1   ",
    "sg:postcode":"19078",
    "sg:province":"PA",
    "sg:tags":[
        "item",
        "sport",
        "golf"
    ],
    "wof:name":"Star Light Golf & Sports",
    "wof:placetype":"venue"
},
  "geometry": {"coordinates":[-75.334469,39.87363],"type":"Point"}
}