{
  "type": "Feature",
  "properties": {
    "addr:full":"2701 Grant Ave Philadelphia PA 19114",
    "addr:housenumber":"2701",
    "addr:postcode":"19114",
    "addr:street":"Grant Ave",
    "iso:country":"US",
    "sg:address":"2701 Grant Ave",
    "sg:city":"Philadelphia",
    "sg:classifiers":[
        {
            "category":"Building & Trades",
            "subcategory":"Construction",
            "type":"Services"
        }
    ],
    "sg:phone":"+1 215 698 4466",
    "sg:postcode":"19114",
    "sg:province":"PA",
    "sg:tags":[
        "crane"
    ],
    "sg:website":"http://www.sauttercrane.com",
    "wof:name":"Sautter Crane Rental Inc",
    "wof:placetype":"venue"
},
  "geometry": {"coordinates":[-75.021005,40.076699],"type":"Point"}
}