{
  "type": "Feature",
  "properties": {
    "iso:country":"US",
    "sg:address":"421 Steele Hollow Rd",
    "sg:city":"Julian",
    "sg:classifiers":[
        {
            "category":"Farming",
            "subcategory":"Farm",
            "type":"Manufacturing & Wholesale Goods"
        }
    ],
    "sg:phone":"+1 814 692 8111",
    "sg:postcode":"16844",
    "sg:province":"PA",
    "sg:tags":[
        "crop",
        "general"
    ],
    "wof:name":"Mathis Farm",
    "wof:placetype":"venue"
},
  "geometry": {"coordinates":[-77.996067,40.839398],"type":"Point"}
}