{
  "type": "Feature",
  "properties": {
    "addr:full":"3424 William Penn Hwy Ste 168 Pittsburgh PA 15235",
    "addr:housenumber":"3424",
    "addr:postcode":"15235",
    "addr:street":"William Penn Hwy Ste 168",
    "iso:country":"US",
    "sg:address":"3424 William Penn Hwy Ste 168",
    "sg:city":"Pittsburgh",
    "sg:classifiers":[
        {
            "category":"Personal",
            "subcategory":"Massage",
            "type":"Services"
        },
        {
            "category":"Health Services",
            "subcategory":"Health Practitioner",
            "type":"Services"
        },
        {
            "category":"Health Services",
            "subcategory":"Chiropractor",
            "type":"Services"
        }
    ],
    "sg:phone":"+1 412 823 2180",
    "sg:postcode":"15235",
    "sg:province":"PA",
    "sg:tags":[
        "sport",
        "chiropractic",
        "therapist",
        "treatment",
        "medicine",
        "injury"
    ],
    "sg:website":"http://www.penncenterchiro.com",
    "wof:name":"Penn Center Chiropractic Clinic",
    "wof:placetype":"venue"
},
  "geometry": {"coordinates":[-79.81277900000001,40.430184],"type":"Point"}
}