{
  "type": "Feature",
  "properties": {
    "iso:country":"US",
    "sg:address":"406 W Ridge Pike",
    "sg:city":"Conshohocken",
    "sg:classifiers":[
        {
            "category":"Banks & Credit Unions",
            "subcategory":"Bank",
            "type":"Services"
        }
    ],
    "sg:phone":"+1 610 238 0600",
    "sg:postcode":"19428",
    "sg:province":"PA",
    "sg:tags":[
        "loan",
        "real estate"
    ],
    "sg:website":"www.archfinancial.com",
    "wof:name":"Arch Financial Svc Inc",
    "wof:placetype":"venue"
},
  "geometry": {"coordinates":[-75.29288099999999,40.09528],"type":"Point"}
}