{
  "type": "Feature",
  "properties": {
    "iso:country":"US",
    "sg:address":"903 5th Ave",
    "sg:city":"New Brighton",
    "sg:classifiers":[
        {
            "category":"Food & Beverages",
            "subcategory":"Specialty",
            "type":"Retail Goods"
        }
    ],
    "sg:phone":"+1 724 847 3742",
    "sg:postcode":"15066",
    "sg:province":"PA",
    "sg:tags":[
        "gourmet",
        "shop"
    ],
    "wof:name":"Eric & Renee's Gourmet Takeout",
    "wof:placetype":"venue"
},
  "geometry": {"coordinates":[-80.31117,40.733988],"type":"Point"}
}