{
  "type": "Feature",
  "properties": {
    "iso:country":"US",
    "sg:address":"12 S Walnut St",
    "sg:city":"Mt Holly Springs",
    "sg:classifiers":[
        {
            "category":"Building & Trades",
            "subcategory":"Construction",
            "type":"Services"
        }
    ],
    "sg:phone":"+1 717 486 7898",
    "sg:postcode":"17065",
    "sg:province":"PA",
    "sg:tags":[
        "hanging",
        "painter",
        "contractor"
    ],
    "wof:name":"Michael L Miller Painting",
    "wof:placetype":"venue"
},
  "geometry": {"coordinates":[-77.191884,40.11333],"type":"Point"}
}