{
  "type": "Feature",
  "properties": {
    "addr:full":"196 Willow Rd Waynesburg PA 15370",
    "addr:housenumber":"196",
    "addr:postcode":"15370",
    "addr:street":"Willow Rd",
    "iso:country":"US",
    "sg:address":"196 Willow Rd",
    "sg:city":"Waynesburg",
    "sg:classifiers":[
        {
            "category":"Building & Trades",
            "subcategory":"Plumbing",
            "type":"Services"
        }
    ],
    "sg:phone":"+1 724 627 8646",
    "sg:postcode":"15370",
    "sg:province":"PA",
    "sg:tags":[
        "plumbing",
        "contractor"
    ],
    "wof:name":"Roto-Rooter Plumbing & Drain",
    "wof:placetype":"venue"
},
  "geometry": {"coordinates":[-80.141649,39.890476],"type":"Point"}
}