{
  "type": "Feature",
  "properties": {
    "iso:country":"US",
    "sg:address":"1354 Stanley Ave",
    "sg:city":"Bethlehem",
    "sg:classifiers":[
        {
            "category":"Building & Trades",
            "subcategory":"Electrical",
            "type":"Services"
        }
    ],
    "sg:phone":"+1 610 867 1014",
    "sg:postcode":"18015",
    "sg:province":"PA",
    "sg:tags":[
        "electrical",
        "electric",
        "contractor"
    ],
    "wof:name":"Jim Young Electric",
    "wof:placetype":"venue"
},
  "geometry": {"coordinates":[-75.40069200000001,40.600688],"type":"Point"}
}