{
  "type": "Feature",
  "properties": {
    "iso:country":"US",
    "sg:address":"4140 Old Philadelphia Pike",
    "sg:city":"Gordonville",
    "sg:classifiers":[
        {
            "category":"Building & Trades",
            "subcategory":"Construction",
            "type":"Services"
        }
    ],
    "sg:phone":"+1 717 768 0583",
    "sg:postcode":"17529",
    "sg:province":"PA",
    "sg:tags":[
        "roofing",
        "contractor"
    ],
    "wof:name":"Elmer's Roofing",
    "wof:placetype":"venue"
},
  "geometry": {"coordinates":[-76.06413000000001,40.039068],"type":"Point"}
}