{
  "type": "Feature",
  "properties": {
    "iso:country":"US",
    "sg:address":"720 Wilkes Barre Township Blvd",
    "sg:city":"Wilkes Barre",
    "sg:classifiers":[
        {
            "category":"Restaurant",
            "type":"Food & Drink"
        }
    ],
    "sg:phone":"+1 570 826 0164",
    "sg:postcode":"18702",
    "sg:province":"PA",
    "sg:tags":[
        "drinking",
        "eating"
    ],
    "wof:name":"Krugel's Place",
    "wof:placetype":"venue"
},
  "geometry": {"coordinates":[-75.877454,41.2254],"type":"Point"}
}