{
  "type": "Feature",
  "properties": {
    "iso:country":"US",
    "sg:address":"45 N George St",
    "sg:city":"York",
    "sg:classifiers":[
        {
            "category":"Education",
            "subcategory":"Library",
            "type":"Public Place"
        }
    ],
    "sg:phone":"+1 717 854 0754",
    "sg:postcode":"17401",
    "sg:province":"PA",
    "sg:tags":[
        "special",
        "interest"
    ],
    "wof:name":"York County Law Library",
    "wof:placetype":"venue"
},
  "geometry": {"coordinates":[-76.72837199999999,39.963792],"type":"Point"}
}