{
  "type": "Feature",
  "properties": {
    "iso:country":"US",
    "sg:address":"920 Center Dr",
    "sg:city":"Chicora",
    "sg:classifiers":[
        {
            "category":"Building & Trades",
            "subcategory":"Plumbing",
            "type":"Services"
        }
    ],
    "sg:phone":"+1 724 445 3312",
    "sg:postcode":"16025",
    "sg:province":"PA",
    "sg:tags":[
        "conditioning",
        "air",
        "system",
        "contractor"
    ],
    "wof:name":"Matt Mc Donald Heating & Air",
    "wof:placetype":"venue"
},
  "geometry": {"coordinates":[-79.81256,40.945978],"type":"Point"}
}