{
  "type": "Feature",
  "properties": {
    "addr:full":"83 Murtland Ave Washington PA 15301",
    "addr:housenumber":"83",
    "addr:postcode":"15301",
    "addr:street":"Murtland Ave",
    "iso:country":"US",
    "sg:address":"83 Murtland Ave",
    "sg:city":"Washington",
    "sg:classifiers":[
        {
            "category":"Government",
            "subcategory":"Police Station",
            "type":"Public Place"
        }
    ],
    "sg:phone":"+1   ",
    "sg:postcode":"15301",
    "sg:province":"PA",
    "sg:tags":[
        "barrack",
        "state"
    ],
    "wof:name":"State Police Barracks",
    "wof:placetype":"venue"
},
  "geometry": {"coordinates":[-80.23786699999999,40.180128],"type":"Point"}
}