{
  "type": "Feature",
  "properties": {
    "addr:full":"20 W Lancaster Ave Paoli PA 19301",
    "addr:housenumber":"20",
    "addr:postcode":"19301",
    "addr:street":"W Lancaster Ave",
    "iso:country":"US",
    "sg:address":"20 W Lancaster Ave",
    "sg:city":"Paoli",
    "sg:classifiers":[
        {
            "category":"Bagels",
            "type":"Food & Drink"
        },
        {
            "category":"Coffee & Tea",
            "type":"Food & Drink"
        },
        {
            "category":"Food & Beverages",
            "subcategory":"Bakery",
            "type":"Retail Goods"
        },
        {
            "category":"Bakery",
            "type":"Food & Drink"
        },
        {
            "category":"Donuts",
            "type":"Food & Drink"
        }
    ],
    "sg:menulink":"http://www.allmenus.com/pa/tredyffrin/143738-dunkin-donuts/menu/",
    "sg:phone":"+1 610 670 1890",
    "sg:postcode":"19301",
    "sg:province":"PA",
    "sg:tags":[
        "coffee",
        "diner",
        "tea",
        "bakery",
        "bagel",
        "american",
        "pastry"
    ],
    "wof:name":"Dunkin' Donuts",
    "wof:placetype":"venue"
},
  "geometry": {"coordinates":[-75.484757,40.041927],"type":"Point"}
}