{
  "type": "Feature",
  "properties": {
    "iso:country":"US",
    "sg:address":"245 N Sherman St",
    "sg:city":"Wilkes Barre",
    "sg:classifiers":[
        {
            "category":"Food & Beverages",
            "subcategory":"Specialty",
            "type":"Retail Goods"
        }
    ],
    "sg:phone":"+1 570 822 4297",
    "sg:postcode":"18702",
    "sg:province":"PA",
    "sg:tags":[
        "herb"
    ],
    "wof:name":"JBS Natural Products Inc",
    "wof:placetype":"venue"
},
  "geometry": {"coordinates":[-75.864289,41.243183],"type":"Point"}
}