{
  "type": "Feature",
  "properties": {
    "iso:country":"US",
    "sg:address":"3601 N Front St",
    "sg:city":"Harrisburg",
    "sg:classifiers":[
        {
            "category":"Banks & Credit Unions",
            "subcategory":"Investment Brokerage",
            "type":"Services"
        }
    ],
    "sg:phone":"+1 717 238 1921",
    "sg:postcode":"17110",
    "sg:province":"PA",
    "sg:tags":[
        "consultant",
        "planning",
        "financial"
    ],
    "wof:name":"BGM Financial Assoc LTD",
    "wof:placetype":"venue"
},
  "geometry": {"coordinates":[-76.901303,40.308065],"type":"Point"}
}