{
  "type": "Feature",
  "properties": {
    "iso:country":"US",
    "sg:address":"9 E Chestnut Hill Ave",
    "sg:city":"Philadelphia",
    "sg:classifiers":[
        {
            "category":"Organizations",
            "subcategory":"Religious Organization",
            "type":"Services"
        }
    ],
    "sg:phone":"+1   ",
    "sg:postcode":"19118",
    "sg:province":"PA",
    "wof:name":"Our Mother of Consolation",
    "wof:placetype":"venue"
},
  "geometry": {"coordinates":[-75.209481,40.079155],"type":"Point"}
}