{
  "type": "Feature",
  "properties": {
    "iso:country":"US",
    "sg:address":"4347 Phyllis Dr",
    "sg:city":"Erie",
    "sg:classifiers":[
        {
            "category":"Personal",
            "subcategory":"Beauty Salon",
            "type":"Services"
        }
    ],
    "sg:phone":"+1   ",
    "sg:postcode":"16510",
    "sg:province":"PA",
    "sg:tags":[
        "shop"
    ],
    "wof:name":"Miss Bridgets",
    "wof:placetype":"venue"
},
  "geometry": {"coordinates":[-79.963461,42.076347],"type":"Point"}
}