{
  "type": "Feature",
  "properties": {
    "iso:country":"US",
    "sg:address":"115 W City Ave",
    "sg:city":"Jenkintown",
    "sg:classifiers":[
        {
            "category":"Professional",
            "subcategory":"Lawyer & Legal Services",
            "type":"Services"
        }
    ],
    "sg:phone":"+1   ",
    "sg:postcode":"19004",
    "sg:province":"PA",
    "sg:tags":[
        "attorney"
    ],
    "wof:name":"M Kristi Cook",
    "wof:placetype":"venue"
},
  "geometry": {"coordinates":[-75.23285300000001,39.998362],"type":"Point"}
}