{
  "type": "Feature",
  "properties": {
    "iso:country":"US",
    "sg:address":"1637 Manheim Pike",
    "sg:city":"Lancaster",
    "sg:classifiers":[
        {
            "category":"Shopping",
            "subcategory":"Gifts & Souvenirs",
            "type":"Retail Goods"
        }
    ],
    "sg:phone":"+1   ",
    "sg:postcode":"17601",
    "sg:province":"PA",
    "wof:name":"Cardtique Ltd",
    "wof:placetype":"venue"
},
  "geometry": {"coordinates":[-76.340644,40.081796],"type":"Point"}
}