{
  "type": "Feature",
  "properties": {
    "iso:country":"US",
    "sg:address":"400 W Main St",
    "sg:city":"Ephrata",
    "sg:classifiers":[
        {
            "category":"Shopping",
            "subcategory":"Used Merchandise",
            "type":"Retail Goods"
        }
    ],
    "sg:phone":"+1 717 733 8661",
    "sg:postcode":"17522",
    "sg:province":"PA",
    "sg:tags":[
        "furniture"
    ],
    "wof:name":"Nolt's Office Furniture",
    "wof:placetype":"venue"
},
  "geometry": {"coordinates":[-76.184049,40.182108],"type":"Point"}
}