{
  "type": "Feature",
  "properties": {
    "addr:full":"1736 N Center Ave Somerset PA 15501",
    "addr:housenumber":"1736",
    "addr:postcode":"15501",
    "addr:street":"N Center Ave",
    "iso:country":"US",
    "sg:address":"1736 N Center Ave",
    "sg:city":"Somerset",
    "sg:classifiers":[
        {
            "category":"Shopping",
            "subcategory":"Clothing, Apparel, & Fashions",
            "type":"Retail Goods"
        }
    ],
    "sg:phone":"+1 814 443 9771",
    "sg:postcode":"15501",
    "sg:province":"PA",
    "wof:name":"Fashion Bug",
    "wof:placetype":"venue"
},
  "geometry": {"coordinates":[-79.07541000000001,40.042314],"type":"Point"}
}