{
  "type": "Feature",
  "properties": {
    "iso:country":"US",
    "sg:address":"908 Hanover Ave",
    "sg:city":"Allentown",
    "sg:classifiers":[
        {
            "category":"Retail",
            "subcategory":"Funeral Services",
            "type":"Services"
        }
    ],
    "sg:phone":"+1 610 432 8522",
    "sg:postcode":"18109",
    "sg:province":"PA",
    "sg:tags":[
        "cemetery",
        "plan"
    ],
    "wof:name":"O'donnell Funeral Home",
    "wof:placetype":"venue"
},
  "geometry": {"coordinates":[-75.441498,40.616901],"type":"Point"}
}