{
  "type": "Feature",
  "properties": {
    "addr:full":"701 W Broad St Ste 200 Bethlehem PA 18018",
    "addr:housenumber":"701",
    "addr:postcode":"18018",
    "addr:street":"W Broad St Ste 200",
    "iso:country":"US",
    "sg:address":"701 W Broad St Ste 200",
    "sg:city":"Bethlehem",
    "sg:classifiers":[
        {
            "category":"Government",
            "subcategory":"Court House",
            "type":"Public Place"
        },
        {
            "category":"Government",
            "subcategory":"Office",
            "type":"Public Place"
        }
    ],
    "sg:phone":"+1 610 861 9734",
    "sg:postcode":"18018",
    "sg:province":"PA",
    "sg:tags":[
        "government-united",
        "state",
        "legislator"
    ],
    "sg:website":"http://www.house.gov",
    "wof:name":"Us Rep Charlie Dent",
    "wof:placetype":"venue"
},
  "geometry": {"coordinates":[-75.392319,40.622509],"type":"Point"}
}