{
  "type": "Feature",
  "properties": {
    "iso:country":"US",
    "sg:address":"50B High Sky Ln",
    "sg:city":"Birdsboro",
    "sg:classifiers":[
        {
            "category":"Shopping",
            "subcategory":"Jewelry",
            "type":"Retail Goods"
        },
        {
            "category":"Manufacturing",
            "subcategory":"Jewelry",
            "type":"Manufacturing & Wholesale Goods"
        }
    ],
    "sg:phone":"+1 610 404 8129",
    "sg:postcode":"19508",
    "sg:province":"PA",
    "sg:tags":[
        "stone",
        "designer",
        "semi-precious",
        "precious",
        "jeweler"
    ],
    "wof:name":"J&L Grube Jewelers",
    "wof:placetype":"venue"
},
  "geometry": {"coordinates":[-75.835228,40.252645],"type":"Point"}
}