{
  "type": "Feature",
  "properties": {
    "iso:country":"US",
    "sg:address":"4061 Patterson Rd",
    "sg:city":"Aliquippa",
    "sg:classifiers":[
        {
            "category":"Government",
            "subcategory":"Fire Station",
            "type":"Public Place"
        }
    ],
    "sg:phone":"+1   ",
    "sg:postcode":"15001",
    "sg:province":"PA",
    "sg:tags":[
        "dept",
        "volunteer"
    ],
    "wof:name":"Raccoon Fire Department",
    "wof:placetype":"venue"
},
  "geometry": {"coordinates":[-80.36895,40.61902],"type":"Point"}
}