{
  "type": "Feature",
  "properties": {
    "iso:country":"US",
    "sg:address":"210 Cricket Ave",
    "sg:city":"Ardmore",
    "sg:classifiers":[
        {
            "category":"Personal",
            "type":"Services"
        },
        {
            "category":"Building & Trades",
            "subcategory":"Cleaning & Sanitation",
            "type":"Services"
        }
    ],
    "sg:phone":"+1 610 649 1422",
    "sg:postcode":"19003",
    "sg:province":"PA",
    "sg:tags":[
        "window",
        "butlers'",
        "maids'"
    ],
    "sg:website":"http://ardmorewindowcleaning.com",
    "wof:name":"Ardmore Window Cleaning Co",
    "wof:placetype":"venue"
},
  "geometry": {"coordinates":[-75.297077,40.004714],"type":"Point"}
}