{
  "type": "Feature",
  "properties": {
    "addr:full":"51 Cadwalader Ct Ambler PA 19002",
    "addr:housenumber":"51",
    "addr:postcode":"19002",
    "addr:street":"Cadwalader Ct",
    "iso:country":"US",
    "sg:address":"51 Cadwalader Ct",
    "sg:city":"Ambler",
    "sg:classifiers":[
        {
            "category":"Real Estate",
            "subcategory":"Architect",
            "type":"Services"
        }
    ],
    "sg:phone":"+1   ",
    "sg:postcode":"19002",
    "sg:province":"PA",
    "sg:tags":[
        "architectural"
    ],
    "wof:name":"Focus Collaborative",
    "wof:placetype":"venue"
},
  "geometry": {"coordinates":[-75.23851500000001,40.189684],"type":"Point"}
}