{
  "type": "Feature",
  "properties": {
    "addr:full":"1844 Elston St Philadelphia PA 19126",
    "addr:housenumber":"1844",
    "addr:postcode":"19126",
    "addr:street":"Elston St",
    "iso:country":"US",
    "sg:address":"1844 Elston St",
    "sg:city":"Philadelphia",
    "sg:classifiers":[
        {
            "category":"Manufacturing",
            "subcategory":"Tools & Machinery",
            "type":"Manufacturing & Wholesale Goods"
        }
    ],
    "sg:phone":"+1 215 424 1309",
    "sg:postcode":"19126",
    "sg:province":"PA",
    "sg:tags":[
        "mowers-sharpening",
        "lawn",
        "repairing"
    ],
    "wof:name":"Oak Lane Lawn Mower Co",
    "wof:placetype":"venue"
},
  "geometry": {"coordinates":[-75.14638600000001,40.064735],"type":"Point"}
}