{
  "type": "Feature",
  "properties": {
    "addr:full":"108 Delaware Ave Olyphant PA 18447",
    "addr:housenumber":"108",
    "addr:postcode":"18447",
    "addr:street":"Delaware Ave",
    "iso:country":"US",
    "sg:address":"108 Delaware Ave",
    "sg:city":"Olyphant",
    "sg:classifiers":[
        {
            "category":"Manufacturing",
            "subcategory":"Signs",
            "type":"Manufacturing & Wholesale Goods"
        }
    ],
    "sg:phone":"+1 570 383 6815",
    "sg:postcode":"18447",
    "sg:province":"PA",
    "wof:name":"S & M Designs & Airbrush",
    "wof:placetype":"venue"
},
  "geometry": {"coordinates":[-75.60226900000001,41.469812],"type":"Point"}
}