{
  "type": "Feature",
  "properties": {
    "addr:full":"262 Ridgeview Rd S Elizabethtown PA 17022",
    "addr:housenumber":"262",
    "addr:postcode":"17022",
    "addr:street":"Ridgeview Rd",
    "iso:country":"US",
    "sg:address":"262 Ridgeview Rd S",
    "sg:city":"Elizabethtown",
    "sg:classifiers":[
        {
            "category":"Farming",
            "subcategory":"Farm",
            "type":"Manufacturing & Wholesale Goods"
        }
    ],
    "sg:phone":"+1   ",
    "sg:postcode":"17022",
    "sg:province":"PA",
    "sg:tags":[
        "crop",
        "general"
    ],
    "wof:name":"Steve W Alleman",
    "wof:placetype":"venue"
},
  "geometry": {"coordinates":[-76.57239800000001,40.161122],"type":"Point"}
}