{
  "type": "Feature",
  "properties": {
    "iso:country":"US",
    "sg:address":"1205 N 6th St",
    "sg:city":"Harrisburg",
    "sg:classifiers":[
        {
            "category":"Education",
            "subcategory":"School",
            "type":"Public Place"
        }
    ],
    "sg:phone":"+1 717 255 2456",
    "sg:postcode":"17102",
    "sg:province":"PA",
    "wof:name":"Ben Franklin Academic Prep Sch",
    "wof:placetype":"venue"
},
  "geometry": {"coordinates":[-76.884604,40.268636],"type":"Point"}
}