{
  "type": "Feature",
  "properties": {
    "iso:country":"US",
    "sg:address":"1534 Old Rte 30",
    "sg:city":"Orrtanna",
    "sg:classifiers":[
        {
            "category":"Bars & Pubs",
            "type":"Food & Drink"
        }
    ],
    "sg:phone":"+1   ",
    "sg:postcode":"17353",
    "sg:province":"PA",
    "sg:tags":[
        "club",
        "night"
    ],
    "wof:name":"Rock Top",
    "wof:placetype":"venue"
},
  "geometry": {"coordinates":[-77.368269,39.886676],"type":"Point"}
}