{
  "type": "Feature",
  "properties": {
    "iso:country":"US",
    "sg:address":"3701 Conshohocken Ave",
    "sg:city":"Philadelphia",
    "sg:classifiers":[
        {
            "category":"Banks & Credit Unions",
            "subcategory":"Investment Brokerage",
            "type":"Services"
        }
    ],
    "sg:phone":"+1   ",
    "sg:postcode":"19131",
    "sg:province":"PA",
    "sg:tags":[
        "advisory"
    ],
    "wof:name":"Citywide Financial Services",
    "wof:placetype":"venue"
},
  "geometry": {"coordinates":[-75.204764,40.003158],"type":"Point"}
}