{
  "type": "Feature",
  "properties": {
    "addr:full":"149 Fairhill Dr Southampton PA 18966",
    "addr:housenumber":"149",
    "addr:postcode":"18966",
    "addr:street":"Fairhill Dr",
    "iso:country":"US",
    "sg:address":"149 Fairhill Dr",
    "sg:city":"Southampton",
    "sg:classifiers":[
        {
            "category":"Building & Trades",
            "subcategory":"Landscaping Services",
            "type":"Services"
        }
    ],
    "sg:phone":"+1 215 355 5524",
    "sg:postcode":"18966",
    "sg:province":"PA",
    "sg:tags":[
        "landscape",
        "contractor"
    ],
    "wof:name":"Precision Property Maintenance",
    "wof:placetype":"venue"
},
  "geometry": {"coordinates":[-75.02190400000001,40.188545],"type":"Point"}
}