{
  "type": "Feature",
  "properties": {
    "iso:country":"US",
    "sg:address":"2567 Brindle Dr",
    "sg:city":"Harrisburg",
    "sg:classifiers":[
        {
            "category":"Shopping",
            "subcategory":"Clothing, Apparel, & Fashions",
            "type":"Retail Goods"
        }
    ],
    "sg:phone":"+1 717 652 2753",
    "sg:postcode":"17109",
    "sg:province":"PA",
    "sg:website":"coldwatercreek.com",
    "wof:name":"Coldwater Creek",
    "wof:placetype":"venue"
},
  "geometry": {"coordinates":[-76.846612,40.302843],"type":"Point"}
}