{
  "type": "Feature",
  "properties": {
    "addr:full":"4044 Dickey Rd Gibsonia PA 15044",
    "addr:housenumber":"4044",
    "addr:postcode":"15044",
    "addr:street":"Dickey Rd",
    "iso:country":"US",
    "sg:address":"4044 Dickey Rd",
    "sg:city":"Gibsonia",
    "sg:classifiers":[
        {
            "category":"Professional",
            "subcategory":"Research",
            "type":"Services"
        }
    ],
    "sg:phone":"+1 724 443 4112",
    "sg:postcode":"15044",
    "sg:province":"PA",
    "sg:tags":[
        "foundation",
        "philanthropic"
    ],
    "wof:name":"Verland Foundation",
    "wof:placetype":"venue"
},
  "geometry": {"coordinates":[-79.945717,40.643765],"type":"Point"}
}