{
  "type": "Feature",
  "properties": {
    "addr:full":"1500 Market St Philadelphia PA 19102",
    "addr:housenumber":"1500",
    "addr:postcode":"19102",
    "addr:street":"Market St",
    "iso:country":"US",
    "sg:address":"1500 Market St",
    "sg:city":"Philadelphia",
    "sg:classifiers":[
        {
            "category":"Building & Trades",
            "subcategory":"Plumbing",
            "type":"Services"
        }
    ],
    "sg:phone":"+1 215 563 7577",
    "sg:postcode":"19102",
    "sg:province":"PA",
    "sg:tags":[
        "conditioning",
        "air",
        "system",
        "contractor"
    ],
    "wof:name":"Eastern Air Conditioning",
    "wof:placetype":"venue"
},
  "geometry": {"coordinates":[-75.16685699999999,39.952779],"type":"Point"}
}