{
  "type": "Feature",
  "properties": {
    "addr:full":"915 Whisler Rd Etters PA 17319",
    "addr:housenumber":"915",
    "addr:postcode":"17319",
    "addr:street":"Whisler Rd",
    "iso:country":"US",
    "sg:address":"915 Whisler Rd",
    "sg:city":"Etters",
    "sg:classifiers":[
        {
            "category":"Wholesale",
            "subcategory":"Hardware",
            "type":"Manufacturing & Wholesale Goods"
        },
        {
            "category":"Manufacturing",
            "subcategory":"Rubber & Plastics",
            "type":"Manufacturing & Wholesale Goods"
        }
    ],
    "sg:phone":"+1 717 761 2081",
    "sg:postcode":"17319",
    "sg:province":"PA",
    "sg:tags":[
        "mfg",
        "windows",
        "energy",
        "system",
        "equipment",
        "vinyl",
        "solar",
        "replacement"
    ],
    "wof:name":"Kimex International Tech",
    "wof:placetype":"venue"
},
  "geometry": {"coordinates":[-76.77361000000001,40.135514],"type":"Point"}
}