{
  "type": "Feature",
  "properties": {
    "iso:country":"US",
    "sg:address":"88 E Connelly Blvd",
    "sg:city":"Sharon",
    "sg:classifiers":[
        {
            "category":"Personal",
            "subcategory":"Beauty Salon",
            "type":"Services"
        }
    ],
    "sg:phone":"+1 724 981 3680",
    "sg:postcode":"16146",
    "sg:province":"PA",
    "wof:name":"American Hair",
    "wof:placetype":"venue"
},
  "geometry": {"coordinates":[-80.50736000000001,41.2315],"type":"Point"}
}