{
  "type": "Feature",
  "properties": {
    "iso:country":"US",
    "sg:address":"1037 Lehigh St",
    "sg:city":"Allentown",
    "sg:classifiers":[
        {
            "category":"Autos & Motor Vehicles",
            "subcategory":"Automobile Sales",
            "type":"Retail Goods"
        }
    ],
    "sg:phone":"+1 610 774 0224",
    "sg:postcode":"18103",
    "sg:province":"PA",
    "sg:tags":[
        "car",
        "dealer"
    ],
    "wof:name":"Classic Auto Sales",
    "wof:placetype":"venue"
},
  "geometry": {"coordinates":[-75.473648,40.588906],"type":"Point"}
}