{
  "type": "Feature",
  "properties": {
    "iso:country":"US",
    "sg:address":"2611 Philmont Ave",
    "sg:city":"Huntingdon Vly",
    "sg:classifiers":[
        {
            "category":"Wholesale",
            "subcategory":"Sporting Goods",
            "type":"Manufacturing & Wholesale Goods"
        }
    ],
    "sg:phone":"+1 215 947 8644",
    "sg:postcode":"19006",
    "sg:province":"PA",
    "sg:tags":[
        "spa",
        "hot",
        "tub"
    ],
    "wof:name":"Mid Atlantic Spa Distributors",
    "wof:placetype":"venue"
},
  "geometry": {"coordinates":[-75.055424,40.121],"type":"Point"}
}