{
  "type": "Feature",
  "properties": {
    "iso:country":"US",
    "sg:address":"318 Alder St",
    "sg:city":"Scranton",
    "sg:classifiers":[
        {
            "category":"Building & Trades",
            "subcategory":"Construction",
            "type":"Services"
        }
    ],
    "sg:phone":"+1 570 346 2877",
    "sg:postcode":"18505",
    "sg:province":"PA",
    "sg:tags":[
        "excavation",
        "masonry",
        "contractor",
        "mason"
    ],
    "wof:name":"R J Chiavacci Construction Inc",
    "wof:placetype":"venue"
},
  "geometry": {"coordinates":[-75.667638,41.400845],"type":"Point"}
}