{
  "type": "Feature",
  "properties": {
    "addr:full":"2101 Beale Ave Altoona PA 16601",
    "addr:housenumber":"2101",
    "addr:postcode":"16601",
    "addr:street":"Beale Ave",
    "iso:country":"US",
    "sg:address":"2101 Beale Ave",
    "sg:city":"Altoona",
    "sg:classifiers":[
        {
            "category":"Manufacturing",
            "subcategory":"Furniture",
            "type":"Manufacturing & Wholesale Goods"
        },
        {
            "category":"Building & Trades",
            "subcategory":"Construction",
            "type":"Services"
        }
    ],
    "sg:phone":"+1 814 941 7250",
    "sg:postcode":"16601",
    "sg:province":"PA",
    "sg:tags":[
        "maker",
        "mfg",
        "wooden",
        "fixture",
        "laminated",
        "cabinet",
        "wood",
        "display"
    ],
    "sg:website":"www.keystonecaseworks.com",
    "wof:name":"Keystone Casework Inc",
    "wof:placetype":"venue"
},
  "geometry": {"coordinates":[-78.40629199999999,40.507612],"type":"Point"}
}