{
  "type": "Feature",
  "properties": {
    "iso:country":"US",
    "sg:address":"1236 Gravel Pond Rd",
    "sg:city":"Clarks Summit",
    "sg:classifiers":[
        {
            "category":"Real Estate",
            "subcategory":"Real Estate Operator",
            "type":"Services"
        }
    ],
    "sg:phone":"+1   ",
    "sg:postcode":"18411",
    "sg:province":"PA",
    "sg:tags":[
        "building",
        "nonresidential"
    ],
    "wof:name":"Millett Associates",
    "wof:placetype":"venue"
},
  "geometry": {"coordinates":[-75.742892,41.496734],"type":"Point"}
}