{
  "type": "Feature",
  "properties": {
    "iso:country":"US",
    "sg:address":"5209 Woodland Ave",
    "sg:city":"Philadelphia",
    "sg:classifiers":[
        {
            "category":"Personal",
            "subcategory":"Beauty Salon",
            "type":"Services"
        }
    ],
    "sg:phone":"+1 215 727 8630",
    "sg:postcode":"19143",
    "sg:province":"PA",
    "sg:tags":[
        "hair"
    ],
    "wof:name":"New Growth Beauty Salon",
    "wof:placetype":"venue"
},
  "geometry": {"coordinates":[-75.21667600000001,39.938179],"type":"Point"}
}