{
  "type": "Feature",
  "properties": {
    "iso:country":"US",
    "sg:address":"52 School House Ln",
    "sg:city":"Turbotville",
    "sg:classifiers":[
        {
            "category":"Professional",
            "subcategory":"Engineering",
            "type":"Services"
        }
    ],
    "sg:phone":"+1 570 437 4070",
    "sg:postcode":"17772",
    "sg:province":"PA",
    "sg:tags":[
        "engineer"
    ],
    "wof:name":"Engineering Consultation & Svc",
    "wof:placetype":"venue"
},
  "geometry": {"coordinates":[-76.700694,41.110773],"type":"Point"}
}