{
  "type": "Feature",
  "properties": {
    "iso:country":"US",
    "sg:address":"525 Fairview Ave",
    "sg:city":"Media",
    "sg:classifiers":[
        {
            "category":"Building & Trades",
            "subcategory":"Construction",
            "type":"Services"
        }
    ],
    "sg:phone":"+1 610 565 9165",
    "sg:postcode":"19063",
    "sg:province":"PA",
    "sg:tags":[
        "restoration",
        "cleaning",
        "patio",
        "deck"
    ],
    "wof:name":"Mc Shane Construction",
    "wof:placetype":"venue"
},
  "geometry": {"coordinates":[-75.39991499999999,39.891885],"type":"Point"}
}