{
  "type": "Feature",
  "properties": {
    "iso:country":"US",
    "sg:address":"53 W 33rd St",
    "sg:city":"Reading",
    "sg:classifiers":[
        {
            "category":"Building & Trades",
            "subcategory":"Construction",
            "type":"Services"
        }
    ],
    "sg:phone":"+1 610 370 9811",
    "sg:postcode":"19606",
    "sg:province":"PA",
    "sg:tags":[
        "concrete",
        "contractor"
    ],
    "wof:name":"S & S Concrete",
    "wof:placetype":"venue"
},
  "geometry": {"coordinates":[-75.878463,40.320311],"type":"Point"}
}