{
  "type": "Feature",
  "properties": {
    "iso:country":"US",
    "sg:address":"102 N Abington Rd",
    "sg:city":"Clarks Summit",
    "sg:classifiers":[
        {
            "category":"Health Services",
            "subcategory":"Health Practitioner",
            "type":"Services"
        }
    ],
    "sg:phone":"+1   ",
    "sg:postcode":"18411",
    "sg:province":"PA",
    "wof:name":"Tracey Boros",
    "wof:placetype":"venue"
},
  "geometry": {"coordinates":[-75.69618,41.499353],"type":"Point"}
}