{
  "type": "Feature",
  "properties": {
    "addr:full":"413 Hazel Ave Butler PA 16001",
    "addr:housenumber":"413",
    "addr:postcode":"16001",
    "addr:street":"Hazel Ave",
    "iso:country":"US",
    "sg:address":"413 Hazel Ave",
    "sg:city":"Butler",
    "sg:classifiers":[
        {
            "category":"Building & Trades",
            "subcategory":"Landscaping Services",
            "type":"Services"
        }
    ],
    "sg:phone":"+1   ",
    "sg:postcode":"16001",
    "sg:province":"PA",
    "wof:name":"Kennedy Lawn Maintenance",
    "wof:placetype":"venue"
},
  "geometry": {"coordinates":[-79.901779,40.857736],"type":"Point"}
}