{
  "type": "Feature",
  "properties": {
    "iso:country":"US",
    "sg:address":"35 Conestoga Woods Rd",
    "sg:city":"Lancaster",
    "sg:classifiers":[
        {
            "category":"Building & Trades",
            "subcategory":"Construction",
            "type":"Services"
        }
    ],
    "sg:phone":"+1 717 569 5191",
    "sg:postcode":"17602",
    "sg:province":"PA",
    "sg:tags":[
        "stone",
        "pointing"
    ],
    "wof:name":"Kessler's Power Wash",
    "wof:placetype":"venue"
},
  "geometry": {"coordinates":[-76.275133,40.037482],"type":"Point"}
}