{
  "type": "Feature",
  "properties": {
    "iso:country":"US",
    "sg:address":"600 Vista Park Dr",
    "sg:city":"Pittsburgh",
    "sg:classifiers":[
        {
            "category":"Professional",
            "subcategory":"Lawyer & Legal Services",
            "type":"Services"
        }
    ],
    "sg:phone":"+1 800 463 3339",
    "sg:postcode":"15205",
    "sg:province":"PA",
    "sg:tags":[
        "notary"
    ],
    "sg:website":"www.kinkos.com",
    "wof:name":"Fedex World Service Center",
    "wof:placetype":"venue"
},
  "geometry": {"coordinates":[-80.13517899999999,40.433708],"type":"Point"}
}