{
  "type": "Feature",
  "properties": {
    "iso:country":"US",
    "sg:address":"9104 Babcock Blvd",
    "sg:city":"Pittsburgh",
    "sg:classifiers":[
        {
            "category":"Health Services",
            "subcategory":"Doctor",
            "type":"Services"
        }
    ],
    "sg:phone":"+1 412 367 4545",
    "sg:postcode":"15237",
    "sg:province":"PA",
    "wof:name":"Plaza Ponte Mario MD",
    "wof:placetype":"venue"
},
  "geometry": {"coordinates":[-80.01619700000001,40.5714],"type":"Point"}
}