{
  "type": "Feature",
  "properties": {
    "iso:country":"US",
    "sg:address":"3405 N 16th St",
    "sg:city":"Philadelphia",
    "sg:classifiers":[
        {
            "category":"Manufacturing",
            "subcategory":"Tools & Machinery",
            "type":"Manufacturing & Wholesale Goods"
        },
        {
            "category":"Shopping",
            "subcategory":"Discount & Variety Stores",
            "type":"Retail Goods"
        },
        {
            "category":"Home & Garden",
            "subcategory":"Carpets & Floor Coverings",
            "type":"Retail Goods"
        }
    ],
    "sg:phone":"+1 267 879 1692",
    "sg:postcode":"19140",
    "sg:province":"PA",
    "sg:tags":[
        "vaults-movers",
        "safe",
        "rigger",
        "erectors",
        "mover"
    ],
    "wof:name":"Fountain Rigging Company",
    "wof:placetype":"venue"
},
  "geometry": {"coordinates":[-75.155428,40.00515],"type":"Point"}
}