{
  "type": "Feature",
  "properties": {
    "iso:country":"US",
    "sg:address":"811 Moravia St",
    "sg:city":"New Castle",
    "sg:classifiers":[
        {
            "category":"Retail",
            "subcategory":"Auto Repair",
            "type":"Services"
        }
    ],
    "sg:phone":"+1 724 654 6866",
    "sg:postcode":"16101",
    "sg:province":"PA",
    "sg:tags":[
        "repairing",
        "automobile"
    ],
    "wof:name":"Pallerino M Svc",
    "wof:placetype":"venue"
},
  "geometry": {"coordinates":[-80.34805900000001,40.991216],"type":"Point"}
}