{
  "type": "Feature",
  "properties": {
    "addr:full":"4503 Old William Penn Hwy Monroeville PA 15146",
    "addr:housenumber":"4503",
    "addr:postcode":"15146",
    "addr:street":"Old William Penn Hwy",
    "iso:country":"US",
    "sg:address":"4503 Old William Penn Hwy",
    "sg:city":"Monroeville",
    "sg:classifiers":[
        {
            "category":"Organizations",
            "subcategory":"Religious Organization",
            "type":"Services"
        }
    ],
    "sg:phone":"+1 412 372 2934",
    "sg:postcode":"15146",
    "sg:province":"PA",
    "wof:name":"Good Shepherd Lutheran Church",
    "wof:placetype":"venue"
},
  "geometry": {"coordinates":[-79.75903099999999,40.444389],"type":"Point"}
}