{
  "type": "Feature",
  "properties": {
    "iso:country":"US",
    "sg:address":"7 Great Valley Pkwy",
    "sg:city":"Malvern",
    "sg:classifiers":[
        {
            "category":"Professional",
            "subcategory":"Management & Consulting",
            "type":"Services"
        }
    ],
    "sg:phone":"+1 610 251 6893",
    "sg:postcode":"19355",
    "sg:province":"PA",
    "sg:tags":[
        "counselor",
        "public",
        "relations"
    ],
    "wof:name":"TMP Worldwide",
    "wof:placetype":"venue"
},
  "geometry": {"coordinates":[-75.536012,40.06364],"type":"Point"}
}