{
  "type": "Feature",
  "properties": {
    "addr:full":"1819 Parade St Erie PA 16503",
    "addr:housenumber":"1819",
    "addr:postcode":"16503",
    "addr:street":"Parade St",
    "iso:country":"US",
    "sg:address":"1819 Parade St",
    "sg:city":"Erie",
    "sg:classifiers":[
        {
            "category":"Retail",
            "subcategory":"Auto Rental",
            "type":"Services"
        },
        {
            "category":"Autos & Motor Vehicles",
            "subcategory":"Auto Supplies",
            "type":"Retail Goods"
        },
        {
            "category":"Retail",
            "subcategory":"Storage",
            "type":"Services"
        },
        {
            "category":"Freight",
            "type":"Transportation"
        },
        {
            "category":"Personal",
            "type":"Services"
        },
        {
            "category":"Building & Trades",
            "subcategory":"Equipment Rental",
            "type":"Services"
        }
    ],
    "sg:phone":"+1 814 806 1117",
    "sg:postcode":"16503",
    "sg:province":"PA",
    "sg:tags":[
        "renting",
        "moving-self",
        "store",
        "leasing",
        "car",
        "household",
        "commercial",
        "trucking",
        "truck",
        "yard",
        "moving",
        "mover",
        "hitch",
        "local",
        "self",
        "trailer"
    ],
    "sg:website":"http://www.uhaul.com",
    "wof:name":"U-Haul Neighborhood Dealer - Sams Auto Sales",
    "wof:placetype":"venue"
},
  "geometry": {"coordinates":[-80.06928600000001,42.121486],"type":"Point"}
}