{
  "type": "Feature",
  "properties": {
    "addr:full":"1815 S 68th St Philadelphia PA 19142",
    "addr:housenumber":"1815",
    "addr:postcode":"19142",
    "addr:street":"S 68Th St",
    "iso:country":"US",
    "sg:address":"1815 S 68th St",
    "sg:city":"Philadelphia",
    "sg:classifiers":[
        {
            "category":"Building & Trades",
            "subcategory":"Plumbing",
            "type":"Services"
        }
    ],
    "sg:phone":"+1 215 727 9240",
    "sg:postcode":"19142",
    "sg:province":"PA",
    "sg:tags":[
        "plumber",
        "contractor"
    ],
    "wof:name":"Knowles' Plumbing",
    "wof:placetype":"venue"
},
  "geometry": {"coordinates":[-75.243296,39.92685],"type":"Point"}
}