{
  "type": "Feature",
  "properties": {
    "iso:country":"US",
    "sg:address":"16 W Pike St",
    "sg:city":"Canonsburg",
    "sg:classifiers":[
        {
            "category":"Personal",
            "subcategory":"Tattoo Parlor",
            "type":"Services"
        },
        {
            "category":"Personal",
            "subcategory":"Piercing",
            "type":"Services"
        }
    ],
    "sg:phone":"+1 724 743 0585",
    "sg:postcode":"15317",
    "sg:province":"PA",
    "wof:name":"Independent Tattoo",
    "wof:placetype":"venue"
},
  "geometry": {"coordinates":[-80.188599,40.258499],"type":"Point"}
}