{
  "type": "Feature",
  "properties": {
    "iso:country":"US",
    "sg:address":"250 Alcoma Blvd Apt 610",
    "sg:city":"Pittsburgh",
    "sg:classifiers":[
        {
            "category":"Professional",
            "subcategory":"Business Services",
            "type":"Services"
        }
    ],
    "sg:phone":"+1 412 969 9757",
    "sg:postcode":"15235",
    "sg:province":"PA",
    "sg:tags":[
        "consultant",
        "coach"
    ],
    "wof:name":"George Special Events",
    "wof:placetype":"venue"
},
  "geometry": {"coordinates":[-79.80011,40.485001],"type":"Point"}
}