{
  "type": "Feature",
  "properties": {
    "iso:country":"US",
    "sg:address":"4117 Old William Penn Hwy",
    "sg:city":"Murrysville",
    "sg:classifiers":[
        {
            "category":"Manufacturing",
            "subcategory":"Buildings",
            "type":"Manufacturing & Wholesale Goods"
        },
        {
            "category":"Real Estate",
            "subcategory":"Real Estate Services",
            "type":"Services"
        },
        {
            "category":"Real Estate",
            "subcategory":"Developer",
            "type":"Services"
        },
        {
            "category":"Building & Trades",
            "subcategory":"Construction",
            "type":"Services"
        }
    ],
    "sg:phone":"+1 724 733 2933",
    "sg:postcode":"15668",
    "sg:province":"PA",
    "sg:tags":[
        "home",
        "builder",
        "management",
        "contractor"
    ],
    "wof:name":"Crawford Realty Company",
    "wof:placetype":"venue"
},
  "geometry": {"coordinates":[-79.689385,40.428103],"type":"Point"}
}