{
  "type": "Feature",
  "properties": {
    "iso:country":"US",
    "sg:address":"4315 Jonestown Rd",
    "sg:city":"Harrisburg",
    "sg:classifiers":[
        {
            "category":"Professional",
            "subcategory":"Art Services",
            "type":"Services"
        },
        {
            "category":"Professional",
            "subcategory":"Printing & Photocopies",
            "type":"Services"
        }
    ],
    "sg:phone":"+1 717 657 3800",
    "sg:postcode":"17109",
    "sg:province":"PA",
    "sg:tags":[
        "graphic",
        "design"
    ],
    "wof:name":"Fastsigns",
    "wof:placetype":"venue"
},
  "geometry": {"coordinates":[-76.820702,40.298901],"type":"Point"}
}