{
  "type": "Feature",
  "properties": {
    "iso:country":"US",
    "sg:address":"1014 Chestnut St",
    "sg:city":"Darby",
    "sg:classifiers":[
        {
            "category":"Manufacturing",
            "subcategory":"Apparel",
            "type":"Manufacturing & Wholesale Goods"
        }
    ],
    "sg:phone":"+1   ",
    "sg:postcode":"19023",
    "sg:province":"PA",
    "sg:tags":[
        "mfg"
    ],
    "wof:name":"Kelly Surplus",
    "wof:placetype":"venue"
},
  "geometry": {"coordinates":[-75.285971,39.91449],"type":"Point"}
}