{
  "type": "Feature",
  "properties": {
    "iso:country":"US",
    "sg:address":"2240 Pinetown Rd",
    "sg:city":"Lewisberry",
    "sg:classifiers":[
        {
            "category":"Professional",
            "type":"Services"
        }
    ],
    "sg:phone":"+1 717 697 0580",
    "sg:postcode":"17339",
    "sg:province":"PA",
    "sg:tags":[
        "establishment"
    ],
    "wof:name":"Nature's Harmony",
    "wof:placetype":"venue"
},
  "geometry": {"coordinates":[-76.90484499999999,40.10121],"type":"Point"}
}