{
  "type": "Feature",
  "properties": {
    "iso:country":"US",
    "sg:address":"525 W Chester Pike",
    "sg:city":"Havertown",
    "sg:classifiers":[
        {
            "category":"Health Services",
            "subcategory":"Doctor",
            "type":"Services"
        }
    ],
    "sg:phone":"+1 610 853 9328",
    "sg:postcode":"19083",
    "sg:province":"PA",
    "sg:tags":[
        "physician",
        "surgeon"
    ],
    "wof:name":"Jefferson Faculty Foundations",
    "wof:placetype":"venue"
},
  "geometry": {"coordinates":[-75.307327,39.970834],"type":"Point"}
}