{
  "type": "Feature",
  "properties": {
    "iso:country":"US",
    "sg:address":"2373 Spring Rd",
    "sg:city":"Punxsutawney",
    "sg:classifiers":[
        {
            "category":"Building & Trades",
            "subcategory":"Construction",
            "type":"Services"
        }
    ],
    "sg:phone":"+1   ",
    "sg:postcode":"15767",
    "sg:province":"PA",
    "sg:tags":[
        "excavation",
        "contractor"
    ],
    "wof:name":"Muths Excavation",
    "wof:placetype":"venue"
},
  "geometry": {"coordinates":[-78.84924700000001,40.998775],"type":"Point"}
}