{
  "type": "Feature",
  "properties": {
    "addr:full":"3400 Aramingo Ave Philadelphia PA 19134",
    "addr:postcode":"3400;19134",
    "addr:street":"Aramingo Ave",
    "iso:country":"US",
    "sg:address":"3400 Aramingo Ave",
    "sg:city":"Philadelphia",
    "sg:classifiers":[
        {
            "category":"Restaurant",
            "type":"Food & Drink"
        }
    ],
    "sg:menulink":"http://www.allmenus.com/pa/philadelphia/56753-subway/menu/",
    "sg:phone":"+1 215 423 0885",
    "sg:postcode":"19134",
    "sg:province":"PA",
    "sg:tags":[
        "american",
        "sandwich"
    ],
    "wof:name":"Subway",
    "wof:placetype":"venue"
},
  "geometry": {"coordinates":[-75.101455,39.99126],"type":"Point"}
}