{
  "type": "Feature",
  "properties": {
    "iso:country":"US",
    "sg:address":"2601 Pennsylvania Ave",
    "sg:city":"Philadelphia",
    "sg:classifiers":[
        {
            "category":"Real Estate",
            "subcategory":"Architect",
            "type":"Services"
        }
    ],
    "sg:phone":"+1 215 763 9973",
    "sg:postcode":"19130",
    "sg:province":"PA",
    "wof:name":"Cecelia Denegre Architecture",
    "wof:placetype":"venue"
},
  "geometry": {"coordinates":[-75.18016299999999,39.967793],"type":"Point"}
}