{
  "type": "Feature",
  "properties": {
    "iso:country":"US",
    "sg:address":"795 Blockhouse Rd",
    "sg:city":"Trout Run",
    "sg:classifiers":[
        {
            "category":"Building & Trades",
            "subcategory":"Construction",
            "type":"Services"
        }
    ],
    "sg:phone":"+1 570 324 2484",
    "sg:postcode":"17771",
    "sg:province":"PA",
    "sg:tags":[
        "excavating",
        "contractor"
    ],
    "wof:name":"Schmouder Construction",
    "wof:placetype":"venue"
},
  "geometry": {"coordinates":[-77.136678,41.497217],"type":"Point"}
}