{
  "type": "Feature",
  "properties": {
    "addr:full":"368 E Washington St New Castle PA 16101",
    "addr:housenumber":"368",
    "addr:postcode":"16101",
    "addr:street":"E Washington St",
    "iso:country":"US",
    "sg:address":"368 E Washington St",
    "sg:city":"New Castle",
    "sg:classifiers":[
        {
            "category":"Shopping",
            "subcategory":"Jewelry",
            "type":"Retail Goods"
        }
    ],
    "sg:phone":"+1 724 658 5441",
    "sg:postcode":"16101",
    "sg:province":"PA",
    "sg:tags":[
        "jeweler"
    ],
    "wof:name":"Greek's House Of Gold",
    "wof:placetype":"venue"
},
  "geometry": {"coordinates":[-80.340484,40.998453],"type":"Point"}
}