{
  "type": "Feature",
  "properties": {
    "iso:country":"US",
    "sg:address":"363 S 7th St",
    "sg:city":"Akron",
    "sg:classifiers":[
        {
            "category":"Restaurant",
            "type":"Food & Drink"
        }
    ],
    "sg:phone":"+1 717 859 4000",
    "sg:postcode":"17501",
    "sg:province":"PA",
    "wof:name":"Piero's Pizza 'N Pasta",
    "wof:placetype":"venue"
},
  "geometry": {"coordinates":[-76.208665,40.149723],"type":"Point"}
}