{
  "type": "Feature",
  "properties": {
    "addr:full":"305 Lincoln Hall Rd Elizabeth PA 15037",
    "addr:housenumber":"305",
    "addr:postcode":"15037",
    "addr:street":"Lincoln Hall Rd",
    "iso:country":"US",
    "sg:address":"305 Lincoln Hall Rd",
    "sg:city":"Elizabeth",
    "sg:classifiers":[
        {
            "category":"Real Estate",
            "subcategory":"Real Estate Services",
            "type":"Services"
        },
        {
            "category":"Banks & Credit Unions",
            "subcategory":"Financial Services",
            "type":"Services"
        }
    ],
    "sg:phone":"+1 412 872 4207",
    "sg:postcode":"15037",
    "sg:province":"PA",
    "sg:tags":[
        "loan",
        "mortgage"
    ],
    "wof:name":"First Commonwealth Home Mortgage",
    "wof:placetype":"venue"
},
  "geometry": {"coordinates":[-79.828907,40.278145],"type":"Point"}
}