{
  "type": "Feature",
  "properties": {
    "iso:country":"US",
    "sg:address":"141 E College Ave",
    "sg:city":"Pleasant Gap",
    "sg:classifiers":[
        {
            "category":"Retail",
            "subcategory":"Pet Boarding",
            "type":"Services"
        }
    ],
    "sg:phone":"+1 814 359 1223",
    "sg:postcode":"16823",
    "sg:province":"PA",
    "sg:tags":[
        "boarding/pet",
        "sitting"
    ],
    "wof:name":"Adrian's Dog House",
    "wof:placetype":"venue"
},
  "geometry": {"coordinates":[-77.744904,40.868801],"type":"Point"}
}