{
  "type": "Feature",
  "properties": {
    "iso:country":"US",
    "sg:address":"413 Klines Corner Rd",
    "sg:city":"Mertztown",
    "sg:classifiers":[
        {
            "category":"Building & Trades",
            "subcategory":"Construction",
            "type":"Services"
        }
    ],
    "sg:phone":"+1 610 682 4615",
    "sg:postcode":"19539",
    "sg:province":"PA",
    "wof:name":"R H Driveway Sealing",
    "wof:placetype":"venue"
},
  "geometry": {"coordinates":[-75.688249,40.525599],"type":"Point"}
}