{
  "type": "Feature",
  "properties": {
    "addr:full":"1738 N Broad St Lansdale PA 19446",
    "addr:housenumber":"1738",
    "addr:postcode":"19446",
    "addr:street":"N Broad St",
    "iso:country":"US",
    "sg:address":"1738 N Broad St",
    "sg:city":"Lansdale",
    "sg:classifiers":[
        {
            "category":"Bars & Pubs",
            "subcategory":"Nightclub",
            "type":"Food & Drink"
        }
    ],
    "sg:phone":"+1 215 368 2640",
    "sg:postcode":"19446",
    "sg:province":"PA",
    "sg:tags":[
        "nightlife"
    ],
    "wof:name":"Luxor Hookah Cafe",
    "wof:placetype":"venue"
},
  "geometry": {"coordinates":[-75.267605,40.257766],"type":"Point"}
}