{
  "type": "Feature",
  "properties": {
    "iso:country":"US",
    "sg:address":"390 Schriver Rd",
    "sg:city":"Gettysburg",
    "sg:classifiers":[
        {
            "category":"Education",
            "subcategory":"Special Training",
            "type":"Public Place"
        }
    ],
    "sg:phone":"+1 717 337 0748",
    "sg:postcode":"17325",
    "sg:province":"PA",
    "sg:tags":[
        "educational"
    ],
    "wof:name":"Wayne E Belt",
    "wof:placetype":"venue"
},
  "geometry": {"coordinates":[-77.291237,39.775243],"type":"Point"}
}