{
  "type": "Feature",
  "properties": {
    "iso:country":"US",
    "sg:address":"217 E Main St ",
    "sg:city":"Lansdale",
    "sg:classifiers":[
        {
            "category":"Restaurant",
            "type":"Food & Drink"
        }
    ],
    "sg:menulink":"http://www.allmenus.com/pa/lansdale/288583-quality-pizza/menu/",
    "sg:phone":"+1 215 361 7400",
    "sg:postcode":"19446",
    "sg:province":"PA",
    "sg:tags":[
        "american",
        "pizza"
    ],
    "wof:name":"Quality Pizza",
    "wof:placetype":"venue"
},
  "geometry": {"coordinates":[-75.28018400000001,40.239613],"type":"Point"}
}