{
  "type": "Feature",
  "properties": {
    "addr:full":"532 Prospect Ave West Grove PA 19390",
    "addr:housenumber":"532",
    "addr:postcode":"19390",
    "addr:street":"Prospect Ave",
    "iso:country":"US",
    "sg:address":"532 Prospect Ave",
    "sg:city":"West Grove",
    "sg:classifiers":[
        {
            "category":"Building & Trades",
            "subcategory":"Construction",
            "type":"Services"
        }
    ],
    "sg:phone":"+1 610 869 2054",
    "sg:postcode":"19390",
    "sg:province":"PA",
    "sg:tags":[
        "painter"
    ],
    "wof:name":"Speakman Painting",
    "wof:placetype":"venue"
},
  "geometry": {"coordinates":[-75.82597800000001,39.814603],"type":"Point"}
}