{
  "type": "Feature",
  "properties": {
    "iso:country":"US",
    "sg:address":"569 13th Ave",
    "sg:city":"New Brighton",
    "sg:classifiers":[
        {
            "category":"Organizations",
            "subcategory":"Religious Organization",
            "type":"Services"
        }
    ],
    "sg:phone":"+1 724 891 0382",
    "sg:postcode":"15066",
    "sg:province":"PA",
    "sg:tags":[
        "church"
    ],
    "wof:name":"Church Of Jesus Christ Of Lds",
    "wof:placetype":"venue"
},
  "geometry": {"coordinates":[-80.310143,40.740802],"type":"Point"}
}