{
  "type": "Feature",
  "properties": {
    "iso:country":"US",
    "sg:address":"113 Deep Brook Rd",
    "sg:city":"Milford",
    "sg:classifiers":[
        {
            "category":"Building & Trades",
            "subcategory":"Construction",
            "type":"Services"
        }
    ],
    "sg:phone":"+1 570 409 1722",
    "sg:postcode":"18337",
    "sg:province":"PA",
    "sg:tags":[
        "handyman"
    ],
    "wof:name":"Bob's Handyman's Svc",
    "wof:placetype":"venue"
},
  "geometry": {"coordinates":[-74.799155,41.337702],"type":"Point"}
}