{
  "type": "Feature",
  "properties": {
    "iso:country":"US",
    "sg:address":"5357 Maple Grove Rd",
    "sg:city":"Bulger",
    "sg:classifiers":[
        {
            "category":"Farming",
            "subcategory":"Livestock Farm",
            "type":"Manufacturing & Wholesale Goods"
        }
    ],
    "sg:phone":"+1   ",
    "sg:postcode":"15019",
    "sg:province":"PA",
    "sg:tags":[
        "beef",
        "feedlot",
        "cattle"
    ],
    "wof:name":"James Jones",
    "wof:placetype":"venue"
},
  "geometry": {"coordinates":[-80.333549,40.406566],"type":"Point"}
}