{
  "type": "Feature",
  "properties": {
    "iso:country":"US",
    "sg:address":"106 S 3rd St",
    "sg:city":"Darby",
    "sg:classifiers":[
        {
            "category":"Building & Trades",
            "subcategory":"Locksmith",
            "type":"Services"
        }
    ],
    "sg:phone":"+1 215 642 2051",
    "sg:postcode":"19023",
    "sg:province":"PA",
    "sg:tags":[
        "key"
    ],
    "wof:name":"20 Minute Locksmith",
    "wof:placetype":"venue"
},
  "geometry": {"coordinates":[-75.252323,39.915497],"type":"Point"}
}