{
  "type": "Feature",
  "properties": {
    "iso:country":"US",
    "sg:address":"1525 5th Ave",
    "sg:city":"Pittsburgh",
    "sg:classifiers":[
        {
            "category":"Restaurant",
            "type":"Food & Drink"
        }
    ],
    "sg:menulink":"http://www.allmenus.com/pa/pittsburgh/287579-da-pizza-bella/menu/",
    "sg:phone":"+1 412 281 8585",
    "sg:postcode":"15219",
    "sg:province":"PA",
    "sg:tags":[
        "sandwich",
        "salad",
        "dessert",
        "wing",
        "calzones",
        "american",
        "gyro",
        "pasta",
        "pizza",
        "hoagy",
        "italian"
    ],
    "wof:name":"Da Pizza Bella",
    "wof:placetype":"venue"
},
  "geometry": {"coordinates":[-79.984353,40.438726],"type":"Point"}
}