{
  "type": "Feature",
  "properties": {
    "iso:country":"US",
    "sg:address":"1793 Folk Rd",
    "sg:city":"Fogelsville",
    "sg:classifiers":[
        {
            "category":"Farming",
            "subcategory":"Farm",
            "type":"Manufacturing & Wholesale Goods"
        }
    ],
    "sg:phone":"+1   ",
    "sg:postcode":"18051",
    "sg:province":"PA",
    "sg:tags":[
        "crop",
        "general"
    ],
    "wof:name":"Timothy Schadler",
    "wof:placetype":"venue"
},
  "geometry": {"coordinates":[-75.670725,40.578075],"type":"Point"}
}