{
  "type": "Feature",
  "properties": {
    "iso:country":"US",
    "sg:address":"28 Main St",
    "sg:city":"Lawrenceville",
    "sg:classifiers":[
        {
            "category":"Manufacturing",
            "subcategory":"Furniture",
            "type":"Manufacturing & Wholesale Goods"
        }
    ],
    "sg:phone":"+1   ",
    "sg:postcode":"16901",
    "sg:province":"PA",
    "sg:tags":[
        "household",
        "wood",
        "mfg"
    ],
    "wof:name":"Lockhrts Amish Hndcrafted Furn",
    "wof:placetype":"venue"
},
  "geometry": {"coordinates":[-77.29955200000001,41.749373],"type":"Point"}
}