{
  "type": "Feature",
  "properties": {
    "iso:country":"US",
    "sg:address":"700 W High St",
    "sg:city":"Stowe",
    "sg:phone":"+1 610 326 3283",
    "sg:postcode":"19464",
    "sg:province":"PA",
    "sg:tags":[
        "oil"
    ],
    "wof:name":"Reed's Fuel Oil",
    "wof:placetype":"venue"
},
  "geometry": {"coordinates":[-75.679317,40.246643],"type":"Point"}
}