{
  "type": "Feature",
  "properties": {
    "iso:country":"US",
    "sg:address":"930 Dewberry Ct",
    "sg:city":"Chambersburg",
    "sg:classifiers":[
        {
            "category":"Professional",
            "type":"Services"
        }
    ],
    "sg:phone":"+1   ",
    "sg:postcode":"17201",
    "sg:province":"PA",
    "wof:name":"Sandsons Inc",
    "wof:placetype":"venue"
},
  "geometry": {"coordinates":[-77.64866600000001,39.924058],"type":"Point"}
}