{
  "type": "Feature",
  "properties": {
    "iso:country":"US",
    "sg:address":"507 W Broad St",
    "sg:city":"New Holland",
    "sg:classifiers":[
        {
            "category":"Health Services",
            "subcategory":"Doctor",
            "type":"Services"
        }
    ],
    "sg:phone":"+1   ",
    "sg:postcode":"17557",
    "sg:province":"PA",
    "wof:name":"J Sheaffer II D",
    "wof:placetype":"venue"
},
  "geometry": {"coordinates":[-76.102144,40.099462],"type":"Point"}
}