{
  "type": "Feature",
  "properties": {
    "iso:country":"US",
    "sg:address":"7038 Front River Rd",
    "sg:city":"Pittsburgh",
    "sg:classifiers":[
        {
            "category":"Insurance",
            "subcategory":"Insurance Agent",
            "type":"Services"
        }
    ],
    "sg:phone":"+1   ",
    "sg:postcode":"15225",
    "sg:province":"PA",
    "sg:tags":[
        "research"
    ],
    "wof:name":"Praesidium Technologies Inc",
    "wof:placetype":"venue"
},
  "geometry": {"coordinates":[-80.142594,40.516426],"type":"Point"}
}