{
  "type": "Feature",
  "properties": {
    "addr:full":"205 Newtown Rd Ste 107 Warminster PA 18974",
    "addr:housenumber":"205",
    "addr:postcode":"18974",
    "addr:street":"Newtown Rd Ste 107",
    "iso:country":"US",
    "sg:address":"205 Newtown Rd Ste 107",
    "sg:city":"Warminster",
    "sg:classifiers":[
        {
            "category":"Health Services",
            "subcategory":"Doctor",
            "type":"Services"
        }
    ],
    "sg:phone":"+1 215 442 9984",
    "sg:postcode":"18974",
    "sg:province":"PA",
    "sg:tags":[
        "physician",
        "surgeon",
        "neurology",
        "surgeons"
    ],
    "wof:name":"Beken Ferhan DR Management Center",
    "wof:placetype":"venue"
},
  "geometry": {"coordinates":[-75.080873,40.184356],"type":"Point"}
}