{
  "type": "Feature",
  "properties": {
    "addr:full":"1849 2nd Ave York PA 17402",
    "addr:housenumber":"1849",
    "addr:postcode":"17402",
    "addr:street":"2Nd Ave",
    "iso:country":"US",
    "sg:address":"1849 2nd Ave",
    "sg:city":"York",
    "sg:classifiers":[
        {
            "category":"Professional",
            "subcategory":"Business Services",
            "type":"Services"
        }
    ],
    "sg:phone":"+1 717 840 7870",
    "sg:postcode":"17402",
    "sg:province":"PA",
    "sg:tags":[
        "notary"
    ],
    "wof:name":"Sue's Office Svc",
    "wof:placetype":"venue"
},
  "geometry": {"coordinates":[-76.689652,39.96972],"type":"Point"}
}