{
  "type": "Feature",
  "properties": {
    "addr:full":"2865 William Flynn Hwy Slippery Rock PA 16057",
    "addr:housenumber":"2865",
    "addr:postcode":"16057",
    "addr:street":"William Flynn Hwy",
    "iso:country":"US",
    "sg:address":"2865 William Flynn Hwy",
    "sg:city":"Slippery Rock",
    "sg:classifiers":[
        {
            "category":"Museum",
            "type":"Entertainment"
        }
    ],
    "sg:phone":"+1 724 794 4296",
    "sg:postcode":"16057",
    "sg:province":"PA",
    "sg:tags":[
        "gallery"
    ],
    "wof:name":"Old Stone House",
    "wof:placetype":"venue"
},
  "geometry": {"coordinates":[-80.002404,41.011307],"type":"Point"}
}