{
  "type": "Feature",
  "properties": {
    "iso:country":"US",
    "sg:address":"2231 Lebanon Valley Mall",
    "sg:city":"Lebanon",
    "sg:classifiers":[
        {
            "category":"Shopping",
            "subcategory":"Department Store",
            "type":"Retail Goods"
        }
    ],
    "sg:phone":"+1 717 274 1485",
    "sg:postcode":"17042",
    "sg:province":"PA",
    "wof:name":"Ames Department Store",
    "wof:placetype":"venue"
},
  "geometry": {"coordinates":[-76.453312,40.339794],"type":"Point"}
}