{
  "type": "Feature",
  "properties": {
    "iso:country":"US",
    "sg:address":"709 S Chester Rd",
    "sg:city":"Swarthmore",
    "sg:classifiers":[
        {
            "category":"Health Services",
            "subcategory":"Clinic",
            "type":"Services"
        }
    ],
    "sg:phone":"+1   ",
    "sg:postcode":"19081",
    "sg:province":"PA",
    "sg:tags":[
        "kidney",
        "dialysis",
        "center"
    ],
    "wof:name":"Swarthmore Dialysis Ctr 2020",
    "wof:placetype":"venue"
},
  "geometry": {"coordinates":[-75.355323,39.887843],"type":"Point"}
}