{
  "type": "Feature",
  "properties": {
    "iso:country":"US",
    "sg:address":"59 Minard Run Rd",
    "sg:city":"Bradford",
    "sg:classifiers":[
        {
            "category":"Professional",
            "type":"Services"
        }
    ],
    "sg:phone":"+1 814 362 1221",
    "sg:postcode":"16701",
    "sg:province":"PA",
    "sg:tags":[
        "establishment"
    ],
    "wof:name":"Rod Shop",
    "wof:placetype":"venue"
},
  "geometry": {"coordinates":[-78.6485,41.914287],"type":"Point"}
}