{
  "type": "Feature",
  "properties": {
    "iso:country":"US",
    "sg:address":"231 9th St",
    "sg:city":"Saltsburg",
    "sg:classifiers":[
        {
            "category":"Freight",
            "type":"Transportation"
        },
        {
            "category":"Professional",
            "subcategory":"Business Services",
            "type":"Services"
        }
    ],
    "sg:phone":"+1 724 639 3444",
    "sg:postcode":"15681",
    "sg:province":"PA",
    "sg:tags":[
        "operator",
        "water",
        "local",
        "hauling",
        "trucking"
    ],
    "wof:name":"Wagner Trucking Inc",
    "wof:placetype":"venue"
},
  "geometry": {"coordinates":[-79.447889,40.493497],"type":"Point"}
}