{
  "type": "Feature",
  "properties": {
    "iso:country":"US",
    "sg:address":"227 W Broad St",
    "sg:city":"Bethlehem",
    "sg:classifiers":[
        {
            "category":"Professional",
            "type":"Services"
        },
        {
            "category":"Professional",
            "subcategory":"Management & Consulting",
            "type":"Services"
        }
    ],
    "sg:phone":"+1 610 866 8665",
    "sg:postcode":"18018",
    "sg:province":"PA",
    "sg:tags":[
        "establishment"
    ],
    "wof:name":"College Funding Associates",
    "wof:placetype":"venue"
},
  "geometry": {"coordinates":[-75.38545499999999,40.622408],"type":"Point"}
}