{
  "type": "Feature",
  "properties": {
    "addr:full":"1 Industrial Way Denver PA 17517",
    "addr:housenumber":"1",
    "addr:postcode":"17517",
    "addr:street":"Industrial Way",
    "iso:country":"US",
    "sg:address":"1 Industrial Way",
    "sg:city":"Denver",
    "sg:classifiers":[
        {
            "category":"Manufacturing",
            "subcategory":"Chemicals & Compounds",
            "type":"Manufacturing & Wholesale Goods"
        }
    ],
    "sg:phone":"+1 717 336 7900",
    "sg:postcode":"17517",
    "sg:province":"PA",
    "sg:tags":[
        "paint",
        "varnish",
        "allied",
        "product"
    ],
    "sg:website":"www.proguardcoatings.com",
    "wof:name":"Pro Guard Coatings",
    "wof:placetype":"venue"
},
  "geometry": {"coordinates":[-76.111992,40.22179],"type":"Point"}
}