{
  "type": "Feature",
  "properties": {
    "addr:full":"2108 New Danville Pike Lancaster PA 17603",
    "addr:housenumber":"2108",
    "addr:postcode":"17603",
    "addr:street":"New Danville Pike",
    "iso:country":"US",
    "sg:address":"2108 New Danville Pike",
    "sg:city":"Lancaster",
    "sg:classifiers":[
        {
            "category":"Food & Beverages",
            "subcategory":"Groceries & Convenience Stores",
            "type":"Retail Goods"
        }
    ],
    "sg:phone":"+1 717 871 1470",
    "sg:postcode":"17603",
    "sg:province":"PA",
    "wof:name":"Country Boy Meats",
    "wof:placetype":"venue"
},
  "geometry": {"coordinates":[-76.31572199999999,39.985277],"type":"Point"}
}