{
  "type": "Feature",
  "properties": {
    "addr:full":"628 Barkeyville Rd Grove City PA 16127",
    "addr:housenumber":"628",
    "addr:postcode":"16127",
    "addr:street":"Barkeyville Rd",
    "iso:country":"US",
    "sg:address":"628 Barkeyville Rd",
    "sg:city":"Grove City",
    "sg:phone":"+1 724 458 4300",
    "sg:postcode":"16127",
    "sg:province":"PA",
    "sg:tags":[
        "food",
        "equipment",
        "processing"
    ],
    "wof:name":"Commercial Appliance Contracts",
    "wof:placetype":"venue"
},
  "geometry": {"coordinates":[-80.06881799999999,41.169221],"type":"Point"}
}