{
  "type": "Feature",
  "properties": {
    "addr:full":"100 Lincoln Ave Carbondale PA 18407",
    "addr:housenumber":"100",
    "addr:postcode":"18407",
    "addr:street":"Lincoln Ave",
    "iso:country":"US",
    "sg:address":"100 Lincoln Ave",
    "sg:city":"Carbondale",
    "sg:classifiers":[
        {
            "category":"Social Services",
            "type":"Services"
        }
    ],
    "sg:phone":"+1 570 282 7135",
    "sg:postcode":"18407",
    "sg:province":"PA",
    "sg:tags":[
        "care",
        "center",
        "day"
    ],
    "wof:name":"Adult Day Svc",
    "wof:placetype":"venue"
},
  "geometry": {"coordinates":[-75.496904,41.572434],"type":"Point"}
}