{
  "type": "Feature",
  "properties": {
    "iso:country":"US",
    "sg:address":"5100 Peach St",
    "sg:city":"Erie",
    "sg:classifiers":[
        {
            "category":"Health Services",
            "subcategory":"Health Practitioner",
            "type":"Services"
        }
    ],
    "sg:phone":"+1   ",
    "sg:postcode":"16509",
    "sg:province":"PA",
    "wof:name":"Theraputic Rehab & Athc Care",
    "wof:placetype":"venue"
},
  "geometry": {"coordinates":[-80.091779,42.078484],"type":"Point"}
}