{
  "type": "Feature",
  "properties": {
    "iso:country":"US",
    "sg:address":"2652 Frankford Ave 58",
    "sg:city":"Philadelphia",
    "sg:classifiers":[
        {
            "category":"Manufacturing",
            "subcategory":"Petroleum Products",
            "type":"Manufacturing & Wholesale Goods"
        },
        {
            "category":"Wholesale",
            "subcategory":"Petroleum",
            "type":"Manufacturing & Wholesale Goods"
        }
    ],
    "sg:phone":"+1 215 680 0103",
    "sg:postcode":"19125",
    "sg:province":"PA",
    "sg:tags":[
        "manufacturer",
        "products-wholesale",
        "oils-petroleum"
    ],
    "wof:name":"Ravi Petroleum",
    "wof:placetype":"venue"
},
  "geometry": {"coordinates":[-75.123096,39.98634],"type":"Point"}
}