{
  "type": "Feature",
  "properties": {
    "addr:full":"2217 Derry St Harrisburg PA 17104",
    "addr:housenumber":"2217",
    "addr:postcode":"17104",
    "addr:street":"Derry St",
    "iso:country":"US",
    "sg:address":"2217 Derry St",
    "sg:city":"Harrisburg",
    "sg:classifiers":[
        {
            "category":"Autos & Motor Vehicles",
            "subcategory":"Automobile Sales",
            "type":"Retail Goods"
        }
    ],
    "sg:phone":"+1   ",
    "sg:postcode":"17104",
    "sg:province":"PA",
    "wof:name":"Lehman Motors",
    "wof:placetype":"venue"
},
  "geometry": {"coordinates":[-76.84977499999999,40.26028],"type":"Point"}
}