{
  "type": "Feature",
  "properties": {
    "addr:full":"9477 Roosevelt Blvd Philadelphia PA 19114",
    "addr:housenumber":"9477",
    "addr:postcode":"19114",
    "addr:street":"Roosevelt Blvd",
    "iso:country":"US",
    "sg:address":"9477 Roosevelt Blvd",
    "sg:city":"Philadelphia",
    "sg:classifiers":[
        {
            "category":"Shopping",
            "subcategory":"Clothing, Apparel, & Fashions",
            "type":"Retail Goods"
        }
    ],
    "sg:phone":"+1 215 676 7772",
    "sg:postcode":"19114",
    "sg:province":"PA",
    "wof:name":"Annie Sez",
    "wof:placetype":"venue"
},
  "geometry": {"coordinates":[-75.029487,40.079258],"type":"Point"}
}