{
  "type": "Feature",
  "properties": {
    "addr:full":"3755 Aramingo Ave Philadelphia PA 19137",
    "addr:housenumber":"3755",
    "addr:postcode":"19137",
    "addr:street":"Aramingo Ave",
    "iso:country":"US",
    "sg:address":"3755 Aramingo Ave",
    "sg:city":"Philadelphia",
    "sg:classifiers":[
        {
            "category":"Autos & Motor Vehicles",
            "subcategory":"Auto Supplies",
            "type":"Retail Goods"
        }
    ],
    "sg:phone":"+1 215 289 0829",
    "sg:postcode":"19137",
    "sg:province":"PA",
    "sg:tags":[
        "automobile",
        "part",
        "tire"
    ],
    "sg:website":"www.straussauto.com",
    "wof:name":"Strauss Discount Auto",
    "wof:placetype":"venue"
},
  "geometry": {"coordinates":[-75.092499,39.995899],"type":"Point"}
}