{
  "type": "Feature",
  "properties": {
    "iso:country":"US",
    "sg:address":"250 Barcladen Cir",
    "sg:city":"Bryn Mawr",
    "sg:classifiers":[
        {
            "category":"Shopping",
            "subcategory":"Bicycles & Sporting Goods",
            "type":"Retail Goods"
        }
    ],
    "sg:phone":"+1   ",
    "sg:postcode":"19010",
    "sg:province":"PA",
    "wof:name":"No End Productions Inc",
    "wof:placetype":"venue"
},
  "geometry": {"coordinates":[-75.342017,40.027616],"type":"Point"}
}