{
  "type": "Feature",
  "properties": {
    "iso:country":"US",
    "sg:address":"671 Bryn Mawr Rd",
    "sg:city":"Pittsburgh",
    "sg:classifiers":[
        {
            "category":"Social Services",
            "subcategory":"Child Care",
            "type":"Services"
        }
    ],
    "sg:phone":"+1 412 681 9104",
    "sg:postcode":"15219",
    "sg:province":"PA",
    "sg:tags":[
        "day"
    ],
    "wof:name":"First Stop Child Care Center",
    "wof:placetype":"venue"
},
  "geometry": {"coordinates":[-79.962367,40.453102],"type":"Point"}
}