{
  "type": "Feature",
  "properties": {
    "addr:full":"439 W Main St Ridgway PA 15853",
    "addr:housenumber":"439",
    "addr:postcode":"15853",
    "addr:street":"W Main St",
    "iso:country":"US",
    "sg:address":"439 W Main St",
    "sg:city":"Ridgway",
    "sg:classifiers":[
        {
            "category":"Building & Trades",
            "subcategory":"Construction",
            "type":"Services"
        }
    ],
    "sg:phone":"+1 814 772 9809",
    "sg:postcode":"15853",
    "sg:province":"PA",
    "sg:tags":[
        "contractor"
    ],
    "wof:name":"Mercer Welding & Repair",
    "wof:placetype":"venue"
},
  "geometry": {"coordinates":[-78.744298,41.420733],"type":"Point"}
}