{
  "type": "Feature",
  "properties": {
    "iso:country":"US",
    "sg:address":"37 Farmington Rd",
    "sg:city":"Mertztown",
    "sg:classifiers":[
        {
            "category":"Professional",
            "subcategory":"Engineering",
            "type":"Services"
        }
    ],
    "sg:phone":"+1   ",
    "sg:postcode":"19539",
    "sg:province":"PA",
    "wof:name":"Arts Custom Engineering & Mch",
    "wof:placetype":"venue"
},
  "geometry": {"coordinates":[-75.688078,40.541046],"type":"Point"}
}