{
  "type": "Feature",
  "properties": {
    "iso:country":"US",
    "sg:address":"1728 N Keyser Ave",
    "sg:city":"Scranton",
    "sg:classifiers":[
        {
            "category":"Building & Trades",
            "subcategory":"Equipment Rental",
            "type":"Services"
        }
    ],
    "sg:phone":"+1 570 348 4000",
    "sg:postcode":"18508",
    "sg:province":"PA",
    "sg:tags":[
        "own",
        "offer",
        "to",
        "rent",
        "which",
        "home",
        "electronics",
        "store"
    ],
    "wof:name":"Rent-A-Center",
    "wof:placetype":"venue"
},
  "geometry": {"coordinates":[-75.670396,41.444552],"type":"Point"}
}