{
  "type": "Feature",
  "properties": {
    "iso:country":"US",
    "sg:address":"3641 Pricetown Rd",
    "sg:city":"Fleetwood",
    "sg:classifiers":[
        {
            "category":"Manufacturing",
            "subcategory":"Buildings",
            "type":"Manufacturing & Wholesale Goods"
        },
        {
            "category":"Building & Trades",
            "subcategory":"Construction",
            "type":"Services"
        }
    ],
    "sg:phone":"+1 610 944 6100",
    "sg:postcode":"19522",
    "sg:province":"PA",
    "sg:tags":[
        "home",
        "builder",
        "contractor"
    ],
    "wof:name":"Deysher Custom Homes Inc",
    "wof:placetype":"venue"
},
  "geometry": {"coordinates":[-75.828671,40.425203],"type":"Point"}
}