{
  "type": "Feature",
  "properties": {
    "addr:full":"7150 Carlisle Rd Dover PA 17315",
    "addr:housenumber":"7150",
    "addr:postcode":"17315",
    "addr:street":"Carlisle Rd",
    "iso:country":"US",
    "sg:address":"7150 Carlisle Rd",
    "sg:city":"Dover",
    "sg:classifiers":[
        {
            "category":"Farming",
            "subcategory":"Livestock Farm",
            "type":"Manufacturing & Wholesale Goods"
        }
    ],
    "sg:phone":"+1   ",
    "sg:postcode":"17315",
    "sg:province":"PA",
    "sg:tags":[
        "hog",
        "beef",
        "far",
        "corn",
        "cattle",
        "or",
        "feedlot"
    ],
    "wof:name":"Ricky Grove",
    "wof:placetype":"venue"
},
  "geometry": {"coordinates":[-76.90403999999999,40.049189],"type":"Point"}
}