{
  "type": "Feature",
  "properties": {
    "iso:country":"US",
    "sg:address":"14 Knob Rd",
    "sg:city":"Mt Pocono",
    "sg:classifiers":[
        {
            "category":"Real Estate",
            "subcategory":"Real Estate Agent",
            "type":"Services"
        }
    ],
    "sg:phone":"+1 570 839 9191",
    "sg:postcode":"18344",
    "sg:province":"PA",
    "sg:website":"www.remaxofthepoconos.com",
    "wof:name":"Re/Max Of The Poconos",
    "wof:placetype":"venue"
},
  "geometry": {"coordinates":[-75.352897,41.1198],"type":"Point"}
}