{
  "type": "Feature",
  "properties": {
    "addr:full":"331 Fanker Rd Harmony PA 16037",
    "addr:housenumber":"331",
    "addr:postcode":"16037",
    "addr:street":"Fanker Rd",
    "iso:country":"US",
    "sg:address":"331 Fanker Rd",
    "sg:city":"Harmony",
    "sg:classifiers":[
        {
            "category":"Building & Trades",
            "subcategory":"Construction",
            "type":"Services"
        }
    ],
    "sg:phone":"+1   ",
    "sg:postcode":"16037",
    "sg:province":"PA",
    "sg:tags":[
        "residential"
    ],
    "wof:name":"Lariat Development",
    "wof:placetype":"venue"
},
  "geometry": {"coordinates":[-80.146772,40.813921],"type":"Point"}
}