{
  "type": "Feature",
  "properties": {
    "addr:full":"1307 E Carson St Pittsburgh PA 15203",
    "addr:housenumber":"1307",
    "addr:postcode":"15203",
    "addr:street":"E Carson St",
    "iso:country":"US",
    "sg:address":"1307 E Carson St",
    "sg:city":"Pittsburgh",
    "sg:classifiers":[
        {
            "category":"Shopping",
            "subcategory":"Gifts & Souvenirs",
            "type":"Retail Goods"
        }
    ],
    "sg:phone":"+1 412 481 2750",
    "sg:postcode":"15203",
    "sg:province":"PA",
    "sg:tags":[
        "shop"
    ],
    "wof:name":"Howerla Parcels",
    "wof:placetype":"venue"
},
  "geometry": {"coordinates":[-79.98420400000001,40.428872],"type":"Point"}
}