{
  "type": "Feature",
  "properties": {
    "iso:country":"US",
    "sg:address":"1311 S Albemarle St",
    "sg:city":"York",
    "sg:classifiers":[
        {
            "category":"Arena",
            "subcategory":"Sports Club",
            "type":"Entertainment"
        }
    ],
    "sg:phone":"+1 717 843 0311",
    "sg:postcode":"17403",
    "sg:province":"PA",
    "sg:tags":[
        "health"
    ],
    "wof:name":"Unity York Sports",
    "wof:placetype":"venue"
},
  "geometry": {"coordinates":[-76.70129,39.950498],"type":"Point"}
}