{
  "type": "Feature",
  "properties": {
    "iso:country":"US",
    "sg:address":"3050 N 5th Street Hwy Ste G3",
    "sg:city":"Reading",
    "sg:classifiers":[
        {
            "category":"Personal",
            "subcategory":"Beauty Salon",
            "type":"Services"
        }
    ],
    "sg:phone":"+1 610 921 8626",
    "sg:postcode":"19605",
    "sg:province":"PA",
    "wof:name":"Cost Cutters",
    "wof:placetype":"venue"
},
  "geometry": {"coordinates":[-75.927249,40.37959],"type":"Point"}
}