{
  "type": "Feature",
  "properties": {
    "iso:country":"US",
    "sg:address":"15 Merion Ave",
    "sg:city":"Conshohocken",
    "sg:classifiers":[
        {
            "category":"Arts & Performance",
            "subcategory":"Theater",
            "type":"Entertainment"
        }
    ],
    "sg:phone":"+1 610 631 5796",
    "sg:postcode":"19428",
    "sg:province":"PA",
    "sg:tags":[
        "clown"
    ],
    "wof:name":"Pookie The Clown",
    "wof:placetype":"venue"
},
  "geometry": {"coordinates":[-75.313568,40.069547],"type":"Point"}
}