{
  "type": "Feature",
  "properties": {
    "iso:country":"US",
    "sg:address":"107 6th St",
    "sg:city":"Pittsburgh",
    "sg:classifiers":[
        {
            "category":"Wholesale",
            "subcategory":"Medical Equipment & Supplies",
            "type":"Manufacturing & Wholesale Goods"
        }
    ],
    "sg:phone":"+1   ",
    "sg:postcode":"15222",
    "sg:province":"PA",
    "wof:name":"Herman Feldman Dental Sup Co",
    "wof:placetype":"venue"
},
  "geometry": {"coordinates":[-80.00264199999999,40.444034],"type":"Point"}
}