{
  "type": "Feature",
  "properties": {
    "addr:full":"60 Clay St Mountville PA 17554",
    "addr:housenumber":"60",
    "addr:postcode":"17554",
    "addr:street":"Clay St",
    "iso:country":"US",
    "sg:address":"60 Clay St",
    "sg:city":"Mountville",
    "sg:classifiers":[
        {
            "category":"Organizations",
            "subcategory":"Religious Organization",
            "type":"Services"
        }
    ],
    "sg:phone":"+1 717 285 5122",
    "sg:postcode":"17554",
    "sg:province":"PA",
    "sg:tags":[
        "church",
        "day",
        "care"
    ],
    "wof:name":"Mountville Church of Brethren",
    "wof:placetype":"venue"
},
  "geometry": {"coordinates":[-76.427179,40.041954],"type":"Point"}
}