{
  "type": "Feature",
  "properties": {
    "iso:country":"US",
    "sg:address":"2699 S Queen St",
    "sg:city":"York",
    "sg:classifiers":[
        {
            "category":"Wholesale",
            "subcategory":"Furniture",
            "type":"Manufacturing & Wholesale Goods"
        }
    ],
    "sg:phone":"+1 717 741 4894",
    "sg:postcode":"17402",
    "sg:province":"PA",
    "wof:name":"Quality Digital Office Tech",
    "wof:placetype":"venue"
},
  "geometry": {"coordinates":[-76.681225,39.909386],"type":"Point"}
}