{
  "type": "Feature",
  "properties": {
    "iso:country":"US",
    "sg:address":"1344 Washington Rd",
    "sg:city":"Pittsburgh",
    "sg:classifiers":[
        {
            "category":"Professional",
            "subcategory":"Computer Services",
            "type":"Services"
        }
    ],
    "sg:phone":"+1 412 341 1470",
    "sg:postcode":"15228",
    "sg:province":"PA",
    "sg:tags":[
        "consultant",
        "designer"
    ],
    "wof:name":"Bimpal Computer",
    "wof:placetype":"venue"
},
  "geometry": {"coordinates":[-80.04995599999999,40.358428],"type":"Point"}
}