{
  "type": "Feature",
  "properties": {
    "iso:country":"US",
    "sg:address":"181 Willow St",
    "sg:city":"Toughkenamon",
    "sg:classifiers":[
        {
            "category":"Professional",
            "subcategory":"Business Services",
            "type":"Services"
        }
    ],
    "sg:phone":"+1   ",
    "sg:postcode":"19374",
    "sg:province":"PA",
    "wof:name":"Warehouse",
    "wof:placetype":"venue"
},
  "geometry": {"coordinates":[-75.75570999999999,39.830233],"type":"Point"}
}