{
  "type": "Feature",
  "properties": {
    "iso:country":"US",
    "sg:address":"2002 Rittenhouse Sq",
    "sg:city":"Philadelphia",
    "sg:classifiers":[
        {
            "category":"Health Services",
            "subcategory":"Chiropractor",
            "type":"Services"
        }
    ],
    "sg:phone":"+1 215 985 9520",
    "sg:postcode":"19103",
    "sg:province":"PA",
    "wof:name":"Chiropractic Centers of Rittenhouse Sq & Cherry Hl",
    "wof:placetype":"venue"
},
  "geometry": {"coordinates":[-75.17440000000001,39.948799],"type":"Point"}
}