{
  "type": "Feature",
  "properties": {
    "iso:country":"US",
    "sg:address":"6035 Memorial Rd",
    "sg:city":"Germansville",
    "sg:classifiers":[
        {
            "category":"Building & Trades",
            "subcategory":"Construction",
            "type":"Services"
        }
    ],
    "sg:phone":"+1 610 767 6515",
    "sg:postcode":"18053",
    "sg:province":"PA",
    "sg:tags":[
        "carpenter"
    ],
    "sg:website":"http://www.glumber.com",
    "wof:name":"Grothouse Lumber & Fine Carpentry",
    "wof:placetype":"venue"
},
  "geometry": {"coordinates":[-75.70681999999999,40.701464],"type":"Point"}
}