{
  "type": "Feature",
  "properties": {
    "addr:full":"1611 Manor Blvd Lancaster PA 17603",
    "addr:housenumber":"1611",
    "addr:postcode":"17603",
    "addr:street":"Manor Blvd",
    "iso:country":"US",
    "sg:address":"1611 Manor Blvd",
    "sg:city":"Lancaster",
    "sg:classifiers":[
        {
            "category":"Recreation",
            "type":"Entertainment"
        }
    ],
    "sg:phone":"+1   ",
    "sg:postcode":"17603",
    "sg:province":"PA",
    "sg:tags":[
        "club",
        "membership"
    ],
    "wof:name":"S Fairview Rod Gun Club",
    "wof:placetype":"venue"
},
  "geometry": {"coordinates":[-76.375484,40.015922],"type":"Point"}
}