{
  "type": "Feature",
  "properties": {
    "iso:country":"US",
    "sg:address":"11 Grace Dr",
    "sg:city":"Wilkes Barre",
    "sg:classifiers":[
        {
            "category":"Building & Trades",
            "subcategory":"Construction",
            "type":"Services"
        }
    ],
    "sg:phone":"+1 570 823 4846",
    "sg:postcode":"18705",
    "sg:province":"PA",
    "sg:tags":[
        "contractor"
    ],
    "wof:name":"Joe Shem Building Contractor",
    "wof:placetype":"venue"
},
  "geometry": {"coordinates":[-75.835154,41.278903],"type":"Point"}
}