{
  "type": "Feature",
  "properties": {
    "iso:country":"US",
    "sg:address":"38 N 5th St",
    "sg:city":"Indiana",
    "sg:classifiers":[
        {
            "category":"Shopping",
            "subcategory":"Bicycles & Sporting Goods",
            "type":"Retail Goods"
        }
    ],
    "sg:phone":"+1 724 349 3520",
    "sg:postcode":"15701",
    "sg:province":"PA",
    "sg:tags":[
        "gun",
        "gunsmith"
    ],
    "wof:name":"Joe's Guns & Ammo",
    "wof:placetype":"venue"
},
  "geometry": {"coordinates":[-79.14827200000001,40.624186],"type":"Point"}
}