{
  "type": "Feature",
  "properties": {
    "iso:country":"US",
    "sg:address":"56 E 3rd St",
    "sg:city":"Williamsport",
    "sg:classifiers":[
        {
            "category":"Travel",
            "subcategory":"Travel Agent",
            "type":"Entertainment"
        }
    ],
    "sg:phone":"+1   ",
    "sg:postcode":"17701",
    "sg:province":"PA",
    "sg:tags":[
        "operator",
        "tour"
    ],
    "wof:name":"Susquehanna Transit Co",
    "wof:placetype":"venue"
},
  "geometry": {"coordinates":[-76.999624,41.241693],"type":"Point"}
}