{
  "type": "Feature",
  "properties": {
    "iso:country":"US",
    "sg:address":"390 Lenape Rd",
    "sg:city":"Bechtelsville",
    "sg:classifiers":[
        {
            "category":"Social Services",
            "subcategory":"Child Care",
            "type":"Services"
        }
    ],
    "sg:phone":"+1 610 367 5363",
    "sg:postcode":"19505",
    "sg:province":"PA",
    "sg:tags":[
        "day"
    ],
    "wof:name":"Kauffman Family Child Care",
    "wof:placetype":"venue"
},
  "geometry": {"coordinates":[-75.632341,40.407284],"type":"Point"}
}