{
  "type": "Feature",
  "properties": {
    "addr:full":"315 Preston Ave Pittsburgh PA 15214",
    "addr:housenumber":"315",
    "addr:postcode":"15214",
    "addr:street":"Preston Ave",
    "iso:country":"US",
    "sg:address":"315 Preston Ave",
    "sg:city":"Pittsburgh",
    "sg:classifiers":[
        {
            "category":"Building & Trades",
            "subcategory":"Pest Control",
            "type":"Services"
        }
    ],
    "sg:phone":"+1 412 931 6030",
    "sg:postcode":"15214",
    "sg:province":"PA",
    "wof:name":"Swat Pest Control",
    "wof:placetype":"venue"
},
  "geometry": {"coordinates":[-80.032309,40.493862],"type":"Point"}
}