{
  "type": "Feature",
  "properties": {
    "addr:full":"104 Market St Enola PA 17025",
    "addr:housenumber":"104",
    "addr:postcode":"17025",
    "addr:street":"Market St",
    "iso:country":"US",
    "sg:address":"104 Market St",
    "sg:city":"Enola",
    "sg:classifiers":[
        {
            "category":"Restaurant",
            "type":"Food & Drink"
        }
    ],
    "sg:phone":"+1 717 728 9995",
    "sg:postcode":"17025",
    "sg:province":"PA",
    "sg:tags":[
        "traditional",
        "american"
    ],
    "wof:name":"Grotto Pub",
    "wof:placetype":"venue"
},
  "geometry": {"coordinates":[-76.916044,40.273871],"type":"Point"}
}