{
  "type": "Feature",
  "properties": {
    "iso:country":"US",
    "sg:address":"16 Gum Tree Ln",
    "sg:city":"Lafayette Hill",
    "sg:classifiers":[
        {
            "category":"Retail",
            "subcategory":"Laundry & Dry Cleaning",
            "type":"Services"
        }
    ],
    "sg:phone":"+1   ",
    "sg:postcode":"19444",
    "sg:province":"PA",
    "sg:tags":[
        "garment",
        "agent"
    ],
    "wof:name":"Camp Nock A Mixon Inc",
    "wof:placetype":"venue"
},
  "geometry": {"coordinates":[-75.278178,40.080048],"type":"Point"}
}