{
  "type": "Feature",
  "properties": {
    "iso:country":"US",
    "sg:address":"3239 Phoenixville Pike",
    "sg:city":"Malvern",
    "sg:classifiers":[
        {
            "category":"Organizations",
            "subcategory":"Non-profit Organization",
            "type":"Services"
        }
    ],
    "sg:phone":"+1 610 644 3044",
    "sg:postcode":"19355",
    "sg:province":"PA",
    "sg:tags":[
        "fund",
        "counselor",
        "raising"
    ],
    "wof:name":"Ross Galleries",
    "wof:placetype":"venue"
},
  "geometry": {"coordinates":[-75.551953,40.072991],"type":"Point"}
}