{
  "type": "Feature",
  "properties": {
    "addr:full":"1794 S Center St Exd Grove City PA 16127",
    "addr:housenumber":"1794",
    "addr:postcode":"16127",
    "addr:street":"S Center St Exd",
    "iso:country":"US",
    "sg:address":"1794 S Center St Exd",
    "sg:city":"Grove City",
    "sg:classifiers":[
        {
            "category":"Shopping",
            "subcategory":"Clothing, Apparel, & Fashions",
            "type":"Retail Goods"
        }
    ],
    "sg:phone":"+1 724 748 5748",
    "sg:postcode":"16127",
    "sg:province":"PA",
    "sg:tags":[
        "tailor"
    ],
    "wof:name":"Jean's Tailor Shop",
    "wof:placetype":"venue"
},
  "geometry": {"coordinates":[-80.148267,41.143779],"type":"Point"}
}