{
  "type": "Feature",
  "properties": {
    "addr:full":"3223 Phoenixville Pike C Malvern PA 19355",
    "addr:housenumber":"3223",
    "addr:postcode":"19355",
    "addr:street":"Phoenixville Pike",
    "iso:country":"US",
    "sg:address":"3223 Phoenixville Pike C",
    "sg:city":"Malvern",
    "sg:classifiers":[
        {
            "category":"Shopping",
            "subcategory":"Computers & Home Electronics",
            "type":"Retail Goods"
        },
        {
            "category":"Wholesale",
            "subcategory":"Computers",
            "type":"Manufacturing & Wholesale Goods"
        }
    ],
    "sg:phone":"+1 610 695 0695",
    "sg:postcode":"19355",
    "sg:province":"PA",
    "sg:tags":[
        "hardware",
        "equipment",
        "manufacturer",
        "computer-wholesale",
        "supply"
    ],
    "sg:website":"http://www.apexcompu.com",
    "wof:name":"Apexcompu Corporation",
    "wof:placetype":"venue"
},
  "geometry": {"coordinates":[-75.54587600000001,40.075553],"type":"Point"}
}