{
  "type": "Feature",
  "properties": {
    "iso:country":"US",
    "sg:address":"6105 Hegerman St",
    "sg:city":"Philadelphia",
    "sg:classifiers":[
        {
            "category":"Manufacturing",
            "subcategory":"Signs",
            "type":"Manufacturing & Wholesale Goods"
        }
    ],
    "sg:phone":"+1   ",
    "sg:postcode":"19135",
    "sg:province":"PA",
    "sg:tags":[
        "specialty",
        "mfg"
    ],
    "wof:name":"McCalls Signs and Graphics",
    "wof:placetype":"venue"
},
  "geometry": {"coordinates":[-75.05483599999999,40.018407],"type":"Point"}
}