{
  "type": "Feature",
  "properties": {
    "iso:country":"US",
    "sg:address":"192 Millbrook Rd",
    "sg:city":"Mercer",
    "sg:classifiers":[
        {
            "category":"Building & Trades",
            "subcategory":"Plumbing",
            "type":"Services"
        }
    ],
    "sg:phone":"+1 724 347 4368",
    "sg:postcode":"16137",
    "sg:province":"PA",
    "sg:tags":[
        "heating",
        "contractor"
    ],
    "wof:name":"Tropic Air",
    "wof:placetype":"venue"
},
  "geometry": {"coordinates":[-80.15416,41.24194],"type":"Point"}
}