{
  "type": "Feature",
  "properties": {
    "iso:country":"US",
    "sg:address":"21 Vernon Rd",
    "sg:city":"Havertown",
    "sg:classifiers":[
        {
            "category":"Building & Trades",
            "subcategory":"Construction",
            "type":"Services"
        }
    ],
    "sg:phone":"+1 610 449 9350",
    "sg:postcode":"19083",
    "sg:province":"PA",
    "sg:tags":[
        "fire",
        "restoration",
        "damage"
    ],
    "wof:name":"Servpro Of Woodbury Deptford",
    "wof:placetype":"venue"
},
  "geometry": {"coordinates":[-75.30126199999999,39.970434],"type":"Point"}
}