{
  "type": "Feature",
  "properties": {
    "iso:country":"US",
    "sg:address":"230 W Kensinger Dr",
    "sg:city":"Cranberry Twp",
    "sg:classifiers":[
        {
            "category":"Banks & Credit Unions",
            "subcategory":"Investment Brokerage",
            "type":"Services"
        }
    ],
    "sg:phone":"+1 724 935 9190",
    "sg:postcode":"16066",
    "sg:province":"PA",
    "sg:tags":[
        "investing"
    ],
    "wof:name":"Plastikoil of Pennsylvania",
    "wof:placetype":"venue"
},
  "geometry": {"coordinates":[-80.117465,40.710958],"type":"Point"}
}