{
  "type": "Feature",
  "properties": {
    "iso:country":"US",
    "sg:address":"7179 Chambers Hill Rd",
    "sg:city":"Harrisburg",
    "sg:classifiers":[
        {
            "category":"Mining & Drilling",
            "type":"Manufacturing & Wholesale Goods"
        }
    ],
    "sg:phone":"+1   ",
    "sg:postcode":"17111",
    "sg:province":"PA",
    "sg:tags":[
        "horizontal",
        "directional"
    ],
    "wof:name":"D L Fry Inc",
    "wof:placetype":"venue"
},
  "geometry": {"coordinates":[-76.76753600000001,40.25728],"type":"Point"}
}