{
  "type": "Feature",
  "properties": {
    "addr:full":"99 N Caln Rd Coatesville PA 19320",
    "addr:housenumber":"99",
    "addr:postcode":"19320",
    "addr:street":"N Caln Rd",
    "iso:country":"US",
    "sg:address":"99 N Caln Rd",
    "sg:city":"Coatesville",
    "sg:classifiers":[
        {
            "category":"Building & Trades",
            "subcategory":"Cleaning & Sanitation",
            "type":"Services"
        }
    ],
    "sg:phone":"+1 610 383 6587",
    "sg:postcode":"19320",
    "sg:province":"PA",
    "sg:tags":[
        "janitorial"
    ],
    "wof:name":"Keeper Clean Janitor",
    "wof:placetype":"venue"
},
  "geometry": {"coordinates":[-75.78724699999999,39.989128],"type":"Point"}
}