{
  "type": "Feature",
  "properties": {
    "addr:full":"1 Signal Hill Dr Wilmerding PA 15148",
    "addr:housenumber":"1",
    "addr:postcode":"15148",
    "addr:street":"Signal Hill Dr",
    "iso:country":"US",
    "sg:address":"1 Signal Hill Dr",
    "sg:city":"Wilmerding",
    "sg:classifiers":[
        {
            "category":"Communications",
            "subcategory":"Television Station",
            "type":"Services"
        }
    ],
    "sg:phone":"+1   ",
    "sg:postcode":"15148",
    "sg:province":"PA",
    "sg:tags":[
        "organization",
        "religious"
    ],
    "wof:name":"WPCB Channel 40",
    "wof:placetype":"venue"
},
  "geometry": {"coordinates":[-79.780642,40.392023],"type":"Point"}
}