{
  "type": "Feature",
  "properties": {
    "addr:full":"3775 Northern Pike Monroeville PA 15146",
    "addr:housenumber":"3775",
    "addr:postcode":"15146",
    "addr:street":"Northern Pike",
    "iso:country":"US",
    "sg:address":"3775 Northern Pike",
    "sg:city":"Monroeville",
    "sg:classifiers":[
        {
            "category":"Personal",
            "type":"Services"
        }
    ],
    "sg:phone":"+1 412 372 0890",
    "sg:postcode":"15146",
    "sg:province":"PA",
    "sg:tags":[
        "miscellaneous"
    ],
    "wof:name":"Posh Parties Of Distinction",
    "wof:placetype":"venue"
},
  "geometry": {"coordinates":[-79.78676299999999,40.438666],"type":"Point"}
}