{
  "type": "Feature",
  "properties": {
    "iso:country":"US",
    "sg:address":"5460 Clymer Rd",
    "sg:city":"Quakertown",
    "sg:classifiers":[
        {
            "category":"Building & Trades",
            "subcategory":"Electrical",
            "type":"Services"
        }
    ],
    "sg:phone":"+1 215 538 8108",
    "sg:postcode":"18951",
    "sg:province":"PA",
    "sg:tags":[
        "electric",
        "contractor"
    ],
    "wof:name":"Brooks Electric",
    "wof:placetype":"venue"
},
  "geometry": {"coordinates":[-75.28289700000001,40.430175],"type":"Point"}
}