{
  "type": "Feature",
  "properties": {
    "iso:country":"US",
    "sg:address":"1420 Walnut St",
    "sg:city":"Philadelphia",
    "sg:classifiers":[
        {
            "category":"Retail",
            "subcategory":"Repair Shop",
            "type":"Services"
        }
    ],
    "sg:phone":"+1 484 636 0849",
    "sg:postcode":"19102",
    "sg:province":"PA",
    "sg:tags":[
        "machine",
        "copy"
    ],
    "sg:website":"http://www.yext.com/p/superpages/fraser-advanced-information-systems-philadelphia-pennsylvania.html",
    "wof:name":"Fraser Advanced Information Systems",
    "wof:placetype":"venue"
},
  "geometry": {"coordinates":[-75.165195,39.949461],"type":"Point"}
}