{
  "type": "Feature",
  "properties": {
    "iso:country":"US",
    "sg:address":"1118 Smithbridge Rd",
    "sg:city":"Glen Mills",
    "sg:classifiers":[
        {
            "category":"Ice Cream",
            "type":"Food & Drink"
        }
    ],
    "sg:menulink":"http://www.allmenus.com/pa/concord/220760-braums-ice-cream--dairy-stores/menu/",
    "sg:phone":"+1 610 558 2311",
    "sg:postcode":"19342",
    "sg:province":"PA",
    "sg:tags":[
        "american"
    ],
    "wof:name":"Braum's Ice Cream & Dairy Stores",
    "wof:placetype":"venue"
},
  "geometry": {"coordinates":[-75.506708,39.869714],"type":"Point"}
}