{
  "type": "Feature",
  "properties": {
    "iso:country":"US",
    "sg:address":"737 Kingston St",
    "sg:city":"Philadelphia",
    "sg:classifiers":[
        {
            "category":"Building & Trades",
            "subcategory":"Construction",
            "type":"Services"
        }
    ],
    "sg:phone":"+1 215 425 5110",
    "sg:postcode":"19134",
    "sg:province":"PA",
    "sg:tags":[
        "roofing",
        "industrial",
        "contractors-commercial",
        "contractor"
    ],
    "wof:name":"Soriano Roofing",
    "wof:placetype":"venue"
},
  "geometry": {"coordinates":[-75.11547299999999,40.002505],"type":"Point"}
}