{
  "type": "Feature",
  "properties": {
    "iso:country":"US",
    "sg:address":"1029 S Center Ave",
    "sg:city":"Somerset",
    "sg:classifiers":[
        {
            "category":"Wholesale",
            "subcategory":"Scrap",
            "type":"Manufacturing & Wholesale Goods"
        }
    ],
    "sg:phone":"+1 814 443 3070",
    "sg:postcode":"15501",
    "sg:province":"PA",
    "sg:tags":[
        "recycling",
        "center"
    ],
    "wof:name":"Jms Recycling",
    "wof:placetype":"venue"
},
  "geometry": {"coordinates":[-79.080054,39.992125],"type":"Point"}
}