{
  "type": "Feature",
  "properties": {
    "iso:country":"US",
    "sg:address":"3402 Richmond St",
    "sg:city":"Philadelphia",
    "sg:classifiers":[
        {
            "category":"Professional",
            "subcategory":"Detective & Security Services",
            "type":"Services"
        }
    ],
    "sg:phone":"+1 267 973 6077",
    "sg:postcode":"19134",
    "sg:province":"PA",
    "sg:tags":[
        "information",
        "bureau"
    ],
    "wof:name":"Jc Property Services",
    "wof:placetype":"venue"
},
  "geometry": {"coordinates":[-75.096678,39.985479],"type":"Point"}
}