{
  "type": "Feature",
  "properties": {
    "iso:country":"US",
    "sg:address":"2315 Powell Ave",
    "sg:city":"Erie",
    "sg:classifiers":[
        {
            "category":"Shopping",
            "subcategory":"Discount & Variety Stores",
            "type":"Retail Goods"
        }
    ],
    "sg:phone":"+1 814 833 7713",
    "sg:postcode":"16506",
    "sg:province":"PA",
    "sg:tags":[
        "merchandise",
        "general"
    ],
    "wof:name":"O Kay Auto Sales & Equipment",
    "wof:placetype":"venue"
},
  "geometry": {"coordinates":[-80.16061999999999,42.081727],"type":"Point"}
}