{
  "type": "Feature",
  "properties": {
    "addr:full":"3700 5th Ave Pittsburgh PA 15213",
    "addr:housenumber":"3700",
    "addr:postcode":"15213",
    "addr:street":"5Th Ave",
    "iso:country":"US",
    "sg:address":"3700 5th Ave",
    "sg:city":"Pittsburgh",
    "sg:classifiers":[
        {
            "category":"Banks & Credit Unions",
            "subcategory":"Bank",
            "type":"Services"
        }
    ],
    "sg:phone":"+1 412 687 7670",
    "sg:postcode":"15213",
    "sg:province":"PA",
    "sg:tags":[
        "state",
        "commercial"
    ],
    "wof:name":"National City Bank",
    "wof:placetype":"venue"
},
  "geometry": {"coordinates":[-79.95800699999999,40.4421],"type":"Point"}
}