{
  "type": "Feature",
  "properties": {
    "addr:full":"1180 Swedesford Rd Berwyn PA 19312",
    "addr:housenumber":"1180",
    "addr:postcode":"19312",
    "addr:street":"Swedesford Rd",
    "iso:country":"US",
    "sg:address":"1180 Swedesford Rd",
    "sg:city":"Berwyn",
    "sg:classifiers":[
        {
            "category":"Health Services",
            "subcategory":"Doctor",
            "type":"Services"
        }
    ],
    "sg:phone":"+1 610 725 0829",
    "sg:postcode":"19312",
    "sg:province":"PA",
    "sg:tags":[
        "clinic"
    ],
    "wof:name":"Renal Treatment Ctr",
    "wof:placetype":"venue"
},
  "geometry": {"coordinates":[-75.464158,40.06207],"type":"Point"}
}