{
  "type": "Feature",
  "properties": {
    "iso:country":"US",
    "sg:address":"346 Arch St",
    "sg:city":"Sunbury",
    "sg:classifiers":[
        {
            "category":"Health Services",
            "subcategory":"Doctor",
            "type":"Services"
        }
    ],
    "sg:phone":"+1   ",
    "sg:postcode":"17801",
    "sg:province":"PA",
    "sg:tags":[
        "physician"
    ],
    "wof:name":"J J Delcastillo MD Inc",
    "wof:placetype":"venue"
},
  "geometry": {"coordinates":[-76.79161999999999,40.863044],"type":"Point"}
}