{
  "type": "Feature",
  "properties": {
    "addr:full":"454 Gateway Ave Chambersburg PA 17201",
    "addr:housenumber":"454",
    "addr:postcode":"17201",
    "addr:street":"Gateway Ave",
    "iso:country":"US",
    "sg:address":"454 Gateway Ave",
    "sg:city":"Chambersburg",
    "sg:classifiers":[
        {
            "category":"Fast Food",
            "type":"Food & Drink"
        },
        {
            "category":"Restaurant",
            "type":"Food & Drink"
        },
        {
            "category":"Food & Beverages",
            "subcategory":"Groceries & Convenience Stores",
            "type":"Retail Goods"
        }
    ],
    "sg:phone":"+1 717 263 5344",
    "sg:postcode":"17201",
    "sg:province":"PA",
    "sg:tags":[
        "shop",
        "american",
        "sandwich",
        "take"
    ],
    "sg:website":"http://www.quiznos.com",
    "wof:name":"Quiznos Classic Subs",
    "wof:placetype":"venue"
},
  "geometry": {"coordinates":[-77.63318599999999,39.937044],"type":"Point"}
}