{
  "type": "Feature",
  "properties": {
    "iso:country":"US",
    "sg:address":"108 Green St",
    "sg:city":"Green Lane",
    "sg:classifiers":[
        {
            "category":"Autos & Motor Vehicles",
            "subcategory":"Automobile Sales",
            "type":"Retail Goods"
        }
    ],
    "sg:phone":"+1 215 234 9111",
    "sg:postcode":"18054",
    "sg:province":"PA",
    "sg:tags":[
        "car",
        "dealer"
    ],
    "wof:name":"Green Lane Auto Mall Inc",
    "wof:placetype":"venue"
},
  "geometry": {"coordinates":[-75.46781,40.333804],"type":"Point"}
}