{
  "type": "Feature",
  "properties": {
    "iso:country":"US",
    "sg:address":"20 N Lehman St",
    "sg:city":"York",
    "sg:classifiers":[
        {
            "category":"Organizations",
            "subcategory":"Religious Organization",
            "type":"Services"
        }
    ],
    "sg:phone":"+1   ",
    "sg:postcode":"17403",
    "sg:province":"PA",
    "wof:name":"Fourth United Methodist Church",
    "wof:placetype":"venue"
},
  "geometry": {"coordinates":[-76.70607800000001,39.970839],"type":"Point"}
}