{
  "type": "Feature",
  "properties": {
    "addr:full":"431 Wimer Dr Pittsburgh PA 15237",
    "addr:housenumber":"431",
    "addr:postcode":"15237",
    "addr:street":"Wimer Dr",
    "iso:country":"US",
    "sg:address":"431 Wimer Dr",
    "sg:city":"Pittsburgh",
    "sg:classifiers":[
        {
            "category":"Insurance",
            "subcategory":"Insurance Agent",
            "type":"Services"
        }
    ],
    "sg:phone":"+1   ",
    "sg:postcode":"15237",
    "sg:province":"PA",
    "wof:name":"Rocco Catalfamo Insurance Agcy",
    "wof:placetype":"venue"
},
  "geometry": {"coordinates":[-80.00913,40.532666],"type":"Point"}
}