{
  "type": "Feature",
  "properties": {
    "iso:country":"US",
    "sg:address":"565 Pike St",
    "sg:city":"Meadow Lands",
    "sg:classifiers":[
        {
            "category":"Building & Trades",
            "subcategory":"Construction",
            "type":"Services"
        }
    ],
    "sg:phone":"+1 724 222 3855",
    "sg:postcode":"15347",
    "sg:province":"PA",
    "sg:tags":[
        "contractor"
    ],
    "wof:name":"Mingo Creek Construction Lp",
    "wof:placetype":"venue"
},
  "geometry": {"coordinates":[-80.224447,40.215176],"type":"Point"}
}