{
  "type": "Feature",
  "properties": {
    "iso:country":"US",
    "sg:address":"1629 Lincoln Way",
    "sg:city":"Mckeesport",
    "sg:classifiers":[
        {
            "category":"Insurance",
            "subcategory":"Insurance Agent",
            "type":"Services"
        }
    ],
    "sg:phone":"+1 412 678 8608",
    "sg:postcode":"15131",
    "sg:province":"PA",
    "wof:name":"Lee Agency",
    "wof:placetype":"venue"
},
  "geometry": {"coordinates":[-79.816596,40.347225],"type":"Point"}
}