{
  "type": "Feature",
  "properties": {
    "addr:full":"311 Market St Bristol PA 19007",
    "addr:housenumber":"311",
    "addr:postcode":"19007",
    "addr:street":"Market St",
    "iso:country":"US",
    "sg:address":"311 Market St",
    "sg:city":"Bristol",
    "sg:classifiers":[
        {
            "category":"Building & Trades",
            "subcategory":"Electrical",
            "type":"Services"
        }
    ],
    "sg:phone":"+1 215 785 4242",
    "sg:postcode":"19007",
    "sg:province":"PA",
    "sg:tags":[
        "electrician"
    ],
    "wof:name":"McGuire Bob Electrical Contractor",
    "wof:placetype":"venue"
},
  "geometry": {"coordinates":[-74.857803,40.096298],"type":"Point"}
}