{
  "type": "Feature",
  "properties": {
    "iso:country":"US",
    "sg:address":"964 Miller Rd",
    "sg:city":"Strasburg",
    "sg:classifiers":[
        {
            "category":"Wholesale",
            "subcategory":"Furniture",
            "type":"Manufacturing & Wholesale Goods"
        }
    ],
    "sg:phone":"+1   ",
    "sg:postcode":"17579",
    "sg:province":"PA",
    "wof:name":"Amish Furniture Peddler The",
    "wof:placetype":"venue"
},
  "geometry": {"coordinates":[-76.172873,39.943891],"type":"Point"}
}