{
  "type": "Feature",
  "properties": {
    "addr:full":"134 E Market St Blairsville PA 15717",
    "addr:housenumber":"134",
    "addr:postcode":"15717",
    "addr:street":"E Market St",
    "iso:country":"US",
    "sg:address":"134 E Market St",
    "sg:city":"Blairsville",
    "sg:classifiers":[
        {
            "category":"Social Services",
            "type":"Services"
        }
    ],
    "sg:phone":"+1   ",
    "sg:postcode":"15717",
    "sg:province":"PA",
    "sg:tags":[
        "clinic",
        "specialty",
        "outpatient"
    ],
    "wof:name":"Benchmark Medical",
    "wof:placetype":"venue"
},
  "geometry": {"coordinates":[-79.262593,40.430868],"type":"Point"}
}