{
  "type": "Feature",
  "properties": {
    "addr:full":"540 5th Ave Chambersburg PA 17201",
    "addr:housenumber":"540",
    "addr:postcode":"17201",
    "addr:street":"5Th Ave",
    "iso:country":"US",
    "sg:address":"540 5th Ave",
    "sg:city":"Chambersburg",
    "sg:classifiers":[
        {
            "category":"Utilities",
            "subcategory":"Fuel Oil & Lpg",
            "type":"Services"
        }
    ],
    "sg:phone":"+1   ",
    "sg:postcode":"17201",
    "sg:province":"PA",
    "sg:tags":[
        "wholesale",
        "retail",
        "petroleum",
        "liquefied"
    ],
    "wof:name":"Suburban Propane",
    "wof:placetype":"venue"
},
  "geometry": {"coordinates":[-77.648383,39.942718],"type":"Point"}
}