{
  "type": "Feature",
  "properties": {
    "iso:country":"US",
    "sg:address":"140 Market St",
    "sg:city":"Bloomsburg",
    "sg:classifiers":[
        {
            "category":"Health Services",
            "subcategory":"Hospital",
            "type":"Services"
        }
    ],
    "sg:phone":"+1 570 389 1249",
    "sg:postcode":"17815",
    "sg:province":"PA",
    "wof:name":"New Hp-Psychlgical Svcs Clinic",
    "wof:placetype":"venue"
},
  "geometry": {"coordinates":[-76.458504,41.003159],"type":"Point"}
}