{
  "type": "Feature",
  "properties": {
    "iso:country":"US",
    "sg:address":"891 Putnam Blvd",
    "sg:city":"Wallingford",
    "sg:classifiers":[
        {
            "category":"Real Estate",
            "subcategory":"Real Estate Operator",
            "type":"Services"
        }
    ],
    "sg:phone":"+1 610 874 7274",
    "sg:postcode":"19086",
    "sg:province":"PA",
    "sg:tags":[
        "condominium"
    ],
    "wof:name":"Danbury Village Condominium",
    "wof:placetype":"venue"
},
  "geometry": {"coordinates":[-75.379892,39.879117],"type":"Point"}
}