{
  "type": "Feature",
  "properties": {
    "iso:country":"US",
    "sg:address":"1927 Audubon Dr",
    "sg:city":"Dresher",
    "sg:classifiers":[
        {
            "category":"Professional",
            "subcategory":"Accounting & Tax Preparation",
            "type":"Services"
        }
    ],
    "sg:phone":"+1 215 646 1170",
    "sg:postcode":"19025",
    "sg:province":"PA",
    "sg:tags":[
        "accountant"
    ],
    "wof:name":"Financial Services Group",
    "wof:placetype":"venue"
},
  "geometry": {"coordinates":[-75.168435,40.13182],"type":"Point"}
}