{
  "type": "Feature",
  "properties": {
    "addr:full":"4944 N 5th St Philadelphia PA 19120",
    "addr:housenumber":"4944",
    "addr:postcode":"19120",
    "addr:street":"N 5Th St",
    "iso:country":"US",
    "sg:address":"4944 N 5th St",
    "sg:city":"Philadelphia",
    "sg:classifiers":[
        {
            "category":"Building & Trades",
            "subcategory":"Locksmith",
            "type":"Services"
        }
    ],
    "sg:phone":"+1 267 338 2840",
    "sg:postcode":"19120",
    "sg:province":"PA",
    "sg:tags":[
        "key"
    ],
    "wof:name":"All Day Available Emergency Locksmith",
    "wof:placetype":"venue"
},
  "geometry": {"coordinates":[-75.132841,40.026483],"type":"Point"}
}