{
  "type": "Feature",
  "properties": {
    "iso:country":"US",
    "sg:address":"2247 N Broad St",
    "sg:city":"Philadelphia",
    "sg:classifiers":[
        {
            "category":"Arts & Performance",
            "subcategory":"Theater",
            "type":"Entertainment"
        }
    ],
    "sg:phone":"+1 215 787 1050",
    "sg:postcode":"19132",
    "sg:province":"PA",
    "sg:tags":[
        "dance",
        "company"
    ],
    "wof:name":"Rhythm & Moves",
    "wof:placetype":"venue"
},
  "geometry": {"coordinates":[-75.15598300000001,39.987117],"type":"Point"}
}