{
  "type": "Feature",
  "properties": {
    "iso:country":"US",
    "sg:address":"3411 State Rte 309",
    "sg:city":"Orefield",
    "sg:classifiers":[
        {
            "category":"Professional",
            "subcategory":"Accounting & Tax Preparation",
            "type":"Services"
        }
    ],
    "sg:phone":"+1   ",
    "sg:postcode":"18069",
    "sg:province":"PA",
    "wof:name":"Associate Management Services",
    "wof:placetype":"venue"
},
  "geometry": {"coordinates":[-75.591745,40.64442],"type":"Point"}
}