{
  "type": "Feature",
  "properties": {
    "iso:country":"US",
    "sg:address":"1109 Long Run Rd",
    "sg:city":"Mc Keesport",
    "sg:classifiers":[
        {
            "category":"Social Services",
            "subcategory":"Child Care",
            "type":"Services"
        }
    ],
    "sg:phone":"+1   ",
    "sg:postcode":"15131",
    "sg:province":"PA",
    "sg:tags":[
        "day"
    ],
    "wof:name":"Long Run Childrens Lrng Ctr",
    "wof:placetype":"venue"
},
  "geometry": {"coordinates":[-79.816412,40.329456],"type":"Point"}
}