{
  "type": "Feature",
  "properties": {
    "addr:full":"9 Flowers Dr Mechanicsburg PA 17050",
    "addr:housenumber":"9",
    "addr:postcode":"17050",
    "addr:street":"Flowers Dr",
    "iso:country":"US",
    "sg:address":"9 Flowers Dr",
    "sg:city":"Mechanicsburg",
    "sg:classifiers":[
        {
            "category":"Health Services",
            "subcategory":"Doctor",
            "type":"Services"
        }
    ],
    "sg:phone":"+1 717 691 8750",
    "sg:postcode":"17050",
    "sg:province":"PA",
    "sg:tags":[
        "physician",
        "surgeon"
    ],
    "wof:name":"Cumberland Valley Obstetrics",
    "wof:placetype":"venue"
},
  "geometry": {"coordinates":[-77.031222,40.250542],"type":"Point"}
}