{
  "type": "Feature",
  "properties": {
    "iso:country":"US",
    "sg:address":"123 Ramcat Rd",
    "sg:city":"Confluence",
    "sg:classifiers":[
        {
            "category":"Wholesale",
            "subcategory":"Beer",
            "type":"Manufacturing & Wholesale Goods"
        }
    ],
    "sg:phone":"+1 814 395 5736",
    "sg:postcode":"15424",
    "sg:province":"PA",
    "sg:tags":[
        "ale"
    ],
    "wof:name":"Ramcat Beverage Inc",
    "wof:placetype":"venue"
},
  "geometry": {"coordinates":[-79.395849,39.815827],"type":"Point"}
}