{
  "type": "Feature",
  "properties": {
    "iso:country":"US",
    "sg:address":"8301 Henry Ave",
    "sg:city":"Philadelphia",
    "sg:classifiers":[
        {
            "category":"Banks & Credit Unions",
            "subcategory":"Bank",
            "type":"Services"
        }
    ],
    "sg:phone":"+1 215 508 7400",
    "sg:postcode":"19128",
    "sg:province":"PA",
    "sg:tags":[
        "state",
        "commercial"
    ],
    "wof:name":"Commerce Bank NA",
    "wof:placetype":"venue"
},
  "geometry": {"coordinates":[-75.237269,40.062251],"type":"Point"}
}