{
  "type": "Feature",
  "properties": {
    "iso:country":"US",
    "sg:address":"9920 Meadville St",
    "sg:city":"Cranesville",
    "sg:classifiers":[
        {
            "category":"Government",
            "subcategory":"Fire Station",
            "type":"Public Place"
        }
    ],
    "sg:phone":"+1 814 756 3441",
    "sg:postcode":"16410",
    "sg:province":"PA",
    "sg:tags":[
        "protection"
    ],
    "wof:name":"Cranesville Fire Dept",
    "wof:placetype":"venue"
},
  "geometry": {"coordinates":[-80.34372999999999,41.906087],"type":"Point"}
}