{
  "type": "Feature",
  "properties": {
    "iso:country":"US",
    "sg:address":"1021 Central Ave Exd",
    "sg:city":"Oil City",
    "sg:classifiers":[
        {
            "category":"Social Services",
            "type":"Services"
        }
    ],
    "sg:phone":"+1   ",
    "sg:postcode":"16301",
    "sg:province":"PA",
    "sg:tags":[
        "family"
    ],
    "wof:name":"Caring For The Caregiver-Jack",
    "wof:placetype":"venue"
},
  "geometry": {"coordinates":[-79.709906,41.417949],"type":"Point"}
}