{
  "type": "Feature",
  "properties": {
    "addr:full":"900 Washington St Easton PA 18042",
    "addr:housenumber":"900",
    "addr:postcode":"18042",
    "addr:street":"Washington St",
    "iso:country":"US",
    "sg:address":"900 Washington St",
    "sg:city":"Easton",
    "sg:classifiers":[
        {
            "category":"Organizations",
            "subcategory":"Religious Organization",
            "type":"Services"
        }
    ],
    "sg:phone":"+1   ",
    "sg:postcode":"18042",
    "sg:province":"PA",
    "sg:tags":[
        "catholic",
        "roman",
        "church"
    ],
    "wof:name":"Saint Anthonys Rectory",
    "wof:placetype":"venue"
},
  "geometry": {"coordinates":[-75.22211299999999,40.686806],"type":"Point"}
}