{
  "type": "Feature",
  "properties": {
    "iso:country":"US",
    "sg:address":"971 York Rd",
    "sg:city":"Dillsburg",
    "sg:classifiers":[
        {
            "category":"Health Services",
            "subcategory":"Chiropractor",
            "type":"Services"
        }
    ],
    "sg:phone":"+1 717 432 3912",
    "sg:postcode":"17019",
    "sg:province":"PA",
    "wof:name":"Gamber Family Chiropractic",
    "wof:placetype":"venue"
},
  "geometry": {"coordinates":[-77.039845,40.133199],"type":"Point"}
}