{
  "type": "Feature",
  "properties": {
    "iso:country":"US",
    "sg:address":"312 Towne Square Way",
    "sg:city":"Pittsburgh",
    "sg:classifiers":[
        {
            "category":"Personal",
            "subcategory":"Barber",
            "type":"Services"
        }
    ],
    "sg:phone":"+1 412 882 2080",
    "sg:postcode":"15227",
    "sg:province":"PA",
    "sg:website":"www.borics.com",
    "wof:name":"Borics Hair Care",
    "wof:placetype":"venue"
},
  "geometry": {"coordinates":[-79.982472,40.367697],"type":"Point"}
}