{
  "type": "Feature",
  "properties": {
    "iso:country":"US",
    "sg:address":"8749 Kirsch Rd",
    "sg:city":"Erie",
    "sg:classifiers":[
        {
            "category":"Real Estate",
            "subcategory":"Real Estate Services",
            "type":"Services"
        },
        {
            "category":"Building & Trades",
            "subcategory":"Cleaning & Sanitation",
            "type":"Services"
        }
    ],
    "sg:phone":"+1 814 824 4890",
    "sg:postcode":"16510",
    "sg:province":"PA",
    "sg:tags":[
        "maintenance",
        "cleaners-interior"
    ],
    "wof:name":"David's Maintenance",
    "wof:placetype":"venue"
},
  "geometry": {"coordinates":[-79.98164,42.080974],"type":"Point"}
}