{
  "type": "Feature",
  "properties": {
    "addr:full":"364 Pine Rd Pittsburgh PA 15237",
    "addr:housenumber":"364",
    "addr:postcode":"15237",
    "addr:street":"Pine Rd",
    "iso:country":"US",
    "sg:address":"364 Pine Rd",
    "sg:city":"Pittsburgh",
    "sg:classifiers":[
        {
            "category":"Recreation",
            "type":"Entertainment"
        }
    ],
    "sg:phone":"+1   ",
    "sg:postcode":"15237",
    "sg:province":"PA",
    "sg:tags":[
        "club",
        "membership",
        "physical",
        "fitness"
    ],
    "wof:name":"Blawnox Athletic Club",
    "wof:placetype":"venue"
},
  "geometry": {"coordinates":[-80.038572,40.580678],"type":"Point"}
}