{
  "type": "Feature",
  "properties": {
    "iso:country":"US",
    "sg:address":"3025 Pittston Ave",
    "sg:city":"Scranton",
    "sg:classifiers":[
        {
            "category":"Home & Garden",
            "subcategory":"Garden Supply",
            "type":"Retail Goods"
        }
    ],
    "sg:phone":"+1   ",
    "sg:postcode":"18505",
    "sg:province":"PA",
    "wof:name":"Georgettis Garden Center",
    "wof:placetype":"venue"
},
  "geometry": {"coordinates":[-75.692989,41.377681],"type":"Point"}
}