{
  "type": "Feature",
  "properties": {
    "iso:country":"US",
    "sg:address":"300 N Railroad St",
    "sg:city":"Myerstown",
    "sg:classifiers":[
        {
            "category":"Shopping",
            "subcategory":"Music",
            "type":"Retail Goods"
        },
        {
            "category":"Cinema",
            "subcategory":"Movie Rental",
            "type":"Entertainment"
        }
    ],
    "sg:phone":"+1 717 866 6094",
    "sg:postcode":"17067",
    "sg:province":"PA",
    "sg:tags":[
        "leasing",
        "video",
        "disc",
        "tape"
    ],
    "wof:name":"Lefty's Video",
    "wof:placetype":"venue"
},
  "geometry": {"coordinates":[-76.30699799999999,40.381643],"type":"Point"}
}