{
  "type": "Feature",
  "properties": {
    "addr:full":"1700 Markley St Norristown PA 19401",
    "addr:housenumber":"1700",
    "addr:postcode":"19401",
    "addr:street":"Markley St",
    "iso:country":"US",
    "sg:address":"1700 Markley St",
    "sg:city":"Norristown",
    "sg:classifiers":[
        {
            "category":"Government",
            "subcategory":"Office",
            "type":"Public Place"
        }
    ],
    "sg:phone":"+1   ",
    "sg:postcode":"19401",
    "sg:province":"PA",
    "sg:tags":[
        "security",
        "social"
    ],
    "wof:name":"Social Security Administration",
    "wof:placetype":"venue"
},
  "geometry": {"coordinates":[-75.33347999999999,40.132871],"type":"Point"}
}