{
  "type": "Feature",
  "properties": {
    "iso:country":"US",
    "sg:address":"601 N Baltimore Ave",
    "sg:city":"Mt Holly Springs",
    "sg:phone":"+1 717 486 3921",
    "sg:postcode":"17065",
    "sg:province":"PA",
    "sg:tags":[
        "oil"
    ],
    "wof:name":"Shipley Energy",
    "wof:placetype":"venue"
},
  "geometry": {"coordinates":[-77.190731,40.123602],"type":"Point"}
}