{
  "type": "Feature",
  "properties": {
    "addr:full":"444 S Pennsylvania Ave Morrisville PA 19067",
    "addr:housenumber":"444",
    "addr:postcode":"19067",
    "addr:street":"S Pennsylvania Ave",
    "iso:country":"US",
    "sg:address":"444 S Pennsylvania Ave",
    "sg:city":"Morrisville",
    "sg:classifiers":[
        {
            "category":"Autos & Motor Vehicles",
            "subcategory":"Automobile Sales",
            "type":"Retail Goods"
        }
    ],
    "sg:phone":"+1 215 295 7695",
    "sg:postcode":"19067",
    "sg:province":"PA",
    "sg:tags":[
        "car",
        "sales",
        "dealer"
    ],
    "wof:name":"Stus Quality Cars and Trucks",
    "wof:placetype":"venue"
},
  "geometry": {"coordinates":[-74.773197,40.203246],"type":"Point"}
}