{
  "type": "Feature",
  "properties": {
    "iso:country":"US",
    "sg:address":"363 Millett Ln",
    "sg:city":"Pittsburgh",
    "sg:classifiers":[
        {
            "category":"Professional",
            "subcategory":"Credit Reporting & Collection",
            "type":"Services"
        }
    ],
    "sg:phone":"+1 412 653 0917",
    "sg:postcode":"15236",
    "sg:province":"PA",
    "sg:tags":[
        "agency"
    ],
    "wof:name":"Recovery Inc A Community",
    "wof:placetype":"venue"
},
  "geometry": {"coordinates":[-79.96665900000001,40.324681],"type":"Point"}
}