{
  "type": "Feature",
  "properties": {
    "iso:country":"US",
    "sg:address":"119 S 3rd St",
    "sg:city":"Lemoyne",
    "sg:classifiers":[
        {
            "category":"Shopping",
            "subcategory":"Jewelry",
            "type":"Retail Goods"
        },
        {
            "category":"Personal",
            "subcategory":"Piercing",
            "type":"Services"
        }
    ],
    "sg:phone":"+1 717 737 2587",
    "sg:postcode":"17043",
    "sg:province":"PA",
    "wof:name":"Dark Side Body Jewelry",
    "wof:placetype":"venue"
},
  "geometry": {"coordinates":[-76.892371,40.244729],"type":"Point"}
}