{
  "type": "Feature",
  "properties": {
    "iso:country":"US",
    "sg:address":"2709 W Market St",
    "sg:city":"York",
    "sg:classifiers":[
        {
            "category":"Insurance",
            "subcategory":"Hazard Insurance",
            "type":"Services"
        },
        {
            "category":"Insurance",
            "subcategory":"Insurance Agent",
            "type":"Services"
        },
        {
            "category":"Insurance",
            "subcategory":"Life Insurance",
            "type":"Services"
        },
        {
            "category":"Insurance",
            "subcategory":"Title Insurance",
            "type":"Services"
        }
    ],
    "sg:phone":"+1 717 650 1053",
    "sg:postcode":"17404",
    "sg:province":"PA",
    "sg:tags":[
        "auto",
        "homeowner"
    ],
    "sg:website":"http://www.nationwide.com/agent/York-PENNSYLVANIA-insurance-agent/tweekley/office.html",
    "wof:name":"The Weekley Agency Inc - Nationwide Insurance",
    "wof:placetype":"venue"
},
  "geometry": {"coordinates":[-76.780402,39.94818],"type":"Point"}
}