{
  "type": "Feature",
  "properties": {
    "iso:country":"US",
    "sg:address":"2054 Old York Rd",
    "sg:city":"Dillsburg",
    "sg:classifiers":[
        {
            "category":"Professional",
            "type":"Services"
        }
    ],
    "sg:phone":"+1 717 432 4377",
    "sg:postcode":"17019",
    "sg:province":"PA",
    "wof:name":"Hauser Therapy Svc LTD",
    "wof:placetype":"venue"
},
  "geometry": {"coordinates":[-76.97353699999999,40.097979],"type":"Point"}
}