{
  "type": "Feature",
  "properties": {
    "iso:country":"US",
    "sg:address":"5520 Derry St",
    "sg:city":"Harrisburg",
    "sg:classifiers":[
        {
            "category":"Professional",
            "subcategory":"Computer Services",
            "type":"Services"
        }
    ],
    "sg:phone":"+1 717 920 2600",
    "sg:postcode":"17111",
    "sg:province":"PA",
    "sg:tags":[
        "repair"
    ],
    "wof:name":"Alliance Computer Solutions",
    "wof:placetype":"venue"
},
  "geometry": {"coordinates":[-76.796662,40.259235],"type":"Point"}
}