{
  "type": "Feature",
  "properties": {
    "addr:full":"536 Township Line Rd Plymouth Meeting PA 19462",
    "addr:housenumber":"536",
    "addr:postcode":"19462",
    "addr:street":"Township Line Rd",
    "iso:country":"US",
    "sg:address":"536 Township Line Rd",
    "sg:city":"Plymouth Meeting",
    "sg:classifiers":[
        {
            "category":"Wholesale",
            "subcategory":"Machinery & Supplies",
            "type":"Manufacturing & Wholesale Goods"
        }
    ],
    "sg:phone":"+1 610 643 0966",
    "sg:postcode":"19462",
    "sg:province":"PA",
    "sg:tags":[
        "heat",
        "exchanger"
    ],
    "wof:name":"Allied Fluid Conditioners",
    "wof:placetype":"venue"
},
  "geometry": {"coordinates":[-75.27024299999999,40.127452],"type":"Point"}
}