{
  "type": "Feature",
  "properties": {
    "iso:country":"US",
    "sg:address":"2 Center St",
    "sg:city":"Oil City",
    "sg:classifiers":[
        {
            "category":"Education",
            "subcategory":"School",
            "type":"Public Place"
        }
    ],
    "sg:phone":"+1   ",
    "sg:postcode":"16301",
    "sg:province":"PA",
    "sg:tags":[
        "kindergarten"
    ],
    "wof:name":"Twin Creek Head Start",
    "wof:placetype":"venue"
},
  "geometry": {"coordinates":[-79.708491,41.434084],"type":"Point"}
}