{
  "type": "Feature",
  "properties": {
    "addr:full":"8933 Rowe Run Rd Shippensburg PA 17257",
    "addr:housenumber":"8933",
    "addr:postcode":"17257",
    "addr:street":"Rowe Run Rd",
    "iso:country":"US",
    "sg:address":"8933 Rowe Run Rd",
    "sg:city":"Shippensburg",
    "sg:classifiers":[
        {
            "category":"Manufacturing",
            "subcategory":"Furniture",
            "type":"Manufacturing & Wholesale Goods"
        }
    ],
    "sg:phone":"+1 717 530 8823",
    "sg:postcode":"17257",
    "sg:province":"PA",
    "wof:name":"Newburg Woodcrafts",
    "wof:placetype":"venue"
},
  "geometry": {"coordinates":[-77.592404,40.036106],"type":"Point"}
}