{
  "type": "Feature",
  "properties": {
    "iso:country":"US",
    "sg:address":"312 Broad St",
    "sg:city":"Sewickley",
    "sg:classifiers":[
        {
            "category":"Manufacturing",
            "subcategory":"Printing",
            "type":"Manufacturing & Wholesale Goods"
        }
    ],
    "sg:phone":"+1   ",
    "sg:postcode":"15143",
    "sg:province":"PA",
    "sg:tags":[
        "commercial"
    ],
    "wof:name":"Visual Impact Business Cards",
    "wof:placetype":"venue"
},
  "geometry": {"coordinates":[-80.18205399999999,40.538654],"type":"Point"}
}