{
  "type": "Feature",
  "properties": {
    "iso:country":"US",
    "sg:address":"2224 Bedford St",
    "sg:city":"Johnstown",
    "sg:classifiers":[
        {
            "category":"Autos & Motor Vehicles",
            "subcategory":"Automobile Sales",
            "type":"Retail Goods"
        },
        {
            "category":"Retail",
            "subcategory":"Auto Rental",
            "type":"Services"
        },
        {
            "category":"Retail",
            "subcategory":"Storage",
            "type":"Services"
        }
    ],
    "sg:phone":"+1 814 266 3128",
    "sg:postcode":"15904",
    "sg:province":"PA",
    "sg:tags":[
        "renting",
        "moving-self",
        "used",
        "leasing",
        "car",
        "dealers-used",
        "truck",
        "cars-wholesale",
        "trailer"
    ],
    "sg:website":"http://www.uhaul.com/Locations/Rentals-near-Johnstown-PA-15904/052238",
    "wof:name":"U-Haul Neighborhood Dealer - The Autobahn Auto Sls & Svc",
    "wof:placetype":"venue"
},
  "geometry": {"coordinates":[-78.87701,40.2971],"type":"Point"}
}