{
  "type": "Feature",
  "properties": {
    "addr:full":"14 E 3rd Ave Everett PA 15537",
    "addr:housenumber":"14",
    "addr:postcode":"15537",
    "addr:street":"E 3Rd Ave",
    "iso:country":"US",
    "sg:address":"14 E 3rd Ave",
    "sg:city":"Everett",
    "sg:classifiers":[
        {
            "category":"Health Services",
            "subcategory":"Doctor",
            "type":"Services"
        }
    ],
    "sg:phone":"+1 814 652 2141",
    "sg:postcode":"15537",
    "sg:province":"PA",
    "sg:tags":[
        "physician",
        "surgeon"
    ],
    "wof:name":"Jeffrey L Foor Pediatrics",
    "wof:placetype":"venue"
},
  "geometry": {"coordinates":[-78.368773,40.007121],"type":"Point"}
}