{
  "type": "Feature",
  "properties": {
    "iso:country":"US",
    "sg:address":"621 Cumberland St",
    "sg:city":"Lebanon",
    "sg:classifiers":[
        {
            "category":"Professional",
            "subcategory":"Employment Agencies",
            "type":"Services"
        }
    ],
    "sg:phone":"+1   ",
    "sg:postcode":"17042",
    "sg:province":"PA",
    "sg:tags":[
        "help",
        "supply"
    ],
    "wof:name":"Dept Co",
    "wof:placetype":"venue"
},
  "geometry": {"coordinates":[-76.42139299999999,40.339624],"type":"Point"}
}