{
  "type": "Feature",
  "properties": {
    "iso:country":"US",
    "sg:address":"2970 Old Tree Dr",
    "sg:city":"Lancaster",
    "sg:classifiers":[
        {
            "category":"Manufacturing",
            "subcategory":"Tools & Machinery",
            "type":"Manufacturing & Wholesale Goods"
        }
    ],
    "sg:phone":"+1 717 397 2542",
    "sg:postcode":"17603",
    "sg:province":"PA",
    "sg:tags":[
        "die",
        "maker",
        "special",
        "mfg"
    ],
    "wof:name":"Custom Tool and Die Inc",
    "wof:placetype":"venue"
},
  "geometry": {"coordinates":[-76.391006,40.049676],"type":"Point"}
}