{
  "type": "Feature",
  "properties": {
    "iso:country":"US",
    "sg:address":"242 Main St",
    "sg:city":"Luzerne",
    "sg:classifiers":[
        {
            "category":"Shopping",
            "subcategory":"Used Merchandise",
            "type":"Retail Goods"
        }
    ],
    "sg:phone":"+1   ",
    "sg:postcode":"18709",
    "sg:province":"PA",
    "wof:name":"Collectors Corner",
    "wof:placetype":"venue"
},
  "geometry": {"coordinates":[-75.89987499999999,41.28467],"type":"Point"}
}