{
  "type": "Feature",
  "properties": {
    "addr:full":"50 Foote Ave Duryea PA 18642",
    "addr:housenumber":"50",
    "addr:postcode":"18642",
    "addr:street":"Foote Ave",
    "iso:country":"US",
    "sg:address":"50 Foote Ave",
    "sg:city":"Duryea",
    "sg:classifiers":[
        {
            "category":"Place Of Worship",
            "subcategory":"Church",
            "type":"Public Place"
        },
        {
            "category":"Place Of Worship",
            "type":"Public Place"
        }
    ],
    "sg:phone":"+1 570 655 6255",
    "sg:postcode":"18642",
    "sg:province":"PA",
    "sg:tags":[
        "churches-jehovah's",
        "witness"
    ],
    "sg:website":"http://www.watchtower.org",
    "wof:name":"Jehovah's Witnesses",
    "wof:placetype":"venue"
},
  "geometry": {"coordinates":[-75.766863,41.336235],"type":"Point"}
}