{
  "type": "Feature",
  "properties": {
    "addr:full":"930 Forrester Ave Darby PA 19023",
    "addr:housenumber":"930",
    "addr:postcode":"19023",
    "addr:street":"Forrester Ave",
    "iso:country":"US",
    "sg:address":"930 Forrester Ave",
    "sg:city":"Darby",
    "sg:classifiers":[
        {
            "category":"Shopping",
            "subcategory":"Catalog Store",
            "type":"Retail Goods"
        }
    ],
    "sg:phone":"+1 610 532 8273",
    "sg:postcode":"19023",
    "sg:province":"PA",
    "sg:tags":[
        "mail",
        "merchandise",
        "house"
    ],
    "wof:name":"Westwood Int'l",
    "wof:placetype":"venue"
},
  "geometry": {"coordinates":[-75.26011099999999,39.920688],"type":"Point"}
}