{
  "type": "Feature",
  "properties": {
    "addr:full":"857 Baltimore Pike Springfield PA 19064",
    "addr:housenumber":"857",
    "addr:postcode":"19064",
    "addr:street":"Baltimore Pike Springfield",
    "iso:country":"US",
    "sg:address":"857 Baltimore Pike",
    "sg:city":"Springfield",
    "sg:classifiers":[
        {
            "category":"Shopping",
            "subcategory":"Pharmacy",
            "type":"Retail Goods"
        }
    ],
    "sg:phone":"+1 610 338 0530",
    "sg:postcode":"19064",
    "sg:province":"PA",
    "sg:tags":[
        "department",
        "store"
    ],
    "wof:name":"Target",
    "wof:placetype":"venue"
},
  "geometry": {"coordinates":[-75.338201,39.915318],"type":"Point"}
}