{
  "type": "Feature",
  "properties": {
    "iso:country":"US",
    "sg:address":"301 N Broad St",
    "sg:city":"Lititz",
    "sg:classifiers":[
        {
            "category":"Shopping",
            "subcategory":"Clothing, Apparel, & Fashions",
            "type":"Retail Goods"
        }
    ],
    "sg:phone":"+1 717 626 5299",
    "sg:postcode":"17543",
    "sg:province":"PA",
    "sg:tags":[
        "operation",
        "lodging"
    ],
    "sg:website":"http://www.lititzhouse.com",
    "wof:name":"Lititz House Bed and Breakfast",
    "wof:placetype":"venue"
},
  "geometry": {"coordinates":[-76.3078,40.1614],"type":"Point"}
}