{
  "type": "Feature",
  "properties": {
    "iso:country":"US",
    "sg:address":"1049 N Sekol Ave",
    "sg:city":"Scranton",
    "sg:classifiers":[
        {
            "category":"Communications",
            "subcategory":"Radio Station",
            "type":"Services"
        }
    ],
    "sg:phone":"+1 570 344 1221",
    "sg:postcode":"18504",
    "sg:province":"PA",
    "sg:tags":[
        "company",
        "broadcasting"
    ],
    "sg:website":"www.dl.com",
    "wof:name":"WICK",
    "wof:placetype":"venue"
},
  "geometry": {"coordinates":[-75.71794800000001,41.440218],"type":"Point"}
}