{
  "type": "Feature",
  "properties": {
    "addr:full":"1051 E Main St Waynesboro PA 17268",
    "addr:housenumber":"1051",
    "addr:postcode":"17268",
    "addr:street":"E Main St",
    "iso:country":"US",
    "sg:address":"1051 E Main St",
    "sg:city":"Waynesboro",
    "sg:classifiers":[
        {
            "category":"Shopping",
            "subcategory":"Pharmacy",
            "type":"Retail Goods"
        }
    ],
    "sg:phone":"+1   ",
    "sg:postcode":"17268",
    "sg:province":"PA",
    "wof:name":"Smiths Drugs",
    "wof:placetype":"venue"
},
  "geometry": {"coordinates":[-77.570059,39.751726],"type":"Point"}
}