{
  "type": "Feature",
  "properties": {
    "addr:full":"500 Garbrick Rd Bellefonte PA 16823",
    "addr:housenumber":"500",
    "addr:postcode":"16823",
    "addr:street":"Garbrick Rd",
    "iso:country":"US",
    "sg:address":"500 Garbrick Rd",
    "sg:city":"Bellefonte",
    "sg:classifiers":[
        {
            "category":"Building & Trades",
            "subcategory":"Landscaping Services",
            "type":"Services"
        }
    ],
    "sg:phone":"+1 814 353 8363",
    "sg:postcode":"16823",
    "sg:province":"PA",
    "sg:tags":[
        "landscape"
    ],
    "wof:name":"Drew Smith Custom Work",
    "wof:placetype":"venue"
},
  "geometry": {"coordinates":[-77.71985599999999,40.904157],"type":"Point"}
}