{
  "type": "Feature",
  "properties": {
    "iso:country":"US",
    "sg:address":"3849 Union Deposit Rd",
    "sg:city":"Harrisburg",
    "sg:classifiers":[
        {
            "category":"Real Estate",
            "subcategory":"Real Estate Agent",
            "type":"Services"
        }
    ],
    "sg:phone":"+1 717 564 4500",
    "sg:postcode":"17109",
    "sg:province":"PA",
    "sg:tags":[
        "agency",
        "rental"
    ],
    "wof:name":"MAJIK Rent To Own",
    "wof:placetype":"venue"
},
  "geometry": {"coordinates":[-76.825554,40.27825],"type":"Point"}
}