{
  "type": "Feature",
  "properties": {
    "iso:country":"US",
    "sg:address":"3239 Kensington Ave",
    "sg:city":"Philadelphia",
    "sg:classifiers":[
        {
            "category":"Bars & Pubs",
            "type":"Food & Drink"
        }
    ],
    "sg:phone":"+1 215 426 5169",
    "sg:postcode":"19134",
    "sg:province":"PA",
    "sg:tags":[
        "drinking"
    ],
    "wof:name":"New Hot Spot",
    "wof:placetype":"venue"
},
  "geometry": {"coordinates":[-75.11271000000001,39.996859],"type":"Point"}
}