{
  "type": "Feature",
  "properties": {
    "iso:country":"US",
    "sg:address":"5047 Jonestown Rd",
    "sg:city":"Harrisburg",
    "sg:classifiers":[
        {
            "category":"Shopping",
            "subcategory":"Music",
            "type":"Retail Goods"
        }
    ],
    "sg:phone":"+1 717 652 4200",
    "sg:postcode":"17112",
    "sg:province":"PA",
    "sg:tags":[
        "compact",
        "record",
        "disc",
        "tape"
    ],
    "wof:name":"Media Play",
    "wof:placetype":"venue"
},
  "geometry": {"coordinates":[-76.80459399999999,40.307412],"type":"Point"}
}