{
  "type": "Feature",
  "properties": {
    "addr:full":"4411 Whitaker Ave Philadelphia PA 19120",
    "addr:housenumber":"4411",
    "addr:postcode":"19120",
    "addr:street":"Whitaker Ave",
    "iso:country":"US",
    "sg:address":"4411 Whitaker Ave",
    "sg:city":"Philadelphia",
    "sg:classifiers":[
        {
            "category":"Professional",
            "type":"Services"
        }
    ],
    "sg:phone":"+1 215 669 8144",
    "sg:postcode":"19120",
    "sg:province":"PA",
    "sg:tags":[
        "establishment"
    ],
    "wof:name":"Speiser & Leventhal Inc",
    "wof:placetype":"venue"
},
  "geometry": {"coordinates":[-75.116654,40.016748],"type":"Point"}
}