{
  "type": "Feature",
  "properties": {
    "iso:country":"US",
    "sg:address":"100 W Front St",
    "sg:city":"Berwick",
    "sg:classifiers":[
        {
            "category":"Shopping",
            "subcategory":"Department Store",
            "type":"Retail Goods"
        }
    ],
    "sg:phone":"+1 570 752 1386",
    "sg:postcode":"18603",
    "sg:province":"PA",
    "sg:tags":[
        "variety"
    ],
    "wof:name":"Geppetto's",
    "wof:placetype":"venue"
},
  "geometry": {"coordinates":[-76.233597,41.054779],"type":"Point"}
}