{
  "type": "Feature",
  "properties": {
    "iso:country":"US",
    "sg:address":"1851 E Allegheny Ave",
    "sg:city":"Philadelphia",
    "sg:classifiers":[
        {
            "category":"Social Services",
            "type":"Services"
        }
    ],
    "sg:phone":"+1   ",
    "sg:postcode":"19134",
    "sg:province":"PA",
    "wof:name":"Hispanic Comm Couseling S",
    "wof:placetype":"venue"
},
  "geometry": {"coordinates":[-75.11261,39.995889],"type":"Point"}
}