{
  "type": "Feature",
  "properties": {
    "addr:full":"303 E Maple St Coudersport PA 16915",
    "addr:housenumber":"303",
    "addr:postcode":"16915",
    "addr:street":"E Maple St",
    "iso:country":"US",
    "sg:address":"303 E Maple St",
    "sg:city":"Coudersport",
    "sg:classifiers":[
        {
            "category":"Health Services",
            "subcategory":"Doctor",
            "type":"Services"
        },
        {
            "category":"Health Services",
            "subcategory":"Dentist",
            "type":"Services"
        }
    ],
    "sg:phone":"+1 814 274 8838",
    "sg:postcode":"16915",
    "sg:province":"PA",
    "sg:tags":[
        "dentists-oral",
        "physician",
        "maxillofacial",
        "surgeons",
        "surgery",
        "oral"
    ],
    "wof:name":"Cornish Lynn M D",
    "wof:placetype":"venue"
},
  "geometry": {"coordinates":[-78.017313,41.770361],"type":"Point"}
}