{
  "type": "Feature",
  "properties": {
    "addr:full":"400 Long Ln Lancaster PA 17603",
    "addr:housenumber":"400",
    "addr:postcode":"17603",
    "addr:street":"Long Ln",
    "iso:country":"US",
    "sg:address":"400 Long Ln",
    "sg:city":"Lancaster",
    "sg:classifiers":[
        {
            "category":"Food & Beverages",
            "subcategory":"Fruits & Vegetables",
            "type":"Retail Goods"
        }
    ],
    "sg:phone":"+1 717 872 9311",
    "sg:postcode":"17603",
    "sg:province":"PA",
    "sg:tags":[
        "produce"
    ],
    "wof:name":"Cherry Hill Orchards-Outlet",
    "wof:placetype":"venue"
},
  "geometry": {"coordinates":[-76.311116,39.979991],"type":"Point"}
}