{
  "type": "Feature",
  "properties": {
    "iso:country":"US",
    "sg:address":"700 5th Ave",
    "sg:city":"Pittsburgh",
    "sg:classifiers":[
        {
            "category":"Wholesale",
            "subcategory":"Machinery & Supplies",
            "type":"Manufacturing & Wholesale Goods"
        }
    ],
    "sg:phone":"+1 412 325 1565",
    "sg:postcode":"15219",
    "sg:province":"PA",
    "sg:tags":[
        "equipment",
        "industrial"
    ],
    "wof:name":"World-Class Industrial Network",
    "wof:placetype":"venue"
},
  "geometry": {"coordinates":[-79.992727,40.438881],"type":"Point"}
}