{
  "type": "Feature",
  "properties": {
    "iso:country":"US",
    "sg:address":"4674 Tulane Ave",
    "sg:city":"Erie",
    "sg:classifiers":[
        {
            "category":"Professional",
            "subcategory":"Detective & Security Services",
            "type":"Services"
        }
    ],
    "sg:phone":"+1 814 836 9882",
    "sg:postcode":"16506",
    "sg:province":"PA",
    "sg:tags":[
        "guard",
        "patrol"
    ],
    "wof:name":"Ameritech Security Link",
    "wof:placetype":"venue"
},
  "geometry": {"coordinates":[-80.177824,42.066486],"type":"Point"}
}