{
  "type": "Feature",
  "properties": {
    "addr:full":"411 Bank St Nazareth PA 18064",
    "addr:housenumber":"411",
    "addr:postcode":"18064",
    "addr:street":"Bank St",
    "iso:country":"US",
    "sg:address":"411 Bank St",
    "sg:city":"Nazareth",
    "sg:classifiers":[
        {
            "category":"Personal",
            "subcategory":"Beauty Salon",
            "type":"Services"
        }
    ],
    "sg:phone":"+1 610 759 4652",
    "sg:postcode":"18064",
    "sg:province":"PA",
    "wof:name":"Barbara Bok's Beauty Salon",
    "wof:placetype":"venue"
},
  "geometry": {"coordinates":[-75.302571,40.739696],"type":"Point"}
}