{
  "type": "Feature",
  "properties": {
    "iso:country":"US",
    "sg:address":"1452 N Wales Rd",
    "sg:city":"North Wales",
    "sg:classifiers":[
        {
            "category":"Education",
            "subcategory":"Vocational School",
            "type":"Public Place"
        }
    ],
    "sg:phone":"+1 215 628 4011",
    "sg:postcode":"19454",
    "sg:province":"PA",
    "sg:tags":[
        "training",
        "computer"
    ],
    "wof:name":"Computer & Office Training",
    "wof:placetype":"venue"
},
  "geometry": {"coordinates":[-75.266766,40.224153],"type":"Point"}
}