{
  "type": "Feature",
  "properties": {
    "iso:country":"US",
    "sg:address":"824 W Cedarville Rd",
    "sg:city":"Pottstown",
    "sg:classifiers":[
        {
            "category":"Building & Trades",
            "subcategory":"Construction",
            "type":"Services"
        }
    ],
    "sg:phone":"+1 610 323 1094",
    "sg:postcode":"19465",
    "sg:province":"PA",
    "sg:tags":[
        "house",
        "construct",
        "contractor"
    ],
    "wof:name":"Mike Moser",
    "wof:placetype":"venue"
},
  "geometry": {"coordinates":[-75.669031,40.228576],"type":"Point"}
}