{
  "type": "Feature",
  "properties": {
    "iso:country":"US",
    "sg:address":"3 Hallmark Dr",
    "sg:city":"Pittsburgh",
    "sg:classifiers":[
        {
            "category":"Building & Trades",
            "subcategory":"Landscaping Services",
            "type":"Services"
        }
    ],
    "sg:phone":"+1   ",
    "sg:postcode":"15235",
    "sg:province":"PA",
    "sg:tags":[
        "landscape"
    ],
    "wof:name":"Barbieri Landscaping",
    "wof:placetype":"venue"
},
  "geometry": {"coordinates":[-79.795759,40.481349],"type":"Point"}
}