{
  "type": "Feature",
  "properties": {
    "iso:country":"US",
    "sg:address":"43 W Broad St",
    "sg:city":"Tamaqua",
    "sg:classifiers":[
        {
            "category":"Personal",
            "subcategory":"Beauty Salon",
            "type":"Services"
        }
    ],
    "sg:phone":"+1 570 668 6990",
    "sg:postcode":"18252",
    "sg:province":"PA",
    "sg:tags":[
        "shop"
    ],
    "wof:name":"Heavenly Hair Designs",
    "wof:placetype":"venue"
},
  "geometry": {"coordinates":[-75.9705,40.797135],"type":"Point"}
}