{
  "type": "Feature",
  "properties": {
    "addr:full":"4200 Dermond Rd Drexel Hill PA 19026",
    "addr:housenumber":"4200",
    "addr:postcode":"19026",
    "addr:street":"Dermond Rd",
    "iso:country":"US",
    "sg:address":"4200 Dermond Rd",
    "sg:city":"Drexel Hill",
    "sg:classifiers":[
        {
            "category":"Professional",
            "subcategory":"Engineering",
            "type":"Services"
        }
    ],
    "sg:phone":"+1   ",
    "sg:postcode":"19026",
    "sg:province":"PA",
    "wof:name":"Energy Res Group Inc",
    "wof:placetype":"venue"
},
  "geometry": {"coordinates":[-75.31287399999999,39.95795],"type":"Point"}
}