{
  "type": "Feature",
  "properties": {
    "addr:full":"1930 E Carson St Pittsburgh PA 15203",
    "addr:housenumber":"1930",
    "addr:postcode":"15203",
    "addr:street":"E Carson St",
    "iso:country":"US",
    "sg:address":"1930 E Carson St",
    "sg:city":"Pittsburgh",
    "sg:classifiers":[
        {
            "category":"Shopping",
            "type":"Retail Goods"
        }
    ],
    "sg:phone":"+1 412 432 1945",
    "sg:postcode":"15203",
    "sg:province":"PA",
    "sg:tags":[
        "material",
        "artist",
        "supply"
    ],
    "wof:name":"Utrecht Art Supplies",
    "wof:placetype":"venue"
},
  "geometry": {"coordinates":[-79.978061,40.428537],"type":"Point"}
}