{
  "type": "Feature",
  "properties": {
    "iso:country":"US",
    "sg:address":"700 Spruce St",
    "sg:city":"Philadelphia",
    "sg:classifiers":[
        {
            "category":"Health Services",
            "subcategory":"Doctor",
            "type":"Services"
        }
    ],
    "sg:phone":"+1 215 829 3001",
    "sg:postcode":"19106",
    "sg:province":"PA",
    "sg:tags":[
        "medicine",
        "internal"
    ],
    "wof:name":"Weber Valerie MD",
    "wof:placetype":"venue"
},
  "geometry": {"coordinates":[-75.153198,39.945599],"type":"Point"}
}