{
  "type": "Feature",
  "properties": {
    "addr:full":"309 Davis Ave Millvale PA 15223",
    "addr:housenumber":"309",
    "addr:postcode":"15223",
    "addr:street":"Davis Ave",
    "iso:country":"US",
    "sg:address":"309 Davis Ave",
    "sg:city":"Millvale",
    "sg:classifiers":[
        {
            "category":"Government",
            "subcategory":"Fire Station",
            "type":"Public Place"
        }
    ],
    "sg:phone":"+1 412 822 7000",
    "sg:postcode":"15223",
    "sg:province":"PA",
    "sg:tags":[
        "department",
        "company"
    ],
    "wof:name":"Cherry City Volunteer Fire Co",
    "wof:placetype":"venue"
},
  "geometry": {"coordinates":[-79.95925699999999,40.494827],"type":"Point"}
}