{
  "type": "Feature",
  "properties": {
    "addr:full":"6384 Lincoln Hwy Wrightsville PA 17406",
    "addr:housenumber":"6384",
    "addr:postcode":"17406",
    "addr:street":"Lincoln Hwy",
    "iso:country":"US",
    "sg:address":"6384 Lincoln Hwy",
    "sg:city":"Wrightsville",
    "sg:classifiers":[
        {
            "category":"Autos & Motor Vehicles",
            "subcategory":"Automobile Sales",
            "type":"Retail Goods"
        }
    ],
    "sg:phone":"+1 717 252 4700",
    "sg:postcode":"17406",
    "sg:province":"PA",
    "sg:tags":[
        "car",
        "dealer"
    ],
    "wof:name":"European Car Buyers",
    "wof:placetype":"venue"
},
  "geometry": {"coordinates":[-76.550078,40.021269],"type":"Point"}
}