{
  "type": "Feature",
  "properties": {
    "iso:country":"US",
    "sg:address":"10 W Chocolate Ave",
    "sg:city":"Hershey",
    "sg:classifiers":[
        {
            "category":"Banks & Credit Unions",
            "subcategory":"Bank",
            "type":"Services"
        }
    ],
    "sg:phone":"+1 717 533 9980",
    "sg:postcode":"17033",
    "sg:province":"PA",
    "sg:website":"www.northwestsavingsbank.com",
    "wof:name":"Northwest Savings Bank",
    "wof:placetype":"venue"
},
  "geometry": {"coordinates":[-76.6502,40.285702],"type":"Point"}
}