{
  "type": "Feature",
  "properties": {
    "addr:full":"200 Mall Blvd Monroeville PA 15146",
    "addr:housenumber":"200",
    "addr:postcode":"15146",
    "addr:street":"Mall Blvd",
    "iso:country":"US",
    "sg:address":"200 Mall Blvd",
    "sg:city":"Monroeville",
    "sg:classifiers":[
        {
            "category":"Social Services",
            "type":"Services"
        }
    ],
    "sg:phone":"+1 412 856 2251",
    "sg:postcode":"15146",
    "sg:province":"PA",
    "sg:tags":[
        "program",
        "services-information",
        "referral"
    ],
    "wof:name":"Senior Information Station",
    "wof:placetype":"venue"
},
  "geometry": {"coordinates":[-79.789742,40.43294],"type":"Point"}
}