{
  "type": "Feature",
  "properties": {
    "iso:country":"US",
    "sg:address":"108 W Beaver Ave",
    "sg:city":"State College",
    "sg:classifiers":[
        {
            "category":"Arts & Performance",
            "subcategory":"Theater",
            "type":"Entertainment"
        }
    ],
    "sg:phone":"+1 814 867 4288",
    "sg:postcode":"16801",
    "sg:province":"PA",
    "sg:tags":[
        "musician"
    ],
    "wof:name":"Barry Kemfeld",
    "wof:placetype":"venue"
},
  "geometry": {"coordinates":[-77.86074499999999,40.792997],"type":"Point"}
}