{
  "type": "Feature",
  "properties": {
    "addr:full":"820 Bingaman St Reading PA 19602",
    "addr:housenumber":"820",
    "addr:postcode":"19602",
    "addr:street":"Bingaman St",
    "iso:country":"US",
    "sg:address":"820 Bingaman St",
    "sg:city":"Reading",
    "sg:classifiers":[
        {
            "category":"Organizations",
            "subcategory":"Professional Association",
            "type":"Services"
        },
        {
            "category":"Organizations",
            "subcategory":"Community Association",
            "type":"Services"
        }
    ],
    "sg:phone":"+1 610 378 5767",
    "sg:postcode":"19602",
    "sg:province":"PA",
    "wof:name":"Polish Falcons Assn",
    "wof:placetype":"venue"
},
  "geometry": {"coordinates":[-75.921623,40.330984],"type":"Point"}
}