{
  "type": "Feature",
  "properties": {
    "addr:full":"848 Science Park Rd State College PA 16803",
    "addr:housenumber":"848",
    "addr:postcode":"16803",
    "addr:street":"Science Park Rd",
    "iso:country":"US",
    "sg:address":"848 Science Park Rd",
    "sg:city":"State College",
    "sg:classifiers":[
        {
            "category":"Organizations",
            "subcategory":"Religious Organization",
            "type":"Services"
        }
    ],
    "sg:phone":"+1 814 237 4076",
    "sg:postcode":"16803",
    "sg:province":"PA",
    "sg:website":"www.stcollegefreemethodist.org",
    "wof:name":"Free Methodist Church",
    "wof:placetype":"venue"
},
  "geometry": {"coordinates":[-77.905873,40.788431],"type":"Point"}
}