{
  "type": "Feature",
  "properties": {
    "addr:full":"113 Willow Crossing Rd Greensburg PA 15601",
    "addr:housenumber":"113",
    "addr:postcode":"15601",
    "addr:street":"Willow Crossing Rd",
    "iso:country":"US",
    "sg:address":"113 Willow Crossing Rd",
    "sg:city":"Greensburg",
    "sg:classifiers":[
        {
            "category":"Retail",
            "subcategory":"Photofinishing",
            "type":"Services"
        }
    ],
    "sg:phone":"+1   ",
    "sg:postcode":"15601",
    "sg:province":"PA",
    "sg:tags":[
        "laboratory"
    ],
    "wof:name":"Color Lab",
    "wof:placetype":"venue"
},
  "geometry": {"coordinates":[-79.571831,40.281401],"type":"Point"}
}