{
  "type": "Feature",
  "properties": {
    "addr:full":"345 Freeport Rd Aspinwall PA 15215",
    "addr:housenumber":"345",
    "addr:postcode":"15215",
    "addr:street":"Freeport Rd",
    "iso:country":"US",
    "sg:address":"345 Freeport Rd",
    "sg:city":"Aspinwall",
    "sg:classifiers":[
        {
            "category":"Education",
            "subcategory":"Special Training",
            "type":"Public Place"
        }
    ],
    "sg:phone":"+1 412 781 5050",
    "sg:postcode":"15215",
    "sg:province":"PA",
    "sg:tags":[
        "instruction",
        "music"
    ],
    "wof:name":"Santucci Music Studios",
    "wof:placetype":"venue"
},
  "geometry": {"coordinates":[-79.90140599999999,40.489006],"type":"Point"}
}