{
  "type": "Feature",
  "properties": {
    "iso:country":"US",
    "sg:address":"625 Church St",
    "sg:city":"Indiana",
    "sg:classifiers":[
        {
            "category":"Real Estate",
            "subcategory":"Surveying",
            "type":"Services"
        }
    ],
    "sg:phone":"+1 724 349 6910",
    "sg:postcode":"15701",
    "sg:province":"PA",
    "sg:tags":[
        "surveyor"
    ],
    "wof:name":"Bernard D Houllion Pro Srvyr",
    "wof:placetype":"venue"
},
  "geometry": {"coordinates":[-79.151667,40.621647],"type":"Point"}
}