{
  "type": "Feature",
  "properties": {
    "iso:country":"US",
    "sg:address":"1010 W Chester Rd",
    "sg:city":"West Chester",
    "sg:classifiers":[
        {
            "category":"Autos & Motor Vehicles",
            "subcategory":"Automobile Sales",
            "type":"Retail Goods"
        }
    ],
    "sg:phone":"+1 610 692 5500",
    "sg:postcode":"19382",
    "sg:province":"PA",
    "sg:tags":[
        "car",
        "dealer"
    ],
    "sg:website":"www.jamesauto.com",
    "wof:name":"James Chevrolet Inc",
    "wof:placetype":"venue"
},
  "geometry": {"coordinates":[-75.54619,39.910953],"type":"Point"}
}