{
  "type": "Feature",
  "properties": {
    "addr:full":"625 South Ave Bradford PA 16701",
    "addr:housenumber":"625",
    "addr:postcode":"16701",
    "addr:street":"South Ave",
    "iso:country":"US",
    "sg:address":"625 South Ave",
    "sg:city":"Bradford",
    "sg:classifiers":[
        {
            "category":"Organizations",
            "subcategory":"Professional Association",
            "type":"Services"
        }
    ],
    "sg:phone":"+1 814 368 5212",
    "sg:postcode":"16701",
    "sg:province":"PA",
    "wof:name":"Masonic Lodge",
    "wof:placetype":"venue"
},
  "geometry": {"coordinates":[-78.652123,41.925981],"type":"Point"}
}