{
  "type": "Feature",
  "properties": {
    "addr:full":"1963 Lincoln Way Mc Keesport PA 15131",
    "addr:housenumber":"1963",
    "addr:postcode":"15131",
    "addr:street":"Lincoln Way",
    "iso:country":"US",
    "sg:address":"1963 Lincoln Way",
    "sg:city":"Mc Keesport",
    "sg:classifiers":[
        {
            "category":"Food & Beverages",
            "subcategory":"Fruits & Vegetables",
            "type":"Retail Goods"
        }
    ],
    "sg:phone":"+1   ",
    "sg:postcode":"15131",
    "sg:province":"PA",
    "wof:name":"Martins Cafe-Deli",
    "wof:placetype":"venue"
},
  "geometry": {"coordinates":[-79.812364,40.341549],"type":"Point"}
}