{
  "type": "Feature",
  "properties": {
    "iso:country":"US",
    "sg:address":"220 Hickory St",
    "sg:city":"Warren",
    "sg:classifiers":[
        {
            "category":"Shopping",
            "subcategory":"Catalog Store",
            "type":"Retail Goods"
        }
    ],
    "sg:phone":"+1   ",
    "sg:postcode":"16365",
    "sg:province":"PA",
    "sg:tags":[
        "marketing",
        "direct",
        "channel"
    ],
    "wof:name":"BLAIR",
    "wof:placetype":"venue"
},
  "geometry": {"coordinates":[-79.14951600000001,41.845846],"type":"Point"}
}