{
  "type": "Feature",
  "properties": {
    "iso:country":"US",
    "sg:address":"3925 Chessrown Ave",
    "sg:city":"Gibsonia",
    "sg:classifiers":[
        {
            "category":"Shopping",
            "subcategory":"Gifts & Souvenirs",
            "type":"Retail Goods"
        }
    ],
    "sg:phone":"+1   ",
    "sg:postcode":"15044",
    "sg:province":"PA",
    "sg:tags":[
        "dollar",
        "store"
    ],
    "wof:name":"Cheapskates Stores Inc",
    "wof:placetype":"venue"
},
  "geometry": {"coordinates":[-79.97514099999999,40.666524],"type":"Point"}
}