{
  "type": "Feature",
  "properties": {
    "iso:country":"US",
    "sg:address":"300 N Dithridge St",
    "sg:city":"Pittsburgh",
    "sg:classifiers":[
        {
            "category":"Professional",
            "type":"Services"
        }
    ],
    "sg:phone":"+1   ",
    "sg:postcode":"15213",
    "sg:province":"PA",
    "wof:name":"Xuan Xu",
    "wof:placetype":"venue"
},
  "geometry": {"coordinates":[-79.95415199999999,40.452816],"type":"Point"}
}