{
  "type": "Feature",
  "properties": {
    "iso:country":"US",
    "sg:address":"110 Lenzner Ct",
    "sg:city":"Sewickley",
    "sg:classifiers":[
        {
            "category":"Bus Charters",
            "type":"Transportation"
        }
    ],
    "sg:phone":"+1   ",
    "sg:postcode":"15143",
    "sg:province":"PA",
    "sg:tags":[
        "local"
    ],
    "wof:name":"Lenzner Tours and Travel",
    "wof:placetype":"venue"
},
  "geometry": {"coordinates":[-80.10844299999999,40.554412],"type":"Point"}
}