{
  "type": "Feature",
  "properties": {
    "iso:country":"US",
    "sg:address":"111 Grant Dr",
    "sg:city":"Southampton",
    "sg:classifiers":[
        {
            "category":"Shopping",
            "subcategory":"Bicycles & Sporting Goods",
            "type":"Retail Goods"
        }
    ],
    "sg:phone":"+1   ",
    "sg:postcode":"18966",
    "sg:province":"PA",
    "wof:name":"First Place Corp Awards",
    "wof:placetype":"venue"
},
  "geometry": {"coordinates":[-74.97551300000001,40.194635],"type":"Point"}
}