{
  "type": "Feature",
  "properties": {
    "iso:country":"US",
    "sg:address":"15 Lilac Dr",
    "sg:city":"Mechanicsburg",
    "sg:classifiers":[
        {
            "category":"Building & Trades",
            "subcategory":"Construction",
            "type":"Services"
        }
    ],
    "sg:phone":"+1   ",
    "sg:postcode":"17050",
    "sg:province":"PA",
    "sg:tags":[
        "general",
        "contractor"
    ],
    "wof:name":"Mitchell Construction",
    "wof:placetype":"venue"
},
  "geometry": {"coordinates":[-77.02364900000001,40.220405],"type":"Point"}
}