{
  "type": "Feature",
  "properties": {
    "iso:country":"US",
    "sg:address":"126 Hobart Blvd",
    "sg:city":"Slippery Rock",
    "sg:classifiers":[
        {
            "category":"Building & Trades",
            "subcategory":"Electrical",
            "type":"Services"
        }
    ],
    "sg:phone":"+1   ",
    "sg:postcode":"16057",
    "sg:province":"PA",
    "sg:tags":[
        "electrical",
        "contractor"
    ],
    "wof:name":"S Smith Electrical Contracting",
    "wof:placetype":"venue"
},
  "geometry": {"coordinates":[-80.015952,41.024322],"type":"Point"}
}