{
  "type": "Feature",
  "properties": {
    "iso:country":"US",
    "sg:address":"201 N Centre St",
    "sg:city":"Pottsville",
    "sg:classifiers":[
        {
            "category":"Social Services",
            "type":"Services"
        }
    ],
    "sg:phone":"+1 570 628 3513",
    "sg:postcode":"17901",
    "sg:province":"PA",
    "sg:tags":[
        "organization",
        "welfare"
    ],
    "wof:name":"Pottsville Senior Ctr",
    "wof:placetype":"venue"
},
  "geometry": {"coordinates":[-76.196105,40.686355],"type":"Point"}
}