{
  "type": "Feature",
  "properties": {
    "addr:full":"130 Sylvan Oakes Dr Hollidaysburg PA 16648",
    "addr:housenumber":"130",
    "addr:postcode":"16648",
    "addr:street":"Sylvan Oakes Dr",
    "iso:country":"US",
    "sg:address":"130 Sylvan Oakes Dr",
    "sg:city":"Hollidaysburg",
    "sg:classifiers":[
        {
            "category":"Manufacturing",
            "subcategory":"Buildings",
            "type":"Manufacturing & Wholesale Goods"
        },
        {
            "category":"Building & Trades",
            "subcategory":"Construction",
            "type":"Services"
        }
    ],
    "sg:phone":"+1 814 946 4862",
    "sg:postcode":"16648",
    "sg:province":"PA",
    "sg:tags":[
        "industrial",
        "system",
        "specialty",
        "builder",
        "heating",
        "contractor",
        "contractors-commercial",
        "home",
        "air conditioning"
    ],
    "wof:name":"Douglas K Pine",
    "wof:placetype":"venue"
},
  "geometry": {"coordinates":[-78.373034,40.46637],"type":"Point"}
}