{
  "type": "Feature",
  "properties": {
    "iso:country":"US",
    "sg:address":"665 W Main St",
    "sg:city":"New Holland",
    "sg:classifiers":[
        {
            "category":"Shopping",
            "subcategory":"Clothing, Apparel, & Fashions",
            "type":"Retail Goods"
        }
    ],
    "sg:phone":"+1 717 354 2051",
    "sg:postcode":"17557",
    "sg:province":"PA",
    "wof:name":"Fashion Bug",
    "wof:placetype":"venue"
},
  "geometry": {"coordinates":[-76.111797,40.09467],"type":"Point"}
}