{
  "type": "Feature",
  "properties": {
    "addr:full":"225 Lincoln Hwy Fairless Hills PA 19030",
    "addr:housenumber":"225",
    "addr:postcode":"19030",
    "addr:street":"Lincoln Hwy",
    "iso:country":"US",
    "sg:address":"225 Lincoln Hwy",
    "sg:city":"Fairless Hills",
    "sg:classifiers":[
        {
            "category":"Manufacturing",
            "subcategory":"Printing",
            "type":"Manufacturing & Wholesale Goods"
        }
    ],
    "sg:phone":"+1   ",
    "sg:postcode":"19030",
    "sg:province":"PA",
    "wof:name":"Philadelphia Plate Mfg",
    "wof:placetype":"venue"
},
  "geometry": {"coordinates":[-74.853999,40.184774],"type":"Point"}
}