{
  "type": "Feature",
  "properties": {
    "addr:full":"312 Commerce Dr Exton PA 19341",
    "addr:housenumber":"312",
    "addr:postcode":"19341",
    "addr:street":"Commerce Dr",
    "iso:country":"US",
    "sg:address":"312 Commerce Dr",
    "sg:city":"Exton",
    "sg:classifiers":[
        {
            "category":"Manufacturing",
            "subcategory":"Tools & Machinery",
            "type":"Manufacturing & Wholesale Goods"
        },
        {
            "category":"Utilities",
            "subcategory":"Water",
            "type":"Services"
        },
        {
            "category":"Personal",
            "type":"Services"
        },
        {
            "category":"Building & Trades",
            "subcategory":"Cleaning & Sanitation",
            "type":"Services"
        },
        {
            "category":"Home & Garden",
            "subcategory":"Carpets & Floor Coverings",
            "type":"Retail Goods"
        }
    ],
    "sg:phone":"+1 610 524 8003",
    "sg:postcode":"19341",
    "sg:province":"PA",
    "sg:tags":[
        "control",
        "equipment",
        "counteracting",
        "emergency",
        "extraction",
        "duct",
        "cleaners-water",
        "odor",
        "damage",
        "rug",
        "polishing",
        "flood",
        "waxing",
        "restoration",
        "fire",
        "ventilation",
        "smoke",
        "remediation",
        "air",
        "mold"
    ],
    "sg:website":"https://smclean.custhelp.com/cgi-bin/smclean.cfg/php/enduser/doc_serve.php?2=DR_YP",
    "wof:name":"ServiceMaster Clean",
    "wof:placetype":"venue"
},
  "geometry": {"coordinates":[-75.63565,40.023651],"type":"Point"}
}