{
  "type": "Feature",
  "properties": {
    "addr:full":"117 School St Bradford PA 16701",
    "addr:housenumber":"117",
    "addr:postcode":"16701",
    "addr:street":"School St",
    "iso:country":"US",
    "sg:address":"117 School St",
    "sg:city":"Bradford",
    "sg:classifiers":[
        {
            "category":"Airport",
            "type":"Transportation"
        }
    ],
    "sg:phone":"+1   ",
    "sg:postcode":"16701",
    "sg:province":"PA",
    "wof:name":"Laurel Penn Airlease Inc",
    "wof:placetype":"venue"
},
  "geometry": {"coordinates":[-78.658058,41.95945],"type":"Point"}
}