{
  "type": "Feature",
  "properties": {
    "addr:full":"1004 Pine St Philadelphia PA 19107",
    "addr:housenumber":"1004",
    "addr:postcode":"19107",
    "addr:street":"Pine St",
    "iso:country":"US",
    "sg:address":"1004 Pine St",
    "sg:city":"Philadelphia",
    "sg:classifiers":[
        {
            "category":"Shopping",
            "subcategory":"Used Merchandise",
            "type":"Retail Goods"
        }
    ],
    "sg:phone":"+1 215 925 8600",
    "sg:postcode":"19107",
    "sg:province":"PA",
    "wof:name":"Antiques & Interiors",
    "wof:placetype":"venue"
},
  "geometry": {"coordinates":[-75.15974900000001,39.944828],"type":"Point"}
}