{
  "type": "Feature",
  "properties": {
    "addr:full":"111 Pittsburgh St Uniontown PA 15401",
    "addr:housenumber":"111",
    "addr:postcode":"15401",
    "addr:street":"Pittsburgh St",
    "iso:country":"US",
    "sg:address":"111 Pittsburgh St",
    "sg:city":"Uniontown",
    "sg:classifiers":[
        {
            "category":"Wholesale",
            "subcategory":"Electrical",
            "type":"Manufacturing & Wholesale Goods"
        }
    ],
    "sg:phone":"+1 724 438 8000",
    "sg:postcode":"15401",
    "sg:province":"PA",
    "sg:tags":[
        "communication",
        "radio",
        "system"
    ],
    "wof:name":"Laurel Communications",
    "wof:placetype":"venue"
},
  "geometry": {"coordinates":[-79.727215,39.904681],"type":"Point"}
}