{
  "type": "Feature",
  "properties": {
    "iso:country":"US",
    "sg:address":"1002 E Willow Grove Ave",
    "sg:city":"Glenside",
    "sg:classifiers":[
        {
            "category":"Autos & Motor Vehicles",
            "subcategory":"Fuel & Gas Station",
            "type":"Retail Goods"
        }
    ],
    "sg:phone":"+1 215 233 2358",
    "sg:postcode":"19038",
    "sg:province":"PA",
    "sg:tags":[
        "oil"
    ],
    "wof:name":"Wyndmoor Sunoco & Auto Svc",
    "wof:placetype":"venue"
},
  "geometry": {"coordinates":[-75.187984,40.082966],"type":"Point"}
}