{
  "type": "Feature",
  "properties": {
    "iso:country":"US",
    "sg:address":"235 Main St",
    "sg:city":"New Kensington",
    "sg:classifiers":[
        {
            "category":"Professional",
            "subcategory":"Management & Consulting",
            "type":"Services"
        }
    ],
    "sg:phone":"+1   ",
    "sg:postcode":"15068",
    "sg:province":"PA",
    "sg:tags":[
        "business"
    ],
    "wof:name":"Zielinski Consulting Services",
    "wof:placetype":"venue"
},
  "geometry": {"coordinates":[-79.760711,40.554498],"type":"Point"}
}