{
  "type": "Feature",
  "properties": {
    "iso:country":"US",
    "sg:address":"285 E Canal Rd",
    "sg:city":"Hershey",
    "sg:classifiers":[
        {
            "category":"Professional",
            "subcategory":"Management & Consulting",
            "type":"Services"
        }
    ],
    "sg:phone":"+1   ",
    "sg:postcode":"17033",
    "sg:province":"PA",
    "wof:name":"Griggs & Associates",
    "wof:placetype":"venue"
},
  "geometry": {"coordinates":[-76.665339,40.320208],"type":"Point"}
}