{
  "type": "Feature",
  "properties": {
    "addr:full":"1240 Liberty St Franklin PA 16323",
    "addr:housenumber":"1240",
    "addr:postcode":"16323",
    "addr:street":"Liberty St",
    "iso:country":"US",
    "sg:address":"1240 Liberty St",
    "sg:city":"Franklin",
    "sg:classifiers":[
        {
            "category":"Banks & Credit Unions",
            "subcategory":"Investment Brokerage",
            "type":"Services"
        }
    ],
    "sg:phone":"+1 814 432 8578",
    "sg:postcode":"16323",
    "sg:province":"PA",
    "sg:tags":[
        "stock",
        "bond"
    ],
    "sg:website":"www.edwardjones.com",
    "wof:name":"Edward Jones Co",
    "wof:placetype":"venue"
},
  "geometry": {"coordinates":[-79.82811700000001,41.39755],"type":"Point"}
}