{
  "type": "Feature",
  "properties": {
    "iso:country":"US",
    "sg:address":"250 Center Ave",
    "sg:city":"Uniontown",
    "sg:classifiers":[
        {
            "category":"Building & Trades",
            "subcategory":"Cleaning & Sanitation",
            "type":"Services"
        }
    ],
    "sg:phone":"+1   ",
    "sg:postcode":"15401",
    "sg:province":"PA",
    "sg:tags":[
        "maintenance"
    ],
    "wof:name":"Keepin It Klean",
    "wof:placetype":"venue"
},
  "geometry": {"coordinates":[-79.706047,39.915113],"type":"Point"}
}