{
  "type": "Feature",
  "properties": {
    "addr:full":"104 Park Ave Ephrata PA 17522",
    "addr:housenumber":"104",
    "addr:postcode":"17522",
    "addr:street":"Park Ave",
    "iso:country":"US",
    "sg:address":"104 Park Ave",
    "sg:city":"Ephrata",
    "sg:classifiers":[
        {
            "category":"Building & Trades",
            "subcategory":"Construction",
            "type":"Services"
        }
    ],
    "sg:phone":"+1   ",
    "sg:postcode":"17522",
    "sg:province":"PA",
    "sg:tags":[
        "house"
    ],
    "wof:name":"Excalibur Construction Inc",
    "wof:placetype":"venue"
},
  "geometry": {"coordinates":[-76.175719,40.182994],"type":"Point"}
}