{
  "type": "Feature",
  "properties": {
    "iso:country":"US",
    "sg:address":"401 Wood St Ste 1200",
    "sg:city":"Pittsburgh",
    "sg:classifiers":[
        {
            "category":"Restaurant",
            "type":"Food & Drink"
        },
        {
            "category":"Shopping",
            "subcategory":"Mobile Phones",
            "type":"Retail Goods"
        }
    ],
    "sg:phone":"+1 412 392 0220",
    "sg:postcode":"15222",
    "sg:province":"PA",
    "wof:name":"Lambros & Schilling",
    "wof:placetype":"venue"
},
  "geometry": {"coordinates":[-80.00129699999999,40.4394],"type":"Point"}
}