{
  "type": "Feature",
  "properties": {
    "iso:country":"US",
    "sg:address":"46 S 69th St",
    "sg:city":"Upper Darby",
    "sg:classifiers":[
        {
            "category":"Shopping",
            "subcategory":"Clothing, Apparel, & Fashions",
            "type":"Retail Goods"
        }
    ],
    "sg:phone":"+1 610 734 1006",
    "sg:postcode":"19082",
    "sg:province":"PA",
    "sg:tags":[
        "accessory",
        "clothing",
        "women's"
    ],
    "wof:name":"10 Spot",
    "wof:placetype":"venue"
},
  "geometry": {"coordinates":[-75.258877,39.960256],"type":"Point"}
}