{
  "type": "Feature",
  "properties": {
    "iso:country":"US",
    "sg:address":"5416 E Lake Rd",
    "sg:city":"Erie",
    "sg:classifiers":[
        {
            "category":"Health Services",
            "subcategory":"Nursing And Care Facility",
            "type":"Services"
        }
    ],
    "sg:phone":"+1   ",
    "sg:postcode":"16511",
    "sg:province":"PA",
    "sg:tags":[
        "home"
    ],
    "wof:name":"Brevillier Village",
    "wof:placetype":"venue"
},
  "geometry": {"coordinates":[-79.996514,42.171095],"type":"Point"}
}