{
  "type": "Feature",
  "properties": {
    "addr:full":"7315 Oxford Ave Philadelphia PA 19111",
    "addr:housenumber":"7315",
    "addr:postcode":"19111",
    "addr:street":"Oxford Ave",
    "iso:country":"US",
    "sg:address":"7315 Oxford Ave",
    "sg:city":"Philadelphia",
    "sg:classifiers":[
        {
            "category":"Restaurant",
            "type":"Food & Drink"
        }
    ],
    "sg:phone":"+1 215 722 7300",
    "sg:postcode":"19111",
    "sg:province":"PA",
    "sg:tags":[
        "pizza"
    ],
    "wof:name":"Johnny G's Pizza",
    "wof:placetype":"venue"
},
  "geometry": {"coordinates":[-75.08348100000001,40.061809],"type":"Point"}
}