{
  "type": "Feature",
  "properties": {
    "iso:country":"US",
    "sg:address":"1307 Federal St Ste 300",
    "sg:city":"Pittsburgh",
    "sg:classifiers":[
        {
            "category":"Health Services",
            "subcategory":"Doctor",
            "type":"Services"
        }
    ],
    "sg:phone":"+1 412 281 1757",
    "sg:postcode":"15212",
    "sg:province":"PA",
    "sg:tags":[
        "physician",
        "surgeon",
        "urology",
        "surgery-general",
        "surgeons"
    ],
    "wof:name":"Triangle Urological Group Pc",
    "wof:placetype":"venue"
},
  "geometry": {"coordinates":[-80.007136,40.456989],"type":"Point"}
}