{
  "type": "Feature",
  "properties": {
    "iso:country":"US",
    "sg:address":"44 W Byler Rd",
    "sg:city":"Mercer",
    "sg:classifiers":[
        {
            "category":"Building & Trades",
            "subcategory":"Construction",
            "type":"Services"
        }
    ],
    "sg:phone":"+1   ",
    "sg:postcode":"16137",
    "sg:province":"PA",
    "sg:tags":[
        "hanging",
        "contractor"
    ],
    "wof:name":"Joe Toth Wallcoverings",
    "wof:placetype":"venue"
},
  "geometry": {"coordinates":[-80.312943,41.166457],"type":"Point"}
}