{
  "type": "Feature",
  "properties": {
    "iso:country":"US",
    "sg:address":"1633 Republic Rd",
    "sg:city":"Huntingdon Valley",
    "sg:classifiers":[
        {
            "category":"Shopping",
            "type":"Retail Goods"
        }
    ],
    "sg:phone":"+1   ",
    "sg:postcode":"19006",
    "sg:province":"PA",
    "sg:tags":[
        "repair",
        "electrical",
        "merchandise"
    ],
    "wof:name":"Symtech Solutions",
    "wof:placetype":"venue"
},
  "geometry": {"coordinates":[-75.064747,40.161633],"type":"Point"}
}