{
  "type": "Feature",
  "properties": {
    "iso:country":"US",
    "sg:address":"121 Armstrong Rd",
    "sg:city":"Pittston",
    "sg:classifiers":[
        {
            "category":"Building & Trades",
            "subcategory":"Construction",
            "type":"Services"
        }
    ],
    "sg:phone":"+1 570 655 7806",
    "sg:postcode":"18640",
    "sg:province":"PA",
    "sg:website":"www.tclloyd.com",
    "wof:name":"Northeastern Live Line Inc",
    "wof:placetype":"venue"
},
  "geometry": {"coordinates":[-75.743707,41.309429],"type":"Point"}
}