{
  "type": "Feature",
  "properties": {
    "iso:country":"US",
    "sg:address":"618 2nd Ave",
    "sg:city":"Bethlehem",
    "sg:classifiers":[
        {
            "category":"Organizations",
            "subcategory":"Community Association",
            "type":"Services"
        }
    ],
    "sg:phone":"+1 610 317 6144",
    "sg:postcode":"18018",
    "sg:province":"PA",
    "sg:tags":[
        "club",
        "religious"
    ],
    "wof:name":"University Bible Fellowship",
    "wof:placetype":"venue"
},
  "geometry": {"coordinates":[-75.38659699999999,40.623199],"type":"Point"}
}