{
  "type": "Feature",
  "properties": {
    "addr:full":"705 Roosevelt Ave York PA 17404",
    "addr:housenumber":"705",
    "addr:postcode":"17404",
    "addr:street":"Roosevelt Ave",
    "iso:country":"US",
    "sg:address":"705 Roosevelt Ave",
    "sg:city":"York",
    "sg:classifiers":[
        {
            "category":"Wholesale",
            "subcategory":"Machinery & Supplies",
            "type":"Manufacturing & Wholesale Goods"
        }
    ],
    "sg:phone":"+1 717 845 3691",
    "sg:postcode":"17404",
    "sg:province":"PA",
    "sg:tags":[
        "equipment",
        "material",
        "handling"
    ],
    "wof:name":"Wills Equipment Co",
    "wof:placetype":"venue"
},
  "geometry": {"coordinates":[-76.747925,39.966247],"type":"Point"}
}