{
  "type": "Feature",
  "properties": {
    "addr:full":"1214 N Strickler Rd Manheim PA 17545",
    "addr:housenumber":"1214",
    "addr:postcode":"17545",
    "addr:street":"N Strickler Rd",
    "iso:country":"US",
    "sg:address":"1214 N Strickler Rd",
    "sg:city":"Manheim",
    "sg:classifiers":[
        {
            "category":"Farming",
            "subcategory":"Farm",
            "type":"Manufacturing & Wholesale Goods"
        }
    ],
    "sg:phone":"+1   ",
    "sg:postcode":"17545",
    "sg:province":"PA",
    "sg:tags":[
        "crop",
        "general"
    ],
    "wof:name":"Fahnestock Farms",
    "wof:placetype":"venue"
},
  "geometry": {"coordinates":[-76.47915399999999,40.149701],"type":"Point"}
}