{
  "type": "Feature",
  "properties": {
    "iso:country":"US",
    "sg:address":"114 East Ave",
    "sg:city":"Wellsboro",
    "sg:classifiers":[
        {
            "category":"Health Services",
            "subcategory":"Clinic",
            "type":"Services"
        }
    ],
    "sg:phone":"+1 570 723 0560",
    "sg:postcode":"16901",
    "sg:province":"PA",
    "sg:tags":[
        "organization",
        "maintenance"
    ],
    "sg:website":"www.tyogacarenet.com",
    "wof:name":"Tyoga Care Net",
    "wof:placetype":"venue"
},
  "geometry": {"coordinates":[-77.28783199999999,41.747008],"type":"Point"}
}