{
  "type": "Feature",
  "properties": {
    "iso:country":"US",
    "sg:address":"434 Sterling Rd",
    "sg:city":"Tobyhanna",
    "sg:classifiers":[
        {
            "category":"Restaurant",
            "type":"Food & Drink"
        }
    ],
    "sg:phone":"+1 570 839 1470",
    "sg:postcode":"18466",
    "sg:province":"PA",
    "sg:tags":[
        "parlor",
        "ice",
        "cream"
    ],
    "wof:name":"Just Ice Cream",
    "wof:placetype":"venue"
},
  "geometry": {"coordinates":[-75.35754,41.153677],"type":"Point"}
}