{
  "type": "Feature",
  "properties": {
    "iso:country":"US",
    "sg:address":"523 Fitzwater St",
    "sg:city":"Philadelphia",
    "sg:classifiers":[
        {
            "category":"Professional",
            "subcategory":"Management & Consulting",
            "type":"Services"
        }
    ],
    "sg:phone":"+1 215 351 9060",
    "sg:postcode":"19147",
    "sg:province":"PA",
    "sg:tags":[
        "construction"
    ],
    "wof:name":"Nesmith & Co",
    "wof:placetype":"venue"
},
  "geometry": {"coordinates":[-75.15244199999999,39.940054],"type":"Point"}
}