{
  "type": "Feature",
  "properties": {
    "iso:country":"US",
    "sg:address":"221 Siebert Rd",
    "sg:city":"Pittsburgh",
    "sg:classifiers":[
        {
            "category":"Building & Trades",
            "subcategory":"Construction",
            "type":"Services"
        }
    ],
    "sg:phone":"+1   ",
    "sg:postcode":"15237",
    "sg:province":"PA",
    "sg:tags":[
        "floor",
        "laying",
        "contractor"
    ],
    "wof:name":"Folino Instillations",
    "wof:placetype":"venue"
},
  "geometry": {"coordinates":[-80.00881099999999,40.53025],"type":"Point"}
}