{
  "type": "Feature",
  "properties": {
    "iso:country":"US",
    "sg:address":"5737 Grayson Rd",
    "sg:city":"Harrisburg",
    "sg:classifiers":[
        {
            "category":"Transit Center",
            "subcategory":"Freight",
            "type":"Transportation"
        },
        {
            "category":"Freight",
            "type":"Transportation"
        }
    ],
    "sg:phone":"+1 717 561 8344",
    "sg:postcode":"17111",
    "sg:province":"PA",
    "sg:tags":[
        "local",
        "trucking-motor",
        "trucking"
    ],
    "wof:name":"Hess Trucking Co.",
    "wof:placetype":"venue"
},
  "geometry": {"coordinates":[-76.787262,40.260233],"type":"Point"}
}