{
  "type": "Feature",
  "properties": {
    "iso:country":"US",
    "sg:address":"621 Red Hill Rd",
    "sg:city":"Benton",
    "sg:classifiers":[
        {
            "category":"Farming",
            "subcategory":"Dairy Farm",
            "type":"Manufacturing & Wholesale Goods"
        }
    ],
    "sg:phone":"+1   ",
    "sg:postcode":"17814",
    "sg:province":"PA",
    "wof:name":"Kelly Davis",
    "wof:placetype":"venue"
},
  "geometry": {"coordinates":[-76.248215,41.231294],"type":"Point"}
}