{
  "type": "Feature",
  "properties": {
    "iso:country":"US",
    "sg:address":"1953 Stanton St",
    "sg:city":"York",
    "sg:classifiers":[
        {
            "category":"Real Estate",
            "subcategory":"Architect",
            "type":"Services"
        }
    ],
    "sg:phone":"+1 717 846 9600",
    "sg:postcode":"17404",
    "sg:province":"PA",
    "sg:tags":[
        "engineer"
    ],
    "wof:name":"JLB Engineering",
    "wof:placetype":"venue"
},
  "geometry": {"coordinates":[-76.770568,39.955131],"type":"Point"}
}