{
  "type": "Feature",
  "properties": {
    "iso:country":"US",
    "sg:address":"886 Methodist Rd",
    "sg:city":"Greenville",
    "sg:classifiers":[
        {
            "category":"Professional",
            "subcategory":"Art Services",
            "type":"Services"
        },
        {
            "category":"Shopping",
            "subcategory":"Crafts & Fabrics",
            "type":"Retail Goods"
        }
    ],
    "sg:phone":"+1 724 588 4283",
    "sg:postcode":"16125",
    "sg:province":"PA",
    "sg:tags":[
        "picture",
        "frame",
        "supply"
    ],
    "wof:name":"Crafts & Frames Just Sew",
    "wof:placetype":"venue"
},
  "geometry": {"coordinates":[-80.335144,41.424527],"type":"Point"}
}