{
  "type": "Feature",
  "properties": {
    "addr:full":"861 E Butler Ave Doylestown PA 18901",
    "addr:housenumber":"861",
    "addr:postcode":"18901",
    "addr:street":"E Butler Ave",
    "iso:country":"US",
    "sg:address":"861 E Butler Ave",
    "sg:city":"Doylestown",
    "sg:classifiers":[
        {
            "category":"Home & Garden",
            "subcategory":"Building Materials",
            "type":"Retail Goods"
        }
    ],
    "sg:phone":"+1 215 345 1271",
    "sg:postcode":"18901",
    "sg:province":"PA",
    "sg:tags":[
        "modular"
    ],
    "wof:name":"Melody Homes Inc",
    "wof:placetype":"venue"
},
  "geometry": {"coordinates":[-75.156496,40.299688],"type":"Point"}
}