{
  "type": "Feature",
  "properties": {
    "iso:country":"US",
    "sg:address":"6 Ppg Pl Ste 870",
    "sg:city":"Pittsburgh",
    "sg:classifiers":[
        {
            "category":"Professional",
            "subcategory":"Lawyer & Legal Services",
            "type":"Services"
        }
    ],
    "sg:phone":"+1 412 263 3360",
    "sg:postcode":"15222",
    "sg:province":"PA",
    "wof:name":"Bonacci John A Atty",
    "wof:placetype":"venue"
},
  "geometry": {"coordinates":[-80.0047,40.442402],"type":"Point"}
}