{
  "type": "Feature",
  "properties": {
    "iso:country":"US",
    "sg:address":"1896 York Rd",
    "sg:city":"Gettysburg",
    "sg:classifiers":[
        {
            "category":"Manufacturing",
            "subcategory":"Chemicals & Compounds",
            "type":"Manufacturing & Wholesale Goods"
        }
    ],
    "sg:phone":"+1 717 337 2264",
    "sg:postcode":"17325",
    "sg:province":"PA",
    "sg:tags":[
        "fertilizer"
    ],
    "wof:name":"F S Growmark Inc",
    "wof:placetype":"venue"
},
  "geometry": {"coordinates":[-77.17941500000001,39.848676],"type":"Point"}
}