{
  "type": "Feature",
  "properties": {
    "iso:country":"US",
    "sg:address":"8310 Rugby St",
    "sg:city":"Philadelphia",
    "sg:classifiers":[
        {
            "category":"Building & Trades",
            "subcategory":"Landscaping Services",
            "type":"Services"
        }
    ],
    "sg:phone":"+1 215 247 0483",
    "sg:postcode":"19150",
    "sg:province":"PA",
    "sg:tags":[
        "lawn",
        "maintenance"
    ],
    "wof:name":"Ford Custom Lawn Care",
    "wof:placetype":"venue"
},
  "geometry": {"coordinates":[-75.176677,40.074211],"type":"Point"}
}