{
  "type": "Feature",
  "properties": {
    "addr:full":"628 N Homewood Ave Pittsburgh PA 15208",
    "addr:housenumber":"628",
    "addr:postcode":"15208",
    "addr:street":"N Homewood Ave",
    "iso:country":"US",
    "sg:address":"628 N Homewood Ave",
    "sg:city":"Pittsburgh",
    "sg:classifiers":[
        {
            "category":"Retail",
            "subcategory":"Auto Repair",
            "type":"Services"
        }
    ],
    "sg:phone":"+1   ",
    "sg:postcode":"15208",
    "sg:province":"PA",
    "sg:tags":[
        "automotive"
    ],
    "wof:name":"Roys Car Service",
    "wof:placetype":"venue"
},
  "geometry": {"coordinates":[-79.89697200000001,40.455437],"type":"Point"}
}