{
  "type": "Feature",
  "properties": {
    "iso:country":"US",
    "sg:address":"346 Beechdale Rd",
    "sg:city":"Bird In Hand",
    "sg:classifiers":[
        {
            "category":"Building & Trades",
            "subcategory":"Construction",
            "type":"Services"
        }
    ],
    "sg:phone":"+1 717 295 3022",
    "sg:postcode":"17505",
    "sg:province":"PA",
    "sg:tags":[
        "dry wall",
        "contractor"
    ],
    "wof:name":"Millcreek Drywall Co",
    "wof:placetype":"venue"
},
  "geometry": {"coordinates":[-76.183042,40.040244],"type":"Point"}
}