{
  "type": "Feature",
  "properties": {
    "addr:full":"2337 Neshaminy Blvd Bensalem PA 19020",
    "addr:postcode":"2337;19020",
    "addr:street":"Neshaminy Blvd",
    "iso:country":"US",
    "sg:address":"2337 Neshaminy Blvd",
    "sg:city":"Bensalem",
    "sg:classifiers":[
        {
            "category":"Insurance",
            "subcategory":"Insurance Agent",
            "type":"Services"
        }
    ],
    "sg:phone":"+1 215 891 0655",
    "sg:postcode":"19020",
    "sg:province":"PA",
    "sg:tags":[
        "adjuster"
    ],
    "wof:name":"Anthony T Di Simone",
    "wof:placetype":"venue"
},
  "geometry": {"coordinates":[-74.924922,40.133346],"type":"Point"}
}