{
  "type": "Feature",
  "properties": {
    "addr:full":"6327 Germantown Ave Philadelphia PA 19144",
    "addr:housenumber":"6327",
    "addr:postcode":"19144",
    "addr:street":"Germantown Ave",
    "iso:country":"US",
    "sg:address":"6327 Germantown Ave",
    "sg:city":"Philadelphia",
    "sg:classifiers":[
        {
            "category":"Personal",
            "subcategory":"Shoe Repair & Shine",
            "type":"Services"
        }
    ],
    "sg:phone":"+1 215 844 3323",
    "sg:postcode":"19144",
    "sg:province":"PA",
    "sg:tags":[
        "shining"
    ],
    "wof:name":"Fuller's Shoe Shine",
    "wof:placetype":"venue"
},
  "geometry": {"coordinates":[-75.181539,40.044456],"type":"Point"}
}