{
  "type": "Feature",
  "properties": {
    "addr:full":"3380 Chesterfield Rd Philadelphia PA 19114",
    "addr:housenumber":"3380",
    "addr:postcode":"19114",
    "addr:street":"Chesterfield Rd",
    "iso:country":"US",
    "sg:address":"3380 Chesterfield Rd",
    "sg:city":"Philadelphia",
    "sg:classifiers":[
        {
            "category":"Wholesale",
            "subcategory":"Machinery & Supplies",
            "type":"Manufacturing & Wholesale Goods"
        }
    ],
    "sg:phone":"+1   ",
    "sg:postcode":"19114",
    "sg:province":"PA",
    "sg:tags":[
        "equipment",
        "industrial"
    ],
    "wof:name":"I M S Inc",
    "wof:placetype":"venue"
},
  "geometry": {"coordinates":[-74.99594999999999,40.0752],"type":"Point"}
}