{
  "type": "Feature",
  "properties": {
    "addr:full":"4150 Kensington Ave Philadelphia PA 19124",
    "addr:housenumber":"4150",
    "addr:postcode":"19124",
    "addr:street":"Kensington Ave",
    "iso:country":"US",
    "sg:address":"4150 Kensington Ave",
    "sg:city":"Philadelphia",
    "sg:classifiers":[
        {
            "category":"Building & Trades",
            "subcategory":"Electrical",
            "type":"Services"
        }
    ],
    "sg:phone":"+1 215 537 0400",
    "sg:postcode":"19124",
    "sg:province":"PA",
    "sg:tags":[
        "equipment",
        "fixture",
        "lighting",
        "electric",
        "contractor"
    ],
    "sg:website":"www.barneyroth.com",
    "wof:name":"Barney Roth Co Inc",
    "wof:placetype":"venue"
},
  "geometry": {"coordinates":[-75.09139999999999,40.0084],"type":"Point"}
}