{
  "type": "Feature",
  "properties": {
    "iso:country":"US",
    "sg:address":"1 Old Gap Rd",
    "sg:city":"Annville",
    "sg:classifiers":[
        {
            "category":"Government",
            "subcategory":"Office",
            "type":"Public Place"
        }
    ],
    "sg:phone":"+1   ",
    "sg:postcode":"17013",
    "sg:province":"PA",
    "sg:tags":[
        "affairs",
        "veteran",
        "bureau"
    ],
    "wof:name":"Veterans Affairs PA Bureau For",
    "wof:placetype":"venue"
},
  "geometry": {"coordinates":[-77.208388,40.219178],"type":"Point"}
}