{
  "type": "Feature",
  "properties": {
    "iso:country":"US",
    "sg:address":"1423 Cedar Ave",
    "sg:city":"Scranton",
    "sg:classifiers":[
        {
            "category":"Professional",
            "type":"Services"
        }
    ],
    "sg:phone":"+1   ",
    "sg:postcode":"18505",
    "sg:province":"PA",
    "wof:name":"Mfw Inc",
    "wof:placetype":"venue"
},
  "geometry": {"coordinates":[-75.674998,41.392894],"type":"Point"}
}