{
  "type": "Feature",
  "properties": {
    "iso:country":"US",
    "sg:address":"105 Park Dr",
    "sg:city":"Montgomeryville",
    "sg:classifiers":[
        {
            "category":"Manufacturing",
            "subcategory":"Electronics",
            "type":"Manufacturing & Wholesale Goods"
        }
    ],
    "sg:phone":"+1   ",
    "sg:postcode":"18936",
    "sg:province":"PA",
    "sg:tags":[
        "electronic",
        "component",
        "mfg"
    ],
    "wof:name":"LPC Liquidating Co",
    "wof:placetype":"venue"
},
  "geometry": {"coordinates":[-75.226367,40.212496],"type":"Point"}
}