{
  "type": "Feature",
  "properties": {
    "addr:full":"353 S Harrison St Shamokin PA 17872",
    "addr:housenumber":"353",
    "addr:postcode":"17872",
    "addr:street":"S Harrison St",
    "iso:country":"US",
    "sg:address":"353 S Harrison St",
    "sg:city":"Shamokin",
    "sg:classifiers":[
        {
            "category":"Real Estate",
            "subcategory":"Real Estate Agent",
            "type":"Services"
        }
    ],
    "sg:phone":"+1 570 644 2336",
    "sg:postcode":"17872",
    "sg:province":"PA",
    "sg:tags":[
        "authorities",
        "housing"
    ],
    "wof:name":"Shamokin City Housing Auth",
    "wof:placetype":"venue"
},
  "geometry": {"coordinates":[-76.548874,40.784336],"type":"Point"}
}