{
  "type": "Feature",
  "properties": {
    "iso:country":"US",
    "sg:address":"2710 Ridge Pike",
    "sg:city":"Norristown",
    "sg:classifiers":[
        {
            "category":"Retail",
            "subcategory":"Laundry & Dry Cleaning",
            "type":"Services"
        }
    ],
    "sg:phone":"+1 610 539 6988",
    "sg:postcode":"19403",
    "sg:province":"PA",
    "wof:name":"Trooper Cleaners",
    "wof:placetype":"venue"
},
  "geometry": {"coordinates":[-75.395139,40.146608],"type":"Point"}
}