{
  "type": "Feature",
  "properties": {
    "iso:country":"US",
    "sg:address":"532 9th St",
    "sg:city":"Selinsgrove",
    "sg:classifiers":[
        {
            "category":"Freight",
            "type":"Transportation"
        }
    ],
    "sg:phone":"+1   ",
    "sg:postcode":"17870",
    "sg:province":"PA",
    "sg:tags":[
        "operator",
        "local",
        "trucking"
    ],
    "wof:name":"Brian M Heddings Trucking",
    "wof:placetype":"venue"
},
  "geometry": {"coordinates":[-76.864265,40.806339],"type":"Point"}
}