{
  "type": "Feature",
  "properties": {
    "iso:country":"US",
    "sg:address":"1089 State Rte 12",
    "sg:city":"Frenchtown",
    "sg:classifiers":[
        {
            "category":"Sports & Exercise",
            "subcategory":"Bowling",
            "type":"Entertainment"
        }
    ],
    "sg:phone":"+1 908 996 2248",
    "sg:postcode":"08825",
    "sg:province":"PA",
    "sg:tags":[
        "center"
    ],
    "wof:name":"West Hunterton Lanes",
    "wof:placetype":"venue"
},
  "geometry": {"coordinates":[-74.991828,40.517081],"type":"Point"}
}