{
  "type": "Feature",
  "properties": {
    "addr:full":"2824 US Hwy 30 Georgetown PA 15043",
    "addr:housenumber":"2824",
    "addr:postcode":"15043",
    "addr:street":"Us Hwy 30",
    "iso:country":"US",
    "sg:address":"2824 US Hwy 30",
    "sg:city":"Georgetown",
    "sg:classifiers":[
        {
            "category":"Food & Beverages",
            "subcategory":"Groceries & Convenience Stores",
            "type":"Retail Goods"
        }
    ],
    "sg:phone":"+1 724 573 9535",
    "sg:postcode":"15043",
    "sg:province":"PA",
    "sg:tags":[
        "market"
    ],
    "wof:name":"Pat's Country Pride Market",
    "wof:placetype":"venue"
},
  "geometry": {"coordinates":[-80.491525,40.582794],"type":"Point"}
}