{
  "type": "Feature",
  "properties": {
    "addr:full":"900 Hook Rd Sharon Hill PA 19079",
    "addr:housenumber":"900",
    "addr:postcode":"19079",
    "addr:street":"Hook Rd",
    "iso:country":"US",
    "sg:address":"900 Hook Rd",
    "sg:city":"Sharon Hill",
    "sg:classifiers":[
        {
            "category":"Freight",
            "type":"Transportation"
        }
    ],
    "sg:phone":"+1   ",
    "sg:postcode":"19079",
    "sg:province":"PA",
    "sg:tags":[
        "arrangement"
    ],
    "wof:name":"Associated Air Freight",
    "wof:placetype":"venue"
},
  "geometry": {"coordinates":[-75.265984,39.898517],"type":"Point"}
}