{
  "type": "Feature",
  "properties": {
    "addr:full":"7527 Thouron Ave Philadelphia PA 19150",
    "addr:housenumber":"7527",
    "addr:postcode":"19150",
    "addr:street":"Thouron Ave",
    "iso:country":"US",
    "sg:address":"7527 Thouron Ave",
    "sg:city":"Philadelphia",
    "sg:classifiers":[
        {
            "category":"Personal",
            "subcategory":"Beauty Salon",
            "type":"Services"
        }
    ],
    "sg:phone":"+1   ",
    "sg:postcode":"19150",
    "sg:province":"PA",
    "sg:tags":[
        "shop"
    ],
    "wof:name":"Orig African Hair",
    "wof:placetype":"venue"
},
  "geometry": {"coordinates":[-75.16211199999999,40.067538],"type":"Point"}
}