{
  "type": "Feature",
  "properties": {
    "iso:country":"US",
    "sg:address":"1930 Catasauqua Rd",
    "sg:city":"Allentown",
    "sg:classifiers":[
        {
            "category":"Restaurant",
            "type":"Food & Drink"
        }
    ],
    "sg:phone":"+1 610 821 8488",
    "sg:postcode":"18109",
    "sg:province":"PA",
    "sg:tags":[
        "hot",
        "dog"
    ],
    "sg:website":"yoccos.com/",
    "wof:name":"Yocco's Hot Dog King",
    "wof:placetype":"venue"
},
  "geometry": {"coordinates":[-75.429694,40.641982],"type":"Point"}
}