{
  "type": "Feature",
  "properties": {
    "addr:full":"942 Race St Philadelphia PA 19107",
    "addr:housenumber":"942",
    "addr:postcode":"19107",
    "addr:street":"Race St",
    "iso:country":"US",
    "sg:address":"942 Race St",
    "sg:city":"Philadelphia",
    "sg:classifiers":[
        {
            "category":"Restaurant",
            "type":"Food & Drink"
        }
    ],
    "sg:phone":"+1 215 928 0451",
    "sg:postcode":"19107",
    "sg:province":"PA",
    "sg:tags":[
        "chinese"
    ],
    "wof:name":"Jade Harbor",
    "wof:placetype":"venue"
},
  "geometry": {"coordinates":[-75.1558,39.955399],"type":"Point"}
}