{
  "type": "Feature",
  "properties": {
    "addr:full":"5 Irving Dr West Grove PA 19390",
    "addr:housenumber":"5",
    "addr:postcode":"19390",
    "addr:street":"Irving Dr",
    "iso:country":"US",
    "sg:address":"5 Irving Dr",
    "sg:city":"West Grove",
    "sg:classifiers":[
        {
            "category":"Recreation",
            "type":"Entertainment"
        }
    ],
    "sg:phone":"+1 610 869 8853",
    "sg:postcode":"19390",
    "sg:province":"PA",
    "sg:tags":[
        "stable"
    ],
    "wof:name":"Water Gap Farm",
    "wof:placetype":"venue"
},
  "geometry": {"coordinates":[-75.86408900000001,39.824458],"type":"Point"}
}