{
  "type": "Feature",
  "properties": {
    "addr:full":"706 Broadway Ave Farrell PA 16121",
    "addr:housenumber":"706",
    "addr:postcode":"16121",
    "addr:street":"Broadway Ave",
    "iso:country":"US",
    "sg:address":"706 Broadway Ave",
    "sg:city":"Farrell",
    "sg:classifiers":[
        {
            "category":"Personal",
            "subcategory":"Barber",
            "type":"Services"
        }
    ],
    "sg:phone":"+1 724 342 2214",
    "sg:postcode":"16121",
    "sg:province":"PA",
    "wof:name":"Thomas Stewart Barber Shop",
    "wof:placetype":"venue"
},
  "geometry": {"coordinates":[-80.50657099999999,41.213412],"type":"Point"}
}