{
  "type": "Feature",
  "properties": {
    "iso:country":"US",
    "sg:address":"1521 N Main St",
    "sg:city":"Butler",
    "sg:classifiers":[
        {
            "category":"Shopping",
            "type":"Retail Goods"
        }
    ],
    "sg:phone":"+1 724 287 4300",
    "sg:postcode":"16001",
    "sg:province":"PA",
    "sg:tags":[
        "hearing",
        "equipment",
        "supply",
        "impaired"
    ],
    "wof:name":"Miracle-Ear",
    "wof:placetype":"venue"
},
  "geometry": {"coordinates":[-79.907487,40.895972],"type":"Point"}
}