{
  "type": "Feature",
  "properties": {
    "iso:country":"US",
    "sg:address":"1100 Eynon St",
    "sg:city":"Scranton",
    "sg:classifiers":[
        {
            "category":"Education",
            "subcategory":"School",
            "type":"Public Place"
        }
    ],
    "sg:phone":"+1 570 348 3692",
    "sg:postcode":"18504",
    "sg:province":"PA",
    "wof:name":"Frances Willard School",
    "wof:placetype":"venue"
},
  "geometry": {"coordinates":[-75.68867899999999,41.406815],"type":"Point"}
}