{
  "type": "Feature",
  "properties": {
    "iso:country":"US",
    "sg:address":"301 W 2nd St",
    "sg:city":"Chester",
    "sg:classifiers":[
        {
            "category":"Wholesale",
            "subcategory":"Groceries",
            "type":"Manufacturing & Wholesale Goods"
        }
    ],
    "sg:phone":"+1 610 876 9224",
    "sg:postcode":"19013",
    "sg:province":"PA",
    "sg:tags":[
        "baker"
    ],
    "sg:website":"www.buonobrosbakery.com",
    "wof:name":"Buono Bros Bakery",
    "wof:placetype":"venue"
},
  "geometry": {"coordinates":[-75.36416,39.843253],"type":"Point"}
}