{
  "type": "Feature",
  "properties": {
    "iso:country":"US",
    "sg:address":"969 Ohio River Blvd",
    "sg:city":"Pittsburgh",
    "sg:classifiers":[
        {
            "category":"Restaurant",
            "type":"Food & Drink"
        }
    ],
    "sg:phone":"+1 412 766 2115",
    "sg:postcode":"15202",
    "sg:province":"PA",
    "wof:name":"Subway Sandwiches & Salads",
    "wof:placetype":"venue"
},
  "geometry": {"coordinates":[-80.06655499999999,40.49563],"type":"Point"}
}