{
  "type": "Feature",
  "properties": {
    "iso:country":"US",
    "sg:address":"2673 Sand Beach Rd",
    "sg:city":"Grantville",
    "sg:classifiers":[
        {
            "category":"Education",
            "subcategory":"School",
            "type":"Public Place"
        }
    ],
    "sg:phone":"+1 717 469 2686",
    "sg:postcode":"17028",
    "sg:province":"PA",
    "wof:name":"East Hanover Elementary School",
    "wof:placetype":"venue"
},
  "geometry": {"coordinates":[-76.67460199999999,40.364837],"type":"Point"}
}