{
  "type": "Feature",
  "properties": {
    "addr:full":"6810 Big Beaver Blvd Beaver Falls PA 15010",
    "addr:housenumber":"6810",
    "addr:postcode":"15010",
    "addr:street":"Big Beaver Blvd",
    "iso:country":"US",
    "sg:address":"6810 Big Beaver Blvd",
    "sg:city":"Beaver Falls",
    "sg:classifiers":[
        {
            "category":"Shopping",
            "subcategory":"Discount & Variety Stores",
            "type":"Retail Goods"
        }
    ],
    "sg:phone":"+1 724 846 4074",
    "sg:postcode":"15010",
    "sg:province":"PA",
    "wof:name":"Dollar General",
    "wof:placetype":"venue"
},
  "geometry": {"coordinates":[-80.32722200000001,40.809788],"type":"Point"}
}