{
  "type": "Feature",
  "properties": {
    "iso:country":"US",
    "sg:address":"1105 W Chester Rd",
    "sg:city":"West Chester",
    "sg:classifiers":[
        {
            "category":"Professional",
            "subcategory":"Management & Consulting",
            "type":"Services"
        }
    ],
    "sg:phone":"+1   ",
    "sg:postcode":"19382",
    "sg:province":"PA",
    "sg:tags":[
        "business"
    ],
    "wof:name":"Pakintell LLC",
    "wof:placetype":"venue"
},
  "geometry": {"coordinates":[-75.54634900000001,39.911131],"type":"Point"}
}