{
  "type": "Feature",
  "properties": {
    "addr:full":"3080 Main St Morgantown PA 19543",
    "addr:housenumber":"3080",
    "addr:postcode":"19543",
    "addr:street":"Main St",
    "iso:country":"US",
    "sg:address":"3080 Main St",
    "sg:city":"Morgantown",
    "sg:classifiers":[
        {
            "category":"Restaurant",
            "type":"Food & Drink"
        },
        {
            "category":"Ice Cream",
            "type":"Food & Drink"
        }
    ],
    "sg:phone":"+1 610 286 0733",
    "sg:postcode":"19543",
    "sg:province":"PA",
    "sg:tags":[
        "frozen",
        "dessert"
    ],
    "sg:website":"http://www.ritasice.com",
    "wof:name":"Rita's Italian Ice",
    "wof:placetype":"venue"
},
  "geometry": {"coordinates":[-75.891182,40.15509],"type":"Point"}
}