{
  "type": "Feature",
  "properties": {
    "iso:country":"US",
    "sg:address":"3072 Conestoga Rd",
    "sg:city":"Glenmoore",
    "sg:classifiers":[
        {
            "category":"Building & Trades",
            "subcategory":"Construction",
            "type":"Services"
        }
    ],
    "sg:phone":"+1 610 458 5986",
    "sg:postcode":"19343",
    "sg:province":"PA",
    "sg:tags":[
        "contractor",
        "general",
        "carpentry"
    ],
    "wof:name":"Richard D Hassinger Constr",
    "wof:placetype":"venue"
},
  "geometry": {"coordinates":[-75.700232,40.118159],"type":"Point"}
}