{
  "type": "Feature",
  "properties": {
    "iso:country":"US",
    "sg:address":"5 McDermott Rd",
    "sg:city":"Fawn Grove",
    "sg:classifiers":[
        {
            "category":"Farming",
            "subcategory":"Dairy Farm",
            "type":"Manufacturing & Wholesale Goods"
        }
    ],
    "sg:phone":"+1   ",
    "sg:postcode":"17321",
    "sg:province":"PA",
    "wof:name":"C Richardson Farm",
    "wof:placetype":"venue"
},
  "geometry": {"coordinates":[-76.430937,39.72518],"type":"Point"}
}