{
  "type": "Feature",
  "properties": {
    "iso:country":"US",
    "sg:address":"1414 Friendship St",
    "sg:city":"Philadelphia",
    "sg:classifiers":[
        {
            "category":"Manufacturing",
            "subcategory":"Signs",
            "type":"Manufacturing & Wholesale Goods"
        }
    ],
    "sg:phone":"+1   ",
    "sg:postcode":"19111",
    "sg:province":"PA",
    "sg:tags":[
        "specialty",
        "mfg"
    ],
    "wof:name":"Rieglers Signs",
    "wof:placetype":"venue"
},
  "geometry": {"coordinates":[-75.06869500000001,40.048797],"type":"Point"}
}