{
  "type": "Feature",
  "properties": {
    "addr:full":"20 Cardinal Dr Fleetwood PA 19522",
    "addr:housenumber":"20",
    "addr:postcode":"19522",
    "addr:street":"Cardinal Dr",
    "iso:country":"US",
    "sg:address":"20 Cardinal Dr",
    "sg:city":"Fleetwood",
    "sg:classifiers":[
        {
            "category":"Manufacturing",
            "subcategory":"Jewelry",
            "type":"Manufacturing & Wholesale Goods"
        }
    ],
    "sg:phone":"+1   ",
    "sg:postcode":"19522",
    "sg:province":"PA",
    "sg:tags":[
        "costume",
        "mfg"
    ],
    "wof:name":"Joan C Miller",
    "wof:placetype":"venue"
},
  "geometry": {"coordinates":[-75.773268,40.42508],"type":"Point"}
}