{
  "type": "Feature",
  "properties": {
    "addr:full":"132 Lynndale Rd Lancaster PA 17603",
    "addr:housenumber":"132",
    "addr:postcode":"17603",
    "addr:street":"Lynndale Rd",
    "iso:country":"US",
    "sg:address":"132 Lynndale Rd",
    "sg:city":"Lancaster",
    "sg:classifiers":[
        {
            "category":"Professional",
            "subcategory":"Art Services",
            "type":"Services"
        }
    ],
    "sg:phone":"+1 717 872 1712",
    "sg:postcode":"17603",
    "sg:province":"PA",
    "sg:tags":[
        "photographer"
    ],
    "wof:name":"Aerial Visions",
    "wof:placetype":"venue"
},
  "geometry": {"coordinates":[-76.308226,39.972322],"type":"Point"}
}