{
  "type": "Feature",
  "properties": {
    "iso:country":"US",
    "sg:address":"244 Karen Dr",
    "sg:city":"Apollo",
    "sg:classifiers":[
        {
            "category":"Building & Trades",
            "subcategory":"Construction",
            "type":"Services"
        }
    ],
    "sg:phone":"+1 724 727 7451",
    "sg:postcode":"15613",
    "sg:province":"PA",
    "sg:tags":[
        "house",
        "improvement",
        "home"
    ],
    "wof:name":"Carl's Home Improvements",
    "wof:placetype":"venue"
},
  "geometry": {"coordinates":[-79.601056,40.570454],"type":"Point"}
}