{
  "type": "Feature",
  "properties": {
    "iso:country":"US",
    "sg:address":"6325 Burbridge St",
    "sg:city":"Philadelphia",
    "sg:classifiers":[
        {
            "category":"Social Services",
            "subcategory":"Child Care",
            "type":"Services"
        }
    ],
    "sg:phone":"+1   ",
    "sg:postcode":"19144",
    "sg:province":"PA",
    "sg:tags":[
        "day"
    ],
    "wof:name":"Crittenden Day Care Center",
    "wof:placetype":"venue"
},
  "geometry": {"coordinates":[-75.185228,40.040805],"type":"Point"}
}