{
  "type": "Feature",
  "properties": {
    "iso:country":"US",
    "sg:address":"927 S High St",
    "sg:city":"West Chester",
    "sg:classifiers":[
        {
            "category":"Restaurant",
            "type":"Food & Drink"
        }
    ],
    "sg:phone":"+1 610 692 7342",
    "sg:postcode":"19382",
    "sg:province":"PA",
    "sg:website":"www.mcdonalds.com",
    "wof:name":"McDonald's Hamburgers",
    "wof:placetype":"venue"
},
  "geometry": {"coordinates":[-75.591103,39.941601],"type":"Point"}
}