{
  "type": "Feature",
  "properties": {
    "iso:country":"US",
    "sg:address":"86 McCormick Dr",
    "sg:city":"Lincoln Univ",
    "sg:classifiers":[
        {
            "category":"Building & Trades",
            "subcategory":"Landscaping Services",
            "type":"Services"
        }
    ],
    "sg:phone":"+1 610 869 3727",
    "sg:postcode":"19350",
    "sg:province":"PA",
    "sg:tags":[
        "landscape",
        "contractor"
    ],
    "wof:name":"J & A Landscaping",
    "wof:placetype":"venue"
},
  "geometry": {"coordinates":[-75.75156800000001,39.762892],"type":"Point"}
}