{
  "type": "Feature",
  "properties": {
    "iso:country":"US",
    "sg:address":"1139 S Mountain Rd",
    "sg:city":"Dillsburg",
    "sg:classifiers":[
        {
            "category":"Freight",
            "type":"Transportation"
        }
    ],
    "sg:phone":"+1 717 432 9113",
    "sg:postcode":"17019",
    "sg:province":"PA",
    "sg:tags":[
        "operator",
        "local",
        "trucking"
    ],
    "sg:website":"www.j-squaredtrucking.com",
    "wof:name":"J Squared Trucking LLC",
    "wof:placetype":"venue"
},
  "geometry": {"coordinates":[-77.077011,40.079896],"type":"Point"}
}