{
  "type": "Feature",
  "properties": {
    "addr:full":"551 Easton Rd Warrington PA 18976",
    "addr:housenumber":"551",
    "addr:postcode":"18976",
    "addr:street":"Easton Rd",
    "iso:country":"US",
    "sg:address":"551 Easton Rd",
    "sg:city":"Warrington",
    "sg:classifiers":[
        {
            "category":"Building & Trades",
            "subcategory":"Construction",
            "type":"Services"
        }
    ],
    "sg:phone":"+1   ",
    "sg:postcode":"18976",
    "sg:province":"PA",
    "sg:tags":[
        "contractor"
    ],
    "wof:name":"Mick & Assoc",
    "wof:placetype":"venue"
},
  "geometry": {"coordinates":[-75.13967100000001,40.2271],"type":"Point"}
}