{
  "type": "Feature",
  "properties": {
    "iso:country":"US",
    "sg:address":"10447 Drummond Rd",
    "sg:city":"Philadelphia",
    "sg:classifiers":[
        {
            "category":"Food & Beverages",
            "subcategory":"Specialty",
            "type":"Retail Goods"
        },
        {
            "category":"Wholesale",
            "subcategory":"Groceries",
            "type":"Manufacturing & Wholesale Goods"
        }
    ],
    "sg:phone":"+1 215 824 3300",
    "sg:postcode":"19154",
    "sg:province":"PA",
    "sg:tags":[
        "water",
        "bulk",
        "company",
        "bottled"
    ],
    "sg:website":"www.wspringwater.com",
    "wof:name":"Wissahickon Mtn Spring Wtr Inc",
    "wof:placetype":"venue"
},
  "geometry": {"coordinates":[-74.99499400000001,40.084722],"type":"Point"}
}