{
  "type": "Feature",
  "properties": {
    "iso:country":"US",
    "sg:address":"203 W Chester Rd",
    "sg:city":"West Chester",
    "sg:classifiers":[
        {
            "category":"Professional",
            "type":"Services"
        }
    ],
    "sg:phone":"+1 610 436 1818",
    "sg:postcode":"19382",
    "sg:province":"PA",
    "sg:tags":[
        "establishment"
    ],
    "wof:name":"Care Center Foundation",
    "wof:placetype":"venue"
},
  "geometry": {"coordinates":[-75.544465,39.910821],"type":"Point"}
}