{
  "type": "Feature",
  "properties": {
    "addr:full":"511 S Main St Athens PA 18810",
    "addr:housenumber":"511",
    "addr:postcode":"18810",
    "addr:street":"S Main St",
    "iso:country":"US",
    "sg:address":"511 S Main St",
    "sg:city":"Athens",
    "sg:classifiers":[
        {
            "category":"Organizations",
            "subcategory":"Community Association",
            "type":"Services"
        }
    ],
    "sg:phone":"+1   ",
    "sg:postcode":"18810",
    "sg:province":"PA",
    "wof:name":"Carantouan Greenway",
    "wof:placetype":"venue"
},
  "geometry": {"coordinates":[-76.517692,41.954969],"type":"Point"}
}