{
  "type": "Feature",
  "properties": {
    "iso:country":"US",
    "sg:address":"415 Davisville Rd",
    "sg:city":"Willow Grove",
    "sg:classifiers":[
        {
            "category":"Health Services",
            "subcategory":"Chiropractor",
            "type":"Services"
        }
    ],
    "sg:phone":"+1 215 830 9797",
    "sg:postcode":"19090",
    "sg:province":"PA",
    "wof:name":"Michele Emberger DC",
    "wof:placetype":"venue"
},
  "geometry": {"coordinates":[-75.11120699999999,40.146076],"type":"Point"}
}