{
  "type": "Feature",
  "properties": {
    "iso:country":"US",
    "sg:address":"800 Newtown Richboro Rd",
    "sg:city":"Richboro",
    "sg:classifiers":[
        {
            "category":"Utilities",
            "subcategory":"Telephone",
            "type":"Services"
        }
    ],
    "sg:phone":"+1   ",
    "sg:postcode":"18954",
    "sg:province":"PA",
    "sg:tags":[
        "on",
        "provider"
    ],
    "wof:name":"Coast 2 Coast Financial Svcs",
    "wof:placetype":"venue"
},
  "geometry": {"coordinates":[-74.972172,40.219639],"type":"Point"}
}