{
  "type": "Feature",
  "properties": {
    "iso:country":"US",
    "sg:address":"18 E Springfield Rd",
    "sg:city":"Springfield",
    "sg:classifiers":[
        {
            "category":"Insurance",
            "subcategory":"Hazard Insurance",
            "type":"Services"
        },
        {
            "category":"Insurance",
            "subcategory":"Insurance Agent",
            "type":"Services"
        },
        {
            "category":"Insurance",
            "subcategory":"Life Insurance",
            "type":"Services"
        },
        {
            "category":"Insurance",
            "subcategory":"Title Insurance",
            "type":"Services"
        }
    ],
    "sg:phone":"+1 610 544 8900",
    "sg:postcode":"19064",
    "sg:province":"PA",
    "sg:tags":[
        "auto",
        "homeowner"
    ],
    "sg:website":"http://www.nationwide.com/agent/Springfield-PENNSYLVANIA-insurance-agent/rocco-polidoro/office.html",
    "wof:name":"Rocco J Polidoro, Clu - Nationwide Insurance",
    "wof:placetype":"venue"
},
  "geometry": {"coordinates":[-75.32875799999999,39.933609],"type":"Point"}
}