{
  "type": "Feature",
  "properties": {
    "iso:country":"US",
    "sg:address":"345 Union St",
    "sg:city":"Columbia",
    "sg:classifiers":[
        {
            "category":"Personal",
            "subcategory":"Beauty Salon",
            "type":"Services"
        }
    ],
    "sg:phone":"+1 717 684 9511",
    "sg:postcode":"17512",
    "sg:province":"PA",
    "sg:tags":[
        "shop"
    ],
    "wof:name":"Bonnie's Beauty Bar",
    "wof:placetype":"venue"
},
  "geometry": {"coordinates":[-76.498836,40.030564],"type":"Point"}
}