{
  "type": "Feature",
  "properties": {
    "iso:country":"US",
    "sg:address":"513 3rd St",
    "sg:city":"Ellwood City",
    "sg:classifiers":[
        {
            "category":"Wholesale",
            "subcategory":"Machinery & Supplies",
            "type":"Manufacturing & Wholesale Goods"
        }
    ],
    "sg:phone":"+1   ",
    "sg:postcode":"16117",
    "sg:province":"PA",
    "sg:tags":[
        "equipment",
        "industrial"
    ],
    "wof:name":"Doctor Deck",
    "wof:placetype":"venue"
},
  "geometry": {"coordinates":[-80.283936,40.857545],"type":"Point"}
}