{
  "type": "Feature",
  "properties": {
    "addr:full":"1785 Klines Mill Rd Quakertown PA 18951",
    "addr:housenumber":"1785",
    "addr:postcode":"18951",
    "addr:street":"Klines Mill Rd",
    "iso:country":"US",
    "sg:address":"1785 Klines Mill Rd",
    "sg:city":"Quakertown",
    "sg:classifiers":[
        {
            "category":"Manufacturing",
            "subcategory":"Lumber",
            "type":"Manufacturing & Wholesale Goods"
        }
    ],
    "sg:phone":"+1   ",
    "sg:postcode":"18951",
    "sg:province":"PA",
    "sg:tags":[
        "mill",
        "logging"
    ],
    "wof:name":"Kline Jacob R Lumber Mfg",
    "wof:placetype":"venue"
},
  "geometry": {"coordinates":[-75.441884,40.414853],"type":"Point"}
}