{
  "type": "Feature",
  "properties": {
    "iso:country":"US",
    "sg:address":"720 Linden St",
    "sg:city":"Bethlehem",
    "sg:classifiers":[
        {
            "category":"Retail",
            "subcategory":"Laundry & Dry Cleaning",
            "type":"Services"
        }
    ],
    "sg:phone":"+1 610 866 4621",
    "sg:postcode":"18018",
    "sg:province":"PA",
    "sg:tags":[
        "cleaners"
    ],
    "wof:name":"Linden Street Tailor Shop",
    "wof:placetype":"venue"
},
  "geometry": {"coordinates":[-75.370401,40.623517],"type":"Point"}
}