{
  "type": "Feature",
  "properties": {
    "addr:full":"590 McClures Gap Rd Carlisle PA 17013",
    "addr:housenumber":"590",
    "addr:postcode":"17013",
    "addr:street":"Mcclures Gap Rd",
    "iso:country":"US",
    "sg:address":"590 McClures Gap Rd",
    "sg:city":"Carlisle",
    "sg:classifiers":[
        {
            "category":"Farming",
            "subcategory":"Dairy Farm",
            "type":"Manufacturing & Wholesale Goods"
        }
    ],
    "sg:phone":"+1   ",
    "sg:postcode":"17013",
    "sg:province":"PA",
    "wof:name":"Garmans Dairy",
    "wof:placetype":"venue"
},
  "geometry": {"coordinates":[-77.230946,40.216609],"type":"Point"}
}