{
  "type": "Feature",
  "properties": {
    "addr:full":"712 W Chester Rd West Chester PA 19382",
    "addr:housenumber":"712",
    "addr:postcode":"19382",
    "addr:street":"W Chester Rd",
    "iso:country":"US",
    "sg:address":"712 W Chester Rd",
    "sg:city":"West Chester",
    "sg:classifiers":[
        {
            "category":"Building & Trades",
            "subcategory":"Construction",
            "type":"Services"
        }
    ],
    "sg:phone":"+1   ",
    "sg:postcode":"19382",
    "sg:province":"PA",
    "wof:name":"Comstar Technologies",
    "wof:placetype":"venue"
},
  "geometry": {"coordinates":[-75.545608,39.910857],"type":"Point"}
}