{
  "type": "Feature",
  "properties": {
    "iso:country":"US",
    "sg:address":"126 Oster St",
    "sg:city":"Osterburg",
    "sg:classifiers":[
        {
            "category":"Health Services",
            "subcategory":"Chiropractor",
            "type":"Services"
        }
    ],
    "sg:phone":"+1 814 276 3212",
    "sg:postcode":"16667",
    "sg:province":"PA",
    "wof:name":"Deffibaugh Chiropractic",
    "wof:placetype":"venue"
},
  "geometry": {"coordinates":[-78.521294,40.171199],"type":"Point"}
}