{
  "type": "Feature",
  "properties": {
    "iso:country":"US",
    "sg:address":"152 Eagleview Blvd",
    "sg:city":"Exton",
    "sg:classifiers":[
        {
            "category":"Restaurant",
            "type":"Food & Drink"
        }
    ],
    "sg:phone":"+1   ",
    "sg:postcode":"19341",
    "sg:province":"PA",
    "sg:tags":[
        "eating"
    ],
    "wof:name":"Sals Pizzeria Itln Ristorante",
    "wof:placetype":"venue"
},
  "geometry": {"coordinates":[-75.665243,40.056035],"type":"Point"}
}