{
  "type": "Feature",
  "properties": {
    "iso:country":"US",
    "sg:address":"7028 Ridge Ave",
    "sg:city":"Philadelphia",
    "sg:classifiers":[
        {
            "category":"Shopping",
            "subcategory":"Gifts & Souvenirs",
            "type":"Retail Goods"
        }
    ],
    "sg:phone":"+1 215 508 1055",
    "sg:postcode":"19128",
    "sg:province":"PA",
    "sg:tags":[
        "shop"
    ],
    "wof:name":"Chocolate Stop",
    "wof:placetype":"venue"
},
  "geometry": {"coordinates":[-75.22852899999999,40.043859],"type":"Point"}
}