{
  "type": "Feature",
  "properties": {
    "iso:country":"US",
    "sg:address":"47 Main St",
    "sg:city":"Dallas",
    "sg:classifiers":[
        {
            "category":"Social Services",
            "subcategory":"Child Care",
            "type":"Services"
        }
    ],
    "sg:phone":"+1   ",
    "sg:postcode":"18612",
    "sg:province":"PA",
    "sg:tags":[
        "day"
    ],
    "wof:name":"Whitakers Group Day Care",
    "wof:placetype":"venue"
},
  "geometry": {"coordinates":[-75.95749000000001,41.332265],"type":"Point"}
}