{
  "type": "Feature",
  "properties": {
    "addr:full":"25 E Howard St Dallastown PA 17313",
    "addr:housenumber":"25",
    "addr:postcode":"17313",
    "addr:street":"E Howard St",
    "iso:country":"US",
    "sg:address":"25 E Howard St",
    "sg:city":"Dallastown",
    "sg:classifiers":[
        {
            "category":"Organizations",
            "subcategory":"Community Association",
            "type":"Services"
        }
    ],
    "sg:phone":"+1   ",
    "sg:postcode":"17313",
    "sg:province":"PA",
    "wof:name":"International Assoc of LI",
    "wof:placetype":"venue"
},
  "geometry": {"coordinates":[-76.644048,39.899778],"type":"Point"}
}