{
  "type": "Feature",
  "properties": {
    "iso:country":"US",
    "sg:address":"218 State Rte 428",
    "sg:city":"Oil City",
    "sg:classifiers":[
        {
            "category":"Building & Trades",
            "subcategory":"Construction",
            "type":"Services"
        }
    ],
    "sg:phone":"+1 814 677 9563",
    "sg:postcode":"16301",
    "sg:province":"PA",
    "sg:tags":[
        "concrete",
        "excavating",
        "contractor"
    ],
    "wof:name":"Joseph A Klapec & Son Inc",
    "wof:placetype":"venue"
},
  "geometry": {"coordinates":[-79.73457399999999,41.475917],"type":"Point"}
}