{
  "type": "Feature",
  "properties": {
    "addr:full":"24 Abele Rd Bridgeville PA 15017",
    "addr:housenumber":"24",
    "addr:postcode":"15017",
    "addr:street":"Abele Rd",
    "iso:country":"US",
    "sg:address":"24 Abele Rd",
    "sg:city":"Bridgeville",
    "sg:classifiers":[
        {
            "category":"Food & Beverages",
            "subcategory":"Groceries & Convenience Stores",
            "type":"Retail Goods"
        }
    ],
    "sg:phone":"+1   ",
    "sg:postcode":"15017",
    "sg:province":"PA",
    "wof:name":"Schwans Home Service Inc",
    "wof:placetype":"venue"
},
  "geometry": {"coordinates":[-80.12478,40.352042],"type":"Point"}
}