{
  "type": "Feature",
  "properties": {
    "iso:country":"US",
    "sg:address":"423 Pennsylvania Ave",
    "sg:city":"Lansdale",
    "sg:classifiers":[
        {
            "category":"Health Services",
            "subcategory":"Clinic",
            "type":"Services"
        }
    ],
    "sg:phone":"+1 215 362 0474",
    "sg:postcode":"19446",
    "sg:province":"PA",
    "sg:tags":[
        "counseling",
        "mental"
    ],
    "wof:name":"Advanced Psychological Associates",
    "wof:placetype":"venue"
},
  "geometry": {"coordinates":[-75.295601,40.239201],"type":"Point"}
}