{
  "type": "Feature",
  "properties": {
    "iso:country":"US",
    "sg:address":"9 Oakglade Dr",
    "sg:city":"Hummelstown",
    "sg:classifiers":[
        {
            "category":"Restaurant",
            "type":"Food & Drink"
        }
    ],
    "sg:phone":"+1 717 566 7273",
    "sg:postcode":"17036",
    "sg:province":"PA",
    "sg:tags":[
        "caterer"
    ],
    "wof:name":"Bea's Catering",
    "wof:placetype":"venue"
},
  "geometry": {"coordinates":[-76.72901,40.295577],"type":"Point"}
}