{
  "type": "Feature",
  "properties": {
    "addr:full":"1618 Mountain Rd Hamburg PA 19526",
    "addr:housenumber":"1618",
    "addr:postcode":"19526",
    "addr:street":"Mountain Rd",
    "iso:country":"US",
    "sg:address":"1618 Mountain Rd",
    "sg:city":"Hamburg",
    "sg:classifiers":[
        {
            "category":"Bakery",
            "type":"Food & Drink"
        },
        {
            "category":"Coffee & Tea",
            "type":"Food & Drink"
        },
        {
            "category":"Bagels",
            "type":"Food & Drink"
        },
        {
            "category":"Donuts",
            "type":"Food & Drink"
        }
    ],
    "sg:menulink":"http://www.allmenus.com/pa/windsor/143719-dunkin-donuts/menu/",
    "sg:phone":"+1 610 562 9499",
    "sg:postcode":"19526",
    "sg:province":"PA",
    "sg:tags":[
        "american",
        "diner",
        "pastry"
    ],
    "wof:name":"Dunkin' Donuts",
    "wof:placetype":"venue"
},
  "geometry": {"coordinates":[-75.97762899999999,40.570625],"type":"Point"}
}