{
  "type": "Feature",
  "properties": {
    "addr:full":"53 Grow Ave Montrose PA 18801",
    "addr:housenumber":"53",
    "addr:postcode":"18801",
    "addr:street":"Grow Ave",
    "iso:country":"US",
    "sg:address":"53 Grow Ave",
    "sg:city":"Montrose",
    "sg:classifiers":[
        {
            "category":"Food & Beverages",
            "subcategory":"Liquor & Beverages",
            "type":"Retail Goods"
        },
        {
            "category":"Wholesale",
            "subcategory":"Beer",
            "type":"Manufacturing & Wholesale Goods"
        }
    ],
    "sg:phone":"+1 570 278 2337",
    "sg:postcode":"18801",
    "sg:province":"PA",
    "sg:tags":[
        "grocery",
        "ale"
    ],
    "wof:name":"Montrose Beverage Corp",
    "wof:placetype":"venue"
},
  "geometry": {"coordinates":[-75.867431,41.835833],"type":"Point"}
}