{
  "type": "Feature",
  "properties": {
    "iso:country":"US",
    "sg:address":"209 W High St",
    "sg:city":"Ebensburg",
    "sg:classifiers":[
        {
            "category":"Retail",
            "subcategory":"Repair Shop",
            "type":"Services"
        }
    ],
    "sg:phone":"+1   ",
    "sg:postcode":"15931",
    "sg:province":"PA",
    "wof:name":"Ebensburg Music Mart Aand Elec",
    "wof:placetype":"venue"
},
  "geometry": {"coordinates":[-78.72706599999999,40.485267],"type":"Point"}
}