{
  "type": "Feature",
  "properties": {
    "addr:full":"1255 S Cedar Crest Blvd # 2 Allentown PA 18103",
    "addr:housenumber":"1255",
    "addr:postcode":"18103",
    "addr:street":"S Cedar Crest Blvd # 2",
    "iso:country":"US",
    "sg:address":"1255 S Cedar Crest Blvd # 2",
    "sg:city":"Allentown",
    "sg:classifiers":[
        {
            "category":"Organizations",
            "subcategory":"Non-profit Organization",
            "type":"Services"
        }
    ],
    "sg:phone":"+1 610 439 7420",
    "sg:postcode":"18103",
    "sg:province":"PA",
    "sg:tags":[
        "fund",
        "raising"
    ],
    "wof:name":"March Of Dimes Foundation",
    "wof:placetype":"venue"
},
  "geometry": {"coordinates":[-75.518207,40.564881],"type":"Point"}
}