{
  "type": "Feature",
  "properties": {
    "iso:country":"US",
    "sg:address":"618 S 2nd St",
    "sg:city":"Philadelphia",
    "sg:classifiers":[
        {
            "category":"Wholesale",
            "subcategory":"Books, Periodicals, & Newspapers",
            "type":"Manufacturing & Wholesale Goods"
        }
    ],
    "sg:phone":"+1 215 574 9223",
    "sg:postcode":"19147",
    "sg:province":"PA",
    "sg:tags":[
        "shop",
        "computer",
        "gift",
        "program",
        "export",
        "import"
    ],
    "wof:name":"International Trading & Mktg",
    "wof:placetype":"venue"
},
  "geometry": {"coordinates":[-75.14568800000001,39.941066],"type":"Point"}
}