{
  "type": "Feature",
  "properties": {
    "addr:full":"3400 Dennison Ave Drexel Hill PA 19026",
    "addr:housenumber":"3400",
    "addr:postcode":"19026",
    "addr:street":"Dennison Ave",
    "iso:country":"US",
    "sg:address":"3400 Dennison Ave",
    "sg:city":"Drexel Hill",
    "sg:classifiers":[
        {
            "category":"Education",
            "subcategory":"School",
            "type":"Public Place"
        }
    ],
    "sg:phone":"+1 610 626 4687",
    "sg:postcode":"19026",
    "sg:province":"PA",
    "wof:name":"St Charles Borromeo School",
    "wof:placetype":"venue"
},
  "geometry": {"coordinates":[-75.286653,39.936032],"type":"Point"}
}