{
  "type": "Feature",
  "properties": {
    "iso:country":"US",
    "sg:address":"2661 N 2nd St",
    "sg:city":"Philadelphia",
    "sg:classifiers":[
        {
            "category":"Shopping",
            "subcategory":"Jewelry",
            "type":"Retail Goods"
        }
    ],
    "sg:phone":"+1 215 425 1144",
    "sg:postcode":"19133",
    "sg:province":"PA",
    "wof:name":"F H Gold Buyers of Phila II",
    "wof:placetype":"venue"
},
  "geometry": {"coordinates":[-75.134821,39.990764],"type":"Point"}
}