{
  "type": "Feature",
  "properties": {
    "iso:country":"US",
    "sg:address":"8533 Singer Rd",
    "sg:city":"North East",
    "sg:classifiers":[
        {
            "category":"Farming",
            "subcategory":"Vineyard",
            "type":"Manufacturing & Wholesale Goods"
        }
    ],
    "sg:phone":"+1   ",
    "sg:postcode":"16428",
    "sg:province":"PA",
    "sg:tags":[
        "grape"
    ],
    "wof:name":"Maas Farms Harvesting",
    "wof:placetype":"venue"
},
  "geometry": {"coordinates":[-79.783743,42.211191],"type":"Point"}
}