{
  "type": "Feature",
  "properties": {
    "iso:country":"US",
    "sg:address":"5 Silver Ln",
    "sg:city":"Coraopolis",
    "sg:classifiers":[
        {
            "category":"Restaurant",
            "type":"Food & Drink"
        }
    ],
    "sg:phone":"+1 412 859 6577",
    "sg:postcode":"15108",
    "sg:province":"PA",
    "sg:tags":[
        "pizza"
    ],
    "wof:name":"Barefoot Pizza",
    "wof:placetype":"venue"
},
  "geometry": {"coordinates":[-80.13130200000001,40.477501],"type":"Point"}
}