{
  "type": "Feature",
  "properties": {
    "iso:country":"US",
    "sg:address":"4360 Vista Dr",
    "sg:city":"Nazareth",
    "sg:classifiers":[
        {
            "category":"Professional",
            "type":"Services"
        }
    ],
    "sg:phone":"+1   ",
    "sg:postcode":"18064",
    "sg:province":"PA",
    "wof:name":"Miles For Matt Mem Foundation",
    "wof:placetype":"venue"
},
  "geometry": {"coordinates":[-75.33064400000001,40.707075],"type":"Point"}
}