{
  "type": "Feature",
  "properties": {
    "iso:country":"US",
    "sg:address":"139 Pond View Ln",
    "sg:city":"Clearville",
    "sg:classifiers":[
        {
            "category":"Manufacturing",
            "subcategory":"Tools & Machinery",
            "type":"Manufacturing & Wholesale Goods"
        }
    ],
    "sg:phone":"+1   ",
    "sg:postcode":"15535",
    "sg:province":"PA",
    "sg:tags":[
        "woodworking",
        "mfg"
    ],
    "wof:name":"Buck Ridge Crafts",
    "wof:placetype":"venue"
},
  "geometry": {"coordinates":[-78.513695,39.82204],"type":"Point"}
}