{
  "type": "Feature",
  "properties": {
    "iso:country":"US",
    "sg:address":"643 Dahlia Dr",
    "sg:city":"Monroeville",
    "sg:classifiers":[
        {
            "category":"Freight",
            "type":"Transportation"
        }
    ],
    "sg:phone":"+1   ",
    "sg:postcode":"15146",
    "sg:province":"PA",
    "sg:tags":[
        "operator",
        "trucking"
    ],
    "wof:name":"Vrcic Transportation",
    "wof:placetype":"venue"
},
  "geometry": {"coordinates":[-79.772374,40.450021],"type":"Point"}
}