{
  "type": "Feature",
  "properties": {
    "addr:full":"101 Kappa Dr Pittsburgh PA 15238",
    "addr:housenumber":"101",
    "addr:postcode":"15238",
    "addr:street":"Kappa Dr",
    "iso:country":"US",
    "sg:address":"101 Kappa Dr",
    "sg:city":"Pittsburgh",
    "sg:classifiers":[
        {
            "category":"Professional",
            "subcategory":"Business Services",
            "type":"Services"
        }
    ],
    "sg:phone":"+1 412 967 3750",
    "sg:postcode":"15238",
    "sg:province":"PA",
    "sg:tags":[
        "fund",
        "promotion",
        "raising"
    ],
    "wof:name":"Retail Promotions",
    "wof:placetype":"venue"
},
  "geometry": {"coordinates":[-79.865021,40.505193],"type":"Point"}
}