{
  "type": "Feature",
  "properties": {
    "iso:country":"US",
    "sg:address":"35 E Elizabeth Ave Ste 25",
    "sg:city":"Bethlehem",
    "sg:classifiers":[
        {
            "category":"Health Services",
            "subcategory":"Doctor",
            "type":"Services"
        }
    ],
    "sg:phone":"+1 610 865 9444",
    "sg:postcode":"18018",
    "sg:province":"PA",
    "sg:tags":[
        "psychiatrist"
    ],
    "wof:name":"Rogers John F MD",
    "wof:placetype":"venue"
},
  "geometry": {"coordinates":[-75.376701,40.630901],"type":"Point"}
}