{
  "type": "Feature",
  "properties": {
    "iso:country":"US",
    "sg:address":"1220 Millersville Pike",
    "sg:city":"Lancaster",
    "sg:classifiers":[
        {
            "category":"Shopping",
            "subcategory":"Gifts & Souvenirs",
            "type":"Retail Goods"
        }
    ],
    "sg:phone":"+1 717 299 2160",
    "sg:postcode":"17603",
    "sg:province":"PA",
    "sg:website":"www.willcoxandsavage.com",
    "wof:name":"Manor Cardtique",
    "wof:placetype":"venue"
},
  "geometry": {"coordinates":[-76.32452600000001,40.028755],"type":"Point"}
}