{
  "type": "Feature",
  "properties": {
    "iso:country":"US",
    "sg:address":"537 Beaver St",
    "sg:city":"Sewickley",
    "sg:classifiers":[
        {
            "category":"Restaurant",
            "type":"Food & Drink"
        }
    ],
    "sg:menulink":"http://www.allmenus.com/pa/sewickley/123195-quiznos-sub/menu/",
    "sg:phone":"+1 412 741 8834",
    "sg:postcode":"15143",
    "sg:province":"PA",
    "sg:tags":[
        "wrap",
        "american",
        "sandwich"
    ],
    "wof:name":"Quiznos Sub",
    "wof:placetype":"venue"
},
  "geometry": {"coordinates":[-80.179552,40.539432],"type":"Point"}
}