{
  "type": "Feature",
  "properties": {
    "addr:full":"24 State St Oil City PA 16301",
    "addr:housenumber":"24",
    "addr:postcode":"16301",
    "addr:street":"State St",
    "iso:country":"US",
    "sg:address":"24 State St",
    "sg:city":"Oil City",
    "sg:classifiers":[
        {
            "category":"Banks & Credit Unions",
            "subcategory":"Bank",
            "type":"Services"
        }
    ],
    "sg:phone":"+1   ",
    "sg:postcode":"16301",
    "sg:province":"PA",
    "sg:tags":[
        "state"
    ],
    "wof:name":"Citizens Bank of Pennsylvania",
    "wof:placetype":"venue"
},
  "geometry": {"coordinates":[-79.709706,41.429036],"type":"Point"}
}