{
  "type": "Feature",
  "properties": {
    "addr:full":"238 6th St Milford PA 18337",
    "addr:housenumber":"238",
    "addr:postcode":"18337",
    "addr:street":"6Th St",
    "iso:country":"US",
    "sg:address":"238 6th St",
    "sg:city":"Milford",
    "sg:classifiers":[
        {
            "category":"Food & Beverages",
            "subcategory":"Groceries & Convenience Stores",
            "type":"Retail Goods"
        }
    ],
    "sg:phone":"+1 570 296 4636",
    "sg:postcode":"18337",
    "sg:province":"PA",
    "wof:name":"Hilltop Xtra Mart",
    "wof:placetype":"venue"
},
  "geometry": {"coordinates":[-74.806245,41.324493],"type":"Point"}
}