{
  "type": "Feature",
  "properties": {
    "iso:country":"US",
    "sg:address":"48 S Market St",
    "sg:city":"Elizabethtown",
    "sg:classifiers":[
        {
            "category":"Real Estate",
            "subcategory":"Real Estate Agent",
            "type":"Services"
        }
    ],
    "sg:phone":"+1 717 367 3866",
    "sg:postcode":"17022",
    "sg:province":"PA",
    "sg:website":"http://www.pruhomesaleservices.com",
    "wof:name":"Prudential Homesale Services Group",
    "wof:placetype":"venue"
},
  "geometry": {"coordinates":[-76.605594,40.150898],"type":"Point"}
}