{
  "type": "Feature",
  "properties": {
    "iso:country":"US",
    "sg:address":"1212 South St",
    "sg:city":"Philadelphia",
    "sg:classifiers":[
        {
            "category":"Food & Beverages",
            "subcategory":"Specialty",
            "type":"Retail Goods"
        }
    ],
    "sg:phone":"+1 888 963 4872",
    "sg:postcode":"19147",
    "sg:province":"PA",
    "sg:website":"wmdhotsauce.com",
    "wof:name":"WMD Hot Sauce",
    "wof:placetype":"venue"
},
  "geometry": {"coordinates":[-75.16228099999999,39.94308],"type":"Point"}
}