{
  "type": "Feature",
  "properties": {
    "addr:full":"1680 Beechwood Blvd Pittsburgh PA 15217",
    "addr:housenumber":"1680",
    "addr:postcode":"15217",
    "addr:street":"Beechwood Blvd",
    "iso:country":"US",
    "sg:address":"1680 Beechwood Blvd",
    "sg:city":"Pittsburgh",
    "sg:classifiers":[
        {
            "category":"Professional",
            "subcategory":"Engineering",
            "type":"Services"
        }
    ],
    "sg:phone":"+1 412 521 4006",
    "sg:postcode":"15217",
    "sg:province":"PA",
    "wof:name":"Pressure Sciences Inc",
    "wof:placetype":"venue"
},
  "geometry": {"coordinates":[-79.91663200000001,40.44014],"type":"Point"}
}