{
  "type": "Feature",
  "properties": {
    "iso:country":"US",
    "sg:address":"6335 Larch Cir",
    "sg:city":"Macungie",
    "sg:classifiers":[
        {
            "category":"Wholesale",
            "subcategory":"Machinery & Supplies",
            "type":"Manufacturing & Wholesale Goods"
        }
    ],
    "sg:phone":"+1   ",
    "sg:postcode":"18062",
    "sg:province":"PA",
    "sg:tags":[
        "equipment",
        "industrial"
    ],
    "wof:name":"Unitrak",
    "wof:placetype":"venue"
},
  "geometry": {"coordinates":[-75.562485,40.520551],"type":"Point"}
}