{
  "type": "Feature",
  "properties": {
    "iso:country":"US",
    "sg:address":"701 Ave of the States",
    "sg:city":"Chester",
    "sg:classifiers":[
        {
            "category":"Shopping",
            "subcategory":"News",
            "type":"Retail Goods"
        }
    ],
    "sg:phone":"+1 610 872 2633",
    "sg:postcode":"19013",
    "sg:province":"PA",
    "sg:tags":[
        "dealer"
    ],
    "wof:name":"Chester News",
    "wof:placetype":"venue"
},
  "geometry": {"coordinates":[-75.360715,39.851773],"type":"Point"}
}