{
  "type": "Feature",
  "properties": {
    "iso:country":"US",
    "sg:address":"226 W Rittenhouse Sq",
    "sg:city":"Philadelphia",
    "sg:classifiers":[
        {
            "category":"Professional",
            "subcategory":"Lawyer & Legal Services",
            "type":"Services"
        }
    ],
    "sg:phone":"+1 215 731 9004",
    "sg:postcode":"19103",
    "sg:province":"PA",
    "wof:name":"Richards Ira Neil Atty",
    "wof:placetype":"venue"
},
  "geometry": {"coordinates":[-75.173103,39.9496],"type":"Point"}
}