{
  "type": "Feature",
  "properties": {
    "iso:country":"US",
    "sg:address":"425 Steel Way",
    "sg:city":"Lancaster",
    "sg:classifiers":[
        {
            "category":"Freight",
            "type":"Transportation"
        }
    ],
    "sg:phone":"+1 717 569 5837",
    "sg:postcode":"17601",
    "sg:province":"PA",
    "sg:tags":[
        "trucking"
    ],
    "wof:name":"Dedicated Fatime Express",
    "wof:placetype":"venue"
},
  "geometry": {"coordinates":[-76.32557,40.06544],"type":"Point"}
}