{
  "type": "Feature",
  "properties": {
    "addr:full":"2010 N 29th St Philadelphia PA 19121",
    "addr:housenumber":"2010",
    "addr:postcode":"19121",
    "addr:street":"N 29Th St",
    "iso:country":"US",
    "sg:address":"2010 N 29th St",
    "sg:city":"Philadelphia",
    "sg:classifiers":[
        {
            "category":"Organizations",
            "subcategory":"Professional Association",
            "type":"Services"
        }
    ],
    "sg:phone":"+1 215 609 4538",
    "sg:postcode":"19121",
    "sg:province":"PA",
    "sg:tags":[
        "business",
        "trade"
    ],
    "wof:name":"Building A Village Coalition, Inc.",
    "wof:placetype":"venue"
},
  "geometry": {"coordinates":[-75.18085000000001,39.986608],"type":"Point"}
}