{
  "type": "Feature",
  "properties": {
    "addr:full":"400 S Main St Doylestown PA 18901",
    "addr:housenumber":"400",
    "addr:postcode":"18901",
    "addr:street":"S Main St",
    "iso:country":"US",
    "sg:address":"400 S Main St",
    "sg:city":"Doylestown",
    "sg:classifiers":[
        {
            "category":"Health Services",
            "subcategory":"Nursing And Care Facility",
            "type":"Services"
        }
    ],
    "sg:phone":"+1 215 348 2980",
    "sg:postcode":"18901",
    "sg:province":"PA",
    "sg:tags":[
        "home",
        "skilled",
        "convalescent"
    ],
    "wof:name":"Greenleaf Nursing And Convalescent, Inc",
    "wof:placetype":"venue"
},
  "geometry": {"coordinates":[-75.128377,40.301314],"type":"Point"}
}