{
  "type": "Feature",
  "properties": {
    "iso:country":"US",
    "sg:address":"212 E Marble St",
    "sg:city":"Mechanicsburg",
    "sg:classifiers":[
        {
            "category":"Insurance",
            "subcategory":"Insurance Agent",
            "type":"Services"
        }
    ],
    "sg:phone":"+1 717 697 4353",
    "sg:postcode":"17055",
    "sg:province":"PA",
    "wof:name":"Richard E Cover Agency",
    "wof:placetype":"venue"
},
  "geometry": {"coordinates":[-77.00192199999999,40.20951],"type":"Point"}
}