{
  "type": "Feature",
  "properties": {
    "addr:full":"227 W Cooper St Slippery Rock PA 16057",
    "addr:housenumber":"227",
    "addr:postcode":"16057",
    "addr:street":"W Cooper St",
    "iso:country":"US",
    "sg:address":"227 W Cooper St",
    "sg:city":"Slippery Rock",
    "sg:classifiers":[
        {
            "category":"Professional",
            "type":"Services"
        }
    ],
    "sg:phone":"+1   ",
    "sg:postcode":"16057",
    "sg:province":"PA",
    "wof:name":"Bulgaria International Inc",
    "wof:placetype":"venue"
},
  "geometry": {"coordinates":[-80.05569199999999,41.06095],"type":"Point"}
}