{
  "type": "Feature",
  "properties": {
    "addr:full":"439 Somerset Ave Rockwood PA 15557",
    "addr:housenumber":"439",
    "addr:postcode":"15557",
    "addr:street":"Somerset Ave",
    "iso:country":"US",
    "sg:address":"439 Somerset Ave",
    "sg:city":"Rockwood",
    "sg:classifiers":[
        {
            "category":"Education",
            "subcategory":"School",
            "type":"Public Place"
        }
    ],
    "sg:phone":"+1 814 926 3708",
    "sg:postcode":"15557",
    "sg:province":"PA",
    "wof:name":"Alternative Community Resource",
    "wof:placetype":"venue"
},
  "geometry": {"coordinates":[-79.16024899999999,39.917125],"type":"Point"}
}