{
  "type": "Feature",
  "properties": {
    "iso:country":"US",
    "sg:address":"5320 Rte 322",
    "sg:city":"Knox",
    "sg:classifiers":[
        {
            "category":"Bars & Pubs",
            "type":"Food & Drink"
        }
    ],
    "sg:phone":"+1   ",
    "sg:postcode":"16232",
    "sg:province":"PA",
    "sg:tags":[
        "tavern"
    ],
    "wof:name":"OGrove",
    "wof:placetype":"venue"
},
  "geometry": {"coordinates":[-79.513346,41.269406],"type":"Point"}
}