{
  "type": "Feature",
  "properties": {
    "iso:country":"US",
    "sg:address":"2309 Columbia Ave",
    "sg:city":"Lancaster",
    "sg:classifiers":[
        {
            "category":"Restaurant",
            "type":"Food & Drink"
        }
    ],
    "sg:phone":"+1   ",
    "sg:postcode":"17603",
    "sg:province":"PA",
    "sg:tags":[
        "eating"
    ],
    "wof:name":"Carlos & Charlies Bar & Rest",
    "wof:placetype":"venue"
},
  "geometry": {"coordinates":[-76.369704,40.040031],"type":"Point"}
}