{
  "type": "Feature",
  "properties": {
    "iso:country":"US",
    "sg:address":"5917 Drexel Rd",
    "sg:city":"Philadelphia",
    "sg:classifiers":[
        {
            "category":"Health Services",
            "subcategory":"Health Practitioner",
            "type":"Services"
        }
    ],
    "sg:phone":"+1 215 877 2500",
    "sg:postcode":"19131",
    "sg:province":"PA",
    "sg:tags":[
        "nutritionist"
    ],
    "wof:name":"The Center For Spiritual & Health Awareness",
    "wof:placetype":"venue"
},
  "geometry": {"coordinates":[-75.24479700000001,39.9883],"type":"Point"}
}