{
  "type": "Feature",
  "properties": {
    "iso:country":"US",
    "sg:address":"74 Park Ave",
    "sg:city":"Chalfont",
    "sg:classifiers":[
        {
            "category":"Professional",
            "subcategory":"Printing & Photocopies",
            "type":"Services"
        }
    ],
    "sg:phone":"+1 215 997 8077",
    "sg:postcode":"18914",
    "sg:province":"PA",
    "sg:website":"www.smithprints.com",
    "wof:name":"Smithprints",
    "wof:placetype":"venue"
},
  "geometry": {"coordinates":[-75.20563300000001,40.291484],"type":"Point"}
}