{
  "type": "Feature",
  "properties": {
    "iso:country":"US",
    "sg:address":"803 Mifflin St",
    "sg:city":"West Mifflin",
    "sg:classifiers":[
        {
            "category":"Building & Trades",
            "subcategory":"Construction",
            "type":"Services"
        }
    ],
    "sg:phone":"+1   ",
    "sg:postcode":"15122",
    "sg:province":"PA",
    "sg:tags":[
        "home",
        "general",
        "commercial",
        "family",
        "contractor"
    ],
    "wof:name":"Corinthian Construction Co",
    "wof:placetype":"venue"
},
  "geometry": {"coordinates":[-79.854507,40.361323],"type":"Point"}
}