{
  "type": "Feature",
  "properties": {
    "addr:full":"1029 E Woodland Ave  Springfield PA 19064",
    "addr:housenumber":"1029",
    "addr:postcode":"19064",
    "addr:street":"E Woodland Ave Springfield",
    "iso:country":"US",
    "sg:address":"1029 E Woodland Ave ",
    "sg:city":"Springfield",
    "sg:classifiers":[
        {
            "category":"Restaurant",
            "type":"Food & Drink"
        }
    ],
    "sg:menulink":"http://www.allmenus.com/pa/springfield/288904-420-pizza-house/menu/",
    "sg:phone":"+1 610 544 4951",
    "sg:postcode":"19064",
    "sg:province":"PA",
    "sg:tags":[
        "greek",
        "american",
        "pizza"
    ],
    "wof:name":"420 Pizza House",
    "wof:placetype":"venue"
},
  "geometry": {"coordinates":[-75.331367,39.912624],"type":"Point"}
}