{
  "type": "Feature",
  "properties": {
    "addr:full":"3750 Market St Camp Hill PA 17011",
    "addr:housenumber":"3750",
    "addr:postcode":"17011",
    "addr:street":"Market St",
    "iso:country":"US",
    "sg:address":"3750 Market St",
    "sg:city":"Camp Hill",
    "sg:classifiers":[
        {
            "category":"Shopping",
            "subcategory":"Jewelry",
            "type":"Retail Goods"
        }
    ],
    "sg:phone":"+1 717 737 5808",
    "sg:postcode":"17011",
    "sg:province":"PA",
    "sg:tags":[
        "jeweler"
    ],
    "wof:name":"Morrow Diamonds & Farrar Jewelers",
    "wof:placetype":"venue"
},
  "geometry": {"coordinates":[-76.946297,40.238998],"type":"Point"}
}