{
  "type": "Feature",
  "properties": {
    "iso:country":"US",
    "sg:address":"5 Squire Ln",
    "sg:city":"New Hope",
    "sg:classifiers":[
        {
            "category":"Home & Garden",
            "subcategory":"Carpets & Floor Coverings",
            "type":"Retail Goods"
        }
    ],
    "sg:phone":"+1   ",
    "sg:postcode":"18938",
    "sg:province":"PA",
    "sg:tags":[
        "laying",
        "contractor"
    ],
    "wof:name":"G & B Carpet",
    "wof:placetype":"venue"
},
  "geometry": {"coordinates":[-74.946906,40.332022],"type":"Point"}
}