{
  "type": "Feature",
  "properties": {
    "iso:country":"US",
    "sg:address":"3710 Robin Rd",
    "sg:city":"Furlong",
    "sg:classifiers":[
        {
            "category":"Insurance",
            "subcategory":"Insurance Agent",
            "type":"Services"
        }
    ],
    "sg:phone":"+1 215 794 7499",
    "sg:postcode":"18925",
    "sg:province":"PA",
    "wof:name":"Dee Wells Insurance",
    "wof:placetype":"venue"
},
  "geometry": {"coordinates":[-75.08569799999999,40.307581],"type":"Point"}
}