{
  "type": "Feature",
  "properties": {
    "iso:country":"US",
    "sg:address":"1400 Fox Hill Rd",
    "sg:city":"State College",
    "sg:classifiers":[
        {
            "category":"Professional",
            "subcategory":"Research",
            "type":"Services"
        }
    ],
    "sg:phone":"+1 814 353 8311",
    "sg:postcode":"16823",
    "sg:province":"PA",
    "sg:tags":[
        "development",
        "laboratory"
    ],
    "wof:name":"Star H Corp",
    "wof:placetype":"venue"
},
  "geometry": {"coordinates":[-77.86852,40.841814],"type":"Point"}
}