{
  "type": "Feature",
  "properties": {
    "iso:country":"US",
    "sg:address":"50 West Rd",
    "sg:city":"Newtown",
    "sg:classifiers":[
        {
            "category":"Personal",
            "subcategory":"Beauty Salon",
            "type":"Services"
        },
        {
            "category":"Personal",
            "subcategory":"Day Spa",
            "type":"Services"
        }
    ],
    "sg:phone":"+1 215 860 5200",
    "sg:postcode":"18940",
    "sg:province":"PA",
    "sg:tags":[
        "hair",
        "accessory",
        "supply"
    ],
    "sg:website":"http://www.toppersspa.com",
    "wof:name":"Toppers Spa/Salon Bucks",
    "wof:placetype":"venue"
},
  "geometry": {"coordinates":[-74.942818,40.235279],"type":"Point"}
}