{
  "type": "Feature",
  "properties": {
    "iso:country":"US",
    "sg:address":"252 State Rd",
    "sg:city":"Bensalem",
    "sg:classifiers":[
        {
            "category":"Real Estate",
            "subcategory":"Real Estate Operator",
            "type":"Services"
        }
    ],
    "sg:phone":"+1   ",
    "sg:postcode":"19020",
    "sg:province":"PA",
    "sg:tags":[
        "property",
        "lessor"
    ],
    "wof:name":"Cambria Corporate Center",
    "wof:placetype":"venue"
},
  "geometry": {"coordinates":[-74.977929,40.058443],"type":"Point"}
}