{
  "type": "Feature",
  "properties": {
    "iso:country":"US",
    "sg:address":"1116 Horsham Rd",
    "sg:city":"Ambler",
    "sg:classifiers":[
        {
            "category":"Retail",
            "subcategory":"Laundry & Dry Cleaning",
            "type":"Services"
        }
    ],
    "sg:phone":"+1   ",
    "sg:postcode":"19002",
    "sg:province":"PA",
    "sg:tags":[
        "drycleaning",
        "plant"
    ],
    "wof:name":"Prestige Dry Cleaner",
    "wof:placetype":"venue"
},
  "geometry": {"coordinates":[-75.189224,40.214046],"type":"Point"}
}