{
  "type": "Feature",
  "properties": {
    "addr:full":"2014 Ford Rd Bristol PA 19007",
    "addr:housenumber":"2014",
    "addr:postcode":"19007",
    "addr:street":"Ford Rd",
    "iso:country":"US",
    "sg:address":"2014 Ford Rd",
    "sg:city":"Bristol",
    "sg:classifiers":[
        {
            "category":"Wholesale",
            "subcategory":"Machinery & Supplies",
            "type":"Manufacturing & Wholesale Goods"
        }
    ],
    "sg:phone":"+1 215 826 8060",
    "sg:postcode":"19007",
    "sg:province":"PA",
    "sg:tags":[
        "equipment",
        "screen",
        "printing"
    ],
    "wof:name":"N B Garber",
    "wof:placetype":"venue"
},
  "geometry": {"coordinates":[-74.89448,40.117988],"type":"Point"}
}