{
  "type": "Feature",
  "properties": {
    "iso:country":"US",
    "sg:address":"4982 Path Valley Rd",
    "sg:city":"Fort Loudon",
    "sg:classifiers":[
        {
            "category":"Retail",
            "subcategory":"Repair Shop",
            "type":"Services"
        }
    ],
    "sg:phone":"+1 717 369 4118",
    "sg:postcode":"17224",
    "sg:province":"PA",
    "sg:tags":[
        "sharpening",
        "animal"
    ],
    "sg:website":"www.gilssharpshop.com",
    "wof:name":"Gil's Sharp Shop",
    "wof:placetype":"venue"
},
  "geometry": {"coordinates":[-77.895698,39.995554],"type":"Point"}
}