{
  "type": "Feature",
  "properties": {
    "iso:country":"US",
    "sg:address":"257 Four Seasons Dr",
    "sg:city":"Drums",
    "sg:classifiers":[
        {
            "category":"Communications",
            "type":"Services"
        }
    ],
    "sg:phone":"+1 570 788 9758",
    "sg:postcode":"18222",
    "sg:province":"PA",
    "wof:name":"Warren Communications",
    "wof:placetype":"venue"
},
  "geometry": {"coordinates":[-75.928113,41.044733],"type":"Point"}
}