{
  "type": "Feature",
  "properties": {
    "addr:full":"1945 Millport Rd Lancaster PA 17602",
    "addr:housenumber":"1945",
    "addr:postcode":"17602",
    "addr:street":"Millport Rd",
    "iso:country":"US",
    "sg:address":"1945 Millport Rd",
    "sg:city":"Lancaster",
    "sg:classifiers":[
        {
            "category":"Building & Trades",
            "subcategory":"Landscaping Services",
            "type":"Services"
        }
    ],
    "sg:phone":"+1 717 394 9988",
    "sg:postcode":"17602",
    "sg:province":"PA",
    "sg:tags":[
        "landscape",
        "contractor"
    ],
    "wof:name":"Season's Image",
    "wof:placetype":"venue"
},
  "geometry": {"coordinates":[-76.248823,40.027136],"type":"Point"}
}