{
  "type": "Feature",
  "properties": {
    "addr:full":"1001 Old Clairton Rd Clairton PA 15025",
    "addr:housenumber":"1001",
    "addr:postcode":"15025",
    "addr:street":"Old Clairton Rd",
    "iso:country":"US",
    "sg:address":"1001 Old Clairton Rd",
    "sg:city":"Clairton",
    "sg:classifiers":[
        {
            "category":"Retail",
            "subcategory":"Auto Rental",
            "type":"Services"
        }
    ],
    "sg:phone":"+1 412 466 5120",
    "sg:postcode":"15025",
    "sg:province":"PA",
    "sg:tags":[
        "renting",
        "automobile"
    ],
    "wof:name":"Avis Rent A Car",
    "wof:placetype":"venue"
},
  "geometry": {"coordinates":[-79.935965,40.298065],"type":"Point"}
}