{
  "type": "Feature",
  "properties": {
    "iso:country":"US",
    "sg:address":"33 W Pleasant St",
    "sg:city":"Corry",
    "sg:classifiers":[
        {
            "category":"Organizations",
            "subcategory":"Religious Organization",
            "type":"Services"
        }
    ],
    "sg:phone":"+1 814 664 9187",
    "sg:postcode":"16407",
    "sg:province":"PA",
    "sg:tags":[
        "church"
    ],
    "wof:name":"St Elizabeth Parish Ctr",
    "wof:placetype":"venue"
},
  "geometry": {"coordinates":[-79.640227,41.918744],"type":"Point"}
}