{
  "type": "Feature",
  "properties": {
    "iso:country":"US",
    "sg:address":"621 Goucher St",
    "sg:city":"Johnstown",
    "sg:classifiers":[
        {
            "category":"Arts & Performance",
            "subcategory":"Theater",
            "type":"Entertainment"
        }
    ],
    "sg:phone":"+1 814 255 1371",
    "sg:postcode":"15905",
    "sg:province":"PA",
    "sg:tags":[
        "musician"
    ],
    "wof:name":"Musicians Union Local",
    "wof:placetype":"venue"
},
  "geometry": {"coordinates":[-78.94077,40.298105],"type":"Point"}
}