{
  "type": "Feature",
  "properties": {
    "addr:full":"1300 Brinton Rd Pittsburgh PA 15221",
    "addr:housenumber":"1300",
    "addr:postcode":"15221",
    "addr:street":"Brinton Rd",
    "iso:country":"US",
    "sg:address":"1300 Brinton Rd",
    "sg:city":"Pittsburgh",
    "sg:classifiers":[
        {
            "category":"Government",
            "subcategory":"Police Station",
            "type":"Public Place"
        }
    ],
    "sg:phone":"+1   ",
    "sg:postcode":"15221",
    "sg:province":"PA",
    "sg:tags":[
        "protection"
    ],
    "wof:name":"Police Department",
    "wof:placetype":"venue"
},
  "geometry": {"coordinates":[-79.862053,40.421814],"type":"Point"}
}