{
  "type": "Feature",
  "properties": {
    "iso:country":"US",
    "sg:address":"100 Lackawanna Ave",
    "sg:city":"Scranton",
    "sg:classifiers":[
        {
            "category":"Government",
            "subcategory":"Office",
            "type":"Public Place"
        }
    ],
    "sg:phone":"+1 570 963 4864",
    "sg:postcode":"18503",
    "sg:province":"PA",
    "sg:website":"www.dos.state.pa.us",
    "wof:name":"Commonwealth Dept Of State",
    "wof:placetype":"venue"
},
  "geometry": {"coordinates":[-75.669527,41.409589],"type":"Point"}
}