{
  "type": "Feature",
  "properties": {
    "iso:country":"US",
    "sg:address":"704 Sansom St",
    "sg:city":"Philadelphia",
    "sg:classifiers":[
        {
            "category":"Shopping",
            "subcategory":"Jewelry",
            "type":"Retail Goods"
        }
    ],
    "sg:phone":"+1 215 625 0504",
    "sg:postcode":"19106",
    "sg:province":"PA",
    "sg:tags":[
        "jeweler"
    ],
    "wof:name":"Joan Strott-Alvini",
    "wof:placetype":"venue"
},
  "geometry": {"coordinates":[-75.154084,39.948713],"type":"Point"}
}