{
  "type": "Feature",
  "properties": {
    "addr:full":"8929 Somerset Pike Boswell PA 15531",
    "addr:housenumber":"8929",
    "addr:postcode":"15531",
    "addr:street":"Somerset Pike",
    "iso:country":"US",
    "sg:address":"8929 Somerset Pike",
    "sg:city":"Boswell",
    "sg:classifiers":[
        {
            "category":"Wholesale",
            "subcategory":"Plants",
            "type":"Manufacturing & Wholesale Goods"
        },
        {
            "category":"Shopping",
            "type":"Retail Goods"
        }
    ],
    "sg:phone":"+1 814 629 6708",
    "sg:postcode":"15531",
    "sg:province":"PA",
    "sg:tags":[
        "florist",
        "flower",
        "tree",
        "artificial",
        "supply"
    ],
    "wof:name":"Donna's Weed Barn",
    "wof:placetype":"venue"
},
  "geometry": {"coordinates":[-79.088207,40.126622],"type":"Point"}
}