{
  "type": "Feature",
  "properties": {
    "addr:full":"13 Baltimore St Glen Rock PA 17327",
    "addr:housenumber":"13",
    "addr:postcode":"17327",
    "addr:street":"Baltimore St",
    "iso:country":"US",
    "sg:address":"13 Baltimore St",
    "sg:city":"Glen Rock",
    "sg:classifiers":[
        {
            "category":"Government",
            "subcategory":"Office",
            "type":"Public Place"
        }
    ],
    "sg:phone":"+1 717 235 3206",
    "sg:postcode":"17327",
    "sg:province":"PA",
    "sg:tags":[
        "village"
    ],
    "wof:name":"Glen Rock Borough Municipal",
    "wof:placetype":"venue"
},
  "geometry": {"coordinates":[-76.72946,39.792984],"type":"Point"}
}