{
  "type": "Feature",
  "properties": {
    "addr:full":"4110 Brighton Rd Pittsburgh PA 15212",
    "addr:housenumber":"4110",
    "addr:postcode":"15212",
    "addr:street":"Brighton Rd",
    "iso:country":"US",
    "sg:address":"4110 Brighton Rd",
    "sg:city":"Pittsburgh",
    "sg:classifiers":[
        {
            "category":"Food & Beverages",
            "subcategory":"Groceries & Convenience Stores",
            "type":"Retail Goods"
        }
    ],
    "sg:phone":"+1 412 761 2240",
    "sg:postcode":"15212",
    "sg:province":"PA",
    "wof:name":"Giant Eagle",
    "wof:placetype":"venue"
},
  "geometry": {"coordinates":[-80.04509,40.489926],"type":"Point"}
}