{
  "type": "Feature",
  "properties": {
    "iso:country":"US",
    "sg:address":"314 W Main St",
    "sg:city":"Elizabethville",
    "sg:classifiers":[
        {
            "category":"Shopping",
            "subcategory":"Florist",
            "type":"Retail Goods"
        }
    ],
    "sg:phone":"+1 717 362 4060",
    "sg:postcode":"17023",
    "sg:province":"PA",
    "sg:tags":[
        "shop",
        "gift"
    ],
    "sg:website":"www.forever1.com",
    "wof:name":"Forever Yours",
    "wof:placetype":"venue"
},
  "geometry": {"coordinates":[-76.81982499999999,40.547667],"type":"Point"}
}