{
  "type": "Feature",
  "properties": {
    "iso:country":"US",
    "sg:address":"1939 W 8th St",
    "sg:city":"Erie",
    "sg:classifiers":[
        {
            "category":"Food & Beverages",
            "subcategory":"Groceries & Convenience Stores",
            "type":"Retail Goods"
        }
    ],
    "sg:phone":"+1 814 456 4131",
    "sg:postcode":"16505",
    "sg:province":"PA",
    "wof:name":"Country Fair 1",
    "wof:placetype":"venue"
},
  "geometry": {"coordinates":[-80.12775000000001,42.111259],"type":"Point"}
}