{
  "type": "Feature",
  "properties": {
    "iso:country":"US",
    "sg:address":"210 S 3rd St",
    "sg:city":"North Wales",
    "sg:classifiers":[
        {
            "category":"Manufacturing",
            "subcategory":"Electronics",
            "type":"Manufacturing & Wholesale Goods"
        }
    ],
    "sg:phone":"+1 215 699 2060",
    "sg:postcode":"19454",
    "sg:province":"PA",
    "sg:tags":[
        "equipment",
        "builder",
        "designer",
        "electronic"
    ],
    "sg:website":"www.apogeelabs.com",
    "wof:name":"Apogee Labs Inc",
    "wof:placetype":"venue"
},
  "geometry": {"coordinates":[-75.27553399999999,40.21146],"type":"Point"}
}