{
  "type": "Feature",
  "properties": {
    "iso:country":"US",
    "sg:address":"4535 Peoples Rd",
    "sg:city":"Pittsburgh",
    "sg:classifiers":[
        {
            "category":"Mining & Drilling",
            "type":"Manufacturing & Wholesale Goods"
        },
        {
            "category":"Building & Trades",
            "subcategory":"Landscaping Services",
            "type":"Services"
        }
    ],
    "sg:phone":"+1 412 939 3675",
    "sg:postcode":"15237",
    "sg:province":"PA",
    "sg:tags":[
        "stone",
        "landscape"
    ],
    "wof:name":"Dragun's Landscape Supply Inc",
    "wof:placetype":"venue"
},
  "geometry": {"coordinates":[-80.00227599999999,40.502145],"type":"Point"}
}