{
  "type": "Feature",
  "properties": {
    "addr:full":"153 Schwitter Ave Pittsburgh PA 15229",
    "addr:housenumber":"153",
    "addr:postcode":"15229",
    "addr:street":"Schwitter Ave",
    "iso:country":"US",
    "sg:address":"153 Schwitter Ave",
    "sg:city":"Pittsburgh",
    "sg:classifiers":[
        {
            "category":"Building & Trades",
            "subcategory":"Electrical",
            "type":"Services"
        }
    ],
    "sg:phone":"+1   ",
    "sg:postcode":"15229",
    "sg:province":"PA",
    "sg:tags":[
        "electrical",
        "contractor"
    ],
    "wof:name":"Shaughnessy Electric",
    "wof:placetype":"venue"
},
  "geometry": {"coordinates":[-80.032287,40.524108],"type":"Point"}
}