{
  "type": "Feature",
  "properties": {
    "addr:full":"532 Brittany Dr State College PA 16803",
    "addr:housenumber":"532",
    "addr:postcode":"16803",
    "addr:street":"Brittany Dr",
    "iso:country":"US",
    "sg:address":"532 Brittany Dr",
    "sg:city":"State College",
    "sg:classifiers":[
        {
            "category":"Health Services",
            "subcategory":"Doctor",
            "type":"Services"
        }
    ],
    "sg:phone":"+1 814 238 3803",
    "sg:postcode":"16803",
    "sg:province":"PA",
    "sg:tags":[
        "dentist"
    ],
    "wof:name":"Hughes Paul R P DDS",
    "wof:placetype":"venue"
},
  "geometry": {"coordinates":[-77.91045,40.801532],"type":"Point"}
}