{
  "type": "Feature",
  "properties": {
    "iso:country":"US",
    "sg:address":"1160 Swedesford Rd",
    "sg:city":"Berwyn",
    "sg:classifiers":[
        {
            "category":"Restaurant",
            "type":"Food & Drink"
        }
    ],
    "sg:phone":"+1 610 647 9094",
    "sg:postcode":"19312",
    "sg:province":"PA",
    "sg:tags":[
        "caterer"
    ],
    "wof:name":"Linnea's Cafe & Catering",
    "wof:placetype":"venue"
},
  "geometry": {"coordinates":[-75.464333,40.061965],"type":"Point"}
}