{
  "type": "Feature",
  "properties": {
    "iso:country":"US",
    "sg:address":"617 N 43rd St",
    "sg:city":"Philadelphia",
    "sg:classifiers":[
        {
            "category":"Social Services",
            "type":"Services"
        }
    ],
    "sg:phone":"+1   ",
    "sg:postcode":"19104",
    "sg:province":"PA",
    "wof:name":"Millcreek P A L Center",
    "wof:placetype":"venue"
},
  "geometry": {"coordinates":[-75.20904899999999,39.962656],"type":"Point"}
}