{
  "type": "Feature",
  "properties": {
    "iso:country":"US",
    "sg:address":"306 Colbert St",
    "sg:city":"Stroudsburg",
    "sg:classifiers":[
        {
            "category":"Professional",
            "subcategory":"Business Services",
            "type":"Services"
        }
    ],
    "sg:phone":"+1 570 476 4492",
    "sg:postcode":"18360",
    "sg:province":"PA",
    "wof:name":"Sew Art Enetrprises",
    "wof:placetype":"venue"
},
  "geometry": {"coordinates":[-75.18723199999999,40.984571],"type":"Point"}
}