{
  "type": "Feature",
  "properties": {
    "iso:country":"US",
    "sg:address":"1748 W Penn Pike",
    "sg:city":"New Ringgold",
    "sg:classifiers":[
        {
            "category":"Organizations",
            "subcategory":"Professional Association",
            "type":"Services"
        }
    ],
    "sg:phone":"+1 570 386 2233",
    "sg:postcode":"17960",
    "sg:province":"PA",
    "wof:name":"P M Assn",
    "wof:placetype":"venue"
},
  "geometry": {"coordinates":[-75.877156,40.73213],"type":"Point"}
}