{
  "type": "Feature",
  "properties": {
    "addr:full":"1042 W Elizabethtown Rd Manheim PA 17545",
    "addr:housenumber":"1042",
    "addr:postcode":"17545",
    "addr:street":"W Elizabethtown Rd",
    "iso:country":"US",
    "sg:address":"1042 W Elizabethtown Rd",
    "sg:city":"Manheim",
    "sg:phone":"+1   ",
    "sg:postcode":"17545",
    "sg:province":"PA",
    "sg:tags":[
        "farm",
        "field",
        "corn",
        "dairy",
        "crop"
    ],
    "wof:name":"Nevin Wenger",
    "wof:placetype":"venue"
},
  "geometry": {"coordinates":[-76.45181700000001,40.195029],"type":"Point"}
}