{
  "type": "Feature",
  "properties": {
    "iso:country":"US",
    "sg:address":"309 N 3rd St",
    "sg:city":"Clearfield",
    "sg:classifiers":[
        {
            "category":"Organizations",
            "subcategory":"Community Association",
            "type":"Services"
        }
    ],
    "sg:phone":"+1 814 765 2590",
    "sg:postcode":"16830",
    "sg:province":"PA",
    "sg:tags":[
        "club"
    ],
    "wof:name":"Veterans Of Foreign Wars",
    "wof:placetype":"venue"
},
  "geometry": {"coordinates":[-78.43624199999999,41.026333],"type":"Point"}
}