{
  "type": "Feature",
  "properties": {
    "iso:country":"US",
    "sg:address":"8747 Frankford Ave",
    "sg:city":"Philadelphia",
    "sg:classifiers":[
        {
            "category":"Restaurant",
            "type":"Food & Drink"
        }
    ],
    "sg:phone":"+1   ",
    "sg:postcode":"19136",
    "sg:province":"PA",
    "sg:tags":[
        "eating"
    ],
    "wof:name":"Lucias Restorante DItalia",
    "wof:placetype":"venue"
},
  "geometry": {"coordinates":[-75.012562,40.048471],"type":"Point"}
}