{
  "type": "Feature",
  "properties": {
    "addr:full":"301 Stevenson Blvd New Kensington PA 15068",
    "addr:housenumber":"301",
    "addr:postcode":"15068",
    "addr:street":"Stevenson Blvd",
    "iso:country":"US",
    "sg:address":"301 Stevenson Blvd",
    "sg:city":"New Kensington",
    "sg:classifiers":[
        {
            "category":"Retail",
            "subcategory":"Auto Repair",
            "type":"Services"
        }
    ],
    "sg:phone":"+1   ",
    "sg:postcode":"15068",
    "sg:province":"PA",
    "sg:tags":[
        "executive",
        "general"
    ],
    "wof:name":"City Streets Department Garage",
    "wof:placetype":"venue"
},
  "geometry": {"coordinates":[-79.75904,40.55543],"type":"Point"}
}