{
  "type": "Feature",
  "properties": {
    "addr:full":"115 N Main St Mercersburg PA 17236",
    "addr:housenumber":"115",
    "addr:postcode":"17236",
    "addr:street":"N Main St",
    "iso:country":"US",
    "sg:address":"115 N Main St",
    "sg:city":"Mercersburg",
    "sg:classifiers":[
        {
            "category":"Professional",
            "type":"Services"
        },
        {
            "category":"Bars & Pubs",
            "type":"Food & Drink"
        }
    ],
    "sg:phone":"+1 717 328 3437",
    "sg:postcode":"17236",
    "sg:province":"PA",
    "wof:name":"Rue's Inc",
    "wof:placetype":"venue"
},
  "geometry": {"coordinates":[-77.903778,39.830369],"type":"Point"}
}