{
  "type": "Feature",
  "properties": {
    "addr:full":"322 Boot Rd Downingtown PA 19335",
    "addr:housenumber":"322",
    "addr:postcode":"19335",
    "addr:street":"Boot Rd",
    "iso:country":"US",
    "sg:address":"322 Boot Rd",
    "sg:city":"Downingtown",
    "sg:classifiers":[
        {
            "category":"Utilities",
            "subcategory":"Fuel Oil & Lpg",
            "type":"Services"
        }
    ],
    "sg:phone":"+1 610 269 7900",
    "sg:postcode":"19335",
    "sg:province":"PA",
    "sg:tags":[
        "propane",
        "gas"
    ],
    "wof:name":"A County Propane Co",
    "wof:placetype":"venue"
},
  "geometry": {"coordinates":[-75.69502300000001,40.001436],"type":"Point"}
}