{
  "type": "Feature",
  "properties": {
    "iso:country":"US",
    "sg:address":"6800 Stenton Ave",
    "sg:city":"Philadelphia",
    "sg:classifiers":[
        {
            "category":"Professional",
            "subcategory":"Lawyer & Legal Services",
            "type":"Services"
        }
    ],
    "sg:phone":"+1   ",
    "sg:postcode":"19150",
    "sg:province":"PA",
    "wof:name":"Law Offices of Vincent Johnson",
    "wof:placetype":"venue"
},
  "geometry": {"coordinates":[-75.176526,40.065895],"type":"Point"}
}