{
  "type": "Feature",
  "properties": {
    "addr:full":"2 Avenue Elizabeth PA 15037",
    "addr:housenumber":"2",
    "addr:postcode":"15037",
    "addr:street":"Avenue",
    "iso:country":"US",
    "sg:address":"2 Avenue",
    "sg:city":"Elizabeth",
    "sg:classifiers":[
        {
            "category":"Shopping",
            "subcategory":"Jewelry",
            "type":"Retail Goods"
        }
    ],
    "sg:phone":"+1 412 384 8695",
    "sg:postcode":"15037",
    "sg:province":"PA",
    "wof:name":"Jewelry Station the",
    "wof:placetype":"venue"
},
  "geometry": {"coordinates":[-79.853104,40.268398],"type":"Point"}
}