{
  "type": "Feature",
  "properties": {
    "iso:country":"US",
    "sg:address":"1524 W College Ave",
    "sg:city":"State College",
    "sg:classifiers":[
        {
            "category":"Communications",
            "subcategory":"Television Station",
            "type":"Services"
        }
    ],
    "sg:phone":"+1 814 231 6397",
    "sg:postcode":"16801",
    "sg:province":"PA",
    "sg:tags":[
        "broadcasting",
        "co"
    ],
    "wof:name":"WJAC",
    "wof:placetype":"venue"
},
  "geometry": {"coordinates":[-77.878523,40.780986],"type":"Point"}
}