{
  "type": "Feature",
  "properties": {
    "iso:country":"US",
    "sg:address":"7106 Ridge Ave",
    "sg:city":"Philadelphia",
    "sg:classifiers":[
        {
            "category":"Shopping",
            "subcategory":"Discount & Variety Stores",
            "type":"Retail Goods"
        }
    ],
    "sg:phone":"+1 215 508 5336",
    "sg:postcode":"19128",
    "sg:province":"PA",
    "sg:website":"www.dollartree.com",
    "wof:name":"Dollar Tree",
    "wof:placetype":"venue"
},
  "geometry": {"coordinates":[-75.23295400000001,40.045844],"type":"Point"}
}