{
  "type": "Feature",
  "properties": {
    "addr:full":"5253 Pine St Philadelphia PA 19143",
    "addr:housenumber":"5253",
    "addr:postcode":"19143",
    "addr:street":"Pine St",
    "iso:country":"US",
    "sg:address":"5253 Pine St",
    "sg:city":"Philadelphia",
    "sg:classifiers":[
        {
            "category":"Building & Trades",
            "subcategory":"Plumbing",
            "type":"Services"
        }
    ],
    "sg:phone":"+1 215 471 0346",
    "sg:postcode":"19143",
    "sg:province":"PA",
    "sg:tags":[
        "plumber",
        "contractor"
    ],
    "wof:name":"Mas Plumbing & Heating",
    "wof:placetype":"venue"
},
  "geometry": {"coordinates":[-75.227898,39.953602],"type":"Point"}
}