{
  "type": "Feature",
  "properties": {
    "iso:country":"US",
    "sg:address":"3051 Green Pond Rd",
    "sg:city":"Easton",
    "sg:classifiers":[
        {
            "category":"Real Estate",
            "subcategory":"Developer",
            "type":"Services"
        }
    ],
    "sg:phone":"+1 610 253 2000",
    "sg:postcode":"18045",
    "sg:province":"PA",
    "sg:tags":[
        "cemetery"
    ],
    "wof:name":"Northampton Memorial Shrine",
    "wof:placetype":"venue"
},
  "geometry": {"coordinates":[-75.270822,40.68689],"type":"Point"}
}