{
  "type": "Feature",
  "properties": {
    "iso:country":"US",
    "sg:address":"1956 Pine Dr",
    "sg:city":"Lancaster",
    "sg:classifiers":[
        {
            "category":"Restaurant",
            "type":"Food & Drink"
        }
    ],
    "sg:phone":"+1   ",
    "sg:postcode":"17601",
    "sg:province":"PA",
    "sg:tags":[
        "eating"
    ],
    "wof:name":"Kitchen Source Inc",
    "wof:placetype":"venue"
},
  "geometry": {"coordinates":[-76.25522599999999,40.074418],"type":"Point"}
}