{
  "type": "Feature",
  "properties": {
    "iso:country":"US",
    "sg:address":"601 Wood St",
    "sg:city":"Pittsburgh",
    "sg:classifiers":[
        {
            "category":"Shopping",
            "type":"Retail Goods"
        }
    ],
    "sg:phone":"+1 412 471 5605",
    "sg:postcode":"15222",
    "sg:province":"PA",
    "sg:tags":[
        "art",
        "gallery"
    ],
    "sg:website":"woodstreetgalleries.org/",
    "wof:name":"Wood Street Galleries",
    "wof:placetype":"venue"
},
  "geometry": {"coordinates":[-79.99949599999999,40.442101],"type":"Point"}
}