{
  "type": "Feature",
  "properties": {
    "iso:country":"US",
    "sg:address":"328 Lincoln Ave",
    "sg:city":"Pittsburgh",
    "sg:classifiers":[
        {
            "category":"Education",
            "subcategory":"School",
            "type":"Public Place"
        }
    ],
    "sg:phone":"+1   ",
    "sg:postcode":"15206",
    "sg:province":"PA",
    "wof:name":"Lincoln School",
    "wof:placetype":"venue"
},
  "geometry": {"coordinates":[-79.91352999999999,40.460345],"type":"Point"}
}