{
  "type": "Feature",
  "properties": {
    "iso:country":"US",
    "sg:address":"218 S Main St",
    "sg:city":"Pittston",
    "sg:classifiers":[
        {
            "category":"Social Services",
            "subcategory":"Child Care",
            "type":"Services"
        }
    ],
    "sg:phone":"+1   ",
    "sg:postcode":"18640",
    "sg:province":"PA",
    "sg:tags":[
        "day"
    ],
    "wof:name":"Rose Nanny Child Care",
    "wof:placetype":"venue"
},
  "geometry": {"coordinates":[-75.795423,41.316826],"type":"Point"}
}