{
  "type": "Feature",
  "properties": {
    "iso:country":"US",
    "sg:address":"31 John Dyer Way",
    "sg:city":"Doylestown",
    "sg:classifiers":[
        {
            "category":"Food & Beverages",
            "subcategory":"Groceries & Convenience Stores",
            "type":"Retail Goods"
        }
    ],
    "sg:phone":"+1 215 348 4455",
    "sg:postcode":"18901",
    "sg:province":"PA",
    "wof:name":"Beatreme Foods Inc",
    "wof:placetype":"venue"
},
  "geometry": {"coordinates":[-75.121498,40.344601],"type":"Point"}
}