{
  "type": "Feature",
  "properties": {
    "addr:full":"1005 W 26th St Erie PA 16508",
    "addr:housenumber":"1005",
    "addr:postcode":"16508",
    "addr:street":"W 26Th St",
    "iso:country":"US",
    "sg:address":"1005 W 26th St",
    "sg:city":"Erie",
    "sg:classifiers":[
        {
            "category":"Retail",
            "subcategory":"Auto Repair",
            "type":"Services"
        }
    ],
    "sg:phone":"+1   ",
    "sg:postcode":"16508",
    "sg:province":"PA",
    "sg:tags":[
        "general",
        "supply"
    ],
    "wof:name":"Franks Auto & 4 X 4 Center",
    "wof:placetype":"venue"
},
  "geometry": {"coordinates":[-80.096569,42.103378],"type":"Point"}
}