{
  "type": "Feature",
  "properties": {
    "addr:full":"9042 Roberts Hollow Rd Elizabeth PA 15037",
    "addr:housenumber":"9042",
    "addr:postcode":"15037",
    "addr:street":"Roberts Hollow Rd",
    "iso:country":"US",
    "sg:address":"9042 Roberts Hollow Rd",
    "sg:city":"Elizabeth",
    "sg:classifiers":[
        {
            "category":"Shopping",
            "subcategory":"Bicycles & Sporting Goods",
            "type":"Retail Goods"
        }
    ],
    "sg:phone":"+1 412 384 2205",
    "sg:postcode":"15037",
    "sg:province":"PA",
    "sg:tags":[
        "bait",
        "fishing"
    ],
    "wof:name":"Orchard Lake Fisheries Inc",
    "wof:placetype":"venue"
},
  "geometry": {"coordinates":[-79.877668,40.249487],"type":"Point"}
}