{
  "type": "Feature",
  "properties": {
    "addr:full":"586 E Broad St Souderton PA 18964",
    "addr:housenumber":"586",
    "addr:postcode":"18964",
    "addr:street":"E Broad St",
    "iso:country":"US",
    "sg:address":"586 E Broad St",
    "sg:city":"Souderton",
    "sg:classifiers":[
        {
            "category":"Retail",
            "subcategory":"Self-service Laundry",
            "type":"Services"
        }
    ],
    "sg:phone":"+1   ",
    "sg:postcode":"18964",
    "sg:province":"PA",
    "sg:tags":[
        "dry",
        "plant",
        "coin",
        "cleaning"
    ],
    "wof:name":"Country Fresh",
    "wof:placetype":"venue"
},
  "geometry": {"coordinates":[-75.315989,40.312015],"type":"Point"}
}