{
  "type": "Feature",
  "properties": {
    "iso:country":"US",
    "sg:address":"4534 Hedge St",
    "sg:city":"Philadelphia",
    "sg:classifiers":[
        {
            "category":"Wholesale",
            "subcategory":"Auto Parts",
            "type":"Manufacturing & Wholesale Goods"
        }
    ],
    "sg:phone":"+1 215 533 1233",
    "sg:postcode":"19124",
    "sg:province":"PA",
    "sg:tags":[
        "used"
    ],
    "wof:name":"KARR Parts",
    "wof:placetype":"venue"
},
  "geometry": {"coordinates":[-75.08336,40.013547],"type":"Point"}
}