{
  "type": "Feature",
  "properties": {
    "addr:full":"35 Oak Dr Mountain Top PA 18707",
    "addr:housenumber":"35",
    "addr:postcode":"18707",
    "addr:street":"Oak Dr",
    "iso:country":"US",
    "sg:address":"35 Oak Dr",
    "sg:city":"Mountain Top",
    "sg:classifiers":[
        {
            "category":"Professional",
            "type":"Services"
        }
    ],
    "sg:phone":"+1   ",
    "sg:postcode":"18707",
    "sg:province":"PA",
    "wof:name":"Kennard Johnston",
    "wof:placetype":"venue"
},
  "geometry": {"coordinates":[-75.90970799999999,41.14967],"type":"Point"}
}