{
  "type": "Feature",
  "properties": {
    "iso:country":"US",
    "sg:address":"325 Smith St",
    "sg:city":"Scranton",
    "sg:classifiers":[
        {
            "category":"Building & Trades",
            "subcategory":"Construction",
            "type":"Services"
        }
    ],
    "sg:phone":"+1   ",
    "sg:postcode":"18512",
    "sg:province":"PA",
    "sg:tags":[
        "cleaning",
        "exterior"
    ],
    "wof:name":"Underpressure Power Washers",
    "wof:placetype":"venue"
},
  "geometry": {"coordinates":[-75.62343,41.415454],"type":"Point"}
}