{
  "type": "Feature",
  "properties": {
    "addr:full":"2500 S 6th St Philadelphia PA 19148",
    "addr:housenumber":"2500",
    "addr:postcode":"19148",
    "addr:street":"S 6Th St",
    "iso:country":"US",
    "sg:address":"2500 S 6th St",
    "sg:city":"Philadelphia",
    "sg:classifiers":[
        {
            "category":"Wholesale",
            "subcategory":"Machinery & Supplies",
            "type":"Manufacturing & Wholesale Goods"
        }
    ],
    "sg:phone":"+1   ",
    "sg:postcode":"19148",
    "sg:province":"PA",
    "sg:tags":[
        "equipment",
        "establishment"
    ],
    "wof:name":"M P Discounts",
    "wof:placetype":"venue"
},
  "geometry": {"coordinates":[-75.15797999999999,39.916473],"type":"Point"}
}