{
  "type": "Feature",
  "properties": {
    "addr:full":"429 Scranton Carbondale Hwy Scranton PA 18508",
    "addr:housenumber":"429",
    "addr:postcode":"18508",
    "addr:street":"Scranton Carbondale Hwy",
    "iso:country":"US",
    "sg:address":"429 Scranton Carbondale Hwy",
    "sg:city":"Scranton",
    "sg:classifiers":[
        {
            "category":"Home & Garden",
            "subcategory":"Household Appliances",
            "type":"Retail Goods"
        }
    ],
    "sg:phone":"+1 570 344 9515",
    "sg:postcode":"18508",
    "sg:province":"PA",
    "sg:tags":[
        "machine",
        "sewing"
    ],
    "wof:name":"Viking Sewing Gallery",
    "wof:placetype":"venue"
},
  "geometry": {"coordinates":[-75.65422700000001,41.462721],"type":"Point"}
}