{
  "type": "Feature",
  "properties": {
    "addr:full":"113 N Main St Zelienople PA 16063",
    "addr:housenumber":"113",
    "addr:postcode":"16063",
    "addr:street":"N Main St",
    "iso:country":"US",
    "sg:address":"113 N Main St",
    "sg:city":"Zelienople",
    "sg:classifiers":[
        {
            "category":"Insurance",
            "subcategory":"Hazard Insurance",
            "type":"Services"
        },
        {
            "category":"Insurance",
            "subcategory":"Insurance Agent",
            "type":"Services"
        },
        {
            "category":"Insurance",
            "subcategory":"Life Insurance",
            "type":"Services"
        },
        {
            "category":"Insurance",
            "subcategory":"Title Insurance",
            "type":"Services"
        }
    ],
    "sg:phone":"+1 724 473 0406",
    "sg:postcode":"16063",
    "sg:province":"PA",
    "sg:tags":[
        "auto",
        "homeowner"
    ],
    "sg:website":"http://www.nationwide.com/agent/Zelienople-PENNSYLVANIA-insurance-agent/jamiekerr/office.html",
    "wof:name":"Jamie L Kerr Agency - Nationwide Insurance",
    "wof:placetype":"venue"
},
  "geometry": {"coordinates":[-80.13708699999999,40.795867],"type":"Point"}
}