{
  "type": "Feature",
  "properties": {
    "iso:country":"US",
    "sg:address":"4874 Old Bethlehem Pike",
    "sg:city":"Bethlehem",
    "sg:classifiers":[
        {
            "category":"Professional",
            "type":"Services"
        }
    ],
    "sg:phone":"+1   ",
    "sg:postcode":"18015",
    "sg:province":"PA",
    "wof:name":"Southern Craftsman Co",
    "wof:placetype":"venue"
},
  "geometry": {"coordinates":[-75.39399899999999,40.556712],"type":"Point"}
}