{
  "type": "Feature",
  "properties": {
    "iso:country":"US",
    "sg:address":"568 Hazle St",
    "sg:city":"Wilkes Barre",
    "sg:classifiers":[
        {
            "category":"Wholesale",
            "subcategory":"Machinery & Supplies",
            "type":"Manufacturing & Wholesale Goods"
        }
    ],
    "sg:phone":"+1 570 822 6165",
    "sg:postcode":"18702",
    "sg:province":"PA",
    "sg:tags":[
        "distributor",
        "product",
        "upholstery",
        "foam"
    ],
    "sg:website":"www.efoamstore.com",
    "wof:name":"Smith Co",
    "wof:placetype":"venue"
},
  "geometry": {"coordinates":[-75.89358199999999,41.22641],"type":"Point"}
}