{
  "type": "Feature",
  "properties": {
    "iso:country":"US",
    "sg:address":"279 Crawford Dr",
    "sg:city":"Hermitage",
    "sg:classifiers":[
        {
            "category":"Farming",
            "subcategory":"Livestock Farm",
            "type":"Manufacturing & Wholesale Goods"
        }
    ],
    "sg:phone":"+1   ",
    "sg:postcode":"16148",
    "sg:province":"PA",
    "sg:tags":[
        "beef",
        "feedlot",
        "cattle"
    ],
    "wof:name":"Joe Plawky",
    "wof:placetype":"venue"
},
  "geometry": {"coordinates":[-80.513294,41.245118],"type":"Point"}
}