{
  "type": "Feature",
  "properties": {
    "addr:full":"301 1st St Butler PA 16001",
    "addr:housenumber":"301",
    "addr:postcode":"16001",
    "addr:street":"1St St",
    "iso:country":"US",
    "sg:address":"301 1st St",
    "sg:city":"Butler",
    "sg:classifiers":[
        {
            "category":"Real Estate",
            "subcategory":"Real Estate Operator",
            "type":"Services"
        }
    ],
    "sg:phone":"+1   ",
    "sg:postcode":"16001",
    "sg:province":"PA",
    "sg:tags":[
        "building",
        "nonresidential"
    ],
    "wof:name":"Mch Associates",
    "wof:placetype":"venue"
},
  "geometry": {"coordinates":[-79.885499,40.8644],"type":"Point"}
}