{
  "type": "Feature",
  "properties": {
    "iso:country":"US",
    "sg:address":"1200 New Rodgers Rd",
    "sg:city":"Bristol",
    "sg:classifiers":[
        {
            "category":"Health Services",
            "subcategory":"Nursing And Care Facility",
            "type":"Services"
        }
    ],
    "sg:phone":"+1 215 781 3985",
    "sg:postcode":"19007",
    "sg:province":"PA",
    "sg:tags":[
        "home",
        "convalescent"
    ],
    "wof:name":"Sauers Consultation & Svc",
    "wof:placetype":"venue"
},
  "geometry": {"coordinates":[-74.878854,40.110999],"type":"Point"}
}