{
  "type": "Feature",
  "properties": {
    "addr:full":"1807 Cherry Ave Easton PA 18040",
    "addr:housenumber":"1807",
    "addr:postcode":"18040",
    "addr:street":"Cherry Ave",
    "iso:country":"US",
    "sg:address":"1807 Cherry Ave",
    "sg:city":"Easton",
    "sg:classifiers":[
        {
            "category":"Retail",
            "subcategory":"Auto Repair",
            "type":"Services"
        }
    ],
    "sg:phone":"+1   ",
    "sg:postcode":"18040",
    "sg:province":"PA",
    "sg:tags":[
        "general"
    ],
    "wof:name":"Kleins Auto Inc",
    "wof:placetype":"venue"
},
  "geometry": {"coordinates":[-75.244029,40.714487],"type":"Point"}
}