{
  "type": "Feature",
  "properties": {
    "addr:full":"194 Rolling Rd Bala Cynwyd PA 19004",
    "addr:housenumber":"194",
    "addr:postcode":"19004",
    "addr:street":"Rolling Rd",
    "iso:country":"US",
    "sg:address":"194 Rolling Rd",
    "sg:city":"Bala Cynwyd",
    "sg:classifiers":[
        {
            "category":"Health Services",
            "subcategory":"Health Practitioner",
            "type":"Services"
        }
    ],
    "sg:phone":"+1   ",
    "sg:postcode":"19004",
    "sg:province":"PA",
    "wof:name":"Allan N Tanenbaum PHD",
    "wof:placetype":"venue"
},
  "geometry": {"coordinates":[-75.230356,40.015221],"type":"Point"}
}