{
  "type": "Feature",
  "properties": {
    "iso:country":"US",
    "sg:address":"10 Fairlane Rd",
    "sg:city":"Reading",
    "sg:classifiers":[
        {
            "category":"Government",
            "subcategory":"Court House",
            "type":"Public Place"
        }
    ],
    "sg:phone":"+1   ",
    "sg:postcode":"19606",
    "sg:province":"PA",
    "sg:tags":[
        "state"
    ],
    "wof:name":"Magisterial District 23-2-03",
    "wof:placetype":"venue"
},
  "geometry": {"coordinates":[-75.854021,40.302676],"type":"Point"}
}