{
  "type": "Feature",
  "properties": {
    "addr:full":"11 Academy Rd Cogan Station PA 17728",
    "addr:housenumber":"11",
    "addr:postcode":"17728",
    "addr:street":"Academy Rd Cogan Station",
    "iso:country":"US",
    "sg:address":"11 Academy Rd",
    "sg:city":"Cogan Station",
    "sg:classifiers":[
        {
            "category":"Wholesale",
            "subcategory":"Stationery",
            "type":"Manufacturing & Wholesale Goods"
        }
    ],
    "sg:phone":"+1   ",
    "sg:postcode":"17728",
    "sg:province":"PA",
    "sg:tags":[
        "custom",
        "printed",
        "specialty"
    ],
    "wof:name":"Janway Company",
    "wof:placetype":"venue"
},
  "geometry": {"coordinates":[-77.026854,41.3189],"type":"Point"}
}