{
  "type": "Feature",
  "properties": {
    "iso:country":"US",
    "sg:address":"7940 Saltsburg Rd",
    "sg:city":"Pittsburgh",
    "sg:classifiers":[
        {
            "category":"Insurance",
            "subcategory":"Hazard Insurance",
            "type":"Services"
        }
    ],
    "sg:phone":"+1 412 793 8200",
    "sg:postcode":"15239",
    "sg:province":"PA",
    "wof:name":"Athena Financial Group Inc",
    "wof:placetype":"venue"
},
  "geometry": {"coordinates":[-79.75772600000001,40.478271],"type":"Point"}
}