{
  "type": "Feature",
  "properties": {
    "iso:country":"US",
    "sg:address":"140 Allegheny River Blvd ",
    "sg:city":"Verona",
    "sg:classifiers":[
        {
            "category":"Restaurant",
            "type":"Food & Drink"
        }
    ],
    "sg:menulink":"http://www.allmenus.com/pa/verona/287174-dragon-chinese-restaurant/menu/",
    "sg:phone":"+1 412 828 4881",
    "sg:postcode":"15147",
    "sg:province":"PA",
    "sg:tags":[
        "asian",
        "chinese"
    ],
    "wof:name":"Dragon Chinese Restaurant",
    "wof:placetype":"venue"
},
  "geometry": {"coordinates":[-79.843324,40.500719],"type":"Point"}
}