{
  "type": "Feature",
  "properties": {
    "iso:country":"US",
    "sg:address":"1239 Lois Rd",
    "sg:city":"Ambler",
    "sg:classifiers":[
        {
            "category":"Shopping",
            "subcategory":"Bicycles & Sporting Goods",
            "type":"Retail Goods"
        }
    ],
    "sg:phone":"+1   ",
    "sg:postcode":"19002",
    "sg:province":"PA",
    "wof:name":"Martins Dam Club",
    "wof:placetype":"venue"
},
  "geometry": {"coordinates":[-75.211736,40.202254],"type":"Point"}
}