{
  "type": "Feature",
  "properties": {
    "iso:country":"US",
    "sg:address":"3286 Babcock Blvd ",
    "sg:city":"Pittsburgh",
    "sg:classifiers":[
        {
            "category":"Restaurant",
            "type":"Food & Drink"
        }
    ],
    "sg:menulink":"http://www.allmenus.com/pa/ross/289694-large-plain/menu/",
    "sg:phone":"+1 412 364 4565",
    "sg:postcode":"15237",
    "sg:province":"PA",
    "sg:tags":[
        "american",
        "pizza"
    ],
    "wof:name":"Large Plain",
    "wof:placetype":"venue"
},
  "geometry": {"coordinates":[-80.017684,40.530901],"type":"Point"}
}