{
  "type": "Feature",
  "properties": {
    "addr:full":"22 Cumberland St Lebanon PA 17042",
    "addr:housenumber":"22",
    "addr:postcode":"17042",
    "addr:street":"Cumberland St",
    "iso:country":"US",
    "sg:address":"22 Cumberland St",
    "sg:city":"Lebanon",
    "sg:classifiers":[
        {
            "category":"Shopping",
            "subcategory":"Shoes",
            "type":"Retail Goods"
        }
    ],
    "sg:phone":"+1 717 277 0920",
    "sg:postcode":"17042",
    "sg:province":"PA",
    "wof:name":"Shoe Department",
    "wof:placetype":"venue"
},
  "geometry": {"coordinates":[-76.41186399999999,40.340317],"type":"Point"}
}