{
  "type": "Feature",
  "properties": {
    "addr:full":"154 Barkley Rd Clarksburg PA 15725",
    "addr:housenumber":"154",
    "addr:postcode":"15725",
    "addr:street":"Barkley Rd",
    "iso:country":"US",
    "sg:address":"154 Barkley Rd",
    "sg:city":"Clarksburg",
    "sg:classifiers":[
        {
            "category":"Organizations",
            "subcategory":"Religious Organization",
            "type":"Services"
        }
    ],
    "sg:phone":"+1 724 459 9660",
    "sg:postcode":"15725",
    "sg:province":"PA",
    "sg:tags":[
        "church"
    ],
    "wof:name":"Lewisville-Ebenezer Presby Ch",
    "wof:placetype":"venue"
},
  "geometry": {"coordinates":[-79.32425000000001,40.496515],"type":"Point"}
}