{
  "type": "Feature",
  "properties": {
    "iso:country":"US",
    "sg:address":"751 Ridge Ln",
    "sg:city":"Warminster",
    "sg:classifiers":[
        {
            "category":"Professional",
            "subcategory":"Accounting & Tax Preparation",
            "type":"Services"
        }
    ],
    "sg:phone":"+1   ",
    "sg:postcode":"18974",
    "sg:province":"PA",
    "wof:name":"J Lauf Tax Acct Svcs",
    "wof:placetype":"venue"
},
  "geometry": {"coordinates":[-75.046606,40.197323],"type":"Point"}
}