{
  "type": "Feature",
  "properties": {
    "iso:country":"US",
    "sg:address":"2135 Ritner Hwy",
    "sg:city":"Carlisle",
    "sg:classifiers":[
        {
            "category":"Social Services",
            "subcategory":"Child Care",
            "type":"Services"
        }
    ],
    "sg:phone":"+1 717 249 1806",
    "sg:postcode":"17015",
    "sg:province":"PA",
    "wof:name":"Little Lamb's Daycare Ctr",
    "wof:placetype":"venue"
},
  "geometry": {"coordinates":[-77.263659,40.181041],"type":"Point"}
}