{
  "type": "Feature",
  "properties": {
    "iso:country":"US",
    "sg:address":"315 N Charlotte St",
    "sg:city":"Lancaster",
    "sg:classifiers":[
        {
            "category":"Manufacturing",
            "subcategory":"Glass & Minerals",
            "type":"Manufacturing & Wholesale Goods"
        }
    ],
    "sg:phone":"+1   ",
    "sg:postcode":"17603",
    "sg:province":"PA",
    "sg:tags":[
        "ready",
        "concrete",
        "mfg"
    ],
    "wof:name":"Mix USA",
    "wof:placetype":"venue"
},
  "geometry": {"coordinates":[-76.3135,40.042911],"type":"Point"}
}