{
  "type": "Feature",
  "properties": {
    "iso:country":"US",
    "sg:address":"221 Jalyn Dr",
    "sg:city":"New Holland",
    "sg:classifiers":[
        {
            "category":"Retail",
            "subcategory":"Repair Shop",
            "type":"Services"
        },
        {
            "category":"Building & Trades",
            "subcategory":"Construction",
            "type":"Services"
        }
    ],
    "sg:phone":"+1 717 355 0779",
    "sg:postcode":"17557",
    "sg:province":"PA",
    "sg:tags":[
        "welding",
        "general",
        "fabricating"
    ],
    "wof:name":"Meadowcreek Welding LLC",
    "wof:placetype":"venue"
},
  "geometry": {"coordinates":[-76.08834400000001,40.091104],"type":"Point"}
}