{
  "type": "Feature",
  "properties": {
    "addr:full":"15 Mystic Ln Malvern PA 19355",
    "addr:housenumber":"15",
    "addr:postcode":"19355",
    "addr:street":"Mystic Ln",
    "iso:country":"US",
    "sg:address":"15 Mystic Ln",
    "sg:city":"Malvern",
    "sg:classifiers":[
        {
            "category":"Banks & Credit Unions",
            "subcategory":"Investment Brokerage",
            "type":"Services"
        }
    ],
    "sg:phone":"+1 610 722 0900",
    "sg:postcode":"19355",
    "sg:province":"PA",
    "sg:tags":[
        "advisory",
        "financial"
    ],
    "sg:website":"www.morriscapitaladvisors.com",
    "wof:name":"Morris Capital Advisors Inc",
    "wof:placetype":"venue"
},
  "geometry": {"coordinates":[-75.57749800000001,40.03255],"type":"Point"}
}