{
  "type": "Feature",
  "properties": {
    "iso:country":"US",
    "sg:address":"105 E Market St",
    "sg:city":"Williamstown",
    "sg:classifiers":[
        {
            "category":"Food & Beverages",
            "subcategory":"Liquor & Beverages",
            "type":"Retail Goods"
        },
        {
            "category":"Wholesale",
            "subcategory":"Wine & Distilled Alcoholic Beverages",
            "type":"Manufacturing & Wholesale Goods"
        }
    ],
    "sg:phone":"+1 717 647 7421",
    "sg:postcode":"17098",
    "sg:province":"PA",
    "sg:tags":[
        "broker"
    ],
    "wof:name":"Main Street Wine Racks",
    "wof:placetype":"venue"
},
  "geometry": {"coordinates":[-76.617822,40.58004],"type":"Point"}
}