{
  "type": "Feature",
  "properties": {
    "addr:full":"479 Austin Blvd  Acme PA 15610",
    "addr:housenumber":"479",
    "addr:postcode":"15610",
    "addr:street":"Austin Blvd",
    "iso:country":"US",
    "sg:address":"479 Austin Blvd ",
    "sg:city":"Acme",
    "sg:classifiers":[
        {
            "category":"Cafe",
            "type":"Food & Drink"
        }
    ],
    "sg:menulink":"http://www.allmenus.com/pa/donegal/287696-rodney-corner-cafe/menu/",
    "sg:phone":"+1 724 423 9789",
    "sg:postcode":"15610",
    "sg:province":"PA",
    "sg:tags":[
        "soup",
        "american",
        "sandwich",
        "salad"
    ],
    "wof:name":"Rodney Corner Cafe",
    "wof:placetype":"venue"
},
  "geometry": {"coordinates":[-79.39336,40.167369],"type":"Point"}
}