{
  "type": "Feature",
  "properties": {
    "iso:country":"US",
    "sg:address":"1414 Bristol Rd",
    "sg:city":"Morrisville",
    "sg:classifiers":[
        {
            "category":"Retail",
            "subcategory":"Repair Shop",
            "type":"Services"
        }
    ],
    "sg:phone":"+1 215 736 3100",
    "sg:postcode":"19067",
    "sg:province":"PA",
    "sg:tags":[
        "welding"
    ],
    "wof:name":"Johnson's Welding Svc",
    "wof:placetype":"venue"
},
  "geometry": {"coordinates":[-74.79510500000001,40.169124],"type":"Point"}
}