{
  "type": "Feature",
  "properties": {
    "iso:country":"US",
    "sg:address":"110 Roessler Rd",
    "sg:city":"Pittsburgh",
    "sg:classifiers":[
        {
            "category":"Health Services",
            "subcategory":"Chiropractor",
            "type":"Services"
        }
    ],
    "sg:phone":"+1 412 571 2242",
    "sg:postcode":"15220",
    "sg:province":"PA",
    "wof:name":"Aivalotis Chiropractic",
    "wof:placetype":"venue"
},
  "geometry": {"coordinates":[-80.059651,40.394751],"type":"Point"}
}