{
  "type": "Feature",
  "properties": {
    "addr:full":"78 Cottage St Carbondale PA 18407",
    "addr:housenumber":"78",
    "addr:postcode":"18407",
    "addr:street":"Cottage St",
    "iso:country":"US",
    "sg:address":"78 Cottage St",
    "sg:city":"Carbondale",
    "sg:classifiers":[
        {
            "category":"Utilities",
            "type":"Services"
        }
    ],
    "sg:phone":"+1   ",
    "sg:postcode":"18407",
    "sg:province":"PA",
    "sg:tags":[
        "sanitary"
    ],
    "wof:name":"Jva Deicing Distribution Ctr",
    "wof:placetype":"venue"
},
  "geometry": {"coordinates":[-75.5202,41.561769],"type":"Point"}
}