{
  "type": "Feature",
  "properties": {
    "addr:full":"2800 Bethel St New Kensington PA 15068",
    "addr:housenumber":"2800",
    "addr:postcode":"15068",
    "addr:street":"Bethel St",
    "iso:country":"US",
    "sg:address":"2800 Bethel St",
    "sg:city":"New Kensington",
    "sg:classifiers":[
        {
            "category":"Government",
            "subcategory":"Office",
            "type":"Public Place"
        }
    ],
    "sg:phone":"+1   ",
    "sg:postcode":"15068",
    "sg:province":"PA",
    "sg:tags":[
        "legislative",
        "body"
    ],
    "wof:name":"John P Murtha Congressman",
    "wof:placetype":"venue"
},
  "geometry": {"coordinates":[-79.728588,40.589545],"type":"Point"}
}