{
  "type": "Feature",
  "properties": {
    "iso:country":"US",
    "sg:address":"4690 Horseshoe Pike",
    "sg:city":"Honey Brook",
    "sg:classifiers":[
        {
            "category":"Travel",
            "subcategory":"Hotels & Motels",
            "type":"Entertainment"
        }
    ],
    "sg:phone":"+1 610 273 2444",
    "sg:postcode":"19344",
    "sg:province":"PA",
    "wof:name":"Waynebrook Inn",
    "wof:placetype":"venue"
},
  "geometry": {"coordinates":[-75.91324400000001,40.095734],"type":"Point"}
}