{
  "type": "Feature",
  "properties": {
    "iso:country":"US",
    "sg:address":"1428 Ben Franklin Hwy",
    "sg:city":"Douglassville",
    "sg:classifiers":[
        {
            "category":"Sports & Exercise",
            "subcategory":"Bowling",
            "type":"Entertainment"
        }
    ],
    "sg:phone":"+1   ",
    "sg:postcode":"19518",
    "sg:province":"PA",
    "sg:tags":[
        "center"
    ],
    "wof:name":"Jay Lanes Inc",
    "wof:placetype":"venue"
},
  "geometry": {"coordinates":[-75.71352899999999,40.252787],"type":"Point"}
}