{
  "type": "Feature",
  "properties": {
    "iso:country":"US",
    "sg:address":"215 Means Hollow Rd",
    "sg:city":"Shippensburg",
    "sg:classifiers":[
        {
            "category":"Professional",
            "type":"Services"
        }
    ],
    "sg:phone":"+1   ",
    "sg:postcode":"17257",
    "sg:province":"PA",
    "wof:name":"Jay M Wyrick",
    "wof:placetype":"venue"
},
  "geometry": {"coordinates":[-77.48355100000001,39.995143],"type":"Point"}
}