{
  "type": "Feature",
  "properties": {
    "iso:country":"US",
    "sg:address":"9 Union Hill Rd",
    "sg:city":"Conshohocken",
    "sg:classifiers":[
        {
            "category":"Wholesale",
            "subcategory":"Hardware",
            "type":"Manufacturing & Wholesale Goods"
        },
        {
            "category":"Wholesale",
            "subcategory":"Electrical",
            "type":"Manufacturing & Wholesale Goods"
        }
    ],
    "sg:phone":"+1 610 825 7200",
    "sg:postcode":"19428",
    "sg:province":"PA",
    "sg:tags":[
        "control",
        "air",
        "heating",
        "system",
        "conditioning"
    ],
    "wof:name":"Broudy Precision Equipment Co",
    "wof:placetype":"venue"
},
  "geometry": {"coordinates":[-75.325704,40.068579],"type":"Point"}
}