{
  "type": "Feature",
  "properties": {
    "addr:full":"1617 John F Kennedy Blvd Ste 1200 Philadelphia PA 19103",
    "addr:housenumber":"1617",
    "addr:postcode":"19103",
    "addr:street":"John F Kennedy Blvd Ste 1200",
    "iso:country":"US",
    "sg:address":"1617 John F Kennedy Blvd Ste 1200",
    "sg:city":"Philadelphia",
    "sg:classifiers":[
        {
            "category":"Professional",
            "subcategory":"Lawyer & Legal Services",
            "type":"Services"
        }
    ],
    "sg:phone":"+1 215 568 1800",
    "sg:postcode":"19103",
    "sg:province":"PA",
    "sg:tags":[
        "attorney",
        "criminal",
        "personal",
        "practice",
        "product",
        "liability",
        "injury",
        "insurance",
        "law"
    ],
    "sg:website":"http://www.kentmcbride.com",
    "wof:name":"Devanny, Christopher D. - Kent & McBride, P.C.",
    "wof:placetype":"venue"
},
  "geometry": {"coordinates":[-75.16695799999999,39.953849],"type":"Point"}
}