{
  "type": "Feature",
  "properties": {
    "iso:country":"US",
    "sg:address":"784 School House Ln",
    "sg:city":"Lewisberry",
    "sg:classifiers":[
        {
            "category":"Building & Trades",
            "subcategory":"Construction",
            "type":"Services"
        }
    ],
    "sg:phone":"+1 717 932 8990",
    "sg:postcode":"17339",
    "sg:province":"PA",
    "sg:tags":[
        "general",
        "contractor"
    ],
    "wof:name":"Harkins Construction",
    "wof:placetype":"venue"
},
  "geometry": {"coordinates":[-76.868055,40.162956],"type":"Point"}
}