{
  "type": "Feature",
  "properties": {
    "iso:country":"US",
    "sg:address":"600 N 40th St",
    "sg:city":"Philadelphia",
    "sg:classifiers":[
        {
            "category":"Restaurant",
            "type":"Food & Drink"
        }
    ],
    "sg:phone":"+1 215 382 0803",
    "sg:postcode":"19104",
    "sg:province":"PA",
    "sg:tags":[
        "eating"
    ],
    "wof:name":"Lancaster Hoagie City",
    "wof:placetype":"venue"
},
  "geometry": {"coordinates":[-75.202202,39.963699],"type":"Point"}
}