{
  "type": "Feature",
  "properties": {
    "iso:country":"US",
    "sg:address":"320 Atwood St",
    "sg:city":"Pittsburgh",
    "sg:classifiers":[
        {
            "category":"Professional",
            "type":"Services"
        }
    ],
    "sg:phone":"+1   ",
    "sg:postcode":"15213",
    "sg:province":"PA",
    "wof:name":"Maggies Merchantile",
    "wof:placetype":"venue"
},
  "geometry": {"coordinates":[-79.954382,40.438386],"type":"Point"}
}