{
  "type": "Feature",
  "properties": {
    "iso:country":"US",
    "sg:address":"2251 Lehigh Pkwy N",
    "sg:city":"Allentown",
    "sg:classifiers":[
        {
            "category":"Professional",
            "type":"Services"
        }
    ],
    "sg:phone":"+1   ",
    "sg:postcode":"18103",
    "sg:province":"PA",
    "wof:name":"Wendy Sheetz",
    "wof:placetype":"venue"
},
  "geometry": {"coordinates":[-75.496863,40.580088],"type":"Point"}
}