{
  "type": "Feature",
  "properties": {
    "iso:country":"US",
    "sg:address":"401 US Hwy 30",
    "sg:city":"Malvern",
    "sg:classifiers":[
        {
            "category":"Personal",
            "subcategory":"Barber",
            "type":"Services"
        }
    ],
    "sg:phone":"+1   ",
    "sg:postcode":"19355",
    "sg:province":"PA",
    "sg:tags":[
        "shop"
    ],
    "wof:name":"DAscanios Family Hair Styling",
    "wof:placetype":"venue"
},
  "geometry": {"coordinates":[-75.55982899999999,40.037399],"type":"Point"}
}