{
  "type": "Feature",
  "properties": {
    "iso:country":"US",
    "sg:address":"705 West Ave",
    "sg:city":"Jenkintown",
    "sg:classifiers":[
        {
            "category":"Shopping",
            "subcategory":"Jewelry",
            "type":"Retail Goods"
        }
    ],
    "sg:phone":"+1 215 576 1215",
    "sg:postcode":"19046",
    "sg:province":"PA",
    "sg:tags":[
        "stone",
        "jeweler"
    ],
    "wof:name":"Reggie Lawson Inc",
    "wof:placetype":"venue"
},
  "geometry": {"coordinates":[-75.12665200000001,40.096019],"type":"Point"}
}