{
  "type": "Feature",
  "properties": {
    "addr:full":"31 Arrow Dr Leesport PA 19525",
    "addr:housenumber":"31",
    "addr:postcode":"19525",
    "addr:street":"Arrow Dr",
    "iso:country":"US",
    "sg:address":"31 Arrow Dr",
    "sg:city":"Leesport",
    "sg:classifiers":[
        {
            "category":"Building & Trades",
            "subcategory":"Construction",
            "type":"Services"
        }
    ],
    "sg:phone":"+1 610 926 9871",
    "sg:postcode":"19525",
    "sg:province":"PA",
    "sg:tags":[
        "home",
        "improvement"
    ],
    "wof:name":"Mc Ginty Home Improvements",
    "wof:placetype":"venue"
},
  "geometry": {"coordinates":[-75.612008,40.303259],"type":"Point"}
}