{
  "type": "Feature",
  "properties": {
    "iso:country":"US",
    "sg:address":"1222 S 10th St",
    "sg:city":"Philadelphia",
    "sg:classifiers":[
        {
            "category":"Building & Trades",
            "subcategory":"Construction",
            "type":"Services"
        }
    ],
    "sg:phone":"+1 215 462 1861",
    "sg:postcode":"19147",
    "sg:province":"PA",
    "sg:tags":[
        "general",
        "contractor"
    ],
    "wof:name":"Society Contractors",
    "wof:placetype":"venue"
},
  "geometry": {"coordinates":[-75.16074,39.933557],"type":"Point"}
}