{
  "type": "Feature",
  "properties": {
    "iso:country":"US",
    "sg:address":"1055 Oldstone Rd",
    "sg:city":"Allentown",
    "sg:classifiers":[
        {
            "category":"Wholesale",
            "subcategory":"Home Furnishings",
            "type":"Manufacturing & Wholesale Goods"
        }
    ],
    "sg:phone":"+1 610 721 6630",
    "sg:postcode":"18103",
    "sg:province":"PA",
    "sg:tags":[
        "plumbing",
        "supplies-wholesale",
        "part",
        "fixture",
        "manufacturer"
    ],
    "wof:name":"Hansen Air & Light Inc.",
    "wof:placetype":"venue"
},
  "geometry": {"coordinates":[-75.510317,40.573821],"type":"Point"}
}