{
  "type": "Feature",
  "properties": {
    "iso:country":"US",
    "sg:address":"4230 Brownsville Rd",
    "sg:city":"Pittsburgh",
    "sg:classifiers":[
        {
            "category":"Banks & Credit Unions",
            "subcategory":"Bank",
            "type":"Services"
        }
    ],
    "sg:phone":"+1 412 884 1234",
    "sg:postcode":"15227",
    "sg:province":"PA",
    "sg:tags":[
        "saving",
        "commercial"
    ],
    "sg:website":"http://www.pncbank.com",
    "wof:name":"Pnc Bank",
    "wof:placetype":"venue"
},
  "geometry": {"coordinates":[-79.983625,40.36455],"type":"Point"}
}