{
  "type": "Feature",
  "properties": {
    "iso:country":"US",
    "sg:address":"895 Providence Rd",
    "sg:city":"Scranton",
    "sg:classifiers":[
        {
            "category":"Home & Garden",
            "subcategory":"Building Materials",
            "type":"Retail Goods"
        }
    ],
    "sg:phone":"+1 570 961 3200",
    "sg:postcode":"18508",
    "sg:province":"PA",
    "sg:tags":[
        "glass",
        "window",
        "plate"
    ],
    "wof:name":"Atlas Glass",
    "wof:placetype":"venue"
},
  "geometry": {"coordinates":[-75.66537099999999,41.420589],"type":"Point"}
}