{
  "type": "Feature",
  "properties": {
    "iso:country":"US",
    "sg:address":"4594 William Penn Hwy",
    "sg:city":"Murrysville",
    "sg:classifiers":[
        {
            "category":"Building & Trades",
            "subcategory":"Landscaping Services",
            "type":"Services"
        }
    ],
    "sg:phone":"+1 724 327 2539",
    "sg:postcode":"15668",
    "sg:province":"PA",
    "sg:tags":[
        "landscape",
        "contractor"
    ],
    "wof:name":"Alex Landscaping & Lawn Care",
    "wof:placetype":"venue"
},
  "geometry": {"coordinates":[-79.669021,40.424966],"type":"Point"}
}