{
  "type": "Feature",
  "properties": {
    "addr:full":"736 Main St Honesdale PA 18431",
    "addr:housenumber":"736",
    "addr:postcode":"18431",
    "addr:street":"Main St",
    "iso:country":"US",
    "sg:address":"736 Main St",
    "sg:city":"Honesdale",
    "sg:classifiers":[
        {
            "category":"Organizations",
            "subcategory":"Community Association",
            "type":"Services"
        }
    ],
    "sg:phone":"+1 570 253 5373",
    "sg:postcode":"18431",
    "sg:province":"PA",
    "sg:tags":[
        "club"
    ],
    "wof:name":"VFW 531",
    "wof:placetype":"venue"
},
  "geometry": {"coordinates":[-75.25552999999999,41.57182],"type":"Point"}
}