{
  "type": "Feature",
  "properties": {
    "addr:full":"3961 Perrysville Ave Pittsburgh PA 15214",
    "addr:housenumber":"3961",
    "addr:postcode":"15214",
    "addr:street":"Perrysville Ave",
    "iso:country":"US",
    "sg:address":"3961 Perrysville Ave",
    "sg:city":"Pittsburgh",
    "sg:classifiers":[
        {
            "category":"Health Services",
            "subcategory":"Chiropractor",
            "type":"Services"
        }
    ],
    "sg:phone":"+1 412 321 5096",
    "sg:postcode":"15214",
    "sg:province":"PA",
    "wof:name":"Observatory Hill Chiropractic",
    "wof:placetype":"venue"
},
  "geometry": {"coordinates":[-80.01933200000001,40.490618],"type":"Point"}
}