{
  "type": "Feature",
  "properties": {
    "addr:full":"5821 N Broad St Philadelphia PA 19141",
    "addr:housenumber":"5821",
    "addr:postcode":"19141",
    "addr:street":"N Broad St",
    "iso:country":"US",
    "sg:address":"5821 N Broad St",
    "sg:city":"Philadelphia",
    "sg:classifiers":[
        {
            "category":"Retail",
            "subcategory":"Auto Repair",
            "type":"Services"
        }
    ],
    "sg:phone":"+1   ",
    "sg:postcode":"19141",
    "sg:province":"PA",
    "sg:tags":[
        "general"
    ],
    "wof:name":"Repair On Spot Auto",
    "wof:placetype":"venue"
},
  "geometry": {"coordinates":[-75.14401599999999,40.041839],"type":"Point"}
}