{
  "type": "Feature",
  "properties": {
    "iso:country":"US",
    "sg:address":"807 Cleardale Dr",
    "sg:city":"Greensburg",
    "sg:classifiers":[
        {
            "category":"Professional",
            "subcategory":"Management & Consulting",
            "type":"Services"
        }
    ],
    "sg:phone":"+1 724 853 1830",
    "sg:postcode":"15601",
    "sg:province":"PA",
    "sg:tags":[
        "consultant",
        "business"
    ],
    "wof:name":"Fox's Worth Consulting",
    "wof:placetype":"venue"
},
  "geometry": {"coordinates":[-79.581744,40.296418],"type":"Point"}
}