{
  "type": "Feature",
  "properties": {
    "addr:full":"1722 Lincoln Ave Pittsburgh PA 15206",
    "addr:housenumber":"1722",
    "addr:postcode":"15206",
    "addr:street":"Lincoln Ave",
    "iso:country":"US",
    "sg:address":"1722 Lincoln Ave",
    "sg:city":"Pittsburgh",
    "sg:classifiers":[
        {
            "category":"Social Services",
            "type":"Services"
        }
    ],
    "sg:phone":"+1 412 362 1857",
    "sg:postcode":"15206",
    "sg:province":"PA",
    "sg:tags":[
        "mission"
    ],
    "wof:name":"International Assembly-The Chr",
    "wof:placetype":"venue"
},
  "geometry": {"coordinates":[-79.890407,40.472487],"type":"Point"}
}