{
  "type": "Feature",
  "properties": {
    "iso:country":"US",
    "sg:address":"101 E. Mill Street Suite P-16",
    "sg:city":"Quakertown",
    "sg:classifiers":[
        {
            "category":"Professional",
            "subcategory":"Business Services",
            "type":"Services"
        }
    ],
    "sg:phone":"+1 215 529 9440",
    "sg:postcode":"18951",
    "sg:province":"PA",
    "sg:website":"http://www.rcdtechnology.com",
    "wof:name":"RCD Technology",
    "wof:placetype":"venue"
},
  "geometry": {"coordinates":[-75.3381,40.445395],"type":"Point"}
}