{
  "type": "Feature",
  "properties": {
    "addr:full":"311 E Main St Fleetwood PA 19522",
    "addr:housenumber":"311",
    "addr:postcode":"19522",
    "addr:street":"E Main St",
    "iso:country":"US",
    "sg:address":"311 E Main St",
    "sg:city":"Fleetwood",
    "sg:classifiers":[
        {
            "category":"Real Estate",
            "subcategory":"Surveying",
            "type":"Services"
        }
    ],
    "sg:phone":"+1   ",
    "sg:postcode":"19522",
    "sg:province":"PA",
    "wof:name":"Bruce T Raders Pls Pe",
    "wof:placetype":"venue"
},
  "geometry": {"coordinates":[-75.81187799999999,40.457612],"type":"Point"}
}