{
  "type": "Feature",
  "properties": {
    "iso:country":"US",
    "sg:address":"1331 E Wyoming Ave",
    "sg:city":"Philadelphia",
    "sg:classifiers":[
        {
            "category":"Health Services",
            "subcategory":"Doctor",
            "type":"Services"
        }
    ],
    "sg:phone":"+1   ",
    "sg:postcode":"19124",
    "sg:province":"PA",
    "sg:tags":[
        "osteopathic"
    ],
    "wof:name":"Elizabeth Shandor Do",
    "wof:placetype":"venue"
},
  "geometry": {"coordinates":[-75.09981500000001,40.018634],"type":"Point"}
}