{
  "type": "Feature",
  "properties": {
    "addr:full":"3835 Yost Rd Gordonville PA 17529",
    "addr:housenumber":"3835",
    "addr:postcode":"17529",
    "addr:street":"Yost Rd",
    "iso:country":"US",
    "sg:address":"3835 Yost Rd",
    "sg:city":"Gordonville",
    "sg:classifiers":[
        {
            "category":"Building & Trades",
            "subcategory":"Construction",
            "type":"Services"
        }
    ],
    "sg:phone":"+1 717 354 0041",
    "sg:postcode":"17529",
    "sg:province":"PA",
    "sg:tags":[
        "siding",
        "contractor"
    ],
    "wof:name":"R & L Siding Co",
    "wof:placetype":"venue"
},
  "geometry": {"coordinates":[-76.092313,40.065153],"type":"Point"}
}