{
  "type": "Feature",
  "properties": {
    "addr:full":"260 Telford Pike Telford PA 18969",
    "addr:housenumber":"260",
    "addr:postcode":"18969",
    "addr:street":"Telford Pike",
    "iso:country":"US",
    "sg:address":"260 Telford Pike",
    "sg:city":"Telford",
    "sg:classifiers":[
        {
            "category":"Building & Trades",
            "subcategory":"Construction",
            "type":"Services"
        }
    ],
    "sg:phone":"+1 215 721 1566",
    "sg:postcode":"18969",
    "sg:province":"PA",
    "sg:tags":[
        "maker",
        "cabinet"
    ],
    "wof:name":"Byron Hecker Cabinetmaker",
    "wof:placetype":"venue"
},
  "geometry": {"coordinates":[-75.345415,40.316324],"type":"Point"}
}