{
  "type": "Feature",
  "properties": {
    "iso:country":"US",
    "sg:address":"1149 W 10th St",
    "sg:city":"Erie",
    "sg:classifiers":[
        {
            "category":"Professional",
            "subcategory":"Management & Consulting",
            "type":"Services"
        }
    ],
    "sg:phone":"+1 814 449 9977",
    "sg:postcode":"16502",
    "sg:province":"PA",
    "sg:tags":[
        "consultant"
    ],
    "wof:name":"Technologically Advanced Network For Non-Profits, Inc",
    "wof:placetype":"venue"
},
  "geometry": {"coordinates":[-80.105902,42.11688],"type":"Point"}
}