{
  "type": "Feature",
  "properties": {
    "iso:country":"US",
    "sg:address":"232 W Creamery Rd",
    "sg:city":"Perkasie",
    "sg:phone":"+1   ",
    "sg:postcode":"18944",
    "sg:province":"PA",
    "sg:tags":[
        "farm",
        "corn"
    ],
    "wof:name":"Hodale Farms",
    "wof:placetype":"venue"
},
  "geometry": {"coordinates":[-75.252774,40.345349],"type":"Point"}
}