{
  "type": "Feature",
  "properties": {
    "iso:country":"US",
    "sg:address":"108 Chestnut St 4th Fl",
    "sg:city":"Philadelphia",
    "sg:classifiers":[
        {
            "category":"Arts & Performance",
            "subcategory":"Art Gallery",
            "type":"Entertainment"
        }
    ],
    "sg:phone":"+1 215 588 4445",
    "sg:postcode":"19106",
    "sg:province":"PA",
    "sg:website":"www.blinkartgallery.com",
    "wof:name":"Blink Art Gallery",
    "wof:placetype":"venue"
},
  "geometry": {"coordinates":[-75.142934,39.94806],"type":"Point"}
}