{
  "type": "Feature",
  "properties": {
    "addr:full":"1107 Pilgrims Pathway Peach Bottom PA 17563",
    "addr:housenumber":"1107",
    "addr:postcode":"17563",
    "addr:street":"Pilgrims Pathway;Bottom",
    "iso:country":"US",
    "sg:address":"1107 Pilgrims Pathway",
    "sg:city":"Peach Bottom",
    "sg:classifiers":[
        {
            "category":"Sports & Exercise",
            "subcategory":"Golf",
            "type":"Entertainment"
        },
        {
            "category":"Recreation",
            "type":"Entertainment"
        }
    ],
    "sg:phone":"+1 717 548 3011",
    "sg:postcode":"17563",
    "sg:province":"PA",
    "sg:tags":[
        "course",
        "range",
        "practice"
    ],
    "sg:website":"www.pilgrimsoak.com",
    "wof:name":"Pilgrim's Oak Golf Course",
    "wof:placetype":"venue"
},
  "geometry": {"coordinates":[-76.193493,39.796737],"type":"Point"}
}