{
  "type": "Feature",
  "properties": {
    "addr:full":"1982 Butler Pike Conshohocken PA 19428",
    "addr:housenumber":"1982",
    "addr:postcode":"19428",
    "addr:street":"Butler Pike",
    "iso:country":"US",
    "sg:address":"1982 Butler Pike",
    "sg:city":"Conshohocken",
    "sg:classifiers":[
        {
            "category":"Health Services",
            "subcategory":"Doctor",
            "type":"Services"
        }
    ],
    "sg:phone":"+1 610 260 0888",
    "sg:postcode":"19428",
    "sg:province":"PA",
    "sg:tags":[
        "physician",
        "surgeon"
    ],
    "wof:name":"Colonial Medical Group LTD",
    "wof:placetype":"venue"
},
  "geometry": {"coordinates":[-75.28640799999999,40.094516],"type":"Point"}
}