{
  "type": "Feature",
  "properties": {
    "addr:full":"10000 Roosevelt Blvd # 1 Philadelphia PA 19116",
    "addr:housenumber":"10000",
    "addr:postcode":"19116",
    "addr:street":"Roosevelt Blvd # 1",
    "iso:country":"US",
    "sg:address":"10000 Roosevelt Blvd # 1",
    "sg:city":"Philadelphia",
    "sg:classifiers":[
        {
            "category":"Utilities",
            "subcategory":"Mobile Phone",
            "type":"Services"
        },
        {
            "category":"Coffee & Tea",
            "type":"Food & Drink"
        }
    ],
    "sg:phone":"+1 215 552 9737",
    "sg:postcode":"19116",
    "sg:province":"PA",
    "sg:tags":[
        "shop",
        "wi-fi",
        "espresso",
        "hotspot",
        "restaurant"
    ],
    "sg:website":"http://www.starbuckscoffee.com",
    "wof:name":"Starbucks Coffee",
    "wof:placetype":"venue"
},
  "geometry": {"coordinates":[-75.001762,40.104939],"type":"Point"}
}