{
  "type": "Feature",
  "properties": {
    "addr:full":"840 Park City Center Lancaster PA 17601",
    "addr:housenumber":"840",
    "addr:postcode":"17601",
    "addr:street":"Park",
    "iso:country":"US",
    "sg:address":"840 Park City Center",
    "sg:city":"Lancaster",
    "sg:classifiers":[
        {
            "category":"Shopping",
            "subcategory":"Clothing, Apparel, & Fashions",
            "type":"Retail Goods"
        }
    ],
    "sg:phone":"+1 717 393 5259",
    "sg:postcode":"17601",
    "sg:province":"PA",
    "sg:tags":[
        "leather"
    ],
    "wof:name":"Deerskin Leather",
    "wof:placetype":"venue"
},
  "geometry": {"coordinates":[-76.340878,40.064696],"type":"Point"}
}