{
  "type": "Feature",
  "properties": {
    "iso:country":"US",
    "sg:address":"549 Georges Fairchance Rd",
    "sg:city":"Uniontown",
    "sg:classifiers":[
        {
            "category":"Autos & Motor Vehicles",
            "subcategory":"Automobile Sales",
            "type":"Retail Goods"
        }
    ],
    "sg:phone":"+1 724 564 1300",
    "sg:postcode":"15401",
    "sg:province":"PA",
    "sg:tags":[
        "car",
        "dealer"
    ],
    "wof:name":"O'Neil's Auto",
    "wof:placetype":"venue"
},
  "geometry": {"coordinates":[-79.748898,39.835759],"type":"Point"}
}