{
  "type": "Feature",
  "properties": {
    "iso:country":"US",
    "sg:address":"6661 N 20th St",
    "sg:city":"Philadelphia",
    "sg:classifiers":[
        {
            "category":"Shopping",
            "subcategory":"Discount & Variety Stores",
            "type":"Retail Goods"
        }
    ],
    "sg:phone":"+1   ",
    "sg:postcode":"19138",
    "sg:province":"PA",
    "wof:name":"Tropical Springs",
    "wof:placetype":"venue"
},
  "geometry": {"coordinates":[-75.1511,40.055336],"type":"Point"}
}