{
  "type": "Feature",
  "properties": {
    "iso:country":"US",
    "sg:address":"307 Owen Ave",
    "sg:city":"Lansdowne",
    "sg:classifiers":[
        {
            "category":"Building & Trades",
            "subcategory":"Construction",
            "type":"Services"
        }
    ],
    "sg:phone":"+1   ",
    "sg:postcode":"19050",
    "sg:province":"PA",
    "sg:tags":[
        "contractor"
    ],
    "wof:name":"Denis Isel Contractor",
    "wof:placetype":"venue"
},
  "geometry": {"coordinates":[-75.283164,39.950703],"type":"Point"}
}