{
  "type": "Feature",
  "properties": {
    "iso:country":"US",
    "sg:address":"807 S 2nd St",
    "sg:city":"Philadelphia",
    "sg:classifiers":[
        {
            "category":"Banks & Credit Unions",
            "subcategory":"Bank",
            "type":"Services"
        }
    ],
    "sg:phone":"+1   ",
    "sg:postcode":"19147",
    "sg:province":"PA",
    "sg:tags":[
        "federal",
        "savings",
        "institution"
    ],
    "wof:name":"Jzf P O0niatiowski Bld/Ln Assn",
    "wof:placetype":"venue"
},
  "geometry": {"coordinates":[-75.146495,39.937103],"type":"Point"}
}