{
  "type": "Feature",
  "properties": {
    "iso:country":"US",
    "sg:address":"742 Spring St",
    "sg:city":"Latrobe",
    "sg:classifiers":[
        {
            "category":"Professional",
            "type":"Services"
        }
    ],
    "sg:phone":"+1 724 537 5093",
    "sg:postcode":"15650",
    "sg:province":"PA",
    "sg:tags":[
        "establishment"
    ],
    "wof:name":"Keystone Refrigeration",
    "wof:placetype":"venue"
},
  "geometry": {"coordinates":[-79.375266,40.317762],"type":"Point"}
}