{
  "type": "Feature",
  "properties": {
    "iso:country":"US",
    "sg:address":"501 Elm Ave",
    "sg:city":"Swarthmore",
    "sg:classifiers":[
        {
            "category":"Health Services",
            "subcategory":"Doctor",
            "type":"Services"
        }
    ],
    "sg:phone":"+1 610 543 2737",
    "sg:postcode":"19081",
    "sg:province":"PA",
    "sg:tags":[
        "physician",
        "surgeon"
    ],
    "wof:name":"Caleb, Mae H Md",
    "wof:placetype":"venue"
},
  "geometry": {"coordinates":[-75.35140199999999,39.90839],"type":"Point"}
}