{
  "type": "Feature",
  "properties": {
    "iso:country":"US",
    "sg:address":"6239 State Rte 309",
    "sg:city":"Germansville",
    "sg:classifiers":[
        {
            "category":"Building & Trades",
            "subcategory":"Construction",
            "type":"Services"
        }
    ],
    "sg:phone":"+1   ",
    "sg:postcode":"18053",
    "sg:province":"PA",
    "sg:tags":[
        "carpentry",
        "contractor"
    ],
    "wof:name":"Capstone Custom Homes",
    "wof:placetype":"venue"
},
  "geometry": {"coordinates":[-75.688517,40.684698],"type":"Point"}
}