{
  "type": "Feature",
  "properties": {
    "iso:country":"US",
    "sg:address":"1230 Jefferson Ave",
    "sg:city":"Washington",
    "sg:classifiers":[
        {
            "category":"Personal",
            "subcategory":"Beauty Salon",
            "type":"Services"
        }
    ],
    "sg:phone":"+1 724 222 3391",
    "sg:postcode":"15301",
    "sg:province":"PA",
    "sg:tags":[
        "shop",
        "tanning"
    ],
    "wof:name":"Knots & Tangles",
    "wof:placetype":"venue"
},
  "geometry": {"coordinates":[-80.267303,40.186199],"type":"Point"}
}