{
  "type": "Feature",
  "properties": {
    "addr:full":"310 Queen City Rd Catawissa PA 17820",
    "addr:housenumber":"310",
    "addr:postcode":"17820",
    "addr:street":"Queen City Rd",
    "iso:country":"US",
    "sg:address":"310 Queen City Rd",
    "sg:city":"Catawissa",
    "sg:classifiers":[
        {
            "category":"Farming",
            "subcategory":"Livestock Farm",
            "type":"Manufacturing & Wholesale Goods"
        }
    ],
    "sg:phone":"+1   ",
    "sg:postcode":"17820",
    "sg:province":"PA",
    "sg:tags":[
        "feedlot",
        "hog",
        "or",
        "beef",
        "cattle"
    ],
    "wof:name":"Donald Hresko Farm",
    "wof:placetype":"venue"
},
  "geometry": {"coordinates":[-76.43981599999999,40.910094],"type":"Point"}
}