{
  "type": "Feature",
  "properties": {
    "iso:country":"US",
    "sg:address":"1 E Main St",
    "sg:city":"North East",
    "sg:classifiers":[
        {
            "category":"Professional",
            "type":"Services"
        }
    ],
    "sg:phone":"+1 814 725 9933",
    "sg:postcode":"16428",
    "sg:province":"PA",
    "sg:tags":[
        "establishment"
    ],
    "wof:name":"Jimmy's Meeting Place Pub",
    "wof:placetype":"venue"
},
  "geometry": {"coordinates":[-79.83367200000001,42.216252],"type":"Point"}
}