{
  "type": "Feature",
  "properties": {
    "addr:full":"2625 Shillington Rd Reading PA 19608",
    "addr:housenumber":"2625",
    "addr:postcode":"19608",
    "addr:street":"Shillington Rd",
    "iso:country":"US",
    "sg:address":"2625 Shillington Rd",
    "sg:city":"Reading",
    "sg:classifiers":[
        {
            "category":"Home & Garden",
            "subcategory":"Building Materials",
            "type":"Retail Goods"
        }
    ],
    "sg:phone":"+1 610 401 2200",
    "sg:postcode":"19608",
    "sg:province":"PA",
    "sg:tags":[
        "center"
    ],
    "wof:name":"Lowe's",
    "wof:placetype":"venue"
},
  "geometry": {"coordinates":[-76.000068,40.315597],"type":"Point"}
}