{
  "type": "Feature",
  "properties": {
    "iso:country":"US",
    "sg:address":"314 Chestnut St",
    "sg:city":"York",
    "sg:classifiers":[
        {
            "category":"Autos & Motor Vehicles",
            "subcategory":"Automobile Sales",
            "type":"Retail Goods"
        }
    ],
    "sg:phone":"+1 717 848 4731",
    "sg:postcode":"17403",
    "sg:province":"PA",
    "sg:tags":[
        "dealers-used",
        "car",
        "used",
        "cars-wholesale"
    ],
    "wof:name":"P & S Motor",
    "wof:placetype":"venue"
},
  "geometry": {"coordinates":[-76.723488,39.967869],"type":"Point"}
}