{
  "type": "Feature",
  "properties": {
    "iso:country":"US",
    "sg:address":"28 W Upsal St",
    "sg:city":"Philadelphia",
    "sg:classifiers":[
        {
            "category":"Professional",
            "subcategory":"Lawyer & Legal Services",
            "type":"Services"
        }
    ],
    "sg:phone":"+1 215 843 6101",
    "sg:postcode":"19119",
    "sg:province":"PA",
    "sg:tags":[
        "attorney"
    ],
    "wof:name":"Velma Johnson Law Office",
    "wof:placetype":"venue"
},
  "geometry": {"coordinates":[-75.184826,40.046863],"type":"Point"}
}