{
  "type": "Feature",
  "properties": {
    "iso:country":"US",
    "sg:address":"1369 E Main St",
    "sg:city":"Clarion",
    "sg:classifiers":[
        {
            "category":"Retail",
            "subcategory":"Auto Rental",
            "type":"Services"
        }
    ],
    "sg:phone":"+1 814 226 7788",
    "sg:postcode":"16214",
    "sg:province":"PA",
    "sg:tags":[
        "renting",
        "truck",
        "leasing"
    ],
    "wof:name":"U-Haul Co",
    "wof:placetype":"venue"
},
  "geometry": {"coordinates":[-79.365752,41.207803],"type":"Point"}
}