{
  "type": "Feature",
  "properties": {
    "addr:full":"140 York Rd Jenkintown PA 19046",
    "addr:housenumber":"140",
    "addr:postcode":"19046",
    "addr:street":"York Rd",
    "iso:country":"US",
    "sg:address":"140 York Rd",
    "sg:city":"Jenkintown",
    "sg:classifiers":[
        {
            "category":"Retail",
            "subcategory":"Auto Rental",
            "type":"Services"
        }
    ],
    "sg:phone":"+1 215 884 1769",
    "sg:postcode":"19046",
    "sg:province":"PA",
    "sg:tags":[
        "renting",
        "automobile"
    ],
    "wof:name":"Enterprise Rent A Car & Lsng",
    "wof:placetype":"venue"
},
  "geometry": {"coordinates":[-75.127486,40.088181],"type":"Point"}
}