{
  "type": "Feature",
  "properties": {
    "iso:country":"US",
    "sg:address":"1617 Oneida Valley Rd",
    "sg:city":"Chicora",
    "sg:classifiers":[
        {
            "category":"Shopping",
            "type":"Retail Goods"
        }
    ],
    "sg:phone":"+1 724 776 4930",
    "sg:postcode":"16025",
    "sg:province":"PA",
    "sg:tags":[
        "merchandise"
    ],
    "wof:name":"Dr Waterheater",
    "wof:placetype":"venue"
},
  "geometry": {"coordinates":[-79.832885,40.990522],"type":"Point"}
}