{
  "type": "Feature",
  "properties": {
    "iso:country":"US",
    "sg:address":"5670 Lincoln Hwy",
    "sg:city":"York",
    "sg:classifiers":[
        {
            "category":"Shopping",
            "subcategory":"Florist",
            "type":"Retail Goods"
        }
    ],
    "sg:phone":"+1 717 252 5014",
    "sg:postcode":"17406",
    "sg:province":"PA",
    "wof:name":"Rambler 's Flowers & Things",
    "wof:placetype":"venue"
},
  "geometry": {"coordinates":[-76.575751,40.014885],"type":"Point"}
}