{
  "type": "Feature",
  "properties": {
    "iso:country":"US",
    "sg:address":"1391 Moselem Spring Rd",
    "sg:city":"Hamburg",
    "sg:classifiers":[
        {
            "category":"Recreation",
            "type":"Entertainment"
        }
    ],
    "sg:phone":"+1   ",
    "sg:postcode":"19526",
    "sg:province":"PA",
    "sg:tags":[
        "club",
        "membership"
    ],
    "wof:name":"Wing Pointe Corp",
    "wof:placetype":"venue"
},
  "geometry": {"coordinates":[-75.899418,40.504106],"type":"Point"}
}