{
  "type": "Feature",
  "properties": {
    "iso:country":"US",
    "sg:address":"1040 N Jerome St",
    "sg:city":"Allentown",
    "sg:classifiers":[
        {
            "category":"Building & Trades",
            "subcategory":"Construction",
            "type":"Services"
        }
    ],
    "sg:phone":"+1 610 432 2301",
    "sg:postcode":"18109",
    "sg:province":"PA",
    "sg:tags":[
        "fire",
        "restoration",
        "damage",
        "contractor"
    ],
    "wof:name":"Barclay Contracting Co",
    "wof:placetype":"venue"
},
  "geometry": {"coordinates":[-75.440697,40.6264],"type":"Point"}
}