{
  "type": "Feature",
  "properties": {
    "iso:country":"US",
    "sg:address":"2 N State St",
    "sg:city":"Newtown",
    "sg:classifiers":[
        {
            "category":"Government",
            "subcategory":"Office",
            "type":"Public Place"
        }
    ],
    "sg:phone":"+1   ",
    "sg:postcode":"18940",
    "sg:province":"PA",
    "sg:tags":[
        "legislative",
        "body"
    ],
    "wof:name":"Steil David J State Rep",
    "wof:placetype":"venue"
},
  "geometry": {"coordinates":[-74.936562,40.230469],"type":"Point"}
}