{
  "type": "Feature",
  "properties": {
    "iso:country":"US",
    "sg:address":"2101 E Grand Ave",
    "sg:city":"Tower City",
    "sg:classifiers":[
        {
            "category":"Wholesale",
            "subcategory":"Beer",
            "type":"Manufacturing & Wholesale Goods"
        }
    ],
    "sg:phone":"+1 717 647 2396",
    "sg:postcode":"17980",
    "sg:province":"PA",
    "sg:tags":[
        "ale",
        "beverage",
        "alcoholic"
    ],
    "wof:name":"Nelson Beer Distributors",
    "wof:placetype":"venue"
},
  "geometry": {"coordinates":[-76.52520199999999,40.593843],"type":"Point"}
}