{
  "type": "Feature",
  "properties": {
    "addr:full":"227 N Broad St Philadelphia PA 19107",
    "addr:housenumber":"227",
    "addr:postcode":"19107",
    "addr:street":"N Broad St",
    "iso:country":"US",
    "sg:address":"227 N Broad St",
    "sg:city":"Philadelphia",
    "sg:classifiers":[
        {
            "category":"Health Services",
            "subcategory":"Doctor",
            "type":"Services"
        },
        {
            "category":"Health Services",
            "subcategory":"Clinic",
            "type":"Services"
        }
    ],
    "sg:phone":"+1 215 988 0611",
    "sg:postcode":"19107",
    "sg:province":"PA",
    "sg:tags":[
        "physician",
        "surgeon",
        "osteopathic"
    ],
    "wof:name":"Corey K Ruth Md",
    "wof:placetype":"venue"
},
  "geometry": {"coordinates":[-75.16260200000001,39.956982],"type":"Point"}
}