{
  "type": "Feature",
  "properties": {
    "addr:full":"1518 Clifford Dr Erie PA 16505",
    "addr:housenumber":"1518",
    "addr:postcode":"16505",
    "addr:street":"Clifford Dr",
    "iso:country":"US",
    "sg:address":"1518 Clifford Dr",
    "sg:city":"Erie",
    "sg:classifiers":[
        {
            "category":"Professional",
            "subcategory":"Management & Consulting",
            "type":"Services"
        }
    ],
    "sg:phone":"+1   ",
    "sg:postcode":"16505",
    "sg:province":"PA",
    "wof:name":"Bar & Restaurant Services LLC",
    "wof:placetype":"venue"
},
  "geometry": {"coordinates":[-80.203557,42.07423],"type":"Point"}
}