{
  "type": "Feature",
  "properties": {
    "iso:country":"US",
    "sg:address":"1851 Center St",
    "sg:city":"Camp Hill",
    "sg:classifiers":[
        {
            "category":"Health Services",
            "subcategory":"Doctor",
            "type":"Services"
        }
    ],
    "sg:phone":"+1 717 761 0325",
    "sg:postcode":"17011",
    "sg:province":"PA",
    "sg:tags":[
        "surgeon",
        "oral"
    ],
    "wof:name":"Nester John DDS",
    "wof:placetype":"venue"
},
  "geometry": {"coordinates":[-76.929703,40.257702],"type":"Point"}
}