{
  "type": "Feature",
  "properties": {
    "iso:country":"US",
    "sg:address":"29169 Great Cove Rd",
    "sg:city":"Fort Littleton",
    "sg:classifiers":[
        {
            "category":"Building & Trades",
            "subcategory":"Plumbing",
            "type":"Services"
        }
    ],
    "sg:phone":"+1 717 987 4340",
    "sg:postcode":"17223",
    "sg:province":"PA",
    "sg:tags":[
        "septic"
    ],
    "wof:name":"County Septic",
    "wof:placetype":"venue"
},
  "geometry": {"coordinates":[-77.961065,40.051633],"type":"Point"}
}