{
  "type": "Feature",
  "properties": {
    "iso:country":"US",
    "sg:address":"529 Adams Ave",
    "sg:city":"Philadelphia",
    "sg:classifiers":[
        {
            "category":"Travel",
            "subcategory":"Travel Agent",
            "type":"Entertainment"
        }
    ],
    "sg:phone":"+1 215 722 0217",
    "sg:postcode":"19120",
    "sg:province":"PA",
    "sg:tags":[
        "agency"
    ],
    "wof:name":"Seven Seas Travel Inc",
    "wof:placetype":"venue"
},
  "geometry": {"coordinates":[-75.110011,40.039148],"type":"Point"}
}