{
  "type": "Feature",
  "properties": {
    "iso:country":"US",
    "sg:address":"63 Kreider Ln",
    "sg:city":"Manheim",
    "sg:classifiers":[
        {
            "category":"Retail",
            "subcategory":"Auto Repair",
            "type":"Services"
        }
    ],
    "sg:phone":"+1 717 898 2401",
    "sg:postcode":"17545",
    "sg:province":"PA",
    "sg:tags":[
        "repairing",
        "automobile"
    ],
    "sg:website":"www.brkreider.com",
    "wof:name":"Pinoak Service Ctr",
    "wof:placetype":"venue"
},
  "geometry": {"coordinates":[-76.37502499999999,40.124293],"type":"Point"}
}