{
  "type": "Feature",
  "properties": {
    "addr:full":"627 Merchant St Ambridge PA 15003",
    "addr:housenumber":"627",
    "addr:postcode":"15003",
    "addr:street":"Merchant St",
    "iso:country":"US",
    "sg:address":"627 Merchant St",
    "sg:city":"Ambridge",
    "sg:classifiers":[
        {
            "category":"Organizations",
            "subcategory":"Community Association",
            "type":"Services"
        }
    ],
    "sg:phone":"+1   ",
    "sg:postcode":"15003",
    "sg:province":"PA",
    "sg:tags":[
        "civic",
        "social"
    ],
    "wof:name":"Ambridge Lodge No 701 F & A M",
    "wof:placetype":"venue"
},
  "geometry": {"coordinates":[-80.228168,40.587521],"type":"Point"}
}