{
  "type": "Feature",
  "properties": {
    "addr:full":"4730 Cortland Rd New Paris PA 15554",
    "addr:housenumber":"4730",
    "addr:postcode":"15554",
    "addr:street":"Cortland Rd",
    "iso:country":"US",
    "sg:address":"4730 Cortland Rd",
    "sg:city":"New Paris",
    "sg:classifiers":[
        {
            "category":"Real Estate",
            "subcategory":"Real Estate Operator",
            "type":"Services"
        }
    ],
    "sg:phone":"+1   ",
    "sg:postcode":"15554",
    "sg:province":"PA",
    "sg:tags":[
        "property",
        "lessor"
    ],
    "wof:name":"Sean Gluffner",
    "wof:placetype":"venue"
},
  "geometry": {"coordinates":[-78.63789800000001,40.128179],"type":"Point"}
}