{
  "type": "Feature",
  "properties": {
    "iso:country":"US",
    "sg:address":"648 Cooper Rd",
    "sg:city":"Delta",
    "sg:classifiers":[
        {
            "category":"Building & Trades",
            "subcategory":"Landscaping Services",
            "type":"Services"
        }
    ],
    "sg:phone":"+1 717 456 7151",
    "sg:postcode":"17314",
    "sg:province":"PA",
    "sg:tags":[
        "landscape",
        "contractor"
    ],
    "wof:name":"Nature By Design Inc",
    "wof:placetype":"venue"
},
  "geometry": {"coordinates":[-76.2577,39.728262],"type":"Point"}
}