{
  "type": "Feature",
  "properties": {
    "iso:country":"US",
    "sg:address":"33 N Brown St",
    "sg:city":"Lewistown",
    "sg:classifiers":[
        {
            "category":"Organizations",
            "subcategory":"Membership Organization",
            "type":"Services"
        }
    ],
    "sg:phone":"+1   ",
    "sg:postcode":"17044",
    "sg:province":"PA",
    "sg:tags":[
        "club",
        "automobile",
        "travel",
        "agency",
        "insurance"
    ],
    "wof:name":"AAA Central Penn",
    "wof:placetype":"venue"
},
  "geometry": {"coordinates":[-77.573348,40.598541],"type":"Point"}
}