{
  "type": "Feature",
  "properties": {
    "iso:country":"US",
    "sg:address":"3820 Southwood Dr",
    "sg:city":"Easton",
    "sg:classifiers":[
        {
            "category":"Real Estate",
            "subcategory":"Real Estate Agent",
            "type":"Services"
        }
    ],
    "sg:phone":"+1   ",
    "sg:postcode":"18045",
    "sg:province":"PA",
    "wof:name":"W L Moore & Son Real Estate",
    "wof:placetype":"venue"
},
  "geometry": {"coordinates":[-75.266096,40.653086],"type":"Point"}
}