{
  "type": "Feature",
  "properties": {
    "iso:country":"US",
    "sg:address":"1355 E Lehman St",
    "sg:city":"Lebanon",
    "sg:classifiers":[
        {
            "category":"Health Services",
            "subcategory":"Optometrist",
            "type":"Services"
        }
    ],
    "sg:phone":"+1   ",
    "sg:postcode":"17046",
    "sg:province":"PA",
    "wof:name":"Stephanie D Attig Od",
    "wof:placetype":"venue"
},
  "geometry": {"coordinates":[-76.38723899999999,40.349306],"type":"Point"}
}