{
  "type": "Feature",
  "properties": {
    "iso:country":"US",
    "sg:address":"289 Arcola Rd",
    "sg:city":"Collegeville",
    "sg:classifiers":[
        {
            "category":"Government",
            "subcategory":"Post Office",
            "type":"Public Place"
        }
    ],
    "sg:phone":"+1 610 489 4311",
    "sg:postcode":"19426",
    "sg:province":"PA",
    "wof:name":"US Post Office",
    "wof:placetype":"venue"
},
  "geometry": {"coordinates":[-75.456717,40.15312],"type":"Point"}
}