{
  "type": "Feature",
  "properties": {
    "iso:country":"US",
    "sg:address":"15 N Front St",
    "sg:city":"Clearfield",
    "sg:classifiers":[
        {
            "category":"Professional",
            "subcategory":"Lawyer & Legal Services",
            "type":"Services"
        }
    ],
    "sg:phone":"+1 814 765 8972",
    "sg:postcode":"16830",
    "sg:province":"PA",
    "sg:tags":[
        "attorney"
    ],
    "wof:name":"Belin & Kubista",
    "wof:placetype":"venue"
},
  "geometry": {"coordinates":[-78.439842,41.022079],"type":"Point"}
}