{
  "type": "Feature",
  "properties": {
    "iso:country":"US",
    "sg:address":"36 S Main St",
    "sg:city":"Manchester",
    "sg:classifiers":[
        {
            "category":"Personal",
            "subcategory":"Beauty Salon",
            "type":"Services"
        }
    ],
    "sg:phone":"+1 717 266 1385",
    "sg:postcode":"17345",
    "sg:province":"PA",
    "wof:name":"Rose's Magic Shears",
    "wof:placetype":"venue"
},
  "geometry": {"coordinates":[-76.721517,40.058231],"type":"Point"}
}