{
  "type": "Feature",
  "properties": {
    "iso:country":"US",
    "sg:address":"447 W Pittsburgh St",
    "sg:city":"Greensburg",
    "sg:classifiers":[
        {
            "category":"Health Services",
            "subcategory":"Doctor",
            "type":"Services"
        }
    ],
    "sg:phone":"+1   ",
    "sg:postcode":"15601",
    "sg:province":"PA",
    "sg:tags":[
        "medical"
    ],
    "wof:name":"Roman Stephen J MD PC",
    "wof:placetype":"venue"
},
  "geometry": {"coordinates":[-79.553202,40.300844],"type":"Point"}
}