{
  "type": "Feature",
  "properties": {
    "iso:country":"US",
    "sg:address":"145 Ridge St",
    "sg:city":"Bloomsburg",
    "sg:classifiers":[
        {
            "category":"Organizations",
            "subcategory":"Religious Organization",
            "type":"Services"
        }
    ],
    "sg:phone":"+1   ",
    "sg:postcode":"17815",
    "sg:province":"PA",
    "wof:name":"Ridge St Untd Methdst Church",
    "wof:placetype":"venue"
},
  "geometry": {"coordinates":[-76.38740900000001,41.013264],"type":"Point"}
}