{
  "type": "Feature",
  "properties": {
    "addr:full":"3180 W College Ave State College PA 16801",
    "addr:housenumber":"3180",
    "addr:postcode":"16801",
    "addr:street":"W College Ave",
    "iso:country":"US",
    "sg:address":"3180 W College Ave",
    "sg:city":"State College",
    "sg:classifiers":[
        {
            "category":"Manufacturing",
            "subcategory":"Rubber & Plastics",
            "type":"Manufacturing & Wholesale Goods"
        }
    ],
    "sg:phone":"+1   ",
    "sg:postcode":"16801",
    "sg:province":"PA",
    "sg:tags":[
        "injection",
        "molding"
    ],
    "wof:name":"Sol TEC Innovations Inc",
    "wof:placetype":"venue"
},
  "geometry": {"coordinates":[-77.876496,40.758137],"type":"Point"}
}