{
  "type": "Feature",
  "properties": {
    "iso:country":"US",
    "sg:address":"3551 S Broad St",
    "sg:city":"Philadelphia",
    "sg:classifiers":[
        {
            "category":"Manufacturing",
            "subcategory":"Printing",
            "type":"Manufacturing & Wholesale Goods"
        }
    ],
    "sg:phone":"+1 215 462 7244",
    "sg:postcode":"19148",
    "sg:province":"PA",
    "sg:tags":[
        "newspaper"
    ],
    "wof:name":"Chicago Sun-Times",
    "wof:placetype":"venue"
},
  "geometry": {"coordinates":[-75.173132,39.906673],"type":"Point"}
}