{
  "type": "Feature",
  "properties": {
    "iso:country":"US",
    "sg:address":"916 Strickler Rd",
    "sg:city":"Mount Joy",
    "sg:classifiers":[
        {
            "category":"Manufacturing",
            "subcategory":"Food",
            "type":"Manufacturing & Wholesale Goods"
        }
    ],
    "sg:phone":"+1   ",
    "sg:postcode":"17552",
    "sg:province":"PA",
    "sg:tags":[
        "product",
        "mfg"
    ],
    "wof:name":"Interstate Brands",
    "wof:placetype":"venue"
},
  "geometry": {"coordinates":[-76.46299500000001,40.116528],"type":"Point"}
}