{
  "type": "Feature",
  "properties": {
    "iso:country":"US",
    "sg:address":"2901 N 18th St Ste 2",
    "sg:city":"Philadelphia",
    "sg:classifiers":[
        {
            "category":"Personal",
            "type":"Services"
        }
    ],
    "sg:phone":"+1 215 842 3221",
    "sg:postcode":"19132",
    "sg:province":"PA",
    "sg:tags":[
        "party",
        "planning",
        "event"
    ],
    "sg:website":"www.cpgevents.com",
    "wof:name":"Cpg Events Llc",
    "wof:placetype":"venue"
},
  "geometry": {"coordinates":[-75.160085,39.997821],"type":"Point"}
}