{
  "type": "Feature",
  "properties": {
    "iso:country":"US",
    "sg:address":"165 Greble Rd",
    "sg:city":"Myerstown",
    "sg:classifiers":[
        {
            "category":"Home & Garden",
            "subcategory":"Building Materials",
            "type":"Retail Goods"
        }
    ],
    "sg:phone":"+1 717 738 4499",
    "sg:postcode":"17067",
    "sg:province":"PA",
    "sg:tags":[
        "door"
    ],
    "sg:website":"www.shankdoor.com",
    "wof:name":"Shank Door Co",
    "wof:placetype":"venue"
},
  "geometry": {"coordinates":[-76.32751399999999,40.427092],"type":"Point"}
}