{
  "type": "Feature",
  "properties": {
    "iso:country":"US",
    "sg:address":"1725 Summit Hill Rd",
    "sg:city":"Howard",
    "sg:classifiers":[
        {
            "category":"Organizations",
            "subcategory":"Religious Organization",
            "type":"Services"
        }
    ],
    "sg:phone":"+1 814 355 3995",
    "sg:postcode":"16841",
    "sg:province":"PA",
    "sg:tags":[
        "church"
    ],
    "wof:name":"Summit Hill Wesleyan Church",
    "wof:placetype":"venue"
},
  "geometry": {"coordinates":[-77.76738400000001,41.03996],"type":"Point"}
}