{
  "type": "Feature",
  "properties": {
    "iso:country":"US",
    "sg:address":"1146 Granite Dr",
    "sg:city":"Bethlehem",
    "sg:classifiers":[
        {
            "category":"Banks & Credit Unions",
            "subcategory":"Investment Brokerage",
            "type":"Services"
        }
    ],
    "sg:phone":"+1 610 691 2070",
    "sg:postcode":"18017",
    "sg:province":"PA",
    "sg:tags":[
        "advisory",
        "financial"
    ],
    "wof:name":"Jade Financial Advisors LLC",
    "wof:placetype":"venue"
},
  "geometry": {"coordinates":[-75.399458,40.663636],"type":"Point"}
}