{
  "type": "Feature",
  "properties": {
    "iso:country":"US",
    "sg:address":"1718 Sansom St",
    "sg:city":"Philadelphia",
    "sg:classifiers":[
        {
            "category":"Arts & Performance",
            "subcategory":"Arts Center",
            "type":"Entertainment"
        },
        {
            "category":"Arts & Performance",
            "subcategory":"Jazz & Blues",
            "type":"Entertainment"
        },
        {
            "category":"Bars & Pubs",
            "subcategory":"Lounge",
            "type":"Food & Drink"
        }
    ],
    "sg:phone":"+1 215 840 3577",
    "sg:postcode":"19103",
    "sg:province":"PA",
    "sg:tags":[
        "performing"
    ],
    "sg:website":"www.ravenlounge.com",
    "wof:name":"The Raven Lounge",
    "wof:placetype":"venue"
},
  "geometry": {"coordinates":[-75.169231,39.950744],"type":"Point"}
}