{
  "type": "Feature",
  "properties": {
    "iso:country":"US",
    "sg:address":"111 S 10th St",
    "sg:city":"Lemoyne",
    "sg:classifiers":[
        {
            "category":"Freight",
            "type":"Transportation"
        }
    ],
    "sg:phone":"+1   ",
    "sg:postcode":"17043",
    "sg:province":"PA",
    "sg:tags":[
        "courier"
    ],
    "wof:name":"United States Cargo & Courier",
    "wof:placetype":"venue"
},
  "geometry": {"coordinates":[-76.90219,40.239573],"type":"Point"}
}