{
  "type": "Feature",
  "properties": {
    "iso:country":"US",
    "sg:address":"1018 Penn St",
    "sg:city":"Pittsburgh",
    "sg:classifiers":[
        {
            "category":"Wholesale",
            "subcategory":"Home Furnishings",
            "type":"Manufacturing & Wholesale Goods"
        }
    ],
    "sg:phone":"+1 412 243 8557",
    "sg:postcode":"15215",
    "sg:province":"PA",
    "sg:tags":[
        "plumbing",
        "supplies-wholesale",
        "part",
        "fixture",
        "manufacturer"
    ],
    "wof:name":"Nbs Fabricating",
    "wof:placetype":"venue"
},
  "geometry": {"coordinates":[-79.932132,40.495995],"type":"Point"}
}