{
  "type": "Feature",
  "properties": {
    "iso:country":"US",
    "sg:address":"SE Cor 12th & Lombard",
    "sg:city":"Philadelphia",
    "sg:classifiers":[
        {
            "category":"Health Services",
            "subcategory":"Doctor",
            "type":"Services"
        }
    ],
    "sg:phone":"+1 800 257 7246",
    "sg:postcode":"19102",
    "sg:province":"PA",
    "wof:name":"Pain Center the",
    "wof:placetype":"venue"
},
  "geometry": {"coordinates":[-75.161557,39.944197],"type":"Point"}
}