{
  "type": "Feature",
  "properties": {
    "iso:country":"US",
    "sg:address":"1672 Graham Rd",
    "sg:city":"Williamsport",
    "sg:classifiers":[
        {
            "category":"Personal",
            "type":"Services"
        }
    ],
    "sg:phone":"+1 570 321 9567",
    "sg:postcode":"17701",
    "sg:province":"PA",
    "sg:tags":[
        "assistant"
    ],
    "sg:website":"http://www.kemcoenterprises.com",
    "wof:name":"Kemco Enterprises, Inc.",
    "wof:placetype":"venue"
},
  "geometry": {"coordinates":[-77.022694,41.256777],"type":"Point"}
}