{
  "type": "Feature",
  "properties": {
    "iso:country":"US",
    "sg:address":"109 48th St",
    "sg:city":"Pittsburgh",
    "sg:classifiers":[
        {
            "category":"Manufacturing",
            "subcategory":"Metals",
            "type":"Manufacturing & Wholesale Goods"
        }
    ],
    "sg:phone":"+1   ",
    "sg:postcode":"15201",
    "sg:province":"PA",
    "sg:tags":[
        "steel",
        "mining",
        "product",
        "related",
        "fabrication"
    ],
    "wof:name":"Diversified Wear Products",
    "wof:placetype":"venue"
},
  "geometry": {"coordinates":[-79.959182,40.476997],"type":"Point"}
}