{
  "type": "Feature",
  "properties": {
    "addr:full":"920 Mt. Airy Rd Collegeville PA 19426",
    "addr:housenumber":"920",
    "addr:postcode":"19426",
    "addr:street":"Mt. Airy Rd",
    "iso:country":"US",
    "sg:address":"920 Mt. Airy Rd",
    "sg:city":"Collegeville",
    "sg:classifiers":[
        {
            "category":"Arts & Performance",
            "subcategory":"Art Gallery",
            "type":"Entertainment"
        }
    ],
    "sg:phone":"+1 610 454 1321",
    "sg:postcode":"19426",
    "sg:province":"PA",
    "wof:name":"artexpo NY 2008",
    "wof:placetype":"venue"
},
  "geometry": {"coordinates":[-75.421531,40.211225],"type":"Point"}
}