{
  "type": "Feature",
  "properties": {
    "iso:country":"US",
    "sg:address":"300 2nd St",
    "sg:city":"Conemaugh",
    "sg:classifiers":[
        {
            "category":"Wholesale",
            "subcategory":"Beer",
            "type":"Manufacturing & Wholesale Goods"
        }
    ],
    "sg:phone":"+1 814 535 3359",
    "sg:postcode":"15909",
    "sg:province":"PA",
    "sg:tags":[
        "ale"
    ],
    "wof:name":"Conemaugh Beer",
    "wof:placetype":"venue"
},
  "geometry": {"coordinates":[-78.88602299999999,40.347941],"type":"Point"}
}