{
  "type": "Feature",
  "properties": {
    "iso:country":"US",
    "sg:address":"1917 W Cheltenham Ave",
    "sg:city":"Elkins Park",
    "sg:classifiers":[
        {
            "category":"Restaurant",
            "type":"Food & Drink"
        }
    ],
    "sg:phone":"+1 215 887 2337",
    "sg:postcode":"19027",
    "sg:province":"PA",
    "wof:name":"Jay Cheltenham Deli",
    "wof:placetype":"venue"
},
  "geometry": {"coordinates":[-75.147201,40.067829],"type":"Point"}
}