{
  "type": "Feature",
  "properties": {
    "iso:country":"US",
    "sg:address":"1600 W Ritner St",
    "sg:city":"Philadelphia",
    "sg:classifiers":[
        {
            "category":"Shopping",
            "subcategory":"Discount & Variety Stores",
            "type":"Retail Goods"
        }
    ],
    "sg:phone":"+1 215 462 3350",
    "sg:postcode":"19145",
    "sg:province":"PA",
    "wof:name":"DNT'S Variety Store",
    "wof:placetype":"venue"
},
  "geometry": {"coordinates":[-75.17430299999999,39.921129],"type":"Point"}
}