{
  "type": "Feature",
  "properties": {
    "iso:country":"US",
    "sg:address":"462 E King Rd",
    "sg:city":"Malvern",
    "sg:classifiers":[
        {
            "category":"Freight",
            "type":"Transportation"
        }
    ],
    "sg:phone":"+1 610 993 0911",
    "sg:postcode":"19355",
    "sg:province":"PA",
    "sg:tags":[
        "consultant"
    ],
    "wof:name":"Transportation Management",
    "wof:placetype":"venue"
},
  "geometry": {"coordinates":[-75.506604,40.038422],"type":"Point"}
}