{
  "type": "Feature",
  "properties": {
    "addr:full":"340 Logan St Carnegie PA 15106",
    "addr:housenumber":"340",
    "addr:postcode":"15106",
    "addr:street":"Logan St",
    "iso:country":"US",
    "sg:address":"340 Logan St",
    "sg:city":"Carnegie",
    "sg:classifiers":[
        {
            "category":"Retail",
            "subcategory":"Auto Repair",
            "type":"Services"
        }
    ],
    "sg:phone":"+1 412 277 5337",
    "sg:postcode":"15106",
    "sg:province":"PA",
    "sg:tags":[
        "oil",
        "change"
    ],
    "sg:website":"www.allabout-autos.com",
    "wof:name":"All About Autos",
    "wof:placetype":"venue"
},
  "geometry": {"coordinates":[-80.091677,40.405273],"type":"Point"}
}