{
  "type": "Feature",
  "properties": {
    "addr:full":"44 E Lancaster Ave Ardmore PA 19003",
    "addr:housenumber":"44",
    "addr:postcode":"19003",
    "addr:street":"E Lancaster Ave",
    "iso:country":"US",
    "sg:address":"44 E Lancaster Ave",
    "sg:city":"Ardmore",
    "sg:classifiers":[
        {
            "category":"Banks & Credit Unions",
            "subcategory":"Bank",
            "type":"Services"
        }
    ],
    "sg:phone":"+1   ",
    "sg:postcode":"19003",
    "sg:province":"PA",
    "sg:tags":[
        "federal",
        "savings",
        "institution"
    ],
    "wof:name":"Sovereign Bank",
    "wof:placetype":"venue"
},
  "geometry": {"coordinates":[-75.257576,39.990036],"type":"Point"}
}