{
  "type": "Feature",
  "properties": {
    "iso:country":"US",
    "sg:address":"3427 Freemont St",
    "sg:city":"Reading",
    "sg:classifiers":[
        {
            "category":"Building & Trades",
            "subcategory":"Construction",
            "type":"Services"
        }
    ],
    "sg:phone":"+1   ",
    "sg:postcode":"19605",
    "sg:province":"PA",
    "sg:tags":[
        "hanging",
        "contractor"
    ],
    "wof:name":"TLC Painting",
    "wof:placetype":"venue"
},
  "geometry": {"coordinates":[-75.918055,40.388582],"type":"Point"}
}