{
  "type": "Feature",
  "properties": {
    "iso:country":"US",
    "sg:address":"201 Industrial Blvd",
    "sg:city":"New Kensington",
    "sg:classifiers":[
        {
            "category":"Manufacturing",
            "subcategory":"Petroleum Products",
            "type":"Manufacturing & Wholesale Goods"
        }
    ],
    "sg:phone":"+1 724 339 1900",
    "sg:postcode":"15068",
    "sg:province":"PA",
    "sg:tags":[
        "asphalt"
    ],
    "wof:name":"I A Construction Corp",
    "wof:placetype":"venue"
},
  "geometry": {"coordinates":[-79.76481,40.55459],"type":"Point"}
}