{
  "type": "Feature",
  "properties": {
    "iso:country":"US",
    "sg:address":"503 School St",
    "sg:city":"Jeannette",
    "sg:classifiers":[
        {
            "category":"Building & Trades",
            "subcategory":"Construction",
            "type":"Services"
        }
    ],
    "sg:phone":"+1   ",
    "sg:postcode":"15644",
    "sg:province":"PA",
    "sg:tags":[
        "house"
    ],
    "wof:name":"Larry S Home Improvements",
    "wof:placetype":"venue"
},
  "geometry": {"coordinates":[-79.619186,40.336331],"type":"Point"}
}