{
  "type": "Feature",
  "properties": {
    "iso:country":"US",
    "sg:address":"356 Fairview Ave",
    "sg:city":"Mc Sherrystown",
    "sg:classifiers":[
        {
            "category":"Manufacturing",
            "subcategory":"Signs",
            "type":"Manufacturing & Wholesale Goods"
        }
    ],
    "sg:phone":"+1   ",
    "sg:postcode":"17344",
    "sg:province":"PA",
    "sg:tags":[
        "specialty",
        "mfg"
    ],
    "wof:name":"Delco Signs Inc",
    "wof:placetype":"venue"
},
  "geometry": {"coordinates":[-77.02010300000001,39.807135],"type":"Point"}
}