{
  "type": "Feature",
  "properties": {
    "iso:country":"US",
    "sg:address":"1100 E Orange St",
    "sg:city":"Lancaster",
    "sg:classifiers":[
        {
            "category":"Professional",
            "subcategory":"Management & Consulting",
            "type":"Services"
        }
    ],
    "sg:phone":"+1 717 291 8416",
    "sg:postcode":"17602",
    "sg:province":"PA",
    "sg:tags":[
        "health",
        "care"
    ],
    "wof:name":"Health Network Of Lancaster",
    "wof:placetype":"venue"
},
  "geometry": {"coordinates":[-76.27899499999999,40.0423],"type":"Point"}
}