{
  "type": "Feature",
  "properties": {
    "iso:country":"US",
    "sg:address":"8707 Cheltenham Ave",
    "sg:city":"Glenside",
    "sg:classifiers":[
        {
            "category":"Social Services",
            "subcategory":"Child Care",
            "type":"Services"
        }
    ],
    "sg:phone":"+1 215 836 5175",
    "sg:postcode":"19038",
    "sg:province":"PA",
    "wof:name":"Top Of The Hill Day Care Ctr",
    "wof:placetype":"venue"
},
  "geometry": {"coordinates":[-75.193337,40.095328],"type":"Point"}
}