{
  "type": "Feature",
  "properties": {
    "addr:full":"1406 3rd Ave Duncansville PA 16635",
    "addr:housenumber":"1406",
    "addr:postcode":"16635",
    "addr:street":"3Rd Ave",
    "iso:country":"US",
    "sg:address":"1406 3rd Ave",
    "sg:city":"Duncansville",
    "sg:classifiers":[
        {
            "category":"Personal",
            "type":"Services"
        }
    ],
    "sg:phone":"+1 814 695 7925",
    "sg:postcode":"16635",
    "sg:province":"PA",
    "wof:name":"Paragon Tattoo",
    "wof:placetype":"venue"
},
  "geometry": {"coordinates":[-78.436689,40.422567],"type":"Point"}
}