{
  "type": "Feature",
  "properties": {
    "addr:full":"54 E Oakland Ave Doylestown PA 18901",
    "addr:housenumber":"54",
    "addr:postcode":"18901",
    "addr:street":"E Oakland Ave",
    "iso:country":"US",
    "sg:address":"54 E Oakland Ave",
    "sg:city":"Doylestown",
    "sg:classifiers":[
        {
            "category":"Health Services",
            "subcategory":"Doctor",
            "type":"Services"
        }
    ],
    "sg:phone":"+1 215 489 2998",
    "sg:postcode":"18901",
    "sg:province":"PA",
    "sg:tags":[
        "psychiatrist"
    ],
    "wof:name":"Abel David R Psychiatrist",
    "wof:placetype":"venue"
},
  "geometry": {"coordinates":[-75.12869999999999,40.3097],"type":"Point"}
}