{
  "type": "Feature",
  "properties": {
    "addr:full":"1500 Industry Rd Ste H Hatfield PA 19440",
    "addr:housenumber":"1500",
    "addr:postcode":"19440",
    "addr:street":"Industry Rd Ste H",
    "iso:country":"US",
    "sg:address":"1500 Industry Rd Ste H",
    "sg:city":"Hatfield",
    "sg:classifiers":[
        {
            "category":"Retail",
            "subcategory":"Auto Repair",
            "type":"Services"
        }
    ],
    "sg:phone":"+1 215 361 1700",
    "sg:postcode":"19440",
    "sg:province":"PA",
    "sg:tags":[
        "windshield"
    ],
    "wof:name":"The Glass Emporium",
    "wof:placetype":"venue"
},
  "geometry": {"coordinates":[-75.282448,40.263131],"type":"Point"}
}