{
  "type": "Feature",
  "properties": {
    "iso:country":"US",
    "sg:address":"3125 Banksville Rd",
    "sg:city":"Pittsburgh",
    "sg:classifiers":[
        {
            "category":"Shopping",
            "subcategory":"Pharmacy",
            "type":"Retail Goods"
        }
    ],
    "sg:phone":"+1 412 531 8999",
    "sg:postcode":"15216",
    "sg:province":"PA",
    "sg:tags":[
        "drugstore"
    ],
    "wof:name":"Medfast Pharmacy Inc",
    "wof:placetype":"venue"
},
  "geometry": {"coordinates":[-80.044197,40.399601],"type":"Point"}
}