{
  "type": "Feature",
  "properties": {
    "iso:country":"US",
    "sg:address":"404 Fountain St",
    "sg:city":"Philadelphia",
    "sg:classifiers":[
        {
            "category":"Building & Trades",
            "subcategory":"Plumbing",
            "type":"Services"
        }
    ],
    "sg:phone":"+1 215 487 3113",
    "sg:postcode":"19128",
    "sg:province":"PA",
    "sg:tags":[
        "plumber",
        "industrial",
        "contractors-commercial"
    ],
    "wof:name":"Bruce Tinneny Plumbing & Htg",
    "wof:placetype":"venue"
},
  "geometry": {"coordinates":[-75.223827,40.037632],"type":"Point"}
}