{
  "type": "Feature",
  "properties": {
    "addr:full":"30 S 17th St Philadelphia PA 19103",
    "addr:housenumber":"30",
    "addr:postcode":"19103",
    "addr:street":"S 17Th St",
    "iso:country":"US",
    "sg:address":"30 S 17th St",
    "sg:city":"Philadelphia",
    "sg:classifiers":[
        {
            "category":"Professional",
            "subcategory":"Lawyer & Legal Services",
            "type":"Services"
        }
    ],
    "sg:phone":"+1 215 568 6400",
    "sg:postcode":"19103",
    "sg:province":"PA",
    "wof:name":"Koenig C Fredrick III Attorney",
    "wof:placetype":"venue"
},
  "geometry": {"coordinates":[-75.16860200000001,39.952099],"type":"Point"}
}