{
  "type": "Feature",
  "properties": {
    "addr:full":"141 E Main St Silverdale PA 18962",
    "addr:housenumber":"141",
    "addr:postcode":"18962",
    "addr:street":"E Main St",
    "iso:country":"US",
    "sg:address":"141 E Main St",
    "sg:city":"Silverdale",
    "sg:classifiers":[
        {
            "category":"Arts & Performance",
            "subcategory":"Arts Center",
            "type":"Entertainment"
        }
    ],
    "sg:phone":"+1 215 257 2292",
    "sg:postcode":"18962",
    "sg:province":"PA",
    "sg:tags":[
        "performing"
    ],
    "sg:website":"www.shannoncarneydance.com",
    "wof:name":"Shannon Carney Dance Academy",
    "wof:placetype":"venue"
},
  "geometry": {"coordinates":[-75.270172,40.349031],"type":"Point"}
}