{
  "type": "Feature",
  "properties": {
    "iso:country":"US",
    "sg:address":"77 Glendale Dr",
    "sg:city":"Lancaster",
    "sg:classifiers":[
        {
            "category":"Personal",
            "type":"Services"
        }
    ],
    "sg:phone":"+1 717 468 5214",
    "sg:postcode":"17602",
    "sg:province":"PA",
    "sg:tags":[
        "therapist",
        "massage"
    ],
    "wof:name":"KAT Massage",
    "wof:placetype":"venue"
},
  "geometry": {"coordinates":[-76.248166,40.040033],"type":"Point"}
}