{
  "type": "Feature",
  "properties": {
    "iso:country":"US",
    "sg:address":"243 S York Rd",
    "sg:city":"Hatboro",
    "sg:classifiers":[
        {
            "category":"Education",
            "subcategory":"Library",
            "type":"Public Place"
        }
    ],
    "sg:phone":"+1 215 672 1420",
    "sg:postcode":"19040",
    "sg:province":"PA",
    "wof:name":"Union Library-Hatboro",
    "wof:placetype":"venue"
},
  "geometry": {"coordinates":[-75.10763,40.173411],"type":"Point"}
}