{
  "type": "Feature",
  "properties": {
    "iso:country":"US",
    "sg:address":"1946 E Ontario St",
    "sg:city":"Philadelphia",
    "sg:classifiers":[
        {
            "category":"Bars & Pubs",
            "type":"Food & Drink"
        }
    ],
    "sg:phone":"+1   ",
    "sg:postcode":"19134",
    "sg:province":"PA",
    "sg:tags":[
        "drinking"
    ],
    "wof:name":"Murphys Tavern",
    "wof:placetype":"venue"
},
  "geometry": {"coordinates":[-75.107432,39.997596],"type":"Point"}
}