{
  "type": "Feature",
  "properties": {
    "iso:country":"US",
    "sg:address":"2240 Dekalb Pike",
    "sg:city":"Norristown",
    "sg:classifiers":[
        {
            "category":"Professional",
            "subcategory":"Lawyer & Legal Services",
            "type":"Services"
        }
    ],
    "sg:phone":"+1 610 272 7224",
    "sg:postcode":"19401",
    "sg:province":"PA",
    "sg:tags":[
        "attorney"
    ],
    "wof:name":"Wayne R Cromie",
    "wof:placetype":"venue"
},
  "geometry": {"coordinates":[-75.321455,40.132609],"type":"Point"}
}