{
  "type": "Feature",
  "properties": {
    "addr:full":"1524 Friedensburg Rd Reading PA 19606",
    "addr:housenumber":"1524",
    "addr:postcode":"19606",
    "addr:street":"Friedensburg Rd",
    "iso:country":"US",
    "sg:address":"1524 Friedensburg Rd",
    "sg:city":"Reading",
    "sg:classifiers":[
        {
            "category":"Wholesale",
            "subcategory":"Electrical",
            "type":"Manufacturing & Wholesale Goods"
        },
        {
            "category":"Autos & Motor Vehicles",
            "subcategory":"Auto Supplies",
            "type":"Retail Goods"
        }
    ],
    "sg:phone":"+1 610 370 2120",
    "sg:postcode":"19606",
    "sg:province":"PA",
    "sg:tags":[
        "automobile",
        "stereo",
        "radio",
        "car"
    ],
    "wof:name":"Jake's Discount Car Stereo",
    "wof:placetype":"venue"
},
  "geometry": {"coordinates":[-75.86776999999999,40.349776],"type":"Point"}
}