{
  "type": "Feature",
  "properties": {
    "iso:country":"US",
    "sg:address":"6564 Frankstown Ave",
    "sg:city":"Pittsburgh",
    "sg:classifiers":[
        {
            "category":"Autos & Motor Vehicles",
            "subcategory":"Auto Supplies",
            "type":"Retail Goods"
        }
    ],
    "sg:phone":"+1 412 363 0677",
    "sg:postcode":"15206",
    "sg:province":"PA",
    "sg:tags":[
        "automobile",
        "parts"
    ],
    "wof:name":"Pittsburgh Battery & Supplies",
    "wof:placetype":"venue"
},
  "geometry": {"coordinates":[-79.91237599999999,40.459946],"type":"Point"}
}