{
  "type": "Feature",
  "properties": {
    "addr:full":"628 Macbeth Dr Pittsburgh PA 15235",
    "addr:housenumber":"628",
    "addr:postcode":"15235",
    "addr:street":"Macbeth Dr",
    "iso:country":"US",
    "sg:address":"628 Macbeth Dr",
    "sg:city":"Pittsburgh",
    "sg:classifiers":[
        {
            "category":"Banks & Credit Unions",
            "subcategory":"Bank",
            "type":"Services"
        }
    ],
    "sg:phone":"+1   ",
    "sg:postcode":"15235",
    "sg:province":"PA",
    "sg:tags":[
        "broker",
        "mortgage"
    ],
    "wof:name":"Marquee Mortgage",
    "wof:placetype":"venue"
},
  "geometry": {"coordinates":[-79.807599,40.457168],"type":"Point"}
}