{
  "type": "Feature",
  "properties": {
    "addr:full":"15421 State Rte 8 Union City PA 16438",
    "addr:housenumber":"15421",
    "addr:postcode":"16438",
    "addr:street":"State Rte 8",
    "iso:country":"US",
    "sg:address":"15421 State Rte 8",
    "sg:city":"Union City",
    "sg:classifiers":[
        {
            "category":"Retail",
            "subcategory":"Repair Shop",
            "type":"Services"
        }
    ],
    "sg:phone":"+1   ",
    "sg:postcode":"16438",
    "sg:province":"PA",
    "wof:name":"Brian K & Tammy Sanden",
    "wof:placetype":"venue"
},
  "geometry": {"coordinates":[-79.843518,41.929885],"type":"Point"}
}