{
  "type": "Feature",
  "properties": {
    "iso:country":"US",
    "sg:address":"219 Gale Ln",
    "sg:city":"Kennett Square",
    "sg:classifiers":[
        {
            "category":"Retail",
            "subcategory":"Auto Repair",
            "type":"Services"
        },
        {
            "category":"Wholesale",
            "subcategory":"Auto Parts",
            "type":"Manufacturing & Wholesale Goods"
        }
    ],
    "sg:phone":"+1 610 444 5656",
    "sg:postcode":"19348",
    "sg:province":"PA",
    "sg:tags":[
        "trim",
        "upholstery",
        "supply",
        "automotive",
        "top",
        "automobile",
        "interior",
        "marine"
    ],
    "wof:name":"George Shaw & Associates Inc",
    "wof:placetype":"venue"
},
  "geometry": {"coordinates":[-75.703791,39.85211],"type":"Point"}
}