{
  "type": "Feature",
  "properties": {
    "iso:country":"US",
    "sg:address":"314 S Henderson Rd ",
    "sg:city":"King Of Prussia",
    "sg:classifiers":[
        {
            "category":"Restaurant",
            "type":"Food & Drink"
        }
    ],
    "sg:menulink":"http://www.allmenus.com/pa/upper-merion/288668-lemon-grass-thai-restaurant/menu/",
    "sg:phone":"+1 610 337 5986",
    "sg:postcode":"19406",
    "sg:province":"PA",
    "sg:tags":[
        "thai",
        "asian"
    ],
    "wof:name":"Lemon Grass Thai Restaurant",
    "wof:placetype":"venue"
},
  "geometry": {"coordinates":[-75.36035699999999,40.091581],"type":"Point"}
}