{
  "type": "Feature",
  "properties": {
    "iso:country":"US",
    "sg:address":"119 Otter St",
    "sg:city":"Bristol",
    "sg:classifiers":[
        {
            "category":"Building & Trades",
            "subcategory":"Plumbing",
            "type":"Services"
        }
    ],
    "sg:phone":"+1 215 785 1185",
    "sg:postcode":"19007",
    "sg:province":"PA",
    "wof:name":"Messenger Frank Plumber",
    "wof:placetype":"venue"
},
  "geometry": {"coordinates":[-74.861,40.096802],"type":"Point"}
}