{
  "type": "Feature",
  "properties": {
    "iso:country":"US",
    "sg:address":"225 Blvd of the Allies",
    "sg:city":"Pittsburgh",
    "sg:classifiers":[
        {
            "category":"Social Services",
            "type":"Services"
        }
    ],
    "sg:phone":"+1   ",
    "sg:postcode":"15222",
    "sg:province":"PA",
    "wof:name":"Red Cross",
    "wof:placetype":"venue"
},
  "geometry": {"coordinates":[-80.002298,40.438661],"type":"Point"}
}