{
  "type": "Feature",
  "properties": {
    "iso:country":"US",
    "sg:address":"515 S 12th St",
    "sg:city":"Philadelphia",
    "sg:classifiers":[
        {
            "category":"Health Services",
            "subcategory":"Clinic",
            "type":"Services"
        }
    ],
    "sg:phone":"+1   ",
    "sg:postcode":"19147",
    "sg:province":"PA",
    "wof:name":"Billing Office For Health Svcs",
    "wof:placetype":"venue"
},
  "geometry": {"coordinates":[-75.16170200000001,39.943207],"type":"Point"}
}