{
  "type": "Feature",
  "properties": {
    "addr:full":"717 Center St Scranton PA 18512",
    "addr:housenumber":"717",
    "addr:postcode":"18512",
    "addr:street":"Center St",
    "iso:country":"US",
    "sg:address":"717 Center St",
    "sg:city":"Scranton",
    "sg:classifiers":[
        {
            "category":"Shopping",
            "subcategory":"Musical Instruments",
            "type":"Retail Goods"
        }
    ],
    "sg:phone":"+1 570 383 3772",
    "sg:postcode":"18512",
    "sg:province":"PA",
    "sg:tags":[
        "repair",
        "equipment"
    ],
    "wof:name":"Cliff Girard Music Inc",
    "wof:placetype":"venue"
},
  "geometry": {"coordinates":[-75.617301,41.416784],"type":"Point"}
}