{
  "type": "Feature",
  "properties": {
    "iso:country":"US",
    "sg:address":"201 Colonial Park Dr",
    "sg:city":"Springfield",
    "sg:classifiers":[
        {
            "category":"Building & Trades",
            "subcategory":"Plumbing",
            "type":"Services"
        }
    ],
    "sg:phone":"+1   ",
    "sg:postcode":"19064",
    "sg:province":"PA",
    "sg:tags":[
        "air",
        "heating",
        "conditioning",
        "contractor"
    ],
    "wof:name":"Mainline Hvac",
    "wof:placetype":"venue"
},
  "geometry": {"coordinates":[-75.312219,39.938006],"type":"Point"}
}