{
  "type": "Feature",
  "properties": {
    "iso:country":"US",
    "sg:address":"331 Main St",
    "sg:city":"Ridgway",
    "sg:classifiers":[
        {
            "category":"Social Services",
            "type":"Services"
        }
    ],
    "sg:phone":"+1 814 772 4333",
    "sg:postcode":"15853",
    "sg:province":"PA",
    "sg:tags":[
        "organization",
        "welfare"
    ],
    "wof:name":"Early Intervention Services",
    "wof:placetype":"venue"
},
  "geometry": {"coordinates":[-78.72872099999999,41.422356],"type":"Point"}
}