{
  "type": "Feature",
  "properties": {
    "addr:full":"3100 Brownlee St Mc Keesport PA 15132",
    "addr:housenumber":"3100",
    "addr:postcode":"15132",
    "addr:street":"Brownlee St",
    "iso:country":"US",
    "sg:address":"3100 Brownlee St",
    "sg:city":"Mc Keesport",
    "sg:classifiers":[
        {
            "category":"Retail",
            "subcategory":"Self-service Laundry",
            "type":"Services"
        }
    ],
    "sg:phone":"+1   ",
    "sg:postcode":"15132",
    "sg:province":"PA",
    "sg:tags":[
        "coin"
    ],
    "wof:name":"J & L Laundry",
    "wof:placetype":"venue"
},
  "geometry": {"coordinates":[-79.839382,40.348797],"type":"Point"}
}