{
  "type": "Feature",
  "properties": {
    "addr:full":"12 State Rd Media PA 19063",
    "addr:housenumber":"12",
    "addr:postcode":"19063",
    "addr:street":"State Rd",
    "iso:country":"US",
    "sg:address":"12 State Rd",
    "sg:city":"Media",
    "sg:classifiers":[
        {
            "category":"Retail",
            "subcategory":"Auto Repair",
            "type":"Services"
        }
    ],
    "sg:phone":"+1 610 566 5017",
    "sg:postcode":"19063",
    "sg:province":"PA",
    "sg:tags":[
        "repairing",
        "automobile"
    ],
    "wof:name":"G & G Foreign Car Repair",
    "wof:placetype":"venue"
},
  "geometry": {"coordinates":[-75.384247,39.927933],"type":"Point"}
}