{
  "type": "Feature",
  "properties": {
    "addr:full":"145 Rockledge Ave Jenkintown PA 19046",
    "addr:housenumber":"145",
    "addr:postcode":"19046",
    "addr:street":"Rockledge Ave",
    "iso:country":"US",
    "sg:address":"145 Rockledge Ave",
    "sg:city":"Jenkintown",
    "sg:classifiers":[
        {
            "category":"Communications",
            "type":"Services"
        },
        {
            "category":"Communications",
            "subcategory":"Television Station",
            "type":"Services"
        }
    ],
    "sg:phone":"+1 215 663 3600",
    "sg:postcode":"19046",
    "sg:province":"PA",
    "sg:tags":[
        "satellite",
        "telecommunication",
        "systems-repair",
        "consultant",
        "telephone",
        "equipment",
        "cable"
    ],
    "wof:name":"Professional Services Incorporated",
    "wof:placetype":"venue"
},
  "geometry": {"coordinates":[-75.082892,40.084045],"type":"Point"}
}