{
  "type": "Feature",
  "properties": {
    "addr:full":"111 Cherry St Punxsutawney PA 15767",
    "addr:housenumber":"111",
    "addr:postcode":"15767",
    "addr:street":"Cherry St",
    "iso:country":"US",
    "sg:address":"111 Cherry St",
    "sg:city":"Punxsutawney",
    "sg:classifiers":[
        {
            "category":"Museum",
            "type":"Entertainment"
        }
    ],
    "sg:phone":"+1   ",
    "sg:postcode":"15767",
    "sg:province":"PA",
    "sg:tags":[
        "art",
        "gallery"
    ],
    "wof:name":"Images From Nature",
    "wof:placetype":"venue"
},
  "geometry": {"coordinates":[-78.97516299999999,40.945651],"type":"Point"}
}