{
  "type": "Feature",
  "properties": {
    "addr:full":"5545 N 5th St Philadelphia PA 19120",
    "addr:housenumber":"5545",
    "addr:postcode":"19120",
    "addr:street":"N 5Th St",
    "iso:country":"US",
    "sg:address":"5545 N 5th St",
    "sg:city":"Philadelphia",
    "sg:classifiers":[
        {
            "category":"Shopping",
            "subcategory":"Gifts & Souvenirs",
            "type":"Retail Goods"
        }
    ],
    "sg:phone":"+1   ",
    "sg:postcode":"19120",
    "sg:province":"PA",
    "wof:name":"Krazy Dollar Plus",
    "wof:placetype":"venue"
},
  "geometry": {"coordinates":[-75.130568,40.035665],"type":"Point"}
}