{
  "type": "Feature",
  "properties": {
    "iso:country":"US",
    "sg:address":"2127 7th Ave",
    "sg:city":"Altoona",
    "sg:classifiers":[
        {
            "category":"Professional",
            "subcategory":"Computer Services",
            "type":"Services"
        }
    ],
    "sg:phone":"+1 814 943 7008",
    "sg:postcode":"16602",
    "sg:province":"PA",
    "sg:tags":[
        "programing",
        "custom"
    ],
    "wof:name":"Affordable Computers Plus",
    "wof:placetype":"venue"
},
  "geometry": {"coordinates":[-78.404831,40.504903],"type":"Point"}
}