{
  "type": "Feature",
  "properties": {
    "iso:country":"US",
    "sg:address":"6606 Frankford Ave",
    "sg:city":"Philadelphia",
    "sg:classifiers":[
        {
            "category":"Food & Beverages",
            "subcategory":"Bakery",
            "type":"Retail Goods"
        }
    ],
    "sg:phone":"+1 215 332 3033",
    "sg:postcode":"19135",
    "sg:province":"PA",
    "sg:tags":[
        "baker"
    ],
    "wof:name":"Nonno Ugo's Italian Bakery",
    "wof:placetype":"venue"
},
  "geometry": {"coordinates":[-75.054277,40.031073],"type":"Point"}
}