{
  "type": "Feature",
  "properties": {
    "iso:country":"US",
    "sg:address":"29 S Enola Dr",
    "sg:city":"Enola",
    "sg:classifiers":[
        {
            "category":"Retail",
            "subcategory":"Funeral Services",
            "type":"Services"
        }
    ],
    "sg:phone":"+1 717 732 0587",
    "sg:postcode":"17025",
    "sg:province":"PA",
    "sg:tags":[
        "home",
        "cemetery"
    ],
    "wof:name":"Richardson Funeral Home Inc",
    "wof:placetype":"venue"
},
  "geometry": {"coordinates":[-76.93289900000001,40.287899],"type":"Point"}
}