{
  "type": "Feature",
  "properties": {
    "iso:country":"US",
    "sg:address":"4421 Pottsville Pike",
    "sg:city":"Reading",
    "sg:classifiers":[
        {
            "category":"Autos & Motor Vehicles",
            "subcategory":"Automobile Sales",
            "type":"Retail Goods"
        }
    ],
    "sg:phone":"+1 610 929 1086",
    "sg:postcode":"19605",
    "sg:province":"PA",
    "sg:tags":[
        "car",
        "dealer"
    ],
    "wof:name":"Matos Used Auto & Notary",
    "wof:placetype":"venue"
},
  "geometry": {"coordinates":[-75.936286,40.402011],"type":"Point"}
}