{
  "type": "Feature",
  "properties": {
    "iso:country":"US",
    "sg:address":"101 Lackawanna Trl",
    "sg:city":"Dalton",
    "sg:classifiers":[
        {
            "category":"Wholesale",
            "subcategory":"Hardware",
            "type":"Manufacturing & Wholesale Goods"
        },
        {
            "category":"Building & Trades",
            "subcategory":"Plumbing",
            "type":"Services"
        }
    ],
    "sg:phone":"+1 570 563 2923",
    "sg:postcode":"18414",
    "sg:province":"PA",
    "sg:tags":[
        "system",
        "air",
        "equipment",
        "refrigeration",
        "conditioning",
        "contractor"
    ],
    "wof:name":"Rite Temp Associates Inc",
    "wof:placetype":"venue"
},
  "geometry": {"coordinates":[-75.735518,41.526098],"type":"Point"}
}