{
  "type": "Feature",
  "properties": {
    "iso:country":"US",
    "sg:address":"1536 W Main St Apt E",
    "sg:city":"Ephrata",
    "sg:classifiers":[
        {
            "category":"Professional",
            "subcategory":"Lawyer & Legal Services",
            "type":"Services"
        }
    ],
    "sg:phone":"+1 717 733 2313",
    "sg:postcode":"17522",
    "sg:province":"PA",
    "sg:tags":[
        "attorney",
        "practice"
    ],
    "wof:name":"Morgan, George J",
    "wof:placetype":"venue"
},
  "geometry": {"coordinates":[-76.20237,40.197497],"type":"Point"}
}