{
  "type": "Feature",
  "properties": {
    "iso:country":"US",
    "sg:address":"901 E Brady St",
    "sg:city":"Butler",
    "sg:classifiers":[
        {
            "category":"Health Services",
            "subcategory":"Doctor",
            "type":"Services"
        }
    ],
    "sg:phone":"+1   ",
    "sg:postcode":"16001",
    "sg:province":"PA",
    "sg:tags":[
        "medical"
    ],
    "wof:name":"Philip M Lenko MD",
    "wof:placetype":"venue"
},
  "geometry": {"coordinates":[-79.88342299999999,40.866725],"type":"Point"}
}