{
  "type": "Feature",
  "properties": {
    "iso:country":"US",
    "sg:address":"5500 Aiken Rd",
    "sg:city":"Mc Kees Rocks",
    "sg:classifiers":[
        {
            "category":"Manufacturing",
            "subcategory":"Tools & Machinery",
            "type":"Manufacturing & Wholesale Goods"
        }
    ],
    "sg:phone":"+1 412 787 5377",
    "sg:postcode":"15136",
    "sg:province":"PA",
    "sg:tags":[
        "works",
        "mfg",
        "blast",
        "rolling",
        "mill",
        "furnace"
    ],
    "wof:name":"Furmanek Machine Co",
    "wof:placetype":"venue"
},
  "geometry": {"coordinates":[-80.12522800000001,40.457761],"type":"Point"}
}