{
  "type": "Feature",
  "properties": {
    "iso:country":"US",
    "sg:address":"607 Bethlehem Pike",
    "sg:city":"Flourtown",
    "sg:classifiers":[
        {
            "category":"Personal",
            "subcategory":"Beauty Salon",
            "type":"Services"
        }
    ],
    "sg:phone":"+1 215 233 2033",
    "sg:postcode":"19031",
    "sg:province":"PA",
    "sg:tags":[
        "manicuring"
    ],
    "wof:name":"Hot Nails",
    "wof:placetype":"venue"
},
  "geometry": {"coordinates":[-75.21580400000001,40.119879],"type":"Point"}
}