{
  "type": "Feature",
  "properties": {
    "addr:full":"1648 Allegheny Rd Manns Choice PA 15550",
    "addr:housenumber":"1648",
    "addr:postcode":"15550",
    "addr:street":"Allegheny Rd",
    "iso:country":"US",
    "sg:address":"1648 Allegheny Rd",
    "sg:city":"Manns Choice",
    "sg:classifiers":[
        {
            "category":"Retail",
            "subcategory":"Auto Repair",
            "type":"Services"
        }
    ],
    "sg:phone":"+1 814 733 4821",
    "sg:postcode":"15550",
    "sg:province":"PA",
    "sg:tags":[
        "repairing",
        "automobile"
    ],
    "wof:name":"Mike's Auto Electric",
    "wof:placetype":"venue"
},
  "geometry": {"coordinates":[-78.742192,39.972028],"type":"Point"}
}