{
  "type": "Feature",
  "properties": {
    "addr:full":"1082 Dekalb St Bridgeport PA 19405",
    "addr:housenumber":"1082",
    "addr:postcode":"19405",
    "addr:street":"Dekalb St",
    "iso:country":"US",
    "sg:address":"1082 Dekalb St",
    "sg:city":"Bridgeport",
    "sg:classifiers":[
        {
            "category":"Autos & Motor Vehicles",
            "subcategory":"Automobile Sales",
            "type":"Retail Goods"
        }
    ],
    "sg:phone":"+1   ",
    "sg:postcode":"19405",
    "sg:province":"PA",
    "sg:tags":[
        "new",
        "used"
    ],
    "wof:name":"Eger Subaru-Suzuki",
    "wof:placetype":"venue"
},
  "geometry": {"coordinates":[-75.349301,40.101824],"type":"Point"}
}