{
  "type": "Feature",
  "properties": {
    "addr:full":"1306 W State St New Castle PA 16101",
    "addr:housenumber":"1306",
    "addr:postcode":"16101",
    "addr:street":"W State St",
    "iso:country":"US",
    "sg:address":"1306 W State St",
    "sg:city":"New Castle",
    "sg:classifiers":[
        {
            "category":"Restaurant",
            "type":"Food & Drink"
        }
    ],
    "sg:phone":"+1 724 658 5000",
    "sg:postcode":"16101",
    "sg:province":"PA",
    "sg:tags":[
        "eating"
    ],
    "wof:name":"Triple Crown Events",
    "wof:placetype":"venue"
},
  "geometry": {"coordinates":[-80.368826,41.005147],"type":"Point"}
}