{
  "type": "Feature",
  "properties": {
    "iso:country":"US",
    "sg:address":"Fleecy Dale Rd",
    "sg:city":"Carversville",
    "sg:classifiers":[
        {
            "category":"Building & Trades",
            "subcategory":"Construction",
            "type":"Services"
        },
        {
            "category":"Building & Trades",
            "subcategory":"Electrical",
            "type":"Services"
        }
    ],
    "sg:phone":"+1 215 297 5777",
    "sg:postcode":"18913",
    "sg:province":"PA",
    "sg:tags":[
        "electrician",
        "contractor"
    ],
    "wof:name":"Livezey J Walter & Sons",
    "wof:placetype":"venue"
},
  "geometry": {"coordinates":[-75.04239699999999,40.379501],"type":"Point"}
}