{
  "type": "Feature",
  "properties": {
    "iso:country":"US",
    "sg:address":"710 5th Ave",
    "sg:city":"New Kensington",
    "sg:classifiers":[
        {
            "category":"Manufacturing",
            "subcategory":"Glass & Minerals",
            "type":"Manufacturing & Wholesale Goods"
        }
    ],
    "sg:phone":"+1   ",
    "sg:postcode":"15068",
    "sg:province":"PA",
    "sg:tags":[
        "beveled",
        "mfr"
    ],
    "wof:name":"Valley Glass and Beveling",
    "wof:placetype":"venue"
},
  "geometry": {"coordinates":[-79.76472200000001,40.563827],"type":"Point"}
}