{
  "type": "Feature",
  "properties": {
    "iso:country":"US",
    "sg:address":"2700 Duss Ave",
    "sg:city":"Ambridge",
    "sg:classifiers":[
        {
            "category":"Home & Garden",
            "subcategory":"Building Materials",
            "type":"Retail Goods"
        }
    ],
    "sg:phone":"+1   ",
    "sg:postcode":"15003",
    "sg:province":"PA",
    "sg:tags":[
        "lumber",
        "supply"
    ],
    "wof:name":"Ambridge Lumber & Bldrs Sup Co",
    "wof:placetype":"venue"
},
  "geometry": {"coordinates":[-80.22635,40.612774],"type":"Point"}
}