{
  "type": "Feature",
  "properties": {
    "addr:full":"830 Unionville Rd Prospect PA 16052",
    "addr:housenumber":"830",
    "addr:postcode":"16052",
    "addr:street":"Unionville Rd",
    "iso:country":"US",
    "sg:address":"830 Unionville Rd",
    "sg:city":"Prospect",
    "sg:classifiers":[
        {
            "category":"Manufacturing",
            "subcategory":"Chemicals & Compounds",
            "type":"Manufacturing & Wholesale Goods"
        },
        {
            "category":"Building & Trades",
            "subcategory":"Cleaning & Sanitation",
            "type":"Services"
        },
        {
            "category":"Building & Trades",
            "subcategory":"Construction",
            "type":"Services"
        },
        {
            "category":"Manufacturing",
            "subcategory":"Building Materials",
            "type":"Manufacturing & Wholesale Goods"
        }
    ],
    "sg:phone":"+1 724 576 4042",
    "sg:postcode":"16052",
    "sg:province":"PA",
    "sg:tags":[
        "concrete-stamped",
        "decorative",
        "product",
        "patching",
        "concrete",
        "restoration",
        "sealing"
    ],
    "wof:name":"Specialty Concrete Coatings, LLC.",
    "wof:placetype":"venue"
},
  "geometry": {"coordinates":[-80.031678,40.907301],"type":"Point"}
}