{
  "type": "Feature",
  "properties": {
    "addr:full":"125 Scarlet Dr Conshohocken PA 19428",
    "addr:housenumber":"125",
    "addr:postcode":"19428",
    "addr:street":"Scarlet Dr",
    "iso:country":"US",
    "sg:address":"125 Scarlet Dr",
    "sg:city":"Conshohocken",
    "sg:classifiers":[
        {
            "category":"Autos & Motor Vehicles",
            "subcategory":"Fuel & Gas Station",
            "type":"Retail Goods"
        }
    ],
    "sg:phone":"+1   ",
    "sg:postcode":"19428",
    "sg:province":"PA",
    "sg:tags":[
        "station",
        "gasoline"
    ],
    "wof:name":"Selvanathan Rani",
    "wof:placetype":"venue"
},
  "geometry": {"coordinates":[-75.29760400000001,40.090595],"type":"Point"}
}