{
  "type": "Feature",
  "properties": {
    "addr:full":"45 W Delaware Ave Marcus Hook PA 19061",
    "addr:housenumber":"45",
    "addr:postcode":"19061",
    "addr:street":"W Delaware Ave",
    "iso:country":"US",
    "sg:address":"45 W Delaware Ave",
    "sg:city":"Marcus Hook",
    "sg:classifiers":[
        {
            "category":"Ferry",
            "type":"Transportation"
        }
    ],
    "sg:phone":"+1 610 485 0852",
    "sg:postcode":"19061",
    "sg:province":"PA",
    "sg:tags":[
        "boat"
    ],
    "wof:name":"Huebner Launch Svc",
    "wof:placetype":"venue"
},
  "geometry": {"coordinates":[-75.413105,39.812169],"type":"Point"}
}