{
  "type": "Feature",
  "properties": {
    "iso:country":"US",
    "sg:address":"39 State Dr",
    "sg:city":"Harrisburg",
    "sg:classifiers":[
        {
            "category":"Travel",
            "subcategory":"Hotels & Motels",
            "type":"Entertainment"
        }
    ],
    "sg:phone":"+1 717 652 9578",
    "sg:postcode":"17112",
    "sg:province":"PA",
    "sg:website":"www.tatravelcenters.com",
    "wof:name":"Day Stop Motel",
    "wof:placetype":"venue"
},
  "geometry": {"coordinates":[-76.80015899999999,40.31918],"type":"Point"}
}