{
  "type": "Feature",
  "properties": {
    "iso:country":"US",
    "sg:address":"104 Mulberry St",
    "sg:city":"Kittanning",
    "sg:classifiers":[
        {
            "category":"Professional",
            "subcategory":"Lawyer & Legal Services",
            "type":"Services"
        }
    ],
    "sg:phone":"+1   ",
    "sg:postcode":"16201",
    "sg:province":"PA",
    "wof:name":"Cindy L Calarie",
    "wof:placetype":"venue"
},
  "geometry": {"coordinates":[-79.51786300000001,40.811105],"type":"Point"}
}