{
  "type": "Feature",
  "properties": {
    "iso:country":"US",
    "sg:address":"2 19th St",
    "sg:city":"Sharpsburg",
    "sg:classifiers":[
        {
            "category":"Building & Trades",
            "subcategory":"Equipment Rental",
            "type":"Services"
        },
        {
            "category":"Building & Trades",
            "subcategory":"Construction",
            "type":"Services"
        }
    ],
    "sg:phone":"+1 412 782 2060",
    "sg:postcode":"15215",
    "sg:province":"PA",
    "sg:tags":[
        "yard",
        "scaffolding",
        "lift",
        "leasing",
        "aerial",
        "store"
    ],
    "sg:website":"http://www.safway.com",
    "wof:name":"Safway Services",
    "wof:placetype":"venue"
},
  "geometry": {"coordinates":[-79.918098,40.494068],"type":"Point"}
}