{
  "type": "Feature",
  "properties": {
    "iso:country":"US",
    "sg:address":"6325 State Rte 309",
    "sg:city":"New Tripoli",
    "sg:classifiers":[
        {
            "category":"Professional",
            "subcategory":"Management & Consulting",
            "type":"Services"
        },
        {
            "category":"Professional",
            "subcategory":"Accounting & Tax Preparation",
            "type":"Services"
        }
    ],
    "sg:phone":"+1 610 767 9560",
    "sg:postcode":"18066",
    "sg:province":"PA",
    "sg:tags":[
        "consultant",
        "s",
        "business"
    ],
    "wof:name":"Small Business Associates",
    "wof:placetype":"venue"
},
  "geometry": {"coordinates":[-75.70787900000001,40.680103],"type":"Point"}
}