{
  "type": "Feature",
  "properties": {
    "addr:full":"221 N Broad St Philadelphia PA 19107",
    "addr:housenumber":"221",
    "addr:postcode":"19107",
    "addr:street":"N Broad St",
    "iso:country":"US",
    "sg:address":"221 N Broad St",
    "sg:city":"Philadelphia",
    "sg:classifiers":[
        {
            "category":"Government",
            "subcategory":"Office",
            "type":"Public Place"
        }
    ],
    "sg:phone":"+1 215 597 7282",
    "sg:postcode":"19107",
    "sg:province":"PA",
    "sg:tags":[
        "armed",
        "force",
        "recruiting"
    ],
    "wof:name":"Us Coast Guard Recruiting",
    "wof:placetype":"venue"
},
  "geometry": {"coordinates":[-75.16234900000001,39.957343],"type":"Point"}
}