{
  "type": "Feature",
  "properties": {
    "addr:full":"1551 S Valley Forge Rd Lansdale PA 19446",
    "addr:housenumber":"1551",
    "addr:postcode":"19446",
    "addr:street":"S Valley Forge Rd",
    "iso:country":"US",
    "sg:address":"1551 S Valley Forge Rd",
    "sg:city":"Lansdale",
    "sg:classifiers":[
        {
            "category":"Arena",
            "subcategory":"Sports Club",
            "type":"Entertainment"
        }
    ],
    "sg:phone":"+1 215 393 5425",
    "sg:postcode":"19446",
    "sg:province":"PA",
    "sg:tags":[
        "martial art"
    ],
    "wof:name":"AmeriKick Karate",
    "wof:placetype":"venue"
},
  "geometry": {"coordinates":[-75.31515400000001,40.228754],"type":"Point"}
}