{
  "type": "Feature",
  "properties": {
    "iso:country":"US",
    "sg:address":"3079 William Penn Hwy",
    "sg:city":"Easton",
    "sg:classifiers":[
        {
            "category":"Retail",
            "subcategory":"Laundry & Dry Cleaning",
            "type":"Services"
        }
    ],
    "sg:phone":"+1 610 258 8988",
    "sg:postcode":"18045",
    "sg:province":"PA",
    "sg:tags":[
        "cleaners"
    ],
    "wof:name":"Lehigh Valley Dry Cleaning",
    "wof:placetype":"venue"
},
  "geometry": {"coordinates":[-75.26114099999999,40.676989],"type":"Point"}
}