{
  "type": "Feature",
  "properties": {
    "addr:full":"2200 Stafford Ave Scranton PA 18505",
    "addr:housenumber":"2200",
    "addr:postcode":"18505",
    "addr:street":"Stafford Ave",
    "iso:country":"US",
    "sg:address":"2200 Stafford Ave",
    "sg:city":"Scranton",
    "sg:classifiers":[
        {
            "category":"Shopping",
            "type":"Retail Goods"
        }
    ],
    "sg:phone":"+1 570 342 5040",
    "sg:postcode":"18505",
    "sg:province":"PA",
    "sg:tags":[
        "merchandise"
    ],
    "wof:name":"Edwards Business Systems Inc",
    "wof:placetype":"venue"
},
  "geometry": {"coordinates":[-75.670902,41.380206],"type":"Point"}
}