{
  "type": "Feature",
  "properties": {
    "iso:country":"US",
    "sg:address":"2344 Back Run Rd",
    "sg:city":"Manheim",
    "sg:classifiers":[
        {
            "category":"Health Services",
            "subcategory":"Nursing And Care Facility",
            "type":"Services"
        }
    ],
    "sg:phone":"+1   ",
    "sg:postcode":"17545",
    "sg:province":"PA",
    "sg:tags":[
        "skilled"
    ],
    "wof:name":"Premier Care Nursing",
    "wof:placetype":"venue"
},
  "geometry": {"coordinates":[-76.458656,40.140838],"type":"Point"}
}