{
  "type": "Feature",
  "properties": {
    "iso:country":"US",
    "sg:address":"390 Paradise Rd",
    "sg:city":"Denver",
    "sg:classifiers":[
        {
            "category":"Personal",
            "subcategory":"Beauty Salon",
            "type":"Services"
        }
    ],
    "sg:phone":"+1 717 336 1223",
    "sg:postcode":"17517",
    "sg:province":"PA",
    "sg:tags":[
        "shop"
    ],
    "wof:name":"Kelly's Hair Design",
    "wof:placetype":"venue"
},
  "geometry": {"coordinates":[-76.136584,40.256048],"type":"Point"}
}