{
  "type": "Feature",
  "properties": {
    "iso:country":"US",
    "sg:address":"3720 N Broad St",
    "sg:city":"Philadelphia",
    "sg:classifiers":[
        {
            "category":"Education",
            "subcategory":"Library",
            "type":"Public Place"
        }
    ],
    "sg:phone":"+1 215 685 9790",
    "sg:postcode":"19140",
    "sg:province":"PA",
    "wof:name":"Nicetown Library",
    "wof:placetype":"venue"
},
  "geometry": {"coordinates":[-75.15084,40.010648],"type":"Point"}
}