{
  "type": "Feature",
  "properties": {
    "iso:country":"US",
    "sg:address":"910 Robertson Rd",
    "sg:city":"Hermitage",
    "sg:classifiers":[
        {
            "category":"Building & Trades",
            "subcategory":"Construction",
            "type":"Services"
        }
    ],
    "sg:phone":"+1 724 981 8134",
    "sg:postcode":"16148",
    "sg:province":"PA",
    "sg:tags":[
        "contractor"
    ],
    "wof:name":"Mega Builders",
    "wof:placetype":"venue"
},
  "geometry": {"coordinates":[-80.41847,41.245513],"type":"Point"}
}