{
  "type": "Feature",
  "properties": {
    "iso:country":"US",
    "sg:address":"437 Main St",
    "sg:city":"Prospect",
    "sg:classifiers":[
        {
            "category":"Building & Trades",
            "subcategory":"Plumbing",
            "type":"Services"
        }
    ],
    "sg:phone":"+1 724 865 2891",
    "sg:postcode":"16052",
    "sg:province":"PA",
    "sg:tags":[
        "plumbing",
        "contractor"
    ],
    "wof:name":"M D Sarvey Plumbing & Heating",
    "wof:placetype":"venue"
},
  "geometry": {"coordinates":[-80.05137999999999,40.904452],"type":"Point"}
}