{
  "type": "Feature",
  "properties": {
    "iso:country":"US",
    "sg:address":"603 Georgian Pl",
    "sg:city":"Somerset",
    "sg:classifiers":[
        {
            "category":"Sports & Exercise",
            "subcategory":"Gym",
            "type":"Entertainment"
        }
    ],
    "sg:phone":"+1 814 444 9110",
    "sg:postcode":"15501",
    "sg:province":"PA",
    "sg:tags":[
        "club",
        "health",
        "studio",
        "gymnasium"
    ],
    "wof:name":"New World Gym",
    "wof:placetype":"venue"
},
  "geometry": {"coordinates":[-79.07426,40.022923],"type":"Point"}
}