{
  "type": "Feature",
  "properties": {
    "iso:country":"US",
    "sg:address":"329 Market St",
    "sg:city":"Middletown",
    "sg:classifiers":[
        {
            "category":"Organizations",
            "subcategory":"Religious Organization",
            "type":"Services"
        }
    ],
    "sg:phone":"+1 717 944 3797",
    "sg:postcode":"17057",
    "sg:province":"PA",
    "sg:tags":[
        "church"
    ],
    "wof:name":"Ebenezer African Methodist",
    "wof:placetype":"venue"
},
  "geometry": {"coordinates":[-76.738443,40.19319],"type":"Point"}
}