{
  "type": "Feature",
  "properties": {
    "iso:country":"US",
    "sg:address":"912 Washington Ave",
    "sg:city":"Carnegie",
    "sg:classifiers":[
        {
            "category":"Banks & Credit Unions",
            "subcategory":"Investment Brokerage",
            "type":"Services"
        },
        {
            "category":"Insurance",
            "subcategory":"Hazard Insurance",
            "type":"Services"
        }
    ],
    "sg:phone":"+1 412 276 5010",
    "sg:postcode":"15106",
    "sg:province":"PA",
    "sg:tags":[
        "investing"
    ],
    "sg:website":"www.selectfg.com",
    "wof:name":"Select Financial Group",
    "wof:placetype":"venue"
},
  "geometry": {"coordinates":[-80.08290100000001,40.4002],"type":"Point"}
}