{
  "type": "Feature",
  "properties": {
    "iso:country":"US",
    "sg:address":"2936 Normandy Dr",
    "sg:city":"Philadelphia",
    "sg:classifiers":[
        {
            "category":"Wholesale",
            "subcategory":"Machinery & Supplies",
            "type":"Manufacturing & Wholesale Goods"
        }
    ],
    "sg:phone":"+1 215 947 1499",
    "sg:postcode":"19154",
    "sg:province":"PA",
    "sg:tags":[
        "designed",
        "specially"
    ],
    "wof:name":"Rfs Design Enterprises, Inc.",
    "wof:placetype":"venue"
},
  "geometry": {"coordinates":[-74.99665299999999,40.105703],"type":"Point"}
}