{
  "type": "Feature",
  "properties": {
    "iso:country":"US",
    "sg:address":"315 W Aaron Dr",
    "sg:city":"State College",
    "sg:classifiers":[
        {
            "category":"Retail",
            "subcategory":"Self-service Laundry",
            "type":"Services"
        }
    ],
    "sg:phone":"+1 814 238 7235",
    "sg:postcode":"16803",
    "sg:province":"PA",
    "wof:name":"Proservco Inc",
    "wof:placetype":"venue"
},
  "geometry": {"coordinates":[-77.893376,40.806208],"type":"Point"}
}