{
  "type": "Feature",
  "properties": {
    "addr:full":"345 Ewing Rd Carnegie PA 15106",
    "addr:housenumber":"345",
    "addr:postcode":"15106",
    "addr:street":"Ewing Rd",
    "iso:country":"US",
    "sg:address":"345 Ewing Rd",
    "sg:city":"Carnegie",
    "sg:classifiers":[
        {
            "category":"Building & Trades",
            "subcategory":"Landscaping Services",
            "type":"Services"
        }
    ],
    "sg:phone":"+1 412 429 8873",
    "sg:postcode":"15106",
    "sg:province":"PA",
    "sg:tags":[
        "landscape",
        "contractor"
    ],
    "wof:name":"Perma Green Lawn Care",
    "wof:placetype":"venue"
},
  "geometry": {"coordinates":[-80.113787,40.408949],"type":"Point"}
}