{
  "type": "Feature",
  "properties": {
    "iso:country":"US",
    "sg:address":"2006 Paper Mill Rd",
    "sg:city":"Oreland",
    "sg:classifiers":[
        {
            "category":"Building & Trades",
            "subcategory":"Landscaping Services",
            "type":"Services"
        }
    ],
    "sg:phone":"+1 215 402 0931",
    "sg:postcode":"19075",
    "sg:province":"PA",
    "sg:tags":[
        "lawn"
    ],
    "wof:name":"Cantres Landscaping Inc",
    "wof:placetype":"venue"
},
  "geometry": {"coordinates":[-75.191442,40.104236],"type":"Point"}
}