{
  "type": "Feature",
  "properties": {
    "iso:country":"US",
    "sg:address":"55 N 22nd St",
    "sg:city":"Philadelphia",
    "sg:classifiers":[
        {
            "category":"Education",
            "subcategory":"School",
            "type":"Public Place"
        }
    ],
    "sg:phone":"+1 215 979 5620",
    "sg:postcode":"19103",
    "sg:province":"PA",
    "sg:tags":[
        "high",
        "middle"
    ],
    "sg:website":"http://www.philsch.k12.pa.us",
    "wof:name":"Science Leadership Academy",
    "wof:placetype":"venue"
},
  "geometry": {"coordinates":[-75.176284,39.95483],"type":"Point"}
}