{
  "type": "Feature",
  "properties": {
    "addr:full":"849 Oak St Lebanon PA 17042",
    "addr:housenumber":"849",
    "addr:postcode":"17042",
    "addr:street":"Oak St",
    "iso:country":"US",
    "sg:address":"849 Oak St",
    "sg:city":"Lebanon",
    "sg:classifiers":[
        {
            "category":"Restaurant",
            "type":"Food & Drink"
        }
    ],
    "sg:phone":"+1 717 270 9830",
    "sg:postcode":"17042",
    "sg:province":"PA",
    "sg:tags":[
        "eating"
    ],
    "wof:name":"R C Deli & Catering",
    "wof:placetype":"venue"
},
  "geometry": {"coordinates":[-76.42472100000001,40.333428],"type":"Point"}
}