{
  "type": "Feature",
  "properties": {
    "iso:country":"US",
    "sg:address":"4690 List Rd",
    "sg:city":"Red Lion",
    "sg:classifiers":[
        {
            "category":"Building & Trades",
            "subcategory":"Construction",
            "type":"Services"
        }
    ],
    "sg:phone":"+1   ",
    "sg:postcode":"17356",
    "sg:province":"PA",
    "sg:tags":[
        "subcontractor",
        "carpentry"
    ],
    "wof:name":"Jensco",
    "wof:placetype":"venue"
},
  "geometry": {"coordinates":[-76.657245,39.859083],"type":"Point"}
}