{
  "type": "Feature",
  "properties": {
    "iso:country":"US",
    "sg:address":"1705 E Carson St",
    "sg:city":"Pittsburgh",
    "sg:classifiers":[
        {
            "category":"Food & Beverages",
            "subcategory":"Candy",
            "type":"Retail Goods"
        },
        {
            "category":"Ice Cream",
            "type":"Food & Drink"
        }
    ],
    "sg:phone":"+1 877 488 1808",
    "sg:postcode":"15217",
    "sg:province":"PA",
    "sg:tags":[
        "frozen",
        "dessert",
        "yogurt"
    ],
    "sg:website":"www.themilkshakefactory.com",
    "wof:name":"The Milk Shake Factory",
    "wof:placetype":"venue"
},
  "geometry": {"coordinates":[-79.981722,40.429118],"type":"Point"}
}