{
  "type": "Feature",
  "properties": {
    "iso:country":"US",
    "sg:address":"705 Cragmoor Rd",
    "sg:city":"York Haven",
    "sg:classifiers":[
        {
            "category":"Building & Trades",
            "subcategory":"Construction",
            "type":"Services"
        }
    ],
    "sg:phone":"+1 717 268 1880",
    "sg:postcode":"17370",
    "sg:province":"PA",
    "sg:tags":[
        "concrete",
        "contractor"
    ],
    "wof:name":"Sipe Driveway Sealing",
    "wof:placetype":"venue"
},
  "geometry": {"coordinates":[-76.760729,40.100972],"type":"Point"}
}