{
  "type": "Feature",
  "properties": {
    "iso:country":"US",
    "sg:address":"181 Simons Dr",
    "sg:city":"Morrisville",
    "sg:classifiers":[
        {
            "category":"Professional",
            "subcategory":"Secretarial Services",
            "type":"Services"
        },
        {
            "category":"Professional",
            "subcategory":"Employment Agencies",
            "type":"Services"
        }
    ],
    "sg:phone":"+1 215 736 8037",
    "sg:postcode":"19067",
    "sg:province":"PA",
    "sg:tags":[
        "typing"
    ],
    "wof:name":"Accu-Type",
    "wof:placetype":"venue"
},
  "geometry": {"coordinates":[-74.832454,40.200654],"type":"Point"}
}