{
  "type": "Feature",
  "properties": {
    "iso:country":"US",
    "sg:address":"944 Penn Green Rd",
    "sg:city":"Avondale",
    "sg:classifiers":[
        {
            "category":"Wholesale",
            "subcategory":"Fruits & Vegetables",
            "type":"Manufacturing & Wholesale Goods"
        }
    ],
    "sg:phone":"+1 610 268 3110",
    "sg:postcode":"19311",
    "sg:province":"PA",
    "wof:name":"Village Farms LP",
    "wof:placetype":"venue"
},
  "geometry": {"coordinates":[-75.768756,39.823938],"type":"Point"}
}