{
  "type": "Feature",
  "properties": {
    "iso:country":"US",
    "sg:address":"2806 Township Line Rd",
    "sg:city":"Drexel Hill",
    "sg:classifiers":[
        {
            "category":"Autos & Motor Vehicles",
            "subcategory":"Fuel & Gas Station",
            "type":"Retail Goods"
        }
    ],
    "sg:phone":"+1   ",
    "sg:postcode":"19026",
    "sg:province":"PA",
    "sg:tags":[
        "station",
        "gasoline"
    ],
    "wof:name":"Township Line Texaco",
    "wof:placetype":"venue"
},
  "geometry": {"coordinates":[-75.302903,39.964533],"type":"Point"}
}