{
  "type": "Feature",
  "properties": {
    "iso:country":"US",
    "sg:address":"6005 Schoolhouse Rd",
    "sg:city":"Elizabethtown",
    "sg:classifiers":[
        {
            "category":"Farming",
            "subcategory":"Nursery",
            "type":"Manufacturing & Wholesale Goods"
        }
    ],
    "sg:phone":"+1 717 367 7490",
    "sg:postcode":"17022",
    "sg:province":"PA",
    "sg:tags":[
        "greenhouse"
    ],
    "wof:name":"Warburton Greenhouses",
    "wof:placetype":"venue"
},
  "geometry": {"coordinates":[-76.61596,40.227003],"type":"Point"}
}