{
  "type": "Feature",
  "properties": {
    "addr:full":"91 Queen Ave Enola PA 17025",
    "addr:housenumber":"91",
    "addr:postcode":"17025",
    "addr:street":"Queen Ave",
    "iso:country":"US",
    "sg:address":"91 Queen Ave",
    "sg:city":"Enola",
    "sg:classifiers":[
        {
            "category":"Shopping",
            "subcategory":"Clothing, Apparel, & Fashions",
            "type":"Retail Goods"
        }
    ],
    "sg:phone":"+1 717 732 4982",
    "sg:postcode":"17025",
    "sg:province":"PA",
    "wof:name":"Sew Unique",
    "wof:placetype":"venue"
},
  "geometry": {"coordinates":[-76.93083900000001,40.299233],"type":"Point"}
}