{
  "type": "Feature",
  "properties": {
    "iso:country":"US",
    "sg:address":"2331 E Cumberland St",
    "sg:city":"Philadelphia",
    "sg:classifiers":[
        {
            "category":"Bars & Pubs",
            "type":"Food & Drink"
        }
    ],
    "sg:phone":"+1   ",
    "sg:postcode":"19125",
    "sg:province":"PA",
    "sg:tags":[
        "drinking"
    ],
    "wof:name":"Kaisers Kafe",
    "wof:placetype":"venue"
},
  "geometry": {"coordinates":[-75.122449,39.979411],"type":"Point"}
}