{
  "type": "Feature",
  "properties": {
    "iso:country":"US",
    "sg:address":"1153 Regitz Ln",
    "sg:city":"Jeannette",
    "sg:phone":"+1   ",
    "sg:postcode":"15644",
    "sg:province":"PA",
    "sg:tags":[
        "orchard",
        "farm",
        "tree",
        "crop",
        "field",
        "fruit"
    ],
    "wof:name":"Douglas Loughner",
    "wof:placetype":"venue"
},
  "geometry": {"coordinates":[-79.59192899999999,40.380331],"type":"Point"}
}