{
  "type": "Feature",
  "properties": {
    "iso:country":"US",
    "sg:address":"4 Boylston St",
    "sg:city":"Bradford",
    "sg:classifiers":[
        {
            "category":"Building & Trades",
            "subcategory":"Construction",
            "type":"Services"
        }
    ],
    "sg:phone":"+1 814 368 3242",
    "sg:postcode":"16701",
    "sg:province":"PA",
    "sg:tags":[
        "painter"
    ],
    "wof:name":"Daniel M Ross Painting",
    "wof:placetype":"venue"
},
  "geometry": {"coordinates":[-78.65046599999999,41.95652],"type":"Point"}
}