{
  "type": "Feature",
  "properties": {
    "iso:country":"US",
    "sg:address":"404 Rte 18",
    "sg:city":"Monaca",
    "sg:classifiers":[
        {
            "category":"Banks & Credit Unions",
            "subcategory":"Bank",
            "type":"Services"
        }
    ],
    "sg:phone":"+1 724 774 8900",
    "sg:postcode":"15061",
    "sg:province":"PA",
    "sg:tags":[
        "financing"
    ],
    "wof:name":"Household Finance",
    "wof:placetype":"venue"
},
  "geometry": {"coordinates":[-80.316103,40.669002],"type":"Point"}
}