{
  "type": "Feature",
  "properties": {
    "addr:full":"600 Hamilton Ave Kingston PA 18704",
    "addr:housenumber":"600",
    "addr:postcode":"18704",
    "addr:street":"Hamilton Ave",
    "iso:country":"US",
    "sg:address":"600 Hamilton Ave",
    "sg:city":"Kingston",
    "sg:classifiers":[
        {
            "category":"Recreation",
            "type":"Entertainment"
        }
    ],
    "sg:phone":"+1   ",
    "sg:postcode":"18704",
    "sg:province":"PA",
    "sg:tags":[
        "club",
        "league",
        "baseball"
    ],
    "wof:name":"Kingston Baseball & Softball",
    "wof:placetype":"venue"
},
  "geometry": {"coordinates":[-75.87830700000001,41.264143],"type":"Point"}
}