{
  "type": "Feature",
  "properties": {
    "addr:full":"15870 Rte 322 Clarion PA 16214",
    "addr:postcode":"15870;16214",
    "addr:street":"Rte 322",
    "iso:country":"US",
    "sg:address":"15870 Rte 322",
    "sg:city":"Clarion",
    "sg:classifiers":[
        {
            "category":"Communications",
            "type":"Services"
        }
    ],
    "sg:phone":"+1 814 764 6225",
    "sg:postcode":"16214",
    "sg:province":"PA",
    "wof:name":"Clarion Communications",
    "wof:placetype":"venue"
},
  "geometry": {"coordinates":[-79.346615,41.204462],"type":"Point"}
}