{
  "type": "Feature",
  "properties": {
    "iso:country":"US",
    "sg:address":"717 S 17th St",
    "sg:city":"Philadelphia",
    "sg:classifiers":[
        {
            "category":"Manufacturing",
            "subcategory":"Tools & Machinery",
            "type":"Manufacturing & Wholesale Goods"
        }
    ],
    "sg:phone":"+1 215 790 0144",
    "sg:postcode":"19146",
    "sg:province":"PA",
    "sg:tags":[
        "house",
        "fixture",
        "lighting",
        "furnishing",
        "residential"
    ],
    "sg:website":"http://www.groundworkgroup.com",
    "wof:name":"Groundwork Group",
    "wof:placetype":"venue"
},
  "geometry": {"coordinates":[-75.170632,39.942825],"type":"Point"}
}