{
  "type": "Feature",
  "properties": {
    "iso:country":"US",
    "sg:address":"1245 N Chester Rd",
    "sg:city":"West Chester",
    "sg:classifiers":[
        {
            "category":"Wholesale",
            "subcategory":"Machinery & Supplies",
            "type":"Manufacturing & Wholesale Goods"
        }
    ],
    "sg:phone":"+1 484 356 0223",
    "sg:postcode":"19380",
    "sg:province":"PA",
    "sg:tags":[
        "equipment",
        "railroad"
    ],
    "wof:name":"National Railway Supply Inc",
    "wof:placetype":"venue"
},
  "geometry": {"coordinates":[-75.54796899999999,40.020038],"type":"Point"}
}