{
  "type": "Feature",
  "properties": {
    "addr:full":"1628 W Cabot St Philadelphia PA 19121",
    "addr:housenumber":"1628",
    "addr:postcode":"19121",
    "addr:street":"W Cabot St",
    "iso:country":"US",
    "sg:address":"1628 W Cabot St",
    "sg:city":"Philadelphia",
    "sg:classifiers":[
        {
            "category":"Building & Trades",
            "subcategory":"Plumbing",
            "type":"Services"
        }
    ],
    "sg:phone":"+1 215 236 2574",
    "sg:postcode":"19121",
    "sg:province":"PA",
    "sg:tags":[
        "plumber",
        "industrial",
        "contractors-commercial"
    ],
    "wof:name":"Briscoe Plumbing",
    "wof:placetype":"venue"
},
  "geometry": {"coordinates":[-75.16286700000001,39.973237],"type":"Point"}
}