{
  "type": "Feature",
  "properties": {
    "addr:full":"337 Homestead Dr Harleysville PA 19438",
    "addr:housenumber":"337",
    "addr:postcode":"19438",
    "addr:street":"Homestead Dr",
    "iso:country":"US",
    "sg:address":"337 Homestead Dr",
    "sg:city":"Harleysville",
    "sg:classifiers":[
        {
            "category":"Building & Trades",
            "subcategory":"Construction",
            "type":"Services"
        }
    ],
    "sg:phone":"+1   ",
    "sg:postcode":"19438",
    "sg:province":"PA",
    "sg:tags":[
        "house"
    ],
    "wof:name":"Chad Hacker Construction",
    "wof:placetype":"venue"
},
  "geometry": {"coordinates":[-75.41102600000001,40.290091],"type":"Point"}
}