{
  "type": "Feature",
  "properties": {
    "addr:full":"2459 Walnut St Harrisburg PA 17103",
    "addr:housenumber":"2459",
    "addr:postcode":"17103",
    "addr:street":"Walnut St",
    "iso:country":"US",
    "sg:address":"2459 Walnut St",
    "sg:city":"Harrisburg",
    "sg:classifiers":[
        {
            "category":"Health Services",
            "subcategory":"Chiropractor",
            "type":"Services"
        }
    ],
    "sg:phone":"+1 717 920 0836",
    "sg:postcode":"17103",
    "sg:province":"PA",
    "wof:name":"Remillard Chiropractic",
    "wof:placetype":"venue"
},
  "geometry": {"coordinates":[-76.851099,40.277355],"type":"Point"}
}