{
  "type": "Feature",
  "properties": {
    "iso:country":"US",
    "sg:address":"3737 Cloverdale Rd",
    "sg:city":"Bensalem",
    "sg:classifiers":[
        {
            "category":"Personal",
            "subcategory":"Hair Removal",
            "type":"Services"
        }
    ],
    "sg:phone":"+1   ",
    "sg:postcode":"19020",
    "sg:province":"PA",
    "wof:name":"Bucks County Financial Plg",
    "wof:placetype":"venue"
},
  "geometry": {"coordinates":[-74.96897199999999,40.120046],"type":"Point"}
}