{
  "type": "Feature",
  "properties": {
    "iso:country":"US",
    "sg:address":"1319 W Hamilton St",
    "sg:city":"Allentown",
    "sg:classifiers":[
        {
            "category":"Sports & Exercise",
            "subcategory":"Gym",
            "type":"Entertainment"
        }
    ],
    "sg:phone":"+1 610 770 7040",
    "sg:postcode":"18102",
    "sg:province":"PA",
    "sg:tags":[
        "facility",
        "spa",
        "physical",
        "day",
        "fitness"
    ],
    "wof:name":"Evergreen Spas",
    "wof:placetype":"venue"
},
  "geometry": {"coordinates":[-75.484703,40.598701],"type":"Point"}
}