{
  "type": "Feature",
  "properties": {
    "iso:country":"US",
    "sg:address":"548 Morgantown Rd",
    "sg:city":"Uniontown",
    "sg:classifiers":[
        {
            "category":"Restaurant",
            "type":"Food & Drink"
        }
    ],
    "sg:menulink":"http://www.allmenus.com/pa/south-union/200171-long-john-silvers/menu/",
    "sg:phone":"+1 724 439 1068",
    "sg:postcode":"15401",
    "sg:province":"PA",
    "sg:tags":[
        "seafood",
        "american"
    ],
    "wof:name":"Long John Silver's",
    "wof:placetype":"venue"
},
  "geometry": {"coordinates":[-79.735857,39.884431],"type":"Point"}
}