{
  "type": "Feature",
  "properties": {
    "iso:country":"US",
    "sg:address":"1811 Ranstead St",
    "sg:city":"Philadelphia",
    "sg:classifiers":[
        {
            "category":"Personal",
            "subcategory":"Beauty Salon",
            "type":"Services"
        }
    ],
    "sg:phone":"+1 215 568 3399",
    "sg:postcode":"19103",
    "sg:province":"PA",
    "sg:tags":[
        "hair"
    ],
    "wof:name":"Ranstead Barber Shop",
    "wof:placetype":"venue"
},
  "geometry": {"coordinates":[-75.170269,39.952343],"type":"Point"}
}