{
  "type": "Feature",
  "properties": {
    "iso:country":"US",
    "sg:address":"47 Market Sq",
    "sg:city":"Manheim",
    "sg:classifiers":[
        {
            "category":"Government",
            "subcategory":"Court House",
            "type":"Public Place"
        }
    ],
    "sg:phone":"+1 717 664 4979",
    "sg:postcode":"17545",
    "sg:province":"PA",
    "sg:tags":[
        "legislator"
    ],
    "sg:website":"http://www.curtschroder.com",
    "wof:name":"House Of Representatives, Pennsylvania",
    "wof:placetype":"venue"
},
  "geometry": {"coordinates":[-76.395967,40.163198],"type":"Point"}
}