{
  "type": "Feature",
  "properties": {
    "addr:full":"43 S State St Newtown PA 18940",
    "addr:housenumber":"43",
    "addr:postcode":"18940",
    "addr:street":"S State St",
    "iso:country":"US",
    "sg:address":"43 S State St",
    "sg:city":"Newtown",
    "sg:classifiers":[
        {
            "category":"Shopping",
            "subcategory":"Clothing, Apparel, & Fashions",
            "type":"Retail Goods"
        }
    ],
    "sg:phone":"+1   ",
    "sg:postcode":"18940",
    "sg:province":"PA",
    "sg:tags":[
        "family",
        "store"
    ],
    "wof:name":"Gap",
    "wof:placetype":"venue"
},
  "geometry": {"coordinates":[-74.93677099999999,40.228492],"type":"Point"}
}