{
  "type": "Feature",
  "properties": {
    "iso:country":"US",
    "sg:address":"7194 Herber Rd",
    "sg:city":"New Tripoli",
    "sg:classifiers":[
        {
            "category":"Building & Trades",
            "subcategory":"Construction",
            "type":"Services"
        }
    ],
    "sg:phone":"+1   ",
    "sg:postcode":"18066",
    "sg:province":"PA",
    "sg:tags":[
        "home",
        "improvement",
        "contractor"
    ],
    "wof:name":"Quality Improvements",
    "wof:placetype":"venue"
},
  "geometry": {"coordinates":[-75.69493300000001,40.64974],"type":"Point"}
}