{
  "type": "Feature",
  "properties": {
    "iso:country":"US",
    "sg:address":"9229 Pine Rd",
    "sg:city":"Philadelphia",
    "sg:classifiers":[
        {
            "category":"Professional",
            "type":"Services"
        }
    ],
    "sg:phone":"+1 215 673 4422",
    "sg:postcode":"19115",
    "sg:province":"PA",
    "sg:tags":[
        "establishment"
    ],
    "wof:name":"Neman Office",
    "wof:placetype":"venue"
},
  "geometry": {"coordinates":[-75.061836,40.102034],"type":"Point"}
}