{
  "type": "Feature",
  "properties": {
    "addr:full":"959 Airbrake Ave Turtle Creek PA 15145",
    "addr:housenumber":"959",
    "addr:postcode":"15145",
    "addr:street":"Airbrake Ave",
    "iso:country":"US",
    "sg:address":"959 Airbrake Ave",
    "sg:city":"Turtle Creek",
    "sg:classifiers":[
        {
            "category":"Shopping",
            "subcategory":"Clothing, Apparel, & Fashions",
            "type":"Retail Goods"
        }
    ],
    "sg:phone":"+1   ",
    "sg:postcode":"15145",
    "sg:province":"PA",
    "wof:name":"Excel Sportswear",
    "wof:placetype":"venue"
},
  "geometry": {"coordinates":[-79.824078,40.403847],"type":"Point"}
}