{
  "type": "Feature",
  "properties": {
    "addr:full":"250 Maple Ave Bird In Hand PA 17505",
    "addr:housenumber":"250",
    "addr:postcode":"17505",
    "addr:street":"Maple Ave",
    "iso:country":"US",
    "sg:address":"250 Maple Ave",
    "sg:city":"Bird In Hand",
    "sg:classifiers":[
        {
            "category":"Manufacturing",
            "subcategory":"Motor Vehicles & Parts",
            "type":"Manufacturing & Wholesale Goods"
        }
    ],
    "sg:phone":"+1   ",
    "sg:postcode":"17505",
    "sg:province":"PA",
    "sg:tags":[
        "carriage",
        "mfg",
        "metal",
        "fabrication",
        "structural"
    ],
    "wof:name":"Carriage Machine Shop",
    "wof:placetype":"venue"
},
  "geometry": {"coordinates":[-76.175386,40.035968],"type":"Point"}
}