{
  "type": "Feature",
  "properties": {
    "iso:country":"US",
    "sg:address":"103 Taylor Ave",
    "sg:city":"Wyalusing",
    "sg:classifiers":[
        {
            "category":"Banks & Credit Unions",
            "subcategory":"Bank",
            "type":"Services"
        }
    ],
    "sg:phone":"+1 570 746 5101",
    "sg:postcode":"18853",
    "sg:province":"PA",
    "wof:name":"P & G Employees Federal Cu",
    "wof:placetype":"venue"
},
  "geometry": {"coordinates":[-76.25929499999999,41.668624],"type":"Point"}
}