{
  "type": "Feature",
  "properties": {
    "addr:full":"2000 Titlow Rd East Greenville PA 18041",
    "addr:housenumber":"2000",
    "addr:postcode":"18041",
    "addr:street":"Titlow Rd",
    "iso:country":"US",
    "sg:address":"2000 Titlow Rd",
    "sg:city":"East Greenville",
    "sg:classifiers":[
        {
            "category":"Shopping",
            "subcategory":"Department Store",
            "type":"Retail Goods"
        }
    ],
    "sg:phone":"+1   ",
    "sg:postcode":"18041",
    "sg:province":"PA",
    "wof:name":"Weis Bakery",
    "wof:placetype":"venue"
},
  "geometry": {"coordinates":[-75.473677,40.423849],"type":"Point"}
}