{
  "type": "Feature",
  "properties": {
    "addr:full":"2440 Headhouse Sq S Bensalem PA 19020",
    "addr:postcode":"2440;19020",
    "addr:street":"Headhouse Sq S",
    "iso:country":"US",
    "sg:address":"2440 Headhouse Sq S",
    "sg:city":"Bensalem",
    "sg:classifiers":[
        {
            "category":"Retail",
            "subcategory":"Repair Shop",
            "type":"Services"
        }
    ],
    "sg:phone":"+1 215 638 9800",
    "sg:postcode":"19020",
    "sg:province":"PA",
    "sg:tags":[
        "bathtub",
        "sink",
        "refinishing"
    ],
    "wof:name":"Miracle Method",
    "wof:placetype":"venue"
},
  "geometry": {"coordinates":[-74.953101,40.088923],"type":"Point"}
}