{
  "type": "Feature",
  "properties": {
    "iso:country":"US",
    "sg:address":"1651 Mount Zion Rd",
    "sg:city":"York",
    "sg:classifiers":[
        {
            "category":"Health Services",
            "subcategory":"Clinic",
            "type":"Services"
        }
    ],
    "sg:phone":"+1 717 757 0774",
    "sg:postcode":"17406",
    "sg:province":"PA",
    "sg:tags":[
        "home"
    ],
    "sg:website":"www.lutheranhomecare.org",
    "wof:name":"Lutheran Home Care Svc",
    "wof:placetype":"venue"
},
  "geometry": {"coordinates":[-76.676807,39.997319],"type":"Point"}
}