{
  "type": "Feature",
  "properties": {
    "iso:country":"US",
    "sg:address":"2268 S 12th St Ste 202",
    "sg:city":"Allentown",
    "sg:classifiers":[
        {
            "category":"Health Services",
            "subcategory":"Doctor",
            "type":"Services"
        },
        {
            "category":"Health Services",
            "subcategory":"Hospital",
            "type":"Services"
        }
    ],
    "sg:phone":"+1 610 798 4500",
    "sg:postcode":"18103",
    "sg:province":"PA",
    "wof:name":"Lehigh Valley Physician Group Central Billing Office",
    "wof:placetype":"venue"
},
  "geometry": {"coordinates":[-75.47365600000001,40.570675],"type":"Point"}
}