{
  "type": "Feature",
  "properties": {
    "addr:full":"115 Little John Dr Canonsburg PA 15317",
    "addr:housenumber":"115",
    "addr:postcode":"15317",
    "addr:street":"Little John Dr",
    "iso:country":"US",
    "sg:address":"115 Little John Dr",
    "sg:city":"Canonsburg",
    "sg:classifiers":[
        {
            "category":"Professional",
            "subcategory":"Computer Services",
            "type":"Services"
        }
    ],
    "sg:phone":"+1   ",
    "sg:postcode":"15317",
    "sg:province":"PA",
    "sg:tags":[
        "development",
        "software"
    ],
    "wof:name":"Tem Software",
    "wof:placetype":"venue"
},
  "geometry": {"coordinates":[-80.129493,40.263324],"type":"Point"}
}