{
  "type": "Feature",
  "properties": {
    "iso:country":"US",
    "sg:address":"502 W Main St",
    "sg:city":"Mt Pleasant",
    "sg:classifiers":[
        {
            "category":"Utilities",
            "subcategory":"Mobile Phone",
            "type":"Services"
        }
    ],
    "sg:phone":"+1 724 542 7533",
    "sg:postcode":"15666",
    "sg:province":"PA",
    "sg:tags":[
        "communication",
        "telephone",
        "cellular",
        "radiotelephone"
    ],
    "wof:name":"RGE Wireless Communications",
    "wof:placetype":"venue"
},
  "geometry": {"coordinates":[-79.542,40.148883],"type":"Point"}
}