{
  "type": "Feature",
  "properties": {
    "iso:country":"US",
    "sg:address":"524 S Chester Rd",
    "sg:city":"Swarthmore",
    "sg:classifiers":[
        {
            "category":"Professional",
            "subcategory":"Testing Lab",
            "type":"Services"
        }
    ],
    "sg:phone":"+1 610 544 0496",
    "sg:postcode":"19081",
    "sg:province":"PA",
    "sg:tags":[
        "inspection",
        "infrared"
    ],
    "wof:name":"Trinity Associates Inc",
    "wof:placetype":"venue"
},
  "geometry": {"coordinates":[-75.352965,39.892129],"type":"Point"}
}