{
  "type": "Feature",
  "properties": {
    "iso:country":"US",
    "sg:address":"145 Vanceville Rd",
    "sg:city":"Eighty Four",
    "sg:classifiers":[
        {
            "category":"Real Estate",
            "subcategory":"Real Estate Agent",
            "type":"Services"
        }
    ],
    "sg:phone":"+1   ",
    "sg:postcode":"15330",
    "sg:province":"PA",
    "wof:name":"84 Real Estate",
    "wof:placetype":"venue"
},
  "geometry": {"coordinates":[-80.09020200000001,40.165422],"type":"Point"}
}