{
  "type": "Feature",
  "properties": {
    "iso:country":"US",
    "sg:address":"954 Montgomery Ave",
    "sg:city":"Narberth",
    "sg:classifiers":[
        {
            "category":"Professional",
            "subcategory":"Business Services",
            "type":"Services"
        }
    ],
    "sg:phone":"+1 610 667 4949",
    "sg:postcode":"19072",
    "sg:province":"PA",
    "sg:tags":[
        "auctioneer"
    ],
    "wof:name":"Auction World U S A",
    "wof:placetype":"venue"
},
  "geometry": {"coordinates":[-75.260774,40.011612],"type":"Point"}
}