{
  "type": "Feature",
  "properties": {
    "addr:full":"1526 Ferndale Ave Abington PA 19001",
    "addr:housenumber":"1526",
    "addr:postcode":"19001",
    "addr:street":"Ferndale Ave",
    "iso:country":"US",
    "sg:address":"1526 Ferndale Ave",
    "sg:city":"Abington",
    "sg:classifiers":[
        {
            "category":"Building & Trades",
            "subcategory":"Landscaping Services",
            "type":"Services"
        }
    ],
    "sg:phone":"+1   ",
    "sg:postcode":"19001",
    "sg:province":"PA",
    "wof:name":"R M Hunt Landscaping",
    "wof:placetype":"venue"
},
  "geometry": {"coordinates":[-75.11864799999999,40.126771],"type":"Point"}
}