{
  "type": "Feature",
  "properties": {
    "iso:country":"US",
    "sg:address":"215 Arlington Ave",
    "sg:city":"Butler",
    "sg:classifiers":[
        {
            "category":"Professional",
            "type":"Services"
        }
    ],
    "sg:phone":"+1   ",
    "sg:postcode":"16001",
    "sg:province":"PA",
    "wof:name":"Beacon Gide Mtvtional Programs",
    "wof:placetype":"venue"
},
  "geometry": {"coordinates":[-79.93223999999999,40.852122],"type":"Point"}
}