{
  "type": "Feature",
  "properties": {
    "iso:country":"US",
    "sg:address":"334 Washington St",
    "sg:city":"Johnstown",
    "sg:classifiers":[
        {
            "category":"Government",
            "subcategory":"Office",
            "type":"Public Place"
        }
    ],
    "sg:phone":"+1   ",
    "sg:postcode":"15901",
    "sg:province":"PA",
    "sg:tags":[
        "program",
        "administrative"
    ],
    "wof:name":"Social Security District Off",
    "wof:placetype":"venue"
},
  "geometry": {"coordinates":[-78.91898999999999,40.327457],"type":"Point"}
}