{
  "type": "Feature",
  "properties": {
    "addr:full":"14 S 13th St Jeannette PA 15644",
    "addr:housenumber":"14",
    "addr:postcode":"15644",
    "addr:street":"S 13Th St",
    "iso:country":"US",
    "sg:address":"14 S 13th St",
    "sg:city":"Jeannette",
    "sg:classifiers":[
        {
            "category":"Autos & Motor Vehicles",
            "subcategory":"Automobile Sales",
            "type":"Retail Goods"
        }
    ],
    "sg:phone":"+1 724 523 2450",
    "sg:postcode":"15644",
    "sg:province":"PA",
    "sg:tags":[
        "dealers-used",
        "car",
        "used",
        "cars-wholesale",
        "new"
    ],
    "wof:name":"Goodwin Auto Sales, Inc",
    "wof:placetype":"venue"
},
  "geometry": {"coordinates":[-79.626178,40.33132],"type":"Point"}
}