{
  "type": "Feature",
  "properties": {
    "addr:full":"1511 Potomac Ave Pittsburgh PA 15216",
    "addr:housenumber":"1511",
    "addr:postcode":"15216",
    "addr:street":"Potomac Ave",
    "iso:country":"US",
    "sg:address":"1511 Potomac Ave",
    "sg:city":"Pittsburgh",
    "sg:classifiers":[
        {
            "category":"Wholesale",
            "subcategory":"Non-durable Goods",
            "type":"Manufacturing & Wholesale Goods"
        }
    ],
    "sg:phone":"+1 412 563 7666",
    "sg:postcode":"15216",
    "sg:province":"PA",
    "sg:tags":[
        "advertising",
        "specialty"
    ],
    "wof:name":"Greco Advertising Specialty Co",
    "wof:placetype":"venue"
},
  "geometry": {"coordinates":[-80.03588999999999,40.397051],"type":"Point"}
}