{
  "type": "Feature",
  "properties": {
    "iso:country":"US",
    "sg:address":"322 S 6th St",
    "sg:city":"Lebanon",
    "sg:classifiers":[
        {
            "category":"Professional",
            "subcategory":"Detective & Security Services",
            "type":"Services"
        }
    ],
    "sg:phone":"+1 717 228 2756",
    "sg:postcode":"17042",
    "sg:province":"PA",
    "sg:tags":[
        "information",
        "bureau"
    ],
    "wof:name":"Russell Himmelberger",
    "wof:placetype":"venue"
},
  "geometry": {"coordinates":[-76.420514,40.334702],"type":"Point"}
}