{
  "type": "Feature",
  "properties": {
    "iso:country":"US",
    "sg:address":"205 S Main St",
    "sg:city":"Davidsville",
    "sg:classifiers":[
        {
            "category":"Restaurant",
            "type":"Food & Drink"
        }
    ],
    "sg:menulink":"http://www.allmenus.com/pa/conemaugh/67686-foxs-pizza-den/menu/",
    "sg:phone":"+1 814 479 4411",
    "sg:postcode":"15928",
    "sg:province":"PA",
    "sg:tags":[
        "american",
        "pizza"
    ],
    "wof:name":"Fox's Pizza Den",
    "wof:placetype":"venue"
},
  "geometry": {"coordinates":[-78.93765,40.225554],"type":"Point"}
}