{
  "type": "Feature",
  "properties": {
    "iso:country":"US",
    "sg:address":"190 Welles St",
    "sg:city":"Kingston",
    "sg:classifiers":[
        {
            "category":"Health Services",
            "subcategory":"Health Practitioner",
            "type":"Services"
        }
    ],
    "sg:phone":"+1   ",
    "sg:postcode":"18704",
    "sg:province":"PA",
    "sg:tags":[
        "merchandise"
    ],
    "wof:name":"Sieminski Louis S Dr",
    "wof:placetype":"venue"
},
  "geometry": {"coordinates":[-75.87648900000001,41.275638],"type":"Point"}
}