{
  "type": "Feature",
  "properties": {
    "iso:country":"US",
    "sg:address":"680 State St",
    "sg:city":"Harrisburg",
    "sg:classifiers":[
        {
            "category":"Professional",
            "type":"Services"
        }
    ],
    "sg:phone":"+1 717 909 6095",
    "sg:postcode":"17101",
    "sg:province":"PA",
    "sg:tags":[
        "establishment"
    ],
    "wof:name":"Higgins Auctioneering",
    "wof:placetype":"venue"
},
  "geometry": {"coordinates":[-76.88511,40.264008],"type":"Point"}
}