{
  "type": "Feature",
  "properties": {
    "addr:full":"4003 Business 220 Bedford PA 15522",
    "addr:housenumber":"4003;220",
    "addr:postcode":"15522",
    "addr:street":"Business",
    "iso:country":"US",
    "sg:address":"4003 Business 220",
    "sg:city":"Bedford",
    "sg:classifiers":[
        {
            "category":"Retail",
            "subcategory":"Auto Rental",
            "type":"Services"
        },
        {
            "category":"Retail",
            "subcategory":"Storage",
            "type":"Services"
        }
    ],
    "sg:phone":"+1 814 623 6025",
    "sg:postcode":"15522",
    "sg:province":"PA",
    "sg:tags":[
        "renting",
        "moving-self",
        "leasing",
        "car",
        "truck",
        "trailer"
    ],
    "wof:name":"Payless Car Rental",
    "wof:placetype":"venue"
},
  "geometry": {"coordinates":[-78.50699899999999,40.04355],"type":"Point"}
}