{
  "type": "Feature",
  "properties": {
    "iso:country":"US",
    "sg:address":"2803 Papermill Rd",
    "sg:city":"Reading",
    "sg:classifiers":[
        {
            "category":"Restaurant",
            "type":"Food & Drink"
        }
    ],
    "sg:menulink":"http://www.allmenus.com/pa/spring/10376-texas-roadhouse/menu/",
    "sg:phone":"+1 610 373 9600",
    "sg:postcode":"19610",
    "sg:province":"PA",
    "sg:tags":[
        "american",
        "steakhouse"
    ],
    "wof:name":"Texas Roadhouse",
    "wof:placetype":"venue"
},
  "geometry": {"coordinates":[-75.98950499999999,40.362201],"type":"Point"}
}