{
  "type": "Feature",
  "properties": {
    "iso:country":"US",
    "sg:address":"1126 Washington Blvd",
    "sg:city":"Williamsport",
    "sg:classifiers":[
        {
            "category":"Real Estate",
            "subcategory":"Real Estate Agent",
            "type":"Services"
        }
    ],
    "sg:phone":"+1   ",
    "sg:postcode":"17701",
    "sg:province":"PA",
    "wof:name":"Colonial Plaza",
    "wof:placetype":"venue"
},
  "geometry": {"coordinates":[-76.983687,41.249384],"type":"Point"}
}