{
  "type": "Feature",
  "properties": {
    "addr:full":"820 William Pitt Way Pittsburgh PA 15238",
    "addr:housenumber":"820",
    "addr:postcode":"15238",
    "addr:street":"William Pitt Way",
    "iso:country":"US",
    "sg:address":"820 William Pitt Way",
    "sg:city":"Pittsburgh",
    "sg:classifiers":[
        {
            "category":"Professional",
            "subcategory":"Research",
            "type":"Services"
        }
    ],
    "sg:phone":"+1 412 826 3055",
    "sg:postcode":"15238",
    "sg:province":"PA",
    "sg:tags":[
        "environmental",
        "ecological"
    ],
    "wof:name":"Environmental Management",
    "wof:placetype":"venue"
},
  "geometry": {"coordinates":[-79.83446499999999,40.542848],"type":"Point"}
}