{
  "type": "Feature",
  "properties": {
    "iso:country":"US",
    "sg:address":"6622 Leah Dr",
    "sg:city":"Slatington",
    "sg:classifiers":[
        {
            "category":"Freight",
            "type":"Transportation"
        }
    ],
    "sg:phone":"+1   ",
    "sg:postcode":"18080",
    "sg:province":"PA",
    "sg:tags":[
        "operator",
        "local",
        "trucking"
    ],
    "wof:name":"Leon Borger Trucking Inc",
    "wof:placetype":"venue"
},
  "geometry": {"coordinates":[-75.609802,40.724352],"type":"Point"}
}