{
  "type": "Feature",
  "properties": {
    "iso:country":"US",
    "sg:address":"667 New Castle Rd",
    "sg:city":"Butler",
    "sg:classifiers":[
        {
            "category":"Building & Trades",
            "subcategory":"Construction",
            "type":"Services"
        }
    ],
    "sg:phone":"+1   ",
    "sg:postcode":"16001",
    "sg:province":"PA",
    "sg:tags":[
        "contractor"
    ],
    "wof:name":"Rebath West Central PA",
    "wof:placetype":"venue"
},
  "geometry": {"coordinates":[-79.980307,40.887765],"type":"Point"}
}