{
  "type": "Feature",
  "properties": {
    "iso:country":"US",
    "sg:address":"1808 Colonial Village Ln",
    "sg:city":"Lancaster",
    "sg:classifiers":[
        {
            "category":"Manufacturing",
            "subcategory":"Printing",
            "type":"Manufacturing & Wholesale Goods"
        }
    ],
    "sg:phone":"+1   ",
    "sg:postcode":"17601",
    "sg:province":"PA",
    "sg:tags":[
        "publishing"
    ],
    "wof:name":"Reprint Management Services",
    "wof:placetype":"venue"
},
  "geometry": {"coordinates":[-76.248024,40.048324],"type":"Point"}
}