{
  "type": "Feature",
  "properties": {
    "addr:full":"2831 N Broad St Philadelphia PA 19132",
    "addr:housenumber":"2831",
    "addr:postcode":"19132",
    "addr:street":"N Broad St",
    "iso:country":"US",
    "sg:address":"2831 N Broad St",
    "sg:city":"Philadelphia",
    "sg:classifiers":[
        {
            "category":"Banks & Credit Unions",
            "subcategory":"Bank",
            "type":"Services"
        }
    ],
    "sg:phone":"+1 215 229 3680",
    "sg:postcode":"19132",
    "sg:province":"PA",
    "wof:name":"Wachovia",
    "wof:placetype":"venue"
},
  "geometry": {"coordinates":[-75.154099,39.996601],"type":"Point"}
}