{
  "type": "Feature",
  "properties": {
    "addr:full":"209 9th St Pittsburgh PA 15222",
    "addr:housenumber":"209",
    "addr:postcode":"15222",
    "addr:street":"9Th St",
    "iso:country":"US",
    "sg:address":"209 9th St",
    "sg:city":"Pittsburgh",
    "sg:classifiers":[
        {
            "category":"Professional",
            "type":"Services"
        }
    ],
    "sg:phone":"+1 412 281 3033",
    "sg:postcode":"15222",
    "sg:province":"PA",
    "sg:tags":[
        "establishment"
    ],
    "wof:name":"Wrecking Crew Music",
    "wof:placetype":"venue"
},
  "geometry": {"coordinates":[-79.99811699999999,40.443442],"type":"Point"}
}