{
  "type": "Feature",
  "properties": {
    "addr:full":"223 Grove City Rd Slippery Rock PA 16057",
    "addr:housenumber":"223",
    "addr:postcode":"16057",
    "addr:street":"Grove City Rd",
    "iso:country":"US",
    "sg:address":"223 Grove City Rd",
    "sg:city":"Slippery Rock",
    "sg:classifiers":[
        {
            "category":"Sports & Exercise",
            "subcategory":"Gym",
            "type":"Entertainment"
        }
    ],
    "sg:phone":"+1 724 794 1851",
    "sg:postcode":"16057",
    "sg:province":"PA",
    "sg:tags":[
        "club",
        "health",
        "studio",
        "gymnasium"
    ],
    "wof:name":"Curves For Women",
    "wof:placetype":"venue"
},
  "geometry": {"coordinates":[-80.05175199999999,41.071881],"type":"Point"}
}