{
  "type": "Feature",
  "properties": {
    "addr:full":"108 Olde Saxony Trl Cheswick PA 15024",
    "addr:housenumber":"108",
    "addr:postcode":"15024",
    "addr:street":"Olde Saxony Trl",
    "iso:country":"US",
    "sg:address":"108 Olde Saxony Trl",
    "sg:city":"Cheswick",
    "sg:classifiers":[
        {
            "category":"Professional",
            "type":"Services"
        }
    ],
    "sg:phone":"+1   ",
    "sg:postcode":"15024",
    "sg:province":"PA",
    "wof:name":"Gary Pennington",
    "wof:placetype":"venue"
},
  "geometry": {"coordinates":[-79.878651,40.58568],"type":"Point"}
}