{
  "type": "Feature",
  "properties": {
    "addr:full":"899 Penn St Bryn Mawr PA 19010",
    "addr:housenumber":"899",
    "addr:postcode":"19010",
    "addr:street":"Penn St",
    "iso:country":"US",
    "sg:address":"899 Penn St",
    "sg:city":"Bryn Mawr",
    "sg:classifiers":[
        {
            "category":"Personal",
            "subcategory":"Tanning Parlor",
            "type":"Services"
        }
    ],
    "sg:phone":"+1 610 527 5566",
    "sg:postcode":"19010",
    "sg:province":"PA",
    "sg:tags":[
        "salon"
    ],
    "wof:name":"Body Bronze",
    "wof:placetype":"venue"
},
  "geometry": {"coordinates":[-75.311786,40.017457],"type":"Point"}
}