{
  "type": "Feature",
  "properties": {
    "iso:country":"US",
    "sg:address":"1520 Sylvan Ave",
    "sg:city":"Latrobe",
    "sg:classifiers":[
        {
            "category":"Manufacturing",
            "subcategory":"Apparel",
            "type":"Manufacturing & Wholesale Goods"
        }
    ],
    "sg:phone":"+1   ",
    "sg:postcode":"15650",
    "sg:province":"PA",
    "wof:name":"Phoenix Embroidery",
    "wof:placetype":"venue"
},
  "geometry": {"coordinates":[-79.373808,40.314278],"type":"Point"}
}