{
  "type": "Feature",
  "properties": {
    "iso:country":"US",
    "sg:address":"119 Market St",
    "sg:city":"Lewisburg",
    "sg:classifiers":[
        {
            "category":"Home & Garden",
            "subcategory":"Household Appliances",
            "type":"Retail Goods"
        }
    ],
    "sg:phone":"+1 570 523 3321",
    "sg:postcode":"17837",
    "sg:province":"PA",
    "sg:tags":[
        "television",
        "electrical"
    ],
    "wof:name":"Stamm's TV & Appliances",
    "wof:placetype":"venue"
},
  "geometry": {"coordinates":[-76.88264700000001,40.965512],"type":"Point"}
}