{
  "type": "Feature",
  "properties": {
    "iso:country":"US",
    "sg:address":"1500 John F Kennedy Blvd",
    "sg:city":"Philadelphia",
    "sg:classifiers":[
        {
            "category":"Real Estate",
            "subcategory":"Architect",
            "type":"Services"
        }
    ],
    "sg:phone":"+1 215 423 4900",
    "sg:postcode":"19102",
    "sg:province":"PA",
    "wof:name":"Sfcs Inc",
    "wof:placetype":"venue"
},
  "geometry": {"coordinates":[-75.165071,39.953474],"type":"Point"}
}