{
  "type": "Feature",
  "properties": {
    "iso:country":"US",
    "sg:address":"523 E Christine Rd",
    "sg:city":"Nottingham",
    "sg:classifiers":[
        {
            "category":"Real Estate",
            "subcategory":"Real Estate Agent",
            "type":"Services"
        }
    ],
    "sg:phone":"+1 610 932 2151",
    "sg:postcode":"19362",
    "sg:province":"PA",
    "wof:name":"Bell Nottingham Real Estate",
    "wof:placetype":"venue"
},
  "geometry": {"coordinates":[-76.015989,39.74834],"type":"Point"}
}