{
  "type": "Feature",
  "properties": {
    "iso:country":"US",
    "sg:address":"389 Allendale Rd",
    "sg:city":"King Of Prussia",
    "sg:classifiers":[
        {
            "category":"Retail",
            "subcategory":"Portrait Studio",
            "type":"Services"
        }
    ],
    "sg:phone":"+1 610 337 4908",
    "sg:postcode":"19406",
    "sg:province":"PA",
    "sg:tags":[
        "photo"
    ],
    "sg:website":"www.ultimateimages-photography.com",
    "wof:name":"Ultimate Images Photography",
    "wof:placetype":"venue"
},
  "geometry": {"coordinates":[-75.392687,40.09718],"type":"Point"}
}