{
  "type": "Feature",
  "properties": {
    "iso:country":"US",
    "sg:address":"135 Edge Rock Dr",
    "sg:city":"Drums",
    "sg:classifiers":[
        {
            "category":"Professional",
            "subcategory":"Lawyer & Legal Services",
            "type":"Services"
        }
    ],
    "sg:phone":"+1 570 788 3401",
    "sg:postcode":"18222",
    "sg:province":"PA",
    "sg:tags":[
        "plan"
    ],
    "wof:name":"Art Malady's",
    "wof:placetype":"venue"
},
  "geometry": {"coordinates":[-75.938846,41.038743],"type":"Point"}
}