{
  "type": "Feature",
  "properties": {
    "addr:full":"1315 New Rodgers Rd Bristol PA 19007",
    "addr:housenumber":"1315",
    "addr:postcode":"19007",
    "addr:street":"New Rodgers Rd",
    "iso:country":"US",
    "sg:address":"1315 New Rodgers Rd",
    "sg:city":"Bristol",
    "sg:classifiers":[
        {
            "category":"Health Services",
            "subcategory":"Doctor",
            "type":"Services"
        }
    ],
    "sg:phone":"+1   ",
    "sg:postcode":"19007",
    "sg:province":"PA",
    "sg:tags":[
        "medical"
    ],
    "wof:name":"Federico A Peguero MD",
    "wof:placetype":"venue"
},
  "geometry": {"coordinates":[-74.87822799999999,40.109317],"type":"Point"}
}