{
  "type": "Feature",
  "properties": {
    "iso:country":"US",
    "sg:address":"2938 Cambridge St",
    "sg:city":"Philadelphia",
    "sg:classifiers":[
        {
            "category":"Real Estate",
            "subcategory":"Real Estate Services",
            "type":"Services"
        },
        {
            "category":"Real Estate",
            "subcategory":"Real Estate Agent",
            "type":"Services"
        }
    ],
    "sg:phone":"+1 917 446 3087",
    "sg:postcode":"19130",
    "sg:province":"PA",
    "sg:tags":[
        "management"
    ],
    "wof:name":"Ldk Associates",
    "wof:placetype":"venue"
},
  "geometry": {"coordinates":[-75.18425000000001,39.973936],"type":"Point"}
}