{
  "type": "Feature",
  "properties": {
    "iso:country":"US",
    "sg:address":"4500 Pennell Rd",
    "sg:city":"Aston",
    "sg:classifiers":[
        {
            "category":"Banks & Credit Unions",
            "subcategory":"Bank",
            "type":"Services"
        }
    ],
    "sg:phone":"+1 610 485 2960",
    "sg:postcode":"19014",
    "sg:province":"PA",
    "sg:tags":[
        "federally",
        "chartered"
    ],
    "sg:website":"www.suneast.org",
    "wof:name":"Sun East Federal Credit Union",
    "wof:placetype":"venue"
},
  "geometry": {"coordinates":[-75.428816,39.870379],"type":"Point"}
}