{
  "type": "Feature",
  "properties": {
    "iso:country":"US",
    "sg:address":"110 Eisenhower Dr",
    "sg:city":"New Paris",
    "sg:classifiers":[
        {
            "category":"Freight",
            "type":"Transportation"
        }
    ],
    "sg:phone":"+1   ",
    "sg:postcode":"15554",
    "sg:province":"PA",
    "sg:tags":[
        "distance",
        "trucking",
        "local",
        "long",
        "arrangement"
    ],
    "wof:name":"Penrod Trucking",
    "wof:placetype":"venue"
},
  "geometry": {"coordinates":[-78.574336,40.117796],"type":"Point"}
}