{
  "type": "Feature",
  "properties": {
    "iso:country":"US",
    "sg:address":"118 N Main St",
    "sg:city":"Doylestown",
    "sg:classifiers":[
        {
            "category":"Shopping",
            "subcategory":"Stationery & Office Supplies",
            "type":"Retail Goods"
        },
        {
            "category":"Shopping",
            "subcategory":"Gifts & Souvenirs",
            "type":"Retail Goods"
        }
    ],
    "sg:phone":"+1 215 348 1296",
    "sg:postcode":"18901",
    "sg:province":"PA",
    "sg:tags":[
        "shop",
        "store"
    ],
    "wof:name":"Chelsea Clothing & Gifts",
    "wof:placetype":"venue"
},
  "geometry": {"coordinates":[-75.13057499999999,40.31176],"type":"Point"}
}