{
  "type": "Feature",
  "properties": {
    "iso:country":"US",
    "sg:address":"710 Hite Rd",
    "sg:city":"Harwick",
    "sg:classifiers":[
        {
            "category":"Professional",
            "subcategory":"Research",
            "type":"Services"
        }
    ],
    "sg:phone":"+1   ",
    "sg:postcode":"15049",
    "sg:province":"PA",
    "sg:tags":[
        "nonphysical",
        "commercial"
    ],
    "wof:name":"Argo Research and Comm",
    "wof:placetype":"venue"
},
  "geometry": {"coordinates":[-79.807975,40.555591],"type":"Point"}
}