{
  "type": "Feature",
  "properties": {
    "addr:full":"300 S Chester Rd Swarthmore PA 19081",
    "addr:housenumber":"300",
    "addr:postcode":"19081",
    "addr:street":"S Chester Rd",
    "iso:country":"US",
    "sg:address":"300 S Chester Rd",
    "sg:city":"Swarthmore",
    "sg:classifiers":[
        {
            "category":"Professional",
            "subcategory":"Management & Consulting",
            "type":"Services"
        }
    ],
    "sg:phone":"+1 610 690 5184",
    "sg:postcode":"19081",
    "sg:province":"PA",
    "sg:tags":[
        "party",
        "planning"
    ],
    "wof:name":"Lead Dog",
    "wof:placetype":"venue"
},
  "geometry": {"coordinates":[-75.351705,39.895078],"type":"Point"}
}