{
  "type": "Feature",
  "properties": {
    "iso:country":"US",
    "sg:address":"33 S 7th St",
    "sg:city":"Allentown",
    "sg:classifiers":[
        {
            "category":"Professional",
            "subcategory":"Lawyer & Legal Services",
            "type":"Services"
        }
    ],
    "sg:phone":"+1 610 433 0121",
    "sg:postcode":"18101",
    "sg:province":"PA",
    "wof:name":"Fonzone Chas J Atty",
    "wof:placetype":"venue"
},
  "geometry": {"coordinates":[-75.471603,40.602001],"type":"Point"}
}