{
  "type": "Feature",
  "properties": {
    "iso:country":"US",
    "sg:address":"809 Spruce St",
    "sg:city":"Pottstown",
    "sg:classifiers":[
        {
            "category":"Building & Trades",
            "subcategory":"Construction",
            "type":"Services"
        },
        {
            "category":"Building & Trades",
            "subcategory":"Plumbing",
            "type":"Services"
        }
    ],
    "sg:phone":"+1 610 327 1053",
    "sg:postcode":"19464",
    "sg:province":"PA",
    "sg:tags":[
        "repair",
        "sewer",
        "contractor"
    ],
    "wof:name":"Mc Kissic Plumbing & Heating",
    "wof:placetype":"venue"
},
  "geometry": {"coordinates":[-75.63733000000001,40.258888],"type":"Point"}
}