{
  "type": "Feature",
  "properties": {
    "iso:country":"US",
    "sg:address":"870 Green Ridge Rd",
    "sg:city":"New Oxford",
    "sg:classifiers":[
        {
            "category":"Insurance",
            "subcategory":"Insurance Agent",
            "type":"Services"
        }
    ],
    "sg:phone":"+1   ",
    "sg:postcode":"17350",
    "sg:province":"PA",
    "wof:name":"Sue A Arthur",
    "wof:placetype":"venue"
},
  "geometry": {"coordinates":[-77.03389799999999,39.928588],"type":"Point"}
}