{
  "type": "Feature",
  "properties": {
    "addr:full":"621 E North Ave Pittsburgh PA 15212",
    "addr:housenumber":"621",
    "addr:postcode":"15212",
    "addr:street":"E North Ave",
    "iso:country":"US",
    "sg:address":"621 E North Ave",
    "sg:city":"Pittsburgh",
    "sg:classifiers":[
        {
            "category":"Social Services",
            "subcategory":"Child Care",
            "type":"Services"
        }
    ],
    "sg:phone":"+1 412 231 0250",
    "sg:postcode":"15212",
    "sg:province":"PA",
    "sg:tags":[
        "day"
    ],
    "sg:website":"www.brighthorizons.com",
    "wof:name":"Agh Center For Children",
    "wof:placetype":"venue"
},
  "geometry": {"coordinates":[-79.999166,40.456745],"type":"Point"}
}