{
  "type": "Feature",
  "properties": {
    "iso:country":"US",
    "sg:address":"5016 N Convent Ln",
    "sg:city":"Philadelphia",
    "sg:classifiers":[
        {
            "category":"Retail",
            "subcategory":"Portrait Studio",
            "type":"Services"
        }
    ],
    "sg:phone":"+1   ",
    "sg:postcode":"19114",
    "sg:province":"PA",
    "sg:tags":[
        "photography",
        "production",
        "video"
    ],
    "wof:name":"Coopersmith Photography Video",
    "wof:placetype":"venue"
},
  "geometry": {"coordinates":[-74.984324,40.048736],"type":"Point"}
}