{
  "type": "Feature",
  "properties": {
    "iso:country":"US",
    "sg:address":"534 Main St",
    "sg:city":"Stroudsburg",
    "sg:classifiers":[
        {
            "category":"Personal",
            "subcategory":"Beauty Salon",
            "type":"Services"
        }
    ],
    "sg:phone":"+1 570 426 9003",
    "sg:postcode":"18360",
    "sg:province":"PA",
    "wof:name":"New York Styles",
    "wof:placetype":"venue"
},
  "geometry": {"coordinates":[-75.1913,40.986171],"type":"Point"}
}