{
  "type": "Feature",
  "properties": {
    "iso:country":"US",
    "sg:address":"100 S Jackson Ave",
    "sg:city":"Pittsburgh",
    "sg:classifiers":[
        {
            "category":"Health Services",
            "subcategory":"Doctor",
            "type":"Services"
        }
    ],
    "sg:phone":"+1 412 734 6162",
    "sg:postcode":"15202",
    "sg:province":"PA",
    "sg:tags":[
        "physician",
        "surgeon"
    ],
    "wof:name":"Bellevue Anesthesia Assoc",
    "wof:placetype":"venue"
},
  "geometry": {"coordinates":[-80.060131,40.49524],"type":"Point"}
}