{
  "type": "Feature",
  "properties": {
    "addr:full":"603 Wilson Ave Hanover PA 17331",
    "addr:housenumber":"603",
    "addr:postcode":"17331",
    "addr:street":"Wilson Ave",
    "iso:country":"US",
    "sg:address":"603 Wilson Ave",
    "sg:city":"Hanover",
    "sg:classifiers":[
        {
            "category":"Social Services",
            "subcategory":"Child Care",
            "type":"Services"
        },
        {
            "category":"Organizations",
            "subcategory":"Religious Organization",
            "type":"Services"
        }
    ],
    "sg:phone":"+1 717 632 2676",
    "sg:postcode":"17331",
    "sg:province":"PA",
    "wof:name":"Shepherds Fold Day Care Center",
    "wof:placetype":"venue"
},
  "geometry": {"coordinates":[-76.96871299999999,39.817257],"type":"Point"}
}