{
  "type": "Feature",
  "properties": {
    "iso:country":"US",
    "sg:address":"125 Rock St",
    "sg:city":"Pittston",
    "sg:classifiers":[
        {
            "category":"Autos & Motor Vehicles",
            "subcategory":"Automobile Sales",
            "type":"Retail Goods"
        }
    ],
    "sg:phone":"+1   ",
    "sg:postcode":"18640",
    "sg:province":"PA",
    "sg:tags":[
        "used"
    ],
    "wof:name":"Unique Autos",
    "wof:placetype":"venue"
},
  "geometry": {"coordinates":[-75.77161599999999,41.326027],"type":"Point"}
}