{
  "type": "Feature",
  "properties": {
    "iso:country":"US",
    "sg:address":"1600 N 5th St",
    "sg:city":"Philadelphia",
    "sg:classifiers":[
        {
            "category":"Professional",
            "subcategory":"Advertising",
            "type":"Services"
        }
    ],
    "sg:phone":"+1   ",
    "sg:postcode":"19122",
    "sg:province":"PA",
    "sg:tags":[
        "mail",
        "printing",
        "laser",
        "direct",
        "first"
    ],
    "wof:name":"City Sort Ltd",
    "wof:placetype":"venue"
},
  "geometry": {"coordinates":[-75.14353,39.976869],"type":"Point"}
}