{
  "type": "Feature",
  "properties": {
    "addr:full":"1308 Alvira Rd Allenwood PA 17810",
    "addr:housenumber":"1308",
    "addr:postcode":"17810",
    "addr:street":"Alvira Rd",
    "iso:country":"US",
    "sg:address":"1308 Alvira Rd",
    "sg:city":"Allenwood",
    "sg:classifiers":[
        {
            "category":"Building & Trades",
            "subcategory":"Construction",
            "type":"Services"
        }
    ],
    "sg:phone":"+1   ",
    "sg:postcode":"17810",
    "sg:province":"PA",
    "sg:tags":[
        "carpentry",
        "contractor"
    ],
    "wof:name":"Fred Hill Jr",
    "wof:placetype":"venue"
},
  "geometry": {"coordinates":[-76.97608700000001,41.144927],"type":"Point"}
}