{
  "type": "Feature",
  "properties": {
    "addr:full":"155 Levittown Pkwy Levittown PA 19055",
    "addr:housenumber":"155",
    "addr:postcode":"19055",
    "addr:street":"Levittown Pkwy",
    "iso:country":"US",
    "sg:address":"155 Levittown Pkwy",
    "sg:city":"Levittown",
    "sg:classifiers":[
        {
            "category":"Shopping",
            "subcategory":"Clothing, Apparel, & Fashions",
            "type":"Retail Goods"
        }
    ],
    "sg:phone":"+1 215 945 1232",
    "sg:postcode":"19055",
    "sg:province":"PA",
    "sg:tags":[
        "accessory",
        "clothing",
        "women's"
    ],
    "wof:name":"Deb Shops",
    "wof:placetype":"venue"
},
  "geometry": {"coordinates":[-74.820284,40.143634],"type":"Point"}
}