{
  "type": "Feature",
  "properties": {
    "addr:full":"12 Stover Dr Carlisle PA 17015",
    "addr:housenumber":"12",
    "addr:postcode":"17015",
    "addr:street":"Stover Dr",
    "iso:country":"US",
    "sg:address":"12 Stover Dr",
    "sg:city":"Carlisle",
    "sg:classifiers":[
        {
            "category":"Organizations",
            "subcategory":"Political Organization",
            "type":"Services"
        }
    ],
    "sg:phone":"+1 717 258 0708",
    "sg:postcode":"17015",
    "sg:province":"PA",
    "wof:name":"Cumberland County Republican",
    "wof:placetype":"venue"
},
  "geometry": {"coordinates":[-77.137908,40.222733],"type":"Point"}
}