{
  "type": "Feature",
  "properties": {
    "iso:country":"US",
    "sg:address":"7720 Perry Hwy",
    "sg:city":"Pittsburgh",
    "sg:classifiers":[
        {
            "category":"Professional",
            "subcategory":"Business Services",
            "type":"Services"
        }
    ],
    "sg:phone":"+1   ",
    "sg:postcode":"15237",
    "sg:province":"PA",
    "wof:name":"William F Ellis Interiors",
    "wof:placetype":"venue"
},
  "geometry": {"coordinates":[-80.036993,40.54952],"type":"Point"}
}