{
  "type": "Feature",
  "properties": {
    "iso:country":"US",
    "sg:address":"278 S Mercer St",
    "sg:city":"Greenville",
    "sg:classifiers":[
        {
            "category":"Government",
            "subcategory":"Office",
            "type":"Public Place"
        }
    ],
    "sg:phone":"+1   ",
    "sg:postcode":"16125",
    "sg:province":"PA",
    "sg:tags":[
        "executive"
    ],
    "wof:name":"Hempfield Township Supervisors",
    "wof:placetype":"venue"
},
  "geometry": {"coordinates":[-80.372484,41.393792],"type":"Point"}
}