{
  "type": "Feature",
  "properties": {
    "iso:country":"US",
    "sg:address":"1201 E Erie Ave",
    "sg:city":"Philadelphia",
    "sg:classifiers":[
        {
            "category":"Manufacturing",
            "subcategory":"Retail Goods",
            "type":"Manufacturing & Wholesale Goods"
        }
    ],
    "sg:phone":"+1   ",
    "sg:postcode":"19124",
    "sg:province":"PA",
    "sg:tags":[
        "product",
        "mfg"
    ],
    "wof:name":"Ziabaris Industries LLC",
    "wof:placetype":"venue"
},
  "geometry": {"coordinates":[-75.10326999999999,40.005601],"type":"Point"}
}