{
  "type": "Feature",
  "properties": {
    "iso:country":"US",
    "sg:address":"717 Millers Run Rd.",
    "sg:city":"Mc Donald",
    "sg:classifiers":[
        {
            "category":"Retail",
            "subcategory":"Auto Repair",
            "type":"Services"
        }
    ],
    "sg:phone":"+1 412 221 4660",
    "sg:postcode":"15057",
    "sg:province":"PA",
    "sg:website":"www.LeeStreetGarage.com/",
    "wof:name":"Lee Street Garage",
    "wof:placetype":"venue"
},
  "geometry": {"coordinates":[-80.172148,40.343286],"type":"Point"}
}