{
  "type": "Feature",
  "properties": {
    "iso:country":"US",
    "sg:address":"272 Main St",
    "sg:city":"Dickson City",
    "sg:classifiers":[
        {
            "category":"Communications",
            "subcategory":"Radio Station",
            "type":"Services"
        },
        {
            "category":"Wholesale",
            "subcategory":"Electrical",
            "type":"Manufacturing & Wholesale Goods"
        }
    ],
    "sg:phone":"+1 570 342 2198",
    "sg:postcode":"18519",
    "sg:province":"PA",
    "sg:tags":[
        "communication",
        "company",
        "broadcasting",
        "system"
    ],
    "wof:name":"Purosky & Tuckerman Radio",
    "wof:placetype":"venue"
},
  "geometry": {"coordinates":[-75.63585,41.451976],"type":"Point"}
}