{
  "type": "Feature",
  "properties": {
    "iso:country":"US",
    "sg:address":"1724 Bridge St",
    "sg:city":"Philadelphia",
    "sg:classifiers":[
        {
            "category":"Restaurant",
            "type":"Food & Drink"
        }
    ],
    "sg:phone":"+1 215 289 1792",
    "sg:postcode":"19124",
    "sg:province":"PA",
    "sg:tags":[
        "eating"
    ],
    "wof:name":"Foo Kwai Inn",
    "wof:placetype":"venue"
},
  "geometry": {"coordinates":[-75.0746,40.020901],"type":"Point"}
}