{
  "type": "Feature",
  "properties": {
    "iso:country":"US",
    "sg:address":"597 Butler St",
    "sg:city":"Pittsburgh",
    "sg:classifiers":[
        {
            "category":"Retail",
            "subcategory":"Repair Shop",
            "type":"Services"
        }
    ],
    "sg:phone":"+1   ",
    "sg:postcode":"15223",
    "sg:province":"PA",
    "sg:tags":[
        "equipment"
    ],
    "wof:name":"Fast Serv Medical",
    "wof:placetype":"venue"
},
  "geometry": {"coordinates":[-79.947022,40.5028],"type":"Point"}
}