{
  "type": "Feature",
  "properties": {
    "iso:country":"US",
    "sg:address":"9 Colonial Hts",
    "sg:city":"Bradford",
    "sg:classifiers":[
        {
            "category":"Professional",
            "subcategory":"Accounting & Tax Preparation",
            "type":"Services"
        }
    ],
    "sg:phone":"+1   ",
    "sg:postcode":"16701",
    "sg:province":"PA",
    "wof:name":"Bookkeeping Express",
    "wof:placetype":"venue"
},
  "geometry": {"coordinates":[-78.647029,41.975854],"type":"Point"}
}