{
  "type": "Feature",
  "properties": {
    "iso:country":"US",
    "sg:address":"2819 Liberty Way",
    "sg:city":"Mckeesport",
    "sg:classifiers":[
        {
            "category":"Building & Trades",
            "subcategory":"Electrical",
            "type":"Services"
        }
    ],
    "sg:phone":"+1 412 678 4988",
    "sg:postcode":"15133",
    "sg:province":"PA",
    "sg:tags":[
        "electrical",
        "electric",
        "contractor"
    ],
    "wof:name":"Katelyn Electrical Systems Inc",
    "wof:placetype":"venue"
},
  "geometry": {"coordinates":[-79.856328,40.326025],"type":"Point"}
}