{
  "type": "Feature",
  "properties": {
    "addr:full":"800 E Lancaster Ave Villanova PA 19085",
    "addr:housenumber":"800",
    "addr:postcode":"19085",
    "addr:street":"E Lancaster Ave",
    "iso:country":"US",
    "sg:address":"800 E Lancaster Ave",
    "sg:city":"Villanova",
    "sg:classifiers":[
        {
            "category":"Education",
            "subcategory":"University",
            "type":"Public Place"
        }
    ],
    "sg:phone":"+1 610 519 6000",
    "sg:postcode":"19085",
    "sg:province":"PA",
    "sg:tags":[
        "college"
    ],
    "wof:name":"Delaware County Authority, Pennsylvania, Villanova University",
    "wof:placetype":"venue"
},
  "geometry": {"coordinates":[-75.34922,40.035919],"type":"Point"}
}