{
  "type": "Feature",
  "properties": {
    "iso:country":"US",
    "sg:address":"313 Carroll St",
    "sg:city":"Reading",
    "sg:classifiers":[
        {
            "category":"Building & Trades",
            "subcategory":"Construction",
            "type":"Services"
        }
    ],
    "sg:phone":"+1   ",
    "sg:postcode":"19611",
    "sg:province":"PA",
    "sg:tags":[
        "house"
    ],
    "wof:name":"Olli Klatt & Sons Hm Remodelin",
    "wof:placetype":"venue"
},
  "geometry": {"coordinates":[-75.930173,40.318672],"type":"Point"}
}