{
  "type": "Feature",
  "properties": {
    "iso:country":"US",
    "sg:address":"10887 Edinboro Rd",
    "sg:city":"Mc Kean",
    "sg:classifiers":[
        {
            "category":"Professional",
            "subcategory":"Business Services",
            "type":"Services"
        }
    ],
    "sg:phone":"+1 814 450 2495",
    "sg:postcode":"16426",
    "sg:province":"PA",
    "sg:tags":[
        "water",
        "treatment"
    ],
    "wof:name":"A A Aqua Alter",
    "wof:placetype":"venue"
},
  "geometry": {"coordinates":[-80.12859400000001,41.93972],"type":"Point"}
}