{
  "type": "Feature",
  "properties": {
    "iso:country":"US",
    "sg:address":"31 Rampart Dr",
    "sg:city":"Chesterbrook",
    "sg:classifiers":[
        {
            "category":"Professional",
            "subcategory":"Computer Services",
            "type":"Services"
        }
    ],
    "sg:phone":"+1 610 408 9800",
    "sg:postcode":"19087",
    "sg:province":"PA",
    "sg:tags":[
        "consultant",
        "designer",
        "programing",
        "custom"
    ],
    "wof:name":"Toole Inc",
    "wof:placetype":"venue"
},
  "geometry": {"coordinates":[-75.464122,40.076797],"type":"Point"}
}