{
  "type": "Feature",
  "properties": {
    "addr:full":"7 Spring St Media PA 19063",
    "addr:housenumber":"7",
    "addr:postcode":"19063",
    "addr:street":"Spring St",
    "iso:country":"US",
    "sg:address":"7 Spring St",
    "sg:city":"Media",
    "sg:classifiers":[
        {
            "category":"Building & Trades",
            "subcategory":"Equipment Rental",
            "type":"Services"
        }
    ],
    "sg:phone":"+1 610 891 0292",
    "sg:postcode":"19063",
    "sg:province":"PA",
    "sg:tags":[
        "supply",
        "contractor"
    ],
    "wof:name":"Robin W Seitz Contractor",
    "wof:placetype":"venue"
},
  "geometry": {"coordinates":[-75.384208,39.926238],"type":"Point"}
}