{
  "type": "Feature",
  "properties": {
    "iso:country":"US",
    "sg:address":"1503 Quentin Rd",
    "sg:city":"Lebanon",
    "sg:classifiers":[
        {
            "category":"Professional",
            "subcategory":"Accounting & Tax Preparation",
            "type":"Services"
        }
    ],
    "sg:phone":"+1 717 274 7576",
    "sg:postcode":"17042",
    "sg:province":"PA",
    "sg:tags":[
        "billing"
    ],
    "wof:name":"Professional Financial Svc",
    "wof:placetype":"venue"
},
  "geometry": {"coordinates":[-76.423328,40.317429],"type":"Point"}
}