{
  "type": "Feature",
  "properties": {
    "iso:country":"US",
    "sg:address":"860 Market St",
    "sg:city":"Mt Wolf",
    "sg:classifiers":[
        {
            "category":"Organizations",
            "subcategory":"Religious Organization",
            "type":"Services"
        }
    ],
    "sg:phone":"+1 717 266 6186",
    "sg:postcode":"17347",
    "sg:province":"PA",
    "sg:tags":[
        "church"
    ],
    "wof:name":"Community United Methodist Chr",
    "wof:placetype":"venue"
},
  "geometry": {"coordinates":[-76.675887,40.063819],"type":"Point"}
}