{
  "type": "Feature",
  "properties": {
    "iso:country":"US",
    "sg:address":"1174 Tinker St",
    "sg:city":"Willow Grove",
    "sg:classifiers":[
        {
            "category":"Government",
            "subcategory":"Office",
            "type":"Public Place"
        }
    ],
    "sg:phone":"+1   ",
    "sg:postcode":"19090",
    "sg:province":"PA",
    "sg:tags":[
        "national",
        "security"
    ],
    "wof:name":"270 Eis",
    "wof:placetype":"venue"
},
  "geometry": {"coordinates":[-75.144811,40.212334],"type":"Point"}
}