{
  "type": "Feature",
  "properties": {
    "addr:full":"220 Radcliffe St Bristol PA 19007",
    "addr:housenumber":"220",
    "addr:postcode":"19007",
    "addr:street":"Radcliffe St",
    "iso:country":"US",
    "sg:address":"220 Radcliffe St",
    "sg:city":"Bristol",
    "sg:classifiers":[
        {
            "category":"Professional",
            "subcategory":"Lawyer & Legal Services",
            "type":"Services"
        }
    ],
    "sg:phone":"+1 215 788 5450",
    "sg:postcode":"19007",
    "sg:province":"PA",
    "sg:tags":[
        "attorney",
        "practice",
        "plan"
    ],
    "wof:name":"William J Salerno",
    "wof:placetype":"venue"
},
  "geometry": {"coordinates":[-74.85526299999999,40.095199],"type":"Point"}
}