{
  "type": "Feature",
  "properties": {
    "addr:full":"1711 Moyer Rd Hatfield PA 19440",
    "addr:housenumber":"1711",
    "addr:postcode":"19440",
    "addr:street":"Moyer Rd",
    "iso:country":"US",
    "sg:address":"1711 Moyer Rd",
    "sg:city":"Hatfield",
    "sg:classifiers":[
        {
            "category":"Professional",
            "subcategory":"Business Services",
            "type":"Services"
        }
    ],
    "sg:phone":"+1 267 496 7901",
    "sg:postcode":"19440",
    "sg:province":"PA",
    "sg:tags":[
        "consultant",
        "coach"
    ],
    "wof:name":"Global Biopharm Solutions",
    "wof:placetype":"venue"
},
  "geometry": {"coordinates":[-75.27533699999999,40.263168],"type":"Point"}
}