{
  "type": "Feature",
  "properties": {
    "addr:full":"6330 River Dr York PA 17406",
    "addr:housenumber":"6330",
    "addr:postcode":"17406",
    "addr:street":"River Dr",
    "iso:country":"US",
    "sg:address":"6330 River Dr",
    "sg:city":"York",
    "sg:classifiers":[
        {
            "category":"Restaurant",
            "type":"Food & Drink"
        }
    ],
    "sg:phone":"+1 717 252 4058",
    "sg:postcode":"17406",
    "sg:province":"PA",
    "sg:tags":[
        "caterer"
    ],
    "sg:website":"www.accomaccatering.com",
    "wof:name":"Accomac Catering",
    "wof:placetype":"venue"
},
  "geometry": {"coordinates":[-76.563563,40.045394],"type":"Point"}
}