{
  "type": "Feature",
  "properties": {
    "addr:full":"7 S Penn Ave Greenville PA 16125",
    "addr:housenumber":"7",
    "addr:postcode":"16125",
    "addr:street":"S Penn Ave",
    "iso:country":"US",
    "sg:address":"7 S Penn Ave",
    "sg:city":"Greenville",
    "sg:classifiers":[
        {
            "category":"Health Services",
            "subcategory":"Podiatrist",
            "type":"Services"
        }
    ],
    "sg:phone":"+1 724 588 4011",
    "sg:postcode":"16125",
    "sg:province":"PA",
    "wof:name":"Ray R Schneider DPM",
    "wof:placetype":"venue"
},
  "geometry": {"coordinates":[-80.38576500000001,41.404833],"type":"Point"}
}