{
  "type": "Feature",
  "properties": {
    "iso:country":"US",
    "sg:address":"7018 Shannon Rd",
    "sg:city":"Verona",
    "sg:classifiers":[
        {
            "category":"Retail",
            "subcategory":"Auto Repair",
            "type":"Services"
        }
    ],
    "sg:phone":"+1   ",
    "sg:postcode":"15147",
    "sg:province":"PA",
    "sg:tags":[
        "general"
    ],
    "wof:name":"Scot Auto",
    "wof:placetype":"venue"
},
  "geometry": {"coordinates":[-79.827427,40.4911],"type":"Point"}
}