{
  "type": "Feature",
  "properties": {
    "addr:full":"1220 Wood Rd Hummelstown PA 17036",
    "addr:housenumber":"1220",
    "addr:postcode":"17036",
    "addr:street":"Wood Rd",
    "iso:country":"US",
    "sg:address":"1220 Wood Rd",
    "sg:city":"Hummelstown",
    "sg:classifiers":[
        {
            "category":"Manufacturing",
            "subcategory":"Furniture",
            "type":"Manufacturing & Wholesale Goods"
        }
    ],
    "sg:phone":"+1   ",
    "sg:postcode":"17036",
    "sg:province":"PA",
    "sg:tags":[
        "household",
        "wood",
        "mfg"
    ],
    "wof:name":"Richard Wachtman",
    "wof:placetype":"venue"
},
  "geometry": {"coordinates":[-76.689205,40.255503],"type":"Point"}
}