{
  "type": "Feature",
  "properties": {
    "iso:country":"US",
    "sg:address":"1485 Valley Forge Rd",
    "sg:city":"Norristown",
    "sg:classifiers":[
        {
            "category":"Organizations",
            "subcategory":"Religious Organization",
            "type":"Services"
        }
    ],
    "sg:phone":"+1 610 935 7960",
    "sg:postcode":"19403",
    "sg:province":"PA",
    "sg:tags":[
        "church"
    ],
    "sg:website":"www.gracevalleyfellowship.org",
    "wof:name":"Grace Valley Fellowship",
    "wof:placetype":"venue"
},
  "geometry": {"coordinates":[-75.364302,40.178381],"type":"Point"}
}