{
  "type": "Feature",
  "properties": {
    "iso:country":"US",
    "sg:address":"611 McGovern Blvd",
    "sg:city":"Coraopolis",
    "sg:classifiers":[
        {
            "category":"Recreation",
            "type":"Entertainment"
        }
    ],
    "sg:phone":"+1   ",
    "sg:postcode":"15108",
    "sg:province":"PA",
    "sg:tags":[
        "club",
        "membership"
    ],
    "wof:name":"Consumers Fighting Back",
    "wof:placetype":"venue"
},
  "geometry": {"coordinates":[-80.218581,40.544427],"type":"Point"}
}