{
  "type": "Feature",
  "properties": {
    "iso:country":"US",
    "sg:address":"4410 Township Line Rd",
    "sg:city":"Drexel Hill",
    "sg:classifiers":[
        {
            "category":"Professional",
            "type":"Services"
        }
    ],
    "sg:phone":"+1 610 449 3578",
    "sg:postcode":"19026",
    "sg:province":"PA",
    "sg:tags":[
        "scientist"
    ],
    "wof:name":"Sans Technology Assoc",
    "wof:placetype":"venue"
},
  "geometry": {"coordinates":[-75.315956,39.958771],"type":"Point"}
}