{
  "type": "Feature",
  "properties": {
    "iso:country":"US",
    "sg:address":"112 Fennel Dr",
    "sg:city":"Butler",
    "sg:classifiers":[
        {
            "category":"Manufacturing",
            "subcategory":"Petroleum Products",
            "type":"Manufacturing & Wholesale Goods"
        }
    ],
    "sg:phone":"+1 724 283 8055",
    "sg:postcode":"16002",
    "sg:province":"PA",
    "sg:tags":[
        "lubricating",
        "oil",
        "additive",
        "mfg",
        "production",
        "grease",
        "lubricant"
    ],
    "sg:website":"www.mpc-home.com",
    "wof:name":"Muscle Products Corporation",
    "wof:placetype":"venue"
},
  "geometry": {"coordinates":[-79.86913800000001,40.839376],"type":"Point"}
}