{
  "type": "Feature",
  "properties": {
    "addr:full":"352 Allenwood Camp Ln Montgomery PA 17752",
    "addr:housenumber":"352",
    "addr:postcode":"17752",
    "addr:street":"Allenwood Camp Ln",
    "iso:country":"US",
    "sg:address":"352 Allenwood Camp Ln",
    "sg:city":"Montgomery",
    "sg:classifiers":[
        {
            "category":"Sports & Exercise",
            "subcategory":"Golf",
            "type":"Entertainment"
        }
    ],
    "sg:phone":"+1 570 547 2186",
    "sg:postcode":"17752",
    "sg:province":"PA",
    "sg:tags":[
        "course"
    ],
    "wof:name":"White Deer Park & Golf Course",
    "wof:placetype":"venue"
},
  "geometry": {"coordinates":[-76.918408,41.167477],"type":"Point"}
}