{
  "type": "Feature",
  "properties": {
    "addr:full":"627 Oregon Ave Erie PA 16505",
    "addr:housenumber":"627",
    "addr:postcode":"16505",
    "addr:street":"Oregon Ave",
    "iso:country":"US",
    "sg:address":"627 Oregon Ave",
    "sg:city":"Erie",
    "sg:classifiers":[
        {
            "category":"Real Estate",
            "subcategory":"Real Estate Agent",
            "type":"Services"
        }
    ],
    "sg:phone":"+1 814 833 5392",
    "sg:postcode":"16505",
    "sg:province":"PA",
    "wof:name":"William J Dorris",
    "wof:placetype":"venue"
},
  "geometry": {"coordinates":[-80.156903,42.101458],"type":"Point"}
}