{
  "type": "Feature",
  "properties": {
    "iso:country":"US",
    "sg:address":"PO Box 177",
    "sg:city":"Mount Holly Springs",
    "sg:classifiers":[
        {
            "category":"Personal",
            "subcategory":"Tanning Parlor",
            "type":"Services"
        }
    ],
    "sg:phone":"+1 717 486 3804",
    "sg:postcode":"17065",
    "sg:province":"PA",
    "wof:name":"Jill's Beauty Salon",
    "wof:placetype":"venue"
},
  "geometry": {"coordinates":[-77.194901,40.123798],"type":"Point"}
}