{
  "type": "Feature",
  "properties": {
    "addr:full":"41 N Center St Corry PA 16407",
    "addr:housenumber":"41",
    "addr:postcode":"16407",
    "addr:street":"N Center St",
    "iso:country":"US",
    "sg:address":"41 N Center St",
    "sg:city":"Corry",
    "sg:classifiers":[
        {
            "category":"Health Services",
            "subcategory":"Health Practitioner",
            "type":"Services"
        }
    ],
    "sg:phone":"+1 814 663 7878",
    "sg:postcode":"16407",
    "sg:province":"PA",
    "sg:tags":[
        "therapist",
        "physical"
    ],
    "wof:name":"Masters Physical Therapy",
    "wof:placetype":"venue"
},
  "geometry": {"coordinates":[-79.640489,41.920471],"type":"Point"}
}