{
  "type": "Feature",
  "properties": {
    "iso:country":"US",
    "sg:address":"717 Liberty Ave",
    "sg:city":"Pittsburgh",
    "sg:classifiers":[
        {
            "category":"Shopping",
            "subcategory":"Clothing, Apparel, & Fashions",
            "type":"Retail Goods"
        }
    ],
    "sg:phone":"+1 866 452 4425",
    "sg:postcode":"15219",
    "sg:province":"PA",
    "sg:tags":[
        "clothing",
        "women's"
    ],
    "sg:website":"www.chickdowntown.com",
    "wof:name":"Chick Clothing Boutique",
    "wof:placetype":"venue"
},
  "geometry": {"coordinates":[-79.999307,40.442705],"type":"Point"}
}