{
  "type": "Feature",
  "properties": {
    "addr:full":"598 Skippack Pike Fort Washington PA 19034",
    "addr:housenumber":"598",
    "addr:postcode":"19034",
    "addr:street":"Skippack Pike",
    "iso:country":"US",
    "sg:address":"598 Skippack Pike",
    "sg:city":"Fort Washington",
    "sg:classifiers":[
        {
            "category":"Real Estate",
            "subcategory":"Real Estate Agent",
            "type":"Services"
        }
    ],
    "sg:phone":"+1 215 654 5950",
    "sg:postcode":"19034",
    "sg:province":"PA",
    "wof:name":"Long & Foster Realtors",
    "wof:placetype":"venue"
},
  "geometry": {"coordinates":[-75.220035,40.124019],"type":"Point"}
}