{
  "type": "Feature",
  "properties": {
    "addr:full":"1360 Old Freeport Rd Pittsburgh PA 15238",
    "addr:housenumber":"1360",
    "addr:postcode":"15238",
    "addr:street":"Old Freeport Rd",
    "iso:country":"US",
    "sg:address":"1360 Old Freeport Rd",
    "sg:city":"Pittsburgh",
    "sg:classifiers":[
        {
            "category":"Health Services",
            "subcategory":"Hospital",
            "type":"Services"
        },
        {
            "category":"Health Services",
            "subcategory":"Nursing And Care Facility",
            "type":"Services"
        },
        {
            "category":"Health Services",
            "subcategory":"Health Practitioner",
            "type":"Services"
        },
        {
            "category":"Social Services",
            "subcategory":"Adult Care",
            "type":"Services"
        }
    ],
    "sg:phone":"+1 800 679 8783",
    "sg:postcode":"15238",
    "sg:province":"PA",
    "sg:tags":[
        "nurses-home",
        "nurse",
        "registry",
        "home"
    ],
    "sg:website":"http://www.careconnectionsinc.com",
    "wof:name":"Care Connections Inc",
    "wof:placetype":"venue"
},
  "geometry": {"coordinates":[-79.87253699999999,40.488809],"type":"Point"}
}