{
  "type": "Feature",
  "properties": {
    "addr:full":"69 Hazelwood Dr Washington PA 15301",
    "addr:housenumber":"69",
    "addr:postcode":"15301",
    "addr:street":"Hazelwood Dr",
    "iso:country":"US",
    "sg:address":"69 Hazelwood Dr",
    "sg:city":"Washington",
    "sg:classifiers":[
        {
            "category":"Building & Trades",
            "subcategory":"Construction",
            "type":"Services"
        }
    ],
    "sg:phone":"+1   ",
    "sg:postcode":"15301",
    "sg:province":"PA",
    "sg:tags":[
        "contractor"
    ],
    "wof:name":"Ringer Masonry Inc",
    "wof:placetype":"venue"
},
  "geometry": {"coordinates":[-80.248631,40.160492],"type":"Point"}
}