{
  "type": "Feature",
  "properties": {
    "iso:country":"US",
    "sg:address":"1725 Chestnut St",
    "sg:city":"Philadelphia",
    "sg:classifiers":[
        {
            "category":"Restaurant",
            "type":"Food & Drink"
        }
    ],
    "sg:phone":"+1 215 563 7601",
    "sg:postcode":"19103",
    "sg:province":"PA",
    "sg:tags":[
        "barbeque"
    ],
    "wof:name":"Famous Daves",
    "wof:placetype":"venue"
},
  "geometry": {"coordinates":[-75.169687,39.951826],"type":"Point"}
}