{
  "type": "Feature",
  "properties": {
    "addr:full":"158 Wyoming St Wilkes Barre PA 18705",
    "addr:housenumber":"158",
    "addr:postcode":"18705",
    "addr:street":"Wyoming St",
    "iso:country":"US",
    "sg:address":"158 Wyoming St",
    "sg:city":"Wilkes Barre",
    "sg:classifiers":[
        {
            "category":"Shopping",
            "subcategory":"Jewelry",
            "type":"Retail Goods"
        }
    ],
    "sg:phone":"+1   ",
    "sg:postcode":"18705",
    "sg:province":"PA",
    "wof:name":"Prestige Jewelers Inc",
    "wof:placetype":"venue"
},
  "geometry": {"coordinates":[-75.868748,41.25042],"type":"Point"}
}