{
  "type": "Feature",
  "properties": {
    "iso:country":"US",
    "sg:address":"408 E Pennsylvania Blvd",
    "sg:city":"Feastervl Trvs",
    "sg:classifiers":[
        {
            "category":"Health Services",
            "subcategory":"Medical Lab",
            "type":"Services"
        }
    ],
    "sg:phone":"+1 215 364 2105",
    "sg:postcode":"19053",
    "sg:province":"PA",
    "sg:tags":[
        "detection",
        "equipment",
        "drug",
        "laboratory"
    ],
    "wof:name":"National Precision Analysis",
    "wof:placetype":"venue"
},
  "geometry": {"coordinates":[-75.009979,40.151874],"type":"Point"}
}