{
  "type": "Feature",
  "properties": {
    "iso:country":"US",
    "sg:address":"2133 Arch St Fl 2",
    "sg:city":"Philadelphia",
    "sg:classifiers":[
        {
            "category":"Shopping",
            "subcategory":"Stationery & Office Supplies",
            "type":"Retail Goods"
        }
    ],
    "sg:phone":"+1 215 561 8765",
    "sg:postcode":"19103",
    "sg:province":"PA",
    "sg:tags":[
        "equipment"
    ],
    "wof:name":"Advanced Office Environments Inc",
    "wof:placetype":"venue"
},
  "geometry": {"coordinates":[-75.173203,39.951302],"type":"Point"}
}