{
  "type": "Feature",
  "properties": {
    "addr:full":"104 E 3rd Ave Collegeville PA 19426",
    "addr:housenumber":"104",
    "addr:postcode":"19426",
    "addr:street":"E 3Rd Ave",
    "iso:country":"US",
    "sg:address":"104 E 3rd Ave",
    "sg:city":"Collegeville",
    "sg:classifiers":[
        {
            "category":"Farming",
            "subcategory":"Dairy Farm",
            "type":"Manufacturing & Wholesale Goods"
        }
    ],
    "sg:phone":"+1   ",
    "sg:postcode":"19426",
    "sg:province":"PA",
    "wof:name":"Charles Wiser",
    "wof:placetype":"venue"
},
  "geometry": {"coordinates":[-75.462439,40.205077],"type":"Point"}
}