{
  "type": "Feature",
  "properties": {
    "iso:country":"US",
    "sg:address":"745 Wallace Rd",
    "sg:city":"New Holland",
    "sg:classifiers":[
        {
            "category":"Retail",
            "subcategory":"Auto Repair",
            "type":"Services"
        }
    ],
    "sg:phone":"+1 717 354 8651",
    "sg:postcode":"17557",
    "sg:province":"PA",
    "sg:tags":[
        "wrecker"
    ],
    "wof:name":"Wagner & Jackson",
    "wof:placetype":"venue"
},
  "geometry": {"coordinates":[-76.04406400000001,40.078345],"type":"Point"}
}