{
  "type": "Feature",
  "properties": {
    "iso:country":"US",
    "sg:address":"202 S 3rd St Ste 6",
    "sg:city":"Coopersburg",
    "sg:classifiers":[
        {
            "category":"Communications",
            "subcategory":"Newspaper",
            "type":"Services"
        }
    ],
    "sg:phone":"+1 610 282 4808",
    "sg:postcode":"18036",
    "sg:province":"PA",
    "sg:tags":[
        "print",
        "medium"
    ],
    "wof:name":"Penny Power",
    "wof:placetype":"venue"
},
  "geometry": {"coordinates":[-75.386224,40.508235],"type":"Point"}
}