{
  "type": "Feature",
  "properties": {
    "iso:country":"US",
    "sg:address":"550 W Frederick St",
    "sg:city":"Lancaster",
    "sg:classifiers":[
        {
            "category":"Professional",
            "subcategory":"Research",
            "type":"Services"
        }
    ],
    "sg:phone":"+1 717 399 4448",
    "sg:postcode":"17603",
    "sg:province":"PA",
    "sg:tags":[
        "educational"
    ],
    "wof:name":"Heds",
    "wof:placetype":"venue"
},
  "geometry": {"coordinates":[-76.317958,40.046342],"type":"Point"}
}