{
  "type": "Feature",
  "properties": {
    "iso:country":"US",
    "sg:address":"141 Coal Bank Rd",
    "sg:city":"Greenville",
    "sg:classifiers":[
        {
            "category":"Wholesale",
            "subcategory":"Stationery",
            "type":"Manufacturing & Wholesale Goods"
        }
    ],
    "sg:phone":"+1   ",
    "sg:postcode":"16125",
    "sg:province":"PA",
    "sg:tags":[
        "supply"
    ],
    "wof:name":"Purr-Fect Pages",
    "wof:placetype":"venue"
},
  "geometry": {"coordinates":[-80.425043,41.42733],"type":"Point"}
}