{
  "type": "Feature",
  "properties": {
    "iso:country":"US",
    "sg:address":"36 N 34th St",
    "sg:city":"Harrisburg",
    "sg:classifiers":[
        {
            "category":"Real Estate",
            "subcategory":"Real Estate Agent",
            "type":"Services"
        }
    ],
    "sg:phone":"+1   ",
    "sg:postcode":"17109",
    "sg:province":"PA",
    "sg:tags":[
        "property",
        "management"
    ],
    "wof:name":"Sac Properties",
    "wof:placetype":"venue"
},
  "geometry": {"coordinates":[-76.841416,40.286645],"type":"Point"}
}