{
  "type": "Feature",
  "properties": {
    "iso:country":"US",
    "sg:address":"194 Fr Martin Telenson Rd",
    "sg:city":"Penn Run",
    "sg:classifiers":[
        {
            "category":"Social Services",
            "subcategory":"Child Care",
            "type":"Services"
        }
    ],
    "sg:phone":"+1 724 465 6101",
    "sg:postcode":"15765",
    "sg:province":"PA",
    "wof:name":"Treasures From Heaven Daycare",
    "wof:placetype":"venue"
},
  "geometry": {"coordinates":[-79.005094,40.595824],"type":"Point"}
}