{
  "type": "Feature",
  "properties": {
    "iso:country":"US",
    "sg:address":"93 Carson Rd",
    "sg:city":"Clarion",
    "sg:classifiers":[
        {
            "category":"Home & Garden",
            "subcategory":"Building Materials",
            "type":"Retail Goods"
        }
    ],
    "sg:phone":"+1   ",
    "sg:postcode":"16214",
    "sg:province":"PA",
    "wof:name":"84 Lumber",
    "wof:placetype":"venue"
},
  "geometry": {"coordinates":[-79.3922,41.182274],"type":"Point"}
}