{
  "type": "Feature",
  "properties": {
    "iso:country":"US",
    "sg:address":"108 S Beech St",
    "sg:city":"Fleetwood",
    "sg:classifiers":[
        {
            "category":"Building & Trades",
            "subcategory":"Construction",
            "type":"Services"
        }
    ],
    "sg:phone":"+1   ",
    "sg:postcode":"19522",
    "sg:province":"PA",
    "sg:tags":[
        "house"
    ],
    "wof:name":"Kramer General Contractors",
    "wof:placetype":"venue"
},
  "geometry": {"coordinates":[-75.810946,40.456675],"type":"Point"}
}