{
  "type": "Feature",
  "properties": {
    "addr:full":"1271 Franklin Mills Cir Philadelphia PA 19154",
    "addr:housenumber":"1271",
    "addr:postcode":"19154",
    "addr:street":"Franklin Mills Cir",
    "iso:country":"US",
    "sg:address":"1271 Franklin Mills Cir",
    "sg:city":"Philadelphia",
    "sg:classifiers":[
        {
            "category":"Personal",
            "subcategory":"Beauty Salon",
            "type":"Services"
        },
        {
            "category":"Personal",
            "subcategory":"Barber",
            "type":"Services"
        }
    ],
    "sg:phone":"+1 215 281 9770",
    "sg:postcode":"19154",
    "sg:province":"PA",
    "sg:tags":[
        "hair",
        "accessory",
        "stylist",
        "supply"
    ],
    "sg:website":"http://www.haircuttery.com/",
    "wof:name":"Hair Cuttery",
    "wof:placetype":"venue"
},
  "geometry": {"coordinates":[-74.958945,40.088121],"type":"Point"}
}