{
  "type": "Feature",
  "properties": {
    "iso:country":"US",
    "sg:address":"22nd & Pine St",
    "sg:city":"Philadelphia",
    "sg:classifiers":[
        {
            "category":"Parking",
            "type":"Transportation"
        }
    ],
    "sg:phone":"+1 215 732 9900",
    "sg:postcode":"19102",
    "sg:province":"PA",
    "wof:name":"Acorn Garage Inc",
    "wof:placetype":"venue"
},
  "geometry": {"coordinates":[-75.178156,39.94719],"type":"Point"}
}