{
  "type": "Feature",
  "properties": {
    "iso:country":"US",
    "sg:address":"1201 N Progress Ave",
    "sg:city":"Harrisburg",
    "sg:classifiers":[
        {
            "category":"Education",
            "subcategory":"School",
            "type":"Public Place"
        }
    ],
    "sg:phone":"+1   ",
    "sg:postcode":"17109",
    "sg:province":"PA",
    "wof:name":"Saralindemuth Primary School",
    "wof:placetype":"venue"
},
  "geometry": {"coordinates":[-76.84844699999999,40.301868],"type":"Point"}
}