{
  "type": "Feature",
  "properties": {
    "iso:country":"US",
    "sg:address":"34 Penn Ridge Dr",
    "sg:city":"Bernville",
    "sg:classifiers":[
        {
            "category":"Building & Trades",
            "subcategory":"Landscaping Services",
            "type":"Services"
        }
    ],
    "sg:phone":"+1   ",
    "sg:postcode":"19506",
    "sg:province":"PA",
    "sg:tags":[
        "lawn",
        "garden"
    ],
    "wof:name":"Penn Ridge Nursery & Ldscp Co",
    "wof:placetype":"venue"
},
  "geometry": {"coordinates":[-76.030978,40.412965],"type":"Point"}
}