{
  "type": "Feature",
  "properties": {
    "iso:country":"US",
    "sg:address":"2013 N 63rd St",
    "sg:city":"Philadelphia",
    "sg:classifiers":[
        {
            "category":"Building & Trades",
            "subcategory":"Locksmith",
            "type":"Services"
        }
    ],
    "sg:phone":"+1 215 879 2611",
    "sg:postcode":"19151",
    "sg:province":"PA",
    "sg:tags":[
        "key"
    ],
    "wof:name":"Twenty Four Hour A Locksmith",
    "wof:placetype":"venue"
},
  "geometry": {"coordinates":[-75.248001,39.986198],"type":"Point"}
}