{
  "type": "Feature",
  "properties": {
    "iso:country":"US",
    "sg:address":"50 Longview Dr",
    "sg:city":"Glenmoore",
    "sg:classifiers":[
        {
            "category":"Restaurant",
            "type":"Food & Drink"
        }
    ],
    "sg:phone":"+1   ",
    "sg:postcode":"19343",
    "sg:province":"PA",
    "sg:tags":[
        "eating"
    ],
    "wof:name":"Dart Food Services",
    "wof:placetype":"venue"
},
  "geometry": {"coordinates":[-75.805516,40.092888],"type":"Point"}
}