{
  "type": "Feature",
  "properties": {
    "iso:country":"US",
    "sg:address":"1167 Smithbridge Rd",
    "sg:city":"Chadds Ford",
    "sg:classifiers":[
        {
            "category":"Building & Trades",
            "subcategory":"Plumbing",
            "type":"Services"
        }
    ],
    "sg:phone":"+1   ",
    "sg:postcode":"19317",
    "sg:province":"PA",
    "sg:tags":[
        "mechanical",
        "work",
        "remodeling",
        "contractor"
    ],
    "wof:name":"Scott Contractor",
    "wof:placetype":"venue"
},
  "geometry": {"coordinates":[-75.546077,39.854987],"type":"Point"}
}