{
  "type": "Feature",
  "properties": {
    "iso:country":"US",
    "sg:address":"19 Reid Dr",
    "sg:city":"Nottingham",
    "sg:classifiers":[
        {
            "category":"Wholesale",
            "subcategory":"Farm Supplies",
            "type":"Manufacturing & Wholesale Goods"
        }
    ],
    "sg:phone":"+1 484 883 8841",
    "sg:postcode":"19362",
    "sg:province":"PA",
    "sg:tags":[
        "equipment"
    ],
    "wof:name":"Mccarrahers Timber Framing",
    "wof:placetype":"venue"
},
  "geometry": {"coordinates":[-76.049611,39.749923],"type":"Point"}
}