{
  "type": "Feature",
  "properties": {
    "iso:country":"US",
    "sg:address":"1518 Elmira St",
    "sg:city":"Williamsport",
    "sg:classifiers":[
        {
            "category":"Professional",
            "subcategory":"Advertising",
            "type":"Services"
        }
    ],
    "sg:phone":"+1   ",
    "sg:postcode":"17701",
    "sg:province":"PA",
    "sg:tags":[
        "agency"
    ],
    "wof:name":"Network Advertising",
    "wof:placetype":"venue"
},
  "geometry": {"coordinates":[-77.009941,41.255038],"type":"Point"}
}