{
  "type": "Feature",
  "properties": {
    "iso:country":"US",
    "sg:address":"2590 Cranberry Rd",
    "sg:city":"York Springs",
    "sg:classifiers":[
        {
            "category":"Retail",
            "subcategory":"Auto Repair",
            "type":"Services"
        }
    ],
    "sg:phone":"+1 717 528 4186",
    "sg:postcode":"17372",
    "sg:province":"PA",
    "sg:tags":[
        "body",
        "automobile",
        "painting"
    ],
    "wof:name":"Dale E Pifer Body Shop",
    "wof:placetype":"venue"
},
  "geometry": {"coordinates":[-77.11919899999999,40.000396],"type":"Point"}
}