{
  "type": "Feature",
  "properties": {
    "addr:full":"43 Chestnut Rd Paoli PA 19301",
    "addr:housenumber":"43",
    "addr:postcode":"19301",
    "addr:street":"Chestnut Rd",
    "iso:country":"US",
    "sg:address":"43 Chestnut Rd",
    "sg:city":"Paoli",
    "sg:classifiers":[
        {
            "category":"Building & Trades",
            "subcategory":"Construction",
            "type":"Services"
        }
    ],
    "sg:phone":"+1   ",
    "sg:postcode":"19301",
    "sg:province":"PA",
    "sg:tags":[
        "hanging",
        "contractor"
    ],
    "wof:name":"Wassers Paperhanging & Pntg",
    "wof:placetype":"venue"
},
  "geometry": {"coordinates":[-75.47949,40.040737],"type":"Point"}
}