{
  "type": "Feature",
  "properties": {
    "addr:full":"226 Broad St Waverly PA 14892",
    "addr:housenumber":"226",
    "addr:postcode":"14892",
    "addr:street":"Broad St",
    "iso:country":"US",
    "sg:address":"226 Broad St",
    "sg:city":"Waverly",
    "sg:classifiers":[
        {
            "category":"Personal",
            "subcategory":"Beauty Salon",
            "type":"Services"
        }
    ],
    "sg:phone":"+1 607 565 3963",
    "sg:postcode":"14892",
    "sg:province":"PA",
    "wof:name":"Terry's Styling Salon",
    "wof:placetype":"venue"
},
  "geometry": {"coordinates":[-76.54454800000001,42.000724],"type":"Point"}
}