{
  "type": "Feature",
  "properties": {
    "iso:country":"US",
    "sg:address":"59 S Hickory Ln",
    "sg:city":"New Oxford",
    "sg:classifiers":[
        {
            "category":"Building & Trades",
            "subcategory":"Construction",
            "type":"Services"
        }
    ],
    "sg:phone":"+1 717 624 8460",
    "sg:postcode":"17350",
    "sg:province":"PA",
    "sg:tags":[
        "paving",
        "contractor"
    ],
    "wof:name":"Lewis P Reinhart & Sons Black",
    "wof:placetype":"venue"
},
  "geometry": {"coordinates":[-77.067086,39.89944],"type":"Point"}
}