{
  "type": "Feature",
  "properties": {
    "iso:country":"US",
    "sg:address":"2813 Jefferson St",
    "sg:city":"Altoona",
    "sg:classifiers":[
        {
            "category":"Building & Trades",
            "subcategory":"Construction",
            "type":"Services"
        }
    ],
    "sg:phone":"+1 814 944 6110",
    "sg:postcode":"16601",
    "sg:province":"PA",
    "sg:tags":[
        "handyman"
    ],
    "wof:name":"Newburg Handyman Svc",
    "wof:placetype":"venue"
},
  "geometry": {"coordinates":[-78.422662,40.519876],"type":"Point"}
}