{
  "type": "Feature",
  "properties": {
    "iso:country":"US",
    "sg:address":"1315 Randall Ave",
    "sg:city":"Levittown",
    "sg:classifiers":[
        {
            "category":"Retail",
            "subcategory":"Auto Repair",
            "type":"Services"
        }
    ],
    "sg:phone":"+1 215 943 2588",
    "sg:postcode":"19057",
    "sg:province":"PA",
    "sg:tags":[
        "automotive"
    ],
    "wof:name":"Street Sweep Towing",
    "wof:placetype":"venue"
},
  "geometry": {"coordinates":[-74.832256,40.129028],"type":"Point"}
}