{
  "type": "Feature",
  "properties": {
    "addr:full":"4002 Fenton Ave Harrisburg PA 17109",
    "addr:housenumber":"4002",
    "addr:postcode":"17109",
    "addr:street":"Fenton Ave",
    "iso:country":"US",
    "sg:address":"4002 Fenton Ave",
    "sg:city":"Harrisburg",
    "sg:classifiers":[
        {
            "category":"Organizations",
            "subcategory":"Membership Organization",
            "type":"Services"
        }
    ],
    "sg:phone":"+1 717 234 7927",
    "sg:postcode":"17109",
    "sg:province":"PA",
    "sg:tags":[
        "military",
        "veteran"
    ],
    "sg:website":"http://www.vfw.org",
    "wof:name":"Veterans of Foreign Wars",
    "wof:placetype":"venue"
},
  "geometry": {"coordinates":[-76.81955499999999,40.272832],"type":"Point"}
}