{
  "type": "Feature",
  "properties": {
    "iso:country":"US",
    "sg:address":"2188 Merrimac Ave",
    "sg:city":"Mechanicsburg",
    "sg:classifiers":[
        {
            "category":"Professional",
            "subcategory":"Computer Services",
            "type":"Services"
        }
    ],
    "sg:phone":"+1   ",
    "sg:postcode":"17055",
    "sg:province":"PA",
    "sg:tags":[
        "related"
    ],
    "wof:name":"Stonesifer Computing Syst",
    "wof:placetype":"venue"
},
  "geometry": {"coordinates":[-77.012541,40.166112],"type":"Point"}
}