{
  "type": "Feature",
  "properties": {
    "addr:full":"137 Pavia Plz Verona PA 15147",
    "addr:housenumber":"137",
    "addr:postcode":"15147",
    "addr:street":"Pavia Plz",
    "iso:country":"US",
    "sg:address":"137 Pavia Plz",
    "sg:city":"Verona",
    "sg:classifiers":[
        {
            "category":"Real Estate",
            "subcategory":"Real Estate Agent",
            "type":"Services"
        }
    ],
    "sg:phone":"+1 412 795 4410",
    "sg:postcode":"15147",
    "sg:province":"PA",
    "sg:tags":[
        "inspection"
    ],
    "wof:name":"Cratsa Construction",
    "wof:placetype":"venue"
},
  "geometry": {"coordinates":[-79.839376,40.498877],"type":"Point"}
}