{
  "type": "Feature",
  "properties": {
    "addr:full":"1036 N Irving St Allentown PA 18109",
    "addr:housenumber":"1036",
    "addr:postcode":"18109",
    "addr:street":"N Irving St",
    "iso:country":"US",
    "sg:address":"1036 N Irving St",
    "sg:city":"Allentown",
    "sg:classifiers":[
        {
            "category":"Manufacturing",
            "subcategory":"Chemicals & Compounds",
            "type":"Manufacturing & Wholesale Goods"
        }
    ],
    "sg:phone":"+1   ",
    "sg:postcode":"18109",
    "sg:province":"PA",
    "sg:tags":[
        "mfg",
        "printing",
        "ink"
    ],
    "wof:name":"Arcar Graphics Llc (del)",
    "wof:placetype":"venue"
},
  "geometry": {"coordinates":[-75.444277,40.626127],"type":"Point"}
}