{
  "type": "Feature",
  "properties": {
    "iso:country":"US",
    "sg:address":"790 Penllyn Blue Bell Pike",
    "sg:city":"Blue Bell",
    "sg:classifiers":[
        {
            "category":"Professional",
            "subcategory":"Engineering",
            "type":"Services"
        }
    ],
    "sg:phone":"+1 215 793 4220",
    "sg:postcode":"19422",
    "sg:province":"PA",
    "sg:tags":[
        "engineer"
    ],
    "wof:name":"Motion Engineering Inc",
    "wof:placetype":"venue"
},
  "geometry": {"coordinates":[-75.263471,40.155997],"type":"Point"}
}