{
  "type": "Feature",
  "properties": {
    "iso:country":"US",
    "sg:address":"99 Water St",
    "sg:city":"Punxsutawney",
    "sg:classifiers":[
        {
            "category":"Retail",
            "subcategory":"Auto Repair",
            "type":"Services"
        }
    ],
    "sg:phone":"+1 814 938 2371",
    "sg:postcode":"15767",
    "sg:province":"PA",
    "sg:tags":[
        "glass",
        "replacement",
        "contractor"
    ],
    "wof:name":"Punxsutawney Glass Co",
    "wof:placetype":"venue"
},
  "geometry": {"coordinates":[-78.992581,40.942999],"type":"Point"}
}