{
  "type": "Feature",
  "properties": {
    "addr:full":"201 Pine St Berwick PA 18603",
    "addr:housenumber":"201",
    "addr:postcode":"18603",
    "addr:street":"Pine St",
    "iso:country":"US",
    "sg:address":"201 Pine St",
    "sg:city":"Berwick",
    "sg:classifiers":[
        {
            "category":"Government",
            "subcategory":"Office",
            "type":"Public Place"
        }
    ],
    "sg:phone":"+1 570 759 4504",
    "sg:postcode":"18603",
    "sg:province":"PA",
    "sg:tags":[
        "state",
        "security"
    ],
    "wof:name":"National Guard",
    "wof:placetype":"venue"
},
  "geometry": {"coordinates":[-76.232805,41.056768],"type":"Point"}
}