{
  "type": "Feature",
  "properties": {
    "iso:country":"US",
    "sg:address":"1128 Matamoras Rd",
    "sg:city":"Halifax",
    "sg:classifiers":[
        {
            "category":"Farming",
            "subcategory":"Farm & Veterinary Services",
            "type":"Manufacturing & Wholesale Goods"
        }
    ],
    "sg:phone":"+1   ",
    "sg:postcode":"17032",
    "sg:province":"PA",
    "sg:tags":[
        "crop",
        "harvesting"
    ],
    "wof:name":"W Warfel",
    "wof:placetype":"venue"
},
  "geometry": {"coordinates":[-76.877861,40.449375],"type":"Point"}
}