{
  "type": "Feature",
  "properties": {
    "iso:country":"US",
    "sg:address":"50 Hudson Ave",
    "sg:city":"Lewistown",
    "sg:classifiers":[
        {
            "category":"Organizations",
            "subcategory":"Religious Organization",
            "type":"Services"
        }
    ],
    "sg:phone":"+1   ",
    "sg:postcode":"17044",
    "sg:province":"PA",
    "wof:name":"Christian Mssnary Alnce Church",
    "wof:placetype":"venue"
},
  "geometry": {"coordinates":[-77.57869599999999,40.587179],"type":"Point"}
}