{
  "type": "Feature",
  "properties": {
    "addr:full":"931 Hoffnagle St Philadelphia PA 19111",
    "addr:housenumber":"931",
    "addr:postcode":"19111",
    "addr:street":"Hoffnagle St",
    "iso:country":"US",
    "sg:address":"931 Hoffnagle St",
    "sg:city":"Philadelphia",
    "sg:classifiers":[
        {
            "category":"Wholesale",
            "subcategory":"Electrical",
            "type":"Manufacturing & Wholesale Goods"
        }
    ],
    "sg:phone":"+1 215 722 6649",
    "sg:postcode":"19111",
    "sg:province":"PA",
    "sg:tags":[
        "alarm",
        "burglar",
        "system"
    ],
    "wof:name":"Haussmann's Lock Svc",
    "wof:placetype":"venue"
},
  "geometry": {"coordinates":[-75.07096799999999,40.075902],"type":"Point"}
}