{
  "type": "Feature",
  "properties": {
    "iso:country":"US",
    "sg:address":"400 Pike Rd",
    "sg:city":"Huntingdon Valley",
    "sg:classifiers":[
        {
            "category":"Professional",
            "subcategory":"Computer Services",
            "type":"Services"
        }
    ],
    "sg:phone":"+1   ",
    "sg:postcode":"19006",
    "sg:province":"PA",
    "sg:tags":[
        "design",
        "system",
        "programing",
        "custom"
    ],
    "wof:name":"A M S",
    "wof:placetype":"venue"
},
  "geometry": {"coordinates":[-75.021911,40.146649],"type":"Point"}
}