{
  "type": "Feature",
  "properties": {
    "addr:full":"1 E 9th St Chester PA 19013",
    "addr:housenumber":"1",
    "addr:postcode":"19013",
    "addr:street":"E 9Th St",
    "iso:country":"US",
    "sg:address":"1 E 9th St",
    "sg:city":"Chester",
    "sg:classifiers":[
        {
            "category":"Social Services",
            "type":"Services"
        }
    ],
    "sg:phone":"+1 610 876 4474",
    "sg:postcode":"19013",
    "sg:province":"PA",
    "sg:tags":[
        "organization",
        "welfare"
    ],
    "wof:name":"New Foundations",
    "wof:placetype":"venue"
},
  "geometry": {"coordinates":[-75.36264199999999,39.851922],"type":"Point"}
}