{
  "type": "Feature",
  "properties": {
    "iso:country":"US",
    "sg:address":"562 W Third St",
    "sg:city":"Bloomsburg",
    "sg:classifiers":[
        {
            "category":"Building & Trades",
            "subcategory":"Construction",
            "type":"Services"
        }
    ],
    "sg:phone":"+1   ",
    "sg:postcode":"17815",
    "sg:province":"PA",
    "sg:tags":[
        "contractor"
    ],
    "wof:name":"Ceilings Unlimited",
    "wof:placetype":"venue"
},
  "geometry": {"coordinates":[-76.464873,40.997713],"type":"Point"}
}