{
  "type": "Feature",
  "properties": {
    "iso:country":"US",
    "sg:address":"509 State Rte 29",
    "sg:city":"Tunkhannock",
    "sg:classifiers":[
        {
            "category":"Retail",
            "subcategory":"Auto Repair",
            "type":"Services"
        }
    ],
    "sg:phone":"+1 570 836 2300",
    "sg:postcode":"18657",
    "sg:province":"PA",
    "sg:tags":[
        "repairing",
        "automobile"
    ],
    "wof:name":"Tunkhannock Auto Mart",
    "wof:placetype":"venue"
},
  "geometry": {"coordinates":[-75.94927199999999,41.526816],"type":"Point"}
}