{
  "type": "Feature",
  "properties": {
    "addr:full":"725 Maple St Lebanon PA 17046",
    "addr:housenumber":"725",
    "addr:postcode":"17046",
    "addr:street":"Maple St",
    "iso:country":"US",
    "sg:address":"725 Maple St",
    "sg:city":"Lebanon",
    "sg:classifiers":[
        {
            "category":"Real Estate",
            "subcategory":"Real Estate Operator",
            "type":"Services"
        }
    ],
    "sg:phone":"+1   ",
    "sg:postcode":"17046",
    "sg:province":"PA",
    "sg:tags":[
        "building",
        "apartment"
    ],
    "wof:name":"Willow Terrace",
    "wof:placetype":"venue"
},
  "geometry": {"coordinates":[-76.42371900000001,40.350235],"type":"Point"}
}