{
  "type": "Feature",
  "properties": {
    "addr:full":"2005 Market St Fl 32 Philadelphia PA 19103",
    "addr:housenumber":"2005;32",
    "addr:postcode":"19103",
    "addr:street":"Market St Fl",
    "iso:country":"US",
    "sg:address":"2005 Market St Fl 32",
    "sg:city":"Philadelphia",
    "sg:classifiers":[
        {
            "category":"Insurance",
            "subcategory":"Hazard Insurance",
            "type":"Services"
        },
        {
            "category":"Professional",
            "subcategory":"Business Services",
            "type":"Services"
        },
        {
            "category":"Professional",
            "subcategory":"Computer Services",
            "type":"Services"
        }
    ],
    "sg:phone":"+1 215 569 8722",
    "sg:postcode":"19103",
    "sg:province":"PA",
    "sg:tags":[
        "coach",
        "network",
        "consultant",
        "system",
        "designer",
        "design"
    ],
    "sg:website":"http://www.alliance-consulting.com",
    "wof:name":"Alliance Consulting Group Associates Inc",
    "wof:placetype":"venue"
},
  "geometry": {"coordinates":[-75.17326199999999,39.95358],"type":"Point"}
}