{
  "type": "Feature",
  "properties": {
    "iso:country":"US",
    "sg:address":"2101 Cottman Ave",
    "sg:city":"Philadelphia",
    "sg:classifiers":[
        {
            "category":"Home & Garden",
            "subcategory":"Furniture",
            "type":"Retail Goods"
        }
    ],
    "sg:phone":"+1   ",
    "sg:postcode":"19149",
    "sg:province":"PA",
    "wof:name":"Seamans",
    "wof:placetype":"venue"
},
  "geometry": {"coordinates":[-75.06343699999999,40.049751],"type":"Point"}
}