{
  "type": "Feature",
  "properties": {
    "iso:country":"US",
    "sg:address":"427 Weaver Rd",
    "sg:city":"Strasburg",
    "sg:classifiers":[
        {
            "category":"Food & Beverages",
            "subcategory":"Bakery",
            "type":"Retail Goods"
        }
    ],
    "sg:phone":"+1   ",
    "sg:postcode":"17579",
    "sg:province":"PA",
    "wof:name":"Kenton Baker",
    "wof:placetype":"venue"
},
  "geometry": {"coordinates":[-76.160101,39.946722],"type":"Point"}
}