{
  "type": "Feature",
  "properties": {
    "iso:country":"US",
    "sg:address":"2200 State Rte 286",
    "sg:city":"Pittsburgh",
    "sg:classifiers":[
        {
            "category":"Organizations",
            "subcategory":"Community Association",
            "type":"Services"
        }
    ],
    "sg:phone":"+1   ",
    "sg:postcode":"15239",
    "sg:province":"PA",
    "sg:tags":[
        "member"
    ],
    "wof:name":"East Suburban YMCA Program",
    "wof:placetype":"venue"
},
  "geometry": {"coordinates":[-79.70529399999999,40.465729],"type":"Point"}
}