{
  "type": "Feature",
  "properties": {
    "iso:country":"US",
    "sg:address":"112 S Spruce St",
    "sg:city":"Lititz",
    "sg:classifiers":[
        {
            "category":"Manufacturing",
            "subcategory":"Printing",
            "type":"Manufacturing & Wholesale Goods"
        }
    ],
    "sg:phone":"+1 717 626 5800",
    "sg:postcode":"17543",
    "sg:province":"PA",
    "sg:tags":[
        "printer",
        "letterpress",
        "offset"
    ],
    "wof:name":"Robert C Miller Printing",
    "wof:placetype":"venue"
},
  "geometry": {"coordinates":[-76.308982,40.154979],"type":"Point"}
}