{
  "type": "Feature",
  "properties": {
    "addr:full":"1852 Salemville Rd New Enterprise PA 16664",
    "addr:housenumber":"1852",
    "addr:postcode":"16664",
    "addr:street":"Salemville Rd",
    "iso:country":"US",
    "sg:address":"1852 Salemville Rd",
    "sg:city":"New Enterprise",
    "sg:classifiers":[
        {
            "category":"Building & Trades",
            "subcategory":"Construction",
            "type":"Services"
        }
    ],
    "sg:phone":"+1   ",
    "sg:postcode":"16664",
    "sg:province":"PA",
    "sg:tags":[
        "hanging",
        "contractor"
    ],
    "wof:name":"Ebersole Enterprises",
    "wof:placetype":"venue"
},
  "geometry": {"coordinates":[-78.444563,40.160693],"type":"Point"}
}