{
  "type": "Feature",
  "properties": {
    "iso:country":"US",
    "sg:address":"795 Glen Rd",
    "sg:city":"Jenkintown",
    "sg:classifiers":[
        {
            "category":"Wholesale",
            "subcategory":"Sporting Goods",
            "type":"Manufacturing & Wholesale Goods"
        }
    ],
    "sg:phone":"+1   ",
    "sg:postcode":"19046",
    "sg:province":"PA",
    "sg:tags":[
        "par",
        "bicycle",
        "for",
        "agent",
        "importer",
        "distributor"
    ],
    "wof:name":"Cunnane Bicycle Company Inc",
    "wof:placetype":"venue"
},
  "geometry": {"coordinates":[-75.13035000000001,40.105349],"type":"Point"}
}