{
  "type": "Feature",
  "properties": {
    "iso:country":"US",
    "sg:address":"150 W Girard Ave",
    "sg:city":"Philadelphia",
    "sg:classifiers":[
        {
            "category":"Arts & Performance",
            "subcategory":"Theater",
            "type":"Entertainment"
        }
    ],
    "sg:phone":"+1   ",
    "sg:postcode":"19123",
    "sg:province":"PA",
    "sg:tags":[
        "theatrical"
    ],
    "wof:name":"Gospel Entertainment Productio",
    "wof:placetype":"venue"
},
  "geometry": {"coordinates":[-75.13776300000001,39.969167],"type":"Point"}
}