{
  "type": "Feature",
  "properties": {
    "iso:country":"US",
    "sg:address":"4339 Morgantown Rd",
    "sg:city":"Mohnton",
    "sg:classifiers":[
        {
            "category":"Shopping",
            "type":"Retail Goods"
        }
    ],
    "sg:phone":"+1 610 856 0741",
    "sg:postcode":"19540",
    "sg:province":"PA",
    "sg:tags":[
        "telephone",
        "cellular"
    ],
    "wof:name":"Verizon Wireless",
    "wof:placetype":"venue"
},
  "geometry": {"coordinates":[-75.90831900000001,40.217838],"type":"Point"}
}