{
  "type": "Feature",
  "properties": {
    "addr:full":"607 Arch St Williamsport PA 17701",
    "addr:housenumber":"607",
    "addr:postcode":"17701",
    "addr:street":"Arch St",
    "iso:country":"US",
    "sg:address":"607 Arch St",
    "sg:city":"Williamsport",
    "sg:classifiers":[
        {
            "category":"Bars & Pubs",
            "type":"Food & Drink"
        }
    ],
    "sg:phone":"+1 570 322 3801",
    "sg:postcode":"17701",
    "sg:province":"PA",
    "sg:tags":[
        "tavern",
        "drinking"
    ],
    "wof:name":"Fredericks' Tavern",
    "wof:placetype":"venue"
},
  "geometry": {"coordinates":[-77.05036200000001,41.235701],"type":"Point"}
}