{
  "type": "Feature",
  "properties": {
    "iso:country":"US",
    "sg:address":"155 Lonesome Ln",
    "sg:city":"Palmerton",
    "sg:classifiers":[
        {
            "category":"Professional",
            "subcategory":"Art Services",
            "type":"Services"
        }
    ],
    "sg:phone":"+1 610 751 9243",
    "sg:postcode":"18071",
    "sg:province":"PA",
    "sg:tags":[
        "designer",
        "display",
        "producer"
    ],
    "wof:name":"Premier Designs Jeweler",
    "wof:placetype":"venue"
},
  "geometry": {"coordinates":[-75.52279799999999,40.858647],"type":"Point"}
}