{
  "type": "Feature",
  "properties": {
    "iso:country":"US",
    "sg:address":"166 Valley Rd",
    "sg:city":"Schellsburg",
    "sg:classifiers":[
        {
            "category":"Local Transit",
            "type":"Transportation"
        }
    ],
    "sg:phone":"+1 814 733 4595",
    "sg:postcode":"15559",
    "sg:province":"PA",
    "sg:tags":[
        "ambulance"
    ],
    "wof:name":"Shawnee Valley Ambulance Svc",
    "wof:placetype":"venue"
},
  "geometry": {"coordinates":[-78.640676,40.055945],"type":"Point"}
}