{
  "type": "Feature",
  "properties": {
    "iso:country":"US",
    "sg:address":"66 Vermillion Way",
    "sg:city":"Levittown",
    "sg:classifiers":[
        {
            "category":"Building & Trades",
            "subcategory":"Construction",
            "type":"Services"
        }
    ],
    "sg:phone":"+1   ",
    "sg:postcode":"19054",
    "sg:province":"PA",
    "sg:tags":[
        "contractor"
    ],
    "wof:name":"Classic Pool Installers Inc",
    "wof:placetype":"venue"
},
  "geometry": {"coordinates":[-74.830988,40.184516],"type":"Point"}
}