{
  "type": "Feature",
  "properties": {
    "iso:country":"US",
    "sg:address":"4805 Lehigh Dr",
    "sg:city":"Walnutport",
    "sg:classifiers":[
        {
            "category":"Professional",
            "subcategory":"Art Services",
            "type":"Services"
        }
    ],
    "sg:phone":"+1 610 760 8146",
    "sg:postcode":"18088",
    "sg:province":"PA",
    "sg:tags":[
        "designer",
        "display",
        "producer"
    ],
    "wof:name":"Forever Friends Designs",
    "wof:placetype":"venue"
},
  "geometry": {"coordinates":[-75.58865400000001,40.774593],"type":"Point"}
}