{
  "type": "Feature",
  "properties": {
    "addr:full":"30 M Y Ln Morrisville PA 19067",
    "addr:housenumber":"30",
    "addr:postcode":"19067",
    "addr:street":"M Y Ln",
    "iso:country":"US",
    "sg:address":"30 M Y Ln",
    "sg:city":"Morrisville",
    "sg:classifiers":[
        {
            "category":"Manufacturing",
            "subcategory":"Lumber",
            "type":"Manufacturing & Wholesale Goods"
        }
    ],
    "sg:phone":"+1 215 295 8074",
    "sg:postcode":"19067",
    "sg:province":"PA",
    "sg:tags":[
        "lumber-wholesale"
    ],
    "wof:name":"Probuild Company",
    "wof:placetype":"venue"
},
  "geometry": {"coordinates":[-74.79114300000001,40.200804],"type":"Point"}
}