{
  "type": "Feature",
  "properties": {
    "iso:country":"US",
    "sg:address":"21 Chrisman Dr",
    "sg:city":"Elverson",
    "sg:classifiers":[
        {
            "category":"Professional",
            "subcategory":"Advertising",
            "type":"Services"
        }
    ],
    "sg:phone":"+1 610 286 7576",
    "sg:postcode":"19520",
    "sg:province":"PA",
    "sg:tags":[
        "counselor"
    ],
    "wof:name":"Lizard Graphics",
    "wof:placetype":"venue"
},
  "geometry": {"coordinates":[-75.774562,40.150996],"type":"Point"}
}