{
  "type": "Feature",
  "properties": {
    "iso:country":"US",
    "sg:address":"246 Allegheny Blvd",
    "sg:city":"Brookville",
    "sg:classifiers":[
        {
            "category":"Restaurant",
            "type":"Food & Drink"
        }
    ],
    "sg:phone":"+1 814 849 7588",
    "sg:postcode":"15825",
    "sg:province":"PA",
    "wof:name":"Country Market Restaurant",
    "wof:placetype":"venue"
},
  "geometry": {"coordinates":[-79.098204,41.174426],"type":"Point"}
}