{
  "type": "Feature",
  "properties": {
    "iso:country":"US",
    "sg:address":"361 Alexander Spring Rd",
    "sg:city":"Carlisle",
    "sg:classifiers":[
        {
            "category":"Health Services",
            "subcategory":"Hospital",
            "type":"Services"
        }
    ],
    "sg:phone":"+1 717 960 1683",
    "sg:postcode":"17015",
    "sg:province":"PA",
    "sg:website":"www.celtichealthcare.com",
    "wof:name":"Carlisle Regional Medical Center",
    "wof:placetype":"venue"
},
  "geometry": {"coordinates":[-77.223006,40.184633],"type":"Point"}
}