{
  "type": "Feature",
  "properties": {
    "iso:country":"US",
    "sg:address":"3378 Pruss Hill Rd",
    "sg:city":"Pottstown",
    "sg:classifiers":[
        {
            "category":"Military Area",
            "type":"Public Place"
        }
    ],
    "sg:phone":"+1 610 287 0266",
    "sg:postcode":"19464",
    "sg:province":"PA",
    "sg:tags":[
        "guns-manufacturers"
    ],
    "sg:website":"http://www.dinaarms.com",
    "wof:name":"Dina Arms Corp",
    "wof:placetype":"venue"
},
  "geometry": {"coordinates":[-75.559476,40.253819],"type":"Point"}
}