{
  "type": "Feature",
  "properties": {
    "addr:full":"1136 Oakridge Dr Johnstown PA 15904",
    "addr:housenumber":"1136",
    "addr:postcode":"15904",
    "addr:street":"Oakridge Dr",
    "iso:country":"US",
    "sg:address":"1136 Oakridge Dr",
    "sg:city":"Johnstown",
    "sg:phone":"+1   ",
    "sg:postcode":"15904",
    "sg:province":"PA",
    "sg:tags":[
        "farm",
        "field",
        "corn",
        "crop"
    ],
    "wof:name":"Wilson John",
    "wof:placetype":"venue"
},
  "geometry": {"coordinates":[-78.810911,40.296483],"type":"Point"}
}