{
  "type": "Feature",
  "properties": {
    "iso:country":"US",
    "sg:address":"75 Gunning Ln",
    "sg:city":"Downingtown",
    "sg:classifiers":[
        {
            "category":"Building & Trades",
            "subcategory":"Construction",
            "type":"Services"
        }
    ],
    "sg:phone":"+1   ",
    "sg:postcode":"19335",
    "sg:province":"PA",
    "sg:tags":[
        "excavation",
        "contractor"
    ],
    "wof:name":"Kempter Excavating Inc",
    "wof:placetype":"venue"
},
  "geometry": {"coordinates":[-75.68953399999999,40.027238],"type":"Point"}
}