{
  "type": "Feature",
  "properties": {
    "addr:full":"39 Hadley Rd Greenville PA 16125",
    "addr:housenumber":"39",
    "addr:postcode":"16125",
    "addr:street":"Hadley Rd",
    "iso:country":"US",
    "sg:address":"39 Hadley Rd",
    "sg:city":"Greenville",
    "sg:classifiers":[
        {
            "category":"Shopping",
            "type":"Retail Goods"
        }
    ],
    "sg:phone":"+1 724 588 4220",
    "sg:postcode":"16125",
    "sg:province":"PA",
    "sg:tags":[
        "wedding",
        "supply"
    ],
    "wof:name":"Special Occasions",
    "wof:placetype":"venue"
},
  "geometry": {"coordinates":[-80.361503,41.411977],"type":"Point"}
}