{
  "type": "Feature",
  "properties": {
    "iso:country":"US",
    "sg:address":"10981 Decatur Rd",
    "sg:city":"Philadelphia",
    "sg:classifiers":[
        {
            "category":"Manufacturing",
            "subcategory":"Furniture",
            "type":"Manufacturing & Wholesale Goods"
        },
        {
            "category":"Wholesale",
            "subcategory":"Metals & Minerals",
            "type":"Manufacturing & Wholesale Goods"
        }
    ],
    "sg:phone":"+1 215 632 0191",
    "sg:postcode":"19154",
    "sg:province":"PA",
    "sg:tags":[
        "aluminum"
    ],
    "sg:website":"www.all-luminum.com",
    "wof:name":"All-Aluminum Products Inc",
    "wof:placetype":"venue"
},
  "geometry": {"coordinates":[-74.99205600000001,40.091485],"type":"Point"}
}