{
  "type": "Feature",
  "properties": {
    "iso:country":"US",
    "sg:address":"451 W Chew St Ste 301",
    "sg:city":"Allentown",
    "sg:classifiers":[
        {
            "category":"Health Services",
            "subcategory":"Doctor",
            "type":"Services"
        }
    ],
    "sg:phone":"+1 610 439 1666",
    "sg:postcode":"18102",
    "sg:province":"PA",
    "sg:tags":[
        "surgeon",
        "cosmetic"
    ],
    "sg:website":"www.drguarino.com",
    "wof:name":"Guarino Edward F MD",
    "wof:placetype":"venue"
},
  "geometry": {"coordinates":[-75.469065,40.60773],"type":"Point"}
}