{
  "type": "Feature",
  "properties": {
    "iso:country":"US",
    "sg:address":"28388 Deckards Rd",
    "sg:city":"Cochranton",
    "sg:classifiers":[
        {
            "category":"Organizations",
            "subcategory":"Religious Organization",
            "type":"Services"
        }
    ],
    "sg:phone":"+1 814 425 7380",
    "sg:postcode":"16314",
    "sg:province":"PA",
    "sg:tags":[
        "church"
    ],
    "wof:name":"Deckards United Methodist Chr",
    "wof:placetype":"venue"
},
  "geometry": {"coordinates":[-79.974298,41.524879],"type":"Point"}
}