{
  "type": "Feature",
  "properties": {
    "addr:full":"758 S 9th St Philadelphia PA 19147",
    "addr:housenumber":"758",
    "addr:postcode":"19147",
    "addr:street":"S 9Th St",
    "iso:country":"US",
    "sg:address":"758 S 9th St",
    "sg:city":"Philadelphia",
    "sg:classifiers":[
        {
            "category":"Bakery",
            "type":"Food & Drink"
        }
    ],
    "sg:phone":"+1 215 922 0445",
    "sg:postcode":"19147",
    "sg:province":"PA",
    "wof:name":"Sarcone's",
    "wof:placetype":"venue"
},
  "geometry": {"coordinates":[-75.15770000000001,39.940102],"type":"Point"}
}