{
  "type": "Feature",
  "properties": {
    "iso:country":"US",
    "sg:address":"201 E Lancaster Ave",
    "sg:city":"Reading",
    "sg:classifiers":[
        {
            "category":"Autos & Motor Vehicles",
            "subcategory":"Auto Supplies",
            "type":"Retail Goods"
        }
    ],
    "sg:phone":"+1 610 478 8060",
    "sg:postcode":"19611",
    "sg:province":"PA",
    "sg:tags":[
        "automobile",
        "parts"
    ],
    "wof:name":"A & A Auto Parts",
    "wof:placetype":"venue"
},
  "geometry": {"coordinates":[-75.934331,40.321903],"type":"Point"}
}