{
  "type": "Feature",
  "properties": {
    "iso:country":"US",
    "sg:address":"140 Constitution Ave",
    "sg:city":"Jessup",
    "sg:classifiers":[
        {
            "category":"Shopping",
            "subcategory":"Pharmacy",
            "type":"Retail Goods"
        }
    ],
    "sg:phone":"+1 570 383 7311",
    "sg:postcode":"18434",
    "sg:province":"PA",
    "wof:name":"Family Pharmacy Of Jessup Inc",
    "wof:placetype":"venue"
},
  "geometry": {"coordinates":[-75.573412,41.476542],"type":"Point"}
}