{
  "type": "Feature",
  "properties": {
    "iso:country":"US",
    "sg:address":"142 Putnam St",
    "sg:city":"Pittsburgh",
    "sg:classifiers":[
        {
            "category":"Home & Garden",
            "subcategory":"Carpets & Floor Coverings",
            "type":"Retail Goods"
        }
    ],
    "sg:phone":"+1 412 361 3545",
    "sg:postcode":"15206",
    "sg:province":"PA",
    "sg:tags":[
        "sell",
        "to",
        "mat",
        "business",
        "rent"
    ],
    "sg:website":"www.millermats.com",
    "wof:name":"Miller Mats",
    "wof:placetype":"venue"
},
  "geometry": {"coordinates":[-79.912758,40.459158],"type":"Point"}
}