{
  "type": "Feature",
  "properties": {
    "addr:full":"700 W Dekalb Pike King Of Prussia PA 19406",
    "addr:housenumber":"700",
    "addr:postcode":"19406",
    "addr:street":"W Dekalb Pike",
    "iso:country":"US",
    "sg:address":"700 W Dekalb Pike",
    "sg:city":"King Of Prussia",
    "sg:classifiers":[
        {
            "category":"Restaurant",
            "type":"Food & Drink"
        }
    ],
    "sg:menulink":"http://www.allmenus.com/pa/upper-merion/19194-sullivans-steakhouse/menu/",
    "sg:phone":"+1 610 878 9025",
    "sg:postcode":"19406",
    "sg:province":"PA",
    "sg:tags":[
        "american",
        "steakhouse"
    ],
    "wof:name":"Sullivan's Steakhouse",
    "wof:placetype":"venue"
},
  "geometry": {"coordinates":[-75.386309,40.086514],"type":"Point"}
}