{
  "type": "Feature",
  "properties": {
    "iso:country":"US",
    "sg:address":"418 N George St",
    "sg:city":"Millersville",
    "sg:classifiers":[
        {
            "category":"Building & Trades",
            "subcategory":"Construction",
            "type":"Services"
        }
    ],
    "sg:phone":"+1   ",
    "sg:postcode":"17551",
    "sg:province":"PA",
    "sg:tags":[
        "i",
        "residential",
        "commercial",
        "exterior",
        "interior",
        "painting"
    ],
    "wof:name":"Wagner George B Pntg Papering",
    "wof:placetype":"venue"
},
  "geometry": {"coordinates":[-76.35736,40.005277],"type":"Point"}
}