{
  "type": "Feature",
  "properties": {
    "iso:country":"US",
    "sg:address":"468 Stoney Lonesome Rd",
    "sg:city":"Clarion",
    "sg:classifiers":[
        {
            "category":"Building & Trades",
            "subcategory":"Construction",
            "type":"Services"
        }
    ],
    "sg:phone":"+1 814 745 2557",
    "sg:postcode":"16214",
    "sg:province":"PA",
    "sg:tags":[
        "general",
        "contractor"
    ],
    "wof:name":"G & H General Contracting",
    "wof:placetype":"venue"
},
  "geometry": {"coordinates":[-79.389422,41.162212],"type":"Point"}
}