{
  "type": "Feature",
  "properties": {
    "addr:full":"1000 S Mountain Blvd Wilkes Barre PA 18707",
    "addr:housenumber":"1000",
    "addr:postcode":"18707",
    "addr:street":"S Mountain Blvd",
    "iso:country":"US",
    "sg:address":"1000 S Mountain Blvd",
    "sg:city":"Wilkes Barre",
    "sg:classifiers":[
        {
            "category":"Banks & Credit Unions",
            "subcategory":"Bank",
            "type":"Services"
        }
    ],
    "sg:phone":"+1   ",
    "sg:postcode":"18707",
    "sg:province":"PA",
    "sg:tags":[
        "federal"
    ],
    "wof:name":"Service 1st Federal Credit Un",
    "wof:placetype":"venue"
},
  "geometry": {"coordinates":[-75.93335399999999,41.095766],"type":"Point"}
}