{
  "type": "Feature",
  "properties": {
    "iso:country":"US",
    "sg:address":"4455 Edgemont St",
    "sg:city":"Philadelphia",
    "sg:classifiers":[
        {
            "category":"Building & Trades",
            "subcategory":"Construction",
            "type":"Services"
        }
    ],
    "sg:phone":"+1 215 533 1266",
    "sg:postcode":"19137",
    "sg:province":"PA",
    "sg:tags":[
        "contractor"
    ],
    "wof:name":"C R Mason General Contractors Inc",
    "wof:placetype":"venue"
},
  "geometry": {"coordinates":[-75.07315699999999,39.999354],"type":"Point"}
}