{
  "type": "Feature",
  "properties": {
    "iso:country":"US",
    "sg:address":"9907 Grandview Ave",
    "sg:city":"Pittsburgh",
    "sg:classifiers":[
        {
            "category":"Organizations",
            "subcategory":"Non-profit Organization",
            "type":"Services"
        }
    ],
    "sg:phone":"+1 412 243 3930",
    "sg:postcode":"15235",
    "sg:province":"PA",
    "sg:tags":[
        "fund",
        "counselor",
        "raising"
    ],
    "wof:name":"Race Nite Inc",
    "wof:placetype":"venue"
},
  "geometry": {"coordinates":[-79.857422,40.468314],"type":"Point"}
}