{
  "type": "Feature",
  "properties": {
    "addr:full":"2 Liberty Dr Bensalem PA 19020",
    "addr:housenumber":"2",
    "addr:postcode":"19020",
    "addr:street":"Liberty Dr",
    "iso:country":"US",
    "sg:address":"2 Liberty Dr",
    "sg:city":"Bensalem",
    "sg:classifiers":[
        {
            "category":"Building & Trades",
            "subcategory":"Construction",
            "type":"Services"
        }
    ],
    "sg:phone":"+1 215 639 0500",
    "sg:postcode":"19020",
    "sg:province":"PA",
    "sg:tags":[
        "contractor"
    ],
    "wof:name":"Villas At Chancellors Glen",
    "wof:placetype":"venue"
},
  "geometry": {"coordinates":[-74.908203,40.1278],"type":"Point"}
}