{
  "type": "Feature",
  "properties": {
    "addr:full":"500 Chesterbrook Blvd Chesterbrook PA 19087",
    "addr:housenumber":"500",
    "addr:postcode":"19087",
    "addr:street":"Chesterbrook Blvd",
    "iso:country":"US",
    "sg:address":"500 Chesterbrook Blvd",
    "sg:city":"Chesterbrook",
    "sg:classifiers":[
        {
            "category":"Insurance",
            "subcategory":"Insurance Agent",
            "type":"Services"
        },
        {
            "category":"Insurance",
            "subcategory":"Hazard Insurance",
            "type":"Services"
        },
        {
            "category":"Insurance",
            "subcategory":"Title Insurance",
            "type":"Services"
        },
        {
            "category":"Insurance",
            "subcategory":"Life Insurance",
            "type":"Services"
        }
    ],
    "sg:phone":"+1 610 296 9320",
    "sg:postcode":"19087",
    "sg:province":"PA",
    "sg:tags":[
        "business",
        "auto",
        "commercial",
        "homeowner",
        "motorcycle",
        "renter"
    ],
    "wof:name":"Allstate Insurance Company - Steven Trojanov",
    "wof:placetype":"venue"
},
  "geometry": {"coordinates":[-75.455292,40.075142],"type":"Point"}
}