{
  "type": "Feature",
  "properties": {
    "addr:full":"14331 Greenview Dr Greencastle PA 17225",
    "addr:housenumber":"14331",
    "addr:postcode":"17225",
    "addr:street":"Greenview Dr",
    "iso:country":"US",
    "sg:address":"14331 Greenview Dr",
    "sg:city":"Greencastle",
    "sg:classifiers":[
        {
            "category":"Social Services",
            "subcategory":"Adult Care",
            "type":"Services"
        }
    ],
    "sg:phone":"+1 717 597 4775",
    "sg:postcode":"17225",
    "sg:province":"PA",
    "sg:tags":[
        "residential",
        "aged",
        "homes-institutional"
    ],
    "wof:name":"Shank's Pch",
    "wof:placetype":"venue"
},
  "geometry": {"coordinates":[-77.72345799999999,39.742532],"type":"Point"}
}