{
  "type": "Feature",
  "properties": {
    "iso:country":"US",
    "sg:address":"1800 N 5th St",
    "sg:city":"Reading",
    "sg:classifiers":[
        {
            "category":"Food & Beverages",
            "subcategory":"Groceries & Convenience Stores",
            "type":"Retail Goods"
        }
    ],
    "sg:phone":"+1 610 372 6206",
    "sg:postcode":"19601",
    "sg:province":"PA",
    "wof:name":"Sidh Mart Inc",
    "wof:placetype":"venue"
},
  "geometry": {"coordinates":[-75.92717,40.36232],"type":"Point"}
}