{
  "type": "Feature",
  "properties": {
    "addr:full":"16589 McMath Ave Meadville PA 16335",
    "addr:housenumber":"16589",
    "addr:postcode":"16335",
    "addr:street":"Mcmath Ave",
    "iso:country":"US",
    "sg:address":"16589 McMath Ave",
    "sg:city":"Meadville",
    "sg:classifiers":[
        {
            "category":"Government",
            "subcategory":"Fire Station",
            "type":"Public Place"
        }
    ],
    "sg:phone":"+1   ",
    "sg:postcode":"16335",
    "sg:province":"PA",
    "sg:tags":[
        "protection"
    ],
    "wof:name":"Vernon Central Hose Co Inc",
    "wof:placetype":"venue"
},
  "geometry": {"coordinates":[-80.204748,41.616297],"type":"Point"}
}