{
  "type": "Feature",
  "properties": {
    "addr:full":"2541 S Broad St Philadelphia PA 19148",
    "addr:housenumber":"2541",
    "addr:postcode":"19148",
    "addr:street":"S Broad St",
    "iso:country":"US",
    "sg:address":"2541 S Broad St",
    "sg:city":"Philadelphia",
    "sg:classifiers":[
        {
            "category":"Professional",
            "subcategory":"Lawyer & Legal Services",
            "type":"Services"
        }
    ],
    "sg:phone":"+1 215 551 9099",
    "sg:postcode":"19148",
    "sg:province":"PA",
    "wof:name":"Starinieri Nicholas J Atty",
    "wof:placetype":"venue"
},
  "geometry": {"coordinates":[-75.17065100000001,39.918353],"type":"Point"}
}