{
  "type": "Feature",
  "properties": {
    "addr:full":"100 Lancaster Ave Reading PA 19611",
    "addr:housenumber":"100",
    "addr:postcode":"19611",
    "addr:street":"Lancaster Ave",
    "iso:country":"US",
    "sg:address":"100 Lancaster Ave",
    "sg:city":"Reading",
    "sg:phone":"+1 610 376 1888",
    "sg:postcode":"19611",
    "sg:province":"PA",
    "wof:name":"Queen City Family Restaurant",
    "wof:placetype":"venue"
},
  "geometry": {"coordinates":[-75.93373099999999,40.323738],"type":"Point"}
}