{
  "type": "Feature",
  "properties": {
    "addr:full":"219 Granite Run Dr Lancaster PA 17601",
    "addr:housenumber":"219",
    "addr:postcode":"17601",
    "addr:street":"Granite Run Dr",
    "iso:country":"US",
    "sg:address":"219 Granite Run Dr",
    "sg:city":"Lancaster",
    "sg:classifiers":[
        {
            "category":"Professional",
            "subcategory":"Employment Agencies",
            "type":"Services"
        }
    ],
    "sg:phone":"+1 717 519 3930",
    "sg:postcode":"17601",
    "sg:province":"PA",
    "sg:tags":[
        "opportunity"
    ],
    "wof:name":"Aerotek",
    "wof:placetype":"venue"
},
  "geometry": {"coordinates":[-76.33443,40.078017],"type":"Point"}
}