{
  "type": "Feature",
  "properties": {
    "addr:full":"439 Hepburn St Williamsport PA 17701",
    "addr:housenumber":"439",
    "addr:postcode":"17701",
    "addr:street":"Hepburn St",
    "iso:country":"US",
    "sg:address":"439 Hepburn St",
    "sg:city":"Williamsport",
    "sg:classifiers":[
        {
            "category":"Real Estate",
            "subcategory":"Surveying",
            "type":"Services"
        }
    ],
    "sg:phone":"+1   ",
    "sg:postcode":"17701",
    "sg:province":"PA",
    "wof:name":"U S Geog Survey Wrd",
    "wof:placetype":"venue"
},
  "geometry": {"coordinates":[-77.006975,41.241478],"type":"Point"}
}