{
  "type": "Feature",
  "properties": {
    "iso:country":"US",
    "sg:address":"89 S Main St",
    "sg:city":"Carbondale",
    "sg:classifiers":[
        {
            "category":"Retail",
            "subcategory":"Auto Repair",
            "type":"Services"
        }
    ],
    "sg:phone":"+1 570 282 9822",
    "sg:postcode":"18407",
    "sg:province":"PA",
    "sg:tags":[
        "repairing",
        "automobile"
    ],
    "wof:name":"Brennan's Garage",
    "wof:placetype":"venue"
},
  "geometry": {"coordinates":[-75.50312599999999,41.568866],"type":"Point"}
}