{
  "type": "Feature",
  "properties": {
    "iso:country":"US",
    "sg:address":"134 Miller Rd",
    "sg:city":"Mcknight",
    "sg:classifiers":[
        {
            "category":"Building & Trades",
            "subcategory":"Electrical",
            "type":"Services"
        }
    ],
    "sg:phone":"+1 412 766 6781",
    "sg:postcode":"15237",
    "sg:province":"PA",
    "sg:tags":[
        "industrial",
        "electrician",
        "contractors-commercial",
        "electric"
    ],
    "wof:name":"Robert E Ansell Electric",
    "wof:placetype":"venue"
},
  "geometry": {"coordinates":[-79.99216199999999,40.523087],"type":"Point"}
}