{
  "type": "Feature",
  "properties": {
    "iso:country":"US",
    "sg:address":"4114 W Ridge Rd",
    "sg:city":"Erie",
    "sg:classifiers":[
        {
            "category":"Retail",
            "subcategory":"Repair Shop",
            "type":"Services"
        }
    ],
    "sg:phone":"+1 814 833 9450",
    "sg:postcode":"16506",
    "sg:province":"PA",
    "sg:tags":[
        "upholsterer"
    ],
    "wof:name":"Acadia Upholstery & Fabric",
    "wof:placetype":"venue"
},
  "geometry": {"coordinates":[-80.16673299999999,42.078832],"type":"Point"}
}