{
  "type": "Feature",
  "properties": {
    "iso:country":"US",
    "sg:address":"2994 E State St",
    "sg:city":"Hermitage",
    "sg:classifiers":[
        {
            "category":"Wholesale",
            "subcategory":"Machinery & Supplies",
            "type":"Manufacturing & Wholesale Goods"
        }
    ],
    "sg:phone":"+1 724 347 0530",
    "sg:postcode":"16148",
    "sg:province":"PA",
    "sg:tags":[
        "salon",
        "beauty"
    ],
    "wof:name":"Barnum Beauty Supply",
    "wof:placetype":"venue"
},
  "geometry": {"coordinates":[-80.45483299999999,41.233301],"type":"Point"}
}