{
  "type": "Feature",
  "properties": {
    "iso:country":"US",
    "sg:address":"2632 Virginia Ln",
    "sg:city":"Jamison",
    "sg:classifiers":[
        {
            "category":"Health Services",
            "subcategory":"Clinic",
            "type":"Services"
        }
    ],
    "sg:phone":"+1 215 491 6920",
    "sg:postcode":"18929",
    "sg:province":"PA",
    "sg:tags":[
        "home",
        "care"
    ],
    "wof:name":"First Home Health Care Inc",
    "wof:placetype":"venue"
},
  "geometry": {"coordinates":[-75.083388,40.265491],"type":"Point"}
}