{
  "type": "Feature",
  "properties": {
    "iso:country":"US",
    "sg:address":"6200 Brooktree Rd Ste 105",
    "sg:city":"Wexford",
    "sg:classifiers":[
        {
            "category":"Professional",
            "subcategory":"Accounting & Tax Preparation",
            "type":"Services"
        },
        {
            "category":"Professional",
            "subcategory":"Management & Consulting",
            "type":"Services"
        },
        {
            "category":"Banks & Credit Unions",
            "subcategory":"Financial Services",
            "type":"Services"
        }
    ],
    "sg:phone":"+1 724 934 3122",
    "sg:postcode":"15090",
    "sg:province":"PA",
    "sg:tags":[
        "financing",
        "return",
        "accountants-certified",
        "preparation-business",
        "consultant",
        "planning",
        "public"
    ],
    "sg:website":"http://www.reliancefinancial.net",
    "wof:name":"Trauman, Mark Cpa Cfp",
    "wof:placetype":"venue"
},
  "geometry": {"coordinates":[-80.060741,40.614118],"type":"Point"}
}