{
  "type": "Feature",
  "properties": {
    "iso:country":"US",
    "sg:address":"1238 Callowhill St Ste 702",
    "sg:city":"Philadelphia",
    "sg:classifiers":[
        {
            "category":"Arts & Performance",
            "subcategory":"Arts Center",
            "type":"Entertainment"
        }
    ],
    "sg:phone":"+1 215 627 3374",
    "sg:postcode":"19123",
    "sg:province":"PA",
    "sg:tags":[
        "performing"
    ],
    "wof:name":"Convergence Dancers & Musicians",
    "wof:placetype":"venue"
},
  "geometry": {"coordinates":[-75.159599,39.960602],"type":"Point"}
}