{
  "type": "Feature",
  "properties": {
    "iso:country":"US",
    "sg:address":"7270 Decatur St",
    "sg:city":"New Tripoli",
    "sg:classifiers":[
        {
            "category":"Retail",
            "subcategory":"Auto Repair",
            "type":"Services"
        }
    ],
    "sg:phone":"+1   ",
    "sg:postcode":"18066",
    "sg:province":"PA",
    "sg:tags":[
        "automotive"
    ],
    "wof:name":"Lenharts Towing Rollback Svcs",
    "wof:placetype":"venue"
},
  "geometry": {"coordinates":[-75.757165,40.680485],"type":"Point"}
}