{
  "type": "Feature",
  "properties": {
    "addr:full":"223 Springdale Rd York PA 17403",
    "addr:housenumber":"223",
    "addr:postcode":"17403",
    "addr:street":"Springdale Rd",
    "iso:country":"US",
    "sg:address":"223 Springdale Rd",
    "sg:city":"York",
    "sg:classifiers":[
        {
            "category":"Autos & Motor Vehicles",
            "subcategory":"Auto Supplies",
            "type":"Retail Goods"
        }
    ],
    "sg:phone":"+1 717 845 4749",
    "sg:postcode":"17403",
    "sg:province":"PA",
    "sg:tags":[
        "equipment",
        "racing",
        "car",
        "automobile"
    ],
    "wof:name":"Heagy Auto Upholstery",
    "wof:placetype":"venue"
},
  "geometry": {"coordinates":[-76.71485,39.950881],"type":"Point"}
}