{
  "type": "Feature",
  "properties": {
    "iso:country":"US",
    "sg:address":"1022 Philadelphia St",
    "sg:city":"Indiana",
    "sg:classifiers":[
        {
            "category":"Personal",
            "subcategory":"Beauty Salon",
            "type":"Services"
        }
    ],
    "sg:phone":"+1   ",
    "sg:postcode":"15701",
    "sg:province":"PA",
    "sg:tags":[
        "shop"
    ],
    "wof:name":"PHD Salon",
    "wof:placetype":"venue"
},
  "geometry": {"coordinates":[-79.159209,40.622948],"type":"Point"}
}