{
  "type": "Feature",
  "properties": {
    "iso:country":"US",
    "sg:address":"3063 Freeport Rd",
    "sg:city":"Natrona Heights",
    "sg:classifiers":[
        {
            "category":"Health Services",
            "subcategory":"Doctor",
            "type":"Services"
        },
        {
            "category":"Health Services",
            "subcategory":"Medical Lab",
            "type":"Services"
        }
    ],
    "sg:phone":"+1 724 224 4220",
    "sg:postcode":"15065",
    "sg:province":"PA",
    "sg:tags":[
        "laboratory",
        "surgeon",
        "physician"
    ],
    "wof:name":"Oncology & Hematology Assoc",
    "wof:placetype":"venue"
},
  "geometry": {"coordinates":[-79.71060199999999,40.642242],"type":"Point"}
}