{
  "type": "Feature",
  "properties": {
    "iso:country":"US",
    "sg:address":"1520 Monterey St",
    "sg:city":"Pittsburgh",
    "sg:classifiers":[
        {
            "category":"Professional",
            "type":"Services"
        }
    ],
    "sg:phone":"+1 412 321 8869",
    "sg:postcode":"15212",
    "sg:province":"PA",
    "sg:tags":[
        "caterer"
    ],
    "sg:website":"www.allingoodtasteproductions.com",
    "wof:name":"All In Good Taste Productions",
    "wof:placetype":"venue"
},
  "geometry": {"coordinates":[-80.013457,40.457796],"type":"Point"}
}