{
  "type": "Feature",
  "properties": {
    "iso:country":"US",
    "sg:address":"31 W 4th St",
    "sg:city":"Williamsport",
    "sg:classifiers":[
        {
            "category":"Shopping",
            "subcategory":"Clothing, Apparel, & Fashions",
            "type":"Retail Goods"
        }
    ],
    "sg:phone":"+1 570 322 6414",
    "sg:postcode":"17701",
    "sg:province":"PA",
    "sg:tags":[
        "tailor"
    ],
    "wof:name":"Alterations Dun-Right",
    "wof:placetype":"venue"
},
  "geometry": {"coordinates":[-77.00304800000001,41.24171],"type":"Point"}
}