{
  "type": "Feature",
  "properties": {
    "addr:full":"1792 Pine Hollow Rd Mc Kees Rocks PA 15136",
    "addr:housenumber":"1792",
    "addr:postcode":"15136",
    "addr:street":"Pine Hollow Rd;Kees Rocks",
    "iso:country":"US",
    "sg:address":"1792 Pine Hollow Rd",
    "sg:city":"Mc Kees Rocks",
    "sg:classifiers":[
        {
            "category":"Autos & Motor Vehicles",
            "subcategory":"Auto Supplies",
            "type":"Retail Goods"
        },
        {
            "category":"Retail",
            "subcategory":"Auto Repair",
            "type":"Services"
        }
    ],
    "sg:phone":"+1 412 771 0124",
    "sg:postcode":"15136",
    "sg:province":"PA",
    "sg:tags":[
        "tire"
    ],
    "wof:name":"Brutt's Tire & Auto Center Inc",
    "wof:placetype":"venue"
},
  "geometry": {"coordinates":[-80.10169999999999,40.477001],"type":"Point"}
}