{
  "type": "Feature",
  "properties": {
    "iso:country":"US",
    "sg:address":"1140 Washington Ave",
    "sg:city":"Lansdale",
    "sg:classifiers":[
        {
            "category":"Wholesale",
            "subcategory":"Machinery & Supplies",
            "type":"Manufacturing & Wholesale Goods"
        }
    ],
    "sg:phone":"+1 215 362 5742",
    "sg:postcode":"19446",
    "sg:province":"PA",
    "sg:tags":[
        "equipment",
        "system",
        "vacuum"
    ],
    "wof:name":"Jenlyn Associates",
    "wof:placetype":"venue"
},
  "geometry": {"coordinates":[-75.309224,40.242795],"type":"Point"}
}