{
  "type": "Feature",
  "properties": {
    "iso:country":"US",
    "sg:address":"4635 Umbria St",
    "sg:city":"Philadelphia",
    "sg:classifiers":[
        {
            "category":"Personal",
            "subcategory":"Beauty Salon",
            "type":"Services"
        }
    ],
    "sg:phone":"+1 215 460 4635",
    "sg:postcode":"19127",
    "sg:province":"PA",
    "sg:tags":[
        "shop"
    ],
    "wof:name":"V Salon",
    "wof:placetype":"venue"
},
  "geometry": {"coordinates":[-75.23030799999999,40.030892],"type":"Point"}
}