{
  "type": "Feature",
  "properties": {
    "iso:country":"US",
    "sg:address":"120 Felton Ave",
    "sg:city":"Darby",
    "sg:classifiers":[
        {
            "category":"Shopping",
            "subcategory":"Clothing, Apparel, & Fashions",
            "type":"Retail Goods"
        }
    ],
    "sg:phone":"+1   ",
    "sg:postcode":"19023",
    "sg:province":"PA",
    "sg:tags":[
        "wear"
    ],
    "wof:name":"Rock-A-Bye Baby",
    "wof:placetype":"venue"
},
  "geometry": {"coordinates":[-75.274624,39.912694],"type":"Point"}
}