{
  "type": "Feature",
  "properties": {
    "iso:country":"US",
    "sg:address":"1500 E Erie Ave",
    "sg:city":"Philadelphia",
    "sg:classifiers":[
        {
            "category":"Restaurant",
            "type":"Food & Drink"
        }
    ],
    "sg:phone":"+1 215 535 1500",
    "sg:postcode":"19124",
    "sg:province":"PA",
    "wof:name":"Buona Cera",
    "wof:placetype":"venue"
},
  "geometry": {"coordinates":[-75.09703399999999,40.005832],"type":"Point"}
}