{
  "type": "Feature",
  "properties": {
    "iso:country":"US",
    "sg:address":"23 E 2nd St",
    "sg:city":"Lansdale",
    "sg:classifiers":[
        {
            "category":"Professional",
            "subcategory":"Art Services",
            "type":"Services"
        }
    ],
    "sg:phone":"+1 267 421 5623",
    "sg:postcode":"19446",
    "sg:province":"PA",
    "sg:tags":[
        "designer",
        "display",
        "producer"
    ],
    "wof:name":"Premier Designs",
    "wof:placetype":"venue"
},
  "geometry": {"coordinates":[-75.282811,40.241773],"type":"Point"}
}