{
  "type": "Feature",
  "properties": {
    "addr:full":"511 E Main St Carnegie PA 15106",
    "addr:housenumber":"511",
    "addr:postcode":"15106",
    "addr:street":"E Main St",
    "iso:country":"US",
    "sg:address":"511 E Main St",
    "sg:city":"Carnegie",
    "sg:classifiers":[
        {
            "category":"Shopping",
            "subcategory":"Computers & Home Electronics",
            "type":"Retail Goods"
        }
    ],
    "sg:phone":"+1 412 279 5611",
    "sg:postcode":"15106",
    "sg:province":"PA",
    "wof:name":"Custom Audio Works Inc",
    "wof:placetype":"venue"
},
  "geometry": {"coordinates":[-80.09079699999999,40.404202],"type":"Point"}
}