{
  "type": "Feature",
  "properties": {
    "addr:full":"1810 Sanderson Ave Scranton PA 18509",
    "addr:housenumber":"1810",
    "addr:postcode":"18509",
    "addr:street":"Sanderson Ave",
    "iso:country":"US",
    "sg:address":"1810 Sanderson Ave",
    "sg:city":"Scranton",
    "sg:classifiers":[
        {
            "category":"Retail",
            "subcategory":"Funeral Services",
            "type":"Services"
        }
    ],
    "sg:phone":"+1 570 343 0712",
    "sg:postcode":"18509",
    "sg:province":"PA",
    "sg:tags":[
        "home"
    ],
    "sg:website":"www.snowdonfuneralhomes.com",
    "wof:name":"Snowdon Funeral Directors",
    "wof:placetype":"venue"
},
  "geometry": {"coordinates":[-75.648006,41.433025],"type":"Point"}
}