{
  "type": "Feature",
  "properties": {
    "addr:full":"262 Roundhouse Rd Lewistown PA 17044",
    "addr:housenumber":"262",
    "addr:postcode":"17044",
    "addr:street":"Roundhouse Rd",
    "iso:country":"US",
    "sg:address":"262 Roundhouse Rd",
    "sg:city":"Lewistown",
    "sg:classifiers":[
        {
            "category":"Manufacturing",
            "subcategory":"Tools & Machinery",
            "type":"Manufacturing & Wholesale Goods"
        }
    ],
    "sg:phone":"+1 717 242 0101",
    "sg:postcode":"17044",
    "sg:province":"PA",
    "sg:tags":[
        "machine",
        "industrial",
        "mfg"
    ],
    "wof:name":"Freedom Components Inc",
    "wof:placetype":"venue"
},
  "geometry": {"coordinates":[-77.58848999999999,40.577888],"type":"Point"}
}