{
  "type": "Feature",
  "properties": {
    "addr:full":"2062 Lycoming Creek Rd Williamsport PA 17701",
    "addr:housenumber":"2062",
    "addr:postcode":"17701",
    "addr:street":"Lycoming Creek Rd",
    "iso:country":"US",
    "sg:address":"2062 Lycoming Creek Rd",
    "sg:city":"Williamsport",
    "sg:classifiers":[
        {
            "category":"Banks & Credit Unions",
            "subcategory":"Investment Brokerage",
            "type":"Services"
        }
    ],
    "sg:phone":"+1 570 321 8711",
    "sg:postcode":"17701",
    "sg:province":"PA",
    "sg:tags":[
        "tape",
        "video",
        "sale",
        "dvds-rental"
    ],
    "wof:name":"Movie Gallery",
    "wof:placetype":"venue"
},
  "geometry": {"coordinates":[-77.04405199999999,41.261028],"type":"Point"}
}