{
  "type": "Feature",
  "properties": {
    "iso:country":"US",
    "sg:address":"5360 Lincoln Hwy",
    "sg:city":"Gap",
    "sg:classifiers":[
        {
            "category":"Personal",
            "subcategory":"Beauty Salon",
            "type":"Services"
        }
    ],
    "sg:phone":"+1   ",
    "sg:postcode":"17527",
    "sg:province":"PA",
    "sg:tags":[
        "hair"
    ],
    "wof:name":"Creative Hairdressers",
    "wof:placetype":"venue"
},
  "geometry": {"coordinates":[-76.01604500000001,39.991269],"type":"Point"}
}