{
  "type": "Feature",
  "properties": {
    "iso:country":"US",
    "sg:address":"602 McGrann Blvd",
    "sg:city":"Lancaster",
    "sg:classifiers":[
        {
            "category":"Personal",
            "subcategory":"Beauty Salon",
            "type":"Services"
        }
    ],
    "sg:phone":"+1 717 291 0499",
    "sg:postcode":"17601",
    "sg:province":"PA",
    "sg:tags":[
        "shop"
    ],
    "wof:name":"Prime Cut",
    "wof:placetype":"venue"
},
  "geometry": {"coordinates":[-76.28790100000001,40.054979],"type":"Point"}
}