{
  "type": "Feature",
  "properties": {
    "addr:full":"531 Bower Hill Rd Venetia PA 15367",
    "addr:housenumber":"531",
    "addr:postcode":"15367",
    "addr:street":"Bower Hill Rd",
    "iso:country":"US",
    "sg:address":"531 Bower Hill Rd",
    "sg:city":"Venetia",
    "sg:classifiers":[
        {
            "category":"Shopping",
            "subcategory":"Florist",
            "type":"Retail Goods"
        }
    ],
    "sg:phone":"+1   ",
    "sg:postcode":"15367",
    "sg:province":"PA",
    "wof:name":"Mary Scheitzer",
    "wof:placetype":"venue"
},
  "geometry": {"coordinates":[-80.06687599999999,40.264708],"type":"Point"}
}