{
  "type": "Feature",
  "properties": {
    "iso:country":"US",
    "sg:address":"835 E Lawrence Ave",
    "sg:city":"Ellwood City",
    "sg:classifiers":[
        {
            "category":"Manufacturing",
            "subcategory":"Printing",
            "type":"Manufacturing & Wholesale Goods"
        }
    ],
    "sg:phone":"+1 724 758 5573",
    "sg:postcode":"16117",
    "sg:province":"PA",
    "sg:tags":[
        "newspaper"
    ],
    "sg:website":"www.ellwoodcityledger.com",
    "wof:name":"Citizens Publishing & Printing",
    "wof:placetype":"venue"
},
  "geometry": {"coordinates":[-80.29266699999999,40.858343],"type":"Point"}
}