{
  "type": "Feature",
  "properties": {
    "addr:full":"1500 Boyce Rd Pittsburgh PA 15241",
    "addr:housenumber":"1500",
    "addr:postcode":"15241",
    "addr:street":"Boyce Rd",
    "iso:country":"US",
    "sg:address":"1500 Boyce Rd",
    "sg:city":"Pittsburgh",
    "sg:classifiers":[
        {
            "category":"Education",
            "subcategory":"School",
            "type":"Public Place"
        }
    ],
    "sg:phone":"+1 412 854 3043",
    "sg:postcode":"15241",
    "sg:province":"PA",
    "wof:name":"Boyce Middle School",
    "wof:placetype":"venue"
},
  "geometry": {"coordinates":[-80.09302,40.315526],"type":"Point"}
}