{
  "type": "Feature",
  "properties": {
    "addr:full":"3111 W Allegheny Ave Philadelphia PA 19132",
    "addr:housenumber":"3111",
    "addr:postcode":"19132",
    "addr:street":"W Allegheny Ave",
    "iso:country":"US",
    "sg:address":"3111 W Allegheny Ave",
    "sg:city":"Philadelphia",
    "sg:classifiers":[
        {
            "category":"Autos & Motor Vehicles",
            "subcategory":"Auto Supplies",
            "type":"Retail Goods"
        }
    ],
    "sg:phone":"+1 704 344 0597",
    "sg:postcode":"19132",
    "sg:province":"PA",
    "sg:tags":[
        "automotive",
        "part",
        "tire",
        "maintenance",
        "accessory"
    ],
    "wof:name":"Pep Boys",
    "wof:placetype":"venue"
},
  "geometry": {"coordinates":[-75.180603,40.005001],"type":"Point"}
}