{
  "type": "Feature",
  "properties": {
    "iso:country":"US",
    "sg:address":"1572 Main St",
    "sg:city":"Olyphant",
    "sg:classifiers":[
        {
            "category":"Shopping",
            "subcategory":"Optical Goods",
            "type":"Retail Goods"
        }
    ],
    "sg:phone":"+1 570 489 9500",
    "sg:postcode":"18519",
    "sg:province":"PA",
    "wof:name":"Crystal Vision Ctr Inc",
    "wof:placetype":"venue"
},
  "geometry": {"coordinates":[-75.613837,41.467319],"type":"Point"}
}