{
  "type": "Feature",
  "properties": {
    "iso:country":"US",
    "sg:address":"1272 E Earl Rd",
    "sg:city":"East Earl",
    "sg:classifiers":[
        {
            "category":"Farming",
            "subcategory":"Poultry Farm",
            "type":"Manufacturing & Wholesale Goods"
        }
    ],
    "sg:phone":"+1   ",
    "sg:postcode":"17519",
    "sg:province":"PA",
    "sg:tags":[
        "hatchery"
    ],
    "wof:name":"Harvey Z Martin",
    "wof:placetype":"venue"
},
  "geometry": {"coordinates":[-76.031584,40.11258],"type":"Point"}
}