{
  "type": "Feature",
  "properties": {
    "addr:full":"251 Vance Dr Burgettstown PA 15021",
    "addr:housenumber":"251",
    "addr:postcode":"15021",
    "addr:street":"Vance Dr",
    "iso:country":"US",
    "sg:address":"251 Vance Dr",
    "sg:city":"Burgettstown",
    "sg:classifiers":[
        {
            "category":"Professional",
            "subcategory":"Business Services",
            "type":"Services"
        }
    ],
    "sg:phone":"+1   ",
    "sg:postcode":"15021",
    "sg:province":"PA",
    "sg:tags":[
        "consulting"
    ],
    "wof:name":"C & S",
    "wof:placetype":"venue"
},
  "geometry": {"coordinates":[-80.40700200000001,40.354725],"type":"Point"}
}