{
  "type": "Feature",
  "properties": {
    "iso:country":"US",
    "sg:address":"64 Almost Country Rd",
    "sg:city":"Cogan Station",
    "sg:classifiers":[
        {
            "category":"Recreation",
            "type":"Entertainment"
        }
    ],
    "sg:phone":"+1   ",
    "sg:postcode":"17728",
    "sg:province":"PA",
    "wof:name":"Wintop Morgans",
    "wof:placetype":"venue"
},
  "geometry": {"coordinates":[-77.089643,41.289059],"type":"Point"}
}