{
  "type": "Feature",
  "properties": {
    "iso:country":"US",
    "sg:address":"2094 E Scenic Dr",
    "sg:city":"Bath",
    "sg:classifiers":[
        {
            "category":"Building & Trades",
            "subcategory":"Construction",
            "type":"Services"
        }
    ],
    "sg:phone":"+1   ",
    "sg:postcode":"18014",
    "sg:province":"PA",
    "sg:tags":[
        "special",
        "contractor"
    ],
    "wof:name":"J A Wright Masonry",
    "wof:placetype":"venue"
},
  "geometry": {"coordinates":[-75.369274,40.800412],"type":"Point"}
}