{
  "type": "Feature",
  "properties": {
    "iso:country":"US",
    "sg:address":"178 Concord St",
    "sg:city":"Union City",
    "sg:classifiers":[
        {
            "category":"Utilities",
            "subcategory":"Natural Gas",
            "type":"Services"
        }
    ],
    "sg:phone":"+1   ",
    "sg:postcode":"16438",
    "sg:province":"PA",
    "sg:tags":[
        "transmission"
    ],
    "wof:name":"Norse Pipeline LLC",
    "wof:placetype":"venue"
},
  "geometry": {"coordinates":[-79.83672799999999,41.891324],"type":"Point"}
}