{
  "type": "Feature",
  "properties": {
    "addr:full":"2555 N 5th St Philadelphia PA 19133",
    "addr:housenumber":"2555",
    "addr:postcode":"19133",
    "addr:street":"N 5Th St",
    "iso:country":"US",
    "sg:address":"2555 N 5th St",
    "sg:city":"Philadelphia",
    "sg:classifiers":[
        {
            "category":"Organizations",
            "subcategory":"Religious Organization",
            "type":"Services"
        }
    ],
    "sg:phone":"+1 215 203 7227",
    "sg:postcode":"19133",
    "sg:province":"PA",
    "sg:tags":[
        "church"
    ],
    "wof:name":"Segunda Iglesia Nueva Jrslm",
    "wof:placetype":"venue"
},
  "geometry": {"coordinates":[-75.140603,39.98966],"type":"Point"}
}