{
  "type": "Feature",
  "properties": {
    "iso:country":"US",
    "sg:address":"435 N 2nd St",
    "sg:city":"Lemoyne",
    "sg:classifiers":[
        {
            "category":"Professional",
            "type":"Services"
        }
    ],
    "sg:phone":"+1   ",
    "sg:postcode":"17043",
    "sg:province":"PA",
    "wof:name":"Wendy Baldwin",
    "wof:placetype":"venue"
},
  "geometry": {"coordinates":[-76.905018,40.258962],"type":"Point"}
}