{
  "type": "Feature",
  "properties": {
    "iso:country":"US",
    "sg:address":"4 W Penn Ave",
    "sg:city":"Reading",
    "sg:classifiers":[
        {
            "category":"Health Services",
            "subcategory":"Hospital",
            "type":"Services"
        }
    ],
    "sg:phone":"+1   ",
    "sg:postcode":"19608",
    "sg:province":"PA",
    "sg:tags":[
        "general"
    ],
    "wof:name":"Catholic Health Initiatives",
    "wof:placetype":"venue"
},
  "geometry": {"coordinates":[-76.00842299999999,40.32554],"type":"Point"}
}