{
  "type": "Feature",
  "properties": {
    "iso:country":"US",
    "sg:address":"8090 Mcgill Rd",
    "sg:city":"Harborcreek",
    "sg:classifiers":[
        {
            "category":"Real Estate",
            "subcategory":"Real Estate Services",
            "type":"Services"
        },
        {
            "category":"Building & Trades",
            "subcategory":"Cleaning & Sanitation",
            "type":"Services"
        }
    ],
    "sg:phone":"+1 814 898 1576",
    "sg:postcode":"16421",
    "sg:province":"PA",
    "sg:tags":[
        "maintenance",
        "cleaners-interior"
    ],
    "wof:name":"Smith's Maintenance & Tool Repairs",
    "wof:placetype":"venue"
},
  "geometry": {"coordinates":[-79.922907,42.150917],"type":"Point"}
}