{
  "type": "Feature",
  "properties": {
    "iso:country":"US",
    "sg:address":"2797 Leechburg Rd",
    "sg:city":"New Kensington",
    "sg:classifiers":[
        {
            "category":"Professional",
            "subcategory":"Lawyer & Legal Services",
            "type":"Services"
        }
    ],
    "sg:phone":"+1   ",
    "sg:postcode":"15068",
    "sg:province":"PA",
    "wof:name":"Edward T Rowe Jr",
    "wof:placetype":"venue"
},
  "geometry": {"coordinates":[-79.73205900000001,40.591889],"type":"Point"}
}