{
  "type": "Feature",
  "properties": {
    "addr:full":"33 Bear Dr Newfoundland PA 18445",
    "addr:housenumber":"33",
    "addr:postcode":"18445",
    "addr:street":"Bear Dr",
    "iso:country":"US",
    "sg:address":"33 Bear Dr",
    "sg:city":"Newfoundland",
    "sg:classifiers":[
        {
            "category":"Professional",
            "subcategory":"Accounting & Tax Preparation",
            "type":"Services"
        }
    ],
    "sg:phone":"+1   ",
    "sg:postcode":"18445",
    "sg:province":"PA",
    "wof:name":"Visions",
    "wof:placetype":"venue"
},
  "geometry": {"coordinates":[-75.40451899999999,41.287526],"type":"Point"}
}