{
  "type": "Feature",
  "properties": {
    "addr:full":"265 Circle Dr Red Lion PA 17356",
    "addr:housenumber":"265",
    "addr:postcode":"17356",
    "addr:street":"Circle Dr",
    "iso:country":"US",
    "sg:address":"265 Circle Dr",
    "sg:city":"Red Lion",
    "sg:classifiers":[
        {
            "category":"Organizations",
            "subcategory":"Religious Organization",
            "type":"Services"
        }
    ],
    "sg:phone":"+1   ",
    "sg:postcode":"17356",
    "sg:province":"PA",
    "wof:name":"Springvale Untd Methdst Church",
    "wof:placetype":"venue"
},
  "geometry": {"coordinates":[-76.582453,39.8923],"type":"Point"}
}