{
  "type": "Feature",
  "properties": {
    "addr:full":"9623 Oakview Rd Kempton PA 19529",
    "addr:housenumber":"9623",
    "addr:postcode":"19529",
    "addr:street":"Oakview Rd",
    "iso:country":"US",
    "sg:address":"9623 Oakview Rd",
    "sg:city":"Kempton",
    "sg:classifiers":[
        {
            "category":"Freight",
            "type":"Transportation"
        }
    ],
    "sg:phone":"+1   ",
    "sg:postcode":"19529",
    "sg:province":"PA",
    "sg:tags":[
        "operator",
        "trucking"
    ],
    "wof:name":"Richter Transport LLC",
    "wof:placetype":"venue"
},
  "geometry": {"coordinates":[-75.78837799999999,40.617233],"type":"Point"}
}