{
  "type": "Feature",
  "properties": {
    "iso:country":"US",
    "sg:address":"2312 Pitt Ave",
    "sg:city":"Johnstown",
    "sg:classifiers":[
        {
            "category":"Personal",
            "type":"Services"
        }
    ],
    "sg:phone":"+1   ",
    "sg:postcode":"15905",
    "sg:province":"PA",
    "wof:name":"Home Pet Care Services",
    "wof:placetype":"venue"
},
  "geometry": {"coordinates":[-78.967795,40.312366],"type":"Point"}
}