{
  "type": "Feature",
  "properties": {
    "iso:country":"US",
    "sg:address":"309 Camer Dr",
    "sg:city":"Bensalem",
    "sg:classifiers":[
        {
            "category":"Manufacturing",
            "subcategory":"Metals",
            "type":"Manufacturing & Wholesale Goods"
        },
        {
            "category":"Home & Garden",
            "subcategory":"Building Materials",
            "type":"Retail Goods"
        }
    ],
    "sg:phone":"+1 215 244 4090",
    "sg:postcode":"19020",
    "sg:province":"PA",
    "sg:tags":[
        "windows",
        "door",
        "storm",
        "mfg"
    ],
    "wof:name":"Karey Kassl Corp",
    "wof:placetype":"venue"
},
  "geometry": {"coordinates":[-74.937905,40.069648],"type":"Point"}
}