{
  "type": "Feature",
  "properties": {
    "iso:country":"US",
    "sg:address":"5920 Steubenville Pike",
    "sg:city":"Mc Kees Rocks",
    "sg:classifiers":[
        {
            "category":"Retail",
            "subcategory":"Laundry & Dry Cleaning",
            "type":"Services"
        }
    ],
    "sg:phone":"+1 412 490 6920",
    "sg:postcode":"15136",
    "sg:province":"PA",
    "wof:name":"Peng Laudromat",
    "wof:placetype":"venue"
},
  "geometry": {"coordinates":[-80.143894,40.445987],"type":"Point"}
}