{
  "type": "Feature",
  "properties": {
    "iso:country":"US",
    "sg:address":"104 N 7th St",
    "sg:city":"Lemoyne",
    "sg:classifiers":[
        {
            "category":"Banks & Credit Unions",
            "subcategory":"Investment Brokerage",
            "type":"Services"
        },
        {
            "category":"Insurance",
            "subcategory":"Hazard Insurance",
            "type":"Services"
        }
    ],
    "sg:phone":"+1 717 737 8673",
    "sg:postcode":"17043",
    "sg:province":"PA",
    "sg:tags":[
        "commercial",
        "agent",
        "business",
        "resume"
    ],
    "sg:website":"http://www.uiccayman.com",
    "wof:name":"United Insurance Company Of America",
    "wof:placetype":"venue"
},
  "geometry": {"coordinates":[-76.89969600000001,40.245228],"type":"Point"}
}