{
  "type": "Feature",
  "properties": {
    "iso:country":"US",
    "sg:address":"610 Pittsburgh Rd",
    "sg:city":"Uniontown",
    "sg:classifiers":[
        {
            "category":"Restaurant",
            "type":"Food & Drink"
        }
    ],
    "sg:phone":"+1 724 438 3340",
    "sg:postcode":"15401",
    "sg:province":"PA",
    "wof:name":"Subway Sandwiches & Salads",
    "wof:placetype":"venue"
},
  "geometry": {"coordinates":[-79.726235,39.920084],"type":"Point"}
}