{
  "type": "Feature",
  "properties": {
    "iso:country":"US",
    "sg:address":"47 N Main St",
    "sg:city":"Washington",
    "sg:classifiers":[
        {
            "category":"Wholesale",
            "subcategory":"Electrical",
            "type":"Manufacturing & Wholesale Goods"
        }
    ],
    "sg:phone":"+1 724 228 8488",
    "sg:postcode":"15301",
    "sg:province":"PA",
    "sg:tags":[
        "communication",
        "facsimile",
        "equipment"
    ],
    "wof:name":"Slagle's LP",
    "wof:placetype":"venue"
},
  "geometry": {"coordinates":[-80.24572000000001,40.171617],"type":"Point"}
}