{
  "type": "Feature",
  "properties": {
    "addr:full":"547 Adams Ave Philadelphia PA 19120",
    "addr:housenumber":"547",
    "addr:postcode":"19120",
    "addr:street":"Adams Ave",
    "iso:country":"US",
    "sg:address":"547 Adams Ave",
    "sg:city":"Philadelphia",
    "sg:classifiers":[
        {
            "category":"Banks & Credit Unions",
            "subcategory":"Bank",
            "type":"Services"
        }
    ],
    "sg:phone":"+1 215 342 8357",
    "sg:postcode":"19120",
    "sg:province":"PA",
    "sg:tags":[
        "cashing",
        "check"
    ],
    "wof:name":"Cash Today Inc",
    "wof:placetype":"venue"
},
  "geometry": {"coordinates":[-75.108683,40.036425],"type":"Point"}
}