{
  "type": "Feature",
  "properties": {
    "addr:full":"4665 Canterbury Ct Bensalem PA 19020",
    "addr:housenumber":"4665",
    "addr:postcode":"19020",
    "addr:street":"Canterbury Ct",
    "iso:country":"US",
    "sg:address":"4665 Canterbury Ct",
    "sg:city":"Bensalem",
    "sg:classifiers":[
        {
            "category":"Banks & Credit Unions",
            "subcategory":"Financial Services",
            "type":"Services"
        }
    ],
    "sg:phone":"+1 215 750 7534",
    "sg:postcode":"19020",
    "sg:province":"PA",
    "sg:tags":[
        "card-merchant",
        "card"
    ],
    "wof:name":"Enterprise Services",
    "wof:placetype":"venue"
},
  "geometry": {"coordinates":[-74.93575199999999,40.137852],"type":"Point"}
}