{
  "type": "Feature",
  "properties": {
    "iso:country":"US",
    "sg:address":"441 Sharon Ave",
    "sg:city":"Sharon Hill",
    "sg:classifiers":[
        {
            "category":"Building & Trades",
            "subcategory":"Construction",
            "type":"Services"
        }
    ],
    "sg:phone":"+1   ",
    "sg:postcode":"19079",
    "sg:province":"PA",
    "sg:tags":[
        "house"
    ],
    "wof:name":"Jim OConnor Contracting",
    "wof:placetype":"venue"
},
  "geometry": {"coordinates":[-75.270017,39.904027],"type":"Point"}
}