{
  "type": "Feature",
  "properties": {
    "iso:country":"US",
    "sg:address":"1533 3rd Ave",
    "sg:city":"New Brighton",
    "sg:classifiers":[
        {
            "category":"Real Estate",
            "subcategory":"Real Estate Operator",
            "type":"Services"
        }
    ],
    "sg:phone":"+1 724 846 3194",
    "sg:postcode":"15066",
    "sg:province":"PA",
    "sg:tags":[
        "apartment"
    ],
    "wof:name":"Brighton Court Apartments",
    "wof:placetype":"venue"
},
  "geometry": {"coordinates":[-80.307025,40.72658],"type":"Point"}
}