{
  "type": "Feature",
  "properties": {
    "iso:country":"US",
    "sg:address":"1440 W Walnut St Unit 3",
    "sg:city":"Allentown",
    "sg:classifiers":[
        {
            "category":"Deli",
            "type":"Food & Drink"
        },
        {
            "category":"Food & Beverages",
            "subcategory":"Bakery",
            "type":"Retail Goods"
        }
    ],
    "sg:phone":"+1 484 664 2900",
    "sg:postcode":"18102",
    "sg:province":"PA",
    "sg:tags":[
        "sandwich"
    ],
    "wof:name":"Allentown Deli",
    "wof:placetype":"venue"
},
  "geometry": {"coordinates":[-75.486699,40.596301],"type":"Point"}
}