{
  "type": "Feature",
  "properties": {
    "addr:full":"418 Radcliff Dr Pittsburgh PA 15235",
    "addr:housenumber":"418",
    "addr:postcode":"15235",
    "addr:street":"Radcliff Dr",
    "iso:country":"US",
    "sg:address":"418 Radcliff Dr",
    "sg:city":"Pittsburgh",
    "sg:classifiers":[
        {
            "category":"Health Services",
            "subcategory":"Dentist",
            "type":"Services"
        }
    ],
    "sg:phone":"+1 412 242 4736",
    "sg:postcode":"15235",
    "sg:province":"PA",
    "sg:tags":[
        "dentists-orthodontists"
    ],
    "wof:name":"Light Force America",
    "wof:placetype":"venue"
},
  "geometry": {"coordinates":[-79.821895,40.427464],"type":"Point"}
}