{
  "type": "Feature",
  "properties": {
    "iso:country":"US",
    "sg:address":"1735 Swamp Rd",
    "sg:city":"Furlong",
    "sg:classifiers":[
        {
            "category":"Building & Trades",
            "subcategory":"Landscaping Services",
            "type":"Services"
        }
    ],
    "sg:phone":"+1 215 794 8700",
    "sg:postcode":"18925",
    "sg:province":"PA",
    "sg:tags":[
        "landscape",
        "contractor"
    ],
    "wof:name":"Superior Turf & Landscape Inc",
    "wof:placetype":"venue"
},
  "geometry": {"coordinates":[-75.06618899999999,40.281084],"type":"Point"}
}