{
  "type": "Feature",
  "properties": {
    "iso:country":"US",
    "sg:address":"208 E Evergreen Rd",
    "sg:city":"Lebanon",
    "sg:classifiers":[
        {
            "category":"Sports & Exercise",
            "subcategory":"Race Track",
            "type":"Entertainment"
        }
    ],
    "sg:phone":"+1 717 376 0141",
    "sg:postcode":"17042",
    "sg:province":"PA",
    "wof:name":"Nasus Racing Technology",
    "wof:placetype":"venue"
},
  "geometry": {"coordinates":[-76.400642,40.310104],"type":"Point"}
}