{
  "type": "Feature",
  "properties": {
    "iso:country":"US",
    "sg:address":"1017 4th Ave",
    "sg:city":"Coraopolis",
    "sg:classifiers":[
        {
            "category":"Food & Beverages",
            "subcategory":"Groceries & Convenience Stores",
            "type":"Retail Goods"
        }
    ],
    "sg:phone":"+1   ",
    "sg:postcode":"15108",
    "sg:province":"PA",
    "wof:name":"Cash Market",
    "wof:placetype":"venue"
},
  "geometry": {"coordinates":[-80.16227000000001,40.517957],"type":"Point"}
}