{
  "type": "Feature",
  "properties": {
    "iso:country":"US",
    "sg:address":"2710 Kreider Rd",
    "sg:city":"Lititz",
    "sg:classifiers":[
        {
            "category":"Communications",
            "subcategory":"Film & Video Production",
            "type":"Services"
        }
    ],
    "sg:phone":"+1 717 569 4665",
    "sg:postcode":"17543",
    "sg:province":"PA",
    "sg:tags":[
        "taping"
    ],
    "sg:website":"www.jkmpro.com",
    "wof:name":"JKM Productions",
    "wof:placetype":"venue"
},
  "geometry": {"coordinates":[-76.323274,40.106922],"type":"Point"}
}