{
  "type": "Feature",
  "properties": {
    "iso:country":"US",
    "sg:address":"510 Mountain Laurel Plz",
    "sg:city":"Latrobe",
    "sg:classifiers":[
        {
            "category":"Restaurant",
            "type":"Food & Drink"
        }
    ],
    "sg:menulink":"http://www.allmenus.com/pa/unity/215052-taco-bell/menu/",
    "sg:phone":"+1 724 537 8390",
    "sg:postcode":"15650",
    "sg:province":"PA",
    "sg:tags":[
        "mexican"
    ],
    "wof:name":"Taco Bell",
    "wof:placetype":"venue"
},
  "geometry": {"coordinates":[-79.389889,40.283826],"type":"Point"}
}