{
  "type": "Feature",
  "properties": {
    "addr:full":"818 Pittsburgh St Springdale PA 15144",
    "addr:housenumber":"818",
    "addr:postcode":"15144",
    "addr:street":"Pittsburgh St",
    "iso:country":"US",
    "sg:address":"818 Pittsburgh St",
    "sg:city":"Springdale",
    "sg:classifiers":[
        {
            "category":"Manufacturing",
            "subcategory":"Signs",
            "type":"Manufacturing & Wholesale Goods"
        }
    ],
    "sg:phone":"+1 724 274 1900",
    "sg:postcode":"15144",
    "sg:province":"PA",
    "sg:tags":[
        "specialty",
        "mfg"
    ],
    "wof:name":"KAS Signs",
    "wof:placetype":"venue"
},
  "geometry": {"coordinates":[-79.778857,40.541304],"type":"Point"}
}