{
  "type": "Feature",
  "properties": {
    "iso:country":"US",
    "sg:address":"3226 Eastview Rd",
    "sg:city":"Bethel Park",
    "sg:classifiers":[
        {
            "category":"Professional",
            "subcategory":"Business Services",
            "type":"Services"
        }
    ],
    "sg:phone":"+1   ",
    "sg:postcode":"15102",
    "sg:province":"PA",
    "sg:tags":[
        "printing",
        "commercial",
        "broker"
    ],
    "wof:name":"Mizr Print Management Co LLC",
    "wof:placetype":"venue"
},
  "geometry": {"coordinates":[-80.053495,40.328299],"type":"Point"}
}