{
  "type": "Feature",
  "properties": {
    "iso:country":"US",
    "sg:address":"7600 Stenton Ave",
    "sg:city":"Philadelphia",
    "sg:classifiers":[
        {
            "category":"Travel",
            "subcategory":"Travel Agent",
            "type":"Entertainment"
        }
    ],
    "sg:phone":"+1   ",
    "sg:postcode":"19118",
    "sg:province":"PA",
    "sg:tags":[
        "operator",
        "tour"
    ],
    "wof:name":"Timothy Tours",
    "wof:placetype":"venue"
},
  "geometry": {"coordinates":[-75.190831,40.074114],"type":"Point"}
}