{
  "type": "Feature",
  "properties": {
    "iso:country":"US",
    "sg:address":"100 Woodside Dr",
    "sg:city":"Canonsburg",
    "sg:classifiers":[
        {
            "category":"Health Services",
            "subcategory":"Doctor",
            "type":"Services"
        }
    ],
    "sg:phone":"+1   ",
    "sg:postcode":"15317",
    "sg:province":"PA",
    "wof:name":"JAS S Elmore DMD",
    "wof:placetype":"venue"
},
  "geometry": {"coordinates":[-80.08903599999999,40.286809],"type":"Point"}
}