{
  "type": "Feature",
  "properties": {
    "iso:country":"US",
    "sg:address":"975 Mud Level Rd",
    "sg:city":"Shippensburg",
    "sg:classifiers":[
        {
            "category":"Farming",
            "subcategory":"Dairy Farm",
            "type":"Manufacturing & Wholesale Goods"
        }
    ],
    "sg:phone":"+1   ",
    "sg:postcode":"17257",
    "sg:province":"PA",
    "wof:name":"Ivan Wenger",
    "wof:placetype":"venue"
},
  "geometry": {"coordinates":[-77.514034,40.086239],"type":"Point"}
}