{
  "type": "Feature",
  "properties": {
    "iso:country":"US",
    "sg:address":"31 Garrett Rd",
    "sg:city":"Upper Darby",
    "sg:classifiers":[
        {
            "category":"Personal",
            "subcategory":"Beauty Salon",
            "type":"Services"
        }
    ],
    "sg:phone":"+1 610 713 9464",
    "sg:postcode":"19082",
    "sg:province":"PA",
    "sg:tags":[
        "nail",
        "manicuring"
    ],
    "wof:name":"Just For Nails",
    "wof:placetype":"venue"
},
  "geometry": {"coordinates":[-75.262001,39.960899],"type":"Point"}
}