{
  "type": "Feature",
  "properties": {
    "iso:country":"US",
    "sg:address":"175 Layton Rd",
    "sg:city":"Olyphant",
    "sg:classifiers":[
        {
            "category":"Retail",
            "subcategory":"Auto Repair",
            "type":"Services"
        }
    ],
    "sg:phone":"+1   ",
    "sg:postcode":"18411",
    "sg:province":"PA",
    "sg:tags":[
        "general"
    ],
    "wof:name":"Garage Service",
    "wof:placetype":"venue"
},
  "geometry": {"coordinates":[-75.679095,41.474015],"type":"Point"}
}