{
  "type": "Feature",
  "properties": {
    "iso:country":"US",
    "sg:address":"110 Old Kennett Rd",
    "sg:city":"Kennett Square",
    "sg:classifiers":[
        {
            "category":"Banks & Credit Unions",
            "subcategory":"Investment Brokerage",
            "type":"Services"
        }
    ],
    "sg:phone":"+1   ",
    "sg:postcode":"19348",
    "sg:province":"PA",
    "sg:tags":[
        "security"
    ],
    "wof:name":"Prudential",
    "wof:placetype":"venue"
},
  "geometry": {"coordinates":[-75.70217100000001,39.829827],"type":"Point"}
}