{
  "type": "Feature",
  "properties": {
    "addr:full":"1214 E Market St York PA 17403",
    "addr:housenumber":"1214",
    "addr:postcode":"17403",
    "addr:street":"E Market St",
    "iso:country":"US",
    "sg:address":"1214 E Market St",
    "sg:city":"York",
    "sg:classifiers":[
        {
            "category":"Home & Garden",
            "subcategory":"Carpets & Floor Coverings",
            "type":"Retail Goods"
        }
    ],
    "sg:phone":"+1 717 848 2879",
    "sg:postcode":"17403",
    "sg:province":"PA",
    "sg:tags":[
        "contractor"
    ],
    "wof:name":"D N Wolf Inc",
    "wof:placetype":"venue"
},
  "geometry": {"coordinates":[-76.703174,39.971841],"type":"Point"}
}