{
  "type": "Feature",
  "properties": {
    "addr:full":"18 Carlisle St Gettysburg PA 17325",
    "addr:housenumber":"18",
    "addr:postcode":"17325",
    "addr:street":"Carlisle St",
    "iso:country":"US",
    "sg:address":"18 Carlisle St",
    "sg:city":"Gettysburg",
    "sg:classifiers":[
        {
            "category":"Health Services",
            "subcategory":"Clinic",
            "type":"Services"
        }
    ],
    "sg:phone":"+1 717 337 0620",
    "sg:postcode":"17325",
    "sg:province":"PA",
    "sg:tags":[
        "home"
    ],
    "wof:name":"Visiting Angels",
    "wof:placetype":"venue"
},
  "geometry": {"coordinates":[-77.231099,39.831043],"type":"Point"}
}