{
  "type": "Feature",
  "properties": {
    "iso:country":"US",
    "sg:address":"6967 US Hwy 15",
    "sg:city":"Montgomery",
    "sg:classifiers":[
        {
            "category":"Travel",
            "subcategory":"Hotels & Motels",
            "type":"Entertainment"
        }
    ],
    "sg:phone":"+1 570 547 1007",
    "sg:postcode":"17752",
    "sg:province":"PA",
    "wof:name":"White Deer Motel",
    "wof:placetype":"venue"
},
  "geometry": {"coordinates":[-76.908698,41.170334],"type":"Point"}
}