{
  "type": "Feature",
  "properties": {
    "iso:country":"US",
    "sg:address":"231 W Wingohocking St",
    "sg:city":"Philadelphia",
    "sg:classifiers":[
        {
            "category":"Retail",
            "subcategory":"Auto Repair",
            "type":"Services"
        }
    ],
    "sg:phone":"+1 215 324 2200",
    "sg:postcode":"19140",
    "sg:province":"PA",
    "sg:tags":[
        "repairing",
        "automobile"
    ],
    "wof:name":"Northeastern Automotive Group",
    "wof:placetype":"venue"
},
  "geometry": {"coordinates":[-75.130515,40.019219],"type":"Point"}
}