{
  "type": "Feature",
  "properties": {
    "iso:country":"US",
    "sg:address":"125 N Enola Dr",
    "sg:city":"Enola",
    "sg:classifiers":[
        {
            "category":"Health Services",
            "subcategory":"Doctor",
            "type":"Services"
        }
    ],
    "sg:phone":"+1 717 732 7171",
    "sg:postcode":"17025",
    "sg:province":"PA",
    "sg:tags":[
        "physician",
        "surgeon",
        "medical"
    ],
    "wof:name":"Pennsboro Pediatrics",
    "wof:placetype":"venue"
},
  "geometry": {"coordinates":[-76.934127,40.293324],"type":"Point"}
}