{
  "type": "Feature",
  "properties": {
    "addr:full":"230 N Keswick Ave Glenside PA 19038",
    "addr:housenumber":"230",
    "addr:postcode":"19038",
    "addr:street":"N Keswick Ave",
    "iso:country":"US",
    "sg:address":"230 N Keswick Ave",
    "sg:city":"Glenside",
    "sg:classifiers":[
        {
            "category":"Health Services",
            "subcategory":"Dentist",
            "type":"Services"
        }
    ],
    "sg:phone":"+1 215 885 4252",
    "sg:postcode":"19038",
    "sg:province":"PA",
    "wof:name":"Dynamic Modern Dentistry",
    "wof:placetype":"venue"
},
  "geometry": {"coordinates":[-75.14712299999999,40.104537],"type":"Point"}
}