{
  "type": "Feature",
  "properties": {
    "addr:full":"300 Bursca Dr Ste 302 Bridgeville PA 15017",
    "addr:housenumber":"300",
    "addr:postcode":"15017",
    "addr:street":"Bursca Dr Ste 302",
    "iso:country":"US",
    "sg:address":"300 Bursca Dr Ste 302",
    "sg:city":"Bridgeville",
    "sg:classifiers":[
        {
            "category":"Building & Trades",
            "subcategory":"Construction",
            "type":"Services"
        }
    ],
    "sg:phone":"+1 412 220 1100",
    "sg:postcode":"15017",
    "sg:province":"PA",
    "sg:tags":[
        "contractor"
    ],
    "sg:website":"www.enerfab.com",
    "wof:name":"Enerfab Corp",
    "wof:placetype":"venue"
},
  "geometry": {"coordinates":[-80.11199999999999,40.3479],"type":"Point"}
}