{
  "type": "Feature",
  "properties": {
    "iso:country":"US",
    "sg:address":"1706 N 2nd St",
    "sg:city":"Philadelphia",
    "sg:classifiers":[
        {
            "category":"Professional",
            "subcategory":"Business Services",
            "type":"Services"
        }
    ],
    "sg:phone":"+1 215 425 4475",
    "sg:postcode":"19122",
    "sg:province":"PA",
    "sg:tags":[
        "holding"
    ],
    "wof:name":"Gm Holdings",
    "wof:placetype":"venue"
},
  "geometry": {"coordinates":[-75.138075,39.976424],"type":"Point"}
}