{
  "type": "Feature",
  "properties": {
    "iso:country":"US",
    "sg:address":"15 Roemer Blvd",
    "sg:city":"Farrell",
    "sg:classifiers":[
        {
            "category":"Manufacturing",
            "subcategory":"Metals",
            "type":"Manufacturing & Wholesale Goods"
        }
    ],
    "sg:phone":"+1   ",
    "sg:postcode":"16121",
    "sg:province":"PA",
    "sg:tags":[
        "steel",
        "cold",
        "nonferrous",
        "shape",
        "mfg"
    ],
    "wof:name":"Farrell Duferco Corp",
    "wof:placetype":"venue"
},
  "geometry": {"coordinates":[-80.505319,41.211851],"type":"Point"}
}