{
  "type": "Feature",
  "properties": {
    "iso:country":"US",
    "sg:address":"535 S Middlesex Rd",
    "sg:city":"Carlisle",
    "sg:classifiers":[
        {
            "category":"Building & Trades",
            "subcategory":"Cleaning & Sanitation",
            "type":"Services"
        },
        {
            "category":"Utilities",
            "subcategory":"Sewage",
            "type":"Services"
        }
    ],
    "sg:phone":"+1 717 243 4214",
    "sg:postcode":"17015",
    "sg:province":"PA",
    "sg:tags":[
        "control",
        "deodorizing",
        "odor",
        "disinfecting"
    ],
    "wof:name":"Container Bright Inc",
    "wof:placetype":"venue"
},
  "geometry": {"coordinates":[-77.127342,40.188751],"type":"Point"}
}