{
  "type": "Feature",
  "properties": {
    "iso:country":"US",
    "sg:address":"2 Logan Sq",
    "sg:city":"Philadelphia",
    "sg:classifiers":[
        {
            "category":"Professional",
            "subcategory":"Lawyer & Legal Services",
            "type":"Services"
        }
    ],
    "sg:phone":"+1 215 981 4692",
    "sg:postcode":"19103",
    "sg:province":"PA",
    "wof:name":"Remick Lani A Atty",
    "wof:placetype":"venue"
},
  "geometry": {"coordinates":[-75.17055499999999,39.957256],"type":"Point"}
}