{
  "type": "Feature",
  "properties": {
    "iso:country":"US",
    "sg:address":"395 Bedford St",
    "sg:city":"Clarks Summit",
    "sg:classifiers":[
        {
            "category":"Government",
            "subcategory":"Office",
            "type":"Public Place"
        }
    ],
    "sg:phone":"+1   ",
    "sg:postcode":"18411",
    "sg:province":"PA",
    "wof:name":"Pocono-Northeast RC & D",
    "wof:placetype":"venue"
},
  "geometry": {"coordinates":[-75.706464,41.493268],"type":"Point"}
}