{
  "type": "Feature",
  "properties": {
    "iso:country":"US",
    "sg:address":"230 S Broad St",
    "sg:city":"Philadelphia",
    "sg:classifiers":[
        {
            "category":"Banks & Credit Unions",
            "subcategory":"Investment Brokerage",
            "type":"Services"
        }
    ],
    "sg:phone":"+1 215 546 7500",
    "sg:postcode":"19102",
    "sg:province":"PA",
    "sg:tags":[
        "advisory",
        "manager",
        "counselor",
        "financial"
    ],
    "sg:website":"www.ajopartners.com",
    "wof:name":"Aronson Johnson & Ortiz LP",
    "wof:placetype":"venue"
},
  "geometry": {"coordinates":[-75.16461,39.948486],"type":"Point"}
}