{
  "type": "Feature",
  "properties": {
    "addr:full":"626 Meadow Dr West Chester PA 19380",
    "addr:housenumber":"626",
    "addr:postcode":"19380",
    "addr:street":"Meadow Dr",
    "iso:country":"US",
    "sg:address":"626 Meadow Dr",
    "sg:city":"West Chester",
    "sg:classifiers":[
        {
            "category":"Professional",
            "subcategory":"Management & Consulting",
            "type":"Services"
        }
    ],
    "sg:phone":"+1 610 431 5782",
    "sg:postcode":"19380",
    "sg:province":"PA",
    "sg:tags":[
        "consultant",
        "business"
    ],
    "wof:name":"Five Winds Intl",
    "wof:placetype":"venue"
},
  "geometry": {"coordinates":[-75.55893500000001,39.982463],"type":"Point"}
}