{
  "type": "Feature",
  "properties": {
    "addr:full":"2310 76th Ave Philadelphia PA 19150",
    "addr:housenumber":"2310",
    "addr:postcode":"19150",
    "addr:street":"76Th Ave",
    "iso:country":"US",
    "sg:address":"2310 76th Ave",
    "sg:city":"Philadelphia",
    "sg:classifiers":[
        {
            "category":"Retail",
            "subcategory":"Photofinishing",
            "type":"Services"
        }
    ],
    "sg:phone":"+1   ",
    "sg:postcode":"19150",
    "sg:province":"PA",
    "sg:tags":[
        "laboratory"
    ],
    "wof:name":"Photo Graphic Creat",
    "wof:placetype":"venue"
},
  "geometry": {"coordinates":[-75.157015,40.06992],"type":"Point"}
}