{
  "type": "Feature",
  "properties": {
    "iso:country":"US",
    "sg:address":"1208 Empire Cir",
    "sg:city":"Lancaster",
    "sg:classifiers":[
        {
            "category":"Real Estate",
            "subcategory":"Real Estate Operator",
            "type":"Services"
        }
    ],
    "sg:phone":"+1   ",
    "sg:postcode":"17601",
    "sg:province":"PA",
    "sg:tags":[
        "property",
        "lessor"
    ],
    "wof:name":"Stephen A Brillhart",
    "wof:placetype":"venue"
},
  "geometry": {"coordinates":[-76.389017,40.081333],"type":"Point"}
}