{
  "type": "Feature",
  "properties": {
    "addr:full":"6951 Allentown Blvd Harrisburg PA 17112",
    "addr:housenumber":"6951",
    "addr:postcode":"17112",
    "addr:street":"Allentown Blvd",
    "iso:country":"US",
    "sg:address":"6951 Allentown Blvd",
    "sg:city":"Harrisburg",
    "sg:classifiers":[
        {
            "category":"Home & Garden",
            "subcategory":"Carpets & Floor Coverings",
            "type":"Retail Goods"
        },
        {
            "category":"Building & Trades",
            "subcategory":"Construction",
            "type":"Services"
        }
    ],
    "sg:phone":"+1 717 540 8190",
    "sg:postcode":"17112",
    "sg:province":"PA",
    "sg:tags":[
        "tile",
        "dealer"
    ],
    "wof:name":"Hursts Flooring",
    "wof:placetype":"venue"
},
  "geometry": {"coordinates":[-76.75479199999999,40.329988],"type":"Point"}
}