{
  "type": "Feature",
  "properties": {
    "iso:country":"US",
    "sg:address":"719 Long Ln",
    "sg:city":"Lansdowne",
    "sg:classifiers":[
        {
            "category":"Bakery",
            "type":"Food & Drink"
        }
    ],
    "sg:phone":"+1 610 626 2126",
    "sg:postcode":"19050",
    "sg:province":"PA",
    "wof:name":"Heavens Delights Cakes & More",
    "wof:placetype":"venue"
},
  "geometry": {"coordinates":[-75.2556,39.9412],"type":"Point"}
}