{
  "type": "Feature",
  "properties": {
    "iso:country":"US",
    "sg:address":"1230 S Cedar Crest Blvd",
    "sg:city":"Allentown",
    "sg:classifiers":[
        {
            "category":"Health Services",
            "subcategory":"Doctor",
            "type":"Services"
        }
    ],
    "sg:phone":"+1   ",
    "sg:postcode":"18103",
    "sg:province":"PA",
    "wof:name":"Candio Kovacs & Lakata PC",
    "wof:placetype":"venue"
},
  "geometry": {"coordinates":[-75.518784,40.567775],"type":"Point"}
}