{
  "type": "Feature",
  "properties": {
    "iso:country":"US",
    "sg:address":"50 Poplar Dr",
    "sg:city":"Denver",
    "sg:classifiers":[
        {
            "category":"Building & Trades",
            "subcategory":"Construction",
            "type":"Services"
        }
    ],
    "sg:phone":"+1   ",
    "sg:postcode":"17517",
    "sg:province":"PA",
    "sg:tags":[
        "residential",
        "contractor"
    ],
    "wof:name":"Cosy Homes",
    "wof:placetype":"venue"
},
  "geometry": {"coordinates":[-76.08315,40.238574],"type":"Point"}
}