{
  "type": "Feature",
  "properties": {
    "iso:country":"US",
    "sg:address":"15 Kinsey St",
    "sg:city":"Montgomery",
    "sg:classifiers":[
        {
            "category":"Personal",
            "subcategory":"Beauty Salon",
            "type":"Services"
        }
    ],
    "sg:phone":"+1 570 547 2647",
    "sg:postcode":"17752",
    "sg:province":"PA",
    "wof:name":"Karen Hunt Hair Shop",
    "wof:placetype":"venue"
},
  "geometry": {"coordinates":[-76.879876,41.169936],"type":"Point"}
}