{
  "type": "Feature",
  "properties": {
    "iso:country":"US",
    "sg:address":"2432 N 19th St",
    "sg:city":"Philadelphia",
    "sg:classifiers":[
        {
            "category":"Personal",
            "subcategory":"Massage",
            "type":"Services"
        }
    ],
    "sg:phone":"+1 215 430 7678",
    "sg:postcode":"19132",
    "sg:province":"PA",
    "sg:tags":[
        "therapist"
    ],
    "wof:name":"Monica N Dillon",
    "wof:placetype":"venue"
},
  "geometry": {"coordinates":[-75.163404,39.990882],"type":"Point"}
}