{
  "type": "Feature",
  "properties": {
    "iso:country":"US",
    "sg:address":"307 Run Rd",
    "sg:city":"Carlisle",
    "sg:classifiers":[
        {
            "category":"Home & Garden",
            "subcategory":"Furniture",
            "type":"Retail Goods"
        }
    ],
    "sg:phone":"+1 717 241 2266",
    "sg:postcode":"17013",
    "sg:province":"PA",
    "sg:tags":[
        "store"
    ],
    "wof:name":"Rb Furniture",
    "wof:placetype":"venue"
},
  "geometry": {"coordinates":[-77.257896,40.213501],"type":"Point"}
}