{
  "type": "Feature",
  "properties": {
    "iso:country":"US",
    "sg:address":"1634 Wharton St",
    "sg:city":"Philadelphia",
    "sg:classifiers":[
        {
            "category":"Food & Beverages",
            "subcategory":"Groceries & Convenience Stores",
            "type":"Retail Goods"
        }
    ],
    "sg:phone":"+1 215 463 1661",
    "sg:postcode":"19146",
    "sg:province":"PA",
    "wof:name":"Neighbors In Action Assn",
    "wof:placetype":"venue"
},
  "geometry": {"coordinates":[-75.172389,39.934765],"type":"Point"}
}