{
  "type": "Feature",
  "properties": {
    "iso:country":"US",
    "sg:address":"158 E Union St",
    "sg:city":"Somerset",
    "sg:classifiers":[
        {
            "category":"Food & Beverages",
            "subcategory":"Specialty",
            "type":"Retail Goods"
        }
    ],
    "sg:phone":"+1 814 443 2016",
    "sg:postcode":"15501",
    "sg:province":"PA",
    "sg:tags":[
        "herb",
        "mfr",
        "spice"
    ],
    "wof:name":"Erbe Shoppe",
    "wof:placetype":"venue"
},
  "geometry": {"coordinates":[-79.07711500000001,40.009238],"type":"Point"}
}