{
  "type": "Feature",
  "properties": {
    "iso:country":"US",
    "sg:address":"21 Fairview Ave",
    "sg:city":"Oil City",
    "sg:classifiers":[
        {
            "category":"Organizations",
            "subcategory":"Religious Organization",
            "type":"Services"
        }
    ],
    "sg:phone":"+1 814 677 2079",
    "sg:postcode":"16301",
    "sg:province":"PA",
    "sg:tags":[
        "church"
    ],
    "wof:name":"Hasson Hts Presbyterian Church",
    "wof:placetype":"venue"
},
  "geometry": {"coordinates":[-79.682648,41.441999],"type":"Point"}
}