{
  "type": "Feature",
  "properties": {
    "addr:full":"603 Locust St Wrightsville PA 17368",
    "addr:housenumber":"603",
    "addr:postcode":"17368",
    "addr:street":"Locust St",
    "iso:country":"US",
    "sg:address":"603 Locust St",
    "sg:city":"Wrightsville",
    "sg:classifiers":[
        {
            "category":"Shopping",
            "subcategory":"Photographic Equipment",
            "type":"Retail Goods"
        }
    ],
    "sg:phone":"+1   ",
    "sg:postcode":"17368",
    "sg:province":"PA",
    "sg:tags":[
        "photography",
        "camera",
        "studio"
    ],
    "wof:name":"D & G Photographic Services",
    "wof:placetype":"venue"
},
  "geometry": {"coordinates":[-76.53709000000001,40.025245],"type":"Point"}
}