{
  "type": "Feature",
  "properties": {
    "addr:full":"1980 Smith Township State Rd Burgettstown PA 15021",
    "addr:housenumber":"1980",
    "addr:postcode":"15021",
    "addr:street":"Smith;State Rd",
    "iso:country":"US",
    "sg:address":"1980 Smith Township State Rd",
    "sg:city":"Burgettstown",
    "sg:classifiers":[
        {
            "category":"Manufacturing",
            "subcategory":"Food",
            "type":"Manufacturing & Wholesale Goods"
        }
    ],
    "sg:phone":"+1 724 947 2216",
    "sg:postcode":"15021",
    "sg:province":"PA",
    "sg:tags":[
        "product",
        "manufacturer"
    ],
    "wof:name":"Panhandle Food Sales",
    "wof:placetype":"venue"
},
  "geometry": {"coordinates":[-80.39097,40.362102],"type":"Point"}
}