{
  "type": "Feature",
  "properties": {
    "iso:country":"US",
    "sg:address":"2052 Fortune Rd",
    "sg:city":"Abington",
    "sg:classifiers":[
        {
            "category":"Building & Trades",
            "subcategory":"Plumbing",
            "type":"Services"
        }
    ],
    "sg:phone":"+1 215 576 5541",
    "sg:postcode":"19038",
    "sg:province":"PA",
    "sg:tags":[
        "plumbing",
        "contractor"
    ],
    "wof:name":"Hughes Plumbing",
    "wof:placetype":"venue"
},
  "geometry": {"coordinates":[-75.138482,40.1039],"type":"Point"}
}