{
  "type": "Feature",
  "properties": {
    "iso:country":"US",
    "sg:address":"400 N Harris St",
    "sg:city":"Lebanon",
    "sg:classifiers":[
        {
            "category":"Farming",
            "subcategory":"Farm",
            "type":"Manufacturing & Wholesale Goods"
        }
    ],
    "sg:phone":"+1   ",
    "sg:postcode":"17042",
    "sg:province":"PA",
    "sg:tags":[
        "livestock",
        "crop",
        "general"
    ],
    "wof:name":"Elmer Books",
    "wof:placetype":"venue"
},
  "geometry": {"coordinates":[-76.48432699999999,40.344965],"type":"Point"}
}