{
  "type": "Feature",
  "properties": {
    "addr:full":"1120 Meetinghouse Rd Gwynedd PA 19436",
    "addr:housenumber":"1120",
    "addr:postcode":"19436",
    "addr:street":"Meetinghouse Rd",
    "iso:country":"US",
    "sg:address":"1120 Meetinghouse Rd",
    "sg:city":"Gwynedd",
    "sg:classifiers":[
        {
            "category":"Social Services",
            "subcategory":"Adult Care",
            "type":"Services"
        }
    ],
    "sg:phone":"+1 215 643 2200",
    "sg:postcode":"19436",
    "sg:province":"PA",
    "sg:tags":[
        "residential",
        "aged",
        "for"
    ],
    "sg:website":"www.foulkeways.org",
    "wof:name":"Foulkeways At Gwynedd",
    "wof:placetype":"venue"
},
  "geometry": {"coordinates":[-75.254036,40.204285],"type":"Point"}
}