{
  "type": "Feature",
  "properties": {
    "addr:full":"190 Robbins Rd Downingtown PA 19335",
    "addr:housenumber":"190",
    "addr:postcode":"19335",
    "addr:street":"Robbins Rd",
    "iso:country":"US",
    "sg:address":"190 Robbins Rd",
    "sg:city":"Downingtown",
    "sg:classifiers":[
        {
            "category":"Home & Garden",
            "subcategory":"Household Appliances",
            "type":"Retail Goods"
        },
        {
            "category":"Wholesale",
            "subcategory":"Electrical",
            "type":"Manufacturing & Wholesale Goods"
        }
    ],
    "sg:phone":"+1 610 873 3000",
    "sg:postcode":"19335",
    "sg:province":"PA",
    "wof:name":"Trible's Inc",
    "wof:placetype":"venue"
},
  "geometry": {"coordinates":[-75.697867,39.999372],"type":"Point"}
}