{
  "type": "Feature",
  "properties": {
    "iso:country":"US",
    "sg:address":"1080 Swiss Way",
    "sg:city":"Elizabeth",
    "sg:classifiers":[
        {
            "category":"Health Services",
            "subcategory":"Chiropractor",
            "type":"Services"
        }
    ],
    "sg:phone":"+1 412 754 1214",
    "sg:postcode":"15037",
    "sg:province":"PA",
    "sg:tags":[
        "chiropractic"
    ],
    "wof:name":"Gatto Chiropractic",
    "wof:placetype":"venue"
},
  "geometry": {"coordinates":[-79.83469100000001,40.280577],"type":"Point"}
}