{
  "type": "Feature",
  "properties": {
    "iso:country":"US",
    "sg:address":"30 Meng Rd",
    "sg:city":"Schwenksville",
    "sg:classifiers":[
        {
            "category":"Personal",
            "type":"Services"
        },
        {
            "category":"Retail",
            "subcategory":"Animal Services",
            "type":"Services"
        }
    ],
    "sg:phone":"+1 610 287 6251",
    "sg:postcode":"19473",
    "sg:province":"PA",
    "sg:tags":[
        "pet",
        "exercising"
    ],
    "wof:name":"Buttonwood Animal Inn LLC",
    "wof:placetype":"venue"
},
  "geometry": {"coordinates":[-75.47939,40.26583],"type":"Point"}
}