{
  "type": "Feature",
  "properties": {
    "addr:full":"2732 S Cleveland St Philadelphia PA 19145",
    "addr:housenumber":"2732",
    "addr:postcode":"19145",
    "addr:street":"S Cleveland St",
    "iso:country":"US",
    "sg:address":"2732 S Cleveland St",
    "sg:city":"Philadelphia",
    "sg:classifiers":[
        {
            "category":"Building & Trades",
            "subcategory":"Construction",
            "type":"Services"
        }
    ],
    "sg:phone":"+1   ",
    "sg:postcode":"19145",
    "sg:province":"PA",
    "sg:tags":[
        "contracting",
        "general"
    ],
    "wof:name":"Nicholas Ghionni Jr",
    "wof:placetype":"venue"
},
  "geometry": {"coordinates":[-75.17862599999999,39.916817],"type":"Point"}
}