{
  "type": "Feature",
  "properties": {
    "addr:full":"10 Fairway Dr Malvern PA 19355",
    "addr:housenumber":"10",
    "addr:postcode":"19355",
    "addr:street":"Fairway Dr",
    "iso:country":"US",
    "sg:address":"10 Fairway Dr",
    "sg:city":"Malvern",
    "sg:classifiers":[
        {
            "category":"Professional",
            "subcategory":"Accounting & Tax Preparation",
            "type":"Services"
        }
    ],
    "sg:phone":"+1 610 640 0351",
    "sg:postcode":"19355",
    "sg:province":"PA",
    "sg:tags":[
        "return",
        "filing"
    ],
    "wof:name":"Tax Advantage",
    "wof:placetype":"venue"
},
  "geometry": {"coordinates":[-75.573284,40.040021],"type":"Point"}
}