{
  "type": "Feature",
  "properties": {
    "iso:country":"US",
    "sg:address":"675 Hostetter Rd A",
    "sg:city":"Hanover",
    "sg:classifiers":[
        {
            "category":"Farming",
            "subcategory":"Livestock Farm",
            "type":"Manufacturing & Wholesale Goods"
        }
    ],
    "sg:phone":"+1 717 637 8473",
    "sg:postcode":"17331",
    "sg:province":"PA",
    "sg:tags":[
        "ranch"
    ],
    "wof:name":"Grove Brothers",
    "wof:placetype":"venue"
},
  "geometry": {"coordinates":[-77.053039,39.782382],"type":"Point"}
}