{
  "type": "Feature",
  "properties": {
    "addr:full":"110 4th St New Cumberland PA 17070",
    "addr:housenumber":"110",
    "addr:postcode":"17070",
    "addr:street":"4Th St",
    "iso:country":"US",
    "sg:address":"110 4th St",
    "sg:city":"New Cumberland",
    "sg:classifiers":[
        {
            "category":"Building & Trades",
            "subcategory":"Construction",
            "type":"Services"
        }
    ],
    "sg:phone":"+1 717 774 4702",
    "sg:postcode":"17070",
    "sg:province":"PA",
    "sg:tags":[
        "concrete",
        "contractor"
    ],
    "wof:name":"M J Di Tonno Concrete Constr",
    "wof:placetype":"venue"
},
  "geometry": {"coordinates":[-76.864808,40.228205],"type":"Point"}
}