{
  "type": "Feature",
  "properties": {
    "iso:country":"US",
    "sg:address":"121 Gamma Dr",
    "sg:city":"Pittsburgh",
    "sg:classifiers":[
        {
            "category":"Banks & Credit Unions",
            "subcategory":"Bank",
            "type":"Services"
        }
    ],
    "sg:phone":"+1 412 967 3123",
    "sg:postcode":"15238",
    "sg:province":"PA",
    "sg:tags":[
        "federally",
        "chartered"
    ],
    "wof:name":"Msa Employees Federal Cu",
    "wof:placetype":"venue"
},
  "geometry": {"coordinates":[-79.86690900000001,40.499344],"type":"Point"}
}