{
  "type": "Feature",
  "properties": {
    "iso:country":"US",
    "sg:address":"4006 Old Rte 8",
    "sg:city":"Allison Park",
    "sg:classifiers":[
        {
            "category":"Manufacturing",
            "subcategory":"Metals",
            "type":"Manufacturing & Wholesale Goods"
        }
    ],
    "sg:phone":"+1 412 961 0413",
    "sg:postcode":"15101",
    "sg:province":"PA",
    "sg:tags":[
        "ornamental",
        "work",
        "iron",
        "fabricator"
    ],
    "wof:name":"H R Leuenberger Inc",
    "wof:placetype":"venue"
},
  "geometry": {"coordinates":[-79.95925099999999,40.562789],"type":"Point"}
}