{
  "type": "Feature",
  "properties": {
    "iso:country":"US",
    "sg:address":"723 W Chew St",
    "sg:city":"Allentown",
    "sg:classifiers":[
        {
            "category":"Government",
            "subcategory":"Office",
            "type":"Public Place"
        }
    ],
    "sg:phone":"+1 610 437 7568",
    "sg:postcode":"18102",
    "sg:province":"PA",
    "sg:tags":[
        "village"
    ],
    "wof:name":"Allentown Emergency Medical",
    "wof:placetype":"venue"
},
  "geometry": {"coordinates":[-75.47503399999999,40.606068],"type":"Point"}
}