{
  "type": "Feature",
  "properties": {
    "iso:country":"US",
    "sg:address":"9043 Mountain Rd",
    "sg:city":"Alburtis",
    "sg:classifiers":[
        {
            "category":"Professional",
            "subcategory":"Management & Consulting",
            "type":"Services"
        }
    ],
    "sg:phone":"+1   ",
    "sg:postcode":"18011",
    "sg:province":"PA",
    "sg:tags":[
        "retail",
        "direct",
        "sales"
    ],
    "wof:name":"Hearth & Hm At Maple Grove Co",
    "wof:placetype":"venue"
},
  "geometry": {"coordinates":[-75.615685,40.490922],"type":"Point"}
}