{
  "type": "Feature",
  "properties": {
    "addr:full":"58 Laurel Rd Southampton PA 18966",
    "addr:housenumber":"58",
    "addr:postcode":"18966",
    "addr:street":"Laurel Rd",
    "iso:country":"US",
    "sg:address":"58 Laurel Rd",
    "sg:city":"Southampton",
    "sg:classifiers":[
        {
            "category":"Real Estate",
            "subcategory":"Real Estate Agent",
            "type":"Services"
        }
    ],
    "sg:phone":"+1 215 357 1613",
    "sg:postcode":"18966",
    "sg:province":"PA",
    "wof:name":"Crawford Partnership",
    "wof:placetype":"venue"
},
  "geometry": {"coordinates":[-75.066186,40.173819],"type":"Point"}
}