{
  "type": "Feature",
  "properties": {
    "addr:full":"1705 River Rd Pittston PA 18640",
    "addr:housenumber":"1705",
    "addr:postcode":"18640",
    "addr:street":"River Rd",
    "iso:country":"US",
    "sg:address":"1705 River Rd",
    "sg:city":"Pittston",
    "sg:classifiers":[
        {
            "category":"Bars & Pubs",
            "type":"Food & Drink"
        },
        {
            "category":"Restaurant",
            "type":"Food & Drink"
        }
    ],
    "sg:phone":"+1 570 883 0444",
    "sg:postcode":"18640",
    "sg:province":"PA",
    "sg:tags":[
        "bar"
    ],
    "wof:name":"Brews Brothers Inc",
    "wof:placetype":"venue"
},
  "geometry": {"coordinates":[-75.831593,41.300564],"type":"Point"}
}