{
  "type": "Feature",
  "properties": {
    "iso:country":"US",
    "sg:address":"558 Center Grange Rd",
    "sg:city":"Monaca",
    "sg:classifiers":[
        {
            "category":"Manufacturing",
            "subcategory":"Building Materials",
            "type":"Manufacturing & Wholesale Goods"
        }
    ],
    "sg:phone":"+1 724 375 7744",
    "sg:postcode":"15061",
    "sg:province":"PA",
    "sg:tags":[
        "mfg",
        "wood",
        "kitchen",
        "cabinet"
    ],
    "wof:name":"Mike Lucci Cabinets",
    "wof:placetype":"venue"
},
  "geometry": {"coordinates":[-80.268789,40.642977],"type":"Point"}
}