{
  "type": "Feature",
  "properties": {
    "iso:country":"US",
    "sg:address":"6960 York Rd",
    "sg:city":"Abbottstown",
    "sg:classifiers":[
        {
            "category":"Shopping",
            "subcategory":"Used Merchandise",
            "type":"Retail Goods"
        }
    ],
    "sg:phone":"+1 717 624 8361",
    "sg:postcode":"17301",
    "sg:province":"PA",
    "sg:tags":[
        "flea",
        "market"
    ],
    "wof:name":"Old Barn Antique",
    "wof:placetype":"venue"
},
  "geometry": {"coordinates":[-77.00526499999999,39.879419],"type":"Point"}
}