{
  "type": "Feature",
  "properties": {
    "iso:country":"US",
    "sg:address":"11933 Glenfield Rd",
    "sg:city":"Philadelphia",
    "sg:classifiers":[
        {
            "category":"Insurance",
            "subcategory":"Insurance Agent",
            "type":"Services"
        }
    ],
    "sg:phone":"+1   ",
    "sg:postcode":"19154",
    "sg:province":"PA",
    "wof:name":"Elite Public Adjusters",
    "wof:placetype":"venue"
},
  "geometry": {"coordinates":[-74.978493,40.084677],"type":"Point"}
}