{
  "type": "Feature",
  "properties": {
    "addr:full":"995 Pittsville Rd Kennerdell PA 16374",
    "addr:housenumber":"995",
    "addr:postcode":"16374",
    "addr:street":"Pittsville Rd",
    "iso:country":"US",
    "sg:address":"995 Pittsville Rd",
    "sg:city":"Kennerdell",
    "sg:classifiers":[
        {
            "category":"Government",
            "subcategory":"Fire Station",
            "type":"Public Place"
        }
    ],
    "sg:phone":"+1 814 498 2450",
    "sg:postcode":"16374",
    "sg:province":"PA",
    "sg:tags":[
        "department"
    ],
    "wof:name":"Rockland Twp Vol Fire Hall",
    "wof:placetype":"venue"
},
  "geometry": {"coordinates":[-79.748611,41.274191],"type":"Point"}
}