{
  "type": "Feature",
  "properties": {
    "iso:country":"US",
    "sg:address":"714 3rd Ave",
    "sg:city":"New Brighton",
    "sg:classifiers":[
        {
            "category":"Personal",
            "subcategory":"Beauty Salon",
            "type":"Services"
        }
    ],
    "sg:phone":"+1 724 846 7800",
    "sg:postcode":"15066",
    "sg:province":"PA",
    "wof:name":"Four Seasons Beauty Salon",
    "wof:placetype":"venue"
},
  "geometry": {"coordinates":[-80.31502399999999,40.735752],"type":"Point"}
}