{
  "type": "Feature",
  "properties": {
    "iso:country":"US",
    "sg:address":"1045 Bustleton Pike",
    "sg:city":"Feastervl Trvs",
    "sg:classifiers":[
        {
            "category":"Restaurant",
            "type":"Food & Drink"
        }
    ],
    "sg:phone":"+1 215 355 6266",
    "sg:postcode":"19053",
    "sg:province":"PA",
    "sg:tags":[
        "pizza"
    ],
    "wof:name":"Lamberti's Cucina",
    "wof:placetype":"venue"
},
  "geometry": {"coordinates":[-75.002139,40.151588],"type":"Point"}
}