{
  "type": "Feature",
  "properties": {
    "iso:country":"US",
    "sg:address":"515 Stump Rd",
    "sg:city":"North Wales",
    "sg:classifiers":[
        {
            "category":"Professional",
            "subcategory":"Computer Services",
            "type":"Services"
        }
    ],
    "sg:phone":"+1 215 855 9720",
    "sg:postcode":"19454",
    "sg:province":"PA",
    "sg:tags":[
        "repair"
    ],
    "wof:name":"Strategic Technology Solutions & Design Llc",
    "wof:placetype":"venue"
},
  "geometry": {"coordinates":[-75.250198,40.2267],"type":"Point"}
}