{
  "type": "Feature",
  "properties": {
    "iso:country":"US",
    "sg:address":"1 Liberty Pl",
    "sg:city":"Doylestown",
    "sg:classifiers":[
        {
            "category":"Banks & Credit Unions",
            "subcategory":"Bank",
            "type":"Services"
        }
    ],
    "sg:phone":"+1 800 886 5107",
    "sg:postcode":"18901",
    "sg:province":"PA",
    "sg:website":"www.wilmingtontrust.com",
    "wof:name":"Wilmington Trust",
    "wof:placetype":"venue"
},
  "geometry": {"coordinates":[-75.149378,40.31266],"type":"Point"}
}