{
  "type": "Feature",
  "properties": {
    "addr:full":"1024 S 9th St Philadelphia PA 19147",
    "addr:housenumber":"1024",
    "addr:postcode":"19147",
    "addr:street":"S 9Th St",
    "iso:country":"US",
    "sg:address":"1024 S 9th St",
    "sg:city":"Philadelphia",
    "sg:classifiers":[
        {
            "category":"Restaurant",
            "type":"Food & Drink"
        }
    ],
    "sg:phone":"+1   ",
    "sg:postcode":"19147",
    "sg:province":"PA",
    "sg:tags":[
        "grocery",
        "eating"
    ],
    "wof:name":"Marc Deli",
    "wof:placetype":"venue"
},
  "geometry": {"coordinates":[-75.158379,39.936961],"type":"Point"}
}