{
  "type": "Feature",
  "properties": {
    "addr:full":"1800 Oak St Lebanon PA 17042",
    "addr:housenumber":"1800",
    "addr:postcode":"17042",
    "addr:street":"Oak St",
    "iso:country":"US",
    "sg:address":"1800 Oak St",
    "sg:city":"Lebanon",
    "sg:classifiers":[
        {
            "category":"Organizations",
            "subcategory":"Religious Organization",
            "type":"Services"
        }
    ],
    "sg:phone":"+1 717 272 2922",
    "sg:postcode":"17042",
    "sg:province":"PA",
    "wof:name":"Messiah Lutheran Church",
    "wof:placetype":"venue"
},
  "geometry": {"coordinates":[-76.44179099999999,40.327865],"type":"Point"}
}