{
  "type": "Feature",
  "properties": {
    "iso:country":"US",
    "sg:address":"201 S Blakely St 328",
    "sg:city":"Dunmore",
    "sg:classifiers":[
        {
            "category":"Professional",
            "subcategory":"Business Services",
            "type":"Services"
        }
    ],
    "sg:phone":"+1 570 702 3029",
    "sg:postcode":"18512",
    "sg:province":"PA",
    "sg:tags":[
        "holding"
    ],
    "wof:name":"Sub 3 Holdings",
    "wof:placetype":"venue"
},
  "geometry": {"coordinates":[-75.63180199999999,41.420395],"type":"Point"}
}