{
  "type": "Feature",
  "properties": {
    "iso:country":"US",
    "sg:address":"910 Jefferson Ave",
    "sg:city":"Washington",
    "sg:classifiers":[
        {
            "category":"Food & Beverages",
            "subcategory":"Bakery",
            "type":"Retail Goods"
        },
        {
            "category":"Bakery",
            "type":"Food & Drink"
        }
    ],
    "sg:phone":"+1 724 222 1224",
    "sg:postcode":"15301",
    "sg:province":"PA",
    "sg:tags":[
        "bakers-wholesale"
    ],
    "sg:website":"http://www.interstatebakeriescorp.com",
    "wof:name":"Wonder & Hostess",
    "wof:placetype":"venue"
},
  "geometry": {"coordinates":[-80.262554,40.180761],"type":"Point"}
}