{
  "type": "Feature",
  "properties": {
    "iso:country":"US",
    "sg:address":"1233 Columbia Blvd",
    "sg:city":"Bloomsburg",
    "sg:classifiers":[
        {
            "category":"Food & Beverages",
            "subcategory":"Liquor & Beverages",
            "type":"Retail Goods"
        }
    ],
    "sg:phone":"+1   ",
    "sg:postcode":"17815",
    "sg:province":"PA",
    "sg:tags":[
        "alcoholic"
    ],
    "wof:name":"Bloom Party Center",
    "wof:placetype":"venue"
},
  "geometry": {"coordinates":[-76.432149,41.005986],"type":"Point"}
}