{
  "type": "Feature",
  "properties": {
    "addr:full":"169 York Rd Warminster PA 18974",
    "addr:housenumber":"169",
    "addr:postcode":"18974",
    "addr:street":"York Rd",
    "iso:country":"US",
    "sg:address":"169 York Rd",
    "sg:city":"Warminster",
    "sg:classifiers":[
        {
            "category":"Wholesale",
            "subcategory":"Construction Materials",
            "type":"Manufacturing & Wholesale Goods"
        }
    ],
    "sg:phone":"+1   ",
    "sg:postcode":"18974",
    "sg:province":"PA",
    "wof:name":"Vinyl Window and Door Company",
    "wof:placetype":"venue"
},
  "geometry": {"coordinates":[-75.10211,40.194246],"type":"Point"}
}