{
  "type": "Feature",
  "properties": {
    "addr:full":"4893 State Rte 30 Greensburg PA 15601",
    "addr:housenumber":"4893",
    "addr:postcode":"15601",
    "addr:street":"State Rte 30",
    "iso:country":"US",
    "sg:address":"4893 State Rte 30",
    "sg:city":"Greensburg",
    "sg:classifiers":[
        {
            "category":"Health Services",
            "subcategory":"Chiropractor",
            "type":"Services"
        }
    ],
    "sg:phone":"+1 724 837 1105",
    "sg:postcode":"15601",
    "sg:province":"PA",
    "wof:name":"Fitch Chiropractic Ctr",
    "wof:placetype":"venue"
},
  "geometry": {"coordinates":[-79.47853000000001,40.296814],"type":"Point"}
}