{
  "type": "Feature",
  "properties": {
    "addr:full":"4207 St Stans Ave Northern Cambria PA 15714",
    "addr:housenumber":"4207",
    "addr:postcode":"15714",
    "addr:street":"St Stans Ave",
    "iso:country":"US",
    "sg:address":"4207 St Stans Ave",
    "sg:city":"Northern Cambria",
    "sg:classifiers":[
        {
            "category":"Restaurant",
            "type":"Food & Drink"
        }
    ],
    "sg:menulink":"http://www.allmenus.com/pa/northern-cambria/286235-italian-village-pizza/menu/",
    "sg:phone":"+1 814 948 6634",
    "sg:postcode":"15714",
    "sg:province":"PA",
    "sg:tags":[
        "american",
        "pizza"
    ],
    "wof:name":"Italian Village Pizza",
    "wof:placetype":"venue"
},
  "geometry": {"coordinates":[-78.778796,40.660938],"type":"Point"}
}