{
  "type": "Feature",
  "properties": {
    "iso:country":"US",
    "sg:address":"110 Highland Ave",
    "sg:city":"New Stanton",
    "sg:classifiers":[
        {
            "category":"Health Services",
            "subcategory":"Doctor",
            "type":"Services"
        }
    ],
    "sg:phone":"+1 724 925 6010",
    "sg:postcode":"15672",
    "sg:province":"PA",
    "sg:tags":[
        "dentist"
    ],
    "wof:name":"James Mack DDS",
    "wof:placetype":"venue"
},
  "geometry": {"coordinates":[-79.60878,40.220571],"type":"Point"}
}