{
  "type": "Feature",
  "properties": {
    "iso:country":"US",
    "sg:address":"2039 Miller Rd",
    "sg:city":"East Petersburg",
    "sg:classifiers":[
        {
            "category":"Insurance",
            "subcategory":"Hazard Insurance",
            "type":"Services"
        }
    ],
    "sg:phone":"+1   ",
    "sg:postcode":"17520",
    "sg:province":"PA",
    "sg:tags":[
        "automobile",
        "homeowner"
    ],
    "wof:name":"Allstate",
    "wof:placetype":"venue"
},
  "geometry": {"coordinates":[-76.35033300000001,40.093626],"type":"Point"}
}