{
  "type": "Feature",
  "properties": {
    "iso:country":"US",
    "sg:address":"3 Haddon Pl",
    "sg:city":"Fort Washington",
    "sg:classifiers":[
        {
            "category":"Manufacturing",
            "subcategory":"Retail Goods",
            "type":"Manufacturing & Wholesale Goods"
        }
    ],
    "sg:phone":"+1   ",
    "sg:postcode":"19034",
    "sg:province":"PA",
    "sg:tags":[
        "product",
        "mfg"
    ],
    "wof:name":"Redoak Industries Inc",
    "wof:placetype":"venue"
},
  "geometry": {"coordinates":[-75.19774200000001,40.147042],"type":"Point"}
}