{
  "type": "Feature",
  "properties": {
    "addr:full":"1724 Walnut St Philadelphia PA 19103",
    "addr:housenumber":"1724",
    "addr:postcode":"19103",
    "addr:street":"Walnut St",
    "iso:country":"US",
    "sg:address":"1724 Walnut St",
    "sg:city":"Philadelphia",
    "sg:classifiers":[
        {
            "category":"Shopping",
            "subcategory":"Clothing, Apparel, & Fashions",
            "type":"Retail Goods"
        }
    ],
    "sg:phone":"+1 215 735 3814",
    "sg:postcode":"19103",
    "sg:province":"PA",
    "sg:tags":[
        "children's",
        "infant",
        "clothing",
        "wear"
    ],
    "sg:website":"www.childrensplace.com",
    "wof:name":"The Children's Place",
    "wof:placetype":"venue"
},
  "geometry": {"coordinates":[-75.170197,39.950199],"type":"Point"}
}