{
  "type": "Feature",
  "properties": {
    "iso:country":"US",
    "sg:address":"327 Beaver Valley Rd",
    "sg:city":"Bloomsburg",
    "sg:classifiers":[
        {
            "category":"Building & Trades",
            "subcategory":"Construction",
            "type":"Services"
        }
    ],
    "sg:phone":"+1 570 784 1807",
    "sg:postcode":"17815",
    "sg:province":"PA",
    "sg:tags":[
        "excavating",
        "contractor"
    ],
    "wof:name":"Floyd Frey",
    "wof:placetype":"venue"
},
  "geometry": {"coordinates":[-76.307241,40.958747],"type":"Point"}
}