{
  "type": "Feature",
  "properties": {
    "iso:country":"US",
    "sg:address":"1043 Park Ave",
    "sg:city":"Meadville",
    "sg:classifiers":[
        {
            "category":"Restaurant",
            "type":"Food & Drink"
        }
    ],
    "sg:menulink":"http://www.allmenus.com/pa/meadville/200169-long-john-silvers/menu/",
    "sg:phone":"+1 814 724 2300",
    "sg:postcode":"16335",
    "sg:province":"PA",
    "sg:tags":[
        "seafood",
        "american"
    ],
    "wof:name":"Long John Silver's",
    "wof:placetype":"venue"
},
  "geometry": {"coordinates":[-80.153738,41.634745],"type":"Point"}
}