{
  "type": "Feature",
  "properties": {
    "addr:full":"506 Hepburn St Williamsport PA 17701",
    "addr:housenumber":"506",
    "addr:postcode":"17701",
    "addr:street":"Hepburn St",
    "iso:country":"US",
    "sg:address":"506 Hepburn St",
    "sg:city":"Williamsport",
    "sg:classifiers":[
        {
            "category":"Professional",
            "subcategory":"Business Services",
            "type":"Services"
        }
    ],
    "sg:phone":"+1 570 326 4102",
    "sg:postcode":"17701",
    "sg:province":"PA",
    "sg:tags":[
        "packaging"
    ],
    "wof:name":"Crate & Freight Packing",
    "wof:placetype":"venue"
},
  "geometry": {"coordinates":[-77.006719,41.243144],"type":"Point"}
}