{
  "type": "Feature",
  "properties": {
    "addr:full":"39 Roberta Ln Royersford PA 19468",
    "addr:housenumber":"39",
    "addr:postcode":"19468",
    "addr:street":"Roberta Ln",
    "iso:country":"US",
    "sg:address":"39 Roberta Ln",
    "sg:city":"Royersford",
    "sg:classifiers":[
        {
            "category":"Shopping",
            "subcategory":"Bicycles & Sporting Goods",
            "type":"Retail Goods"
        }
    ],
    "sg:phone":"+1   ",
    "sg:postcode":"19468",
    "sg:province":"PA",
    "wof:name":"Steves Shooter Supply",
    "wof:placetype":"venue"
},
  "geometry": {"coordinates":[-75.536384,40.244107],"type":"Point"}
}