{
  "type": "Feature",
  "properties": {
    "addr:full":"203 S Broad St Philadelphia PA 19107",
    "addr:housenumber":"203",
    "addr:postcode":"19107",
    "addr:street":"S Broad St",
    "iso:country":"US",
    "sg:address":"203 S Broad St",
    "sg:city":"Philadelphia",
    "sg:classifiers":[
        {
            "category":"Professional",
            "subcategory":"Lawyer & Legal Services",
            "type":"Services"
        }
    ],
    "sg:phone":"+1 215 985 1515",
    "sg:postcode":"19107",
    "sg:province":"PA",
    "wof:name":"Cohen Fred R Atty",
    "wof:placetype":"venue"
},
  "geometry": {"coordinates":[-75.16419999999999,39.9491],"type":"Point"}
}