{
  "type": "Feature",
  "properties": {
    "iso:country":"US",
    "sg:address":"443 W Main St",
    "sg:city":"Dallastown",
    "sg:classifiers":[
        {
            "category":"Autos & Motor Vehicles",
            "subcategory":"Automobile Sales",
            "type":"Retail Goods"
        }
    ],
    "sg:phone":"+1 717 244 2770",
    "sg:postcode":"17313",
    "sg:province":"PA",
    "sg:tags":[
        "car",
        "dealer"
    ],
    "wof:name":"Werner Brothers Auto Sales",
    "wof:placetype":"venue"
},
  "geometry": {"coordinates":[-76.652435,39.905412],"type":"Point"}
}