{
  "type": "Feature",
  "properties": {
    "addr:full":"2104 W 7th St Chester PA 19013",
    "addr:housenumber":"2104",
    "addr:postcode":"19013",
    "addr:street":"W 7Th St",
    "iso:country":"US",
    "sg:address":"2104 W 7th St",
    "sg:city":"Chester",
    "sg:classifiers":[
        {
            "category":"Personal",
            "type":"Services"
        }
    ],
    "sg:phone":"+1 484 483 9273",
    "sg:postcode":"19013",
    "sg:province":"PA",
    "sg:tags":[
        "assistant"
    ],
    "wof:name":"Slydell & Slydell, Lp",
    "wof:placetype":"venue"
},
  "geometry": {"coordinates":[-75.387131,39.838692],"type":"Point"}
}