{
  "type": "Feature",
  "properties": {
    "iso:country":"US",
    "sg:address":"4036 Peach St",
    "sg:city":"Erie",
    "sg:classifiers":[
        {
            "category":"Autos & Motor Vehicles",
            "subcategory":"Automobile Sales",
            "type":"Retail Goods"
        }
    ],
    "sg:phone":"+1 814 868 2525",
    "sg:postcode":"16509",
    "sg:province":"PA",
    "sg:tags":[
        "car",
        "dealer"
    ],
    "wof:name":"Gary Miller Auto Group",
    "wof:placetype":"venue"
},
  "geometry": {"coordinates":[-80.084115,42.092747],"type":"Point"}
}