{
  "type": "Feature",
  "properties": {
    "iso:country":"US",
    "sg:address":"1408 S 18th St",
    "sg:city":"Harrisburg",
    "sg:classifiers":[
        {
            "category":"Social Services",
            "type":"Services"
        }
    ],
    "sg:phone":"+1 717 920 1575",
    "sg:postcode":"17104",
    "sg:province":"PA",
    "sg:tags":[
        "youth",
        "organization",
        "center"
    ],
    "wof:name":"Just 4 The Kidz Outreach",
    "wof:placetype":"venue"
},
  "geometry": {"coordinates":[-76.85443100000001,40.248899],"type":"Point"}
}