{
  "type": "Feature",
  "properties": {
    "iso:country":"US",
    "sg:address":"319 North 11th Street 2nd Floor",
    "sg:city":"Philadelphia",
    "sg:classifiers":[
        {
            "category":"Arts & Performance",
            "subcategory":"Art Gallery",
            "type":"Entertainment"
        }
    ],
    "sg:postcode":"19107",
    "sg:province":"PA",
    "sg:website":"www.marginalutility.org/",
    "wof:name":"Marginal Utility",
    "wof:placetype":"venue"
},
  "geometry": {"coordinates":[-75.15660099999999,39.958302],"type":"Point"}
}