{
  "type": "Feature",
  "properties": {
    "iso:country":"US",
    "sg:address":"1600 Park Ave",
    "sg:city":"Washington",
    "sg:classifiers":[
        {
            "category":"Wholesale",
            "subcategory":"Non-durable Goods",
            "type":"Manufacturing & Wholesale Goods"
        }
    ],
    "sg:phone":"+1   ",
    "sg:postcode":"15301",
    "sg:province":"PA",
    "wof:name":"Donald Anderson Distributors",
    "wof:placetype":"venue"
},
  "geometry": {"coordinates":[-80.267078,40.149283],"type":"Point"}
}