{
  "type": "Feature",
  "properties": {
    "iso:country":"US",
    "sg:address":"110 Heather Dr",
    "sg:city":"Monaca",
    "sg:classifiers":[
        {
            "category":"Professional",
            "type":"Services"
        }
    ],
    "sg:phone":"+1   ",
    "sg:postcode":"15061",
    "sg:province":"PA",
    "wof:name":"Janine D Pantely",
    "wof:placetype":"venue"
},
  "geometry": {"coordinates":[-80.307042,40.662175],"type":"Point"}
}