{
  "type": "Feature",
  "properties": {
    "iso:country":"US",
    "sg:address":"912 W Main St",
    "sg:city":"New Holland",
    "sg:classifiers":[
        {
            "category":"Banks & Credit Unions",
            "subcategory":"Investment Brokerage",
            "type":"Services"
        }
    ],
    "sg:phone":"+1   ",
    "sg:postcode":"17557",
    "sg:province":"PA",
    "sg:tags":[
        "security"
    ],
    "wof:name":"Edward Jones 14992",
    "wof:placetype":"venue"
},
  "geometry": {"coordinates":[-76.122759,40.091946],"type":"Point"}
}