{
  "type": "Feature",
  "properties": {
    "addr:full":"205 Courtney Dr Verona PA 15147",
    "addr:housenumber":"205",
    "addr:postcode":"15147",
    "addr:street":"Courtney Dr",
    "iso:country":"US",
    "sg:address":"205 Courtney Dr",
    "sg:city":"Verona",
    "sg:classifiers":[
        {
            "category":"Utilities",
            "subcategory":"Telephone",
            "type":"Services"
        }
    ],
    "sg:phone":"+1 412 798 8220",
    "sg:postcode":"15147",
    "sg:province":"PA",
    "sg:tags":[
        "telecommunication"
    ],
    "wof:name":"10th Planet Communications",
    "wof:placetype":"venue"
},
  "geometry": {"coordinates":[-79.805171,40.48809],"type":"Point"}
}