{
  "type": "Feature",
  "properties": {
    "iso:country":"US",
    "sg:address":"639 Meadow Dr",
    "sg:city":"West Chester",
    "sg:classifiers":[
        {
            "category":"Professional",
            "subcategory":"Business Services",
            "type":"Services"
        }
    ],
    "sg:phone":"+1   ",
    "sg:postcode":"19380",
    "sg:province":"PA",
    "wof:name":"Ueble Enterprises",
    "wof:placetype":"venue"
},
  "geometry": {"coordinates":[-75.55827600000001,39.983747],"type":"Point"}
}