{
  "type": "Feature",
  "properties": {
    "iso:country":"US",
    "sg:address":"2524 N 32nd St",
    "sg:city":"Philadelphia",
    "sg:classifiers":[
        {
            "category":"Manufacturing",
            "subcategory":"Printing",
            "type":"Manufacturing & Wholesale Goods"
        }
    ],
    "sg:phone":"+1 215 900 2763",
    "sg:postcode":"19132",
    "sg:province":"PA",
    "sg:tags":[
        "magazines-distributors"
    ],
    "wof:name":"Ja'ebza Hair And Fashion Magazine",
    "wof:placetype":"venue"
},
  "geometry": {"coordinates":[-75.183903,39.995192],"type":"Point"}
}