{
  "type": "Feature",
  "properties": {
    "iso:country":"US",
    "sg:address":"3341 Sardis Rd",
    "sg:city":"Murrysville",
    "sg:classifiers":[
        {
            "category":"Building & Trades",
            "subcategory":"Plumbing",
            "type":"Services"
        }
    ],
    "sg:phone":"+1 724 327 3868",
    "sg:postcode":"15668",
    "sg:province":"PA",
    "sg:tags":[
        "heating",
        "contractor"
    ],
    "wof:name":"Jeff Thomas Heating Inc",
    "wof:placetype":"venue"
},
  "geometry": {"coordinates":[-79.695233,40.432341],"type":"Point"}
}