{
  "type": "Feature",
  "properties": {
    "iso:country":"US",
    "sg:address":"1664 Street Rd",
    "sg:city":"Bensalem",
    "sg:classifiers":[
        {
            "category":"Personal",
            "subcategory":"Barber",
            "type":"Services"
        }
    ],
    "sg:phone":"+1 215 639 1149",
    "sg:postcode":"19020",
    "sg:province":"PA",
    "wof:name":"John's Barber Shop",
    "wof:placetype":"venue"
},
  "geometry": {"coordinates":[-74.944397,40.0956],"type":"Point"}
}