{
  "type": "Feature",
  "properties": {
    "iso:country":"US",
    "sg:address":"8 Opportunity Dr",
    "sg:city":"Loysville",
    "sg:classifiers":[
        {
            "category":"Real Estate",
            "subcategory":"Developer",
            "type":"Services"
        }
    ],
    "sg:phone":"+1 717 789 3841",
    "sg:postcode":"17047",
    "sg:province":"PA",
    "wof:name":"Youth Development Center",
    "wof:placetype":"venue"
},
  "geometry": {"coordinates":[-77.347284,40.370079],"type":"Point"}
}