{
  "type": "Feature",
  "properties": {
    "addr:full":"389 Rutt Rd Bangor PA 18013",
    "addr:housenumber":"389",
    "addr:postcode":"18013",
    "addr:street":"Rutt Rd",
    "iso:country":"US",
    "sg:address":"389 Rutt Rd",
    "sg:city":"Bangor",
    "sg:classifiers":[
        {
            "category":"Wholesale",
            "subcategory":"Hardware",
            "type":"Manufacturing & Wholesale Goods"
        }
    ],
    "sg:phone":"+1 610 588 5367",
    "sg:postcode":"18013",
    "sg:province":"PA",
    "sg:tags":[
        "heating"
    ],
    "wof:name":"Heat Tech Distributors",
    "wof:placetype":"venue"
},
  "geometry": {"coordinates":[-75.19076200000001,40.867651],"type":"Point"}
}