{
  "type": "Feature",
  "properties": {
    "addr:full":"511 Limekiln Pike Ambler PA 19002",
    "addr:housenumber":"511",
    "addr:postcode":"19002",
    "addr:street":"Limekiln Pike",
    "iso:country":"US",
    "sg:address":"511 Limekiln Pike",
    "sg:city":"Ambler",
    "sg:classifiers":[
        {
            "category":"Food & Beverages",
            "subcategory":"Liquor & Beverages",
            "type":"Retail Goods"
        },
        {
            "category":"Wholesale",
            "subcategory":"Beer",
            "type":"Manufacturing & Wholesale Goods"
        }
    ],
    "sg:phone":"+1 215 646 5000",
    "sg:postcode":"19002",
    "sg:province":"PA",
    "sg:tags":[
        "ale",
        "alcoholic"
    ],
    "wof:name":"Mac's Neighborhood Beverage",
    "wof:placetype":"venue"
},
  "geometry": {"coordinates":[-75.183044,40.177424],"type":"Point"}
}