{
  "type": "Feature",
  "properties": {
    "iso:country":"US",
    "sg:address":"5700 Perry Hwy",
    "sg:city":"Erie",
    "sg:classifiers":[
        {
            "category":"Wholesale",
            "subcategory":"Machinery & Supplies",
            "type":"Manufacturing & Wholesale Goods"
        }
    ],
    "sg:phone":"+1 814 864 3093",
    "sg:postcode":"16509",
    "sg:province":"PA",
    "sg:tags":[
        "ladder"
    ],
    "wof:name":"Padden's/Allpro",
    "wof:placetype":"venue"
},
  "geometry": {"coordinates":[-80.06232199999999,42.083778],"type":"Point"}
}