{
  "type": "Feature",
  "properties": {
    "iso:country":"US",
    "sg:address":"135 E 6th St",
    "sg:city":"Erie",
    "sg:classifiers":[
        {
            "category":"Professional",
            "subcategory":"Lawyer & Legal Services",
            "type":"Services"
        }
    ],
    "sg:phone":"+1   ",
    "sg:postcode":"16501",
    "sg:province":"PA",
    "wof:name":"Negri Darrel C Atty",
    "wof:placetype":"venue"
},
  "geometry": {"coordinates":[-80.082099,42.130439],"type":"Point"}
}