{
  "type": "Feature",
  "properties": {
    "addr:full":"4095 Lancaster Ave Philadelphia PA 19104",
    "addr:housenumber":"4095",
    "addr:postcode":"19104",
    "addr:street":"Lancaster Ave",
    "iso:country":"US",
    "sg:address":"4095 Lancaster Ave",
    "sg:city":"Philadelphia",
    "sg:classifiers":[
        {
            "category":"Shopping",
            "subcategory":"Clothing, Apparel, & Fashions",
            "type":"Retail Goods"
        }
    ],
    "sg:phone":"+1 215 387 6922",
    "sg:postcode":"19104",
    "sg:province":"PA",
    "sg:tags":[
        "family",
        "pizza"
    ],
    "wof:name":"Designer Outlet",
    "wof:placetype":"venue"
},
  "geometry": {"coordinates":[-75.20549800000001,39.965],"type":"Point"}
}