{
  "type": "Feature",
  "properties": {
    "iso:country":"US",
    "sg:address":"73 E Broad St",
    "sg:city":"Bethlehem",
    "sg:classifiers":[
        {
            "category":"Real Estate",
            "subcategory":"Real Estate Services",
            "type":"Services"
        },
        {
            "category":"Real Estate",
            "subcategory":"Real Estate Operator",
            "type":"Services"
        }
    ],
    "sg:phone":"+1 610 868 1996",
    "sg:postcode":"18018",
    "sg:province":"PA",
    "sg:tags":[
        "property",
        "management",
        "apartment",
        "rental",
        "finder"
    ],
    "sg:website":"www.apex-management.com",
    "wof:name":"Apex Management",
    "wof:placetype":"venue"
},
  "geometry": {"coordinates":[-75.37629699999999,40.622398],"type":"Point"}
}