{
  "type": "Feature",
  "properties": {
    "addr:full":"1422 Saint Matthews Rd Chester Springs PA 19425",
    "addr:housenumber":"1422",
    "addr:postcode":"19425",
    "addr:street":"Saint Matthews Rd",
    "iso:country":"US",
    "sg:address":"1422 Saint Matthews Rd",
    "sg:city":"Chester Springs",
    "sg:classifiers":[
        {
            "category":"Farming",
            "subcategory":"Farm",
            "type":"Manufacturing & Wholesale Goods"
        }
    ],
    "sg:phone":"+1 610 827 7687",
    "sg:postcode":"19425",
    "sg:province":"PA",
    "sg:tags":[
        "field",
        "corn",
        "crop"
    ],
    "wof:name":"Bryn Coed Farms Company",
    "wof:placetype":"venue"
},
  "geometry": {"coordinates":[-75.629138,40.126101],"type":"Point"}
}