{
  "type": "Feature",
  "properties": {
    "iso:country":"US",
    "sg:address":"271 Old William Penn Hwy",
    "sg:city":"Blairsville",
    "sg:classifiers":[
        {
            "category":"Autos & Motor Vehicles",
            "subcategory":"Auto Supplies",
            "type":"Retail Goods"
        }
    ],
    "sg:phone":"+1   ",
    "sg:postcode":"15717",
    "sg:province":"PA",
    "sg:tags":[
        "bus",
        "school"
    ],
    "wof:name":"Smith Auto Division Inc",
    "wof:placetype":"venue"
},
  "geometry": {"coordinates":[-79.242313,40.436922],"type":"Point"}
}