{
  "type": "Feature",
  "properties": {
    "iso:country":"US",
    "sg:address":"4149 N Franklin St",
    "sg:city":"Philadelphia",
    "sg:classifiers":[
        {
            "category":"Restaurant",
            "type":"Food & Drink"
        }
    ],
    "sg:phone":"+1   ",
    "sg:postcode":"19140",
    "sg:province":"PA",
    "sg:tags":[
        "eating"
    ],
    "wof:name":"Lick ME Water Ice Co Inc",
    "wof:placetype":"venue"
},
  "geometry": {"coordinates":[-75.13951900000001,40.01481],"type":"Point"}
}