{
  "type": "Feature",
  "properties": {
    "iso:country":"US",
    "sg:address":"127 Ewe Rd",
    "sg:city":"Mechanicsburg",
    "sg:classifiers":[
        {
            "category":"Travel",
            "subcategory":"Travel Agent",
            "type":"Entertainment"
        }
    ],
    "sg:phone":"+1   ",
    "sg:postcode":"17055",
    "sg:province":"PA",
    "sg:tags":[
        "agency"
    ],
    "wof:name":"Violago Gordon Travel Inc",
    "wof:placetype":"venue"
},
  "geometry": {"coordinates":[-76.932478,40.199983],"type":"Point"}
}