{
  "type": "Feature",
  "properties": {
    "iso:country":"US",
    "sg:address":"53 Pottsville St",
    "sg:city":"Cressona",
    "sg:classifiers":[
        {
            "category":"Manufacturing",
            "subcategory":"Metals",
            "type":"Manufacturing & Wholesale Goods"
        }
    ],
    "sg:phone":"+1 570 385 5000",
    "sg:postcode":"17929",
    "sg:province":"PA",
    "sg:tags":[
        "extruded",
        "product",
        "aluminum"
    ],
    "wof:name":"Alcoa Engineered Products",
    "wof:placetype":"venue"
},
  "geometry": {"coordinates":[-76.19017599999999,40.634833],"type":"Point"}
}