{
  "type": "Feature",
  "properties": {
    "iso:country":"US",
    "sg:address":"56 W Market St",
    "sg:city":"Bethlehem",
    "sg:classifiers":[
        {
            "category":"Food & Beverages",
            "subcategory":"Groceries & Convenience Stores",
            "type":"Retail Goods"
        }
    ],
    "sg:phone":"+1   ",
    "sg:postcode":"18018",
    "sg:province":"PA",
    "sg:tags":[
        "organization",
        "noncommercial",
        "research"
    ],
    "wof:name":"Market St Condo Assoc",
    "wof:placetype":"venue"
},
  "geometry": {"coordinates":[-75.37952199999999,40.620763],"type":"Point"}
}