{
  "type": "Feature",
  "properties": {
    "addr:full":"3445 Bristol Pke Bensalem PA 19020",
    "addr:housenumber":"3445",
    "addr:postcode":"19020",
    "addr:street":"Bristol Pke",
    "iso:country":"US",
    "sg:address":"3445 Bristol Pke",
    "sg:city":"Bensalem",
    "sg:classifiers":[
        {
            "category":"Arts & Performance",
            "subcategory":"Music",
            "type":"Entertainment"
        }
    ],
    "sg:phone":"+1 215 633 1200",
    "sg:postcode":"19020",
    "sg:province":"PA",
    "sg:tags":[
        "dj"
    ],
    "sg:website":"www.synergeticsounds.com",
    "wof:name":"Synergetic Sounds and Lighting",
    "wof:placetype":"venue"
},
  "geometry": {"coordinates":[-74.926878,40.088627],"type":"Point"}
}