{
  "type": "Feature",
  "properties": {
    "addr:full":"3401 Friendship St Philadelphia PA 19149",
    "addr:housenumber":"3401",
    "addr:postcode":"19149",
    "addr:street":"Friendship St",
    "iso:country":"US",
    "sg:address":"3401 Friendship St",
    "sg:city":"Philadelphia",
    "sg:classifiers":[
        {
            "category":"Education",
            "subcategory":"Dance Studio",
            "type":"Public Place"
        }
    ],
    "sg:phone":"+1 215 333 1435",
    "sg:postcode":"19149",
    "sg:province":"PA",
    "sg:tags":[
        "instruction",
        "dancing"
    ],
    "wof:name":"Tina's Center Stage Studio",
    "wof:placetype":"venue"
},
  "geometry": {"coordinates":[-75.04405199999999,40.035095],"type":"Point"}
}