{
  "type": "Feature",
  "properties": {
    "addr:full":"89 Militia Hill Rd Warrington PA 18976",
    "addr:housenumber":"89",
    "addr:postcode":"18976",
    "addr:street":"Militia Hill Rd",
    "iso:country":"US",
    "sg:address":"89 Militia Hill Rd",
    "sg:city":"Warrington",
    "sg:classifiers":[
        {
            "category":"Airport",
            "type":"Transportation"
        }
    ],
    "sg:phone":"+1   ",
    "sg:postcode":"18976",
    "sg:province":"PA",
    "sg:tags":[
        "sell",
        "support"
    ],
    "wof:name":"The Shain Group",
    "wof:placetype":"venue"
},
  "geometry": {"coordinates":[-75.149247,40.276425],"type":"Point"}
}