{
  "type": "Feature",
  "properties": {
    "addr:full":"230 E Water St Lock Haven PA 17745",
    "addr:housenumber":"230",
    "addr:postcode":"17745",
    "addr:street":"E Water St",
    "iso:country":"US",
    "sg:address":"230 E Water St",
    "sg:city":"Lock Haven",
    "sg:classifiers":[
        {
            "category":"Government",
            "subcategory":"Court House",
            "type":"Public Place"
        }
    ],
    "sg:phone":"+1 570 893 4012",
    "sg:postcode":"17745",
    "sg:province":"PA",
    "sg:tags":[
        "county"
    ],
    "wof:name":"Clinton County Judges Chambers",
    "wof:placetype":"venue"
},
  "geometry": {"coordinates":[-77.442949,41.138003],"type":"Point"}
}