{
  "type": "Feature",
  "properties": {
    "iso:country":"US",
    "sg:address":"1148 Van Reed Rd",
    "sg:city":"Reading",
    "sg:classifiers":[
        {
            "category":"Wholesale",
            "subcategory":"Plants",
            "type":"Manufacturing & Wholesale Goods"
        },
        {
            "category":"Home & Garden",
            "subcategory":"Garden Supply",
            "type":"Retail Goods"
        }
    ],
    "sg:phone":"+1 610 372 9696",
    "sg:postcode":"19605",
    "sg:province":"PA",
    "sg:tags":[
        "nurseryman",
        "landscape"
    ],
    "sg:website":"www.tulpehockennursery.com",
    "wof:name":"Tulpehocken Nursery Inc",
    "wof:placetype":"venue"
},
  "geometry": {"coordinates":[-75.988569,40.371999],"type":"Point"}
}