{
  "type": "Feature",
  "properties": {
    "iso:country":"US",
    "sg:address":"7500 W Ave",
    "sg:city":"Elkins Park",
    "sg:classifiers":[
        {
            "category":"Social Services",
            "subcategory":"Child Care",
            "type":"Services"
        }
    ],
    "sg:phone":"+1 215 635 5570",
    "sg:postcode":"19027",
    "sg:province":"PA",
    "wof:name":"Federal Early Learning Svc",
    "wof:placetype":"venue"
},
  "geometry": {"coordinates":[-75.13118299999999,40.066313],"type":"Point"}
}