{
  "type": "Feature",
  "properties": {
    "iso:country":"US",
    "sg:address":"206 S Main St",
    "sg:city":"Seneca",
    "sg:classifiers":[
        {
            "category":"Autos & Motor Vehicles",
            "subcategory":"Automobile Sales",
            "type":"Retail Goods"
        }
    ],
    "sg:phone":"+1   ",
    "sg:postcode":"16346",
    "sg:province":"PA",
    "sg:tags":[
        "used"
    ],
    "wof:name":"Best Auto Sales",
    "wof:placetype":"venue"
},
  "geometry": {"coordinates":[-79.702344,41.378421],"type":"Point"}
}