{
  "type": "Feature",
  "properties": {
    "addr:full":"1 Fayette St Conshohocken PA 19428",
    "addr:housenumber":"1",
    "addr:postcode":"19428",
    "addr:street":"Fayette St",
    "iso:country":"US",
    "sg:address":"1 Fayette St",
    "sg:city":"Conshohocken",
    "sg:classifiers":[
        {
            "category":"Insurance",
            "subcategory":"Life Insurance",
            "type":"Services"
        }
    ],
    "sg:phone":"+1   ",
    "sg:postcode":"19428",
    "sg:province":"PA",
    "wof:name":"Pacific Life",
    "wof:placetype":"venue"
},
  "geometry": {"coordinates":[-75.308036,40.072015],"type":"Point"}
}