{
  "type": "Feature",
  "properties": {
    "iso:country":"US",
    "sg:address":"4400 Campbells Run Rd",
    "sg:city":"Pittsburgh",
    "sg:classifiers":[
        {
            "category":"Professional",
            "subcategory":"Computer Services",
            "type":"Services"
        }
    ],
    "sg:phone":"+1   ",
    "sg:postcode":"15205",
    "sg:province":"PA",
    "sg:tags":[
        "design",
        "programming",
        "system"
    ],
    "wof:name":"Rapidigm Inc",
    "wof:placetype":"venue"
},
  "geometry": {"coordinates":[-80.120294,40.425687],"type":"Point"}
}