{
  "type": "Feature",
  "properties": {
    "addr:full":"2027 Murray Ave Pittsburgh PA 15217",
    "addr:housenumber":"2027",
    "addr:postcode":"15217",
    "addr:street":"Murray Ave",
    "iso:country":"US",
    "sg:address":"2027 Murray Ave",
    "sg:city":"Pittsburgh",
    "sg:classifiers":[
        {
            "category":"Shopping",
            "subcategory":"Hobbies, Toys, & Games",
            "type":"Retail Goods"
        },
        {
            "category":"Shopping",
            "subcategory":"Crafts & Fabrics",
            "type":"Retail Goods"
        }
    ],
    "sg:phone":"+1 412 422 9984",
    "sg:postcode":"15217",
    "sg:province":"PA",
    "sg:tags":[
        "shop",
        "hobby",
        "model",
        "supplies-wholesale",
        "manufacturer"
    ],
    "wof:name":"Mexico Lindo",
    "wof:placetype":"venue"
},
  "geometry": {"coordinates":[-79.922844,40.434547],"type":"Point"}
}