{
  "type": "Feature",
  "properties": {
    "addr:full":"601 Crest Rd Lebanon PA 17042",
    "addr:housenumber":"601",
    "addr:postcode":"17042",
    "addr:street":"Crest Rd",
    "iso:country":"US",
    "sg:address":"601 Crest Rd",
    "sg:city":"Lebanon",
    "sg:classifiers":[
        {
            "category":"Professional",
            "type":"Services"
        }
    ],
    "sg:phone":"+1   ",
    "sg:postcode":"17042",
    "sg:province":"PA",
    "wof:name":"Mark H Krall",
    "wof:placetype":"venue"
},
  "geometry": {"coordinates":[-76.356914,40.299907],"type":"Point"}
}