{
  "type": "Feature",
  "properties": {
    "iso:country":"US",
    "sg:address":"400 E General Robinson St",
    "sg:city":"Pittsburgh",
    "sg:classifiers":[
        {
            "category":"Shopping",
            "subcategory":"Clothing, Apparel, & Fashions",
            "type":"Retail Goods"
        }
    ],
    "sg:phone":"+1   ",
    "sg:postcode":"15212",
    "sg:province":"PA",
    "sg:tags":[
        "tailored"
    ],
    "wof:name":"Jos A Bank Clothiers Inc",
    "wof:placetype":"venue"
},
  "geometry": {"coordinates":[-79.999009,40.449321],"type":"Point"}
}