{
  "type": "Feature",
  "properties": {
    "addr:full":"186 E Court St Doylestown PA 18901",
    "addr:housenumber":"186",
    "addr:postcode":"18901",
    "addr:street":"E Court St",
    "iso:country":"US",
    "sg:address":"186 E Court St",
    "sg:city":"Doylestown",
    "sg:classifiers":[
        {
            "category":"Organizations",
            "subcategory":"Religious Organization",
            "type":"Services"
        }
    ],
    "sg:phone":"+1 215 348 9860",
    "sg:postcode":"18901",
    "sg:province":"PA",
    "sg:tags":[
        "christ",
        "church"
    ],
    "wof:name":"Salem United Church Of Christ",
    "wof:placetype":"venue"
},
  "geometry": {"coordinates":[-75.127439,40.31374],"type":"Point"}
}