{
  "type": "Feature",
  "properties": {
    "iso:country":"US",
    "sg:address":"200 Ross St",
    "sg:city":"Pittsburgh",
    "sg:classifiers":[
        {
            "category":"Government",
            "subcategory":"Office",
            "type":"Public Place"
        }
    ],
    "sg:phone":"+1 412 255 2175",
    "sg:postcode":"15219",
    "sg:province":"PA",
    "sg:tags":[
        "village"
    ],
    "wof:name":"Pittsburgh Building Inspection",
    "wof:placetype":"venue"
},
  "geometry": {"coordinates":[-79.99679399999999,40.437048],"type":"Point"}
}