{
  "type": "Feature",
  "properties": {
    "addr:full":"250 N Monroe St Bellefonte PA 16823",
    "addr:housenumber":"250",
    "addr:postcode":"16823",
    "addr:street":"N Monroe St",
    "iso:country":"US",
    "sg:address":"250 N Monroe St",
    "sg:city":"Bellefonte",
    "sg:classifiers":[
        {
            "category":"Government",
            "subcategory":"Office",
            "type":"Public Place"
        }
    ],
    "sg:phone":"+1   ",
    "sg:postcode":"16823",
    "sg:province":"PA",
    "sg:tags":[
        "national",
        "security"
    ],
    "wof:name":"Civil Air Patrol Inc",
    "wof:placetype":"venue"
},
  "geometry": {"coordinates":[-77.768579,40.917889],"type":"Point"}
}