{
  "type": "Feature",
  "properties": {
    "iso:country":"US",
    "sg:address":"1530 Chestnut St",
    "sg:city":"Philadelphia",
    "sg:classifiers":[
        {
            "category":"Professional",
            "subcategory":"Lawyer & Legal Services",
            "type":"Services"
        }
    ],
    "sg:phone":"+1   ",
    "sg:postcode":"19102",
    "sg:province":"PA",
    "sg:tags":[
        "pr",
        "administrative"
    ],
    "wof:name":"John S Fusco",
    "wof:placetype":"venue"
},
  "geometry": {"coordinates":[-75.16683399999999,39.95113],"type":"Point"}
}