{
  "type": "Feature",
  "properties": {
    "addr:full":"31 S Eagle Rd Havertown PA 19083",
    "addr:housenumber":"31",
    "addr:postcode":"19083",
    "addr:street":"S Eagle Rd",
    "iso:country":"US",
    "sg:address":"31 S Eagle Rd",
    "sg:city":"Havertown",
    "sg:classifiers":[
        {
            "category":"Professional",
            "subcategory":"Accounting & Tax Preparation",
            "type":"Services"
        }
    ],
    "sg:phone":"+1   ",
    "sg:postcode":"19083",
    "sg:province":"PA",
    "sg:tags":[
        "return"
    ],
    "wof:name":"H & R Block",
    "wof:placetype":"venue"
},
  "geometry": {"coordinates":[-75.31965,39.972734],"type":"Point"}
}