{
  "type": "Feature",
  "properties": {
    "addr:full":"151 Miller Rd Barto PA 19504",
    "addr:housenumber":"151",
    "addr:postcode":"19504",
    "addr:street":"Miller Rd",
    "iso:country":"US",
    "sg:address":"151 Miller Rd",
    "sg:city":"Barto",
    "sg:classifiers":[
        {
            "category":"Shopping",
            "subcategory":"Clothing, Apparel, & Fashions",
            "type":"Retail Goods"
        }
    ],
    "sg:phone":"+1 610 754 6548",
    "sg:postcode":"19504",
    "sg:province":"PA",
    "sg:tags":[
        "alteration"
    ],
    "wof:name":"Janet's Alterations & Drapes",
    "wof:placetype":"venue"
},
  "geometry": {"coordinates":[-75.58136399999999,40.374376],"type":"Point"}
}