{
  "type": "Feature",
  "properties": {
    "iso:country":"US",
    "sg:address":"7260 Frankford Ave",
    "sg:city":"Philadelphia",
    "sg:classifiers":[
        {
            "category":"Personal",
            "subcategory":"Beauty Salon",
            "type":"Services"
        }
    ],
    "sg:phone":"+1   ",
    "sg:postcode":"19135",
    "sg:province":"PA",
    "sg:tags":[
        "shop"
    ],
    "wof:name":"Kim Hair & Nail Salon",
    "wof:placetype":"venue"
},
  "geometry": {"coordinates":[-75.041071,40.036708],"type":"Point"}
}