{
  "type": "Feature",
  "properties": {
    "iso:country":"US",
    "sg:address":"2004 W Market St",
    "sg:city":"Pottsville",
    "sg:classifiers":[
        {
            "category":"Autos & Motor Vehicles",
            "subcategory":"Auto Supplies",
            "type":"Retail Goods"
        },
        {
            "category":"Shopping",
            "subcategory":"Computers & Home Electronics",
            "type":"Retail Goods"
        }
    ],
    "sg:phone":"+1 570 628 4561",
    "sg:postcode":"17901",
    "sg:province":"PA",
    "sg:tags":[
        "automobile",
        "stereo",
        "part",
        "radio"
    ],
    "wof:name":"12 Volt Dave's Audio",
    "wof:placetype":"venue"
},
  "geometry": {"coordinates":[-76.22001899999999,40.677192],"type":"Point"}
}