{
  "type": "Feature",
  "properties": {
    "iso:country":"US",
    "sg:address":"219 Atwood St",
    "sg:city":"Pittsburgh",
    "sg:classifiers":[
        {
            "category":"Restaurant",
            "type":"Food & Drink"
        }
    ],
    "sg:menulink":"http://www.allmenus.com/pa/pittsburgh/285450-big-joes-pizzeria/menu/",
    "sg:phone":"+1 412 621 6200",
    "sg:postcode":"15213",
    "sg:province":"PA",
    "sg:tags":[
        "american",
        "pizza"
    ],
    "wof:name":"Big Joe's Pizzeria",
    "wof:placetype":"venue"
},
  "geometry": {"coordinates":[-79.956805,40.440708],"type":"Point"}
}