{
  "type": "Feature",
  "properties": {
    "iso:country":"US",
    "sg:address":"960 Logan Rd",
    "sg:city":"Bethel Park",
    "sg:classifiers":[
        {
            "category":"Retail",
            "subcategory":"Repair Shop",
            "type":"Services"
        }
    ],
    "sg:phone":"+1 412 831 3311",
    "sg:postcode":"15102",
    "sg:province":"PA",
    "sg:tags":[
        "scale"
    ],
    "wof:name":"Don A Roberts & Sons",
    "wof:placetype":"venue"
},
  "geometry": {"coordinates":[-80.045345,40.316815],"type":"Point"}
}