{
  "type": "Feature",
  "properties": {
    "iso:country":"US",
    "sg:address":"528 E Main St",
    "sg:city":"Somerset",
    "sg:classifiers":[
        {
            "category":"Building & Trades",
            "subcategory":"Equipment Rental",
            "type":"Services"
        }
    ],
    "sg:phone":"+1   ",
    "sg:postcode":"15501",
    "sg:province":"PA",
    "sg:tags":[
        "aircraft"
    ],
    "wof:name":"Laurel Aviation Inc",
    "wof:placetype":"venue"
},
  "geometry": {"coordinates":[-79.069188,40.006734],"type":"Point"}
}