{
  "type": "Feature",
  "properties": {
    "iso:country":"US",
    "sg:address":"113 W Allegheny St",
    "sg:city":"Martinsburg",
    "sg:classifiers":[
        {
            "category":"Banks & Credit Unions",
            "subcategory":"Investment Brokerage",
            "type":"Services"
        }
    ],
    "sg:phone":"+1 814 793 2154",
    "sg:postcode":"16662",
    "sg:province":"PA",
    "sg:tags":[
        "trust"
    ],
    "wof:name":"Omega Bank Na",
    "wof:placetype":"venue"
},
  "geometry": {"coordinates":[-78.32508900000001,40.3113],"type":"Point"}
}