{
  "type": "Feature",
  "properties": {
    "addr:full":"152 Mt Pleasant Rd Mt Pleasant PA 15666",
    "addr:housenumber":"152",
    "addr:postcode":"15666",
    "addr:street":"Mt Pleasant Rd",
    "iso:country":"US",
    "sg:address":"152 Mt Pleasant Rd",
    "sg:city":"Mt Pleasant",
    "sg:classifiers":[
        {
            "category":"Building & Trades",
            "subcategory":"Construction",
            "type":"Services"
        }
    ],
    "sg:phone":"+1 724 547 3262",
    "sg:postcode":"15666",
    "sg:province":"PA",
    "sg:tags":[
        "general",
        "contractor"
    ],
    "wof:name":"Baird Construction",
    "wof:placetype":"venue"
},
  "geometry": {"coordinates":[-79.55599100000001,40.090346],"type":"Point"}
}