{
  "type": "Feature",
  "properties": {
    "iso:country":"US",
    "sg:address":"205 Fayette St",
    "sg:city":"Conshohocken",
    "sg:classifiers":[
        {
            "category":"Education",
            "subcategory":"School",
            "type":"Public Place"
        }
    ],
    "sg:phone":"+1 610 828 2007",
    "sg:postcode":"19428",
    "sg:province":"PA",
    "wof:name":"Conshohocken Catholic School",
    "wof:placetype":"venue"
},
  "geometry": {"coordinates":[-75.304558,40.075491],"type":"Point"}
}