{
  "type": "Feature",
  "properties": {
    "addr:full":"200 S Broad St Fl 3 Philadelphia PA 19102",
    "addr:housenumber":"200;3",
    "addr:postcode":"19102",
    "addr:street":"S Broad St",
    "iso:country":"US",
    "sg:address":"200 S Broad St Fl 3",
    "sg:city":"Philadelphia",
    "sg:classifiers":[
        {
            "category":"Real Estate",
            "subcategory":"Real Estate Services",
            "type":"Services"
        },
        {
            "category":"Real Estate",
            "subcategory":"Real Estate Agent",
            "type":"Services"
        }
    ],
    "sg:phone":"+1 215 875 0700",
    "sg:postcode":"19102",
    "sg:province":"PA",
    "sg:tags":[
        "buyer",
        "broker"
    ],
    "wof:name":"Preit-Rubin, Inc.",
    "wof:placetype":"venue"
},
  "geometry": {"coordinates":[-75.164253,39.949341],"type":"Point"}
}