{
  "type": "Feature",
  "properties": {
    "iso:country":"US",
    "sg:address":"134 S Washington St",
    "sg:city":"Wilkes Barre",
    "sg:classifiers":[
        {
            "category":"Social Services",
            "subcategory":"Child Care",
            "type":"Services"
        }
    ],
    "sg:phone":"+1   ",
    "sg:postcode":"18701",
    "sg:province":"PA",
    "sg:tags":[
        "day"
    ],
    "wof:name":"Kings & St Marys Dev Dcc",
    "wof:placetype":"venue"
},
  "geometry": {"coordinates":[-75.88567,41.241882],"type":"Point"}
}