{
  "type": "Feature",
  "properties": {
    "iso:country":"US",
    "sg:address":"5009 Woodbox Ln",
    "sg:city":"Mechanicsburg",
    "sg:classifiers":[
        {
            "category":"Professional",
            "type":"Services"
        }
    ],
    "sg:phone":"+1   ",
    "sg:postcode":"17055",
    "sg:province":"PA",
    "wof:name":"Jane Waite",
    "wof:placetype":"venue"
},
  "geometry": {"coordinates":[-76.95486099999999,40.199014],"type":"Point"}
}