{
  "type": "Feature",
  "properties": {
    "iso:country":"US",
    "sg:address":"3448 Garrett Rd",
    "sg:city":"Drexel Hill",
    "sg:classifiers":[
        {
            "category":"Retail",
            "subcategory":"Auto Repair",
            "type":"Services"
        }
    ],
    "sg:phone":"+1 610 622 2006",
    "sg:postcode":"19026",
    "sg:province":"PA",
    "sg:tags":[
        "repairing",
        "automotive",
        "automobile",
        "general"
    ],
    "wof:name":"Todd's Brake Shop Inc",
    "wof:placetype":"venue"
},
  "geometry": {"coordinates":[-75.293863,39.945816],"type":"Point"}
}