{
  "type": "Feature",
  "properties": {
    "addr:full":"312 Church St Jessup PA 18434",
    "addr:housenumber":"312",
    "addr:postcode":"18434",
    "addr:street":"Church St",
    "iso:country":"US",
    "sg:address":"312 Church St",
    "sg:city":"Jessup",
    "sg:classifiers":[
        {
            "category":"Bars & Pubs",
            "type":"Food & Drink"
        }
    ],
    "sg:phone":"+1   ",
    "sg:postcode":"18434",
    "sg:province":"PA",
    "sg:tags":[
        "drinking"
    ],
    "wof:name":"Schooners Pub",
    "wof:placetype":"venue"
},
  "geometry": {"coordinates":[-75.570764,41.474617],"type":"Point"}
}