{
  "type": "Feature",
  "properties": {
    "addr:full":"1169 Harwood Rd Bensalem PA 19020",
    "addr:housenumber":"1169",
    "addr:postcode":"19020",
    "addr:street":"Harwood Rd",
    "iso:country":"US",
    "sg:address":"1169 Harwood Rd",
    "sg:city":"Bensalem",
    "sg:classifiers":[
        {
            "category":"Shopping",
            "subcategory":"Clothing, Apparel, & Fashions",
            "type":"Retail Goods"
        }
    ],
    "sg:phone":"+1   ",
    "sg:postcode":"19020",
    "sg:province":"PA",
    "sg:tags":[
        "wear"
    ],
    "wof:name":"Just For You",
    "wof:placetype":"venue"
},
  "geometry": {"coordinates":[-74.91787600000001,40.108551],"type":"Point"}
}