{
  "type": "Feature",
  "properties": {
    "addr:full":"50 Peggy Cir Port Matilda PA 16870",
    "addr:housenumber":"50",
    "addr:postcode":"16870",
    "addr:street":"Peggy Cir",
    "iso:country":"US",
    "sg:address":"50 Peggy Cir",
    "sg:city":"Port Matilda",
    "sg:classifiers":[
        {
            "category":"Manufacturing",
            "subcategory":"Petroleum Products",
            "type":"Manufacturing & Wholesale Goods"
        },
        {
            "category":"Building & Trades",
            "subcategory":"Construction",
            "type":"Services"
        }
    ],
    "sg:phone":"+1 814 692 7797",
    "sg:postcode":"16870",
    "sg:province":"PA",
    "sg:tags":[
        "contractor",
        "paving",
        "asphalt",
        "mfg"
    ],
    "wof:name":"Beck's Paving",
    "wof:placetype":"venue"
},
  "geometry": {"coordinates":[-77.992835,40.801592],"type":"Point"}
}