{
  "type": "Feature",
  "properties": {
    "addr:full":"105 E Lancaster Ave Downingtown PA 19335",
    "addr:housenumber":"105",
    "addr:postcode":"19335",
    "addr:street":"E Lancaster Ave",
    "iso:country":"US",
    "sg:address":"105 E Lancaster Ave",
    "sg:city":"Downingtown",
    "sg:classifiers":[
        {
            "category":"Banks & Credit Unions",
            "subcategory":"Financial Services",
            "type":"Services"
        }
    ],
    "sg:phone":"+1   ",
    "sg:postcode":"19335",
    "sg:province":"PA",
    "sg:tags":[
        "investor"
    ],
    "wof:name":"Downingtown Investment Assoc",
    "wof:placetype":"venue"
},
  "geometry": {"coordinates":[-75.702427,40.006859],"type":"Point"}
}