{
  "type": "Feature",
  "properties": {
    "addr:full":"3328 Wilmington Rd New Castle PA 16105",
    "addr:housenumber":"3328",
    "addr:postcode":"16105",
    "addr:street":"Wilmington Rd New",
    "iso:country":"US",
    "sg:address":"3328 Wilmington Rd",
    "sg:city":"New Castle",
    "sg:classifiers":[
        {
            "category":"Shopping",
            "subcategory":"Discount & Variety Stores",
            "type":"Retail Goods"
        }
    ],
    "sg:phone":"+1 724 658 9444",
    "sg:postcode":"16105",
    "sg:province":"PA",
    "sg:tags":[
        "merchandise",
        "general"
    ],
    "wof:name":"Dollar Worth",
    "wof:placetype":"venue"
},
  "geometry": {"coordinates":[-80.35691300000001,41.045572],"type":"Point"}
}