{
  "type": "Feature",
  "properties": {
    "iso:country":"US",
    "sg:address":"2400 Old Washington Rd",
    "sg:city":"Pittsburgh",
    "sg:classifiers":[
        {
            "category":"Social Services",
            "subcategory":"Child Care",
            "type":"Services"
        }
    ],
    "sg:phone":"+1 412 835 3340",
    "sg:postcode":"15241",
    "sg:province":"PA",
    "sg:tags":[
        "elementary",
        "school",
        "day"
    ],
    "wof:name":"Montessori Early Childhood Center Inc",
    "wof:placetype":"venue"
},
  "geometry": {"coordinates":[-80.08290100000001,40.323399],"type":"Point"}
}