{
  "type": "Feature",
  "properties": {
    "addr:full":"2797 S Queen St Dallastown PA 17313",
    "addr:housenumber":"2797",
    "addr:postcode":"17313",
    "addr:street":"S Queen St",
    "iso:country":"US",
    "sg:address":"2797 S Queen St",
    "sg:city":"Dallastown",
    "sg:classifiers":[
        {
            "category":"Travel",
            "subcategory":"Hotels & Motels",
            "type":"Entertainment"
        }
    ],
    "sg:phone":"+1 717 741 5756",
    "sg:postcode":"17313",
    "sg:province":"PA",
    "sg:tags":[
        "operation"
    ],
    "wof:name":"Marriott",
    "wof:placetype":"venue"
},
  "geometry": {"coordinates":[-76.65835199999999,39.906846],"type":"Point"}
}