{
  "type": "Feature",
  "properties": {
    "iso:country":"US",
    "sg:address":"616 N Queen St",
    "sg:city":"Lancaster",
    "sg:classifiers":[
        {
            "category":"Building & Trades",
            "subcategory":"Construction",
            "type":"Services"
        }
    ],
    "sg:phone":"+1   ",
    "sg:postcode":"17603",
    "sg:province":"PA",
    "sg:tags":[
        "hanging",
        "contractor"
    ],
    "wof:name":"T Mickey Painting Co",
    "wof:placetype":"venue"
},
  "geometry": {"coordinates":[-76.307789,40.048656],"type":"Point"}
}