{
  "type": "Feature",
  "properties": {
    "iso:country":"US",
    "sg:address":"319 5th St",
    "sg:city":"Windber",
    "sg:classifiers":[
        {
            "category":"Retail",
            "subcategory":"Auto Repair",
            "type":"Services"
        }
    ],
    "sg:phone":"+1 814 467 6465",
    "sg:postcode":"15963",
    "sg:province":"PA",
    "sg:tags":[
        "body",
        "automobile",
        "painting",
        "repairing"
    ],
    "wof:name":"Evans Bob Auto Body",
    "wof:placetype":"venue"
},
  "geometry": {"coordinates":[-78.841752,40.240502],"type":"Point"}
}