{
  "type": "Feature",
  "properties": {
    "iso:country":"US",
    "sg:address":"600 Hidden Valley Rd",
    "sg:city":"King Of Prussia",
    "sg:classifiers":[
        {
            "category":"Professional",
            "subcategory":"Accounting & Tax Preparation",
            "type":"Services"
        }
    ],
    "sg:phone":"+1   ",
    "sg:postcode":"19406",
    "sg:province":"PA",
    "sg:tags":[
        "auditing",
        "investment",
        "bookkeeping"
    ],
    "wof:name":"A Gibbs Assoc PC",
    "wof:placetype":"venue"
},
  "geometry": {"coordinates":[-75.37437300000001,40.10759],"type":"Point"}
}