{
  "type": "Feature",
  "properties": {
    "iso:country":"US",
    "sg:address":"123 S Broad St Ste 1840",
    "sg:city":"Philadelphia",
    "sg:classifiers":[
        {
            "category":"Professional",
            "subcategory":"Lawyer & Legal Services",
            "type":"Services"
        }
    ],
    "sg:phone":"+1 215 735 3090",
    "sg:postcode":"19109",
    "sg:province":"PA",
    "wof:name":"Harper & Driver",
    "wof:placetype":"venue"
},
  "geometry": {"coordinates":[-75.163994,39.950087],"type":"Point"}
}