{
  "type": "Feature",
  "properties": {
    "iso:country":"US",
    "sg:address":"304 N Allegheny St",
    "sg:city":"Bellefonte",
    "sg:classifiers":[
        {
            "category":"Personal",
            "subcategory":"Beauty Salon",
            "type":"Services"
        }
    ],
    "sg:phone":"+1 814 355 4064",
    "sg:postcode":"16823",
    "sg:province":"PA",
    "wof:name":"Sylvia's Beauty Salon",
    "wof:placetype":"venue"
},
  "geometry": {"coordinates":[-77.77919900000001,40.915782],"type":"Point"}
}