{
  "type": "Feature",
  "properties": {
    "iso:country":"US",
    "sg:address":"745 N Highland Ave",
    "sg:city":"Pittsburgh",
    "sg:classifiers":[
        {
            "category":"Health Services",
            "subcategory":"Nursing And Care Facility",
            "type":"Services"
        }
    ],
    "sg:phone":"+1 412 362 6622",
    "sg:postcode":"15206",
    "sg:province":"PA",
    "sg:tags":[
        "home",
        "convalescent"
    ],
    "sg:website":"www.grane.com",
    "wof:name":"Highland Park Ctr",
    "wof:placetype":"venue"
},
  "geometry": {"coordinates":[-79.921228,40.469384],"type":"Point"}
}