{
  "type": "Feature",
  "properties": {
    "iso:country":"US",
    "sg:address":"1070 Berkshire Blvd",
    "sg:city":"Reading",
    "sg:classifiers":[
        {
            "category":"Home & Garden",
            "subcategory":"Furniture",
            "type":"Retail Goods"
        }
    ],
    "sg:phone":"+1 610 371 9350",
    "sg:postcode":"19610",
    "sg:province":"PA",
    "sg:tags":[
        "bedding",
        "bed"
    ],
    "wof:name":"Rockaway Bedding Inc",
    "wof:placetype":"venue"
},
  "geometry": {"coordinates":[-75.973079,40.345375],"type":"Point"}
}