{
  "type": "Feature",
  "properties": {
    "addr:full":"2267 High St Elizabethtown PA 17022",
    "addr:housenumber":"2267",
    "addr:postcode":"17022",
    "addr:street":"High St",
    "iso:country":"US",
    "sg:address":"2267 High St",
    "sg:city":"Elizabethtown",
    "sg:classifiers":[
        {
            "category":"Building & Trades",
            "subcategory":"Construction",
            "type":"Services"
        }
    ],
    "sg:phone":"+1   ",
    "sg:postcode":"17022",
    "sg:province":"PA",
    "sg:tags":[
        "house"
    ],
    "wof:name":"J L Woods Construction",
    "wof:placetype":"venue"
},
  "geometry": {"coordinates":[-76.565459,40.122849],"type":"Point"}
}