{
  "type": "Feature",
  "properties": {
    "iso:country":"US",
    "sg:address":"608 S Main St",
    "sg:city":"Chambersburg",
    "sg:classifiers":[
        {
            "category":"Personal",
            "subcategory":"Beauty Salon",
            "type":"Services"
        }
    ],
    "sg:phone":"+1   ",
    "sg:postcode":"17201",
    "sg:province":"PA",
    "sg:tags":[
        "shop"
    ],
    "wof:name":"Above & Beyond Salon",
    "wof:placetype":"venue"
},
  "geometry": {"coordinates":[-77.663167,39.928347],"type":"Point"}
}