{
  "type": "Feature",
  "properties": {
    "iso:country":"US",
    "sg:address":"3809 Jewell Ave",
    "sg:city":"Downingtown",
    "sg:classifiers":[
        {
            "category":"Home & Garden",
            "subcategory":"Furniture",
            "type":"Retail Goods"
        }
    ],
    "sg:phone":"+1 610 384 6265",
    "sg:postcode":"19335",
    "sg:province":"PA",
    "sg:tags":[
        "equipment",
        "kitchen",
        "cabinet"
    ],
    "wof:name":"Beacon Design",
    "wof:placetype":"venue"
},
  "geometry": {"coordinates":[-75.74706999999999,39.991117],"type":"Point"}
}