{
  "type": "Feature",
  "properties": {
    "iso:country":"US",
    "sg:address":"1966 Newport Rd",
    "sg:city":"Manheim",
    "sg:classifiers":[
        {
            "category":"Insurance",
            "subcategory":"Insurance Agent",
            "type":"Services"
        }
    ],
    "sg:phone":"+1 717 664 2384",
    "sg:postcode":"17545",
    "sg:province":"PA",
    "wof:name":"G E Financial-Ed Nissley",
    "wof:placetype":"venue"
},
  "geometry": {"coordinates":[-76.392989,40.205816],"type":"Point"}
}