{
  "type": "Feature",
  "properties": {
    "iso:country":"US",
    "sg:address":"4755 Linglestown Rd",
    "sg:city":"Harrisburg",
    "sg:classifiers":[
        {
            "category":"Professional",
            "subcategory":"Management & Consulting",
            "type":"Services"
        },
        {
            "category":"Banks & Credit Unions",
            "subcategory":"Financial Services",
            "type":"Services"
        }
    ],
    "sg:phone":"+1 717 545 5375",
    "sg:postcode":"17112",
    "sg:province":"PA",
    "sg:tags":[
        "consultant",
        "financing",
        "planning"
    ],
    "wof:name":"Weigel Financial Services",
    "wof:placetype":"venue"
},
  "geometry": {"coordinates":[-76.815022,40.337196],"type":"Point"}
}