{
  "type": "Feature",
  "properties": {
    "iso:country":"US",
    "sg:address":"500 Galleria Dr",
    "sg:city":"Johnstown",
    "sg:classifiers":[
        {
            "category":"Restaurant",
            "type":"Food & Drink"
        }
    ],
    "sg:menulink":"http://www.allmenus.com/pa/richland/82871-villa-pizza/menu/",
    "sg:phone":"+1 814 262 0348",
    "sg:postcode":"15904",
    "sg:province":"PA",
    "sg:tags":[
        "american",
        "italian",
        "pizza"
    ],
    "wof:name":"Villa Pizza",
    "wof:placetype":"venue"
},
  "geometry": {"coordinates":[-78.83655,40.296427],"type":"Point"}
}