{
  "type": "Feature",
  "properties": {
    "addr:full":"120 Stony Ln Dover PA 17315",
    "addr:housenumber":"120",
    "addr:postcode":"17315",
    "addr:street":"Stony Ln",
    "iso:country":"US",
    "sg:address":"120 Stony Ln",
    "sg:city":"Dover",
    "sg:classifiers":[
        {
            "category":"Professional",
            "type":"Services"
        }
    ],
    "sg:phone":"+1 717 292 1202",
    "sg:postcode":"17315",
    "sg:province":"PA",
    "sg:tags":[
        "establishment"
    ],
    "wof:name":"Mormon Elders",
    "wof:placetype":"venue"
},
  "geometry": {"coordinates":[-76.858069,40.001839],"type":"Point"}
}