{
  "type": "Feature",
  "properties": {
    "addr:full":"240 Alpha Dr Pittsburgh PA 15238",
    "addr:housenumber":"240",
    "addr:postcode":"15238",
    "addr:street":"Alpha Dr",
    "iso:country":"US",
    "sg:address":"240 Alpha Dr",
    "sg:city":"Pittsburgh",
    "sg:classifiers":[
        {
            "category":"Manufacturing",
            "subcategory":"Tools & Machinery",
            "type":"Manufacturing & Wholesale Goods"
        }
    ],
    "sg:phone":"+1   ",
    "sg:postcode":"15238",
    "sg:province":"PA",
    "sg:tags":[
        "instrument",
        "medical",
        "mfg"
    ],
    "wof:name":"Cardiac Assist Inc",
    "wof:placetype":"venue"
},
  "geometry": {"coordinates":[-79.871444,40.491934],"type":"Point"}
}