{
  "type": "Feature",
  "properties": {
    "addr:full":"169 Christian Hill Rd Milford PA 18337",
    "addr:housenumber":"169",
    "addr:postcode":"18337",
    "addr:street":"Christian Hill Rd",
    "iso:country":"US",
    "sg:address":"169 Christian Hill Rd",
    "sg:city":"Milford",
    "sg:classifiers":[
        {
            "category":"Professional",
            "subcategory":"Research",
            "type":"Services"
        }
    ],
    "sg:phone":"+1 570 296 6351",
    "sg:postcode":"18337",
    "sg:province":"PA",
    "sg:tags":[
        "environmental",
        "ecological"
    ],
    "wof:name":"Environmental Service Systems",
    "wof:placetype":"venue"
},
  "geometry": {"coordinates":[-74.82064699999999,41.322753],"type":"Point"}
}