{
  "type": "Feature",
  "properties": {
    "iso:country":"US",
    "sg:address":"7034 Ely Rd",
    "sg:city":"New Hope",
    "sg:classifiers":[
        {
            "category":"Health Services",
            "subcategory":"Doctor",
            "type":"Services"
        },
        {
            "category":"Health Services",
            "subcategory":"Clinic",
            "type":"Services"
        }
    ],
    "sg:phone":"+1 215 862 5161",
    "sg:postcode":"18938",
    "sg:province":"PA",
    "sg:tags":[
        "counseling",
        "mental"
    ],
    "wof:name":"Caffentzis Wilma PHD",
    "wof:placetype":"venue"
},
  "geometry": {"coordinates":[-74.97605799999999,40.39114],"type":"Point"}
}