{
  "type": "Feature",
  "properties": {
    "iso:country":"US",
    "sg:address":"60 Duncan Ln",
    "sg:city":"Springfield",
    "sg:classifiers":[
        {
            "category":"Building & Trades",
            "subcategory":"Landscaping Services",
            "type":"Services"
        }
    ],
    "sg:phone":"+1 610 328 0437",
    "sg:postcode":"19064",
    "sg:province":"PA",
    "sg:tags":[
        "landscape",
        "contractor"
    ],
    "wof:name":"Burke Landscaping",
    "wof:placetype":"venue"
},
  "geometry": {"coordinates":[-75.342275,39.935085],"type":"Point"}
}