{
  "type": "Feature",
  "properties": {
    "iso:country":"US",
    "sg:address":"72 Tuscarawas Rd",
    "sg:city":"Beaver",
    "sg:classifiers":[
        {
            "category":"Autos & Motor Vehicles",
            "subcategory":"Auto Supplies",
            "type":"Retail Goods"
        }
    ],
    "sg:phone":"+1   ",
    "sg:postcode":"15009",
    "sg:province":"PA",
    "sg:tags":[
        "automotive",
        "general",
        "tire",
        "repair"
    ],
    "wof:name":"Crawford Tire Service Inc",
    "wof:placetype":"venue"
},
  "geometry": {"coordinates":[-80.315524,40.693296],"type":"Point"}
}