{
  "type": "Feature",
  "properties": {
    "iso:country":"US",
    "sg:address":"259 Lebanon Ave",
    "sg:city":"Mt Lebanon",
    "sg:classifiers":[
        {
            "category":"Professional",
            "subcategory":"Engineering",
            "type":"Services"
        }
    ],
    "sg:phone":"+1 412 561 2021",
    "sg:postcode":"15228",
    "sg:province":"PA",
    "sg:tags":[
        "engineer"
    ],
    "wof:name":"P S Systems",
    "wof:placetype":"venue"
},
  "geometry": {"coordinates":[-80.050072,40.377152],"type":"Point"}
}