{
  "type": "Feature",
  "properties": {
    "iso:country":"US",
    "sg:address":"1127 Eichelberger St",
    "sg:city":"Hanover",
    "sg:classifiers":[
        {
            "category":"Banks & Credit Unions",
            "subcategory":"Bank",
            "type":"Services"
        }
    ],
    "sg:phone":"+1 717 633 6200",
    "sg:postcode":"17331",
    "sg:province":"PA",
    "wof:name":"Adams County National Bank",
    "wof:placetype":"venue"
},
  "geometry": {"coordinates":[-76.991131,39.820115],"type":"Point"}
}