{
  "type": "Feature",
  "properties": {
    "iso:country":"US",
    "sg:address":"129 E Market St",
    "sg:city":"Williamstown",
    "sg:classifiers":[
        {
            "category":"Health Services",
            "subcategory":"Chiropractor",
            "type":"Services"
        }
    ],
    "sg:phone":"+1 717 647 7477",
    "sg:postcode":"17098",
    "sg:province":"PA",
    "wof:name":"Williamstown Chiropractic Ctr",
    "wof:placetype":"venue"
},
  "geometry": {"coordinates":[-76.61640800000001,40.580178],"type":"Point"}
}