{
  "type": "Feature",
  "properties": {
    "addr:full":"615 South St Philadelphia PA 19147",
    "addr:housenumber":"615",
    "addr:postcode":"19147",
    "addr:street":"South St",
    "iso:country":"US",
    "sg:address":"615 South St",
    "sg:city":"Philadelphia",
    "sg:classifiers":[
        {
            "category":"Coffee & Tea",
            "type":"Food & Drink"
        }
    ],
    "sg:phone":"+1 215 629 2250",
    "sg:postcode":"19147",
    "sg:province":"PA",
    "sg:website":"www.the-coffee-bean-cafe.com",
    "wof:name":"The Bean Cafe",
    "wof:placetype":"venue"
},
  "geometry": {"coordinates":[-75.152496,39.942001],"type":"Point"}
}