{
  "type": "Feature",
  "properties": {
    "iso:country":"US",
    "sg:address":"1398 N Chester Rd",
    "sg:city":"West Chester",
    "sg:classifiers":[
        {
            "category":"Professional",
            "subcategory":"Management & Consulting",
            "type":"Services"
        }
    ],
    "sg:phone":"+1 610 696 1905",
    "sg:postcode":"19355",
    "sg:province":"PA",
    "sg:tags":[
        "consultant",
        "business"
    ],
    "sg:website":"www.brandywineconsulting.com",
    "wof:name":"Brandywine Consulting Group",
    "wof:placetype":"venue"
},
  "geometry": {"coordinates":[-75.547973,40.020354],"type":"Point"}
}