{
  "type": "Feature",
  "properties": {
    "iso:country":"US",
    "sg:address":"480 W Broad St",
    "sg:city":"Hazleton",
    "sg:classifiers":[
        {
            "category":"Retail",
            "subcategory":"Funeral Services",
            "type":"Services"
        }
    ],
    "sg:phone":"+1 570 454 0251",
    "sg:postcode":"18201",
    "sg:province":"PA",
    "sg:tags":[
        "director"
    ],
    "wof:name":"John J Pusti Funeral Home",
    "wof:placetype":"venue"
},
  "geometry": {"coordinates":[-75.98211999999999,40.956227],"type":"Point"}
}