{
  "type": "Feature",
  "properties": {
    "iso:country":"US",
    "sg:address":"150 Market St",
    "sg:city":"Lehman",
    "sg:classifiers":[
        {
            "category":"Shopping",
            "subcategory":"Used Merchandise",
            "type":"Retail Goods"
        }
    ],
    "sg:phone":"+1 570 675 1025",
    "sg:postcode":"18612",
    "sg:province":"PA",
    "sg:tags":[
        "antique"
    ],
    "wof:name":"Barn",
    "wof:placetype":"venue"
},
  "geometry": {"coordinates":[-76.009365,41.30897],"type":"Point"}
}