{
  "type": "Feature",
  "properties": {
    "iso:country":"US",
    "sg:address":"3001 Philmont Ave",
    "sg:city":"Huntingdon Vly",
    "sg:classifiers":[
        {
            "category":"Banks & Credit Unions",
            "subcategory":"Investment Brokerage",
            "type":"Services"
        }
    ],
    "sg:phone":"+1 215 938 9092",
    "sg:postcode":"19006",
    "sg:province":"PA",
    "sg:tags":[
        "advisory",
        "financial"
    ],
    "wof:name":"Money Tree Capital Group",
    "wof:placetype":"venue"
},
  "geometry": {"coordinates":[-75.040509,40.123994],"type":"Point"}
}