{
  "type": "Feature",
  "properties": {
    "addr:full":"1200 N Wales Rd North Wales PA 19454",
    "addr:housenumber":"1200",
    "addr:postcode":"19454",
    "addr:street":"N Wales Rd",
    "iso:country":"US",
    "sg:address":"1200 N Wales Rd",
    "sg:city":"North Wales",
    "sg:classifiers":[
        {
            "category":"Shopping",
            "subcategory":"Department Store",
            "type":"Retail Goods"
        }
    ],
    "sg:phone":"+1 215 412 4597",
    "sg:postcode":"19454",
    "sg:province":"PA",
    "sg:tags":[
        "shop"
    ],
    "sg:website":"www.dollartree.com",
    "wof:name":"Dollar Tree",
    "wof:placetype":"venue"
},
  "geometry": {"coordinates":[-75.272047,40.220188],"type":"Point"}
}