{
  "type": "Feature",
  "properties": {
    "iso:country":"US",
    "sg:address":"204 Kenmar Dr",
    "sg:city":"Monroeville",
    "sg:classifiers":[
        {
            "category":"Education",
            "subcategory":"Dance Studio",
            "type":"Public Place"
        }
    ],
    "sg:phone":"+1 412 373 5020",
    "sg:postcode":"15146",
    "sg:province":"PA",
    "sg:tags":[
        "instruction",
        "dancing"
    ],
    "sg:website":"http://www.mmdance.com",
    "wof:name":"M & M Dance Academy",
    "wof:placetype":"venue"
},
  "geometry": {"coordinates":[-79.764745,40.440332],"type":"Point"}
}