{
  "type": "Feature",
  "properties": {
    "addr:full":"108 S 20th Street Philadelphia PA 19103",
    "addr:housenumber":"108",
    "addr:postcode":"19103",
    "addr:street":"S 20Th Street",
    "iso:country":"US",
    "sg:address":"108 S 20th Street",
    "sg:city":"Philadelphia",
    "sg:classifiers":[
        {
            "category":"Arts & Performance",
            "subcategory":"Art Gallery",
            "type":"Entertainment"
        },
        {
            "category":"Shopping",
            "subcategory":"Jewelry",
            "type":"Retail Goods"
        },
        {
            "category":"Arts & Performance",
            "subcategory":"Arts Center",
            "type":"Entertainment"
        }
    ],
    "sg:phone":"+1 215 360 5548",
    "sg:postcode":"19103",
    "sg:province":"PA",
    "sg:website":"www.squarepegartery.com",
    "wof:name":"Square Peg Artery and Salvage",
    "wof:placetype":"venue"
},
  "geometry": {"coordinates":[-75.173563,39.951687],"type":"Point"}
}