{
  "type": "Feature",
  "properties": {
    "addr:full":"1609 Harmer St Levittown PA 19057",
    "addr:housenumber":"1609",
    "addr:postcode":"19057",
    "addr:street":"Harmer St Levittown",
    "iso:country":"US",
    "sg:address":"1609 Harmer St",
    "sg:city":"Levittown",
    "sg:classifiers":[
        {
            "category":"Retail",
            "subcategory":"Auto Repair",
            "type":"Services"
        }
    ],
    "sg:phone":"+1 215 943 4510",
    "sg:postcode":"19057",
    "sg:province":"PA",
    "sg:tags":[
        "repairing",
        "automobile",
        "general"
    ],
    "wof:name":"US 1 Automotive Restyling",
    "wof:placetype":"venue"
},
  "geometry": {"coordinates":[-74.839821,40.12885],"type":"Point"}
}