{
  "type": "Feature",
  "properties": {
    "addr:full":"4 Hook Rd Glenolden PA 19056",
    "addr:housenumber":"4",
    "addr:postcode":"19056",
    "addr:street":"Hook Rd",
    "iso:country":"US",
    "sg:address":"4 Hook Rd",
    "sg:city":"Glenolden",
    "sg:classifiers":[
        {
            "category":"Health Services",
            "subcategory":"Doctor",
            "type":"Services"
        }
    ],
    "sg:phone":"+1 610 583 2351",
    "sg:postcode":"19056",
    "sg:province":"PA",
    "sg:tags":[
        "physician",
        "surgeon"
    ],
    "wof:name":"Us Neurology Corp",
    "wof:placetype":"venue"
},
  "geometry": {"coordinates":[-74.896373,40.165063],"type":"Point"}
}