{
  "type": "Feature",
  "properties": {
    "iso:country":"US",
    "sg:address":"1109 Main St",
    "sg:city":"Dickson City",
    "sg:classifiers":[
        {
            "category":"Home & Garden",
            "subcategory":"Building Materials",
            "type":"Retail Goods"
        }
    ],
    "sg:phone":"+1 570 342 3056",
    "sg:postcode":"18519",
    "sg:province":"PA",
    "sg:tags":[
        "door"
    ],
    "sg:website":"www.alldoorsales.com",
    "wof:name":"All Door Sales Co",
    "wof:placetype":"venue"
},
  "geometry": {"coordinates":[-75.61720800000001,41.465835],"type":"Point"}
}