{
  "type": "Feature",
  "properties": {
    "iso:country":"US",
    "sg:address":"2 S Plum St",
    "sg:city":"Media",
    "sg:classifiers":[
        {
            "category":"Professional",
            "subcategory":"Lawyer & Legal Services",
            "type":"Services"
        }
    ],
    "sg:phone":"+1   ",
    "sg:postcode":"19063",
    "sg:province":"PA",
    "wof:name":"Murphy & Carmen",
    "wof:placetype":"venue"
},
  "geometry": {"coordinates":[-75.390169,39.918545],"type":"Point"}
}