{
  "type": "Feature",
  "properties": {
    "addr:full":"4934 Peach St Erie PA 16509",
    "addr:housenumber":"4934",
    "addr:postcode":"16509",
    "addr:street":"Peach St",
    "iso:country":"US",
    "sg:address":"4934 Peach St",
    "sg:city":"Erie",
    "sg:classifiers":[
        {
            "category":"Health Services",
            "subcategory":"Doctor",
            "type":"Services"
        }
    ],
    "sg:phone":"+1 814 868 8673",
    "sg:postcode":"16509",
    "sg:province":"PA",
    "sg:tags":[
        "dentist"
    ],
    "wof:name":"Pediatric Dentistry",
    "wof:placetype":"venue"
},
  "geometry": {"coordinates":[-80.08999799999999,42.081827],"type":"Point"}
}