{
  "type": "Feature",
  "properties": {
    "addr:full":"220 N Broad St Lansdale PA 19446",
    "addr:housenumber":"220",
    "addr:postcode":"19446",
    "addr:street":"N Broad St",
    "iso:country":"US",
    "sg:address":"220 N Broad St",
    "sg:city":"Lansdale",
    "sg:classifiers":[
        {
            "category":"Arts & Performance",
            "subcategory":"Dance",
            "type":"Entertainment"
        }
    ],
    "sg:phone":"+1 215 368 8785",
    "sg:postcode":"19446",
    "sg:province":"PA",
    "sg:tags":[
        "instruction",
        "dancing"
    ],
    "sg:website":"http://www.newdanceworkshop.com",
    "wof:name":"Abramson Marlyn School Of Dance",
    "wof:placetype":"venue"
},
  "geometry": {"coordinates":[-75.282819,40.24245],"type":"Point"}
}