{
  "type": "Feature",
  "properties": {
    "iso:country":"US",
    "sg:address":"4247 Union Deposit Rd",
    "sg:city":"Harrisburg",
    "sg:classifiers":[
        {
            "category":"Shopping",
            "subcategory":"Clothing, Apparel, & Fashions",
            "type":"Retail Goods"
        }
    ],
    "sg:phone":"+1 717 561 9992",
    "sg:postcode":"17111",
    "sg:province":"PA",
    "sg:tags":[
        "department",
        "family",
        "store"
    ],
    "wof:name":"Burlington Coat Factory",
    "wof:placetype":"venue"
},
  "geometry": {"coordinates":[-76.815572,40.278953],"type":"Point"}
}