{
  "type": "Feature",
  "properties": {
    "iso:country":"US",
    "sg:address":"498 Anna Lynn Ln",
    "sg:city":"Horsham",
    "sg:classifiers":[
        {
            "category":"Wholesale",
            "subcategory":"Metals & Minerals",
            "type":"Manufacturing & Wholesale Goods"
        }
    ],
    "sg:phone":"+1 215 654 8100",
    "sg:postcode":"19044",
    "sg:province":"PA",
    "sg:tags":[
        "lead"
    ],
    "wof:name":"Environmental Protection Inspe",
    "wof:placetype":"venue"
},
  "geometry": {"coordinates":[-75.167422,40.173496],"type":"Point"}
}