{
  "type": "Feature",
  "properties": {
    "addr:full":"22 State Rte 487 Benton PA 17814",
    "addr:housenumber":"22",
    "addr:postcode":"17814",
    "addr:street":"State Rte 487",
    "iso:country":"US",
    "sg:address":"22 State Rte 487",
    "sg:city":"Benton",
    "sg:classifiers":[
        {
            "category":"Travel",
            "subcategory":"Campground",
            "type":"Entertainment"
        }
    ],
    "sg:phone":"+1 570 925 5039",
    "sg:postcode":"17814",
    "sg:province":"PA",
    "wof:name":"Red Rock Mountain Campground",
    "wof:placetype":"venue"
},
  "geometry": {"coordinates":[-76.38366499999999,41.193592],"type":"Point"}
}