{
  "type": "Feature",
  "properties": {
    "iso:country":"US",
    "sg:address":"210 Water Forest Dr",
    "sg:city":"Dingmans Ferry",
    "sg:classifiers":[
        {
            "category":"Professional",
            "subcategory":"Management & Consulting",
            "type":"Services"
        }
    ],
    "sg:phone":"+1 570 686 9867",
    "sg:postcode":"18337",
    "sg:province":"PA",
    "sg:tags":[
        "food"
    ],
    "wof:name":"Woods Food Svc",
    "wof:placetype":"venue"
},
  "geometry": {"coordinates":[-74.912144,41.292739],"type":"Point"}
}