{
  "type": "Feature",
  "properties": {
    "iso:country":"US",
    "sg:address":"157 S Broad St",
    "sg:city":"Grove City",
    "sg:classifiers":[
        {
            "category":"Shopping",
            "type":"Retail Goods"
        }
    ],
    "sg:phone":"+1   ",
    "sg:postcode":"16127",
    "sg:province":"PA",
    "sg:tags":[
        "merchandise"
    ],
    "wof:name":"Creative Framing",
    "wof:placetype":"venue"
},
  "geometry": {"coordinates":[-80.086429,41.160489],"type":"Point"}
}