{
  "type": "Feature",
  "properties": {
    "iso:country":"US",
    "sg:address":"116 Keystone Dr",
    "sg:city":"Montgomeryville",
    "sg:classifiers":[
        {
            "category":"Wholesale",
            "subcategory":"Electrical",
            "type":"Manufacturing & Wholesale Goods"
        }
    ],
    "sg:phone":"+1   ",
    "sg:postcode":"18936",
    "sg:province":"PA",
    "wof:name":"Lochinvar Corporation",
    "wof:placetype":"venue"
},
  "geometry": {"coordinates":[-75.236098,40.214287],"type":"Point"}
}