{
  "type": "Feature",
  "properties": {
    "addr:full":"121 N Cedar Crest Blvd Allentown PA 18104",
    "addr:housenumber":"121",
    "addr:postcode":"18104",
    "addr:street":"N Cedar Crest Blvd",
    "iso:country":"US",
    "sg:address":"121 N Cedar Crest Blvd",
    "sg:city":"Allentown",
    "sg:classifiers":[
        {
            "category":"Insurance",
            "subcategory":"Insurance Agent",
            "type":"Services"
        }
    ],
    "sg:phone":"+1 610 432 6881",
    "sg:postcode":"18104",
    "sg:province":"PA",
    "sg:tags":[
        "notary"
    ],
    "wof:name":"Heydt Insurance Agency",
    "wof:placetype":"venue"
},
  "geometry": {"coordinates":[-75.5252,40.590401],"type":"Point"}
}