{
  "type": "Feature",
  "properties": {
    "iso:country":"US",
    "sg:address":"4345 Frankford Ave",
    "sg:city":"Philadelphia",
    "sg:classifiers":[
        {
            "category":"Organizations",
            "subcategory":"Labor Organization",
            "type":"Services"
        }
    ],
    "sg:phone":"+1 215 288 1430",
    "sg:postcode":"19124",
    "sg:province":"PA",
    "wof:name":"Teamsters Local Union 929 Inc",
    "wof:placetype":"venue"
},
  "geometry": {"coordinates":[-75.088418,40.011359],"type":"Point"}
}