{
  "type": "Feature",
  "properties": {
    "iso:country":"US",
    "sg:address":"225 W Spring St",
    "sg:city":"Titusville",
    "sg:classifiers":[
        {
            "category":"Home & Garden",
            "subcategory":"Building Materials",
            "type":"Retail Goods"
        }
    ],
    "sg:phone":"+1 814 827 1953",
    "sg:postcode":"16354",
    "sg:province":"PA",
    "sg:tags":[
        "wallpaper"
    ],
    "wof:name":"Robinson's Interiors",
    "wof:placetype":"venue"
},
  "geometry": {"coordinates":[-79.673343,41.626452],"type":"Point"}
}