{
  "type": "Feature",
  "properties": {
    "addr:full":"1302 Philadelphia St Indiana PA 15701",
    "addr:housenumber":"1302",
    "addr:postcode":"15701",
    "addr:street":"Philadelphia St",
    "iso:country":"US",
    "sg:address":"1302 Philadelphia St",
    "sg:city":"Indiana",
    "sg:classifiers":[
        {
            "category":"Shopping",
            "subcategory":"Musical Instruments",
            "type":"Retail Goods"
        }
    ],
    "sg:phone":"+1 724 463 7707",
    "sg:postcode":"15701",
    "sg:province":"PA",
    "wof:name":"Drawl's Strings & Things",
    "wof:placetype":"venue"
},
  "geometry": {"coordinates":[-79.16696899999999,40.62319],"type":"Point"}
}