{
  "type": "Feature",
  "properties": {
    "iso:country":"US",
    "sg:address":"100 Billott Ave",
    "sg:city":"Irwin",
    "sg:classifiers":[
        {
            "category":"Organizations",
            "subcategory":"Community Association",
            "type":"Services"
        }
    ],
    "sg:phone":"+1   ",
    "sg:postcode":"15642",
    "sg:province":"PA",
    "wof:name":"VFW",
    "wof:placetype":"venue"
},
  "geometry": {"coordinates":[-79.71858400000001,40.326896],"type":"Point"}
}