{
  "type": "Feature",
  "properties": {
    "iso:country":"US",
    "sg:address":"PO Box 46312",
    "sg:city":"Philadelphia",
    "sg:classifiers":[
        {
            "category":"Social Services",
            "subcategory":"Child Care",
            "type":"Services"
        }
    ],
    "sg:phone":"+1 215 455 6741",
    "sg:postcode":"19160",
    "sg:province":"PA",
    "sg:tags":[
        "day"
    ],
    "wof:name":"Afro-Centric-Christian Educational Day Care",
    "wof:placetype":"venue"
},
  "geometry": {"coordinates":[-75.125198,40.015999],"type":"Point"}
}