{
  "type": "Feature",
  "properties": {
    "addr:full":"127 S 3rd St Perkasie PA 18944",
    "addr:housenumber":"127",
    "addr:postcode":"18944",
    "addr:street":"S 3Rd St",
    "iso:country":"US",
    "sg:address":"127 S 3rd St",
    "sg:city":"Perkasie",
    "sg:classifiers":[
        {
            "category":"Building & Trades",
            "subcategory":"Construction",
            "type":"Services"
        }
    ],
    "sg:phone":"+1 215 257 6000",
    "sg:postcode":"18944",
    "sg:province":"PA",
    "sg:tags":[
        "fire",
        "restoration",
        "damage"
    ],
    "wof:name":"Service Master Of Bux-Mont",
    "wof:placetype":"venue"
},
  "geometry": {"coordinates":[-75.29520599999999,40.370014],"type":"Point"}
}