{
  "type": "Feature",
  "properties": {
    "addr:full":"1104 N Broad St Lansdale PA 19446",
    "addr:housenumber":"1104",
    "addr:postcode":"19446",
    "addr:street":"N Broad St",
    "iso:country":"US",
    "sg:address":"1104 N Broad St",
    "sg:city":"Lansdale",
    "sg:classifiers":[
        {
            "category":"Personal",
            "subcategory":"Nail Salon",
            "type":"Services"
        }
    ],
    "sg:phone":"+1 215 393 1202",
    "sg:postcode":"19446",
    "sg:province":"PA",
    "wof:name":"Kim Nails",
    "wof:placetype":"venue"
},
  "geometry": {"coordinates":[-75.275257,40.250372],"type":"Point"}
}