{
  "type": "Feature",
  "properties": {
    "addr:full":"115 S Providence Rd Wallingford PA 19086",
    "addr:housenumber":"115",
    "addr:postcode":"19086",
    "addr:street":"S Providence Rd",
    "iso:country":"US",
    "sg:address":"115 S Providence Rd",
    "sg:city":"Wallingford",
    "sg:classifiers":[
        {
            "category":"Health Services",
            "subcategory":"Nursing And Care Facility",
            "type":"Services"
        }
    ],
    "sg:phone":"+1 610 565 3232",
    "sg:postcode":"19086",
    "sg:province":"PA",
    "sg:tags":[
        "skilled"
    ],
    "wof:name":"Wallingford Nursing & Rehab",
    "wof:placetype":"venue"
},
  "geometry": {"coordinates":[-75.372659,39.898553],"type":"Point"}
}