{
  "type": "Feature",
  "properties": {
    "addr:full":"721 Court St Ste Frnt Scranton PA 18508",
    "addr:housenumber":"721",
    "addr:postcode":"18508",
    "addr:street":"Court St Ste Frnt",
    "iso:country":"US",
    "sg:address":"721 Court St Ste Frnt",
    "sg:city":"Scranton",
    "sg:classifiers":[
        {
            "category":"Restaurant",
            "type":"Food & Drink"
        }
    ],
    "sg:phone":"+1 570 963 9853",
    "sg:postcode":"18508",
    "sg:province":"PA",
    "sg:tags":[
        "pizza"
    ],
    "wof:name":"Pizza House",
    "wof:placetype":"venue"
},
  "geometry": {"coordinates":[-75.663433,41.427582],"type":"Point"}
}