{
  "type": "Feature",
  "properties": {
    "iso:country":"US",
    "sg:address":"1919 Creek Rd",
    "sg:city":"Bethlehem",
    "sg:classifiers":[
        {
            "category":"Building & Trades",
            "subcategory":"Electrical",
            "type":"Services"
        }
    ],
    "sg:phone":"+1   ",
    "sg:postcode":"18015",
    "sg:province":"PA",
    "sg:tags":[
        "underground",
        "installation",
        "cable"
    ],
    "wof:name":"Under Tech Cable",
    "wof:placetype":"venue"
},
  "geometry": {"coordinates":[-75.349271,40.586637],"type":"Point"}
}