{
  "type": "Feature",
  "properties": {
    "addr:full":"27 N 4th St Columbia PA 17512",
    "addr:housenumber":"27",
    "addr:postcode":"17512",
    "addr:street":"N 4Th St",
    "iso:country":"US",
    "sg:address":"27 N 4th St",
    "sg:city":"Columbia",
    "sg:classifiers":[
        {
            "category":"Government",
            "subcategory":"Fire Station",
            "type":"Public Place"
        }
    ],
    "sg:phone":"+1 717 684 9712",
    "sg:postcode":"17512",
    "sg:province":"PA",
    "sg:tags":[
        "department"
    ],
    "wof:name":"Keystone Truck & Chemical Co",
    "wof:placetype":"venue"
},
  "geometry": {"coordinates":[-76.50125300000001,40.033165],"type":"Point"}
}