{
  "type": "Feature",
  "properties": {
    "iso:country":"US",
    "sg:address":"7650 City Ave",
    "sg:city":"Philadelphia",
    "sg:classifiers":[
        {
            "category":"Restaurant",
            "type":"Food & Drink"
        }
    ],
    "sg:phone":"+1 215 477 3397",
    "sg:postcode":"19151",
    "sg:province":"PA",
    "wof:name":"Applebee's Neighborhood Grill",
    "wof:placetype":"venue"
},
  "geometry": {"coordinates":[-75.272592,39.978665],"type":"Point"}
}