{
  "type": "Feature",
  "properties": {
    "iso:country":"US",
    "sg:address":"5585 Stoney Hill Rd",
    "sg:city":"New Hope",
    "sg:classifiers":[
        {
            "category":"Wholesale",
            "subcategory":"Non-durable Goods",
            "type":"Manufacturing & Wholesale Goods"
        }
    ],
    "sg:phone":"+1   ",
    "sg:postcode":"18938",
    "sg:province":"PA",
    "sg:tags":[
        "advertising",
        "specialty"
    ],
    "wof:name":"Horse Show Affiliates",
    "wof:placetype":"venue"
},
  "geometry": {"coordinates":[-75.005242,40.332156],"type":"Point"}
}