{
  "type": "Feature",
  "properties": {
    "iso:country":"US",
    "sg:address":"5 Creamery Rd",
    "sg:city":"Reinholds",
    "sg:classifiers":[
        {
            "category":"Retail",
            "subcategory":"Auto Repair",
            "type":"Services"
        }
    ],
    "sg:phone":"+1 717 336 7972",
    "sg:postcode":"17569",
    "sg:province":"PA",
    "sg:tags":[
        "repairing",
        "automobile"
    ],
    "wof:name":"Eli Fisher's Garage",
    "wof:placetype":"venue"
},
  "geometry": {"coordinates":[-76.116118,40.263445],"type":"Point"}
}