{
  "type": "Feature",
  "properties": {
    "iso:country":"US",
    "sg:address":"552 Colbert Ave",
    "sg:city":"Oil City",
    "sg:classifiers":[
        {
            "category":"Shopping",
            "subcategory":"Florist",
            "type":"Retail Goods"
        }
    ],
    "sg:phone":"+1 814 677 3028",
    "sg:postcode":"16301",
    "sg:province":"PA",
    "wof:name":"Sloan's Florist",
    "wof:placetype":"venue"
},
  "geometry": {"coordinates":[-79.69380700000001,41.420609],"type":"Point"}
}