{
  "type": "Feature",
  "properties": {
    "addr:full":"415 Joffre Cherry Valley Rd Burgettstown PA 15021",
    "addr:housenumber":"415",
    "addr:postcode":"15021",
    "addr:street":"Joffre Cherry Valley Rd",
    "iso:country":"US",
    "sg:address":"415 Joffre Cherry Valley Rd",
    "sg:city":"Burgettstown",
    "sg:classifiers":[
        {
            "category":"Building & Trades",
            "subcategory":"Construction",
            "type":"Services"
        }
    ],
    "sg:phone":"+1 724 947 9456",
    "sg:postcode":"15021",
    "sg:province":"PA",
    "sg:tags":[
        "marking",
        "maintenance",
        "parking"
    ],
    "wof:name":"Smith Twp Road Dept",
    "wof:placetype":"venue"
},
  "geometry": {"coordinates":[-80.344537,40.351082],"type":"Point"}
}