{
  "type": "Feature",
  "properties": {
    "addr:full":"600 Sherwood Cir Connellsville PA 15425",
    "addr:housenumber":"600",
    "addr:postcode":"15425",
    "addr:street":"Sherwood Cir",
    "iso:country":"US",
    "sg:address":"600 Sherwood Cir",
    "sg:city":"Connellsville",
    "sg:classifiers":[
        {
            "category":"Real Estate",
            "subcategory":"Real Estate Operator",
            "type":"Services"
        }
    ],
    "sg:phone":"+1 724 628 5310",
    "sg:postcode":"15425",
    "sg:province":"PA",
    "sg:tags":[
        "apartment"
    ],
    "wof:name":"Woodland Hills Townhomes",
    "wof:placetype":"venue"
},
  "geometry": {"coordinates":[-79.563523,40.032981],"type":"Point"}
}