{
  "type": "Feature",
  "properties": {
    "addr:full":"701 W Market St Perkasie PA 18944",
    "addr:housenumber":"701",
    "addr:postcode":"18944",
    "addr:street":"W Market St",
    "iso:country":"US",
    "sg:address":"701 W Market St",
    "sg:city":"Perkasie",
    "sg:classifiers":[
        {
            "category":"Insurance",
            "subcategory":"Title Insurance",
            "type":"Services"
        }
    ],
    "sg:phone":"+1 215 453 3521",
    "sg:postcode":"18944",
    "sg:province":"PA",
    "sg:tags":[
        "carrier"
    ],
    "wof:name":"Camelot Abstract Inc",
    "wof:placetype":"venue"
},
  "geometry": {"coordinates":[-75.296037,40.374795],"type":"Point"}
}