{
  "type": "Feature",
  "properties": {
    "addr:full":"301 N Main St Doylestown PA 18901",
    "addr:housenumber":"301",
    "addr:postcode":"18901",
    "addr:street":"N Main St",
    "iso:country":"US",
    "sg:address":"301 N Main St",
    "sg:city":"Doylestown",
    "sg:classifiers":[
        {
            "category":"Education",
            "subcategory":"Preschool",
            "type":"Public Place"
        },
        {
            "category":"Education",
            "subcategory":"School",
            "type":"Public Place"
        }
    ],
    "sg:phone":"+1 215 348 4004",
    "sg:postcode":"18901",
    "sg:province":"PA",
    "sg:tags":[
        "elementary"
    ],
    "wof:name":"St Paul's Growing Together Preschool",
    "wof:placetype":"venue"
},
  "geometry": {"coordinates":[-75.1306,40.316601],"type":"Point"}
}