{
  "type": "Feature",
  "properties": {
    "addr:full":"2811 W Whitehall Rd State College PA 16801",
    "addr:housenumber":"2811",
    "addr:postcode":"16801",
    "addr:street":"W Whitehall Rd",
    "iso:country":"US",
    "sg:address":"2811 W Whitehall Rd",
    "sg:city":"State College",
    "sg:classifiers":[
        {
            "category":"Farming",
            "subcategory":"Farm",
            "type":"Manufacturing & Wholesale Goods"
        }
    ],
    "sg:phone":"+1   ",
    "sg:postcode":"16801",
    "sg:province":"PA",
    "sg:tags":[
        "crop",
        "general"
    ],
    "wof:name":"Guy Fleck",
    "wof:placetype":"venue"
},
  "geometry": {"coordinates":[-77.896584,40.749275],"type":"Point"}
}