{
  "type": "Feature",
  "properties": {
    "addr:full":"122 Westdale Rd Upper Darby PA 19082",
    "addr:housenumber":"122",
    "addr:postcode":"19082",
    "addr:street":"Westdale Rd",
    "iso:country":"US",
    "sg:address":"122 Westdale Rd",
    "sg:city":"Upper Darby",
    "sg:classifiers":[
        {
            "category":"Professional",
            "type":"Services"
        }
    ],
    "sg:phone":"+1   ",
    "sg:postcode":"19082",
    "sg:province":"PA",
    "wof:name":"Barnster Inc",
    "wof:placetype":"venue"
},
  "geometry": {"coordinates":[-75.275138,39.967616],"type":"Point"}
}