{
  "type": "Feature",
  "properties": {
    "iso:country":"US",
    "sg:address":"149 Venetia Rd",
    "sg:city":"Wind Ridge",
    "sg:classifiers":[
        {
            "category":"Professional",
            "type":"Services"
        }
    ],
    "sg:phone":"+1   ",
    "sg:postcode":"15367",
    "sg:province":"PA",
    "wof:name":"Richard Dixon",
    "wof:placetype":"venue"
},
  "geometry": {"coordinates":[-80.06320599999999,40.243342],"type":"Point"}
}