{
  "type": "Feature",
  "properties": {
    "iso:country":"US",
    "sg:address":"6571 Roosevelt Blvd",
    "sg:city":"Philadelphia",
    "sg:classifiers":[
        {
            "category":"Restaurant",
            "type":"Food & Drink"
        }
    ],
    "sg:phone":"+1 215 744 8890",
    "sg:postcode":"19149",
    "sg:province":"PA",
    "sg:tags":[
        "eating"
    ],
    "wof:name":"Chinese Garden Inn",
    "wof:placetype":"venue"
},
  "geometry": {"coordinates":[-75.067763,40.035385],"type":"Point"}
}