{
  "type": "Feature",
  "properties": {
    "iso:country":"US",
    "sg:address":"302 S Saint Clair St",
    "sg:city":"Pittsburgh",
    "sg:classifiers":[
        {
            "category":"Restaurant",
            "type":"Food & Drink"
        }
    ],
    "sg:menulink":"http://www.allmenus.com/pa/pittsburgh/35288-sharp-edge/menu/",
    "sg:phone":"+1 412 661 3537",
    "sg:postcode":"15206",
    "sg:province":"PA",
    "sg:tags":[
        "new",
        "american"
    ],
    "wof:name":"Sharp Edge",
    "wof:placetype":"venue"
},
  "geometry": {"coordinates":[-79.93069,40.459955],"type":"Point"}
}