{
  "type": "Feature",
  "properties": {
    "iso:country":"US",
    "sg:address":"668 Fairview Ave",
    "sg:city":"Sidman",
    "sg:classifiers":[
        {
            "category":"Arts & Performance",
            "subcategory":"Theater",
            "type":"Entertainment"
        }
    ],
    "sg:phone":"+1 814 495 9317",
    "sg:postcode":"15955",
    "sg:province":"PA",
    "sg:tags":[
        "live",
        "music"
    ],
    "wof:name":"Big City Sounds",
    "wof:placetype":"venue"
},
  "geometry": {"coordinates":[-78.72847299999999,40.348053],"type":"Point"}
}