{
  "type": "Feature",
  "properties": {
    "iso:country":"US",
    "sg:address":"1039 Green St",
    "sg:city":"Reading",
    "sg:classifiers":[
        {
            "category":"Building & Trades",
            "subcategory":"Plumbing",
            "type":"Services"
        }
    ],
    "sg:phone":"+1 610 372 5110",
    "sg:postcode":"19604",
    "sg:province":"PA",
    "sg:tags":[
        "plumbing",
        "contractor"
    ],
    "wof:name":"J R Rubendall Plumbing & Htg",
    "wof:placetype":"venue"
},
  "geometry": {"coordinates":[-75.916955,40.342848],"type":"Point"}
}