{
  "type": "Feature",
  "properties": {
    "addr:full":"140 Edgemont Ave Palmerton PA 18071",
    "addr:housenumber":"140",
    "addr:postcode":"18071",
    "addr:street":"Edgemont Ave",
    "iso:country":"US",
    "sg:address":"140 Edgemont Ave",
    "sg:city":"Palmerton",
    "sg:classifiers":[
        {
            "category":"Shopping",
            "type":"Retail Goods"
        }
    ],
    "sg:phone":"+1 610 826 8401",
    "sg:postcode":"18071",
    "sg:province":"PA",
    "sg:tags":[
        "ready",
        "picture",
        "frame",
        "made"
    ],
    "wof:name":"Creative Framing By Carla",
    "wof:placetype":"venue"
},
  "geometry": {"coordinates":[-75.616142,40.805432],"type":"Point"}
}