{
  "type": "Feature",
  "properties": {
    "iso:country":"US",
    "sg:address":"1400 Spring Garden St",
    "sg:city":"Philadelphia",
    "sg:classifiers":[
        {
            "category":"Government",
            "subcategory":"Office",
            "type":"Public Place"
        }
    ],
    "sg:phone":"+1 215 560 2509",
    "sg:postcode":"19130",
    "sg:province":"PA",
    "sg:tags":[
        "government-united",
        "state"
    ],
    "wof:name":"Veterans/Military Education",
    "wof:placetype":"venue"
},
  "geometry": {"coordinates":[-75.161423,39.962429],"type":"Point"}
}