{
  "type": "Feature",
  "properties": {
    "iso:country":"US",
    "sg:address":"1990 N Main St",
    "sg:city":"Butler",
    "sg:classifiers":[
        {
            "category":"Autos & Motor Vehicles",
            "subcategory":"Automobile Sales",
            "type":"Retail Goods"
        }
    ],
    "sg:phone":"+1 724 283 4663",
    "sg:postcode":"16001",
    "sg:province":"PA",
    "sg:tags":[
        "car",
        "used",
        "dealer"
    ],
    "wof:name":"Quality Car Sales LTD",
    "wof:placetype":"venue"
},
  "geometry": {"coordinates":[-79.94241700000001,40.915991],"type":"Point"}
}