{
  "type": "Feature",
  "properties": {
    "iso:country":"US",
    "sg:address":"RR 4",
    "sg:city":"Mc Donald",
    "sg:classifiers":[
        {
            "category":"Professional",
            "subcategory":"Lawyer & Legal Services",
            "type":"Services"
        }
    ],
    "sg:phone":"+1 724 745 6395",
    "sg:postcode":"15057",
    "sg:province":"PA",
    "wof:name":"Fuchs Janet",
    "wof:placetype":"venue"
},
  "geometry": {"coordinates":[-80.23580200000001,40.368],"type":"Point"}
}