{
  "type": "Feature",
  "properties": {
    "iso:country":"US",
    "sg:address":"8002 Germantown Ave",
    "sg:city":"Philadelphia",
    "sg:classifiers":[
        {
            "category":"Home & Garden",
            "subcategory":"Building Materials",
            "type":"Retail Goods"
        }
    ],
    "sg:phone":"+1 215 248 6030",
    "sg:postcode":"19118",
    "sg:province":"PA",
    "sg:tags":[
        "wallcoverings",
        "wallpaper",
        "contractor"
    ],
    "wof:name":"Chestnut Hill Paint & Dctg",
    "wof:placetype":"venue"
},
  "geometry": {"coordinates":[-75.20083,40.07078],"type":"Point"}
}