{
  "type": "Feature",
  "properties": {
    "addr:full":"229 17th St Pittsburgh PA 15215",
    "addr:housenumber":"229",
    "addr:postcode":"15215",
    "addr:street":"17Th St",
    "iso:country":"US",
    "sg:address":"229 17th St",
    "sg:city":"Pittsburgh",
    "sg:classifiers":[
        {
            "category":"Building & Trades",
            "subcategory":"Construction",
            "type":"Services"
        }
    ],
    "sg:phone":"+1   ",
    "sg:postcode":"15215",
    "sg:province":"PA",
    "sg:tags":[
        "contracting",
        "nonresidential"
    ],
    "wof:name":"Salerno Carpenter Contracting",
    "wof:placetype":"venue"
},
  "geometry": {"coordinates":[-79.923417,40.496322],"type":"Point"}
}