{
  "type": "Feature",
  "properties": {
    "iso:country":"US",
    "sg:address":"130 S 12th St",
    "sg:city":"Philadelphia",
    "sg:classifiers":[
        {
            "category":"Shopping",
            "subcategory":"Bicycles & Sporting Goods",
            "type":"Retail Goods"
        },
        {
            "category":"Sports & Exercise",
            "subcategory":"Tennis Court",
            "type":"Entertainment"
        }
    ],
    "sg:phone":"+1 215 665 1221",
    "sg:postcode":"19107",
    "sg:province":"PA",
    "sg:website":"www.everyonesracquet.com",
    "wof:name":"Everyone's Racquet",
    "wof:placetype":"venue"
},
  "geometry": {"coordinates":[-75.160462,39.949315],"type":"Point"}
}