{
  "type": "Feature",
  "properties": {
    "iso:country":"US",
    "sg:address":"9 N 4th Ave",
    "sg:city":"Clarion",
    "sg:classifiers":[
        {
            "category":"Wholesale",
            "subcategory":"Beer",
            "type":"Manufacturing & Wholesale Goods"
        }
    ],
    "sg:phone":"+1 814 226 7031",
    "sg:postcode":"16214",
    "sg:province":"PA",
    "sg:tags":[
        "ale"
    ],
    "wof:name":"Clarion Beverage Co",
    "wof:placetype":"venue"
},
  "geometry": {"coordinates":[-79.387314,41.215395],"type":"Point"}
}