{
  "type": "Feature",
  "properties": {
    "addr:full":"2701 E Luzerne St Philadelphia PA 19137",
    "addr:housenumber":"2701",
    "addr:postcode":"19137",
    "addr:street":"E Luzerne St",
    "iso:country":"US",
    "sg:address":"2701 E Luzerne St",
    "sg:city":"Philadelphia",
    "sg:classifiers":[
        {
            "category":"Professional",
            "subcategory":"Computer Services",
            "type":"Services"
        },
        {
            "category":"Wholesale",
            "subcategory":"Computers",
            "type":"Manufacturing & Wholesale Goods"
        }
    ],
    "sg:phone":"+1 215 743 9311",
    "sg:postcode":"19137",
    "sg:province":"PA",
    "sg:tags":[
        "repair"
    ],
    "wof:name":"Sierra Computer Services Inc",
    "wof:placetype":"venue"
},
  "geometry": {"coordinates":[-75.08319899999999,39.992802],"type":"Point"}
}