{
  "type": "Feature",
  "properties": {
    "iso:country":"US",
    "sg:address":"200 Corporate Center Dr",
    "sg:city":"Camp Hill",
    "sg:classifiers":[
        {
            "category":"Insurance",
            "subcategory":"Insurance Agent",
            "type":"Services"
        }
    ],
    "sg:phone":"+1   ",
    "sg:postcode":"17011",
    "sg:province":"PA",
    "sg:tags":[
        "claim",
        "processing"
    ],
    "wof:name":"Highmark Inc",
    "wof:placetype":"venue"
},
  "geometry": {"coordinates":[-76.920649,40.263241],"type":"Point"}
}