{
  "type": "Feature",
  "properties": {
    "iso:country":"US",
    "sg:address":"1421 W Market St",
    "sg:city":"York",
    "sg:classifiers":[
        {
            "category":"Health Services",
            "subcategory":"Doctor",
            "type":"Services"
        },
        {
            "category":"Health Services",
            "subcategory":"Dentist",
            "type":"Services"
        }
    ],
    "sg:phone":"+1 717 845 5789",
    "sg:postcode":"17404",
    "sg:province":"PA",
    "sg:tags":[
        "dentists-oral",
        "physician",
        "maxillofacial",
        "surgeons",
        "surgery",
        "oral"
    ],
    "wof:name":"Dellinger David H DMD PC",
    "wof:placetype":"venue"
},
  "geometry": {"coordinates":[-76.759516,39.953604],"type":"Point"}
}