{
  "type": "Feature",
  "properties": {
    "iso:country":"US",
    "sg:address":"2280 E College Ave",
    "sg:city":"State College",
    "sg:classifiers":[
        {
            "category":"Home & Garden",
            "subcategory":"Building Materials",
            "type":"Retail Goods"
        }
    ],
    "sg:phone":"+1 814 238 0558",
    "sg:postcode":"16801",
    "sg:province":"PA",
    "sg:tags":[
        "mixed",
        "concrete"
    ],
    "wof:name":"Centre Concrete Co",
    "wof:placetype":"venue"
},
  "geometry": {"coordinates":[-77.81423599999999,40.821996],"type":"Point"}
}