{
  "type": "Feature",
  "properties": {
    "iso:country":"US",
    "sg:address":"1421 Freeport Rd",
    "sg:city":"Natrona Heights",
    "sg:classifiers":[
        {
            "category":"Government",
            "subcategory":"Office",
            "type":"Public Place"
        }
    ],
    "sg:phone":"+1 724 230 2000",
    "sg:postcode":"15065",
    "sg:province":"PA",
    "wof:name":"Senator James Ferlo",
    "wof:placetype":"venue"
},
  "geometry": {"coordinates":[-79.732513,40.618228],"type":"Point"}
}