{
  "type": "Feature",
  "properties": {
    "addr:full":"333 W 7th Ave Tarentum PA 15084",
    "addr:housenumber":"333",
    "addr:postcode":"15084",
    "addr:street":"W 7Th Ave",
    "iso:country":"US",
    "sg:address":"333 W 7th Ave",
    "sg:city":"Tarentum",
    "sg:classifiers":[
        {
            "category":"Retail",
            "subcategory":"Repair Shop",
            "type":"Services"
        }
    ],
    "sg:phone":"+1 724 352 3232",
    "sg:postcode":"15084",
    "sg:province":"PA",
    "sg:tags":[
        "television",
        "radio"
    ],
    "wof:name":"NRS-Dave's TV",
    "wof:placetype":"venue"
},
  "geometry": {"coordinates":[-79.763992,40.598454],"type":"Point"}
}