{
  "type": "Feature",
  "properties": {
    "iso:country":"US",
    "sg:address":"831 Catch Basin Rd",
    "sg:city":"Sellersville",
    "sg:classifiers":[
        {
            "category":"Building & Trades",
            "subcategory":"Construction",
            "type":"Services"
        }
    ],
    "sg:phone":"+1 215 257 8711",
    "sg:postcode":"18960",
    "sg:province":"PA",
    "sg:tags":[
        "concrete",
        "contractor"
    ],
    "wof:name":"Wright Concrete & Paving",
    "wof:placetype":"venue"
},
  "geometry": {"coordinates":[-75.338228,40.386373],"type":"Point"}
}