{
  "type": "Feature",
  "properties": {
    "iso:country":"US",
    "sg:address":"3550 Woodcliff Ct",
    "sg:city":"Murrysville",
    "sg:classifiers":[
        {
            "category":"Banks & Credit Unions",
            "subcategory":"Bank",
            "type":"Services"
        }
    ],
    "sg:phone":"+1 724 465 4618",
    "sg:postcode":"15668",
    "sg:province":"PA",
    "sg:tags":[
        "saving",
        "commercial"
    ],
    "wof:name":"St Bank",
    "wof:placetype":"venue"
},
  "geometry": {"coordinates":[-79.681122,40.439869],"type":"Point"}
}