{
  "type": "Feature",
  "properties": {
    "iso:country":"US",
    "sg:address":"2100 Wood Ave",
    "sg:city":"Easton",
    "sg:classifiers":[
        {
            "category":"Freight",
            "type":"Transportation"
        }
    ],
    "sg:phone":"+1 610 250 0390",
    "sg:postcode":"18042",
    "sg:province":"PA",
    "sg:tags":[
        "trucking"
    ],
    "wof:name":"Johnson Motor Line Inc",
    "wof:placetype":"venue"
},
  "geometry": {"coordinates":[-75.25001399999999,40.687397],"type":"Point"}
}