{
  "type": "Feature",
  "properties": {
    "addr:full":"545 Church St Mc Intyre PA 15756",
    "addr:housenumber":"545",
    "addr:postcode":"15756",
    "addr:street":"Church St",
    "iso:country":"US",
    "sg:address":"545 Church St",
    "sg:city":"Mc Intyre",
    "sg:classifiers":[
        {
            "category":"Organizations",
            "subcategory":"Non-profit Organization",
            "type":"Services"
        }
    ],
    "sg:phone":"+1 724 726 1050",
    "sg:postcode":"15756",
    "sg:province":"PA",
    "sg:tags":[
        "fund",
        "counselor",
        "raising"
    ],
    "wof:name":"84 Services Fund Raising",
    "wof:placetype":"venue"
},
  "geometry": {"coordinates":[-79.304265,40.5695],"type":"Point"}
}