{
  "type": "Feature",
  "properties": {
    "iso:country":"US",
    "sg:address":"105 S 5th Ave",
    "sg:city":"Clarion",
    "sg:classifiers":[
        {
            "category":"Social Services",
            "type":"Services"
        }
    ],
    "sg:phone":"+1 814 226 7273",
    "sg:postcode":"16214",
    "sg:province":"PA",
    "sg:website":"www.passagesinc.net",
    "wof:name":"Passages",
    "wof:placetype":"venue"
},
  "geometry": {"coordinates":[-79.387699,41.211506],"type":"Point"}
}