{
  "type": "Feature",
  "properties": {
    "addr:full":"2619 Tattoo Dr Chambersburg PA 17202",
    "addr:postcode":"17202",
    "addr:street":"Dr",
    "iso:country":"US",
    "sg:address":"2619 Tattoo Dr",
    "sg:city":"Chambersburg",
    "sg:classifiers":[
        {
            "category":"Communications",
            "type":"Services"
        }
    ],
    "sg:phone":"+1 717 264 2886",
    "sg:postcode":"17202",
    "sg:province":"PA",
    "wof:name":"Meyer Communications",
    "wof:placetype":"venue"
},
  "geometry": {"coordinates":[-80.19989099999999,40.187584],"type":"Point"}
}