{
  "type": "Feature",
  "properties": {
    "iso:country":"US",
    "sg:address":"227 S 7th St",
    "sg:city":"Easton",
    "sg:classifiers":[
        {
            "category":"Professional",
            "subcategory":"Lawyer & Legal Services",
            "type":"Services"
        }
    ],
    "sg:phone":"+1 610 258 2393",
    "sg:postcode":"18042",
    "sg:province":"PA",
    "sg:tags":[
        "attorney"
    ],
    "wof:name":"Baurkot & Baurkot",
    "wof:placetype":"venue"
},
  "geometry": {"coordinates":[-75.21795899999999,40.687239],"type":"Point"}
}