{
  "type": "Feature",
  "properties": {
    "iso:country":"US",
    "sg:address":"24 Buck Heights Rd",
    "sg:city":"Holtwood",
    "sg:classifiers":[
        {
            "category":"Retail",
            "subcategory":"Veterinary Services",
            "type":"Services"
        }
    ],
    "sg:phone":"+1   ",
    "sg:postcode":"17532",
    "sg:province":"PA",
    "wof:name":"Kill Winning Vet Services LLC",
    "wof:placetype":"venue"
},
  "geometry": {"coordinates":[-76.249522,39.882645],"type":"Point"}
}