{
  "type": "Feature",
  "properties": {
    "iso:country":"US",
    "sg:address":"2700 Elroy Rd",
    "sg:city":"Hatfield",
    "sg:classifiers":[
        {
            "category":"Real Estate",
            "subcategory":"Real Estate Operator",
            "type":"Services"
        }
    ],
    "sg:phone":"+1 215 855 9900",
    "sg:postcode":"19440",
    "sg:province":"PA",
    "sg:tags":[
        "apartment"
    ],
    "wof:name":"Pennfield Manor Apartments Inc",
    "wof:placetype":"venue"
},
  "geometry": {"coordinates":[-75.318398,40.277401],"type":"Point"}
}