{
  "type": "Feature",
  "properties": {
    "iso:country":"US",
    "sg:address":"525 S 29th St",
    "sg:city":"Harrisburg",
    "sg:classifiers":[
        {
            "category":"Professional",
            "subcategory":"Employment Agencies",
            "type":"Services"
        }
    ],
    "sg:phone":"+1 717 561 8033",
    "sg:postcode":"17104",
    "sg:province":"PA",
    "sg:tags":[
        "opportunity"
    ],
    "wof:name":"Central Penn Temp",
    "wof:placetype":"venue"
},
  "geometry": {"coordinates":[-76.840709,40.264608],"type":"Point"}
}