{
  "type": "Feature",
  "properties": {
    "iso:country":"US",
    "sg:address":"860 S Lincoln Ave",
    "sg:city":"Walnutport",
    "sg:classifiers":[
        {
            "category":"Real Estate",
            "subcategory":"Real Estate Agent",
            "type":"Services"
        }
    ],
    "sg:phone":"+1   ",
    "sg:postcode":"18088",
    "sg:province":"PA",
    "wof:name":"Benjamin Real Estate",
    "wof:placetype":"venue"
},
  "geometry": {"coordinates":[-75.591346,40.743464],"type":"Point"}
}