{
  "type": "Feature",
  "properties": {
    "iso:country":"US",
    "sg:address":"1455 Conewago Creek Rd",
    "sg:city":"Manchester",
    "sg:classifiers":[
        {
            "category":"Building & Trades",
            "subcategory":"Pest Control",
            "type":"Services"
        }
    ],
    "sg:phone":"+1 717 266 1712",
    "sg:postcode":"17345",
    "sg:province":"PA",
    "sg:tags":[
        "mothproofing"
    ],
    "wof:name":"Ellis Wildlife Pest Control",
    "wof:placetype":"venue"
},
  "geometry": {"coordinates":[-76.728886,40.087751],"type":"Point"}
}