{
  "type": "Feature",
  "properties": {
    "iso:country":"US",
    "sg:address":"1101 S Front St",
    "sg:city":"Harrisburg",
    "sg:classifiers":[
        {
            "category":"Professional",
            "subcategory":"Business Services",
            "type":"Services"
        },
        {
            "category":"Building & Trades",
            "subcategory":"Construction",
            "type":"Services"
        }
    ],
    "sg:phone":"+1 717 221 8600",
    "sg:postcode":"17104",
    "sg:province":"PA",
    "sg:tags":[
        "general",
        "contractor"
    ],
    "wof:name":"Palmer Construction Company",
    "wof:placetype":"venue"
},
  "geometry": {"coordinates":[-76.872687,40.250683],"type":"Point"}
}