{
  "type": "Feature",
  "properties": {
    "addr:full":"6752 Elk Rush Dr Imperial PA 15126",
    "addr:housenumber":"6752",
    "addr:postcode":"15126",
    "addr:street":"Elk Rush Dr",
    "iso:country":"US",
    "sg:address":"6752 Elk Rush Dr",
    "sg:city":"Imperial",
    "sg:classifiers":[
        {
            "category":"Personal",
            "subcategory":"Beauty Salon",
            "type":"Services"
        }
    ],
    "sg:phone":"+1   ",
    "sg:postcode":"15126",
    "sg:province":"PA",
    "sg:tags":[
        "shop"
    ],
    "wof:name":"All About Nails",
    "wof:placetype":"venue"
},
  "geometry": {"coordinates":[-80.21834699999999,40.449138],"type":"Point"}
}