{
  "type": "Feature",
  "properties": {
    "addr:full":"7930 Bustleton Ave Philadelphia PA 19152",
    "addr:housenumber":"7930",
    "addr:postcode":"19152",
    "addr:street":"Bustleton Ave",
    "iso:country":"US",
    "sg:address":"7930 Bustleton Ave",
    "sg:city":"Philadelphia",
    "sg:classifiers":[
        {
            "category":"Restaurant",
            "type":"Food & Drink"
        }
    ],
    "sg:phone":"+1 215 742 8558",
    "sg:postcode":"19152",
    "sg:province":"PA",
    "sg:tags":[
        "eating"
    ],
    "wof:name":"Vito Gina & Sons Restaurant",
    "wof:placetype":"venue"
},
  "geometry": {"coordinates":[-75.052262,40.059104],"type":"Point"}
}