{
  "type": "Feature",
  "properties": {
    "addr:full":"674 N River St Wilkes Barre PA 18705",
    "addr:housenumber":"674",
    "addr:postcode":"18705",
    "addr:street":"N River St",
    "iso:country":"US",
    "sg:address":"674 N River St",
    "sg:city":"Wilkes Barre",
    "sg:classifiers":[
        {
            "category":"Restaurant",
            "type":"Food & Drink"
        }
    ],
    "sg:menulink":"http://www.allmenus.com/pa/wilkes-barre/206893-mcdonalds/menu/",
    "sg:phone":"+1 570 970 7952",
    "sg:postcode":"18705",
    "sg:province":"PA",
    "sg:tags":[
        "burger",
        "american"
    ],
    "wof:name":"McDonald's",
    "wof:placetype":"venue"
},
  "geometry": {"coordinates":[-75.867521,41.26011],"type":"Point"}
}