{
  "type": "Feature",
  "properties": {
    "iso:country":"US",
    "sg:address":"1029 Liberty St",
    "sg:city":"Franklin",
    "sg:classifiers":[
        {
            "category":"Shopping",
            "type":"Retail Goods"
        },
        {
            "category":"Health Services",
            "subcategory":"Doctor",
            "type":"Services"
        }
    ],
    "sg:phone":"+1 814 437 7266",
    "sg:postcode":"16323",
    "sg:province":"PA",
    "sg:tags":[
        "physician",
        "surgeon",
        "merchandise"
    ],
    "sg:website":"www.crawfordandfitch.com",
    "wof:name":"Crawford & Fitch-Ear Nose & Th",
    "wof:placetype":"venue"
},
  "geometry": {"coordinates":[-79.826319,41.394655],"type":"Point"}
}