{
  "type": "Feature",
  "properties": {
    "iso:country":"US",
    "sg:address":"40 W North St",
    "sg:city":"Waynesboro",
    "sg:classifiers":[
        {
            "category":"Social Services",
            "type":"Services"
        }
    ],
    "sg:phone":"+1 717 263 5060",
    "sg:postcode":"17268",
    "sg:province":"PA",
    "sg:tags":[
        "organization",
        "welfare"
    ],
    "wof:name":"South Central Community Action",
    "wof:placetype":"venue"
},
  "geometry": {"coordinates":[-77.577607,39.757846],"type":"Point"}
}