{
  "type": "Feature",
  "properties": {
    "iso:country":"US",
    "sg:address":"1216 S York St",
    "sg:city":"Mechanicsburg",
    "sg:classifiers":[
        {
            "category":"Food & Beverages",
            "subcategory":"Groceries & Convenience Stores",
            "type":"Retail Goods"
        }
    ],
    "sg:phone":"+1 717 697 4330",
    "sg:postcode":"17055",
    "sg:province":"PA",
    "sg:tags":[
        "market",
        "farmer"
    ],
    "sg:website":"www.paulusfarmmarket.com",
    "wof:name":"Paulus Farm Market",
    "wof:placetype":"venue"
},
  "geometry": {"coordinates":[-77.003998,40.1954],"type":"Point"}
}