{
  "type": "Feature",
  "properties": {
    "iso:country":"US",
    "sg:address":"27 Pearl St",
    "sg:city":"Biglerville",
    "sg:classifiers":[
        {
            "category":"Real Estate",
            "subcategory":"Surveying",
            "type":"Services"
        }
    ],
    "sg:phone":"+1 717 677 6986",
    "sg:postcode":"17307",
    "sg:province":"PA",
    "sg:tags":[
        "surveyor",
        "land",
        "engineer"
    ],
    "wof:name":"Price Richard C",
    "wof:placetype":"venue"
},
  "geometry": {"coordinates":[-77.298875,39.923623],"type":"Point"}
}