{
  "type": "Feature",
  "properties": {
    "addr:full":"400 Armbrust Rd Youngwood PA 15601",
    "addr:housenumber":"400",
    "addr:postcode":"15601",
    "addr:street":"Armbrust Rd",
    "iso:country":"US",
    "sg:address":"400 Armbrust Rd",
    "sg:city":"Youngwood",
    "sg:classifiers":[
        {
            "category":"Education",
            "subcategory":"Junior College",
            "type":"Public Place"
        }
    ],
    "sg:phone":"+1   ",
    "sg:postcode":"15601",
    "sg:province":"PA",
    "sg:tags":[
        "community"
    ],
    "wof:name":"Business and Industry Center",
    "wof:placetype":"venue"
},
  "geometry": {"coordinates":[-79.56617300000001,40.237151],"type":"Point"}
}