{
  "type": "Feature",
  "properties": {
    "addr:full":"1180 Knoxlyn Rd Gettysburg PA 17325",
    "addr:housenumber":"1180",
    "addr:postcode":"17325",
    "addr:street":"Knoxlyn Rd",
    "iso:country":"US",
    "sg:address":"1180 Knoxlyn Rd",
    "sg:city":"Gettysburg",
    "sg:classifiers":[
        {
            "category":"Shopping",
            "type":"Retail Goods"
        },
        {
            "category":"Professional",
            "subcategory":"Art Services",
            "type":"Services"
        }
    ],
    "sg:phone":"+1 717 334 0430",
    "sg:postcode":"17325",
    "sg:province":"PA",
    "sg:tags":[
        "merchandise",
        "artist"
    ],
    "wof:name":"Dale Gallon Historical Arts",
    "wof:placetype":"venue"
},
  "geometry": {"coordinates":[-77.31767000000001,39.830445],"type":"Point"}
}