{
  "type": "Feature",
  "properties": {
    "iso:country":"US",
    "sg:address":"940 South Ave",
    "sg:city":"Bradford",
    "sg:classifiers":[
        {
            "category":"Social Services",
            "type":"Services"
        }
    ],
    "sg:phone":"+1 814 362 6562",
    "sg:postcode":"16725",
    "sg:province":"PA",
    "sg:tags":[
        "guidance",
        "child"
    ],
    "wof:name":"Children's Home Of Bradford",
    "wof:placetype":"venue"
},
  "geometry": {"coordinates":[-78.651417,41.907698],"type":"Point"}
}