{
  "type": "Feature",
  "properties": {
    "iso:country":"US",
    "sg:address":"1818 Mearns Rd",
    "sg:city":"Warminster",
    "sg:classifiers":[
        {
            "category":"Building & Trades",
            "subcategory":"Plumbing",
            "type":"Services"
        }
    ],
    "sg:phone":"+1 215 674 4390",
    "sg:postcode":"18974",
    "sg:province":"PA",
    "sg:tags":[
        "sheet",
        "work",
        "metal",
        "contractor"
    ],
    "wof:name":"Central Sheetmetal",
    "wof:placetype":"venue"
},
  "geometry": {"coordinates":[-75.06762500000001,40.227957],"type":"Point"}
}