{
  "type": "Feature",
  "properties": {
    "addr:full":"971 Schoffers Rd Birdsboro PA 19508",
    "addr:housenumber":"971",
    "addr:postcode":"19508",
    "addr:street":"Schoffers Rd",
    "iso:country":"US",
    "sg:address":"971 Schoffers Rd",
    "sg:city":"Birdsboro",
    "sg:classifiers":[
        {
            "category":"Building & Trades",
            "subcategory":"Construction",
            "type":"Services"
        }
    ],
    "sg:phone":"+1   ",
    "sg:postcode":"19508",
    "sg:province":"PA",
    "sg:tags":[
        "contractor"
    ],
    "wof:name":"Funkhouser Roofg Siding Cnstr",
    "wof:placetype":"venue"
},
  "geometry": {"coordinates":[-75.816417,40.304725],"type":"Point"}
}