{
  "type": "Feature",
  "properties": {
    "iso:country":"US",
    "sg:address":"439 S Maple Ave",
    "sg:city":"Greensburg",
    "sg:classifiers":[
        {
            "category":"Professional",
            "type":"Services"
        }
    ],
    "sg:phone":"+1   ",
    "sg:postcode":"15601",
    "sg:province":"PA",
    "wof:name":"Florence M Miller",
    "wof:placetype":"venue"
},
  "geometry": {"coordinates":[-79.54195199999999,40.299002],"type":"Point"}
}