{
  "type": "Feature",
  "properties": {
    "iso:country":"US",
    "sg:address":"580 Village Rd",
    "sg:city":"Muncy",
    "sg:classifiers":[
        {
            "category":"Shopping",
            "subcategory":"Gifts & Souvenirs",
            "type":"Retail Goods"
        }
    ],
    "sg:phone":"+1 570 546 3887",
    "sg:postcode":"17756",
    "sg:province":"PA",
    "sg:tags":[
        "shop"
    ],
    "wof:name":"Weister Woods Mercantile",
    "wof:placetype":"venue"
},
  "geometry": {"coordinates":[-76.796989,41.243114],"type":"Point"}
}