{
  "type": "Feature",
  "properties": {
    "iso:country":"US",
    "sg:address":"354 N Easton Rd",
    "sg:city":"Glenside",
    "sg:classifiers":[
        {
            "category":"Retail",
            "subcategory":"Funeral Services",
            "type":"Services"
        }
    ],
    "sg:phone":"+1 215 884 8410",
    "sg:postcode":"19038",
    "sg:province":"PA",
    "sg:tags":[
        "director",
        "home"
    ],
    "wof:name":"William R May Funeral Home Inc",
    "wof:placetype":"venue"
},
  "geometry": {"coordinates":[-75.14872,40.105653],"type":"Point"}
}