{
  "type": "Feature",
  "properties": {
    "iso:country":"US",
    "sg:address":"7228 Germantown Ave",
    "sg:city":"Philadelphia",
    "sg:classifiers":[
        {
            "category":"Shopping",
            "subcategory":"Optical Goods",
            "type":"Retail Goods"
        }
    ],
    "sg:phone":"+1 215 248 6070",
    "sg:postcode":"19119",
    "sg:province":"PA",
    "wof:name":"Mr Peeper's Optical",
    "wof:placetype":"venue"
},
  "geometry": {"coordinates":[-75.191896,40.061138],"type":"Point"}
}