{
  "type": "Feature",
  "properties": {
    "addr:full":"518 Hanover Kendall Rd Hookstown PA 15050",
    "addr:housenumber":"518",
    "addr:postcode":"15050",
    "addr:street":"Hanover Kendall Rd",
    "iso:country":"US",
    "sg:address":"518 Hanover Kendall Rd",
    "sg:city":"Hookstown",
    "sg:classifiers":[
        {
            "category":"Insurance",
            "subcategory":"Insurance Agent",
            "type":"Services"
        }
    ],
    "sg:phone":"+1 724 899 3381",
    "sg:postcode":"15050",
    "sg:province":"PA",
    "wof:name":"Viti Insurance Agency",
    "wof:placetype":"venue"
},
  "geometry": {"coordinates":[-80.446388,40.530418],"type":"Point"}
}