{
  "type": "Feature",
  "properties": {
    "addr:full":"437 Grant St Pittsburgh PA 15219",
    "addr:housenumber":"437",
    "addr:postcode":"15219",
    "addr:street":"Grant St",
    "iso:country":"US",
    "sg:address":"437 Grant St",
    "sg:city":"Pittsburgh",
    "sg:classifiers":[
        {
            "category":"Professional",
            "subcategory":"Lawyer & Legal Services",
            "type":"Services"
        }
    ],
    "sg:phone":"+1 412 261 1600",
    "sg:postcode":"15219",
    "sg:province":"PA",
    "sg:tags":[
        "attorney",
        "business",
        "tax",
        "planning",
        "real estate",
        "law"
    ],
    "wof:name":"Carr, Alisa N - Leech Tishman Fuscaldo Lampl",
    "wof:placetype":"venue"
},
  "geometry": {"coordinates":[-79.997142,40.438779],"type":"Point"}
}