{
  "type": "Feature",
  "properties": {
    "iso:country":"US",
    "sg:address":"1835 Market St Ste 2000",
    "sg:city":"Philadelphia",
    "sg:classifiers":[
        {
            "category":"Professional",
            "subcategory":"Employment Agencies",
            "type":"Services"
        }
    ],
    "sg:phone":"+1 215 496 6666",
    "sg:postcode":"19103",
    "sg:province":"PA",
    "wof:name":"Korn Ferry International",
    "wof:placetype":"venue"
},
  "geometry": {"coordinates":[-75.170946,39.953537],"type":"Point"}
}