{
  "type": "Feature",
  "properties": {
    "iso:country":"US",
    "sg:address":"260 Reitz Blvd",
    "sg:city":"Lewisburg",
    "sg:classifiers":[
        {
            "category":"Health Services",
            "subcategory":"Doctor",
            "type":"Services"
        }
    ],
    "sg:phone":"+1 570 523 3368",
    "sg:postcode":"17837",
    "sg:province":"PA",
    "sg:tags":[
        "physician",
        "surgery",
        "oral",
        "surgeons"
    ],
    "wof:name":"Family Dentistry",
    "wof:placetype":"venue"
},
  "geometry": {"coordinates":[-76.911174,40.961522],"type":"Point"}
}