{
  "type": "Feature",
  "properties": {
    "iso:country":"US",
    "sg:address":"2848 Blakeslee Boulevard Dr W",
    "sg:city":"Lehighton",
    "sg:classifiers":[
        {
            "category":"Autos & Motor Vehicles",
            "subcategory":"Automobile Sales",
            "type":"Retail Goods"
        }
    ],
    "sg:phone":"+1   ",
    "sg:postcode":"18235",
    "sg:province":"PA",
    "sg:tags":[
        "used"
    ],
    "wof:name":"443 Auto Sales LLC",
    "wof:placetype":"venue"
},
  "geometry": {"coordinates":[-75.81994,40.783438],"type":"Point"}
}