{
  "type": "Feature",
  "properties": {
    "iso:country":"US",
    "sg:address":"612 Andover Rd",
    "sg:city":"Upper Darby",
    "sg:classifiers":[
        {
            "category":"Building & Trades",
            "subcategory":"Landscaping Services",
            "type":"Services"
        }
    ],
    "sg:phone":"+1   ",
    "sg:postcode":"19082",
    "sg:province":"PA",
    "sg:tags":[
        "construction"
    ],
    "wof:name":"Ward Landscaping",
    "wof:placetype":"venue"
},
  "geometry": {"coordinates":[-75.25404399999999,39.948875],"type":"Point"}
}