{
  "type": "Feature",
  "properties": {
    "iso:country":"US",
    "sg:address":"300 Coleman Rd",
    "sg:city":"Gettysburg",
    "sg:classifiers":[
        {
            "category":"Manufacturing",
            "subcategory":"Retail Goods",
            "type":"Manufacturing & Wholesale Goods"
        }
    ],
    "sg:phone":"+1 717 334 9136",
    "sg:postcode":"17325",
    "sg:province":"PA",
    "sg:tags":[
        "pencil"
    ],
    "wof:name":"Pen & Inc Crafts",
    "wof:placetype":"venue"
},
  "geometry": {"coordinates":[-77.146567,39.868257],"type":"Point"}
}