{
  "type": "Feature",
  "properties": {
    "iso:country":"US",
    "sg:address":"1167 Bridge St",
    "sg:city":"Philadelphia",
    "sg:classifiers":[
        {
            "category":"Professional",
            "subcategory":"Lawyer & Legal Services",
            "type":"Services"
        }
    ],
    "sg:phone":"+1 215 537 2785",
    "sg:postcode":"19124",
    "sg:province":"PA",
    "wof:name":"Bobb Howard L Attorney",
    "wof:placetype":"venue"
},
  "geometry": {"coordinates":[-75.083,40.027401],"type":"Point"}
}