{
  "type": "Feature",
  "properties": {
    "iso:country":"US",
    "sg:address":"6400 Woodland Ave",
    "sg:city":"Philadelphia",
    "sg:classifiers":[
        {
            "category":"Banks & Credit Unions",
            "subcategory":"Bank",
            "type":"Services"
        }
    ],
    "sg:phone":"+1 215 729 7392",
    "sg:postcode":"19142",
    "sg:province":"PA",
    "sg:tags":[
        "cashing",
        "check"
    ],
    "wof:name":"George's Check Cashing",
    "wof:placetype":"venue"
},
  "geometry": {"coordinates":[-75.23370799999999,39.926021],"type":"Point"}
}