{
  "type": "Feature",
  "properties": {
    "addr:full":"65 Seven Hills Rd Strattanville PA 16258",
    "addr:housenumber":"65",
    "addr:postcode":"16258",
    "addr:street":"Seven Hills Rd",
    "iso:country":"US",
    "sg:address":"65 Seven Hills Rd",
    "sg:city":"Strattanville",
    "sg:classifiers":[
        {
            "category":"Freight",
            "type":"Transportation"
        }
    ],
    "sg:phone":"+1 814 764 3935",
    "sg:postcode":"16258",
    "sg:province":"PA",
    "sg:tags":[
        "trucking"
    ],
    "wof:name":"DGB Trucking",
    "wof:placetype":"venue"
},
  "geometry": {"coordinates":[-79.298897,41.203115],"type":"Point"}
}