{
  "type": "Feature",
  "properties": {
    "iso:country":"US",
    "sg:address":"134 Veterans Ln",
    "sg:city":"Doylestown",
    "sg:classifiers":[
        {
            "category":"Building & Trades",
            "subcategory":"Locksmith",
            "type":"Services"
        }
    ],
    "sg:phone":"+1 215 589 6579",
    "sg:postcode":"18901",
    "sg:province":"PA",
    "sg:tags":[
        "key"
    ],
    "wof:name":"Available Locksmith All Day",
    "wof:placetype":"venue"
},
  "geometry": {"coordinates":[-75.131902,40.319281],"type":"Point"}
}