{
  "type": "Feature",
  "properties": {
    "iso:country":"US",
    "sg:address":"190 Lathrop St",
    "sg:city":"Kingston",
    "sg:classifiers":[
        {
            "category":"Professional",
            "subcategory":"Accounting & Tax Preparation",
            "type":"Services"
        }
    ],
    "sg:phone":"+1 570 283 2727",
    "sg:postcode":"18704",
    "sg:province":"PA",
    "sg:tags":[
        "firm",
        "accountant"
    ],
    "wof:name":"Kronick Kalada Berdy & Co PC",
    "wof:placetype":"venue"
},
  "geometry": {"coordinates":[-75.88171699999999,41.267949],"type":"Point"}
}