{
  "type": "Feature",
  "properties": {
    "iso:country":"US",
    "sg:address":"204 W 1st Ave",
    "sg:city":"Parkesburg",
    "sg:classifiers":[
        {
            "category":"Personal",
            "subcategory":"Barber",
            "type":"Services"
        }
    ],
    "sg:phone":"+1 610 857 1840",
    "sg:postcode":"19365",
    "sg:province":"PA",
    "sg:tags":[
        "shop"
    ],
    "wof:name":"Corporate Cuts",
    "wof:placetype":"venue"
},
  "geometry": {"coordinates":[-75.915576,39.959566],"type":"Point"}
}