{
  "type": "Feature",
  "properties": {
    "addr:full":"355 Faggs Manor Rd Cochranville PA 19330",
    "addr:housenumber":"355",
    "addr:postcode":"19330",
    "addr:street":"Faggs Manor Rd",
    "iso:country":"US",
    "sg:address":"355 Faggs Manor Rd",
    "sg:city":"Cochranville",
    "sg:classifiers":[
        {
            "category":"Farming",
            "subcategory":"Farm & Veterinary Services",
            "type":"Manufacturing & Wholesale Goods"
        }
    ],
    "sg:phone":"+1 610 869 8508",
    "sg:postcode":"19330",
    "sg:province":"PA",
    "sg:tags":[
        "breeder",
        "livestock"
    ],
    "wof:name":"Tomorrows Dream Thoroughbred",
    "wof:placetype":"venue"
},
  "geometry": {"coordinates":[-75.91189799999999,39.865431],"type":"Point"}
}