{
  "type": "Feature",
  "properties": {
    "addr:full":"1020 Chestnut St Emmaus PA 18049",
    "addr:housenumber":"1020",
    "addr:postcode":"18049",
    "addr:street":"Chestnut St",
    "iso:country":"US",
    "sg:address":"1020 Chestnut St",
    "sg:city":"Emmaus",
    "sg:classifiers":[
        {
            "category":"Retail",
            "subcategory":"Veterinary Services",
            "type":"Services"
        }
    ],
    "sg:phone":"+1   ",
    "sg:postcode":"18049",
    "sg:province":"PA",
    "wof:name":"Wayne H Hachten Dvm",
    "wof:placetype":"venue"
},
  "geometry": {"coordinates":[-75.50556899999999,40.529043],"type":"Point"}
}