{
  "type": "Feature",
  "properties": {
    "iso:country":"US",
    "sg:address":"701 Kilduff Ct",
    "sg:city":"Chadds Ford",
    "sg:classifiers":[
        {
            "category":"Professional",
            "subcategory":"Computer Services",
            "type":"Services"
        }
    ],
    "sg:phone":"+1   ",
    "sg:postcode":"19317",
    "sg:province":"PA",
    "sg:tags":[
        "related"
    ],
    "wof:name":"My Sherpa LLC",
    "wof:placetype":"venue"
},
  "geometry": {"coordinates":[-75.64019999999999,39.846511],"type":"Point"}
}