{
  "type": "Feature",
  "properties": {
    "addr:full":"1030 Summer Pl Pittsburgh PA 15243",
    "addr:housenumber":"1030",
    "addr:postcode":"15243",
    "addr:street":"Summer Pl",
    "iso:country":"US",
    "sg:address":"1030 Summer Pl",
    "sg:city":"Pittsburgh",
    "sg:classifiers":[
        {
            "category":"Professional",
            "subcategory":"Management & Consulting",
            "type":"Services"
        }
    ],
    "sg:phone":"+1 412 344 9050",
    "sg:postcode":"15243",
    "sg:province":"PA",
    "sg:tags":[
        "public",
        "relations",
        "advertising"
    ],
    "wof:name":"Maddigan Communications Inc",
    "wof:placetype":"venue"
},
  "geometry": {"coordinates":[-80.061415,40.376493],"type":"Point"}
}