{
  "type": "Feature",
  "properties": {
    "addr:full":"405 Elm St Watsontown PA 17777",
    "addr:housenumber":"405",
    "addr:postcode":"17777",
    "addr:street":"Elm St",
    "iso:country":"US",
    "sg:address":"405 Elm St",
    "sg:city":"Watsontown",
    "sg:classifiers":[
        {
            "category":"Organizations",
            "subcategory":"Religious Organization",
            "type":"Services"
        }
    ],
    "sg:phone":"+1 570 538 2253",
    "sg:postcode":"17777",
    "sg:province":"PA",
    "sg:tags":[
        "church"
    ],
    "wof:name":"Watsontown Baptist Church",
    "wof:placetype":"venue"
},
  "geometry": {"coordinates":[-76.86499000000001,41.083922],"type":"Point"}
}