{
  "type": "Feature",
  "properties": {
    "iso:country":"US",
    "sg:address":"228 S Cliff St",
    "sg:city":"Butler",
    "sg:classifiers":[
        {
            "category":"Banks & Credit Unions",
            "subcategory":"Investment Brokerage",
            "type":"Services"
        }
    ],
    "sg:phone":"+1 724 283 5162",
    "sg:postcode":"16001",
    "sg:province":"PA",
    "sg:tags":[
        "consultant",
        "planning",
        "financial"
    ],
    "wof:name":"Larry Stimpert Financial Svc",
    "wof:placetype":"venue"
},
  "geometry": {"coordinates":[-79.892871,40.859505],"type":"Point"}
}