{
  "type": "Feature",
  "properties": {
    "iso:country":"US",
    "sg:address":"402 Rampart Blvd",
    "sg:city":"New Kensington",
    "sg:classifiers":[
        {
            "category":"Building & Trades",
            "subcategory":"Plumbing",
            "type":"Services"
        }
    ],
    "sg:phone":"+1 412 793 5961",
    "sg:postcode":"15068",
    "sg:province":"PA",
    "sg:tags":[
        "contractor"
    ],
    "wof:name":"Backflow Management Inc",
    "wof:placetype":"venue"
},
  "geometry": {"coordinates":[-79.77774700000001,40.520358],"type":"Point"}
}