{
  "type": "Feature",
  "properties": {
    "addr:full":"307 Pike Rd Howard PA 16841",
    "addr:housenumber":"307",
    "addr:postcode":"16841",
    "addr:street":"Pike Rd",
    "iso:country":"US",
    "sg:address":"307 Pike Rd",
    "sg:city":"Howard",
    "sg:classifiers":[
        {
            "category":"Autos & Motor Vehicles",
            "subcategory":"Auto Supplies",
            "type":"Retail Goods"
        }
    ],
    "sg:phone":"+1   ",
    "sg:postcode":"16841",
    "sg:province":"PA",
    "wof:name":"Bargers Auto Audio",
    "wof:placetype":"venue"
},
  "geometry": {"coordinates":[-77.555767,40.99691],"type":"Point"}
}