{
  "type": "Feature",
  "properties": {
    "iso:country":"US",
    "sg:address":"4401 Richmond St",
    "sg:city":"Philadelphia",
    "sg:classifiers":[
        {
            "category":"Personal",
            "subcategory":"Beauty Salon",
            "type":"Services"
        }
    ],
    "sg:phone":"+1 215 535 8997",
    "sg:postcode":"19137",
    "sg:province":"PA",
    "sg:tags":[
        "hair"
    ],
    "wof:name":"Phil's Hair Styling",
    "wof:placetype":"venue"
},
  "geometry": {"coordinates":[-75.072931,39.997595],"type":"Point"}
}