{
  "type": "Feature",
  "properties": {
    "iso:country":"US",
    "sg:address":"300 Market St",
    "sg:city":"Kingston",
    "sg:classifiers":[
        {
            "category":"Travel",
            "subcategory":"Travel Agent",
            "type":"Entertainment"
        }
    ],
    "sg:phone":"+1   ",
    "sg:postcode":"18704",
    "sg:province":"PA",
    "sg:tags":[
        "tour",
        "agency"
    ],
    "wof:name":"Tenebaums Travel",
    "wof:placetype":"venue"
},
  "geometry": {"coordinates":[-75.89026699999999,41.25444],"type":"Point"}
}