{
  "type": "Feature",
  "properties": {
    "addr:full":"118 Deerpath Rd Media PA 19063",
    "addr:housenumber":"118",
    "addr:postcode":"19063",
    "addr:street":"Deerpath Rd",
    "iso:country":"US",
    "sg:address":"118 Deerpath Rd",
    "sg:city":"Media",
    "sg:classifiers":[
        {
            "category":"Wholesale",
            "subcategory":"Construction Materials",
            "type":"Manufacturing & Wholesale Goods"
        }
    ],
    "sg:phone":"+1 610 325 8828",
    "sg:postcode":"19063",
    "sg:province":"PA",
    "sg:tags":[
        "fence"
    ],
    "wof:name":"Cliff Thomas Tri State Fence",
    "wof:placetype":"venue"
},
  "geometry": {"coordinates":[-75.37568400000001,39.948631],"type":"Point"}
}