{
  "type": "Feature",
  "properties": {
    "iso:country":"US",
    "sg:address":"7733 State Rte 97",
    "sg:city":"Union City",
    "sg:classifiers":[
        {
            "category":"Wholesale",
            "subcategory":"Farm Supplies",
            "type":"Manufacturing & Wholesale Goods"
        }
    ],
    "sg:phone":"+1 814 438 2411",
    "sg:postcode":"16438",
    "sg:province":"PA",
    "sg:tags":[
        "feed"
    ],
    "sg:website":"www.ericcrawford.com",
    "wof:name":"Erie Crawford Co-Op",
    "wof:placetype":"venue"
},
  "geometry": {"coordinates":[-79.882873,41.904187],"type":"Point"}
}