{
  "type": "Feature",
  "properties": {
    "iso:country":"US",
    "sg:address":"112 N 4th St",
    "sg:city":"Columbia",
    "sg:classifiers":[
        {
            "category":"Building & Trades",
            "subcategory":"Construction",
            "type":"Services"
        }
    ],
    "sg:phone":"+1 717 684 6005",
    "sg:postcode":"17512",
    "sg:province":"PA",
    "sg:tags":[
        "windows"
    ],
    "wof:name":"DPS Screen & Window Repair",
    "wof:placetype":"venue"
},
  "geometry": {"coordinates":[-76.502343,40.0339],"type":"Point"}
}