{
  "type": "Feature",
  "properties": {
    "iso:country":"US",
    "sg:address":"4200 Whitaker Ave",
    "sg:city":"Philadelphia",
    "sg:classifiers":[
        {
            "category":"Autos & Motor Vehicles",
            "subcategory":"Fuel & Gas Station",
            "type":"Retail Goods"
        }
    ],
    "sg:phone":"+1 215 423 5123",
    "sg:postcode":"19124",
    "sg:province":"PA",
    "wof:name":"Exxon Station",
    "wof:placetype":"venue"
},
  "geometry": {"coordinates":[-75.1194,40.013],"type":"Point"}
}