{
  "type": "Feature",
  "properties": {
    "addr:full":"3514 W Chester Pike Newtown Square PA 19073",
    "addr:housenumber":"3514",
    "addr:postcode":"19073",
    "addr:street":"W Chester Pike",
    "iso:country":"US",
    "sg:address":"3514 W Chester Pike",
    "sg:city":"Newtown Square",
    "sg:classifiers":[
        {
            "category":"Banks & Credit Unions",
            "subcategory":"Bank",
            "type":"Services"
        }
    ],
    "sg:phone":"+1   ",
    "sg:postcode":"19073",
    "sg:province":"PA",
    "sg:tags":[
        "state"
    ],
    "wof:name":"Citizens Bank of Pennsylvania",
    "wof:placetype":"venue"
},
  "geometry": {"coordinates":[-75.392796,39.984953],"type":"Point"}
}