{
  "type": "Feature",
  "properties": {
    "addr:full":"1352 Easton Rd Warrington PA 18976",
    "addr:housenumber":"1352",
    "addr:postcode":"18976",
    "addr:street":"Easton Rd",
    "iso:country":"US",
    "sg:address":"1352 Easton Rd",
    "sg:city":"Warrington",
    "sg:classifiers":[
        {
            "category":"Utilities",
            "subcategory":"Mobile Phone",
            "type":"Services"
        },
        {
            "category":"Shopping",
            "type":"Retail Goods"
        }
    ],
    "sg:phone":"+1 215 491 1776",
    "sg:postcode":"18976",
    "sg:province":"PA",
    "sg:tags":[
        "communication",
        "merchandise",
        "telephone",
        "cellular",
        "radiotelephone"
    ],
    "wof:name":"Advanced Wireless Comm",
    "wof:placetype":"venue"
},
  "geometry": {"coordinates":[-75.133499,40.250301],"type":"Point"}
}