{
  "type": "Feature",
  "properties": {
    "iso:country":"US",
    "sg:address":"36 Railroad St",
    "sg:city":"Royersford",
    "sg:classifiers":[
        {
            "category":"Restaurant",
            "type":"Food & Drink"
        }
    ],
    "sg:phone":"+1   ",
    "sg:postcode":"19468",
    "sg:province":"PA",
    "sg:tags":[
        "eating"
    ],
    "wof:name":"Savannahs Kitchen Catering",
    "wof:placetype":"venue"
},
  "geometry": {"coordinates":[-75.566278,40.210052],"type":"Point"}
}