{
  "type": "Feature",
  "properties": {
    "iso:country":"US",
    "sg:address":"889 Poplar Church Rd",
    "sg:city":"Camp Hill",
    "sg:classifiers":[
        {
            "category":"Health Services",
            "subcategory":"Chiropractor",
            "type":"Services"
        }
    ],
    "sg:phone":"+1   ",
    "sg:postcode":"17011",
    "sg:province":"PA",
    "wof:name":"Countryside Chiropractic",
    "wof:placetype":"venue"
},
  "geometry": {"coordinates":[-76.924195,40.254048],"type":"Point"}
}