{
  "type": "Feature",
  "properties": {
    "iso:country":"US",
    "sg:address":"401 N Chester Rd",
    "sg:city":"West Chester",
    "sg:classifiers":[
        {
            "category":"Government",
            "subcategory":"Office",
            "type":"Public Place"
        }
    ],
    "sg:phone":"+1 610 436 1900",
    "sg:postcode":"19380",
    "sg:province":"PA",
    "sg:tags":[
        "state",
        "program"
    ],
    "sg:website":"www.dot.state.pa.us",
    "wof:name":"Transportation Dept-Mntnc",
    "wof:placetype":"venue"
},
  "geometry": {"coordinates":[-75.537712,39.978936],"type":"Point"}
}