{
  "type": "Feature",
  "properties": {
    "addr:full":"31 W City Ave Bala Cynwyd PA 19004",
    "addr:housenumber":"31",
    "addr:postcode":"19004",
    "addr:street":"W City Ave",
    "iso:country":"US",
    "sg:address":"31 W City Ave",
    "sg:city":"Bala Cynwyd",
    "sg:classifiers":[
        {
            "category":"Autos & Motor Vehicles",
            "subcategory":"Auto Supplies",
            "type":"Retail Goods"
        }
    ],
    "sg:phone":"+1 610 668 9448",
    "sg:postcode":"19004",
    "sg:province":"PA",
    "sg:tags":[
        "tire"
    ],
    "wof:name":"Firestone Tire & Service Centers",
    "wof:placetype":"venue"
},
  "geometry": {"coordinates":[-75.22820299999999,40.000301],"type":"Point"}
}