{
  "type": "Feature",
  "properties": {
    "iso:country":"US",
    "sg:address":"7616 Williams Way",
    "sg:city":"Elkins Park",
    "sg:classifiers":[
        {
            "category":"Social Services",
            "type":"Services"
        }
    ],
    "sg:phone":"+1   ",
    "sg:postcode":"19027",
    "sg:province":"PA",
    "sg:tags":[
        "national",
        "security"
    ],
    "wof:name":"Lynnewood Gardens Learning Ctr",
    "wof:placetype":"venue"
},
  "geometry": {"coordinates":[-75.150541,40.071919],"type":"Point"}
}