{
  "type": "Feature",
  "properties": {
    "addr:full":"205 Windsor Rd Pottstown PA 19464",
    "addr:housenumber":"205",
    "addr:postcode":"19464",
    "addr:street":"Windsor Rd",
    "iso:country":"US",
    "sg:address":"205 Windsor Rd",
    "sg:city":"Pottstown",
    "sg:classifiers":[
        {
            "category":"Professional",
            "subcategory":"Business Services",
            "type":"Services"
        }
    ],
    "sg:phone":"+1   ",
    "sg:postcode":"19464",
    "sg:province":"PA",
    "sg:tags":[
        "trade",
        "show"
    ],
    "wof:name":"General Exposition Services",
    "wof:placetype":"venue"
},
  "geometry": {"coordinates":[-75.555954,40.228981],"type":"Point"}
}