{
  "type": "Feature",
  "properties": {
    "iso:country":"US",
    "sg:address":"902 N Front St",
    "sg:city":"Lemoyne",
    "sg:classifiers":[
        {
            "category":"Shopping",
            "subcategory":"Mobile Phones",
            "type":"Retail Goods"
        }
    ],
    "sg:phone":"+1 717 579 2355",
    "sg:postcode":"17043",
    "sg:province":"PA",
    "sg:website":"www.celloneusa.com",
    "wof:name":"Cellular One",
    "wof:placetype":"venue"
},
  "geometry": {"coordinates":[-76.909897,40.266102],"type":"Point"}
}