{
  "type": "Feature",
  "properties": {
    "iso:country":"US",
    "sg:address":"4635 Old Oak Rd",
    "sg:city":"Doylestown",
    "sg:classifiers":[
        {
            "category":"Professional",
            "subcategory":"Art Services",
            "type":"Services"
        }
    ],
    "sg:phone":"+1 215 230 3439",
    "sg:postcode":"18902",
    "sg:province":"PA",
    "sg:tags":[
        "graphic",
        "designer"
    ],
    "wof:name":"Elf Designs",
    "wof:placetype":"venue"
},
  "geometry": {"coordinates":[-75.122299,40.352392],"type":"Point"}
}