{
  "type": "Feature",
  "properties": {
    "iso:country":"US",
    "sg:address":"534 Haines St",
    "sg:city":"Kane",
    "sg:classifiers":[
        {
            "category":"Professional",
            "type":"Services"
        }
    ],
    "sg:phone":"+1   ",
    "sg:postcode":"16735",
    "sg:province":"PA",
    "wof:name":"Pierson Hollowell Company Inc",
    "wof:placetype":"venue"
},
  "geometry": {"coordinates":[-78.80176,41.664171],"type":"Point"}
}