{
  "type": "Feature",
  "properties": {
    "iso:country":"US",
    "sg:address":"508 Center St",
    "sg:city":"Kennett Square",
    "sg:classifiers":[
        {
            "category":"Building & Trades",
            "subcategory":"Construction",
            "type":"Services"
        }
    ],
    "sg:phone":"+1 610 444 0995",
    "sg:postcode":"19348",
    "sg:province":"PA",
    "sg:tags":[
        "general",
        "contractor"
    ],
    "wof:name":"Giffin Construction",
    "wof:placetype":"venue"
},
  "geometry": {"coordinates":[-75.712188,39.839997],"type":"Point"}
}