{
  "type": "Feature",
  "properties": {
    "addr:full":"3500 Gillespie Dr York PA 17404",
    "addr:housenumber":"3500",
    "addr:postcode":"17404",
    "addr:street":"Gillespie Dr",
    "iso:country":"US",
    "sg:address":"3500 Gillespie Dr",
    "sg:city":"York",
    "sg:classifiers":[
        {
            "category":"Building & Trades",
            "subcategory":"Equipment Rental",
            "type":"Services"
        }
    ],
    "sg:phone":"+1   ",
    "sg:postcode":"17404",
    "sg:province":"PA",
    "wof:name":"Rent-All Service Inc",
    "wof:placetype":"venue"
},
  "geometry": {"coordinates":[-76.79669800000001,39.938814],"type":"Point"}
}