{
  "type": "Feature",
  "properties": {
    "addr:full":"2950 Brownsville Rd Pittsburgh PA 15227",
    "addr:housenumber":"2950",
    "addr:postcode":"15227",
    "addr:street":"Brownsville Rd",
    "iso:country":"US",
    "sg:address":"2950 Brownsville Rd",
    "sg:city":"Pittsburgh",
    "sg:classifiers":[
        {
            "category":"Autos & Motor Vehicles",
            "subcategory":"Automobile Sales",
            "type":"Retail Goods"
        }
    ],
    "sg:phone":"+1 412 882 4191",
    "sg:postcode":"15227",
    "sg:province":"PA",
    "sg:tags":[
        "car",
        "dealer"
    ],
    "wof:name":"Chester Mc Gann Auto Sales",
    "wof:placetype":"venue"
},
  "geometry": {"coordinates":[-79.976247,40.38137],"type":"Point"}
}