{
  "type": "Feature",
  "properties": {
    "iso:country":"US",
    "sg:address":"605 W Pike St",
    "sg:city":"Canonsburg",
    "sg:classifiers":[
        {
            "category":"Sports & Exercise",
            "subcategory":"Bowling",
            "type":"Entertainment"
        }
    ],
    "sg:phone":"+1 724 745 2695",
    "sg:postcode":"15317",
    "sg:province":"PA",
    "sg:website":"www.westpikebowl.com",
    "wof:name":"Westpike Bowl",
    "wof:placetype":"venue"
},
  "geometry": {"coordinates":[-80.20410200000001,40.257401],"type":"Point"}
}