{
  "type": "Feature",
  "properties": {
    "iso:country":"US",
    "sg:address":"5 Winterstown Rd",
    "sg:city":"Red Lion",
    "sg:classifiers":[
        {
            "category":"Food & Beverages",
            "subcategory":"Groceries & Convenience Stores",
            "type":"Retail Goods"
        }
    ],
    "sg:phone":"+1   ",
    "sg:postcode":"17356",
    "sg:province":"PA",
    "wof:name":"Rutters Farm Store 48",
    "wof:placetype":"venue"
},
  "geometry": {"coordinates":[-76.60218500000001,39.88686],"type":"Point"}
}