{
  "type": "Feature",
  "properties": {
    "iso:country":"US",
    "sg:address":"3017 W 12th St",
    "sg:city":"Erie",
    "sg:classifiers":[
        {
            "category":"Personal",
            "type":"Services"
        },
        {
            "category":"Retail",
            "subcategory":"Auto Rental",
            "type":"Services"
        },
        {
            "category":"Freight",
            "type":"Transportation"
        }
    ],
    "sg:phone":"+1 814 833 1727",
    "sg:postcode":"16505",
    "sg:province":"PA",
    "sg:tags":[
        "renting",
        "full",
        "leasing",
        "storage",
        "trucking",
        "truck",
        "mover",
        "local",
        "trailer"
    ],
    "wof:name":"U-Haul Neighborhood Dealer - Erie Drive Train",
    "wof:placetype":"venue"
},
  "geometry": {"coordinates":[-80.149534,42.098321],"type":"Point"}
}