{
  "type": "Feature",
  "properties": {
    "iso:country":"US",
    "sg:address":"1801 John F Kennedy Blvd",
    "sg:city":"Philadelphia",
    "sg:classifiers":[
        {
            "category":"Restaurant",
            "type":"Food & Drink"
        }
    ],
    "sg:phone":"+1 215 569 8686",
    "sg:postcode":"19103",
    "sg:province":"PA",
    "sg:tags":[
        "chinese"
    ],
    "wof:name":"City Garden Chinese Restaurant",
    "wof:placetype":"venue"
},
  "geometry": {"coordinates":[-75.1698,39.954102],"type":"Point"}
}