{
  "type": "Feature",
  "properties": {
    "iso:country":"US",
    "sg:address":"1819 John F Kennedy Blvd",
    "sg:city":"Philadelphia",
    "sg:classifiers":[
        {
            "category":"Professional",
            "subcategory":"Lawyer & Legal Services",
            "type":"Services"
        }
    ],
    "sg:phone":"+1 215 751 9440",
    "sg:postcode":"19103",
    "sg:province":"PA",
    "wof:name":"Gafni-Adler Sandra H",
    "wof:placetype":"venue"
},
  "geometry": {"coordinates":[-75.170097,39.954201],"type":"Point"}
}