{
  "type": "Feature",
  "properties": {
    "iso:country":"US",
    "sg:address":"525 Bridge St",
    "sg:city":"Old Forge",
    "sg:classifiers":[
        {
            "category":"Manufacturing",
            "subcategory":"Metals",
            "type":"Manufacturing & Wholesale Goods"
        }
    ],
    "sg:phone":"+1 570 457 7433",
    "sg:postcode":"18518",
    "sg:province":"PA",
    "wof:name":"Broan-Nu Tone Group",
    "wof:placetype":"venue"
},
  "geometry": {"coordinates":[-75.749683,41.353966],"type":"Point"}
}