{
  "type": "Feature",
  "properties": {
    "iso:country":"US",
    "sg:address":"424 N Main St",
    "sg:city":"Pittston",
    "sg:classifiers":[
        {
            "category":"Social Services",
            "subcategory":"Child Care",
            "type":"Services"
        }
    ],
    "sg:phone":"+1 570 655 6855",
    "sg:postcode":"18640",
    "sg:province":"PA",
    "sg:tags":[
        "day"
    ],
    "wof:name":"Sand Castle Day Care Svc",
    "wof:placetype":"venue"
},
  "geometry": {"coordinates":[-75.786599,41.334144],"type":"Point"}
}