{
  "type": "Feature",
  "properties": {
    "iso:country":"US",
    "sg:address":"1301 Oram St",
    "sg:city":"Scranton",
    "sg:classifiers":[
        {
            "category":"Wholesale",
            "subcategory":"Durable Goods & Equipment",
            "type":"Manufacturing & Wholesale Goods"
        }
    ],
    "sg:phone":"+1   ",
    "sg:postcode":"18504",
    "sg:province":"PA",
    "wof:name":"Ottos Treasures",
    "wof:placetype":"venue"
},
  "geometry": {"coordinates":[-75.675247,41.422678],"type":"Point"}
}