{
  "type": "Feature",
  "properties": {
    "iso:country":"US",
    "sg:address":"654 Knox Rd",
    "sg:city":"Knox",
    "sg:classifiers":[
        {
            "category":"Shopping",
            "type":"Retail Goods"
        }
    ],
    "sg:phone":"+1   ",
    "sg:postcode":"16232",
    "sg:province":"PA",
    "sg:tags":[
        "repair",
        "merchandise"
    ],
    "wof:name":"Daniel C Keth",
    "wof:placetype":"venue"
},
  "geometry": {"coordinates":[-79.54168,41.220387],"type":"Point"}
}