{
  "type": "Feature",
  "properties": {
    "iso:country":"US",
    "sg:address":"3535 Spear St",
    "sg:city":"Bethlehem",
    "sg:classifiers":[
        {
            "category":"Professional",
            "subcategory":"Computer Services",
            "type":"Services"
        }
    ],
    "sg:phone":"+1   ",
    "sg:postcode":"18020",
    "sg:province":"PA",
    "sg:tags":[
        "related"
    ],
    "wof:name":"Rmb Systems Corp",
    "wof:placetype":"venue"
},
  "geometry": {"coordinates":[-75.328692,40.654621],"type":"Point"}
}