{
  "type": "Feature",
  "properties": {
    "iso:country":"US",
    "sg:address":"135 Carol Rd",
    "sg:city":"East Stroudsburg",
    "sg:classifiers":[
        {
            "category":"Education",
            "subcategory":"Vocational School",
            "type":"Public Place"
        }
    ],
    "sg:phone":"+1   ",
    "sg:postcode":"18302",
    "sg:province":"PA",
    "sg:tags":[
        "training",
        "computer"
    ],
    "wof:name":"Computer Training Service",
    "wof:placetype":"venue"
},
  "geometry": {"coordinates":[-75.782886,41.322999],"type":"Point"}
}