{
  "type": "Feature",
  "properties": {
    "addr:full":"2070 Allentown Rd Quakertown PA 18951",
    "addr:postcode":"2070;18951",
    "addr:street":"Allentown Rd",
    "iso:country":"US",
    "sg:address":"2070 Allentown Rd",
    "sg:city":"Quakertown",
    "sg:classifiers":[
        {
            "category":"Professional",
            "subcategory":"Business Services",
            "type":"Services"
        }
    ],
    "sg:phone":"+1 215 536 2324",
    "sg:postcode":"18951",
    "sg:province":"PA",
    "sg:tags":[
        "auctioneer"
    ],
    "wof:name":"James W Mohr & Son Auction Co",
    "wof:placetype":"venue"
},
  "geometry": {"coordinates":[-75.398764,40.433603],"type":"Point"}
}