{
  "type": "Feature",
  "properties": {
    "iso:country":"US",
    "sg:address":"237 Shady Ln",
    "sg:city":"Middletown",
    "sg:classifiers":[
        {
            "category":"Building & Trades",
            "subcategory":"Construction",
            "type":"Services"
        }
    ],
    "sg:phone":"+1   ",
    "sg:postcode":"17057",
    "sg:province":"PA",
    "wof:name":"R M Miller Home Improvements",
    "wof:placetype":"venue"
},
  "geometry": {"coordinates":[-76.751577,40.21839],"type":"Point"}
}