{
  "type": "Feature",
  "properties": {
    "iso:country":"US",
    "sg:address":"200 Moores Rd",
    "sg:city":"Frazer",
    "sg:classifiers":[
        {
            "category":"Shopping",
            "subcategory":"Florist",
            "type":"Retail Goods"
        }
    ],
    "sg:phone":"+1 610 889 0110",
    "sg:postcode":"19355",
    "sg:province":"PA",
    "wof:name":"Philadelphia Memeorial Flowers",
    "wof:placetype":"venue"
},
  "geometry": {"coordinates":[-75.56574999999999,40.05161],"type":"Point"}
}