{
  "type": "Feature",
  "properties": {
    "iso:country":"US",
    "sg:address":"7936 Steubenville Pike",
    "sg:city":"Imperial",
    "sg:classifiers":[
        {
            "category":"Restaurant",
            "type":"Food & Drink"
        }
    ],
    "sg:phone":"+1 724 695 0434",
    "sg:postcode":"15126",
    "sg:province":"PA",
    "sg:tags":[
        "pizza"
    ],
    "wof:name":"Dons Pizza",
    "wof:placetype":"venue"
},
  "geometry": {"coordinates":[-80.239258,40.441738],"type":"Point"}
}