{
  "type": "Feature",
  "properties": {
    "iso:country":"US",
    "sg:address":"224 N 6th St",
    "sg:city":"Allentown",
    "sg:classifiers":[
        {
            "category":"Organizations",
            "subcategory":"Religious Organization",
            "type":"Services"
        }
    ],
    "sg:phone":"+1 610 434 1477",
    "sg:postcode":"18102",
    "sg:province":"PA",
    "wof:name":"Bethany E C Church",
    "wof:placetype":"venue"
},
  "geometry": {"coordinates":[-75.471603,40.6063],"type":"Point"}
}