{
  "type": "Feature",
  "properties": {
    "iso:country":"US",
    "sg:address":"5602 Field Stream Dr",
    "sg:city":"Export",
    "sg:classifiers":[
        {
            "category":"Professional",
            "subcategory":"Engineering",
            "type":"Services"
        }
    ],
    "sg:phone":"+1 724 733 1823",
    "sg:postcode":"15632",
    "sg:province":"PA",
    "sg:tags":[
        "engineer"
    ],
    "wof:name":"Aluminum Consultants Group",
    "wof:placetype":"venue"
},
  "geometry": {"coordinates":[-79.63690800000001,40.443215],"type":"Point"}
}