{
  "type": "Feature",
  "properties": {
    "iso:country":"US",
    "sg:address":"5122 Penn Ave",
    "sg:city":"Pittsburgh",
    "sg:classifiers":[
        {
            "category":"Education",
            "subcategory":"School",
            "type":"Public Place"
        }
    ],
    "sg:phone":"+1 412 361 6080",
    "sg:postcode":"15224",
    "sg:province":"PA",
    "wof:name":"Little Angels Learning Ctr",
    "wof:placetype":"venue"
},
  "geometry": {"coordinates":[-79.941951,40.464793],"type":"Point"}
}