{
  "type": "Feature",
  "properties": {
    "addr:full":"2604 Moravian Ave Allentown PA 18103",
    "addr:housenumber":"2604",
    "addr:postcode":"18103",
    "addr:street":"Moravian Ave",
    "iso:country":"US",
    "sg:address":"2604 Moravian Ave",
    "sg:city":"Allentown",
    "sg:classifiers":[
        {
            "category":"Utilities",
            "subcategory":"Fuel Oil & Lpg",
            "type":"Services"
        }
    ],
    "sg:phone":"+1   ",
    "sg:postcode":"18103",
    "sg:province":"PA",
    "sg:tags":[
        "dealer"
    ],
    "wof:name":"Petrilla Fuel",
    "wof:placetype":"venue"
},
  "geometry": {"coordinates":[-75.485759,40.565342],"type":"Point"}
}