{
  "type": "Feature",
  "properties": {
    "iso:country":"US",
    "sg:address":"2708 W Girard Ave",
    "sg:city":"Philadelphia",
    "sg:classifiers":[
        {
            "category":"Shopping",
            "subcategory":"Pets & Pet Supplies",
            "type":"Retail Goods"
        },
        {
            "category":"Retail",
            "subcategory":"Animal Services",
            "type":"Services"
        }
    ],
    "sg:phone":"+1 267 514 7991",
    "sg:postcode":"19130",
    "sg:province":"PA",
    "sg:tags":[
        "grooming",
        "furnishing",
        "dog",
        "store",
        "cat"
    ],
    "sg:website":"www.bestinshowgrooming.com",
    "wof:name":"Best In Show Grooming Salon",
    "wof:placetype":"venue"
},
  "geometry": {"coordinates":[-75.180908,39.974141],"type":"Point"}
}