{
  "type": "Feature",
  "properties": {
    "iso:country":"US",
    "sg:address":"440 W Sedgwick St",
    "sg:city":"Philadelphia",
    "sg:classifiers":[
        {
            "category":"Museum",
            "subcategory":"Botanical Garden",
            "type":"Entertainment"
        }
    ],
    "sg:phone":"+1 215 848 2853",
    "sg:postcode":"19119",
    "sg:province":"PA",
    "wof:name":"Sedgwick Gardens",
    "wof:placetype":"venue"
},
  "geometry": {"coordinates":[-75.194862,40.049229],"type":"Point"}
}