{
  "type": "Feature",
  "properties": {
    "iso:country":"US",
    "sg:address":"4477 Niblick Dr",
    "sg:city":"Pittsburgh",
    "sg:classifiers":[
        {
            "category":"Home & Garden",
            "subcategory":"Household Appliances",
            "type":"Retail Goods"
        }
    ],
    "sg:phone":"+1 412 882 4678",
    "sg:postcode":"15236",
    "sg:province":"PA",
    "sg:tags":[
        "repair",
        "major"
    ],
    "wof:name":"Point Appliance Service",
    "wof:placetype":"venue"
},
  "geometry": {"coordinates":[-79.983299,40.358501],"type":"Point"}
}