{
  "type": "Feature",
  "properties": {
    "iso:country":"US",
    "sg:address":"28 Northbrook Ln",
    "sg:city":"Shrewsbury",
    "sg:classifiers":[
        {
            "category":"Health Services",
            "subcategory":"Health Practitioner",
            "type":"Services"
        }
    ],
    "sg:phone":"+1 717 235 6900",
    "sg:postcode":"17361",
    "sg:province":"PA",
    "sg:tags":[
        "therapist",
        "physical"
    ],
    "wof:name":"Shrewsbury Physical Therapy",
    "wof:placetype":"venue"
},
  "geometry": {"coordinates":[-76.670991,39.778049],"type":"Point"}
}