{
  "type": "Feature",
  "properties": {
    "addr:full":"1762 Oak Hill Dr Huntingdon Vly PA 19006",
    "addr:housenumber":"1762",
    "addr:postcode":"19006",
    "addr:street":"Oak Hill Dr",
    "iso:country":"US",
    "sg:address":"1762 Oak Hill Dr",
    "sg:city":"Huntingdon Vly",
    "sg:classifiers":[
        {
            "category":"Wholesale",
            "subcategory":"Non-durable Goods",
            "type":"Manufacturing & Wholesale Goods"
        }
    ],
    "sg:phone":"+1 215 938 7679",
    "sg:postcode":"19006",
    "sg:province":"PA",
    "sg:tags":[
        "advertising"
    ],
    "sg:website":"www.gilbertpromos.com",
    "wof:name":"Gilbert Advertising Inc",
    "wof:placetype":"venue"
},
  "geometry": {"coordinates":[-75.076519,40.109429],"type":"Point"}
}