{
  "type": "Feature",
  "properties": {
    "iso:country":"US",
    "sg:address":"65 Meadow Rd",
    "sg:city":"Quakertown",
    "sg:classifiers":[
        {
            "category":"Building & Trades",
            "subcategory":"Plumbing",
            "type":"Services"
        }
    ],
    "sg:phone":"+1 215 536 8413",
    "sg:postcode":"18951",
    "sg:province":"PA",
    "sg:tags":[
        "air",
        "conditioning",
        "contractor",
        "system",
        "heating"
    ],
    "wof:name":"Brown's Heating & Cooling",
    "wof:placetype":"venue"
},
  "geometry": {"coordinates":[-75.311595,40.473975],"type":"Point"}
}