{
  "type": "Feature",
  "properties": {
    "iso:country":"US",
    "sg:address":"203 Williams St",
    "sg:city":"Bradford",
    "sg:classifiers":[
        {
            "category":"Retail",
            "subcategory":"Repair Shop",
            "type":"Services"
        },
        {
            "category":"Building & Trades",
            "subcategory":"Plumbing",
            "type":"Services"
        }
    ],
    "sg:phone":"+1 814 362 1878",
    "sg:postcode":"16701",
    "sg:province":"PA",
    "sg:tags":[
        "refuse",
        "consulting",
        "business",
        "septic",
        "system"
    ],
    "wof:name":"J & J Honey Dipping Inc",
    "wof:placetype":"venue"
},
  "geometry": {"coordinates":[-78.639003,41.964111],"type":"Point"}
}