{
  "type": "Feature",
  "properties": {
    "addr:full":"588 E Broad St Souderton PA 18964",
    "addr:housenumber":"588",
    "addr:postcode":"18964",
    "addr:street":"E Broad St",
    "iso:country":"US",
    "sg:address":"588 E Broad St",
    "sg:city":"Souderton",
    "sg:classifiers":[
        {
            "category":"Retail",
            "subcategory":"Laundry & Dry Cleaning",
            "type":"Services"
        }
    ],
    "sg:phone":"+1   ",
    "sg:postcode":"18964",
    "sg:province":"PA",
    "sg:tags":[
        "drycleaning",
        "plant"
    ],
    "wof:name":"Countryfair Cleaners",
    "wof:placetype":"venue"
},
  "geometry": {"coordinates":[-75.31602599999999,40.311997],"type":"Point"}
}