{
  "type": "Feature",
  "properties": {
    "iso:country":"US",
    "sg:address":"1325 N River St",
    "sg:city":"Wilkes Barre",
    "sg:classifiers":[
        {
            "category":"Shopping",
            "subcategory":"Hobbies, Toys, & Games",
            "type":"Retail Goods"
        }
    ],
    "sg:phone":"+1 570 822 9088",
    "sg:postcode":"18705",
    "sg:province":"PA",
    "wof:name":"Joes & Bows",
    "wof:placetype":"venue"
},
  "geometry": {"coordinates":[-75.84593099999999,41.289294],"type":"Point"}
}