{
  "type": "Feature",
  "properties": {
    "addr:full":"100 Church Rd Schuylkill Haven PA 17972",
    "addr:housenumber":"100",
    "addr:postcode":"17972",
    "addr:street":"Church Rd",
    "iso:country":"US",
    "sg:address":"100 Church Rd",
    "sg:city":"Schuylkill Haven",
    "sg:classifiers":[
        {
            "category":"Building & Trades",
            "subcategory":"Construction",
            "type":"Services"
        }
    ],
    "sg:phone":"+1   ",
    "sg:postcode":"17972",
    "sg:province":"PA",
    "sg:tags":[
        "excavation",
        "contractor"
    ],
    "wof:name":"L & L Excavating",
    "wof:placetype":"venue"
},
  "geometry": {"coordinates":[-76.25,40.60696],"type":"Point"}
}