{
  "type": "Feature",
  "properties": {
    "iso:country":"US",
    "sg:address":"331 1st St",
    "sg:city":"Butler",
    "sg:classifiers":[
        {
            "category":"Real Estate",
            "subcategory":"Real Estate Operator",
            "type":"Services"
        }
    ],
    "sg:phone":"+1   ",
    "sg:postcode":"16001",
    "sg:province":"PA",
    "sg:tags":[
        "building",
        "nonresidential"
    ],
    "wof:name":"Thundermart Shopping",
    "wof:placetype":"venue"
},
  "geometry": {"coordinates":[-79.885621,40.864965],"type":"Point"}
}