{
  "type": "Feature",
  "properties": {
    "iso:country":"US",
    "sg:address":"320 S Richland Ave",
    "sg:city":"York",
    "sg:classifiers":[
        {
            "category":"Autos & Motor Vehicles",
            "subcategory":"Automobile Sales",
            "type":"Retail Goods"
        }
    ],
    "sg:phone":"+1 717 846 3070",
    "sg:postcode":"17404",
    "sg:province":"PA",
    "sg:tags":[
        "used"
    ],
    "wof:name":"West Side Sales",
    "wof:placetype":"venue"
},
  "geometry": {"coordinates":[-76.746557,39.949676],"type":"Point"}
}