{
  "type": "Feature",
  "properties": {
    "addr:full":"3415 Ligonier St Pittsburgh PA 15201",
    "addr:housenumber":"3415",
    "addr:postcode":"15201",
    "addr:street":"Ligonier St",
    "iso:country":"US",
    "sg:address":"3415 Ligonier St",
    "sg:city":"Pittsburgh",
    "sg:classifiers":[
        {
            "category":"Organizations",
            "subcategory":"Religious Organization",
            "type":"Services"
        }
    ],
    "sg:phone":"+1 412 621 4311",
    "sg:postcode":"15201",
    "sg:province":"PA",
    "sg:tags":[
        "church"
    ],
    "wof:name":"Trinity Baptist Church",
    "wof:placetype":"venue"
},
  "geometry": {"coordinates":[-79.965766,40.462696],"type":"Point"}
}