{
  "type": "Feature",
  "properties": {
    "addr:full":"5126 W State St Coopersburg PA 18036",
    "addr:housenumber":"5126",
    "addr:postcode":"18036",
    "addr:street":"W State St",
    "iso:country":"US",
    "sg:address":"5126 W State St",
    "sg:city":"Coopersburg",
    "sg:classifiers":[
        {
            "category":"Real Estate",
            "subcategory":"Real Estate Services",
            "type":"Services"
        },
        {
            "category":"Building & Trades",
            "subcategory":"Electrical",
            "type":"Services"
        }
    ],
    "sg:phone":"+1 610 282 4775",
    "sg:postcode":"18036",
    "sg:province":"PA",
    "sg:tags":[
        "home",
        "inspector",
        "electrician"
    ],
    "wof:name":"Oswald Willis A Jr Electrical Contractor",
    "wof:placetype":"venue"
},
  "geometry": {"coordinates":[-75.40540300000001,40.509602],"type":"Point"}
}