{
  "type": "Feature",
  "properties": {
    "iso:country":"US",
    "sg:address":"806 S Potomac St",
    "sg:city":"Waynesboro",
    "sg:classifiers":[
        {
            "category":"Autos & Motor Vehicles",
            "subcategory":"Fuel & Gas Station",
            "type":"Retail Goods"
        }
    ],
    "sg:phone":"+1 717 762 9984",
    "sg:postcode":"17268",
    "sg:province":"PA",
    "wof:name":"Spsi-Waynesboro Food & Fuel",
    "wof:placetype":"venue"
},
  "geometry": {"coordinates":[-77.591202,39.743698],"type":"Point"}
}