{
  "type": "Feature",
  "properties": {
    "iso:country":"US",
    "sg:address":"500 Lurgan Rd",
    "sg:city":"New Hope",
    "sg:classifiers":[
        {
            "category":"Professional",
            "type":"Services"
        }
    ],
    "sg:phone":"+1   ",
    "sg:postcode":"18938",
    "sg:province":"PA",
    "wof:name":"Alva Corporation",
    "wof:placetype":"venue"
},
  "geometry": {"coordinates":[-74.93870800000001,40.323759],"type":"Point"}
}