{
  "type": "Feature",
  "properties": {
    "iso:country":"US",
    "sg:address":"54 Park Ave",
    "sg:city":"Jenkintown",
    "sg:classifiers":[
        {
            "category":"Building & Trades",
            "subcategory":"Plumbing",
            "type":"Services"
        }
    ],
    "sg:phone":"+1 215 379 2219",
    "sg:postcode":"19046",
    "sg:province":"PA",
    "sg:tags":[
        "plumbing",
        "contractor"
    ],
    "wof:name":"Luke Weidemann Inc",
    "wof:placetype":"venue"
},
  "geometry": {"coordinates":[-75.089761,40.082673],"type":"Point"}
}