{
  "type": "Feature",
  "properties": {
    "addr:full":"423 E Main St Middleburg PA 17842",
    "addr:housenumber":"423",
    "addr:postcode":"17842",
    "addr:street":"E Main St",
    "iso:country":"US",
    "sg:address":"423 E Main St",
    "sg:city":"Middleburg",
    "sg:classifiers":[
        {
            "category":"Health Services",
            "subcategory":"Optometrist",
            "type":"Services"
        }
    ],
    "sg:phone":"+1 570 837 0112",
    "sg:postcode":"17842",
    "sg:province":"PA",
    "wof:name":"Daniel K Gift OD",
    "wof:placetype":"venue"
},
  "geometry": {"coordinates":[-77.0386,40.788812],"type":"Point"}
}