{
  "type": "Feature",
  "properties": {
    "iso:country":"US",
    "sg:address":"216 N River St",
    "sg:city":"Wilkes Barre",
    "sg:classifiers":[
        {
            "category":"Insurance",
            "subcategory":"Health Insurance",
            "type":"Services"
        }
    ],
    "sg:phone":"+1   ",
    "sg:postcode":"18702",
    "sg:province":"PA",
    "sg:tags":[
        "organization",
        "maintenance"
    ],
    "wof:name":"Healthamerica PA Regional Off",
    "wof:placetype":"venue"
},
  "geometry": {"coordinates":[-75.87681000000001,41.252297],"type":"Point"}
}