{
  "type": "Feature",
  "properties": {
    "iso:country":"US",
    "sg:address":"396 Rodi Rd",
    "sg:city":"Pittsburgh",
    "sg:classifiers":[
        {
            "category":"Professional",
            "subcategory":"Lawyer & Legal Services",
            "type":"Services"
        }
    ],
    "sg:phone":"+1 412 244 0327",
    "sg:postcode":"15235",
    "sg:province":"PA",
    "wof:name":"John P Donovan",
    "wof:placetype":"venue"
},
  "geometry": {"coordinates":[-79.826077,40.452879],"type":"Point"}
}