{
  "type": "Feature",
  "properties": {
    "addr:full":"7830 Main St Fogelsville PA 18051",
    "addr:housenumber":"7830",
    "addr:postcode":"18051",
    "addr:street":"Main St",
    "iso:country":"US",
    "sg:address":"7830 Main St",
    "sg:city":"Fogelsville",
    "sg:classifiers":[
        {
            "category":"Home & Garden",
            "subcategory":"Household Appliances",
            "type":"Retail Goods"
        }
    ],
    "sg:phone":"+1 610 366 7936",
    "sg:postcode":"18051",
    "sg:province":"PA",
    "wof:name":"Hontz's",
    "wof:placetype":"venue"
},
  "geometry": {"coordinates":[-75.629992,40.583699],"type":"Point"}
}