{
  "type": "Feature",
  "properties": {
    "iso:country":"US",
    "sg:address":"20 E Washington St",
    "sg:city":"New Castle",
    "sg:classifiers":[
        {
            "category":"Manufacturing",
            "subcategory":"Food",
            "type":"Manufacturing & Wholesale Goods"
        }
    ],
    "sg:phone":"+1 724 658 4348",
    "sg:postcode":"16101",
    "sg:province":"PA",
    "sg:tags":[
        "brewer"
    ],
    "wof:name":"House Of Brews",
    "wof:placetype":"venue"
},
  "geometry": {"coordinates":[-80.34571200000001,40.999955],"type":"Point"}
}