{
  "type": "Feature",
  "properties": {
    "addr:full":"179 Hughes Rd King Of Prussia PA 19406",
    "addr:housenumber":"179",
    "addr:postcode":"19406",
    "addr:street":"Hughes Rd",
    "iso:country":"US",
    "sg:address":"179 Hughes Rd",
    "sg:city":"King Of Prussia",
    "sg:classifiers":[
        {
            "category":"Health Services",
            "subcategory":"Doctor",
            "type":"Services"
        }
    ],
    "sg:phone":"+1   ",
    "sg:postcode":"19406",
    "sg:province":"PA",
    "sg:tags":[
        "medical"
    ],
    "wof:name":"David A Scola MD",
    "wof:placetype":"venue"
},
  "geometry": {"coordinates":[-75.35486299999999,40.072415],"type":"Point"}
}