{
  "type": "Feature",
  "properties": {
    "iso:country":"US",
    "sg:address":"2810 Paxton St Ste C",
    "sg:city":"Harrisburg",
    "sg:classifiers":[
        {
            "category":"Personal",
            "subcategory":"Skin Care",
            "type":"Services"
        },
        {
            "category":"Personal",
            "subcategory":"Day Spa",
            "type":"Services"
        }
    ],
    "sg:phone":"+1 717 558 7585",
    "sg:postcode":"17111",
    "sg:province":"PA",
    "wof:name":"Xpose",
    "wof:placetype":"venue"
},
  "geometry": {"coordinates":[-76.841432,40.255966],"type":"Point"}
}