{
  "type": "Feature",
  "properties": {
    "iso:country":"US",
    "sg:address":"230 Clifton Ave",
    "sg:city":"Pittsburgh",
    "sg:classifiers":[
        {
            "category":"Professional",
            "subcategory":"Business Services",
            "type":"Services"
        }
    ],
    "sg:phone":"+1 412 782 0664",
    "sg:postcode":"15215",
    "sg:province":"PA",
    "sg:tags":[
        "pool",
        "swimming"
    ],
    "wof:name":"JME Pools Inc",
    "wof:placetype":"venue"
},
  "geometry": {"coordinates":[-79.928496,40.496698],"type":"Point"}
}