{
  "type": "Feature",
  "properties": {
    "addr:full":"57 E City Ave Bala Cynwyd PA 19004",
    "addr:housenumber":"57",
    "addr:postcode":"19004",
    "addr:street":"E City Ave",
    "iso:country":"US",
    "sg:address":"57 E City Ave",
    "sg:city":"Bala Cynwyd",
    "sg:classifiers":[
        {
            "category":"Shopping",
            "subcategory":"Shoes",
            "type":"Retail Goods"
        }
    ],
    "sg:phone":"+1 610 668 8812",
    "sg:postcode":"19004",
    "sg:province":"PA",
    "sg:tags":[
        "store"
    ],
    "wof:name":"Bare Feet Shoes",
    "wof:placetype":"venue"
},
  "geometry": {"coordinates":[-75.22489899999999,40.002102],"type":"Point"}
}