{
  "type": "Feature",
  "properties": {
    "addr:full":"10986 Greenlee Rd Waterford PA 16441",
    "addr:postcode":"10986;16441",
    "addr:street":"Greenlee Rd",
    "iso:country":"US",
    "sg:address":"10986 Greenlee Rd",
    "sg:city":"Waterford",
    "sg:classifiers":[
        {
            "category":"Autos & Motor Vehicles",
            "subcategory":"Auto Supplies",
            "type":"Retail Goods"
        }
    ],
    "sg:phone":"+1   ",
    "sg:postcode":"16441",
    "sg:province":"PA",
    "wof:name":"Show N Go Auto Accessories",
    "wof:placetype":"venue"
},
  "geometry": {"coordinates":[-80.02860200000001,41.970325],"type":"Point"}
}