{
  "type": "Feature",
  "properties": {
    "addr:full":"879 Douglass Ave Elkins Park PA 19027",
    "addr:housenumber":"879",
    "addr:postcode":"19027",
    "addr:street":"Douglass Ave",
    "iso:country":"US",
    "sg:address":"879 Douglass Ave",
    "sg:city":"Elkins Park",
    "sg:classifiers":[
        {
            "category":"Building & Trades",
            "subcategory":"Cleaning & Sanitation",
            "type":"Services"
        }
    ],
    "sg:phone":"+1 215 576 8040",
    "sg:postcode":"19027",
    "sg:province":"PA",
    "sg:tags":[
        "janitor"
    ],
    "wof:name":"Pride Janitorial Svc",
    "wof:placetype":"venue"
},
  "geometry": {"coordinates":[-75.10764,40.08519],"type":"Point"}
}