{
  "type": "Feature",
  "properties": {
    "addr:full":"105 E Glenside Ave Glenside PA 19038",
    "addr:housenumber":"105",
    "addr:postcode":"19038",
    "addr:street":"E Glenside Ave",
    "iso:country":"US",
    "sg:address":"105 E Glenside Ave",
    "sg:city":"Glenside",
    "sg:classifiers":[
        {
            "category":"Professional",
            "subcategory":"Detective & Security Services",
            "type":"Services"
        }
    ],
    "sg:phone":"+1 215 886 6004",
    "sg:postcode":"19038",
    "sg:province":"PA",
    "sg:tags":[
        "information",
        "bureau"
    ],
    "wof:name":"Icom Services Inc",
    "wof:placetype":"venue"
},
  "geometry": {"coordinates":[-75.152179,40.100237],"type":"Point"}
}