{
  "type": "Feature",
  "properties": {
    "addr:full":"940 Scattergood St Philadelphia PA 19124",
    "addr:housenumber":"940",
    "addr:postcode":"19124",
    "addr:street":"Scattergood St",
    "iso:country":"US",
    "sg:address":"940 Scattergood St",
    "sg:city":"Philadelphia",
    "sg:classifiers":[
        {
            "category":"Building & Trades",
            "subcategory":"Construction",
            "type":"Services"
        }
    ],
    "sg:phone":"+1 215 289 6198",
    "sg:postcode":"19124",
    "sg:province":"PA",
    "sg:tags":[
        "contractor",
        "painting",
        "hanging"
    ],
    "wof:name":"Maher Painting Tom",
    "wof:placetype":"venue"
},
  "geometry": {"coordinates":[-75.090827,40.032254],"type":"Point"}
}