{
  "type": "Feature",
  "properties": {
    "iso:country":"US",
    "sg:address":"410 Franklin St",
    "sg:city":"Clymer",
    "sg:classifiers":[
        {
            "category":"Professional",
            "subcategory":"Accounting & Tax Preparation",
            "type":"Services"
        }
    ],
    "sg:phone":"+1   ",
    "sg:postcode":"15728",
    "sg:province":"PA",
    "wof:name":"Ronald Thornton",
    "wof:placetype":"venue"
},
  "geometry": {"coordinates":[-79.01029200000001,40.669628],"type":"Point"}
}