{
  "type": "Feature",
  "properties": {
    "addr:full":"6236 Nathan Hale Ct Bensalem PA 19020",
    "addr:housenumber":"6236",
    "addr:postcode":"19020",
    "addr:street":"Nathan Hale Ct",
    "iso:country":"US",
    "sg:address":"6236 Nathan Hale Ct",
    "sg:city":"Bensalem",
    "sg:classifiers":[
        {
            "category":"Building & Trades",
            "subcategory":"Pest Control",
            "type":"Services"
        }
    ],
    "sg:phone":"+1   ",
    "sg:postcode":"19020",
    "sg:province":"PA",
    "wof:name":"R & M Pest Control",
    "wof:placetype":"venue"
},
  "geometry": {"coordinates":[-74.927769,40.142841],"type":"Point"}
}