{
  "type": "Feature",
  "properties": {
    "iso:country":"US",
    "sg:address":"543 Maple Ave",
    "sg:city":"Doylestown",
    "sg:classifiers":[
        {
            "category":"Retail",
            "subcategory":"Laundry & Dry Cleaning",
            "type":"Services"
        }
    ],
    "sg:phone":"+1 215 348 0188",
    "sg:postcode":"18901",
    "sg:province":"PA",
    "sg:tags":[
        "cleaners",
        "rug",
        "carpet"
    ],
    "wof:name":"Rainbow Brite Carpet Care",
    "wof:placetype":"venue"
},
  "geometry": {"coordinates":[-75.117965,40.318887],"type":"Point"}
}