{
  "type": "Feature",
  "properties": {
    "iso:country":"US",
    "sg:address":"2649 Schoenersville Rd",
    "sg:city":"Bethlehem",
    "sg:classifiers":[
        {
            "category":"Health Services",
            "subcategory":"Doctor",
            "type":"Services"
        }
    ],
    "sg:phone":"+1 610 866 2233",
    "sg:postcode":"18017",
    "sg:province":"PA",
    "sg:tags":[
        "cardiologist"
    ],
    "sg:website":"www.lvcardiology.com",
    "wof:name":"Lehigh Valley Cardiology Assoc",
    "wof:placetype":"venue"
},
  "geometry": {"coordinates":[-75.40830200000001,40.647499],"type":"Point"}
}