{
  "type": "Feature",
  "properties": {
    "addr:full":"705 Darby Ln Lancaster PA 17601",
    "addr:housenumber":"705",
    "addr:postcode":"17601",
    "addr:street":"Darby Ln",
    "iso:country":"US",
    "sg:address":"705 Darby Ln",
    "sg:city":"Lancaster",
    "sg:classifiers":[
        {
            "category":"Building & Trades",
            "subcategory":"Landscaping Services",
            "type":"Services"
        }
    ],
    "sg:phone":"+1   ",
    "sg:postcode":"17601",
    "sg:province":"PA",
    "wof:name":"A Plus Lawn Care",
    "wof:placetype":"venue"
},
  "geometry": {"coordinates":[-76.39444899999999,40.059081],"type":"Point"}
}