{
  "type": "Feature",
  "properties": {
    "iso:country":"US",
    "sg:address":"401 Cranberry St",
    "sg:city":"Erie",
    "sg:classifiers":[
        {
            "category":"Insurance",
            "subcategory":"Insurance Agent",
            "type":"Services"
        }
    ],
    "sg:phone":"+1 814 453 4357",
    "sg:postcode":"16507",
    "sg:province":"PA",
    "sg:tags":[
        "employee",
        "benefit"
    ],
    "sg:website":"www.chreams.com",
    "wof:name":"C H Reams & Associates Inc",
    "wof:placetype":"venue"
},
  "geometry": {"coordinates":[-80.111863,42.12169],"type":"Point"}
}