{
  "type": "Feature",
  "properties": {
    "iso:country":"US",
    "sg:address":"661 Palomino Dr",
    "sg:city":"Catasauqua",
    "sg:classifiers":[
        {
            "category":"Professional",
            "subcategory":"Testing Lab",
            "type":"Services"
        }
    ],
    "sg:phone":"+1   ",
    "sg:postcode":"18032",
    "sg:province":"PA",
    "sg:tags":[
        "laboratory"
    ],
    "wof:name":"Susan J Hirner",
    "wof:placetype":"venue"
},
  "geometry": {"coordinates":[-75.474199,40.668311],"type":"Point"}
}