{
  "type": "Feature",
  "properties": {
    "addr:full":"6829 Ruppsville Rd Allentown PA 18106",
    "addr:housenumber":"6829",
    "addr:postcode":"18106",
    "addr:street":"Ruppsville Rd",
    "iso:country":"US",
    "sg:address":"6829 Ruppsville Rd",
    "sg:city":"Allentown",
    "sg:classifiers":[
        {
            "category":"Wholesale",
            "subcategory":"Machinery & Supplies",
            "type":"Manufacturing & Wholesale Goods"
        }
    ],
    "sg:phone":"+1 610 395 8757",
    "sg:postcode":"18106",
    "sg:province":"PA",
    "sg:tags":[
        "packaging"
    ],
    "wof:name":"Pax Industries",
    "wof:placetype":"venue"
},
  "geometry": {"coordinates":[-75.59906100000001,40.575764],"type":"Point"}
}