{
  "type": "Feature",
  "properties": {
    "addr:full":"250 E Fayette St Uniontown PA 15401",
    "addr:housenumber":"250",
    "addr:postcode":"15401",
    "addr:street":"E Fayette St",
    "iso:country":"US",
    "sg:address":"250 E Fayette St",
    "sg:city":"Uniontown",
    "sg:classifiers":[
        {
            "category":"Health Services",
            "subcategory":"Hospital",
            "type":"Services"
        },
        {
            "category":"Health Services",
            "subcategory":"Clinic",
            "type":"Services"
        }
    ],
    "sg:phone":"+1 724 437 1151",
    "sg:postcode":"15401",
    "sg:province":"PA",
    "sg:tags":[
        "mental"
    ],
    "wof:name":"Chestnut Ridge Counseling Svcs",
    "wof:placetype":"venue"
},
  "geometry": {"coordinates":[-79.716829,39.89524],"type":"Point"}
}