{
  "type": "Feature",
  "properties": {
    "addr:full":"135 S Main St Pittston PA 18640",
    "addr:housenumber":"135",
    "addr:postcode":"18640",
    "addr:street":"S Main St",
    "iso:country":"US",
    "sg:address":"135 S Main St",
    "sg:city":"Pittston",
    "sg:classifiers":[
        {
            "category":"Professional",
            "subcategory":"Lawyer & Legal Services",
            "type":"Services"
        }
    ],
    "sg:phone":"+1   ",
    "sg:postcode":"18640",
    "sg:province":"PA",
    "wof:name":"Approprate Dspute Rsltion Svcs",
    "wof:placetype":"venue"
},
  "geometry": {"coordinates":[-75.79324200000001,41.319091],"type":"Point"}
}