{
  "type": "Feature",
  "properties": {
    "iso:country":"US",
    "sg:address":"444 Swedesford Rd",
    "sg:city":"Berwyn",
    "sg:classifiers":[
        {
            "category":"Restaurant",
            "type":"Food & Drink"
        }
    ],
    "sg:phone":"+1 610 993 0885",
    "sg:postcode":"19312",
    "sg:province":"PA",
    "sg:tags":[
        "pizza"
    ],
    "wof:name":"Dimeo Pizza, Inc",
    "wof:placetype":"venue"
},
  "geometry": {"coordinates":[-75.447468,40.069275],"type":"Point"}
}