{
  "type": "Feature",
  "properties": {
    "iso:country":"US",
    "sg:address":"36 S 7th St",
    "sg:city":"Philadelphia",
    "sg:classifiers":[
        {
            "category":"Coffee & Tea",
            "type":"Food & Drink"
        }
    ],
    "sg:phone":"+1 215 627 3233",
    "sg:postcode":"19106",
    "sg:province":"PA",
    "sg:website":"www.loreschocolates.com",
    "wof:name":"Lore's Espresso",
    "wof:placetype":"venue"
},
  "geometry": {"coordinates":[-75.15222300000001,39.949934],"type":"Point"}
}