{
  "type": "Feature",
  "properties": {
    "iso:country":"US",
    "sg:address":"969 Trenton Rd",
    "sg:city":"Fairless Hills",
    "sg:classifiers":[
        {
            "category":"Personal",
            "subcategory":"Beauty Salon",
            "type":"Services"
        }
    ],
    "sg:phone":"+1 215 295 0300",
    "sg:postcode":"19030",
    "sg:province":"PA",
    "sg:tags":[
        "shop"
    ],
    "wof:name":"Marty's Beauty Salon",
    "wof:placetype":"venue"
},
  "geometry": {"coordinates":[-74.828845,40.187919],"type":"Point"}
}