{
  "type": "Feature",
  "properties": {
    "iso:country":"US",
    "sg:address":"743 Chain St",
    "sg:city":"Norristown",
    "sg:classifiers":[
        {
            "category":"Retail",
            "subcategory":"Repair Shop",
            "type":"Services"
        }
    ],
    "sg:phone":"+1   ",
    "sg:postcode":"19401",
    "sg:province":"PA",
    "wof:name":"Masters Touch Cleaning Service",
    "wof:placetype":"venue"
},
  "geometry": {"coordinates":[-75.346705,40.122458],"type":"Point"}
}