{
  "type": "Feature",
  "properties": {
    "iso:country":"US",
    "sg:address":"3020 Robbins Station Rd",
    "sg:city":"Irwin",
    "sg:classifiers":[
        {
            "category":"Building & Trades",
            "subcategory":"Construction",
            "type":"Services"
        }
    ],
    "sg:phone":"+1   ",
    "sg:postcode":"15642",
    "sg:province":"PA",
    "sg:tags":[
        "house"
    ],
    "wof:name":"A To Z Construction",
    "wof:placetype":"venue"
},
  "geometry": {"coordinates":[-79.771315,40.303488],"type":"Point"}
}