{
  "type": "Feature",
  "properties": {
    "iso:country":"US",
    "sg:address":"6856 Wilson St",
    "sg:city":"West Mifflin",
    "sg:classifiers":[
        {
            "category":"Building & Trades",
            "subcategory":"Plumbing",
            "type":"Services"
        }
    ],
    "sg:phone":"+1 412 466 3171",
    "sg:postcode":"15122",
    "sg:province":"PA",
    "sg:tags":[
        "contractor"
    ],
    "wof:name":"Gregg Plumbing",
    "wof:placetype":"venue"
},
  "geometry": {"coordinates":[-79.909672,40.354448],"type":"Point"}
}