{
  "type": "Feature",
  "properties": {
    "addr:full":"2 Danforth Rd Easton PA 18045",
    "addr:housenumber":"2",
    "addr:postcode":"18045",
    "addr:street":"Danforth Rd",
    "iso:country":"US",
    "sg:address":"2 Danforth Rd",
    "sg:city":"Easton",
    "sg:classifiers":[
        {
            "category":"Manufacturing",
            "subcategory":"Tools & Machinery",
            "type":"Manufacturing & Wholesale Goods"
        }
    ],
    "sg:phone":"+1   ",
    "sg:postcode":"18045",
    "sg:province":"PA",
    "sg:tags":[
        "manufacture",
        "polymer",
        "concentrate",
        "color",
        "plastic"
    ],
    "wof:name":"Fluortek Compounding Inc",
    "wof:placetype":"venue"
},
  "geometry": {"coordinates":[-75.265248,40.732892],"type":"Point"}
}