{
  "type": "Feature",
  "properties": {
    "iso:country":"US",
    "sg:address":"4710 Wingate St",
    "sg:city":"Philadelphia",
    "sg:classifiers":[
        {
            "category":"Manufacturing",
            "subcategory":"Metals",
            "type":"Manufacturing & Wholesale Goods"
        }
    ],
    "sg:phone":"+1 215 332 4043",
    "sg:postcode":"19136",
    "sg:province":"PA",
    "sg:tags":[
        "ornamental",
        "mfg",
        "iron",
        "rails",
        "hand"
    ],
    "sg:website":"www.stur-dee.com",
    "wof:name":"Stur-Dee Ornamental Hand Rails",
    "wof:placetype":"venue"
},
  "geometry": {"coordinates":[-75.015446,40.038945],"type":"Point"}
}