{
  "type": "Feature",
  "properties": {
    "addr:full":"317 W 4th St Oil City PA 16301",
    "addr:housenumber":"317",
    "addr:postcode":"16301",
    "addr:street":"W 4Th St",
    "iso:country":"US",
    "sg:address":"317 W 4th St",
    "sg:city":"Oil City",
    "sg:classifiers":[
        {
            "category":"Personal",
            "subcategory":"Beauty Salon",
            "type":"Services"
        }
    ],
    "sg:phone":"+1 814 676 1901",
    "sg:postcode":"16301",
    "sg:province":"PA",
    "wof:name":"Bonnie Cassatt's A Cut Above",
    "wof:placetype":"venue"
},
  "geometry": {"coordinates":[-79.71641,41.423336],"type":"Point"}
}