{
  "type": "Feature",
  "properties": {
    "iso:country":"US",
    "sg:address":"7847 Cross Creek Cir",
    "sg:city":"Breinigsville",
    "sg:classifiers":[
        {
            "category":"Banks & Credit Unions",
            "subcategory":"Bank",
            "type":"Services"
        }
    ],
    "sg:phone":"+1   ",
    "sg:postcode":"18031",
    "sg:province":"PA",
    "sg:tags":[
        "mortgage"
    ],
    "wof:name":"Superior Home Mortgage",
    "wof:placetype":"venue"
},
  "geometry": {"coordinates":[-75.610021,40.555601],"type":"Point"}
}