{
  "type": "Feature",
  "properties": {
    "iso:country":"US",
    "sg:address":"630 N 5th St",
    "sg:city":"Lebanon",
    "sg:classifiers":[
        {
            "category":"Building & Trades",
            "subcategory":"Construction",
            "type":"Services"
        },
        {
            "category":"Building & Trades",
            "subcategory":"Plumbing",
            "type":"Services"
        }
    ],
    "sg:phone":"+1 717 273 8001",
    "sg:postcode":"17046",
    "sg:province":"PA",
    "sg:tags":[
        "sheet",
        "mfg",
        "work",
        "metal",
        "contractor",
        "metalwork"
    ],
    "wof:name":"Herb Sheet Metal Inc",
    "wof:placetype":"venue"
},
  "geometry": {"coordinates":[-76.41928799999999,40.348787],"type":"Point"}
}