{
  "type": "Feature",
  "properties": {
    "iso:country":"US",
    "sg:address":"209 Unity St",
    "sg:city":"Latrobe",
    "sg:classifiers":[
        {
            "category":"Organizations",
            "subcategory":"Community Association",
            "type":"Services"
        }
    ],
    "sg:phone":"+1   ",
    "sg:postcode":"15650",
    "sg:province":"PA",
    "wof:name":"Slovene National Benefit Soc",
    "wof:placetype":"venue"
},
  "geometry": {"coordinates":[-79.38901799999999,40.312839],"type":"Point"}
}