{
  "type": "Feature",
  "properties": {
    "iso:country":"US",
    "sg:address":"5900 Corporate Dr",
    "sg:city":"Pittsburgh",
    "sg:classifiers":[
        {
            "category":"Health Services",
            "subcategory":"Hospital",
            "type":"Services"
        }
    ],
    "sg:phone":"+1   ",
    "sg:postcode":"15237",
    "sg:province":"PA",
    "sg:tags":[
        "optical",
        "good",
        "general"
    ],
    "wof:name":"Upmc",
    "wof:placetype":"venue"
},
  "geometry": {"coordinates":[-80.02134,40.563413],"type":"Point"}
}