{
  "type": "Feature",
  "properties": {
    "iso:country":"US",
    "sg:address":"6611 Germantown Ave",
    "sg:city":"Philadelphia",
    "sg:classifiers":[
        {
            "category":"Professional",
            "type":"Services"
        }
    ],
    "sg:phone":"+1 215 848 5563",
    "sg:postcode":"19119",
    "sg:province":"PA",
    "wof:name":"Lafiya Family Svc",
    "wof:placetype":"venue"
},
  "geometry": {"coordinates":[-75.183982,40.049417],"type":"Point"}
}