{
  "type": "Feature",
  "properties": {
    "iso:country":"US",
    "sg:address":"126 Grant St",
    "sg:city":"Franklin",
    "sg:classifiers":[
        {
            "category":"Retail",
            "subcategory":"Auto Repair",
            "type":"Services"
        }
    ],
    "sg:phone":"+1 814 432 2304",
    "sg:postcode":"16323",
    "sg:province":"PA",
    "sg:tags":[
        "automobile",
        "inspection"
    ],
    "wof:name":"Phillips Auto Repair",
    "wof:placetype":"venue"
},
  "geometry": {"coordinates":[-79.8334,41.404777],"type":"Point"}
}