{
  "type": "Feature",
  "properties": {
    "iso:country":"US",
    "sg:address":"80 E Lancaster Ave",
    "sg:city":"Devon",
    "sg:classifiers":[
        {
            "category":"Banks & Credit Unions",
            "subcategory":"Bank",
            "type":"Services"
        }
    ],
    "sg:phone":"+1 610 000 1111",
    "sg:postcode":"19333",
    "sg:province":"PA",
    "wof:name":"Bank Of America",
    "wof:placetype":"venue"
},
  "geometry": {"coordinates":[-75.41818600000001,40.04783],"type":"Point"}
}