{
  "type": "Feature",
  "properties": {
    "iso:country":"US",
    "sg:address":"216 Ridge Ave",
    "sg:city":"Punxsutawney",
    "sg:classifiers":[
        {
            "category":"Retail",
            "subcategory":"Car Wash",
            "type":"Services"
        }
    ],
    "sg:phone":"+1   ",
    "sg:postcode":"15767",
    "sg:province":"PA",
    "sg:tags":[
        "carwash"
    ],
    "wof:name":"Elk Run Car Wash",
    "wof:placetype":"venue"
},
  "geometry": {"coordinates":[-78.96254,40.950189],"type":"Point"}
}