{
  "type": "Feature",
  "properties": {
    "iso:country":"US",
    "sg:address":"224 Hahnstown Rd",
    "sg:city":"Ephrata",
    "sg:classifiers":[
        {
            "category":"Freight",
            "type":"Transportation"
        }
    ],
    "sg:phone":"+1   ",
    "sg:postcode":"17522",
    "sg:province":"PA",
    "sg:tags":[
        "operator",
        "trucking"
    ],
    "wof:name":"Ervin S Hoover",
    "wof:placetype":"venue"
},
  "geometry": {"coordinates":[-76.117135,40.174628],"type":"Point"}
}