{
  "type": "Feature",
  "properties": {
    "iso:country":"US",
    "sg:address":"2602 Wilmington Rd",
    "sg:city":"New Castle",
    "sg:classifiers":[
        {
            "category":"Health Services",
            "subcategory":"Doctor",
            "type":"Services"
        },
        {
            "category":"Health Services",
            "subcategory":"Medical Lab",
            "type":"Services"
        }
    ],
    "sg:phone":"+1 724 658 7300",
    "sg:postcode":"16105",
    "sg:province":"PA",
    "sg:tags":[
        "laboratory",
        "surgeon",
        "physician"
    ],
    "sg:website":"www.usoncology.com",
    "wof:name":"Oncology Hematology",
    "wof:placetype":"venue"
},
  "geometry": {"coordinates":[-80.35473399999999,41.031438],"type":"Point"}
}