{
  "type": "Feature",
  "properties": {
    "iso:country":"US",
    "sg:address":"1270 Monticello Ave",
    "sg:city":"Sharpsville",
    "sg:classifiers":[
        {
            "category":"Building & Trades",
            "subcategory":"Construction",
            "type":"Services"
        }
    ],
    "sg:phone":"+1   ",
    "sg:postcode":"16148",
    "sg:province":"PA",
    "sg:tags":[
        "house"
    ],
    "wof:name":"Mudrey Construction",
    "wof:placetype":"venue"
},
  "geometry": {"coordinates":[-80.470445,41.250788],"type":"Point"}
}