{
  "type": "Feature",
  "properties": {
    "iso:country":"US",
    "sg:address":"3650 Chestnut St",
    "sg:city":"Philadelphia",
    "sg:classifiers":[
        {
            "category":"Education",
            "subcategory":"Special Training",
            "type":"Public Place"
        }
    ],
    "sg:phone":"+1 800 288 8221",
    "sg:postcode":"19104",
    "sg:province":"PA",
    "sg:tags":[
        "school",
        "computer",
        "technology"
    ],
    "sg:website":"http://ONLC.com",
    "wof:name":"ONLC Training Centers - University Center",
    "wof:placetype":"venue"
},
  "geometry": {"coordinates":[-75.195458,39.954802],"type":"Point"}
}