{
  "type": "Feature",
  "properties": {
    "iso:country":"US",
    "sg:address":"1000 E Welsh Rd",
    "sg:city":"Ambler",
    "sg:classifiers":[
        {
            "category":"Health Services",
            "subcategory":"Doctor",
            "type":"Services"
        },
        {
            "category":"Health Services",
            "subcategory":"Clinic",
            "type":"Services"
        }
    ],
    "sg:phone":"+1 215 646 0165",
    "sg:postcode":"19002",
    "sg:province":"PA",
    "sg:tags":[
        "physician",
        "surgeon",
        "osteopathic"
    ],
    "wof:name":"Resnick Brian M DO",
    "wof:placetype":"venue"
},
  "geometry": {"coordinates":[-75.195457,40.188202],"type":"Point"}
}