{
  "type": "Feature",
  "properties": {
    "addr:full":"229 Railroad Dr Warminster PA 18974",
    "addr:housenumber":"229",
    "addr:postcode":"18974",
    "addr:street":"Railroad Dr",
    "iso:country":"US",
    "sg:address":"229 Railroad Dr",
    "sg:city":"Warminster",
    "sg:classifiers":[
        {
            "category":"Retail",
            "subcategory":"Auto Repair",
            "type":"Services"
        }
    ],
    "sg:phone":"+1   ",
    "sg:postcode":"18974",
    "sg:province":"PA",
    "sg:tags":[
        "general"
    ],
    "wof:name":"Steel Wings",
    "wof:placetype":"venue"
},
  "geometry": {"coordinates":[-75.061387,40.228094],"type":"Point"}
}