{
  "type": "Feature",
  "properties": {
    "iso:country":"US",
    "sg:address":"33 Conwell Dr",
    "sg:city":"Ambler",
    "sg:classifiers":[
        {
            "category":"Organizations",
            "subcategory":"Religious Organization",
            "type":"Services"
        }
    ],
    "sg:phone":"+1   ",
    "sg:postcode":"19002",
    "sg:province":"PA",
    "sg:tags":[
        "school"
    ],
    "wof:name":"St Alphonsus Catolic Parish",
    "wof:placetype":"venue"
},
  "geometry": {"coordinates":[-75.186818,40.168918],"type":"Point"}
}