{
  "type": "Feature",
  "properties": {
    "iso:country":"US",
    "sg:address":"341 S Graham St",
    "sg:city":"Pittsburgh",
    "sg:classifiers":[
        {
            "category":"Professional",
            "type":"Services"
        }
    ],
    "sg:phone":"+1 412 441 1773",
    "sg:postcode":"15232",
    "sg:province":"PA",
    "sg:tags":[
        "apartment"
    ],
    "wof:name":"Mazzotta Manor",
    "wof:placetype":"venue"
},
  "geometry": {"coordinates":[-79.936514,40.460803],"type":"Point"}
}