{
  "type": "Feature",
  "properties": {
    "addr:full":"1600 3rd Ave Altoona PA 16602",
    "addr:housenumber":"1600",
    "addr:postcode":"16602",
    "addr:street":"3Rd Ave",
    "iso:country":"US",
    "sg:address":"1600 3rd Ave",
    "sg:city":"Altoona",
    "sg:classifiers":[
        {
            "category":"Personal",
            "subcategory":"Beauty Salon",
            "type":"Services"
        }
    ],
    "sg:phone":"+1 814 943 8483",
    "sg:postcode":"16602",
    "sg:province":"PA",
    "wof:name":"Illusions By Tom",
    "wof:placetype":"venue"
},
  "geometry": {"coordinates":[-78.397615,40.506401],"type":"Point"}
}