{
  "type": "Feature",
  "properties": {
    "addr:full":"8 Hattman Dr Coraopolis PA 15108",
    "addr:housenumber":"8",
    "addr:postcode":"15108",
    "addr:street":"Hattman Dr",
    "iso:country":"US",
    "sg:address":"8 Hattman Dr",
    "sg:city":"Coraopolis",
    "sg:classifiers":[
        {
            "category":"Health Services",
            "subcategory":"Nursing And Care Facility",
            "type":"Services"
        }
    ],
    "sg:phone":"+1   ",
    "sg:postcode":"15108",
    "sg:province":"PA",
    "sg:tags":[
        "home",
        "reta",
        "intermediate",
        "mentally",
        "for"
    ],
    "wof:name":"Robinson Developmental Center",
    "wof:placetype":"venue"
},
  "geometry": {"coordinates":[-80.10786,40.478642],"type":"Point"}
}