{
  "type": "Feature",
  "properties": {
    "addr:full":"2501 Bristol Rd Warrington PA 18976",
    "addr:housenumber":"2501",
    "addr:postcode":"18976",
    "addr:street":"Bristol Rd",
    "iso:country":"US",
    "sg:address":"2501 Bristol Rd",
    "sg:city":"Warrington",
    "sg:classifiers":[
        {
            "category":"Building & Trades",
            "subcategory":"Electrical",
            "type":"Services"
        }
    ],
    "sg:phone":"+1 215 918 0277",
    "sg:postcode":"18976",
    "sg:province":"PA",
    "sg:tags":[
        "electrical",
        "contractor"
    ],
    "wof:name":"Meridian Electrical Assoc Inc",
    "wof:placetype":"venue"
},
  "geometry": {"coordinates":[-75.13737999999999,40.253971],"type":"Point"}
}