{
  "type": "Feature",
  "properties": {
    "addr:full":"772 S Broad St Philadelphia PA 19146",
    "addr:housenumber":"772",
    "addr:postcode":"19146",
    "addr:street":"S Broad St",
    "iso:country":"US",
    "sg:address":"772 S Broad St",
    "sg:city":"Philadelphia",
    "sg:classifiers":[
        {
            "category":"Organizations",
            "subcategory":"Religious Organization",
            "type":"Services"
        }
    ],
    "sg:phone":"+1 215 735 3917",
    "sg:postcode":"19146",
    "sg:province":"PA",
    "wof:name":"Cir Msn Church Home & Training School Inc of Penna",
    "wof:placetype":"venue"
},
  "geometry": {"coordinates":[-75.166298,39.941002],"type":"Point"}
}