{
  "type": "Feature",
  "properties": {
    "iso:country":"US",
    "sg:address":"30 Donat Rd",
    "sg:city":"Lenhartsville",
    "sg:classifiers":[
        {
            "category":"Manufacturing",
            "subcategory":"Tools & Machinery",
            "type":"Manufacturing & Wholesale Goods"
        }
    ],
    "sg:phone":"+1   ",
    "sg:postcode":"19530",
    "sg:province":"PA",
    "sg:tags":[
        "industrial",
        "mfg"
    ],
    "wof:name":"Meck Manufacturing",
    "wof:placetype":"venue"
},
  "geometry": {"coordinates":[-75.855625,40.578076],"type":"Point"}
}