{
  "type": "Feature",
  "properties": {
    "iso:country":"US",
    "sg:address":"616 Summerlea St",
    "sg:city":"Pittsburgh",
    "sg:classifiers":[
        {
            "category":"Communications",
            "subcategory":"Film & Video Production",
            "type":"Services"
        }
    ],
    "sg:phone":"+1   ",
    "sg:postcode":"15232",
    "sg:province":"PA",
    "sg:tags":[
        "motion"
    ],
    "wof:name":"Lewis Kensley Productions",
    "wof:placetype":"venue"
},
  "geometry": {"coordinates":[-79.93176099999999,40.455077],"type":"Point"}
}