{
  "type": "Feature",
  "properties": {
    "addr:full":"219 Hunlock Harveyville Rd Hunlock Creek PA 18621",
    "addr:housenumber":"219",
    "addr:postcode":"18621",
    "addr:street":"Hunlock Harveyville Rd",
    "iso:country":"US",
    "sg:address":"219 Hunlock Harveyville Rd",
    "sg:city":"Hunlock Creek",
    "sg:classifiers":[
        {
            "category":"Sports & Exercise",
            "subcategory":"Golf",
            "type":"Entertainment"
        }
    ],
    "sg:phone":"+1   ",
    "sg:postcode":"18621",
    "sg:province":"PA",
    "sg:tags":[
        "course",
        "public"
    ],
    "wof:name":"Morgan Hills Golf Course",
    "wof:placetype":"venue"
},
  "geometry": {"coordinates":[-76.17076,41.229795],"type":"Point"}
}