{
  "type": "Feature",
  "properties": {
    "iso:country":"US",
    "sg:address":"211 Meadow Dr",
    "sg:city":"Trafford",
    "sg:classifiers":[
        {
            "category":"Professional",
            "type":"Services"
        }
    ],
    "sg:phone":"+1 724 327 5631",
    "sg:postcode":"15085",
    "sg:province":"PA",
    "sg:tags":[
        "establishment"
    ],
    "wof:name":"JCB Systems",
    "wof:placetype":"venue"
},
  "geometry": {"coordinates":[-79.709918,40.394678],"type":"Point"}
}