{
  "type": "Feature",
  "properties": {
    "addr:full":"1838 Markley St Norristown PA 19401",
    "addr:housenumber":"1838",
    "addr:postcode":"19401",
    "addr:street":"Markley St",
    "iso:country":"US",
    "sg:address":"1838 Markley St",
    "sg:city":"Norristown",
    "sg:classifiers":[
        {
            "category":"Utilities",
            "subcategory":"Cable",
            "type":"Services"
        },
        {
            "category":"Building & Trades",
            "subcategory":"Construction",
            "type":"Services"
        }
    ],
    "sg:phone":"+1 610 272 2606",
    "sg:postcode":"19401",
    "sg:province":"PA",
    "sg:tags":[
        "television",
        "telephone",
        "contractor"
    ],
    "wof:name":"In Atlantic Telecommunications",
    "wof:placetype":"venue"
},
  "geometry": {"coordinates":[-75.33287300000001,40.133801],"type":"Point"}
}