{
  "type": "Feature",
  "properties": {
    "iso:country":"US",
    "sg:address":"2140 Woodland Rd",
    "sg:city":"Baden",
    "sg:classifiers":[
        {
            "category":"Health Services",
            "subcategory":"Health Practitioner",
            "type":"Services"
        }
    ],
    "sg:phone":"+1 724 625 6255",
    "sg:postcode":"15005",
    "sg:province":"PA",
    "sg:tags":[
        "psychologist"
    ],
    "wof:name":"DVD Empire",
    "wof:placetype":"venue"
},
  "geometry": {"coordinates":[-80.21204299999999,40.617373],"type":"Point"}
}