{
  "type": "Feature",
  "properties": {
    "iso:country":"US",
    "sg:address":"6920 Swagger Rd",
    "sg:city":"Point Pleasant",
    "sg:classifiers":[
        {
            "category":"Wholesale",
            "subcategory":"Home Furnishings",
            "type":"Manufacturing & Wholesale Goods"
        }
    ],
    "sg:phone":"+1 215 297 9363",
    "sg:postcode":"18938",
    "sg:province":"PA",
    "sg:tags":[
        "tile"
    ],
    "wof:name":"Vitrium Corp",
    "wof:placetype":"venue"
},
  "geometry": {"coordinates":[-75.07068200000001,40.420141],"type":"Point"}
}