{
  "type": "Feature",
  "properties": {
    "addr:full":"7 S 3rd St Harrisburg PA 17101",
    "addr:housenumber":"7",
    "addr:postcode":"17101",
    "addr:street":"S 3Rd St",
    "iso:country":"US",
    "sg:address":"7 S 3rd St",
    "sg:city":"Harrisburg",
    "sg:classifiers":[
        {
            "category":"Home & Garden",
            "subcategory":"Building Materials",
            "type":"Retail Goods"
        }
    ],
    "sg:phone":"+1 717 645 0482",
    "sg:postcode":"17101",
    "sg:province":"PA",
    "sg:tags":[
        "glass",
        "window",
        "plate"
    ],
    "wof:name":"Englebright's Glass",
    "wof:placetype":"venue"
},
  "geometry": {"coordinates":[-76.88018,40.260648],"type":"Point"}
}