{
  "type": "Feature",
  "properties": {
    "iso:country":"US",
    "sg:address":"2552 Jefferson St",
    "sg:city":"Harrisburg",
    "sg:classifiers":[
        {
            "category":"Organizations",
            "subcategory":"Labor Organization",
            "type":"Services"
        }
    ],
    "sg:phone":"+1 717 233 8766",
    "sg:postcode":"17110",
    "sg:province":"PA",
    "sg:tags":[
        "union",
        "teamster"
    ],
    "wof:name":"Teamsters Chauffeurs & Helpers",
    "wof:placetype":"venue"
},
  "geometry": {"coordinates":[-76.892658,40.288715],"type":"Point"}
}