{
  "type": "Feature",
  "properties": {
    "iso:country":"US",
    "sg:address":"1942 State Rte 313",
    "sg:city":"Perkasie",
    "sg:classifiers":[
        {
            "category":"Utilities",
            "subcategory":"Telephone",
            "type":"Services"
        }
    ],
    "sg:phone":"+1   ",
    "sg:postcode":"18944",
    "sg:province":"PA",
    "sg:tags":[
        "communications"
    ],
    "wof:name":"Oldmachinery Com",
    "wof:placetype":"venue"
},
  "geometry": {"coordinates":[-75.275942,40.42004],"type":"Point"}
}