{
  "type": "Feature",
  "properties": {
    "iso:country":"US",
    "sg:address":"2004 Sproul Rd",
    "sg:city":"Broomall",
    "sg:classifiers":[
        {
            "category":"Health Services",
            "subcategory":"Health Practitioner",
            "type":"Services"
        }
    ],
    "sg:phone":"+1   ",
    "sg:postcode":"19008",
    "sg:province":"PA",
    "wof:name":"Total Rehab",
    "wof:placetype":"venue"
},
  "geometry": {"coordinates":[-75.35853299999999,39.965095],"type":"Point"}
}