{
  "type": "Feature",
  "properties": {
    "addr:full":"141 Adams Xing Rd Strongstown PA 15957",
    "addr:housenumber":"141",
    "addr:postcode":"15957",
    "addr:street":"Adams Xing Rd",
    "iso:country":"US",
    "sg:address":"141 Adams Xing Rd",
    "sg:city":"Strongstown",
    "sg:classifiers":[
        {
            "category":"Retail",
            "subcategory":"Auto Repair",
            "type":"Services"
        }
    ],
    "sg:phone":"+1 814 749 9760",
    "sg:postcode":"15957",
    "sg:province":"PA",
    "sg:tags":[
        "body",
        "automobile",
        "painting"
    ],
    "wof:name":"CAM Auto",
    "wof:placetype":"venue"
},
  "geometry": {"coordinates":[-78.87983699999999,40.543665],"type":"Point"}
}