{
  "type": "Feature",
  "properties": {
    "iso:country":"US",
    "sg:address":"10 W Dutton Mill Rd ",
    "sg:city":"Aston",
    "sg:classifiers":[
        {
            "category":"Restaurant",
            "type":"Food & Drink"
        }
    ],
    "sg:menulink":"http://www.allmenus.com/pa/aston/289174-coccos-pizza/menu/",
    "sg:phone":"+1 610 494 4797",
    "sg:postcode":"19014",
    "sg:province":"PA",
    "sg:tags":[
        "american",
        "pizza"
    ],
    "wof:name":"Cocco's Pizza",
    "wof:placetype":"venue"
},
  "geometry": {"coordinates":[-75.41687,39.863896],"type":"Point"}
}