{
  "type": "Feature",
  "properties": {
    "iso:country":"US",
    "sg:address":"419 Suedberg Rd",
    "sg:city":"Pine Grove",
    "sg:classifiers":[
        {
            "category":"Travel",
            "subcategory":"Hotels & Motels",
            "type":"Entertainment"
        }
    ],
    "sg:phone":"+1 570 345 4099",
    "sg:postcode":"17963",
    "sg:province":"PA",
    "wof:name":"Econo Lodge",
    "wof:placetype":"venue"
},
  "geometry": {"coordinates":[-76.426041,40.534921],"type":"Point"}
}