{
  "type": "Feature",
  "properties": {
    "addr:full":"820 Rte 18 Monaca PA 15061",
    "addr:housenumber":"820",
    "addr:postcode":"15061",
    "addr:street":"Rte 18",
    "iso:country":"US",
    "sg:address":"820 Rte 18",
    "sg:city":"Monaca",
    "sg:classifiers":[
        {
            "category":"Restaurant",
            "type":"Food & Drink"
        }
    ],
    "sg:phone":"+1 724 728 8471",
    "sg:postcode":"15061",
    "sg:province":"PA",
    "sg:website":"www.arbys.com",
    "wof:name":"Arby's",
    "wof:placetype":"venue"
},
  "geometry": {"coordinates":[-80.32856,40.668666],"type":"Point"}
}