{
  "type": "Feature",
  "properties": {
    "iso:country":"US",
    "sg:address":"290 Pittsburgh Cir",
    "sg:city":"Ellwood City",
    "sg:classifiers":[
        {
            "category":"Building & Trades",
            "subcategory":"Plumbing",
            "type":"Services"
        }
    ],
    "sg:phone":"+1 724 758 7528",
    "sg:postcode":"16117",
    "sg:province":"PA",
    "sg:tags":[
        "heating",
        "contractor"
    ],
    "wof:name":"Sitler & Lemmon Heating & Clng",
    "wof:placetype":"venue"
},
  "geometry": {"coordinates":[-80.28442099999999,40.863708],"type":"Point"}
}