{
  "type": "Feature",
  "properties": {
    "iso:country":"US",
    "sg:address":"216 Market St",
    "sg:city":"Lewisburg",
    "sg:classifiers":[
        {
            "category":"Professional",
            "subcategory":"Advertising",
            "type":"Services"
        }
    ],
    "sg:phone":"+1 570 523 8772",
    "sg:postcode":"17837",
    "sg:province":"PA",
    "sg:website":"www.targetselect.com",
    "wof:name":"Target Select Cable",
    "wof:placetype":"venue"
},
  "geometry": {"coordinates":[-76.88384600000001,40.965006],"type":"Point"}
}