{
  "type": "Feature",
  "properties": {
    "iso:country":"US",
    "sg:address":"10339 Perry Hwy",
    "sg:city":"Wexford",
    "sg:classifiers":[
        {
            "category":"Restaurant",
            "type":"Food & Drink"
        }
    ],
    "sg:phone":"+1 724 935 3663",
    "sg:postcode":"15090",
    "sg:province":"PA",
    "sg:tags":[
        "delicatessen",
        "eating"
    ],
    "wof:name":"Reb's Place",
    "wof:placetype":"venue"
},
  "geometry": {"coordinates":[-80.053371,40.610003],"type":"Point"}
}