{
  "type": "Feature",
  "properties": {
    "addr:full":"220 Henry Ave Boyertown PA 19512",
    "addr:housenumber":"220",
    "addr:postcode":"19512",
    "addr:street":"Henry Ave",
    "iso:country":"US",
    "sg:address":"220 Henry Ave",
    "sg:city":"Boyertown",
    "sg:classifiers":[
        {
            "category":"Building & Trades",
            "subcategory":"Landscaping Services",
            "type":"Services"
        }
    ],
    "sg:phone":"+1   ",
    "sg:postcode":"19512",
    "sg:province":"PA",
    "sg:tags":[
        "landscape",
        "contractor"
    ],
    "wof:name":"Touch of Green Landscaping",
    "wof:placetype":"venue"
},
  "geometry": {"coordinates":[-75.63552300000001,40.346507],"type":"Point"}
}