{
  "type": "Feature",
  "properties": {
    "iso:country":"US",
    "sg:address":"204 E Harford St",
    "sg:city":"Milford",
    "sg:classifiers":[
        {
            "category":"Communications",
            "subcategory":"Television Station",
            "type":"Services"
        }
    ],
    "sg:phone":"+1   ",
    "sg:postcode":"18337",
    "sg:province":"PA",
    "wof:name":"T V 13",
    "wof:placetype":"venue"
},
  "geometry": {"coordinates":[-74.801221,41.320564],"type":"Point"}
}