{
  "type": "Feature",
  "properties": {
    "iso:country":"US",
    "sg:address":"439 Millville Rd",
    "sg:city":"Bloomsburg",
    "sg:classifiers":[
        {
            "category":"Manufacturing",
            "subcategory":"Furniture",
            "type":"Manufacturing & Wholesale Goods"
        }
    ],
    "sg:phone":"+1 570 784 0874",
    "sg:postcode":"17815",
    "sg:province":"PA",
    "sg:tags":[
        "equipment",
        "supply"
    ],
    "wof:name":"Custom Fab Co",
    "wof:placetype":"venue"
},
  "geometry": {"coordinates":[-76.46623700000001,41.012081],"type":"Point"}
}