{
  "type": "Feature",
  "properties": {
    "iso:country":"US",
    "sg:address":"12 King Rd",
    "sg:city":"Honey Brook",
    "sg:classifiers":[
        {
            "category":"Local Transit",
            "type":"Transportation"
        }
    ],
    "sg:phone":"+1 610 273 2539",
    "sg:postcode":"19344",
    "sg:province":"PA",
    "sg:tags":[
        "ambulance"
    ],
    "wof:name":"Honey Brook Ambulance Assn",
    "wof:placetype":"venue"
},
  "geometry": {"coordinates":[-75.918072,40.062897],"type":"Point"}
}