{
  "type": "Feature",
  "properties": {
    "iso:country":"US",
    "sg:address":"1737 Green St",
    "sg:city":"Allentown",
    "sg:classifiers":[
        {
            "category":"Building & Trades",
            "subcategory":"Construction",
            "type":"Services"
        }
    ],
    "sg:phone":"+1   ",
    "sg:postcode":"18104",
    "sg:province":"PA",
    "sg:tags":[
        "roofing",
        "sheet",
        "metal",
        "contractor"
    ],
    "wof:name":"M & O Roofing & Sheet Metal",
    "wof:placetype":"venue"
},
  "geometry": {"coordinates":[-75.498402,40.606763],"type":"Point"}
}