{
  "type": "Feature",
  "properties": {
    "iso:country":"US",
    "sg:address":"62 E Church St",
    "sg:city":"Lock Haven",
    "sg:classifiers":[
        {
            "category":"Health Services",
            "subcategory":"Chiropractor",
            "type":"Services"
        }
    ],
    "sg:phone":"+1 570 748 9486",
    "sg:postcode":"17745",
    "sg:province":"PA",
    "wof:name":"Rodney G Shaffer DC",
    "wof:placetype":"venue"
},
  "geometry": {"coordinates":[-77.446493,41.136037],"type":"Point"}
}