{
  "type": "Feature",
  "properties": {
    "addr:full":"1 Sunnybrook Rd Pottstown PA 19464",
    "addr:housenumber":"1",
    "addr:postcode":"19464",
    "addr:street":"Sunnybrook Rd",
    "iso:country":"US",
    "sg:address":"1 Sunnybrook Rd",
    "sg:city":"Pottstown",
    "sg:classifiers":[
        {
            "category":"Shopping",
            "subcategory":"Gifts & Souvenirs",
            "type":"Retail Goods"
        }
    ],
    "sg:phone":"+1 610 970 0307",
    "sg:postcode":"19464",
    "sg:province":"PA",
    "wof:name":"Expressions Inc",
    "wof:placetype":"venue"
},
  "geometry": {"coordinates":[-75.60936599999999,40.243811],"type":"Point"}
}