{
  "type": "Feature",
  "properties": {
    "iso:country":"US",
    "sg:address":"255 N Blettner Ave",
    "sg:city":"Hanover",
    "sg:classifiers":[
        {
            "category":"Manufacturing",
            "subcategory":"Tools & Machinery",
            "type":"Manufacturing & Wholesale Goods"
        }
    ],
    "sg:phone":"+1 717 632 1291",
    "sg:postcode":"17331",
    "sg:province":"PA",
    "sg:tags":[
        "control",
        "mfg",
        "aqua",
        "kit"
    ],
    "wof:name":"Aqua Phoenix Scientific",
    "wof:placetype":"venue"
},
  "geometry": {"coordinates":[-77.00229299999999,39.795013],"type":"Point"}
}