{
  "type": "Feature",
  "properties": {
    "iso:country":"US",
    "sg:address":"411 Vine St",
    "sg:city":"Philadelphia",
    "sg:classifiers":[
        {
            "category":"Wholesale",
            "subcategory":"Apparel",
            "type":"Manufacturing & Wholesale Goods"
        },
        {
            "category":"Shopping",
            "subcategory":"Shoes",
            "type":"Retail Goods"
        }
    ],
    "sg:phone":"+1 215 922 1935",
    "sg:postcode":"19106",
    "sg:province":"PA",
    "sg:tags":[
        "shoes-wholesale",
        "store",
        "manufacturer"
    ],
    "sg:website":"http://www.cbshoes.com",
    "wof:name":"Shoes On The Web",
    "wof:placetype":"venue"
},
  "geometry": {"coordinates":[-75.146477,39.956095],"type":"Point"}
}