{
  "type": "Feature",
  "properties": {
    "iso:country":"US",
    "sg:address":"3276 Bethel Wilmington Rd",
    "sg:city":"New Wilmington",
    "sg:classifiers":[
        {
            "category":"Farming",
            "subcategory":"Dairy Farm",
            "type":"Manufacturing & Wholesale Goods"
        }
    ],
    "sg:phone":"+1   ",
    "sg:postcode":"16142",
    "sg:province":"PA",
    "wof:name":"David Minner Barn",
    "wof:placetype":"venue"
},
  "geometry": {"coordinates":[-80.393973,41.18017],"type":"Point"}
}