{
  "type": "Feature",
  "properties": {
    "iso:country":"US",
    "sg:address":"7615 National Pike",
    "sg:city":"Uniontown",
    "sg:classifiers":[
        {
            "category":"Retail",
            "subcategory":"Repair Shop",
            "type":"Services"
        }
    ],
    "sg:phone":"+1 724 437 8771",
    "sg:postcode":"15401",
    "sg:province":"PA",
    "sg:tags":[
        "lock",
        "locksmith"
    ],
    "wof:name":"Ed & Mark's Locksmith",
    "wof:placetype":"venue"
},
  "geometry": {"coordinates":[-79.781329,39.936694],"type":"Point"}
}