{
  "type": "Feature",
  "properties": {
    "iso:country":"US",
    "sg:address":"2100 Whitney Rd",
    "sg:city":"Williamsport",
    "sg:classifiers":[
        {
            "category":"Freight",
            "type":"Transportation"
        }
    ],
    "sg:phone":"+1   ",
    "sg:postcode":"17701",
    "sg:province":"PA",
    "sg:tags":[
        "local",
        "storage",
        "truck"
    ],
    "wof:name":"Roans Mayflower",
    "wof:placetype":"venue"
},
  "geometry": {"coordinates":[-77.046201,41.228539],"type":"Point"}
}