{
  "type": "Feature",
  "properties": {
    "addr:full":"216 Dickson St Duryea PA 18642",
    "addr:housenumber":"216",
    "addr:postcode":"18642",
    "addr:street":"Dickson St",
    "iso:country":"US",
    "sg:address":"216 Dickson St",
    "sg:city":"Duryea",
    "sg:classifiers":[
        {
            "category":"Manufacturing",
            "subcategory":"Printing",
            "type":"Manufacturing & Wholesale Goods"
        }
    ],
    "sg:phone":"+1 570 457 1770",
    "sg:postcode":"18642",
    "sg:province":"PA",
    "sg:tags":[
        "printer"
    ],
    "wof:name":"X-Press Printing Co",
    "wof:placetype":"venue"
},
  "geometry": {"coordinates":[-75.76216100000001,41.352019],"type":"Point"}
}