{
  "type": "Feature",
  "properties": {
    "iso:country":"US",
    "sg:address":"206 September Way",
    "sg:city":"York",
    "sg:classifiers":[
        {
            "category":"Wholesale",
            "subcategory":"Drugs",
            "type":"Manufacturing & Wholesale Goods"
        }
    ],
    "sg:phone":"+1   ",
    "sg:postcode":"17403",
    "sg:province":"PA",
    "wof:name":"Giant Pharmacy",
    "wof:placetype":"venue"
},
  "geometry": {"coordinates":[-76.692072,39.931928],"type":"Point"}
}