{
  "type": "Feature",
  "properties": {
    "iso:country":"US",
    "sg:address":"2867 Holme Ave",
    "sg:city":"Philadelphia",
    "sg:classifiers":[
        {
            "category":"Retail",
            "subcategory":"Laundry & Dry Cleaning",
            "type":"Services"
        }
    ],
    "sg:phone":"+1   ",
    "sg:postcode":"19152",
    "sg:province":"PA",
    "sg:tags":[
        "drycleaning",
        "plant"
    ],
    "wof:name":"Madison Avenue Ltd",
    "wof:placetype":"venue"
},
  "geometry": {"coordinates":[-75.033706,40.05719],"type":"Point"}
}