{
  "type": "Feature",
  "properties": {
    "iso:country":"US",
    "sg:address":"261 Old York Rd Ste 304",
    "sg:city":"Jenkintown",
    "sg:classifiers":[
        {
            "category":"Personal",
            "subcategory":"Beauty Salon",
            "type":"Services"
        }
    ],
    "sg:phone":"+1 215 887 9840",
    "sg:postcode":"19046",
    "sg:province":"PA",
    "wof:name":"Serenity Aesthetic Centre",
    "wof:placetype":"venue"
},
  "geometry": {"coordinates":[-75.126572,40.09],"type":"Point"}
}