{
  "type": "Feature",
  "properties": {
    "addr:full":"219 E Main St Ste 115 Mechanicsburg PA 17055",
    "addr:housenumber":"219",
    "addr:postcode":"17055",
    "addr:street":"E Main St Ste 115",
    "iso:country":"US",
    "sg:address":"219 E Main St Ste 115",
    "sg:city":"Mechanicsburg",
    "sg:classifiers":[
        {
            "category":"Health Services",
            "subcategory":"Dentist",
            "type":"Services"
        }
    ],
    "sg:phone":"+1 717 591 7050",
    "sg:postcode":"17055",
    "sg:province":"PA",
    "sg:website":"www.drshowley.com",
    "wof:name":"Showley Jack Ellis DDS",
    "wof:placetype":"venue"
},
  "geometry": {"coordinates":[-77.00371199999999,40.214675],"type":"Point"}
}