{
  "type": "Feature",
  "properties": {
    "addr:full":"311 Pearl St Brownsville PA 15417",
    "addr:housenumber":"311",
    "addr:postcode":"15417",
    "addr:street":"Pearl St",
    "iso:country":"US",
    "sg:address":"311 Pearl St",
    "sg:city":"Brownsville",
    "sg:classifiers":[
        {
            "category":"Real Estate",
            "subcategory":"Real Estate Operator",
            "type":"Services"
        }
    ],
    "sg:phone":"+1 724 785 6315",
    "sg:postcode":"15417",
    "sg:province":"PA",
    "sg:tags":[
        "building",
        "nonresidential"
    ],
    "wof:name":"C & J Quality Properties",
    "wof:placetype":"venue"
},
  "geometry": {"coordinates":[-79.890719,40.017989],"type":"Point"}
}