{
  "type": "Feature",
  "properties": {
    "iso:country":"US",
    "sg:address":"3272 Fulling Mill Rd",
    "sg:city":"Middletown",
    "sg:classifiers":[
        {
            "category":"Shopping",
            "subcategory":"Pets & Pet Supplies",
            "type":"Retail Goods"
        },
        {
            "category":"Retail",
            "subcategory":"Animal Services",
            "type":"Services"
        }
    ],
    "sg:phone":"+1 717 939 3759",
    "sg:postcode":"17057",
    "sg:province":"PA",
    "sg:tags":[
        "grooming",
        "dog",
        "cat"
    ],
    "wof:name":"Dunn's Dog Grooming",
    "wof:placetype":"venue"
},
  "geometry": {"coordinates":[-76.794792,40.2253],"type":"Point"}
}