{
  "type": "Feature",
  "properties": {
    "iso:country":"US",
    "sg:address":"4331 Fairview Rd",
    "sg:city":"Columbia",
    "sg:classifiers":[
        {
            "category":"Retail",
            "subcategory":"Auto Repair",
            "type":"Services"
        }
    ],
    "sg:phone":"+1 717 684 4554",
    "sg:postcode":"17512",
    "sg:province":"PA",
    "sg:tags":[
        "wrecker"
    ],
    "wof:name":"Randelle Inc",
    "wof:placetype":"venue"
},
  "geometry": {"coordinates":[-76.4764,40.056567],"type":"Point"}
}