{
  "type": "Feature",
  "properties": {
    "iso:country":"US",
    "sg:address":"622 Farmersville Rd",
    "sg:city":"New Holland",
    "sg:classifiers":[
        {
            "category":"Home & Garden",
            "subcategory":"Building Materials",
            "type":"Retail Goods"
        },
        {
            "category":"Manufacturing",
            "subcategory":"Lumber",
            "type":"Manufacturing & Wholesale Goods"
        }
    ],
    "sg:phone":"+1 717 354 4911",
    "sg:postcode":"17557",
    "sg:province":"PA",
    "sg:tags":[
        "hardwood",
        "mills",
        "dimension",
        "flooring"
    ],
    "wof:name":"Walter & Jackson Inc",
    "wof:placetype":"venue"
},
  "geometry": {"coordinates":[-76.122803,40.145922],"type":"Point"}
}