{
  "type": "Feature",
  "properties": {
    "addr:full":"6616 Rising Sun Ave Philadelphia PA 19111",
    "addr:housenumber":"6616",
    "addr:postcode":"19111",
    "addr:street":"Rising Sun Ave",
    "iso:country":"US",
    "sg:address":"6616 Rising Sun Ave",
    "sg:city":"Philadelphia",
    "sg:classifiers":[
        {
            "category":"Shopping",
            "subcategory":"Used Merchandise",
            "type":"Retail Goods"
        }
    ],
    "sg:phone":"+1 215 742 4869",
    "sg:postcode":"19111",
    "sg:province":"PA",
    "sg:tags":[
        "shop",
        "consignment"
    ],
    "wof:name":"Rising Sun Consignment",
    "wof:placetype":"venue"
},
  "geometry": {"coordinates":[-75.09295,40.052312],"type":"Point"}
}