{
  "type": "Feature",
  "properties": {
    "iso:country":"US",
    "sg:address":"89 B St",
    "sg:city":"Carlisle",
    "sg:classifiers":[
        {
            "category":"Shopping",
            "subcategory":"Gifts & Souvenirs",
            "type":"Retail Goods"
        }
    ],
    "sg:phone":"+1   ",
    "sg:postcode":"17013",
    "sg:province":"PA",
    "wof:name":"Innovative Gifts",
    "wof:placetype":"venue"
},
  "geometry": {"coordinates":[-77.18983900000001,40.209228],"type":"Point"}
}