{
  "type": "Feature",
  "properties": {
    "iso:country":"US",
    "sg:address":"1067 Churchville Rd",
    "sg:city":"Southampton",
    "sg:classifiers":[
        {
            "category":"Manufacturing",
            "subcategory":"Tools & Machinery",
            "type":"Manufacturing & Wholesale Goods"
        }
    ],
    "sg:phone":"+1   ",
    "sg:postcode":"18966",
    "sg:province":"PA",
    "sg:tags":[
        "machine",
        "cleaning",
        "mfg"
    ],
    "wof:name":"R & R Briggs Inc",
    "wof:placetype":"venue"
},
  "geometry": {"coordinates":[-75.03313900000001,40.174996],"type":"Point"}
}