{
  "type": "Feature",
  "properties": {
    "iso:country":"US",
    "sg:address":"924 Buttonwood St",
    "sg:city":"Reading",
    "sg:classifiers":[
        {
            "category":"Organizations",
            "subcategory":"Professional Association",
            "type":"Services"
        }
    ],
    "sg:phone":"+1 610 373 7440",
    "sg:postcode":"19604",
    "sg:province":"PA",
    "sg:tags":[
        "business"
    ],
    "wof:name":"North Eastern Democratic Assn",
    "wof:placetype":"venue"
},
  "geometry": {"coordinates":[-75.917995,40.341312],"type":"Point"}
}