{
  "type": "Feature",
  "properties": {
    "addr:full":"385 Whitehall Rd Reinholds PA 17569",
    "addr:housenumber":"385",
    "addr:postcode":"17569",
    "addr:street":"Whitehall Rd",
    "iso:country":"US",
    "sg:address":"385 Whitehall Rd",
    "sg:city":"Reinholds",
    "sg:classifiers":[
        {
            "category":"Personal",
            "subcategory":"Beauty Salon",
            "type":"Services"
        }
    ],
    "sg:phone":"+1   ",
    "sg:postcode":"17569",
    "sg:province":"PA",
    "sg:tags":[
        "shop"
    ],
    "wof:name":"Curl Up & Dye Hair Salon",
    "wof:placetype":"venue"
},
  "geometry": {"coordinates":[-76.133961,40.286542],"type":"Point"}
}