{
  "type": "Feature",
  "properties": {
    "addr:full":"2515 E Thompson St Philadelphia PA 19125",
    "addr:housenumber":"2515",
    "addr:postcode":"19125",
    "addr:street":"E Thompson St",
    "iso:country":"US",
    "sg:address":"2515 E Thompson St",
    "sg:city":"Philadelphia",
    "sg:classifiers":[
        {
            "category":"Retail",
            "subcategory":"Auto Repair",
            "type":"Services"
        }
    ],
    "sg:phone":"+1 215 426 4031",
    "sg:postcode":"19125",
    "sg:province":"PA",
    "wof:name":"Deater Service",
    "wof:placetype":"venue"
},
  "geometry": {"coordinates":[-75.118797,39.976601],"type":"Point"}
}