{
  "type": "Feature",
  "properties": {
    "iso:country":"US",
    "sg:address":"150 Ridge Pike",
    "sg:city":"Lafayette Hill",
    "sg:classifiers":[
        {
            "category":"Real Estate",
            "subcategory":"Real Estate Operator",
            "type":"Services"
        }
    ],
    "sg:phone":"+1 610 828 8700",
    "sg:postcode":"19444",
    "sg:province":"PA",
    "sg:tags":[
        "building",
        "apartment"
    ],
    "wof:name":"Green Valley Manor Apts",
    "wof:placetype":"venue"
},
  "geometry": {"coordinates":[-75.278773,40.092548],"type":"Point"}
}