{
  "type": "Feature",
  "properties": {
    "addr:full":"46 Chambersburg St Gettysburg PA 17325",
    "addr:housenumber":"46",
    "addr:postcode":"17325",
    "addr:street":"Chambersburg St",
    "iso:country":"US",
    "sg:address":"46 Chambersburg St",
    "sg:city":"Gettysburg",
    "sg:classifiers":[
        {
            "category":"Shopping",
            "subcategory":"Clothing, Apparel, & Fashions",
            "type":"Retail Goods"
        }
    ],
    "sg:phone":"+1   ",
    "sg:postcode":"17325",
    "sg:province":"PA",
    "wof:name":"Spin Wheel Fashions & Suv",
    "wof:placetype":"venue"
},
  "geometry": {"coordinates":[-77.232591,39.830846],"type":"Point"}
}