{
  "type": "Feature",
  "properties": {
    "addr:full":"11650 Roosevelt Blvd Philadelphia PA 19116",
    "addr:housenumber":"11650",
    "addr:postcode":"19116",
    "addr:street":"Roosevelt Blvd",
    "iso:country":"US",
    "sg:address":"11650 Roosevelt Blvd",
    "sg:city":"Philadelphia",
    "sg:classifiers":[
        {
            "category":"Restaurant",
            "type":"Food & Drink"
        }
    ],
    "sg:phone":"+1 215 677 4135",
    "sg:postcode":"19116",
    "sg:province":"PA",
    "wof:name":"Mesmus 1 LLC",
    "wof:placetype":"venue"
},
  "geometry": {"coordinates":[-75.00300799999999,40.104118],"type":"Point"}
}