{
  "type": "Feature",
  "properties": {
    "iso:country":"US",
    "sg:address":"328 Pheasant Run Dr",
    "sg:city":"Doylestown",
    "sg:classifiers":[
        {
            "category":"Building & Trades",
            "subcategory":"Construction",
            "type":"Services"
        }
    ],
    "sg:phone":"+1   ",
    "sg:postcode":"18901",
    "sg:province":"PA",
    "sg:tags":[
        "hanging",
        "contractor"
    ],
    "wof:name":"Haagen Painting",
    "wof:placetype":"venue"
},
  "geometry": {"coordinates":[-75.194615,40.299226],"type":"Point"}
}