{
  "type": "Feature",
  "properties": {
    "addr:full":"4950 Parkside Ave Ste 503 Philadelphia PA 19131",
    "addr:housenumber":"4950",
    "addr:postcode":"19131",
    "addr:street":"Parkside Ave Ste 503",
    "iso:country":"US",
    "sg:address":"4950 Parkside Ave Ste 503",
    "sg:city":"Philadelphia",
    "sg:classifiers":[
        {
            "category":"Real Estate",
            "subcategory":"Real Estate Services",
            "type":"Services"
        }
    ],
    "sg:phone":"+1 215 921 8107",
    "sg:postcode":"19131",
    "sg:province":"PA",
    "sg:website":"www.mosaicdp.com",
    "wof:name":"Mosaic Development Partners",
    "wof:placetype":"venue"
},
  "geometry": {"coordinates":[-75.21878100000001,39.979738],"type":"Point"}
}