{
  "type": "Feature",
  "properties": {
    "addr:full":"304 Evans Dr Ellwood City PA 16117",
    "addr:housenumber":"304",
    "addr:postcode":"16117",
    "addr:street":"Evans Dr",
    "iso:country":"US",
    "sg:address":"304 Evans Dr",
    "sg:city":"Ellwood City",
    "sg:classifiers":[
        {
            "category":"Health Services",
            "subcategory":"Doctor",
            "type":"Services"
        }
    ],
    "sg:phone":"+1 724 752 5274",
    "sg:postcode":"16117",
    "sg:province":"PA",
    "sg:tags":[
        "physician",
        "surgeon"
    ],
    "wof:name":"KASI & KASI",
    "wof:placetype":"venue"
},
  "geometry": {"coordinates":[-80.27641800000001,40.868273],"type":"Point"}
}