{
  "type": "Feature",
  "properties": {
    "iso:country":"US",
    "sg:address":"16487 Lincoln Hwy",
    "sg:city":"Breezewood",
    "sg:classifiers":[
        {
            "category":"Recreation",
            "subcategory":"Boat Charter",
            "type":"Entertainment"
        },
        {
            "category":"Shopping",
            "subcategory":"Bicycles & Sporting Goods",
            "type":"Retail Goods"
        },
        {
            "category":"Parking",
            "subcategory":"Bicycle",
            "type":"Transportation"
        }
    ],
    "sg:phone":"+1 814 735 2453",
    "sg:postcode":"15533",
    "sg:province":"PA",
    "sg:tags":[
        "shop",
        "canoe",
        "system",
        "kayak",
        "security",
        "rack"
    ],
    "sg:website":"http://www.fatjimmys.com",
    "wof:name":"Fat Jimmy's Outfitters",
    "wof:placetype":"venue"
},
  "geometry": {"coordinates":[-78.239845,39.99942],"type":"Point"}
}