{
  "type": "Feature",
  "properties": {
    "iso:country":"US",
    "sg:address":"239 Madison Ave",
    "sg:city":"Warminster",
    "sg:classifiers":[
        {
            "category":"Manufacturing",
            "subcategory":"Printing",
            "type":"Manufacturing & Wholesale Goods"
        }
    ],
    "sg:phone":"+1   ",
    "sg:postcode":"18974",
    "sg:province":"PA",
    "sg:tags":[
        "commercial"
    ],
    "wof:name":"High Fidelity Productions Inc",
    "wof:placetype":"venue"
},
  "geometry": {"coordinates":[-75.095713,40.193603],"type":"Point"}
}