{
  "type": "Feature",
  "properties": {
    "iso:country":"US",
    "sg:address":"59 Plank Ave",
    "sg:city":"Paoli",
    "sg:classifiers":[
        {
            "category":"Professional",
            "subcategory":"Management & Consulting",
            "type":"Services"
        },
        {
            "category":"Professional",
            "subcategory":"Lawyer & Legal Services",
            "type":"Services"
        },
        {
            "category":"Banks & Credit Unions",
            "subcategory":"Financial Services",
            "type":"Services"
        }
    ],
    "sg:phone":"+1 610 251 0360",
    "sg:postcode":"19301",
    "sg:province":"PA",
    "sg:tags":[
        "attorney",
        "estate",
        "consultant",
        "wills",
        "financing",
        "planning",
        "trust"
    ],
    "sg:website":"http://www.pmc-corp.com",
    "wof:name":"Pension Management Co (Inc)",
    "wof:placetype":"venue"
},
  "geometry": {"coordinates":[-75.49155399999999,40.042323],"type":"Point"}
}