{
  "type": "Feature",
  "properties": {
    "iso:country":"US",
    "sg:address":"1134 Manheim Pike",
    "sg:city":"Lancaster",
    "sg:classifiers":[
        {
            "category":"Manufacturing",
            "subcategory":"Tools & Machinery",
            "type":"Manufacturing & Wholesale Goods"
        }
    ],
    "sg:phone":"+1 717 393 4841",
    "sg:postcode":"17601",
    "sg:province":"PA",
    "sg:tags":[
        "treating",
        "metal"
    ],
    "wof:name":"Seasholtz Metallurgy Inc",
    "wof:placetype":"venue"
},
  "geometry": {"coordinates":[-76.317256,40.058022],"type":"Point"}
}