{
  "type": "Feature",
  "properties": {
    "iso:country":"US",
    "sg:address":"224 Penn Ave",
    "sg:city":"Scranton",
    "sg:classifiers":[
        {
            "category":"Parking",
            "type":"Transportation"
        }
    ],
    "sg:phone":"+1 570 344 1379",
    "sg:postcode":"18503",
    "sg:province":"PA",
    "sg:tags":[
        "automobile"
    ],
    "wof:name":"Penn Parking Plaza",
    "wof:placetype":"venue"
},
  "geometry": {"coordinates":[-75.665237,41.410423],"type":"Point"}
}