{
  "type": "Feature",
  "properties": {
    "addr:full":"126 Venango Ct New Kensington PA 15068",
    "addr:housenumber":"126",
    "addr:postcode":"15068",
    "addr:street":"Venango Ct",
    "iso:country":"US",
    "sg:address":"126 Venango Ct",
    "sg:city":"New Kensington",
    "sg:classifiers":[
        {
            "category":"Professional",
            "subcategory":"Accounting & Tax Preparation",
            "type":"Services"
        }
    ],
    "sg:phone":"+1   ",
    "sg:postcode":"15068",
    "sg:province":"PA",
    "sg:tags":[
        "return"
    ],
    "wof:name":"Voss Tax Service Christin",
    "wof:placetype":"venue"
},
  "geometry": {"coordinates":[-79.775784,40.524955],"type":"Point"}
}