{
  "type": "Feature",
  "properties": {
    "iso:country":"US",
    "sg:address":"1200 Market St Unit 23",
    "sg:city":"Lemoyne",
    "sg:classifiers":[
        {
            "category":"Banks & Credit Unions",
            "subcategory":"Bank",
            "type":"Services"
        }
    ],
    "sg:phone":"+1 717 731 1730",
    "sg:postcode":"17043",
    "sg:province":"PA",
    "wof:name":"M & T Bank",
    "wof:placetype":"venue"
},
  "geometry": {"coordinates":[-76.90797000000001,40.241621],"type":"Point"}
}