{
  "type": "Feature",
  "properties": {
    "iso:country":"US",
    "sg:address":"56 Lulay St",
    "sg:city":"Johnstown",
    "sg:classifiers":[
        {
            "category":"Shopping",
            "subcategory":"Department Store",
            "type":"Retail Goods"
        }
    ],
    "sg:phone":"+1   ",
    "sg:postcode":"15904",
    "sg:province":"PA",
    "wof:name":"Value City 135",
    "wof:placetype":"venue"
},
  "geometry": {"coordinates":[-78.873018,40.29621],"type":"Point"}
}