{
  "type": "Feature",
  "properties": {
    "iso:country":"US",
    "sg:address":"699 Baltimore Pike",
    "sg:city":"Gardners",
    "sg:classifiers":[
        {
            "category":"Travel",
            "subcategory":"Hotels & Motels",
            "type":"Entertainment"
        }
    ],
    "sg:phone":"+1 717 486 5672",
    "sg:postcode":"17324",
    "sg:province":"PA",
    "sg:tags":[
        "operation"
    ],
    "wof:name":"Old Town Run Mountain Lodge",
    "wof:placetype":"venue"
},
  "geometry": {"coordinates":[-77.16327800000001,40.079342],"type":"Point"}
}