{
  "type": "Feature",
  "properties": {
    "addr:full":"709 6th St Mc Keesport PA 15132",
    "addr:housenumber":"709",
    "addr:postcode":"15132",
    "addr:street":"6Th St",
    "iso:country":"US",
    "sg:address":"709 6th St",
    "sg:city":"Mc Keesport",
    "sg:classifiers":[
        {
            "category":"Real Estate",
            "subcategory":"Real Estate Operator",
            "type":"Services"
        }
    ],
    "sg:phone":"+1   ",
    "sg:postcode":"15132",
    "sg:province":"PA",
    "sg:tags":[
        "building",
        "apartment"
    ],
    "wof:name":"Aimco",
    "wof:placetype":"venue"
},
  "geometry": {"coordinates":[-79.857787,40.350289],"type":"Point"}
}