{
  "type": "Feature",
  "properties": {
    "iso:country":"US",
    "sg:address":"9400 McKnight Rd",
    "sg:city":"Pittsburgh",
    "sg:classifiers":[
        {
            "category":"Wholesale",
            "subcategory":"Durable Goods & Equipment",
            "type":"Manufacturing & Wholesale Goods"
        }
    ],
    "sg:phone":"+1 724 443 3904",
    "sg:postcode":"15237",
    "sg:province":"PA",
    "sg:tags":[
        "representative",
        "manufacturer"
    ],
    "wof:name":"Karen L Lund",
    "wof:placetype":"venue"
},
  "geometry": {"coordinates":[-80.028701,40.580859],"type":"Point"}
}