{
  "type": "Feature",
  "properties": {
    "iso:country":"US",
    "sg:address":"1605 N Cedar Crest Blvd",
    "sg:city":"Allentown",
    "sg:classifiers":[
        {
            "category":"Banks & Credit Unions",
            "subcategory":"Bank",
            "type":"Services"
        }
    ],
    "sg:phone":"+1 610 000 1111",
    "sg:postcode":"18104",
    "sg:province":"PA",
    "sg:tags":[
        "national",
        "commercial"
    ],
    "sg:website":"www.natpennbank.com",
    "wof:name":"National Penn Bank Inc",
    "wof:placetype":"venue"
},
  "geometry": {"coordinates":[-75.533294,40.613757],"type":"Point"}
}