{
  "type": "Feature",
  "properties": {
    "addr:full":"135 Wolfe Run Rd Cranberry Township PA 16066",
    "addr:housenumber":"135",
    "addr:postcode":"16066",
    "addr:street":"Wolfe Run Rd",
    "iso:country":"US",
    "sg:address":"135 Wolfe Run Rd",
    "sg:city":"Cranberry Township",
    "sg:classifiers":[
        {
            "category":"Building & Trades",
            "subcategory":"Cleaning & Sanitation",
            "type":"Services"
        }
    ],
    "sg:phone":"+1   ",
    "sg:postcode":"16066",
    "sg:province":"PA",
    "sg:tags":[
        "janitorial"
    ],
    "wof:name":"Swisher International",
    "wof:placetype":"venue"
},
  "geometry": {"coordinates":[-80.063895,40.731564],"type":"Point"}
}