{
  "type": "Feature",
  "properties": {
    "iso:country":"US",
    "sg:address":"1877 School Rd",
    "sg:city":"Hatfield",
    "sg:classifiers":[
        {
            "category":"Building & Trades",
            "subcategory":"Electrical",
            "type":"Services"
        }
    ],
    "sg:phone":"+1   ",
    "sg:postcode":"19440",
    "sg:province":"PA",
    "sg:tags":[
        "contracting",
        "electrical"
    ],
    "wof:name":"MJM Electric",
    "wof:placetype":"venue"
},
  "geometry": {"coordinates":[-75.28356700000001,40.284191],"type":"Point"}
}