{
  "type": "Feature",
  "properties": {
    "addr:full":"1223 Pottsville Pike Shoemakersville PA 19555",
    "addr:housenumber":"1223",
    "addr:postcode":"19555",
    "addr:street":"Pottsville Pike",
    "iso:country":"US",
    "sg:address":"1223 Pottsville Pike",
    "sg:city":"Shoemakersville",
    "sg:classifiers":[
        {
            "category":"Autos & Motor Vehicles",
            "subcategory":"Automobile Sales",
            "type":"Retail Goods"
        }
    ],
    "sg:phone":"+1 610 562 8152",
    "sg:postcode":"19555",
    "sg:province":"PA",
    "sg:tags":[
        "used"
    ],
    "wof:name":"Keystone Auto Sales",
    "wof:placetype":"venue"
},
  "geometry": {"coordinates":[-75.968379,40.51687],"type":"Point"}
}