{
  "type": "Feature",
  "properties": {
    "addr:full":"843 N Providence Rd Media PA 19063",
    "addr:housenumber":"843",
    "addr:postcode":"19063",
    "addr:street":"N Providence Rd",
    "iso:country":"US",
    "sg:address":"843 N Providence Rd",
    "sg:city":"Media",
    "sg:classifiers":[
        {
            "category":"Home & Garden",
            "subcategory":"Garden Supply",
            "type":"Retail Goods"
        }
    ],
    "sg:phone":"+1   ",
    "sg:postcode":"19063",
    "sg:province":"PA",
    "sg:tags":[
        "repair"
    ],
    "wof:name":"Media Lawn Mower Service",
    "wof:placetype":"venue"
},
  "geometry": {"coordinates":[-75.38692500000001,39.929003],"type":"Point"}
}