{
  "type": "Feature",
  "properties": {
    "iso:country":"US",
    "sg:address":"3217 Hidden Ln",
    "sg:city":"Erie",
    "sg:classifiers":[
        {
            "category":"Wholesale",
            "subcategory":"Machinery & Supplies",
            "type":"Manufacturing & Wholesale Goods"
        }
    ],
    "sg:phone":"+1 814 833 2923",
    "sg:postcode":"16506",
    "sg:province":"PA",
    "sg:tags":[
        "equipment",
        "industrial"
    ],
    "wof:name":"KML Ind Supply",
    "wof:placetype":"venue"
},
  "geometry": {"coordinates":[-80.172197,42.068127],"type":"Point"}
}