{
  "type": "Feature",
  "properties": {
    "addr:full":"1432 E 36th St Erie PA 16504",
    "addr:housenumber":"1432",
    "addr:postcode":"16504",
    "addr:street":"E 36Th St",
    "iso:country":"US",
    "sg:address":"1432 E 36th St",
    "sg:city":"Erie",
    "sg:classifiers":[
        {
            "category":"Communications",
            "type":"Services"
        }
    ],
    "sg:phone":"+1 814 456 0528",
    "sg:postcode":"16504",
    "sg:province":"PA",
    "wof:name":"Ocasio Graphics & Multimedia Solutions",
    "wof:placetype":"venue"
},
  "geometry": {"coordinates":[-80.035398,42.115705],"type":"Point"}
}