{
  "type": "Feature",
  "properties": {
    "iso:country":"US",
    "sg:address":"864 N 9th St",
    "sg:city":"Stroudsburg",
    "sg:classifiers":[
        {
            "category":"Retail",
            "subcategory":"Laundry & Dry Cleaning",
            "type":"Services"
        }
    ],
    "sg:phone":"+1 570 422 6760",
    "sg:postcode":"18360",
    "sg:province":"PA",
    "sg:tags":[
        "cleaners",
        "rug",
        "carpet"
    ],
    "wof:name":"Royal Carpet Curtain Inc",
    "wof:placetype":"venue"
},
  "geometry": {"coordinates":[-75.212947,40.989758],"type":"Point"}
}