{
  "type": "Feature",
  "properties": {
    "iso:country":"US",
    "sg:address":"235 Philmont Ave",
    "sg:city":"Feastervl Trvs",
    "sg:classifiers":[
        {
            "category":"Retail",
            "subcategory":"Auto Repair",
            "type":"Services"
        }
    ],
    "sg:phone":"+1 215 364 7449",
    "sg:postcode":"19053",
    "sg:province":"PA",
    "sg:tags":[
        "body",
        "automobile",
        "painting"
    ],
    "wof:name":"First Choice Auto Body",
    "wof:placetype":"venue"
},
  "geometry": {"coordinates":[-75.004,40.133909],"type":"Point"}
}