{
  "type": "Feature",
  "properties": {
    "iso:country":"US",
    "sg:address":"1324 Locust St",
    "sg:city":"Philadelphia",
    "sg:classifiers":[
        {
            "category":"Organizations",
            "subcategory":"Membership Organization",
            "type":"Services"
        },
        {
            "category":"Organizations",
            "subcategory":"Professional Association",
            "type":"Services"
        }
    ],
    "sg:phone":"+1 215 893 1260",
    "sg:postcode":"19107",
    "sg:province":"PA",
    "sg:website":"www.ebaphila.org",
    "wof:name":"East Of Borad Improvement Assn",
    "wof:placetype":"venue"
},
  "geometry": {"coordinates":[-75.163382,39.948065],"type":"Point"}
}