{
  "type": "Feature",
  "properties": {
    "addr:full":"1 Brandywine St Chadds Ford PA 19317",
    "addr:housenumber":"1",
    "addr:postcode":"19317",
    "addr:street":"Brandywine St",
    "iso:country":"US",
    "sg:address":"1 Brandywine St",
    "sg:city":"Chadds Ford",
    "sg:classifiers":[
        {
            "category":"Insurance",
            "subcategory":"Insurance Agent",
            "type":"Services"
        }
    ],
    "sg:phone":"+1   ",
    "sg:postcode":"19317",
    "sg:province":"PA",
    "sg:tags":[
        "agency"
    ],
    "wof:name":"Allstate",
    "wof:placetype":"venue"
},
  "geometry": {"coordinates":[-75.53917199999999,39.844249],"type":"Point"}
}