{
  "type": "Feature",
  "properties": {
    "addr:full":"2544 Mosside Blvd Monroeville PA 15146",
    "addr:housenumber":"2544",
    "addr:postcode":"15146",
    "addr:street":"Mosside Blvd",
    "iso:country":"US",
    "sg:address":"2544 Mosside Blvd",
    "sg:city":"Monroeville",
    "sg:classifiers":[
        {
            "category":"Banks & Credit Unions",
            "subcategory":"Bank",
            "type":"Services"
        }
    ],
    "sg:phone":"+1 412 856 5090",
    "sg:postcode":"15146",
    "sg:province":"PA",
    "sg:tags":[
        "loan",
        "real estate"
    ],
    "wof:name":"Countrywide Home Loans",
    "wof:placetype":"venue"
},
  "geometry": {"coordinates":[-79.754487,40.423855],"type":"Point"}
}