{
  "type": "Feature",
  "properties": {
    "iso:country":"US",
    "sg:address":"259 W King St",
    "sg:city":"Lancaster",
    "sg:classifiers":[
        {
            "category":"Home & Garden",
            "subcategory":"Household Appliances",
            "type":"Retail Goods"
        }
    ],
    "sg:phone":"+1 717 295 1973",
    "sg:postcode":"17603",
    "sg:province":"PA",
    "wof:name":"Luciano's Corner",
    "wof:placetype":"venue"
},
  "geometry": {"coordinates":[-76.30962700000001,40.037635],"type":"Point"}
}