{
  "type": "Feature",
  "properties": {
    "iso:country":"US",
    "sg:address":"240 W Roberts Ave",
    "sg:city":"Philadelphia",
    "sg:classifiers":[
        {
            "category":"Wholesale",
            "subcategory":"Scrap",
            "type":"Manufacturing & Wholesale Goods"
        }
    ],
    "sg:phone":"+1 215 842 3587",
    "sg:postcode":"19144",
    "sg:province":"PA",
    "sg:tags":[
        "recycling",
        "center"
    ],
    "wof:name":"American Box & Recycling Co",
    "wof:placetype":"venue"
},
  "geometry": {"coordinates":[-75.16260699999999,40.021017],"type":"Point"}
}