{
  "type": "Feature",
  "properties": {
    "iso:country":"US",
    "sg:address":"1541 Alta Dr",
    "sg:city":"Whitehall",
    "sg:classifiers":[
        {
            "category":"Wholesale",
            "subcategory":"Electrical",
            "type":"Manufacturing & Wholesale Goods"
        }
    ],
    "sg:phone":"+1 610 432 1191",
    "sg:postcode":"18052",
    "sg:province":"PA",
    "sg:tags":[
        "alarm",
        "burglar",
        "system"
    ],
    "wof:name":"Tri State Alarm Co",
    "wof:placetype":"venue"
},
  "geometry": {"coordinates":[-75.48641499999999,40.627621],"type":"Point"}
}