{
  "type": "Feature",
  "properties": {
    "iso:country":"US",
    "sg:address":"601 S 16th St",
    "sg:city":"Columbia",
    "sg:classifiers":[
        {
            "category":"Sports & Exercise",
            "subcategory":"Bowling",
            "type":"Entertainment"
        },
        {
            "category":"Bars & Pubs",
            "type":"Food & Drink"
        }
    ],
    "sg:phone":"+1 717 684 2511",
    "sg:postcode":"17512",
    "sg:province":"PA",
    "sg:tags":[
        "lounge",
        "alley",
        "cocktail"
    ],
    "wof:name":"Columbia Bowling Center",
    "wof:placetype":"venue"
},
  "geometry": {"coordinates":[-76.479699,40.029137],"type":"Point"}
}