{
  "type": "Feature",
  "properties": {
    "iso:country":"US",
    "sg:address":"214 W Plank Rd",
    "sg:city":"Altoona",
    "sg:classifiers":[
        {
            "category":"Banks & Credit Unions",
            "subcategory":"Bank",
            "type":"Services"
        }
    ],
    "sg:phone":"+1 814 949 5844",
    "sg:postcode":"16602",
    "sg:province":"PA",
    "sg:tags":[
        "loan",
        "real estate"
    ],
    "wof:name":"Altoona Financial Svc",
    "wof:placetype":"venue"
},
  "geometry": {"coordinates":[-78.40415299999999,40.477109],"type":"Point"}
}