{
  "type": "Feature",
  "properties": {
    "iso:country":"US",
    "sg:address":"2804 Baltimore Pike",
    "sg:city":"Gettysburg",
    "sg:phone":"+1   ",
    "sg:postcode":"17325",
    "sg:province":"PA",
    "sg:tags":[
        "farm",
        "corn",
        "soybean"
    ],
    "wof:name":"Wilbur Danner",
    "wof:placetype":"venue"
},
  "geometry": {"coordinates":[-77.169775,39.780694],"type":"Point"}
}