{
  "type": "Feature",
  "properties": {
    "addr:full":"1570 Oakland Ave Indiana PA 15701",
    "addr:housenumber":"1570",
    "addr:postcode":"15701",
    "addr:street":"Oakland Ave",
    "iso:country":"US",
    "sg:address":"1570 Oakland Ave",
    "sg:city":"Indiana",
    "sg:classifiers":[
        {
            "category":"Social Services",
            "type":"Services"
        }
    ],
    "sg:phone":"+1 724 463 6212",
    "sg:postcode":"15701",
    "sg:province":"PA",
    "sg:tags":[
        "organization",
        "welfare"
    ],
    "wof:name":"Goodwill Industries",
    "wof:placetype":"venue"
},
  "geometry": {"coordinates":[-79.17130299999999,40.615058],"type":"Point"}
}