{
  "type": "Feature",
  "properties": {
    "addr:full":"1154 Saint Ann Dr Erie PA 16509",
    "addr:housenumber":"1154",
    "addr:postcode":"16509",
    "addr:street":"Saint Ann Dr",
    "iso:country":"US",
    "sg:address":"1154 Saint Ann Dr",
    "sg:city":"Erie",
    "sg:classifiers":[
        {
            "category":"Building & Trades",
            "subcategory":"Electrical",
            "type":"Services"
        }
    ],
    "sg:phone":"+1   ",
    "sg:postcode":"16509",
    "sg:province":"PA",
    "sg:tags":[
        "electrical",
        "contractor"
    ],
    "wof:name":"Brocki Blackman Electric",
    "wof:placetype":"venue"
},
  "geometry": {"coordinates":[-80.080671,42.073755],"type":"Point"}
}