{
  "type": "Feature",
  "properties": {
    "iso:country":"US",
    "sg:address":"449 Hamilton St",
    "sg:city":"Norristown",
    "sg:classifiers":[
        {
            "category":"Personal",
            "subcategory":"Beauty Salon",
            "type":"Services"
        }
    ],
    "sg:phone":"+1   ",
    "sg:postcode":"19401",
    "sg:province":"PA",
    "sg:tags":[
        "shop"
    ],
    "wof:name":"Tiffany II Beauty Salon",
    "wof:placetype":"venue"
},
  "geometry": {"coordinates":[-75.35932,40.121875],"type":"Point"}
}