{
  "type": "Feature",
  "properties": {
    "iso:country":"US",
    "sg:address":"1038 W Lancaster Ave",
    "sg:city":"Bryn Mawr",
    "sg:classifiers":[
        {
            "category":"Home & Garden",
            "subcategory":"Home Furnishings",
            "type":"Retail Goods"
        }
    ],
    "sg:phone":"+1 610 520 3446",
    "sg:postcode":"19010",
    "sg:province":"PA",
    "sg:tags":[
        "linen"
    ],
    "wof:name":"Yves Delorme",
    "wof:placetype":"venue"
},
  "geometry": {"coordinates":[-75.324128,40.024228],"type":"Point"}
}