{
  "type": "Feature",
  "properties": {
    "iso:country":"US",
    "sg:address":"110 N Chester Rd",
    "sg:city":"West Chester",
    "sg:classifiers":[
        {
            "category":"Sports & Exercise",
            "subcategory":"Gym",
            "type":"Entertainment"
        }
    ],
    "sg:phone":"+1   ",
    "sg:postcode":"19380",
    "sg:province":"PA",
    "sg:tags":[
        "fitness",
        "physical",
        "facility"
    ],
    "wof:name":"Greg Smiths Power Fitness",
    "wof:placetype":"venue"
},
  "geometry": {"coordinates":[-75.52749,39.96927],"type":"Point"}
}