{
  "type": "Feature",
  "properties": {
    "addr:full":"629 2nd Street Pike Southampton PA 18966",
    "addr:housenumber":"629",
    "addr:postcode":"18966",
    "addr:street":"2Nd Street Pike",
    "iso:country":"US",
    "sg:address":"629 2nd Street Pike",
    "sg:city":"Southampton",
    "sg:classifiers":[
        {
            "category":"Shopping",
            "subcategory":"Clothing, Apparel, & Fashions",
            "type":"Retail Goods"
        }
    ],
    "sg:phone":"+1 215 357 5844",
    "sg:postcode":"18966",
    "sg:province":"PA",
    "sg:tags":[
        "storage",
        "fur",
        "coat"
    ],
    "wof:name":"Hubert Furs",
    "wof:placetype":"venue"
},
  "geometry": {"coordinates":[-75.044476,40.172159],"type":"Point"}
}