{
  "type": "Feature",
  "properties": {
    "iso:country":"US",
    "sg:address":"1825 Murray Ave",
    "sg:city":"Pittsburgh",
    "sg:classifiers":[
        {
            "category":"Health Services",
            "subcategory":"Doctor",
            "type":"Services"
        }
    ],
    "sg:phone":"+1 412 521 5343",
    "sg:postcode":"15217",
    "sg:province":"PA",
    "sg:tags":[
        "dentist"
    ],
    "wof:name":"Edward J Horan DDS",
    "wof:placetype":"venue"
},
  "geometry": {"coordinates":[-79.922816,40.436258],"type":"Point"}
}