{
  "type": "Feature",
  "properties": {
    "addr:full":"112 E Summit Ave Oxford PA 19363",
    "addr:housenumber":"112",
    "addr:postcode":"19363",
    "addr:street":"E Summit Ave",
    "iso:country":"US",
    "sg:address":"112 E Summit Ave",
    "sg:city":"Oxford",
    "sg:classifiers":[
        {
            "category":"Food & Beverages",
            "subcategory":"Specialty",
            "type":"Retail Goods"
        }
    ],
    "sg:phone":"+1   ",
    "sg:postcode":"19363",
    "sg:province":"PA",
    "wof:name":"Alm Haus Foods",
    "wof:placetype":"venue"
},
  "geometry": {"coordinates":[-75.981863,39.779352],"type":"Point"}
}