{
  "type": "Feature",
  "properties": {
    "iso:country":"US",
    "sg:address":"846 E Street Rd",
    "sg:city":"Warminster",
    "sg:classifiers":[
        {
            "category":"Restaurant",
            "type":"Food & Drink"
        }
    ],
    "sg:phone":"+1   ",
    "sg:postcode":"18974",
    "sg:province":"PA",
    "sg:tags":[
        "eating"
    ],
    "wof:name":"Tonys Pizza",
    "wof:placetype":"venue"
},
  "geometry": {"coordinates":[-75.108734,40.211736],"type":"Point"}
}