{
  "type": "Feature",
  "properties": {
    "addr:full":"464 2nd Street Pike Southampton PA 18966",
    "addr:housenumber":"464",
    "addr:postcode":"18966",
    "addr:street":"2Nd Street Pike",
    "iso:country":"US",
    "sg:address":"464 2nd Street Pike",
    "sg:city":"Southampton",
    "sg:classifiers":[
        {
            "category":"Banks & Credit Unions",
            "subcategory":"Bank",
            "type":"Services"
        }
    ],
    "sg:phone":"+1   ",
    "sg:postcode":"18966",
    "sg:province":"PA",
    "sg:tags":[
        "state"
    ],
    "wof:name":"Citizens Bank of Pennsylvania",
    "wof:placetype":"venue"
},
  "geometry": {"coordinates":[-75.04489700000001,40.170702],"type":"Point"}
}