{
  "type": "Feature",
  "properties": {
    "iso:country":"US",
    "sg:address":"120 E Main St",
    "sg:city":"Palmyra",
    "sg:classifiers":[
        {
            "category":"Food & Beverages",
            "subcategory":"Specialty",
            "type":"Retail Goods"
        }
    ],
    "sg:phone":"+1 717 838 2501",
    "sg:postcode":"17078",
    "sg:province":"PA",
    "sg:tags":[
        "health",
        "market"
    ],
    "wof:name":"Palmyra Natural Foods",
    "wof:placetype":"venue"
},
  "geometry": {"coordinates":[-76.5942,40.308102],"type":"Point"}
}