{
  "type": "Feature",
  "properties": {
    "iso:country":"US",
    "sg:address":"155 Wyoming Ave",
    "sg:city":"Wyoming",
    "sg:classifiers":[
        {
            "category":"Real Estate",
            "subcategory":"Developer",
            "type":"Services"
        }
    ],
    "sg:phone":"+1 570 693 4411",
    "sg:postcode":"18644",
    "sg:province":"PA",
    "sg:tags":[
        "cemetery"
    ],
    "wof:name":"Wyoming Cemetery Association",
    "wof:placetype":"venue"
},
  "geometry": {"coordinates":[-75.834688,41.313735],"type":"Point"}
}