{
  "type": "Feature",
  "properties": {
    "addr:full":"508 Prudential Rd Horsham PA 19044",
    "addr:housenumber":"508",
    "addr:postcode":"19044",
    "addr:street":"Prudential Rd",
    "iso:country":"US",
    "sg:address":"508 Prudential Rd",
    "sg:city":"Horsham",
    "sg:classifiers":[
        {
            "category":"Banks & Credit Unions",
            "subcategory":"Bank",
            "type":"Services"
        }
    ],
    "sg:phone":"+1   ",
    "sg:postcode":"19044",
    "sg:province":"PA",
    "sg:tags":[
        "personal",
        "institution"
    ],
    "wof:name":"Fleet",
    "wof:placetype":"venue"
},
  "geometry": {"coordinates":[-75.137249,40.169934],"type":"Point"}
}