{
  "type": "Feature",
  "properties": {
    "iso:country":"US",
    "sg:address":"3140 State Rte 257",
    "sg:city":"Seneca",
    "sg:classifiers":[
        {
            "category":"Health Services",
            "subcategory":"Doctor",
            "type":"Services"
        }
    ],
    "sg:phone":"+1 814 677 6470",
    "sg:postcode":"16346",
    "sg:province":"PA",
    "sg:tags":[
        "physician",
        "surgeon"
    ],
    "wof:name":"Fritz Orthopedic Ctr",
    "wof:placetype":"venue"
},
  "geometry": {"coordinates":[-79.70368999999999,41.375787],"type":"Point"}
}