{
  "type": "Feature",
  "properties": {
    "iso:country":"US",
    "sg:address":"104 E Main St",
    "sg:city":"Lansdale",
    "sg:classifiers":[
        {
            "category":"Wholesale",
            "subcategory":"Drugs",
            "type":"Manufacturing & Wholesale Goods"
        }
    ],
    "sg:phone":"+1 215 361 9880",
    "sg:postcode":"19446",
    "sg:province":"PA",
    "wof:name":"Martek Biosciences Corp",
    "wof:placetype":"venue"
},
  "geometry": {"coordinates":[-75.280672,40.239686],"type":"Point"}
}