{
  "type": "Feature",
  "properties": {
    "addr:full":"10770 Wattsburg Rd Erie PA 16509",
    "addr:housenumber":"10770",
    "addr:postcode":"16509",
    "addr:street":"Wattsburg Rd",
    "iso:country":"US",
    "sg:address":"10770 Wattsburg Rd",
    "sg:city":"Erie",
    "sg:classifiers":[
        {
            "category":"Education",
            "subcategory":"School",
            "type":"Public Place"
        }
    ],
    "sg:phone":"+1   ",
    "sg:postcode":"16509",
    "sg:province":"PA",
    "sg:tags":[
        "high"
    ],
    "wof:name":"Seneca High School",
    "wof:placetype":"venue"
},
  "geometry": {"coordinates":[-79.904062,42.056711],"type":"Point"}
}