{
  "type": "Feature",
  "properties": {
    "addr:full":"1415 Gail Ave Allentown PA 18103",
    "addr:housenumber":"1415",
    "addr:postcode":"18103",
    "addr:street":"Gail Ave",
    "iso:country":"US",
    "sg:address":"1415 Gail Ave",
    "sg:city":"Allentown",
    "sg:classifiers":[
        {
            "category":"Professional",
            "subcategory":"Lawyer & Legal Services",
            "type":"Services"
        }
    ],
    "sg:phone":"+1   ",
    "sg:postcode":"18103",
    "sg:province":"PA",
    "sg:tags":[
        "law"
    ],
    "wof:name":"Dawn Casselle Astride",
    "wof:placetype":"venue"
},
  "geometry": {"coordinates":[-75.42043700000001,40.586969],"type":"Point"}
}