{
  "type": "Feature",
  "properties": {
    "addr:full":"18 E Maple St Dallastown PA 17313",
    "addr:housenumber":"18",
    "addr:postcode":"17313",
    "addr:street":"E Maple St",
    "iso:country":"US",
    "sg:address":"18 E Maple St",
    "sg:city":"Dallastown",
    "sg:classifiers":[
        {
            "category":"Retail",
            "subcategory":"Auto Repair",
            "type":"Services"
        }
    ],
    "sg:phone":"+1   ",
    "sg:postcode":"17313",
    "sg:province":"PA",
    "sg:tags":[
        "automotive"
    ],
    "wof:name":"Pro Mobile Algnmt Specialist",
    "wof:placetype":"venue"
},
  "geometry": {"coordinates":[-76.641868,39.901564],"type":"Point"}
}