{
  "type": "Feature",
  "properties": {
    "addr:full":"357 N Craig St Pittsburgh PA 15213",
    "addr:housenumber":"357",
    "addr:postcode":"15213",
    "addr:street":"N Craig St",
    "iso:country":"US",
    "sg:address":"357 N Craig St",
    "sg:city":"Pittsburgh",
    "sg:classifiers":[
        {
            "category":"Professional",
            "subcategory":"Accounting & Tax Preparation",
            "type":"Services"
        }
    ],
    "sg:phone":"+1   ",
    "sg:postcode":"15213",
    "sg:province":"PA",
    "sg:tags":[
        "accountant",
        "public",
        "certified"
    ],
    "wof:name":"Exler & Company Inc",
    "wof:placetype":"venue"
},
  "geometry": {"coordinates":[-79.95330800000001,40.453762],"type":"Point"}
}