{
  "type": "Feature",
  "properties": {
    "addr:full":"126 Analomink St East Stroudsburg PA 18301",
    "addr:housenumber":"126",
    "addr:postcode":"18301",
    "addr:street":"Analomink St",
    "iso:country":"US",
    "sg:address":"126 Analomink St",
    "sg:city":"East Stroudsburg",
    "sg:classifiers":[
        {
            "category":"Professional",
            "subcategory":"Business Services",
            "type":"Services"
        }
    ],
    "sg:phone":"+1 570 476 4290",
    "sg:postcode":"18301",
    "sg:province":"PA",
    "sg:tags":[
        "interior",
        "consultant",
        "design",
        "decorator"
    ],
    "wof:name":"J & L Studios",
    "wof:placetype":"venue"
},
  "geometry": {"coordinates":[-75.177441,41.001558],"type":"Point"}
}