{
  "type": "Feature",
  "properties": {
    "iso:country":"US",
    "sg:address":"620 Freedom Business Center Dr",
    "sg:city":"King Of Prussia",
    "sg:classifiers":[
        {
            "category":"Professional",
            "subcategory":"Lawyer & Legal Services",
            "type":"Services"
        }
    ],
    "sg:phone":"+1 610 205 6000",
    "sg:postcode":"19406",
    "sg:province":"PA",
    "sg:tags":[
        "attorney"
    ],
    "wof:name":"Stevens & Lee",
    "wof:placetype":"venue"
},
  "geometry": {"coordinates":[-75.41086300000001,40.094881],"type":"Point"}
}