{
  "type": "Feature",
  "properties": {
    "iso:country":"US",
    "sg:address":"44 Hanover St",
    "sg:city":"Glen Rock",
    "sg:classifiers":[
        {
            "category":"Shopping",
            "type":"Retail Goods"
        }
    ],
    "sg:phone":"+1   ",
    "sg:postcode":"17327",
    "sg:province":"PA",
    "sg:tags":[
        "merchandise"
    ],
    "wof:name":"Confections Parrot & Etc",
    "wof:placetype":"venue"
},
  "geometry": {"coordinates":[-76.73206999999999,39.792891],"type":"Point"}
}