{
  "type": "Feature",
  "properties": {
    "addr:full":"8 Hastings Ave Havertown PA 19083",
    "addr:housenumber":"8",
    "addr:postcode":"19083",
    "addr:street":"Hastings Ave",
    "iso:country":"US",
    "sg:address":"8 Hastings Ave",
    "sg:city":"Havertown",
    "sg:classifiers":[
        {
            "category":"Home & Garden",
            "subcategory":"Building Materials",
            "type":"Retail Goods"
        }
    ],
    "sg:phone":"+1 610 853 3535",
    "sg:postcode":"19083",
    "sg:province":"PA",
    "sg:tags":[
        "windows"
    ],
    "wof:name":"A & J Contractors",
    "wof:placetype":"venue"
},
  "geometry": {"coordinates":[-75.306318,39.987352],"type":"Point"}
}