{
  "type": "Feature",
  "properties": {
    "iso:country":"US",
    "sg:address":"212 Neshaminy Rd",
    "sg:city":"Croydon",
    "sg:classifiers":[
        {
            "category":"Shopping",
            "type":"Retail Goods"
        }
    ],
    "sg:phone":"+1   ",
    "sg:postcode":"19021",
    "sg:province":"PA",
    "sg:tags":[
        "pet",
        "supply"
    ],
    "wof:name":"Kritters Pet Center",
    "wof:placetype":"venue"
},
  "geometry": {"coordinates":[-74.911058,40.097354],"type":"Point"}
}