{
  "type": "Feature",
  "properties": {
    "addr:full":"12878 Raymond Dr Meadville PA 16335",
    "addr:housenumber":"12878",
    "addr:postcode":"16335",
    "addr:street":"Raymond Dr",
    "iso:country":"US",
    "sg:address":"12878 Raymond Dr",
    "sg:city":"Meadville",
    "sg:classifiers":[
        {
            "category":"Real Estate",
            "subcategory":"Real Estate Operator",
            "type":"Services"
        }
    ],
    "sg:phone":"+1 814 724 2744",
    "sg:postcode":"16335",
    "sg:province":"PA",
    "sg:tags":[
        "apartment"
    ],
    "wof:name":"Oakwood Apartments",
    "wof:placetype":"venue"
},
  "geometry": {"coordinates":[-80.112123,41.645537],"type":"Point"}
}