{
  "type": "Feature",
  "properties": {
    "iso:country":"US",
    "sg:address":"1724 Mount Royal Blvd",
    "sg:city":"Glenshaw",
    "sg:classifiers":[
        {
            "category":"Health Services",
            "subcategory":"Doctor",
            "type":"Services"
        }
    ],
    "sg:phone":"+1 412 213 1999",
    "sg:postcode":"15116",
    "sg:province":"PA",
    "sg:tags":[
        "dentist"
    ],
    "wof:name":"Katsur Dental & Orthodontics",
    "wof:placetype":"venue"
},
  "geometry": {"coordinates":[-79.96299500000001,40.526044],"type":"Point"}
}