{
  "type": "Feature",
  "properties": {
    "addr:full":"65 Church Rd Wyoming PA 18644",
    "addr:housenumber":"65",
    "addr:postcode":"18644",
    "addr:street":"Church Rd",
    "iso:country":"US",
    "sg:address":"65 Church Rd",
    "sg:city":"Wyoming",
    "sg:classifiers":[
        {
            "category":"Retail",
            "subcategory":"Animal Services",
            "type":"Services"
        }
    ],
    "sg:phone":"+1 570 675 9511",
    "sg:postcode":"18644",
    "sg:province":"PA",
    "sg:tags":[
        "pet",
        "boarding",
        "sitting"
    ],
    "wof:name":"Peach's Pet Sitting Svc",
    "wof:placetype":"venue"
},
  "geometry": {"coordinates":[-75.908191,41.35471],"type":"Point"}
}