{
  "type": "Feature",
  "properties": {
    "iso:country":"US",
    "sg:address":"115 Kuebler Rd",
    "sg:city":"Easton",
    "sg:classifiers":[
        {
            "category":"Manufacturing",
            "subcategory":"Rubber & Plastics",
            "type":"Manufacturing & Wholesale Goods"
        }
    ],
    "sg:phone":"+1   ",
    "sg:postcode":"18040",
    "sg:province":"PA",
    "sg:tags":[
        "extrude",
        "pipe",
        "teflon",
        "rod"
    ],
    "wof:name":"Surf Technology",
    "wof:placetype":"venue"
},
  "geometry": {"coordinates":[-75.218502,40.740007],"type":"Point"}
}