{
  "type": "Feature",
  "properties": {
    "addr:full":"5128 Rte 210 Smicksburg PA 16256",
    "addr:housenumber":"5128",
    "addr:postcode":"16256",
    "addr:street":"Rte 210",
    "iso:country":"US",
    "sg:address":"5128 Rte 210",
    "sg:city":"Smicksburg",
    "sg:classifiers":[
        {
            "category":"Professional",
            "subcategory":"Research",
            "type":"Services"
        }
    ],
    "sg:phone":"+1   ",
    "sg:postcode":"16256",
    "sg:province":"PA",
    "sg:tags":[
        "nonphysical",
        "commercial"
    ],
    "wof:name":"Bernard D Houllion",
    "wof:placetype":"venue"
},
  "geometry": {"coordinates":[-79.08134200000001,40.859653],"type":"Point"}
}