{
  "type": "Feature",
  "properties": {
    "addr:full":"2039 Saw Mill Run Blvd Pittsburgh PA 15210",
    "addr:housenumber":"2039",
    "addr:postcode":"15210",
    "addr:street":"Saw Mill Run Blvd",
    "iso:country":"US",
    "sg:address":"2039 Saw Mill Run Blvd",
    "sg:city":"Pittsburgh",
    "sg:classifiers":[
        {
            "category":"Retail",
            "subcategory":"Repair Shop",
            "type":"Services"
        }
    ],
    "sg:phone":"+1 412 881 0632",
    "sg:postcode":"15210",
    "sg:province":"PA",
    "sg:tags":[
        "equipment",
        "hydraulic"
    ],
    "wof:name":"A-Jax Hydraulics",
    "wof:placetype":"venue"
},
  "geometry": {"coordinates":[-79.99665899999999,40.390407],"type":"Point"}
}