{
  "type": "Feature",
  "properties": {
    "iso:country":"US",
    "sg:address":"315 Bantam Ave",
    "sg:city":"Butler",
    "sg:classifiers":[
        {
            "category":"Wholesale",
            "subcategory":"Machinery & Supplies",
            "type":"Manufacturing & Wholesale Goods"
        }
    ],
    "sg:phone":"+1 724 285 5184",
    "sg:postcode":"16001",
    "sg:province":"PA",
    "sg:tags":[
        "medical-cylinder",
        "bulk",
        "gas-industrial"
    ],
    "sg:website":"http://www.cryostar.com",
    "wof:name":"Boc Gases",
    "wof:placetype":"venue"
},
  "geometry": {"coordinates":[-79.907478,40.858051],"type":"Point"}
}