{
  "type": "Feature",
  "properties": {
    "iso:country":"US",
    "sg:address":"372 W High St",
    "sg:city":"Pottstown",
    "sg:classifiers":[
        {
            "category":"Recreation",
            "type":"Entertainment"
        }
    ],
    "sg:phone":"+1 610 327 8322",
    "sg:postcode":"19464",
    "sg:province":"PA",
    "sg:tags":[
        "hall",
        "auditorium"
    ],
    "wof:name":"Hall Nate",
    "wof:placetype":"venue"
},
  "geometry": {"coordinates":[-75.66465700000001,40.248645],"type":"Point"}
}