{
  "type": "Feature",
  "properties": {
    "addr:full":"1806 Edgmont Ave Chester PA 19013",
    "addr:housenumber":"1806",
    "addr:postcode":"19013",
    "addr:street":"Edgmont Ave",
    "iso:country":"US",
    "sg:address":"1806 Edgmont Ave",
    "sg:city":"Chester",
    "sg:classifiers":[
        {
            "category":"Building & Trades",
            "subcategory":"Landscaping Services",
            "type":"Services"
        }
    ],
    "sg:phone":"+1   ",
    "sg:postcode":"19013",
    "sg:province":"PA",
    "sg:tags":[
        "landscape"
    ],
    "wof:name":"Green Garden Inc",
    "wof:placetype":"venue"
},
  "geometry": {"coordinates":[-75.363969,39.861826],"type":"Point"}
}