{
  "type": "Feature",
  "properties": {
    "iso:country":"US",
    "sg:address":"133 Sundew Ct",
    "sg:city":"Allentown",
    "sg:classifiers":[
        {
            "category":"Building & Trades",
            "subcategory":"Construction",
            "type":"Services"
        }
    ],
    "sg:phone":"+1   ",
    "sg:postcode":"18104",
    "sg:province":"PA",
    "sg:tags":[
        "house"
    ],
    "wof:name":"Ferrell Construction Co",
    "wof:placetype":"venue"
},
  "geometry": {"coordinates":[-75.58463399999999,40.581352],"type":"Point"}
}