{
  "type": "Feature",
  "properties": {
    "iso:country":"US",
    "sg:address":"712 Federal St",
    "sg:city":"Lebanon",
    "sg:classifiers":[
        {
            "category":"Organizations",
            "subcategory":"Community Association",
            "type":"Services"
        }
    ],
    "sg:phone":"+1 717 272 8319",
    "sg:postcode":"17042",
    "sg:province":"PA",
    "sg:tags":[
        "fraternal"
    ],
    "wof:name":"Travelers Protective Assoc",
    "wof:placetype":"venue"
},
  "geometry": {"coordinates":[-76.423348,40.33733],"type":"Point"}
}