{
  "type": "Feature",
  "properties": {
    "iso:country":"US",
    "sg:address":"100 Stotler Rd",
    "sg:city":"Pittsburgh",
    "sg:classifiers":[
        {
            "category":"Autos & Motor Vehicles",
            "subcategory":"Fuel & Gas Station",
            "type":"Retail Goods"
        }
    ],
    "sg:phone":"+1   ",
    "sg:postcode":"15235",
    "sg:province":"PA",
    "sg:tags":[
        "station",
        "gasoline"
    ],
    "wof:name":"Autos R US Inc",
    "wof:placetype":"venue"
},
  "geometry": {"coordinates":[-79.80529799999999,40.462308],"type":"Point"}
}