{
  "type": "Feature",
  "properties": {
    "iso:country":"US",
    "sg:address":"1122 Commons Blvd",
    "sg:city":"Reading",
    "sg:classifiers":[
        {
            "category":"Wholesale",
            "subcategory":"Stationery",
            "type":"Manufacturing & Wholesale Goods"
        }
    ],
    "sg:phone":"+1 610 926 6551",
    "sg:postcode":"19605",
    "sg:province":"PA",
    "sg:tags":[
        "scrap",
        "paper",
        "buying",
        "selling"
    ],
    "wof:name":"Damore Brothers",
    "wof:placetype":"venue"
},
  "geometry": {"coordinates":[-75.95109600000001,40.40139],"type":"Point"}
}