{
  "type": "Feature",
  "properties": {
    "iso:country":"US",
    "sg:address":"4004 Monroeville Blvd",
    "sg:city":"Monroeville",
    "sg:classifiers":[
        {
            "category":"Shopping",
            "subcategory":"Department Store",
            "type":"Retail Goods"
        }
    ],
    "sg:phone":"+1 412 374 9611",
    "sg:postcode":"15146",
    "sg:province":"PA",
    "wof:name":"Target",
    "wof:placetype":"venue"
},
  "geometry": {"coordinates":[-79.77008499999999,40.435419],"type":"Point"}
}