{
  "type": "Feature",
  "properties": {
    "addr:full":"340 Carsonia Ave Reading PA 19606",
    "addr:housenumber":"340",
    "addr:postcode":"19606",
    "addr:street":"Carsonia Ave",
    "iso:country":"US",
    "sg:address":"340 Carsonia Ave",
    "sg:city":"Reading",
    "sg:classifiers":[
        {
            "category":"Building & Trades",
            "subcategory":"Construction",
            "type":"Services"
        }
    ],
    "sg:phone":"+1   ",
    "sg:postcode":"19606",
    "sg:province":"PA",
    "sg:tags":[
        "hanging",
        "contractor"
    ],
    "wof:name":"William Erkert",
    "wof:placetype":"venue"
},
  "geometry": {"coordinates":[-75.888677,40.332705],"type":"Point"}
}