{
  "type": "Feature",
  "properties": {
    "iso:country":"US",
    "sg:address":"4235 Carolyn Dr",
    "sg:city":"Slatington",
    "sg:classifiers":[
        {
            "category":"Home & Garden",
            "subcategory":"Home Furnishings",
            "type":"Retail Goods"
        }
    ],
    "sg:phone":"+1 610 767 4178",
    "sg:postcode":"18080",
    "sg:province":"PA",
    "wof:name":"Performance Closets & More",
    "wof:placetype":"venue"
},
  "geometry": {"coordinates":[-75.62574600000001,40.697728],"type":"Point"}
}