{
  "type": "Feature",
  "properties": {
    "iso:country":"US",
    "sg:address":"3109 Crab Hollow Rd",
    "sg:city":"Pittsburgh",
    "sg:classifiers":[
        {
            "category":"Professional",
            "subcategory":"Detective & Security Services",
            "type":"Services"
        }
    ],
    "sg:phone":"+1   ",
    "sg:postcode":"15235",
    "sg:province":"PA",
    "sg:tags":[
        "agency"
    ],
    "wof:name":"A Adam Detective Agency",
    "wof:placetype":"venue"
},
  "geometry": {"coordinates":[-79.8494,40.460548],"type":"Point"}
}