{
  "type": "Feature",
  "properties": {
    "iso:country":"US",
    "sg:address":"1831 Harrison St",
    "sg:city":"Philadelphia",
    "sg:classifiers":[
        {
            "category":"Retail",
            "subcategory":"Laundry & Dry Cleaning",
            "type":"Services"
        }
    ],
    "sg:phone":"+1 215 537 0803",
    "sg:postcode":"19124",
    "sg:province":"PA",
    "wof:name":"Ban Nguyen",
    "wof:placetype":"venue"
},
  "geometry": {"coordinates":[-75.075839,40.016137],"type":"Point"}
}