{
  "type": "Feature",
  "properties": {
    "addr:full":"62 Grove St Carbondale PA 18407",
    "addr:housenumber":"62",
    "addr:postcode":"18407",
    "addr:street":"Grove St",
    "iso:country":"US",
    "sg:address":"62 Grove St",
    "sg:city":"Carbondale",
    "sg:classifiers":[
        {
            "category":"Building & Trades",
            "subcategory":"Construction",
            "type":"Services"
        }
    ],
    "sg:phone":"+1 570 282 1334",
    "sg:postcode":"18407",
    "sg:province":"PA",
    "sg:tags":[
        "altering",
        "remodeling",
        "contractor"
    ],
    "wof:name":"Jack Mangan's General Contracting",
    "wof:placetype":"venue"
},
  "geometry": {"coordinates":[-75.49325399999999,41.57221],"type":"Point"}
}