{
  "type": "Feature",
  "properties": {
    "iso:country":"US",
    "sg:address":"6300 E Liberty Blvd",
    "sg:city":"Pittsburgh",
    "sg:classifiers":[
        {
            "category":"Organizations",
            "subcategory":"Religious Organization",
            "type":"Services"
        }
    ],
    "sg:phone":"+1 412 361 7000",
    "sg:postcode":"15206",
    "sg:province":"PA",
    "sg:tags":[
        "church"
    ],
    "wof:name":"Pentecostal Temple Church-God",
    "wof:placetype":"venue"
},
  "geometry": {"coordinates":[-79.91981,40.464973],"type":"Point"}
}