{
  "type": "Feature",
  "properties": {
    "iso:country":"US",
    "sg:address":"125 W Main St",
    "sg:city":"Kutztown",
    "sg:classifiers":[
        {
            "category":"Manufacturing",
            "subcategory":"Jewelry",
            "type":"Manufacturing & Wholesale Goods"
        }
    ],
    "sg:phone":"+1 610 683 9544",
    "sg:postcode":"19530",
    "sg:province":"PA",
    "sg:tags":[
        "costume",
        "mfg"
    ],
    "sg:website":"www.sorrelli.com",
    "wof:name":"Sorrelli Jewelry Co",
    "wof:placetype":"venue"
},
  "geometry": {"coordinates":[-75.77661500000001,40.518227],"type":"Point"}
}