{
  "type": "Feature",
  "properties": {
    "addr:full":"1505 Laurel Cir Warrington PA 18976",
    "addr:housenumber":"1505",
    "addr:postcode":"18976",
    "addr:street":"Laurel Cir",
    "iso:country":"US",
    "sg:address":"1505 Laurel Cir",
    "sg:city":"Warrington",
    "sg:classifiers":[
        {
            "category":"Wholesale",
            "subcategory":"Stationery",
            "type":"Manufacturing & Wholesale Goods"
        }
    ],
    "sg:phone":"+1 215 343 2245",
    "sg:postcode":"18976",
    "sg:province":"PA",
    "sg:tags":[
        "business",
        "form",
        "system"
    ],
    "wof:name":"Prime Business Systems",
    "wof:placetype":"venue"
},
  "geometry": {"coordinates":[-75.10818500000001,40.242226],"type":"Point"}
}