{
  "type": "Feature",
  "properties": {
    "iso:country":"US",
    "sg:address":"401 Norristown Rd",
    "sg:city":"Horsham",
    "sg:classifiers":[
        {
            "category":"Retail",
            "subcategory":"Auto Rental",
            "type":"Services"
        }
    ],
    "sg:phone":"+1   ",
    "sg:postcode":"19044",
    "sg:province":"PA",
    "sg:tags":[
        "truck"
    ],
    "wof:name":"Ryder",
    "wof:placetype":"venue"
},
  "geometry": {"coordinates":[-75.150335,40.187833],"type":"Point"}
}