{
  "type": "Feature",
  "properties": {
    "addr:full":"2930 N 5th Street Hwy Reading PA 19605",
    "addr:housenumber":"2930",
    "addr:postcode":"19605",
    "addr:street":"N 5Th Street Hwy",
    "iso:country":"US",
    "sg:address":"2930 N 5th Street Hwy",
    "sg:city":"Reading",
    "sg:classifiers":[
        {
            "category":"Shopping",
            "subcategory":"Gifts & Souvenirs",
            "type":"Retail Goods"
        }
    ],
    "sg:phone":"+1   ",
    "sg:postcode":"19605",
    "sg:province":"PA",
    "wof:name":"L B S N O Z S",
    "wof:placetype":"venue"
},
  "geometry": {"coordinates":[-75.92757400000001,40.384742],"type":"Point"}
}