{
  "type": "Feature",
  "properties": {
    "iso:country":"US",
    "sg:address":"425 6th Ave",
    "sg:city":"Pittsburgh",
    "sg:classifiers":[
        {
            "category":"Organizations",
            "subcategory":"Professional Association",
            "type":"Services"
        }
    ],
    "sg:phone":"+1 412 261 2328",
    "sg:postcode":"15219",
    "sg:province":"PA",
    "wof:name":"Building Owners & Managers",
    "wof:placetype":"venue"
},
  "geometry": {"coordinates":[-79.99592199999999,40.440799],"type":"Point"}
}