{
  "type": "Feature",
  "properties": {
    "iso:country":"US",
    "sg:address":"910 Ruth Ave",
    "sg:city":"Erie",
    "sg:classifiers":[
        {
            "category":"Shopping",
            "subcategory":"Clothing, Apparel, & Fashions",
            "type":"Retail Goods"
        }
    ],
    "sg:phone":"+1   ",
    "sg:postcode":"16509",
    "sg:province":"PA",
    "wof:name":"Simply Bridal",
    "wof:placetype":"venue"
},
  "geometry": {"coordinates":[-80.07457700000001,42.076264],"type":"Point"}
}