{
  "type": "Feature",
  "properties": {
    "iso:country":"US",
    "sg:address":"2552 State Rd",
    "sg:city":"Bensalem",
    "sg:classifiers":[
        {
            "category":"Shopping",
            "subcategory":"Beauty & Cosmetics",
            "type":"Retail Goods"
        }
    ],
    "sg:phone":"+1   ",
    "sg:postcode":"19020",
    "sg:province":"PA",
    "sg:tags":[
        "merchandise"
    ],
    "wof:name":"Why & G LLC",
    "wof:placetype":"venue"
},
  "geometry": {"coordinates":[-74.934557,40.073468],"type":"Point"}
}