{
  "type": "Feature",
  "properties": {
    "iso:country":"US",
    "sg:address":"237 Mars Valencia Rd",
    "sg:city":"Mars",
    "sg:classifiers":[
        {
            "category":"Ice Cream",
            "type":"Food & Drink"
        }
    ],
    "sg:phone":"+1 724 625 9533",
    "sg:postcode":"16046",
    "sg:province":"PA",
    "sg:tags":[
        "frozen",
        "yogurt"
    ],
    "wof:name":"Kennedy's Twist & Shake",
    "wof:placetype":"venue"
},
  "geometry": {"coordinates":[-80.00749999999999,40.692299],"type":"Point"}
}