{
  "type": "Feature",
  "properties": {
    "addr:full":"1029 N Washington St Wilkes Barre PA 18705",
    "addr:housenumber":"1029",
    "addr:postcode":"18705",
    "addr:street":"N Washington St",
    "iso:country":"US",
    "sg:address":"1029 N Washington St",
    "sg:city":"Wilkes Barre",
    "sg:classifiers":[
        {
            "category":"Insurance",
            "subcategory":"Insurance Agent",
            "type":"Services"
        }
    ],
    "sg:phone":"+1 570 823 2500",
    "sg:postcode":"18705",
    "sg:province":"PA",
    "wof:name":"State Farm Insurance",
    "wof:placetype":"venue"
},
  "geometry": {"coordinates":[-75.85289299999999,41.260386],"type":"Point"}
}