{
  "type": "Feature",
  "properties": {
    "addr:full":"30 Public Ave Montrose PA 18801",
    "addr:housenumber":"30",
    "addr:postcode":"18801",
    "addr:street":"Public Ave",
    "iso:country":"US",
    "sg:address":"30 Public Ave",
    "sg:city":"Montrose",
    "sg:classifiers":[
        {
            "category":"Shopping",
            "type":"Retail Goods"
        }
    ],
    "sg:phone":"+1   ",
    "sg:postcode":"18801",
    "sg:province":"PA",
    "sg:tags":[
        "merchandise"
    ],
    "wof:name":"Bird Shoppe",
    "wof:placetype":"venue"
},
  "geometry": {"coordinates":[-75.877543,41.833595],"type":"Point"}
}