{
  "type": "Feature",
  "properties": {
    "addr:full":"13851 Old Rte 19 Waterford PA 16441",
    "addr:housenumber":"13851",
    "addr:postcode":"16441",
    "addr:street":"Old Rte 19",
    "iso:country":"US",
    "sg:address":"13851 Old Rte 19",
    "sg:city":"Waterford",
    "sg:classifiers":[
        {
            "category":"Building & Trades",
            "subcategory":"Construction",
            "type":"Services"
        }
    ],
    "sg:phone":"+1 814 796 4693",
    "sg:postcode":"16441",
    "sg:province":"PA",
    "sg:tags":[
        "boring",
        "drilling",
        "contractor"
    ],
    "sg:website":"www.rrdrill.com",
    "wof:name":"R Rindfuss Well Drilling",
    "wof:placetype":"venue"
},
  "geometry": {"coordinates":[-80.01310100000001,41.866327],"type":"Point"}
}