{
  "type": "Feature",
  "properties": {
    "iso:country":"US",
    "sg:address":"8895 Norwin Ave",
    "sg:city":"Irwin",
    "sg:classifiers":[
        {
            "category":"Social Services",
            "subcategory":"Child Care",
            "type":"Services"
        }
    ],
    "sg:phone":"+1   ",
    "sg:postcode":"15642",
    "sg:province":"PA",
    "sg:tags":[
        "day"
    ],
    "wof:name":"North Huntington Kindercare",
    "wof:placetype":"venue"
},
  "geometry": {"coordinates":[-79.693212,40.317895],"type":"Point"}
}