{
  "type": "Feature",
  "properties": {
    "addr:full":"12111 Eureka Rd Edinboro PA 16412",
    "addr:housenumber":"12111",
    "addr:postcode":"16412",
    "addr:street":"Eureka Rd",
    "iso:country":"US",
    "sg:address":"12111 Eureka Rd",
    "sg:city":"Edinboro",
    "sg:classifiers":[
        {
            "category":"Building & Trades",
            "subcategory":"Cleaning & Sanitation",
            "type":"Services"
        }
    ],
    "sg:phone":"+1 814 734 7354",
    "sg:postcode":"16412",
    "sg:province":"PA",
    "sg:tags":[
        "fireplace",
        "chimney"
    ],
    "wof:name":"Goss Brothers Chimney Svc",
    "wof:placetype":"venue"
},
  "geometry": {"coordinates":[-80.20624100000001,41.86991],"type":"Point"}
}