{
  "type": "Feature",
  "properties": {
    "iso:country":"US",
    "sg:address":"RR 1",
    "sg:city":"Dawson",
    "sg:classifiers":[
        {
            "category":"Health Services",
            "subcategory":"Doctor",
            "type":"Services"
        }
    ],
    "sg:phone":"+1 724 529 2645",
    "sg:postcode":"15428",
    "sg:province":"PA",
    "wof:name":"Rumbaugh Ronald C Dr",
    "wof:placetype":"venue"
},
  "geometry": {"coordinates":[-79.685997,40.083302],"type":"Point"}
}