{
  "type": "Feature",
  "properties": {
    "iso:country":"US",
    "sg:address":"61 Marchwood Rd",
    "sg:city":"Exton",
    "sg:classifiers":[
        {
            "category":"Banks & Credit Unions",
            "subcategory":"Bank",
            "type":"Services"
        }
    ],
    "sg:phone":"+1   ",
    "sg:postcode":"19341",
    "sg:province":"PA",
    "sg:tags":[
        "mortgage"
    ],
    "wof:name":"Real Estate Lenders",
    "wof:placetype":"venue"
},
  "geometry": {"coordinates":[-75.63892800000001,40.048097],"type":"Point"}
}