{
  "type": "Feature",
  "properties": {
    "iso:country":"US",
    "sg:address":"1116 N 3rd St",
    "sg:city":"Harrisburg",
    "sg:classifiers":[
        {
            "category":"Professional",
            "type":"Services"
        },
        {
            "category":"Building & Trades",
            "subcategory":"Construction",
            "type":"Services"
        }
    ],
    "sg:phone":"+1 717 232 9592",
    "sg:postcode":"17102",
    "sg:province":"PA",
    "sg:tags":[
        "art",
        "for",
        "artist",
        "restoration",
        "provides",
        "painter"
    ],
    "wof:name":"Albert Michaels Conservations",
    "wof:placetype":"venue"
},
  "geometry": {"coordinates":[-76.888166,40.268469],"type":"Point"}
}