{
  "type": "Feature",
  "properties": {
    "iso:country":"US",
    "sg:address":"901 Main St",
    "sg:city":"Darby",
    "sg:classifiers":[
        {
            "category":"Banks & Credit Unions",
            "subcategory":"Bank",
            "type":"Services"
        }
    ],
    "sg:phone":"+1 610 586 6190",
    "sg:postcode":"19023",
    "sg:province":"PA",
    "wof:name":"Sharon Savings Bank",
    "wof:placetype":"venue"
},
  "geometry": {"coordinates":[-75.262559,39.918901],"type":"Point"}
}