{
  "type": "Feature",
  "properties": {
    "iso:country":"US",
    "sg:address":"28 S Queen St",
    "sg:city":"Littlestown",
    "sg:classifiers":[
        {
            "category":"Shopping",
            "subcategory":"Used Merchandise",
            "type":"Retail Goods"
        }
    ],
    "sg:phone":"+1 717 359 0902",
    "sg:postcode":"17340",
    "sg:province":"PA",
    "sg:tags":[
        "antique"
    ],
    "wof:name":"Rosch's Antiques & Upholstery",
    "wof:placetype":"venue"
},
  "geometry": {"coordinates":[-77.087673,39.744006],"type":"Point"}
}