{
  "type": "Feature",
  "properties": {
    "iso:country":"US",
    "sg:address":"962 N Broad St Exd",
    "sg:city":"Grove City",
    "sg:classifiers":[
        {
            "category":"Professional",
            "subcategory":"Management & Consulting",
            "type":"Services"
        }
    ],
    "sg:phone":"+1 724 458 7319",
    "sg:postcode":"16127",
    "sg:province":"PA",
    "sg:tags":[
        "business"
    ],
    "wof:name":"Danielson Heating & Cooling",
    "wof:placetype":"venue"
},
  "geometry": {"coordinates":[-80.081672,41.191462],"type":"Point"}
}