{
  "type": "Feature",
  "properties": {
    "iso:country":"US",
    "sg:address":"520 Center Hill Rd",
    "sg:city":"Pittsburgh",
    "sg:phone":"+1   ",
    "sg:postcode":"15239",
    "sg:province":"PA",
    "sg:tags":[
        "equipment",
        "commercial"
    ],
    "wof:name":"Conti Bar & Restaurant Sups",
    "wof:placetype":"venue"
},
  "geometry": {"coordinates":[-79.751623,40.477671],"type":"Point"}
}