{
  "type": "Feature",
  "properties": {
    "iso:country":"US",
    "sg:address":"3600 N 20th St",
    "sg:city":"Philadelphia",
    "sg:classifiers":[
        {
            "category":"Retail",
            "subcategory":"Self-service Laundry",
            "type":"Services"
        }
    ],
    "sg:phone":"+1 215 225 8720",
    "sg:postcode":"19140",
    "sg:province":"PA",
    "wof:name":"U Do It Laundry",
    "wof:placetype":"venue"
},
  "geometry": {"coordinates":[-75.16093499999999,40.009632],"type":"Point"}
}