{
  "type": "Feature",
  "properties": {
    "iso:country":"US",
    "sg:address":"504 E Market St",
    "sg:city":"Scranton",
    "sg:classifiers":[
        {
            "category":"Personal",
            "subcategory":"Barber",
            "type":"Services"
        }
    ],
    "sg:phone":"+1 570 342 1433",
    "sg:postcode":"18509",
    "sg:province":"PA",
    "wof:name":"Ferraro's Hair Styling",
    "wof:placetype":"venue"
},
  "geometry": {"coordinates":[-75.649894,41.433913],"type":"Point"}
}