{
  "type": "Feature",
  "properties": {
    "iso:country":"US",
    "sg:address":"588 Hopewell Rd",
    "sg:city":"White",
    "sg:classifiers":[
        {
            "category":"Building & Trades",
            "subcategory":"Plumbing",
            "type":"Services"
        }
    ],
    "sg:phone":"+1   ",
    "sg:postcode":"15490",
    "sg:province":"PA",
    "sg:tags":[
        "contractor"
    ],
    "wof:name":"Dipaola Quality Climate Contro",
    "wof:placetype":"venue"
},
  "geometry": {"coordinates":[-79.4016,40.047309],"type":"Point"}
}