{
  "type": "Feature",
  "properties": {
    "iso:country":"US",
    "sg:address":"1314 Western Ave",
    "sg:city":"Pittsburgh",
    "sg:classifiers":[
        {
            "category":"Wholesale",
            "subcategory":"Chemicals & Plastics",
            "type":"Manufacturing & Wholesale Goods"
        }
    ],
    "sg:phone":"+1 412 231 0333",
    "sg:postcode":"15233",
    "sg:province":"PA",
    "sg:tags":[
        "absorbent"
    ],
    "wof:name":"Universal Emergency Relief Inc",
    "wof:placetype":"venue"
},
  "geometry": {"coordinates":[-80.023909,40.450664],"type":"Point"}
}