{
  "type": "Feature",
  "properties": {
    "iso:country":"US",
    "sg:address":"4938 Silo Hill Rd",
    "sg:city":"Doylestown",
    "sg:classifiers":[
        {
            "category":"Shopping",
            "subcategory":"Party Supplies",
            "type":"Retail Goods"
        }
    ],
    "sg:phone":"+1 215 348 1620",
    "sg:postcode":"18902",
    "sg:province":"PA",
    "sg:website":"www.goodtimesrental.com",
    "wof:name":"Good Times Rental",
    "wof:placetype":"venue"
},
  "geometry": {"coordinates":[-75.13762199999999,40.354339],"type":"Point"}
}