{
  "type": "Feature",
  "properties": {
    "iso:country":"US",
    "sg:address":"1323 Kepler Rd",
    "sg:city":"Pottstown",
    "sg:classifiers":[
        {
            "category":"Building & Trades",
            "subcategory":"Construction",
            "type":"Services"
        }
    ],
    "sg:phone":"+1 610 689 3811",
    "sg:postcode":"19464",
    "sg:province":"PA",
    "sg:tags":[
        "barn"
    ],
    "wof:name":"Red Barn Studio Inc",
    "wof:placetype":"venue"
},
  "geometry": {"coordinates":[-75.59669100000001,40.261215],"type":"Point"}
}