{
  "type": "Feature",
  "properties": {
    "addr:full":"5119 Penton Rd Pittsburgh PA 15213",
    "addr:housenumber":"5119",
    "addr:postcode":"15213",
    "addr:street":"Penton Rd",
    "iso:country":"US",
    "sg:address":"5119 Penton Rd",
    "sg:city":"Pittsburgh",
    "sg:classifiers":[
        {
            "category":"Professional",
            "subcategory":"Management & Consulting",
            "type":"Services"
        }
    ],
    "sg:phone":"+1 412 683 2475",
    "sg:postcode":"15213",
    "sg:province":"PA",
    "sg:tags":[
        "consultant",
        "business"
    ],
    "wof:name":"Davis & Davis",
    "wof:placetype":"venue"
},
  "geometry": {"coordinates":[-79.939188,40.44485],"type":"Point"}
}