{
  "type": "Feature",
  "properties": {
    "iso:country":"US",
    "sg:address":"9 Quince Rd",
    "sg:city":"Clymer",
    "sg:classifiers":[
        {
            "category":"Freight",
            "type":"Transportation"
        }
    ],
    "sg:phone":"+1   ",
    "sg:postcode":"15728",
    "sg:province":"PA",
    "sg:tags":[
        "operator",
        "local",
        "trucking"
    ],
    "wof:name":"B J & J Land Services",
    "wof:placetype":"venue"
},
  "geometry": {"coordinates":[-79.005982,40.703431],"type":"Point"}
}