{
  "type": "Feature",
  "properties": {
    "iso:country":"US",
    "sg:address":"4676 Broadway",
    "sg:city":"Allentown",
    "sg:classifiers":[
        {
            "category":"Building & Trades",
            "subcategory":"Construction",
            "type":"Services"
        }
    ],
    "sg:phone":"+1   ",
    "sg:postcode":"18104",
    "sg:province":"PA",
    "sg:tags":[
        "home",
        "general",
        "contractor"
    ],
    "wof:name":"Newton Willow Cstm Built Homes",
    "wof:placetype":"venue"
},
  "geometry": {"coordinates":[-75.558689,40.588413],"type":"Point"}
}