{
  "type": "Feature",
  "properties": {
    "addr:full":"101 Big Knob Rd Rochester PA 15074",
    "addr:housenumber":"101",
    "addr:postcode":"15074",
    "addr:street":"Big Knob Rd",
    "iso:country":"US",
    "sg:address":"101 Big Knob Rd",
    "sg:city":"Rochester",
    "sg:classifiers":[
        {
            "category":"Organizations",
            "subcategory":"Religious Organization",
            "type":"Services"
        }
    ],
    "sg:phone":"+1   ",
    "sg:postcode":"15074",
    "sg:province":"PA",
    "sg:tags":[
        "church"
    ],
    "wof:name":"New Swckley Untd Presbt Church",
    "wof:placetype":"venue"
},
  "geometry": {"coordinates":[-80.238617,40.72948],"type":"Point"}
}