{
  "type": "Feature",
  "properties": {
    "iso:country":"US",
    "sg:address":"2655 Philmont Ave",
    "sg:city":"Huntingdon Vly",
    "sg:classifiers":[
        {
            "category":"Professional",
            "subcategory":"Accounting & Tax Preparation",
            "type":"Services"
        }
    ],
    "sg:phone":"+1 215 938 6161",
    "sg:postcode":"19006",
    "sg:province":"PA",
    "sg:tags":[
        "accountant"
    ],
    "wof:name":"Raggi & Weinstein CPA",
    "wof:placetype":"venue"
},
  "geometry": {"coordinates":[-75.04406899999999,40.123142],"type":"Point"}
}