{
  "type": "Feature",
  "properties": {
    "addr:full":"191 Beaver Dr Du Bois PA 15801",
    "addr:housenumber":"191",
    "addr:postcode":"15801",
    "addr:street":"Beaver Dr Du Bois",
    "iso:country":"US",
    "sg:address":"191 Beaver Dr",
    "sg:city":"Du Bois",
    "sg:classifiers":[
        {
            "category":"Professional",
            "type":"Services"
        }
    ],
    "sg:phone":"+1   ",
    "sg:postcode":"15801",
    "sg:province":"PA",
    "wof:name":"Timberland Fcu",
    "wof:placetype":"venue"
},
  "geometry": {"coordinates":[-78.75152300000001,41.123311],"type":"Point"}
}