{
  "type": "Feature",
  "properties": {
    "iso:country":"US",
    "sg:address":"2632 Ridge Ave",
    "sg:city":"Philadelphia",
    "sg:classifiers":[
        {
            "category":"Food & Beverages",
            "subcategory":"Groceries & Convenience Stores",
            "type":"Retail Goods"
        }
    ],
    "sg:phone":"+1 215 763 7747",
    "sg:postcode":"19121",
    "sg:province":"PA",
    "wof:name":"Ridge Food Market",
    "wof:placetype":"venue"
},
  "geometry": {"coordinates":[-75.177803,39.984699],"type":"Point"}
}