{
  "type": "Feature",
  "properties": {
    "addr:full":"1420 Walnut St Ste 1500 Philadelphia PA 19102",
    "addr:housenumber":"1420",
    "addr:postcode":"19102",
    "addr:street":"Walnut St Ste 1500",
    "iso:country":"US",
    "sg:address":"1420 Walnut St Ste 1500",
    "sg:city":"Philadelphia",
    "sg:classifiers":[
        {
            "category":"Professional",
            "subcategory":"Lawyer & Legal Services",
            "type":"Services"
        }
    ],
    "sg:phone":"+1 215 790 0404",
    "sg:postcode":"19102",
    "sg:province":"PA",
    "sg:tags":[
        "personal",
        "injury"
    ],
    "wof:name":"Skale Stephen H Atty",
    "wof:placetype":"venue"
},
  "geometry": {"coordinates":[-75.164597,39.949402],"type":"Point"}
}