{
  "type": "Feature",
  "properties": {
    "addr:full":"4053 Lancaster Ave Philadelphia PA 19104",
    "addr:housenumber":"4053",
    "addr:postcode":"19104",
    "addr:street":"Lancaster Ave",
    "iso:country":"US",
    "sg:address":"4053 Lancaster Ave",
    "sg:city":"Philadelphia",
    "sg:classifiers":[
        {
            "category":"Shopping",
            "subcategory":"Used Merchandise",
            "type":"Retail Goods"
        }
    ],
    "sg:phone":"+1   ",
    "sg:postcode":"19104",
    "sg:province":"PA",
    "sg:tags":[
        "broker",
        "pawn",
        "general"
    ],
    "wof:name":"Leonards",
    "wof:placetype":"venue"
},
  "geometry": {"coordinates":[-75.20362900000001,39.963991],"type":"Point"}
}