{
  "type": "Feature",
  "properties": {
    "addr:full":"1500 W Chestnut St Washington PA 15301",
    "addr:housenumber":"1500",
    "addr:postcode":"15301",
    "addr:street":"W Chestnut St",
    "iso:country":"US",
    "sg:address":"1500 W Chestnut St",
    "sg:city":"Washington",
    "sg:classifiers":[
        {
            "category":"Utilities",
            "subcategory":"Mobile Phone",
            "type":"Services"
        }
    ],
    "sg:phone":"+1 724 228 5933",
    "sg:postcode":"15301",
    "sg:province":"PA",
    "sg:tags":[
        "telephone",
        "cellular"
    ],
    "sg:website":"www.verizonwireless.com",
    "wof:name":"Verizon Wireless",
    "wof:placetype":"venue"
},
  "geometry": {"coordinates":[-80.27434599999999,40.16448],"type":"Point"}
}