{
  "type": "Feature",
  "properties": {
    "iso:country":"US",
    "sg:address":"34 E Main St",
    "sg:city":"Bloomsburg",
    "sg:classifiers":[
        {
            "category":"Cinema",
            "subcategory":"Movie Rental",
            "type":"Entertainment"
        }
    ],
    "sg:phone":"+1 570 387 8111",
    "sg:postcode":"17815",
    "sg:province":"PA",
    "sg:tags":[
        "leasing",
        "video",
        "disc",
        "tape"
    ],
    "wof:name":"Video Gallery",
    "wof:placetype":"venue"
},
  "geometry": {"coordinates":[-76.455123,41.003698],"type":"Point"}
}