{
  "type": "Feature",
  "properties": {
    "addr:full":"40 2nd St Slatington PA 18080",
    "addr:housenumber":"40",
    "addr:postcode":"18080",
    "addr:street":"2Nd St",
    "iso:country":"US",
    "sg:address":"40 2nd St",
    "sg:city":"Slatington",
    "sg:classifiers":[
        {
            "category":"Organizations",
            "subcategory":"Religious Organization",
            "type":"Services"
        }
    ],
    "sg:phone":"+1 610 767 6361",
    "sg:postcode":"18080",
    "sg:province":"PA",
    "sg:tags":[
        "church"
    ],
    "wof:name":"St John's Lutheran Church",
    "wof:placetype":"venue"
},
  "geometry": {"coordinates":[-75.611659,40.751383],"type":"Point"}
}