{
  "type": "Feature",
  "properties": {
    "iso:country":"US",
    "sg:address":"83 W Central Ave",
    "sg:city":"Paoli",
    "sg:classifiers":[
        {
            "category":"Building & Trades",
            "subcategory":"Construction",
            "type":"Services"
        }
    ],
    "sg:phone":"+1 610 296 5603",
    "sg:postcode":"19301",
    "sg:province":"PA",
    "sg:tags":[
        "contractor",
        "carpenter",
        "carpentry"
    ],
    "wof:name":"Steven Kraegel",
    "wof:placetype":"venue"
},
  "geometry": {"coordinates":[-75.48973100000001,40.044708],"type":"Point"}
}