{
  "type": "Feature",
  "properties": {
    "iso:country":"US",
    "sg:address":"500 E Providence Rd",
    "sg:city":"Aldan",
    "sg:classifiers":[
        {
            "category":"Restaurant",
            "type":"Food & Drink"
        }
    ],
    "sg:phone":"+1 610 259 8161",
    "sg:postcode":"19018",
    "sg:province":"PA",
    "wof:name":"New Xing",
    "wof:placetype":"venue"
},
  "geometry": {"coordinates":[-75.280079,39.925542],"type":"Point"}
}