{
  "type": "Feature",
  "properties": {
    "iso:country":"US",
    "sg:address":"129 Overbrook Rd",
    "sg:city":"Valencia",
    "sg:classifiers":[
        {
            "category":"Wholesale",
            "subcategory":"Machinery & Supplies",
            "type":"Manufacturing & Wholesale Goods"
        }
    ],
    "sg:phone":"+1   ",
    "sg:postcode":"16059",
    "sg:province":"PA",
    "sg:tags":[
        "equipment",
        "industrial"
    ],
    "wof:name":"Automated Equipment & Engrg",
    "wof:placetype":"venue"
},
  "geometry": {"coordinates":[-79.92983099999999,40.703371],"type":"Point"}
}