{
  "type": "Feature",
  "properties": {
    "iso:country":"US",
    "sg:address":"332 Joy Ln",
    "sg:city":"West Chester",
    "sg:classifiers":[
        {
            "category":"Social Services",
            "type":"Services"
        }
    ],
    "sg:phone":"+1 610 429 9551",
    "sg:postcode":"19380",
    "sg:province":"PA",
    "sg:tags":[
        "counseling"
    ],
    "wof:name":"David D Dickey Min",
    "wof:placetype":"venue"
},
  "geometry": {"coordinates":[-75.565162,39.974581],"type":"Point"}
}