{
  "type": "Feature",
  "properties": {
    "iso:country":"US",
    "sg:address":"432 Rte 66",
    "sg:city":"Apollo",
    "sg:classifiers":[
        {
            "category":"Restaurant",
            "type":"Food & Drink"
        }
    ],
    "sg:phone":"+1 724 727 9651",
    "sg:postcode":"15613",
    "sg:province":"PA",
    "wof:name":"Gail's Cafe",
    "wof:placetype":"venue"
},
  "geometry": {"coordinates":[-79.58901400000001,40.550946],"type":"Point"}
}