{
  "type": "Feature",
  "properties": {
    "addr:full":"637 Glenwood Way Butler PA 16001",
    "addr:housenumber":"637",
    "addr:postcode":"16001",
    "addr:street":"Glenwood Way",
    "iso:country":"US",
    "sg:address":"637 Glenwood Way",
    "sg:city":"Butler",
    "sg:classifiers":[
        {
            "category":"Utilities",
            "subcategory":"Fuel Oil & Lpg",
            "type":"Services"
        }
    ],
    "sg:phone":"+1 724 285 3170",
    "sg:postcode":"16001",
    "sg:province":"PA",
    "sg:tags":[
        "liquefied",
        "gas",
        "petroleum"
    ],
    "wof:name":"Route 38 Bottled Gas Service",
    "wof:placetype":"venue"
},
  "geometry": {"coordinates":[-79.893575,40.901498],"type":"Point"}
}