{
  "type": "Feature",
  "properties": {
    "iso:country":"US",
    "sg:address":"745 Shady Ln",
    "sg:city":"Pittsburgh",
    "sg:classifiers":[
        {
            "category":"Professional",
            "subcategory":"Lawyer & Legal Services",
            "type":"Services"
        }
    ],
    "sg:phone":"+1 412 343 7198",
    "sg:postcode":"15228",
    "sg:province":"PA",
    "wof:name":"Deluca Wayne V Atty",
    "wof:placetype":"venue"
},
  "geometry": {"coordinates":[-80.02950300000001,40.372398],"type":"Point"}
}