{
  "type": "Feature",
  "properties": {
    "addr:full":"322 S West St Carlisle PA 17013",
    "addr:housenumber":"322",
    "addr:postcode":"west;17013",
    "addr:street":"S;St",
    "iso:country":"US",
    "sg:address":"322 S West St",
    "sg:city":"Carlisle",
    "sg:classifiers":[
        {
            "category":"Government",
            "subcategory":"Office",
            "type":"Public Place"
        }
    ],
    "sg:phone":"+1 717 245 0902",
    "sg:postcode":"17013",
    "sg:province":"PA",
    "sg:tags":[
        "legislative",
        "body",
        "representative",
        "taxes-consultants"
    ],
    "wof:name":"Morgan Plant & Associates",
    "wof:placetype":"venue"
},
  "geometry": {"coordinates":[-77.194602,40.196695],"type":"Point"}
}