{
  "type": "Feature",
  "properties": {
    "iso:country":"US",
    "sg:address":"2005 W Front St",
    "sg:city":"Berwick",
    "sg:classifiers":[
        {
            "category":"Autos & Motor Vehicles",
            "subcategory":"Auto Supplies",
            "type":"Retail Goods"
        }
    ],
    "sg:phone":"+1 570 759 0376",
    "sg:postcode":"18603",
    "sg:province":"PA",
    "sg:tags":[
        "tire"
    ],
    "wof:name":"Jack Williams Tire Co",
    "wof:placetype":"venue"
},
  "geometry": {"coordinates":[-76.26978699999999,41.04755],"type":"Point"}
}