{
  "type": "Feature",
  "properties": {
    "addr:full":"24 N Wolf St Manheim PA 17545",
    "addr:housenumber":"24",
    "addr:postcode":"17545",
    "addr:street":"N Wolf St",
    "iso:country":"US",
    "sg:address":"24 N Wolf St",
    "sg:city":"Manheim",
    "sg:classifiers":[
        {
            "category":"Retail",
            "subcategory":"Car Wash",
            "type":"Services"
        }
    ],
    "sg:phone":"+1 717 664 0021",
    "sg:postcode":"17545",
    "sg:province":"PA",
    "sg:tags":[
        "automobile",
        "detail",
        "clean"
    ],
    "wof:name":"One Stop Recon Shop",
    "wof:placetype":"venue"
},
  "geometry": {"coordinates":[-76.394541,40.164453],"type":"Point"}
}