{
  "type": "Feature",
  "properties": {
    "addr:full":"211 Pillow St Butler PA 16001",
    "addr:housenumber":"211",
    "addr:postcode":"16001",
    "addr:street":"Pillow St",
    "iso:country":"US",
    "sg:address":"211 Pillow St",
    "sg:city":"Butler",
    "sg:classifiers":[
        {
            "category":"Utilities",
            "subcategory":"Refuse",
            "type":"Services"
        }
    ],
    "sg:phone":"+1   ",
    "sg:postcode":"16001",
    "sg:province":"PA",
    "sg:tags":[
        "waste",
        "hazardous",
        "management",
        "consulting"
    ],
    "wof:name":"Horizon Environmental Svcs",
    "wof:placetype":"venue"
},
  "geometry": {"coordinates":[-79.90618600000001,40.860324],"type":"Point"}
}