{
  "type": "Feature",
  "properties": {
    "iso:country":"US",
    "sg:address":"4215 Washington Rd",
    "sg:city":"Canonsburg",
    "sg:classifiers":[
        {
            "category":"Real Estate",
            "subcategory":"Real Estate Agent",
            "type":"Services"
        }
    ],
    "sg:phone":"+1 412 343 5523",
    "sg:postcode":"15317",
    "sg:province":"PA",
    "wof:name":"North Boros",
    "wof:placetype":"venue"
},
  "geometry": {"coordinates":[-80.132347,40.26315],"type":"Point"}
}