{
  "type": "Feature",
  "properties": {
    "iso:country":"US",
    "sg:address":"238 S Richard St",
    "sg:city":"Bedford",
    "sg:classifiers":[
        {
            "category":"Professional",
            "subcategory":"Lawyer & Legal Services",
            "type":"Services"
        }
    ],
    "sg:phone":"+1 814 623 5347",
    "sg:postcode":"15522",
    "sg:province":"PA",
    "sg:tags":[
        "attorney"
    ],
    "wof:name":"Carol Ann Rose Law Office",
    "wof:placetype":"venue"
},
  "geometry": {"coordinates":[-78.50169699999999,40.016563],"type":"Point"}
}