{
  "type": "Feature",
  "properties": {
    "iso:country":"US",
    "sg:address":"2712 Wassergass Rd",
    "sg:city":"Hellertown",
    "sg:classifiers":[
        {
            "category":"Communications",
            "type":"Services"
        }
    ],
    "sg:phone":"+1 610 838 9696",
    "sg:postcode":"18055",
    "sg:province":"PA",
    "wof:name":"Mccarren Communications",
    "wof:placetype":"venue"
},
  "geometry": {"coordinates":[-75.27803400000001,40.583622],"type":"Point"}
}