{
  "type": "Feature",
  "properties": {
    "addr:full":"91 Circle Dr Manheim PA 17545",
    "addr:housenumber":"91",
    "addr:postcode":"17545",
    "addr:street":"Circle Dr",
    "iso:country":"US",
    "sg:address":"91 Circle Dr",
    "sg:city":"Manheim",
    "sg:classifiers":[
        {
            "category":"Travel",
            "subcategory":"Travel Agent",
            "type":"Entertainment"
        }
    ],
    "sg:phone":"+1 717 665 6462",
    "sg:postcode":"17545",
    "sg:province":"PA",
    "sg:tags":[
        "agency",
        "bureau"
    ],
    "wof:name":"Newsy Travel Inc",
    "wof:placetype":"venue"
},
  "geometry": {"coordinates":[-76.385604,40.148551],"type":"Point"}
}