{
  "type": "Feature",
  "properties": {
    "iso:country":"US",
    "sg:address":"442 W Broad St",
    "sg:city":"Hazleton",
    "sg:classifiers":[
        {
            "category":"Restaurant",
            "type":"Food & Drink"
        }
    ],
    "sg:phone":"+1 570 459 0400",
    "sg:postcode":"18201",
    "sg:province":"PA",
    "sg:tags":[
        "sandwich"
    ],
    "wof:name":"Subs & Suds Biagio's",
    "wof:placetype":"venue"
},
  "geometry": {"coordinates":[-75.980442,40.955815],"type":"Point"}
}