{
  "type": "Feature",
  "properties": {
    "addr:full":"70 Academy St Mc Sherrystown PA 17344",
    "addr:housenumber":"70",
    "addr:postcode":"17344",
    "addr:street":"Academy St",
    "iso:country":"US",
    "sg:address":"70 Academy St",
    "sg:city":"Mc Sherrystown",
    "sg:classifiers":[
        {
            "category":"Health Services",
            "subcategory":"Doctor",
            "type":"Services"
        }
    ],
    "sg:phone":"+1 717 637 4188",
    "sg:postcode":"17344",
    "sg:province":"PA",
    "sg:tags":[
        "physician",
        "medical",
        "surgeon"
    ],
    "wof:name":"Mc Sherrystown Family Practice",
    "wof:placetype":"venue"
},
  "geometry": {"coordinates":[-77.023865,39.800648],"type":"Point"}
}