{
  "type": "Feature",
  "properties": {
    "addr:full":"248 Market St Philadelphia PA 19106",
    "addr:housenumber":"248",
    "addr:postcode":"19106",
    "addr:street":"Market St",
    "iso:country":"US",
    "sg:address":"248 Market St",
    "sg:city":"Philadelphia",
    "sg:classifiers":[
        {
            "category":"Building & Trades",
            "subcategory":"Locksmith",
            "type":"Services"
        }
    ],
    "sg:phone":"+1 215 717 7863",
    "sg:postcode":"19106",
    "sg:province":"PA",
    "sg:tags":[
        "key"
    ],
    "wof:name":"24 Hour Emergency Locksmith",
    "wof:placetype":"venue"
},
  "geometry": {"coordinates":[-75.14528900000001,39.949969],"type":"Point"}
}