{
  "type": "Feature",
  "properties": {
    "iso:country":"US",
    "sg:address":"1003 W Trindle Rd",
    "sg:city":"Mechanicsburg",
    "sg:classifiers":[
        {
            "category":"Professional",
            "type":"Services"
        }
    ],
    "sg:phone":"+1   ",
    "sg:postcode":"17055",
    "sg:province":"PA",
    "wof:name":"Professional ADM Resources",
    "wof:placetype":"venue"
},
  "geometry": {"coordinates":[-77.05043499999999,40.200745],"type":"Point"}
}