{
  "type": "Feature",
  "properties": {
    "addr:full":"7242 Elmwood Ave Philadelphia PA 19142",
    "addr:housenumber":"7242",
    "addr:postcode":"19142",
    "addr:street":"Elmwood Ave",
    "iso:country":"US",
    "sg:address":"7242 Elmwood Ave",
    "sg:city":"Philadelphia",
    "sg:classifiers":[
        {
            "category":"Food & Beverages",
            "subcategory":"Groceries & Convenience Stores",
            "type":"Retail Goods"
        }
    ],
    "sg:phone":"+1 215 365 5088",
    "sg:postcode":"19142",
    "sg:province":"PA",
    "wof:name":"Sofie's",
    "wof:placetype":"venue"
},
  "geometry": {"coordinates":[-75.241636,39.914163],"type":"Point"}
}