{
  "type": "Feature",
  "properties": {
    "iso:country":"US",
    "sg:address":"5219 N Lawrence St",
    "sg:city":"Philadelphia",
    "sg:classifiers":[
        {
            "category":"Building & Trades",
            "subcategory":"Construction",
            "type":"Services"
        }
    ],
    "sg:phone":"+1 215 329 1550",
    "sg:postcode":"19120",
    "sg:province":"PA",
    "sg:tags":[
        "institutional",
        "commercial",
        "contractor"
    ],
    "wof:name":"Myers W H Construction Co",
    "wof:placetype":"venue"
},
  "geometry": {"coordinates":[-75.130798,40.030899],"type":"Point"}
}