{
  "type": "Feature",
  "properties": {
    "iso:country":"US",
    "sg:address":"438 W Sedgley Ave",
    "sg:city":"Philadelphia",
    "sg:classifiers":[
        {
            "category":"Retail",
            "subcategory":"Auto Repair",
            "type":"Services"
        }
    ],
    "sg:phone":"+1 215 423 5543",
    "sg:postcode":"19140",
    "sg:province":"PA",
    "sg:tags":[
        "repairing",
        "automobile"
    ],
    "wof:name":"Ruben's Auto Shop",
    "wof:placetype":"venue"
},
  "geometry": {"coordinates":[-75.137345,40.004628],"type":"Point"}
}