{
  "type": "Feature",
  "properties": {
    "iso:country":"US",
    "sg:address":"5930 Hamilton Blvd",
    "sg:city":"Allentown",
    "sg:classifiers":[
        {
            "category":"Professional",
            "subcategory":"Employment Agencies",
            "type":"Services"
        }
    ],
    "sg:phone":"+1 610 530 2540",
    "sg:postcode":"18106",
    "sg:province":"PA",
    "sg:tags":[
        "truck",
        "driver",
        "help",
        "supply"
    ],
    "sg:website":"www.optimumstaffing.com",
    "wof:name":"Optimum Staffing Inc",
    "wof:placetype":"venue"
},
  "geometry": {"coordinates":[-75.56719,40.560615],"type":"Point"}
}