{
  "type": "Feature",
  "properties": {
    "iso:country":"US",
    "sg:address":"1442 County Line Rd",
    "sg:city":"Huntingdon Vly",
    "sg:classifiers":[
        {
            "category":"Retail",
            "subcategory":"Auto Repair",
            "type":"Services"
        }
    ],
    "sg:phone":"+1 215 364 0606",
    "sg:postcode":"19006",
    "sg:province":"PA",
    "sg:tags":[
        "automobile",
        "inspection"
    ],
    "wof:name":"Bob's Auto Svc Ctr",
    "wof:placetype":"venue"
},
  "geometry": {"coordinates":[-75.038771,40.15215],"type":"Point"}
}