{
  "type": "Feature",
  "properties": {
    "iso:country":"US",
    "sg:address":"398 Mount Morris Rd",
    "sg:city":"Mt Morris",
    "sg:classifiers":[
        {
            "category":"Restaurant",
            "type":"Food & Drink"
        }
    ],
    "sg:phone":"+1 724 324 2254",
    "sg:postcode":"15349",
    "sg:province":"PA",
    "wof:name":"Martinsville Night Club",
    "wof:placetype":"venue"
},
  "geometry": {"coordinates":[-80.06525000000001,39.738748],"type":"Point"}
}