{
  "type": "Feature",
  "properties": {
    "iso:country":"US",
    "sg:address":"1925 Ferry St",
    "sg:city":"Easton",
    "sg:classifiers":[
        {
            "category":"Building & Trades",
            "subcategory":"Plumbing",
            "type":"Services"
        },
        {
            "category":"Home & Garden",
            "subcategory":"Building Materials",
            "type":"Retail Goods"
        },
        {
            "category":"Building & Trades",
            "subcategory":"Construction",
            "type":"Services"
        }
    ],
    "sg:phone":"+1 610 258 6307",
    "sg:postcode":"18042",
    "sg:province":"PA",
    "sg:tags":[
        "repair",
        "plumber",
        "heater",
        "bathroom",
        "contractor",
        "water",
        "improvement",
        "remodeling"
    ],
    "sg:website":"http://www.longsplumbingandremodeling.com",
    "wof:name":"Longs Plumbing & Remodeling",
    "wof:placetype":"venue"
},
  "geometry": {"coordinates":[-75.239344,40.688663],"type":"Point"}
}