{
  "type": "Feature",
  "properties": {
    "iso:country":"US",
    "sg:address":"1840 Forbes Ave",
    "sg:city":"Pittsburgh",
    "sg:classifiers":[
        {
            "category":"Wholesale",
            "subcategory":"Machinery & Supplies",
            "type":"Manufacturing & Wholesale Goods"
        }
    ],
    "sg:phone":"+1   ",
    "sg:postcode":"15219",
    "sg:province":"PA",
    "sg:tags":[
        "to",
        "industry",
        "graphic",
        "art",
        "sign"
    ],
    "wof:name":"Pioneer Supply Company NJ",
    "wof:placetype":"venue"
},
  "geometry": {"coordinates":[-79.98020099999999,40.437376],"type":"Point"}
}