{
  "type": "Feature",
  "properties": {
    "iso:country":"US",
    "sg:address":"1618 Katherine St",
    "sg:city":"New Castle",
    "sg:classifiers":[
        {
            "category":"Building & Trades",
            "subcategory":"Construction",
            "type":"Services"
        }
    ],
    "sg:phone":"+1 724 654 9844",
    "sg:postcode":"16105",
    "sg:province":"PA",
    "sg:tags":[
        "painting",
        "painter"
    ],
    "wof:name":"Fitzgeralds Painting",
    "wof:placetype":"venue"
},
  "geometry": {"coordinates":[-80.358194,41.019363],"type":"Point"}
}