{
  "type": "Feature",
  "properties": {
    "iso:country":"US",
    "sg:address":"1992 Butler Dr",
    "sg:city":"Monroeville",
    "sg:classifiers":[
        {
            "category":"Professional",
            "subcategory":"Management & Consulting",
            "type":"Services"
        }
    ],
    "sg:phone":"+1   ",
    "sg:postcode":"15146",
    "sg:province":"PA",
    "sg:tags":[
        "business"
    ],
    "wof:name":"Hamel Geotechnical Consultants",
    "wof:placetype":"venue"
},
  "geometry": {"coordinates":[-79.808893,40.414404],"type":"Point"}
}