{
  "type": "Feature",
  "properties": {
    "iso:country":"US",
    "sg:address":"304 Richview Dr",
    "sg:city":"Darlington",
    "sg:classifiers":[
        {
            "category":"Building & Trades",
            "subcategory":"Landscaping Services",
            "type":"Services"
        }
    ],
    "sg:phone":"+1   ",
    "sg:postcode":"16115",
    "sg:province":"PA",
    "wof:name":"Marks Lawn and Landscaping",
    "wof:placetype":"venue"
},
  "geometry": {"coordinates":[-80.370001,40.811284],"type":"Point"}
}