{
  "type": "Feature",
  "properties": {
    "iso:country":"US",
    "sg:address":"1319 Washington Ave",
    "sg:city":"Altoona",
    "sg:classifiers":[
        {
            "category":"Government",
            "subcategory":"Fire Station",
            "type":"Public Place"
        }
    ],
    "sg:phone":"+1 814 949 2230",
    "sg:postcode":"16601",
    "sg:province":"PA",
    "sg:tags":[
        "department"
    ],
    "wof:name":"Altoona City Fire Adm",
    "wof:placetype":"venue"
},
  "geometry": {"coordinates":[-78.408237,40.514696],"type":"Point"}
}