{
  "type": "Feature",
  "properties": {
    "iso:country":"US",
    "sg:address":"38 E Main St",
    "sg:city":"Dallastown",
    "sg:classifiers":[
        {
            "category":"Building & Trades",
            "subcategory":"Construction",
            "type":"Services"
        }
    ],
    "sg:phone":"+1   ",
    "sg:postcode":"17313",
    "sg:province":"PA",
    "sg:tags":[
        "house"
    ],
    "wof:name":"Deck Master",
    "wof:placetype":"venue"
},
  "geometry": {"coordinates":[-76.64352,39.900788],"type":"Point"}
}