{
  "type": "Feature",
  "properties": {
    "iso:country":"US",
    "sg:address":"316 W 4th Ave",
    "sg:city":"Derry",
    "sg:classifiers":[
        {
            "category":"Building & Trades",
            "subcategory":"Construction",
            "type":"Services"
        }
    ],
    "sg:phone":"+1   ",
    "sg:postcode":"15627",
    "sg:province":"PA",
    "sg:tags":[
        "contractor"
    ],
    "wof:name":"Gerthoffer Masonry",
    "wof:placetype":"venue"
},
  "geometry": {"coordinates":[-79.29993899999999,40.32938],"type":"Point"}
}