{
  "type": "Feature",
  "properties": {
    "addr:full":"5502 Litchfield St Philadelphia PA 19143",
    "addr:housenumber":"5502",
    "addr:postcode":"19143",
    "addr:street":"Litchfield St",
    "iso:country":"US",
    "sg:address":"5502 Litchfield St",
    "sg:city":"Philadelphia",
    "sg:classifiers":[
        {
            "category":"Travel",
            "subcategory":"Travel Agent",
            "type":"Entertainment"
        }
    ],
    "sg:phone":"+1 215 729 0185",
    "sg:postcode":"19143",
    "sg:province":"PA",
    "sg:tags":[
        "agency",
        "services-commercial"
    ],
    "wof:name":"Moore-Amour Travel",
    "wof:placetype":"venue"
},
  "geometry": {"coordinates":[-75.227368,39.941261],"type":"Point"}
}