{
  "type": "Feature",
  "properties": {
    "iso:country":"US",
    "sg:address":"315 E Wyoming Ave",
    "sg:city":"Philadelphia",
    "sg:classifiers":[
        {
            "category":"Retail",
            "subcategory":"Auto Repair",
            "type":"Services"
        }
    ],
    "sg:phone":"+1 215 324 0933",
    "sg:postcode":"19120",
    "sg:province":"PA",
    "sg:tags":[
        "repairing",
        "automobile"
    ],
    "wof:name":"Marco Auto Ctr",
    "wof:placetype":"venue"
},
  "geometry": {"coordinates":[-75.119586,40.021063],"type":"Point"}
}