{
  "type": "Feature",
  "properties": {
    "iso:country":"US",
    "sg:address":"2311 S Queen St",
    "sg:city":"York",
    "sg:classifiers":[
        {
            "category":"Retail",
            "subcategory":"Car Wash",
            "type":"Services"
        },
        {
            "category":"Autos & Motor Vehicles",
            "subcategory":"Automobile Sales",
            "type":"Retail Goods"
        }
    ],
    "sg:phone":"+1 717 747 5463",
    "sg:postcode":"17402",
    "sg:province":"PA",
    "sg:tags":[
        "carwash",
        "used",
        "dealer"
    ],
    "wof:name":"Queen Street Auto Center",
    "wof:placetype":"venue"
},
  "geometry": {"coordinates":[-76.685483,39.925351],"type":"Point"}
}