{
  "type": "Feature",
  "properties": {
    "iso:country":"US",
    "sg:address":"372 Allie Buck Rd",
    "sg:city":"Nanty Glo",
    "sg:classifiers":[
        {
            "category":"Building & Trades",
            "subcategory":"Construction",
            "type":"Services"
        }
    ],
    "sg:phone":"+1   ",
    "sg:postcode":"15943",
    "sg:province":"PA",
    "sg:tags":[
        "contractor"
    ],
    "wof:name":"Cambria Smless Gtters Dwnsputs",
    "wof:placetype":"venue"
},
  "geometry": {"coordinates":[-78.810653,40.491935],"type":"Point"}
}