{
  "type": "Feature",
  "properties": {
    "addr:full":"7 E King St Malvern PA 19355",
    "addr:housenumber":"7",
    "addr:postcode":"19355",
    "addr:street":"E King St",
    "iso:country":"US",
    "sg:address":"7 E King St",
    "sg:city":"Malvern",
    "sg:classifiers":[
        {
            "category":"Manufacturing",
            "subcategory":"Buildings",
            "type":"Manufacturing & Wholesale Goods"
        },
        {
            "category":"Building & Trades",
            "subcategory":"Construction",
            "type":"Services"
        },
        {
            "category":"Professional",
            "subcategory":"Computer Services",
            "type":"Services"
        }
    ],
    "sg:phone":"+1 610 644 6700",
    "sg:postcode":"19355",
    "sg:province":"PA",
    "sg:tags":[
        "information",
        "recovery",
        "builder",
        "processing",
        "system",
        "contractor",
        "equipment",
        "home",
        "data",
        "retrieval"
    ],
    "sg:website":"http://www.jschwartzconstruction.com/",
    "wof:name":"J Schwartz Constr Mgmt",
    "wof:placetype":"venue"
},
  "geometry": {"coordinates":[-75.51457000000001,40.035999],"type":"Point"}
}