{
  "type": "Feature",
  "properties": {
    "iso:country":"US",
    "sg:address":"495 Washington Ave",
    "sg:city":"Sellersville",
    "sg:classifiers":[
        {
            "category":"Home & Garden",
            "subcategory":"Garden Supply",
            "type":"Retail Goods"
        }
    ],
    "sg:phone":"+1   ",
    "sg:postcode":"18960",
    "sg:province":"PA",
    "wof:name":"Dons Top Soil",
    "wof:placetype":"venue"
},
  "geometry": {"coordinates":[-75.317482,40.363888],"type":"Point"}
}