{
  "type": "Feature",
  "properties": {
    "addr:full":"2106 Hoffnagle St Philadelphia PA 19152",
    "addr:housenumber":"2106",
    "addr:postcode":"19152",
    "addr:street":"Hoffnagle St",
    "iso:country":"US",
    "sg:address":"2106 Hoffnagle St",
    "sg:city":"Philadelphia",
    "sg:classifiers":[
        {
            "category":"Communications",
            "subcategory":"Film & Video Production",
            "type":"Services"
        }
    ],
    "sg:phone":"+1   ",
    "sg:postcode":"19152",
    "sg:province":"PA",
    "sg:tags":[
        "toy",
        "licensing",
        "merchandising"
    ],
    "wof:name":"Camera Bug The",
    "wof:placetype":"venue"
},
  "geometry": {"coordinates":[-75.04905100000001,40.063479],"type":"Point"}
}