{
  "type": "Feature",
  "properties": {
    "iso:country":"US",
    "sg:address":"111 N High St",
    "sg:city":"Selinsgrove",
    "sg:classifiers":[
        {
            "category":"Professional",
            "subcategory":"Lawyer & Legal Services",
            "type":"Services"
        }
    ],
    "sg:phone":"+1 570 374 1234",
    "sg:postcode":"17870",
    "sg:province":"PA",
    "sg:tags":[
        "attorney"
    ],
    "wof:name":"Hugh A Benson",
    "wof:placetype":"venue"
},
  "geometry": {"coordinates":[-76.862786,40.801341],"type":"Point"}
}