{
  "type": "Feature",
  "properties": {
    "iso:country":"US",
    "sg:address":"301 W New St",
    "sg:city":"Annville",
    "sg:classifiers":[
        {
            "category":"Real Estate",
            "subcategory":"Real Estate Operator",
            "type":"Services"
        }
    ],
    "sg:phone":"+1 717 867 3037",
    "sg:postcode":"17003",
    "sg:province":"PA",
    "sg:tags":[
        "apartment"
    ],
    "wof:name":"Quittapahilla Commons",
    "wof:placetype":"venue"
},
  "geometry": {"coordinates":[-76.521301,40.331501],"type":"Point"}
}