{
  "type": "Feature",
  "properties": {
    "iso:country":"US",
    "sg:address":"1321 7th Ave",
    "sg:city":"Beaver Falls",
    "sg:classifiers":[
        {
            "category":"Shopping",
            "subcategory":"Clothing, Apparel, & Fashions",
            "type":"Retail Goods"
        }
    ],
    "sg:phone":"+1   ",
    "sg:postcode":"15010",
    "sg:province":"PA",
    "sg:tags":[
        "family"
    ],
    "wof:name":"Kennections",
    "wof:placetype":"venue"
},
  "geometry": {"coordinates":[-80.319509,40.754757],"type":"Point"}
}