{
  "type": "Feature",
  "properties": {
    "addr:full":"2130 Schoenersville Rd Bethlehem PA 18018",
    "addr:housenumber":"2130",
    "addr:postcode":"18018",
    "addr:street":"Schoenersville Rd",
    "iso:country":"US",
    "sg:address":"2130 Schoenersville Rd",
    "sg:city":"Bethlehem",
    "sg:classifiers":[
        {
            "category":"Autos & Motor Vehicles",
            "subcategory":"Fuel & Gas Station",
            "type":"Retail Goods"
        }
    ],
    "sg:phone":"+1 610 807 9920",
    "sg:postcode":"18018",
    "sg:province":"PA",
    "sg:tags":[
        "convenience",
        "oil",
        "store"
    ],
    "sg:website":"http://www.mobil.com",
    "wof:name":"Schoenersville Mobil Mart",
    "wof:placetype":"venue"
},
  "geometry": {"coordinates":[-75.398499,40.639301],"type":"Point"}
}