{
  "type": "Feature",
  "properties": {
    "addr:full":"1201 Spring Garden St Philadelphia PA 19123",
    "addr:housenumber":"1201",
    "addr:postcode":"19123",
    "addr:street":"Spring Garden St",
    "iso:country":"US",
    "sg:address":"1201 Spring Garden St",
    "sg:city":"Philadelphia",
    "sg:classifiers":[
        {
            "category":"Real Estate",
            "subcategory":"Real Estate Services",
            "type":"Services"
        },
        {
            "category":"Banks & Credit Unions",
            "subcategory":"Investment Brokerage",
            "type":"Services"
        },
        {
            "category":"Banks & Credit Unions",
            "subcategory":"Bank",
            "type":"Services"
        },
        {
            "category":"Banks & Credit Unions",
            "subcategory":"Financial Services",
            "type":"Services"
        }
    ],
    "sg:phone":"+1 215 235 3900",
    "sg:postcode":"19123",
    "sg:province":"PA",
    "sg:tags":[
        "commercial",
        "loan",
        "saving"
    ],
    "sg:website":"www.citizensbank.com",
    "wof:name":"Citizens Bank",
    "wof:placetype":"venue"
},
  "geometry": {"coordinates":[-75.15799699999999,39.9618],"type":"Point"}
}