{
  "type": "Feature",
  "properties": {
    "addr:full":"414 E Lincoln Ave Mc Donald PA 15057",
    "addr:housenumber":"414",
    "addr:postcode":"15057",
    "addr:street":"E Lincoln Ave Mc",
    "iso:country":"US",
    "sg:address":"414 E Lincoln Ave",
    "sg:city":"Mc Donald",
    "sg:classifiers":[
        {
            "category":"Wholesale",
            "subcategory":"Vending Machines",
            "type":"Manufacturing & Wholesale Goods"
        }
    ],
    "sg:phone":"+1   ",
    "sg:postcode":"15057",
    "sg:province":"PA",
    "sg:tags":[
        "operator"
    ],
    "wof:name":"Astk Vending Co",
    "wof:placetype":"venue"
},
  "geometry": {"coordinates":[-80.229372,40.371235],"type":"Point"}
}