{
  "type": "Feature",
  "properties": {
    "addr:full":"3200 W Diamond St Philadelphia PA 19121",
    "addr:housenumber":"3200",
    "addr:postcode":"19121",
    "addr:street":"W Diamond St",
    "iso:country":"US",
    "sg:address":"3200 W Diamond St",
    "sg:city":"Philadelphia",
    "sg:classifiers":[
        {
            "category":"Real Estate",
            "subcategory":"Real Estate Operator",
            "type":"Services"
        }
    ],
    "sg:phone":"+1   ",
    "sg:postcode":"19121",
    "sg:province":"PA",
    "sg:tags":[
        "building",
        "apartment"
    ],
    "wof:name":"Manor Court",
    "wof:placetype":"venue"
},
  "geometry": {"coordinates":[-75.185999,39.988524],"type":"Point"}
}