{
  "type": "Feature",
  "properties": {
    "iso:country":"US",
    "sg:address":"1513 Tyson Ave",
    "sg:city":"Philadelphia",
    "sg:classifiers":[
        {
            "category":"Personal",
            "subcategory":"Beauty Salon",
            "type":"Services"
        }
    ],
    "sg:phone":"+1   ",
    "sg:postcode":"19149",
    "sg:province":"PA",
    "sg:tags":[
        "shop"
    ],
    "wof:name":"David Allen Beauty",
    "wof:placetype":"venue"
},
  "geometry": {"coordinates":[-75.06993199999999,40.04673],"type":"Point"}
}