{
  "type": "Feature",
  "properties": {
    "addr:full":"16 E Hinckley Ave Ridley Park PA 19078",
    "addr:housenumber":"16",
    "addr:postcode":"19078",
    "addr:street":"E Hinckley Ave;Park",
    "iso:country":"US",
    "sg:address":"16 E Hinckley Ave",
    "sg:city":"Ridley Park",
    "sg:classifiers":[
        {
            "category":"Professional",
            "type":"Services"
        }
    ],
    "sg:phone":"+1 610 521 0780",
    "sg:postcode":"19078",
    "sg:province":"PA",
    "wof:name":"Candy For Occasions",
    "wof:placetype":"venue"
},
  "geometry": {"coordinates":[-75.322548,39.879451],"type":"Point"}
}