{
  "type": "Feature",
  "properties": {
    "iso:country":"US",
    "sg:address":"270 Middle Creek Rd",
    "sg:city":"Gilbertsville",
    "sg:classifiers":[
        {
            "category":"Building & Trades",
            "subcategory":"Landscaping Services",
            "type":"Services"
        }
    ],
    "sg:phone":"+1 610 367 5986",
    "sg:postcode":"19525",
    "sg:province":"PA",
    "sg:tags":[
        "tree"
    ],
    "wof:name":"Brook Enterprises",
    "wof:placetype":"venue"
},
  "geometry": {"coordinates":[-75.602633,40.332933],"type":"Point"}
}