{
  "type": "Feature",
  "properties": {
    "addr:full":"601 Dunn Ave Old Forge PA 18518",
    "addr:housenumber":"601",
    "addr:postcode":"18518",
    "addr:street":"Dunn Ave",
    "iso:country":"US",
    "sg:address":"601 Dunn Ave",
    "sg:city":"Old Forge",
    "sg:classifiers":[
        {
            "category":"Organizations",
            "subcategory":"Labor Organization",
            "type":"Services"
        }
    ],
    "sg:phone":"+1   ",
    "sg:postcode":"18518",
    "sg:province":"PA",
    "wof:name":"United Autoworkers Local",
    "wof:placetype":"venue"
},
  "geometry": {"coordinates":[-75.73231699999999,41.378513],"type":"Point"}
}