{
  "type": "Feature",
  "properties": {
    "iso:country":"US",
    "sg:address":"2178 Cloverfield Dr",
    "sg:city":"Lebanon",
    "sg:classifiers":[
        {
            "category":"Government",
            "subcategory":"Fire Station",
            "type":"Public Place"
        },
        {
            "category":"Retail",
            "subcategory":"Laundry & Dry Cleaning",
            "type":"Services"
        },
        {
            "category":"Building & Trades",
            "subcategory":"Cleaning & Sanitation",
            "type":"Services"
        },
        {
            "category":"Home & Garden",
            "subcategory":"Carpets & Floor Coverings",
            "type":"Retail Goods"
        }
    ],
    "sg:phone":"+1 717 274 0860",
    "sg:postcode":"17046",
    "sg:province":"PA",
    "sg:tags":[
        "cleaner",
        "recovery",
        "rug",
        "relief",
        "janitorial",
        "disaster"
    ],
    "wof:name":"Swisher's Cleaning Co",
    "wof:placetype":"venue"
},
  "geometry": {"coordinates":[-76.461708,40.36264],"type":"Point"}
}