{
  "type": "Feature",
  "properties": {
    "iso:country":"US",
    "sg:address":"108 Dixon Dr",
    "sg:city":"Pittsburgh",
    "sg:classifiers":[
        {
            "category":"Wholesale",
            "subcategory":"Non-durable Goods",
            "type":"Manufacturing & Wholesale Goods"
        }
    ],
    "sg:phone":"+1   ",
    "sg:postcode":"15209",
    "sg:province":"PA",
    "wof:name":"Ronald P Debreczeni",
    "wof:placetype":"venue"
},
  "geometry": {"coordinates":[-79.98898699999999,40.52306],"type":"Point"}
}