{
  "type": "Feature",
  "properties": {
    "addr:full":"4068 Mount Royal Blvd Allison Park PA 15101",
    "addr:housenumber":"4068",
    "addr:postcode":"15101",
    "addr:street":"Mount Royal Blvd;Park",
    "iso:country":"US",
    "sg:address":"4068 Mount Royal Blvd",
    "sg:city":"Allison Park",
    "sg:classifiers":[
        {
            "category":"Professional",
            "subcategory":"Accounting & Tax Preparation",
            "type":"Services"
        }
    ],
    "sg:phone":"+1 412 486 1017",
    "sg:postcode":"15101",
    "sg:province":"PA",
    "sg:tags":[
        "return",
        "filing"
    ],
    "wof:name":"Estate Accounting and Tax Svcs",
    "wof:placetype":"venue"
},
  "geometry": {"coordinates":[-79.965476,40.566865],"type":"Point"}
}