{
  "type": "Feature",
  "properties": {
    "iso:country":"US",
    "sg:address":"233 Bridge St",
    "sg:city":"Jessup",
    "sg:classifiers":[
        {
            "category":"Bars & Pubs",
            "type":"Food & Drink"
        },
        {
            "category":"Coffee & Tea",
            "type":"Food & Drink"
        },
        {
            "category":"Restaurant",
            "type":"Food & Drink"
        }
    ],
    "sg:phone":"+1 570 489 2456",
    "sg:postcode":"18434",
    "sg:province":"PA",
    "sg:tags":[
        "tavern",
        "espresso",
        "pizza"
    ],
    "wof:name":"Colarusso's Cafe",
    "wof:placetype":"venue"
},
  "geometry": {"coordinates":[-75.57528499999999,41.476972],"type":"Point"}
}