{
  "type": "Feature",
  "properties": {
    "addr:full":"232 S Center St Coal Twp PA 17866",
    "addr:housenumber":"232",
    "addr:postcode":"17866",
    "addr:street":"S Center St",
    "iso:country":"US",
    "sg:address":"232 S Center St",
    "sg:city":"Coal Twp",
    "sg:classifiers":[
        {
            "category":"Retail",
            "subcategory":"Auto Repair",
            "type":"Services"
        }
    ],
    "sg:phone":"+1 570 644 1984",
    "sg:postcode":"17866",
    "sg:province":"PA",
    "sg:tags":[
        "body",
        "automobile",
        "painting"
    ],
    "wof:name":"Avellino Autobody",
    "wof:placetype":"venue"
},
  "geometry": {"coordinates":[-76.567729,40.801187],"type":"Point"}
}