{
  "type": "Feature",
  "properties": {
    "addr:full":"13 Wild Deer Dr Stevens PA 17578",
    "addr:housenumber":"13",
    "addr:postcode":"stevens;17578",
    "addr:street":"Wild Deer Dr",
    "iso:country":"US",
    "sg:address":"13 Wild Deer Dr",
    "sg:city":"Stevens",
    "sg:classifiers":[
        {
            "category":"Education",
            "subcategory":"Special Training",
            "type":"Public Place"
        }
    ],
    "sg:phone":"+1 717 336 0662",
    "sg:postcode":"17578",
    "sg:province":"PA",
    "sg:tags":[
        "instruction",
        "music"
    ],
    "wof:name":"Carolyn Englert Master-Music",
    "wof:placetype":"venue"
},
  "geometry": {"coordinates":[-76.112618,40.204542],"type":"Point"}
}