{
  "type": "Feature",
  "properties": {
    "addr:full":"111 E Church Rd King Of Prussia PA 19406",
    "addr:housenumber":"111",
    "addr:postcode":"19406",
    "addr:street":"E Church Rd",
    "iso:country":"US",
    "sg:address":"111 E Church Rd",
    "sg:city":"King Of Prussia",
    "sg:classifiers":[
        {
            "category":"Building & Trades",
            "subcategory":"Construction",
            "type":"Services"
        }
    ],
    "sg:phone":"+1 610 265 2110",
    "sg:postcode":"19406",
    "sg:province":"PA",
    "sg:tags":[
        "concrete",
        "contractor"
    ],
    "wof:name":"B Pietrini & Sons",
    "wof:placetype":"venue"
},
  "geometry": {"coordinates":[-75.354474,40.086367],"type":"Point"}
}