{
  "type": "Feature",
  "properties": {
    "iso:country":"US",
    "sg:address":"150 N Derr Dr",
    "sg:city":"Lewisburg",
    "sg:classifiers":[
        {
            "category":"Building & Trades",
            "subcategory":"Construction",
            "type":"Services"
        }
    ],
    "sg:phone":"+1 570 523 8800",
    "sg:postcode":"17837",
    "sg:province":"PA",
    "sg:tags":[
        "retaining",
        "wall"
    ],
    "wof:name":"Hillyard's Landscaping",
    "wof:placetype":"venue"
},
  "geometry": {"coordinates":[-76.892201,40.961909],"type":"Point"}
}