{
  "type": "Feature",
  "properties": {
    "iso:country":"US",
    "sg:address":"814 Diamond St",
    "sg:city":"Berlin",
    "sg:classifiers":[
        {
            "category":"Retail",
            "subcategory":"Animal Services",
            "type":"Services"
        }
    ],
    "sg:phone":"+1   ",
    "sg:postcode":"15530",
    "sg:province":"PA",
    "wof:name":"Lori L Dog Grooming",
    "wof:placetype":"venue"
},
  "geometry": {"coordinates":[-78.95586900000001,39.926635],"type":"Point"}
}