{
  "type": "Feature",
  "properties": {
    "iso:country":"US",
    "sg:address":"1839 Newport Rd",
    "sg:city":"Duncannon",
    "sg:classifiers":[
        {
            "category":"Manufacturing",
            "subcategory":"Buildings",
            "type":"Manufacturing & Wholesale Goods"
        },
        {
            "category":"Building & Trades",
            "subcategory":"Construction",
            "type":"Services"
        }
    ],
    "sg:phone":"+1 717 889 2126",
    "sg:postcode":"17020",
    "sg:province":"PA",
    "sg:tags":[
        "home",
        "builder",
        "contractor"
    ],
    "wof:name":"John D. Geiling Construction",
    "wof:placetype":"venue"
},
  "geometry": {"coordinates":[-77.10499799999999,40.441969],"type":"Point"}
}