{
  "type": "Feature",
  "properties": {
    "addr:full":"190 Hazleton Apartment West Hazleton PA 18202",
    "addr:housenumber":"190;apartment",
    "addr:postcode":"18202",
    "addr:street":"West",
    "iso:country":"US",
    "sg:address":"190 Hazleton Apartment",
    "sg:city":"West Hazleton",
    "sg:classifiers":[
        {
            "category":"Bars & Pubs",
            "type":"Food & Drink"
        }
    ],
    "sg:phone":"+1 570 501 9482",
    "sg:postcode":"18202",
    "sg:province":"PA",
    "sg:tags":[
        "lounge",
        "cocktail"
    ],
    "wof:name":"Ten Pin Lounge At Bowl Arena",
    "wof:placetype":"venue"
},
  "geometry": {"coordinates":[-75.982973,40.976112],"type":"Point"}
}