{
  "type": "Feature",
  "properties": {
    "addr:full":"494 2nd Street Pike Southampton PA 18966",
    "addr:housenumber":"494",
    "addr:postcode":"18966",
    "addr:street":"2Nd Street Pike",
    "iso:country":"US",
    "sg:address":"494 2nd Street Pike",
    "sg:city":"Southampton",
    "sg:classifiers":[
        {
            "category":"Real Estate",
            "subcategory":"Real Estate Agent",
            "type":"Services"
        }
    ],
    "sg:phone":"+1 215 396 7801",
    "sg:postcode":"18966",
    "sg:province":"PA",
    "wof:name":"Landmark Realty Co",
    "wof:placetype":"venue"
},
  "geometry": {"coordinates":[-75.045106,40.170126],"type":"Point"}
}