{
  "type": "Feature",
  "properties": {
    "iso:country":"US",
    "sg:address":"249 Hilands Ave",
    "sg:city":"Pittsburgh",
    "sg:classifiers":[
        {
            "category":"Professional",
            "subcategory":"Business Services",
            "type":"Services"
        }
    ],
    "sg:phone":"+1 412 389 7722",
    "sg:postcode":"15202",
    "sg:province":"PA",
    "wof:name":"Balloons Instead",
    "wof:placetype":"venue"
},
  "geometry": {"coordinates":[-80.087947,40.509409],"type":"Point"}
}