{
  "type": "Feature",
  "properties": {
    "addr:full":"1046 New Holland Ave Lancaster PA 17601",
    "addr:housenumber":"1046",
    "addr:postcode":"17601",
    "addr:street":"New Holland Ave",
    "iso:country":"US",
    "sg:address":"1046 New Holland Ave",
    "sg:city":"Lancaster",
    "sg:classifiers":[
        {
            "category":"Manufacturing",
            "subcategory":"Metals",
            "type":"Manufacturing & Wholesale Goods"
        }
    ],
    "sg:phone":"+1   ",
    "sg:postcode":"17601",
    "sg:province":"PA",
    "sg:tags":[
        "development",
        "thermal",
        "technology",
        "product"
    ],
    "wof:name":"Advanced Cooling Technologies",
    "wof:placetype":"venue"
},
  "geometry": {"coordinates":[-76.283523,40.055968],"type":"Point"}
}