{
  "type": "Feature",
  "properties": {
    "iso:country":"US",
    "sg:address":"1809 W Oregon Ave",
    "sg:city":"Philadelphia",
    "sg:classifiers":[
        {
            "category":"Health Services",
            "subcategory":"Doctor",
            "type":"Services"
        }
    ],
    "sg:phone":"+1 215 389 3890",
    "sg:postcode":"19145",
    "sg:province":"PA",
    "wof:name":"Nestico Pasquale F MD",
    "wof:placetype":"venue"
},
  "geometry": {"coordinates":[-75.178101,39.917599],"type":"Point"}
}