{
  "type": "Feature",
  "properties": {
    "addr:full":"400 E 25th Ave Altoona PA 16601",
    "addr:housenumber":"400",
    "addr:postcode":"16601",
    "addr:street":"E 25Th Ave",
    "iso:country":"US",
    "sg:address":"400 E 25th Ave",
    "sg:city":"Altoona",
    "sg:classifiers":[
        {
            "category":"Restaurant",
            "type":"Food & Drink"
        }
    ],
    "sg:menulink":"http://www.allmenus.com/pa/altoona/71947-pizza-hut/menu/",
    "sg:phone":"+1 814 944 2229",
    "sg:postcode":"16601",
    "sg:province":"PA",
    "sg:tags":[
        "american",
        "pizza"
    ],
    "wof:name":"Pizza Hut",
    "wof:placetype":"venue"
},
  "geometry": {"coordinates":[-78.402259,40.534426],"type":"Point"}
}