{
  "type": "Feature",
  "properties": {
    "iso:country":"US",
    "sg:address":"495 Morgan Ct",
    "sg:city":"Southampton",
    "sg:classifiers":[
        {
            "category":"Manufacturing",
            "subcategory":"Tools & Machinery",
            "type":"Manufacturing & Wholesale Goods"
        }
    ],
    "sg:phone":"+1   ",
    "sg:postcode":"18966",
    "sg:province":"PA",
    "sg:tags":[
        "process",
        "control",
        "mfg",
        "e",
        "instrument"
    ],
    "wof:name":"Trutemp Sensors",
    "wof:placetype":"venue"
},
  "geometry": {"coordinates":[-74.97017,40.21218],"type":"Point"}
}