{
  "type": "Feature",
  "properties": {
    "iso:country":"US",
    "sg:address":"3044 Appledale Rd",
    "sg:city":"Norristown",
    "sg:classifiers":[
        {
            "category":"Professional",
            "subcategory":"Engineering",
            "type":"Services"
        }
    ],
    "sg:phone":"+1 610 631 5241",
    "sg:postcode":"19403",
    "sg:province":"PA",
    "sg:tags":[
        "engineer"
    ],
    "wof:name":"Snyder Environmental Engnrng",
    "wof:placetype":"venue"
},
  "geometry": {"coordinates":[-75.415122,40.148122],"type":"Point"}
}