{
  "type": "Feature",
  "properties": {
    "iso:country":"US",
    "sg:address":"201 Ross Ave",
    "sg:city":"New Cumberland",
    "sg:classifiers":[
        {
            "category":"Professional",
            "type":"Services"
        }
    ],
    "sg:phone":"+1   ",
    "sg:postcode":"17070",
    "sg:province":"PA",
    "wof:name":"Netguruz",
    "wof:placetype":"venue"
},
  "geometry": {"coordinates":[-76.85646800000001,40.223651],"type":"Point"}
}