{
  "type": "Feature",
  "properties": {
    "addr:full":"110 5th St Olyphant PA 18447",
    "addr:housenumber":"110",
    "addr:postcode":"18447",
    "addr:street":"5Th St",
    "iso:country":"US",
    "sg:address":"110 5th St",
    "sg:city":"Olyphant",
    "sg:classifiers":[
        {
            "category":"Utilities",
            "subcategory":"Refuse",
            "type":"Services"
        }
    ],
    "sg:phone":"+1   ",
    "sg:postcode":"18447",
    "sg:province":"PA",
    "sg:tags":[
        "system"
    ],
    "wof:name":"Advanced Waste Services",
    "wof:placetype":"venue"
},
  "geometry": {"coordinates":[-75.61067199999999,41.476977],"type":"Point"}
}