{
  "type": "Feature",
  "properties": {
    "addr:full":"6045 State Rte 655 Belleville PA 17004",
    "addr:housenumber":"6045",
    "addr:postcode":"17004",
    "addr:street":"State Rte 655",
    "iso:country":"US",
    "sg:address":"6045 State Rte 655",
    "sg:city":"Belleville",
    "sg:classifiers":[
        {
            "category":"Restaurant",
            "type":"Food & Drink"
        }
    ],
    "sg:phone":"+1 717 667 9191",
    "sg:postcode":"17004",
    "sg:province":"PA",
    "sg:tags":[
        "eating"
    ],
    "wof:name":"Sal-Lee's Dream",
    "wof:placetype":"venue"
},
  "geometry": {"coordinates":[-77.662307,40.637775],"type":"Point"}
}