{
  "type": "Feature",
  "properties": {
    "iso:country":"US",
    "sg:address":"1 E Main St",
    "sg:city":"Camp Hill",
    "sg:classifiers":[
        {
            "category":"Professional",
            "subcategory":"Lawyer & Legal Services",
            "type":"Services"
        }
    ],
    "sg:phone":"+1 717 737 8761",
    "sg:postcode":"17011",
    "sg:province":"PA",
    "wof:name":"Hipp Jennifer B Atty",
    "wof:placetype":"venue"
},
  "geometry": {"coordinates":[-76.954903,40.223202],"type":"Point"}
}