{
  "type": "Feature",
  "properties": {
    "iso:country":"US",
    "sg:address":"2686 Peach St",
    "sg:city":"Erie",
    "sg:classifiers":[
        {
            "category":"Health Services",
            "subcategory":"Nursing And Care Facility",
            "type":"Services"
        }
    ],
    "sg:phone":"+1   ",
    "sg:postcode":"16508",
    "sg:province":"PA",
    "sg:tags":[
        "skilled"
    ],
    "wof:name":"Beverly",
    "wof:placetype":"venue"
},
  "geometry": {"coordinates":[-80.076266,42.107982],"type":"Point"}
}