{
  "type": "Feature",
  "properties": {
    "iso:country":"US",
    "sg:address":"532 W Penn St",
    "sg:city":"Carlisle",
    "sg:classifiers":[
        {
            "category":"Professional",
            "subcategory":"Printing & Photocopies",
            "type":"Services"
        }
    ],
    "sg:phone":"+1 717 258 3220",
    "sg:postcode":"17013",
    "sg:province":"PA",
    "sg:tags":[
        "photographers-commercial"
    ],
    "wof:name":"Gills Positive Images",
    "wof:placetype":"venue"
},
  "geometry": {"coordinates":[-77.201136,40.206442],"type":"Point"}
}