{
  "type": "Feature",
  "properties": {
    "iso:country":"US",
    "sg:address":"25 S Main St",
    "sg:city":"Morrisville",
    "sg:classifiers":[
        {
            "category":"Restaurant",
            "type":"Food & Drink"
        }
    ],
    "sg:phone":"+1   ",
    "sg:postcode":"19067",
    "sg:province":"PA",
    "sg:tags":[
        "eating"
    ],
    "wof:name":"Vinces Pizza & Restaurant",
    "wof:placetype":"venue"
},
  "geometry": {"coordinates":[-74.83617,40.240473],"type":"Point"}
}