{
  "type": "Feature",
  "properties": {
    "addr:full":"51 Railroad St Valencia PA 16059",
    "addr:housenumber":"51",
    "addr:postcode":"16059",
    "addr:street":"Railroad St",
    "iso:country":"US",
    "sg:address":"51 Railroad St",
    "sg:city":"Valencia",
    "sg:classifiers":[
        {
            "category":"Wholesale",
            "subcategory":"Machinery & Supplies",
            "type":"Manufacturing & Wholesale Goods"
        }
    ],
    "sg:phone":"+1 724 625 1690",
    "sg:postcode":"16059",
    "sg:province":"PA",
    "sg:tags":[
        "equipment",
        "material",
        "handling"
    ],
    "wof:name":"R & C Lift",
    "wof:placetype":"venue"
},
  "geometry": {"coordinates":[-79.988885,40.67397],"type":"Point"}
}