{
  "type": "Feature",
  "properties": {
    "addr:full":"399 Carver Dr Bethlehem PA 18017",
    "addr:housenumber":"399",
    "addr:postcode":"18017",
    "addr:street":"Carver Dr",
    "iso:country":"US",
    "sg:address":"399 Carver Dr",
    "sg:city":"Bethlehem",
    "sg:classifiers":[
        {
            "category":"Banks & Credit Unions",
            "subcategory":"Investment Brokerage",
            "type":"Services"
        }
    ],
    "sg:phone":"+1   ",
    "sg:postcode":"18017",
    "sg:province":"PA",
    "sg:tags":[
        "advisory"
    ],
    "wof:name":"Carver Capital Management",
    "wof:placetype":"venue"
},
  "geometry": {"coordinates":[-75.36662,40.639623],"type":"Point"}
}