{
  "type": "Feature",
  "properties": {
    "iso:country":"US",
    "sg:address":"116 S State St",
    "sg:city":"Clarks Summit",
    "sg:classifiers":[
        {
            "category":"Insurance",
            "subcategory":"Insurance Agent",
            "type":"Services"
        }
    ],
    "sg:phone":"+1 570 585 0200",
    "sg:postcode":"18411",
    "sg:province":"PA",
    "wof:name":"Tri County General Insurance",
    "wof:placetype":"venue"
},
  "geometry": {"coordinates":[-75.704449,41.494803],"type":"Point"}
}