{
  "type": "Feature",
  "properties": {
    "iso:country":"US",
    "sg:address":"4921 Clairton Blvd",
    "sg:city":"Pittsburgh",
    "sg:classifiers":[
        {
            "category":"Home & Garden",
            "subcategory":"Furniture",
            "type":"Retail Goods"
        }
    ],
    "sg:phone":"+1 412 885 1600",
    "sg:postcode":"15236",
    "sg:province":"PA",
    "wof:name":"Colonial Gallery Inc",
    "wof:placetype":"venue"
},
  "geometry": {"coordinates":[-79.97649199999999,40.350187],"type":"Point"}
}