{
  "type": "Feature",
  "properties": {
    "iso:country":"US",
    "sg:address":"15 Central Ave",
    "sg:city":"York",
    "sg:classifiers":[
        {
            "category":"Building & Trades",
            "subcategory":"Construction",
            "type":"Services"
        }
    ],
    "sg:phone":"+1 717 848 3227",
    "sg:postcode":"17406",
    "sg:province":"PA",
    "sg:tags":[
        "home",
        "builder"
    ],
    "sg:website":"www.hauberthomes.com",
    "wof:name":"Haubert Homes",
    "wof:placetype":"venue"
},
  "geometry": {"coordinates":[-76.753646,40.034354],"type":"Point"}
}