{
  "type": "Feature",
  "properties": {
    "iso:country":"US",
    "sg:address":"3951 Haverford Ave",
    "sg:city":"Philadelphia",
    "sg:classifiers":[
        {
            "category":"Place Of Worship",
            "subcategory":"Church",
            "type":"Public Place"
        },
        {
            "category":"Place Of Worship",
            "type":"Public Place"
        }
    ],
    "sg:phone":"+1 215 222 6280",
    "sg:postcode":"19104",
    "sg:province":"PA",
    "sg:tags":[
        "testament",
        "churches-church",
        "christ",
        "christ-new"
    ],
    "wof:name":"Community Bible Inc",
    "wof:placetype":"venue"
},
  "geometry": {"coordinates":[-75.20144000000001,39.962972],"type":"Point"}
}