{
  "type": "Feature",
  "properties": {
    "iso:country":"US",
    "sg:address":"1124 S Braddock Ave",
    "sg:city":"Pittsburgh",
    "sg:classifiers":[
        {
            "category":"Retail",
            "subcategory":"Animal Services",
            "type":"Services"
        }
    ],
    "sg:phone":"+1 412 371 7297",
    "sg:postcode":"15218",
    "sg:province":"PA",
    "sg:tags":[
        "pet",
        "grooming",
        "washing"
    ],
    "wof:name":"Paws Itively Pets",
    "wof:placetype":"venue"
},
  "geometry": {"coordinates":[-79.893528,40.431982],"type":"Point"}
}