{
  "type": "Feature",
  "properties": {
    "iso:country":"US",
    "sg:address":"1300 Camp Hill By Pass",
    "sg:city":"Camp Hill",
    "sg:classifiers":[
        {
            "category":"Bars & Pubs",
            "type":"Food & Drink"
        },
        {
            "category":"Fast Food",
            "type":"Food & Drink"
        }
    ],
    "sg:phone":"+1 717 730 9464",
    "sg:postcode":"17011",
    "sg:province":"PA",
    "sg:tags":[
        "chicken",
        "wing"
    ],
    "sg:website":"www.aroogas.com",
    "wof:name":"Aroogas Grille House & Sports Bar",
    "wof:placetype":"venue"
},
  "geometry": {"coordinates":[-76.915601,40.250719],"type":"Point"}
}