{
  "type": "Feature",
  "properties": {
    "addr:full":"1100 Adams Ave Norristown PA 19403",
    "addr:housenumber":"1100",
    "addr:postcode":"19403",
    "addr:street":"Adams Ave",
    "iso:country":"US",
    "sg:address":"1100 Adams Ave",
    "sg:city":"Norristown",
    "sg:classifiers":[
        {
            "category":"Professional",
            "subcategory":"Accounting & Tax Preparation",
            "type":"Services"
        }
    ],
    "sg:phone":"+1 610 650 8100",
    "sg:postcode":"19403",
    "sg:province":"PA",
    "sg:tags":[
        "computerized",
        "payroll"
    ],
    "wof:name":"Paychex Inc",
    "wof:placetype":"venue"
},
  "geometry": {"coordinates":[-75.421055,40.119997],"type":"Point"}
}