{
  "type": "Feature",
  "properties": {
    "iso:country":"US",
    "sg:address":"6560 Market St",
    "sg:city":"Upper Darby",
    "sg:classifiers":[
        {
            "category":"Insurance",
            "subcategory":"Insurance Agent",
            "type":"Services"
        }
    ],
    "sg:phone":"+1 610 734 2000",
    "sg:postcode":"19082",
    "sg:province":"PA",
    "wof:name":"Accent Insurance",
    "wof:placetype":"venue"
},
  "geometry": {"coordinates":[-75.254088,39.96236],"type":"Point"}
}