{
  "type": "Feature",
  "properties": {
    "iso:country":"US",
    "sg:address":"808 Lauber Rd",
    "sg:city":"West Chester",
    "sg:classifiers":[
        {
            "category":"Manufacturing",
            "subcategory":"Printing",
            "type":"Manufacturing & Wholesale Goods"
        }
    ],
    "sg:phone":"+1 610 692 9872",
    "sg:postcode":"19382",
    "sg:province":"PA",
    "sg:tags":[
        "screen",
        "contract",
        "embroidery"
    ],
    "wof:name":"Leisure Graphics Inc",
    "wof:placetype":"venue"
},
  "geometry": {"coordinates":[-75.59000399999999,39.963971],"type":"Point"}
}