{
  "type": "Feature",
  "properties": {
    "addr:full":"2249 Lincoln Hwy E Lancaster PA 17602",
    "addr:housenumber":"2249",
    "addr:postcode":"17602",
    "addr:street":"Lincoln Hwy E",
    "iso:country":"US",
    "sg:address":"2249 Lincoln Hwy E",
    "sg:city":"Lancaster",
    "sg:classifiers":[
        {
            "category":"Ice Cream",
            "type":"Food & Drink"
        }
    ],
    "sg:menulink":"http://www.allmenus.com/pa/east-lampeter/224880-dels-frozen-lemonade/menu/",
    "sg:postcode":"17602",
    "sg:province":"PA",
    "sg:tags":[
        "smoothy",
        "juice",
        "american"
    ],
    "wof:name":"Del's Frozen Lemonade",
    "wof:placetype":"venue"
},
  "geometry": {"coordinates":[-76.219469,40.027844],"type":"Point"}
}