{
  "type": "Feature",
  "properties": {
    "iso:country":"US",
    "sg:address":"5238 N Delaware Dr",
    "sg:city":"Easton",
    "sg:classifiers":[
        {
            "category":"Autos & Motor Vehicles",
            "subcategory":"Auto Supplies",
            "type":"Retail Goods"
        }
    ],
    "sg:phone":"+1 610 252 0121",
    "sg:postcode":"18040",
    "sg:province":"PA",
    "sg:tags":[
        "automobile",
        "parts"
    ],
    "wof:name":"Autometrics",
    "wof:placetype":"venue"
},
  "geometry": {"coordinates":[-75.17857600000001,40.770525],"type":"Point"}
}