{
  "type": "Feature",
  "properties": {
    "iso:country":"US",
    "sg:address":"6259 Hulmeville Rd",
    "sg:city":"Bensalem",
    "sg:classifiers":[
        {
            "category":"Building & Trades",
            "subcategory":"Construction",
            "type":"Services"
        }
    ],
    "sg:phone":"+1   ",
    "sg:postcode":"19020",
    "sg:province":"PA",
    "sg:tags":[
        "contractor"
    ],
    "wof:name":"Bgs Contracting Inc",
    "wof:placetype":"venue"
},
  "geometry": {"coordinates":[-74.917462,40.13595],"type":"Point"}
}