{
  "type": "Feature",
  "properties": {
    "iso:country":"US",
    "sg:address":"3525 Carlisle Pike",
    "sg:city":"Camp Hill",
    "sg:classifiers":[
        {
            "category":"Shopping",
            "subcategory":"Florist",
            "type":"Retail Goods"
        }
    ],
    "sg:phone":"+1 717 731 9390",
    "sg:postcode":"17011",
    "sg:province":"PA",
    "wof:name":"Retherford Al Flowers",
    "wof:placetype":"venue"
},
  "geometry": {"coordinates":[-76.943072,40.239055],"type":"Point"}
}