{
  "type": "Feature",
  "properties": {
    "iso:country":"US",
    "sg:address":"2380 Catherine St",
    "sg:city":"York",
    "sg:classifiers":[
        {
            "category":"Building & Trades",
            "subcategory":"Construction",
            "type":"Services"
        }
    ],
    "sg:phone":"+1 717 792 0675",
    "sg:postcode":"17408",
    "sg:province":"PA",
    "sg:tags":[
        "new",
        "remodeling",
        "residential"
    ],
    "wof:name":"T & P Handyman",
    "wof:placetype":"venue"
},
  "geometry": {"coordinates":[-76.784063,39.959655],"type":"Point"}
}