{
  "type": "Feature",
  "properties": {
    "iso:country":"US",
    "sg:address":"605 Freeport Rd",
    "sg:city":"Sharpsburg",
    "sg:classifiers":[
        {
            "category":"Real Estate",
            "subcategory":"Real Estate Agent",
            "type":"Services"
        }
    ],
    "sg:phone":"+1 412 784 8400",
    "sg:postcode":"15215",
    "sg:province":"PA",
    "wof:name":"Suzanne H Kraft Inc",
    "wof:placetype":"venue"
},
  "geometry": {"coordinates":[-79.898484,40.488119],"type":"Point"}
}