{
  "type": "Feature",
  "properties": {
    "iso:country":"US",
    "sg:address":"337 Cattell St",
    "sg:city":"Easton",
    "sg:classifiers":[
        {
            "category":"Insurance",
            "subcategory":"Insurance Agent",
            "type":"Services"
        }
    ],
    "sg:phone":"+1 610 252 1658",
    "sg:postcode":"18042",
    "sg:province":"PA",
    "wof:name":"Zulick Insurance",
    "wof:placetype":"venue"
},
  "geometry": {"coordinates":[-75.206217,40.701154],"type":"Point"}
}