{
  "type": "Feature",
  "properties": {
    "iso:country":"US",
    "sg:address":"9600 Roosevelt Blvd",
    "sg:city":"Philadelphia",
    "sg:classifiers":[
        {
            "category":"Building & Trades",
            "subcategory":"Pest Control",
            "type":"Services"
        }
    ],
    "sg:phone":"+1 215 676 3301",
    "sg:postcode":"19115",
    "sg:province":"PA",
    "wof:name":"Vanish Exterminating Corp",
    "wof:placetype":"venue"
},
  "geometry": {"coordinates":[-75.02679500000001,40.083189],"type":"Point"}
}