{
  "type": "Feature",
  "properties": {
    "iso:country":"US",
    "sg:address":"32 Forrest St",
    "sg:city":"Wilkes Barre",
    "sg:classifiers":[
        {
            "category":"Professional",
            "subcategory":"Computer Services",
            "type":"Services"
        }
    ],
    "sg:phone":"+1   ",
    "sg:postcode":"18702",
    "sg:province":"PA",
    "sg:tags":[
        "information",
        "imaging",
        "business",
        "record"
    ],
    "wof:name":"Midwest Imaging",
    "wof:placetype":"venue"
},
  "geometry": {"coordinates":[-75.891435,41.228628],"type":"Point"}
}