{
  "type": "Feature",
  "properties": {
    "iso:country":"US",
    "sg:address":"458 3rd St",
    "sg:city":"Beaver",
    "sg:classifiers":[
        {
            "category":"Shopping",
            "subcategory":"Florist",
            "type":"Retail Goods"
        }
    ],
    "sg:phone":"+1 724 728 2567",
    "sg:postcode":"15009",
    "sg:province":"PA",
    "wof:name":"Bonnie August Florals",
    "wof:placetype":"venue"
},
  "geometry": {"coordinates":[-80.30256300000001,40.696159],"type":"Point"}
}