{
  "type": "Feature",
  "properties": {
    "iso:country":"US",
    "sg:address":"170 Woodcrest Ln",
    "sg:city":"Stevens",
    "sg:classifiers":[
        {
            "category":"Building & Trades",
            "subcategory":"Construction",
            "type":"Services"
        }
    ],
    "sg:phone":"+1 717 336 2306",
    "sg:postcode":"17578",
    "sg:province":"PA",
    "sg:tags":[
        "mason",
        "masonry",
        "industrial",
        "contractors-commercial",
        "contractor"
    ],
    "wof:name":"Zimmerman & Herr Mason Contractors",
    "wof:placetype":"venue"
},
  "geometry": {"coordinates":[-76.119559,40.201232],"type":"Point"}
}