{
  "type": "Feature",
  "properties": {
    "addr:full":"124 Chestnut St Philadelphia PA 19106",
    "addr:housenumber":"124",
    "addr:postcode":"19106",
    "addr:street":"Chestnut St",
    "iso:country":"US",
    "sg:address":"124 Chestnut St",
    "sg:city":"Philadelphia",
    "sg:classifiers":[
        {
            "category":"Manufacturing",
            "subcategory":"Rubber & Plastics",
            "type":"Manufacturing & Wholesale Goods"
        },
        {
            "category":"Shopping",
            "type":"Retail Goods"
        }
    ],
    "sg:phone":"+1 215 922 3480",
    "sg:postcode":"19106",
    "sg:province":"PA",
    "sg:tags":[
        "clothing-wholesale",
        "equipment",
        "safety",
        "clothing",
        "manufacturer"
    ],
    "wof:name":"Russell Pga Associates",
    "wof:placetype":"venue"
},
  "geometry": {"coordinates":[-75.143359,39.948298],"type":"Point"}
}