{
  "type": "Feature",
  "properties": {
    "iso:country":"US",
    "sg:address":"194 W Lexington Rd",
    "sg:city":"Lititz",
    "sg:classifiers":[
        {
            "category":"Farming",
            "subcategory":"Dairy Farm",
            "type":"Manufacturing & Wholesale Goods"
        }
    ],
    "sg:phone":"+1   ",
    "sg:postcode":"17543",
    "sg:province":"PA",
    "wof:name":"Nelson Stoner",
    "wof:placetype":"venue"
},
  "geometry": {"coordinates":[-76.31944300000001,40.189921],"type":"Point"}
}