{
  "type": "Feature",
  "properties": {
    "iso:country":"US",
    "sg:address":"2329 N Main Ave",
    "sg:city":"Scranton",
    "sg:classifiers":[
        {
            "category":"Building & Trades",
            "subcategory":"Construction",
            "type":"Services"
        }
    ],
    "sg:phone":"+1 570 342 7402",
    "sg:postcode":"18508",
    "sg:province":"PA",
    "sg:tags":[
        "concrete",
        "contractor",
        "general"
    ],
    "wof:name":"Ronco Fence Co",
    "wof:placetype":"venue"
},
  "geometry": {"coordinates":[-75.6499,41.439583],"type":"Point"}
}