{
  "type": "Feature",
  "properties": {
    "iso:country":"US",
    "sg:address":"206 Parrish St",
    "sg:city":"Wilkes Barre",
    "sg:classifiers":[
        {
            "category":"Building & Trades",
            "subcategory":"Plumbing",
            "type":"Services"
        }
    ],
    "sg:phone":"+1   ",
    "sg:postcode":"18702",
    "sg:province":"PA",
    "sg:tags":[
        "plumbing",
        "air",
        "heating",
        "conditioning",
        "contractor"
    ],
    "wof:name":"C W Schultz & Son Inc",
    "wof:placetype":"venue"
},
  "geometry": {"coordinates":[-75.89775400000001,41.231445],"type":"Point"}
}