{
  "type": "Feature",
  "properties": {
    "iso:country":"US",
    "sg:address":"180 Airport Rd",
    "sg:city":"Coatesville",
    "sg:phone":"+1 877 865 4965",
    "sg:postcode":"19320",
    "sg:province":"PA",
    "sg:website":"http://local.ingenio.com/Listings/Details.aspx?NUM=a%3a9778478%3a13%3a4859924%3a14%3a0%3a7",
    "wof:name":"Arty's Auto Svc Inc",
    "wof:placetype":"venue"
},
  "geometry": {"coordinates":[-75.86760200000001,39.984008],"type":"Point"}
}