{
  "type": "Feature",
  "properties": {
    "iso:country":"US",
    "sg:address":"2902 W Chester Pike ",
    "sg:city":"Broomall",
    "sg:classifiers":[
        {
            "category":"Restaurant",
            "type":"Food & Drink"
        }
    ],
    "sg:menulink":"http://www.allmenus.com/pa/marple/289296-valentinos-restaurant/menu/",
    "sg:phone":"+1 610 353 1111",
    "sg:postcode":"19008",
    "sg:province":"PA",
    "sg:tags":[
        "american"
    ],
    "wof:name":"Valentino's Restaurant",
    "wof:placetype":"venue"
},
  "geometry": {"coordinates":[-75.37141,39.983079],"type":"Point"}
}