{
  "type": "Feature",
  "properties": {
    "iso:country":"US",
    "sg:address":"315 Gordon Dr",
    "sg:city":"Exton",
    "sg:classifiers":[
        {
            "category":"Government",
            "subcategory":"Office",
            "type":"Public Place"
        }
    ],
    "sg:phone":"+1 610 524 5595",
    "sg:postcode":"19341",
    "sg:province":"PA",
    "sg:tags":[
        "executive"
    ],
    "wof:name":"Curt Schroder State Rep",
    "wof:placetype":"venue"
},
  "geometry": {"coordinates":[-75.650578,40.060749],"type":"Point"}
}