{
  "type": "Feature",
  "properties": {
    "iso:country":"US",
    "sg:address":"4813 Jonestown Rd",
    "sg:city":"Harrisburg",
    "sg:classifiers":[
        {
            "category":"Health Services",
            "subcategory":"Optometrist",
            "type":"Services"
        }
    ],
    "sg:phone":"+1 717 657 3682",
    "sg:postcode":"17109",
    "sg:province":"PA",
    "wof:name":"Gerchberg Smith Eye Assoc",
    "wof:placetype":"venue"
},
  "geometry": {"coordinates":[-76.80782000000001,40.304539],"type":"Point"}
}