{
  "type": "Feature",
  "properties": {
    "iso:country":"US",
    "sg:address":"1604 N 2nd St",
    "sg:city":"Harrisburg",
    "sg:classifiers":[
        {
            "category":"Organizations",
            "subcategory":"Non-profit Organization",
            "type":"Services"
        }
    ],
    "sg:phone":"+1 717 920 8450",
    "sg:postcode":"17102",
    "sg:province":"PA",
    "sg:tags":[
        "service/non-profit",
        "community"
    ],
    "wof:name":"Reddi-Regional Econ Dev Dist Init",
    "wof:placetype":"venue"
},
  "geometry": {"coordinates":[-76.894383,40.271907],"type":"Point"}
}