{
  "type": "Feature",
  "properties": {
    "iso:country":"US",
    "sg:address":"201 S Enola Dr",
    "sg:city":"Enola",
    "sg:classifiers":[
        {
            "category":"Manufacturing",
            "subcategory":"Furniture",
            "type":"Manufacturing & Wholesale Goods"
        }
    ],
    "sg:phone":"+1   ",
    "sg:postcode":"17025",
    "sg:province":"PA",
    "sg:tags":[
        "household",
        "wood",
        "mfg"
    ],
    "wof:name":"Woodchuck",
    "wof:placetype":"venue"
},
  "geometry": {"coordinates":[-76.931646,40.282873],"type":"Point"}
}