{
  "type": "Feature",
  "properties": {
    "addr:full":"11 Russell St Warren PA 16365",
    "addr:housenumber":"11",
    "addr:postcode":"16365",
    "addr:street":"Russell St",
    "iso:country":"US",
    "sg:address":"11 Russell St",
    "sg:city":"Warren",
    "sg:classifiers":[
        {
            "category":"Organizations",
            "subcategory":"Religious Organization",
            "type":"Services"
        }
    ],
    "sg:phone":"+1   ",
    "sg:postcode":"16365",
    "sg:province":"PA",
    "wof:name":"Holy Rdmer Rman Cathlic Church",
    "wof:placetype":"venue"
},
  "geometry": {"coordinates":[-79.13127799999999,41.839817],"type":"Point"}
}