{
  "type": "Feature",
  "properties": {
    "addr:full":"925 Liberty Ave Pittsburgh PA 15222",
    "addr:housenumber":"925",
    "addr:postcode":"15222",
    "addr:street":"Liberty Ave",
    "iso:country":"US",
    "sg:address":"925 Liberty Ave",
    "sg:city":"Pittsburgh",
    "sg:classifiers":[
        {
            "category":"Shopping",
            "subcategory":"Computers & Home Electronics",
            "type":"Retail Goods"
        }
    ],
    "sg:phone":"+1 412 232 3250",
    "sg:postcode":"15222",
    "sg:province":"PA",
    "sg:tags":[
        "software"
    ],
    "wof:name":"Time Sys Corp",
    "wof:placetype":"venue"
},
  "geometry": {"coordinates":[-79.99638,40.443413],"type":"Point"}
}