{
  "type": "Feature",
  "properties": {
    "addr:full":"644 Henderson Dr Springdale PA 15144",
    "addr:housenumber":"644",
    "addr:postcode":"15144",
    "addr:street":"Henderson Dr",
    "iso:country":"US",
    "sg:address":"644 Henderson Dr",
    "sg:city":"Springdale",
    "sg:classifiers":[
        {
            "category":"Manufacturing",
            "subcategory":"Printing",
            "type":"Manufacturing & Wholesale Goods"
        }
    ],
    "sg:phone":"+1 724 274 4103",
    "sg:postcode":"15144",
    "sg:province":"PA",
    "sg:tags":[
        "publisher",
        "book",
        "publishing"
    ],
    "wof:name":"Grace Dawning Publications",
    "wof:placetype":"venue"
},
  "geometry": {"coordinates":[-79.78269,40.548992],"type":"Point"}
}