{
  "type": "Feature",
  "properties": {
    "iso:country":"US",
    "sg:address":"1256 Brookline Blvd",
    "sg:city":"Pittsburgh",
    "sg:classifiers":[
        {
            "category":"Health Services",
            "subcategory":"Dentist",
            "type":"Services"
        }
    ],
    "sg:phone":"+1 412 531 3155",
    "sg:postcode":"15226",
    "sg:province":"PA",
    "wof:name":"Kyros James M DMD",
    "wof:placetype":"venue"
},
  "geometry": {"coordinates":[-80.012001,40.3922],"type":"Point"}
}