{
  "type": "Feature",
  "properties": {
    "addr:full":"5269 Jonestown Rd Harrisburg PA 17112",
    "addr:housenumber":"5269",
    "addr:postcode":"17112",
    "addr:street":"Jonestown Rd",
    "iso:country":"US",
    "sg:address":"5269 Jonestown Rd",
    "sg:city":"Harrisburg",
    "sg:classifiers":[
        {
            "category":"Health Services",
            "subcategory":"Doctor",
            "type":"Services"
        }
    ],
    "sg:phone":"+1   ",
    "sg:postcode":"17112",
    "sg:province":"PA",
    "sg:tags":[
        "medical"
    ],
    "wof:name":"Gault Chiropratic",
    "wof:placetype":"venue"
},
  "geometry": {"coordinates":[-76.79786300000001,40.315111],"type":"Point"}
}