{
  "type": "Feature",
  "properties": {
    "addr:full":"1125 Berkshire Blvd Reading PA 19610",
    "addr:housenumber":"1125",
    "addr:postcode":"19610",
    "addr:street":"Berkshire Blvd",
    "iso:country":"US",
    "sg:address":"1125 Berkshire Blvd",
    "sg:city":"Reading",
    "sg:classifiers":[
        {
            "category":"Insurance",
            "subcategory":"Insurance Agent",
            "type":"Services"
        }
    ],
    "sg:phone":"+1   ",
    "sg:postcode":"19610",
    "sg:province":"PA",
    "wof:name":"American Gen Lf Accident Insur",
    "wof:placetype":"venue"
},
  "geometry": {"coordinates":[-75.974503,40.344443],"type":"Point"}
}