{
  "type": "Feature",
  "properties": {
    "iso:country":"US",
    "sg:address":"1508 S 13th St",
    "sg:city":"Philadelphia",
    "sg:classifiers":[
        {
            "category":"Arts & Performance",
            "subcategory":"Dance",
            "type":"Entertainment"
        }
    ],
    "sg:phone":"+1 215 962 4773",
    "sg:postcode":"19147",
    "sg:province":"PA",
    "sg:tags":[
        "instruction",
        "dancing"
    ],
    "wof:name":"Miro Dance Theatre",
    "wof:placetype":"venue"
},
  "geometry": {"coordinates":[-75.165971,39.93132],"type":"Point"}
}