{
  "type": "Feature",
  "properties": {
    "iso:country":"US",
    "sg:address":"47 Public Sq",
    "sg:city":"Wilkes Barre",
    "sg:classifiers":[
        {
            "category":"Professional",
            "subcategory":"Management & Consulting",
            "type":"Services"
        }
    ],
    "sg:phone":"+1 570 826 9055",
    "sg:postcode":"18701",
    "sg:province":"PA",
    "sg:tags":[
        "consultant",
        "safety"
    ],
    "wof:name":"National Safety Assoc",
    "wof:placetype":"venue"
},
  "geometry": {"coordinates":[-75.88145900000001,41.245325],"type":"Point"}
}