{
  "type": "Feature",
  "properties": {
    "addr:full":"312 W Main St Camp Hill PA 17011",
    "addr:housenumber":"312",
    "addr:postcode":"17011",
    "addr:street":"W Main St",
    "iso:country":"US",
    "sg:address":"312 W Main St",
    "sg:city":"Camp Hill",
    "sg:classifiers":[
        {
            "category":"Building & Trades",
            "subcategory":"Landscaping Services",
            "type":"Services"
        }
    ],
    "sg:phone":"+1   ",
    "sg:postcode":"17011",
    "sg:province":"PA",
    "wof:name":"Shedlosky Landscaping Co",
    "wof:placetype":"venue"
},
  "geometry": {"coordinates":[-76.964476,40.220955],"type":"Point"}
}