{
  "type": "Feature",
  "properties": {
    "iso:country":"US",
    "sg:address":"2670 Wyngate Rd",
    "sg:city":"Dover",
    "sg:classifiers":[
        {
            "category":"Transit Center",
            "subcategory":"Freight",
            "type":"Transportation"
        }
    ],
    "sg:phone":"+1 717 292 2957",
    "sg:postcode":"17315",
    "sg:province":"PA",
    "sg:tags":[
        "trucking-heavy",
        "hauling"
    ],
    "wof:name":"Universal Am-Can",
    "wof:placetype":"venue"
},
  "geometry": {"coordinates":[-76.839668,39.98317],"type":"Point"}
}