{
  "type": "Feature",
  "properties": {
    "addr:full":"4260 Ohio River Blvd Pittsburgh PA 15202",
    "addr:housenumber":"4260",
    "addr:postcode":"15202",
    "addr:street":"Ohio River Blvd",
    "iso:country":"US",
    "sg:address":"4260 Ohio River Blvd",
    "sg:city":"Pittsburgh",
    "sg:classifiers":[
        {
            "category":"Fast Food",
            "type":"Food & Drink"
        },
        {
            "category":"Restaurant",
            "type":"Food & Drink"
        }
    ],
    "sg:phone":"+1 412 766 3020",
    "sg:postcode":"15202",
    "sg:province":"PA",
    "sg:tags":[
        "american",
        "hot",
        "hamburger",
        "dog"
    ],
    "sg:website":"http://www.bk.com",
    "wof:name":"Burger King",
    "wof:placetype":"venue"
},
  "geometry": {"coordinates":[-80.055471,40.487201],"type":"Point"}
}