{
  "type": "Feature",
  "properties": {
    "addr:full":"4402 Peach St Erie PA 16509",
    "addr:housenumber":"4402",
    "addr:postcode":"16509",
    "addr:street":"Peach St",
    "iso:country":"US",
    "sg:address":"4402 Peach St",
    "sg:city":"Erie",
    "sg:classifiers":[
        {
            "category":"Real Estate",
            "subcategory":"Real Estate Agent",
            "type":"Services"
        }
    ],
    "sg:phone":"+1 814 860 8400",
    "sg:postcode":"16509",
    "sg:province":"PA",
    "wof:name":"25 Real Estate Direct",
    "wof:placetype":"venue"
},
  "geometry": {"coordinates":[-80.08688600000001,42.087556],"type":"Point"}
}