{
  "type": "Feature",
  "properties": {
    "iso:country":"US",
    "sg:address":"11 N. 3rd Street 2nd Floor",
    "sg:city":"Philadelphia",
    "sg:classifiers":[
        {
            "category":"Professional",
            "subcategory":"Advertising",
            "type":"Services"
        }
    ],
    "sg:phone":"+1 415 669 4306",
    "sg:postcode":"19106",
    "sg:province":"PA",
    "sg:tags":[
        "web",
        "design",
        "development",
        "strategy",
        "agency",
        "interactive",
        "digital",
        "full-service",
        "advertising",
        "marketing",
        "pr",
        "social-media",
        "social-networking",
        "iphone",
        "apps",
        "applications",
        "agile",
        "twitter",
        "facebook"
    ],
    "sg:website":"http://freshout.us",
    "wof:name":"Freshout",
    "wof:placetype":"venue"
},
  "geometry": {"coordinates":[-75.14360600000001,39.950083],"type":"Point"}
}