{
  "type": "Feature",
  "properties": {
    "addr:full":"55 N Norwinden Dr Springfield PA 19064",
    "addr:housenumber":"55",
    "addr:postcode":"19064",
    "addr:street":"N Norwinden Dr",
    "iso:country":"US",
    "sg:address":"55 N Norwinden Dr",
    "sg:city":"Springfield",
    "sg:classifiers":[
        {
            "category":"Professional",
            "subcategory":"Management & Consulting",
            "type":"Services"
        }
    ],
    "sg:phone":"+1 610 543 7533",
    "sg:postcode":"19064",
    "sg:province":"PA",
    "sg:tags":[
        "conference",
        "consultant",
        "meeting"
    ],
    "wof:name":"A Planned A Phayre",
    "wof:placetype":"venue"
},
  "geometry": {"coordinates":[-75.32034899999999,39.931956],"type":"Point"}
}