{
  "type": "Feature",
  "properties": {
    "addr:full":"571 Mountain Home Rd Reading PA 19608",
    "addr:housenumber":"571",
    "addr:postcode":"19608",
    "addr:street":"Mountain Home Rd",
    "iso:country":"US",
    "sg:address":"571 Mountain Home Rd",
    "sg:city":"Reading",
    "sg:classifiers":[
        {
            "category":"Manufacturing",
            "subcategory":"Metals",
            "type":"Manufacturing & Wholesale Goods"
        }
    ],
    "sg:phone":"+1 610 678 2910",
    "sg:postcode":"19608",
    "sg:province":"PA",
    "sg:tags":[
        "fabricator",
        "metalwork",
        "sheet",
        "mfg"
    ],
    "wof:name":"Webber's Sheet Metal",
    "wof:placetype":"venue"
},
  "geometry": {"coordinates":[-76.055083,40.313045],"type":"Point"}
}