{
  "type": "Feature",
  "properties": {
    "iso:country":"US",
    "sg:address":"28 Country Ln",
    "sg:city":"Glen Mills",
    "sg:classifiers":[
        {
            "category":"Professional",
            "subcategory":"Accounting & Tax Preparation",
            "type":"Services"
        }
    ],
    "sg:phone":"+1 610 558 4151",
    "sg:postcode":"19342",
    "sg:province":"PA",
    "sg:tags":[
        "bookkeeping",
        "general"
    ],
    "wof:name":"Diversified Management",
    "wof:placetype":"venue"
},
  "geometry": {"coordinates":[-75.488726,39.874966],"type":"Point"}
}