{
  "type": "Feature",
  "properties": {
    "addr:full":"3020 Market St Philadelphia PA 19104",
    "addr:housenumber":"3020",
    "addr:postcode":"19104",
    "addr:street":"Market St",
    "iso:country":"US",
    "sg:address":"3020 Market St",
    "sg:city":"Philadelphia",
    "sg:classifiers":[
        {
            "category":"Professional",
            "type":"Services"
        }
    ],
    "sg:phone":"+1 215 360 3380",
    "sg:postcode":"19104",
    "sg:province":"PA",
    "sg:tags":[
        "renting",
        "equipment",
        "computer",
        "leasing"
    ],
    "wof:name":"Netcarrier",
    "wof:placetype":"venue"
},
  "geometry": {"coordinates":[-75.183849,39.954891],"type":"Point"}
}