{
  "type": "Feature",
  "properties": {
    "iso:country":"US",
    "sg:address":"2871 Freeport Rd",
    "sg:city":"Pittsburgh",
    "sg:classifiers":[
        {
            "category":"Autos & Motor Vehicles",
            "subcategory":"Automobile Sales",
            "type":"Retail Goods"
        }
    ],
    "sg:phone":"+1   ",
    "sg:postcode":"15238",
    "sg:province":"PA",
    "wof:name":"Shults Ford At Route 28",
    "wof:placetype":"venue"
},
  "geometry": {"coordinates":[-79.82961899999999,40.538889],"type":"Point"}
}