{
  "type": "Feature",
  "properties": {
    "iso:country":"US",
    "sg:address":"2 Pine St",
    "sg:city":"Alfred",
    "sg:classifiers":[
        {
            "category":"Education",
            "subcategory":"Library",
            "type":"Public Place"
        }
    ],
    "sg:phone":"+1 607 871 2492",
    "sg:postcode":"14892",
    "sg:province":"PA",
    "sg:tags":[
        "college"
    ],
    "wof:name":"Scholes Library Of Ceramics",
    "wof:placetype":"venue"
},
  "geometry": {"coordinates":[-76.54700099999999,42.001954],"type":"Point"}
}