{
  "type": "Feature",
  "properties": {
    "addr:full":"3 Webster St Bangor PA 18013",
    "addr:housenumber":"3",
    "addr:postcode":"18013",
    "addr:street":"Webster St",
    "iso:country":"US",
    "sg:address":"3 Webster St",
    "sg:city":"Bangor",
    "sg:classifiers":[
        {
            "category":"Health Services",
            "subcategory":"Chiropractor",
            "type":"Services"
        }
    ],
    "sg:phone":"+1 610 588 1396",
    "sg:postcode":"18013",
    "sg:province":"PA",
    "sg:tags":[
        "chiropractic"
    ],
    "wof:name":"Anthony Perone Dc",
    "wof:placetype":"venue"
},
  "geometry": {"coordinates":[-75.190079,40.877585],"type":"Point"}
}