{
  "type": "Feature",
  "properties": {
    "iso:country":"US",
    "sg:address":"300 W Pittsburgh St",
    "sg:city":"Greensburg",
    "sg:classifiers":[
        {
            "category":"Home & Garden",
            "subcategory":"Building Materials",
            "type":"Retail Goods"
        },
        {
            "category":"Retail",
            "subcategory":"Auto Repair",
            "type":"Services"
        }
    ],
    "sg:phone":"+1 724 837 3884",
    "sg:postcode":"15601",
    "sg:province":"PA",
    "sg:tags":[
        "plate",
        "window",
        "replacement",
        "glass"
    ],
    "wof:name":"SAFELITE AUTO GLASS",
    "wof:placetype":"venue"
},
  "geometry": {"coordinates":[-79.549469,40.301418],"type":"Point"}
}