{
  "type": "Feature",
  "properties": {
    "iso:country":"US",
    "sg:address":"1117 N 38th St",
    "sg:city":"Philadelphia",
    "sg:classifiers":[
        {
            "category":"Retail",
            "subcategory":"Auto Repair",
            "type":"Services"
        }
    ],
    "sg:phone":"+1 215 382 3936",
    "sg:postcode":"19104",
    "sg:province":"PA",
    "sg:tags":[
        "body",
        "automobile",
        "painting"
    ],
    "wof:name":"Willie Tucker's Auto Repair",
    "wof:placetype":"venue"
},
  "geometry": {"coordinates":[-75.199505,39.974646],"type":"Point"}
}