{
  "type": "Feature",
  "properties": {
    "iso:country":"US",
    "sg:address":"937 Park Ave",
    "sg:city":"Wycombe",
    "sg:classifiers":[
        {
            "category":"Retail",
            "subcategory":"Repair Shop",
            "type":"Services"
        }
    ],
    "sg:phone":"+1 215 598 3336",
    "sg:postcode":"18940",
    "sg:province":"PA",
    "sg:tags":[
        "blacksmith"
    ],
    "wof:name":"Solebury Forge",
    "wof:placetype":"venue"
},
  "geometry": {"coordinates":[-75.00456699999999,40.281347],"type":"Point"}
}