{
  "type": "Feature",
  "properties": {
    "iso:country":"US",
    "sg:address":"300 Hollar Ave",
    "sg:city":"Shippensburg",
    "sg:classifiers":[
        {
            "category":"Building & Trades",
            "subcategory":"Electrical",
            "type":"Services"
        }
    ],
    "sg:phone":"+1 717 532 3187",
    "sg:postcode":"17257",
    "sg:province":"PA",
    "sg:tags":[
        "electrician"
    ],
    "wof:name":"M & M Electric Associates",
    "wof:placetype":"venue"
},
  "geometry": {"coordinates":[-77.505623,40.052429],"type":"Point"}
}