{
  "type": "Feature",
  "properties": {
    "addr:full":"2830 Pacific Ave Orefield PA 18069",
    "addr:housenumber":"2830",
    "addr:postcode":"18069",
    "addr:street":"Pacific Ave",
    "iso:country":"US",
    "sg:address":"2830 Pacific Ave",
    "sg:city":"Orefield",
    "sg:classifiers":[
        {
            "category":"Freight",
            "type":"Transportation"
        }
    ],
    "sg:phone":"+1   ",
    "sg:postcode":"18069",
    "sg:province":"PA",
    "sg:tags":[
        "local",
        "hauling"
    ],
    "wof:name":"Reuben K Krause Water Hauling",
    "wof:placetype":"venue"
},
  "geometry": {"coordinates":[-75.58797199999999,40.632056],"type":"Point"}
}