{
  "type": "Feature",
  "properties": {
    "iso:country":"US",
    "sg:address":"25 Chatham Rd",
    "sg:city":"Ardmore",
    "sg:classifiers":[
        {
            "category":"Building & Trades",
            "subcategory":"Construction",
            "type":"Services"
        }
    ],
    "sg:phone":"+1 610 896 7190",
    "sg:postcode":"19003",
    "sg:province":"PA",
    "sg:tags":[
        "house",
        "general",
        "contractor"
    ],
    "wof:name":"Bruce E Madden Inc",
    "wof:placetype":"venue"
},
  "geometry": {"coordinates":[-75.28501900000001,40.003557],"type":"Point"}
}