{
  "type": "Feature",
  "properties": {
    "iso:country":"US",
    "sg:address":"1315 Arch St",
    "sg:city":"Pittsburgh",
    "sg:classifiers":[
        {
            "category":"Manufacturing",
            "subcategory":"Glass & Minerals",
            "type":"Manufacturing & Wholesale Goods"
        }
    ],
    "sg:phone":"+1 412 231 8000",
    "sg:postcode":"15212",
    "sg:province":"PA",
    "sg:tags":[
        "tile"
    ],
    "wof:name":"Hunnell Street Tile Works",
    "wof:placetype":"venue"
},
  "geometry": {"coordinates":[-80.009304,40.456935],"type":"Point"}
}