{
  "type": "Feature",
  "properties": {
    "iso:country":"US",
    "sg:address":"99 Ashford Dr",
    "sg:city":"Cranberry Twp",
    "sg:classifiers":[
        {
            "category":"Organizations",
            "subcategory":"Professional Association",
            "type":"Services"
        },
        {
            "category":"Banks & Credit Unions",
            "subcategory":"Bank",
            "type":"Services"
        }
    ],
    "sg:phone":"+1 724 776 0999",
    "sg:postcode":"16066",
    "sg:province":"PA",
    "sg:tags":[
        "short",
        "institution",
        "business"
    ],
    "wof:name":"Ashford Manor Condominium",
    "wof:placetype":"venue"
},
  "geometry": {"coordinates":[-80.12571199999999,40.687613],"type":"Point"}
}