{
  "type": "Feature",
  "properties": {
    "iso:country":"US",
    "sg:address":"5505 Fordham Ave",
    "sg:city":"Harrisburg",
    "sg:classifiers":[
        {
            "category":"Building & Trades",
            "subcategory":"Construction",
            "type":"Services"
        }
    ],
    "sg:phone":"+1   ",
    "sg:postcode":"17111",
    "sg:province":"PA",
    "wof:name":"Arthur Proctor",
    "wof:placetype":"venue"
},
  "geometry": {"coordinates":[-76.79476699999999,40.266491],"type":"Point"}
}