{
  "type": "Feature",
  "properties": {
    "iso:country":"US",
    "sg:address":"9750 Easton Rd",
    "sg:city":"Kintnersville",
    "sg:classifiers":[
        {
            "category":"Shopping",
            "subcategory":"Used Merchandise",
            "type":"Retail Goods"
        }
    ],
    "sg:phone":"+1 610 847 8011",
    "sg:postcode":"18930",
    "sg:province":"PA",
    "sg:tags":[
        "antique"
    ],
    "wof:name":"Corner Antiques",
    "wof:placetype":"venue"
},
  "geometry": {"coordinates":[-75.181231,40.540052],"type":"Point"}
}