{
  "type": "Feature",
  "properties": {
    "addr:full":"3981 Perkiomen Ave Reading PA 19606",
    "addr:housenumber":"3981",
    "addr:postcode":"19606",
    "addr:street":"Perkiomen Ave",
    "iso:country":"US",
    "sg:address":"3981 Perkiomen Ave",
    "sg:city":"Reading",
    "sg:classifiers":[
        {
            "category":"Shopping",
            "subcategory":"Shoes",
            "type":"Retail Goods"
        }
    ],
    "sg:phone":"+1 610 370 2323",
    "sg:postcode":"19606",
    "sg:province":"PA",
    "sg:tags":[
        "family"
    ],
    "wof:name":"Berkshire Boot & Shoe Shoppe",
    "wof:placetype":"venue"
},
  "geometry": {"coordinates":[-75.87043,40.314173],"type":"Point"}
}