{
  "type": "Feature",
  "properties": {
    "addr:full":"1171 Ringling Ave Johnstown PA 15902",
    "addr:housenumber":"1171",
    "addr:postcode":"15902",
    "addr:street":"Ringling Ave",
    "iso:country":"US",
    "sg:address":"1171 Ringling Ave",
    "sg:city":"Johnstown",
    "sg:classifiers":[
        {
            "category":"Manufacturing",
            "subcategory":"Tools & Machinery",
            "type":"Manufacturing & Wholesale Goods"
        }
    ],
    "sg:phone":"+1 814 269 9531",
    "sg:postcode":"15902",
    "sg:province":"PA",
    "sg:tags":[
        "medical",
        "stump",
        "support",
        "mfg"
    ],
    "sg:website":"www.gerberchairmates.com",
    "wof:name":"Gerber Chair Mates Inc",
    "wof:placetype":"venue"
},
  "geometry": {"coordinates":[-78.891801,40.307476],"type":"Point"}
}