{
  "type": "Feature",
  "properties": {
    "addr:full":"1920 N 20th St Philadelphia PA 19121",
    "addr:housenumber":"1920",
    "addr:postcode":"19121",
    "addr:street":"N 20Th St",
    "iso:country":"US",
    "sg:address":"1920 N 20th St",
    "sg:city":"Philadelphia",
    "sg:classifiers":[
        {
            "category":"Health Services",
            "subcategory":"Doctor",
            "type":"Services"
        }
    ],
    "sg:phone":"+1   ",
    "sg:postcode":"19121",
    "sg:province":"PA",
    "sg:tags":[
        "medical"
    ],
    "wof:name":"Public Health Dept",
    "wof:placetype":"venue"
},
  "geometry": {"coordinates":[-75.166545,39.984143],"type":"Point"}
}