{
  "type": "Feature",
  "properties": {
    "iso:country":"US",
    "sg:address":"909 N 7th St",
    "sg:city":"Lebanon",
    "sg:classifiers":[
        {
            "category":"Retail",
            "subcategory":"Auto Repair",
            "type":"Services"
        }
    ],
    "sg:phone":"+1 717 272 2094",
    "sg:postcode":"17046",
    "sg:province":"PA",
    "sg:tags":[
        "repairing",
        "automobile",
        "station",
        "gasoline",
        "general"
    ],
    "wof:name":"Snyder's Service Station",
    "wof:placetype":"venue"
},
  "geometry": {"coordinates":[-76.42385899999999,40.353882],"type":"Point"}
}