{
  "type": "Feature",
  "properties": {
    "iso:country":"US",
    "sg:address":"396 Adams St",
    "sg:city":"Rochester",
    "sg:classifiers":[
        {
            "category":"Professional",
            "subcategory":"Lawyer & Legal Services",
            "type":"Services"
        }
    ],
    "sg:phone":"+1 724 774 5470",
    "sg:postcode":"15074",
    "sg:province":"PA",
    "sg:tags":[
        "attorney"
    ],
    "wof:name":"Frank S Kelker",
    "wof:placetype":"venue"
},
  "geometry": {"coordinates":[-80.28152799999999,40.703224],"type":"Point"}
}