{
  "type": "Feature",
  "properties": {
    "addr:full":"5746 Brandy Ln Nazareth PA 18064",
    "addr:housenumber":"5746",
    "addr:postcode":"18064",
    "addr:street":"Brandy Ln",
    "iso:country":"US",
    "sg:address":"5746 Brandy Ln",
    "sg:city":"Nazareth",
    "sg:classifiers":[
        {
            "category":"Organizations",
            "subcategory":"Religious Organization",
            "type":"Services"
        }
    ],
    "sg:phone":"+1 610 746 5084",
    "sg:postcode":"18064",
    "sg:province":"PA",
    "sg:tags":[
        "clergy"
    ],
    "wof:name":"Arthur S Gilmore",
    "wof:placetype":"venue"
},
  "geometry": {"coordinates":[-75.276507,40.771641],"type":"Point"}
}