{
  "type": "Feature",
  "properties": {
    "iso:country":"US",
    "sg:address":"644 Fruit Ave",
    "sg:city":"Farrell",
    "sg:classifiers":[
        {
            "category":"Retail",
            "subcategory":"Auto Repair",
            "type":"Services"
        }
    ],
    "sg:phone":"+1 724 346 1088",
    "sg:postcode":"16121",
    "sg:province":"PA",
    "sg:tags":[
        "repairing",
        "automobile"
    ],
    "wof:name":"Hogue Automotive",
    "wof:placetype":"venue"
},
  "geometry": {"coordinates":[-80.500395,41.211153],"type":"Point"}
}