{
  "type": "Feature",
  "properties": {
    "iso:country":"US",
    "sg:address":"646 Follett Run Rd",
    "sg:city":"Warren",
    "sg:classifiers":[
        {
            "category":"Building & Trades",
            "subcategory":"Construction",
            "type":"Services"
        }
    ],
    "sg:phone":"+1   ",
    "sg:postcode":"16365",
    "sg:province":"PA",
    "sg:tags":[
        "general",
        "contractor"
    ],
    "wof:name":"Doyle Construction",
    "wof:placetype":"venue"
},
  "geometry": {"coordinates":[-79.218806,41.879055],"type":"Point"}
}