{
  "type": "Feature",
  "properties": {
    "iso:country":"US",
    "sg:address":"409 W Pittsburgh St",
    "sg:city":"Greensburg",
    "sg:classifiers":[
        {
            "category":"Retail",
            "subcategory":"Funeral Services",
            "type":"Services"
        }
    ],
    "sg:phone":"+1 724 837 0020",
    "sg:postcode":"15601",
    "sg:province":"PA",
    "sg:tags":[
        "director"
    ],
    "sg:website":"www.pantalone.com",
    "wof:name":"Clement L Pantalone Funeral",
    "wof:placetype":"venue"
},
  "geometry": {"coordinates":[-79.551778,40.301018],"type":"Point"}
}