{
  "type": "Feature",
  "properties": {
    "addr:full":"424 Merchant St Ambridge PA 15003",
    "addr:housenumber":"424",
    "addr:postcode":"15003",
    "addr:street":"Merchant St",
    "iso:country":"US",
    "sg:address":"424 Merchant St",
    "sg:city":"Ambridge",
    "sg:classifiers":[
        {
            "category":"Building & Trades",
            "subcategory":"Construction",
            "type":"Services"
        }
    ],
    "sg:phone":"+1 724 266 1243",
    "sg:postcode":"15003",
    "sg:province":"PA",
    "sg:tags":[
        "remodeling",
        "contractor"
    ],
    "wof:name":"Tim Cassidy Remodeling",
    "wof:placetype":"venue"
},
  "geometry": {"coordinates":[-80.225939,40.584813],"type":"Point"}
}