{
  "type": "Feature",
  "properties": {
    "addr:full":"2510 Huntingdon Pike Huntingdon Valley PA 19006",
    "addr:housenumber":"2510",
    "addr:postcode":"19006",
    "addr:street":"Huntingdon Pike",
    "iso:country":"US",
    "sg:address":"2510 Huntingdon Pike",
    "sg:city":"Huntingdon Valley",
    "sg:classifiers":[
        {
            "category":"Building & Trades",
            "subcategory":"Plumbing",
            "type":"Services"
        }
    ],
    "sg:phone":"+1   ",
    "sg:postcode":"19006",
    "sg:province":"PA",
    "sg:tags":[
        "contractor"
    ],
    "wof:name":"Denco Plumbing",
    "wof:placetype":"venue"
},
  "geometry": {"coordinates":[-75.06319000000001,40.124538],"type":"Point"}
}