{
  "type": "Feature",
  "properties": {
    "iso:country":"US",
    "sg:address":"148 W Penn St",
    "sg:city":"Carlisle",
    "sg:classifiers":[
        {
            "category":"Organizations",
            "subcategory":"Community Association",
            "type":"Services"
        }
    ],
    "sg:phone":"+1 717 243 0021",
    "sg:postcode":"17013",
    "sg:province":"PA",
    "sg:tags":[
        "military"
    ],
    "wof:name":"Haines Stackfield American Lgn",
    "wof:placetype":"venue"
},
  "geometry": {"coordinates":[-77.1922,40.205593],"type":"Point"}
}