{
  "type": "Feature",
  "properties": {
    "addr:full":"913 Bullock Ave Lansdowne PA 19050",
    "addr:housenumber":"913",
    "addr:postcode":"19050",
    "addr:street":"Bullock Ave",
    "iso:country":"US",
    "sg:address":"913 Bullock Ave",
    "sg:city":"Lansdowne",
    "sg:classifiers":[
        {
            "category":"Professional",
            "subcategory":"Employment Agencies",
            "type":"Services"
        }
    ],
    "sg:phone":"+1   ",
    "sg:postcode":"19050",
    "sg:province":"PA",
    "sg:tags":[
        "refund",
        "specialist",
        "recovery"
    ],
    "wof:name":"WCbc Professional Bus Svcs",
    "wof:placetype":"venue"
},
  "geometry": {"coordinates":[-75.247496,39.928488],"type":"Point"}
}