{
  "type": "Feature",
  "properties": {
    "iso:country":"US",
    "sg:address":"170 McCracken Run Rd",
    "sg:city":"Du Bois",
    "sg:classifiers":[
        {
            "category":"Social Services",
            "type":"Services"
        }
    ],
    "sg:phone":"+1 814 371 1224",
    "sg:postcode":"15801",
    "sg:province":"PA",
    "sg:tags":[
        "worker"
    ],
    "wof:name":"Brenda Manno Msw Lsw",
    "wof:placetype":"venue"
},
  "geometry": {"coordinates":[-78.739062,41.133393],"type":"Point"}
}