{
  "type": "Feature",
  "properties": {
    "iso:country":"US",
    "sg:address":"740 E Cherry Rd",
    "sg:city":"Quakertown",
    "sg:classifiers":[
        {
            "category":"Building & Trades",
            "subcategory":"Construction",
            "type":"Services"
        }
    ],
    "sg:phone":"+1 215 538 1874",
    "sg:postcode":"18951",
    "sg:province":"PA",
    "sg:tags":[
        "masonry",
        "contractor"
    ],
    "sg:website":"www.mccarthymasonry.com",
    "wof:name":"McCarthy Masonry and Concrete",
    "wof:placetype":"venue"
},
  "geometry": {"coordinates":[-75.347381,40.475549],"type":"Point"}
}