{
  "type": "Feature",
  "properties": {
    "iso:country":"US",
    "sg:address":"237 Roanoke Way",
    "sg:city":"Imperial",
    "sg:classifiers":[
        {
            "category":"Professional",
            "subcategory":"Computer Services",
            "type":"Services"
        }
    ],
    "sg:phone":"+1   ",
    "sg:postcode":"15126",
    "sg:province":"PA",
    "sg:tags":[
        "related"
    ],
    "wof:name":"Kelley Dalton Inc",
    "wof:placetype":"venue"
},
  "geometry": {"coordinates":[-80.231905,40.441894],"type":"Point"}
}