{
  "type": "Feature",
  "properties": {
    "addr:full":"1825 W Chew St Allentown PA 18104",
    "addr:housenumber":"1825",
    "addr:postcode":"18104",
    "addr:street":"W Chew St",
    "iso:country":"US",
    "sg:address":"1825 W Chew St",
    "sg:city":"Allentown",
    "sg:classifiers":[
        {
            "category":"Food & Beverages",
            "subcategory":"Specialty",
            "type":"Retail Goods"
        }
    ],
    "sg:phone":"+1 610 432 1108",
    "sg:postcode":"18104",
    "sg:province":"PA",
    "sg:tags":[
        "poultry"
    ],
    "sg:website":"www.mrbills.com",
    "wof:name":"Mr Bill's Poultry & Deli",
    "wof:placetype":"venue"
},
  "geometry": {"coordinates":[-75.49841000000001,40.599715],"type":"Point"}
}