{
  "type": "Feature",
  "properties": {
    "iso:country":"US",
    "sg:address":"800 Chester Pike",
    "sg:city":"Sharon Hill",
    "sg:classifiers":[
        {
            "category":"Manufacturing",
            "subcategory":"Food",
            "type":"Manufacturing & Wholesale Goods"
        }
    ],
    "sg:phone":"+1 610 522 2650",
    "sg:postcode":"19079",
    "sg:province":"PA",
    "sg:tags":[
        "product",
        "manufacturer"
    ],
    "wof:name":"Jyoti Cuisine India-Gourmail",
    "wof:placetype":"venue"
},
  "geometry": {"coordinates":[-75.268916,39.911755],"type":"Point"}
}