{
  "type": "Feature",
  "properties": {
    "iso:country":"US",
    "sg:address":"300 Fox Chapel Rd",
    "sg:city":"Pittsburgh",
    "sg:classifiers":[
        {
            "category":"Insurance",
            "subcategory":"Hazard Insurance",
            "type":"Services"
        }
    ],
    "sg:phone":"+1 412 781 0778",
    "sg:postcode":"15238",
    "sg:province":"PA",
    "sg:tags":[
        "commercial",
        "business"
    ],
    "wof:name":"Wagner Agency Inc Insurance Res Of No",
    "wof:placetype":"venue"
},
  "geometry": {"coordinates":[-79.881378,40.492222],"type":"Point"}
}