{
  "type": "Feature",
  "properties": {
    "addr:full":"135 Ridge Rd Monongahela PA 15063",
    "addr:housenumber":"135",
    "addr:postcode":"15063",
    "addr:street":"Ridge Rd",
    "iso:country":"US",
    "sg:address":"135 Ridge Rd",
    "sg:city":"Monongahela",
    "sg:classifiers":[
        {
            "category":"Manufacturing",
            "subcategory":"Wood Products",
            "type":"Manufacturing & Wholesale Goods"
        }
    ],
    "sg:phone":"+1 724 258 6937",
    "sg:postcode":"15063",
    "sg:province":"PA",
    "sg:tags":[
        "millwork"
    ],
    "wof:name":"Monongahela Millwork",
    "wof:placetype":"venue"
},
  "geometry": {"coordinates":[-79.914687,40.204272],"type":"Point"}
}