{
  "type": "Feature",
  "properties": {
    "iso:country":"US",
    "sg:address":"221 Snyder Rd",
    "sg:city":"Hermitage",
    "sg:classifiers":[
        {
            "category":"Manufacturing",
            "subcategory":"Signs",
            "type":"Manufacturing & Wholesale Goods"
        }
    ],
    "sg:phone":"+1 724 983 1066",
    "sg:postcode":"16148",
    "sg:province":"PA",
    "sg:website":"www.mccpromotions.com",
    "wof:name":"Print ONE/Mcc",
    "wof:placetype":"venue"
},
  "geometry": {"coordinates":[-80.441784,41.234834],"type":"Point"}
}