{
  "type": "Feature",
  "properties": {
    "addr:full":"920 Harwick St Chester PA 19013",
    "addr:housenumber":"920",
    "addr:postcode":"19013",
    "addr:street":"Harwick St",
    "iso:country":"US",
    "sg:address":"920 Harwick St",
    "sg:city":"Chester",
    "sg:classifiers":[
        {
            "category":"Building & Trades",
            "subcategory":"Plumbing",
            "type":"Services"
        }
    ],
    "sg:phone":"+1   ",
    "sg:postcode":"19013",
    "sg:province":"PA",
    "sg:tags":[
        "contractor"
    ],
    "wof:name":"Allstar Services",
    "wof:placetype":"venue"
},
  "geometry": {"coordinates":[-75.39787,39.835974],"type":"Point"}
}