{
  "type": "Feature",
  "properties": {
    "iso:country":"US",
    "sg:address":"526 Elm St",
    "sg:city":"Tionesta",
    "sg:classifiers":[
        {
            "category":"Education",
            "subcategory":"College",
            "type":"Public Place"
        }
    ],
    "sg:phone":"+1   ",
    "sg:postcode":"16353",
    "sg:province":"PA",
    "sg:tags":[
        "university"
    ],
    "wof:name":"Forest County Cooperative EXT",
    "wof:placetype":"venue"
},
  "geometry": {"coordinates":[-79.456236,41.496762],"type":"Point"}
}