{
  "type": "Feature",
  "properties": {
    "iso:country":"US",
    "sg:address":"3326 York Rd",
    "sg:city":"Furlong",
    "sg:classifiers":[
        {
            "category":"Personal",
            "type":"Services"
        }
    ],
    "sg:phone":"+1 215 794 2676",
    "sg:postcode":"18925",
    "sg:province":"PA",
    "sg:tags":[
        "therapist",
        "massage"
    ],
    "wof:name":"Warwick Wellness Ctr",
    "wof:placetype":"venue"
},
  "geometry": {"coordinates":[-75.083348,40.290582],"type":"Point"}
}