{
  "type": "Feature",
  "properties": {
    "addr:full":"718 Milford Rd East Stroudsburg PA 18301",
    "addr:housenumber":"718",
    "addr:postcode":"18301",
    "addr:street":"Milford Rd",
    "iso:country":"US",
    "sg:address":"718 Milford Rd",
    "sg:city":"East Stroudsburg",
    "sg:classifiers":[
        {
            "category":"Building & Trades",
            "subcategory":"Construction",
            "type":"Services"
        }
    ],
    "sg:phone":"+1 570 421 9820",
    "sg:postcode":"18301",
    "sg:province":"PA",
    "sg:tags":[
        "house",
        "builder",
        "home"
    ],
    "wof:name":"Nuwaze Custom Homes",
    "wof:placetype":"venue"
},
  "geometry": {"coordinates":[-75.17973600000001,41.019139],"type":"Point"}
}