{
  "type": "Feature",
  "properties": {
    "addr:full":"474 Hickman St Bridgeville PA 15017",
    "addr:housenumber":"474",
    "addr:postcode":"15017",
    "addr:street":"Hickman St",
    "iso:country":"US",
    "sg:address":"474 Hickman St",
    "sg:city":"Bridgeville",
    "sg:classifiers":[
        {
            "category":"Building & Trades",
            "subcategory":"Construction",
            "type":"Services"
        }
    ],
    "sg:phone":"+1 800 896 5655",
    "sg:postcode":"15017",
    "sg:province":"PA",
    "sg:tags":[
        "contractor"
    ],
    "sg:website":"www.atechrefrigeration.com",
    "wof:name":"A-Tech refrigeration of Pittsburgh",
    "wof:placetype":"venue"
},
  "geometry": {"coordinates":[-80.11687000000001,40.358497],"type":"Point"}
}