{
  "type": "Feature",
  "properties": {
    "iso:country":"US",
    "sg:address":"105 Brierley Ct",
    "sg:city":"Downingtown",
    "sg:classifiers":[
        {
            "category":"Building & Trades",
            "subcategory":"Construction",
            "type":"Services"
        }
    ],
    "sg:phone":"+1 610 524 6250",
    "sg:postcode":"19335",
    "sg:province":"PA",
    "sg:tags":[
        "general",
        "contractor"
    ],
    "wof:name":"Truco Construction Co",
    "wof:placetype":"venue"
},
  "geometry": {"coordinates":[-75.688559,40.049307],"type":"Point"}
}