{
  "type": "Feature",
  "properties": {
    "iso:country":"US",
    "sg:address":"246 Green Lane Dr",
    "sg:city":"Camp Hill",
    "sg:classifiers":[
        {
            "category":"Building & Trades",
            "subcategory":"Construction",
            "type":"Services"
        }
    ],
    "sg:phone":"+1   ",
    "sg:postcode":"17011",
    "sg:province":"PA",
    "sg:tags":[
        "carpentry",
        "contractor"
    ],
    "wof:name":"Pinchock Carpentry",
    "wof:placetype":"venue"
},
  "geometry": {"coordinates":[-76.89776999999999,40.215054],"type":"Point"}
}