{
  "type": "Feature",
  "properties": {
    "addr:full":"1905 E 3rd St Williamsport PA 17701",
    "addr:housenumber":"1905",
    "addr:postcode":"17701",
    "addr:street":"E 3Rd St",
    "iso:country":"US",
    "sg:address":"1905 E 3rd St",
    "sg:city":"Williamsport",
    "sg:classifiers":[
        {
            "category":"Shopping",
            "subcategory":"Computers & Home Electronics",
            "type":"Retail Goods"
        }
    ],
    "sg:phone":"+1 570 326 2346",
    "sg:postcode":"17701",
    "sg:province":"PA",
    "sg:website":"www.radioshack.com",
    "wof:name":"Radio Shack",
    "wof:placetype":"venue"
},
  "geometry": {"coordinates":[-76.961142,41.248347],"type":"Point"}
}