{
  "type": "Feature",
  "properties": {
    "iso:country":"US",
    "sg:address":"110 Lincoln Hwy",
    "sg:city":"Fairless Hills",
    "sg:classifiers":[
        {
            "category":"Restaurant",
            "type":"Food & Drink"
        }
    ],
    "sg:menulink":"http://www.allmenus.com/pa/falls/229698-slacks-hoagie-shack/menu/",
    "sg:phone":"+1 215 949 0200",
    "sg:postcode":"19030",
    "sg:province":"PA",
    "sg:tags":[
        "wrap",
        "american",
        "sandwich"
    ],
    "wof:name":"Slack's Hoagie Shack",
    "wof:placetype":"venue"
},
  "geometry": {"coordinates":[-74.868157,40.180836],"type":"Point"}
}