{
  "type": "Feature",
  "properties": {
    "iso:country":"US",
    "sg:address":"422 Old Baltimore Pike",
    "sg:city":"Chadds Ford",
    "sg:classifiers":[
        {
            "category":"Real Estate",
            "subcategory":"Real Estate Operator",
            "type":"Services"
        }
    ],
    "sg:phone":"+1   ",
    "sg:postcode":"19317",
    "sg:province":"PA",
    "sg:tags":[
        "building",
        "nonresidential"
    ],
    "wof:name":"Cicconi Land Corporation",
    "wof:placetype":"venue"
},
  "geometry": {"coordinates":[-75.617924,39.872977],"type":"Point"}
}