{
  "type": "Feature",
  "properties": {
    "iso:country":"US",
    "sg:address":"1064 Rising Sun Rd",
    "sg:city":"Laurys Station",
    "sg:classifiers":[
        {
            "category":"Building & Trades",
            "subcategory":"Construction",
            "type":"Services"
        }
    ],
    "sg:phone":"+1   ",
    "sg:postcode":"18059",
    "sg:province":"PA",
    "sg:tags":[
        "contractor"
    ],
    "wof:name":"Haneys Ldscp Design Trctr Svc",
    "wof:placetype":"venue"
},
  "geometry": {"coordinates":[-75.534209,40.72348],"type":"Point"}
}