{
  "type": "Feature",
  "properties": {
    "iso:country":"US",
    "sg:address":"2627 Robert Fulton Hwy",
    "sg:city":"Peach Bottom",
    "sg:classifiers":[
        {
            "category":"Building & Trades",
            "subcategory":"Construction",
            "type":"Services"
        }
    ],
    "sg:phone":"+1 717 548 0975",
    "sg:postcode":"17563",
    "sg:province":"PA",
    "sg:tags":[
        "hanging",
        "painter",
        "contractor"
    ],
    "wof:name":"Crotti's Painting",
    "wof:placetype":"venue"
},
  "geometry": {"coordinates":[-76.154163,39.727494],"type":"Point"}
}