{
  "type": "Feature",
  "properties": {
    "iso:country":"US",
    "sg:address":"109 Tall Oak Dr",
    "sg:city":"New Cumberland",
    "sg:classifiers":[
        {
            "category":"Restaurant",
            "type":"Food & Drink"
        }
    ],
    "sg:phone":"+1   ",
    "sg:postcode":"17070",
    "sg:province":"PA",
    "sg:tags":[
        "eating"
    ],
    "wof:name":"McDonald 2133",
    "wof:placetype":"venue"
},
  "geometry": {"coordinates":[-76.88649599999999,40.204758],"type":"Point"}
}