{
  "type": "Feature",
  "properties": {
    "iso:country":"US",
    "sg:address":"717 N Arch St",
    "sg:city":"Allentown",
    "sg:classifiers":[
        {
            "category":"Building & Trades",
            "subcategory":"Construction",
            "type":"Services"
        }
    ],
    "sg:phone":"+1 610 821 5634",
    "sg:postcode":"18104",
    "sg:province":"PA",
    "sg:tags":[
        "general",
        "contractor"
    ],
    "wof:name":"Penn Construction Co",
    "wof:placetype":"venue"
},
  "geometry": {"coordinates":[-75.52364,40.600323],"type":"Point"}
}