{
  "type": "Feature",
  "properties": {
    "iso:country":"US",
    "sg:address":"48 New Schaefferstown Rd",
    "sg:city":"Bernville",
    "sg:classifiers":[
        {
            "category":"Travel",
            "subcategory":"Campground",
            "type":"Entertainment"
        }
    ],
    "sg:phone":"+1 717 933 8902",
    "sg:postcode":"19506",
    "sg:province":"PA",
    "sg:tags":[
        "camp"
    ],
    "wof:name":"Campcamp Calvery",
    "wof:placetype":"venue"
},
  "geometry": {"coordinates":[-76.225148,40.453869],"type":"Point"}
}