{
  "type": "Feature",
  "properties": {
    "iso:country":"US",
    "sg:address":"1175 Manheim Pike",
    "sg:city":"Lancaster",
    "sg:classifiers":[
        {
            "category":"Home & Garden",
            "subcategory":"Garden Supply",
            "type":"Retail Goods"
        },
        {
            "category":"Manufacturing",
            "subcategory":"Paper Products",
            "type":"Manufacturing & Wholesale Goods"
        }
    ],
    "sg:phone":"+1 717 394 4449",
    "sg:postcode":"17601",
    "sg:province":"PA",
    "sg:tags":[
        "bamboo"
    ],
    "wof:name":"Stirling Ventures Inc",
    "wof:placetype":"venue"
},
  "geometry": {"coordinates":[-76.318747,40.059134],"type":"Point"}
}