{
  "type": "Feature",
  "properties": {
    "iso:country":"US",
    "sg:address":"4411 N 5th Street Hwy",
    "sg:city":"Temple",
    "sg:classifiers":[
        {
            "category":"Home & Garden",
            "subcategory":"Furniture",
            "type":"Retail Goods"
        }
    ],
    "sg:phone":"+1 610 921 3136",
    "sg:postcode":"19560",
    "sg:province":"PA",
    "sg:tags":[
        "water",
        "bed"
    ],
    "wof:name":"House Of Slumber Waterbeds",
    "wof:placetype":"venue"
},
  "geometry": {"coordinates":[-75.92753500000001,40.401813],"type":"Point"}
}