{
  "type": "Feature",
  "properties": {
    "iso:country":"US",
    "sg:address":"1061 Waterdam Plaza Dr # 202",
    "sg:city":"Canonsburg",
    "sg:classifiers":[
        {
            "category":"Real Estate",
            "subcategory":"Developer",
            "type":"Services"
        }
    ],
    "sg:phone":"+1 724 941 4013",
    "sg:postcode":"15317",
    "sg:province":"PA",
    "wof:name":"Hardy Enterprises, Inc.",
    "wof:placetype":"venue"
},
  "geometry": {"coordinates":[-80.133734,40.262699],"type":"Point"}
}