{
  "type": "Feature",
  "properties": {
    "iso:country":"US",
    "sg:address":"20 Chapel Rd",
    "sg:city":"Birdsboro",
    "sg:classifiers":[
        {
            "category":"Freight",
            "type":"Transportation"
        }
    ],
    "sg:phone":"+1 610 286 3740",
    "sg:postcode":"19508",
    "sg:province":"PA",
    "sg:tags":[
        "broker",
        "trucking"
    ],
    "wof:name":"Three Rivers Brokerage",
    "wof:placetype":"venue"
},
  "geometry": {"coordinates":[-75.84318500000001,40.21002],"type":"Point"}
}