{
  "type": "Feature",
  "properties": {
    "iso:country":"US",
    "sg:address":"472 Old Bethlehem Rd",
    "sg:city":"Quakertown",
    "sg:classifiers":[
        {
            "category":"Real Estate",
            "subcategory":"Real Estate Agent",
            "type":"Services"
        }
    ],
    "sg:phone":"+1 215 536 6800",
    "sg:postcode":"18951",
    "sg:province":"PA",
    "wof:name":"Cope Real Estate",
    "wof:placetype":"venue"
},
  "geometry": {"coordinates":[-75.268148,40.46054],"type":"Point"}
}