{
  "type": "Feature",
  "properties": {
    "addr:full":"2711 N 4th St Harrisburg PA 17110",
    "addr:housenumber":"2711",
    "addr:postcode":"17110",
    "addr:street":"N 4Th St",
    "iso:country":"US",
    "sg:address":"2711 N 4th St",
    "sg:city":"Harrisburg",
    "sg:classifiers":[
        {
            "category":"Shopping",
            "subcategory":"Clothing, Apparel, & Fashions",
            "type":"Retail Goods"
        }
    ],
    "sg:phone":"+1 717 232 2918",
    "sg:postcode":"17110",
    "sg:province":"PA",
    "sg:tags":[
        "designer"
    ],
    "wof:name":"Fantasy Factory Designs Studio",
    "wof:placetype":"venue"
},
  "geometry": {"coordinates":[-76.899441,40.291323],"type":"Point"}
}