{
  "type": "Feature",
  "properties": {
    "iso:country":"US",
    "sg:address":"2608 E County Line Rd",
    "sg:city":"Ardmore",
    "sg:classifiers":[
        {
            "category":"Personal",
            "subcategory":"Beauty Salon",
            "type":"Services"
        }
    ],
    "sg:phone":"+1 610 896 5334",
    "sg:postcode":"19003",
    "sg:province":"PA",
    "sg:tags":[
        "shop"
    ],
    "wof:name":"Joyce's Hair Fashions",
    "wof:placetype":"venue"
},
  "geometry": {"coordinates":[-75.295464,39.999989],"type":"Point"}
}