{
  "type": "Feature",
  "properties": {
    "addr:full":"682 Central Manor Rd Lancaster PA 17603",
    "addr:housenumber":"682",
    "addr:postcode":"17603",
    "addr:street":"Central Manor Rd",
    "iso:country":"US",
    "sg:address":"682 Central Manor Rd",
    "sg:city":"Lancaster",
    "sg:classifiers":[
        {
            "category":"Retail",
            "subcategory":"Auto Repair",
            "type":"Services"
        }
    ],
    "sg:phone":"+1 717 285 5650",
    "sg:postcode":"17603",
    "sg:province":"PA",
    "sg:tags":[
        "machine",
        "automobile",
        "shop"
    ],
    "wof:name":"Scott's Automotive Machine",
    "wof:placetype":"venue"
},
  "geometry": {"coordinates":[-76.431944,40.010734],"type":"Point"}
}