{
  "type": "Feature",
  "properties": {
    "addr:full":"4804 Mooreridge Dr Pittsburgh PA 15227",
    "addr:housenumber":"4804",
    "addr:postcode":"15227",
    "addr:street":"Mooreridge Dr",
    "iso:country":"US",
    "sg:address":"4804 Mooreridge Dr",
    "sg:city":"Pittsburgh",
    "sg:classifiers":[
        {
            "category":"Building & Trades",
            "subcategory":"Construction",
            "type":"Services"
        }
    ],
    "sg:phone":"+1 412 885 8855",
    "sg:postcode":"15227",
    "sg:province":"PA",
    "sg:tags":[
        "general",
        "contractor"
    ],
    "wof:name":"Bruno Delsey & Son",
    "wof:placetype":"venue"
},
  "geometry": {"coordinates":[-79.971143,40.362891],"type":"Point"}
}