{
  "type": "Feature",
  "properties": {
    "addr:full":"270 S 11th St Philadelphia PA 19107",
    "addr:housenumber":"270",
    "addr:postcode":"19107",
    "addr:street":"S 11Th St",
    "iso:country":"US",
    "sg:address":"270 S 11th St",
    "sg:city":"Philadelphia",
    "sg:classifiers":[
        {
            "category":"Personal",
            "subcategory":"Barber",
            "type":"Services"
        }
    ],
    "sg:phone":"+1 215 925 3505",
    "sg:postcode":"19107",
    "sg:province":"PA",
    "sg:tags":[
        "shop"
    ],
    "wof:name":"2 B Groomed Barbering Studio",
    "wof:placetype":"venue"
},
  "geometry": {"coordinates":[-75.159491,39.946362],"type":"Point"}
}