{
  "type": "Feature",
  "properties": {
    "iso:country":"US",
    "sg:address":"1376 Franklin Mills Cir",
    "sg:city":"Philadelphia",
    "sg:classifiers":[
        {
            "category":"Manufacturing",
            "subcategory":"Leather Goods",
            "type":"Manufacturing & Wholesale Goods"
        }
    ],
    "sg:phone":"+1 215 632 4300",
    "sg:postcode":"19154",
    "sg:province":"PA",
    "wof:name":"Leather Works Inc",
    "wof:placetype":"venue"
},
  "geometry": {"coordinates":[-74.95908,40.086924],"type":"Point"}
}