{
  "type": "Feature",
  "properties": {
    "addr:full":"115 Chestnut St Philadelphia PA 19106",
    "addr:housenumber":"115",
    "addr:postcode":"19106",
    "addr:street":"Chestnut St",
    "iso:country":"US",
    "sg:address":"115 Chestnut St",
    "sg:city":"Philadelphia",
    "sg:classifiers":[
        {
            "category":"Professional",
            "subcategory":"Printing & Photocopies",
            "type":"Services"
        }
    ],
    "sg:phone":"+1   ",
    "sg:postcode":"19106",
    "sg:province":"PA",
    "wof:name":"Medical Legal Reproductions",
    "wof:placetype":"venue"
},
  "geometry": {"coordinates":[-75.14408,39.948378],"type":"Point"}
}