{
  "type": "Feature",
  "properties": {
    "addr:full":"137 W Knowlton Rd Media PA 19063",
    "addr:housenumber":"137",
    "addr:postcode":"19063",
    "addr:street":"W Knowlton Rd",
    "iso:country":"US",
    "sg:address":"137 W Knowlton Rd",
    "sg:city":"Media",
    "sg:classifiers":[
        {
            "category":"Food & Beverages",
            "subcategory":"Fruits & Vegetables",
            "type":"Retail Goods"
        }
    ],
    "sg:phone":"+1 610 876 7116",
    "sg:postcode":"19063",
    "sg:province":"PA",
    "sg:tags":[
        "farm",
        "market"
    ],
    "sg:website":"www.linvilla.com",
    "wof:name":"Linvilla Orchards",
    "wof:placetype":"venue"
},
  "geometry": {"coordinates":[-75.428088,39.869177],"type":"Point"}
}