{
  "type": "Feature",
  "properties": {
    "iso:country":"US",
    "sg:address":"9620 Donation Rd",
    "sg:city":"Waterford",
    "sg:classifiers":[
        {
            "category":"Bars & Pubs",
            "type":"Food & Drink"
        }
    ],
    "sg:phone":"+1   ",
    "sg:postcode":"16441",
    "sg:province":"PA",
    "sg:tags":[
        "bar"
    ],
    "wof:name":"Shakespiers Waterfront Bar",
    "wof:placetype":"venue"
},
  "geometry": {"coordinates":[-80.005133,42.033593],"type":"Point"}
}