{
  "type": "Feature",
  "properties": {
    "iso:country":"US",
    "sg:address":"1405 Grasshopper Rd",
    "sg:city":"Huntingdon Valley",
    "sg:classifiers":[
        {
            "category":"Recreation",
            "type":"Entertainment"
        }
    ],
    "sg:phone":"+1   ",
    "sg:postcode":"19006",
    "sg:province":"PA",
    "sg:tags":[
        "club",
        "membership"
    ],
    "wof:name":"Siberian Husky Club of De",
    "wof:placetype":"venue"
},
  "geometry": {"coordinates":[-75.087953,40.128464],"type":"Point"}
}