{
  "type": "Feature",
  "properties": {
    "iso:country":"US",
    "sg:address":"1204 Wabank Rd",
    "sg:city":"Lancaster",
    "sg:classifiers":[
        {
            "category":"Organizations",
            "subcategory":"Religious Organization",
            "type":"Services"
        }
    ],
    "sg:phone":"+1 717 393 3431",
    "sg:postcode":"17603",
    "sg:province":"PA",
    "wof:name":"Faith United Church Of Christ",
    "wof:placetype":"venue"
},
  "geometry": {"coordinates":[-76.31801,40.022179],"type":"Point"}
}