{
  "type": "Feature",
  "properties": {
    "iso:country":"US",
    "sg:address":"66 Lions Dr",
    "sg:city":"Morrisville",
    "sg:classifiers":[
        {
            "category":"Building & Trades",
            "subcategory":"Electrical",
            "type":"Services"
        }
    ],
    "sg:phone":"+1 215 736 9440",
    "sg:postcode":"19067",
    "sg:province":"PA",
    "sg:tags":[
        "electrical",
        "electric",
        "contractor"
    ],
    "wof:name":"Grover A W Electric",
    "wof:placetype":"venue"
},
  "geometry": {"coordinates":[-74.827173,40.20239],"type":"Point"}
}