{
  "type": "Feature",
  "properties": {
    "addr:full":"1201 Chestnut St Philadelphia PA 19107",
    "addr:housenumber":"1201",
    "addr:postcode":"19107",
    "addr:street":"Chestnut St",
    "iso:country":"US",
    "sg:address":"1201 Chestnut St",
    "sg:city":"Philadelphia",
    "sg:classifiers":[
        {
            "category":"Professional",
            "subcategory":"Lawyer & Legal Services",
            "type":"Services"
        }
    ],
    "sg:phone":"+1 215 563 2541",
    "sg:postcode":"19107",
    "sg:province":"PA",
    "wof:name":"Miller Irwin Atty",
    "wof:placetype":"venue"
},
  "geometry": {"coordinates":[-75.160202,39.9505],"type":"Point"}
}