{
  "type": "Feature",
  "properties": {
    "addr:full":"399 Dartmouth Ct Bensalem PA 19020",
    "addr:housenumber":"399",
    "addr:postcode":"19020",
    "addr:street":"Dartmouth Ct",
    "iso:country":"US",
    "sg:address":"399 Dartmouth Ct",
    "sg:city":"Bensalem",
    "sg:classifiers":[
        {
            "category":"Professional",
            "subcategory":"Management & Consulting",
            "type":"Services"
        }
    ],
    "sg:phone":"+1   ",
    "sg:postcode":"19020",
    "sg:province":"PA",
    "wof:name":"Alphamed",
    "wof:placetype":"venue"
},
  "geometry": {"coordinates":[-74.907051,40.10983],"type":"Point"}
}