{
  "type": "Feature",
  "properties": {
    "iso:country":"US",
    "sg:address":"492 Cove St",
    "sg:city":"Everett",
    "sg:classifiers":[
        {
            "category":"Shopping",
            "subcategory":"Gifts & Souvenirs",
            "type":"Retail Goods"
        }
    ],
    "sg:phone":"+1   ",
    "sg:postcode":"15537",
    "sg:province":"PA",
    "wof:name":"Country Pastthymes",
    "wof:placetype":"venue"
},
  "geometry": {"coordinates":[-78.323205,40.041034],"type":"Point"}
}