{
  "type": "Feature",
  "properties": {
    "iso:country":"US",
    "sg:address":"210 W Cheltenham Ave",
    "sg:city":"Philadelphia",
    "sg:classifiers":[
        {
            "category":"Professional",
            "type":"Services"
        }
    ],
    "sg:phone":"+1 215 548 9280",
    "sg:postcode":"19126",
    "sg:province":"PA",
    "sg:tags":[
        "establishment"
    ],
    "wof:name":"Liberty Estates",
    "wof:placetype":"venue"
},
  "geometry": {"coordinates":[-75.123268,40.053618],"type":"Point"}
}