{
  "type": "Feature",
  "properties": {
    "iso:country":"US",
    "sg:address":"587 DeKalb Pike",
    "sg:city":"North Wales",
    "sg:classifiers":[
        {
            "category":"Restaurant",
            "type":"Food & Drink"
        }
    ],
    "sg:phone":"+1 215 699 3361",
    "sg:postcode":"19454",
    "sg:province":"PA",
    "sg:tags":[
        "italian"
    ],
    "sg:website":"www.baccobacco.com",
    "wof:name":"Bacco",
    "wof:placetype":"venue"
},
  "geometry": {"coordinates":[-75.24773,40.21874],"type":"Point"}
}