{
  "type": "Feature",
  "properties": {
    "iso:country":"US",
    "sg:address":"40 S Main St",
    "sg:city":"Loganville",
    "sg:classifiers":[
        {
            "category":"Organizations",
            "subcategory":"Religious Organization",
            "type":"Services"
        }
    ],
    "sg:phone":"+1 717 428 0117",
    "sg:postcode":"17360",
    "sg:province":"PA",
    "sg:tags":[
        "church"
    ],
    "wof:name":"Emanuel United Methodist Chr",
    "wof:placetype":"venue"
},
  "geometry": {"coordinates":[-76.708679,39.853739],"type":"Point"}
}