{
  "type": "Feature",
  "properties": {
    "addr:full":"344 Spence Rd Indiana PA 15701",
    "addr:housenumber":"344",
    "addr:postcode":"15701",
    "addr:street":"Spence Rd",
    "iso:country":"US",
    "sg:address":"344 Spence Rd",
    "sg:city":"Indiana",
    "sg:phone":"+1   ",
    "sg:postcode":"15701",
    "sg:province":"PA",
    "sg:tags":[
        "farm"
    ],
    "wof:name":"Yarnicks Farm",
    "wof:placetype":"venue"
},
  "geometry": {"coordinates":[-79.24827399999999,40.67523],"type":"Point"}
}