{
  "type": "Feature",
  "properties": {
    "iso:country":"US",
    "sg:address":"195 Broad St",
    "sg:city":"Leetsdale",
    "sg:classifiers":[
        {
            "category":"Travel",
            "subcategory":"Hotels & Motels",
            "type":"Entertainment"
        }
    ],
    "sg:phone":"+1 724 251 0852",
    "sg:postcode":"15056",
    "sg:province":"PA",
    "sg:tags":[
        "breakfast",
        "accommodation",
        "bed"
    ],
    "wof:name":"Whistlestop Bed & Breakfast",
    "wof:placetype":"venue"
},
  "geometry": {"coordinates":[-80.207211,40.56378],"type":"Point"}
}