{
  "type": "Feature",
  "properties": {
    "iso:country":"US",
    "sg:address":"162 Royal Oak Dr",
    "sg:city":"Butler",
    "sg:classifiers":[
        {
            "category":"Food & Beverages",
            "subcategory":"Bakery",
            "type":"Retail Goods"
        }
    ],
    "sg:phone":"+1   ",
    "sg:postcode":"16002",
    "sg:province":"PA",
    "wof:name":"TLC Flowers",
    "wof:placetype":"venue"
},
  "geometry": {"coordinates":[-79.953115,40.755297],"type":"Point"}
}