{
  "type": "Feature",
  "properties": {
    "iso:country":"US",
    "sg:address":"711 Hamilton St 2nd Floor",
    "sg:city":"Allentown",
    "sg:classifiers":[
        {
            "category":"Personal",
            "subcategory":"Tattoo Parlor",
            "type":"Services"
        }
    ],
    "sg:phone":"+1 570 778 6443",
    "sg:postcode":"18101",
    "sg:province":"PA",
    "sg:website":"myspace.com/cberzerko",
    "wof:name":"NYF Ink",
    "wof:placetype":"venue"
},
  "geometry": {"coordinates":[-75.47248999999999,40.60227],"type":"Point"}
}