{
  "type": "Feature",
  "properties": {
    "addr:full":"416 Short Run Rd Galeton PA 16922",
    "addr:housenumber":"416",
    "addr:postcode":"16922",
    "addr:street":"Short Run Rd",
    "iso:country":"US",
    "sg:address":"416 Short Run Rd",
    "sg:city":"Galeton",
    "sg:classifiers":[
        {
            "category":"Professional",
            "subcategory":"Business Services",
            "type":"Services"
        }
    ],
    "sg:phone":"+1 814 435 8274",
    "sg:postcode":"16922",
    "sg:province":"PA",
    "sg:tags":[
        "consultant",
        "coach"
    ],
    "wof:name":"Branch West Consulting",
    "wof:placetype":"venue"
},
  "geometry": {"coordinates":[-77.753805,41.617539],"type":"Point"}
}