{
  "type": "Feature",
  "properties": {
    "iso:country":"US",
    "sg:address":"436 Jefferson Ave",
    "sg:city":"Scranton",
    "sg:classifiers":[
        {
            "category":"Professional",
            "subcategory":"Lawyer & Legal Services",
            "type":"Services"
        }
    ],
    "sg:phone":"+1 570 961 1064",
    "sg:postcode":"18510",
    "sg:province":"PA",
    "sg:tags":[
        "attorney"
    ],
    "wof:name":"Roth & Dempsey",
    "wof:placetype":"venue"
},
  "geometry": {"coordinates":[-75.65765,41.409465],"type":"Point"}
}