{
  "type": "Feature",
  "properties": {
    "iso:country":"US",
    "sg:address":"1079 Ridge Rd",
    "sg:city":"Gettysburg",
    "sg:classifiers":[
        {
            "category":"Building & Trades",
            "subcategory":"Construction",
            "type":"Services"
        }
    ],
    "sg:phone":"+1 717 334 1249",
    "sg:postcode":"17325",
    "sg:province":"PA",
    "sg:tags":[
        "drywall",
        "contractor"
    ],
    "wof:name":"Heiges Exterior System",
    "wof:placetype":"venue"
},
  "geometry": {"coordinates":[-77.254558,39.759434],"type":"Point"}
}