{
  "type": "Feature",
  "properties": {
    "addr:full":"5515 Meadville Rd New Holland PA 17557",
    "addr:housenumber":"5515",
    "addr:postcode":"17557",
    "addr:street":"Meadville Rd",
    "iso:country":"US",
    "sg:address":"5515 Meadville Rd",
    "sg:city":"New Holland",
    "sg:classifiers":[
        {
            "category":"Building & Trades",
            "subcategory":"Construction",
            "type":"Services"
        }
    ],
    "sg:phone":"+1 717 354 7517",
    "sg:postcode":"17557",
    "sg:province":"PA",
    "sg:tags":[
        "woodworker"
    ],
    "wof:name":"Smucker Bros",
    "wof:placetype":"venue"
},
  "geometry": {"coordinates":[-76.006626,40.063551],"type":"Point"}
}