{
  "type": "Feature",
  "properties": {
    "iso:country":"US",
    "sg:address":"7449 Old Easton Rd",
    "sg:city":"Pipersville",
    "sg:classifiers":[
        {
            "category":"Manufacturing",
            "subcategory":"Furniture",
            "type":"Manufacturing & Wholesale Goods"
        }
    ],
    "sg:phone":"+1   ",
    "sg:postcode":"18947",
    "sg:province":"PA",
    "sg:tags":[
        "household",
        "mfg"
    ],
    "wof:name":"Dingeldezeins",
    "wof:placetype":"venue"
},
  "geometry": {"coordinates":[-75.14833299999999,40.443532],"type":"Point"}
}