{
  "type": "Feature",
  "properties": {
    "addr:full":"1030 E Main St Bradford PA 16701",
    "addr:housenumber":"1030",
    "addr:postcode":"16701",
    "addr:street":"E Main St",
    "iso:country":"US",
    "sg:address":"1030 E Main St",
    "sg:city":"Bradford",
    "sg:classifiers":[
        {
            "category":"Retail",
            "subcategory":"Auto Repair",
            "type":"Services"
        }
    ],
    "sg:phone":"+1 814 362 6888",
    "sg:postcode":"16701",
    "sg:province":"PA",
    "sg:tags":[
        "repairing",
        "automobile",
        "exhaust"
    ],
    "wof:name":"Monro Muffler Brake & Svc",
    "wof:placetype":"venue"
},
  "geometry": {"coordinates":[-78.617294,41.978997],"type":"Point"}
}