{
  "type": "Feature",
  "properties": {
    "iso:country":"US",
    "sg:address":"269 Dairy Ln",
    "sg:city":"Palmyra",
    "sg:classifiers":[
        {
            "category":"Retail",
            "subcategory":"Animal Services",
            "type":"Services"
        }
    ],
    "sg:phone":"+1 717 469 7507",
    "sg:postcode":"17078",
    "sg:province":"PA",
    "sg:tags":[
        "cat",
        "dog",
        "kennel"
    ],
    "wof:name":"Allmac's Kennel",
    "wof:placetype":"venue"
},
  "geometry": {"coordinates":[-76.63954,40.350685],"type":"Point"}
}