{
  "type": "Feature",
  "properties": {
    "iso:country":"US",
    "sg:address":"642 Lake St",
    "sg:city":"Lancaster",
    "sg:classifiers":[
        {
            "category":"Professional",
            "subcategory":"Management & Consulting",
            "type":"Services"
        }
    ],
    "sg:phone":"+1 717 509 7832",
    "sg:postcode":"17603",
    "sg:province":"PA",
    "sg:tags":[
        "consultant"
    ],
    "wof:name":"Brown Consulting",
    "wof:placetype":"venue"
},
  "geometry": {"coordinates":[-76.319425,40.037223],"type":"Point"}
}