{
  "type": "Feature",
  "properties": {
    "iso:country":"US",
    "sg:address":"4718 Rorer St",
    "sg:city":"Philadelphia",
    "sg:classifiers":[
        {
            "category":"Organizations",
            "subcategory":"Religious Organization",
            "type":"Services"
        }
    ],
    "sg:phone":"+1   ",
    "sg:postcode":"19120",
    "sg:province":"PA",
    "wof:name":"Brotherly Church of God",
    "wof:placetype":"venue"
},
  "geometry": {"coordinates":[-75.11445999999999,40.021618],"type":"Point"}
}