{
  "type": "Feature",
  "properties": {
    "iso:country":"US",
    "sg:address":"940 Cagni Dr",
    "sg:city":"Canonsburg",
    "sg:classifiers":[
        {
            "category":"Building & Trades",
            "subcategory":"Construction",
            "type":"Services"
        }
    ],
    "sg:phone":"+1 724 941 9730",
    "sg:postcode":"15317",
    "sg:province":"PA",
    "sg:tags":[
        "masonry",
        "contractor"
    ],
    "wof:name":"Joseph Cagni & Sons",
    "wof:placetype":"venue"
},
  "geometry": {"coordinates":[-80.102412,40.295902],"type":"Point"}
}