{
  "type": "Feature",
  "properties": {
    "addr:full":"703 Overlook Dr Bethlehem PA 18017",
    "addr:housenumber":"703",
    "addr:postcode":"18017",
    "addr:street":"Overlook Dr",
    "iso:country":"US",
    "sg:address":"703 Overlook Dr",
    "sg:city":"Bethlehem",
    "sg:classifiers":[
        {
            "category":"Real Estate",
            "subcategory":"Real Estate Agent",
            "type":"Services"
        }
    ],
    "sg:phone":"+1   ",
    "sg:postcode":"18017",
    "sg:province":"PA",
    "wof:name":"Landlord Assoc",
    "wof:placetype":"venue"
},
  "geometry": {"coordinates":[-75.39527,40.658499],"type":"Point"}
}