{
  "type": "Feature",
  "properties": {
    "addr:full":"179 W Broad St Telford PA 18969",
    "addr:housenumber":"179",
    "addr:postcode":"18969",
    "addr:street":"W Broad St",
    "iso:country":"US",
    "sg:address":"179 W Broad St",
    "sg:city":"Telford",
    "sg:classifiers":[
        {
            "category":"Home & Garden",
            "subcategory":"Furniture",
            "type":"Retail Goods"
        }
    ],
    "sg:phone":"+1 215 721 2249",
    "sg:postcode":"18969",
    "sg:province":"PA",
    "sg:tags":[
        "builder",
        "custom"
    ],
    "wof:name":"Danek Custom Furniture",
    "wof:placetype":"venue"
},
  "geometry": {"coordinates":[-75.332364,40.324186],"type":"Point"}
}