{
  "type": "Feature",
  "properties": {
    "iso:country":"US",
    "sg:address":"316 Bunnell Rd",
    "sg:city":"Ulysses",
    "sg:classifiers":[
        {
            "category":"Farming",
            "subcategory":"Farm",
            "type":"Manufacturing & Wholesale Goods"
        }
    ],
    "sg:phone":"+1   ",
    "sg:postcode":"16948",
    "sg:province":"PA",
    "sg:tags":[
        "crop",
        "general"
    ],
    "wof:name":"Phylene Farm",
    "wof:placetype":"venue"
},
  "geometry": {"coordinates":[-77.751102,41.940365],"type":"Point"}
}