{
  "type": "Feature",
  "properties": {
    "iso:country":"US",
    "sg:address":"919 E 7th St",
    "sg:city":"Berwick",
    "sg:classifiers":[
        {
            "category":"Professional",
            "subcategory":"Accounting & Tax Preparation",
            "type":"Services"
        }
    ],
    "sg:phone":"+1 570 759 1420",
    "sg:postcode":"18603",
    "sg:province":"PA",
    "sg:tags":[
        "bookkeeping"
    ],
    "wof:name":"Daniel Dautrich Cpa",
    "wof:placetype":"venue"
},
  "geometry": {"coordinates":[-76.222401,41.065469],"type":"Point"}
}