{
  "type": "Feature",
  "properties": {
    "addr:full":"20 Hemlock Dr Boyertown PA 19512",
    "addr:housenumber":"20",
    "addr:postcode":"19512",
    "addr:street":"Hemlock Dr",
    "iso:country":"US",
    "sg:address":"20 Hemlock Dr",
    "sg:city":"Boyertown",
    "sg:classifiers":[
        {
            "category":"Building & Trades",
            "subcategory":"Construction",
            "type":"Services"
        }
    ],
    "sg:phone":"+1 610 367 9076",
    "sg:postcode":"19512",
    "sg:province":"PA",
    "sg:tags":[
        "general",
        "contractor"
    ],
    "wof:name":"JMD Construction",
    "wof:placetype":"venue"
},
  "geometry": {"coordinates":[-75.657602,40.32301],"type":"Point"}
}