{
  "type": "Feature",
  "properties": {
    "addr:full":"612 Ohio River Blvd Sewickley PA 15143",
    "addr:housenumber":"612",
    "addr:postcode":"15143",
    "addr:street":"Ohio River Blvd",
    "iso:country":"US",
    "sg:address":"612 Ohio River Blvd",
    "sg:city":"Sewickley",
    "sg:classifiers":[
        {
            "category":"Retail",
            "subcategory":"Laundry & Dry Cleaning",
            "type":"Services"
        }
    ],
    "sg:phone":"+1 412 741 1522",
    "sg:postcode":"15143",
    "sg:province":"PA",
    "sg:tags":[
        "cleaners",
        "rug",
        "carpet"
    ],
    "wof:name":"Sewickley Rug Cleaners",
    "wof:placetype":"venue"
},
  "geometry": {"coordinates":[-80.1827,40.535649],"type":"Point"}
}