{
  "type": "Feature",
  "properties": {
    "iso:country":"US",
    "sg:address":"600 Main St",
    "sg:city":"Stroudsburg",
    "sg:classifiers":[
        {
            "category":"Real Estate",
            "subcategory":"Real Estate Agent",
            "type":"Services"
        }
    ],
    "sg:phone":"+1 570 517 0445",
    "sg:postcode":"18360",
    "sg:province":"PA",
    "wof:name":"Lockwood Properties",
    "wof:placetype":"venue"
},
  "geometry": {"coordinates":[-75.19307499999999,40.985651],"type":"Point"}
}