{
  "type": "Feature",
  "properties": {
    "addr:full":"595 Stracks Dam Rd Myerstown PA 17067",
    "addr:housenumber":"595",
    "addr:postcode":"17067",
    "addr:street":"Stracks Dam Rd",
    "iso:country":"US",
    "sg:address":"595 Stracks Dam Rd",
    "sg:city":"Myerstown",
    "sg:classifiers":[
        {
            "category":"Wholesale",
            "subcategory":"Electrical",
            "type":"Manufacturing & Wholesale Goods"
        }
    ],
    "sg:phone":"+1 717 866 6404",
    "sg:postcode":"17067",
    "sg:province":"PA",
    "sg:tags":[
        "generator"
    ],
    "wof:name":"Penn Power Systems",
    "wof:placetype":"venue"
},
  "geometry": {"coordinates":[-76.33470699999999,40.387554],"type":"Point"}
}