{
  "type": "Feature",
  "properties": {
    "iso:country":"US",
    "sg:address":"29 Tioga St",
    "sg:city":"Wellsboro",
    "sg:classifiers":[
        {
            "category":"Restaurant",
            "type":"Food & Drink"
        }
    ],
    "sg:phone":"+1 570 724 4450",
    "sg:postcode":"16901",
    "sg:province":"PA",
    "sg:tags":[
        "parlor",
        "ice",
        "cream"
    ],
    "wof:name":"Pioneer Dairy Bar & Grill",
    "wof:placetype":"venue"
},
  "geometry": {"coordinates":[-77.29741199999999,41.752294],"type":"Point"}
}