{
  "type": "Feature",
  "properties": {
    "iso:country":"US",
    "sg:address":"1445 City Ave",
    "sg:city":"Wynnewood",
    "sg:classifiers":[
        {
            "category":"Personal",
            "type":"Services"
        }
    ],
    "sg:phone":"+1 610 896 2300",
    "sg:postcode":"19096",
    "sg:province":"PA",
    "sg:tags":[
        "therapist",
        "massage"
    ],
    "wof:name":"Back To Normal",
    "wof:placetype":"venue"
},
  "geometry": {"coordinates":[-75.270083,39.980065],"type":"Point"}
}