{
  "type": "Feature",
  "properties": {
    "addr:full":"901 E Main St Palmyra PA 17078",
    "addr:housenumber":"901",
    "addr:postcode":"17078",
    "addr:street":"E Main St",
    "iso:country":"US",
    "sg:address":"901 E Main St",
    "sg:city":"Palmyra",
    "sg:classifiers":[
        {
            "category":"Shopping",
            "subcategory":"Discount & Variety Stores",
            "type":"Retail Goods"
        }
    ],
    "sg:phone":"+1   ",
    "sg:postcode":"17078",
    "sg:province":"PA",
    "wof:name":"Dollar General",
    "wof:placetype":"venue"
},
  "geometry": {"coordinates":[-76.58095899999999,40.314672],"type":"Point"}
}