{
  "type": "Feature",
  "properties": {
    "iso:country":"US",
    "sg:address":"140 W Germantown Pike",
    "sg:city":"Norristown",
    "sg:classifiers":[
        {
            "category":"Health Services",
            "subcategory":"Doctor",
            "type":"Services"
        }
    ],
    "sg:phone":"+1 610 828 1608",
    "sg:postcode":"19401",
    "sg:province":"PA",
    "wof:name":"Womens Health Care Center",
    "wof:placetype":"venue"
},
  "geometry": {"coordinates":[-75.32066,40.145523],"type":"Point"}
}