{
  "type": "Feature",
  "properties": {
    "addr:full":"7316 Frankford Ave Philadelphia PA 19136",
    "addr:housenumber":"7316",
    "addr:postcode":"19136",
    "addr:street":"Frankford Ave",
    "iso:country":"US",
    "sg:address":"7316 Frankford Ave",
    "sg:city":"Philadelphia",
    "sg:classifiers":[
        {
            "category":"Professional",
            "subcategory":"Accounting & Tax Preparation",
            "type":"Services"
        }
    ],
    "sg:phone":"+1 215 333 6740",
    "sg:postcode":"19136",
    "sg:province":"PA",
    "sg:tags":[
        "return",
        "filing"
    ],
    "wof:name":"A & M Berk Tax Svc",
    "wof:placetype":"venue"
},
  "geometry": {"coordinates":[-75.040278,40.037014],"type":"Point"}
}