{
  "type": "Feature",
  "properties": {
    "addr:full":"1107 E Carson St Pittsburgh PA 15203",
    "addr:housenumber":"1107",
    "addr:postcode":"15203",
    "addr:street":"E Carson St",
    "iso:country":"US",
    "sg:address":"1107 E Carson St",
    "sg:city":"Pittsburgh",
    "sg:classifiers":[
        {
            "category":"Cafe",
            "type":"Food & Drink"
        },
        {
            "category":"Restaurant",
            "type":"Food & Drink"
        }
    ],
    "sg:menulink":"http://www.allmenus.com/pa/pittsburgh/5985-cafe-du-jour/menu/",
    "sg:phone":"+1 412 488 9695",
    "sg:postcode":"15203",
    "sg:province":"PA",
    "sg:tags":[
        "soup",
        "american",
        "sandwich",
        "french",
        "salad"
    ],
    "wof:name":"Cafe Du Jour",
    "wof:placetype":"venue"
},
  "geometry": {"coordinates":[-79.987441,40.428742],"type":"Point"}
}