{
  "type": "Feature",
  "properties": {
    "iso:country":"US",
    "sg:address":"1024 Covington Rd",
    "sg:city":"Allison Park",
    "sg:classifiers":[
        {
            "category":"Wholesale",
            "subcategory":"Home Furnishings",
            "type":"Manufacturing & Wholesale Goods"
        }
    ],
    "sg:phone":"+1   ",
    "sg:postcode":"15101",
    "sg:province":"PA",
    "wof:name":"Broderick Associates Inc",
    "wof:placetype":"venue"
},
  "geometry": {"coordinates":[-80.014444,40.583719],"type":"Point"}
}