{
  "type": "Feature",
  "properties": {
    "addr:full":"47 W Walnut St Kingston PA 18704",
    "addr:housenumber":"47",
    "addr:postcode":"18704",
    "addr:street":"W Walnut St",
    "iso:country":"US",
    "sg:address":"47 W Walnut St",
    "sg:city":"Kingston",
    "sg:classifiers":[
        {
            "category":"Home & Garden",
            "subcategory":"Building Materials",
            "type":"Retail Goods"
        }
    ],
    "sg:phone":"+1 570 714 8224",
    "sg:postcode":"18704",
    "sg:province":"PA",
    "wof:name":"Selpzer Brothers Inc",
    "wof:placetype":"venue"
},
  "geometry": {"coordinates":[-75.884974,41.274632],"type":"Point"}
}