{
  "type": "Feature",
  "properties": {
    "iso:country":"US",
    "sg:address":"833 Chestnut St Ste 703",
    "sg:city":"Philadelphia",
    "sg:classifiers":[
        {
            "category":"Health Services",
            "subcategory":"Doctor",
            "type":"Services"
        }
    ],
    "sg:phone":"+1 215 955 1000",
    "sg:postcode":"19107",
    "sg:province":"PA",
    "sg:tags":[
        "physician",
        "family",
        "practice",
        "surgeons",
        "medicine"
    ],
    "wof:name":"Goldstein Larry E MD",
    "wof:placetype":"venue"
},
  "geometry": {"coordinates":[-75.15450300000001,39.949799],"type":"Point"}
}