{
  "type": "Feature",
  "properties": {
    "iso:country":"US",
    "sg:address":"900 W 9th St",
    "sg:city":"Chester",
    "sg:classifiers":[
        {
            "category":"Banks & Credit Unions",
            "subcategory":"Bank",
            "type":"Services"
        }
    ],
    "sg:phone":"+1 610 874 3940",
    "sg:postcode":"19013",
    "sg:province":"PA",
    "sg:tags":[
        "machine",
        "teller",
        "automated"
    ],
    "wof:name":"Fast Cash Atm",
    "wof:placetype":"venue"
},
  "geometry": {"coordinates":[-75.375394,39.846932],"type":"Point"}
}