{
  "type": "Feature",
  "properties": {
    "iso:country":"US",
    "sg:address":"106 Ohio Ave",
    "sg:city":"Glassport",
    "sg:classifiers":[
        {
            "category":"Real Estate",
            "subcategory":"Real Estate Operator",
            "type":"Services"
        }
    ],
    "sg:phone":"+1   ",
    "sg:postcode":"15045",
    "sg:province":"PA",
    "sg:tags":[
        "property",
        "rental",
        "owns"
    ],
    "wof:name":"Accp Limited Partnership",
    "wof:placetype":"venue"
},
  "geometry": {"coordinates":[-79.890884,40.33245],"type":"Point"}
}