{
  "type": "Feature",
  "properties": {
    "addr:full":"61 Builtwell Ave Schuylkill Haven PA 17972",
    "addr:housenumber":"61",
    "addr:postcode":"17972",
    "addr:street":"Builtwell Ave",
    "iso:country":"US",
    "sg:address":"61 Builtwell Ave",
    "sg:city":"Schuylkill Haven",
    "sg:classifiers":[
        {
            "category":"Wholesale",
            "subcategory":"Fruits & Vegetables",
            "type":"Manufacturing & Wholesale Goods"
        }
    ],
    "sg:phone":"+1   ",
    "sg:postcode":"17972",
    "sg:province":"PA",
    "sg:tags":[
        "fresh"
    ],
    "wof:name":"Bedways Produce Co Inc",
    "wof:placetype":"venue"
},
  "geometry": {"coordinates":[-76.144204,40.64918],"type":"Point"}
}