{
  "type": "Feature",
  "properties": {
    "iso:country":"US",
    "sg:address":"700 River Ave",
    "sg:city":"Pittsburgh",
    "sg:classifiers":[
        {
            "category":"Organizations",
            "subcategory":"Non-profit Organization",
            "type":"Services"
        }
    ],
    "sg:phone":"+1 412 323 1958",
    "sg:postcode":"15212",
    "sg:province":"PA",
    "sg:tags":[
        "fund",
        "counselor",
        "raising"
    ],
    "wof:name":"R L Thompson Assoc",
    "wof:placetype":"venue"
},
  "geometry": {"coordinates":[-79.996814,40.449366],"type":"Point"}
}