{
  "type": "Feature",
  "properties": {
    "iso:country":"US",
    "sg:address":"843 School St",
    "sg:city":"Collegeville",
    "sg:classifiers":[
        {
            "category":"Building & Trades",
            "subcategory":"Construction",
            "type":"Services"
        }
    ],
    "sg:phone":"+1   ",
    "sg:postcode":"19426",
    "sg:province":"PA",
    "sg:tags":[
        "hanging",
        "contractor"
    ],
    "wof:name":"Certa-Pro Painters",
    "wof:placetype":"venue"
},
  "geometry": {"coordinates":[-75.464461,40.190241],"type":"Point"}
}