{
  "type": "Feature",
  "properties": {
    "iso:country":"US",
    "sg:address":"378 Mellott Rd",
    "sg:city":"Everett",
    "sg:classifiers":[
        {
            "category":"Organizations",
            "subcategory":"Religious Organization",
            "type":"Services"
        }
    ],
    "sg:phone":"+1 814 735 4738",
    "sg:postcode":"15537",
    "sg:province":"PA",
    "sg:tags":[
        "church"
    ],
    "wof:name":"Cedar Grove Lutheran Church",
    "wof:placetype":"venue"
},
  "geometry": {"coordinates":[-78.298187,39.9422],"type":"Point"}
}