{
  "type": "Feature",
  "properties": {
    "iso:country":"US",
    "sg:address":"901 Commerce Blvd",
    "sg:city":"Dickson City",
    "sg:classifiers":[
        {
            "category":"Banks & Credit Unions",
            "subcategory":"Bank",
            "type":"Services"
        }
    ],
    "sg:phone":"+1 570 307 7500",
    "sg:postcode":"18519",
    "sg:province":"PA",
    "wof:name":"First Liberty Bank & Trust",
    "wof:placetype":"venue"
},
  "geometry": {"coordinates":[-75.649458,41.461262],"type":"Point"}
}