{
  "type": "Feature",
  "properties": {
    "iso:country":"US",
    "sg:address":"500 State Rd",
    "sg:city":"Croydon",
    "sg:classifiers":[
        {
            "category":"Food & Beverages",
            "subcategory":"Bakery",
            "type":"Retail Goods"
        }
    ],
    "sg:phone":"+1 215 785 5915",
    "sg:postcode":"19021",
    "sg:province":"PA",
    "sg:tags":[
        "baker"
    ],
    "wof:name":"Fritz's Bakery",
    "wof:placetype":"venue"
},
  "geometry": {"coordinates":[-74.90679900000001,40.086102],"type":"Point"}
}