{
  "type": "Feature",
  "properties": {
    "iso:country":"US",
    "sg:address":"620 E Olney Ave",
    "sg:city":"Philadelphia",
    "sg:classifiers":[
        {
            "category":"Building & Trades",
            "subcategory":"Cleaning & Sanitation",
            "type":"Services"
        }
    ],
    "sg:phone":"+1   ",
    "sg:postcode":"19120",
    "sg:province":"PA",
    "sg:tags":[
        "maintenance"
    ],
    "wof:name":"Joseph Lombo",
    "wof:placetype":"venue"
},
  "geometry": {"coordinates":[-75.113033,40.032099],"type":"Point"}
}