{
  "type": "Feature",
  "properties": {
    "iso:country":"US",
    "sg:address":"172 Penny Ln",
    "sg:city":"Everett",
    "sg:classifiers":[
        {
            "category":"Manufacturing",
            "subcategory":"Toys & Sporting Goods",
            "type":"Manufacturing & Wholesale Goods"
        },
        {
            "category":"Shopping",
            "subcategory":"Bicycles & Sporting Goods",
            "type":"Retail Goods"
        }
    ],
    "sg:phone":"+1 814 652 6951",
    "sg:postcode":"15537",
    "sg:province":"PA",
    "sg:tags":[
        "goods-wholesale",
        "manufacturer"
    ],
    "wof:name":"Gene's Athletic Sales",
    "wof:placetype":"venue"
},
  "geometry": {"coordinates":[-78.35761599999999,39.99476],"type":"Point"}
}