{
  "type": "Feature",
  "properties": {
    "iso:country":"US",
    "sg:address":"5000 Bensalem Blvd",
    "sg:city":"Bensalem",
    "sg:classifiers":[
        {
            "category":"Health Services",
            "subcategory":"Doctor",
            "type":"Services"
        }
    ],
    "sg:phone":"+1 215 638 4446",
    "sg:postcode":"19020",
    "sg:province":"PA",
    "sg:tags":[
        "podiatrist"
    ],
    "wof:name":"Dr Mitchell D Shikoff",
    "wof:placetype":"venue"
},
  "geometry": {"coordinates":[-74.910004,40.1129],"type":"Point"}
}