{
  "type": "Feature",
  "properties": {
    "iso:country":"US",
    "sg:address":"1246 Winola Rd",
    "sg:city":"Clarks Summit",
    "sg:classifiers":[
        {
            "category":"Autos & Motor Vehicles",
            "subcategory":"Motorcycle Sales",
            "type":"Retail Goods"
        }
    ],
    "sg:phone":"+1 570 586 0345",
    "sg:postcode":"18411",
    "sg:province":"PA",
    "sg:tags":[
        "scooter"
    ],
    "wof:name":"Milwaukee Cycle Svc",
    "wof:placetype":"venue"
},
  "geometry": {"coordinates":[-75.75620000000001,41.486977],"type":"Point"}
}