{
  "type": "Feature",
  "properties": {
    "iso:country":"US",
    "sg:address":"910 Market St",
    "sg:city":"Meadville",
    "sg:classifiers":[
        {
            "category":"Food & Beverages",
            "subcategory":"Bakery",
            "type":"Retail Goods"
        }
    ],
    "sg:phone":"+1 814 336 3480",
    "sg:postcode":"16335",
    "sg:province":"PA",
    "wof:name":"Little Red Hen Bake Shop",
    "wof:placetype":"venue"
},
  "geometry": {"coordinates":[-80.153482,41.638616],"type":"Point"}
}