{
  "type": "Feature",
  "properties": {
    "iso:country":"US",
    "sg:address":"125 Sansom St",
    "sg:city":"William Penn Annex East",
    "sg:classifiers":[
        {
            "category":"Cafe",
            "type":"Food & Drink"
        }
    ],
    "sg:menulink":"http://www.allmenus.com/pa/philadelphia/262208-pagoda-noodle-cafe/menu/",
    "sg:phone":"+1 215 928 2320",
    "sg:postcode":"19106",
    "sg:province":"PA",
    "sg:tags":[
        "asian",
        "chinese"
    ],
    "wof:name":"Pagoda Noodle Cafe",
    "wof:placetype":"venue"
},
  "geometry": {"coordinates":[-75.143039,39.947433],"type":"Point"}
}