{
  "type": "Feature",
  "properties": {
    "iso:country":"US",
    "sg:address":"3000 York Rd",
    "sg:city":"Gettysburg",
    "sg:classifiers":[
        {
            "category":"Manufacturing",
            "subcategory":"Signs",
            "type":"Manufacturing & Wholesale Goods"
        }
    ],
    "sg:phone":"+1   ",
    "sg:postcode":"17325",
    "sg:province":"PA",
    "sg:tags":[
        "specialty",
        "mfg"
    ],
    "wof:name":"Dick Leonard Signs",
    "wof:placetype":"venue"
},
  "geometry": {"coordinates":[-77.139437,39.858698],"type":"Point"}
}