{
  "type": "Feature",
  "properties": {
    "iso:country":"US",
    "sg:address":"3000 W Valley Forge Cir",
    "sg:city":"King Of Prussia",
    "sg:classifiers":[
        {
            "category":"Professional",
            "subcategory":"Management & Consulting",
            "type":"Services"
        }
    ],
    "sg:phone":"+1 610 783 6800",
    "sg:postcode":"19406",
    "sg:province":"PA",
    "sg:tags":[
        "consultant",
        "business"
    ],
    "wof:name":"Axenfeld Associate",
    "wof:placetype":"venue"
},
  "geometry": {"coordinates":[-75.412419,40.104009],"type":"Point"}
}