{
  "type": "Feature",
  "properties": {
    "iso:country":"US",
    "sg:address":"906 Chartiers Ave",
    "sg:city":"Pittsburgh",
    "sg:classifiers":[
        {
            "category":"Restaurant",
            "type":"Food & Drink"
        }
    ],
    "sg:phone":"+1 412 331 1007",
    "sg:postcode":"15220",
    "sg:province":"PA",
    "wof:name":"Terry's Snack Shop",
    "wof:placetype":"venue"
},
  "geometry": {"coordinates":[-80.03980300000001,40.443501],"type":"Point"}
}