{
  "type": "Feature",
  "properties": {
    "iso:country":"US",
    "sg:address":"25 W Market St",
    "sg:city":"York",
    "sg:classifiers":[
        {
            "category":"Restaurant",
            "type":"Food & Drink"
        }
    ],
    "sg:phone":"+1   ",
    "sg:postcode":"17401",
    "sg:province":"PA",
    "sg:tags":[
        "eating"
    ],
    "wof:name":"Marcellos Pizza Inc",
    "wof:placetype":"venue"
},
  "geometry": {"coordinates":[-76.727851,39.962511],"type":"Point"}
}