{
  "type": "Feature",
  "properties": {
    "iso:country":"US",
    "sg:address":"4401 Jonestown Rd",
    "sg:city":"Harrisburg",
    "sg:classifiers":[
        {
            "category":"Restaurant",
            "type":"Food & Drink"
        }
    ],
    "sg:menulink":"http://www.allmenus.com/pa/lower-paxton/28044-applebees/menu/",
    "sg:phone":"+1 717 652 3061",
    "sg:postcode":"17109",
    "sg:province":"PA",
    "sg:tags":[
        "burger",
        "american",
        "sandwich",
        "soup"
    ],
    "wof:name":"Applebee's",
    "wof:placetype":"venue"
},
  "geometry": {"coordinates":[-76.818966,40.299344],"type":"Point"}
}