{
  "type": "Feature",
  "properties": {
    "addr:full":"4 Crittenden Dr Newtown PA 18940",
    "addr:housenumber":"4",
    "addr:postcode":"18940",
    "addr:street":"Crittenden Dr",
    "iso:country":"US",
    "sg:address":"4 Crittenden Dr",
    "sg:city":"Newtown",
    "sg:classifiers":[
        {
            "category":"Building & Trades",
            "subcategory":"Construction",
            "type":"Services"
        }
    ],
    "sg:phone":"+1   ",
    "sg:postcode":"18940",
    "sg:province":"PA",
    "sg:tags":[
        "contractor"
    ],
    "wof:name":"WG Siding Inc",
    "wof:placetype":"venue"
},
  "geometry": {"coordinates":[-74.939635,40.24204],"type":"Point"}
}