{
  "type": "Feature",
  "properties": {
    "addr:full":"703 Glade City Rd Meyersdale PA 15552",
    "addr:housenumber":"703",
    "addr:postcode":"15552",
    "addr:street":"Glade City Rd",
    "iso:country":"US",
    "sg:address":"703 Glade City Rd",
    "sg:city":"Meyersdale",
    "sg:classifiers":[
        {
            "category":"Autos & Motor Vehicles",
            "subcategory":"Automobile Sales",
            "type":"Retail Goods"
        }
    ],
    "sg:phone":"+1 814 634 0297",
    "sg:postcode":"15552",
    "sg:province":"PA",
    "sg:tags":[
        "car",
        "dealer"
    ],
    "wof:name":"Shultz's Used Cars",
    "wof:placetype":"venue"
},
  "geometry": {"coordinates":[-79.00638499999999,39.817106],"type":"Point"}
}