{
  "type": "Feature",
  "properties": {
    "addr:full":"107 Lilac Ct Northampton PA 18067",
    "addr:housenumber":"107",
    "addr:postcode":"18067",
    "addr:street":"Lilac Ct",
    "iso:country":"US",
    "sg:address":"107 Lilac Ct",
    "sg:city":"Northampton",
    "sg:classifiers":[
        {
            "category":"Insurance",
            "subcategory":"Insurance Agent",
            "type":"Services"
        }
    ],
    "sg:phone":"+1 610 317 2264",
    "sg:postcode":"18067",
    "sg:province":"PA",
    "wof:name":"Allstate Insurance",
    "wof:placetype":"venue"
},
  "geometry": {"coordinates":[-75.496837,40.690717],"type":"Point"}
}