{
  "type": "Feature",
  "properties": {
    "iso:country":"US",
    "sg:address":"321 W Uwchlan Ave",
    "sg:city":"Downingtown",
    "sg:classifiers":[
        {
            "category":"Professional",
            "subcategory":"Management & Consulting",
            "type":"Services"
        }
    ],
    "sg:phone":"+1 610 873 0067",
    "sg:postcode":"19335",
    "sg:province":"PA",
    "sg:tags":[
        "consultant",
        "security",
        "system"
    ],
    "wof:name":"Automated Security",
    "wof:placetype":"venue"
},
  "geometry": {"coordinates":[-75.68214500000001,40.030363],"type":"Point"}
}