{
  "type": "Feature",
  "properties": {
    "iso:country":"US",
    "sg:address":"6589 Rosemoor St",
    "sg:city":"Pittsburgh",
    "sg:classifiers":[
        {
            "category":"Wholesale",
            "subcategory":"Stationery",
            "type":"Manufacturing & Wholesale Goods"
        }
    ],
    "sg:phone":"+1   ",
    "sg:postcode":"15217",
    "sg:province":"PA",
    "sg:tags":[
        "paper"
    ],
    "wof:name":"Twin Trees Personal Care",
    "wof:placetype":"venue"
},
  "geometry": {"coordinates":[-79.921035,40.422761],"type":"Point"}
}