{
  "type": "Feature",
  "properties": {
    "addr:full":"950 Sussex Blvd Broomall PA 19008",
    "addr:housenumber":"950",
    "addr:postcode":"19008",
    "addr:street":"Sussex Blvd",
    "iso:country":"US",
    "sg:address":"950 Sussex Blvd",
    "sg:city":"Broomall",
    "sg:classifiers":[
        {
            "category":"Autos & Motor Vehicles",
            "subcategory":"Automobile Sales",
            "type":"Retail Goods"
        },
        {
            "category":"Retail",
            "subcategory":"Auto Repair",
            "type":"Services"
        }
    ],
    "sg:phone":"+1 610 544 1445",
    "sg:postcode":"19008",
    "sg:province":"PA",
    "sg:tags":[
        "car",
        "new"
    ],
    "wof:name":"Petes Auto Marine",
    "wof:placetype":"venue"
},
  "geometry": {"coordinates":[-75.339653,39.95793],"type":"Point"}
}