{
  "type": "Feature",
  "properties": {
    "addr:full":"7977 Steubenville Pike Oakdale PA 15126",
    "addr:housenumber":"7977",
    "addr:postcode":"15126",
    "addr:street":"Steubenville Pike",
    "iso:country":"US",
    "sg:address":"7977 Steubenville Pike",
    "sg:city":"Oakdale",
    "sg:classifiers":[
        {
            "category":"Health Services",
            "subcategory":"Chiropractor",
            "type":"Services"
        }
    ],
    "sg:phone":"+1 724 695 9120",
    "sg:postcode":"15126",
    "sg:province":"PA",
    "wof:name":"Henke Family Chiropractic",
    "wof:placetype":"venue"
},
  "geometry": {"coordinates":[-80.234376,40.441238],"type":"Point"}
}