{
  "type": "Feature",
  "properties": {
    "iso:country":"US",
    "sg:address":"265 Mundy St",
    "sg:city":"Wilkes Barre",
    "sg:classifiers":[
        {
            "category":"Restaurant",
            "type":"Food & Drink"
        }
    ],
    "sg:phone":"+1 570 825 2540",
    "sg:postcode":"18702",
    "sg:province":"PA",
    "wof:name":"Smokey Bones Bbq",
    "wof:placetype":"venue"
},
  "geometry": {"coordinates":[-75.841555,41.243172],"type":"Point"}
}