{
  "type": "Feature",
  "properties": {
    "addr:full":"1541 Poorhouse Rd Downingtown PA 19335",
    "addr:housenumber":"1541",
    "addr:postcode":"19335",
    "addr:street":"Poorhouse Rd",
    "iso:country":"US",
    "sg:address":"1541 Poorhouse Rd",
    "sg:city":"Downingtown",
    "sg:classifiers":[
        {
            "category":"Retail",
            "subcategory":"Auto Repair",
            "type":"Services"
        }
    ],
    "sg:phone":"+1 610 269 5858",
    "sg:postcode":"19335",
    "sg:province":"PA",
    "sg:tags":[
        "repairing",
        "automobile",
        "general"
    ],
    "wof:name":"Jones Automotive Inc",
    "wof:placetype":"venue"
},
  "geometry": {"coordinates":[-75.735218,39.980952],"type":"Point"}
}