{
  "type": "Feature",
  "properties": {
    "addr:full":"26 Charlie Dr Morgantown PA 19543",
    "addr:housenumber":"26",
    "addr:postcode":"19543",
    "addr:street":"Charlie Dr",
    "iso:country":"US",
    "sg:address":"26 Charlie Dr",
    "sg:city":"Morgantown",
    "sg:classifiers":[
        {
            "category":"Professional",
            "subcategory":"Detective & Security Services",
            "type":"Services"
        }
    ],
    "sg:phone":"+1 610 286 1996",
    "sg:postcode":"19543",
    "sg:province":"PA",
    "sg:tags":[
        "car",
        "guard",
        "patrol",
        "se"
    ],
    "wof:name":"M & G Security Inc",
    "wof:placetype":"venue"
},
  "geometry": {"coordinates":[-75.890378,40.202439],"type":"Point"}
}