{
  "type": "Feature",
  "properties": {
    "iso:country":"US",
    "sg:address":"102 E Station Ave",
    "sg:city":"Coopersburg",
    "sg:classifiers":[
        {
            "category":"Professional",
            "subcategory":"Business Services",
            "type":"Services"
        }
    ],
    "sg:phone":"+1 610 282 2369",
    "sg:postcode":"18036",
    "sg:province":"PA",
    "sg:tags":[
        "engineering",
        "consulting"
    ],
    "sg:website":"www.arencibia.com",
    "wof:name":"Arencibia Associates Inc",
    "wof:placetype":"venue"
},
  "geometry": {"coordinates":[-75.38255700000001,40.508898],"type":"Point"}
}