{
  "type": "Feature",
  "properties": {
    "addr:full":"430 Cleveland Ave Waynesboro PA 17268",
    "addr:housenumber":"430",
    "addr:postcode":"17268",
    "addr:street":"Cleveland Ave",
    "iso:country":"US",
    "sg:address":"430 Cleveland Ave",
    "sg:city":"Waynesboro",
    "sg:classifiers":[
        {
            "category":"Professional",
            "subcategory":"Research",
            "type":"Services"
        }
    ],
    "sg:phone":"+1 717 762 0904",
    "sg:postcode":"17268",
    "sg:province":"PA",
    "sg:tags":[
        "laboratory"
    ],
    "wof:name":"Z 430 Custom Color Lab",
    "wof:placetype":"venue"
},
  "geometry": {"coordinates":[-77.591228,39.755128],"type":"Point"}
}