{
  "type": "Feature",
  "properties": {
    "iso:country":"US",
    "sg:address":"307 Lincoln Hwy",
    "sg:city":"Coatesville",
    "sg:classifiers":[
        {
            "category":"Personal",
            "subcategory":"Beauty Salon",
            "type":"Services"
        }
    ],
    "sg:phone":"+1 610 384 4459",
    "sg:postcode":"19320",
    "sg:province":"PA",
    "wof:name":"Duke Of Hair",
    "wof:placetype":"venue"
},
  "geometry": {"coordinates":[-75.83505700000001,39.980058],"type":"Point"}
}