{
  "type": "Feature",
  "properties": {
    "iso:country":"US",
    "sg:address":"309 Walnut St",
    "sg:city":"Vandergrift",
    "sg:classifiers":[
        {
            "category":"Autos & Motor Vehicles",
            "subcategory":"Automobile Sales",
            "type":"Retail Goods"
        }
    ],
    "sg:phone":"+1 724 567 7461",
    "sg:postcode":"15690",
    "sg:province":"PA",
    "sg:tags":[
        "car",
        "dealer"
    ],
    "wof:name":"Clark Auto Sales",
    "wof:placetype":"venue"
},
  "geometry": {"coordinates":[-79.570944,40.597742],"type":"Point"}
}