{
  "type": "Feature",
  "properties": {
    "addr:full":"1001 E Cheltenham Ave Philadelphia PA 19124",
    "addr:housenumber":"1001",
    "addr:postcode":"19124",
    "addr:street":"E Cheltenham Ave",
    "iso:country":"US",
    "sg:address":"1001 E Cheltenham Ave",
    "sg:city":"Philadelphia",
    "sg:classifiers":[
        {
            "category":"Shopping",
            "subcategory":"Computers & Home Electronics",
            "type":"Retail Goods"
        }
    ],
    "sg:phone":"+1 215 782 8201",
    "sg:postcode":"19124",
    "sg:province":"PA",
    "sg:tags":[
        "software"
    ],
    "wof:name":"Centel Corp",
    "wof:placetype":"venue"
},
  "geometry": {"coordinates":[-75.08937299999999,40.034653],"type":"Point"}
}