{
  "type": "Feature",
  "properties": {
    "iso:country":"US",
    "sg:address":"4 Dudie Dr",
    "sg:city":"Newtown Square",
    "sg:classifiers":[
        {
            "category":"Professional",
            "subcategory":"Accounting & Tax Preparation",
            "type":"Services"
        }
    ],
    "sg:phone":"+1 610 356 9495",
    "sg:postcode":"19073",
    "sg:province":"PA",
    "sg:tags":[
        "return",
        "filing"
    ],
    "wof:name":"William J Smith",
    "wof:placetype":"venue"
},
  "geometry": {"coordinates":[-75.40049500000001,39.979815],"type":"Point"}
}