{
  "type": "Feature",
  "properties": {
    "addr:full":"17 Longmeadow Ln Mountain Top PA 18707",
    "addr:housenumber":"17",
    "addr:postcode":"18707",
    "addr:street":"Longmeadow Ln",
    "iso:country":"US",
    "sg:address":"17 Longmeadow Ln",
    "sg:city":"Mountain Top",
    "sg:classifiers":[
        {
            "category":"Shopping",
            "type":"Retail Goods"
        }
    ],
    "sg:phone":"+1   ",
    "sg:postcode":"18707",
    "sg:province":"PA",
    "sg:tags":[
        "merchandise"
    ],
    "wof:name":"HI Tech Water Group Inc",
    "wof:placetype":"venue"
},
  "geometry": {"coordinates":[-75.873803,41.150559],"type":"Point"}
}