{
  "type": "Feature",
  "properties": {
    "iso:country":"US",
    "sg:address":"98 W Main St",
    "sg:city":"Waynesboro",
    "sg:classifiers":[
        {
            "category":"Professional",
            "subcategory":"Computer Services",
            "type":"Services"
        }
    ],
    "sg:phone":"+1 717 788 4065",
    "sg:postcode":"17268",
    "sg:province":"PA",
    "sg:tags":[
        "repair"
    ],
    "sg:website":"innemet.net",
    "wof:name":"Innernet",
    "wof:placetype":"venue"
},
  "geometry": {"coordinates":[-77.580696,39.75721],"type":"Point"}
}