{
  "type": "Feature",
  "properties": {
    "addr:full":"200 W Main St Collegeville PA 19426",
    "addr:housenumber":"200",
    "addr:postcode":"19426",
    "addr:street":"W Main St",
    "iso:country":"US",
    "sg:address":"200 W Main St",
    "sg:city":"Collegeville",
    "sg:classifiers":[
        {
            "category":"Organizations",
            "subcategory":"Religious Organization",
            "type":"Services"
        }
    ],
    "sg:phone":"+1 610 454 9720",
    "sg:postcode":"19426",
    "sg:province":"PA",
    "wof:name":"St Lukes United Church",
    "wof:placetype":"venue"
},
  "geometry": {"coordinates":[-75.46929900000001,40.196098],"type":"Point"}
}