{
  "type": "Feature",
  "properties": {
    "iso:country":"US",
    "sg:address":"100 5th Ave",
    "sg:city":"West Mifflin",
    "sg:classifiers":[
        {
            "category":"Professional",
            "subcategory":"Employment Agencies",
            "type":"Services"
        }
    ],
    "sg:phone":"+1 412 261 4820",
    "sg:postcode":"15122",
    "sg:province":"PA",
    "sg:tags":[
        "opportunity"
    ],
    "wof:name":"Pancoast Staffing Svc",
    "wof:placetype":"venue"
},
  "geometry": {"coordinates":[-79.88656400000001,40.387717],"type":"Point"}
}