{
  "type": "Feature",
  "properties": {
    "iso:country":"US",
    "sg:address":"23 Market St",
    "sg:city":"Union City",
    "sg:classifiers":[
        {
            "category":"Personal",
            "type":"Services"
        },
        {
            "category":"Wholesale",
            "subcategory":"Meat",
            "type":"Manufacturing & Wholesale Goods"
        }
    ],
    "sg:phone":"+1 814 438 2931",
    "sg:postcode":"16438",
    "sg:province":"PA",
    "sg:tags":[
        "product",
        "plant",
        "packing"
    ],
    "wof:name":"Frozen Food Center",
    "wof:placetype":"venue"
},
  "geometry": {"coordinates":[-79.843593,41.898471],"type":"Point"}
}