{
  "type": "Feature",
  "properties": {
    "iso:country":"US",
    "sg:address":"431 Brownsdale Rd",
    "sg:city":"Renfrew",
    "sg:classifiers":[
        {
            "category":"Farming",
            "subcategory":"Farm",
            "type":"Manufacturing & Wholesale Goods"
        }
    ],
    "sg:phone":"+1   ",
    "sg:postcode":"16053",
    "sg:province":"PA",
    "sg:tags":[
        "crop",
        "general"
    ],
    "wof:name":"Merling Meadows Farm",
    "wof:placetype":"venue"
},
  "geometry": {"coordinates":[-79.97222600000001,40.781242],"type":"Point"}
}