{
  "type": "Feature",
  "properties": {
    "iso:country":"US",
    "sg:address":"3435 Simpson Ferry Rd",
    "sg:city":"Camp Hill",
    "sg:classifiers":[
        {
            "category":"Home & Garden",
            "subcategory":"Home Furnishings",
            "type":"Retail Goods"
        }
    ],
    "sg:phone":"+1 717 635 2016",
    "sg:postcode":"17011",
    "sg:province":"PA",
    "sg:tags":[
        "bath",
        "kitchen"
    ],
    "sg:website":"www.therestaurantstore.com/",
    "wof:name":"The Restaurant Store",
    "wof:placetype":"venue"
},
  "geometry": {"coordinates":[-76.93816,40.225919],"type":"Point"}
}