{
  "type": "Feature",
  "properties": {
    "iso:country":"US",
    "sg:address":"1940 Goodnaw St",
    "sg:city":"Philadelphia",
    "sg:classifiers":[
        {
            "category":"Shopping",
            "subcategory":"Crafts & Fabrics",
            "type":"Retail Goods"
        }
    ],
    "sg:phone":"+1 215 969 1938",
    "sg:postcode":"19115",
    "sg:province":"PA",
    "sg:tags":[
        "supply"
    ],
    "wof:name":"Shirley S Craft World",
    "wof:placetype":"venue"
},
  "geometry": {"coordinates":[-75.03541,40.080219],"type":"Point"}
}