{
  "type": "Feature",
  "properties": {
    "addr:full":"250 Furnace Hill Rd Dunbar PA 15431",
    "addr:housenumber":"250",
    "addr:postcode":"15431",
    "addr:street":"Furnace Hill Rd",
    "iso:country":"US",
    "sg:address":"250 Furnace Hill Rd",
    "sg:city":"Dunbar",
    "sg:classifiers":[
        {
            "category":"Wholesale",
            "subcategory":"Durable Goods & Equipment",
            "type":"Manufacturing & Wholesale Goods"
        }
    ],
    "sg:phone":"+1 724 277 4213",
    "sg:postcode":"15431",
    "sg:province":"PA",
    "sg:tags":[
        "fire",
        "alarm",
        "system",
        "installs",
        "protection",
        "servicing",
        "equipment-repairing"
    ],
    "sg:website":"http://www.safetyfirstfire.net",
    "wof:name":"Safety First Fire Equipment",
    "wof:placetype":"venue"
},
  "geometry": {"coordinates":[-79.601682,39.969737],"type":"Point"}
}