{
  "type": "Feature",
  "properties": {
    "iso:country":"US",
    "sg:address":"1245 W Chester Rd",
    "sg:city":"West Chester",
    "sg:classifiers":[
        {
            "category":"Organizations",
            "subcategory":"Religious Organization",
            "type":"Services"
        }
    ],
    "sg:phone":"+1 610 793 1734",
    "sg:postcode":"19382",
    "sg:province":"PA",
    "sg:tags":[
        "church"
    ],
    "wof:name":"Birmingham Friends Meeting",
    "wof:placetype":"venue"
},
  "geometry": {"coordinates":[-75.54707399999999,39.911186],"type":"Point"}
}