{
  "type": "Feature",
  "properties": {
    "addr:full":"777 Main St Russellton PA 15076",
    "addr:housenumber":"777",
    "addr:postcode":"15076",
    "addr:street":"Main St",
    "iso:country":"US",
    "sg:address":"777 Main St",
    "sg:city":"Russellton",
    "sg:classifiers":[
        {
            "category":"Retail",
            "subcategory":"Laundry & Dry Cleaning",
            "type":"Services"
        }
    ],
    "sg:phone":"+1 724 265 3360",
    "sg:postcode":"15076",
    "sg:province":"PA",
    "sg:tags":[
        "cleaners"
    ],
    "wof:name":"Yute's Ideal Cleaning Inc",
    "wof:placetype":"venue"
},
  "geometry": {"coordinates":[-79.833853,40.619396],"type":"Point"}
}