{
  "type": "Feature",
  "properties": {
    "iso:country":"US",
    "sg:address":"10 Creek Pkwy",
    "sg:city":"Boothwyn",
    "sg:classifiers":[
        {
            "category":"Wholesale",
            "subcategory":"Stationery",
            "type":"Manufacturing & Wholesale Goods"
        }
    ],
    "sg:phone":"+1 610 497 5100",
    "sg:postcode":"19061",
    "sg:province":"PA",
    "sg:tags":[
        "product",
        "paper"
    ],
    "sg:website":"www.huffunited.com",
    "wof:name":"Huff Paper Co",
    "wof:placetype":"venue"
},
  "geometry": {"coordinates":[-75.46094600000001,39.854937],"type":"Point"}
}