{
  "type": "Feature",
  "properties": {
    "iso:country":"US",
    "sg:address":"1555 Brinton Rd",
    "sg:city":"Pittsburgh",
    "sg:classifiers":[
        {
            "category":"Freight",
            "type":"Transportation"
        }
    ],
    "sg:phone":"+1 412 351 4444",
    "sg:postcode":"15221",
    "sg:province":"PA",
    "sg:tags":[
        "commercial",
        "storage",
        "special"
    ],
    "wof:name":"Brinton Road Self Storage LLC",
    "wof:placetype":"venue"
},
  "geometry": {"coordinates":[-79.85838200000001,40.416316],"type":"Point"}
}