{
  "type": "Feature",
  "properties": {
    "iso:country":"US",
    "sg:address":"5124 E Trindle Rd",
    "sg:city":"Mechanicsburg",
    "sg:classifiers":[
        {
            "category":"Health Services",
            "subcategory":"Doctor",
            "type":"Services"
        }
    ],
    "sg:phone":"+1 717 795 7943",
    "sg:postcode":"17050",
    "sg:province":"PA",
    "wof:name":"Rehab Medicine Associates",
    "wof:placetype":"venue"
},
  "geometry": {"coordinates":[-76.980904,40.221901],"type":"Point"}
}