{
  "type": "Feature",
  "properties": {
    "iso:country":"US",
    "sg:address":"772 E Providence Rd",
    "sg:city":"Aldan",
    "sg:classifiers":[
        {
            "category":"Travel",
            "subcategory":"Travel Agent",
            "type":"Entertainment"
        }
    ],
    "sg:phone":"+1 610 623 0158",
    "sg:postcode":"19018",
    "sg:province":"PA",
    "sg:tags":[
        "agency",
        "services-commercial"
    ],
    "wof:name":"Hm Travel Plus",
    "wof:placetype":"venue"
},
  "geometry": {"coordinates":[-75.273352,39.928698],"type":"Point"}
}