{
  "type": "Feature",
  "properties": {
    "iso:country":"US",
    "sg:address":"125 W Ridge St",
    "sg:city":"Lansford",
    "sg:classifiers":[
        {
            "category":"Insurance",
            "subcategory":"Insurance Agent",
            "type":"Services"
        }
    ],
    "sg:phone":"+1 570 645 2239",
    "sg:postcode":"18232",
    "sg:province":"PA",
    "wof:name":"Melnick Insurance Agency",
    "wof:placetype":"venue"
},
  "geometry": {"coordinates":[-75.887424,40.831449],"type":"Point"}
}