{
  "type": "Feature",
  "properties": {
    "iso:country":"US",
    "sg:address":"2 N Chester Rd",
    "sg:city":"West Chester",
    "sg:classifiers":[
        {
            "category":"Government",
            "subcategory":"Office",
            "type":"Public Place"
        }
    ],
    "sg:phone":"+1 610 344 6155",
    "sg:postcode":"19380",
    "sg:province":"PA",
    "sg:tags":[
        "policy",
        "county",
        "taxation"
    ],
    "sg:website":"www.chesco.org",
    "wof:name":"County Controller",
    "wof:placetype":"venue"
},
  "geometry": {"coordinates":[-75.52457099999999,39.967524],"type":"Point"}
}