{
  "type": "Feature",
  "properties": {
    "iso:country":"US",
    "sg:address":"585 Cloverbrook Dr",
    "sg:city":"Ephrata",
    "sg:classifiers":[
        {
            "category":"Insurance",
            "subcategory":"Hazard Insurance",
            "type":"Services"
        }
    ],
    "sg:phone":"+1 717 738 1323",
    "sg:postcode":"17522",
    "sg:province":"PA",
    "sg:tags":[
        "commercial",
        "business"
    ],
    "wof:name":"Jeff P Rinehimer Insurance",
    "wof:placetype":"venue"
},
  "geometry": {"coordinates":[-76.16877700000001,40.195252],"type":"Point"}
}