{
  "type": "Feature",
  "properties": {
    "iso:country":"US",
    "sg:address":"21 S Wyoming Ave",
    "sg:city":"Edwardsville",
    "sg:classifiers":[
        {
            "category":"Wholesale",
            "subcategory":"Auto Parts",
            "type":"Manufacturing & Wholesale Goods"
        }
    ],
    "sg:phone":"+1 570 288 3112",
    "sg:postcode":"18704",
    "sg:province":"PA",
    "sg:tags":[
        "automobile",
        "rebuilt"
    ],
    "wof:name":"Valenti Scrap Yard Inc",
    "wof:placetype":"venue"
},
  "geometry": {"coordinates":[-75.89984800000001,41.259253],"type":"Point"}
}