{
  "type": "Feature",
  "properties": {
    "iso:country":"US",
    "sg:address":"1500 Gehman Rd",
    "sg:city":"Harleysville",
    "sg:classifiers":[
        {
            "category":"Professional",
            "subcategory":"Advertising",
            "type":"Services"
        }
    ],
    "sg:phone":"+1 215 256 4070",
    "sg:postcode":"19438",
    "sg:province":"PA",
    "sg:tags":[
        "mailing",
        "shipping"
    ],
    "wof:name":"C E Howe & Co Inc",
    "wof:placetype":"venue"
},
  "geometry": {"coordinates":[-75.343694,40.256948],"type":"Point"}
}