{
  "type": "Feature",
  "properties": {
    "iso:country":"US",
    "sg:address":"3425 Rosstown Rd",
    "sg:city":"Wellsville",
    "sg:classifiers":[
        {
            "category":"Food & Beverages",
            "subcategory":"Groceries & Convenience Stores",
            "type":"Retail Goods"
        }
    ],
    "sg:phone":"+1   ",
    "sg:postcode":"17365",
    "sg:province":"PA",
    "wof:name":"Roundtop Market Inc",
    "wof:placetype":"venue"
},
  "geometry": {"coordinates":[-76.914962,40.065611],"type":"Point"}
}