{
  "type": "Feature",
  "properties": {
    "iso:country":"US",
    "sg:address":"410 McClerge Ave",
    "sg:city":"Herminie",
    "sg:classifiers":[
        {
            "category":"Professional",
            "type":"Services"
        }
    ],
    "sg:phone":"+1   ",
    "sg:postcode":"15637",
    "sg:province":"PA",
    "wof:name":"Nomak Renevations Inc",
    "wof:placetype":"venue"
},
  "geometry": {"coordinates":[-79.71237000000001,40.260285],"type":"Point"}
}