{
  "type": "Feature",
  "properties": {
    "iso:country":"US",
    "sg:address":"708 Colonial Rd",
    "sg:city":"Harrisburg",
    "sg:classifiers":[
        {
            "category":"Personal",
            "subcategory":"Nail Salon",
            "type":"Services"
        }
    ],
    "sg:phone":"+1 717 526 4860",
    "sg:postcode":"17112",
    "sg:province":"PA",
    "wof:name":"B Q Nails",
    "wof:placetype":"venue"
},
  "geometry": {"coordinates":[-76.824065,40.309151],"type":"Point"}
}