{
  "type": "Feature",
  "properties": {
    "addr:full":"30 S Queen St York PA 17403",
    "addr:housenumber":"30",
    "addr:postcode":"17403",
    "addr:street":"S Queen St",
    "iso:country":"US",
    "sg:address":"30 S Queen St",
    "sg:city":"York",
    "sg:classifiers":[
        {
            "category":"Real Estate",
            "subcategory":"Real Estate Agent",
            "type":"Services"
        }
    ],
    "sg:phone":"+1 717 699 4434",
    "sg:postcode":"17403",
    "sg:province":"PA",
    "sg:tags":[
        "appraiser"
    ],
    "wof:name":"Mid-Atlantic Appraisals",
    "wof:placetype":"venue"
},
  "geometry": {"coordinates":[-76.72310400000001,39.96224],"type":"Point"}
}