{
  "type": "Feature",
  "properties": {
    "addr:full":"1300 Hanover Ave Allentown PA 18109",
    "addr:housenumber":"1300",
    "addr:postcode":"18109",
    "addr:street":"Hanover Ave",
    "iso:country":"US",
    "sg:address":"1300 Hanover Ave",
    "sg:city":"Allentown",
    "sg:classifiers":[
        {
            "category":"Banks & Credit Unions",
            "subcategory":"Bank",
            "type":"Services"
        }
    ],
    "sg:phone":"+1 610 433 3126",
    "sg:postcode":"18109",
    "sg:province":"PA",
    "sg:tags":[
        "cashing",
        "check"
    ],
    "wof:name":"Flexcheck Cash Advance Ctr",
    "wof:placetype":"venue"
},
  "geometry": {"coordinates":[-75.435008,40.618455],"type":"Point"}
}