{
  "type": "Feature",
  "properties": {
    "iso:country":"US",
    "sg:address":"155 Wise Rd",
    "sg:city":"Greenville",
    "sg:classifiers":[
        {
            "category":"Farming",
            "subcategory":"Farm & Veterinary Services",
            "type":"Manufacturing & Wholesale Goods"
        }
    ],
    "sg:phone":"+1 724 588 8653",
    "sg:postcode":"16125",
    "sg:province":"PA",
    "sg:tags":[
        "breeder",
        "livestock"
    ],
    "wof:name":"Silver Maple Holsteins",
    "wof:placetype":"venue"
},
  "geometry": {"coordinates":[-80.44174,41.434738],"type":"Point"}
}