{
  "type": "Feature",
  "properties": {
    "iso:country":"US",
    "sg:address":"545 Old 22",
    "sg:city":"Lenhartsville",
    "sg:classifiers":[
        {
            "category":"Building & Trades",
            "subcategory":"Plumbing",
            "type":"Services"
        }
    ],
    "sg:phone":"+1   ",
    "sg:postcode":"19530",
    "sg:province":"PA",
    "sg:tags":[
        "plumbing",
        "air",
        "conditioning",
        "heating"
    ],
    "wof:name":"Stump Plumbing & Heating",
    "wof:placetype":"venue"
},
  "geometry": {"coordinates":[-75.79749700000001,40.578921],"type":"Point"}
}