{
  "type": "Feature",
  "properties": {
    "addr:full":"2201 Stetler Dr Ranshaw PA 17866",
    "addr:housenumber":"2201",
    "addr:postcode":"17866",
    "addr:street":"Stetler Dr Ranshaw",
    "iso:country":"US",
    "sg:address":"2201 Stetler Dr",
    "sg:city":"Ranshaw",
    "sg:classifiers":[
        {
            "category":"Wholesale",
            "subcategory":"Machinery & Supplies",
            "type":"Manufacturing & Wholesale Goods"
        }
    ],
    "sg:phone":"+1 570 644 0787",
    "sg:postcode":"17866",
    "sg:province":"PA",
    "sg:tags":[
        "commercial",
        "fan"
    ],
    "wof:name":"John F Scanlan Co Inc",
    "wof:placetype":"venue"
},
  "geometry": {"coordinates":[-76.586294,40.784411],"type":"Point"}
}