{
  "type": "Feature",
  "properties": {
    "addr:full":"8550 Peach St Erie PA 16509",
    "addr:housenumber":"8550",
    "addr:postcode":"16509",
    "addr:street":"Peach St",
    "iso:country":"US",
    "sg:address":"8550 Peach St",
    "sg:city":"Erie",
    "sg:classifiers":[
        {
            "category":"Manufacturing",
            "subcategory":"Signs",
            "type":"Manufacturing & Wholesale Goods"
        }
    ],
    "sg:phone":"+1 814 864 1710",
    "sg:postcode":"16509",
    "sg:province":"PA",
    "sg:tags":[
        "specialty",
        "mfg"
    ],
    "wof:name":"A A Trailer Signs Inc",
    "wof:placetype":"venue"
},
  "geometry": {"coordinates":[-80.067155,42.037086],"type":"Point"}
}