{
  "type": "Feature",
  "properties": {
    "iso:country":"US",
    "sg:address":"37 Brookfield Dr",
    "sg:city":"Elizabethtown",
    "sg:classifiers":[
        {
            "category":"Professional",
            "subcategory":"Computer Services",
            "type":"Services"
        }
    ],
    "sg:phone":"+1 717 361 9511",
    "sg:postcode":"17022",
    "sg:province":"PA",
    "sg:tags":[
        "consultant",
        "designer"
    ],
    "sg:website":"www.valtrainusa.com",
    "wof:name":"Valtrain",
    "wof:placetype":"venue"
},
  "geometry": {"coordinates":[-76.567886,40.137582],"type":"Point"}
}