{
  "type": "Feature",
  "properties": {
    "iso:country":"US",
    "sg:address":"15 Wildwood Ave",
    "sg:city":"Lansdowne",
    "sg:classifiers":[
        {
            "category":"Health Services",
            "subcategory":"Doctor",
            "type":"Services"
        }
    ],
    "sg:phone":"+1   ",
    "sg:postcode":"19050",
    "sg:province":"PA",
    "sg:tags":[
        "medical"
    ],
    "wof:name":"Abu Agiya",
    "wof:placetype":"venue"
},
  "geometry": {"coordinates":[-75.258312,39.943102],"type":"Point"}
}