{
  "type": "Feature",
  "properties": {
    "iso:country":"US",
    "sg:address":"4211 Clairton Blvd",
    "sg:city":"Pittsburgh",
    "sg:classifiers":[
        {
            "category":"Professional",
            "subcategory":"Accounting & Tax Preparation",
            "type":"Services"
        }
    ],
    "sg:phone":"+1 412 884 0088",
    "sg:postcode":"15227",
    "sg:province":"PA",
    "sg:tags":[
        "return",
        "filing"
    ],
    "wof:name":"H & R Block Tax Svc",
    "wof:placetype":"venue"
},
  "geometry": {"coordinates":[-79.98464,40.365256],"type":"Point"}
}