{
  "type": "Feature",
  "properties": {
    "iso:country":"US",
    "sg:address":"3322 Tilton St",
    "sg:city":"Philadelphia",
    "sg:classifiers":[
        {
            "category":"Building & Trades",
            "subcategory":"Construction",
            "type":"Services"
        }
    ],
    "sg:phone":"+1 215 739 8020",
    "sg:postcode":"19134",
    "sg:province":"PA",
    "sg:tags":[
        "roofing",
        "contractor"
    ],
    "wof:name":"William Wismann",
    "wof:placetype":"venue"
},
  "geometry": {"coordinates":[-75.097854,39.986046],"type":"Point"}
}