{
  "type": "Feature",
  "properties": {
    "iso:country":"US",
    "sg:address":"1105 Snyder Ave",
    "sg:city":"Philadelphia",
    "sg:classifiers":[
        {
            "category":"Travel",
            "subcategory":"Travel Agent",
            "type":"Entertainment"
        }
    ],
    "sg:phone":"+1 215 218 9099",
    "sg:postcode":"19148",
    "sg:province":"PA",
    "sg:tags":[
        "agency",
        "services-commercial"
    ],
    "wof:name":"Alianza Express Travel Agency",
    "wof:placetype":"venue"
},
  "geometry": {"coordinates":[-75.164494,39.923707],"type":"Point"}
}