{
  "type": "Feature",
  "properties": {
    "addr:full":"1209 Baldwin Ave Sharon PA 16146",
    "addr:housenumber":"1209",
    "addr:postcode":"16146",
    "addr:street":"Baldwin Ave",
    "iso:country":"US",
    "sg:address":"1209 Baldwin Ave",
    "sg:city":"Sharon",
    "sg:classifiers":[
        {
            "category":"Wholesale",
            "subcategory":"Vending Machines",
            "type":"Manufacturing & Wholesale Goods"
        }
    ],
    "sg:phone":"+1   ",
    "sg:postcode":"16146",
    "sg:province":"PA",
    "sg:tags":[
        "operator"
    ],
    "wof:name":"Penn Ohio Vending",
    "wof:placetype":"venue"
},
  "geometry": {"coordinates":[-80.495504,41.214862],"type":"Point"}
}