{
  "type": "Feature",
  "properties": {
    "iso:country":"US",
    "sg:address":"1065 S Main St",
    "sg:city":"Chambersburg",
    "sg:classifiers":[
        {
            "category":"Insurance",
            "subcategory":"Insurance Agent",
            "type":"Services"
        }
    ],
    "sg:phone":"+1 717 263 4897",
    "sg:postcode":"17201",
    "sg:province":"PA",
    "wof:name":"Bob Martin Insurance",
    "wof:placetype":"venue"
},
  "geometry": {"coordinates":[-77.665881,39.920676],"type":"Point"}
}