{
  "type": "Feature",
  "properties": {
    "iso:country":"US",
    "sg:address":"851 S West End Blvd",
    "sg:city":"Quakertown",
    "sg:classifiers":[
        {
            "category":"Organizations",
            "subcategory":"Professional Association",
            "type":"Services"
        }
    ],
    "sg:phone":"+1 215 538 7090",
    "sg:postcode":"18951",
    "sg:province":"PA",
    "sg:tags":[
        "business",
        "trade"
    ],
    "wof:name":"Pennridge Education Assn",
    "wof:placetype":"venue"
},
  "geometry": {"coordinates":[-75.34654,40.422441],"type":"Point"}
}