{
  "type": "Feature",
  "properties": {
    "addr:full":"307 Mt Pleasant Rd Mt Pleasant PA 15666",
    "addr:housenumber":"307",
    "addr:postcode":"15666",
    "addr:street":"Mt Pleasant Rd",
    "iso:country":"US",
    "sg:address":"307 Mt Pleasant Rd",
    "sg:city":"Mt Pleasant",
    "sg:classifiers":[
        {
            "category":"Autos & Motor Vehicles",
            "subcategory":"Auto Supplies",
            "type":"Retail Goods"
        }
    ],
    "sg:phone":"+1 724 547 5781",
    "sg:postcode":"15666",
    "sg:province":"PA",
    "sg:tags":[
        "automobile",
        "parts"
    ],
    "wof:name":"Oppman Auto Parts Co",
    "wof:placetype":"venue"
},
  "geometry": {"coordinates":[-79.55404900000001,40.109529],"type":"Point"}
}