{
  "type": "Feature",
  "properties": {
    "iso:country":"US",
    "sg:address":"3505 Sullivan St",
    "sg:city":"Mechanicsburg",
    "sg:classifiers":[
        {
            "category":"Building & Trades",
            "subcategory":"Construction",
            "type":"Services"
        }
    ],
    "sg:phone":"+1 717 234 1919",
    "sg:postcode":"17050",
    "sg:province":"PA",
    "sg:tags":[
        "contractor"
    ],
    "wof:name":"M L Acri Inc",
    "wof:placetype":"venue"
},
  "geometry": {"coordinates":[-76.956001,40.276901],"type":"Point"}
}