{
  "type": "Feature",
  "properties": {
    "addr:full":"886 Scouten Rd Mansfield PA 16933",
    "addr:housenumber":"886",
    "addr:postcode":"16933",
    "addr:street":"Scouten Rd",
    "iso:country":"US",
    "sg:address":"886 Scouten Rd",
    "sg:city":"Mansfield",
    "sg:classifiers":[
        {
            "category":"Farming",
            "subcategory":"Livestock Farm",
            "type":"Manufacturing & Wholesale Goods"
        }
    ],
    "sg:phone":"+1   ",
    "sg:postcode":"16933",
    "sg:province":"PA",
    "sg:tags":[
        "beef",
        "feedlot",
        "cattle"
    ],
    "wof:name":"Joseph Bartholomew",
    "wof:placetype":"venue"
},
  "geometry": {"coordinates":[-77.020685,41.802696],"type":"Point"}
}