{
  "type": "Feature",
  "properties": {
    "addr:full":"10517 Perry Hwy Wexford PA 15090",
    "addr:housenumber":"10517",
    "addr:postcode":"15090",
    "addr:street":"Perry Hwy",
    "iso:country":"US",
    "sg:address":"10517 Perry Hwy",
    "sg:city":"Wexford",
    "sg:classifiers":[
        {
            "category":"Retail",
            "subcategory":"Auto Rental",
            "type":"Services"
        }
    ],
    "sg:phone":"+1 724 935 2660",
    "sg:postcode":"15090",
    "sg:province":"PA",
    "sg:tags":[
        "car"
    ],
    "sg:website":"www.hertz.com",
    "wof:name":"Hertz Local Edition",
    "wof:placetype":"venue"
},
  "geometry": {"coordinates":[-80.053099,40.609111],"type":"Point"}
}