{
  "type": "Feature",
  "properties": {
    "iso:country":"US",
    "sg:address":"435 S 6th St",
    "sg:city":"Emmaus",
    "sg:classifiers":[
        {
            "category":"Education",
            "subcategory":"School",
            "type":"Public Place"
        }
    ],
    "sg:phone":"+1   ",
    "sg:postcode":"18049",
    "sg:province":"PA",
    "wof:name":"Saint Ann School",
    "wof:placetype":"venue"
},
  "geometry": {"coordinates":[-75.49191999999999,40.528114],"type":"Point"}
}