{
  "type": "Feature",
  "properties": {
    "iso:country":"US",
    "sg:address":"107 Schoolhouse Rd",
    "sg:city":"Sellersville",
    "sg:classifiers":[
        {
            "category":"Manufacturing",
            "subcategory":"Printing",
            "type":"Manufacturing & Wholesale Goods"
        }
    ],
    "sg:phone":"+1 215 453 6518",
    "sg:postcode":"18960",
    "sg:province":"PA",
    "sg:tags":[
        "manifold",
        "business",
        "form",
        "mfg"
    ],
    "wof:name":"Safeguard Business Systems",
    "wof:placetype":"venue"
},
  "geometry": {"coordinates":[-75.285301,40.339626],"type":"Point"}
}