{
  "type": "Feature",
  "properties": {
    "iso:country":"US",
    "sg:address":"8864 Frankstown Rd",
    "sg:city":"Pittsburgh",
    "sg:classifiers":[
        {
            "category":"Health Services",
            "subcategory":"Clinic",
            "type":"Services"
        }
    ],
    "sg:phone":"+1 412 731 0515",
    "sg:postcode":"15235",
    "sg:province":"PA",
    "sg:tags":[
        "home"
    ],
    "wof:name":"Home Healthcare Staffing & Svc",
    "wof:placetype":"venue"
},
  "geometry": {"coordinates":[-79.872766,40.460568],"type":"Point"}
}