{
  "type": "Feature",
  "properties": {
    "iso:country":"US",
    "sg:address":"16058 Rogers Ferry Rd",
    "sg:city":"Meadville",
    "sg:classifiers":[
        {
            "category":"Building & Trades",
            "subcategory":"Construction",
            "type":"Services"
        }
    ],
    "sg:phone":"+1   ",
    "sg:postcode":"16335",
    "sg:province":"PA",
    "sg:tags":[
        "concrete",
        "contractor"
    ],
    "wof:name":"Lybargers Cement Contracting",
    "wof:placetype":"venue"
},
  "geometry": {"coordinates":[-80.225537,41.672507],"type":"Point"}
}