{
  "type": "Feature",
  "properties": {
    "iso:country":"US",
    "sg:address":"1301 Hornyak Dr",
    "sg:city":"Aliquippa",
    "sg:classifiers":[
        {
            "category":"Professional",
            "subcategory":"Lawyer & Legal Services",
            "type":"Services"
        }
    ],
    "sg:phone":"+1 724 378 5432",
    "sg:postcode":"15001",
    "sg:province":"PA",
    "sg:tags":[
        "attorney"
    ],
    "wof:name":"Mark R Galzerano Law Office",
    "wof:placetype":"venue"
},
  "geometry": {"coordinates":[-80.257835,40.587904],"type":"Point"}
}