{
  "type": "Feature",
  "properties": {
    "iso:country":"US",
    "sg:address":"600 N 3rd St",
    "sg:city":"Philadelphia",
    "sg:classifiers":[
        {
            "category":"Place Of Worship",
            "type":"Public Place"
        }
    ],
    "sg:phone":"+1 215 923 9596",
    "sg:postcode":"19123",
    "sg:province":"PA",
    "sg:tags":[
        "church"
    ],
    "wof:name":"Upper Room Recordings",
    "wof:placetype":"venue"
},
  "geometry": {"coordinates":[-75.14331799999999,39.961411],"type":"Point"}
}