{
  "type": "Feature",
  "properties": {
    "iso:country":"US",
    "sg:address":"10 E Mill Rd",
    "sg:city":"Flourtown",
    "sg:classifiers":[
        {
            "category":"Health Services",
            "subcategory":"Doctor",
            "type":"Services"
        }
    ],
    "sg:phone":"+1 215 836 4605",
    "sg:postcode":"19031",
    "sg:province":"PA",
    "wof:name":"Paul M Mayer DDS",
    "wof:placetype":"venue"
},
  "geometry": {"coordinates":[-75.210081,40.108278],"type":"Point"}
}