{
  "type": "Feature",
  "properties": {
    "iso:country":"US",
    "sg:address":"119 N Main St",
    "sg:city":"Du Bois",
    "sg:classifiers":[
        {
            "category":"Bars & Pubs",
            "type":"Food & Drink"
        }
    ],
    "sg:phone":"+1 814 375 0276",
    "sg:postcode":"15801",
    "sg:province":"PA",
    "sg:tags":[
        "organization",
        "drinking",
        "membership"
    ],
    "wof:name":"Swedish American Club",
    "wof:placetype":"venue"
},
  "geometry": {"coordinates":[-78.767917,41.123888],"type":"Point"}
}