{
  "type": "Feature",
  "properties": {
    "addr:full":"1010 Underwood Rd Olyphant PA 18447",
    "addr:housenumber":"1010",
    "addr:postcode":"18447",
    "addr:street":"Underwood Rd",
    "iso:country":"US",
    "sg:address":"1010 Underwood Rd",
    "sg:city":"Olyphant",
    "sg:classifiers":[
        {
            "category":"Wholesale",
            "subcategory":"Groceries",
            "type":"Manufacturing & Wholesale Goods"
        }
    ],
    "sg:phone":"+1 570 489 2727",
    "sg:postcode":"18447",
    "sg:province":"PA",
    "sg:tags":[
        "beverage"
    ],
    "wof:name":"Canada Dry Royal Crown Co",
    "wof:placetype":"venue"
},
  "geometry": {"coordinates":[-75.588086,41.453454],"type":"Point"}
}