{
  "type": "Feature",
  "properties": {
    "iso:country":"US",
    "sg:address":"3387 Rising Sun Ct",
    "sg:city":"Nazareth",
    "sg:classifiers":[
        {
            "category":"Restaurant",
            "type":"Food & Drink"
        }
    ],
    "sg:phone":"+1 610 762 3432",
    "sg:postcode":"18064",
    "sg:province":"PA",
    "wof:name":"Ciao Restaurant Group",
    "wof:placetype":"venue"
},
  "geometry": {"coordinates":[-75.377596,40.720333],"type":"Point"}
}