{
  "type": "Feature",
  "properties": {
    "addr:full":"80 N Washington St Wilkes Barre PA 18701",
    "addr:housenumber":"80",
    "addr:postcode":"18701",
    "addr:street":"N Washington St",
    "iso:country":"US",
    "sg:address":"80 N Washington St",
    "sg:city":"Wilkes Barre",
    "sg:classifiers":[
        {
            "category":"Education",
            "subcategory":"School",
            "type":"Public Place"
        }
    ],
    "sg:phone":"+1 570 826 7201",
    "sg:postcode":"18701",
    "sg:province":"PA",
    "wof:name":"James M Coughlin High School",
    "wof:placetype":"venue"
},
  "geometry": {"coordinates":[-75.879034,41.24566],"type":"Point"}
}