{
  "type": "Feature",
  "properties": {
    "addr:full":"2150 Old 22 Lenhartsville PA 19534",
    "addr:housenumber":"2150",
    "addr:postcode":"19534",
    "addr:street":"Old 22 Lenhartsville",
    "iso:country":"US",
    "sg:address":"2150 Old 22",
    "sg:city":"Lenhartsville",
    "sg:classifiers":[
        {
            "category":"Place Of Worship",
            "subcategory":"Church",
            "type":"Public Place"
        },
        {
            "category":"Place Of Worship",
            "type":"Public Place"
        }
    ],
    "sg:phone":"+1 610 562 5033",
    "sg:postcode":"19534",
    "sg:province":"PA",
    "sg:tags":[
        "churches-evangelical",
        "churches-covenant",
        "covenant"
    ],
    "wof:name":"Salem Evangelical Congrg Church Inc",
    "wof:placetype":"venue"
},
  "geometry": {"coordinates":[-75.92734900000001,40.570938],"type":"Point"}
}