{
  "type": "Feature",
  "properties": {
    "iso:country":"US",
    "sg:address":"122 5th St",
    "sg:city":"Jermyn",
    "sg:classifiers":[
        {
            "category":"Home & Garden",
            "subcategory":"Hardware",
            "type":"Retail Goods"
        }
    ],
    "sg:phone":"+1   ",
    "sg:postcode":"18433",
    "sg:province":"PA",
    "wof:name":"L&L Designs Inc",
    "wof:placetype":"venue"
},
  "geometry": {"coordinates":[-75.548294,41.536788],"type":"Point"}
}