{
  "type": "Feature",
  "properties": {
    "iso:country":"US",
    "sg:address":"21 Stella Dr",
    "sg:city":"Southampton",
    "sg:classifiers":[
        {
            "category":"Health Services",
            "subcategory":"Health Practitioner",
            "type":"Services"
        }
    ],
    "sg:phone":"+1 215 364 9920",
    "sg:postcode":"18966",
    "sg:province":"PA",
    "sg:tags":[
        "psychologist"
    ],
    "wof:name":"Merrill D Paletz Phd",
    "wof:placetype":"venue"
},
  "geometry": {"coordinates":[-75.03161799999999,40.208433],"type":"Point"}
}