{
  "type": "Feature",
  "properties": {
    "addr:full":"1913 S 10th St Philadelphia PA 19148",
    "addr:housenumber":"1913",
    "addr:postcode":"19148",
    "addr:street":"S 10Th St",
    "iso:country":"US",
    "sg:address":"1913 S 10th St",
    "sg:city":"Philadelphia",
    "sg:classifiers":[
        {
            "category":"Deli",
            "type":"Food & Drink"
        },
        {
            "category":"Food & Beverages",
            "subcategory":"Bakery",
            "type":"Retail Goods"
        }
    ],
    "sg:phone":"+1 215 336 1733",
    "sg:postcode":"19148",
    "sg:province":"PA",
    "sg:tags":[
        "sandwich"
    ],
    "wof:name":"J D Grill Deli Inc",
    "wof:placetype":"venue"
},
  "geometry": {"coordinates":[-75.162255,39.925481],"type":"Point"}
}