{
  "type": "Feature",
  "properties": {
    "iso:country":"US",
    "sg:address":"2652 Frankford Ave",
    "sg:city":"Philadelphia",
    "sg:classifiers":[
        {
            "category":"Autos & Motor Vehicles",
            "subcategory":"Fuel & Gas Station",
            "type":"Retail Goods"
        }
    ],
    "sg:phone":"+1 215 427 1760",
    "sg:postcode":"19125",
    "sg:province":"PA",
    "wof:name":"Universal Coral Street",
    "wof:placetype":"venue"
},
  "geometry": {"coordinates":[-75.12339900000001,39.986264],"type":"Point"}
}