{
  "type": "Feature",
  "properties": {
    "iso:country":"US",
    "sg:address":"1119 Pawlings Rd",
    "sg:city":"Norristown",
    "sg:classifiers":[
        {
            "category":"Restaurant",
            "type":"Food & Drink"
        }
    ],
    "sg:phone":"+1 610 666 1688",
    "sg:postcode":"19403",
    "sg:province":"PA",
    "sg:tags":[
        "asian",
        "chinese",
        "pan"
    ],
    "wof:name":"Panda Pavilion Of Audubon",
    "wof:placetype":"venue"
},
  "geometry": {"coordinates":[-75.433902,40.126177],"type":"Point"}
}