{
  "type": "Feature",
  "properties": {
    "iso:country":"US",
    "sg:address":"719 Jackson St",
    "sg:city":"Philadelphia",
    "sg:classifiers":[
        {
            "category":"Social Services",
            "subcategory":"Child Care",
            "type":"Services"
        }
    ],
    "sg:phone":"+1 215 389 2991",
    "sg:postcode":"19148",
    "sg:province":"PA",
    "sg:tags":[
        "day"
    ],
    "wof:name":"Franklin Day Nursery",
    "wof:placetype":"venue"
},
  "geometry": {"coordinates":[-75.158897,39.9216],"type":"Point"}
}