{
  "type": "Feature",
  "properties": {
    "iso:country":"US",
    "sg:address":"843 Kimmerlings Rd",
    "sg:city":"Lebanon",
    "sg:classifiers":[
        {
            "category":"Organizations",
            "subcategory":"Religious Organization",
            "type":"Services"
        }
    ],
    "sg:phone":"+1 717 270 1216",
    "sg:postcode":"17046",
    "sg:province":"PA",
    "sg:tags":[
        "clergy"
    ],
    "wof:name":"Miller Linda M",
    "wof:placetype":"venue"
},
  "geometry": {"coordinates":[-76.404037,40.36898],"type":"Point"}
}