{
  "type": "Feature",
  "properties": {
    "iso:country":"US",
    "sg:address":"119 Commonwealth Dr",
    "sg:city":"Warrendale",
    "sg:classifiers":[
        {
            "category":"Manufacturing",
            "subcategory":"Chemicals & Compounds",
            "type":"Manufacturing & Wholesale Goods"
        },
        {
            "category":"Wholesale",
            "subcategory":"Medical Equipment & Supplies",
            "type":"Manufacturing & Wholesale Goods"
        }
    ],
    "sg:phone":"+1 724 778 6100",
    "sg:postcode":"15086",
    "sg:province":"PA",
    "sg:tags":[
        "pharmaceutical",
        "product",
        "products-wholesale",
        "manufacturer"
    ],
    "sg:website":"http://www.3riverspharma.com",
    "wof:name":"Three Rivers Pharmaceuticals",
    "wof:placetype":"venue"
},
  "geometry": {"coordinates":[-80.10237499999999,40.668234],"type":"Point"}
}