{
  "type": "Feature",
  "properties": {
    "addr:full":"2107 18th St Altoona PA 16601",
    "addr:housenumber":"2107",
    "addr:postcode":"16601",
    "addr:street":"18Th St",
    "iso:country":"US",
    "sg:address":"2107 18th St",
    "sg:city":"Altoona",
    "sg:classifiers":[
        {
            "category":"Building & Trades",
            "subcategory":"Construction",
            "type":"Services"
        }
    ],
    "sg:phone":"+1   ",
    "sg:postcode":"16601",
    "sg:province":"PA",
    "sg:tags":[
        "house"
    ],
    "wof:name":"Acts 4 Improvement",
    "wof:placetype":"venue"
},
  "geometry": {"coordinates":[-78.41677199999999,40.517286],"type":"Point"}
}