{
  "type": "Feature",
  "properties": {
    "iso:country":"US",
    "sg:address":"272 Bethlehem Pike",
    "sg:city":"Colmar",
    "sg:classifiers":[
        {
            "category":"Retail",
            "subcategory":"Auto Rental",
            "type":"Services"
        },
        {
            "category":"Building & Trades",
            "subcategory":"Equipment Rental",
            "type":"Services"
        }
    ],
    "sg:phone":"+1 215 822 2276",
    "sg:postcode":"18915",
    "sg:province":"PA",
    "sg:tags":[
        "truck",
        "moving"
    ],
    "sg:website":"http://www.uhaul.com/Locations/Rentals-near-Colmar-PA-18915/883044",
    "wof:name":"U-Haul Moving & Storage of Colmar",
    "wof:placetype":"venue"
},
  "geometry": {"coordinates":[-75.259439,40.275039],"type":"Point"}
}