{
  "type": "Feature",
  "properties": {
    "addr:full":"958 Ruth Ave New Castle PA 16101",
    "addr:housenumber":"958",
    "addr:postcode":"16101",
    "addr:street":"Ruth Ave",
    "iso:country":"US",
    "sg:address":"958 Ruth Ave",
    "sg:city":"New Castle",
    "sg:classifiers":[
        {
            "category":"Shopping",
            "subcategory":"Discount & Variety Stores",
            "type":"Retail Goods"
        }
    ],
    "sg:phone":"+1   ",
    "sg:postcode":"16101",
    "sg:province":"PA",
    "sg:tags":[
        "merchandise",
        "general"
    ],
    "wof:name":"Roses General Store",
    "wof:placetype":"venue"
},
  "geometry": {"coordinates":[-80.27855,40.946605],"type":"Point"}
}