{
  "type": "Feature",
  "properties": {
    "addr:full":"2841 W Lehigh Ave Philadelphia PA 19132",
    "addr:housenumber":"2841",
    "addr:postcode":"19132",
    "addr:street":"W Lehigh Ave",
    "iso:country":"US",
    "sg:address":"2841 W Lehigh Ave",
    "sg:city":"Philadelphia",
    "sg:classifiers":[
        {
            "category":"Food & Beverages",
            "subcategory":"Groceries & Convenience Stores",
            "type":"Retail Goods"
        }
    ],
    "sg:phone":"+1   ",
    "sg:postcode":"19132",
    "sg:province":"PA",
    "wof:name":"Lehigh Food Center",
    "wof:placetype":"venue"
},
  "geometry": {"coordinates":[-75.17848499999999,39.997101],"type":"Point"}
}