{
  "type": "Feature",
  "properties": {
    "iso:country":"US",
    "sg:address":"1450 Scalp Ave",
    "sg:city":"Johnstown",
    "sg:classifiers":[
        {
            "category":"Professional",
            "subcategory":"Employment Agencies",
            "type":"Services"
        }
    ],
    "sg:phone":"+1 814 266 8193",
    "sg:postcode":"15904",
    "sg:province":"PA",
    "sg:tags":[
        "temporary",
        "help",
        "contractor"
    ],
    "sg:website":"www.kellyservices.com",
    "wof:name":"Kelly Services Inc",
    "wof:placetype":"venue"
},
  "geometry": {"coordinates":[-78.857946,40.271209],"type":"Point"}
}