{
  "type": "Feature",
  "properties": {
    "iso:country":"US",
    "sg:address":"149 Barrisville Rd",
    "sg:city":"Beaver Falls",
    "sg:classifiers":[
        {
            "category":"Professional",
            "type":"Services"
        }
    ],
    "sg:phone":"+1   ",
    "sg:postcode":"15010",
    "sg:province":"PA",
    "wof:name":"Dan Suboch",
    "wof:placetype":"venue"
},
  "geometry": {"coordinates":[-80.250224,40.792748],"type":"Point"}
}