{
  "type": "Feature",
  "properties": {
    "iso:country":"US",
    "sg:address":"1070 Georgetown Rd",
    "sg:city":"Paradise",
    "sg:classifiers":[
        {
            "category":"Organizations",
            "subcategory":"Religious Organization",
            "type":"Services"
        }
    ],
    "sg:phone":"+1 717 786 7821",
    "sg:postcode":"17562",
    "sg:province":"PA",
    "sg:tags":[
        "place",
        "worship",
        "church"
    ],
    "wof:name":"Georgetown United Methodist Ch",
    "wof:placetype":"venue"
},
  "geometry": {"coordinates":[-76.08477000000001,39.941222],"type":"Point"}
}