{
  "type": "Feature",
  "properties": {
    "iso:country":"US",
    "sg:address":"1637 N Atherton St",
    "sg:city":"State College",
    "sg:classifiers":[
        {
            "category":"Shopping",
            "subcategory":"Gifts & Souvenirs",
            "type":"Retail Goods"
        }
    ],
    "sg:phone":"+1   ",
    "sg:postcode":"16803",
    "sg:province":"PA",
    "sg:tags":[
        "supply"
    ],
    "wof:name":"Barbaras Hallmark",
    "wof:placetype":"venue"
},
  "geometry": {"coordinates":[-77.893998,40.807861],"type":"Point"}
}