{
  "type": "Feature",
  "properties": {
    "iso:country":"US",
    "sg:address":"400 Brandywine Ln",
    "sg:city":"King Of Prussia",
    "sg:classifiers":[
        {
            "category":"Recreation",
            "type":"Entertainment"
        }
    ],
    "sg:phone":"+1 610 265 3376",
    "sg:postcode":"19406",
    "sg:province":"PA",
    "sg:tags":[
        "psychic",
        "medium"
    ],
    "wof:name":"Psychic Readings By Sandra",
    "wof:placetype":"venue"
},
  "geometry": {"coordinates":[-75.373364,40.091581],"type":"Point"}
}