{
  "type": "Feature",
  "properties": {
    "addr:full":"204 Windsor Ave Hamburg PA 19526",
    "addr:housenumber":"204",
    "addr:postcode":"19526",
    "addr:street":"Windsor Ave",
    "iso:country":"US",
    "sg:address":"204 Windsor Ave",
    "sg:city":"Hamburg",
    "sg:classifiers":[
        {
            "category":"Manufacturing",
            "subcategory":"Glass & Minerals",
            "type":"Manufacturing & Wholesale Goods"
        }
    ],
    "sg:phone":"+1 610 562 3000",
    "sg:postcode":"19526",
    "sg:province":"PA",
    "sg:tags":[
        "hydraulic",
        "cement",
        "mfg"
    ],
    "sg:website":"www.lehighcement.com",
    "wof:name":"Lehigh Cement Company",
    "wof:placetype":"venue"
},
  "geometry": {"coordinates":[-75.961476,40.568837],"type":"Point"}
}