{
  "type": "Feature",
  "properties": {
    "addr:full":"2427 State Rte 143 Kempton PA 19529",
    "addr:housenumber":"2427",
    "addr:postcode":"19529",
    "addr:street":"State Rte 143",
    "iso:country":"US",
    "sg:address":"2427 State Rte 143",
    "sg:city":"Kempton",
    "sg:classifiers":[
        {
            "category":"Professional",
            "type":"Services"
        }
    ],
    "sg:phone":"+1 610 756 4404",
    "sg:postcode":"19529",
    "sg:province":"PA",
    "sg:tags":[
        "establishment"
    ],
    "wof:name":"Harvest Technology",
    "wof:placetype":"venue"
},
  "geometry": {"coordinates":[-75.86367199999999,40.623333],"type":"Point"}
}