{
  "type": "Feature",
  "properties": {
    "iso:country":"US",
    "sg:address":"3614 Beale Ave",
    "sg:city":"Altoona",
    "sg:classifiers":[
        {
            "category":"Personal",
            "subcategory":"Beauty Salon",
            "type":"Services"
        }
    ],
    "sg:phone":"+1 814 946 1836",
    "sg:postcode":"16601",
    "sg:province":"PA",
    "wof:name":"My Fair Lady Beauty Salon",
    "wof:placetype":"venue"
},
  "geometry": {"coordinates":[-78.418764,40.491112],"type":"Point"}
}