{
  "type": "Feature",
  "properties": {
    "iso:country":"US",
    "sg:address":"16 N Franklin St",
    "sg:city":"Doylestown",
    "sg:classifiers":[
        {
            "category":"Health Services",
            "subcategory":"Health Practitioner",
            "type":"Services"
        }
    ],
    "sg:phone":"+1   ",
    "sg:postcode":"18901",
    "sg:province":"PA",
    "wof:name":"Court Conciliation & Eval Svc",
    "wof:placetype":"venue"
},
  "geometry": {"coordinates":[-75.135932,40.309298],"type":"Point"}
}