{
  "type": "Feature",
  "properties": {
    "iso:country":"US",
    "sg:address":"130 E Market St",
    "sg:city":"York",
    "sg:classifiers":[
        {
            "category":"Utilities",
            "subcategory":"Water",
            "type":"Services"
        }
    ],
    "sg:phone":"+1 717 845 3601",
    "sg:postcode":"17401",
    "sg:province":"PA",
    "sg:tags":[
        "system",
        "supply"
    ],
    "sg:website":"www.yorkwater.com",
    "wof:name":"York Water Co",
    "wof:placetype":"venue"
},
  "geometry": {"coordinates":[-76.724356,39.963404],"type":"Point"}
}