{
  "type": "Feature",
  "properties": {
    "iso:country":"US",
    "sg:address":"40 N 2nd St",
    "sg:city":"Souderton",
    "sg:classifiers":[
        {
            "category":"Building & Trades",
            "subcategory":"Construction",
            "type":"Services"
        }
    ],
    "sg:phone":"+1 215 721 1850",
    "sg:postcode":"18964",
    "sg:province":"PA",
    "sg:tags":[
        "excavation",
        "hauling",
        "contractor"
    ],
    "wof:name":"Scott A Seifert",
    "wof:placetype":"venue"
},
  "geometry": {"coordinates":[-75.319864,40.310834],"type":"Point"}
}