{
  "type": "Feature",
  "properties": {
    "addr:full":"1701 3rd St Beaver PA 15009",
    "addr:housenumber":"1701",
    "addr:postcode":"15009",
    "addr:street":"3Rd St",
    "iso:country":"US",
    "sg:address":"1701 3rd St",
    "sg:city":"Beaver",
    "sg:classifiers":[
        {
            "category":"Restaurant",
            "type":"Food & Drink"
        }
    ],
    "sg:menulink":"http://www.allmenus.com/pa/vanport/133263-subway/menu/",
    "sg:phone":"+1 724 728 4929",
    "sg:postcode":"15009",
    "sg:province":"PA",
    "sg:tags":[
        "american",
        "sandwich"
    ],
    "wof:name":"Subway",
    "wof:placetype":"venue"
},
  "geometry": {"coordinates":[-80.319925,40.688654],"type":"Point"}
}