{
  "type": "Feature",
  "properties": {
    "addr:full":"433 Fort Pitt Blvd Pittsburgh PA 15219",
    "addr:housenumber":"433",
    "addr:postcode":"15219",
    "addr:street":"Fort Pitt Blvd",
    "iso:country":"US",
    "sg:address":"433 Fort Pitt Blvd",
    "sg:city":"Pittsburgh",
    "sg:classifiers":[
        {
            "category":"Travel",
            "subcategory":"Hotels & Motels",
            "type":"Entertainment"
        }
    ],
    "sg:phone":"+1 412 281 0357",
    "sg:postcode":"15219",
    "sg:province":"PA",
    "wof:name":"Hotel & Rstrnt Employees",
    "wof:placetype":"venue"
},
  "geometry": {"coordinates":[-79.999359,40.436161],"type":"Point"}
}