{
  "type": "Feature",
  "properties": {
    "iso:country":"US",
    "sg:address":"5956 Chester Ave",
    "sg:city":"Philadelphia",
    "sg:classifiers":[
        {
            "category":"Restaurant",
            "type":"Food & Drink"
        }
    ],
    "sg:phone":"+1 215 724 5990",
    "sg:postcode":"19143",
    "sg:province":"PA",
    "sg:tags":[
        "eating",
        "pizza"
    ],
    "wof:name":"60th Street Pizza",
    "wof:placetype":"venue"
},
  "geometry": {"coordinates":[-75.23159800000001,39.9338],"type":"Point"}
}