{
  "type": "Feature",
  "properties": {
    "addr:full":"1500 Market St Philadelphia PA 19102",
    "addr:housenumber":"1500",
    "addr:postcode":"19102",
    "addr:street":"Market St",
    "iso:country":"US",
    "sg:address":"1500 Market St",
    "sg:city":"Philadelphia",
    "sg:classifiers":[
        {
            "category":"Professional",
            "subcategory":"Lawyer & Legal Services",
            "type":"Services"
        }
    ],
    "sg:phone":"+1 215 972 7770",
    "sg:postcode":"19102",
    "sg:province":"PA",
    "wof:name":"Beatty Edw F Jr Atty",
    "wof:placetype":"venue"
},
  "geometry": {"coordinates":[-75.16529800000001,39.952599],"type":"Point"}
}