{
  "type": "Feature",
  "properties": {
    "iso:country":"US",
    "sg:address":"36 Spring St",
    "sg:city":"Wilkes Barre",
    "sg:classifiers":[
        {
            "category":"Retail",
            "subcategory":"Laundry & Dry Cleaning",
            "type":"Services"
        }
    ],
    "sg:phone":"+1   ",
    "sg:postcode":"18702",
    "sg:province":"PA",
    "wof:name":"Ashley Carpet Care",
    "wof:placetype":"venue"
},
  "geometry": {"coordinates":[-75.86287299999999,41.244777],"type":"Point"}
}