{
  "type": "Feature",
  "properties": {
    "iso:country":"US",
    "sg:address":"460 Salem Dr",
    "sg:city":"Pittsburgh",
    "sg:classifiers":[
        {
            "category":"Building & Trades",
            "subcategory":"Construction",
            "type":"Services"
        }
    ],
    "sg:phone":"+1   ",
    "sg:postcode":"15243",
    "sg:province":"PA",
    "sg:tags":[
        "house",
        "nonresidential"
    ],
    "wof:name":"Paul E Schmidt",
    "wof:placetype":"venue"
},
  "geometry": {"coordinates":[-80.056826,40.379438],"type":"Point"}
}