{
  "type": "Feature",
  "properties": {
    "iso:country":"US",
    "sg:address":"1236 Main St",
    "sg:city":"Hellertown",
    "sg:classifiers":[
        {
            "category":"Shopping",
            "subcategory":"News",
            "type":"Retail Goods"
        },
        {
            "category":"Restaurant",
            "type":"Food & Drink"
        }
    ],
    "sg:phone":"+1 610 838 8621",
    "sg:postcode":"18055",
    "sg:province":"PA",
    "sg:tags":[
        "parlor",
        "cream",
        "desert",
        "ice",
        "mfg"
    ],
    "wof:name":"Ice Cream Shoppe",
    "wof:placetype":"venue"
},
  "geometry": {"coordinates":[-75.34124799999999,40.587386],"type":"Point"}
}