{
  "type": "Feature",
  "properties": {
    "addr:full":"1510 Pennsylvania Ave Peckville PA 18452",
    "addr:housenumber":"1510",
    "addr:postcode":"18452",
    "addr:street":"Pennsylvania Ave",
    "iso:country":"US",
    "sg:address":"1510 Pennsylvania Ave",
    "sg:city":"Peckville",
    "sg:classifiers":[
        {
            "category":"Personal",
            "subcategory":"Beauty Salon",
            "type":"Services"
        }
    ],
    "sg:phone":"+1 570 383 5090",
    "sg:postcode":"18452",
    "sg:province":"PA",
    "wof:name":"Class Act Salon",
    "wof:placetype":"venue"
},
  "geometry": {"coordinates":[-75.599565,41.478448],"type":"Point"}
}