{
  "type": "Feature",
  "properties": {
    "addr:full":"2240 Farmersville Rd Bethlehem PA 18020",
    "addr:postcode":"2240;18020",
    "addr:street":"Farmersville Rd",
    "iso:country":"US",
    "sg:address":"2240 Farmersville Rd",
    "sg:city":"Bethlehem",
    "sg:classifiers":[
        {
            "category":"Social Services",
            "type":"Services"
        }
    ],
    "sg:phone":"+1 610 954 5580",
    "sg:postcode":"18020",
    "sg:province":"PA",
    "sg:tags":[
        "counseling"
    ],
    "wof:name":"Alan Shapiro Counseling Svc",
    "wof:placetype":"venue"
},
  "geometry": {"coordinates":[-75.308798,40.649385],"type":"Point"}
}