{
  "type": "Feature",
  "properties": {
    "addr:full":"727 Delancey St Philadelphia PA 19106",
    "addr:housenumber":"727",
    "addr:postcode":"19106",
    "addr:street":"Delancey St",
    "iso:country":"US",
    "sg:address":"727 Delancey St",
    "sg:city":"Philadelphia",
    "sg:classifiers":[
        {
            "category":"Health Services",
            "subcategory":"Doctor",
            "type":"Services"
        }
    ],
    "sg:phone":"+1 215 829 3523",
    "sg:postcode":"19106",
    "sg:province":"PA",
    "sg:tags":[
        "medical"
    ],
    "wof:name":"Margerum Bryan S MD",
    "wof:placetype":"venue"
},
  "geometry": {"coordinates":[-75.154701,39.944801],"type":"Point"}
}