{
  "type": "Feature",
  "properties": {
    "addr:full":"130 S Washington St Butler PA 16001",
    "addr:housenumber":"130",
    "addr:postcode":"16001",
    "addr:street":"S Washington St",
    "iso:country":"US",
    "sg:address":"130 S Washington St",
    "sg:city":"Butler",
    "sg:classifiers":[
        {
            "category":"Personal",
            "subcategory":"Beauty Salon",
            "type":"Services"
        }
    ],
    "sg:phone":"+1   ",
    "sg:postcode":"16001",
    "sg:province":"PA",
    "sg:tags":[
        "shop"
    ],
    "wof:name":"Heads Up Hair and Nail Studio",
    "wof:placetype":"venue"
},
  "geometry": {"coordinates":[-79.897003,40.860355],"type":"Point"}
}