{
  "type": "Feature",
  "properties": {
    "iso:country":"US",
    "sg:address":"88 Oak Grove Rd",
    "sg:city":"Morgantown",
    "sg:classifiers":[
        {
            "category":"Professional",
            "subcategory":"Management & Consulting",
            "type":"Services"
        }
    ],
    "sg:phone":"+1   ",
    "sg:postcode":"19543",
    "sg:province":"PA",
    "sg:tags":[
        "business"
    ],
    "wof:name":"Tank Compliance Inc",
    "wof:placetype":"venue"
},
  "geometry": {"coordinates":[-75.86321599999999,40.196615],"type":"Point"}
}