{
  "type": "Feature",
  "properties": {
    "iso:country":"US",
    "sg:address":"131 Main Entrance Dr",
    "sg:city":"Pittsburgh",
    "sg:classifiers":[
        {
            "category":"Building & Trades",
            "subcategory":"Construction",
            "type":"Services"
        }
    ],
    "sg:phone":"+1 412 462 2099",
    "sg:postcode":"15228",
    "sg:province":"PA",
    "sg:tags":[
        "coping",
        "plastering",
        "tiling",
        "pool",
        "swimming"
    ],
    "wof:name":"Moriah Service",
    "wof:placetype":"venue"
},
  "geometry": {"coordinates":[-80.04713700000001,40.372722],"type":"Point"}
}