{
  "type": "Feature",
  "properties": {
    "iso:country":"US",
    "sg:address":"3614 5th Ave",
    "sg:city":"Pittsburgh",
    "sg:classifiers":[
        {
            "category":"Shopping",
            "subcategory":"News",
            "type":"Retail Goods"
        }
    ],
    "sg:phone":"+1 412 681 9496",
    "sg:postcode":"15213",
    "sg:province":"PA",
    "sg:tags":[
        "dealer"
    ],
    "wof:name":"5th Ave News & Snacks",
    "wof:placetype":"venue"
},
  "geometry": {"coordinates":[-79.958562,40.441782],"type":"Point"}
}