{
  "type": "Feature",
  "properties": {
    "addr:full":"2630 Monroeville Blvd Monroeville PA 15146",
    "addr:postcode":"2630;15146",
    "addr:street":"Monroeville Blvd",
    "iso:country":"US",
    "sg:address":"2630 Monroeville Blvd",
    "sg:city":"Monroeville",
    "sg:classifiers":[
        {
            "category":"Government",
            "subcategory":"Post Office",
            "type":"Public Place"
        }
    ],
    "sg:phone":"+1 412 242 0540",
    "sg:postcode":"15146",
    "sg:province":"PA",
    "sg:tags":[
        "postal",
        "us"
    ],
    "wof:name":"US Post Office",
    "wof:placetype":"venue"
},
  "geometry": {"coordinates":[-79.784851,40.431564],"type":"Point"}
}