{
  "type": "Feature",
  "properties": {
    "iso:country":"US",
    "sg:address":"616 S 3rd St",
    "sg:city":"Philadelphia",
    "sg:classifiers":[
        {
            "category":"Shopping",
            "type":"Retail Goods"
        }
    ],
    "sg:phone":"+1 215 629 1733",
    "sg:postcode":"19147",
    "sg:province":"PA",
    "sg:tags":[
        "supply",
        "furnishing",
        "dog",
        "merchandise",
        "cat"
    ],
    "wof:name":"Chic Petique",
    "wof:placetype":"venue"
},
  "geometry": {"coordinates":[-75.14761799999999,39.941326],"type":"Point"}
}