{
  "type": "Feature",
  "properties": {
    "addr:full":"3555 Lewisberry Rd York Haven PA 17370",
    "addr:housenumber":"3555",
    "addr:postcode":"17370",
    "addr:street":"Lewisberry Rd",
    "iso:country":"US",
    "sg:address":"3555 Lewisberry Rd",
    "sg:city":"York Haven",
    "sg:classifiers":[
        {
            "category":"Organizations",
            "subcategory":"Religious Organization",
            "type":"Services"
        }
    ],
    "sg:phone":"+1 717 938 3657",
    "sg:postcode":"17370",
    "sg:province":"PA",
    "sg:tags":[
        "church"
    ],
    "wof:name":"Redland Valley Brethren Church",
    "wof:placetype":"venue"
},
  "geometry": {"coordinates":[-76.84641999999999,40.131033],"type":"Point"}
}