{
  "type": "Feature",
  "properties": {
    "iso:country":"US",
    "sg:address":"4011 Dickey Rd",
    "sg:city":"Gibsonia",
    "sg:classifiers":[
        {
            "category":"Government",
            "subcategory":"Office",
            "type":"Public Place"
        }
    ],
    "sg:phone":"+1 724 443 5921",
    "sg:postcode":"15044",
    "sg:province":"PA",
    "sg:tags":[
        "village"
    ],
    "sg:website":"www.richland.pa.us",
    "wof:name":"Municipal Building",
    "wof:placetype":"venue"
},
  "geometry": {"coordinates":[-79.94795499999999,40.642888],"type":"Point"}
}