{
  "type": "Feature",
  "properties": {
    "iso:country":"US",
    "sg:address":"954 Town Ctr",
    "sg:city":"Doylestown",
    "sg:classifiers":[
        {
            "category":"Health Services",
            "subcategory":"Doctor",
            "type":"Services"
        }
    ],
    "sg:phone":"+1 215 345 5323",
    "sg:postcode":"18901",
    "sg:province":"PA",
    "sg:tags":[
        "throat",
        "ear",
        "nose"
    ],
    "wof:name":"Ent Associates of Bucks & Montgomery",
    "wof:placetype":"venue"
},
  "geometry": {"coordinates":[-75.191002,40.298],"type":"Point"}
}