{
  "type": "Feature",
  "properties": {
    "iso:country":"US",
    "sg:address":"2220 Lebanon Church Rd",
    "sg:city":"West Mifflin",
    "sg:classifiers":[
        {
            "category":"Restaurant",
            "type":"Food & Drink"
        }
    ],
    "sg:menulink":"http://www.allmenus.com/pa/west-mifflin/200182-long-john-silvers/menu/",
    "sg:phone":"+1 412 653 9993",
    "sg:postcode":"15122",
    "sg:province":"PA",
    "sg:tags":[
        "seafood",
        "american"
    ],
    "wof:name":"Long John Silver's",
    "wof:placetype":"venue"
},
  "geometry": {"coordinates":[-79.941878,40.348561],"type":"Point"}
}