{
  "type": "Feature",
  "properties": {
    "iso:country":"US",
    "sg:address":"2542 E Ann St",
    "sg:city":"Philadelphia",
    "sg:classifiers":[
        {
            "category":"Building & Trades",
            "subcategory":"Electrical",
            "type":"Services"
        }
    ],
    "sg:phone":"+1 215 289 6565",
    "sg:postcode":"19134",
    "sg:province":"PA",
    "sg:tags":[
        "electric",
        "contractor"
    ],
    "wof:name":"Sommerville Electrical Contr",
    "wof:placetype":"venue"
},
  "geometry": {"coordinates":[-75.109825,39.982984],"type":"Point"}
}