{
  "type": "Feature",
  "properties": {
    "addr:full":"1819 Lincoln Way Mc Keesport PA 15131",
    "addr:housenumber":"1819",
    "addr:postcode":"15131",
    "addr:street":"Lincoln Way",
    "iso:country":"US",
    "sg:address":"1819 Lincoln Way",
    "sg:city":"Mc Keesport",
    "sg:classifiers":[
        {
            "category":"Personal",
            "subcategory":"Beauty Salon",
            "type":"Services"
        }
    ],
    "sg:phone":"+1 412 672 6811",
    "sg:postcode":"15131",
    "sg:province":"PA",
    "sg:tags":[
        "shop",
        "barber"
    ],
    "wof:name":"Fantastic Sam's",
    "wof:placetype":"venue"
},
  "geometry": {"coordinates":[-79.813312,40.342943],"type":"Point"}
}