{
  "type": "Feature",
  "properties": {
    "iso:country":"US",
    "sg:address":"300 Ryers Ave",
    "sg:city":"Cheltenham",
    "sg:classifiers":[
        {
            "category":"Education",
            "subcategory":"Vocational School",
            "type":"Public Place"
        }
    ],
    "sg:phone":"+1 215 663 8412",
    "sg:postcode":"19012",
    "sg:province":"PA",
    "sg:tags":[
        "training",
        "computer"
    ],
    "sg:website":"www.seletc.com",
    "wof:name":"Software Evaluation Labs Etc",
    "wof:placetype":"venue"
},
  "geometry": {"coordinates":[-75.09244700000001,40.06165],"type":"Point"}
}