{
  "type": "Feature",
  "properties": {
    "addr:full":"3250 Industrial Blvd Bethel Park PA 15102",
    "addr:housenumber":"3250",
    "addr:postcode":"15102",
    "addr:street":"Industrial Blvd",
    "iso:country":"US",
    "sg:address":"3250 Industrial Blvd",
    "sg:city":"Bethel Park",
    "sg:classifiers":[
        {
            "category":"Building & Trades",
            "subcategory":"Construction",
            "type":"Services"
        }
    ],
    "sg:phone":"+1   ",
    "sg:postcode":"15102",
    "sg:province":"PA",
    "sg:tags":[
        "residential"
    ],
    "wof:name":"RB Witt Construction",
    "wof:placetype":"venue"
},
  "geometry": {"coordinates":[-80.04659599999999,40.322612],"type":"Point"}
}