{
  "type": "Feature",
  "properties": {
    "iso:country":"US",
    "sg:address":"307 Lincoln Ave",
    "sg:city":"Hatboro",
    "sg:classifiers":[
        {
            "category":"Wholesale",
            "subcategory":"Machinery & Supplies",
            "type":"Manufacturing & Wholesale Goods"
        }
    ],
    "sg:phone":"+1 215 674 8488",
    "sg:postcode":"19040",
    "sg:province":"PA",
    "sg:tags":[
        "pneumatic",
        "tool",
        "component",
        "hydraulic",
        "equipment",
        "distributor",
        "electronic"
    ],
    "wof:name":"Air Hydraulic Sales Co, Inc",
    "wof:placetype":"venue"
},
  "geometry": {"coordinates":[-75.097138,40.180939],"type":"Point"}
}