{
  "type": "Feature",
  "properties": {
    "iso:country":"US",
    "sg:address":"1 Forrest Ln",
    "sg:city":"Chester",
    "sg:classifiers":[
        {
            "category":"Government",
            "subcategory":"Office",
            "type":"Public Place"
        }
    ],
    "sg:phone":"+1 610 447 7751",
    "sg:postcode":"19087",
    "sg:province":"PA",
    "sg:tags":[
        "village"
    ],
    "wof:name":"Chester Building Official",
    "wof:placetype":"venue"
},
  "geometry": {"coordinates":[-75.402416,40.047328],"type":"Point"}
}