{
  "type": "Feature",
  "properties": {
    "iso:country":"US",
    "sg:address":"205 Redington Ave",
    "sg:city":"Troy",
    "sg:classifiers":[
        {
            "category":"Organizations",
            "subcategory":"Religious Organization",
            "type":"Services"
        }
    ],
    "sg:phone":"+1 570 297 3070",
    "sg:postcode":"16947",
    "sg:province":"PA",
    "sg:tags":[
        "church"
    ],
    "wof:name":"First United Methodist Church",
    "wof:placetype":"venue"
},
  "geometry": {"coordinates":[-76.790384,41.784834],"type":"Point"}
}