{
  "type": "Feature",
  "properties": {
    "iso:country":"US",
    "sg:address":"6 W Main Ave",
    "sg:city":"Myerstown",
    "sg:classifiers":[
        {
            "category":"Restaurant",
            "type":"Food & Drink"
        }
    ],
    "sg:phone":"+1 717 866 7732",
    "sg:postcode":"17067",
    "sg:province":"PA",
    "sg:tags":[
        "pizza"
    ],
    "wof:name":"Old Turnpike Pizza",
    "wof:placetype":"venue"
},
  "geometry": {"coordinates":[-76.303434,40.37533],"type":"Point"}
}