{
  "type": "Feature",
  "properties": {
    "iso:country":"US",
    "sg:address":"4343 Frankford Ave",
    "sg:city":"Philadelphia",
    "sg:classifiers":[
        {
            "category":"Personal",
            "subcategory":"Beauty Salon",
            "type":"Services"
        }
    ],
    "sg:phone":"+1 215 743 2731",
    "sg:postcode":"19124",
    "sg:province":"PA",
    "sg:tags":[
        "hair",
        "shop",
        "stylist"
    ],
    "wof:name":"Nini's African Hair Braiding",
    "wof:placetype":"venue"
},
  "geometry": {"coordinates":[-75.088431,40.011338],"type":"Point"}
}