{
  "type": "Feature",
  "properties": {
    "iso:country":"US",
    "sg:address":"185 Eisele Rd",
    "sg:city":"Cheswick",
    "sg:classifiers":[
        {
            "category":"Building & Trades",
            "subcategory":"Construction",
            "type":"Services"
        }
    ],
    "sg:phone":"+1   ",
    "sg:postcode":"15024",
    "sg:province":"PA",
    "sg:tags":[
        "house"
    ],
    "wof:name":"Bazner Construction Inc D",
    "wof:placetype":"venue"
},
  "geometry": {"coordinates":[-79.870546,40.595516],"type":"Point"}
}