{
  "type": "Feature",
  "properties": {
    "addr:full":"628 College Ave Lancaster PA 17603",
    "addr:housenumber":"628",
    "addr:postcode":"17603",
    "addr:street":"College Ave",
    "iso:country":"US",
    "sg:address":"628 College Ave",
    "sg:city":"Lancaster",
    "sg:classifiers":[
        {
            "category":"Education",
            "subcategory":"College",
            "type":"Public Place"
        }
    ],
    "sg:phone":"+1 717 291 3911",
    "sg:postcode":"17603",
    "sg:province":"PA",
    "sg:tags":[
        "academic",
        "school"
    ],
    "sg:website":"www.fandm.edu",
    "wof:name":"Franklin & Marshall College",
    "wof:placetype":"venue"
},
  "geometry": {"coordinates":[-76.31834499999999,40.047412],"type":"Point"}
}