{
  "type": "Feature",
  "properties": {
    "addr:full":"411 Main St Stroudsburg PA 18360",
    "addr:housenumber":"411",
    "addr:postcode":"18360",
    "addr:street":"Main St",
    "iso:country":"US",
    "sg:address":"411 Main St",
    "sg:city":"Stroudsburg",
    "sg:classifiers":[
        {
            "category":"Professional",
            "subcategory":"Lawyer & Legal Services",
            "type":"Services"
        }
    ],
    "sg:phone":"+1 570 213 0045",
    "sg:postcode":"18360",
    "sg:province":"PA",
    "sg:tags":[
        "attorney"
    ],
    "wof:name":"Saba Endler & Assoc",
    "wof:placetype":"venue"
},
  "geometry": {"coordinates":[-75.18989000000001,40.986923],"type":"Point"}
}