{
  "type": "Feature",
  "properties": {
    "iso:country":"US",
    "sg:address":"100 W Mount Carmel Ave",
    "sg:city":"Mt Carmel",
    "sg:classifiers":[
        {
            "category":"Wholesale",
            "subcategory":"Beer",
            "type":"Manufacturing & Wholesale Goods"
        }
    ],
    "sg:phone":"+1 570 339 2740",
    "sg:postcode":"17851",
    "sg:province":"PA",
    "sg:tags":[
        "ale"
    ],
    "wof:name":"Bumper's Beverage",
    "wof:placetype":"venue"
},
  "geometry": {"coordinates":[-76.415238,40.798804],"type":"Point"}
}