{
  "type": "Feature",
  "properties": {
    "iso:country":"US",
    "sg:address":"2301 5th St",
    "sg:city":"Altoona",
    "sg:classifiers":[
        {
            "category":"Organizations",
            "subcategory":"Religious Organization",
            "type":"Services"
        }
    ],
    "sg:phone":"+1   ",
    "sg:postcode":"16601",
    "sg:province":"PA",
    "wof:name":"St Theresa Church Emp",
    "wof:placetype":"venue"
},
  "geometry": {"coordinates":[-78.40705699999999,40.527112],"type":"Point"}
}