{
  "type": "Feature",
  "properties": {
    "addr:full":"3209 Maplecrest Ter Lancaster PA 17601",
    "addr:housenumber":"3209",
    "addr:postcode":"17601",
    "addr:street":"Maplecrest Ter",
    "iso:country":"US",
    "sg:address":"3209 Maplecrest Ter",
    "sg:city":"Lancaster",
    "sg:classifiers":[
        {
            "category":"Building & Trades",
            "subcategory":"Construction",
            "type":"Services"
        }
    ],
    "sg:phone":"+1 717 285 5187",
    "sg:postcode":"17601",
    "sg:province":"PA",
    "sg:tags":[
        "wallcoverings-installation",
        "wallpaper",
        "painting",
        "contractor"
    ],
    "wof:name":"Tim The Painter",
    "wof:placetype":"venue"
},
  "geometry": {"coordinates":[-76.412239,40.05117],"type":"Point"}
}