{
  "type": "Feature",
  "properties": {
    "iso:country":"US",
    "sg:address":"460 Twin Hills Rd",
    "sg:city":"Grindstone",
    "sg:classifiers":[
        {
            "category":"Building & Trades",
            "subcategory":"Construction",
            "type":"Services"
        }
    ],
    "sg:phone":"+1 724 246 1374",
    "sg:postcode":"15442",
    "sg:province":"PA",
    "sg:tags":[
        "contractor",
        "mason"
    ],
    "wof:name":"Brian King",
    "wof:placetype":"venue"
},
  "geometry": {"coordinates":[-79.865791,39.974411],"type":"Point"}
}