{
  "type": "Feature",
  "properties": {
    "addr:full":"3874 Perrysville Ave Pittsburgh PA 15214",
    "addr:housenumber":"3874",
    "addr:postcode":"15214",
    "addr:street":"Perrysville Ave",
    "iso:country":"US",
    "sg:address":"3874 Perrysville Ave",
    "sg:city":"Pittsburgh",
    "sg:classifiers":[
        {
            "category":"Government",
            "subcategory":"Court House",
            "type":"Public Place"
        }
    ],
    "sg:phone":"+1   ",
    "sg:postcode":"15214",
    "sg:province":"PA",
    "sg:tags":[
        "state"
    ],
    "wof:name":"Magisterial District 05-2-42",
    "wof:placetype":"venue"
},
  "geometry": {"coordinates":[-80.018148,40.489285],"type":"Point"}
}