{
  "type": "Feature",
  "properties": {
    "addr:full":"3439 Bath Pike Bethlehem PA 18017",
    "addr:housenumber":"3439",
    "addr:postcode":"18017",
    "addr:street":"Bath Pike",
    "iso:country":"US",
    "sg:address":"3439 Bath Pike",
    "sg:city":"Bethlehem",
    "sg:classifiers":[
        {
            "category":"Retail",
            "subcategory":"Auto Repair",
            "type":"Services"
        }
    ],
    "sg:phone":"+1 610 691 8000",
    "sg:postcode":"18017",
    "sg:province":"PA",
    "sg:tags":[
        "repairing",
        "automobile"
    ],
    "sg:website":"www.keypontiacgmc.com",
    "wof:name":"Key Pontiac",
    "wof:placetype":"venue"
},
  "geometry": {"coordinates":[-75.384415,40.663585],"type":"Point"}
}