{
  "type": "Feature",
  "properties": {
    "addr:full":"411 Pansy St Reading PA 19611",
    "addr:housenumber":"411",
    "addr:postcode":"19611",
    "addr:street":"Pansy St",
    "iso:country":"US",
    "sg:address":"411 Pansy St",
    "sg:city":"Reading",
    "sg:classifiers":[
        {
            "category":"Building & Trades",
            "subcategory":"Landscaping Services",
            "type":"Services"
        }
    ],
    "sg:phone":"+1 610 376 9364",
    "sg:postcode":"19611",
    "sg:province":"PA",
    "sg:tags":[
        "designer",
        "consultant",
        "tree",
        "contractor",
        "landscape"
    ],
    "wof:name":"Paul's Tree Service",
    "wof:placetype":"venue"
},
  "geometry": {"coordinates":[-75.93044500000001,40.317277],"type":"Point"}
}