{
  "type": "Feature",
  "properties": {
    "iso:country":"US",
    "sg:address":"37 W 4th St",
    "sg:city":"Williamsport",
    "sg:classifiers":[
        {
            "category":"Bars & Pubs",
            "type":"Food & Drink"
        }
    ],
    "sg:phone":"+1 570 327 9570",
    "sg:postcode":"17701",
    "sg:province":"PA",
    "wof:name":"Kelly's Grill",
    "wof:placetype":"venue"
},
  "geometry": {"coordinates":[-77.002999,41.241741],"type":"Point"}
}