{
  "type": "Feature",
  "properties": {
    "iso:country":"US",
    "sg:address":"2555 New Centerville Rd",
    "sg:city":"Rockwood",
    "sg:classifiers":[
        {
            "category":"Mining & Drilling",
            "type":"Manufacturing & Wholesale Goods"
        }
    ],
    "sg:phone":"+1 814 926 2815",
    "sg:postcode":"15557",
    "sg:province":"PA",
    "sg:tags":[
        "stone"
    ],
    "wof:name":"New Centerville Stone & Sand",
    "wof:placetype":"venue"
},
  "geometry": {"coordinates":[-79.184118,39.955965],"type":"Point"}
}