{
  "type": "Feature",
  "properties": {
    "iso:country":"US",
    "sg:address":"3301 Birney Ave",
    "sg:city":"Moosic",
    "sg:classifiers":[
        {
            "category":"Restaurant",
            "type":"Food & Drink"
        }
    ],
    "sg:phone":"+1 570 342 4247",
    "sg:postcode":"18507",
    "sg:province":"PA",
    "sg:tags":[
        "eating",
        "pizza"
    ],
    "wof:name":"L&L Pizza Subs & More",
    "wof:placetype":"venue"
},
  "geometry": {"coordinates":[-75.69776899999999,41.375519],"type":"Point"}
}