{
  "type": "Feature",
  "properties": {
    "iso:country":"US",
    "sg:address":"4091 Saltsburg Rd Ste B",
    "sg:city":"Murrysville",
    "sg:classifiers":[
        {
            "category":"Personal",
            "subcategory":"Beauty Salon",
            "type":"Services"
        }
    ],
    "sg:phone":"+1 412 795 5599",
    "sg:postcode":"15668",
    "sg:province":"PA",
    "sg:tags":[
        "hair",
        "stylist"
    ],
    "wof:name":"Hair Dimensions",
    "wof:placetype":"venue"
},
  "geometry": {"coordinates":[-79.69072,40.490631],"type":"Point"}
}