{
  "type": "Feature",
  "properties": {
    "iso:country":"US",
    "sg:address":"2660 Lititz Pike",
    "sg:city":"Lancaster",
    "sg:classifiers":[
        {
            "category":"Organizations",
            "subcategory":"Religious Organization",
            "type":"Services"
        }
    ],
    "sg:phone":"+1   ",
    "sg:postcode":"17601",
    "sg:province":"PA",
    "sg:tags":[
        "denomination",
        "miscellaneous",
        "church"
    ],
    "wof:name":"Long Mem Untd Methdst Church",
    "wof:placetype":"venue"
},
  "geometry": {"coordinates":[-76.305336,40.099927],"type":"Point"}
}