{
  "type": "Feature",
  "properties": {
    "iso:country":"US",
    "sg:address":"390 Chester Pike",
    "sg:city":"Ridley Park",
    "sg:classifiers":[
        {
            "category":"Retail",
            "subcategory":"Auto Repair",
            "type":"Services"
        }
    ],
    "sg:phone":"+1 610 583 1500",
    "sg:postcode":"19078",
    "sg:province":"PA",
    "sg:tags":[
        "repairing",
        "automobile"
    ],
    "wof:name":"Lou's Gulf Svc Ctr",
    "wof:placetype":"venue"
},
  "geometry": {"coordinates":[-75.329813,39.872059],"type":"Point"}
}