{
  "type": "Feature",
  "properties": {
    "iso:country":"US",
    "sg:address":"5000 Waterdam Plaza Dr",
    "sg:city":"Canonsburg",
    "sg:classifiers":[
        {
            "category":"Health Services",
            "subcategory":"Doctor",
            "type":"Services"
        }
    ],
    "sg:phone":"+1 724 942 4372",
    "sg:postcode":"15317",
    "sg:province":"PA",
    "sg:tags":[
        "physician",
        "pediatrics",
        "family",
        "practice",
        "surgeons",
        "medicine",
        "surgeon",
        "public"
    ],
    "sg:website":"http://www.waterdamfamilypractice.com",
    "wof:name":"Mittell David C MD",
    "wof:placetype":"venue"
},
  "geometry": {"coordinates":[-80.136239,40.264206],"type":"Point"}
}