{
  "type": "Feature",
  "properties": {
    "iso:country":"US",
    "sg:address":"105 Laporte Dr",
    "sg:city":"Cranberry Twp",
    "sg:classifiers":[
        {
            "category":"Building & Trades",
            "subcategory":"Construction",
            "type":"Services"
        }
    ],
    "sg:phone":"+1 724 776 5833",
    "sg:postcode":"16066",
    "sg:province":"PA",
    "sg:tags":[
        "tile",
        "dealer"
    ],
    "wof:name":"Regis J Kuntz Ceramic Tile",
    "wof:placetype":"venue"
},
  "geometry": {"coordinates":[-80.12522800000001,40.680815],"type":"Point"}
}