{
  "type": "Feature",
  "properties": {
    "iso:country":"US",
    "sg:address":"5912 Ridge Ave",
    "sg:city":"Philadelphia",
    "sg:classifiers":[
        {
            "category":"Health Services",
            "subcategory":"Dentist",
            "type":"Services"
        }
    ],
    "sg:phone":"+1 215 482 8500",
    "sg:postcode":"19128",
    "sg:province":"PA",
    "sg:tags":[
        "orthodontist"
    ],
    "sg:website":"www.broganbraces.com",
    "wof:name":"Brogan Orthodontics",
    "wof:placetype":"venue"
},
  "geometry": {"coordinates":[-75.212001,40.030413],"type":"Point"}
}