{
  "type": "Feature",
  "properties": {
    "iso:country":"US",
    "sg:address":"5010 Carlisle Rd",
    "sg:city":"Dover",
    "sg:classifiers":[
        {
            "category":"Home & Garden",
            "subcategory":"Furniture",
            "type":"Retail Goods"
        }
    ],
    "sg:phone":"+1   ",
    "sg:postcode":"17315",
    "sg:province":"PA",
    "wof:name":"Goods Furniture",
    "wof:placetype":"venue"
},
  "geometry": {"coordinates":[-76.86012700000001,40.011299],"type":"Point"}
}