{
  "type": "Feature",
  "properties": {
    "iso:country":"US",
    "sg:address":"46 S Mountain Blvd",
    "sg:city":"Mountain Top",
    "sg:classifiers":[
        {
            "category":"Banks & Credit Unions",
            "subcategory":"Bank",
            "type":"Services"
        }
    ],
    "sg:phone":"+1 570 474 6232",
    "sg:postcode":"18707",
    "sg:province":"PA",
    "wof:name":"Omega Bank",
    "wof:placetype":"venue"
},
  "geometry": {"coordinates":[-75.88773399999999,41.160147],"type":"Point"}
}