{
  "type": "Feature",
  "properties": {
    "iso:country":"US",
    "sg:address":"224 Rushley Way",
    "sg:city":"Media",
    "sg:classifiers":[
        {
            "category":"Building & Trades",
            "subcategory":"Cleaning & Sanitation",
            "type":"Services"
        }
    ],
    "sg:phone":"+1 610 459 4624",
    "sg:postcode":"19063",
    "sg:province":"PA",
    "sg:tags":[
        "janitor"
    ],
    "wof:name":"Chester House Window Cleaning",
    "wof:placetype":"venue"
},
  "geometry": {"coordinates":[-75.45738799999999,39.923561],"type":"Point"}
}