{
  "type": "Feature",
  "properties": {
    "iso:country":"US",
    "sg:address":"214 S 4th St",
    "sg:city":"Perkasie",
    "sg:classifiers":[
        {
            "category":"Manufacturing",
            "subcategory":"Pottery",
            "type":"Manufacturing & Wholesale Goods"
        }
    ],
    "sg:phone":"+1 215 258 1050",
    "sg:postcode":"18944",
    "sg:province":"PA",
    "wof:name":"Seasons Gone By",
    "wof:placetype":"venue"
},
  "geometry": {"coordinates":[-75.296541,40.370572],"type":"Point"}
}