{
  "type": "Feature",
  "properties": {
    "addr:full":"387 W Lancaster Ave Wayne PA 19087",
    "addr:housenumber":"387",
    "addr:postcode":"19087",
    "addr:street":"W Lancaster Ave",
    "iso:country":"US",
    "sg:address":"387 W Lancaster Ave",
    "sg:city":"Wayne",
    "sg:classifiers":[
        {
            "category":"Professional",
            "type":"Services"
        },
        {
            "category":"Restaurant",
            "type":"Food & Drink"
        }
    ],
    "sg:phone":"+1 610 687 3320",
    "sg:postcode":"19087",
    "sg:province":"PA",
    "sg:tags":[
        "style",
        "bar",
        "family",
        "sushi",
        "japanese",
        "lunch",
        "caterer",
        "brunch",
        "breakfast"
    ],
    "wof:name":"Hana",
    "wof:placetype":"venue"
},
  "geometry": {"coordinates":[-75.39955,40.044265],"type":"Point"}
}