{
  "type": "Feature",
  "properties": {
    "iso:country":"US",
    "sg:address":"1309 Beechwood Blvd",
    "sg:city":"Pittsburgh",
    "sg:classifiers":[
        {
            "category":"Professional",
            "type":"Services"
        }
    ],
    "sg:phone":"+1   ",
    "sg:postcode":"15217",
    "sg:province":"PA",
    "wof:name":"Jordan L Schlessel Co",
    "wof:placetype":"venue"
},
  "geometry": {"coordinates":[-79.917737,40.444496],"type":"Point"}
}