{
  "type": "Feature",
  "properties": {
    "iso:country":"US",
    "sg:address":"3648 Greenwood Cir",
    "sg:city":"Chalfont",
    "sg:classifiers":[
        {
            "category":"Building & Trades",
            "subcategory":"Construction",
            "type":"Services"
        }
    ],
    "sg:phone":"+1 215 313 0445",
    "sg:postcode":"18914",
    "sg:province":"PA",
    "sg:tags":[
        "contractor"
    ],
    "sg:website":"www.bold-construction.com",
    "wof:name":"Bold Construction, LLC",
    "wof:placetype":"venue"
},
  "geometry": {"coordinates":[-75.182773,40.276809],"type":"Point"}
}