{
  "type": "Feature",
  "properties": {
    "iso:country":"US",
    "sg:address":"2485 Swamp Pike",
    "sg:city":"Gilbertsville",
    "sg:classifiers":[
        {
            "category":"Restaurant",
            "type":"Food & Drink"
        },
        {
            "category":"Bars & Pubs",
            "type":"Food & Drink"
        }
    ],
    "sg:phone":"+1 610 327 9192",
    "sg:postcode":"19525",
    "sg:province":"PA",
    "sg:tags":[
        "drinking",
        "eating"
    ],
    "wof:name":"All Star Cafe Inc",
    "wof:placetype":"venue"
},
  "geometry": {"coordinates":[-75.56794600000001,40.279624],"type":"Point"}
}