{
  "type": "Feature",
  "properties": {
    "iso:country":"US",
    "sg:address":"611 S 3rd St",
    "sg:city":"Philadelphia",
    "sg:classifiers":[
        {
            "category":"Bars & Pubs",
            "type":"Food & Drink"
        },
        {
            "category":"Restaurant",
            "type":"Food & Drink"
        },
        {
            "category":"Bars & Pubs",
            "subcategory":"Sports Bar",
            "type":"Food & Drink"
        }
    ],
    "sg:phone":"+1 215 574 9495",
    "sg:postcode":"19147",
    "sg:province":"PA",
    "sg:tags":[
        "irish"
    ],
    "sg:website":"www.onealspub.com",
    "wof:name":"O'Neal's Pub",
    "wof:placetype":"venue"
},
  "geometry": {"coordinates":[-75.147644,39.94116],"type":"Point"}
}