{
  "type": "Feature",
  "properties": {
    "iso:country":"US",
    "sg:address":"113 Talbot Ave",
    "sg:city":"Greensburg",
    "sg:classifiers":[
        {
            "category":"Building & Trades",
            "subcategory":"Cleaning & Sanitation",
            "type":"Services"
        }
    ],
    "sg:phone":"+1   ",
    "sg:postcode":"15601",
    "sg:province":"PA",
    "sg:tags":[
        "maintenance"
    ],
    "wof:name":"Greensburg Svc ADM Maint Off",
    "wof:placetype":"venue"
},
  "geometry": {"coordinates":[-79.541043,40.302959],"type":"Point"}
}