{
  "type": "Feature",
  "properties": {
    "iso:country":"US",
    "sg:address":"166 Covington Rd",
    "sg:city":"Philadelphia",
    "sg:classifiers":[
        {
            "category":"Professional",
            "type":"Services"
        }
    ],
    "sg:phone":"+1   ",
    "sg:postcode":"19120",
    "sg:province":"PA",
    "wof:name":"Herbert Frayer",
    "wof:placetype":"venue"
},
  "geometry": {"coordinates":[-75.11891900000001,40.050743],"type":"Point"}
}