{
  "type": "Feature",
  "properties": {
    "iso:country":"US",
    "sg:address":"6800 Essington Ave",
    "sg:city":"Philadelphia",
    "sg:classifiers":[
        {
            "category":"Autos & Motor Vehicles",
            "subcategory":"Automobile Sales",
            "type":"Retail Goods"
        }
    ],
    "sg:phone":"+1 215 937 9412",
    "sg:postcode":"19153",
    "sg:province":"PA",
    "sg:tags":[
        "automotive"
    ],
    "sg:website":"giannaupullit.com",
    "wof:name":"Gianna's Salvage & U Pull It",
    "wof:placetype":"venue"
},
  "geometry": {"coordinates":[-75.223432,39.90725],"type":"Point"}
}