{
  "type": "Feature",
  "properties": {
    "addr:full":"2415 Kutztown Rd Reading PA 19605",
    "addr:housenumber":"2415",
    "addr:postcode":"19605",
    "addr:street":"Kutztown Rd",
    "iso:country":"US",
    "sg:address":"2415 Kutztown Rd",
    "sg:city":"Reading",
    "sg:classifiers":[
        {
            "category":"Manufacturing",
            "subcategory":"Petroleum Products",
            "type":"Manufacturing & Wholesale Goods"
        }
    ],
    "sg:phone":"+1 610 929 0716",
    "sg:postcode":"19605",
    "sg:province":"PA",
    "sg:tags":[
        "asphalt"
    ],
    "sg:website":"www.hkgroup.com",
    "wof:name":"Windsor Service Inc",
    "wof:placetype":"venue"
},
  "geometry": {"coordinates":[-75.91985099999999,40.37176],"type":"Point"}
}