{
  "type": "Feature",
  "properties": {
    "iso:country":"US",
    "sg:address":"746 Washington St",
    "sg:city":"Easton",
    "sg:classifiers":[
        {
            "category":"Building & Trades",
            "subcategory":"Construction",
            "type":"Services"
        }
    ],
    "sg:phone":"+1 610 258 3784",
    "sg:postcode":"18042",
    "sg:province":"PA",
    "sg:tags":[
        "control",
        "corrosion",
        "contractor"
    ],
    "sg:website":"http://www.sil-mar.com",
    "wof:name":"Sil-Mar Construction Corp",
    "wof:placetype":"venue"
},
  "geometry": {"coordinates":[-75.218992,40.686971],"type":"Point"}
}