{
  "type": "Feature",
  "properties": {
    "addr:full":"691 Woodland Bigler Hwy Woodland PA 16881",
    "addr:housenumber":"691",
    "addr:postcode":"16881",
    "addr:street":"Woodland Bigler Hwy",
    "iso:country":"US",
    "sg:address":"691 Woodland Bigler Hwy",
    "sg:city":"Woodland",
    "sg:classifiers":[
        {
            "category":"Manufacturing",
            "subcategory":"Tools & Machinery",
            "type":"Manufacturing & Wholesale Goods"
        }
    ],
    "sg:phone":"+1 814 857 5244",
    "sg:postcode":"16881",
    "sg:province":"PA",
    "sg:tags":[
        "machine",
        "shop"
    ],
    "wof:name":"Utmost Machine Inc",
    "wof:placetype":"venue"
},
  "geometry": {"coordinates":[-78.309451,40.992573],"type":"Point"}
}