{
  "type": "Feature",
  "properties": {
    "addr:full":"1680 S 4th St Allentown PA 18103",
    "addr:housenumber":"1680",
    "addr:postcode":"18103",
    "addr:street":"S 4Th St",
    "iso:country":"US",
    "sg:address":"1680 S 4th St",
    "sg:city":"Allentown",
    "sg:classifiers":[
        {
            "category":"Personal",
            "subcategory":"Beauty Salon",
            "type":"Services"
        }
    ],
    "sg:phone":"+1 610 797 0681",
    "sg:postcode":"18103",
    "sg:province":"PA",
    "sg:tags":[
        "shop"
    ],
    "wof:name":"Studio Nails",
    "wof:placetype":"venue"
},
  "geometry": {"coordinates":[-75.459233,40.584977],"type":"Point"}
}