{
  "type": "Feature",
  "properties": {
    "iso:country":"US",
    "sg:address":"304 Philadelphia St",
    "sg:city":"Indiana",
    "sg:classifiers":[
        {
            "category":"Autos & Motor Vehicles",
            "subcategory":"Fuel & Gas Station",
            "type":"Retail Goods"
        },
        {
            "category":"Retail",
            "subcategory":"Auto Repair",
            "type":"Services"
        }
    ],
    "sg:phone":"+1 724 349 9450",
    "sg:postcode":"15701",
    "sg:province":"PA",
    "sg:tags":[
        "automobile",
        "inspection"
    ],
    "sg:website":"http://www.napaautocare.com/",
    "wof:name":"Tire Express Service Center Inc",
    "wof:placetype":"venue"
},
  "geometry": {"coordinates":[-79.143307,40.622814],"type":"Point"}
}