{
  "type": "Feature",
  "properties": {
    "iso:country":"US",
    "sg:address":"2300 Computer Ave",
    "sg:city":"Willow Grove",
    "sg:classifiers":[
        {
            "category":"Shopping",
            "subcategory":"Computers & Home Electronics",
            "type":"Retail Goods"
        }
    ],
    "sg:phone":"+1 215 658 1601",
    "sg:postcode":"19090",
    "sg:province":"PA",
    "sg:tags":[
        "software"
    ],
    "sg:website":"www.triviaphone.com",
    "wof:name":"Pliner Solutions Inc",
    "wof:placetype":"venue"
},
  "geometry": {"coordinates":[-75.136898,40.155933],"type":"Point"}
}