{
  "type": "Feature",
  "properties": {
    "iso:country":"US",
    "sg:address":"5019 Friendship St",
    "sg:city":"Philadelphia",
    "sg:classifiers":[
        {
            "category":"Autos & Motor Vehicles",
            "subcategory":"Auto Supplies",
            "type":"Retail Goods"
        }
    ],
    "sg:phone":"+1 215 332 4900",
    "sg:postcode":"19135",
    "sg:province":"PA",
    "sg:tags":[
        "equipment",
        "racing",
        "car",
        "automobile"
    ],
    "wof:name":"Speed Factor",
    "wof:placetype":"venue"
},
  "geometry": {"coordinates":[-75.03400600000001,40.023889],"type":"Point"}
}