{
  "type": "Feature",
  "properties": {
    "iso:country":"US",
    "sg:address":"6 James Pl",
    "sg:city":"White Haven",
    "sg:classifiers":[
        {
            "category":"Building & Trades",
            "subcategory":"Construction",
            "type":"Services"
        }
    ],
    "sg:phone":"+1   ",
    "sg:postcode":"18661",
    "sg:province":"PA",
    "sg:tags":[
        "hanging",
        "contractor"
    ],
    "wof:name":"Ld Painting",
    "wof:placetype":"venue"
},
  "geometry": {"coordinates":[-75.77563499999999,41.064166],"type":"Point"}
}