{
  "type": "Feature",
  "properties": {
    "addr:full":"1132 Rte 18 Burgettstown PA 15021",
    "addr:housenumber":"1132",
    "addr:postcode":"15021",
    "addr:street":"Rte 18",
    "iso:country":"US",
    "sg:address":"1132 Rte 18",
    "sg:city":"Burgettstown",
    "sg:classifiers":[
        {
            "category":"Retail",
            "subcategory":"Repair Shop",
            "type":"Services"
        },
        {
            "category":"Professional",
            "subcategory":"Business Services",
            "type":"Services"
        }
    ],
    "sg:phone":"+1 724 947 9020",
    "sg:postcode":"15021",
    "sg:province":"PA",
    "sg:tags":[
        "inspection",
        "welding"
    ],
    "wof:name":"Three Rivers Gamma Service",
    "wof:placetype":"venue"
},
  "geometry": {"coordinates":[-80.441508,40.453324],"type":"Point"}
}