{
  "type": "Feature",
  "properties": {
    "iso:country":"US",
    "sg:address":"24 Sandy Rd",
    "sg:city":"New Bethlehem",
    "sg:classifiers":[
        {
            "category":"Manufacturing",
            "subcategory":"Glass & Minerals",
            "type":"Manufacturing & Wholesale Goods"
        }
    ],
    "sg:phone":"+1 814 275 3511",
    "sg:postcode":"16254",
    "sg:province":"PA",
    "sg:tags":[
        "refractory",
        "clay"
    ],
    "wof:name":"KMS Refractories",
    "wof:placetype":"venue"
},
  "geometry": {"coordinates":[-79.45149499999999,41.32851],"type":"Point"}
}