{
  "type": "Feature",
  "properties": {
    "iso:country":"US",
    "sg:address":"5425 Andrea Dr",
    "sg:city":"Allentown",
    "sg:classifiers":[
        {
            "category":"Insurance",
            "subcategory":"Insurance Agent",
            "type":"Services"
        }
    ],
    "sg:phone":"+1   ",
    "sg:postcode":"18106",
    "sg:province":"PA",
    "wof:name":"Columbia Mutual Life Insur Co",
    "wof:placetype":"venue"
},
  "geometry": {"coordinates":[-75.559808,40.558114],"type":"Point"}
}