{
  "type": "Feature",
  "properties": {
    "iso:country":"US",
    "sg:address":"3220B Mauch Chunk Rd",
    "sg:city":"Coplay",
    "sg:classifiers":[
        {
            "category":"Personal",
            "subcategory":"Tanning Parlor",
            "type":"Services"
        }
    ],
    "sg:phone":"+1 610 769 4545",
    "sg:postcode":"18037",
    "sg:province":"PA",
    "wof:name":"Montego Bay Tans",
    "wof:placetype":"venue"
},
  "geometry": {"coordinates":[-75.546122,40.653],"type":"Point"}
}