{
  "type": "Feature",
  "properties": {
    "iso:country":"US",
    "sg:address":"3328 Amber St",
    "sg:city":"Philadelphia",
    "sg:classifiers":[
        {
            "category":"Home & Garden",
            "subcategory":"Building Materials",
            "type":"Retail Goods"
        }
    ],
    "sg:phone":"+1 215 291 9007",
    "sg:postcode":"19134",
    "sg:province":"PA",
    "sg:tags":[
        "concrete",
        "contractor"
    ],
    "sg:website":"http://www.Clearspancontractors.com",
    "wof:name":"Clearspan Inc",
    "wof:placetype":"venue"
},
  "geometry": {"coordinates":[-75.10661399999999,39.993955],"type":"Point"}
}