{
  "type": "Feature",
  "properties": {
    "addr:full":"2400 Dairy Rd Lancaster PA 17601",
    "addr:housenumber":"2400",
    "addr:postcode":"17601",
    "addr:street":"Dairy Rd",
    "iso:country":"US",
    "sg:address":"2400 Dairy Rd",
    "sg:city":"Lancaster",
    "sg:phone":"+1 717 898 0129",
    "sg:postcode":"17601",
    "sg:province":"PA",
    "sg:tags":[
        "oil"
    ],
    "wof:name":"Franklin H Kreider",
    "wof:placetype":"venue"
},
  "geometry": {"coordinates":[-76.36468600000001,40.082932],"type":"Point"}
}