{
  "type": "Feature",
  "properties": {
    "addr:full":"544 Howe Rd Merion Station PA 19066",
    "addr:housenumber":"544",
    "addr:postcode":"19066",
    "addr:street":"Howe Rd Merion Station",
    "iso:country":"US",
    "sg:address":"544 Howe Rd",
    "sg:city":"Merion Station",
    "sg:classifiers":[
        {
            "category":"Health Services",
            "subcategory":"Health Practitioner",
            "type":"Services"
        }
    ],
    "sg:phone":"+1   ",
    "sg:postcode":"19066",
    "sg:province":"PA",
    "wof:name":"Addis-Gnkin Spech Lngage Assoc",
    "wof:placetype":"venue"
},
  "geometry": {"coordinates":[-75.248107,40.014842],"type":"Point"}
}