{
  "type": "Feature",
  "properties": {
    "iso:country":"US",
    "sg:address":"6456 Sackett St",
    "sg:city":"Philadelphia",
    "sg:classifiers":[
        {
            "category":"Restaurant",
            "type":"Food & Drink"
        }
    ],
    "sg:phone":"+1 215 335 4101",
    "sg:postcode":"19149",
    "sg:province":"PA",
    "wof:name":"Happy Wok Chinese Restaurant",
    "wof:placetype":"venue"
},
  "geometry": {"coordinates":[-75.058342,40.028997],"type":"Point"}
}