{
  "type": "Feature",
  "properties": {
    "iso:country":"US",
    "sg:address":"378 Pottsville Saint Clair Hwy",
    "sg:city":"Pottsville",
    "sg:classifiers":[
        {
            "category":"Retail",
            "subcategory":"Auto Repair",
            "type":"Services"
        }
    ],
    "sg:phone":"+1 570 429 1414",
    "sg:postcode":"17901",
    "sg:province":"PA",
    "sg:tags":[
        "transmission"
    ],
    "wof:name":"AAMCO Transmissions",
    "wof:placetype":"venue"
},
  "geometry": {"coordinates":[-76.187623,40.703282],"type":"Point"}
}