{
  "type": "Feature",
  "properties": {
    "iso:country":"US",
    "sg:address":"213 Market St",
    "sg:city":"Elizabeth",
    "sg:classifiers":[
        {
            "category":"Professional",
            "subcategory":"Lawyer & Legal Services",
            "type":"Services"
        }
    ],
    "sg:phone":"+1 412 384 3003",
    "sg:postcode":"15037",
    "sg:province":"PA",
    "sg:tags":[
        "attorney"
    ],
    "wof:name":"Yablonski Costello & Leckie Leckie PC",
    "wof:placetype":"venue"
},
  "geometry": {"coordinates":[-79.886703,40.2728],"type":"Point"}
}