{
  "type": "Feature",
  "properties": {
    "addr:full":"5830 Ellsworth Ave Pittsburgh PA 15232",
    "addr:housenumber":"5830",
    "addr:postcode":"15232",
    "addr:street":"Ellsworth Ave",
    "iso:country":"US",
    "sg:address":"5830 Ellsworth Ave",
    "sg:city":"Pittsburgh",
    "sg:classifiers":[
        {
            "category":"Restaurant",
            "type":"Food & Drink"
        }
    ],
    "sg:phone":"+1 412 441 9344",
    "sg:postcode":"15232",
    "sg:province":"PA",
    "sg:tags":[
        "eating"
    ],
    "wof:name":"Crazy Mocha Coffee Co",
    "wof:placetype":"venue"
},
  "geometry": {"coordinates":[-79.930516,40.456359],"type":"Point"}
}