{
  "type": "Feature",
  "properties": {
    "iso:country":"US",
    "sg:address":"108 Walnut St",
    "sg:city":"Harrisburg",
    "sg:classifiers":[
        {
            "category":"Professional",
            "subcategory":"Lawyer & Legal Services",
            "type":"Services"
        }
    ],
    "sg:phone":"+1 717 238 3645",
    "sg:postcode":"17101",
    "sg:province":"PA",
    "wof:name":"Berman Arthur Atty",
    "wof:placetype":"venue"
},
  "geometry": {"coordinates":[-76.883913,40.259558],"type":"Point"}
}