{
  "type": "Feature",
  "properties": {
    "addr:full":"100 Feidt Rd Millersburg PA 17061",
    "addr:housenumber":"100",
    "addr:postcode":"17061",
    "addr:street":"Feidt Rd",
    "iso:country":"US",
    "sg:address":"100 Feidt Rd",
    "sg:city":"Millersburg",
    "sg:classifiers":[
        {
            "category":"Farming",
            "subcategory":"Dairy Farm",
            "type":"Manufacturing & Wholesale Goods"
        }
    ],
    "sg:phone":"+1   ",
    "sg:postcode":"17061",
    "sg:province":"PA",
    "wof:name":"Feidt Eugenea",
    "wof:placetype":"venue"
},
  "geometry": {"coordinates":[-76.85678799999999,40.556094],"type":"Point"}
}