{
  "type": "Feature",
  "properties": {
    "iso:country":"US",
    "sg:address":"2990 Industrial Blvd",
    "sg:city":"Bethel Park",
    "sg:classifiers":[
        {
            "category":"Manufacturing",
            "subcategory":"Tools & Machinery",
            "type":"Manufacturing & Wholesale Goods"
        }
    ],
    "sg:phone":"+1 412 854 1133",
    "sg:postcode":"15102",
    "sg:province":"PA",
    "sg:tags":[
        "physician",
        "surgeon"
    ],
    "wof:name":"Instrumentation Industries Inc",
    "wof:placetype":"venue"
},
  "geometry": {"coordinates":[-80.040104,40.32706],"type":"Point"}
}