{
  "type": "Feature",
  "properties": {
    "iso:country":"US",
    "sg:address":"129 Harristown Rd",
    "sg:city":"Paradise",
    "sg:classifiers":[
        {
            "category":"Building & Trades",
            "subcategory":"Construction",
            "type":"Services"
        }
    ],
    "sg:phone":"+1   ",
    "sg:postcode":"17562",
    "sg:province":"PA",
    "sg:tags":[
        "contractor"
    ],
    "wof:name":"Lefever Masonry",
    "wof:placetype":"venue"
},
  "geometry": {"coordinates":[-76.08793799999999,40.006445],"type":"Point"}
}