{
  "type": "Feature",
  "properties": {
    "iso:country":"US",
    "sg:address":"212 Oakmont Dr",
    "sg:city":"Blue Bell",
    "sg:classifiers":[
        {
            "category":"Shopping",
            "subcategory":"Gifts & Souvenirs",
            "type":"Retail Goods"
        }
    ],
    "sg:phone":"+1   ",
    "sg:postcode":"19422",
    "sg:province":"PA",
    "wof:name":"First Equity Card Corp",
    "wof:placetype":"venue"
},
  "geometry": {"coordinates":[-75.290353,40.173692],"type":"Point"}
}