{
  "type": "Feature",
  "properties": {
    "iso:country":"US",
    "sg:address":"209 W Chester Rd",
    "sg:city":"West Chester",
    "sg:classifiers":[
        {
            "category":"Wholesale",
            "subcategory":"Construction Materials",
            "type":"Manufacturing & Wholesale Goods"
        }
    ],
    "sg:phone":"+1 610 696 4061",
    "sg:postcode":"19382",
    "sg:province":"PA",
    "wof:name":"Pleasant Hardware & Supply",
    "wof:placetype":"venue"
},
  "geometry": {"coordinates":[-75.544476,39.910824],"type":"Point"}
}