{
  "type": "Feature",
  "properties": {
    "iso:country":"US",
    "sg:address":"73 Wyoming Valley Mall",
    "sg:city":"Wilkes Barre",
    "sg:classifiers":[
        {
            "category":"Utilities",
            "subcategory":"Mobile Phone",
            "type":"Services"
        }
    ],
    "sg:phone":"+1   ",
    "sg:postcode":"18702",
    "sg:province":"PA",
    "sg:tags":[
        "communication",
        "radiotelephone"
    ],
    "wof:name":"Verizon",
    "wof:placetype":"venue"
},
  "geometry": {"coordinates":[-75.84219,41.249955],"type":"Point"}
}