{
  "type": "Feature",
  "properties": {
    "addr:full":"350 S 2nd St Philadelphia PA 19106",
    "addr:housenumber":"350",
    "addr:postcode":"19106",
    "addr:street":"S 2Nd St",
    "iso:country":"US",
    "sg:address":"350 S 2nd St",
    "sg:city":"Philadelphia",
    "sg:classifiers":[
        {
            "category":"Banks & Credit Unions",
            "subcategory":"Bank",
            "type":"Services"
        }
    ],
    "sg:phone":"+1   ",
    "sg:postcode":"19106",
    "sg:province":"PA",
    "sg:tags":[
        "national",
        "commercial"
    ],
    "wof:name":"Wachovia Bank National Assn",
    "wof:placetype":"venue"
},
  "geometry": {"coordinates":[-75.145293,39.943242],"type":"Point"}
}