{
  "type": "Feature",
  "properties": {
    "addr:full":"12 Penns Trl Newtown PA 18940",
    "addr:housenumber":"12",
    "addr:postcode":"18940",
    "addr:street":"Penns Trl",
    "iso:country":"US",
    "sg:address":"12 Penns Trl",
    "sg:city":"Newtown",
    "sg:classifiers":[
        {
            "category":"Social Services",
            "type":"Services"
        }
    ],
    "sg:phone":"+1   ",
    "sg:postcode":"18940",
    "sg:province":"PA",
    "wof:name":"Busby Associates",
    "wof:placetype":"venue"
},
  "geometry": {"coordinates":[-74.909358,40.228297],"type":"Point"}
}