{
  "type": "Feature",
  "properties": {
    "iso:country":"US",
    "sg:address":"16 Observatory St",
    "sg:city":"Manor",
    "sg:classifiers":[
        {
            "category":"Professional",
            "subcategory":"Detective & Security Services",
            "type":"Services"
        }
    ],
    "sg:phone":"+1 724 864 4981",
    "sg:postcode":"15665",
    "sg:province":"PA",
    "sg:tags":[
        "information",
        "bureau"
    ],
    "wof:name":"Gongaware, S.M. Market Research Service, Inc.",
    "wof:placetype":"venue"
},
  "geometry": {"coordinates":[-79.669327,40.334728],"type":"Point"}
}