{
  "type": "Feature",
  "properties": {
    "iso:country":"US",
    "sg:address":"440 Gooseville Rd",
    "sg:city":"New Oxford",
    "sg:phone":"+1   ",
    "sg:postcode":"17350",
    "sg:province":"PA",
    "sg:tags":[
        "farm",
        "corn",
        "soybean"
    ],
    "wof:name":"Gary Keckler",
    "wof:placetype":"venue"
},
  "geometry": {"coordinates":[-77.07425000000001,39.932006],"type":"Point"}
}