{
  "type": "Feature",
  "properties": {
    "addr:full":"145 N 6th St Reading PA 19601",
    "addr:housenumber":"145",
    "addr:postcode":"19601",
    "addr:street":"N 6Th St",
    "iso:country":"US",
    "sg:address":"145 N 6th St",
    "sg:city":"Reading",
    "sg:classifiers":[
        {
            "category":"Social Services",
            "type":"Services"
        },
        {
            "category":"Social Services",
            "subcategory":"Child Care",
            "type":"Services"
        }
    ],
    "sg:phone":"+1 610 378 2267",
    "sg:postcode":"19601",
    "sg:province":"PA",
    "sg:tags":[
        "centers-adult",
        "center",
        "day"
    ],
    "sg:website":"http://www.westlakecdc.com",
    "wof:name":"St Joseph Adult Day Care Ctr",
    "wof:placetype":"venue"
},
  "geometry": {"coordinates":[-75.925845,40.337588],"type":"Point"}
}