{
  "type": "Feature",
  "properties": {
    "iso:country":"US",
    "sg:address":"416 Broad St",
    "sg:city":"Montoursville",
    "sg:classifiers":[
        {
            "category":"Retail",
            "subcategory":"Veterinary Services",
            "type":"Services"
        }
    ],
    "sg:phone":"+1 570 368 5937",
    "sg:postcode":"17754",
    "sg:province":"PA",
    "wof:name":"Montoursville Veterinary Hosp",
    "wof:placetype":"venue"
},
  "geometry": {"coordinates":[-76.92404500000001,41.249201],"type":"Point"}
}