{
  "type": "Feature",
  "properties": {
    "addr:full":"340 W Bayfront Pkwy Erie PA 16507",
    "addr:housenumber":"340",
    "addr:postcode":"16507",
    "addr:street":"W Bayfront Pkwy",
    "iso:country":"US",
    "sg:address":"340 W Bayfront Pkwy",
    "sg:city":"Erie",
    "sg:classifiers":[
        {
            "category":"Government",
            "subcategory":"Office",
            "type":"Public Place"
        }
    ],
    "sg:phone":"+1 814 455 1256",
    "sg:postcode":"16507",
    "sg:province":"PA",
    "sg:tags":[
        "village"
    ],
    "wof:name":"Parking Authority-Meter Repair",
    "wof:placetype":"venue"
},
  "geometry": {"coordinates":[-80.099197,42.130572],"type":"Point"}
}