{
  "type": "Feature",
  "properties": {
    "addr:full":"36 Market Sq Manheim PA 17545",
    "addr:housenumber":"36",
    "addr:postcode":"17545",
    "addr:street":"Market Sq",
    "iso:country":"US",
    "sg:address":"36 Market Sq",
    "sg:city":"Manheim",
    "sg:classifiers":[
        {
            "category":"Building & Trades",
            "subcategory":"Construction",
            "type":"Services"
        }
    ],
    "sg:phone":"+1   ",
    "sg:postcode":"17545",
    "sg:province":"PA",
    "sg:tags":[
        "contractor"
    ],
    "wof:name":"Bathcrest",
    "wof:placetype":"venue"
},
  "geometry": {"coordinates":[-76.39644800000001,40.163249],"type":"Point"}
}