{
  "type": "Feature",
  "properties": {
    "iso:country":"US",
    "sg:address":"255 Elm St",
    "sg:city":"Oil City",
    "sg:classifiers":[
        {
            "category":"Professional",
            "subcategory":"Employment Agencies",
            "type":"Services"
        }
    ],
    "sg:phone":"+1   ",
    "sg:postcode":"16301",
    "sg:province":"PA",
    "wof:name":"Oil Region Career Link",
    "wof:placetype":"venue"
},
  "geometry": {"coordinates":[-79.708152,41.435183],"type":"Point"}
}