{
  "type": "Feature",
  "properties": {
    "addr:full":"1665 State Hill Rd Reading PA 19610",
    "addr:housenumber":"1665",
    "addr:postcode":"19610",
    "addr:street":"State Hill Rd",
    "iso:country":"US",
    "sg:address":"1665 State Hill Rd",
    "sg:city":"Reading",
    "sg:classifiers":[
        {
            "category":"Utilities",
            "subcategory":"Mobile Phone",
            "type":"Services"
        },
        {
            "category":"Shopping",
            "subcategory":"Mobile Phones",
            "type":"Retail Goods"
        },
        {
            "category":"Communications",
            "type":"Services"
        },
        {
            "category":"Internet Cafe",
            "subcategory":"None",
            "type":"Food & Drink"
        }
    ],
    "sg:phone":"+1 610 376 2600",
    "sg:postcode":"19610",
    "sg:province":"PA",
    "sg:tags":[
        "supply",
        "telephone",
        "wireless",
        "equipment",
        "paging",
        "signaling",
        "cellular",
        "provider"
    ],
    "sg:website":"http://www.att.com",
    "wof:name":"AT&T",
    "wof:placetype":"venue"
},
  "geometry": {"coordinates":[-75.97295699999999,40.338329],"type":"Point"}
}