{
  "type": "Feature",
  "properties": {
    "addr:full":"218 Quarry Rd Kutztown PA 19530",
    "addr:housenumber":"218",
    "addr:postcode":"19530",
    "addr:street":"Quarry Rd",
    "iso:country":"US",
    "sg:address":"218 Quarry Rd",
    "sg:city":"Kutztown",
    "sg:classifiers":[
        {
            "category":"Freight",
            "type":"Transportation"
        }
    ],
    "sg:phone":"+1 610 683 9943",
    "sg:postcode":"19530",
    "sg:province":"PA",
    "sg:tags":[
        "terminal",
        "truck",
        "facility"
    ],
    "wof:name":"Dietz & Watson Inc",
    "wof:placetype":"venue"
},
  "geometry": {"coordinates":[-75.733273,40.52478],"type":"Point"}
}