{
  "type": "Feature",
  "properties": {
    "iso:country":"US",
    "sg:address":"690 Mehring Rd",
    "sg:city":"Littlestown",
    "sg:classifiers":[
        {
            "category":"Professional",
            "subcategory":"Art Services",
            "type":"Services"
        }
    ],
    "sg:phone":"+1 717 359 8199",
    "sg:postcode":"17340",
    "sg:province":"PA",
    "sg:tags":[
        "graphic",
        "designer"
    ],
    "wof:name":"Graphics Plus",
    "wof:placetype":"venue"
},
  "geometry": {"coordinates":[-77.055189,39.736297],"type":"Point"}
}