{
  "type": "Feature",
  "properties": {
    "iso:country":"US",
    "sg:address":"224 W Court St",
    "sg:city":"Doylestown",
    "sg:classifiers":[
        {
            "category":"Real Estate",
            "subcategory":"Real Estate Agent",
            "type":"Services"
        }
    ],
    "sg:phone":"+1 215 345 3530",
    "sg:postcode":"18901",
    "sg:province":"PA",
    "wof:name":"Alliance Group Inc",
    "wof:placetype":"venue"
},
  "geometry": {"coordinates":[-75.134591,40.30719],"type":"Point"}
}