{
  "type": "Feature",
  "properties": {
    "iso:country":"US",
    "sg:address":"518 Chestnut St",
    "sg:city":"Emmaus",
    "sg:classifiers":[
        {
            "category":"Health Services",
            "subcategory":"Health Practitioner",
            "type":"Services"
        }
    ],
    "sg:phone":"+1 610 967 0770",
    "sg:postcode":"18049",
    "sg:province":"PA",
    "sg:tags":[
        "therapy",
        "physical"
    ],
    "wof:name":"St Luke's Hospital",
    "wof:placetype":"venue"
},
  "geometry": {"coordinates":[-75.49390699999999,40.534016],"type":"Point"}
}