{
  "type": "Feature",
  "properties": {
    "addr:full":"214 S High St Zelienople PA 16063",
    "addr:housenumber":"214",
    "addr:postcode":"16063",
    "addr:street":"S High St",
    "iso:country":"US",
    "sg:address":"214 S High St",
    "sg:city":"Zelienople",
    "sg:classifiers":[
        {
            "category":"Health Services",
            "subcategory":"Nursing And Care Facility",
            "type":"Services"
        }
    ],
    "sg:phone":"+1 724 287 6797",
    "sg:postcode":"16063",
    "sg:province":"PA",
    "sg:tags":[
        "home",
        "retirement",
        "community"
    ],
    "wof:name":"Maple Court Apartments",
    "wof:placetype":"venue"
},
  "geometry": {"coordinates":[-80.134979,40.793001],"type":"Point"}
}