{
  "type": "Feature",
  "properties": {
    "addr:full":"1760 Market St Ste 605 Philadelphia PA 19103",
    "addr:housenumber":"1760",
    "addr:postcode":"19103",
    "addr:street":"Market St Ste 605",
    "iso:country":"US",
    "sg:address":"1760 Market St Ste 605",
    "sg:city":"Philadelphia",
    "sg:classifiers":[
        {
            "category":"Professional",
            "subcategory":"Employment Agencies",
            "type":"Services"
        }
    ],
    "sg:phone":"+1 215 567 2390",
    "sg:postcode":"19103",
    "sg:province":"PA",
    "wof:name":"Adecco Employment Services",
    "wof:placetype":"venue"
},
  "geometry": {"coordinates":[-75.16950199999999,39.953098],"type":"Point"}
}