{
  "type": "Feature",
  "properties": {
    "addr:full":"810 Taylor Rd Windsor PA 17366",
    "addr:housenumber":"810",
    "addr:postcode":"17366",
    "addr:street":"Taylor Rd",
    "iso:country":"US",
    "sg:address":"810 Taylor Rd",
    "sg:city":"Windsor",
    "sg:classifiers":[
        {
            "category":"Professional",
            "type":"Services"
        }
    ],
    "sg:phone":"+1 717 244 6616",
    "sg:postcode":"17366",
    "sg:province":"PA",
    "sg:tags":[
        "establishment"
    ],
    "wof:name":"Motivation Corp",
    "wof:placetype":"venue"
},
  "geometry": {"coordinates":[-76.55682299999999,39.953379],"type":"Point"}
}