{
  "type": "Feature",
  "properties": {
    "addr:full":"1005 W Main St Smethport PA 16749",
    "addr:housenumber":"1005",
    "addr:postcode":"16749",
    "addr:street":"W Main St",
    "iso:country":"US",
    "sg:address":"1005 W Main St",
    "sg:city":"Smethport",
    "sg:classifiers":[
        {
            "category":"Manufacturing",
            "subcategory":"Rubber & Plastics",
            "type":"Manufacturing & Wholesale Goods"
        }
    ],
    "sg:phone":"+1 814 887 5575",
    "sg:postcode":"16749",
    "sg:province":"PA",
    "sg:tags":[
        "sealing",
        "devices",
        "gasket"
    ],
    "wof:name":"Rubberfab Gasket & Mold Inc",
    "wof:placetype":"venue"
},
  "geometry": {"coordinates":[-78.45285,41.809437],"type":"Point"}
}