{
  "type": "Feature",
  "properties": {
    "addr:full":"6500 Frankford Ave Philadelphia PA 19135",
    "addr:housenumber":"6500",
    "addr:postcode":"19135",
    "addr:street":"Frankford Ave",
    "iso:country":"US",
    "sg:address":"6500 Frankford Ave",
    "sg:city":"Philadelphia",
    "sg:classifiers":[
        {
            "category":"Food & Beverages",
            "subcategory":"Liquor & Beverages",
            "type":"Retail Goods"
        }
    ],
    "sg:phone":"+1 215 338 1910",
    "sg:postcode":"19135",
    "sg:province":"PA",
    "sg:tags":[
        "alcoholic",
        "ale-wholesale",
        "mfg",
        "drink",
        "beer",
        "soft",
        "manufacturer"
    ],
    "wof:name":"Mayfair Beverage Inc",
    "wof:placetype":"venue"
},
  "geometry": {"coordinates":[-75.056152,40.029449],"type":"Point"}
}