{
  "type": "Feature",
  "properties": {
    "addr:full":"55 E Locust Ln New Oxford PA 17350",
    "addr:housenumber":"55",
    "addr:postcode":"17350",
    "addr:street":"E Locust Ln",
    "iso:country":"US",
    "sg:address":"55 E Locust Ln",
    "sg:city":"New Oxford",
    "sg:classifiers":[
        {
            "category":"Shopping",
            "subcategory":"Gifts & Souvenirs",
            "type":"Retail Goods"
        }
    ],
    "sg:phone":"+1 717 624 4385",
    "sg:postcode":"17350",
    "sg:province":"PA",
    "wof:name":"Hodge Podge",
    "wof:placetype":"venue"
},
  "geometry": {"coordinates":[-77.046426,39.860025],"type":"Point"}
}