{
  "type": "Feature",
  "properties": {
    "iso:country":"US",
    "sg:address":"266 Woolston Dr",
    "sg:city":"Morrisville",
    "sg:classifiers":[
        {
            "category":"Organizations",
            "subcategory":"Membership Organization",
            "type":"Services"
        }
    ],
    "sg:phone":"+1   ",
    "sg:postcode":"19067",
    "sg:province":"PA",
    "sg:tags":[
        "club",
        "historical"
    ],
    "wof:name":"Delaware Valley Wing",
    "wof:placetype":"venue"
},
  "geometry": {"coordinates":[-74.818809,40.195546],"type":"Point"}
}