{
  "type": "Feature",
  "properties": {
    "iso:country":"US",
    "sg:address":"290 Locust Grove Rd",
    "sg:city":"Bainbridge",
    "sg:classifiers":[
        {
            "category":"Shopping",
            "subcategory":"Clothing, Apparel, & Fashions",
            "type":"Retail Goods"
        }
    ],
    "sg:phone":"+1   ",
    "sg:postcode":"17502",
    "sg:province":"PA",
    "sg:tags":[
        "family"
    ],
    "wof:name":"Eichhorns Inc",
    "wof:placetype":"venue"
},
  "geometry": {"coordinates":[-76.656503,40.07947],"type":"Point"}
}