{
  "type": "Feature",
  "properties": {
    "iso:country":"US",
    "sg:address":"215 Homestead St",
    "sg:city":"Pittsburgh",
    "sg:classifiers":[
        {
            "category":"Building & Trades",
            "subcategory":"Electrical",
            "type":"Services"
        }
    ],
    "sg:phone":"+1   ",
    "sg:postcode":"15218",
    "sg:province":"PA",
    "sg:tags":[
        "electrical",
        "contractor"
    ],
    "wof:name":"Fantini Electric",
    "wof:placetype":"venue"
},
  "geometry": {"coordinates":[-79.898537,40.422221],"type":"Point"}
}