{
  "type": "Feature",
  "properties": {
    "iso:country":"US",
    "sg:address":"7921 Grayson Rd",
    "sg:city":"Harrisburg",
    "sg:classifiers":[
        {
            "category":"Real Estate",
            "subcategory":"Real Estate Services",
            "type":"Services"
        },
        {
            "category":"Building & Trades",
            "subcategory":"Cleaning & Sanitation",
            "type":"Services"
        }
    ],
    "sg:phone":"+1 717 561 1404",
    "sg:postcode":"17111",
    "sg:province":"PA",
    "sg:tags":[
        "maintenance",
        "cleaners-interior"
    ],
    "wof:name":"Servpro",
    "wof:placetype":"venue"
},
  "geometry": {"coordinates":[-76.750763,40.263069],"type":"Point"}
}