{
  "type": "Feature",
  "properties": {
    "addr:full":"1724 Hillsdale Ave Pittsburgh PA 15216",
    "addr:housenumber":"1724",
    "addr:postcode":"15216",
    "addr:street":"Hillsdale Ave",
    "iso:country":"US",
    "sg:address":"1724 Hillsdale Ave",
    "sg:city":"Pittsburgh",
    "sg:classifiers":[
        {
            "category":"Building & Trades",
            "subcategory":"Construction",
            "type":"Services"
        }
    ],
    "sg:phone":"+1 412 563 6653",
    "sg:postcode":"15216",
    "sg:province":"PA",
    "sg:tags":[
        "house",
        "contractor"
    ],
    "wof:name":"E Z Repairs & Remodeling",
    "wof:placetype":"venue"
},
  "geometry": {"coordinates":[-80.041123,40.398827],"type":"Point"}
}