{
  "type": "Feature",
  "properties": {
    "addr:full":"115 West Ave Jenkintown PA 19046",
    "addr:housenumber":"115",
    "addr:postcode":"19046",
    "addr:street":"West Ave",
    "iso:country":"US",
    "sg:address":"115 West Ave",
    "sg:city":"Jenkintown",
    "sg:classifiers":[
        {
            "category":"Manufacturing",
            "subcategory":"Printing",
            "type":"Manufacturing & Wholesale Goods"
        }
    ],
    "sg:phone":"+1 215 886 3700",
    "sg:postcode":"19046",
    "sg:province":"PA",
    "sg:tags":[
        "publisher"
    ],
    "wof:name":"Breakaway Magazine",
    "wof:placetype":"venue"
},
  "geometry": {"coordinates":[-75.13775,40.093924],"type":"Point"}
}