{
  "type": "Feature",
  "properties": {
    "iso:country":"US",
    "sg:address":"499 Evans City Rd",
    "sg:city":"Butler",
    "sg:classifiers":[
        {
            "category":"Food & Beverages",
            "subcategory":"Groceries & Convenience Stores",
            "type":"Retail Goods"
        }
    ],
    "sg:phone":"+1 724 482 2059",
    "sg:postcode":"16001",
    "sg:province":"PA",
    "sg:website":"http://www.sheetz.com",
    "wof:name":"Sheetz 335",
    "wof:placetype":"venue"
},
  "geometry": {"coordinates":[-79.967697,40.862228],"type":"Point"}
}