{
  "type": "Feature",
  "properties": {
    "addr:full":"472 N Shirk Rd New Holland PA 17557",
    "addr:housenumber":"472",
    "addr:postcode":"17557",
    "addr:street":"N Shirk Rd",
    "iso:country":"US",
    "sg:address":"472 N Shirk Rd",
    "sg:city":"New Holland",
    "sg:classifiers":[
        {
            "category":"Autos & Motor Vehicles",
            "subcategory":"Automobile Sales",
            "type":"Retail Goods"
        }
    ],
    "sg:phone":"+1 717 351 9200",
    "sg:postcode":"17557",
    "sg:province":"PA",
    "sg:tags":[
        "equipment",
        "commercial",
        "truck"
    ],
    "wof:name":"Marco Equipment Sales LLC",
    "wof:placetype":"venue"
},
  "geometry": {"coordinates":[-76.11008200000001,40.117996],"type":"Point"}
}