{
  "type": "Feature",
  "properties": {
    "iso:country":"US",
    "sg:address":"709 Lincoln Ave",
    "sg:city":"Bowmanstown",
    "sg:classifiers":[
        {
            "category":"Restaurant",
            "type":"Food & Drink"
        }
    ],
    "sg:phone":"+1 610 852 3500",
    "sg:postcode":"18030",
    "sg:province":"PA",
    "wof:name":"Lorenzo's Pizza",
    "wof:placetype":"venue"
},
  "geometry": {"coordinates":[-75.66946299999999,40.802364],"type":"Point"}
}