{
  "type": "Feature",
  "properties": {
    "addr:full":"111 S Independence Mall E Philadelphia PA 19106",
    "addr:housenumber":"111;e",
    "addr:postcode":"19106",
    "addr:street":"S Independence Mall",
    "iso:country":"US",
    "sg:address":"111 S Independence Mall E",
    "sg:city":"Philadelphia",
    "sg:classifiers":[
        {
            "category":"Professional",
            "subcategory":"Employment Agencies",
            "type":"Services"
        }
    ],
    "sg:phone":"+1 215 592 7600",
    "sg:postcode":"19106",
    "sg:province":"PA",
    "sg:website":"www.atchealthcare.com",
    "wof:name":"Atc Healthcare Staffing Services",
    "wof:placetype":"venue"
},
  "geometry": {"coordinates":[-75.14919999999999,39.949001],"type":"Point"}
}