{
  "type": "Feature",
  "properties": {
    "addr:full":"520 South St Philadelphia PA 19147",
    "addr:housenumber":"520",
    "addr:postcode":"19147",
    "addr:street":"South St",
    "iso:country":"US",
    "sg:address":"520 South St",
    "sg:city":"Philadelphia",
    "sg:classifiers":[
        {
            "category":"Shopping",
            "subcategory":"Clothing, Apparel, & Fashions",
            "type":"Retail Goods"
        },
        {
            "category":"Shopping",
            "subcategory":"Shoes",
            "type":"Retail Goods"
        }
    ],
    "sg:phone":"+1 215 925 2333",
    "sg:postcode":"19147",
    "sg:province":"PA",
    "sg:tags":[
        "clothing",
        "store",
        "women's"
    ],
    "wof:name":"Blondie's Boutique",
    "wof:placetype":"venue"
},
  "geometry": {"coordinates":[-75.151634,39.941891],"type":"Point"}
}