{
  "type": "Feature",
  "properties": {
    "iso:country":"US",
    "sg:address":"2891 Terry Ln",
    "sg:city":"Lancaster",
    "sg:classifiers":[
        {
            "category":"Organizations",
            "subcategory":"Religious Organization",
            "type":"Services"
        }
    ],
    "sg:phone":"+1 717 299 2410",
    "sg:postcode":"17603",
    "sg:province":"PA",
    "sg:tags":[
        "clergy"
    ],
    "wof:name":"Richard L Peris",
    "wof:placetype":"venue"
},
  "geometry": {"coordinates":[-76.383447,40.04284],"type":"Point"}
}