{
  "type": "Feature",
  "properties": {
    "iso:country":"US",
    "sg:address":"409 Centennial Dr",
    "sg:city":"Morrisville",
    "sg:classifiers":[
        {
            "category":"Retail",
            "subcategory":"Auto Repair",
            "type":"Services"
        }
    ],
    "sg:phone":"+1 215 295 2822",
    "sg:postcode":"19067",
    "sg:province":"PA",
    "sg:tags":[
        "body",
        "automobile",
        "painting"
    ],
    "wof:name":"Buck's County Dent Repair",
    "wof:placetype":"venue"
},
  "geometry": {"coordinates":[-74.812809,40.200784],"type":"Point"}
}