{
  "type": "Feature",
  "properties": {
    "iso:country":"US",
    "sg:address":"1155 Washington Pike Ste 40",
    "sg:city":"Bridgeville",
    "sg:classifiers":[
        {
            "category":"Communications",
            "subcategory":"Newspaper",
            "type":"Services"
        }
    ],
    "sg:phone":"+1 412 221 3722",
    "sg:postcode":"15017",
    "sg:province":"PA",
    "sg:tags":[
        "magazine"
    ],
    "wof:name":"News Lottery & More",
    "wof:placetype":"venue"
},
  "geometry": {"coordinates":[-80.105239,40.369691],"type":"Point"}
}