{
  "type": "Feature",
  "properties": {
    "iso:country":"US",
    "sg:address":"104 Willow Wood Dr",
    "sg:city":"Collegeville",
    "sg:classifiers":[
        {
            "category":"Real Estate",
            "subcategory":"Real Estate Agent",
            "type":"Services"
        }
    ],
    "sg:phone":"+1 610 489 7150",
    "sg:postcode":"19426",
    "sg:province":"PA",
    "sg:tags":[
        "inspection"
    ],
    "wof:name":"Home Critic",
    "wof:placetype":"venue"
},
  "geometry": {"coordinates":[-75.46733399999999,40.1388],"type":"Point"}
}