{
  "type": "Feature",
  "properties": {
    "iso:country":"US",
    "sg:address":"30 Harmony Rd",
    "sg:city":"Levittown",
    "sg:classifiers":[
        {
            "category":"Education",
            "subcategory":"School",
            "type":"Public Place"
        }
    ],
    "sg:phone":"+1 215 943 1110",
    "sg:postcode":"19056",
    "sg:province":"PA",
    "sg:website":"www.neshaminy.org",
    "wof:name":"Albert Schweitzer Elementary",
    "wof:placetype":"venue"
},
  "geometry": {"coordinates":[-74.885903,40.165171],"type":"Point"}
}