{
  "type": "Feature",
  "properties": {
    "addr:full":"116 S Lake Dr Lake Harmony PA 18624",
    "addr:housenumber":"116",
    "addr:postcode":"18624",
    "addr:street":"S Lake Dr",
    "iso:country":"US",
    "sg:address":"116 S Lake Dr",
    "sg:city":"Lake Harmony",
    "sg:classifiers":[
        {
            "category":"Restaurant",
            "type":"Food & Drink"
        }
    ],
    "sg:phone":"+1 570 722 7437",
    "sg:postcode":"18624",
    "sg:province":"PA",
    "sg:tags":[
        "eating"
    ],
    "wof:name":"Harmony Pizza",
    "wof:placetype":"venue"
},
  "geometry": {"coordinates":[-75.592579,41.059382],"type":"Point"}
}