{
  "type": "Feature",
  "properties": {
    "iso:country":"US",
    "sg:address":"1650 Hewes Ave",
    "sg:city":"Linwood",
    "sg:classifiers":[
        {
            "category":"Wholesale",
            "subcategory":"Machinery & Supplies",
            "type":"Manufacturing & Wholesale Goods"
        }
    ],
    "sg:phone":"+1 610 859 2830",
    "sg:postcode":"19061",
    "sg:province":"PA",
    "wof:name":"Delaware Bay River Co-Op",
    "wof:placetype":"venue"
},
  "geometry": {"coordinates":[-75.427528,39.824615],"type":"Point"}
}