{
  "type": "Feature",
  "properties": {
    "iso:country":"US",
    "sg:address":"2116 Hartel Ave",
    "sg:city":"Philadelphia",
    "sg:classifiers":[
        {
            "category":"Wholesale",
            "subcategory":"Stationery",
            "type":"Manufacturing & Wholesale Goods"
        }
    ],
    "sg:phone":"+1   ",
    "sg:postcode":"19152",
    "sg:province":"PA",
    "sg:tags":[
        "supply"
    ],
    "wof:name":"Heller Trading Co",
    "wof:placetype":"venue"
},
  "geometry": {"coordinates":[-75.056203,40.056095],"type":"Point"}
}