{
  "type": "Feature",
  "properties": {
    "iso:country":"US",
    "sg:address":"7208 Rte 908",
    "sg:city":"Tarentum",
    "sg:classifiers":[
        {
            "category":"Food & Beverages",
            "subcategory":"Groceries & Convenience Stores",
            "type":"Retail Goods"
        }
    ],
    "sg:phone":"+1 724 224 2005",
    "sg:postcode":"15084",
    "sg:province":"PA",
    "sg:tags":[
        "farm",
        "market"
    ],
    "wof:name":"Cedar Hollow Farm Market",
    "wof:placetype":"venue"
},
  "geometry": {"coordinates":[-79.787812,40.655856],"type":"Point"}
}