{
  "type": "Feature",
  "properties": {
    "addr:full":"3033 Hemlock Dr Erie PA 16506",
    "addr:housenumber":"3033",
    "addr:postcode":"16506",
    "addr:street":"Hemlock Dr",
    "iso:country":"US",
    "sg:address":"3033 Hemlock Dr",
    "sg:city":"Erie",
    "sg:classifiers":[
        {
            "category":"Manufacturing",
            "subcategory":"Buildings",
            "type":"Manufacturing & Wholesale Goods"
        },
        {
            "category":"Building & Trades",
            "subcategory":"Construction",
            "type":"Services"
        }
    ],
    "sg:phone":"+1 814 833 7842",
    "sg:postcode":"16506",
    "sg:province":"PA",
    "sg:tags":[
        "home",
        "builder",
        "contractor"
    ],
    "wof:name":"Home Interior And Gifts Rep",
    "wof:placetype":"venue"
},
  "geometry": {"coordinates":[-80.193544,42.063841],"type":"Point"}
}