{
  "type": "Feature",
  "properties": {
    "iso:country":"US",
    "sg:address":"2406 N Charlotte St",
    "sg:city":"Pottstown",
    "sg:classifiers":[
        {
            "category":"Retail",
            "subcategory":"Auto Repair",
            "type":"Services"
        }
    ],
    "sg:phone":"+1 610 327 0105",
    "sg:postcode":"19464",
    "sg:province":"PA",
    "sg:tags":[
        "repairing",
        "automobile"
    ],
    "wof:name":"Reyn's Auto Repair",
    "wof:placetype":"venue"
},
  "geometry": {"coordinates":[-75.60105900000001,40.284147],"type":"Point"}
}