{
  "type": "Feature",
  "properties": {
    "addr:full":"211 N Ann St Lancaster PA 17602",
    "addr:housenumber":"211",
    "addr:postcode":"17602",
    "addr:street":"N Ann St",
    "iso:country":"US",
    "sg:address":"211 N Ann St",
    "sg:city":"Lancaster",
    "sg:classifiers":[
        {
            "category":"Professional",
            "type":"Services"
        }
    ],
    "sg:phone":"+1 717 293 1558",
    "sg:postcode":"17602",
    "sg:province":"PA",
    "wof:name":"Working Machine Performance",
    "wof:placetype":"venue"
},
  "geometry": {"coordinates":[-76.295648,40.042596],"type":"Point"}
}