{
  "type": "Feature",
  "properties": {
    "iso:country":"US",
    "sg:address":"436 Harleysville Pike",
    "sg:city":"Souderton",
    "sg:classifiers":[
        {
            "category":"Retail",
            "subcategory":"Auto Rental",
            "type":"Services"
        }
    ],
    "sg:phone":"+1   ",
    "sg:postcode":"18964",
    "sg:province":"PA",
    "sg:tags":[
        "truck"
    ],
    "wof:name":"R B L Leasing Corp",
    "wof:placetype":"venue"
},
  "geometry": {"coordinates":[-75.35511099999999,40.309993],"type":"Point"}
}