{
  "type": "Feature",
  "properties": {
    "iso:country":"US",
    "sg:address":"3049 Glenwood Park Ave",
    "sg:city":"Erie",
    "sg:classifiers":[
        {
            "category":"Food & Beverages",
            "subcategory":"Groceries & Convenience Stores",
            "type":"Retail Goods"
        }
    ],
    "sg:phone":"+1   ",
    "sg:postcode":"16508",
    "sg:province":"PA",
    "wof:name":"Tickles Deli",
    "wof:placetype":"venue"
},
  "geometry": {"coordinates":[-80.07374,42.106108],"type":"Point"}
}