{
  "type": "Feature",
  "properties": {
    "addr:full":"2308 Big Oak Rd Langhorne PA 19047",
    "addr:housenumber":"2308",
    "addr:postcode":"19047",
    "addr:street":"Big Oak Rd",
    "iso:country":"US",
    "sg:address":"2308 Big Oak Rd",
    "sg:city":"Langhorne",
    "sg:classifiers":[
        {
            "category":"Building & Trades",
            "subcategory":"Construction",
            "type":"Services"
        }
    ],
    "sg:phone":"+1 215 750 0400",
    "sg:postcode":"19047",
    "sg:province":"PA",
    "sg:tags":[
        "insulation",
        "heat",
        "contractor"
    ],
    "wof:name":"Tri-State Insulation Inc",
    "wof:placetype":"venue"
},
  "geometry": {"coordinates":[-74.879215,40.200794],"type":"Point"}
}