{
  "type": "Feature",
  "properties": {
    "iso:country":"US",
    "sg:address":"248 S Main St",
    "sg:city":"Shrewsbury",
    "sg:classifiers":[
        {
            "category":"Shopping",
            "type":"Retail Goods"
        }
    ],
    "sg:phone":"+1 717 235 1922",
    "sg:postcode":"17361",
    "sg:province":"PA",
    "sg:tags":[
        "memorial",
        "cemetery"
    ],
    "wof:name":"Silbaugh Memorials",
    "wof:placetype":"venue"
},
  "geometry": {"coordinates":[-76.678121,39.757032],"type":"Point"}
}