{
  "type": "Feature",
  "properties": {
    "addr:full":"3901 Market St Philadelphia PA 19104",
    "addr:housenumber":"3901",
    "addr:postcode":"19104",
    "addr:street":"Market St",
    "iso:country":"US",
    "sg:address":"3901 Market St",
    "sg:city":"Philadelphia",
    "sg:classifiers":[
        {
            "category":"Health Services",
            "subcategory":"Doctor",
            "type":"Services"
        }
    ],
    "sg:phone":"+1 215 662 1030",
    "sg:postcode":"19104",
    "sg:province":"PA",
    "sg:tags":[
        "dentist"
    ],
    "wof:name":"University Square Dental Assoc",
    "wof:placetype":"venue"
},
  "geometry": {"coordinates":[-75.201953,39.957149],"type":"Point"}
}