{
  "type": "Feature",
  "properties": {
    "iso:country":"US",
    "sg:address":"800 W Germantown Pike",
    "sg:city":"Norristown",
    "sg:classifiers":[
        {
            "category":"Education",
            "subcategory":"Special Training",
            "type":"Public Place"
        }
    ],
    "sg:phone":"+1 610 539 3393",
    "sg:postcode":"19403",
    "sg:province":"PA",
    "sg:tags":[
        "school",
        "art"
    ],
    "sg:website":"www.gnal.org",
    "wof:name":"Greater Norristown Art League",
    "wof:placetype":"venue"
},
  "geometry": {"coordinates":[-75.3526,40.1534],"type":"Point"}
}