{
  "type": "Feature",
  "properties": {
    "iso:country":"US",
    "sg:address":"17 S Mercer St",
    "sg:city":"New Castle",
    "sg:classifiers":[
        {
            "category":"Personal",
            "subcategory":"Shoe Repair & Shine",
            "type":"Services"
        }
    ],
    "sg:phone":"+1 724 654 8980",
    "sg:postcode":"16101",
    "sg:province":"PA",
    "sg:tags":[
        "repairing",
        "boot"
    ],
    "wof:name":"A & F Shoe Svc",
    "wof:placetype":"venue"
},
  "geometry": {"coordinates":[-80.345788,40.999989],"type":"Point"}
}