{
  "type": "Feature",
  "properties": {
    "addr:full":"9819 Cherry Hill Rd Albion PA 16401",
    "addr:housenumber":"9819",
    "addr:postcode":"16401",
    "addr:street":"Cherry Hill Rd",
    "iso:country":"US",
    "sg:address":"9819 Cherry Hill Rd",
    "sg:city":"Albion",
    "sg:classifiers":[
        {
            "category":"Farming",
            "subcategory":"Farm",
            "type":"Manufacturing & Wholesale Goods"
        }
    ],
    "sg:phone":"+1   ",
    "sg:postcode":"16401",
    "sg:province":"PA",
    "sg:tags":[
        "crop",
        "general"
    ],
    "wof:name":"Jeff Fellows",
    "wof:placetype":"venue"
},
  "geometry": {"coordinates":[-80.37580800000001,41.900965],"type":"Point"}
}