{
  "type": "Feature",
  "properties": {
    "addr:full":"1005 Kedron Ave Morton PA 19070",
    "addr:housenumber":"1005",
    "addr:postcode":"19070",
    "addr:street":"Kedron Ave",
    "iso:country":"US",
    "sg:address":"1005 Kedron Ave",
    "sg:city":"Morton",
    "sg:classifiers":[
        {
            "category":"Health Services",
            "subcategory":"Chiropractor",
            "type":"Services"
        }
    ],
    "sg:phone":"+1 610 543 5408",
    "sg:postcode":"19070",
    "sg:province":"PA",
    "wof:name":"Devinney Chiropractic",
    "wof:placetype":"venue"
},
  "geometry": {"coordinates":[-75.32602900000001,39.906815],"type":"Point"}
}