{
  "type": "Feature",
  "properties": {
    "iso:country":"US",
    "sg:address":"51 Qsi Ln",
    "sg:city":"Allison Park",
    "sg:classifiers":[
        {
            "category":"Professional",
            "subcategory":"Lawyer & Legal Services",
            "type":"Services"
        }
    ],
    "sg:phone":"+1 724 449 8355",
    "sg:postcode":"15101",
    "sg:province":"PA",
    "sg:tags":[
        "attorney"
    ],
    "wof:name":"Wade Osterhout & Casey",
    "wof:placetype":"venue"
},
  "geometry": {"coordinates":[-79.891715,40.60523],"type":"Point"}
}