{
  "type": "Feature",
  "properties": {
    "iso:country":"US",
    "sg:address":"4521 Old State Rd",
    "sg:city":"Mc Kean",
    "sg:classifiers":[
        {
            "category":"Farming",
            "subcategory":"Dairy Farm",
            "type":"Manufacturing & Wholesale Goods"
        }
    ],
    "sg:phone":"+1   ",
    "sg:postcode":"16426",
    "sg:province":"PA",
    "sg:tags":[
        "field",
        "corn",
        "grain",
        "cash",
        "crop"
    ],
    "wof:name":"Pavkov Milan",
    "wof:placetype":"venue"
},
  "geometry": {"coordinates":[-80.118032,41.932586],"type":"Point"}
}