{
  "type": "Feature",
  "properties": {
    "addr:full":"200 Treaty Rd Drexel Hill PA 19026",
    "addr:housenumber":"200",
    "addr:postcode":"19026",
    "addr:street":"Treaty Rd",
    "iso:country":"US",
    "sg:address":"200 Treaty Rd",
    "sg:city":"Drexel Hill",
    "sg:classifiers":[
        {
            "category":"Health Services",
            "subcategory":"Doctor",
            "type":"Services"
        }
    ],
    "sg:phone":"+1   ",
    "sg:postcode":"19026",
    "sg:province":"PA",
    "wof:name":"Philip A Shore DMD",
    "wof:placetype":"venue"
},
  "geometry": {"coordinates":[-75.331452,39.957499],"type":"Point"}
}