{
  "type": "Feature",
  "properties": {
    "iso:country":"US",
    "sg:address":"3028 Kensington Ave",
    "sg:city":"Philadelphia",
    "sg:classifiers":[
        {
            "category":"Shopping",
            "subcategory":"Discount & Variety Stores",
            "type":"Retail Goods"
        }
    ],
    "sg:phone":"+1 215 425 0919",
    "sg:postcode":"19134",
    "sg:province":"PA",
    "wof:name":"Valu Plus Inc",
    "wof:placetype":"venue"
},
  "geometry": {"coordinates":[-75.116316,39.994872],"type":"Point"}
}