{
  "type": "Feature",
  "properties": {
    "iso:country":"US",
    "sg:address":"1711 Sarah St",
    "sg:city":"Pittsburgh",
    "sg:classifiers":[
        {
            "category":"Freight",
            "type":"Transportation"
        }
    ],
    "sg:phone":"+1 412 381 0686",
    "sg:postcode":"15203",
    "sg:province":"PA",
    "wof:name":"Sun Moon & Star Trnsprtn",
    "wof:placetype":"venue"
},
  "geometry": {"coordinates":[-79.980761,40.427922],"type":"Point"}
}