{
  "type": "Feature",
  "properties": {
    "iso:country":"US",
    "sg:address":"1453 W Front St",
    "sg:city":"Berwick",
    "sg:classifiers":[
        {
            "category":"Health Services",
            "subcategory":"Doctor",
            "type":"Services"
        }
    ],
    "sg:phone":"+1 570 752 3133",
    "sg:postcode":"18603",
    "sg:province":"PA",
    "sg:tags":[
        "physician",
        "surgeon",
        "medical"
    ],
    "wof:name":"M Joseph John MD",
    "wof:placetype":"venue"
},
  "geometry": {"coordinates":[-76.256874,41.049198],"type":"Point"}
}