{
  "type": "Feature",
  "properties": {
    "addr:full":"3 Main Rd Glen Lyon PA 18617",
    "addr:housenumber":"3",
    "addr:postcode":"18617",
    "addr:street":"Main Rd Glen",
    "iso:country":"US",
    "sg:address":"3 Main Rd",
    "sg:city":"Glen Lyon",
    "sg:classifiers":[
        {
            "category":"Shopping",
            "subcategory":"Florist",
            "type":"Retail Goods"
        }
    ],
    "sg:phone":"+1 570 736 4380",
    "sg:postcode":"18617",
    "sg:province":"PA",
    "wof:name":"Susie's Red Caboose",
    "wof:placetype":"venue"
},
  "geometry": {"coordinates":[-76.09348199999999,41.152722],"type":"Point"}
}