{
  "type": "Feature",
  "properties": {
    "iso:country":"US",
    "sg:address":"2701 Allentown Rd",
    "sg:city":"Quakertown",
    "sg:classifiers":[
        {
            "category":"Banks & Credit Unions",
            "subcategory":"Bank",
            "type":"Services"
        }
    ],
    "sg:phone":"+1   ",
    "sg:postcode":"18951",
    "sg:province":"PA",
    "sg:tags":[
        "national",
        "commercial"
    ],
    "wof:name":"Tir NA Nog Farm",
    "wof:placetype":"venue"
},
  "geometry": {"coordinates":[-75.42237900000001,40.467956],"type":"Point"}
}