{
  "type": "Feature",
  "properties": {
    "iso:country":"US",
    "sg:address":"140 N 2nd St",
    "sg:city":"Stroudsburg",
    "sg:classifiers":[
        {
            "category":"Manufacturing",
            "subcategory":"Chemicals & Compounds",
            "type":"Manufacturing & Wholesale Goods"
        }
    ],
    "sg:phone":"+1   ",
    "sg:postcode":"18360",
    "sg:province":"PA",
    "sg:tags":[
        "product",
        "extrusion",
        "mfg",
        "silicone",
        "sponge",
        "sheet"
    ],
    "wof:name":"Rebtech Corporation",
    "wof:placetype":"venue"
},
  "geometry": {"coordinates":[-75.190814,40.994742],"type":"Point"}
}