{
  "type": "Feature",
  "properties": {
    "addr:full":"103 Gamma Dr Pittsburgh PA 15238",
    "addr:housenumber":"103",
    "addr:postcode":"15238",
    "addr:street":"Gamma Dr",
    "iso:country":"US",
    "sg:address":"103 Gamma Dr",
    "sg:city":"Pittsburgh",
    "sg:classifiers":[
        {
            "category":"Real Estate",
            "subcategory":"Architect",
            "type":"Services"
        }
    ],
    "sg:phone":"+1   ",
    "sg:postcode":"15238",
    "sg:province":"PA",
    "sg:tags":[
        "architectural"
    ],
    "wof:name":"Ashford Partners LLC",
    "wof:placetype":"venue"
},
  "geometry": {"coordinates":[-79.865662,40.500153],"type":"Point"}
}