{
  "type": "Feature",
  "properties": {
    "addr:full":"408 Baldy Hill Rd Alburtis PA 18011",
    "addr:housenumber":"408",
    "addr:postcode":"18011",
    "addr:street":"Baldy Hill Rd",
    "iso:country":"US",
    "sg:address":"408 Baldy Hill Rd",
    "sg:city":"Alburtis",
    "sg:classifiers":[
        {
            "category":"Manufacturing",
            "subcategory":"Building Materials",
            "type":"Manufacturing & Wholesale Goods"
        }
    ],
    "sg:phone":"+1   ",
    "sg:postcode":"18011",
    "sg:province":"PA",
    "sg:tags":[
        "woodwork",
        "architectural"
    ],
    "wof:name":"Cutting Edge",
    "wof:placetype":"venue"
},
  "geometry": {"coordinates":[-75.677719,40.448796],"type":"Point"}
}