{
  "type": "Feature",
  "properties": {
    "iso:country":"US",
    "sg:address":"632 Glendale Valley Blvd",
    "sg:city":"Fallentimber",
    "sg:classifiers":[
        {
            "category":"Wholesale",
            "subcategory":"Metals & Minerals",
            "type":"Manufacturing & Wholesale Goods"
        }
    ],
    "sg:phone":"+1   ",
    "sg:postcode":"16639",
    "sg:province":"PA",
    "sg:tags":[
        "steel",
        "plate",
        "mfg",
        "fabricated",
        "st",
        "fabricator"
    ],
    "wof:name":"Consolidated Steel Services",
    "wof:placetype":"venue"
},
  "geometry": {"coordinates":[-78.488305,40.652709],"type":"Point"}
}