{
  "type": "Feature",
  "properties": {
    "iso:country":"US",
    "sg:address":"9906 Bustleton Ave",
    "sg:city":"Philadelphia",
    "sg:classifiers":[
        {
            "category":"Organizations",
            "subcategory":"Professional Association",
            "type":"Services"
        }
    ],
    "sg:phone":"+1 215 969 9595",
    "sg:postcode":"19115",
    "sg:province":"PA",
    "wof:name":"Doral II Condo Assn",
    "wof:placetype":"venue"
},
  "geometry": {"coordinates":[-75.03003699999999,40.100118],"type":"Point"}
}