{
  "type": "Feature",
  "properties": {
    "addr:full":"4424 Pennypack St Philadelphia PA 19136",
    "addr:housenumber":"4424",
    "addr:postcode":"19136",
    "addr:street":"Pennypack St",
    "iso:country":"US",
    "sg:address":"4424 Pennypack St",
    "sg:city":"Philadelphia",
    "sg:classifiers":[
        {
            "category":"Building & Trades",
            "subcategory":"Construction",
            "type":"Services"
        }
    ],
    "sg:phone":"+1 215 632 0888",
    "sg:postcode":"19136",
    "sg:province":"PA",
    "sg:tags":[
        "roofing",
        "contractor"
    ],
    "wof:name":"Hy-Tech Roofing & Siding",
    "wof:placetype":"venue"
},
  "geometry": {"coordinates":[-75.012531,40.046247],"type":"Point"}
}