{
  "type": "Feature",
  "properties": {
    "iso:country":"US",
    "sg:address":"1948 General Potter Hwy Route 322",
    "sg:city":"Centre Hall",
    "sg:classifiers":[
        {
            "category":"Home & Garden",
            "subcategory":"Garden Supply",
            "type":"Retail Goods"
        }
    ],
    "sg:postcode":"16828",
    "sg:province":"PA",
    "sg:tags":[
        "nursery",
        "gardening"
    ],
    "sg:website":"www.wheatfield.com",
    "wof:name":"Wheatfield Nursery",
    "wof:placetype":"venue"
},
  "geometry": {"coordinates":[-77.708694,40.789599],"type":"Point"}
}