{
  "type": "Feature",
  "properties": {
    "addr:full":"306 Valley Ave Wilmerding PA 15148",
    "addr:housenumber":"306",
    "addr:postcode":"15148",
    "addr:street":"Valley Ave",
    "iso:country":"US",
    "sg:address":"306 Valley Ave",
    "sg:city":"Wilmerding",
    "sg:classifiers":[
        {
            "category":"Professional",
            "type":"Services"
        }
    ],
    "sg:phone":"+1   ",
    "sg:postcode":"15148",
    "sg:province":"PA",
    "wof:name":"Kelley Lori Wall",
    "wof:placetype":"venue"
},
  "geometry": {"coordinates":[-79.791809,40.39313],"type":"Point"}
}