{
  "type": "Feature",
  "properties": {
    "addr:full":"2402 W 8th St Erie PA 16502",
    "addr:housenumber":"2402",
    "addr:postcode":"16502",
    "addr:street":"W 8Th St",
    "iso:country":"US",
    "sg:address":"2402 W 8th St",
    "sg:city":"Erie",
    "sg:classifiers":[
        {
            "category":"Professional",
            "subcategory":"Accounting & Tax Preparation",
            "type":"Services"
        }
    ],
    "sg:phone":"+1 814 454 4008",
    "sg:postcode":"16502",
    "sg:province":"PA",
    "sg:tags":[
        "accountant"
    ],
    "wof:name":"Malin Bergquist & Co",
    "wof:placetype":"venue"
},
  "geometry": {"coordinates":[-80.140242,42.106762],"type":"Point"}
}