{
  "type": "Feature",
  "properties": {
    "addr:full":"207 E 16th Ave Homestead PA 15120",
    "addr:housenumber":"207",
    "addr:postcode":"15120",
    "addr:street":"E 16Th Ave",
    "iso:country":"US",
    "sg:address":"207 E 16th Ave",
    "sg:city":"Homestead",
    "sg:classifiers":[
        {
            "category":"Local Transit",
            "type":"Transportation"
        }
    ],
    "sg:phone":"+1 412 462 8000",
    "sg:postcode":"15120",
    "sg:province":"PA",
    "sg:tags":[
        "passenger",
        "limousine",
        "transport"
    ],
    "wof:name":"First Class Limousine Service",
    "wof:placetype":"venue"
},
  "geometry": {"coordinates":[-79.903378,40.402988],"type":"Point"}
}