{
  "type": "Feature",
  "properties": {
    "iso:country":"US",
    "sg:address":"353 W Lancaster Ave",
    "sg:city":"Malvern",
    "sg:classifiers":[
        {
            "category":"Professional",
            "subcategory":"Accounting & Tax Preparation",
            "type":"Services"
        }
    ],
    "sg:phone":"+1   ",
    "sg:postcode":"19355",
    "sg:province":"PA",
    "sg:tags":[
        "return"
    ],
    "wof:name":"McLean Wini Accounting Tax Svc",
    "wof:placetype":"venue"
},
  "geometry": {"coordinates":[-75.51171100000001,40.043281],"type":"Point"}
}