{
  "type": "Feature",
  "properties": {
    "iso:country":"US",
    "sg:address":"3131 Forbes Ave",
    "sg:city":"Pittsburgh",
    "sg:classifiers":[
        {
            "category":"Professional",
            "type":"Services"
        }
    ],
    "sg:phone":"+1   ",
    "sg:postcode":"15213",
    "sg:province":"PA",
    "wof:name":"M E A Inc",
    "wof:placetype":"venue"
},
  "geometry": {"coordinates":[-79.96475599999999,40.435866],"type":"Point"}
}