{
  "type": "Feature",
  "properties": {
    "iso:country":"US",
    "sg:address":"2646 Kensington Ave",
    "sg:city":"Philadelphia",
    "sg:classifiers":[
        {
            "category":"Place Of Worship",
            "subcategory":"Church",
            "type":"Public Place"
        },
        {
            "category":"Place Of Worship",
            "type":"Public Place"
        }
    ],
    "sg:phone":"+1 215 426 9422",
    "sg:postcode":"19125",
    "sg:province":"PA",
    "sg:tags":[
        "churches-catholic-traditional",
        "churches-catholic"
    ],
    "wof:name":"Archdiocese Of Philadelphia",
    "wof:placetype":"venue"
},
  "geometry": {"coordinates":[-75.12595399999999,39.989571],"type":"Point"}
}