{
  "type": "Feature",
  "properties": {
    "iso:country":"US",
    "sg:address":"2999 Welsh Rd",
    "sg:city":"Philadelphia",
    "sg:classifiers":[
        {
            "category":"Travel",
            "subcategory":"Travel Agent",
            "type":"Entertainment"
        }
    ],
    "sg:phone":"+1 215 464 2860",
    "sg:postcode":"19152",
    "sg:province":"PA",
    "sg:tags":[
        "agency",
        "bureau"
    ],
    "wof:name":"Voyagers Travel",
    "wof:placetype":"venue"
},
  "geometry": {"coordinates":[-75.02903000000001,40.057709],"type":"Point"}
}