{
  "type": "Feature",
  "properties": {
    "iso:country":"US",
    "sg:address":"101 N Dithridge St Ste 130",
    "sg:city":"Pittsburgh",
    "sg:classifiers":[
        {
            "category":"Real Estate",
            "subcategory":"Real Estate Services",
            "type":"Services"
        },
        {
            "category":"Real Estate",
            "subcategory":"Real Estate Operator",
            "type":"Services"
        }
    ],
    "sg:phone":"+1 412 621 4132",
    "sg:postcode":"15213",
    "sg:province":"PA",
    "sg:tags":[
        "apartment",
        "rental",
        "finder"
    ],
    "wof:name":"Webster Hall",
    "wof:placetype":"venue"
},
  "geometry": {"coordinates":[-79.950592,40.446812],"type":"Point"}
}