{
  "type": "Feature",
  "properties": {
    "iso:country":"US",
    "sg:address":"310 Kane Blvd",
    "sg:city":"Pittsburgh",
    "sg:classifiers":[
        {
            "category":"Organizations",
            "subcategory":"Religious Organization",
            "type":"Services"
        }
    ],
    "sg:phone":"+1 412 279 6620",
    "sg:postcode":"15243",
    "sg:province":"PA",
    "sg:tags":[
        "clergy"
    ],
    "wof:name":"Msgr Michael J Conroy",
    "wof:placetype":"venue"
},
  "geometry": {"coordinates":[-80.082988,40.371957],"type":"Point"}
}