{
  "type": "Feature",
  "properties": {
    "addr:full":"470 Nelson St Chambersburg PA 17201",
    "addr:housenumber":"470",
    "addr:postcode":"17201",
    "addr:street":"Nelson St",
    "iso:country":"US",
    "sg:address":"470 Nelson St",
    "sg:city":"Chambersburg",
    "sg:classifiers":[
        {
            "category":"Manufacturing",
            "subcategory":"Signs",
            "type":"Manufacturing & Wholesale Goods"
        }
    ],
    "sg:phone":"+1 717 264 4211",
    "sg:postcode":"17201",
    "sg:province":"PA",
    "wof:name":"Art Sign Co",
    "wof:placetype":"venue"
},
  "geometry": {"coordinates":[-77.652627,39.935882],"type":"Point"}
}