{
  "type": "Feature",
  "properties": {
    "iso:country":"US",
    "sg:address":"7256 Herber Rd",
    "sg:city":"New Tripoli",
    "sg:classifiers":[
        {
            "category":"Building & Trades",
            "subcategory":"Construction",
            "type":"Services"
        }
    ],
    "sg:phone":"+1 610 298 2835",
    "sg:postcode":"18066",
    "sg:province":"PA",
    "sg:tags":[
        "house"
    ],
    "wof:name":"RPB Construction",
    "wof:placetype":"venue"
},
  "geometry": {"coordinates":[-75.699628,40.64877],"type":"Point"}
}