{
  "type": "Feature",
  "properties": {
    "iso:country":"US",
    "sg:address":"323 E Allegheny Ave",
    "sg:city":"Philadelphia",
    "sg:classifiers":[
        {
            "category":"Restaurant",
            "type":"Food & Drink"
        }
    ],
    "sg:phone":"+1 215 291 2883",
    "sg:postcode":"19134",
    "sg:province":"PA",
    "sg:tags":[
        "style",
        "family"
    ],
    "wof:name":"Ninas Kitchen",
    "wof:placetype":"venue"
},
  "geometry": {"coordinates":[-75.12462600000001,39.997956],"type":"Point"}
}