{
  "type": "Feature",
  "properties": {
    "iso:country":"US",
    "sg:address":"2545 Highland Cir",
    "sg:city":"Bethel Park",
    "sg:classifiers":[
        {
            "category":"Building & Trades",
            "subcategory":"Electrical",
            "type":"Services"
        }
    ],
    "sg:phone":"+1 412 833 8191",
    "sg:postcode":"15102",
    "sg:province":"PA",
    "sg:tags":[
        "electrician"
    ],
    "wof:name":"Klink Electric",
    "wof:placetype":"venue"
},
  "geometry": {"coordinates":[-80.0299,40.336201],"type":"Point"}
}