{
  "type": "Feature",
  "properties": {
    "iso:country":"US",
    "sg:address":"410 W King St",
    "sg:city":"Littlestown",
    "sg:classifiers":[
        {
            "category":"Recreation",
            "type":"Entertainment"
        }
    ],
    "sg:phone":"+1 717 359 9347",
    "sg:postcode":"17340",
    "sg:province":"PA",
    "sg:tags":[
        "martial",
        "arts",
        "instruction"
    ],
    "wof:name":"Penn-Mar Karate Academy",
    "wof:placetype":"venue"
},
  "geometry": {"coordinates":[-77.096557,39.742863],"type":"Point"}
}