{
  "type": "Feature",
  "properties": {
    "addr:full":"1168 Washington Pike Bridgeville PA 15017",
    "addr:housenumber":"1168",
    "addr:postcode":"15017",
    "addr:street":"Washington Pike",
    "iso:country":"US",
    "sg:address":"1168 Washington Pike",
    "sg:city":"Bridgeville",
    "sg:classifiers":[
        {
            "category":"Building & Trades",
            "subcategory":"Construction",
            "type":"Services"
        }
    ],
    "sg:phone":"+1 412 257 2502",
    "sg:postcode":"15017",
    "sg:province":"PA",
    "sg:tags":[
        "contractor"
    ],
    "wof:name":"Benchmark Building Co",
    "wof:placetype":"venue"
},
  "geometry": {"coordinates":[-80.101432,40.369422],"type":"Point"}
}