{
  "type": "Feature",
  "properties": {
    "iso:country":"US",
    "sg:address":"600 Apple St",
    "sg:city":"Conshohocken",
    "sg:classifiers":[
        {
            "category":"Building & Trades",
            "subcategory":"Construction",
            "type":"Services"
        }
    ],
    "sg:phone":"+1 610 825 9471",
    "sg:postcode":"19428",
    "sg:province":"PA",
    "sg:tags":[
        "coping",
        "plastering",
        "tiling",
        "pool",
        "swimming"
    ],
    "wof:name":"Wolfe Lew Inc",
    "wof:placetype":"venue"
},
  "geometry": {"coordinates":[-75.31897499999999,40.067682],"type":"Point"}
}