{
  "type": "Feature",
  "properties": {
    "iso:country":"US",
    "sg:address":"910 State Ave",
    "sg:city":"Coraopolis",
    "sg:classifiers":[
        {
            "category":"Wholesale",
            "subcategory":"Computers",
            "type":"Manufacturing & Wholesale Goods"
        }
    ],
    "sg:phone":"+1 412 269 9473",
    "sg:postcode":"15108",
    "sg:province":"PA",
    "sg:tags":[
        "equipment"
    ],
    "sg:website":"http://www.bulletproofsoftware.com",
    "wof:name":"Bullet Proof Software",
    "wof:placetype":"venue"
},
  "geometry": {"coordinates":[-80.166831,40.518042],"type":"Point"}
}