{
  "type": "Feature",
  "properties": {
    "addr:full":"821 W 30th St Erie PA 16508",
    "addr:housenumber":"821",
    "addr:postcode":"16508",
    "addr:street":"W 30Th St",
    "iso:country":"US",
    "sg:address":"821 W 30th St",
    "sg:city":"Erie",
    "sg:classifiers":[
        {
            "category":"Professional",
            "subcategory":"Accounting & Tax Preparation",
            "type":"Services"
        }
    ],
    "sg:phone":"+1   ",
    "sg:postcode":"16508",
    "sg:province":"PA",
    "sg:tags":[
        "return"
    ],
    "wof:name":"Holders Accounting and Tax Svc",
    "wof:placetype":"venue"
},
  "geometry": {"coordinates":[-80.089539,42.101961],"type":"Point"}
}