{
  "type": "Feature",
  "properties": {
    "addr:full":"721 Brushton Ave Pittsburgh PA 15208",
    "addr:housenumber":"721",
    "addr:postcode":"15208",
    "addr:street":"Brushton Ave",
    "iso:country":"US",
    "sg:address":"721 Brushton Ave",
    "sg:city":"Pittsburgh",
    "sg:classifiers":[
        {
            "category":"Retail",
            "subcategory":"Funeral Services",
            "type":"Services"
        }
    ],
    "sg:phone":"+1 412 371 8800",
    "sg:postcode":"15208",
    "sg:province":"PA",
    "sg:tags":[
        "director"
    ],
    "wof:name":"George W Douglas Funeral Home",
    "wof:placetype":"venue"
},
  "geometry": {"coordinates":[-79.888603,40.454428],"type":"Point"}
}