{
  "type": "Feature",
  "properties": {
    "iso:country":"US",
    "sg:address":"312 4th Ave",
    "sg:city":"Pittsburgh",
    "sg:classifiers":[
        {
            "category":"Professional",
            "subcategory":"Management & Consulting",
            "type":"Services"
        }
    ],
    "sg:phone":"+1   ",
    "sg:postcode":"15222",
    "sg:province":"PA",
    "sg:tags":[
        "consultant",
        "health",
        "care"
    ],
    "wof:name":"Diversified Medical Management",
    "wof:placetype":"venue"
},
  "geometry": {"coordinates":[-79.999741,40.438737],"type":"Point"}
}