{
  "type": "Feature",
  "properties": {
    "iso:country":"US",
    "sg:address":"280 Mundy St",
    "sg:city":"Wilkes Barre",
    "sg:classifiers":[
        {
            "category":"Restaurant",
            "type":"Food & Drink"
        }
    ],
    "sg:phone":"+1 570 820 8200",
    "sg:postcode":"18702",
    "sg:province":"PA",
    "sg:website":"www.groundround.com",
    "wof:name":"Ground Round",
    "wof:placetype":"venue"
},
  "geometry": {"coordinates":[-75.842445,41.243149],"type":"Point"}
}