{
  "type": "Feature",
  "properties": {
    "iso:country":"US",
    "sg:address":"523 Hawthorne St",
    "sg:city":"Reading",
    "sg:classifiers":[
        {
            "category":"Building & Trades",
            "subcategory":"Construction",
            "type":"Services"
        }
    ],
    "sg:phone":"+1   ",
    "sg:postcode":"19611",
    "sg:province":"PA",
    "sg:tags":[
        "builder",
        "operative"
    ],
    "wof:name":"Keystone Custom Contracting",
    "wof:placetype":"venue"
},
  "geometry": {"coordinates":[-75.931169,40.317085],"type":"Point"}
}