{
  "type": "Feature",
  "properties": {
    "iso:country":"US",
    "sg:address":"12875 Ferguson Valley Rd",
    "sg:city":"Burnham",
    "sg:classifiers":[
        {
            "category":"Retail",
            "subcategory":"Auto Repair",
            "type":"Services"
        }
    ],
    "sg:phone":"+1 717 248 4122",
    "sg:postcode":"17044",
    "sg:province":"PA",
    "sg:tags":[
        "body",
        "automobile",
        "painting"
    ],
    "wof:name":"Precision Autobody Inc",
    "wof:placetype":"venue"
},
  "geometry": {"coordinates":[-77.584307,40.627857],"type":"Point"}
}