{
  "type": "Feature",
  "properties": {
    "addr:full":"102 Radcliffe St Bristol PA 19007",
    "addr:housenumber":"102",
    "addr:postcode":"19007",
    "addr:street":"Radcliffe St",
    "iso:country":"US",
    "sg:address":"102 Radcliffe St",
    "sg:city":"Bristol",
    "sg:classifiers":[
        {
            "category":"Restaurant",
            "type":"Food & Drink"
        }
    ],
    "sg:phone":"+1 215 788 5536",
    "sg:postcode":"19007",
    "sg:province":"PA",
    "sg:tags":[
        "tavern"
    ],
    "wof:name":"King George II Inn",
    "wof:placetype":"venue"
},
  "geometry": {"coordinates":[-74.85610200000001,40.094601],"type":"Point"}
}