{
  "type": "Feature",
  "properties": {
    "addr:full":"1725 Victoria Ave Arnold PA 15068",
    "addr:housenumber":"1725",
    "addr:postcode":"15068",
    "addr:street":"Victoria Ave",
    "iso:country":"US",
    "sg:address":"1725 Victoria Ave",
    "sg:city":"Arnold",
    "sg:classifiers":[
        {
            "category":"Organizations",
            "subcategory":"Religious Organization",
            "type":"Services"
        }
    ],
    "sg:phone":"+1 724 335 0101",
    "sg:postcode":"15068",
    "sg:province":"PA",
    "sg:tags":[
        "church"
    ],
    "wof:name":"Calvary Lutheran Church",
    "wof:placetype":"venue"
},
  "geometry": {"coordinates":[-79.763358,40.577802],"type":"Point"}
}