{
  "type": "Feature",
  "properties": {
    "addr:full":"4975 W Chester Pike Newtown Square PA 19073",
    "addr:housenumber":"4975",
    "addr:postcode":"19073",
    "addr:street":"W Chester Pike",
    "iso:country":"US",
    "sg:address":"4975 W Chester Pike",
    "sg:city":"Newtown Square",
    "sg:classifiers":[
        {
            "category":"Professional",
            "subcategory":"Management & Consulting",
            "type":"Services"
        }
    ],
    "sg:phone":"+1 610 325 9905",
    "sg:postcode":"19073",
    "sg:province":"PA",
    "sg:tags":[
        "consultant",
        "publishing"
    ],
    "wof:name":"Matrix Medical Communications",
    "wof:placetype":"venue"
},
  "geometry": {"coordinates":[-75.448182,39.974655],"type":"Point"}
}