{
  "type": "Feature",
  "properties": {
    "addr:full":"Ridge Pike & Trooper Norristown PA 19403",
    "addr:postcode":"19403",
    "addr:street":"Ridge",
    "iso:country":"US",
    "sg:address":"Ridge Pike & Trooper",
    "sg:city":"Norristown",
    "sg:classifiers":[
        {
            "category":"Autos & Motor Vehicles",
            "subcategory":"Automobile Sales",
            "type":"Retail Goods"
        },
        {
            "category":"Retail",
            "subcategory":"Auto Repair",
            "type":"Services"
        }
    ],
    "sg:phone":"+1 610 539 5400",
    "sg:postcode":"19403",
    "sg:province":"PA",
    "sg:tags":[
        "car"
    ],
    "wof:name":"Norristown Ford",
    "wof:placetype":"venue"
},
  "geometry": {"coordinates":[-75.38020299999999,40.144501],"type":"Point"}
}