{
  "type": "Feature",
  "properties": {
    "addr:full":"533 Meldon Ave Donora PA 15033",
    "addr:housenumber":"533",
    "addr:postcode":"15033",
    "addr:street":"Meldon Ave",
    "iso:country":"US",
    "sg:address":"533 Meldon Ave",
    "sg:city":"Donora",
    "sg:classifiers":[
        {
            "category":"Retail",
            "subcategory":"Auto Repair",
            "type":"Services"
        }
    ],
    "sg:phone":"+1 724 379 5433",
    "sg:postcode":"15033",
    "sg:province":"PA",
    "sg:tags":[
        "body",
        "shop",
        "painting",
        "automobile"
    ],
    "sg:website":"www.naylorsbodyshop.com",
    "wof:name":"Naylor's Body Shop",
    "wof:placetype":"venue"
},
  "geometry": {"coordinates":[-79.85549899999999,40.1772],"type":"Point"}
}