{
  "type": "Feature",
  "properties": {
    "iso:country":"US",
    "sg:address":"3812 William Flynn Hwy",
    "sg:city":"Allison Park",
    "sg:classifiers":[
        {
            "category":"Home & Garden",
            "subcategory":"Home Furnishings",
            "type":"Retail Goods"
        }
    ],
    "sg:phone":"+1 412 561 2800",
    "sg:postcode":"15101",
    "sg:province":"PA",
    "sg:tags":[
        "cutlery"
    ],
    "wof:name":"Kevin Mc Guire",
    "wof:placetype":"venue"
},
  "geometry": {"coordinates":[-79.95832299999999,40.556324],"type":"Point"}
}