{
  "type": "Feature",
  "properties": {
    "iso:country":"US",
    "sg:address":"675 State Ave",
    "sg:city":"Emmaus",
    "sg:classifiers":[
        {
            "category":"Autos & Motor Vehicles",
            "subcategory":"Automobile Sales",
            "type":"Retail Goods"
        },
        {
            "category":"Retail",
            "subcategory":"Auto Repair",
            "type":"Services"
        }
    ],
    "sg:phone":"+1 610 965 1200",
    "sg:postcode":"18049",
    "sg:province":"PA",
    "sg:tags":[
        "car"
    ],
    "sg:website":"www.vinart.com",
    "wof:name":"Vinart Dealerships",
    "wof:placetype":"venue"
},
  "geometry": {"coordinates":[-75.491302,40.550201],"type":"Point"}
}