{
  "type": "Feature",
  "properties": {
    "addr:full":"4884 Pine Run Rd Linden PA 17744",
    "addr:housenumber":"4884",
    "addr:postcode":"17744",
    "addr:street":"Pine Run Rd",
    "iso:country":"US",
    "sg:address":"4884 Pine Run Rd",
    "sg:city":"Linden",
    "sg:classifiers":[
        {
            "category":"Farming",
            "subcategory":"Dairy Farm",
            "type":"Manufacturing & Wholesale Goods"
        }
    ],
    "sg:phone":"+1   ",
    "sg:postcode":"17744",
    "sg:province":"PA",
    "wof:name":"Earl Hensler",
    "wof:placetype":"venue"
},
  "geometry": {"coordinates":[-77.186627,41.280461],"type":"Point"}
}