{
  "type": "Feature",
  "properties": {
    "addr:full":"142 Shoemaker Rd Pottstown PA 19464",
    "addr:housenumber":"142",
    "addr:postcode":"19464",
    "addr:street":"Shoemaker Rd",
    "iso:country":"US",
    "sg:address":"142 Shoemaker Rd",
    "sg:city":"Pottstown",
    "sg:classifiers":[
        {
            "category":"Sports & Exercise",
            "subcategory":"Gym",
            "type":"Entertainment"
        }
    ],
    "sg:phone":"+1 610 718 1265",
    "sg:postcode":"19464",
    "sg:province":"PA",
    "sg:tags":[
        "fitness",
        "physical",
        "facility"
    ],
    "wof:name":"World Health Systems LLC",
    "wof:placetype":"venue"
},
  "geometry": {"coordinates":[-75.660416,40.249708],"type":"Point"}
}