{
  "type": "Feature",
  "properties": {
    "addr:full":"6261 Sullivan Trl Nazareth PA 18064",
    "addr:housenumber":"6261",
    "addr:postcode":"18064",
    "addr:street":"Sullivan Trl",
    "iso:country":"US",
    "sg:address":"6261 Sullivan Trl",
    "sg:city":"Nazareth",
    "sg:classifiers":[
        {
            "category":"Bus Charters",
            "type":"Transportation"
        }
    ],
    "sg:phone":"+1 610 759 7090",
    "sg:postcode":"18064",
    "sg:province":"PA",
    "sg:tags":[
        "rental"
    ],
    "wof:name":"Laidlaw Transit Inc",
    "wof:placetype":"venue"
},
  "geometry": {"coordinates":[-75.28716,40.805216],"type":"Point"}
}