{
  "type": "Feature",
  "properties": {
    "iso:country":"US",
    "sg:address":"3885 Saline St",
    "sg:city":"Pittsburgh",
    "sg:classifiers":[
        {
            "category":"Professional",
            "subcategory":"Engineering",
            "type":"Services"
        }
    ],
    "sg:phone":"+1   ",
    "sg:postcode":"15217",
    "sg:province":"PA",
    "wof:name":"Project",
    "wof:placetype":"venue"
},
  "geometry": {"coordinates":[-79.926427,40.426547],"type":"Point"}
}