{
  "type": "Feature",
  "properties": {
    "addr:full":"3401 6th Ave Altoona PA 16602",
    "addr:housenumber":"3401",
    "addr:postcode":"16602",
    "addr:street":"6Th Ave",
    "iso:country":"US",
    "sg:address":"3401 6th Ave",
    "sg:city":"Altoona",
    "sg:classifiers":[
        {
            "category":"Home & Garden",
            "subcategory":"Furniture",
            "type":"Retail Goods"
        }
    ],
    "sg:phone":"+1   ",
    "sg:postcode":"16602",
    "sg:province":"PA",
    "sg:tags":[
        "household",
        "floor",
        "bedding",
        "covering"
    ],
    "wof:name":"Wolf Furniture Enterprises",
    "wof:placetype":"venue"
},
  "geometry": {"coordinates":[-78.41311899999999,40.491276],"type":"Point"}
}