{
  "type": "Feature",
  "properties": {
    "iso:country":"US",
    "sg:address":"202 N Jay St",
    "sg:city":"Lock Haven",
    "sg:classifiers":[
        {
            "category":"Real Estate",
            "subcategory":"Real Estate Agent",
            "type":"Services"
        }
    ],
    "sg:phone":"+1   ",
    "sg:postcode":"17745",
    "sg:province":"PA",
    "wof:name":"Fish Real Estate G M A C",
    "wof:placetype":"venue"
},
  "geometry": {"coordinates":[-77.44241,41.136238],"type":"Point"}
}