{
  "type": "Feature",
  "properties": {
    "iso:country":"US",
    "sg:address":"432 S Main St",
    "sg:city":"Jersey Shore",
    "sg:classifiers":[
        {
            "category":"Professional",
            "subcategory":"Business Services",
            "type":"Services"
        }
    ],
    "sg:phone":"+1 570 398 4003",
    "sg:postcode":"17740",
    "sg:province":"PA",
    "sg:tags":[
        "water",
        "treatment"
    ],
    "wof:name":"Gottschall Enviramental",
    "wof:placetype":"venue"
},
  "geometry": {"coordinates":[-77.25462899999999,41.19743],"type":"Point"}
}