{
  "type": "Feature",
  "properties": {
    "iso:country":"US",
    "sg:address":"11203 Frankstown Rd",
    "sg:city":"Penn Hills",
    "sg:classifiers":[
        {
            "category":"Real Estate",
            "subcategory":"Surveying",
            "type":"Services"
        }
    ],
    "sg:phone":"+1 412 247 1722",
    "sg:postcode":"15235",
    "sg:province":"PA",
    "sg:tags":[
        "surveyor"
    ],
    "wof:name":"Territ & Assoc Inc",
    "wof:placetype":"venue"
},
  "geometry": {"coordinates":[-79.835115,40.467414],"type":"Point"}
}