{
  "type": "Feature",
  "properties": {
    "addr:full":"800 W Pennsylvania Ave Pen Argyl PA 18072",
    "addr:housenumber":"800",
    "addr:postcode":"18072",
    "addr:street":"W Pennsylvania Ave",
    "iso:country":"US",
    "sg:address":"800 W Pennsylvania Ave",
    "sg:city":"Pen Argyl",
    "sg:classifiers":[
        {
            "category":"Retail",
            "subcategory":"Auto Repair",
            "type":"Services"
        }
    ],
    "sg:phone":"+1 610 863 8829",
    "sg:postcode":"18072",
    "sg:province":"PA",
    "sg:tags":[
        "repairing",
        "automobile",
        "body"
    ],
    "wof:name":"Woody's Creative Automotive",
    "wof:placetype":"venue"
},
  "geometry": {"coordinates":[-75.263783,40.865702],"type":"Point"}
}