{
  "type": "Feature",
  "properties": {
    "iso:country":"US",
    "sg:address":"111 Elizabeth Dr",
    "sg:city":"Jeannette",
    "sg:classifiers":[
        {
            "category":"Professional",
            "subcategory":"Printing & Photocopies",
            "type":"Services"
        }
    ],
    "sg:phone":"+1 724 640 6645",
    "sg:postcode":"15644",
    "sg:province":"PA",
    "sg:tags":[
        "photographers-commercial"
    ],
    "wof:name":"Photography By Jeff Valenta",
    "wof:placetype":"venue"
},
  "geometry": {"coordinates":[-79.63564,40.35176],"type":"Point"}
}