{
  "type": "Feature",
  "properties": {
    "iso:country":"US",
    "sg:address":"7110 Fairlane Village Mall",
    "sg:city":"Pottsville",
    "sg:classifiers":[
        {
            "category":"Shopping",
            "subcategory":"Department Store",
            "type":"Retail Goods"
        }
    ],
    "sg:phone":"+1 570 429 1796",
    "sg:postcode":"17901",
    "sg:province":"PA",
    "sg:tags":[
        "shop"
    ],
    "sg:website":"www.valuecity.com",
    "wof:name":"Value City Department Store",
    "wof:placetype":"venue"
},
  "geometry": {"coordinates":[-76.191108,40.705064],"type":"Point"}
}