{
  "type": "Feature",
  "properties": {
    "iso:country":"US",
    "sg:address":"1155 Carlisle St",
    "sg:city":"Hanover",
    "sg:classifiers":[
        {
            "category":"Utilities",
            "subcategory":"Mobile Phone",
            "type":"Services"
        },
        {
            "category":"Shopping",
            "subcategory":"Mobile Phones",
            "type":"Retail Goods"
        },
        {
            "category":"Utilities",
            "subcategory":"Telephone",
            "type":"Services"
        },
        {
            "category":"Professional",
            "subcategory":"Computer Services",
            "type":"Services"
        }
    ],
    "sg:phone":"+1 717 632 3046",
    "sg:postcode":"17331",
    "sg:province":"PA",
    "sg:tags":[
        "distance",
        "telecommunication",
        "supply",
        "communication",
        "wireless",
        "equipment",
        "cellular",
        "companies-long"
    ],
    "wof:name":"Verizon Wireless",
    "wof:placetype":"venue"
},
  "geometry": {"coordinates":[-76.996764,39.821885],"type":"Point"}
}