{
  "type": "Feature",
  "properties": {
    "addr:full":"140 Norwood Dr Beaver Falls PA 15010",
    "addr:housenumber":"140",
    "addr:postcode":"15010",
    "addr:street":"Norwood Dr",
    "iso:country":"US",
    "sg:address":"140 Norwood Dr",
    "sg:city":"Beaver Falls",
    "sg:classifiers":[
        {
            "category":"Utilities",
            "type":"Services"
        }
    ],
    "sg:phone":"+1   ",
    "sg:postcode":"15010",
    "sg:province":"PA",
    "sg:tags":[
        "sanitary",
        "repair"
    ],
    "wof:name":"Daltons Sanitary Service",
    "wof:placetype":"venue"
},
  "geometry": {"coordinates":[-80.335595,40.788946],"type":"Point"}
}