{
  "type": "Feature",
  "properties": {
    "iso:country":"US",
    "sg:address":"45 E Afton Ave",
    "sg:city":"Yardley",
    "sg:classifiers":[
        {
            "category":"Health Services",
            "subcategory":"Doctor",
            "type":"Services"
        },
        {
            "category":"Health Services",
            "subcategory":"Clinic",
            "type":"Services"
        },
        {
            "category":"Personal",
            "subcategory":"Massage",
            "type":"Services"
        },
        {
            "category":"Health Services",
            "subcategory":"Health Practitioner",
            "type":"Services"
        },
        {
            "category":"Health Services",
            "subcategory":"Chiropractor",
            "type":"Services"
        }
    ],
    "sg:phone":"+1 215 321 0505",
    "sg:postcode":"19067",
    "sg:province":"PA",
    "sg:tags":[
        "physician",
        "chiropractic",
        "medical",
        "therapist",
        "medicine",
        "surgeon",
        "alternative"
    ],
    "wof:name":"Center for Chiropractic & Holistic Care",
    "wof:placetype":"venue"
},
  "geometry": {"coordinates":[-74.837773,40.243347],"type":"Point"}
}