{
  "type": "Feature",
  "properties": {
    "iso:country":"US",
    "sg:address":"421 Laurel St",
    "sg:city":"Susquehanna",
    "sg:classifiers":[
        {
            "category":"Building & Trades",
            "subcategory":"Construction",
            "type":"Services"
        }
    ],
    "sg:phone":"+1   ",
    "sg:postcode":"18847",
    "sg:province":"PA",
    "sg:tags":[
        "house"
    ],
    "wof:name":"Greg Norton Construction",
    "wof:placetype":"venue"
},
  "geometry": {"coordinates":[-75.593492,41.945537],"type":"Point"}
}