{
  "type": "Feature",
  "properties": {
    "iso:country":"US",
    "sg:address":"26 N Hanover St",
    "sg:city":"Carlisle",
    "sg:classifiers":[
        {
            "category":"Restaurant",
            "type":"Food & Drink"
        }
    ],
    "sg:postcode":"17013",
    "sg:province":"PA",
    "sg:tags":[
        "moroccan"
    ],
    "sg:website":"www.arganacarlisle.com",
    "wof:name":"Argana",
    "wof:placetype":"venue"
},
  "geometry": {"coordinates":[-77.18946,40.20271],"type":"Point"}
}