{
  "type": "Feature",
  "properties": {
    "iso:country":"US",
    "sg:address":"333 W State St",
    "sg:city":"Media",
    "sg:classifiers":[
        {
            "category":"Banks & Credit Unions",
            "subcategory":"Bank",
            "type":"Services"
        }
    ],
    "sg:phone":"+1   ",
    "sg:postcode":"19063",
    "sg:province":"PA",
    "sg:tags":[
        "broker",
        "mortgage"
    ],
    "wof:name":"Sunset Mortgage Company LP",
    "wof:placetype":"venue"
},
  "geometry": {"coordinates":[-75.394379,39.918688],"type":"Point"}
}