{
  "type": "Feature",
  "properties": {
    "addr:full":"2205 Gettysburg Rd Camp Hill PA 17011",
    "addr:housenumber":"2205",
    "addr:postcode":"17011",
    "addr:street":"Gettysburg Rd",
    "iso:country":"US",
    "sg:address":"2205 Gettysburg Rd",
    "sg:city":"Camp Hill",
    "sg:classifiers":[
        {
            "category":"Restaurant",
            "type":"Food & Drink"
        }
    ],
    "sg:phone":"+1   ",
    "sg:postcode":"17011",
    "sg:province":"PA",
    "sg:tags":[
        "eating",
        "station",
        "gas"
    ],
    "wof:name":"Exxon",
    "wof:placetype":"venue"
},
  "geometry": {"coordinates":[-76.920294,40.229352],"type":"Point"}
}