{
  "type": "Feature",
  "properties": {
    "addr:full":"904 Penn Ave Pittsburgh PA 15221",
    "addr:housenumber":"904",
    "addr:postcode":"15221",
    "addr:street":"Penn Ave",
    "iso:country":"US",
    "sg:address":"904 Penn Ave",
    "sg:city":"Pittsburgh",
    "sg:classifiers":[
        {
            "category":"Autos & Motor Vehicles",
            "subcategory":"Automobile Sales",
            "type":"Retail Goods"
        }
    ],
    "sg:phone":"+1   ",
    "sg:postcode":"15221",
    "sg:province":"PA",
    "sg:tags":[
        "used"
    ],
    "wof:name":"J&A Auto Sales",
    "wof:placetype":"venue"
},
  "geometry": {"coordinates":[-79.879355,40.441971],"type":"Point"}
}