{
  "type": "Feature",
  "properties": {
    "iso:country":"US",
    "sg:address":"115 E Broad St",
    "sg:city":"Bethlehem",
    "sg:classifiers":[
        {
            "category":"Health Services",
            "subcategory":"Chiropractor",
            "type":"Services"
        }
    ],
    "sg:phone":"+1 610 997 3992",
    "sg:postcode":"18018",
    "sg:province":"PA",
    "wof:name":"Peterson Carol Dr",
    "wof:placetype":"venue"
},
  "geometry": {"coordinates":[-75.374865,40.622337],"type":"Point"}
}