{
  "type": "Feature",
  "properties": {
    "addr:full":"193 Fisher St Jonestown PA 17038",
    "addr:housenumber":"193",
    "addr:postcode":"17038",
    "addr:street":"Fisher St",
    "iso:country":"US",
    "sg:address":"193 Fisher St",
    "sg:city":"Jonestown",
    "sg:classifiers":[
        {
            "category":"Autos & Motor Vehicles",
            "subcategory":"Automobile Sales",
            "type":"Retail Goods"
        }
    ],
    "sg:phone":"+1   ",
    "sg:postcode":"17038",
    "sg:province":"PA",
    "sg:tags":[
        "used"
    ],
    "wof:name":"Wolfe Larry Used Cars",
    "wof:placetype":"venue"
},
  "geometry": {"coordinates":[-76.48464,40.413748],"type":"Point"}
}