{
  "type": "Feature",
  "properties": {
    "addr:full":"7 Timber Ln Trafford PA 15085",
    "addr:housenumber":"7",
    "addr:postcode":"15085",
    "addr:street":"Timber Ln",
    "iso:country":"US",
    "sg:address":"7 Timber Ln",
    "sg:city":"Trafford",
    "sg:classifiers":[
        {
            "category":"Insurance",
            "subcategory":"Insurance Agent",
            "type":"Services"
        }
    ],
    "sg:phone":"+1   ",
    "sg:postcode":"15085",
    "sg:province":"PA",
    "wof:name":"St Paul Companies Corporation",
    "wof:placetype":"venue"
},
  "geometry": {"coordinates":[-79.746488,40.387675],"type":"Point"}
}