{
  "type": "Feature",
  "properties": {
    "addr:full":"500 Orchard Ave Kennett Square PA 19348",
    "addr:housenumber":"500",
    "addr:postcode":"19348",
    "addr:street":"Orchard Ave",
    "iso:country":"US",
    "sg:address":"500 Orchard Ave",
    "sg:city":"Kennett Square",
    "sg:classifiers":[
        {
            "category":"Building & Trades",
            "subcategory":"Construction",
            "type":"Services"
        }
    ],
    "sg:phone":"+1 610 388 2652",
    "sg:postcode":"19348",
    "sg:province":"PA",
    "sg:tags":[
        "interior",
        "design"
    ],
    "wof:name":"Pritchard & Associates",
    "wof:placetype":"venue"
},
  "geometry": {"coordinates":[-75.6772,39.864601],"type":"Point"}
}