{
  "type": "Feature",
  "properties": {
    "iso:country":"US",
    "sg:address":"1809 Spring Garden St",
    "sg:city":"Philadelphia",
    "sg:classifiers":[
        {
            "category":"Organizations",
            "subcategory":"Non-profit Organization",
            "type":"Services"
        }
    ],
    "sg:phone":"+1 215 751 9300",
    "sg:postcode":"19130",
    "sg:province":"PA",
    "wof:name":"Phila Martin Luther King Jr",
    "wof:placetype":"venue"
},
  "geometry": {"coordinates":[-75.166647,39.963195],"type":"Point"}
}