{
  "type": "Feature",
  "properties": {
    "addr:full":"1809 Spring Garden St Philadelphia PA 19130",
    "addr:housenumber":"1809",
    "addr:postcode":"19130",
    "addr:street":"Spring Garden St",
    "iso:country":"US",
    "sg:address":"1809 Spring Garden St",
    "sg:city":"Philadelphia",
    "sg:classifiers":[
        {
            "category":"Organizations",
            "subcategory":"Non-profit Organization",
            "type":"Services"
        }
    ],
    "sg:phone":"+1 215 751 9300",
    "sg:postcode":"19130",
    "sg:province":"PA",
    "wof:name":"Phila Martin Luther King Jr",
    "wof:placetype":"venue"
},
  "geometry": {"coordinates":[-75.166647,39.963195],"type":"Point"}
}