{
  "type": "Feature",
  "properties": {
    "iso:country":"US",
    "sg:address":"31 Millers Dr",
    "sg:city":"Oakdale",
    "sg:classifiers":[
        {
            "category":"Farming",
            "subcategory":"Farm",
            "type":"Manufacturing & Wholesale Goods"
        }
    ],
    "sg:phone":"+1 724 693 0513",
    "sg:postcode":"15071",
    "sg:province":"PA",
    "wof:name":"Hankey Farms Pool",
    "wof:placetype":"venue"
},
  "geometry": {"coordinates":[-80.208718,40.419142],"type":"Point"}
}