{
  "type": "Feature",
  "properties": {
    "iso:country":"US",
    "sg:address":"526 Brodhead Ave",
    "sg:city":"Bethlehem",
    "sg:classifiers":[
        {
            "category":"Education",
            "subcategory":"College",
            "type":"Public Place"
        }
    ],
    "sg:phone":"+1   ",
    "sg:postcode":"18015",
    "sg:province":"PA",
    "wof:name":"Office of Research",
    "wof:placetype":"venue"
},
  "geometry": {"coordinates":[-75.381005,40.607],"type":"Point"}
}