{
  "type": "Feature",
  "properties": {
    "addr:full":"3700 Sheaff Ln Philadelphia PA 19145",
    "addr:housenumber":"3700",
    "addr:postcode":"19145",
    "addr:street":"Sheaff Ln",
    "iso:country":"US",
    "sg:address":"3700 Sheaff Ln",
    "sg:city":"Philadelphia",
    "sg:classifiers":[
        {
            "category":"Building & Trades",
            "subcategory":"Cleaning & Sanitation",
            "type":"Services"
        }
    ],
    "sg:phone":"+1 215 755 8018",
    "sg:postcode":"19145",
    "sg:province":"PA",
    "sg:tags":[
        "janitor"
    ],
    "wof:name":"Avram Cleaning",
    "wof:placetype":"venue"
},
  "geometry": {"coordinates":[-75.19174700000001,39.904128],"type":"Point"}
}