{
  "type": "Feature",
  "properties": {
    "iso:country":"US",
    "sg:address":"1242 Liberty St",
    "sg:city":"Franklin",
    "sg:classifiers":[
        {
            "category":"Banks & Credit Unions",
            "subcategory":"Bank",
            "type":"Services"
        }
    ],
    "sg:phone":"+1 814 432 3734",
    "sg:postcode":"16323",
    "sg:province":"PA",
    "sg:tags":[
        "depository",
        "banking"
    ],
    "wof:name":"Cash Station Short Term Loans",
    "wof:placetype":"venue"
},
  "geometry": {"coordinates":[-79.82808,41.397539],"type":"Point"}
}