{
  "type": "Feature",
  "properties": {
    "iso:country":"US",
    "sg:address":"679 Lake Minsi Dr",
    "sg:city":"Bangor",
    "sg:classifiers":[
        {
            "category":"Building & Trades",
            "subcategory":"Landscaping Services",
            "type":"Services"
        }
    ],
    "sg:phone":"+1 610 588 1034",
    "sg:postcode":"18013",
    "sg:province":"PA",
    "sg:tags":[
        "tree"
    ],
    "wof:name":"Gary Eagle Tree Service, Inc.",
    "wof:placetype":"venue"
},
  "geometry": {"coordinates":[-75.196334,40.906714],"type":"Point"}
}