{
  "type": "Feature",
  "properties": {
    "iso:country":"US",
    "sg:address":"1125 Rosedale Ave",
    "sg:city":"Middletown",
    "sg:classifiers":[
        {
            "category":"Building & Trades",
            "subcategory":"Construction",
            "type":"Services"
        }
    ],
    "sg:phone":"+1   ",
    "sg:postcode":"17057",
    "sg:province":"PA",
    "sg:tags":[
        "hanging",
        "contractor"
    ],
    "wof:name":"Master Pro Painting",
    "wof:placetype":"venue"
},
  "geometry": {"coordinates":[-76.75793899999999,40.20382],"type":"Point"}
}