{
  "type": "Feature",
  "properties": {
    "addr:full":"550 Memorial Hwy Dallas PA 18612",
    "addr:housenumber":"550",
    "addr:postcode":"18612",
    "addr:street":"Memorial Hwy",
    "iso:country":"US",
    "sg:address":"550 Memorial Hwy",
    "sg:city":"Dallas",
    "sg:classifiers":[
        {
            "category":"Restaurant",
            "type":"Food & Drink"
        }
    ],
    "sg:phone":"+1 570 674 3697",
    "sg:postcode":"18612",
    "sg:province":"PA",
    "sg:tags":[
        "asian",
        "chinese",
        "pan"
    ],
    "sg:website":"http://www.chinaking.org",
    "wof:name":"China King",
    "wof:placetype":"venue"
},
  "geometry": {"coordinates":[-75.96502099999999,41.336123],"type":"Point"}
}