{
  "type": "Feature",
  "properties": {
    "iso:country":"US",
    "sg:address":"266 Ridgemont Dr",
    "sg:city":"Industry",
    "sg:classifiers":[
        {
            "category":"Farming",
            "subcategory":"Livestock Farm",
            "type":"Manufacturing & Wholesale Goods"
        }
    ],
    "sg:phone":"+1   ",
    "sg:postcode":"15052",
    "sg:province":"PA",
    "sg:tags":[
        "wheat",
        "beef",
        "feedlot",
        "cattle"
    ],
    "wof:name":"Thelma McGafflic",
    "wof:placetype":"venue"
},
  "geometry": {"coordinates":[-80.460154,40.677929],"type":"Point"}
}