{
  "type": "Feature",
  "properties": {
    "iso:country":"US",
    "sg:address":"113 N Olive St",
    "sg:city":"Media",
    "sg:classifiers":[
        {
            "category":"Professional",
            "subcategory":"Management & Consulting",
            "type":"Services"
        }
    ],
    "sg:phone":"+1   ",
    "sg:postcode":"19063",
    "sg:province":"PA",
    "wof:name":"Nee & Associates",
    "wof:placetype":"venue"
},
  "geometry": {"coordinates":[-75.390618,39.91976],"type":"Point"}
}