{
  "type": "Feature",
  "properties": {
    "iso:country":"US",
    "sg:address":"2716 Richmond Rd",
    "sg:city":"Easton",
    "sg:classifiers":[
        {
            "category":"Building & Trades",
            "subcategory":"Landscaping Services",
            "type":"Services"
        }
    ],
    "sg:phone":"+1   ",
    "sg:postcode":"18040",
    "sg:province":"PA",
    "sg:tags":[
        "lawn",
        "care"
    ],
    "wof:name":"Woolverton Lawncare",
    "wof:placetype":"venue"
},
  "geometry": {"coordinates":[-75.21843,40.732429],"type":"Point"}
}