{
  "type": "Feature",
  "properties": {
    "iso:country":"US",
    "sg:address":"301 3rd Ave",
    "sg:city":"Pittsburgh",
    "sg:classifiers":[
        {
            "category":"Real Estate",
            "subcategory":"Real Estate Operator",
            "type":"Services"
        }
    ],
    "sg:phone":"+1   ",
    "sg:postcode":"15222",
    "sg:province":"PA",
    "sg:tags":[
        "building",
        "commercial",
        "low",
        "income"
    ],
    "wof:name":"Wood Street Commons Associates",
    "wof:placetype":"venue"
},
  "geometry": {"coordinates":[-79.999888,40.438212],"type":"Point"}
}