{
  "type": "Feature",
  "properties": {
    "addr:full":"719 Highland Ave Lancaster PA 17603",
    "addr:housenumber":"719",
    "addr:postcode":"17603",
    "addr:street":"Highland Ave",
    "iso:country":"US",
    "sg:address":"719 Highland Ave",
    "sg:city":"Lancaster",
    "sg:classifiers":[
        {
            "category":"Retail",
            "subcategory":"Funeral Services",
            "type":"Services"
        }
    ],
    "sg:phone":"+1   ",
    "sg:postcode":"17603",
    "sg:province":"PA",
    "sg:tags":[
        "home",
        "cemetery"
    ],
    "wof:name":"Greenwood Cemetery",
    "wof:placetype":"venue"
},
  "geometry": {"coordinates":[-76.303353,40.025917],"type":"Point"}
}