{
  "type": "Feature",
  "properties": {
    "iso:country":"US",
    "sg:address":"1800 Baltimore Pike",
    "sg:city":"Oxford",
    "sg:classifiers":[
        {
            "category":"Sports & Exercise",
            "subcategory":"Bowling",
            "type":"Entertainment"
        }
    ],
    "sg:phone":"+1 610 932 8850",
    "sg:postcode":"19363",
    "sg:province":"PA",
    "sg:tags":[
        "center"
    ],
    "wof:name":"Oxford Strike 'n Spare Lanes",
    "wof:placetype":"venue"
},
  "geometry": {"coordinates":[-75.98559299999999,39.773229],"type":"Point"}
}