{
  "type": "Feature",
  "properties": {
    "addr:full":"5217 Rexford St Philadelphia PA 19131",
    "addr:housenumber":"5217",
    "addr:postcode":"19131",
    "addr:street":"Rexford St",
    "iso:country":"US",
    "sg:address":"5217 Rexford St",
    "sg:city":"Philadelphia",
    "sg:classifiers":[
        {
            "category":"Organizations",
            "subcategory":"Religious Organization",
            "type":"Services"
        }
    ],
    "sg:phone":"+1 215 473 9423",
    "sg:postcode":"19131",
    "sg:province":"PA",
    "sg:tags":[
        "clergy"
    ],
    "wof:name":"David L Randolph",
    "wof:placetype":"venue"
},
  "geometry": {"coordinates":[-75.232888,39.996161],"type":"Point"}
}