{
  "type": "Feature",
  "properties": {
    "iso:country":"US",
    "sg:address":"383 W Lancaster Ave",
    "sg:city":"Frazer",
    "sg:classifiers":[
        {
            "category":"Social Services",
            "subcategory":"Child Care",
            "type":"Services"
        }
    ],
    "sg:phone":"+1 610 296 9200",
    "sg:postcode":"19355",
    "sg:province":"PA",
    "sg:tags":[
        "kindergarten",
        "academic",
        "school",
        "day"
    ],
    "wof:name":"Malvern Pre School",
    "wof:placetype":"venue"
},
  "geometry": {"coordinates":[-75.51146799999999,40.043256],"type":"Point"}
}