{
  "type": "Feature",
  "properties": {
    "iso:country":"US",
    "sg:address":"317 E Lancaster Ave",
    "sg:city":"Reading",
    "sg:classifiers":[
        {
            "category":"Professional",
            "subcategory":"Lawyer & Legal Services",
            "type":"Services"
        }
    ],
    "sg:phone":"+1 610 775 0555",
    "sg:postcode":"19607",
    "sg:province":"PA",
    "sg:tags":[
        "attorney"
    ],
    "wof:name":"David J Batdorf",
    "wof:placetype":"venue"
},
  "geometry": {"coordinates":[-75.961673,40.306118],"type":"Point"}
}