{
  "type": "Feature",
  "properties": {
    "iso:country":"US",
    "sg:address":"1588 Fairfield Rd",
    "sg:city":"Gettysburg",
    "sg:classifiers":[
        {
            "category":"Professional",
            "subcategory":"Business Services",
            "type":"Services"
        }
    ],
    "sg:phone":"+1 717 334 9262",
    "sg:postcode":"17325",
    "sg:province":"PA",
    "sg:tags":[
        "license"
    ],
    "wof:name":"Federal Licensing",
    "wof:placetype":"venue"
},
  "geometry": {"coordinates":[-77.268013,39.822525],"type":"Point"}
}