{
  "type": "Feature",
  "properties": {
    "addr:full":"3629 Forest Ave Munhall PA 15120",
    "addr:housenumber":"3629",
    "addr:postcode":"15120",
    "addr:street":"Forest Ave",
    "iso:country":"US",
    "sg:address":"3629 Forest Ave",
    "sg:city":"Munhall",
    "sg:classifiers":[
        {
            "category":"Arts & Performance",
            "subcategory":"Theater",
            "type":"Entertainment"
        }
    ],
    "sg:phone":"+1 412 462 1450",
    "sg:postcode":"15120",
    "sg:province":"PA",
    "sg:tags":[
        "entertainer"
    ],
    "wof:name":"New York Hot Bodies",
    "wof:placetype":"venue"
},
  "geometry": {"coordinates":[-79.90791900000001,40.384484],"type":"Point"}
}