{
  "type": "Feature",
  "properties": {
    "iso:country":"US",
    "sg:address":"321 E Mercer St",
    "sg:city":"Harrisville",
    "sg:classifiers":[
        {
            "category":"Health Services",
            "subcategory":"Doctor",
            "type":"Services"
        }
    ],
    "sg:phone":"+1 724 735 4241",
    "sg:postcode":"16038",
    "sg:province":"PA",
    "sg:tags":[
        "physician",
        "surgeon"
    ],
    "wof:name":"Family Healthcare Partners",
    "wof:placetype":"venue"
},
  "geometry": {"coordinates":[-80.00659,41.136918],"type":"Point"}
}