{
  "type": "Feature",
  "properties": {
    "iso:country":"US",
    "sg:address":"1570 Oakland Ave",
    "sg:city":"Indiana",
    "sg:classifiers":[
        {
            "category":"Food & Beverages",
            "subcategory":"Groceries & Convenience Stores",
            "type":"Retail Goods"
        }
    ],
    "sg:phone":"+1 724 465 5943",
    "sg:postcode":"15701",
    "sg:province":"PA",
    "sg:website":"http://www.giantpa.com",
    "wof:name":"Giant",
    "wof:placetype":"venue"
},
  "geometry": {"coordinates":[-79.17340900000001,40.614315],"type":"Point"}
}