{
  "type": "Feature",
  "properties": {
    "addr:full":"120 5th St Pittsburgh PA 15229",
    "addr:housenumber":"120",
    "addr:postcode":"15229",
    "addr:street":"5Th St",
    "iso:country":"US",
    "sg:address":"120 5th St",
    "sg:city":"Pittsburgh",
    "sg:classifiers":[
        {
            "category":"Restaurant",
            "type":"Food & Drink"
        }
    ],
    "sg:phone":"+1   ",
    "sg:postcode":"15229",
    "sg:province":"PA",
    "wof:name":"Sunrise Food Svc Inc",
    "wof:placetype":"venue"
},
  "geometry": {"coordinates":[-80.018496,40.530182],"type":"Point"}
}