{
  "type": "Feature",
  "properties": {
    "iso:country":"US",
    "sg:address":"81 S 15th St",
    "sg:city":"Pittsburgh",
    "sg:classifiers":[
        {
            "category":"Professional",
            "subcategory":"Business Services",
            "type":"Services"
        }
    ],
    "sg:phone":"+1 412 381 0997",
    "sg:postcode":"15203",
    "sg:province":"PA",
    "sg:tags":[
        "interior",
        "consultant",
        "design",
        "decorator"
    ],
    "wof:name":"Paolozzi Design Inc",
    "wof:placetype":"venue"
},
  "geometry": {"coordinates":[-79.983436,40.428556],"type":"Point"}
}