{
  "type": "Feature",
  "properties": {
    "addr:full":"2277 Salem Rd Coopersburg PA 18036",
    "addr:housenumber":"2277",
    "addr:postcode":"18036",
    "addr:street":"Salem Rd",
    "iso:country":"US",
    "sg:address":"2277 Salem Rd",
    "sg:city":"Coopersburg",
    "sg:classifiers":[
        {
            "category":"Building & Trades",
            "subcategory":"Construction",
            "type":"Services"
        }
    ],
    "sg:phone":"+1 610 282 1842",
    "sg:postcode":"18036",
    "sg:province":"PA",
    "sg:tags":[
        "general",
        "contractor"
    ],
    "wof:name":"Klines Home Improvements",
    "wof:placetype":"venue"
},
  "geometry": {"coordinates":[-75.37896600000001,40.507039],"type":"Point"}
}