{
  "type": "Feature",
  "properties": {
    "iso:country":"US",
    "sg:address":"3824 N 5th St",
    "sg:city":"Philadelphia",
    "sg:classifiers":[
        {
            "category":"Restaurant",
            "type":"Food & Drink"
        }
    ],
    "sg:phone":"+1 215 221 6243",
    "sg:postcode":"19140",
    "sg:province":"PA",
    "wof:name":"Jorge A Gonzalez Restaurant",
    "wof:placetype":"venue"
},
  "geometry": {"coordinates":[-75.13645699999999,40.009397],"type":"Point"}
}