{
  "type": "Feature",
  "properties": {
    "addr:full":"1105 Overlook Dr Coatesville PA 19320",
    "addr:housenumber":"1105",
    "addr:postcode":"19320",
    "addr:street":"Overlook Dr",
    "iso:country":"US",
    "sg:address":"1105 Overlook Dr",
    "sg:city":"Coatesville",
    "sg:classifiers":[
        {
            "category":"Restaurant",
            "type":"Food & Drink"
        }
    ],
    "sg:phone":"+1 610 486 6238",
    "sg:postcode":"19320",
    "sg:province":"PA",
    "wof:name":"The Green Papaya Restaurant",
    "wof:placetype":"venue"
},
  "geometry": {"coordinates":[-75.74023200000001,39.954988],"type":"Point"}
}