{
  "type": "Feature",
  "properties": {
    "iso:country":"US",
    "sg:address":"63 Church St",
    "sg:city":"Seven Valleys",
    "sg:classifiers":[
        {
            "category":"Government",
            "subcategory":"Post Office",
            "type":"Public Place"
        }
    ],
    "sg:phone":"+1 717 428 1607",
    "sg:postcode":"17360",
    "sg:province":"PA",
    "wof:name":"US Post Office",
    "wof:placetype":"venue"
},
  "geometry": {"coordinates":[-76.769971,39.854625],"type":"Point"}
}