{
  "type": "Feature",
  "properties": {
    "iso:country":"US",
    "sg:address":"230 Wyoming Ave",
    "sg:city":"Kingston",
    "sg:classifiers":[
        {
            "category":"Social Services",
            "subcategory":"Child Care",
            "type":"Services"
        }
    ],
    "sg:phone":"+1 570 288 5825",
    "sg:postcode":"18704",
    "sg:province":"PA",
    "sg:tags":[
        "day"
    ],
    "wof:name":"Kiddie Space West",
    "wof:placetype":"venue"
},
  "geometry": {"coordinates":[-75.895674,41.262941],"type":"Point"}
}