{
  "type": "Feature",
  "properties": {
    "iso:country":"US",
    "sg:address":"50 Barnsley Ave",
    "sg:city":"Morrisville",
    "sg:classifiers":[
        {
            "category":"Health Services",
            "subcategory":"Doctor",
            "type":"Services"
        }
    ],
    "sg:phone":"+1 215 295 6725",
    "sg:postcode":"19067",
    "sg:province":"PA",
    "sg:tags":[
        "physician",
        "surgeon"
    ],
    "wof:name":"Gmh Associates Of America Inc",
    "wof:placetype":"venue"
},
  "geometry": {"coordinates":[-74.788017,40.201939],"type":"Point"}
}