{
  "type": "Feature",
  "properties": {
    "iso:country":"US",
    "sg:address":"35 E State St",
    "sg:city":"Doylestown",
    "sg:classifiers":[
        {
            "category":"Shopping",
            "subcategory":"Antiques",
            "type":"Retail Goods"
        }
    ],
    "sg:phone":"+1 215 348 4864",
    "sg:postcode":"18901",
    "sg:province":"PA",
    "wof:name":"Expressions Then & Now",
    "wof:placetype":"venue"
},
  "geometry": {"coordinates":[-75.129901,40.310425],"type":"Point"}
}