{
  "type": "Feature",
  "properties": {
    "iso:country":"US",
    "sg:address":"373 Crestview Dr",
    "sg:city":"Fort Washington",
    "sg:classifiers":[
        {
            "category":"Professional",
            "subcategory":"Employment Agencies",
            "type":"Services"
        }
    ],
    "sg:phone":"+1 215 654 9299",
    "sg:postcode":"19034",
    "sg:province":"PA",
    "sg:tags":[
        "opportunity"
    ],
    "wof:name":"Emlin Group",
    "wof:placetype":"venue"
},
  "geometry": {"coordinates":[-75.177891,40.131697],"type":"Point"}
}