{
  "type": "Feature",
  "properties": {
    "iso:country":"US",
    "sg:address":"1125 William Pitt Way",
    "sg:city":"Pittsburgh",
    "sg:classifiers":[
        {
            "category":"Professional",
            "subcategory":"Research",
            "type":"Services"
        }
    ],
    "sg:phone":"+1 412 826 3239",
    "sg:postcode":"15238",
    "sg:province":"PA",
    "wof:name":"Ferro Technologies Inc",
    "wof:placetype":"venue"
},
  "geometry": {"coordinates":[-79.834279,40.542757],"type":"Point"}
}