{
  "type": "Feature",
  "properties": {
    "addr:full":"200 Merrimac St Pittsburgh PA 15211",
    "addr:housenumber":"200",
    "addr:postcode":"15211",
    "addr:street":"Merrimac St",
    "iso:country":"US",
    "sg:address":"200 Merrimac St",
    "sg:city":"Pittsburgh",
    "sg:classifiers":[
        {
            "category":"Home & Garden",
            "subcategory":"Home Furnishings",
            "type":"Retail Goods"
        }
    ],
    "sg:phone":"+1 412 381 1230",
    "sg:postcode":"15211",
    "sg:province":"PA",
    "sg:tags":[
        "decor"
    ],
    "sg:website":"www.dlschwarz.com/",
    "wof:name":"D.L. Schwarz",
    "wof:placetype":"venue"
},
  "geometry": {"coordinates":[-80.013767,40.43278],"type":"Point"}
}