{
  "type": "Feature",
  "properties": {
    "iso:country":"US",
    "sg:address":"5145 N 2nd St",
    "sg:city":"Philadelphia",
    "sg:classifiers":[
        {
            "category":"Manufacturing",
            "subcategory":"Metals",
            "type":"Manufacturing & Wholesale Goods"
        },
        {
            "category":"Shopping",
            "type":"Retail Goods"
        }
    ],
    "sg:phone":"+1 215 457 5858",
    "sg:postcode":"19120",
    "sg:province":"PA",
    "sg:tags":[
        "aluminum",
        "mfg",
        "fiberglass",
        "awning",
        "home",
        "canopy"
    ],
    "wof:name":"Phoenix Awning Company Inc",
    "wof:placetype":"venue"
},
  "geometry": {"coordinates":[-75.12688799999999,40.028703],"type":"Point"}
}