{
  "type": "Feature",
  "properties": {
    "iso:country":"US",
    "sg:address":"500 W State St",
    "sg:city":"Kennett Square",
    "sg:classifiers":[
        {
            "category":"Shopping",
            "type":"Retail Goods"
        }
    ],
    "sg:phone":"+1 610 444 3500",
    "sg:postcode":"19348",
    "sg:province":"PA",
    "sg:tags":[
        "telephone",
        "cellular"
    ],
    "sg:website":"www.tristatewireless.net",
    "wof:name":"TSW Communications",
    "wof:placetype":"venue"
},
  "geometry": {"coordinates":[-75.716922,39.845915],"type":"Point"}
}