{
  "type": "Feature",
  "properties": {
    "addr:full":"5340 Allentown Pike Temple PA 19560",
    "addr:housenumber":"5340",
    "addr:postcode":"19560",
    "addr:street":"Allentown Pike",
    "iso:country":"US",
    "sg:address":"5340 Allentown Pike",
    "sg:city":"Temple",
    "sg:classifiers":[
        {
            "category":"Restaurant",
            "type":"Food & Drink"
        }
    ],
    "sg:phone":"+1 610 929 0543",
    "sg:postcode":"19560",
    "sg:province":"PA",
    "sg:tags":[
        "family"
    ],
    "wof:name":"5th Street Diner",
    "wof:placetype":"venue"
},
  "geometry": {"coordinates":[-75.92088800000001,40.414675],"type":"Point"}
}