{
  "type": "Feature",
  "properties": {
    "iso:country":"US",
    "sg:address":"2 Harvest Dr",
    "sg:city":"Coatesville",
    "sg:classifiers":[
        {
            "category":"Building & Trades",
            "subcategory":"Construction",
            "type":"Services"
        }
    ],
    "sg:phone":"+1 610 384 4151",
    "sg:postcode":"19330",
    "sg:province":"PA",
    "sg:tags":[
        "painter"
    ],
    "wof:name":"Stewart's Painting & Papering",
    "wof:placetype":"venue"
},
  "geometry": {"coordinates":[-75.88954,39.86495],"type":"Point"}
}