{
  "type": "Feature",
  "properties": {
    "iso:country":"US",
    "sg:address":"1707 S Pennsylvania Ave",
    "sg:city":"Morrisville",
    "sg:classifiers":[
        {
            "category":"Building & Trades",
            "subcategory":"Construction",
            "type":"Services"
        }
    ],
    "sg:phone":"+1 215 295 5055",
    "sg:postcode":"19067",
    "sg:province":"PA",
    "sg:tags":[
        "specializing",
        "contractor",
        "manage",
        "general"
    ],
    "sg:website":"www.pennvall.com",
    "wof:name":"Penn Valley Constructors Inc",
    "wof:placetype":"venue"
},
  "geometry": {"coordinates":[-74.761528,40.184144],"type":"Point"}
}