{
  "type": "Feature",
  "properties": {
    "iso:country":"US",
    "sg:address":"32 Station St",
    "sg:city":"Bulger",
    "sg:classifiers":[
        {
            "category":"Real Estate",
            "subcategory":"Developer",
            "type":"Services"
        }
    ],
    "sg:phone":"+1 724 947 4381",
    "sg:postcode":"15019",
    "sg:province":"PA",
    "wof:name":"Station Street Partners",
    "wof:placetype":"venue"
},
  "geometry": {"coordinates":[-80.359965,40.381259],"type":"Point"}
}