{
  "type": "Feature",
  "properties": {
    "iso:country":"US",
    "sg:address":"2305 Reed St",
    "sg:city":"Williamsport",
    "sg:classifiers":[
        {
            "category":"Utilities",
            "subcategory":"Fuel Oil & Lpg",
            "type":"Services"
        }
    ],
    "sg:phone":"+1   ",
    "sg:postcode":"17701",
    "sg:province":"PA",
    "sg:tags":[
        "dealer"
    ],
    "wof:name":"Loyalsock Firewood Co",
    "wof:placetype":"venue"
},
  "geometry": {"coordinates":[-76.958231,41.253632],"type":"Point"}
}