{
  "type": "Feature",
  "properties": {
    "addr:full":"101 W Cherry St Ste 2 Palmyra PA 17078",
    "addr:housenumber":"101",
    "addr:postcode":"17078",
    "addr:street":"W Cherry St Ste 2",
    "iso:country":"US",
    "sg:address":"101 W Cherry St Ste 2",
    "sg:city":"Palmyra",
    "sg:classifiers":[
        {
            "category":"Banks & Credit Unions",
            "subcategory":"Financial Services",
            "type":"Services"
        }
    ],
    "sg:phone":"+1 717 838 2700",
    "sg:postcode":"17078",
    "sg:province":"PA",
    "sg:tags":[
        "broker",
        "mortgage"
    ],
    "wof:name":"Commonwealth Funding Group",
    "wof:placetype":"venue"
},
  "geometry": {"coordinates":[-76.59613299999999,40.306183],"type":"Point"}
}