{
  "type": "Feature",
  "properties": {
    "addr:full":"237 E King St Lancaster PA 17602",
    "addr:housenumber":"237",
    "addr:postcode":"17602",
    "addr:street":"E King St",
    "iso:country":"US",
    "sg:address":"237 E King St",
    "sg:city":"Lancaster",
    "sg:classifiers":[
        {
            "category":"Health Services",
            "subcategory":"Nursing And Care Facility",
            "type":"Services"
        }
    ],
    "sg:phone":"+1 717 291 9780",
    "sg:postcode":"17602",
    "sg:province":"PA",
    "sg:tags":[
        "home",
        "convalescent",
        "rest"
    ],
    "wof:name":"Lehman's Rest Home",
    "wof:placetype":"venue"
},
  "geometry": {"coordinates":[-76.299432,40.038708],"type":"Point"}
}