{
  "type": "Feature",
  "properties": {
    "iso:country":"US",
    "sg:address":"2134 Farmington Ave",
    "sg:city":"Boyertown",
    "sg:classifiers":[
        {
            "category":"Retail",
            "subcategory":"Repair Shop",
            "type":"Services"
        }
    ],
    "sg:phone":"+1   ",
    "sg:postcode":"19512",
    "sg:province":"PA",
    "sg:tags":[
        "upgrade",
        "system"
    ],
    "wof:name":"Ers Services",
    "wof:placetype":"venue"
},
  "geometry": {"coordinates":[-75.65350100000001,40.317061],"type":"Point"}
}