{
  "type": "Feature",
  "properties": {
    "iso:country":"US",
    "sg:address":"2034 Limekiln Pike",
    "sg:city":"Dresher",
    "sg:classifiers":[
        {
            "category":"Manufacturing",
            "subcategory":"Tools & Machinery",
            "type":"Manufacturing & Wholesale Goods"
        }
    ],
    "sg:phone":"+1 215 646 6600",
    "sg:postcode":"19025",
    "sg:province":"PA",
    "sg:tags":[
        "furnace"
    ],
    "sg:website":"www.selas.com",
    "wof:name":"Selas Corp Of America",
    "wof:placetype":"venue"
},
  "geometry": {"coordinates":[-75.16632,40.135813],"type":"Point"}
}