{
  "type": "Feature",
  "properties": {
    "addr:full":"126 Market St Philadelphia PA 19106",
    "addr:housenumber":"126",
    "addr:postcode":"19106",
    "addr:street":"Market St",
    "iso:country":"US",
    "sg:address":"126 Market St",
    "sg:city":"Philadelphia",
    "sg:classifiers":[
        {
            "category":"Arts & Performance",
            "subcategory":"Art Gallery",
            "type":"Entertainment"
        }
    ],
    "sg:phone":"+1 215 717 7774",
    "sg:postcode":"19106",
    "sg:province":"PA",
    "sg:website":"www.musherlovelundphoto.com/",
    "wof:name":"Gallery ML",
    "wof:placetype":"venue"
},
  "geometry": {"coordinates":[-75.143323,39.94959],"type":"Point"}
}