{
  "type": "Feature",
  "properties": {
    "addr:full":"300 Monroeville Mall Monroeville PA 15146",
    "addr:housenumber":"300",
    "addr:postcode":"15146",
    "addr:street":"Monroeville Mall",
    "iso:country":"US",
    "sg:address":"300 Monroeville Mall",
    "sg:city":"Monroeville",
    "sg:classifiers":[
        {
            "category":"Restaurant",
            "type":"Food & Drink"
        }
    ],
    "sg:phone":"+1 412 373 8520",
    "sg:postcode":"15146",
    "sg:province":"PA",
    "sg:tags":[
        "style",
        "american",
        "family"
    ],
    "sg:website":"http://www.houlihans.com/",
    "wof:name":"Houlihan's",
    "wof:placetype":"venue"
},
  "geometry": {"coordinates":[-79.795689,40.431635],"type":"Point"}
}