{
  "type": "Feature",
  "properties": {
    "addr:full":"1229 Chestnut St Ofc M7 Philadelphia PA 19107",
    "addr:housenumber":"1229;m7",
    "addr:postcode":"19107",
    "addr:street":"Chestnut St",
    "iso:country":"US",
    "sg:address":"1229 Chestnut St Ofc M7",
    "sg:city":"Philadelphia",
    "sg:classifiers":[
        {
            "category":"Personal",
            "type":"Services"
        }
    ],
    "sg:phone":"+1 215 592 8411",
    "sg:postcode":"19107",
    "sg:province":"PA",
    "sg:tags":[
        "mover"
    ],
    "wof:name":"Fox Piano Movers Inc",
    "wof:placetype":"venue"
},
  "geometry": {"coordinates":[-75.160599,39.9506],"type":"Point"}
}