{
  "type": "Feature",
  "properties": {
    "addr:full":"1841 Bethlehem Pike Flourtown PA 19031",
    "addr:housenumber":"1841",
    "addr:postcode":"19031",
    "addr:street":"Bethlehem Pike",
    "iso:country":"US",
    "sg:address":"1841 Bethlehem Pike",
    "sg:city":"Flourtown",
    "sg:classifiers":[
        {
            "category":"Shopping",
            "subcategory":"Clothing, Apparel, & Fashions",
            "type":"Retail Goods"
        }
    ],
    "sg:phone":"+1 215 836 1770",
    "sg:postcode":"19031",
    "sg:province":"PA",
    "wof:name":"Dress Barn",
    "wof:placetype":"venue"
},
  "geometry": {"coordinates":[-75.214049,40.109991],"type":"Point"}
}