{
  "type": "Feature",
  "properties": {
    "iso:country":"US",
    "sg:address":"4955 Steubenville Pike",
    "sg:city":"Pittsburgh",
    "sg:classifiers":[
        {
            "category":"Organizations",
            "subcategory":"Non-profit Organization",
            "type":"Services"
        },
        {
            "category":"Health Services",
            "subcategory":"Hospital",
            "type":"Services"
        }
    ],
    "sg:phone":"+1 412 788 6292",
    "sg:postcode":"15205",
    "sg:province":"PA",
    "sg:tags":[
        "information",
        "alcoholism",
        "treatment"
    ],
    "wof:name":"Greenbriar Treatment Center",
    "wof:placetype":"venue"
},
  "geometry": {"coordinates":[-80.112551,40.449768],"type":"Point"}
}