{
  "type": "Feature",
  "properties": {
    "iso:country":"US",
    "sg:address":"1340 Newark Rd",
    "sg:city":"Toughkenamon",
    "sg:classifiers":[
        {
            "category":"Farming",
            "subcategory":"Farm",
            "type":"Manufacturing & Wholesale Goods"
        }
    ],
    "sg:phone":"+1 610 268 3773",
    "sg:postcode":"19374",
    "sg:province":"PA",
    "sg:tags":[
        "mushroom"
    ],
    "sg:website":"www.modernmush.com",
    "wof:name":"C & C Carriage Mushroom Co",
    "wof:placetype":"venue"
},
  "geometry": {"coordinates":[-75.76504199999999,39.844728],"type":"Point"}
}