{
  "type": "Feature",
  "properties": {
    "addr:full":"122 Gregg Cir Edinburg PA 16116",
    "addr:housenumber":"122",
    "addr:postcode":"16116",
    "addr:street":"Gregg Cir",
    "iso:country":"US",
    "sg:address":"122 Gregg Cir",
    "sg:city":"Edinburg",
    "sg:classifiers":[
        {
            "category":"Retail",
            "subcategory":"Auto Repair",
            "type":"Services"
        }
    ],
    "sg:phone":"+1   ",
    "sg:postcode":"16116",
    "sg:province":"PA",
    "sg:tags":[
        "glass",
        "replacement"
    ],
    "wof:name":"Car Shield",
    "wof:placetype":"venue"
},
  "geometry": {"coordinates":[-80.46448599999999,41.011623],"type":"Point"}
}