{
  "type": "Feature",
  "properties": {
    "iso:country":"US",
    "sg:address":"2349 N 22nd St",
    "sg:city":"Philadelphia",
    "sg:classifiers":[
        {
            "category":"Shopping",
            "subcategory":"Clothing, Apparel, & Fashions",
            "type":"Retail Goods"
        }
    ],
    "sg:phone":"+1 215 223 2231",
    "sg:postcode":"19132",
    "sg:province":"PA",
    "sg:tags":[
        "shop",
        "cap",
        "hat",
        "sportswear"
    ],
    "sg:website":"http://www.lids.com",
    "wof:name":"Lids",
    "wof:placetype":"venue"
},
  "geometry": {"coordinates":[-75.168637,39.990612],"type":"Point"}
}