{
  "type": "Feature",
  "properties": {
    "iso:country":"US",
    "sg:address":"2455 Warrensville Rd",
    "sg:city":"Montoursville",
    "sg:classifiers":[
        {
            "category":"Utilities",
            "subcategory":"Fuel Oil & Lpg",
            "type":"Services"
        }
    ],
    "sg:phone":"+1 570 433 3898",
    "sg:postcode":"17754",
    "sg:province":"PA",
    "sg:tags":[
        "firewood"
    ],
    "wof:name":"Loyalsock Firewood Co",
    "wof:placetype":"venue"
},
  "geometry": {"coordinates":[-76.940247,41.293031],"type":"Point"}
}