{
  "type": "Feature",
  "properties": {
    "addr:full":"213 S Maple Ave Greensburg PA 15601",
    "addr:housenumber":"213",
    "addr:postcode":"15601",
    "addr:street":"S Maple Ave",
    "iso:country":"US",
    "sg:address":"213 S Maple Ave",
    "sg:city":"Greensburg",
    "sg:classifiers":[
        {
            "category":"Insurance",
            "subcategory":"Insurance Agent",
            "type":"Services"
        }
    ],
    "sg:phone":"+1 724 834 2444",
    "sg:postcode":"15601",
    "sg:province":"PA",
    "wof:name":"Liberty Insurance Corp",
    "wof:placetype":"venue"
},
  "geometry": {"coordinates":[-79.54271199999999,40.301283],"type":"Point"}
}