{
  "type": "Feature",
  "properties": {
    "iso:country":"US",
    "sg:address":"128 Ornida Dr",
    "sg:city":"Beaver",
    "sg:classifiers":[
        {
            "category":"Food & Beverages",
            "subcategory":"Meat & Fish",
            "type":"Retail Goods"
        }
    ],
    "sg:phone":"+1 724 775 9730",
    "sg:postcode":"15009",
    "sg:province":"PA",
    "sg:tags":[
        "convenience",
        "store"
    ],
    "wof:name":"Patsy's Deli",
    "wof:placetype":"venue"
},
  "geometry": {"coordinates":[-80.347679,40.698509],"type":"Point"}
}