{
  "type": "Feature",
  "properties": {
    "iso:country":"US",
    "sg:address":"860 Springdale Dr Ste 500",
    "sg:city":"Exton",
    "sg:classifiers":[
        {
            "category":"Professional",
            "subcategory":"Lawyer & Legal Services",
            "type":"Services"
        }
    ],
    "sg:phone":"+1 610 647 6000",
    "sg:postcode":"19341",
    "sg:province":"PA",
    "sg:tags":[
        "plan"
    ],
    "sg:website":"http://www.meliordiscovery.com",
    "wof:name":"Melior Discovery",
    "wof:placetype":"venue"
},
  "geometry": {"coordinates":[-75.602417,40.027279],"type":"Point"}
}