{
  "type": "Feature",
  "properties": {
    "iso:country":"US",
    "sg:address":"70 Broad St",
    "sg:city":"Pittston",
    "sg:classifiers":[
        {
            "category":"Autos & Motor Vehicles",
            "subcategory":"Automobile Sales",
            "type":"Retail Goods"
        }
    ],
    "sg:phone":"+1 570 655 2249",
    "sg:postcode":"18640",
    "sg:province":"PA",
    "sg:tags":[
        "car",
        "dealer",
        "sales"
    ],
    "wof:name":"Ridolfi Brothers Inc",
    "wof:placetype":"venue"
},
  "geometry": {"coordinates":[-75.788083,41.321859],"type":"Point"}
}