{
  "type": "Feature",
  "properties": {
    "addr:full":"23 Main St Clarksville PA 15322",
    "addr:housenumber":"23",
    "addr:postcode":"15322",
    "addr:street":"Main St",
    "iso:country":"US",
    "sg:address":"23 Main St",
    "sg:city":"Clarksville",
    "sg:classifiers":[
        {
            "category":"Health Services",
            "subcategory":"Nursing And Care Facility",
            "type":"Services"
        }
    ],
    "sg:phone":"+1 724 377 2680",
    "sg:postcode":"15322",
    "sg:province":"PA",
    "sg:tags":[
        "personal",
        "home"
    ],
    "wof:name":"Lasoskys Personal Care Home I",
    "wof:placetype":"venue"
},
  "geometry": {"coordinates":[-80.04091,39.975902],"type":"Point"}
}