{
  "type": "Feature",
  "properties": {
    "iso:country":"US",
    "sg:address":"326 Shady Side Rd",
    "sg:city":"Uniontown",
    "sg:classifiers":[
        {
            "category":"Professional",
            "subcategory":"Lawyer & Legal Services",
            "type":"Services"
        }
    ],
    "sg:phone":"+1 724 439 8188",
    "sg:postcode":"15401",
    "sg:province":"PA",
    "sg:tags":[
        "plan"
    ],
    "wof:name":"Moody Mcelorath & Johnston P C",
    "wof:placetype":"venue"
},
  "geometry": {"coordinates":[-79.772366,39.842419],"type":"Point"}
}