{
  "type": "Feature",
  "properties": {
    "iso:country":"US",
    "sg:address":"801 N 9th St",
    "sg:city":"Reading",
    "sg:classifiers":[
        {
            "category":"Shopping",
            "subcategory":"Clothing, Apparel, & Fashions",
            "type":"Retail Goods"
        }
    ],
    "sg:phone":"+1   ",
    "sg:postcode":"19604",
    "sg:province":"PA",
    "sg:tags":[
        "woman",
        "specialty",
        "store",
        "accessory"
    ],
    "wof:name":"Carole Hochman",
    "wof:placetype":"venue"
},
  "geometry": {"coordinates":[-75.919702,40.348817],"type":"Point"}
}