{
  "type": "Feature",
  "properties": {
    "addr:full":"513 11th St New Brighton PA 15066",
    "addr:housenumber":"513",
    "addr:postcode":"15066",
    "addr:street":"11Th St",
    "iso:country":"US",
    "sg:address":"513 11th St",
    "sg:city":"New Brighton",
    "sg:classifiers":[
        {
            "category":"Government",
            "subcategory":"Court House",
            "type":"Public Place"
        }
    ],
    "sg:phone":"+1   ",
    "sg:postcode":"15066",
    "sg:province":"PA",
    "sg:tags":[
        "state"
    ],
    "wof:name":"Magisterial District 36-3-01",
    "wof:placetype":"venue"
},
  "geometry": {"coordinates":[-80.309786,40.733294],"type":"Point"}
}