{
  "type": "Feature",
  "properties": {
    "addr:full":"2100 E Market St York PA 17402",
    "addr:housenumber":"2100",
    "addr:postcode":"17402",
    "addr:street":"E Market St",
    "iso:country":"US",
    "sg:address":"2100 E Market St",
    "sg:city":"York",
    "sg:classifiers":[
        {
            "category":"Banks & Credit Unions",
            "subcategory":"Bank",
            "type":"Services"
        }
    ],
    "sg:phone":"+1 717 757 1555",
    "sg:postcode":"17402",
    "sg:province":"PA",
    "sg:tags":[
        "mortgage"
    ],
    "wof:name":"Bay Capital Corp",
    "wof:placetype":"venue"
},
  "geometry": {"coordinates":[-76.68555000000001,39.973665],"type":"Point"}
}