{
  "type": "Feature",
  "properties": {
    "iso:country":"US",
    "sg:address":"900 Jacobsburg Rd",
    "sg:city":"Wind Gap",
    "sg:classifiers":[
        {
            "category":"Building & Trades",
            "subcategory":"Construction",
            "type":"Services"
        }
    ],
    "sg:phone":"+1   ",
    "sg:postcode":"18091",
    "sg:province":"PA",
    "sg:tags":[
        "new",
        "custom",
        "improvement"
    ],
    "wof:name":"B Mac Donald & Sons",
    "wof:placetype":"venue"
},
  "geometry": {"coordinates":[-75.301427,40.792953],"type":"Point"}
}