{
  "type": "Feature",
  "properties": {
    "iso:country":"US",
    "sg:address":"2 Papercraft Park",
    "sg:city":"Blawnox",
    "sg:classifiers":[
        {
            "category":"Government",
            "subcategory":"Office",
            "type":"Public Place"
        }
    ],
    "sg:phone":"+1 412 826 6560",
    "sg:postcode":"15238",
    "sg:province":"PA",
    "sg:tags":[
        "state",
        "inspection"
    ],
    "sg:website":"www.lcb.state.pa.us",
    "wof:name":"Liquor Control Board",
    "wof:placetype":"venue"
},
  "geometry": {"coordinates":[-79.873516,40.486377],"type":"Point"}
}