{
  "type": "Feature",
  "properties": {
    "iso:country":"US",
    "sg:address":"5444 Penn Ave",
    "sg:city":"Pittsburgh",
    "sg:classifiers":[
        {
            "category":"Autos & Motor Vehicles",
            "subcategory":"Automobile Sales",
            "type":"Retail Goods"
        }
    ],
    "sg:phone":"+1   ",
    "sg:postcode":"15206",
    "sg:province":"PA",
    "wof:name":"Red-Line Racing Inc",
    "wof:placetype":"venue"
},
  "geometry": {"coordinates":[-79.934243,40.464617],"type":"Point"}
}