{
  "type": "Feature",
  "properties": {
    "iso:country":"US",
    "sg:address":"54 S 69th St",
    "sg:city":"Upper Darby",
    "sg:classifiers":[
        {
            "category":"Shopping",
            "subcategory":"Clothing, Apparel, & Fashions",
            "type":"Retail Goods"
        }
    ],
    "sg:phone":"+1   ",
    "sg:postcode":"19082",
    "sg:province":"PA",
    "wof:name":"Shoes",
    "wof:placetype":"venue"
},
  "geometry": {"coordinates":[-75.25862499999999,39.959825],"type":"Point"}
}