{
  "type": "Feature",
  "properties": {
    "iso:country":"US",
    "sg:address":"130 Almshouse Rd Ste 100",
    "sg:city":"Richboro",
    "sg:classifiers":[
        {
            "category":"Professional",
            "subcategory":"Art Services",
            "type":"Services"
        },
        {
            "category":"Home & Garden",
            "subcategory":"Home Furnishings",
            "type":"Retail Goods"
        },
        {
            "category":"Home & Garden",
            "subcategory":"Building Materials",
            "type":"Retail Goods"
        },
        {
            "category":"Building & Trades",
            "subcategory":"Construction",
            "type":"Services"
        }
    ],
    "sg:phone":"+1 215 322 4414",
    "sg:postcode":"18954",
    "sg:province":"PA",
    "sg:tags":[
        "draperies",
        "designer",
        "wallcoverings-installation",
        "wallpaper",
        "window",
        "treatment",
        "wallcoverings",
        "interior",
        "curtain",
        "decorator"
    ],
    "sg:website":"http://classicinteriors-richboro.com",
    "wof:name":"Classic Interiors",
    "wof:placetype":"venue"
},
  "geometry": {"coordinates":[-75.01486199999999,40.21639],"type":"Point"}
}