{
  "type": "Feature",
  "properties": {
    "iso:country":"US",
    "sg:address":"220 N Center St",
    "sg:city":"Fredericksburg",
    "sg:classifiers":[
        {
            "category":"Wholesale",
            "subcategory":"Meat",
            "type":"Manufacturing & Wholesale Goods"
        }
    ],
    "sg:phone":"+1 717 865 2136",
    "sg:postcode":"17026",
    "sg:province":"PA",
    "sg:tags":[
        "poultry",
        "plant",
        "processing"
    ],
    "wof:name":"Raised Right Clg Hill Poultry",
    "wof:placetype":"venue"
},
  "geometry": {"coordinates":[-76.430201,40.448148],"type":"Point"}
}