{
  "type": "Feature",
  "properties": {
    "iso:country":"US",
    "sg:address":"1700 N Market St",
    "sg:city":"Berwick",
    "sg:classifiers":[
        {
            "category":"Restaurant",
            "type":"Food & Drink"
        }
    ],
    "sg:phone":"+1 570 752 7780",
    "sg:postcode":"18603",
    "sg:province":"PA",
    "sg:tags":[
        "eating",
        "pizza"
    ],
    "wof:name":"Scicchitano's",
    "wof:placetype":"venue"
},
  "geometry": {"coordinates":[-76.243832,41.066091],"type":"Point"}
}