{
  "type": "Feature",
  "properties": {
    "addr:full":"6945 Marshall Rd Upper Darby PA 19082",
    "addr:housenumber":"6945",
    "addr:postcode":"19082",
    "addr:street":"Marshall Rd",
    "iso:country":"US",
    "sg:address":"6945 Marshall Rd",
    "sg:city":"Upper Darby",
    "sg:classifiers":[
        {
            "category":"Building & Trades",
            "subcategory":"Locksmith",
            "type":"Services"
        }
    ],
    "sg:phone":"+1 610 553 5057",
    "sg:postcode":"19082",
    "sg:province":"PA",
    "sg:tags":[
        "key"
    ],
    "wof:name":"One Eight Hundred Locksmith",
    "wof:placetype":"venue"
},
  "geometry": {"coordinates":[-75.25787,39.954315],"type":"Point"}
}