{
  "type": "Feature",
  "properties": {
    "addr:full":"919 Sharon New Castle Rd Farrell PA 16121",
    "addr:housenumber":"919",
    "addr:postcode":"16121",
    "addr:street":"Sharon New Castle Rd",
    "iso:country":"US",
    "sg:address":"919 Sharon New Castle Rd",
    "sg:city":"Farrell",
    "sg:classifiers":[
        {
            "category":"Health Services",
            "subcategory":"Doctor",
            "type":"Services"
        }
    ],
    "sg:phone":"+1 724 347 7167",
    "sg:postcode":"16121",
    "sg:province":"PA",
    "sg:tags":[
        "dentist"
    ],
    "wof:name":"George E Lowe DDS",
    "wof:placetype":"venue"
},
  "geometry": {"coordinates":[-80.48313899999999,41.214172],"type":"Point"}
}