{
  "type": "Feature",
  "properties": {
    "addr:full":"56 E Main St Palmyra PA 17078",
    "addr:housenumber":"56",
    "addr:postcode":"17078",
    "addr:street":"E Main St",
    "iso:country":"US",
    "sg:address":"56 E Main St",
    "sg:city":"Palmyra",
    "sg:classifiers":[
        {
            "category":"Personal",
            "subcategory":"Barber",
            "type":"Services"
        }
    ],
    "sg:phone":"+1 717 838 0323",
    "sg:postcode":"17078",
    "sg:province":"PA",
    "wof:name":"Main Street Barber Shop",
    "wof:placetype":"venue"
},
  "geometry": {"coordinates":[-76.595136,40.307781],"type":"Point"}
}