{
  "type": "Feature",
  "properties": {
    "addr:full":"201 S 4th St Du Bois PA 15801",
    "addr:housenumber":"201",
    "addr:postcode":"15801",
    "addr:street":"S 4Th St Du Bois",
    "iso:country":"US",
    "sg:address":"201 S 4th St",
    "sg:city":"Du Bois",
    "sg:classifiers":[
        {
            "category":"Government",
            "subcategory":"Office",
            "type":"Public Place"
        }
    ],
    "sg:phone":"+1 814 371 3490",
    "sg:postcode":"15801",
    "sg:province":"PA",
    "sg:tags":[
        "armed",
        "force",
        "recruiting"
    ],
    "wof:name":"US Naval Recruiting",
    "wof:placetype":"venue"
},
  "geometry": {"coordinates":[-78.75277,41.11497],"type":"Point"}
}