{
  "type": "Feature",
  "properties": {
    "iso:country":"US",
    "sg:address":"1100 Walnut St",
    "sg:city":"Philadelphia",
    "sg:classifiers":[
        {
            "category":"Health Services",
            "subcategory":"Hospital",
            "type":"Services"
        }
    ],
    "sg:phone":"+1   ",
    "sg:postcode":"19107",
    "sg:province":"PA",
    "sg:tags":[
        "general"
    ],
    "wof:name":"Medical Genetic Department",
    "wof:placetype":"venue"
},
  "geometry": {"coordinates":[-75.159751,39.948783],"type":"Point"}
}