{
  "type": "Feature",
  "properties": {
    "iso:country":"US",
    "sg:address":"436 7th Ave",
    "sg:city":"Pittsburgh",
    "sg:classifiers":[
        {
            "category":"Professional",
            "subcategory":"Lawyer & Legal Services",
            "type":"Services"
        }
    ],
    "sg:phone":"+1 412 471 0924",
    "sg:postcode":"15219",
    "sg:province":"PA",
    "wof:name":"Santoro Steven S ESQ",
    "wof:placetype":"venue"
},
  "geometry": {"coordinates":[-79.995697,40.442402],"type":"Point"}
}