{
  "type": "Feature",
  "properties": {
    "iso:country":"US",
    "sg:address":"2501 N 3rd St",
    "sg:city":"Harrisburg",
    "sg:classifiers":[
        {
            "category":"Health Services",
            "subcategory":"Health Practitioner",
            "type":"Services"
        }
    ],
    "sg:phone":"+1 717 782 2344",
    "sg:postcode":"17110",
    "sg:province":"PA",
    "sg:tags":[
        "therapist",
        "physical"
    ],
    "wof:name":"Polyclinic Physical Therapy",
    "wof:placetype":"venue"
},
  "geometry": {"coordinates":[-76.899382,40.286894],"type":"Point"}
}