{
  "type": "Feature",
  "properties": {
    "addr:full":"303 1st St Charleroi PA 15022",
    "addr:housenumber":"303",
    "addr:postcode":"15022",
    "addr:street":"1St St",
    "iso:country":"US",
    "sg:address":"303 1st St",
    "sg:city":"Charleroi",
    "sg:classifiers":[
        {
            "category":"Health Services",
            "subcategory":"Optometrist",
            "type":"Services"
        }
    ],
    "sg:phone":"+1 724 483 3675",
    "sg:postcode":"15022",
    "sg:province":"PA",
    "sg:website":"www.martinelli-eye.com",
    "wof:name":"Martinelli Eye Clinic",
    "wof:placetype":"venue"
},
  "geometry": {"coordinates":[-79.893675,40.133763],"type":"Point"}
}