{
  "type": "Feature",
  "properties": {
    "iso:country":"US",
    "sg:address":"6 S Keyser Ave",
    "sg:city":"Taylor",
    "sg:classifiers":[
        {
            "category":"Freight",
            "type":"Transportation"
        }
    ],
    "sg:phone":"+1 570 344 7055",
    "sg:postcode":"18517",
    "sg:province":"PA",
    "sg:tags":[
        "mover"
    ],
    "wof:name":"Joseph Sparacino Movers",
    "wof:placetype":"venue"
},
  "geometry": {"coordinates":[-75.728623,41.395465],"type":"Point"}
}