{
  "type": "Feature",
  "properties": {
    "addr:full":"206 N Centre St Pottsville PA 17901",
    "addr:housenumber":"206",
    "addr:postcode":"17901",
    "addr:street":"N Centre St",
    "iso:country":"US",
    "sg:address":"206 N Centre St",
    "sg:city":"Pottsville",
    "sg:classifiers":[
        {
            "category":"Shopping",
            "subcategory":"Used Merchandise",
            "type":"Retail Goods"
        }
    ],
    "sg:phone":"+1 570 628 3552",
    "sg:postcode":"17901",
    "sg:province":"PA",
    "sg:tags":[
        "shop",
        "thrift"
    ],
    "wof:name":"Salvation Army Thrift Store",
    "wof:placetype":"venue"
},
  "geometry": {"coordinates":[-76.196063,40.686431],"type":"Point"}
}