{
  "type": "Feature",
  "properties": {
    "addr:full":"16 Maffett St Wilkes Barre PA 18705",
    "addr:housenumber":"16",
    "addr:postcode":"18705",
    "addr:street":"Maffett St",
    "iso:country":"US",
    "sg:address":"16 Maffett St",
    "sg:city":"Wilkes Barre",
    "sg:classifiers":[
        {
            "category":"Retail",
            "subcategory":"Laundry & Dry Cleaning",
            "type":"Services"
        }
    ],
    "sg:phone":"+1   ",
    "sg:postcode":"18705",
    "sg:province":"PA",
    "sg:tags":[
        "drycleaning",
        "plant"
    ],
    "wof:name":"Siani Dry Cleaning",
    "wof:placetype":"venue"
},
  "geometry": {"coordinates":[-75.852259,41.274327],"type":"Point"}
}