{
  "type": "Feature",
  "properties": {
    "addr:full":"1769 Old York Rd Abington PA 19001",
    "addr:housenumber":"1769",
    "addr:postcode":"19001",
    "addr:street":"Old York Rd",
    "iso:country":"US",
    "sg:address":"1769 Old York Rd",
    "sg:city":"Abington",
    "sg:classifiers":[
        {
            "category":"Retail",
            "subcategory":"Repair Shop",
            "type":"Services"
        }
    ],
    "sg:phone":"+1 215 659 1122",
    "sg:postcode":"19001",
    "sg:province":"PA",
    "sg:tags":[
        "player",
        "recorder",
        "video"
    ],
    "sg:website":"www.geloso.com",
    "wof:name":"Geloso Electronics",
    "wof:placetype":"venue"
},
  "geometry": {"coordinates":[-75.11536599999999,40.133444],"type":"Point"}
}