{
  "type": "Feature",
  "properties": {
    "iso:country":"US",
    "sg:address":"75 Meckville Rd",
    "sg:city":"Myerstown",
    "sg:classifiers":[
        {
            "category":"Building & Trades",
            "subcategory":"Construction",
            "type":"Services"
        }
    ],
    "sg:phone":"+1   ",
    "sg:postcode":"17067",
    "sg:province":"PA",
    "sg:tags":[
        "home",
        "kitchen",
        "remodeling",
        "contractor"
    ],
    "wof:name":"Boltz and Sons",
    "wof:placetype":"venue"
},
  "geometry": {"coordinates":[-76.34610000000001,40.45386],"type":"Point"}
}