{
  "type": "Feature",
  "properties": {
    "iso:country":"US",
    "sg:address":"2420 Old Route 422 E",
    "sg:city":"Fenelton",
    "sg:classifiers":[
        {
            "category":"Building & Trades",
            "subcategory":"Landscaping Services",
            "type":"Services"
        }
    ],
    "sg:phone":"+1 724 285 8270",
    "sg:postcode":"16034",
    "sg:province":"PA",
    "sg:tags":[
        "tree"
    ],
    "wof:name":"Tamburo Tree Surgery",
    "wof:placetype":"venue"
},
  "geometry": {"coordinates":[-79.76638,40.859436],"type":"Point"}
}