{
  "type": "Feature",
  "properties": {
    "iso:country":"US",
    "sg:address":"18246 Rigby Rd",
    "sg:city":"Spartansburg",
    "sg:classifiers":[
        {
            "category":"Manufacturing",
            "subcategory":"Furniture",
            "type":"Manufacturing & Wholesale Goods"
        }
    ],
    "sg:phone":"+1   ",
    "sg:postcode":"16434",
    "sg:province":"PA",
    "sg:tags":[
        "drapery",
        "mfg"
    ],
    "wof:name":"Lauries Custom Window",
    "wof:placetype":"venue"
},
  "geometry": {"coordinates":[-79.634666,41.721248],"type":"Point"}
}