{
  "type": "Feature",
  "properties": {
    "addr:full":"131 Montville St Pittsburgh PA 15214",
    "addr:housenumber":"131",
    "addr:postcode":"15214",
    "addr:street":"Montville St",
    "iso:country":"US",
    "sg:address":"131 Montville St",
    "sg:city":"Pittsburgh",
    "sg:classifiers":[
        {
            "category":"Wholesale",
            "subcategory":"Durable Goods & Equipment",
            "type":"Manufacturing & Wholesale Goods"
        }
    ],
    "sg:phone":"+1 412 322 3288",
    "sg:postcode":"15214",
    "sg:province":"PA",
    "sg:tags":[
        "engineering",
        "supply"
    ],
    "wof:name":"G & W Leach Co",
    "wof:placetype":"venue"
},
  "geometry": {"coordinates":[-80.016975,40.499047],"type":"Point"}
}