{
  "type": "Feature",
  "properties": {
    "iso:country":"US",
    "sg:address":"55 Grumbacher Rd",
    "sg:city":"York",
    "sg:classifiers":[
        {
            "category":"Wholesale",
            "subcategory":"Sporting Goods",
            "type":"Manufacturing & Wholesale Goods"
        }
    ],
    "sg:phone":"+1 717 764 8551",
    "sg:postcode":"17406",
    "sg:province":"PA",
    "wof:name":"Bell Sports Inc",
    "wof:placetype":"venue"
},
  "geometry": {"coordinates":[-76.742712,40.039593],"type":"Point"}
}