{
  "type": "Feature",
  "properties": {
    "addr:full":"200 Butler Mall Butler PA 16001",
    "addr:housenumber":"200",
    "addr:postcode":"16001",
    "addr:street":"Butler Mall",
    "iso:country":"US",
    "sg:address":"200 Butler Mall",
    "sg:city":"Butler",
    "sg:classifiers":[
        {
            "category":"Shopping",
            "subcategory":"Department Store",
            "type":"Retail Goods"
        }
    ],
    "sg:phone":"+1 724 284 8566",
    "sg:postcode":"16001",
    "sg:province":"PA",
    "wof:name":"Montgomery Ward & Co",
    "wof:placetype":"venue"
},
  "geometry": {"coordinates":[-79.943729,40.875895],"type":"Point"}
}