{
  "type": "Feature",
  "properties": {
    "addr:full":"841 Kutztown Rd Myerstown PA 17067",
    "addr:housenumber":"841",
    "addr:postcode":"17067",
    "addr:street":"Kutztown Rd",
    "iso:country":"US",
    "sg:address":"841 Kutztown Rd",
    "sg:city":"Myerstown",
    "sg:classifiers":[
        {
            "category":"Manufacturing",
            "subcategory":"Metals",
            "type":"Manufacturing & Wholesale Goods"
        }
    ],
    "sg:phone":"+1 717 933 9365",
    "sg:postcode":"17067",
    "sg:province":"PA",
    "sg:tags":[
        "steel"
    ],
    "wof:name":"BSM Inc",
    "wof:placetype":"venue"
},
  "geometry": {"coordinates":[-76.331524,40.413462],"type":"Point"}
}