{
  "type": "Feature",
  "properties": {
    "addr:full":"230 Lehigh Valley Mall Whitehall PA 18052",
    "addr:housenumber":"230",
    "addr:postcode":"18052",
    "addr:street":"Lehigh Valley Mall",
    "iso:country":"US",
    "sg:address":"230 Lehigh Valley Mall",
    "sg:city":"Whitehall",
    "sg:classifiers":[
        {
            "category":"Restaurant",
            "type":"Food & Drink"
        }
    ],
    "sg:phone":"+1 610 264 9884",
    "sg:postcode":"18052",
    "sg:province":"PA",
    "wof:name":"Mc Donald's",
    "wof:placetype":"venue"
},
  "geometry": {"coordinates":[-75.484245,40.62882],"type":"Point"}
}