{
  "type": "Feature",
  "properties": {
    "iso:country":"US",
    "sg:address":"1027 W Nevada St",
    "sg:city":"Philadelphia",
    "sg:classifiers":[
        {
            "category":"Place Of Worship",
            "type":"Public Place"
        }
    ],
    "sg:phone":"+1 215 684 4170",
    "sg:postcode":"19133",
    "sg:province":"PA",
    "sg:tags":[
        "church"
    ],
    "wof:name":"Temple Heavenly Church Inc",
    "wof:placetype":"venue"
},
  "geometry": {"coordinates":[-75.14952599999999,39.986517],"type":"Point"}
}