{
  "type": "Feature",
  "properties": {
    "iso:country":"US",
    "sg:address":"1014 Logan Ave",
    "sg:city":"Tyrone",
    "sg:classifiers":[
        {
            "category":"Health Services",
            "subcategory":"Doctor",
            "type":"Services"
        }
    ],
    "sg:phone":"+1   ",
    "sg:postcode":"16686",
    "sg:province":"PA",
    "wof:name":"Francis McClain",
    "wof:placetype":"venue"
},
  "geometry": {"coordinates":[-78.23960599999999,40.670985],"type":"Point"}
}