{
  "type": "Feature",
  "properties": {
    "iso:country":"US",
    "sg:address":"7 Cabot Blvd E",
    "sg:city":"Langhorne",
    "sg:classifiers":[
        {
            "category":"Sports & Exercise",
            "subcategory":"Gym",
            "type":"Entertainment"
        }
    ],
    "sg:phone":"+1 215 943 4247",
    "sg:postcode":"19047",
    "sg:province":"PA",
    "sg:tags":[
        "club",
        "health",
        "studio",
        "gymnasium"
    ],
    "sg:website":"www.bodyofchange.com",
    "wof:name":"Personal Fitness Group LLC",
    "wof:placetype":"venue"
},
  "geometry": {"coordinates":[-74.847049,40.193409],"type":"Point"}
}