{
  "type": "Feature",
  "properties": {
    "iso:country":"US",
    "sg:address":"206 State St",
    "sg:city":"Clairton",
    "sg:classifiers":[
        {
            "category":"Restaurant",
            "type":"Food & Drink"
        }
    ],
    "sg:phone":"+1 412 384 7868",
    "sg:postcode":"15025",
    "sg:province":"PA",
    "wof:name":"Ciccanti Ristorante",
    "wof:placetype":"venue"
},
  "geometry": {"coordinates":[-79.877701,40.301498],"type":"Point"}
}