{
  "type": "Feature",
  "properties": {
    "addr:full":"114 Delancey St Philadelphia PA 19106",
    "addr:housenumber":"114",
    "addr:postcode":"19106",
    "addr:street":"Delancey St",
    "iso:country":"US",
    "sg:address":"114 Delancey St",
    "sg:city":"Philadelphia",
    "sg:classifiers":[
        {
            "category":"Professional",
            "subcategory":"Employment Agencies",
            "type":"Services"
        }
    ],
    "sg:phone":"+1   ",
    "sg:postcode":"19106",
    "sg:province":"PA",
    "wof:name":"College Plcment Inst Philadelp",
    "wof:placetype":"venue"
},
  "geometry": {"coordinates":[-75.14495100000001,39.943553],"type":"Point"}
}