{
  "type": "Feature",
  "properties": {
    "iso:country":"US",
    "sg:address":"3 Faber Cir",
    "sg:city":"Tannersville",
    "sg:classifiers":[
        {
            "category":"Building & Trades",
            "subcategory":"Construction",
            "type":"Services"
        }
    ],
    "sg:phone":"+1 570 620 9494",
    "sg:postcode":"18372",
    "sg:province":"PA",
    "sg:tags":[
        "mason",
        "masonry",
        "industrial",
        "contractors-commercial",
        "contractor"
    ],
    "wof:name":"Tanner Ville Storage",
    "wof:placetype":"venue"
},
  "geometry": {"coordinates":[-75.304771,41.041939],"type":"Point"}
}