{
  "type": "Feature",
  "properties": {
    "addr:full":"243 S Camac St Philadelphia PA 19107",
    "addr:housenumber":"243",
    "addr:postcode":"19107",
    "addr:street":"S Camac St",
    "iso:country":"US",
    "sg:address":"243 S Camac St",
    "sg:city":"Philadelphia",
    "sg:classifiers":[
        {
            "category":"Bars & Pubs",
            "type":"Food & Drink"
        }
    ],
    "sg:phone":"+1 215 545 0900",
    "sg:postcode":"19107",
    "sg:province":"PA",
    "sg:tags":[
        "new",
        "american"
    ],
    "sg:website":"www.tavernoncamac.com",
    "wof:name":"Tavern On Camac",
    "wof:placetype":"venue"
},
  "geometry": {"coordinates":[-75.16153300000001,39.947309],"type":"Point"}
}