{
  "type": "Feature",
  "properties": {
    "addr:full":"100 Market Place Dr Oakdale PA 15071",
    "addr:housenumber":"100",
    "addr:postcode":"15071",
    "addr:street":"Market Place Dr",
    "iso:country":"US",
    "sg:address":"100 Market Place Dr",
    "sg:city":"Oakdale",
    "sg:classifiers":[
        {
            "category":"Wholesale",
            "subcategory":"Beer",
            "type":"Manufacturing & Wholesale Goods"
        }
    ],
    "sg:phone":"+1 724 695 0268",
    "sg:postcode":"15071",
    "sg:province":"PA",
    "sg:tags":[
        "ale"
    ],
    "wof:name":"Essex Beer Distributors",
    "wof:placetype":"venue"
},
  "geometry": {"coordinates":[-80.239901,40.440719],"type":"Point"}
}