{
  "type": "Feature",
  "properties": {
    "addr:full":"41 Highland Dr Richboro PA 18954",
    "addr:housenumber":"41",
    "addr:postcode":"18954",
    "addr:street":"Highland Dr",
    "iso:country":"US",
    "sg:address":"41 Highland Dr",
    "sg:city":"Richboro",
    "sg:classifiers":[
        {
            "category":"Building & Trades",
            "subcategory":"Plumbing",
            "type":"Services"
        }
    ],
    "sg:phone":"+1 215 357 2390",
    "sg:postcode":"18954",
    "sg:province":"PA",
    "sg:tags":[
        "conditioning",
        "air",
        "system",
        "contractor"
    ],
    "wof:name":"Boyer Heating & Air Condition",
    "wof:placetype":"venue"
},
  "geometry": {"coordinates":[-75.003083,40.221383],"type":"Point"}
}