{
  "type": "Feature",
  "properties": {
    "addr:full":"2 Genesis Dr New Ringgold PA 17960",
    "addr:housenumber":"2",
    "addr:postcode":"17960",
    "addr:street":"Genesis Dr",
    "iso:country":"US",
    "sg:address":"2 Genesis Dr",
    "sg:city":"New Ringgold",
    "sg:classifiers":[
        {
            "category":"Banks & Credit Unions",
            "subcategory":"Investment Brokerage",
            "type":"Services"
        }
    ],
    "sg:phone":"+1 570 386 8500",
    "sg:postcode":"17960",
    "sg:province":"PA",
    "sg:tags":[
        "advisory",
        "financial"
    ],
    "wof:name":"Maiden Creek Financial Svc",
    "wof:placetype":"venue"
},
  "geometry": {"coordinates":[-75.91131900000001,40.700355],"type":"Point"}
}