{
  "type": "Feature",
  "properties": {
    "iso:country":"US",
    "sg:address":"4322 N 5th St",
    "sg:city":"Philadelphia",
    "sg:classifiers":[
        {
            "category":"Education",
            "subcategory":"Special Training",
            "type":"Public Place"
        }
    ],
    "sg:phone":"+1 215 455 2300",
    "sg:postcode":"19140",
    "sg:province":"PA",
    "wof:name":"Hostos Charter School",
    "wof:placetype":"venue"
},
  "geometry": {"coordinates":[-75.13475099999999,40.017096],"type":"Point"}
}