{
  "type": "Feature",
  "properties": {
    "iso:country":"US",
    "sg:address":"205 Lehigh Valley Mall",
    "sg:city":"Whitehall",
    "sg:classifiers":[
        {
            "category":"Shopping",
            "subcategory":"Jewelry",
            "type":"Retail Goods"
        }
    ],
    "sg:phone":"+1 610 264 7406",
    "sg:postcode":"18052",
    "sg:province":"PA",
    "sg:website":"www.kay.com",
    "wof:name":"Kay Jewelers",
    "wof:placetype":"venue"
},
  "geometry": {"coordinates":[-75.48332000000001,40.630953],"type":"Point"}
}