{
  "type": "Feature",
  "properties": {
    "iso:country":"US",
    "sg:address":"18 Morganza Rd",
    "sg:city":"Canonsburg",
    "sg:classifiers":[
        {
            "category":"Retail",
            "subcategory":"Auto Repair",
            "type":"Services"
        }
    ],
    "sg:phone":"+1 724 746 1200",
    "sg:postcode":"15317",
    "sg:province":"PA",
    "sg:tags":[
        "body",
        "shop"
    ],
    "wof:name":"B Z Auto Body",
    "wof:placetype":"venue"
},
  "geometry": {"coordinates":[-80.1763,40.262001],"type":"Point"}
}