{
  "type": "Feature",
  "properties": {
    "iso:country":"US",
    "sg:address":"6583 Roosevelt Blvd",
    "sg:city":"Philadelphia",
    "sg:classifiers":[
        {
            "category":"Banks & Credit Unions",
            "subcategory":"Bank",
            "type":"Services"
        }
    ],
    "sg:phone":"+1   ",
    "sg:postcode":"19149",
    "sg:province":"PA",
    "sg:tags":[
        "national"
    ],
    "wof:name":"Wachovia Bank National Assn",
    "wof:placetype":"venue"
},
  "geometry": {"coordinates":[-75.067763,40.035385],"type":"Point"}
}