{
  "type": "Feature",
  "properties": {
    "iso:country":"US",
    "sg:address":"135 S 6th St",
    "sg:city":"Indiana",
    "sg:classifiers":[
        {
            "category":"Health Services",
            "subcategory":"Doctor",
            "type":"Services"
        }
    ],
    "sg:phone":"+1 724 465 2370",
    "sg:postcode":"15701",
    "sg:province":"PA",
    "sg:tags":[
        "dentist"
    ],
    "wof:name":"Robert P Lipinski DDS",
    "wof:placetype":"venue"
},
  "geometry": {"coordinates":[-79.150749,40.621225],"type":"Point"}
}