{
  "type": "Feature",
  "properties": {
    "iso:country":"US",
    "sg:address":"79 E Main St",
    "sg:city":"Mount Joy",
    "sg:classifiers":[
        {
            "category":"Restaurant",
            "type":"Food & Drink"
        }
    ],
    "sg:menulink":"http://www.allmenus.com/pa/mount-joy/133565-subway/menu/",
    "sg:phone":"+1 717 653 0433",
    "sg:postcode":"17552",
    "sg:province":"PA",
    "sg:tags":[
        "american",
        "sandwich"
    ],
    "wof:name":"Subway",
    "wof:placetype":"venue"
},
  "geometry": {"coordinates":[-76.49972699999999,40.109677],"type":"Point"}
}