{
  "type": "Feature",
  "properties": {
    "iso:country":"US",
    "sg:address":"38 Southgate Rd",
    "sg:city":"Bradford",
    "sg:classifiers":[
        {
            "category":"Farming",
            "subcategory":"Farm",
            "type":"Manufacturing & Wholesale Goods"
        }
    ],
    "sg:phone":"+1   ",
    "sg:postcode":"16701",
    "sg:province":"PA",
    "sg:tags":[
        "food",
        "covered",
        "crop"
    ],
    "wof:name":"Hart Designs Inc",
    "wof:placetype":"venue"
},
  "geometry": {"coordinates":[-78.672129,41.963745],"type":"Point"}
}