{
  "type": "Feature",
  "properties": {
    "addr:full":"1274 Layton Rd Clarks Summit PA 18411",
    "addr:housenumber":"1274",
    "addr:postcode":"18411",
    "addr:street":"Layton Rd",
    "iso:country":"US",
    "sg:address":"1274 Layton Rd",
    "sg:city":"Clarks Summit",
    "sg:classifiers":[
        {
            "category":"Building & Trades",
            "subcategory":"Construction",
            "type":"Services"
        }
    ],
    "sg:phone":"+1 570 586 0036",
    "sg:postcode":"18411",
    "sg:province":"PA",
    "sg:tags":[
        "general",
        "contractor"
    ],
    "wof:name":"Joe Barrese Construction",
    "wof:placetype":"venue"
},
  "geometry": {"coordinates":[-75.662324,41.490099],"type":"Point"}
}