{
  "type": "Feature",
  "properties": {
    "iso:country":"US",
    "sg:address":"43 Leopard Rd",
    "sg:city":"Paoli",
    "sg:classifiers":[
        {
            "category":"Wholesale",
            "subcategory":"Durable Goods & Equipment",
            "type":"Manufacturing & Wholesale Goods"
        }
    ],
    "sg:phone":"+1 610 408 8440",
    "sg:postcode":"19301",
    "sg:province":"PA",
    "sg:tags":[
        "importer"
    ],
    "sg:website":"www.tophet.com",
    "wof:name":"Tophet Alloys Corp",
    "wof:placetype":"venue"
},
  "geometry": {"coordinates":[-75.471282,40.035546],"type":"Point"}
}