{
  "type": "Feature",
  "properties": {
    "addr:full":"200 Fleet Street Suite 2A Pittsburgh PA 15220",
    "addr:housenumber":"200",
    "addr:postcode":"15220",
    "addr:street":"Fleet Street Suite 2A",
    "iso:country":"US",
    "sg:address":"200 Fleet Street Suite 2A",
    "sg:city":"Pittsburgh",
    "sg:classifiers":[
        {
            "category":"Professional",
            "subcategory":"Computer Services",
            "type":"Services"
        }
    ],
    "sg:postcode":"15220",
    "sg:province":"PA",
    "sg:tags":[
        "wine",
        "restaraunt",
        "ipad",
        "inventory-management"
    ],
    "sg:website":"http://winepicks.com",
    "wof:name":"WinePicks",
    "wof:placetype":"venue"
},
  "geometry": {"coordinates":[-80.048694,40.421246],"type":"Point"}
}