{
  "type": "Feature",
  "properties": {
    "iso:country":"US",
    "sg:address":"1033 Florence St",
    "sg:city":"Lebanon",
    "sg:classifiers":[
        {
            "category":"Freight",
            "type":"Transportation"
        }
    ],
    "sg:phone":"+1 717 272 1926",
    "sg:postcode":"17042",
    "sg:province":"PA",
    "sg:tags":[
        "trucking"
    ],
    "wof:name":"Ginder & Son Inc",
    "wof:placetype":"venue"
},
  "geometry": {"coordinates":[-76.426912,40.331217],"type":"Point"}
}