{
  "type": "Feature",
  "properties": {
    "addr:full":"243 S 8th St Reading PA 19602",
    "addr:housenumber":"243",
    "addr:postcode":"19602",
    "addr:street":"S 8Th St",
    "iso:country":"US",
    "sg:address":"243 S 8th St",
    "sg:city":"Reading",
    "sg:classifiers":[
        {
            "category":"Organizations",
            "subcategory":"Religious Organization",
            "type":"Services"
        }
    ],
    "sg:phone":"+1 610 372 2983",
    "sg:postcode":"19602",
    "sg:province":"PA",
    "sg:tags":[
        "church"
    ],
    "wof:name":"Pentecostal Church Christ Is",
    "wof:placetype":"venue"
},
  "geometry": {"coordinates":[-75.922212,40.331622],"type":"Point"}
}