{
  "type": "Feature",
  "properties": {
    "iso:country":"US",
    "sg:address":"106 Oxbridge Dr",
    "sg:city":"Pittsburgh",
    "sg:classifiers":[
        {
            "category":"Insurance",
            "subcategory":"Insurance Agent",
            "type":"Services"
        }
    ],
    "sg:phone":"+1 412 366 2081",
    "sg:postcode":"15237",
    "sg:province":"PA",
    "wof:name":"James M Stitt",
    "wof:placetype":"venue"
},
  "geometry": {"coordinates":[-80.004705,40.553316],"type":"Point"}
}