{
  "type": "Feature",
  "properties": {
    "iso:country":"US",
    "sg:address":"547 Sugartown Rd",
    "sg:city":"Malvern",
    "sg:classifiers":[
        {
            "category":"Professional",
            "subcategory":"Management & Consulting",
            "type":"Services"
        }
    ],
    "sg:phone":"+1 610 647 6755",
    "sg:postcode":"19355",
    "sg:province":"PA",
    "sg:tags":[
        "consultant",
        "educational"
    ],
    "wof:name":"College Planning",
    "wof:placetype":"venue"
},
  "geometry": {"coordinates":[-75.508196,40.000062],"type":"Point"}
}