{
  "type": "Feature",
  "properties": {
    "iso:country":"US",
    "sg:address":"100 Grand Ave",
    "sg:city":"Aliquippa",
    "sg:classifiers":[
        {
            "category":"Personal",
            "subcategory":"Beauty Salon",
            "type":"Services"
        }
    ],
    "sg:phone":"+1 724 375 2828",
    "sg:postcode":"15001",
    "sg:province":"PA",
    "wof:name":"Aliquippa Hair Ctr",
    "wof:placetype":"venue"
},
  "geometry": {"coordinates":[-80.27427900000001,40.610279],"type":"Point"}
}