{
  "type": "Feature",
  "properties": {
    "addr:full":"221 E York St Biglerville PA 17307",
    "addr:housenumber":"221",
    "addr:postcode":"17307",
    "addr:street":"E York St",
    "iso:country":"US",
    "sg:address":"221 E York St",
    "sg:city":"Biglerville",
    "sg:classifiers":[
        {
            "category":"Professional",
            "type":"Services"
        }
    ],
    "sg:phone":"+1   ",
    "sg:postcode":"17307",
    "sg:province":"PA",
    "wof:name":"Peaceful Moments",
    "wof:placetype":"venue"
},
  "geometry": {"coordinates":[-77.2409,39.930909],"type":"Point"}
}