{
  "type": "Feature",
  "properties": {
    "iso:country":"US",
    "sg:address":"2197 Duss Ave",
    "sg:city":"Ambridge",
    "sg:classifiers":[
        {
            "category":"Utilities",
            "subcategory":"Refuse",
            "type":"Services"
        }
    ],
    "sg:phone":"+1   ",
    "sg:postcode":"15003",
    "sg:province":"PA",
    "sg:tags":[
        "system"
    ],
    "wof:name":"Waste Managementtransfer Stat",
    "wof:placetype":"venue"
},
  "geometry": {"coordinates":[-80.22632,40.602798],"type":"Point"}
}