{
  "type": "Feature",
  "properties": {
    "iso:country":"US",
    "sg:address":"830 McConnell Ave",
    "sg:city":"Erie",
    "sg:classifiers":[
        {
            "category":"Real Estate",
            "subcategory":"Architect",
            "type":"Services"
        }
    ],
    "sg:phone":"+1 814 838 2878",
    "sg:postcode":"16505",
    "sg:province":"PA",
    "wof:name":"Architectural Services",
    "wof:placetype":"venue"
},
  "geometry": {"coordinates":[-80.173935,42.092131],"type":"Point"}
}