{
  "type": "Feature",
  "properties": {
    "addr:full":"1100 W Moyamensing Ave Philadelphia PA 19148",
    "addr:housenumber":"1100",
    "addr:postcode":"19148",
    "addr:street":"W Moyamensing Ave",
    "iso:country":"US",
    "sg:address":"1100 W Moyamensing Ave",
    "sg:city":"Philadelphia",
    "sg:classifiers":[
        {
            "category":"Restaurant",
            "type":"Food & Drink"
        }
    ],
    "sg:phone":"+1 215 336 9099",
    "sg:postcode":"19148",
    "sg:province":"PA",
    "sg:tags":[
        "italian"
    ],
    "wof:name":"Lou's Crab Bar & Seafood",
    "wof:placetype":"venue"
},
  "geometry": {"coordinates":[-75.165367,39.919399],"type":"Point"}
}