{
  "type": "Feature",
  "properties": {
    "addr:full":"2350 Noblestown Rd Pittsburgh PA 15205",
    "addr:housenumber":"2350",
    "addr:postcode":"15205",
    "addr:street":"Noblestown Rd",
    "iso:country":"US",
    "sg:address":"2350 Noblestown Rd",
    "sg:city":"Pittsburgh",
    "sg:classifiers":[
        {
            "category":"Personal",
            "subcategory":"Tanning Parlor",
            "type":"Services"
        }
    ],
    "sg:phone":"+1 412 922 9871",
    "sg:postcode":"15205",
    "sg:province":"PA",
    "wof:name":"Sunny Dayz Tanning Studio",
    "wof:placetype":"venue"
},
  "geometry": {"coordinates":[-80.054526,40.427616],"type":"Point"}
}