{
  "type": "Feature",
  "properties": {
    "addr:full":"19 N Lehigh Ave Frackville PA 17931",
    "addr:housenumber":"19",
    "addr:postcode":"17931",
    "addr:street":"N Lehigh Ave",
    "iso:country":"US",
    "sg:address":"19 N Lehigh Ave",
    "sg:city":"Frackville",
    "sg:classifiers":[
        {
            "category":"Organizations",
            "subcategory":"Religious Organization",
            "type":"Services"
        }
    ],
    "sg:phone":"+1 570 874 0843",
    "sg:postcode":"17931",
    "sg:province":"PA",
    "sg:tags":[
        "church"
    ],
    "wof:name":"Foursquare Gospel Church",
    "wof:placetype":"venue"
},
  "geometry": {"coordinates":[-76.2317,40.786314],"type":"Point"}
}