{
  "type": "Feature",
  "properties": {
    "iso:country":"US",
    "sg:address":"230 Ferry St",
    "sg:city":"Easton",
    "sg:classifiers":[
        {
            "category":"Wholesale",
            "subcategory":"Durable Goods & Equipment",
            "type":"Manufacturing & Wholesale Goods"
        }
    ],
    "sg:phone":"+1 610 253 3600",
    "sg:postcode":"18042",
    "sg:province":"PA",
    "sg:tags":[
        "environmental",
        "ecological",
        "prod"
    ],
    "wof:name":"Miratech Corp",
    "wof:placetype":"venue"
},
  "geometry": {"coordinates":[-75.208961,40.689639],"type":"Point"}
}