{
  "type": "Feature",
  "properties": {
    "iso:country":"US",
    "sg:address":"100 Logan Valley Mall",
    "sg:city":"Altoona",
    "sg:classifiers":[
        {
            "category":"Shopping",
            "subcategory":"Clothing, Apparel, & Fashions",
            "type":"Retail Goods"
        }
    ],
    "sg:phone":"+1 814 941 7079",
    "sg:postcode":"16602",
    "sg:province":"PA",
    "wof:name":"Buckle",
    "wof:placetype":"venue"
},
  "geometry": {"coordinates":[-78.40951699999999,40.47147],"type":"Point"}
}