{
  "type": "Feature",
  "properties": {
    "iso:country":"US",
    "sg:address":"1209 Hausman Rd",
    "sg:city":"Allentown",
    "sg:classifiers":[
        {
            "category":"Real Estate",
            "subcategory":"Architect",
            "type":"Services"
        }
    ],
    "sg:phone":"+1 610 366 2081",
    "sg:postcode":"18104",
    "sg:province":"PA",
    "wof:name":"Mksd Llc",
    "wof:placetype":"venue"
},
  "geometry": {"coordinates":[-75.563068,40.602202],"type":"Point"}
}