{
  "type": "Feature",
  "properties": {
    "iso:country":"US",
    "sg:address":"700 N Preston St",
    "sg:city":"Philadelphia",
    "sg:classifiers":[
        {
            "category":"Retail",
            "subcategory":"Funeral Services",
            "type":"Services"
        }
    ],
    "sg:phone":"+1   ",
    "sg:postcode":"19104",
    "sg:province":"PA",
    "wof:name":"Lillian T David",
    "wof:placetype":"venue"
},
  "geometry": {"coordinates":[-75.203952,39.966164],"type":"Point"}
}