{
  "type": "Feature",
  "properties": {
    "addr:full":"2095 Valley Green Rd Etters PA 17319",
    "addr:housenumber":"2095",
    "addr:postcode":"17319",
    "addr:street":"Valley Green Rd",
    "iso:country":"US",
    "sg:address":"2095 Valley Green Rd",
    "sg:city":"Etters",
    "sg:classifiers":[
        {
            "category":"Wholesale",
            "subcategory":"Durable Goods & Equipment",
            "type":"Manufacturing & Wholesale Goods"
        }
    ],
    "sg:phone":"+1   ",
    "sg:postcode":"17319",
    "sg:province":"PA",
    "sg:tags":[
        "trade"
    ],
    "wof:name":"Aci Computer Supplies",
    "wof:placetype":"venue"
},
  "geometry": {"coordinates":[-76.781088,40.141931],"type":"Point"}
}