{
  "type": "Feature",
  "properties": {
    "addr:full":"945 Roselle Ct Pittsburgh PA 15207",
    "addr:housenumber":"945",
    "addr:postcode":"15207",
    "addr:street":"Roselle Ct",
    "iso:country":"US",
    "sg:address":"945 Roselle Ct",
    "sg:city":"Pittsburgh",
    "sg:classifiers":[
        {
            "category":"Social Services",
            "type":"Services"
        }
    ],
    "sg:phone":"+1   ",
    "sg:postcode":"15207",
    "sg:province":"PA",
    "wof:name":"Bernice W Crawley Manor Tenant",
    "wof:placetype":"venue"
},
  "geometry": {"coordinates":[-79.93238700000001,40.407471],"type":"Point"}
}