{
  "type": "Feature",
  "properties": {
    "iso:country":"US",
    "sg:address":"285 Schuylkill Rd",
    "sg:city":"Spring City",
    "sg:classifiers":[
        {
            "category":"Retail",
            "subcategory":"Auto Repair",
            "type":"Services"
        }
    ],
    "sg:phone":"+1 610 948 0555",
    "sg:postcode":"19475",
    "sg:province":"PA",
    "sg:tags":[
        "repairing",
        "automobile",
        "general"
    ],
    "wof:name":"Red's Auto Repair",
    "wof:placetype":"venue"
},
  "geometry": {"coordinates":[-75.576398,40.191758],"type":"Point"}
}