{
  "type": "Feature",
  "properties": {
    "iso:country":"US",
    "sg:address":"1733 Easton Rd",
    "sg:city":"Willow Grove",
    "sg:classifiers":[
        {
            "category":"Organizations",
            "subcategory":"Religious Organization",
            "type":"Services"
        }
    ],
    "sg:phone":"+1 215 658 1590",
    "sg:postcode":"19090",
    "sg:province":"PA",
    "sg:tags":[
        "church"
    ],
    "wof:name":"Shiloh Missionary Bapt Church",
    "wof:placetype":"venue"
},
  "geometry": {"coordinates":[-75.121144,40.137197],"type":"Point"}
}