{
  "type": "Feature",
  "properties": {
    "iso:country":"US",
    "sg:address":"120 Thousand Oaks Dr",
    "sg:city":"Pittsburgh",
    "sg:classifiers":[
        {
            "category":"Fast Food",
            "type":"Food & Drink"
        },
        {
            "category":"Restaurant",
            "type":"Food & Drink"
        }
    ],
    "sg:phone":"+1 724 941 1131",
    "sg:postcode":"15241",
    "sg:province":"PA",
    "sg:tags":[
        "take"
    ],
    "wof:name":"Ss Fast Foods, Inc.",
    "wof:placetype":"venue"
},
  "geometry": {"coordinates":[-80.092265,40.306469],"type":"Point"}
}