{
  "type": "Feature",
  "properties": {
    "iso:country":"US",
    "sg:address":"100 Pleasant Dr",
    "sg:city":"Aliquippa",
    "sg:classifiers":[
        {
            "category":"Autos & Motor Vehicles",
            "subcategory":"Auto Supplies",
            "type":"Retail Goods"
        }
    ],
    "sg:phone":"+1   ",
    "sg:postcode":"15001",
    "sg:province":"PA",
    "sg:tags":[
        "tire"
    ],
    "wof:name":"Olszanskis Center Exit Tire",
    "wof:placetype":"venue"
},
  "geometry": {"coordinates":[-80.31289599999999,40.631933],"type":"Point"}
}