{
  "type": "Feature",
  "properties": {
    "iso:country":"US",
    "sg:address":"1015 Airport Rd",
    "sg:city":"Allentown",
    "sg:classifiers":[
        {
            "category":"Shopping",
            "subcategory":"Used Merchandise",
            "type":"Retail Goods"
        }
    ],
    "sg:phone":"+1   ",
    "sg:postcode":"18109",
    "sg:province":"PA",
    "wof:name":"Goodwill Inds Mid-Eastern PA",
    "wof:placetype":"venue"
},
  "geometry": {"coordinates":[-75.442847,40.625083],"type":"Point"}
}