{
  "type": "Feature",
  "properties": {
    "addr:full":"8051 Peach St Erie PA 16509",
    "addr:housenumber":"8051",
    "addr:postcode":"16509",
    "addr:street":"Peach St",
    "iso:country":"US",
    "sg:address":"8051 Peach St",
    "sg:city":"Erie",
    "sg:classifiers":[
        {
            "category":"Travel",
            "subcategory":"Hotels & Motels",
            "type":"Entertainment"
        }
    ],
    "sg:phone":"+1 814 866 6666",
    "sg:postcode":"16509",
    "sg:province":"PA",
    "wof:name":"Comfort Inn",
    "wof:placetype":"venue"
},
  "geometry": {"coordinates":[-80.07764299999999,42.046407],"type":"Point"}
}