{
  "type": "Feature",
  "properties": {
    "iso:country":"US",
    "sg:address":"3100 N Main Ave",
    "sg:city":"Scranton",
    "sg:classifiers":[
        {
            "category":"Manufacturing",
            "subcategory":"Glass & Minerals",
            "type":"Manufacturing & Wholesale Goods"
        }
    ],
    "sg:phone":"+1   ",
    "sg:postcode":"18508",
    "sg:province":"PA",
    "sg:tags":[
        "ready",
        "concrete",
        "mfg"
    ],
    "wof:name":"Coon Industries Inc",
    "wof:placetype":"venue"
},
  "geometry": {"coordinates":[-75.64305,41.448417],"type":"Point"}
}