{
  "type": "Feature",
  "properties": {
    "iso:country":"US",
    "sg:address":"400 Main St",
    "sg:city":"Darby",
    "sg:classifiers":[
        {
            "category":"Place Of Worship",
            "subcategory":"Church",
            "type":"Public Place"
        },
        {
            "category":"Place Of Worship",
            "type":"Public Place"
        }
    ],
    "sg:phone":"+1 610 522 0142",
    "sg:postcode":"19023",
    "sg:province":"PA",
    "sg:tags":[
        "churches-presbyterian-arp",
        "churches-presbyterian"
    ],
    "sg:website":"http://www.pcwoodbury.com",
    "wof:name":"First Presbyterian Church",
    "wof:placetype":"venue"
},
  "geometry": {"coordinates":[-75.252861,39.91713],"type":"Point"}
}