{
  "type": "Feature",
  "properties": {
    "iso:country":"US",
    "sg:address":"628 Main St",
    "sg:city":"Stroudsburg",
    "sg:classifiers":[
        {
            "category":"Fast Food",
            "type":"Food & Drink"
        },
        {
            "category":"Restaurant",
            "type":"Food & Drink"
        }
    ],
    "sg:phone":"+1 570 421 4388",
    "sg:postcode":"18360",
    "sg:province":"PA",
    "sg:tags":[
        "seafood",
        "japanese",
        "dining",
        "take",
        "fine",
        "pan",
        "asian"
    ],
    "sg:website":"http://www.eastcafepa.com",
    "wof:name":"East Caf? Restaurant",
    "wof:placetype":"venue"
},
  "geometry": {"coordinates":[-75.193331,40.985564],"type":"Point"}
}