{
  "type": "Feature",
  "properties": {
    "iso:country":"US",
    "sg:address":"111 E Broad St",
    "sg:city":"Hatfield",
    "sg:classifiers":[
        {
            "category":"Personal",
            "subcategory":"Beauty Salon",
            "type":"Services"
        }
    ],
    "sg:phone":"+1 215 362 1909",
    "sg:postcode":"19440",
    "sg:province":"PA",
    "sg:tags":[
        "shop"
    ],
    "wof:name":"Salon Shabella Inc",
    "wof:placetype":"venue"
},
  "geometry": {"coordinates":[-75.298123,40.280973],"type":"Point"}
}