{
  "type": "Feature",
  "properties": {
    "iso:country":"US",
    "sg:address":"100 Graham St",
    "sg:city":"Mc Kees Rocks",
    "sg:classifiers":[
        {
            "category":"Home & Garden",
            "subcategory":"Furniture",
            "type":"Retail Goods"
        }
    ],
    "sg:phone":"+1 412 331 6711",
    "sg:postcode":"15136",
    "sg:province":"PA",
    "wof:name":"Office Furniture Warehouse",
    "wof:placetype":"venue"
},
  "geometry": {"coordinates":[-80.059613,40.476223],"type":"Point"}
}