{
  "type": "Feature",
  "properties": {
    "addr:full":"6399 Douglas St Pittsburgh PA 15217",
    "addr:housenumber":"6399",
    "addr:postcode":"15217",
    "addr:street":"Douglas St",
    "iso:country":"US",
    "sg:address":"6399 Douglas St",
    "sg:city":"Pittsburgh",
    "sg:classifiers":[
        {
            "category":"Real Estate",
            "subcategory":"Real Estate Operator",
            "type":"Services"
        }
    ],
    "sg:phone":"+1   ",
    "sg:postcode":"15217",
    "sg:province":"PA",
    "sg:tags":[
        "building",
        "apartment"
    ],
    "wof:name":"Apartment Washer Co Inc",
    "wof:placetype":"venue"
},
  "geometry": {"coordinates":[-79.917925,40.433592],"type":"Point"}
}