{
  "type": "Feature",
  "properties": {
    "addr:full":"12 Creek Pkwy Boothwyn PA 19061",
    "addr:housenumber":"12",
    "addr:postcode":"19061",
    "addr:street":"Creek Pkwy",
    "iso:country":"US",
    "sg:address":"12 Creek Pkwy",
    "sg:city":"Boothwyn",
    "sg:classifiers":[
        {
            "category":"Shopping",
            "subcategory":"Clothing, Apparel, & Fashions",
            "type":"Retail Goods"
        }
    ],
    "sg:phone":"+1 610 494 4120",
    "sg:postcode":"19061",
    "sg:province":"PA",
    "sg:tags":[
        "theatrical",
        "costume"
    ],
    "sg:website":"www.halloweenadventure.com",
    "wof:name":"Masquerade",
    "wof:placetype":"venue"
},
  "geometry": {"coordinates":[-75.460864,39.854907],"type":"Point"}
}