{
  "type": "Feature",
  "properties": {
    "iso:country":"US",
    "sg:address":"336 Bloomfield St",
    "sg:city":"Johnstown",
    "sg:classifiers":[
        {
            "category":"Building & Trades",
            "subcategory":"Construction",
            "type":"Services"
        }
    ],
    "sg:phone":"+1 814 288 5146",
    "sg:postcode":"15904",
    "sg:province":"PA",
    "sg:tags":[
        "altering",
        "consultant",
        "remodeling",
        "contractor"
    ],
    "wof:name":"Aecom",
    "wof:placetype":"venue"
},
  "geometry": {"coordinates":[-78.846852,40.273367],"type":"Point"}
}