{
  "type": "Feature",
  "properties": {
    "iso:country":"US",
    "sg:address":"2312 Lincoln Hwy",
    "sg:city":"Stoystown",
    "sg:classifiers":[
        {
            "category":"Personal",
            "subcategory":"Beauty Salon",
            "type":"Services"
        }
    ],
    "sg:phone":"+1 814 629 1543",
    "sg:postcode":"15563",
    "sg:province":"PA",
    "wof:name":"Barnick's Simple Elegance Saln",
    "wof:placetype":"venue"
},
  "geometry": {"coordinates":[-79.039652,40.146753],"type":"Point"}
}