{
  "type": "Feature",
  "properties": {
    "addr:full":"2632 E Allegheny Ave Philadelphia PA 19134",
    "addr:housenumber":"2632",
    "addr:postcode":"19134",
    "addr:street":"E Allegheny Ave",
    "iso:country":"US",
    "sg:address":"2632 E Allegheny Ave",
    "sg:city":"Philadelphia",
    "sg:classifiers":[
        {
            "category":"Retail",
            "subcategory":"Funeral Services",
            "type":"Services"
        }
    ],
    "sg:phone":"+1 215 739 1777",
    "sg:postcode":"19134",
    "sg:province":"PA",
    "sg:tags":[
        "cemetery"
    ],
    "wof:name":"Reilly Michael J Funrl Dir",
    "wof:placetype":"venue"
},
  "geometry": {"coordinates":[-75.10320299999999,39.984798],"type":"Point"}
}