{
  "type": "Feature",
  "properties": {
    "iso:country":"US",
    "sg:address":"386 Parkmount Rd",
    "sg:city":"Media",
    "sg:classifiers":[
        {
            "category":"Utilities",
            "subcategory":"Refuse",
            "type":"Services"
        }
    ],
    "sg:phone":"+1 610 459 1135",
    "sg:postcode":"19063",
    "sg:province":"PA",
    "sg:tags":[
        "garbage",
        "collection"
    ],
    "wof:name":"John L Blosenski & Sons Inc",
    "wof:placetype":"venue"
},
  "geometry": {"coordinates":[-75.442666,39.893164],"type":"Point"}
}