{
  "type": "Feature",
  "properties": {
    "iso:country":"US",
    "sg:address":"577 Cedarcrest Dr",
    "sg:city":"Duncansville",
    "sg:classifiers":[
        {
            "category":"Government",
            "subcategory":"Office",
            "type":"Public Place"
        }
    ],
    "sg:phone":"+1 814 695 6300",
    "sg:postcode":"16635",
    "sg:province":"PA",
    "sg:tags":[
        "govt",
        "city"
    ],
    "wof:name":"Blair Twp Water Authority",
    "wof:placetype":"venue"
},
  "geometry": {"coordinates":[-78.402012,40.419963],"type":"Point"}
}