{
  "type": "Feature",
  "properties": {
    "iso:country":"US",
    "sg:address":"2650 E Indiana Ave",
    "sg:city":"Philadelphia",
    "sg:classifiers":[
        {
            "category":"Professional",
            "subcategory":"Engineering",
            "type":"Services"
        }
    ],
    "sg:phone":"+1 215 634 6380",
    "sg:postcode":"19134",
    "sg:province":"PA",
    "sg:tags":[
        "engineer"
    ],
    "sg:website":"www.prengineers.com",
    "wof:name":"Port Richmond Engineering Services Inc",
    "wof:placetype":"venue"
},
  "geometry": {"coordinates":[-75.107437,39.982255],"type":"Point"}
}