{
  "type": "Feature",
  "properties": {
    "iso:country":"US",
    "sg:address":"278 W Park Rd",
    "sg:city":"Portersville",
    "sg:classifiers":[
        {
            "category":"Building & Trades",
            "subcategory":"Landscaping Services",
            "type":"Services"
        }
    ],
    "sg:phone":"+1 724 368 9212",
    "sg:postcode":"16051",
    "sg:province":"PA",
    "sg:tags":[
        "landscape",
        "contractor"
    ],
    "wof:name":"Wolthers' Landscaping",
    "wof:placetype":"venue"
},
  "geometry": {"coordinates":[-80.144217,40.941306],"type":"Point"}
}