{
  "type": "Feature",
  "properties": {
    "iso:country":"US",
    "sg:address":"6649 Chrisphalt Dr",
    "sg:city":"Bath",
    "sg:classifiers":[
        {
            "category":"Health Services",
            "subcategory":"Doctor",
            "type":"Services"
        }
    ],
    "sg:phone":"+1 610 837 7396",
    "sg:postcode":"18014",
    "sg:province":"PA",
    "sg:tags":[
        "physician",
        "surgeon"
    ],
    "wof:name":"Lehigh Valley Ctr",
    "wof:placetype":"venue"
},
  "geometry": {"coordinates":[-75.393089,40.718929],"type":"Point"}
}