{
  "type": "Feature",
  "properties": {
    "iso:country":"US",
    "sg:address":"8538 Sipes Mill Rd",
    "sg:city":"Needmore",
    "sg:classifiers":[
        {
            "category":"Building & Trades",
            "subcategory":"Construction",
            "type":"Services"
        }
    ],
    "sg:phone":"+1   ",
    "sg:postcode":"17238",
    "sg:province":"PA",
    "sg:tags":[
        "excavation",
        "contractor"
    ],
    "wof:name":"Fogal S Excavating",
    "wof:placetype":"venue"
},
  "geometry": {"coordinates":[-78.145977,39.922187],"type":"Point"}
}