{
  "type": "Feature",
  "properties": {
    "iso:country":"US",
    "sg:address":"917 W Main St Ste 100",
    "sg:city":"Somerset",
    "sg:classifiers":[
        {
            "category":"Health Services",
            "subcategory":"Dentist",
            "type":"Services"
        }
    ],
    "sg:phone":"+1 814 445 4769",
    "sg:postcode":"15501",
    "sg:province":"PA",
    "wof:name":"Don Kaufman Dds",
    "wof:placetype":"venue"
},
  "geometry": {"coordinates":[-79.096475,40.009105],"type":"Point"}
}