{
  "type": "Feature",
  "properties": {
    "iso:country":"US",
    "sg:address":"273 Freidhof Ln",
    "sg:city":"Nicktown",
    "sg:classifiers":[
        {
            "category":"Farming",
            "subcategory":"Livestock Farm",
            "type":"Manufacturing & Wholesale Goods"
        }
    ],
    "sg:phone":"+1 814 948 8832",
    "sg:postcode":"15762",
    "sg:province":"PA",
    "sg:tags":[
        "feeding"
    ],
    "wof:name":"Freidhof Farms",
    "wof:placetype":"venue"
},
  "geometry": {"coordinates":[-78.794123,40.648545],"type":"Point"}
}