{
  "type": "Feature",
  "properties": {
    "addr:full":"400 W King St Littlestown PA 17340",
    "addr:housenumber":"400",
    "addr:postcode":"17340",
    "addr:street":"W King St",
    "iso:country":"US",
    "sg:address":"400 W King St",
    "sg:city":"Littlestown",
    "sg:classifiers":[
        {
            "category":"Banks & Credit Unions",
            "subcategory":"Bank",
            "type":"Services"
        }
    ],
    "sg:phone":"+1 717 359 8188",
    "sg:postcode":"17340",
    "sg:province":"PA",
    "wof:name":"Bank Of Hanover & Trust Co",
    "wof:placetype":"venue"
},
  "geometry": {"coordinates":[-77.096453,39.742934],"type":"Point"}
}