{
  "type": "Feature",
  "properties": {
    "iso:country":"US",
    "sg:address":"1110 Maple St",
    "sg:city":"Lebanon",
    "sg:classifiers":[
        {
            "category":"Home & Garden",
            "subcategory":"Carpets & Floor Coverings",
            "type":"Retail Goods"
        }
    ],
    "sg:phone":"+1 717 270 4337",
    "sg:postcode":"17046",
    "sg:province":"PA",
    "sg:tags":[
        "material"
    ],
    "wof:name":"Tightstretch Carpet Install",
    "wof:placetype":"venue"
},
  "geometry": {"coordinates":[-76.43161000000001,40.34991],"type":"Point"}
}