{
  "type": "Feature",
  "properties": {
    "addr:full":"4521 Centre Ave Pittsburgh PA 15213",
    "addr:housenumber":"4521",
    "addr:postcode":"15213",
    "addr:street":"Centre Ave",
    "iso:country":"US",
    "sg:address":"4521 Centre Ave",
    "sg:city":"Pittsburgh",
    "sg:classifiers":[
        {
            "category":"Restaurant",
            "type":"Food & Drink"
        }
    ],
    "sg:menulink":"http://www.allmenus.com/pa/pittsburgh/279103-k--ts-fish--chicken/menu/",
    "sg:phone":"+1 412 621 2526",
    "sg:postcode":"15213",
    "sg:province":"PA",
    "sg:tags":[
        "american",
        "seafood",
        "chicken",
        "salad"
    ],
    "wof:name":"K & T's Fish & Chicken",
    "wof:placetype":"venue"
},
  "geometry": {"coordinates":[-79.95250299999999,40.451852],"type":"Point"}
}