{
  "type": "Feature",
  "properties": {
    "iso:country":"US",
    "sg:address":"1504 E 3rd St",
    "sg:city":"Williamsport",
    "sg:phone":"+1 570 326 7114",
    "sg:postcode":"17701",
    "sg:province":"PA",
    "sg:website":"http://www.ponderosasteakhouses.com",
    "wof:name":"Bonanza",
    "wof:placetype":"venue"
},
  "geometry": {"coordinates":[-76.976688,41.250337],"type":"Point"}
}