{
  "type": "Feature",
  "properties": {
    "iso:country":"US",
    "sg:address":"22 Walnut St",
    "sg:city":"Wellsboro",
    "sg:classifiers":[
        {
            "category":"Real Estate",
            "subcategory":"Real Estate Agent",
            "type":"Services"
        }
    ],
    "sg:phone":"+1 570 723 0571",
    "sg:postcode":"16901",
    "sg:province":"PA",
    "wof:name":"Laurel Realty",
    "wof:placetype":"venue"
},
  "geometry": {"coordinates":[-77.299301,41.747106],"type":"Point"}
}