{
  "type": "Feature",
  "properties": {
    "iso:country":"US",
    "sg:address":"6015 Penn Ave",
    "sg:city":"Pittsburgh",
    "sg:classifiers":[
        {
            "category":"Shopping",
            "subcategory":"Clothing, Apparel, & Fashions",
            "type":"Retail Goods"
        }
    ],
    "sg:phone":"+1   ",
    "sg:postcode":"15206",
    "sg:province":"PA",
    "sg:tags":[
        "wear"
    ],
    "wof:name":"Magic World",
    "wof:placetype":"venue"
},
  "geometry": {"coordinates":[-79.924059,40.461236],"type":"Point"}
}