{
  "type": "Feature",
  "properties": {
    "addr:full":"121 Creekwood Dr Feastervl Trvs PA 19053",
    "addr:housenumber":"121",
    "addr:postcode":"19053",
    "addr:street":"Creekwood Dr;Trvs",
    "iso:country":"US",
    "sg:address":"121 Creekwood Dr",
    "sg:city":"Feastervl Trvs",
    "sg:classifiers":[
        {
            "category":"Insurance",
            "subcategory":"Insurance Agent",
            "type":"Services"
        }
    ],
    "sg:phone":"+1 215 357 7074",
    "sg:postcode":"19053",
    "sg:province":"PA",
    "wof:name":"Anthony Kaniewski Insurance",
    "wof:placetype":"venue"
},
  "geometry": {"coordinates":[-75.0003,40.161907],"type":"Point"}
}