{
  "type": "Feature",
  "properties": {
    "iso:country":"US",
    "sg:address":"8432 Germantown Ave",
    "sg:city":"Philadelphia",
    "sg:classifiers":[
        {
            "category":"Shopping",
            "subcategory":"Stationery & Office Supplies",
            "type":"Retail Goods"
        },
        {
            "category":"Shopping",
            "subcategory":"Gifts & Souvenirs",
            "type":"Retail Goods"
        },
        {
            "category":"Home & Garden",
            "subcategory":"Home Furnishings",
            "type":"Retail Goods"
        }
    ],
    "sg:phone":"+1 215 248 1459",
    "sg:postcode":"19118",
    "sg:province":"PA",
    "sg:tags":[
        "shop",
        "store",
        "candle"
    ],
    "wof:name":"The Candle Shop",
    "wof:placetype":"venue"
},
  "geometry": {"coordinates":[-75.20540099999999,40.075394],"type":"Point"}
}