{
  "type": "Feature",
  "properties": {
    "iso:country":"US",
    "sg:address":"38 Mahoning Dr E",
    "sg:city":"Lehighton",
    "sg:classifiers":[
        {
            "category":"Health Services",
            "subcategory":"Doctor",
            "type":"Services"
        }
    ],
    "sg:phone":"+1 610 377 9000",
    "sg:postcode":"18235",
    "sg:province":"PA",
    "sg:tags":[
        "physician",
        "surgeon"
    ],
    "wof:name":"Robert M Taxin & Assoc",
    "wof:placetype":"venue"
},
  "geometry": {"coordinates":[-75.72968,40.828262],"type":"Point"}
}