{
  "type": "Feature",
  "properties": {
    "addr:full":"1525 N 13th St Philadelphia PA 19122",
    "addr:housenumber":"1525",
    "addr:postcode":"19122",
    "addr:street":"N 13Th St",
    "iso:country":"US",
    "sg:address":"1525 N 13th St",
    "sg:city":"Philadelphia",
    "sg:classifiers":[
        {
            "category":"Health Services",
            "subcategory":"Doctor",
            "type":"Services"
        }
    ],
    "sg:phone":"+1 215 471 2469",
    "sg:postcode":"19122",
    "sg:province":"PA",
    "wof:name":"Levy Elizabeth MD",
    "wof:placetype":"venue"
},
  "geometry": {"coordinates":[-75.156057,39.975888],"type":"Point"}
}