{
  "type": "Feature",
  "properties": {
    "iso:country":"US",
    "sg:address":"3920 Market St",
    "sg:city":"Camp Hill",
    "sg:classifiers":[
        {
            "category":"Health Services",
            "subcategory":"Dentist",
            "type":"Services"
        }
    ],
    "sg:phone":"+1 717 737 4337",
    "sg:postcode":"17011",
    "sg:province":"PA",
    "sg:website":"www.verberfamilydentistry.com",
    "wof:name":"Verber Michael C DMD",
    "wof:placetype":"venue"
},
  "geometry": {"coordinates":[-76.95003800000001,40.238658],"type":"Point"}
}