{
  "type": "Feature",
  "properties": {
    "addr:full":"2131 Oregon Pike Lancaster PA 17601",
    "addr:housenumber":"2131",
    "addr:postcode":"17601",
    "addr:street":"Oregon Pike",
    "iso:country":"US",
    "sg:address":"2131 Oregon Pike",
    "sg:city":"Lancaster",
    "sg:classifiers":[
        {
            "category":"Health Services",
            "subcategory":"Doctor",
            "type":"Services"
        }
    ],
    "sg:phone":"+1 717 569 6484",
    "sg:postcode":"17601",
    "sg:province":"PA",
    "sg:tags":[
        "dentist"
    ],
    "wof:name":"Loeffler & Pitt Dental Assoc",
    "wof:placetype":"venue"
},
  "geometry": {"coordinates":[-76.287752,40.084905],"type":"Point"}
}