{
  "type": "Feature",
  "properties": {
    "addr:full":"887 Centennial Dr Indiana PA 15701",
    "addr:housenumber":"887",
    "addr:postcode":"15701",
    "addr:street":"Centennial Dr",
    "iso:country":"US",
    "sg:address":"887 Centennial Dr",
    "sg:city":"Indiana",
    "sg:classifiers":[
        {
            "category":"Real Estate",
            "subcategory":"Real Estate Operator",
            "type":"Services"
        }
    ],
    "sg:phone":"+1 724 463 9290",
    "sg:postcode":"15701",
    "sg:province":"PA",
    "sg:tags":[
        "apartment"
    ],
    "wof:name":"Colonial Manor Apartments",
    "wof:placetype":"venue"
},
  "geometry": {"coordinates":[-79.19877700000001,40.610176],"type":"Point"}
}