{
  "type": "Feature",
  "properties": {
    "addr:full":"135 N Main St Cambridge Spgs PA 16403",
    "addr:housenumber":"135",
    "addr:postcode":"16403",
    "addr:street":"N Main St",
    "iso:country":"US",
    "sg:address":"135 N Main St",
    "sg:city":"Cambridge Spgs",
    "sg:classifiers":[
        {
            "category":"Food & Beverages",
            "subcategory":"Groceries & Convenience Stores",
            "type":"Retail Goods"
        }
    ],
    "sg:phone":"+1 814 398 8453",
    "sg:postcode":"16403",
    "sg:province":"PA",
    "wof:name":"KWIK Fill",
    "wof:placetype":"venue"
},
  "geometry": {"coordinates":[-80.055592,41.805109],"type":"Point"}
}