{
  "type": "Feature",
  "properties": {
    "iso:country":"US",
    "sg:address":"249 N 7th St",
    "sg:city":"Allentown",
    "sg:classifiers":[
        {
            "category":"Food & Beverages",
            "subcategory":"Groceries & Convenience Stores",
            "type":"Retail Goods"
        }
    ],
    "sg:phone":"+1 484 788 0153",
    "sg:postcode":"18102",
    "sg:province":"PA",
    "wof:name":"J & J Grocery",
    "wof:placetype":"venue"
},
  "geometry": {"coordinates":[-75.47316499999999,40.605805],"type":"Point"}
}