{
  "type": "Feature",
  "properties": {
    "iso:country":"US",
    "sg:address":"750 E Cathedral Rd",
    "sg:city":"Philadelphia",
    "sg:classifiers":[
        {
            "category":"Real Estate",
            "subcategory":"Real Estate Operator",
            "type":"Services"
        }
    ],
    "sg:phone":"+1 215 483 8880",
    "sg:postcode":"19128",
    "sg:province":"PA",
    "sg:tags":[
        "apartment",
        "complex"
    ],
    "wof:name":"Cathedral East Apartments",
    "wof:placetype":"venue"
},
  "geometry": {"coordinates":[-75.238551,40.064762],"type":"Point"}
}