{
  "type": "Feature",
  "properties": {
    "iso:country":"US",
    "sg:address":"8746 New Falls Rd",
    "sg:city":"Levittown",
    "sg:classifiers":[
        {
            "category":"Retail",
            "subcategory":"Animal Services",
            "type":"Services"
        }
    ],
    "sg:phone":"+1   ",
    "sg:postcode":"19054",
    "sg:province":"PA",
    "wof:name":"All Gods Cratures Pet Grooming",
    "wof:placetype":"venue"
},
  "geometry": {"coordinates":[-74.832703,40.172599],"type":"Point"}
}