{
  "type": "Feature",
  "properties": {
    "iso:country":"US",
    "sg:address":"25 N 8th St",
    "sg:city":"Stroudsburg",
    "sg:classifiers":[
        {
            "category":"Health Services",
            "subcategory":"Clinic",
            "type":"Services"
        }
    ],
    "sg:phone":"+1   ",
    "sg:postcode":"18360",
    "sg:province":"PA",
    "sg:tags":[
        "specialty",
        "outpatient"
    ],
    "wof:name":"Salisbury House Inc",
    "wof:placetype":"venue"
},
  "geometry": {"coordinates":[-75.196511,40.985711],"type":"Point"}
}