{
  "type": "Feature",
  "properties": {
    "addr:full":"133 Pine Dr Cresson PA 16630",
    "addr:housenumber":"133",
    "addr:postcode":"16630",
    "addr:street":"Pine Dr",
    "iso:country":"US",
    "sg:address":"133 Pine Dr",
    "sg:city":"Cresson",
    "sg:classifiers":[
        {
            "category":"Recreation",
            "type":"Entertainment"
        }
    ],
    "sg:phone":"+1   ",
    "sg:postcode":"16630",
    "sg:province":"PA",
    "sg:tags":[
        "club",
        "membership"
    ],
    "wof:name":"V F W Post Inc",
    "wof:placetype":"venue"
},
  "geometry": {"coordinates":[-78.577743,40.469806],"type":"Point"}
}