{
  "type": "Feature",
  "properties": {
    "addr:full":"1320 Chester Pike Sharon Hill PA 19079",
    "addr:housenumber":"1320",
    "addr:postcode":"19079",
    "addr:street":"Chester Pike",
    "iso:country":"US",
    "sg:address":"1320 Chester Pike",
    "sg:city":"Sharon Hill",
    "sg:classifiers":[
        {
            "category":"Professional",
            "subcategory":"Accounting & Tax Preparation",
            "type":"Services"
        }
    ],
    "sg:phone":"+1 610 532 0344",
    "sg:postcode":"19079",
    "sg:province":"PA",
    "sg:tags":[
        "return",
        "filing"
    ],
    "wof:name":"Charles Applegate & Assoc",
    "wof:placetype":"venue"
},
  "geometry": {"coordinates":[-75.27722799999999,39.906703],"type":"Point"}
}