{
  "type": "Feature",
  "properties": {
    "iso:country":"US",
    "sg:address":"7024 Route 13",
    "sg:city":"Levittown",
    "sg:classifiers":[
        {
            "category":"Professional",
            "subcategory":"Lawyer & Legal Services",
            "type":"Services"
        }
    ],
    "sg:phone":"+1 215 547 5297",
    "sg:postcode":"19055",
    "sg:province":"PA",
    "wof:name":"Capriglione Scott J & Assocs",
    "wof:placetype":"venue"
},
  "geometry": {"coordinates":[-74.835503,40.147202],"type":"Point"}
}