{
  "type": "Feature",
  "properties": {
    "iso:country":"US",
    "sg:address":"339 Jopa Rd",
    "sg:city":"Greencastle",
    "sg:classifiers":[
        {
            "category":"Building & Trades",
            "subcategory":"Construction",
            "type":"Services"
        }
    ],
    "sg:phone":"+1 717 597 0774",
    "sg:postcode":"17225",
    "sg:province":"PA",
    "sg:tags":[
        "specializing",
        "residential",
        "con",
        "commercial",
        "contractor"
    ],
    "wof:name":"Hudson Construction",
    "wof:placetype":"venue"
},
  "geometry": {"coordinates":[-77.717823,39.78373],"type":"Point"}
}