{
  "type": "Feature",
  "properties": {
    "iso:country":"US",
    "sg:address":"11 Hillcrest Dr",
    "sg:city":"Dallas",
    "sg:classifiers":[
        {
            "category":"Professional",
            "subcategory":"Business Services",
            "type":"Services"
        }
    ],
    "sg:phone":"+1 570 674 5433",
    "sg:postcode":"18612",
    "sg:province":"PA",
    "sg:tags":[
        "appraiser"
    ],
    "wof:name":"Associated Appraisers",
    "wof:placetype":"venue"
},
  "geometry": {"coordinates":[-75.957848,41.337379],"type":"Point"}
}