{
  "type": "Feature",
  "properties": {
    "iso:country":"US",
    "sg:address":"1512 S 13th St",
    "sg:city":"Philadelphia",
    "sg:classifiers":[
        {
            "category":"Professional",
            "subcategory":"Employment Agencies",
            "type":"Services"
        }
    ],
    "sg:phone":"+1 215 551 1214",
    "sg:postcode":"19147",
    "sg:province":"PA",
    "sg:tags":[
        "temporary",
        "contractor"
    ],
    "wof:name":"Event Technologies",
    "wof:placetype":"venue"
},
  "geometry": {"coordinates":[-75.165982,39.93127],"type":"Point"}
}