{
  "type": "Feature",
  "properties": {
    "iso:country":"US",
    "sg:address":"2 Baltimore St",
    "sg:city":"Codorus",
    "sg:classifiers":[
        {
            "category":"Home & Garden",
            "subcategory":"Building Materials",
            "type":"Retail Goods"
        }
    ],
    "sg:phone":"+1   ",
    "sg:postcode":"17311",
    "sg:province":"PA",
    "wof:name":"Gladfelter Construction Inc",
    "wof:placetype":"venue"
},
  "geometry": {"coordinates":[-76.840914,39.816527],"type":"Point"}
}