{
  "type": "Feature",
  "properties": {
    "iso:country":"US",
    "sg:address":"4666 Broadway",
    "sg:city":"Allentown",
    "sg:classifiers":[
        {
            "category":"Banks & Credit Unions",
            "subcategory":"Bank",
            "type":"Services"
        }
    ],
    "sg:phone":"+1   ",
    "sg:postcode":"18104",
    "sg:province":"PA",
    "sg:tags":[
        "mortgage"
    ],
    "wof:name":"Citifinancial Mortgage Company",
    "wof:placetype":"venue"
},
  "geometry": {"coordinates":[-75.55898999999999,40.588523],"type":"Point"}
}