{
  "type": "Feature",
  "properties": {
    "addr:full":"849 Diamond St Williamsport PA 17701",
    "addr:housenumber":"849",
    "addr:postcode":"17701",
    "addr:street":"Diamond St",
    "iso:country":"US",
    "sg:address":"849 Diamond St",
    "sg:city":"Williamsport",
    "sg:classifiers":[
        {
            "category":"Shopping",
            "subcategory":"Department Store",
            "type":"Retail Goods"
        },
        {
            "category":"Shopping",
            "subcategory":"Beauty & Cosmetics",
            "type":"Retail Goods"
        }
    ],
    "sg:phone":"+1 570 327 1927",
    "sg:postcode":"17701",
    "sg:province":"PA",
    "sg:tags":[
        "shop",
        "merchandise"
    ],
    "wof:name":"Dollar Bazaar",
    "wof:placetype":"venue"
},
  "geometry": {"coordinates":[-77.055537,41.238779],"type":"Point"}
}