{
  "type": "Feature",
  "properties": {
    "addr:full":"6456 Market St Upper Darby PA 19082",
    "addr:housenumber":"6456",
    "addr:postcode":"19082",
    "addr:street":"Market St",
    "iso:country":"US",
    "sg:address":"6456 Market St",
    "sg:city":"Upper Darby",
    "sg:classifiers":[
        {
            "category":"Recreation",
            "type":"Entertainment"
        },
        {
            "category":"Organizations",
            "subcategory":"Community Association",
            "type":"Services"
        }
    ],
    "sg:phone":"+1 610 352 3525",
    "sg:postcode":"19082",
    "sg:province":"PA",
    "sg:tags":[
        "club",
        "membership"
    ],
    "wof:name":"Pontiac Society Akritai",
    "wof:placetype":"venue"
},
  "geometry": {"coordinates":[-75.252433,39.962559],"type":"Point"}
}