{
  "type": "Feature",
  "properties": {
    "addr:full":"1100 Weiser St Reading PA 19601",
    "addr:housenumber":"1100",
    "addr:postcode":"19601",
    "addr:street":"Weiser St",
    "iso:country":"US",
    "sg:address":"1100 Weiser St",
    "sg:city":"Reading",
    "sg:classifiers":[
        {
            "category":"Structure",
            "subcategory":"Office Building",
            "type":"Public Place"
        }
    ],
    "sg:phone":"+1 610 374 1134",
    "sg:postcode":"19601",
    "sg:province":"PA",
    "sg:tags":[
        "park"
    ],
    "wof:name":"Reading Properties Lp",
    "wof:placetype":"venue"
},
  "geometry": {"coordinates":[-75.93764899999999,40.351343],"type":"Point"}
}