{
  "type": "Feature",
  "properties": {
    "iso:country":"US",
    "sg:address":"435 Green Ridge St",
    "sg:city":"Scranton",
    "sg:classifiers":[
        {
            "category":"Education",
            "subcategory":"Special Training",
            "type":"Public Place"
        }
    ],
    "sg:phone":"+1   ",
    "sg:postcode":"18509",
    "sg:province":"PA",
    "wof:name":"Collegerecruitingcom",
    "wof:placetype":"venue"
},
  "geometry": {"coordinates":[-75.65456399999999,41.430555],"type":"Point"}
}