{
  "type": "Feature",
  "properties": {
    "iso:country":"US",
    "sg:address":"62 N Main St",
    "sg:city":"Dover",
    "sg:classifiers":[
        {
            "category":"Shopping",
            "subcategory":"Gifts & Souvenirs",
            "type":"Retail Goods"
        }
    ],
    "sg:phone":"+1 717 292 3500",
    "sg:postcode":"17315",
    "sg:province":"PA",
    "wof:name":"Crafty Basket",
    "wof:placetype":"venue"
},
  "geometry": {"coordinates":[-76.85392299999999,40.004492],"type":"Point"}
}