{
  "type": "Feature",
  "properties": {
    "addr:full":"3400 Horizon Dr King Of Prussia PA 19406",
    "addr:housenumber":"3400",
    "addr:postcode":"19406",
    "addr:street":"Horizon Dr",
    "iso:country":"US",
    "sg:address":"3400 Horizon Dr",
    "sg:city":"King Of Prussia",
    "sg:classifiers":[
        {
            "category":"Utilities",
            "subcategory":"Telephone",
            "type":"Services"
        }
    ],
    "sg:phone":"+1 610 313 8700",
    "sg:postcode":"19406",
    "sg:province":"PA",
    "sg:tags":[
        "telecommunication"
    ],
    "sg:website":"www.verizon.com",
    "wof:name":"Verizon Communications",
    "wof:placetype":"venue"
},
  "geometry": {"coordinates":[-75.338922,40.087451],"type":"Point"}
}