{
  "type": "Feature",
  "properties": {
    "iso:country":"US",
    "sg:address":"887 Progress St",
    "sg:city":"Pittsburgh",
    "sg:classifiers":[
        {
            "category":"Social Services",
            "subcategory":"Child Care",
            "type":"Services"
        }
    ],
    "sg:phone":"+1 412 323 2662",
    "sg:postcode":"15212",
    "sg:province":"PA",
    "wof:name":"Allegheny Playhouse",
    "wof:placetype":"venue"
},
  "geometry": {"coordinates":[-79.992688,40.453185],"type":"Point"}
}