{
  "type": "Feature",
  "properties": {
    "addr:full":"635 Industrial Dr Easton PA 18042",
    "addr:housenumber":"635",
    "addr:postcode":"18042",
    "addr:street":"Industrial Dr",
    "iso:country":"US",
    "sg:address":"635 Industrial Dr",
    "sg:city":"Easton",
    "sg:classifiers":[
        {
            "category":"Utilities",
            "subcategory":"Refuse",
            "type":"Services"
        }
    ],
    "sg:phone":"+1 610 258 8737",
    "sg:postcode":"18042",
    "sg:province":"PA",
    "sg:tags":[
        "collection",
        "garbage"
    ],
    "sg:website":"http://www.chrin.org",
    "wof:name":"Chrin Hauling Inc",
    "wof:placetype":"venue"
},
  "geometry": {"coordinates":[-75.224428,40.668296],"type":"Point"}
}