{
  "type": "Feature",
  "properties": {
    "addr:full":"117 E 22nd Ave Homestead PA 15120",
    "addr:housenumber":"117",
    "addr:postcode":"15120",
    "addr:street":"E 22Nd Ave",
    "iso:country":"US",
    "sg:address":"117 E 22nd Ave",
    "sg:city":"Homestead",
    "sg:classifiers":[
        {
            "category":"Restaurant",
            "type":"Food & Drink"
        }
    ],
    "sg:menulink":"http://www.allmenus.com/pa/munhall/232496-vocelli-pizza/menu/",
    "sg:phone":"+1 800 707 1111",
    "sg:postcode":"15120",
    "sg:province":"PA",
    "sg:tags":[
        "american",
        "italian",
        "pizza"
    ],
    "wof:name":"Vocelli Pizza",
    "wof:placetype":"venue"
},
  "geometry": {"coordinates":[-79.90175000000001,40.39783],"type":"Point"}
}