{
  "type": "Feature",
  "properties": {
    "addr:full":"1702 W Allen St Allentown PA 18104",
    "addr:housenumber":"1702",
    "addr:postcode":"18104",
    "addr:street":"W Allen St",
    "iso:country":"US",
    "sg:address":"1702 W Allen St",
    "sg:city":"Allentown",
    "sg:classifiers":[
        {
            "category":"Retail",
            "subcategory":"Self-service Laundry",
            "type":"Services"
        }
    ],
    "sg:phone":"+1 610 439 9686",
    "sg:postcode":"18104",
    "sg:province":"PA",
    "wof:name":"Carriage House Coin Laundry",
    "wof:placetype":"venue"
},
  "geometry": {"coordinates":[-75.49711600000001,40.604522],"type":"Point"}
}