{
  "type": "Feature",
  "properties": {
    "iso:country":"US",
    "sg:address":"2569 Huntingdon Pike",
    "sg:city":"Huntingdon Valley",
    "sg:classifiers":[
        {
            "category":"Building & Trades",
            "subcategory":"Construction",
            "type":"Services"
        }
    ],
    "sg:phone":"+1   ",
    "sg:postcode":"19006",
    "sg:province":"PA",
    "sg:tags":[
        "refuse",
        "system"
    ],
    "wof:name":"Apcon Environmental Services",
    "wof:placetype":"venue"
},
  "geometry": {"coordinates":[-75.063931,40.122937],"type":"Point"}
}