{
  "type": "Feature",
  "properties": {
    "iso:country":"US",
    "sg:address":"238 S Pacific Ave",
    "sg:city":"Pittsburgh",
    "sg:classifiers":[
        {
            "category":"Social Services",
            "subcategory":"Job Training",
            "type":"Services"
        }
    ],
    "sg:phone":"+1 412 362 7119",
    "sg:postcode":"15224",
    "sg:province":"PA",
    "sg:tags":[
        "rehabilitation"
    ],
    "wof:name":"Achieve Rehab Svc",
    "wof:placetype":"venue"
},
  "geometry": {"coordinates":[-79.94036,40.462823],"type":"Point"}
}