{
  "type": "Feature",
  "properties": {
    "iso:country":"US",
    "sg:address":"119 N High St",
    "sg:city":"West Chester",
    "sg:classifiers":[
        {
            "category":"Professional",
            "subcategory":"Computer Services",
            "type":"Services"
        }
    ],
    "sg:phone":"+1 610 431 8246",
    "sg:postcode":"19380",
    "sg:province":"PA",
    "sg:tags":[
        "website",
        "design",
        "system"
    ],
    "wof:name":"Triton Web Studios Inc",
    "wof:placetype":"venue"
},
  "geometry": {"coordinates":[-75.605908,39.961443],"type":"Point"}
}