{
  "type": "Feature",
  "properties": {
    "iso:country":"US",
    "sg:address":"5660 Warrington Ave",
    "sg:city":"Philadelphia",
    "sg:classifiers":[
        {
            "category":"Professional",
            "subcategory":"Employment Agencies",
            "type":"Services"
        }
    ],
    "sg:phone":"+1   ",
    "sg:postcode":"19143",
    "sg:province":"PA",
    "sg:tags":[
        "help",
        "supply"
    ],
    "wof:name":"A K J Building Maintenance",
    "wof:placetype":"venue"
},
  "geometry": {"coordinates":[-75.22900300000001,39.939479],"type":"Point"}
}