{
  "type": "Feature",
  "properties": {
    "iso:country":"US",
    "sg:address":"533 Pocono Blvd",
    "sg:city":"Mount Pocono",
    "sg:classifiers":[
        {
            "category":"Retail",
            "subcategory":"Auto Repair",
            "type":"Services"
        }
    ],
    "sg:phone":"+1   ",
    "sg:postcode":"18344",
    "sg:province":"PA",
    "sg:tags":[
        "automotive"
    ],
    "wof:name":"Alm Jiffy Lube",
    "wof:placetype":"venue"
},
  "geometry": {"coordinates":[-75.362692,41.130732],"type":"Point"}
}