{
  "type": "Feature",
  "properties": {
    "iso:country":"US",
    "sg:address":"5701 Boyertown Pike",
    "sg:city":"Birdsboro",
    "sg:classifiers":[
        {
            "category":"Travel",
            "subcategory":"Hotels & Motels",
            "type":"Entertainment"
        },
        {
            "category":"Restaurant",
            "type":"Food & Drink"
        }
    ],
    "sg:phone":"+1 610 689 8699",
    "sg:postcode":"19508",
    "sg:province":"PA",
    "wof:name":"Stonersville Hotel",
    "wof:placetype":"venue"
},
  "geometry": {"coordinates":[-75.80421200000001,40.316589],"type":"Point"}
}