{
  "type": "Feature",
  "properties": {
    "iso:country":"US",
    "sg:address":"1205 Sylvan Cir",
    "sg:city":"Bellefonte",
    "sg:classifiers":[
        {
            "category":"Manufacturing",
            "subcategory":"Glass & Minerals",
            "type":"Manufacturing & Wholesale Goods"
        },
        {
            "category":"Manufacturing",
            "subcategory":"Building Materials",
            "type":"Manufacturing & Wholesale Goods"
        }
    ],
    "sg:phone":"+1 814 357 8328",
    "sg:postcode":"16823",
    "sg:province":"PA",
    "sg:tags":[
        "plate",
        "window",
        "glazier",
        "replacement",
        "repair"
    ],
    "wof:name":"Felix Glass & Mirror",
    "wof:placetype":"venue"
},
  "geometry": {"coordinates":[-77.752609,40.920528],"type":"Point"}
}