{
  "type": "Feature",
  "properties": {
    "iso:country":"US",
    "sg:address":"2200 E Harrison Ave",
    "sg:city":"Latrobe",
    "sg:classifiers":[
        {
            "category":"Personal",
            "subcategory":"Beauty Salon",
            "type":"Services"
        }
    ],
    "sg:phone":"+1 724 539 9190",
    "sg:postcode":"15650",
    "sg:province":"PA",
    "sg:tags":[
        "shop"
    ],
    "wof:name":"Jocelyn's Beauty Salon",
    "wof:placetype":"venue"
},
  "geometry": {"coordinates":[-79.36918,40.305217],"type":"Point"}
}