{
  "type": "Feature",
  "properties": {
    "iso:country":"US",
    "sg:address":"1057 Brookline Blvd",
    "sg:city":"Pittsburgh",
    "sg:classifiers":[
        {
            "category":"Personal",
            "subcategory":"Beauty Salon",
            "type":"Services"
        }
    ],
    "sg:phone":"+1   ",
    "sg:postcode":"15226",
    "sg:province":"PA",
    "sg:tags":[
        "shop"
    ],
    "wof:name":"Vogue Beauty Salon",
    "wof:placetype":"venue"
},
  "geometry": {"coordinates":[-80.015356,40.391953],"type":"Point"}
}