{
  "type": "Feature",
  "properties": {
    "iso:country":"US",
    "sg:address":"6410 N 11th St",
    "sg:city":"Philadelphia",
    "sg:classifiers":[
        {
            "category":"Professional",
            "subcategory":"Computer Services",
            "type":"Services"
        }
    ],
    "sg:phone":"+1 215 549 7836",
    "sg:postcode":"19126",
    "sg:province":"PA",
    "sg:tags":[
        "isp",
        "provider",
        "internet"
    ],
    "wof:name":"W C I Internet",
    "wof:placetype":"venue"
},
  "geometry": {"coordinates":[-75.1374,40.049783],"type":"Point"}
}