{
  "type": "Feature",
  "properties": {
    "iso:country":"US",
    "sg:address":"6212 Walnut St",
    "sg:city":"Philadelphia",
    "sg:classifiers":[
        {
            "category":"Health Services",
            "subcategory":"Nursing And Care Facility",
            "type":"Services"
        }
    ],
    "sg:phone":"+1 215 476 6264",
    "sg:postcode":"19139",
    "sg:province":"PA",
    "sg:tags":[
        "skilled",
        "intermediate"
    ],
    "wof:name":"Care Pavilion Of Walnut Park",
    "wof:placetype":"venue"
},
  "geometry": {"coordinates":[-75.24730099999999,39.959572],"type":"Point"}
}