{
  "type": "Feature",
  "properties": {
    "addr:full":"121 Galloping Hill Rd New London PA 19360",
    "addr:housenumber":"121",
    "addr:postcode":"19360",
    "addr:street":"Galloping Hill Rd",
    "iso:country":"US",
    "sg:address":"121 Galloping Hill Rd",
    "sg:city":"New London",
    "sg:classifiers":[
        {
            "category":"Organizations",
            "subcategory":"Religious Organization",
            "type":"Services"
        }
    ],
    "sg:phone":"+1 610 255 4329",
    "sg:postcode":"19360",
    "sg:province":"PA",
    "wof:name":"Meute Raymond Rev Jr",
    "wof:placetype":"venue"
},
  "geometry": {"coordinates":[-75.923103,39.8041],"type":"Point"}
}