{
  "type": "Feature",
  "properties": {
    "addr:full":"14 Latchstring Ln Hatboro PA 19040",
    "addr:housenumber":"14",
    "addr:postcode":"19040",
    "addr:street":"Latchstring Ln",
    "iso:country":"US",
    "sg:address":"14 Latchstring Ln",
    "sg:city":"Hatboro",
    "sg:classifiers":[
        {
            "category":"Building & Trades",
            "subcategory":"Electrical",
            "type":"Services"
        }
    ],
    "sg:phone":"+1 215 956 0988",
    "sg:postcode":"19040",
    "sg:province":"PA",
    "sg:tags":[
        "electrical",
        "contractor"
    ],
    "wof:name":"Bruder Electric Inc",
    "wof:placetype":"venue"
},
  "geometry": {"coordinates":[-75.13153200000001,40.202397],"type":"Point"}
}