{
  "type": "Feature",
  "properties": {
    "addr:full":"314 S Irving Ave Scranton PA 18505",
    "addr:housenumber":"314",
    "addr:postcode":"18505",
    "addr:street":"S Irving Ave",
    "iso:country":"US",
    "sg:address":"314 S Irving Ave",
    "sg:city":"Scranton",
    "sg:classifiers":[
        {
            "category":"Health Services",
            "subcategory":"Doctor",
            "type":"Services"
        }
    ],
    "sg:phone":"+1 570 343 2755",
    "sg:postcode":"18505",
    "sg:province":"PA",
    "sg:tags":[
        "psychologist"
    ],
    "wof:name":"Hoffman Diana Ma",
    "wof:placetype":"venue"
},
  "geometry": {"coordinates":[-75.657133,41.39826],"type":"Point"}
}