{
  "type": "Feature",
  "properties": {
    "iso:country":"US",
    "sg:address":"399 Old Allentown Rd",
    "sg:city":"Wind Gap",
    "sg:classifiers":[
        {
            "category":"Building & Trades",
            "subcategory":"Construction",
            "type":"Services"
        }
    ],
    "sg:phone":"+1 610 863 5321",
    "sg:postcode":"18091",
    "sg:province":"PA",
    "sg:tags":[
        "water",
        "well",
        "drilling"
    ],
    "wof:name":"Tomsic Well Drilling",
    "wof:placetype":"venue"
},
  "geometry": {"coordinates":[-75.31925,40.837322],"type":"Point"}
}