{
  "type": "Feature",
  "properties": {
    "iso:country":"US",
    "sg:address":"3960 N 9th St",
    "sg:city":"Philadelphia",
    "sg:classifiers":[
        {
            "category":"Restaurant",
            "type":"Food & Drink"
        }
    ],
    "sg:phone":"+1 215 225 5915",
    "sg:postcode":"19140",
    "sg:province":"PA",
    "sg:tags":[
        "pizza"
    ],
    "wof:name":"Philly's",
    "wof:placetype":"venue"
},
  "geometry": {"coordinates":[-75.141955,40.012749],"type":"Point"}
}