{
  "type": "Feature",
  "properties": {
    "iso:country":"US",
    "sg:address":"1754 Franklin Mills Cir",
    "sg:city":"Philadelphia",
    "sg:classifiers":[
        {
            "category":"Shopping",
            "subcategory":"Baby Store",
            "type":"Retail Goods"
        },
        {
            "category":"Shopping",
            "subcategory":"Department Store",
            "type":"Retail Goods"
        },
        {
            "category":"Shopping",
            "subcategory":"Clothing, Apparel, & Fashions",
            "type":"Retail Goods"
        }
    ],
    "sg:phone":"+1 215 632 7400",
    "sg:postcode":"19154",
    "sg:province":"PA",
    "sg:tags":[
        "furniture",
        "clothing",
        "gear",
        "women's"
    ],
    "sg:website":"www.JCPenney.com",
    "wof:name":"JCPenney",
    "wof:placetype":"venue"
},
  "geometry": {"coordinates":[-74.957818,40.092573],"type":"Point"}
}