{
  "type": "Feature",
  "properties": {
    "iso:country":"US",
    "sg:address":"3348 Babcock Blvd",
    "sg:city":"Pittsburgh",
    "sg:classifiers":[
        {
            "category":"Banks & Credit Unions",
            "subcategory":"Bank",
            "type":"Services"
        }
    ],
    "sg:phone":"+1 412 369 0663",
    "sg:postcode":"15237",
    "sg:province":"PA",
    "sg:tags":[
        "broker",
        "mortgage"
    ],
    "wof:name":"Approval One Mortgage Corp",
    "wof:placetype":"venue"
},
  "geometry": {"coordinates":[-80.019668,40.534814],"type":"Point"}
}