{
  "type": "Feature",
  "properties": {
    "iso:country":"US",
    "sg:address":"134 Bunker Hill Rd",
    "sg:city":"Aliquippa",
    "sg:classifiers":[
        {
            "category":"Organizations",
            "subcategory":"Community Association",
            "type":"Services"
        }
    ],
    "sg:phone":"+1 724 375 4754",
    "sg:postcode":"15001",
    "sg:province":"PA",
    "sg:tags":[
        "club"
    ],
    "wof:name":"Center Township Veterans Post",
    "wof:placetype":"venue"
},
  "geometry": {"coordinates":[-80.315893,40.62993],"type":"Point"}
}