{
  "type": "Feature",
  "properties": {
    "iso:country":"US",
    "sg:address":"15 Mill St",
    "sg:city":"Endicott",
    "sg:classifiers":[
        {
            "category":"Professional",
            "type":"Services"
        }
    ],
    "sg:phone":"+1 607 748 1676",
    "sg:postcode":"13783",
    "sg:province":"PA",
    "sg:tags":[
        "establishment"
    ],
    "wof:name":"Shop Vac Endicott",
    "wof:placetype":"venue"
},
  "geometry": {"coordinates":[-75.283366,41.953139],"type":"Point"}
}