{
  "type": "Feature",
  "properties": {
    "iso:country":"US",
    "sg:address":"740 N Henderson Rd",
    "sg:city":"King Of Prussia",
    "sg:classifiers":[
        {
            "category":"Social Services",
            "subcategory":"Child Care",
            "type":"Services"
        },
        {
            "category":"Shopping",
            "subcategory":"Shoes",
            "type":"Retail Goods"
        }
    ],
    "sg:phone":"+1 610 962 9955",
    "sg:postcode":"19406",
    "sg:province":"PA",
    "sg:tags":[
        "kindergarten",
        "academic",
        "school"
    ],
    "wof:name":"Footsteps Academy Inc",
    "wof:placetype":"venue"
},
  "geometry": {"coordinates":[-75.376341,40.112074],"type":"Point"}
}