{
  "type": "Feature",
  "properties": {
    "iso:country":"US",
    "sg:address":"64 Troxel Rd",
    "sg:city":"Shoemakersville",
    "sg:classifiers":[
        {
            "category":"Professional",
            "subcategory":"Management & Consulting",
            "type":"Services"
        }
    ],
    "sg:phone":"+1   ",
    "sg:postcode":"19555",
    "sg:province":"PA",
    "sg:tags":[
        "retail",
        "direct",
        "sales"
    ],
    "wof:name":"Sherry S Gifts",
    "wof:placetype":"venue"
},
  "geometry": {"coordinates":[-75.938621,40.471794],"type":"Point"}
}