{
  "type": "Feature",
  "properties": {
    "iso:country":"US",
    "sg:address":"4143 Serenity St",
    "sg:city":"Schwenksville",
    "sg:classifiers":[
        {
            "category":"Government",
            "subcategory":"Office",
            "type":"Public Place"
        }
    ],
    "sg:phone":"+1 610 584 4143",
    "sg:postcode":"19473",
    "sg:province":"PA",
    "wof:name":"Jong Min Lee",
    "wof:placetype":"venue"
},
  "geometry": {"coordinates":[-75.400299,40.232571],"type":"Point"}
}