{
  "type": "Feature",
  "properties": {
    "addr:full":"564 W Uwchlan Ave Exton PA 19341",
    "addr:housenumber":"564",
    "addr:postcode":"19341",
    "addr:street":"W Uwchlan Ave",
    "iso:country":"US",
    "sg:address":"564 W Uwchlan Ave",
    "sg:city":"Exton",
    "sg:classifiers":[
        {
            "category":"Health Services",
            "subcategory":"Doctor",
            "type":"Services"
        }
    ],
    "sg:phone":"+1 610 363 7658",
    "sg:postcode":"19341",
    "sg:province":"PA",
    "wof:name":"Robert A Boden DDS",
    "wof:placetype":"venue"
},
  "geometry": {"coordinates":[-75.660884,40.051891],"type":"Point"}
}