{
  "type": "Feature",
  "properties": {
    "iso:country":"US",
    "sg:address":"2710 Terwood Rd",
    "sg:city":"Willow Grove",
    "sg:classifiers":[
        {
            "category":"Social Services",
            "subcategory":"Job Training",
            "type":"Services"
        },
        {
            "category":"Social Services",
            "type":"Services"
        }
    ],
    "sg:phone":"+1 215 659 5904",
    "sg:postcode":"19090",
    "sg:province":"PA",
    "sg:tags":[
        "rehabilitation"
    ],
    "wof:name":"Developmental Enterprises Corp",
    "wof:placetype":"venue"
},
  "geometry": {"coordinates":[-75.106662,40.156668],"type":"Point"}
}