{
  "type": "Feature",
  "properties": {
    "iso:country":"US",
    "sg:address":"5711 Stump Rd",
    "sg:city":"Pipersville",
    "sg:classifiers":[
        {
            "category":"Professional",
            "type":"Services"
        }
    ],
    "sg:phone":"+1   ",
    "sg:postcode":"18947",
    "sg:province":"PA",
    "wof:name":"Donald L Stauffer Sr",
    "wof:placetype":"venue"
},
  "geometry": {"coordinates":[-75.124095,40.40396],"type":"Point"}
}