{
  "type": "Feature",
  "properties": {
    "iso:country":"US",
    "sg:address":"98 Valley Dr",
    "sg:city":"Pittsburgh",
    "sg:classifiers":[
        {
            "category":"Shopping",
            "subcategory":"Clothing, Apparel, & Fashions",
            "type":"Retail Goods"
        }
    ],
    "sg:phone":"+1 412 782 5005",
    "sg:postcode":"15215",
    "sg:province":"PA",
    "wof:name":"Needlepoint & Counter Point",
    "wof:placetype":"venue"
},
  "geometry": {"coordinates":[-79.89833,40.494724],"type":"Point"}
}