{
  "type": "Feature",
  "properties": {
    "iso:country":"US",
    "sg:address":"641 Country Ln",
    "sg:city":"Morton",
    "sg:classifiers":[
        {
            "category":"Home & Garden",
            "subcategory":"Building Materials",
            "type":"Retail Goods"
        },
        {
            "category":"Professional",
            "type":"Services"
        }
    ],
    "sg:phone":"+1 610 604 4443",
    "sg:postcode":"19070",
    "sg:province":"PA",
    "sg:tags":[
        "door"
    ],
    "wof:name":"Excel Door Company Inc",
    "wof:placetype":"venue"
},
  "geometry": {"coordinates":[-75.320503,39.912875],"type":"Point"}
}