{
  "type": "Feature",
  "properties": {
    "iso:country":"US",
    "sg:address":"1489 Baltimore Pike",
    "sg:city":"Springfield",
    "sg:classifiers":[
        {
            "category":"Professional",
            "subcategory":"Research",
            "type":"Services"
        }
    ],
    "sg:phone":"+1 610 543 6215",
    "sg:postcode":"19064",
    "sg:province":"PA",
    "sg:tags":[
        "nonphysical",
        "commercial",
        "market",
        "analysis"
    ],
    "wof:name":"Ivy Group",
    "wof:placetype":"venue"
},
  "geometry": {"coordinates":[-75.359262,39.9127],"type":"Point"}
}