{
  "type": "Feature",
  "properties": {
    "iso:country":"US",
    "sg:address":"1 Baldwin Blvd",
    "sg:city":"Shamokin Dam",
    "sg:classifiers":[
        {
            "category":"Food & Beverages",
            "subcategory":"Groceries & Convenience Stores",
            "type":"Retail Goods"
        }
    ],
    "sg:phone":"+1 570 743 5065",
    "sg:postcode":"17876",
    "sg:province":"PA",
    "wof:name":"Choice Cigarette Discount Otlt",
    "wof:placetype":"venue"
},
  "geometry": {"coordinates":[-76.81779,40.855333],"type":"Point"}
}