{
  "type": "Feature",
  "properties": {
    "iso:country":"US",
    "sg:address":"259 N Radnor Chester Rd",
    "sg:city":"Wayne",
    "sg:classifiers":[
        {
            "category":"Real Estate",
            "subcategory":"Real Estate Agent",
            "type":"Services"
        }
    ],
    "sg:phone":"+1   ",
    "sg:postcode":"19087",
    "sg:province":"PA",
    "wof:name":"Private Equity Management Co",
    "wof:placetype":"venue"
},
  "geometry": {"coordinates":[-75.359155,40.043281],"type":"Point"}
}