{
  "type": "Feature",
  "properties": {
    "addr:full":"1801 Snyder Ave Philadelphia PA 19145",
    "addr:housenumber":"1801",
    "addr:postcode":"19145",
    "addr:street":"Snyder Ave",
    "iso:country":"US",
    "sg:address":"1801 Snyder Ave",
    "sg:city":"Philadelphia",
    "sg:classifiers":[
        {
            "category":"Restaurant",
            "type":"Food & Drink"
        }
    ],
    "sg:phone":"+1 215 462 3939",
    "sg:postcode":"19145",
    "sg:province":"PA",
    "sg:tags":[
        "pizza"
    ],
    "sg:website":"www.daynightpizza.com",
    "wof:name":"Day Night Pizza",
    "wof:placetype":"venue"
},
  "geometry": {"coordinates":[-75.176039,39.925346],"type":"Point"}
}