{
  "type": "Feature",
  "properties": {
    "iso:country":"US",
    "sg:address":"332 Rices Mill Rd",
    "sg:city":"Wyncote",
    "sg:classifiers":[
        {
            "category":"Real Estate",
            "subcategory":"Surveying",
            "type":"Services"
        }
    ],
    "sg:phone":"+1 215 576 8388",
    "sg:postcode":"19095",
    "sg:province":"PA",
    "sg:tags":[
        "surveyor"
    ],
    "wof:name":"Alon Engineering Assoc Inc",
    "wof:placetype":"venue"
},
  "geometry": {"coordinates":[-75.15339,40.090639],"type":"Point"}
}