{
  "type": "Feature",
  "properties": {
    "addr:full":"10045 Frankstown Rd Pittsburgh PA 15235",
    "addr:housenumber":"10045",
    "addr:postcode":"15235",
    "addr:street":"Frankstown Rd",
    "iso:country":"US",
    "sg:address":"10045 Frankstown Rd",
    "sg:city":"Pittsburgh",
    "sg:classifiers":[
        {
            "category":"Retail",
            "subcategory":"Laundry & Dry Cleaning",
            "type":"Services"
        }
    ],
    "sg:phone":"+1 412 241 1994",
    "sg:postcode":"15235",
    "sg:province":"PA",
    "sg:tags":[
        "drycleaning",
        "plant",
        "cleaners"
    ],
    "wof:name":"Dutch Girl Cleaners Inc",
    "wof:placetype":"venue"
},
  "geometry": {"coordinates":[-79.85419899999999,40.464808],"type":"Point"}
}