{
  "type": "Feature",
  "properties": {
    "iso:country":"US",
    "sg:address":"980 W Sunbury Rd",
    "sg:city":"West Sunbury",
    "sg:classifiers":[
        {
            "category":"Building & Trades",
            "subcategory":"Construction",
            "type":"Services"
        }
    ],
    "sg:phone":"+1   ",
    "sg:postcode":"16061",
    "sg:province":"PA",
    "sg:tags":[
        "house"
    ],
    "wof:name":"Fencil Quality Contracting",
    "wof:placetype":"venue"
},
  "geometry": {"coordinates":[-79.905373,40.974599],"type":"Point"}
}