{
  "type": "Feature",
  "properties": {
    "iso:country":"US",
    "sg:address":"123 Cedar Ave",
    "sg:city":"W Conshohocken",
    "sg:classifiers":[
        {
            "category":"Manufacturing",
            "subcategory":"Furniture",
            "type":"Manufacturing & Wholesale Goods"
        }
    ],
    "sg:phone":"+1 267 972 9599",
    "sg:postcode":"19428",
    "sg:province":"PA",
    "sg:tags":[
        "baby",
        "accessory"
    ],
    "wof:name":"Safety Seats",
    "wof:placetype":"venue"
},
  "geometry": {"coordinates":[-75.315713,40.070511],"type":"Point"}
}