{
  "type": "Feature",
  "properties": {
    "addr:full":"405 Caredean Dr Horsham PA 19044",
    "addr:housenumber":"405",
    "addr:postcode":"19044",
    "addr:street":"Caredean Dr",
    "iso:country":"US",
    "sg:address":"405 Caredean Dr",
    "sg:city":"Horsham",
    "sg:classifiers":[
        {
            "category":"Health Services",
            "subcategory":"Doctor",
            "type":"Services"
        }
    ],
    "sg:phone":"+1 215 441 9710",
    "sg:postcode":"19044",
    "sg:province":"PA",
    "sg:tags":[
        "physician",
        "surgeon",
        "medical"
    ],
    "wof:name":"Horsham Pediatrics",
    "wof:placetype":"venue"
},
  "geometry": {"coordinates":[-75.175471,40.203094],"type":"Point"}
}