{
  "type": "Feature",
  "properties": {
    "addr:full":"103 N Division St Mt Union PA 17066",
    "addr:housenumber":"103",
    "addr:postcode":"17066",
    "addr:street":"N Division St",
    "iso:country":"US",
    "sg:address":"103 N Division St",
    "sg:city":"Mt Union",
    "sg:classifiers":[
        {
            "category":"Health Services",
            "subcategory":"Chiropractor",
            "type":"Services"
        }
    ],
    "sg:phone":"+1 814 542 2752",
    "sg:postcode":"17066",
    "sg:province":"PA",
    "wof:name":"David L Battistella DC",
    "wof:placetype":"venue"
},
  "geometry": {"coordinates":[-77.88191999999999,40.385775],"type":"Point"}
}