{
  "type": "Feature",
  "properties": {
    "iso:country":"US",
    "sg:address":"200 Swinderman Rd",
    "sg:city":"Wexford",
    "sg:classifiers":[
        {
            "category":"Insurance",
            "subcategory":"Insurance Agent",
            "type":"Services"
        },
        {
            "category":"Insurance",
            "subcategory":"Hazard Insurance",
            "type":"Services"
        },
        {
            "category":"Insurance",
            "subcategory":"Title Insurance",
            "type":"Services"
        }
    ],
    "sg:phone":"+1 724 776 6077",
    "sg:postcode":"15090",
    "sg:province":"PA",
    "sg:tags":[
        "property",
        "commercial",
        "casualty",
        "business",
        "homeowner"
    ],
    "wof:name":"Commercial Insurance Associates Inc",
    "wof:placetype":"venue"
},
  "geometry": {"coordinates":[-80.06102,40.638228],"type":"Point"}
}