{
  "type": "Feature",
  "properties": {
    "iso:country":"US",
    "sg:address":"5678 W Ridge Rd",
    "sg:city":"Erie",
    "sg:classifiers":[
        {
            "category":"Professional",
            "subcategory":"Advertising",
            "type":"Services"
        }
    ],
    "sg:phone":"+1 814 838 6471",
    "sg:postcode":"16506",
    "sg:province":"PA",
    "sg:tags":[
        "specialty"
    ],
    "wof:name":"C P S",
    "wof:placetype":"venue"
},
  "geometry": {"coordinates":[-80.204977,42.061482],"type":"Point"}
}