{
  "type": "Feature",
  "properties": {
    "addr:full":"928 W 4th St Williamsport PA 17701",
    "addr:housenumber":"928",
    "addr:postcode":"17701",
    "addr:street":"W 4Th St",
    "iso:country":"US",
    "sg:address":"928 W 4th St",
    "sg:city":"Williamsport",
    "sg:classifiers":[
        {
            "category":"Real Estate",
            "subcategory":"Real Estate Operator",
            "type":"Services"
        }
    ],
    "sg:phone":"+1   ",
    "sg:postcode":"17701",
    "sg:province":"PA",
    "sg:tags":[
        "building",
        "apartment"
    ],
    "wof:name":"Kranz Apts",
    "wof:placetype":"venue"
},
  "geometry": {"coordinates":[-77.02186399999999,41.239692],"type":"Point"}
}