{
  "type": "Feature",
  "properties": {
    "addr:full":"211 W Market St Scranton PA 18508",
    "addr:housenumber":"211",
    "addr:postcode":"18508",
    "addr:street":"W Market St",
    "iso:country":"US",
    "sg:address":"211 W Market St",
    "sg:city":"Scranton",
    "sg:classifiers":[
        {
            "category":"Professional",
            "type":"Services"
        }
    ],
    "sg:phone":"+1 570 342 4429",
    "sg:postcode":"18508",
    "sg:province":"PA",
    "sg:tags":[
        "establishment"
    ],
    "wof:name":"A Lomma Co",
    "wof:placetype":"venue"
},
  "geometry": {"coordinates":[-75.659209,41.439366],"type":"Point"}
}