{
  "type": "Feature",
  "properties": {
    "iso:country":"US",
    "sg:address":"943 Thorne Dr",
    "sg:city":"West Chester",
    "sg:classifiers":[
        {
            "category":"Building & Trades",
            "subcategory":"Construction",
            "type":"Services"
        }
    ],
    "sg:phone":"+1 610 430 7985",
    "sg:postcode":"19382",
    "sg:province":"PA",
    "sg:tags":[
        "designer"
    ],
    "wof:name":"Maraska Artistic Concept-Desgn",
    "wof:placetype":"venue"
},
  "geometry": {"coordinates":[-75.56851399999999,39.945385],"type":"Point"}
}