{
  "type": "Feature",
  "properties": {
    "iso:country":"US",
    "sg:address":"714 Macdade Blvd",
    "sg:city":"Darby",
    "sg:classifiers":[
        {
            "category":"Professional",
            "subcategory":"Credit Reporting & Collection",
            "type":"Services"
        }
    ],
    "sg:phone":"+1 610 461 5555",
    "sg:postcode":"19023",
    "sg:province":"PA",
    "sg:tags":[
        "debt",
        "adjuster"
    ],
    "sg:website":"http://www.laydenadjustment.com",
    "wof:name":"Layden Adjustment Services Inc",
    "wof:placetype":"venue"
},
  "geometry": {"coordinates":[-75.276608,39.91212],"type":"Point"}
}