{
  "type": "Feature",
  "properties": {
    "iso:country":"US",
    "sg:address":"470 N 2nd St",
    "sg:city":"Philadelphia",
    "sg:classifiers":[
        {
            "category":"Professional",
            "subcategory":"Management & Consulting",
            "type":"Services"
        }
    ],
    "sg:phone":"+1 215 592 7000",
    "sg:postcode":"19123",
    "sg:province":"PA",
    "sg:tags":[
        "consultant",
        "educational"
    ],
    "wof:name":"Reads Educational & Counseling",
    "wof:placetype":"venue"
},
  "geometry": {"coordinates":[-75.14194000000001,39.958509],"type":"Point"}
}