{
  "type": "Feature",
  "properties": {
    "iso:country":"US",
    "sg:address":"51 N 13th St",
    "sg:city":"Philadelphia",
    "sg:classifiers":[
        {
            "category":"Recreation",
            "type":"Entertainment"
        },
        {
            "category":"Organizations",
            "subcategory":"Community Association",
            "type":"Services"
        }
    ],
    "sg:phone":"+1 215 569 8988",
    "sg:postcode":"19107",
    "sg:province":"PA",
    "sg:tags":[
        "club",
        "membership"
    ],
    "wof:name":"Goodfellows Dance Club",
    "wof:placetype":"venue"
},
  "geometry": {"coordinates":[-75.160948,39.954042],"type":"Point"}
}