{
  "type": "Feature",
  "properties": {
    "iso:country":"US",
    "sg:address":"538 McDermott Rd",
    "sg:city":"Fawn Grove",
    "sg:classifiers":[
        {
            "category":"Building & Trades",
            "subcategory":"Construction",
            "type":"Services"
        }
    ],
    "sg:phone":"+1   ",
    "sg:postcode":"17321",
    "sg:province":"PA",
    "sg:tags":[
        "excavating"
    ],
    "wof:name":"Fawn View Construction Inc",
    "wof:placetype":"venue"
},
  "geometry": {"coordinates":[-76.422939,39.735029],"type":"Point"}
}