{
  "type": "Feature",
  "properties": {
    "addr:full":"1743 Newport Ave Northampton PA 18067",
    "addr:housenumber":"1743",
    "addr:postcode":"18067",
    "addr:street":"Newport Ave",
    "iso:country":"US",
    "sg:address":"1743 Newport Ave",
    "sg:city":"Northampton",
    "sg:classifiers":[
        {
            "category":"Farming",
            "subcategory":"Orchard",
            "type":"Manufacturing & Wholesale Goods"
        }
    ],
    "sg:phone":"+1   ",
    "sg:postcode":"18067",
    "sg:province":"PA",
    "sg:tags":[
        "fruit",
        "tree"
    ],
    "wof:name":"Wolf Orchards Market",
    "wof:placetype":"venue"
},
  "geometry": {"coordinates":[-75.499796,40.687379],"type":"Point"}
}