{
  "type": "Feature",
  "properties": {
    "iso:country":"US",
    "sg:address":"172 Borowicz Rd",
    "sg:city":"New Wilmington",
    "sg:classifiers":[
        {
            "category":"Shopping",
            "subcategory":"Bicycles & Sporting Goods",
            "type":"Retail Goods"
        }
    ],
    "sg:phone":"+1   ",
    "sg:postcode":"16142",
    "sg:province":"PA",
    "sg:tags":[
        "shop",
        "golf",
        "pro",
        "an",
        "course",
        "hole",
        "operates"
    ],
    "wof:name":"Borland Golf Center Inc",
    "wof:placetype":"venue"
},
  "geometry": {"coordinates":[-80.37195199999999,41.131358],"type":"Point"}
}