{
  "type": "Feature",
  "properties": {
    "iso:country":"US",
    "sg:address":"140 Upper Coleville Rd",
    "sg:city":"Bellefonte",
    "sg:classifiers":[
        {
            "category":"Organizations",
            "subcategory":"Religious Organization",
            "type":"Services"
        }
    ],
    "sg:phone":"+1 814 355 4556",
    "sg:postcode":"16823",
    "sg:province":"PA",
    "sg:tags":[
        "clergy"
    ],
    "wof:name":"Coleville Wesleyan Parsonage",
    "wof:placetype":"venue"
},
  "geometry": {"coordinates":[-77.793755,40.911353],"type":"Point"}
}