{
  "type": "Feature",
  "properties": {
    "addr:full":"553 Carnot Rd Coraopolis PA 15108",
    "addr:housenumber":"553",
    "addr:postcode":"15108",
    "addr:street":"Carnot Rd",
    "iso:country":"US",
    "sg:address":"553 Carnot Rd",
    "sg:city":"Coraopolis",
    "sg:classifiers":[
        {
            "category":"Restaurant",
            "type":"Food & Drink"
        }
    ],
    "sg:phone":"+1 412 262 2272",
    "sg:postcode":"15108",
    "sg:province":"PA",
    "sg:tags":[
        "pizza"
    ],
    "wof:name":"Hometown Pizza",
    "wof:placetype":"venue"
},
  "geometry": {"coordinates":[-80.21977200000001,40.51598],"type":"Point"}
}