{
  "type": "Feature",
  "properties": {
    "iso:country":"US",
    "sg:address":"416 Brentwood Rd",
    "sg:city":"Havertown",
    "sg:classifiers":[
        {
            "category":"Health Services",
            "subcategory":"Doctor",
            "type":"Services"
        }
    ],
    "sg:phone":"+1 610 789 4041",
    "sg:postcode":"19083",
    "sg:province":"PA",
    "sg:tags":[
        "dentist"
    ],
    "wof:name":"Melissa D'Ambrosio DDS",
    "wof:placetype":"venue"
},
  "geometry": {"coordinates":[-75.29221200000001,39.978922],"type":"Point"}
}