{
  "type": "Feature",
  "properties": {
    "iso:country":"US",
    "sg:address":"1845 Fairview Ave",
    "sg:city":"Willow Grove",
    "sg:classifiers":[
        {
            "category":"Wholesale",
            "subcategory":"Auto Parts",
            "type":"Manufacturing & Wholesale Goods"
        }
    ],
    "sg:phone":"+1 215 657 1770",
    "sg:postcode":"19090",
    "sg:province":"PA",
    "sg:tags":[
        "automobile",
        "supply"
    ],
    "wof:name":"Parts For Imports",
    "wof:placetype":"venue"
},
  "geometry": {"coordinates":[-75.11789899999999,40.13889],"type":"Point"}
}