{
  "type": "Feature",
  "properties": {
    "addr:full":"300 King Air Cir Washington PA 15301",
    "addr:housenumber":"300",
    "addr:postcode":"15301",
    "addr:street":"King Air Cir",
    "iso:country":"US",
    "sg:address":"300 King Air Cir",
    "sg:city":"Washington",
    "sg:classifiers":[
        {
            "category":"Building & Trades",
            "subcategory":"Construction",
            "type":"Services"
        }
    ],
    "sg:phone":"+1 724 225 0726",
    "sg:postcode":"15301",
    "sg:province":"PA",
    "sg:tags":[
        "woodworker"
    ],
    "wof:name":"Wooden Dreams",
    "wof:placetype":"venue"
},
  "geometry": {"coordinates":[-80.29436800000001,40.131177],"type":"Point"}
}