{
  "type": "Feature",
  "properties": {
    "iso:country":"US",
    "sg:address":"55 N 2nd St",
    "sg:city":"Doylestown",
    "sg:classifiers":[
        {
            "category":"Government",
            "subcategory":"Office",
            "type":"Public Place"
        }
    ],
    "sg:phone":"+1 215 348 6163",
    "sg:postcode":"18964",
    "sg:province":"PA",
    "sg:website":"www.buckscounty.org",
    "wof:name":"Bucks Cnty Voter Registration",
    "wof:placetype":"venue"
},
  "geometry": {"coordinates":[-75.319934,40.311155],"type":"Point"}
}