{
  "type": "Feature",
  "properties": {
    "iso:country":"US",
    "sg:address":"31 N Main St",
    "sg:city":"Jacobus",
    "sg:classifiers":[
        {
            "category":"Home & Garden",
            "subcategory":"Home Furnishings",
            "type":"Retail Goods"
        },
        {
            "category":"Home & Garden",
            "subcategory":"Furniture",
            "type":"Retail Goods"
        }
    ],
    "sg:phone":"+1 717 428 1922",
    "sg:postcode":"17407",
    "sg:province":"PA",
    "sg:tags":[
        "house",
        "store"
    ],
    "sg:website":"http://www.smithvillage.com",
    "wof:name":"Smith Village Home Furnishings",
    "wof:placetype":"venue"
},
  "geometry": {"coordinates":[-76.710136,39.882149],"type":"Point"}
}