{
  "type": "Feature",
  "properties": {
    "iso:country":"US",
    "sg:address":"890 N Graham St",
    "sg:city":"Allentown",
    "sg:classifiers":[
        {
            "category":"Professional",
            "subcategory":"Testing Lab",
            "type":"Services"
        }
    ],
    "sg:phone":"+1 610 434 9015",
    "sg:postcode":"18109",
    "sg:province":"PA",
    "sg:tags":[
        "laboratory"
    ],
    "wof:name":"American Aquatic Testing Inc",
    "wof:placetype":"venue"
},
  "geometry": {"coordinates":[-75.446755,40.622263],"type":"Point"}
}