{
  "type": "Feature",
  "properties": {
    "iso:country":"US",
    "sg:address":"142 Adams Rd",
    "sg:city":"Breinigsville",
    "sg:classifiers":[
        {
            "category":"Professional",
            "subcategory":"Business Services",
            "type":"Services"
        }
    ],
    "sg:phone":"+1 610 391 0788",
    "sg:postcode":"18031",
    "sg:province":"PA",
    "sg:tags":[
        "interior",
        "consultant",
        "design",
        "decorator"
    ],
    "wof:name":"Home Interiors By Pam Nidlund",
    "wof:placetype":"venue"
},
  "geometry": {"coordinates":[-75.654462,40.558802],"type":"Point"}
}