{
  "type": "Feature",
  "properties": {
    "iso:country":"US",
    "sg:address":"8301 Henry Ave",
    "sg:city":"Philadelphia",
    "sg:classifiers":[
        {
            "category":"Shopping",
            "subcategory":"Clothing, Apparel, & Fashions",
            "type":"Retail Goods"
        }
    ],
    "sg:phone":"+1   ",
    "sg:postcode":"19128",
    "sg:province":"PA",
    "sg:tags":[
        "woman"
    ],
    "wof:name":"Dress Barn 126",
    "wof:placetype":"venue"
},
  "geometry": {"coordinates":[-75.237269,40.062251],"type":"Point"}
}