{
  "type": "Feature",
  "properties": {
    "iso:country":"US",
    "sg:address":"2700 State Rd",
    "sg:city":"Bensalem",
    "sg:classifiers":[
        {
            "category":"Retail",
            "subcategory":"Auto Rental",
            "type":"Services"
        }
    ],
    "sg:phone":"+1 215 633 7678",
    "sg:postcode":"19020",
    "sg:province":"PA",
    "sg:tags":[
        "renting",
        "leasing",
        "trailer"
    ],
    "sg:website":"http://www.premier-us.net",
    "wof:name":"PLM Trailer Leasing",
    "wof:placetype":"venue"
},
  "geometry": {"coordinates":[-74.933087,40.074107],"type":"Point"}
}