{
  "type": "Feature",
  "properties": {
    "iso:country":"US",
    "sg:address":"50 Geigertown Rd",
    "sg:city":"Douglassville",
    "sg:classifiers":[
        {
            "category":"Retail",
            "subcategory":"Repair Shop",
            "type":"Services"
        }
    ],
    "sg:phone":"+1 610 582 1060",
    "sg:postcode":"19518",
    "sg:province":"PA",
    "sg:tags":[
        "repairing",
        "saw"
    ],
    "wof:name":"Dan Kennedy's Chain Saw Shop",
    "wof:placetype":"venue"
},
  "geometry": {"coordinates":[-75.80862999999999,40.224858],"type":"Point"}
}