{
  "type": "Feature",
  "properties": {
    "iso:country":"US",
    "sg:address":"56 Whitetail Ln",
    "sg:city":"Lock Haven",
    "sg:classifiers":[
        {
            "category":"Building & Trades",
            "subcategory":"Construction",
            "type":"Services"
        }
    ],
    "sg:phone":"+1   ",
    "sg:postcode":"17745",
    "sg:province":"PA",
    "sg:tags":[
        "builder",
        "operative"
    ],
    "wof:name":"Steve Herman Building Contr",
    "wof:placetype":"venue"
},
  "geometry": {"coordinates":[-77.41977900000001,41.176753],"type":"Point"}
}