{
  "type": "Feature",
  "properties": {
    "iso:country":"US",
    "sg:address":"1106 Millersville Pike",
    "sg:city":"Lancaster",
    "sg:classifiers":[
        {
            "category":"Restaurant",
            "type":"Food & Drink"
        }
    ],
    "sg:phone":"+1 717 393 1801",
    "sg:postcode":"17603",
    "sg:province":"PA",
    "sg:tags":[
        "banquet",
        "rooms"
    ],
    "sg:website":"www.tasteoflancaster.com",
    "wof:name":"Taste Of Lancaster LLC",
    "wof:placetype":"venue"
},
  "geometry": {"coordinates":[-76.326196,40.027713],"type":"Point"}
}