{
  "type": "Feature",
  "properties": {
    "iso:country":"US",
    "sg:address":"20 Winters Ct",
    "sg:city":"Philadelphia",
    "sg:classifiers":[
        {
            "category":"Education",
            "subcategory":"Library",
            "type":"Public Place"
        }
    ],
    "sg:phone":"+1   ",
    "sg:postcode":"19107",
    "sg:province":"PA",
    "wof:name":"Pedagogical Library",
    "wof:placetype":"venue"
},
  "geometry": {"coordinates":[-75.156744,39.956356],"type":"Point"}
}