{
  "type": "Feature",
  "properties": {
    "iso:country":"US",
    "sg:address":"4820 Old Harrisburg Rd",
    "sg:city":"Gettysburg",
    "sg:classifiers":[
        {
            "category":"Home & Garden",
            "subcategory":"Mobile Homes",
            "type":"Retail Goods"
        }
    ],
    "sg:phone":"+1 717 334 2025",
    "sg:postcode":"17325",
    "sg:province":"PA",
    "sg:tags":[
        "modular"
    ],
    "wof:name":"Quality Homes Inc",
    "wof:placetype":"venue"
},
  "geometry": {"coordinates":[-77.149396,39.944604],"type":"Point"}
}