{
  "type": "Feature",
  "properties": {
    "iso:country":"US",
    "sg:address":"920 Matsonford Rd",
    "sg:city":"Conshohocken",
    "sg:classifiers":[
        {
            "category":"Professional",
            "subcategory":"Accounting & Tax Preparation",
            "type":"Services"
        }
    ],
    "sg:phone":"+1 215 283 2550",
    "sg:postcode":"19428",
    "sg:province":"PA",
    "sg:tags":[
        "payroll"
    ],
    "wof:name":"Professional Payroll Solutions",
    "wof:placetype":"venue"
},
  "geometry": {"coordinates":[-75.32302799999999,40.066615],"type":"Point"}
}