{
  "type": "Feature",
  "properties": {
    "iso:country":"US",
    "sg:address":"652 State St",
    "sg:city":"Beaver",
    "sg:classifiers":[
        {
            "category":"Wholesale",
            "subcategory":"Electrical",
            "type":"Manufacturing & Wholesale Goods"
        },
        {
            "category":"Shopping",
            "subcategory":"Computers & Home Electronics",
            "type":"Retail Goods"
        }
    ],
    "sg:phone":"+1 724 728 8440",
    "sg:postcode":"15009",
    "sg:province":"PA",
    "sg:tags":[
        "sell",
        "communication",
        "radio",
        "system",
        "equipment"
    ],
    "wof:name":"Interstate Communications Elec",
    "wof:placetype":"venue"
},
  "geometry": {"coordinates":[-80.33771400000001,40.680492],"type":"Point"}
}