{
  "type": "Feature",
  "properties": {
    "iso:country":"US",
    "sg:address":"227 New Haven Dr",
    "sg:city":"Lititz",
    "sg:classifiers":[
        {
            "category":"Retail",
            "subcategory":"Repair Shop",
            "type":"Services"
        }
    ],
    "sg:phone":"+1   ",
    "sg:postcode":"17543",
    "sg:province":"PA",
    "sg:tags":[
        "equipment",
        "printing",
        "rebuilds"
    ],
    "wof:name":"Groves Printing Equipment Inc",
    "wof:placetype":"venue"
},
  "geometry": {"coordinates":[-76.296967,40.138278],"type":"Point"}
}