{
  "type": "Feature",
  "properties": {
    "iso:country":"US",
    "sg:address":"3001 Byberry Rd",
    "sg:city":"Philadelphia",
    "sg:classifiers":[
        {
            "category":"Social Services",
            "subcategory":"Child Care",
            "type":"Services"
        }
    ],
    "sg:phone":"+1 215 612 1776",
    "sg:postcode":"19154",
    "sg:province":"PA",
    "sg:website":"www.kinderacademy.com",
    "wof:name":"Kinder Academy Inc",
    "wof:placetype":"venue"
},
  "geometry": {"coordinates":[-74.979698,40.100589],"type":"Point"}
}