{
  "type": "Feature",
  "properties": {
    "addr:full":"1008 W 9th Ave King Of Prussia PA 19406",
    "addr:housenumber":"1008",
    "addr:postcode":"19406",
    "addr:street":"W 9Th Ave",
    "iso:country":"US",
    "sg:address":"1008 W 9th Ave",
    "sg:city":"King Of Prussia",
    "sg:classifiers":[
        {
            "category":"Professional",
            "subcategory":"Testing Lab",
            "type":"Services"
        }
    ],
    "sg:phone":"+1 610 337 9992",
    "sg:postcode":"19406",
    "sg:province":"PA",
    "sg:tags":[
        "environmental"
    ],
    "sg:website":"www.glalab.com",
    "wof:name":"GLA Laboratories",
    "wof:placetype":"venue"
},
  "geometry": {"coordinates":[-75.41477,40.100751],"type":"Point"}
}