{
  "type": "Feature",
  "properties": {
    "iso:country":"US",
    "sg:address":"167 W Lancaster Ave",
    "sg:city":"Ardmore",
    "sg:classifiers":[
        {
            "category":"Personal",
            "subcategory":"Beauty Salon",
            "type":"Services"
        }
    ],
    "sg:phone":"+1   ",
    "sg:postcode":"19003",
    "sg:province":"PA",
    "sg:tags":[
        "shop"
    ],
    "wof:name":"Rose Nail Salon",
    "wof:placetype":"venue"
},
  "geometry": {"coordinates":[-75.29380500000001,40.009299],"type":"Point"}
}