{
  "type": "Feature",
  "properties": {
    "addr:full":"5934 Race St Philadelphia PA 19139",
    "addr:housenumber":"5934",
    "addr:postcode":"19139",
    "addr:street":"Race St",
    "iso:country":"US",
    "sg:address":"5934 Race St",
    "sg:city":"Philadelphia",
    "sg:classifiers":[
        {
            "category":"Food & Beverages",
            "subcategory":"Groceries & Convenience Stores",
            "type":"Retail Goods"
        }
    ],
    "sg:phone":"+1 215 476 2809",
    "sg:postcode":"19139",
    "sg:province":"PA",
    "wof:name":"Market Redfield Mini",
    "wof:placetype":"venue"
},
  "geometry": {"coordinates":[-75.238823,39.96489],"type":"Point"}
}