{
  "type": "Feature",
  "properties": {
    "iso:country":"US",
    "sg:address":"512 Market St",
    "sg:city":"Lewisburg",
    "sg:classifiers":[
        {
            "category":"Personal",
            "subcategory":"Beauty Salon",
            "type":"Services"
        }
    ],
    "sg:phone":"+1 570 524 7710",
    "sg:postcode":"17837",
    "sg:province":"PA",
    "sg:tags":[
        "shop"
    ],
    "wof:name":"A Classic U",
    "wof:placetype":"venue"
},
  "geometry": {"coordinates":[-76.88769499999999,40.962813],"type":"Point"}
}