{
  "type": "Feature",
  "properties": {
    "iso:country":"US",
    "sg:address":"3 Harvey Rd",
    "sg:city":"Wallingford",
    "sg:classifiers":[
        {
            "category":"Building & Trades",
            "subcategory":"Construction",
            "type":"Services"
        }
    ],
    "sg:phone":"+1   ",
    "sg:postcode":"19086",
    "sg:province":"PA",
    "sg:tags":[
        "industrial",
        "nonresidential"
    ],
    "wof:name":"Commercial Building Services",
    "wof:placetype":"venue"
},
  "geometry": {"coordinates":[-75.361935,39.878928],"type":"Point"}
}