{
  "type": "Feature",
  "properties": {
    "iso:country":"US",
    "sg:address":"222 Church St Apt 6E",
    "sg:city":"Philadelphia",
    "sg:classifiers":[
        {
            "category":"Retail",
            "subcategory":"Photofinishing",
            "type":"Services"
        },
        {
            "category":"Retail",
            "subcategory":"Portrait Studio",
            "type":"Services"
        },
        {
            "category":"Professional",
            "subcategory":"Printing & Photocopies",
            "type":"Services"
        }
    ],
    "sg:phone":"+1 215 625 8538",
    "sg:postcode":"19106",
    "sg:province":"PA",
    "sg:tags":[
        "photo",
        "photography",
        "retouching",
        "restoration",
        "photographers-commercial",
        "store"
    ],
    "wof:name":"Powers Lindy Photogrphr",
    "wof:placetype":"venue"
},
  "geometry": {"coordinates":[-75.144699,39.950699],"type":"Point"}
}