{
  "type": "Feature",
  "properties": {
    "iso:country":"US",
    "sg:address":"235 Redington Ave",
    "sg:city":"Troy",
    "sg:classifiers":[
        {
            "category":"Health Services",
            "subcategory":"Chiropractor",
            "type":"Services"
        }
    ],
    "sg:phone":"+1 570 297 2086",
    "sg:postcode":"16947",
    "sg:province":"PA",
    "wof:name":"Granville Chiropractic Ctr",
    "wof:placetype":"venue"
},
  "geometry": {"coordinates":[-76.79209899999999,41.784624],"type":"Point"}
}