{
  "type": "Feature",
  "properties": {
    "addr:full":"1530 Lincoln Rd Lititz PA 17543",
    "addr:housenumber":"1530",
    "addr:postcode":"17543",
    "addr:street":"Lincoln Rd",
    "iso:country":"US",
    "sg:address":"1530 Lincoln Rd",
    "sg:city":"Lititz",
    "sg:classifiers":[
        {
            "category":"Food & Beverages",
            "subcategory":"Meat & Fish",
            "type":"Retail Goods"
        }
    ],
    "sg:phone":"+1   ",
    "sg:postcode":"17543",
    "sg:province":"PA",
    "wof:name":"Custom Butcher Shop",
    "wof:placetype":"venue"
},
  "geometry": {"coordinates":[-76.230496,40.188321],"type":"Point"}
}