{
  "type": "Feature",
  "properties": {
    "iso:country":"US",
    "sg:address":"569 Otter St",
    "sg:city":"Bristol",
    "sg:classifiers":[
        {
            "category":"Building & Trades",
            "subcategory":"Construction",
            "type":"Services"
        }
    ],
    "sg:phone":"+1 215 788 8508",
    "sg:postcode":"19007",
    "sg:province":"PA",
    "sg:tags":[
        "contractor"
    ],
    "wof:name":"Bayard Pump & Tank Co",
    "wof:placetype":"venue"
},
  "geometry": {"coordinates":[-74.86799600000001,40.096802],"type":"Point"}
}