{
  "type": "Feature",
  "properties": {
    "iso:country":"US",
    "sg:address":"524 Forest Ave",
    "sg:city":"Trafford",
    "sg:classifiers":[
        {
            "category":"Personal",
            "subcategory":"Beauty Salon",
            "type":"Services"
        }
    ],
    "sg:phone":"+1 412 373 7558",
    "sg:postcode":"15085",
    "sg:province":"PA",
    "sg:tags":[
        "shop"
    ],
    "wof:name":"Victoria's Hair Design Studio",
    "wof:placetype":"venue"
},
  "geometry": {"coordinates":[-79.757915,40.386481],"type":"Point"}
}