{
  "type": "Feature",
  "properties": {
    "iso:country":"US",
    "sg:address":"106 W State St",
    "sg:city":"Media",
    "sg:classifiers":[
        {
            "category":"Cafe",
            "type":"Food & Drink"
        }
    ],
    "sg:menulink":"http://www.allmenus.com/pa/media/19191-fellini-cafe-media/menu/",
    "sg:phone":"+1 610 892 7616",
    "sg:postcode":"19063",
    "sg:province":"PA",
    "sg:tags":[
        "italian"
    ],
    "wof:name":"Fellini Cafe Media",
    "wof:placetype":"venue"
},
  "geometry": {"coordinates":[-75.391201,39.918185],"type":"Point"}
}