{
  "type": "Feature",
  "properties": {
    "addr:full":"211 2nd St Charleroi PA 15022",
    "addr:housenumber":"211",
    "addr:postcode":"15022",
    "addr:street":"2Nd St",
    "iso:country":"US",
    "sg:address":"211 2nd St",
    "sg:city":"Charleroi",
    "sg:classifiers":[
        {
            "category":"Health Services",
            "subcategory":"Podiatrist",
            "type":"Services"
        }
    ],
    "sg:phone":"+1 724 483 8068",
    "sg:postcode":"15022",
    "sg:province":"PA",
    "wof:name":"Mvpa",
    "wof:placetype":"venue"
},
  "geometry": {"coordinates":[-79.894288,40.135396],"type":"Point"}
}