{
  "type": "Feature",
  "properties": {
    "addr:full":"2251 N Bancroft St Philadelphia PA 19132",
    "addr:housenumber":"2251",
    "addr:postcode":"19132",
    "addr:street":"N Bancroft St",
    "iso:country":"US",
    "sg:address":"2251 N Bancroft St",
    "sg:city":"Philadelphia",
    "sg:classifiers":[
        {
            "category":"Building & Trades",
            "subcategory":"Construction",
            "type":"Services"
        }
    ],
    "sg:phone":"+1 215 235 1148",
    "sg:postcode":"19132",
    "sg:province":"PA",
    "sg:tags":[
        "contractor"
    ],
    "wof:name":"Millenium Enterprises",
    "wof:placetype":"venue"
},
  "geometry": {"coordinates":[-75.15983199999999,39.987586],"type":"Point"}
}