{
  "type": "Feature",
  "properties": {
    "addr:full":"2023 E Carson St Pittsburgh PA 15203",
    "addr:housenumber":"2023",
    "addr:postcode":"15203",
    "addr:street":"E Carson St",
    "iso:country":"US",
    "sg:address":"2023 E Carson St",
    "sg:city":"Pittsburgh",
    "sg:classifiers":[
        {
            "category":"Shopping",
            "subcategory":"Gifts & Souvenirs",
            "type":"Retail Goods"
        }
    ],
    "sg:phone":"+1 412 432 0300",
    "sg:postcode":"15203",
    "sg:province":"PA",
    "sg:tags":[
        "shop"
    ],
    "wof:name":"Gems Of The World",
    "wof:placetype":"venue"
},
  "geometry": {"coordinates":[-79.97655899999999,40.428599],"type":"Point"}
}