{
  "type": "Feature",
  "properties": {
    "iso:country":"US",
    "sg:address":"4565 Prestwick Dr",
    "sg:city":"Reading",
    "sg:classifiers":[
        {
            "category":"Education",
            "subcategory":"Library",
            "type":"Public Place"
        }
    ],
    "sg:phone":"+1   ",
    "sg:postcode":"19606",
    "sg:province":"PA",
    "wof:name":"Exeter Community Library",
    "wof:placetype":"venue"
},
  "geometry": {"coordinates":[-75.86295,40.304189],"type":"Point"}
}