{
  "type": "Feature",
  "properties": {
    "iso:country":"US",
    "sg:address":"1600 Skyline Dr",
    "sg:city":"Pittsburgh",
    "sg:classifiers":[
        {
            "category":"Restaurant",
            "type":"Food & Drink"
        }
    ],
    "sg:phone":"+1   ",
    "sg:postcode":"15227",
    "sg:province":"PA",
    "sg:tags":[
        "eating"
    ],
    "wof:name":"Ocean Star Gourmet",
    "wof:placetype":"venue"
},
  "geometry": {"coordinates":[-79.96407499999999,40.367122],"type":"Point"}
}