{
  "type": "Feature",
  "properties": {
    "iso:country":"US",
    "sg:address":"30 Sunfire Ave",
    "sg:city":"Camp Hill",
    "sg:classifiers":[
        {
            "category":"Building & Trades",
            "subcategory":"Construction",
            "type":"Services"
        }
    ],
    "sg:phone":"+1   ",
    "sg:postcode":"17011",
    "sg:province":"PA",
    "sg:tags":[
        "floor",
        "laying",
        "contractor"
    ],
    "wof:name":"Mike Murphey",
    "wof:placetype":"venue"
},
  "geometry": {"coordinates":[-76.94234899999999,40.263154],"type":"Point"}
}