{
  "type": "Feature",
  "properties": {
    "iso:country":"US",
    "sg:address":"69 S Broad St",
    "sg:city":"Nazareth",
    "sg:classifiers":[
        {
            "category":"Shopping",
            "type":"Retail Goods"
        }
    ],
    "sg:phone":"+1   ",
    "sg:postcode":"18064",
    "sg:province":"PA",
    "sg:tags":[
        "merchandise"
    ],
    "wof:name":"Creative Details",
    "wof:placetype":"venue"
},
  "geometry": {"coordinates":[-75.309425,40.741172],"type":"Point"}
}