{
  "type": "Feature",
  "properties": {
    "iso:country":"US",
    "sg:address":"1359 Allentown Rd",
    "sg:city":"Quakertown",
    "sg:classifiers":[
        {
            "category":"Wholesale",
            "subcategory":"Non-durable Goods",
            "type":"Manufacturing & Wholesale Goods"
        }
    ],
    "sg:phone":"+1 215 538 2023",
    "sg:postcode":"18951",
    "sg:province":"PA",
    "wof:name":"Meridian Industries Inc",
    "wof:placetype":"venue"
},
  "geometry": {"coordinates":[-75.37767599999999,40.401505],"type":"Point"}
}