{
  "type": "Feature",
  "properties": {
    "addr:full":"320 Broadway St Meyersdale PA 15552",
    "addr:housenumber":"320",
    "addr:postcode":"15552",
    "addr:street":"Broadway St",
    "iso:country":"US",
    "sg:address":"320 Broadway St",
    "sg:city":"Meyersdale",
    "sg:classifiers":[
        {
            "category":"Shopping",
            "type":"Retail Goods"
        }
    ],
    "sg:phone":"+1 814 634 5618",
    "sg:postcode":"15552",
    "sg:province":"PA",
    "sg:tags":[
        "plastic"
    ],
    "wof:name":"Shultz Plastics",
    "wof:placetype":"venue"
},
  "geometry": {"coordinates":[-79.02459899999999,39.817463],"type":"Point"}
}