{
  "type": "Feature",
  "properties": {
    "iso:country":"US",
    "sg:address":"45 Alliance Rd",
    "sg:city":"Clearfield",
    "sg:classifiers":[
        {
            "category":"Organizations",
            "subcategory":"Religious Organization",
            "type":"Services"
        }
    ],
    "sg:phone":"+1   ",
    "sg:postcode":"16830",
    "sg:province":"PA",
    "wof:name":"Christian Mssnary Alnce Church",
    "wof:placetype":"venue"
},
  "geometry": {"coordinates":[-78.410644,41.029572],"type":"Point"}
}