{
  "type": "Feature",
  "properties": {
    "addr:full":"155 Victoria Pl Davidsville PA 15928",
    "addr:housenumber":"155",
    "addr:postcode":"15928",
    "addr:street":"Victoria Pl",
    "iso:country":"US",
    "sg:address":"155 Victoria Pl",
    "sg:city":"Davidsville",
    "sg:classifiers":[
        {
            "category":"Structure",
            "subcategory":"Office Building",
            "type":"Public Place"
        }
    ],
    "sg:phone":"+1 814 479 5361",
    "sg:postcode":"15928",
    "sg:province":"PA",
    "sg:tags":[
        "park"
    ],
    "wof:name":"Amy Properties Inc",
    "wof:placetype":"venue"
},
  "geometry": {"coordinates":[-78.914749,40.247619],"type":"Point"}
}