{
  "type": "Feature",
  "properties": {
    "addr:full":"10 E Harrison St Tunkhannock PA 18657",
    "addr:housenumber":"10",
    "addr:postcode":"18657",
    "addr:street":"E Harrison St",
    "iso:country":"US",
    "sg:address":"10 E Harrison St",
    "sg:city":"Tunkhannock",
    "sg:classifiers":[
        {
            "category":"Building & Trades",
            "subcategory":"Construction",
            "type":"Services"
        }
    ],
    "sg:phone":"+1   ",
    "sg:postcode":"18657",
    "sg:province":"PA",
    "sg:tags":[
        "house"
    ],
    "wof:name":"Rail Construction Inc",
    "wof:placetype":"venue"
},
  "geometry": {"coordinates":[-75.946332,41.540594],"type":"Point"}
}