{
  "type": "Feature",
  "properties": {
    "iso:country":"US",
    "sg:address":"7837 Germantown Ave",
    "sg:city":"Philadelphia",
    "sg:classifiers":[
        {
            "category":"Shopping",
            "subcategory":"Bicycles & Sporting Goods",
            "type":"Retail Goods"
        }
    ],
    "sg:phone":"+1 215 248 2829",
    "sg:postcode":"19118",
    "sg:province":"PA",
    "sg:website":"www.wiss-cycles.com",
    "wof:name":"Wissahickon Cyclery Inc",
    "wof:placetype":"venue"
},
  "geometry": {"coordinates":[-75.199388,40.069246],"type":"Point"}
}