{
  "type": "Feature",
  "properties": {
    "iso:country":"US",
    "sg:address":"7022 Frankford Ave",
    "sg:city":"Philadelphia",
    "sg:classifiers":[
        {
            "category":"Restaurant",
            "type":"Food & Drink"
        }
    ],
    "sg:phone":"+1 215 333 2656",
    "sg:postcode":"19135",
    "sg:province":"PA",
    "sg:tags":[
        "out"
    ],
    "wof:name":"Golden Wok",
    "wof:placetype":"venue"
},
  "geometry": {"coordinates":[-75.04638199999999,40.033868],"type":"Point"}
}