{
  "type": "Feature",
  "properties": {
    "addr:full":"655 Rosalind Run Morrisville PA 19067",
    "addr:housenumber":"655",
    "addr:postcode":"19067",
    "addr:street":"Rosalind Run",
    "iso:country":"US",
    "sg:address":"655 Rosalind Run",
    "sg:city":"Morrisville",
    "sg:classifiers":[
        {
            "category":"Professional",
            "type":"Services"
        }
    ],
    "sg:phone":"+1   ",
    "sg:postcode":"19067",
    "sg:province":"PA",
    "wof:name":"Bernard L Hirsh Inc",
    "wof:placetype":"venue"
},
  "geometry": {"coordinates":[-74.86370599999999,40.221643],"type":"Point"}
}