{
  "type": "Feature",
  "properties": {
    "iso:country":"US",
    "sg:address":"1005 Tule St",
    "sg:city":"Montoursville",
    "sg:classifiers":[
        {
            "category":"Health Services",
            "subcategory":"Nursing And Care Facility",
            "type":"Services"
        },
        {
            "category":"Health Services",
            "subcategory":"Health Practitioner",
            "type":"Services"
        }
    ],
    "sg:phone":"+1 570 368 8718",
    "sg:postcode":"17754",
    "sg:province":"PA",
    "sg:tags":[
        "home",
        "physician",
        "nurse",
        "eldercare-home",
        "assistant"
    ],
    "wof:name":"Richard W Wurster Mrs Rn",
    "wof:placetype":"venue"
},
  "geometry": {"coordinates":[-76.911179,41.258993],"type":"Point"}
}