{
  "type": "Feature",
  "properties": {
    "iso:country":"US",
    "sg:address":"1255 Montgomery Ave",
    "sg:city":"New Berlinville",
    "sg:classifiers":[
        {
            "category":"Food & Beverages",
            "subcategory":"Groceries & Convenience Stores",
            "type":"Retail Goods"
        }
    ],
    "sg:phone":"+1 610 473 0901",
    "sg:postcode":"19512",
    "sg:province":"PA",
    "wof:name":"Cumberland Farms",
    "wof:placetype":"venue"
},
  "geometry": {"coordinates":[-75.626783,40.344283],"type":"Point"}
}