{
  "type": "Feature",
  "properties": {
    "iso:country":"US",
    "sg:address":"515 Austin St",
    "sg:city":"Greensburg",
    "sg:classifiers":[
        {
            "category":"Shopping",
            "subcategory":"Catalog Store",
            "type":"Retail Goods"
        }
    ],
    "sg:phone":"+1   ",
    "sg:postcode":"15601",
    "sg:province":"PA",
    "sg:tags":[
        "mail",
        "order",
        "doll"
    ],
    "wof:name":"Chapel Hill Collection",
    "wof:placetype":"venue"
},
  "geometry": {"coordinates":[-79.57590399999999,40.282975],"type":"Point"}
}