{
  "type": "Feature",
  "properties": {
    "iso:country":"US",
    "sg:address":"539 Yellow Hill Rd",
    "sg:city":"Narvon",
    "sg:classifiers":[
        {
            "category":"Building & Trades",
            "subcategory":"Construction",
            "type":"Services"
        }
    ],
    "sg:phone":"+1   ",
    "sg:postcode":"17555",
    "sg:province":"PA",
    "sg:tags":[
        "house"
    ],
    "wof:name":"Integrity Cnstr & Remodel",
    "wof:placetype":"venue"
},
  "geometry": {"coordinates":[-75.973422,40.194703],"type":"Point"}
}