{
  "type": "Feature",
  "properties": {
    "addr:full":"214 Laurel St Barnesboro PA 15714",
    "addr:housenumber":"214",
    "addr:postcode":"15714",
    "addr:street":"Laurel St",
    "iso:country":"US",
    "sg:address":"214 Laurel St",
    "sg:city":"Barnesboro",
    "sg:classifiers":[
        {
            "category":"Personal",
            "subcategory":"Beauty Salon",
            "type":"Services"
        }
    ],
    "sg:phone":"+1   ",
    "sg:postcode":"15714",
    "sg:province":"PA",
    "sg:tags":[
        "shop"
    ],
    "wof:name":"Styling Station",
    "wof:placetype":"venue"
},
  "geometry": {"coordinates":[-78.78643599999999,40.669123],"type":"Point"}
}