{
  "type": "Feature",
  "properties": {
    "iso:country":"US",
    "sg:address":"3025 Ashlyn St",
    "sg:city":"Pittsburgh",
    "sg:classifiers":[
        {
            "category":"Retail",
            "subcategory":"Repair Shop",
            "type":"Services"
        }
    ],
    "sg:phone":"+1   ",
    "sg:postcode":"15204",
    "sg:province":"PA",
    "sg:tags":[
        "painting",
        "cleaning"
    ],
    "wof:name":"Lynns Cindy Office & APT Maint",
    "wof:placetype":"venue"
},
  "geometry": {"coordinates":[-80.056316,40.455646],"type":"Point"}
}