{
  "type": "Feature",
  "properties": {
    "iso:country":"US",
    "sg:address":"321 Borbeck Ave",
    "sg:city":"Philadelphia",
    "sg:classifiers":[
        {
            "category":"Professional",
            "subcategory":"Computer Services",
            "type":"Services"
        }
    ],
    "sg:phone":"+1   ",
    "sg:postcode":"19111",
    "sg:province":"PA",
    "sg:tags":[
        "hardware",
        "sales"
    ],
    "wof:name":"Melrom",
    "wof:placetype":"venue"
},
  "geometry": {"coordinates":[-75.08674600000001,40.075173],"type":"Point"}
}