{
  "type": "Feature",
  "properties": {
    "iso:country":"US",
    "sg:address":"1140 N Wales Rd",
    "sg:city":"North Wales",
    "sg:classifiers":[
        {
            "category":"Professional",
            "type":"Services"
        }
    ],
    "sg:phone":"+1 215 631 1400",
    "sg:postcode":"19454",
    "sg:province":"PA",
    "sg:tags":[
        "establishment"
    ],
    "sg:website":"www.talltowers.com",
    "wof:name":"Stainless Inc",
    "wof:placetype":"venue"
},
  "geometry": {"coordinates":[-75.272502,40.219812],"type":"Point"}
}