{
  "type": "Feature",
  "properties": {
    "iso:country":"US",
    "sg:address":"504 Bissetts Ln",
    "sg:city":"Bloomsburg",
    "sg:classifiers":[
        {
            "category":"Home & Garden",
            "subcategory":"Furniture",
            "type":"Retail Goods"
        }
    ],
    "sg:phone":"+1 570 784 8830",
    "sg:postcode":"17815",
    "sg:province":"PA",
    "wof:name":"Statewide Furniture Gallery",
    "wof:placetype":"venue"
},
  "geometry": {"coordinates":[-76.38988500000001,41.025808],"type":"Point"}
}