{
  "type": "Feature",
  "properties": {
    "iso:country":"US",
    "sg:address":"893 Stoystown Rd",
    "sg:city":"Somerset",
    "sg:classifiers":[
        {
            "category":"Home & Garden",
            "subcategory":"Building Materials",
            "type":"Retail Goods"
        }
    ],
    "sg:phone":"+1 814 445 6528",
    "sg:postcode":"15501",
    "sg:province":"PA",
    "wof:name":"84 Lumber Co",
    "wof:placetype":"venue"
},
  "geometry": {"coordinates":[-79.048963,40.02732],"type":"Point"}
}