{
  "type": "Feature",
  "properties": {
    "addr:full":"401 E Louther St Carlisle PA 17013",
    "addr:housenumber":"401",
    "addr:postcode":"17013",
    "addr:street":"E Louther St",
    "iso:country":"US",
    "sg:address":"401 E Louther St",
    "sg:city":"Carlisle",
    "sg:classifiers":[
        {
            "category":"Organizations",
            "subcategory":"Non-profit Organization",
            "type":"Services"
        }
    ],
    "sg:phone":"+1 717 249 5010",
    "sg:postcode":"17013",
    "sg:province":"PA",
    "sg:tags":[
        "information",
        "alcoholism",
        "treatment"
    ],
    "wof:name":"Roxbury",
    "wof:placetype":"venue"
},
  "geometry": {"coordinates":[-77.17739400000001,40.203641],"type":"Point"}
}