{
  "type": "Feature",
  "properties": {
    "iso:country":"US",
    "sg:address":"1452 W Allen St",
    "sg:city":"Allentown",
    "sg:classifiers":[
        {
            "category":"Building & Trades",
            "subcategory":"Construction",
            "type":"Services"
        }
    ],
    "sg:phone":"+1   ",
    "sg:postcode":"18102",
    "sg:province":"PA",
    "sg:tags":[
        "roofing",
        "siding",
        "aluminum",
        "contractor"
    ],
    "wof:name":"Whitaker Window & Door Co",
    "wof:placetype":"venue"
},
  "geometry": {"coordinates":[-75.491085,40.606254],"type":"Point"}
}