{
  "type": "Feature",
  "properties": {
    "iso:country":"US",
    "sg:address":"445 Walnut St",
    "sg:city":"York",
    "sg:classifiers":[
        {
            "category":"Shopping",
            "type":"Retail Goods"
        }
    ],
    "sg:phone":"+1 717 718 4112",
    "sg:postcode":"17403",
    "sg:province":"PA",
    "sg:tags":[
        "cosmetic",
        "perfume"
    ],
    "wof:name":"Mary Kay Cosmetics",
    "wof:placetype":"venue"
},
  "geometry": {"coordinates":[-76.719824,39.967669],"type":"Point"}
}