{
  "type": "Feature",
  "properties": {
    "iso:country":"US",
    "sg:address":"1515 Locust St",
    "sg:city":"Philadelphia",
    "sg:classifiers":[
        {
            "category":"Professional",
            "subcategory":"Lawyer & Legal Services",
            "type":"Services"
        }
    ],
    "sg:phone":"+1 215 546 6811",
    "sg:postcode":"19102",
    "sg:province":"PA",
    "wof:name":"Paul & Miller PC Atty",
    "wof:placetype":"venue"
},
  "geometry": {"coordinates":[-75.166901,39.948502],"type":"Point"}
}