{
  "type": "Feature",
  "properties": {
    "iso:country":"US",
    "sg:address":"902 N Broad St",
    "sg:city":"Lansdale",
    "sg:classifiers":[
        {
            "category":"Health Services",
            "subcategory":"Doctor",
            "type":"Services"
        }
    ],
    "sg:phone":"+1 215 368 1950",
    "sg:postcode":"19446",
    "sg:province":"PA",
    "wof:name":"Heuchert Christine Msn Crnp",
    "wof:placetype":"venue"
},
  "geometry": {"coordinates":[-75.276802,40.248402],"type":"Point"}
}