{
  "type": "Feature",
  "properties": {
    "iso:country":"US",
    "sg:address":"5854 Forbes Ave",
    "sg:city":"Pittsburgh",
    "sg:classifiers":[
        {
            "category":"Professional",
            "type":"Services"
        }
    ],
    "sg:phone":"+1 412 421 0474",
    "sg:postcode":"15217",
    "sg:province":"PA",
    "sg:tags":[
        "establishment"
    ],
    "wof:name":"Sunroth Inc",
    "wof:placetype":"venue"
},
  "geometry": {"coordinates":[-79.921053,40.437972],"type":"Point"}
}