{
  "type": "Feature",
  "properties": {
    "addr:full":"5420 Darlington Rd Pittsburgh PA 15217",
    "addr:housenumber":"5420",
    "addr:postcode":"15217",
    "addr:street":"Darlington Rd",
    "iso:country":"US",
    "sg:address":"5420 Darlington Rd",
    "sg:city":"Pittsburgh",
    "sg:classifiers":[
        {
            "category":"Health Services",
            "subcategory":"Doctor",
            "type":"Services"
        }
    ],
    "sg:phone":"+1   ",
    "sg:postcode":"15217",
    "sg:province":"PA",
    "sg:tags":[
        "medical"
    ],
    "wof:name":"Cyril H Wecht MD",
    "wof:placetype":"venue"
},
  "geometry": {"coordinates":[-79.931304,40.436383],"type":"Point"}
}