{
  "type": "Feature",
  "properties": {
    "addr:full":"2319 E Buck Rd Pennsburg PA 18073",
    "addr:housenumber":"2319",
    "addr:postcode":"18073",
    "addr:street":"E Buck Rd",
    "iso:country":"US",
    "sg:address":"2319 E Buck Rd",
    "sg:city":"Pennsburg",
    "sg:classifiers":[
        {
            "category":"Building & Trades",
            "subcategory":"Landscaping Services",
            "type":"Services"
        }
    ],
    "sg:phone":"+1   ",
    "sg:postcode":"18073",
    "sg:province":"PA",
    "wof:name":"Paragon Landscaping",
    "wof:placetype":"venue"
},
  "geometry": {"coordinates":[-75.483321,40.398616],"type":"Point"}
}