{
  "type": "Feature",
  "properties": {
    "addr:full":"2486 Markleton School Rd Rockwood PA 15557",
    "addr:housenumber":"2486",
    "addr:postcode":"15557",
    "addr:street":"Markleton School Rd",
    "iso:country":"US",
    "sg:address":"2486 Markleton School Rd",
    "sg:city":"Rockwood",
    "sg:classifiers":[
        {
            "category":"Retail",
            "subcategory":"Animal Services",
            "type":"Services"
        }
    ],
    "sg:phone":"+1   ",
    "sg:postcode":"15557",
    "sg:province":"PA",
    "wof:name":"Kristens K-9 Kreations",
    "wof:placetype":"venue"
},
  "geometry": {"coordinates":[-79.17623399999999,39.89496],"type":"Point"}
}