{
  "type": "Feature",
  "properties": {
    "iso:country":"US",
    "sg:address":"2502 E 3rd St",
    "sg:city":"Williamsport",
    "sg:classifiers":[
        {
            "category":"Restaurant",
            "type":"Food & Drink"
        }
    ],
    "sg:phone":"+1   ",
    "sg:postcode":"17701",
    "sg:province":"PA",
    "sg:tags":[
        "mexican"
    ],
    "wof:name":"CHI-Chis",
    "wof:placetype":"venue"
},
  "geometry": {"coordinates":[-76.95241300000001,41.247117],"type":"Point"}
}