{
  "type": "Feature",
  "properties": {
    "addr:full":"600 Weaver Rd Elliottsburg PA 17061",
    "addr:housenumber":"600",
    "addr:postcode":"17061",
    "addr:street":"Weaver Rd",
    "iso:country":"US",
    "sg:address":"600 Weaver Rd",
    "sg:city":"Elliottsburg",
    "sg:classifiers":[
        {
            "category":"Education",
            "subcategory":"School",
            "type":"Public Place"
        }
    ],
    "sg:phone":"+1 717 789 4263",
    "sg:postcode":"17061",
    "sg:province":"PA",
    "wof:name":"West Perry School Dist",
    "wof:placetype":"venue"
},
  "geometry": {"coordinates":[-76.873403,40.591359],"type":"Point"}
}