{
  "type": "Feature",
  "properties": {
    "iso:country":"US",
    "sg:address":"550 Hexenkoph Rd",
    "sg:city":"Hellertown",
    "sg:classifiers":[
        {
            "category":"Building & Trades",
            "subcategory":"Construction",
            "type":"Services"
        }
    ],
    "sg:phone":"+1   ",
    "sg:postcode":"18055",
    "sg:province":"PA",
    "sg:tags":[
        "roofing",
        "siding",
        "contractor"
    ],
    "wof:name":"Glenn Zimpfer Roofing & Siding",
    "wof:placetype":"venue"
},
  "geometry": {"coordinates":[-75.25566999999999,40.606392],"type":"Point"}
}