{
  "type": "Feature",
  "properties": {
    "iso:country":"US",
    "sg:address":"1548 S 16th St",
    "sg:city":"Philadelphia",
    "sg:classifiers":[
        {
            "category":"Real Estate",
            "subcategory":"Real Estate Operator",
            "type":"Services"
        }
    ],
    "sg:phone":"+1 215 462 2235",
    "sg:postcode":"19146",
    "sg:province":"PA",
    "sg:tags":[
        "apartment"
    ],
    "wof:name":"Tasker Village Apartments",
    "wof:placetype":"venue"
},
  "geometry": {"coordinates":[-75.1716,39.931509],"type":"Point"}
}