{
  "type": "Feature",
  "properties": {
    "addr:full":"100 55th St Pittsburgh PA 15201",
    "addr:housenumber":"100",
    "addr:postcode":"15201",
    "addr:street":"55Th St",
    "iso:country":"US",
    "sg:address":"100 55th St",
    "sg:city":"Pittsburgh",
    "sg:classifiers":[
        {
            "category":"Retail",
            "subcategory":"Auto Repair",
            "type":"Services"
        }
    ],
    "sg:phone":"+1   ",
    "sg:postcode":"15201",
    "sg:province":"PA",
    "sg:tags":[
        "general"
    ],
    "wof:name":"A K S Inc",
    "wof:placetype":"venue"
},
  "geometry": {"coordinates":[-79.950531,40.483981],"type":"Point"}
}