{
  "type": "Feature",
  "properties": {
    "iso:country":"US",
    "sg:address":"1243 W Tioga St",
    "sg:city":"Philadelphia",
    "sg:classifiers":[
        {
            "category":"Travel",
            "subcategory":"Bed & Breakfast",
            "type":"Entertainment"
        }
    ],
    "sg:phone":"+1 215 228 9591",
    "sg:postcode":"19140",
    "sg:province":"PA",
    "sg:tags":[
        "house"
    ],
    "wof:name":"Scoggins Boarding Home",
    "wof:placetype":"venue"
},
  "geometry": {"coordinates":[-75.14924499999999,40.00588],"type":"Point"}
}