{
  "type": "Feature",
  "properties": {
    "iso:country":"US",
    "sg:address":"5 Radnor Corporate Center",
    "sg:city":"Wayne",
    "sg:classifiers":[
        {
            "category":"Banks & Credit Unions",
            "subcategory":"Bank",
            "type":"Services"
        }
    ],
    "sg:phone":"+1 610 971 2065",
    "sg:postcode":"19087",
    "sg:province":"PA",
    "wof:name":"Silicon Valley Bank",
    "wof:placetype":"venue"
},
  "geometry": {"coordinates":[-75.36229299999999,40.049658],"type":"Point"}
}