{
  "type": "Feature",
  "properties": {
    "iso:country":"US",
    "sg:address":"38 E Penn St",
    "sg:city":"Philadelphia",
    "sg:classifiers":[
        {
            "category":"Retail",
            "subcategory":"Storage",
            "type":"Services"
        }
    ],
    "sg:phone":"+1 215 849 0720",
    "sg:postcode":"19144",
    "sg:province":"PA",
    "sg:tags":[
        "self"
    ],
    "wof:name":"Penn Street Craftsperson's Associates",
    "wof:placetype":"venue"
},
  "geometry": {"coordinates":[-75.168188,40.033286],"type":"Point"}
}