{
  "type": "Feature",
  "properties": {
    "iso:country":"US",
    "sg:address":"943 N 24th St",
    "sg:city":"Allentown",
    "sg:classifiers":[
        {
            "category":"Professional",
            "subcategory":"Advertising",
            "type":"Services"
        }
    ],
    "sg:phone":"+1   ",
    "sg:postcode":"18104",
    "sg:province":"PA",
    "sg:tags":[
        "mail",
        "direct"
    ],
    "wof:name":"Custom Designed Mailing Labels",
    "wof:placetype":"venue"
},
  "geometry": {"coordinates":[-75.51366899999999,40.606891],"type":"Point"}
}