{
  "type": "Feature",
  "properties": {
    "iso:country":"US",
    "sg:address":"201 S Pittsburgh St",
    "sg:city":"Connellsville",
    "sg:classifiers":[
        {
            "category":"Health Services",
            "subcategory":"Health Practitioner",
            "type":"Services"
        }
    ],
    "sg:phone":"+1 724 626 2958",
    "sg:postcode":"15425",
    "sg:province":"PA",
    "sg:tags":[
        "therapist",
        "physical"
    ],
    "wof:name":"Barclay Rehab Ctr",
    "wof:placetype":"venue"
},
  "geometry": {"coordinates":[-79.58901,40.016639],"type":"Point"}
}