{
  "type": "Feature",
  "properties": {
    "iso:country":"US",
    "sg:address":"1112 Ligonier St",
    "sg:city":"Latrobe",
    "sg:classifiers":[
        {
            "category":"Education",
            "subcategory":"Library",
            "type":"Public Place"
        }
    ],
    "sg:phone":"+1 724 539 1972",
    "sg:postcode":"15650",
    "sg:province":"PA",
    "sg:website":"www.adamslib.org",
    "wof:name":"Adams Memorial Library",
    "wof:placetype":"venue"
},
  "geometry": {"coordinates":[-79.38307,40.315292],"type":"Point"}
}