{
  "type": "Feature",
  "properties": {
    "iso:country":"US",
    "sg:address":"350 N Main St",
    "sg:city":"Butler",
    "sg:classifiers":[
        {
            "category":"Real Estate",
            "subcategory":"Real Estate Agent",
            "type":"Services"
        }
    ],
    "sg:phone":"+1 724 283 1216",
    "sg:postcode":"16001",
    "sg:province":"PA",
    "wof:name":"Home Realty Co Insurance",
    "wof:placetype":"venue"
},
  "geometry": {"coordinates":[-79.895239,40.864493],"type":"Point"}
}