{
  "type": "Feature",
  "properties": {
    "iso:country":"US",
    "sg:address":"104 S Main St",
    "sg:city":"Pittston",
    "sg:classifiers":[
        {
            "category":"Building & Trades",
            "subcategory":"Construction",
            "type":"Services"
        }
    ],
    "sg:phone":"+1 570 655 7155",
    "sg:postcode":"18640",
    "sg:province":"PA",
    "sg:tags":[
        "mobile",
        "home"
    ],
    "wof:name":"Complete MHPS Inc",
    "wof:placetype":"venue"
},
  "geometry": {"coordinates":[-75.792035,41.320223],"type":"Point"}
}