{
  "type": "Feature",
  "properties": {
    "iso:country":"US",
    "sg:address":"605 Plaza Dr",
    "sg:city":"Annville",
    "sg:phone":"+1   ",
    "sg:postcode":"17003",
    "sg:province":"PA",
    "sg:tags":[
        "farm",
        "corn",
        "wheat",
        "soybean"
    ],
    "wof:name":"Ledmond Valley Farms",
    "wof:placetype":"venue"
},
  "geometry": {"coordinates":[-76.566227,40.308277],"type":"Point"}
}