{
  "type": "Feature",
  "properties": {
    "iso:country":"US",
    "sg:address":"202 Hickory Rd",
    "sg:city":"Bear Creek Twp",
    "sg:classifiers":[
        {
            "category":"Building & Trades",
            "subcategory":"Construction",
            "type":"Services"
        }
    ],
    "sg:phone":"+1 570 472 0360",
    "sg:postcode":"18702",
    "sg:province":"PA",
    "sg:tags":[
        "general",
        "contractor"
    ],
    "wof:name":"Sennett Enterprises",
    "wof:placetype":"venue"
},
  "geometry": {"coordinates":[-75.790459,41.19618],"type":"Point"}
}