{
  "type": "Feature",
  "properties": {
    "iso:country":"US",
    "sg:address":"315 Main St",
    "sg:city":"Stroudsburg",
    "sg:classifiers":[
        {
            "category":"Shopping",
            "type":"Retail Goods"
        }
    ],
    "sg:phone":"+1   ",
    "sg:postcode":"18360",
    "sg:province":"PA",
    "sg:tags":[
        "farm",
        "pet",
        "lawn",
        "garden",
        "supply"
    ],
    "wof:name":"Canfields Pet & Farm",
    "wof:placetype":"venue"
},
  "geometry": {"coordinates":[-75.18890399999999,40.988593],"type":"Point"}
}