{
  "type": "Feature",
  "properties": {
    "addr:full":"410 E 4th St Bethlehem PA 18015",
    "addr:housenumber":"410",
    "addr:postcode":"18015",
    "addr:street":"E 4Th St",
    "iso:country":"US",
    "sg:address":"410 E 4th St",
    "sg:city":"Bethlehem",
    "sg:classifiers":[
        {
            "category":"Personal",
            "subcategory":"Beauty Salon",
            "type":"Services"
        }
    ],
    "sg:phone":"+1 610 868 0284",
    "sg:postcode":"18015",
    "sg:province":"PA",
    "wof:name":"Butterfly Beauty Supplys",
    "wof:placetype":"venue"
},
  "geometry": {"coordinates":[-75.37198600000001,40.610533],"type":"Point"}
}