{
  "type": "Feature",
  "properties": {
    "iso:country":"US",
    "sg:address":"1351 S Side Ave",
    "sg:city":"Pittsburgh",
    "sg:classifiers":[
        {
            "category":"Organizations",
            "subcategory":"Membership Organization",
            "type":"Services"
        },
        {
            "category":"Organizations",
            "subcategory":"Professional Association",
            "type":"Services"
        }
    ],
    "sg:phone":"+1 412 322 7822",
    "sg:postcode":"15212",
    "sg:province":"PA",
    "wof:name":"Spring View Athletic Assoc",
    "wof:placetype":"venue"
},
  "geometry": {"coordinates":[-79.993273,40.470484],"type":"Point"}
}