{
  "type": "Feature",
  "properties": {
    "iso:country":"US",
    "sg:address":"465 Valley Rd",
    "sg:city":"Coatesville",
    "sg:classifiers":[
        {
            "category":"Building & Trades",
            "subcategory":"Construction",
            "type":"Services"
        }
    ],
    "sg:phone":"+1   ",
    "sg:postcode":"19320",
    "sg:province":"PA",
    "sg:tags":[
        "contracting",
        "electrical"
    ],
    "wof:name":"Hardwired LLC",
    "wof:placetype":"venue"
},
  "geometry": {"coordinates":[-75.834541,39.97692],"type":"Point"}
}