{
  "type": "Feature",
  "properties": {
    "iso:country":"US",
    "sg:address":"107 Concord St",
    "sg:city":"Union City",
    "sg:classifiers":[
        {
            "category":"Education",
            "subcategory":"School",
            "type":"Public Place"
        }
    ],
    "sg:phone":"+1 814 438 3804",
    "sg:postcode":"16438",
    "sg:province":"PA",
    "sg:tags":[
        "district"
    ],
    "wof:name":"Union City Area Schools Adm",
    "wof:placetype":"venue"
},
  "geometry": {"coordinates":[-79.840321,41.893067],"type":"Point"}
}