{
  "type": "Feature",
  "properties": {
    "addr:full":"36 Walnut St Marcus Hook PA 19061",
    "addr:housenumber":"36",
    "addr:postcode":"19061",
    "addr:street":"Walnut St",
    "iso:country":"US",
    "sg:address":"36 Walnut St",
    "sg:city":"Marcus Hook",
    "sg:classifiers":[
        {
            "category":"Arts & Performance",
            "subcategory":"Theater",
            "type":"Entertainment"
        }
    ],
    "sg:phone":"+1 610 494 2204",
    "sg:postcode":"19061",
    "sg:province":"PA",
    "sg:tags":[
        "live",
        "music"
    ],
    "wof:name":"Dual Sound Disc Jockeys",
    "wof:placetype":"venue"
},
  "geometry": {"coordinates":[-75.41196600000001,39.823845],"type":"Point"}
}