{
  "type": "Feature",
  "properties": {
    "iso:country":"US",
    "sg:address":"2323 Amber St",
    "sg:city":"Philadelphia",
    "sg:classifiers":[
        {
            "category":"Retail",
            "subcategory":"Auto Repair",
            "type":"Services"
        }
    ],
    "sg:phone":"+1 215 634 9079",
    "sg:postcode":"19125",
    "sg:province":"PA",
    "sg:tags":[
        "repairing",
        "automobile"
    ],
    "wof:name":"Tom Remick Auto Repair",
    "wof:placetype":"venue"
},
  "geometry": {"coordinates":[-75.128998,39.9823],"type":"Point"}
}