{
  "type": "Feature",
  "properties": {
    "addr:full":"180 Conarroe St Philadelphia PA 19127",
    "addr:housenumber":"180",
    "addr:postcode":"19127",
    "addr:street":"Conarroe St",
    "iso:country":"US",
    "sg:address":"180 Conarroe St",
    "sg:city":"Philadelphia",
    "sg:classifiers":[
        {
            "category":"Organizations",
            "subcategory":"Religious Organization",
            "type":"Services"
        }
    ],
    "sg:phone":"+1 215 232 4931",
    "sg:postcode":"19127",
    "sg:province":"PA",
    "sg:tags":[
        "church"
    ],
    "wof:name":"St Mary Of The Assumption",
    "wof:placetype":"venue"
},
  "geometry": {"coordinates":[-75.223095,40.028196],"type":"Point"}
}