{
  "type": "Feature",
  "properties": {
    "iso:country":"US",
    "sg:address":"373 Benner Pike",
    "sg:city":"State College",
    "sg:classifiers":[
        {
            "category":"Health Services",
            "subcategory":"Optometrist",
            "type":"Services"
        }
    ],
    "sg:phone":"+1   ",
    "sg:postcode":"16801",
    "sg:province":"PA",
    "wof:name":"Ja Alianiello",
    "wof:placetype":"venue"
},
  "geometry": {"coordinates":[-77.801349,40.835715],"type":"Point"}
}