{
  "type": "Feature",
  "properties": {
    "addr:full":"628 S Irving Ave Scranton PA 18505",
    "addr:housenumber":"628",
    "addr:postcode":"18505",
    "addr:street":"S Irving Ave",
    "iso:country":"US",
    "sg:address":"628 S Irving Ave",
    "sg:city":"Scranton",
    "sg:classifiers":[
        {
            "category":"Arts & Performance",
            "subcategory":"Theater",
            "type":"Entertainment"
        }
    ],
    "sg:phone":"+1 570 499 3357",
    "sg:postcode":"18505",
    "sg:province":"PA",
    "sg:tags":[
        "live",
        "music"
    ],
    "wof:name":"Deborah Strasburger Live Music",
    "wof:placetype":"venue"
},
  "geometry": {"coordinates":[-75.66051400000001,41.395311],"type":"Point"}
}