{
  "type": "Feature",
  "properties": {
    "addr:full":"609 E 17th Ave Homestead PA 15120",
    "addr:housenumber":"609",
    "addr:postcode":"15120",
    "addr:street":"E 17Th Ave",
    "iso:country":"US",
    "sg:address":"609 E 17th Ave",
    "sg:city":"Homestead",
    "sg:classifiers":[
        {
            "category":"Professional",
            "type":"Services"
        }
    ],
    "sg:phone":"+1   ",
    "sg:postcode":"15120",
    "sg:province":"PA",
    "wof:name":"Susie L Catron",
    "wof:placetype":"venue"
},
  "geometry": {"coordinates":[-79.90034799999999,40.403331],"type":"Point"}
}