{
  "type": "Feature",
  "properties": {
    "addr:full":"228 Bala Ave Oreland PA 19075",
    "addr:housenumber":"228",
    "addr:postcode":"19075",
    "addr:street":"Bala Ave",
    "iso:country":"US",
    "sg:address":"228 Bala Ave",
    "sg:city":"Oreland",
    "sg:classifiers":[
        {
            "category":"Education",
            "subcategory":"Special Training",
            "type":"Public Place"
        }
    ],
    "sg:phone":"+1 215 572 6855",
    "sg:postcode":"19075",
    "sg:province":"PA",
    "sg:tags":[
        "school",
        "instruction",
        "art"
    ],
    "wof:name":"Oreland Art Ctr",
    "wof:placetype":"venue"
},
  "geometry": {"coordinates":[-75.17862,40.120615],"type":"Point"}
}