{
  "type": "Feature",
  "properties": {
    "iso:country":"US",
    "sg:address":"2180 York Crossing Dr",
    "sg:city":"York",
    "sg:classifiers":[
        {
            "category":"Fast Food",
            "type":"Food & Drink"
        },
        {
            "category":"Restaurant",
            "type":"Food & Drink"
        }
    ],
    "sg:phone":"+1 717 767 2776",
    "sg:postcode":"17408",
    "sg:province":"PA",
    "sg:tags":[
        "american",
        "take"
    ],
    "sg:website":"http://www.logansroadhouse.com",
    "wof:name":"Logan's Roadhouse",
    "wof:placetype":"venue"
},
  "geometry": {"coordinates":[-76.776184,39.965363],"type":"Point"}
}