{
  "type": "Feature",
  "properties": {
    "iso:country":"US",
    "sg:address":"930 Old Berwick Rd",
    "sg:city":"Bloomsburg",
    "sg:classifiers":[
        {
            "category":"Autos & Motor Vehicles",
            "subcategory":"Fuel & Gas Station",
            "type":"Retail Goods"
        }
    ],
    "sg:phone":"+1 570 784 8573",
    "sg:postcode":"17815",
    "sg:province":"PA",
    "sg:tags":[
        "repair",
        "station",
        "oil",
        "gasoline",
        "general"
    ],
    "wof:name":"Walt's Best",
    "wof:placetype":"venue"
},
  "geometry": {"coordinates":[-76.437656,41.001745],"type":"Point"}
}