{
  "type": "Feature",
  "properties": {
    "iso:country":"US",
    "sg:address":"401 E Winding Hill Rd",
    "sg:city":"Mechanicsburg",
    "sg:classifiers":[
        {
            "category":"Building & Trades",
            "subcategory":"Construction",
            "type":"Services"
        }
    ],
    "sg:phone":"+1   ",
    "sg:postcode":"17055",
    "sg:province":"PA",
    "sg:tags":[
        "general",
        "bu",
        "apartment",
        "commercial",
        "contractor"
    ],
    "wof:name":"Baron Group",
    "wof:placetype":"venue"
},
  "geometry": {"coordinates":[-76.972692,40.193529],"type":"Point"}
}