{
  "type": "Feature",
  "properties": {
    "iso:country":"US",
    "sg:address":"2231 Dorn Rd",
    "sg:city":"Waterford",
    "sg:classifiers":[
        {
            "category":"Retail",
            "subcategory":"Animal Services",
            "type":"Services"
        }
    ],
    "sg:phone":"+1 814 392 6908",
    "sg:postcode":"16441",
    "sg:province":"PA",
    "sg:tags":[
        "pet",
        "grooming",
        "washing"
    ],
    "wof:name":"Rikki's Shampoochie",
    "wof:placetype":"venue"
},
  "geometry": {"coordinates":[-80.072239,42.029141],"type":"Point"}
}