{
  "type": "Feature",
  "properties": {
    "addr:full":"146 N 10th St Allentown PA 18102",
    "addr:housenumber":"146",
    "addr:postcode":"18102",
    "addr:street":"N 10Th St",
    "iso:country":"US",
    "sg:address":"146 N 10th St",
    "sg:city":"Allentown",
    "sg:classifiers":[
        {
            "category":"Communications",
            "subcategory":"Film & Video Production",
            "type":"Services"
        }
    ],
    "sg:phone":"+1 610 776 5070",
    "sg:postcode":"18102",
    "sg:province":"PA",
    "sg:tags":[
        "taping"
    ],
    "wof:name":"Highrise Entertainment Group",
    "wof:placetype":"venue"
},
  "geometry": {"coordinates":[-75.47924500000001,40.603052],"type":"Point"}
}