{
  "type": "Feature",
  "properties": {
    "iso:country":"US",
    "sg:address":"226 Elm Dr",
    "sg:city":"Waynesburg",
    "sg:classifiers":[
        {
            "category":"Shopping",
            "subcategory":"Optical Goods",
            "type":"Retail Goods"
        }
    ],
    "sg:phone":"+1   ",
    "sg:postcode":"15370",
    "sg:province":"PA",
    "wof:name":"Precision Optical",
    "wof:placetype":"venue"
},
  "geometry": {"coordinates":[-80.14738199999999,39.896237],"type":"Point"}
}