{
  "type": "Feature",
  "properties": {
    "iso:country":"US",
    "sg:address":"125 Seneca Trl",
    "sg:city":"Boyertown",
    "sg:classifiers":[
        {
            "category":"Wholesale",
            "subcategory":"Groceries",
            "type":"Manufacturing & Wholesale Goods"
        }
    ],
    "sg:phone":"+1   ",
    "sg:postcode":"19512",
    "sg:province":"PA",
    "sg:tags":[
        "item",
        "mfg",
        "representative",
        "general"
    ],
    "wof:name":"G & H International Traders",
    "wof:placetype":"venue"
},
  "geometry": {"coordinates":[-75.65607,40.353987],"type":"Point"}
}