{
  "type": "Feature",
  "properties": {
    "iso:country":"US",
    "sg:address":"3609 Nicholas St",
    "sg:city":"Easton",
    "sg:classifiers":[
        {
            "category":"Manufacturing",
            "subcategory":"Building Materials",
            "type":"Manufacturing & Wholesale Goods"
        }
    ],
    "sg:phone":"+1   ",
    "sg:postcode":"18045",
    "sg:province":"PA",
    "sg:tags":[
        "mfg",
        "kitchen",
        "cabinet"
    ],
    "wof:name":"Laslo Custom Kitchens Inc",
    "wof:placetype":"venue"
},
  "geometry": {"coordinates":[-75.26307,40.672324],"type":"Point"}
}