{
  "type": "Feature",
  "properties": {
    "iso:country":"US",
    "sg:address":"675 Saxonburg Rd",
    "sg:city":"Butler",
    "sg:classifiers":[
        {
            "category":"Manufacturing",
            "subcategory":"Electronics",
            "type":"Manufacturing & Wholesale Goods"
        }
    ],
    "sg:phone":"+1 724 352 3790",
    "sg:postcode":"16002",
    "sg:province":"PA",
    "sg:tags":[
        "semiconductor",
        "related",
        "devices"
    ],
    "sg:website":"www.filmtronics.com",
    "wof:name":"Filmtronics Inc",
    "wof:placetype":"venue"
},
  "geometry": {"coordinates":[-79.849465,40.799631],"type":"Point"}
}