{
  "type": "Feature",
  "properties": {
    "iso:country":"US",
    "sg:address":"110 Main St W",
    "sg:city":"Girard",
    "sg:classifiers":[
        {
            "category":"Banks & Credit Unions",
            "subcategory":"Bank",
            "type":"Services"
        }
    ],
    "sg:phone":"+1 814 774 3111",
    "sg:postcode":"16417",
    "sg:province":"PA",
    "sg:website":"http://nationalcity.com",
    "wof:name":"PNC",
    "wof:placetype":"venue"
},
  "geometry": {"coordinates":[-80.31811399999999,42.000234],"type":"Point"}
}