{
  "type": "Feature",
  "properties": {
    "addr:full":"210 S Patterson St State College PA 16801",
    "addr:housenumber":"210",
    "addr:postcode":"16801",
    "addr:street":"S Patterson St",
    "iso:country":"US",
    "sg:address":"210 S Patterson St",
    "sg:city":"State College",
    "sg:classifiers":[
        {
            "category":"Government",
            "subcategory":"Office",
            "type":"Public Place"
        }
    ],
    "sg:phone":"+1   ",
    "sg:postcode":"16801",
    "sg:province":"PA",
    "sg:tags":[
        "educational",
        "program",
        "administrative"
    ],
    "wof:name":"Campus Photography",
    "wof:placetype":"venue"
},
  "geometry": {"coordinates":[-77.86836099999999,40.786857],"type":"Point"}
}