{
  "type": "Feature",
  "properties": {
    "addr:full":"359 Farm Ln North Wales PA 19454",
    "addr:housenumber":"359",
    "addr:postcode":"19454",
    "addr:street":"Farm Ln",
    "iso:country":"US",
    "sg:address":"359 Farm Ln",
    "sg:city":"North Wales",
    "sg:classifiers":[
        {
            "category":"Real Estate",
            "subcategory":"Real Estate Operator",
            "type":"Services"
        }
    ],
    "sg:phone":"+1   ",
    "sg:postcode":"19454",
    "sg:province":"PA",
    "sg:tags":[
        "building",
        "apartment"
    ],
    "wof:name":"Gwyned Woods Condominiums",
    "wof:placetype":"venue"
},
  "geometry": {"coordinates":[-75.266451,40.21752],"type":"Point"}
}