{
  "type": "Feature",
  "properties": {
    "iso:country":"US",
    "sg:address":"3103 Hulmeville Rd",
    "sg:city":"Bensalem",
    "sg:classifiers":[
        {
            "category":"Health Services",
            "subcategory":"Clinic",
            "type":"Services"
        },
        {
            "category":"Health Services",
            "subcategory":"Hospital",
            "type":"Services"
        }
    ],
    "sg:phone":"+1 215 638 8600",
    "sg:postcode":"19020",
    "sg:province":"PA",
    "sg:tags":[
        "mental",
        "outpatient",
        "specialty"
    ],
    "wof:name":"New Life Of Community Health",
    "wof:placetype":"venue"
},
  "geometry": {"coordinates":[-74.94378399999999,40.097557],"type":"Point"}
}