{
  "type": "Feature",
  "properties": {
    "addr:full":"640 E Market St Scranton PA 18509",
    "addr:housenumber":"640",
    "addr:postcode":"18509",
    "addr:street":"E Market St",
    "iso:country":"US",
    "sg:address":"640 E Market St",
    "sg:city":"Scranton",
    "sg:classifiers":[
        {
            "category":"Shopping",
            "subcategory":"Gifts & Souvenirs",
            "type":"Retail Goods"
        }
    ],
    "sg:phone":"+1 570 969 6111",
    "sg:postcode":"18509",
    "sg:province":"PA",
    "sg:tags":[
        "shop"
    ],
    "wof:name":"Curiosity Shop The",
    "wof:placetype":"venue"
},
  "geometry": {"coordinates":[-75.648712,41.433396],"type":"Point"}
}