{
  "type": "Feature",
  "properties": {
    "iso:country":"US",
    "sg:address":"9038 Audubon Dr",
    "sg:city":"Gibsonia",
    "sg:classifiers":[
        {
            "category":"Professional",
            "subcategory":"Business Services",
            "type":"Services"
        }
    ],
    "sg:phone":"+1   ",
    "sg:postcode":"15044",
    "sg:province":"PA",
    "wof:name":"OConnor Group The",
    "wof:placetype":"venue"
},
  "geometry": {"coordinates":[-80.037784,40.679729],"type":"Point"}
}