{
  "type": "Feature",
  "properties": {
    "iso:country":"US",
    "sg:address":"501 S 54th St",
    "sg:city":"Philadelphia",
    "sg:classifiers":[
        {
            "category":"Shopping",
            "type":"Retail Goods"
        }
    ],
    "sg:phone":"+1 215 748 9446",
    "sg:postcode":"19143",
    "sg:province":"PA",
    "sg:tags":[
        "hearing",
        "equipment",
        "supply",
        "impaired"
    ],
    "wof:name":"Hear Now Hearing Aid Ctr",
    "wof:placetype":"venue"
},
  "geometry": {"coordinates":[-75.23063399999999,39.950922],"type":"Point"}
}