{
  "type": "Feature",
  "properties": {
    "addr:full":"625 State Rte 568 Mohnton PA 19540",
    "addr:housenumber":"625",
    "addr:postcode":"19540",
    "addr:street":"State Rte 568 Mohnton",
    "iso:country":"US",
    "sg:address":"625 State Rte 568",
    "sg:city":"Mohnton",
    "sg:classifiers":[
        {
            "category":"Personal",
            "subcategory":"Beauty Salon",
            "type":"Services"
        }
    ],
    "sg:phone":"+1   ",
    "sg:postcode":"19540",
    "sg:province":"PA",
    "sg:tags":[
        "shop"
    ],
    "wof:name":"Kims Nails",
    "wof:placetype":"venue"
},
  "geometry": {"coordinates":[-75.935236,40.238889],"type":"Point"}
}