{
  "type": "Feature",
  "properties": {
    "iso:country":"US",
    "sg:address":"206 E State St",
    "sg:city":"Kennett Square",
    "sg:classifiers":[
        {
            "category":"Organizations",
            "subcategory":"Professional Association",
            "type":"Services"
        }
    ],
    "sg:phone":"+1 610 444 0774",
    "sg:postcode":"19348",
    "sg:province":"PA",
    "sg:tags":[
        "chambers",
        "commerce"
    ],
    "wof:name":"Southern Chester Cnty Chamber",
    "wof:placetype":"venue"
},
  "geometry": {"coordinates":[-75.709946,39.847094],"type":"Point"}
}