{
  "type": "Feature",
  "properties": {
    "iso:country":"US",
    "sg:address":"2107 McMinn St",
    "sg:city":"Aliquippa",
    "sg:classifiers":[
        {
            "category":"Organizations",
            "subcategory":"Religious Organization",
            "type":"Services"
        }
    ],
    "sg:phone":"+1 724 375 6653",
    "sg:postcode":"15001",
    "sg:province":"PA",
    "sg:tags":[
        "baptist",
        "church"
    ],
    "wof:name":"First Baptist Church",
    "wof:placetype":"venue"
},
  "geometry": {"coordinates":[-80.278741,40.605147],"type":"Point"}
}