{
  "type": "Feature",
  "properties": {
    "addr:full":"92 Bethlehem Pike Philadelphia PA 19118",
    "addr:housenumber":"92",
    "addr:postcode":"19118",
    "addr:street":"Bethlehem Pike",
    "iso:country":"US",
    "sg:address":"92 Bethlehem Pike",
    "sg:city":"Philadelphia",
    "sg:classifiers":[
        {
            "category":"Professional",
            "subcategory":"Lawyer & Legal Services",
            "type":"Services"
        }
    ],
    "sg:phone":"+1 215 242 8920",
    "sg:postcode":"19118",
    "sg:province":"PA",
    "sg:tags":[
        "attorney"
    ],
    "wof:name":"Terrance G Lohr",
    "wof:placetype":"venue"
},
  "geometry": {"coordinates":[-75.20791699999999,40.078127],"type":"Point"}
}