{
  "type": "Feature",
  "properties": {
    "iso:country":"US",
    "sg:address":"1919 Babcock Blvd",
    "sg:city":"Pittsburgh",
    "sg:classifiers":[
        {
            "category":"Retail",
            "subcategory":"Auto Repair",
            "type":"Services"
        }
    ],
    "sg:phone":"+1 412 821 3806",
    "sg:postcode":"15209",
    "sg:province":"PA",
    "sg:tags":[
        "repairing",
        "automobile",
        "body"
    ],
    "wof:name":"Dave Bohn Auto Body",
    "wof:placetype":"venue"
},
  "geometry": {"coordinates":[-79.988862,40.504501],"type":"Point"}
}