{
  "type": "Feature",
  "properties": {
    "addr:full":"1312 Porter St Conway PA 15027",
    "addr:housenumber":"1312",
    "addr:postcode":"15027",
    "addr:street":"Porter St",
    "iso:country":"US",
    "sg:address":"1312 Porter St",
    "sg:city":"Conway",
    "sg:classifiers":[
        {
            "category":"Shopping",
            "subcategory":"Bicycles & Sporting Goods",
            "type":"Retail Goods"
        }
    ],
    "sg:phone":"+1   ",
    "sg:postcode":"15027",
    "sg:province":"PA",
    "wof:name":"Freedom Firearms",
    "wof:placetype":"venue"
},
  "geometry": {"coordinates":[-80.234188,40.665091],"type":"Point"}
}