{
  "type": "Feature",
  "properties": {
    "addr:full":"225 Eldred St Williamsport PA 17701",
    "addr:housenumber":"225",
    "addr:postcode":"17701",
    "addr:street":"Eldred St",
    "iso:country":"US",
    "sg:address":"225 Eldred St",
    "sg:city":"Williamsport",
    "sg:classifiers":[
        {
            "category":"Freight",
            "type":"Transportation"
        }
    ],
    "sg:phone":"+1   ",
    "sg:postcode":"17701",
    "sg:province":"PA",
    "sg:tags":[
        "operator",
        "local",
        "trucking"
    ],
    "wof:name":"Franks Moving & Storage",
    "wof:placetype":"venue"
},
  "geometry": {"coordinates":[-76.999831,41.251893],"type":"Point"}
}