{
  "type": "Feature",
  "properties": {
    "iso:country":"US",
    "sg:address":"628 4th Ave",
    "sg:city":"New Kensington",
    "sg:classifiers":[
        {
            "category":"Personal",
            "subcategory":"Beauty Salon",
            "type":"Services"
        }
    ],
    "sg:phone":"+1 724 335 6441",
    "sg:postcode":"15068",
    "sg:province":"PA",
    "wof:name":"Jule's House Of Beauty",
    "wof:placetype":"venue"
},
  "geometry": {"coordinates":[-79.76542600000001,40.561971],"type":"Point"}
}