{
  "type": "Feature",
  "properties": {
    "addr:full":"2 Old Farm Ln Milton PA 17847",
    "addr:housenumber":"2",
    "addr:postcode":"17847",
    "addr:street":"Old Farm Ln",
    "iso:country":"US",
    "sg:address":"2 Old Farm Ln",
    "sg:city":"Milton",
    "sg:classifiers":[
        {
            "category":"Home & Garden",
            "subcategory":"Mobile Homes",
            "type":"Retail Goods"
        }
    ],
    "sg:phone":"+1 570 742 8519",
    "sg:postcode":"17847",
    "sg:province":"PA",
    "wof:name":"Astro Village Listing Svc",
    "wof:placetype":"venue"
},
  "geometry": {"coordinates":[-76.83842799999999,40.996787],"type":"Point"}
}