{
  "type": "Feature",
  "properties": {
    "iso:country":"US",
    "sg:address":"46 Rittenhouse Pl",
    "sg:city":"Ardmore",
    "sg:classifiers":[
        {
            "category":"Personal",
            "subcategory":"Beauty Salon",
            "type":"Services"
        }
    ],
    "sg:phone":"+1 610 642 6843",
    "sg:postcode":"19003",
    "sg:province":"PA",
    "wof:name":"Town & Country Salon Of Beauty",
    "wof:placetype":"venue"
},
  "geometry": {"coordinates":[-75.290727,40.006219],"type":"Point"}
}