{
  "type": "Feature",
  "properties": {
    "addr:full":"1016 Evans St Bethlehem PA 18015",
    "addr:housenumber":"1016",
    "addr:postcode":"18015",
    "addr:street":"Evans St",
    "iso:country":"US",
    "sg:address":"1016 Evans St",
    "sg:city":"Bethlehem",
    "sg:classifiers":[
        {
            "category":"Sports & Exercise",
            "subcategory":"Bowling",
            "type":"Entertainment"
        }
    ],
    "sg:phone":"+1   ",
    "sg:postcode":"18015",
    "sg:province":"PA",
    "sg:tags":[
        "center"
    ],
    "wof:name":"Bethlehem Panthers A A",
    "wof:placetype":"venue"
},
  "geometry": {"coordinates":[-75.363755,40.612142],"type":"Point"}
}