{
  "type": "Feature",
  "properties": {
    "iso:country":"US",
    "sg:address":"712 Poplar St",
    "sg:city":"Langhorne",
    "sg:classifiers":[
        {
            "category":"Building & Trades",
            "subcategory":"Construction",
            "type":"Services"
        }
    ],
    "sg:phone":"+1 215 752 6145",
    "sg:postcode":"19047",
    "sg:province":"PA",
    "sg:tags":[
        "roofing",
        "industrial",
        "contractors-commercial",
        "contractor"
    ],
    "sg:website":"http://www.abrooksconstruction.com",
    "wof:name":"Brooks Roofing",
    "wof:placetype":"venue"
},
  "geometry": {"coordinates":[-74.926102,40.161973],"type":"Point"}
}