{
  "type": "Feature",
  "properties": {
    "addr:full":"610 W Germantown Pike Plymouth Meeting PA 19462",
    "addr:housenumber":"610",
    "addr:postcode":"19462",
    "addr:street":"W Germantown Pike",
    "iso:country":"US",
    "sg:address":"610 W Germantown Pike",
    "sg:city":"Plymouth Meeting",
    "sg:classifiers":[
        {
            "category":"Professional",
            "subcategory":"Employment Agencies",
            "type":"Services"
        }
    ],
    "sg:phone":"+1 610 825 8334",
    "sg:postcode":"19462",
    "sg:province":"PA",
    "sg:tags":[
        "supply",
        "help",
        "contractor"
    ],
    "wof:name":"Volt Services Group",
    "wof:placetype":"venue"
},
  "geometry": {"coordinates":[-75.28616700000001,40.118402],"type":"Point"}
}