{
  "type": "Feature",
  "properties": {
    "addr:full":"712 Ridge St Honesdale PA 18431",
    "addr:housenumber":"712",
    "addr:postcode":"18431",
    "addr:street":"Ridge St",
    "iso:country":"US",
    "sg:address":"712 Ridge St",
    "sg:city":"Honesdale",
    "sg:classifiers":[
        {
            "category":"Building & Trades",
            "subcategory":"Construction",
            "type":"Services"
        }
    ],
    "sg:phone":"+1   ",
    "sg:postcode":"18431",
    "sg:province":"PA",
    "sg:tags":[
        "contractor"
    ],
    "wof:name":"Landers Masonry",
    "wof:placetype":"venue"
},
  "geometry": {"coordinates":[-75.258814,41.564224],"type":"Point"}
}