{
  "type": "Feature",
  "properties": {
    "addr:full":"1619 S Braddock Ave Pittsburgh PA 15218",
    "addr:housenumber":"1619",
    "addr:postcode":"15218",
    "addr:street":"S Braddock Ave",
    "iso:country":"US",
    "sg:address":"1619 S Braddock Ave",
    "sg:city":"Pittsburgh",
    "sg:classifiers":[
        {
            "category":"Professional",
            "subcategory":"Accounting & Tax Preparation",
            "type":"Services"
        },
        {
            "category":"Banks & Credit Unions",
            "subcategory":"Financial Services",
            "type":"Services"
        }
    ],
    "sg:phone":"+1 412 244 1331",
    "sg:postcode":"15218",
    "sg:province":"PA",
    "sg:tags":[
        "return",
        "preparation-business",
        "taxes-consultants",
        "loan",
        "reporting",
        "representative",
        "alternative",
        "bookkeeping"
    ],
    "sg:website":"http://www.hrblock.com",
    "wof:name":"H&R Block",
    "wof:placetype":"venue"
},
  "geometry": {"coordinates":[-79.890097,40.426632],"type":"Point"}
}