{
  "type": "Feature",
  "properties": {
    "iso:country":"US",
    "sg:address":"9505 Meadow Rd",
    "sg:city":"Allison Park",
    "sg:classifiers":[
        {
            "category":"Professional",
            "type":"Services"
        }
    ],
    "sg:phone":"+1   ",
    "sg:postcode":"15101",
    "sg:province":"PA",
    "wof:name":"Delight Digital Ltd",
    "wof:placetype":"venue"
},
  "geometry": {"coordinates":[-79.997181,40.577698],"type":"Point"}
}