{
  "type": "Feature",
  "properties": {
    "iso:country":"US",
    "sg:address":"4 S 4th St",
    "sg:city":"Youngwood",
    "sg:classifiers":[
        {
            "category":"Professional",
            "subcategory":"Detective & Security Services",
            "type":"Services"
        }
    ],
    "sg:phone":"+1 724 755 6262",
    "sg:postcode":"15697",
    "sg:province":"PA",
    "sg:tags":[
        "guard",
        "patrol"
    ],
    "wof:name":"Point Security Company Inc",
    "wof:placetype":"venue"
},
  "geometry": {"coordinates":[-79.579863,40.238508],"type":"Point"}
}