{
  "type": "Feature",
  "properties": {
    "iso:country":"US",
    "sg:address":"6901 Old York Rd",
    "sg:city":"Philadelphia",
    "sg:classifiers":[
        {
            "category":"Food & Beverages",
            "subcategory":"Dairy",
            "type":"Retail Goods"
        }
    ],
    "sg:phone":"+1 215 548 0200",
    "sg:postcode":"19126",
    "sg:province":"PA",
    "sg:tags":[
        "product"
    ],
    "wof:name":"L & L Distribution Services",
    "wof:placetype":"venue"
},
  "geometry": {"coordinates":[-75.13861199999999,40.058737],"type":"Point"}
}