{
  "type": "Feature",
  "properties": {
    "iso:country":"US",
    "sg:address":"3432 Old Berwick Rd",
    "sg:city":"Bloomsburg",
    "sg:classifiers":[
        {
            "category":"Organizations",
            "subcategory":"Labor Organization",
            "type":"Services"
        }
    ],
    "sg:phone":"+1   ",
    "sg:postcode":"17815",
    "sg:province":"PA",
    "wof:name":"Union of Utility Workers",
    "wof:placetype":"venue"
},
  "geometry": {"coordinates":[-76.38950699999999,41.01228],"type":"Point"}
}