{
  "type": "Feature",
  "properties": {
    "iso:country":"US",
    "sg:address":"518 Swarthmore Ave",
    "sg:city":"Folsom",
    "sg:classifiers":[
        {
            "category":"Professional",
            "type":"Services"
        }
    ],
    "sg:phone":"+1 610 461 4881",
    "sg:postcode":"19033",
    "sg:province":"PA",
    "sg:tags":[
        "establishment"
    ],
    "wof:name":"Franklin Electric",
    "wof:placetype":"venue"
},
  "geometry": {"coordinates":[-75.32413,39.896271],"type":"Point"}
}