{
  "type": "Feature",
  "properties": {
    "addr:full":"540 S Oak Ave  Clifton Heights PA 19018",
    "addr:housenumber":"540",
    "addr:postcode":"19018",
    "addr:street":"S Oak Ave",
    "iso:country":"US",
    "sg:address":"540 S Oak Ave ",
    "sg:city":"Clifton Heights",
    "sg:classifiers":[
        {
            "category":"Restaurant",
            "type":"Food & Drink"
        }
    ],
    "sg:menulink":"http://www.allmenus.com/pa/upper-darby/289255-coccos-pizza/menu/",
    "sg:phone":"+1 610 622 4147",
    "sg:postcode":"19018",
    "sg:province":"PA",
    "sg:tags":[
        "american",
        "pizza"
    ],
    "wof:name":"Cocco's Pizza",
    "wof:placetype":"venue"
},
  "geometry": {"coordinates":[-75.29855999999999,39.920549],"type":"Point"}
}