{
  "type": "Feature",
  "properties": {
    "iso:country":"US",
    "sg:address":"2820 W 21st St",
    "sg:city":"Erie",
    "sg:classifiers":[
        {
            "category":"Professional",
            "subcategory":"Management & Consulting",
            "type":"Services"
        },
        {
            "category":"Professional",
            "subcategory":"Advertising",
            "type":"Services"
        }
    ],
    "sg:phone":"+1 814 833 5026",
    "sg:postcode":"16506",
    "sg:province":"PA",
    "sg:tags":[
        "marketing",
        "program",
        "consultant"
    ],
    "wof:name":"Skyrocket Group Inc",
    "wof:placetype":"venue"
},
  "geometry": {"coordinates":[-80.138458,42.093104],"type":"Point"}
}