{
  "type": "Feature",
  "properties": {
    "iso:country":"US",
    "sg:address":"13 Front St",
    "sg:city":"Cressona",
    "sg:classifiers":[
        {
            "category":"Manufacturing",
            "subcategory":"Food",
            "type":"Manufacturing & Wholesale Goods"
        }
    ],
    "sg:phone":"+1 570 385 5277",
    "sg:postcode":"17929",
    "sg:province":"PA",
    "sg:tags":[
        "creamery",
        "butter"
    ],
    "wof:name":"West Haven Creamery",
    "wof:placetype":"venue"
},
  "geometry": {"coordinates":[-76.19519699999999,40.630285],"type":"Point"}
}