{
  "type": "Feature",
  "properties": {
    "iso:country":"US",
    "sg:address":"64 Hunters Ln",
    "sg:city":"Loganton",
    "sg:classifiers":[
        {
            "category":"Manufacturing",
            "subcategory":"Apparel",
            "type":"Manufacturing & Wholesale Goods"
        }
    ],
    "sg:phone":"+1   ",
    "sg:postcode":"17771",
    "sg:province":"PA",
    "wof:name":"Pjs Kreations",
    "wof:placetype":"venue"
},
  "geometry": {"coordinates":[-77.253766,41.392605],"type":"Point"}
}