{
  "type": "Feature",
  "properties": {
    "iso:country":"US",
    "sg:address":"10686 Jamestown Rd",
    "sg:city":"Wattsburg",
    "sg:classifiers":[
        {
            "category":"Farming",
            "subcategory":"Dairy Farm",
            "type":"Manufacturing & Wholesale Goods"
        }
    ],
    "sg:phone":"+1   ",
    "sg:postcode":"16442",
    "sg:province":"PA",
    "wof:name":"Bush Farms",
    "wof:placetype":"venue"
},
  "geometry": {"coordinates":[-79.77612499999999,42.020146],"type":"Point"}
}