{
  "type": "Feature",
  "properties": {
    "iso:country":"US",
    "sg:address":"647 Race St",
    "sg:city":"Bristol",
    "sg:classifiers":[
        {
            "category":"Retail",
            "subcategory":"Laundry & Dry Cleaning",
            "type":"Services"
        }
    ],
    "sg:phone":"+1 215 788 1028",
    "sg:postcode":"19007",
    "sg:province":"PA",
    "sg:tags":[
        "commercial"
    ],
    "wof:name":"Total Spotless Cleaning",
    "wof:placetype":"venue"
},
  "geometry": {"coordinates":[-74.860466,40.100512],"type":"Point"}
}