{
  "type": "Feature",
  "properties": {
    "addr:full":"9880 Bustleton Ave Philadelphia PA 19115",
    "addr:postcode":"9880;19115",
    "addr:street":"Bustleton Ave",
    "iso:country":"US",
    "sg:address":"9880 Bustleton Ave",
    "sg:city":"Philadelphia",
    "sg:classifiers":[
        {
            "category":"Professional",
            "subcategory":"Testing Lab",
            "type":"Services"
        }
    ],
    "sg:phone":"+1 215 698 9434",
    "sg:postcode":"19115",
    "sg:province":"PA",
    "sg:tags":[
        "laboratory"
    ],
    "wof:name":"Laboratory Corp Of America",
    "wof:placetype":"venue"
},
  "geometry": {"coordinates":[-75.03074700000001,40.095967],"type":"Point"}
}