{
  "type": "Feature",
  "properties": {
    "addr:full":"240 N Hermitage Rd Hermitage PA 16148",
    "addr:housenumber":"240",
    "addr:postcode":"16148",
    "addr:street":"N Hermitage Rd",
    "iso:country":"US",
    "sg:address":"240 N Hermitage Rd",
    "sg:city":"Hermitage",
    "sg:classifiers":[
        {
            "category":"Place Of Worship",
            "subcategory":"Church",
            "type":"Public Place"
        },
        {
            "category":"Place Of Worship",
            "type":"Public Place"
        }
    ],
    "sg:phone":"+1 724 981 9450",
    "sg:postcode":"16148",
    "sg:province":"PA",
    "sg:tags":[
        "churches-methodist"
    ],
    "wof:name":"Hickory United Methodist Church",
    "wof:placetype":"venue"
},
  "geometry": {"coordinates":[-80.449725,41.235892],"type":"Point"}
}