{
  "type": "Feature",
  "properties": {
    "iso:country":"US",
    "sg:address":"315 40th St",
    "sg:city":"Altoona",
    "sg:classifiers":[
        {
            "category":"Professional",
            "type":"Services"
        }
    ],
    "sg:phone":"+1 814 944 1858",
    "sg:postcode":"16602",
    "sg:province":"PA",
    "sg:tags":[
        "establishment"
    ],
    "wof:name":"Coalition For Religious Frdm",
    "wof:placetype":"venue"
},
  "geometry": {"coordinates":[-78.41315899999999,40.485494],"type":"Point"}
}