{
  "type": "Feature",
  "properties": {
    "iso:country":"US",
    "sg:address":"403 W Chester Rd",
    "sg:city":"West Chester",
    "sg:classifiers":[
        {
            "category":"Wholesale",
            "subcategory":"Electrical",
            "type":"Manufacturing & Wholesale Goods"
        }
    ],
    "sg:phone":"+1 610 429 0383",
    "sg:postcode":"19382",
    "sg:province":"PA",
    "sg:tags":[
        "electric",
        "motor"
    ],
    "wof:name":"Grainger Inc",
    "wof:placetype":"venue"
},
  "geometry": {"coordinates":[-75.544979,39.910905],"type":"Point"}
}