{
  "type": "Feature",
  "properties": {
    "addr:full":"195 Phillips Park Dr S Williamsport PA 17702",
    "addr:housenumber":"195",
    "addr:postcode":"17702",
    "addr:street":"Phillips Park Dr S",
    "iso:country":"US",
    "sg:address":"195 Phillips Park Dr",
    "sg:city":"S Williamsport",
    "sg:classifiers":[
        {
            "category":"Building & Trades",
            "subcategory":"Construction",
            "type":"Services"
        }
    ],
    "sg:phone":"+1 570 323 7233",
    "sg:postcode":"17702",
    "sg:province":"PA",
    "sg:tags":[
        "home",
        "improvement"
    ],
    "wof:name":"Construction Solution",
    "wof:placetype":"venue"
},
  "geometry": {"coordinates":[-77.015227,41.22744],"type":"Point"}
}