{
  "type": "Feature",
  "properties": {
    "iso:country":"US",
    "sg:address":"119 Providence Ave",
    "sg:city":"Doylestown",
    "sg:classifiers":[
        {
            "category":"Shopping",
            "subcategory":"Computers & Home Electronics",
            "type":"Retail Goods"
        }
    ],
    "sg:phone":"+1 215 759 1726",
    "sg:postcode":"18901",
    "sg:province":"PA",
    "sg:tags":[
        "software"
    ],
    "wof:name":"Cyber Broadcasters Inc",
    "wof:placetype":"venue"
},
  "geometry": {"coordinates":[-75.152017,40.31371],"type":"Point"}
}