{
  "type": "Feature",
  "properties": {
    "addr:full":"364 Wilmington Pike Glen Mills PA 19342",
    "addr:housenumber":"364",
    "addr:postcode":"19342",
    "addr:street":"Wilmington Pike",
    "iso:country":"US",
    "sg:address":"364 Wilmington Pike",
    "sg:city":"Glen Mills",
    "sg:classifiers":[
        {
            "category":"Personal",
            "subcategory":"Day Spa",
            "type":"Services"
        },
        {
            "category":"Personal",
            "subcategory":"Nail Salon",
            "type":"Services"
        }
    ],
    "sg:phone":"+1 610 358 3185",
    "sg:postcode":"19342",
    "sg:province":"PA",
    "wof:name":"Salon Allure",
    "wof:placetype":"venue"
},
  "geometry": {"coordinates":[-75.534897,39.8517],"type":"Point"}
}