{
  "type": "Feature",
  "properties": {
    "iso:country":"US",
    "sg:address":"8012 Ridge Ave",
    "sg:city":"Philadelphia",
    "sg:classifiers":[
        {
            "category":"Insurance",
            "subcategory":"Insurance Agent",
            "type":"Services"
        },
        {
            "category":"Insurance",
            "subcategory":"Hazard Insurance",
            "type":"Services"
        },
        {
            "category":"Insurance",
            "subcategory":"Title Insurance",
            "type":"Services"
        },
        {
            "category":"Insurance",
            "subcategory":"Life Insurance",
            "type":"Services"
        }
    ],
    "sg:phone":"+1 215 482 3300",
    "sg:postcode":"19128",
    "sg:province":"PA",
    "sg:tags":[
        "business",
        "auto",
        "commercial",
        "homeowner",
        "motorcycle",
        "renter"
    ],
    "wof:name":"Allstate Insurance Company - Anthony Perretta",
    "wof:placetype":"venue"
},
  "geometry": {"coordinates":[-75.23593200000001,40.055901],"type":"Point"}
}