{
  "type": "Feature",
  "properties": {
    "addr:full":"300 Pottstown Pike Exton PA 19341",
    "addr:housenumber":"300",
    "addr:postcode":"19341",
    "addr:street":"Pottstown Pike",
    "iso:country":"US",
    "sg:address":"300 Pottstown Pike",
    "sg:city":"Exton",
    "sg:classifiers":[
        {
            "category":"Health Services",
            "subcategory":"Doctor",
            "type":"Services"
        }
    ],
    "sg:phone":"+1 610 524 2400",
    "sg:postcode":"19341",
    "sg:province":"PA",
    "sg:tags":[
        "physician",
        "surgeon"
    ],
    "wof:name":"Pennhurst",
    "wof:placetype":"venue"
},
  "geometry": {"coordinates":[-75.63227500000001,40.03552],"type":"Point"}
}