{
  "type": "Feature",
  "properties": {
    "addr:full":"355 E Conestoga Rd Wayne PA 19087",
    "addr:housenumber":"355",
    "addr:postcode":"19087",
    "addr:street":"E Conestoga Rd",
    "iso:country":"US",
    "sg:address":"355 E Conestoga Rd",
    "sg:city":"Wayne",
    "sg:classifiers":[
        {
            "category":"Professional",
            "subcategory":"Advertising",
            "type":"Services"
        }
    ],
    "sg:phone":"+1   ",
    "sg:postcode":"19087",
    "sg:province":"PA",
    "sg:tags":[
        "mail",
        "direct"
    ],
    "wof:name":"Anro Inc of Pennsylvania",
    "wof:placetype":"venue"
},
  "geometry": {"coordinates":[-75.409396,40.048574],"type":"Point"}
}