{
  "type": "Feature",
  "properties": {
    "iso:country":"US",
    "sg:address":"1197 W Chester Rd",
    "sg:city":"West Chester",
    "sg:classifiers":[
        {
            "category":"Banks & Credit Unions",
            "subcategory":"Bank",
            "type":"Services"
        }
    ],
    "sg:phone":"+1 610 399 9798",
    "sg:postcode":"19382",
    "sg:province":"PA",
    "sg:tags":[
        "federal",
        "savings",
        "institution"
    ],
    "wof:name":"First Financial Bank",
    "wof:placetype":"venue"
},
  "geometry": {"coordinates":[-75.546981,39.911166],"type":"Point"}
}