{
  "type": "Feature",
  "properties": {
    "addr:full":"Walnut & 19th St Philadelphia PA 19102",
    "addr:postcode":"19102",
    "addr:street":"St",
    "iso:country":"US",
    "sg:address":"Walnut & 19th St",
    "sg:city":"Philadelphia",
    "sg:classifiers":[
        {
            "category":"Professional",
            "subcategory":"Lawyer & Legal Services",
            "type":"Services"
        }
    ],
    "sg:phone":"+1 215 569 1050",
    "sg:postcode":"19102",
    "sg:province":"PA",
    "wof:name":"A M R Cohen Esquire Law Offices",
    "wof:placetype":"venue"
},
  "geometry": {"coordinates":[-75.172254,39.950345],"type":"Point"}
}