{
  "type": "Feature",
  "properties": {
    "iso:country":"US",
    "sg:address":"134 S 7th St",
    "sg:city":"Philadelphia",
    "sg:classifiers":[
        {
            "category":"Shopping",
            "subcategory":"Jewelry",
            "type":"Retail Goods"
        }
    ],
    "sg:phone":"+1   ",
    "sg:postcode":"19106",
    "sg:province":"PA",
    "wof:name":"Cuggini",
    "wof:placetype":"venue"
},
  "geometry": {"coordinates":[-75.15272899999999,39.948008],"type":"Point"}
}