{
  "type": "Feature",
  "properties": {
    "addr:full":"1156 Steinmetz Rd Ephrata PA 17522",
    "addr:housenumber":"1156",
    "addr:postcode":"17522",
    "addr:street":"Steinmetz Rd",
    "iso:country":"US",
    "sg:address":"1156 Steinmetz Rd",
    "sg:city":"Ephrata",
    "sg:classifiers":[
        {
            "category":"Manufacturing",
            "subcategory":"Furniture",
            "type":"Manufacturing & Wholesale Goods"
        }
    ],
    "sg:phone":"+1   ",
    "sg:postcode":"17522",
    "sg:province":"PA",
    "sg:tags":[
        "mfg",
        "fixture",
        "custom",
        "cabinet",
        "display",
        "store"
    ],
    "wof:name":"Millers Fabricating",
    "wof:placetype":"venue"
},
  "geometry": {"coordinates":[-76.19957100000001,40.165136],"type":"Point"}
}