{
  "type": "Feature",
  "properties": {
    "iso:country":"US",
    "sg:address":"18 School St",
    "sg:city":"Lawrence",
    "sg:classifiers":[
        {
            "category":"Government",
            "subcategory":"Post Office",
            "type":"Public Place"
        }
    ],
    "sg:phone":"+1 724 941 3360",
    "sg:postcode":"15055",
    "sg:province":"PA",
    "wof:name":"US Post Office",
    "wof:placetype":"venue"
},
  "geometry": {"coordinates":[-80.12454099999999,40.305951],"type":"Point"}
}