{
  "type": "Feature",
  "properties": {
    "addr:full":"103 Erie St Edinboro PA 16412",
    "addr:housenumber":"103",
    "addr:postcode":"16412",
    "addr:street":"Erie St",
    "iso:country":"US",
    "sg:address":"103 Erie St",
    "sg:city":"Edinboro",
    "sg:classifiers":[
        {
            "category":"Health Services",
            "subcategory":"Optometrist",
            "type":"Services"
        }
    ],
    "sg:phone":"+1 814 734 5193",
    "sg:postcode":"16412",
    "sg:province":"PA",
    "wof:name":"James T Bolard OD",
    "wof:placetype":"venue"
},
  "geometry": {"coordinates":[-80.13206,41.875039],"type":"Point"}
}