{
  "type": "Feature",
  "properties": {
    "addr:full":"420 Smithfield St Pittsburgh PA 15222",
    "addr:housenumber":"420",
    "addr:postcode":"15222",
    "addr:street":"Smithfield St",
    "iso:country":"US",
    "sg:address":"420 Smithfield St",
    "sg:city":"Pittsburgh",
    "sg:classifiers":[
        {
            "category":"Restaurant",
            "type":"Food & Drink"
        }
    ],
    "sg:menulink":"http://www.allmenus.com/pa/pittsburgh/6026-sammys/menu/",
    "sg:phone":"+1 412 471 3122",
    "sg:postcode":"15222",
    "sg:province":"PA",
    "sg:tags":[
        "irish",
        "sandwich",
        "american",
        "pub"
    ],
    "wof:name":"Sammy's",
    "wof:placetype":"venue"
},
  "geometry": {"coordinates":[-79.99928300000001,40.439219],"type":"Point"}
}