{
  "type": "Feature",
  "properties": {
    "iso:country":"US",
    "sg:address":"11 Colonial Way",
    "sg:city":"Malvern",
    "sg:classifiers":[
        {
            "category":"Professional",
            "subcategory":"Business Services",
            "type":"Services"
        }
    ],
    "sg:phone":"+1   ",
    "sg:postcode":"19355",
    "sg:province":"PA",
    "sg:tags":[
        "interior",
        "decorating"
    ],
    "wof:name":"S Mitchell Interiors",
    "wof:placetype":"venue"
},
  "geometry": {"coordinates":[-75.489154,40.02801],"type":"Point"}
}