{
  "type": "Feature",
  "properties": {
    "iso:country":"US",
    "sg:address":"108 Sunrise Dr",
    "sg:city":"Dalton",
    "sg:classifiers":[
        {
            "category":"Building & Trades",
            "subcategory":"Construction",
            "type":"Services"
        }
    ],
    "sg:phone":"+1 570 563 1930",
    "sg:postcode":"18414",
    "sg:province":"PA",
    "sg:tags":[
        "masonry",
        "contractor"
    ],
    "wof:name":"Herbert C Noll Mason Contr",
    "wof:placetype":"venue"
},
  "geometry": {"coordinates":[-75.743324,41.529253],"type":"Point"}
}