{
  "type": "Feature",
  "properties": {
    "addr:full":"142 S 5th Ave Clarion PA 16214",
    "addr:housenumber":"142",
    "addr:postcode":"16214",
    "addr:street":"S 5Th Ave",
    "iso:country":"US",
    "sg:address":"142 S 5th Ave",
    "sg:city":"Clarion",
    "sg:classifiers":[
        {
            "category":"Building & Trades",
            "subcategory":"Construction",
            "type":"Services"
        }
    ],
    "sg:phone":"+1   ",
    "sg:postcode":"16214",
    "sg:province":"PA",
    "sg:tags":[
        "house"
    ],
    "wof:name":"Tucker Cunstruction",
    "wof:placetype":"venue"
},
  "geometry": {"coordinates":[-79.388553,41.210581],"type":"Point"}
}