{
  "type": "Feature",
  "properties": {
    "iso:country":"US",
    "sg:address":"210 Market St",
    "sg:city":"Mifflinburg",
    "sg:classifiers":[
        {
            "category":"Building & Trades",
            "subcategory":"Construction",
            "type":"Services"
        }
    ],
    "sg:phone":"+1   ",
    "sg:postcode":"17844",
    "sg:province":"PA",
    "wof:name":"Glenn O Hawbaker Inc",
    "wof:placetype":"venue"
},
  "geometry": {"coordinates":[-77.04281899999999,40.918543],"type":"Point"}
}