{
  "type": "Feature",
  "properties": {
    "addr:full":"Rts 73 & 113 Skippack PA 19474",
    "addr:housenumber":"73 & 113",
    "addr:postcode":"19474",
    "addr:street":"Rts",
    "iso:country":"US",
    "sg:address":"Rts 73 & 113",
    "sg:city":"Skippack",
    "sg:classifiers":[
        {
            "category":"Retail",
            "subcategory":"Portrait Studio",
            "type":"Services"
        },
        {
            "category":"Shopping",
            "subcategory":"Pharmacy",
            "type":"Retail Goods"
        }
    ],
    "sg:phone":"+1 610 584 6544",
    "sg:postcode":"19474",
    "sg:province":"PA",
    "sg:tags":[
        "photography",
        "drugstore",
        "store"
    ],
    "wof:name":"Skippack Pharmacy",
    "wof:placetype":"venue"
},
  "geometry": {"coordinates":[-75.405694,40.228605],"type":"Point"}
}