{
  "type": "Feature",
  "properties": {
    "addr:full":"914 COLUMBIA AVE LANCASTER PA 17603",
    "addr:housenumber":"914",
    "addr:postcode":"17603",
    "addr:street":"Columbia Ave",
    "iso:country":"US",
    "sg:address":"914 COLUMBIA AVE",
    "sg:city":"LANCASTER",
    "sg:classifiers":[
        {
            "category":"Real Estate",
            "subcategory":"Real Estate Services",
            "type":"Services"
        },
        {
            "category":"Professional",
            "subcategory":"Business Services",
            "type":"Services"
        },
        {
            "category":"Real Estate",
            "subcategory":"Surveying",
            "type":"Services"
        }
    ],
    "sg:phone":"+1 717 299 7234",
    "sg:postcode":"17603",
    "sg:province":"PA",
    "sg:tags":[
        "consultant",
        "industrial",
        "appraisers-commercial",
        "appraiser"
    ],
    "sg:website":"http://www.aailanc.com",
    "wof:name":"Appraisal Associates",
    "wof:placetype":"venue"
},
  "geometry": {"coordinates":[-76.324049,40.038278],"type":"Point"}
}