{
  "type": "Feature",
  "properties": {
    "iso:country":"US",
    "sg:address":"3249 N Front St",
    "sg:city":"Philadelphia",
    "sg:classifiers":[
        {
            "category":"Shopping",
            "subcategory":"Clothing, Apparel, & Fashions",
            "type":"Retail Goods"
        }
    ],
    "sg:phone":"+1 215 291 4348",
    "sg:postcode":"19140",
    "sg:province":"PA",
    "wof:name":"Gina Fashion",
    "wof:placetype":"venue"
},
  "geometry": {"coordinates":[-75.128974,39.99934],"type":"Point"}
}