{
  "type": "Feature",
  "properties": {
    "addr:full":"413 N Vesper St Lock Haven PA 17745",
    "addr:housenumber":"413",
    "addr:postcode":"17745",
    "addr:street":"N Vesper St",
    "iso:country":"US",
    "sg:address":"413 N Vesper St",
    "sg:city":"Lock Haven",
    "sg:classifiers":[
        {
            "category":"Professional",
            "subcategory":"Secretarial Services",
            "type":"Services"
        }
    ],
    "sg:phone":"+1 570 748 1041",
    "sg:postcode":"17745",
    "sg:province":"PA",
    "sg:tags":[
        "convention",
        "court",
        "reporter"
    ],
    "wof:name":"MLP Reporting",
    "wof:placetype":"venue"
},
  "geometry": {"coordinates":[-77.445824,41.138243],"type":"Point"}
}