{
  "type": "Feature",
  "properties": {
    "addr:full":"110 Brandywine Ave Downingtown PA 19335",
    "addr:housenumber":"110",
    "addr:postcode":"19335",
    "addr:street":"Brandywine Ave",
    "iso:country":"US",
    "sg:address":"110 Brandywine Ave",
    "sg:city":"Downingtown",
    "sg:classifiers":[
        {
            "category":"Professional",
            "subcategory":"Management & Consulting",
            "type":"Services"
        }
    ],
    "sg:phone":"+1 610 518 7690",
    "sg:postcode":"19335",
    "sg:province":"PA",
    "sg:tags":[
        "business"
    ],
    "wof:name":"Herpetological Associates Inc",
    "wof:placetype":"venue"
},
  "geometry": {"coordinates":[-75.702968,40.00518],"type":"Point"}
}