{
  "type": "Feature",
  "properties": {
    "iso:country":"US",
    "sg:address":"5416 Rising Sun Ave",
    "sg:city":"Philadelphia",
    "sg:classifiers":[
        {
            "category":"Organizations",
            "subcategory":"Labor Organization",
            "type":"Services"
        }
    ],
    "sg:phone":"+1 215 457 4666",
    "sg:postcode":"19120",
    "sg:province":"PA",
    "wof:name":"Bakery & Confectionery Workers",
    "wof:placetype":"venue"
},
  "geometry": {"coordinates":[-75.116083,40.033037],"type":"Point"}
}