{
  "type": "Feature",
  "properties": {
    "addr:full":"102 Center Ave Butler PA 16001",
    "addr:housenumber":"102",
    "addr:postcode":"16001",
    "addr:street":"Center Ave",
    "iso:country":"US",
    "sg:address":"102 Center Ave",
    "sg:city":"Butler",
    "sg:classifiers":[
        {
            "category":"Education",
            "subcategory":"School",
            "type":"Public Place"
        }
    ],
    "sg:phone":"+1   ",
    "sg:postcode":"16001",
    "sg:province":"PA",
    "wof:name":"Intermediate H Midwestern",
    "wof:placetype":"venue"
},
  "geometry": {"coordinates":[-79.890435,40.855604],"type":"Point"}
}