{
  "type": "Feature",
  "properties": {
    "iso:country":"US",
    "sg:address":"104 E Baltimore St",
    "sg:city":"Greencastle",
    "sg:classifiers":[
        {
            "category":"Restaurant",
            "type":"Food & Drink"
        }
    ],
    "sg:phone":"+1 717 597 8111",
    "sg:postcode":"17225",
    "sg:province":"PA",
    "wof:name":"Antrim House",
    "wof:placetype":"venue"
},
  "geometry": {"coordinates":[-77.72584999999999,39.789923],"type":"Point"}
}