{
  "type": "Feature",
  "properties": {
    "addr:full":"951 E Orange St Lancaster PA 17602",
    "addr:housenumber":"951",
    "addr:postcode":"17602",
    "addr:street":"E Orange St",
    "iso:country":"US",
    "sg:address":"951 E Orange St",
    "sg:city":"Lancaster",
    "sg:classifiers":[
        {
            "category":"Retail",
            "subcategory":"Portrait Studio",
            "type":"Services"
        }
    ],
    "sg:phone":"+1 717 291 9601",
    "sg:postcode":"17602",
    "sg:province":"PA",
    "wof:name":"Distinctive Images By Steph",
    "wof:placetype":"venue"
},
  "geometry": {"coordinates":[-76.285314,40.041734],"type":"Point"}
}