{
  "type": "Feature",
  "properties": {
    "addr:full":"6714 Glades Pike Somerset PA 15501",
    "addr:housenumber":"6714",
    "addr:postcode":"15501",
    "addr:street":"Glades Pike",
    "iso:country":"US",
    "sg:address":"6714 Glades Pike",
    "sg:city":"Somerset",
    "sg:classifiers":[
        {
            "category":"Home & Garden",
            "subcategory":"Building Materials",
            "type":"Retail Goods"
        }
    ],
    "sg:phone":"+1 814 443 1688",
    "sg:postcode":"15501",
    "sg:province":"PA",
    "sg:tags":[
        "lumber",
        "supply"
    ],
    "wof:name":"Village Lumber Co",
    "wof:placetype":"venue"
},
  "geometry": {"coordinates":[-78.99629299999999,39.989216],"type":"Point"}
}