{
  "type": "Feature",
  "properties": {
    "iso:country":"US",
    "sg:address":"102 Drury Ct",
    "sg:city":"Gibsonia",
    "sg:classifiers":[
        {
            "category":"Professional",
            "subcategory":"Advertising",
            "type":"Services"
        }
    ],
    "sg:phone":"+1   ",
    "sg:postcode":"15044",
    "sg:province":"PA",
    "sg:tags":[
        "mail",
        "direct"
    ],
    "wof:name":"Best of Pittsburgh",
    "wof:placetype":"venue"
},
  "geometry": {"coordinates":[-79.992672,40.627334],"type":"Point"}
}