{
  "type": "Feature",
  "properties": {
    "iso:country":"US",
    "sg:address":"315 W Newport St",
    "sg:city":"Glen Lyon",
    "sg:classifiers":[
        {
            "category":"Professional",
            "subcategory":"Employment Agencies",
            "type":"Services"
        }
    ],
    "sg:phone":"+1   ",
    "sg:postcode":"18617",
    "sg:province":"PA",
    "wof:name":"Antoinette B Paczkowski Rn",
    "wof:placetype":"venue"
},
  "geometry": {"coordinates":[-76.086229,41.171767],"type":"Point"}
}