{
  "type": "Feature",
  "properties": {
    "iso:country":"US",
    "sg:address":"162 Bradbury Rd",
    "sg:city":"Brookhaven",
    "sg:classifiers":[
        {
            "category":"Professional",
            "subcategory":"Management & Consulting",
            "type":"Services"
        }
    ],
    "sg:phone":"+1 610 876 9444",
    "sg:postcode":"19015",
    "sg:province":"PA",
    "sg:tags":[
        "association"
    ],
    "wof:name":"Magee Management Co",
    "wof:placetype":"venue"
},
  "geometry": {"coordinates":[-75.389943,39.879253],"type":"Point"}
}