{
  "type": "Feature",
  "properties": {
    "iso:country":"US",
    "sg:address":"985 Airport Rd",
    "sg:city":"Mercer",
    "sg:classifiers":[
        {
            "category":"Farming",
            "subcategory":"Farm",
            "type":"Manufacturing & Wholesale Goods"
        }
    ],
    "sg:phone":"+1   ",
    "sg:postcode":"16137",
    "sg:province":"PA",
    "sg:tags":[
        "crop",
        "general"
    ],
    "wof:name":"Oehlbeck Farm",
    "wof:placetype":"venue"
},
  "geometry": {"coordinates":[-80.206509,41.31314],"type":"Point"}
}