{
  "type": "Feature",
  "properties": {
    "iso:country":"US",
    "sg:address":"337 W Water St",
    "sg:city":"Slippery Rock",
    "sg:classifiers":[
        {
            "category":"Health Services",
            "subcategory":"Doctor",
            "type":"Services"
        }
    ],
    "sg:phone":"+1 724 794 5317",
    "sg:postcode":"16057",
    "sg:province":"PA",
    "sg:tags":[
        "dentist"
    ],
    "wof:name":"David J Duryea DDS",
    "wof:placetype":"venue"
},
  "geometry": {"coordinates":[-80.064841,41.062891],"type":"Point"}
}