{
  "type": "Feature",
  "properties": {
    "addr:full":"228 W College Ave State College PA 16801",
    "addr:housenumber":"228",
    "addr:postcode":"16801",
    "addr:street":"W College Ave",
    "iso:country":"US",
    "sg:address":"228 W College Ave",
    "sg:city":"State College",
    "sg:classifiers":[
        {
            "category":"Government",
            "subcategory":"Office",
            "type":"Public Place"
        }
    ],
    "sg:phone":"+1 814 238 1262",
    "sg:postcode":"16801",
    "sg:province":"PA",
    "sg:tags":[
        "armed",
        "force",
        "recruiting"
    ],
    "wof:name":"US Army Recruiting",
    "wof:placetype":"venue"
},
  "geometry": {"coordinates":[-77.863612,40.792903],"type":"Point"}
}