{
  "type": "Feature",
  "properties": {
    "iso:country":"US",
    "sg:address":"7113 Salem Park Cir",
    "sg:city":"Mechanicsburg",
    "sg:classifiers":[
        {
            "category":"Shopping",
            "subcategory":"Computers & Home Electronics",
            "type":"Retail Goods"
        }
    ],
    "sg:phone":"+1   ",
    "sg:postcode":"17050",
    "sg:province":"PA",
    "wof:name":"C & B Svcs",
    "wof:placetype":"venue"
},
  "geometry": {"coordinates":[-77.001136,40.242703],"type":"Point"}
}