{
  "type": "Feature",
  "properties": {
    "iso:country":"US",
    "sg:address":"5049 Oxford Ave",
    "sg:city":"Philadelphia",
    "sg:classifiers":[
        {
            "category":"Health Services",
            "subcategory":"Doctor",
            "type":"Services"
        }
    ],
    "sg:phone":"+1 215 288 2343",
    "sg:postcode":"19124",
    "sg:province":"PA",
    "sg:tags":[
        "physician",
        "surgeon"
    ],
    "wof:name":"Werthan-Ludolph Neurosurgical Assocs",
    "wof:placetype":"venue"
},
  "geometry": {"coordinates":[-75.084602,40.0229],"type":"Point"}
}