{
  "type": "Feature",
  "properties": {
    "iso:country":"US",
    "sg:address":"7103 Bristol Pike",
    "sg:city":"Levittown",
    "sg:classifiers":[
        {
            "category":"Shopping",
            "subcategory":"Discount & Variety Stores",
            "type":"Retail Goods"
        }
    ],
    "sg:phone":"+1 215 945 5000",
    "sg:postcode":"19057",
    "sg:province":"PA",
    "sg:tags":[
        "car",
        "used",
        "merchandise"
    ],
    "wof:name":"Urglavitch Auto Sales of PA Inc",
    "wof:placetype":"venue"
},
  "geometry": {"coordinates":[-74.83470199999999,40.1287],"type":"Point"}
}