{
  "type": "Feature",
  "properties": {
    "iso:country":"US",
    "sg:address":"360 Steel Way",
    "sg:city":"Lancaster",
    "sg:classifiers":[
        {
            "category":"Wholesale",
            "subcategory":"Electrical",
            "type":"Manufacturing & Wholesale Goods"
        }
    ],
    "sg:phone":"+1   ",
    "sg:postcode":"17601",
    "sg:province":"PA",
    "sg:tags":[
        "equipment"
    ],
    "wof:name":"All Commercial Lighting Sup Co",
    "wof:placetype":"venue"
},
  "geometry": {"coordinates":[-76.323238,40.066942],"type":"Point"}
}