{
  "type": "Feature",
  "properties": {
    "iso:country":"US",
    "sg:address":"32 Gildersleeve St",
    "sg:city":"Wilkes Barre",
    "sg:classifiers":[
        {
            "category":"Government",
            "subcategory":"Office",
            "type":"Public Place"
        }
    ],
    "sg:phone":"+1   ",
    "sg:postcode":"18701",
    "sg:province":"PA",
    "sg:tags":[
        "guard"
    ],
    "wof:name":"Michelle Klinefelter",
    "wof:placetype":"venue"
},
  "geometry": {"coordinates":[-75.888958,41.240857],"type":"Point"}
}