{
  "type": "Feature",
  "properties": {
    "iso:country":"US",
    "sg:address":"58 Michael Rd",
    "sg:city":"Havertown",
    "sg:classifiers":[
        {
            "category":"Manufacturing",
            "subcategory":"Printing",
            "type":"Manufacturing & Wholesale Goods"
        }
    ],
    "sg:phone":"+1 215 953 9975",
    "sg:postcode":"19083",
    "sg:province":"PA",
    "sg:tags":[
        "printer"
    ],
    "wof:name":"All American Printing",
    "wof:placetype":"venue"
},
  "geometry": {"coordinates":[-75.326973,39.987818],"type":"Point"}
}