{
  "type": "Feature",
  "properties": {
    "iso:country":"US",
    "sg:address":"4310 Londonderry Rd",
    "sg:city":"Harrisburg",
    "sg:classifiers":[
        {
            "category":"Health Services",
            "subcategory":"Doctor",
            "type":"Services"
        }
    ],
    "sg:phone":"+1   ",
    "sg:postcode":"17109",
    "sg:province":"PA",
    "sg:tags":[
        "medical"
    ],
    "wof:name":"Pnni",
    "wof:placetype":"venue"
},
  "geometry": {"coordinates":[-76.814002,40.283099],"type":"Point"}
}