{
  "type": "Feature",
  "properties": {
    "iso:country":"US",
    "sg:address":"301 Rohrerstown Rd",
    "sg:city":"Lancaster",
    "sg:classifiers":[
        {
            "category":"Food & Beverages",
            "subcategory":"Meat & Fish",
            "type":"Retail Goods"
        }
    ],
    "sg:phone":"+1 717 293 0351",
    "sg:postcode":"17603",
    "sg:province":"PA",
    "wof:name":"Willie The Butcher's Meat",
    "wof:placetype":"venue"
},
  "geometry": {"coordinates":[-76.362864,40.047492],"type":"Point"}
}