{
  "type": "Feature",
  "properties": {
    "addr:full":"5500 Grand Ave Pittsburgh PA 15225",
    "addr:housenumber":"5500",
    "addr:postcode":"15225",
    "addr:street":"Grand Ave",
    "iso:country":"US",
    "sg:address":"5500 Grand Ave",
    "sg:city":"Pittsburgh",
    "sg:classifiers":[
        {
            "category":"Wholesale",
            "subcategory":"Machinery & Supplies",
            "type":"Manufacturing & Wholesale Goods"
        }
    ],
    "sg:phone":"+1   ",
    "sg:postcode":"15225",
    "sg:province":"PA",
    "sg:tags":[
        "industrial"
    ],
    "wof:name":"Berry Bearing Co",
    "wof:placetype":"venue"
},
  "geometry": {"coordinates":[-80.134111,40.512797],"type":"Point"}
}