{
  "type": "Feature",
  "properties": {
    "addr:full":"2541 E Somerset St Philadelphia PA 19134",
    "addr:housenumber":"2541",
    "addr:postcode":"19134",
    "addr:street":"E Somerset St",
    "iso:country":"US",
    "sg:address":"2541 E Somerset St",
    "sg:city":"Philadelphia",
    "sg:classifiers":[
        {
            "category":"Banks & Credit Unions",
            "subcategory":"Bank",
            "type":"Services"
        }
    ],
    "sg:phone":"+1   ",
    "sg:postcode":"19134",
    "sg:province":"PA",
    "sg:tags":[
        "broker",
        "mortgage"
    ],
    "wof:name":"Miller Mortgage",
    "wof:placetype":"venue"
},
  "geometry": {"coordinates":[-75.113353,39.981136],"type":"Point"}
}