{
  "type": "Feature",
  "properties": {
    "iso:country":"US",
    "sg:address":"3974 Sunnycrest Dr",
    "sg:city":"Harrisburg",
    "sg:classifiers":[
        {
            "category":"Building & Trades",
            "subcategory":"Construction",
            "type":"Services"
        }
    ],
    "sg:phone":"+1 717 564 9293",
    "sg:postcode":"17109",
    "sg:province":"PA",
    "sg:tags":[
        "contractor"
    ],
    "wof:name":"Kenneth Smith Mirror & Glass",
    "wof:placetype":"venue"
},
  "geometry": {"coordinates":[-76.823095,40.275216],"type":"Point"}
}