{
  "type": "Feature",
  "properties": {
    "addr:full":"2845 Holme Ave Philadelphia PA 19152",
    "addr:housenumber":"2845",
    "addr:postcode":"19152",
    "addr:street":"Holme Ave",
    "iso:country":"US",
    "sg:address":"2845 Holme Ave",
    "sg:city":"Philadelphia",
    "sg:classifiers":[
        {
            "category":"Banks & Credit Unions",
            "subcategory":"Bank",
            "type":"Services"
        }
    ],
    "sg:phone":"+1 215 602 8800",
    "sg:postcode":"19152",
    "sg:province":"PA",
    "wof:name":"Beneficial Savings Bank",
    "wof:placetype":"venue"
},
  "geometry": {"coordinates":[-75.033387,40.057111],"type":"Point"}
}