{
  "type": "Feature",
  "properties": {
    "iso:country":"US",
    "sg:address":"2481 State Hwy 173",
    "sg:city":"Cochranton",
    "sg:classifiers":[
        {
            "category":"Farming",
            "subcategory":"Livestock Farm",
            "type":"Manufacturing & Wholesale Goods"
        }
    ],
    "sg:phone":"+1   ",
    "sg:postcode":"16314",
    "sg:province":"PA",
    "sg:tags":[
        "beef",
        "feedlot",
        "cattle"
    ],
    "wof:name":"Steven Lynch",
    "wof:placetype":"venue"
},
  "geometry": {"coordinates":[-80.06120900000001,41.497513],"type":"Point"}
}