{
  "type": "Feature",
  "properties": {
    "iso:country":"US",
    "sg:address":"2823 W Somerset St",
    "sg:city":"Philadelphia",
    "sg:classifiers":[
        {
            "category":"Autos & Motor Vehicles",
            "subcategory":"Automobile Sales",
            "type":"Retail Goods"
        }
    ],
    "sg:phone":"+1 215 229 1137",
    "sg:postcode":"19132",
    "sg:province":"PA",
    "sg:tags":[
        "limo"
    ],
    "wof:name":"R J Bates Limousine and Hearse Service",
    "wof:placetype":"venue"
},
  "geometry": {"coordinates":[-75.177376,39.998688],"type":"Point"}
}