{
  "type": "Feature",
  "properties": {
    "iso:country":"US",
    "sg:address":"3895 Daystar Dr",
    "sg:city":"Doylestown",
    "sg:classifiers":[
        {
            "category":"Food & Beverages",
            "subcategory":"Groceries & Convenience Stores",
            "type":"Retail Goods"
        }
    ],
    "sg:phone":"+1 215 348 5871",
    "sg:postcode":"18902",
    "sg:province":"PA",
    "wof:name":"Vincent Alfieri",
    "wof:placetype":"venue"
},
  "geometry": {"coordinates":[-75.088866,40.355381],"type":"Point"}
}