{
  "type": "Feature",
  "properties": {
    "addr:full":"2903 W Fairview St Allentown PA 18103",
    "addr:housenumber":"2903",
    "addr:postcode":"18103",
    "addr:street":"W Fairview St",
    "iso:country":"US",
    "sg:address":"2903 W Fairview St",
    "sg:city":"Allentown",
    "sg:classifiers":[
        {
            "category":"Insurance",
            "subcategory":"Insurance Agent",
            "type":"Services"
        }
    ],
    "sg:phone":"+1 610 435 9556",
    "sg:postcode":"18103",
    "sg:province":"PA",
    "wof:name":"Kincel & Co",
    "wof:placetype":"venue"
},
  "geometry": {"coordinates":[-75.51356800000001,40.585693],"type":"Point"}
}