{
  "type": "Feature",
  "properties": {
    "iso:country":"US",
    "sg:address":"133 Valley Rd",
    "sg:city":"Ardmore",
    "sg:classifiers":[
        {
            "category":"Conference Center",
            "type":"Public Place"
        }
    ],
    "sg:phone":"+1 215 615 3371",
    "sg:postcode":"19003",
    "sg:province":"PA",
    "sg:tags":[
        "lecture",
        "speakers",
        "seminar"
    ],
    "wof:name":"Linda Jacobs",
    "wof:placetype":"venue"
},
  "geometry": {"coordinates":[-75.29171100000001,40.012879],"type":"Point"}
}