{
  "type": "Feature",
  "properties": {
    "iso:country":"US",
    "sg:address":"457 Davidson Rd",
    "sg:city":"Pittsburgh",
    "sg:classifiers":[
        {
            "category":"Building & Trades",
            "subcategory":"Construction",
            "type":"Services"
        }
    ],
    "sg:phone":"+1 412 793 3870",
    "sg:postcode":"15239",
    "sg:province":"PA",
    "wof:name":"Plum Contracting Inc",
    "wof:placetype":"venue"
},
  "geometry": {"coordinates":[-79.766819,40.471875],"type":"Point"}
}