{
  "type": "Feature",
  "properties": {
    "iso:country":"US",
    "sg:address":"9 Niles Hill Rd",
    "sg:city":"Coudersport",
    "sg:classifiers":[
        {
            "category":"Real Estate",
            "subcategory":"Surveying",
            "type":"Services"
        }
    ],
    "sg:phone":"+1 814 274 7236",
    "sg:postcode":"16915",
    "sg:province":"PA",
    "sg:tags":[
        "surveyor"
    ],
    "wof:name":"M J Menard Surveying",
    "wof:placetype":"venue"
},
  "geometry": {"coordinates":[-78.02102600000001,41.780853],"type":"Point"}
}