{
  "type": "Feature",
  "properties": {
    "addr:full":"211 Smithfield St Pittsburgh PA 15222",
    "addr:housenumber":"211",
    "addr:postcode":"15222",
    "addr:street":"Smithfield St",
    "iso:country":"US",
    "sg:address":"211 Smithfield St",
    "sg:city":"Pittsburgh",
    "sg:classifiers":[
        {
            "category":"Banks & Credit Unions",
            "subcategory":"Investment Brokerage",
            "type":"Services"
        }
    ],
    "sg:phone":"+1   ",
    "sg:postcode":"15222",
    "sg:province":"PA",
    "sg:tags":[
        "security"
    ],
    "wof:name":"H & R Block Financial Advisors",
    "wof:placetype":"venue"
},
  "geometry": {"coordinates":[-79.999977,40.438201],"type":"Point"}
}