{
  "type": "Feature",
  "properties": {
    "iso:country":"US",
    "sg:address":"875 Dekalb Pike",
    "sg:city":"Blue Bell",
    "sg:classifiers":[
        {
            "category":"Personal",
            "subcategory":"Day Spa",
            "type":"Services"
        }
    ],
    "sg:phone":"+1 610 277 8171",
    "sg:postcode":"19422",
    "sg:province":"PA",
    "wof:name":"Dana Spa",
    "wof:placetype":"venue"
},
  "geometry": {"coordinates":[-75.28988699999999,40.167579],"type":"Point"}
}