{
  "type": "Feature",
  "properties": {
    "iso:country":"US",
    "sg:address":"24 N Main St",
    "sg:city":"Milroy",
    "sg:classifiers":[
        {
            "category":"Shopping",
            "type":"Retail Goods"
        }
    ],
    "sg:phone":"+1 717 667 3333",
    "sg:postcode":"17063",
    "sg:province":"PA",
    "sg:tags":[
        "candle"
    ],
    "wof:name":"Open Hearth Candle Co",
    "wof:placetype":"venue"
},
  "geometry": {"coordinates":[-77.59428,40.715791],"type":"Point"}
}