{
  "type": "Feature",
  "properties": {
    "addr:full":"11000 Roosevelt Blvd # 19 Philadelphia PA 19116",
    "addr:housenumber":"11000;19",
    "addr:postcode":"19116",
    "addr:street":"Roosevelt Blvd #",
    "iso:country":"US",
    "sg:address":"11000 Roosevelt Blvd # 19",
    "sg:city":"Philadelphia",
    "sg:classifiers":[
        {
            "category":"Utilities",
            "subcategory":"Telephone",
            "type":"Services"
        },
        {
            "category":"Shopping",
            "subcategory":"Mobile Phones",
            "type":"Retail Goods"
        },
        {
            "category":"Manufacturing",
            "subcategory":"Electronics",
            "type":"Manufacturing & Wholesale Goods"
        },
        {
            "category":"Shopping",
            "subcategory":"Computers & Home Electronics",
            "type":"Retail Goods"
        },
        {
            "category":"Communications",
            "type":"Services"
        }
    ],
    "sg:phone":"+1 215 673 8845",
    "sg:postcode":"19116",
    "sg:province":"PA",
    "sg:tags":[
        "sound",
        "television",
        "theater",
        "supply",
        "system",
        "equipment",
        "radio",
        "cellular",
        "telecommunications-equipment",
        "consumer",
        "store"
    ],
    "sg:website":"http://www.radioshack.com",
    "wof:name":"RadioShack",
    "wof:placetype":"venue"
},
  "geometry": {"coordinates":[-75.00138099999999,40.105208],"type":"Point"}
}