{
  "type": "Feature",
  "properties": {
    "iso:country":"US",
    "sg:address":"2695 MacArthur Rd",
    "sg:city":"Whitehall",
    "sg:classifiers":[
        {
            "category":"Fast Food",
            "type":"Food & Drink"
        }
    ],
    "sg:phone":"+1 610 776 6243",
    "sg:postcode":"18052",
    "sg:province":"PA",
    "wof:name":"Burger King",
    "wof:placetype":"venue"
},
  "geometry": {"coordinates":[-75.4944,40.646301],"type":"Point"}
}