{
  "type": "Feature",
  "properties": {
    "iso:country":"US",
    "sg:address":"55 Crennell Ave",
    "sg:city":"Pittsburgh",
    "sg:classifiers":[
        {
            "category":"Retail",
            "subcategory":"Auto Repair",
            "type":"Services"
        }
    ],
    "sg:phone":"+1 412 921 2757",
    "sg:postcode":"15205",
    "sg:province":"PA",
    "sg:tags":[
        "body",
        "shop"
    ],
    "wof:name":"Sterling Autobody Crafton",
    "wof:placetype":"venue"
},
  "geometry": {"coordinates":[-80.067497,40.435398],"type":"Point"}
}