{
  "type": "Feature",
  "properties": {
    "iso:country":"US",
    "sg:address":"1685 Long Run Rd",
    "sg:city":"Schuylkill Haven",
    "sg:classifiers":[
        {
            "category":"Restaurant",
            "type":"Food & Drink"
        }
    ],
    "sg:phone":"+1 570 739 4888",
    "sg:postcode":"17972",
    "sg:province":"PA",
    "wof:name":"Suglias Express Pizzeria",
    "wof:placetype":"venue"
},
  "geometry": {"coordinates":[-76.216736,40.612176],"type":"Point"}
}