{
  "type": "Feature",
  "properties": {
    "iso:country":"US",
    "sg:address":"320 N Bobbin Mill Ln",
    "sg:city":"Broomall",
    "sg:classifiers":[
        {
            "category":"Wholesale",
            "subcategory":"Construction Materials",
            "type":"Manufacturing & Wholesale Goods"
        }
    ],
    "sg:phone":"+1   ",
    "sg:postcode":"19008",
    "sg:province":"PA",
    "sg:tags":[
        "roofing",
        "siding"
    ],
    "wof:name":"Galway Flashing Company Inc",
    "wof:placetype":"venue"
},
  "geometry": {"coordinates":[-75.36781000000001,39.97474],"type":"Point"}
}