{
  "type": "Feature",
  "properties": {
    "iso:country":"US",
    "sg:address":"515 W Linden St Ste 1",
    "sg:city":"Allentown",
    "sg:classifiers":[
        {
            "category":"Professional",
            "subcategory":"Lawyer & Legal Services",
            "type":"Services"
        }
    ],
    "sg:phone":"+1 610 821 8100",
    "sg:postcode":"18101",
    "sg:province":"PA",
    "sg:tags":[
        "divorce",
        "law",
        "family"
    ],
    "wof:name":"Conrad Erik J Atty",
    "wof:placetype":"venue"
},
  "geometry": {"coordinates":[-75.4692,40.6045],"type":"Point"}
}