{
  "type": "Feature",
  "properties": {
    "iso:country":"US",
    "sg:address":"339 Fawcett Church Rd",
    "sg:city":"Bridgeville",
    "sg:classifiers":[
        {
            "category":"Building & Trades",
            "subcategory":"Construction",
            "type":"Services"
        }
    ],
    "sg:phone":"+1 724 743 3920",
    "sg:postcode":"15017",
    "sg:province":"PA",
    "sg:tags":[
        "boring",
        "drilling",
        "contractor"
    ],
    "wof:name":"Bioni Caisson Drilling",
    "wof:placetype":"venue"
},
  "geometry": {"coordinates":[-80.142169,40.320129],"type":"Point"}
}