{
  "type": "Feature",
  "properties": {
    "iso:country":"US",
    "sg:address":"1431 N Wales Rd",
    "sg:city":"North Wales",
    "sg:classifiers":[
        {
            "category":"Real Estate",
            "subcategory":"Real Estate Agent",
            "type":"Services"
        }
    ],
    "sg:phone":"+1   ",
    "sg:postcode":"19454",
    "sg:province":"PA",
    "wof:name":"Inn Site Hospitality Prpts",
    "wof:placetype":"venue"
},
  "geometry": {"coordinates":[-75.266009,40.225405],"type":"Point"}
}