{
  "type": "Feature",
  "properties": {
    "iso:country":"US",
    "sg:address":"4755 W Lincoln Hwy",
    "sg:city":"Parkesburg",
    "sg:classifiers":[
        {
            "category":"Building & Trades",
            "subcategory":"Construction",
            "type":"Services"
        }
    ],
    "sg:phone":"+1 610 384 6278",
    "sg:postcode":"19365",
    "sg:province":"PA",
    "sg:tags":[
        "paving",
        "contractor"
    ],
    "sg:website":"http://www.harlanconstruction.com",
    "wof:name":"Harlan Construction Co",
    "wof:placetype":"venue"
},
  "geometry": {"coordinates":[-75.951674,39.985457],"type":"Point"}
}