{
  "type": "Feature",
  "properties": {
    "iso:country":"US",
    "sg:address":"70 Main St",
    "sg:city":"Roulette",
    "sg:classifiers":[
        {
            "category":"Freight",
            "type":"Transportation"
        }
    ],
    "sg:phone":"+1 814 544 7745",
    "sg:postcode":"16746",
    "sg:province":"PA",
    "sg:tags":[
        "operator",
        "local",
        "trucking"
    ],
    "wof:name":"Johnson Trucking",
    "wof:placetype":"venue"
},
  "geometry": {"coordinates":[-78.14864300000001,41.779666],"type":"Point"}
}