{
  "type": "Feature",
  "properties": {
    "iso:country":"US",
    "sg:address":"210 Brainerd Blvd",
    "sg:city":"Sharon Hill",
    "sg:classifiers":[
        {
            "category":"Professional",
            "subcategory":"Employment Agencies",
            "type":"Services"
        }
    ],
    "sg:phone":"+1 610 461 1640",
    "sg:postcode":"19079",
    "sg:province":"PA",
    "sg:tags":[
        "modeling",
        "help",
        "supply"
    ],
    "wof:name":"Link Model Management Agency",
    "wof:placetype":"venue"
},
  "geometry": {"coordinates":[-75.276318,39.9043],"type":"Point"}
}