{
  "type": "Feature",
  "properties": {
    "iso:country":"US",
    "sg:address":"401 Schuylkill Rd",
    "sg:city":"Phoenixville",
    "sg:classifiers":[
        {
            "category":"Autos & Motor Vehicles",
            "subcategory":"Automobile Sales",
            "type":"Retail Goods"
        }
    ],
    "sg:phone":"+1 610 933 4277",
    "sg:postcode":"19460",
    "sg:province":"PA",
    "sg:tags":[
        "dealers-used",
        "car",
        "used",
        "cars-wholesale"
    ],
    "wof:name":"J T Pauto Sales And Services Inc",
    "wof:placetype":"venue"
},
  "geometry": {"coordinates":[-75.550815,40.15163],"type":"Point"}
}