{
  "type": "Feature",
  "properties": {
    "iso:country":"US",
    "sg:address":"709 S 5th St",
    "sg:city":"Philadelphia",
    "sg:classifiers":[
        {
            "category":"Health Services",
            "subcategory":"Optometrist",
            "type":"Services"
        }
    ],
    "sg:phone":"+1 215 925 6633",
    "sg:postcode":"19147",
    "sg:province":"PA",
    "sg:tags":[
        "ophthalmologist"
    ],
    "wof:name":"Strong Mortimer J DO",
    "wof:placetype":"venue"
},
  "geometry": {"coordinates":[-75.150902,39.940498],"type":"Point"}
}