{
  "type": "Feature",
  "properties": {
    "addr:full":"777 Park Ave Meadville PA 16335",
    "addr:housenumber":"777",
    "addr:postcode":"16335",
    "addr:street":"Park Ave",
    "iso:country":"US",
    "sg:address":"777 Park Ave",
    "sg:city":"Meadville",
    "sg:classifiers":[
        {
            "category":"Banks & Credit Unions",
            "subcategory":"Bank",
            "type":"Services"
        }
    ],
    "sg:phone":"+1 814 724 2523",
    "sg:postcode":"16335",
    "sg:province":"PA",
    "sg:tags":[
        "state",
        "commercial"
    ],
    "wof:name":"Citizens Bank",
    "wof:placetype":"venue"
},
  "geometry": {"coordinates":[-80.15109099999999,41.641854],"type":"Point"}
}