{
  "type": "Feature",
  "properties": {
    "iso:country":"US",
    "sg:address":"601 Upland Ave",
    "sg:city":"Brookhaven",
    "sg:classifiers":[
        {
            "category":"Health Services",
            "subcategory":"Health Practitioner",
            "type":"Services"
        }
    ],
    "sg:phone":"+1 610 499 1987",
    "sg:postcode":"19015",
    "sg:province":"PA",
    "sg:tags":[
        "nurse",
        "registry"
    ],
    "wof:name":"Nursepro",
    "wof:placetype":"venue"
},
  "geometry": {"coordinates":[-75.37947699999999,39.854689],"type":"Point"}
}