{
  "type": "Feature",
  "properties": {
    "addr:full":"196 S Kersey Rd Kersey PA 15846",
    "addr:housenumber":"196",
    "addr:postcode":"15846",
    "addr:street":"S Kersey Rd",
    "iso:country":"US",
    "sg:address":"196 S Kersey Rd",
    "sg:city":"Kersey",
    "sg:classifiers":[
        {
            "category":"Retail",
            "subcategory":"Auto Repair",
            "type":"Services"
        }
    ],
    "sg:phone":"+1 814 885 6869",
    "sg:postcode":"15846",
    "sg:province":"PA",
    "sg:tags":[
        "automotive"
    ],
    "wof:name":"Dowie Skidsteer & Garage",
    "wof:placetype":"venue"
},
  "geometry": {"coordinates":[-78.598034,41.346605],"type":"Point"}
}