{
  "type": "Feature",
  "properties": {
    "addr:full":"230 S Fairmount Rd Ephrata PA 17522",
    "addr:housenumber":"230",
    "addr:postcode":"17522",
    "addr:street":"S Fairmount Rd",
    "iso:country":"US",
    "sg:address":"230 S Fairmount Rd",
    "sg:city":"Ephrata",
    "sg:classifiers":[
        {
            "category":"Manufacturing",
            "subcategory":"Furniture",
            "type":"Manufacturing & Wholesale Goods"
        },
        {
            "category":"Home & Garden",
            "subcategory":"Furniture",
            "type":"Retail Goods"
        }
    ],
    "sg:phone":"+1 717 354 5657",
    "sg:postcode":"17522",
    "sg:province":"PA",
    "sg:tags":[
        "household",
        "wood",
        "mfg"
    ],
    "wof:name":"Martin's Furniture",
    "wof:placetype":"venue"
},
  "geometry": {"coordinates":[-76.144656,40.124918],"type":"Point"}
}