{
  "type": "Feature",
  "properties": {
    "iso:country":"US",
    "sg:address":"201 Buck Ln",
    "sg:city":"Haverford",
    "sg:classifiers":[
        {
            "category":"Real Estate",
            "subcategory":"Real Estate Operator",
            "type":"Services"
        }
    ],
    "sg:phone":"+1   ",
    "sg:postcode":"19041",
    "sg:province":"PA",
    "sg:tags":[
        "building",
        "apartment"
    ],
    "wof:name":"Darby Brook Associates",
    "wof:placetype":"venue"
},
  "geometry": {"coordinates":[-75.318789,40.009878],"type":"Point"}
}