{
  "type": "Feature",
  "properties": {
    "iso:country":"US",
    "sg:address":"3561 Washington Ave",
    "sg:city":"Finleyville",
    "sg:classifiers":[
        {
            "category":"Wholesale",
            "subcategory":"Hardware",
            "type":"Manufacturing & Wholesale Goods"
        }
    ],
    "sg:phone":"+1 724 348 6880",
    "sg:postcode":"15332",
    "sg:province":"PA",
    "sg:tags":[
        "fastener"
    ],
    "sg:website":"www.thomasfastening.com",
    "wof:name":"Thomas Fastening Systems Inc",
    "wof:placetype":"venue"
},
  "geometry": {"coordinates":[-80.00304199999999,40.252706],"type":"Point"}
}