{
  "type": "Feature",
  "properties": {
    "iso:country":"US",
    "sg:address":"518 W Crawford Ave",
    "sg:city":"Connellsville",
    "sg:classifiers":[
        {
            "category":"Personal",
            "subcategory":"Beauty Salon",
            "type":"Services"
        }
    ],
    "sg:phone":"+1 724 626 8090",
    "sg:postcode":"15425",
    "sg:province":"PA",
    "wof:name":"Staceys Hair Salon",
    "wof:placetype":"venue"
},
  "geometry": {"coordinates":[-79.59557599999999,40.017152],"type":"Point"}
}