{
  "type": "Feature",
  "properties": {
    "iso:country":"US",
    "sg:address":"2428 Bachman Rd",
    "sg:city":"Lancaster",
    "sg:classifiers":[
        {
            "category":"Professional",
            "subcategory":"Lawyer & Legal Services",
            "type":"Services"
        }
    ],
    "sg:phone":"+1 717 687 9311",
    "sg:postcode":"17602",
    "sg:province":"PA",
    "sg:tags":[
        "attorney"
    ],
    "wof:name":"Joyce A Nettke Law Offices",
    "wof:placetype":"venue"
},
  "geometry": {"coordinates":[-76.21242599999999,39.961848],"type":"Point"}
}