{
  "type": "Feature",
  "properties": {
    "addr:full":"102 W 7th Ave Collegeville PA 19426",
    "addr:housenumber":"102",
    "addr:postcode":"19426",
    "addr:street":"W 7Th Ave",
    "iso:country":"US",
    "sg:address":"102 W 7th Ave",
    "sg:city":"Collegeville",
    "sg:classifiers":[
        {
            "category":"Manufacturing",
            "subcategory":"Electronics",
            "type":"Manufacturing & Wholesale Goods"
        }
    ],
    "sg:phone":"+1 610 489 5500",
    "sg:postcode":"19426",
    "sg:province":"PA",
    "sg:tags":[
        "equipment",
        "electronic",
        "supply"
    ],
    "sg:website":"www.hbinstrument.com",
    "wof:name":"H-B Instrument Co",
    "wof:placetype":"venue"
},
  "geometry": {"coordinates":[-75.482215,40.199857],"type":"Point"}
}