{
  "type": "Feature",
  "properties": {
    "addr:full":"95 S Main St Morrisville PA 19067",
    "addr:housenumber":"95",
    "addr:postcode":"19067",
    "addr:street":"S Main St",
    "iso:country":"US",
    "sg:address":"95 S Main St",
    "sg:city":"Morrisville",
    "sg:classifiers":[
        {
            "category":"Banks & Credit Unions",
            "subcategory":"Bank",
            "type":"Services"
        }
    ],
    "sg:phone":"+1 215 000 1111",
    "sg:postcode":"19067",
    "sg:province":"PA",
    "sg:tags":[
        "federal",
        "savings"
    ],
    "wof:name":"Sovereign Bank",
    "wof:placetype":"venue"
},
  "geometry": {"coordinates":[-74.838148,40.241904],"type":"Point"}
}