{
  "type": "Feature",
  "properties": {
    "addr:full":"100 N 18th St Philadelphia PA 19103",
    "addr:housenumber":"100",
    "addr:postcode":"19103",
    "addr:street":"N 18Th St",
    "iso:country":"US",
    "sg:address":"100 N 18th St",
    "sg:city":"Philadelphia",
    "sg:classifiers":[
        {
            "category":"Banks & Credit Unions",
            "subcategory":"Bank",
            "type":"Services"
        }
    ],
    "sg:phone":"+1 215 563 0377",
    "sg:postcode":"19103",
    "sg:province":"PA",
    "wof:name":"Haas David W",
    "wof:placetype":"venue"
},
  "geometry": {"coordinates":[-75.169403,39.955299],"type":"Point"}
}