{
  "type": "Feature",
  "properties": {
    "addr:full":"248 W County Line Rd Hatboro PA 19040",
    "addr:housenumber":"248",
    "addr:postcode":"19040",
    "addr:street":"W County Line Rd",
    "iso:country":"US",
    "sg:address":"248 W County Line Rd",
    "sg:city":"Hatboro",
    "sg:classifiers":[
        {
            "category":"Home & Garden",
            "subcategory":"Building Materials",
            "type":"Retail Goods"
        }
    ],
    "sg:phone":"+1 215 675 8900",
    "sg:postcode":"19040",
    "sg:province":"PA",
    "sg:tags":[
        "mixed",
        "concrete"
    ],
    "wof:name":"Delaware Valley Concrete Co",
    "wof:placetype":"venue"
},
  "geometry": {"coordinates":[-75.096836,40.186395],"type":"Point"}
}