{
  "type": "Feature",
  "properties": {
    "addr:full":"1083 Steffy Rd Stevens PA 17578",
    "addr:housenumber":"1083",
    "addr:postcode":"17578",
    "addr:street":"Steffy Rd",
    "iso:country":"US",
    "sg:address":"1083 Steffy Rd",
    "sg:city":"Stevens",
    "sg:classifiers":[
        {
            "category":"Building & Trades",
            "subcategory":"Construction",
            "type":"Services"
        }
    ],
    "sg:phone":"+1 717 336 0300",
    "sg:postcode":"17578",
    "sg:province":"PA",
    "sg:tags":[
        "contractor"
    ],
    "wof:name":"Burkholder Contracting",
    "wof:placetype":"venue"
},
  "geometry": {"coordinates":[-76.10144099999999,40.193878],"type":"Point"}
}