{
  "type": "Feature",
  "properties": {
    "addr:full":"4634 Woodland Philadelphia PA 19143",
    "addr:housenumber":"4634",
    "addr:postcode":"19143",
    "addr:street":"Woodland",
    "iso:country":"US",
    "sg:address":"4634 Woodland",
    "sg:city":"Philadelphia",
    "sg:classifiers":[
        {
            "category":"Bakery",
            "type":"Food & Drink"
        }
    ],
    "sg:phone":"+1 215 967 1458",
    "sg:postcode":"19143",
    "sg:province":"PA",
    "sg:website":"www.fourworldsbakery.com",
    "wof:name":"Four Worlds Bakery",
    "wof:placetype":"venue"
},
  "geometry": {"coordinates":[-75.21038799999999,39.943133],"type":"Point"}
}