{
  "type": "Feature",
  "properties": {
    "addr:full":"1 W Main St Loysville PA 17057",
    "addr:housenumber":"1",
    "addr:postcode":"17057",
    "addr:street":"W Main St",
    "iso:country":"US",
    "sg:address":"1 W Main St",
    "sg:city":"Loysville",
    "sg:classifiers":[
        {
            "category":"Insurance",
            "subcategory":"Insurance Agent",
            "type":"Services"
        }
    ],
    "sg:phone":"+1 717 789 3720",
    "sg:postcode":"17057",
    "sg:province":"PA",
    "sg:website":"www.bittingins.com",
    "wof:name":"Ray M Bitting Insurance",
    "wof:placetype":"venue"
},
  "geometry": {"coordinates":[-76.731437,40.199738],"type":"Point"}
}