{
  "type": "Feature",
  "properties": {
    "iso:country":"US",
    "sg:address":"20 Eastgate Dr",
    "sg:city":"Grove City",
    "sg:classifiers":[
        {
            "category":"Wholesale",
            "subcategory":"Durable Goods & Equipment",
            "type":"Manufacturing & Wholesale Goods"
        }
    ],
    "sg:phone":"+1 724 458 0700",
    "sg:postcode":"16127",
    "sg:province":"PA",
    "sg:tags":[
        "representative",
        "manufacturer"
    ],
    "wof:name":"J & B Ind Sales Co Inc",
    "wof:placetype":"venue"
},
  "geometry": {"coordinates":[-80.06269,41.169394],"type":"Point"}
}