{
  "type": "Feature",
  "properties": {
    "iso:country":"US",
    "sg:address":"9700 McKnight Rd",
    "sg:city":"Pittsburgh",
    "sg:classifiers":[
        {
            "category":"Cinema",
            "subcategory":"Movie Theater",
            "type":"Entertainment"
        }
    ],
    "sg:phone":"+1 724 935 5770",
    "sg:postcode":"15237",
    "sg:province":"PA",
    "sg:website":"www.ravemotionpictures.com",
    "wof:name":"Rave Movie Theater Pittsburgh North 11",
    "wof:placetype":"venue"
},
  "geometry": {"coordinates":[-80.031197,40.584],"type":"Point"}
}