{
  "type": "Feature",
  "properties": {
    "addr:full":"6200 Derry St Harrisburg PA 17111",
    "addr:housenumber":"6200",
    "addr:postcode":"17111",
    "addr:street":"Derry St",
    "iso:country":"US",
    "sg:address":"6200 Derry St",
    "sg:city":"Harrisburg",
    "sg:classifiers":[
        {
            "category":"Restaurant",
            "type":"Food & Drink"
        }
    ],
    "sg:phone":"+1 717 564 4420",
    "sg:postcode":"17111",
    "sg:province":"PA",
    "wof:name":"Pepper's",
    "wof:placetype":"venue"
},
  "geometry": {"coordinates":[-76.77815099999999,40.264039],"type":"Point"}
}