{
  "type": "Feature",
  "properties": {
    "addr:full":"43 Dewey St Bangor PA 18013",
    "addr:housenumber":"43",
    "addr:postcode":"18013",
    "addr:street":"Dewey St",
    "iso:country":"US",
    "sg:address":"43 Dewey St",
    "sg:city":"Bangor",
    "sg:classifiers":[
        {
            "category":"Building & Trades",
            "subcategory":"Construction",
            "type":"Services"
        }
    ],
    "sg:phone":"+1 610 588 6394",
    "sg:postcode":"18013",
    "sg:province":"PA",
    "sg:tags":[
        "hanging",
        "contractor"
    ],
    "wof:name":"Andrews Custom Painting",
    "wof:placetype":"venue"
},
  "geometry": {"coordinates":[-75.215749,40.876177],"type":"Point"}
}