{
  "type": "Feature",
  "properties": {
    "addr:full":"4163 Lancaster Ave Philadelphia PA 19104",
    "addr:housenumber":"4163",
    "addr:postcode":"19104",
    "addr:street":"Lancaster Ave",
    "iso:country":"US",
    "sg:address":"4163 Lancaster Ave",
    "sg:city":"Philadelphia",
    "sg:classifiers":[
        {
            "category":"Social Services",
            "type":"Services"
        },
        {
            "category":"Shopping",
            "subcategory":"Clothing, Apparel, & Fashions",
            "type":"Retail Goods"
        }
    ],
    "sg:phone":"+1 215 386 3390",
    "sg:postcode":"19104",
    "sg:province":"PA",
    "sg:tags":[
        "organization",
        "welfare"
    ],
    "wof:name":"Maternity Care Cltn Greater",
    "wof:placetype":"venue"
},
  "geometry": {"coordinates":[-75.207306,39.966272],"type":"Point"}
}