{
  "type": "Feature",
  "properties": {
    "addr:full":"398 Sherwood Dr Morrisville PA 19067",
    "addr:housenumber":"398",
    "addr:postcode":"19067",
    "addr:street":"Sherwood Dr",
    "iso:country":"US",
    "sg:address":"398 Sherwood Dr",
    "sg:city":"Morrisville",
    "sg:classifiers":[
        {
            "category":"Professional",
            "subcategory":"Business Services",
            "type":"Services"
        }
    ],
    "sg:phone":"+1   ",
    "sg:postcode":"19067",
    "sg:province":"PA",
    "wof:name":"Byron Reimus & Assoc",
    "wof:placetype":"venue"
},
  "geometry": {"coordinates":[-74.812949,40.21505],"type":"Point"}
}