{
  "type": "Feature",
  "properties": {
    "iso:country":"US",
    "sg:address":"26852 Stockton Corners Rd",
    "sg:city":"Cochranton",
    "sg:classifiers":[
        {
            "category":"Farming",
            "subcategory":"Dairy Farm",
            "type":"Manufacturing & Wholesale Goods"
        }
    ],
    "sg:phone":"+1   ",
    "sg:postcode":"16314",
    "sg:province":"PA",
    "wof:name":"Gum Acres Farm",
    "wof:placetype":"venue"
},
  "geometry": {"coordinates":[-79.998744,41.520855],"type":"Point"}
}