{
  "type": "Feature",
  "properties": {
    "iso:country":"US",
    "sg:address":"699 W Germantown Pike",
    "sg:city":"Norristown",
    "sg:classifiers":[
        {
            "category":"Retail",
            "subcategory":"Portrait Studio",
            "type":"Services"
        },
        {
            "category":"Shopping",
            "subcategory":"Pharmacy",
            "type":"Retail Goods"
        }
    ],
    "sg:phone":"+1 610 630 5861",
    "sg:postcode":"19403",
    "sg:province":"PA",
    "sg:tags":[
        "photography",
        "drugstore",
        "store"
    ],
    "wof:name":"Walgreens Drug Stores",
    "wof:placetype":"venue"
},
  "geometry": {"coordinates":[-75.34699999999999,40.151699],"type":"Point"}
}