{
  "type": "Feature",
  "properties": {
    "iso:country":"US",
    "sg:address":"1352 Woodland Cir",
    "sg:city":"Bethlehem",
    "sg:classifiers":[
        {
            "category":"Wholesale",
            "subcategory":"Metals & Minerals",
            "type":"Manufacturing & Wholesale Goods"
        }
    ],
    "sg:phone":"+1 610 865 0378",
    "sg:postcode":"18017",
    "sg:province":"PA",
    "sg:tags":[
        "steel",
        "warehouse"
    ],
    "wof:name":"Nucor-Yamato Steel Co",
    "wof:placetype":"venue"
},
  "geometry": {"coordinates":[-75.40445099999999,40.662052],"type":"Point"}
}