{
  "type": "Feature",
  "properties": {
    "addr:full":"3409 Oregon St Pittsburgh PA 15204",
    "addr:housenumber":"3409",
    "addr:postcode":"15204",
    "addr:street":"Oregon St",
    "iso:country":"US",
    "sg:address":"3409 Oregon St",
    "sg:city":"Pittsburgh",
    "sg:classifiers":[
        {
            "category":"Manufacturing",
            "subcategory":"Tools & Machinery",
            "type":"Manufacturing & Wholesale Goods"
        }
    ],
    "sg:phone":"+1   ",
    "sg:postcode":"15204",
    "sg:province":"PA",
    "sg:tags":[
        "stone",
        "demolition",
        "mfr",
        "forging"
    ],
    "wof:name":"Wessel Tool & Manufacturing",
    "wof:placetype":"venue"
},
  "geometry": {"coordinates":[-80.053316,40.461228],"type":"Point"}
}