{
  "type": "Feature",
  "properties": {
    "addr:full":"717 State St Erie PA 16501",
    "addr:housenumber":"717",
    "addr:postcode":"16501",
    "addr:street":"State St",
    "iso:country":"US",
    "sg:address":"717 State St",
    "sg:city":"Erie",
    "sg:classifiers":[
        {
            "category":"Banks & Credit Unions",
            "subcategory":"Bank",
            "type":"Services"
        }
    ],
    "sg:phone":"+1 814 871 9700",
    "sg:postcode":"16501",
    "sg:province":"PA",
    "wof:name":"Pnc Bank",
    "wof:placetype":"venue"
},
  "geometry": {"coordinates":[-80.08412800000001,42.127895],"type":"Point"}
}