{
  "type": "Feature",
  "properties": {
    "iso:country":"US",
    "sg:address":"357 Highland Ridge Rd",
    "sg:city":"Marianna",
    "sg:classifiers":[
        {
            "category":"Building & Trades",
            "subcategory":"Cleaning & Sanitation",
            "type":"Services"
        }
    ],
    "sg:phone":"+1 724 267 4049",
    "sg:postcode":"15345",
    "sg:province":"PA",
    "sg:tags":[
        "janitor"
    ],
    "wof:name":"C & R Automotive",
    "wof:placetype":"venue"
},
  "geometry": {"coordinates":[-80.123923,40.044694],"type":"Point"}
}