{
  "type": "Feature",
  "properties": {
    "iso:country":"US",
    "sg:address":"309 E Front St",
    "sg:city":"Berwick",
    "sg:classifiers":[
        {
            "category":"Health Services",
            "subcategory":"Chiropractor",
            "type":"Services"
        }
    ],
    "sg:phone":"+1   ",
    "sg:postcode":"18603",
    "sg:province":"PA",
    "wof:name":"Berwick Chrpractic Hlth Clinic",
    "wof:placetype":"venue"
},
  "geometry": {"coordinates":[-76.228632,41.05725],"type":"Point"}
}