{
  "type": "Feature",
  "properties": {
    "iso:country":"US",
    "sg:address":"150 Farmington Ln",
    "sg:city":"Lancaster",
    "sg:classifiers":[
        {
            "category":"Health Services",
            "subcategory":"Chiropractor",
            "type":"Services"
        }
    ],
    "sg:phone":"+1   ",
    "sg:postcode":"17601",
    "sg:province":"PA",
    "wof:name":"Granite Run Chiropractic",
    "wof:placetype":"venue"
},
  "geometry": {"coordinates":[-76.318134,40.073019],"type":"Point"}
}