{
  "type": "Feature",
  "properties": {
    "addr:full":"8437 Sharon-Mercer Rd Mercer PA 16137",
    "addr:housenumber":"8437",
    "addr:postcode":"16137",
    "addr:street":"Sharon-Mercer Rd",
    "iso:country":"US",
    "sg:address":"8437 Sharon-Mercer Rd",
    "sg:city":"Mercer",
    "sg:classifiers":[
        {
            "category":"Home & Garden",
            "subcategory":"Garden Supply",
            "type":"Retail Goods"
        }
    ],
    "sg:phone":"+1   ",
    "sg:postcode":"16137",
    "sg:province":"PA",
    "sg:tags":[
        "operator",
        "local",
        "trucking"
    ],
    "wof:name":"Rt 62 Supply",
    "wof:placetype":"venue"
},
  "geometry": {"coordinates":[-80.25743300000001,41.226188],"type":"Point"}
}