{
  "type": "Feature",
  "properties": {
    "iso:country":"US",
    "sg:address":"405 W Main St",
    "sg:city":"Plymouth",
    "sg:classifiers":[
        {
            "category":"Insurance",
            "subcategory":"Insurance Agent",
            "type":"Services"
        }
    ],
    "sg:phone":"+1 570 779 9555",
    "sg:postcode":"18651",
    "sg:province":"PA",
    "wof:name":"Gawat, F J Insurance Agency",
    "wof:placetype":"venue"
},
  "geometry": {"coordinates":[-75.953591,41.238456],"type":"Point"}
}