{
  "type": "Feature",
  "properties": {
    "iso:country":"US",
    "sg:address":"445 Phoenix Dr",
    "sg:city":"Chambersburg",
    "sg:classifiers":[
        {
            "category":"Insurance",
            "subcategory":"Insurance Agent",
            "type":"Services"
        }
    ],
    "sg:phone":"+1 717 263 4267",
    "sg:postcode":"17201",
    "sg:province":"PA",
    "wof:name":"Erickson Financial",
    "wof:placetype":"venue"
},
  "geometry": {"coordinates":[-77.636414,39.934844],"type":"Point"}
}