{
  "type": "Feature",
  "properties": {
    "iso:country":"US",
    "sg:address":"1314 Justus Blvd",
    "sg:city":"Clarks Summit",
    "sg:classifiers":[
        {
            "category":"Retail",
            "subcategory":"Animal Services",
            "type":"Services"
        }
    ],
    "sg:phone":"+1 570 586 0078",
    "sg:postcode":"18411",
    "sg:province":"PA",
    "sg:tags":[
        "pet",
        "grooming",
        "washing"
    ],
    "wof:name":"Shear Elegance Grooming",
    "wof:placetype":"venue"
},
  "geometry": {"coordinates":[-75.64022799999999,41.502728],"type":"Point"}
}