{
  "type": "Feature",
  "properties": {
    "iso:country":"US",
    "sg:address":"128 Eagleview Blvd",
    "sg:city":"Exton",
    "sg:classifiers":[
        {
            "category":"Shopping",
            "subcategory":"Hobbies, Toys, & Games",
            "type":"Retail Goods"
        }
    ],
    "sg:phone":"+1   ",
    "sg:postcode":"19341",
    "sg:province":"PA",
    "sg:tags":[
        "educational"
    ],
    "wof:name":"Learning Express of Exton",
    "wof:placetype":"venue"
},
  "geometry": {"coordinates":[-75.664089,40.054176],"type":"Point"}
}