{
  "type": "Feature",
  "properties": {
    "addr:full":"7125 Saltsburg Rd Pittsburgh PA 15235",
    "addr:housenumber":"7125",
    "addr:postcode":"15235",
    "addr:street":"Saltsburg Rd",
    "iso:country":"US",
    "sg:address":"7125 Saltsburg Rd",
    "sg:city":"Pittsburgh",
    "sg:classifiers":[
        {
            "category":"Insurance",
            "subcategory":"Insurance Agent",
            "type":"Services"
        }
    ],
    "sg:phone":"+1 412 798 8822",
    "sg:postcode":"15235",
    "sg:province":"PA",
    "sg:tags":[
        "processing"
    ],
    "wof:name":"Independent Billing Svc",
    "wof:placetype":"venue"
},
  "geometry": {"coordinates":[-79.791038,40.47507],"type":"Point"}
}