{
  "type": "Feature",
  "properties": {
    "iso:country":"US",
    "sg:address":"2917 N Broad St",
    "sg:city":"Philadelphia",
    "sg:classifiers":[
        {
            "category":"Professional",
            "subcategory":"Lawyer & Legal Services",
            "type":"Services"
        }
    ],
    "sg:phone":"+1 215 229 1193",
    "sg:postcode":"19132",
    "sg:province":"PA",
    "sg:tags":[
        "attorney"
    ],
    "wof:name":"Frazier-Lyde & Assoc",
    "wof:placetype":"venue"
},
  "geometry": {"coordinates":[-75.153831,39.996956],"type":"Point"}
}