{
  "type": "Feature",
  "properties": {
    "addr:full":"4158 Kistler Rd Schnecksville PA 18078",
    "addr:housenumber":"4158",
    "addr:postcode":"18078",
    "addr:street":"Kistler Rd",
    "iso:country":"US",
    "sg:address":"4158 Kistler Rd",
    "sg:city":"Schnecksville",
    "sg:classifiers":[
        {
            "category":"Building & Trades",
            "subcategory":"Construction",
            "type":"Services"
        }
    ],
    "sg:phone":"+1   ",
    "sg:postcode":"18078",
    "sg:province":"PA",
    "sg:tags":[
        "excavation",
        "contractor"
    ],
    "wof:name":"Hoppy Excavating Inc",
    "wof:placetype":"venue"
},
  "geometry": {"coordinates":[-75.653559,40.64346],"type":"Point"}
}