{
  "type": "Feature",
  "properties": {
    "iso:country":"US",
    "sg:address":"755 Mount Royal Ave",
    "sg:city":"Langhorne",
    "sg:classifiers":[
        {
            "category":"Farming",
            "subcategory":"Farm & Veterinary Services",
            "type":"Manufacturing & Wholesale Goods"
        }
    ],
    "sg:phone":"+1   ",
    "sg:postcode":"19047",
    "sg:province":"PA",
    "sg:tags":[
        "management"
    ],
    "wof:name":"Wilbur Anderson Farm",
    "wof:placetype":"venue"
},
  "geometry": {"coordinates":[-74.92829399999999,40.163232],"type":"Point"}
}