{
  "type": "Feature",
  "properties": {
    "iso:country":"US",
    "sg:address":"715 Philadelphia St",
    "sg:city":"Indiana",
    "sg:classifiers":[
        {
            "category":"Retail",
            "subcategory":"Laundry & Dry Cleaning",
            "type":"Services"
        }
    ],
    "sg:phone":"+1 724 349 7015",
    "sg:postcode":"15701",
    "sg:province":"PA",
    "sg:tags":[
        "drycleaning",
        "plant",
        "except",
        "rug"
    ],
    "wof:name":"One Hour Downtown Dry Cleaners",
    "wof:placetype":"venue"
},
  "geometry": {"coordinates":[-79.154516,40.623049],"type":"Point"}
}