{
  "type": "Feature",
  "properties": {
    "addr:full":"65 Rockwood Ave Oil City PA 16301",
    "addr:housenumber":"65",
    "addr:postcode":"16301",
    "addr:street":"Rockwood Ave",
    "iso:country":"US",
    "sg:address":"65 Rockwood Ave",
    "sg:city":"Oil City",
    "sg:classifiers":[
        {
            "category":"Building & Trades",
            "subcategory":"Construction",
            "type":"Services"
        }
    ],
    "sg:phone":"+1   ",
    "sg:postcode":"16301",
    "sg:province":"PA",
    "sg:tags":[
        "contractor"
    ],
    "wof:name":"Lorenz Antenna",
    "wof:placetype":"venue"
},
  "geometry": {"coordinates":[-79.674397,41.444668],"type":"Point"}
}