{
  "type": "Feature",
  "properties": {
    "iso:country":"US",
    "sg:address":"397 W Ridge Pike",
    "sg:city":"Royersford",
    "sg:classifiers":[
        {
            "category":"Health Services",
            "subcategory":"Doctor",
            "type":"Services"
        },
        {
            "category":"Health Services",
            "subcategory":"Dentist",
            "type":"Services"
        }
    ],
    "sg:phone":"+1 610 409 2644",
    "sg:postcode":"19468",
    "sg:province":"PA",
    "sg:tags":[
        "dentists-oral",
        "physician",
        "maxillofacial",
        "dental",
        "surgeons",
        "clinic",
        "surgery",
        "oral"
    ],
    "wof:name":"Adolf Vanessa DMD",
    "wof:placetype":"venue"
},
  "geometry": {"coordinates":[-75.52278099999999,40.23136],"type":"Point"}
}