{
  "type": "Feature",
  "properties": {
    "addr:full":"2856 Galloway Ave Abington PA 19001",
    "addr:housenumber":"2856",
    "addr:postcode":"19001",
    "addr:street":"Galloway Ave",
    "iso:country":"US",
    "sg:address":"2856 Galloway Ave",
    "sg:city":"Abington",
    "sg:classifiers":[
        {
            "category":"Banks & Credit Unions",
            "subcategory":"Investment Brokerage",
            "type":"Services"
        }
    ],
    "sg:phone":"+1 215 657 4191",
    "sg:postcode":"19001",
    "sg:province":"PA",
    "sg:tags":[
        "advisory",
        "financial"
    ],
    "wof:name":"B & B First Capitol Financial",
    "wof:placetype":"venue"
},
  "geometry": {"coordinates":[-75.138473,40.140994],"type":"Point"}
}