{
  "type": "Feature",
  "properties": {
    "iso:country":"US",
    "sg:address":"200 Kendall Ave",
    "sg:city":"Bellevue",
    "sg:classifiers":[
        {
            "category":"Professional",
            "subcategory":"Engineering",
            "type":"Services"
        }
    ],
    "sg:phone":"+1 412 761 7757",
    "sg:postcode":"15202",
    "sg:province":"PA",
    "sg:tags":[
        "engineer"
    ],
    "wof:name":"Thermal Engineering Intl",
    "wof:placetype":"venue"
},
  "geometry": {"coordinates":[-80.05402599999999,40.486397],"type":"Point"}
}