{
  "type": "Feature",
  "properties": {
    "addr:full":"5 York Galleria York PA 17402",
    "addr:housenumber":"5",
    "addr:postcode":"17402",
    "addr:street":"York Galleria",
    "iso:country":"US",
    "sg:address":"5 York Galleria",
    "sg:city":"York",
    "sg:classifiers":[
        {
            "category":"Professional",
            "subcategory":"Accounting & Tax Preparation",
            "type":"Services"
        }
    ],
    "sg:phone":"+1 717 751 6167",
    "sg:postcode":"17402",
    "sg:province":"PA",
    "sg:tags":[
        "return",
        "filing"
    ],
    "wof:name":"H & R Block Tax Svc",
    "wof:placetype":"venue"
},
  "geometry": {"coordinates":[-76.676677,39.989543],"type":"Point"}
}