{
  "type": "Feature",
  "properties": {
    "iso:country":"US",
    "sg:address":"410 Camp Hill Byp",
    "sg:city":"Camp Hill",
    "sg:classifiers":[
        {
            "category":"Retail",
            "subcategory":"Repair Shop",
            "type":"Services"
        }
    ],
    "sg:phone":"+1   ",
    "sg:postcode":"17011",
    "sg:province":"PA",
    "sg:tags":[
        "picture",
        "framing",
        "artwork"
    ],
    "wof:name":"Artworks",
    "wof:placetype":"venue"
},
  "geometry": {"coordinates":[-76.933286,40.234677],"type":"Point"}
}