{
  "type": "Feature",
  "properties": {
    "iso:country":"US",
    "sg:address":"111 N Main St",
    "sg:city":"Ashley",
    "sg:classifiers":[
        {
            "category":"Restaurant",
            "type":"Food & Drink"
        }
    ],
    "sg:phone":"+1 570 824 8747",
    "sg:postcode":"18706",
    "sg:province":"PA",
    "sg:tags":[
        "eating"
    ],
    "wof:name":"Gonda's Hoagies Wings & Spirit",
    "wof:placetype":"venue"
},
  "geometry": {"coordinates":[-75.897353,41.21703],"type":"Point"}
}