{
  "type": "Feature",
  "properties": {
    "addr:full":"29 E Main St Bloomsburg PA 17815",
    "addr:housenumber":"29",
    "addr:postcode":"17815",
    "addr:street":"E Main St",
    "iso:country":"US",
    "sg:address":"29 E Main St",
    "sg:city":"Bloomsburg",
    "sg:classifiers":[
        {
            "category":"Professional",
            "subcategory":"Management & Consulting",
            "type":"Services"
        }
    ],
    "sg:phone":"+1 570 784 5566",
    "sg:postcode":"17815",
    "sg:province":"PA",
    "sg:tags":[
        "consultant",
        "business"
    ],
    "sg:website":"www.bloominstitute.com",
    "wof:name":"Bloom Institute Inc",
    "wof:placetype":"venue"
},
  "geometry": {"coordinates":[-76.45614399999999,41.003374],"type":"Point"}
}