{
  "type": "Feature",
  "properties": {
    "iso:country":"US",
    "sg:address":"112 Lindbergh Ave",
    "sg:city":"Broomall",
    "sg:classifiers":[
        {
            "category":"Wholesale",
            "subcategory":"Electrical",
            "type":"Manufacturing & Wholesale Goods"
        }
    ],
    "sg:phone":"+1   ",
    "sg:postcode":"19008",
    "sg:province":"PA",
    "sg:tags":[
        "control",
        "industrial"
    ],
    "wof:name":"Yokogawa Corporation America",
    "wof:placetype":"venue"
},
  "geometry": {"coordinates":[-75.345691,39.984985],"type":"Point"}
}