{
  "type": "Feature",
  "properties": {
    "iso:country":"US",
    "sg:address":"35 W Maple St",
    "sg:city":"Hazleton",
    "sg:classifiers":[
        {
            "category":"Government",
            "subcategory":"Office",
            "type":"Public Place"
        }
    ],
    "sg:phone":"+1   ",
    "sg:postcode":"18201",
    "sg:province":"PA",
    "sg:tags":[
        "regional"
    ],
    "wof:name":"Bureau of Mediation",
    "wof:placetype":"venue"
},
  "geometry": {"coordinates":[-75.97468600000001,40.955952],"type":"Point"}
}