{
  "type": "Feature",
  "properties": {
    "iso:country":"US",
    "sg:address":"2200 Saint James St",
    "sg:city":"Philadelphia",
    "sg:classifiers":[
        {
            "category":"Professional",
            "subcategory":"Lawyer & Legal Services",
            "type":"Services"
        }
    ],
    "sg:phone":"+1 215 569 2000",
    "sg:postcode":"19103",
    "sg:province":"PA",
    "wof:name":"Nearey Bernard J Attorney",
    "wof:placetype":"venue"
},
  "geometry": {"coordinates":[-75.17759700000001,39.950401],"type":"Point"}
}