{
  "type": "Feature",
  "properties": {
    "addr:full":"1300 Leonard St Clearfield PA 16830",
    "addr:housenumber":"1300",
    "addr:postcode":"16830",
    "addr:street":"Leonard St",
    "iso:country":"US",
    "sg:address":"1300 Leonard St",
    "sg:city":"Clearfield",
    "sg:classifiers":[
        {
            "category":"Health Services",
            "subcategory":"Nursing And Care Facility",
            "type":"Services"
        }
    ],
    "sg:phone":"+1 814 765 0300",
    "sg:postcode":"16830",
    "sg:province":"PA",
    "sg:tags":[
        "home",
        "convalescent"
    ],
    "wof:name":"Colonial Courtyard",
    "wof:placetype":"venue"
},
  "geometry": {"coordinates":[-78.41083399999999,41.024174],"type":"Point"}
}