{
  "type": "Feature",
  "properties": {
    "iso:country":"US",
    "sg:address":"161 Seigfried Rd",
    "sg:city":"Bernville",
    "sg:classifiers":[
        {
            "category":"Farming",
            "subcategory":"Orchard",
            "type":"Manufacturing & Wholesale Goods"
        }
    ],
    "sg:phone":"+1 610 488 1461",
    "sg:postcode":"19506",
    "sg:province":"PA",
    "wof:name":"Elwood Moyer",
    "wof:placetype":"venue"
},
  "geometry": {"coordinates":[-76.2009,40.4628],"type":"Point"}
}