{
  "type": "Feature",
  "properties": {
    "iso:country":"US",
    "sg:address":"5 Madonna Ln",
    "sg:city":"Broomall",
    "sg:classifiers":[
        {
            "category":"Wholesale",
            "subcategory":"Chemicals & Plastics",
            "type":"Manufacturing & Wholesale Goods"
        }
    ],
    "sg:phone":"+1 610 325 7754",
    "sg:postcode":"19008",
    "sg:province":"PA",
    "sg:tags":[
        "absorbent"
    ],
    "wof:name":"Step-Dri Inc",
    "wof:placetype":"venue"
},
  "geometry": {"coordinates":[-75.362808,39.96835],"type":"Point"}
}