{
  "type": "Feature",
  "properties": {
    "iso:country":"US",
    "sg:address":"812 S 5th St",
    "sg:city":"Philadelphia",
    "sg:classifiers":[
        {
            "category":"Professional",
            "subcategory":"Management & Consulting",
            "type":"Services"
        }
    ],
    "sg:phone":"+1   ",
    "sg:postcode":"19147",
    "sg:province":"PA",
    "wof:name":"Totem Marketing",
    "wof:placetype":"venue"
},
  "geometry": {"coordinates":[-75.151657,39.938214],"type":"Point"}
}