{
  "type": "Feature",
  "properties": {
    "iso:country":"US",
    "sg:address":"1301 Beech St",
    "sg:city":"Scranton",
    "sg:classifiers":[
        {
            "category":"Organizations",
            "subcategory":"Membership Organization",
            "type":"Services"
        }
    ],
    "sg:phone":"+1 570 347 3746",
    "sg:postcode":"18505",
    "sg:province":"PA",
    "wof:name":"Irish Cultural Society",
    "wof:placetype":"venue"
},
  "geometry": {"coordinates":[-75.654173,41.388039],"type":"Point"}
}