{
  "type": "Feature",
  "properties": {
    "iso:country":"US",
    "sg:address":"438 Faith Dr",
    "sg:city":"Catasauqua",
    "sg:classifiers":[
        {
            "category":"Coffee & Tea",
            "type":"Food & Drink"
        },
        {
            "category":"Restaurant",
            "type":"Food & Drink"
        }
    ],
    "sg:phone":"+1 610 443 0596",
    "sg:postcode":"18032",
    "sg:province":"PA",
    "sg:tags":[
        "espresso"
    ],
    "wof:name":"Sparacello Caf",
    "wof:placetype":"venue"
},
  "geometry": {"coordinates":[-75.46090700000001,40.650594],"type":"Point"}
}