{
  "type": "Feature",
  "properties": {
    "iso:country":"US",
    "sg:address":"569 Furnace Hills Pike",
    "sg:city":"Lititz",
    "sg:classifiers":[
        {
            "category":"Wholesale",
            "subcategory":"Construction Materials",
            "type":"Manufacturing & Wholesale Goods"
        }
    ],
    "sg:phone":"+1   ",
    "sg:postcode":"17543",
    "sg:province":"PA",
    "wof:name":"East Side Frames",
    "wof:placetype":"venue"
},
  "geometry": {"coordinates":[-76.30823100000001,40.170491],"type":"Point"}
}