{
  "type": "Feature",
  "properties": {
    "iso:country":"US",
    "sg:address":"33 Deerfield Way",
    "sg:city":"Scotrun",
    "sg:classifiers":[
        {
            "category":"Building & Trades",
            "subcategory":"Construction",
            "type":"Services"
        }
    ],
    "sg:phone":"+1   ",
    "sg:postcode":"18355",
    "sg:province":"PA",
    "sg:tags":[
        "contractor"
    ],
    "wof:name":"Sayre Roofing",
    "wof:placetype":"venue"
},
  "geometry": {"coordinates":[-75.32021400000001,41.073309],"type":"Point"}
}