{
  "type": "Feature",
  "properties": {
    "iso:country":"US",
    "sg:address":"301 E City Ave Ste 100",
    "sg:city":"Bala Cynwyd",
    "sg:classifiers":[
        {
            "category":"Health Services",
            "subcategory":"Doctor",
            "type":"Services"
        }
    ],
    "sg:phone":"+1 610 660 8864",
    "sg:postcode":"19004",
    "sg:province":"PA",
    "wof:name":"Bralow Scott DO",
    "wof:placetype":"venue"
},
  "geometry": {"coordinates":[-75.21819600000001,40.005725],"type":"Point"}
}