{
  "type": "Feature",
  "properties": {
    "iso:country":"US",
    "sg:address":"12 N Creamery Ave",
    "sg:city":"Middleburg",
    "sg:classifiers":[
        {
            "category":"Recreation",
            "type":"Entertainment"
        }
    ],
    "sg:phone":"+1 570 837 0649",
    "sg:postcode":"17842",
    "sg:province":"PA",
    "sg:tags":[
        "skating",
        "rink"
    ],
    "wof:name":"Criss-Cross",
    "wof:placetype":"venue"
},
  "geometry": {"coordinates":[-77.035116,40.790606],"type":"Point"}
}