{
  "type": "Feature",
  "properties": {
    "iso:country":"US",
    "sg:address":"111 S Centre St",
    "sg:city":"Pottsville",
    "sg:classifiers":[
        {
            "category":"Health Services",
            "subcategory":"Doctor",
            "type":"Services"
        }
    ],
    "sg:phone":"+1   ",
    "sg:postcode":"17901",
    "sg:province":"PA",
    "wof:name":"DArco Daniel J MD",
    "wof:placetype":"venue"
},
  "geometry": {"coordinates":[-76.194146,40.683839],"type":"Point"}
}