{
  "type": "Feature",
  "properties": {
    "iso:country":"US",
    "sg:address":"3201 Schoenersville Rd",
    "sg:city":"Bethlehem",
    "sg:classifiers":[
        {
            "category":"Food & Beverages",
            "subcategory":"Groceries & Convenience Stores",
            "type":"Retail Goods"
        }
    ],
    "sg:phone":"+1 610 264 0947",
    "sg:postcode":"18017",
    "sg:province":"PA",
    "sg:website":"www.sheetz.com",
    "wof:name":"Sheetz Inc",
    "wof:placetype":"venue"
},
  "geometry": {"coordinates":[-75.416495,40.655511],"type":"Point"}
}