{
  "type": "Feature",
  "properties": {
    "addr:full":"117 S 18th St Philadelphia PA 19103",
    "addr:housenumber":"117",
    "addr:postcode":"19103",
    "addr:street":"S 18Th St",
    "iso:country":"US",
    "sg:address":"117 S 18th St",
    "sg:city":"Philadelphia",
    "sg:classifiers":[
        {
            "category":"Home & Garden",
            "subcategory":"Building Materials",
            "type":"Retail Goods"
        },
        {
            "category":"Building & Trades",
            "subcategory":"Construction",
            "type":"Services"
        },
        {
            "category":"Military Area",
            "subcategory":"Armory",
            "type":"Public Place"
        }
    ],
    "sg:phone":"+1 215 665 1509",
    "sg:postcode":"19103",
    "sg:province":"PA",
    "sg:tags":[
        "repair",
        "fence-sales",
        "fence",
        "contractor"
    ],
    "sg:website":"http://www.mandtbank.com",
    "wof:name":"M&T",
    "wof:placetype":"venue"
},
  "geometry": {"coordinates":[-75.170464,39.95116],"type":"Point"}
}