{
  "type": "Feature",
  "properties": {
    "iso:country":"US",
    "sg:address":"578 Main St",
    "sg:city":"Slatington",
    "sg:classifiers":[
        {
            "category":"Retail",
            "subcategory":"Repair Shop",
            "type":"Services"
        }
    ],
    "sg:phone":"+1 610 262 6184",
    "sg:postcode":"18080",
    "sg:province":"PA",
    "sg:tags":[
        "television",
        "radio"
    ],
    "wof:name":"Frank G Schwartz Radio & TV",
    "wof:placetype":"venue"
},
  "geometry": {"coordinates":[-75.613016,40.751788],"type":"Point"}
}