{
  "type": "Feature",
  "properties": {
    "iso:country":"US",
    "sg:address":"900 Limekiln Rd",
    "sg:city":"New Cumberland",
    "sg:classifiers":[
        {
            "category":"Building & Trades",
            "subcategory":"Landscaping Services",
            "type":"Services"
        }
    ],
    "sg:phone":"+1 717 774 6011",
    "sg:postcode":"17070",
    "sg:province":"PA",
    "sg:tags":[
        "lawn",
        "design",
        "garden",
        "landscape"
    ],
    "sg:website":"www.rosehillfarmgreenhouses.com",
    "wof:name":"Rose Hill Farm Greenhouses",
    "wof:placetype":"venue"
},
  "geometry": {"coordinates":[-76.903532,40.202769],"type":"Point"}
}