{
  "type": "Feature",
  "properties": {
    "iso:country":"US",
    "sg:address":"74 S Center St",
    "sg:city":"Coal Township",
    "sg:classifiers":[
        {
            "category":"Retail",
            "subcategory":"Auto Repair",
            "type":"Services"
        }
    ],
    "sg:phone":"+1 570 648 8368",
    "sg:postcode":"17866",
    "sg:province":"PA",
    "sg:tags":[
        "repairing",
        "automobile",
        "general"
    ],
    "wof:name":"Dimmicks Garage",
    "wof:placetype":"venue"
},
  "geometry": {"coordinates":[-76.566441,40.7995],"type":"Point"}
}