{
  "type": "Feature",
  "properties": {
    "iso:country":"US",
    "sg:address":"4 Sherwood Dr",
    "sg:city":"Enola",
    "sg:classifiers":[
        {
            "category":"Retail",
            "subcategory":"Repair Shop",
            "type":"Services"
        }
    ],
    "sg:phone":"+1 717 732 2076",
    "sg:postcode":"17025",
    "sg:province":"PA",
    "sg:tags":[
        "picture",
        "coffee",
        "tea",
        "monogramming",
        "wood",
        "framing",
        "embroidery",
        "custom"
    ],
    "wof:name":"Walters Embroidery",
    "wof:placetype":"venue"
},
  "geometry": {"coordinates":[-76.952797,40.2855],"type":"Point"}
}