{
  "type": "Feature",
  "properties": {
    "iso:country":"US",
    "sg:address":"330 Sims St",
    "sg:city":"Ellwood City",
    "sg:classifiers":[
        {
            "category":"Retail",
            "subcategory":"Auto Repair",
            "type":"Services"
        }
    ],
    "sg:phone":"+1 724 752 2511",
    "sg:postcode":"16117",
    "sg:province":"PA",
    "sg:tags":[
        "repairing",
        "automobile"
    ],
    "wof:name":"Beatrice's Ewing Park Svc Sta",
    "wof:placetype":"venue"
},
  "geometry": {"coordinates":[-80.274415,40.864048],"type":"Point"}
}