{
  "type": "Feature",
  "properties": {
    "addr:full":"1789 N Keyser Ave Scranton PA 18508",
    "addr:housenumber":"1789",
    "addr:postcode":"18508",
    "addr:street":"N Keyser Ave",
    "iso:country":"US",
    "sg:address":"1789 N Keyser Ave",
    "sg:city":"Scranton",
    "sg:classifiers":[
        {
            "category":"Health Services",
            "subcategory":"Medical Lab",
            "type":"Services"
        }
    ],
    "sg:phone":"+1 570 558 1620",
    "sg:postcode":"18508",
    "sg:province":"PA",
    "sg:tags":[
        "laboratory"
    ],
    "wof:name":"Pennant Laboratory Svc",
    "wof:placetype":"venue"
},
  "geometry": {"coordinates":[-75.668795,41.445078],"type":"Point"}
}