{
  "type": "Feature",
  "properties": {
    "iso:country":"US",
    "sg:address":"1517 Mount Rose Ave",
    "sg:city":"York",
    "sg:classifiers":[
        {
            "category":"Professional",
            "subcategory":"Computer Services",
            "type":"Services"
        }
    ],
    "sg:phone":"+1 717 845 1165",
    "sg:postcode":"17403",
    "sg:province":"PA",
    "sg:tags":[
        "consultant",
        "designer"
    ],
    "wof:name":"Office Ingenuity",
    "wof:placetype":"venue"
},
  "geometry": {"coordinates":[-76.694632,39.958885],"type":"Point"}
}