{
  "type": "Feature",
  "properties": {
    "addr:full":"1916 Lincoln Hwy E Lancaster PA 17602",
    "addr:housenumber":"1916",
    "addr:postcode":"17602",
    "addr:street":"Lincoln Hwy E",
    "iso:country":"US",
    "sg:address":"1916 Lincoln Hwy E",
    "sg:city":"Lancaster",
    "sg:classifiers":[
        {
            "category":"Social Services",
            "subcategory":"Child Care",
            "type":"Services"
        }
    ],
    "sg:phone":"+1 717 397 5717",
    "sg:postcode":"17602",
    "sg:province":"PA",
    "sg:tags":[
        "kindergarten",
        "academic",
        "school",
        "day"
    ],
    "wof:name":"Parent & Preschool Center",
    "wof:placetype":"venue"
},
  "geometry": {"coordinates":[-76.250102,40.033957],"type":"Point"}
}