{
  "type": "Feature",
  "properties": {
    "addr:full":"14959 Keesey Ct Stewartstown PA 17363",
    "addr:postcode":"14959;17363",
    "addr:street":"Keesey Ct",
    "iso:country":"US",
    "sg:address":"14959 Keesey Ct",
    "sg:city":"Stewartstown",
    "sg:classifiers":[
        {
            "category":"Building & Trades",
            "subcategory":"Construction",
            "type":"Services"
        }
    ],
    "sg:phone":"+1   ",
    "sg:postcode":"17363",
    "sg:province":"PA",
    "sg:tags":[
        "house"
    ],
    "wof:name":"D W G Associates",
    "wof:placetype":"venue"
},
  "geometry": {"coordinates":[-76.576016,39.797445],"type":"Point"}
}