{
  "type": "Feature",
  "properties": {
    "iso:country":"US",
    "sg:address":"814 E Pittsburgh St",
    "sg:city":"Greensburg",
    "sg:classifiers":[
        {
            "category":"Professional",
            "type":"Services"
        }
    ],
    "sg:phone":"+1 724 834 6990",
    "sg:postcode":"15601",
    "sg:province":"PA",
    "sg:tags":[
        "establishment"
    ],
    "wof:name":"Tci Of Greensburg",
    "wof:placetype":"venue"
},
  "geometry": {"coordinates":[-79.524277,40.302118],"type":"Point"}
}