{
  "type": "Feature",
  "properties": {
    "addr:full":"2199 Cortland Rd Schellsburg PA 15559",
    "addr:housenumber":"2199",
    "addr:postcode":"15559",
    "addr:street":"Cortland Rd",
    "iso:country":"US",
    "sg:address":"2199 Cortland Rd",
    "sg:city":"Schellsburg",
    "sg:classifiers":[
        {
            "category":"Government",
            "subcategory":"Office",
            "type":"Public Place"
        }
    ],
    "sg:phone":"+1   ",
    "sg:postcode":"15559",
    "sg:province":"PA",
    "sg:tags":[
        "executive"
    ],
    "wof:name":"Schellsburg Borough",
    "wof:placetype":"venue"
},
  "geometry": {"coordinates":[-78.64403799999999,40.067964],"type":"Point"}
}