{
  "type": "Feature",
  "properties": {
    "iso:country":"US",
    "sg:address":"320 E North Ave",
    "sg:city":"Pittsburgh",
    "sg:classifiers":[
        {
            "category":"Health Services",
            "subcategory":"Doctor",
            "type":"Services"
        }
    ],
    "sg:phone":"+1 412 359 4186",
    "sg:postcode":"15212",
    "sg:province":"PA",
    "wof:name":"Thomas Ronald L MD",
    "wof:placetype":"venue"
},
  "geometry": {"coordinates":[-80.00342,40.457029],"type":"Point"}
}