{
  "type": "Feature",
  "properties": {
    "iso:country":"US",
    "sg:address":"5943 Haverford Ave",
    "sg:city":"Philadelphia",
    "sg:classifiers":[
        {
            "category":"Building & Trades",
            "subcategory":"Locksmith",
            "type":"Services"
        }
    ],
    "sg:phone":"+1 267 295 2464",
    "sg:postcode":"19151",
    "sg:province":"PA",
    "sg:tags":[
        "key"
    ],
    "wof:name":"Available Emergency Locksmith",
    "wof:placetype":"venue"
},
  "geometry": {"coordinates":[-75.23853200000001,39.969715],"type":"Point"}
}