{
  "type": "Feature",
  "properties": {
    "iso:country":"US",
    "sg:address":"20 Signal Hill Rd",
    "sg:city":"Southampton",
    "sg:classifiers":[
        {
            "category":"Banks & Credit Unions",
            "subcategory":"Bank",
            "type":"Services"
        }
    ],
    "sg:phone":"+1   ",
    "sg:postcode":"18966",
    "sg:province":"PA",
    "sg:tags":[
        "institution",
        "business"
    ],
    "wof:name":"Charles S Havelka",
    "wof:placetype":"venue"
},
  "geometry": {"coordinates":[-74.94692000000001,40.203859],"type":"Point"}
}