{
  "type": "Feature",
  "properties": {
    "iso:country":"US",
    "sg:address":"1412 Chestnut St",
    "sg:city":"Philadelphia",
    "sg:classifiers":[
        {
            "category":"Arts & Performance",
            "subcategory":"Arts Center",
            "type":"Entertainment"
        },
        {
            "category":"Cinema",
            "subcategory":"Movie Theater",
            "type":"Entertainment"
        },
        {
            "category":"Arts & Performance",
            "subcategory":"Theater",
            "type":"Entertainment"
        }
    ],
    "sg:phone":"+1 215 569 9700",
    "sg:postcode":"19102",
    "sg:province":"PA",
    "sg:tags":[
        "performing",
        "theatre"
    ],
    "sg:website":"www.princemusictheater.org",
    "wof:name":"Prince Music Theater",
    "wof:placetype":"venue"
},
  "geometry": {"coordinates":[-75.164497,39.951199],"type":"Point"}
}