{
  "type": "Feature",
  "properties": {
    "iso:country":"US",
    "sg:address":"2195 Baltimore Pike",
    "sg:city":"Oxford",
    "sg:classifiers":[
        {
            "category":"Home & Garden",
            "subcategory":"Hardware",
            "type":"Retail Goods"
        }
    ],
    "sg:phone":"+1 610 932 2416",
    "sg:postcode":"19363",
    "sg:province":"PA",
    "wof:name":"Cameron's True Value Hardware",
    "wof:placetype":"venue"
},
  "geometry": {"coordinates":[-75.98614600000001,39.772405],"type":"Point"}
}