{
  "type": "Feature",
  "properties": {
    "iso:country":"US",
    "sg:address":"2080 E College Ave",
    "sg:city":"State College",
    "sg:classifiers":[
        {
            "category":"Home & Garden",
            "subcategory":"Home Furnishings",
            "type":"Retail Goods"
        }
    ],
    "sg:phone":"+1 814 237 2561",
    "sg:postcode":"16801",
    "sg:province":"PA",
    "sg:tags":[
        "lighting",
        "fixture"
    ],
    "wof:name":"Zach's Lighting & Electrical",
    "wof:placetype":"venue"
},
  "geometry": {"coordinates":[-77.815907,40.820419],"type":"Point"}
}