{
  "type": "Feature",
  "properties": {
    "iso:country":"US",
    "sg:address":"471 New York Ave",
    "sg:city":"Rochester",
    "sg:classifiers":[
        {
            "category":"Organizations",
            "subcategory":"Religious Organization",
            "type":"Services"
        }
    ],
    "sg:phone":"+1   ",
    "sg:postcode":"15074",
    "sg:province":"PA",
    "wof:name":"First Wsleyan Church Rochester",
    "wof:placetype":"venue"
},
  "geometry": {"coordinates":[-80.28293499999999,40.706999],"type":"Point"}
}