{
  "type": "Feature",
  "properties": {
    "iso:country":"US",
    "sg:address":"78 Sugarloaf Ave",
    "sg:city":"Conyngham",
    "sg:classifiers":[
        {
            "category":"Insurance",
            "subcategory":"Insurance Agent",
            "type":"Services"
        }
    ],
    "sg:phone":"+1 570 788 3543",
    "sg:postcode":"18219",
    "sg:province":"PA",
    "wof:name":"Boyer's Insurance",
    "wof:placetype":"venue"
},
  "geometry": {"coordinates":[-76.06394299999999,40.989889],"type":"Point"}
}