{
  "type": "Feature",
  "properties": {
    "addr:full":"390 Mulberry St Mifflinburg PA 17844",
    "addr:housenumber":"390",
    "addr:postcode":"17844",
    "addr:street":"Mulberry St",
    "iso:country":"US",
    "sg:address":"390 Mulberry St",
    "sg:city":"Mifflinburg",
    "sg:classifiers":[
        {
            "category":"Wholesale",
            "subcategory":"Groceries",
            "type":"Manufacturing & Wholesale Goods"
        }
    ],
    "sg:phone":"+1   ",
    "sg:postcode":"17844",
    "sg:province":"PA",
    "sg:tags":[
        "general"
    ],
    "wof:name":"Warehouse",
    "wof:placetype":"venue"
},
  "geometry": {"coordinates":[-77.047854,40.918871],"type":"Point"}
}