{
  "type": "Feature",
  "properties": {
    "addr:full":"200 Short St Philipsburg PA 16866",
    "addr:housenumber":"200",
    "addr:postcode":"16866",
    "addr:street":"Short St",
    "iso:country":"US",
    "sg:address":"200 Short St",
    "sg:city":"Philipsburg",
    "sg:classifiers":[
        {
            "category":"Education",
            "subcategory":"School",
            "type":"Public Place"
        }
    ],
    "sg:phone":"+1 814 342 1050",
    "sg:postcode":"16866",
    "sg:province":"PA",
    "sg:website":"www.pomounties.org",
    "wof:name":"Philipsburg Administration Ofc",
    "wof:placetype":"venue"
},
  "geometry": {"coordinates":[-78.234892,40.888495],"type":"Point"}
}