{
  "type": "Feature",
  "properties": {
    "iso:country":"US",
    "sg:address":"6660 Passer Rd",
    "sg:city":"Coopersburg",
    "sg:classifiers":[
        {
            "category":"Restaurant",
            "type":"Food & Drink"
        }
    ],
    "sg:phone":"+1 610 282 9003",
    "sg:postcode":"18036",
    "sg:province":"PA",
    "wof:name":"Peppercorn Pub",
    "wof:placetype":"venue"
},
  "geometry": {"coordinates":[-75.387398,40.523399],"type":"Point"}
}