{
  "type": "Feature",
  "properties": {
    "iso:country":"US",
    "sg:address":"428 Westerly Pkwy",
    "sg:city":"State College",
    "sg:classifiers":[
        {
            "category":"Restaurant",
            "type":"Food & Drink"
        }
    ],
    "sg:menulink":"http://www.allmenus.com/pa/state-college/241981-hi-way-pizza---west/menu/",
    "sg:phone":"+1 814 237 1074",
    "sg:postcode":"16801",
    "sg:province":"PA",
    "sg:tags":[
        "american",
        "italian",
        "pizza"
    ],
    "wof:name":"Hi Way Pizza - West",
    "wof:placetype":"venue"
},
  "geometry": {"coordinates":[-77.85267399999999,40.784204],"type":"Point"}
}