{
  "type": "Feature",
  "properties": {
    "iso:country":"US",
    "sg:address":"12339 Academy Rd",
    "sg:city":"Philadelphia",
    "sg:classifiers":[
        {
            "category":"Real Estate",
            "subcategory":"Real Estate Agent",
            "type":"Services"
        }
    ],
    "sg:phone":"+1   ",
    "sg:postcode":"19154",
    "sg:province":"PA",
    "sg:tags":[
        "agency",
        "rental"
    ],
    "wof:name":"Delaware Valley Development",
    "wof:placetype":"venue"
},
  "geometry": {"coordinates":[-74.976311,40.096087],"type":"Point"}
}