{
  "type": "Feature",
  "properties": {
    "addr:full":"299 E Chestnut St Mifflinburg PA 17844",
    "addr:housenumber":"299",
    "addr:postcode":"17844",
    "addr:street":"E Chestnut St",
    "iso:country":"US",
    "sg:address":"299 E Chestnut St",
    "sg:city":"Mifflinburg",
    "sg:classifiers":[
        {
            "category":"Insurance",
            "subcategory":"Insurance Agent",
            "type":"Services"
        },
        {
            "category":"Insurance",
            "subcategory":"Hazard Insurance",
            "type":"Services"
        }
    ],
    "sg:phone":"+1 570 966 3835",
    "sg:postcode":"17844",
    "sg:province":"PA",
    "sg:tags":[
        "auto"
    ],
    "wof:name":"Deihl Insurance",
    "wof:placetype":"venue"
},
  "geometry": {"coordinates":[-77.029312,40.924019],"type":"Point"}
}