{
  "type": "Feature",
  "properties": {
    "addr:full":"878 Rostraver Rd Belle Vernon PA 15012",
    "addr:housenumber":"878",
    "addr:postcode":"15012",
    "addr:street":"Rostraver Rd",
    "iso:country":"US",
    "sg:address":"878 Rostraver Rd",
    "sg:city":"Belle Vernon",
    "sg:classifiers":[
        {
            "category":"Food & Beverages",
            "subcategory":"Liquor & Beverages",
            "type":"Retail Goods"
        }
    ],
    "sg:phone":"+1   ",
    "sg:postcode":"15012",
    "sg:province":"PA",
    "sg:tags":[
        "regulation",
        "commercial",
        "sect",
        "alcoholic"
    ],
    "wof:name":"Wine & Spirits Shoppe 6524",
    "wof:placetype":"venue"
},
  "geometry": {"coordinates":[-79.84263,40.13803],"type":"Point"}
}