{
  "type": "Feature",
  "properties": {
    "addr:full":"2630 W Liberty Ave Pittsburgh PA 15216",
    "addr:housenumber":"2630",
    "addr:postcode":"15216",
    "addr:street":"W Liberty Ave",
    "iso:country":"US",
    "sg:address":"2630 W Liberty Ave",
    "sg:city":"Pittsburgh",
    "sg:classifiers":[
        {
            "category":"Retail",
            "subcategory":"Funeral Services",
            "type":"Services"
        }
    ],
    "sg:phone":"+1 412 531 4000",
    "sg:postcode":"15216",
    "sg:province":"PA",
    "sg:tags":[
        "plan"
    ],
    "wof:name":"Beinhauer Funeral Service",
    "wof:placetype":"venue"
},
  "geometry": {"coordinates":[-80.042314,40.38891],"type":"Point"}
}