{
  "type": "Feature",
  "properties": {
    "iso:country":"US",
    "sg:address":"321 Ridgway Rd",
    "sg:city":"St Marys",
    "sg:classifiers":[
        {
            "category":"Professional",
            "subcategory":"Employment Agencies",
            "type":"Services"
        }
    ],
    "sg:phone":"+1 814 781 7611",
    "sg:postcode":"15857",
    "sg:province":"PA",
    "sg:tags":[
        "help",
        "contractor"
    ],
    "wof:name":"Manpower Inc",
    "wof:placetype":"venue"
},
  "geometry": {"coordinates":[-78.575794,41.420783],"type":"Point"}
}