{
  "type": "Feature",
  "properties": {
    "iso:country":"US",
    "sg:address":"204 E Calder Way",
    "sg:city":"State College",
    "sg:classifiers":[
        {
            "category":"Manufacturing",
            "subcategory":"Tools & Machinery",
            "type":"Manufacturing & Wholesale Goods"
        },
        {
            "category":"Shopping",
            "subcategory":"Computers & Home Electronics",
            "type":"Retail Goods"
        }
    ],
    "sg:phone":"+1 814 235 7790",
    "sg:postcode":"16801",
    "sg:province":"PA",
    "sg:tags":[
        "control",
        "for",
        "supply",
        "mfg",
        "equipment",
        "design",
        "board",
        "mechanical",
        "electronic"
    ],
    "sg:website":"www.intuitivecontrols.com",
    "wof:name":"Intuitive Control Systems LLC",
    "wof:placetype":"venue"
},
  "geometry": {"coordinates":[-77.859835,40.794937],"type":"Point"}
}