{
  "type": "Feature",
  "properties": {
    "addr:full":"704 State Rd Croydon PA 19021",
    "addr:housenumber":"704",
    "addr:postcode":"19021",
    "addr:street":"State Rd",
    "iso:country":"US",
    "sg:address":"704 State Rd",
    "sg:city":"Croydon",
    "sg:classifiers":[
        {
            "category":"Retail",
            "subcategory":"Funeral Services",
            "type":"Services"
        }
    ],
    "sg:phone":"+1 215 785 1710",
    "sg:postcode":"19021",
    "sg:province":"PA",
    "sg:tags":[
        "cemetery"
    ],
    "wof:name":"Bristol Cemetery Land Co",
    "wof:placetype":"venue"
},
  "geometry": {"coordinates":[-74.904999,40.0867],"type":"Point"}
}