{
  "type": "Feature",
  "properties": {
    "iso:country":"US",
    "sg:address":"83 Ct Run",
    "sg:city":"Malvern",
    "sg:classifiers":[
        {
            "category":"Professional",
            "subcategory":"Management & Consulting",
            "type":"Services"
        }
    ],
    "sg:phone":"+1   ",
    "sg:postcode":"19355",
    "sg:province":"PA",
    "sg:tags":[
        "development",
        "software"
    ],
    "wof:name":"Solutioncom",
    "wof:placetype":"venue"
},
  "geometry": {"coordinates":[-75.492481,40.015349],"type":"Point"}
}