{
  "type": "Feature",
  "properties": {
    "iso:country":"US",
    "sg:address":"4932 Library Rd",
    "sg:city":"Bethel Park",
    "sg:classifiers":[
        {
            "category":"Shopping",
            "subcategory":"Computers & Home Electronics",
            "type":"Retail Goods"
        }
    ],
    "sg:phone":"+1 412 851 1374",
    "sg:postcode":"15102",
    "sg:province":"PA",
    "sg:tags":[
        "software"
    ],
    "wof:name":"Symserv",
    "wof:placetype":"venue"
},
  "geometry": {"coordinates":[-80.027449,40.34461],"type":"Point"}
}