{
  "type": "Feature",
  "properties": {
    "addr:full":"20 Penn Valley Rd Levittown PA 19054",
    "addr:housenumber":"20",
    "addr:postcode":"19054",
    "addr:street":"Penn Valley Rd Levittown",
    "iso:country":"US",
    "sg:address":"20 Penn Valley Rd",
    "sg:city":"Levittown",
    "sg:classifiers":[
        {
            "category":"Food & Beverages",
            "subcategory":"Bakery",
            "type":"Retail Goods"
        }
    ],
    "sg:phone":"+1 215 547 7266",
    "sg:postcode":"19054",
    "sg:province":"PA",
    "sg:tags":[
        "baker"
    ],
    "wof:name":"Piazza's Bakery",
    "wof:placetype":"venue"
},
  "geometry": {"coordinates":[-74.83143099999999,40.171537],"type":"Point"}
}