{
  "type": "Feature",
  "properties": {
    "iso:country":"US",
    "sg:address":"2422 Bristol Rd",
    "sg:city":"Bensalem",
    "sg:classifiers":[
        {
            "category":"Health Services",
            "subcategory":"Doctor",
            "type":"Services"
        }
    ],
    "sg:phone":"+1 215 750 9060",
    "sg:postcode":"19020",
    "sg:province":"PA",
    "wof:name":"Masceri Stephen J MD",
    "wof:placetype":"venue"
},
  "geometry": {"coordinates":[-74.92890199999999,40.132999],"type":"Point"}
}