{
  "type": "Feature",
  "properties": {
    "iso:country":"US",
    "sg:address":"724 Main St",
    "sg:city":"Portage",
    "sg:classifiers":[
        {
            "category":"Banks & Credit Unions",
            "subcategory":"Bank",
            "type":"Services"
        }
    ],
    "sg:phone":"+1 814 736 9292",
    "sg:postcode":"15946",
    "sg:province":"PA",
    "sg:tags":[
        "loan"
    ],
    "wof:name":"Cambria Thrift Consumer Co",
    "wof:placetype":"venue"
},
  "geometry": {"coordinates":[-78.672991,40.385646],"type":"Point"}
}