{
  "type": "Feature",
  "properties": {
    "iso:country":"US",
    "sg:address":"200 Wren Dr",
    "sg:city":"Greensburg",
    "sg:classifiers":[
        {
            "category":"Banks & Credit Unions",
            "subcategory":"Investment Brokerage",
            "type":"Services"
        }
    ],
    "sg:phone":"+1 724 468 3545",
    "sg:postcode":"15601",
    "sg:province":"PA",
    "sg:tags":[
        "consultant",
        "planning",
        "financial"
    ],
    "wof:name":"J E Harris & Assoc",
    "wof:placetype":"venue"
},
  "geometry": {"coordinates":[-79.58806800000001,40.274687],"type":"Point"}
}