{
  "type": "Feature",
  "properties": {
    "addr:full":"1056 E Lycoming St Philadelphia PA 19124",
    "addr:housenumber":"1056",
    "addr:postcode":"19124",
    "addr:street":"E Lycoming St",
    "iso:country":"US",
    "sg:address":"1056 E Lycoming St",
    "sg:city":"Philadelphia",
    "sg:classifiers":[
        {
            "category":"Personal",
            "subcategory":"Nail Salon",
            "type":"Services"
        }
    ],
    "sg:phone":"+1 215 744 7897",
    "sg:postcode":"19124",
    "sg:province":"PA",
    "wof:name":"May's Nail Salon",
    "wof:placetype":"venue"
},
  "geometry": {"coordinates":[-75.106454,40.009564],"type":"Point"}
}