{
  "type": "Feature",
  "properties": {
    "iso:country":"US",
    "sg:address":"462 W 18th St",
    "sg:city":"Erie",
    "sg:classifiers":[
        {
            "category":"Social Services",
            "type":"Services"
        }
    ],
    "sg:phone":"+1 814 454 6224",
    "sg:postcode":"16502",
    "sg:province":"PA",
    "wof:name":"Agape Center For Human Growth",
    "wof:placetype":"venue"
},
  "geometry": {"coordinates":[-80.087744,42.115126],"type":"Point"}
}