{
  "type": "Feature",
  "properties": {
    "iso:country":"US",
    "sg:address":"13291 North Ave",
    "sg:city":"Blue Ridge Summit",
    "sg:classifiers":[
        {
            "category":"Organizations",
            "subcategory":"Community Association",
            "type":"Services"
        }
    ],
    "sg:phone":"+1   ",
    "sg:postcode":"17214",
    "sg:province":"PA",
    "wof:name":"International Assoc of LI",
    "wof:placetype":"venue"
},
  "geometry": {"coordinates":[-77.46435099999999,39.725649],"type":"Point"}
}