{
  "type": "Feature",
  "properties": {
    "iso:country":"US",
    "sg:address":"2120 Herbert St",
    "sg:city":"Philadelphia",
    "sg:classifiers":[
        {
            "category":"Wholesale",
            "subcategory":"Machinery & Supplies",
            "type":"Manufacturing & Wholesale Goods"
        }
    ],
    "sg:phone":"+1   ",
    "sg:postcode":"19124",
    "sg:province":"PA",
    "sg:tags":[
        "equipment",
        "industrial"
    ],
    "wof:name":"Warehouse",
    "wof:placetype":"venue"
},
  "geometry": {"coordinates":[-75.075261,40.010301],"type":"Point"}
}