{
  "type": "Feature",
  "properties": {
    "iso:country":"US",
    "sg:address":"20 Bysher Ave",
    "sg:city":"Flourtown",
    "sg:classifiers":[
        {
            "category":"Shopping",
            "subcategory":"Clothing, Apparel, & Fashions",
            "type":"Retail Goods"
        }
    ],
    "sg:phone":"+1   ",
    "sg:postcode":"19031",
    "sg:province":"PA",
    "wof:name":"M B Designs Inc",
    "wof:placetype":"venue"
},
  "geometry": {"coordinates":[-75.209487,40.105357],"type":"Point"}
}