{
  "type": "Feature",
  "properties": {
    "addr:full":"64 E Uwchlan Ave Exton PA 19341",
    "addr:housenumber":"64",
    "addr:postcode":"19341",
    "addr:street":"E Uwchlan Ave",
    "iso:country":"US",
    "sg:address":"64 E Uwchlan Ave",
    "sg:city":"Exton",
    "sg:classifiers":[
        {
            "category":"Wholesale",
            "subcategory":"Electrical",
            "type":"Manufacturing & Wholesale Goods"
        }
    ],
    "sg:phone":"+1   ",
    "sg:postcode":"19341",
    "sg:province":"PA",
    "sg:tags":[
        "communication",
        "electronic",
        "devices"
    ],
    "wof:name":"American Comm Specialist",
    "wof:placetype":"venue"
},
  "geometry": {"coordinates":[-75.654954,40.059156],"type":"Point"}
}