{
  "type": "Feature",
  "properties": {
    "addr:full":"226 Cambridge Chase Exton PA 19341",
    "addr:housenumber":"226",
    "addr:postcode":"19341",
    "addr:street":"Cambridge Chase",
    "iso:country":"US",
    "sg:address":"226 Cambridge Chase",
    "sg:city":"Exton",
    "sg:classifiers":[
        {
            "category":"Professional",
            "type":"Services"
        }
    ],
    "sg:phone":"+1   ",
    "sg:postcode":"19341",
    "sg:province":"PA",
    "wof:name":"Jean C Griffith Family Limit",
    "wof:placetype":"venue"
},
  "geometry": {"coordinates":[-75.64104399999999,40.034129],"type":"Point"}
}