{
  "type": "Feature",
  "properties": {
    "iso:country":"US",
    "sg:address":"832 N 6th St",
    "sg:city":"Reading",
    "sg:classifiers":[
        {
            "category":"Professional",
            "type":"Services"
        }
    ],
    "sg:phone":"+1   ",
    "sg:postcode":"19601",
    "sg:province":"PA",
    "wof:name":"Elizabeth Colusso",
    "wof:placetype":"venue"
},
  "geometry": {"coordinates":[-75.925601,40.348429],"type":"Point"}
}