{
  "type": "Feature",
  "properties": {
    "addr:full":"220 W Main St Ligonier PA 15658",
    "addr:housenumber":"220",
    "addr:postcode":"15658",
    "addr:street":"W Main St",
    "iso:country":"US",
    "sg:address":"220 W Main St",
    "sg:city":"Ligonier",
    "sg:classifiers":[
        {
            "category":"Professional",
            "type":"Services"
        },
        {
            "category":"Education",
            "subcategory":"Special Training",
            "type":"Public Place"
        }
    ],
    "sg:phone":"+1 724 238 6360",
    "sg:postcode":"15658",
    "sg:province":"PA",
    "sg:tags":[
        "school",
        "instruction",
        "art"
    ],
    "wof:name":"Amy Roadman's Techniques",
    "wof:placetype":"venue"
},
  "geometry": {"coordinates":[-79.239294,40.244069],"type":"Point"}
}