{
  "type": "Feature",
  "properties": {
    "iso:country":"US",
    "sg:address":"107 Penns Trl",
    "sg:city":"Newtown",
    "sg:classifiers":[
        {
            "category":"Professional",
            "subcategory":"Research",
            "type":"Services"
        }
    ],
    "sg:phone":"+1 215 504 6131",
    "sg:postcode":"18940",
    "sg:province":"PA",
    "sg:tags":[
        "commercial",
        "physical"
    ],
    "wof:name":"Wide Band Systems Inc",
    "wof:placetype":"venue"
},
  "geometry": {"coordinates":[-74.90951,40.226513],"type":"Point"}
}