{
  "type": "Feature",
  "properties": {
    "addr:full":"337 W Middle Rd Lykens PA 17048",
    "addr:housenumber":"337",
    "addr:postcode":"17048",
    "addr:street":"W Middle Rd",
    "iso:country":"US",
    "sg:address":"337 W Middle Rd",
    "sg:city":"Lykens",
    "sg:classifiers":[
        {
            "category":"Professional",
            "subcategory":"Art Services",
            "type":"Services"
        }
    ],
    "sg:phone":"+1 717 365 3376",
    "sg:postcode":"17048",
    "sg:province":"PA",
    "sg:tags":[
        "photographer"
    ],
    "sg:website":"www.joelandersonphoto.com",
    "wof:name":"Joel Anderson Photography",
    "wof:placetype":"venue"
},
  "geometry": {"coordinates":[-76.76545900000001,40.619355],"type":"Point"}
}