{
  "type": "Feature",
  "properties": {
    "iso:country":"US",
    "sg:address":"2153 Ridge Ave",
    "sg:city":"Philadelphia",
    "sg:classifiers":[
        {
            "category":"Food & Beverages",
            "subcategory":"Meat & Fish",
            "type":"Retail Goods"
        }
    ],
    "sg:phone":"+1 215 232 1522",
    "sg:postcode":"19121",
    "sg:province":"PA",
    "sg:tags":[
        "seafood",
        "market"
    ],
    "wof:name":"Ahn's Produce",
    "wof:placetype":"venue"
},
  "geometry": {"coordinates":[-75.170799,39.979198],"type":"Point"}
}