{
  "type": "Feature",
  "properties": {
    "iso:country":"US",
    "sg:address":"238 1/2 Freeport Rd",
    "sg:city":"Pittsburgh",
    "sg:classifiers":[
        {
            "category":"Shopping",
            "subcategory":"Jewelry",
            "type":"Retail Goods"
        },
        {
            "category":"Manufacturing",
            "subcategory":"Jewelry",
            "type":"Manufacturing & Wholesale Goods"
        }
    ],
    "sg:phone":"+1 412 963 9132",
    "sg:postcode":"15238",
    "sg:province":"PA",
    "sg:tags":[
        "manufacturer",
        "jewelers-wholesale",
        "jeweler"
    ],
    "sg:website":"http://www.marleneharriscol.com",
    "wof:name":"Buttons & Bangles",
    "wof:placetype":"venue"
},
  "geometry": {"coordinates":[-79.863707,40.492561],"type":"Point"}
}