{
  "type": "Feature",
  "properties": {
    "iso:country":"US",
    "sg:address":"2915 Limeport Pike",
    "sg:city":"Coopersburg",
    "sg:classifiers":[
        {
            "category":"Farming",
            "subcategory":"Orchard",
            "type":"Manufacturing & Wholesale Goods"
        }
    ],
    "sg:phone":"+1 610 967 2440",
    "sg:postcode":"18036",
    "sg:province":"PA",
    "sg:tags":[
        "grove",
        "management"
    ],
    "wof:name":"Hausman's Fruit Farm",
    "wof:placetype":"venue"
},
  "geometry": {"coordinates":[-75.46134499999999,40.480757],"type":"Point"}
}