{
  "type": "Feature",
  "properties": {
    "addr:full":"290 Ruth Rd Fleetwood PA 19522",
    "addr:housenumber":"290",
    "addr:postcode":"19522",
    "addr:street":"Ruth Rd",
    "iso:country":"US",
    "sg:address":"290 Ruth Rd",
    "sg:city":"Fleetwood",
    "sg:classifiers":[
        {
            "category":"Farming",
            "subcategory":"Dairy Farm",
            "type":"Manufacturing & Wholesale Goods"
        }
    ],
    "sg:phone":"+1   ",
    "sg:postcode":"19522",
    "sg:province":"PA",
    "wof:name":"David Bitler",
    "wof:placetype":"venue"
},
  "geometry": {"coordinates":[-75.775532,40.46482],"type":"Point"}
}