{
  "type": "Feature",
  "properties": {
    "addr:full":"120 Boltz St Johnstown PA 15902",
    "addr:housenumber":"120",
    "addr:postcode":"15902",
    "addr:street":"Boltz St",
    "iso:country":"US",
    "sg:address":"120 Boltz St",
    "sg:city":"Johnstown",
    "sg:classifiers":[
        {
            "category":"Organizations",
            "subcategory":"Religious Organization",
            "type":"Services"
        }
    ],
    "sg:phone":"+1 814 536 6818",
    "sg:postcode":"15902",
    "sg:province":"PA",
    "sg:tags":[
        "church"
    ],
    "wof:name":"Saint Gregory Church",
    "wof:placetype":"venue"
},
  "geometry": {"coordinates":[-78.900747,40.320099],"type":"Point"}
}