{
  "type": "Feature",
  "properties": {
    "iso:country":"US",
    "sg:address":"89 Creek Rd",
    "sg:city":"Mifflinburg",
    "sg:classifiers":[
        {
            "category":"Building & Trades",
            "subcategory":"Plumbing",
            "type":"Services"
        }
    ],
    "sg:phone":"+1   ",
    "sg:postcode":"17815",
    "sg:province":"PA",
    "sg:tags":[
        "plumbing",
        "refrigeration",
        "contractor"
    ],
    "wof:name":"Midstate Mechanical",
    "wof:placetype":"venue"
},
  "geometry": {"coordinates":[-76.476499,41.016876],"type":"Point"}
}