{
  "type": "Feature",
  "properties": {
    "addr:full":"1025 N 66th St Philadelphia PA 19151",
    "addr:housenumber":"1025",
    "addr:postcode":"19151",
    "addr:street":"N 66Th St",
    "iso:country":"US",
    "sg:address":"1025 N 66th St",
    "sg:city":"Philadelphia",
    "sg:classifiers":[
        {
            "category":"Health Services",
            "subcategory":"Doctor",
            "type":"Services"
        }
    ],
    "sg:phone":"+1 215 477 8800",
    "sg:postcode":"19151",
    "sg:province":"PA",
    "sg:tags":[
        "surgeon",
        "oral"
    ],
    "wof:name":"Chang Vicky DDS",
    "wof:placetype":"venue"
},
  "geometry": {"coordinates":[-75.253502,39.979401],"type":"Point"}
}