{
  "type": "Feature",
  "properties": {
    "addr:full":"1890 Bethlehem Pike Flourtown PA 19031",
    "addr:housenumber":"1890",
    "addr:postcode":"19031",
    "addr:street":"Bethlehem Pike",
    "iso:country":"US",
    "sg:address":"1890 Bethlehem Pike",
    "sg:city":"Flourtown",
    "sg:classifiers":[
        {
            "category":"Restaurant",
            "type":"Food & Drink"
        }
    ],
    "sg:menulink":"http://www.allmenus.com/pa/whitemarsh/206059-mcdonalds/menu/",
    "sg:phone":"+1 215 233 5998",
    "sg:postcode":"19031",
    "sg:province":"PA",
    "sg:tags":[
        "burger",
        "american"
    ],
    "wof:name":"McDonald's",
    "wof:placetype":"venue"
},
  "geometry": {"coordinates":[-75.214144,40.111177],"type":"Point"}
}