{
  "type": "Feature",
  "properties": {
    "iso:country":"US",
    "sg:address":"250 Rochester Rd",
    "sg:city":"Freedom",
    "sg:classifiers":[
        {
            "category":"Recreation",
            "type":"Entertainment"
        }
    ],
    "sg:phone":"+1   ",
    "sg:postcode":"15042",
    "sg:province":"PA",
    "wof:name":"Three Rivers Paintball Pro Sp",
    "wof:placetype":"venue"
},
  "geometry": {"coordinates":[-80.170323,40.702626],"type":"Point"}
}