{
  "type": "Feature",
  "properties": {
    "addr:full":"713 N Pike Rd Cabot PA 16023",
    "addr:housenumber":"713",
    "addr:postcode":"16023",
    "addr:street":"N Pike Rd",
    "iso:country":"US",
    "sg:address":"713 N Pike Rd",
    "sg:city":"Cabot",
    "sg:classifiers":[
        {
            "category":"Wholesale",
            "subcategory":"Farm Supplies",
            "type":"Manufacturing & Wholesale Goods"
        }
    ],
    "sg:phone":"+1 724 352 5859",
    "sg:postcode":"16023",
    "sg:province":"PA",
    "wof:name":"Kushkowski Nursery & Garden",
    "wof:placetype":"venue"
},
  "geometry": {"coordinates":[-79.79568399999999,40.776477],"type":"Point"}
}