{
  "type": "Feature",
  "properties": {
    "iso:country":"US",
    "sg:address":"230 W Main St",
    "sg:city":"Plymouth",
    "sg:classifiers":[
        {
            "category":"Personal",
            "subcategory":"Beauty Salon",
            "type":"Services"
        }
    ],
    "sg:phone":"+1 570 779 5577",
    "sg:postcode":"18651",
    "sg:province":"PA",
    "wof:name":"Totalook",
    "wof:placetype":"venue"
},
  "geometry": {"coordinates":[-75.948826,41.239533],"type":"Point"}
}