{
  "type": "Feature",
  "properties": {
    "addr:full":"205 W Germantown Pike Norristown PA 19401",
    "addr:housenumber":"205",
    "addr:postcode":"19401",
    "addr:street":"W Germantown Pike",
    "iso:country":"US",
    "sg:address":"205 W Germantown Pike",
    "sg:city":"Norristown",
    "sg:classifiers":[
        {
            "category":"Food & Beverages",
            "subcategory":"Groceries & Convenience Stores",
            "type":"Retail Goods"
        },
        {
            "category":"Restaurant",
            "type":"Food & Drink"
        }
    ],
    "sg:phone":"+1 610 270 8098",
    "sg:postcode":"19401",
    "sg:province":"PA",
    "sg:tags":[
        "delicatessen"
    ],
    "wof:name":"Dino's Deli",
    "wof:placetype":"venue"
},
  "geometry": {"coordinates":[-75.326711,40.147253],"type":"Point"}
}