{
  "type": "Feature",
  "properties": {
    "addr:full":"96 E Main St Uniontown PA 15401",
    "addr:housenumber":"96",
    "addr:postcode":"15401",
    "addr:street":"E Main St",
    "iso:country":"US",
    "sg:address":"96 E Main St",
    "sg:city":"Uniontown",
    "sg:classifiers":[
        {
            "category":"Professional",
            "subcategory":"Lawyer & Legal Services",
            "type":"Services"
        }
    ],
    "sg:phone":"+1 724 438 8560",
    "sg:postcode":"15401",
    "sg:province":"PA",
    "sg:tags":[
        "attorney",
        "planning",
        "estate"
    ],
    "sg:website":"http://www.JohnandJohnLaw.com",
    "wof:name":"John & John",
    "wof:placetype":"venue"
},
  "geometry": {"coordinates":[-79.721785,39.900791],"type":"Point"}
}