{
  "type": "Feature",
  "properties": {
    "addr:full":"555 Ashbourne Rd Elkins Park PA 19027",
    "addr:housenumber":"555",
    "addr:postcode":"19027",
    "addr:street":"Ashbourne Rd",
    "iso:country":"US",
    "sg:address":"555 Ashbourne Rd",
    "sg:city":"Elkins Park",
    "sg:classifiers":[
        {
            "category":"Recreation",
            "type":"Entertainment"
        }
    ],
    "sg:phone":"+1 215 635 4185",
    "sg:postcode":"19027",
    "sg:province":"PA",
    "sg:tags":[
        "hall",
        "auditorium"
    ],
    "wof:name":"Jay Cooke Hall",
    "wof:placetype":"venue"
},
  "geometry": {"coordinates":[-75.13356899999999,40.071108],"type":"Point"}
}