{
  "type": "Feature",
  "properties": {
    "iso:country":"US",
    "sg:address":"2399 Bryansville Rd",
    "sg:city":"Delta",
    "sg:classifiers":[
        {
            "category":"Retail",
            "subcategory":"Auto Repair",
            "type":"Services"
        }
    ],
    "sg:phone":"+1   ",
    "sg:postcode":"17314",
    "sg:province":"PA",
    "sg:tags":[
        "automotive"
    ],
    "wof:name":"Heffners Towing",
    "wof:placetype":"venue"
},
  "geometry": {"coordinates":[-76.349222,39.748372],"type":"Point"}
}