{
  "type": "Feature",
  "properties": {
    "addr:full":"1232 Varner Rd Pittsburgh PA 15227",
    "addr:housenumber":"1232",
    "addr:postcode":"15227",
    "addr:street":"Varner Rd",
    "iso:country":"US",
    "sg:address":"1232 Varner Rd",
    "sg:city":"Pittsburgh",
    "sg:classifiers":[
        {
            "category":"Real Estate",
            "subcategory":"Real Estate Agent",
            "type":"Services"
        }
    ],
    "sg:phone":"+1   ",
    "sg:postcode":"15227",
    "sg:province":"PA",
    "wof:name":"K J Properties",
    "wof:placetype":"venue"
},
  "geometry": {"coordinates":[-79.972555,40.362714],"type":"Point"}
}