{
  "type": "Feature",
  "properties": {
    "iso:country":"US",
    "sg:address":"1014 Catasauqua Rd",
    "sg:city":"Whitehall",
    "sg:classifiers":[
        {
            "category":"Arts & Performance",
            "subcategory":"Theater",
            "type":"Entertainment"
        }
    ],
    "sg:phone":"+1 610 266 9019",
    "sg:postcode":"18052",
    "sg:province":"PA",
    "sg:tags":[
        "live",
        "music"
    ],
    "wof:name":"J P & Co",
    "wof:placetype":"venue"
},
  "geometry": {"coordinates":[-75.469133,40.639192],"type":"Point"}
}