{
  "type": "Feature",
  "properties": {
    "addr:full":"891 Peninsula Dr Central City PA 15926",
    "addr:housenumber":"891",
    "addr:postcode":"15926",
    "addr:street":"Peninsula Dr",
    "iso:country":"US",
    "sg:address":"891 Peninsula Dr",
    "sg:city":"Central City",
    "sg:classifiers":[
        {
            "category":"Real Estate",
            "subcategory":"Real Estate Agent",
            "type":"Services"
        }
    ],
    "sg:phone":"+1   ",
    "sg:postcode":"15926",
    "sg:province":"PA",
    "wof:name":"Exclusive Property",
    "wof:placetype":"venue"
},
  "geometry": {"coordinates":[-78.861431,40.046748],"type":"Point"}
}