{
  "type": "Feature",
  "properties": {
    "addr:full":"808 Green Ave Altoona PA 16601",
    "addr:housenumber":"808",
    "addr:postcode":"16601",
    "addr:street":"Green Ave",
    "iso:country":"US",
    "sg:address":"808 Green Ave",
    "sg:city":"Altoona",
    "sg:classifiers":[
        {
            "category":"Wholesale",
            "subcategory":"Books, Periodicals, & Newspapers",
            "type":"Manufacturing & Wholesale Goods"
        }
    ],
    "sg:phone":"+1 814 944 3593",
    "sg:postcode":"16601",
    "sg:province":"PA",
    "sg:tags":[
        "magazine"
    ],
    "wof:name":"Newborn Enterprises Inc",
    "wof:placetype":"venue"
},
  "geometry": {"coordinates":[-78.397857,40.517896],"type":"Point"}
}