{
  "type": "Feature",
  "properties": {
    "addr:full":"1401 Trindle Rd Carlisle PA 17015",
    "addr:housenumber":"1401",
    "addr:postcode":"17015",
    "addr:street":"Trindle Rd",
    "iso:country":"US",
    "sg:address":"1401 Trindle Rd",
    "sg:city":"Carlisle",
    "sg:classifiers":[
        {
            "category":"Retail",
            "subcategory":"Auto Rental",
            "type":"Services"
        }
    ],
    "sg:phone":"+1 717 477 0900",
    "sg:postcode":"17015",
    "sg:province":"PA",
    "sg:tags":[
        "renting",
        "truck",
        "leasing"
    ],
    "wof:name":"Penske Truck Rental",
    "wof:placetype":"venue"
},
  "geometry": {"coordinates":[-77.153381,40.199047],"type":"Point"}
}