{
  "type": "Feature",
  "properties": {
    "addr:full":"231 State Rte 590 Greeley PA 18425",
    "addr:housenumber":"231",
    "addr:postcode":"18425",
    "addr:street":"State Rte 590",
    "iso:country":"US",
    "sg:address":"231 State Rte 590",
    "sg:city":"Greeley",
    "sg:classifiers":[
        {
            "category":"Bars & Pubs",
            "type":"Food & Drink"
        }
    ],
    "sg:phone":"+1 570 685 7217",
    "sg:postcode":"18425",
    "sg:province":"PA",
    "wof:name":"Ernies Place",
    "wof:placetype":"venue"
},
  "geometry": {"coordinates":[-74.99550000000001,41.423857],"type":"Point"}
}