{
  "type": "Feature",
  "properties": {
    "addr:full":"501 S Broad St Lansdale PA 19446",
    "addr:housenumber":"501",
    "addr:postcode":"19446",
    "addr:street":"S Broad St",
    "iso:country":"US",
    "sg:address":"501 S Broad St",
    "sg:city":"Lansdale",
    "sg:classifiers":[
        {
            "category":"Restaurant",
            "type":"Food & Drink"
        }
    ],
    "sg:phone":"+1 215 362 5778",
    "sg:postcode":"19446",
    "sg:province":"PA",
    "sg:website":"www.subway.com",
    "wof:name":"Subway Sandwiches & Salads",
    "wof:placetype":"venue"
},
  "geometry": {"coordinates":[-75.29160299999999,40.233398],"type":"Point"}
}