{
  "type": "Feature",
  "properties": {
    "iso:country":"US",
    "sg:address":"1076 Eagle Ln",
    "sg:city":"Doylestown",
    "sg:classifiers":[
        {
            "category":"Government",
            "subcategory":"Police Station",
            "type":"Public Place"
        }
    ],
    "sg:phone":"+1   ",
    "sg:postcode":"18901",
    "sg:province":"PA",
    "sg:tags":[
        "protection"
    ],
    "wof:name":"Doylestown Police Department",
    "wof:placetype":"venue"
},
  "geometry": {"coordinates":[-75.125758,40.269076],"type":"Point"}
}