{
  "type": "Feature",
  "properties": {
    "iso:country":"US",
    "sg:address":"107 Oakwood Ln",
    "sg:city":"Shippenville",
    "sg:classifiers":[
        {
            "category":"Wholesale",
            "subcategory":"Office Equipment",
            "type":"Manufacturing & Wholesale Goods"
        },
        {
            "category":"Manufacturing",
            "subcategory":"Tools & Machinery",
            "type":"Manufacturing & Wholesale Goods"
        }
    ],
    "sg:phone":"+1 814 226 6830",
    "sg:postcode":"16254",
    "sg:province":"PA",
    "sg:tags":[
        "machine",
        "shop",
        "typewriter"
    ],
    "wof:name":"Landers Business Machines",
    "wof:placetype":"venue"
},
  "geometry": {"coordinates":[-79.426181,41.243246],"type":"Point"}
}