{
  "type": "Feature",
  "properties": {
    "iso:country":"US",
    "sg:address":"110 Old Eberhart Rd",
    "sg:city":"Butler",
    "sg:classifiers":[
        {
            "category":"Government",
            "subcategory":"Fire Station",
            "type":"Public Place"
        }
    ],
    "sg:phone":"+1 724 287 1042",
    "sg:postcode":"16001",
    "sg:province":"PA",
    "sg:tags":[
        "department"
    ],
    "wof:name":"Greenwood Volunteer Fire Dept",
    "wof:placetype":"venue"
},
  "geometry": {"coordinates":[-79.955375,40.884627],"type":"Point"}
}