{
  "type": "Feature",
  "properties": {
    "iso:country":"US",
    "sg:address":"3300 Aramingo Ave",
    "sg:city":"Philadelphia",
    "sg:classifiers":[
        {
            "category":"Health Services",
            "subcategory":"Health Practitioner",
            "type":"Services"
        }
    ],
    "sg:phone":"+1 215 427 2242",
    "sg:postcode":"19134",
    "sg:province":"PA",
    "sg:tags":[
        "therapy",
        "physical"
    ],
    "wof:name":"Lafortaleza Physical Therapy Center",
    "wof:placetype":"venue"
},
  "geometry": {"coordinates":[-75.10340100000001,39.989899],"type":"Point"}
}