{
  "type": "Feature",
  "properties": {
    "iso:country":"US",
    "sg:address":"24 Parkway Blvd",
    "sg:city":"York",
    "sg:classifiers":[
        {
            "category":"Wholesale",
            "subcategory":"Electrical",
            "type":"Manufacturing & Wholesale Goods"
        }
    ],
    "sg:phone":"+1 717 843 0891",
    "sg:postcode":"17404",
    "sg:province":"PA",
    "sg:tags":[
        "equipment",
        "industrial",
        "electric",
        "supply"
    ],
    "sg:website":"www.wesco.com",
    "wof:name":"Wesco Distribution Inc",
    "wof:placetype":"venue"
},
  "geometry": {"coordinates":[-76.733504,39.971364],"type":"Point"}
}