{
  "type": "Feature",
  "properties": {
    "iso:country":"US",
    "sg:address":"529 Reading Ave",
    "sg:city":"Reading",
    "sg:classifiers":[
        {
            "category":"Professional",
            "subcategory":"Management & Consulting",
            "type":"Services"
        }
    ],
    "sg:phone":"+1 610 373 3700",
    "sg:postcode":"19611",
    "sg:province":"PA",
    "sg:tags":[
        "consultant",
        "business"
    ],
    "wof:name":"I R Financial Solutions Inc",
    "wof:placetype":"venue"
},
  "geometry": {"coordinates":[-75.949561,40.336847],"type":"Point"}
}