{
  "type": "Feature",
  "properties": {
    "iso:country":"US",
    "sg:address":"178 Taylorsville Rd",
    "sg:city":"Washington Crossing",
    "sg:classifiers":[
        {
            "category":"Building & Trades",
            "subcategory":"Landscaping Services",
            "type":"Services"
        }
    ],
    "sg:phone":"+1   ",
    "sg:postcode":"18977",
    "sg:province":"PA",
    "sg:tags":[
        "ornamental",
        "nursery"
    ],
    "wof:name":"Shearer/Penn Tree & Lawn Care",
    "wof:placetype":"venue"
},
  "geometry": {"coordinates":[-74.85923200000001,40.265379],"type":"Point"}
}