{
  "type": "Feature",
  "properties": {
    "iso:country":"US",
    "sg:address":"900 Commerce Dr",
    "sg:city":"Coraopolis",
    "sg:classifiers":[
        {
            "category":"Professional",
            "subcategory":"Business Services",
            "type":"Services"
        }
    ],
    "sg:phone":"+1   ",
    "sg:postcode":"15108",
    "sg:province":"PA",
    "wof:name":"Canella Carilli Fincl Group",
    "wof:placetype":"venue"
},
  "geometry": {"coordinates":[-80.211675,40.503463],"type":"Point"}
}