{
  "type": "Feature",
  "properties": {
    "iso:country":"US",
    "sg:address":"2362 Buffalo Rd",
    "sg:city":"Erie",
    "sg:classifiers":[
        {
            "category":"Organizations",
            "subcategory":"Professional Association",
            "type":"Services"
        }
    ],
    "sg:phone":"+1   ",
    "sg:postcode":"16510",
    "sg:province":"PA",
    "wof:name":"Norman E Davis",
    "wof:placetype":"venue"
},
  "geometry": {"coordinates":[-80.025201,42.135652],"type":"Point"}
}