{
  "type": "Feature",
  "properties": {
    "iso:country":"US",
    "sg:address":"122 N Main St",
    "sg:city":"Doylestown",
    "sg:classifiers":[
        {
            "category":"Professional",
            "type":"Services"
        },
        {
            "category":"Professional",
            "subcategory":"Lawyer & Legal Services",
            "type":"Services"
        }
    ],
    "sg:phone":"+1 215 348 8786",
    "sg:postcode":"18901",
    "sg:province":"PA",
    "sg:tags":[
        "establishment"
    ],
    "wof:name":"Sugarman & Assocs",
    "wof:placetype":"venue"
},
  "geometry": {"coordinates":[-75.13051,40.31259],"type":"Point"}
}