{
  "type": "Feature",
  "properties": {
    "iso:country":"US",
    "sg:address":"5060 Painted Sky Rd",
    "sg:city":"Reading",
    "sg:classifiers":[
        {
            "category":"Shopping",
            "subcategory":"Stationery & Office Supplies",
            "type":"Retail Goods"
        },
        {
            "category":"Professional",
            "subcategory":"Research",
            "type":"Services"
        },
        {
            "category":"Professional",
            "subcategory":"Art Services",
            "type":"Services"
        },
        {
            "category":"Professional",
            "subcategory":"Advertising",
            "type":"Services"
        }
    ],
    "sg:phone":"+1 610 207 0965",
    "sg:postcode":"19606",
    "sg:province":"PA",
    "sg:tags":[
        "announcement",
        "designer",
        "agency",
        "direct",
        "analysis",
        "graphic",
        "invitation",
        "mail",
        "market"
    ],
    "sg:website":"http://thebdesignssite.com",
    "wof:name":"BDesigns",
    "wof:placetype":"venue"
},
  "geometry": {"coordinates":[-75.856224,40.29093],"type":"Point"}
}