{
  "type": "Feature",
  "properties": {
    "addr:full":"1109 Milton St Pittsburgh PA 15218",
    "addr:housenumber":"1109",
    "addr:postcode":"15218",
    "addr:street":"Milton St",
    "iso:country":"US",
    "sg:address":"1109 Milton St",
    "sg:city":"Pittsburgh",
    "sg:classifiers":[
        {
            "category":"Professional",
            "subcategory":"Lawyer & Legal Services",
            "type":"Services"
        }
    ],
    "sg:phone":"+1   ",
    "sg:postcode":"15218",
    "sg:province":"PA",
    "wof:name":"Begler Ann Lee Atty",
    "wof:placetype":"venue"
},
  "geometry": {"coordinates":[-79.894245,40.431462],"type":"Point"}
}