{
  "type": "Feature",
  "properties": {
    "iso:country":"US",
    "sg:address":"285 High St",
    "sg:city":"Sharpsville",
    "sg:classifiers":[
        {
            "category":"Restaurant",
            "type":"Food & Drink"
        }
    ],
    "sg:phone":"+1 724 962 9596",
    "sg:postcode":"16150",
    "sg:province":"PA",
    "wof:name":"Danny's Bar & Grille",
    "wof:placetype":"venue"
},
  "geometry": {"coordinates":[-80.480475,41.265938],"type":"Point"}
}