{
  "type": "Feature",
  "properties": {
    "addr:full":"45 Darby Rd Paoli PA 19301",
    "addr:housenumber":"45",
    "addr:postcode":"19301",
    "addr:street":"Darby Rd",
    "iso:country":"US",
    "sg:address":"45 Darby Rd",
    "sg:city":"Paoli",
    "sg:classifiers":[
        {
            "category":"Banks & Credit Unions",
            "subcategory":"Investment Brokerage",
            "type":"Services"
        },
        {
            "category":"Banks & Credit Unions",
            "subcategory":"Financial Services",
            "type":"Services"
        }
    ],
    "sg:phone":"+1 610 695 3020",
    "sg:postcode":"19301",
    "sg:province":"PA",
    "sg:tags":[
        "advisory",
        "planner"
    ],
    "wof:name":"Commonwealth Financial Network",
    "wof:placetype":"venue"
},
  "geometry": {"coordinates":[-75.481799,40.040847],"type":"Point"}
}