{
  "type": "Feature",
  "properties": {
    "addr:full":"455 Conerty Rd Chicora PA 16025",
    "addr:housenumber":"455",
    "addr:postcode":"16025",
    "addr:street":"Conerty Rd",
    "iso:country":"US",
    "sg:address":"455 Conerty Rd",
    "sg:city":"Chicora",
    "sg:classifiers":[
        {
            "category":"Building & Trades",
            "subcategory":"Construction",
            "type":"Services"
        }
    ],
    "sg:phone":"+1   ",
    "sg:postcode":"16025",
    "sg:province":"PA",
    "sg:tags":[
        "excavation",
        "contractor"
    ],
    "wof:name":"A1 Excavating",
    "wof:placetype":"venue"
},
  "geometry": {"coordinates":[-79.70063,40.915446],"type":"Point"}
}