{
  "type": "Feature",
  "properties": {
    "iso:country":"US",
    "sg:address":"1870 Colt Rd",
    "sg:city":"Media",
    "sg:classifiers":[
        {
            "category":"Arena",
            "subcategory":"Sports Club",
            "type":"Entertainment"
        }
    ],
    "sg:phone":"+1 610 566 1171",
    "sg:postcode":"19063",
    "sg:province":"PA",
    "sg:tags":[
        "manager",
        "recruiter",
        "promoter"
    ],
    "wof:name":"Executive Diversions Inc",
    "wof:placetype":"venue"
},
  "geometry": {"coordinates":[-75.40336600000001,39.941498],"type":"Point"}
}