{
  "type": "Feature",
  "properties": {
    "iso:country":"US",
    "sg:address":"220 Commerce Dr",
    "sg:city":"Fort Washington",
    "sg:classifiers":[
        {
            "category":"Professional",
            "type":"Services"
        }
    ],
    "sg:phone":"+1   ",
    "sg:postcode":"19034",
    "sg:province":"PA",
    "wof:name":"Andrew Junikiewicz",
    "wof:placetype":"venue"
},
  "geometry": {"coordinates":[-75.204787,40.136441],"type":"Point"}
}