{
  "type": "Feature",
  "properties": {
    "addr:full":"27 S Main St Montrose PA 18801",
    "addr:housenumber":"27",
    "addr:postcode":"18801",
    "addr:street":"S Main St",
    "iso:country":"US",
    "sg:address":"27 S Main St",
    "sg:city":"Montrose",
    "sg:classifiers":[
        {
            "category":"Restaurant",
            "type":"Food & Drink"
        }
    ],
    "sg:phone":"+1 570 278 1500",
    "sg:postcode":"18801",
    "sg:province":"PA",
    "wof:name":"Original Italian Pizza",
    "wof:placetype":"venue"
},
  "geometry": {"coordinates":[-75.87952900000001,41.832418],"type":"Point"}
}