{
  "type": "Feature",
  "properties": {
    "addr:full":"909 W Union Blvd Bethlehem PA 18018",
    "addr:housenumber":"909",
    "addr:postcode":"18018",
    "addr:street":"W Union Blvd",
    "iso:country":"US",
    "sg:address":"909 W Union Blvd",
    "sg:city":"Bethlehem",
    "sg:classifiers":[
        {
            "category":"Education",
            "subcategory":"School",
            "type":"Public Place"
        }
    ],
    "sg:phone":"+1 610 866 3790",
    "sg:postcode":"18018",
    "sg:province":"PA",
    "sg:tags":[
        "high",
        "middle",
        "elementary"
    ],
    "wof:name":"Colonial Northampton Intermediate Unit No 20",
    "wof:placetype":"venue"
},
  "geometry": {"coordinates":[-75.394989,40.625156],"type":"Point"}
}