{
  "type": "Feature",
  "properties": {
    "iso:country":"US",
    "sg:address":"3601 McKnight East Dr",
    "sg:city":"Pittsburgh",
    "sg:classifiers":[
        {
            "category":"Health Services",
            "subcategory":"Doctor",
            "type":"Services"
        }
    ],
    "sg:phone":"+1   ",
    "sg:postcode":"15237",
    "sg:province":"PA",
    "sg:tags":[
        "medical"
    ],
    "wof:name":"Jackline & Baker Associates",
    "wof:placetype":"venue"
},
  "geometry": {"coordinates":[-80.007501,40.536889],"type":"Point"}
}