{
  "type": "Feature",
  "properties": {
    "iso:country":"US",
    "sg:address":"54 W Ferry St",
    "sg:city":"New Hope",
    "sg:classifiers":[
        {
            "category":"Freight",
            "type":"Transportation"
        }
    ],
    "sg:phone":"+1   ",
    "sg:postcode":"18938",
    "sg:province":"PA",
    "sg:tags":[
        "general"
    ],
    "wof:name":"Ernie Enterprises Inc",
    "wof:placetype":"venue"
},
  "geometry": {"coordinates":[-74.95341500000001,40.363445],"type":"Point"}
}