{
  "type": "Feature",
  "properties": {
    "iso:country":"US",
    "sg:address":"6741 Perkiomen Ave",
    "sg:city":"Birdsboro",
    "sg:classifiers":[
        {
            "category":"Personal",
            "subcategory":"Beauty Salon",
            "type":"Services"
        }
    ],
    "sg:phone":"+1 610 404 4247",
    "sg:postcode":"19508",
    "sg:province":"PA",
    "wof:name":"Hair We Are",
    "wof:placetype":"venue"
},
  "geometry": {"coordinates":[-75.817481,40.287872],"type":"Point"}
}