{
  "type": "Feature",
  "properties": {
    "iso:country":"US",
    "sg:address":"122 S 18th St",
    "sg:city":"Philadelphia",
    "sg:classifiers":[
        {
            "category":"Restaurant",
            "type":"Food & Drink"
        }
    ],
    "sg:phone":"+1 215 988 1211",
    "sg:postcode":"19103",
    "sg:province":"PA",
    "sg:tags":[
        "style",
        "family",
        "mongolian",
        "pan",
        "asian"
    ],
    "wof:name":"Mantra",
    "wof:placetype":"venue"
},
  "geometry": {"coordinates":[-75.17049400000001,39.95098],"type":"Point"}
}