{
  "type": "Feature",
  "properties": {
    "addr:full":"401 E High St Carlisle PA 17013",
    "addr:housenumber":"401",
    "addr:postcode":"17013",
    "addr:street":"E High St",
    "iso:country":"US",
    "sg:address":"401 E High St",
    "sg:city":"Carlisle",
    "sg:classifiers":[
        {
            "category":"Restaurant",
            "type":"Food & Drink"
        }
    ],
    "sg:menulink":"http://www.allmenus.com/pa/carlisle/215075-taco-bell/menu/",
    "sg:phone":"+1 717 258 9040",
    "sg:postcode":"17013",
    "sg:province":"PA",
    "sg:tags":[
        "mexican"
    ],
    "wof:name":"Taco Bell",
    "wof:placetype":"venue"
},
  "geometry": {"coordinates":[-77.18026500000001,40.201216],"type":"Point"}
}