{
  "type": "Feature",
  "properties": {
    "addr:full":"3 Buch Mill Rd Lititz PA 17543",
    "addr:housenumber":"3",
    "addr:postcode":"17543",
    "addr:street":"Buch Mill Rd",
    "iso:country":"US",
    "sg:address":"3 Buch Mill Rd",
    "sg:city":"Lititz",
    "sg:classifiers":[
        {
            "category":"Wholesale",
            "subcategory":"Machinery & Supplies",
            "type":"Manufacturing & Wholesale Goods"
        }
    ],
    "sg:phone":"+1   ",
    "sg:postcode":"17543",
    "sg:province":"PA",
    "sg:tags":[
        "construction",
        "nonresidential"
    ],
    "wof:name":"Country AG Service",
    "wof:placetype":"venue"
},
  "geometry": {"coordinates":[-76.254082,40.17831],"type":"Point"}
}