{
  "type": "Feature",
  "properties": {
    "iso:country":"US",
    "sg:address":"34 N. Front Street Lower Level",
    "sg:city":"Philadelphia",
    "sg:classifiers":[
        {
            "category":"Professional",
            "subcategory":"Computer Services",
            "type":"Services"
        }
    ],
    "sg:postcode":"19106",
    "sg:province":"PA",
    "sg:website":"http://LTLprints.com/",
    "wof:name":"Larger Than Life Prints",
    "wof:placetype":"venue"
},
  "geometry": {"coordinates":[-75.141943,39.950648],"type":"Point"}
}