{
  "type": "Feature",
  "properties": {
    "iso:country":"US",
    "sg:address":"103 Renaissance Dr",
    "sg:city":"Irwin",
    "sg:classifiers":[
        {
            "category":"Banks & Credit Unions",
            "subcategory":"Bank",
            "type":"Services"
        }
    ],
    "sg:phone":"+1   ",
    "sg:postcode":"15642",
    "sg:province":"PA",
    "sg:tags":[
        "broker",
        "mortgage"
    ],
    "wof:name":"West-All Financial Services",
    "wof:placetype":"venue"
},
  "geometry": {"coordinates":[-79.666552,40.30512],"type":"Point"}
}