{
  "type": "Feature",
  "properties": {
    "addr:full":"2244 Egolf Rd Bedford PA 15522",
    "addr:housenumber":"2244",
    "addr:postcode":"15522",
    "addr:street":"Egolf Rd",
    "iso:country":"US",
    "sg:address":"2244 Egolf Rd",
    "sg:city":"Bedford",
    "sg:classifiers":[
        {
            "category":"Professional",
            "type":"Services"
        }
    ],
    "sg:phone":"+1   ",
    "sg:postcode":"15522",
    "sg:province":"PA",
    "wof:name":"Robert W Turkovich",
    "wof:placetype":"venue"
},
  "geometry": {"coordinates":[-78.465822,40.004826],"type":"Point"}
}