{
  "type": "Feature",
  "properties": {
    "addr:full":"427 Foote Ave Duryea PA 18642",
    "addr:housenumber":"427",
    "addr:postcode":"18642",
    "addr:street":"Foote Ave",
    "iso:country":"US",
    "sg:address":"427 Foote Ave",
    "sg:city":"Duryea",
    "sg:classifiers":[
        {
            "category":"Health Services",
            "subcategory":"Doctor",
            "type":"Services"
        }
    ],
    "sg:phone":"+1   ",
    "sg:postcode":"18642",
    "sg:province":"PA",
    "sg:tags":[
        "medical"
    ],
    "wof:name":"Marcy A Turkos",
    "wof:placetype":"venue"
},
  "geometry": {"coordinates":[-75.7597,41.344559],"type":"Point"}
}