{
  "type": "Feature",
  "properties": {
    "iso:country":"US",
    "sg:address":"557 Wendel Rd",
    "sg:city":"Irwin",
    "sg:classifiers":[
        {
            "category":"Bars & Pubs",
            "type":"Food & Drink"
        },
        {
            "category":"Restaurant",
            "type":"Food & Drink"
        },
        {
            "category":"Bars & Pubs",
            "subcategory":"Lounge",
            "type":"Food & Drink"
        }
    ],
    "sg:phone":"+1 724 864 3222",
    "sg:postcode":"15642",
    "sg:province":"PA",
    "sg:tags":[
        "tavern",
        "grill",
        "style",
        "family",
        "cocktail"
    ],
    "wof:name":"Rodney's Restaurant & Lounge",
    "wof:placetype":"venue"
},
  "geometry": {"coordinates":[-79.675211,40.306523],"type":"Point"}
}