{
  "type": "Feature",
  "properties": {
    "addr:full":"7333 Milnor St 200 Philadelphia PA 19136",
    "addr:housenumber":"7333;200",
    "addr:postcode":"19136",
    "addr:street":"Milnor St",
    "iso:country":"US",
    "sg:address":"7333 Milnor St 200",
    "sg:city":"Philadelphia",
    "sg:classifiers":[
        {
            "category":"Home & Garden",
            "subcategory":"Household Appliances",
            "type":"Retail Goods"
        },
        {
            "category":"Building & Trades",
            "subcategory":"Cleaning & Sanitation",
            "type":"Services"
        },
        {
            "category":"Utilities",
            "subcategory":"Natural Gas",
            "type":"Services"
        }
    ],
    "sg:phone":"+1 215 331 7200",
    "sg:postcode":"19136",
    "sg:province":"PA",
    "sg:tags":[
        "purifying",
        "filters-air",
        "filters-cleaning",
        "air",
        "equipment"
    ],
    "wof:name":"Pure Air Systems",
    "wof:placetype":"venue"
},
  "geometry": {"coordinates":[-75.029234,40.024225],"type":"Point"}
}