{
  "type": "Feature",
  "properties": {
    "iso:country":"US",
    "sg:address":"2713 E Clearfield St",
    "sg:city":"Philadelphia",
    "sg:classifiers":[
        {
            "category":"Building & Trades",
            "subcategory":"Electrical",
            "type":"Services"
        }
    ],
    "sg:phone":"+1 215 423 7734",
    "sg:postcode":"19134",
    "sg:province":"PA",
    "sg:tags":[
        "industrial",
        "electrical",
        "electric",
        "contractor"
    ],
    "wof:name":"Conley Electrical Corp",
    "wof:placetype":"venue"
},
  "geometry": {"coordinates":[-75.104951,39.982901],"type":"Point"}
}