{
  "type": "Feature",
  "properties": {
    "addr:full":"2501 W 12th St Erie PA 16505",
    "addr:housenumber":"2501",
    "addr:postcode":"16505",
    "addr:street":"W 12Th St",
    "iso:country":"US",
    "sg:address":"2501 W 12th St",
    "sg:city":"Erie",
    "sg:classifiers":[
        {
            "category":"Bakery",
            "type":"Food & Drink"
        }
    ],
    "sg:menulink":"http://www.allmenus.com/pa/millcreek/102850-panera-bread/menu/",
    "sg:phone":"+1 814 833 9101",
    "sg:postcode":"16505",
    "sg:province":"PA",
    "sg:tags":[
        "american",
        "sandwich",
        "pastry"
    ],
    "wof:name":"Panera Bread",
    "wof:placetype":"venue"
},
  "geometry": {"coordinates":[-80.13625399999999,42.101405],"type":"Point"}
}