{
  "type": "Feature",
  "properties": {
    "addr:full":"2428 Cherryville Rd Northampton PA 18067",
    "addr:postcode":"2428;18067",
    "addr:street":"Cherryville Rd",
    "iso:country":"US",
    "sg:address":"2428 Cherryville Rd",
    "sg:city":"Northampton",
    "sg:classifiers":[
        {
            "category":"Restaurant",
            "type":"Food & Drink"
        }
    ],
    "sg:phone":"+1 610 261 2388",
    "sg:postcode":"18067",
    "sg:province":"PA",
    "wof:name":"M R Pizza",
    "wof:placetype":"venue"
},
  "geometry": {"coordinates":[-75.500299,40.697784],"type":"Point"}
}