{
  "type": "Feature",
  "properties": {
    "iso:country":"US",
    "sg:address":"205 Saint Charles Way",
    "sg:city":"York",
    "sg:classifiers":[
        {
            "category":"Health Services",
            "subcategory":"Doctor",
            "type":"Services"
        }
    ],
    "sg:phone":"+1   ",
    "sg:postcode":"17402",
    "sg:province":"PA",
    "sg:tags":[
        "medical"
    ],
    "wof:name":"John G Stoner MD",
    "wof:placetype":"venue"
},
  "geometry": {"coordinates":[-76.689509,39.930015],"type":"Point"}
}