{
  "type": "Feature",
  "properties": {
    "iso:country":"US",
    "sg:address":"16683 S Mead Rd",
    "sg:city":"Saegertown",
    "sg:classifiers":[
        {
            "category":"Home & Garden",
            "subcategory":"Furniture",
            "type":"Retail Goods"
        }
    ],
    "sg:phone":"+1 814 763 6098",
    "sg:postcode":"16433",
    "sg:province":"PA",
    "wof:name":"Hayfield Furniture Store",
    "wof:placetype":"venue"
},
  "geometry": {"coordinates":[-80.164326,41.69672],"type":"Point"}
}