{
  "type": "Feature",
  "properties": {
    "iso:country":"US",
    "sg:address":"12 Kelly Ave",
    "sg:city":"Lansdowne",
    "sg:classifiers":[
        {
            "category":"Building & Trades",
            "subcategory":"Construction",
            "type":"Services"
        }
    ],
    "sg:phone":"+1 610 356 1389",
    "sg:postcode":"19050",
    "sg:province":"PA",
    "sg:tags":[
        "windows"
    ],
    "wof:name":"A Window One Co",
    "wof:placetype":"venue"
},
  "geometry": {"coordinates":[-75.254131,39.940765],"type":"Point"}
}