{
  "type": "Feature",
  "properties": {
    "iso:country":"US",
    "sg:address":"4015 W 12th St",
    "sg:city":"Erie",
    "sg:classifiers":[
        {
            "category":"Social Services",
            "subcategory":"Child Care",
            "type":"Services"
        }
    ],
    "sg:phone":"+1 814 838 0322",
    "sg:postcode":"16505",
    "sg:province":"PA",
    "sg:tags":[
        "center",
        "day"
    ],
    "wof:name":"Little Wonders Child Care Center, Inc",
    "wof:placetype":"venue"
},
  "geometry": {"coordinates":[-80.17325599999999,42.089572],"type":"Point"}
}