{
  "type": "Feature",
  "properties": {
    "iso:country":"US",
    "sg:address":"2537 Meetinghouse Rd",
    "sg:city":"Jamison",
    "sg:classifiers":[
        {
            "category":"Building & Trades",
            "subcategory":"Landscaping Services",
            "type":"Services"
        }
    ],
    "sg:phone":"+1   ",
    "sg:postcode":"18929",
    "sg:province":"PA",
    "wof:name":"Open Field Fantasy",
    "wof:placetype":"venue"
},
  "geometry": {"coordinates":[-75.07504400000001,40.259074],"type":"Point"}
}