{
  "type": "Feature",
  "properties": {
    "iso:country":"US",
    "sg:address":"335 Mcchain Rd",
    "sg:city":"Finleyville",
    "sg:classifiers":[
        {
            "category":"Arts & Performance",
            "subcategory":"Theater",
            "type":"Entertainment"
        }
    ],
    "sg:phone":"+1 724 348 8110",
    "sg:postcode":"15332",
    "sg:province":"PA",
    "sg:tags":[
        "theatre"
    ],
    "wof:name":"McCaffery Mysteries",
    "wof:placetype":"venue"
},
  "geometry": {"coordinates":[-79.999568,40.275883],"type":"Point"}
}