{
  "type": "Feature",
  "properties": {
    "addr:full":"603 Williamsburg Dr Broomall PA 19008",
    "addr:housenumber":"603",
    "addr:postcode":"19008",
    "addr:street":"Williamsburg Dr",
    "iso:country":"US",
    "sg:address":"603 Williamsburg Dr",
    "sg:city":"Broomall",
    "sg:classifiers":[
        {
            "category":"Health Services",
            "subcategory":"Doctor",
            "type":"Services"
        }
    ],
    "sg:phone":"+1   ",
    "sg:postcode":"19008",
    "sg:province":"PA",
    "wof:name":"Murray C Tanz DDS",
    "wof:placetype":"venue"
},
  "geometry": {"coordinates":[-75.358396,39.960349],"type":"Point"}
}