{
  "type": "Feature",
  "properties": {
    "iso:country":"US",
    "sg:address":"254 Harrogate Rd",
    "sg:city":"Wynnewood",
    "sg:classifiers":[
        {
            "category":"Professional",
            "type":"Services"
        },
        {
            "category":"Professional",
            "subcategory":"Advertising",
            "type":"Services"
        }
    ],
    "sg:phone":"+1 610 995 2200",
    "sg:postcode":"19096",
    "sg:province":"PA",
    "sg:tags":[
        "product",
        "fair",
        "trade",
        "exposition",
        "advertising-promotional",
        "shows"
    ],
    "wof:name":"Interactive Documents",
    "wof:placetype":"venue"
},
  "geometry": {"coordinates":[-75.28053800000001,39.984723],"type":"Point"}
}