{
  "type": "Feature",
  "properties": {
    "iso:country":"US",
    "sg:address":"400 Eisenhower Blvd",
    "sg:city":"Johnstown",
    "sg:classifiers":[
        {
            "category":"Home & Garden",
            "subcategory":"Garden Supply",
            "type":"Retail Goods"
        }
    ],
    "sg:phone":"+1 814 288 2625",
    "sg:postcode":"15904",
    "sg:province":"PA",
    "sg:tags":[
        "nurseryman"
    ],
    "wof:name":"Ray's Nurseries",
    "wof:placetype":"venue"
},
  "geometry": {"coordinates":[-78.92070099999999,40.280722],"type":"Point"}
}