{
  "type": "Feature",
  "properties": {
    "iso:country":"US",
    "sg:address":"315 Logan Rd",
    "sg:city":"Imperial",
    "sg:classifiers":[
        {
            "category":"Building & Trades",
            "subcategory":"Construction",
            "type":"Services"
        }
    ],
    "sg:phone":"+1   ",
    "sg:postcode":"15126",
    "sg:province":"PA",
    "sg:tags":[
        "hanging",
        "contractor"
    ],
    "wof:name":"Allegheny Painting and Contg",
    "wof:placetype":"venue"
},
  "geometry": {"coordinates":[-80.22827100000001,40.444072],"type":"Point"}
}