{
  "type": "Feature",
  "properties": {
    "iso:country":"US",
    "sg:address":"172 Arrowhead Ln",
    "sg:city":"Breinigsville",
    "sg:classifiers":[
        {
            "category":"Manufacturing",
            "subcategory":"Food",
            "type":"Manufacturing & Wholesale Goods"
        }
    ],
    "sg:phone":"+1 610 398 7525",
    "sg:postcode":"18031",
    "sg:province":"PA",
    "sg:tags":[
        "winery",
        "mfg"
    ],
    "sg:website":"www.vynecrest.com",
    "wof:name":"Vynecrest Winery LLC",
    "wof:placetype":"venue"
},
  "geometry": {"coordinates":[-75.652919,40.562277],"type":"Point"}
}