{
  "type": "Feature",
  "properties": {
    "iso:country":"US",
    "sg:address":"4835 W 23rd St",
    "sg:city":"Erie",
    "sg:classifiers":[
        {
            "category":"Wholesale",
            "subcategory":"Machinery & Supplies",
            "type":"Manufacturing & Wholesale Goods"
        }
    ],
    "sg:phone":"+1 814 838 6373",
    "sg:postcode":"16506",
    "sg:province":"PA",
    "sg:tags":[
        "valve"
    ],
    "wof:name":"Air-Con Inc",
    "wof:placetype":"venue"
},
  "geometry": {"coordinates":[-80.18410299999999,42.072828],"type":"Point"}
}