{
  "type": "Feature",
  "properties": {
    "iso:country":"US",
    "sg:address":"300 Brush Creek Rd",
    "sg:city":"Warrendale",
    "sg:classifiers":[
        {
            "category":"Banks & Credit Unions",
            "subcategory":"Bank",
            "type":"Services"
        }
    ],
    "sg:phone":"+1 724 776 6620",
    "sg:postcode":"15086",
    "sg:province":"PA",
    "wof:name":"Pittsburgh Post Office Employees Credit Union",
    "wof:placetype":"venue"
},
  "geometry": {"coordinates":[-80.102097,40.667],"type":"Point"}
}