{
  "type": "Feature",
  "properties": {
    "addr:full":"3880 Martin Rd Huntingdon Valley PA 19006",
    "addr:housenumber":"3880",
    "addr:postcode":"19006",
    "addr:street":"Martin Rd",
    "iso:country":"US",
    "sg:address":"3880 Martin Rd",
    "sg:city":"Huntingdon Valley",
    "sg:classifiers":[
        {
            "category":"Health Services",
            "subcategory":"Doctor",
            "type":"Services"
        }
    ],
    "sg:phone":"+1   ",
    "sg:postcode":"19006",
    "sg:province":"PA",
    "wof:name":"Paul Greco",
    "wof:placetype":"venue"
},
  "geometry": {"coordinates":[-75.036629,40.146222],"type":"Point"}
}