{
  "type": "Feature",
  "properties": {
    "iso:country":"US",
    "sg:address":"321 Pearl St",
    "sg:city":"Pittsburgh",
    "sg:classifiers":[
        {
            "category":"Social Services",
            "type":"Services"
        }
    ],
    "sg:phone":"+1   ",
    "sg:postcode":"15224",
    "sg:province":"PA",
    "wof:name":"Bloomfield Section",
    "wof:placetype":"venue"
},
  "geometry": {"coordinates":[-79.949921,40.461922],"type":"Point"}
}