{
  "type": "Feature",
  "properties": {
    "addr:full":"800 Fairfax Rd Drexel Hill PA 19026",
    "addr:housenumber":"800",
    "addr:postcode":"19026",
    "addr:street":"Fairfax Rd",
    "iso:country":"US",
    "sg:address":"800 Fairfax Rd",
    "sg:city":"Drexel Hill",
    "sg:classifiers":[
        {
            "category":"Personal",
            "subcategory":"Beauty Salon",
            "type":"Services"
        }
    ],
    "sg:phone":"+1 610 853 2800",
    "sg:postcode":"19026",
    "sg:province":"PA",
    "wof:name":"Corner Salon",
    "wof:placetype":"venue"
},
  "geometry": {"coordinates":[-75.29242000000001,39.959193],"type":"Point"}
}