{
  "type": "Feature",
  "properties": {
    "iso:country":"US",
    "sg:address":"111 Maharg St",
    "sg:city":"Butler",
    "sg:classifiers":[
        {
            "category":"Building & Trades",
            "subcategory":"Cleaning & Sanitation",
            "type":"Services"
        }
    ],
    "sg:phone":"+1 724 282 6506",
    "sg:postcode":"16001",
    "sg:province":"PA",
    "sg:tags":[
        "janitor"
    ],
    "wof:name":"Rainbow Janitorial Svc",
    "wof:placetype":"venue"
},
  "geometry": {"coordinates":[-79.911294,40.867698],"type":"Point"}
}