{
  "type": "Feature",
  "properties": {
    "iso:country":"US",
    "sg:address":"934 Delaware Ave",
    "sg:city":"Bethlehem",
    "sg:classifiers":[
        {
            "category":"Health Services",
            "subcategory":"Doctor",
            "type":"Services"
        }
    ],
    "sg:phone":"+1   ",
    "sg:postcode":"18015",
    "sg:province":"PA",
    "sg:tags":[
        "medical"
    ],
    "wof:name":"Visperas Emiliana P MD",
    "wof:placetype":"venue"
},
  "geometry": {"coordinates":[-75.393219,40.606318],"type":"Point"}
}