{
  "type": "Feature",
  "properties": {
    "addr:full":"244 W Skippack Pike Ambler PA 19422",
    "addr:housenumber":"244",
    "addr:postcode":"19422",
    "addr:street":"W Skippack Pike",
    "iso:country":"US",
    "sg:address":"244 W Skippack Pike",
    "sg:city":"Ambler",
    "sg:classifiers":[
        {
            "category":"Government",
            "subcategory":"Fire Station",
            "type":"Public Place"
        }
    ],
    "sg:phone":"+1 215 643 9883",
    "sg:postcode":"19422",
    "sg:province":"PA",
    "sg:tags":[
        "department"
    ],
    "wof:name":"Centre Square Fire Co",
    "wof:placetype":"venue"
},
  "geometry": {"coordinates":[-75.254402,40.145083],"type":"Point"}
}