{
  "type": "Feature",
  "properties": {
    "iso:country":"US",
    "sg:address":"102 White Pine Dr",
    "sg:city":"Milford",
    "sg:classifiers":[
        {
            "category":"Professional",
            "type":"Services"
        }
    ],
    "sg:phone":"+1 570 296 0220",
    "sg:postcode":"18337",
    "sg:province":"PA",
    "wof:name":"Superior Concepts Inc",
    "wof:placetype":"venue"
},
  "geometry": {"coordinates":[-74.94708900000001,41.308715],"type":"Point"}
}