{
  "type": "Feature",
  "properties": {
    "addr:full":"1227 W Venango St Philadelphia PA 19140",
    "addr:housenumber":"1227",
    "addr:postcode":"19140",
    "addr:street":"W Venango St",
    "iso:country":"US",
    "sg:address":"1227 W Venango St",
    "sg:city":"Philadelphia",
    "sg:classifiers":[
        {
            "category":"Arena",
            "subcategory":"Sports Club",
            "type":"Entertainment"
        }
    ],
    "sg:phone":"+1 215 228 1442",
    "sg:postcode":"19140",
    "sg:province":"PA",
    "sg:tags":[
        "martial art"
    ],
    "wof:name":"Yong Kim",
    "wof:placetype":"venue"
},
  "geometry": {"coordinates":[-75.14877199999999,40.007426],"type":"Point"}
}