{
  "type": "Feature",
  "properties": {
    "iso:country":"US",
    "sg:address":"39 Crystal St",
    "sg:city":"East Stroudsburg",
    "sg:classifiers":[
        {
            "category":"Health Services",
            "subcategory":"Doctor",
            "type":"Services"
        }
    ],
    "sg:phone":"+1 570 476 4161",
    "sg:postcode":"18301",
    "sg:province":"PA",
    "sg:tags":[
        "physician",
        "surgeon"
    ],
    "wof:name":"Pocono Adult/Pediatric Med Grp",
    "wof:placetype":"venue"
},
  "geometry": {"coordinates":[-75.18186300000001,40.998738],"type":"Point"}
}