{
  "type": "Feature",
  "properties": {
    "addr:full":"1008 Silver Lake Rd Lewisberry PA 17339",
    "addr:housenumber":"1008",
    "addr:postcode":"17339",
    "addr:street":"Silver Lake Rd",
    "iso:country":"US",
    "sg:address":"1008 Silver Lake Rd",
    "sg:city":"Lewisberry",
    "sg:classifiers":[
        {
            "category":"Building & Trades",
            "subcategory":"Construction",
            "type":"Services"
        }
    ],
    "sg:phone":"+1   ",
    "sg:postcode":"17339",
    "sg:province":"PA",
    "sg:tags":[
        "house"
    ],
    "wof:name":"Unique Landscaping",
    "wof:placetype":"venue"
},
  "geometry": {"coordinates":[-76.889617,40.135933],"type":"Point"}
}