{
  "type": "Feature",
  "properties": {
    "iso:country":"US",
    "sg:address":"120 N Juniata St",
    "sg:city":"Lewistown",
    "sg:classifiers":[
        {
            "category":"Retail",
            "subcategory":"Auto Repair",
            "type":"Services"
        }
    ],
    "sg:phone":"+1 717 242 3940",
    "sg:postcode":"17044",
    "sg:province":"PA",
    "sg:tags":[
        "repairing",
        "automobile"
    ],
    "wof:name":"Hillard's Service Ctr",
    "wof:placetype":"venue"
},
  "geometry": {"coordinates":[-77.58228099999999,40.595622],"type":"Point"}
}