{
  "type": "Feature",
  "properties": {
    "addr:full":"1818 Colwell St Pittsburgh PA 15219",
    "addr:housenumber":"1818",
    "addr:postcode":"15219",
    "addr:street":"Colwell St",
    "iso:country":"US",
    "sg:address":"1818 Colwell St",
    "sg:city":"Pittsburgh",
    "sg:classifiers":[
        {
            "category":"Retail",
            "subcategory":"Auto Repair",
            "type":"Services"
        }
    ],
    "sg:phone":"+1 412 391 4442",
    "sg:postcode":"15219",
    "sg:province":"PA",
    "sg:tags":[
        "automobile",
        "inspection"
    ],
    "wof:name":"David Lundy Co",
    "wof:placetype":"venue"
},
  "geometry": {"coordinates":[-79.97994,40.438932],"type":"Point"}
}