{
  "type": "Feature",
  "properties": {
    "addr:full":"3310 S 20th St Philadelphia PA 19145",
    "addr:housenumber":"3310",
    "addr:postcode":"19145",
    "addr:street":"S 20Th St",
    "iso:country":"US",
    "sg:address":"3310 S 20th St",
    "sg:city":"Philadelphia",
    "sg:classifiers":[
        {
            "category":"Professional",
            "type":"Services"
        }
    ],
    "sg:phone":"+1 215 463 0499",
    "sg:postcode":"19145",
    "sg:province":"PA",
    "sg:tags":[
        "elementary",
        "school"
    ],
    "wof:name":"First Impressions Nursery School",
    "wof:placetype":"venue"
},
  "geometry": {"coordinates":[-75.18293,39.909795],"type":"Point"}
}