{
  "type": "Feature",
  "properties": {
    "iso:country":"US",
    "sg:address":"450 Erie St",
    "sg:city":"Edinboro",
    "sg:classifiers":[
        {
            "category":"Health Services",
            "subcategory":"Doctor",
            "type":"Services"
        }
    ],
    "sg:phone":"+1 814 734 1618",
    "sg:postcode":"16412",
    "sg:province":"PA",
    "sg:tags":[
        "physician",
        "surgeon"
    ],
    "wof:name":"Edinboro Medical Ctr",
    "wof:placetype":"venue"
},
  "geometry": {"coordinates":[-80.12820499999999,41.88283],"type":"Point"}
}