{
  "type": "Feature",
  "properties": {
    "iso:country":"US",
    "sg:address":"360 Poplar Church Rd",
    "sg:city":"Camp Hill",
    "sg:classifiers":[
        {
            "category":"Professional",
            "type":"Services"
        }
    ],
    "sg:phone":"+1 717 731 9649",
    "sg:postcode":"17011",
    "sg:province":"PA",
    "sg:tags":[
        "establishment"
    ],
    "wof:name":"WMIX-Mix",
    "wof:placetype":"venue"
},
  "geometry": {"coordinates":[-76.90883100000001,40.260773],"type":"Point"}
}