{
  "type": "Feature",
  "properties": {
    "iso:country":"US",
    "sg:address":"296 Airport Dr",
    "sg:city":"Middletown",
    "sg:classifiers":[
        {
            "category":"Freight",
            "type":"Transportation"
        },
        {
            "category":"Airline",
            "type":"Transportation"
        }
    ],
    "sg:phone":"+1 717 944 9711",
    "sg:postcode":"17057",
    "sg:province":"PA",
    "sg:tags":[
        "courier",
        "air"
    ],
    "sg:website":"www.emeryworld.com",
    "wof:name":"Menlo Worldwide Forwarding Inc",
    "wof:placetype":"venue"
},
  "geometry": {"coordinates":[-76.751152,40.197428],"type":"Point"}
}