{
  "type": "Feature",
  "properties": {
    "addr:full":"451 S University Ave Philadelphia PA 19104",
    "addr:housenumber":"451",
    "addr:postcode":"19104",
    "addr:street":"S University Ave",
    "iso:country":"US",
    "sg:address":"451 S University Ave",
    "sg:city":"Philadelphia",
    "sg:classifiers":[
        {
            "category":"Health Services",
            "subcategory":"Clinic",
            "type":"Services"
        }
    ],
    "sg:phone":"+1 215 596 8000",
    "sg:postcode":"19104",
    "sg:province":"PA",
    "sg:tags":[
        "counseling",
        "mental"
    ],
    "sg:website":"www.consortium-inc.org/home.html",
    "wof:name":"The Consortium",
    "wof:placetype":"venue"
},
  "geometry": {"coordinates":[-75.197148,39.946891],"type":"Point"}
}