{
  "type": "Feature",
  "properties": {
    "iso:country":"US",
    "sg:address":"5941 N Norwood St",
    "sg:city":"Philadelphia",
    "sg:classifiers":[
        {
            "category":"Professional",
            "subcategory":"Employment Agencies",
            "type":"Services"
        }
    ],
    "sg:phone":"+1 215 843 1090",
    "sg:postcode":"19138",
    "sg:province":"PA",
    "sg:tags":[
        "opportunity"
    ],
    "wof:name":"Intersolutions Incorporated",
    "wof:placetype":"venue"
},
  "geometry": {"coordinates":[-75.15666400000001,40.044409],"type":"Point"}
}