{
  "type": "Feature",
  "properties": {
    "addr:full":"163 Sleepy Hollow Rd New Bloomfield PA 17090",
    "addr:housenumber":"163",
    "addr:postcode":"17090",
    "addr:street":"Sleepy Hollow Rd",
    "iso:country":"US",
    "sg:address":"163 Sleepy Hollow Rd",
    "sg:city":"New Bloomfield",
    "sg:classifiers":[
        {
            "category":"Autos & Motor Vehicles",
            "subcategory":"Auto Supplies",
            "type":"Retail Goods"
        }
    ],
    "sg:phone":"+1 717 582 2009",
    "sg:postcode":"17090",
    "sg:province":"PA",
    "sg:tags":[
        "tire"
    ],
    "wof:name":"Deimler's Tire Svc",
    "wof:placetype":"venue"
},
  "geometry": {"coordinates":[-77.149283,40.369769],"type":"Point"}
}