{
  "type": "Feature",
  "properties": {
    "iso:country":"US",
    "sg:address":"2420 Bethlehem Pike",
    "sg:city":"Hatfield",
    "sg:classifiers":[
        {
            "category":"Education",
            "subcategory":"Dance Studio",
            "type":"Public Place"
        }
    ],
    "sg:phone":"+1 215 822 4640",
    "sg:postcode":"19440",
    "sg:province":"PA",
    "sg:tags":[
        "school",
        "instruction",
        "dancing"
    ],
    "sg:website":"www.delawarevalleydance.com",
    "wof:name":"Delaware Valley Dance Academy",
    "wof:placetype":"venue"
},
  "geometry": {"coordinates":[-75.282898,40.297798],"type":"Point"}
}