{
  "type": "Feature",
  "properties": {
    "addr:full":"209 Beaver Rd Southampton PA 18966",
    "addr:housenumber":"209",
    "addr:postcode":"18966",
    "addr:street":"Beaver Rd",
    "iso:country":"US",
    "sg:address":"209 Beaver Rd",
    "sg:city":"Southampton",
    "sg:classifiers":[
        {
            "category":"Professional",
            "type":"Services"
        }
    ],
    "sg:phone":"+1   ",
    "sg:postcode":"18966",
    "sg:province":"PA",
    "wof:name":"American Craft Collection",
    "wof:placetype":"venue"
},
  "geometry": {"coordinates":[-75.042252,40.195376],"type":"Point"}
}