{
  "type": "Feature",
  "properties": {
    "addr:full":"2100 Cemetery Rd North East PA 16428",
    "addr:housenumber":"2100",
    "addr:postcode":"16428",
    "addr:street":"Cemetery Rd",
    "iso:country":"US",
    "sg:address":"2100 Cemetery Rd",
    "sg:city":"North East",
    "sg:classifiers":[
        {
            "category":"Home & Garden",
            "subcategory":"Building Materials",
            "type":"Retail Goods"
        }
    ],
    "sg:phone":"+1   ",
    "sg:postcode":"16428",
    "sg:province":"PA",
    "wof:name":"Saras Shop",
    "wof:placetype":"venue"
},
  "geometry": {"coordinates":[-79.85587099999999,42.215999],"type":"Point"}
}