{
  "type": "Feature",
  "properties": {
    "iso:country":"US",
    "sg:address":"124 Grove St",
    "sg:city":"Wilkes Barre",
    "sg:classifiers":[
        {
            "category":"Food & Beverages",
            "subcategory":"Groceries & Convenience Stores",
            "type":"Retail Goods"
        },
        {
            "category":"Professional",
            "type":"Services"
        }
    ],
    "sg:phone":"+1 570 822 0462",
    "sg:postcode":"18702",
    "sg:province":"PA",
    "sg:tags":[
        "establishment"
    ],
    "wof:name":"Thomas Family Markets",
    "wof:placetype":"venue"
},
  "geometry": {"coordinates":[-75.89399400000001,41.234185],"type":"Point"}
}