{
  "type": "Feature",
  "properties": {
    "iso:country":"US",
    "sg:address":"3001 Pulaski Way",
    "sg:city":"Pittsburgh",
    "sg:classifiers":[
        {
            "category":"Professional",
            "type":"Services"
        }
    ],
    "sg:phone":"+1 412 688 8554",
    "sg:postcode":"15219",
    "sg:province":"PA",
    "sg:tags":[
        "establishment"
    ],
    "wof:name":"Optoplast",
    "wof:placetype":"venue"
},
  "geometry": {"coordinates":[-79.967485,40.457105],"type":"Point"}
}