{
  "type": "Feature",
  "properties": {
    "addr:full":"1320 Church St Ambridge PA 15003",
    "addr:housenumber":"1320",
    "addr:postcode":"15003",
    "addr:street":"Church St",
    "iso:country":"US",
    "sg:address":"1320 Church St",
    "sg:city":"Ambridge",
    "sg:classifiers":[
        {
            "category":"Organizations",
            "subcategory":"Religious Organization",
            "type":"Services"
        }
    ],
    "sg:phone":"+1 724 266 5618",
    "sg:postcode":"15003",
    "sg:province":"PA",
    "sg:tags":[
        "church"
    ],
    "wof:name":"St John's Lutheran Church",
    "wof:placetype":"venue"
},
  "geometry": {"coordinates":[-80.23222199999999,40.596626],"type":"Point"}
}