{
  "type": "Feature",
  "properties": {
    "iso:country":"US",
    "sg:address":"140 Derry Ct",
    "sg:city":"York",
    "sg:classifiers":[
        {
            "category":"Manufacturing",
            "subcategory":"Tools & Machinery",
            "type":"Manufacturing & Wholesale Goods"
        }
    ],
    "sg:phone":"+1 717 764 6383",
    "sg:postcode":"17406",
    "sg:province":"PA",
    "sg:tags":[
        "machine",
        "shop",
        "general"
    ],
    "wof:name":"L & S Tool & Machine Corp",
    "wof:placetype":"venue"
},
  "geometry": {"coordinates":[-76.744559,40.019175],"type":"Point"}
}