{
  "type": "Feature",
  "properties": {
    "iso:country":"US",
    "sg:address":"4710 Bath Pike",
    "sg:city":"Bethlehem",
    "sg:classifiers":[
        {
            "category":"Real Estate",
            "subcategory":"Real Estate Operator",
            "type":"Services"
        }
    ],
    "sg:phone":"+1 610 867 1712",
    "sg:postcode":"18017",
    "sg:province":"PA",
    "sg:tags":[
        "building",
        "apartment"
    ],
    "wof:name":"Kk Apts Owners",
    "wof:placetype":"venue"
},
  "geometry": {"coordinates":[-75.387614,40.680324],"type":"Point"}
}