{
  "type": "Feature",
  "properties": {
    "addr:full":"427 N Enola Rd Enola PA 17025",
    "addr:housenumber":"427",
    "addr:postcode":"17025",
    "addr:street":"N Enola Rd",
    "iso:country":"US",
    "sg:address":"427 N Enola Rd",
    "sg:city":"Enola",
    "sg:classifiers":[
        {
            "category":"Personal",
            "subcategory":"Tanning Parlor",
            "type":"Services"
        }
    ],
    "sg:phone":"+1 717 728 9433",
    "sg:postcode":"17025",
    "sg:province":"PA",
    "sg:tags":[
        "salon"
    ],
    "wof:name":"Sun Spot",
    "wof:placetype":"venue"
},
  "geometry": {"coordinates":[-76.928399,40.298442],"type":"Point"}
}