{
  "type": "Feature",
  "properties": {
    "addr:full":"103 Holly Ln Mechanicsburg PA 17050",
    "addr:housenumber":"103",
    "addr:postcode":"17050",
    "addr:street":"Holly Ln",
    "iso:country":"US",
    "sg:address":"103 Holly Ln",
    "sg:city":"Mechanicsburg",
    "sg:classifiers":[
        {
            "category":"Building & Trades",
            "subcategory":"Construction",
            "type":"Services"
        }
    ],
    "sg:phone":"+1 717 691 1929",
    "sg:postcode":"17050",
    "sg:province":"PA",
    "sg:tags":[
        "equipment",
        "supply",
        "drywall",
        "contractor"
    ],
    "wof:name":"Mcfadden Drywall",
    "wof:placetype":"venue"
},
  "geometry": {"coordinates":[-77.02849500000001,40.228879],"type":"Point"}
}