{
  "type": "Feature",
  "properties": {
    "iso:country":"US",
    "sg:address":"2 Park Rd",
    "sg:city":"Mechanicsburg",
    "sg:classifiers":[
        {
            "category":"Retail",
            "subcategory":"Car Wash",
            "type":"Services"
        }
    ],
    "sg:phone":"+1 717 766 9315",
    "sg:postcode":"17050",
    "sg:province":"PA",
    "sg:tags":[
        "automobile",
        "detail",
        "clean"
    ],
    "wof:name":"Auto Truck & Van Recondition",
    "wof:placetype":"venue"
},
  "geometry": {"coordinates":[-77.009548,40.227843],"type":"Point"}
}