{
  "type": "Feature",
  "properties": {
    "addr:full":"444 Perry Hwy Pittsburgh PA 15229",
    "addr:housenumber":"444",
    "addr:postcode":"15229",
    "addr:street":"Perry Hwy",
    "iso:country":"US",
    "sg:address":"444 Perry Hwy",
    "sg:city":"Pittsburgh",
    "sg:classifiers":[
        {
            "category":"Health Services",
            "subcategory":"Doctor",
            "type":"Services"
        }
    ],
    "sg:phone":"+1   ",
    "sg:postcode":"15229",
    "sg:province":"PA",
    "sg:tags":[
        "medical"
    ],
    "wof:name":"Hj Heck MD",
    "wof:placetype":"venue"
},
  "geometry": {"coordinates":[-80.032546,40.519879],"type":"Point"}
}