{
  "type": "Feature",
  "properties": {
    "addr:full":"1 Liberty Ln East Stroudsburg PA 18343",
    "addr:housenumber":"1",
    "addr:postcode":"18343",
    "addr:street":"Liberty Ln",
    "iso:country":"US",
    "sg:address":"1 Liberty Ln",
    "sg:city":"East Stroudsburg",
    "sg:classifiers":[
        {
            "category":"Shopping",
            "subcategory":"Clothing, Apparel, & Fashions",
            "type":"Retail Goods"
        }
    ],
    "sg:phone":"+1 570 223 1300",
    "sg:postcode":"18343",
    "sg:province":"PA",
    "sg:tags":[
        "lingerie"
    ],
    "wof:name":"Annas Classy Lingerie III LLC",
    "wof:placetype":"venue"
},
  "geometry": {"coordinates":[-75.132442,40.877933],"type":"Point"}
}