{
  "type": "Feature",
  "properties": {
    "iso:country":"US",
    "sg:address":"311 7th St",
    "sg:city":"New Kensington",
    "sg:classifiers":[
        {
            "category":"Health Services",
            "subcategory":"Doctor",
            "type":"Services"
        }
    ],
    "sg:phone":"+1   ",
    "sg:postcode":"15068",
    "sg:province":"PA",
    "sg:tags":[
        "medical"
    ],
    "wof:name":"Prakash Kaur MD",
    "wof:placetype":"venue"
},
  "geometry": {"coordinates":[-79.76567799999999,40.562447],"type":"Point"}
}