{
  "type": "Feature",
  "properties": {
    "iso:country":"US",
    "sg:address":"935 Penn Cir",
    "sg:city":"King Of Prussia",
    "sg:classifiers":[
        {
            "category":"Home & Garden",
            "subcategory":"Home Furnishings",
            "type":"Retail Goods"
        }
    ],
    "sg:phone":"+1 610 783 5804",
    "sg:postcode":"19406",
    "sg:province":"PA",
    "sg:tags":[
        "curtain",
        "made",
        "drapery"
    ],
    "wof:name":"Custom Draperies By Henri",
    "wof:placetype":"venue"
},
  "geometry": {"coordinates":[-75.41659900000001,40.103709],"type":"Point"}
}