{
  "type": "Feature",
  "properties": {
    "addr:full":"100 Boston Store Pl Erie PA 16501",
    "addr:housenumber":"100",
    "addr:postcode":"16501",
    "addr:street":"Boston Store Pl",
    "iso:country":"US",
    "sg:address":"100 Boston Store Pl",
    "sg:city":"Erie",
    "sg:classifiers":[
        {
            "category":"Real Estate",
            "subcategory":"Real Estate Operator",
            "type":"Services"
        }
    ],
    "sg:phone":"+1 814 456 9566",
    "sg:postcode":"16501",
    "sg:province":"PA",
    "sg:tags":[
        "building",
        "apartment"
    ],
    "wof:name":"Boston Store Apartments",
    "wof:placetype":"venue"
},
  "geometry": {"coordinates":[-80.08398,42.127494],"type":"Point"}
}