{
  "type": "Feature",
  "properties": {
    "iso:country":"US",
    "sg:address":"413 Burmont Rd",
    "sg:city":"Drexel Hill",
    "sg:classifiers":[
        {
            "category":"Restaurant",
            "type":"Food & Drink"
        }
    ],
    "sg:phone":"+1   ",
    "sg:postcode":"19026",
    "sg:province":"PA",
    "sg:tags":[
        "eating"
    ],
    "wof:name":"C J Demarco Inc",
    "wof:placetype":"venue"
},
  "geometry": {"coordinates":[-75.29765399999999,39.944502],"type":"Point"}
}