{
  "type": "Feature",
  "properties": {
    "addr:full":"2701 East Ave Erie PA 16504",
    "addr:housenumber":"2701",
    "addr:postcode":"16504",
    "addr:street":"East Ave",
    "iso:country":"US",
    "sg:address":"2701 East Ave",
    "sg:city":"Erie",
    "sg:classifiers":[
        {
            "category":"Organizations",
            "subcategory":"Religious Organization",
            "type":"Services"
        }
    ],
    "sg:phone":"+1 814 456 4524",
    "sg:postcode":"16504",
    "sg:province":"PA",
    "wof:name":"Holy Rosary Church",
    "wof:placetype":"venue"
},
  "geometry": {"coordinates":[-80.050209,42.118396],"type":"Point"}
}