{
  "type": "Feature",
  "properties": {
    "iso:country":"US",
    "sg:address":"520 W 28th Division Hwy",
    "sg:city":"Lititz",
    "sg:classifiers":[
        {
            "category":"Retail",
            "subcategory":"Animal Services",
            "type":"Services"
        }
    ],
    "sg:phone":"+1 717 626 6961",
    "sg:postcode":"17543",
    "sg:province":"PA",
    "sg:tags":[
        "pet",
        "boarding",
        "sitting"
    ],
    "wof:name":"Kieffer's Kennel Boarding",
    "wof:placetype":"venue"
},
  "geometry": {"coordinates":[-76.331473,40.235257],"type":"Point"}
}