{
  "type": "Feature",
  "properties": {
    "iso:country":"US",
    "sg:address":"1958 Split Rock Rd",
    "sg:city":"Lancaster",
    "sg:classifiers":[
        {
            "category":"Health Services",
            "subcategory":"Doctor",
            "type":"Services"
        }
    ],
    "sg:phone":"+1 717 569 5805",
    "sg:postcode":"17601",
    "sg:province":"PA",
    "sg:tags":[
        "physician",
        "surgeon"
    ],
    "wof:name":"William E Niblette MD",
    "wof:placetype":"venue"
},
  "geometry": {"coordinates":[-76.29297099999999,40.077983],"type":"Point"}
}