{
  "type": "Feature",
  "properties": {
    "iso:country":"US",
    "sg:address":"1520 W 26th St",
    "sg:city":"Erie",
    "sg:classifiers":[
        {
            "category":"Food & Beverages",
            "subcategory":"Groceries & Convenience Stores",
            "type":"Retail Goods"
        }
    ],
    "sg:phone":"+1 814 455 9000",
    "sg:postcode":"16508",
    "sg:province":"PA",
    "sg:tags":[
        "grocer",
        "supermarket"
    ],
    "wof:name":"Tops Friendly Markets 602",
    "wof:placetype":"venue"
},
  "geometry": {"coordinates":[-80.104619,42.10056],"type":"Point"}
}