{
  "type": "Feature",
  "properties": {
    "addr:full":"225 S 15th St Fl 29 Philadelphia PA 19102",
    "addr:housenumber":"225;29",
    "addr:postcode":"19102",
    "addr:street":"S 15Th St Fl",
    "iso:country":"US",
    "sg:address":"225 S 15th St Fl 29",
    "sg:city":"Philadelphia",
    "sg:classifiers":[
        {
            "category":"Insurance",
            "subcategory":"Hazard Insurance",
            "type":"Services"
        }
    ],
    "sg:phone":"+1 215 546 9620",
    "sg:postcode":"19102",
    "sg:province":"PA",
    "wof:name":"Progressive Insurance",
    "wof:placetype":"venue"
},
  "geometry": {"coordinates":[-75.16614199999999,39.948641],"type":"Point"}
}