{
  "type": "Feature",
  "properties": {
    "iso:country":"US",
    "sg:address":"5694 Rising Sun Ave Ste 9",
    "sg:city":"Philadelphia",
    "sg:classifiers":[
        {
            "category":"Personal",
            "subcategory":"Beauty Salon",
            "type":"Services"
        }
    ],
    "sg:phone":"+1 215 742 3007",
    "sg:postcode":"19120",
    "sg:province":"PA",
    "sg:tags":[
        "wig",
        "hair",
        "piece"
    ],
    "wof:name":"Beauty Time",
    "wof:placetype":"venue"
},
  "geometry": {"coordinates":[-75.109238,40.039694],"type":"Point"}
}