{
  "type": "Feature",
  "properties": {
    "iso:country":"US",
    "sg:address":"9951 Academy Rd",
    "sg:city":"Philadelphia",
    "sg:classifiers":[
        {
            "category":"Real Estate",
            "subcategory":"Real Estate Operator",
            "type":"Services"
        }
    ],
    "sg:phone":"+1   ",
    "sg:postcode":"19114",
    "sg:province":"PA",
    "sg:tags":[
        "building",
        "apartment"
    ],
    "wof:name":"Canerbury Court Apts Mana",
    "wof:placetype":"venue"
},
  "geometry": {"coordinates":[-74.999792,40.076526],"type":"Point"}
}