{
  "type": "Feature",
  "properties": {
    "iso:country":"US",
    "sg:address":"100 Hunsberger Dr",
    "sg:city":"Limerick",
    "sg:classifiers":[
        {
            "category":"Real Estate",
            "subcategory":"Real Estate Operator",
            "type":"Services"
        }
    ],
    "sg:phone":"+1 610 495 8921",
    "sg:postcode":"19468",
    "sg:province":"PA",
    "sg:tags":[
        "building",
        "apartment"
    ],
    "wof:name":"Summer Chase Apartment Homes",
    "wof:placetype":"venue"
},
  "geometry": {"coordinates":[-75.53537,40.234508],"type":"Point"}
}