{
  "type": "Feature",
  "properties": {
    "addr:full":"3900 Rockhill Dr Bensalem PA 19020",
    "addr:housenumber":"3900",
    "addr:postcode":"19020",
    "addr:street":"Rockhill Dr",
    "iso:country":"US",
    "sg:address":"3900 Rockhill Dr",
    "sg:city":"Bensalem",
    "sg:classifiers":[
        {
            "category":"Shopping",
            "subcategory":"Mobile Phones",
            "type":"Retail Goods"
        }
    ],
    "sg:phone":"+1 215 364 2197",
    "sg:postcode":"19020",
    "sg:province":"PA",
    "sg:website":"www.executivecellularphones.com",
    "wof:name":"Executive Cellular Phones",
    "wof:placetype":"venue"
},
  "geometry": {"coordinates":[-74.961365,40.139655],"type":"Point"}
}