{
  "type": "Feature",
  "properties": {
    "addr:full":"102 Cedar Rd Hellertown PA 18055",
    "addr:housenumber":"102",
    "addr:postcode":"18055",
    "addr:street":"Cedar Rd",
    "iso:country":"US",
    "sg:address":"102 Cedar Rd",
    "sg:city":"Hellertown",
    "sg:classifiers":[
        {
            "category":"Shopping",
            "subcategory":"Catalog Store",
            "type":"Retail Goods"
        }
    ],
    "sg:phone":"+1 610 838 8350",
    "sg:postcode":"18055",
    "sg:province":"PA",
    "sg:tags":[
        "mail",
        "order",
        "online"
    ],
    "sg:website":"http://www.helenbeedle.com",
    "wof:name":"The Galop",
    "wof:placetype":"venue"
},
  "geometry": {"coordinates":[-75.331526,40.573062],"type":"Point"}
}