{
  "type": "Feature",
  "properties": {
    "iso:country":"US",
    "sg:address":"3197 Washington Pike",
    "sg:city":"Bridgeville",
    "sg:classifiers":[
        {
            "category":"Education",
            "subcategory":"Preschool",
            "type":"Public Place"
        },
        {
            "category":"Education",
            "subcategory":"School",
            "type":"Public Place"
        }
    ],
    "sg:phone":"+1 412 221 4776",
    "sg:postcode":"15017",
    "sg:province":"PA",
    "sg:tags":[
        "elementary"
    ],
    "wof:name":"Zion Lutheran Church",
    "wof:placetype":"venue"
},
  "geometry": {"coordinates":[-80.117302,40.342899],"type":"Point"}
}