{
  "type": "Feature",
  "properties": {
    "iso:country":"US",
    "sg:address":"1369 Oakland Ave",
    "sg:city":"Levittown",
    "sg:classifiers":[
        {
            "category":"Shopping",
            "type":"Retail Goods"
        }
    ],
    "sg:phone":"+1 215 943 5323",
    "sg:postcode":"19056",
    "sg:province":"PA",
    "sg:tags":[
        "merchandise"
    ],
    "wof:name":"Shoppe 23",
    "wof:placetype":"venue"
},
  "geometry": {"coordinates":[-74.887344,40.144424],"type":"Point"}
}