{
  "type": "Feature",
  "properties": {
    "iso:country":"US",
    "sg:address":"131 State St",
    "sg:city":"Harrisburg",
    "sg:classifiers":[
        {
            "category":"Health Services",
            "subcategory":"Doctor",
            "type":"Services"
        }
    ],
    "sg:phone":"+1 717 234 4187",
    "sg:postcode":"17101",
    "sg:province":"PA",
    "sg:tags":[
        "medicine",
        "medical",
        "internal"
    ],
    "wof:name":"Grandon Raymond C",
    "wof:placetype":"venue"
},
  "geometry": {"coordinates":[-76.887199,40.263],"type":"Point"}
}