{
  "type": "Feature",
  "properties": {
    "addr:full":"733 E Main St Monongahela PA 15063",
    "addr:housenumber":"733",
    "addr:postcode":"15063",
    "addr:street":"E Main St",
    "iso:country":"US",
    "sg:address":"733 E Main St",
    "sg:city":"Monongahela",
    "sg:classifiers":[
        {
            "category":"Manufacturing",
            "subcategory":"Chemicals & Compounds",
            "type":"Manufacturing & Wholesale Goods"
        },
        {
            "category":"Wholesale",
            "subcategory":"Construction Materials",
            "type":"Manufacturing & Wholesale Goods"
        }
    ],
    "sg:phone":"+1 724 258 6873",
    "sg:postcode":"15063",
    "sg:province":"PA",
    "sg:tags":[
        "manufacturer",
        "waterproof",
        "chemicals-wholesale",
        "waterproofing",
        "mfg"
    ],
    "sg:website":"http://www.wallfirma.com",
    "wof:name":"Wall-Firma Inc",
    "wof:placetype":"venue"
},
  "geometry": {"coordinates":[-79.905345,40.193142],"type":"Point"}
}