{
  "type": "Feature",
  "properties": {
    "addr:full":"1650 Limekiln Pike Dresher PA 19025",
    "addr:housenumber":"1650",
    "addr:postcode":"19025",
    "addr:street":"Limekiln Pike",
    "iso:country":"US",
    "sg:address":"1650 Limekiln Pike",
    "sg:city":"Dresher",
    "sg:classifiers":[
        {
            "category":"Food & Beverages",
            "subcategory":"Groceries & Convenience Stores",
            "type":"Retail Goods"
        }
    ],
    "sg:phone":"+1 215 628 8055",
    "sg:postcode":"19025",
    "sg:province":"PA",
    "sg:tags":[
        "grocer"
    ],
    "wof:name":"Dresher Shop-N-Bag",
    "wof:placetype":"venue"
},
  "geometry": {"coordinates":[-75.169434,40.147343],"type":"Point"}
}