{
  "type": "Feature",
  "properties": {
    "iso:country":"US",
    "sg:address":"101 Sycamore Ave",
    "sg:city":"Folsom",
    "sg:classifiers":[
        {
            "category":"Wholesale",
            "subcategory":"Construction Materials",
            "type":"Manufacturing & Wholesale Goods"
        }
    ],
    "sg:phone":"+1 484 494 0273",
    "sg:postcode":"19033",
    "sg:province":"PA",
    "sg:tags":[
        "fence"
    ],
    "wof:name":"Folsom Wholesale Fence Co",
    "wof:placetype":"venue"
},
  "geometry": {"coordinates":[-75.32148599999999,39.890437],"type":"Point"}
}