{
  "type": "Feature",
  "properties": {
    "addr:full":"501 Avery St Pittsburgh PA 15212",
    "addr:housenumber":"501",
    "addr:postcode":"15212",
    "addr:street":"Avery St",
    "iso:country":"US",
    "sg:address":"501 Avery St",
    "sg:city":"Pittsburgh",
    "sg:classifiers":[
        {
            "category":"Organizations",
            "subcategory":"Religious Organization",
            "type":"Services"
        }
    ],
    "sg:phone":"+1 412 321 1328",
    "sg:postcode":"15212",
    "sg:province":"PA",
    "sg:tags":[
        "church"
    ],
    "wof:name":"Allegheny United Church-Christ",
    "wof:placetype":"venue"
},
  "geometry": {"coordinates":[-79.999728,40.452924],"type":"Point"}
}