{
  "type": "Feature",
  "properties": {
    "addr:full":"2426 Duss Ave Ambridge PA 15003",
    "addr:housenumber":"2426",
    "addr:postcode":"15003",
    "addr:street":"Duss Ave",
    "iso:country":"US",
    "sg:address":"2426 Duss Ave",
    "sg:city":"Ambridge",
    "sg:classifiers":[
        {
            "category":"Home & Garden",
            "subcategory":"Hardware",
            "type":"Retail Goods"
        }
    ],
    "sg:phone":"+1 724 266 8675",
    "sg:postcode":"15003",
    "sg:province":"PA",
    "sg:tags":[
        "plumbing"
    ],
    "wof:name":"Guzyk Lock Safe & Security Co",
    "wof:placetype":"venue"
},
  "geometry": {"coordinates":[-80.226197,40.605807],"type":"Point"}
}