{
  "type": "Feature",
  "properties": {
    "addr:full":"942 Mount Zion Rd Lebanon PA 17046",
    "addr:housenumber":"942",
    "addr:postcode":"17046",
    "addr:street":"Mount Zion Rd",
    "iso:country":"US",
    "sg:address":"942 Mount Zion Rd",
    "sg:city":"Lebanon",
    "sg:classifiers":[
        {
            "category":"Freight",
            "type":"Transportation"
        }
    ],
    "sg:phone":"+1   ",
    "sg:postcode":"17046",
    "sg:province":"PA",
    "sg:tags":[
        "operator",
        "trucking"
    ],
    "wof:name":"Dale E Hawkins Trucking",
    "wof:placetype":"venue"
},
  "geometry": {"coordinates":[-76.39216399999999,40.368011],"type":"Point"}
}