{
  "type": "Feature",
  "properties": {
    "addr:full":"1016 E Willow Grove Ave Glenside PA 19038",
    "addr:housenumber":"1016",
    "addr:postcode":"19038",
    "addr:street":"E Willow Grove Ave",
    "iso:country":"US",
    "sg:address":"1016 E Willow Grove Ave",
    "sg:city":"Glenside",
    "sg:classifiers":[
        {
            "category":"Insurance",
            "subcategory":"Insurance Agent",
            "type":"Services"
        }
    ],
    "sg:phone":"+1   ",
    "sg:postcode":"19038",
    "sg:province":"PA",
    "wof:name":"Prudential",
    "wof:placetype":"venue"
},
  "geometry": {"coordinates":[-75.18808799999999,40.082829],"type":"Point"}
}