{
  "type": "Feature",
  "properties": {
    "iso:country":"US",
    "sg:address":"617 Dreshertown Rd",
    "sg:city":"Fort Washington",
    "sg:classifiers":[
        {
            "category":"Building & Trades",
            "subcategory":"Electrical",
            "type":"Services"
        }
    ],
    "sg:phone":"+1   ",
    "sg:postcode":"19034",
    "sg:province":"PA",
    "sg:tags":[
        "electrical",
        "contractor"
    ],
    "wof:name":"Phelan Fine Lighting",
    "wof:placetype":"venue"
},
  "geometry": {"coordinates":[-75.169763,40.136293],"type":"Point"}
}