{
  "type": "Feature",
  "properties": {
    "addr:full":"1110 E Columbia Ave Philadelphia PA 19125",
    "addr:housenumber":"1110",
    "addr:postcode":"19125",
    "addr:street":"E Columbia Ave",
    "iso:country":"US",
    "sg:address":"1110 E Columbia Ave",
    "sg:city":"Philadelphia",
    "sg:classifiers":[
        {
            "category":"Professional",
            "type":"Services"
        }
    ],
    "sg:phone":"+1   ",
    "sg:postcode":"19125",
    "sg:province":"PA",
    "wof:name":"Spabarn",
    "wof:placetype":"venue"
},
  "geometry": {"coordinates":[-75.12997,39.969074],"type":"Point"}
}