{
  "type": "Feature",
  "properties": {
    "addr:full":"1865 Welsh Rd Philadelphia PA 19115",
    "addr:housenumber":"1865",
    "addr:postcode":"19115",
    "addr:street":"Welsh Rd",
    "iso:country":"US",
    "sg:address":"1865 Welsh Rd",
    "sg:city":"Philadelphia",
    "sg:classifiers":[
        {
            "category":"Professional",
            "subcategory":"Business Services",
            "type":"Services"
        }
    ],
    "sg:phone":"+1 215 464 9203",
    "sg:postcode":"19115",
    "sg:province":"PA",
    "sg:tags":[
        "paralegal"
    ],
    "wof:name":"Pro Se Paralegals",
    "wof:placetype":"venue"
},
  "geometry": {"coordinates":[-75.038113,40.083997],"type":"Point"}
}