{
  "type": "Feature",
  "properties": {
    "iso:country":"US",
    "sg:address":"916 5th Ave",
    "sg:city":"Pittsburgh",
    "sg:classifiers":[
        {
            "category":"Banks & Credit Unions",
            "subcategory":"Bank",
            "type":"Services"
        }
    ],
    "sg:phone":"+1 412 281 0126",
    "sg:postcode":"15219",
    "sg:province":"PA",
    "sg:tags":[
        "loan",
        "real estate"
    ],
    "wof:name":"Corinthian Mortgage",
    "wof:placetype":"venue"
},
  "geometry": {"coordinates":[-79.991456,40.438756],"type":"Point"}
}