{
  "type": "Feature",
  "properties": {
    "iso:country":"US",
    "sg:address":"2121 Robinson Blvd",
    "sg:city":"Pittsburgh",
    "sg:classifiers":[
        {
            "category":"Manufacturing",
            "subcategory":"Chemicals & Compounds",
            "type":"Manufacturing & Wholesale Goods"
        },
        {
            "category":"Wholesale",
            "subcategory":"Non-durable Goods",
            "type":"Manufacturing & Wholesale Goods"
        }
    ],
    "sg:phone":"+1 412 243 2121",
    "sg:postcode":"15221",
    "sg:province":"PA",
    "sg:tags":[
        "merchandise-wholesale"
    ],
    "wof:name":"Ideal Distributors Inc",
    "wof:placetype":"venue"
},
  "geometry": {"coordinates":[-79.866058,40.45295],"type":"Point"}
}