{
  "type": "Feature",
  "properties": {
    "addr:full":"2519 Mount Rose Ave York PA 17402",
    "addr:housenumber":"2519",
    "addr:postcode":"17402",
    "addr:street":"Mount Rose Ave",
    "iso:country":"US",
    "sg:address":"2519 Mount Rose Ave",
    "sg:city":"York",
    "sg:classifiers":[
        {
            "category":"Restaurant",
            "type":"Food & Drink"
        }
    ],
    "sg:phone":"+1   ",
    "sg:postcode":"17402",
    "sg:province":"PA",
    "sg:tags":[
        "personal",
        "drinking",
        "eating"
    ],
    "wof:name":"Eagles Nest",
    "wof:placetype":"venue"
},
  "geometry": {"coordinates":[-76.668294,39.958549],"type":"Point"}
}