{
  "type": "Feature",
  "properties": {
    "iso:country":"US",
    "sg:address":"800 N Easton Rd",
    "sg:city":"Doylestown",
    "sg:classifiers":[
        {
            "category":"Retail",
            "subcategory":"Veterinary Services",
            "type":"Services"
        }
    ],
    "sg:phone":"+1 215 345 7782",
    "sg:postcode":"18901",
    "sg:province":"PA",
    "sg:tags":[
        "veterinarian"
    ],
    "wof:name":"Doylestown Animal Medical Clinic",
    "wof:placetype":"venue"
},
  "geometry": {"coordinates":[-75.13020299999999,40.335602],"type":"Point"}
}