{
  "type": "Feature",
  "properties": {
    "iso:country":"US",
    "sg:address":"385 Centre St",
    "sg:city":"Parryville",
    "sg:classifiers":[
        {
            "category":"Education",
            "subcategory":"Special Training",
            "type":"Public Place"
        }
    ],
    "sg:phone":"+1 610 852 2631",
    "sg:postcode":"18244",
    "sg:province":"PA",
    "sg:tags":[
        "instruction",
        "music"
    ],
    "wof:name":"Adele Kunkle Piano Instruction",
    "wof:placetype":"venue"
},
  "geometry": {"coordinates":[-75.67486700000001,40.821378],"type":"Point"}
}