{
  "type": "Feature",
  "properties": {
    "addr:full":"147 E High St Waynesburg PA 15370",
    "addr:housenumber":"147",
    "addr:postcode":"15370",
    "addr:street":"E High St",
    "iso:country":"US",
    "sg:address":"147 E High St",
    "sg:city":"Waynesburg",
    "sg:classifiers":[
        {
            "category":"Shopping",
            "subcategory":"Computers & Home Electronics",
            "type":"Retail Goods"
        }
    ],
    "sg:phone":"+1 724 852 2025",
    "sg:postcode":"15370",
    "sg:province":"PA",
    "sg:tags":[
        "equipment",
        "dealer"
    ],
    "wof:name":"PC Squared",
    "wof:placetype":"venue"
},
  "geometry": {"coordinates":[-80.184861,39.896514],"type":"Point"}
}