{
  "type": "Feature",
  "properties": {
    "iso:country":"US",
    "sg:address":"104 Blue Mountain Dr",
    "sg:city":"New Ringgold",
    "sg:classifiers":[
        {
            "category":"Retail",
            "subcategory":"Repair Shop",
            "type":"Services"
        }
    ],
    "sg:phone":"+1 570 386 4000",
    "sg:postcode":"17960",
    "sg:province":"PA",
    "sg:tags":[
        "plumbing",
        "drain",
        "cleaning",
        "sewer"
    ],
    "wof:name":"Power Rooter W Sewer & Drains",
    "wof:placetype":"venue"
},
  "geometry": {"coordinates":[-75.896992,40.693472],"type":"Point"}
}