{
  "type": "Feature",
  "properties": {
    "iso:country":"US",
    "sg:address":"6003 Gem Bridge Rd",
    "sg:city":"Needmore",
    "sg:classifiers":[
        {
            "category":"Farming",
            "subcategory":"Dairy Farm",
            "type":"Manufacturing & Wholesale Goods"
        },
        {
            "category":"Farming",
            "subcategory":"Farm",
            "type":"Manufacturing & Wholesale Goods"
        }
    ],
    "sg:phone":"+1 717 573 4131",
    "sg:postcode":"17238",
    "sg:province":"PA",
    "wof:name":"Glenn Mellot",
    "wof:placetype":"venue"
},
  "geometry": {"coordinates":[-78.106109,39.82686],"type":"Point"}
}