{
  "type": "Feature",
  "properties": {
    "iso:country":"US",
    "sg:address":"5845 Master St",
    "sg:city":"Philadelphia",
    "sg:classifiers":[
        {
            "category":"Organizations",
            "subcategory":"Religious Organization",
            "type":"Services"
        }
    ],
    "sg:phone":"+1 215 871 0248",
    "sg:postcode":"19131",
    "sg:province":"PA",
    "sg:tags":[
        "church"
    ],
    "wof:name":"Victory & Praise Productions",
    "wof:placetype":"venue"
},
  "geometry": {"coordinates":[-75.23789600000001,39.973045],"type":"Point"}
}