{
  "type": "Feature",
  "properties": {
    "iso:country":"US",
    "sg:address":"507 S 9th St",
    "sg:city":"Youngwood",
    "sg:classifiers":[
        {
            "category":"Education",
            "subcategory":"Dance Studio",
            "type":"Public Place"
        }
    ],
    "sg:phone":"+1 724 925 3884",
    "sg:postcode":"15697",
    "sg:province":"PA",
    "sg:tags":[
        "instruction",
        "dancing"
    ],
    "wof:name":"Peoria School Of Ballroom",
    "wof:placetype":"venue"
},
  "geometry": {"coordinates":[-79.588925,40.233437],"type":"Point"}
}