{
  "type": "Feature",
  "properties": {
    "iso:country":"US",
    "sg:address":"7 E Broad St",
    "sg:city":"Bethlehem",
    "sg:classifiers":[
        {
            "category":"Professional",
            "subcategory":"Lawyer & Legal Services",
            "type":"Services"
        }
    ],
    "sg:phone":"+1 610 866 9220",
    "sg:postcode":"18018",
    "sg:province":"PA",
    "sg:tags":[
        "attorney"
    ],
    "wof:name":"Judith A Dexter",
    "wof:placetype":"venue"
},
  "geometry": {"coordinates":[-75.377672,40.622348],"type":"Point"}
}