{
  "type": "Feature",
  "properties": {
    "iso:country":"US",
    "sg:address":"217 Bohn Rd",
    "sg:city":"Bedford",
    "sg:classifiers":[
        {
            "category":"Autos & Motor Vehicles",
            "subcategory":"Automobile Sales",
            "type":"Retail Goods"
        }
    ],
    "sg:phone":"+1 814 623 2451",
    "sg:postcode":"15522",
    "sg:province":"PA",
    "sg:tags":[
        "car",
        "dealer"
    ],
    "wof:name":"Chet Bohn Cars",
    "wof:placetype":"venue"
},
  "geometry": {"coordinates":[-78.530573,40.086953],"type":"Point"}
}