{
  "type": "Feature",
  "properties": {
    "iso:country":"US",
    "sg:address":"839 Radclyffe St",
    "sg:city":"Bethlehem",
    "sg:classifiers":[
        {
            "category":"Building & Trades",
            "subcategory":"Construction",
            "type":"Services"
        }
    ],
    "sg:phone":"+1 610 509 9430",
    "sg:postcode":"18017",
    "sg:province":"PA",
    "sg:tags":[
        "handyman"
    ],
    "wof:name":"Shemp's Computer Repair & Upgr",
    "wof:placetype":"venue"
},
  "geometry": {"coordinates":[-75.357681,40.63207],"type":"Point"}
}