{
  "type": "Feature",
  "properties": {
    "addr:full":"650 Main St Clarion PA 16214",
    "addr:housenumber":"650",
    "addr:postcode":"16214",
    "addr:street":"Main St",
    "iso:country":"US",
    "sg:address":"650 Main St",
    "sg:city":"Clarion",
    "sg:classifiers":[
        {
            "category":"Banks & Credit Unions",
            "subcategory":"Bank",
            "type":"Services"
        }
    ],
    "sg:phone":"+1 814 226 6307",
    "sg:postcode":"16214",
    "sg:province":"PA",
    "sg:website":"www.stbank.com",
    "wof:name":"S & T Bank",
    "wof:placetype":"venue"
},
  "geometry": {"coordinates":[-79.38288799999999,41.213506],"type":"Point"}
}