{
  "type": "Feature",
  "properties": {
    "iso:country":"US",
    "sg:address":"2135 Forest St",
    "sg:city":"Lehighton",
    "sg:classifiers":[
        {
            "category":"Autos & Motor Vehicles",
            "subcategory":"Automobile Sales",
            "type":"Retail Goods"
        }
    ],
    "sg:phone":"+1 610 379 0445",
    "sg:postcode":"18235",
    "sg:province":"PA",
    "sg:tags":[
        "used"
    ],
    "wof:name":"Beltzville Auto Sales",
    "wof:placetype":"venue"
},
  "geometry": {"coordinates":[-75.625344,40.888301],"type":"Point"}
}