{
  "type": "Feature",
  "properties": {
    "iso:country":"US",
    "sg:address":"2412 Ferguson Rd",
    "sg:city":"Allison Park",
    "sg:classifiers":[
        {
            "category":"Restaurant",
            "type":"Food & Drink"
        }
    ],
    "sg:menulink":"http://www.allmenus.com/pa/hampton/62111-pasqualies-pizzeria/menu/",
    "sg:phone":"+1 412 487 2446",
    "sg:postcode":"15101",
    "sg:province":"PA",
    "sg:tags":[
        "american",
        "pizza"
    ],
    "wof:name":"Pasqualie's Pizzeria",
    "wof:placetype":"venue"
},
  "geometry": {"coordinates":[-79.972472,40.55476],"type":"Point"}
}