{
  "type": "Feature",
  "properties": {
    "iso:country":"US",
    "sg:address":"1020 S 10th St",
    "sg:city":"Philadelphia",
    "sg:classifiers":[
        {
            "category":"Organizations",
            "subcategory":"Religious Organization",
            "type":"Services"
        }
    ],
    "sg:phone":"+1 215 389 2281",
    "sg:postcode":"19147",
    "sg:province":"PA",
    "sg:tags":[
        "place",
        "worship",
        "church"
    ],
    "wof:name":"Christs United Presbyterian Ch",
    "wof:placetype":"venue"
},
  "geometry": {"coordinates":[-75.15979400000001,39.937418],"type":"Point"}
}