{
  "type": "Feature",
  "properties": {
    "addr:full":"145 Royal St Reedsville PA 17084",
    "addr:housenumber":"145",
    "addr:postcode":"17084",
    "addr:street":"Royal St",
    "iso:country":"US",
    "sg:address":"145 Royal St",
    "sg:city":"Reedsville",
    "sg:classifiers":[
        {
            "category":"Freight",
            "type":"Transportation"
        }
    ],
    "sg:phone":"+1   ",
    "sg:postcode":"17084",
    "sg:province":"PA",
    "sg:tags":[
        "courier"
    ],
    "wof:name":"UPS",
    "wof:placetype":"venue"
},
  "geometry": {"coordinates":[-77.590907,40.695479],"type":"Point"}
}