{
  "type": "Feature",
  "properties": {
    "iso:country":"US",
    "sg:address":"6738 Ruppsville Rd",
    "sg:city":"Allentown",
    "sg:classifiers":[
        {
            "category":"Building & Trades",
            "subcategory":"Landscaping Services",
            "type":"Services"
        }
    ],
    "sg:phone":"+1   ",
    "sg:postcode":"18106",
    "sg:province":"PA",
    "sg:tags":[
        "tree"
    ],
    "wof:name":"Craico Tree Service Inc",
    "wof:placetype":"venue"
},
  "geometry": {"coordinates":[-75.60161100000001,40.582527],"type":"Point"}
}