{
  "type": "Feature",
  "properties": {
    "iso:country":"US",
    "sg:address":"205 Boyle Rd",
    "sg:city":"Fairfield",
    "sg:classifiers":[
        {
            "category":"Farming",
            "subcategory":"Livestock Farm",
            "type":"Manufacturing & Wholesale Goods"
        }
    ],
    "sg:phone":"+1   ",
    "sg:postcode":"17320",
    "sg:province":"PA",
    "sg:tags":[
        "beef",
        "equine",
        "feedlot",
        "cattle"
    ],
    "wof:name":"Rose Yellow Ranch",
    "wof:placetype":"venue"
},
  "geometry": {"coordinates":[-77.313221,39.728344],"type":"Point"}
}