{
  "type": "Feature",
  "properties": {
    "addr:full":"10501 Cross Station Rd Girard PA 16417",
    "addr:housenumber":"10501",
    "addr:postcode":"16417",
    "addr:street":"Cross Station Rd",
    "iso:country":"US",
    "sg:address":"10501 Cross Station Rd",
    "sg:city":"Girard",
    "sg:classifiers":[
        {
            "category":"Building & Trades",
            "subcategory":"Construction",
            "type":"Services"
        }
    ],
    "sg:phone":"+1 814 774 9989",
    "sg:postcode":"16417",
    "sg:province":"PA",
    "sg:tags":[
        "excavation",
        "contractor"
    ],
    "wof:name":"Bruce K Vollbrecht",
    "wof:placetype":"venue"
},
  "geometry": {"coordinates":[-80.346851,41.970094],"type":"Point"}
}