{
  "type": "Feature",
  "properties": {
    "iso:country":"US",
    "sg:address":"156 W Milton St",
    "sg:city":"Easton",
    "sg:classifiers":[
        {
            "category":"Shopping",
            "type":"Retail Goods"
        }
    ],
    "sg:phone":"+1   ",
    "sg:postcode":"18042",
    "sg:province":"PA",
    "sg:tags":[
        "merchandise"
    ],
    "wof:name":"House of Lloyd",
    "wof:placetype":"venue"
},
  "geometry": {"coordinates":[-75.208927,40.677526],"type":"Point"}
}