{
  "type": "Feature",
  "properties": {
    "addr:full":"210 W Girard Ave Philadelphia PA 19123",
    "addr:housenumber":"210",
    "addr:postcode":"19123",
    "addr:street":"W Girard Ave",
    "iso:country":"US",
    "sg:address":"210 W Girard Ave",
    "sg:city":"Philadelphia",
    "sg:classifiers":[
        {
            "category":"Manufacturing",
            "subcategory":"Chemicals & Compounds",
            "type":"Manufacturing & Wholesale Goods"
        },
        {
            "category":"Wholesale",
            "subcategory":"Painting Supplies",
            "type":"Manufacturing & Wholesale Goods"
        },
        {
            "category":"Manufacturing",
            "subcategory":"Building Materials",
            "type":"Manufacturing & Wholesale Goods"
        }
    ],
    "sg:phone":"+1 215 625 8300",
    "sg:postcode":"19123",
    "sg:province":"PA",
    "sg:tags":[
        "equipment",
        "paint-wholesale",
        "paint",
        "painter",
        "manufacturer"
    ],
    "sg:website":"http://www.colomypaint.benmoorepaints.com",
    "wof:name":"Colomy Paint and Decorating LLC",
    "wof:placetype":"venue"
},
  "geometry": {"coordinates":[-75.139942,39.969559],"type":"Point"}
}