{
  "type": "Feature",
  "properties": {
    "iso:country":"US",
    "sg:address":"21 Spring Garden Mill Dr",
    "sg:city":"Newtown",
    "sg:classifiers":[
        {
            "category":"Shopping",
            "subcategory":"Books",
            "type":"Retail Goods"
        }
    ],
    "sg:phone":"+1   ",
    "sg:postcode":"18940",
    "sg:province":"PA",
    "wof:name":"Philadelphia Chapter One",
    "wof:placetype":"venue"
},
  "geometry": {"coordinates":[-74.972578,40.220351],"type":"Point"}
}