{
  "type": "Feature",
  "properties": {
    "iso:country":"US",
    "sg:address":"451 Buch Mill Rd",
    "sg:city":"Lititz",
    "sg:classifiers":[
        {
            "category":"Farming",
            "subcategory":"Dairy Farm",
            "type":"Manufacturing & Wholesale Goods"
        }
    ],
    "sg:phone":"+1   ",
    "sg:postcode":"17543",
    "sg:province":"PA",
    "wof:name":"Earl Obertholtzer",
    "wof:placetype":"venue"
},
  "geometry": {"coordinates":[-76.255117,40.174579],"type":"Point"}
}