{
  "type": "Feature",
  "properties": {
    "iso:country":"US",
    "sg:address":"613 W Valley Forge Rd",
    "sg:city":"King Of Prussia",
    "sg:classifiers":[
        {
            "category":"Wholesale",
            "subcategory":"Hardware",
            "type":"Manufacturing & Wholesale Goods"
        }
    ],
    "sg:phone":"+1   ",
    "sg:postcode":"19406",
    "sg:province":"PA",
    "sg:tags":[
        "control",
        "elements",
        "electrical",
        "heating",
        "temperature"
    ],
    "wof:name":"P P S",
    "wof:placetype":"venue"
},
  "geometry": {"coordinates":[-75.396759,40.103851],"type":"Point"}
}