{
  "type": "Feature",
  "properties": {
    "addr:full":"220 W 2nd Ave Latrobe PA 15650",
    "addr:housenumber":"220",
    "addr:postcode":"15650",
    "addr:street":"W 2Nd Ave",
    "iso:country":"US",
    "sg:address":"220 W 2nd Ave",
    "sg:city":"Latrobe",
    "sg:classifiers":[
        {
            "category":"Health Services",
            "subcategory":"Hospital",
            "type":"Services"
        }
    ],
    "sg:phone":"+1 724 537 5677",
    "sg:postcode":"15650",
    "sg:province":"PA",
    "sg:tags":[
        "nurse",
        "registry"
    ],
    "wof:name":"John L Puchan Mrs Nurse",
    "wof:placetype":"venue"
},
  "geometry": {"coordinates":[-79.395171,40.321428],"type":"Point"}
}