{
  "type": "Feature",
  "properties": {
    "iso:country":"US",
    "sg:address":"117 S Eagle Rd",
    "sg:city":"Havertown",
    "sg:classifiers":[
        {
            "category":"Freight",
            "type":"Transportation"
        }
    ],
    "sg:phone":"+1   ",
    "sg:postcode":"19083",
    "sg:province":"PA",
    "sg:tags":[
        "arrangement"
    ],
    "wof:name":"B K Trucking",
    "wof:placetype":"venue"
},
  "geometry": {"coordinates":[-75.32017,39.970367],"type":"Point"}
}