{
  "type": "Feature",
  "properties": {
    "addr:full":"1411 Bethlehem Pike Flourtown PA 19031",
    "addr:housenumber":"1411",
    "addr:postcode":"19031",
    "addr:street":"Bethlehem Pike",
    "iso:country":"US",
    "sg:address":"1411 Bethlehem Pike",
    "sg:city":"Flourtown",
    "sg:classifiers":[
        {
            "category":"Personal",
            "subcategory":"Beauty Salon",
            "type":"Services"
        }
    ],
    "sg:phone":"+1 215 233 9954",
    "sg:postcode":"19031",
    "sg:province":"PA",
    "wof:name":"Hair Flair",
    "wof:placetype":"venue"
},
  "geometry": {"coordinates":[-75.213223,40.10424],"type":"Point"}
}