{
  "type": "Feature",
  "properties": {
    "addr:full":"2500 E High St Pottstown PA 19464",
    "addr:housenumber":"2500",
    "addr:postcode":"19464",
    "addr:street":"E High St",
    "iso:country":"US",
    "sg:address":"2500 E High St",
    "sg:city":"Pottstown",
    "sg:classifiers":[
        {
            "category":"Real Estate",
            "subcategory":"Real Estate Agent",
            "type":"Services"
        }
    ],
    "sg:phone":"+1   ",
    "sg:postcode":"19464",
    "sg:province":"PA",
    "wof:name":"All County Properties",
    "wof:placetype":"venue"
},
  "geometry": {"coordinates":[-75.585424,40.244423],"type":"Point"}
}