{
  "type": "Feature",
  "properties": {
    "iso:country":"US",
    "sg:address":"2975 E State St",
    "sg:city":"Hermitage",
    "sg:classifiers":[
        {
            "category":"Sports & Exercise",
            "subcategory":"Bowling",
            "type":"Entertainment"
        }
    ],
    "sg:phone":"+1   ",
    "sg:postcode":"16148",
    "sg:province":"PA",
    "sg:tags":[
        "center"
    ],
    "wof:name":"Sunset Lanes",
    "wof:placetype":"venue"
},
  "geometry": {"coordinates":[-80.454509,41.233454],"type":"Point"}
}