{
  "type": "Feature",
  "properties": {
    "iso:country":"US",
    "sg:address":"117 Whitaker Rd",
    "sg:city":"Saxonburg",
    "sg:classifiers":[
        {
            "category":"Education",
            "subcategory":"Special Training",
            "type":"Public Place"
        }
    ],
    "sg:phone":"+1 724 352 4794",
    "sg:postcode":"16056",
    "sg:province":"PA",
    "sg:tags":[
        "aid",
        "instruction",
        "first"
    ],
    "wof:name":"Keep Up The Beat",
    "wof:placetype":"venue"
},
  "geometry": {"coordinates":[-79.835978,40.755298],"type":"Point"}
}