{
  "type": "Feature",
  "properties": {
    "iso:country":"US",
    "sg:address":"1719 Phillippy Rd",
    "sg:city":"Greencastle",
    "sg:classifiers":[
        {
            "category":"Farming",
            "subcategory":"Dairy Farm",
            "type":"Manufacturing & Wholesale Goods"
        }
    ],
    "sg:phone":"+1   ",
    "sg:postcode":"17225",
    "sg:province":"PA",
    "sg:tags":[
        "corn"
    ],
    "wof:name":"Myron EBY",
    "wof:placetype":"venue"
},
  "geometry": {"coordinates":[-77.663453,39.803826],"type":"Point"}
}