{
  "type": "Feature",
  "properties": {
    "iso:country":"US",
    "sg:address":"RR 2",
    "sg:city":"Newport",
    "sg:classifiers":[
        {
            "category":"Place Of Worship",
            "subcategory":"Church",
            "type":"Public Place"
        },
        {
            "category":"Place Of Worship",
            "type":"Public Place"
        }
    ],
    "sg:phone":"+1 717 567 3709",
    "sg:postcode":"17074",
    "sg:province":"PA",
    "sg:tags":[
        "churches-interdenominational",
        "churches-various",
        "denomination"
    ],
    "wof:name":"Smith Tire & Service Center",
    "wof:placetype":"venue"
},
  "geometry": {"coordinates":[-77.141884,40.458736],"type":"Point"}
}