{
  "type": "Feature",
  "properties": {
    "addr:full":"120 W Main St Ligonier PA 15658",
    "addr:housenumber":"120",
    "addr:postcode":"15658",
    "addr:street":"W Main St",
    "iso:country":"US",
    "sg:address":"120 W Main St",
    "sg:city":"Ligonier",
    "sg:classifiers":[
        {
            "category":"Education",
            "subcategory":"Library",
            "type":"Public Place"
        }
    ],
    "sg:phone":"+1 724 238 6451",
    "sg:postcode":"15658",
    "sg:province":"PA",
    "sg:website":"www.ligonierlibrary.org",
    "wof:name":"Ligonier Valley Library",
    "wof:placetype":"venue"
},
  "geometry": {"coordinates":[-79.23792299999999,40.243197],"type":"Point"}
}