{
  "type": "Feature",
  "properties": {
    "iso:country":"US",
    "sg:address":"728 Rodman Ave",
    "sg:city":"Jenkintown",
    "sg:classifiers":[
        {
            "category":"Shopping",
            "subcategory":"Computers & Home Electronics",
            "type":"Retail Goods"
        }
    ],
    "sg:phone":"+1 215 887 7200",
    "sg:postcode":"19046",
    "sg:province":"PA",
    "sg:tags":[
        "software"
    ],
    "wof:name":"E Z Net Solutions",
    "wof:placetype":"venue"
},
  "geometry": {"coordinates":[-75.127213,40.103469],"type":"Point"}
}