{
  "type": "Feature",
  "properties": {
    "addr:full":"2060 Millersville Rd Lancaster PA 17603",
    "addr:housenumber":"2060",
    "addr:postcode":"17603",
    "addr:street":"Millersville Rd",
    "iso:country":"US",
    "sg:address":"2060 Millersville Rd",
    "sg:city":"Lancaster",
    "sg:classifiers":[
        {
            "category":"Building & Trades",
            "subcategory":"Landscaping Services",
            "type":"Services"
        }
    ],
    "sg:phone":"+1 717 872 1800",
    "sg:postcode":"17603",
    "sg:province":"PA",
    "wof:name":"Honeysuckle Hill Farm",
    "wof:placetype":"venue"
},
  "geometry": {"coordinates":[-76.322789,39.997873],"type":"Point"}
}