{
  "type": "Feature",
  "properties": {
    "iso:country":"US",
    "sg:address":"150 Pond Rd",
    "sg:city":"Felton",
    "sg:classifiers":[
        {
            "category":"Building & Trades",
            "subcategory":"Construction",
            "type":"Services"
        }
    ],
    "sg:phone":"+1 717 246 8060",
    "sg:postcode":"17322",
    "sg:province":"PA",
    "sg:tags":[
        "hanging",
        "contractor"
    ],
    "wof:name":"Mary Patterson",
    "wof:placetype":"venue"
},
  "geometry": {"coordinates":[-76.54732799999999,39.866864],"type":"Point"}
}