{
  "type": "Feature",
  "properties": {
    "iso:country":"US",
    "sg:address":"200 Franklin St",
    "sg:city":"Lehighton",
    "sg:classifiers":[
        {
            "category":"Retail",
            "subcategory":"Funeral Services",
            "type":"Services"
        }
    ],
    "sg:phone":"+1   ",
    "sg:postcode":"18235",
    "sg:province":"PA",
    "wof:name":"Edward Melber Funeral Home",
    "wof:placetype":"venue"
},
  "geometry": {"coordinates":[-75.70228,40.829229],"type":"Point"}
}