{
  "type": "Feature",
  "properties": {
    "addr:full":"3104 Banksville Rd Pittsburgh PA 15216",
    "addr:housenumber":"3104",
    "addr:postcode":"15216",
    "addr:street":"Banksville Rd",
    "iso:country":"US",
    "sg:address":"3104 Banksville Rd",
    "sg:city":"Pittsburgh",
    "sg:classifiers":[
        {
            "category":"Personal",
            "type":"Services"
        }
    ],
    "sg:phone":"+1   ",
    "sg:postcode":"15216",
    "sg:province":"PA",
    "sg:tags":[
        "clothing",
        "mi"
    ],
    "wof:name":"Mr Formal",
    "wof:placetype":"venue"
},
  "geometry": {"coordinates":[-80.044684,40.399253],"type":"Point"}
}