{
  "type": "Feature",
  "properties": {
    "iso:country":"US",
    "sg:address":"749 Polo Rd",
    "sg:city":"Bryn Mawr",
    "sg:classifiers":[
        {
            "category":"Food & Beverages",
            "subcategory":"Dairy",
            "type":"Retail Goods"
        }
    ],
    "sg:phone":"+1   ",
    "sg:postcode":"19010",
    "sg:province":"PA",
    "sg:tags":[
        "product"
    ],
    "wof:name":"Ardmore Cheese",
    "wof:placetype":"venue"
},
  "geometry": {"coordinates":[-75.316547,40.015165],"type":"Point"}
}