{
  "type": "Feature",
  "properties": {
    "addr:full":"5610 Lancaster Ave Philadelphia PA 19131",
    "addr:housenumber":"5610",
    "addr:postcode":"19131",
    "addr:street":"Lancaster Ave",
    "iso:country":"US",
    "sg:address":"5610 Lancaster Ave",
    "sg:city":"Philadelphia",
    "sg:classifiers":[
        {
            "category":"Shopping",
            "subcategory":"Department Store",
            "type":"Retail Goods"
        }
    ],
    "sg:phone":"+1 215 473 0980",
    "sg:postcode":"19131",
    "sg:province":"PA",
    "sg:tags":[
        "shop"
    ],
    "wof:name":"Real Mc Coy Co",
    "wof:placetype":"venue"
},
  "geometry": {"coordinates":[-75.23603300000001,39.980828],"type":"Point"}
}