{
  "type": "Feature",
  "properties": {
    "addr:full":"712 Penn Ave Reading PA 19611",
    "addr:housenumber":"712",
    "addr:postcode":"19611",
    "addr:street":"Penn Ave",
    "iso:country":"US",
    "sg:address":"712 Penn Ave",
    "sg:city":"Reading",
    "sg:classifiers":[
        {
            "category":"Restaurant",
            "type":"Food & Drink"
        }
    ],
    "sg:menulink":"http://www.allmenus.com/pa/west-reading/173029-wendys/menu/",
    "sg:phone":"+1 610 372 8905",
    "sg:postcode":"19611",
    "sg:province":"PA",
    "sg:tags":[
        "burger",
        "american",
        "soup"
    ],
    "wof:name":"Wendy's",
    "wof:placetype":"venue"
},
  "geometry": {"coordinates":[-75.952384,40.335627],"type":"Point"}
}