{
  "type": "Feature",
  "properties": {
    "addr:full":"1140 Yankee Bush Rd Warren PA 16365",
    "addr:housenumber":"1140",
    "addr:postcode":"16365",
    "addr:street":"Yankee Bush Rd",
    "iso:country":"US",
    "sg:address":"1140 Yankee Bush Rd",
    "sg:city":"Warren",
    "sg:classifiers":[
        {
            "category":"Farming",
            "subcategory":"Dairy Farm",
            "type":"Manufacturing & Wholesale Goods"
        }
    ],
    "sg:phone":"+1   ",
    "sg:postcode":"16365",
    "sg:province":"PA",
    "wof:name":"Pine Shade Dairy",
    "wof:placetype":"venue"
},
  "geometry": {"coordinates":[-79.261551,41.898901],"type":"Point"}
}