{
  "type": "Feature",
  "properties": {
    "iso:country":"US",
    "sg:address":"104 Egypt Rd",
    "sg:city":"Norristown",
    "sg:classifiers":[
        {
            "category":"Health Services",
            "subcategory":"Doctor",
            "type":"Services"
        }
    ],
    "sg:phone":"+1 610 539 2500",
    "sg:postcode":"19403",
    "sg:province":"PA",
    "sg:tags":[
        "medical"
    ],
    "wof:name":"J Andre Garabedian MD",
    "wof:placetype":"venue"
},
  "geometry": {"coordinates":[-75.38524200000001,40.132088],"type":"Point"}
}