{
  "type": "Feature",
  "properties": {
    "iso:country":"US",
    "sg:address":"6601 Hegerman St",
    "sg:city":"Philadelphia",
    "sg:classifiers":[
        {
            "category":"Home & Garden",
            "subcategory":"Home Furnishings",
            "type":"Retail Goods"
        },
        {
            "category":"Home & Garden",
            "subcategory":"Building Materials",
            "type":"Retail Goods"
        }
    ],
    "sg:phone":"+1 215 332 7563",
    "sg:postcode":"19135",
    "sg:province":"PA",
    "sg:tags":[
        "bathroom",
        "baths-equipment",
        "supply",
        "cabinet",
        "mirror",
        "fixtures",
        "accessory"
    ],
    "wof:name":"Tri Mirrors & Glass",
    "wof:placetype":"venue"
},
  "geometry": {"coordinates":[-75.047501,40.022308],"type":"Point"}
}