{
  "type": "Feature",
  "properties": {
    "addr:full":"66 E Liberty St Hanover Twp PA 18706",
    "addr:housenumber":"66",
    "addr:postcode":"18706",
    "addr:street":"E Liberty St",
    "iso:country":"US",
    "sg:address":"66 E Liberty St",
    "sg:city":"Hanover Twp",
    "sg:classifiers":[
        {
            "category":"Home & Garden",
            "subcategory":"Building Materials",
            "type":"Retail Goods"
        }
    ],
    "sg:phone":"+1 570 819 1450",
    "sg:postcode":"18706",
    "sg:province":"PA",
    "sg:tags":[
        "siding"
    ],
    "wof:name":"GSI Building Products",
    "wof:placetype":"venue"
},
  "geometry": {"coordinates":[-75.89412799999999,41.220638],"type":"Point"}
}