{
  "type": "Feature",
  "properties": {
    "iso:country":"US",
    "sg:address":"1232 Chestnut Rd",
    "sg:city":"Orwigsburg",
    "sg:classifiers":[
        {
            "category":"Retail",
            "subcategory":"Auto Repair",
            "type":"Services"
        }
    ],
    "sg:phone":"+1 570 943 2794",
    "sg:postcode":"17961",
    "sg:province":"PA",
    "sg:tags":[
        "body",
        "automotive",
        "painting",
        "automobile"
    ],
    "wof:name":"R K Body Shop",
    "wof:placetype":"venue"
},
  "geometry": {"coordinates":[-76.073311,40.671782],"type":"Point"}
}