{
  "type": "Feature",
  "properties": {
    "addr:full":"815 Mulberry St Scranton PA 18510",
    "addr:housenumber":"815",
    "addr:postcode":"18510",
    "addr:street":"Mulberry St",
    "iso:country":"US",
    "sg:address":"815 Mulberry St",
    "sg:city":"Scranton",
    "sg:classifiers":[
        {
            "category":"Restaurant",
            "type":"Food & Drink"
        }
    ],
    "sg:phone":"+1 570 969 9989",
    "sg:postcode":"18510",
    "sg:province":"PA",
    "sg:tags":[
        "eating"
    ],
    "wof:name":"Green Frog Cafe",
    "wof:placetype":"venue"
},
  "geometry": {"coordinates":[-75.657375,41.408085],"type":"Point"}
}