{
  "type": "Feature",
  "properties": {
    "iso:country":"US",
    "sg:address":"1074 E Main St",
    "sg:city":"Clarion",
    "sg:classifiers":[
        {
            "category":"Autos & Motor Vehicles",
            "subcategory":"Automobile Sales",
            "type":"Retail Goods"
        }
    ],
    "sg:phone":"+1   ",
    "sg:postcode":"16214",
    "sg:province":"PA",
    "sg:tags":[
        "new",
        "used"
    ],
    "wof:name":"Sherman Dodge",
    "wof:placetype":"venue"
},
  "geometry": {"coordinates":[-79.372889,41.210007],"type":"Point"}
}