{
  "type": "Feature",
  "properties": {
    "iso:country":"US",
    "sg:address":"365 Hill Rd",
    "sg:city":"Hyndman",
    "sg:classifiers":[
        {
            "category":"Farming",
            "subcategory":"Dairy Farm",
            "type":"Manufacturing & Wholesale Goods"
        },
        {
            "category":"Farming",
            "subcategory":"Farm",
            "type":"Manufacturing & Wholesale Goods"
        }
    ],
    "sg:phone":"+1 814 324 4456",
    "sg:postcode":"15545",
    "sg:province":"PA",
    "wof:name":"J T Windy Farm",
    "wof:placetype":"venue"
},
  "geometry": {"coordinates":[-78.820542,39.753686],"type":"Point"}
}