{
  "type": "Feature",
  "properties": {
    "addr:full":"1625 W Champlost St Philadelphia PA 19141",
    "addr:housenumber":"1625",
    "addr:postcode":"19141",
    "addr:street":"W Champlost St",
    "iso:country":"US",
    "sg:address":"1625 W Champlost St",
    "sg:city":"Philadelphia",
    "sg:classifiers":[
        {
            "category":"Travel",
            "subcategory":"Travel Agent",
            "type":"Entertainment"
        }
    ],
    "sg:phone":"+1   ",
    "sg:postcode":"19141",
    "sg:province":"PA",
    "sg:tags":[
        "operator",
        "tour"
    ],
    "wof:name":"Ruby Tours",
    "wof:placetype":"venue"
},
  "geometry": {"coordinates":[-75.14806900000001,40.044978],"type":"Point"}
}