{
  "type": "Feature",
  "properties": {
    "addr:full":"16550 Lincoln Hwy Breezewood PA 15533",
    "addr:housenumber":"16550",
    "addr:postcode":"15533",
    "addr:street":"Lincoln Hwy",
    "iso:country":"US",
    "sg:address":"16550 Lincoln Hwy",
    "sg:city":"Breezewood",
    "sg:classifiers":[
        {
            "category":"Travel",
            "subcategory":"Hotels & Motels",
            "type":"Entertainment"
        }
    ],
    "sg:phone":"+1 814 735 2200",
    "sg:postcode":"15533",
    "sg:province":"PA",
    "sg:tags":[
        "lodging"
    ],
    "wof:name":"Howard Johnson Breezewood, PA",
    "wof:placetype":"venue"
},
  "geometry": {"coordinates":[-78.239845,39.99942],"type":"Point"}
}