{
  "type": "Feature",
  "properties": {
    "iso:country":"US",
    "sg:address":"2590 Northway Rd",
    "sg:city":"Williamsport",
    "sg:classifiers":[
        {
            "category":"Building & Trades",
            "subcategory":"Construction",
            "type":"Services"
        }
    ],
    "sg:phone":"+1   ",
    "sg:postcode":"17701",
    "sg:province":"PA",
    "sg:tags":[
        "carpentry"
    ],
    "wof:name":"Segraves Construction",
    "wof:placetype":"venue"
},
  "geometry": {"coordinates":[-76.979281,41.27888],"type":"Point"}
}