{
  "type": "Feature",
  "properties": {
    "iso:country":"US",
    "sg:address":"1910 Ligonier St",
    "sg:city":"Latrobe",
    "sg:classifiers":[
        {
            "category":"Wholesale",
            "subcategory":"Electrical",
            "type":"Manufacturing & Wholesale Goods"
        }
    ],
    "sg:phone":"+1 724 537 7469",
    "sg:postcode":"15650",
    "sg:province":"PA",
    "sg:tags":[
        "supply"
    ],
    "wof:name":"S & H Electric Supply Co",
    "wof:placetype":"venue"
},
  "geometry": {"coordinates":[-79.37537,40.30708],"type":"Point"}
}