{
  "type": "Feature",
  "properties": {
    "iso:country":"US",
    "sg:address":"2416 Durham Rd",
    "sg:city":"Bristol",
    "sg:classifiers":[
        {
            "category":"Farming",
            "subcategory":"Livestock Farm",
            "type":"Manufacturing & Wholesale Goods"
        }
    ],
    "sg:phone":"+1   ",
    "sg:postcode":"19007",
    "sg:province":"PA",
    "sg:tags":[
        "breeding"
    ],
    "wof:name":"Pennfield Breeding Farms Inc",
    "wof:placetype":"venue"
},
  "geometry": {"coordinates":[-74.882593,40.126745],"type":"Point"}
}