{
  "type": "Feature",
  "properties": {
    "iso:country":"US",
    "sg:address":"2840 River Rd",
    "sg:city":"Ellwood City",
    "sg:classifiers":[
        {
            "category":"Organizations",
            "subcategory":"Religious Organization",
            "type":"Services"
        }
    ],
    "sg:phone":"+1 724 758 8591",
    "sg:postcode":"16117",
    "sg:province":"PA",
    "sg:tags":[
        "church"
    ],
    "wof:name":"Park Gate Baptist Church",
    "wof:placetype":"venue"
},
  "geometry": {"coordinates":[-80.310928,40.838372],"type":"Point"}
}