{
  "type": "Feature",
  "properties": {
    "iso:country":"US",
    "sg:address":"750 College Blvd",
    "sg:city":"Kutztown",
    "sg:classifiers":[
        {
            "category":"Farming",
            "subcategory":"Farm",
            "type":"Manufacturing & Wholesale Goods"
        }
    ],
    "sg:phone":"+1   ",
    "sg:postcode":"19530",
    "sg:province":"PA",
    "sg:tags":[
        "crop",
        "general"
    ],
    "wof:name":"Harvey Silfies",
    "wof:placetype":"venue"
},
  "geometry": {"coordinates":[-75.799768,40.525218],"type":"Point"}
}