{
  "type": "Feature",
  "properties": {
    "addr:full":"2018 Murray Ave Pittsburgh PA 15217",
    "addr:housenumber":"2018",
    "addr:postcode":"15217",
    "addr:street":"Murray Ave",
    "iso:country":"US",
    "sg:address":"2018 Murray Ave",
    "sg:city":"Pittsburgh",
    "sg:classifiers":[
        {
            "category":"Restaurant",
            "type":"Food & Drink"
        }
    ],
    "sg:menulink":"http://www.allmenus.com/pa/pittsburgh/60181-chopstix/menu/",
    "sg:phone":"+1 412 421 1920",
    "sg:postcode":"15217",
    "sg:province":"PA",
    "sg:tags":[
        "asian",
        "chinese"
    ],
    "wof:name":"Chopstix",
    "wof:placetype":"venue"
},
  "geometry": {"coordinates":[-79.922787,40.434464],"type":"Point"}
}