{
  "type": "Feature",
  "properties": {
    "addr:full":"121 Forge Rd Boiling Springs PA 17007",
    "addr:housenumber":"121",
    "addr:postcode":"17007",
    "addr:street":"Forge Rd",
    "iso:country":"US",
    "sg:address":"121 Forge Rd",
    "sg:city":"Boiling Springs",
    "sg:classifiers":[
        {
            "category":"Restaurant",
            "type":"Food & Drink"
        }
    ],
    "sg:phone":"+1   ",
    "sg:postcode":"17007",
    "sg:province":"PA",
    "sg:tags":[
        "eating"
    ],
    "wof:name":"Selenas Place Subs and Pizza",
    "wof:placetype":"venue"
},
  "geometry": {"coordinates":[-77.13306900000001,40.153649],"type":"Point"}
}