{
  "type": "Feature",
  "properties": {
    "iso:country":"US",
    "sg:address":"3801 N Broad St",
    "sg:city":"Philadelphia",
    "sg:classifiers":[
        {
            "category":"Organizations",
            "subcategory":"Religious Organization",
            "type":"Services"
        }
    ],
    "sg:phone":"+1 215 221 0409",
    "sg:postcode":"19140",
    "sg:province":"PA",
    "sg:tags":[
        "church"
    ],
    "wof:name":"Universal Church",
    "wof:placetype":"venue"
},
  "geometry": {"coordinates":[-75.15058399999999,40.012283],"type":"Point"}
}