{
  "type": "Feature",
  "properties": {
    "addr:full":"1510 Stoystown Rd Friedens PA 15541",
    "addr:housenumber":"1510",
    "addr:postcode":"15541",
    "addr:street":"Stoystown Rd",
    "iso:country":"US",
    "sg:address":"1510 Stoystown Rd",
    "sg:city":"Friedens",
    "sg:classifiers":[
        {
            "category":"Professional",
            "subcategory":"Engineering",
            "type":"Services"
        }
    ],
    "sg:phone":"+1 814 443 1319",
    "sg:postcode":"15541",
    "sg:province":"PA",
    "sg:tags":[
        "engineer"
    ],
    "wof:name":"Somerset Planning & Engrg Svc",
    "wof:placetype":"venue"
},
  "geometry": {"coordinates":[-79.023093,40.039043],"type":"Point"}
}