{
  "type": "Feature",
  "properties": {
    "iso:country":"US",
    "sg:address":"801 Estelle Dr",
    "sg:city":"Lancaster",
    "sg:classifiers":[
        {
            "category":"Banks & Credit Unions",
            "subcategory":"Bank",
            "type":"Services"
        }
    ],
    "sg:phone":"+1   ",
    "sg:postcode":"17601",
    "sg:province":"PA",
    "sg:tags":[
        "federal",
        "savings",
        "institution"
    ],
    "wof:name":"Washington Mutual Home Ln Ctr",
    "wof:placetype":"venue"
},
  "geometry": {"coordinates":[-76.39566000000001,40.05463],"type":"Point"}
}