{
  "type": "Feature",
  "properties": {
    "iso:country":"US",
    "sg:address":"1676 Tunkhannock Trl",
    "sg:city":"Long Pond",
    "sg:classifiers":[
        {
            "category":"Building & Trades",
            "subcategory":"Construction",
            "type":"Services"
        }
    ],
    "sg:phone":"+1   ",
    "sg:postcode":"18334",
    "sg:province":"PA",
    "sg:tags":[
        "contractor"
    ],
    "wof:name":"J & S Gutters",
    "wof:placetype":"venue"
},
  "geometry": {"coordinates":[-75.47165099999999,41.111748],"type":"Point"}
}