{
  "type": "Feature",
  "properties": {
    "addr:full":"700 Deimler Ln Harrisburg PA 17111",
    "addr:housenumber":"700",
    "addr:postcode":"17111",
    "addr:street":"Deimler Ln",
    "iso:country":"US",
    "sg:address":"700 Deimler Ln",
    "sg:city":"Harrisburg",
    "sg:classifiers":[
        {
            "category":"Building & Trades",
            "subcategory":"Construction",
            "type":"Services"
        }
    ],
    "sg:phone":"+1   ",
    "sg:postcode":"17111",
    "sg:province":"PA",
    "sg:tags":[
        "excavation",
        "contractor"
    ],
    "wof:name":"Edward J Siegfried",
    "wof:placetype":"venue"
},
  "geometry": {"coordinates":[-76.76310700000001,40.25644],"type":"Point"}
}