{
  "type": "Feature",
  "properties": {
    "iso:country":"US",
    "sg:address":"4301 Richlieu Rd",
    "sg:city":"Bensalem",
    "sg:classifiers":[
        {
            "category":"Recreation",
            "type":"Entertainment"
        }
    ],
    "sg:phone":"+1 215 752 9649",
    "sg:postcode":"19020",
    "sg:province":"PA",
    "sg:tags":[
        "parks"
    ],
    "wof:name":"Washington Lane Recreation",
    "wof:placetype":"venue"
},
  "geometry": {"coordinates":[-74.94113900000001,40.132872],"type":"Point"}
}