{
  "type": "Feature",
  "properties": {
    "iso:country":"US",
    "sg:address":"1325 E Drinker St",
    "sg:city":"Dunmore",
    "sg:classifiers":[
        {
            "category":"Shopping",
            "subcategory":"Gifts & Souvenirs",
            "type":"Retail Goods"
        }
    ],
    "sg:phone":"+1 570 963 1691",
    "sg:postcode":"18512",
    "sg:province":"PA",
    "sg:tags":[
        "basket",
        "parcel"
    ],
    "wof:name":"Constantino's Pasta",
    "wof:placetype":"venue"
},
  "geometry": {"coordinates":[-75.604935,41.414872],"type":"Point"}
}