{
  "type": "Feature",
  "properties": {
    "addr:full":"19059 Paint Blvd Shippenville PA 16254",
    "addr:postcode":"19059;16254",
    "addr:street":"Paint Blvd",
    "iso:country":"US",
    "sg:address":"19059 Paint Blvd",
    "sg:city":"Shippenville",
    "sg:classifiers":[
        {
            "category":"Manufacturing",
            "subcategory":"Metals",
            "type":"Manufacturing & Wholesale Goods"
        },
        {
            "category":"Building & Trades",
            "subcategory":"Construction",
            "type":"Services"
        }
    ],
    "sg:phone":"+1 814 227 2627",
    "sg:postcode":"16254",
    "sg:province":"PA",
    "sg:tags":[
        "contractor",
        "fabrication",
        "structural"
    ],
    "wof:name":"Unique Fabrication LLC",
    "wof:placetype":"venue"
},
  "geometry": {"coordinates":[-79.435377,41.217015],"type":"Point"}
}