{
  "type": "Feature",
  "properties": {
    "iso:country":"US",
    "sg:address":"7032 Jackson St",
    "sg:city":"Philadelphia",
    "sg:classifiers":[
        {
            "category":"Professional",
            "subcategory":"Business Services",
            "type":"Services"
        }
    ],
    "sg:phone":"+1   ",
    "sg:postcode":"19135",
    "sg:province":"PA",
    "wof:name":"Davis Bros Construction",
    "wof:placetype":"venue"
},
  "geometry": {"coordinates":[-75.041312,40.029982],"type":"Point"}
}