{
  "type": "Feature",
  "properties": {
    "iso:country":"US",
    "sg:address":"304 W Main St",
    "sg:city":"Waynesboro",
    "sg:classifiers":[
        {
            "category":"Restaurant",
            "type":"Food & Drink"
        }
    ],
    "sg:phone":"+1 717 762 3838",
    "sg:postcode":"17268",
    "sg:province":"PA",
    "sg:tags":[
        "pizza"
    ],
    "wof:name":"Little Frattelli's Pizza",
    "wof:placetype":"venue"
},
  "geometry": {"coordinates":[-77.584247,39.758768],"type":"Point"}
}