{
  "type": "Feature",
  "properties": {
    "iso:country":"US",
    "sg:address":"2821 Guffey Rd",
    "sg:city":"North Huntingdon",
    "sg:classifiers":[
        {
            "category":"Building & Trades",
            "subcategory":"Construction",
            "type":"Services"
        }
    ],
    "sg:phone":"+1 412 678 0626",
    "sg:postcode":"15642",
    "sg:province":"PA",
    "sg:tags":[
        "sewer",
        "contractor"
    ],
    "wof:name":"F & J Sewer Cleaning",
    "wof:placetype":"venue"
},
  "geometry": {"coordinates":[-79.74547800000001,40.29734],"type":"Point"}
}