{
  "type": "Feature",
  "properties": {
    "iso:country":"US",
    "sg:address":"45 Locust St",
    "sg:city":"Milton",
    "sg:classifiers":[
        {
            "category":"Social Services",
            "subcategory":"Child Care",
            "type":"Services"
        }
    ],
    "sg:phone":"+1   ",
    "sg:postcode":"17847",
    "sg:province":"PA",
    "sg:tags":[
        "day"
    ],
    "wof:name":"C S I U-Milton-Children Center",
    "wof:placetype":"venue"
},
  "geometry": {"coordinates":[-76.853415,41.02347],"type":"Point"}
}