{
  "type": "Feature",
  "properties": {
    "addr:full":"1356 N Washington Ave Scranton PA 18509",
    "addr:housenumber":"1356",
    "addr:postcode":"18509",
    "addr:street":"N Washington Ave",
    "iso:country":"US",
    "sg:address":"1356 N Washington Ave",
    "sg:city":"Scranton",
    "sg:classifiers":[
        {
            "category":"Organizations",
            "subcategory":"Non-profit Organization",
            "type":"Services"
        }
    ],
    "sg:phone":"+1 570 341 0811",
    "sg:postcode":"18509",
    "sg:province":"PA",
    "sg:website":"www.nechildcare.org",
    "wof:name":"Northeastern Child Care Svc",
    "wof:placetype":"venue"
},
  "geometry": {"coordinates":[-75.64823800000001,41.42166],"type":"Point"}
}