{
  "type": "Feature",
  "properties": {
    "iso:country":"US",
    "sg:address":"113 Northview Cir",
    "sg:city":"Beaver",
    "sg:classifiers":[
        {
            "category":"Health Services",
            "subcategory":"Health Practitioner",
            "type":"Services"
        }
    ],
    "sg:phone":"+1 724 774 1882",
    "sg:postcode":"15009",
    "sg:province":"PA",
    "sg:tags":[
        "physician",
        "assistant"
    ],
    "wof:name":"GIG Of Pa",
    "wof:placetype":"venue"
},
  "geometry": {"coordinates":[-80.342947,40.70386],"type":"Point"}
}