{
  "type": "Feature",
  "properties": {
    "iso:country":"US",
    "sg:address":"1032 E Passyunk Ave",
    "sg:city":"Philadelphia",
    "sg:classifiers":[
        {
            "category":"Retail",
            "subcategory":"Repair Shop",
            "type":"Services"
        }
    ],
    "sg:phone":"+1   ",
    "sg:postcode":"19147",
    "sg:province":"PA",
    "sg:tags":[
        "merchandise"
    ],
    "wof:name":"C K Auto Alarms & Accessories",
    "wof:placetype":"venue"
},
  "geometry": {"coordinates":[-75.156271,39.935873],"type":"Point"}
}