{
  "type": "Feature",
  "properties": {
    "addr:full":"511 Academy St Ulysses PA 16948",
    "addr:housenumber":"511",
    "addr:postcode":"16948",
    "addr:street":"Academy St",
    "iso:country":"US",
    "sg:address":"511 Academy St",
    "sg:city":"Ulysses",
    "sg:classifiers":[
        {
            "category":"Health Services",
            "subcategory":"Doctor",
            "type":"Services"
        }
    ],
    "sg:phone":"+1   ",
    "sg:postcode":"16948",
    "sg:province":"PA",
    "sg:tags":[
        "medical"
    ],
    "wof:name":"Glenney Robert MD",
    "wof:placetype":"venue"
},
  "geometry": {"coordinates":[-77.76121999999999,41.901653],"type":"Point"}
}