{
  "type": "Feature",
  "properties": {
    "addr:full":"64 N Main St Port Allegany PA 16743",
    "addr:housenumber":"64",
    "addr:postcode":"16743",
    "addr:street":"N Main St",
    "iso:country":"US",
    "sg:address":"64 N Main St",
    "sg:city":"Port Allegany",
    "sg:classifiers":[
        {
            "category":"Banks & Credit Unions",
            "subcategory":"Bank",
            "type":"Services"
        }
    ],
    "sg:phone":"+1 814 642 2531",
    "sg:postcode":"16743",
    "sg:province":"PA",
    "sg:website":"www.fnbpa.com",
    "wof:name":"First National Bank",
    "wof:placetype":"venue"
},
  "geometry": {"coordinates":[-78.28105499999999,41.812073],"type":"Point"}
}