{
  "type": "Feature",
  "properties": {
    "addr:full":"619 Altamont Blvd Frackville PA 17931",
    "addr:housenumber":"619",
    "addr:postcode":"17931",
    "addr:street":"Altamont Blvd",
    "iso:country":"US",
    "sg:address":"619 Altamont Blvd",
    "sg:city":"Frackville",
    "sg:classifiers":[
        {
            "category":"Professional",
            "type":"Services"
        }
    ],
    "sg:phone":"+1   ",
    "sg:postcode":"17931",
    "sg:province":"PA",
    "wof:name":"Pennsylvania Bass Chapter",
    "wof:placetype":"venue"
},
  "geometry": {"coordinates":[-76.22434,40.775699],"type":"Point"}
}