{
  "type": "Feature",
  "properties": {
    "addr:full":"1820 E Race St Allentown PA 18109",
    "addr:housenumber":"1820",
    "addr:postcode":"18109",
    "addr:street":"E Race St",
    "iso:country":"US",
    "sg:address":"1820 E Race St",
    "sg:city":"Allentown",
    "sg:classifiers":[
        {
            "category":"Shopping",
            "subcategory":"Discount & Variety Stores",
            "type":"Retail Goods"
        }
    ],
    "sg:phone":"+1 610 266 3440",
    "sg:postcode":"18109",
    "sg:province":"PA",
    "sg:tags":[
        "outlet"
    ],
    "sg:website":"www.sears.com",
    "wof:name":"Sears Outlet Store",
    "wof:placetype":"venue"
},
  "geometry": {"coordinates":[-75.439903,40.6455],"type":"Point"}
}