{
  "type": "Feature",
  "properties": {
    "iso:country":"US",
    "sg:address":"540 N Neville St Ste 4",
    "sg:city":"Pittsburgh",
    "sg:classifiers":[
        {
            "category":"Health Services",
            "subcategory":"Doctor",
            "type":"Services"
        }
    ],
    "sg:phone":"+1 412 681 1003",
    "sg:postcode":"15213",
    "sg:province":"PA",
    "sg:tags":[
        "psychiatry",
        "physician",
        "surgeon",
        "surgeons"
    ],
    "wof:name":"Reis, Alan J Md",
    "wof:placetype":"venue"
},
  "geometry": {"coordinates":[-79.948323,40.449436],"type":"Point"}
}