{
  "type": "Feature",
  "properties": {
    "iso:country":"US",
    "sg:address":"2130 S 21st St",
    "sg:city":"Philadelphia",
    "sg:classifiers":[
        {
            "category":"Organizations",
            "subcategory":"Religious Organization",
            "type":"Services"
        }
    ],
    "sg:phone":"+1   ",
    "sg:postcode":"19145",
    "sg:province":"PA",
    "wof:name":"Saint Edmonds Parish",
    "wof:placetype":"venue"
},
  "geometry": {"coordinates":[-75.18144100000001,39.925009],"type":"Point"}
}