{
  "type": "Feature",
  "properties": {
    "iso:country":"US",
    "sg:address":"4011 Cortland Dr",
    "sg:city":"New Paris",
    "sg:classifiers":[
        {
            "category":"Personal",
            "subcategory":"Beauty Salon",
            "type":"Services"
        }
    ],
    "sg:phone":"+1 814 839 2004",
    "sg:postcode":"15554",
    "sg:province":"PA",
    "wof:name":"Divine Designs",
    "wof:placetype":"venue"
},
  "geometry": {"coordinates":[-78.64335800000001,40.108027],"type":"Point"}
}