{
  "type": "Feature",
  "properties": {
    "iso:country":"US",
    "sg:address":"1310 Perry Hwy",
    "sg:city":"Portersville",
    "sg:classifiers":[
        {
            "category":"Shopping",
            "type":"Retail Goods"
        }
    ],
    "sg:phone":"+1 724 368 3772",
    "sg:postcode":"16051",
    "sg:province":"PA",
    "sg:tags":[
        "art",
        "gallery",
        "dealer"
    ],
    "wof:name":"Muddy Creek Originals",
    "wof:placetype":"venue"
},
  "geometry": {"coordinates":[-80.144475,40.926476],"type":"Point"}
}