{
  "type": "Feature",
  "properties": {
    "iso:country":"US",
    "sg:address":"3048 Enterprise Dr",
    "sg:city":"State College",
    "sg:classifiers":[
        {
            "category":"Health Services",
            "subcategory":"Hospital",
            "type":"Services"
        }
    ],
    "sg:phone":"+1 814 867 5415",
    "sg:postcode":"16801",
    "sg:province":"PA",
    "sg:tags":[
        "hosp",
        "ex",
        "psychiatric",
        "government"
    ],
    "wof:name":"US Veterans Medical Ctr",
    "wof:placetype":"venue"
},
  "geometry": {"coordinates":[-77.881052,40.764622],"type":"Point"}
}