{
  "type": "Feature",
  "properties": {
    "iso:country":"US",
    "sg:address":"1331 State Ave",
    "sg:city":"Coraopolis",
    "sg:classifiers":[
        {
            "category":"Professional",
            "subcategory":"Engineering",
            "type":"Services"
        }
    ],
    "sg:phone":"+1 412 269 6180",
    "sg:postcode":"15108",
    "sg:province":"PA",
    "sg:tags":[
        "engineer"
    ],
    "wof:name":"Kingsway Engineering Services",
    "wof:placetype":"venue"
},
  "geometry": {"coordinates":[-80.1571,40.514173],"type":"Point"}
}