{
  "type": "Feature",
  "properties": {
    "iso:country":"US",
    "sg:address":"31 Lasso Dr",
    "sg:city":"Honey Brook",
    "sg:classifiers":[
        {
            "category":"Travel",
            "subcategory":"Campground",
            "type":"Entertainment"
        }
    ],
    "sg:phone":"+1   ",
    "sg:postcode":"19344",
    "sg:province":"PA",
    "sg:tags":[
        "organization",
        "camp",
        "religious"
    ],
    "wof:name":"Tel Hai Camp & Retreat",
    "wof:placetype":"venue"
},
  "geometry": {"coordinates":[-75.886658,40.057406],"type":"Point"}
}