{
  "type": "Feature",
  "properties": {
    "addr:full":"1021 N Chester Rd West Chester PA 19380",
    "addr:housenumber":"1021",
    "addr:postcode":"19380",
    "addr:street":"N Chester Rd",
    "iso:country":"US",
    "sg:address":"1021 N Chester Rd",
    "sg:city":"West Chester",
    "sg:classifiers":[
        {
            "category":"Insurance",
            "subcategory":"Insurance Agent",
            "type":"Services"
        }
    ],
    "sg:phone":"+1   ",
    "sg:postcode":"19380",
    "sg:province":"PA",
    "wof:name":"Robert G Larkin Agency",
    "wof:placetype":"venue"
},
  "geometry": {"coordinates":[-75.54641100000001,40.003961],"type":"Point"}
}