{
  "type": "Feature",
  "properties": {
    "iso:country":"US",
    "sg:address":"327 York Rd",
    "sg:city":"Warminster",
    "sg:classifiers":[
        {
            "category":"Health Services",
            "subcategory":"Health Practitioner",
            "type":"Services"
        }
    ],
    "sg:phone":"+1 215 672 7373",
    "sg:postcode":"18974",
    "sg:province":"PA",
    "sg:tags":[
        "therapist",
        "physical"
    ],
    "wof:name":"Bucks Physical Thrpy & Sports",
    "wof:placetype":"venue"
},
  "geometry": {"coordinates":[-75.10114900000001,40.199369],"type":"Point"}
}