{
  "type": "Feature",
  "properties": {
    "addr:full":"1111 E Street Rd Southampton PA 18966",
    "addr:housenumber":"1111",
    "addr:postcode":"18966",
    "addr:street":"E Street Rd",
    "iso:country":"US",
    "sg:address":"1111 E Street Rd",
    "sg:city":"Southampton",
    "sg:classifiers":[
        {
            "category":"Real Estate",
            "subcategory":"Real Estate Operator",
            "type":"Services"
        }
    ],
    "sg:phone":"+1 215 357 3577",
    "sg:postcode":"18966",
    "sg:province":"PA",
    "sg:tags":[
        "building",
        "parks"
    ],
    "wof:name":"Morelyn Plaza",
    "wof:placetype":"venue"
},
  "geometry": {"coordinates":[-75.03328399999999,40.168779],"type":"Point"}
}