{
  "type": "Feature",
  "properties": {
    "iso:country":"US",
    "sg:address":"171 Red Horse Rd",
    "sg:city":"Pottsville",
    "sg:classifiers":[
        {
            "category":"Health Services",
            "subcategory":"Doctor",
            "type":"Services"
        }
    ],
    "sg:phone":"+1 570 628 2229",
    "sg:postcode":"17901",
    "sg:province":"PA",
    "sg:tags":[
        "physician",
        "reproductive",
        "family",
        "gynecology",
        "endocrinology",
        "practice",
        "surgeons",
        "obstetrics",
        "medicine",
        "surgeon",
        "public"
    ],
    "sg:website":"http://www.comprehensivewomenshealthservices.com/",
    "wof:name":"Comprehensive Women's Health",
    "wof:placetype":"venue"
},
  "geometry": {"coordinates":[-76.223572,40.663719],"type":"Point"}
}