{
  "type": "Feature",
  "properties": {
    "iso:country":"US",
    "sg:address":"216 Spring St",
    "sg:city":"Pittston",
    "sg:classifiers":[
        {
            "category":"Government",
            "subcategory":"Fire Station",
            "type":"Public Place"
        }
    ],
    "sg:phone":"+1   ",
    "sg:postcode":"18643",
    "sg:province":"PA",
    "sg:tags":[
        "protection"
    ],
    "wof:name":"West Pittston House Co 1",
    "wof:placetype":"venue"
},
  "geometry": {"coordinates":[-75.79761499999999,41.330329],"type":"Point"}
}