{
  "type": "Feature",
  "properties": {
    "iso:country":"US",
    "sg:address":"3717 W Chester Pike",
    "sg:city":"Newtown Square",
    "sg:classifiers":[
        {
            "category":"Wholesale",
            "subcategory":"Non-durable Goods",
            "type":"Manufacturing & Wholesale Goods"
        }
    ],
    "sg:phone":"+1 610 356 1117",
    "sg:postcode":"19073",
    "sg:province":"PA",
    "sg:tags":[
        "leather",
        "clothes"
    ],
    "wof:name":"Newton Square Shoe Svc",
    "wof:placetype":"venue"
},
  "geometry": {"coordinates":[-75.40277399999999,39.986613],"type":"Point"}
}