{
  "type": "Feature",
  "properties": {
    "iso:country":"US",
    "sg:address":"401 Allegheny Ave",
    "sg:city":"Hanover",
    "sg:classifiers":[
        {
            "category":"Health Services",
            "subcategory":"Health Practitioner",
            "type":"Services"
        }
    ],
    "sg:phone":"+1 717 633 5519",
    "sg:postcode":"17331",
    "sg:province":"PA",
    "sg:tags":[
        "psychologist"
    ],
    "wof:name":"Hanover Counseling",
    "wof:placetype":"venue"
},
  "geometry": {"coordinates":[-76.980991,39.810287],"type":"Point"}
}