{
  "type": "Feature",
  "properties": {
    "iso:country":"US",
    "sg:address":"313 E 3rd St",
    "sg:city":"Emporium",
    "sg:classifiers":[
        {
            "category":"Building & Trades",
            "subcategory":"Construction",
            "type":"Services"
        }
    ],
    "sg:phone":"+1   ",
    "sg:postcode":"15834",
    "sg:province":"PA",
    "sg:tags":[
        "remodeling",
        "renovation",
        "contractor"
    ],
    "wof:name":"Robinson Builders",
    "wof:placetype":"venue"
},
  "geometry": {"coordinates":[-78.231216,41.510947],"type":"Point"}
}