{
  "type": "Feature",
  "properties": {
    "iso:country":"US",
    "sg:address":"2200 Sumneytown Pike",
    "sg:city":"Harleysville",
    "sg:classifiers":[
        {
            "category":"Place Of Worship",
            "subcategory":"Church",
            "type":"Public Place"
        }
    ],
    "sg:postcode":"19438",
    "sg:province":"PA",
    "sg:website":"www.christ-covenant.org",
    "wof:name":"Christ Covenant Church",
    "wof:placetype":"venue"
},
  "geometry": {"coordinates":[-75.349262,40.250197],"type":"Point"}
}