{
  "type": "Feature",
  "properties": {
    "addr:full":"517 Grant St Pittsburgh PA 15219",
    "addr:housenumber":"517",
    "addr:postcode":"15219",
    "addr:street":"Grant St",
    "iso:country":"US",
    "sg:address":"517 Grant St",
    "sg:city":"Pittsburgh",
    "sg:classifiers":[
        {
            "category":"Shopping",
            "subcategory":"Florist",
            "type":"Retail Goods"
        }
    ],
    "sg:phone":"+1 412 281 0350",
    "sg:postcode":"15219",
    "sg:province":"PA",
    "wof:name":"Oliver Flower Shop Inc",
    "wof:placetype":"venue"
},
  "geometry": {"coordinates":[-79.996596,40.43992],"type":"Point"}
}