{
  "type": "Feature",
  "properties": {
    "iso:country":"US",
    "sg:address":"444 Liberty Ave",
    "sg:city":"Pittsburgh",
    "sg:classifiers":[
        {
            "category":"Professional",
            "subcategory":"Lawyer & Legal Services",
            "type":"Services"
        }
    ],
    "sg:phone":"+1 412 394 3333",
    "sg:postcode":"15222",
    "sg:province":"PA",
    "sg:tags":[
        "firm",
        "attorney",
        "law"
    ],
    "wof:name":"Polito & Smock PC",
    "wof:placetype":"venue"
},
  "geometry": {"coordinates":[-80.00672,40.441014],"type":"Point"}
}