{
  "type": "Feature",
  "properties": {
    "iso:country":"US",
    "sg:address":"100 Evergreen Dr",
    "sg:city":"Glen Mills",
    "sg:classifiers":[
        {
            "category":"Health Services",
            "subcategory":"Optometrist",
            "type":"Services"
        },
        {
            "category":"Shopping",
            "subcategory":"Optician",
            "type":"Retail Goods"
        }
    ],
    "sg:phone":"+1 610 558 9803",
    "sg:postcode":"19342",
    "sg:province":"PA",
    "sg:tags":[
        "eyewear"
    ],
    "wof:name":"Pearl Vision Center",
    "wof:placetype":"venue"
},
  "geometry": {"coordinates":[-75.531097,39.8848],"type":"Point"}
}