{
  "type": "Feature",
  "properties": {
    "addr:full":"1514 E Drinker St Scranton PA 18512",
    "addr:housenumber":"1514",
    "addr:postcode":"18512",
    "addr:street":"E Drinker St",
    "iso:country":"US",
    "sg:address":"1514 E Drinker St",
    "sg:city":"Scranton",
    "sg:classifiers":[
        {
            "category":"Building & Trades",
            "subcategory":"Construction",
            "type":"Services"
        }
    ],
    "sg:phone":"+1   ",
    "sg:postcode":"18512",
    "sg:province":"PA",
    "sg:tags":[
        "carpentry",
        "contractor"
    ],
    "wof:name":"Perrys General Contracting",
    "wof:placetype":"venue"
},
  "geometry": {"coordinates":[-75.60073300000001,41.411345],"type":"Point"}
}