{
  "type": "Feature",
  "properties": {
    "addr:full":"1745 Eaton Ave Bethlehem PA 18018",
    "addr:housenumber":"1745",
    "addr:postcode":"18018",
    "addr:street":"Eaton Ave",
    "iso:country":"US",
    "sg:address":"1745 Eaton Ave",
    "sg:city":"Bethlehem",
    "sg:classifiers":[
        {
            "category":"Wholesale",
            "subcategory":"Medical Equipment & Supplies",
            "type":"Manufacturing & Wholesale Goods"
        }
    ],
    "sg:phone":"+1 610 882 1820",
    "sg:postcode":"18018",
    "sg:province":"PA",
    "sg:tags":[
        "physician",
        "surgeon"
    ],
    "wof:name":"Orasure Technologies Inc",
    "wof:placetype":"venue"
},
  "geometry": {"coordinates":[-75.40690600000001,40.632022],"type":"Point"}
}