{
  "type": "Feature",
  "properties": {
    "iso:country":"US",
    "sg:address":"2627 Ellwood Rd",
    "sg:city":"New Castle",
    "sg:classifiers":[
        {
            "category":"Wholesale",
            "subcategory":"Auto Parts",
            "type":"Manufacturing & Wholesale Goods"
        }
    ],
    "sg:phone":"+1 724 652 7733",
    "sg:postcode":"16101",
    "sg:province":"PA",
    "sg:tags":[
        "automobile",
        "rebuilt"
    ],
    "sg:website":"www.newcastleautowrecking.com",
    "wof:name":"New Castle Auto Wrecking Inc",
    "wof:placetype":"venue"
},
  "geometry": {"coordinates":[-80.31257100000001,40.969905],"type":"Point"}
}