{
  "type": "Feature",
  "properties": {
    "iso:country":"US",
    "sg:address":"304 W Monroe St",
    "sg:city":"Latrobe",
    "sg:classifiers":[
        {
            "category":"Retail",
            "subcategory":"Repair Shop",
            "type":"Services"
        }
    ],
    "sg:phone":"+1 724 539 2028",
    "sg:postcode":"15650",
    "sg:province":"PA",
    "sg:tags":[
        "auto",
        "general"
    ],
    "wof:name":"Lambert Fire Truck Repair Inc",
    "wof:placetype":"venue"
},
  "geometry": {"coordinates":[-79.38001199999999,40.305306],"type":"Point"}
}