{
  "type": "Feature",
  "properties": {
    "addr:full":"1991 Sproul Rd Broomall PA 19008",
    "addr:housenumber":"1991",
    "addr:postcode":"19008",
    "addr:street":"Sproul Rd",
    "iso:country":"US",
    "sg:address":"1991 Sproul Rd",
    "sg:city":"Broomall",
    "sg:classifiers":[
        {
            "category":"Utilities",
            "subcategory":"Mobile Phone",
            "type":"Services"
        }
    ],
    "sg:phone":"+1 610 541 0100",
    "sg:postcode":"19008",
    "sg:province":"PA",
    "sg:tags":[
        "telephone",
        "cellular"
    ],
    "wof:name":"Sprint PCS",
    "wof:placetype":"venue"
},
  "geometry": {"coordinates":[-75.356489,39.961244],"type":"Point"}
}