{
  "type": "Feature",
  "properties": {
    "addr:full":"589 Fairground Rd Lewisburg PA 17837",
    "addr:housenumber":"589",
    "addr:postcode":"17837",
    "addr:street":"Fairground Rd",
    "iso:country":"US",
    "sg:address":"589 Fairground Rd",
    "sg:city":"Lewisburg",
    "sg:classifiers":[
        {
            "category":"Government",
            "subcategory":"Police Station",
            "type":"Public Place"
        }
    ],
    "sg:phone":"+1 570 524 2943",
    "sg:postcode":"17837",
    "sg:province":"PA",
    "sg:tags":[
        "department"
    ],
    "wof:name":"East Buffalo Twp Police Dept",
    "wof:placetype":"venue"
},
  "geometry": {"coordinates":[-76.906272,40.961221],"type":"Point"}
}