{
  "type": "Feature",
  "properties": {
    "iso:country":"US",
    "sg:address":"1139 3rd Ave",
    "sg:city":"Altoona",
    "sg:classifiers":[
        {
            "category":"Home & Garden",
            "subcategory":"Building Materials",
            "type":"Retail Goods"
        },
        {
            "category":"Building & Trades",
            "subcategory":"Construction",
            "type":"Services"
        },
        {
            "category":"Manufacturing",
            "subcategory":"Building Materials",
            "type":"Manufacturing & Wholesale Goods"
        }
    ],
    "sg:phone":"+1 814 695 1112",
    "sg:postcode":"16602",
    "sg:province":"PA",
    "sg:tags":[
        "roofing",
        "industrial",
        "supply",
        "shingle",
        "contractor",
        "equipment",
        "contractors-commercial",
        "consultant"
    ],
    "sg:website":"http://www.mandmroofing.com",
    "wof:name":"M & M Roofing",
    "wof:placetype":"venue"
},
  "geometry": {"coordinates":[-78.393064,40.511475],"type":"Point"}
}