{
  "type": "Feature",
  "properties": {
    "iso:country":"US",
    "sg:address":"1 Maple Ave",
    "sg:city":"Hatboro",
    "sg:classifiers":[
        {
            "category":"Building & Trades",
            "subcategory":"Construction",
            "type":"Services"
        }
    ],
    "sg:phone":"+1   ",
    "sg:postcode":"19040",
    "sg:province":"PA",
    "sg:tags":[
        "contractor"
    ],
    "wof:name":"Mac Floors",
    "wof:placetype":"venue"
},
  "geometry": {"coordinates":[-75.12615700000001,40.201245],"type":"Point"}
}