{
  "type": "Feature",
  "properties": {
    "addr:full":"Hanover Hospital Bethlehem PA 18017",
    "addr:postcode":"18017",
    "iso:country":"US",
    "sg:address":"Hanover Hospital",
    "sg:city":"Bethlehem",
    "sg:classifiers":[
        {
            "category":"Health Services",
            "subcategory":"Doctor",
            "type":"Services"
        }
    ],
    "sg:phone":"+1 717 633 2155",
    "sg:postcode":"18017",
    "sg:province":"PA",
    "sg:tags":[
        "medicine",
        "sport"
    ],
    "wof:name":"Hanover Rehab Centers",
    "wof:placetype":"venue"
},
  "geometry": {"coordinates":[-75.37979900000001,40.654301],"type":"Point"}
}