{
  "type": "Feature",
  "properties": {
    "addr:full":"2030 Swallow Hill Rd Ste 2 Pittsburgh PA 15220",
    "addr:housenumber":"2030",
    "addr:postcode":"15220",
    "addr:street":"Swallow Hill Rd Ste 2",
    "iso:country":"US",
    "sg:address":"2030 Swallow Hill Rd Ste 2",
    "sg:city":"Pittsburgh",
    "sg:classifiers":[
        {
            "category":"Education",
            "subcategory":"School",
            "type":"Public Place"
        }
    ],
    "sg:phone":"+1 412 429 2201",
    "sg:postcode":"15220",
    "sg:province":"PA",
    "sg:tags":[
        "high",
        "middle",
        "elementary"
    ],
    "wof:name":"Chartiers Valley School District",
    "wof:placetype":"venue"
},
  "geometry": {"coordinates":[-80.075992,40.398886],"type":"Point"}
}