{
  "type": "Feature",
  "properties": {
    "addr:full":"1152 Lees Bridge Rd Nottingham PA 19362",
    "addr:housenumber":"1152",
    "addr:postcode":"19362",
    "addr:street":"Lees Bridge Rd",
    "iso:country":"US",
    "sg:address":"1152 Lees Bridge Rd",
    "sg:city":"Nottingham",
    "sg:classifiers":[
        {
            "category":"Professional",
            "type":"Services"
        }
    ],
    "sg:phone":"+1   ",
    "sg:postcode":"19362",
    "sg:province":"PA",
    "wof:name":"Jerry Schroder",
    "wof:placetype":"venue"
},
  "geometry": {"coordinates":[-76.02693600000001,39.767703],"type":"Point"}
}