{
  "type": "Feature",
  "properties": {
    "iso:country":"US",
    "sg:address":"3200 Conewango Ave",
    "sg:city":"Warren",
    "sg:classifiers":[
        {
            "category":"Building & Trades",
            "subcategory":"Equipment Rental",
            "type":"Services"
        },
        {
            "category":"Personal",
            "type":"Services"
        },
        {
            "category":"Retail",
            "subcategory":"Auto Rental",
            "type":"Services"
        },
        {
            "category":"Wholesale",
            "subcategory":"Machinery & Supplies",
            "type":"Manufacturing & Wholesale Goods"
        },
        {
            "category":"Retail",
            "subcategory":"Storage",
            "type":"Services"
        }
    ],
    "sg:phone":"+1 814 726 3303",
    "sg:postcode":"16365",
    "sg:province":"PA",
    "sg:tags":[
        "renting",
        "moving-self",
        "industrial",
        "leasing",
        "full",
        "truck",
        "store",
        "yard",
        "mover",
        "trailer",
        "contractors'"
    ],
    "sg:website":"http://www.uhaul.com/Locations/Rentals-near-Warren-PA-16365/054057",
    "wof:name":"U-Haul Neighborhood Dealer - Davies & Sons",
    "wof:placetype":"venue"
},
  "geometry": {"coordinates":[-79.137967,41.883777],"type":"Point"}
}