{
  "type": "Feature",
  "properties": {
    "addr:full":"111 S 38th St Philadelphia PA 19104",
    "addr:housenumber":"111",
    "addr:postcode":"19104",
    "addr:street":"S 38Th St",
    "iso:country":"US",
    "sg:address":"111 S 38th St",
    "sg:city":"Philadelphia",
    "sg:classifiers":[
        {
            "category":"Personal",
            "type":"Services"
        }
    ],
    "sg:phone":"+1 215 895 3470",
    "sg:postcode":"19104",
    "sg:province":"PA",
    "sg:tags":[
        "food",
        "delivery"
    ],
    "sg:website":"http://www.readynetgo.net",
    "wof:name":"N D S",
    "wof:placetype":"venue"
},
  "geometry": {"coordinates":[-75.198543,39.954344],"type":"Point"}
}