{
  "type": "Feature",
  "properties": {
    "iso:country":"US",
    "sg:address":"447 Washington Ave",
    "sg:city":"Bridgeville",
    "sg:classifiers":[
        {
            "category":"Professional",
            "subcategory":"Accounting & Tax Preparation",
            "type":"Services"
        }
    ],
    "sg:phone":"+1 412 221 7100",
    "sg:postcode":"15017",
    "sg:province":"PA",
    "sg:tags":[
        "accountant"
    ],
    "wof:name":"Deblasio and Deblasio Assoc CPA",
    "wof:placetype":"venue"
},
  "geometry": {"coordinates":[-80.111801,40.3591],"type":"Point"}
}