{
  "type": "Feature",
  "properties": {
    "iso:country":"US",
    "sg:address":"220 E Front St",
    "sg:city":"Bridgeport",
    "sg:classifiers":[
        {
            "category":"Professional",
            "subcategory":"Management & Consulting",
            "type":"Services"
        }
    ],
    "sg:phone":"+1   ",
    "sg:postcode":"19405",
    "sg:province":"PA",
    "sg:tags":[
        "support",
        "facility"
    ],
    "wof:name":"Hill Environmental Group Inc",
    "wof:placetype":"venue"
},
  "geometry": {"coordinates":[-75.337,40.106136],"type":"Point"}
}