{
  "type": "Feature",
  "properties": {
    "addr:full":"2764 Grant St New Kensington PA 15068",
    "addr:housenumber":"2764",
    "addr:postcode":"15068",
    "addr:street":"Grant St",
    "iso:country":"US",
    "sg:address":"2764 Grant St",
    "sg:city":"New Kensington",
    "sg:classifiers":[
        {
            "category":"Manufacturing",
            "subcategory":"Retail Goods",
            "type":"Manufacturing & Wholesale Goods"
        }
    ],
    "sg:phone":"+1   ",
    "sg:postcode":"15068",
    "sg:province":"PA",
    "sg:tags":[
        "lawn",
        "ornament",
        "mfg"
    ],
    "wof:name":"Copper Creations By Ray",
    "wof:placetype":"venue"
},
  "geometry": {"coordinates":[-79.733594,40.592515],"type":"Point"}
}