{
  "type": "Feature",
  "properties": {
    "addr:full":"2 W Long Ave Du Bois PA 15801",
    "addr:housenumber":"2",
    "addr:postcode":"15801",
    "addr:street":"W Long Ave Du Bois",
    "iso:country":"US",
    "sg:address":"2 W Long Ave",
    "sg:city":"Du Bois",
    "sg:classifiers":[
        {
            "category":"Food & Beverages",
            "subcategory":"Candy",
            "type":"Retail Goods"
        }
    ],
    "sg:phone":"+1 814 371 9484",
    "sg:postcode":"15801",
    "sg:province":"PA",
    "sg:tags":[
        "confectionery"
    ],
    "wof:name":"Hockman Candy",
    "wof:placetype":"venue"
},
  "geometry": {"coordinates":[-78.763412,41.11962],"type":"Point"}
}