{
  "type": "Feature",
  "properties": {
    "addr:full":"428 E Street Rd Southampton PA 18966",
    "addr:housenumber":"428",
    "addr:postcode":"18966",
    "addr:street":"E Street Rd",
    "iso:country":"US",
    "sg:address":"428 E Street Rd",
    "sg:city":"Southampton",
    "sg:classifiers":[
        {
            "category":"Personal",
            "subcategory":"Beauty Salon",
            "type":"Services"
        }
    ],
    "sg:phone":"+1 215 354 0196",
    "sg:postcode":"18966",
    "sg:province":"PA",
    "sg:tags":[
        "manicuring"
    ],
    "wof:name":"TNT Nail Salon",
    "wof:placetype":"venue"
},
  "geometry": {"coordinates":[-75.048535,40.177136],"type":"Point"}
}