{
  "type": "Feature",
  "properties": {
    "addr:full":"922 Shiloh Rd West Chester PA 19382",
    "addr:housenumber":"922",
    "addr:postcode":"19382",
    "addr:street":"Shiloh Rd",
    "iso:country":"US",
    "sg:address":"922 Shiloh Rd",
    "sg:city":"West Chester",
    "sg:classifiers":[
        {
            "category":"Social Services",
            "subcategory":"Adult Care",
            "type":"Services"
        }
    ],
    "sg:phone":"+1 610 344 0675",
    "sg:postcode":"19382",
    "sg:province":"PA",
    "sg:tags":[
        "home",
        "group"
    ],
    "wof:name":"Community Homes Inc",
    "wof:placetype":"venue"
},
  "geometry": {"coordinates":[-75.556462,39.949171],"type":"Point"}
}