{
  "type": "Feature",
  "properties": {
    "addr:full":"124 Hamilton St Indiana PA 15701",
    "addr:housenumber":"124",
    "addr:postcode":"15701",
    "addr:street":"Hamilton St",
    "iso:country":"US",
    "sg:address":"124 Hamilton St",
    "sg:city":"Indiana",
    "sg:classifiers":[
        {
            "category":"Professional",
            "type":"Services"
        }
    ],
    "sg:phone":"+1   ",
    "sg:postcode":"15701",
    "sg:province":"PA",
    "wof:name":"Brian Plyler",
    "wof:placetype":"venue"
},
  "geometry": {"coordinates":[-79.18230699999999,40.616631],"type":"Point"}
}