{
  "type": "Feature",
  "properties": {
    "addr:full":"140 Highland Ave Washington PA 15301",
    "addr:housenumber":"140",
    "addr:postcode":"15301",
    "addr:street":"Highland Ave",
    "iso:country":"US",
    "sg:address":"140 Highland Ave",
    "sg:city":"Washington",
    "sg:classifiers":[
        {
            "category":"Retail",
            "subcategory":"Auto Repair",
            "type":"Services"
        }
    ],
    "sg:phone":"+1 724 222 3077",
    "sg:postcode":"15301",
    "sg:province":"PA",
    "sg:tags":[
        "body",
        "automobile",
        "painting"
    ],
    "wof:name":"Lombardis Auto Body & Repair",
    "wof:placetype":"venue"
},
  "geometry": {"coordinates":[-80.242729,40.176128],"type":"Point"}
}