{
  "type": "Feature",
  "properties": {
    "iso:country":"US",
    "sg:address":"1067 Lakemont Dr",
    "sg:city":"Pittsburgh",
    "sg:classifiers":[
        {
            "category":"Professional",
            "subcategory":"Management & Consulting",
            "type":"Services"
        }
    ],
    "sg:phone":"+1 412 344 5444",
    "sg:postcode":"15243",
    "sg:province":"PA",
    "sg:tags":[
        "consultant",
        "business"
    ],
    "wof:name":"Mc William Group LLC",
    "wof:placetype":"venue"
},
  "geometry": {"coordinates":[-80.06521600000001,40.371306],"type":"Point"}
}