{
  "type": "Feature",
  "properties": {
    "addr:full":"225 Concord Ave Chester PA 19013",
    "addr:housenumber":"225",
    "addr:postcode":"19013",
    "addr:street":"Concord Ave",
    "iso:country":"US",
    "sg:address":"225 Concord Ave",
    "sg:city":"Chester",
    "sg:classifiers":[
        {
            "category":"Restaurant",
            "type":"Food & Drink"
        }
    ],
    "sg:phone":"+1 610 874 6430",
    "sg:postcode":"19013",
    "sg:province":"PA",
    "sg:tags":[
        "out"
    ],
    "wof:name":"Stacky's Sandwich Shop",
    "wof:placetype":"venue"
},
  "geometry": {"coordinates":[-75.363474,39.844562],"type":"Point"}
}