{
  "type": "Feature",
  "properties": {
    "iso:country":"US",
    "sg:address":"11732 E Main Rd",
    "sg:city":"North East",
    "sg:classifiers":[
        {
            "category":"Health Services",
            "subcategory":"Doctor",
            "type":"Services"
        }
    ],
    "sg:phone":"+1   ",
    "sg:postcode":"16428",
    "sg:province":"PA",
    "sg:tags":[
        "medical"
    ],
    "wof:name":"Dr Richard L Schaffnit",
    "wof:placetype":"venue"
},
  "geometry": {"coordinates":[-79.79858299999999,42.227156],"type":"Point"}
}