{
  "type": "Feature",
  "properties": {
    "iso:country":"US",
    "sg:address":"1600 Cochran Rd",
    "sg:city":"Pittsburgh",
    "sg:classifiers":[
        {
            "category":"Shopping",
            "subcategory":"Bicycles & Sporting Goods",
            "type":"Retail Goods"
        }
    ],
    "sg:phone":"+1 412 343 5857",
    "sg:postcode":"15220",
    "sg:province":"PA",
    "wof:name":"Perani's Hockey Shop",
    "wof:placetype":"venue"
},
  "geometry": {"coordinates":[-80.061096,40.3918],"type":"Point"}
}