{
  "type": "Feature",
  "properties": {
    "iso:country":"US",
    "sg:address":"226 E High St",
    "sg:city":"Pottstown",
    "sg:classifiers":[
        {
            "category":"Home & Garden",
            "subcategory":"Furniture",
            "type":"Retail Goods"
        }
    ],
    "sg:phone":"+1   ",
    "sg:postcode":"19464",
    "sg:province":"PA",
    "wof:name":"Tibbetts Realty",
    "wof:placetype":"venue"
},
  "geometry": {"coordinates":[-75.649911,40.245553],"type":"Point"}
}