{
  "type": "Feature",
  "properties": {
    "addr:full":"1816 Greengarden Rd Erie PA 16502",
    "addr:housenumber":"1816",
    "addr:postcode":"16502",
    "addr:street":"Greengarden Rd",
    "iso:country":"US",
    "sg:address":"1816 Greengarden Rd",
    "sg:city":"Erie",
    "sg:classifiers":[
        {
            "category":"Wholesale",
            "subcategory":"Machinery & Supplies",
            "type":"Manufacturing & Wholesale Goods"
        }
    ],
    "sg:phone":"+1 814 454 5001",
    "sg:postcode":"16502",
    "sg:province":"PA",
    "sg:tags":[
        "concrete",
        "mixer"
    ],
    "wof:name":"Baycrete Inc",
    "wof:placetype":"venue"
},
  "geometry": {"coordinates":[-80.113184,42.106378],"type":"Point"}
}