{
  "type": "Feature",
  "properties": {
    "iso:country":"US",
    "sg:address":"306 N Mercer St",
    "sg:city":"New Castle",
    "sg:classifiers":[
        {
            "category":"Professional",
            "subcategory":"Accounting & Tax Preparation",
            "type":"Services"
        }
    ],
    "sg:phone":"+1   ",
    "sg:postcode":"16101",
    "sg:province":"PA",
    "sg:tags":[
        "return"
    ],
    "wof:name":"Antonio Pat",
    "wof:placetype":"venue"
},
  "geometry": {"coordinates":[-80.345777,41.004404],"type":"Point"}
}