{
  "type": "Feature",
  "properties": {
    "addr:full":"1278 Ash Ln Lebanon PA 17042",
    "addr:housenumber":"1278",
    "addr:postcode":"17042",
    "addr:street":"Ash Ln",
    "iso:country":"US",
    "sg:address":"1278 Ash Ln",
    "sg:city":"Lebanon",
    "sg:classifiers":[
        {
            "category":"Real Estate",
            "subcategory":"Real Estate Operator",
            "type":"Services"
        }
    ],
    "sg:phone":"+1   ",
    "sg:postcode":"17042",
    "sg:province":"PA",
    "sg:tags":[
        "building",
        "apartment",
        "business"
    ],
    "wof:name":"Regency House Interiors",
    "wof:placetype":"venue"
},
  "geometry": {"coordinates":[-76.431483,40.245996],"type":"Point"}
}