{
  "type": "Feature",
  "properties": {
    "iso:country":"US",
    "sg:address":"658 Buchanan St",
    "sg:city":"Bethlehem",
    "sg:classifiers":[
        {
            "category":"Professional",
            "type":"Services"
        }
    ],
    "sg:phone":"+1   ",
    "sg:postcode":"18015",
    "sg:province":"PA",
    "wof:name":"Jasmin Ortiz",
    "wof:placetype":"venue"
},
  "geometry": {"coordinates":[-75.36732000000001,40.607324],"type":"Point"}
}