{
  "type": "Feature",
  "properties": {
    "iso:country":"US",
    "sg:address":"3618 Limestone Rd",
    "sg:city":"Parkesburg",
    "sg:classifiers":[
        {
            "category":"Shopping",
            "subcategory":"Used Merchandise",
            "type":"Retail Goods"
        }
    ],
    "sg:phone":"+1 610 857 2149",
    "sg:postcode":"19365",
    "sg:province":"PA",
    "sg:tags":[
        "antique"
    ],
    "wof:name":"Griest Auction",
    "wof:placetype":"venue"
},
  "geometry": {"coordinates":[-75.914186,39.94292],"type":"Point"}
}