{
  "type": "Feature",
  "properties": {
    "iso:country":"US",
    "sg:address":"1510 Mount Zion Rd",
    "sg:city":"York",
    "sg:classifiers":[
        {
            "category":"Restaurant",
            "type":"Food & Drink"
        }
    ],
    "sg:menulink":"http://www.allmenus.com/pa/springettsbury/10387-texas-roadhouse/menu/",
    "sg:phone":"+1 717 600 1441",
    "sg:postcode":"17402",
    "sg:province":"PA",
    "sg:tags":[
        "american",
        "steakhouse"
    ],
    "wof:name":"Texas Roadhouse",
    "wof:placetype":"venue"
},
  "geometry": {"coordinates":[-76.671434,39.991685],"type":"Point"}
}