{
  "type": "Feature",
  "properties": {
    "iso:country":"US",
    "sg:address":"318 N 9th St",
    "sg:city":"Easton",
    "sg:classifiers":[
        {
            "category":"Building & Trades",
            "subcategory":"Construction",
            "type":"Services"
        }
    ],
    "sg:phone":"+1 610 554 4913",
    "sg:postcode":"18042",
    "sg:province":"PA",
    "sg:tags":[
        "repair",
        "handyman",
        "maintenance",
        "home"
    ],
    "wof:name":"Jays Quick Response Handyman Services",
    "wof:placetype":"venue"
},
  "geometry": {"coordinates":[-75.221321,40.69413],"type":"Point"}
}