{
  "type": "Feature",
  "properties": {
    "addr:full":"145 W Gay St West Chester PA 19380",
    "addr:housenumber":"145",
    "addr:postcode":"19380",
    "addr:street":"W Gay St",
    "iso:country":"US",
    "sg:address":"145 W Gay St",
    "sg:city":"West Chester",
    "sg:classifiers":[
        {
            "category":"Shopping",
            "subcategory":"Clothing, Apparel, & Fashions",
            "type":"Retail Goods"
        }
    ],
    "sg:phone":"+1 610 738 9952",
    "sg:postcode":"19380",
    "sg:province":"PA",
    "sg:tags":[
        "item",
        "boutique"
    ],
    "wof:name":"Malena's",
    "wof:placetype":"venue"
},
  "geometry": {"coordinates":[-75.607224,39.959707],"type":"Point"}
}