{
  "type": "Feature",
  "properties": {
    "addr:full":"4901 Catharine St Philadelphia PA 19143",
    "addr:housenumber":"4901",
    "addr:postcode":"19143",
    "addr:street":"Catharine St",
    "iso:country":"US",
    "sg:address":"4901 Catharine St",
    "sg:city":"Philadelphia",
    "sg:classifiers":[
        {
            "category":"Organizations",
            "subcategory":"Community Association",
            "type":"Services"
        }
    ],
    "sg:phone":"+1 215 476 1515",
    "sg:postcode":"19143",
    "sg:province":"PA",
    "sg:tags":[
        "club"
    ],
    "wof:name":"Third World Lounge",
    "wof:placetype":"venue"
},
  "geometry": {"coordinates":[-75.22322699999999,39.948471],"type":"Point"}
}