{
  "type": "Feature",
  "properties": {
    "iso:country":"US",
    "sg:address":"1815 Crestline St",
    "sg:city":"Pittsburgh",
    "sg:classifiers":[
        {
            "category":"Building & Trades",
            "subcategory":"Construction",
            "type":"Services"
        }
    ],
    "sg:phone":"+1   ",
    "sg:postcode":"15221",
    "sg:province":"PA",
    "sg:tags":[
        "special",
        "contractor"
    ],
    "wof:name":"Door Plus",
    "wof:placetype":"venue"
},
  "geometry": {"coordinates":[-79.87589199999999,40.451884],"type":"Point"}
}