{
  "type": "Feature",
  "properties": {
    "iso:country":"US",
    "sg:address":"3653 Lincoln Way E",
    "sg:city":"Fayetteville",
    "sg:classifiers":[
        {
            "category":"Shopping",
            "subcategory":"Used Merchandise",
            "type":"Retail Goods"
        }
    ],
    "sg:phone":"+1 717 352 8485",
    "sg:postcode":"17222",
    "sg:province":"PA",
    "wof:name":"Fayetteville Antique Mall",
    "wof:placetype":"venue"
},
  "geometry": {"coordinates":[-77.56195099999999,39.910976],"type":"Point"}
}