{
  "type": "Feature",
  "properties": {
    "addr:full":"100 Spring St Coal Center PA 15423",
    "addr:housenumber":"100",
    "addr:postcode":"15423",
    "addr:street":"Spring St",
    "iso:country":"US",
    "sg:address":"100 Spring St",
    "sg:city":"Coal Center",
    "sg:classifiers":[
        {
            "category":"Restaurant",
            "type":"Food & Drink"
        }
    ],
    "sg:phone":"+1 724 938 3470",
    "sg:postcode":"15423",
    "sg:province":"PA",
    "wof:name":"Lagerheads",
    "wof:placetype":"venue"
},
  "geometry": {"coordinates":[-79.899621,40.070696],"type":"Point"}
}