{
  "type": "Feature",
  "properties": {
    "addr:full":"3300 Henry Ave Philadelphia PA 19129",
    "addr:housenumber":"3300",
    "addr:postcode":"19129",
    "addr:street":"Henry Ave",
    "iso:country":"US",
    "sg:address":"3300 Henry Ave",
    "sg:city":"Philadelphia",
    "sg:classifiers":[
        {
            "category":"Health Services",
            "subcategory":"Doctor",
            "type":"Services"
        }
    ],
    "sg:phone":"+1 215 842 6555",
    "sg:postcode":"19129",
    "sg:province":"PA",
    "wof:name":"Kahng Kim MD",
    "wof:placetype":"venue"
},
  "geometry": {"coordinates":[-75.182472,40.011713],"type":"Point"}
}