{
  "type": "Feature",
  "properties": {
    "addr:full":"5074 Raintree Ct Buckingham PA 18912",
    "addr:housenumber":"5074",
    "addr:postcode":"18912",
    "addr:street":"Raintree Ct",
    "iso:country":"US",
    "sg:address":"5074 Raintree Ct",
    "sg:city":"Buckingham",
    "sg:classifiers":[
        {
            "category":"Professional",
            "subcategory":"Lawyer & Legal Services",
            "type":"Services"
        }
    ],
    "sg:phone":"+1 267 247 0162",
    "sg:postcode":"18912",
    "sg:province":"PA",
    "wof:name":"McCullough & Eisenberg Law Office PC",
    "wof:placetype":"venue"
},
  "geometry": {"coordinates":[-75.0625,40.321701],"type":"Point"}
}