{
  "type": "Feature",
  "properties": {
    "iso:country":"US",
    "sg:address":"16 Wyndena Ln",
    "sg:city":"Newtown Square",
    "sg:classifiers":[
        {
            "category":"Personal",
            "type":"Services"
        }
    ],
    "sg:phone":"+1   ",
    "sg:postcode":"19073",
    "sg:province":"PA",
    "wof:name":"Timothy T Irvine",
    "wof:placetype":"venue"
},
  "geometry": {"coordinates":[-75.383059,39.983999],"type":"Point"}
}