{
  "type": "Feature",
  "properties": {
    "iso:country":"US",
    "sg:address":"4914 Somers Ave",
    "sg:city":"Bensalem",
    "sg:classifiers":[
        {
            "category":"Building & Trades",
            "subcategory":"Cleaning & Sanitation",
            "type":"Services"
        },
        {
            "category":"Building & Trades",
            "subcategory":"Plumbing",
            "type":"Services"
        }
    ],
    "sg:phone":"+1 215 364 5458",
    "sg:postcode":"19053",
    "sg:province":"PA",
    "sg:tags":[
        "plumbing",
        "janitor",
        "contractor"
    ],
    "wof:name":"Vogt Drain Cleaning",
    "wof:placetype":"venue"
},
  "geometry": {"coordinates":[-74.972306,40.154061],"type":"Point"}
}