{
  "type": "Feature",
  "properties": {
    "iso:country":"US",
    "sg:address":"2066 W 20th St",
    "sg:city":"Erie",
    "sg:classifiers":[
        {
            "category":"Retail",
            "subcategory":"Repair Shop",
            "type":"Services"
        },
        {
            "category":"Autos & Motor Vehicles",
            "subcategory":"Motorcycle Sales",
            "type":"Retail Goods"
        }
    ],
    "sg:phone":"+1 814 459 3911",
    "sg:postcode":"16502",
    "sg:province":"PA",
    "sg:tags":[
        "classic"
    ],
    "wof:name":"Dino's Motorcycle Repair",
    "wof:placetype":"venue"
},
  "geometry": {"coordinates":[-80.122974,42.099983],"type":"Point"}
}