{
  "type": "Feature",
  "properties": {
    "iso:country":"US",
    "sg:address":"961 Marcon Blvd Ste 440",
    "sg:city":"Allentown",
    "sg:classifiers":[
        {
            "category":"Banks & Credit Unions",
            "subcategory":"Investment Brokerage",
            "type":"Services"
        }
    ],
    "sg:phone":"+1 610 231 1850",
    "sg:postcode":"18109",
    "sg:province":"PA",
    "sg:tags":[
        "investing"
    ],
    "wof:name":"O'neill Sandra P Cfp",
    "wof:placetype":"venue"
},
  "geometry": {"coordinates":[-75.43849899999999,40.6451],"type":"Point"}
}