{
  "type": "Feature",
  "properties": {
    "iso:country":"US",
    "sg:address":"434 Deer Creek Rd",
    "sg:city":"Cochranton",
    "sg:classifiers":[
        {
            "category":"Wholesale",
            "subcategory":"Office Equipment",
            "type":"Manufacturing & Wholesale Goods"
        },
        {
            "category":"Retail",
            "subcategory":"Repair Shop",
            "type":"Services"
        }
    ],
    "sg:phone":"+1 724 253 2700",
    "sg:postcode":"16314",
    "sg:province":"PA",
    "sg:tags":[
        "register",
        "electrical",
        "cash"
    ],
    "wof:name":"Office Equipment Technical Svc",
    "wof:placetype":"venue"
},
  "geometry": {"coordinates":[-80.11153299999999,41.449553],"type":"Point"}
}