{
  "type": "Feature",
  "properties": {
    "iso:country":"US",
    "sg:address":"2655 S Iseminger St",
    "sg:city":"Philadelphia",
    "sg:classifiers":[
        {
            "category":"Manufacturing",
            "subcategory":"Food",
            "type":"Manufacturing & Wholesale Goods"
        },
        {
            "category":"Food & Beverages",
            "subcategory":"Bakery",
            "type":"Retail Goods"
        }
    ],
    "sg:phone":"+1 215 462 6991",
    "sg:postcode":"19148",
    "sg:province":"PA",
    "sg:tags":[
        "baker",
        "bread",
        "specialty",
        "italian"
    ],
    "sg:website":"www.carangibakery.com/",
    "wof:name":"Carangi Baking Co",
    "wof:placetype":"venue"
},
  "geometry": {"coordinates":[-75.16860200000001,39.916599],"type":"Point"}
}