{
  "type": "Feature",
  "properties": {
    "addr:full":"1330 Kimberly Rd Sharon PA 16146",
    "addr:housenumber":"1330",
    "addr:postcode":"16146",
    "addr:street":"Kimberly Rd",
    "iso:country":"US",
    "sg:address":"1330 Kimberly Rd",
    "sg:city":"Sharon",
    "sg:classifiers":[
        {
            "category":"Restaurant",
            "type":"Food & Drink"
        }
    ],
    "sg:phone":"+1 724 347 4024",
    "sg:postcode":"16146",
    "sg:province":"PA",
    "wof:name":"Golden Lion Restaurant",
    "wof:placetype":"venue"
},
  "geometry": {"coordinates":[-80.48472099999999,41.237086],"type":"Point"}
}