{
  "type": "Feature",
  "properties": {
    "iso:country":"US",
    "sg:address":"519 Vander Ave",
    "sg:city":"York",
    "sg:classifiers":[
        {
            "category":"Organizations",
            "subcategory":"Religious Organization",
            "type":"Services"
        }
    ],
    "sg:phone":"+1   ",
    "sg:postcode":"17403",
    "sg:province":"PA",
    "wof:name":"York First Church of God",
    "wof:placetype":"venue"
},
  "geometry": {"coordinates":[-76.71360199999999,39.96011],"type":"Point"}
}