{
  "type": "Feature",
  "properties": {
    "addr:full":"72 E Swedesford Rd Malvern PA 19355",
    "addr:housenumber":"72",
    "addr:postcode":"19355",
    "addr:street":"E Swedesford Rd",
    "iso:country":"US",
    "sg:address":"72 E Swedesford Rd",
    "sg:city":"Malvern",
    "sg:classifiers":[
        {
            "category":"Banks & Credit Unions",
            "subcategory":"Investment Brokerage",
            "type":"Services"
        }
    ],
    "sg:phone":"+1   ",
    "sg:postcode":"19355",
    "sg:province":"PA",
    "sg:tags":[
        "insurance"
    ],
    "wof:name":"Prudential",
    "wof:placetype":"venue"
},
  "geometry": {"coordinates":[-75.517183,40.056084],"type":"Point"}
}