{
  "type": "Feature",
  "properties": {
    "iso:country":"US",
    "sg:address":"2300 Adams Ave",
    "sg:city":"Scranton",
    "sg:classifiers":[
        {
            "category":"Place Of Worship",
            "subcategory":"Monastery",
            "type":"Public Place"
        }
    ],
    "sg:phone":"+1 570 346 5431",
    "sg:postcode":"18509",
    "sg:province":"PA",
    "sg:tags":[
        "convent"
    ],
    "wof:name":"Sisters Servants of The Immaculate Heart of Mary",
    "wof:placetype":"venue"
},
  "geometry": {"coordinates":[-75.63716100000001,41.432911],"type":"Point"}
}