{
  "type": "Feature",
  "properties": {
    "iso:country":"US",
    "sg:address":"100 Productivity Pl",
    "sg:city":"Irwin",
    "sg:classifiers":[
        {
            "category":"Manufacturing",
            "subcategory":"Tools & Machinery",
            "type":"Manufacturing & Wholesale Goods"
        }
    ],
    "sg:phone":"+1 724 864 2500",
    "sg:postcode":"15642",
    "sg:province":"PA",
    "sg:tags":[
        "shop",
        "machine",
        "industry",
        "metalworking",
        "mfg"
    ],
    "sg:website":"www.astroautomationinc.com",
    "wof:name":"Astro Automation Inc",
    "wof:placetype":"venue"
},
  "geometry": {"coordinates":[-79.70938,40.33403],"type":"Point"}
}