{
  "type": "Feature",
  "properties": {
    "iso:country":"US",
    "sg:address":"178 Juniata Pkwy E",
    "sg:city":"Newport",
    "sg:classifiers":[
        {
            "category":"Shopping",
            "type":"Retail Goods"
        }
    ],
    "sg:phone":"+1   ",
    "sg:postcode":"17074",
    "sg:province":"PA",
    "sg:tags":[
        "merchandise"
    ],
    "wof:name":"Pet Safe of Central PA Un",
    "wof:placetype":"venue"
},
  "geometry": {"coordinates":[-77.08066599999999,40.489367],"type":"Point"}
}