{
  "type": "Feature",
  "properties": {
    "iso:country":"US",
    "sg:address":"1258 Hwy 315",
    "sg:city":"Wilkes Barre",
    "sg:classifiers":[
        {
            "category":"Banks & Credit Unions",
            "subcategory":"Investment Brokerage",
            "type":"Services"
        }
    ],
    "sg:phone":"+1 570 822 5571",
    "sg:postcode":"18702",
    "sg:province":"PA",
    "sg:tags":[
        "advisory",
        "financial"
    ],
    "wof:name":"Primerica Financial Svc",
    "wof:placetype":"venue"
},
  "geometry": {"coordinates":[-75.81483,41.265548],"type":"Point"}
}