{
  "type": "Feature",
  "properties": {
    "addr:full":"11 N Baltimore St Dillsburg PA 17019",
    "addr:housenumber":"11",
    "addr:postcode":"17019",
    "addr:street":"N Baltimore St",
    "iso:country":"US",
    "sg:address":"11 N Baltimore St",
    "sg:city":"Dillsburg",
    "sg:classifiers":[
        {
            "category":"Organizations",
            "subcategory":"Religious Organization",
            "type":"Services"
        }
    ],
    "sg:phone":"+1 717 502 8808",
    "sg:postcode":"17019",
    "sg:province":"PA",
    "sg:tags":[
        "church"
    ],
    "wof:name":"Mountain Ridge Regional Church",
    "wof:placetype":"venue"
},
  "geometry": {"coordinates":[-77.03582,40.111329],"type":"Point"}
}