{
  "type": "Feature",
  "properties": {
    "addr:full":"3860 Hamilton Blvd Allentown PA 18103",
    "addr:housenumber":"3860",
    "addr:postcode":"18103",
    "addr:street":"Hamilton Blvd",
    "iso:country":"US",
    "sg:address":"3860 Hamilton Blvd",
    "sg:city":"Allentown",
    "sg:classifiers":[
        {
            "category":"Restaurant",
            "type":"Food & Drink"
        }
    ],
    "sg:menulink":"http://www.allmenus.com/pa/south-whitehall/205928-mcdonalds/menu/",
    "sg:phone":"+1 610 770 8996",
    "sg:postcode":"18103",
    "sg:province":"PA",
    "sg:tags":[
        "burger",
        "american"
    ],
    "wof:name":"McDonald's",
    "wof:placetype":"venue"
},
  "geometry": {"coordinates":[-75.533036,40.574445],"type":"Point"}
}