{
  "type": "Feature",
  "properties": {
    "iso:country":"US",
    "sg:address":"407 Bell Ave",
    "sg:city":"New Castle",
    "sg:classifiers":[
        {
            "category":"Building & Trades",
            "subcategory":"Construction",
            "type":"Services"
        }
    ],
    "sg:phone":"+1   ",
    "sg:postcode":"16101",
    "sg:province":"PA",
    "sg:tags":[
        "general"
    ],
    "wof:name":"Rapid Construction",
    "wof:placetype":"venue"
},
  "geometry": {"coordinates":[-80.360707,41.005073],"type":"Point"}
}