{
  "type": "Feature",
  "properties": {
    "addr:full":"810 Lincoln Hwy Coatesville PA 19320",
    "addr:housenumber":"810",
    "addr:postcode":"19320",
    "addr:street":"Lincoln Hwy",
    "iso:country":"US",
    "sg:address":"810 Lincoln Hwy",
    "sg:city":"Coatesville",
    "sg:classifiers":[
        {
            "category":"Shopping",
            "subcategory":"Discount & Variety Stores",
            "type":"Retail Goods"
        }
    ],
    "sg:phone":"+1   ",
    "sg:postcode":"19320",
    "sg:province":"PA",
    "sg:tags":[
        "department"
    ],
    "wof:name":"Family Dollar Stores",
    "wof:placetype":"venue"
},
  "geometry": {"coordinates":[-75.843277,39.98368],"type":"Point"}
}