{
  "type": "Feature",
  "properties": {
    "iso:country":"US",
    "sg:address":"506 W Cypress St",
    "sg:city":"Kennett Square",
    "sg:classifiers":[
        {
            "category":"Autos & Motor Vehicles",
            "subcategory":"Fuel & Gas Station",
            "type":"Retail Goods"
        }
    ],
    "sg:phone":"+1 610 444 3985",
    "sg:postcode":"19348",
    "sg:province":"PA",
    "sg:tags":[
        "oil"
    ],
    "wof:name":"Kennett Texaco",
    "wof:placetype":"venue"
},
  "geometry": {"coordinates":[-75.695556,39.82824],"type":"Point"}
}