{
  "type": "Feature",
  "properties": {
    "addr:full":"4121 Franklin Way Lafayette Hill PA 19444",
    "addr:housenumber":"4121",
    "addr:postcode":"19444",
    "addr:street":"Franklin Way",
    "iso:country":"US",
    "sg:address":"4121 Franklin Way",
    "sg:city":"Lafayette Hill",
    "sg:classifiers":[
        {
            "category":"Building & Trades",
            "subcategory":"Construction",
            "type":"Services"
        }
    ],
    "sg:phone":"+1   ",
    "sg:postcode":"19444",
    "sg:province":"PA",
    "sg:tags":[
        "house"
    ],
    "wof:name":"Carpenter Construction Co",
    "wof:placetype":"venue"
},
  "geometry": {"coordinates":[-75.260007,40.101997],"type":"Point"}
}