{
  "type": "Feature",
  "properties": {
    "iso:country":"US",
    "sg:address":"834 W 3rd St",
    "sg:city":"Lansdale",
    "sg:classifiers":[
        {
            "category":"Building & Trades",
            "subcategory":"Construction",
            "type":"Services"
        }
    ],
    "sg:phone":"+1 215 361 6120",
    "sg:postcode":"19446",
    "sg:province":"PA",
    "sg:tags":[
        "masonry",
        "contractor"
    ],
    "wof:name":"Giampa Construction",
    "wof:placetype":"venue"
},
  "geometry": {"coordinates":[-75.292514,40.249354],"type":"Point"}
}