{
  "type": "Feature",
  "properties": {
    "addr:full":"1415 Jay St Lebanon PA 17046",
    "addr:housenumber":"1415",
    "addr:postcode":"17046",
    "addr:street":"Jay St",
    "iso:country":"US",
    "sg:address":"1415 Jay St",
    "sg:city":"Lebanon",
    "sg:classifiers":[
        {
            "category":"Building & Trades",
            "subcategory":"Construction",
            "type":"Services"
        }
    ],
    "sg:phone":"+1   ",
    "sg:postcode":"17046",
    "sg:province":"PA",
    "sg:tags":[
        "contractor"
    ],
    "wof:name":"Bower Constructions",
    "wof:placetype":"venue"
},
  "geometry": {"coordinates":[-76.44024899999999,40.36588],"type":"Point"}
}