{
  "type": "Feature",
  "properties": {
    "iso:country":"US",
    "sg:address":"750 W Chester Rd",
    "sg:city":"West Chester",
    "sg:classifiers":[
        {
            "category":"Education",
            "subcategory":"School",
            "type":"Public Place"
        }
    ],
    "sg:phone":"+1   ",
    "sg:postcode":"19382",
    "sg:province":"PA",
    "wof:name":"Westtwn-Thrnbury Elmntary Schl",
    "wof:placetype":"venue"
},
  "geometry": {"coordinates":[-75.545683,39.910869],"type":"Point"}
}