{
  "type": "Feature",
  "properties": {
    "iso:country":"US",
    "sg:address":"176 Oak Terrace Dr",
    "sg:city":"Birdsboro",
    "sg:classifiers":[
        {
            "category":"Shopping",
            "subcategory":"Computers & Home Electronics",
            "type":"Retail Goods"
        }
    ],
    "sg:phone":"+1   ",
    "sg:postcode":"19508",
    "sg:province":"PA",
    "wof:name":"PC Pro",
    "wof:placetype":"venue"
},
  "geometry": {"coordinates":[-75.87716899999999,40.264173],"type":"Point"}
}