{
  "type": "Feature",
  "properties": {
    "iso:country":"US",
    "sg:address":"2716 Birney Ave",
    "sg:city":"Scranton",
    "sg:classifiers":[
        {
            "category":"Bars & Pubs",
            "type":"Food & Drink"
        }
    ],
    "sg:phone":"+1 570 963 0770",
    "sg:postcode":"18505",
    "sg:province":"PA",
    "wof:name":"Diskin's Salon",
    "wof:placetype":"venue"
},
  "geometry": {"coordinates":[-75.68875800000001,41.381702],"type":"Point"}
}