{
  "type": "Feature",
  "properties": {
    "addr:full":"2450 Wilson St Reading PA 19605",
    "addr:housenumber":"2450",
    "addr:postcode":"19605",
    "addr:street":"Wilson St",
    "iso:country":"US",
    "sg:address":"2450 Wilson St",
    "sg:city":"Reading",
    "sg:classifiers":[
        {
            "category":"Building & Trades",
            "subcategory":"Construction",
            "type":"Services"
        }
    ],
    "sg:phone":"+1   ",
    "sg:postcode":"19605",
    "sg:province":"PA",
    "sg:tags":[
        "new",
        "s",
        "general",
        "remodeling",
        "contractor"
    ],
    "wof:name":"Bob Billman Building Contr",
    "wof:placetype":"venue"
},
  "geometry": {"coordinates":[-75.966843,40.387252],"type":"Point"}
}