{
  "type": "Feature",
  "properties": {
    "iso:country":"US",
    "sg:address":"1433 W Erie Ave",
    "sg:city":"Philadelphia",
    "sg:classifiers":[
        {
            "category":"Social Services",
            "subcategory":"Child Care",
            "type":"Services"
        }
    ],
    "sg:phone":"+1 215 221 9111",
    "sg:postcode":"19140",
    "sg:province":"PA",
    "sg:tags":[
        "day"
    ],
    "wof:name":"Precious Babies Day Care",
    "wof:placetype":"venue"
},
  "geometry": {"coordinates":[-75.15280199999999,40.0093],"type":"Point"}
}