{
  "type": "Feature",
  "properties": {
    "iso:country":"US",
    "sg:address":"954 Red Coat Farm Dr",
    "sg:city":"Chalfont",
    "sg:classifiers":[
        {
            "category":"Professional",
            "subcategory":"Art Services",
            "type":"Services"
        }
    ],
    "sg:phone":"+1   ",
    "sg:postcode":"18914",
    "sg:province":"PA",
    "sg:tags":[
        "re",
        "commercial",
        "maintenance"
    ],
    "wof:name":"Bluemedia",
    "wof:placetype":"venue"
},
  "geometry": {"coordinates":[-75.181196,40.266674],"type":"Point"}
}