{
  "type": "Feature",
  "properties": {
    "iso:country":"US",
    "sg:address":"301 1st St",
    "sg:city":"Port Carbon",
    "sg:classifiers":[
        {
            "category":"Government",
            "subcategory":"Police Station",
            "type":"Public Place"
        }
    ],
    "sg:phone":"+1 570 622 5411",
    "sg:postcode":"17965",
    "sg:province":"PA",
    "sg:tags":[
        "department"
    ],
    "wof:name":"Port Carbon Police Dept",
    "wof:placetype":"venue"
},
  "geometry": {"coordinates":[-76.16797099999999,40.696531],"type":"Point"}
}