{
  "type": "Feature",
  "properties": {
    "iso:country":"US",
    "sg:address":"17602 Rte 286 E",
    "sg:city":"Commodore",
    "sg:classifiers":[
        {
            "category":"Freight",
            "type":"Transportation"
        }
    ],
    "sg:phone":"+1 724 254 2386",
    "sg:postcode":"15729",
    "sg:province":"PA",
    "sg:tags":[
        "commercial",
        "storage",
        "special"
    ],
    "wof:name":"Baker's Storage",
    "wof:placetype":"venue"
},
  "geometry": {"coordinates":[-78.90235,40.738906],"type":"Point"}
}