{
  "type": "Feature",
  "properties": {
    "addr:full":"3876 Union Deposit Rd Harrisburg PA 17109",
    "addr:housenumber":"3876",
    "addr:postcode":"17109",
    "addr:street":"Union Deposit Rd",
    "iso:country":"US",
    "sg:address":"3876 Union Deposit Rd",
    "sg:city":"Harrisburg",
    "sg:classifiers":[
        {
            "category":"Banks & Credit Unions",
            "subcategory":"Bank",
            "type":"Services"
        }
    ],
    "sg:phone":"+1 717 540 7066",
    "sg:postcode":"17109",
    "sg:province":"PA",
    "sg:tags":[
        "cashing",
        "check"
    ],
    "wof:name":"Check 'n Go",
    "wof:placetype":"venue"
},
  "geometry": {"coordinates":[-76.82606800000001,40.278371],"type":"Point"}
}