{
  "type": "Feature",
  "properties": {
    "addr:full":"3950 Tecport Dr Ste 160 Harrisburg PA 17111",
    "addr:housenumber":"3950",
    "addr:postcode":"17111",
    "addr:street":"Tecport Dr Ste 160",
    "iso:country":"US",
    "sg:address":"3950 Tecport Dr Ste 160",
    "sg:city":"Harrisburg",
    "sg:classifiers":[
        {
            "category":"Personal",
            "subcategory":"Tanning Parlor",
            "type":"Services"
        }
    ],
    "sg:phone":"+1 717 561 3808",
    "sg:postcode":"17111",
    "sg:province":"PA",
    "wof:name":"Italian Tan & Spa",
    "wof:placetype":"venue"
},
  "geometry": {"coordinates":[-76.820031,40.251946],"type":"Point"}
}