{
  "type": "Feature",
  "properties": {
    "iso:country":"US",
    "sg:address":"801 N Wales Rd",
    "sg:city":"North Wales",
    "sg:classifiers":[
        {
            "category":"Shopping",
            "subcategory":"Department Store",
            "type":"Retail Goods"
        }
    ],
    "sg:phone":"+1 215 362 7433",
    "sg:postcode":"19454",
    "sg:province":"PA",
    "sg:website":"www.marshalls.com",
    "wof:name":"Marshalls",
    "wof:placetype":"venue"
},
  "geometry": {"coordinates":[-75.29195900000001,40.19556],"type":"Point"}
}