{
  "type": "Feature",
  "properties": {
    "iso:country":"US",
    "sg:address":"15 W Highland Ave",
    "sg:city":"Philadelphia",
    "sg:classifiers":[
        {
            "category":"Real Estate",
            "subcategory":"Architect",
            "type":"Services"
        }
    ],
    "sg:phone":"+1   ",
    "sg:postcode":"19118",
    "sg:province":"PA",
    "sg:tags":[
        "architectural"
    ],
    "wof:name":"Joel Levinson & Assocs",
    "wof:placetype":"venue"
},
  "geometry": {"coordinates":[-75.207666,40.074899],"type":"Point"}
}