{
  "type": "Feature",
  "properties": {
    "addr:full":"995 Burns Ave Meadville PA 16335",
    "addr:housenumber":"995",
    "addr:postcode":"16335",
    "addr:street":"Burns Ave",
    "iso:country":"US",
    "sg:address":"995 Burns Ave",
    "sg:city":"Meadville",
    "sg:classifiers":[
        {
            "category":"Professional",
            "type":"Services"
        }
    ],
    "sg:phone":"+1   ",
    "sg:postcode":"16335",
    "sg:province":"PA",
    "wof:name":"David Paul Volna",
    "wof:placetype":"venue"
},
  "geometry": {"coordinates":[-80.138948,41.633453],"type":"Point"}
}