{
  "type": "Feature",
  "properties": {
    "iso:country":"US",
    "sg:address":"319 N Duke St",
    "sg:city":"Lancaster",
    "sg:classifiers":[
        {
            "category":"Health Services",
            "subcategory":"Optometrist",
            "type":"Services"
        }
    ],
    "sg:phone":"+1   ",
    "sg:postcode":"17602",
    "sg:province":"PA",
    "wof:name":"Diamantoni Assc Optometrist",
    "wof:placetype":"venue"
},
  "geometry": {"coordinates":[-76.304759,40.044201],"type":"Point"}
}