{
  "type": "Feature",
  "properties": {
    "addr:full":"200 Dinsmore Ave Pittsburgh PA 15205",
    "addr:housenumber":"200",
    "addr:postcode":"15205",
    "addr:street":"Dinsmore Ave",
    "iso:country":"US",
    "sg:address":"200 Dinsmore Ave",
    "sg:city":"Pittsburgh",
    "sg:classifiers":[
        {
            "category":"Insurance",
            "subcategory":"Insurance Agent",
            "type":"Services"
        }
    ],
    "sg:phone":"+1 412 922 1122",
    "sg:postcode":"15205",
    "sg:province":"PA",
    "wof:name":"Allstate Insurance",
    "wof:placetype":"venue"
},
  "geometry": {"coordinates":[-80.064516,40.435417],"type":"Point"}
}