{
  "type": "Feature",
  "properties": {
    "iso:country":"US",
    "sg:address":"4320 Frankford Ave",
    "sg:city":"Philadelphia",
    "sg:classifiers":[
        {
            "category":"Retail",
            "subcategory":"Repair Shop",
            "type":"Services"
        }
    ],
    "sg:phone":"+1 215 676 0404",
    "sg:postcode":"19124",
    "sg:province":"PA",
    "sg:tags":[
        "lock",
        "locksmith"
    ],
    "wof:name":"Northeast 24 Hour Fast",
    "wof:placetype":"venue"
},
  "geometry": {"coordinates":[-75.087924,40.012192],"type":"Point"}
}