{
  "type": "Feature",
  "properties": {
    "iso:country":"US",
    "sg:address":"38 N Main St",
    "sg:city":"Chambersburg",
    "sg:classifiers":[
        {
            "category":"Professional",
            "subcategory":"Lawyer & Legal Services",
            "type":"Services"
        }
    ],
    "sg:phone":"+1   ",
    "sg:postcode":"17201",
    "sg:province":"PA",
    "wof:name":"Gray Law Office PC",
    "wof:placetype":"venue"
},
  "geometry": {"coordinates":[-77.66119999999999,39.937709],"type":"Point"}
}