{
  "type": "Feature",
  "properties": {
    "addr:full":"805 East St Pittsburgh PA 15212",
    "addr:housenumber":"805",
    "addr:postcode":"15212",
    "addr:street":"East St",
    "iso:country":"US",
    "sg:address":"805 East St",
    "sg:city":"Pittsburgh",
    "sg:classifiers":[
        {
            "category":"Recreation",
            "type":"Entertainment"
        },
        {
            "category":"Organizations",
            "subcategory":"Community Association",
            "type":"Services"
        }
    ],
    "sg:phone":"+1 412 321 8104",
    "sg:postcode":"15212",
    "sg:province":"PA",
    "sg:tags":[
        "club",
        "membership"
    ],
    "wof:name":"Croatian National Hall Inc",
    "wof:placetype":"venue"
},
  "geometry": {"coordinates":[-79.998285,40.455033],"type":"Point"}
}