{
  "type": "Feature",
  "properties": {
    "iso:country":"US",
    "sg:address":"1513 Bethlehem Pike",
    "sg:city":"Hilltown",
    "sg:classifiers":[
        {
            "category":"Banks & Credit Unions",
            "subcategory":"Bank",
            "type":"Services"
        }
    ],
    "sg:phone":"+1 215 996 1100",
    "sg:postcode":"18927",
    "sg:province":"PA",
    "wof:name":"Sovereign Bank",
    "wof:placetype":"venue"
},
  "geometry": {"coordinates":[-75.26677599999999,40.288317],"type":"Point"}
}