{
  "type": "Feature",
  "properties": {
    "iso:country":"US",
    "sg:address":"312 Thompson Ave",
    "sg:city":"Mc Kees Rocks",
    "sg:classifiers":[
        {
            "category":"Professional",
            "subcategory":"Computer Services",
            "type":"Services"
        }
    ],
    "sg:phone":"+1 412 771 8307",
    "sg:postcode":"15136",
    "sg:province":"PA",
    "sg:tags":[
        "repair"
    ],
    "wof:name":"Smart Print Technologies",
    "wof:placetype":"venue"
},
  "geometry": {"coordinates":[-80.058899,40.464901],"type":"Point"}
}