{
  "type": "Feature",
  "properties": {
    "addr:full":"412 Main St Duryea PA 18642",
    "addr:housenumber":"412",
    "addr:postcode":"18642",
    "addr:street":"Main St",
    "iso:country":"US",
    "sg:address":"412 Main St",
    "sg:city":"Duryea",
    "sg:classifiers":[
        {
            "category":"Food & Beverages",
            "subcategory":"Groceries & Convenience Stores",
            "type":"Retail Goods"
        }
    ],
    "sg:phone":"+1 570 457 3261",
    "sg:postcode":"18642",
    "sg:province":"PA",
    "sg:tags":[
        "grocer"
    ],
    "wof:name":"Komensky's Market",
    "wof:placetype":"venue"
},
  "geometry": {"coordinates":[-75.762186,41.351351],"type":"Point"}
}