{
  "type": "Feature",
  "properties": {
    "addr:full":"49 E College Ave Morrisville PA 19067",
    "addr:housenumber":"49",
    "addr:postcode":"19067",
    "addr:street":"E College Ave",
    "iso:country":"US",
    "sg:address":"49 E College Ave",
    "sg:city":"Morrisville",
    "sg:classifiers":[
        {
            "category":"Wholesale",
            "subcategory":"Drugs",
            "type":"Manufacturing & Wholesale Goods"
        }
    ],
    "sg:phone":"+1   ",
    "sg:postcode":"19067",
    "sg:province":"PA",
    "wof:name":"Tap Pharmaceutical Products",
    "wof:placetype":"venue"
},
  "geometry": {"coordinates":[-74.83450499999999,40.241234],"type":"Point"}
}