{
  "type": "Feature",
  "properties": {
    "addr:full":"2511 W York St Philadelphia PA 19132",
    "addr:housenumber":"2511",
    "addr:postcode":"19132",
    "addr:street":"W York St",
    "iso:country":"US",
    "sg:address":"2511 W York St",
    "sg:city":"Philadelphia",
    "sg:classifiers":[
        {
            "category":"Retail",
            "subcategory":"Repair Shop",
            "type":"Services"
        }
    ],
    "sg:phone":"+1 215 223 7691",
    "sg:postcode":"19132",
    "sg:province":"PA",
    "sg:tags":[
        "related"
    ],
    "wof:name":"Bobby's Auto Repair",
    "wof:placetype":"venue"
},
  "geometry": {"coordinates":[-75.174813,39.991925],"type":"Point"}
}