{
  "type": "Feature",
  "properties": {
    "iso:country":"US",
    "sg:address":"105 Eileen Dr",
    "sg:city":"Pittsburgh",
    "sg:classifiers":[
        {
            "category":"Banks & Credit Unions",
            "subcategory":"Bank",
            "type":"Services"
        }
    ],
    "sg:phone":"+1   ",
    "sg:postcode":"15214",
    "sg:province":"PA",
    "sg:tags":[
        "state"
    ],
    "wof:name":"Pittsburgh Pepsi Cola Cr Un",
    "wof:placetype":"venue"
},
  "geometry": {"coordinates":[-80.03365700000001,40.50194],"type":"Point"}
}