{
  "type": "Feature",
  "properties": {
    "iso:country":"US",
    "sg:address":"134 Andrew Ln",
    "sg:city":"Lansdale",
    "sg:classifiers":[
        {
            "category":"Professional",
            "subcategory":"Accounting & Tax Preparation",
            "type":"Services"
        }
    ],
    "sg:phone":"+1 215 997 8166",
    "sg:postcode":"19446",
    "sg:province":"PA",
    "sg:tags":[
        "accountant"
    ],
    "wof:name":"Paul R Harvitz Accounting",
    "wof:placetype":"venue"
},
  "geometry": {"coordinates":[-75.239458,40.2651],"type":"Point"}
}