{
  "type": "Feature",
  "properties": {
    "addr:full":"929 Chippewa Rd Rockwood PA 15557",
    "addr:housenumber":"929",
    "addr:postcode":"15557",
    "addr:street":"Chippewa Rd",
    "iso:country":"US",
    "sg:address":"929 Chippewa Rd",
    "sg:city":"Rockwood",
    "sg:classifiers":[
        {
            "category":"Travel",
            "subcategory":"Hotels & Motels",
            "type":"Entertainment"
        }
    ],
    "sg:phone":"+1 814 926 4774",
    "sg:postcode":"15557",
    "sg:province":"PA",
    "sg:tags":[
        "operation"
    ],
    "wof:name":"Country Dreams",
    "wof:placetype":"venue"
},
  "geometry": {"coordinates":[-79.21035500000001,39.981345],"type":"Point"}
}