{
  "type": "Feature",
  "properties": {
    "iso:country":"US",
    "sg:address":"801 Ostrum St",
    "sg:city":"Bethlehem",
    "sg:classifiers":[
        {
            "category":"Health Services",
            "subcategory":"Doctor",
            "type":"Services"
        }
    ],
    "sg:phone":"+1 610 954 4300",
    "sg:postcode":"18015",
    "sg:province":"PA",
    "sg:tags":[
        "physician",
        "surgeon"
    ],
    "wof:name":"St Luke's Cancer Ctr",
    "wof:placetype":"venue"
},
  "geometry": {"coordinates":[-75.39397700000001,40.607161],"type":"Point"}
}