{
  "type": "Feature",
  "properties": {
    "iso:country":"US",
    "sg:address":"3099 Lincoln Hwy E",
    "sg:city":"Paradise",
    "sg:classifiers":[
        {
            "category":"Restaurant",
            "type":"Food & Drink"
        }
    ],
    "sg:phone":"+1 717 687 6900",
    "sg:postcode":"17562",
    "sg:province":"PA",
    "wof:name":"Two Cousins Family Restaurant",
    "wof:placetype":"venue"
},
  "geometry": {"coordinates":[-76.132385,40.010521],"type":"Point"}
}