{
  "type": "Feature",
  "properties": {
    "iso:country":"US",
    "sg:address":"950 Township Line Rd",
    "sg:city":"Chester",
    "sg:classifiers":[
        {
            "category":"Building & Trades",
            "subcategory":"Construction",
            "type":"Services"
        }
    ],
    "sg:phone":"+1 610 497 4450",
    "sg:postcode":"19013",
    "sg:province":"PA",
    "sg:tags":[
        "glass",
        "window",
        "installation",
        "aluminum",
        "contractor"
    ],
    "wof:name":"I Steinman & Sons Inc",
    "wof:placetype":"venue"
},
  "geometry": {"coordinates":[-75.40822199999999,39.836225],"type":"Point"}
}