{
  "type": "Feature",
  "properties": {
    "iso:country":"US",
    "sg:address":"240 Lincoln St",
    "sg:city":"Carlisle",
    "sg:classifiers":[
        {
            "category":"Government",
            "subcategory":"Police Station",
            "type":"Public Place"
        }
    ],
    "sg:phone":"+1 717 243 5252",
    "sg:postcode":"17013",
    "sg:province":"PA",
    "sg:tags":[
        "department"
    ],
    "wof:name":"Carlisle Police Headquarters",
    "wof:placetype":"venue"
},
  "geometry": {"coordinates":[-77.19475199999999,40.206913],"type":"Point"}
}