{
  "type": "Feature",
  "properties": {
    "iso:country":"US",
    "sg:address":"87 Street Rd",
    "sg:city":"Southampton",
    "sg:classifiers":[
        {
            "category":"Real Estate",
            "subcategory":"Real Estate Services",
            "type":"Services"
        },
        {
            "category":"Banks & Credit Unions",
            "subcategory":"Financial Services",
            "type":"Services"
        }
    ],
    "sg:phone":"+1 215 953 0606",
    "sg:postcode":"18966",
    "sg:province":"PA",
    "sg:tags":[
        "loan",
        "mortgage"
    ],
    "wof:name":"Sun Financial Corporation",
    "wof:placetype":"venue"
},
  "geometry": {"coordinates":[-75.05593500000001,40.181453],"type":"Point"}
}