{
  "type": "Feature",
  "properties": {
    "addr:full":"1613 Dogwood Rd Springfield PA 19031",
    "addr:housenumber":"1613",
    "addr:postcode":"19031",
    "addr:street":"Dogwood Rd",
    "iso:country":"US",
    "sg:address":"1613 Dogwood Rd",
    "sg:city":"Springfield",
    "sg:classifiers":[
        {
            "category":"Professional",
            "type":"Services"
        }
    ],
    "sg:phone":"+1 267 335 0570",
    "sg:postcode":"19031",
    "sg:province":"PA",
    "sg:tags":[
        "establishment"
    ],
    "wof:name":"Avatar",
    "wof:placetype":"venue"
},
  "geometry": {"coordinates":[-75.201471,40.111343],"type":"Point"}
}