{
  "type": "Feature",
  "properties": {
    "addr:full":"1620 Filmore St Aliquippa PA 15001",
    "addr:housenumber":"1620",
    "addr:postcode":"15001",
    "addr:street":"Filmore St",
    "iso:country":"US",
    "sg:address":"1620 Filmore St",
    "sg:city":"Aliquippa",
    "sg:classifiers":[
        {
            "category":"Professional",
            "type":"Services"
        }
    ],
    "sg:phone":"+1   ",
    "sg:postcode":"15001",
    "sg:province":"PA",
    "wof:name":"Levantis Inc",
    "wof:placetype":"venue"
},
  "geometry": {"coordinates":[-80.27132899999999,40.613547],"type":"Point"}
}