{
  "type": "Feature",
  "properties": {
    "iso:country":"US",
    "sg:address":"1620 Filmore St",
    "sg:city":"Aliquippa",
    "sg:classifiers":[
        {
            "category":"Professional",
            "type":"Services"
        }
    ],
    "sg:phone":"+1   ",
    "sg:postcode":"15001",
    "sg:province":"PA",
    "wof:name":"Levantis Inc",
    "wof:placetype":"venue"
},
  "geometry": {"coordinates":[-80.27132899999999,40.613547],"type":"Point"}
}