{
  "type": "Feature",
  "properties": {
    "iso:country":"US",
    "sg:address":"631 N Wales Rd",
    "sg:city":"North Wales",
    "sg:classifiers":[
        {
            "category":"Health Services",
            "subcategory":"Chiropractor",
            "type":"Services"
        }
    ],
    "sg:phone":"+1 215 661 8600",
    "sg:postcode":"19454",
    "sg:province":"PA",
    "wof:name":"Gwynedd Chiropractic",
    "wof:placetype":"venue"
},
  "geometry": {"coordinates":[-75.28532800000001,40.202601],"type":"Point"}
}