{
  "type": "Feature",
  "properties": {
    "iso:country":"US",
    "sg:address":"1216 E 38th St",
    "sg:city":"Erie",
    "sg:classifiers":[
        {
            "category":"Shopping",
            "subcategory":"Tobacco",
            "type":"Retail Goods"
        }
    ],
    "sg:phone":"+1 814 825 4730",
    "sg:postcode":"16504",
    "sg:province":"PA",
    "sg:tags":[
        "cigarette",
        "cigar",
        "dealer"
    ],
    "wof:name":"B & M Variety",
    "wof:placetype":"venue"
},
  "geometry": {"coordinates":[-80.039643,42.112275],"type":"Point"}
}