{
  "type": "Feature",
  "properties": {
    "iso:country":"US",
    "sg:address":"2011 Scotland Ave",
    "sg:city":"Chambersburg",
    "sg:classifiers":[
        {
            "category":"Education",
            "subcategory":"School",
            "type":"Public Place"
        }
    ],
    "sg:phone":"+1 717 261 1110",
    "sg:postcode":"17201",
    "sg:province":"PA",
    "wof:name":"Montessori Academy",
    "wof:placetype":"venue"
},
  "geometry": {"coordinates":[-77.63402600000001,39.9565],"type":"Point"}
}