{
  "type": "Feature",
  "properties": {
    "iso:country":"US",
    "sg:address":"1723 Diamond Station Rd",
    "sg:city":"Ephrata",
    "sg:classifiers":[
        {
            "category":"Farming",
            "subcategory":"Farm",
            "type":"Manufacturing & Wholesale Goods"
        }
    ],
    "sg:phone":"+1   ",
    "sg:postcode":"17522",
    "sg:province":"PA",
    "sg:tags":[
        "crop",
        "general"
    ],
    "wof:name":"Mervin Hoover",
    "wof:placetype":"venue"
},
  "geometry": {"coordinates":[-76.163183,40.158804],"type":"Point"}
}