{
  "type": "Feature",
  "properties": {
    "iso:country":"US",
    "sg:address":"122 S 2nd St",
    "sg:city":"Perkasie",
    "sg:classifiers":[
        {
            "category":"Health Services",
            "subcategory":"Chiropractor",
            "type":"Services"
        }
    ],
    "sg:phone":"+1 215 257 0104",
    "sg:postcode":"18944",
    "sg:province":"PA",
    "wof:name":"Kunze & Snyder",
    "wof:placetype":"venue"
},
  "geometry": {"coordinates":[-75.29487399999999,40.369209],"type":"Point"}
}