{
  "type": "Feature",
  "properties": {
    "iso:country":"US",
    "sg:address":"211 N 2nd St",
    "sg:city":"Hamburg",
    "sg:classifiers":[
        {
            "category":"Professional",
            "type":"Services"
        }
    ],
    "sg:phone":"+1   ",
    "sg:postcode":"19526",
    "sg:province":"PA",
    "wof:name":"Windsor Forge Pewter Brass Sp",
    "wof:placetype":"venue"
},
  "geometry": {"coordinates":[-75.98675,40.558628],"type":"Point"}
}