{
  "type": "Feature",
  "properties": {
    "addr:full":"7218 Lamport Rd Upper Darby PA 19082",
    "addr:housenumber":"7218",
    "addr:postcode":"19082",
    "addr:street":"Lamport Rd",
    "iso:country":"US",
    "sg:address":"7218 Lamport Rd",
    "sg:city":"Upper Darby",
    "sg:classifiers":[
        {
            "category":"Shopping",
            "subcategory":"Bicycles & Sporting Goods",
            "type":"Retail Goods"
        }
    ],
    "sg:phone":"+1   ",
    "sg:postcode":"19082",
    "sg:province":"PA",
    "wof:name":"Glenbos Sporting Pub",
    "wof:placetype":"venue"
},
  "geometry": {"coordinates":[-75.261743,39.949287],"type":"Point"}
}