{
  "type": "Feature",
  "properties": {
    "iso:country":"US",
    "sg:address":"2090 Linglestown Rd",
    "sg:city":"Harrisburg",
    "sg:classifiers":[
        {
            "category":"Social Services",
            "type":"Services"
        }
    ],
    "sg:phone":"+1 717 657 8848",
    "sg:postcode":"17110",
    "sg:province":"PA",
    "sg:tags":[
        "counselor",
        "marriage",
        "family"
    ],
    "wof:name":"Janet J Eisenbise",
    "wof:placetype":"venue"
},
  "geometry": {"coordinates":[-76.867209,40.328488],"type":"Point"}
}