{
  "type": "Feature",
  "properties": {
    "iso:country":"US",
    "sg:address":"5126 Mary Jo's Way",
    "sg:city":"Erie",
    "sg:classifiers":[
        {
            "category":"Retail",
            "subcategory":"Auto Repair",
            "type":"Services"
        }
    ],
    "sg:phone":"+1   ",
    "sg:postcode":"16509",
    "sg:province":"PA",
    "sg:tags":[
        "carwash",
        "automotive"
    ],
    "wof:name":"Car Gard",
    "wof:placetype":"venue"
},
  "geometry": {"coordinates":[-80.027809,42.101766],"type":"Point"}
}