{
  "type": "Feature",
  "properties": {
    "addr:full":"15 Junction Rd Dillsburg PA 17019",
    "addr:housenumber":"15",
    "addr:postcode":"17019",
    "addr:street":"Junction Rd",
    "iso:country":"US",
    "sg:address":"15 Junction Rd",
    "sg:city":"Dillsburg",
    "sg:classifiers":[
        {
            "category":"Organizations",
            "subcategory":"Community Association",
            "type":"Services"
        }
    ],
    "sg:phone":"+1   ",
    "sg:postcode":"17019",
    "sg:province":"PA",
    "wof:name":"Kiwanis Club of Dillsburg",
    "wof:placetype":"venue"
},
  "geometry": {"coordinates":[-77.02732399999999,40.14019],"type":"Point"}
}