{
  "type": "Feature",
  "properties": {
    "iso:country":"US",
    "sg:address":"303 Jonlyn Dr",
    "sg:city":"Elizabethtown",
    "sg:classifiers":[
        {
            "category":"Building & Trades",
            "subcategory":"Plumbing",
            "type":"Services"
        }
    ],
    "sg:phone":"+1 717 367 1363",
    "sg:postcode":"17022",
    "sg:province":"PA",
    "sg:tags":[
        "heating",
        "contractor"
    ],
    "wof:name":"Leo KOB Co Inc",
    "wof:placetype":"venue"
},
  "geometry": {"coordinates":[-76.574405,40.136247],"type":"Point"}
}