{
  "type": "Feature",
  "properties": {
    "addr:full":"223 Shiloh St Pittsburgh PA 15211",
    "addr:housenumber":"223",
    "addr:postcode":"15211",
    "addr:street":"Shiloh St",
    "iso:country":"US",
    "sg:address":"223 Shiloh St",
    "sg:city":"Pittsburgh",
    "sg:classifiers":[
        {
            "category":"Restaurant",
            "type":"Food & Drink"
        }
    ],
    "sg:phone":"+1 412 381 9221",
    "sg:postcode":"15211",
    "sg:province":"PA",
    "sg:tags":[
        "grocery",
        "eating"
    ],
    "wof:name":"Shiloh Village Dairy",
    "wof:placetype":"venue"
},
  "geometry": {"coordinates":[-80.007265,40.42952],"type":"Point"}
}