{
  "type": "Feature",
  "properties": {
    "iso:country":"US",
    "sg:address":"4600 Roosevelt Blvd",
    "sg:city":"Philadelphia",
    "sg:classifiers":[
        {
            "category":"Shopping",
            "subcategory":"Clothing, Apparel, & Fashions",
            "type":"Retail Goods"
        }
    ],
    "sg:phone":"+1   ",
    "sg:postcode":"19124",
    "sg:province":"PA",
    "wof:name":"Mothers Work",
    "wof:placetype":"venue"
},
  "geometry": {"coordinates":[-75.09912300000001,40.028313],"type":"Point"}
}