{
  "type": "Feature",
  "properties": {
    "iso:country":"US",
    "sg:address":"230 S Broad St Fl 5A",
    "sg:city":"Philadelphia",
    "sg:classifiers":[
        {
            "category":"Professional",
            "subcategory":"Accounting & Tax Preparation",
            "type":"Services"
        }
    ],
    "sg:phone":"+1 215 546 8016",
    "sg:postcode":"19102",
    "sg:province":"PA",
    "sg:tags":[
        "reporting"
    ],
    "wof:name":"Kauffman & Drebing",
    "wof:placetype":"venue"
},
  "geometry": {"coordinates":[-75.16449,39.9482],"type":"Point"}
}