{
  "type": "Feature",
  "properties": {
    "addr:full":"301 E City Ave Ste G1 Bala Cynwyd PA 19004",
    "addr:housenumber":"301",
    "addr:postcode":"19004",
    "addr:street":"E City Ave Ste G1",
    "iso:country":"US",
    "sg:address":"301 E City Ave Ste G1",
    "sg:city":"Bala Cynwyd",
    "sg:classifiers":[
        {
            "category":"Health Services",
            "subcategory":"Chiropractor",
            "type":"Services"
        }
    ],
    "sg:phone":"+1 610 668 6868",
    "sg:postcode":"19004",
    "sg:province":"PA",
    "wof:name":"Valley Forge Chiropractic Center",
    "wof:placetype":"venue"
},
  "geometry": {"coordinates":[-75.21819600000001,40.005725],"type":"Point"}
}