{
  "type": "Feature",
  "properties": {
    "addr:full":"320 Market St Kittanning PA 16201",
    "addr:housenumber":"320",
    "addr:postcode":"16201",
    "addr:street":"Market St",
    "iso:country":"US",
    "sg:address":"320 Market St",
    "sg:city":"Kittanning",
    "sg:classifiers":[
        {
            "category":"Government",
            "subcategory":"Office",
            "type":"Public Place"
        }
    ],
    "sg:phone":"+1 724 543 1885",
    "sg:postcode":"16201",
    "sg:province":"PA",
    "sg:tags":[
        "armed",
        "force",
        "recruiting"
    ],
    "wof:name":"US Army Recruiting",
    "wof:placetype":"venue"
},
  "geometry": {"coordinates":[-79.51845899999999,40.814845],"type":"Point"}
}