{
  "type": "Feature",
  "properties": {
    "iso:country":"US",
    "sg:address":"416 7th Ave",
    "sg:city":"Pittsburgh",
    "sg:classifiers":[
        {
            "category":"Cinema",
            "subcategory":"Movie Rental",
            "type":"Entertainment"
        },
        {
            "category":"Retail",
            "subcategory":"Portrait Studio",
            "type":"Services"
        },
        {
            "category":"Bakery",
            "type":"Food & Drink"
        },
        {
            "category":"Shopping",
            "subcategory":"Florist",
            "type":"Retail Goods"
        }
    ],
    "sg:phone":"+1 412 961 0436",
    "sg:postcode":"15219",
    "sg:province":"PA",
    "sg:tags":[
        "photography",
        "video",
        "game",
        "store"
    ],
    "sg:website":"www.gianteagle.com",
    "wof:name":"Giant Eagle Inc",
    "wof:placetype":"venue"
},
  "geometry": {"coordinates":[-79.99630000000001,40.442501],"type":"Point"}
}