{
  "type": "Feature",
  "properties": {
    "iso:country":"US",
    "sg:address":"5 Edgewood Dr",
    "sg:city":"Greenville",
    "sg:classifiers":[
        {
            "category":"Professional",
            "subcategory":"Business Services",
            "type":"Services"
        }
    ],
    "sg:phone":"+1 724 646 5321",
    "sg:postcode":"16125",
    "sg:province":"PA",
    "sg:tags":[
        "paging",
        "answering"
    ],
    "wof:name":"Pymatuning",
    "wof:placetype":"venue"
},
  "geometry": {"coordinates":[-80.41148699999999,41.330204],"type":"Point"}
}