{
  "type": "Feature",
  "properties": {
    "iso:country":"US",
    "sg:address":"4328 Old William Penn Hwy",
    "sg:city":"Monroeville",
    "sg:classifiers":[
        {
            "category":"Social Services",
            "type":"Services"
        }
    ],
    "sg:phone":"+1 412 372 6707",
    "sg:postcode":"15146",
    "sg:province":"PA",
    "sg:tags":[
        "counselor",
        "marriage",
        "family"
    ],
    "wof:name":"Harlee Abromson",
    "wof:placetype":"venue"
},
  "geometry": {"coordinates":[-79.774303,40.442464],"type":"Point"}
}