{
  "type": "Feature",
  "properties": {
    "iso:country":"US",
    "sg:address":"415 S 19th St",
    "sg:city":"Philadelphia",
    "sg:classifiers":[
        {
            "category":"Sports & Exercise",
            "subcategory":"Stables",
            "type":"Entertainment"
        }
    ],
    "sg:phone":"+1 215 546 1065",
    "sg:postcode":"19146",
    "sg:province":"PA",
    "sg:tags":[
        "riding",
        "academy"
    ],
    "wof:name":"Academy Square Assoc",
    "wof:placetype":"venue"
},
  "geometry": {"coordinates":[-75.173187,39.94603],"type":"Point"}
}