{
  "type": "Feature",
  "properties": {
    "addr:full":"139 E Walnut St Lancaster PA 17602",
    "addr:housenumber":"139",
    "addr:postcode":"17602",
    "addr:street":"E Walnut St",
    "iso:country":"US",
    "sg:address":"139 E Walnut St",
    "sg:city":"Lancaster",
    "sg:classifiers":[
        {
            "category":"Manufacturing",
            "subcategory":"Printing",
            "type":"Manufacturing & Wholesale Goods"
        }
    ],
    "sg:phone":"+1 717 299 4427",
    "sg:postcode":"17602",
    "sg:province":"PA",
    "sg:tags":[
        "printer"
    ],
    "wof:name":"Expressive Ink",
    "wof:placetype":"venue"
},
  "geometry": {"coordinates":[-76.302463,40.043182],"type":"Point"}
}