{
  "type": "Feature",
  "properties": {
    "iso:country":"US",
    "sg:address":"5150 Centre Ave",
    "sg:city":"Pittsburgh",
    "sg:classifiers":[
        {
            "category":"Professional",
            "subcategory":"Management & Consulting",
            "type":"Services"
        }
    ],
    "sg:phone":"+1   ",
    "sg:postcode":"15232",
    "sg:province":"PA",
    "wof:name":"Margaret",
    "wof:placetype":"venue"
},
  "geometry": {"coordinates":[-79.942485,40.454599],"type":"Point"}
}