{
  "type": "Feature",
  "properties": {
    "addr:full":"1364 Linden St Bethlehem PA 18018",
    "addr:housenumber":"1364",
    "addr:postcode":"18018",
    "addr:street":"Linden St",
    "iso:country":"US",
    "sg:address":"1364 Linden St",
    "sg:city":"Bethlehem",
    "sg:classifiers":[
        {
            "category":"Retail",
            "subcategory":"Laundry & Dry Cleaning",
            "type":"Services"
        }
    ],
    "sg:phone":"+1 610 867 0600",
    "sg:postcode":"18018",
    "sg:province":"PA",
    "sg:tags":[
        "drycleaning",
        "plant"
    ],
    "wof:name":"Bethlehem Star Cleaners",
    "wof:placetype":"venue"
},
  "geometry": {"coordinates":[-75.369963,40.630813],"type":"Point"}
}