{
  "type": "Feature",
  "properties": {
    "addr:full":"6311 Edmund St Philadelphia PA 19135",
    "addr:housenumber":"6311",
    "addr:postcode":"19135",
    "addr:street":"Edmund St",
    "iso:country":"US",
    "sg:address":"6311 Edmund St",
    "sg:city":"Philadelphia",
    "sg:classifiers":[
        {
            "category":"Building & Trades",
            "subcategory":"Plumbing",
            "type":"Services"
        }
    ],
    "sg:phone":"+1   ",
    "sg:postcode":"19135",
    "sg:province":"PA",
    "sg:tags":[
        "contractor"
    ],
    "wof:name":"Ron S Grzywna Plumbing & Htg",
    "wof:placetype":"venue"
},
  "geometry": {"coordinates":[-75.05056,40.01986],"type":"Point"}
}