{
  "type": "Feature",
  "properties": {
    "addr:full":"454 Piedmont Cir York PA 17404",
    "addr:housenumber":"454",
    "addr:postcode":"17404",
    "addr:street":"Piedmont Cir",
    "iso:country":"US",
    "sg:address":"454 Piedmont Cir",
    "sg:city":"York",
    "sg:classifiers":[
        {
            "category":"Social Services",
            "type":"Services"
        }
    ],
    "sg:phone":"+1   ",
    "sg:postcode":"17404",
    "sg:province":"PA",
    "wof:name":"Nurtured Women",
    "wof:placetype":"venue"
},
  "geometry": {"coordinates":[-76.745228,39.985641],"type":"Point"}
}