{
  "type": "Feature",
  "properties": {
    "iso:country":"US",
    "sg:address":"2631 Egolf Rd",
    "sg:city":"Bedford",
    "sg:classifiers":[
        {
            "category":"Retail",
            "subcategory":"Animal Services",
            "type":"Services"
        }
    ],
    "sg:phone":"+1 814 623 2374",
    "sg:postcode":"15522",
    "sg:province":"PA",
    "sg:tags":[
        "pet",
        "grooming",
        "washing"
    ],
    "wof:name":"Stottlemyer Groom-N-Board",
    "wof:placetype":"venue"
},
  "geometry": {"coordinates":[-78.46969900000001,40.010833],"type":"Point"}
}