{
  "type": "Feature",
  "properties": {
    "addr:full":"2029 Laurel Hill Rd Clarks Summit PA 18411",
    "addr:housenumber":"2029",
    "addr:postcode":"18411",
    "addr:street":"Laurel Hill Rd",
    "iso:country":"US",
    "sg:address":"2029 Laurel Hill Rd",
    "sg:city":"Clarks Summit",
    "sg:classifiers":[
        {
            "category":"Farming",
            "subcategory":"Farm",
            "type":"Manufacturing & Wholesale Goods"
        }
    ],
    "sg:phone":"+1   ",
    "sg:postcode":"18411",
    "sg:province":"PA",
    "sg:tags":[
        "crop",
        "general"
    ],
    "wof:name":"Becks Farm",
    "wof:placetype":"venue"
},
  "geometry": {"coordinates":[-75.748221,41.451528],"type":"Point"}
}