{
  "type": "Feature",
  "properties": {
    "iso:country":"US",
    "sg:address":"150 W End Dr",
    "sg:city":"Hawley",
    "sg:classifiers":[
        {
            "category":"Organizations",
            "subcategory":"Religious Organization",
            "type":"Services"
        }
    ],
    "sg:phone":"+1 570 775 1854",
    "sg:postcode":"18428",
    "sg:province":"PA",
    "sg:tags":[
        "clergy"
    ],
    "wof:name":"Dale Sandstrom",
    "wof:placetype":"venue"
},
  "geometry": {"coordinates":[-75.062561,41.335639],"type":"Point"}
}