{
  "type": "Feature",
  "properties": {
    "iso:country":"US",
    "sg:address":"740 Burmont Rd",
    "sg:city":"Drexel Hill",
    "sg:classifiers":[
        {
            "category":"Wholesale",
            "subcategory":"Machinery & Supplies",
            "type":"Manufacturing & Wholesale Goods"
        }
    ],
    "sg:phone":"+1 610 259 2009",
    "sg:postcode":"19026",
    "sg:province":"PA",
    "sg:tags":[
        "fire",
        "department",
        "equipment"
    ],
    "sg:website":"www.fire-one.com",
    "wof:name":"Fire One",
    "wof:placetype":"venue"
},
  "geometry": {"coordinates":[-75.307635,39.949521],"type":"Point"}
}