{
  "type": "Feature",
  "properties": {
    "iso:country":"US",
    "sg:address":"7370 Rowland Ave",
    "sg:city":"Philadelphia",
    "sg:classifiers":[
        {
            "category":"Real Estate",
            "subcategory":"Real Estate Agent",
            "type":"Services"
        }
    ],
    "sg:phone":"+1 215 338 7686",
    "sg:postcode":"19136",
    "sg:province":"PA",
    "sg:tags":[
        "operator",
        "apartment",
        "broker"
    ],
    "wof:name":"Coldwell Banker",
    "wof:placetype":"venue"
},
  "geometry": {"coordinates":[-75.042115,40.040845],"type":"Point"}
}