{
  "type": "Feature",
  "properties": {
    "iso:country":"US",
    "sg:address":"345 Scarlet Rd",
    "sg:city":"Kennett Square",
    "sg:classifiers":[
        {
            "category":"Shopping",
            "subcategory":"Discount & Variety Stores",
            "type":"Retail Goods"
        }
    ],
    "sg:phone":"+1   ",
    "sg:postcode":"19317",
    "sg:province":"PA",
    "wof:name":"Dollar General 3415",
    "wof:placetype":"venue"
},
  "geometry": {"coordinates":[-75.728471,39.839672],"type":"Point"}
}