{
  "type": "Feature",
  "properties": {
    "iso:country":"US",
    "sg:address":"2430 Springwood Rd",
    "sg:city":"York",
    "sg:classifiers":[
        {
            "category":"Farming",
            "subcategory":"Livestock Farm",
            "type":"Manufacturing & Wholesale Goods"
        }
    ],
    "sg:phone":"+1   ",
    "sg:postcode":"17402",
    "sg:province":"PA",
    "sg:tags":[
        "chicken",
        "egg"
    ],
    "wof:name":"Steward Ebersole",
    "wof:placetype":"venue"
},
  "geometry": {"coordinates":[-76.676902,39.933955],"type":"Point"}
}