{
  "type": "Feature",
  "properties": {
    "iso:country":"US",
    "sg:address":"863 Echo Hill Rd",
    "sg:city":"West Chester",
    "sg:classifiers":[
        {
            "category":"Building & Trades",
            "subcategory":"Electrical",
            "type":"Services"
        }
    ],
    "sg:phone":"+1 610 399 9300",
    "sg:postcode":"19382",
    "sg:province":"PA",
    "sg:tags":[
        "electrician"
    ],
    "wof:name":"Dunn Electric Company",
    "wof:placetype":"venue"
},
  "geometry": {"coordinates":[-75.547203,39.920502],"type":"Point"}
}