{
  "type": "Feature",
  "properties": {
    "addr:full":"6802A Hamilton Blvd Allentown PA 18106",
    "addr:housenumber":"6802a",
    "addr:postcode":"18106",
    "addr:street":"Hamilton Blvd",
    "iso:country":"US",
    "sg:address":"6802A Hamilton Blvd",
    "sg:city":"Allentown",
    "sg:classifiers":[
        {
            "category":"Fast Food",
            "type":"Food & Drink"
        },
        {
            "category":"Restaurant",
            "type":"Food & Drink"
        }
    ],
    "sg:phone":"+1 610 481 0436",
    "sg:postcode":"18106",
    "sg:province":"PA",
    "sg:tags":[
        "style",
        "hamburger",
        "family",
        "dog",
        "hot",
        "take",
        "american"
    ],
    "sg:website":"http://www.redrobin.com/",
    "wof:name":"Red Robin Gourmet Burgers",
    "wof:placetype":"venue"
},
  "geometry": {"coordinates":[-75.55122,40.567348],"type":"Point"}
}