{
  "type": "Feature",
  "properties": {
    "iso:country":"US",
    "sg:address":"102 Montgomery Ave",
    "sg:city":"Oaks",
    "sg:classifiers":[
        {
            "category":"Manufacturing",
            "subcategory":"Building Materials",
            "type":"Manufacturing & Wholesale Goods"
        }
    ],
    "sg:phone":"+1 610 666 0984",
    "sg:postcode":"19456",
    "sg:province":"PA",
    "sg:tags":[
        "cabinet"
    ],
    "sg:website":"www.innovativecabinetry.com",
    "wof:name":"Innovative Cabinetry",
    "wof:placetype":"venue"
},
  "geometry": {"coordinates":[-75.459417,40.130151],"type":"Point"}
}