{
  "type": "Feature",
  "properties": {
    "iso:country":"US",
    "sg:address":"138 S Grims Mill Rd",
    "sg:city":"Boyertown",
    "sg:classifiers":[
        {
            "category":"Professional",
            "type":"Services"
        }
    ],
    "sg:phone":"+1 610 367 9676",
    "sg:postcode":"19512",
    "sg:province":"PA",
    "sg:tags":[
        "establishment"
    ],
    "wof:name":"Sweet-Lea Enterprises",
    "wof:placetype":"venue"
},
  "geometry": {"coordinates":[-75.670614,40.356855],"type":"Point"}
}