{
  "type": "Feature",
  "properties": {
    "addr:full":"2614 Brownsville Rd Pittsburgh PA 15227",
    "addr:housenumber":"2614",
    "addr:postcode":"15227",
    "addr:street":"Brownsville Rd",
    "iso:country":"US",
    "sg:address":"2614 Brownsville Rd",
    "sg:city":"Pittsburgh",
    "sg:classifiers":[
        {
            "category":"Food & Beverages",
            "subcategory":"Specialty",
            "type":"Retail Goods"
        }
    ],
    "sg:phone":"+1   ",
    "sg:postcode":"15227",
    "sg:province":"PA",
    "wof:name":"Carrick Poultry",
    "wof:placetype":"venue"
},
  "geometry": {"coordinates":[-79.978031,40.384605],"type":"Point"}
}