{
  "type": "Feature",
  "properties": {
    "iso:country":"US",
    "sg:address":"901 Mifflin St",
    "sg:city":"Huntingdon",
    "sg:classifiers":[
        {
            "category":"Shopping",
            "subcategory":"Jewelry",
            "type":"Retail Goods"
        }
    ],
    "sg:phone":"+1   ",
    "sg:postcode":"16652",
    "sg:province":"PA",
    "sg:tags":[
        "instrument",
        "used",
        "musical"
    ],
    "wof:name":"Swartz Jewelery Co",
    "wof:placetype":"venue"
},
  "geometry": {"coordinates":[-78.01621299999999,40.489892],"type":"Point"}
}