{
  "type": "Feature",
  "properties": {
    "addr:full":"3895 Adler Pl Bethlehem PA 18017",
    "addr:housenumber":"3895",
    "addr:postcode":"18017",
    "addr:street":"Adler Pl",
    "iso:country":"US",
    "sg:address":"3895 Adler Pl",
    "sg:city":"Bethlehem",
    "sg:classifiers":[
        {
            "category":"Professional",
            "subcategory":"Lawyer & Legal Services",
            "type":"Services"
        }
    ],
    "sg:phone":"+1 215 868 9968",
    "sg:postcode":"18017",
    "sg:province":"PA",
    "wof:name":"Feege Edward H Attorney",
    "wof:placetype":"venue"
},
  "geometry": {"coordinates":[-75.382513,40.66906],"type":"Point"}
}