{
  "type": "Feature",
  "properties": {
    "iso:country":"US",
    "sg:address":"3523 Cliff St",
    "sg:city":"Finleyville",
    "sg:classifiers":[
        {
            "category":"Wholesale",
            "subcategory":"Non-durable Goods",
            "type":"Manufacturing & Wholesale Goods"
        },
        {
            "category":"Home & Garden",
            "subcategory":"Hardware",
            "type":"Retail Goods"
        }
    ],
    "sg:phone":"+1 417 293 0504",
    "sg:postcode":"15332",
    "sg:province":"PA",
    "sg:tags":[
        "janitor",
        "equipment",
        "manufacturer",
        "supplies-wholesale",
        "supply"
    ],
    "wof:name":"Sca Enterprises Inc",
    "wof:placetype":"venue"
},
  "geometry": {"coordinates":[-80.004762,40.251629],"type":"Point"}
}