{
  "type": "Feature",
  "properties": {
    "iso:country":"US",
    "sg:address":"9825 Perry Hwy",
    "sg:city":"Wexford",
    "sg:classifiers":[
        {
            "category":"Professional",
            "subcategory":"Business Services",
            "type":"Services"
        }
    ],
    "sg:phone":"+1 412 369 5990",
    "sg:postcode":"15090",
    "sg:province":"PA",
    "sg:tags":[
        "information",
        "referral"
    ],
    "wof:name":"Information Resource Tech",
    "wof:placetype":"venue"
},
  "geometry": {"coordinates":[-80.047822,40.592398],"type":"Point"}
}