{
  "type": "Feature",
  "properties": {
    "iso:country":"US",
    "sg:address":"1266 Manheim Pike",
    "sg:city":"Lancaster",
    "sg:classifiers":[
        {
            "category":"Manufacturing",
            "subcategory":"Tools & Machinery",
            "type":"Manufacturing & Wholesale Goods"
        }
    ],
    "sg:phone":"+1 717 393 5678",
    "sg:postcode":"17601",
    "sg:province":"PA",
    "sg:tags":[
        "lighting",
        "fixture"
    ],
    "wof:name":"Brontech",
    "wof:placetype":"venue"
},
  "geometry": {"coordinates":[-76.322351,40.061977],"type":"Point"}
}