{
  "type": "Feature",
  "properties": {
    "addr:full":"2772 Leechburg Rd New Kensington PA 15068",
    "addr:housenumber":"2772",
    "addr:postcode":"15068",
    "addr:street":"Leechburg Rd",
    "iso:country":"US",
    "sg:address":"2772 Leechburg Rd",
    "sg:city":"New Kensington",
    "sg:classifiers":[
        {
            "category":"Health Services",
            "subcategory":"Chiropractor",
            "type":"Services"
        }
    ],
    "sg:phone":"+1   ",
    "sg:postcode":"15068",
    "sg:province":"PA",
    "wof:name":"Skalski Ronald E DC",
    "wof:placetype":"venue"
},
  "geometry": {"coordinates":[-79.73492899999999,40.590869],"type":"Point"}
}