{
  "type": "Feature",
  "properties": {
    "iso:country":"US",
    "sg:address":"2555 Washington Rd Ste 630",
    "sg:city":"Pittsburgh",
    "sg:classifiers":[
        {
            "category":"Professional",
            "subcategory":"Lawyer & Legal Services",
            "type":"Services"
        }
    ],
    "sg:phone":"+1 412 831 7211",
    "sg:postcode":"15241",
    "sg:province":"PA",
    "wof:name":"Dudash Mark J Attorney",
    "wof:placetype":"venue"
},
  "geometry": {"coordinates":[-80.08869900000001,40.3167],"type":"Point"}
}