{
  "type": "Feature",
  "properties": {
    "iso:country":"US",
    "sg:address":"101 Water St",
    "sg:city":"Everett",
    "sg:classifiers":[
        {
            "category":"Personal",
            "subcategory":"Beauty Salon",
            "type":"Services"
        }
    ],
    "sg:phone":"+1 814 652 5385",
    "sg:postcode":"15537",
    "sg:province":"PA",
    "wof:name":"Water Street Hair Factory",
    "wof:placetype":"venue"
},
  "geometry": {"coordinates":[-78.372711,40.013771],"type":"Point"}
}