{
  "type": "Feature",
  "properties": {
    "iso:country":"US",
    "sg:address":"810 River Ave Ste 120",
    "sg:city":"Pittsburgh",
    "sg:classifiers":[
        {
            "category":"Personal",
            "subcategory":"Barber",
            "type":"Services"
        }
    ],
    "sg:phone":"+1 412 231 8015",
    "sg:postcode":"15212",
    "sg:province":"PA",
    "sg:website":"www.supercuts.com",
    "wof:name":"Supercuts Offices",
    "wof:placetype":"venue"
},
  "geometry": {"coordinates":[-79.995102,40.450199],"type":"Point"}
}