{
  "type": "Feature",
  "properties": {
    "addr:full":"3051 Souderton Pike Hatfield PA 19440",
    "addr:housenumber":"3051",
    "addr:postcode":"19440",
    "addr:street":"Souderton Pike",
    "iso:country":"US",
    "sg:address":"3051 Souderton Pike",
    "sg:city":"Hatfield",
    "sg:classifiers":[
        {
            "category":"Wholesale",
            "subcategory":"Metals & Minerals",
            "type":"Manufacturing & Wholesale Goods"
        }
    ],
    "sg:phone":"+1   ",
    "sg:postcode":"19440",
    "sg:province":"PA",
    "sg:tags":[
        "rope",
        "synthetic",
        "wire",
        "chain",
        "sling"
    ],
    "wof:name":"Nelson Wire Rope Corp",
    "wof:placetype":"venue"
},
  "geometry": {"coordinates":[-75.310354,40.295922],"type":"Point"}
}