{
  "type": "Feature",
  "properties": {
    "iso:country":"US",
    "sg:address":"4051 Buffalo Rd",
    "sg:city":"Erie",
    "sg:classifiers":[
        {
            "category":"Personal",
            "subcategory":"Beauty Salon",
            "type":"Services"
        }
    ],
    "sg:phone":"+1 814 898 8804",
    "sg:postcode":"16510",
    "sg:province":"PA",
    "sg:tags":[
        "shop",
        "manicuring"
    ],
    "wof:name":"Foxy Nails",
    "wof:placetype":"venue"
},
  "geometry": {"coordinates":[-80.004447,42.145389],"type":"Point"}
}