{
  "type": "Feature",
  "properties": {
    "iso:country":"US",
    "sg:address":"958 Mercer Rd",
    "sg:city":"Beaver Falls",
    "sg:classifiers":[
        {
            "category":"Building & Trades",
            "subcategory":"Construction",
            "type":"Services"
        }
    ],
    "sg:phone":"+1   ",
    "sg:postcode":"15010",
    "sg:province":"PA",
    "sg:tags":[
        "fire",
        "damage",
        "water",
        "restoration",
        "cleaning",
        "carpet"
    ],
    "wof:name":"Disaster Pro",
    "wof:placetype":"venue"
},
  "geometry": {"coordinates":[-80.28995,40.801267],"type":"Point"}
}