{
  "type": "Feature",
  "properties": {
    "addr:full":"2576 Evans City Rd Harmony PA 16037",
    "addr:housenumber":"2576",
    "addr:postcode":"16037",
    "addr:street":"Evans City Rd",
    "iso:country":"US",
    "sg:address":"2576 Evans City Rd",
    "sg:city":"Harmony",
    "sg:phone":"+1   ",
    "sg:postcode":"16037",
    "sg:province":"PA",
    "sg:tags":[
        "oil",
        "gasoline"
    ],
    "wof:name":"Mon Valley Petroleum Inc",
    "wof:placetype":"venue"
},
  "geometry": {"coordinates":[-80.120935,40.802243],"type":"Point"}
}