{
  "type": "Feature",
  "properties": {
    "iso:country":"US",
    "sg:address":"215 Kelso Cir",
    "sg:city":"Collegeville",
    "sg:classifiers":[
        {
            "category":"Real Estate",
            "subcategory":"Real Estate Agent",
            "type":"Services"
        }
    ],
    "sg:phone":"+1 610 831 1977",
    "sg:postcode":"19426",
    "sg:province":"PA",
    "sg:tags":[
        "inspection"
    ],
    "wof:name":"Buyers Alliance Bldg Inspctn",
    "wof:placetype":"venue"
},
  "geometry": {"coordinates":[-75.48770399999999,40.196936],"type":"Point"}
}