{
  "type": "Feature",
  "properties": {
    "iso:country":"US",
    "sg:address":"2 E Main St",
    "sg:city":"Macungie",
    "sg:classifiers":[
        {
            "category":"Retail",
            "subcategory":"Animal Services",
            "type":"Services"
        }
    ],
    "sg:phone":"+1 610 966 3222",
    "sg:postcode":"18062",
    "sg:province":"PA",
    "sg:tags":[
        "pet",
        "grooming",
        "washing"
    ],
    "wof:name":"Doggie Do's Grooming",
    "wof:placetype":"venue"
},
  "geometry": {"coordinates":[-75.555627,40.515755],"type":"Point"}
}