{
  "type": "Feature",
  "properties": {
    "iso:country":"US",
    "sg:address":"2625 B St",
    "sg:city":"Philadelphia",
    "sg:classifiers":[
        {
            "category":"Professional",
            "subcategory":"Employment Agencies",
            "type":"Services"
        }
    ],
    "sg:phone":"+1 215 423 7786",
    "sg:postcode":"19125",
    "sg:province":"PA",
    "sg:tags":[
        "help",
        "contractor"
    ],
    "wof:name":"Futura Inc",
    "wof:placetype":"venue"
},
  "geometry": {"coordinates":[-75.12698399999999,39.990199],"type":"Point"}
}