{
  "type": "Feature",
  "properties": {
    "addr:full":"750 N Wales Rd North Wales PA 19446",
    "addr:housenumber":"750",
    "addr:postcode":"19446",
    "addr:street":"N Wales Rd",
    "iso:country":"US",
    "sg:address":"750 N Wales Rd",
    "sg:city":"North Wales",
    "sg:classifiers":[
        {
            "category":"Restaurant",
            "type":"Food & Drink"
        }
    ],
    "sg:phone":"+1 215 393 9100",
    "sg:postcode":"19446",
    "sg:province":"PA",
    "wof:name":"Houlihan's",
    "wof:placetype":"venue"
},
  "geometry": {"coordinates":[-75.288954,40.198943],"type":"Point"}
}