{
  "type": "Feature",
  "properties": {
    "addr:full":"550 State Rd Bensalem PA 19020",
    "addr:housenumber":"550",
    "addr:postcode":"19020",
    "addr:street":"State Rd",
    "iso:country":"US",
    "sg:address":"550 State Rd",
    "sg:city":"Bensalem",
    "sg:classifiers":[
        {
            "category":"Retail",
            "subcategory":"Repair Shop",
            "type":"Services"
        },
        {
            "category":"Building & Trades",
            "subcategory":"Construction",
            "type":"Services"
        }
    ],
    "sg:phone":"+1 215 633 7429",
    "sg:postcode":"19020",
    "sg:province":"PA",
    "sg:tags":[
        "major",
        "refinishing",
        "handyman",
        "appliance",
        "dryer",
        "small",
        "washer"
    ],
    "sg:website":"http://www.sickappliance.com",
    "wof:name":"Appliance Doctor",
    "wof:placetype":"venue"
},
  "geometry": {"coordinates":[-74.976692,40.058868],"type":"Point"}
}