{
  "type": "Feature",
  "properties": {
    "iso:country":"US",
    "sg:address":"515 Chestnut St",
    "sg:city":"Emmaus",
    "sg:classifiers":[
        {
            "category":"Personal",
            "subcategory":"Tattoo Parlor",
            "type":"Services"
        },
        {
            "category":"Personal",
            "subcategory":"Piercing",
            "type":"Services"
        }
    ],
    "sg:phone":"+1 610 965 9030",
    "sg:postcode":"18049",
    "sg:province":"PA",
    "sg:website":"www.mindseyetat2.com",
    "wof:name":"Mind's Eye Tattoo & Body Piercing",
    "wof:placetype":"venue"
},
  "geometry": {"coordinates":[-75.493996,40.534294],"type":"Point"}
}