{
  "type": "Feature",
  "properties": {
    "addr:full":"3555 Old Windy Bush Rd New Hope PA 18938",
    "addr:housenumber":"3555",
    "addr:postcode":"18938",
    "addr:street":"Old Windy Bush Rd New",
    "iso:country":"US",
    "sg:address":"3555 Old Windy Bush Rd",
    "sg:city":"New Hope",
    "sg:classifiers":[
        {
            "category":"Banks & Credit Unions",
            "subcategory":"Bank",
            "type":"Services"
        }
    ],
    "sg:phone":"+1   ",
    "sg:postcode":"18938",
    "sg:province":"PA",
    "sg:tags":[
        "mortgage"
    ],
    "wof:name":"Dorrance Mortgage Corp",
    "wof:placetype":"venue"
},
  "geometry": {"coordinates":[-74.962135,40.337132],"type":"Point"}
}