{
  "type": "Feature",
  "properties": {
    "addr:full":"217 Post Rd Somerset PA 15501",
    "addr:housenumber":"217",
    "addr:postcode":"15501",
    "addr:street":"Post Rd",
    "iso:country":"US",
    "sg:address":"217 Post Rd",
    "sg:city":"Somerset",
    "sg:classifiers":[
        {
            "category":"Retail",
            "subcategory":"Animal Services",
            "type":"Services"
        }
    ],
    "sg:phone":"+1 814 443 1510",
    "sg:postcode":"15501",
    "sg:province":"PA",
    "wof:name":"Double K Stables",
    "wof:placetype":"venue"
},
  "geometry": {"coordinates":[-79.177277,40.031611],"type":"Point"}
}