{
  "type": "Feature",
  "properties": {
    "iso:country":"US",
    "sg:address":"107 N Chester Rd",
    "sg:city":"West Chester",
    "sg:classifiers":[
        {
            "category":"Professional",
            "subcategory":"Advertising",
            "type":"Services"
        }
    ],
    "sg:phone":"+1 610 280 0434",
    "sg:postcode":"19380",
    "sg:province":"PA",
    "sg:tags":[
        "counselor"
    ],
    "wof:name":"Associates LLC",
    "wof:placetype":"venue"
},
  "geometry": {"coordinates":[-75.527446,39.969426],"type":"Point"}
}