{
  "type": "Feature",
  "properties": {
    "iso:country":"US",
    "sg:address":"12041 Bustleton Ave",
    "sg:city":"Philadelphia",
    "sg:classifiers":[
        {
            "category":"Shopping",
            "type":"Retail Goods"
        }
    ],
    "sg:phone":"+1 215 464 3424",
    "sg:postcode":"19116",
    "sg:province":"PA",
    "sg:tags":[
        "monument"
    ],
    "wof:name":"All American Monuments",
    "wof:placetype":"venue"
},
  "geometry": {"coordinates":[-75.015872,40.122607],"type":"Point"}
}