{
  "type": "Feature",
  "properties": {
    "iso:country":"US",
    "sg:address":"1105 Dogwood Ct",
    "sg:city":"Pottstown",
    "sg:classifiers":[
        {
            "category":"Autos & Motor Vehicles",
            "subcategory":"Automobile Sales",
            "type":"Retail Goods"
        }
    ],
    "sg:phone":"+1   ",
    "sg:postcode":"19465",
    "sg:province":"PA",
    "sg:tags":[
        "car",
        "used"
    ],
    "wof:name":"Morris Motor Co",
    "wof:placetype":"venue"
},
  "geometry": {"coordinates":[-75.67553599999999,40.225017],"type":"Point"}
}