{
  "type": "Feature",
  "properties": {
    "addr:full":"568 Hollander Rd New Holland PA 17557",
    "addr:housenumber":"568",
    "addr:postcode":"17557",
    "addr:street":"Hollander Rd",
    "iso:country":"US",
    "sg:address":"568 Hollander Rd",
    "sg:city":"New Holland",
    "sg:phone":"+1   ",
    "sg:postcode":"17557",
    "sg:province":"PA",
    "sg:tags":[
        "farm",
        "corn"
    ],
    "wof:name":"David Newswanger",
    "wof:placetype":"venue"
},
  "geometry": {"coordinates":[-76.09926299999999,40.083808],"type":"Point"}
}