{
  "type": "Feature",
  "properties": {
    "iso:country":"US",
    "sg:address":"880 Church St",
    "sg:city":"Indiana",
    "sg:classifiers":[
        {
            "category":"Health Services",
            "subcategory":"Doctor",
            "type":"Services"
        }
    ],
    "sg:phone":"+1 724 463 7270",
    "sg:postcode":"15701",
    "sg:province":"PA",
    "sg:tags":[
        "dentist"
    ],
    "wof:name":"M Frederick Dills Jr DDS",
    "wof:placetype":"venue"
},
  "geometry": {"coordinates":[-79.15540900000001,40.62156],"type":"Point"}
}