{
  "type": "Feature",
  "properties": {
    "iso:country":"US",
    "sg:address":"1077 W Chester Rd",
    "sg:city":"West Chester",
    "sg:classifiers":[
        {
            "category":"Freight",
            "type":"Transportation"
        }
    ],
    "sg:phone":"+1   ",
    "sg:postcode":"19382",
    "sg:province":"PA",
    "sg:tags":[
        "special"
    ],
    "wof:name":"Rorke Data",
    "wof:placetype":"venue"
},
  "geometry": {"coordinates":[-75.546294,39.911122],"type":"Point"}
}