{
  "type": "Feature",
  "properties": {
    "addr:full":"310 Grant St Ste 1109 Pittsburgh PA 15219",
    "addr:housenumber":"310",
    "addr:postcode":"15219",
    "addr:street":"Grant St Ste 1109",
    "iso:country":"US",
    "sg:address":"310 Grant St Ste 1109",
    "sg:city":"Pittsburgh",
    "sg:classifiers":[
        {
            "category":"Professional",
            "subcategory":"Lawyer & Legal Services",
            "type":"Services"
        }
    ],
    "sg:phone":"+1 412 255 6500",
    "sg:postcode":"15219",
    "sg:province":"PA",
    "sg:tags":[
        "attorney",
        "business",
        "planning",
        "real estate",
        "law"
    ],
    "wof:name":"Brandt Milnes & Rea",
    "wof:placetype":"venue"
},
  "geometry": {"coordinates":[-79.998031,40.437562],"type":"Point"}
}