{
  "type": "Feature",
  "properties": {
    "addr:full":"6250 Passyunk Ave Philadelphia PA 19153",
    "addr:postcode":"6250;19153",
    "addr:street":"Passyunk Ave",
    "iso:country":"US",
    "sg:address":"6250 Passyunk Ave",
    "sg:city":"Philadelphia",
    "sg:classifiers":[
        {
            "category":"Autos & Motor Vehicles",
            "subcategory":"Auto Supplies",
            "type":"Retail Goods"
        },
        {
            "category":"Manufacturing",
            "subcategory":"Glass & Minerals",
            "type":"Manufacturing & Wholesale Goods"
        },
        {
            "category":"Retail",
            "subcategory":"Auto Repair",
            "type":"Services"
        }
    ],
    "sg:phone":"+1 215 729 5000",
    "sg:postcode":"19153",
    "sg:province":"PA",
    "sg:tags":[
        "plate",
        "automobile",
        "glass-auto",
        "window",
        "part",
        "windshield"
    ],
    "sg:website":"http://www.ajaxautoglass.com",
    "wof:name":"Ajax Auto Glass",
    "wof:placetype":"venue"
},
  "geometry": {"coordinates":[-75.21379899999999,39.917348],"type":"Point"}
}