{
  "type": "Feature",
  "properties": {
    "addr:full":"2049 N 4th St Harrisburg PA 17102",
    "addr:housenumber":"2049",
    "addr:postcode":"17102",
    "addr:street":"N 4Th St",
    "iso:country":"US",
    "sg:address":"2049 N 4th St",
    "sg:city":"Harrisburg",
    "sg:classifiers":[
        {
            "category":"Organizations",
            "subcategory":"Religious Organization",
            "type":"Services"
        }
    ],
    "sg:phone":"+1 717 233 3503",
    "sg:postcode":"17102",
    "sg:province":"PA",
    "sg:tags":[
        "church"
    ],
    "wof:name":"Trinity Church Of God",
    "wof:placetype":"venue"
},
  "geometry": {"coordinates":[-76.893835,40.279366],"type":"Point"}
}