{
  "type": "Feature",
  "properties": {
    "iso:country":"US",
    "sg:address":"2547 Washington Rd",
    "sg:city":"Pittsburgh",
    "sg:classifiers":[
        {
            "category":"Health Services",
            "subcategory":"Clinic",
            "type":"Services"
        }
    ],
    "sg:phone":"+1 412 341 2200",
    "sg:postcode":"15241",
    "sg:province":"PA",
    "sg:tags":[
        "home"
    ],
    "wof:name":"Ambassador Nursing Care",
    "wof:placetype":"venue"
},
  "geometry": {"coordinates":[-80.088244,40.31792],"type":"Point"}
}