{
  "type": "Feature",
  "properties": {
    "addr:full":"1530 Commerce Dr Lancaster PA 17601",
    "addr:housenumber":"1530",
    "addr:postcode":"17601",
    "addr:street":"Commerce Dr",
    "iso:country":"US",
    "sg:address":"1530 Commerce Dr",
    "sg:city":"Lancaster",
    "sg:classifiers":[
        {
            "category":"Travel",
            "subcategory":"Travel Agent",
            "type":"Entertainment"
        }
    ],
    "sg:phone":"+1 717 560 7777",
    "sg:postcode":"17601",
    "sg:province":"PA",
    "sg:tags":[
        "agency",
        "bureau"
    ],
    "wof:name":"Lancaster Travel Carlson Wgnlt",
    "wof:placetype":"venue"
},
  "geometry": {"coordinates":[-76.341768,40.079392],"type":"Point"}
}