{
  "type": "Feature",
  "properties": {
    "iso:country":"US",
    "sg:address":"1320 Manheim Pike",
    "sg:city":"Lancaster",
    "sg:phone":"+1 800 394 3064",
    "sg:postcode":"17601",
    "sg:province":"PA",
    "sg:website":"http://www.filitrac.com/Click.aspx?tid=BDEDC5D5EF8BAE3541B5938870DA3DDECE60F60FEE115906&FiliAff=15016&sid=99202&utm_source=YellowPages&utm_medium=ppc&utm_campaign=national&utm_term=17601",
    "wof:name":"Essis & Sons Carpet One Floor & Home",
    "wof:placetype":"venue"
},
  "geometry": {"coordinates":[-76.326864,40.065763],"type":"Point"}
}