{
  "type": "Feature",
  "properties": {
    "iso:country":"US",
    "sg:address":"162 S 2nd Ave",
    "sg:city":"Clarion",
    "sg:classifiers":[
        {
            "category":"Government",
            "subcategory":"Office",
            "type":"Public Place"
        }
    ],
    "sg:phone":"+1   ",
    "sg:postcode":"16214",
    "sg:province":"PA",
    "sg:tags":[
        "job",
        "center"
    ],
    "wof:name":"Clarion Job Center",
    "wof:placetype":"venue"
},
  "geometry": {"coordinates":[-79.39355399999999,41.213007],"type":"Point"}
}