{
  "type": "Feature",
  "properties": {
    "iso:country":"US",
    "sg:address":"38 Timber Knoll Dr",
    "sg:city":"Washington Crsng",
    "sg:classifiers":[
        {
            "category":"Retail",
            "subcategory":"Portrait Studio",
            "type":"Services"
        }
    ],
    "sg:phone":"+1 215 493 6792",
    "sg:postcode":"18977",
    "sg:province":"PA",
    "sg:tags":[
        "photographer"
    ],
    "sg:website":"www.casualcandids.com",
    "wof:name":"Casual Candids",
    "wof:placetype":"venue"
},
  "geometry": {"coordinates":[-74.898815,40.299598],"type":"Point"}
}