{
  "type": "Feature",
  "properties": {
    "addr:full":"3 N 25th St Harrisburg PA 17103",
    "addr:housenumber":"3",
    "addr:postcode":"17103",
    "addr:street":"N 25Th St",
    "iso:country":"US",
    "sg:address":"3 N 25th St",
    "sg:city":"Harrisburg",
    "sg:classifiers":[
        {
            "category":"Organizations",
            "subcategory":"Religious Organization",
            "type":"Services"
        }
    ],
    "sg:phone":"+1   ",
    "sg:postcode":"17103",
    "sg:province":"PA",
    "wof:name":"Trnty Untd Methdst Chrch",
    "wof:placetype":"venue"
},
  "geometry": {"coordinates":[-76.851158,40.279013],"type":"Point"}
}