{
  "type": "Feature",
  "properties": {
    "addr:full":"4 Centre Ave Leesport PA 19533",
    "addr:housenumber":"4",
    "addr:postcode":"19533",
    "addr:street":"Centre Ave",
    "iso:country":"US",
    "sg:address":"4 Centre Ave",
    "sg:city":"Leesport",
    "sg:classifiers":[
        {
            "category":"Food & Beverages",
            "subcategory":"Groceries & Convenience Stores",
            "type":"Retail Goods"
        }
    ],
    "sg:phone":"+1 610 926 1540",
    "sg:postcode":"19533",
    "sg:province":"PA",
    "wof:name":"Turkey Hill Minit Market",
    "wof:placetype":"venue"
},
  "geometry": {"coordinates":[-75.965861,40.449551],"type":"Point"}
}