{
  "type": "Feature",
  "properties": {
    "iso:country":"US",
    "sg:address":"3800 Greenacres Rd",
    "sg:city":"Philadelphia",
    "sg:classifiers":[
        {
            "category":"Professional",
            "subcategory":"Employment Agencies",
            "type":"Services"
        }
    ],
    "sg:phone":"+1 215 637 1775",
    "sg:postcode":"19154",
    "sg:province":"PA",
    "sg:tags":[
        "modeling"
    ],
    "wof:name":"Dolores Deck Management",
    "wof:placetype":"venue"
},
  "geometry": {"coordinates":[-74.983301,40.074501],"type":"Point"}
}