{
  "type": "Feature",
  "properties": {
    "addr:full":"501 N 6th St Allentown PA 18102",
    "addr:housenumber":"501",
    "addr:postcode":"18102",
    "addr:street":"N 6Th St",
    "iso:country":"US",
    "sg:address":"501 N 6th St",
    "sg:city":"Allentown",
    "sg:classifiers":[
        {
            "category":"Food & Beverages",
            "subcategory":"Groceries & Convenience Stores",
            "type":"Retail Goods"
        }
    ],
    "sg:phone":"+1 610 433 0591",
    "sg:postcode":"18102",
    "sg:province":"PA",
    "wof:name":"Kim's Market",
    "wof:placetype":"venue"
},
  "geometry": {"coordinates":[-75.473198,40.609699],"type":"Point"}
}