{
  "type": "Feature",
  "properties": {
    "iso:country":"US",
    "sg:address":"1531 S Jefferson St",
    "sg:city":"Allentown",
    "sg:classifiers":[
        {
            "category":"Home & Garden",
            "subcategory":"Building Materials",
            "type":"Retail Goods"
        },
        {
            "category":"Building & Trades",
            "subcategory":"Construction",
            "type":"Services"
        }
    ],
    "sg:phone":"+1 610 797 6262",
    "sg:postcode":"18103",
    "sg:province":"PA",
    "sg:tags":[
        "concrete",
        "staining",
        "contractor"
    ],
    "wof:name":"Nick Coringrato",
    "wof:placetype":"venue"
},
  "geometry": {"coordinates":[-75.48076500000001,40.580038],"type":"Point"}
}