{
  "type": "Feature",
  "properties": {
    "iso:country":"US",
    "sg:address":"431 W Roosevelt Blvd",
    "sg:city":"Philadelphia",
    "sg:classifiers":[
        {
            "category":"Health Services",
            "subcategory":"Doctor",
            "type":"Services"
        }
    ],
    "sg:phone":"+1 215 455 3444",
    "sg:postcode":"19120",
    "sg:province":"PA",
    "wof:name":"Vangore Surya MD",
    "wof:placetype":"venue"
},
  "geometry": {"coordinates":[-75.131699,40.024399],"type":"Point"}
}