{
  "type": "Feature",
  "properties": {
    "iso:country":"US",
    "sg:address":"3993 Huntingdon Pike",
    "sg:city":"Huntingdon Vly",
    "sg:classifiers":[
        {
            "category":"Professional",
            "subcategory":"Accounting & Tax Preparation",
            "type":"Services"
        }
    ],
    "sg:phone":"+1 215 947 7800",
    "sg:postcode":"19006",
    "sg:province":"PA",
    "sg:tags":[
        "accountant"
    ],
    "wof:name":"Leonard Schwartz & Co",
    "wof:placetype":"venue"
},
  "geometry": {"coordinates":[-75.049111,40.157579],"type":"Point"}
}