{
  "type": "Feature",
  "properties": {
    "addr:full":"1414 Prospect Ave Scranton PA 18505",
    "addr:housenumber":"1414",
    "addr:postcode":"18505",
    "addr:street":"Prospect Ave",
    "iso:country":"US",
    "sg:address":"1414 Prospect Ave",
    "sg:city":"Scranton",
    "sg:classifiers":[
        {
            "category":"Bars & Pubs",
            "type":"Food & Drink"
        }
    ],
    "sg:phone":"+1   ",
    "sg:postcode":"18505",
    "sg:province":"PA",
    "sg:tags":[
        "drinking"
    ],
    "wof:name":"Waldorf Park GAf",
    "wof:placetype":"venue"
},
  "geometry": {"coordinates":[-75.67169699999999,41.390703],"type":"Point"}
}