{
  "type": "Feature",
  "properties": {
    "iso:country":"US",
    "sg:address":"18276 Conneaut Lake Rd",
    "sg:city":"Meadville",
    "sg:classifiers":[
        {
            "category":"Bakery",
            "type":"Food & Drink"
        }
    ],
    "sg:menulink":"http://www.allmenus.com/pa/vernon/102231-perkins-restaurant--bakery/menu/",
    "sg:phone":"+1 814 336 6000",
    "sg:postcode":"16335",
    "sg:province":"PA",
    "sg:tags":[
        "sandwich",
        "salad",
        "soup",
        "american",
        "pastry",
        "wrap"
    ],
    "wof:name":"Perkins Restaurant & Bakery",
    "wof:placetype":"venue"
},
  "geometry": {"coordinates":[-80.171542,41.621805],"type":"Point"}
}