{
  "type": "Feature",
  "properties": {
    "iso:country":"US",
    "sg:address":"130 N 1st St",
    "sg:city":"Lehighton",
    "sg:classifiers":[
        {
            "category":"Shopping",
            "type":"Retail Goods"
        }
    ],
    "sg:phone":"+1 610 377 6293",
    "sg:postcode":"18235",
    "sg:province":"PA",
    "sg:tags":[
        "hearing",
        "equipment",
        "supply",
        "merchandise",
        "impaired"
    ],
    "wof:name":"Beltone Hearing Aid Center",
    "wof:placetype":"venue"
},
  "geometry": {"coordinates":[-75.708932,40.835189],"type":"Point"}
}