{
  "type": "Feature",
  "properties": {
    "addr:full":"529 Lauschtown Rd Denver PA 17517",
    "addr:housenumber":"529",
    "addr:postcode":"17517",
    "addr:street":"Lauschtown Rd",
    "iso:country":"US",
    "sg:address":"529 Lauschtown Rd",
    "sg:city":"Denver",
    "sg:classifiers":[
        {
            "category":"Place Of Worship",
            "subcategory":"Church",
            "type":"Public Place"
        },
        {
            "category":"Place Of Worship",
            "type":"Public Place"
        }
    ],
    "sg:phone":"+1 717 445 0838",
    "sg:postcode":"17517",
    "sg:province":"PA",
    "sg:tags":[
        "churches-interdenominational",
        "denomination",
        "churches-various",
        "churches-non-denominational"
    ],
    "wof:name":"Cornerstone Bible Church",
    "wof:placetype":"venue"
},
  "geometry": {"coordinates":[-76.052757,40.211696],"type":"Point"}
}