{
  "type": "Feature",
  "properties": {
    "iso:country":"US",
    "sg:address":"419 Spruce St",
    "sg:city":"Scranton",
    "sg:classifiers":[
        {
            "category":"Banks & Credit Unions",
            "subcategory":"Bank",
            "type":"Services"
        }
    ],
    "sg:phone":"+1 570 343 6572",
    "sg:postcode":"18503",
    "sg:province":"PA",
    "sg:tags":[
        "national",
        "commercial"
    ],
    "sg:website":"www.fncb.com",
    "wof:name":"First National Community Bank",
    "wof:placetype":"venue"
},
  "geometry": {"coordinates":[-75.66408800000001,41.408314],"type":"Point"}
}