{
  "type": "Feature",
  "properties": {
    "iso:country":"US",
    "sg:address":"113 S State St",
    "sg:city":"Ephrata",
    "sg:classifiers":[
        {
            "category":"Personal",
            "subcategory":"Beauty Salon",
            "type":"Services"
        }
    ],
    "sg:phone":"+1 717 733 0101",
    "sg:postcode":"17522",
    "sg:province":"PA",
    "wof:name":"Hats Off Hair Care",
    "wof:placetype":"venue"
},
  "geometry": {"coordinates":[-76.179287,40.178095],"type":"Point"}
}