{
  "type": "Feature",
  "properties": {
    "iso:country":"US",
    "sg:address":"11554 Lindbergh St",
    "sg:city":"Meadville",
    "sg:classifiers":[
        {
            "category":"Arts & Performance",
            "subcategory":"Music",
            "type":"Entertainment"
        }
    ],
    "sg:phone":"+1 814 336 4559",
    "sg:postcode":"16335",
    "sg:province":"PA",
    "sg:tags":[
        "jockey",
        "disc"
    ],
    "wof:name":"Opm Group",
    "wof:placetype":"venue"
},
  "geometry": {"coordinates":[-80.130492,41.62566],"type":"Point"}
}