{
  "type": "Feature",
  "properties": {
    "addr:full":"3515 6th Ave Altoona PA 16602",
    "addr:housenumber":"3515",
    "addr:postcode":"16602",
    "addr:street":"6Th Ave",
    "iso:country":"US",
    "sg:address":"3515 6th Ave",
    "sg:city":"Altoona",
    "sg:classifiers":[
        {
            "category":"Professional",
            "subcategory":"Employment Agencies",
            "type":"Services"
        }
    ],
    "sg:phone":"+1 814 942 1199",
    "sg:postcode":"16602",
    "sg:province":"PA",
    "wof:name":"Spherion",
    "wof:placetype":"venue"
},
  "geometry": {"coordinates":[-78.41341799999999,40.490274],"type":"Point"}
}