{
  "type": "Feature",
  "properties": {
    "addr:full":"11965 State Rte 618 Conneaut Lake PA 16316",
    "addr:housenumber":"11965",
    "addr:postcode":"16316",
    "addr:street":"State Rte 618 Conneaut",
    "iso:country":"US",
    "sg:address":"11965 State Rte 618",
    "sg:city":"Conneaut Lake",
    "sg:classifiers":[
        {
            "category":"Government",
            "subcategory":"Fire Station",
            "type":"Public Place"
        }
    ],
    "sg:phone":"+1 814 382 2875",
    "sg:postcode":"16316",
    "sg:province":"PA",
    "sg:tags":[
        "department"
    ],
    "wof:name":"Conneaut Lake Park Volunteer",
    "wof:placetype":"venue"
},
  "geometry": {"coordinates":[-80.32571799999999,41.626986],"type":"Point"}
}