{
  "type": "Feature",
  "properties": {
    "iso:country":"US",
    "sg:address":"9850 Old Perry Hwy",
    "sg:city":"Wexford",
    "sg:classifiers":[
        {
            "category":"Health Services",
            "subcategory":"Nursing And Care Facility",
            "type":"Services"
        }
    ],
    "sg:phone":"+1   ",
    "sg:postcode":"15090",
    "sg:province":"PA",
    "sg:tags":[
        "skilled"
    ],
    "wof:name":"Wexford House",
    "wof:placetype":"venue"
},
  "geometry": {"coordinates":[-80.04547599999999,40.589396],"type":"Point"}
}