{
  "type": "Feature",
  "properties": {
    "addr:full":"10830 John Wayne Dr Greencastle PA 17225",
    "addr:housenumber":"10830",
    "addr:postcode":"17225",
    "addr:street":"John Wayne Dr",
    "iso:country":"US",
    "sg:address":"10830 John Wayne Dr",
    "sg:city":"Greencastle",
    "sg:classifiers":[
        {
            "category":"Restaurant",
            "type":"Food & Drink"
        }
    ],
    "sg:menulink":"http://www.allmenus.com/pa/antrim/133527-subway/menu/",
    "sg:phone":"+1 717 597 4020",
    "sg:postcode":"17225",
    "sg:province":"PA",
    "sg:tags":[
        "american",
        "sandwich"
    ],
    "wof:name":"Subway",
    "wof:placetype":"venue"
},
  "geometry": {"coordinates":[-77.71213,39.785117],"type":"Point"}
}