{
  "type": "Feature",
  "properties": {
    "iso:country":"US",
    "sg:address":"627 Wyandotte St",
    "sg:city":"Irwin",
    "sg:classifiers":[
        {
            "category":"Professional",
            "subcategory":"Testing Lab",
            "type":"Services"
        }
    ],
    "sg:phone":"+1 724 861 9554",
    "sg:postcode":"15642",
    "sg:province":"PA",
    "sg:tags":[
        "inspection",
        "infrared"
    ],
    "wof:name":"IRIS Assoc",
    "wof:placetype":"venue"
},
  "geometry": {"coordinates":[-79.69103200000001,40.325476],"type":"Point"}
}