{
  "type": "Feature",
  "properties": {
    "iso:country":"US",
    "sg:address":"905 Jenkintown Rd",
    "sg:city":"Elkins Park",
    "sg:classifiers":[
        {
            "category":"Wholesale",
            "subcategory":"Jewelry",
            "type":"Manufacturing & Wholesale Goods"
        }
    ],
    "sg:phone":"+1 215 886 1431",
    "sg:postcode":"19027",
    "sg:province":"PA",
    "sg:tags":[
        "costume",
        "jeweler"
    ],
    "sg:website":"www.rainbowsalesinc.com",
    "wof:name":"Rainbow Sales Inc",
    "wof:placetype":"venue"
},
  "geometry": {"coordinates":[-75.11379100000001,40.083934],"type":"Point"}
}