{
  "type": "Feature",
  "properties": {
    "addr:full":"1291 Bushkill Center Rd Nazareth PA 18064",
    "addr:housenumber":"1291",
    "addr:postcode":"18064",
    "addr:street":"Bushkill Center Rd",
    "iso:country":"US",
    "sg:address":"1291 Bushkill Center Rd",
    "sg:city":"Nazareth",
    "sg:classifiers":[
        {
            "category":"Manufacturing",
            "subcategory":"Buildings",
            "type":"Manufacturing & Wholesale Goods"
        },
        {
            "category":"Building & Trades",
            "subcategory":"Construction",
            "type":"Services"
        }
    ],
    "sg:phone":"+1 610 746 0700",
    "sg:postcode":"18064",
    "sg:province":"PA",
    "sg:tags":[
        "home",
        "builder",
        "contractor"
    ],
    "sg:website":"http://www.aspen-homes.com",
    "wof:name":"Aspen Quality Homes Co",
    "wof:placetype":"venue"
},
  "geometry": {"coordinates":[-75.342992,40.803434],"type":"Point"}
}