{
  "type": "Feature",
  "properties": {
    "addr:full":"Mall At Robinson 2000 Robinson Center Dr Pittsburgh PA 15205",
    "addr:housenumber":"2000",
    "addr:postcode":"15205",
    "addr:street":"Robinson Center Dr",
    "iso:country":"US",
    "sg:address":"Mall At Robinson 2000 Robinson Center Dr",
    "sg:city":"Pittsburgh",
    "sg:classifiers":[
        {
            "category":"Shopping",
            "subcategory":"Department Store",
            "type":"Retail Goods"
        },
        {
            "category":"Personal",
            "subcategory":"Beauty Salon",
            "type":"Services"
        },
        {
            "category":"Personal",
            "subcategory":"Nail Salon",
            "type":"Services"
        }
    ],
    "sg:phone":"+1 412 787 4136",
    "sg:postcode":"15205",
    "sg:province":"PA",
    "sg:tags":[
        "hair"
    ],
    "sg:website":"www.jcpenney.net/about/jcp_produ...",
    "wof:name":"JCPenney salon",
    "wof:placetype":"venue"
},
  "geometry": {"coordinates":[-80.161317,40.454165],"type":"Point"}
}