{
  "type": "Feature",
  "properties": {
    "addr:full":"145 Doe Run Rd Coatesville PA 19320",
    "addr:housenumber":"145",
    "addr:postcode":"19320",
    "addr:street":"Doe Run Rd",
    "iso:country":"US",
    "sg:address":"145 Doe Run Rd",
    "sg:city":"Coatesville",
    "sg:classifiers":[
        {
            "category":"Organizations",
            "subcategory":"Religious Organization",
            "type":"Services"
        }
    ],
    "sg:phone":"+1 610 593 6464",
    "sg:postcode":"19320",
    "sg:province":"PA",
    "sg:tags":[
        "church"
    ],
    "wof:name":"Newlinville Mennonite Church",
    "wof:placetype":"venue"
},
  "geometry": {"coordinates":[-75.82862900000001,39.973172],"type":"Point"}
}