{
  "type": "Feature",
  "properties": {
    "iso:country":"US",
    "sg:address":"200 S School St",
    "sg:city":"Mount Carmel",
    "sg:classifiers":[
        {
            "category":"Home & Garden",
            "subcategory":"Carpets & Floor Coverings",
            "type":"Retail Goods"
        }
    ],
    "sg:phone":"+1   ",
    "sg:postcode":"17851",
    "sg:province":"PA",
    "wof:name":"Baileys Carpet & More",
    "wof:placetype":"venue"
},
  "geometry": {"coordinates":[-76.441856,40.797954],"type":"Point"}
}