{
  "type": "Feature",
  "properties": {
    "iso:country":"US",
    "sg:address":"930 Pointview Ave",
    "sg:city":"Ephrata",
    "sg:classifiers":[
        {
            "category":"Professional",
            "subcategory":"Research",
            "type":"Services"
        }
    ],
    "sg:phone":"+1 717 738 7272",
    "sg:postcode":"17522",
    "sg:province":"PA",
    "sg:tags":[
        "environmental",
        "ecological"
    ],
    "sg:website":"www.altenv.com",
    "wof:name":"Alternative Environmental",
    "wof:placetype":"venue"
},
  "geometry": {"coordinates":[-76.194681,40.170949],"type":"Point"}
}