{
  "type": "Feature",
  "properties": {
    "iso:country":"US",
    "sg:address":"669 Hayes St",
    "sg:city":"Hazleton",
    "sg:classifiers":[
        {
            "category":"Personal",
            "subcategory":"Beauty Salon",
            "type":"Services"
        }
    ],
    "sg:phone":"+1 570 459 0125",
    "sg:postcode":"18201",
    "sg:province":"PA",
    "wof:name":"Francine Paisley Beauty Salon",
    "wof:placetype":"venue"
},
  "geometry": {"coordinates":[-75.96724500000001,40.966037],"type":"Point"}
}