{
  "type": "Feature",
  "properties": {
    "addr:full":"9000 Bartram Avenue Philadelphia PA 19153",
    "addr:housenumber":"9000",
    "addr:postcode":"19153",
    "addr:street":"Bartram Avenue",
    "iso:country":"US",
    "sg:address":"9000 Bartram Avenue",
    "sg:city":"Philadelphia",
    "sg:classifiers":[
        {
            "category":"Travel",
            "subcategory":"Hotels & Motels",
            "type":"Entertainment"
        }
    ],
    "sg:phone":"+1 866 618 8101",
    "sg:postcode":"19153",
    "sg:province":"PA",
    "sg:website":"embassysuites1.hilton.com/",
    "wof:name":"Embassy Suites Philadelphia - Airport Hotel",
    "wof:placetype":"venue"
},
  "geometry": {"coordinates":[-75.24989600000001,39.883996],"type":"Point"}
}