{
  "type": "Feature",
  "properties": {
    "iso:country":"US",
    "sg:address":"516 Ashbourne Rd",
    "sg:city":"Cheltenham",
    "sg:classifiers":[
        {
            "category":"Organizations",
            "subcategory":"Religious Organization",
            "type":"Services"
        }
    ],
    "sg:phone":"+1 215 379 6799",
    "sg:postcode":"19012",
    "sg:province":"PA",
    "sg:tags":[
        "church"
    ],
    "wof:name":"Community Church Of God",
    "wof:placetype":"venue"
},
  "geometry": {"coordinates":[-75.100657,40.061935],"type":"Point"}
}