{
  "type": "Feature",
  "properties": {
    "addr:full":"9 Parsonage St Newville PA 17241",
    "addr:housenumber":"9",
    "addr:postcode":"17241",
    "addr:street":"Parsonage St",
    "iso:country":"US",
    "sg:address":"9 Parsonage St",
    "sg:city":"Newville",
    "sg:classifiers":[
        {
            "category":"Education",
            "subcategory":"Library",
            "type":"Public Place"
        }
    ],
    "sg:phone":"+1 717 776 5900",
    "sg:postcode":"17241",
    "sg:province":"PA",
    "wof:name":"Graham John Public Library",
    "wof:placetype":"venue"
},
  "geometry": {"coordinates":[-77.400274,40.171422],"type":"Point"}
}