{
  "type": "Feature",
  "properties": {
    "iso:country":"US",
    "sg:address":"3409 Overview Dr",
    "sg:city":"York",
    "sg:classifiers":[
        {
            "category":"Building & Trades",
            "subcategory":"Cleaning & Sanitation",
            "type":"Services"
        }
    ],
    "sg:phone":"+1   ",
    "sg:postcode":"17406",
    "sg:province":"PA",
    "sg:tags":[
        "maintenance"
    ],
    "wof:name":"K&C Cleaning Services",
    "wof:placetype":"venue"
},
  "geometry": {"coordinates":[-76.67139,39.996809],"type":"Point"}
}