{
  "type": "Feature",
  "properties": {
    "iso:country":"US",
    "sg:address":"235 Atwood St",
    "sg:city":"Pittsburgh",
    "sg:classifiers":[
        {
            "category":"Real Estate",
            "subcategory":"Real Estate Operator",
            "type":"Services"
        }
    ],
    "sg:phone":"+1   ",
    "sg:postcode":"15213",
    "sg:province":"PA",
    "sg:tags":[
        "building",
        "nonresidential"
    ],
    "wof:name":"Central Property Services",
    "wof:placetype":"venue"
},
  "geometry": {"coordinates":[-79.956023,40.439907],"type":"Point"}
}