{
  "type": "Feature",
  "properties": {
    "iso:country":"US",
    "sg:address":"1375 Pershing Blvd",
    "sg:city":"Reading",
    "sg:classifiers":[
        {
            "category":"Real Estate",
            "subcategory":"Real Estate Operator",
            "type":"Services"
        }
    ],
    "sg:phone":"+1 610 775 1177",
    "sg:postcode":"19607",
    "sg:province":"PA",
    "sg:tags":[
        "condominium"
    ],
    "wof:name":"Hummingbird Hill Condominium",
    "wof:placetype":"venue"
},
  "geometry": {"coordinates":[-75.952905,40.318592],"type":"Point"}
}