{
  "type": "Feature",
  "properties": {
    "iso:country":"US",
    "sg:address":"714 Chestnut St",
    "sg:city":"Philadelphia",
    "sg:classifiers":[
        {
            "category":"Restaurant",
            "type":"Food & Drink"
        }
    ],
    "sg:phone":"+1 215 733 0895",
    "sg:postcode":"19106",
    "sg:province":"PA",
    "sg:tags":[
        "mexican"
    ],
    "sg:website":"www.elazteca2.net",
    "wof:name":"El Azteca Mexican Restaurant",
    "wof:placetype":"venue"
},
  "geometry": {"coordinates":[-75.152901,39.949699],"type":"Point"}
}