{
  "type": "Feature",
  "properties": {
    "iso:country":"US",
    "sg:address":"249 W High St",
    "sg:city":"Pottstown",
    "sg:classifiers":[
        {
            "category":"Health Services",
            "subcategory":"Hospital",
            "type":"Services"
        }
    ],
    "sg:phone":"+1 610 970 5301",
    "sg:postcode":"19464",
    "sg:province":"PA",
    "sg:tags":[
        "mental"
    ],
    "wof:name":"Mental Health Assn-Se Pa",
    "wof:placetype":"venue"
},
  "geometry": {"coordinates":[-75.668598,40.249602],"type":"Point"}
}