{
  "type": "Feature",
  "properties": {
    "addr:full":"3901 Market St Ste M6 Philadelphia PA 19104",
    "addr:housenumber":"3901",
    "addr:postcode":"19104",
    "addr:street":"Market St Ste M6",
    "iso:country":"US",
    "sg:address":"3901 Market St Ste M6",
    "sg:city":"Philadelphia",
    "sg:classifiers":[
        {
            "category":"Food & Beverages",
            "subcategory":"Ethnic Foods",
            "type":"Retail Goods"
        }
    ],
    "sg:phone":"+1 215 240 7630",
    "sg:postcode":"19104",
    "sg:province":"PA",
    "sg:tags":[
        "soul"
    ],
    "wof:name":"Mother's Garden Restaurant",
    "wof:placetype":"venue"
},
  "geometry": {"coordinates":[-75.199642,39.956897],"type":"Point"}
}