{
  "type": "Feature",
  "properties": {
    "iso:country":"US",
    "sg:address":"1320 Sherman St",
    "sg:city":"Allentown",
    "sg:classifiers":[
        {
            "category":"Social Services",
            "subcategory":"Child Care",
            "type":"Services"
        },
        {
            "category":"Education",
            "subcategory":"Preschool",
            "type":"Public Place"
        },
        {
            "category":"Education",
            "subcategory":"School",
            "type":"Public Place"
        }
    ],
    "sg:phone":"+1 610 434 2301",
    "sg:postcode":"18109",
    "sg:province":"PA",
    "sg:tags":[
        "elementary",
        "day"
    ],
    "wof:name":"Little People Child Care School",
    "wof:placetype":"venue"
},
  "geometry": {"coordinates":[-75.428802,40.631802],"type":"Point"}
}