{
  "type": "Feature",
  "properties": {
    "addr:full":"14 N 10th St Lebanon PA 17046",
    "addr:housenumber":"14",
    "addr:postcode":"17046",
    "addr:street":"N 10Th St",
    "iso:country":"US",
    "sg:address":"14 N 10th St",
    "sg:city":"Lebanon",
    "sg:classifiers":[
        {
            "category":"Professional",
            "type":"Services"
        }
    ],
    "sg:phone":"+1   ",
    "sg:postcode":"17046",
    "sg:province":"PA",
    "wof:name":"Donald Weiser",
    "wof:placetype":"venue"
},
  "geometry": {"coordinates":[-76.42793,40.339254],"type":"Point"}
}