{
  "type": "Feature",
  "properties": {
    "addr:full":"515 Broadway Hanover PA 17331",
    "addr:housenumber":"515",
    "addr:postcode":"17331",
    "addr:street":"Broadway",
    "iso:country":"US",
    "sg:address":"515 Broadway",
    "sg:city":"Hanover",
    "sg:classifiers":[
        {
            "category":"Autos & Motor Vehicles",
            "subcategory":"Auto Supplies",
            "type":"Retail Goods"
        },
        {
            "category":"Retail",
            "subcategory":"Auto Repair",
            "type":"Services"
        }
    ],
    "sg:phone":"+1 866 977 3192",
    "sg:postcode":"17331",
    "sg:province":"PA",
    "sg:tags":[
        "transmission",
        "transmissions-other"
    ],
    "sg:website":"http://hanovertransmissions.com",
    "wof:name":"Hanover Transmissions LLC",
    "wof:placetype":"venue"
},
  "geometry": {"coordinates":[-76.97933,39.806682],"type":"Point"}
}