{
  "type": "Feature",
  "properties": {
    "iso:country":"US",
    "sg:address":"1401 Blvd of the Allies",
    "sg:city":"Pittsburgh",
    "sg:classifiers":[
        {
            "category":"Education",
            "subcategory":"Vocational School",
            "type":"Public Place"
        }
    ],
    "sg:phone":"+1   ",
    "sg:postcode":"15219",
    "sg:province":"PA",
    "sg:tags":[
        "nursing"
    ],
    "wof:name":"The Mercy School of Nursing",
    "wof:placetype":"venue"
},
  "geometry": {"coordinates":[-79.984393,40.435383],"type":"Point"}
}