{
  "type": "Feature",
  "properties": {
    "iso:country":"US",
    "sg:address":"333 W Lafayette St",
    "sg:city":"Norristown",
    "sg:classifiers":[
        {
            "category":"Wholesale",
            "subcategory":"Groceries",
            "type":"Manufacturing & Wholesale Goods"
        }
    ],
    "sg:phone":"+1 610 239 0200",
    "sg:postcode":"19401",
    "sg:province":"PA",
    "sg:tags":[
        "frozen",
        "foods-wholesale"
    ],
    "sg:website":"http://www.efundraisers.com",
    "wof:name":"Peters Pzza Chscake Ckie Dough",
    "wof:placetype":"venue"
},
  "geometry": {"coordinates":[-75.349892,40.116038],"type":"Point"}
}