{
  "type": "Feature",
  "properties": {
    "iso:country":"US",
    "sg:address":"10 Viewmont Mall",
    "sg:city":"Scranton",
    "sg:classifiers":[
        {
            "category":"Shopping",
            "subcategory":"Clothing, Apparel, & Fashions",
            "type":"Retail Goods"
        }
    ],
    "sg:phone":"+1 570 963 9091",
    "sg:postcode":"18508",
    "sg:province":"PA",
    "wof:name":"Old Navy",
    "wof:placetype":"venue"
},
  "geometry": {"coordinates":[-75.65682099999999,41.460834],"type":"Point"}
}