{
  "type": "Feature",
  "properties": {
    "addr:full":"1265 Almshouse Rd Warrington PA 18976",
    "addr:housenumber":"1265",
    "addr:postcode":"18976",
    "addr:street":"Almshouse Rd",
    "iso:country":"US",
    "sg:address":"1265 Almshouse Rd",
    "sg:city":"Warrington",
    "sg:classifiers":[
        {
            "category":"Building & Trades",
            "subcategory":"Construction",
            "type":"Services"
        }
    ],
    "sg:phone":"+1 215 343 7088",
    "sg:postcode":"18976",
    "sg:province":"PA",
    "sg:tags":[
        "general",
        "contractor"
    ],
    "wof:name":"Carney Inc",
    "wof:placetype":"venue"
},
  "geometry": {"coordinates":[-75.12721500000001,40.269629],"type":"Point"}
}