{
  "type": "Feature",
  "properties": {
    "addr:full":"4 Edward Ct Orrtanna PA 17307",
    "addr:housenumber":"4",
    "addr:postcode":"17307",
    "addr:street":"Edward Ct",
    "iso:country":"US",
    "sg:address":"4 Edward Ct",
    "sg:city":"Orrtanna",
    "sg:classifiers":[
        {
            "category":"Building & Trades",
            "subcategory":"Landscaping Services",
            "type":"Services"
        }
    ],
    "sg:phone":"+1 717 337 0887",
    "sg:postcode":"17307",
    "sg:province":"PA",
    "sg:tags":[
        "lawn",
        "maintenance",
        "grounds"
    ],
    "wof:name":"Lawn Doctor-Chambersburg",
    "wof:placetype":"venue"
},
  "geometry": {"coordinates":[-77.34846400000001,39.877767],"type":"Point"}
}