{
  "type": "Feature",
  "properties": {
    "addr:full":"309 Smithfield St Pittsburgh PA 15222",
    "addr:housenumber":"309",
    "addr:postcode":"15222",
    "addr:street":"Smithfield St",
    "iso:country":"US",
    "sg:address":"309 Smithfield St",
    "sg:city":"Pittsburgh",
    "sg:classifiers":[
        {
            "category":"Professional",
            "subcategory":"Lawyer & Legal Services",
            "type":"Services"
        }
    ],
    "sg:phone":"+1 412 566 1818",
    "sg:postcode":"15222",
    "sg:province":"PA",
    "sg:tags":[
        "attorney"
    ],
    "wof:name":"Mc Cann Garland Ridall & Burke",
    "wof:placetype":"venue"
},
  "geometry": {"coordinates":[-79.99963200000001,40.438716],"type":"Point"}
}