{
  "type": "Feature",
  "properties": {
    "iso:country":"US",
    "sg:address":"110 Montgomery Ave",
    "sg:city":"Bala Cynwyd",
    "sg:classifiers":[
        {
            "category":"Wholesale",
            "subcategory":"Vending Machines",
            "type":"Manufacturing & Wholesale Goods"
        }
    ],
    "sg:phone":"+1   ",
    "sg:postcode":"19004",
    "sg:province":"PA",
    "sg:tags":[
        "operator"
    ],
    "wof:name":"Marathon Vending",
    "wof:placetype":"venue"
},
  "geometry": {"coordinates":[-75.238761,40.005421],"type":"Point"}
}