{
  "type": "Feature",
  "properties": {
    "addr:full":"4984 W Thompson St Philadelphia PA 19131",
    "addr:housenumber":"4984",
    "addr:postcode":"19131",
    "addr:street":"W Thompson St",
    "iso:country":"US",
    "sg:address":"4984 W Thompson St",
    "sg:city":"Philadelphia",
    "sg:classifiers":[
        {
            "category":"Building & Trades",
            "subcategory":"Locksmith",
            "type":"Services"
        }
    ],
    "sg:phone":"+1 267 298 2547",
    "sg:postcode":"19131",
    "sg:province":"PA",
    "sg:tags":[
        "key"
    ],
    "wof:name":"24 Hour Available Locksmith",
    "wof:placetype":"venue"
},
  "geometry": {"coordinates":[-75.222262,39.973264],"type":"Point"}
}