{
  "type": "Feature",
  "properties": {
    "addr:full":"1650 Market St Philadelphia PA 19103",
    "addr:housenumber":"1650",
    "addr:postcode":"19103",
    "addr:street":"Market St",
    "iso:country":"US",
    "sg:address":"1650 Market St",
    "sg:city":"Philadelphia",
    "sg:classifiers":[
        {
            "category":"Professional",
            "subcategory":"Lawyer & Legal Services",
            "type":"Services"
        }
    ],
    "sg:phone":"+1 215 979 1000",
    "sg:postcode":"19103",
    "sg:province":"PA",
    "sg:tags":[
        "attorney"
    ],
    "sg:website":"www.duanemorris.com",
    "wof:name":"Duane Morris",
    "wof:placetype":"venue"
},
  "geometry": {"coordinates":[-75.167835,39.9528],"type":"Point"}
}