{
  "type": "Feature",
  "properties": {
    "iso:country":"US",
    "sg:address":"4628 Stafford Ave",
    "sg:city":"Bethlehem",
    "sg:classifiers":[
        {
            "category":"Building & Trades",
            "subcategory":"Construction",
            "type":"Services"
        }
    ],
    "sg:phone":"+1 610 759 5911",
    "sg:postcode":"18020",
    "sg:province":"PA",
    "sg:tags":[
        "coping",
        "plastering",
        "tiling",
        "pool",
        "swimming"
    ],
    "wof:name":"Aqua-Ducks",
    "wof:placetype":"venue"
},
  "geometry": {"coordinates":[-75.35074899999999,40.691773],"type":"Point"}
}