{
  "type": "Feature",
  "properties": {
    "addr:full":"424 Davis St Easton PA 18042",
    "addr:housenumber":"424",
    "addr:postcode":"18042",
    "addr:street":"Davis St",
    "iso:country":"US",
    "sg:address":"424 Davis St",
    "sg:city":"Easton",
    "sg:classifiers":[
        {
            "category":"Professional",
            "type":"Services"
        }
    ],
    "sg:phone":"+1 610 253 8036",
    "sg:postcode":"18042",
    "sg:province":"PA",
    "sg:tags":[
        "establishment"
    ],
    "wof:name":"Wr Dilts",
    "wof:placetype":"venue"
},
  "geometry": {"coordinates":[-75.212502,40.679835],"type":"Point"}
}