{
  "type": "Feature",
  "properties": {
    "iso:country":"US",
    "sg:address":"1215 Foster Ave",
    "sg:city":"Pittsburgh",
    "sg:classifiers":[
        {
            "category":"Real Estate",
            "subcategory":"Real Estate Operator",
            "type":"Services"
        }
    ],
    "sg:phone":"+1 412 921 5057",
    "sg:postcode":"15205",
    "sg:province":"PA",
    "sg:tags":[
        "apartment"
    ],
    "wof:name":"Crafton Tower",
    "wof:placetype":"venue"
},
  "geometry": {"coordinates":[-80.068199,40.442001],"type":"Point"}
}