{
  "type": "Feature",
  "properties": {
    "addr:full":"Hopkinson House Philadelphia PA 19106",
    "addr:postcode":"19106",
    "iso:country":"US",
    "sg:address":"Hopkinson House",
    "sg:city":"Philadelphia",
    "sg:classifiers":[
        {
            "category":"Health Services",
            "subcategory":"Doctor",
            "type":"Services"
        }
    ],
    "sg:phone":"+1 215 925 1968",
    "sg:postcode":"19106",
    "sg:province":"PA",
    "wof:name":"Feldman Julian D MD",
    "wof:placetype":"venue"
},
  "geometry": {"coordinates":[-75.15149700000001,39.946098],"type":"Point"}
}