{
  "type": "Feature",
  "properties": {
    "iso:country":"US",
    "sg:address":"55 Laurel Way",
    "sg:city":"Palmerton",
    "sg:classifiers":[
        {
            "category":"Banks & Credit Unions",
            "subcategory":"Bank",
            "type":"Services"
        }
    ],
    "sg:phone":"+1 610 826 5156",
    "sg:postcode":"18071",
    "sg:province":"PA",
    "sg:tags":[
        "mortgage"
    ],
    "wof:name":"Total Mortgage Resource",
    "wof:placetype":"venue"
},
  "geometry": {"coordinates":[-75.516604,40.845086],"type":"Point"}
}