{
  "type": "Feature",
  "properties": {
    "iso:country":"US",
    "sg:address":"2063 Red Lion Rd",
    "sg:city":"Philadelphia",
    "sg:classifiers":[
        {
            "category":"Manufacturing",
            "subcategory":"Textiles",
            "type":"Manufacturing & Wholesale Goods"
        }
    ],
    "sg:phone":"+1 215 840 5556",
    "sg:postcode":"19115",
    "sg:province":"PA",
    "sg:tags":[
        "textiles-manufacturers"
    ],
    "wof:name":"Denim House Blues",
    "wof:placetype":"venue"
},
  "geometry": {"coordinates":[-75.020173,40.098792],"type":"Point"}
}