{
  "type": "Feature",
  "properties": {
    "iso:country":"US",
    "sg:address":"3628 W Creek Rd",
    "sg:city":"Smicksburg",
    "sg:classifiers":[
        {
            "category":"Farming",
            "subcategory":"Farm",
            "type":"Manufacturing & Wholesale Goods"
        }
    ],
    "sg:phone":"+1   ",
    "sg:postcode":"16256",
    "sg:province":"PA",
    "sg:tags":[
        "crop",
        "general"
    ],
    "wof:name":"Lar Ran Farms",
    "wof:placetype":"venue"
},
  "geometry": {"coordinates":[-79.081028,40.857059],"type":"Point"}
}