{
  "type": "Feature",
  "properties": {
    "iso:country":"US",
    "sg:address":"3901 N Delaware Ave",
    "sg:city":"Philadelphia",
    "sg:classifiers":[
        {
            "category":"Utilities",
            "subcategory":"Electric",
            "type":"Services"
        }
    ],
    "sg:phone":"+1 215 831 7600",
    "sg:postcode":"19137",
    "sg:province":"PA",
    "sg:website":"http://www.peco.com",
    "wof:name":"Peco Energy",
    "wof:placetype":"venue"
},
  "geometry": {"coordinates":[-75.08116,39.983808],"type":"Point"}
}