{
  "type": "Feature",
  "properties": {
    "addr:full":"66 Seminary Ave Gettysburg PA 17325",
    "addr:housenumber":"66",
    "addr:postcode":"17325",
    "addr:street":"Seminary Ave",
    "iso:country":"US",
    "sg:address":"66 Seminary Ave",
    "sg:city":"Gettysburg",
    "sg:classifiers":[
        {
            "category":"Education",
            "subcategory":"Library",
            "type":"Public Place"
        }
    ],
    "sg:phone":"+1 717 338 3014",
    "sg:postcode":"17325",
    "sg:province":"PA",
    "wof:name":"A R Wentz Library",
    "wof:placetype":"venue"
},
  "geometry": {"coordinates":[-77.239543,39.83186],"type":"Point"}
}