{
  "type": "Feature",
  "properties": {
    "iso:country":"US",
    "sg:address":"20 Marchwood Rd",
    "sg:city":"Exton",
    "sg:classifiers":[
        {
            "category":"Restaurant",
            "type":"Food & Drink"
        }
    ],
    "sg:phone":"+1   ",
    "sg:postcode":"19341",
    "sg:province":"PA",
    "sg:tags":[
        "eating"
    ],
    "wof:name":"House of Beans Cafe",
    "wof:placetype":"venue"
},
  "geometry": {"coordinates":[-75.638563,40.048493],"type":"Point"}
}