{
  "type": "Feature",
  "properties": {
    "iso:country":"US",
    "sg:address":"637 Lorraine Ave",
    "sg:city":"Ardmore",
    "sg:classifiers":[
        {
            "category":"Manufacturing",
            "subcategory":"Food",
            "type":"Manufacturing & Wholesale Goods"
        },
        {
            "category":"Ice Cream",
            "type":"Food & Drink"
        }
    ],
    "sg:phone":"+1 610 649 9462",
    "sg:postcode":"19003",
    "sg:province":"PA",
    "sg:tags":[
        "frozen",
        "desserts-manufacturers",
        "distributor",
        "dessert"
    ],
    "wof:name":"Sugar Magnolia Inc",
    "wof:placetype":"venue"
},
  "geometry": {"coordinates":[-75.29984899999999,39.997038],"type":"Point"}
}