{
  "type": "Feature",
  "properties": {
    "iso:country":"US",
    "sg:address":"228 Holland Rd",
    "sg:city":"Holland",
    "sg:classifiers":[
        {
            "category":"Health Services",
            "subcategory":"Doctor",
            "type":"Services"
        }
    ],
    "sg:phone":"+1 215 357 3131",
    "sg:postcode":"18966",
    "sg:province":"PA",
    "sg:tags":[
        "dentist"
    ],
    "wof:name":"Smile Designers",
    "wof:placetype":"venue"
},
  "geometry": {"coordinates":[-74.986789,40.174715],"type":"Point"}
}