{
  "type": "Feature",
  "properties": {
    "iso:country":"US",
    "sg:address":"1062 W Lancaster Ave",
    "sg:city":"Bryn Mawr",
    "sg:classifiers":[
        {
            "category":"Health Services",
            "subcategory":"Clinic",
            "type":"Services"
        }
    ],
    "sg:phone":"+1   ",
    "sg:postcode":"19010",
    "sg:province":"PA",
    "sg:tags":[
        "specialty",
        "outpatient"
    ],
    "wof:name":"Paula T Sivler",
    "wof:placetype":"venue"
},
  "geometry": {"coordinates":[-75.32391,40.024089],"type":"Point"}
}