{
  "type": "Feature",
  "properties": {
    "addr:full":"1128 State St Ste 302 Erie PA 16501",
    "addr:housenumber":"1128",
    "addr:postcode":"16501",
    "addr:street":"State St Ste 302",
    "iso:country":"US",
    "sg:address":"1128 State St Ste 302",
    "sg:city":"Erie",
    "sg:classifiers":[
        {
            "category":"Wholesale",
            "subcategory":"Medical Equipment & Supplies",
            "type":"Manufacturing & Wholesale Goods"
        },
        {
            "category":"Health Services",
            "subcategory":"Doctor",
            "type":"Services"
        },
        {
            "category":"Health Services",
            "subcategory":"Medical Lab",
            "type":"Services"
        },
        {
            "category":"Shopping",
            "subcategory":"Pharmacy",
            "type":"Retail Goods"
        }
    ],
    "sg:phone":"+1 814 454 0715",
    "sg:postcode":"16501",
    "sg:province":"PA",
    "sg:tags":[
        "physician",
        "educational",
        "endocrinology",
        "support",
        "surgeons",
        "home",
        "surgeon",
        "referral",
        "metabolism",
        "care",
        "diabetes"
    ],
    "wof:name":"Diabetes Association Of E",
    "wof:placetype":"venue"
},
  "geometry": {"coordinates":[-80.081746,42.124215],"type":"Point"}
}