{
  "type": "Feature",
  "properties": {
    "iso:country":"US",
    "sg:address":"1075 Progress St",
    "sg:city":"Pittsburgh",
    "sg:classifiers":[
        {
            "category":"Food & Beverages",
            "subcategory":"Groceries & Convenience Stores",
            "type":"Retail Goods"
        }
    ],
    "sg:phone":"+1 412 222 2200",
    "sg:postcode":"15212",
    "sg:province":"PA",
    "sg:tags":[
        "product"
    ],
    "wof:name":"Del Monte Foods",
    "wof:placetype":"venue"
},
  "geometry": {"coordinates":[-79.990774,40.454628],"type":"Point"}
}