{
  "type": "Feature",
  "properties": {
    "addr:full":"3595 E State St Hermitage PA 16148",
    "addr:housenumber":"3595",
    "addr:postcode":"16148",
    "addr:street":"E State St",
    "iso:country":"US",
    "sg:address":"3595 E State St",
    "sg:city":"Hermitage",
    "sg:classifiers":[
        {
            "category":"Manufacturing",
            "subcategory":"Printing",
            "type":"Manufacturing & Wholesale Goods"
        }
    ],
    "sg:phone":"+1   ",
    "sg:postcode":"16148",
    "sg:province":"PA",
    "sg:tags":[
        "copying",
        "offset"
    ],
    "wof:name":"R and R Printing and Copying",
    "wof:placetype":"venue"
},
  "geometry": {"coordinates":[-80.44340699999999,41.233808],"type":"Point"}
}