{
  "type": "Feature",
  "properties": {
    "addr:full":"637 E 28th Division Hwy Lititz PA 17543",
    "addr:housenumber":"637",
    "addr:postcode":"17543",
    "addr:street":"E 28Th Division Hwy",
    "iso:country":"US",
    "sg:address":"637 E 28th Division Hwy",
    "sg:city":"Lititz",
    "sg:classifiers":[
        {
            "category":"Professional",
            "subcategory":"Computer Services",
            "type":"Services"
        }
    ],
    "sg:phone":"+1 717 625 1161",
    "sg:postcode":"17543",
    "sg:province":"PA",
    "sg:tags":[
        "website",
        "design"
    ],
    "wof:name":"Franklin Graphics",
    "wof:placetype":"venue"
},
  "geometry": {"coordinates":[-76.26325,40.221499],"type":"Point"}
}