{
  "type": "Feature",
  "properties": {
    "iso:country":"US",
    "sg:address":"1215 5th St",
    "sg:city":"New Brighton",
    "sg:classifiers":[
        {
            "category":"Food & Beverages",
            "subcategory":"Groceries & Convenience Stores",
            "type":"Retail Goods"
        },
        {
            "category":"Restaurant",
            "type":"Food & Drink"
        }
    ],
    "sg:phone":"+1 724 847 3090",
    "sg:postcode":"15066",
    "sg:province":"PA",
    "sg:tags":[
        "delicatessen",
        "eating"
    ],
    "wof:name":"Fifth Street Deli",
    "wof:placetype":"venue"
},
  "geometry": {"coordinates":[-80.31202,40.742466],"type":"Point"}
}