{
  "type": "Feature",
  "properties": {
    "addr:full":"325 Auburn St Pittsburgh PA 15235",
    "addr:housenumber":"325",
    "addr:postcode":"15235",
    "addr:street":"Auburn St",
    "iso:country":"US",
    "sg:address":"325 Auburn St",
    "sg:city":"Pittsburgh",
    "sg:classifiers":[
        {
            "category":"Retail",
            "subcategory":"Repair Shop",
            "type":"Services"
        }
    ],
    "sg:phone":"+1   ",
    "sg:postcode":"15235",
    "sg:province":"PA",
    "sg:tags":[
        "electrical"
    ],
    "wof:name":"Bob Tuskys Appl Htg & Coolg",
    "wof:placetype":"venue"
},
  "geometry": {"coordinates":[-79.79208199999999,40.494871],"type":"Point"}
}