{
  "type": "Feature",
  "properties": {
    "iso:country":"US",
    "sg:address":"2056 S Queen St",
    "sg:city":"York",
    "sg:classifiers":[
        {
            "category":"Retail",
            "subcategory":"Car Wash",
            "type":"Services"
        }
    ],
    "sg:phone":"+1 717 845 1529",
    "sg:postcode":"17403",
    "sg:province":"PA",
    "sg:tags":[
        "polishing",
        "washing"
    ],
    "wof:name":"Anderson's Car Wash",
    "wof:placetype":"venue"
},
  "geometry": {"coordinates":[-76.693679,39.938091],"type":"Point"}
}