{
  "type": "Feature",
  "properties": {
    "addr:full":"733 Fairyland Rd Lehighton PA 18235",
    "addr:housenumber":"733",
    "addr:postcode":"18235",
    "addr:street":"Fairyland Rd",
    "iso:country":"US",
    "sg:address":"733 Fairyland Rd",
    "sg:city":"Lehighton",
    "sg:classifiers":[
        {
            "category":"Retail",
            "subcategory":"Auto Repair",
            "type":"Services"
        }
    ],
    "sg:phone":"+1 610 377 5928",
    "sg:postcode":"18235",
    "sg:province":"PA",
    "sg:tags":[
        "repairing",
        "automobile"
    ],
    "wof:name":"Barry's Alternator & Starter",
    "wof:placetype":"venue"
},
  "geometry": {"coordinates":[-75.68576899999999,40.843578],"type":"Point"}
}