{
  "type": "Feature",
  "properties": {
    "addr:full":"649 South Ave Secane PA 19018",
    "addr:housenumber":"649",
    "addr:postcode":"19018",
    "addr:street":"South Ave",
    "iso:country":"US",
    "sg:address":"649 South Ave",
    "sg:city":"Secane",
    "sg:classifiers":[
        {
            "category":"Professional",
            "subcategory":"Business Services",
            "type":"Services"
        }
    ],
    "sg:phone":"+1 610 604 9920",
    "sg:postcode":"19018",
    "sg:province":"PA",
    "wof:name":"J & R Systems For Business",
    "wof:placetype":"venue"
},
  "geometry": {"coordinates":[-75.309972,39.915184],"type":"Point"}
}