{
  "type": "Feature",
  "properties": {
    "iso:country":"US",
    "sg:address":"653 Washington Blvd",
    "sg:city":"Williamsport",
    "sg:classifiers":[
        {
            "category":"Food & Beverages",
            "subcategory":"Groceries & Convenience Stores",
            "type":"Retail Goods"
        }
    ],
    "sg:phone":"+1 570 322 8220",
    "sg:postcode":"17701",
    "sg:province":"PA",
    "wof:name":"Choice Discount Tobacco Outlet",
    "wof:placetype":"venue"
},
  "geometry": {"coordinates":[-76.990831,41.247704],"type":"Point"}
}