{
  "type": "Feature",
  "properties": {
    "addr:full":"75 N Market St Nanticoke PA 18634",
    "addr:housenumber":"75",
    "addr:postcode":"18634",
    "addr:street":"N Market St",
    "iso:country":"US",
    "sg:address":"75 N Market St",
    "sg:city":"Nanticoke",
    "sg:classifiers":[
        {
            "category":"Sports & Exercise",
            "subcategory":"Gym",
            "type":"Entertainment"
        }
    ],
    "sg:phone":"+1 570 740 2777",
    "sg:postcode":"18634",
    "sg:province":"PA",
    "sg:tags":[
        "fitness",
        "physical",
        "facility"
    ],
    "wof:name":"Curves For Women",
    "wof:placetype":"venue"
},
  "geometry": {"coordinates":[-76.007938,41.206281],"type":"Point"}
}