{
  "type": "Feature",
  "properties": {
    "addr:full":"270 Coon Trail Ln Gratz PA 17030",
    "addr:housenumber":"270",
    "addr:postcode":"17030",
    "addr:street":"Coon Trail Ln",
    "iso:country":"US",
    "sg:address":"270 Coon Trail Ln",
    "sg:city":"Gratz",
    "sg:classifiers":[
        {
            "category":"Manufacturing",
            "subcategory":"Buildings",
            "type":"Manufacturing & Wholesale Goods"
        },
        {
            "category":"Building & Trades",
            "subcategory":"Construction",
            "type":"Services"
        }
    ],
    "sg:phone":"+1 717 365 3954",
    "sg:postcode":"17030",
    "sg:province":"PA",
    "sg:tags":[
        "home",
        "builder",
        "contractor"
    ],
    "wof:name":"Esh Builders",
    "wof:placetype":"venue"
},
  "geometry": {"coordinates":[-76.745541,40.604888],"type":"Point"}
}