{
  "type": "Feature",
  "properties": {
    "iso:country":"US",
    "sg:address":"860 Tuck St",
    "sg:city":"Lebanon",
    "sg:classifiers":[
        {
            "category":"Health Services",
            "subcategory":"Dentist",
            "type":"Services"
        }
    ],
    "sg:phone":"+1 717 273 6745",
    "sg:postcode":"17042",
    "sg:province":"PA",
    "wof:name":"Jeffrey Horowitz Dds",
    "wof:placetype":"venue"
},
  "geometry": {"coordinates":[-76.416391,40.31949],"type":"Point"}
}