{
  "type": "Feature",
  "properties": {
    "iso:country":"US",
    "sg:address":"1201 Chestnut Street",
    "sg:city":"Philadelphia",
    "sg:classifiers":[
        {
            "category":"Fast Food",
            "type":"Food & Drink"
        },
        {
            "category":"Restaurant",
            "type":"Food & Drink"
        },
        {
            "category":"Food & Beverages",
            "subcategory":"Bakery",
            "type":"Retail Goods"
        },
        {
            "category":"Food & Beverages",
            "subcategory":"Groceries & Convenience Stores",
            "type":"Retail Goods"
        }
    ],
    "sg:phone":"+1 215 568 1233",
    "sg:postcode":"19107",
    "sg:province":"PA",
    "sg:tags":[
        "shop",
        "american",
        "sandwich",
        "take"
    ],
    "sg:website":"www.quiznos.com",
    "wof:name":"Quizno's Classic Subs",
    "wof:placetype":"venue"
},
  "geometry": {"coordinates":[-75.160332,39.950317],"type":"Point"}
}