{
  "type": "Feature",
  "properties": {
    "addr:full":"3009 Hazel St Erie PA 16508",
    "addr:housenumber":"3009",
    "addr:postcode":"16508",
    "addr:street":"Hazel St",
    "iso:country":"US",
    "sg:address":"3009 Hazel St",
    "sg:city":"Erie",
    "sg:classifiers":[
        {
            "category":"Utilities",
            "subcategory":"Refuse",
            "type":"Services"
        }
    ],
    "sg:phone":"+1 814 868 2241",
    "sg:postcode":"16508",
    "sg:province":"PA",
    "sg:tags":[
        "management",
        "garbage",
        "collection",
        "system"
    ],
    "wof:name":"Oblinski's Trash Hauling",
    "wof:placetype":"venue"
},
  "geometry": {"coordinates":[-80.085804,42.10246],"type":"Point"}
}