{
  "type": "Feature",
  "properties": {
    "addr:full":"259 W Main St Ringtown PA 17967",
    "addr:housenumber":"259",
    "addr:postcode":"17967",
    "addr:street":"W Main St",
    "iso:country":"US",
    "sg:address":"259 W Main St",
    "sg:city":"Ringtown",
    "sg:classifiers":[
        {
            "category":"Manufacturing",
            "subcategory":"Metals",
            "type":"Manufacturing & Wholesale Goods"
        }
    ],
    "sg:phone":"+1 570 889 3173",
    "sg:postcode":"17967",
    "sg:province":"PA",
    "sg:tags":[
        "trim",
        "frame",
        "door",
        "sash"
    ],
    "wof:name":"Wenco Of Pennsylvania",
    "wof:placetype":"venue"
},
  "geometry": {"coordinates":[-76.23650000000001,40.857493],"type":"Point"}
}