{
  "type": "Feature",
  "properties": {
    "addr:full":"133 W Broad St Shillington PA 19607",
    "addr:housenumber":"133",
    "addr:postcode":"19607",
    "addr:street":"W Broad St",
    "iso:country":"US",
    "sg:address":"133 W Broad St",
    "sg:city":"Shillington",
    "sg:classifiers":[
        {
            "category":"Organizations",
            "subcategory":"Religious Organization",
            "type":"Services"
        }
    ],
    "sg:phone":"+1 610 775 4461",
    "sg:postcode":"19607",
    "sg:province":"PA",
    "sg:tags":[
        "church"
    ],
    "wof:name":"St Herman's Orthodox Church",
    "wof:placetype":"venue"
},
  "geometry": {"coordinates":[-75.97286800000001,40.301767],"type":"Point"}
}