{
  "type": "Feature",
  "properties": {
    "iso:country":"US",
    "sg:address":"1307 Ligonier St",
    "sg:city":"Latrobe",
    "sg:classifiers":[
        {
            "category":"Home & Garden",
            "subcategory":"Household Appliances",
            "type":"Retail Goods"
        }
    ],
    "sg:phone":"+1 724 539 1988",
    "sg:postcode":"15650",
    "sg:province":"PA",
    "wof:name":"Payne & Dumont Appliance Parts",
    "wof:placetype":"venue"
},
  "geometry": {"coordinates":[-79.381884,40.314166],"type":"Point"}
}