{
  "type": "Feature",
  "properties": {
    "iso:country":"US",
    "sg:address":"2001 State St",
    "sg:city":"Harrisburg",
    "sg:classifiers":[
        {
            "category":"Professional",
            "subcategory":"Management & Consulting",
            "type":"Services"
        }
    ],
    "sg:phone":"+1 717 730 0956",
    "sg:postcode":"17103",
    "sg:province":"PA",
    "sg:tags":[
        "industrial",
        "equipment",
        "construction",
        "supply"
    ],
    "wof:name":"Cleveland Brothers Equipment",
    "wof:placetype":"venue"
},
  "geometry": {"coordinates":[-76.861389,40.273548],"type":"Point"}
}