{
  "type": "Feature",
  "properties": {
    "addr:full":"940 E Park Dr Harrisburg PA 17111",
    "addr:housenumber":"940",
    "addr:postcode":"17111",
    "addr:street":"E Park Dr",
    "iso:country":"US",
    "sg:address":"940 E Park Dr",
    "sg:city":"Harrisburg",
    "sg:classifiers":[
        {
            "category":"Professional",
            "subcategory":"Engineering",
            "type":"Services"
        }
    ],
    "sg:phone":"+1 717 545 5742",
    "sg:postcode":"17111",
    "sg:province":"PA",
    "sg:tags":[
        "engineer"
    ],
    "wof:name":"Dauphin Engineering Co",
    "wof:placetype":"venue"
},
  "geometry": {"coordinates":[-76.809466,40.267745],"type":"Point"}
}