{
  "type": "Feature",
  "properties": {
    "addr:full":"407 Railroad St Danville PA 17821",
    "addr:housenumber":"407",
    "addr:postcode":"17821",
    "addr:street":"Railroad St",
    "iso:country":"US",
    "sg:address":"407 Railroad St",
    "sg:city":"Danville",
    "sg:classifiers":[
        {
            "category":"Manufacturing",
            "subcategory":"Tools & Machinery",
            "type":"Manufacturing & Wholesale Goods"
        }
    ],
    "sg:phone":"+1   ",
    "sg:postcode":"17821",
    "sg:province":"PA",
    "sg:tags":[
        "repair",
        "wheelchair",
        "retail",
        "sales"
    ],
    "wof:name":"Handy Harolds Repair",
    "wof:placetype":"venue"
},
  "geometry": {"coordinates":[-76.608328,40.961242],"type":"Point"}
}