{
  "type": "Feature",
  "properties": {
    "iso:country":"US",
    "sg:address":"29 E South St",
    "sg:city":"Everett",
    "sg:classifiers":[
        {
            "category":"Restaurant",
            "type":"Food & Drink"
        }
    ],
    "sg:phone":"+1 814 652 0260",
    "sg:postcode":"15537",
    "sg:province":"PA",
    "wof:name":"Best Way Pizza",
    "wof:placetype":"venue"
},
  "geometry": {"coordinates":[-78.372501,40.010289],"type":"Point"}
}