{
  "type": "Feature",
  "properties": {
    "addr:full":"160 W Walnut St Allentown PA 18102",
    "addr:housenumber":"160",
    "addr:postcode":"18102",
    "addr:street":"W Walnut St",
    "iso:country":"US",
    "sg:address":"160 W Walnut St",
    "sg:city":"Allentown",
    "sg:classifiers":[
        {
            "category":"Manufacturing",
            "subcategory":"Metals",
            "type":"Manufacturing & Wholesale Goods"
        }
    ],
    "sg:phone":"+1 610 770 1100",
    "sg:postcode":"18102",
    "sg:province":"PA",
    "sg:tags":[
        "industrial",
        "valve"
    ],
    "wof:name":"Homestead Valve Co",
    "wof:placetype":"venue"
},
  "geometry": {"coordinates":[-75.4572,40.605613],"type":"Point"}
}