{
  "type": "Feature",
  "properties": {
    "iso:country":"US",
    "sg:address":"40 Hilton St",
    "sg:city":"Easton",
    "sg:classifiers":[
        {
            "category":"Wholesale",
            "subcategory":"Construction Materials",
            "type":"Manufacturing & Wholesale Goods"
        }
    ],
    "sg:phone":"+1   ",
    "sg:postcode":"18042",
    "sg:province":"PA",
    "wof:name":"Wholesale Insulation Materials",
    "wof:placetype":"venue"
},
  "geometry": {"coordinates":[-75.224557,40.670259],"type":"Point"}
}