{
  "type": "Feature",
  "properties": {
    "addr:full":"1018 Street Rd Ste 102 Southampton PA 18966",
    "addr:housenumber":"1018",
    "addr:postcode":"18966",
    "addr:street":"Street Rd Ste 102",
    "iso:country":"US",
    "sg:address":"1018 Street Rd Ste 102",
    "sg:city":"Southampton",
    "sg:classifiers":[
        {
            "category":"Insurance",
            "subcategory":"Hazard Insurance",
            "type":"Services"
        },
        {
            "category":"Insurance",
            "subcategory":"Health Insurance",
            "type":"Services"
        }
    ],
    "sg:phone":"+1 215 396 8972",
    "sg:postcode":"18966",
    "sg:province":"PA",
    "sg:tags":[
        "employee",
        "benefit"
    ],
    "wof:name":"Addval",
    "wof:placetype":"venue"
},
  "geometry": {"coordinates":[-75.035943,40.170133],"type":"Point"}
}