{
  "type": "Feature",
  "properties": {
    "addr:full":"6701 Frankford Ave Philadelphia PA 19135",
    "addr:housenumber":"6701",
    "addr:postcode":"19135",
    "addr:street":"Frankford Ave",
    "iso:country":"US",
    "sg:address":"6701 Frankford Ave",
    "sg:city":"Philadelphia",
    "sg:classifiers":[
        {
            "category":"Place Of Worship",
            "subcategory":"Church",
            "type":"Public Place"
        },
        {
            "category":"Place Of Worship",
            "type":"Public Place"
        }
    ],
    "sg:phone":"+1 215 333 4185",
    "sg:postcode":"19135",
    "sg:province":"PA",
    "sg:tags":[
        "churches-episcopal-anglican",
        "churches-episcopal"
    ],
    "wof:name":"Bishop Hoffman Reformed Episcopal Church",
    "wof:placetype":"venue"
},
  "geometry": {"coordinates":[-75.05284899999999,40.031841],"type":"Point"}
}