{
  "type": "Feature",
  "properties": {
    "addr:full":"635 Luzerne St Scranton PA 18504",
    "addr:housenumber":"635",
    "addr:postcode":"18504",
    "addr:street":"Luzerne St",
    "iso:country":"US",
    "sg:address":"635 Luzerne St",
    "sg:city":"Scranton",
    "sg:classifiers":[
        {
            "category":"Restaurant",
            "type":"Food & Drink"
        }
    ],
    "sg:phone":"+1 570 348 1904",
    "sg:postcode":"18504",
    "sg:province":"PA",
    "wof:name":"Roberto's Pizza",
    "wof:placetype":"venue"
},
  "geometry": {"coordinates":[-75.678252,41.405224],"type":"Point"}
}