{
  "type": "Feature",
  "properties": {
    "iso:country":"US",
    "sg:address":"200 Ross St",
    "sg:city":"Pittsburgh",
    "sg:classifiers":[
        {
            "category":"Government",
            "subcategory":"Fire Station",
            "type":"Public Place"
        }
    ],
    "sg:phone":"+1 412 255 2863",
    "sg:postcode":"15219",
    "sg:province":"PA",
    "sg:tags":[
        "department"
    ],
    "wof:name":"Pittsburgh Fire Prevention Div",
    "wof:placetype":"venue"
},
  "geometry": {"coordinates":[-79.99679399999999,40.437048],"type":"Point"}
}