{
  "type": "Feature",
  "properties": {
    "iso:country":"US",
    "sg:address":"4191 E Texas Rd",
    "sg:city":"Allentown",
    "sg:classifiers":[
        {
            "category":"Utilities",
            "type":"Services"
        }
    ],
    "sg:phone":"+1   ",
    "sg:postcode":"18103",
    "sg:province":"PA",
    "sg:tags":[
        "sanitary"
    ],
    "wof:name":"Snow Prowling",
    "wof:placetype":"venue"
},
  "geometry": {"coordinates":[-75.53346500000001,40.560488],"type":"Point"}
}