{
  "type": "Feature",
  "properties": {
    "iso:country":"US",
    "sg:address":"6323 Salem Park Cir",
    "sg:city":"Mechanicsburg",
    "sg:classifiers":[
        {
            "category":"Organizations",
            "subcategory":"Membership Organization",
            "type":"Services"
        }
    ],
    "sg:phone":"+1   ",
    "sg:postcode":"17050",
    "sg:province":"PA",
    "wof:name":"Literacy Empwerment Foundation",
    "wof:placetype":"venue"
},
  "geometry": {"coordinates":[-77.001569,40.243657],"type":"Point"}
}