{
  "type": "Feature",
  "properties": {
    "iso:country":"US",
    "sg:address":"17 Brilliant Ave",
    "sg:city":"Pittsburgh",
    "sg:classifiers":[
        {
            "category":"Banks & Credit Unions",
            "subcategory":"Bank",
            "type":"Services"
        }
    ],
    "sg:phone":"+1   ",
    "sg:postcode":"15215",
    "sg:province":"PA",
    "sg:tags":[
        "mortgage"
    ],
    "wof:name":"Mortgage Steel City",
    "wof:placetype":"venue"
},
  "geometry": {"coordinates":[-79.90103499999999,40.489238],"type":"Point"}
}