{
  "type": "Feature",
  "properties": {
    "iso:country":"US",
    "sg:address":"200 Shady Lane Dr",
    "sg:city":"Philipsburg",
    "sg:classifiers":[
        {
            "category":"Education",
            "subcategory":"Junior College",
            "type":"Public Place"
        }
    ],
    "sg:phone":"+1 814 342 7427",
    "sg:postcode":"16866",
    "sg:province":"PA",
    "sg:tags":[
        "technical",
        "institute"
    ],
    "wof:name":"South Hills Business School",
    "wof:placetype":"venue"
},
  "geometry": {"coordinates":[-78.209655,40.909362],"type":"Point"}
}