{
  "type": "Feature",
  "properties": {
    "addr:full":"4 E Germantown Pike Plymouth Meeting PA 19462",
    "addr:housenumber":"4",
    "addr:postcode":"19462",
    "addr:street":"E Germantown Pike",
    "iso:country":"US",
    "sg:address":"4 E Germantown Pike",
    "sg:city":"Plymouth Meeting",
    "sg:classifiers":[
        {
            "category":"Health Services",
            "subcategory":"Health Practitioner",
            "type":"Services"
        }
    ],
    "sg:phone":"+1   ",
    "sg:postcode":"19462",
    "sg:province":"PA",
    "wof:name":"Gerald & Margaret Cooke PHD PC",
    "wof:placetype":"venue"
},
  "geometry": {"coordinates":[-75.27831999999999,40.102456],"type":"Point"}
}