{
  "type": "Feature",
  "properties": {
    "addr:full":"320 Main St Irwin PA 15642",
    "addr:housenumber":"320",
    "addr:postcode":"15642",
    "addr:street":"Main St",
    "iso:country":"US",
    "sg:address":"320 Main St",
    "sg:city":"Irwin",
    "sg:classifiers":[
        {
            "category":"Professional",
            "subcategory":"Employment Agencies",
            "type":"Services"
        }
    ],
    "sg:phone":"+1 724 864 9512",
    "sg:postcode":"15642",
    "sg:province":"PA",
    "sg:tags":[
        "opportunity"
    ],
    "wof:name":"John Morrow & Assoc",
    "wof:placetype":"venue"
},
  "geometry": {"coordinates":[-79.710742,40.332688],"type":"Point"}
}