{
  "type": "Feature",
  "properties": {
    "addr:full":"2608 Columbia Ave Lancaster PA 17603",
    "addr:housenumber":"2608",
    "addr:postcode":"17603",
    "addr:street":"Columbia Ave",
    "iso:country":"US",
    "sg:address":"2608 Columbia Ave",
    "sg:city":"Lancaster",
    "sg:classifiers":[
        {
            "category":"Personal",
            "subcategory":"Beauty Salon",
            "type":"Services"
        }
    ],
    "sg:phone":"+1 717 299 5658",
    "sg:postcode":"17603",
    "sg:province":"PA",
    "wof:name":"Tres Chic",
    "wof:placetype":"venue"
},
  "geometry": {"coordinates":[-76.37667399999999,40.040133],"type":"Point"}
}