{
  "type": "Feature",
  "properties": {
    "iso:country":"US",
    "sg:address":"4520 Old Lincoln Hwy",
    "sg:city":"Feastervl Trvs",
    "sg:classifiers":[
        {
            "category":"Wholesale",
            "subcategory":"Hardware",
            "type":"Manufacturing & Wholesale Goods"
        },
        {
            "category":"Manufacturing",
            "subcategory":"Chemicals & Compounds",
            "type":"Manufacturing & Wholesale Goods"
        }
    ],
    "sg:phone":"+1 215 322 1016",
    "sg:postcode":"19053",
    "sg:province":"PA",
    "sg:tags":[
        "plumbing",
        "building",
        "s",
        "maintenance"
    ],
    "wof:name":"Active Chemical Corporation",
    "wof:placetype":"venue"
},
  "geometry": {"coordinates":[-74.956523,40.145694],"type":"Point"}
}