{
  "type": "Feature",
  "properties": {
    "addr:full":"1177 E 9th St Chester PA 19013",
    "addr:housenumber":"1177",
    "addr:postcode":"19013",
    "addr:street":"E 9Th St",
    "iso:country":"US",
    "sg:address":"1177 E 9th St",
    "sg:city":"Chester",
    "sg:classifiers":[
        {
            "category":"Building & Trades",
            "subcategory":"Construction",
            "type":"Services"
        }
    ],
    "sg:phone":"+1 610 872 0892",
    "sg:postcode":"19013",
    "sg:province":"PA",
    "sg:tags":[
        "paving",
        "contractor"
    ],
    "wof:name":"Joseph E Sucher & Sons Inc",
    "wof:placetype":"venue"
},
  "geometry": {"coordinates":[-75.344607,39.858689],"type":"Point"}
}