{
  "type": "Feature",
  "properties": {
    "iso:country":"US",
    "sg:address":"900 Eisenhower Blvd",
    "sg:city":"Swatara",
    "sg:classifiers":[
        {
            "category":"Personal",
            "subcategory":"Barber",
            "type":"Services"
        }
    ],
    "sg:phone":"+1 717 939 5950",
    "sg:postcode":"17111",
    "sg:province":"PA",
    "wof:name":"Barber Shop Connection",
    "wof:placetype":"venue"
},
  "geometry": {"coordinates":[-76.80556300000001,40.240309],"type":"Point"}
}