{
  "type": "Feature",
  "properties": {
    "iso:country":"US",
    "sg:address":"8106 Castor Ave",
    "sg:city":"Philadelphia",
    "sg:classifiers":[
        {
            "category":"Government",
            "subcategory":"Embassy",
            "type":"Public Place"
        },
        {
            "category":"Travel",
            "subcategory":"Travel Agent",
            "type":"Entertainment"
        }
    ],
    "sg:phone":"+1 215 342 7075",
    "sg:postcode":"19152",
    "sg:province":"PA",
    "sg:tags":[
        "information",
        "photo",
        "agency",
        "services-commercial",
        "visa",
        "passport"
    ],
    "wof:name":"Gmp Passport & Visa Services",
    "wof:placetype":"venue"
},
  "geometry": {"coordinates":[-75.05490399999999,40.063146],"type":"Point"}
}