{
  "type": "Feature",
  "properties": {
    "addr:full":"2900 Oley Turnpike Rd Reading PA 19606",
    "addr:postcode":"2900;19606",
    "addr:street":"Oley Turnpike Rd",
    "iso:country":"US",
    "sg:address":"2900 Oley Turnpike Rd",
    "sg:city":"Reading",
    "sg:classifiers":[
        {
            "category":"Real Estate",
            "subcategory":"Real Estate Operator",
            "type":"Services"
        }
    ],
    "sg:phone":"+1   ",
    "sg:postcode":"19606",
    "sg:province":"PA",
    "sg:tags":[
        "building",
        "apartment"
    ],
    "wof:name":"St Lawrence Garden Apts",
    "wof:placetype":"venue"
},
  "geometry": {"coordinates":[-75.87499099999999,40.326097],"type":"Point"}
}