{
  "type": "Feature",
  "properties": {
    "iso:country":"US",
    "sg:address":"138 Mifflin St",
    "sg:city":"West Mifflin",
    "sg:classifiers":[
        {
            "category":"Freight",
            "type":"Transportation"
        }
    ],
    "sg:phone":"+1   ",
    "sg:postcode":"15122",
    "sg:province":"PA",
    "sg:tags":[
        "dock",
        "boat"
    ],
    "wof:name":"Cessna Logans Ferry Marina",
    "wof:placetype":"venue"
},
  "geometry": {"coordinates":[-79.85828100000001,40.366321],"type":"Point"}
}