{
  "type": "Feature",
  "properties": {
    "addr:full":"5231 Market St Philadelphia PA 19139",
    "addr:housenumber":"5231",
    "addr:postcode":"19139",
    "addr:street":"Market St",
    "iso:country":"US",
    "sg:address":"5231 Market St",
    "sg:city":"Philadelphia",
    "sg:classifiers":[
        {
            "category":"Bars & Pubs",
            "type":"Food & Drink"
        }
    ],
    "sg:phone":"+1   ",
    "sg:postcode":"19139",
    "sg:province":"PA",
    "sg:tags":[
        "drinking"
    ],
    "wof:name":"Corral",
    "wof:placetype":"venue"
},
  "geometry": {"coordinates":[-75.225386,39.960111],"type":"Point"}
}