{
  "type": "Feature",
  "properties": {
    "iso:country":"US",
    "sg:address":"103 N 7th St",
    "sg:city":"Stroudsburg",
    "sg:classifiers":[
        {
            "category":"Social Services",
            "type":"Services"
        }
    ],
    "sg:phone":"+1 570 476 7704",
    "sg:postcode":"18360",
    "sg:province":"PA",
    "sg:tags":[
        "counseling"
    ],
    "wof:name":"Forensic Consulting Associates",
    "wof:placetype":"venue"
},
  "geometry": {"coordinates":[-75.19488200000001,40.986403],"type":"Point"}
}