{
  "type": "Feature",
  "properties": {
    "iso:country":"US",
    "sg:address":"398 Airport Rd",
    "sg:city":"Indiana",
    "sg:classifiers":[
        {
            "category":"Airport",
            "type":"Transportation"
        }
    ],
    "sg:phone":"+1 724 463 3883",
    "sg:postcode":"15701",
    "sg:province":"PA",
    "wof:name":"Indiana County Airport Inc",
    "wof:placetype":"venue"
},
  "geometry": {"coordinates":[-79.103594,40.635837],"type":"Point"}
}