{
  "type": "Feature",
  "properties": {
    "iso:country":"US",
    "sg:address":"473 Central Ave",
    "sg:city":"Horsham",
    "sg:classifiers":[
        {
            "category":"Retail",
            "subcategory":"Auto Repair",
            "type":"Services"
        }
    ],
    "sg:phone":"+1 215 672 5040",
    "sg:postcode":"19044",
    "sg:province":"PA",
    "sg:tags":[
        "truck"
    ],
    "wof:name":"D E Tennett & Sons",
    "wof:placetype":"venue"
},
  "geometry": {"coordinates":[-75.131844,40.180012],"type":"Point"}
}