{
  "type": "Feature",
  "properties": {
    "iso:country":"US",
    "sg:address":"603 County Line",
    "sg:city":"Huntingdon Valley",
    "sg:classifiers":[
        {
            "category":"Professional",
            "subcategory":"Computer Services",
            "type":"Services"
        }
    ],
    "sg:phone":"+1 877 548 3001",
    "sg:postcode":"19006",
    "sg:province":"PA",
    "sg:tags":[
        "help-desk-software",
        "ecommerce-solutions",
        "customer-service-software",
        "live-chat-software",
        "website-chat",
        "issue-tracking",
        "knowledge-base-management"
    ],
    "sg:website":"http://www.livehelpnow.net",
    "wof:name":"LiveHelpNow",
    "wof:placetype":"venue"
},
  "geometry": {"coordinates":[-75.036687,40.150732],"type":"Point"}
}