{
  "type": "Feature",
  "properties": {
    "iso:country":"US",
    "sg:address":"18 N Lansdowne Ave",
    "sg:city":"Lansdowne",
    "sg:classifiers":[
        {
            "category":"Professional",
            "subcategory":"Lawyer & Legal Services",
            "type":"Services"
        }
    ],
    "sg:phone":"+1 610 622 3660",
    "sg:postcode":"19050",
    "sg:province":"PA",
    "sg:tags":[
        "attorney"
    ],
    "wof:name":"Traffic Law Ctr",
    "wof:placetype":"venue"
},
  "geometry": {"coordinates":[-75.272499,39.939142],"type":"Point"}
}