{
  "type": "Feature",
  "properties": {
    "addr:full":"2301 Woodward St Philadelphia PA 19115",
    "addr:housenumber":"2301",
    "addr:postcode":"19115",
    "addr:street":"Woodward St",
    "iso:country":"US",
    "sg:address":"2301 Woodward St",
    "sg:city":"Philadelphia",
    "sg:classifiers":[
        {
            "category":"Real Estate",
            "subcategory":"Real Estate Operator",
            "type":"Services"
        }
    ],
    "sg:phone":"+1   ",
    "sg:postcode":"19115",
    "sg:province":"PA",
    "sg:tags":[
        "building",
        "apartment"
    ],
    "wof:name":"Evergreen Park Manor Apts",
    "wof:placetype":"venue"
},
  "geometry": {"coordinates":[-75.03917199999999,40.071757],"type":"Point"}
}