{
  "type": "Feature",
  "properties": {
    "iso:country":"US",
    "sg:address":"813 Burbridge Ave",
    "sg:city":"Mc Keesport",
    "sg:classifiers":[
        {
            "category":"Organizations",
            "subcategory":"Community Association",
            "type":"Services"
        }
    ],
    "sg:phone":"+1   ",
    "sg:postcode":"15133",
    "sg:province":"PA",
    "wof:name":"Optimist International",
    "wof:placetype":"venue"
},
  "geometry": {"coordinates":[-79.864806,40.330904],"type":"Point"}
}