{
  "type": "Feature",
  "properties": {
    "addr:full":"300 W Main St Monongahela PA 15063",
    "addr:housenumber":"300",
    "addr:postcode":"15063",
    "addr:street":"W Main St",
    "iso:country":"US",
    "sg:address":"300 W Main St",
    "sg:city":"Monongahela",
    "sg:classifiers":[
        {
            "category":"Banks & Credit Unions",
            "subcategory":"Bank",
            "type":"Services"
        }
    ],
    "sg:phone":"+1 724 258 3500",
    "sg:postcode":"15063",
    "sg:province":"PA",
    "wof:name":"Pnc Bank",
    "wof:placetype":"venue"
},
  "geometry": {"coordinates":[-79.925499,40.202702],"type":"Point"}
}