{
  "type": "Feature",
  "properties": {
    "iso:country":"US",
    "sg:address":"5 E 34th St",
    "sg:city":"Erie",
    "sg:classifiers":[
        {
            "category":"Banks & Credit Unions",
            "subcategory":"Bank",
            "type":"Services"
        }
    ],
    "sg:phone":"+1   ",
    "sg:postcode":"16504",
    "sg:province":"PA",
    "sg:tags":[
        "federal"
    ],
    "wof:name":"Erie Cy Emplyees Federal Cr Un",
    "wof:placetype":"venue"
},
  "geometry": {"coordinates":[-80.068083,42.106133],"type":"Point"}
}