{
  "type": "Feature",
  "properties": {
    "addr:full":"526 N Keyser Ave Scranton PA 18504",
    "addr:housenumber":"526",
    "addr:postcode":"18504",
    "addr:street":"N Keyser Ave",
    "iso:country":"US",
    "sg:address":"526 N Keyser Ave",
    "sg:city":"Scranton",
    "sg:classifiers":[
        {
            "category":"Shopping",
            "subcategory":"Gifts & Souvenirs",
            "type":"Retail Goods"
        }
    ],
    "sg:phone":"+1 570 961 2835",
    "sg:postcode":"18504",
    "sg:province":"PA",
    "sg:tags":[
        "basket"
    ],
    "wof:name":"Precious Moments Gift Baskets",
    "wof:placetype":"venue"
},
  "geometry": {"coordinates":[-75.694627,41.426778],"type":"Point"}
}