{
  "type": "Feature",
  "properties": {
    "addr:full":"304 Shaffner Ave Brownsville PA 15417",
    "addr:housenumber":"304",
    "addr:postcode":"15417",
    "addr:street":"Shaffner Ave",
    "iso:country":"US",
    "sg:address":"304 Shaffner Ave",
    "sg:city":"Brownsville",
    "sg:classifiers":[
        {
            "category":"Organizations",
            "subcategory":"Religious Organization",
            "type":"Services"
        }
    ],
    "sg:phone":"+1   ",
    "sg:postcode":"15417",
    "sg:province":"PA",
    "sg:tags":[
        "catholic",
        "church"
    ],
    "wof:name":"St Peters Church",
    "wof:placetype":"venue"
},
  "geometry": {"coordinates":[-79.876008,40.023678],"type":"Point"}
}