{
  "type": "Feature",
  "properties": {
    "iso:country":"US",
    "sg:address":"384 Park St",
    "sg:city":"Uniontown",
    "sg:classifiers":[
        {
            "category":"Building & Trades",
            "subcategory":"Construction",
            "type":"Services"
        }
    ],
    "sg:phone":"+1   ",
    "sg:postcode":"15401",
    "sg:province":"PA",
    "sg:tags":[
        "excavating",
        "contractor"
    ],
    "wof:name":"R B Provance Construction Co",
    "wof:placetype":"venue"
},
  "geometry": {"coordinates":[-79.67917300000001,39.921492],"type":"Point"}
}