{
  "type": "Feature",
  "properties": {
    "iso:country":"US",
    "sg:address":"1275 Glenlivet Dr Suite 100",
    "sg:city":"Allentown",
    "sg:classifiers":[
        {
            "category":"Professional",
            "subcategory":"Accounting & Tax Preparation",
            "type":"Services"
        },
        {
            "category":"Professional",
            "subcategory":"Lawyer & Legal Services",
            "type":"Services"
        }
    ],
    "sg:phone":"+1 484 866 8790",
    "sg:postcode":"18106",
    "sg:province":"PA",
    "sg:tags":[
        "attorney",
        "reporting",
        "representative",
        "taxes-consultants"
    ],
    "sg:website":"http://www.wallandassociates.net",
    "wof:name":"E Kenneth Wall PC",
    "wof:placetype":"venue"
},
  "geometry": {"coordinates":[-75.628027,40.59065],"type":"Point"}
}