{
  "type": "Feature",
  "properties": {
    "addr:full":"258 Tomkenn Rd Wynnewood PA 19096",
    "addr:housenumber":"258",
    "addr:postcode":"19096",
    "addr:street":"Tomkenn Rd",
    "iso:country":"US",
    "sg:address":"258 Tomkenn Rd",
    "sg:city":"Wynnewood",
    "sg:classifiers":[
        {
            "category":"Shopping",
            "subcategory":"Gifts & Souvenirs",
            "type":"Retail Goods"
        }
    ],
    "sg:phone":"+1 610 642 9044",
    "sg:postcode":"19096",
    "sg:province":"PA",
    "sg:tags":[
        "basket",
        "parcel"
    ],
    "sg:website":"www.cathysbraidedbasket.com",
    "wof:name":"Cathy's Braided Basket",
    "wof:placetype":"venue"
},
  "geometry": {"coordinates":[-75.27563000000001,39.989654],"type":"Point"}
}