{
  "type": "Feature",
  "properties": {
    "iso:country":"US",
    "sg:address":"1801 Union Blvd.",
    "sg:city":"Allentown",
    "sg:classifiers":[
        {
            "category":"Personal",
            "type":"Services"
        }
    ],
    "sg:phone":"+1 610 264 0681",
    "sg:postcode":"18109",
    "sg:province":"PA",
    "sg:tags":[
        "home"
    ],
    "sg:website":"www.apwagner.com/index.php?main_...",
    "wof:name":"AP Wagner Appliance Parts",
    "wof:placetype":"venue"
},
  "geometry": {"coordinates":[-75.429523,40.625431],"type":"Point"}
}