{
  "type": "Feature",
  "properties": {
    "iso:country":"US",
    "sg:address":"1439 Snyder Ave",
    "sg:city":"Philadelphia",
    "sg:classifiers":[
        {
            "category":"Bars & Pubs",
            "type":"Food & Drink"
        }
    ],
    "sg:phone":"+1 215 468 4482",
    "sg:postcode":"19145",
    "sg:province":"PA",
    "sg:tags":[
        "drinking"
    ],
    "wof:name":"Cianno's Cafe Sportsbar",
    "wof:placetype":"venue"
},
  "geometry": {"coordinates":[-75.1713,39.924656],"type":"Point"}
}