{
  "type": "Feature",
  "properties": {
    "iso:country":"US",
    "sg:address":"100 Pine St",
    "sg:city":"Darby",
    "sg:classifiers":[
        {
            "category":"Real Estate",
            "subcategory":"Architect",
            "type":"Services"
        }
    ],
    "sg:phone":"+1 215 928 8930",
    "sg:postcode":"19023",
    "sg:province":"PA",
    "wof:name":"Ambric Technology Corporation",
    "wof:placetype":"venue"
},
  "geometry": {"coordinates":[-75.264971,39.915547],"type":"Point"}
}