{
  "type": "Feature",
  "properties": {
    "addr:full":"221 43rd St Pittsburgh PA 15201",
    "addr:housenumber":"221",
    "addr:postcode":"15201",
    "addr:street":"43Rd St",
    "iso:country":"US",
    "sg:address":"221 43rd St",
    "sg:city":"Pittsburgh",
    "sg:classifiers":[
        {
            "category":"Organizations",
            "subcategory":"Religious Organization",
            "type":"Services"
        }
    ],
    "sg:phone":"+1 412 621 2155",
    "sg:postcode":"15201",
    "sg:province":"PA",
    "wof:name":"New Bethel Baptist Church",
    "wof:placetype":"venue"
},
  "geometry": {"coordinates":[-79.96033799999999,40.470632],"type":"Point"}
}