{
  "type": "Feature",
  "properties": {
    "addr:full":"2548 Brownsville Rd Pittsburgh PA 15210",
    "addr:housenumber":"2548",
    "addr:postcode":"15210",
    "addr:street":"Brownsville Rd",
    "iso:country":"US",
    "sg:address":"2548 Brownsville Rd",
    "sg:city":"Pittsburgh",
    "sg:classifiers":[
        {
            "category":"Shopping",
            "subcategory":"Florist",
            "type":"Retail Goods"
        }
    ],
    "sg:phone":"+1 412 884 6670",
    "sg:postcode":"15210",
    "sg:province":"PA",
    "wof:name":"Hess' Floral Shop",
    "wof:placetype":"venue"
},
  "geometry": {"coordinates":[-79.978758,40.385585],"type":"Point"}
}