{
  "type": "Feature",
  "properties": {
    "addr:full":"723 State Rte 611 Bartonsville PA 18343",
    "addr:housenumber":"723",
    "addr:postcode":"18343",
    "addr:street":"State Rte 611",
    "iso:country":"US",
    "sg:address":"723 State Rte 611",
    "sg:city":"Bartonsville",
    "sg:classifiers":[
        {
            "category":"Insurance",
            "subcategory":"Insurance Agent",
            "type":"Services"
        }
    ],
    "sg:phone":"+1   ",
    "sg:postcode":"18343",
    "sg:province":"PA",
    "wof:name":"Benninger Insurance Agency",
    "wof:placetype":"venue"
},
  "geometry": {"coordinates":[-75.128686,40.865254],"type":"Point"}
}