{
  "type": "Feature",
  "properties": {
    "iso:country":"US",
    "sg:address":"626 Williams Grove Rd",
    "sg:city":"Mechanicsburg",
    "sg:classifiers":[
        {
            "category":"Place Of Worship",
            "subcategory":"Church",
            "type":"Public Place"
        },
        {
            "category":"Place Of Worship",
            "type":"Public Place"
        }
    ],
    "sg:phone":"+1 717 766 7931",
    "sg:postcode":"17055",
    "sg:province":"PA",
    "sg:tags":[
        "testament",
        "christ-new",
        "churches-church",
        "christ"
    ],
    "wof:name":"St Pauls United Church Of Christ",
    "wof:placetype":"venue"
},
  "geometry": {"coordinates":[-77.017,40.200061],"type":"Point"}
}