{
  "type": "Feature",
  "properties": {
    "iso:country":"US",
    "sg:address":"1 Park Ln",
    "sg:city":"Douglassville",
    "sg:classifiers":[
        {
            "category":"Health Services",
            "subcategory":"Doctor",
            "type":"Services"
        }
    ],
    "sg:phone":"+1   ",
    "sg:postcode":"19518",
    "sg:province":"PA",
    "sg:tags":[
        "surgeon",
        "oral"
    ],
    "wof:name":"Oral Surgery and Maxel Facial",
    "wof:placetype":"venue"
},
  "geometry": {"coordinates":[-75.73768699999999,40.263625],"type":"Point"}
}