{
  "type": "Feature",
  "properties": {
    "iso:country":"US",
    "sg:address":"451 Aberdeen Dr",
    "sg:city":"Somerset",
    "sg:classifiers":[
        {
            "category":"Sports & Exercise",
            "subcategory":"Gym",
            "type":"Entertainment"
        }
    ],
    "sg:phone":"+1 814 445 4566",
    "sg:postcode":"15501",
    "sg:province":"PA",
    "sg:tags":[
        "club",
        "health",
        "studio",
        "gymnasium"
    ],
    "wof:name":"Somerset Court Sports",
    "wof:placetype":"venue"
},
  "geometry": {"coordinates":[-79.098123,40.005088],"type":"Point"}
}