{
  "type": "Feature",
  "properties": {
    "addr:full":"30 E Main St Ephrata PA 17522",
    "addr:housenumber":"30",
    "addr:postcode":"17522",
    "addr:street":"E Main St",
    "iso:country":"US",
    "sg:address":"30 E Main St",
    "sg:city":"Ephrata",
    "sg:classifiers":[
        {
            "category":"Utilities",
            "subcategory":"Mobile Phone",
            "type":"Services"
        }
    ],
    "sg:phone":"+1 717 738 7673",
    "sg:postcode":"17522",
    "sg:province":"PA",
    "sg:tags":[
        "telephone",
        "cellular"
    ],
    "wof:name":"D & E Tele Store",
    "wof:placetype":"venue"
},
  "geometry": {"coordinates":[-76.176788,40.178401],"type":"Point"}
}