{
  "type": "Feature",
  "properties": {
    "addr:full":"21 W Ferry St New Hope PA 18938",
    "addr:housenumber":"21",
    "addr:postcode":"18938",
    "addr:street":"W Ferry St",
    "iso:country":"US",
    "sg:address":"21 W Ferry St",
    "sg:city":"New Hope",
    "sg:classifiers":[
        {
            "category":"Shopping",
            "subcategory":"Used Merchandise",
            "type":"Retail Goods"
        }
    ],
    "sg:phone":"+1   ",
    "sg:postcode":"18938",
    "sg:province":"PA",
    "sg:tags":[
        "antique",
        "shop"
    ],
    "wof:name":"Sally Goodman Antq & Interiors",
    "wof:placetype":"venue"
},
  "geometry": {"coordinates":[-74.952057,40.363173],"type":"Point"}
}