{
  "type": "Feature",
  "properties": {
    "iso:country":"US",
    "sg:address":"117 E Park St",
    "sg:city":"Rochester",
    "sg:classifiers":[
        {
            "category":"Education",
            "subcategory":"School",
            "type":"Public Place"
        }
    ],
    "sg:phone":"+1 724 775 1676",
    "sg:postcode":"15074",
    "sg:province":"PA",
    "wof:name":"Samuel A Pasco School",
    "wof:placetype":"venue"
},
  "geometry": {"coordinates":[-80.285377,40.7028],"type":"Point"}
}