{
  "type": "Feature",
  "properties": {
    "addr:full":"1009 Clifton Ave Darby PA 19023",
    "addr:housenumber":"1009",
    "addr:postcode":"19023",
    "addr:street":"Clifton Ave",
    "iso:country":"US",
    "sg:address":"1009 Clifton Ave",
    "sg:city":"Darby",
    "sg:classifiers":[
        {
            "category":"Professional",
            "type":"Services"
        }
    ],
    "sg:phone":"+1   ",
    "sg:postcode":"19023",
    "sg:province":"PA",
    "wof:name":"Keyboys Inc",
    "wof:placetype":"venue"
},
  "geometry": {"coordinates":[-75.28290699999999,39.917543],"type":"Point"}
}