{
  "type": "Feature",
  "properties": {
    "addr:full":"2294 N Penn Rd Hatfield PA 19440",
    "addr:housenumber":"2294",
    "addr:postcode":"19440",
    "addr:street":"N Penn Rd",
    "iso:country":"US",
    "sg:address":"2294 N Penn Rd",
    "sg:city":"Hatfield",
    "sg:classifiers":[
        {
            "category":"Manufacturing",
            "subcategory":"Electronics",
            "type":"Manufacturing & Wholesale Goods"
        }
    ],
    "sg:phone":"+1   ",
    "sg:postcode":"19440",
    "sg:province":"PA",
    "sg:tags":[
        "military",
        "mfg",
        "machinery",
        "for",
        "semi"
    ],
    "wof:name":"Penn North Technology",
    "wof:placetype":"venue"
},
  "geometry": {"coordinates":[-75.284918,40.290359],"type":"Point"}
}