{
  "type": "Feature",
  "properties": {
    "iso:country":"US",
    "sg:address":"300 Church St",
    "sg:city":"Huntingdon",
    "sg:classifiers":[
        {
            "category":"Government",
            "subcategory":"Court House",
            "type":"Public Place"
        },
        {
            "category":"Government",
            "subcategory":"Office",
            "type":"Public Place"
        }
    ],
    "sg:phone":"+1 814 643 2490",
    "sg:postcode":"16652",
    "sg:province":"PA",
    "sg:tags":[
        "justice",
        "parish",
        "government-county"
    ],
    "wof:name":"Huntingdon County Prison",
    "wof:placetype":"venue"
},
  "geometry": {"coordinates":[-78.008282,40.485892],"type":"Point"}
}