{
  "type": "Feature",
  "properties": {
    "addr:full":"314 E Filbert St Lancaster PA 17603",
    "addr:housenumber":"314",
    "addr:postcode":"17603",
    "addr:street":"E Filbert St",
    "iso:country":"US",
    "sg:address":"314 E Filbert St",
    "sg:city":"Lancaster",
    "sg:classifiers":[
        {
            "category":"Retail",
            "subcategory":"Auto Repair",
            "type":"Services"
        }
    ],
    "sg:phone":"+1 717 509 5157",
    "sg:postcode":"17603",
    "sg:province":"PA",
    "sg:tags":[
        "repairing",
        "automobile"
    ],
    "wof:name":"G & D Towing & Auto Repair",
    "wof:placetype":"venue"
},
  "geometry": {"coordinates":[-76.31022,40.032959],"type":"Point"}
}