{
  "type": "Feature",
  "properties": {
    "addr:full":"5779 Library Rd Bethel Park PA 15102",
    "addr:housenumber":"5779",
    "addr:postcode":"15102",
    "addr:street":"Library Rd",
    "iso:country":"US",
    "sg:address":"5779 Library Rd",
    "sg:city":"Bethel Park",
    "sg:classifiers":[
        {
            "category":"Home & Garden",
            "subcategory":"Hardware",
            "type":"Retail Goods"
        }
    ],
    "sg:phone":"+1 412 835 5780",
    "sg:postcode":"15102",
    "sg:province":"PA",
    "sg:tags":[
        "store"
    ],
    "wof:name":"Evey Hardware Co",
    "wof:placetype":"venue"
},
  "geometry": {"coordinates":[-80.032799,40.311298],"type":"Point"}
}