{
  "type": "Feature",
  "properties": {
    "iso:country":"US",
    "sg:address":"3005 Trinity Ct",
    "sg:city":"Chester Springs",
    "sg:classifiers":[
        {
            "category":"Professional",
            "subcategory":"Management & Consulting",
            "type":"Services"
        }
    ],
    "sg:phone":"+1 610 594 4744",
    "sg:postcode":"19425",
    "sg:province":"PA",
    "sg:tags":[
        "consultant",
        "business"
    ],
    "wof:name":"Reno & Assoc",
    "wof:placetype":"venue"
},
  "geometry": {"coordinates":[-75.643681,40.06674],"type":"Point"}
}