{
  "type": "Feature",
  "properties": {
    "iso:country":"US",
    "sg:address":"4107 Meadow Ln",
    "sg:city":"Newtown Square",
    "sg:classifiers":[
        {
            "category":"Insurance",
            "subcategory":"Insurance Agent",
            "type":"Services"
        }
    ],
    "sg:phone":"+1 610 356 3332",
    "sg:postcode":"19073",
    "sg:province":"PA",
    "wof:name":"Nebsco Financial Svc LTD",
    "wof:placetype":"venue"
},
  "geometry": {"coordinates":[-75.432091,39.996387],"type":"Point"}
}