{
  "type": "Feature",
  "properties": {
    "iso:country":"US",
    "sg:address":"1 Country Ln",
    "sg:city":"Douglassville",
    "sg:classifiers":[
        {
            "category":"Wholesale",
            "subcategory":"Medical Equipment & Supplies",
            "type":"Manufacturing & Wholesale Goods"
        }
    ],
    "sg:phone":"+1 610 689 4540",
    "sg:postcode":"19518",
    "sg:province":"PA",
    "sg:tags":[
        "x",
        "apparatus"
    ],
    "wof:name":"Atps Inc",
    "wof:placetype":"venue"
},
  "geometry": {"coordinates":[-75.743994,40.305171],"type":"Point"}
}