{
  "type": "Feature",
  "properties": {
    "iso:country":"US",
    "sg:address":"214 Rodi Rd",
    "sg:city":"Pittsburgh",
    "sg:classifiers":[
        {
            "category":"Autos & Motor Vehicles",
            "subcategory":"Fuel & Gas Station",
            "type":"Retail Goods"
        }
    ],
    "sg:phone":"+1 412 242 6428",
    "sg:postcode":"15235",
    "sg:province":"PA",
    "sg:tags":[
        "station",
        "gasoline",
        "oil"
    ],
    "wof:name":"Anlauf's Atlantic",
    "wof:placetype":"venue"
},
  "geometry": {"coordinates":[-79.824181,40.463377],"type":"Point"}
}