{
  "type": "Feature",
  "properties": {
    "iso:country":"US",
    "sg:address":"3812 Market St",
    "sg:city":"Camp Hill",
    "sg:classifiers":[
        {
            "category":"Social Services",
            "type":"Services"
        }
    ],
    "sg:phone":"+1   ",
    "sg:postcode":"17011",
    "sg:province":"PA",
    "wof:name":"Mitch Smith Lsw",
    "wof:placetype":"venue"
},
  "geometry": {"coordinates":[-76.94929999999999,40.238689],"type":"Point"}
}