{
  "type": "Feature",
  "properties": {
    "iso:country":"US",
    "sg:address":"1708 Pheasant Rd",
    "sg:city":"Norristown",
    "sg:classifiers":[
        {
            "category":"Restaurant",
            "type":"Food & Drink"
        }
    ],
    "sg:phone":"+1   ",
    "sg:postcode":"19403",
    "sg:province":"PA",
    "sg:tags":[
        "eating"
    ],
    "wof:name":"Rumours Cafe Inc",
    "wof:placetype":"venue"
},
  "geometry": {"coordinates":[-75.375557,40.121432],"type":"Point"}
}