{
  "type": "Feature",
  "properties": {
    "iso:country":"US",
    "sg:address":"23 Delaware St",
    "sg:city":"Wilkes Barre",
    "sg:classifiers":[
        {
            "category":"Personal",
            "subcategory":"Beauty Salon",
            "type":"Services"
        }
    ],
    "sg:phone":"+1 570 824 7888",
    "sg:postcode":"18705",
    "sg:province":"PA",
    "wof:name":"Sandy Browning Beauty Salon",
    "wof:placetype":"venue"
},
  "geometry": {"coordinates":[-75.84580699999999,41.277628],"type":"Point"}
}