{
  "type": "Feature",
  "properties": {
    "addr:full":"525 Delaware Ave Rochester PA 15074",
    "addr:housenumber":"525",
    "addr:postcode":"15074",
    "addr:street":"Delaware Ave",
    "iso:country":"US",
    "sg:address":"525 Delaware Ave",
    "sg:city":"Rochester",
    "sg:classifiers":[
        {
            "category":"Retail",
            "subcategory":"Car Wash",
            "type":"Services"
        }
    ],
    "sg:phone":"+1 724 728 7070",
    "sg:postcode":"15074",
    "sg:province":"PA",
    "sg:tags":[
        "carwash"
    ],
    "wof:name":"Inman Car Wash",
    "wof:placetype":"venue"
},
  "geometry": {"coordinates":[-80.291229,40.704815],"type":"Point"}
}