{
  "type": "Feature",
  "properties": {
    "addr:full":"1410 Hanover Ave Allentown PA 18109",
    "addr:housenumber":"1410",
    "addr:postcode":"18109",
    "addr:street":"Hanover Ave",
    "iso:country":"US",
    "sg:address":"1410 Hanover Ave",
    "sg:city":"Allentown",
    "sg:classifiers":[
        {
            "category":"Restaurant",
            "type":"Food & Drink"
        }
    ],
    "sg:phone":"+1 610 437 2208",
    "sg:postcode":"18109",
    "sg:province":"PA",
    "sg:tags":[
        "buffet",
        "chinese",
        "pan",
        "asian"
    ],
    "wof:name":"New Century Buffet",
    "wof:placetype":"venue"
},
  "geometry": {"coordinates":[-75.43367600000001,40.618383],"type":"Point"}
}