{
  "type": "Feature",
  "properties": {
    "iso:country":"US",
    "sg:address":"638 Powder Mill Hollow Rd",
    "sg:city":"Boyertown",
    "sg:classifiers":[
        {
            "category":"Building & Trades",
            "subcategory":"Construction",
            "type":"Services"
        }
    ],
    "sg:phone":"+1 610 369 0003",
    "sg:postcode":"19512",
    "sg:province":"PA",
    "sg:tags":[
        "home",
        "builder",
        "general",
        "contractor"
    ],
    "wof:name":"Lance-Berk Construction Co",
    "wof:placetype":"venue"
},
  "geometry": {"coordinates":[-75.68069199999999,40.340065],"type":"Point"}
}