{
  "type": "Feature",
  "properties": {
    "addr:full":"1 Hollow Crest Rd Tunkhannock PA 18657",
    "addr:housenumber":"1",
    "addr:postcode":"18657",
    "addr:street":"Hollow Crest Rd",
    "iso:country":"US",
    "sg:address":"1 Hollow Crest Rd",
    "sg:city":"Tunkhannock",
    "sg:classifiers":[
        {
            "category":"Government",
            "subcategory":"Office",
            "type":"Public Place"
        },
        {
            "category":"Organizations",
            "subcategory":"Community Association",
            "type":"Services"
        }
    ],
    "sg:phone":"+1 570 836 2589",
    "sg:postcode":"18657",
    "sg:province":"PA",
    "sg:tags":[
        "county",
        "environmental",
        "org"
    ],
    "wof:name":"Wyoming Cnty Conservation Dst",
    "wof:placetype":"venue"
},
  "geometry": {"coordinates":[-75.9751,41.58069],"type":"Point"}
}