{
  "type": "Feature",
  "properties": {
    "iso:country":"US",
    "sg:address":"3448 Old York Rd",
    "sg:city":"Philadelphia",
    "sg:classifiers":[
        {
            "category":"Building & Trades",
            "subcategory":"Construction",
            "type":"Services"
        }
    ],
    "sg:phone":"+1   ",
    "sg:postcode":"19140",
    "sg:province":"PA",
    "sg:tags":[
        "roofing",
        "mfg",
        "system",
        "contractor"
    ],
    "wof:name":"North American Roofers Inc",
    "wof:placetype":"venue"
},
  "geometry": {"coordinates":[-75.148377,40.005564],"type":"Point"}
}