{
  "type": "Feature",
  "properties": {
    "iso:country":"US",
    "sg:address":"825 Sycamore Ave",
    "sg:city":"Croydon",
    "sg:classifiers":[
        {
            "category":"Professional",
            "subcategory":"Engineering",
            "type":"Services"
        }
    ],
    "sg:phone":"+1   ",
    "sg:postcode":"19021",
    "sg:province":"PA",
    "sg:tags":[
        "equipment",
        "electrical",
        "electric"
    ],
    "wof:name":"Burlington Electrical Tstg Co",
    "wof:placetype":"venue"
},
  "geometry": {"coordinates":[-74.905157,40.091869],"type":"Point"}
}