{
  "type": "Feature",
  "properties": {
    "addr:full":"400 Highpoint Dr Chalfont PA 18914",
    "addr:housenumber":"400",
    "addr:postcode":"18914",
    "addr:street":"Highpoint Dr",
    "iso:country":"US",
    "sg:address":"400 Highpoint Dr",
    "sg:city":"Chalfont",
    "sg:classifiers":[
        {
            "category":"Manufacturing",
            "subcategory":"Tools & Machinery",
            "type":"Manufacturing & Wholesale Goods"
        }
    ],
    "sg:phone":"+1 215 822 4300",
    "sg:postcode":"18914",
    "sg:province":"PA",
    "sg:tags":[
        "equipment",
        "conveyor",
        "conveying"
    ],
    "sg:website":"www.fmcagv.com",
    "wof:name":"FMC Technologies Inc",
    "wof:placetype":"venue"
},
  "geometry": {"coordinates":[-75.21499799999999,40.265319],"type":"Point"}
}