{
  "type": "Feature",
  "properties": {
    "iso:country":"US",
    "sg:address":"875 877 E Baltimore Pike",
    "sg:city":"Kennett Square",
    "sg:classifiers":[
        {
            "category":"Restaurant",
            "type":"Food & Drink"
        }
    ],
    "sg:menulink":"http://www.allmenus.com/pa/east-marlborough/123128-quiznos-sub/menu/",
    "sg:phone":"+1 610 444 2606",
    "sg:postcode":"19348",
    "sg:province":"PA",
    "sg:tags":[
        "wrap",
        "american",
        "sandwich"
    ],
    "wof:name":"Quiznos Sub",
    "wof:placetype":"venue"
},
  "geometry": {"coordinates":[-75.679241,39.863116],"type":"Point"}
}