{
  "type": "Feature",
  "properties": {
    "addr:full":"2315 Old Philadelphia Pike Lancaster PA 17602",
    "addr:housenumber":"2315",
    "addr:postcode":"17602",
    "addr:street":"Old Philadelphia Pike",
    "iso:country":"US",
    "sg:address":"2315 Old Philadelphia Pike",
    "sg:city":"Lancaster",
    "sg:classifiers":[
        {
            "category":"Travel",
            "subcategory":"Travel Agent",
            "type":"Entertainment"
        }
    ],
    "sg:phone":"+1 717 394 2821",
    "sg:postcode":"17602",
    "sg:province":"PA",
    "sg:tags":[
        "tours",
        "promoter"
    ],
    "wof:name":"Fun Time Tours",
    "wof:placetype":"venue"
},
  "geometry": {"coordinates":[-76.216638,40.039812],"type":"Point"}
}