{
  "type": "Feature",
  "properties": {
    "iso:country":"US",
    "sg:address":"1472 E High St",
    "sg:city":"Pottstown",
    "sg:classifiers":[
        {
            "category":"Building & Trades",
            "subcategory":"Equipment Rental",
            "type":"Services"
        }
    ],
    "sg:phone":"+1 610 326 1200",
    "sg:postcode":"19464",
    "sg:province":"PA",
    "sg:tags":[
        "leasing"
    ],
    "wof:name":"Dillon E Capitol Group",
    "wof:placetype":"venue"
},
  "geometry": {"coordinates":[-75.615724,40.243858],"type":"Point"}
}