{
  "type": "Feature",
  "properties": {
    "iso:country":"US",
    "sg:address":"1295 Texter Mountain Rd",
    "sg:city":"Robesonia",
    "sg:classifiers":[
        {
            "category":"Professional",
            "subcategory":"Management & Consulting",
            "type":"Services"
        }
    ],
    "sg:phone":"+1 717 484 0234",
    "sg:postcode":"19551",
    "sg:province":"PA",
    "sg:tags":[
        "consultant"
    ],
    "sg:website":"www.kernkonsultusa.com",
    "wof:name":"KERN Konsult USA Inc",
    "wof:placetype":"venue"
},
  "geometry": {"coordinates":[-76.160089,40.312383],"type":"Point"}
}