{
  "type": "Feature",
  "properties": {
    "addr:full":"933 Arch St Philadelphia PA 19107",
    "addr:housenumber":"933",
    "addr:postcode":"19107",
    "addr:street":"Arch St",
    "iso:country":"US",
    "sg:address":"933 Arch St",
    "sg:city":"Philadelphia",
    "sg:classifiers":[
        {
            "category":"Professional",
            "subcategory":"Lawyer & Legal Services",
            "type":"Services"
        }
    ],
    "sg:phone":"+1   ",
    "sg:postcode":"19107",
    "sg:province":"PA",
    "wof:name":"Mark Immigration Service",
    "wof:placetype":"venue"
},
  "geometry": {"coordinates":[-75.156156,39.9536],"type":"Point"}
}