{
  "type": "Feature",
  "properties": {
    "addr:full":"3111 Agate St Philadelphia PA 19134",
    "addr:housenumber":"3111",
    "addr:postcode":"19134",
    "addr:street":"Agate St",
    "iso:country":"US",
    "sg:address":"3111 Agate St",
    "sg:city":"Philadelphia",
    "sg:classifiers":[
        {
            "category":"Building & Trades",
            "subcategory":"Construction",
            "type":"Services"
        }
    ],
    "sg:phone":"+1 215 426 5050",
    "sg:postcode":"19134",
    "sg:province":"PA",
    "sg:tags":[
        "roofing",
        "consultant",
        "contractor"
    ],
    "wof:name":"O'leary Roofing & Siding",
    "wof:placetype":"venue"
},
  "geometry": {"coordinates":[-75.109246,39.988159],"type":"Point"}
}