{
  "type": "Feature",
  "properties": {
    "addr:full":"600 Memory Ln York PA 17402",
    "addr:housenumber":"600",
    "addr:postcode":"17402",
    "addr:street":"Memory Ln",
    "iso:country":"US",
    "sg:address":"600 Memory Ln",
    "sg:city":"York",
    "sg:classifiers":[
        {
            "category":"Professional",
            "type":"Services"
        }
    ],
    "sg:phone":"+1 717 840 2543",
    "sg:postcode":"17402",
    "sg:province":"PA",
    "sg:tags":[
        "establishment"
    ],
    "wof:name":"New York Wire Div",
    "wof:placetype":"venue"
},
  "geometry": {"coordinates":[-76.68270099999999,39.980671],"type":"Point"}
}