{
  "type": "Feature",
  "properties": {
    "addr:full":"2711 Red Gate Dr Doylestown PA 18902",
    "addr:housenumber":"2711",
    "addr:postcode":"18902",
    "addr:street":"Red Gate Dr",
    "iso:country":"US",
    "sg:address":"2711 Red Gate Dr",
    "sg:city":"Doylestown",
    "sg:classifiers":[
        {
            "category":"Professional",
            "type":"Services"
        }
    ],
    "sg:phone":"+1 215 794 7641",
    "sg:postcode":"18902",
    "sg:province":"PA",
    "sg:tags":[
        "publication",
        "editorial"
    ],
    "sg:website":"http://www.camedcomm.com",
    "wof:name":"Ca Medical Communications",
    "wof:placetype":"venue"
},
  "geometry": {"coordinates":[-75.071777,40.320441],"type":"Point"}
}