{
  "type": "Feature",
  "properties": {
    "iso:country":"US",
    "sg:address":"422 N Main St",
    "sg:city":"Doylestown",
    "sg:classifiers":[
        {
            "category":"Retail",
            "subcategory":"Portrait Studio",
            "type":"Services"
        }
    ],
    "sg:phone":"+1 215 348 7226",
    "sg:postcode":"18901",
    "sg:province":"PA",
    "sg:tags":[
        "photography",
        "store"
    ],
    "wof:name":"Jack's Cameras Inc",
    "wof:placetype":"venue"
},
  "geometry": {"coordinates":[-75.13073,40.319821],"type":"Point"}
}