{
  "type": "Feature",
  "properties": {
    "iso:country":"US",
    "sg:address":"241 N Keswick Ave",
    "sg:city":"Glenside",
    "sg:classifiers":[
        {
            "category":"Shopping",
            "type":"Retail Goods"
        }
    ],
    "sg:phone":"+1 215 887 5600",
    "sg:postcode":"19038",
    "sg:province":"PA",
    "sg:tags":[
        "merchandise"
    ],
    "wof:name":"Frugal Frames",
    "wof:placetype":"venue"
},
  "geometry": {"coordinates":[-75.146973,40.104752],"type":"Point"}
}