{
  "type": "Feature",
  "properties": {
    "addr:full":"611 Enfield Dr Lancaster PA 17601",
    "addr:housenumber":"611",
    "addr:postcode":"17601",
    "addr:street":"Enfield Dr",
    "iso:country":"US",
    "sg:address":"611 Enfield Dr",
    "sg:city":"Lancaster",
    "sg:classifiers":[
        {
            "category":"Building & Trades",
            "subcategory":"Construction",
            "type":"Services"
        }
    ],
    "sg:phone":"+1   ",
    "sg:postcode":"17601",
    "sg:province":"PA",
    "sg:tags":[
        "contractor"
    ],
    "wof:name":"Theresa Borders",
    "wof:placetype":"venue"
},
  "geometry": {"coordinates":[-76.257547,40.055896],"type":"Point"}
}