{
  "type": "Feature",
  "properties": {
    "iso:country":"US",
    "sg:address":"6036 Fisher Dr",
    "sg:city":"Narvon",
    "sg:classifiers":[
        {
            "category":"Building & Trades",
            "subcategory":"Construction",
            "type":"Services"
        }
    ],
    "sg:phone":"+1   ",
    "sg:postcode":"17555",
    "sg:province":"PA",
    "sg:tags":[
        "general",
        "contractor"
    ],
    "wof:name":"R L King Construction",
    "wof:placetype":"venue"
},
  "geometry": {"coordinates":[-75.95743299999999,40.074798],"type":"Point"}
}