{
  "type": "Feature",
  "properties": {
    "iso:country":"US",
    "sg:address":"4100 Perkiomen Ave",
    "sg:city":"Reading",
    "sg:classifiers":[
        {
            "category":"Restaurant",
            "type":"Food & Drink"
        }
    ],
    "sg:phone":"+1 610 779 9980",
    "sg:postcode":"19606",
    "sg:province":"PA",
    "sg:tags":[
        "grill",
        "bar"
    ],
    "wof:name":"Perkiomen Grill",
    "wof:placetype":"venue"
},
  "geometry": {"coordinates":[-75.868942,40.31274],"type":"Point"}
}