{
  "type": "Feature",
  "properties": {
    "addr:full":"23 Bedford Sq Pittsburgh PA 15203",
    "addr:housenumber":"23",
    "addr:postcode":"15203",
    "addr:street":"Bedford Sq",
    "iso:country":"US",
    "sg:address":"23 Bedford Sq",
    "sg:city":"Pittsburgh",
    "sg:classifiers":[
        {
            "category":"Real Estate",
            "subcategory":"Developer",
            "type":"Services"
        }
    ],
    "sg:phone":"+1 412 431 5151",
    "sg:postcode":"15203",
    "sg:province":"PA",
    "sg:tags":[
        "manager"
    ],
    "wof:name":"Jaxon Development Company",
    "wof:placetype":"venue"
},
  "geometry": {"coordinates":[-79.986749,40.429408],"type":"Point"}
}