{
  "type": "Feature",
  "properties": {
    "addr:full":"524 Margin Dr Lebanon PA 17042",
    "addr:housenumber":"524",
    "addr:postcode":"17042",
    "addr:street":"Margin Dr",
    "iso:country":"US",
    "sg:address":"524 Margin Dr",
    "sg:city":"Lebanon",
    "sg:classifiers":[
        {
            "category":"Real Estate",
            "subcategory":"Real Estate Operator",
            "type":"Services"
        }
    ],
    "sg:phone":"+1   ",
    "sg:postcode":"17042",
    "sg:province":"PA",
    "sg:tags":[
        "building",
        "nonresidential"
    ],
    "wof:name":"Kingdom Properties",
    "wof:placetype":"venue"
},
  "geometry": {"coordinates":[-76.374736,40.311903],"type":"Point"}
}