{
  "type": "Feature",
  "properties": {
    "iso:country":"US",
    "sg:address":"629 Dulancey Dr",
    "sg:city":"Portage",
    "sg:classifiers":[
        {
            "category":"Wholesale",
            "subcategory":"Petroleum",
            "type":"Manufacturing & Wholesale Goods"
        }
    ],
    "sg:phone":"+1 814 736 3947",
    "sg:postcode":"15946",
    "sg:province":"PA",
    "sg:tags":[
        "home",
        "product",
        "oil",
        "heating"
    ],
    "wof:name":"Ray Oil & Gas Co",
    "wof:placetype":"venue"
},
  "geometry": {"coordinates":[-78.672016,40.390226],"type":"Point"}
}