{
  "type": "Feature",
  "properties": {
    "addr:full":"714 Reed St Philadelphia PA 19147",
    "addr:housenumber":"714",
    "addr:postcode":"19147",
    "addr:street":"Reed St",
    "iso:country":"US",
    "sg:address":"714 Reed St",
    "sg:city":"Philadelphia",
    "sg:classifiers":[
        {
            "category":"Health Services",
            "subcategory":"Chiropractor",
            "type":"Services"
        }
    ],
    "sg:phone":"+1 215 339 0630",
    "sg:postcode":"19147",
    "sg:province":"PA",
    "wof:name":"Karmich Chiropractic",
    "wof:placetype":"venue"
},
  "geometry": {"coordinates":[-75.156302,39.931413],"type":"Point"}
}