{
  "type": "Feature",
  "properties": {
    "iso:country":"US",
    "sg:address":"9530 Banes St",
    "sg:city":"Philadelphia",
    "sg:classifiers":[
        {
            "category":"Shopping",
            "subcategory":"Department Store",
            "type":"Retail Goods"
        }
    ],
    "sg:phone":"+1 215 673 4840",
    "sg:postcode":"19115",
    "sg:province":"PA",
    "wof:name":"J C Penney Co",
    "wof:placetype":"venue"
},
  "geometry": {"coordinates":[-75.037916,40.087059],"type":"Point"}
}