{
  "type": "Feature",
  "properties": {
    "iso:country":"US",
    "sg:address":"36 Davis St",
    "sg:city":"Bradford",
    "sg:classifiers":[
        {
            "category":"Personal",
            "subcategory":"Beauty Salon",
            "type":"Services"
        }
    ],
    "sg:phone":"+1 814 368 3303",
    "sg:postcode":"16701",
    "sg:province":"PA",
    "wof:name":"Gaetano's Hair Studio",
    "wof:placetype":"venue"
},
  "geometry": {"coordinates":[-78.645059,41.955964],"type":"Point"}
}