{
  "type": "Feature",
  "properties": {
    "iso:country":"US",
    "sg:address":"503 Grant St",
    "sg:city":"Newtown",
    "sg:classifiers":[
        {
            "category":"Organizations",
            "subcategory":"Religious Organization",
            "type":"Services"
        }
    ],
    "sg:phone":"+1 215 968 0830",
    "sg:postcode":"18940",
    "sg:province":"PA",
    "sg:tags":[
        "church"
    ],
    "wof:name":"Newton Methodist Church",
    "wof:placetype":"venue"
},
  "geometry": {"coordinates":[-74.91988499999999,40.22419],"type":"Point"}
}