{
  "type": "Feature",
  "properties": {
    "iso:country":"US",
    "sg:address":"313 6th Ave",
    "sg:city":"Pittsburgh",
    "sg:classifiers":[
        {
            "category":"Banks & Credit Unions",
            "subcategory":"Bank",
            "type":"Services"
        }
    ],
    "sg:phone":"+1 412 394 6915",
    "sg:postcode":"15222",
    "sg:province":"PA",
    "sg:tags":[
        "savings",
        "loan",
        "association"
    ],
    "wof:name":"Atlantic Financial",
    "wof:placetype":"venue"
},
  "geometry": {"coordinates":[-79.999155,40.442071],"type":"Point"}
}