{
  "type": "Feature",
  "properties": {
    "addr:full":"40 S Water Ave Sharon PA 16146",
    "addr:housenumber":"40",
    "addr:postcode":"16146",
    "addr:street":"S Water Ave",
    "iso:country":"US",
    "sg:address":"40 S Water Ave",
    "sg:city":"Sharon",
    "sg:classifiers":[
        {
            "category":"Shopping",
            "subcategory":"Shoes",
            "type":"Retail Goods"
        }
    ],
    "sg:phone":"+1 724 981 2200",
    "sg:postcode":"16146",
    "sg:province":"PA",
    "sg:tags":[
        "shoes-wholesale",
        "manufacturer"
    ],
    "sg:website":"http://www.reyers.com",
    "wof:name":"Reyers Shoe Store",
    "wof:placetype":"venue"
},
  "geometry": {"coordinates":[-80.51085,41.23269],"type":"Point"}
}