{
  "type": "Feature",
  "properties": {
    "iso:country":"US",
    "sg:address":"1322 Main St",
    "sg:city":"Browndale",
    "sg:classifiers":[
        {
            "category":"Personal",
            "subcategory":"Beauty Salon",
            "type":"Services"
        }
    ],
    "sg:phone":"+1 570 785 3321",
    "sg:postcode":"18421",
    "sg:province":"PA",
    "wof:name":"Paulines Beauty",
    "wof:placetype":"venue"
},
  "geometry": {"coordinates":[-75.458676,41.649726],"type":"Point"}
}