{
  "type": "Feature",
  "properties": {
    "iso:country":"US",
    "sg:address":"968 Easton Rd",
    "sg:city":"Warrington",
    "sg:classifiers":[
        {
            "category":"Recreation",
            "type":"Entertainment"
        }
    ],
    "sg:phone":"+1 215 343 5575",
    "sg:postcode":"18976",
    "sg:province":"PA",
    "sg:tags":[
        "parlor",
        "billiard"
    ],
    "wof:name":"APA",
    "wof:placetype":"venue"
},
  "geometry": {"coordinates":[-75.13647899999999,40.242274],"type":"Point"}
}