{
  "type": "Feature",
  "properties": {
    "addr:full":"950 W Valley Rd Wayne PA 19087",
    "addr:housenumber":"950",
    "addr:postcode":"19087",
    "addr:street":"W Valley Rd",
    "iso:country":"US",
    "sg:address":"950 W Valley Rd",
    "sg:city":"Wayne",
    "sg:classifiers":[
        {
            "category":"Professional",
            "subcategory":"Art Services",
            "type":"Services"
        },
        {
            "category":"Professional",
            "subcategory":"Advertising",
            "type":"Services"
        }
    ],
    "sg:phone":"+1 610 688 6550",
    "sg:postcode":"19087",
    "sg:province":"PA",
    "sg:tags":[
        "design",
        "graphic",
        "counselor",
        "studio"
    ],
    "sg:website":"www.crgdirect.com",
    "wof:name":"Creative Resource Group Inc",
    "wof:placetype":"venue"
},
  "geometry": {"coordinates":[-75.424257,40.069108],"type":"Point"}
}