{
  "type": "Feature",
  "properties": {
    "addr:full":"8123 Pettis Rd Meadville PA 16335",
    "addr:housenumber":"8123",
    "addr:postcode":"16335",
    "addr:street":"Pettis Rd",
    "iso:country":"US",
    "sg:address":"8123 Pettis Rd",
    "sg:city":"Meadville",
    "sg:classifiers":[
        {
            "category":"Manufacturing",
            "subcategory":"Wood Products",
            "type":"Manufacturing & Wholesale Goods"
        }
    ],
    "sg:phone":"+1   ",
    "sg:postcode":"16335",
    "sg:province":"PA",
    "sg:tags":[
        "mfg"
    ],
    "wof:name":"Tamarack Wood Products",
    "wof:placetype":"venue"
},
  "geometry": {"coordinates":[-80.09510299999999,41.612266],"type":"Point"}
}