{
  "type": "Feature",
  "properties": {
    "addr:full":"389 Moyer Rd Kutztown PA 19530",
    "addr:housenumber":"389",
    "addr:postcode":"19530",
    "addr:street":"Moyer Rd",
    "iso:country":"US",
    "sg:address":"389 Moyer Rd",
    "sg:city":"Kutztown",
    "sg:classifiers":[
        {
            "category":"Professional",
            "subcategory":"Business Services",
            "type":"Services"
        }
    ],
    "sg:phone":"+1 610 683 6362",
    "sg:postcode":"19530",
    "sg:province":"PA",
    "sg:tags":[
        "notary"
    ],
    "wof:name":"Shirley J Lutz",
    "wof:placetype":"venue"
},
  "geometry": {"coordinates":[-75.742994,40.568078],"type":"Point"}
}