{
  "type": "Feature",
  "properties": {
    "addr:full":"945 Washington Ave Philadelphia PA 19147",
    "addr:housenumber":"945",
    "addr:postcode":"19147",
    "addr:street":"Washington Ave",
    "iso:country":"US",
    "sg:address":"945 Washington Ave",
    "sg:city":"Philadelphia",
    "sg:classifiers":[
        {
            "category":"Home & Garden",
            "subcategory":"Carpets & Floor Coverings",
            "type":"Retail Goods"
        },
        {
            "category":"Home & Garden",
            "subcategory":"Furniture",
            "type":"Retail Goods"
        }
    ],
    "sg:phone":"+1 215 629 4050",
    "sg:postcode":"19147",
    "sg:province":"PA",
    "sg:tags":[
        "rug",
        "store"
    ],
    "wof:name":"Z Discount Furniture",
    "wof:placetype":"venue"
},
  "geometry": {"coordinates":[-75.159751,39.936731],"type":"Point"}
}