{
  "type": "Feature",
  "properties": {
    "iso:country":"US",
    "sg:address":"2315 Wharton St",
    "sg:city":"Pittsburgh",
    "sg:classifiers":[
        {
            "category":"Shopping",
            "subcategory":"Stationery & Office Supplies",
            "type":"Retail Goods"
        },
        {
            "category":"Manufacturing",
            "subcategory":"Metals",
            "type":"Manufacturing & Wholesale Goods"
        }
    ],
    "sg:phone":"+1 412 481 6500",
    "sg:postcode":"15203",
    "sg:province":"PA",
    "sg:tags":[
        "equipment",
        "marking",
        "stamping",
        "coding"
    ],
    "wof:name":"Accurate Marking Products Co",
    "wof:placetype":"venue"
},
  "geometry": {"coordinates":[-79.972533,40.43015],"type":"Point"}
}