{
  "type": "Feature",
  "properties": {
    "iso:country":"US",
    "sg:address":"3 Maple St",
    "sg:city":"Port Allegany",
    "sg:classifiers":[
        {
            "category":"Government",
            "subcategory":"Fire Station",
            "type":"Public Place"
        }
    ],
    "sg:phone":"+1 814 642 2773",
    "sg:postcode":"16743",
    "sg:province":"PA",
    "sg:tags":[
        "department"
    ],
    "wof:name":"Star Hose Firemen's Auxiliary",
    "wof:placetype":"venue"
},
  "geometry": {"coordinates":[-78.28026199999999,41.81191],"type":"Point"}
}