{
  "type": "Feature",
  "properties": {
    "iso:country":"US",
    "sg:address":"28 N Walnut St",
    "sg:city":"Blairsville",
    "sg:classifiers":[
        {
            "category":"Insurance",
            "subcategory":"Insurance Agent",
            "type":"Services"
        }
    ],
    "sg:phone":"+1   ",
    "sg:postcode":"15717",
    "sg:province":"PA",
    "wof:name":"Cable Mark C Insurance Agency",
    "wof:placetype":"venue"
},
  "geometry": {"coordinates":[-79.26452999999999,40.431085],"type":"Point"}
}