{
  "type": "Feature",
  "properties": {
    "addr:full":"5449 Wolfe Dr Pittsburgh PA 15236",
    "addr:housenumber":"5449",
    "addr:postcode":"15236",
    "addr:street":"Wolfe Dr",
    "iso:country":"US",
    "sg:address":"5449 Wolfe Dr",
    "sg:city":"Pittsburgh",
    "sg:classifiers":[
        {
            "category":"Building & Trades",
            "subcategory":"Electrical",
            "type":"Services"
        }
    ],
    "sg:phone":"+1   ",
    "sg:postcode":"15236",
    "sg:province":"PA",
    "sg:tags":[
        "electrical",
        "contractor"
    ],
    "wof:name":"Candor Electric Co",
    "wof:placetype":"venue"
},
  "geometry": {"coordinates":[-79.97469599999999,40.3408],"type":"Point"}
}