{
  "type": "Feature",
  "properties": {
    "iso:country":"US",
    "sg:address":"2 Brenneman Cir",
    "sg:city":"Mechanicsburg",
    "sg:classifiers":[
        {
            "category":"Freight",
            "type":"Transportation"
        }
    ],
    "sg:phone":"+1 717 697 5729",
    "sg:postcode":"17050",
    "sg:province":"PA",
    "sg:tags":[
        "operator",
        "local",
        "trucking"
    ],
    "wof:name":"Brother's Trucking",
    "wof:placetype":"venue"
},
  "geometry": {"coordinates":[-77.054703,40.218692],"type":"Point"}
}