{
  "type": "Feature",
  "properties": {
    "addr:full":"48 S Sproul Rd Broomall PA 19008",
    "addr:housenumber":"48",
    "addr:postcode":"19008",
    "addr:street":"S Sproul Rd",
    "iso:country":"US",
    "sg:address":"48 S Sproul Rd",
    "sg:city":"Broomall",
    "sg:classifiers":[
        {
            "category":"Building & Trades",
            "subcategory":"Electrical",
            "type":"Services"
        }
    ],
    "sg:phone":"+1 610 355 7570",
    "sg:postcode":"19008",
    "sg:province":"PA",
    "sg:tags":[
        "industrial",
        "electrician",
        "contractors-commercial",
        "electric"
    ],
    "wof:name":"Harold Smith Electrician",
    "wof:placetype":"venue"
},
  "geometry": {"coordinates":[-75.361464,39.980131],"type":"Point"}
}