{
  "type": "Feature",
  "properties": {
    "iso:country":"US",
    "sg:address":"2966 Whistler Rd",
    "sg:city":"Stoystown",
    "sg:classifiers":[
        {
            "category":"Mining & Drilling",
            "type":"Manufacturing & Wholesale Goods"
        }
    ],
    "sg:phone":"+1   ",
    "sg:postcode":"15563",
    "sg:province":"PA",
    "sg:tags":[
        "coal"
    ],
    "wof:name":"Donald Greathouse",
    "wof:placetype":"venue"
},
  "geometry": {"coordinates":[-78.92407300000001,40.121944],"type":"Point"}
}