{
  "type": "Feature",
  "properties": {
    "iso:country":"US",
    "sg:address":"700 700 Rd",
    "sg:city":"New Oxford",
    "sg:classifiers":[
        {
            "category":"Building & Trades",
            "subcategory":"Construction",
            "type":"Services"
        }
    ],
    "sg:phone":"+1 717 624 8744",
    "sg:postcode":"17350",
    "sg:province":"PA",
    "sg:tags":[
        "painting",
        "contractor"
    ],
    "wof:name":"Donald E Brown Painting Contr",
    "wof:placetype":"venue"
},
  "geometry": {"coordinates":[-77.057795,39.890845],"type":"Point"}
}