{
  "type": "Feature",
  "properties": {
    "iso:country":"US",
    "sg:address":"150 E 8th St",
    "sg:city":"Erie",
    "sg:classifiers":[
        {
            "category":"Insurance",
            "subcategory":"Insurance Agent",
            "type":"Services"
        }
    ],
    "sg:phone":"+1 814 870 3148",
    "sg:postcode":"16501",
    "sg:province":"PA",
    "wof:name":"Northshore Insurance",
    "wof:placetype":"venue"
},
  "geometry": {"coordinates":[-80.081249,42.128431],"type":"Point"}
}