{
  "type": "Feature",
  "properties": {
    "iso:country":"US",
    "sg:address":"102 Pickering Way",
    "sg:city":"Exton",
    "sg:classifiers":[
        {
            "category":"Professional",
            "subcategory":"Lawyer & Legal Services",
            "type":"Services"
        }
    ],
    "sg:phone":"+1 610 458 4400",
    "sg:postcode":"19341",
    "sg:province":"PA",
    "sg:tags":[
        "attorney"
    ],
    "wof:name":"Riley Riper Hollin & Colagreco",
    "wof:placetype":"venue"
},
  "geometry": {"coordinates":[-75.647891,40.057861],"type":"Point"}
}