{
  "type": "Feature",
  "properties": {
    "iso:country":"US",
    "sg:address":"330 Arch St",
    "sg:city":"Sunbury",
    "sg:classifiers":[
        {
            "category":"Personal",
            "subcategory":"Beauty Salon",
            "type":"Services"
        }
    ],
    "sg:phone":"+1 570 286 9977",
    "sg:postcode":"17801",
    "sg:province":"PA",
    "wof:name":"Pick Family Hair Salon",
    "wof:placetype":"venue"
},
  "geometry": {"coordinates":[-76.79189599999999,40.863073],"type":"Point"}
}