{
  "type": "Feature",
  "properties": {
    "addr:full":"1800 Lombard St Philadelphia PA 19146",
    "addr:housenumber":"1800",
    "addr:postcode":"19146",
    "addr:street":"Lombard St",
    "iso:country":"US",
    "sg:address":"1800 Lombard St",
    "sg:city":"Philadelphia",
    "sg:classifiers":[
        {
            "category":"Health Services",
            "subcategory":"Doctor",
            "type":"Services"
        },
        {
            "category":"Health Services",
            "subcategory":"Clinic",
            "type":"Services"
        }
    ],
    "sg:phone":"+1 610 935 0106",
    "sg:postcode":"19146",
    "sg:province":"PA",
    "sg:tags":[
        "physician",
        "pediatrics-orthopedic",
        "surgeons",
        "orthopedics",
        "osteopathic",
        "surgeon",
        "surgery"
    ],
    "wof:name":"Vincent Distefano Md Pc",
    "wof:placetype":"venue"
},
  "geometry": {"coordinates":[-75.172256,39.945549],"type":"Point"}
}