{
  "type": "Feature",
  "properties": {
    "iso:country":"US",
    "sg:address":"67 Chapman Ave",
    "sg:city":"Doylestown",
    "sg:classifiers":[
        {
            "category":"Health Services",
            "subcategory":"Health Practitioner",
            "type":"Services"
        }
    ],
    "sg:phone":"+1   ",
    "sg:postcode":"18901",
    "sg:province":"PA",
    "wof:name":"Jennifer Capaldi",
    "wof:placetype":"venue"
},
  "geometry": {"coordinates":[-75.126858,40.324143],"type":"Point"}
}