{
  "type": "Feature",
  "properties": {
    "addr:full":"10225 Ambridge Pl Philadelphia PA 19114",
    "addr:housenumber":"10225",
    "addr:postcode":"19114",
    "addr:street":"Ambridge Pl",
    "iso:country":"US",
    "sg:address":"10225 Ambridge Pl",
    "sg:city":"Philadelphia",
    "sg:classifiers":[
        {
            "category":"Restaurant",
            "type":"Food & Drink"
        }
    ],
    "sg:phone":"+1   ",
    "sg:postcode":"19114",
    "sg:province":"PA",
    "sg:tags":[
        "eating"
    ],
    "wof:name":"Family Village Pizzeria",
    "wof:placetype":"venue"
},
  "geometry": {"coordinates":[-74.99475700000001,40.0796],"type":"Point"}
}