{
  "type": "Feature",
  "properties": {
    "iso:country":"US",
    "sg:address":"105 Memory Ln",
    "sg:city":"Telford",
    "sg:classifiers":[
        {
            "category":"Building & Trades",
            "subcategory":"Construction",
            "type":"Services"
        }
    ],
    "sg:phone":"+1   ",
    "sg:postcode":"18969",
    "sg:province":"PA",
    "sg:tags":[
        "excavation",
        "contractor"
    ],
    "wof:name":"James Shisler Construction",
    "wof:placetype":"venue"
},
  "geometry": {"coordinates":[-75.360687,40.306972],"type":"Point"}
}