{
  "type": "Feature",
  "properties": {
    "iso:country":"US",
    "sg:address":"4611 HAMILTON BLVD",
    "sg:city":"ALLENTOWN",
    "sg:classifiers":[
        {
            "category":"Autos & Motor Vehicles",
            "subcategory":"Automobile Sales",
            "type":"Retail Goods"
        },
        {
            "category":"Retail",
            "subcategory":"Auto Repair",
            "type":"Services"
        }
    ],
    "sg:phone":"+1 484 550 7507",
    "sg:postcode":"18103",
    "sg:province":"PA",
    "sg:tags":[
        "car",
        "used",
        "new"
    ],
    "sg:website":"http://www.beckersubaru.com",
    "wof:name":"Becker Subaru",
    "wof:placetype":"venue"
},
  "geometry": {"coordinates":[-75.549015,40.568262],"type":"Point"}
}