{
  "type": "Feature",
  "properties": {
    "iso:country":"US",
    "sg:address":"4756 Pennell Rd",
    "sg:city":"Aston",
    "sg:classifiers":[
        {
            "category":"Shopping",
            "subcategory":"Computers & Home Electronics",
            "type":"Retail Goods"
        }
    ],
    "sg:phone":"+1   ",
    "sg:postcode":"19014",
    "sg:province":"PA",
    "sg:tags":[
        "repair",
        "equipment"
    ],
    "wof:name":"T N I Computer Resources",
    "wof:placetype":"venue"
},
  "geometry": {"coordinates":[-75.428757,39.870142],"type":"Point"}
}