{
  "type": "Feature",
  "properties": {
    "iso:country":"US",
    "sg:address":"18 Shadow Ln",
    "sg:city":"Chadds Ford",
    "sg:classifiers":[
        {
            "category":"Organizations",
            "subcategory":"Community Association",
            "type":"Services"
        }
    ],
    "sg:phone":"+1   ",
    "sg:postcode":"19317",
    "sg:province":"PA",
    "wof:name":"Heilbron Home Owners Assn",
    "wof:placetype":"venue"
},
  "geometry": {"coordinates":[-75.622619,39.838975],"type":"Point"}
}