{
  "type": "Feature",
  "properties": {
    "addr:full":"2400 Market St Ste 326 Philadelphia PA 19103",
    "addr:housenumber":"2400",
    "addr:postcode":"19103",
    "addr:street":"Market St Ste 326",
    "iso:country":"US",
    "sg:address":"2400 Market St Ste 326",
    "sg:city":"Philadelphia",
    "sg:classifiers":[
        {
            "category":"Shopping",
            "subcategory":"Crafts & Fabrics",
            "type":"Retail Goods"
        },
        {
            "category":"Wholesale",
            "subcategory":"Home Furnishings",
            "type":"Manufacturing & Wholesale Goods"
        }
    ],
    "sg:phone":"+1 215 567 0750",
    "sg:postcode":"19103",
    "sg:province":"PA",
    "sg:tags":[
        "draperies",
        "curtain",
        "manufacturer",
        "drapery",
        "shades-wholesale"
    ],
    "sg:website":"http://www.fschumacher.com",
    "wof:name":"F. Schumacher & Co.",
    "wof:placetype":"venue"
},
  "geometry": {"coordinates":[-75.179501,39.954362],"type":"Point"}
}