{
  "type": "Feature",
  "properties": {
    "addr:full":"2616 Wilmington Rd New Castle PA 16105",
    "addr:housenumber":"2616",
    "addr:postcode":"16105",
    "addr:street":"Wilmington Rd New",
    "iso:country":"US",
    "sg:address":"2616 Wilmington Rd",
    "sg:city":"New Castle",
    "sg:classifiers":[
        {
            "category":"Insurance",
            "subcategory":"Insurance Agent",
            "type":"Services"
        }
    ],
    "sg:phone":"+1 724 652 1320",
    "sg:postcode":"16105",
    "sg:province":"PA",
    "wof:name":"State Farm Insurance",
    "wof:placetype":"venue"
},
  "geometry": {"coordinates":[-80.35473399999999,41.031438],"type":"Point"}
}