{
  "type": "Feature",
  "properties": {
    "iso:country":"US",
    "sg:address":"1718 State Rte 980",
    "sg:city":"Canonsburg",
    "sg:classifiers":[
        {
            "category":"Personal",
            "type":"Services"
        }
    ],
    "sg:phone":"+1   ",
    "sg:postcode":"15317",
    "sg:province":"PA",
    "sg:tags":[
        "shop",
        "beauty"
    ],
    "wof:name":"Bronzing Barn",
    "wof:placetype":"venue"
},
  "geometry": {"coordinates":[-80.217136,40.295478],"type":"Point"}
}