{
  "type": "Feature",
  "properties": {
    "addr:full":"202 Carter Dr West Chester PA 19382",
    "addr:housenumber":"202",
    "addr:postcode":"19382",
    "addr:street":"Carter Dr",
    "iso:country":"US",
    "sg:address":"202 Carter Dr",
    "sg:city":"West Chester",
    "sg:classifiers":[
        {
            "category":"Banks & Credit Unions",
            "subcategory":"Bank",
            "type":"Services"
        },
        {
            "category":"Banks & Credit Unions",
            "subcategory":"Financial Services",
            "type":"Services"
        }
    ],
    "sg:phone":"+1 484 881 4290",
    "sg:postcode":"19382",
    "sg:province":"PA",
    "sg:tags":[
        "broker",
        "mortgage"
    ],
    "sg:website":"www.firstnational.com",
    "wof:name":"First National Bank of Chester County",
    "wof:placetype":"venue"
},
  "geometry": {"coordinates":[-75.590861,39.950367],"type":"Point"}
}