{
  "type": "Feature",
  "properties": {
    "addr:full":"1538 W Broad St Quakertown PA 18951",
    "addr:housenumber":"1538",
    "addr:postcode":"18951",
    "addr:street":"W Broad St",
    "iso:country":"US",
    "sg:address":"1538 W Broad St",
    "sg:city":"Quakertown",
    "sg:classifiers":[
        {
            "category":"Health Services",
            "subcategory":"Clinic",
            "type":"Services"
        }
    ],
    "sg:phone":"+1 215 529 6810",
    "sg:postcode":"18951",
    "sg:province":"PA",
    "sg:tags":[
        "home",
        "care"
    ],
    "wof:name":"Comfort Keepers",
    "wof:placetype":"venue"
},
  "geometry": {"coordinates":[-75.359821,40.443656],"type":"Point"}
}