{
  "type": "Feature",
  "properties": {
    "iso:country":"US",
    "sg:address":"332 Miller St",
    "sg:city":"Strasburg",
    "sg:classifiers":[
        {
            "category":"Professional",
            "type":"Services"
        }
    ],
    "sg:phone":"+1   ",
    "sg:postcode":"17579",
    "sg:province":"PA",
    "wof:name":"Strasburg Swimming & Recr",
    "wof:placetype":"venue"
},
  "geometry": {"coordinates":[-76.199243,39.979711],"type":"Point"}
}