{
  "type": "Feature",
  "properties": {
    "iso:country":"US",
    "sg:address":"11 Bedford St",
    "sg:city":"Hollidaysburg",
    "sg:classifiers":[
        {
            "category":"Home & Garden",
            "subcategory":"Furniture",
            "type":"Retail Goods"
        }
    ],
    "sg:phone":"+1   ",
    "sg:postcode":"16648",
    "sg:province":"PA",
    "wof:name":"EDS Furniture",
    "wof:placetype":"venue"
},
  "geometry": {"coordinates":[-78.394446,40.423683],"type":"Point"}
}