{
  "type": "Feature",
  "properties": {
    "addr:full":"269 W County Line Rd Hatboro PA 19040",
    "addr:housenumber":"269",
    "addr:postcode":"19040",
    "addr:street":"W County Line Rd",
    "iso:country":"US",
    "sg:address":"269 W County Line Rd",
    "sg:city":"Hatboro",
    "sg:classifiers":[
        {
            "category":"Professional",
            "subcategory":"Computer Services",
            "type":"Services"
        }
    ],
    "sg:phone":"+1 215 443 9713",
    "sg:postcode":"19040",
    "sg:province":"PA",
    "sg:tags":[
        "repair"
    ],
    "wof:name":"Diversified Technicians Inc",
    "wof:placetype":"venue"
},
  "geometry": {"coordinates":[-75.082697,40.178184],"type":"Point"}
}