{
  "type": "Feature",
  "properties": {
    "addr:full":"9955 Grubbs Rd Wexford PA 15090",
    "addr:housenumber":"9955",
    "addr:postcode":"15090",
    "addr:street":"Grubbs Rd",
    "iso:country":"US",
    "sg:address":"9955 Grubbs Rd",
    "sg:city":"Wexford",
    "sg:classifiers":[
        {
            "category":"Government",
            "subcategory":"Police Station",
            "type":"Public Place"
        }
    ],
    "sg:phone":"+1 724 369 7992",
    "sg:postcode":"15090",
    "sg:province":"PA",
    "sg:tags":[
        "department"
    ],
    "wof:name":"Mc Candless Police Dept",
    "wof:placetype":"venue"
},
  "geometry": {"coordinates":[-80.020268,40.591392],"type":"Point"}
}