{
  "type": "Feature",
  "properties": {
    "iso:country":"US",
    "sg:address":"1011 Yorkshire Rd",
    "sg:city":"Bethlehem",
    "sg:classifiers":[
        {
            "category":"Retail",
            "subcategory":"Repair Shop",
            "type":"Services"
        },
        {
            "category":"Building & Trades",
            "subcategory":"Plumbing",
            "type":"Services"
        }
    ],
    "sg:phone":"+1 610 433 2121",
    "sg:postcode":"18017",
    "sg:province":"PA",
    "sg:tags":[
        "equipment",
        "air",
        "conditioning",
        "contractor"
    ],
    "wof:name":"Anthony Refrigeration & Air",
    "wof:placetype":"venue"
},
  "geometry": {"coordinates":[-75.39476999999999,40.651373],"type":"Point"}
}