{
  "type": "Feature",
  "properties": {
    "iso:country":"US",
    "sg:address":"319 S Maple Ave",
    "sg:city":"Greensburg",
    "sg:classifiers":[
        {
            "category":"Professional",
            "subcategory":"Lawyer & Legal Services",
            "type":"Services"
        }
    ],
    "sg:phone":"+1 724 834 5010",
    "sg:postcode":"15601",
    "sg:province":"PA",
    "sg:tags":[
        "attorney"
    ],
    "wof:name":"William Stillwagon PC",
    "wof:placetype":"venue"
},
  "geometry": {"coordinates":[-79.542198,40.299751],"type":"Point"}
}