{
  "type": "Feature",
  "properties": {
    "addr:full":"1483 Romansville Rd Downingtown PA 19335",
    "addr:housenumber":"1483",
    "addr:postcode":"19335",
    "addr:street":"Romansville Rd",
    "iso:country":"US",
    "sg:address":"1483 Romansville Rd",
    "sg:city":"Downingtown",
    "sg:classifiers":[
        {
            "category":"Freight",
            "type":"Transportation"
        }
    ],
    "sg:phone":"+1 610 380 2174",
    "sg:postcode":"19335",
    "sg:province":"PA",
    "sg:tags":[
        "delivery",
        "courier"
    ],
    "wof:name":"Astro Courier",
    "wof:placetype":"venue"
},
  "geometry": {"coordinates":[-75.75687499999999,39.978428],"type":"Point"}
}