{
  "type": "Feature",
  "properties": {
    "iso:country":"US",
    "sg:address":"1 Fayette St",
    "sg:city":"Conshohocken",
    "sg:classifiers":[
        {
            "category":"Organizations",
            "subcategory":"Membership Organization",
            "type":"Services"
        }
    ],
    "sg:phone":"+1   ",
    "sg:postcode":"19428",
    "sg:province":"PA",
    "sg:tags":[
        "charitable"
    ],
    "wof:name":"Huston Foundation",
    "wof:placetype":"venue"
},
  "geometry": {"coordinates":[-75.308036,40.072015],"type":"Point"}
}