{
  "type": "Feature",
  "properties": {
    "iso:country":"US",
    "sg:address":"122 Lampliter Ln",
    "sg:city":"Canonsburg",
    "sg:classifiers":[
        {
            "category":"Building & Trades",
            "subcategory":"Construction",
            "type":"Services"
        }
    ],
    "sg:phone":"+1   ",
    "sg:postcode":"15317",
    "sg:province":"PA",
    "sg:tags":[
        "house"
    ],
    "wof:name":"Kldm Homes",
    "wof:placetype":"venue"
},
  "geometry": {"coordinates":[-80.08569900000001,40.274376],"type":"Point"}
}