{
  "type": "Feature",
  "properties": {
    "addr:full":"2127 Margaret St Philadelphia PA 19124",
    "addr:housenumber":"2127",
    "addr:postcode":"19124",
    "addr:street":"Margaret St",
    "iso:country":"US",
    "sg:address":"2127 Margaret St",
    "sg:city":"Philadelphia",
    "sg:classifiers":[
        {
            "category":"Manufacturing",
            "subcategory":"Metals",
            "type":"Manufacturing & Wholesale Goods"
        }
    ],
    "sg:phone":"+1 215 289 4944",
    "sg:postcode":"19124",
    "sg:province":"PA",
    "sg:tags":[
        "plating"
    ],
    "wof:name":"NEL Auto Sales",
    "wof:placetype":"venue"
},
  "geometry": {"coordinates":[-75.07651,40.009436],"type":"Point"}
}