{
  "type": "Feature",
  "properties": {
    "addr:full":"1356 Rte 51 Clairton PA 15025",
    "addr:housenumber":"1356",
    "addr:postcode":"15025",
    "addr:street":"Rte 51",
    "iso:country":"US",
    "sg:address":"1356 Rte 51",
    "sg:city":"Clairton",
    "sg:classifiers":[
        {
            "category":"Manufacturing",
            "subcategory":"Signs",
            "type":"Manufacturing & Wholesale Goods"
        }
    ],
    "sg:phone":"+1 412 384 8731",
    "sg:postcode":"15025",
    "sg:province":"PA",
    "sg:tags":[
        "specialty",
        "mfg"
    ],
    "wof:name":"P T Sign",
    "wof:placetype":"venue"
},
  "geometry": {"coordinates":[-79.93673699999999,40.308641],"type":"Point"}
}