{
  "type": "Feature",
  "properties": {
    "addr:full":"509 Swede St Norristown PA 19401",
    "addr:housenumber":"509",
    "addr:postcode":"19401",
    "addr:street":"Swede St",
    "iso:country":"US",
    "sg:address":"509 Swede St",
    "sg:city":"Norristown",
    "sg:classifiers":[
        {
            "category":"Professional",
            "subcategory":"Lawyer & Legal Services",
            "type":"Services"
        }
    ],
    "sg:phone":"+1 610 292 9300",
    "sg:postcode":"19401",
    "sg:province":"PA",
    "sg:tags":[
        "attorney",
        "practice"
    ],
    "wof:name":"Devine, James I Law Offices",
    "wof:placetype":"venue"
},
  "geometry": {"coordinates":[-75.34356200000001,40.116215],"type":"Point"}
}