{
  "type": "Feature",
  "properties": {
    "addr:full":"573 Yoder Rd Harleysville PA 19438",
    "addr:housenumber":"573",
    "addr:postcode":"19438",
    "addr:street":"Yoder Rd",
    "iso:country":"US",
    "sg:address":"573 Yoder Rd",
    "sg:city":"Harleysville",
    "sg:classifiers":[
        {
            "category":"Organizations",
            "subcategory":"Religious Organization",
            "type":"Services"
        }
    ],
    "sg:phone":"+1 215 256 7850",
    "sg:postcode":"19438",
    "sg:province":"PA",
    "sg:website":"www.goclc.net",
    "wof:name":"Christian Life Church",
    "wof:placetype":"venue"
},
  "geometry": {"coordinates":[-75.380605,40.289776],"type":"Point"}
}