{
  "type": "Feature",
  "properties": {
    "iso:country":"US",
    "sg:address":"524 Mill St",
    "sg:city":"Lebanon",
    "sg:classifiers":[
        {
            "category":"Organizations",
            "subcategory":"Religious Organization",
            "type":"Services"
        }
    ],
    "sg:phone":"+1 717 228 2071",
    "sg:postcode":"17042",
    "sg:province":"PA",
    "sg:tags":[
        "clergy"
    ],
    "wof:name":"William J Mc Ellroy",
    "wof:placetype":"venue"
},
  "geometry": {"coordinates":[-76.47634100000001,40.330276],"type":"Point"}
}