{
  "type": "Feature",
  "properties": {
    "iso:country":"US",
    "sg:address":"175 N Cedar St",
    "sg:city":"Hazleton",
    "sg:classifiers":[
        {
            "category":"Building & Trades",
            "subcategory":"Plumbing",
            "type":"Services"
        }
    ],
    "sg:phone":"+1 570 454 8029",
    "sg:postcode":"18201",
    "sg:province":"PA",
    "sg:tags":[
        "plumbing",
        "heating",
        "contractor"
    ],
    "wof:name":"Rex D'Amico Plumbing & Heating",
    "wof:placetype":"venue"
},
  "geometry": {"coordinates":[-75.968723,40.957506],"type":"Point"}
}