{
  "type": "Feature",
  "properties": {
    "iso:country":"US",
    "sg:address":"7430 Frankford Ave",
    "sg:city":"Philadelphia",
    "sg:classifiers":[
        {
            "category":"Shopping",
            "subcategory":"Used Merchandise",
            "type":"Retail Goods"
        }
    ],
    "sg:phone":"+1 215 332 0992",
    "sg:postcode":"19136",
    "sg:province":"PA",
    "sg:tags":[
        "resale",
        "shop"
    ],
    "wof:name":"Uptown Consignment",
    "wof:placetype":"venue"
},
  "geometry": {"coordinates":[-75.03681899999999,40.038283],"type":"Point"}
}