{
  "type": "Feature",
  "properties": {
    "addr:full":"826 Mahoning Dr W Lehighton PA 18235",
    "addr:housenumber":"826",
    "addr:postcode":"18235",
    "addr:street":"Mahoning Dr W",
    "iso:country":"US",
    "sg:address":"826 Mahoning Dr W",
    "sg:city":"Lehighton",
    "sg:classifiers":[
        {
            "category":"Place Of Worship",
            "subcategory":"Church",
            "type":"Public Place"
        },
        {
            "category":"Place Of Worship",
            "type":"Public Place"
        }
    ],
    "sg:phone":"+1 570 386 9960",
    "sg:postcode":"18235",
    "sg:province":"PA",
    "sg:tags":[
        "lutheran",
        "america",
        "churches-lutheran",
        "churches-lutheran-evangelical"
    ],
    "wof:name":"St John's Church Of Mahoning",
    "wof:placetype":"venue"
},
  "geometry": {"coordinates":[-75.787999,40.807807],"type":"Point"}
}