{
  "type": "Feature",
  "properties": {
    "iso:country":"US",
    "sg:address":"140 Erie St",
    "sg:city":"Scranton",
    "sg:classifiers":[
        {
            "category":"Restaurant",
            "type":"Food & Drink"
        }
    ],
    "sg:phone":"+1 570 961 3070",
    "sg:postcode":"18510",
    "sg:province":"PA",
    "sg:tags":[
        "drinking",
        "eating"
    ],
    "wof:name":"Carmella's",
    "wof:placetype":"venue"
},
  "geometry": {"coordinates":[-75.627144,41.40704],"type":"Point"}
}