{
  "type": "Feature",
  "properties": {
    "iso:country":"US",
    "sg:address":"120 Mcclintock Dr",
    "sg:city":"Canonsburg",
    "sg:classifiers":[
        {
            "category":"Building & Trades",
            "subcategory":"Electrical",
            "type":"Services"
        }
    ],
    "sg:phone":"+1 724 942 1291",
    "sg:postcode":"15317",
    "sg:province":"PA",
    "sg:tags":[
        "electrician"
    ],
    "wof:name":"Lamb Electric",
    "wof:placetype":"venue"
},
  "geometry": {"coordinates":[-80.08967,40.278593],"type":"Point"}
}