{
  "type": "Feature",
  "properties": {
    "iso:country":"US",
    "sg:address":"542 W Moreland Ave",
    "sg:city":"Philadelphia",
    "sg:classifiers":[
        {
            "category":"Health Services",
            "subcategory":"Doctor",
            "type":"Services"
        }
    ],
    "sg:phone":"+1 215 753 7186",
    "sg:postcode":"19118",
    "sg:province":"PA",
    "sg:tags":[
        "physician",
        "surgeon"
    ],
    "wof:name":"Robert E Booth MD",
    "wof:placetype":"venue"
},
  "geometry": {"coordinates":[-75.206579,40.061128],"type":"Point"}
}