{
  "type": "Feature",
  "properties": {
    "addr:full":"3401 Kensington Ave Philadelphia PA 19134",
    "addr:housenumber":"3401",
    "addr:postcode":"19134",
    "addr:street":"Kensington Ave",
    "iso:country":"US",
    "sg:address":"3401 Kensington Ave",
    "sg:city":"Philadelphia",
    "sg:classifiers":[
        {
            "category":"Real Estate",
            "subcategory":"Real Estate Services",
            "type":"Services"
        }
    ],
    "sg:phone":"+1 215 423 3050",
    "sg:postcode":"19134",
    "sg:province":"PA",
    "wof:name":"Lee Agcy Realtr",
    "wof:placetype":"venue"
},
  "geometry": {"coordinates":[-75.108704,39.999199],"type":"Point"}
}