{
  "type": "Feature",
  "properties": {
    "iso:country":"US",
    "sg:address":"111 N Independence Mall E",
    "sg:city":"Philadelphia",
    "sg:classifiers":[
        {
            "category":"Recreation",
            "type":"Entertainment"
        }
    ],
    "sg:phone":"+1 215 923 5008",
    "sg:postcode":"19106",
    "sg:province":"PA",
    "sg:tags":[
        "attraction",
        "tourist"
    ],
    "wof:name":"Big Bus Co Of Pa Inc",
    "wof:placetype":"venue"
},
  "geometry": {"coordinates":[-75.148512,39.951886],"type":"Point"}
}