{
  "type": "Feature",
  "properties": {
    "addr:full":"184 Main St Luzerne PA 18709",
    "addr:housenumber":"184",
    "addr:postcode":"18709",
    "addr:street":"Main St",
    "iso:country":"US",
    "sg:address":"184 Main St",
    "sg:city":"Luzerne",
    "sg:classifiers":[
        {
            "category":"Personal",
            "subcategory":"Beauty Salon",
            "type":"Services"
        }
    ],
    "sg:phone":"+1 570 288 5005",
    "sg:postcode":"18709",
    "sg:province":"PA",
    "wof:name":"Ann Marie Guarnieri Beauty Sln",
    "wof:placetype":"venue"
},
  "geometry": {"coordinates":[-75.89707300000001,41.284127],"type":"Point"}
}