{
  "type": "Feature",
  "properties": {
    "addr:full":"45 Dunkle Ln Knox PA 16232",
    "addr:housenumber":"45",
    "addr:postcode":"16232",
    "addr:street":"Dunkle Ln",
    "iso:country":"US",
    "sg:address":"45 Dunkle Ln",
    "sg:city":"Knox",
    "sg:classifiers":[
        {
            "category":"Building & Trades",
            "subcategory":"Construction",
            "type":"Services"
        }
    ],
    "sg:phone":"+1 814 797 2814",
    "sg:postcode":"16232",
    "sg:province":"PA",
    "sg:tags":[
        "repairing",
        "remodeling",
        "contractor"
    ],
    "wof:name":"Rocky's Remodeling Woodworking",
    "wof:placetype":"venue"
},
  "geometry": {"coordinates":[-79.593126,41.186792],"type":"Point"}
}