{
  "type": "Feature",
  "properties": {
    "iso:country":"US",
    "sg:address":"1270 Wakefield Ct",
    "sg:city":"Glen Mills",
    "sg:classifiers":[
        {
            "category":"Health Services",
            "subcategory":"Health Practitioner",
            "type":"Services"
        }
    ],
    "sg:phone":"+1   ",
    "sg:postcode":"19342",
    "sg:province":"PA",
    "wof:name":"Charlotte F Stare",
    "wof:placetype":"venue"
},
  "geometry": {"coordinates":[-75.466656,39.940092],"type":"Point"}
}