{
  "type": "Feature",
  "properties": {
    "addr:full":"64 Ponderosa Dr Southampton PA 18966",
    "addr:housenumber":"64",
    "addr:postcode":"18966",
    "addr:street":"Ponderosa Dr",
    "iso:country":"US",
    "sg:address":"64 Ponderosa Dr",
    "sg:city":"Southampton",
    "sg:classifiers":[
        {
            "category":"Professional",
            "subcategory":"Computer Services",
            "type":"Services"
        }
    ],
    "sg:phone":"+1   ",
    "sg:postcode":"18966",
    "sg:province":"PA",
    "sg:tags":[
        "related"
    ],
    "wof:name":"Trisis Technology Partners",
    "wof:placetype":"venue"
},
  "geometry": {"coordinates":[-74.95995000000001,40.188044],"type":"Point"}
}