{
  "type": "Feature",
  "properties": {
    "iso:country":"US",
    "sg:address":"1145 N 5th St",
    "sg:city":"Perkasie",
    "sg:classifiers":[
        {
            "category":"Restaurant",
            "type":"Food & Drink"
        }
    ],
    "sg:menulink":"http://www.allmenus.com/pa/perkasie/66247-dominos-pizza/menu/",
    "sg:phone":"+1 215 453 8440",
    "sg:postcode":"18944",
    "sg:province":"PA",
    "sg:tags":[
        "american",
        "wing",
        "pizza"
    ],
    "wof:name":"Domino's Pizza",
    "wof:placetype":"venue"
},
  "geometry": {"coordinates":[-75.278451,40.382413],"type":"Point"}
}