{
  "type": "Feature",
  "properties": {
    "addr:full":"16 Indian Way Malvern PA 19355",
    "addr:housenumber":"16",
    "addr:postcode":"19355",
    "addr:street":"Indian Way",
    "iso:country":"US",
    "sg:address":"16 Indian Way",
    "sg:city":"Malvern",
    "sg:classifiers":[
        {
            "category":"Professional",
            "subcategory":"Management & Consulting",
            "type":"Services"
        }
    ],
    "sg:phone":"+1   ",
    "sg:postcode":"19355",
    "sg:province":"PA",
    "wof:name":"Sierra Communications Inc",
    "wof:placetype":"venue"
},
  "geometry": {"coordinates":[-75.53474799999999,40.017364],"type":"Point"}
}