{
  "type": "Feature",
  "properties": {
    "addr:full":"3400 N 11th St Philadelphia PA 19140",
    "addr:housenumber":"3400",
    "addr:postcode":"19140",
    "addr:street":"N 11Th St",
    "iso:country":"US",
    "sg:address":"3400 N 11th St",
    "sg:city":"Philadelphia",
    "sg:classifiers":[
        {
            "category":"Health Services",
            "subcategory":"Hospital",
            "type":"Services"
        }
    ],
    "sg:phone":"+1   ",
    "sg:postcode":"19140",
    "sg:province":"PA",
    "sg:tags":[
        "specialty",
        "social"
    ],
    "wof:name":"Mystic Knights of Sea",
    "wof:placetype":"venue"
},
  "geometry": {"coordinates":[-75.146776,40.004514],"type":"Point"}
}