{
  "type": "Feature",
  "properties": {
    "addr:full":"5695 Rising Sun Ave Philadelphia PA 19120",
    "addr:housenumber":"5695",
    "addr:postcode":"19120",
    "addr:street":"Rising Sun Ave",
    "iso:country":"US",
    "sg:address":"5695 Rising Sun Ave",
    "sg:city":"Philadelphia",
    "sg:classifiers":[
        {
            "category":"Manufacturing",
            "subcategory":"Apparel",
            "type":"Manufacturing & Wholesale Goods"
        }
    ],
    "sg:phone":"+1 215 342 7773",
    "sg:postcode":"19120",
    "sg:province":"PA",
    "sg:tags":[
        "dress",
        "mfg"
    ],
    "wof:name":"Style Setter Fashions Inc",
    "wof:placetype":"venue"
},
  "geometry": {"coordinates":[-75.108953,40.039398],"type":"Point"}
}