{
  "type": "Feature",
  "properties": {
    "addr:full":"2129 Wallace St Philadelphia PA 19130",
    "addr:housenumber":"2129",
    "addr:postcode":"19130",
    "addr:street":"Wallace St",
    "iso:country":"US",
    "sg:address":"2129 Wallace St",
    "sg:city":"Philadelphia",
    "sg:classifiers":[
        {
            "category":"Health Services",
            "subcategory":"Health Practitioner",
            "type":"Services"
        }
    ],
    "sg:phone":"+1   ",
    "sg:postcode":"19130",
    "sg:province":"PA",
    "wof:name":"Perkins Whaley Clara Dr",
    "wof:placetype":"venue"
},
  "geometry": {"coordinates":[-75.173497,39.966791],"type":"Point"}
}