{
  "type": "Feature",
  "properties": {
    "addr:full":"171 Muir Ave Hazleton PA 18201",
    "addr:housenumber":"171",
    "addr:postcode":"18201",
    "addr:street":"Muir Ave",
    "iso:country":"US",
    "sg:address":"171 Muir Ave",
    "sg:city":"Hazleton",
    "sg:classifiers":[
        {
            "category":"Recreation",
            "type":"Entertainment"
        }
    ],
    "sg:phone":"+1   ",
    "sg:postcode":"18201",
    "sg:province":"PA",
    "sg:tags":[
        "club",
        "membership"
    ],
    "wof:name":"American Legion",
    "wof:placetype":"venue"
},
  "geometry": {"coordinates":[-75.976,40.942235],"type":"Point"}
}