{
  "type": "Feature",
  "properties": {
    "addr:full":"324 S 34th St Philadelphia PA 19104",
    "addr:housenumber":"324",
    "addr:postcode":"19104",
    "addr:street":"S 34Th St",
    "iso:country":"US",
    "sg:address":"324 S 34th St",
    "sg:city":"Philadelphia",
    "sg:classifiers":[
        {
            "category":"Health Services",
            "subcategory":"Doctor",
            "type":"Services"
        }
    ],
    "sg:phone":"+1 215 590 1879",
    "sg:postcode":"19104",
    "sg:province":"PA",
    "sg:tags":[
        "physician",
        "surgeon",
        "neurology",
        "surgeons"
    ],
    "wof:name":"Godinez, Rodolfo I, Md - Children's Hospital Of Pa",
    "wof:placetype":"venue"
},
  "geometry": {"coordinates":[-75.192757,39.94931],"type":"Point"}
}