{
  "type": "Feature",
  "properties": {
    "iso:country":"US",
    "sg:address":"212 W Long Ave",
    "sg:city":"Du Bois",
    "sg:classifiers":[
        {
            "category":"Retail",
            "subcategory":"Laundry & Dry Cleaning",
            "type":"Services"
        },
        {
            "category":"Shopping",
            "subcategory":"Clothing, Apparel, & Fashions",
            "type":"Retail Goods"
        }
    ],
    "sg:phone":"+1 814 371 3890",
    "sg:postcode":"15801",
    "sg:province":"PA",
    "sg:tags":[
        "cleaners",
        "tailor",
        "custom"
    ],
    "wof:name":"Paris Dry Cleaners",
    "wof:placetype":"venue"
},
  "geometry": {"coordinates":[-78.764685,41.12079],"type":"Point"}
}