{
  "type": "Feature",
  "properties": {
    "addr:full":"4080 Parkside Ct Mount Joy PA 17552",
    "addr:housenumber":"4080",
    "addr:postcode":"17552",
    "addr:street":"Parkside Ct",
    "iso:country":"US",
    "sg:address":"4080 Parkside Ct",
    "sg:city":"Mount Joy",
    "sg:classifiers":[
        {
            "category":"Building & Trades",
            "subcategory":"Construction",
            "type":"Services"
        }
    ],
    "sg:phone":"+1   ",
    "sg:postcode":"17552",
    "sg:province":"PA",
    "sg:tags":[
        "contractor"
    ],
    "wof:name":"John Wonders Drywall Inc",
    "wof:placetype":"venue"
},
  "geometry": {"coordinates":[-76.464635,40.06861],"type":"Point"}
}