{
  "type": "Feature",
  "properties": {
    "addr:full":"47 Progress Ave Cranberry Township PA 16066",
    "addr:housenumber":"47",
    "addr:postcode":"16066",
    "addr:street":"Progress Ave",
    "iso:country":"US",
    "sg:address":"47 Progress Ave",
    "sg:city":"Cranberry Township",
    "sg:classifiers":[
        {
            "category":"Wholesale",
            "subcategory":"Machinery & Supplies",
            "type":"Manufacturing & Wholesale Goods"
        }
    ],
    "sg:phone":"+1   ",
    "sg:postcode":"16066",
    "sg:province":"PA",
    "sg:tags":[
        "equipment",
        "material",
        "forklift",
        "handling"
    ],
    "wof:name":"Wellco Equipment LLC",
    "wof:placetype":"venue"
},
  "geometry": {"coordinates":[-80.10799799999999,40.708378],"type":"Point"}
}