{
  "type": "Feature",
  "properties": {
    "addr:full":"2649 Schoenersville Rd Bethlehem PA 18017",
    "addr:housenumber":"2649",
    "addr:postcode":"18017",
    "addr:street":"Schoenersville Rd",
    "iso:country":"US",
    "sg:address":"2649 Schoenersville Rd",
    "sg:city":"Bethlehem",
    "sg:classifiers":[
        {
            "category":"Health Services",
            "subcategory":"Doctor",
            "type":"Services"
        }
    ],
    "sg:phone":"+1 610 317 3440",
    "sg:postcode":"18017",
    "sg:province":"PA",
    "sg:tags":[
        "orthopedist"
    ],
    "wof:name":"Berger Barry MD",
    "wof:placetype":"venue"
},
  "geometry": {"coordinates":[-75.40830200000001,40.647499],"type":"Point"}
}