{
  "type": "Feature",
  "properties": {
    "iso:country":"US",
    "sg:address":"1429 Jackson St",
    "sg:city":"Philadelphia",
    "sg:classifiers":[
        {
            "category":"Restaurant",
            "type":"Food & Drink"
        }
    ],
    "sg:phone":"+1 215 755 1834",
    "sg:postcode":"19145",
    "sg:province":"PA",
    "sg:tags":[
        "pizza"
    ],
    "wof:name":"Salvatore's Pizzeria",
    "wof:placetype":"venue"
},
  "geometry": {"coordinates":[-75.17111300000001,39.923456],"type":"Point"}
}