{
  "type": "Feature",
  "properties": {
    "iso:country":"US",
    "sg:address":"14441 Mountain Green Rd",
    "sg:city":"Willow Hill",
    "sg:classifiers":[
        {
            "category":"Farming",
            "subcategory":"Livestock Farm",
            "type":"Manufacturing & Wholesale Goods"
        }
    ],
    "sg:phone":"+1   ",
    "sg:postcode":"17271",
    "sg:province":"PA",
    "sg:tags":[
        "hog",
        "or",
        "feedlot"
    ],
    "wof:name":"Diem & Yohn Swine Enterpr",
    "wof:placetype":"venue"
},
  "geometry": {"coordinates":[-77.794956,40.10953],"type":"Point"}
}