{
  "type": "Feature",
  "properties": {
    "addr:full":"304 N Saint Johns Rd Camp Hill PA 17011",
    "addr:housenumber":"304",
    "addr:postcode":"17011",
    "addr:street":"N Saint Johns Rd",
    "iso:country":"US",
    "sg:address":"304 N Saint Johns Rd",
    "sg:city":"Camp Hill",
    "sg:classifiers":[
        {
            "category":"Manufacturing",
            "subcategory":"Wood Products",
            "type":"Manufacturing & Wholesale Goods"
        }
    ],
    "sg:phone":"+1   ",
    "sg:postcode":"17011",
    "sg:province":"PA",
    "sg:tags":[
        "mfg"
    ],
    "wof:name":"Appalachian Wood Designs",
    "wof:placetype":"venue"
},
  "geometry": {"coordinates":[-76.94199500000001,40.220334],"type":"Point"}
}