{
  "type": "Feature",
  "properties": {
    "iso:country":"US",
    "sg:address":"277 Rolling Hills Rd",
    "sg:city":"Kittanning",
    "sg:classifiers":[
        {
            "category":"Farming",
            "subcategory":"Livestock Farm",
            "type":"Manufacturing & Wholesale Goods"
        },
        {
            "category":"Farming",
            "subcategory":"Farm",
            "type":"Manufacturing & Wholesale Goods"
        }
    ],
    "sg:phone":"+1 724 543 9050",
    "sg:postcode":"16201",
    "sg:province":"PA",
    "sg:tags":[
        "ranch"
    ],
    "wof:name":"Arthur Storey",
    "wof:placetype":"venue"
},
  "geometry": {"coordinates":[-79.588865,40.86137],"type":"Point"}
}