{
  "type": "Feature",
  "properties": {
    "addr:full":"2035 Harrison Ave Jeannette PA 15644",
    "addr:housenumber":"2035",
    "addr:postcode":"15644",
    "addr:street":"Harrison Ave",
    "iso:country":"US",
    "sg:address":"2035 Harrison Ave",
    "sg:city":"Jeannette",
    "sg:classifiers":[
        {
            "category":"Bars & Pubs",
            "type":"Food & Drink"
        }
    ],
    "sg:phone":"+1   ",
    "sg:postcode":"15644",
    "sg:province":"PA",
    "sg:tags":[
        "bar"
    ],
    "wof:name":"Skis & Nicks Lounge Inc",
    "wof:placetype":"venue"
},
  "geometry": {"coordinates":[-79.63800500000001,40.347287],"type":"Point"}
}