{
  "type": "Feature",
  "properties": {
    "addr:full":"15 S Stewart St Blairsville PA 15717",
    "addr:housenumber":"15",
    "addr:postcode":"15717",
    "addr:street":"S Stewart St",
    "iso:country":"US",
    "sg:address":"15 S Stewart St",
    "sg:city":"Blairsville",
    "sg:classifiers":[
        {
            "category":"Banks & Credit Unions",
            "subcategory":"Investment Brokerage",
            "type":"Services"
        }
    ],
    "sg:phone":"+1 724 459 5390",
    "sg:postcode":"15717",
    "sg:province":"PA",
    "wof:name":"KWW Investments Inc",
    "wof:placetype":"venue"
},
  "geometry": {"coordinates":[-79.262973,40.430563],"type":"Point"}
}