{
  "type": "Feature",
  "properties": {
    "iso:country":"US",
    "sg:address":"78 S Wyoming Ave",
    "sg:city":"Kingston",
    "sg:classifiers":[
        {
            "category":"Banks & Credit Unions",
            "subcategory":"Bank",
            "type":"Services"
        }
    ],
    "sg:phone":"+1 570 283 4462",
    "sg:postcode":"18704",
    "sg:province":"PA",
    "sg:tags":[
        "loan",
        "commercial",
        "real estate",
        "national"
    ],
    "wof:name":"First Liberty Bank and Trust",
    "wof:placetype":"venue"
},
  "geometry": {"coordinates":[-75.89900299999999,41.260224],"type":"Point"}
}