{
  "type": "Feature",
  "properties": {
    "iso:country":"US",
    "sg:address":"311 Sharp Ave",
    "sg:city":"Glenolden",
    "sg:classifiers":[
        {
            "category":"Arts & Performance",
            "subcategory":"Theater",
            "type":"Entertainment"
        }
    ],
    "sg:phone":"+1 610 506 2083",
    "sg:postcode":"19036",
    "sg:province":"PA",
    "sg:tags":[
        "music"
    ],
    "wof:name":"Sound Mission Inc",
    "wof:placetype":"venue"
},
  "geometry": {"coordinates":[-75.287175,39.892414],"type":"Point"}
}