{
  "type": "Feature",
  "properties": {
    "addr:full":"50 Paradise Ln Paradise PA 17562",
    "addr:housenumber":"50",
    "addr:postcode":"17562",
    "addr:street":"Paradise Ln",
    "iso:country":"US",
    "sg:address":"50 Paradise Ln",
    "sg:city":"Paradise",
    "sg:classifiers":[
        {
            "category":"Manufacturing",
            "subcategory":"Wood Products",
            "type":"Manufacturing & Wholesale Goods"
        }
    ],
    "sg:phone":"+1 717 687 8866",
    "sg:postcode":"17562",
    "sg:province":"PA",
    "sg:tags":[
        "turning",
        "carving"
    ],
    "wof:name":"R M Mccullough & Company",
    "wof:placetype":"venue"
},
  "geometry": {"coordinates":[-76.13514499999999,40.009262],"type":"Point"}
}