{
  "type": "Feature",
  "properties": {
    "addr:full":"3619 Germantown Ave Philadelphia PA 19140",
    "addr:housenumber":"3619",
    "addr:postcode":"19140",
    "addr:street":"Germantown Ave",
    "iso:country":"US",
    "sg:address":"3619 Germantown Ave",
    "sg:city":"Philadelphia",
    "sg:classifiers":[
        {
            "category":"Shopping",
            "subcategory":"Shoes",
            "type":"Retail Goods"
        }
    ],
    "sg:phone":"+1 215 229 2700",
    "sg:postcode":"19140",
    "sg:province":"PA",
    "sg:tags":[
        "store"
    ],
    "wof:name":"Brothers Shoes Inc",
    "wof:placetype":"venue"
},
  "geometry": {"coordinates":[-75.150398,40.007801],"type":"Point"}
}