{
  "type": "Feature",
  "properties": {
    "iso:country":"US",
    "sg:address":"2156 E Chelten Ave ",
    "sg:city":"Philadelphia",
    "sg:classifiers":[
        {
            "category":"Restaurant",
            "type":"Food & Drink"
        }
    ],
    "sg:menulink":"http://www.allmenus.com/pa/philadelphia/292169-china-ruby-chinese-restaurant/menu/",
    "sg:phone":"+1 215 927 5949",
    "sg:postcode":"19138",
    "sg:province":"PA",
    "sg:tags":[
        "soup",
        "seafood",
        "chicken"
    ],
    "wof:name":"China Ruby Chinese Restaurant",
    "wof:placetype":"venue"
},
  "geometry": {"coordinates":[-75.157257,40.0518],"type":"Point"}
}