{
  "type": "Feature",
  "properties": {
    "iso:country":"US",
    "sg:address":"1925 Waldheim Rd",
    "sg:city":"Hellertown",
    "sg:classifiers":[
        {
            "category":"Building & Trades",
            "subcategory":"Construction",
            "type":"Services"
        }
    ],
    "sg:phone":"+1 610 838 0997",
    "sg:postcode":"18015",
    "sg:province":"PA",
    "sg:tags":[
        "interior",
        "design"
    ],
    "sg:website":"web.me.com/catharine2/freedombyd...",
    "wof:name":"Freedom by Design",
    "wof:placetype":"venue"
},
  "geometry": {"coordinates":[-75.3422,40.5503],"type":"Point"}
}