{
  "type": "Feature",
  "properties": {
    "addr:full":"2245 Downing St Reading PA 19605",
    "addr:housenumber":"2245",
    "addr:postcode":"19605",
    "addr:street":"Downing St",
    "iso:country":"US",
    "sg:address":"2245 Downing St",
    "sg:city":"Reading",
    "sg:classifiers":[
        {
            "category":"Building & Trades",
            "subcategory":"Electrical",
            "type":"Services"
        }
    ],
    "sg:phone":"+1 610 926 7761",
    "sg:postcode":"19605",
    "sg:province":"PA",
    "sg:tags":[
        "electric",
        "contractor"
    ],
    "wof:name":"Dale T Sweigart Electric",
    "wof:placetype":"venue"
},
  "geometry": {"coordinates":[-75.942091,40.368373],"type":"Point"}
}