{
  "type": "Feature",
  "properties": {
    "iso:country":"US",
    "sg:address":"318 Newport Pl",
    "sg:city":"Exton",
    "sg:classifiers":[
        {
            "category":"Utilities",
            "subcategory":"Cable",
            "type":"Services"
        }
    ],
    "sg:phone":"+1   ",
    "sg:postcode":"19341",
    "sg:province":"PA",
    "sg:tags":[
        "television"
    ],
    "wof:name":"Teleshop Ltd",
    "wof:placetype":"venue"
},
  "geometry": {"coordinates":[-75.66274900000001,40.02568],"type":"Point"}
}