{
  "type": "Feature",
  "properties": {
    "addr:full":"110 S Main Ave Scranton PA 18504",
    "addr:housenumber":"110",
    "addr:postcode":"18504",
    "addr:street":"S Main Ave",
    "iso:country":"US",
    "sg:address":"110 S Main Ave",
    "sg:city":"Scranton",
    "sg:classifiers":[
        {
            "category":"Recreation",
            "type":"Entertainment"
        }
    ],
    "sg:phone":"+1 570 348 0342",
    "sg:postcode":"18504",
    "sg:province":"PA",
    "sg:tags":[
        "karate",
        "judo",
        "instr"
    ],
    "wof:name":"Summit Karate Club",
    "wof:placetype":"venue"
},
  "geometry": {"coordinates":[-75.680655,41.412205],"type":"Point"}
}