{
  "type": "Feature",
  "properties": {
    "addr:full":"34 Whitetail Dr Chadds Ford PA 19317",
    "addr:housenumber":"34",
    "addr:postcode":"19317",
    "addr:street":"Whitetail Dr",
    "iso:country":"US",
    "sg:address":"34 Whitetail Dr",
    "sg:city":"Chadds Ford",
    "sg:classifiers":[
        {
            "category":"Communications",
            "type":"Services"
        }
    ],
    "sg:phone":"+1   ",
    "sg:postcode":"19317",
    "sg:province":"PA",
    "sg:tags":[
        "communication"
    ],
    "wof:name":"Media Rooms Inc",
    "wof:placetype":"venue"
},
  "geometry": {"coordinates":[-75.647537,39.842953],"type":"Point"}
}