{
  "type": "Feature",
  "properties": {
    "iso:country":"US",
    "sg:address":"10111 Valley Forge Cir",
    "sg:city":"King Of Prussia",
    "sg:classifiers":[
        {
            "category":"Health Services",
            "subcategory":"Doctor",
            "type":"Services"
        }
    ],
    "sg:phone":"+1 610 337 2070",
    "sg:postcode":"19406",
    "sg:province":"PA",
    "sg:tags":[
        "dentist"
    ],
    "wof:name":"Rose Hollander Dental Assoc PC",
    "wof:placetype":"venue"
},
  "geometry": {"coordinates":[-75.41257,40.106802],"type":"Point"}
}