{
  "type": "Feature",
  "properties": {
    "addr:full":"RR 179 New Hope PA 18938",
    "addr:housenumber":"179",
    "addr:postcode":"18938",
    "iso:country":"US",
    "sg:address":"RR 179",
    "sg:city":"New Hope",
    "sg:classifiers":[
        {
            "category":"Shopping",
            "subcategory":"Pharmacy",
            "type":"Retail Goods"
        }
    ],
    "sg:phone":"+1 215 862 0101",
    "sg:postcode":"18938",
    "sg:province":"PA",
    "sg:tags":[
        "drugstore"
    ],
    "wof:name":"Cvs Pharmacy",
    "wof:placetype":"venue"
},
  "geometry": {"coordinates":[-75.003601,40.3629],"type":"Point"}
}