{
  "type": "Feature",
  "properties": {
    "iso:country":"US",
    "sg:address":"140 E Church St",
    "sg:city":"Sellersville",
    "sg:classifiers":[
        {
            "category":"Recreation",
            "type":"Entertainment"
        }
    ],
    "sg:phone":"+1   ",
    "sg:postcode":"18960",
    "sg:province":"PA",
    "wof:name":"Holiday House",
    "wof:placetype":"venue"
},
  "geometry": {"coordinates":[-75.31154600000001,40.361556],"type":"Point"}
}