{
  "type": "Feature",
  "properties": {
    "iso:country":"US",
    "sg:address":"2370 Morrow Rd",
    "sg:city":"Pittsburgh",
    "sg:classifiers":[
        {
            "category":"Health Services",
            "subcategory":"Doctor",
            "type":"Services"
        }
    ],
    "sg:phone":"+1 412 221 5249",
    "sg:postcode":"15241",
    "sg:province":"PA",
    "wof:name":"Axelson Alan A",
    "wof:placetype":"venue"
},
  "geometry": {"coordinates":[-80.091758,40.338577],"type":"Point"}
}