{
  "type": "Feature",
  "properties": {
    "iso:country":"US",
    "sg:address":"934 Western Ave",
    "sg:city":"Pittsburgh",
    "sg:classifiers":[
        {
            "category":"Professional",
            "subcategory":"Accounting & Tax Preparation",
            "type":"Services"
        }
    ],
    "sg:phone":"+1 412 322 2662",
    "sg:postcode":"15233",
    "sg:province":"PA",
    "sg:tags":[
        "accountant"
    ],
    "wof:name":"Poloka Michalik & Co",
    "wof:placetype":"venue"
},
  "geometry": {"coordinates":[-80.017303,40.451801],"type":"Point"}
}