{
  "type": "Feature",
  "properties": {
    "addr:full":"1900 Market St Philadelphia PA 19103",
    "addr:housenumber":"1900",
    "addr:postcode":"19103",
    "addr:street":"Market St",
    "iso:country":"US",
    "sg:address":"1900 Market St",
    "sg:city":"Philadelphia",
    "sg:classifiers":[
        {
            "category":"Professional",
            "subcategory":"Lawyer & Legal Services",
            "type":"Services"
        }
    ],
    "sg:phone":"+1 215 665 2000",
    "sg:postcode":"19103",
    "sg:province":"PA",
    "sg:tags":[
        "governmental",
        "law",
        "administrative",
        "attorney"
    ],
    "wof:name":"Rotella Jr., Salvatore G. - Cozen O'Connor, A Professional Corporation",
    "wof:placetype":"venue"
},
  "geometry": {"coordinates":[-75.17233299999999,39.953468],"type":"Point"}
}