{
  "type": "Feature",
  "properties": {
    "addr:full":"440 Brown St Philadelphia PA 19123",
    "addr:housenumber":"440",
    "addr:postcode":"19123",
    "addr:street":"Brown St",
    "iso:country":"US",
    "sg:address":"440 Brown St",
    "sg:city":"Philadelphia",
    "sg:classifiers":[
        {
            "category":"Shopping",
            "subcategory":"Stationery & Office Supplies",
            "type":"Retail Goods"
        }
    ],
    "sg:phone":"+1 215 627 2233",
    "sg:postcode":"19123",
    "sg:province":"PA",
    "sg:tags":[
        "equipment"
    ],
    "wof:name":"Market Street Stationers",
    "wof:placetype":"venue"
},
  "geometry": {"coordinates":[-75.145203,39.9641],"type":"Point"}
}