{
  "type": "Feature",
  "properties": {
    "iso:country":"US",
    "sg:address":"37 W Roseville Rd",
    "sg:city":"Lancaster",
    "sg:classifiers":[
        {
            "category":"Building & Trades",
            "subcategory":"Equipment Rental",
            "type":"Services"
        }
    ],
    "sg:phone":"+1 717 569 1122",
    "sg:postcode":"17601",
    "sg:province":"PA",
    "sg:tags":[
        "leasing"
    ],
    "wof:name":"Redstone Vendor Leasing",
    "wof:placetype":"venue"
},
  "geometry": {"coordinates":[-76.31494000000001,40.075545],"type":"Point"}
}