{
  "type": "Feature",
  "properties": {
    "iso:country":"US",
    "sg:address":"2959 Burnt House Hill Rd",
    "sg:city":"Doylestown",
    "sg:classifiers":[
        {
            "category":"Home & Garden",
            "subcategory":"Kitchen Supply",
            "type":"Retail Goods"
        }
    ],
    "sg:phone":"+1 215 794 5191",
    "sg:postcode":"18902",
    "sg:province":"PA",
    "sg:tags":[
        "utensil",
        "cookware"
    ],
    "wof:name":"Stovemate Products",
    "wof:placetype":"venue"
},
  "geometry": {"coordinates":[-75.07658600000001,40.327261],"type":"Point"}
}