{
  "type": "Feature",
  "properties": {
    "addr:full":"2529 Main St Birdsboro PA 19508",
    "addr:housenumber":"2529",
    "addr:postcode":"19508",
    "addr:street":"Main St",
    "iso:country":"US",
    "sg:address":"2529 Main St",
    "sg:city":"Birdsboro",
    "sg:classifiers":[
        {
            "category":"Manufacturing",
            "subcategory":"Chemicals & Compounds",
            "type":"Manufacturing & Wholesale Goods"
        }
    ],
    "sg:phone":"+1   ",
    "sg:postcode":"19508",
    "sg:province":"PA",
    "sg:tags":[
        "mfg",
        "cyclic"
    ],
    "wof:name":"Boczar Inc",
    "wof:placetype":"venue"
},
  "geometry": {"coordinates":[-75.87481099999999,40.285646],"type":"Point"}
}