{
  "type": "Feature",
  "properties": {
    "iso:country":"US",
    "sg:address":"8125 Slade Rd",
    "sg:city":"Harborcreek",
    "sg:classifiers":[
        {
            "category":"Farming",
            "subcategory":"Vineyard",
            "type":"Manufacturing & Wholesale Goods"
        }
    ],
    "sg:phone":"+1   ",
    "sg:postcode":"16421",
    "sg:province":"PA",
    "sg:tags":[
        "grape"
    ],
    "wof:name":"David & Mike Schneider",
    "wof:placetype":"venue"
},
  "geometry": {"coordinates":[-79.919095,42.171651],"type":"Point"}
}