{
  "type": "Feature",
  "properties": {
    "addr:full":"242 W Main St Monongahela PA 15063",
    "addr:housenumber":"242",
    "addr:postcode":"15063",
    "addr:street":"W Main St",
    "iso:country":"US",
    "sg:address":"242 W Main St",
    "sg:city":"Monongahela",
    "sg:classifiers":[
        {
            "category":"Shopping",
            "subcategory":"Jewelry",
            "type":"Retail Goods"
        }
    ],
    "sg:phone":"+1 724 258 2430",
    "sg:postcode":"15063",
    "sg:province":"PA",
    "wof:name":"Jewelry Store",
    "wof:placetype":"venue"
},
  "geometry": {"coordinates":[-79.924775,40.202019],"type":"Point"}
}