{
  "type": "Feature",
  "properties": {
    "addr:full":"2560 Renaissance Blvd King Of Prussia PA 19406",
    "addr:housenumber":"2560",
    "addr:postcode":"19406",
    "addr:street":"Renaissance Blvd",
    "iso:country":"US",
    "sg:address":"2560 Renaissance Blvd",
    "sg:city":"King Of Prussia",
    "sg:classifiers":[
        {
            "category":"Manufacturing",
            "subcategory":"Printing",
            "type":"Manufacturing & Wholesale Goods"
        }
    ],
    "sg:phone":"+1   ",
    "sg:postcode":"19406",
    "sg:province":"PA",
    "sg:tags":[
        "publishing"
    ],
    "wof:name":"Yellowbookcom",
    "wof:placetype":"venue"
},
  "geometry": {"coordinates":[-75.339524,40.084394],"type":"Point"}
}