{
  "type": "Feature",
  "properties": {
    "iso:country":"US",
    "sg:address":"1125 N 4th St",
    "sg:city":"Sunbury",
    "sg:classifiers":[
        {
            "category":"Wholesale",
            "subcategory":"Medical Equipment & Supplies",
            "type":"Manufacturing & Wholesale Goods"
        }
    ],
    "sg:phone":"+1 570 286 4400",
    "sg:postcode":"17801",
    "sg:province":"PA",
    "sg:tags":[
        "assistive",
        "aid",
        "device",
        "hearing"
    ],
    "wof:name":"Nu Ear",
    "wof:placetype":"venue"
},
  "geometry": {"coordinates":[-76.783973,40.87458],"type":"Point"}
}