{
  "type": "Feature",
  "properties": {
    "iso:country":"US",
    "sg:address":"1210 Stuart Ln",
    "sg:city":"Southampton",
    "sg:classifiers":[
        {
            "category":"Building & Trades",
            "subcategory":"Plumbing",
            "type":"Services"
        }
    ],
    "sg:phone":"+1   ",
    "sg:postcode":"18966",
    "sg:province":"PA",
    "sg:tags":[
        "contractor"
    ],
    "wof:name":"Ace Aire Inc",
    "wof:placetype":"venue"
},
  "geometry": {"coordinates":[-75.03536,40.18617],"type":"Point"}
}