{
  "type": "Feature",
  "properties": {
    "iso:country":"US",
    "sg:address":"5890 Easton Rd",
    "sg:city":"Pipersville",
    "sg:classifiers":[
        {
            "category":"Utilities",
            "subcategory":"Mobile Phone",
            "type":"Services"
        }
    ],
    "sg:phone":"+1 215 766 3900",
    "sg:postcode":"18947",
    "sg:province":"PA",
    "sg:tags":[
        "telephone",
        "cellular"
    ],
    "wof:name":"Americom Communications Inc",
    "wof:placetype":"venue"
},
  "geometry": {"coordinates":[-75.146643,40.387981],"type":"Point"}
}