{
  "type": "Feature",
  "properties": {
    "iso:country":"US",
    "sg:address":"2728 Germantown Ave",
    "sg:city":"Philadelphia",
    "sg:classifiers":[
        {
            "category":"Food & Beverages",
            "subcategory":"Meat & Fish",
            "type":"Retail Goods"
        }
    ],
    "sg:phone":"+1 215 223 0905",
    "sg:postcode":"19133",
    "sg:province":"PA",
    "sg:tags":[
        "shop"
    ],
    "wof:name":"Integrity Meats",
    "wof:placetype":"venue"
},
  "geometry": {"coordinates":[-75.147499,39.993801],"type":"Point"}
}