{
  "type": "Feature",
  "properties": {
    "iso:country":"US",
    "sg:address":"965 N 2nd St",
    "sg:city":"Philadelphia",
    "sg:classifiers":[
        {
            "category":"Sports & Exercise",
            "subcategory":"Gym",
            "type":"Entertainment"
        }
    ],
    "sg:phone":"+1 215 925 0525",
    "sg:postcode":"19123",
    "sg:province":"PA",
    "wof:name":"Jp Sneed Personal Fitness Studio",
    "wof:placetype":"venue"
},
  "geometry": {"coordinates":[-75.14005899999999,39.966165],"type":"Point"}
}