{
  "type": "Feature",
  "properties": {
    "iso:country":"US",
    "sg:address":"406 Countryside Dr",
    "sg:city":"Ephrata",
    "sg:classifiers":[
        {
            "category":"Professional",
            "type":"Services"
        }
    ],
    "sg:phone":"+1   ",
    "sg:postcode":"17522",
    "sg:province":"PA",
    "wof:name":"Katherine R Singer",
    "wof:placetype":"venue"
},
  "geometry": {"coordinates":[-76.200998,40.208593],"type":"Point"}
}