{
  "type": "Feature",
  "properties": {
    "iso:country":"US",
    "sg:address":"3019 N 25th St",
    "sg:city":"Philadelphia",
    "sg:classifiers":[
        {
            "category":"Retail",
            "subcategory":"Photofinishing",
            "type":"Services"
        }
    ],
    "sg:phone":"+1   ",
    "sg:postcode":"19132",
    "sg:province":"PA",
    "sg:tags":[
        "laboratory"
    ],
    "wof:name":"Providence Photo",
    "wof:placetype":"venue"
},
  "geometry": {"coordinates":[-75.171188,40.001086],"type":"Point"}
}