{
  "type": "Feature",
  "properties": {
    "iso:country":"US",
    "sg:address":"415 McFarlan Rd Ste 112",
    "sg:city":"Kennett Square",
    "sg:classifiers":[
        {
            "category":"Professional",
            "subcategory":"Lawyer & Legal Services",
            "type":"Services"
        }
    ],
    "sg:phone":"+1 610 444 2509",
    "sg:postcode":"19348",
    "sg:province":"PA",
    "wof:name":"James T Marsh P C",
    "wof:placetype":"venue"
},
  "geometry": {"coordinates":[-75.693298,39.853901],"type":"Point"}
}