{
  "type": "Feature",
  "properties": {
    "iso:country":"US",
    "sg:address":"523 Franklin Ave",
    "sg:city":"Vandergrift",
    "sg:classifiers":[
        {
            "category":"Food & Beverages",
            "subcategory":"Groceries & Convenience Stores",
            "type":"Retail Goods"
        }
    ],
    "sg:phone":"+1 724 567 1502",
    "sg:postcode":"15690",
    "sg:province":"PA",
    "sg:tags":[
        "grocer"
    ],
    "wof:name":"Vandergrift IGA",
    "wof:placetype":"venue"
},
  "geometry": {"coordinates":[-79.56641999999999,40.598072],"type":"Point"}
}