{
  "type": "Feature",
  "properties": {
    "addr:full":"19 E Main St Macungie PA 18062",
    "addr:housenumber":"19",
    "addr:postcode":"18062",
    "addr:street":"E Main St",
    "iso:country":"US",
    "sg:address":"19 E Main St",
    "sg:city":"Macungie",
    "sg:classifiers":[
        {
            "category":"Real Estate",
            "subcategory":"Real Estate Agent",
            "type":"Services"
        }
    ],
    "sg:phone":"+1 610 966 6000",
    "sg:postcode":"18062",
    "sg:province":"PA",
    "wof:name":"Greater Lehigh Vly Real Est Co",
    "wof:placetype":"venue"
},
  "geometry": {"coordinates":[-75.55555099999999,40.515795],"type":"Point"}
}