{
  "type": "Feature",
  "properties": {
    "iso:country":"US",
    "sg:address":"27 Avon St",
    "sg:city":"Wilkes Barre",
    "sg:classifiers":[
        {
            "category":"Professional",
            "type":"Services"
        }
    ],
    "sg:phone":"+1   ",
    "sg:postcode":"18702",
    "sg:province":"PA",
    "wof:name":"RA Snyder",
    "wof:placetype":"venue"
},
  "geometry": {"coordinates":[-75.830626,41.247554],"type":"Point"}
}