{
  "type": "Feature",
  "properties": {
    "addr:full":"11262 Baco Rd Meadville PA 16335",
    "addr:postcode":"11262;16335",
    "addr:street":"Baco Rd",
    "iso:country":"US",
    "sg:address":"11262 Baco Rd",
    "sg:city":"Meadville",
    "sg:classifiers":[
        {
            "category":"Freight",
            "type":"Transportation"
        }
    ],
    "sg:phone":"+1 814 724 5285",
    "sg:postcode":"16335",
    "sg:province":"PA",
    "sg:tags":[
        "operator",
        "local",
        "courier",
        "trucking"
    ],
    "sg:website":"www.velocityexpress.com",
    "wof:name":"Velocity Express Inc",
    "wof:placetype":"venue"
},
  "geometry": {"coordinates":[-80.218552,41.621283],"type":"Point"}
}