{
  "type": "Feature",
  "properties": {
    "iso:country":"US",
    "sg:address":"2605 E Street Rd",
    "sg:city":"Bensalem",
    "sg:classifiers":[
        {
            "category":"Building & Trades",
            "subcategory":"Equipment Rental",
            "type":"Services"
        },
        {
            "category":"Cinema",
            "subcategory":"Movie Rental",
            "type":"Entertainment"
        }
    ],
    "sg:phone":"+1 215 245 0199",
    "sg:postcode":"19020",
    "sg:province":"PA",
    "sg:tags":[
        "video",
        "game",
        "leasing"
    ],
    "wof:name":"Bonbay Video",
    "wof:placetype":"venue"
},
  "geometry": {"coordinates":[-74.952174,40.10809],"type":"Point"}
}