{
  "type": "Feature",
  "properties": {
    "iso:country":"US",
    "sg:address":"376 Freeport Rd",
    "sg:city":"Pittsburgh",
    "sg:classifiers":[
        {
            "category":"Government",
            "subcategory":"Fire Station",
            "type":"Public Place"
        }
    ],
    "sg:phone":"+1 412 000 1111",
    "sg:postcode":"15238",
    "sg:province":"PA",
    "sg:tags":[
        "department"
    ],
    "wof:name":"O'Hara Twp Fire Dept",
    "wof:placetype":"venue"
},
  "geometry": {"coordinates":[-79.860023,40.494236],"type":"Point"}
}