{
  "type": "Feature",
  "properties": {
    "iso:country":"US",
    "sg:address":"400 Tasker St",
    "sg:city":"Philadelphia",
    "sg:classifiers":[
        {
            "category":"Government",
            "subcategory":"Office",
            "type":"Public Place"
        }
    ],
    "sg:phone":"+1 215 685 1885",
    "sg:postcode":"19148",
    "sg:province":"PA",
    "sg:tags":[
        "village"
    ],
    "wof:name":"Dickinson Square Playground",
    "wof:placetype":"venue"
},
  "geometry": {"coordinates":[-75.15267799999999,39.928416],"type":"Point"}
}