{
  "type": "Feature",
  "properties": {
    "iso:country":"US",
    "sg:address":"145 N Narberth Ave",
    "sg:city":"Narberth",
    "sg:classifiers":[
        {
            "category":"Health Services",
            "subcategory":"Doctor",
            "type":"Services"
        }
    ],
    "sg:phone":"+1 610 667 0650",
    "sg:postcode":"19072",
    "sg:province":"PA",
    "wof:name":"Lytton & Hart Family Medicine",
    "wof:placetype":"venue"
},
  "geometry": {"coordinates":[-75.260696,40.006699],"type":"Point"}
}