{
  "type": "Feature",
  "properties": {
    "iso:country":"US",
    "sg:address":"301 Hammond Rd",
    "sg:city":"Shippensburg",
    "sg:classifiers":[
        {
            "category":"Building & Trades",
            "subcategory":"Construction",
            "type":"Services"
        }
    ],
    "sg:phone":"+1 717 530 1247",
    "sg:postcode":"17257",
    "sg:province":"PA",
    "sg:tags":[
        "excavation",
        "grading",
        "contractor"
    ],
    "wof:name":"Affordable Excavating",
    "wof:placetype":"venue"
},
  "geometry": {"coordinates":[-77.43979299999999,40.091898],"type":"Point"}
}