{
  "type": "Feature",
  "properties": {
    "iso:country":"US",
    "sg:address":"1411 Liberty St",
    "sg:city":"Erie",
    "sg:classifiers":[
        {
            "category":"Manufacturing",
            "subcategory":"Tools & Machinery",
            "type":"Manufacturing & Wholesale Goods"
        },
        {
            "category":"Shopping",
            "subcategory":"Gifts & Souvenirs",
            "type":"Retail Goods"
        }
    ],
    "sg:phone":"+1 814 456 4228",
    "sg:postcode":"16502",
    "sg:province":"PA",
    "wof:name":"Bob's Speed & Sports Cards",
    "wof:placetype":"venue"
},
  "geometry": {"coordinates":[-80.095968,42.11394],"type":"Point"}
}