{
  "type": "Feature",
  "properties": {
    "addr:full":"20 S Maple St Easton PA 18042",
    "addr:housenumber":"20",
    "addr:postcode":"18042",
    "addr:street":"S Maple St",
    "iso:country":"US",
    "sg:address":"20 S Maple St",
    "sg:city":"Easton",
    "sg:classifiers":[
        {
            "category":"Shopping",
            "subcategory":"Musical Instruments",
            "type":"Retail Goods"
        }
    ],
    "sg:phone":"+1   ",
    "sg:postcode":"18042",
    "sg:province":"PA",
    "wof:name":"Finocchio Guitar Works",
    "wof:placetype":"venue"
},
  "geometry": {"coordinates":[-75.236058,40.688909],"type":"Point"}
}