{
  "type": "Feature",
  "properties": {
    "iso:country":"US",
    "sg:address":"204 Sunnybrook Rd",
    "sg:city":"Flourtown",
    "sg:classifiers":[
        {
            "category":"Restaurant",
            "type":"Food & Drink"
        }
    ],
    "sg:phone":"+1   ",
    "sg:postcode":"19031",
    "sg:province":"PA",
    "sg:tags":[
        "eating"
    ],
    "wof:name":"In Good Taste",
    "wof:placetype":"venue"
},
  "geometry": {"coordinates":[-75.207809,40.115231],"type":"Point"}
}