{
  "type": "Feature",
  "properties": {
    "iso:country":"US",
    "sg:address":"123 N 5th St",
    "sg:city":"Allentown",
    "sg:classifiers":[
        {
            "category":"Professional",
            "subcategory":"Lawyer & Legal Services",
            "type":"Services"
        }
    ],
    "sg:phone":"+1   ",
    "sg:postcode":"18102",
    "sg:province":"PA",
    "wof:name":"Maryesther S Merlo Esq",
    "wof:placetype":"venue"
},
  "geometry": {"coordinates":[-75.46925400000001,40.606089],"type":"Point"}
}