{
  "type": "Feature",
  "properties": {
    "iso:country":"US",
    "sg:address":"4610 W Penn Ave",
    "sg:city":"Sinking Spring",
    "sg:classifiers":[
        {
            "category":"Shopping",
            "type":"Retail Goods"
        }
    ],
    "sg:phone":"+1 610 678 6605",
    "sg:postcode":"19608",
    "sg:province":"PA",
    "sg:tags":[
        "candle"
    ],
    "sg:website":"www.shoppesofgreenvalley.com",
    "wof:name":"Candle Shoppe Of Green Valley",
    "wof:placetype":"venue"
},
  "geometry": {"coordinates":[-76.03516999999999,40.326367],"type":"Point"}
}