{
  "type": "Feature",
  "properties": {
    "addr:full":"1942 S Columbus Blvd Philadelphia PA 19148",
    "addr:housenumber":"1942",
    "addr:postcode":"19148",
    "addr:street":"S Columbus Blvd",
    "iso:country":"US",
    "sg:address":"1942 S Columbus Blvd",
    "sg:city":"Philadelphia",
    "sg:classifiers":[
        {
            "category":"Home & Garden",
            "subcategory":"Carpets & Floor Coverings",
            "type":"Retail Goods"
        }
    ],
    "sg:phone":"+1 215 755 4310",
    "sg:postcode":"19148",
    "sg:province":"PA",
    "sg:tags":[
        "mattress"
    ],
    "sg:website":"www.sleepys.com/",
    "wof:name":"Sleepy's, The Mattress Professionals",
    "wof:placetype":"venue"
},
  "geometry": {"coordinates":[-75.142568,39.922457],"type":"Point"}
}