{
  "type": "Feature",
  "properties": {
    "iso:country":"US",
    "sg:address":"1 Friends Ln",
    "sg:city":"Newtown",
    "sg:classifiers":[
        {
            "category":"Utilities",
            "subcategory":"Electric",
            "type":"Services"
        }
    ],
    "sg:phone":"+1   ",
    "sg:postcode":"18940",
    "sg:province":"PA",
    "wof:name":"Peco Energy",
    "wof:placetype":"venue"
},
  "geometry": {"coordinates":[-74.909395,40.227959],"type":"Point"}
}