{
  "type": "Feature",
  "properties": {
    "iso:country":"US",
    "sg:address":"208 W Main St",
    "sg:city":"Monongahela",
    "sg:classifiers":[
        {
            "category":"Banks & Credit Unions",
            "subcategory":"Bank",
            "type":"Services"
        }
    ],
    "sg:phone":"+1 724 258 7600",
    "sg:postcode":"15063",
    "sg:province":"PA",
    "sg:tags":[
        "financing",
        "broker",
        "mortgage"
    ],
    "wof:name":"Civic Consumer Discount Co",
    "wof:placetype":"venue"
},
  "geometry": {"coordinates":[-79.92440000000001,40.201698],"type":"Point"}
}