{
  "type": "Feature",
  "properties": {
    "iso:country":"US",
    "sg:address":"19 Providence Rd",
    "sg:city":"Hazleton",
    "sg:classifiers":[
        {
            "category":"Wholesale",
            "subcategory":"Construction Materials",
            "type":"Manufacturing & Wholesale Goods"
        }
    ],
    "sg:phone":"+1   ",
    "sg:postcode":"18202",
    "sg:province":"PA",
    "wof:name":"Burke E Educational Svstem",
    "wof:placetype":"venue"
},
  "geometry": {"coordinates":[-76.01276799999999,40.981536],"type":"Point"}
}