{
  "type": "Feature",
  "properties": {
    "iso:country":"US",
    "sg:address":"1800 Linglestown Rd",
    "sg:city":"Harrisburg",
    "sg:classifiers":[
        {
            "category":"Travel",
            "subcategory":"Travel Agent",
            "type":"Entertainment"
        }
    ],
    "sg:phone":"+1 717 233 7222",
    "sg:postcode":"17110",
    "sg:province":"PA",
    "sg:tags":[
        "agency",
        "bureau"
    ],
    "wof:name":"Firstworld Professional Travel",
    "wof:placetype":"venue"
},
  "geometry": {"coordinates":[-76.87136,40.327718],"type":"Point"}
}