{
  "type": "Feature",
  "properties": {
    "iso:country":"US",
    "sg:address":"608 Morgantown St",
    "sg:city":"Point Marion",
    "sg:classifiers":[
        {
            "category":"Restaurant",
            "type":"Food & Drink"
        }
    ],
    "sg:phone":"+1   ",
    "sg:postcode":"15474",
    "sg:province":"PA",
    "sg:tags":[
        "eating"
    ],
    "wof:name":"Pampered Chef",
    "wof:placetype":"venue"
},
  "geometry": {"coordinates":[-79.90005600000001,39.736105],"type":"Point"}
}