{
  "type": "Feature",
  "properties": {
    "iso:country":"US",
    "sg:address":"211 E 5th Ave",
    "sg:city":"Conshohocken",
    "sg:classifiers":[
        {
            "category":"Building & Trades",
            "subcategory":"Construction",
            "type":"Services"
        }
    ],
    "sg:phone":"+1   ",
    "sg:postcode":"19428",
    "sg:province":"PA",
    "sg:tags":[
        "contractor"
    ],
    "wof:name":"Sene Inc",
    "wof:placetype":"venue"
},
  "geometry": {"coordinates":[-75.300229,40.075598],"type":"Point"}
}