{
  "type": "Feature",
  "properties": {
    "iso:country":"US",
    "sg:address":"5219 Market St",
    "sg:city":"Philadelphia",
    "sg:classifiers":[
        {
            "category":"Shopping",
            "subcategory":"Gifts & Souvenirs",
            "type":"Retail Goods"
        }
    ],
    "sg:phone":"+1   ",
    "sg:postcode":"19139",
    "sg:province":"PA",
    "sg:tags":[
        "novelty"
    ],
    "wof:name":"Nothing Over 98 Store",
    "wof:placetype":"venue"
},
  "geometry": {"coordinates":[-75.225711,39.96016],"type":"Point"}
}