{
  "type": "Feature",
  "properties": {
    "addr:full":"222 E Hamilton St Allentown PA 18109",
    "addr:housenumber":"222",
    "addr:postcode":"18109",
    "addr:street":"E Hamilton St",
    "iso:country":"US",
    "sg:address":"222 E Hamilton St",
    "sg:city":"Allentown",
    "sg:classifiers":[
        {
            "category":"Bars & Pubs",
            "type":"Food & Drink"
        }
    ],
    "sg:phone":"+1 610 776 0383",
    "sg:postcode":"18109",
    "sg:province":"PA",
    "wof:name":"Freddie's Bar & Grille",
    "wof:placetype":"venue"
},
  "geometry": {"coordinates":[-75.450486,40.607907],"type":"Point"}
}