{
  "type": "Feature",
  "properties": {
    "iso:country":"US",
    "sg:address":"7211 Fairlane Village Mall",
    "sg:city":"Pottsville",
    "sg:classifiers":[
        {
            "category":"Real Estate",
            "subcategory":"Real Estate Operator",
            "type":"Services"
        }
    ],
    "sg:phone":"+1 570 429 1563",
    "sg:postcode":"17901",
    "sg:province":"PA",
    "sg:tags":[
        "mall",
        "shopping",
        "center"
    ],
    "sg:website":"www.shopfairlanevillage.com",
    "wof:name":"Fairlane Village Mall",
    "wof:placetype":"venue"
},
  "geometry": {"coordinates":[-76.191147,40.704854],"type":"Point"}
}