{
  "type": "Feature",
  "properties": {
    "iso:country":"US",
    "sg:address":"1706 Elmhurst Dr",
    "sg:city":"Whitehall",
    "sg:classifiers":[
        {
            "category":"Retail",
            "subcategory":"Portrait Studio",
            "type":"Services"
        }
    ],
    "sg:phone":"+1 610 799 5107",
    "sg:postcode":"18052",
    "sg:province":"PA",
    "sg:tags":[
        "photographer"
    ],
    "wof:name":"I-Do Videos Productions",
    "wof:placetype":"venue"
},
  "geometry": {"coordinates":[-75.505799,40.633761],"type":"Point"}
}