{
  "type": "Feature",
  "properties": {
    "iso:country":"US",
    "sg:address":"2165 Long Ln",
    "sg:city":"Lebanon",
    "sg:classifiers":[
        {
            "category":"Travel",
            "subcategory":"Hotels & Motels",
            "type":"Entertainment"
        }
    ],
    "sg:phone":"+1   ",
    "sg:postcode":"17046",
    "sg:province":"PA",
    "sg:tags":[
        "membership",
        "lodging"
    ],
    "wof:name":"Nu Chapter of Alpha State",
    "wof:placetype":"venue"
},
  "geometry": {"coordinates":[-76.45902,40.36194],"type":"Point"}
}