{
  "type": "Feature",
  "properties": {
    "addr:full":"8 S Huntington Ave Ste B Danville PA 17821",
    "addr:housenumber":"8",
    "addr:postcode":"17821",
    "addr:street":"S Huntington Ave Ste B",
    "iso:country":"US",
    "sg:address":"8 S Huntington Ave Ste B",
    "sg:city":"Danville",
    "sg:classifiers":[
        {
            "category":"Health Services",
            "subcategory":"Clinic",
            "type":"Services"
        },
        {
            "category":"Community Center",
            "type":"Public Place"
        }
    ],
    "sg:phone":"+1 570 458 0115",
    "sg:postcode":"17821",
    "sg:province":"PA",
    "sg:tags":[
        "medical"
    ],
    "wof:name":"Hollywood Clinic",
    "wof:placetype":"venue"
},
  "geometry": {"coordinates":[-76.60097,40.964109],"type":"Point"}
}