{
  "type": "Feature",
  "properties": {
    "iso:country":"US",
    "sg:address":"21884 US Hwy 119",
    "sg:city":"Punxsutawney",
    "sg:classifiers":[
        {
            "category":"Cinema",
            "subcategory":"Movie Rental",
            "type":"Entertainment"
        }
    ],
    "sg:phone":"+1   ",
    "sg:postcode":"15767",
    "sg:province":"PA",
    "sg:tags":[
        "video",
        "tape"
    ],
    "wof:name":"Movie Castle Inc",
    "wof:placetype":"venue"
},
  "geometry": {"coordinates":[-78.983481,40.928226],"type":"Point"}
}