{
  "type": "Feature",
  "properties": {
    "addr:full":"330 Progress Dr Telford PA 18969",
    "addr:housenumber":"330",
    "addr:postcode":"18969",
    "addr:street":"Progress Dr",
    "iso:country":"US",
    "sg:address":"330 Progress Dr",
    "sg:city":"Telford",
    "sg:classifiers":[
        {
            "category":"Manufacturing",
            "subcategory":"Metals",
            "type":"Manufacturing & Wholesale Goods"
        }
    ],
    "sg:phone":"+1 215 257 6519",
    "sg:postcode":"18969",
    "sg:province":"PA",
    "sg:tags":[
        "casting",
        "aluminum",
        "mfg",
        "foundry",
        "brass",
        "bronze"
    ],
    "wof:name":"Active Brass Foundry Inc",
    "wof:placetype":"venue"
},
  "geometry": {"coordinates":[-75.30773000000001,40.336267],"type":"Point"}
}