{
  "type": "Feature",
  "properties": {
    "iso:country":"US",
    "sg:address":"3045 Marietta Ave",
    "sg:city":"Lancaster",
    "sg:classifiers":[
        {
            "category":"Health Services",
            "subcategory":"Doctor",
            "type":"Services"
        }
    ],
    "sg:phone":"+1   ",
    "sg:postcode":"17601",
    "sg:province":"PA",
    "sg:tags":[
        "medical"
    ],
    "wof:name":"David E Fuchs MD",
    "wof:placetype":"venue"
},
  "geometry": {"coordinates":[-76.401319,40.058106],"type":"Point"}
}