{
  "type": "Feature",
  "properties": {
    "addr:full":"131 S Main St Alburtis PA 18011",
    "addr:housenumber":"131",
    "addr:postcode":"18011",
    "addr:street":"S Main St",
    "iso:country":"US",
    "sg:address":"131 S Main St",
    "sg:city":"Alburtis",
    "sg:classifiers":[
        {
            "category":"Shopping",
            "type":"Retail Goods"
        }
    ],
    "sg:phone":"+1 610 967 6618",
    "sg:postcode":"18011",
    "sg:province":"PA",
    "sg:tags":[
        "art",
        "gallery",
        "dealer"
    ],
    "wof:name":"Old Vic Art Gallery & Frame",
    "wof:placetype":"venue"
},
  "geometry": {"coordinates":[-75.603683,40.511307],"type":"Point"}
}