{
  "type": "Feature",
  "properties": {
    "addr:full":"592 Moores Hill Rd Berwick PA 18603",
    "addr:housenumber":"592",
    "addr:postcode":"18603",
    "addr:street":"Moores Hill Rd",
    "iso:country":"US",
    "sg:address":"592 Moores Hill Rd",
    "sg:city":"Berwick",
    "sg:classifiers":[
        {
            "category":"Shopping",
            "subcategory":"Gifts & Souvenirs",
            "type":"Retail Goods"
        }
    ],
    "sg:phone":"+1 570 387 6157",
    "sg:postcode":"18603",
    "sg:province":"PA",
    "sg:tags":[
        "shop"
    ],
    "wof:name":"Into Light",
    "wof:placetype":"venue"
},
  "geometry": {"coordinates":[-76.223945,41.104585],"type":"Point"}
}