{
  "type": "Feature",
  "properties": {
    "iso:country":"US",
    "sg:address":"130 Anderson Ln",
    "sg:city":"Pittsburgh",
    "sg:classifiers":[
        {
            "category":"Building & Trades",
            "subcategory":"Plumbing",
            "type":"Services"
        }
    ],
    "sg:phone":"+1   ",
    "sg:postcode":"15239",
    "sg:province":"PA",
    "sg:tags":[
        "contractor"
    ],
    "wof:name":"Restano Michael Htg & Coolg",
    "wof:placetype":"venue"
},
  "geometry": {"coordinates":[-79.769792,40.485363],"type":"Point"}
}