{
  "type": "Feature",
  "properties": {
    "iso:country":"US",
    "sg:address":"100 West Ave",
    "sg:city":"Hanover",
    "sg:classifiers":[
        {
            "category":"Professional",
            "subcategory":"Advertising",
            "type":"Services"
        }
    ],
    "sg:phone":"+1   ",
    "sg:postcode":"17331",
    "sg:province":"PA",
    "sg:tags":[
        "agency"
    ],
    "wof:name":"Smeltzer Advertising",
    "wof:placetype":"venue"
},
  "geometry": {"coordinates":[-76.98724300000001,39.813679],"type":"Point"}
}