{
  "type": "Feature",
  "properties": {
    "iso:country":"US",
    "sg:address":"850 Clairton Blvd # 3300",
    "sg:city":"Pittsburgh",
    "sg:classifiers":[
        {
            "category":"Health Services",
            "subcategory":"Doctor",
            "type":"Services"
        }
    ],
    "sg:phone":"+1 412 466 5004",
    "sg:postcode":"15236",
    "sg:province":"PA",
    "sg:tags":[
        "physician",
        "surgeon"
    ],
    "wof:name":"Godinez, Lucas, Do - Pediatric Alliance",
    "wof:placetype":"venue"
},
  "geometry": {"coordinates":[-79.943624,40.324341],"type":"Point"}
}