{
  "type": "Feature",
  "properties": {
    "iso:country":"US",
    "sg:address":"3360 Kensington Ave",
    "sg:city":"Philadelphia",
    "sg:classifiers":[
        {
            "category":"Home & Garden",
            "subcategory":"Hardware",
            "type":"Retail Goods"
        }
    ],
    "sg:phone":"+1 215 423 4070",
    "sg:postcode":"19134",
    "sg:province":"PA",
    "sg:tags":[
        "store"
    ],
    "wof:name":"Siedmans Hardware",
    "wof:placetype":"venue"
},
  "geometry": {"coordinates":[-75.109497,39.998501],"type":"Point"}
}