{
  "type": "Feature",
  "properties": {
    "iso:country":"US",
    "sg:address":"109 Cherry St",
    "sg:city":"Towanda",
    "sg:classifiers":[
        {
            "category":"Organizations",
            "subcategory":"Religious Organization",
            "type":"Services"
        }
    ],
    "sg:phone":"+1 570 265 6213",
    "sg:postcode":"18848",
    "sg:province":"PA",
    "sg:tags":[
        "church"
    ],
    "wof:name":"Independent Baptist Church",
    "wof:placetype":"venue"
},
  "geometry": {"coordinates":[-76.445381,41.777658],"type":"Point"}
}