{
  "type": "Feature",
  "properties": {
    "iso:country":"US",
    "sg:address":"513 Hamel Ave",
    "sg:city":"Glenside",
    "sg:classifiers":[
        {
            "category":"Wholesale",
            "subcategory":"Construction Materials",
            "type":"Manufacturing & Wholesale Goods"
        },
        {
            "category":"Home & Garden",
            "subcategory":"Building Materials",
            "type":"Retail Goods"
        }
    ],
    "sg:phone":"+1 215 887 8482",
    "sg:postcode":"19038",
    "sg:province":"PA",
    "sg:tags":[
        "windows-wholesale",
        "window",
        "manufacturer"
    ],
    "wof:name":"Nicole Gesing Window Treatment",
    "wof:placetype":"venue"
},
  "geometry": {"coordinates":[-75.15801500000001,40.11639],"type":"Point"}
}