{
  "type": "Feature",
  "properties": {
    "iso:country":"US",
    "sg:address":"1518 Mount Nebo Rd",
    "sg:city":"Sewickley",
    "sg:classifiers":[
        {
            "category":"Manufacturing",
            "subcategory":"Signs",
            "type":"Manufacturing & Wholesale Goods"
        }
    ],
    "sg:phone":"+1 412 741 3153",
    "sg:postcode":"15143",
    "sg:province":"PA",
    "sg:tags":[
        "specialty",
        "business",
        "mfg"
    ],
    "wof:name":"Fred's Signs",
    "wof:placetype":"venue"
},
  "geometry": {"coordinates":[-80.105357,40.552983],"type":"Point"}
}