{
  "type": "Feature",
  "properties": {
    "iso:country":"US",
    "sg:address":"1044 Black Rock Rd",
    "sg:city":"Gladwyne",
    "sg:classifiers":[
        {
            "category":"Government",
            "subcategory":"Fire Station",
            "type":"Public Place"
        }
    ],
    "sg:phone":"+1 610 642 9586",
    "sg:postcode":"19035",
    "sg:province":"PA",
    "sg:tags":[
        "department"
    ],
    "wof:name":"Gladwyne Fire Co",
    "wof:placetype":"venue"
},
  "geometry": {"coordinates":[-75.279988,40.03959],"type":"Point"}
}