{
  "type": "Feature",
  "properties": {
    "iso:country":"US",
    "sg:address":"3 E Dutton Mill Rd",
    "sg:city":"Aston",
    "sg:classifiers":[
        {
            "category":"Insurance",
            "subcategory":"Insurance Agent",
            "type":"Services"
        }
    ],
    "sg:phone":"+1   ",
    "sg:postcode":"19014",
    "sg:province":"PA",
    "wof:name":"Jerry Fiordimondo Lutcf",
    "wof:placetype":"venue"
},
  "geometry": {"coordinates":[-75.416224,39.864543],"type":"Point"}
}