{
  "type": "Feature",
  "properties": {
    "iso:country":"US",
    "sg:address":"615 Knoxlyn Rd",
    "sg:city":"Gettysburg",
    "sg:classifiers":[
        {
            "category":"Retail",
            "subcategory":"Auto Repair",
            "type":"Services"
        }
    ],
    "sg:phone":"+1 717 337 2321",
    "sg:postcode":"17325",
    "sg:province":"PA",
    "sg:tags":[
        "body",
        "automobile",
        "painting",
        "repairing"
    ],
    "sg:website":"http://www.tckruisers.com",
    "wof:name":"T C Kruisers",
    "wof:placetype":"venue"
},
  "geometry": {"coordinates":[-77.301414,39.839534],"type":"Point"}
}