{
  "type": "Feature",
  "properties": {
    "iso:country":"US",
    "sg:address":"36 W Blaine St",
    "sg:city":"Mcadoo",
    "sg:classifiers":[
        {
            "category":"Recreation",
            "subcategory":"Arcade",
            "type":"Entertainment"
        }
    ],
    "sg:phone":"+1   ",
    "sg:postcode":"18237",
    "sg:province":"PA",
    "sg:tags":[
        "device",
        "operator",
        "machine",
        "vending",
        "amusement"
    ],
    "wof:name":"McAdoo Vending Company Inc",
    "wof:placetype":"venue"
},
  "geometry": {"coordinates":[-75.994107,40.902077],"type":"Point"}
}