{
  "type": "Feature",
  "properties": {
    "iso:country":"US",
    "sg:address":"100 Nesbitt Rd",
    "sg:city":"Neshannock",
    "sg:classifiers":[
        {
            "category":"Wholesale",
            "subcategory":"Machinery & Supplies",
            "type":"Manufacturing & Wholesale Goods"
        }
    ],
    "sg:phone":"+1 724 657 8930",
    "sg:postcode":"16105",
    "sg:province":"PA",
    "sg:tags":[
        "contractor"
    ],
    "wof:name":"Adam's Grove",
    "wof:placetype":"venue"
},
  "geometry": {"coordinates":[-80.357664,41.055555],"type":"Point"}
}