{
  "type": "Feature",
  "properties": {
    "iso:country":"US",
    "sg:address":"132 Market Rd",
    "sg:city":"Greeley",
    "sg:classifiers":[
        {
            "category":"Freight",
            "type":"Transportation"
        },
        {
            "category":"Wholesale",
            "subcategory":"Scrap",
            "type":"Manufacturing & Wholesale Goods"
        }
    ],
    "sg:phone":"+1 570 685 7586",
    "sg:postcode":"18425",
    "sg:province":"PA",
    "sg:tags":[
        "operator",
        "recycling",
        "local",
        "center",
        "trucking"
    ],
    "wof:name":"Charles E Steuhl & Sons Inc",
    "wof:placetype":"venue"
},
  "geometry": {"coordinates":[-75.00888999999999,41.432609],"type":"Point"}
}