{
  "type": "Feature",
  "properties": {
    "addr:full":"1115 New Rodgers Rd Bristol PA 19007",
    "addr:housenumber":"1115",
    "addr:postcode":"19007",
    "addr:street":"New Rodgers Rd",
    "iso:country":"US",
    "sg:address":"1115 New Rodgers Rd",
    "sg:city":"Bristol",
    "sg:classifiers":[
        {
            "category":"Professional",
            "subcategory":"Employment Agencies",
            "type":"Services"
        }
    ],
    "sg:phone":"+1 215 826 9590",
    "sg:postcode":"19007",
    "sg:province":"PA",
    "sg:tags":[
        "help",
        "supply"
    ],
    "wof:name":"Labor Ready Inc",
    "wof:placetype":"venue"
},
  "geometry": {"coordinates":[-74.877554,40.107908],"type":"Point"}
}