{
  "type": "Feature",
  "properties": {
    "addr:full":"375 Lime Oak Dr Pittsburgh PA 15235",
    "addr:housenumber":"375",
    "addr:postcode":"15235",
    "addr:street":"Lime Oak Dr",
    "iso:country":"US",
    "sg:address":"375 Lime Oak Dr",
    "sg:city":"Pittsburgh",
    "sg:classifiers":[
        {
            "category":"Professional",
            "subcategory":"Business Services",
            "type":"Services"
        }
    ],
    "sg:phone":"+1   ",
    "sg:postcode":"15235",
    "sg:province":"PA",
    "wof:name":"Ebony Enterprises",
    "wof:placetype":"venue"
},
  "geometry": {"coordinates":[-79.809031,40.471767],"type":"Point"}
}