{
  "type": "Feature",
  "properties": {
    "iso:country":"US",
    "sg:address":"1489 Willowbrook Dr",
    "sg:city":"Bethlehem",
    "sg:classifiers":[
        {
            "category":"Building & Trades",
            "subcategory":"Landscaping Services",
            "type":"Services"
        }
    ],
    "sg:phone":"+1 610 868 7484",
    "sg:postcode":"18015",
    "sg:province":"PA",
    "sg:tags":[
        "lawn",
        "maintenance",
        "gardener"
    ],
    "wof:name":"Freedom Lawn Care",
    "wof:placetype":"venue"
},
  "geometry": {"coordinates":[-75.381844,40.579849],"type":"Point"}
}