{
  "type": "Feature",
  "properties": {
    "iso:country":"US",
    "sg:address":"11 Kugler Rd",
    "sg:city":"Limerick",
    "sg:classifiers":[
        {
            "category":"Personal",
            "subcategory":"Beauty Salon",
            "type":"Services"
        }
    ],
    "sg:phone":"+1 610 495 8245",
    "sg:postcode":"19468",
    "sg:province":"PA",
    "sg:tags":[
        "shop",
        "manicuring"
    ],
    "wof:name":"Pretty Nails",
    "wof:placetype":"venue"
},
  "geometry": {"coordinates":[-75.52963200000001,40.242264],"type":"Point"}
}