{
  "type": "Feature",
  "properties": {
    "iso:country":"US",
    "sg:address":"127 E Brookhaven Rd",
    "sg:city":"Brookhaven",
    "sg:classifiers":[
        {
            "category":"Manufacturing",
            "subcategory":"Tools & Machinery",
            "type":"Manufacturing & Wholesale Goods"
        }
    ],
    "sg:phone":"+1 610 872 7991",
    "sg:postcode":"19015",
    "sg:province":"PA",
    "sg:tags":[
        "machine",
        "shop"
    ],
    "wof:name":"Dynamic Tool Co",
    "wof:placetype":"venue"
},
  "geometry": {"coordinates":[-75.387687,39.87299],"type":"Point"}
}