{
  "type": "Feature",
  "properties": {
    "iso:country":"US",
    "sg:address":"833 Market St",
    "sg:city":"Lemoyne",
    "sg:classifiers":[
        {
            "category":"Health Services",
            "subcategory":"Optometrist",
            "type":"Services"
        }
    ],
    "sg:phone":"+1   ",
    "sg:postcode":"17043",
    "sg:province":"PA",
    "wof:name":"Schwartz John F Dr",
    "wof:placetype":"venue"
},
  "geometry": {"coordinates":[-76.902603,40.24373],"type":"Point"}
}