{
  "type": "Feature",
  "properties": {
    "addr:full":"100 Porter Rd Tower City PA 17980",
    "addr:housenumber":"100",
    "addr:postcode":"17980",
    "addr:street":"Porter Rd",
    "iso:country":"US",
    "sg:address":"100 Porter Rd",
    "sg:city":"Tower City",
    "sg:classifiers":[
        {
            "category":"Building & Trades",
            "subcategory":"Cleaning & Sanitation",
            "type":"Services"
        }
    ],
    "sg:phone":"+1   ",
    "sg:postcode":"17980",
    "sg:province":"PA",
    "sg:tags":[
        "maintenance"
    ],
    "wof:name":"Garys Prof Crpt Clg Svc",
    "wof:placetype":"venue"
},
  "geometry": {"coordinates":[-76.583404,40.584466],"type":"Point"}
}