{
  "type": "Feature",
  "properties": {
    "addr:full":"2781 Buffalo Run Rd Bellefonte PA 16823",
    "addr:housenumber":"2781",
    "addr:postcode":"16823",
    "addr:street":"Buffalo Run Rd",
    "iso:country":"US",
    "sg:address":"2781 Buffalo Run Rd",
    "sg:city":"Bellefonte",
    "sg:classifiers":[
        {
            "category":"Food & Beverages",
            "subcategory":"Groceries & Convenience Stores",
            "type":"Retail Goods"
        }
    ],
    "sg:phone":"+1 814 355 4145",
    "sg:postcode":"16823",
    "sg:province":"PA",
    "wof:name":"Fillmore General Store",
    "wof:placetype":"venue"
},
  "geometry": {"coordinates":[-77.88153,40.854832],"type":"Point"}
}