{
  "type": "Feature",
  "properties": {
    "iso:country":"US",
    "sg:address":"1628 Elephant Rd",
    "sg:city":"Perkasie",
    "sg:classifiers":[
        {
            "category":"Social Services",
            "type":"Services"
        }
    ],
    "sg:phone":"+1 215 257 2923",
    "sg:postcode":"18944",
    "sg:province":"PA",
    "sg:tags":[
        "youth",
        "organization",
        "center"
    ],
    "wof:name":"Youth Services Of Bucks County",
    "wof:placetype":"venue"
},
  "geometry": {"coordinates":[-75.23092699999999,40.419323],"type":"Point"}
}