{
  "type": "Feature",
  "properties": {
    "iso:country":"US",
    "sg:address":"101 W Trenton Ave",
    "sg:city":"Morrisville",
    "sg:classifiers":[
        {
            "category":"Wholesale",
            "subcategory":"Machinery & Supplies",
            "type":"Manufacturing & Wholesale Goods"
        }
    ],
    "sg:phone":"+1 215 295 7400",
    "sg:postcode":"19067",
    "sg:province":"PA",
    "sg:tags":[
        "valve"
    ],
    "wof:name":"Managed Industrial",
    "wof:placetype":"venue"
},
  "geometry": {"coordinates":[-74.788082,40.214136],"type":"Point"}
}