{
  "type": "Feature",
  "properties": {
    "addr:full":"417 7th Ave Pittsburgh PA 15219",
    "addr:housenumber":"417",
    "addr:postcode":"15219",
    "addr:street":"7Th Ave",
    "iso:country":"US",
    "sg:address":"417 7th Ave",
    "sg:city":"Pittsburgh",
    "sg:classifiers":[
        {
            "category":"Manufacturing",
            "subcategory":"Printing",
            "type":"Manufacturing & Wholesale Goods"
        }
    ],
    "sg:phone":"+1   ",
    "sg:postcode":"15219",
    "sg:province":"PA",
    "sg:tags":[
        "lithographic",
        "commercial"
    ],
    "wof:name":"Sir Speedy",
    "wof:placetype":"venue"
},
  "geometry": {"coordinates":[-79.995841,40.442562],"type":"Point"}
}