{
  "type": "Feature",
  "properties": {
    "iso:country":"US",
    "sg:address":"2021 Cabot Blvd W",
    "sg:city":"Langhorne",
    "sg:classifiers":[
        {
            "category":"Manufacturing",
            "subcategory":"Chemicals & Compounds",
            "type":"Manufacturing & Wholesale Goods"
        }
    ],
    "sg:phone":"+1   ",
    "sg:postcode":"19047",
    "sg:province":"PA",
    "sg:tags":[
        "gelatin",
        "flavor",
        "dairy",
        "product",
        "mfg"
    ],
    "wof:name":"Degussa Hlth Ntrtn Amricas LLC",
    "wof:placetype":"venue"
},
  "geometry": {"coordinates":[-74.867632,40.191579],"type":"Point"}
}