{
  "type": "Feature",
  "properties": {
    "addr:full":"1720 State Rte 309 Coopersburg PA 18036",
    "addr:housenumber":"1720",
    "addr:postcode":"18036",
    "addr:street":"State Rte 309",
    "iso:country":"US",
    "sg:address":"1720 State Rte 309",
    "sg:city":"Coopersburg",
    "sg:classifiers":[
        {
            "category":"Retail",
            "subcategory":"Auto Rental",
            "type":"Services"
        }
    ],
    "sg:phone":"+1 610 282 9490",
    "sg:postcode":"18036",
    "sg:province":"PA",
    "sg:tags":[
        "renting",
        "truck",
        "leasing"
    ],
    "wof:name":"U-Haul Co",
    "wof:placetype":"venue"
},
  "geometry": {"coordinates":[-75.37996,40.491051],"type":"Point"}
}