{
  "type": "Feature",
  "properties": {
    "iso:country":"US",
    "sg:address":"1311 W Chester Rd",
    "sg:city":"West Chester",
    "sg:classifiers":[
        {
            "category":"Insurance",
            "subcategory":"Insurance Agent",
            "type":"Services"
        }
    ],
    "sg:phone":"+1   ",
    "sg:postcode":"19382",
    "sg:province":"PA",
    "wof:name":"Ed McCaffrey",
    "wof:placetype":"venue"
},
  "geometry": {"coordinates":[-75.547202,39.911213],"type":"Point"}
}