{
  "type": "Feature",
  "properties": {
    "iso:country":"US",
    "sg:address":"1111 North St",
    "sg:city":"Jim Thorpe",
    "sg:classifiers":[
        {
            "category":"Banks & Credit Unions",
            "subcategory":"Bank",
            "type":"Services"
        }
    ],
    "sg:phone":"+1 570 325 2265",
    "sg:postcode":"18229",
    "sg:province":"PA",
    "sg:website":"www.mauchchunktrust.com",
    "wof:name":"Mauch Chunk Trust Co",
    "wof:placetype":"venue"
},
  "geometry": {"coordinates":[-75.726479,40.881659],"type":"Point"}
}