{
  "type": "Feature",
  "properties": {
    "iso:country":"US",
    "sg:address":"1015 Prawls Hollow Rd",
    "sg:city":"Peach Bottom",
    "sg:classifiers":[
        {
            "category":"Personal",
            "subcategory":"Beauty Salon",
            "type":"Services"
        }
    ],
    "sg:phone":"+1 717 548 3550",
    "sg:postcode":"17563",
    "sg:province":"PA",
    "wof:name":"Christine Dickson Styling Sln",
    "wof:placetype":"venue"
},
  "geometry": {"coordinates":[-76.191591,39.815842],"type":"Point"}
}