{
  "type": "Feature",
  "properties": {
    "addr:full":"531 Crossroads Rd Mc Connellsburg PA 17233",
    "addr:housenumber":"531",
    "addr:postcode":"17233",
    "addr:street":"Crossroads Rd",
    "iso:country":"US",
    "sg:address":"531 Crossroads Rd",
    "sg:city":"Mc Connellsburg",
    "sg:classifiers":[
        {
            "category":"Building & Trades",
            "subcategory":"Construction",
            "type":"Services"
        }
    ],
    "sg:phone":"+1   ",
    "sg:postcode":"17233",
    "sg:province":"PA",
    "sg:tags":[
        "house"
    ],
    "wof:name":"Fred L Mellott Builders",
    "wof:placetype":"venue"
},
  "geometry": {"coordinates":[-77.99197700000001,39.899172],"type":"Point"}
}