{
  "type": "Feature",
  "properties": {
    "iso:country":"US",
    "sg:address":"12 Worman Rd",
    "sg:city":"Douglassville",
    "sg:classifiers":[
        {
            "category":"Professional",
            "subcategory":"Accounting & Tax Preparation",
            "type":"Services"
        }
    ],
    "sg:phone":"+1   ",
    "sg:postcode":"19518",
    "sg:province":"PA",
    "sg:tags":[
        "return"
    ],
    "wof:name":"Dinnella Income Tax Service",
    "wof:placetype":"venue"
},
  "geometry": {"coordinates":[-75.707497,40.302012],"type":"Point"}
}