{
  "type": "Feature",
  "properties": {
    "addr:full":"7122 Rising Sun Ave Philadelphia PA 19111",
    "addr:housenumber":"7122",
    "addr:postcode":"19111",
    "addr:street":"Rising Sun Ave",
    "iso:country":"US",
    "sg:address":"7122 Rising Sun Ave",
    "sg:city":"Philadelphia",
    "sg:classifiers":[
        {
            "category":"Health Services",
            "subcategory":"Dentist",
            "type":"Services"
        }
    ],
    "sg:phone":"+1 215 725 8300",
    "sg:postcode":"19111",
    "sg:province":"PA",
    "sg:tags":[
        "dentists-pediatric",
        "dentistry"
    ],
    "wof:name":"Reich Douglas R Dds",
    "wof:placetype":"venue"
},
  "geometry": {"coordinates":[-75.08656000000001,40.058802],"type":"Point"}
}