{
  "type": "Feature",
  "properties": {
    "addr:full":"1372 W Main St Uniontown PA 15401",
    "addr:housenumber":"1372",
    "addr:postcode":"15401",
    "addr:street":"W Main St",
    "iso:country":"US",
    "sg:address":"1372 W Main St",
    "sg:city":"Uniontown",
    "sg:classifiers":[
        {
            "category":"Cinema",
            "subcategory":"Movie Theater",
            "type":"Entertainment"
        }
    ],
    "sg:phone":"+1   ",
    "sg:postcode":"15401",
    "sg:province":"PA",
    "sg:tags":[
        "motion",
        "picture"
    ],
    "wof:name":"Carmike Cinemas",
    "wof:placetype":"venue"
},
  "geometry": {"coordinates":[-79.74830900000001,39.9128],"type":"Point"}
}