{
  "type": "Feature",
  "properties": {
    "iso:country":"US",
    "sg:address":"368 Eyth Rd",
    "sg:city":"Butler",
    "sg:classifiers":[
        {
            "category":"Professional",
            "subcategory":"Management & Consulting",
            "type":"Services"
        }
    ],
    "sg:phone":"+1 724 285 8181",
    "sg:postcode":"16002",
    "sg:province":"PA",
    "wof:name":"Darrell G Filges Inc",
    "wof:placetype":"venue"
},
  "geometry": {"coordinates":[-79.842787,40.893951],"type":"Point"}
}