{
  "type": "Feature",
  "properties": {
    "addr:full":"4457 Buffalo Rd Erie PA 16510",
    "addr:housenumber":"4457",
    "addr:postcode":"16510",
    "addr:street":"Buffalo Rd",
    "iso:country":"US",
    "sg:address":"4457 Buffalo Rd",
    "sg:city":"Erie",
    "sg:classifiers":[
        {
            "category":"Retail",
            "subcategory":"Laundry & Dry Cleaning",
            "type":"Services"
        }
    ],
    "sg:phone":"+1 814 898 3952",
    "sg:postcode":"16510",
    "sg:province":"PA",
    "sg:tags":[
        "cleaners"
    ],
    "wof:name":"VIP Laundry & Dry Cleaning",
    "wof:placetype":"venue"
},
  "geometry": {"coordinates":[-80.00173599999999,42.146706],"type":"Point"}
}