{
  "type": "Feature",
  "properties": {
    "addr:full":"1534 E State St Hermitage PA 16148",
    "addr:housenumber":"1534",
    "addr:postcode":"16148",
    "addr:street":"E State St",
    "iso:country":"US",
    "sg:address":"1534 E State St",
    "sg:city":"Hermitage",
    "sg:classifiers":[
        {
            "category":"Real Estate",
            "subcategory":"Real Estate Agent",
            "type":"Services"
        }
    ],
    "sg:phone":"+1 724 981 9979",
    "sg:postcode":"16148",
    "sg:province":"PA",
    "wof:name":"Colonial Penn Real Estate",
    "wof:placetype":"venue"
},
  "geometry": {"coordinates":[-80.48094399999999,41.23313],"type":"Point"}
}