{
  "type": "Feature",
  "properties": {
    "iso:country":"US",
    "sg:address":"920 Utica St",
    "sg:city":"Allentown",
    "sg:classifiers":[
        {
            "category":"Manufacturing",
            "subcategory":"Textiles",
            "type":"Manufacturing & Wholesale Goods"
        }
    ],
    "sg:phone":"+1 215 538 2880",
    "sg:postcode":"18102",
    "sg:province":"PA",
    "sg:tags":[
        "other",
        "fabric",
        "narrow"
    ],
    "wof:name":"Lawrence Schiff Silk Mls",
    "wof:placetype":"venue"
},
  "geometry": {"coordinates":[-75.48102,40.610015],"type":"Point"}
}