{
  "type": "Feature",
  "properties": {
    "iso:country":"US",
    "sg:address":"128 W Vaughn St",
    "sg:city":"Kingston",
    "sg:classifiers":[
        {
            "category":"Building & Trades",
            "subcategory":"Construction",
            "type":"Services"
        }
    ],
    "sg:phone":"+1 570 283 2057",
    "sg:postcode":"18704",
    "sg:province":"PA",
    "sg:tags":[
        "industrial",
        "contractors-commercial"
    ],
    "sg:website":"http://www.apickett.com",
    "wof:name":"A. Pickett Construction, Inc.",
    "wof:placetype":"venue"
},
  "geometry": {"coordinates":[-75.88755,41.27566],"type":"Point"}
}