{
  "type": "Feature",
  "properties": {
    "addr:full":"124 E Mill St Port Allegany PA 16743",
    "addr:housenumber":"124",
    "addr:postcode":"16743",
    "addr:street":"E Mill St",
    "iso:country":"US",
    "sg:address":"124 E Mill St",
    "sg:city":"Port Allegany",
    "sg:classifiers":[
        {
            "category":"Professional",
            "subcategory":"Accounting & Tax Preparation",
            "type":"Services"
        }
    ],
    "sg:phone":"+1 814 642 7553",
    "sg:postcode":"16743",
    "sg:province":"PA",
    "sg:tags":[
        "return",
        "filing"
    ],
    "wof:name":"R J Healy Tax Preparation",
    "wof:placetype":"venue"
},
  "geometry": {"coordinates":[-78.27805499999999,41.811676],"type":"Point"}
}