{
  "type": "Feature",
  "properties": {
    "iso:country":"US",
    "sg:address":"663 W Lancaster Ave",
    "sg:city":"Bryn Mawr",
    "sg:classifiers":[
        {
            "category":"Bakery",
            "type":"Food & Drink"
        }
    ],
    "sg:menulink":"http://www.allmenus.com/pa/haverford/23160-metropolitan-bakery/menu/",
    "sg:phone":"+1 610 581 7209",
    "sg:postcode":"19010",
    "sg:province":"PA",
    "sg:tags":[
        "american",
        "pastry"
    ],
    "wof:name":"Metropolitan Bakery",
    "wof:placetype":"venue"
},
  "geometry": {"coordinates":[-75.31251899999999,40.018715],"type":"Point"}
}