{
  "type": "Feature",
  "properties": {
    "addr:full":"1034 Strawntown Rd Quakertown PA 18951",
    "addr:housenumber":"1034",
    "addr:postcode":"18951",
    "addr:street":"Strawntown Rd",
    "iso:country":"US",
    "sg:address":"1034 Strawntown Rd",
    "sg:city":"Quakertown",
    "sg:classifiers":[
        {
            "category":"Arts & Performance",
            "subcategory":"Art Gallery",
            "type":"Entertainment"
        }
    ],
    "sg:phone":"+1 215 536 7130",
    "sg:postcode":"18951",
    "sg:province":"PA",
    "sg:tags":[
        "fine",
        "artist"
    ],
    "wof:name":"Joanne Isaac Etchings",
    "wof:placetype":"venue"
},
  "geometry": {"coordinates":[-75.28620100000001,40.470779],"type":"Point"}
}