{
  "type": "Feature",
  "properties": {
    "iso:country":"US",
    "sg:address":"202 Old York Rd",
    "sg:city":"Jenkintown",
    "sg:classifiers":[
        {
            "category":"Wholesale",
            "subcategory":"Home Furnishings",
            "type":"Manufacturing & Wholesale Goods"
        }
    ],
    "sg:phone":"+1 215 885 4455",
    "sg:postcode":"19046",
    "sg:province":"PA",
    "sg:tags":[
        "lamp",
        "shades"
    ],
    "wof:name":"Logan Electric",
    "wof:placetype":"venue"
},
  "geometry": {"coordinates":[-75.125348,40.093307],"type":"Point"}
}