{
  "type": "Feature",
  "properties": {
    "iso:country":"US",
    "sg:address":"401 Booth St",
    "sg:city":"Chester",
    "sg:classifiers":[
        {
            "category":"Home & Garden",
            "subcategory":"Building Materials",
            "type":"Retail Goods"
        }
    ],
    "sg:phone":"+1 610 497 0350",
    "sg:postcode":"19013",
    "sg:province":"PA",
    "sg:tags":[
        "glass",
        "window",
        "plate"
    ],
    "wof:name":"Chief's Auto Glass",
    "wof:placetype":"venue"
},
  "geometry": {"coordinates":[-75.39610999999999,39.8323],"type":"Point"}
}