{
  "type": "Feature",
  "properties": {
    "iso:country":"US",
    "sg:address":"4603 Springfield Ave",
    "sg:city":"Philadelphia",
    "sg:classifiers":[
        {
            "category":"Health Services",
            "subcategory":"Doctor",
            "type":"Services"
        }
    ],
    "sg:phone":"+1 215 222 0700",
    "sg:postcode":"19143",
    "sg:province":"PA",
    "sg:tags":[
        "dentist"
    ],
    "wof:name":"Lazarus Henry MD",
    "wof:placetype":"venue"
},
  "geometry": {"coordinates":[-75.213898,39.947701],"type":"Point"}
}