{
  "type": "Feature",
  "properties": {
    "addr:full":"27 N Chestnut St Elverson PA 19520",
    "addr:housenumber":"27",
    "addr:postcode":"19520",
    "addr:street":"N Chestnut St",
    "iso:country":"US",
    "sg:address":"27 N Chestnut St",
    "sg:city":"Elverson",
    "sg:classifiers":[
        {
            "category":"Social Services",
            "type":"Services"
        }
    ],
    "sg:phone":"+1 610 913 8413",
    "sg:postcode":"19520",
    "sg:province":"PA",
    "sg:tags":[
        "youth",
        "organization",
        "center"
    ],
    "wof:name":"Christian Service Brigade",
    "wof:placetype":"venue"
},
  "geometry": {"coordinates":[-75.83320399999999,40.157872],"type":"Point"}
}