{
  "type": "Feature",
  "properties": {
    "iso:country":"US",
    "sg:address":"847 Valley Forge Rd ",
    "sg:city":"Phoenixville",
    "sg:classifiers":[
        {
            "category":"Cafe",
            "type":"Food & Drink"
        }
    ],
    "sg:menulink":"http://www.allmenus.com/pa/schuylkill/289578-bookend-cafe/menu/",
    "sg:phone":"+1 610 933 4649",
    "sg:postcode":"19460",
    "sg:province":"PA",
    "sg:tags":[
        "american",
        "sandwich"
    ],
    "wof:name":"Bookend Cafe",
    "wof:placetype":"venue"
},
  "geometry": {"coordinates":[-75.50178099999999,40.120254],"type":"Point"}
}