{
  "type": "Feature",
  "properties": {
    "iso:country":"US",
    "sg:address":"2017 Market St",
    "sg:city":"Lewisburg",
    "sg:classifiers":[
        {
            "category":"Building & Trades",
            "subcategory":"Landscaping Services",
            "type":"Services"
        }
    ],
    "sg:phone":"+1 570 524 4933",
    "sg:postcode":"17837",
    "sg:province":"PA",
    "sg:tags":[
        "landscape",
        "contractor"
    ],
    "wof:name":"Hepners Landscaping Systems",
    "wof:placetype":"venue"
},
  "geometry": {"coordinates":[-76.904826,40.957863],"type":"Point"}
}