{
  "type": "Feature",
  "properties": {
    "iso:country":"US",
    "sg:address":"501 Grant St",
    "sg:city":"Pittsburgh",
    "sg:classifiers":[
        {
            "category":"Education",
            "subcategory":"Special Training",
            "type":"Public Place"
        }
    ],
    "sg:phone":"+1   ",
    "sg:postcode":"15219",
    "sg:province":"PA",
    "wof:name":"Disciplinry Bd Supm Court PA",
    "wof:placetype":"venue"
},
  "geometry": {"coordinates":[-79.99638899999999,40.440124],"type":"Point"}
}