{
  "type": "Feature",
  "properties": {
    "addr:full":"2 Walnut Grove Dr Horsham PA 19044",
    "addr:housenumber":"2",
    "addr:postcode":"19044",
    "addr:street":"Walnut Grove Dr",
    "iso:country":"US",
    "sg:address":"2 Walnut Grove Dr",
    "sg:city":"Horsham",
    "sg:classifiers":[
        {
            "category":"Professional",
            "subcategory":"Management & Consulting",
            "type":"Services"
        }
    ],
    "sg:phone":"+1   ",
    "sg:postcode":"19044",
    "sg:province":"PA",
    "sg:tags":[
        "launch",
        "trial",
        "clinical",
        "accelerate",
        "pharmaceutical"
    ],
    "wof:name":"Acurian Inc",
    "wof:placetype":"venue"
},
  "geometry": {"coordinates":[-75.14258100000001,40.167056],"type":"Point"}
}