{
  "type": "Feature",
  "properties": {
    "iso:country":"US",
    "sg:address":"925 New Rodgers Rd",
    "sg:city":"Levittown",
    "sg:classifiers":[
        {
            "category":"Retail",
            "subcategory":"Laundry & Dry Cleaning",
            "type":"Services"
        }
    ],
    "sg:phone":"+1 215 750 6925",
    "sg:postcode":"19056",
    "sg:province":"PA",
    "sg:tags":[
        "cleaners"
    ],
    "wof:name":"Aladdin Cleaners",
    "wof:placetype":"venue"
},
  "geometry": {"coordinates":[-74.894993,40.157654],"type":"Point"}
}