{
  "type": "Feature",
  "properties": {
    "iso:country":"US",
    "sg:address":"6225 Ridge Ave",
    "sg:city":"Philadelphia",
    "sg:classifiers":[
        {
            "category":"Autos & Motor Vehicles",
            "subcategory":"Automobile Sales",
            "type":"Retail Goods"
        }
    ],
    "sg:phone":"+1 215 483 3700",
    "sg:postcode":"19128",
    "sg:province":"PA",
    "sg:tags":[
        "car",
        "used",
        "dealer",
        "new"
    ],
    "wof:name":"Golden Chrysler Plymouth Parts",
    "wof:placetype":"venue"
},
  "geometry": {"coordinates":[-75.21753200000001,40.035743],"type":"Point"}
}