{
  "type": "Feature",
  "properties": {
    "iso:country":"US",
    "sg:address":"3266 Chichester Ave",
    "sg:city":"Marcus Hook",
    "sg:classifiers":[
        {
            "category":"Sports & Exercise",
            "subcategory":"Gym",
            "type":"Entertainment"
        }
    ],
    "sg:phone":"+1 610 485 2434",
    "sg:postcode":"19061",
    "sg:province":"PA",
    "sg:tags":[
        "club",
        "health",
        "studio",
        "gymnasium"
    ],
    "wof:name":"Curves For Women",
    "wof:placetype":"venue"
},
  "geometry": {"coordinates":[-75.44258000000001,39.837728],"type":"Point"}
}