{
  "type": "Feature",
  "properties": {
    "iso:country":"US",
    "sg:address":"5949 Steubenville Pike",
    "sg:city":"Mc Kees Rocks",
    "sg:classifiers":[
        {
            "category":"Building & Trades",
            "subcategory":"Construction",
            "type":"Services"
        }
    ],
    "sg:phone":"+1 412 787 8807",
    "sg:postcode":"15136",
    "sg:province":"PA",
    "sg:tags":[
        "home",
        "builder",
        "contractor"
    ],
    "wof:name":"Paragon Homes Inc",
    "wof:placetype":"venue"
},
  "geometry": {"coordinates":[-80.143799,40.445702],"type":"Point"}
}