{
  "type": "Feature",
  "properties": {
    "addr:full":"20 Walden Ct York PA 17404",
    "addr:housenumber":"20",
    "addr:postcode":"17404",
    "addr:street":"Walden Ct",
    "iso:country":"US",
    "sg:address":"20 Walden Ct",
    "sg:city":"York",
    "sg:classifiers":[
        {
            "category":"Banks & Credit Unions",
            "subcategory":"Financial Services",
            "type":"Services"
        }
    ],
    "sg:phone":"+1   ",
    "sg:postcode":"17404",
    "sg:province":"PA",
    "sg:tags":[
        "investor"
    ],
    "wof:name":"Investment Real Estate",
    "wof:placetype":"venue"
},
  "geometry": {"coordinates":[-76.79120500000001,40.015654],"type":"Point"}
}