{
  "type": "Feature",
  "properties": {
    "iso:country":"US",
    "sg:address":"100 8th St",
    "sg:city":"Charleroi",
    "sg:classifiers":[
        {
            "category":"Manufacturing",
            "subcategory":"Glass & Minerals",
            "type":"Manufacturing & Wholesale Goods"
        }
    ],
    "sg:phone":"+1   ",
    "sg:postcode":"15022",
    "sg:province":"PA",
    "sg:tags":[
        "product",
        "nonmetallic",
        "mfg"
    ],
    "wof:name":"Corning",
    "wof:placetype":"venue"
},
  "geometry": {"coordinates":[-79.900622,40.14187],"type":"Point"}
}