{
  "type": "Feature",
  "properties": {
    "addr:full":"5050 W Tilghman St Allentown PA 18104",
    "addr:housenumber":"5050",
    "addr:postcode":"18104",
    "addr:street":"W Tilghman St",
    "iso:country":"US",
    "sg:address":"5050 W Tilghman St",
    "sg:city":"Allentown",
    "sg:classifiers":[
        {
            "category":"Professional",
            "subcategory":"Lawyer & Legal Services",
            "type":"Services"
        }
    ],
    "sg:phone":"+1 610 391 1120",
    "sg:postcode":"18104",
    "sg:province":"PA",
    "sg:tags":[
        "attorney"
    ],
    "wof:name":"Maria C Mullane",
    "wof:placetype":"venue"
},
  "geometry": {"coordinates":[-75.569322,40.591239],"type":"Point"}
}