{
  "type": "Feature",
  "properties": {
    "iso:country":"US",
    "sg:address":"2103 W Market St",
    "sg:city":"York",
    "sg:classifiers":[
        {
            "category":"Wholesale",
            "subcategory":"Computers",
            "type":"Manufacturing & Wholesale Goods"
        }
    ],
    "sg:phone":"+1 717 854 2898",
    "sg:postcode":"17404",
    "sg:province":"PA",
    "sg:tags":[
        "consulting",
        "management"
    ],
    "wof:name":"Landmark Distributions Inc",
    "wof:placetype":"venue"
},
  "geometry": {"coordinates":[-76.77340700000001,39.952016],"type":"Point"}
}