{
  "type": "Feature",
  "properties": {
    "iso:country":"US",
    "sg:address":"2761 Orthodox St",
    "sg:city":"Philadelphia",
    "sg:classifiers":[
        {
            "category":"Real Estate",
            "subcategory":"Real Estate Services",
            "type":"Services"
        }
    ],
    "sg:phone":"+1 215 744 9426",
    "sg:postcode":"19137",
    "sg:province":"PA",
    "sg:tags":[
        "management",
        "property"
    ],
    "wof:name":"Rah Managaement Corp",
    "wof:placetype":"venue"
},
  "geometry": {"coordinates":[-75.073745,39.997827],"type":"Point"}
}