{
  "type": "Feature",
  "properties": {
    "iso:country":"US",
    "sg:address":"331 E Main St",
    "sg:city":"Collegeville",
    "sg:classifiers":[
        {
            "category":"Retail",
            "subcategory":"Car Wash",
            "type":"Services"
        }
    ],
    "sg:phone":"+1 610 291 7059",
    "sg:postcode":"19426",
    "sg:province":"PA",
    "sg:tags":[
        "carwash",
        "automobile",
        "detail",
        "clean"
    ],
    "wof:name":"Just Give Me The Details",
    "wof:placetype":"venue"
},
  "geometry": {"coordinates":[-75.45280200000001,40.187422],"type":"Point"}
}