{
  "type": "Feature",
  "properties": {
    "iso:country":"US",
    "sg:address":"5717 6th Ave",
    "sg:city":"Altoona",
    "sg:classifiers":[
        {
            "category":"Shopping",
            "subcategory":"Musical Instruments",
            "type":"Retail Goods"
        }
    ],
    "sg:phone":"+1 814 943 5569",
    "sg:postcode":"16602",
    "sg:province":"PA",
    "wof:name":"Ricche Music Store",
    "wof:placetype":"venue"
},
  "geometry": {"coordinates":[-78.42486,40.472365],"type":"Point"}
}