{
  "type": "Feature",
  "properties": {
    "iso:country":"US",
    "sg:address":"2134 S 10th St",
    "sg:city":"Philadelphia",
    "sg:classifiers":[
        {
            "category":"Food & Beverages",
            "subcategory":"Bakery",
            "type":"Retail Goods"
        }
    ],
    "sg:phone":"+1 215 339 9544",
    "sg:postcode":"19148",
    "sg:province":"PA",
    "sg:tags":[
        "restaurant"
    ],
    "wof:name":"Villari Brothers Bakery",
    "wof:placetype":"venue"
},
  "geometry": {"coordinates":[-75.1632,39.9226],"type":"Point"}
}