{
  "type": "Feature",
  "properties": {
    "iso:country":"US",
    "sg:address":"415 Johnson St",
    "sg:city":"Freeland",
    "sg:classifiers":[
        {
            "category":"Manufacturing",
            "subcategory":"Building Materials",
            "type":"Manufacturing & Wholesale Goods"
        }
    ],
    "sg:phone":"+1 570 636 1280",
    "sg:postcode":"18224",
    "sg:province":"PA",
    "wof:name":"Freeland Pattern Works Inc",
    "wof:placetype":"venue"
},
  "geometry": {"coordinates":[-75.89057099999999,41.020221],"type":"Point"}
}