{
  "type": "Feature",
  "properties": {
    "iso:country":"US",
    "sg:address":"500 Jones St",
    "sg:city":"Verona",
    "sg:classifiers":[
        {
            "category":"Bars & Pubs",
            "type":"Food & Drink"
        },
        {
            "category":"Restaurant",
            "type":"Food & Drink"
        }
    ],
    "sg:phone":"+1 412 828 3707",
    "sg:postcode":"15147",
    "sg:province":"PA",
    "sg:tags":[
        "tavern",
        "american",
        "pizza"
    ],
    "wof:name":"Rivertowne Inn",
    "wof:placetype":"venue"
},
  "geometry": {"coordinates":[-79.843559,40.501862],"type":"Point"}
}