{
  "type": "Feature",
  "properties": {
    "iso:country":"US",
    "sg:address":"1456 N Wales Rd",
    "sg:city":"North Wales",
    "sg:classifiers":[
        {
            "category":"Manufacturing",
            "subcategory":"Chemicals & Compounds",
            "type":"Manufacturing & Wholesale Goods"
        }
    ],
    "sg:phone":"+1   ",
    "sg:postcode":"19454",
    "sg:province":"PA",
    "sg:tags":[
        "preparation",
        "mfg"
    ],
    "wof:name":"Hardt Chemical Inc",
    "wof:placetype":"venue"
},
  "geometry": {"coordinates":[-75.26725500000001,40.223909],"type":"Point"}
}