{
  "type": "Feature",
  "properties": {
    "iso:country":"US",
    "sg:address":"812 Meredith Dr",
    "sg:city":"Media",
    "sg:classifiers":[
        {
            "category":"Professional",
            "subcategory":"Management & Consulting",
            "type":"Services"
        }
    ],
    "sg:phone":"+1 610 566 7270",
    "sg:postcode":"19063",
    "sg:province":"PA",
    "sg:tags":[
        "consultant",
        "business"
    ],
    "wof:name":"Pew-Dingfelder Corp",
    "wof:placetype":"venue"
},
  "geometry": {"coordinates":[-75.37340399999999,39.918697],"type":"Point"}
}