{
  "type": "Feature",
  "properties": {
    "iso:country":"US",
    "sg:address":"247 S 5th St",
    "sg:city":"Philadelphia",
    "sg:classifiers":[
        {
            "category":"Organizations",
            "subcategory":"Religious Organization",
            "type":"Services"
        }
    ],
    "sg:phone":"+1   ",
    "sg:postcode":"19106",
    "sg:province":"PA",
    "wof:name":"St Mary Convent",
    "wof:placetype":"venue"
},
  "geometry": {"coordinates":[-75.149666,39.94681],"type":"Point"}
}