{
  "type": "Feature",
  "properties": {
    "iso:country":"US",
    "sg:address":"6920 Gehr Rd",
    "sg:city":"St Thomas",
    "sg:classifiers":[
        {
            "category":"Building & Trades",
            "subcategory":"Construction",
            "type":"Services"
        }
    ],
    "sg:phone":"+1 717 369 2834",
    "sg:postcode":"17252",
    "sg:province":"PA",
    "sg:tags":[
        "concrete",
        "contractor"
    ],
    "wof:name":"Roy E Rummel Concrete Constr",
    "wof:placetype":"venue"
},
  "geometry": {"coordinates":[-77.79857699999999,39.891165],"type":"Point"}
}