{
  "type": "Feature",
  "properties": {
    "iso:country":"US",
    "sg:address":"581 Roberta Dr",
    "sg:city":"Pottstown",
    "sg:classifiers":[
        {
            "category":"Wholesale",
            "subcategory":"Motor Vehicles",
            "type":"Manufacturing & Wholesale Goods"
        }
    ],
    "sg:phone":"+1 610 326 8938",
    "sg:postcode":"19465",
    "sg:province":"PA",
    "sg:tags":[
        "automobile",
        "transporter"
    ],
    "wof:name":"Seaside Auto Transport Inc",
    "wof:placetype":"venue"
},
  "geometry": {"coordinates":[-75.661135,40.216549],"type":"Point"}
}