{
  "type": "Feature",
  "properties": {
    "iso:country":"US",
    "sg:address":"506 Saline St",
    "sg:city":"Pittsburgh",
    "sg:classifiers":[
        {
            "category":"Organizations",
            "subcategory":"Religious Organization",
            "type":"Services"
        }
    ],
    "sg:phone":"+1 412 421 0243",
    "sg:postcode":"15207",
    "sg:province":"PA",
    "sg:tags":[
        "church"
    ],
    "wof:name":"St John Chrysostom Church",
    "wof:placetype":"venue"
},
  "geometry": {"coordinates":[-79.94319400000001,40.429024],"type":"Point"}
}