{
  "type": "Feature",
  "properties": {
    "iso:country":"US",
    "sg:address":"105 McKinley Rd",
    "sg:city":"Beaver Falls",
    "sg:classifiers":[
        {
            "category":"Restaurant",
            "type":"Food & Drink"
        }
    ],
    "sg:phone":"+1 724 843 8040",
    "sg:postcode":"15010",
    "sg:province":"PA",
    "sg:tags":[
        "parlor",
        "ice",
        "cream"
    ],
    "wof:name":"Cow",
    "wof:placetype":"venue"
},
  "geometry": {"coordinates":[-80.388879,40.779886],"type":"Point"}
}