{
  "type": "Feature",
  "properties": {
    "addr:full":"802 Stony Battery Rd Lancaster PA 17601",
    "addr:housenumber":"802",
    "addr:postcode":"17601",
    "addr:street":"Stony Battery Rd",
    "iso:country":"US",
    "sg:address":"802 Stony Battery Rd",
    "sg:city":"Lancaster",
    "sg:classifiers":[
        {
            "category":"Food & Beverages",
            "subcategory":"Groceries & Convenience Stores",
            "type":"Retail Goods"
        }
    ],
    "sg:phone":"+1 717 285 3470",
    "sg:postcode":"17601",
    "sg:province":"PA",
    "wof:name":"Turkey Hill Minit Market",
    "wof:placetype":"venue"
},
  "geometry": {"coordinates":[-76.409502,40.063618],"type":"Point"}
}