{
  "type": "Feature",
  "properties": {
    "addr:full":"453 S Main Rd Mountain Top PA 18707",
    "addr:housenumber":"453",
    "addr:postcode":"18707",
    "addr:street":"S Main Rd",
    "iso:country":"US",
    "sg:address":"453 S Main Rd",
    "sg:city":"Mountain Top",
    "sg:classifiers":[
        {
            "category":"Health Services",
            "subcategory":"Nursing And Care Facility",
            "type":"Services"
        }
    ],
    "sg:phone":"+1 570 868 3664",
    "sg:postcode":"18707",
    "sg:province":"PA",
    "sg:tags":[
        "personal",
        "home",
        "skilled",
        "convalescent"
    ],
    "wof:name":"Smith Health Care LTD",
    "wof:placetype":"venue"
},
  "geometry": {"coordinates":[-75.92624000000001,41.125167],"type":"Point"}
}