{
  "type": "Feature",
  "properties": {
    "iso:country":"US",
    "sg:address":"100 Wally Dr",
    "sg:city":"Pittsburgh",
    "sg:classifiers":[
        {
            "category":"Professional",
            "subcategory":"Management & Consulting",
            "type":"Services"
        }
    ],
    "sg:phone":"+1   ",
    "sg:postcode":"15237",
    "sg:province":"PA",
    "sg:tags":[
        "administrative"
    ],
    "wof:name":"Conair Group",
    "wof:placetype":"venue"
},
  "geometry": {"coordinates":[-80.046667,40.542854],"type":"Point"}
}