{
  "type": "Feature",
  "properties": {
    "addr:full":"141 Rose Hill Rd Ephrata PA 17522",
    "addr:housenumber":"141",
    "addr:postcode":"17522",
    "addr:street":"Rose Hill Rd",
    "iso:country":"US",
    "sg:address":"141 Rose Hill Rd",
    "sg:city":"Ephrata",
    "sg:classifiers":[
        {
            "category":"Food & Beverages",
            "subcategory":"Fruits & Vegetables",
            "type":"Retail Goods"
        }
    ],
    "sg:phone":"+1   ",
    "sg:postcode":"17522",
    "sg:province":"PA",
    "wof:name":"Paul Neidermyers",
    "wof:placetype":"venue"
},
  "geometry": {"coordinates":[-76.231635,40.124355],"type":"Point"}
}