{
  "type": "Feature",
  "properties": {
    "iso:country":"US",
    "sg:address":"1314 Chestnut St",
    "sg:city":"Philadelphia",
    "sg:classifiers":[
        {
            "category":"Health Services",
            "subcategory":"Clinic",
            "type":"Services"
        },
        {
            "category":"Social Services",
            "type":"Services"
        }
    ],
    "sg:phone":"+1 215 735 0821",
    "sg:postcode":"19107",
    "sg:province":"PA",
    "sg:tags":[
        "home"
    ],
    "wof:name":"Home Care Associates",
    "wof:placetype":"venue"
},
  "geometry": {"coordinates":[-75.162358,39.950569],"type":"Point"}
}