{
  "type": "Feature",
  "properties": {
    "iso:country":"US",
    "sg:address":"101 W Meadow Dr",
    "sg:city":"West Grove",
    "sg:classifiers":[
        {
            "category":"Building & Trades",
            "subcategory":"Construction",
            "type":"Services"
        }
    ],
    "sg:phone":"+1 302 893 1970",
    "sg:postcode":"19390",
    "sg:province":"PA",
    "sg:tags":[
        "painter"
    ],
    "sg:website":"art-in-residence.com/",
    "wof:name":"Art in Residence",
    "wof:placetype":"venue"
},
  "geometry": {"coordinates":[-75.828309,39.815478],"type":"Point"}
}