{
  "type": "Feature",
  "properties": {
    "iso:country":"US",
    "sg:address":"60 Abele Rd",
    "sg:city":"Bridgeville",
    "sg:classifiers":[
        {
            "category":"Insurance",
            "subcategory":"Insurance Agent",
            "type":"Services"
        }
    ],
    "sg:phone":"+1 412 257 8353",
    "sg:postcode":"15017",
    "sg:province":"PA",
    "wof:name":"Biblical Financial Concepts",
    "wof:placetype":"venue"
},
  "geometry": {"coordinates":[-80.12538499999999,40.352206],"type":"Point"}
}