{
  "type": "Feature",
  "properties": {
    "iso:country":"US",
    "sg:address":"136 Kline Vlg",
    "sg:city":"Harrisburg",
    "sg:classifiers":[
        {
            "category":"Banks & Credit Unions",
            "subcategory":"Bank",
            "type":"Services"
        }
    ],
    "sg:phone":"+1 717 237 7389",
    "sg:postcode":"17104",
    "sg:province":"PA",
    "wof:name":"Pnc Bank",
    "wof:placetype":"venue"
},
  "geometry": {"coordinates":[-76.842326,40.27206],"type":"Point"}
}