{
  "type": "Feature",
  "properties": {
    "iso:country":"US",
    "sg:address":"110 Dolph St",
    "sg:city":"Olyphant",
    "sg:classifiers":[
        {
            "category":"Travel",
            "subcategory":"Travel Agent",
            "type":"Entertainment"
        }
    ],
    "sg:phone":"+1 570 489 5049",
    "sg:postcode":"18447",
    "sg:province":"PA",
    "sg:tags":[
        "tours",
        "promoter"
    ],
    "wof:name":"Tiger Tours",
    "wof:placetype":"venue"
},
  "geometry": {"coordinates":[-75.58066599999999,41.472263],"type":"Point"}
}