{
  "type": "Feature",
  "properties": {
    "iso:country":"US",
    "sg:address":"615 Main St",
    "sg:city":"Stroudsburg",
    "sg:classifiers":[
        {
            "category":"Manufacturing",
            "subcategory":"Electronics",
            "type":"Manufacturing & Wholesale Goods"
        }
    ],
    "sg:phone":"+1   ",
    "sg:postcode":"18360",
    "sg:province":"PA",
    "sg:tags":[
        "electronic",
        "component",
        "mfg"
    ],
    "wof:name":"Mitsubi-Spd/Larry Moucha",
    "wof:placetype":"venue"
},
  "geometry": {"coordinates":[-75.19315899999999,40.985542],"type":"Point"}
}