{
  "type": "Feature",
  "properties": {
    "iso:country":"US",
    "sg:address":"223 Ridge Rd",
    "sg:city":"Sellersville",
    "sg:classifiers":[
        {
            "category":"Personal",
            "subcategory":"Beauty Salon",
            "type":"Services"
        }
    ],
    "sg:phone":"+1 215 257 5782",
    "sg:postcode":"18960",
    "sg:province":"PA",
    "wof:name":"Sue Marx",
    "wof:placetype":"venue"
},
  "geometry": {"coordinates":[-75.31903200000001,40.373535],"type":"Point"}
}