{
  "type": "Feature",
  "properties": {
    "addr:full":"2459 Grace Ave Lebanon PA 17046",
    "addr:housenumber":"2459",
    "addr:postcode":"17046",
    "addr:street":"Grace Ave",
    "iso:country":"US",
    "sg:address":"2459 Grace Ave",
    "sg:city":"Lebanon",
    "sg:classifiers":[
        {
            "category":"Real Estate",
            "subcategory":"Real Estate Operator",
            "type":"Services"
        }
    ],
    "sg:phone":"+1   ",
    "sg:postcode":"17046",
    "sg:province":"PA",
    "sg:tags":[
        "mobile",
        "home",
        "site"
    ],
    "wof:name":"Swatara Mobile Home Pk",
    "wof:placetype":"venue"
},
  "geometry": {"coordinates":[-76.473527,40.394772],"type":"Point"}
}