{
  "type": "Feature",
  "properties": {
    "addr:full":"700 N Delaware Ave Philadelphia PA 19123",
    "addr:housenumber":"700",
    "addr:postcode":"19123",
    "addr:street":"N Delaware Ave",
    "iso:country":"US",
    "sg:address":"700 N Delaware Ave",
    "sg:city":"Philadelphia",
    "sg:phone":"+1 215 629 3569",
    "sg:postcode":"19123",
    "sg:province":"PA",
    "wof:name":"Club Flow",
    "wof:placetype":"venue"
},
  "geometry": {"coordinates":[-75.137047,39.960918],"type":"Point"}
}