{
  "type": "Feature",
  "properties": {
    "iso:country":"US",
    "sg:address":"2300 Chestnut St",
    "sg:city":"Philadelphia",
    "sg:classifiers":[
        {
            "category":"Professional",
            "subcategory":"Lawyer & Legal Services",
            "type":"Services"
        }
    ],
    "sg:phone":"+1 215 468 5444",
    "sg:postcode":"19103",
    "sg:province":"PA",
    "wof:name":"Kulp Rocco Dolores",
    "wof:placetype":"venue"
},
  "geometry": {"coordinates":[-75.178162,39.952494],"type":"Point"}
}