{
  "type": "Feature",
  "properties": {
    "iso:country":"US",
    "sg:address":"235 Industry Rd",
    "sg:city":"Buena Vista",
    "sg:classifiers":[
        {
            "category":"Building & Trades",
            "subcategory":"Electrical",
            "type":"Services"
        }
    ],
    "sg:phone":"+1   ",
    "sg:postcode":"15018",
    "sg:province":"PA",
    "sg:tags":[
        "electrical",
        "contractor"
    ],
    "wof:name":"S&L Electric",
    "wof:placetype":"venue"
},
  "geometry": {"coordinates":[-79.798346,40.272914],"type":"Point"}
}