{
  "type": "Feature",
  "properties": {
    "addr:full":"11205 Country Club Rd Waynesboro PA 17268",
    "addr:housenumber":"11205",
    "addr:postcode":"17268",
    "addr:street":"Country Club Rd",
    "iso:country":"US",
    "sg:address":"11205 Country Club Rd",
    "sg:city":"Waynesboro",
    "sg:classifiers":[
        {
            "category":"Travel",
            "subcategory":"Hotels & Motels",
            "type":"Entertainment"
        }
    ],
    "sg:phone":"+1 717 762 8525",
    "sg:postcode":"17268",
    "sg:province":"PA",
    "sg:tags":[
        "breakfast",
        "accommodation",
        "bed"
    ],
    "wof:name":"Risser & Risser",
    "wof:placetype":"venue"
},
  "geometry": {"coordinates":[-77.535956,39.761629],"type":"Point"}
}