{
  "type": "Feature",
  "properties": {
    "addr:full":"3330 Hulmeville Rd Bensalem PA 19020",
    "addr:housenumber":"3330",
    "addr:postcode":"19020",
    "addr:street":"Hulmeville Rd",
    "iso:country":"US",
    "sg:address":"3330 Hulmeville Rd",
    "sg:city":"Bensalem",
    "sg:classifiers":[
        {
            "category":"Social Services",
            "type":"Services"
        }
    ],
    "sg:phone":"+1 215 638 2130",
    "sg:postcode":"19020",
    "sg:province":"PA",
    "sg:tags":[
        "organization",
        "welfare"
    ],
    "wof:name":"Vita Family Literacy",
    "wof:placetype":"venue"
},
  "geometry": {"coordinates":[-74.941722,40.101159],"type":"Point"}
}