{
  "type": "Feature",
  "properties": {
    "addr:full":"3275 Washington Pike Bridgeville PA 15017",
    "addr:housenumber":"3275",
    "addr:postcode":"15017",
    "addr:street":"Washington Pike",
    "iso:country":"US",
    "sg:address":"3275 Washington Pike",
    "sg:city":"Bridgeville",
    "sg:classifiers":[
        {
            "category":"Health Services",
            "subcategory":"Health Practitioner",
            "type":"Services"
        }
    ],
    "sg:phone":"+1 412 257 8462",
    "sg:postcode":"15017",
    "sg:province":"PA",
    "wof:name":"Vissman Therapeutics",
    "wof:placetype":"venue"
},
  "geometry": {"coordinates":[-80.121987,40.340051],"type":"Point"}
}