{
  "type": "Feature",
  "properties": {
    "addr:full":"1000 Liberty Ave Pittsburgh PA 15222",
    "addr:housenumber":"1000",
    "addr:postcode":"15222",
    "addr:street":"Liberty Ave",
    "iso:country":"US",
    "sg:address":"1000 Liberty Ave",
    "sg:city":"Pittsburgh",
    "sg:classifiers":[
        {
            "category":"Banks & Credit Unions",
            "subcategory":"Investment Brokerage",
            "type":"Services"
        }
    ],
    "sg:phone":"+1 412 395 4467",
    "sg:postcode":"15222",
    "sg:province":"PA",
    "sg:tags":[
        "stock",
        "bond"
    ],
    "wof:name":"Defence Security Svc",
    "wof:placetype":"venue"
},
  "geometry": {"coordinates":[-79.994998,40.443715],"type":"Point"}
}