{
  "type": "Feature",
  "properties": {
    "iso:country":"US",
    "sg:address":"504 9th St",
    "sg:city":"Matamoras",
    "sg:classifiers":[
        {
            "category":"Building & Trades",
            "subcategory":"Cleaning & Sanitation",
            "type":"Services"
        }
    ],
    "sg:phone":"+1 570 491 2446",
    "sg:postcode":"18336",
    "sg:province":"PA",
    "sg:tags":[
        "fireplace",
        "chimney"
    ],
    "wof:name":"Adonai Chimney Sweeps",
    "wof:placetype":"venue"
},
  "geometry": {"coordinates":[-74.707308,41.36557],"type":"Point"}
}