{
  "type": "Feature",
  "properties": {
    "addr:full":"7501 Derry St Harrisburg PA 17111",
    "addr:housenumber":"7501",
    "addr:postcode":"17111",
    "addr:street":"Derry St",
    "iso:country":"US",
    "sg:address":"7501 Derry St",
    "sg:city":"Harrisburg",
    "sg:classifiers":[
        {
            "category":"Manufacturing",
            "subcategory":"Tools & Machinery",
            "type":"Manufacturing & Wholesale Goods"
        }
    ],
    "sg:phone":"+1 717 564 7960",
    "sg:postcode":"17111",
    "sg:province":"PA",
    "sg:tags":[
        "physician",
        "surgeon"
    ],
    "wof:name":"Mold-Base Industries",
    "wof:placetype":"venue"
},
  "geometry": {"coordinates":[-76.758261,40.265976],"type":"Point"}
}