{
  "type": "Feature",
  "properties": {
    "iso:country":"US",
    "sg:address":"47 Tunbridge Rd",
    "sg:city":"Haverford",
    "sg:classifiers":[
        {
            "category":"Professional",
            "subcategory":"Business Services",
            "type":"Services"
        }
    ],
    "sg:phone":"+1 610 896 6873",
    "sg:postcode":"19041",
    "sg:province":"PA",
    "sg:tags":[
        "interior",
        "consultant",
        "design",
        "decorator"
    ],
    "wof:name":"Carole Smith Design Inc",
    "wof:placetype":"venue"
},
  "geometry": {"coordinates":[-75.319261,40.001735],"type":"Point"}
}