{
  "type": "Feature",
  "properties": {
    "addr:full":"411 Glade City Rd Meyersdale PA 15552",
    "addr:housenumber":"411",
    "addr:postcode":"15552",
    "addr:street":"Glade City Rd",
    "iso:country":"US",
    "sg:address":"411 Glade City Rd",
    "sg:city":"Meyersdale",
    "sg:classifiers":[
        {
            "category":"Home & Garden",
            "subcategory":"Garden Supply",
            "type":"Retail Goods"
        }
    ],
    "sg:phone":"+1   ",
    "sg:postcode":"15552",
    "sg:province":"PA",
    "sg:tags":[
        "lawn"
    ],
    "wof:name":"Jons Repair",
    "wof:placetype":"venue"
},
  "geometry": {"coordinates":[-79.015942,39.813982],"type":"Point"}
}