{
  "type": "Feature",
  "properties": {
    "iso:country":"US",
    "sg:address":"175 E Walnut St",
    "sg:city":"Red Lion",
    "sg:classifiers":[
        {
            "category":"Manufacturing",
            "subcategory":"Paper Products",
            "type":"Manufacturing & Wholesale Goods"
        }
    ],
    "sg:phone":"+1 717 246 1661",
    "sg:postcode":"17356",
    "sg:province":"PA",
    "sg:tags":[
        "corrugated",
        "solid",
        "fiber",
        "box"
    ],
    "sg:website":"www.specialtypackaging.net",
    "wof:name":"Specialty Industries Inc",
    "wof:placetype":"venue"
},
  "geometry": {"coordinates":[-76.59653,39.892575],"type":"Point"}
}