{
  "type": "Feature",
  "properties": {
    "addr:full":"1613 Andrew St Homestead PA 15120",
    "addr:housenumber":"1613",
    "addr:postcode":"15120",
    "addr:street":"Andrew St",
    "iso:country":"US",
    "sg:address":"1613 Andrew St",
    "sg:city":"Homestead",
    "sg:classifiers":[
        {
            "category":"Professional",
            "type":"Services"
        }
    ],
    "sg:phone":"+1   ",
    "sg:postcode":"15120",
    "sg:province":"PA",
    "wof:name":"Jam Products",
    "wof:placetype":"venue"
},
  "geometry": {"coordinates":[-79.900203,40.403323],"type":"Point"}
}