{
  "type": "Feature",
  "properties": {
    "iso:country":"US",
    "sg:address":"671 Onyx Cave Rd",
    "sg:city":"Hamburg",
    "sg:classifiers":[
        {
            "category":"Real Estate",
            "subcategory":"Real Estate Agent",
            "type":"Services"
        }
    ],
    "sg:phone":"+1 610 562 5500",
    "sg:postcode":"19526",
    "sg:province":"PA",
    "sg:tags":[
        "appraiser"
    ],
    "wof:name":"Rockwell Appraisals",
    "wof:placetype":"venue"
},
  "geometry": {"coordinates":[-75.89857499999999,40.516283],"type":"Point"}
}