{
  "type": "Feature",
  "properties": {
    "iso:country":"US",
    "sg:address":"731 E Main St",
    "sg:city":"Monongahela",
    "sg:classifiers":[
        {
            "category":"Wholesale",
            "subcategory":"Stationery",
            "type":"Manufacturing & Wholesale Goods"
        }
    ],
    "sg:phone":"+1 724 258 8208",
    "sg:postcode":"15063",
    "sg:province":"PA",
    "sg:tags":[
        "packaging",
        "material"
    ],
    "wof:name":"Mon Co Products Inc",
    "wof:placetype":"venue"
},
  "geometry": {"coordinates":[-79.905676,40.193245],"type":"Point"}
}