{
  "type": "Feature",
  "properties": {
    "iso:country":"US",
    "sg:address":"155 Clay St",
    "sg:city":"Mountville",
    "sg:classifiers":[
        {
            "category":"Government",
            "subcategory":"Office",
            "type":"Public Place"
        }
    ],
    "sg:phone":"+1 717 285 7818",
    "sg:postcode":"17554",
    "sg:province":"PA",
    "sg:tags":[
        "village"
    ],
    "wof:name":"Maintenance Building",
    "wof:placetype":"venue"
},
  "geometry": {"coordinates":[-76.427936,40.043273],"type":"Point"}
}