{
  "type": "Feature",
  "properties": {
    "iso:country":"US",
    "sg:address":"680 Corn Hill Rd",
    "sg:city":"Etters",
    "sg:classifiers":[
        {
            "category":"Professional",
            "subcategory":"Business Services",
            "type":"Services"
        }
    ],
    "sg:phone":"+1 717 932 9500",
    "sg:postcode":"17319",
    "sg:province":"PA",
    "sg:tags":[
        "embroidery"
    ],
    "wof:name":"Hearing Originals",
    "wof:placetype":"venue"
},
  "geometry": {"coordinates":[-76.80176299999999,40.170354],"type":"Point"}
}