{
  "type": "Feature",
  "properties": {
    "iso:country":"US",
    "sg:address":"115 W Maple Grove Rd",
    "sg:city":"Denver",
    "sg:classifiers":[
        {
            "category":"Autos & Motor Vehicles",
            "subcategory":"Motorcycle Sales",
            "type":"Retail Goods"
        }
    ],
    "sg:phone":"+1 717 445 5442",
    "sg:postcode":"17555",
    "sg:province":"PA",
    "sg:tags":[
        "car",
        "golf",
        "cart"
    ],
    "wof:name":"Renninger's Golf Carts",
    "wof:placetype":"venue"
},
  "geometry": {"coordinates":[-76.020899,40.197041],"type":"Point"}
}