{
  "type": "Feature",
  "properties": {
    "iso:country":"US",
    "sg:address":"130 Haverford Rd",
    "sg:city":"Wynnewood",
    "sg:classifiers":[
        {
            "category":"Education",
            "subcategory":"School",
            "type":"Public Place"
        }
    ],
    "sg:phone":"+1   ",
    "sg:postcode":"19096",
    "sg:province":"PA",
    "wof:name":"Penn Wynne Elementary",
    "wof:placetype":"venue"
},
  "geometry": {"coordinates":[-75.27449,39.984655],"type":"Point"}
}