{
  "type": "Feature",
  "properties": {
    "iso:country":"US",
    "sg:address":"130 W Union St",
    "sg:city":"Somerset",
    "sg:classifiers":[
        {
            "category":"Health Services",
            "subcategory":"Doctor",
            "type":"Services"
        }
    ],
    "sg:phone":"+1   ",
    "sg:postcode":"15501",
    "sg:province":"PA",
    "sg:tags":[
        "medical"
    ],
    "wof:name":"Linda Moran MD",
    "wof:placetype":"venue"
},
  "geometry": {"coordinates":[-79.07872,40.009416],"type":"Point"}
}