{
  "type": "Feature",
  "properties": {
    "iso:country":"US",
    "sg:address":"1365 Easton Rd",
    "sg:city":"Bethlehem",
    "sg:classifiers":[
        {
            "category":"Shopping",
            "subcategory":"Music",
            "type":"Retail Goods"
        }
    ],
    "sg:phone":"+1 610 868 3070",
    "sg:postcode":"18055",
    "sg:province":"PA",
    "sg:tags":[
        "compact",
        "record",
        "disc",
        "tape"
    ],
    "wof:name":"Compact Disc Center",
    "wof:placetype":"venue"
},
  "geometry": {"coordinates":[-75.33589600000001,40.588148],"type":"Point"}
}