{
  "type": "Feature",
  "properties": {
    "addr:full":"1835 Fairview Ave Easton PA 18042",
    "addr:housenumber":"1835",
    "addr:postcode":"18042",
    "addr:street":"Fairview Ave",
    "iso:country":"US",
    "sg:address":"1835 Fairview Ave",
    "sg:city":"Easton",
    "sg:classifiers":[
        {
            "category":"Building & Trades",
            "subcategory":"Construction",
            "type":"Services"
        }
    ],
    "sg:phone":"+1 610 253 9281",
    "sg:postcode":"18042",
    "sg:province":"PA",
    "sg:tags":[
        "bathroom",
        "for",
        "contractor",
        "custom",
        "remodeling",
        "kitchen"
    ],
    "wof:name":"Fehnel's Custom Kitchens",
    "wof:placetype":"venue"
},
  "geometry": {"coordinates":[-75.238165,40.687886],"type":"Point"}
}