{
  "type": "Feature",
  "properties": {
    "addr:full":"3447 Harts Run Rd Ste 4 Glenshaw PA 15116",
    "addr:housenumber":"3447",
    "addr:postcode":"15116",
    "addr:street":"Harts Run Rd Ste 4",
    "iso:country":"US",
    "sg:address":"3447 Harts Run Rd Ste 4",
    "sg:city":"Glenshaw",
    "sg:classifiers":[
        {
            "category":"Shopping",
            "subcategory":"Gifts & Souvenirs",
            "type":"Retail Goods"
        },
        {
            "category":"Shopping",
            "subcategory":"Florist",
            "type":"Retail Goods"
        }
    ],
    "sg:phone":"+1 412 767 9915",
    "sg:postcode":"15116",
    "sg:province":"PA",
    "sg:tags":[
        "shop"
    ],
    "wof:name":"My Garden Inc",
    "wof:placetype":"venue"
},
  "geometry": {"coordinates":[-79.914688,40.551601],"type":"Point"}
}