{
  "type": "Feature",
  "properties": {
    "iso:country":"US",
    "sg:address":"215 Hickory St",
    "sg:city":"Scranton",
    "sg:classifiers":[
        {
            "category":"Education",
            "subcategory":"Vocational School",
            "type":"Public Place"
        }
    ],
    "sg:phone":"+1 570 348 0203",
    "sg:postcode":"18505",
    "sg:province":"PA",
    "sg:tags":[
        "technical",
        "trade"
    ],
    "wof:name":"Wyoming Valley College",
    "wof:placetype":"venue"
},
  "geometry": {"coordinates":[-75.667525,41.402292],"type":"Point"}
}