{
  "type": "Feature",
  "properties": {
    "iso:country":"US",
    "sg:address":"937 Penn Ave",
    "sg:city":"Reading",
    "sg:classifiers":[
        {
            "category":"Personal",
            "subcategory":"Beauty Salon",
            "type":"Services"
        }
    ],
    "sg:phone":"+1 610 371 9070",
    "sg:postcode":"19610",
    "sg:province":"PA",
    "wof:name":"Sam-Gar Salons",
    "wof:placetype":"venue"
},
  "geometry": {"coordinates":[-75.95756,40.335389],"type":"Point"}
}