{
  "type": "Feature",
  "properties": {
    "iso:country":"US",
    "sg:address":"1315 S 56th St",
    "sg:city":"Philadelphia",
    "sg:classifiers":[
        {
            "category":"Organizations",
            "subcategory":"Labor Organization",
            "type":"Services"
        }
    ],
    "sg:phone":"+1   ",
    "sg:postcode":"19143",
    "sg:province":"PA",
    "wof:name":"Thinking Out of Box Lrng Ctr",
    "wof:placetype":"venue"
},
  "geometry": {"coordinates":[-75.230709,39.942193],"type":"Point"}
}