{
  "type": "Feature",
  "properties": {
    "iso:country":"US",
    "sg:address":"104 S 2nd St",
    "sg:city":"Perkasie",
    "sg:classifiers":[
        {
            "category":"Shopping",
            "subcategory":"Antiques",
            "type":"Retail Goods"
        },
        {
            "category":"Home & Garden",
            "subcategory":"Furniture",
            "type":"Retail Goods"
        }
    ],
    "sg:phone":"+1 215 453 8490",
    "sg:postcode":"18944",
    "sg:province":"PA",
    "sg:tags":[
        "store"
    ],
    "sg:website":"http://www.stenellaantiques.com",
    "wof:name":"Stenella Antiques",
    "wof:placetype":"venue"
},
  "geometry": {"coordinates":[-75.292813,40.370011],"type":"Point"}
}