{
  "type": "Feature",
  "properties": {
    "iso:country":"US",
    "sg:address":"206 W Main St",
    "sg:city":"Reynoldsville",
    "sg:classifiers":[
        {
            "category":"Government",
            "subcategory":"Office",
            "type":"Public Place"
        }
    ],
    "sg:phone":"+1 814 653 8080",
    "sg:postcode":"15851",
    "sg:province":"PA",
    "wof:name":"Jefferson County Coroner",
    "wof:placetype":"venue"
},
  "geometry": {"coordinates":[-78.896541,41.101646],"type":"Point"}
}