{
  "type": "Feature",
  "properties": {
    "addr:full":"1600 N Cedar Crest Blvd Allentown PA 18104",
    "addr:housenumber":"1600",
    "addr:postcode":"18104",
    "addr:street":"N Cedar Crest Blvd",
    "iso:country":"US",
    "sg:address":"1600 N Cedar Crest Blvd",
    "sg:city":"Allentown",
    "sg:classifiers":[
        {
            "category":"Retail",
            "subcategory":"Photofinishing",
            "type":"Services"
        }
    ],
    "sg:phone":"+1 610 336 0957",
    "sg:postcode":"18104",
    "sg:province":"PA",
    "sg:tags":[
        "photo",
        "finishing"
    ],
    "wof:name":"Qualex Inc",
    "wof:placetype":"venue"
},
  "geometry": {"coordinates":[-75.53340799999999,40.613873],"type":"Point"}
}