{
  "type": "Feature",
  "properties": {
    "iso:country":"US",
    "sg:address":"452 Durham Rd",
    "sg:city":"Newtown",
    "sg:classifiers":[
        {
            "category":"Organizations",
            "subcategory":"Religious Organization",
            "type":"Services"
        }
    ],
    "sg:phone":"+1 215 860 9640",
    "sg:postcode":"18940",
    "sg:province":"PA",
    "sg:tags":[
        "church"
    ],
    "sg:website":"www.stmarksoca.org",
    "wof:name":"St Mark's Orthodox Church",
    "wof:placetype":"venue"
},
  "geometry": {"coordinates":[-74.9747,40.264017],"type":"Point"}
}