{
  "type": "Feature",
  "properties": {
    "addr:full":"129 College Ave Lancaster PA 17603",
    "addr:housenumber":"129",
    "addr:postcode":"17603",
    "addr:street":"College Ave",
    "iso:country":"US",
    "sg:address":"129 College Ave",
    "sg:city":"Lancaster",
    "sg:classifiers":[
        {
            "category":"Restaurant",
            "type":"Food & Drink"
        }
    ],
    "sg:phone":"+1   ",
    "sg:postcode":"17603",
    "sg:province":"PA",
    "sg:tags":[
        "eating"
    ],
    "wof:name":"Subway",
    "wof:placetype":"venue"
},
  "geometry": {"coordinates":[-76.32092299999999,40.039546],"type":"Point"}
}