{
  "type": "Feature",
  "properties": {
    "iso:country":"US",
    "sg:address":"11 West Ave",
    "sg:city":"Radnor",
    "sg:classifiers":[
        {
            "category":"Travel",
            "subcategory":"Travel Agent",
            "type":"Entertainment"
        }
    ],
    "sg:phone":"+1 610 687 9066",
    "sg:postcode":"19087",
    "sg:province":"PA",
    "sg:tags":[
        "agency",
        "bureau",
        "real estate"
    ],
    "wof:name":"El Sol",
    "wof:placetype":"venue"
},
  "geometry": {"coordinates":[-75.39112799999999,40.046049],"type":"Point"}
}