{
  "type": "Feature",
  "properties": {
    "iso:country":"US",
    "sg:address":"3853 Old Easton Rd",
    "sg:city":"Doylestown",
    "sg:classifiers":[
        {
            "category":"Retail",
            "subcategory":"Auto Repair",
            "type":"Services"
        }
    ],
    "sg:phone":"+1 215 345 8620",
    "sg:postcode":"18902",
    "sg:province":"PA",
    "sg:tags":[
        "repairing",
        "automobile"
    ],
    "sg:website":"www.southmain.com",
    "wof:name":"South Main Tire Co",
    "wof:placetype":"venue"
},
  "geometry": {"coordinates":[-76.65353,39.912423],"type":"Point"}
}