{
  "type": "Feature",
  "properties": {
    "iso:country":"US",
    "sg:address":"25 Rustleaf Ln",
    "sg:city":"Levittown",
    "sg:classifiers":[
        {
            "category":"Wholesale",
            "subcategory":"Sporting Goods",
            "type":"Manufacturing & Wholesale Goods"
        }
    ],
    "sg:phone":"+1   ",
    "sg:postcode":"19055",
    "sg:province":"PA",
    "wof:name":"Delaware Valley Fly Fishe",
    "wof:placetype":"venue"
},
  "geometry": {"coordinates":[-74.85266799999999,40.153414],"type":"Point"}
}