{
  "type": "Feature",
  "properties": {
    "iso:country":"US",
    "sg:address":"10 Main Ave",
    "sg:city":"Berwyn",
    "sg:classifiers":[
        {
            "category":"Banks & Credit Unions",
            "subcategory":"Financial Services",
            "type":"Services"
        }
    ],
    "sg:phone":"+1   ",
    "sg:postcode":"19312",
    "sg:province":"PA",
    "sg:tags":[
        "company",
        "holding"
    ],
    "wof:name":"North Amrcn Taiwanese Wns Assn",
    "wof:placetype":"venue"
},
  "geometry": {"coordinates":[-75.441607,40.046881],"type":"Point"}
}