{
  "type": "Feature",
  "properties": {
    "iso:country":"US",
    "sg:address":"179 Lancaster Blvd",
    "sg:city":"Mechanicsburg",
    "sg:classifiers":[
        {
            "category":"Health Services",
            "subcategory":"Hospital",
            "type":"Services"
        },
        {
            "category":"Health Services",
            "subcategory":"Clinic",
            "type":"Services"
        }
    ],
    "sg:phone":"+1   ",
    "sg:postcode":"17055",
    "sg:province":"PA",
    "sg:tags":[
        "surgery",
        "center",
        "outpatient"
    ],
    "wof:name":"HealthSouth",
    "wof:placetype":"venue"
},
  "geometry": {"coordinates":[-76.97462299999999,40.210908],"type":"Point"}
}