{
  "type": "Feature",
  "properties": {
    "addr:full":"5521 Greene St Philadelphia PA 19144",
    "addr:housenumber":"5521",
    "addr:postcode":"19144",
    "addr:street":"Greene St",
    "iso:country":"US",
    "sg:address":"5521 Greene St",
    "sg:city":"Philadelphia",
    "sg:classifiers":[
        {
            "category":"Health Services",
            "subcategory":"Doctor",
            "type":"Services"
        }
    ],
    "sg:phone":"+1   ",
    "sg:postcode":"19144",
    "sg:province":"PA",
    "wof:name":"Dr Robert Wood",
    "wof:placetype":"venue"
},
  "geometry": {"coordinates":[-75.17526700000001,40.03333],"type":"Point"}
}