{
  "type": "Feature",
  "properties": {
    "addr:full":"508 Grant Ave Millvale PA 15209",
    "addr:housenumber":"508",
    "addr:postcode":"15209",
    "addr:street":"Grant Ave",
    "iso:country":"US",
    "sg:address":"508 Grant Ave",
    "sg:city":"Millvale",
    "sg:classifiers":[
        {
            "category":"Health Services",
            "subcategory":"Podiatrist",
            "type":"Services"
        }
    ],
    "sg:phone":"+1 412 821 1692",
    "sg:postcode":"15209",
    "sg:province":"PA",
    "wof:name":"James J Flynn DPM",
    "wof:placetype":"venue"
},
  "geometry": {"coordinates":[-79.974075,40.480467],"type":"Point"}
}