{
  "type": "Feature",
  "properties": {
    "iso:country":"US",
    "sg:address":"1 S Home Ave",
    "sg:city":"Topton",
    "sg:classifiers":[
        {
            "category":"Social Services",
            "subcategory":"Adult Care",
            "type":"Services"
        }
    ],
    "sg:phone":"+1 610 682 2145",
    "sg:postcode":"19562",
    "sg:province":"PA",
    "sg:tags":[
        "organization",
        "senior",
        "citizen"
    ],
    "wof:name":"Diakon Lutheran Social Mnstrys",
    "wof:placetype":"venue"
},
  "geometry": {"coordinates":[-75.700964,40.50344],"type":"Point"}
}