{
  "type": "Feature",
  "properties": {
    "iso:country":"US",
    "sg:address":"2450 Mansfield Ave",
    "sg:city":"Drexel Hill",
    "sg:classifiers":[
        {
            "category":"Recreation",
            "type":"Entertainment"
        }
    ],
    "sg:phone":"+1   ",
    "sg:postcode":"19026",
    "sg:province":"PA",
    "sg:tags":[
        "club",
        "membership"
    ],
    "wof:name":"Sunshine Thrpy Club",
    "wof:placetype":"venue"
},
  "geometry": {"coordinates":[-75.28418600000001,39.94657],"type":"Point"}
}