{
  "type": "Feature",
  "properties": {
    "iso:country":"US",
    "sg:address":"279 Wagner Bridge Rd",
    "sg:city":"Catawissa",
    "sg:classifiers":[
        {
            "category":"Manufacturing",
            "subcategory":"Buildings",
            "type":"Manufacturing & Wholesale Goods"
        },
        {
            "category":"Building & Trades",
            "subcategory":"Construction",
            "type":"Services"
        }
    ],
    "sg:phone":"+1 570 799 5329",
    "sg:postcode":"17820",
    "sg:province":"PA",
    "sg:tags":[
        "industrial",
        "builder",
        "system",
        "specialty",
        "heating",
        "contractor",
        "contractors-commercial",
        "home",
        "air conditioning"
    ],
    "wof:name":"Zubowicz Building",
    "wof:placetype":"venue"
},
  "geometry": {"coordinates":[-76.373732,40.900542],"type":"Point"}
}