{
  "type": "Feature",
  "properties": {
    "addr:full":"50 E Main St Uniontown PA 15401",
    "addr:housenumber":"50",
    "addr:postcode":"15401",
    "addr:street":"E Main St",
    "iso:country":"US",
    "sg:address":"50 E Main St",
    "sg:city":"Uniontown",
    "sg:classifiers":[
        {
            "category":"Restaurant",
            "type":"Food & Drink"
        }
    ],
    "sg:phone":"+1 724 415 0000",
    "sg:postcode":"15401",
    "sg:province":"PA",
    "sg:tags":[
        "cafe"
    ],
    "wof:name":"Uniontown Courthouse Cafe'",
    "wof:placetype":"venue"
},
  "geometry": {"coordinates":[-79.723302,39.901291],"type":"Point"}
}