{
  "type": "Feature",
  "properties": {
    "iso:country":"US",
    "sg:address":"900 S Market St",
    "sg:city":"Elizabethtown",
    "sg:classifiers":[
        {
            "category":"Autos & Motor Vehicles",
            "subcategory":"Auto Supplies",
            "type":"Retail Goods"
        }
    ],
    "sg:phone":"+1 717 367 0006",
    "sg:postcode":"17022",
    "sg:province":"PA",
    "sg:tags":[
        "automobile",
        "accessory"
    ],
    "wof:name":"Susquehanna Solar Control",
    "wof:placetype":"venue"
},
  "geometry": {"coordinates":[-76.59707400000001,40.143544],"type":"Point"}
}