{
  "type": "Feature",
  "properties": {
    "iso:country":"US",
    "sg:address":"970 Milton Grove Rd S",
    "sg:city":"Elizabethtown",
    "sg:classifiers":[
        {
            "category":"Organizations",
            "subcategory":"Religious Organization",
            "type":"Services"
        }
    ],
    "sg:phone":"+1 717 665 7222",
    "sg:postcode":"17022",
    "sg:province":"PA",
    "sg:tags":[
        "church"
    ],
    "wof:name":"Grace Community Fellowship",
    "wof:placetype":"venue"
},
  "geometry": {"coordinates":[-76.531841,40.162392],"type":"Point"}
}