{
  "type": "Feature",
  "properties": {
    "addr:full":"6922 McCartney Rd Lowellville PA 44436",
    "addr:postcode":"6922;44436",
    "addr:street":"Mccartney Rd",
    "iso:country":"US",
    "sg:address":"6922 McCartney Rd",
    "sg:city":"Lowellville",
    "sg:classifiers":[
        {
            "category":"Restaurant",
            "type":"Food & Drink"
        }
    ],
    "sg:phone":"+1 330 536 8044",
    "sg:postcode":"44436",
    "sg:province":"PA",
    "wof:name":"Clearwater Cafe",
    "wof:placetype":"venue"
},
  "geometry": {"coordinates":[-80.522144,41.090737],"type":"Point"}
}