{
  "type": "Feature",
  "properties": {
    "iso:country":"US",
    "sg:address":"3811 Kutztown Rd",
    "sg:city":"Reading",
    "sg:classifiers":[
        {
            "category":"Personal",
            "subcategory":"Beauty Salon",
            "type":"Services"
        }
    ],
    "sg:phone":"+1 610 685 4100",
    "sg:postcode":"19605",
    "sg:province":"PA",
    "sg:tags":[
        "hair",
        "stylist"
    ],
    "wof:name":"4 Friends Hair Center",
    "wof:placetype":"venue"
},
  "geometry": {"coordinates":[-75.91950199999999,40.394852],"type":"Point"}
}