{
  "type": "Feature",
  "properties": {
    "iso:country":"US",
    "sg:address":"1408 Jackson St",
    "sg:city":"Philadelphia",
    "sg:classifiers":[
        {
            "category":"Professional",
            "subcategory":"Accounting & Tax Preparation",
            "type":"Services"
        }
    ],
    "sg:phone":"+1   ",
    "sg:postcode":"19145",
    "sg:province":"PA",
    "sg:tags":[
        "return"
    ],
    "wof:name":"Richard E Weisz",
    "wof:placetype":"venue"
},
  "geometry": {"coordinates":[-75.17039699999999,39.923101],"type":"Point"}
}