{
  "type": "Feature",
  "properties": {
    "iso:country":"US",
    "sg:address":"1031 S Braddock Ave",
    "sg:city":"Pittsburgh",
    "sg:classifiers":[
        {
            "category":"Shopping",
            "type":"Retail Goods"
        }
    ],
    "sg:phone":"+1 412 242 9200",
    "sg:postcode":"15218",
    "sg:province":"PA",
    "sg:tags":[
        "art",
        "gallery",
        "dealer"
    ],
    "sg:website":"www.conceptgallery.com",
    "wof:name":"Concept Art Gallery Inc",
    "wof:placetype":"venue"
},
  "geometry": {"coordinates":[-79.894008,40.432888],"type":"Point"}
}