{
  "type": "Feature",
  "properties": {
    "addr:full":"275 Lauriston St Philadelphia PA 19128",
    "addr:housenumber":"275",
    "addr:postcode":"19128",
    "addr:street":"Lauriston St",
    "iso:country":"US",
    "sg:address":"275 Lauriston St",
    "sg:city":"Philadelphia",
    "sg:classifiers":[
        {
            "category":"Building & Trades",
            "subcategory":"Construction",
            "type":"Services"
        }
    ],
    "sg:phone":"+1   ",
    "sg:postcode":"19128",
    "sg:province":"PA",
    "sg:tags":[
        "house"
    ],
    "wof:name":"B & D Construction",
    "wof:placetype":"venue"
},
  "geometry": {"coordinates":[-75.206485,40.020695],"type":"Point"}
}