{
  "type": "Feature",
  "properties": {
    "iso:country":"US",
    "sg:address":"1543 Dawson St",
    "sg:city":"Pittston",
    "sg:classifiers":[
        {
            "category":"Recreation",
            "type":"Entertainment"
        }
    ],
    "sg:phone":"+1   ",
    "sg:postcode":"18641",
    "sg:province":"PA",
    "sg:tags":[
        "club",
        "membership"
    ],
    "wof:name":"Browns Sportsmen Club",
    "wof:placetype":"venue"
},
  "geometry": {"coordinates":[-75.727628,41.343737],"type":"Point"}
}