{
  "type": "Feature",
  "properties": {
    "addr:full":"451 Airport Rd Philipsburg PA 16823",
    "addr:housenumber":"451",
    "addr:postcode":"16823",
    "addr:street":"Airport Rd",
    "iso:country":"US",
    "sg:address":"451 Airport Rd",
    "sg:city":"Philipsburg",
    "sg:classifiers":[
        {
            "category":"Airport",
            "type":"Transportation"
        }
    ],
    "sg:phone":"+1   ",
    "sg:postcode":"16823",
    "sg:province":"PA",
    "sg:tags":[
        "municipal"
    ],
    "wof:name":"Mid State Regional Arprt Auth",
    "wof:placetype":"venue"
},
  "geometry": {"coordinates":[-77.752565,40.912374],"type":"Point"}
}