{
  "type": "Feature",
  "properties": {
    "addr:full":"115 Friar Ln Bloomsburg PA 17815",
    "addr:housenumber":"115",
    "addr:postcode":"17815",
    "addr:street":"Friar Ln",
    "iso:country":"US",
    "sg:address":"115 Friar Ln",
    "sg:city":"Bloomsburg",
    "sg:classifiers":[
        {
            "category":"Education",
            "subcategory":"Special Training",
            "type":"Public Place"
        }
    ],
    "sg:phone":"+1   ",
    "sg:postcode":"17815",
    "sg:province":"PA",
    "wof:name":"Impact Resources Inc",
    "wof:placetype":"venue"
},
  "geometry": {"coordinates":[-76.42110099999999,41.00401],"type":"Point"}
}