{
  "type": "Feature",
  "properties": {
    "addr:full":"111 Revco Rd Somerset PA 15501",
    "addr:housenumber":"111",
    "addr:postcode":"15501",
    "addr:street":"Revco Rd",
    "iso:country":"US",
    "sg:address":"111 Revco Rd",
    "sg:city":"Somerset",
    "sg:classifiers":[
        {
            "category":"Shopping",
            "subcategory":"Computers & Home Electronics",
            "type":"Retail Goods"
        }
    ],
    "sg:phone":"+1   ",
    "sg:postcode":"15501",
    "sg:province":"PA",
    "wof:name":"Somerset Computer Center Inc",
    "wof:placetype":"venue"
},
  "geometry": {"coordinates":[-79.076076,40.030401],"type":"Point"}
}