{
  "type": "Feature",
  "properties": {
    "iso:country":"US",
    "sg:address":"501 Bath Rd",
    "sg:city":"Bristol",
    "sg:classifiers":[
        {
            "category":"Health Services",
            "subcategory":"Hospital",
            "type":"Services"
        },
        {
            "category":"Health Services",
            "subcategory":"Doctor",
            "type":"Services"
        }
    ],
    "sg:phone":"+1 215 785 9910",
    "sg:postcode":"19007",
    "sg:province":"PA",
    "sg:tags":[
        "physician",
        "surgeon",
        "general"
    ],
    "wof:name":"Thomas Jefferson Univ Hospital",
    "wof:placetype":"venue"
},
  "geometry": {"coordinates":[-74.863343,40.102169],"type":"Point"}
}