{
  "type": "Feature",
  "properties": {
    "addr:full":"141 S Juliana St Bedford PA 15522",
    "addr:housenumber":"141",
    "addr:postcode":"15522",
    "addr:street":"S Juliana St",
    "iso:country":"US",
    "sg:address":"141 S Juliana St",
    "sg:city":"Bedford",
    "sg:classifiers":[
        {
            "category":"Social Services",
            "type":"Services"
        }
    ],
    "sg:phone":"+1 814 623 2411",
    "sg:postcode":"15522",
    "sg:province":"PA",
    "sg:tags":[
        "organization",
        "welfare"
    ],
    "wof:name":"Retired Senior Volunteer",
    "wof:placetype":"venue"
},
  "geometry": {"coordinates":[-78.50368,40.018065],"type":"Point"}
}