{
  "type": "Feature",
  "properties": {
    "addr:full":"55 W Chelten Ave Philadelphia PA 19144",
    "addr:housenumber":"55",
    "addr:postcode":"19144",
    "addr:street":"W Chelten Ave",
    "iso:country":"US",
    "sg:address":"55 W Chelten Ave",
    "sg:city":"Philadelphia",
    "sg:classifiers":[
        {
            "category":"Utilities",
            "subcategory":"Electric",
            "type":"Services"
        }
    ],
    "sg:phone":"+1   ",
    "sg:postcode":"19144",
    "sg:province":"PA",
    "wof:name":"Peco",
    "wof:placetype":"venue"
},
  "geometry": {"coordinates":[-75.17580700000001,40.035092],"type":"Point"}
}