{
  "type": "Feature",
  "properties": {
    "iso:country":"US",
    "sg:address":"120 Devonwood Dr",
    "sg:city":"Pittsburgh",
    "sg:classifiers":[
        {
            "category":"Health Services",
            "subcategory":"Doctor",
            "type":"Services"
        }
    ],
    "sg:phone":"+1 412 833 8782",
    "sg:postcode":"15241",
    "sg:province":"PA",
    "wof:name":"Nellas Constantine L MD",
    "wof:placetype":"venue"
},
  "geometry": {"coordinates":[-80.06710099999999,40.339802],"type":"Point"}
}