{
  "type": "Feature",
  "properties": {
    "addr:full":"324 N Pennsylvania Ave Greensburg PA 15601",
    "addr:housenumber":"324",
    "addr:postcode":"15601",
    "addr:street":"N Pennsylvania Ave",
    "iso:country":"US",
    "sg:address":"324 N Pennsylvania Ave",
    "sg:city":"Greensburg",
    "sg:classifiers":[
        {
            "category":"Professional",
            "type":"Services"
        }
    ],
    "sg:phone":"+1 724 836 5683",
    "sg:postcode":"15601",
    "sg:province":"PA",
    "sg:tags":[
        "establishment"
    ],
    "wof:name":"Denale C",
    "wof:placetype":"venue"
},
  "geometry": {"coordinates":[-79.546396,40.305314],"type":"Point"}
}