{
  "type": "Feature",
  "properties": {
    "iso:country":"US",
    "sg:address":"121 N Eagle Rd",
    "sg:city":"Havertown",
    "sg:classifiers":[
        {
            "category":"Organizations",
            "subcategory":"Labor Organization",
            "type":"Services"
        }
    ],
    "sg:phone":"+1 610 446 4700",
    "sg:postcode":"19083",
    "sg:province":"PA",
    "sg:tags":[
        "consultant",
        "relation"
    ],
    "wof:name":"John A. Dash & Associates,",
    "wof:placetype":"venue"
},
  "geometry": {"coordinates":[-75.319199,39.975029],"type":"Point"}
}