{
  "type": "Feature",
  "properties": {
    "iso:country":"US",
    "sg:address":"145 Shaffer Ln",
    "sg:city":"Jersey Shore",
    "sg:classifiers":[
        {
            "category":"Retail",
            "subcategory":"Auto Repair",
            "type":"Services"
        }
    ],
    "sg:phone":"+1 570 398 7230",
    "sg:postcode":"17740",
    "sg:province":"PA",
    "sg:tags":[
        "body",
        "automobile",
        "painting"
    ],
    "wof:name":"Show Case Auto Repair",
    "wof:placetype":"venue"
},
  "geometry": {"coordinates":[-77.26976500000001,41.195214],"type":"Point"}
}