{
  "type": "Feature",
  "properties": {
    "iso:country":"US",
    "sg:address":"326 Donald Rd",
    "sg:city":"Hermitage",
    "sg:classifiers":[
        {
            "category":"Professional",
            "type":"Services"
        }
    ],
    "sg:phone":"+1   ",
    "sg:postcode":"16148",
    "sg:province":"PA",
    "wof:name":"Magdits",
    "wof:placetype":"venue"
},
  "geometry": {"coordinates":[-80.446091,41.22872],"type":"Point"}
}