{
  "type": "Feature",
  "properties": {
    "addr:full":"19 Wyndena Ln Newtown Square PA 19073",
    "addr:housenumber":"19",
    "addr:postcode":"19073",
    "addr:street":"Wyndena Ln",
    "iso:country":"US",
    "sg:address":"19 Wyndena Ln",
    "sg:city":"Newtown Square",
    "sg:classifiers":[
        {
            "category":"Insurance",
            "subcategory":"Hazard Insurance",
            "type":"Services"
        }
    ],
    "sg:phone":"+1   ",
    "sg:postcode":"19073",
    "sg:province":"PA",
    "sg:tags":[
        "union",
        "administer",
        "benefit",
        "health",
        "pension",
        "plan"
    ],
    "wof:name":"National Elevator Industry",
    "wof:placetype":"venue"
},
  "geometry": {"coordinates":[-75.38320899999999,39.983973],"type":"Point"}
}