{
  "type": "Feature",
  "properties": {
    "iso:country":"US",
    "sg:address":"2134 W Tioga St",
    "sg:city":"Philadelphia",
    "sg:classifiers":[
        {
            "category":"Building & Trades",
            "subcategory":"Locksmith",
            "type":"Services"
        }
    ],
    "sg:phone":"+1 267 702 1100",
    "sg:postcode":"19140",
    "sg:province":"PA",
    "sg:tags":[
        "key"
    ],
    "wof:name":"Available Locksmith All Day",
    "wof:placetype":"venue"
},
  "geometry": {"coordinates":[-75.163865,40.007567],"type":"Point"}
}