{
  "type": "Feature",
  "properties": {
    "addr:full":"2952 Neville Rd Pittsburgh PA 15225",
    "addr:housenumber":"2952",
    "addr:postcode":"15225",
    "addr:street":"Neville Rd",
    "iso:country":"US",
    "sg:address":"2952 Neville Rd",
    "sg:city":"Pittsburgh",
    "sg:classifiers":[
        {
            "category":"Freight",
            "type":"Transportation"
        }
    ],
    "sg:phone":"+1   ",
    "sg:postcode":"15225",
    "sg:province":"PA",
    "sg:tags":[
        "warehouse",
        "property",
        "rent"
    ],
    "wof:name":"Rich Leasing Inc",
    "wof:placetype":"venue"
},
  "geometry": {"coordinates":[-80.10724500000001,40.504149],"type":"Point"}
}