{
  "type": "Feature",
  "properties": {
    "iso:country":"US",
    "sg:address":"909 Main St",
    "sg:city":"Pittsburgh",
    "sg:classifiers":[
        {
            "category":"Shopping",
            "subcategory":"Discount & Variety Stores",
            "type":"Retail Goods"
        },
        {
            "category":"Shopping",
            "subcategory":"Department Store",
            "type":"Retail Goods"
        }
    ],
    "sg:phone":"+1 412 781 0966",
    "sg:postcode":"15215",
    "sg:province":"PA",
    "sg:tags":[
        "shop"
    ],
    "wof:name":"Family Dollar Stores",
    "wof:placetype":"venue"
},
  "geometry": {"coordinates":[-79.9332,40.494504],"type":"Point"}
}