{
  "type": "Feature",
  "properties": {
    "iso:country":"US",
    "sg:address":"211 N 2nd Street",
    "sg:city":"Harrisburg",
    "sg:classifiers":[
        {
            "category":"Restaurant",
            "type":"Food & Drink"
        }
    ],
    "sg:phone":"+1 717 233 6699",
    "sg:postcode":"17101",
    "sg:province":"PA",
    "sg:tags":[
        "new",
        "american"
    ],
    "sg:website":"www.stocksonsecond.com/",
    "wof:name":"Stock's on Second",
    "wof:placetype":"venue"
},
  "geometry": {"coordinates":[-76.884298,40.2612],"type":"Point"}
}