{
  "type": "Feature",
  "properties": {
    "iso:country":"US",
    "sg:address":"986 Sumneytown Pike",
    "sg:city":"Lansdale",
    "sg:classifiers":[
        {
            "category":"Retail",
            "subcategory":"Car Wash",
            "type":"Services"
        }
    ],
    "sg:phone":"+1 215 393 0722",
    "sg:postcode":"19446",
    "sg:province":"PA",
    "sg:tags":[
        "automobile",
        "detail",
        "clean"
    ],
    "wof:name":"EK2 Detail Shop",
    "wof:placetype":"venue"
},
  "geometry": {"coordinates":[-75.31377999999999,40.228968],"type":"Point"}
}