{
  "type": "Feature",
  "properties": {
    "iso:country":"US",
    "sg:address":"508 Main St",
    "sg:city":"Saxton",
    "sg:classifiers":[
        {
            "category":"Government",
            "subcategory":"Post Office",
            "type":"Public Place"
        }
    ],
    "sg:phone":"+1 814 635 2941",
    "sg:postcode":"16678",
    "sg:province":"PA",
    "wof:name":"US Post Office",
    "wof:placetype":"venue"
},
  "geometry": {"coordinates":[-78.24090099999999,40.215913],"type":"Point"}
}