{
  "type": "Feature",
  "properties": {
    "iso:country":"US",
    "sg:address":"21 S Line St",
    "sg:city":"Frackville",
    "sg:classifiers":[
        {
            "category":"Wholesale",
            "subcategory":"Non-durable Goods",
            "type":"Manufacturing & Wholesale Goods"
        }
    ],
    "sg:phone":"+1 570 874 0903",
    "sg:postcode":"17931",
    "sg:province":"PA",
    "wof:name":"Crown Bingo Supply",
    "wof:placetype":"venue"
},
  "geometry": {"coordinates":[-76.227114,40.785856],"type":"Point"}
}