{
  "type": "Feature",
  "properties": {
    "iso:country":"US",
    "sg:address":"1382 Beulah Rd",
    "sg:city":"Pittsburgh",
    "sg:classifiers":[
        {
            "category":"Insurance",
            "subcategory":"Insurance Agent",
            "type":"Services"
        }
    ],
    "sg:phone":"+1 412 242 7840",
    "sg:postcode":"15235",
    "sg:province":"PA",
    "wof:name":"SMC Insurance",
    "wof:placetype":"venue"
},
  "geometry": {"coordinates":[-79.846898,40.443137],"type":"Point"}
}