{
  "type": "Feature",
  "properties": {
    "addr:full":"130 Cornell Rd Bala Cynwyd PA 19004",
    "addr:housenumber":"130",
    "addr:postcode":"19004",
    "addr:street":"Cornell Rd",
    "iso:country":"US",
    "sg:address":"130 Cornell Rd",
    "sg:city":"Bala Cynwyd",
    "sg:classifiers":[
        {
            "category":"Building & Trades",
            "subcategory":"Construction",
            "type":"Services"
        }
    ],
    "sg:phone":"+1 610 664 4424",
    "sg:postcode":"19004",
    "sg:province":"PA",
    "sg:tags":[
        "house",
        "general",
        "contractor"
    ],
    "wof:name":"Salove Construction Company",
    "wof:placetype":"venue"
},
  "geometry": {"coordinates":[-75.23186699999999,40.019372],"type":"Point"}
}