{
  "type": "Feature",
  "properties": {
    "iso:country":"US",
    "sg:address":"1151 E Earl Rd",
    "sg:city":"East Earl",
    "sg:classifiers":[
        {
            "category":"Shopping",
            "subcategory":"Gifts & Souvenirs",
            "type":"Retail Goods"
        }
    ],
    "sg:phone":"+1   ",
    "sg:postcode":"17519",
    "sg:province":"PA",
    "wof:name":"Sports Collector",
    "wof:placetype":"venue"
},
  "geometry": {"coordinates":[-76.045948,40.109051],"type":"Point"}
}