{
  "type": "Feature",
  "properties": {
    "iso:country":"US",
    "sg:address":"1061 6th St",
    "sg:city":"Whitehall",
    "sg:classifiers":[
        {
            "category":"Bars & Pubs",
            "type":"Food & Drink"
        }
    ],
    "sg:phone":"+1 610 439 8414",
    "sg:postcode":"18052",
    "sg:province":"PA",
    "wof:name":"Park Inn",
    "wof:placetype":"venue"
},
  "geometry": {"coordinates":[-75.475505,40.638241],"type":"Point"}
}