{
  "type": "Feature",
  "properties": {
    "iso:country":"US",
    "sg:address":"25 Heather Way",
    "sg:city":"York",
    "sg:classifiers":[
        {
            "category":"Health Services",
            "subcategory":"Nursing And Care Facility",
            "type":"Services"
        },
        {
            "category":"Health Services",
            "subcategory":"Health Practitioner",
            "type":"Services"
        }
    ],
    "sg:phone":"+1 717 718 5514",
    "sg:postcode":"17404",
    "sg:province":"PA",
    "sg:tags":[
        "home",
        "eldercare-home"
    ],
    "wof:name":"Paul & Thecla Personal Care Homes",
    "wof:placetype":"venue"
},
  "geometry": {"coordinates":[-76.78305400000001,40.055983],"type":"Point"}
}