{
  "type": "Feature",
  "properties": {
    "addr:full":"325 Chestnut St Ste 509 Philadelphia PA 19106",
    "addr:housenumber":"325",
    "addr:postcode":"19106",
    "addr:street":"Chestnut St Ste 509",
    "iso:country":"US",
    "sg:address":"325 Chestnut St Ste 509",
    "sg:city":"Philadelphia",
    "sg:classifiers":[
        {
            "category":"Wholesale",
            "subcategory":"Machinery & Supplies",
            "type":"Manufacturing & Wholesale Goods"
        },
        {
            "category":"Building & Trades",
            "subcategory":"Electrical",
            "type":"Services"
        }
    ],
    "sg:phone":"+1 215 925 2867",
    "sg:postcode":"19106",
    "sg:province":"PA",
    "sg:tags":[
        "control",
        "scientific",
        "apparatus",
        "system",
        "controls",
        "regulator",
        "instrument"
    ],
    "wof:name":"Herman D Steel Co",
    "wof:placetype":"venue"
},
  "geometry": {"coordinates":[-75.146869,39.94874],"type":"Point"}
}