{
  "type": "Feature",
  "properties": {
    "addr:full":"430 Stouffer Ave Chambersburg PA 17201",
    "addr:housenumber":"430",
    "addr:postcode":"17201",
    "addr:street":"Stouffer Ave",
    "iso:country":"US",
    "sg:address":"430 Stouffer Ave",
    "sg:city":"Chambersburg",
    "sg:classifiers":[
        {
            "category":"Banks & Credit Unions",
            "subcategory":"Bank",
            "type":"Services"
        }
    ],
    "sg:phone":"+1 717 267 3171",
    "sg:postcode":"17201",
    "sg:province":"PA",
    "wof:name":"M & T Bank",
    "wof:placetype":"venue"
},
  "geometry": {"coordinates":[-77.6404,39.926922],"type":"Point"}
}