{
  "type": "Feature",
  "properties": {
    "addr:full":"1245 S Cedar Crest Blvd Allentown PA 18103",
    "addr:housenumber":"1245",
    "addr:postcode":"18103",
    "addr:street":"S Cedar Crest Blvd",
    "iso:country":"US",
    "sg:address":"1245 S Cedar Crest Blvd",
    "sg:city":"Allentown",
    "sg:classifiers":[
        {
            "category":"Health Services",
            "subcategory":"Dentist",
            "type":"Services"
        }
    ],
    "sg:phone":"+1 610 437 7993",
    "sg:postcode":"18103",
    "sg:province":"PA",
    "sg:tags":[
        "dentists-cosmetic",
        "dentists-orthodontists",
        "dentistry"
    ],
    "sg:website":"http://www.drbernardich.com",
    "wof:name":"Bernardich Michele A, DMD, MSD",
    "wof:placetype":"venue"
},
  "geometry": {"coordinates":[-75.518297,40.565229],"type":"Point"}
}