{
  "type": "Feature",
  "properties": {
    "iso:country":"US",
    "sg:address":"87 Wyoming Valley Mall",
    "sg:city":"Wilkes Barre",
    "sg:classifiers":[
        {
            "category":"Shopping",
            "subcategory":"Gifts & Souvenirs",
            "type":"Retail Goods"
        }
    ],
    "sg:phone":"+1   ",
    "sg:postcode":"18702",
    "sg:province":"PA",
    "sg:tags":[
        "cards"
    ],
    "wof:name":"Hallmark",
    "wof:placetype":"venue"
},
  "geometry": {"coordinates":[-75.842144,41.250075],"type":"Point"}
}