{
  "type": "Feature",
  "properties": {
    "iso:country":"US",
    "sg:address":"4431 Remo Crescent Rd",
    "sg:city":"Bensalem",
    "sg:classifiers":[
        {
            "category":"Professional",
            "subcategory":"Management & Consulting",
            "type":"Services"
        }
    ],
    "sg:phone":"+1   ",
    "sg:postcode":"19020",
    "sg:province":"PA",
    "sg:tags":[
        "business"
    ],
    "wof:name":"Gretz and Associate L L C",
    "wof:placetype":"venue"
},
  "geometry": {"coordinates":[-74.93329799999999,40.116813],"type":"Point"}
}