{
  "type": "Feature",
  "properties": {
    "iso:country":"US",
    "sg:address":"4123 Lancaster Ave",
    "sg:city":"Philadelphia",
    "sg:classifiers":[
        {
            "category":"Personal",
            "subcategory":"Shoe Repair & Shine",
            "type":"Services"
        },
        {
            "category":"Home & Garden",
            "subcategory":"Furniture",
            "type":"Retail Goods"
        }
    ],
    "sg:phone":"+1 215 921 8324",
    "sg:postcode":"19104",
    "sg:province":"PA",
    "sg:tags":[
        "store"
    ],
    "wof:name":"Megadeal",
    "wof:placetype":"venue"
},
  "geometry": {"coordinates":[-75.206193,39.96572],"type":"Point"}
}