{
  "type": "Feature",
  "properties": {
    "addr:full":"307 Glade Mill Rd Valencia PA 16059",
    "addr:housenumber":"307",
    "addr:postcode":"16059",
    "addr:street":"Glade Mill Rd",
    "iso:country":"US",
    "sg:address":"307 Glade Mill Rd",
    "sg:city":"Valencia",
    "sg:classifiers":[
        {
            "category":"Retail",
            "subcategory":"Auto Repair",
            "type":"Services"
        }
    ],
    "sg:phone":"+1 724 898 3430",
    "sg:postcode":"16059",
    "sg:province":"PA",
    "sg:tags":[
        "body",
        "automobile",
        "painting"
    ],
    "wof:name":"Lennon's Auto Body",
    "wof:placetype":"venue"
},
  "geometry": {"coordinates":[-79.884908,40.720934],"type":"Point"}
}