{
  "type": "Feature",
  "properties": {
    "iso:country":"US",
    "sg:address":"38 Cook St",
    "sg:city":"Wilkes Barre",
    "sg:classifiers":[
        {
            "category":"Wholesale",
            "subcategory":"Farm Supplies",
            "type":"Manufacturing & Wholesale Goods"
        }
    ],
    "sg:phone":"+1   ",
    "sg:postcode":"18705",
    "sg:province":"PA",
    "sg:tags":[
        "greenhouse"
    ],
    "wof:name":"Merlino Greenhouses LLC",
    "wof:placetype":"venue"
},
  "geometry": {"coordinates":[-75.838109,41.27684],"type":"Point"}
}