{
  "type": "Feature",
  "properties": {
    "addr:full":"1735 E 3rd St Williamsport PA 17701",
    "addr:housenumber":"1735",
    "addr:postcode":"17701",
    "addr:street":"E 3Rd St",
    "iso:country":"US",
    "sg:address":"1735 E 3rd St",
    "sg:city":"Williamsport",
    "sg:classifiers":[
        {
            "category":"Insurance",
            "subcategory":"Insurance Agent",
            "type":"Services"
        }
    ],
    "sg:phone":"+1 570 323 3600",
    "sg:postcode":"17701",
    "sg:province":"PA",
    "wof:name":"Fischer Insurance",
    "wof:placetype":"venue"
},
  "geometry": {"coordinates":[-76.96849899999999,41.249793],"type":"Point"}
}