{
  "type": "Feature",
  "properties": {
    "addr:full":"5925 Torresdale Ave Philadelphia PA 19135",
    "addr:housenumber":"5925",
    "addr:postcode":"19135",
    "addr:street":"Torresdale Ave",
    "iso:country":"US",
    "sg:address":"5925 Torresdale Ave",
    "sg:city":"Philadelphia",
    "sg:classifiers":[
        {
            "category":"Restaurant",
            "type":"Food & Drink"
        },
        {
            "category":"Manufacturing",
            "subcategory":"Pet Food",
            "type":"Manufacturing & Wholesale Goods"
        }
    ],
    "sg:phone":"+1 215 533 7777",
    "sg:postcode":"19135",
    "sg:province":"PA",
    "sg:tags":[
        "pizza",
        "pizza-wholesale",
        "manufacturer"
    ],
    "wof:name":"Hermano Pizza",
    "wof:placetype":"venue"
},
  "geometry": {"coordinates":[-75.060329,40.017122],"type":"Point"}
}