{
  "type": "Feature",
  "properties": {
    "iso:country":"US",
    "sg:address":"936 Elm St",
    "sg:city":"Lehighton",
    "sg:classifiers":[
        {
            "category":"Utilities",
            "subcategory":"Cable",
            "type":"Services"
        }
    ],
    "sg:phone":"+1   ",
    "sg:postcode":"18235",
    "sg:province":"PA",
    "sg:tags":[
        "newspaper",
        "television"
    ],
    "wof:name":"Penn Cor Sev Inc",
    "wof:placetype":"venue"
},
  "geometry": {"coordinates":[-75.65319599999999,40.828779],"type":"Point"}
}