{
  "type": "Feature",
  "properties": {
    "addr:full":"600 Chester Pike Norwood PA 19074",
    "addr:housenumber":"600",
    "addr:postcode":"19074",
    "addr:street":"Chester Pike",
    "iso:country":"US",
    "sg:address":"600 Chester Pike",
    "sg:city":"Norwood",
    "sg:classifiers":[
        {
            "category":"Food & Beverages",
            "subcategory":"Bakery",
            "type":"Retail Goods"
        }
    ],
    "sg:phone":"+1 610 532 6547",
    "sg:postcode":"19074",
    "sg:province":"PA",
    "sg:tags":[
        "shop",
        "donut"
    ],
    "wof:name":"Dunkin Donuts",
    "wof:placetype":"venue"
},
  "geometry": {"coordinates":[-75.300034,39.888235],"type":"Point"}
}