{
  "type": "Feature",
  "properties": {
    "addr:full":"900 Concord Rd Aston PA 19014",
    "addr:housenumber":"900",
    "addr:postcode":"19014",
    "addr:street":"Concord Rd",
    "iso:country":"US",
    "sg:address":"900 Concord Rd",
    "sg:city":"Aston",
    "sg:classifiers":[
        {
            "category":"Real Estate",
            "subcategory":"Real Estate Operator",
            "type":"Services"
        }
    ],
    "sg:phone":"+1 610 494 1986",
    "sg:postcode":"19014",
    "sg:province":"PA",
    "sg:tags":[
        "apartment"
    ],
    "wof:name":"Concord Court Apartments",
    "wof:placetype":"venue"
},
  "geometry": {"coordinates":[-75.429266,39.869417],"type":"Point"}
}