{
  "type": "Feature",
  "properties": {
    "addr:full":"8420 Clear Ridge Rd Clearville PA 15535",
    "addr:housenumber":"8420",
    "addr:postcode":"15535",
    "addr:street":"Clear Ridge Rd",
    "iso:country":"US",
    "sg:address":"8420 Clear Ridge Rd",
    "sg:city":"Clearville",
    "sg:classifiers":[
        {
            "category":"Wholesale",
            "subcategory":"Hardware",
            "type":"Manufacturing & Wholesale Goods"
        },
        {
            "category":"Building & Trades",
            "subcategory":"Plumbing",
            "type":"Services"
        }
    ],
    "sg:phone":"+1 814 784 5716",
    "sg:postcode":"15535",
    "sg:province":"PA",
    "sg:tags":[
        "system",
        "equipment",
        "heating",
        "contractor"
    ],
    "wof:name":"Clark's Plumbing & Heating",
    "wof:placetype":"venue"
},
  "geometry": {"coordinates":[-78.38562400000001,39.917304],"type":"Point"}
}