{
  "type": "Feature",
  "properties": {
    "iso:country":"US",
    "sg:address":"2830 Welshtown Rd",
    "sg:city":"Slatington",
    "sg:classifiers":[
        {
            "category":"Manufacturing",
            "subcategory":"Tools & Machinery",
            "type":"Manufacturing & Wholesale Goods"
        }
    ],
    "sg:phone":"+1   ",
    "sg:postcode":"18080",
    "sg:province":"PA",
    "sg:tags":[
        "industrial",
        "mfg"
    ],
    "wof:name":"Daves Auto Repair",
    "wof:placetype":"venue"
},
  "geometry": {"coordinates":[-75.63066499999999,40.758059],"type":"Point"}
}