{
  "type": "Feature",
  "properties": {
    "iso:country":"US",
    "sg:address":"65 Garlor Dr",
    "sg:city":"Havertown",
    "sg:classifiers":[
        {
            "category":"Building & Trades",
            "subcategory":"Construction",
            "type":"Services"
        }
    ],
    "sg:phone":"+1 610 543 2528",
    "sg:postcode":"19083",
    "sg:province":"PA",
    "sg:tags":[
        "paving",
        "contractor"
    ],
    "wof:name":"J Tarquini Paving Co",
    "wof:placetype":"venue"
},
  "geometry": {"coordinates":[-75.33036199999999,39.984941],"type":"Point"}
}