{
  "type": "Feature",
  "properties": {
    "iso:country":"US",
    "sg:address":"2761 Kingsview Ave",
    "sg:city":"Easton",
    "sg:classifiers":[
        {
            "category":"Manufacturing",
            "subcategory":"Metals",
            "type":"Manufacturing & Wholesale Goods"
        }
    ],
    "sg:phone":"+1 610 253 8214",
    "sg:postcode":"18045",
    "sg:province":"PA",
    "sg:tags":[
        "fitting",
        "mfg"
    ],
    "wof:name":"Laurian Outdoors",
    "wof:placetype":"venue"
},
  "geometry": {"coordinates":[-75.272775,40.65886],"type":"Point"}
}