{
  "type": "Feature",
  "properties": {
    "addr:full":"1846 Union Ave Natrona Heights PA 15065",
    "addr:housenumber":"1846",
    "addr:postcode":"15065",
    "addr:street":"Union Ave",
    "iso:country":"US",
    "sg:address":"1846 Union Ave",
    "sg:city":"Natrona Heights",
    "sg:classifiers":[
        {
            "category":"Shopping",
            "subcategory":"Pharmacy",
            "type":"Retail Goods"
        }
    ],
    "sg:phone":"+1 724 224 9084",
    "sg:postcode":"15065",
    "sg:province":"PA",
    "sg:website":"www.cvs.com",
    "wof:name":"CVS Pharmacy",
    "wof:placetype":"venue"
},
  "geometry": {"coordinates":[-79.724661,40.621961],"type":"Point"}
}