{
  "type": "Feature",
  "properties": {
    "addr:full":"1405 N 52nd St Philadelphia PA 19131",
    "addr:housenumber":"1405",
    "addr:postcode":"19131",
    "addr:street":"N 52Nd St",
    "iso:country":"US",
    "sg:address":"1405 N 52nd St",
    "sg:city":"Philadelphia",
    "sg:classifiers":[
        {
            "category":"Personal",
            "subcategory":"Beauty Salon",
            "type":"Services"
        }
    ],
    "sg:phone":"+1 215 473 4442",
    "sg:postcode":"19131",
    "sg:province":"PA",
    "wof:name":"Ruth Brooks",
    "wof:placetype":"venue"
},
  "geometry": {"coordinates":[-75.226372,39.974643],"type":"Point"}
}