{
  "type": "Feature",
  "properties": {
    "iso:country":"US",
    "sg:address":"1022 E Lawrence Ave",
    "sg:city":"Ellwood City",
    "sg:classifiers":[
        {
            "category":"Wholesale",
            "subcategory":"Beer",
            "type":"Manufacturing & Wholesale Goods"
        }
    ],
    "sg:phone":"+1 724 758 4576",
    "sg:postcode":"16117",
    "sg:province":"PA",
    "sg:tags":[
        "ale",
        "alcoholic",
        "beverage"
    ],
    "wof:name":"Pete's Uptown Beer & Beverage",
    "wof:placetype":"venue"
},
  "geometry": {"coordinates":[-80.29580900000001,40.858435],"type":"Point"}
}