{
  "type": "Feature",
  "properties": {
    "iso:country":"US",
    "sg:address":"3 W Green St",
    "sg:city":"Nanticoke",
    "sg:classifiers":[
        {
            "category":"Shopping",
            "subcategory":"Catalog Store",
            "type":"Retail Goods"
        }
    ],
    "sg:phone":"+1   ",
    "sg:postcode":"18634",
    "sg:province":"PA",
    "sg:tags":[
        "mail",
        "house"
    ],
    "wof:name":"Art316",
    "wof:placetype":"venue"
},
  "geometry": {"coordinates":[-76.004665,41.201038],"type":"Point"}
}