{
  "type": "Feature",
  "properties": {
    "addr:full":"496 Bradford Rd Oreland PA 19075",
    "addr:housenumber":"496",
    "addr:postcode":"19075",
    "addr:street":"Bradford Rd",
    "iso:country":"US",
    "sg:address":"496 Bradford Rd",
    "sg:city":"Oreland",
    "sg:classifiers":[
        {
            "category":"Health Services",
            "subcategory":"Clinic",
            "type":"Services"
        }
    ],
    "sg:phone":"+1   ",
    "sg:postcode":"19075",
    "sg:province":"PA",
    "sg:tags":[
        "specialty",
        "outpatient"
    ],
    "wof:name":"Nancy Small PHD",
    "wof:placetype":"venue"
},
  "geometry": {"coordinates":[-75.196462,40.105862],"type":"Point"}
}