{
  "type": "Feature",
  "properties": {
    "iso:country":"US",
    "sg:address":"1136 Ashbourne Dr",
    "sg:city":"Reading",
    "sg:classifiers":[
        {
            "category":"Professional",
            "subcategory":"Lawyer & Legal Services",
            "type":"Services"
        }
    ],
    "sg:phone":"+1 610 939 9051",
    "sg:postcode":"19605",
    "sg:province":"PA",
    "sg:tags":[
        "attorney"
    ],
    "wof:name":"Andrew Onwudinjo",
    "wof:placetype":"venue"
},
  "geometry": {"coordinates":[-75.967077,40.396235],"type":"Point"}
}