{
  "type": "Feature",
  "properties": {
    "addr:full":"1815 Newport Rd Ephrata PA 17522",
    "addr:housenumber":"1815",
    "addr:postcode":"17522",
    "addr:street":"Newport Rd",
    "iso:country":"US",
    "sg:address":"1815 Newport Rd",
    "sg:city":"Ephrata",
    "sg:classifiers":[
        {
            "category":"Wholesale",
            "subcategory":"Painting Supplies",
            "type":"Manufacturing & Wholesale Goods"
        }
    ],
    "sg:phone":"+1   ",
    "sg:postcode":"17522",
    "sg:province":"PA",
    "wof:name":"Colors",
    "wof:placetype":"venue"
},
  "geometry": {"coordinates":[-76.218316,40.1333],"type":"Point"}
}