{
  "type": "Feature",
  "properties": {
    "iso:country":"US",
    "sg:address":"2435 Bellwood Dr",
    "sg:city":"Pittsburgh",
    "sg:classifiers":[
        {
            "category":"Wholesale",
            "subcategory":"Jewelry",
            "type":"Manufacturing & Wholesale Goods"
        }
    ],
    "sg:phone":"+1 412 369 4011",
    "sg:postcode":"15237",
    "sg:province":"PA",
    "sg:tags":[
        "jeweler"
    ],
    "wof:name":"Elizabeth Gail LTD",
    "wof:placetype":"venue"
},
  "geometry": {"coordinates":[-80.080844,40.585339],"type":"Point"}
}