{
  "type": "Feature",
  "properties": {
    "iso:country":"US",
    "sg:address":"310 E Market St",
    "sg:city":"Clearfield",
    "sg:classifiers":[
        {
            "category":"Organizations",
            "subcategory":"Community Association",
            "type":"Services"
        }
    ],
    "sg:phone":"+1 814 765 8153",
    "sg:postcode":"16830",
    "sg:province":"PA",
    "sg:tags":[
        "club"
    ],
    "wof:name":"Fraternal Order Of Eagles",
    "wof:placetype":"venue"
},
  "geometry": {"coordinates":[-78.436173,41.022151],"type":"Point"}
}