{
  "type": "Feature",
  "properties": {
    "iso:country":"US",
    "sg:address":"1403 Dalehurst Dr",
    "sg:city":"Bethlehem",
    "sg:classifiers":[
        {
            "category":"Building & Trades",
            "subcategory":"Construction",
            "type":"Services"
        }
    ],
    "sg:phone":"+1 610 868 5086",
    "sg:postcode":"18018",
    "sg:province":"PA",
    "sg:tags":[
        "contractor"
    ],
    "wof:name":"Oakes Construction Services",
    "wof:placetype":"venue"
},
  "geometry": {"coordinates":[-75.401737,40.631621],"type":"Point"}
}