{
  "type": "Feature",
  "properties": {
    "addr:full":"401 W Spring St Titusville PA 16354",
    "addr:housenumber":"401",
    "addr:postcode":"16354",
    "addr:street":"W Spring St",
    "iso:country":"US",
    "sg:address":"401 W Spring St",
    "sg:city":"Titusville",
    "sg:classifiers":[
        {
            "category":"Health Services",
            "subcategory":"Doctor",
            "type":"Services"
        }
    ],
    "sg:phone":"+1   ",
    "sg:postcode":"16354",
    "sg:province":"PA",
    "sg:tags":[
        "medical"
    ],
    "wof:name":"Orthopedic Spt Medicine Assoc",
    "wof:placetype":"venue"
},
  "geometry": {"coordinates":[-79.68076499999999,41.627075],"type":"Point"}
}