{
  "type": "Feature",
  "properties": {
    "iso:country":"US",
    "sg:address":"2100 Quaker Pointe Dr",
    "sg:city":"Quakertown",
    "sg:classifiers":[
        {
            "category":"Health Services",
            "subcategory":"Doctor",
            "type":"Services"
        }
    ],
    "sg:phone":"+1 215 536 1137",
    "sg:postcode":"18951",
    "sg:province":"PA",
    "sg:tags":[
        "medical"
    ],
    "sg:website":"www.clinicalanalysiscorporation.net",
    "wof:name":"Clinical Analysis Corp",
    "wof:placetype":"venue"
},
  "geometry": {"coordinates":[-75.413355,40.433873],"type":"Point"}
}