{
  "type": "Feature",
  "properties": {
    "iso:country":"US",
    "sg:address":"45 N 2nd St",
    "sg:city":"Philadelphia",
    "sg:classifiers":[
        {
            "category":"Shopping",
            "subcategory":"Hobbies, Toys, & Games",
            "type":"Retail Goods"
        },
        {
            "category":"Shopping",
            "subcategory":"Gifts & Souvenirs",
            "type":"Retail Goods"
        },
        {
            "category":"Shopping",
            "subcategory":"Books",
            "type":"Retail Goods"
        },
        {
            "category":"Shopping",
            "subcategory":"Comic Books",
            "type":"Retail Goods"
        }
    ],
    "sg:phone":"+1 215 925 6525",
    "sg:postcode":"19106",
    "sg:province":"PA",
    "sg:tags":[
        "shop",
        "toy",
        "rare",
        "dealers-used",
        "hobby",
        "store"
    ],
    "sg:website":"www.bravenewworldscomics.com",
    "wof:name":"Brave New Worlds",
    "wof:placetype":"venue"
},
  "geometry": {"coordinates":[-75.143433,39.951237],"type":"Point"}
}