{
  "type": "Feature",
  "properties": {
    "addr:full":"11 Robinson St Pottstown PA 19464",
    "addr:housenumber":"11",
    "addr:postcode":"19464",
    "addr:street":"Robinson St",
    "iso:country":"US",
    "sg:address":"11 Robinson St",
    "sg:city":"Pottstown",
    "sg:classifiers":[
        {
            "category":"Banks & Credit Unions",
            "subcategory":"Investment Brokerage",
            "type":"Services"
        }
    ],
    "sg:phone":"+1 610 705 3013",
    "sg:postcode":"19464",
    "sg:province":"PA",
    "sg:tags":[
        "advisory",
        "financial"
    ],
    "wof:name":"Dearden Maguire & Weaver",
    "wof:placetype":"venue"
},
  "geometry": {"coordinates":[-75.66371100000001,40.257304],"type":"Point"}
}