{
  "type": "Feature",
  "properties": {
    "iso:country":"US",
    "sg:address":"306 Butztown Rd",
    "sg:city":"Bethlehem",
    "sg:classifiers":[
        {
            "category":"Government",
            "subcategory":"Office",
            "type":"Public Place"
        }
    ],
    "sg:phone":"+1   ",
    "sg:postcode":"18020",
    "sg:province":"PA",
    "sg:tags":[
        "city"
    ],
    "wof:name":"Lower Nazareth Zoning Office",
    "wof:placetype":"venue"
},
  "geometry": {"coordinates":[-75.332064,40.696602],"type":"Point"}
}