{
  "type": "Feature",
  "properties": {
    "iso:country":"US",
    "sg:address":"171 Greyhorse Rd",
    "sg:city":"Willow Grove",
    "sg:classifiers":[
        {
            "category":"Home & Garden",
            "subcategory":"Building Materials",
            "type":"Retail Goods"
        }
    ],
    "sg:phone":"+1 215 659 4120",
    "sg:postcode":"19090",
    "sg:province":"PA",
    "sg:tags":[
        "door"
    ],
    "wof:name":"Alta Co",
    "wof:placetype":"venue"
},
  "geometry": {"coordinates":[-75.103296,40.147947],"type":"Point"}
}