{
  "type": "Feature",
  "properties": {
    "iso:country":"US",
    "sg:address":"1517A N Gratz St",
    "sg:city":"Philadelphia",
    "sg:classifiers":[
        {
            "category":"Professional",
            "subcategory":"Computer Services",
            "type":"Services"
        }
    ],
    "sg:phone":"+1 267 670 0467",
    "sg:postcode":"19121",
    "sg:province":"PA",
    "sg:tags":[
        "consultant",
        "designer",
        "system"
    ],
    "wof:name":"Latchkey Solutions",
    "wof:placetype":"venue"
},
  "geometry": {"coordinates":[-75.165494,39.977611],"type":"Point"}
}