{
  "type": "Feature",
  "properties": {
    "addr:full":"501 S 9th St Reading PA 19602",
    "addr:housenumber":"501",
    "addr:postcode":"19602",
    "addr:street":"S 9Th St",
    "iso:country":"US",
    "sg:address":"501 S 9th St",
    "sg:city":"Reading",
    "sg:classifiers":[
        {
            "category":"Building & Trades",
            "subcategory":"Construction",
            "type":"Services"
        }
    ],
    "sg:phone":"+1 610 376 8686",
    "sg:postcode":"19602",
    "sg:province":"PA",
    "sg:tags":[
        "maker",
        "cabinet"
    ],
    "sg:website":"www.craft-maid.com",
    "wof:name":"Craft Maid",
    "wof:placetype":"venue"
},
  "geometry": {"coordinates":[-75.92034,40.327501],"type":"Point"}
}