{
  "type": "Feature",
  "properties": {
    "iso:country":"US",
    "sg:address":"209 Hughes Rd",
    "sg:city":"Watsontown",
    "sg:classifiers":[
        {
            "category":"Retail",
            "subcategory":"Auto Repair",
            "type":"Services"
        }
    ],
    "sg:phone":"+1 570 538 4341",
    "sg:postcode":"17771",
    "sg:province":"PA",
    "sg:tags":[
        "repairing",
        "automobile"
    ],
    "wof:name":"Ray's Auto Repair",
    "wof:placetype":"venue"
},
  "geometry": {"coordinates":[-77.255534,41.392987],"type":"Point"}
}