{
  "type": "Feature",
  "properties": {
    "iso:country":"US",
    "sg:address":"1801 E Market St Ste B, Ste B",
    "sg:city":"York",
    "sg:phone":"+1 717 840 1956",
    "sg:postcode":"17402",
    "sg:province":"PA",
    "sg:website":"http://www.nationwide.com/agent/York-PENNSYLVANIA-insurance-agent/frank-guerrini/office.html",
    "wof:name":"Frank L Guerrini - Nationwide Insurance",
    "wof:placetype":"venue"
},
  "geometry": {"coordinates":[-76.691711,39.973221],"type":"Point"}
}