{
  "type": "Feature",
  "properties": {
    "iso:country":"US",
    "sg:address":"47 Laurel Mall",
    "sg:city":"Hazleton",
    "sg:classifiers":[
        {
            "category":"Shopping",
            "subcategory":"Beauty & Cosmetics",
            "type":"Retail Goods"
        }
    ],
    "sg:phone":"+1   ",
    "sg:postcode":"18201",
    "sg:province":"PA",
    "sg:tags":[
        "merchandise"
    ],
    "wof:name":"Bath & Body Works",
    "wof:placetype":"venue"
},
  "geometry": {"coordinates":[-76.01933099999999,40.981352],"type":"Point"}
}