{
  "type": "Feature",
  "properties": {
    "iso:country":"US",
    "sg:address":"147 Old Newport St",
    "sg:city":"Nanticoke",
    "sg:classifiers":[
        {
            "category":"Health Services",
            "subcategory":"Clinic",
            "type":"Services"
        },
        {
            "category":"Health Services",
            "subcategory":"Health Practitioner",
            "type":"Services"
        }
    ],
    "sg:phone":"+1 570 735 7300",
    "sg:postcode":"18634",
    "sg:province":"PA",
    "sg:tags":[
        "home",
        "therapist",
        "rehabilitation",
        "physical"
    ],
    "sg:website":"http://www.guardianeldercare.com",
    "wof:name":"Guardian Health Care",
    "wof:placetype":"venue"
},
  "geometry": {"coordinates":[-76.018102,41.192153],"type":"Point"}
}