{
  "type": "Feature",
  "properties": {
    "iso:country":"US",
    "sg:address":"1225 S Market St",
    "sg:city":"Mechanicsburg",
    "sg:classifiers":[
        {
            "category":"Shopping",
            "subcategory":"Books",
            "type":"Retail Goods"
        }
    ],
    "sg:phone":"+1 717 918 2665",
    "sg:postcode":"17055",
    "sg:province":"PA",
    "sg:tags":[
        "dealer"
    ],
    "wof:name":"Book Of The Month Club",
    "wof:placetype":"venue"
},
  "geometry": {"coordinates":[-76.994653,40.196863],"type":"Point"}
}