{
  "type": "Feature",
  "properties": {
    "addr:full":"3400 Versailles Ave Mckeesport PA 15132",
    "addr:housenumber":"3400",
    "addr:postcode":"15132",
    "addr:street":"Versailles Ave",
    "iso:country":"US",
    "sg:address":"3400 Versailles Ave",
    "sg:city":"Mckeesport",
    "sg:classifiers":[
        {
            "category":"Food & Beverages",
            "subcategory":"Groceries & Convenience Stores",
            "type":"Retail Goods"
        }
    ],
    "sg:phone":"+1 412 672 8988",
    "sg:postcode":"15132",
    "sg:province":"PA",
    "wof:name":"Uni-Mart",
    "wof:placetype":"venue"
},
  "geometry": {"coordinates":[-79.836394,40.344795],"type":"Point"}
}