{
  "type": "Feature",
  "properties": {
    "addr:full":"3337 Marietta Ave Lancaster PA 17601",
    "addr:housenumber":"3337",
    "addr:postcode":"17601",
    "addr:street":"Marietta Ave",
    "iso:country":"US",
    "sg:address":"3337 Marietta Ave",
    "sg:city":"Lancaster",
    "sg:classifiers":[
        {
            "category":"Wholesale",
            "subcategory":"Groceries",
            "type":"Manufacturing & Wholesale Goods"
        }
    ],
    "sg:phone":"+1 717 285 5529",
    "sg:postcode":"17601",
    "sg:province":"PA",
    "sg:tags":[
        "chips",
        "potato"
    ],
    "wof:name":"Martin's Potato Chips",
    "wof:placetype":"venue"
},
  "geometry": {"coordinates":[-76.42810799999999,40.062664],"type":"Point"}
}