{
  "type": "Feature",
  "properties": {
    "iso:country":"US",
    "sg:address":"1200 Welsh Rd",
    "sg:city":"North Wales",
    "sg:classifiers":[
        {
            "category":"Restaurant",
            "type":"Food & Drink"
        }
    ],
    "sg:phone":"+1 267 263 4088",
    "sg:postcode":"19454",
    "sg:province":"PA",
    "sg:tags":[
        "new",
        "american"
    ],
    "sg:website":"www.63bistro.com",
    "wof:name":"63 Bistro",
    "wof:placetype":"venue"
},
  "geometry": {"coordinates":[-75.257918,40.226748],"type":"Point"}
}