{
  "type": "Feature",
  "properties": {
    "addr:city":"Stroudsburg",
    "addr:full":"900 Main St Stroudsburg, Pa 18360-1604",
    "addr:house_number":"900",
    "addr:housenumber":"900",
    "addr:phone":"+1 570-421-7703",
    "addr:postcode":"18360-1604",
    "addr:road":"Main St",
    "addr:state":"PA",
    "addr:street":"Main St",
    "iso:country":"US",
    "sg:address":"900 Main St",
    "sg:city":"Stroudsburg",
    "sg:classifiers":[
        {
            "category":"Museum",
            "type":"Entertainment"
        }
    ],
    "sg:phone":"+1 570 421 7703",
    "sg:postcode":"18360",
    "sg:province":"PA",
    "sg:tags":[
        "gallery"
    ],
    "sg:website":"www.mcha-pa.org",
    "wof:name":"Monroe County Historical Association",
    "wof:placetype":"venue"
},
  "geometry": {"coordinates":[-75.19905,40.98411],"type":"Point"}
}