{
  "type": "Feature",
  "properties": {
    "addr:full":"900 Main St Stroudsburg PA 18360",
    "addr:housenumber":"900",
    "addr:postcode":"18360",
    "addr:street":"Main St",
    "iso:country":"US",
    "sg:address":"900 Main St",
    "sg:city":"Stroudsburg",
    "sg:classifiers":[
        {
            "category":"Museum",
            "type":"Entertainment"
        }
    ],
    "sg:phone":"+1 570 421 7703",
    "sg:postcode":"18360",
    "sg:province":"PA",
    "sg:tags":[
        "gallery"
    ],
    "sg:website":"www.mcha-pa.org",
    "wof:name":"Monroe County Historical Assn",
    "wof:placetype":"venue"
},
  "geometry": {"coordinates":[-75.19788200000001,40.984349],"type":"Point"}
}