{
  "type": "Feature",
  "properties": {
    "iso:country":"US",
    "sg:address":"103 S Main St",
    "sg:city":"Quakertown",
    "sg:classifiers":[
        {
            "category":"Manufacturing",
            "subcategory":"Tools & Machinery",
            "type":"Manufacturing & Wholesale Goods"
        }
    ],
    "sg:phone":"+1 215 536 2991",
    "sg:postcode":"18951",
    "sg:province":"PA",
    "sg:tags":[
        "equipment",
        "safety",
        "clothing"
    ],
    "sg:website":"www.quakersafety.com",
    "wof:name":"Quaker Safety Products Corp",
    "wof:placetype":"venue"
},
  "geometry": {"coordinates":[-75.352225,40.4381],"type":"Point"}
}