{
  "type": "Feature",
  "properties": {
    "addr:full":"2542 W Lehigh Ave Philadelphia PA 19132",
    "addr:housenumber":"2542",
    "addr:postcode":"19132",
    "addr:street":"W Lehigh Ave",
    "iso:country":"US",
    "sg:address":"2542 W Lehigh Ave",
    "sg:city":"Philadelphia",
    "sg:classifiers":[
        {
            "category":"Social Services",
            "type":"Services"
        }
    ],
    "sg:phone":"+1 215 227 7722",
    "sg:postcode":"19132",
    "sg:province":"PA",
    "wof:name":"PCCO",
    "wof:placetype":"venue"
},
  "geometry": {"coordinates":[-75.17343700000001,39.996276],"type":"Point"}
}