{
  "type": "Feature",
  "properties": {
    "iso:country":"US",
    "sg:address":"810 Bitner Rd",
    "sg:city":"Dunbar",
    "sg:classifiers":[
        {
            "category":"Health Services",
            "subcategory":"Nursing And Care Facility",
            "type":"Services"
        }
    ],
    "sg:phone":"+1 724 425 1704",
    "sg:postcode":"15431",
    "sg:province":"PA",
    "sg:tags":[
        "home",
        "retirement",
        "community"
    ],
    "wof:name":"Prinkey's Personal Care Home",
    "wof:placetype":"venue"
},
  "geometry": {"coordinates":[-79.70166999999999,39.98952],"type":"Point"}
}