{
  "type": "Feature",
  "properties": {
    "iso:country":"US",
    "sg:address":"Perelman Center for Advanced Medicine 3400 Civic Center Boulevard",
    "sg:city":"Philadelphia",
    "sg:classifiers":[
        {
            "category":"Health Services",
            "subcategory":"Doctor",
            "type":"Services"
        }
    ],
    "sg:phone":"+1 215 662 2737",
    "sg:postcode":"19104",
    "sg:province":"PA",
    "sg:tags":[
        "dermatologist"
    ],
    "sg:website":"www.pennmedicine.org/dermatology/",
    "wof:name":"Penn Dermatology",
    "wof:placetype":"venue"
},
  "geometry": {"coordinates":[-75.192275,39.947617],"type":"Point"}
}