{
  "type": "Feature",
  "properties": {
    "addr:full":"626 Haverford Rd Haverford PA 19041",
    "addr:housenumber":"626",
    "addr:postcode":"19041",
    "addr:street":"Haverford Rd",
    "iso:country":"US",
    "sg:address":"626 Haverford Rd",
    "sg:city":"Haverford",
    "sg:classifiers":[
        {
            "category":"Health Services",
            "subcategory":"Health Practitioner",
            "type":"Services"
        },
        {
            "category":"Communications",
            "type":"Services"
        }
    ],
    "sg:phone":"+1 610 649 8255",
    "sg:postcode":"19041",
    "sg:province":"PA",
    "sg:tags":[
        "pathologist",
        "speech-language",
        "myofunctional",
        "therapy"
    ],
    "sg:website":"http://mainlinespeech.com",
    "wof:name":"Main Line Speech Consultants Ltd",
    "wof:placetype":"venue"
},
  "geometry": {"coordinates":[-75.314623,40.010232],"type":"Point"}
}