{
  "type": "Feature",
  "properties": {
    "addr:full":"429 Walnut St Reading PA 19601",
    "addr:housenumber":"429",
    "addr:postcode":"19601",
    "addr:street":"Walnut St",
    "iso:country":"US",
    "sg:address":"429 Walnut St",
    "sg:city":"Reading",
    "sg:classifiers":[
        {
            "category":"Health Services",
            "subcategory":"Clinic",
            "type":"Services"
        }
    ],
    "sg:phone":"+1   ",
    "sg:postcode":"19601",
    "sg:province":"PA",
    "wof:name":"Co County Wellness Services",
    "wof:placetype":"venue"
},
  "geometry": {"coordinates":[-75.927869,40.33853],"type":"Point"}
}