{
  "type": "Feature",
  "properties": {
    "iso:country":"US",
    "sg:address":"2134 E Lippincott St",
    "sg:city":"Philadelphia",
    "sg:classifiers":[
        {
            "category":"Manufacturing",
            "subcategory":"Metals",
            "type":"Manufacturing & Wholesale Goods"
        }
    ],
    "sg:phone":"+1 215 634 7300",
    "sg:postcode":"19134",
    "sg:province":"PA",
    "sg:tags":[
        "fabricator",
        "aluminum"
    ],
    "wof:name":"Paragon Welding Co",
    "wof:placetype":"venue"
},
  "geometry": {"coordinates":[-75.110336,39.990937],"type":"Point"}
}