{
  "type": "Feature",
  "properties": {
    "addr:full":"141 Railroad St Tamaqua PA 18252",
    "addr:housenumber":"141",
    "addr:postcode":"18252",
    "addr:street":"Railroad St",
    "iso:country":"US",
    "sg:address":"141 Railroad St",
    "sg:city":"Tamaqua",
    "sg:classifiers":[
        {
            "category":"Food & Beverages",
            "subcategory":"Liquor & Beverages",
            "type":"Retail Goods"
        }
    ],
    "sg:phone":"+1 570 952 3370",
    "sg:postcode":"18252",
    "sg:province":"PA",
    "wof:name":"State Liquor Store",
    "wof:placetype":"venue"
},
  "geometry": {"coordinates":[-75.970304,40.799963],"type":"Point"}
}