{
  "type": "Feature",
  "properties": {
    "iso:country":"US",
    "sg:address":"817 N Easton Rd",
    "sg:city":"Doylestown",
    "sg:classifiers":[
        {
            "category":"Health Services",
            "subcategory":"Dentist",
            "type":"Services"
        }
    ],
    "sg:phone":"+1 215 348 4041",
    "sg:postcode":"18901",
    "sg:province":"PA",
    "sg:tags":[
        "orthodontist"
    ],
    "sg:website":"www.americandentalconcepts.com",
    "wof:name":"Brattelli Steven DMD",
    "wof:placetype":"venue"
},
  "geometry": {"coordinates":[-75.130501,40.336102],"type":"Point"}
}