{
  "type": "Feature",
  "properties": {
    "addr:full":"934 Bustleton Pike Feastervl Trvs PA 19053",
    "addr:housenumber":"934",
    "addr:postcode":"19053",
    "addr:street":"Bustleton Pike",
    "iso:country":"US",
    "sg:address":"934 Bustleton Pike",
    "sg:city":"Feastervl Trvs",
    "sg:classifiers":[
        {
            "category":"Autos & Motor Vehicles",
            "subcategory":"Auto Supplies",
            "type":"Retail Goods"
        },
        {
            "category":"Shopping",
            "subcategory":"Computers & Home Electronics",
            "type":"Retail Goods"
        }
    ],
    "sg:phone":"+1 215 942 0303",
    "sg:postcode":"19053",
    "sg:province":"PA",
    "sg:tags":[
        "automobile",
        "stereo",
        "radio",
        "automotive",
        "volt"
    ],
    "wof:name":"Becker Audio & Communications",
    "wof:placetype":"venue"
},
  "geometry": {"coordinates":[-75.002954,40.149862],"type":"Point"}
}