{
  "type": "Feature",
  "properties": {
    "iso:country":"US",
    "sg:address":"110 Washington St",
    "sg:city":"Conshohocken",
    "sg:classifiers":[
        {
            "category":"Manufacturing",
            "subcategory":"Metals",
            "type":"Manufacturing & Wholesale Goods"
        }
    ],
    "sg:phone":"+1   ",
    "sg:postcode":"19428",
    "sg:province":"PA",
    "sg:tags":[
        "structural",
        "industrial",
        "machinery",
        "mfg"
    ],
    "wof:name":"R J Florig Industrial Company",
    "wof:placetype":"venue"
},
  "geometry": {"coordinates":[-75.30694099999999,40.07157],"type":"Point"}
}