{
  "type": "Feature",
  "properties": {
    "iso:country":"US",
    "sg:address":"2850 W 21st St",
    "sg:city":"Erie",
    "sg:classifiers":[
        {
            "category":"Professional",
            "subcategory":"Employment Agencies",
            "type":"Services"
        }
    ],
    "sg:phone":"+1 814 838 6800",
    "sg:postcode":"16506",
    "sg:province":"PA",
    "sg:website":"www.palladiumemployment.com",
    "wof:name":"Palladium Employment",
    "wof:placetype":"venue"
},
  "geometry": {"coordinates":[-80.136943,42.093879],"type":"Point"}
}