{
  "type": "Feature",
  "properties": {
    "iso:country":"US",
    "sg:address":"5320 National Pike",
    "sg:city":"Markleysburg",
    "sg:classifiers":[
        {
            "category":"Autos & Motor Vehicles",
            "subcategory":"Motorcycle Sales",
            "type":"Retail Goods"
        }
    ],
    "sg:phone":"+1 724 329 0814",
    "sg:postcode":"15459",
    "sg:province":"PA",
    "sg:tags":[
        "scooter"
    ],
    "wof:name":"Sportrider Outdoors LLC",
    "wof:placetype":"venue"
},
  "geometry": {"coordinates":[-79.46812,39.766851],"type":"Point"}
}