{
  "type": "Feature",
  "properties": {
    "iso:country":"US",
    "sg:address":"10 Reitz Blvd",
    "sg:city":"Lewisburg",
    "sg:classifiers":[
        {
            "category":"Banks & Credit Unions",
            "subcategory":"Bank",
            "type":"Services"
        }
    ],
    "sg:phone":"+1   ",
    "sg:postcode":"17837",
    "sg:province":"PA",
    "sg:tags":[
        "state",
        "commercial"
    ],
    "wof:name":"M&T",
    "wof:placetype":"venue"
},
  "geometry": {"coordinates":[-76.912544,40.957686],"type":"Point"}
}