{
  "type": "Feature",
  "properties": {
    "iso:country":"US",
    "sg:address":"409 Pennsylvania Ave",
    "sg:city":"Reading",
    "sg:classifiers":[
        {
            "category":"Banks & Credit Unions",
            "subcategory":"Bank",
            "type":"Services"
        }
    ],
    "sg:phone":"+1   ",
    "sg:postcode":"19607",
    "sg:province":"PA",
    "sg:tags":[
        "broker",
        "mortgage"
    ],
    "wof:name":"Richard H Shuker",
    "wof:placetype":"venue"
},
  "geometry": {"coordinates":[-75.960617,40.310483],"type":"Point"}
}