{
  "type": "Feature",
  "properties": {
    "addr:full":"29 Turner Ln West Chester PA 19380",
    "addr:housenumber":"29",
    "addr:postcode":"19380",
    "addr:street":"Turner Ln",
    "iso:country":"US",
    "sg:address":"29 Turner Ln",
    "sg:city":"West Chester",
    "sg:classifiers":[
        {
            "category":"Professional",
            "subcategory":"Business Services",
            "type":"Services"
        }
    ],
    "sg:phone":"+1 610 692 2500",
    "sg:postcode":"19380",
    "sg:province":"PA",
    "sg:tags":[
        "interior",
        "consultant",
        "design",
        "decorator"
    ],
    "wof:name":"Belgravia Interiors",
    "wof:placetype":"venue"
},
  "geometry": {"coordinates":[-75.587262,39.967992],"type":"Point"}
}