{
  "type": "Feature",
  "properties": {
    "iso:country":"US",
    "sg:address":"3015 Horseshoe Pike",
    "sg:city":"Honey Brook",
    "sg:classifiers":[
        {
            "category":"Retail",
            "subcategory":"Auto Repair",
            "type":"Services"
        }
    ],
    "sg:phone":"+1 610 273 2546",
    "sg:postcode":"19344",
    "sg:province":"PA",
    "sg:tags":[
        "repairing",
        "automotive",
        "automobile"
    ],
    "wof:name":"Gable's Auto Repair",
    "wof:placetype":"venue"
},
  "geometry": {"coordinates":[-75.858518,40.078422],"type":"Point"}
}