{
  "type": "Feature",
  "properties": {
    "addr:full":"5000 Dolores Dr Pittsburgh PA 15227",
    "addr:housenumber":"5000",
    "addr:postcode":"15227",
    "addr:street":"Dolores Dr",
    "iso:country":"US",
    "sg:address":"5000 Dolores Dr",
    "sg:city":"Pittsburgh",
    "sg:classifiers":[
        {
            "category":"Professional",
            "type":"Services"
        }
    ],
    "sg:phone":"+1   ",
    "sg:postcode":"15227",
    "sg:province":"PA",
    "wof:name":"Biomed International Inc",
    "wof:placetype":"venue"
},
  "geometry": {"coordinates":[-79.97194399999999,40.354496],"type":"Point"}
}