{
  "type": "Feature",
  "properties": {
    "iso:country":"US",
    "sg:address":"2300 Sheffield Rd",
    "sg:city":"Aliquippa",
    "sg:classifiers":[
        {
            "category":"Health Services",
            "subcategory":"Dentist",
            "type":"Services"
        }
    ],
    "sg:phone":"+1 724 378 1631",
    "sg:postcode":"15001",
    "sg:province":"PA",
    "wof:name":"University Dental Health Services",
    "wof:placetype":"venue"
},
  "geometry": {"coordinates":[-80.2808,40.606609],"type":"Point"}
}