{
  "type": "Feature",
  "properties": {
    "addr:full":"5553 W Ridge Rd Erie PA 16506",
    "addr:housenumber":"5553",
    "addr:postcode":"16506",
    "addr:street":"W Ridge Rd",
    "iso:country":"US",
    "sg:address":"5553 W Ridge Rd",
    "sg:city":"Erie",
    "sg:classifiers":[
        {
            "category":"Retail",
            "subcategory":"Car Wash",
            "type":"Services"
        }
    ],
    "sg:phone":"+1   ",
    "sg:postcode":"16506",
    "sg:province":"PA",
    "sg:tags":[
        "carwash"
    ],
    "wof:name":"Lake F-X Car Care Studio",
    "wof:placetype":"venue"
},
  "geometry": {"coordinates":[-80.195408,42.064753],"type":"Point"}
}