{
  "type": "Feature",
  "properties": {
    "addr:full":"558 Philadelphia St Indiana PA 15701",
    "addr:housenumber":"558",
    "addr:postcode":"15701",
    "addr:street":"Philadelphia St",
    "iso:country":"US",
    "sg:address":"558 Philadelphia St",
    "sg:city":"Indiana",
    "sg:classifiers":[
        {
            "category":"Professional",
            "type":"Services"
        }
    ],
    "sg:phone":"+1 724 465 6428",
    "sg:postcode":"15701",
    "sg:province":"PA",
    "sg:tags":[
        "establishment"
    ],
    "wof:name":"Valcon LP",
    "wof:placetype":"venue"
},
  "geometry": {"coordinates":[-79.149754,40.622837],"type":"Point"}
}