{
  "type": "Feature",
  "properties": {
    "iso:country":"US",
    "sg:address":"441 Sterling Rd",
    "sg:city":"Tobyhanna",
    "sg:classifiers":[
        {
            "category":"Food & Beverages",
            "subcategory":"Groceries & Convenience Stores",
            "type":"Retail Goods"
        }
    ],
    "sg:phone":"+1 570 895 4530",
    "sg:postcode":"18466",
    "sg:province":"PA",
    "wof:name":"Penmart",
    "wof:placetype":"venue"
},
  "geometry": {"coordinates":[-75.357624,41.152836],"type":"Point"}
}