{
  "type": "Feature",
  "properties": {
    "addr:full":"312 S Tulpehocken St Pine Grove PA 17963",
    "addr:housenumber":"312",
    "addr:postcode":"17963",
    "addr:street":"S Tulpehocken St",
    "iso:country":"US",
    "sg:address":"312 S Tulpehocken St",
    "sg:city":"Pine Grove",
    "sg:classifiers":[
        {
            "category":"Organizations",
            "subcategory":"Religious Organization",
            "type":"Services"
        }
    ],
    "sg:phone":"+1 570 345 3306",
    "sg:postcode":"17963",
    "sg:province":"PA",
    "sg:tags":[
        "church"
    ],
    "wof:name":"St Peter's Lutheran Church",
    "wof:placetype":"venue"
},
  "geometry": {"coordinates":[-76.386374,40.542727],"type":"Point"}
}