{
  "type": "Feature",
  "properties": {
    "iso:country":"US",
    "sg:address":"221 N Cedar Crest Blvd",
    "sg:city":"Allentown",
    "sg:classifiers":[
        {
            "category":"Professional",
            "subcategory":"Lawyer & Legal Services",
            "type":"Services"
        }
    ],
    "sg:phone":"+1 610 437 6642",
    "sg:postcode":"18104",
    "sg:province":"PA",
    "wof:name":"Romberger Karl A Jr Esquire",
    "wof:placetype":"venue"
},
  "geometry": {"coordinates":[-75.525597,40.5914],"type":"Point"}
}