{
  "type": "Feature",
  "properties": {
    "iso:country":"US",
    "sg:address":"2630 Lake St",
    "sg:city":"Lake City",
    "sg:classifiers":[
        {
            "category":"Building & Trades",
            "subcategory":"Plumbing",
            "type":"Services"
        }
    ],
    "sg:phone":"+1   ",
    "sg:postcode":"16423",
    "sg:province":"PA",
    "sg:tags":[
        "contractor"
    ],
    "wof:name":"Lane Plumbing Heating & AC",
    "wof:placetype":"venue"
},
  "geometry": {"coordinates":[-80.346265,42.009546],"type":"Point"}
}