{
  "type": "Feature",
  "properties": {
    "iso:country":"US",
    "sg:address":"4 Grace Dr",
    "sg:city":"Tunkhannock",
    "sg:classifiers":[
        {
            "category":"Personal",
            "type":"Services"
        },
        {
            "category":"Personal",
            "subcategory":"Beauty Salon",
            "type":"Services"
        }
    ],
    "sg:phone":"+1 570 836 1957",
    "sg:postcode":"18657",
    "sg:province":"PA",
    "wof:name":"Hair Zoo",
    "wof:placetype":"venue"
},
  "geometry": {"coordinates":[-75.968187,41.581865],"type":"Point"}
}