{
  "type": "Feature",
  "properties": {
    "addr:full":"2625 N 2nd St Harrisburg PA 17110",
    "addr:housenumber":"2625",
    "addr:postcode":"17110",
    "addr:street":"N 2Nd St",
    "iso:country":"US",
    "sg:address":"2625 N 2nd St",
    "sg:city":"Harrisburg",
    "sg:classifiers":[
        {
            "category":"Professional",
            "type":"Services"
        }
    ],
    "sg:phone":"+1   ",
    "sg:postcode":"17110",
    "sg:province":"PA",
    "wof:name":"Purplepicklecom",
    "wof:placetype":"venue"
},
  "geometry": {"coordinates":[-76.902787,40.287606],"type":"Point"}
}