{
  "type": "Feature",
  "properties": {
    "addr:full":"8244 W Chester Pike Upper Darby PA 19082",
    "addr:housenumber":"8244",
    "addr:postcode":"19082",
    "addr:street":"W Chester Pike",
    "iso:country":"US",
    "sg:address":"8244 W Chester Pike",
    "sg:city":"Upper Darby",
    "sg:classifiers":[
        {
            "category":"Building & Trades",
            "subcategory":"Plumbing",
            "type":"Services"
        }
    ],
    "sg:phone":"+1 610 789 8027",
    "sg:postcode":"19082",
    "sg:province":"PA",
    "sg:tags":[
        "heating",
        "contractor"
    ],
    "wof:name":"Snyder Co",
    "wof:placetype":"venue"
},
  "geometry": {"coordinates":[-75.280095,39.965632],"type":"Point"}
}