{
  "type": "Feature",
  "properties": {
    "iso:country":"US",
    "sg:address":"635 2nd Street Pike",
    "sg:city":"Southampton",
    "sg:classifiers":[
        {
            "category":"Shopping",
            "subcategory":"Florist",
            "type":"Retail Goods"
        }
    ],
    "sg:phone":"+1   ",
    "sg:postcode":"18966",
    "sg:province":"PA",
    "wof:name":"Hampton Flower Shop Inc",
    "wof:placetype":"venue"
},
  "geometry": {"coordinates":[-75.04404599999999,40.173393],"type":"Point"}
}