{
  "type": "Feature",
  "properties": {
    "iso:country":"US",
    "sg:address":"4016 Crooked Hill Rd",
    "sg:city":"Harrisburg",
    "sg:classifiers":[
        {
            "category":"Shopping",
            "subcategory":"Gifts & Souvenirs",
            "type":"Retail Goods"
        }
    ],
    "sg:phone":"+1 717 545 4140",
    "sg:postcode":"17110",
    "sg:province":"PA",
    "sg:tags":[
        "basket",
        "parcel"
    ],
    "wof:name":"Something Special Basket",
    "wof:placetype":"venue"
},
  "geometry": {"coordinates":[-76.87103999999999,40.318215],"type":"Point"}
}