{
  "type": "Feature",
  "properties": {
    "addr:full":"168 Barrington Rd Upper Darby PA 19082",
    "addr:housenumber":"168",
    "addr:postcode":"19082",
    "addr:street":"Barrington Rd",
    "iso:country":"US",
    "sg:address":"168 Barrington Rd",
    "sg:city":"Upper Darby",
    "sg:classifiers":[
        {
            "category":"Real Estate",
            "subcategory":"Real Estate Operator",
            "type":"Services"
        }
    ],
    "sg:phone":"+1 610 352 7163",
    "sg:postcode":"19082",
    "sg:province":"PA",
    "sg:tags":[
        "apartment"
    ],
    "wof:name":"Barrington Court Apartments",
    "wof:placetype":"venue"
},
  "geometry": {"coordinates":[-75.257082,39.95738],"type":"Point"}
}