{
  "type": "Feature",
  "properties": {
    "iso:country":"US",
    "sg:address":"8775 Norwin Ave",
    "sg:city":"North Huntingdon",
    "sg:classifiers":[
        {
            "category":"Banks & Credit Unions",
            "subcategory":"Bank",
            "type":"Services"
        }
    ],
    "sg:phone":"+1 724 861 8701",
    "sg:postcode":"15642",
    "sg:province":"PA",
    "wof:name":"Irwin Bank & Trust Co",
    "wof:placetype":"venue"
},
  "geometry": {"coordinates":[-79.691069,40.319667],"type":"Point"}
}