{
  "type": "Feature",
  "properties": {
    "addr:full":"724 Main St Stroudsburg PA 18360",
    "addr:housenumber":"724",
    "addr:postcode":"18360",
    "addr:street":"Main St",
    "iso:country":"US",
    "sg:address":"724 Main St",
    "sg:city":"Stroudsburg",
    "sg:classifiers":[
        {
            "category":"Shopping",
            "subcategory":"Photographic Equipment",
            "type":"Retail Goods"
        }
    ],
    "sg:phone":"+1 570 421 2830",
    "sg:postcode":"18360",
    "sg:province":"PA",
    "sg:tags":[
        "digital",
        "printing",
        "imaging",
        "supply"
    ],
    "sg:website":"http://www.stroudsburgfotopa.com",
    "wof:name":"Stroudsburg Foto Shop",
    "wof:placetype":"venue"
},
  "geometry": {"coordinates":[-75.19454399999999,40.985227],"type":"Point"}
}