{
  "type": "Feature",
  "properties": {
    "iso:country":"US",
    "sg:address":"970 US Hwy 522",
    "sg:city":"Selinsgrove",
    "sg:classifiers":[
        {
            "category":"Autos & Motor Vehicles",
            "subcategory":"Automobile Sales",
            "type":"Retail Goods"
        }
    ],
    "sg:phone":"+1   ",
    "sg:postcode":"17870",
    "sg:province":"PA",
    "sg:tags":[
        "used"
    ],
    "wof:name":"Stamms Repair Shop",
    "wof:placetype":"venue"
},
  "geometry": {"coordinates":[-76.89013799999999,40.805147],"type":"Point"}
}