{
  "type": "Feature",
  "properties": {
    "iso:country":"US",
    "sg:address":"725 Hamilton Rd",
    "sg:city":"Lancaster",
    "sg:classifiers":[
        {
            "category":"Education",
            "subcategory":"School",
            "type":"Public Place"
        }
    ],
    "sg:phone":"+1 717 392 2916",
    "sg:postcode":"17603",
    "sg:province":"PA",
    "sg:tags":[
        "elementary",
        "private",
        "secondary"
    ],
    "sg:website":"www.e-lcds.org",
    "wof:name":"Lancaster Country Day School",
    "wof:placetype":"venue"
},
  "geometry": {"coordinates":[-76.32883200000001,40.050281],"type":"Point"}
}