{
  "type": "Feature",
  "properties": {
    "iso:country":"US",
    "sg:address":"300 Liberty Ave",
    "sg:city":"Pittsburgh",
    "sg:classifiers":[
        {
            "category":"Restaurant",
            "type":"Food & Drink"
        }
    ],
    "sg:phone":"+1   ",
    "sg:postcode":"15222",
    "sg:province":"PA",
    "sg:tags":[
        "eating"
    ],
    "wof:name":"Brian Webers Snack Bar",
    "wof:placetype":"venue"
},
  "geometry": {"coordinates":[-80.005853,40.441354],"type":"Point"}
}