{
  "type": "Feature",
  "properties": {
    "iso:country":"US",
    "sg:address":"1511 Hollow Tree Dr",
    "sg:city":"Pittsburgh",
    "sg:classifiers":[
        {
            "category":"Health Services",
            "subcategory":"Doctor",
            "type":"Services"
        }
    ],
    "sg:phone":"+1 412 833 7820",
    "sg:postcode":"15241",
    "sg:province":"PA",
    "sg:tags":[
        "surgeon",
        "oral"
    ],
    "wof:name":"Haspel John R DDS",
    "wof:placetype":"venue"
},
  "geometry": {"coordinates":[-80.099701,40.312099],"type":"Point"}
}