{
  "type": "Feature",
  "properties": {
    "iso:country":"US",
    "sg:address":"1255 S Cedar Crest Blvd",
    "sg:city":"Allentown",
    "sg:classifiers":[
        {
            "category":"Health Services",
            "subcategory":"Doctor",
            "type":"Services"
        }
    ],
    "sg:phone":"+1   ",
    "sg:postcode":"18103",
    "sg:province":"PA",
    "sg:tags":[
        "medical"
    ],
    "wof:name":"Lehigh Valley Medical Assoc",
    "wof:placetype":"venue"
},
  "geometry": {"coordinates":[-75.518618,40.567336],"type":"Point"}
}