{
  "type": "Feature",
  "properties": {
    "iso:country":"US",
    "sg:address":"218 S Market St",
    "sg:city":"Elizabethtown",
    "sg:classifiers":[
        {
            "category":"Organizations",
            "subcategory":"Membership Organization",
            "type":"Services"
        }
    ],
    "sg:phone":"+1   ",
    "sg:postcode":"17022",
    "sg:province":"PA",
    "wof:name":"Meadowbrook Associates",
    "wof:placetype":"venue"
},
  "geometry": {"coordinates":[-76.60436300000001,40.148834],"type":"Point"}
}