{
  "type": "Feature",
  "properties": {
    "addr:full":"33 W 3rd St Williamsport PA 17701",
    "addr:housenumber":"33",
    "addr:postcode":"17701",
    "addr:street":"W 3Rd St",
    "iso:country":"US",
    "sg:address":"33 W 3rd St",
    "sg:city":"Williamsport",
    "sg:classifiers":[
        {
            "category":"Banks & Credit Unions",
            "subcategory":"Bank",
            "type":"Services"
        }
    ],
    "sg:phone":"+1 570 327 5069",
    "sg:postcode":"17701",
    "sg:province":"PA",
    "sg:website":"www.sovereignbank.com",
    "wof:name":"Sovereign Bank",
    "wof:placetype":"venue"
},
  "geometry": {"coordinates":[-77.002101,41.240512],"type":"Point"}
}