{
  "type": "Feature",
  "properties": {
    "addr:full":"73 S Mountain Blvd Mountain Top PA 18707",
    "addr:housenumber":"73",
    "addr:postcode":"18707",
    "addr:street":"S Mountain Blvd",
    "iso:country":"US",
    "sg:address":"73 S Mountain Blvd",
    "sg:city":"Mountain Top",
    "sg:classifiers":[
        {
            "category":"Shopping",
            "subcategory":"Florist",
            "type":"Retail Goods"
        }
    ],
    "sg:phone":"+1   ",
    "sg:postcode":"18707",
    "sg:province":"PA",
    "wof:name":"Kristens Floral & Gifts",
    "wof:placetype":"venue"
},
  "geometry": {"coordinates":[-75.886686,41.161362],"type":"Point"}
}