{
  "type": "Feature",
  "properties": {
    "addr:full":"8513 Frankford Ave Philadelphia PA 19136",
    "addr:housenumber":"8513",
    "addr:postcode":"19136",
    "addr:street":"Frankford Ave",
    "iso:country":"US",
    "sg:address":"8513 Frankford Ave",
    "sg:city":"Philadelphia",
    "sg:classifiers":[
        {
            "category":"Real Estate",
            "subcategory":"Real Estate Agent",
            "type":"Services"
        }
    ],
    "sg:phone":"+1 215 333 7000",
    "sg:postcode":"19136",
    "sg:province":"PA",
    "wof:name":"Foundation Real Estate Inc",
    "wof:placetype":"venue"
},
  "geometry": {"coordinates":[-75.016931,40.045257],"type":"Point"}
}