{
  "type": "Feature",
  "properties": {
    "iso:country":"US",
    "sg:address":"13 S Jackson St",
    "sg:city":"Strasburg",
    "sg:classifiers":[
        {
            "category":"Building & Trades",
            "subcategory":"Construction",
            "type":"Services"
        }
    ],
    "sg:phone":"+1   ",
    "sg:postcode":"17579",
    "sg:province":"PA",
    "sg:tags":[
        "house"
    ],
    "wof:name":"Clayton G Winters",
    "wof:placetype":"venue"
},
  "geometry": {"coordinates":[-76.18393,39.981678],"type":"Point"}
}