{
  "type": "Feature",
  "properties": {
    "iso:country":"US",
    "sg:address":"126 W Main St",
    "sg:city":"Grove City",
    "sg:classifiers":[
        {
            "category":"Restaurant",
            "type":"Food & Drink"
        }
    ],
    "sg:phone":"+1 724 458 4800",
    "sg:postcode":"16127",
    "sg:province":"PA",
    "sg:tags":[
        "pizza"
    ],
    "wof:name":"Four Star Pizza",
    "wof:placetype":"venue"
},
  "geometry": {"coordinates":[-80.088408,41.157607],"type":"Point"}
}