{
  "type": "Feature",
  "properties": {
    "iso:country":"US",
    "sg:address":"2287 Old Rte 220 N",
    "sg:city":"Duncansville",
    "sg:classifiers":[
        {
            "category":"Personal",
            "subcategory":"Massage",
            "type":"Services"
        }
    ],
    "sg:phone":"+1 814 934 9208",
    "sg:postcode":"16635",
    "sg:province":"PA",
    "wof:name":"Angel's Touch Massage Therapy",
    "wof:placetype":"venue"
},
  "geometry": {"coordinates":[-78.409265,40.448837],"type":"Point"}
}