{
  "type": "Feature",
  "properties": {
    "addr:full":"3 Pennsylvania Ave Malvern PA 19355",
    "addr:housenumber":"3",
    "addr:postcode":"19355",
    "addr:street":"Pennsylvania Ave",
    "iso:country":"US",
    "sg:address":"3 Pennsylvania Ave",
    "sg:city":"Malvern",
    "sg:classifiers":[
        {
            "category":"Manufacturing",
            "subcategory":"Printing",
            "type":"Manufacturing & Wholesale Goods"
        }
    ],
    "sg:phone":"+1   ",
    "sg:postcode":"19355",
    "sg:province":"PA",
    "sg:tags":[
        "print",
        "lithographic",
        "typesetting"
    ],
    "wof:name":"CMI",
    "wof:placetype":"venue"
},
  "geometry": {"coordinates":[-75.52163299999999,40.036594],"type":"Point"}
}