{
  "type": "Feature",
  "properties": {
    "iso:country":"US",
    "sg:address":"224 Pine St",
    "sg:city":"Harrisburg",
    "sg:classifiers":[
        {
            "category":"Professional",
            "subcategory":"Management & Consulting",
            "type":"Services"
        }
    ],
    "sg:phone":"+1 717 234 8814",
    "sg:postcode":"17101",
    "sg:province":"PA",
    "sg:tags":[
        "lobbyist"
    ],
    "wof:name":"F C Brown & Assoc",
    "wof:placetype":"venue"
},
  "geometry": {"coordinates":[-76.88396299999999,40.262921],"type":"Point"}
}