{
  "type": "Feature",
  "properties": {
    "iso:country":"US",
    "sg:address":"9102 Peebles Rd",
    "sg:city":"Allison Park",
    "sg:classifiers":[
        {
            "category":"Retail",
            "subcategory":"Portrait Studio",
            "type":"Services"
        }
    ],
    "sg:phone":"+1 412 364 0471",
    "sg:postcode":"15101",
    "sg:province":"PA",
    "sg:tags":[
        "photographer"
    ],
    "wof:name":"Captured Moment",
    "wof:placetype":"venue"
},
  "geometry": {"coordinates":[-80.00265400000001,40.570732],"type":"Point"}
}