{
  "type": "Feature",
  "properties": {
    "addr:full":"4970 Lancaster Ave Philadelphia PA 19131",
    "addr:housenumber":"4970",
    "addr:postcode":"19131",
    "addr:street":"Lancaster Ave",
    "iso:country":"US",
    "sg:address":"4970 Lancaster Ave",
    "sg:city":"Philadelphia",
    "sg:classifiers":[
        {
            "category":"Education",
            "subcategory":"Special Training",
            "type":"Public Place"
        },
        {
            "category":"Social Services",
            "subcategory":"Child Care",
            "type":"Services"
        },
        {
            "category":"Education",
            "subcategory":"Preschool",
            "type":"Public Place"
        }
    ],
    "sg:phone":"+1 215 878 8888",
    "sg:postcode":"19131",
    "sg:province":"PA",
    "sg:tags":[
        "kindergarten",
        "educational",
        "nursery",
        "day"
    ],
    "wof:name":"Kids Academy",
    "wof:placetype":"venue"
},
  "geometry": {"coordinates":[-75.221827,39.974923],"type":"Point"}
}