{
  "type": "Feature",
  "properties": {
    "iso:country":"US",
    "sg:address":"100 Exton Square Mall",
    "sg:city":"Exton",
    "sg:classifiers":[
        {
            "category":"Restaurant",
            "type":"Food & Drink"
        }
    ],
    "sg:phone":"+1 610 363 5051",
    "sg:postcode":"19341",
    "sg:province":"PA",
    "sg:tags":[
        "sandwich"
    ],
    "sg:website":"www.harryshotdogs.com",
    "wof:name":"Harry's Hotdogs Exton Inc",
    "wof:placetype":"venue"
},
  "geometry": {"coordinates":[-75.626518,40.03289],"type":"Point"}
}