{
  "type": "Feature",
  "properties": {
    "iso:country":"US",
    "sg:address":"21 James St",
    "sg:city":"Middletown",
    "sg:classifiers":[
        {
            "category":"Personal",
            "subcategory":"Barber",
            "type":"Services"
        }
    ],
    "sg:phone":"+1 717 944 7448",
    "sg:postcode":"17057",
    "sg:province":"PA",
    "wof:name":"Plaza Styling Salon",
    "wof:placetype":"venue"
},
  "geometry": {"coordinates":[-76.767653,40.215134],"type":"Point"}
}