{
  "type": "Feature",
  "properties": {
    "iso:country":"US",
    "sg:address":"925 Noble St",
    "sg:city":"Lebanon",
    "sg:classifiers":[
        {
            "category":"Real Estate",
            "subcategory":"Real Estate Services",
            "type":"Services"
        },
        {
            "category":"Real Estate",
            "subcategory":"Developer",
            "type":"Services"
        }
    ],
    "sg:phone":"+1 717 769 1745",
    "sg:postcode":"17042",
    "sg:province":"PA",
    "sg:tags":[
        "management"
    ],
    "sg:website":"http://www.weberpropertiespa.com",
    "wof:name":"Weber Properties",
    "wof:placetype":"venue"
},
  "geometry": {"coordinates":[-76.41324400000001,40.326943],"type":"Point"}
}