{
  "type": "Feature",
  "properties": {
    "addr:full":"858 Sussex Blvd Broomall PA 19008",
    "addr:housenumber":"858",
    "addr:postcode":"19008",
    "addr:street":"Sussex Blvd",
    "iso:country":"US",
    "sg:address":"858 Sussex Blvd",
    "sg:city":"Broomall",
    "sg:classifiers":[
        {
            "category":"Shopping",
            "type":"Retail Goods"
        }
    ],
    "sg:phone":"+1 610 544 9900",
    "sg:postcode":"19008",
    "sg:province":"PA",
    "sg:tags":[
        "religious"
    ],
    "sg:website":"www.terrasanctaguild.com",
    "wof:name":"Terra Sancta Guild",
    "wof:placetype":"venue"
},
  "geometry": {"coordinates":[-75.33606399999999,39.958417],"type":"Point"}
}