{
  "type": "Feature",
  "properties": {
    "iso:country":"US",
    "sg:address":"3404 Knights Rd",
    "sg:city":"Bensalem",
    "sg:classifiers":[
        {
            "category":"Health Services",
            "subcategory":"Health Practitioner",
            "type":"Services"
        }
    ],
    "sg:phone":"+1   ",
    "sg:postcode":"19020",
    "sg:province":"PA",
    "wof:name":"Mind & Body Theraphy",
    "wof:placetype":"venue"
},
  "geometry": {"coordinates":[-74.944614,40.111886],"type":"Point"}
}