{
  "type": "Feature",
  "properties": {
    "addr:full":"203 N. 34th Street Philadelphia PA 19104",
    "addr:housenumber":"203",
    "addr:postcode":"19104",
    "addr:street":"N. 34Th Street",
    "iso:country":"US",
    "sg:address":"203 N. 34th Street",
    "sg:city":"Philadelphia",
    "sg:classifiers":[
        {
            "category":"Fast Food",
            "type":"Food & Drink"
        }
    ],
    "sg:phone":"+1 215 495 5053",
    "sg:postcode":"19104",
    "sg:province":"PA",
    "sg:website":"www.chick-fil-a.com/",
    "wof:name":"Chick-Fil-A",
    "wof:placetype":"venue"
},
  "geometry": {"coordinates":[-75.190296,39.95915],"type":"Point"}
}