{
  "type": "Feature",
  "properties": {
    "iso:country":"US",
    "sg:address":"115 Pine Blvd",
    "sg:city":"Orwigsburg",
    "sg:classifiers":[
        {
            "category":"Retail",
            "subcategory":"Animal Services",
            "type":"Services"
        }
    ],
    "sg:phone":"+1 570 366 0368",
    "sg:postcode":"17961",
    "sg:province":"PA",
    "wof:name":"M & T Barks A Lot Grooming",
    "wof:placetype":"venue"
},
  "geometry": {"coordinates":[-76.052024,40.620459],"type":"Point"}
}