{
  "type": "Feature",
  "properties": {
    "addr:full":"2413 Charcot St Pittsburgh PA 15210",
    "addr:housenumber":"2413",
    "addr:postcode":"15210",
    "addr:street":"Charcot St",
    "iso:country":"US",
    "sg:address":"2413 Charcot St",
    "sg:city":"Pittsburgh",
    "sg:classifiers":[
        {
            "category":"Professional",
            "type":"Services"
        }
    ],
    "sg:phone":"+1   ",
    "sg:postcode":"15210",
    "sg:province":"PA",
    "wof:name":"Donna Wielock",
    "wof:placetype":"venue"
},
  "geometry": {"coordinates":[-79.97178700000001,40.41694],"type":"Point"}
}