{
  "type": "Feature",
  "properties": {
    "addr:full":"323 E New Castle St Zelienople PA 16063",
    "addr:housenumber":"323",
    "addr:postcode":"16063",
    "addr:street":"E New Castle St",
    "iso:country":"US",
    "sg:address":"323 E New Castle St",
    "sg:city":"Zelienople",
    "sg:classifiers":[
        {
            "category":"Organizations",
            "subcategory":"Religious Organization",
            "type":"Services"
        }
    ],
    "sg:phone":"+1 724 452 5864",
    "sg:postcode":"16063",
    "sg:province":"PA",
    "sg:tags":[
        "church"
    ],
    "wof:name":"Faith Full Gospel Church",
    "wof:placetype":"venue"
},
  "geometry": {"coordinates":[-80.132749,40.796185],"type":"Point"}
}