{
  "type": "Feature",
  "properties": {
    "iso:country":"US",
    "sg:address":"699 Sunset Dr",
    "sg:city":"Hanover",
    "sg:classifiers":[
        {
            "category":"Building & Trades",
            "subcategory":"Construction",
            "type":"Services"
        },
        {
            "category":"Building & Trades",
            "subcategory":"Electrical",
            "type":"Services"
        }
    ],
    "sg:phone":"+1 717 632 7750",
    "sg:postcode":"17331",
    "sg:province":"PA",
    "sg:tags":[
        "industrial",
        "electrician",
        "electric",
        "altering",
        "contractor",
        "contractors-commercial",
        "remodeling"
    ],
    "wof:name":"Sunset Electric & Remodeling",
    "wof:placetype":"venue"
},
  "geometry": {"coordinates":[-76.97831,39.75527],"type":"Point"}
}