{
  "type": "Feature",
  "properties": {
    "iso:country":"US",
    "sg:address":"1097 Wyoming Ave",
    "sg:city":"Kingston",
    "sg:classifiers":[
        {
            "category":"Autos & Motor Vehicles",
            "subcategory":"Fuel & Gas Station",
            "type":"Retail Goods"
        },
        {
            "category":"Autos & Motor Vehicles",
            "subcategory":"Auto Supplies",
            "type":"Retail Goods"
        },
        {
            "category":"Retail",
            "subcategory":"Auto Repair",
            "type":"Services"
        }
    ],
    "sg:phone":"+1 570 718 1501",
    "sg:postcode":"18704",
    "sg:province":"PA",
    "sg:tags":[
        "alternator",
        "oil",
        "automobile",
        "generators-automotive",
        "diagnostic",
        "lube",
        "inspection",
        "repairing"
    ],
    "sg:website":"http://fortyfortlube.com/",
    "wof:name":"Forty Fort Lube & Service Inc",
    "wof:placetype":"venue"
},
  "geometry": {"coordinates":[-75.877014,41.28085],"type":"Point"}
}