{
  "type": "Feature",
  "properties": {
    "addr:full":"900 S Arlington Ave Harrisburg PA 17109",
    "addr:housenumber":"900",
    "addr:postcode":"17109",
    "addr:street":"S Arlington Ave",
    "iso:country":"US",
    "sg:address":"900 S Arlington Ave",
    "sg:city":"Harrisburg",
    "sg:classifiers":[
        {
            "category":"Organizations",
            "subcategory":"Religious Organization",
            "type":"Services"
        }
    ],
    "sg:phone":"+1 717 652 3030",
    "sg:postcode":"17109",
    "sg:province":"PA",
    "sg:tags":[
        "church"
    ],
    "wof:name":"United Methodist Stewardship",
    "wof:placetype":"venue"
},
  "geometry": {"coordinates":[-76.819665,40.284703],"type":"Point"}
}