{
  "type": "Feature",
  "properties": {
    "addr:full":"19 Waln St Wellsboro PA 16901",
    "addr:housenumber":"19",
    "addr:postcode":"16901",
    "addr:street":"Waln St",
    "iso:country":"US",
    "sg:address":"19 Waln St",
    "sg:city":"Wellsboro",
    "sg:classifiers":[
        {
            "category":"Personal",
            "subcategory":"Beauty Salon",
            "type":"Services"
        }
    ],
    "sg:phone":"+1 570 723 4247",
    "sg:postcode":"16901",
    "sg:province":"PA",
    "wof:name":"Karen's",
    "wof:placetype":"venue"
},
  "geometry": {"coordinates":[-77.299947,41.748376],"type":"Point"}
}