{
  "type": "Feature",
  "properties": {
    "iso:country":"US",
    "sg:address":"5523 Carlisle Pike",
    "sg:city":"Mechanicsburg",
    "sg:classifiers":[
        {
            "category":"Retail",
            "subcategory":"Auto Rental",
            "type":"Services"
        }
    ],
    "sg:phone":"+1 717 795 8500",
    "sg:postcode":"17050",
    "sg:province":"PA",
    "sg:tags":[
        "car",
        "passenger"
    ],
    "sg:website":"enterprise.com",
    "wof:name":"Enterprise Rent-A-Car",
    "wof:placetype":"venue"
},
  "geometry": {"coordinates":[-76.985703,40.2407],"type":"Point"}
}