{
  "type": "Feature",
  "properties": {
    "addr:full":"275 Woodcock Ln Ambler PA 19002",
    "addr:housenumber":"275",
    "addr:postcode":"19002",
    "addr:street":"Woodcock Ln",
    "iso:country":"US",
    "sg:address":"275 Woodcock Ln",
    "sg:city":"Ambler",
    "sg:classifiers":[
        {
            "category":"Health Services",
            "subcategory":"Doctor",
            "type":"Services"
        }
    ],
    "sg:phone":"+1   ",
    "sg:postcode":"19002",
    "sg:province":"PA",
    "wof:name":"Robbin L Cramer DMD",
    "wof:placetype":"venue"
},
  "geometry": {"coordinates":[-75.22445500000001,40.142812],"type":"Point"}
}