{
  "type": "Feature",
  "properties": {
    "addr:full":"141 N 2nd St Philadelphia PA 19106",
    "addr:housenumber":"141",
    "addr:postcode":"19106",
    "addr:street":"N 2Nd St",
    "iso:country":"US",
    "sg:address":"141 N 2nd St",
    "sg:city":"Philadelphia",
    "sg:classifiers":[
        {
            "category":"Shopping",
            "subcategory":"Clothing, Apparel, & Fashions",
            "type":"Retail Goods"
        }
    ],
    "sg:phone":"+1 215 923 1700",
    "sg:postcode":"19106",
    "sg:province":"PA",
    "sg:tags":[
        "salvage",
        "surplus",
        "merchandise"
    ],
    "wof:name":"Atlantic City Surplus",
    "wof:placetype":"venue"
},
  "geometry": {"coordinates":[-75.142994,39.95297],"type":"Point"}
}