{
  "type": "Feature",
  "properties": {
    "iso:country":"US",
    "sg:address":"1214 S 17th St",
    "sg:city":"Philadelphia",
    "sg:classifiers":[
        {
            "category":"Organizations",
            "subcategory":"Religious Organization",
            "type":"Services"
        }
    ],
    "sg:phone":"+1 215 334 2021",
    "sg:postcode":"19146",
    "sg:province":"PA",
    "sg:tags":[
        "denomination",
        "churches-various",
        "church"
    ],
    "wof:name":"St Mary's Holiness Church",
    "wof:placetype":"venue"
},
  "geometry": {"coordinates":[-75.172127,39.936008],"type":"Point"}
}