{
  "type": "Feature",
  "properties": {
    "iso:country":"US",
    "sg:address":"232 E 9th Ave PO Box 348",
    "sg:city":"Conshohocken",
    "sg:classifiers":[
        {
            "category":"Insurance",
            "subcategory":"Hazard Insurance",
            "type":"Services"
        },
        {
            "category":"Insurance",
            "subcategory":"Insurance Agent",
            "type":"Services"
        },
        {
            "category":"Insurance",
            "subcategory":"Life Insurance",
            "type":"Services"
        },
        {
            "category":"Insurance",
            "subcategory":"Title Insurance",
            "type":"Services"
        }
    ],
    "sg:phone":"+1 610 832 5960",
    "sg:postcode":"19428",
    "sg:province":"PA",
    "sg:tags":[
        "auto",
        "homeowner"
    ],
    "sg:website":"http://www.nationwide.com/agent/Conshohocken-PENNSYLVANIA-insurance-agent/robert-g-supplee/office.html",
    "wof:name":"Supplee Ins Group Inc - Nationwide Insurance",
    "wof:placetype":"venue"
},
  "geometry": {"coordinates":[-75.296688,40.078776],"type":"Point"}
}