{
  "type": "Feature",
  "properties": {
    "iso:country":"US",
    "sg:address":"243 E 28th Division Hwy",
    "sg:city":"Lititz",
    "sg:classifiers":[
        {
            "category":"Place Of Worship",
            "subcategory":"Church",
            "type":"Public Place"
        },
        {
            "category":"Place Of Worship",
            "type":"Public Place"
        }
    ],
    "sg:phone":"+1 717 625 1155",
    "sg:postcode":"17543",
    "sg:province":"PA",
    "sg:tags":[
        "churches-interdenominational",
        "churches-various",
        "denomination"
    ],
    "wof:name":"Brickerville Grace Fellowship",
    "wof:placetype":"venue"
},
  "geometry": {"coordinates":[-76.29150799999999,40.22348],"type":"Point"}
}