{
  "type": "Feature",
  "properties": {
    "addr:full":"901 5th Ave New Kensington PA 15068",
    "addr:housenumber":"901",
    "addr:postcode":"15068",
    "addr:street":"5Th Ave",
    "iso:country":"US",
    "sg:address":"901 5th Ave",
    "sg:city":"New Kensington",
    "sg:classifiers":[
        {
            "category":"Government",
            "subcategory":"Office",
            "type":"Public Place"
        }
    ],
    "sg:phone":"+1 724 337 3525",
    "sg:postcode":"15068",
    "sg:province":"PA",
    "sg:tags":[
        "county",
        "planning",
        "dev"
    ],
    "wof:name":"Redevelopment Authority",
    "wof:placetype":"venue"
},
  "geometry": {"coordinates":[-79.76550899999999,40.56684],"type":"Point"}
}