{
  "type": "Feature",
  "properties": {
    "iso:country":"US",
    "sg:address":"210 Eisenhower Dr",
    "sg:city":"Orwigsburg",
    "sg:classifiers":[
        {
            "category":"Social Services",
            "subcategory":"Adult Care",
            "type":"Services"
        }
    ],
    "sg:phone":"+1   ",
    "sg:postcode":"17961",
    "sg:province":"PA",
    "sg:tags":[
        "residential"
    ],
    "wof:name":"Site Sam",
    "wof:placetype":"venue"
},
  "geometry": {"coordinates":[-76.106596,40.651281],"type":"Point"}
}