{
  "type": "Feature",
  "properties": {
    "iso:country":"US",
    "sg:address":"1505 Metropolitan St",
    "sg:city":"Pittsburgh",
    "sg:classifiers":[
        {
            "category":"Wholesale",
            "subcategory":"Groceries",
            "type":"Manufacturing & Wholesale Goods"
        },
        {
            "category":"Food & Beverages",
            "subcategory":"Supermarket",
            "type":"Retail Goods"
        }
    ],
    "sg:phone":"+1 412 321 7700",
    "sg:postcode":"15233",
    "sg:province":"PA",
    "sg:tags":[
        "frozen",
        "grocers-wholesale",
        "super",
        "store",
        "foods-wholesale"
    ],
    "wof:name":"Albert & Leff Foods Co-Div",
    "wof:placetype":"venue"
},
  "geometry": {"coordinates":[-80.030869,40.454097],"type":"Point"}
}