{
  "type": "Feature",
  "properties": {
    "addr:full":"701 Glenwood Ave Ambridge PA 15003",
    "addr:housenumber":"701",
    "addr:postcode":"15003",
    "addr:street":"Glenwood Ave",
    "iso:country":"US",
    "sg:address":"701 Glenwood Ave",
    "sg:city":"Ambridge",
    "sg:classifiers":[
        {
            "category":"Organizations",
            "subcategory":"Religious Organization",
            "type":"Services"
        }
    ],
    "sg:phone":"+1 724 266 2194",
    "sg:postcode":"15003",
    "sg:province":"PA",
    "sg:tags":[
        "church"
    ],
    "wof:name":"St Veronica Church",
    "wof:placetype":"venue"
},
  "geometry": {"coordinates":[-80.227182,40.589262],"type":"Point"}
}