{
  "type": "Feature",
  "properties": {
    "addr:full":"11711 Sharp Rd Waterford PA 16441",
    "addr:housenumber":"11711",
    "addr:postcode":"16441",
    "addr:street":"Sharp Rd",
    "iso:country":"US",
    "sg:address":"11711 Sharp Rd",
    "sg:city":"Waterford",
    "sg:classifiers":[
        {
            "category":"Retail",
            "subcategory":"Animal Services",
            "type":"Services"
        }
    ],
    "sg:phone":"+1 814 796 6312",
    "sg:postcode":"16441",
    "sg:province":"PA",
    "sg:tags":[
        "pet",
        "crematory",
        "cemetery"
    ],
    "wof:name":"Animal Friends Cremation Svcs",
    "wof:placetype":"venue"
},
  "geometry": {"coordinates":[-80.056138,41.940304],"type":"Point"}
}