{
  "type": "Feature",
  "properties": {
    "addr:full":"650 Barn St Hooversville PA 15936",
    "addr:housenumber":"650",
    "addr:postcode":"15936",
    "addr:street":"Barn St",
    "iso:country":"US",
    "sg:address":"650 Barn St",
    "sg:city":"Hooversville",
    "sg:classifiers":[
        {
            "category":"Retail",
            "subcategory":"Auto Repair",
            "type":"Services"
        }
    ],
    "sg:phone":"+1 814 798 4611",
    "sg:postcode":"15936",
    "sg:province":"PA",
    "sg:tags":[
        "repairing",
        "automobile"
    ],
    "wof:name":"Miller Service Ctr",
    "wof:placetype":"venue"
},
  "geometry": {"coordinates":[-78.91492100000001,40.153282],"type":"Point"}
}