{
  "type": "Feature",
  "properties": {
    "iso:country":"US",
    "sg:address":"801 Hill Ave",
    "sg:city":"Reading",
    "sg:classifiers":[
        {
            "category":"Food & Beverages",
            "subcategory":"Bakery",
            "type":"Retail Goods"
        }
    ],
    "sg:phone":"+1 610 375 8320",
    "sg:postcode":"19610",
    "sg:province":"PA",
    "sg:tags":[
        "baker"
    ],
    "wof:name":"Pepperidge Farm Inc",
    "wof:placetype":"venue"
},
  "geometry": {"coordinates":[-75.953576,40.337057],"type":"Point"}
}