{
  "type": "Feature",
  "properties": {
    "iso:country":"US",
    "sg:address":"9756 Broadway St",
    "sg:city":"North Huntingdon",
    "sg:classifiers":[
        {
            "category":"Wholesale",
            "subcategory":"Motor Vehicles",
            "type":"Manufacturing & Wholesale Goods"
        }
    ],
    "sg:phone":"+1 724 864 7005",
    "sg:postcode":"15642",
    "sg:province":"PA",
    "sg:tags":[
        "taxicab",
        "broker"
    ],
    "wof:name":"Manor Valley Taxi Co",
    "wof:placetype":"venue"
},
  "geometry": {"coordinates":[-79.694525,40.330797],"type":"Point"}
}