{
  "type": "Feature",
  "properties": {
    "iso:country":"US",
    "sg:address":"791 Enders Rd",
    "sg:city":"Halifax",
    "sg:classifiers":[
        {
            "category":"Education",
            "subcategory":"School",
            "type":"Public Place"
        }
    ],
    "sg:phone":"+1 717 362 9259",
    "sg:postcode":"17032",
    "sg:province":"PA",
    "wof:name":"Enders-Fisherville Elementary",
    "wof:placetype":"venue"
},
  "geometry": {"coordinates":[-76.852638,40.495439],"type":"Point"}
}