{
  "type": "Feature",
  "properties": {
    "iso:country":"US",
    "sg:address":"1178 Lebanon Rd",
    "sg:city":"Manheim",
    "sg:classifiers":[
        {
            "category":"Food & Beverages",
            "subcategory":"Specialty",
            "type":"Retail Goods"
        }
    ],
    "sg:phone":"+1   ",
    "sg:postcode":"17545",
    "sg:province":"PA",
    "wof:name":"Isaac Markets",
    "wof:placetype":"venue"
},
  "geometry": {"coordinates":[-76.414428,40.190709],"type":"Point"}
}