{
  "type": "Feature",
  "properties": {
    "addr:full":"142 Chess St New Eagle PA 15067",
    "addr:housenumber":"142",
    "addr:postcode":"15067",
    "addr:street":"Chess St",
    "iso:country":"US",
    "sg:address":"142 Chess St",
    "sg:city":"New Eagle",
    "sg:classifiers":[
        {
            "category":"Retail",
            "subcategory":"Auto Repair",
            "type":"Services"
        }
    ],
    "sg:phone":"+1 724 292 1001",
    "sg:postcode":"15067",
    "sg:province":"PA",
    "sg:tags":[
        "repairing",
        "automobile"
    ],
    "wof:name":"Ricks Auto Body",
    "wof:placetype":"venue"
},
  "geometry": {"coordinates":[-79.944829,40.207163],"type":"Point"}
}