{
  "type": "Feature",
  "properties": {
    "addr:full":"34 W Church St Fairchance PA 15436",
    "addr:housenumber":"34",
    "addr:postcode":"15436",
    "addr:street":"W Church St",
    "iso:country":"US",
    "sg:address":"34 W Church St",
    "sg:city":"Fairchance",
    "sg:classifiers":[
        {
            "category":"Recreation",
            "type":"Entertainment"
        }
    ],
    "sg:phone":"+1   ",
    "sg:postcode":"15436",
    "sg:province":"PA",
    "sg:tags":[
        "club",
        "membership"
    ],
    "wof:name":"E & F Club Inc",
    "wof:placetype":"venue"
},
  "geometry": {"coordinates":[-79.75332299999999,39.820187],"type":"Point"}
}