{
  "type": "Feature",
  "properties": {
    "iso:country":"US",
    "sg:address":"160 N Washington St",
    "sg:city":"Wilkes Barre",
    "sg:classifiers":[
        {
            "category":"Food & Beverages",
            "subcategory":"Groceries & Convenience Stores",
            "type":"Retail Goods"
        }
    ],
    "sg:phone":"+1   ",
    "sg:postcode":"18701",
    "sg:province":"PA",
    "wof:name":"Knellys Jack Quality Market",
    "wof:placetype":"venue"
},
  "geometry": {"coordinates":[-75.874562,41.248202],"type":"Point"}
}