{
  "type": "Feature",
  "properties": {
    "addr:full":"318 Parklawn Ct Lancaster PA 17601",
    "addr:housenumber":"318",
    "addr:postcode":"17601",
    "addr:street":"Parklawn Ct",
    "iso:country":"US",
    "sg:address":"318 Parklawn Ct",
    "sg:city":"Lancaster",
    "sg:classifiers":[
        {
            "category":"Autos & Motor Vehicles",
            "subcategory":"Automobile Sales",
            "type":"Retail Goods"
        }
    ],
    "sg:phone":"+1   ",
    "sg:postcode":"17601",
    "sg:province":"PA",
    "wof:name":"First Fives BMW",
    "wof:placetype":"venue"
},
  "geometry": {"coordinates":[-76.35663,40.055785],"type":"Point"}
}