{
  "type": "Feature",
  "properties": {
    "addr:full":"963 Franklin Ln Ambler PA 19002",
    "addr:housenumber":"963",
    "addr:postcode":"19002",
    "addr:street":"Franklin Ln",
    "iso:country":"US",
    "sg:address":"963 Franklin Ln",
    "sg:city":"Ambler",
    "sg:classifiers":[
        {
            "category":"Building & Trades",
            "subcategory":"Construction",
            "type":"Services"
        }
    ],
    "sg:phone":"+1   ",
    "sg:postcode":"19002",
    "sg:province":"PA",
    "sg:tags":[
        "specializing",
        "c",
        "addition",
        "contractor",
        "to",
        "renovation"
    ],
    "wof:name":"Paul J Brigidi Inc",
    "wof:placetype":"venue"
},
  "geometry": {"coordinates":[-75.174514,40.17176],"type":"Point"}
}