{
  "type": "Feature",
  "properties": {
    "addr:full":"224 S Logan Blvd Burnham PA 17009",
    "addr:housenumber":"224",
    "addr:postcode":"17009",
    "addr:street":"S Logan Blvd",
    "iso:country":"US",
    "sg:address":"224 S Logan Blvd",
    "sg:city":"Burnham",
    "sg:classifiers":[
        {
            "category":"Shopping",
            "subcategory":"Used Merchandise",
            "type":"Retail Goods"
        }
    ],
    "sg:phone":"+1   ",
    "sg:postcode":"17009",
    "sg:province":"PA",
    "wof:name":"Schultzs Kids Clubhouse",
    "wof:placetype":"venue"
},
  "geometry": {"coordinates":[-77.566458,40.628234],"type":"Point"}
}