{
  "type": "Feature",
  "properties": {
    "iso:country":"US",
    "sg:address":"541 Main St",
    "sg:city":"Honesdale",
    "sg:classifiers":[
        {
            "category":"Food & Beverages",
            "subcategory":"Liquor & Beverages",
            "type":"Retail Goods"
        }
    ],
    "sg:phone":"+1 570 253 7370",
    "sg:postcode":"18431",
    "sg:province":"PA",
    "wof:name":"State Liquor Stores",
    "wof:placetype":"venue"
},
  "geometry": {"coordinates":[-75.254435,41.570068],"type":"Point"}
}