{
  "type": "Feature",
  "properties": {
    "iso:country":"US",
    "sg:address":"162 Walker Rd",
    "sg:city":"Apollo",
    "sg:classifiers":[
        {
            "category":"Museum",
            "type":"Entertainment"
        }
    ],
    "sg:phone":"+1   ",
    "sg:postcode":"15613",
    "sg:province":"PA",
    "sg:tags":[
        "gallery"
    ],
    "wof:name":"Purple Sage Art",
    "wof:placetype":"venue"
},
  "geometry": {"coordinates":[-79.594679,40.509311],"type":"Point"}
}