{
  "type": "Feature",
  "properties": {
    "addr:full":"5718 Lincoln Ave Export PA 15632",
    "addr:housenumber":"5718",
    "addr:postcode":"15632",
    "addr:street":"Lincoln Ave",
    "iso:country":"US",
    "sg:address":"5718 Lincoln Ave",
    "sg:city":"Export",
    "sg:classifiers":[
        {
            "category":"Freight",
            "type":"Transportation"
        }
    ],
    "sg:phone":"+1   ",
    "sg:postcode":"15632",
    "sg:province":"PA",
    "sg:tags":[
        "courier"
    ],
    "wof:name":"Dolans Courier",
    "wof:placetype":"venue"
},
  "geometry": {"coordinates":[-79.628124,40.417707],"type":"Point"}
}