{
  "type": "Feature",
  "properties": {
    "addr:full":"120 Putnam St Pittsburgh PA 15206",
    "addr:housenumber":"120",
    "addr:postcode":"15206",
    "addr:street":"Putnam St",
    "iso:country":"US",
    "sg:address":"120 Putnam St",
    "sg:city":"Pittsburgh",
    "sg:classifiers":[
        {
            "category":"Wholesale",
            "subcategory":"Machinery & Supplies",
            "type":"Manufacturing & Wholesale Goods"
        }
    ],
    "sg:phone":"+1 412 362 6612",
    "sg:postcode":"15206",
    "sg:province":"PA",
    "sg:tags":[
        "bearing"
    ],
    "wof:name":"Bearing Distributors Inc",
    "wof:placetype":"venue"
},
  "geometry": {"coordinates":[-79.912599,40.459471],"type":"Point"}
}