{
  "type": "Feature",
  "properties": {
    "iso:country":"US",
    "sg:address":"1 Pastuszek Ct",
    "sg:city":"Marcus Hook",
    "sg:classifiers":[
        {
            "category":"Shopping",
            "subcategory":"Computers & Home Electronics",
            "type":"Retail Goods"
        }
    ],
    "sg:phone":"+1   ",
    "sg:postcode":"19081",
    "sg:province":"PA",
    "wof:name":"Auto Custumz",
    "wof:placetype":"venue"
},
  "geometry": {"coordinates":[-75.349412,39.902083],"type":"Point"}
}