{
  "type": "Feature",
  "properties": {
    "iso:country":"US",
    "sg:address":"607 W Broad St",
    "sg:city":"Williamstown",
    "sg:classifiers":[
        {
            "category":"Personal",
            "subcategory":"Massage",
            "type":"Services"
        }
    ],
    "sg:phone":"+1 717 418 4305",
    "sg:postcode":"17098",
    "sg:province":"PA",
    "wof:name":"Mccready S Massage",
    "wof:placetype":"venue"
},
  "geometry": {"coordinates":[-76.62758599999999,40.582142],"type":"Point"}
}