{
  "type": "Feature",
  "properties": {
    "addr:full":"1501 Unity St Philadelphia PA 19124",
    "addr:housenumber":"1501",
    "addr:postcode":"19124",
    "addr:street":"Unity St",
    "iso:country":"US",
    "sg:address":"1501 Unity St",
    "sg:city":"Philadelphia",
    "sg:classifiers":[
        {
            "category":"Shopping",
            "subcategory":"Department Store",
            "type":"Retail Goods"
        },
        {
            "category":"Shopping",
            "subcategory":"Discount & Variety Stores",
            "type":"Retail Goods"
        }
    ],
    "sg:phone":"+1 215 744 4707",
    "sg:postcode":"19124",
    "sg:province":"PA",
    "sg:tags":[
        "shop"
    ],
    "sg:website":"www.valu-plus.net",
    "wof:name":"Valu-Plus Inc",
    "wof:placetype":"venue"
},
  "geometry": {"coordinates":[-75.089203,40.01342],"type":"Point"}
}