{
  "type": "Feature",
  "properties": {
    "iso:country":"US",
    "sg:address":"5860 Saltsburg Rd",
    "sg:city":"Verona",
    "sg:classifiers":[
        {
            "category":"Building & Trades",
            "subcategory":"Landscaping Services",
            "type":"Services"
        }
    ],
    "sg:phone":"+1   ",
    "sg:postcode":"15147",
    "sg:province":"PA",
    "sg:tags":[
        "lawn",
        "garden"
    ],
    "wof:name":"Penn Landscape & Cement Works",
    "wof:placetype":"venue"
},
  "geometry": {"coordinates":[-79.82534,40.482421],"type":"Point"}
}