{
  "type": "Feature",
  "properties": {
    "addr:full":"1 Rices Mill Rd Wyncote PA 19095",
    "addr:housenumber":"1",
    "addr:postcode":"19095",
    "addr:street":"Rices Mill Rd",
    "iso:country":"US",
    "sg:address":"1 Rices Mill Rd",
    "sg:city":"Wyncote",
    "sg:classifiers":[
        {
            "category":"Shopping",
            "subcategory":"Stationery & Office Supplies",
            "type":"Retail Goods"
        },
        {
            "category":"Shopping",
            "subcategory":"Party Supplies",
            "type":"Retail Goods"
        },
        {
            "category":"Manufacturing",
            "subcategory":"Paper Products",
            "type":"Manufacturing & Wholesale Goods"
        }
    ],
    "sg:phone":"+1 215 884 5791",
    "sg:postcode":"19095",
    "sg:province":"PA",
    "sg:tags":[
        "announcement",
        "container",
        "favors",
        "utensil",
        "plastic",
        "delivery",
        "balloons-retail",
        "invitation",
        "cups",
        "store"
    ],
    "sg:website":"http://sgspaperco.com",
    "wof:name":"S G S Paper Company",
    "wof:placetype":"venue"
},
  "geometry": {"coordinates":[-75.14614899999999,40.097801],"type":"Point"}
}