{
  "type": "Feature",
  "properties": {
    "addr:full":"331 W Shamokin St Trevorton PA 17881",
    "addr:housenumber":"331",
    "addr:postcode":"17881",
    "addr:street":"W Shamokin St",
    "iso:country":"US",
    "sg:address":"331 W Shamokin St",
    "sg:city":"Trevorton",
    "sg:classifiers":[
        {
            "category":"Organizations",
            "subcategory":"Religious Organization",
            "type":"Services"
        }
    ],
    "sg:phone":"+1   ",
    "sg:postcode":"17881",
    "sg:province":"PA",
    "wof:name":"Saint Patricks Church",
    "wof:placetype":"venue"
},
  "geometry": {"coordinates":[-76.670686,40.781421],"type":"Point"}
}