{
  "type": "Feature",
  "properties": {
    "iso:country":"US",
    "sg:address":"789 Washington Pike",
    "sg:city":"Avella",
    "sg:classifiers":[
        {
            "category":"Wholesale",
            "subcategory":"Groceries",
            "type":"Manufacturing & Wholesale Goods"
        }
    ],
    "sg:phone":"+1   ",
    "sg:postcode":"15312",
    "sg:province":"PA",
    "sg:tags":[
        "food"
    ],
    "wof:name":"Delta Trading Group Inc",
    "wof:placetype":"venue"
},
  "geometry": {"coordinates":[-80.45022899999999,40.248492],"type":"Point"}
}