{
  "type": "Feature",
  "properties": {
    "iso:country":"US",
    "sg:address":"1805 Babcock Blvd",
    "sg:city":"Pittsburgh",
    "sg:classifiers":[
        {
            "category":"Bars & Pubs",
            "type":"Food & Drink"
        }
    ],
    "sg:menulink":"http://www.allmenus.com/pa/shaler/286411-flame-barbeque/menu/",
    "sg:phone":"+1 412 821 0202",
    "sg:postcode":"15209",
    "sg:province":"PA",
    "sg:tags":[
        "barbecue",
        "american"
    ],
    "wof:name":"Flame Barbeque",
    "wof:placetype":"venue"
},
  "geometry": {"coordinates":[-79.983413,40.501569],"type":"Point"}
}