{
  "type": "Feature",
  "properties": {
    "iso:country":"US",
    "sg:address":"221 S Aiken Ave",
    "sg:city":"Pittsburgh",
    "sg:classifiers":[
        {
            "category":"Organizations",
            "subcategory":"Professional Association",
            "type":"Services"
        }
    ],
    "sg:phone":"+1 412 362 4334",
    "sg:postcode":"15206",
    "sg:province":"PA",
    "sg:website":"www.dignitypgh.org",
    "wof:name":"Dignity Pittsburgh",
    "wof:placetype":"venue"
},
  "geometry": {"coordinates":[-79.937495,40.46217],"type":"Point"}
}