{
  "type": "Feature",
  "properties": {
    "addr:full":"196 Reade St Blandburg PA 16619",
    "addr:housenumber":"196",
    "addr:postcode":"16619",
    "addr:street":"Reade St",
    "iso:country":"US",
    "sg:address":"196 Reade St",
    "sg:city":"Blandburg",
    "sg:classifiers":[
        {
            "category":"Building & Trades",
            "subcategory":"Plumbing",
            "type":"Services"
        }
    ],
    "sg:phone":"+1   ",
    "sg:postcode":"16619",
    "sg:province":"PA",
    "sg:tags":[
        "contractor"
    ],
    "wof:name":"Pier Heating & Cooling Inc",
    "wof:placetype":"venue"
},
  "geometry": {"coordinates":[-78.414528,40.683955],"type":"Point"}
}