{
  "type": "Feature",
  "properties": {
    "iso:country":"US",
    "sg:address":"2643 Huntingdon Pike",
    "sg:city":"Huntingdon Valley",
    "sg:classifiers":[
        {
            "category":"Health Services",
            "subcategory":"Doctor",
            "type":"Services"
        }
    ],
    "sg:phone":"+1   ",
    "sg:postcode":"19006",
    "sg:province":"PA",
    "sg:tags":[
        "medical"
    ],
    "wof:name":"Michael Nussbaum MD",
    "wof:placetype":"venue"
},
  "geometry": {"coordinates":[-75.062659,40.125469],"type":"Point"}
}