{
  "type": "Feature",
  "properties": {
    "iso:country":"US",
    "sg:address":"201 S Camac St",
    "sg:city":"Philadelphia",
    "sg:classifiers":[
        {
            "category":"Professional",
            "subcategory":"Detective & Security Services",
            "type":"Services"
        }
    ],
    "sg:phone":"+1 215 732 8255",
    "sg:postcode":"19107",
    "sg:province":"PA",
    "sg:tags":[
        "information",
        "bureau"
    ],
    "wof:name":"Gay Service",
    "wof:placetype":"venue"
},
  "geometry": {"coordinates":[-75.161484,39.948219],"type":"Point"}
}