{
  "type": "Feature",
  "properties": {
    "iso:country":"US",
    "sg:address":"9500 Brooktree Rd",
    "sg:city":"Wexford",
    "sg:classifiers":[
        {
            "category":"Social Services",
            "subcategory":"Child Care",
            "type":"Services"
        }
    ],
    "sg:phone":"+1 724 934 9266",
    "sg:postcode":"15090",
    "sg:province":"PA",
    "sg:tags":[
        "day"
    ],
    "wof:name":"Distance Learning Network",
    "wof:placetype":"venue"
},
  "geometry": {"coordinates":[-80.05514100000001,40.614255],"type":"Point"}
}