{
  "type": "Feature",
  "properties": {
    "addr:full":"350 E Jefferson St Butler PA 16001",
    "addr:housenumber":"350",
    "addr:postcode":"16001",
    "addr:street":"E Jefferson St",
    "iso:country":"US",
    "sg:address":"350 E Jefferson St",
    "sg:city":"Butler",
    "sg:classifiers":[
        {
            "category":"Health Services",
            "subcategory":"Medical Lab",
            "type":"Services"
        }
    ],
    "sg:phone":"+1   ",
    "sg:postcode":"16001",
    "sg:province":"PA",
    "sg:tags":[
        "laboratory",
        "dental"
    ],
    "wof:name":"Superior Ceramics Inc",
    "wof:placetype":"venue"
},
  "geometry": {"coordinates":[-79.890619,40.861045],"type":"Point"}
}