{
  "type": "Feature",
  "properties": {
    "iso:country":"US",
    "sg:address":"1222 Eagle Point Dr",
    "sg:city":"Canonsburg",
    "sg:classifiers":[
        {
            "category":"Professional",
            "type":"Services"
        }
    ],
    "sg:phone":"+1   ",
    "sg:postcode":"15317",
    "sg:province":"PA",
    "wof:name":"Brian T Scales Dr",
    "wof:placetype":"venue"
},
  "geometry": {"coordinates":[-80.170919,40.288483],"type":"Point"}
}