{
  "type": "Feature",
  "properties": {
    "iso:country":"US",
    "sg:address":"206 W Elm Ave",
    "sg:city":"Langhorne",
    "sg:classifiers":[
        {
            "category":"Building & Trades",
            "subcategory":"Construction",
            "type":"Services"
        }
    ],
    "sg:phone":"+1 215 752 7531",
    "sg:postcode":"19047",
    "sg:province":"PA",
    "sg:tags":[
        "contractor",
        "painting",
        "hanging"
    ],
    "wof:name":"Rjb Painting",
    "wof:placetype":"venue"
},
  "geometry": {"coordinates":[-74.915558,40.161671],"type":"Point"}
}