{
  "type": "Feature",
  "properties": {
    "iso:country":"US",
    "sg:address":"2034 S 13th St",
    "sg:city":"Philadelphia",
    "sg:classifiers":[
        {
            "category":"Building & Trades",
            "subcategory":"Construction",
            "type":"Services"
        }
    ],
    "sg:phone":"+1 215 243 9660",
    "sg:postcode":"19148",
    "sg:province":"PA",
    "sg:tags":[
        "contractor"
    ],
    "sg:website":"www.jpcgroupinc.com",
    "wof:name":"Jpc Group Inc",
    "wof:placetype":"venue"
},
  "geometry": {"coordinates":[-75.167683,39.924566],"type":"Point"}
}