{
  "type": "Feature",
  "properties": {
    "addr:full":"1313 Wyoming Ave Exeter PA 18643",
    "addr:housenumber":"1313",
    "addr:postcode":"18643",
    "addr:street":"Wyoming Ave",
    "iso:country":"US",
    "sg:address":"1313 Wyoming Ave",
    "sg:city":"Exeter",
    "sg:classifiers":[
        {
            "category":"Restaurant",
            "type":"Food & Drink"
        }
    ],
    "sg:phone":"+1 570 883 9588",
    "sg:postcode":"18643",
    "sg:province":"PA",
    "sg:tags":[
        "delicatessen"
    ],
    "wof:name":"Pony Boy Subs",
    "wof:placetype":"venue"
},
  "geometry": {"coordinates":[-75.82586999999999,41.316988],"type":"Point"}
}