{
  "type": "Feature",
  "properties": {
    "addr:full":"301 Sunrise Dr Georgetown PA 15043",
    "addr:housenumber":"301",
    "addr:postcode":"15043",
    "addr:street":"Sunrise Dr",
    "iso:country":"US",
    "sg:address":"301 Sunrise Dr",
    "sg:city":"Georgetown",
    "sg:classifiers":[
        {
            "category":"Freight",
            "type":"Transportation"
        }
    ],
    "sg:phone":"+1   ",
    "sg:postcode":"15043",
    "sg:province":"PA",
    "sg:tags":[
        "fright",
        "arrangement"
    ],
    "wof:name":"D & C Truck Escort",
    "wof:placetype":"venue"
},
  "geometry": {"coordinates":[-80.490174,40.559471],"type":"Point"}
}