{
  "type": "Feature",
  "properties": {
    "addr:full":"1426 Fitzwater St Philadelphia PA 19146",
    "addr:housenumber":"1426",
    "addr:postcode":"19146",
    "addr:street":"Fitzwater St",
    "iso:country":"US",
    "sg:address":"1426 Fitzwater St",
    "sg:city":"Philadelphia",
    "sg:classifiers":[
        {
            "category":"Retail",
            "subcategory":"Funeral Services",
            "type":"Services"
        }
    ],
    "sg:phone":"+1 215 545 3055",
    "sg:postcode":"19146",
    "sg:province":"PA",
    "sg:tags":[
        "director"
    ],
    "wof:name":"Slater Funeral Home",
    "wof:placetype":"venue"
},
  "geometry": {"coordinates":[-75.167474,39.941926],"type":"Point"}
}