{
  "type": "Feature",
  "properties": {
    "iso:country":"US",
    "sg:address":"5160 Main St",
    "sg:city":"Whitehall",
    "sg:classifiers":[
        {
            "category":"Manufacturing",
            "subcategory":"Chemicals & Compounds",
            "type":"Manufacturing & Wholesale Goods"
        }
    ],
    "sg:phone":"+1   ",
    "sg:postcode":"18052",
    "sg:province":"PA",
    "sg:tags":[
        "industrial",
        "organic",
        "mfg"
    ],
    "wof:name":"Systech",
    "wof:placetype":"venue"
},
  "geometry": {"coordinates":[-75.50696499999999,40.689434],"type":"Point"}
}