{
  "type": "Feature",
  "properties": {
    "addr:full":"101 W Lippincott St Philadelphia PA 19133",
    "addr:housenumber":"101",
    "addr:postcode":"19133",
    "addr:street":"W Lippincott St",
    "iso:country":"US",
    "sg:address":"101 W Lippincott St",
    "sg:city":"Philadelphia",
    "sg:classifiers":[
        {
            "category":"Freight",
            "type":"Transportation"
        }
    ],
    "sg:phone":"+1 215 634 1030",
    "sg:postcode":"19133",
    "sg:province":"PA",
    "wof:name":"Liberty Transportation",
    "wof:placetype":"venue"
},
  "geometry": {"coordinates":[-75.13000099999999,39.997688],"type":"Point"}
}