{
  "type": "Feature",
  "properties": {
    "addr:full":"820 Alene Rd Ambler PA 19002",
    "addr:housenumber":"820",
    "addr:postcode":"19002",
    "addr:street":"Alene Rd",
    "iso:country":"US",
    "sg:address":"820 Alene Rd",
    "sg:city":"Ambler",
    "sg:classifiers":[
        {
            "category":"Professional",
            "subcategory":"Computer Services",
            "type":"Services"
        }
    ],
    "sg:phone":"+1   ",
    "sg:postcode":"19002",
    "sg:province":"PA",
    "sg:tags":[
        "information",
        "retrieval",
        "consultancy"
    ],
    "wof:name":"Lifecycle Software Inc",
    "wof:placetype":"venue"
},
  "geometry": {"coordinates":[-75.216294,40.172411],"type":"Point"}
}