{
  "type": "Feature",
  "properties": {
    "iso:country":"US",
    "sg:address":"304 Ross St",
    "sg:city":"Pittsburgh",
    "sg:classifiers":[
        {
            "category":"Restaurant",
            "type":"Food & Drink"
        }
    ],
    "sg:menulink":"http://www.allmenus.com/pa/pittsburgh/5949-mitchells/menu/",
    "sg:phone":"+1 412 471 3663",
    "sg:postcode":"15219",
    "sg:province":"PA",
    "sg:tags":[
        "burger",
        "cheesesteaks",
        "sandwich",
        "american"
    ],
    "wof:name":"Mitchell's",
    "wof:placetype":"venue"
},
  "geometry": {"coordinates":[-79.996782,40.4371],"type":"Point"}
}