{
  "type": "Feature",
  "properties": {
    "iso:country":"US",
    "sg:address":"2141 White St",
    "sg:city":"York",
    "sg:classifiers":[
        {
            "category":"Shopping",
            "subcategory":"Shoes",
            "type":"Retail Goods"
        }
    ],
    "sg:phone":"+1   ",
    "sg:postcode":"17404",
    "sg:province":"PA",
    "wof:name":"Mary J Whitfield",
    "wof:placetype":"venue"
},
  "geometry": {"coordinates":[-76.770731,39.962985],"type":"Point"}
}