{
  "type": "Feature",
  "properties": {
    "addr:full":"3470 Ernest Ln Collegeville PA 19426",
    "addr:housenumber":"3470",
    "addr:postcode":"19426",
    "addr:street":"Ernest Ln",
    "iso:country":"US",
    "sg:address":"3470 Ernest Ln",
    "sg:city":"Collegeville",
    "sg:classifiers":[
        {
            "category":"Health Services",
            "subcategory":"Doctor",
            "type":"Services"
        }
    ],
    "sg:phone":"+1 610 584 6909",
    "sg:postcode":"19426",
    "sg:province":"PA",
    "wof:name":"Lipka Robert Dr",
    "wof:placetype":"venue"
},
  "geometry": {"coordinates":[-75.372426,40.211535],"type":"Point"}
}