{
  "type": "Feature",
  "properties": {
    "iso:country":"US",
    "sg:address":"710 Main St",
    "sg:city":"Towanda",
    "sg:classifiers":[
        {
            "category":"Shopping",
            "type":"Retail Goods"
        }
    ],
    "sg:phone":"+1 570 265 6238",
    "sg:postcode":"18848",
    "sg:province":"PA",
    "sg:tags":[
        "cards",
        "sport",
        "baseball",
        "memorabilia"
    ],
    "wof:name":"Joe's Sports Cards",
    "wof:placetype":"venue"
},
  "geometry": {"coordinates":[-76.443133,41.762835],"type":"Point"}
}