{
  "type": "Feature",
  "properties": {
    "addr:full":"531 Broad St Sewickley PA 15143",
    "addr:housenumber":"531",
    "addr:postcode":"15143",
    "addr:street":"Broad St",
    "iso:country":"US",
    "sg:address":"531 Broad St",
    "sg:city":"Sewickley",
    "sg:classifiers":[
        {
            "category":"Banks & Credit Unions",
            "subcategory":"Bank",
            "type":"Services"
        }
    ],
    "sg:phone":"+1 412 741 5000",
    "sg:postcode":"15143",
    "sg:province":"PA",
    "sg:tags":[
        "savings"
    ],
    "wof:name":"Sewickley Savings Bank",
    "wof:placetype":"venue"
},
  "geometry": {"coordinates":[-80.179382,40.540967],"type":"Point"}
}