{
  "type": "Feature",
  "properties": {
    "iso:country":"US",
    "sg:address":"227 Stewart Rd",
    "sg:city":"Hanover Twp",
    "sg:classifiers":[
        {
            "category":"Wholesale",
            "subcategory":"Medical Equipment & Supplies",
            "type":"Manufacturing & Wholesale Goods"
        }
    ],
    "sg:phone":"+1 570 829 4020",
    "sg:postcode":"18706",
    "sg:province":"PA",
    "sg:tags":[
        "physician",
        "surgeon"
    ],
    "wof:name":"CPO2 Inc",
    "wof:placetype":"venue"
},
  "geometry": {"coordinates":[-75.92209200000001,41.214682],"type":"Point"}
}