{
  "type": "Feature",
  "properties": {
    "iso:country":"US",
    "sg:address":"2202 Whistler Rd",
    "sg:city":"Hooversville",
    "sg:classifiers":[
        {
            "category":"Autos & Motor Vehicles",
            "subcategory":"Automobile Sales",
            "type":"Retail Goods"
        }
    ],
    "sg:phone":"+1 814 798 3001",
    "sg:postcode":"15936",
    "sg:province":"PA",
    "sg:tags":[
        "car",
        "dealer"
    ],
    "wof:name":"Tirko Auto Sales",
    "wof:placetype":"venue"
},
  "geometry": {"coordinates":[-78.91815200000001,40.143216],"type":"Point"}
}