{
  "type": "Feature",
  "properties": {
    "iso:country":"US",
    "sg:address":"104 Centerville Rd",
    "sg:city":"Lancaster",
    "sg:classifiers":[
        {
            "category":"Building & Trades",
            "subcategory":"Construction",
            "type":"Services"
        }
    ],
    "sg:phone":"+1 717 290 8106",
    "sg:postcode":"17601",
    "sg:province":"PA",
    "sg:tags":[
        "resurfacing",
        "laying",
        "refinishing",
        "floor"
    ],
    "wof:name":"Richard's Floor Covering Inc",
    "wof:placetype":"venue"
},
  "geometry": {"coordinates":[-76.39228300000001,40.046034],"type":"Point"}
}