{
  "type": "Feature",
  "properties": {
    "iso:country":"US",
    "sg:address":"189 N Wales Rd",
    "sg:city":"North Wales",
    "sg:classifiers":[
        {
            "category":"Shopping",
            "subcategory":"Clothing, Apparel, & Fashions",
            "type":"Retail Goods"
        }
    ],
    "sg:phone":"+1   ",
    "sg:postcode":"19454",
    "sg:province":"PA",
    "wof:name":"Limited The",
    "wof:placetype":"venue"
},
  "geometry": {"coordinates":[-75.25967300000001,40.231119],"type":"Point"}
}