{
  "type": "Feature",
  "properties": {
    "iso:country":"US",
    "sg:address":"304 Ross St",
    "sg:city":"Pittsburgh",
    "sg:classifiers":[
        {
            "category":"Restaurant",
            "type":"Food & Drink"
        }
    ],
    "sg:phone":"+1   ",
    "sg:postcode":"15219",
    "sg:province":"PA",
    "sg:tags":[
        "personal",
        "drinking",
        "eating"
    ],
    "wof:name":"Mitchlls Rest Bar Banquet Cent",
    "wof:placetype":"venue"
},
  "geometry": {"coordinates":[-79.996403,40.437528],"type":"Point"}
}