{
  "type": "Feature",
  "properties": {
    "addr:full":"293 S River St Plains PA 18705",
    "addr:housenumber":"293",
    "addr:postcode":"18705",
    "addr:street":"S River St",
    "iso:country":"US",
    "sg:address":"293 S River St",
    "sg:city":"Plains",
    "sg:classifiers":[
        {
            "category":"Retail",
            "subcategory":"Funeral Services",
            "type":"Services"
        }
    ],
    "sg:phone":"+1 570 822 8602",
    "sg:postcode":"18705",
    "sg:province":"PA",
    "sg:tags":[
        "director",
        "home"
    ],
    "wof:name":"Mikelski Michael J Funeral HM",
    "wof:placetype":"venue"
},
  "geometry": {"coordinates":[-75.863767,41.266987],"type":"Point"}
}