{
  "type": "Feature",
  "properties": {
    "addr:full":"10 N Meadows Dr Wexford PA 15090",
    "addr:housenumber":"10",
    "addr:postcode":"15090",
    "addr:street":"N Meadows Dr",
    "iso:country":"US",
    "sg:address":"10 N Meadows Dr",
    "sg:city":"Wexford",
    "sg:classifiers":[
        {
            "category":"Personal",
            "subcategory":"Beauty Salon",
            "type":"Services"
        }
    ],
    "sg:phone":"+1 724 776 3338",
    "sg:postcode":"15090",
    "sg:province":"PA",
    "sg:tags":[
        "manicuring"
    ],
    "wof:name":"Pedicure Junction Tips",
    "wof:placetype":"venue"
},
  "geometry": {"coordinates":[-80.054672,40.611156],"type":"Point"}
}