{
  "type": "Feature",
  "properties": {
    "iso:country":"US",
    "sg:address":"1515 Locust St",
    "sg:city":"Pittsburgh",
    "sg:classifiers":[
        {
            "category":"Health Services",
            "subcategory":"Doctor",
            "type":"Services"
        }
    ],
    "sg:phone":"+1 412 232 3900",
    "sg:postcode":"15219",
    "sg:province":"PA",
    "wof:name":"Mercy Behavioral Health Part of the Pittsburgh Mercy Hea",
    "wof:placetype":"venue"
},
  "geometry": {"coordinates":[-79.985087,40.436979],"type":"Point"}
}