{
  "type": "Feature",
  "properties": {
    "addr:full":"4309 Buffalo Rd Erie PA 16510",
    "addr:housenumber":"4309",
    "addr:postcode":"16510",
    "addr:street":"Buffalo Rd",
    "iso:country":"US",
    "sg:address":"4309 Buffalo Rd",
    "sg:city":"Erie",
    "sg:classifiers":[
        {
            "category":"Wholesale",
            "subcategory":"Medical Equipment & Supplies",
            "type":"Manufacturing & Wholesale Goods"
        },
        {
            "category":"Shopping",
            "subcategory":"Pharmacy",
            "type":"Retail Goods"
        }
    ],
    "sg:phone":"+1 814 897 7871",
    "sg:postcode":"16510",
    "sg:province":"PA",
    "sg:tags":[
        "home",
        "care",
        "health",
        "first",
        "aid"
    ],
    "sg:website":"http://www.walgreens.com",
    "wof:name":"Walgreen Drug Stores",
    "wof:placetype":"venue"
},
  "geometry": {"coordinates":[-80.004475,42.145476],"type":"Point"}
}