{
  "type": "Feature",
  "properties": {
    "iso:country":"US",
    "sg:address":"38 Cricket Ave",
    "sg:city":"Ardmore",
    "sg:classifiers":[
        {
            "category":"Shopping",
            "subcategory":"Clothing, Apparel, & Fashions",
            "type":"Retail Goods"
        }
    ],
    "sg:phone":"+1 610 642 1714",
    "sg:postcode":"19003",
    "sg:province":"PA",
    "sg:tags":[
        "tailor"
    ],
    "wof:name":"Salvadole",
    "wof:placetype":"venue"
},
  "geometry": {"coordinates":[-75.290998,40.007795],"type":"Point"}
}