{
  "type": "Feature",
  "properties": {
    "iso:country":"US",
    "sg:address":"75 S Maiden St",
    "sg:city":"Waynesburg",
    "sg:classifiers":[
        {
            "category":"Personal",
            "subcategory":"Beauty Salon",
            "type":"Services"
        },
        {
            "category":"Personal",
            "subcategory":"Tanning Parlor",
            "type":"Services"
        }
    ],
    "sg:phone":"+1 724 627 6447",
    "sg:postcode":"15370",
    "sg:province":"PA",
    "wof:name":"Eye Candy Salon",
    "wof:placetype":"venue"
},
  "geometry": {"coordinates":[-80.1776,39.895658],"type":"Point"}
}