{
  "type": "Feature",
  "properties": {
    "addr:full":"1608 Brownsville Rd Feasterville Trevose PA 19053",
    "addr:housenumber":"1608",
    "addr:postcode":"19053",
    "addr:street":"Brownsville Rd",
    "iso:country":"US",
    "sg:address":"1608 Brownsville Rd",
    "sg:city":"Feasterville Trevose",
    "sg:classifiers":[
        {
            "category":"Building & Trades",
            "subcategory":"Pest Control",
            "type":"Services"
        }
    ],
    "sg:phone":"+1   ",
    "sg:postcode":"19053",
    "sg:province":"PA",
    "wof:name":"Lethal Exterminating",
    "wof:placetype":"venue"
},
  "geometry": {"coordinates":[-74.97717400000001,40.149347],"type":"Point"}
}