{
  "type": "Feature",
  "properties": {
    "addr:full":"410 W Main St Ste B Lansdale PA 19446",
    "addr:housenumber":"410",
    "addr:postcode":"19446",
    "addr:street":"W Main St Ste B",
    "iso:country":"US",
    "sg:address":"410 W Main St Ste B",
    "sg:city":"Lansdale",
    "sg:classifiers":[
        {
            "category":"Professional",
            "subcategory":"Accounting & Tax Preparation",
            "type":"Services"
        }
    ],
    "sg:phone":"+1 215 362 9101",
    "sg:postcode":"19446",
    "sg:province":"PA",
    "sg:tags":[
        "accountant"
    ],
    "wof:name":"Kessler Lawrence D CPA",
    "wof:placetype":"venue"
},
  "geometry": {"coordinates":[-75.28766899999999,40.243905],"type":"Point"}
}