{
  "type": "Feature",
  "properties": {
    "iso:country":"US",
    "sg:address":"13 Jenich Dr",
    "sg:city":"Reinholds",
    "sg:classifiers":[
        {
            "category":"Building & Trades",
            "subcategory":"Construction",
            "type":"Services"
        }
    ],
    "sg:phone":"+1 717 336 8229",
    "sg:postcode":"17569",
    "sg:province":"PA",
    "sg:tags":[
        "hanging",
        "contractor"
    ],
    "wof:name":"Brushed Elegance",
    "wof:placetype":"venue"
},
  "geometry": {"coordinates":[-76.112172,40.258543],"type":"Point"}
}