{
  "type": "Feature",
  "properties": {
    "iso:country":"US",
    "sg:address":"380 Sentry Pkwy",
    "sg:city":"Blue Bell",
    "sg:classifiers":[
        {
            "category":"Insurance",
            "subcategory":"Insurance Agent",
            "type":"Services"
        }
    ],
    "sg:phone":"+1 610 397 5000",
    "sg:postcode":"19422",
    "sg:province":"PA",
    "sg:website":"www.pmagroup.com",
    "wof:name":"Pma Insurance Group",
    "wof:placetype":"venue"
},
  "geometry": {"coordinates":[-75.27071100000001,40.133045],"type":"Point"}
}