{
  "type": "Feature",
  "properties": {
    "iso:country":"US",
    "sg:address":"30 W Franklin St",
    "sg:city":"Topton",
    "sg:classifiers":[
        {
            "category":"Banks & Credit Unions",
            "subcategory":"Bank",
            "type":"Services"
        }
    ],
    "sg:phone":"+1 610 682 2107",
    "sg:postcode":"19562",
    "sg:province":"PA",
    "sg:tags":[
        "savings",
        "loan",
        "association"
    ],
    "wof:name":"National Penn Bank Inc",
    "wof:placetype":"venue"
},
  "geometry": {"coordinates":[-75.701837,40.503174],"type":"Point"}
}