{
  "type": "Feature",
  "properties": {
    "iso:country":"US",
    "sg:address":"443 Lycoming Mall Cir",
    "sg:city":"Muncy",
    "sg:classifiers":[
        {
            "category":"Shopping",
            "subcategory":"Photographic Equipment",
            "type":"Retail Goods"
        }
    ],
    "sg:phone":"+1 570 546 7595",
    "sg:postcode":"17756",
    "sg:province":"PA",
    "sg:tags":[
        "supply"
    ],
    "wof:name":"Ritz Camera Ctr",
    "wof:placetype":"venue"
},
  "geometry": {"coordinates":[-76.823166,41.239573],"type":"Point"}
}