{
  "type": "Feature",
  "properties": {
    "iso:country":"US",
    "sg:address":"619 E Girard Ave",
    "sg:city":"Philadelphia",
    "sg:classifiers":[
        {
            "category":"Insurance",
            "subcategory":"Insurance Agent",
            "type":"Services"
        }
    ],
    "sg:phone":"+1 215 425 7640",
    "sg:postcode":"19125",
    "sg:province":"PA",
    "sg:tags":[
        "auto"
    ],
    "sg:website":"http://www.fabeyagency.com?utm_source=yp&utm_medium=cpc&utm_campaign=ck_yp",
    "wof:name":"FABEY INSURANCE AGENCY",
    "wof:placetype":"venue"
},
  "geometry": {"coordinates":[-75.126563,39.971543],"type":"Point"}
}