{
  "type": "Feature",
  "properties": {
    "addr:full":"1116 Hadley Dr Sharon PA 16146",
    "addr:housenumber":"1116",
    "addr:postcode":"16146",
    "addr:street":"Hadley Dr",
    "iso:country":"US",
    "sg:address":"1116 Hadley Dr",
    "sg:city":"Sharon",
    "sg:classifiers":[
        {
            "category":"Building & Trades",
            "subcategory":"Landscaping Services",
            "type":"Services"
        }
    ],
    "sg:phone":"+1 724 983 1392",
    "sg:postcode":"16146",
    "sg:province":"PA",
    "sg:tags":[
        "landscape",
        "contractor"
    ],
    "wof:name":"Del Fratte's Landscaping Inc",
    "wof:placetype":"venue"
},
  "geometry": {"coordinates":[-80.495801,41.248391],"type":"Point"}
}