{
  "type": "Feature",
  "properties": {
    "iso:country":"US",
    "sg:address":"34 Gay Way",
    "sg:city":"Chester",
    "sg:classifiers":[
        {
            "category":"Government",
            "subcategory":"Office",
            "type":"Public Place"
        }
    ],
    "sg:phone":"+1   ",
    "sg:postcode":"19034",
    "sg:province":"PA",
    "sg:tags":[
        "executive"
    ],
    "wof:name":"Human Resources Dept",
    "wof:placetype":"venue"
},
  "geometry": {"coordinates":[-75.19378500000001,40.127688],"type":"Point"}
}