{
  "type": "Feature",
  "properties": {
    "iso:country":"US",
    "sg:address":"4775 Wallingford St",
    "sg:city":"Pittsburgh",
    "sg:classifiers":[
        {
            "category":"Banks & Credit Unions",
            "subcategory":"Investment Brokerage",
            "type":"Services"
        },
        {
            "category":"Mining & Drilling",
            "type":"Manufacturing & Wholesale Goods"
        }
    ],
    "sg:phone":"+1 412 621 6600",
    "sg:postcode":"15213",
    "sg:province":"PA",
    "sg:tags":[
        "gas",
        "security",
        "well"
    ],
    "wof:name":"Thomas M Nixon & Associates",
    "wof:placetype":"venue"
},
  "geometry": {"coordinates":[-79.948007,40.451806],"type":"Point"}
}