{
  "type": "Feature",
  "properties": {
    "iso:country":"US",
    "sg:address":"4917 N 5th St",
    "sg:city":"Philadelphia",
    "sg:classifiers":[
        {
            "category":"Shopping",
            "subcategory":"Jewelry",
            "type":"Retail Goods"
        }
    ],
    "sg:phone":"+1   ",
    "sg:postcode":"19120",
    "sg:province":"PA",
    "wof:name":"Oteris Gold Ltd",
    "wof:placetype":"venue"
},
  "geometry": {"coordinates":[-75.13247699999999,40.027018],"type":"Point"}
}