{
  "type": "Feature",
  "properties": {
    "addr:full":"75 Dale Rd Barto PA 19504",
    "addr:housenumber":"75",
    "addr:postcode":"19504",
    "addr:street":"Dale Rd",
    "iso:country":"US",
    "sg:address":"75 Dale Rd",
    "sg:city":"Barto",
    "sg:classifiers":[
        {
            "category":"Manufacturing",
            "subcategory":"Metals",
            "type":"Manufacturing & Wholesale Goods"
        }
    ],
    "sg:phone":"+1 610 845 2340",
    "sg:postcode":"19504",
    "sg:province":"PA",
    "sg:tags":[
        "coating",
        "powder"
    ],
    "wof:name":"Majestic Auto Paint & Body Shp",
    "wof:placetype":"venue"
},
  "geometry": {"coordinates":[-75.621712,40.438385],"type":"Point"}
}