{
  "type": "Feature",
  "properties": {
    "iso:country":"US",
    "sg:address":"381 Park City Ctr",
    "sg:city":"Lancaster",
    "sg:classifiers":[
        {
            "category":"Shopping",
            "subcategory":"Clothing, Apparel, & Fashions",
            "type":"Retail Goods"
        },
        {
            "category":"Shopping",
            "subcategory":"Baby Store",
            "type":"Retail Goods"
        }
    ],
    "sg:phone":"+1 717 397 7175",
    "sg:postcode":"17601",
    "sg:province":"PA",
    "sg:tags":[
        "infant",
        "children's",
        "wear",
        "girls'",
        "clothing",
        "boys'"
    ],
    "sg:website":"http://www.gymboree.com",
    "wof:name":"Gymboree",
    "wof:placetype":"venue"
},
  "geometry": {"coordinates":[-76.340276,40.06567],"type":"Point"}
}