{
  "type": "Feature",
  "properties": {
    "iso:country":"US",
    "sg:address":"2005 W 8th St",
    "sg:city":"Erie",
    "sg:classifiers":[
        {
            "category":"Insurance",
            "subcategory":"Insurance Agent",
            "type":"Services"
        }
    ],
    "sg:phone":"+1   ",
    "sg:postcode":"16505",
    "sg:province":"PA",
    "wof:name":"Nicklas Insurance Agency",
    "wof:placetype":"venue"
},
  "geometry": {"coordinates":[-80.12810899999999,42.11112],"type":"Point"}
}