{
  "type": "Feature",
  "properties": {
    "iso:country":"US",
    "sg:address":"809 S Main St",
    "sg:city":"Roaring Spring",
    "sg:classifiers":[
        {
            "category":"Shopping",
            "subcategory":"Discount & Variety Stores",
            "type":"Retail Goods"
        }
    ],
    "sg:phone":"+1   ",
    "sg:postcode":"16673",
    "sg:province":"PA",
    "wof:name":"M&W Variety Store",
    "wof:placetype":"venue"
},
  "geometry": {"coordinates":[-78.40049399999999,40.330948],"type":"Point"}
}