{
  "type": "Feature",
  "properties": {
    "addr:full":"1585 Wind Hill Rd Coopersburg PA 18036",
    "addr:housenumber":"1585",
    "addr:postcode":"18036",
    "addr:street":"Wind Hill Rd",
    "iso:country":"US",
    "sg:address":"1585 Wind Hill Rd",
    "sg:city":"Coopersburg",
    "sg:classifiers":[
        {
            "category":"Wholesale",
            "subcategory":"Computers",
            "type":"Manufacturing & Wholesale Goods"
        }
    ],
    "sg:phone":"+1 610 965 1990",
    "sg:postcode":"18036",
    "sg:province":"PA",
    "sg:website":"www.garnetsecure.com",
    "wof:name":"Garnet Secure Systems",
    "wof:placetype":"venue"
},
  "geometry": {"coordinates":[-75.434472,40.487461],"type":"Point"}
}