{
  "type": "Feature",
  "properties": {
    "addr:full":"360 Marsh Rd Elverson PA 19520",
    "addr:housenumber":"360",
    "addr:postcode":"19520",
    "addr:street":"Marsh Rd",
    "iso:country":"US",
    "sg:address":"360 Marsh Rd",
    "sg:city":"Elverson",
    "sg:classifiers":[
        {
            "category":"Manufacturing",
            "subcategory":"Printing",
            "type":"Manufacturing & Wholesale Goods"
        }
    ],
    "sg:phone":"+1   ",
    "sg:postcode":"19520",
    "sg:province":"PA",
    "sg:tags":[
        "lithographic",
        "commercial"
    ],
    "wof:name":"Wolverton Graphics",
    "wof:placetype":"venue"
},
  "geometry": {"coordinates":[-75.780879,40.136323],"type":"Point"}
}