{
  "type": "Feature",
  "properties": {
    "iso:country":"US",
    "sg:address":"322 Torrence Ave",
    "sg:city":"Carnegie",
    "sg:classifiers":[
        {
            "category":"Building & Trades",
            "subcategory":"Electrical",
            "type":"Services"
        }
    ],
    "sg:phone":"+1   ",
    "sg:postcode":"15106",
    "sg:province":"PA",
    "sg:tags":[
        "electrical",
        "contractor"
    ],
    "wof:name":"FM Electric Co",
    "wof:placetype":"venue"
},
  "geometry": {"coordinates":[-80.09167600000001,40.397173],"type":"Point"}
}