{
  "type": "Feature",
  "properties": {
    "addr:full":"15 S Market St Duncannon PA 17020",
    "addr:housenumber":"15",
    "addr:postcode":"17020",
    "addr:street":"S Market St",
    "iso:country":"US",
    "sg:address":"15 S Market St",
    "sg:city":"Duncannon",
    "sg:classifiers":[
        {
            "category":"Sports & Exercise",
            "subcategory":"Gym",
            "type":"Entertainment"
        }
    ],
    "sg:phone":"+1 717 834 6650",
    "sg:postcode":"17020",
    "sg:province":"PA",
    "sg:tags":[
        "fitness",
        "physical",
        "facility"
    ],
    "wof:name":"Curves For Women",
    "wof:placetype":"venue"
},
  "geometry": {"coordinates":[-77.030649,40.389537],"type":"Point"}
}