{
  "type": "Feature",
  "properties": {
    "iso:country":"US",
    "sg:address":"1601 Walnut St Ste 1109",
    "sg:city":"Philadelphia",
    "sg:classifiers":[
        {
            "category":"Health Services",
            "subcategory":"Doctor",
            "type":"Services"
        }
    ],
    "sg:phone":"+1 215 496 0530",
    "sg:postcode":"19102",
    "sg:province":"PA",
    "sg:tags":[
        "physician",
        "surgeon",
        "psychiatrist"
    ],
    "sg:website":"www.davidrburns.yourmd.com",
    "wof:name":"Burns David Russell MD",
    "wof:placetype":"venue"
},
  "geometry": {"coordinates":[-75.167603,39.9496],"type":"Point"}
}