{
  "type": "Feature",
  "properties": {
    "iso:country":"US",
    "sg:address":"822 S Aiken Ave",
    "sg:city":"Pittsburgh",
    "sg:classifiers":[
        {
            "category":"Personal",
            "subcategory":"Tanning Parlor",
            "type":"Services"
        }
    ],
    "sg:phone":"+1 412 621 8266",
    "sg:postcode":"15232",
    "sg:province":"PA",
    "sg:tags":[
        "salon"
    ],
    "wof:name":"Tan 360",
    "wof:placetype":"venue"
},
  "geometry": {"coordinates":[-79.935456,40.450574],"type":"Point"}
}