{
  "type": "Feature",
  "properties": {
    "addr:full":"317 N Market St Mechanicsburg PA 17055",
    "addr:housenumber":"317",
    "addr:postcode":"17055",
    "addr:street":"N Market St",
    "iso:country":"US",
    "sg:address":"317 N Market St",
    "sg:city":"Mechanicsburg",
    "sg:classifiers":[
        {
            "category":"Utilities",
            "subcategory":"Water",
            "type":"Services"
        }
    ],
    "sg:phone":"+1 717 766 4131",
    "sg:postcode":"17055",
    "sg:province":"PA",
    "sg:tags":[
        "company-utility",
        "system",
        "supply"
    ],
    "wof:name":"United Wtr Mchncsburg Oprtions",
    "wof:placetype":"venue"
},
  "geometry": {"coordinates":[-77.009528,40.216276],"type":"Point"}
}