{
  "type": "Feature",
  "properties": {
    "iso:country":"US",
    "sg:address":"532 Rte 66",
    "sg:city":"Apollo",
    "sg:classifiers":[
        {
            "category":"Professional",
            "subcategory":"Engineering",
            "type":"Services"
        }
    ],
    "sg:phone":"+1   ",
    "sg:postcode":"15613",
    "sg:province":"PA",
    "wof:name":"Prep Tech Inc",
    "wof:placetype":"venue"
},
  "geometry": {"coordinates":[-79.591026,40.543494],"type":"Point"}
}