{
  "type": "Feature",
  "properties": {
    "iso:country":"US",
    "sg:address":"135 S 20th Street",
    "sg:city":"Philadelphia",
    "sg:classifiers":[
        {
            "category":"Real Estate",
            "subcategory":"Real Estate Operator",
            "type":"Services"
        }
    ],
    "sg:phone":"+1 215 925 7368",
    "sg:postcode":"19103",
    "sg:province":"PA",
    "sg:tags":[
        "apartment"
    ],
    "sg:website":"www.michaelsingerrealestate.com/",
    "wof:name":"The Chatham",
    "wof:placetype":"venue"
},
  "geometry": {"coordinates":[-75.173653,39.951213],"type":"Point"}
}