{
  "type": "Feature",
  "properties": {
    "addr:full":"993 Greentree Rd Pittsburgh PA 15220",
    "addr:housenumber":"993",
    "addr:postcode":"15220",
    "addr:street":"Greentree Rd",
    "iso:country":"US",
    "sg:address":"993 Greentree Rd",
    "sg:city":"Pittsburgh",
    "sg:classifiers":[
        {
            "category":"Professional",
            "subcategory":"Management & Consulting",
            "type":"Services"
        }
    ],
    "sg:phone":"+1 412 920 1664",
    "sg:postcode":"15220",
    "sg:province":"PA",
    "sg:tags":[
        "consultant",
        "business"
    ],
    "wof:name":"WHS Industries Inc",
    "wof:placetype":"venue"
},
  "geometry": {"coordinates":[-80.044956,40.416936],"type":"Point"}
}