{
  "type": "Feature",
  "properties": {
    "iso:country":"US",
    "sg:address":"43 Washington St",
    "sg:city":"East Stroudsburg",
    "sg:classifiers":[
        {
            "category":"Shopping",
            "subcategory":"Clothing, Apparel, & Fashions",
            "type":"Retail Goods"
        }
    ],
    "sg:phone":"+1   ",
    "sg:postcode":"18301",
    "sg:province":"PA",
    "wof:name":"Rags Off The Rack",
    "wof:placetype":"venue"
},
  "geometry": {"coordinates":[-75.182692,40.996934],"type":"Point"}
}