{
  "type": "Feature",
  "properties": {
    "iso:country":"US",
    "sg:address":"10115 Verree Rd Apt 6A",
    "sg:city":"Philadelphia",
    "sg:classifiers":[
        {
            "category":"Personal",
            "subcategory":"Massage",
            "type":"Services"
        },
        {
            "category":"Health Services",
            "subcategory":"Clinic",
            "type":"Services"
        },
        {
            "category":"Health Services",
            "subcategory":"Health Practitioner",
            "type":"Services"
        }
    ],
    "sg:phone":"+1 215 673 1484",
    "sg:postcode":"19116",
    "sg:province":"PA",
    "sg:tags":[
        "therapist",
        "therapy",
        "physical"
    ],
    "wof:name":"Asparas",
    "wof:placetype":"venue"
},
  "geometry": {"coordinates":[-75.03065100000001,40.106241],"type":"Point"}
}