{
  "type": "Feature",
  "properties": {
    "iso:country":"US",
    "sg:address":"371 Plaza Blvd",
    "sg:city":"Morrisville",
    "sg:classifiers":[
        {
            "category":"Real Estate",
            "subcategory":"Real Estate Operator",
            "type":"Services"
        }
    ],
    "sg:phone":"+1   ",
    "sg:postcode":"19067",
    "sg:province":"PA",
    "sg:tags":[
        "building",
        "apartment"
    ],
    "wof:name":"Americana Apts",
    "wof:placetype":"venue"
},
  "geometry": {"coordinates":[-74.798726,40.204044],"type":"Point"}
}