{
  "type": "Feature",
  "properties": {
    "iso:country":"US",
    "sg:address":"8093 Covered Bridge Rd",
    "sg:city":"Quakertown",
    "sg:classifiers":[
        {
            "category":"Building & Trades",
            "subcategory":"Construction",
            "type":"Services"
        }
    ],
    "sg:phone":"+1 215 538 0124",
    "sg:postcode":"18951",
    "sg:province":"PA",
    "sg:tags":[
        "hanging",
        "contractor"
    ],
    "wof:name":"Thomas Aufiero",
    "wof:placetype":"venue"
},
  "geometry": {"coordinates":[-75.277951,40.45333],"type":"Point"}
}