{
  "type": "Feature",
  "properties": {
    "addr:full":"2951 Pricetown Rd Temple PA 19560",
    "addr:housenumber":"2951",
    "addr:postcode":"19560",
    "addr:street":"Pricetown Rd",
    "iso:country":"US",
    "sg:address":"2951 Pricetown Rd",
    "sg:city":"Temple",
    "sg:classifiers":[
        {
            "category":"Manufacturing",
            "subcategory":"Buildings",
            "type":"Manufacturing & Wholesale Goods"
        }
    ],
    "sg:phone":"+1 610 921 2544",
    "sg:postcode":"19560",
    "sg:province":"PA",
    "sg:tags":[
        "home",
        "log",
        "cabin"
    ],
    "wof:name":"Baum Construction Timber Frame",
    "wof:placetype":"venue"
},
  "geometry": {"coordinates":[-75.888599,40.387789],"type":"Point"}
}