{
  "type": "Feature",
  "properties": {
    "addr:full":"821 Juniata Ave Huntingdon PA 16652",
    "addr:housenumber":"821",
    "addr:postcode":"16652",
    "addr:street":"Juniata Ave",
    "iso:country":"US",
    "sg:address":"821 Juniata Ave",
    "sg:city":"Huntingdon",
    "sg:classifiers":[
        {
            "category":"Manufacturing",
            "subcategory":"Metals",
            "type":"Manufacturing & Wholesale Goods"
        }
    ],
    "sg:phone":"+1 814 643 0451",
    "sg:postcode":"16652",
    "sg:province":"PA",
    "sg:tags":[
        "fabricated",
        "structural"
    ],
    "wof:name":"N E Reihart & Sons",
    "wof:placetype":"venue"
},
  "geometry": {"coordinates":[-78.02554600000001,40.486742],"type":"Point"}
}