{
  "type": "Feature",
  "properties": {
    "iso:country":"US",
    "sg:address":"2927 W Thompson St",
    "sg:city":"Philadelphia",
    "sg:classifiers":[
        {
            "category":"Manufacturing",
            "subcategory":"Printing",
            "type":"Manufacturing & Wholesale Goods"
        }
    ],
    "sg:phone":"+1 215 235 1119",
    "sg:postcode":"19121",
    "sg:province":"PA",
    "sg:tags":[
        "printer"
    ],
    "sg:website":"www.screengemsinc.com",
    "wof:name":"Andrew H Lawson Co",
    "wof:placetype":"venue"
},
  "geometry": {"coordinates":[-75.183689,39.976388],"type":"Point"}
}