{
  "type": "Feature",
  "properties": {
    "iso:country":"US",
    "sg:address":"1012 McKean Ave",
    "sg:city":"Charleroi",
    "sg:classifiers":[
        {
            "category":"Personal",
            "subcategory":"Beauty Salon",
            "type":"Services"
        },
        {
            "category":"Personal",
            "subcategory":"Barber",
            "type":"Services"
        }
    ],
    "sg:phone":"+1 724 483 4835",
    "sg:postcode":"15022",
    "sg:province":"PA",
    "sg:tags":[
        "shop"
    ],
    "wof:name":"Vicki's Men's Styling Salon",
    "wof:placetype":"venue"
},
  "geometry": {"coordinates":[-79.904151,40.144442],"type":"Point"}
}