{
  "type": "Feature",
  "properties": {
    "iso:country":"US",
    "sg:address":"455 Mt Joy Rd",
    "sg:city":"Mt Joy",
    "sg:classifiers":[
        {
            "category":"Manufacturing",
            "subcategory":"Food",
            "type":"Manufacturing & Wholesale Goods"
        }
    ],
    "sg:phone":"+1 717 653 8326",
    "sg:postcode":"17552",
    "sg:province":"PA",
    "sg:tags":[
        "product",
        "manufacturer"
    ],
    "wof:name":"Tyson Foods Inc",
    "wof:placetype":"venue"
},
  "geometry": {"coordinates":[-76.496601,40.117256],"type":"Point"}
}