{
  "type": "Feature",
  "properties": {
    "addr:full":"6035 N Philip St Philadelphia PA 19120",
    "addr:housenumber":"6035",
    "addr:postcode":"19120",
    "addr:street":"N Philip St",
    "iso:country":"US",
    "sg:address":"6035 N Philip St",
    "sg:city":"Philadelphia",
    "sg:classifiers":[
        {
            "category":"Building & Trades",
            "subcategory":"Plumbing",
            "type":"Services"
        }
    ],
    "sg:phone":"+1   ",
    "sg:postcode":"19120",
    "sg:province":"PA",
    "sg:tags":[
        "repair",
        "heating",
        "system",
        "maintenance",
        "plumbing",
        "con"
    ],
    "wof:name":"B J K Plumbing & Heating",
    "wof:placetype":"venue"
},
  "geometry": {"coordinates":[-75.12455,40.042989],"type":"Point"}
}