{
  "type": "Feature",
  "properties": {
    "iso:country":"US",
    "sg:address":"111 E Bishop St",
    "sg:city":"Bellefonte",
    "sg:classifiers":[
        {
            "category":"Personal",
            "subcategory":"Barber",
            "type":"Services"
        }
    ],
    "sg:phone":"+1 814 355 1149",
    "sg:postcode":"16823",
    "sg:province":"PA",
    "wof:name":"Gorgeous Hair Designs by Jonna",
    "wof:placetype":"venue"
},
  "geometry": {"coordinates":[-77.7771,40.9109],"type":"Point"}
}