{
  "type": "Feature",
  "properties": {
    "iso:country":"US",
    "sg:address":"920 Northern Blvd",
    "sg:city":"Clarks Summit",
    "sg:classifiers":[
        {
            "category":"Banks & Credit Unions",
            "subcategory":"Bank",
            "type":"Services"
        }
    ],
    "sg:phone":"+1 570 586 2323",
    "sg:postcode":"18411",
    "sg:province":"PA",
    "wof:name":"Pnc Bank",
    "wof:placetype":"venue"
},
  "geometry": {"coordinates":[-75.691695,41.483768],"type":"Point"}
}