{
  "type": "Feature",
  "properties": {
    "iso:country":"US",
    "sg:address":"255 Glen Dr",
    "sg:city":"Manchester",
    "sg:classifiers":[
        {
            "category":"Shopping",
            "subcategory":"Pharmacy",
            "type":"Retail Goods"
        }
    ],
    "sg:phone":"+1 717 266 3629",
    "sg:postcode":"17345",
    "sg:province":"PA",
    "sg:tags":[
        "drug",
        "store"
    ],
    "wof:name":"Eckerd",
    "wof:placetype":"venue"
},
  "geometry": {"coordinates":[-76.725267,40.04448],"type":"Point"}
}