{
  "type": "Feature",
  "properties": {
    "iso:country":"US",
    "sg:address":"10 W King St",
    "sg:city":"Littlestown",
    "sg:classifiers":[
        {
            "category":"Health Services",
            "subcategory":"Doctor",
            "type":"Services"
        }
    ],
    "sg:phone":"+1   ",
    "sg:postcode":"17340",
    "sg:province":"PA",
    "sg:tags":[
        "medical"
    ],
    "wof:name":"Doctor Rajah",
    "wof:placetype":"venue"
},
  "geometry": {"coordinates":[-77.088453,39.744538],"type":"Point"}
}