{
  "type": "Feature",
  "properties": {
    "iso:country":"US",
    "sg:address":"783 Mckean Ave",
    "sg:city":"Donora",
    "sg:classifiers":[
        {
            "category":"Personal",
            "subcategory":"Barber",
            "type":"Services"
        }
    ],
    "sg:phone":"+1 724 379 7579",
    "sg:postcode":"15033",
    "sg:province":"PA",
    "wof:name":"Ernie's Barber Shop",
    "wof:placetype":"venue"
},
  "geometry": {"coordinates":[-79.855932,40.180473],"type":"Point"}
}