{
  "type": "Feature",
  "properties": {
    "iso:country":"US",
    "sg:address":"1425 Scalp Ave",
    "sg:city":"Johnstown",
    "sg:classifiers":[
        {
            "category":"Recreation",
            "type":"Entertainment"
        }
    ],
    "sg:phone":"+1   ",
    "sg:postcode":"15904",
    "sg:province":"PA",
    "sg:tags":[
        "operation"
    ],
    "wof:name":"Pen National Gaming Corp",
    "wof:placetype":"venue"
},
  "geometry": {"coordinates":[-78.85890999999999,40.273394],"type":"Point"}
}