{
  "type": "Feature",
  "properties": {
    "addr:full":"3730 John St Emmaus PA 18049",
    "addr:housenumber":"3730",
    "addr:postcode":"18049",
    "addr:street":"John St",
    "iso:country":"US",
    "sg:address":"3730 John St",
    "sg:city":"Emmaus",
    "sg:classifiers":[
        {
            "category":"Building & Trades",
            "subcategory":"Landscaping Services",
            "type":"Services"
        }
    ],
    "sg:phone":"+1 610 965 3624",
    "sg:postcode":"18049",
    "sg:province":"PA",
    "sg:tags":[
        "lawn",
        "maintenance"
    ],
    "wof:name":"Josh's Pressure Washing And Lawn Care",
    "wof:placetype":"venue"
},
  "geometry": {"coordinates":[-75.518889,40.526003],"type":"Point"}
}