{
  "type": "Feature",
  "properties": {
    "iso:country":"US",
    "sg:address":"464 E Market Ave",
    "sg:city":"Dallastown",
    "sg:classifiers":[
        {
            "category":"Wholesale",
            "subcategory":"Construction Materials",
            "type":"Manufacturing & Wholesale Goods"
        }
    ],
    "sg:phone":"+1 717 244 2233",
    "sg:postcode":"17313",
    "sg:province":"PA",
    "sg:tags":[
        "trellis",
        "vinyl",
        "fence"
    ],
    "wof:name":"Palkar Inc",
    "wof:placetype":"venue"
},
  "geometry": {"coordinates":[-76.634822,39.897889],"type":"Point"}
}