{
  "type": "Feature",
  "properties": {
    "iso:country":"US",
    "sg:address":"5 Allison Rd",
    "sg:city":"Oreland",
    "sg:classifiers":[
        {
            "category":"Personal",
            "subcategory":"Beauty Salon",
            "type":"Services"
        }
    ],
    "sg:phone":"+1 215 887 2830",
    "sg:postcode":"19075",
    "sg:province":"PA",
    "sg:tags":[
        "shop"
    ],
    "wof:name":"Nails By Alla",
    "wof:placetype":"venue"
},
  "geometry": {"coordinates":[-75.18452499999999,40.116332],"type":"Point"}
}