{
  "type": "Feature",
  "properties": {
    "iso:country":"US",
    "sg:address":"617 Lincoln Ave",
    "sg:city":"Pittsburgh",
    "sg:classifiers":[
        {
            "category":"Professional",
            "subcategory":"Lawyer & Legal Services",
            "type":"Services"
        }
    ],
    "sg:phone":"+1   ",
    "sg:postcode":"15202",
    "sg:province":"PA",
    "wof:name":"Leonard A Dejulio",
    "wof:placetype":"venue"
},
  "geometry": {"coordinates":[-80.058708,40.496974],"type":"Point"}
}