{
  "type": "Feature",
  "properties": {
    "iso:country":"US",
    "sg:address":"263 N Union St",
    "sg:city":"Middletown",
    "sg:classifiers":[
        {
            "category":"Building & Trades",
            "subcategory":"Construction",
            "type":"Services"
        }
    ],
    "sg:phone":"+1 717 608 5999",
    "sg:postcode":"17057",
    "sg:province":"PA",
    "sg:tags":[
        "home",
        "improvement"
    ],
    "wof:name":"Beckwith Custom Carpentry",
    "wof:placetype":"venue"
},
  "geometry": {"coordinates":[-76.730486,40.198358],"type":"Point"}
}