{
  "type": "Feature",
  "properties": {
    "iso:country":"US",
    "sg:address":"2900 Aramingo Ave",
    "sg:city":"Philadelphia",
    "sg:classifiers":[
        {
            "category":"Restaurant",
            "type":"Food & Drink"
        }
    ],
    "sg:phone":"+1 215 291 8122",
    "sg:postcode":"19134",
    "sg:province":"PA",
    "sg:tags":[
        "chinese"
    ],
    "wof:name":"No One China",
    "wof:placetype":"venue"
},
  "geometry": {"coordinates":[-75.113297,39.984798],"type":"Point"}
}