{
  "type": "Feature",
  "properties": {
    "addr:full":"325 Chestnut St Philadelphia PA 19106",
    "addr:housenumber":"325",
    "addr:postcode":"19106",
    "addr:street":"Chestnut St",
    "iso:country":"US",
    "sg:address":"325 Chestnut St",
    "sg:city":"Philadelphia",
    "sg:classifiers":[
        {
            "category":"Professional",
            "subcategory":"Lawyer & Legal Services",
            "type":"Services"
        }
    ],
    "sg:phone":"+1 215 829 0014",
    "sg:postcode":"19106",
    "sg:province":"PA",
    "wof:name":"Bankes Paul J Jr Atty",
    "wof:placetype":"venue"
},
  "geometry": {"coordinates":[-75.146202,39.9487],"type":"Point"}
}