{
  "type": "Feature",
  "properties": {
    "iso:country":"US",
    "sg:address":"265 McCoury Rd",
    "sg:city":"Nottingham",
    "sg:classifiers":[
        {
            "category":"Building & Trades",
            "subcategory":"Construction",
            "type":"Services"
        }
    ],
    "sg:phone":"+1   ",
    "sg:postcode":"19362",
    "sg:province":"PA",
    "sg:tags":[
        "masonry"
    ],
    "wof:name":"Maxwell Masonry",
    "wof:placetype":"venue"
},
  "geometry": {"coordinates":[-75.996627,39.727082],"type":"Point"}
}