{
  "type": "Feature",
  "properties": {
    "addr:full":"1965 Waddle Rd State College PA 16803",
    "addr:housenumber":"1965",
    "addr:postcode":"16803",
    "addr:street":"Waddle Rd",
    "iso:country":"US",
    "sg:address":"1965 Waddle Rd",
    "sg:city":"State College",
    "sg:classifiers":[
        {
            "category":"Travel",
            "subcategory":"Hotels & Motels",
            "type":"Entertainment"
        }
    ],
    "sg:phone":"+1 814 234 4460",
    "sg:postcode":"16803",
    "sg:province":"PA",
    "sg:tags":[
        "inn"
    ],
    "sg:website":"www.shanerhotels.com",
    "wof:name":"Shaner Hotel Group",
    "wof:placetype":"venue"
},
  "geometry": {"coordinates":[-77.899096,40.815996],"type":"Point"}
}