{
  "type": "Feature",
  "properties": {
    "addr:full":"101 E Moreland Rd  Willow Grove PA 19090",
    "addr:housenumber":"101",
    "addr:postcode":"19090",
    "addr:street":"E Moreland Rd",
    "iso:country":"US",
    "sg:address":"101 E Moreland Rd ",
    "sg:city":"Willow Grove",
    "sg:classifiers":[
        {
            "category":"Restaurant",
            "type":"Food & Drink"
        }
    ],
    "sg:menulink":"http://www.allmenus.com/pa/upper-moreland/288407-franconis-pizzeria/menu/",
    "sg:phone":"+1 215 659 0900",
    "sg:postcode":"19090",
    "sg:province":"PA",
    "sg:tags":[
        "american",
        "pizza"
    ],
    "wof:name":"Franconis Pizzeria",
    "wof:placetype":"venue"
},
  "geometry": {"coordinates":[-75.11392499999999,40.139698],"type":"Point"}
}