{
  "type": "Feature",
  "properties": {
    "addr:full":"3232 Anchor Rd Washington Boro PA 17582",
    "addr:housenumber":"3232",
    "addr:postcode":"17582",
    "addr:street":"Anchor Rd",
    "iso:country":"US",
    "sg:address":"3232 Anchor Rd",
    "sg:city":"Washington Boro",
    "sg:classifiers":[
        {
            "category":"Farming",
            "subcategory":"Livestock Farm",
            "type":"Manufacturing & Wholesale Goods"
        }
    ],
    "sg:phone":"+1 717 872 7423",
    "sg:postcode":"17582",
    "sg:province":"PA",
    "sg:tags":[
        "feedlot",
        "hog",
        "or",
        "beef",
        "cattle"
    ],
    "wof:name":"Craig A Frey",
    "wof:placetype":"venue"
},
  "geometry": {"coordinates":[-76.42303099999999,39.982163],"type":"Point"}
}