{
  "type": "Feature",
  "properties": {
    "addr:full":"1927 Hafer Rd Fayetteville PA 17222",
    "addr:housenumber":"1927",
    "addr:postcode":"17222",
    "addr:street":"Hafer Rd",
    "iso:country":"US",
    "sg:address":"1927 Hafer Rd",
    "sg:city":"Fayetteville",
    "sg:classifiers":[
        {
            "category":"Social Services",
            "type":"Services"
        }
    ],
    "sg:phone":"+1 717 263 2820",
    "sg:postcode":"17222",
    "sg:province":"PA",
    "sg:tags":[
        "counselor",
        "marriage",
        "family"
    ],
    "wof:name":"Creative Life Counseling",
    "wof:placetype":"venue"
},
  "geometry": {"coordinates":[-77.580226,39.944432],"type":"Point"}
}