{
  "type": "Feature",
  "properties": {
    "addr:full":"425 Thornbrook Ave Bryn Mawr PA 19010",
    "addr:housenumber":"425",
    "addr:postcode":"19010",
    "addr:street":"Thornbrook Ave",
    "iso:country":"US",
    "sg:address":"425 Thornbrook Ave",
    "sg:city":"Bryn Mawr",
    "sg:classifiers":[
        {
            "category":"Real Estate",
            "subcategory":"Real Estate Agent",
            "type":"Services"
        }
    ],
    "sg:phone":"+1   ",
    "sg:postcode":"19010",
    "sg:province":"PA",
    "wof:name":"Joseph Baranzano Jr",
    "wof:placetype":"venue"
},
  "geometry": {"coordinates":[-75.32636599999999,40.038534],"type":"Point"}
}