{
  "type": "Feature",
  "properties": {
    "iso:country":"US",
    "sg:address":"1101 Harrison St",
    "sg:city":"Allentown",
    "sg:classifiers":[
        {
            "category":"Manufacturing",
            "subcategory":"Food",
            "type":"Manufacturing & Wholesale Goods"
        }
    ],
    "sg:phone":"+1 610 433 4711",
    "sg:postcode":"18103",
    "sg:province":"PA",
    "sg:tags":[
        "preparation",
        "specializing",
        "tofu",
        "mfg"
    ],
    "wof:name":"Fresh Tofu Inc",
    "wof:placetype":"venue"
},
  "geometry": {"coordinates":[-75.47713400000001,40.592987],"type":"Point"}
}