{
  "type": "Feature",
  "properties": {
    "iso:country":"US",
    "sg:address":"245 New York Dr",
    "sg:city":"Fort Washington",
    "sg:classifiers":[
        {
            "category":"Personal",
            "type":"Services"
        }
    ],
    "sg:phone":"+1 215 643 6363",
    "sg:postcode":"19034",
    "sg:province":"PA",
    "sg:tags":[
        "control",
        "weight"
    ],
    "sg:website":"www.slimdowners.com",
    "wof:name":"Weight Watchers",
    "wof:placetype":"venue"
},
  "geometry": {"coordinates":[-75.198955,40.138966],"type":"Point"}
}