{
  "type": "Feature",
  "properties": {
    "iso:country":"US",
    "sg:address":"1743 N 2nd St",
    "sg:city":"Philadelphia",
    "sg:classifiers":[
        {
            "category":"Retail",
            "subcategory":"Auto Rental",
            "type":"Services"
        }
    ],
    "sg:phone":"+1 215 235 8076",
    "sg:postcode":"19122",
    "sg:province":"PA",
    "sg:tags":[
        "renting",
        "leasing",
        "car",
        "truck",
        "trailer"
    ],
    "wof:name":"U-Haul Co",
    "wof:placetype":"venue"
},
  "geometry": {"coordinates":[-75.137911,39.977168],"type":"Point"}
}