{
  "type": "Feature",
  "properties": {
    "addr:full":"807 S 4th St Hamburg PA 19526",
    "addr:housenumber":"807",
    "addr:postcode":"19526",
    "addr:street":"S 4Th St",
    "iso:country":"US",
    "sg:address":"807 S 4th St",
    "sg:city":"Hamburg",
    "sg:classifiers":[
        {
            "category":"Restaurant",
            "type":"Food & Drink"
        }
    ],
    "sg:menulink":"http://www.allmenus.com/pa/hamburg/175392-arbys/menu/",
    "sg:phone":"+1 610 562 9790",
    "sg:postcode":"19526",
    "sg:province":"PA",
    "sg:tags":[
        "burger",
        "american"
    ],
    "wof:name":"Arby's",
    "wof:placetype":"venue"
},
  "geometry": {"coordinates":[-75.97738099999999,40.542227],"type":"Point"}
}