{
  "type": "Feature",
  "properties": {
    "iso:country":"US",
    "sg:address":"108 Horseshoe Cir",
    "sg:city":"Penn Furnace",
    "sg:classifiers":[
        {
            "category":"Home & Garden",
            "subcategory":"Home Furnishings",
            "type":"Retail Goods"
        }
    ],
    "sg:phone":"+1 814 237 6200",
    "sg:postcode":"16865",
    "sg:province":"PA",
    "sg:tags":[
        "curtain",
        "made",
        "drapery"
    ],
    "wof:name":"V2K Window Fashions",
    "wof:placetype":"venue"
},
  "geometry": {"coordinates":[-77.938748,40.729243],"type":"Point"}
}