{
  "type": "Feature",
  "properties": {
    "addr:full":"1648 Huntingdon Rd Abington PA 19001",
    "addr:housenumber":"1648",
    "addr:postcode":"19001",
    "addr:street":"Huntingdon Rd",
    "iso:country":"US",
    "sg:address":"1648 Huntingdon Rd",
    "sg:city":"Abington",
    "sg:classifiers":[
        {
            "category":"Food & Beverages",
            "subcategory":"Specialty",
            "type":"Retail Goods"
        }
    ],
    "sg:phone":"+1 215 938 9840",
    "sg:postcode":"19001",
    "sg:province":"PA",
    "sg:tags":[
        "tea",
        "coffee"
    ],
    "wof:name":"Java Joe's",
    "wof:placetype":"venue"
},
  "geometry": {"coordinates":[-75.107221,40.125351],"type":"Point"}
}