{
  "type": "Feature",
  "properties": {
    "iso:country":"US",
    "sg:address":"924 Newark Rd",
    "sg:city":"Toughkenamon",
    "sg:classifiers":[
        {
            "category":"Building & Trades",
            "subcategory":"Landscaping Services",
            "type":"Services"
        }
    ],
    "sg:phone":"+1 610 268 2250",
    "sg:postcode":"19374",
    "sg:province":"PA",
    "sg:tags":[
        "landscape",
        "contractor"
    ],
    "wof:name":"New Garden Fresh Inc",
    "wof:placetype":"venue"
},
  "geometry": {"coordinates":[-75.75236099999999,39.816655],"type":"Point"}
}