{
  "type": "Feature",
  "properties": {
    "addr:full":"513 Waln Rd Glenside PA 19038",
    "addr:housenumber":"513",
    "addr:postcode":"19038",
    "addr:street":"Waln Rd",
    "iso:country":"US",
    "sg:address":"513 Waln Rd",
    "sg:city":"Glenside",
    "sg:classifiers":[
        {
            "category":"Social Services",
            "type":"Services"
        }
    ],
    "sg:phone":"+1 215 884 7238",
    "sg:postcode":"19038",
    "sg:province":"PA",
    "sg:tags":[
        "human"
    ],
    "wof:name":"Philadelphia A Better",
    "wof:placetype":"venue"
},
  "geometry": {"coordinates":[-75.171927,40.10478],"type":"Point"}
}