{
  "type": "Feature",
  "properties": {
    "iso:country":"US",
    "sg:address":"554 E Heatherfield Way",
    "sg:city":"Red Lion",
    "sg:classifiers":[
        {
            "category":"Utilities",
            "subcategory":"Telephone",
            "type":"Services"
        }
    ],
    "sg:phone":"+1   ",
    "sg:postcode":"17356",
    "sg:province":"PA",
    "sg:tags":[
        "communications"
    ],
    "wof:name":"EZ Computer",
    "wof:placetype":"venue"
},
  "geometry": {"coordinates":[-76.611577,39.926294],"type":"Point"}
}