{
  "type": "Feature",
  "properties": {
    "addr:full":"1 2nd St Upper Darby PA 19015",
    "addr:housenumber":"1",
    "addr:postcode":"19015",
    "addr:street":"2Nd St",
    "iso:country":"US",
    "sg:address":"1 2nd St",
    "sg:city":"Upper Darby",
    "sg:classifiers":[
        {
            "category":"Retail",
            "subcategory":"Auto Repair",
            "type":"Services"
        }
    ],
    "sg:phone":"+1 610 623 2246",
    "sg:postcode":"19015",
    "sg:province":"PA",
    "sg:tags":[
        "repairing",
        "automobile"
    ],
    "wof:name":"M G Auto Repair Inc",
    "wof:placetype":"venue"
},
  "geometry": {"coordinates":[-75.38266900000001,39.851956],"type":"Point"}
}