{
  "type": "Feature",
  "properties": {
    "iso:country":"US",
    "sg:address":"2400 Thea Dr",
    "sg:city":"Harrisburg",
    "sg:classifiers":[
        {
            "category":"Professional",
            "subcategory":"Computer Services",
            "type":"Services"
        }
    ],
    "sg:phone":"+1 717 703 6000",
    "sg:postcode":"17110",
    "sg:province":"PA",
    "sg:tags":[
        "cd-rom"
    ],
    "sg:website":"http://www.dstsystems.com",
    "wof:name":"Dst Systems, Inc.",
    "wof:placetype":"venue"
},
  "geometry": {"coordinates":[-76.850609,40.32127],"type":"Point"}
}