{
  "type": "Feature",
  "properties": {
    "iso:country":"US",
    "sg:address":"526 Fishers Rd",
    "sg:city":"Bryn Mawr",
    "sg:classifiers":[
        {
            "category":"Real Estate",
            "subcategory":"Real Estate Operator",
            "type":"Services"
        }
    ],
    "sg:phone":"+1   ",
    "sg:postcode":"19010",
    "sg:province":"PA",
    "sg:tags":[
        "building",
        "nonresidential"
    ],
    "wof:name":"Five Twenty Six Assoc Inc",
    "wof:placetype":"venue"
},
  "geometry": {"coordinates":[-75.29931000000001,40.029345],"type":"Point"}
}