{
  "type": "Feature",
  "properties": {
    "iso:country":"US",
    "sg:address":"850 Locust St",
    "sg:city":"Philadelphia",
    "sg:classifiers":[
        {
            "category":"Real Estate",
            "subcategory":"Real Estate Operator",
            "type":"Services"
        }
    ],
    "sg:phone":"+1 215 922 5177",
    "sg:postcode":"19107",
    "sg:province":"PA",
    "sg:tags":[
        "housing",
        "apartment",
        "cost",
        "low",
        "elderly"
    ],
    "wof:name":"St George Athenagoras Manor",
    "wof:placetype":"venue"
},
  "geometry": {"coordinates":[-75.155637,39.947094],"type":"Point"}
}