{
  "type": "Feature",
  "properties": {
    "iso:country":"US",
    "sg:address":"22 Castle Rock Dr",
    "sg:city":"Havertown",
    "sg:classifiers":[
        {
            "category":"Building & Trades",
            "subcategory":"Electrical",
            "type":"Services"
        }
    ],
    "sg:phone":"+1 610 789 7679",
    "sg:postcode":"19083",
    "sg:province":"PA",
    "sg:tags":[
        "electrical",
        "contractor"
    ],
    "wof:name":"Anthony Electric",
    "wof:placetype":"venue"
},
  "geometry": {"coordinates":[-75.337018,39.98584],"type":"Point"}
}