{
  "type": "Feature",
  "properties": {
    "addr:full":"920 Oak St Scranton PA 18508",
    "addr:housenumber":"920",
    "addr:postcode":"18508",
    "addr:street":"Oak St",
    "iso:country":"US",
    "sg:address":"920 Oak St",
    "sg:city":"Scranton",
    "sg:classifiers":[
        {
            "category":"Banks & Credit Unions",
            "subcategory":"Bank",
            "type":"Services"
        }
    ],
    "sg:phone":"+1 570 961 5300",
    "sg:postcode":"18508",
    "sg:province":"PA",
    "sg:tags":[
        "federal"
    ],
    "sg:website":"www.netfedcu.org",
    "wof:name":"NET Federal Credit Union",
    "wof:placetype":"venue"
},
  "geometry": {"coordinates":[-75.66691899999999,41.447531],"type":"Point"}
}