{
  "type": "Feature",
  "properties": {
    "addr:full":"632 Poplar Ct Pittsburgh PA 15238",
    "addr:housenumber":"632",
    "addr:postcode":"15238",
    "addr:street":"Poplar Ct",
    "iso:country":"US",
    "sg:address":"632 Poplar Ct",
    "sg:city":"Pittsburgh",
    "sg:classifiers":[
        {
            "category":"Real Estate",
            "subcategory":"Real Estate Operator",
            "type":"Services"
        },
        {
            "category":"Building & Trades",
            "subcategory":"Construction",
            "type":"Services"
        }
    ],
    "sg:phone":"+1 412 828 3757",
    "sg:postcode":"15238",
    "sg:province":"PA",
    "sg:tags":[
        "mobile",
        "home",
        "builder",
        "site"
    ],
    "wof:name":"Carnegie Homes LLC",
    "wof:placetype":"venue"
},
  "geometry": {"coordinates":[-79.863809,40.539324],"type":"Point"}
}