{
  "type": "Feature",
  "properties": {
    "iso:country":"US",
    "sg:address":"423 Chartiers St",
    "sg:city":"Bridgeville",
    "sg:classifiers":[
        {
            "category":"Personal",
            "subcategory":"Day Spa",
            "type":"Services"
        }
    ],
    "sg:phone":"+1 412 257 2691",
    "sg:postcode":"15017",
    "sg:province":"PA",
    "wof:name":"Serenity Day Spa & Salon Inc",
    "wof:placetype":"venue"
},
  "geometry": {"coordinates":[-80.11373399999999,40.355459],"type":"Point"}
}