{
  "type": "Feature",
  "properties": {
    "iso:country":"US",
    "sg:address":"1541 N Randolph St",
    "sg:city":"Philadelphia",
    "sg:classifiers":[
        {
            "category":"Home & Garden",
            "subcategory":"Home Furnishings",
            "type":"Retail Goods"
        }
    ],
    "sg:phone":"+1 215 765 2080",
    "sg:postcode":"19122",
    "sg:province":"PA",
    "sg:tags":[
        "cover",
        "slip"
    ],
    "wof:name":"Affordable Plastic Slipcovers",
    "wof:placetype":"venue"
},
  "geometry": {"coordinates":[-75.14473599999999,39.974938],"type":"Point"}
}