{
  "type": "Feature",
  "properties": {
    "addr:full":"160 Kressman Rd Easton PA 18042",
    "addr:housenumber":"160",
    "addr:postcode":"18042",
    "addr:street":"Kressman Rd",
    "iso:country":"US",
    "sg:address":"160 Kressman Rd",
    "sg:city":"Easton",
    "sg:classifiers":[
        {
            "category":"Wholesale",
            "subcategory":"Construction Materials",
            "type":"Manufacturing & Wholesale Goods"
        }
    ],
    "sg:phone":"+1 610 252 1984",
    "sg:postcode":"18042",
    "sg:province":"PA",
    "sg:tags":[
        "fence"
    ],
    "wof:name":"Advantage Landscaping",
    "wof:placetype":"venue"
},
  "geometry": {"coordinates":[-75.215129,40.622808],"type":"Point"}
}