{
  "type": "Feature",
  "properties": {
    "iso:country":"US",
    "sg:address":"4950 Carlisle Pike",
    "sg:city":"Mechanicsburg",
    "sg:classifiers":[
        {
            "category":"Cinema",
            "subcategory":"Movie Theater",
            "type":"Entertainment"
        }
    ],
    "sg:phone":"+1 717 737 4133",
    "sg:postcode":"17050",
    "sg:province":"PA",
    "sg:website":"www.flagshipcenemas.com",
    "wof:name":"Flagship Cinemas",
    "wof:placetype":"venue"
},
  "geometry": {"coordinates":[-76.968781,40.235807],"type":"Point"}
}