{
  "type": "Feature",
  "properties": {
    "iso:country":"US",
    "sg:address":"2601 Haverford Rd",
    "sg:city":"Ardmore",
    "sg:classifiers":[
        {
            "category":"Retail",
            "subcategory":"Car Wash",
            "type":"Services"
        }
    ],
    "sg:phone":"+1 610 645 5626",
    "sg:postcode":"19003",
    "sg:province":"PA",
    "sg:tags":[
        "automobile",
        "detail",
        "clean"
    ],
    "wof:name":"Whistle Clean Car Wash",
    "wof:placetype":"venue"
},
  "geometry": {"coordinates":[-75.30181899999999,39.996078],"type":"Point"}
}