{
  "type": "Feature",
  "properties": {
    "addr:full":"313 Union St Farrell PA 16121",
    "addr:housenumber":"313",
    "addr:postcode":"16121",
    "addr:street":"Union St",
    "iso:country":"US",
    "sg:address":"313 Union St",
    "sg:city":"Farrell",
    "sg:classifiers":[
        {
            "category":"Restaurant",
            "type":"Food & Drink"
        }
    ],
    "sg:phone":"+1 724 981 1242",
    "sg:postcode":"16121",
    "sg:province":"PA",
    "sg:tags":[
        "eating"
    ],
    "wof:name":"Fabulous Feast",
    "wof:placetype":"venue"
},
  "geometry": {"coordinates":[-80.50444899999999,41.21459],"type":"Point"}
}