{
  "type": "Feature",
  "properties": {
    "iso:country":"US",
    "sg:address":"116 Byberry Rd",
    "sg:city":"Hatboro",
    "sg:classifiers":[
        {
            "category":"Professional",
            "subcategory":"Employment Agencies",
            "type":"Services"
        }
    ],
    "sg:phone":"+1 215 675 6020",
    "sg:postcode":"19040",
    "sg:province":"PA",
    "sg:tags":[
        "contractor"
    ],
    "wof:name":"C U Staffing Inc",
    "wof:placetype":"venue"
},
  "geometry": {"coordinates":[-75.10251700000001,40.174599],"type":"Point"}
}