{
  "type": "Feature",
  "properties": {
    "iso:country":"US",
    "sg:address":"440 Pinney St",
    "sg:city":"Rochester",
    "sg:classifiers":[
        {
            "category":"Organizations",
            "subcategory":"Community Association",
            "type":"Services"
        }
    ],
    "sg:phone":"+1 724 774 3306",
    "sg:postcode":"15074",
    "sg:province":"PA",
    "sg:tags":[
        "fraternal"
    ],
    "wof:name":"Elks Lodge",
    "wof:placetype":"venue"
},
  "geometry": {"coordinates":[-80.278977,40.701211],"type":"Point"}
}