{
  "type": "Feature",
  "properties": {
    "iso:country":"US",
    "sg:address":"1201 S 23rd St Ofc",
    "sg:city":"Philadelphia",
    "sg:classifiers":[
        {
            "category":"Education",
            "subcategory":"Library",
            "type":"Public Place"
        }
    ],
    "sg:phone":"+1 215 685 1899",
    "sg:postcode":"19146",
    "sg:province":"PA",
    "sg:website":"http://www.phila.gov",
    "wof:name":"Free Library Of Philidelphia",
    "wof:placetype":"venue"
},
  "geometry": {"coordinates":[-75.181831,39.938061],"type":"Point"}
}