{
  "type": "Feature",
  "properties": {
    "addr:full":"656 E Swedesford Rd Wayne PA 19087",
    "addr:housenumber":"656",
    "addr:postcode":"19087",
    "addr:street":"E Swedesford Rd",
    "iso:country":"US",
    "sg:address":"656 E Swedesford Rd",
    "sg:city":"Wayne",
    "sg:classifiers":[
        {
            "category":"Professional",
            "subcategory":"Employment Agencies",
            "type":"Services"
        }
    ],
    "sg:phone":"+1   ",
    "sg:postcode":"19087",
    "sg:province":"PA",
    "sg:tags":[
        "help",
        "supply"
    ],
    "wof:name":"Stivers Staffing Services",
    "wof:placetype":"venue"
},
  "geometry": {"coordinates":[-75.414129,40.079909],"type":"Point"}
}