{
  "type": "Feature",
  "properties": {
    "iso:country":"US",
    "sg:address":"3064 W Liberty Ave",
    "sg:city":"Pittsburgh",
    "sg:classifiers":[
        {
            "category":"Personal",
            "subcategory":"Tanning Parlor",
            "type":"Services"
        }
    ],
    "sg:phone":"+1 412 341 7768",
    "sg:postcode":"15216",
    "sg:province":"PA",
    "wof:name":"Hot Spot Tanning",
    "wof:placetype":"venue"
},
  "geometry": {"coordinates":[-80.038374,40.392019],"type":"Point"}
}