{
  "type": "Feature",
  "properties": {
    "iso:country":"US",
    "sg:address":"2398 Rolling Hills Dr",
    "sg:city":"Mechanicsburg",
    "sg:classifiers":[
        {
            "category":"Shopping",
            "type":"Retail Goods"
        }
    ],
    "sg:phone":"+1 717 790 9077",
    "sg:postcode":"17055",
    "sg:province":"PA",
    "sg:tags":[
        "merchandise"
    ],
    "wof:name":"David Young Photography",
    "wof:placetype":"venue"
},
  "geometry": {"coordinates":[-76.983732,40.17214],"type":"Point"}
}