{
  "type": "Feature",
  "properties": {
    "iso:country":"US",
    "sg:address":"2201 Bryn Mawr Ave",
    "sg:city":"Philadelphia",
    "sg:classifiers":[
        {
            "category":"Professional",
            "type":"Services"
        }
    ],
    "sg:phone":"+1 215 879 2590",
    "sg:postcode":"19131",
    "sg:province":"PA",
    "wof:name":"Urban Renaissance Corp",
    "wof:placetype":"venue"
},
  "geometry": {"coordinates":[-75.226573,39.991516],"type":"Point"}
}