{
  "type": "Feature",
  "properties": {
    "addr:full":"5225 N George St Exd Manchester PA 17345",
    "addr:housenumber":"5225",
    "addr:postcode":"17345",
    "addr:street":"N George St Exd",
    "iso:country":"US",
    "sg:address":"5225 N George St Exd",
    "sg:city":"Manchester",
    "sg:classifiers":[
        {
            "category":"Professional",
            "subcategory":"Business Services",
            "type":"Services"
        }
    ],
    "sg:phone":"+1 717 266 8880",
    "sg:postcode":"17345",
    "sg:province":"PA",
    "sg:tags":[
        "auctioneer"
    ],
    "wof:name":"Kyle E Mitzel Auction Svc",
    "wof:placetype":"venue"
},
  "geometry": {"coordinates":[-76.719503,40.073755],"type":"Point"}
}