{
  "type": "Feature",
  "properties": {
    "iso:country":"US",
    "sg:address":"291 Saville Ave",
    "sg:city":"Crum Lynne",
    "sg:classifiers":[
        {
            "category":"Autos & Motor Vehicles",
            "subcategory":"Fuel & Gas Station",
            "type":"Retail Goods"
        }
    ],
    "sg:phone":"+1   ",
    "sg:postcode":"19022",
    "sg:province":"PA",
    "sg:tags":[
        "station",
        "gasoline"
    ],
    "wof:name":"Printz Fuel Co Inc",
    "wof:placetype":"venue"
},
  "geometry": {"coordinates":[-75.340334,39.856258],"type":"Point"}
}