{
  "type": "Feature",
  "properties": {
    "addr:full":"1993 Cato Ave State College PA 16801",
    "addr:housenumber":"1993",
    "addr:postcode":"16801",
    "addr:street":"Cato Ave",
    "iso:country":"US",
    "sg:address":"1993 Cato Ave",
    "sg:city":"State College",
    "sg:classifiers":[
        {
            "category":"Health Services",
            "subcategory":"Health Practitioner",
            "type":"Services"
        }
    ],
    "sg:phone":"+1   ",
    "sg:postcode":"16801",
    "sg:province":"PA",
    "wof:name":"Center Psycho Thearpy",
    "wof:placetype":"venue"
},
  "geometry": {"coordinates":[-77.87895899999999,40.763494],"type":"Point"}
}