{
  "type": "Feature",
  "properties": {
    "iso:country":"US",
    "sg:address":"805 SIR Thomas Ct",
    "sg:city":"Harrisburg",
    "sg:classifiers":[
        {
            "category":"Health Services",
            "subcategory":"Doctor",
            "type":"Services"
        }
    ],
    "sg:phone":"+1 717 652 9555",
    "sg:postcode":"17109",
    "sg:province":"PA",
    "sg:tags":[
        "orthopedist"
    ],
    "wof:name":"Herbert Rex A DO",
    "wof:placetype":"venue"
},
  "geometry": {"coordinates":[-76.823097,40.282299],"type":"Point"}
}