{
  "type": "Feature",
  "properties": {
    "addr:full":"3675 Library Rd Pittsburgh PA 15234",
    "addr:housenumber":"3675",
    "addr:postcode":"15234",
    "addr:street":"Library Rd",
    "iso:country":"US",
    "sg:address":"3675 Library Rd",
    "sg:city":"Pittsburgh",
    "sg:classifiers":[
        {
            "category":"Retail",
            "subcategory":"Auto Repair",
            "type":"Services"
        }
    ],
    "sg:phone":"+1 412 886 0796",
    "sg:postcode":"15234",
    "sg:province":"PA",
    "sg:tags":[
        "glass",
        "replacement"
    ],
    "wof:name":"Guardian Auto Glass",
    "wof:placetype":"venue"
},
  "geometry": {"coordinates":[-80.01979799999999,40.3647],"type":"Point"}
}