{
  "type": "Feature",
  "properties": {
    "iso:country":"US",
    "sg:address":"236 Haverford Ave",
    "sg:city":"Narberth",
    "sg:classifiers":[
        {
            "category":"Shopping",
            "subcategory":"Used Merchandise",
            "type":"Retail Goods"
        }
    ],
    "sg:phone":"+1 610 668 1871",
    "sg:postcode":"19072",
    "sg:province":"PA",
    "sg:tags":[
        "antique"
    ],
    "wof:name":"Antiques At 236",
    "wof:placetype":"venue"
},
  "geometry": {"coordinates":[-75.260597,40.005501],"type":"Point"}
}