{
  "type": "Feature",
  "properties": {
    "addr:full":"1300 Overlook Ave Aliquippa PA 15001",
    "addr:housenumber":"1300",
    "addr:postcode":"15001",
    "addr:street":"Overlook Ave",
    "iso:country":"US",
    "sg:address":"1300 Overlook Ave",
    "sg:city":"Aliquippa",
    "sg:classifiers":[
        {
            "category":"Building & Trades",
            "subcategory":"Construction",
            "type":"Services"
        }
    ],
    "sg:phone":"+1   ",
    "sg:postcode":"15001",
    "sg:province":"PA",
    "sg:tags":[
        "house"
    ],
    "wof:name":"Home Improvements Folkens",
    "wof:placetype":"venue"
},
  "geometry": {"coordinates":[-80.240061,40.577677],"type":"Point"}
}