{
  "type": "Feature",
  "properties": {
    "iso:country":"US",
    "sg:address":"55 Woodland Rd",
    "sg:city":"Hickory",
    "sg:classifiers":[
        {
            "category":"Professional",
            "subcategory":"Management & Consulting",
            "type":"Services"
        }
    ],
    "sg:phone":"+1 724 356 7812",
    "sg:postcode":"15340",
    "sg:province":"PA",
    "sg:tags":[
        "science",
        "consultant",
        "academic"
    ],
    "wof:name":"Hickory Sales Consultants Inc",
    "wof:placetype":"venue"
},
  "geometry": {"coordinates":[-80.276087,40.293323],"type":"Point"}
}