{
  "type": "Feature",
  "properties": {
    "iso:country":"US",
    "sg:address":"222 Verbeke St",
    "sg:city":"Marysville",
    "sg:classifiers":[
        {
            "category":"Building & Trades",
            "subcategory":"Construction",
            "type":"Services"
        }
    ],
    "sg:phone":"+1 717 957 3320",
    "sg:postcode":"17053",
    "sg:province":"PA",
    "sg:tags":[
        "sealer",
        "specialist",
        "pavement",
        "power",
        "repair"
    ],
    "wof:name":"Sutton Brothers",
    "wof:placetype":"venue"
},
  "geometry": {"coordinates":[-76.930201,40.340825],"type":"Point"}
}