{
  "type": "Feature",
  "properties": {
    "iso:country":"US",
    "sg:address":"311 Haines Rd",
    "sg:city":"York",
    "sg:classifiers":[
        {
            "category":"Organizations",
            "subcategory":"Religious Organization",
            "type":"Services"
        }
    ],
    "sg:phone":"+1 717 755 6222",
    "sg:postcode":"17402",
    "sg:province":"PA",
    "sg:tags":[
        "church"
    ],
    "sg:website":"www.eastminster-york.org",
    "wof:name":"Eastminster Presbyterian Church",
    "wof:placetype":"venue"
},
  "geometry": {"coordinates":[-76.680114,39.968463],"type":"Point"}
}