{
  "type": "Feature",
  "properties": {
    "addr:full":"150 Alameda Rd Butler PA 16001",
    "addr:housenumber":"150",
    "addr:postcode":"16001",
    "addr:street":"Alameda Rd",
    "iso:country":"US",
    "sg:address":"150 Alameda Rd",
    "sg:city":"Butler",
    "sg:classifiers":[
        {
            "category":"Real Estate",
            "subcategory":"Real Estate Operator",
            "type":"Services"
        }
    ],
    "sg:phone":"+1 724 283 8430",
    "sg:postcode":"16001",
    "sg:province":"PA",
    "sg:tags":[
        "building",
        "apartment"
    ],
    "wof:name":"Byre Mor Court Apartments",
    "wof:placetype":"venue"
},
  "geometry": {"coordinates":[-79.92795099999999,40.870304],"type":"Point"}
}