{
  "type": "Feature",
  "properties": {
    "iso:country":"US",
    "sg:address":"1070 W Swartzville Rd",
    "sg:city":"Reinholds",
    "sg:classifiers":[
        {
            "category":"Manufacturing",
            "subcategory":"Signs",
            "type":"Manufacturing & Wholesale Goods"
        }
    ],
    "sg:phone":"+1 717 336 7098",
    "sg:postcode":"17569",
    "sg:province":"PA",
    "wof:name":"Horst Signs",
    "wof:placetype":"venue"
},
  "geometry": {"coordinates":[-76.099209,40.261264],"type":"Point"}
}