{
  "type": "Feature",
  "properties": {
    "addr:full":"90 Kennedy Blvd Scranton PA 18504",
    "addr:housenumber":"90",
    "addr:postcode":"18504",
    "addr:street":"Kennedy Blvd",
    "iso:country":"US",
    "sg:address":"90 Kennedy Blvd",
    "sg:city":"Scranton",
    "sg:classifiers":[
        {
            "category":"Government",
            "subcategory":"Office",
            "type":"Public Place"
        }
    ],
    "sg:phone":"+1 570 346 2231",
    "sg:postcode":"18504",
    "sg:province":"PA",
    "sg:tags":[
        "housing",
        "program"
    ],
    "wof:name":"Lackawanna County Housing Auth",
    "wof:placetype":"venue"
},
  "geometry": {"coordinates":[-75.69292299999999,41.393418],"type":"Point"}
}