{
  "type": "Feature",
  "properties": {
    "iso:country":"US",
    "sg:address":"700 S 5th Ave",
    "sg:city":"Lebanon",
    "sg:classifiers":[
        {
            "category":"Wholesale",
            "subcategory":"Home Furnishings",
            "type":"Manufacturing & Wholesale Goods"
        }
    ],
    "sg:phone":"+1 717 272 2022",
    "sg:postcode":"17042",
    "sg:province":"PA",
    "sg:tags":[
        "fixtures-wholesale",
        "lighting",
        "manufacturer"
    ],
    "wof:name":"Pa Lighting & Grip Equipment",
    "wof:placetype":"venue"
},
  "geometry": {"coordinates":[-76.396271,40.331805],"type":"Point"}
}