{
  "type": "Feature",
  "properties": {
    "iso:country":"US",
    "sg:address":"505 Bristol Pike",
    "sg:city":"Bensalem",
    "sg:classifiers":[
        {
            "category":"Restaurant",
            "type":"Food & Drink"
        }
    ],
    "sg:phone":"+1 215 788 7444",
    "sg:postcode":"19020",
    "sg:province":"PA",
    "wof:name":"Patrick's Pub & Restaurant",
    "wof:placetype":"venue"
},
  "geometry": {"coordinates":[-74.97694799999999,40.065273],"type":"Point"}
}