{
  "type": "Feature",
  "properties": {
    "iso:country":"US",
    "sg:address":"105 Doubling Gap Rd",
    "sg:city":"Newville",
    "sg:classifiers":[
        {
            "category":"Building & Trades",
            "subcategory":"Construction",
            "type":"Services"
        }
    ],
    "sg:phone":"+1 717 776 3031",
    "sg:postcode":"17241",
    "sg:province":"PA",
    "sg:tags":[
        "railing"
    ],
    "wof:name":"Lehman's Ornamental Ironwork",
    "wof:placetype":"venue"
},
  "geometry": {"coordinates":[-77.401816,40.177125],"type":"Point"}
}