{
  "type": "Feature",
  "properties": {
    "addr:full":"909 Muirfield Rd Bryn Mawr PA 19010",
    "addr:housenumber":"909",
    "addr:postcode":"19010",
    "addr:street":"Muirfield Rd",
    "iso:country":"US",
    "sg:address":"909 Muirfield Rd",
    "sg:city":"Bryn Mawr",
    "sg:classifiers":[
        {
            "category":"Professional",
            "type":"Services"
        }
    ],
    "sg:phone":"+1   ",
    "sg:postcode":"19010",
    "sg:province":"PA",
    "wof:name":"Cleantech of Philadelphia Inc",
    "wof:placetype":"venue"
},
  "geometry": {"coordinates":[-75.295485,40.040856],"type":"Point"}
}