{
  "type": "Feature",
  "properties": {
    "iso:country":"US",
    "sg:address":"4801 McKnight Rd",
    "sg:city":"Pittsburgh",
    "sg:classifiers":[
        {
            "category":"Food & Beverages",
            "subcategory":"Liquor & Beverages",
            "type":"Retail Goods"
        }
    ],
    "sg:phone":"+1 412 635 2194",
    "sg:postcode":"15237",
    "sg:province":"PA",
    "wof:name":"North Hills Vlg Liquor Store",
    "wof:placetype":"venue"
},
  "geometry": {"coordinates":[-80.010502,40.503356],"type":"Point"}
}