{
  "type": "Feature",
  "properties": {
    "addr:full":"538 Dick Rd Butler PA 16001",
    "addr:housenumber":"538",
    "addr:postcode":"16001",
    "addr:street":"Dick Rd",
    "iso:country":"US",
    "sg:address":"538 Dick Rd",
    "sg:city":"Butler",
    "sg:classifiers":[
        {
            "category":"Organizations",
            "subcategory":"Religious Organization",
            "type":"Services"
        }
    ],
    "sg:phone":"+1 724 865 9611",
    "sg:postcode":"16001",
    "sg:province":"PA",
    "sg:tags":[
        "clergy"
    ],
    "wof:name":"Randal Gullickson",
    "wof:placetype":"venue"
},
  "geometry": {"coordinates":[-80.017242,40.881397],"type":"Point"}
}