{
  "type": "Feature",
  "properties": {
    "addr:full":"5 S Hanover St Carlisle PA 17013",
    "addr:housenumber":"5",
    "addr:postcode":"17013",
    "addr:street":"S Hanover St",
    "iso:country":"US",
    "sg:address":"5 S Hanover St",
    "sg:city":"Carlisle",
    "sg:classifiers":[
        {
            "category":"Professional",
            "subcategory":"Lawyer & Legal Services",
            "type":"Services"
        }
    ],
    "sg:phone":"+1 717 243 5838",
    "sg:postcode":"17013",
    "sg:province":"PA",
    "wof:name":"Frey Robert M Atty",
    "wof:placetype":"venue"
},
  "geometry": {"coordinates":[-77.189003,40.2006],"type":"Point"}
}