{
  "type": "Feature",
  "properties": {
    "iso:country":"US",
    "sg:address":"329 Summerfield Dr",
    "sg:city":"Baden",
    "sg:classifiers":[
        {
            "category":"Professional",
            "subcategory":"Engineering",
            "type":"Services"
        }
    ],
    "sg:phone":"+1 724 869 9560",
    "sg:postcode":"15005",
    "sg:province":"PA",
    "sg:tags":[
        "surveying"
    ],
    "wof:name":"Shoup Engineering Inc",
    "wof:placetype":"venue"
},
  "geometry": {"coordinates":[-80.15482799999999,40.66991],"type":"Point"}
}