{
  "type": "Feature",
  "properties": {
    "iso:country":"US",
    "sg:address":"637 Saylors Mill Rd",
    "sg:city":"Spring City",
    "sg:classifiers":[
        {
            "category":"Food & Beverages",
            "subcategory":"Groceries & Convenience Stores",
            "type":"Retail Goods"
        }
    ],
    "sg:phone":"+1   ",
    "sg:postcode":"19475",
    "sg:province":"PA",
    "wof:name":"Mid ATL Imprtd Pt",
    "wof:placetype":"venue"
},
  "geometry": {"coordinates":[-75.600656,40.18849],"type":"Point"}
}