{
  "type": "Feature",
  "properties": {
    "iso:country":"US",
    "sg:address":"528 2nd Street Pike",
    "sg:city":"Southampton",
    "sg:classifiers":[
        {
            "category":"Restaurant",
            "type":"Food & Drink"
        }
    ],
    "sg:menulink":"http://www.allmenus.com/pa/northampton/37396-robin-hood-restaurant/menu/",
    "sg:phone":"+1 215 355 1522",
    "sg:postcode":"18966",
    "sg:province":"PA",
    "sg:tags":[
        "american",
        "diner"
    ],
    "wof:name":"Robin Hood Restaurant",
    "wof:placetype":"venue"
},
  "geometry": {"coordinates":[-75.01997,40.204154],"type":"Point"}
}