{
  "type": "Feature",
  "properties": {
    "iso:country":"US",
    "sg:address":"2832 Kensington Ave 34",
    "sg:city":"Philadelphia",
    "sg:classifiers":[
        {
            "category":"Retail",
            "subcategory":"Laundry & Dry Cleaning",
            "type":"Services"
        }
    ],
    "sg:phone":"+1 215 739 5960",
    "sg:postcode":"19134",
    "sg:province":"PA",
    "sg:tags":[
        "operated",
        "dryer",
        "laundries-self",
        "washer",
        "coin"
    ],
    "wof:name":"Lam's Laundromat",
    "wof:placetype":"venue"
},
  "geometry": {"coordinates":[-75.121484,39.992028],"type":"Point"}
}