{
  "type": "Feature",
  "properties": {
    "iso:country":"US",
    "sg:address":"106 W Front St",
    "sg:city":"Berwick",
    "sg:classifiers":[
        {
            "category":"Professional",
            "subcategory":"Lawyer & Legal Services",
            "type":"Services"
        }
    ],
    "sg:phone":"+1   ",
    "sg:postcode":"18603",
    "sg:province":"PA",
    "wof:name":"Saba Endler & Associates LLP",
    "wof:placetype":"venue"
},
  "geometry": {"coordinates":[-76.233636,41.054635],"type":"Point"}
}