{
  "type": "Feature",
  "properties": {
    "addr:full":"570 Centerville Rd Bedford PA 15522",
    "addr:housenumber":"570",
    "addr:postcode":"15522",
    "addr:street":"Centerville Rd",
    "iso:country":"US",
    "sg:address":"570 Centerville Rd",
    "sg:city":"Bedford",
    "sg:classifiers":[
        {
            "category":"Restaurant",
            "type":"Food & Drink"
        }
    ],
    "sg:phone":"+1 814 356 3673",
    "sg:postcode":"15522",
    "sg:province":"PA",
    "wof:name":"Moreland's Dads' Restaurant",
    "wof:placetype":"venue"
},
  "geometry": {"coordinates":[-78.66303000000001,39.816475],"type":"Point"}
}