{
  "type": "Feature",
  "properties": {
    "addr:full":"190 Manchester St Manchester PA 17345",
    "addr:housenumber":"190",
    "addr:postcode":"17345",
    "addr:street":"Manchester St",
    "iso:country":"US",
    "sg:address":"190 Manchester St",
    "sg:city":"Manchester",
    "sg:classifiers":[
        {
            "category":"Farming",
            "subcategory":"Livestock Farm",
            "type":"Manufacturing & Wholesale Goods"
        }
    ],
    "sg:phone":"+1   ",
    "sg:postcode":"17345",
    "sg:province":"PA",
    "sg:tags":[
        "beef",
        "feedlot",
        "cattle"
    ],
    "wof:name":"Steven Gross",
    "wof:placetype":"venue"
},
  "geometry": {"coordinates":[-76.72739300000001,40.065053],"type":"Point"}
}