{
  "type": "Feature",
  "properties": {
    "addr:full":"1888 Lafayette Rd Gladwyne PA 19035",
    "addr:housenumber":"1888",
    "addr:postcode":"19035",
    "addr:street":"Rd",
    "iso:country":"US",
    "sg:address":"1888 Lafayette Rd",
    "sg:city":"Gladwyne",
    "sg:classifiers":[
        {
            "category":"Building & Trades",
            "subcategory":"Cleaning & Sanitation",
            "type":"Services"
        }
    ],
    "sg:phone":"+1 610 658 2477",
    "sg:postcode":"19035",
    "sg:province":"PA",
    "sg:tags":[
        "janitor"
    ],
    "wof:name":"Deluxe Office Cleaning Svc",
    "wof:placetype":"venue"
},
  "geometry": {"coordinates":[-75.272891,40.057732],"type":"Point"}
}