{
  "type": "Feature",
  "properties": {
    "iso:country":"US",
    "sg:address":"14 Edith Dr",
    "sg:city":"Windsor",
    "sg:classifiers":[
        {
            "category":"Restaurant",
            "type":"Food & Drink"
        }
    ],
    "sg:phone":"+1   ",
    "sg:postcode":"17366",
    "sg:province":"PA",
    "sg:tags":[
        "personal",
        "chef"
    ],
    "wof:name":"Your Culinary Connection",
    "wof:placetype":"venue"
},
  "geometry": {"coordinates":[-76.56450700000001,39.937585],"type":"Point"}
}