{
  "type": "Feature",
  "properties": {
    "iso:country":"US",
    "sg:address":"1372 Fairyland Rd",
    "sg:city":"Lehighton",
    "sg:classifiers":[
        {
            "category":"Building & Trades",
            "subcategory":"Construction",
            "type":"Services"
        }
    ],
    "sg:phone":"+1   ",
    "sg:postcode":"18235",
    "sg:province":"PA",
    "sg:tags":[
        "excavation",
        "contractor"
    ],
    "wof:name":"Jerome C Dotter",
    "wof:placetype":"venue"
},
  "geometry": {"coordinates":[-75.67966199999999,40.845676],"type":"Point"}
}