{
  "type": "Feature",
  "properties": {
    "addr:full":"523 Mount Jackson Rd New Castle PA 16102",
    "addr:housenumber":"523",
    "addr:postcode":"16102",
    "addr:street":"Mount Jackson Rd New",
    "iso:country":"US",
    "sg:address":"523 Mount Jackson Rd",
    "sg:city":"New Castle",
    "sg:classifiers":[
        {
            "category":"Personal",
            "subcategory":"Beauty Salon",
            "type":"Services"
        }
    ],
    "sg:phone":"+1 724 667 0977",
    "sg:postcode":"16102",
    "sg:province":"PA",
    "sg:tags":[
        "shop"
    ],
    "wof:name":"Robin Wilson's Beauty Salon",
    "wof:placetype":"venue"
},
  "geometry": {"coordinates":[-80.40301599999999,40.970247],"type":"Point"}
}