{
  "type": "Feature",
  "properties": {
    "iso:country":"US",
    "sg:address":"644 E Main St",
    "sg:city":"New Holland",
    "sg:classifiers":[
        {
            "category":"Autos & Motor Vehicles",
            "subcategory":"Fuel & Gas Station",
            "type":"Retail Goods"
        }
    ],
    "sg:phone":"+1 717 354 2810",
    "sg:postcode":"17557",
    "sg:province":"PA",
    "sg:tags":[
        "oil"
    ],
    "wof:name":"Yoder's Fuel Island",
    "wof:placetype":"venue"
},
  "geometry": {"coordinates":[-76.066739,40.110673],"type":"Point"}
}