{
  "type": "Feature",
  "properties": {
    "addr:full":"602 W Saint Andrews Dr Media PA 19063",
    "addr:housenumber":"602",
    "addr:postcode":"19063",
    "addr:street":"W Saint Andrews Dr",
    "iso:country":"US",
    "sg:address":"602 W Saint Andrews Dr",
    "sg:city":"Media",
    "sg:classifiers":[
        {
            "category":"Insurance",
            "subcategory":"Hazard Insurance",
            "type":"Services"
        }
    ],
    "sg:phone":"+1 610 891 2770",
    "sg:postcode":"19063",
    "sg:province":"PA",
    "sg:tags":[
        "commercial",
        "business"
    ],
    "wof:name":"Forrest Insurance Agency",
    "wof:placetype":"venue"
},
  "geometry": {"coordinates":[-75.427952,39.88739],"type":"Point"}
}