{
  "type": "Feature",
  "properties": {
    "iso:country":"US",
    "sg:address":"122 Saint Wendelin Rd",
    "sg:city":"Butler",
    "sg:classifiers":[
        {
            "category":"Professional",
            "subcategory":"Detective & Security Services",
            "type":"Services"
        }
    ],
    "sg:phone":"+1 724 282 6985",
    "sg:postcode":"16002",
    "sg:province":"PA",
    "sg:tags":[
        "information",
        "bureau"
    ],
    "wof:name":"Ivory Farrier Service",
    "wof:placetype":"venue"
},
  "geometry": {"coordinates":[-79.812172,40.887077],"type":"Point"}
}