{
  "type": "Feature",
  "properties": {
    "iso:country":"US",
    "sg:address":"2301 N 5th St",
    "sg:city":"Perkasie",
    "sg:classifiers":[
        {
            "category":"Autos & Motor Vehicles",
            "subcategory":"Automobile Sales",
            "type":"Retail Goods"
        }
    ],
    "sg:phone":"+1   ",
    "sg:postcode":"18944",
    "sg:province":"PA",
    "sg:tags":[
        "new",
        "station",
        "truck",
        "used"
    ],
    "wof:name":"B R Scholl Sales & Service",
    "wof:placetype":"venue"
},
  "geometry": {"coordinates":[-75.25391500000001,40.403597],"type":"Point"}
}