{
  "type": "Feature",
  "properties": {
    "addr:full":"369 Upland Way Drexel Hill PA 19026",
    "addr:housenumber":"369",
    "addr:postcode":"19026",
    "addr:street":"Upland Way",
    "iso:country":"US",
    "sg:address":"369 Upland Way",
    "sg:city":"Drexel Hill",
    "sg:classifiers":[
        {
            "category":"Utilities",
            "subcategory":"Telephone",
            "type":"Services"
        }
    ],
    "sg:phone":"+1   ",
    "sg:postcode":"19026",
    "sg:province":"PA",
    "sg:tags":[
        "communications"
    ],
    "wof:name":"Girl Science Assoc",
    "wof:placetype":"venue"
},
  "geometry": {"coordinates":[-75.2885,39.948349],"type":"Point"}
}