{
  "type": "Feature",
  "properties": {
    "iso:country":"US",
    "sg:address":"7 Petroleum St",
    "sg:city":"Oil City",
    "sg:classifiers":[
        {
            "category":"Health Services",
            "subcategory":"Clinic",
            "type":"Services"
        }
    ],
    "sg:phone":"+1   ",
    "sg:postcode":"16301",
    "sg:province":"PA",
    "sg:tags":[
        "specialty",
        "outpatient"
    ],
    "wof:name":"U P M C Northwest",
    "wof:placetype":"venue"
},
  "geometry": {"coordinates":[-79.712407,41.429047],"type":"Point"}
}