{
  "type": "Feature",
  "properties": {
    "iso:country":"US",
    "sg:address":"936 N Chester Rd",
    "sg:city":"West Chester",
    "sg:classifiers":[
        {
            "category":"Retail",
            "subcategory":"Repair Shop",
            "type":"Services"
        }
    ],
    "sg:phone":"+1   ",
    "sg:postcode":"19380",
    "sg:province":"PA",
    "sg:tags":[
        "cleaning"
    ],
    "wof:name":"Executive Residential Services",
    "wof:placetype":"venue"
},
  "geometry": {"coordinates":[-75.546548,39.999819],"type":"Point"}
}