{
  "type": "Feature",
  "properties": {
    "iso:country":"US",
    "sg:address":"5850 Meridian Rd",
    "sg:city":"Gibsonia",
    "sg:classifiers":[
        {
            "category":"Professional",
            "subcategory":"Detective & Security Services",
            "type":"Services"
        },
        {
            "category":"Professional",
            "subcategory":"Business Services",
            "type":"Services"
        }
    ],
    "sg:phone":"+1 724 443 6453",
    "sg:postcode":"15044",
    "sg:province":"PA",
    "sg:tags":[
        "information",
        "bureau",
        "public",
        "notary"
    ],
    "wof:name":"Zenewicz Notary Service",
    "wof:placetype":"venue"
},
  "geometry": {"coordinates":[-79.959507,40.652467],"type":"Point"}
}