{
  "type": "Feature",
  "properties": {
    "iso:country":"US",
    "sg:address":"737 Water St",
    "sg:city":"Indiana",
    "sg:classifiers":[
        {
            "category":"Professional",
            "subcategory":"Lawyer & Legal Services",
            "type":"Services"
        }
    ],
    "sg:phone":"+1 724 349 8588",
    "sg:postcode":"15701",
    "sg:province":"PA",
    "sg:tags":[
        "attorney"
    ],
    "wof:name":"Dougherty Law Offices",
    "wof:placetype":"venue"
},
  "geometry": {"coordinates":[-79.15361799999999,40.624394],"type":"Point"}
}