{
  "type": "Feature",
  "properties": {
    "iso:country":"US",
    "sg:address":"100 N Meadows Dr",
    "sg:city":"Wexford",
    "sg:classifiers":[
        {
            "category":"Home & Garden",
            "subcategory":"Household Appliances",
            "type":"Retail Goods"
        }
    ],
    "sg:phone":"+1 724 934 1466",
    "sg:postcode":"15090",
    "sg:province":"PA",
    "sg:tags":[
        "repair"
    ],
    "wof:name":"Sears Product Services",
    "wof:placetype":"venue"
},
  "geometry": {"coordinates":[-80.0569,40.612202],"type":"Point"}
}