{
  "type": "Feature",
  "properties": {
    "addr:full":"482 W 8 1/2 St Bloomsburg PA 17815",
    "addr:housenumber":"482;8 1 / 2",
    "addr:postcode":"17815",
    "addr:street":"W;St",
    "iso:country":"US",
    "sg:address":"482 W 8 1/2 St",
    "sg:city":"Bloomsburg",
    "sg:classifiers":[
        {
            "category":"Shopping",
            "subcategory":"Clothing, Apparel, & Fashions",
            "type":"Retail Goods"
        },
        {
            "category":"Shopping",
            "type":"Retail Goods"
        }
    ],
    "sg:phone":"+1 570 784 6185",
    "sg:postcode":"17815",
    "sg:province":"PA",
    "sg:tags":[
        "item",
        "boutique",
        "clothing",
        "store"
    ],
    "wof:name":"Que Pasa",
    "wof:placetype":"venue"
},
  "geometry": {"coordinates":[-76.45876800000001,40.992978],"type":"Point"}
}