{
  "type": "Feature",
  "properties": {
    "iso:country":"US",
    "sg:address":"1201 S 56th St",
    "sg:city":"Philadelphia",
    "sg:classifiers":[
        {
            "category":"Personal",
            "subcategory":"Barber",
            "type":"Services"
        }
    ],
    "sg:phone":"+1 215 472 9552",
    "sg:postcode":"19143",
    "sg:province":"PA",
    "wof:name":"Wyche Barber Shop",
    "wof:placetype":"venue"
},
  "geometry": {"coordinates":[-75.231824,39.942964],"type":"Point"}
}