{
  "type": "Feature",
  "properties": {
    "addr:full":"1 W Market St Blairsville PA 15717",
    "addr:housenumber":"1",
    "addr:postcode":"15717",
    "addr:street":"W Market St",
    "iso:country":"US",
    "sg:address":"1 W Market St",
    "sg:city":"Blairsville",
    "sg:classifiers":[
        {
            "category":"Retail",
            "subcategory":"Auto Repair",
            "type":"Services"
        }
    ],
    "sg:phone":"+1   ",
    "sg:postcode":"15717",
    "sg:province":"PA",
    "sg:tags":[
        "general"
    ],
    "wof:name":"Jim Loucks Auto Repair",
    "wof:placetype":"venue"
},
  "geometry": {"coordinates":[-79.264573,40.430828],"type":"Point"}
}