{
  "type": "Feature",
  "properties": {
    "iso:country":"US",
    "sg:address":"37 Cardinal Dr",
    "sg:city":"Hanover",
    "sg:classifiers":[
        {
            "category":"Banks & Credit Unions",
            "subcategory":"Bank",
            "type":"Services"
        }
    ],
    "sg:phone":"+1 717 630 1283",
    "sg:postcode":"17331",
    "sg:province":"PA",
    "sg:tags":[
        "loan",
        "real estate"
    ],
    "wof:name":"Mortgage One",
    "wof:placetype":"venue"
},
  "geometry": {"coordinates":[-76.96542599999999,39.77097],"type":"Point"}
}