{
  "type": "Feature",
  "properties": {
    "iso:country":"US",
    "sg:address":"1470 S 52nd St",
    "sg:city":"Philadelphia",
    "sg:classifiers":[
        {
            "category":"Professional",
            "subcategory":"Accounting & Tax Preparation",
            "type":"Services"
        }
    ],
    "sg:phone":"+1   ",
    "sg:postcode":"19143",
    "sg:province":"PA",
    "wof:name":"Vance & Associates CPA",
    "wof:placetype":"venue"
},
  "geometry": {"coordinates":[-75.21776800000001,39.939539],"type":"Point"}
}