{
  "type": "Feature",
  "properties": {
    "iso:country":"US",
    "sg:address":"603 Charles St",
    "sg:city":"Lebanon",
    "sg:classifiers":[
        {
            "category":"Manufacturing",
            "subcategory":"Printing",
            "type":"Manufacturing & Wholesale Goods"
        }
    ],
    "sg:phone":"+1 717 272 9442",
    "sg:postcode":"17042",
    "sg:province":"PA",
    "sg:tags":[
        "publisher",
        "book"
    ],
    "wof:name":"Applied Arts Publishers Inc",
    "wof:placetype":"venue"
},
  "geometry": {"coordinates":[-76.37432200000001,40.315862],"type":"Point"}
}