{
  "type": "Feature",
  "properties": {
    "addr:full":"1000 Oley St Reading PA 19604",
    "addr:housenumber":"1000",
    "addr:postcode":"19604",
    "addr:street":"Oley St",
    "iso:country":"US",
    "sg:address":"1000 Oley St",
    "sg:city":"Reading",
    "sg:classifiers":[
        {
            "category":"Food & Beverages",
            "subcategory":"Groceries & Convenience Stores",
            "type":"Retail Goods"
        }
    ],
    "sg:phone":"+1 610 208 0737",
    "sg:postcode":"19604",
    "sg:province":"PA",
    "sg:tags":[
        "grocer"
    ],
    "wof:name":"B & N Grocery Store",
    "wof:placetype":"venue"
},
  "geometry": {"coordinates":[-75.917306,40.345825],"type":"Point"}
}