{
  "type": "Feature",
  "properties": {
    "addr:full":"172 W Crawford Ave Connellsville PA 15425",
    "addr:housenumber":"172",
    "addr:postcode":"15425",
    "addr:street":"W Crawford Ave",
    "iso:country":"US",
    "sg:address":"172 W Crawford Ave",
    "sg:city":"Connellsville",
    "sg:classifiers":[
        {
            "category":"Banks & Credit Unions",
            "subcategory":"Bank",
            "type":"Services"
        }
    ],
    "sg:phone":"+1   ",
    "sg:postcode":"15425",
    "sg:province":"PA",
    "sg:tags":[
        "mortgage"
    ],
    "wof:name":"Peoples Equity Mortgage Inc",
    "wof:placetype":"venue"
},
  "geometry": {"coordinates":[-79.59126500000001,40.017496],"type":"Point"}
}