{
  "type": "Feature",
  "properties": {
    "addr:full":"583 Miller Blvd Mechanicsburg PA 17055",
    "addr:housenumber":"583",
    "addr:postcode":"17055",
    "addr:street":"Miller Blvd",
    "iso:country":"US",
    "sg:address":"583 Miller Blvd",
    "sg:city":"Mechanicsburg",
    "sg:classifiers":[
        {
            "category":"Autos & Motor Vehicles",
            "subcategory":"Automobile Sales",
            "type":"Retail Goods"
        }
    ],
    "sg:phone":"+1 717 249 1183",
    "sg:postcode":"17055",
    "sg:province":"PA",
    "sg:tags":[
        "car",
        "used",
        "dealer"
    ],
    "wof:name":"Sheriff's Auto Sales",
    "wof:placetype":"venue"
},
  "geometry": {"coordinates":[-77.06137,40.142054],"type":"Point"}
}