{
  "type": "Feature",
  "properties": {
    "iso:country":"US",
    "sg:address":"709 Foresman St",
    "sg:city":"Williamsport",
    "sg:classifiers":[
        {
            "category":"Government",
            "subcategory":"Police Station",
            "type":"Public Place"
        }
    ],
    "sg:phone":"+1 570 326 5277",
    "sg:postcode":"17701",
    "sg:province":"PA",
    "sg:tags":[
        "department"
    ],
    "wof:name":"Williamsport Police Station",
    "wof:placetype":"venue"
},
  "geometry": {"coordinates":[-77.068085,41.235093],"type":"Point"}
}