{
  "type": "Feature",
  "properties": {
    "addr:full":"2250 Hickory Rd Plymouth Meeting PA 19462",
    "addr:housenumber":"2250",
    "addr:postcode":"19462",
    "addr:street":"Hickory Rd",
    "iso:country":"US",
    "sg:address":"2250 Hickory Rd",
    "sg:city":"Plymouth Meeting",
    "sg:classifiers":[
        {
            "category":"Professional",
            "subcategory":"Advertising",
            "type":"Services"
        }
    ],
    "sg:phone":"+1 610 260 9800",
    "sg:postcode":"19462",
    "sg:province":"PA",
    "sg:tags":[
        "counselor"
    ],
    "sg:website":"www.rtbadv.com",
    "wof:name":"R T & B Inc",
    "wof:placetype":"venue"
},
  "geometry": {"coordinates":[-75.284638,40.117892],"type":"Point"}
}