{
  "type": "Feature",
  "properties": {
    "iso:country":"US",
    "sg:address":"1438 Laclair Ave",
    "sg:city":"Swissvale",
    "sg:classifiers":[
        {
            "category":"Retail",
            "subcategory":"Laundry & Dry Cleaning",
            "type":"Services"
        }
    ],
    "sg:phone":"+1 412 241 4711",
    "sg:postcode":"15218",
    "sg:province":"PA",
    "sg:tags":[
        "cleaners"
    ],
    "wof:name":"De Luca Cleaners",
    "wof:placetype":"venue"
},
  "geometry": {"coordinates":[-79.893472,40.428411],"type":"Point"}
}