{
  "type": "Feature",
  "properties": {
    "addr:full":"2305 Versailles Ave Mckeesport PA 15132",
    "addr:housenumber":"2305",
    "addr:postcode":"15132",
    "addr:street":"Versailles Ave",
    "iso:country":"US",
    "sg:address":"2305 Versailles Ave",
    "sg:city":"Mckeesport",
    "sg:classifiers":[
        {
            "category":"Restaurant",
            "type":"Food & Drink"
        }
    ],
    "sg:menulink":"http://www.allmenus.com/pa/mckeesport/286489-broadway-pizza/menu/",
    "sg:phone":"+1 412 673 6928",
    "sg:postcode":"15132",
    "sg:province":"PA",
    "sg:tags":[
        "american",
        "pizza"
    ],
    "wof:name":"Broadway Pizza",
    "wof:placetype":"venue"
},
  "geometry": {"coordinates":[-79.849211,40.345837],"type":"Point"}
}