{
  "type": "Feature",
  "properties": {
    "iso:country":"US",
    "sg:address":"1921 Lincoln Hwy E",
    "sg:city":"Lancaster",
    "sg:classifiers":[
        {
            "category":"Autos & Motor Vehicles",
            "subcategory":"Auto Supplies",
            "type":"Retail Goods"
        }
    ],
    "sg:phone":"+1 717 299 1980",
    "sg:postcode":"17602",
    "sg:province":"PA",
    "sg:tags":[
        "repair"
    ],
    "wof:name":"Autorageous Auto Customizing",
    "wof:placetype":"venue"
},
  "geometry": {"coordinates":[-76.24741299999999,40.033557],"type":"Point"}
}