{
  "type": "Feature",
  "properties": {
    "addr:full":"680 Middletown Blvd Langhorne PA 19047",
    "addr:housenumber":"680",
    "addr:postcode":"19047",
    "addr:street":"Middletown Blvd",
    "iso:country":"US",
    "sg:address":"680 Middletown Blvd",
    "sg:city":"Langhorne",
    "sg:classifiers":[
        {
            "category":"Professional",
            "subcategory":"Lawyer & Legal Services",
            "type":"Services"
        }
    ],
    "sg:phone":"+1 215 478 6468",
    "sg:postcode":"19047",
    "sg:province":"PA",
    "sg:tags":[
        "attorney",
        "law",
        "business",
        "family",
        "corporation",
        "partnership",
        "planning",
        "estate",
        "criminal"
    ],
    "sg:website":"http://www.begleycarlin.com",
    "wof:name":"Begley, Carlin & Mandio",
    "wof:placetype":"venue"
},
  "geometry": {"coordinates":[-74.877225,40.180383],"type":"Point"}
}