{
  "type": "Feature",
  "properties": {
    "iso:country":"US",
    "sg:address":"982 Swayze Ave",
    "sg:city":"Washington Crossing",
    "sg:classifiers":[
        {
            "category":"Building & Trades",
            "subcategory":"Landscaping Services",
            "type":"Services"
        }
    ],
    "sg:phone":"+1   ",
    "sg:postcode":"18977",
    "sg:province":"PA",
    "sg:tags":[
        "real estate"
    ],
    "wof:name":"Riverview Lawn Landscape",
    "wof:placetype":"venue"
},
  "geometry": {"coordinates":[-74.86052100000001,40.280484],"type":"Point"}
}