{
  "type": "Feature",
  "properties": {
    "iso:country":"US",
    "sg:address":"2987 Babcock Blvd",
    "sg:city":"Pittsburgh",
    "sg:classifiers":[
        {
            "category":"Building & Trades",
            "subcategory":"Electrical",
            "type":"Services"
        },
        {
            "category":"Communications",
            "type":"Services"
        }
    ],
    "sg:phone":"+1 412 931 4408",
    "sg:postcode":"15237",
    "sg:province":"PA",
    "sg:tags":[
        "electrical",
        "merchandise",
        "contractor"
    ],
    "wof:name":"Advanced Communications Co",
    "wof:placetype":"venue"
},
  "geometry": {"coordinates":[-80.006863,40.514372],"type":"Point"}
}