{
  "type": "Feature",
  "properties": {
    "iso:country":"US",
    "sg:address":"33 S Central Ave",
    "sg:city":"Canonsburg",
    "sg:classifiers":[
        {
            "category":"Building & Trades",
            "subcategory":"Plumbing",
            "type":"Services"
        }
    ],
    "sg:phone":"+1 724 743 4448",
    "sg:postcode":"15317",
    "sg:province":"PA",
    "sg:tags":[
        "contractor"
    ],
    "wof:name":"Mc Murray Cooling & Heating",
    "wof:placetype":"venue"
},
  "geometry": {"coordinates":[-80.18611900000001,40.257906],"type":"Point"}
}