{
  "type": "Feature",
  "properties": {
    "iso:country":"US",
    "sg:address":"25 N Main St",
    "sg:city":"Doylestown",
    "sg:classifiers":[
        {
            "category":"Professional",
            "subcategory":"Lawyer & Legal Services",
            "type":"Services"
        }
    ],
    "sg:phone":"+1 215 489 6160",
    "sg:postcode":"18901",
    "sg:province":"PA",
    "sg:tags":[
        "divorce",
        "law",
        "family"
    ],
    "wof:name":"Carlitz Debbie A",
    "wof:placetype":"venue"
},
  "geometry": {"coordinates":[-75.130798,40.3106],"type":"Point"}
}