{
  "type": "Feature",
  "properties": {
    "addr:full":"1650 N 55th St Philadelphia PA 19131",
    "addr:housenumber":"1650",
    "addr:postcode":"19131",
    "addr:street":"N 55Th St",
    "iso:country":"US",
    "sg:address":"1650 N 55th St",
    "sg:city":"Philadelphia",
    "sg:classifiers":[
        {
            "category":"Travel",
            "subcategory":"Travel Agent",
            "type":"Entertainment"
        }
    ],
    "sg:phone":"+1 215 475 7119",
    "sg:postcode":"19131",
    "sg:province":"PA",
    "sg:tags":[
        "agency",
        "services-commercial"
    ],
    "wof:name":"Farmer's Travel",
    "wof:placetype":"venue"
},
  "geometry": {"coordinates":[-75.232147,39.978329],"type":"Point"}
}