{
  "type": "Feature",
  "properties": {
    "addr:full":"5045 Torresdale Ave Philadelphia PA 19124",
    "addr:housenumber":"5045",
    "addr:postcode":"19124",
    "addr:street":"Torresdale Ave",
    "iso:country":"US",
    "sg:address":"5045 Torresdale Ave",
    "sg:city":"Philadelphia",
    "sg:classifiers":[
        {
            "category":"Food & Beverages",
            "subcategory":"Groceries & Convenience Stores",
            "type":"Retail Goods"
        }
    ],
    "sg:phone":"+1   ",
    "sg:postcode":"19124",
    "sg:province":"PA",
    "wof:name":"D & P Grocery",
    "wof:placetype":"venue"
},
  "geometry": {"coordinates":[-75.07201999999999,40.01273],"type":"Point"}
}