{
  "type": "Feature",
  "properties": {
    "addr:full":"2 Meetinghouse Rd Hatboro PA 19040",
    "addr:housenumber":"2",
    "addr:postcode":"19040",
    "addr:street":"Meetinghouse Rd",
    "iso:country":"US",
    "sg:address":"2 Meetinghouse Rd",
    "sg:city":"Hatboro",
    "sg:classifiers":[
        {
            "category":"Health Services",
            "subcategory":"Health Practitioner",
            "type":"Services"
        }
    ],
    "sg:phone":"+1   ",
    "sg:postcode":"19040",
    "sg:province":"PA",
    "wof:name":"Psychic World By Helen",
    "wof:placetype":"venue"
},
  "geometry": {"coordinates":[-75.11929499999999,40.194542],"type":"Point"}
}