{
  "type": "Feature",
  "properties": {
    "iso:country":"US",
    "sg:address":"213 Old Kennett Rd",
    "sg:city":"Kennett Square",
    "sg:classifiers":[
        {
            "category":"Professional",
            "subcategory":"Business Services",
            "type":"Services"
        }
    ],
    "sg:phone":"+1   ",
    "sg:postcode":"19348",
    "sg:province":"PA",
    "wof:name":"Luara Nicol",
    "wof:placetype":"venue"
},
  "geometry": {"coordinates":[-75.68805,39.826417],"type":"Point"}
}