{
  "type": "Feature",
  "properties": {
    "iso:country":"US",
    "sg:address":"1 Forever Dr",
    "sg:city":"Hollidaysburg",
    "sg:classifiers":[
        {
            "category":"Communications",
            "subcategory":"Radio Station",
            "type":"Services"
        }
    ],
    "sg:phone":"+1   ",
    "sg:postcode":"16648",
    "sg:province":"PA",
    "sg:tags":[
        "broadcast"
    ],
    "wof:name":"Waly Radio 1039",
    "wof:placetype":"venue"
},
  "geometry": {"coordinates":[-78.395076,40.454052],"type":"Point"}
}