{
  "type": "Feature",
  "properties": {
    "iso:country":"US",
    "sg:address":"6724 N Broad St",
    "sg:city":"Philadelphia",
    "sg:classifiers":[
        {
            "category":"Personal",
            "subcategory":"Beauty Salon",
            "type":"Services"
        }
    ],
    "sg:phone":"+1 215 927 5079",
    "sg:postcode":"19126",
    "sg:province":"PA",
    "sg:website":"http://www.regiscorp.com",
    "wof:name":"Shear Pleasure",
    "wof:placetype":"venue"
},
  "geometry": {"coordinates":[-75.141077,40.055535],"type":"Point"}
}