{
  "type": "Feature",
  "properties": {
    "iso:country":"US",
    "sg:address":"5536 Bryant St",
    "sg:city":"Pittsburgh",
    "sg:classifiers":[
        {
            "category":"Shopping",
            "subcategory":"Gifts & Souvenirs",
            "type":"Retail Goods"
        }
    ],
    "sg:phone":"+1 412 661 1498",
    "sg:postcode":"15206",
    "sg:province":"PA",
    "sg:tags":[
        "shop"
    ],
    "wof:name":"Macondo Imports",
    "wof:placetype":"venue"
},
  "geometry": {"coordinates":[-79.92456900000001,40.477505],"type":"Point"}
}