{
  "type": "Feature",
  "properties": {
    "addr:full":"120 Porter Rd Belle Vernon PA 15012",
    "addr:housenumber":"120",
    "addr:postcode":"15012",
    "addr:street":"Porter Rd",
    "iso:country":"US",
    "sg:address":"120 Porter Rd",
    "sg:city":"Belle Vernon",
    "sg:classifiers":[
        {
            "category":"Professional",
            "type":"Services"
        }
    ],
    "sg:phone":"+1   ",
    "sg:postcode":"15012",
    "sg:province":"PA",
    "wof:name":"Amanda Houseman",
    "wof:placetype":"venue"
},
  "geometry": {"coordinates":[-79.771472,40.14512],"type":"Point"}
}