{
  "type": "Feature",
  "properties": {
    "iso:country":"US",
    "sg:address":"88 Ironwood Rd",
    "sg:city":"Levittown",
    "sg:classifiers":[
        {
            "category":"Wholesale",
            "subcategory":"Electrical",
            "type":"Manufacturing & Wholesale Goods"
        }
    ],
    "sg:phone":"+1 215 946 8364",
    "sg:postcode":"19057",
    "sg:province":"PA",
    "sg:tags":[
        "alarm",
        "burglar",
        "system"
    ],
    "wof:name":"Crime Stopper",
    "wof:placetype":"venue"
},
  "geometry": {"coordinates":[-74.857769,40.150231],"type":"Point"}
}