{
  "type": "Feature",
  "properties": {
    "addr:full":"792 Kiski Park Dr Apollo PA 15613",
    "addr:housenumber":"792",
    "addr:postcode":"15613",
    "addr:street":"Kiski Park Dr",
    "iso:country":"US",
    "sg:address":"792 Kiski Park Dr",
    "sg:city":"Apollo",
    "sg:classifiers":[
        {
            "category":"Building & Trades",
            "subcategory":"Construction",
            "type":"Services"
        }
    ],
    "sg:phone":"+1   ",
    "sg:postcode":"15613",
    "sg:province":"PA",
    "sg:tags":[
        "floor",
        "laying",
        "contractor"
    ],
    "wof:name":"Sals Hardwoods",
    "wof:placetype":"venue"
},
  "geometry": {"coordinates":[-79.602772,40.528686],"type":"Point"}
}