{
  "type": "Feature",
  "properties": {
    "iso:country":"US",
    "sg:address":"130 Fairfield Ln",
    "sg:city":"Wayne",
    "sg:classifiers":[
        {
            "category":"Home & Garden",
            "subcategory":"Home Furnishings",
            "type":"Retail Goods"
        }
    ],
    "sg:phone":"+1   ",
    "sg:postcode":"19087",
    "sg:province":"PA",
    "wof:name":"Araksi Custom Lamp Shades",
    "wof:placetype":"venue"
},
  "geometry": {"coordinates":[-75.40271,40.046683],"type":"Point"}
}