{
  "type": "Feature",
  "properties": {
    "addr:full":"236 E Market St Clearfield PA 16830",
    "addr:housenumber":"236",
    "addr:postcode":"16830",
    "addr:street":"E Market St",
    "iso:country":"US",
    "sg:address":"236 E Market St",
    "sg:city":"Clearfield",
    "sg:classifiers":[
        {
            "category":"Home & Garden",
            "subcategory":"Furniture",
            "type":"Retail Goods"
        }
    ],
    "sg:phone":"+1 814 762 8627",
    "sg:postcode":"16830",
    "sg:province":"PA",
    "wof:name":"Henry & Co",
    "wof:placetype":"venue"
},
  "geometry": {"coordinates":[-78.437549,41.022151],"type":"Point"}
}