{
  "type": "Feature",
  "properties": {
    "iso:country":"US",
    "sg:address":"625 Cherry St",
    "sg:city":"Reading",
    "sg:classifiers":[
        {
            "category":"Government",
            "subcategory":"Office",
            "type":"Public Place"
        }
    ],
    "sg:phone":"+1   ",
    "sg:postcode":"19602",
    "sg:province":"PA",
    "sg:tags":[
        "appeal",
        "court"
    ],
    "wof:name":"Unemploymnt Compensatn Ref Ofc",
    "wof:placetype":"venue"
},
  "geometry": {"coordinates":[-75.924497,40.33443],"type":"Point"}
}