{
  "type": "Feature",
  "properties": {
    "iso:country":"US",
    "sg:address":"2500 S Camac St",
    "sg:city":"Philadelphia",
    "sg:classifiers":[
        {
            "category":"Social Services",
            "subcategory":"Child Care",
            "type":"Services"
        }
    ],
    "sg:phone":"+1 215 465 3668",
    "sg:postcode":"19148",
    "sg:province":"PA",
    "sg:tags":[
        "day"
    ],
    "wof:name":"Little Foot Day Care",
    "wof:placetype":"venue"
},
  "geometry": {"coordinates":[-75.1679,39.918701],"type":"Point"}
}