{
  "type": "Feature",
  "properties": {
    "addr:full":"227 E Main St Carnegie PA 15106",
    "addr:housenumber":"227",
    "addr:postcode":"15106",
    "addr:street":"E Main St",
    "iso:country":"US",
    "sg:address":"227 E Main St",
    "sg:city":"Carnegie",
    "sg:classifiers":[
        {
            "category":"Insurance",
            "subcategory":"Insurance Agent",
            "type":"Services"
        }
    ],
    "sg:phone":"+1   ",
    "sg:postcode":"15106",
    "sg:province":"PA",
    "wof:name":"Erie Insurance",
    "wof:placetype":"venue"
},
  "geometry": {"coordinates":[-80.085309,40.408385],"type":"Point"}
}