{
  "type": "Feature",
  "properties": {
    "iso:country":"US",
    "sg:address":"3821 Market St",
    "sg:city":"Camp Hill",
    "sg:classifiers":[
        {
            "category":"Banks & Credit Unions",
            "subcategory":"Bank",
            "type":"Services"
        }
    ],
    "sg:phone":"+1 717 731 8112",
    "sg:postcode":"17011",
    "sg:province":"PA",
    "wof:name":"May Robt Ins",
    "wof:placetype":"venue"
},
  "geometry": {"coordinates":[-76.949402,40.238499],"type":"Point"}
}