{
  "type": "Feature",
  "properties": {
    "iso:country":"US",
    "sg:address":"47 Treeline Dr",
    "sg:city":"Pen Argyl",
    "sg:classifiers":[
        {
            "category":"Real Estate",
            "subcategory":"Real Estate Agent",
            "type":"Services"
        }
    ],
    "sg:phone":"+1 610 252 1712",
    "sg:postcode":"18072",
    "sg:province":"PA",
    "wof:name":"Diane M Mattes Real Estate",
    "wof:placetype":"venue"
},
  "geometry": {"coordinates":[-75.230368,40.840373],"type":"Point"}
}