{
  "type": "Feature",
  "properties": {
    "addr:full":"Swedes Square Shopping Center 101 Germantown Pike Norristown PA 19401",
    "addr:housenumber":"101",
    "addr:postcode":"19401",
    "addr:street":"Germantown Pike",
    "iso:country":"US",
    "sg:address":"Swedes Square Shopping Center 101 Germantown Pike",
    "sg:city":"Norristown",
    "sg:classifiers":[
        {
            "category":"Coffee & Tea",
            "type":"Food & Drink"
        },
        {
            "category":"Food & Beverages",
            "subcategory":"Bakery",
            "type":"Retail Goods"
        },
        {
            "category":"Bakery",
            "type":"Food & Drink"
        }
    ],
    "sg:phone":"+1 610 277 6550",
    "sg:postcode":"19401",
    "sg:province":"PA",
    "sg:tags":[
        "sandwich"
    ],
    "sg:website":"www.panera.com",
    "wof:name":"Panera Bread",
    "wof:placetype":"venue"
},
  "geometry": {"coordinates":[-75.318573,40.145308],"type":"Point"}
}