{
  "type": "Feature",
  "properties": {
    "iso:country":"US",
    "sg:address":"104 Avon Rd",
    "sg:city":"Narberth",
    "sg:classifiers":[
        {
            "category":"Shopping",
            "subcategory":"Used Merchandise",
            "type":"Retail Goods"
        }
    ],
    "sg:phone":"+1 610 667 6550",
    "sg:postcode":"19072",
    "sg:province":"PA",
    "wof:name":"Microcom Soho",
    "wof:placetype":"venue"
},
  "geometry": {"coordinates":[-75.25627900000001,40.005218],"type":"Point"}
}