{
  "type": "Feature",
  "properties": {
    "iso:country":"US",
    "sg:address":"115 E Main St",
    "sg:city":"Plymouth",
    "sg:classifiers":[
        {
            "category":"Personal",
            "subcategory":"Beauty Salon",
            "type":"Services"
        }
    ],
    "sg:phone":"+1 570 779 9818",
    "sg:postcode":"18651",
    "sg:province":"PA",
    "sg:tags":[
        "shop"
    ],
    "wof:name":"Kathy K's Mane Street Salon",
    "wof:placetype":"venue"
},
  "geometry": {"coordinates":[-75.941053,41.24213],"type":"Point"}
}