{
  "type": "Feature",
  "properties": {
    "addr:full":"73 Chestnut Rd Paoli PA 19301",
    "addr:housenumber":"73",
    "addr:postcode":"19301",
    "addr:street":"Chestnut Rd",
    "iso:country":"US",
    "sg:address":"73 Chestnut Rd",
    "sg:city":"Paoli",
    "sg:classifiers":[
        {
            "category":"Professional",
            "subcategory":"Lawyer & Legal Services",
            "type":"Services"
        }
    ],
    "sg:phone":"+1 610 725 8660",
    "sg:postcode":"19301",
    "sg:province":"PA",
    "sg:tags":[
        "attorney"
    ],
    "wof:name":"Richard L Switzer",
    "wof:placetype":"venue"
},
  "geometry": {"coordinates":[-75.480189,40.041732],"type":"Point"}
}