{
  "type": "Feature",
  "properties": {
    "iso:country":"US",
    "sg:address":"636 McKean Ave",
    "sg:city":"Charleroi",
    "sg:classifiers":[
        {
            "category":"Organizations",
            "subcategory":"Religious Organization",
            "type":"Services"
        }
    ],
    "sg:phone":"+1   ",
    "sg:postcode":"15022",
    "sg:province":"PA",
    "wof:name":"Mon Valley Christian & Mission",
    "wof:placetype":"venue"
},
  "geometry": {"coordinates":[-79.899128,40.139865],"type":"Point"}
}