{
  "type": "Feature",
  "properties": {
    "addr:full":"216 Sundew Ct Allentown PA 18104",
    "addr:housenumber":"216",
    "addr:postcode":"18104",
    "addr:street":"Sundew Ct",
    "iso:country":"US",
    "sg:address":"216 Sundew Ct",
    "sg:city":"Allentown",
    "sg:classifiers":[
        {
            "category":"Wholesale",
            "subcategory":"Non-durable Goods",
            "type":"Manufacturing & Wholesale Goods"
        }
    ],
    "sg:phone":"+1 610 770 7884",
    "sg:postcode":"18104",
    "sg:province":"PA",
    "sg:tags":[
        "advertising"
    ],
    "wof:name":"Stellar Promotions",
    "wof:placetype":"venue"
},
  "geometry": {"coordinates":[-75.584779,40.581184],"type":"Point"}
}