{
  "type": "Feature",
  "properties": {
    "iso:country":"US",
    "sg:address":"1103 Ferry St",
    "sg:city":"Easton",
    "sg:classifiers":[
        {
            "category":"Wholesale",
            "subcategory":"Construction Materials",
            "type":"Manufacturing & Wholesale Goods"
        }
    ],
    "sg:phone":"+1 610 923 9690",
    "sg:postcode":"18042",
    "sg:province":"PA",
    "sg:tags":[
        "tile"
    ],
    "wof:name":"B B Tiles",
    "wof:placetype":"venue"
},
  "geometry": {"coordinates":[-75.225166,40.689008],"type":"Point"}
}