{
  "type": "Feature",
  "properties": {
    "addr:full":"136 E Fayette St Uniontown PA 15401",
    "addr:housenumber":"136",
    "addr:postcode":"15401",
    "addr:street":"E Fayette St",
    "iso:country":"US",
    "sg:address":"136 E Fayette St",
    "sg:city":"Uniontown",
    "sg:classifiers":[
        {
            "category":"Health Services",
            "subcategory":"Health Practitioner",
            "type":"Services"
        }
    ],
    "sg:phone":"+1   ",
    "sg:postcode":"15401",
    "sg:province":"PA",
    "sg:tags":[
        "medical"
    ],
    "wof:name":"Foster Arvnda Bonnie W Msw Lsw",
    "wof:placetype":"venue"
},
  "geometry": {"coordinates":[-79.720508,39.896519],"type":"Point"}
}