{
  "type": "Feature",
  "properties": {
    "addr:full":"611 Main St Clarion PA 16214",
    "addr:housenumber":"611",
    "addr:postcode":"16214",
    "addr:street":"Main St",
    "iso:country":"US",
    "sg:address":"611 Main St",
    "sg:city":"Clarion",
    "sg:classifiers":[
        {
            "category":"Restaurant",
            "type":"Food & Drink"
        }
    ],
    "sg:phone":"+1 814 227 2688",
    "sg:postcode":"16214",
    "sg:province":"PA",
    "sg:tags":[
        "shop",
        "coffee",
        "eating"
    ],
    "wof:name":"Michelle's Cafe",
    "wof:placetype":"venue"
},
  "geometry": {"coordinates":[-79.38371600000001,41.213992],"type":"Point"}
}