{
  "type": "Feature",
  "properties": {
    "iso:country":"US",
    "sg:address":"1236 Boden Pl",
    "sg:city":"Fort Washington",
    "sg:classifiers":[
        {
            "category":"Building & Trades",
            "subcategory":"Construction",
            "type":"Services"
        }
    ],
    "sg:phone":"+1   ",
    "sg:postcode":"19034",
    "sg:province":"PA",
    "sg:tags":[
        "contractor"
    ],
    "wof:name":"Exclusive Dsigns By Stravinski",
    "wof:placetype":"venue"
},
  "geometry": {"coordinates":[-75.205358,40.137232],"type":"Point"}
}