{
  "type": "Feature",
  "properties": {
    "iso:country":"US",
    "sg:address":"286 Reath Rd",
    "sg:city":"Kirkwood",
    "sg:classifiers":[
        {
            "category":"Manufacturing",
            "subcategory":"Food",
            "type":"Manufacturing & Wholesale Goods"
        }
    ],
    "sg:phone":"+1   ",
    "sg:postcode":"17536",
    "sg:province":"PA",
    "sg:tags":[
        "cheese",
        "mfg"
    ],
    "wof:name":"Oak Shade Cheese",
    "wof:placetype":"venue"
},
  "geometry": {"coordinates":[-76.09934199999999,39.82565],"type":"Point"}
}