{
  "type": "Feature",
  "properties": {
    "addr:full":"Trenton Rd Levittown PA 19055",
    "addr:postcode":"19055",
    "addr:street":"Trenton Rd Levittown",
    "iso:country":"US",
    "sg:address":"Trenton Rd",
    "sg:city":"Levittown",
    "sg:classifiers":[
        {
            "category":"Education",
            "subcategory":"Preschool",
            "type":"Public Place"
        },
        {
            "category":"Education",
            "subcategory":"School",
            "type":"Public Place"
        }
    ],
    "sg:phone":"+1 215 945 1866",
    "sg:postcode":"19055",
    "sg:province":"PA",
    "sg:tags":[
        "elementary"
    ],
    "wof:name":"Queen of the Universe School",
    "wof:placetype":"venue"
},
  "geometry": {"coordinates":[-74.835503,40.147202],"type":"Point"}
}