{
  "type": "Feature",
  "properties": {
    "iso:country":"US",
    "sg:address":"175 Titus Ave Ste 200",
    "sg:city":"Warrington",
    "sg:classifiers":[
        {
            "category":"Building & Trades",
            "subcategory":"Construction",
            "type":"Services"
        }
    ],
    "sg:phone":"+1 215 343 7040",
    "sg:postcode":"18976",
    "sg:province":"PA",
    "sg:tags":[
        "contractor"
    ],
    "wof:name":"Bostock Company Inc",
    "wof:placetype":"venue"
},
  "geometry": {"coordinates":[-75.14391999999999,40.219151],"type":"Point"}
}