{
  "type": "Feature",
  "properties": {
    "iso:country":"US",
    "sg:address":"352 W Chester Rd",
    "sg:city":"West Chester",
    "sg:classifiers":[
        {
            "category":"Building & Trades",
            "subcategory":"Plumbing",
            "type":"Services"
        }
    ],
    "sg:phone":"+1 610 696 3080",
    "sg:postcode":"19382",
    "sg:province":"PA",
    "sg:tags":[
        "septic"
    ],
    "wof:name":"A Anchor Toilets Portable",
    "wof:placetype":"venue"
},
  "geometry": {"coordinates":[-75.544876,39.910741],"type":"Point"}
}