{
  "type": "Feature",
  "properties": {
    "addr:full":"3159 Kensington Ave Philadelphia PA 19134",
    "addr:housenumber":"3159",
    "addr:postcode":"19134",
    "addr:street":"Kensington Ave",
    "iso:country":"US",
    "sg:address":"3159 Kensington Ave",
    "sg:city":"Philadelphia",
    "sg:classifiers":[
        {
            "category":"Professional",
            "subcategory":"Accounting & Tax Preparation",
            "type":"Services"
        }
    ],
    "sg:phone":"+1 215 425 1654",
    "sg:postcode":"19134",
    "sg:province":"PA",
    "sg:tags":[
        "return",
        "filing"
    ],
    "sg:website":"www.hrblock.com",
    "wof:name":"H & R Block Tax Svc",
    "wof:placetype":"venue"
},
  "geometry": {"coordinates":[-75.11443800000001,39.995903],"type":"Point"}
}