{
  "type": "Feature",
  "properties": {
    "iso:country":"US",
    "sg:address":"6750 Miller Rd",
    "sg:city":"Girard",
    "sg:classifiers":[
        {
            "category":"Wholesale",
            "subcategory":"Machinery & Supplies",
            "type":"Manufacturing & Wholesale Goods"
        }
    ],
    "sg:phone":"+1 814 774 9332",
    "sg:postcode":"16417",
    "sg:province":"PA",
    "sg:tags":[
        "belt"
    ],
    "wof:name":"R L Crowe Enterprises",
    "wof:placetype":"venue"
},
  "geometry": {"coordinates":[-80.28407799999999,41.997354],"type":"Point"}
}