{
  "type": "Feature",
  "properties": {
    "iso:country":"US",
    "sg:address":"62 Robert Rd",
    "sg:city":"Ephrata",
    "sg:classifiers":[
        {
            "category":"Manufacturing",
            "subcategory":"Textiles",
            "type":"Manufacturing & Wholesale Goods"
        },
        {
            "category":"Home & Garden",
            "subcategory":"Home Furnishings",
            "type":"Retail Goods"
        }
    ],
    "sg:phone":"+1 717 336 7664",
    "sg:postcode":"17522",
    "sg:province":"PA",
    "sg:tags":[
        "c",
        "made",
        "fabric",
        "mfg",
        "curtain",
        "mill",
        "drapery",
        "cotton"
    ],
    "wof:name":"Karen Showalter Draperies",
    "wof:placetype":"venue"
},
  "geometry": {"coordinates":[-76.20084,40.198503],"type":"Point"}
}