{
  "type": "Feature",
  "properties": {
    "addr:full":"10400 Grubbs Rd Wexford PA 15090",
    "addr:housenumber":"10400",
    "addr:postcode":"15090",
    "addr:street":"Grubbs Rd",
    "iso:country":"US",
    "sg:address":"10400 Grubbs Rd",
    "sg:city":"Wexford",
    "sg:classifiers":[
        {
            "category":"Building & Trades",
            "subcategory":"Construction",
            "type":"Services"
        }
    ],
    "sg:phone":"+1   ",
    "sg:postcode":"15090",
    "sg:province":"PA",
    "sg:tags":[
        "house"
    ],
    "wof:name":"Sippel Construction Co Inc",
    "wof:placetype":"venue"
},
  "geometry": {"coordinates":[-80.03631799999999,40.606059],"type":"Point"}
}