{
  "type": "Feature",
  "properties": {
    "addr:full":"139 E. Main St. Ste 810 Carnegie PA 15106",
    "addr:housenumber":"139",
    "addr:postcode":"15106",
    "addr:street":"E. Main St. Ste 810",
    "iso:country":"US",
    "sg:address":"139 E. Main St. Ste 810",
    "sg:city":"Carnegie",
    "sg:classifiers":[
        {
            "category":"Professional",
            "subcategory":"Advertising",
            "type":"Services"
        }
    ],
    "sg:phone":"+1 412 567 3934",
    "sg:postcode":"15106",
    "sg:province":"PA",
    "sg:tags":[
        "marketing"
    ],
    "sg:website":"www.connectedcafe.com",
    "wof:name":"Connected Cafe",
    "wof:placetype":"venue"
},
  "geometry": {"coordinates":[-80.08576600000001,40.40822],"type":"Point"}
}