{
  "type": "Feature",
  "properties": {
    "iso:country":"US",
    "sg:address":"2749 Street Rd",
    "sg:city":"Bensalem",
    "sg:classifiers":[
        {
            "category":"Personal",
            "subcategory":"Nail Salon",
            "type":"Services"
        }
    ],
    "sg:phone":"+1 215 633 1867",
    "sg:postcode":"19020",
    "sg:province":"PA",
    "wof:name":"Bensalem Nails",
    "wof:placetype":"venue"
},
  "geometry": {"coordinates":[-74.952951,40.110315],"type":"Point"}
}