{
  "type": "Feature",
  "properties": {
    "addr:full":"818 S 25th St Easton PA 18045",
    "addr:housenumber":"818",
    "addr:postcode":"18045",
    "addr:street":"S 25Th St",
    "iso:country":"US",
    "sg:address":"818 S 25th St",
    "sg:city":"Easton",
    "sg:classifiers":[
        {
            "category":"Retail",
            "subcategory":"Auto Rental",
            "type":"Services"
        }
    ],
    "sg:phone":"+1   ",
    "sg:postcode":"18045",
    "sg:province":"PA",
    "sg:tags":[
        "truck"
    ],
    "wof:name":"Ryder",
    "wof:placetype":"venue"
},
  "geometry": {"coordinates":[-75.246645,40.67753],"type":"Point"}
}