{
  "type": "Feature",
  "properties": {
    "iso:country":"US",
    "sg:address":"580 S Aiken Ave Ste 202",
    "sg:city":"Pittsburgh",
    "sg:classifiers":[
        {
            "category":"Social Services",
            "type":"Services"
        }
    ],
    "sg:phone":"+1 412 687 9775",
    "sg:postcode":"15232",
    "sg:province":"PA",
    "sg:tags":[
        "program",
        "services-information",
        "referral"
    ],
    "wof:name":"Crohn's & Colitis Foundation",
    "wof:placetype":"venue"
},
  "geometry": {"coordinates":[-79.937306,40.45382],"type":"Point"}
}