{
  "type": "Feature",
  "properties": {
    "iso:country":"US",
    "sg:address":"1579 Bethlehem Pike",
    "sg:city":"Flourtown",
    "sg:classifiers":[
        {
            "category":"Restaurant",
            "type":"Food & Drink"
        }
    ],
    "sg:phone":"+1 215 997 2650",
    "sg:postcode":"19031",
    "sg:province":"PA",
    "wof:name":"Quiznos Sub",
    "wof:placetype":"venue"
},
  "geometry": {"coordinates":[-75.213459,40.105903],"type":"Point"}
}