{
  "type": "Feature",
  "properties": {
    "iso:country":"US",
    "sg:address":"1307 Telegraph Rd",
    "sg:city":"Coatesville",
    "sg:classifiers":[
        {
            "category":"Building & Trades",
            "subcategory":"Construction",
            "type":"Services"
        }
    ],
    "sg:phone":"+1 610 384 5512",
    "sg:postcode":"19320",
    "sg:province":"PA",
    "sg:tags":[
        "paving",
        "asphalt",
        "contractor"
    ],
    "wof:name":"East Coast Asphalt Maintenance",
    "wof:placetype":"venue"
},
  "geometry": {"coordinates":[-75.88532499999999,40.047381],"type":"Point"}
}