{
  "type": "Feature",
  "properties": {
    "iso:country":"US",
    "sg:address":"26 N Brown St",
    "sg:city":"Lewistown",
    "sg:classifiers":[
        {
            "category":"Social Services",
            "type":"Services"
        }
    ],
    "sg:phone":"+1   ",
    "sg:postcode":"17044",
    "sg:province":"PA",
    "wof:name":"Mifflin-Juniata Unit",
    "wof:placetype":"venue"
},
  "geometry": {"coordinates":[-77.573525,40.598522],"type":"Point"}
}