{
  "type": "Feature",
  "properties": {
    "addr:full":"1321 Sharon New Castle Rd Farrell PA 16121",
    "addr:housenumber":"1321",
    "addr:postcode":"16121",
    "addr:street":"Sharon New Castle Rd",
    "iso:country":"US",
    "sg:address":"1321 Sharon New Castle Rd",
    "sg:city":"Farrell",
    "sg:classifiers":[
        {
            "category":"Organizations",
            "subcategory":"Community Association",
            "type":"Services"
        }
    ],
    "sg:phone":"+1   ",
    "sg:postcode":"16121",
    "sg:province":"PA",
    "wof:name":"Moose Family Ctr 55 - Farrell",
    "wof:placetype":"venue"
},
  "geometry": {"coordinates":[-80.48076399999999,41.212949],"type":"Point"}
}