{
  "type": "Feature",
  "properties": {
    "iso:country":"US",
    "sg:address":"228 Aspen Ave",
    "sg:city":"Langhorne",
    "sg:classifiers":[
        {
            "category":"Building & Trades",
            "subcategory":"Landscaping Services",
            "type":"Services"
        }
    ],
    "sg:phone":"+1 215 750 1988",
    "sg:postcode":"19047",
    "sg:province":"PA",
    "sg:tags":[
        "landscape",
        "contractor"
    ],
    "wof:name":"Aspen Lawn & Maintenance",
    "wof:placetype":"venue"
},
  "geometry": {"coordinates":[-74.937735,40.173818],"type":"Point"}
}