{
  "type": "Feature",
  "properties": {
    "iso:country":"US",
    "sg:address":"906 Ivy Ln",
    "sg:city":"Reading",
    "sg:classifiers":[
        {
            "category":"Wholesale",
            "subcategory":"Metals & Minerals",
            "type":"Manufacturing & Wholesale Goods"
        }
    ],
    "sg:phone":"+1   ",
    "sg:postcode":"19610",
    "sg:province":"PA",
    "sg:tags":[
        "center"
    ],
    "wof:name":"Hardox Corporation",
    "wof:placetype":"venue"
},
  "geometry": {"coordinates":[-75.99867399999999,40.340647],"type":"Point"}
}