{
  "type": "Feature",
  "properties": {
    "iso:country":"US",
    "sg:address":"1296 Cherrytree Rd",
    "sg:city":"Franklin",
    "sg:classifiers":[
        {
            "category":"Professional",
            "type":"Services"
        }
    ],
    "sg:phone":"+1   ",
    "sg:postcode":"16354",
    "sg:province":"PA",
    "wof:name":"Randy Doutt",
    "wof:placetype":"venue"
},
  "geometry": {"coordinates":[-79.708129,41.577989],"type":"Point"}
}