{
  "type": "Feature",
  "properties": {
    "iso:country":"US",
    "sg:address":"2485 Yellow Springs Rd",
    "sg:city":"Malvern",
    "sg:classifiers":[
        {
            "category":"Wholesale",
            "subcategory":"Machinery & Supplies",
            "type":"Manufacturing & Wholesale Goods"
        }
    ],
    "sg:phone":"+1   ",
    "sg:postcode":"19355",
    "sg:province":"PA",
    "sg:tags":[
        "pump",
        "hydraulic"
    ],
    "wof:name":"Envirotech Pumpsystems Inc",
    "wof:placetype":"venue"
},
  "geometry": {"coordinates":[-75.528978,40.073487],"type":"Point"}
}