{
  "type": "Feature",
  "properties": {
    "iso:country":"US",
    "sg:address":"133 S 7th St Frnt",
    "sg:city":"Allentown",
    "sg:classifiers":[
        {
            "category":"Professional",
            "subcategory":"Accounting & Tax Preparation",
            "type":"Services"
        }
    ],
    "sg:phone":"+1 610 434 9111",
    "sg:postcode":"18101",
    "sg:province":"PA",
    "sg:tags":[
        "accountant"
    ],
    "wof:name":"Simplex Services",
    "wof:placetype":"venue"
},
  "geometry": {"coordinates":[-75.470703,40.6003],"type":"Point"}
}