{
  "type": "Feature",
  "properties": {
    "iso:country":"US",
    "sg:address":"120 Prospect St",
    "sg:city":"Reading",
    "sg:classifiers":[
        {
            "category":"Shopping",
            "subcategory":"Pharmacy",
            "type":"Retail Goods"
        }
    ],
    "sg:phone":"+1 610 898 1341",
    "sg:postcode":"19606",
    "sg:province":"PA",
    "wof:name":"Caresite Pharmacy",
    "wof:placetype":"venue"
},
  "geometry": {"coordinates":[-75.874117,40.327199],"type":"Point"}
}