{
  "type": "Feature",
  "properties": {
    "addr:full":"1000 W View Park Dr Pittsburgh PA 15229",
    "addr:housenumber":"1000",
    "addr:postcode":"15229",
    "addr:street":"W View Park Dr",
    "iso:country":"US",
    "sg:address":"1000 W View Park Dr",
    "sg:city":"Pittsburgh",
    "sg:classifiers":[
        {
            "category":"Education",
            "subcategory":"Dance Studio",
            "type":"Public Place"
        }
    ],
    "sg:phone":"+1 412 931 3131",
    "sg:postcode":"15229",
    "sg:province":"PA",
    "sg:tags":[
        "instruction",
        "dancing"
    ],
    "wof:name":"Tammy Croftcheck Dance Ctr",
    "wof:placetype":"venue"
},
  "geometry": {"coordinates":[-80.034727,40.51669],"type":"Point"}
}