{
  "type": "Feature",
  "properties": {
    "addr:full":"210 W King St Lancaster PA 17603",
    "addr:housenumber":"210",
    "addr:postcode":"17603",
    "addr:street":"W King St",
    "iso:country":"US",
    "sg:address":"210 W King St",
    "sg:city":"Lancaster",
    "sg:classifiers":[
        {
            "category":"Restaurant",
            "type":"Food & Drink"
        }
    ],
    "sg:menulink":"http://www.allmenus.com/pa/lancaster/206146-mcdonalds/menu/",
    "sg:phone":"+1 717 299 6699",
    "sg:postcode":"17603",
    "sg:province":"PA",
    "sg:tags":[
        "burger",
        "american"
    ],
    "wof:name":"McDonald's",
    "wof:placetype":"venue"
},
  "geometry": {"coordinates":[-76.308708,40.037243],"type":"Point"}
}