{
  "type": "Feature",
  "properties": {
    "addr:full":"14300 Townsend Rd Philadelphia PA 19154",
    "addr:housenumber":"14300",
    "addr:postcode":"19154",
    "addr:street":"Townsend Rd",
    "iso:country":"US",
    "sg:address":"14300 Townsend Rd",
    "sg:city":"Philadelphia",
    "sg:classifiers":[
        {
            "category":"Transit Center",
            "subcategory":"Freight",
            "type":"Transportation"
        },
        {
            "category":"Professional",
            "subcategory":"Business Services",
            "type":"Services"
        },
        {
            "category":"Freight",
            "type":"Transportation"
        },
        {
            "category":"Government",
            "subcategory":"Post Office",
            "type":"Public Place"
        },
        {
            "category":"Taxi",
            "type":"Transportation"
        }
    ],
    "sg:phone":"+1 215 856 0914",
    "sg:postcode":"19154",
    "sg:province":"PA",
    "sg:tags":[
        "cargo",
        "courier",
        "package",
        "express",
        "shipping",
        "air",
        "delivery",
        "mail",
        "forwarding",
        "trucking"
    ],
    "wof:name":"Fedex",
    "wof:placetype":"venue"
},
  "geometry": {"coordinates":[-74.98274600000001,40.104126],"type":"Point"}
}