{
  "type": "Feature",
  "properties": {
    "iso:country":"US",
    "sg:address":"2719 Bloom Rd",
    "sg:city":"Danville",
    "sg:classifiers":[
        {
            "category":"Autos & Motor Vehicles",
            "subcategory":"Automobile Sales",
            "type":"Retail Goods"
        }
    ],
    "sg:phone":"+1 570 275 2880",
    "sg:postcode":"17821",
    "sg:province":"PA",
    "sg:tags":[
        "new",
        "car"
    ],
    "wof:name":"Danville Auto Dealer Exchange Inc",
    "wof:placetype":"venue"
},
  "geometry": {"coordinates":[-76.557751,40.969245],"type":"Point"}
}