{
  "type": "Feature",
  "properties": {
    "iso:country":"US",
    "sg:address":"1414 7th Ave",
    "sg:city":"Beaver Falls",
    "sg:classifiers":[
        {
            "category":"Shopping",
            "subcategory":"Clothing, Apparel, & Fashions",
            "type":"Retail Goods"
        }
    ],
    "sg:phone":"+1 724 891 1320",
    "sg:postcode":"15010",
    "sg:province":"PA",
    "sg:tags":[
        "sportswear"
    ],
    "wof:name":"Kenneth Morgan",
    "wof:placetype":"venue"
},
  "geometry": {"coordinates":[-80.319354,40.755822],"type":"Point"}
}