{
  "type": "Feature",
  "properties": {
    "addr:full":"3754 Bossler Rd Elizabethtown PA 17022",
    "addr:housenumber":"3754",
    "addr:postcode":"17022",
    "addr:street":"Bossler Rd",
    "iso:country":"US",
    "sg:address":"3754 Bossler Rd",
    "sg:city":"Elizabethtown",
    "sg:classifiers":[
        {
            "category":"Real Estate",
            "subcategory":"Real Estate Operator",
            "type":"Services"
        }
    ],
    "sg:phone":"+1   ",
    "sg:postcode":"17022",
    "sg:province":"PA",
    "sg:tags":[
        "property",
        "lessor"
    ],
    "wof:name":"Douglas Hawthorn",
    "wof:placetype":"venue"
},
  "geometry": {"coordinates":[-76.64428100000001,40.112904],"type":"Point"}
}