{
  "type": "Feature",
  "properties": {
    "addr:full":"9 Bon Air Dr Warminster PA 18974",
    "addr:housenumber":"9",
    "addr:postcode":"18974",
    "addr:street":"Bon Air Dr",
    "iso:country":"US",
    "sg:address":"9 Bon Air Dr",
    "sg:city":"Warminster",
    "sg:classifiers":[
        {
            "category":"Wholesale",
            "subcategory":"Machinery & Supplies",
            "type":"Manufacturing & Wholesale Goods"
        }
    ],
    "sg:phone":"+1 215 956 9650",
    "sg:postcode":"18974",
    "sg:province":"PA",
    "sg:tags":[
        "equipment",
        "industrial"
    ],
    "wof:name":"MSC Industrial Supply Co",
    "wof:placetype":"venue"
},
  "geometry": {"coordinates":[-75.09093799999999,40.189367],"type":"Point"}
}