{
  "type": "Feature",
  "properties": {
    "iso:country":"US",
    "sg:address":"160 Camp Stewart Rd",
    "sg:city":"Coatesville",
    "sg:phone":"+1 610 942 2648",
    "sg:postcode":"19320",
    "sg:province":"PA",
    "sg:tags":[
        "oil"
    ],
    "wof:name":"Snyder Petroleum Products",
    "wof:placetype":"venue"
},
  "geometry": {"coordinates":[-75.84867,40.016655],"type":"Point"}
}