{
  "type": "Feature",
  "properties": {
    "iso:country":"US",
    "sg:address":"3647 Lancaster Ave",
    "sg:city":"Philadelphia",
    "sg:classifiers":[
        {
            "category":"Restaurant",
            "type":"Food & Drink"
        }
    ],
    "sg:phone":"+1 215 387 6644",
    "sg:postcode":"19104",
    "sg:province":"PA",
    "sg:tags":[
        "commercial",
        "caterer"
    ],
    "sg:website":"www.philadelphiacatering.com",
    "wof:name":"Philadelphia Catering Co",
    "wof:placetype":"venue"
},
  "geometry": {"coordinates":[-75.194704,39.959133],"type":"Point"}
}