{
  "type": "Feature",
  "properties": {
    "iso:country":"US",
    "sg:address":"1215 Baltimore Pike",
    "sg:city":"Media",
    "sg:classifiers":[
        {
            "category":"Professional",
            "subcategory":"Advertising",
            "type":"Services"
        }
    ],
    "sg:phone":"+1 610 566 0334",
    "sg:postcode":"19063",
    "sg:province":"PA",
    "sg:tags":[
        "agency"
    ],
    "sg:website":"www.rothackeradv.com",
    "wof:name":"Rothacker Advertising & Design",
    "wof:placetype":"venue"
},
  "geometry": {"coordinates":[-75.447996,39.909279],"type":"Point"}
}