{
  "type": "Feature",
  "properties": {
    "iso:country":"US",
    "sg:address":"1015 Longfield Rd",
    "sg:city":"Southampton",
    "sg:classifiers":[
        {
            "category":"Building & Trades",
            "subcategory":"Construction",
            "type":"Services"
        },
        {
            "category":"Building & Trades",
            "subcategory":"Plumbing",
            "type":"Services"
        }
    ],
    "sg:phone":"+1 215 364 6742",
    "sg:postcode":"18966",
    "sg:province":"PA",
    "sg:tags":[
        "bathroom",
        "remodeling",
        "contractor"
    ],
    "wof:name":"USA Plumbing & Heating Inc",
    "wof:placetype":"venue"
},
  "geometry": {"coordinates":[-75.02251,40.173397],"type":"Point"}
}