{
  "type": "Feature",
  "properties": {
    "iso:country":"US",
    "sg:address":"41 Ordale Blvd",
    "sg:city":"Pittsburgh",
    "sg:phone":"+1   ",
    "sg:postcode":"15228",
    "sg:province":"PA",
    "sg:tags":[
        "farm",
        "corn",
        "wheat",
        "soybean"
    ],
    "wof:name":"William Keegan Farm",
    "wof:placetype":"venue"
},
  "geometry": {"coordinates":[-80.048436,40.3625],"type":"Point"}
}