{
  "type": "Feature",
  "properties": {
    "iso:country":"US",
    "sg:address":"1020 Sharon Rd",
    "sg:city":"Beaver",
    "sg:classifiers":[
        {
            "category":"Restaurant",
            "type":"Food & Drink"
        }
    ],
    "sg:phone":"+1   ",
    "sg:postcode":"15009",
    "sg:province":"PA",
    "sg:tags":[
        "drinking",
        "eating"
    ],
    "wof:name":"Roberts",
    "wof:placetype":"venue"
},
  "geometry": {"coordinates":[-80.301016,40.708686],"type":"Point"}
}