{
  "type": "Feature",
  "properties": {
    "addr:full":"3055 Maple Ave Reading PA 19605",
    "addr:housenumber":"3055",
    "addr:postcode":"19605",
    "addr:street":"Maple Ave",
    "iso:country":"US",
    "sg:address":"3055 Maple Ave",
    "sg:city":"Reading",
    "sg:classifiers":[
        {
            "category":"Food & Beverages",
            "subcategory":"Groceries & Convenience Stores",
            "type":"Retail Goods"
        }
    ],
    "sg:phone":"+1 610 373 5079",
    "sg:postcode":"19605",
    "sg:province":"PA",
    "sg:tags":[
        "grocer",
        "restaurant"
    ],
    "wof:name":"Chubby's",
    "wof:placetype":"venue"
},
  "geometry": {"coordinates":[-75.942578,40.381394],"type":"Point"}
}