{
  "type": "Feature",
  "properties": {
    "addr:full":"1033 Rhawn St Philadelphia PA 19111",
    "addr:housenumber":"1033",
    "addr:postcode":"19111",
    "addr:street":"Rhawn St",
    "iso:country":"US",
    "sg:address":"1033 Rhawn St",
    "sg:city":"Philadelphia",
    "sg:classifiers":[
        {
            "category":"Freight",
            "type":"Transportation"
        }
    ],
    "sg:phone":"+1   ",
    "sg:postcode":"19111",
    "sg:province":"PA",
    "sg:tags":[
        "operator",
        "local",
        "trucking"
    ],
    "wof:name":"Atkinson Movers",
    "wof:placetype":"venue"
},
  "geometry": {"coordinates":[-75.072411,40.071303],"type":"Point"}
}