{
  "type": "Feature",
  "properties": {
    "iso:country":"US",
    "sg:address":"193 Sunset View Dr",
    "sg:city":"Doylestown",
    "sg:classifiers":[
        {
            "category":"Professional",
            "subcategory":"Management & Consulting",
            "type":"Services"
        }
    ],
    "sg:phone":"+1   ",
    "sg:postcode":"18901",
    "sg:province":"PA",
    "wof:name":"Rine & Assoc LLC Fredric D",
    "wof:placetype":"venue"
},
  "geometry": {"coordinates":[-75.14460800000001,40.29067],"type":"Point"}
}