{
  "type": "Feature",
  "properties": {
    "iso:country":"US",
    "sg:address":"3514 Trindle Rd",
    "sg:city":"Camp Hill",
    "sg:classifiers":[
        {
            "category":"Sports & Exercise",
            "subcategory":"Gym",
            "type":"Entertainment"
        },
        {
            "category":"Health Services",
            "subcategory":"Health Practitioner",
            "type":"Services"
        }
    ],
    "sg:phone":"+1 717 796 2003",
    "sg:postcode":"17011",
    "sg:province":"PA",
    "sg:tags":[
        "trainer",
        "therapy",
        "physical"
    ],
    "sg:website":"www.fit-tone.com",
    "wof:name":"Fit-Tone Personal Fitness",
    "wof:placetype":"venue"
},
  "geometry": {"coordinates":[-76.940887,40.23637],"type":"Point"}
}