{
  "type": "Feature",
  "properties": {
    "iso:country":"US",
    "sg:address":"1207 Moravia St",
    "sg:city":"New Castle",
    "sg:classifiers":[
        {
            "category":"Organizations",
            "subcategory":"Religious Organization",
            "type":"Services"
        }
    ],
    "sg:phone":"+1 724 652 8751",
    "sg:postcode":"16101",
    "sg:province":"PA",
    "sg:tags":[
        "church"
    ],
    "wof:name":"St John United Holy Church",
    "wof:placetype":"venue"
},
  "geometry": {"coordinates":[-80.349372,40.986829],"type":"Point"}
}