{
  "type": "Feature",
  "properties": {
    "addr:full":"1781 Airport Rd Allentown PA 18109",
    "addr:housenumber":"1781",
    "addr:postcode":"18109",
    "addr:street":"Airport Rd",
    "iso:country":"US",
    "sg:address":"1781 Airport Rd",
    "sg:city":"Allentown",
    "sg:phone":"+1 610 266 1988",
    "sg:postcode":"18109",
    "sg:province":"PA",
    "sg:tags":[
        "fuel",
        "diesel"
    ],
    "wof:name":"Pacific Pride",
    "wof:placetype":"venue"
},
  "geometry": {"coordinates":[-75.433368,40.640333],"type":"Point"}
}