{
  "type": "Feature",
  "properties": {
    "addr:full":"127 Radcliffe St Bristol PA 19007",
    "addr:housenumber":"127",
    "addr:postcode":"19007",
    "addr:street":"Radcliffe St",
    "iso:country":"US",
    "sg:address":"127 Radcliffe St",
    "sg:city":"Bristol",
    "sg:classifiers":[
        {
            "category":"Insurance",
            "subcategory":"Insurance Agent",
            "type":"Services"
        }
    ],
    "sg:phone":"+1 215 781 8177",
    "sg:postcode":"19007",
    "sg:province":"PA",
    "wof:name":"Union Adjusters",
    "wof:placetype":"venue"
},
  "geometry": {"coordinates":[-74.855791,40.095001],"type":"Point"}
}