{
  "type": "Feature",
  "properties": {
    "iso:country":"US",
    "sg:address":"106 Park Dr",
    "sg:city":"Montgomeryville",
    "sg:classifiers":[
        {
            "category":"Utilities",
            "subcategory":"Refuse",
            "type":"Services"
        }
    ],
    "sg:phone":"+1 215 540 9160",
    "sg:postcode":"18936",
    "sg:province":"PA",
    "sg:tags":[
        "system"
    ],
    "wof:name":"Recovery Options Inc",
    "wof:placetype":"venue"
},
  "geometry": {"coordinates":[-75.22660399999999,40.212571],"type":"Point"}
}