{
  "type": "Feature",
  "properties": {
    "iso:country":"US",
    "sg:address":"8688 Olean Trl",
    "sg:city":"Fairmount City",
    "sg:classifiers":[
        {
            "category":"Retail",
            "subcategory":"Auto Repair",
            "type":"Services"
        }
    ],
    "sg:phone":"+1 814 764 3582",
    "sg:postcode":"16224",
    "sg:province":"PA",
    "sg:tags":[
        "repairing",
        "automobile"
    ],
    "wof:name":"Bowersox Garage",
    "wof:placetype":"venue"
},
  "geometry": {"coordinates":[-79.316164,41.110596],"type":"Point"}
}