{
  "type": "Feature",
  "properties": {
    "iso:country":"US",
    "sg:address":"937 Ponderosa Rd",
    "sg:city":"Schellsburg",
    "sg:classifiers":[
        {
            "category":"Building & Trades",
            "subcategory":"Construction",
            "type":"Services"
        }
    ],
    "sg:phone":"+1 814 733 4956",
    "sg:postcode":"15559",
    "sg:province":"PA",
    "sg:tags":[
        "masonry",
        "contractor"
    ],
    "wof:name":"Gary P Geller Mason Contractor",
    "wof:placetype":"venue"
},
  "geometry": {"coordinates":[-78.614144,40.065739],"type":"Point"}
}