{
  "type": "Feature",
  "properties": {
    "iso:country":"US",
    "sg:address":"21 Glenola Dr",
    "sg:city":"Leola",
    "sg:classifiers":[
        {
            "category":"Building & Trades",
            "subcategory":"Construction",
            "type":"Services"
        }
    ],
    "sg:phone":"+1 717 656 0512",
    "sg:postcode":"17540",
    "sg:province":"PA",
    "sg:tags":[
        "home",
        "builder"
    ],
    "wof:name":"Better Built Homes Inc",
    "wof:placetype":"venue"
},
  "geometry": {"coordinates":[-76.18092799999999,40.087449],"type":"Point"}
}