{
  "type": "Feature",
  "properties": {
    "iso:country":"US",
    "sg:address":"644 Merchant St",
    "sg:city":"Ambridge",
    "sg:classifiers":[
        {
            "category":"Health Services",
            "subcategory":"Doctor",
            "type":"Services"
        }
    ],
    "sg:phone":"+1 724 266 2639",
    "sg:postcode":"15003",
    "sg:province":"PA",
    "sg:tags":[
        "physician",
        "surgeon"
    ],
    "wof:name":"Howard Cohen MD",
    "wof:placetype":"venue"
},
  "geometry": {"coordinates":[-80.227889,40.587338],"type":"Point"}
}