{
  "type": "Feature",
  "properties": {
    "addr:full":"197 Greenfield Rd Lancaster PA 17601",
    "addr:housenumber":"197",
    "addr:postcode":"17601",
    "addr:street":"Greenfield Rd",
    "iso:country":"US",
    "sg:address":"197 Greenfield Rd",
    "sg:city":"Lancaster",
    "sg:classifiers":[
        {
            "category":"Wholesale",
            "subcategory":"Office Equipment",
            "type":"Manufacturing & Wholesale Goods"
        }
    ],
    "sg:phone":"+1   ",
    "sg:postcode":"17601",
    "sg:province":"PA",
    "sg:tags":[
        "duplicating"
    ],
    "wof:name":"IKON Office Solutions",
    "wof:placetype":"venue"
},
  "geometry": {"coordinates":[-76.255258,40.04702],"type":"Point"}
}