{
  "type": "Feature",
  "properties": {
    "iso:country":"US",
    "sg:address":"620 Liberty Ave",
    "sg:city":"Pittsburgh",
    "sg:classifiers":[
        {
            "category":"Organizations",
            "subcategory":"Non-profit Organization",
            "type":"Services"
        }
    ],
    "sg:phone":"+1 412 201 5750",
    "sg:postcode":"15222",
    "sg:province":"PA",
    "sg:tags":[
        "fund",
        "counselor",
        "raising"
    ],
    "wof:name":"United Negro College Fund Inc",
    "wof:placetype":"venue"
},
  "geometry": {"coordinates":[-80.000975,40.442059],"type":"Point"}
}