{
  "type": "Feature",
  "properties": {
    "iso:country":"US",
    "sg:address":"2955 S Elm Ave",
    "sg:city":"White Cloud",
    "sg:classifiers":[
        {
            "category":"Building & Trades",
            "subcategory":"Landscaping Services",
            "type":"Services"
        }
    ],
    "sg:phone":"+1 231 689 3441",
    "sg:postcode":"99999",
    "sg:province":"PA",
    "sg:tags":[
        "tree"
    ],
    "wof:name":"Steve & Lauries Stumps & Stuff",
    "wof:placetype":"venue"
},
  "geometry": {"coordinates":[-79.066062,40.003081],"type":"Point"}
}