{
  "type": "Feature",
  "properties": {
    "iso:country":"US",
    "sg:address":"3884 Woodley Hollow Rd",
    "sg:city":"Montoursville",
    "sg:classifiers":[
        {
            "category":"Professional",
            "subcategory":"Management & Consulting",
            "type":"Services"
        }
    ],
    "sg:phone":"+1 570 435 4282",
    "sg:postcode":"17754",
    "sg:province":"PA",
    "sg:tags":[
        "marketing",
        "consultant"
    ],
    "wof:name":"Myers Consulting",
    "wof:placetype":"venue"
},
  "geometry": {"coordinates":[-76.817567,41.319603],"type":"Point"}
}