{
  "type": "Feature",
  "properties": {
    "iso:country":"US",
    "sg:address":"128 8th St",
    "sg:city":"Lewistown",
    "sg:classifiers":[
        {
            "category":"Health Services",
            "subcategory":"Doctor",
            "type":"Services"
        }
    ],
    "sg:phone":"+1 717 248 7657",
    "sg:postcode":"17044",
    "sg:province":"PA",
    "sg:tags":[
        "physician",
        "surgeon"
    ],
    "wof:name":"Ruben D Adriano Md",
    "wof:placetype":"venue"
},
  "geometry": {"coordinates":[-77.562871,40.62162],"type":"Point"}
}