{
  "type": "Feature",
  "properties": {
    "addr:full":"251 E Louther St Carlisle PA 17013",
    "addr:housenumber":"251",
    "addr:postcode":"17013",
    "addr:street":"E Louther St",
    "iso:country":"US",
    "sg:address":"251 E Louther St",
    "sg:city":"Carlisle",
    "sg:classifiers":[
        {
            "category":"Building & Trades",
            "subcategory":"Construction",
            "type":"Services"
        }
    ],
    "sg:phone":"+1 717 258 8352",
    "sg:postcode":"17013",
    "sg:province":"PA",
    "sg:tags":[
        "home",
        "improvement"
    ],
    "wof:name":"Millers Home Improvement",
    "wof:placetype":"venue"
},
  "geometry": {"coordinates":[-77.182934,40.202535],"type":"Point"}
}