{
  "type": "Feature",
  "properties": {
    "iso:country":"US",
    "sg:address":"868 W Walnut St",
    "sg:city":"Coal Township",
    "sg:classifiers":[
        {
            "category":"Manufacturing",
            "subcategory":"Printing",
            "type":"Manufacturing & Wholesale Goods"
        }
    ],
    "sg:phone":"+1   ",
    "sg:postcode":"17866",
    "sg:province":"PA",
    "sg:tags":[
        "cards",
        "greeting",
        "mfg"
    ],
    "wof:name":"Cymru Creations",
    "wof:placetype":"venue"
},
  "geometry": {"coordinates":[-76.566123,40.789584],"type":"Point"}
}