{
  "type": "Feature",
  "properties": {
    "addr:full":"2335 W 38th St Erie PA 16506",
    "addr:housenumber":"2335",
    "addr:postcode":"16506",
    "addr:street":"W 38Th St",
    "iso:country":"US",
    "sg:address":"2335 W 38th St",
    "sg:city":"Erie",
    "sg:classifiers":[
        {
            "category":"Insurance",
            "subcategory":"Insurance Agent",
            "type":"Services"
        },
        {
            "category":"Insurance",
            "subcategory":"Life Insurance",
            "type":"Services"
        }
    ],
    "sg:phone":"+1 814 838 0885",
    "sg:postcode":"16506",
    "sg:province":"PA",
    "sg:tags":[
        "accident",
        "health"
    ],
    "sg:website":"www.westernsouthernlife.com",
    "wof:name":"Western-Southern Life Ins Co",
    "wof:placetype":"venue"
},
  "geometry": {"coordinates":[-80.11967,42.082528],"type":"Point"}
}