{
  "type": "Feature",
  "properties": {
    "iso:country":"US",
    "sg:address":"138 W Main St Ste F",
    "sg:city":"Ligonier",
    "sg:classifiers":[
        {
            "category":"Shopping",
            "subcategory":"Stationery & Office Supplies",
            "type":"Retail Goods"
        },
        {
            "category":"Wholesale",
            "subcategory":"Office Equipment",
            "type":"Manufacturing & Wholesale Goods"
        }
    ],
    "sg:phone":"+1 724 238 3230",
    "sg:postcode":"15658",
    "sg:province":"PA",
    "sg:tags":[
        "register",
        "autographic",
        "store"
    ],
    "wof:name":"Ligonier Office Supply",
    "wof:placetype":"venue"
},
  "geometry": {"coordinates":[-79.238262,40.243324],"type":"Point"}
}