{
  "type": "Feature",
  "properties": {
    "addr:full":"112 Dormer St Johnstown PA 15909",
    "addr:housenumber":"112",
    "addr:postcode":"15909",
    "addr:street":"Dormer St",
    "iso:country":"US",
    "sg:address":"112 Dormer St",
    "sg:city":"Johnstown",
    "sg:classifiers":[
        {
            "category":"Building & Trades",
            "subcategory":"Landscaping Services",
            "type":"Services"
        }
    ],
    "sg:phone":"+1   ",
    "sg:postcode":"15909",
    "sg:province":"PA",
    "wof:name":"Tonys Lawncare",
    "wof:placetype":"venue"
},
  "geometry": {"coordinates":[-78.875213,40.360503],"type":"Point"}
}