{
  "type": "Feature",
  "properties": {
    "addr:full":"1026 Tennis Ave Glenside PA 19038",
    "addr:housenumber":"1026",
    "addr:postcode":"19038",
    "addr:street":"Tennis Ave",
    "iso:country":"US",
    "sg:address":"1026 Tennis Ave",
    "sg:city":"Glenside",
    "sg:classifiers":[
        {
            "category":"Communications",
            "subcategory":"Film & Video Production",
            "type":"Services"
        }
    ],
    "sg:phone":"+1   ",
    "sg:postcode":"19038",
    "sg:province":"PA",
    "sg:tags":[
        "motion"
    ],
    "wof:name":"Orchid Moon Productions",
    "wof:placetype":"venue"
},
  "geometry": {"coordinates":[-75.151303,40.128017],"type":"Point"}
}