{
  "type": "Feature",
  "properties": {
    "iso:country":"US",
    "sg:address":"802 Chestnut St",
    "sg:city":"Pittsburgh",
    "sg:classifiers":[
        {
            "category":"Building & Trades",
            "subcategory":"Pest Control",
            "type":"Services"
        }
    ],
    "sg:phone":"+1 412 322 6644",
    "sg:postcode":"15212",
    "sg:province":"PA",
    "wof:name":"Purvis Pest Control",
    "wof:placetype":"venue"
},
  "geometry": {"coordinates":[-79.994598,40.455502],"type":"Point"}
}