{
  "type": "Feature",
  "properties": {
    "addr:full":"1 Roadway Dr Carlisle PA 17015",
    "addr:housenumber":"1",
    "addr:postcode":"17015",
    "addr:street":"Roadway Dr",
    "iso:country":"US",
    "sg:address":"1 Roadway Dr",
    "sg:city":"Carlisle",
    "sg:classifiers":[
        {
            "category":"Home & Garden",
            "subcategory":"Garden Supply",
            "type":"Retail Goods"
        }
    ],
    "sg:phone":"+1 717 249 2313",
    "sg:postcode":"17015",
    "sg:province":"PA",
    "sg:tags":[
        "nursery",
        "gardening"
    ],
    "sg:website":"www.landmarkequip.com",
    "wof:name":"Landmark Equipment Llc",
    "wof:placetype":"venue"
},
  "geometry": {"coordinates":[-77.112246,40.230395],"type":"Point"}
}