{
  "type": "Feature",
  "properties": {
    "addr:full":"803 Horsham Rd Montgomeryville PA 18936",
    "addr:housenumber":"803",
    "addr:postcode":"18936",
    "addr:street":"Horsham Rd",
    "iso:country":"US",
    "sg:address":"803 Horsham Rd",
    "sg:city":"Montgomeryville",
    "sg:classifiers":[
        {
            "category":"Restaurant",
            "type":"Food & Drink"
        }
    ],
    "sg:menulink":"http://www.allmenus.com/pa/montgomery/123152-quiznos-sub/menu/",
    "sg:phone":"+1 215 412 0363",
    "sg:postcode":"18936",
    "sg:province":"PA",
    "sg:tags":[
        "wrap",
        "american",
        "sandwich"
    ],
    "wof:name":"Quiznos Sub",
    "wof:placetype":"venue"
},
  "geometry": {"coordinates":[-75.239593,40.244795],"type":"Point"}
}