{
  "type": "Feature",
  "properties": {
    "addr:full":"45 S 4th St Philadelphia PA 19106",
    "addr:housenumber":"45",
    "addr:postcode":"19106",
    "addr:street":"S 4Th St",
    "iso:country":"US",
    "sg:address":"45 S 4th St",
    "sg:city":"Philadelphia",
    "sg:classifiers":[
        {
            "category":"Shopping",
            "subcategory":"Gifts & Souvenirs",
            "type":"Retail Goods"
        }
    ],
    "sg:phone":"+1 215 925 2434",
    "sg:postcode":"19106",
    "sg:province":"PA",
    "wof:name":"Card City",
    "wof:placetype":"venue"
},
  "geometry": {"coordinates":[-75.147498,39.948867],"type":"Point"}
}