{
  "type": "Feature",
  "properties": {
    "iso:country":"US",
    "sg:address":"232 W High St",
    "sg:city":"Pottstown",
    "sg:classifiers":[
        {
            "category":"Shopping",
            "subcategory":"Used Merchandise",
            "type":"Retail Goods"
        }
    ],
    "sg:phone":"+1 610 323 2787",
    "sg:postcode":"19464",
    "sg:province":"PA",
    "sg:tags":[
        "shop",
        "consignment"
    ],
    "wof:name":"Estate Traders & Co",
    "wof:placetype":"venue"
},
  "geometry": {"coordinates":[-75.668098,40.249426],"type":"Point"}
}