{
  "type": "Feature",
  "properties": {
    "iso:country":"US",
    "sg:address":"31 S Sterley St",
    "sg:city":"Reading",
    "sg:classifiers":[
        {
            "category":"Manufacturing",
            "subcategory":"Tools & Machinery",
            "type":"Manufacturing & Wholesale Goods"
        }
    ],
    "sg:phone":"+1 610 775 4757",
    "sg:postcode":"19607",
    "sg:province":"PA",
    "sg:tags":[
        "apparel",
        "equipment",
        "safety",
        "clothing",
        "mfg"
    ],
    "wof:name":"Mifflin Valley Reflective AP",
    "wof:placetype":"venue"
},
  "geometry": {"coordinates":[-75.97192800000001,40.303643],"type":"Point"}
}