{
  "type": "Feature",
  "properties": {
    "addr:full":"252 N Shirk Rd New Holland PA 17557",
    "addr:housenumber":"252",
    "addr:postcode":"17557",
    "addr:street":"N Shirk Rd",
    "iso:country":"US",
    "sg:address":"252 N Shirk Rd",
    "sg:city":"New Holland",
    "sg:classifiers":[
        {
            "category":"Wholesale",
            "subcategory":"Machinery & Supplies",
            "type":"Manufacturing & Wholesale Goods"
        }
    ],
    "sg:phone":"+1 717 354 2354",
    "sg:postcode":"17557",
    "sg:province":"PA",
    "sg:tags":[
        "equipment",
        "distribute",
        "cleaning",
        "mfg"
    ],
    "wof:name":"Beco Equipment",
    "wof:placetype":"venue"
},
  "geometry": {"coordinates":[-76.11022199999999,40.110903],"type":"Point"}
}