{
  "type": "Feature",
  "properties": {
    "addr:full":"1100 Jackson St Philadelphia PA 19148",
    "addr:housenumber":"1100",
    "addr:postcode":"19148",
    "addr:street":"Jackson St",
    "iso:country":"US",
    "sg:address":"1100 Jackson St",
    "sg:city":"Philadelphia",
    "sg:classifiers":[
        {
            "category":"Building & Trades",
            "subcategory":"Locksmith",
            "type":"Services"
        }
    ],
    "sg:phone":"+1 215 525 5969",
    "sg:postcode":"19148",
    "sg:province":"PA",
    "sg:tags":[
        "key"
    ],
    "wof:name":"Locksmith",
    "wof:placetype":"venue"
},
  "geometry": {"coordinates":[-75.164745,39.922334],"type":"Point"}
}