{
  "type": "Feature",
  "properties": {
    "iso:country":"US",
    "sg:address":"2700 State Rte 864",
    "sg:city":"Montoursville",
    "sg:classifiers":[
        {
            "category":"Wholesale",
            "subcategory":"Machinery & Supplies",
            "type":"Manufacturing & Wholesale Goods"
        }
    ],
    "sg:phone":"+1 570 433 3573",
    "sg:postcode":"17754",
    "sg:province":"PA",
    "sg:tags":[
        "industrial",
        "miscellaneous"
    ],
    "wof:name":"J & L Speed Equipment",
    "wof:placetype":"venue"
},
  "geometry": {"coordinates":[-76.86062,41.295584],"type":"Point"}
}