{
  "type": "Feature",
  "properties": {
    "iso:country":"US",
    "sg:address":"5601 Woodland Ave",
    "sg:city":"Philadelphia",
    "sg:classifiers":[
        {
            "category":"Bars & Pubs",
            "type":"Food & Drink"
        }
    ],
    "sg:phone":"+1   ",
    "sg:postcode":"19143",
    "sg:province":"PA",
    "sg:tags":[
        "drinking"
    ],
    "wof:name":"Gormans Tavern",
    "wof:placetype":"venue"
},
  "geometry": {"coordinates":[-75.222482,39.933904],"type":"Point"}
}