{
  "type": "Feature",
  "properties": {
    "iso:country":"US",
    "sg:address":"1560 Garrett Rd",
    "sg:city":"Upper Darby",
    "sg:classifiers":[
        {
            "category":"Banks & Credit Unions",
            "subcategory":"Bank",
            "type":"Services"
        }
    ],
    "sg:phone":"+1 610 622 7100",
    "sg:postcode":"19082",
    "sg:province":"PA",
    "sg:tags":[
        "loan",
        "real estate"
    ],
    "wof:name":"Beneficial Consumer Discount",
    "wof:placetype":"venue"
},
  "geometry": {"coordinates":[-75.274242,39.955093],"type":"Point"}
}