{
  "type": "Feature",
  "properties": {
    "iso:country":"US",
    "sg:address":"196 James St",
    "sg:city":"Kingston",
    "sg:classifiers":[
        {
            "category":"Wholesale",
            "subcategory":"Medical Equipment & Supplies",
            "type":"Manufacturing & Wholesale Goods"
        }
    ],
    "sg:phone":"+1   ",
    "sg:postcode":"18704",
    "sg:province":"PA",
    "wof:name":"Therapy Rocker of Ne PA Inc",
    "wof:placetype":"venue"
},
  "geometry": {"coordinates":[-75.885463,41.264509],"type":"Point"}
}