{
  "type": "Feature",
  "properties": {
    "iso:country":"US",
    "sg:address":"200 Penn Ave",
    "sg:city":"Pittsburgh",
    "sg:classifiers":[
        {
            "category":"Restaurant",
            "type":"Food & Drink"
        }
    ],
    "sg:phone":"+1   ",
    "sg:postcode":"15221",
    "sg:province":"PA",
    "sg:tags":[
        "eating"
    ],
    "wof:name":"Wendys",
    "wof:placetype":"venue"
},
  "geometry": {"coordinates":[-79.89367799999999,40.446647],"type":"Point"}
}