{
  "type": "Feature",
  "properties": {
    "iso:country":"US",
    "sg:address":"1839 Elk Ave",
    "sg:city":"Pottsville",
    "sg:classifiers":[
        {
            "category":"Building & Trades",
            "subcategory":"Electrical",
            "type":"Services"
        }
    ],
    "sg:phone":"+1   ",
    "sg:postcode":"17901",
    "sg:province":"PA",
    "sg:tags":[
        "electrical",
        "contractor"
    ],
    "wof:name":"Pegasus Electric Service",
    "wof:placetype":"venue"
},
  "geometry": {"coordinates":[-76.217657,40.679504],"type":"Point"}
}