{
  "type": "Feature",
  "properties": {
    "addr:full":"1561 W Liberty Ave Pittsburgh PA 15226",
    "addr:housenumber":"1561",
    "addr:postcode":"15226",
    "addr:street":"W Liberty Ave",
    "iso:country":"US",
    "sg:address":"1561 W Liberty Ave",
    "sg:city":"Pittsburgh",
    "sg:classifiers":[
        {
            "category":"Retail",
            "subcategory":"Auto Rental",
            "type":"Services"
        }
    ],
    "sg:phone":"+1 412 344 2550",
    "sg:postcode":"15226",
    "sg:province":"PA",
    "sg:tags":[
        "car"
    ],
    "sg:website":"www.econocarrental-repair.com",
    "wof:name":"Econo Car & Van Rental Systems",
    "wof:placetype":"venue"
},
  "geometry": {"coordinates":[-80.01615099999999,40.409744],"type":"Point"}
}