{
  "type": "Feature",
  "properties": {
    "iso:country":"US",
    "sg:address":"1 Towne Plz",
    "sg:city":"Tunkhannock",
    "sg:classifiers":[
        {
            "category":"Shopping",
            "subcategory":"Beauty & Cosmetics",
            "type":"Retail Goods"
        },
        {
            "category":"Retail",
            "subcategory":"Photofinishing",
            "type":"Services"
        },
        {
            "category":"Shopping",
            "subcategory":"Gifts & Souvenirs",
            "type":"Retail Goods"
        },
        {
            "category":"Retail",
            "subcategory":"Storage",
            "type":"Services"
        },
        {
            "category":"Shopping",
            "subcategory":"Pharmacy",
            "type":"Retail Goods"
        }
    ],
    "sg:phone":"+1 570 836 6777",
    "sg:postcode":"18657",
    "sg:province":"PA",
    "sg:tags":[
        "supply",
        "photo",
        "sundries",
        "perfume",
        "card",
        "aid",
        "finishing",
        "first",
        "store",
        "greeting"
    ],
    "sg:website":"http://www.cvs.com",
    "wof:name":"Cvs Pharmacy",
    "wof:placetype":"venue"
},
  "geometry": {"coordinates":[-75.96077699999999,41.543152],"type":"Point"}
}