{
  "type": "Feature",
  "properties": {
    "iso:country":"US",
    "sg:address":"11601 Bustleton Ave",
    "sg:city":"Philadelphia",
    "sg:classifiers":[
        {
            "category":"Health Services",
            "subcategory":"Doctor",
            "type":"Services"
        }
    ],
    "sg:phone":"+1   ",
    "sg:postcode":"19116",
    "sg:province":"PA",
    "wof:name":"Yiu-Man Ko DMD",
    "wof:placetype":"venue"
},
  "geometry": {"coordinates":[-75.018005,40.118908],"type":"Point"}
}