{
  "type": "Feature",
  "properties": {
    "iso:country":"US",
    "sg:address":"1051 Newville Rd",
    "sg:city":"Carlisle",
    "sg:classifiers":[
        {
            "category":"Building & Trades",
            "subcategory":"Electrical",
            "type":"Services"
        }
    ],
    "sg:phone":"+1 717 243 1138",
    "sg:postcode":"17013",
    "sg:province":"PA",
    "sg:tags":[
        "electrical",
        "electric",
        "contractor"
    ],
    "wof:name":"Jumper's Electric",
    "wof:placetype":"venue"
},
  "geometry": {"coordinates":[-77.21885399999999,40.203734],"type":"Point"}
}