{
  "type": "Feature",
  "properties": {
    "addr:full":"7300 Germantown Ave Philadelphia PA 19119",
    "addr:housenumber":"7300",
    "addr:postcode":"19119",
    "addr:street":"Germantown Ave",
    "iso:country":"US",
    "sg:address":"7300 Germantown Ave",
    "sg:city":"Philadelphia",
    "sg:classifiers":[
        {
            "category":"Health Services",
            "subcategory":"Doctor",
            "type":"Services"
        }
    ],
    "sg:phone":"+1 215 242 3912",
    "sg:postcode":"19119",
    "sg:province":"PA",
    "sg:tags":[
        "medical"
    ],
    "wof:name":"Joel Pomerantz MD",
    "wof:placetype":"venue"
},
  "geometry": {"coordinates":[-75.191936,40.06134],"type":"Point"}
}