{
  "type": "Feature",
  "properties": {
    "addr:full":"5227 Baltimore Pike Littlestown PA 17340",
    "addr:housenumber":"5227",
    "addr:postcode":"17340",
    "addr:street":"Baltimore Pike",
    "iso:country":"US",
    "sg:address":"5227 Baltimore Pike",
    "sg:city":"Littlestown",
    "sg:classifiers":[
        {
            "category":"Shopping",
            "subcategory":"Gifts & Souvenirs",
            "type":"Retail Goods"
        }
    ],
    "sg:phone":"+1 717 359 8773",
    "sg:postcode":"17340",
    "sg:province":"PA",
    "sg:tags":[
        "shop"
    ],
    "wof:name":"David's Gift World",
    "wof:placetype":"venue"
},
  "geometry": {"coordinates":[-77.102557,39.754403],"type":"Point"}
}