{
  "type": "Feature",
  "properties": {
    "iso:country":"US",
    "sg:address":"176 Mill St",
    "sg:city":"Wilkes Barre",
    "sg:classifiers":[
        {
            "category":"Professional",
            "type":"Services"
        }
    ],
    "sg:phone":"+1   ",
    "sg:postcode":"18705",
    "sg:province":"PA",
    "wof:name":"Donna Nilon",
    "wof:placetype":"venue"
},
  "geometry": {"coordinates":[-75.84642599999999,41.260109],"type":"Point"}
}