{
  "type": "Feature",
  "properties": {
    "addr:full":"384 Shurs Lane Philadelphia PA 19128",
    "addr:housenumber":"384",
    "addr:postcode":"19128",
    "addr:street":"Shurs Lane",
    "iso:country":"US",
    "sg:address":"384 Shurs Lane",
    "sg:city":"Philadelphia",
    "sg:classifiers":[
        {
            "category":"Real Estate",
            "subcategory":"Real Estate Agent",
            "type":"Services"
        }
    ],
    "sg:phone":"+1 267 258 7863",
    "sg:postcode":"19128",
    "sg:province":"PA",
    "wof:name":"C.J. Ferraro",
    "wof:placetype":"venue"
},
  "geometry": {"coordinates":[-75.21302900000001,40.025471],"type":"Point"}
}