{
  "type": "Feature",
  "properties": {
    "iso:country":"US",
    "sg:address":"3328 N Gratz St",
    "sg:city":"Philadelphia",
    "sg:classifiers":[
        {
            "category":"Building & Trades",
            "subcategory":"Electrical",
            "type":"Services"
        }
    ],
    "sg:phone":"+1 215 758 4799",
    "sg:postcode":"19140",
    "sg:province":"PA",
    "sg:tags":[
        "electrician"
    ],
    "wof:name":"Paramount Electric And Telecom",
    "wof:placetype":"venue"
},
  "geometry": {"coordinates":[-75.15960699999999,40.004535],"type":"Point"}
}