{
  "type": "Feature",
  "properties": {
    "addr:full":"108 N Williamson Rd Blossburg PA 16912",
    "addr:housenumber":"108",
    "addr:postcode":"16912",
    "addr:street":"N Williamson Rd",
    "iso:country":"US",
    "sg:address":"108 N Williamson Rd",
    "sg:city":"Blossburg",
    "sg:classifiers":[
        {
            "category":"Organizations",
            "subcategory":"Religious Organization",
            "type":"Services"
        }
    ],
    "sg:phone":"+1 570 638 3046",
    "sg:postcode":"16912",
    "sg:province":"PA",
    "sg:tags":[
        "church"
    ],
    "wof:name":"United Methodist Church",
    "wof:placetype":"venue"
},
  "geometry": {"coordinates":[-77.065484,41.683612],"type":"Point"}
}