{
  "type": "Feature",
  "properties": {
    "iso:country":"US",
    "sg:address":"1196 N Grant Ave",
    "sg:city":"Kittanning",
    "sg:classifiers":[
        {
            "category":"Building & Trades",
            "subcategory":"Plumbing",
            "type":"Services"
        }
    ],
    "sg:phone":"+1 724 548 1526",
    "sg:postcode":"16201",
    "sg:province":"PA",
    "sg:tags":[
        "system",
        "heating",
        "air",
        "refrigeration",
        "conditioning",
        "contractor"
    ],
    "wof:name":"Rosenbergers Hvac Inc",
    "wof:placetype":"venue"
},
  "geometry": {"coordinates":[-79.52719500000001,40.827873],"type":"Point"}
}