{
  "type": "Feature",
  "properties": {
    "iso:country":"US",
    "sg:address":"8267 Admiral Peary Hwy",
    "sg:city":"Cresson",
    "sg:classifiers":[
        {
            "category":"Retail",
            "subcategory":"Auto Repair",
            "type":"Services"
        }
    ],
    "sg:phone":"+1 814 886 4164",
    "sg:postcode":"16630",
    "sg:province":"PA",
    "sg:tags":[
        "truck"
    ],
    "sg:website":"www.customdiesel.com",
    "wof:name":"Cresson Ridge Diesel Garage",
    "wof:placetype":"venue"
},
  "geometry": {"coordinates":[-78.56132700000001,40.456175],"type":"Point"}
}