{
  "type": "Feature",
  "properties": {
    "addr:full":"700 E Weidman St Lebanon PA 17046",
    "addr:housenumber":"700",
    "addr:postcode":"17046",
    "addr:street":"E Weidman St",
    "iso:country":"US",
    "sg:address":"700 E Weidman St",
    "sg:city":"Lebanon",
    "sg:classifiers":[
        {
            "category":"Manufacturing",
            "subcategory":"Signs",
            "type":"Manufacturing & Wholesale Goods"
        }
    ],
    "sg:phone":"+1   ",
    "sg:postcode":"17046",
    "sg:province":"PA",
    "sg:tags":[
        "specialty",
        "mfg"
    ],
    "wof:name":"Walker Sign Service",
    "wof:placetype":"venue"
},
  "geometry": {"coordinates":[-76.39795599999999,40.345839],"type":"Point"}
}