{
  "type": "Feature",
  "properties": {
    "iso:country":"US",
    "sg:address":"1335 Mount Vernon St",
    "sg:city":"Philadelphia",
    "sg:classifiers":[
        {
            "category":"Retail",
            "subcategory":"Auto Repair",
            "type":"Services"
        }
    ],
    "sg:phone":"+1   ",
    "sg:postcode":"19123",
    "sg:province":"PA",
    "sg:tags":[
        "body",
        "general"
    ],
    "wof:name":"C & S Auto Repair",
    "wof:placetype":"venue"
},
  "geometry": {"coordinates":[-75.158914,39.963771],"type":"Point"}
}