{
  "type": "Feature",
  "properties": {
    "addr:full":"237 E High St Pottstown PA 19464",
    "addr:housenumber":"237",
    "addr:postcode":"19464",
    "addr:street":"E High St",
    "iso:country":"US",
    "sg:address":"237 E High St",
    "sg:city":"Pottstown",
    "sg:classifiers":[
        {
            "category":"Shopping",
            "type":"Retail Goods"
        }
    ],
    "sg:phone":"+1 610 323 6700",
    "sg:postcode":"19464",
    "sg:province":"PA",
    "sg:tags":[
        "coin",
        "dealer",
        "supply"
    ],
    "wof:name":"Federal Coin Exchange",
    "wof:placetype":"venue"
},
  "geometry": {"coordinates":[-75.64760699999999,40.245315],"type":"Point"}
}