{
  "type": "Feature",
  "properties": {
    "iso:country":"US",
    "sg:address":"107 E Main St",
    "sg:city":"Uniontown",
    "sg:classifiers":[
        {
            "category":"Real Estate",
            "subcategory":"Surveying",
            "type":"Services"
        }
    ],
    "sg:phone":"+1 724 439 2626",
    "sg:postcode":"15401",
    "sg:province":"PA",
    "sg:tags":[
        "surveyor"
    ],
    "wof:name":"Defino & Sons",
    "wof:placetype":"venue"
},
  "geometry": {"coordinates":[-79.721538,39.900512],"type":"Point"}
}