{
  "type": "Feature",
  "properties": {
    "iso:country":"US",
    "sg:address":"700 W 3rd St",
    "sg:city":"Williamsport",
    "sg:classifiers":[
        {
            "category":"Autos & Motor Vehicles",
            "subcategory":"Auto Supplies",
            "type":"Retail Goods"
        }
    ],
    "sg:phone":"+1 570 320 1700",
    "sg:postcode":"17701",
    "sg:province":"PA",
    "sg:tags":[
        "tire"
    ],
    "wof:name":"K & W Tire Co",
    "wof:placetype":"venue"
},
  "geometry": {"coordinates":[-77.01696699999999,41.237806],"type":"Point"}
}