{
  "type": "Feature",
  "properties": {
    "iso:country":"US",
    "sg:address":"215 Springhouse Ln",
    "sg:city":"Merion Station",
    "sg:classifiers":[
        {
            "category":"Professional",
            "subcategory":"Research",
            "type":"Services"
        }
    ],
    "sg:phone":"+1   ",
    "sg:postcode":"19066",
    "sg:province":"PA",
    "sg:tags":[
        "skin"
    ],
    "wof:name":"Springhouse Skin Research Inc",
    "wof:placetype":"venue"
},
  "geometry": {"coordinates":[-75.24524099999999,40.013441],"type":"Point"}
}