{
  "type": "Feature",
  "properties": {
    "iso:country":"US",
    "sg:address":"640 High Rd",
    "sg:city":"Ashland",
    "sg:classifiers":[
        {
            "category":"Retail",
            "subcategory":"Veterinary Services",
            "type":"Services"
        }
    ],
    "sg:phone":"+1 570 875 4961",
    "sg:postcode":"17921",
    "sg:province":"PA",
    "wof:name":"Anthracite Animal Clinic",
    "wof:placetype":"venue"
},
  "geometry": {"coordinates":[-76.42814,40.754411],"type":"Point"}
}