{
  "type": "Feature",
  "properties": {
    "addr:full":"954 Perry Hwy Pittsburgh PA 15237",
    "addr:housenumber":"954",
    "addr:postcode":"15237",
    "addr:street":"Perry Hwy",
    "iso:country":"US",
    "sg:address":"954 Perry Hwy",
    "sg:city":"Pittsburgh",
    "sg:classifiers":[
        {
            "category":"Retail",
            "subcategory":"Veterinary Services",
            "type":"Services"
        }
    ],
    "sg:phone":"+1 412 364 5511",
    "sg:postcode":"15237",
    "sg:province":"PA",
    "sg:tags":[
        "clinic",
        "hospital",
        "veterinarian",
        "specialty"
    ],
    "sg:website":"http://www.anvh.com",
    "wof:name":"Allegheny North Veterinary Hospital",
    "wof:placetype":"venue"
},
  "geometry": {"coordinates":[-80.035989,40.536381],"type":"Point"}
}