{
  "type": "Feature",
  "properties": {
    "iso:country":"US",
    "sg:address":"721 Main St",
    "sg:city":"Bentleyville",
    "sg:classifiers":[
        {
            "category":"Health Services",
            "subcategory":"Doctor",
            "type":"Services"
        }
    ],
    "sg:phone":"+1   ",
    "sg:postcode":"15314",
    "sg:province":"PA",
    "wof:name":"McClain Dr & Associates DMD",
    "wof:placetype":"venue"
},
  "geometry": {"coordinates":[-80.00760699999999,40.118329],"type":"Point"}
}