{
  "type": "Feature",
  "properties": {
    "iso:country":"US",
    "sg:address":"413 Old York Rd",
    "sg:city":"Jenkintown",
    "sg:classifiers":[
        {
            "category":"Shopping",
            "type":"Retail Goods"
        }
    ],
    "sg:phone":"+1 215 885 6629",
    "sg:postcode":"19046",
    "sg:province":"PA",
    "sg:tags":[
        "ready",
        "picture",
        "frame",
        "art"
    ],
    "wof:name":"Art Of Framing",
    "wof:placetype":"venue"
},
  "geometry": {"coordinates":[-75.125474,40.092287],"type":"Point"}
}