{
  "type": "Feature",
  "properties": {
    "addr:full":"5202 Lancaster Ave Philadelphia PA 19131",
    "addr:housenumber":"5202",
    "addr:postcode":"19131",
    "addr:street":"Lancaster Ave",
    "iso:country":"US",
    "sg:address":"5202 Lancaster Ave",
    "sg:city":"Philadelphia",
    "sg:classifiers":[
        {
            "category":"Restaurant",
            "type":"Food & Drink"
        }
    ],
    "sg:phone":"+1 215 878 4390",
    "sg:postcode":"19131",
    "sg:province":"PA",
    "sg:tags":[
        "pizza"
    ],
    "wof:name":"New Star Express Pizza",
    "wof:placetype":"venue"
},
  "geometry": {"coordinates":[-75.22687000000001,39.977082],"type":"Point"}
}