{
  "type": "Feature",
  "properties": {
    "iso:country":"US",
    "sg:address":"12 Prospect St",
    "sg:city":"Warren",
    "sg:classifiers":[
        {
            "category":"Building & Trades",
            "subcategory":"Electrical",
            "type":"Services"
        }
    ],
    "sg:phone":"+1   ",
    "sg:postcode":"16365",
    "sg:province":"PA",
    "sg:tags":[
        "electrical",
        "contractor"
    ],
    "wof:name":"Williams Electric",
    "wof:placetype":"venue"
},
  "geometry": {"coordinates":[-79.13435,41.842348],"type":"Point"}
}