{
  "type": "Feature",
  "properties": {
    "iso:country":"US",
    "sg:address":"228 Fairlawn Dr",
    "sg:city":"Monroeville",
    "sg:classifiers":[
        {
            "category":"Professional",
            "type":"Services"
        }
    ],
    "sg:phone":"+1   ",
    "sg:postcode":"15146",
    "sg:province":"PA",
    "wof:name":"Jfa Company",
    "wof:placetype":"venue"
},
  "geometry": {"coordinates":[-79.768997,40.447406],"type":"Point"}
}