{
  "type": "Feature",
  "properties": {
    "iso:country":"US",
    "sg:address":"8380 Old York Rd",
    "sg:city":"Elkins Park",
    "sg:classifiers":[
        {
            "category":"Real Estate",
            "subcategory":"Real Estate Operator",
            "type":"Services"
        }
    ],
    "sg:phone":"+1 215 887 6006",
    "sg:postcode":"19027",
    "sg:province":"PA",
    "sg:tags":[
        "building",
        "parks"
    ],
    "wof:name":"Breyer Office Park",
    "wof:placetype":"venue"
},
  "geometry": {"coordinates":[-75.128023,40.08567],"type":"Point"}
}