{
  "type": "Feature",
  "properties": {
    "iso:country":"US",
    "sg:address":"315 W State St",
    "sg:city":"Quarryville",
    "sg:classifiers":[
        {
            "category":"Retail",
            "subcategory":"Laundry & Dry Cleaning",
            "type":"Services"
        }
    ],
    "sg:phone":"+1 717 786 2800",
    "sg:postcode":"17566",
    "sg:province":"PA",
    "sg:tags":[
        "cleaners"
    ],
    "wof:name":"Clean Enterprises",
    "wof:placetype":"venue"
},
  "geometry": {"coordinates":[-76.172506,39.894349],"type":"Point"}
}