{
  "type": "Feature",
  "properties": {
    "addr:full":"817 N Franklin St Philadelphia PA 19123",
    "addr:housenumber":"817",
    "addr:postcode":"19123",
    "addr:street":"N Franklin St",
    "iso:country":"US",
    "sg:address":"817 N Franklin St",
    "sg:city":"Philadelphia",
    "sg:classifiers":[
        {
            "category":"Communications",
            "subcategory":"Newspaper",
            "type":"Services"
        }
    ],
    "sg:phone":"+1 215 627 0233",
    "sg:postcode":"19123",
    "sg:province":"PA",
    "sg:tags":[
        "print",
        "medium"
    ],
    "wof:name":"America Ukrainian Catholic Newspaper",
    "wof:placetype":"venue"
},
  "geometry": {"coordinates":[-75.15010100000001,39.965801],"type":"Point"}
}