{
  "type": "Feature",
  "properties": {
    "iso:country":"US",
    "sg:address":"124 N 15th St",
    "sg:city":"Philadelphia",
    "sg:classifiers":[
        {
            "category":"Parking",
            "type":"Transportation"
        }
    ],
    "sg:phone":"+1   ",
    "sg:postcode":"19102",
    "sg:province":"PA",
    "sg:tags":[
        "automobile"
    ],
    "wof:name":"Philadelphia Parking Authority",
    "wof:placetype":"venue"
},
  "geometry": {"coordinates":[-75.164838,39.954815],"type":"Point"}
}