{
  "type": "Feature",
  "properties": {
    "iso:country":"US",
    "sg:address":"320 Smithfield Highhouse Rd",
    "sg:city":"Smithfield",
    "sg:classifiers":[
        {
            "category":"Government",
            "subcategory":"Office",
            "type":"Public Place"
        }
    ],
    "sg:phone":"+1   ",
    "sg:postcode":"15478",
    "sg:province":"PA",
    "sg:tags":[
        "policy"
    ],
    "wof:name":"Carol A Clay Tax Collector",
    "wof:placetype":"venue"
},
  "geometry": {"coordinates":[-79.802519,39.822036],"type":"Point"}
}