{
  "type": "Feature",
  "properties": {
    "iso:country":"US",
    "sg:address":"1500 Walnut St",
    "sg:city":"Philadelphia",
    "sg:classifiers":[
        {
            "category":"Restaurant",
            "type":"Food & Drink"
        }
    ],
    "sg:menulink":"http://www.allmenus.com/pa/philadelphia/23200-striped-bass/menu/",
    "sg:phone":"+1 215 732 4444",
    "sg:postcode":"19102",
    "sg:province":"PA",
    "sg:tags":[
        "seafood",
        "american"
    ],
    "wof:name":"Striped Bass",
    "wof:placetype":"venue"
},
  "geometry": {"coordinates":[-75.166102,39.949457],"type":"Point"}
}