{
  "type": "Feature",
  "properties": {
    "addr:full":"7 N Chester Rd West Chester PA 19380",
    "addr:housenumber":"7",
    "addr:postcode":"19380",
    "addr:street":"N Chester Rd",
    "iso:country":"US",
    "sg:address":"7 N Chester Rd",
    "sg:city":"West Chester",
    "sg:classifiers":[
        {
            "category":"Building & Trades",
            "subcategory":"Construction",
            "type":"Services"
        }
    ],
    "sg:phone":"+1   ",
    "sg:postcode":"19380",
    "sg:province":"PA",
    "sg:tags":[
        "contractor"
    ],
    "wof:name":"Advanced Exteriors",
    "wof:placetype":"venue"
},
  "geometry": {"coordinates":[-75.524254,39.967368],"type":"Point"}
}