{
  "type": "Feature",
  "properties": {
    "iso:country":"US",
    "sg:address":"164 W Ninth St",
    "sg:city":"Bloomsburg",
    "sg:classifiers":[
        {
            "category":"Organizations",
            "subcategory":"Religious Organization",
            "type":"Services"
        }
    ],
    "sg:phone":"+1 570 784 2900",
    "sg:postcode":"17815",
    "sg:province":"PA",
    "sg:tags":[
        "church"
    ],
    "wof:name":"Family OF Christ Lutheran Chr",
    "wof:placetype":"venue"
},
  "geometry": {"coordinates":[-76.45335900000001,40.994565],"type":"Point"}
}