{
  "type": "Feature",
  "properties": {
    "iso:country":"US",
    "sg:address":"950 Chestnut St",
    "sg:city":"Emmaus",
    "sg:classifiers":[
        {
            "category":"Retail",
            "subcategory":"Auto Repair",
            "type":"Services"
        }
    ],
    "sg:phone":"+1 610 967 6692",
    "sg:postcode":"18049",
    "sg:province":"PA",
    "sg:tags":[
        "transmission",
        "shop"
    ],
    "wof:name":"Cottman Transmission Ctr",
    "wof:placetype":"venue"
},
  "geometry": {"coordinates":[-75.503387,40.530055],"type":"Point"}
}