{
  "type": "Feature",
  "properties": {
    "addr:full":"759 Roble Rd Allentown PA 18109",
    "addr:housenumber":"759",
    "addr:postcode":"18109",
    "addr:street":"Roble Rd",
    "iso:country":"US",
    "sg:address":"759 Roble Rd",
    "sg:city":"Allentown",
    "sg:classifiers":[
        {
            "category":"Education",
            "subcategory":"Junior College",
            "type":"Public Place"
        }
    ],
    "sg:phone":"+1 610 231 0771",
    "sg:postcode":"18109",
    "sg:province":"PA",
    "wof:name":"Universal Technical Institute",
    "wof:placetype":"venue"
},
  "geometry": {"coordinates":[-75.45507000000001,40.637532],"type":"Point"}
}