{
  "type": "Feature",
  "properties": {
    "addr:full":"74 W Broad St Bethlehem PA 18018",
    "addr:housenumber":"74",
    "addr:postcode":"18018",
    "addr:street":"W Broad St",
    "iso:country":"US",
    "sg:address":"74 W Broad St",
    "sg:city":"Bethlehem",
    "sg:classifiers":[
        {
            "category":"Professional",
            "subcategory":"Business Services",
            "type":"Services"
        }
    ],
    "sg:phone":"+1   ",
    "sg:postcode":"18018",
    "sg:province":"PA",
    "wof:name":"Cornersone Advsrs Ast Mgmt In",
    "wof:placetype":"venue"
},
  "geometry": {"coordinates":[-75.381122,40.622417],"type":"Point"}
}