{
  "type": "Feature",
  "properties": {
    "iso:country":"US",
    "sg:address":"1921 Spring Garden St",
    "sg:city":"Philadelphia",
    "sg:classifiers":[
        {
            "category":"Retail",
            "subcategory":"Funeral Services",
            "type":"Services"
        }
    ],
    "sg:phone":"+1 215 563 3655",
    "sg:postcode":"19130",
    "sg:province":"PA",
    "sg:tags":[
        "director",
        "cemetery"
    ],
    "wof:name":"Dinan Funeral Home",
    "wof:placetype":"venue"
},
  "geometry": {"coordinates":[-75.170197,39.963501],"type":"Point"}
}