{
  "type": "Feature",
  "properties": {
    "iso:country":"US",
    "sg:address":"825 Beaver Grade Rd",
    "sg:city":"Coraopolis",
    "sg:classifiers":[
        {
            "category":"Shopping",
            "subcategory":"Pharmacy",
            "type":"Retail Goods"
        }
    ],
    "sg:phone":"+1   ",
    "sg:postcode":"15108",
    "sg:province":"PA",
    "sg:tags":[
        "mail"
    ],
    "wof:name":"Med-Fast Pharmacy Inc",
    "wof:placetype":"venue"
},
  "geometry": {"coordinates":[-80.219798,40.516067],"type":"Point"}
}