{
  "type": "Feature",
  "properties": {
    "iso:country":"US",
    "sg:address":"635 Maple St",
    "sg:city":"Columbia",
    "sg:classifiers":[
        {
            "category":"Professional",
            "subcategory":"Business Services",
            "type":"Services"
        }
    ],
    "sg:phone":"+1 717 684 8423",
    "sg:postcode":"17512",
    "sg:province":"PA",
    "sg:tags":[
        "license"
    ],
    "wof:name":"Yvonne M Yohe Notary Svc",
    "wof:placetype":"venue"
},
  "geometry": {"coordinates":[-76.502075,40.039464],"type":"Point"}
}