{
  "type": "Feature",
  "properties": {
    "iso:country":"US",
    "sg:address":"132 Olympic Rd",
    "sg:city":"Collegeville",
    "sg:classifiers":[
        {
            "category":"Building & Trades",
            "subcategory":"Construction",
            "type":"Services"
        }
    ],
    "sg:phone":"+1   ",
    "sg:postcode":"19426",
    "sg:province":"PA",
    "sg:tags":[
        "hanging",
        "contractor"
    ],
    "wof:name":"Renee Catillo",
    "wof:placetype":"venue"
},
  "geometry": {"coordinates":[-75.461423,40.143611],"type":"Point"}
}