{
  "type": "Feature",
  "properties": {
    "addr:full":"240 S Roland St Pottstown PA 19464",
    "addr:housenumber":"240",
    "addr:postcode":"19464",
    "addr:street":"S Roland St",
    "iso:country":"US",
    "sg:address":"240 S Roland St",
    "sg:city":"Pottstown",
    "sg:classifiers":[
        {
            "category":"Utilities",
            "type":"Services"
        }
    ],
    "sg:phone":"+1 610 705 5700",
    "sg:postcode":"19464",
    "sg:province":"PA",
    "sg:tags":[
        "contractor"
    ],
    "wof:name":"Mgk Construction",
    "wof:placetype":"venue"
},
  "geometry": {"coordinates":[-75.624886,40.239266],"type":"Point"}
}