{
  "type": "Feature",
  "properties": {
    "addr:full":"500 E Main St Lititz PA 17543",
    "addr:housenumber":"500",
    "addr:postcode":"17543",
    "addr:street":"E Main St",
    "iso:country":"US",
    "sg:address":"500 E Main St",
    "sg:city":"Lititz",
    "sg:classifiers":[
        {
            "category":"Professional",
            "subcategory":"Business Services",
            "type":"Services"
        }
    ],
    "sg:phone":"+1   ",
    "sg:postcode":"17543",
    "sg:province":"PA",
    "sg:tags":[
        "sewing"
    ],
    "wof:name":"By Michlle At Broadleays Cornr",
    "wof:placetype":"venue"
},
  "geometry": {"coordinates":[-76.293803,40.154858],"type":"Point"}
}