{
  "type": "Feature",
  "properties": {
    "iso:country":"US",
    "sg:address":"90 Christy Park Dr",
    "sg:city":"Indiana",
    "sg:classifiers":[
        {
            "category":"Wholesale",
            "subcategory":"Sporting Goods",
            "type":"Manufacturing & Wholesale Goods"
        }
    ],
    "sg:phone":"+1 724 463 2122",
    "sg:postcode":"15701",
    "sg:province":"PA",
    "sg:tags":[
        "tackle",
        "fishing"
    ],
    "sg:website":"www.renoskylures.com",
    "wof:name":"Renosky Lure Co",
    "wof:placetype":"venue"
},
  "geometry": {"coordinates":[-79.184838,40.622449],"type":"Point"}
}