{
  "type": "Feature",
  "properties": {
    "addr:full":"54 Church St Montrose PA 18801",
    "addr:housenumber":"54",
    "addr:postcode":"18801",
    "addr:street":"Church St",
    "iso:country":"US",
    "sg:address":"54 Church St",
    "sg:city":"Montrose",
    "sg:classifiers":[
        {
            "category":"Autos & Motor Vehicles",
            "subcategory":"Fuel & Gas Station",
            "type":"Retail Goods"
        }
    ],
    "sg:phone":"+1 570 278 4228",
    "sg:postcode":"18801",
    "sg:province":"PA",
    "sg:tags":[
        "station",
        "gasoline"
    ],
    "wof:name":"Ho Mart",
    "wof:placetype":"venue"
},
  "geometry": {"coordinates":[-75.87751400000001,41.832383],"type":"Point"}
}