{
  "type": "Feature",
  "properties": {
    "iso:country":"US",
    "sg:address":"2415 Horsham Rd",
    "sg:city":"Hatboro",
    "sg:classifiers":[
        {
            "category":"Restaurant",
            "type":"Food & Drink"
        }
    ],
    "sg:phone":"+1   ",
    "sg:postcode":"19040",
    "sg:province":"PA",
    "sg:tags":[
        "eating"
    ],
    "wof:name":"Coffee Table Conversation",
    "wof:placetype":"venue"
},
  "geometry": {"coordinates":[-75.121994,40.176126],"type":"Point"}
}