{
  "type": "Feature",
  "properties": {
    "iso:country":"US",
    "sg:address":"428 S Market St",
    "sg:city":"Martinsburg",
    "sg:classifiers":[
        {
            "category":"Health Services",
            "subcategory":"Health Practitioner",
            "type":"Services"
        }
    ],
    "sg:phone":"+1 814 793 3428",
    "sg:postcode":"16662",
    "sg:province":"PA",
    "sg:tags":[
        "therapist",
        "physical"
    ],
    "wof:name":"Crossroads Physical Therapy",
    "wof:placetype":"venue"
},
  "geometry": {"coordinates":[-78.32844299999999,40.305204],"type":"Point"}
}