{
  "type": "Feature",
  "properties": {
    "addr:full":"728 West Ave Jenkintown PA 19046",
    "addr:housenumber":"728",
    "addr:postcode":"19046",
    "addr:street":"West Ave",
    "iso:country":"US",
    "sg:address":"728 West Ave",
    "sg:city":"Jenkintown",
    "sg:classifiers":[
        {
            "category":"Personal",
            "subcategory":"Beauty Salon",
            "type":"Services"
        }
    ],
    "sg:phone":"+1 215 884 0004",
    "sg:postcode":"19046",
    "sg:province":"PA",
    "wof:name":"Rosa Martinez For Artur Studio",
    "wof:placetype":"venue"
},
  "geometry": {"coordinates":[-75.126484,40.096001],"type":"Point"}
}