{
  "type": "Feature",
  "properties": {
    "addr:full":"203 Pine St Punxsutawney PA 15767",
    "addr:housenumber":"203",
    "addr:postcode":"15767",
    "addr:street":"Pine St",
    "iso:country":"US",
    "sg:address":"203 Pine St",
    "sg:city":"Punxsutawney",
    "sg:classifiers":[
        {
            "category":"Social Services",
            "type":"Services"
        }
    ],
    "sg:phone":"+1   ",
    "sg:postcode":"15767",
    "sg:province":"PA",
    "wof:name":"Vision & Blindness Resources",
    "wof:placetype":"venue"
},
  "geometry": {"coordinates":[-78.97280499999999,40.944133],"type":"Point"}
}