{
  "type": "Feature",
  "properties": {
    "iso:country":"US",
    "sg:address":"900 Russellwood Ave",
    "sg:city":"Mc Kees Rocks",
    "sg:classifiers":[
        {
            "category":"Professional",
            "type":"Services"
        }
    ],
    "sg:phone":"+1   ",
    "sg:postcode":"15136",
    "sg:province":"PA",
    "wof:name":"Nail Illusion Inc",
    "wof:placetype":"venue"
},
  "geometry": {"coordinates":[-80.077561,40.473124],"type":"Point"}
}