{
  "type": "Feature",
  "properties": {
    "addr:full":"79 Walnut Ln Duncansville PA 16635",
    "addr:housenumber":"79",
    "addr:postcode":"16635",
    "addr:street":"Walnut Ln",
    "iso:country":"US",
    "sg:address":"79 Walnut Ln",
    "sg:city":"Duncansville",
    "sg:classifiers":[
        {
            "category":"Building & Trades",
            "subcategory":"Construction",
            "type":"Services"
        }
    ],
    "sg:phone":"+1 814 695 6347",
    "sg:postcode":"16635",
    "sg:province":"PA",
    "sg:tags":[
        "excavation",
        "contractor"
    ],
    "wof:name":"Charles Clapper Excavating",
    "wof:placetype":"venue"
},
  "geometry": {"coordinates":[-78.44149400000001,40.397431],"type":"Point"}
}