{
  "type": "Feature",
  "properties": {
    "iso:country":"US",
    "sg:address":"1426 Elm St",
    "sg:city":"Pittsburgh",
    "sg:classifiers":[
        {
            "category":"Professional",
            "type":"Services"
        }
    ],
    "sg:phone":"+1   ",
    "sg:postcode":"15221",
    "sg:province":"PA",
    "wof:name":"G4orce Image Factory",
    "wof:placetype":"venue"
},
  "geometry": {"coordinates":[-79.88196600000001,40.448881],"type":"Point"}
}