{
  "type": "Feature",
  "properties": {
    "iso:country":"US",
    "sg:address":"2340 Franklin St",
    "sg:city":"Johnstown",
    "sg:classifiers":[
        {
            "category":"Bars & Pubs",
            "type":"Food & Drink"
        },
        {
            "category":"Travel",
            "subcategory":"Bed & Breakfast",
            "type":"Entertainment"
        }
    ],
    "sg:phone":"+1 814 288 5810",
    "sg:postcode":"15905",
    "sg:province":"PA",
    "sg:tags":[
        "tavern",
        "inn"
    ],
    "wof:name":"Pike Inn",
    "wof:placetype":"venue"
},
  "geometry": {"coordinates":[-78.934527,40.284196],"type":"Point"}
}