{
  "type": "Feature",
  "properties": {
    "iso:country":"US",
    "sg:address":"215 W Church St",
    "sg:city":"Somerset",
    "sg:classifiers":[
        {
            "category":"Health Services",
            "subcategory":"Doctor",
            "type":"Services"
        }
    ],
    "sg:phone":"+1   ",
    "sg:postcode":"15501",
    "sg:province":"PA",
    "sg:tags":[
        "clinic",
        "medical"
    ],
    "wof:name":"Dr Satish R Nayak",
    "wof:placetype":"venue"
},
  "geometry": {"coordinates":[-79.081378,40.006582],"type":"Point"}
}