{
  "type": "Feature",
  "properties": {
    "addr:full":"15 Piper St Beaver Falls PA 15010",
    "addr:housenumber":"15",
    "addr:postcode":"15010",
    "addr:street":"Piper St",
    "iso:country":"US",
    "sg:address":"15 Piper St",
    "sg:city":"Beaver Falls",
    "sg:classifiers":[
        {
            "category":"Airport",
            "type":"Transportation"
        }
    ],
    "sg:phone":"+1 724 847 4662",
    "sg:postcode":"15010",
    "sg:province":"PA",
    "sg:tags":[
        "executive"
    ],
    "wof:name":"Beaver County Airport",
    "wof:placetype":"venue"
},
  "geometry": {"coordinates":[-80.38776300000001,40.777248],"type":"Point"}
}