{
  "type": "Feature",
  "properties": {
    "iso:country":"US",
    "sg:address":"608 Monges St",
    "sg:city":"Hazleton",
    "sg:classifiers":[
        {
            "category":"Building & Trades",
            "subcategory":"Landscaping Services",
            "type":"Services"
        }
    ],
    "sg:phone":"+1 570 455 1653",
    "sg:postcode":"18201",
    "sg:province":"PA",
    "sg:tags":[
        "landscape",
        "contractor"
    ],
    "wof:name":"Vito's Lawn Care",
    "wof:placetype":"venue"
},
  "geometry": {"coordinates":[-75.958167,40.964394],"type":"Point"}
}