{
  "type": "Feature",
  "properties": {
    "iso:country":"US",
    "sg:address":"665 Forman Rd",
    "sg:city":"Souderton",
    "sg:classifiers":[
        {
            "category":"Wholesale",
            "subcategory":"Stationery",
            "type":"Manufacturing & Wholesale Goods"
        }
    ],
    "sg:phone":"+1 215 721 1753",
    "sg:postcode":"18964",
    "sg:province":"PA",
    "sg:tags":[
        "room",
        "shipping",
        "supply"
    ],
    "wof:name":"B & R Packaging Inc",
    "wof:placetype":"venue"
},
  "geometry": {"coordinates":[-75.35016899999999,40.280046],"type":"Point"}
}