{
  "type": "Feature",
  "properties": {
    "addr:full":"208 Peary Cir Cresson PA 16630",
    "addr:housenumber":"208",
    "addr:postcode":"16630",
    "addr:street":"Peary Cir",
    "iso:country":"US",
    "sg:address":"208 Peary Cir",
    "sg:city":"Cresson",
    "sg:classifiers":[
        {
            "category":"Freight",
            "type":"Transportation"
        }
    ],
    "sg:phone":"+1   ",
    "sg:postcode":"16630",
    "sg:province":"PA",
    "sg:tags":[
        "operator",
        "local",
        "trucking"
    ],
    "wof:name":"Grove Trucking",
    "wof:placetype":"venue"
},
  "geometry": {"coordinates":[-78.59926299999999,40.462855],"type":"Point"}
}