{
  "type": "Feature",
  "properties": {
    "iso:country":"US",
    "sg:address":"3435 Sportsmans Rd",
    "sg:city":"Greencastle",
    "sg:classifiers":[
        {
            "category":"Arts & Performance",
            "subcategory":"Festival",
            "type":"Entertainment"
        }
    ],
    "sg:phone":"+1 717 597 4871",
    "sg:postcode":"17225",
    "sg:province":"PA",
    "sg:tags":[
        "carnival"
    ],
    "wof:name":"Snyder Amusemnet Inc",
    "wof:placetype":"venue"
},
  "geometry": {"coordinates":[-77.766543,39.819728],"type":"Point"}
}