{
  "type": "Feature",
  "properties": {
    "iso:country":"US",
    "sg:address":"1609 E Passyunk Ave",
    "sg:city":"Philadelphia",
    "sg:classifiers":[
        {
            "category":"Personal",
            "subcategory":"Beauty Salon",
            "type":"Services"
        }
    ],
    "sg:phone":"+1 215 462 0147",
    "sg:postcode":"19148",
    "sg:province":"PA",
    "sg:tags":[
        "hair"
    ],
    "sg:website":"www.novo-salon.com/",
    "wof:name":"Novo Salon",
    "wof:placetype":"venue"
},
  "geometry": {"coordinates":[-75.163563,39.929596],"type":"Point"}
}