{
  "type": "Feature",
  "properties": {
    "addr:full":"443 W Baltimore Ave Media PA 19063",
    "addr:housenumber":"443",
    "addr:postcode":"19063",
    "addr:street":"W Baltimore Ave",
    "iso:country":"US",
    "sg:address":"443 W Baltimore Ave",
    "sg:city":"Media",
    "sg:classifiers":[
        {
            "category":"Coffee & Tea",
            "type":"Food & Drink"
        }
    ],
    "sg:menulink":"http://www.allmenus.com/pa/media/125198-starbucks-coffee/menu/",
    "sg:phone":"+1 610 627 9092",
    "sg:postcode":"19063",
    "sg:province":"PA",
    "sg:tags":[
        "american"
    ],
    "wof:name":"Starbucks Coffee",
    "wof:placetype":"venue"
},
  "geometry": {"coordinates":[-75.396715,39.918235],"type":"Point"}
}