{
  "type": "Feature",
  "properties": {
    "iso:country":"US",
    "sg:address":"155 Salem Church Rd",
    "sg:city":"Mechanicsburg",
    "sg:classifiers":[
        {
            "category":"Shopping",
            "subcategory":"Gifts & Souvenirs",
            "type":"Retail Goods"
        }
    ],
    "sg:phone":"+1 717 795 5636",
    "sg:postcode":"17050",
    "sg:province":"PA",
    "sg:tags":[
        "collectible"
    ],
    "wof:name":"Krissecat Inc",
    "wof:placetype":"venue"
},
  "geometry": {"coordinates":[-76.999809,40.239236],"type":"Point"}
}