{
  "type": "Feature",
  "properties": {
    "addr:full":"379 Keneagy Hill Rd Ronks PA 17572",
    "addr:housenumber":"379",
    "addr:postcode":"17572",
    "addr:street":"Keneagy Hill Rd",
    "iso:country":"US",
    "sg:address":"379 Keneagy Hill Rd",
    "sg:city":"Ronks",
    "sg:classifiers":[
        {
            "category":"Building & Trades",
            "subcategory":"Construction",
            "type":"Services"
        }
    ],
    "sg:phone":"+1   ",
    "sg:postcode":"17572",
    "sg:province":"PA",
    "sg:tags":[
        "contractor"
    ],
    "wof:name":"Hawsy Masonry",
    "wof:placetype":"venue"
},
  "geometry": {"coordinates":[-76.106638,39.965811],"type":"Point"}
}