{
  "type": "Feature",
  "properties": {
    "iso:country":"US",
    "sg:address":"216 Beidler Rd",
    "sg:city":"King Of Prussia",
    "sg:classifiers":[
        {
            "category":"Shopping",
            "subcategory":"Computers & Home Electronics",
            "type":"Retail Goods"
        }
    ],
    "sg:phone":"+1 610 337 5996",
    "sg:postcode":"19406",
    "sg:province":"PA",
    "sg:tags":[
        "equipment",
        "dealer"
    ],
    "wof:name":"L & M Computers",
    "wof:placetype":"venue"
},
  "geometry": {"coordinates":[-75.374308,40.112668],"type":"Point"}
}