{
  "type": "Feature",
  "properties": {
    "iso:country":"US",
    "sg:address":"702 Bank St",
    "sg:city":"Bridgeville",
    "sg:classifiers":[
        {
            "category":"Building & Trades",
            "subcategory":"Construction",
            "type":"Services"
        }
    ],
    "sg:phone":"+1   ",
    "sg:postcode":"15017",
    "sg:province":"PA",
    "sg:tags":[
        "house"
    ],
    "wof:name":"Frank J Exler",
    "wof:placetype":"venue"
},
  "geometry": {"coordinates":[-80.107699,40.35441],"type":"Point"}
}