{
  "type": "Feature",
  "properties": {
    "iso:country":"US",
    "sg:address":"218 W 18th St",
    "sg:city":"Hazleton",
    "sg:classifiers":[
        {
            "category":"Shopping",
            "subcategory":"Florist",
            "type":"Retail Goods"
        }
    ],
    "sg:phone":"+1   ",
    "sg:postcode":"18201",
    "sg:province":"PA",
    "wof:name":"My Darlings Floral & Pty Sups",
    "wof:placetype":"venue"
},
  "geometry": {"coordinates":[-75.977081,40.969733],"type":"Point"}
}