{
  "type": "Feature",
  "properties": {
    "iso:country":"US",
    "sg:address":"1536 Rte 481",
    "sg:city":"Charleroi",
    "sg:classifiers":[
        {
            "category":"Autos & Motor Vehicles",
            "subcategory":"Automobile Sales",
            "type":"Retail Goods"
        }
    ],
    "sg:phone":"+1 724 239 5401",
    "sg:postcode":"15022",
    "sg:province":"PA",
    "sg:tags":[
        "car",
        "dealer"
    ],
    "wof:name":"N & N Auto Sales",
    "wof:placetype":"venue"
},
  "geometry": {"coordinates":[-79.954739,40.130183],"type":"Point"}
}