{
  "type": "Feature",
  "properties": {
    "addr:full":"20254 Rte 19 Cranberry Twp PA 16066",
    "addr:postcode":"20254;16066",
    "addr:street":"Rte 19",
    "iso:country":"US",
    "sg:address":"20254 Rte 19",
    "sg:city":"Cranberry Twp",
    "sg:classifiers":[
        {
            "category":"Home & Garden",
            "subcategory":"Furniture",
            "type":"Retail Goods"
        }
    ],
    "sg:phone":"+1 724 935 1130",
    "sg:postcode":"16066",
    "sg:province":"PA",
    "sg:tags":[
        "trade",
        "cabinet"
    ],
    "wof:name":"Kitchen Innovations Peter",
    "wof:placetype":"venue"
},
  "geometry": {"coordinates":[-80.102453,40.689209],"type":"Point"}
}