{
  "type": "Feature",
  "properties": {
    "addr:full":"121 Chestnut St Philadelphia PA 19106",
    "addr:housenumber":"121",
    "addr:postcode":"19106",
    "addr:street":"Chestnut St",
    "iso:country":"US",
    "sg:address":"121 Chestnut St",
    "sg:city":"Philadelphia",
    "sg:classifiers":[
        {
            "category":"Personal",
            "type":"Services"
        }
    ],
    "sg:phone":"+1 215 629 1655",
    "sg:postcode":"19106",
    "sg:province":"PA",
    "sg:tags":[
        "party",
        "planning",
        "event"
    ],
    "sg:website":"www.whimsforrent.com",
    "wof:name":"Whims For Rent",
    "wof:placetype":"venue"
},
  "geometry": {"coordinates":[-75.14361,39.948332],"type":"Point"}
}