{
  "type": "Feature",
  "properties": {
    "addr:full":"307 Front Mountain Rd Allensville PA 17002",
    "addr:housenumber":"307",
    "addr:postcode":"17002",
    "addr:street":"Front Mountain Rd",
    "iso:country":"US",
    "sg:address":"307 Front Mountain Rd",
    "sg:city":"Allensville",
    "sg:classifiers":[
        {
            "category":"Farming",
            "subcategory":"Farm",
            "type":"Manufacturing & Wholesale Goods"
        }
    ],
    "sg:phone":"+1   ",
    "sg:postcode":"17002",
    "sg:province":"PA",
    "sg:tags":[
        "crop",
        "general"
    ],
    "wof:name":"John B Byler",
    "wof:placetype":"venue"
},
  "geometry": {"coordinates":[-77.819669,40.51689],"type":"Point"}
}