{
  "type": "Feature",
  "properties": {
    "iso:country":"US",
    "sg:address":"806 Poplar St",
    "sg:city":"Scranton",
    "sg:classifiers":[
        {
            "category":"Food & Beverages",
            "subcategory":"Specialty",
            "type":"Retail Goods"
        }
    ],
    "sg:phone":"+1   ",
    "sg:postcode":"18510",
    "sg:province":"PA",
    "sg:tags":[
        "vitamin",
        "basic"
    ],
    "wof:name":"Herbal Shoppe",
    "wof:placetype":"venue"
},
  "geometry": {"coordinates":[-75.647929,41.416019],"type":"Point"}
}