{
  "type": "Feature",
  "properties": {
    "iso:country":"US",
    "sg:address":"2200 N Beaver St",
    "sg:city":"York",
    "sg:classifiers":[
        {
            "category":"Insurance",
            "subcategory":"Insurance Agent",
            "type":"Services"
        }
    ],
    "sg:phone":"+1 717 309 3648",
    "sg:postcode":"17404",
    "sg:province":"PA",
    "wof:name":"Medical Insurance Associates",
    "wof:placetype":"venue"
},
  "geometry": {"coordinates":[-76.739096,39.99051],"type":"Point"}
}