{
  "type": "Feature",
  "properties": {
    "iso:country":"US",
    "sg:address":"406 Delaware Ave",
    "sg:city":"Palmerton",
    "sg:classifiers":[
        {
            "category":"Wholesale",
            "subcategory":"Auto Parts",
            "type":"Manufacturing & Wholesale Goods"
        }
    ],
    "sg:phone":"+1 610 826 4702",
    "sg:postcode":"18071",
    "sg:province":"PA",
    "sg:tags":[
        "supply"
    ],
    "wof:name":"Palmerton Auto Parts Inc",
    "wof:placetype":"venue"
},
  "geometry": {"coordinates":[-75.60475599999999,40.803697],"type":"Point"}
}