{
  "type": "Feature",
  "properties": {
    "addr:full":"821 Ridge Ave Pittsburgh PA 15212",
    "addr:housenumber":"821",
    "addr:postcode":"15212",
    "addr:street":"Ridge Ave",
    "iso:country":"US",
    "sg:address":"821 Ridge Ave",
    "sg:city":"Pittsburgh",
    "sg:classifiers":[
        {
            "category":"Education",
            "subcategory":"Junior College",
            "type":"Public Place"
        }
    ],
    "sg:phone":"+1   ",
    "sg:postcode":"15212",
    "sg:province":"PA",
    "wof:name":"Allegheny Campus Book Store",
    "wof:placetype":"venue"
},
  "geometry": {"coordinates":[-80.015918,40.450123],"type":"Point"}
}