{
  "type": "Feature",
  "properties": {
    "iso:country":"US",
    "sg:address":"1459 Buttonwood Ln",
    "sg:city":"Warminster",
    "sg:classifiers":[
        {
            "category":"Building & Trades",
            "subcategory":"Construction",
            "type":"Services"
        }
    ],
    "sg:phone":"+1 215 672 0886",
    "sg:postcode":"18974",
    "sg:province":"PA",
    "sg:tags":[
        "painter"
    ],
    "wof:name":"Hodgkinson Home Improvement",
    "wof:placetype":"venue"
},
  "geometry": {"coordinates":[-75.11502,40.223933],"type":"Point"}
}