{
  "type": "Feature",
  "properties": {
    "iso:country":"US",
    "sg:address":"4836 E Trindle Rd",
    "sg:city":"Mechanicsburg",
    "sg:classifiers":[
        {
            "category":"Health Services",
            "subcategory":"Doctor",
            "type":"Services"
        },
        {
            "category":"Health Services",
            "subcategory":"Dentist",
            "type":"Services"
        }
    ],
    "sg:phone":"+1 717 737 5834",
    "sg:postcode":"17050",
    "sg:province":"PA",
    "sg:tags":[
        "surgeon",
        "oral",
        "pediatric"
    ],
    "sg:website":"www.kidsdentaloffice.com",
    "wof:name":"Cramer Robt DDS",
    "wof:placetype":"venue"
},
  "geometry": {"coordinates":[-76.968597,40.226601],"type":"Point"}
}