{
  "type": "Feature",
  "properties": {
    "iso:country":"US",
    "sg:address":"1200 Reedsdale St Ste 2",
    "sg:city":"Pittsburgh",
    "sg:classifiers":[
        {
            "category":"Health Services",
            "subcategory":"Hospital",
            "type":"Services"
        }
    ],
    "sg:phone":"+1 412 323 4542",
    "sg:postcode":"15233",
    "sg:province":"PA",
    "wof:name":"Mercy Bhvrl Hlthprt of the Pttsbrgh Mrcy Hlth Syst",
    "wof:placetype":"venue"
},
  "geometry": {"coordinates":[-80.020302,40.447899],"type":"Point"}
}