{
  "type": "Feature",
  "properties": {
    "addr:full":"6601 State Rd Philadelphia PA 19135",
    "addr:housenumber":"6601",
    "addr:postcode":"19135",
    "addr:street":"State Rd",
    "iso:country":"US",
    "sg:address":"6601 State Rd",
    "sg:city":"Philadelphia",
    "sg:classifiers":[
        {
            "category":"Autos & Motor Vehicles",
            "subcategory":"Automobile Sales",
            "type":"Retail Goods"
        },
        {
            "category":"Wholesale",
            "subcategory":"Farm Supplies",
            "type":"Manufacturing & Wholesale Goods"
        },
        {
            "category":"Autos & Motor Vehicles",
            "subcategory":"Auto Supplies",
            "type":"Retail Goods"
        },
        {
            "category":"Wholesale",
            "subcategory":"Auto Parts",
            "type":"Manufacturing & Wholesale Goods"
        },
        {
            "category":"Retail",
            "subcategory":"Auto Repair",
            "type":"Services"
        }
    ],
    "sg:phone":"+1 215 338 5400",
    "sg:postcode":"19135",
    "sg:province":"PA",
    "sg:tags":[
        "wheel",
        "used",
        "vehicles-supplies",
        "drive",
        "transport",
        "four",
        "equipment",
        "truck",
        "trailer",
        "tractor"
    ],
    "sg:website":"http://www.bluediamondparts.com",
    "wof:name":"Freedom International Trucks",
    "wof:placetype":"venue"
},
  "geometry": {"coordinates":[-75.03731500000001,40.022985],"type":"Point"}
}