{
  "type": "Feature",
  "properties": {
    "iso:country":"US",
    "sg:address":"360 Scott St",
    "sg:city":"Wilkes Barre",
    "sg:classifiers":[
        {
            "category":"Shopping",
            "subcategory":"Gifts & Souvenirs",
            "type":"Retail Goods"
        }
    ],
    "sg:phone":"+1   ",
    "sg:postcode":"18702",
    "sg:province":"PA",
    "sg:tags":[
        "jewelry"
    ],
    "wof:name":"E M Foley",
    "wof:placetype":"venue"
},
  "geometry": {"coordinates":[-75.86116,41.247572],"type":"Point"}
}