{
  "type": "Feature",
  "properties": {
    "iso:country":"US",
    "sg:address":"7223 Ogontz Ave",
    "sg:city":"Philadelphia",
    "sg:classifiers":[
        {
            "category":"Professional",
            "subcategory":"Business Services",
            "type":"Services"
        }
    ],
    "sg:phone":"+1   ",
    "sg:postcode":"19138",
    "sg:province":"PA",
    "wof:name":"Omega Record",
    "wof:placetype":"venue"
},
  "geometry": {"coordinates":[-75.154347,40.064756],"type":"Point"}
}