{
  "type": "Feature",
  "properties": {
    "iso:country":"US",
    "sg:address":"51 E Germantown Pike",
    "sg:city":"Norristown",
    "sg:classifiers":[
        {
            "category":"Shopping",
            "subcategory":"Discount & Variety Stores",
            "type":"Retail Goods"
        }
    ],
    "sg:phone":"+1 610 239 6311",
    "sg:postcode":"19401",
    "sg:province":"PA",
    "wof:name":"Amazing Savings",
    "wof:placetype":"venue"
},
  "geometry": {"coordinates":[-75.307181,40.138086],"type":"Point"}
}