{
  "type": "Feature",
  "properties": {
    "iso:country":"US",
    "sg:address":"300 E Main St",
    "sg:city":"Evans City",
    "sg:classifiers":[
        {
            "category":"Autos & Motor Vehicles",
            "subcategory":"Fuel & Gas Station",
            "type":"Retail Goods"
        }
    ],
    "sg:phone":"+1 724 538 9796",
    "sg:postcode":"16033",
    "sg:province":"PA",
    "sg:website":"www.kwikfill.com",
    "wof:name":"Kwik-Fill S-68",
    "wof:placetype":"venue"
},
  "geometry": {"coordinates":[-80.061401,40.769402],"type":"Point"}
}