{
  "type": "Feature",
  "properties": {
    "addr:full":"40 Willow St Adamstown PA 19501",
    "addr:housenumber":"40",
    "addr:postcode":"19501",
    "addr:street":"Willow St",
    "iso:country":"US",
    "sg:address":"40 Willow St",
    "sg:city":"Adamstown",
    "sg:classifiers":[
        {
            "category":"Shopping",
            "subcategory":"Used Merchandise",
            "type":"Retail Goods"
        }
    ],
    "sg:phone":"+1 717 484 4005",
    "sg:postcode":"19501",
    "sg:province":"PA",
    "sg:tags":[
        "antique",
        "store"
    ],
    "wof:name":"Tex Johnson Antiques",
    "wof:placetype":"venue"
},
  "geometry": {"coordinates":[-76.056924,40.241579],"type":"Point"}
}