{
  "type": "Feature",
  "properties": {
    "iso:country":"US",
    "sg:address":"1033 Water St",
    "sg:city":"Wrightsville",
    "sg:classifiers":[
        {
            "category":"Manufacturing",
            "subcategory":"Metals",
            "type":"Manufacturing & Wholesale Goods"
        }
    ],
    "sg:phone":"+1   ",
    "sg:postcode":"17368",
    "sg:province":"PA",
    "sg:tags":[
        "custom",
        "mechanical",
        "fabrication",
        "contractor"
    ],
    "wof:name":"Stewart Welding & Fabricating",
    "wof:placetype":"venue"
},
  "geometry": {"coordinates":[-76.526291,39.982122],"type":"Point"}
}