{
  "type": "Feature",
  "properties": {
    "iso:country":"US",
    "sg:address":"1445 Sanderson Ave",
    "sg:city":"Scranton",
    "sg:classifiers":[
        {
            "category":"Shopping",
            "subcategory":"Clothing, Apparel, & Fashions",
            "type":"Retail Goods"
        }
    ],
    "sg:phone":"+1 570 346 2550",
    "sg:postcode":"18509",
    "sg:province":"PA",
    "wof:name":"Wigs By Karen",
    "wof:placetype":"venue"
},
  "geometry": {"coordinates":[-75.653058,41.427432],"type":"Point"}
}