{
  "type": "Feature",
  "properties": {
    "iso:country":"US",
    "sg:address":"1997 N 63rd St",
    "sg:city":"Philadelphia",
    "sg:classifiers":[
        {
            "category":"Organizations",
            "subcategory":"Religious Organization",
            "type":"Services"
        }
    ],
    "sg:phone":"+1 215 871 3223",
    "sg:postcode":"19151",
    "sg:province":"PA",
    "sg:tags":[
        "church"
    ],
    "wof:name":"Jesus Holy Temple",
    "wof:placetype":"venue"
},
  "geometry": {"coordinates":[-75.247344,39.985135],"type":"Point"}
}