{
  "type": "Feature",
  "properties": {
    "iso:country":"US",
    "sg:address":"95 Isabella St",
    "sg:city":"North East",
    "sg:classifiers":[
        {
            "category":"Building & Trades",
            "subcategory":"Construction",
            "type":"Services"
        }
    ],
    "sg:phone":"+1   ",
    "sg:postcode":"16428",
    "sg:province":"PA",
    "sg:tags":[
        "concrete",
        "contractor"
    ],
    "wof:name":"Seman Concrete",
    "wof:placetype":"venue"
},
  "geometry": {"coordinates":[-79.82710899999999,42.221277],"type":"Point"}
}