{
  "type": "Feature",
  "properties": {
    "addr:full":"7626 City Ave Philadelphia PA 19151",
    "addr:housenumber":"7626",
    "addr:postcode":"19151",
    "addr:street":"City Ave",
    "iso:country":"US",
    "sg:address":"7626 City Ave",
    "sg:city":"Philadelphia",
    "sg:classifiers":[
        {
            "category":"Personal",
            "subcategory":"Beauty Salon",
            "type":"Services"
        }
    ],
    "sg:phone":"+1   ",
    "sg:postcode":"19151",
    "sg:province":"PA",
    "sg:tags":[
        "shop"
    ],
    "wof:name":"Creative Hairdressers",
    "wof:placetype":"venue"
},
  "geometry": {"coordinates":[-75.27293,39.97847],"type":"Point"}
}