{
  "type": "Feature",
  "properties": {
    "addr:full":"84 Lycoming Mall Muncy PA 17756",
    "addr:housenumber":"84",
    "addr:postcode":"17756",
    "addr:street":"Lycoming Mall",
    "iso:country":"US",
    "sg:address":"84 Lycoming Mall",
    "sg:city":"Muncy",
    "sg:classifiers":[
        {
            "category":"Shopping",
            "subcategory":"Department Store",
            "type":"Retail Goods"
        }
    ],
    "sg:phone":"+1   ",
    "sg:postcode":"17756",
    "sg:province":"PA",
    "wof:name":"Value City 177",
    "wof:placetype":"venue"
},
  "geometry": {"coordinates":[-76.828788,41.243806],"type":"Point"}
}