{
  "type": "Feature",
  "properties": {
    "addr:full":"594 W Chocolate Ave Hershey PA 17033",
    "addr:housenumber":"594",
    "addr:postcode":"17033",
    "addr:street":"W Chocolate Ave",
    "iso:country":"US",
    "sg:address":"594 W Chocolate Ave",
    "sg:city":"Hershey",
    "sg:classifiers":[
        {
            "category":"Manufacturing",
            "subcategory":"Printing",
            "type":"Manufacturing & Wholesale Goods"
        }
    ],
    "sg:phone":"+1 717 534 1992",
    "sg:postcode":"17033",
    "sg:province":"PA",
    "sg:tags":[
        "commercial"
    ],
    "sg:website":"www.chocolatecovers.com",
    "wof:name":"Chocolate Covers",
    "wof:placetype":"venue"
},
  "geometry": {"coordinates":[-76.662943,40.280778],"type":"Point"}
}