{
  "type": "Feature",
  "properties": {
    "iso:country":"US",
    "sg:address":"4329 Lancaster Ave",
    "sg:city":"Philadelphia",
    "sg:classifiers":[
        {
            "category":"Health Services",
            "subcategory":"Doctor",
            "type":"Services"
        }
    ],
    "sg:phone":"+1 215 387 1022",
    "sg:postcode":"19104",
    "sg:province":"PA",
    "wof:name":"Strickland David MD",
    "wof:placetype":"venue"
},
  "geometry": {"coordinates":[-75.210375,39.968291],"type":"Point"}
}