{
  "type": "Feature",
  "properties": {
    "iso:country":"US",
    "sg:address":"4401 Deer Path Rd",
    "sg:city":"Harrisburg",
    "sg:classifiers":[
        {
            "category":"Insurance",
            "subcategory":"Hazard Insurance",
            "type":"Services"
        },
        {
            "category":"Insurance",
            "subcategory":"Health Insurance",
            "type":"Services"
        }
    ],
    "sg:phone":"+1 717 260 6800",
    "sg:postcode":"17110",
    "sg:province":"PA",
    "sg:tags":[
        "dental"
    ],
    "wof:name":"Ucci",
    "wof:placetype":"venue"
},
  "geometry": {"coordinates":[-76.87455,40.327011],"type":"Point"}
}