{
  "type": "Feature",
  "properties": {
    "iso:country":"US",
    "sg:address":"1100 Macdade Blvd",
    "sg:city":"Darby",
    "sg:classifiers":[
        {
            "category":"Wholesale",
            "subcategory":"Construction Materials",
            "type":"Manufacturing & Wholesale Goods"
        }
    ],
    "sg:phone":"+1 610 532 3010",
    "sg:postcode":"19023",
    "sg:province":"PA",
    "sg:tags":[
        "supply",
        "heating",
        "systems-wholesale",
        "equipment",
        "part",
        "plumbing",
        "fixtures"
    ],
    "wof:name":"Ferguson",
    "wof:placetype":"venue"
},
  "geometry": {"coordinates":[-75.28231,39.909531],"type":"Point"}
}