{
  "type": "Feature",
  "properties": {
    "addr:full":"500 W Chester Pike Havertown PA 19083",
    "addr:housenumber":"500",
    "addr:postcode":"19083",
    "addr:street":"W Chester Pike",
    "iso:country":"US",
    "sg:address":"500 W Chester Pike",
    "sg:city":"Havertown",
    "sg:classifiers":[
        {
            "category":"Autos & Motor Vehicles",
            "subcategory":"Automobile Sales",
            "type":"Retail Goods"
        }
    ],
    "sg:phone":"+1 215 365 4030",
    "sg:postcode":"19083",
    "sg:province":"PA",
    "sg:tags":[
        "car",
        "dealer"
    ],
    "wof:name":"Auto Rider",
    "wof:placetype":"venue"
},
  "geometry": {"coordinates":[-75.30597899999999,39.970621],"type":"Point"}
}