{
  "type": "Feature",
  "properties": {
    "iso:country":"US",
    "sg:address":"878 Century Dr",
    "sg:city":"Mechanicsburg",
    "sg:classifiers":[
        {
            "category":"Organizations",
            "subcategory":"Professional Association",
            "type":"Services"
        }
    ],
    "sg:phone":"+1   ",
    "sg:postcode":"17055",
    "sg:province":"PA",
    "sg:tags":[
        "membership"
    ],
    "wof:name":"Pennsylvnia Assn Schl Retirees",
    "wof:placetype":"venue"
},
  "geometry": {"coordinates":[-76.963156,40.212789],"type":"Point"}
}