{
  "type": "Feature",
  "properties": {
    "iso:country":"US",
    "sg:address":"1380 E Penn St",
    "sg:city":"Muncy",
    "sg:classifiers":[
        {
            "category":"Restaurant",
            "type":"Food & Drink"
        }
    ],
    "sg:phone":"+1 570 546 3333",
    "sg:postcode":"17756",
    "sg:province":"PA",
    "wof:name":"Subway Sandwiches & Salads",
    "wof:placetype":"venue"
},
  "geometry": {"coordinates":[-76.76033099999999,41.211065],"type":"Point"}
}