{
  "type": "Feature",
  "properties": {
    "iso:country":"US",
    "sg:address":"534 Franklin Ave",
    "sg:city":"Aliquippa",
    "sg:classifiers":[
        {
            "category":"Government",
            "subcategory":"Office",
            "type":"Public Place"
        }
    ],
    "sg:phone":"+1 724 378 3510",
    "sg:postcode":"15001",
    "sg:province":"PA",
    "wof:name":"Intermediate Punishment Div",
    "wof:placetype":"venue"
},
  "geometry": {"coordinates":[-80.249878,40.614498],"type":"Point"}
}