{
  "type": "Feature",
  "properties": {
    "addr:full":"901 N 3rd St Fl 1 Harrisburg PA 17102",
    "addr:housenumber":"901;1",
    "addr:postcode":"17102",
    "addr:street":"N 3Rd St",
    "iso:country":"US",
    "sg:address":"901 N 3rd St Fl 1",
    "sg:city":"Harrisburg",
    "sg:classifiers":[
        {
            "category":"Food & Beverages",
            "subcategory":"Groceries & Convenience Stores",
            "type":"Retail Goods"
        }
    ],
    "sg:phone":"+1 717 232 6643",
    "sg:postcode":"17102",
    "sg:province":"PA",
    "wof:name":"One Stop",
    "wof:placetype":"venue"
},
  "geometry": {"coordinates":[-76.886516,40.266729],"type":"Point"}
}