{
  "type": "Feature",
  "properties": {
    "addr:full":"320 W High St Pottstown PA 19464",
    "addr:housenumber":"320",
    "addr:postcode":"19464",
    "addr:street":"W High St",
    "iso:country":"US",
    "sg:address":"320 W High St",
    "sg:city":"Pottstown",
    "sg:classifiers":[
        {
            "category":"Organizations",
            "subcategory":"Community Association",
            "type":"Services"
        }
    ],
    "sg:phone":"+1 610 326 4960",
    "sg:postcode":"19464",
    "sg:province":"PA",
    "sg:tags":[
        "fraternal"
    ],
    "wof:name":"Loyal Order Of Moose",
    "wof:placetype":"venue"
},
  "geometry": {"coordinates":[-75.66597400000001,40.248979],"type":"Point"}
}