{
  "type": "Feature",
  "properties": {
    "iso:country":"US",
    "sg:address":"1100 Windrim Ave",
    "sg:city":"Philadelphia",
    "sg:classifiers":[
        {
            "category":"Organizations",
            "subcategory":"Religious Organization",
            "type":"Services"
        }
    ],
    "sg:phone":"+1 215 324 7774",
    "sg:postcode":"19141",
    "sg:province":"PA",
    "sg:tags":[
        "church"
    ],
    "wof:name":"Praise Temple Apostolic Way",
    "wof:placetype":"venue"
},
  "geometry": {"coordinates":[-75.14153899999999,40.03224],"type":"Point"}
}