{
  "type": "Feature",
  "properties": {
    "addr:full":"2300 W Cambria St Philadelphia PA 19132",
    "addr:housenumber":"2300",
    "addr:postcode":"19132",
    "addr:street":"W Cambria St",
    "iso:country":"US",
    "sg:address":"2300 W Cambria St",
    "sg:city":"Philadelphia",
    "sg:classifiers":[
        {
            "category":"Education",
            "subcategory":"School",
            "type":"Public Place"
        }
    ],
    "sg:phone":"+1 215 227 4411",
    "sg:postcode":"19132",
    "sg:province":"PA",
    "sg:tags":[
        "high",
        "middle",
        "elementary"
    ],
    "wof:name":"School District of Philadelphia",
    "wof:placetype":"venue"
},
  "geometry": {"coordinates":[-75.168509,39.998775],"type":"Point"}
}