{
  "type": "Feature",
  "properties": {
    "iso:country":"US",
    "sg:address":"810 Willow Valley Sq",
    "sg:city":"Lancaster",
    "sg:classifiers":[
        {
            "category":"Banks & Credit Unions",
            "subcategory":"Bank",
            "type":"Services"
        }
    ],
    "sg:phone":"+1   ",
    "sg:postcode":"17602",
    "sg:province":"PA",
    "sg:tags":[
        "state",
        "commercial"
    ],
    "wof:name":"Willow Valley North Office",
    "wof:placetype":"venue"
},
  "geometry": {"coordinates":[-76.28116199999999,39.998409],"type":"Point"}
}