{
  "type": "Feature",
  "properties": {
    "addr:full":"4326 Sunnyside Dr Doylestown PA 18902",
    "addr:housenumber":"4326",
    "addr:postcode":"18902",
    "addr:street":"Sunnyside Dr",
    "iso:country":"US",
    "sg:address":"4326 Sunnyside Dr",
    "sg:city":"Doylestown",
    "sg:classifiers":[
        {
            "category":"Shopping",
            "subcategory":"Discount & Variety Stores",
            "type":"Retail Goods"
        }
    ],
    "sg:phone":"+1   ",
    "sg:postcode":"18902",
    "sg:province":"PA",
    "sg:tags":[
        "merchandise",
        "general"
    ],
    "wof:name":"R K Enterprise Assoc Inc",
    "wof:placetype":"venue"
},
  "geometry": {"coordinates":[-76.65781699999999,39.905764],"type":"Point"}
}