{
  "type": "Feature",
  "properties": {
    "iso:country":"US",
    "sg:address":"711 Sansom St",
    "sg:city":"Philadelphia",
    "sg:classifiers":[
        {
            "category":"Manufacturing",
            "subcategory":"Jewelry",
            "type":"Manufacturing & Wholesale Goods"
        }
    ],
    "sg:phone":"+1 215 627 7534",
    "sg:postcode":"19106",
    "sg:province":"PA",
    "wof:name":"F H Design",
    "wof:placetype":"venue"
},
  "geometry": {"coordinates":[-75.153944,39.948833],"type":"Point"}
}