{
  "type": "Feature",
  "properties": {
    "addr:full":"1313 Riverview Rd Clearfield PA 16830",
    "addr:housenumber":"1313",
    "addr:postcode":"16830",
    "addr:street":"Riverview Rd",
    "iso:country":"US",
    "sg:address":"1313 Riverview Rd",
    "sg:city":"Clearfield",
    "sg:classifiers":[
        {
            "category":"Manufacturing",
            "subcategory":"Glass & Minerals",
            "type":"Manufacturing & Wholesale Goods"
        },
        {
            "category":"Shopping",
            "type":"Retail Goods"
        }
    ],
    "sg:phone":"+1 814 765 7776",
    "sg:postcode":"16830",
    "sg:province":"PA",
    "sg:tags":[
        "excavating",
        "monument",
        "cemetery",
        "sand",
        "accessory"
    ],
    "wof:name":"Cuetara-Hile Memorial Center",
    "wof:placetype":"venue"
},
  "geometry": {"coordinates":[-78.45508700000001,41.007156],"type":"Point"}
}