{
  "type": "Feature",
  "properties": {
    "iso:country":"US",
    "sg:address":"215 Executive Dr",
    "sg:city":"Cranberry Twp",
    "sg:classifiers":[
        {
            "category":"Health Services",
            "subcategory":"Clinic",
            "type":"Services"
        }
    ],
    "sg:phone":"+1 724 934 8350",
    "sg:postcode":"16066",
    "sg:province":"PA",
    "sg:tags":[
        "counseling",
        "mental"
    ],
    "wof:name":"McCauley Lisa Psychotherapist",
    "wof:placetype":"venue"
},
  "geometry": {"coordinates":[-80.107305,40.685583],"type":"Point"}
}