{
  "type": "Feature",
  "properties": {
    "addr:full":"426 E Noble St Nanticoke PA 18634",
    "addr:housenumber":"426",
    "addr:postcode":"18634",
    "addr:street":"E Noble St",
    "iso:country":"US",
    "sg:address":"426 E Noble St",
    "sg:city":"Nanticoke",
    "sg:classifiers":[
        {
            "category":"Building & Trades",
            "subcategory":"Construction",
            "type":"Services"
        }
    ],
    "sg:phone":"+1 570 740 6115",
    "sg:postcode":"18634",
    "sg:province":"PA",
    "sg:tags":[
        "insulation",
        "heat",
        "contractor"
    ],
    "wof:name":"B & N Insulation",
    "wof:placetype":"venue"
},
  "geometry": {"coordinates":[-75.993813,41.202677],"type":"Point"}
}