{
  "type": "Feature",
  "properties": {
    "iso:country":"US",
    "sg:address":"1305 W Rockland St",
    "sg:city":"Philadelphia",
    "sg:classifiers":[
        {
            "category":"Food & Beverages",
            "subcategory":"Groceries & Convenience Stores",
            "type":"Retail Goods"
        }
    ],
    "sg:phone":"+1 215 329 2511",
    "sg:postcode":"19141",
    "sg:province":"PA",
    "wof:name":"Sine Grocery",
    "wof:placetype":"venue"
},
  "geometry": {"coordinates":[-75.145171,40.027518],"type":"Point"}
}