{
  "type": "Feature",
  "properties": {
    "addr:full":"300 Penn Center Blvd Pittsburgh PA 15235",
    "addr:housenumber":"300",
    "addr:postcode":"15235",
    "addr:street":"Penn Center Blvd",
    "iso:country":"US",
    "sg:address":"300 Penn Center Blvd",
    "sg:city":"Pittsburgh",
    "sg:classifiers":[
        {
            "category":"Insurance",
            "subcategory":"Title Insurance",
            "type":"Services"
        }
    ],
    "sg:phone":"+1   ",
    "sg:postcode":"15235",
    "sg:province":"PA",
    "sg:tags":[
        "underwriter"
    ],
    "wof:name":"Direct Settlement Services LP",
    "wof:placetype":"venue"
},
  "geometry": {"coordinates":[-79.811657,40.426719],"type":"Point"}
}