{
  "type": "Feature",
  "properties": {
    "addr:full":"434 Main St Irwin PA 15642",
    "addr:housenumber":"434",
    "addr:postcode":"15642",
    "addr:street":"Main St",
    "iso:country":"US",
    "sg:address":"434 Main St",
    "sg:city":"Irwin",
    "sg:classifiers":[
        {
            "category":"Professional",
            "subcategory":"Lawyer & Legal Services",
            "type":"Services"
        }
    ],
    "sg:phone":"+1 724 863 6700",
    "sg:postcode":"15642",
    "sg:province":"PA",
    "sg:tags":[
        "attorney"
    ],
    "wof:name":"Ronald W Anderson Attorney",
    "wof:placetype":"venue"
},
  "geometry": {"coordinates":[-79.71131800000001,40.331332],"type":"Point"}
}