{
  "type": "Feature",
  "properties": {
    "iso:country":"US",
    "sg:address":"143 Main St",
    "sg:city":"Watsontown",
    "sg:classifiers":[
        {
            "category":"Cinema",
            "subcategory":"Movie Rental",
            "type":"Entertainment"
        }
    ],
    "sg:phone":"+1 570 538 5587",
    "sg:postcode":"17777",
    "sg:province":"PA",
    "sg:tags":[
        "leasing",
        "video",
        "disc",
        "tape"
    ],
    "wof:name":"Movie Mart",
    "wof:placetype":"venue"
},
  "geometry": {"coordinates":[-76.861726,41.082487],"type":"Point"}
}