{
  "type": "Feature",
  "properties": {
    "addr:full":"612 Davidson Dr Rochester PA 15074",
    "addr:housenumber":"612",
    "addr:postcode":"15074",
    "addr:street":"Davidson Dr",
    "iso:country":"US",
    "sg:address":"612 Davidson Dr",
    "sg:city":"Rochester",
    "sg:classifiers":[
        {
            "category":"Building & Trades",
            "subcategory":"Construction",
            "type":"Services"
        }
    ],
    "sg:phone":"+1 724 774 2575",
    "sg:postcode":"15074",
    "sg:province":"PA",
    "sg:tags":[
        "carpenter"
    ],
    "wof:name":"Jeffrey Carpenter",
    "wof:placetype":"venue"
},
  "geometry": {"coordinates":[-80.282669,40.717717],"type":"Point"}
}