{
  "type": "Feature",
  "properties": {
    "iso:country":"US",
    "sg:address":"34 Tucquan Glen Rd",
    "sg:city":"Holtwood",
    "sg:classifiers":[
        {
            "category":"Building & Trades",
            "subcategory":"Landscaping Services",
            "type":"Services"
        }
    ],
    "sg:phone":"+1   ",
    "sg:postcode":"17532",
    "sg:province":"PA",
    "wof:name":"Paul Wissler",
    "wof:placetype":"venue"
},
  "geometry": {"coordinates":[-76.294391,39.891055],"type":"Point"}
}