{
  "type": "Feature",
  "properties": {
    "iso:country":"US",
    "sg:address":"627 Mumper Ln",
    "sg:city":"Dillsburg",
    "sg:classifiers":[
        {
            "category":"Shopping",
            "subcategory":"Used Merchandise",
            "type":"Retail Goods"
        }
    ],
    "sg:phone":"+1   ",
    "sg:postcode":"17019",
    "sg:province":"PA",
    "wof:name":"Mowery Antiques",
    "wof:placetype":"venue"
},
  "geometry": {"coordinates":[-77.00414499999999,40.114139],"type":"Point"}
}