{
  "type": "Feature",
  "properties": {
    "iso:country":"US",
    "sg:address":"12321 Culbertson Dr",
    "sg:city":"Edinboro",
    "sg:classifiers":[
        {
            "category":"Mining & Drilling",
            "type":"Manufacturing & Wholesale Goods"
        }
    ],
    "sg:phone":"+1 814 734 1496",
    "sg:postcode":"16412",
    "sg:province":"PA",
    "sg:tags":[
        "field",
        "oil"
    ],
    "wof:name":"Mountain Resources Inc",
    "wof:placetype":"venue"
},
  "geometry": {"coordinates":[-80.15016799999999,41.87987],"type":"Point"}
}