{
  "type": "Feature",
  "properties": {
    "iso:country":"US",
    "sg:address":"1030 S 13th St",
    "sg:city":"Harrisburg",
    "sg:classifiers":[
        {
            "category":"Food & Beverages",
            "subcategory":"Groceries & Convenience Stores",
            "type":"Retail Goods"
        }
    ],
    "sg:phone":"+1 717 238 8686",
    "sg:postcode":"17104",
    "sg:province":"PA",
    "wof:name":"K & H Supermarket",
    "wof:placetype":"venue"
},
  "geometry": {"coordinates":[-76.86426299999999,40.251656],"type":"Point"}
}