{
  "type": "Feature",
  "properties": {
    "addr:full":"512 W King St Malvern PA 19355",
    "addr:housenumber":"512",
    "addr:postcode":"19355",
    "addr:street":"W King St",
    "iso:country":"US",
    "sg:address":"512 W King St",
    "sg:city":"Malvern",
    "sg:classifiers":[
        {
            "category":"Autos & Motor Vehicles",
            "subcategory":"Fuel & Gas Station",
            "type":"Retail Goods"
        }
    ],
    "sg:phone":"+1   ",
    "sg:postcode":"19355",
    "sg:province":"PA",
    "sg:tags":[
        "car",
        "station",
        "wash"
    ],
    "wof:name":"Gentle Touch Car Wash",
    "wof:placetype":"venue"
},
  "geometry": {"coordinates":[-75.522564,40.033566],"type":"Point"}
}