{
  "type": "Feature",
  "properties": {
    "iso:country":"US",
    "sg:address":"505 Main St",
    "sg:city":"Leesport",
    "sg:classifiers":[
        {
            "category":"Personal",
            "subcategory":"Beauty Salon",
            "type":"Services"
        }
    ],
    "sg:phone":"+1 610 926 4432",
    "sg:postcode":"19533",
    "sg:province":"PA",
    "wof:name":"Reber's Mildred Beauty Shop",
    "wof:placetype":"venue"
},
  "geometry": {"coordinates":[-75.973344,40.439848],"type":"Point"}
}