{
  "type": "Feature",
  "properties": {
    "addr:full":"113 N Memorial Hwy Shavertown PA 18708",
    "addr:housenumber":"113",
    "addr:postcode":"18708",
    "addr:street":"N Memorial Hwy",
    "iso:country":"US",
    "sg:address":"113 N Memorial Hwy",
    "sg:city":"Shavertown",
    "sg:classifiers":[
        {
            "category":"Health Services",
            "subcategory":"Hospital",
            "type":"Services"
        }
    ],
    "sg:phone":"+1 570 674 6525",
    "sg:postcode":"18708",
    "sg:province":"PA",
    "wof:name":"The Renaissance Center",
    "wof:placetype":"venue"
},
  "geometry": {"coordinates":[-75.933921,41.307137],"type":"Point"}
}