{
  "type": "Feature",
  "properties": {
    "iso:country":"US",
    "sg:address":"480 E College Ave",
    "sg:city":"State College",
    "sg:classifiers":[
        {
            "category":"Shopping",
            "subcategory":"Bicycles & Sporting Goods",
            "type":"Retail Goods"
        }
    ],
    "sg:phone":"+1   ",
    "sg:postcode":"16801",
    "sg:province":"PA",
    "sg:tags":[
        "equipment",
        "sport"
    ],
    "wof:name":"Eddies Bicycles",
    "wof:placetype":"venue"
},
  "geometry": {"coordinates":[-77.85557300000001,40.798758],"type":"Point"}
}