{
  "type": "Feature",
  "properties": {
    "iso:country":"US",
    "sg:address":"21 Wayne St",
    "sg:city":"Wilkes Barre",
    "sg:classifiers":[
        {
            "category":"Recreation",
            "type":"Entertainment"
        }
    ],
    "sg:phone":"+1 570 824 6451",
    "sg:postcode":"18702",
    "sg:province":"PA",
    "sg:tags":[
        "guide"
    ],
    "wof:name":"O'Donnell's Guide Svc",
    "wof:placetype":"venue"
},
  "geometry": {"coordinates":[-75.880546,41.237147],"type":"Point"}
}