{
  "type": "Feature",
  "properties": {
    "iso:country":"US",
    "sg:address":"4001 Cresson St",
    "sg:city":"Philadelphia",
    "sg:classifiers":[
        {
            "category":"Bars & Pubs",
            "type":"Food & Drink"
        }
    ],
    "sg:phone":"+1 215 482 4944",
    "sg:postcode":"19127",
    "sg:province":"PA",
    "wof:name":"East End Tavern",
    "wof:placetype":"venue"
},
  "geometry": {"coordinates":[-75.21647299999999,40.021893],"type":"Point"}
}