{
  "type": "Feature",
  "properties": {
    "addr:full":"5901 Mill Creek Rd Levittown PA 19057",
    "addr:housenumber":"5901",
    "addr:postcode":"19057",
    "addr:street":"Mill Creek Rd Levittown",
    "iso:country":"US",
    "sg:address":"5901 Mill Creek Rd",
    "sg:city":"Levittown",
    "sg:classifiers":[
        {
            "category":"Retail",
            "subcategory":"Auto Rental",
            "type":"Services"
        }
    ],
    "sg:phone":"+1 215 969 4707",
    "sg:postcode":"19057",
    "sg:province":"PA",
    "sg:tags":[
        "renting",
        "truck",
        "leasing"
    ],
    "wof:name":"U-Haul Co",
    "wof:placetype":"venue"
},
  "geometry": {"coordinates":[-74.857843,40.133569],"type":"Point"}
}