{
  "type": "Feature",
  "properties": {
    "iso:country":"US",
    "sg:address":"3185 Delta Rd",
    "sg:city":"Airville",
    "sg:classifiers":[
        {
            "category":"Recreation",
            "type":"Entertainment"
        }
    ],
    "sg:phone":"+1 717 862 1338",
    "sg:postcode":"17302",
    "sg:province":"PA",
    "sg:tags":[
        "stable"
    ],
    "wof:name":"As A Matter Of Tack Inc",
    "wof:placetype":"venue"
},
  "geometry": {"coordinates":[-76.430944,39.851092],"type":"Point"}
}