{
  "type": "Feature",
  "properties": {
    "iso:country":"US",
    "sg:address":"330 Revere Blvd",
    "sg:city":"Reading",
    "sg:classifiers":[
        {
            "category":"Professional",
            "subcategory":"Engineering",
            "type":"Services"
        }
    ],
    "sg:phone":"+1 610 777 8000",
    "sg:postcode":"19608",
    "sg:province":"PA",
    "sg:tags":[
        "engineer"
    ],
    "wof:name":"Stackhouse Seitz & Bensinger",
    "wof:placetype":"venue"
},
  "geometry": {"coordinates":[-75.990549,40.311761],"type":"Point"}
}