{
  "type": "Feature",
  "properties": {
    "iso:country":"US",
    "sg:address":"3943 Mikol Ln",
    "sg:city":"Easton",
    "sg:classifiers":[
        {
            "category":"Building & Trades",
            "subcategory":"Construction",
            "type":"Services"
        }
    ],
    "sg:phone":"+1 610 759 8416",
    "sg:postcode":"18045",
    "sg:province":"PA",
    "sg:tags":[
        "house",
        "general",
        "contractor"
    ],
    "wof:name":"Ed's Remodeling",
    "wof:placetype":"venue"
},
  "geometry": {"coordinates":[-75.30042899999999,40.719348],"type":"Point"}
}