{
  "type": "Feature",
  "properties": {
    "addr:full":"26186 US Hwy 19 Cambridge Springs PA 16403",
    "addr:postcode":"26186;16403",
    "addr:street":"Us Hwy 19",
    "iso:country":"US",
    "sg:address":"26186 US Hwy 19",
    "sg:city":"Cambridge Springs",
    "sg:phone":"+1   ",
    "sg:postcode":"16403",
    "sg:province":"PA",
    "sg:tags":[
        "farm",
        "crop"
    ],
    "wof:name":"Cambridge Drain Stoves",
    "wof:placetype":"venue"
},
  "geometry": {"coordinates":[-80.031105,41.839319],"type":"Point"}
}