{
  "type": "Feature",
  "properties": {
    "iso:country":"US",
    "sg:address":"1515 Market St",
    "sg:city":"Philadelphia",
    "sg:classifiers":[
        {
            "category":"Professional",
            "subcategory":"Lawyer & Legal Services",
            "type":"Services"
        }
    ],
    "sg:phone":"+1 215 510 6755",
    "sg:postcode":"19102",
    "sg:province":"PA",
    "sg:tags":[
        "personal",
        "injury"
    ],
    "sg:website":"www.injurylawyerphiladelphia.com",
    "wof:name":"The Lassen Law Firm",
    "wof:placetype":"venue"
},
  "geometry": {"coordinates":[-75.166155,39.952975],"type":"Point"}
}