{
  "type": "Feature",
  "properties": {
    "iso:country":"US",
    "sg:address":"632 W Beaver Ave",
    "sg:city":"State College",
    "sg:classifiers":[
        {
            "category":"Education",
            "subcategory":"School",
            "type":"Public Place"
        }
    ],
    "sg:phone":"+1 814 238 2655",
    "sg:postcode":"16801",
    "sg:province":"PA",
    "wof:name":"Children's House",
    "wof:placetype":"venue"
},
  "geometry": {"coordinates":[-77.867048,40.788345],"type":"Point"}
}