{
  "type": "Feature",
  "properties": {
    "iso:country":"US",
    "sg:address":"2352 S 7th St",
    "sg:city":"Philadelphia",
    "sg:classifiers":[
        {
            "category":"Personal",
            "subcategory":"Beauty Salon",
            "type":"Services"
        }
    ],
    "sg:phone":"+1 215 389 9641",
    "sg:postcode":"19148",
    "sg:province":"PA",
    "wof:name":"Sengthong's",
    "wof:placetype":"venue"
},
  "geometry": {"coordinates":[-75.159059,39.919252],"type":"Point"}
}