{
  "type": "Feature",
  "properties": {
    "iso:country":"US",
    "sg:address":"45 E Front St",
    "sg:city":"Hancock",
    "sg:classifiers":[
        {
            "category":"Shopping",
            "subcategory":"Discount & Variety Stores",
            "type":"Retail Goods"
        }
    ],
    "sg:phone":"+1 607 637 8783",
    "sg:postcode":"13783",
    "sg:province":"PA",
    "sg:tags":[
        "merchandise",
        "general"
    ],
    "wof:name":"General Store",
    "wof:placetype":"venue"
},
  "geometry": {"coordinates":[-75.27901799999999,41.954101],"type":"Point"}
}