{
  "type": "Feature",
  "properties": {
    "iso:country":"US",
    "sg:address":"1020 Beckford St",
    "sg:city":"New Castle",
    "sg:classifiers":[
        {
            "category":"Building & Trades",
            "subcategory":"Electrical",
            "type":"Services"
        }
    ],
    "sg:phone":"+1 724 657 9912",
    "sg:postcode":"16101",
    "sg:province":"PA",
    "sg:tags":[
        "electrical",
        "electric",
        "contractor"
    ],
    "wof:name":"Warren Electric Inc",
    "wof:placetype":"venue"
},
  "geometry": {"coordinates":[-80.32110400000001,40.989453],"type":"Point"}
}