{
  "type": "Feature",
  "properties": {
    "addr:full":"3809 Darby Rd Harrisburg PA 17109",
    "addr:housenumber":"3809",
    "addr:postcode":"17109",
    "addr:street":"Darby Rd",
    "iso:country":"US",
    "sg:address":"3809 Darby Rd",
    "sg:city":"Harrisburg",
    "sg:classifiers":[
        {
            "category":"Arts & Performance",
            "subcategory":"Theater",
            "type":"Entertainment"
        }
    ],
    "sg:phone":"+1 717 545 9767",
    "sg:postcode":"17109",
    "sg:province":"PA",
    "sg:tags":[
        "musician"
    ],
    "wof:name":"Captain & Patricia",
    "wof:placetype":"venue"
},
  "geometry": {"coordinates":[-76.82893199999999,40.280164],"type":"Point"}
}