{
  "type": "Feature",
  "properties": {
    "iso:country":"US",
    "sg:address":"1967 Streets Run Rd",
    "sg:city":"Pittsburgh",
    "sg:classifiers":[
        {
            "category":"Restaurant",
            "type":"Food & Drink"
        }
    ],
    "sg:phone":"+1   ",
    "sg:postcode":"15236",
    "sg:province":"PA",
    "sg:tags":[
        "drinking",
        "eating"
    ],
    "wof:name":"Office Lounge",
    "wof:placetype":"venue"
},
  "geometry": {"coordinates":[-79.94954199999999,40.365418],"type":"Point"}
}