{
  "type": "Feature",
  "properties": {
    "iso:country":"US",
    "sg:address":"199 England Creamery Rd",
    "sg:city":"North East",
    "sg:classifiers":[
        {
            "category":"Shopping",
            "subcategory":"Used Merchandise",
            "type":"Retail Goods"
        }
    ],
    "sg:phone":"+1 410 658 2881",
    "sg:postcode":"21901",
    "sg:province":"MD",
    "wof:name":"Creamery Corner Antiques",
    "wof:placetype":"venue"
},
  "geometry": {"coordinates":[-75.965104,39.675944],"type":"Point"}
}