{
  "type": "Feature",
  "properties": {
    "iso:country":"US",
    "sg:address":"312 Ryan Ln",
    "sg:city":"Stroudsburg",
    "sg:classifiers":[
        {
            "category":"Wholesale",
            "subcategory":"Drugs",
            "type":"Manufacturing & Wholesale Goods"
        }
    ],
    "sg:phone":"+1 570 619 8664",
    "sg:postcode":"18360",
    "sg:province":"PA",
    "sg:tags":[
        "cosmetic"
    ],
    "wof:name":"Shagbark Research Inc",
    "wof:placetype":"venue"
},
  "geometry": {"coordinates":[-75.28341,40.968903],"type":"Point"}
}