{
  "type": "Feature",
  "properties": {
    "addr:full":"4544 W Ridge Rd Erie PA 16506",
    "addr:housenumber":"4544",
    "addr:postcode":"16506",
    "addr:street":"W Ridge Rd",
    "iso:country":"US",
    "sg:address":"4544 W Ridge Rd",
    "sg:city":"Erie",
    "sg:classifiers":[
        {
            "category":"Health Services",
            "subcategory":"Health Practitioner",
            "type":"Services"
        }
    ],
    "sg:phone":"+1 814 833 3133",
    "sg:postcode":"16506",
    "sg:province":"PA",
    "sg:tags":[
        "psychologist"
    ],
    "wof:name":"Vivian A Tamburello PHD",
    "wof:placetype":"venue"
},
  "geometry": {"coordinates":[-80.179986,42.073357],"type":"Point"}
}