{
  "type": "Feature",
  "properties": {
    "addr:full":"200 Airport Rd Butler PA 16002",
    "addr:housenumber":"200",
    "addr:postcode":"16002",
    "addr:street":"Airport Rd",
    "iso:country":"US",
    "sg:address":"200 Airport Rd",
    "sg:city":"Butler",
    "sg:classifiers":[
        {
            "category":"Manufacturing",
            "subcategory":"Petroleum Products",
            "type":"Manufacturing & Wholesale Goods"
        }
    ],
    "sg:phone":"+1   ",
    "sg:postcode":"16002",
    "sg:province":"PA",
    "sg:tags":[
        "asphalt",
        "mfg"
    ],
    "wof:name":"United Refiney",
    "wof:placetype":"venue"
},
  "geometry": {"coordinates":[-79.93326999999999,40.780163],"type":"Point"}
}