{
  "type": "Feature",
  "properties": {
    "iso:country":"US",
    "sg:address":"400 S State Rd Ste 12",
    "sg:city":"Springfield",
    "sg:classifiers":[
        {
            "category":"Personal",
            "subcategory":"Nail Salon",
            "type":"Services"
        }
    ],
    "sg:phone":"+1 610 543 8117",
    "sg:postcode":"19064",
    "sg:province":"PA",
    "wof:name":"Evian Nails",
    "wof:placetype":"venue"
},
  "geometry": {"coordinates":[-75.354088,39.937401],"type":"Point"}
}