{
  "type": "Feature",
  "properties": {
    "iso:country":"US",
    "sg:address":"101 Bateman Rd",
    "sg:city":"Oakdale",
    "sg:classifiers":[
        {
            "category":"Wholesale",
            "subcategory":"Motor Vehicles",
            "type":"Manufacturing & Wholesale Goods"
        }
    ],
    "sg:phone":"+1 724 695 8783",
    "sg:postcode":"15071",
    "sg:province":"PA",
    "sg:tags":[
        "trailer"
    ],
    "wof:name":"Trailer America",
    "wof:placetype":"venue"
},
  "geometry": {"coordinates":[-80.23724300000001,40.438783],"type":"Point"}
}