{
  "type": "Feature",
  "properties": {
    "iso:country":"US",
    "sg:address":"1401 Third Ave",
    "sg:city":"Berwick",
    "sg:classifiers":[
        {
            "category":"Professional",
            "type":"Services"
        }
    ],
    "sg:phone":"+1   ",
    "sg:postcode":"18603",
    "sg:province":"PA",
    "wof:name":"RT&a Financial Management",
    "wof:placetype":"venue"
},
  "geometry": {"coordinates":[-76.257637,41.056813],"type":"Point"}
}