{
  "type": "Feature",
  "properties": {
    "addr:full":"5031 William Flynn Hwy Gibsonia PA 15044",
    "addr:housenumber":"5031",
    "addr:postcode":"15044",
    "addr:street":"William Flynn Hwy",
    "iso:country":"US",
    "sg:address":"5031 William Flynn Hwy",
    "sg:city":"Gibsonia",
    "sg:classifiers":[
        {
            "category":"Utilities",
            "subcategory":"Telephone",
            "type":"Services"
        }
    ],
    "sg:phone":"+1   ",
    "sg:postcode":"15044",
    "sg:province":"PA",
    "sg:tags":[
        "trivium",
        "line",
        "sport",
        "phone"
    ],
    "wof:name":"Pittsburgh Sports Trivia Inc",
    "wof:placetype":"venue"
},
  "geometry": {"coordinates":[-79.947174,40.602443],"type":"Point"}
}