{
  "type": "Feature",
  "properties": {
    "iso:country":"US",
    "sg:address":"804 S York Rd ",
    "sg:city":"Hatboro",
    "sg:classifiers":[
        {
            "category":"Restaurant",
            "type":"Food & Drink"
        }
    ],
    "sg:menulink":"http://www.allmenus.com/pa/upper-moreland/292058-pasta-fazool-/menu/",
    "sg:phone":"+1 267 282 5442",
    "sg:postcode":"19040",
    "sg:province":"PA",
    "sg:tags":[
        "italian"
    ],
    "wof:name":"Pasta Fazool ",
    "wof:placetype":"venue"
},
  "geometry": {"coordinates":[-75.111243,40.163299],"type":"Point"}
}