{
  "type": "Feature",
  "properties": {
    "iso:country":"US",
    "sg:address":"16 S 52nd St",
    "sg:city":"Philadelphia",
    "sg:classifiers":[
        {
            "category":"Shopping",
            "subcategory":"Bicycles & Sporting Goods",
            "type":"Retail Goods"
        }
    ],
    "sg:phone":"+1 215 747 2644",
    "sg:postcode":"19139",
    "sg:province":"PA",
    "wof:name":"Olympia Sports",
    "wof:placetype":"venue"
},
  "geometry": {"coordinates":[-75.225088,39.959393],"type":"Point"}
}