{
  "type": "Feature",
  "properties": {
    "iso:country":"US",
    "sg:address":"110 Debbie Ln",
    "sg:city":"Easton",
    "sg:classifiers":[
        {
            "category":"Structure",
            "subcategory":"Office Building",
            "type":"Public Place"
        }
    ],
    "sg:phone":"+1 610 253 1076",
    "sg:postcode":"18045",
    "sg:province":"PA",
    "sg:tags":[
        "park"
    ],
    "wof:name":"Jc8 Properties",
    "wof:placetype":"venue"
},
  "geometry": {"coordinates":[-75.26519999999999,40.718961],"type":"Point"}
}