{
  "type": "Feature",
  "properties": {
    "addr:full":"34 S Market St Elizabethville PA 17023",
    "addr:housenumber":"34",
    "addr:postcode":"17023",
    "addr:street":"S Market St",
    "iso:country":"US",
    "sg:address":"34 S Market St",
    "sg:city":"Elizabethville",
    "sg:classifiers":[
        {
            "category":"Shopping",
            "subcategory":"Gifts & Souvenirs",
            "type":"Retail Goods"
        }
    ],
    "sg:phone":"+1 717 362 4335",
    "sg:postcode":"17023",
    "sg:province":"PA",
    "sg:tags":[
        "shop"
    ],
    "wof:name":"Reasons & Seasons",
    "wof:placetype":"venue"
},
  "geometry": {"coordinates":[-76.811562,40.548464],"type":"Point"}
}