{
  "type": "Feature",
  "properties": {
    "iso:country":"US",
    "sg:address":"446 W Chestnut St",
    "sg:city":"Lancaster",
    "sg:classifiers":[
        {
            "category":"Health Services",
            "subcategory":"Doctor",
            "type":"Services"
        }
    ],
    "sg:phone":"+1   ",
    "sg:postcode":"17603",
    "sg:province":"PA",
    "sg:tags":[
        "medical"
    ],
    "wof:name":"Catholic Health Initiatives",
    "wof:placetype":"venue"
},
  "geometry": {"coordinates":[-76.315009,40.040159],"type":"Point"}
}