{
  "type": "Feature",
  "properties": {
    "addr:full":"5722 Frankford Ave Philadelphia PA 19135",
    "addr:housenumber":"5722",
    "addr:postcode":"19135",
    "addr:street":"Frankford Ave",
    "iso:country":"US",
    "sg:address":"5722 Frankford Ave",
    "sg:city":"Philadelphia",
    "sg:classifiers":[
        {
            "category":"Shopping",
            "subcategory":"Florist",
            "type":"Retail Goods"
        }
    ],
    "sg:phone":"+1 215 289 0939",
    "sg:postcode":"19135",
    "sg:province":"PA",
    "sg:tags":[
        "monument"
    ],
    "wof:name":"Scott Monument Co",
    "wof:placetype":"venue"
},
  "geometry": {"coordinates":[-75.072998,40.025299],"type":"Point"}
}