{
  "type": "Feature",
  "properties": {
    "addr:full":"1526 Country Club Ln Williamsport PA 17701",
    "addr:housenumber":"1526",
    "addr:postcode":"17701",
    "addr:street":"Country Club Ln",
    "iso:country":"US",
    "sg:address":"1526 Country Club Ln",
    "sg:city":"Williamsport",
    "sg:classifiers":[
        {
            "category":"Local Transit",
            "type":"Transportation"
        }
    ],
    "sg:phone":"+1 570 322 0689",
    "sg:postcode":"17701",
    "sg:province":"PA",
    "sg:tags":[
        "limousine"
    ],
    "wof:name":"Winner Funeral Livery",
    "wof:placetype":"venue"
},
  "geometry": {"coordinates":[-76.95554799999999,41.260366],"type":"Point"}
}