{
  "type": "Feature",
  "properties": {
    "addr:full":"5 Forbes Rd Trafford PA 15085",
    "addr:housenumber":"5",
    "addr:postcode":"15085",
    "addr:street":"Forbes Rd",
    "iso:country":"US",
    "sg:address":"5 Forbes Rd",
    "sg:city":"Trafford",
    "sg:classifiers":[
        {
            "category":"Deli",
            "type":"Food & Drink"
        },
        {
            "category":"Restaurant",
            "type":"Food & Drink"
        },
        {
            "category":"Food & Beverages",
            "subcategory":"Groceries & Convenience Stores",
            "type":"Retail Goods"
        }
    ],
    "sg:phone":"+1 412 856 6654",
    "sg:postcode":"15085",
    "sg:province":"PA",
    "sg:tags":[
        "delicatessen"
    ],
    "wof:name":"M & M Deli",
    "wof:placetype":"venue"
},
  "geometry": {"coordinates":[-79.749222,40.388859],"type":"Point"}
}