{
  "type": "Feature",
  "properties": {
    "iso:country":"US",
    "sg:address":"3073 Kensington Ave",
    "sg:city":"Philadelphia",
    "sg:classifiers":[
        {
            "category":"Shopping",
            "subcategory":"Used Merchandise",
            "type":"Retail Goods"
        }
    ],
    "sg:phone":"+1 215 426 8335",
    "sg:postcode":"19134",
    "sg:province":"PA",
    "sg:tags":[
        "clothing"
    ],
    "wof:name":"Jam Wally",
    "wof:placetype":"venue"
},
  "geometry": {"coordinates":[-75.116529,39.994536],"type":"Point"}
}