{
  "type": "Feature",
  "properties": {
    "addr:full":"3500 W Chester Pike Newtown Square PA 19073",
    "addr:housenumber":"3500",
    "addr:postcode":"19073",
    "addr:street":"W Chester Pike",
    "iso:country":"US",
    "sg:address":"3500 W Chester Pike",
    "sg:city":"Newtown Square",
    "sg:classifiers":[
        {
            "category":"Shopping",
            "type":"Retail Goods"
        }
    ],
    "sg:phone":"+1   ",
    "sg:postcode":"19073",
    "sg:province":"PA",
    "sg:tags":[
        "merchandise"
    ],
    "wof:name":"The Nice N Sweet Shop",
    "wof:placetype":"venue"
},
  "geometry": {"coordinates":[-75.393108,39.98512],"type":"Point"}
}