{
  "type": "Feature",
  "properties": {
    "iso:country":"US",
    "sg:address":"400 Mifflin St",
    "sg:city":"West Mifflin",
    "sg:classifiers":[
        {
            "category":"Restaurant",
            "type":"Food & Drink"
        }
    ],
    "sg:phone":"+1 412 461 7513",
    "sg:postcode":"15122",
    "sg:province":"PA",
    "sg:tags":[
        "eating"
    ],
    "wof:name":"Dairy Queen",
    "wof:placetype":"venue"
},
  "geometry": {"coordinates":[-79.85432299999999,40.361126],"type":"Point"}
}