{
  "type": "Feature",
  "properties": {
    "addr:full":"505 Cherry Rd Souderton PA 18964",
    "addr:housenumber":"505",
    "addr:postcode":"18964",
    "addr:street":"Cherry Rd",
    "iso:country":"US",
    "sg:address":"505 Cherry Rd",
    "sg:city":"Souderton",
    "sg:classifiers":[
        {
            "category":"Professional",
            "type":"Services"
        }
    ],
    "sg:phone":"+1   ",
    "sg:postcode":"18964",
    "sg:province":"PA",
    "wof:name":"Christian Sky LLC",
    "wof:placetype":"venue"
},
  "geometry": {"coordinates":[-75.30065500000001,40.31873],"type":"Point"}
}