{
  "type": "Feature",
  "properties": {
    "iso:country":"US",
    "sg:address":"1748 Jancey St",
    "sg:city":"Pittsburgh",
    "sg:classifiers":[
        {
            "category":"Real Estate",
            "subcategory":"Real Estate Agent",
            "type":"Services"
        }
    ],
    "sg:phone":"+1 412 362 3333",
    "sg:postcode":"15206",
    "sg:province":"PA",
    "wof:name":"Rockwell Realty",
    "wof:placetype":"venue"
},
  "geometry": {"coordinates":[-79.927026,40.485329],"type":"Point"}
}