{
  "type": "Feature",
  "properties": {
    "addr:full":"10 Fox Glove Ln Reading PA 19606",
    "addr:housenumber":"10",
    "addr:postcode":"19606",
    "addr:street":"Fox Glove Ln",
    "iso:country":"US",
    "sg:address":"10 Fox Glove Ln",
    "sg:city":"Reading",
    "sg:classifiers":[
        {
            "category":"Arts & Performance",
            "subcategory":"Theater",
            "type":"Entertainment"
        }
    ],
    "sg:phone":"+1 610 779 7141",
    "sg:postcode":"19606",
    "sg:province":"PA",
    "sg:tags":[
        "live",
        "music"
    ],
    "wof:name":"Denny Mc Connell's Music",
    "wof:placetype":"venue"
},
  "geometry": {"coordinates":[-75.83214599999999,40.326609],"type":"Point"}
}