{
  "type": "Feature",
  "properties": {
    "iso:country":"US",
    "sg:address":"29 Quakers Way",
    "sg:city":"Quakertown",
    "sg:classifiers":[
        {
            "category":"Restaurant",
            "type":"Food & Drink"
        }
    ],
    "sg:phone":"+1 215 536 2952",
    "sg:postcode":"18951",
    "sg:province":"PA",
    "sg:tags":[
        "fast"
    ],
    "wof:name":"Don's Dandy Dogs",
    "wof:placetype":"venue"
},
  "geometry": {"coordinates":[-75.34462499999999,40.42403],"type":"Point"}
}