{
  "type": "Feature",
  "properties": {
    "iso:country":"US",
    "sg:address":"1906 Bowmansville Rd",
    "sg:city":"Mohnton",
    "sg:classifiers":[
        {
            "category":"Travel",
            "subcategory":"Campground",
            "type":"Entertainment"
        }
    ],
    "sg:phone":"+1 717 484 4806",
    "sg:postcode":"17569",
    "sg:province":"PA",
    "wof:name":"Sill's Campgrounds",
    "wof:placetype":"venue"
},
  "geometry": {"coordinates":[-76.036828,40.237937],"type":"Point"}
}