{
  "type": "Feature",
  "properties": {
    "iso:country":"US",
    "sg:address":"483 Lower Holland Rd",
    "sg:city":"Holland",
    "sg:classifiers":[
        {
            "category":"Insurance",
            "subcategory":"Insurance Agent",
            "type":"Services"
        }
    ],
    "sg:phone":"+1 215 757 6400",
    "sg:postcode":"18966",
    "sg:province":"PA",
    "wof:name":"Ensinger Insurance",
    "wof:placetype":"venue"
},
  "geometry": {"coordinates":[-74.988832,40.19913],"type":"Point"}
}