{
  "type": "Feature",
  "properties": {
    "iso:country":"US",
    "sg:address":"399 Labelle Rd",
    "sg:city":"East Millsboro",
    "sg:classifiers":[
        {
            "category":"Building & Trades",
            "subcategory":"Cleaning & Sanitation",
            "type":"Services"
        }
    ],
    "sg:phone":"+1 724 785 8134",
    "sg:postcode":"15433",
    "sg:province":"PA",
    "sg:tags":[
        "supply"
    ],
    "wof:name":"Fayette Thermal LLC",
    "wof:placetype":"venue"
},
  "geometry": {"coordinates":[-79.98615100000001,40.008452],"type":"Point"}
}