{
  "type": "Feature",
  "properties": {
    "iso:country":"US",
    "sg:address":"31 S Main St",
    "sg:city":"Tioga",
    "sg:classifiers":[
        {
            "category":"Restaurant",
            "type":"Food & Drink"
        }
    ],
    "sg:phone":"+1 570 835 5700",
    "sg:postcode":"16946",
    "sg:province":"PA",
    "wof:name":"Acorn Market",
    "wof:placetype":"venue"
},
  "geometry": {"coordinates":[-77.13330000000001,41.912972],"type":"Point"}
}