{
  "type": "Feature",
  "properties": {
    "iso:country":"US",
    "sg:address":"9 Steinwehr Ave",
    "sg:city":"Gettysburg",
    "sg:classifiers":[
        {
            "category":"Recreation",
            "type":"Entertainment"
        }
    ],
    "sg:phone":"+1   ",
    "sg:postcode":"17325",
    "sg:province":"PA",
    "wof:name":"Gallon Historical Art Inc",
    "wof:placetype":"venue"
},
  "geometry": {"coordinates":[-77.23118700000001,39.824157],"type":"Point"}
}