{
  "type": "Feature",
  "properties": {
    "iso:country":"US",
    "sg:address":"625 Lentz Trl",
    "sg:city":"Jim Thorpe",
    "sg:classifiers":[
        {
            "category":"Travel",
            "subcategory":"Campground",
            "type":"Entertainment"
        }
    ],
    "sg:phone":"+1 570 325 3669",
    "sg:postcode":"18229",
    "sg:province":"PA",
    "sg:tags":[
        "executive",
        "trailer"
    ],
    "sg:website":"www.mauchchunklakepark.com",
    "wof:name":"Mauch Chunk Lake Park",
    "wof:placetype":"venue"
},
  "geometry": {"coordinates":[-75.801996,40.846028],"type":"Point"}
}