{
  "type": "Feature",
  "properties": {
    "addr:full":"951 Main St Honesdale PA 18431",
    "addr:housenumber":"951",
    "addr:postcode":"18431",
    "addr:street":"Main St",
    "iso:country":"US",
    "sg:address":"951 Main St",
    "sg:city":"Honesdale",
    "sg:classifiers":[
        {
            "category":"Restaurant",
            "type":"Food & Drink"
        }
    ],
    "sg:phone":"+1 570 253 3231",
    "sg:postcode":"18431",
    "sg:province":"PA",
    "wof:name":"Jensz Cafe",
    "wof:placetype":"venue"
},
  "geometry": {"coordinates":[-75.256575,41.574021],"type":"Point"}
}