{
  "type": "Feature",
  "properties": {
    "addr:full":"221 Pine Grove Rd Gardners PA 17324",
    "addr:housenumber":"221",
    "addr:postcode":"17324",
    "addr:street":"Pine Grove Rd",
    "iso:country":"US",
    "sg:address":"221 Pine Grove Rd",
    "sg:city":"Gardners",
    "sg:classifiers":[
        {
            "category":"Home & Garden",
            "subcategory":"Carpets & Floor Coverings",
            "type":"Retail Goods"
        }
    ],
    "sg:phone":"+1 717 486 8041",
    "sg:postcode":"17324",
    "sg:province":"PA",
    "wof:name":"Randy S Shull Floor Coverings",
    "wof:placetype":"venue"
},
  "geometry": {"coordinates":[-77.211099,40.069848],"type":"Point"}
}