{
  "type": "Feature",
  "properties": {
    "addr:full":"1321 Arch St Philadelphia PA 19107",
    "addr:housenumber":"1321",
    "addr:postcode":"19107",
    "addr:street":"Arch St",
    "iso:country":"US",
    "sg:address":"1321 Arch St",
    "sg:city":"Philadelphia",
    "sg:classifiers":[
        {
            "category":"Government",
            "subcategory":"Police Station",
            "type":"Public Place"
        }
    ],
    "sg:phone":"+1 215 686 3535",
    "sg:postcode":"19107",
    "sg:province":"PA",
    "sg:tags":[
        "sheriff"
    ],
    "wof:name":"Sheriff's Dept-Real Estate Div",
    "wof:placetype":"venue"
},
  "geometry": {"coordinates":[-75.161306,39.954225],"type":"Point"}
}