{
  "type": "Feature",
  "properties": {
    "iso:country":"US",
    "sg:address":"704 Aster Pl",
    "sg:city":"Tobyhanna",
    "sg:classifiers":[
        {
            "category":"Retail",
            "subcategory":"Repair Shop",
            "type":"Services"
        }
    ],
    "sg:phone":"+1   ",
    "sg:postcode":"18466",
    "sg:province":"PA",
    "wof:name":"American Safe Lock Co Inc",
    "wof:placetype":"venue"
},
  "geometry": {"coordinates":[-75.364457,41.170683],"type":"Point"}
}