{
  "type": "Feature",
  "properties": {
    "iso:country":"US",
    "sg:address":"402 W Germantown Pike",
    "sg:city":"Plymouth Meeting",
    "sg:classifiers":[
        {
            "category":"Freight",
            "type":"Transportation"
        }
    ],
    "sg:phone":"+1   ",
    "sg:postcode":"19462",
    "sg:province":"PA",
    "sg:tags":[
        "turnpike",
        "building"
    ],
    "wof:name":"Plymouth Meeting Maint Bldg",
    "wof:placetype":"venue"
},
  "geometry": {"coordinates":[-75.285087,40.112857],"type":"Point"}
}