{
  "type": "Feature",
  "properties": {
    "iso:country":"US",
    "sg:address":"1688 Diehl Rd",
    "sg:city":"Bedford",
    "sg:classifiers":[
        {
            "category":"Building & Trades",
            "subcategory":"Construction",
            "type":"Services"
        }
    ],
    "sg:phone":"+1 814 847 2390",
    "sg:postcode":"15522",
    "sg:province":"PA",
    "sg:tags":[
        "contractor"
    ],
    "wof:name":"Kevin Cornells Contracting",
    "wof:placetype":"venue"
},
  "geometry": {"coordinates":[-78.47704400000001,39.943356],"type":"Point"}
}