{
  "type": "Feature",
  "properties": {
    "addr:full":"1103 Claremont Rd Carlisle PA 17015",
    "addr:housenumber":"1103",
    "addr:postcode":"17015",
    "addr:street":"Claremont Rd",
    "iso:country":"US",
    "sg:address":"1103 Claremont Rd",
    "sg:city":"Carlisle",
    "sg:classifiers":[
        {
            "category":"Wholesale",
            "subcategory":"Machinery & Supplies",
            "type":"Manufacturing & Wholesale Goods"
        }
    ],
    "sg:phone":"+1   ",
    "sg:postcode":"17015",
    "sg:province":"PA",
    "sg:tags":[
        "product",
        "industrial",
        "petroleum"
    ],
    "wof:name":"Applied Industrial Tech",
    "wof:placetype":"venue"
},
  "geometry": {"coordinates":[-77.15992300000001,40.214666],"type":"Point"}
}