{
  "type": "Feature",
  "properties": {
    "addr:full":"2400 Corporate Dr Wexford PA 15090",
    "addr:housenumber":"2400",
    "addr:postcode":"15090",
    "addr:street":"Corporate Dr",
    "iso:country":"US",
    "sg:address":"2400 Corporate Dr",
    "sg:city":"Wexford",
    "sg:classifiers":[
        {
            "category":"Health Services",
            "subcategory":"Doctor",
            "type":"Services"
        }
    ],
    "sg:phone":"+1 724 935 4700",
    "sg:postcode":"15090",
    "sg:province":"PA",
    "wof:name":"O'rourke Bridget A MD",
    "wof:placetype":"venue"
},
  "geometry": {"coordinates":[-80.088194,40.610039],"type":"Point"}
}