{
  "type": "Feature",
  "properties": {
    "iso:country":"US",
    "sg:address":"Reading Terminal Market 12th and Arch",
    "sg:city":"Philadelphia",
    "sg:classifiers":[
        {
            "category":"Bakery",
            "type":"Food & Drink"
        }
    ],
    "sg:phone":"+1 215 829 9020",
    "sg:postcode":"19107",
    "sg:province":"PA",
    "sg:website":"www.metropolitanbakery.com",
    "wof:name":"Metropolitan Bakery",
    "wof:placetype":"venue"
},
  "geometry": {"coordinates":[-75.15946599999999,39.953949],"type":"Point"}
}