{
  "type": "Feature",
  "properties": {
    "iso:country":"US",
    "sg:address":"201 King Manor Dr",
    "sg:city":"King Of Prussia",
    "sg:classifiers":[
        {
            "category":"Manufacturing",
            "subcategory":"Tools & Machinery",
            "type":"Manufacturing & Wholesale Goods"
        }
    ],
    "sg:phone":"+1   ",
    "sg:postcode":"19406",
    "sg:province":"PA",
    "sg:tags":[
        "repair",
        "mfg",
        "tester"
    ],
    "wof:name":"King Tester Corporation",
    "wof:placetype":"venue"
},
  "geometry": {"coordinates":[-75.34830599999999,40.091789],"type":"Point"}
}