{
  "type": "Feature",
  "properties": {
    "iso:country":"US",
    "sg:address":"26 N Main St",
    "sg:city":"Ashley",
    "sg:classifiers":[
        {
            "category":"Education",
            "subcategory":"Special Training",
            "type":"Public Place"
        },
        {
            "category":"Social Services",
            "subcategory":"Child Care",
            "type":"Services"
        }
    ],
    "sg:phone":"+1 570 824 3227",
    "sg:postcode":"18706",
    "sg:province":"PA",
    "sg:tags":[
        "educational",
        "nursery",
        "day"
    ],
    "wof:name":"Miss Ellies Education Center Inc",
    "wof:placetype":"venue"
},
  "geometry": {"coordinates":[-75.89898700000001,41.214699],"type":"Point"}
}