{
  "type": "Feature",
  "properties": {
    "iso:country":"US",
    "sg:address":"1745 Whiteford Rd",
    "sg:city":"York",
    "sg:classifiers":[
        {
            "category":"Autos & Motor Vehicles",
            "subcategory":"Automobile Sales",
            "type":"Retail Goods"
        }
    ],
    "sg:phone":"+1 717 755 7676",
    "sg:postcode":"17402",
    "sg:province":"PA",
    "sg:tags":[
        "car",
        "dealer"
    ],
    "wof:name":"Lehman Volvo",
    "wof:placetype":"venue"
},
  "geometry": {"coordinates":[-76.69471,39.982821],"type":"Point"}
}