{
  "type": "Feature",
  "properties": {
    "iso:country":"US",
    "sg:address":"137 W High St",
    "sg:city":"Bellefonte",
    "sg:classifiers":[
        {
            "category":"Shopping",
            "subcategory":"Gifts & Souvenirs",
            "type":"Retail Goods"
        }
    ],
    "sg:phone":"+1 814 353 8599",
    "sg:postcode":"16823",
    "sg:province":"PA",
    "sg:tags":[
        "shop",
        "curtain",
        "drapery"
    ],
    "wof:name":"Ruffles & Treasures",
    "wof:placetype":"venue"
},
  "geometry": {"coordinates":[-77.778718,40.911884],"type":"Point"}
}