{
  "type": "Feature",
  "properties": {
    "iso:country":"US",
    "sg:address":"691 Yorktown Rd",
    "sg:city":"Lewisberry",
    "sg:classifiers":[
        {
            "category":"Restaurant",
            "type":"Food & Drink"
        }
    ],
    "sg:phone":"+1 717 938 4188",
    "sg:postcode":"17339",
    "sg:province":"PA",
    "wof:name":"Alpine Inn",
    "wof:placetype":"venue"
},
  "geometry": {"coordinates":[-76.829804,40.16531],"type":"Point"}
}