{
  "type": "Feature",
  "properties": {
    "addr:full":"4 Mylin Ave Willow Street PA 17584",
    "addr:housenumber":"4",
    "addr:postcode":"17584",
    "addr:street":"Mylin Ave Willow Street",
    "iso:country":"US",
    "sg:address":"4 Mylin Ave",
    "sg:city":"Willow Street",
    "sg:classifiers":[
        {
            "category":"Retail",
            "subcategory":"Portrait Studio",
            "type":"Services"
        }
    ],
    "sg:phone":"+1 717 464 4240",
    "sg:postcode":"17584",
    "sg:province":"PA",
    "sg:tags":[
        "photo"
    ],
    "sg:website":"www.millerpix.com",
    "wof:name":"Miller Photography",
    "wof:placetype":"venue"
},
  "geometry": {"coordinates":[-76.278629,39.978838],"type":"Point"}
}