{
  "type": "Feature",
  "properties": {
    "addr:full":"601 Filbert St Pittsburgh PA 15232",
    "addr:housenumber":"601",
    "addr:postcode":"15232",
    "addr:street":"Filbert St",
    "iso:country":"US",
    "sg:address":"601 Filbert St",
    "sg:city":"Pittsburgh",
    "sg:classifiers":[
        {
            "category":"Education",
            "subcategory":"School",
            "type":"Public Place"
        }
    ],
    "sg:phone":"+1 412 622 8450",
    "sg:postcode":"15232",
    "sg:province":"PA",
    "sg:website":"www.pghboe.net",
    "wof:name":"Liberty Elementary School",
    "wof:placetype":"venue"
},
  "geometry": {"coordinates":[-79.93403000000001,40.453362],"type":"Point"}
}