{
  "type": "Feature",
  "properties": {
    "iso:country":"US",
    "sg:address":"2 S Claude A Lord Blvd",
    "sg:city":"Pottsville",
    "sg:classifiers":[
        {
            "category":"Food & Beverages",
            "subcategory":"Groceries & Convenience Stores",
            "type":"Retail Goods"
        }
    ],
    "sg:phone":"+1 570 628 0470",
    "sg:postcode":"17901",
    "sg:province":"PA",
    "wof:name":"Sunoco Aplus",
    "wof:placetype":"venue"
},
  "geometry": {"coordinates":[-76.1935,40.685926],"type":"Point"}
}