{
  "type": "Feature",
  "properties": {
    "addr:full":"1521 Hulseman St Philadelphia PA 19145",
    "addr:housenumber":"1521",
    "addr:postcode":"19145",
    "addr:street":"Hulseman St",
    "iso:country":"US",
    "sg:address":"1521 Hulseman St",
    "sg:city":"Philadelphia",
    "sg:classifiers":[
        {
            "category":"Professional",
            "subcategory":"Computer Services",
            "type":"Services"
        }
    ],
    "sg:phone":"+1 215 805 3289",
    "sg:postcode":"19145",
    "sg:province":"PA",
    "sg:tags":[
        "publisher",
        "software",
        "developer"
    ],
    "wof:name":"Smartwise Solutions",
    "wof:placetype":"venue"
},
  "geometry": {"coordinates":[-75.175371,39.909259],"type":"Point"}
}