{
  "type": "Feature",
  "properties": {
    "iso:country":"US",
    "sg:address":"3940 G St",
    "sg:city":"Philadelphia",
    "sg:classifiers":[
        {
            "category":"Building & Trades",
            "subcategory":"Locksmith",
            "type":"Services"
        }
    ],
    "sg:phone":"+1 267 207 2830",
    "sg:postcode":"19124",
    "sg:province":"PA",
    "sg:tags":[
        "key"
    ],
    "wof:name":"Emergency Locksmith Philadelphia",
    "wof:placetype":"venue"
},
  "geometry": {"coordinates":[-75.113124,40.008437],"type":"Point"}
}