{
  "type": "Feature",
  "properties": {
    "iso:country":"US",
    "sg:address":"4000 New Rodgers Rd",
    "sg:city":"Levittown",
    "sg:classifiers":[
        {
            "category":"Home & Garden",
            "subcategory":"Garden Supply",
            "type":"Retail Goods"
        }
    ],
    "sg:phone":"+1 215 949 8882",
    "sg:postcode":"19056",
    "sg:province":"PA",
    "sg:tags":[
        "center"
    ],
    "wof:name":"Mr Green Jeans' Garden Ctr Inc",
    "wof:placetype":"venue"
},
  "geometry": {"coordinates":[-74.88296200000001,40.129891],"type":"Point"}
}