{
  "type": "Feature",
  "properties": {
    "iso:country":"US",
    "sg:address":"1623 Dutch Ln",
    "sg:city":"Hermitage",
    "sg:classifiers":[
        {
            "category":"Health Services",
            "subcategory":"Health Practitioner",
            "type":"Services"
        }
    ],
    "sg:phone":"+1   ",
    "sg:postcode":"16148",
    "sg:province":"PA",
    "wof:name":"David E Wood",
    "wof:placetype":"venue"
},
  "geometry": {"coordinates":[-80.454654,41.254384],"type":"Point"}
}