{
  "type": "Feature",
  "properties": {
    "iso:country":"US",
    "sg:address":"2200 Georgetown Dr # 402",
    "sg:city":"Sewickley",
    "sg:classifiers":[
        {
            "category":"Banks & Credit Unions",
            "subcategory":"Investment Brokerage",
            "type":"Services"
        },
        {
            "category":"Banks & Credit Unions",
            "subcategory":"Financial Services",
            "type":"Services"
        }
    ],
    "sg:phone":"+1 724 933 0888",
    "sg:postcode":"15143",
    "sg:province":"PA",
    "sg:tags":[
        "advisory",
        "security",
        "planner"
    ],
    "sg:website":"http://www.raymondjames.com",
    "wof:name":"Raymond James",
    "wof:placetype":"venue"
},
  "geometry": {"coordinates":[-80.102305,40.604031],"type":"Point"}
}