{
  "type": "Feature",
  "properties": {
    "iso:country":"US",
    "sg:address":"3504 Main Street",
    "sg:city":"Morgantown",
    "sg:classifiers":[
        {
            "category":"Personal",
            "subcategory":"Beauty Salon",
            "type":"Services"
        },
        {
            "category":"Local Transit",
            "type":"Transportation"
        }
    ],
    "sg:phone":"+1 610 913 4000",
    "sg:postcode":"19543",
    "sg:province":"PA",
    "sg:tags":[
        "tanner"
    ],
    "wof:name":"Twisted Scissors Salon LLLC",
    "wof:placetype":"venue"
},
  "geometry": {"coordinates":[-75.883652,40.156753],"type":"Point"}
}