{
  "type": "Feature",
  "properties": {
    "addr:full":"358 Cranberry Rd Hazleton PA 18202",
    "addr:housenumber":"358",
    "addr:postcode":"18202",
    "addr:street":"Cranberry Rd",
    "iso:country":"US",
    "sg:address":"358 Cranberry Rd",
    "sg:city":"Hazleton",
    "sg:classifiers":[
        {
            "category":"Home & Garden",
            "subcategory":"Garden Supply",
            "type":"Retail Goods"
        }
    ],
    "sg:phone":"+1 570 455 8339",
    "sg:postcode":"18202",
    "sg:province":"PA",
    "sg:tags":[
        "landscaping",
        "equipment"
    ],
    "wof:name":"Cranberry Inc",
    "wof:placetype":"venue"
},
  "geometry": {"coordinates":[-75.994908,40.956348],"type":"Point"}
}