{
  "type": "Feature",
  "properties": {
    "addr:full":"867 Berkshire Blvd Reading PA 19610",
    "addr:housenumber":"867",
    "addr:postcode":"19610",
    "addr:street":"Berkshire Blvd",
    "iso:country":"US",
    "sg:address":"867 Berkshire Blvd",
    "sg:city":"Reading",
    "sg:classifiers":[
        {
            "category":"Home & Garden",
            "subcategory":"Furniture",
            "type":"Retail Goods"
        }
    ],
    "sg:phone":"+1   ",
    "sg:postcode":"19610",
    "sg:province":"PA",
    "wof:name":"Lebanon Valley Centr For Sleep",
    "wof:placetype":"venue"
},
  "geometry": {"coordinates":[-75.97009799999999,40.348715],"type":"Point"}
}