{
  "type": "Feature",
  "properties": {
    "iso:country":"US",
    "sg:address":"975 Paoli Pike ",
    "sg:city":"West Chester",
    "sg:classifiers":[
        {
            "category":"Restaurant",
            "type":"Food & Drink"
        }
    ],
    "sg:menulink":"http://www.allmenus.com/pa/west-goshen/289580-magnolia-grill/menu/",
    "sg:phone":"+1 610 696 1661",
    "sg:postcode":"19380",
    "sg:province":"PA",
    "sg:tags":[
        "american"
    ],
    "wof:name":"Magnolia Grill",
    "wof:placetype":"venue"
},
  "geometry": {"coordinates":[-75.585245,39.969889],"type":"Point"}
}