{
  "type": "Feature",
  "properties": {
    "iso:country":"US",
    "sg:address":"217 Fairview Dr",
    "sg:city":"Irwin",
    "sg:classifiers":[
        {
            "category":"Shopping",
            "subcategory":"Books",
            "type":"Retail Goods"
        }
    ],
    "sg:phone":"+1   ",
    "sg:postcode":"15642",
    "sg:province":"PA",
    "wof:name":"JD Tech Services",
    "wof:placetype":"venue"
},
  "geometry": {"coordinates":[-79.672656,40.343525],"type":"Point"}
}