{
  "type": "Feature",
  "properties": {
    "iso:country":"US",
    "sg:address":"1128 Little Cherry St",
    "sg:city":"Reading",
    "sg:classifiers":[
        {
            "category":"Building & Trades",
            "subcategory":"Plumbing",
            "type":"Services"
        }
    ],
    "sg:phone":"+1 610 375 8808",
    "sg:postcode":"19602",
    "sg:province":"PA",
    "sg:tags":[
        "plumbing",
        "contractor"
    ],
    "wof:name":"Captain Clog",
    "wof:placetype":"venue"
},
  "geometry": {"coordinates":[-75.91566899999999,40.334065],"type":"Point"}
}