{
  "type": "Feature",
  "properties": {
    "iso:country":"US",
    "sg:address":"45 Seneca St",
    "sg:city":"Oil City",
    "sg:classifiers":[
        {
            "category":"Professional",
            "subcategory":"Lawyer & Legal Services",
            "type":"Services"
        }
    ],
    "sg:phone":"+1 814 677 9260",
    "sg:postcode":"16301",
    "sg:province":"PA",
    "sg:tags":[
        "attorney"
    ],
    "wof:name":"Jeannine B Guth",
    "wof:placetype":"venue"
},
  "geometry": {"coordinates":[-79.70823300000001,41.433261],"type":"Point"}
}