{
  "type": "Feature",
  "properties": {
    "iso:country":"US",
    "sg:address":"700 Grant St",
    "sg:city":"Pittsburgh",
    "sg:classifiers":[
        {
            "category":"Professional",
            "subcategory":"Lawyer & Legal Services",
            "type":"Services"
        }
    ],
    "sg:phone":"+1 724 847 3001",
    "sg:postcode":"15219",
    "sg:province":"PA",
    "wof:name":"John Gismondi & Assoc",
    "wof:placetype":"venue"
},
  "geometry": {"coordinates":[-79.99490400000001,40.4422],"type":"Point"}
}