{
  "type": "Feature",
  "properties": {
    "iso:country":"US",
    "sg:address":"705 Old Harrisburg Rd",
    "sg:city":"Gettysburg",
    "sg:classifiers":[
        {
            "category":"Personal",
            "type":"Services"
        }
    ],
    "sg:phone":"+1   ",
    "sg:postcode":"17325",
    "sg:province":"PA",
    "wof:name":"Sunsations",
    "wof:placetype":"venue"
},
  "geometry": {"coordinates":[-77.225013,39.841142],"type":"Point"}
}