{
  "type": "Feature",
  "properties": {
    "iso:country":"US",
    "sg:address":"680 Main St",
    "sg:city":"Rimersburg",
    "sg:classifiers":[
        {
            "category":"Restaurant",
            "type":"Food & Drink"
        }
    ],
    "sg:phone":"+1   ",
    "sg:postcode":"16248",
    "sg:province":"PA",
    "sg:tags":[
        "eating"
    ],
    "wof:name":"Night Spot",
    "wof:placetype":"venue"
},
  "geometry": {"coordinates":[-79.50177499999999,41.043267],"type":"Point"}
}