{
  "type": "Feature",
  "properties": {
    "iso:country":"US",
    "sg:address":"83 PA Tpke",
    "sg:city":"New Cumberland",
    "sg:classifiers":[
        {
            "category":"Bars & Pubs",
            "subcategory":"Nightclub",
            "type":"Food & Drink"
        }
    ],
    "sg:phone":"+1 717 774 2525",
    "sg:postcode":"17070",
    "sg:province":"PA",
    "sg:tags":[
        "nightlife"
    ],
    "wof:name":"Pressbox Sports Lounge Interstate",
    "wof:placetype":"venue"
},
  "geometry": {"coordinates":[-76.87539700000001,40.221199],"type":"Point"}
}