{
  "type": "Feature",
  "properties": {
    "addr:full":"1334 Vernon St Harrisburg PA 17104",
    "addr:housenumber":"1334",
    "addr:postcode":"17104",
    "addr:street":"Vernon St",
    "iso:country":"US",
    "sg:address":"1334 Vernon St",
    "sg:city":"Harrisburg",
    "sg:classifiers":[
        {
            "category":"Building & Trades",
            "subcategory":"Electrical",
            "type":"Services"
        }
    ],
    "sg:phone":"+1 717 540 9080",
    "sg:postcode":"17104",
    "sg:province":"PA",
    "sg:tags":[
        "electric",
        "contractor"
    ],
    "wof:name":"Russel Blust Electrical Svc",
    "wof:placetype":"venue"
},
  "geometry": {"coordinates":[-76.86699299999999,40.264164],"type":"Point"}
}