{
  "type": "Feature",
  "properties": {
    "addr:full":"206 S 3rd St Philadelphia PA 19106",
    "addr:housenumber":"206",
    "addr:postcode":"19106",
    "addr:street":"S 3Rd St",
    "iso:country":"US",
    "sg:address":"206 S 3rd St",
    "sg:city":"Philadelphia",
    "sg:classifiers":[
        {
            "category":"Retail",
            "subcategory":"Laundry & Dry Cleaning",
            "type":"Services"
        }
    ],
    "sg:phone":"+1 215 923 1177",
    "sg:postcode":"19106",
    "sg:province":"PA",
    "sg:tags":[
        "commercial"
    ],
    "wof:name":"Ye Old Clean'ry At Society Hill",
    "wof:placetype":"venue"
},
  "geometry": {"coordinates":[-75.146552,39.947],"type":"Point"}
}