{
  "type": "Feature",
  "properties": {
    "iso:country":"US",
    "sg:address":"8848 Lee Rd",
    "sg:city":"Wattsburg",
    "sg:classifiers":[
        {
            "category":"Home & Garden",
            "subcategory":"Building Materials",
            "type":"Retail Goods"
        }
    ],
    "sg:phone":"+1   ",
    "sg:postcode":"16442",
    "sg:province":"PA",
    "wof:name":"Timber Wolf Lumber",
    "wof:placetype":"venue"
},
  "geometry": {"coordinates":[-79.837062,42.005948],"type":"Point"}
}