{
  "type": "Feature",
  "properties": {
    "iso:country":"US",
    "sg:address":"2910 Duss Ave",
    "sg:city":"Ambridge",
    "sg:classifiers":[
        {
            "category":"Restaurant",
            "type":"Food & Drink"
        },
        {
            "category":"Food & Beverages",
            "subcategory":"Bakery",
            "type":"Retail Goods"
        },
        {
            "category":"Bakery",
            "type":"Food & Drink"
        }
    ],
    "sg:phone":"+1 724 266 9758",
    "sg:postcode":"15003",
    "sg:province":"PA",
    "sg:tags":[
        "bakers-wholesale"
    ],
    "wof:name":"Ambridge Shop N Save",
    "wof:placetype":"venue"
},
  "geometry": {"coordinates":[-80.226325,40.611726],"type":"Point"}
}