{
  "type": "Feature",
  "properties": {
    "iso:country":"US",
    "sg:address":"44953 Buells Corners Rd",
    "sg:city":"Spartansburg",
    "sg:classifiers":[
        {
            "category":"Home & Garden",
            "subcategory":"Building Materials",
            "type":"Retail Goods"
        }
    ],
    "sg:phone":"+1 814 654 2032",
    "sg:postcode":"16434",
    "sg:province":"PA",
    "sg:tags":[
        "lumber"
    ],
    "wof:name":"Brush Run Lumber",
    "wof:placetype":"venue"
},
  "geometry": {"coordinates":[-79.649585,41.755465],"type":"Point"}
}