{
  "type": "Feature",
  "properties": {
    "iso:country":"US",
    "sg:address":"5621 Germantown Ave",
    "sg:city":"Philadelphia",
    "sg:classifiers":[
        {
            "category":"Shopping",
            "subcategory":"Computers & Home Electronics",
            "type":"Retail Goods"
        }
    ],
    "sg:phone":"+1   ",
    "sg:postcode":"19144",
    "sg:province":"PA",
    "sg:tags":[
        "equipment",
        "stereo",
        "record"
    ],
    "wof:name":"Sound of Germantown Inc",
    "wof:placetype":"venue"
},
  "geometry": {"coordinates":[-75.17457899999999,40.035776],"type":"Point"}
}