{
  "type": "Feature",
  "properties": {
    "iso:country":"US",
    "sg:address":"13637 Philmont Ave",
    "sg:city":"Philadelphia",
    "sg:classifiers":[
        {
            "category":"Retail",
            "subcategory":"Laundry & Dry Cleaning",
            "type":"Services"
        }
    ],
    "sg:phone":"+1 215 673 9295",
    "sg:postcode":"19116",
    "sg:province":"PA",
    "sg:tags":[
        "drycleaning",
        "plant"
    ],
    "wof:name":"Parklane Custom Cleaners",
    "wof:placetype":"venue"
},
  "geometry": {"coordinates":[-75.01033700000001,40.131989],"type":"Point"}
}