{
  "type": "Feature",
  "properties": {
    "addr:full":"511 Maple Ave Middleburg PA 17842",
    "addr:housenumber":"511",
    "addr:postcode":"17842",
    "addr:street":"Maple Ave",
    "iso:country":"US",
    "sg:address":"511 Maple Ave",
    "sg:city":"Middleburg",
    "sg:classifiers":[
        {
            "category":"Real Estate",
            "subcategory":"Surveying",
            "type":"Services"
        }
    ],
    "sg:phone":"+1 570 837 3109",
    "sg:postcode":"17842",
    "sg:province":"PA",
    "sg:tags":[
        "engineer"
    ],
    "wof:name":"James F Grose",
    "wof:placetype":"venue"
},
  "geometry": {"coordinates":[-77.03886199999999,40.789194],"type":"Point"}
}