{
  "type": "Feature",
  "properties": {
    "addr:full":"225 E 7th Ave Homestead PA 15120",
    "addr:housenumber":"225",
    "addr:postcode":"15120",
    "addr:street":"E 7Th Ave",
    "iso:country":"US",
    "sg:address":"225 E 7th Ave",
    "sg:city":"Homestead",
    "sg:classifiers":[
        {
            "category":"Professional",
            "subcategory":"Business Services",
            "type":"Services"
        }
    ],
    "sg:phone":"+1   ",
    "sg:postcode":"15120",
    "sg:province":"PA",
    "sg:tags":[
        "contractor"
    ],
    "wof:name":"Lnl Services Inc",
    "wof:placetype":"venue"
},
  "geometry": {"coordinates":[-79.91006400000001,40.40813],"type":"Point"}
}