{
  "type": "Feature",
  "properties": {
    "addr:full":"430 Husson Rd Felton PA 17322",
    "addr:housenumber":"430",
    "addr:postcode":"17322",
    "addr:street":"Husson Rd",
    "iso:country":"US",
    "sg:address":"430 Husson Rd",
    "sg:city":"Felton",
    "sg:classifiers":[
        {
            "category":"Retail",
            "subcategory":"Repair Shop",
            "type":"Services"
        }
    ],
    "sg:phone":"+1 717 244 7465",
    "sg:postcode":"17322",
    "sg:province":"PA",
    "sg:tags":[
        "clocks",
        "parts"
    ],
    "wof:name":"Time & Sound",
    "wof:placetype":"venue"
},
  "geometry": {"coordinates":[-76.58766799999999,39.865827],"type":"Point"}
}