{
  "type": "Feature",
  "properties": {
    "iso:country":"US",
    "sg:address":"2012 E Washington St",
    "sg:city":"New Castle",
    "sg:classifiers":[
        {
            "category":"Autos & Motor Vehicles",
            "subcategory":"Fuel & Gas Station",
            "type":"Retail Goods"
        }
    ],
    "sg:phone":"+1 724 658 6617",
    "sg:postcode":"16101",
    "sg:province":"PA",
    "sg:tags":[
        "oil"
    ],
    "wof:name":"Shenango Sunoco",
    "wof:placetype":"venue"
},
  "geometry": {"coordinates":[-80.318225,40.977214],"type":"Point"}
}