{
  "type": "Feature",
  "properties": {
    "iso:country":"US",
    "sg:address":"42 Progress St Ste A",
    "sg:city":"Brookville",
    "sg:classifiers":[
        {
            "category":"Personal",
            "subcategory":"Beauty Salon",
            "type":"Services"
        }
    ],
    "sg:phone":"+1 814 849 2425",
    "sg:postcode":"15825",
    "sg:province":"PA",
    "wof:name":"Scissors & Rayz",
    "wof:placetype":"venue"
},
  "geometry": {"coordinates":[-79.095531,41.162355],"type":"Point"}
}