{
  "type": "Feature",
  "properties": {
    "iso:country":"US",
    "sg:address":"201 W Wishart St",
    "sg:city":"Philadelphia",
    "sg:classifiers":[
        {
            "category":"Professional",
            "subcategory":"Business Services",
            "type":"Services"
        }
    ],
    "sg:phone":"+1 215 423 3010",
    "sg:postcode":"19133",
    "sg:province":"PA",
    "sg:tags":[
        "license"
    ],
    "wof:name":"Direct Hit Agent Marketing",
    "wof:placetype":"venue"
},
  "geometry": {"coordinates":[-75.13453,39.998698],"type":"Point"}
}