{
  "type": "Feature",
  "properties": {
    "addr:full":"1215 Crest Ave Charleroi PA 15022",
    "addr:housenumber":"1215",
    "addr:postcode":"15022",
    "addr:street":"Crest Ave",
    "iso:country":"US",
    "sg:address":"1215 Crest Ave",
    "sg:city":"Charleroi",
    "sg:classifiers":[
        {
            "category":"Autos & Motor Vehicles",
            "subcategory":"Auto Supplies",
            "type":"Retail Goods"
        }
    ],
    "sg:phone":"+1 724 489 0103",
    "sg:postcode":"15022",
    "sg:province":"PA",
    "sg:tags":[
        "automobile",
        "part"
    ],
    "wof:name":"Shirley Wilson",
    "wof:placetype":"venue"
},
  "geometry": {"coordinates":[-79.906736,40.143876],"type":"Point"}
}