{
  "type": "Feature",
  "properties": {
    "iso:country":"US",
    "sg:address":"695 Delaware Ave",
    "sg:city":"Palmerton",
    "sg:classifiers":[
        {
            "category":"Restaurant",
            "type":"Food & Drink"
        }
    ],
    "sg:phone":"+1   ",
    "sg:postcode":"18071",
    "sg:province":"PA",
    "sg:tags":[
        "eating"
    ],
    "wof:name":"Palmerton Pizza",
    "wof:placetype":"venue"
},
  "geometry": {"coordinates":[-75.60165600000001,40.805096],"type":"Point"}
}