{
  "type": "Feature",
  "properties": {
    "iso:country":"US",
    "sg:address":"6550 Frankford Ave",
    "sg:city":"Philadelphia",
    "sg:classifiers":[
        {
            "category":"Autos & Motor Vehicles",
            "subcategory":"Automobile Sales",
            "type":"Retail Goods"
        },
        {
            "category":"Retail",
            "subcategory":"Auto Repair",
            "type":"Services"
        }
    ],
    "sg:phone":"+1 215 331 9381",
    "sg:postcode":"19135",
    "sg:province":"PA",
    "sg:tags":[
        "dealers-used",
        "new",
        "used",
        "cars-wholesale",
        "car"
    ],
    "wof:name":"Bell Auto Group",
    "wof:placetype":"venue"
},
  "geometry": {"coordinates":[-75.055165,40.030371],"type":"Point"}
}