{
  "type": "Feature",
  "properties": {
    "iso:country":"US",
    "sg:address":"2420 E Allegheny Ave",
    "sg:city":"Philadelphia",
    "sg:classifiers":[
        {
            "category":"Education",
            "subcategory":"School",
            "type":"Public Place"
        }
    ],
    "sg:phone":"+1 215 427 3499",
    "sg:postcode":"19134",
    "sg:province":"PA",
    "wof:name":"Our Lady Help-Christians Sch",
    "wof:placetype":"venue"
},
  "geometry": {"coordinates":[-75.105915,39.988037],"type":"Point"}
}