{
  "type": "Feature",
  "properties": {
    "iso:country":"US",
    "sg:address":"806 E Lancaster Ave",
    "sg:city":"Berwyn",
    "sg:classifiers":[
        {
            "category":"Personal",
            "subcategory":"Beauty Salon",
            "type":"Services"
        }
    ],
    "sg:phone":"+1 610 640 9156",
    "sg:postcode":"19312",
    "sg:province":"PA",
    "sg:tags":[
        "shop"
    ],
    "sg:website":"www.impressionshair.com",
    "wof:name":"Impressions Hair Salon",
    "wof:placetype":"venue"
},
  "geometry": {"coordinates":[-75.445176,40.046326],"type":"Point"}
}