{
  "type": "Feature",
  "properties": {
    "iso:country":"US",
    "sg:address":"86 N Old Turnpike Rd",
    "sg:city":"Drums",
    "sg:classifiers":[
        {
            "category":"Health Services",
            "subcategory":"Clinic",
            "type":"Services"
        },
        {
            "category":"Health Services",
            "subcategory":"Health Practitioner",
            "type":"Services"
        }
    ],
    "sg:phone":"+1 570 788 5357",
    "sg:postcode":"18222",
    "sg:province":"PA",
    "sg:tags":[
        "therapist",
        "therapy",
        "physical"
    ],
    "wof:name":"Physical Therapy Con",
    "wof:placetype":"venue"
},
  "geometry": {"coordinates":[-75.99527399999999,41.022291],"type":"Point"}
}