{
  "type": "Feature",
  "properties": {
    "addr:full":"6110 Carlisle Pike Mechanicsburg PA 17050",
    "addr:housenumber":"6110",
    "addr:postcode":"17050",
    "addr:street":"Carlisle Pike",
    "iso:country":"US",
    "sg:address":"6110 Carlisle Pike",
    "sg:city":"Mechanicsburg",
    "sg:classifiers":[
        {
            "category":"Autos & Motor Vehicles",
            "subcategory":"Automobile Sales",
            "type":"Retail Goods"
        }
    ],
    "sg:phone":"+1 717 697 6970",
    "sg:postcode":"17050",
    "sg:province":"PA",
    "sg:tags":[
        "car",
        "dealer"
    ],
    "wof:name":"Second Chance Credit Ctr",
    "wof:placetype":"venue"
},
  "geometry": {"coordinates":[-76.994101,40.244032],"type":"Point"}
}