{
  "type": "Feature",
  "properties": {
    "addr:full":"31 Catherine St Reading PA 19607",
    "addr:housenumber":"31",
    "addr:postcode":"19607",
    "addr:street":"Catherine St",
    "iso:country":"US",
    "sg:address":"31 Catherine St",
    "sg:city":"Reading",
    "sg:classifiers":[
        {
            "category":"Sports & Exercise",
            "subcategory":"Gym",
            "type":"Entertainment"
        }
    ],
    "sg:phone":"+1 610 775 3435",
    "sg:postcode":"19607",
    "sg:province":"PA",
    "sg:tags":[
        "fitness",
        "physical",
        "facility"
    ],
    "wof:name":"Optihealth Fitness Club",
    "wof:placetype":"venue"
},
  "geometry": {"coordinates":[-75.968728,40.30268],"type":"Point"}
}