{
  "type": "Feature",
  "properties": {
    "iso:country":"US",
    "sg:address":"9942 Ridge Rd",
    "sg:city":"Girard",
    "sg:classifiers":[
        {
            "category":"Retail",
            "subcategory":"Auto Repair",
            "type":"Services"
        }
    ],
    "sg:phone":"+1 814 774 5901",
    "sg:postcode":"16417",
    "sg:province":"PA",
    "sg:tags":[
        "repairing",
        "automobile"
    ],
    "wof:name":"Elk Valley Automotive",
    "wof:placetype":"venue"
},
  "geometry": {"coordinates":[-80.331312,41.994942],"type":"Point"}
}