{
  "type": "Feature",
  "properties": {
    "addr:full":"172 N Wales Rd North Wales PA 19454",
    "addr:housenumber":"172",
    "addr:postcode":"19454",
    "addr:street":"N Wales Rd",
    "iso:country":"US",
    "sg:address":"172 N Wales Rd",
    "sg:city":"North Wales",
    "sg:classifiers":[
        {
            "category":"Home & Garden",
            "subcategory":"Building Materials",
            "type":"Retail Goods"
        },
        {
            "category":"Retail",
            "subcategory":"Auto Repair",
            "type":"Services"
        }
    ],
    "sg:phone":"+1 215 409 8468",
    "sg:postcode":"19454",
    "sg:province":"PA",
    "sg:tags":[
        "coating",
        "tinting",
        "glass",
        "window",
        "safety",
        "solar",
        "film"
    ],
    "sg:website":"www.suncontrolspecialists.com",
    "wof:name":"Sun Control Specialists LLC",
    "wof:placetype":"venue"
},
  "geometry": {"coordinates":[-75.259595,40.231156],"type":"Point"}
}