{
  "type": "Feature",
  "properties": {
    "iso:country":"US",
    "sg:address":"901 S Main St",
    "sg:city":"Taylor",
    "sg:classifiers":[
        {
            "category":"Retail",
            "subcategory":"Car Wash",
            "type":"Services"
        }
    ],
    "sg:phone":"+1 570 562 0957",
    "sg:postcode":"18517",
    "sg:province":"PA",
    "sg:tags":[
        "polishing",
        "washing"
    ],
    "wof:name":"Kleen & Gentle Auto Wash",
    "wof:placetype":"venue"
},
  "geometry": {"coordinates":[-75.72319,41.376612],"type":"Point"}
}