{
  "type": "Feature",
  "properties": {
    "addr:full":"222 E Main St Pen Argyl PA 18072",
    "addr:housenumber":"222",
    "addr:postcode":"18072",
    "addr:street":"E Main St",
    "iso:country":"US",
    "sg:address":"222 E Main St",
    "sg:city":"Pen Argyl",
    "sg:classifiers":[
        {
            "category":"Professional",
            "subcategory":"Lawyer & Legal Services",
            "type":"Services"
        }
    ],
    "sg:phone":"+1 610 863 8186",
    "sg:postcode":"18072",
    "sg:province":"PA",
    "sg:tags":[
        "attorney"
    ],
    "wof:name":"Pierce & Dally",
    "wof:placetype":"venue"
},
  "geometry": {"coordinates":[-75.251307,40.869332],"type":"Point"}
}