{
  "type": "Feature",
  "properties": {
    "iso:country":"US",
    "sg:address":"15386 W Grandview Ave",
    "sg:city":"Meadville",
    "sg:classifiers":[
        {
            "category":"Wholesale",
            "subcategory":"Books, Periodicals, & Newspapers",
            "type":"Manufacturing & Wholesale Goods"
        }
    ],
    "sg:phone":"+1 814 336 3878",
    "sg:postcode":"16335",
    "sg:province":"PA",
    "sg:tags":[
        "publisher",
        "book"
    ],
    "wof:name":"Kosco Press",
    "wof:placetype":"venue"
},
  "geometry": {"coordinates":[-80.22520299999999,41.612483],"type":"Point"}
}