{
  "type": "Feature",
  "properties": {
    "iso:country":"US",
    "sg:address":"3121 Fairway Dr",
    "sg:city":"Altoona",
    "sg:classifiers":[
        {
            "category":"Professional",
            "subcategory":"Engineering",
            "type":"Services"
        }
    ],
    "sg:phone":"+1 814 943 5214",
    "sg:postcode":"16602",
    "sg:province":"PA",
    "sg:tags":[
        "engineer"
    ],
    "sg:website":"www.gdfengineers.com",
    "wof:name":"Gwin Dobson & Foreman Inc",
    "wof:placetype":"venue"
},
  "geometry": {"coordinates":[-78.394831,40.484774],"type":"Point"}
}