{
  "type": "Feature",
  "properties": {
    "addr:full":"101 W Main St Millheim PA 16854",
    "addr:housenumber":"101",
    "addr:postcode":"16854",
    "addr:street":"W Main St",
    "iso:country":"US",
    "sg:address":"101 W Main St",
    "sg:city":"Millheim",
    "sg:classifiers":[
        {
            "category":"Government",
            "subcategory":"Post Office",
            "type":"Public Place"
        }
    ],
    "sg:phone":"+1 814 349 5522",
    "sg:postcode":"16854",
    "sg:province":"PA",
    "wof:name":"US Post Office",
    "wof:placetype":"venue"
},
  "geometry": {"coordinates":[-77.47677299999999,40.890961],"type":"Point"}
}