{
  "type": "Feature",
  "properties": {
    "iso:country":"US",
    "sg:address":"3615 Forbes Ave",
    "sg:city":"Pittsburgh",
    "sg:classifiers":[
        {
            "category":"Restaurant",
            "type":"Food & Drink"
        }
    ],
    "sg:menulink":"http://www.allmenus.com/pa/pittsburgh/222012-chipotle/menu/",
    "sg:phone":"+1 412 621 1557",
    "sg:postcode":"15213",
    "sg:province":"PA",
    "sg:tags":[
        "mexican"
    ],
    "wof:name":"Chipotle",
    "wof:placetype":"venue"
},
  "geometry": {"coordinates":[-79.95828,40.44065],"type":"Point"}
}