{
  "type": "Feature",
  "properties": {
    "iso:country":"US",
    "sg:address":"1500 Broad St",
    "sg:city":"Greensburg",
    "sg:classifiers":[
        {
            "category":"Professional",
            "subcategory":"Management & Consulting",
            "type":"Services"
        }
    ],
    "sg:phone":"+1   ",
    "sg:postcode":"15601",
    "sg:province":"PA",
    "sg:tags":[
        "company"
    ],
    "wof:name":"Dr Bobs Medical Weight Loss",
    "wof:placetype":"venue"
},
  "geometry": {"coordinates":[-79.54847599999999,40.276424],"type":"Point"}
}