{
  "type": "Feature",
  "properties": {
    "iso:country":"US",
    "sg:address":"662 Exton Cmns",
    "sg:city":"Exton",
    "sg:classifiers":[
        {
            "category":"Professional",
            "subcategory":"Management & Consulting",
            "type":"Services"
        }
    ],
    "sg:phone":"+1 610 524 7070",
    "sg:postcode":"19341",
    "sg:province":"PA",
    "sg:tags":[
        "marketing",
        "program"
    ],
    "sg:website":"www.tenaska.com",
    "wof:name":"Grade Finders Inc",
    "wof:placetype":"venue"
},
  "geometry": {"coordinates":[-75.62364599999999,40.034198],"type":"Point"}
}