{
  "type": "Feature",
  "properties": {
    "iso:country":"US",
    "sg:address":"1845 Meadow Ln",
    "sg:city":"Montoursville",
    "sg:classifiers":[
        {
            "category":"Real Estate",
            "subcategory":"Real Estate Operator",
            "type":"Services"
        }
    ],
    "sg:phone":"+1   ",
    "sg:postcode":"17754",
    "sg:province":"PA",
    "sg:tags":[
        "building",
        "apartment"
    ],
    "wof:name":"Insinger Apts",
    "wof:placetype":"venue"
},
  "geometry": {"coordinates":[-76.93326,41.265026],"type":"Point"}
}