{
  "type": "Feature",
  "properties": {
    "iso:country":"US",
    "sg:address":"1802 Stefko Blvd",
    "sg:city":"Bethlehem",
    "sg:classifiers":[
        {
            "category":"Restaurant",
            "type":"Food & Drink"
        }
    ],
    "sg:phone":"+1   ",
    "sg:postcode":"18017",
    "sg:province":"PA",
    "sg:tags":[
        "eating"
    ],
    "wof:name":"JS Submarines",
    "wof:placetype":"venue"
},
  "geometry": {"coordinates":[-75.348623,40.63846],"type":"Point"}
}