{
  "type": "Feature",
  "properties": {
    "iso:country":"US",
    "sg:address":"390 Market St",
    "sg:city":"Kingston",
    "sg:classifiers":[
        {
            "category":"Autos & Motor Vehicles",
            "subcategory":"Auto Supplies",
            "type":"Retail Goods"
        }
    ],
    "sg:phone":"+1 570 714 3515",
    "sg:postcode":"18704",
    "sg:province":"PA",
    "sg:tags":[
        "automobile",
        "alarm"
    ],
    "wof:name":"Rides & Rhythms",
    "wof:placetype":"venue"
},
  "geometry": {"coordinates":[-75.892814,41.257037],"type":"Point"}
}