{
  "type": "Feature",
  "properties": {
    "addr:full":"202 Basin St Williamsport PA 17701",
    "addr:housenumber":"202",
    "addr:postcode":"17701",
    "addr:street":"Basin St",
    "iso:country":"US",
    "sg:address":"202 Basin St",
    "sg:city":"Williamsport",
    "sg:classifiers":[
        {
            "category":"Professional",
            "subcategory":"Management & Consulting",
            "type":"Services"
        }
    ],
    "sg:phone":"+1 570 327 2077",
    "sg:postcode":"17701",
    "sg:province":"PA",
    "sg:tags":[
        "construction"
    ],
    "wof:name":"Myler Co Church Building Systs",
    "wof:placetype":"venue"
},
  "geometry": {"coordinates":[-76.995977,41.241926],"type":"Point"}
}