{
  "type": "Feature",
  "properties": {
    "iso:country":"US",
    "sg:address":"6990 Snowdrift Rd",
    "sg:city":"Allentown",
    "sg:classifiers":[
        {
            "category":"Wholesale",
            "subcategory":"Machinery & Supplies",
            "type":"Manufacturing & Wholesale Goods"
        }
    ],
    "sg:phone":"+1 610 336 6300",
    "sg:postcode":"18106",
    "sg:province":"PA",
    "sg:tags":[
        "equipment",
        "welding"
    ],
    "wof:name":"Airgas East",
    "wof:placetype":"venue"
},
  "geometry": {"coordinates":[-75.609917,40.590585],"type":"Point"}
}