{
  "type": "Feature",
  "properties": {
    "iso:country":"US",
    "sg:address":"869 Thomas St",
    "sg:city":"State College",
    "sg:classifiers":[
        {
            "category":"Building & Trades",
            "subcategory":"Construction",
            "type":"Services"
        }
    ],
    "sg:phone":"+1   ",
    "sg:postcode":"16803",
    "sg:province":"PA",
    "sg:tags":[
        "house"
    ],
    "wof:name":"Lou Pacchioni",
    "wof:placetype":"venue"
},
  "geometry": {"coordinates":[-77.87469400000001,40.80267],"type":"Point"}
}