{
  "type": "Feature",
  "properties": {
    "iso:country":"US",
    "sg:address":"123 Alburger Ave",
    "sg:city":"Philadelphia",
    "sg:classifiers":[
        {
            "category":"Building & Trades",
            "subcategory":"Construction",
            "type":"Services"
        }
    ],
    "sg:phone":"+1 215 330 0966",
    "sg:postcode":"19115",
    "sg:province":"PA",
    "sg:tags":[
        "painter"
    ],
    "wof:name":"Happy Hands Painting & Home",
    "wof:placetype":"venue"
},
  "geometry": {"coordinates":[-75.061263,40.099239],"type":"Point"}
}