{
  "type": "Feature",
  "properties": {
    "iso:country":"US",
    "sg:address":"360 Saint Charles Way",
    "sg:city":"York",
    "sg:classifiers":[
        {
            "category":"Health Services",
            "subcategory":"Doctor",
            "type":"Services"
        }
    ],
    "sg:phone":"+1 717 757 2020",
    "sg:postcode":"17402",
    "sg:province":"PA",
    "sg:tags":[
        "medical"
    ],
    "wof:name":"Christianne Schoedel MD",
    "wof:placetype":"venue"
},
  "geometry": {"coordinates":[-76.695131,39.926451],"type":"Point"}
}