{
  "type": "Feature",
  "properties": {
    "iso:country":"US",
    "sg:address":"35 Tower Rd",
    "sg:city":"Sellersville",
    "sg:classifiers":[
        {
            "category":"Building & Trades",
            "subcategory":"Plumbing",
            "type":"Services"
        }
    ],
    "sg:phone":"+1 215 257 2587",
    "sg:postcode":"18960",
    "sg:province":"PA",
    "sg:tags":[
        "contractor"
    ],
    "wof:name":"Brent Plumbing & Heating",
    "wof:placetype":"venue"
},
  "geometry": {"coordinates":[-75.35154799999999,40.372059],"type":"Point"}
}