{
  "type": "Feature",
  "properties": {
    "addr:full":"859 Water St Meadville PA 16335",
    "addr:housenumber":"859",
    "addr:postcode":"16335",
    "addr:street":"Water St",
    "iso:country":"US",
    "sg:address":"859 Water St",
    "sg:city":"Meadville",
    "sg:classifiers":[
        {
            "category":"Professional",
            "subcategory":"Business Services",
            "type":"Services"
        }
    ],
    "sg:phone":"+1 814 333 2044",
    "sg:postcode":"16335",
    "sg:province":"PA",
    "sg:tags":[
        "personal",
        "clo"
    ],
    "wof:name":"Balloons & Costumes By Lori",
    "wof:placetype":"venue"
},
  "geometry": {"coordinates":[-80.154212,41.640628],"type":"Point"}
}