{
  "type": "Feature",
  "properties": {
    "addr:full":"101 E Pittsburgh St Greensburg PA 15601",
    "addr:housenumber":"101",
    "addr:postcode":"15601",
    "addr:street":"E Pittsburgh St",
    "iso:country":"US",
    "sg:address":"101 E Pittsburgh St",
    "sg:city":"Greensburg",
    "sg:classifiers":[
        {
            "category":"Home & Garden",
            "subcategory":"Home Furnishings",
            "type":"Retail Goods"
        }
    ],
    "sg:phone":"+1 724 834 1118",
    "sg:postcode":"15601",
    "sg:province":"PA",
    "sg:tags":[
        "floor",
        "covering"
    ],
    "wof:name":"An American Place",
    "wof:placetype":"venue"
},
  "geometry": {"coordinates":[-79.541612,40.302956],"type":"Point"}
}