{
  "type": "Feature",
  "properties": {
    "addr:full":"808 E Main St New Holland PA 17557",
    "addr:housenumber":"808",
    "addr:postcode":"17557",
    "addr:street":"E Main St",
    "iso:country":"US",
    "sg:address":"808 E Main St",
    "sg:city":"New Holland",
    "sg:classifiers":[
        {
            "category":"Manufacturing",
            "subcategory":"Rubber & Plastics",
            "type":"Manufacturing & Wholesale Goods"
        }
    ],
    "sg:phone":"+1 717 354 4997",
    "sg:postcode":"17557",
    "sg:province":"PA",
    "sg:tags":[
        "spa",
        "hot",
        "tub"
    ],
    "wof:name":"Anytime Tubs",
    "wof:placetype":"venue"
},
  "geometry": {"coordinates":[-76.063284,40.112152],"type":"Point"}
}