{
  "type": "Feature",
  "properties": {
    "addr:full":"2001 W Cambria St Philadelphia PA 19132",
    "addr:housenumber":"2001",
    "addr:postcode":"19132",
    "addr:street":"W Cambria St",
    "iso:country":"US",
    "sg:address":"2001 W Cambria St",
    "sg:city":"Philadelphia",
    "sg:classifiers":[
        {
            "category":"Organizations",
            "subcategory":"Professional Association",
            "type":"Services"
        },
        {
            "category":"Organizations",
            "subcategory":"Community Association",
            "type":"Services"
        }
    ],
    "sg:phone":"+1 215 229 5508",
    "sg:postcode":"19132",
    "sg:province":"PA",
    "wof:name":"Woodstock Civic Association",
    "wof:placetype":"venue"
},
  "geometry": {"coordinates":[-75.164051,39.99832],"type":"Point"}
}