{
  "type": "Feature",
  "properties": {
    "addr:full":"117 N 15th St Philadelphia PA 19102",
    "addr:housenumber":"117",
    "addr:postcode":"19102",
    "addr:street":"N 15Th St",
    "iso:country":"US",
    "sg:address":"117 N 15th St",
    "sg:city":"Philadelphia",
    "sg:classifiers":[
        {
            "category":"Real Estate",
            "subcategory":"Real Estate Services",
            "type":"Services"
        }
    ],
    "sg:phone":"+1 215 735 7800",
    "sg:postcode":"19102",
    "sg:province":"PA",
    "sg:tags":[
        "management",
        "property"
    ],
    "sg:website":"reinholdresidential.com/",
    "wof:name":"JA Reinhold Residential",
    "wof:placetype":"venue"
},
  "geometry": {"coordinates":[-75.16470200000001,39.955225],"type":"Point"}
}