{
  "type": "Feature",
  "properties": {
    "iso:country":"US",
    "sg:address":"2000 Germantown Ave",
    "sg:city":"Philadelphia",
    "sg:classifiers":[
        {
            "category":"Restaurant",
            "type":"Food & Drink"
        }
    ],
    "sg:phone":"+1 215 232 6998",
    "sg:postcode":"19122",
    "sg:province":"PA",
    "sg:tags":[
        "chinese"
    ],
    "wof:name":"China Star",
    "wof:placetype":"venue"
},
  "geometry": {"coordinates":[-75.1437,39.981701],"type":"Point"}
}