{
  "type": "Feature",
  "properties": {
    "addr:full":"6560 Senator Ln Bensalem PA 19020",
    "addr:housenumber":"6560",
    "addr:postcode":"19020",
    "addr:street":"Senator Ln",
    "iso:country":"US",
    "sg:address":"6560 Senator Ln",
    "sg:city":"Bensalem",
    "sg:classifiers":[
        {
            "category":"Wholesale",
            "subcategory":"Machinery & Supplies",
            "type":"Manufacturing & Wholesale Goods"
        }
    ],
    "sg:phone":"+1 215 750 8686",
    "sg:postcode":"19020",
    "sg:province":"PA",
    "sg:tags":[
        "baling",
        "equipment"
    ],
    "wof:name":"Associated Machine Svc Inc",
    "wof:placetype":"venue"
},
  "geometry": {"coordinates":[-74.92487800000001,40.148303],"type":"Point"}
}