{
  "type": "Feature",
  "properties": {
    "iso:country":"US",
    "sg:address":"26 S 5th St",
    "sg:city":"Perkasie",
    "sg:classifiers":[
        {
            "category":"Health Services",
            "subcategory":"Doctor",
            "type":"Services"
        }
    ],
    "sg:phone":"+1 215 257 2661",
    "sg:postcode":"18944",
    "sg:province":"PA",
    "sg:tags":[
        "dentist"
    ],
    "wof:name":"Dental Health Ctr",
    "wof:placetype":"venue"
},
  "geometry": {"coordinates":[-75.29455,40.372739],"type":"Point"}
}