{
  "type": "Feature",
  "properties": {
    "addr:full":"6242 Roosevelt Blvd Philadelphia PA 19149",
    "addr:housenumber":"6242",
    "addr:postcode":"19149",
    "addr:street":"Roosevelt Blvd",
    "iso:country":"US",
    "sg:address":"6242 Roosevelt Blvd",
    "sg:city":"Philadelphia",
    "sg:classifiers":[
        {
            "category":"Real Estate",
            "subcategory":"Real Estate Operator",
            "type":"Services"
        }
    ],
    "sg:phone":"+1   ",
    "sg:postcode":"19149",
    "sg:province":"PA",
    "sg:tags":[
        "building",
        "apartment"
    ],
    "wof:name":"Korman Suites At Apartment Ctr",
    "wof:placetype":"venue"
},
  "geometry": {"coordinates":[-75.07408100000001,40.034508],"type":"Point"}
}