{
  "type": "Feature",
  "properties": {
    "iso:country":"US",
    "sg:address":"1 Mifflin St",
    "sg:city":"West Mifflin",
    "sg:classifiers":[
        {
            "category":"Social Services",
            "type":"Services"
        }
    ],
    "sg:phone":"+1 412 461 8610",
    "sg:postcode":"15110",
    "sg:province":"PA",
    "sg:tags":[
        "organization",
        "welfare"
    ],
    "wof:name":"Monview Heights YMCA Prgrm",
    "wof:placetype":"venue"
},
  "geometry": {"coordinates":[-79.85893900000001,40.366741],"type":"Point"}
}