{
  "type": "Feature",
  "properties": {
    "iso:country":"US",
    "sg:address":"400 S Main St",
    "sg:city":"Greensburg",
    "sg:classifiers":[
        {
            "category":"Banks & Credit Unions",
            "subcategory":"Bank",
            "type":"Services"
        }
    ],
    "sg:phone":"+1 724 832 5900",
    "sg:postcode":"15601",
    "sg:province":"PA",
    "wof:name":"Citizens Bank",
    "wof:placetype":"venue"
},
  "geometry": {"coordinates":[-79.54288699999999,40.2984],"type":"Point"}
}