{
  "type": "Feature",
  "properties": {
    "iso:country":"US",
    "sg:address":"616 Guilden Rd",
    "sg:city":"Blandon",
    "sg:classifiers":[
        {
            "category":"Shopping",
            "subcategory":"Clothing, Apparel, & Fashions",
            "type":"Retail Goods"
        }
    ],
    "sg:phone":"+1   ",
    "sg:postcode":"19510",
    "sg:province":"PA",
    "wof:name":"C N J Leathers",
    "wof:placetype":"venue"
},
  "geometry": {"coordinates":[-75.875452,40.438575],"type":"Point"}
}