{
  "type": "Feature",
  "properties": {
    "iso:country":"US",
    "sg:address":"3 Wharton Dr",
    "sg:city":"Glen Mills",
    "sg:classifiers":[
        {
            "category":"Building & Trades",
            "subcategory":"Construction",
            "type":"Services"
        }
    ],
    "sg:phone":"+1 610 399 8344",
    "sg:postcode":"19342",
    "sg:province":"PA",
    "sg:tags":[
        "contractor"
    ],
    "wof:name":"Orleans Home Builders",
    "wof:placetype":"venue"
},
  "geometry": {"coordinates":[-75.522288,39.943891],"type":"Point"}
}