{
  "type": "Feature",
  "properties": {
    "addr:full":"206 S Jennersville Rd West Grove PA 19390",
    "addr:housenumber":"206",
    "addr:postcode":"19390",
    "addr:street":"S Jennersville Rd",
    "iso:country":"US",
    "sg:address":"206 S Jennersville Rd",
    "sg:city":"West Grove",
    "sg:classifiers":[
        {
            "category":"Professional",
            "subcategory":"Accounting & Tax Preparation",
            "type":"Services"
        }
    ],
    "sg:phone":"+1 610 869 0300",
    "sg:postcode":"19390",
    "sg:province":"PA",
    "sg:tags":[
        "billing"
    ],
    "wof:name":"Brandywine Collection Inc",
    "wof:placetype":"venue"
},
  "geometry": {"coordinates":[-75.877791,39.809141],"type":"Point"}
}