{
  "type": "Feature",
  "properties": {
    "iso:country":"US",
    "sg:address":"3646 Pottsville Pike",
    "sg:city":"Reading",
    "sg:classifiers":[
        {
            "category":"Organizations",
            "subcategory":"Religious Organization",
            "type":"Services"
        }
    ],
    "sg:phone":"+1 610 929 5212",
    "sg:postcode":"19605",
    "sg:province":"PA",
    "sg:tags":[
        "church"
    ],
    "wof:name":"New Creation Fellowship",
    "wof:placetype":"venue"
},
  "geometry": {"coordinates":[-75.93491,40.388282],"type":"Point"}
}