{
  "type": "Feature",
  "properties": {
    "iso:country":"US",
    "sg:address":"15 N Lime St",
    "sg:city":"Lancaster",
    "sg:classifiers":[
        {
            "category":"Professional",
            "subcategory":"Lawyer & Legal Services",
            "type":"Services"
        }
    ],
    "sg:phone":"+1 717 397 5127",
    "sg:postcode":"17602",
    "sg:province":"PA",
    "sg:tags":[
        "attorney"
    ],
    "wof:name":"Honaman Longo & Longo",
    "wof:placetype":"venue"
},
  "geometry": {"coordinates":[-76.301344,40.038727],"type":"Point"}
}