{
  "type": "Feature",
  "properties": {
    "addr:full":"3300 Hartzdale Dr Camp Hill PA 17011",
    "addr:postcode":"3300;17011",
    "addr:street":"Hartzdale Dr",
    "iso:country":"US",
    "sg:address":"3300 Hartzdale Dr",
    "sg:city":"Camp Hill",
    "sg:classifiers":[
        {
            "category":"Professional",
            "subcategory":"Business Services",
            "type":"Services"
        }
    ],
    "sg:phone":"+1 717 737 7848",
    "sg:postcode":"17011",
    "sg:province":"PA",
    "sg:tags":[
        "packaging"
    ],
    "wof:name":"Packaging Store",
    "wof:placetype":"venue"
},
  "geometry": {"coordinates":[-76.925628,40.228365],"type":"Point"}
}