{
  "type": "Feature",
  "properties": {
    "iso:country":"US",
    "sg:address":"315 Church St",
    "sg:city":"Hawley",
    "sg:classifiers":[
        {
            "category":"Organizations",
            "subcategory":"Religious Organization",
            "type":"Services"
        }
    ],
    "sg:phone":"+1 570 226 3875",
    "sg:postcode":"18428",
    "sg:province":"PA",
    "wof:name":"Hawley Methodist Church",
    "wof:placetype":"venue"
},
  "geometry": {"coordinates":[-75.183868,41.475027],"type":"Point"}
}