{
  "type": "Feature",
  "properties": {
    "iso:country":"US",
    "sg:address":"535 Center St",
    "sg:city":"Bethlehem",
    "sg:classifiers":[
        {
            "category":"Professional",
            "subcategory":"Secretarial Services",
            "type":"Services"
        }
    ],
    "sg:phone":"+1 610 868 8126",
    "sg:postcode":"18018",
    "sg:province":"PA",
    "sg:tags":[
        "processing",
        "word"
    ],
    "wof:name":"Bright Side",
    "wof:placetype":"venue"
},
  "geometry": {"coordinates":[-75.375426,40.622155],"type":"Point"}
}