{
  "type": "Feature",
  "properties": {
    "addr:full":"610 Montgomery Ave Narberth PA 19072",
    "addr:housenumber":"610",
    "addr:postcode":"19072",
    "addr:street":"Montgomery Ave",
    "iso:country":"US",
    "sg:address":"610 Montgomery Ave",
    "sg:city":"Narberth",
    "sg:classifiers":[
        {
            "category":"Personal",
            "subcategory":"Barber",
            "type":"Services"
        }
    ],
    "sg:phone":"+1 610 664 5903",
    "sg:postcode":"19072",
    "sg:province":"PA",
    "wof:name":"Hair Studio One",
    "wof:placetype":"venue"
},
  "geometry": {"coordinates":[-75.25299800000001,40.0089],"type":"Point"}
}