{
  "type": "Feature",
  "properties": {
    "iso:country":"US",
    "sg:address":"903 Broadway",
    "sg:city":"Fountain Hill",
    "sg:classifiers":[
        {
            "category":"Autos & Motor Vehicles",
            "subcategory":"Fuel & Gas Station",
            "type":"Retail Goods"
        }
    ],
    "sg:phone":"+1 610 691 1788",
    "sg:postcode":"18015",
    "sg:province":"PA",
    "sg:website":"www.texaco.com",
    "wof:name":"Broadway Texaco and Service Center",
    "wof:placetype":"venue"
},
  "geometry": {"coordinates":[-75.390099,40.6049],"type":"Point"}
}