{
  "type": "Feature",
  "properties": {
    "addr:full":"2961 W Liberty Ave South Hills PA 15216",
    "addr:housenumber":"2961",
    "addr:postcode":"15216",
    "addr:street":"W Liberty Ave South Hills",
    "iso:country":"US",
    "sg:address":"2961 W Liberty Ave",
    "sg:city":"South Hills",
    "sg:classifiers":[
        {
            "category":"Professional",
            "subcategory":"Business Services",
            "type":"Services"
        }
    ],
    "sg:phone":"+1 412 563 5940",
    "sg:postcode":"15216",
    "sg:province":"PA",
    "sg:tags":[
        "telemarketing"
    ],
    "wof:name":"Automated Protection Svc",
    "wof:placetype":"venue"
},
  "geometry": {"coordinates":[-80.034948,40.394531],"type":"Point"}
}