{
  "type": "Feature",
  "properties": {
    "iso:country":"US",
    "sg:address":"1515 Arch St",
    "sg:city":"Philadelphia",
    "sg:classifiers":[
        {
            "category":"Government",
            "subcategory":"Office",
            "type":"Public Place"
        }
    ],
    "sg:phone":"+1   ",
    "sg:postcode":"19102",
    "sg:province":"PA",
    "sg:tags":[
        "executive",
        "municipality"
    ],
    "wof:name":"Human Services Dept",
    "wof:placetype":"venue"
},
  "geometry": {"coordinates":[-75.166186,39.954862],"type":"Point"}
}