{
  "type": "Feature",
  "properties": {
    "iso:country":"US",
    "sg:address":"8846 Frankford Ave",
    "sg:city":"Philadelphia",
    "sg:classifiers":[
        {
            "category":"Health Services",
            "subcategory":"Doctor",
            "type":"Services"
        }
    ],
    "sg:phone":"+1   ",
    "sg:postcode":"19136",
    "sg:province":"PA",
    "sg:tags":[
        "building",
        "medical",
        "nonresidential"
    ],
    "wof:name":"Stein Franklin M MD",
    "wof:placetype":"venue"
},
  "geometry": {"coordinates":[-75.010379,40.050473],"type":"Point"}
}