{
  "type": "Feature",
  "properties": {
    "addr:full":"30 Spinneweber St Pittsburgh PA 15227",
    "addr:housenumber":"30",
    "addr:postcode":"15227",
    "addr:street":"Spinneweber St",
    "iso:country":"US",
    "sg:address":"30 Spinneweber St",
    "sg:city":"Pittsburgh",
    "sg:classifiers":[
        {
            "category":"Building & Trades",
            "subcategory":"Construction",
            "type":"Services"
        }
    ],
    "sg:phone":"+1 412 884 7379",
    "sg:postcode":"15227",
    "sg:province":"PA",
    "sg:tags":[
        "paving",
        "contractor"
    ],
    "wof:name":"Sciarretti General Contractors, Inc.",
    "wof:placetype":"venue"
},
  "geometry": {"coordinates":[-79.990106,40.380332],"type":"Point"}
}