{
  "type": "Feature",
  "properties": {
    "iso:country":"US",
    "sg:address":"11 Holiday Dr",
    "sg:city":"Kingston",
    "sg:classifiers":[
        {
            "category":"Real Estate",
            "subcategory":"Real Estate Operator",
            "type":"Services"
        }
    ],
    "sg:phone":"+1   ",
    "sg:postcode":"18704",
    "sg:province":"PA",
    "sg:tags":[
        "building",
        "apartment"
    ],
    "wof:name":"Holiday Green Acres Apartments",
    "wof:placetype":"venue"
},
  "geometry": {"coordinates":[-75.878366,41.268199],"type":"Point"}
}