{
  "type": "Feature",
  "properties": {
    "addr:full":"2319 Perkiomen Ave Reading PA 19606",
    "addr:postcode":"2319;19606",
    "addr:street":"Perkiomen Ave",
    "iso:country":"US",
    "sg:address":"2319 Perkiomen Ave",
    "sg:city":"Reading",
    "sg:classifiers":[
        {
            "category":"Personal",
            "subcategory":"Beauty Salon",
            "type":"Services"
        }
    ],
    "sg:phone":"+1 610 779 5520",
    "sg:postcode":"19606",
    "sg:province":"PA",
    "wof:name":"Barry Vogt's Beauty Shop",
    "wof:placetype":"venue"
},
  "geometry": {"coordinates":[-75.890079,40.32788],"type":"Point"}
}