{
  "type": "Feature",
  "properties": {
    "iso:country":"US",
    "sg:address":"103 N 2nd St",
    "sg:city":"West Newton",
    "sg:classifiers":[
        {
            "category":"Manufacturing",
            "subcategory":"Printing",
            "type":"Manufacturing & Wholesale Goods"
        }
    ],
    "sg:phone":"+1 724 872 4160",
    "sg:postcode":"15089",
    "sg:province":"PA",
    "sg:tags":[
        "lithographic",
        "commercial"
    ],
    "wof:name":"Village Print Shop",
    "wof:placetype":"venue"
},
  "geometry": {"coordinates":[-79.76703500000001,40.209997],"type":"Point"}
}