{
  "type": "Feature",
  "properties": {
    "iso:country":"US",
    "sg:address":"126 Ontario Rd",
    "sg:city":"Eighty Four",
    "sg:classifiers":[
        {
            "category":"Manufacturing",
            "subcategory":"Tools & Machinery",
            "type":"Manufacturing & Wholesale Goods"
        }
    ],
    "sg:phone":"+1 724 945 6105",
    "sg:postcode":"15330",
    "sg:province":"PA",
    "sg:tags":[
        "machine",
        "shop"
    ],
    "wof:name":"Ontario Machine Shop",
    "wof:placetype":"venue"
},
  "geometry": {"coordinates":[-80.071996,40.104117],"type":"Point"}
}