{
  "type": "Feature",
  "properties": {
    "iso:country":"US",
    "sg:address":"7242 Hollywood Rd",
    "sg:city":"Fort Washington",
    "sg:classifiers":[
        {
            "category":"Manufacturing",
            "subcategory":"Tools & Machinery",
            "type":"Manufacturing & Wholesale Goods"
        }
    ],
    "sg:phone":"+1   ",
    "sg:postcode":"19034",
    "sg:province":"PA",
    "sg:tags":[
        "mfg",
        "product",
        "indoor",
        "quality",
        "air"
    ],
    "wof:name":"Clenair Manufacturing Inc",
    "wof:placetype":"venue"
},
  "geometry": {"coordinates":[-75.214232,40.138058],"type":"Point"}
}