{
  "type": "Feature",
  "properties": {
    "iso:country":"US",
    "sg:address":"435 W Burkholder Dr",
    "sg:city":"Lititz",
    "sg:classifiers":[
        {
            "category":"Farming",
            "subcategory":"Dairy Farm",
            "type":"Manufacturing & Wholesale Goods"
        }
    ],
    "sg:phone":"+1   ",
    "sg:postcode":"17543",
    "sg:province":"PA",
    "wof:name":"Arlin Hurst",
    "wof:placetype":"venue"
},
  "geometry": {"coordinates":[-76.249594,40.209661],"type":"Point"}
}