{
  "type": "Feature",
  "properties": {
    "iso:country":"US",
    "sg:address":"4415 N 5th St",
    "sg:city":"Philadelphia",
    "sg:classifiers":[
        {
            "category":"Personal",
            "subcategory":"Beauty Salon",
            "type":"Services"
        }
    ],
    "sg:phone":"+1 215 457 3648",
    "sg:postcode":"19140",
    "sg:province":"PA",
    "sg:tags":[
        "shop"
    ],
    "wof:name":"Gladys' Hair Styling Inc",
    "wof:placetype":"venue"
},
  "geometry": {"coordinates":[-75.13434599999999,40.018888],"type":"Point"}
}