{
  "type": "Feature",
  "properties": {
    "addr:full":"3527 Wessex Ln Philadelphia PA 19114",
    "addr:housenumber":"3527",
    "addr:postcode":"19114",
    "addr:street":"Wessex Ln",
    "iso:country":"US",
    "sg:address":"3527 Wessex Ln",
    "sg:city":"Philadelphia",
    "sg:classifiers":[
        {
            "category":"Manufacturing",
            "subcategory":"Petroleum Products",
            "type":"Manufacturing & Wholesale Goods"
        }
    ],
    "sg:phone":"+1 215 281 5862",
    "sg:postcode":"19114",
    "sg:province":"PA",
    "sg:tags":[
        "candles-wholesale",
        "manufacturer"
    ],
    "wof:name":"Breez Candles",
    "wof:placetype":"venue"
},
  "geometry": {"coordinates":[-74.98867799999999,40.070969],"type":"Point"}
}