{
  "type": "Feature",
  "properties": {
    "addr:full":"351 Camer Dr Bensalem PA 19020",
    "addr:housenumber":"351",
    "addr:postcode":"19020",
    "addr:street":"Camer Dr",
    "iso:country":"US",
    "sg:address":"351 Camer Dr",
    "sg:city":"Bensalem",
    "sg:classifiers":[
        {
            "category":"Wholesale",
            "subcategory":"Hardware",
            "type":"Manufacturing & Wholesale Goods"
        }
    ],
    "sg:phone":"+1   ",
    "sg:postcode":"19020",
    "sg:province":"PA",
    "sg:tags":[
        "technical"
    ],
    "wof:name":"AMC",
    "wof:placetype":"venue"
},
  "geometry": {"coordinates":[-74.939297,40.071427],"type":"Point"}
}