{
  "type": "Feature",
  "properties": {
    "iso:country":"US",
    "sg:address":"160 Germany Hollow Rd",
    "sg:city":"Honey Brook",
    "sg:classifiers":[
        {
            "category":"Professional",
            "subcategory":"Management & Consulting",
            "type":"Services"
        }
    ],
    "sg:phone":"+1 610 942 7540",
    "sg:postcode":"19344",
    "sg:province":"PA",
    "sg:tags":[
        "consultant",
        "safety"
    ],
    "wof:name":"Delaware Valley Safety Svc",
    "wof:placetype":"venue"
},
  "geometry": {"coordinates":[-75.821697,40.079179],"type":"Point"}
}