{
  "type": "Feature",
  "properties": {
    "addr:full":"3106 Buffalo Rd Erie PA 16510",
    "addr:housenumber":"3106",
    "addr:postcode":"16510",
    "addr:street":"Buffalo Rd",
    "iso:country":"US",
    "sg:address":"3106 Buffalo Rd",
    "sg:city":"Erie",
    "sg:classifiers":[
        {
            "category":"Shopping",
            "subcategory":"Pharmacy",
            "type":"Retail Goods"
        }
    ],
    "sg:phone":"+1 814 899 6136",
    "sg:postcode":"16510",
    "sg:province":"PA",
    "wof:name":"Medicine Shoppe Pharmacy",
    "wof:placetype":"venue"
},
  "geometry": {"coordinates":[-80.01562699999999,42.140178],"type":"Point"}
}