{
  "type": "Feature",
  "properties": {
    "iso:country":"US",
    "sg:address":"102 N Pitt St",
    "sg:city":"Mercer",
    "sg:classifiers":[
        {
            "category":"Manufacturing",
            "subcategory":"Printing",
            "type":"Manufacturing & Wholesale Goods"
        }
    ],
    "sg:phone":"+1   ",
    "sg:postcode":"16137",
    "sg:province":"PA",
    "sg:tags":[
        "newspaper"
    ],
    "wof:name":"Sharon Herald The",
    "wof:placetype":"venue"
},
  "geometry": {"coordinates":[-80.23782799999999,41.227672],"type":"Point"}
}