{
  "type": "Feature",
  "properties": {
    "iso:country":"US",
    "sg:address":"6730 Allentown Blvd",
    "sg:city":"Harrisburg",
    "sg:classifiers":[
        {
            "category":"Wholesale",
            "subcategory":"Auto Parts",
            "type":"Manufacturing & Wholesale Goods"
        }
    ],
    "sg:phone":"+1 717 541 9400",
    "sg:postcode":"17112",
    "sg:province":"PA",
    "sg:tags":[
        "tire"
    ],
    "wof:name":"Mc Carthy Tire & Svc",
    "wof:placetype":"venue"
},
  "geometry": {"coordinates":[-76.77387,40.326177],"type":"Point"}
}