{
  "type": "Feature",
  "properties": {
    "iso:country":"US",
    "sg:address":"300 Campus Dr",
    "sg:city":"Bradford",
    "sg:classifiers":[
        {
            "category":"Restaurant",
            "type":"Food & Drink"
        }
    ],
    "sg:phone":"+1   ",
    "sg:postcode":"16701",
    "sg:province":"PA",
    "sg:tags":[
        "eating"
    ],
    "wof:name":"Sodexho Inc",
    "wof:placetype":"venue"
},
  "geometry": {"coordinates":[-78.670275,41.946772],"type":"Point"}
}