{
  "type": "Feature",
  "properties": {
    "addr:full":"43 N Brady St Du Bois PA 15801",
    "addr:housenumber":"43",
    "addr:postcode":"15801",
    "addr:street":"N Brady St Du Bois",
    "iso:country":"US",
    "sg:address":"43 N Brady St",
    "sg:city":"Du Bois",
    "sg:classifiers":[
        {
            "category":"Insurance",
            "subcategory":"Insurance Agent",
            "type":"Services"
        }
    ],
    "sg:phone":"+1 814 371 6840",
    "sg:postcode":"15801",
    "sg:province":"PA",
    "wof:name":"State Farm Insurance",
    "wof:placetype":"venue"
},
  "geometry": {"coordinates":[-78.76121000000001,41.119116],"type":"Point"}
}