{
  "type": "Feature",
  "properties": {
    "iso:country":"US",
    "sg:address":"107 7th Ave",
    "sg:city":"West Mifflin",
    "sg:classifiers":[
        {
            "category":"Restaurant",
            "type":"Food & Drink"
        }
    ],
    "sg:phone":"+1 412 391 7336",
    "sg:postcode":"15122",
    "sg:province":"PA",
    "wof:name":"Cower Dining",
    "wof:placetype":"venue"
},
  "geometry": {"coordinates":[-79.88689599999999,40.386154],"type":"Point"}
}