{
  "type": "Feature",
  "properties": {
    "addr:full":"49 Analomink St East Stroudsburg PA 18301",
    "addr:housenumber":"49",
    "addr:postcode":"18301",
    "addr:street":"Analomink St",
    "iso:country":"US",
    "sg:address":"49 Analomink St",
    "sg:city":"East Stroudsburg",
    "sg:classifiers":[
        {
            "category":"Real Estate",
            "subcategory":"Real Estate Operator",
            "type":"Services"
        }
    ],
    "sg:phone":"+1 570 421 7767",
    "sg:postcode":"18301",
    "sg:province":"PA",
    "sg:tags":[
        "apartment"
    ],
    "wof:name":"Dove Island Assoc",
    "wof:placetype":"venue"
},
  "geometry": {"coordinates":[-75.18029199999999,40.999969],"type":"Point"}
}