{
  "type": "Feature",
  "properties": {
    "addr:full":"2954 Cumberland Rd Bedford PA 15522",
    "addr:housenumber":"2954",
    "addr:postcode":"15522",
    "addr:street":"Cumberland Rd",
    "iso:country":"US",
    "sg:address":"2954 Cumberland Rd",
    "sg:city":"Bedford",
    "sg:classifiers":[
        {
            "category":"Shopping",
            "subcategory":"Pharmacy",
            "type":"Retail Goods"
        }
    ],
    "sg:phone":"+1   ",
    "sg:postcode":"15522",
    "sg:province":"PA",
    "wof:name":"Bowsers Rexall Drugs",
    "wof:placetype":"venue"
},
  "geometry": {"coordinates":[-78.55186,39.976596],"type":"Point"}
}