{
  "type": "Feature",
  "properties": {
    "iso:country":"US",
    "sg:address":"221 E Broad St",
    "sg:city":"Hazleton",
    "sg:classifiers":[
        {
            "category":"Food & Beverages",
            "subcategory":"Bakery",
            "type":"Retail Goods"
        }
    ],
    "sg:phone":"+1 570 454 7753",
    "sg:postcode":"18202",
    "sg:province":"PA",
    "sg:tags":[
        "baker"
    ],
    "wof:name":"Janie Lou's Cake Shoppe",
    "wof:placetype":"venue"
},
  "geometry": {"coordinates":[-75.970859,40.95319],"type":"Point"}
}