{
  "type": "Feature",
  "properties": {
    "iso:country":"US",
    "sg:address":"121 N Franklin Ave",
    "sg:city":"Somerset",
    "sg:classifiers":[
        {
            "category":"Professional",
            "subcategory":"Lawyer & Legal Services",
            "type":"Services"
        }
    ],
    "sg:phone":"+1 814 445 4381",
    "sg:postcode":"15501",
    "sg:province":"PA",
    "sg:tags":[
        "attorney"
    ],
    "wof:name":"Robert W Critchfield",
    "wof:placetype":"venue"
},
  "geometry": {"coordinates":[-79.089055,40.009191],"type":"Point"}
}