{
  "type": "Feature",
  "properties": {
    "addr:full":"1240 Meridian Rd Renfrew PA 16053",
    "addr:housenumber":"1240",
    "addr:postcode":"16053",
    "addr:street":"Meridian Rd",
    "iso:country":"US",
    "sg:address":"1240 Meridian Rd",
    "sg:city":"Renfrew",
    "sg:classifiers":[
        {
            "category":"Farming",
            "subcategory":"Livestock Farm",
            "type":"Manufacturing & Wholesale Goods"
        }
    ],
    "sg:phone":"+1   ",
    "sg:postcode":"16053",
    "sg:province":"PA",
    "sg:tags":[
        "beef",
        "feedlot",
        "cattle"
    ],
    "wof:name":"Neil White",
    "wof:placetype":"venue"
},
  "geometry": {"coordinates":[-79.963646,40.779128],"type":"Point"}
}