{
  "type": "Feature",
  "properties": {
    "iso:country":"US",
    "sg:address":"2112 S 7th St",
    "sg:city":"Philadelphia",
    "sg:classifiers":[
        {
            "category":"Health Services",
            "subcategory":"Doctor",
            "type":"Services"
        }
    ],
    "sg:phone":"+1 215 467 7400",
    "sg:postcode":"19148",
    "sg:province":"PA",
    "wof:name":"Salvador Albert MD",
    "wof:placetype":"venue"
},
  "geometry": {"coordinates":[-75.158401,39.922401],"type":"Point"}
}