{
  "type": "Feature",
  "properties": {
    "iso:country":"US",
    "sg:address":"701 Market St",
    "sg:city":"Philadelphia",
    "sg:classifiers":[
        {
            "category":"Communications",
            "subcategory":"Newspaper",
            "type":"Services"
        }
    ],
    "sg:phone":"+1 215 238 0114",
    "sg:postcode":"19106",
    "sg:province":"PA",
    "sg:tags":[
        "magazine"
    ],
    "wof:name":"Su-Ni Headline News Inc",
    "wof:placetype":"venue"
},
  "geometry": {"coordinates":[-75.147301,39.9473],"type":"Point"}
}