{
  "type": "Feature",
  "properties": {
    "addr:full":"1 Belmont Ave Bala Cynwyd PA 19004",
    "addr:housenumber":"1",
    "addr:postcode":"19004",
    "addr:street":"Belmont Ave",
    "iso:country":"US",
    "sg:address":"1 Belmont Ave",
    "sg:city":"Bala Cynwyd",
    "sg:classifiers":[
        {
            "category":"Insurance",
            "subcategory":"Insurance Agent",
            "type":"Services"
        }
    ],
    "sg:phone":"+1 610 660 0200",
    "sg:postcode":"19004",
    "sg:province":"PA",
    "wof:name":"Nif Svc Of Mid-Atlantic Inc",
    "wof:placetype":"venue"
},
  "geometry": {"coordinates":[-75.221884,40.005618],"type":"Point"}
}