{
  "type": "Feature",
  "properties": {
    "iso:country":"US",
    "sg:address":"112 Oscar Way",
    "sg:city":"Uwchland",
    "sg:classifiers":[
        {
            "category":"Professional",
            "subcategory":"Business Services",
            "type":"Services"
        }
    ],
    "sg:phone":"+1 610 321 0900",
    "sg:postcode":"19425",
    "sg:province":"PA",
    "sg:tags":[
        "inventory"
    ],
    "wof:name":"Specialty Resources",
    "wof:placetype":"venue"
},
  "geometry": {"coordinates":[-75.676771,40.071883],"type":"Point"}
}