{
  "type": "Feature",
  "properties": {
    "iso:country":"US",
    "sg:address":"132 W State St",
    "sg:city":"Kennett Square",
    "sg:classifiers":[
        {
            "category":"Personal",
            "subcategory":"Beauty Salon",
            "type":"Services"
        }
    ],
    "sg:phone":"+1   ",
    "sg:postcode":"19348",
    "sg:province":"PA",
    "sg:tags":[
        "shop"
    ],
    "wof:name":"Cliffords Hair Fashions",
    "wof:placetype":"venue"
},
  "geometry": {"coordinates":[-75.71206100000001,39.846525],"type":"Point"}
}