{
  "type": "Feature",
  "properties": {
    "iso:country":"US",
    "sg:address":"602 W Dubois Ave",
    "sg:city":"Du Bois",
    "sg:classifiers":[
        {
            "category":"Personal",
            "subcategory":"Beauty Salon",
            "type":"Services"
        }
    ],
    "sg:phone":"+1 814 371 1600",
    "sg:postcode":"15801",
    "sg:province":"PA",
    "wof:name":"Hair & Skin Xpress",
    "wof:placetype":"venue"
},
  "geometry": {"coordinates":[-78.76702,41.130316],"type":"Point"}
}