{
  "type": "Feature",
  "properties": {
    "iso:country":"US",
    "sg:address":"81 S 8th St",
    "sg:city":"Philadelphia",
    "sg:classifiers":[
        {
            "category":"Wholesale",
            "subcategory":"Jewelry",
            "type":"Manufacturing & Wholesale Goods"
        }
    ],
    "sg:phone":"+1 215 592 4396",
    "sg:postcode":"19106",
    "sg:province":"PA",
    "sg:tags":[
        "buyer"
    ],
    "wof:name":"Simon Sherman Jewelry",
    "wof:placetype":"venue"
},
  "geometry": {"coordinates":[-75.153702,39.949902],"type":"Point"}
}