{
  "type": "Feature",
  "properties": {
    "iso:country":"US",
    "sg:address":"4903 Old William Penn Hwy",
    "sg:city":"Monroeville",
    "sg:classifiers":[
        {
            "category":"Home & Garden",
            "subcategory":"Furniture",
            "type":"Retail Goods"
        }
    ],
    "sg:phone":"+1   ",
    "sg:postcode":"15146",
    "sg:province":"PA",
    "wof:name":"Affordable Panels Intl",
    "wof:placetype":"venue"
},
  "geometry": {"coordinates":[-79.70824399999999,40.429904],"type":"Point"}
}