{
  "type": "Feature",
  "properties": {
    "iso:country":"US",
    "sg:address":"4903 Old William Penn Hwy",
    "sg:city":"Monroeville",
    "sg:classifiers":[
        {
            "category":"Shopping",
            "subcategory":"Used Merchandise",
            "type":"Retail Goods"
        }
    ],
    "sg:phone":"+1   ",
    "sg:postcode":"15146",
    "sg:province":"PA",
    "sg:tags":[
        "westinghouse",
        "knoll",
        "system",
        "equity"
    ],
    "wof:name":"A I Systems",
    "wof:placetype":"venue"
},
  "geometry": {"coordinates":[-79.70824399999999,40.429904],"type":"Point"}
}