{
  "type": "Feature",
  "properties": {
    "iso:country":"US",
    "sg:address":"86 W Saylor Ave",
    "sg:city":"Wilkes Barre",
    "sg:classifiers":[
        {
            "category":"Insurance",
            "subcategory":"Insurance Agent",
            "type":"Services"
        }
    ],
    "sg:phone":"+1   ",
    "sg:postcode":"18702",
    "sg:province":"PA",
    "wof:name":"Allabaugh Mary",
    "wof:placetype":"venue"
},
  "geometry": {"coordinates":[-75.832759,41.293398],"type":"Point"}
}