{
  "type": "Feature",
  "properties": {
    "iso:country":"US",
    "sg:address":"1 Deep Dale Dr E",
    "sg:city":"Levittown",
    "sg:classifiers":[
        {
            "category":"Real Estate",
            "subcategory":"Real Estate Agent",
            "type":"Services"
        }
    ],
    "sg:phone":"+1 215 949 0810",
    "sg:postcode":"19056",
    "sg:province":"PA",
    "sg:website":"http://www.robinkemmerer.com",
    "wof:name":"Robin Kemmerer Associates Inc",
    "wof:placetype":"venue"
},
  "geometry": {"coordinates":[-74.895287,40.158852],"type":"Point"}
}