{
  "type": "Feature",
  "properties": {
    "iso:country":"US",
    "sg:address":"2024 Frankella Ave",
    "sg:city":"Pittsburgh",
    "sg:classifiers":[
        {
            "category":"Professional",
            "type":"Services"
        }
    ],
    "sg:phone":"+1   ",
    "sg:postcode":"15221",
    "sg:province":"PA",
    "wof:name":"Kenya Yelverton",
    "wof:placetype":"venue"
},
  "geometry": {"coordinates":[-79.870429,40.451999],"type":"Point"}
}