{
  "type": "Feature",
  "properties": {
    "addr:full":"536 Shadeland Ave Drexel Hill PA 19026",
    "addr:housenumber":"536",
    "addr:postcode":"19026",
    "addr:street":"Shadeland Ave",
    "iso:country":"US",
    "sg:address":"536 Shadeland Ave",
    "sg:city":"Drexel Hill",
    "sg:classifiers":[
        {
            "category":"Organizations",
            "subcategory":"Membership Organization",
            "type":"Services"
        }
    ],
    "sg:phone":"+1   ",
    "sg:postcode":"19026",
    "sg:province":"PA",
    "wof:name":"Association For Rights Cthlcs",
    "wof:placetype":"venue"
},
  "geometry": {"coordinates":[-75.29521699999999,39.94988],"type":"Point"}
}