{
  "type": "Feature",
  "properties": {
    "iso:country":"US",
    "sg:address":"615 Franklin Ave",
    "sg:city":"Susquehanna",
    "sg:classifiers":[
        {
            "category":"Building & Trades",
            "subcategory":"Electrical",
            "type":"Services"
        }
    ],
    "sg:phone":"+1 570 853 4252",
    "sg:postcode":"18847",
    "sg:province":"PA",
    "sg:tags":[
        "electrical",
        "electric",
        "contractor"
    ],
    "wof:name":"Steve's Electric",
    "wof:placetype":"venue"
},
  "geometry": {"coordinates":[-75.599333,41.941946],"type":"Point"}
}