{
  "type": "Feature",
  "properties": {
    "iso:country":"US",
    "sg:address":"602 Market St",
    "sg:city":"Lykens",
    "sg:classifiers":[
        {
            "category":"Real Estate",
            "subcategory":"Real Estate Operator",
            "type":"Services"
        }
    ],
    "sg:phone":"+1   ",
    "sg:postcode":"17048",
    "sg:province":"PA",
    "sg:tags":[
        "building",
        "apartment"
    ],
    "wof:name":"Gary S Bopp",
    "wof:placetype":"venue"
},
  "geometry": {"coordinates":[-76.700616,40.565852],"type":"Point"}
}