{
  "type": "Feature",
  "properties": {
    "iso:country":"US",
    "sg:address":"817 Eaton Rd",
    "sg:city":"Drexel Hill",
    "sg:classifiers":[
        {
            "category":"Building & Trades",
            "subcategory":"Construction",
            "type":"Services"
        }
    ],
    "sg:phone":"+1   ",
    "sg:postcode":"19026",
    "sg:province":"PA",
    "sg:tags":[
        "contractor"
    ],
    "wof:name":"McAnulla Construction",
    "wof:placetype":"venue"
},
  "geometry": {"coordinates":[-75.29105300000001,39.959514],"type":"Point"}
}