{
  "type": "Feature",
  "properties": {
    "iso:country":"US",
    "sg:address":"1820 Municipal Dr",
    "sg:city":"Lancaster",
    "sg:classifiers":[
        {
            "category":"Local Transit",
            "type":"Transportation"
        }
    ],
    "sg:phone":"+1 717 569 6622",
    "sg:postcode":"17601",
    "sg:province":"PA",
    "sg:tags":[
        "passenger",
        "ambulance",
        "professional"
    ],
    "sg:website":"www.manheimtownshipems.org",
    "wof:name":"Manheim Twnship Ambulance Assn",
    "wof:placetype":"venue"
},
  "geometry": {"coordinates":[-76.298115,40.075331],"type":"Point"}
}