{
  "type": "Feature",
  "properties": {
    "iso:country":"US",
    "sg:address":"2839 Liberty Ave",
    "sg:city":"Pittsburgh",
    "sg:classifiers":[
        {
            "category":"Organizations",
            "subcategory":"Professional Association",
            "type":"Services"
        }
    ],
    "sg:phone":"+1   ",
    "sg:postcode":"15222",
    "sg:province":"PA",
    "wof:name":"B Bs B LP",
    "wof:placetype":"venue"
},
  "geometry": {"coordinates":[-79.974068,40.45695],"type":"Point"}
}