{
  "type": "Feature",
  "properties": {
    "addr:full":"1466 E Cheltenham Ave Philadelphia PA 19124",
    "addr:housenumber":"1466",
    "addr:postcode":"19124",
    "addr:street":"E Cheltenham Ave",
    "iso:country":"US",
    "sg:address":"1466 E Cheltenham Ave",
    "sg:city":"Philadelphia",
    "sg:classifiers":[
        {
            "category":"Coffee & Tea",
            "type":"Food & Drink"
        }
    ],
    "sg:phone":"+1 215 941 8807",
    "sg:postcode":"19124",
    "sg:province":"PA",
    "sg:website":"www.greatawakeningscafe.com",
    "wof:name":"Great Awakenings Cafe",
    "wof:placetype":"venue"
},
  "geometry": {"coordinates":[-75.081131,40.029433],"type":"Point"}
}