{
  "type": "Feature",
  "properties": {
    "iso:country":"US",
    "sg:address":"74 E Forrest Ave",
    "sg:city":"Shrewsbury",
    "sg:classifiers":[
        {
            "category":"Real Estate",
            "subcategory":"Real Estate Services",
            "type":"Services"
        },
        {
            "category":"Real Estate",
            "subcategory":"Real Estate Agent",
            "type":"Services"
        }
    ],
    "sg:phone":"+1 717 235 3197",
    "sg:postcode":"17361",
    "sg:province":"PA",
    "sg:tags":[
        "management"
    ],
    "wof:name":"Home Sales Company",
    "wof:placetype":"venue"
},
  "geometry": {"coordinates":[-76.67674,39.769285],"type":"Point"}
}