{
  "type": "Feature",
  "properties": {
    "iso:country":"US",
    "sg:address":"9043 Eureka Rd",
    "sg:city":"Girard",
    "sg:classifiers":[
        {
            "category":"Autos & Motor Vehicles",
            "subcategory":"Motorcycle Sales",
            "type":"Retail Goods"
        }
    ],
    "sg:phone":"+1   ",
    "sg:postcode":"16417",
    "sg:province":"PA",
    "sg:tags":[
        "body",
        "repair"
    ],
    "wof:name":"Mikes House of Horse Power",
    "wof:placetype":"venue"
},
  "geometry": {"coordinates":[-80.204072,41.981127],"type":"Point"}
}