{
  "type": "Feature",
  "properties": {
    "iso:country":"US",
    "sg:address":"5424 Woods Rd",
    "sg:city":"Stewartstown",
    "sg:classifiers":[
        {
            "category":"Retail",
            "subcategory":"Auto Repair",
            "type":"Services"
        }
    ],
    "sg:phone":"+1 717 993 6077",
    "sg:postcode":"17363",
    "sg:province":"PA",
    "sg:tags":[
        "repairing",
        "automobile"
    ],
    "wof:name":"H & M Svc Ctr",
    "wof:placetype":"venue"
},
  "geometry": {"coordinates":[-76.582483,39.801189],"type":"Point"}
}