{
  "type": "Feature",
  "properties": {
    "iso:country":"US",
    "sg:address":"2425 S Swanson St",
    "sg:city":"Philadelphia",
    "sg:classifiers":[
        {
            "category":"Travel",
            "subcategory":"Travel Agent",
            "type":"Entertainment"
        }
    ],
    "sg:phone":"+1   ",
    "sg:postcode":"19148",
    "sg:province":"PA",
    "sg:tags":[
        "operator",
        "tour"
    ],
    "wof:name":"Adventure Trails",
    "wof:placetype":"venue"
},
  "geometry": {"coordinates":[-75.14696499999999,39.916636],"type":"Point"}
}