{
  "type": "Feature",
  "properties": {
    "iso:country":"US",
    "sg:address":"3912 Washington Rd",
    "sg:city":"Mc Murray",
    "sg:classifiers":[
        {
            "category":"Real Estate",
            "subcategory":"Real Estate Agent",
            "type":"Services"
        }
    ],
    "sg:phone":"+1 724 941 8800",
    "sg:postcode":"15317",
    "sg:province":"PA",
    "wof:name":"Howard Hanna Co",
    "wof:placetype":"venue"
},
  "geometry": {"coordinates":[-80.12778299999999,40.271492],"type":"Point"}
}