{
  "type": "Feature",
  "properties": {
    "iso:country":"US",
    "sg:address":"475 W Ridge Pike",
    "sg:city":"Royersford",
    "sg:classifiers":[
        {
            "category":"Food & Beverages",
            "subcategory":"Specialty",
            "type":"Retail Goods"
        },
        {
            "category":"Restaurant",
            "type":"Food & Drink"
        }
    ],
    "sg:phone":"+1 610 495 6626",
    "sg:postcode":"19468",
    "sg:province":"PA",
    "sg:tags":[
        "gourmet",
        "shop"
    ],
    "wof:name":"Casual Gourmet",
    "wof:placetype":"venue"
},
  "geometry": {"coordinates":[-75.528958,40.23321],"type":"Point"}
}