{
  "type": "Feature",
  "properties": {
    "iso:country":"US",
    "sg:address":"14 Upper Trl",
    "sg:city":"Fairfield",
    "sg:classifiers":[
        {
            "category":"Building & Trades",
            "subcategory":"Construction",
            "type":"Services"
        }
    ],
    "sg:phone":"+1   ",
    "sg:postcode":"17320",
    "sg:province":"PA",
    "sg:tags":[
        "residential"
    ],
    "wof:name":"Dwayne E Mort",
    "wof:placetype":"venue"
},
  "geometry": {"coordinates":[-77.384032,39.727307],"type":"Point"}
}