{
  "type": "Feature",
  "properties": {
    "addr:full":"540 Luther Rd Harrisburg PA 17111",
    "addr:housenumber":"540",
    "addr:postcode":"17111",
    "addr:street":"Luther Rd",
    "iso:country":"US",
    "sg:address":"540 Luther Rd",
    "sg:city":"Harrisburg",
    "sg:classifiers":[
        {
            "category":"Food & Beverages",
            "subcategory":"Fruits & Vegetables",
            "type":"Retail Goods"
        }
    ],
    "sg:phone":"+1   ",
    "sg:postcode":"17111",
    "sg:province":"PA",
    "sg:tags":[
        "farm",
        "produce",
        "market",
        "supply"
    ],
    "wof:name":"Rissers Farm Market",
    "wof:placetype":"venue"
},
  "geometry": {"coordinates":[-76.82398999999999,40.264956],"type":"Point"}
}