{
  "type": "Feature",
  "properties": {
    "iso:country":"US",
    "sg:address":"3950 William Penn Hwy",
    "sg:city":"Murrysville",
    "sg:classifiers":[
        {
            "category":"Health Services",
            "subcategory":"Doctor",
            "type":"Services"
        }
    ],
    "sg:phone":"+1 724 325 4190",
    "sg:postcode":"15668",
    "sg:province":"PA",
    "sg:tags":[
        "physician",
        "surgeon"
    ],
    "wof:name":"Stepanek Suzana Md",
    "wof:placetype":"venue"
},
  "geometry": {"coordinates":[-79.69512899999999,40.427361],"type":"Point"}
}