{
  "type": "Feature",
  "properties": {
    "iso:country":"US",
    "sg:address":"401 McKinley Ave",
    "sg:city":"Morrisville",
    "sg:classifiers":[
        {
            "category":"Building & Trades",
            "subcategory":"Construction",
            "type":"Services"
        }
    ],
    "sg:phone":"+1 215 428 2211",
    "sg:postcode":"19067",
    "sg:province":"PA",
    "sg:tags":[
        "excavation",
        "contractor"
    ],
    "wof:name":"Premium Excavating",
    "wof:placetype":"venue"
},
  "geometry": {"coordinates":[-74.77999,40.203227],"type":"Point"}
}