{
  "type": "Feature",
  "properties": {
    "iso:country":"US",
    "sg:address":"16 Dixon Blvd",
    "sg:city":"Uniontown",
    "sg:classifiers":[
        {
            "category":"Restaurant",
            "type":"Food & Drink"
        }
    ],
    "sg:phone":"+1 724 438 2744",
    "sg:postcode":"15401",
    "sg:province":"PA",
    "wof:name":"Caddyshack",
    "wof:placetype":"venue"
},
  "geometry": {"coordinates":[-79.742987,39.894876],"type":"Point"}
}