{
  "type": "Feature",
  "properties": {
    "iso:country":"US",
    "sg:address":"175 Sunrise Ln",
    "sg:city":"Pottstown",
    "sg:classifiers":[
        {
            "category":"Building & Trades",
            "subcategory":"Construction",
            "type":"Services"
        }
    ],
    "sg:phone":"+1   ",
    "sg:postcode":"19464",
    "sg:province":"PA",
    "sg:tags":[
        "contractor"
    ],
    "wof:name":"Wjs Home Improvement",
    "wof:placetype":"venue"
},
  "geometry": {"coordinates":[-75.60773,40.261766],"type":"Point"}
}