{
  "type": "Feature",
  "properties": {
    "iso:country":"US",
    "sg:address":"124 Springwood Dr",
    "sg:city":"Southampton",
    "sg:classifiers":[
        {
            "category":"Professional",
            "type":"Services"
        }
    ],
    "sg:phone":"+1   ",
    "sg:postcode":"18966",
    "sg:province":"PA",
    "wof:name":"Robin Pollack",
    "wof:placetype":"venue"
},
  "geometry": {"coordinates":[-75.061932,40.176149],"type":"Point"}
}