{
  "type": "Feature",
  "properties": {
    "addr:full":"173 W Main St Kutztown PA 19530",
    "addr:housenumber":"173",
    "addr:postcode":"19530",
    "addr:street":"W Main St",
    "iso:country":"US",
    "sg:address":"173 W Main St",
    "sg:city":"Kutztown",
    "sg:classifiers":[
        {
            "category":"Museum",
            "type":"Entertainment"
        }
    ],
    "sg:phone":"+1 610 683 6440",
    "sg:postcode":"19530",
    "sg:province":"PA",
    "sg:tags":[
        "organization",
        "arts",
        "information"
    ],
    "wof:name":"New Arts Program",
    "wof:placetype":"venue"
},
  "geometry": {"coordinates":[-75.777018,40.517758],"type":"Point"}
}