{
  "type": "Feature",
  "properties": {
    "addr:full":"1096 W Bainbridge St Elizabethtown PA 17022",
    "addr:housenumber":"1096",
    "addr:postcode":"17022",
    "addr:street":"W Bainbridge St",
    "iso:country":"US",
    "sg:address":"1096 W Bainbridge St",
    "sg:city":"Elizabethtown",
    "sg:classifiers":[
        {
            "category":"Retail",
            "subcategory":"Veterinary Services",
            "type":"Services"
        }
    ],
    "sg:phone":"+1 717 367 7156",
    "sg:postcode":"17022",
    "sg:province":"PA",
    "sg:tags":[
        "hospital",
        "animal"
    ],
    "wof:name":"Elizabethtown Area Animal Hosp",
    "wof:placetype":"venue"
},
  "geometry": {"coordinates":[-76.61545599999999,40.135611],"type":"Point"}
}