{
  "type": "Feature",
  "properties": {
    "iso:country":"US",
    "sg:address":"127 Northampton St",
    "sg:city":"Easton",
    "sg:classifiers":[
        {
            "category":"Professional",
            "type":"Services"
        }
    ],
    "sg:phone":"+1   ",
    "sg:postcode":"18042",
    "sg:province":"PA",
    "wof:name":"Lehigh Valley Sewing Center",
    "wof:placetype":"venue"
},
  "geometry": {"coordinates":[-75.205546,40.691469],"type":"Point"}
}