{
  "type": "Feature",
  "properties": {
    "iso:country":"US",
    "sg:address":"211 N Whitfield St",
    "sg:city":"Pittsburgh",
    "sg:classifiers":[
        {
            "category":"Health Services",
            "subcategory":"Hospital",
            "type":"Services"
        }
    ],
    "sg:phone":"+1 412 363 9464",
    "sg:postcode":"15206",
    "sg:province":"PA",
    "sg:tags":[
        "medicine",
        "physician",
        "addiction",
        "surgeons",
        "specialty"
    ],
    "wof:name":"Nelum Inc",
    "wof:placetype":"venue"
},
  "geometry": {"coordinates":[-79.92488899999999,40.463182],"type":"Point"}
}