{
  "type": "Feature",
  "properties": {
    "iso:country":"US",
    "sg:address":"141 W Beau St",
    "sg:city":"Washington",
    "sg:classifiers":[
        {
            "category":"Autos & Motor Vehicles",
            "subcategory":"Auto Supplies",
            "type":"Retail Goods"
        }
    ],
    "sg:phone":"+1 724 228 3500",
    "sg:postcode":"15301",
    "sg:province":"PA",
    "sg:tags":[
        "automobile",
        "part"
    ],
    "sg:website":"http://ad.doubleclick.net/clk;221862232;45455595;j?http://www.carquest.com/carquest/store_locator.html",
    "wof:name":"CARQUEST Auto Parts",
    "wof:placetype":"venue"
},
  "geometry": {"coordinates":[-80.249741,40.170198],"type":"Point"}
}