{
  "type": "Feature",
  "properties": {
    "iso:country":"US",
    "sg:address":"3382 Goshen Rd",
    "sg:city":"Newtown Square",
    "sg:classifiers":[
        {
            "category":"Health Services",
            "subcategory":"Doctor",
            "type":"Services"
        }
    ],
    "sg:phone":"+1 610 356 0666",
    "sg:postcode":"19073",
    "sg:province":"PA",
    "sg:tags":[
        "medical"
    ],
    "wof:name":"Diane House MD",
    "wof:placetype":"venue"
},
  "geometry": {"coordinates":[-75.393101,39.998239],"type":"Point"}
}