{
  "type": "Feature",
  "properties": {
    "iso:country":"US",
    "sg:address":"3819 Groveland Ave",
    "sg:city":"Levittown",
    "sg:classifiers":[
        {
            "category":"Building & Trades",
            "subcategory":"Electrical",
            "type":"Services"
        }
    ],
    "sg:phone":"+1 267 994 2228",
    "sg:postcode":"19056",
    "sg:province":"PA",
    "sg:tags":[
        "electrician"
    ],
    "sg:website":"www.electrican.org",
    "wof:name":"Acquired Connection Electrical",
    "wof:placetype":"venue"
},
  "geometry": {"coordinates":[-74.893951,40.122842],"type":"Point"}
}