{
  "type": "Feature",
  "properties": {
    "iso:country":"US",
    "sg:address":"175 Lakemont Park Blvd",
    "sg:city":"Altoona",
    "sg:classifiers":[
        {
            "category":"Professional",
            "subcategory":"Lawyer & Legal Services",
            "type":"Services"
        }
    ],
    "sg:phone":"+1 814 941 2544",
    "sg:postcode":"16602",
    "sg:province":"PA",
    "sg:tags":[
        "attorney",
        "business",
        "corporation",
        "partnership",
        "planning",
        "real estate",
        "law"
    ],
    "wof:name":"Eberhardt, John E",
    "wof:placetype":"venue"
},
  "geometry": {"coordinates":[-78.3953,40.470767],"type":"Point"}
}