{
  "type": "Feature",
  "properties": {
    "iso:country":"US",
    "sg:address":"61 E State St",
    "sg:city":"Doylestown",
    "sg:classifiers":[
        {
            "category":"Personal",
            "subcategory":"Beauty Salon",
            "type":"Services"
        }
    ],
    "sg:phone":"+1 215 345 7385",
    "sg:postcode":"18901",
    "sg:province":"PA",
    "sg:tags":[
        "nail",
        "shop"
    ],
    "wof:name":"L A D & Co Hairdressing of Distinction",
    "wof:placetype":"venue"
},
  "geometry": {"coordinates":[-75.129501,40.3106],"type":"Point"}
}