{
  "type": "Feature",
  "properties": {
    "iso:country":"US",
    "sg:address":"2879 Oakland Ave",
    "sg:city":"Indiana",
    "sg:classifiers":[
        {
            "category":"Manufacturing",
            "subcategory":"Tools & Machinery",
            "type":"Manufacturing & Wholesale Goods"
        }
    ],
    "sg:phone":"+1 724 349 6300",
    "sg:postcode":"15701",
    "sg:province":"PA",
    "sg:tags":[
        "e",
        "concrete",
        "mixer",
        "equipment",
        "mfr",
        "construction",
        "hydraulic"
    ],
    "sg:website":"www.elkinhitech.com",
    "wof:name":"Elkin Manufacturing Inc",
    "wof:placetype":"venue"
},
  "geometry": {"coordinates":[-79.18847,40.60232],"type":"Point"}
}