{
  "type": "Feature",
  "properties": {
    "iso:country":"US",
    "sg:address":"2510 Clyde Ave",
    "sg:city":"State College",
    "sg:classifiers":[
        {
            "category":"Wholesale",
            "subcategory":"Hardware",
            "type":"Manufacturing & Wholesale Goods"
        }
    ],
    "sg:phone":"+1   ",
    "sg:postcode":"16801",
    "sg:province":"PA",
    "sg:tags":[
        "air",
        "heating",
        "refrigeration",
        "conditioning",
        "supply"
    ],
    "wof:name":"Keystone Rfrgn & Htg Sup",
    "wof:placetype":"venue"
},
  "geometry": {"coordinates":[-77.80412800000001,40.827504],"type":"Point"}
}