{
  "type": "Feature",
  "properties": {
    "iso:country":"US",
    "sg:address":"4358 E Brightview Dr",
    "sg:city":"Pittsburgh",
    "sg:classifiers":[
        {
            "category":"Wholesale",
            "subcategory":"Durable Goods & Equipment",
            "type":"Manufacturing & Wholesale Goods"
        }
    ],
    "sg:phone":"+1   ",
    "sg:postcode":"15227",
    "sg:province":"PA",
    "wof:name":"National Suppliers Company",
    "wof:placetype":"venue"
},
  "geometry": {"coordinates":[-79.987984,40.367788],"type":"Point"}
}