{
  "type": "Feature",
  "properties": {
    "iso:country":"US",
    "sg:address":"168 Allegheny Center Mall",
    "sg:city":"Pittsburgh",
    "sg:classifiers":[
        {
            "category":"Restaurant",
            "type":"Food & Drink"
        }
    ],
    "sg:phone":"+1 412 231 8551",
    "sg:postcode":"15212",
    "sg:province":"PA",
    "wof:name":"Bolo's",
    "wof:placetype":"venue"
},
  "geometry": {"coordinates":[-80.00386,40.451548],"type":"Point"}
}