{
  "type": "Feature",
  "properties": {
    "iso:country":"US",
    "sg:address":"1342 E Derry Rd",
    "sg:city":"Hershey",
    "sg:classifiers":[
        {
            "category":"Professional",
            "type":"Services"
        }
    ],
    "sg:phone":"+1 717 533 6897",
    "sg:postcode":"17033",
    "sg:province":"PA",
    "sg:tags":[
        "caterer"
    ],
    "wof:name":"Serving Spoon the",
    "wof:placetype":"venue"
},
  "geometry": {"coordinates":[-76.620736,40.299223],"type":"Point"}
}