{
  "type": "Feature",
  "properties": {
    "iso:country":"US",
    "sg:address":"2321 W Allen St",
    "sg:city":"Allentown",
    "sg:classifiers":[
        {
            "category":"Manufacturing",
            "subcategory":"Buildings",
            "type":"Manufacturing & Wholesale Goods"
        },
        {
            "category":"Building & Trades",
            "subcategory":"Construction",
            "type":"Services"
        }
    ],
    "sg:phone":"+1 610 417 4582",
    "sg:postcode":"18104",
    "sg:province":"PA",
    "sg:tags":[
        "home",
        "builder",
        "contractor"
    ],
    "wof:name":"Home Solutions Of Lehigh Valley",
    "wof:placetype":"venue"
},
  "geometry": {"coordinates":[-75.50970700000001,40.601116],"type":"Point"}
}