{
  "type": "Feature",
  "properties": {
    "addr:full":"11 Church St Seven Valleys PA 17360",
    "addr:housenumber":"11",
    "addr:postcode":"17360",
    "addr:street":"Church St",
    "iso:country":"US",
    "sg:address":"11 Church St",
    "sg:city":"Seven Valleys",
    "sg:classifiers":[
        {
            "category":"Food & Beverages",
            "subcategory":"Groceries & Convenience Stores",
            "type":"Retail Goods"
        }
    ],
    "sg:phone":"+1   ",
    "sg:postcode":"17360",
    "sg:province":"PA",
    "wof:name":"Smyser Station Grocery",
    "wof:placetype":"venue"
},
  "geometry": {"coordinates":[-76.769408,39.855042],"type":"Point"}
}