{
  "type": "Feature",
  "properties": {
    "addr:full":"2453 W Pike St Houston PA 15342",
    "addr:housenumber":"2453",
    "addr:postcode":"15342",
    "addr:street":"W Pike St",
    "iso:country":"US",
    "sg:address":"2453 W Pike St",
    "sg:city":"Houston",
    "sg:classifiers":[
        {
            "category":"Communications",
            "subcategory":"Television Station",
            "type":"Services"
        }
    ],
    "sg:phone":"+1   ",
    "sg:postcode":"15342",
    "sg:province":"PA",
    "wof:name":"CBS",
    "wof:placetype":"venue"
},
  "geometry": {"coordinates":[-80.218076,40.223701],"type":"Point"}
}