{
  "type": "Feature",
  "properties": {
    "addr:full":"108 N 5th St Allentown PA 18102",
    "addr:housenumber":"108",
    "addr:postcode":"18102",
    "addr:street":"N 5Th St",
    "iso:country":"US",
    "sg:address":"108 N 5th St",
    "sg:city":"Allentown",
    "sg:classifiers":[
        {
            "category":"Place Of Worship",
            "subcategory":"Church",
            "type":"Public Place"
        },
        {
            "category":"Place Of Worship",
            "type":"Public Place"
        },
        {
            "category":"Education",
            "subcategory":"School",
            "type":"Public Place"
        }
    ],
    "sg:phone":"+1 610 435 0782",
    "sg:postcode":"18102",
    "sg:province":"PA",
    "sg:tags":[
        "churches-episcopal-anglican",
        "churches-episcopal"
    ],
    "sg:website":"www.graceallentown.org",
    "wof:name":"Grace Episcopal Church",
    "wof:placetype":"venue"
},
  "geometry": {"coordinates":[-75.468498,40.6049],"type":"Point"}
}