{
  "type": "Feature",
  "properties": {
    "iso:country":"US",
    "sg:address":"126 Onix Dr",
    "sg:city":"Kennett Square",
    "sg:classifiers":[
        {
            "category":"Personal",
            "subcategory":"Day Spa",
            "type":"Services"
        }
    ],
    "sg:phone":"+1 484 732 8134",
    "sg:postcode":"19348",
    "sg:province":"PA",
    "sg:website":"www.handandstone.com",
    "wof:name":"Hand and Stone Massage",
    "wof:placetype":"venue"
},
  "geometry": {"coordinates":[-75.686435,39.86199],"type":"Point"}
}