{
  "type": "Feature",
  "properties": {
    "addr:full":"312 Mill St Danville PA 17821",
    "addr:housenumber":"312",
    "addr:postcode":"17821",
    "addr:street":"Mill St",
    "iso:country":"US",
    "sg:address":"312 Mill St",
    "sg:city":"Danville",
    "sg:classifiers":[
        {
            "category":"Restaurant",
            "type":"Food & Drink"
        }
    ],
    "sg:phone":"+1 570 275 2941",
    "sg:postcode":"17821",
    "sg:province":"PA",
    "sg:tags":[
        "eating"
    ],
    "wof:name":"Pappas Restaurant",
    "wof:placetype":"venue"
},
  "geometry": {"coordinates":[-76.616698,40.963285],"type":"Point"}
}