{
  "type": "Feature",
  "properties": {
    "iso:country":"US",
    "sg:address":"127 S 4th St",
    "sg:city":"Mc Connellsburg",
    "sg:classifiers":[
        {
            "category":"Retail",
            "subcategory":"Auto Repair",
            "type":"Services"
        }
    ],
    "sg:phone":"+1   ",
    "sg:postcode":"17233",
    "sg:province":"PA",
    "sg:tags":[
        "automotive"
    ],
    "wof:name":"Houcks Radiator & Glass Shop",
    "wof:placetype":"venue"
},
  "geometry": {"coordinates":[-77.99560200000001,39.93013],"type":"Point"}
}