{
  "type": "Feature",
  "properties": {
    "iso:country":"US",
    "sg:address":"82 Spring Rd",
    "sg:city":"Tower City",
    "sg:classifiers":[
        {
            "category":"Wholesale",
            "subcategory":"Construction Materials",
            "type":"Manufacturing & Wholesale Goods"
        }
    ],
    "sg:phone":"+1 717 647 2792",
    "sg:postcode":"17980",
    "sg:province":"PA",
    "sg:tags":[
        "fence"
    ],
    "wof:name":"S & S Trimming",
    "wof:placetype":"venue"
},
  "geometry": {"coordinates":[-76.521878,40.577763],"type":"Point"}
}