{
  "type": "Feature",
  "properties": {
    "iso:country":"US",
    "sg:address":"123 Ridgefield Rd",
    "sg:city":"Newtown Square",
    "sg:classifiers":[
        {
            "category":"Professional",
            "type":"Services"
        }
    ],
    "sg:phone":"+1   ",
    "sg:postcode":"19073",
    "sg:province":"PA",
    "wof:name":"Diane A Smith Rn Msn",
    "wof:placetype":"venue"
},
  "geometry": {"coordinates":[-75.39189399999999,39.987921],"type":"Point"}
}