{
  "type": "Feature",
  "properties": {
    "iso:country":"US",
    "sg:address":"4235 Union Deposit Rd",
    "sg:city":"Harrisburg",
    "sg:classifiers":[
        {
            "category":"Shopping",
            "subcategory":"Bicycles & Sporting Goods",
            "type":"Retail Goods"
        }
    ],
    "sg:phone":"+1 717 564 8620",
    "sg:postcode":"17111",
    "sg:province":"PA",
    "sg:tags":[
        "equipment",
        "skateboard"
    ],
    "wof:name":"Funtastik",
    "wof:placetype":"venue"
},
  "geometry": {"coordinates":[-76.815163,40.278994],"type":"Point"}
}