{
  "type": "Feature",
  "properties": {
    "iso:country":"US",
    "sg:address":"PO Box 17",
    "sg:city":"Lemoyne",
    "sg:classifiers":[
        {
            "category":"Taxi",
            "type":"Transportation"
        }
    ],
    "sg:phone":"+1 717 238 7252",
    "sg:postcode":"17043",
    "sg:province":"PA",
    "wof:name":"Yellow Cab Co Baggage Co",
    "wof:placetype":"venue"
},
  "geometry": {"coordinates":[-76.89969600000001,40.244598],"type":"Point"}
}