{
  "type": "Feature",
  "properties": {
    "iso:country":"US",
    "sg:address":"371 Carerra Dr",
    "sg:city":"Lancaster",
    "sg:classifiers":[
        {
            "category":"Recreation",
            "type":"Entertainment"
        }
    ],
    "sg:phone":"+1 717 684 0630",
    "sg:postcode":"17601",
    "sg:province":"PA",
    "sg:tags":[
        "skating",
        "instruction"
    ],
    "wof:name":"Red Rose Figure Skating Club",
    "wof:placetype":"venue"
},
  "geometry": {"coordinates":[-76.32959099999999,40.074832],"type":"Point"}
}