{
  "type": "Feature",
  "properties": {
    "addr:full":"3400 N Broad St Philadelphia PA 19140",
    "addr:housenumber":"3400",
    "addr:postcode":"19140",
    "addr:street":"N Broad St",
    "iso:country":"US",
    "sg:address":"3400 N Broad St",
    "sg:city":"Philadelphia",
    "sg:classifiers":[
        {
            "category":"Health Services",
            "subcategory":"Doctor",
            "type":"Services"
        }
    ],
    "sg:phone":"+1   ",
    "sg:postcode":"19140",
    "sg:province":"PA",
    "sg:tags":[
        "medical",
        "unit"
    ],
    "wof:name":"Thrombosis Research Center",
    "wof:placetype":"venue"
},
  "geometry": {"coordinates":[-75.15191900000001,40.006167],"type":"Point"}
}