{
  "type": "Feature",
  "properties": {
    "iso:country":"US",
    "sg:address":"213 Market St",
    "sg:city":"Harrisburg",
    "sg:classifiers":[
        {
            "category":"Professional",
            "subcategory":"Lawyer & Legal Services",
            "type":"Services"
        }
    ],
    "sg:phone":"+1 717 237 4801",
    "sg:postcode":"17101",
    "sg:province":"PA",
    "wof:name":"Beren Daniel E Attorney",
    "wof:placetype":"venue"
},
  "geometry": {"coordinates":[-76.8815,40.260101],"type":"Point"}
}