{
  "type": "Feature",
  "properties": {
    "addr:full":"111 S Fraser St State College PA 16801",
    "addr:housenumber":"111",
    "addr:postcode":"16801",
    "addr:street":"S Fraser St",
    "iso:country":"US",
    "sg:address":"111 S Fraser St",
    "sg:city":"State College",
    "sg:classifiers":[
        {
            "category":"Shopping",
            "subcategory":"Gifts & Souvenirs",
            "type":"Retail Goods"
        }
    ],
    "sg:phone":"+1 814 234 1328",
    "sg:postcode":"16801",
    "sg:province":"PA",
    "sg:tags":[
        "shop"
    ],
    "wof:name":"Nittany Quill",
    "wof:placetype":"venue"
},
  "geometry": {"coordinates":[-77.86239399999999,40.793416],"type":"Point"}
}