{
  "type": "Feature",
  "properties": {
    "iso:country":"US",
    "sg:address":"801 Bristol Pike",
    "sg:city":"Croydon",
    "sg:classifiers":[
        {
            "category":"Autos & Motor Vehicles",
            "subcategory":"Automobile Sales",
            "type":"Retail Goods"
        }
    ],
    "sg:phone":"+1 215 781 1818",
    "sg:postcode":"19021",
    "sg:province":"PA",
    "sg:tags":[
        "car"
    ],
    "sg:website":"www.hasslefreeautoloan.com",
    "wof:name":"B & B Automotive Buy Here Pay Here",
    "wof:placetype":"venue"
},
  "geometry": {"coordinates":[-74.90641100000001,40.094077],"type":"Point"}
}