{
  "type": "Feature",
  "properties": {
    "addr:full":"30 S Hanover St Carlisle PA 17013",
    "addr:housenumber":"30",
    "addr:postcode":"17013",
    "addr:street":"S Hanover St",
    "iso:country":"US",
    "sg:address":"30 S Hanover St",
    "sg:city":"Carlisle",
    "sg:classifiers":[
        {
            "category":"Professional",
            "subcategory":"Accounting & Tax Preparation",
            "type":"Services"
        }
    ],
    "sg:phone":"+1 717 243 6868",
    "sg:postcode":"17013",
    "sg:province":"PA",
    "sg:tags":[
        "school",
        "return",
        "specialty"
    ],
    "sg:website":"www.hrblock.com",
    "wof:name":"H & R Block",
    "wof:placetype":"venue"
},
  "geometry": {"coordinates":[-77.18940000000001,40.200199],"type":"Point"}
}