{
  "type": "Feature",
  "properties": {
    "iso:country":"US",
    "sg:address":"400 Penn Center Blvd",
    "sg:city":"Pittsburgh",
    "sg:classifiers":[
        {
            "category":"Health Services",
            "subcategory":"Health Practitioner",
            "type":"Services"
        }
    ],
    "sg:phone":"+1 412 829 1844",
    "sg:postcode":"15235",
    "sg:province":"PA",
    "sg:tags":[
        "psychotherapist"
    ],
    "wof:name":"Theresa C Mason",
    "wof:placetype":"venue"
},
  "geometry": {"coordinates":[-79.811809,40.427314],"type":"Point"}
}