{
  "type": "Feature",
  "properties": {
    "addr:full":"4309 Linglestown Rd Harrisburg PA 17112",
    "addr:housenumber":"4309",
    "addr:postcode":"17112",
    "addr:street":"Linglestown Rd",
    "iso:country":"US",
    "sg:address":"4309 Linglestown Rd",
    "sg:city":"Harrisburg",
    "sg:classifiers":[
        {
            "category":"Shopping",
            "subcategory":"Bicycles & Sporting Goods",
            "type":"Retail Goods"
        }
    ],
    "sg:phone":"+1 717 651 9510",
    "sg:postcode":"17112",
    "sg:province":"PA",
    "sg:tags":[
        "equipment",
        "exercise"
    ],
    "sg:website":"www.preventionservicesinc.com",
    "wof:name":"Occupational Athletics Inc",
    "wof:placetype":"venue"
},
  "geometry": {"coordinates":[-76.824474,40.336102],"type":"Point"}
}