{
  "type": "Feature",
  "properties": {
    "addr:full":"2304 E Huntingdon St Philadelphia PA 19125",
    "addr:housenumber":"2304",
    "addr:postcode":"19125",
    "addr:street":"E Huntingdon St",
    "iso:country":"US",
    "sg:address":"2304 E Huntingdon St",
    "sg:city":"Philadelphia",
    "sg:classifiers":[
        {
            "category":"Food & Beverages",
            "subcategory":"Groceries & Convenience Stores",
            "type":"Retail Goods"
        },
        {
            "category":"Restaurant",
            "type":"Food & Drink"
        }
    ],
    "sg:phone":"+1 215 426 1618",
    "sg:postcode":"19125",
    "sg:province":"PA",
    "sg:tags":[
        "delicatessen"
    ],
    "wof:name":"Huntingdon Deli",
    "wof:placetype":"venue"
},
  "geometry": {"coordinates":[-75.121116,39.981624],"type":"Point"}
}