{
  "type": "Feature",
  "properties": {
    "addr:full":"1446 Logan Rd Glen Campbell PA 15742",
    "addr:housenumber":"1446",
    "addr:postcode":"15742",
    "addr:street":"Logan Rd",
    "iso:country":"US",
    "sg:address":"1446 Logan Rd",
    "sg:city":"Glen Campbell",
    "sg:classifiers":[
        {
            "category":"Shopping",
            "subcategory":"Gifts & Souvenirs",
            "type":"Retail Goods"
        }
    ],
    "sg:phone":"+1   ",
    "sg:postcode":"15742",
    "sg:province":"PA",
    "wof:name":"Chiplis Jeans and Ceramics",
    "wof:placetype":"venue"
},
  "geometry": {"coordinates":[-78.874208,40.823852],"type":"Point"}
}