{
  "type": "Feature",
  "properties": {
    "addr:full":"170 N Independence Mall E Philadelphia PA 19106",
    "addr:housenumber":"170;e",
    "addr:postcode":"19106",
    "addr:street":"N Independence Mall",
    "iso:country":"US",
    "sg:address":"170 N Independence Mall E",
    "sg:city":"Philadelphia",
    "sg:classifiers":[
        {
            "category":"Professional",
            "subcategory":"Lawyer & Legal Services",
            "type":"Services"
        }
    ],
    "sg:phone":"+1   ",
    "sg:postcode":"19106",
    "sg:province":"PA",
    "wof:name":"Margolis Richard J",
    "wof:placetype":"venue"
},
  "geometry": {"coordinates":[-75.14873799999999,39.951453],"type":"Point"}
}