{
  "type": "Feature",
  "properties": {
    "iso:country":"US",
    "sg:address":"3107 Liberty Way",
    "sg:city":"Dickerson Run",
    "sg:classifiers":[
        {
            "category":"Banks & Credit Unions",
            "subcategory":"Bank",
            "type":"Services"
        }
    ],
    "sg:phone":"+1 412 664 8707",
    "sg:postcode":"15430",
    "sg:province":"PA",
    "wof:name":"Three Rivers Bank",
    "wof:placetype":"venue"
},
  "geometry": {"coordinates":[-79.660698,40.0425],"type":"Point"}
}