{
  "type": "Feature",
  "properties": {
    "addr:full":"731 W Dekalb Pike King Of Prussia PA 19406",
    "addr:housenumber":"731",
    "addr:postcode":"19406",
    "addr:street":"W Dekalb Pike",
    "iso:country":"US",
    "sg:address":"731 W Dekalb Pike",
    "sg:city":"King Of Prussia",
    "sg:classifiers":[
        {
            "category":"Wholesale",
            "subcategory":"Electrical",
            "type":"Manufacturing & Wholesale Goods"
        }
    ],
    "sg:phone":"+1   ",
    "sg:postcode":"19406",
    "sg:province":"PA",
    "sg:tags":[
        "electronic"
    ],
    "wof:name":"Quintex Cellular",
    "wof:placetype":"venue"
},
  "geometry": {"coordinates":[-75.38418799999999,40.087345],"type":"Point"}
}