{
  "type": "Feature",
  "properties": {
    "iso:country":"US",
    "sg:address":"41 Runway Rd",
    "sg:city":"Levittown",
    "sg:classifiers":[
        {
            "category":"Freight",
            "type":"Transportation"
        }
    ],
    "sg:phone":"+1 215 547 6440",
    "sg:postcode":"19057",
    "sg:province":"PA",
    "sg:tags":[
        "warehouse",
        "self",
        "storage",
        "warehousing"
    ],
    "sg:website":"www.jacobsonco.com",
    "wof:name":"Jacobson Warehouse Company Inc",
    "wof:placetype":"venue"
},
  "geometry": {"coordinates":[-74.84718599999999,40.124758],"type":"Point"}
}