{
  "type": "Feature",
  "properties": {
    "addr:full":"1636 E Market St York PA 17403",
    "addr:housenumber":"1636",
    "addr:postcode":"17403",
    "addr:street":"E Market St",
    "iso:country":"US",
    "sg:address":"1636 E Market St",
    "sg:city":"York",
    "sg:classifiers":[
        {
            "category":"Building & Trades",
            "subcategory":"Construction",
            "type":"Services"
        }
    ],
    "sg:phone":"+1 717 846 1455",
    "sg:postcode":"17403",
    "sg:province":"PA",
    "sg:tags":[
        "general",
        "contractor"
    ],
    "wof:name":"Pro Builders By Grignano",
    "wof:placetype":"venue"
},
  "geometry": {"coordinates":[-76.69589000000001,39.972712],"type":"Point"}
}