{
  "type": "Feature",
  "properties": {
    "iso:country":"US",
    "sg:address":"212 E Locust St",
    "sg:city":"Clearfield",
    "sg:classifiers":[
        {
            "category":"Autos & Motor Vehicles",
            "subcategory":"Auto Supplies",
            "type":"Retail Goods"
        },
        {
            "category":"Wholesale",
            "subcategory":"Auto Parts",
            "type":"Manufacturing & Wholesale Goods"
        }
    ],
    "sg:phone":"+1 814 765 9692",
    "sg:postcode":"16830",
    "sg:province":"PA",
    "sg:tags":[
        "automobile"
    ],
    "wof:name":"Baker Auto Parts Inc",
    "wof:placetype":"venue"
},
  "geometry": {"coordinates":[-78.437873,41.023322],"type":"Point"}
}