{
  "type": "Feature",
  "properties": {
    "iso:country":"US",
    "sg:address":"2960 Skippack Pike",
    "sg:city":"Lansdale",
    "sg:classifiers":[
        {
            "category":"Restaurant",
            "type":"Food & Drink"
        }
    ],
    "sg:phone":"+1 610 584 6958",
    "sg:postcode":"19446",
    "sg:province":"PA",
    "sg:tags":[
        "fusion",
        "asian"
    ],
    "sg:website":"www.fuzionrestaurant.com",
    "wof:name":"Fuzion",
    "wof:placetype":"venue"
},
  "geometry": {"coordinates":[-75.340103,40.197201],"type":"Point"}
}