{
  "type": "Feature",
  "properties": {
    "addr:full":"76 Central Ave Johnstown PA 15902",
    "addr:housenumber":"76",
    "addr:postcode":"15902",
    "addr:street":"Central Ave",
    "iso:country":"US",
    "sg:address":"76 Central Ave",
    "sg:city":"Johnstown",
    "sg:classifiers":[
        {
            "category":"Autos & Motor Vehicles",
            "subcategory":"Auto Supplies",
            "type":"Retail Goods"
        }
    ],
    "sg:phone":"+1   ",
    "sg:postcode":"15902",
    "sg:province":"PA",
    "wof:name":"Advance Auto Parts",
    "wof:placetype":"venue"
},
  "geometry": {"coordinates":[-78.911264,40.304415],"type":"Point"}
}