{
  "type": "Feature",
  "properties": {
    "addr:full":"411 Woods Ave Lock Haven PA 17745",
    "addr:housenumber":"411",
    "addr:postcode":"17745",
    "addr:street":"Woods Ave",
    "iso:country":"US",
    "sg:address":"411 Woods Ave",
    "sg:city":"Lock Haven",
    "sg:classifiers":[
        {
            "category":"Retail",
            "subcategory":"Auto Repair",
            "type":"Services"
        }
    ],
    "sg:phone":"+1 570 748 8851",
    "sg:postcode":"17745",
    "sg:province":"PA",
    "sg:tags":[
        "shop",
        "automotive",
        "general"
    ],
    "wof:name":"D & G Auto Repair & Welding",
    "wof:placetype":"venue"
},
  "geometry": {"coordinates":[-77.467467,41.123256],"type":"Point"}
}