{
  "type": "Feature",
  "properties": {
    "addr:full":"1410 Edgehill St Pittsburgh PA 15216",
    "addr:housenumber":"1410",
    "addr:postcode":"15216",
    "addr:street":"Edgehill St",
    "iso:country":"US",
    "sg:address":"1410 Edgehill St",
    "sg:city":"Pittsburgh",
    "sg:classifiers":[
        {
            "category":"Shopping",
            "subcategory":"Used Merchandise",
            "type":"Retail Goods"
        }
    ],
    "sg:phone":"+1   ",
    "sg:postcode":"15216",
    "sg:province":"PA",
    "wof:name":"Alexandras Attic",
    "wof:placetype":"venue"
},
  "geometry": {"coordinates":[-80.030439,40.397853],"type":"Point"}
}