{
  "type": "Feature",
  "properties": {
    "iso:country":"US",
    "sg:address":"653 E Lancaster Ave",
    "sg:city":"Wayne",
    "sg:classifiers":[
        {
            "category":"Shopping",
            "subcategory":"Crafts & Fabrics",
            "type":"Retail Goods"
        }
    ],
    "sg:phone":"+1   ",
    "sg:postcode":"19087",
    "sg:province":"PA",
    "sg:tags":[
        "sewing"
    ],
    "wof:name":"Everfast Inc",
    "wof:placetype":"venue"
},
  "geometry": {"coordinates":[-75.405413,40.04616],"type":"Point"}
}