{
  "type": "Feature",
  "properties": {
    "iso:country":"US",
    "sg:address":"12040 Edinboro Rd",
    "sg:city":"Edinboro",
    "sg:classifiers":[
        {
            "category":"Shopping",
            "subcategory":"Used Merchandise",
            "type":"Retail Goods"
        }
    ],
    "sg:phone":"+1 814 734 0660",
    "sg:postcode":"16412",
    "sg:province":"PA",
    "sg:tags":[
        "shop",
        "consignment"
    ],
    "wof:name":"Mary Jean's Next To New",
    "wof:placetype":"venue"
},
  "geometry": {"coordinates":[-80.125739,41.907791],"type":"Point"}
}