{
  "type": "Feature",
  "properties": {
    "addr:full":"4826 Old York Rd Philadelphia PA 19141",
    "addr:housenumber":"4826",
    "addr:postcode":"19141",
    "addr:street":"Old York Rd",
    "iso:country":"US",
    "sg:address":"4826 Old York Rd",
    "sg:city":"Philadelphia",
    "sg:classifiers":[
        {
            "category":"Professional",
            "subcategory":"Management & Consulting",
            "type":"Services"
        }
    ],
    "sg:phone":"+1 215 455 1075",
    "sg:postcode":"19141",
    "sg:province":"PA",
    "sg:tags":[
        "consultant",
        "training"
    ],
    "wof:name":"Elite Pro Combat Training",
    "wof:placetype":"venue"
},
  "geometry": {"coordinates":[-75.146693,40.026347],"type":"Point"}
}