{
  "type": "Feature",
  "properties": {
    "iso:country":"US",
    "sg:address":"9 N High St",
    "sg:city":"West Chester",
    "sg:classifiers":[
        {
            "category":"Banks & Credit Unions",
            "subcategory":"Bank",
            "type":"Services"
        }
    ],
    "sg:phone":"+1 484 881 4790",
    "sg:postcode":"19380",
    "sg:province":"PA",
    "wof:name":"First National Bank-Chester",
    "wof:placetype":"venue"
},
  "geometry": {"coordinates":[-75.605538,39.960963],"type":"Point"}
}