{
  "type": "Feature",
  "properties": {
    "iso:country":"US",
    "sg:address":"7 Valmont Trailer Ct",
    "sg:city":"Hazleton",
    "sg:classifiers":[
        {
            "category":"Restaurant",
            "type":"Food & Drink"
        }
    ],
    "sg:phone":"+1 570 455 8200",
    "sg:postcode":"18202",
    "sg:province":"PA",
    "sg:tags":[
        "eating"
    ],
    "wof:name":"Yong Hao Chinese Buffet",
    "wof:placetype":"venue"
},
  "geometry": {"coordinates":[-76.01700700000001,40.980644],"type":"Point"}
}