{
  "type": "Feature",
  "properties": {
    "iso:country":"US",
    "sg:address":"719 W Tilghman St",
    "sg:city":"Allentown",
    "sg:classifiers":[
        {
            "category":"Building & Trades",
            "subcategory":"Construction",
            "type":"Services"
        }
    ],
    "sg:phone":"+1 484 895 9304",
    "sg:postcode":"18102",
    "sg:province":"PA",
    "sg:tags":[
        "painter"
    ],
    "wof:name":"Professional Painterss For Less",
    "wof:placetype":"venue"
},
  "geometry": {"coordinates":[-75.477159,40.611875],"type":"Point"}
}