{
  "type": "Feature",
  "properties": {
    "addr:full":"653 E Broad St Souderton PA 18964",
    "addr:housenumber":"653",
    "addr:postcode":"18964",
    "addr:street":"E Broad St",
    "iso:country":"US",
    "sg:address":"653 E Broad St",
    "sg:city":"Souderton",
    "sg:classifiers":[
        {
            "category":"Bagels",
            "type":"Food & Drink"
        },
        {
            "category":"Coffee & Tea",
            "type":"Food & Drink"
        },
        {
            "category":"Food & Beverages",
            "subcategory":"Bakery",
            "type":"Retail Goods"
        },
        {
            "category":"Bakery",
            "type":"Food & Drink"
        },
        {
            "category":"Donuts",
            "type":"Food & Drink"
        }
    ],
    "sg:menulink":"http://www.allmenus.com/pa/souderton/143864-dunkin-donuts/menu/",
    "sg:phone":"+1 215 799 0199",
    "sg:postcode":"18964",
    "sg:province":"PA",
    "sg:tags":[
        "coffee",
        "diner",
        "tea",
        "bakery",
        "bagel",
        "american",
        "pastry"
    ],
    "wof:name":"Dunkin' Donuts",
    "wof:placetype":"venue"
},
  "geometry": {"coordinates":[-75.312254,40.31403],"type":"Point"}
}