{
  "type": "Feature",
  "properties": {
    "addr:full":"516 Watch Hill Rd Villanova PA 19085",
    "addr:housenumber":"516",
    "addr:postcode":"19085",
    "addr:street":"Watch Hill Rd",
    "iso:country":"US",
    "sg:address":"516 Watch Hill Rd",
    "sg:city":"Villanova",
    "sg:classifiers":[
        {
            "category":"Shopping",
            "subcategory":"Antiques",
            "type":"Retail Goods"
        }
    ],
    "sg:phone":"+1 610 293 1464",
    "sg:postcode":"19085",
    "sg:province":"PA",
    "wof:name":"T Hollingshead Antiques",
    "wof:placetype":"venue"
},
  "geometry": {"coordinates":[-75.371757,40.026287],"type":"Point"}
}