{
  "type": "Feature",
  "properties": {
    "addr:full":"128 Fairfield Ave Johnstown PA 15906",
    "addr:housenumber":"128",
    "addr:postcode":"15906",
    "addr:street":"Fairfield Ave",
    "iso:country":"US",
    "sg:address":"128 Fairfield Ave",
    "sg:city":"Johnstown",
    "sg:classifiers":[
        {
            "category":"Health Services",
            "subcategory":"Doctor",
            "type":"Services"
        }
    ],
    "sg:phone":"+1 814 535 1621",
    "sg:postcode":"15906",
    "sg:province":"PA",
    "sg:tags":[
        "physician",
        "family",
        "medical",
        "practice",
        "surgeons",
        "medicine"
    ],
    "wof:name":"Conemaugh Health Initiative",
    "wof:placetype":"venue"
},
  "geometry": {"coordinates":[-78.943939,40.344711],"type":"Point"}
}