{
  "type": "Feature",
  "properties": {
    "addr:full":"1382 Old Freeport Rd Pittsburgh PA 15238",
    "addr:housenumber":"1382",
    "addr:postcode":"15238",
    "addr:street":"Old Freeport Rd",
    "iso:country":"US",
    "sg:address":"1382 Old Freeport Rd",
    "sg:city":"Pittsburgh",
    "sg:classifiers":[
        {
            "category":"Professional",
            "subcategory":"Lawyer & Legal Services",
            "type":"Services"
        }
    ],
    "sg:phone":"+1 412 963 9308",
    "sg:postcode":"15238",
    "sg:province":"PA",
    "sg:tags":[
        "attorney"
    ],
    "wof:name":"Eric J Lurie",
    "wof:placetype":"venue"
},
  "geometry": {"coordinates":[-79.871172,40.489375],"type":"Point"}
}