{
  "type": "Feature",
  "properties": {
    "iso:country":"US",
    "sg:address":"39 Pinevale Rd",
    "sg:city":"Doylestown",
    "sg:classifiers":[
        {
            "category":"Professional",
            "subcategory":"Management & Consulting",
            "type":"Services"
        }
    ],
    "sg:phone":"+1 215 340 9929",
    "sg:postcode":"18901",
    "sg:province":"PA",
    "sg:tags":[
        "facility",
        "food",
        "integrator",
        "system",
        "process",
        "consultant"
    ],
    "wof:name":"Tek Industrial Corporation",
    "wof:placetype":"venue"
},
  "geometry": {"coordinates":[-75.164584,40.31523],"type":"Point"}
}