{
  "type": "Feature",
  "properties": {
    "iso:country":"US",
    "sg:address":"124 Burmont Rd",
    "sg:city":"Drexel Hill",
    "sg:classifiers":[
        {
            "category":"Retail",
            "subcategory":"Auto Repair",
            "type":"Services"
        }
    ],
    "sg:phone":"+1   ",
    "sg:postcode":"19026",
    "sg:province":"PA",
    "sg:tags":[
        "transmission"
    ],
    "wof:name":"Paper Connection",
    "wof:placetype":"venue"
},
  "geometry": {"coordinates":[-75.290601,39.937166],"type":"Point"}
}