{
  "type": "Feature",
  "properties": {
    "iso:country":"US",
    "sg:address":"2515 W 4th St",
    "sg:city":"Williamsport",
    "sg:classifiers":[
        {
            "category":"Communications",
            "type":"Services"
        }
    ],
    "sg:phone":"+1   ",
    "sg:postcode":"17701",
    "sg:province":"PA",
    "sg:tags":[
        "communication"
    ],
    "wof:name":"J & J Communications",
    "wof:placetype":"venue"
},
  "geometry": {"coordinates":[-77.062479,41.238247],"type":"Point"}
}