{
  "type": "Feature",
  "properties": {
    "addr:full":"470 Landis Rd Harleysville PA 19438",
    "addr:housenumber":"470",
    "addr:postcode":"19438",
    "addr:street":"Landis Rd",
    "iso:country":"US",
    "sg:address":"470 Landis Rd",
    "sg:city":"Harleysville",
    "sg:classifiers":[
        {
            "category":"Place Of Worship",
            "subcategory":"Church",
            "type":"Public Place"
        },
        {
            "category":"Place Of Worship",
            "type":"Public Place"
        }
    ],
    "sg:phone":"+1 215 256 9941",
    "sg:postcode":"19438",
    "sg:province":"PA",
    "sg:tags":[
        "lutheran",
        "america",
        "churches-lutheran",
        "churches-lutheran-evangelical"
    ],
    "sg:website":"http://www.adventharleysville.org",
    "wof:name":"Advent Lutheran Church Of Goschenhoppen (Inc)",
    "wof:placetype":"venue"
},
  "geometry": {"coordinates":[-75.399007,40.266864],"type":"Point"}
}