{
  "type": "Feature",
  "properties": {
    "iso:country":"US",
    "sg:address":"10 Duff Rd",
    "sg:city":"Pittsburgh",
    "sg:classifiers":[
        {
            "category":"Health Services",
            "subcategory":"Doctor",
            "type":"Services"
        }
    ],
    "sg:phone":"+1 412 241 0606",
    "sg:postcode":"15235",
    "sg:province":"PA",
    "sg:tags":[
        "physician",
        "surgeon",
        "medical"
    ],
    "wof:name":"Bernard R Palus MD",
    "wof:placetype":"venue"
},
  "geometry": {"coordinates":[-79.82852699999999,40.463958],"type":"Point"}
}