{
  "type": "Feature",
  "properties": {
    "addr:full":"301 S Queen St York PA 17403",
    "addr:housenumber":"301",
    "addr:postcode":"17403",
    "addr:street":"S Queen St",
    "iso:country":"US",
    "sg:address":"301 S Queen St",
    "sg:city":"York",
    "sg:classifiers":[
        {
            "category":"Food & Beverages",
            "subcategory":"Groceries & Convenience Stores",
            "type":"Retail Goods"
        }
    ],
    "sg:phone":"+1 717 845 3017",
    "sg:postcode":"17403",
    "sg:province":"PA",
    "wof:name":"Caribe Grocery Store",
    "wof:placetype":"venue"
},
  "geometry": {"coordinates":[-76.721358,39.958795],"type":"Point"}
}