{
  "type": "Feature",
  "properties": {
    "iso:country":"US",
    "sg:address":"1637 Oakwood Dr",
    "sg:city":"Narberth",
    "sg:classifiers":[
        {
            "category":"Insurance",
            "subcategory":"Health Insurance",
            "type":"Services"
        }
    ],
    "sg:phone":"+1   ",
    "sg:postcode":"19072",
    "sg:province":"PA",
    "sg:tags":[
        "carrier"
    ],
    "wof:name":"Stanley Abrahams",
    "wof:placetype":"venue"
},
  "geometry": {"coordinates":[-75.25595800000001,40.039477],"type":"Point"}
}