{
  "type": "Feature",
  "properties": {
    "iso:country":"US",
    "sg:address":"315 Pitney Rd",
    "sg:city":"Lancaster",
    "sg:classifiers":[
        {
            "category":"Personal",
            "type":"Services"
        }
    ],
    "sg:phone":"+1 717 393 5883",
    "sg:postcode":"17601",
    "sg:province":"PA",
    "sg:tags":[
        "therapist",
        "massage"
    ],
    "wof:name":"Tracy L Kolb",
    "wof:placetype":"venue"
},
  "geometry": {"coordinates":[-76.25568800000001,40.05716],"type":"Point"}
}