{
  "type": "Feature",
  "properties": {
    "iso:country":"US",
    "sg:address":"1060 Sun Valley Rd",
    "sg:city":"Stevens",
    "sg:classifiers":[
        {
            "category":"Shopping",
            "type":"Retail Goods"
        }
    ],
    "sg:phone":"+1 717 733 9696",
    "sg:postcode":"17578",
    "sg:province":"PA",
    "sg:tags":[
        "wedding",
        "supply"
    ],
    "sg:website":"www.wedica.com",
    "wof:name":"WEDICA.COM",
    "wof:placetype":"venue"
},
  "geometry": {"coordinates":[-76.255408,40.238354],"type":"Point"}
}