{
  "type": "Feature",
  "properties": {
    "iso:country":"US",
    "sg:address":"2650 Brandt School Rd",
    "sg:city":"Wexford",
    "sg:classifiers":[
        {
            "category":"Restaurant",
            "type":"Food & Drink"
        }
    ],
    "sg:menulink":"http://www.allmenus.com/pa/franklin-park/27619-eat-n-park/menu/",
    "sg:phone":"+1 724 940 3270",
    "sg:postcode":"15090",
    "sg:province":"PA",
    "sg:tags":[
        "american",
        "diner"
    ],
    "wof:name":"Eat N' Park",
    "wof:placetype":"venue"
},
  "geometry": {"coordinates":[-80.09293099999999,40.615412],"type":"Point"}
}