{
  "type": "Feature",
  "properties": {
    "iso:country":"US",
    "sg:address":"839 E Germantown Pike",
    "sg:city":"Pottstown",
    "sg:classifiers":[
        {
            "category":"Real Estate",
            "subcategory":"Real Estate Agent",
            "type":"Services"
        }
    ],
    "sg:phone":"+1   ",
    "sg:postcode":"19462",
    "sg:province":"PA",
    "wof:name":"Tornetta Realty",
    "wof:placetype":"venue"
},
  "geometry": {"coordinates":[-75.297163,40.127279],"type":"Point"}
}