{
  "type": "Feature",
  "properties": {
    "iso:country":"US",
    "sg:address":"405 Boyle St",
    "sg:city":"Dunmore",
    "sg:classifiers":[
        {
            "category":"Professional",
            "subcategory":"Computer Services",
            "type":"Services"
        }
    ],
    "sg:phone":"+1 570 342 3677",
    "sg:postcode":"18512",
    "sg:province":"PA",
    "sg:tags":[
        "consultant",
        "designer"
    ],
    "sg:website":"www.rpmwebworx.com",
    "wof:name":"RPM Worldwide",
    "wof:placetype":"venue"
},
  "geometry": {"coordinates":[-75.623627,41.423742],"type":"Point"}
}