{
  "type": "Feature",
  "properties": {
    "iso:country":"US",
    "sg:address":"1725 Bridge St",
    "sg:city":"Philadelphia",
    "sg:classifiers":[
        {
            "category":"Food & Beverages",
            "subcategory":"Groceries & Convenience Stores",
            "type":"Retail Goods"
        }
    ],
    "sg:phone":"+1 215 288 1822",
    "sg:postcode":"19124",
    "sg:province":"PA",
    "wof:name":"Pedrito Minimarket",
    "wof:placetype":"venue"
},
  "geometry": {"coordinates":[-75.074307,40.021008],"type":"Point"}
}