{
  "type": "Feature",
  "properties": {
    "addr:full":"1634 Walnut St Philadelphia PA 19103",
    "addr:housenumber":"1634",
    "addr:postcode":"19103",
    "addr:street":"Walnut St",
    "iso:country":"US",
    "sg:address":"1634 Walnut St",
    "sg:city":"Philadelphia",
    "sg:classifiers":[
        {
            "category":"Shopping",
            "subcategory":"Gifts & Souvenirs",
            "type":"Retail Goods"
        }
    ],
    "sg:phone":"+1 215 732 5324",
    "sg:postcode":"19103",
    "sg:province":"PA",
    "sg:tags":[
        "shop"
    ],
    "wof:name":"Winsome House",
    "wof:placetype":"venue"
},
  "geometry": {"coordinates":[-75.168693,39.9498],"type":"Point"}
}