{
  "type": "Feature",
  "properties": {
    "iso:country":"US",
    "sg:address":"3700 State Route 711 ",
    "sg:city":"Ligonier",
    "sg:classifiers":[
        {
            "category":"Restaurant",
            "type":"Food & Drink"
        }
    ],
    "sg:menulink":"http://www.allmenus.com/pa/ligonier/286735-roadhouse-pizza-subs--wings/menu/",
    "sg:phone":"+1 724 238 7555",
    "sg:postcode":"15658",
    "sg:province":"PA",
    "sg:tags":[
        "american",
        "sandwich",
        "wing",
        "pizza"
    ],
    "wof:name":"Roadhouse Pizza Subs & Wings",
    "wof:placetype":"venue"
},
  "geometry": {"coordinates":[-79.208229,40.256357],"type":"Point"}
}