{
  "type": "Feature",
  "properties": {
    "iso:country":"US",
    "sg:address":"111 Franklin St",
    "sg:city":"Johnstown",
    "sg:classifiers":[
        {
            "category":"Organizations",
            "subcategory":"Labor Organization",
            "type":"Services"
        }
    ],
    "sg:phone":"+1 814 539 6902",
    "sg:postcode":"15901",
    "sg:province":"PA",
    "wof:name":"Apwu Johnstown Local 4469",
    "wof:placetype":"venue"
},
  "geometry": {"coordinates":[-78.917168,40.32629],"type":"Point"}
}