{
  "type": "Feature",
  "properties": {
    "addr:full":"5526 W Thompson St Philadelphia PA 19131",
    "addr:housenumber":"5526",
    "addr:postcode":"19131",
    "addr:street":"W Thompson St",
    "iso:country":"US",
    "sg:address":"5526 W Thompson St",
    "sg:city":"Philadelphia",
    "sg:classifiers":[
        {
            "category":"Retail",
            "subcategory":"Funeral Services",
            "type":"Services"
        }
    ],
    "sg:phone":"+1 215 877 1791",
    "sg:postcode":"19131",
    "sg:province":"PA",
    "sg:tags":[
        "cemetery"
    ],
    "wof:name":"Gray Jas J Funeral Home",
    "wof:placetype":"venue"
},
  "geometry": {"coordinates":[-75.231796,39.9725],"type":"Point"}
}