{
  "type": "Feature",
  "properties": {
    "iso:country":"US",
    "sg:address":"8 Runnemede Ave",
    "sg:city":"Lansdowne",
    "sg:classifiers":[
        {
            "category":"Health Services",
            "subcategory":"Doctor",
            "type":"Services"
        }
    ],
    "sg:phone":"+1 610 626 2442",
    "sg:postcode":"19050",
    "sg:province":"PA",
    "sg:tags":[
        "dentist"
    ],
    "wof:name":"Lansdowne Dental Assoc",
    "wof:placetype":"venue"
},
  "geometry": {"coordinates":[-75.275679,39.939151],"type":"Point"}
}