{
  "type": "Feature",
  "properties": {
    "iso:country":"US",
    "sg:address":"22 N Lansdowne Ave",
    "sg:city":"Lansdowne",
    "sg:classifiers":[
        {
            "category":"Real Estate",
            "subcategory":"Real Estate Agent",
            "type":"Services"
        }
    ],
    "sg:phone":"+1 610 623 2900",
    "sg:postcode":"19050",
    "sg:province":"PA",
    "wof:name":"Creative 2-2 Realty Inc",
    "wof:placetype":"venue"
},
  "geometry": {"coordinates":[-75.272481,39.938989],"type":"Point"}
}