{
  "type": "Feature",
  "properties": {
    "iso:country":"US",
    "sg:address":"3100 Hedley St",
    "sg:city":"Philadelphia",
    "sg:classifiers":[
        {
            "category":"Professional",
            "subcategory":"Research",
            "type":"Services"
        }
    ],
    "sg:phone":"+1 215 289 3700",
    "sg:postcode":"19137",
    "sg:province":"PA",
    "sg:tags":[
        "environmental",
        "ecological"
    ],
    "wof:name":"Onyx Environmental Svc",
    "wof:placetype":"venue"
},
  "geometry": {"coordinates":[-75.072993,39.991982],"type":"Point"}
}