{
  "type": "Feature",
  "properties": {
    "iso:country":"US",
    "sg:address":"5401 Jonestown Rd",
    "sg:city":"Harrisburg",
    "sg:classifiers":[
        {
            "category":"Personal",
            "type":"Services"
        }
    ],
    "sg:phone":"+1 717 651 5551",
    "sg:postcode":"17112",
    "sg:province":"PA",
    "sg:tags":[
        "therapist",
        "massage"
    ],
    "sg:website":"www.spa.com",
    "wof:name":"Ultimate Health & Body Works",
    "wof:placetype":"venue"
},
  "geometry": {"coordinates":[-76.79586999999999,40.316765],"type":"Point"}
}