{
  "type": "Feature",
  "properties": {
    "iso:country":"US",
    "sg:address":"8 8th St",
    "sg:city":"Youngsville",
    "sg:classifiers":[
        {
            "category":"Freight",
            "type":"Transportation"
        }
    ],
    "sg:phone":"+1   ",
    "sg:postcode":"16371",
    "sg:province":"PA",
    "sg:tags":[
        "courier"
    ],
    "wof:name":"Youngsville Courier",
    "wof:placetype":"venue"
},
  "geometry": {"coordinates":[-79.323448,41.858802],"type":"Point"}
}