{
  "type": "Feature",
  "properties": {
    "addr:full":"5719 N Montour Rd Gibsonia PA 15044",
    "addr:housenumber":"5719",
    "addr:postcode":"15044",
    "addr:street":"N Montour Rd",
    "iso:country":"US",
    "sg:address":"5719 N Montour Rd",
    "sg:city":"Gibsonia",
    "sg:classifiers":[
        {
            "category":"Social Services",
            "subcategory":"Child Care",
            "type":"Services"
        }
    ],
    "sg:phone":"+1   ",
    "sg:postcode":"15044",
    "sg:province":"PA",
    "sg:tags":[
        "day"
    ],
    "wof:name":"Stepping Stones Satellite 4",
    "wof:placetype":"venue"
},
  "geometry": {"coordinates":[-79.98271200000001,40.653652],"type":"Point"}
}