{
  "type": "Feature",
  "properties": {
    "iso:country":"US",
    "sg:address":"59 S East St",
    "sg:city":"Spring Grove",
    "sg:classifiers":[
        {
            "category":"Building & Trades",
            "subcategory":"Plumbing",
            "type":"Services"
        }
    ],
    "sg:phone":"+1   ",
    "sg:postcode":"17362",
    "sg:province":"PA",
    "sg:tags":[
        "contractor"
    ],
    "wof:name":"Melado Mechanical Contrac",
    "wof:placetype":"venue"
},
  "geometry": {"coordinates":[-76.863851,39.874044],"type":"Point"}
}