{
  "type": "Feature",
  "properties": {
    "iso:country":"US",
    "sg:address":"1021 Miller Spring Rd",
    "sg:city":"York",
    "sg:classifiers":[
        {
            "category":"Building & Trades",
            "subcategory":"Construction",
            "type":"Services"
        }
    ],
    "sg:phone":"+1   ",
    "sg:postcode":"17406",
    "sg:province":"PA",
    "sg:tags":[
        "house"
    ],
    "wof:name":"Melvin Druck Builder",
    "wof:placetype":"venue"
},
  "geometry": {"coordinates":[-76.53909899999999,39.980625],"type":"Point"}
}