{
  "type": "Feature",
  "properties": {
    "iso:country":"US",
    "sg:address":"363 E Street Rd",
    "sg:city":"Feastervl Trvs",
    "sg:classifiers":[
        {
            "category":"Banks & Credit Unions",
            "subcategory":"Bank",
            "type":"Services"
        }
    ],
    "sg:phone":"+1 215 355 7540",
    "sg:postcode":"19053",
    "sg:province":"PA",
    "sg:tags":[
        "loan",
        "real estate"
    ],
    "wof:name":"Affiliated Mortgage Lending",
    "wof:placetype":"venue"
},
  "geometry": {"coordinates":[-75.01047800000001,40.155387],"type":"Point"}
}