{
  "type": "Feature",
  "properties": {
    "iso:country":"US",
    "sg:address":"12 Glenbrook Rd",
    "sg:city":"Leola",
    "sg:classifiers":[
        {
            "category":"Personal",
            "subcategory":"Beauty Salon",
            "type":"Services"
        }
    ],
    "sg:phone":"+1 717 656 3759",
    "sg:postcode":"17540",
    "sg:province":"PA",
    "wof:name":"Fermalene Dahn's Hair Designs",
    "wof:placetype":"venue"
},
  "geometry": {"coordinates":[-76.19517500000001,40.087584],"type":"Point"}
}