{
  "type": "Feature",
  "properties": {
    "iso:country":"US",
    "sg:address":"969 Natalie Ln",
    "sg:city":"Coopersburg",
    "sg:classifiers":[
        {
            "category":"Building & Trades",
            "subcategory":"Construction",
            "type":"Services"
        }
    ],
    "sg:phone":"+1   ",
    "sg:postcode":"18036",
    "sg:province":"PA",
    "sg:tags":[
        "house"
    ],
    "wof:name":"Wallis Custom Builders Inc",
    "wof:placetype":"venue"
},
  "geometry": {"coordinates":[-75.41783700000001,40.481996],"type":"Point"}
}