{
  "type": "Feature",
  "properties": {
    "addr:full":"23 Laudermilch Rd Hershey PA 17033",
    "addr:housenumber":"23",
    "addr:postcode":"17033",
    "addr:street":"Laudermilch Rd",
    "iso:country":"US",
    "sg:address":"23 Laudermilch Rd",
    "sg:city":"Hershey",
    "sg:classifiers":[
        {
            "category":"Organizations",
            "subcategory":"Community Association",
            "type":"Services"
        }
    ],
    "sg:phone":"+1   ",
    "sg:postcode":"17033",
    "sg:province":"PA",
    "wof:name":"Optimist International",
    "wof:placetype":"venue"
},
  "geometry": {"coordinates":[-76.638884,40.297988],"type":"Point"}
}