{
  "type": "Feature",
  "properties": {
    "iso:country":"US",
    "sg:address":"268 Overbrook Dr",
    "sg:city":"Newtown Square",
    "sg:classifiers":[
        {
            "category":"Wholesale",
            "subcategory":"Durable Goods & Equipment",
            "type":"Manufacturing & Wholesale Goods"
        }
    ],
    "sg:phone":"+1 610 353 2422",
    "sg:postcode":"19073",
    "sg:province":"PA",
    "sg:tags":[
        "representative",
        "manufacturer"
    ],
    "wof:name":"De Young Associates",
    "wof:placetype":"venue"
},
  "geometry": {"coordinates":[-75.386703,39.995589],"type":"Point"}
}