{
  "type": "Feature",
  "properties": {
    "iso:country":"US",
    "sg:address":"945 Main St",
    "sg:city":"Honesdale",
    "sg:classifiers":[
        {
            "category":"Shopping",
            "subcategory":"Bicycles & Sporting Goods",
            "type":"Retail Goods"
        }
    ],
    "sg:phone":"+1 570 253 5528",
    "sg:postcode":"18431",
    "sg:province":"PA",
    "sg:tags":[
        "boards",
        "ski",
        "snow",
        "equipment",
        "skiing",
        "clothing"
    ],
    "sg:website":"www.guenthersskihaus.com",
    "wof:name":"Guenther's Ski Haus",
    "wof:placetype":"venue"
},
  "geometry": {"coordinates":[-75.256603,41.574094],"type":"Point"}
}