{
  "type": "Feature",
  "properties": {
    "iso:country":"US",
    "sg:address":"197 Chestnut Ridge Rd",
    "sg:city":"Blairsville",
    "sg:classifiers":[
        {
            "category":"Professional",
            "type":"Services"
        },
        {
            "category":"Mining & Drilling",
            "type":"Manufacturing & Wholesale Goods"
        }
    ],
    "sg:phone":"+1 724 459 7900",
    "sg:postcode":"15717",
    "sg:province":"PA",
    "sg:tags":[
        "natural",
        "production",
        "gas",
        "liquid",
        "establishment"
    ],
    "wof:name":"Penn View Exploration Inc",
    "wof:placetype":"venue"
},
  "geometry": {"coordinates":[-79.207803,40.440644],"type":"Point"}
}