{
  "type": "Feature",
  "properties": {
    "iso:country":"US",
    "sg:address":"1509 Willowbrook Ln",
    "sg:city":"Villanova",
    "sg:classifiers":[
        {
            "category":"Shopping",
            "subcategory":"Pharmacy",
            "type":"Retail Goods"
        }
    ],
    "sg:phone":"+1   ",
    "sg:postcode":"19085",
    "sg:province":"PA",
    "wof:name":"State Drug Co",
    "wof:placetype":"venue"
},
  "geometry": {"coordinates":[-75.330732,40.043755],"type":"Point"}
}