{
  "type": "Feature",
  "properties": {
    "iso:country":"US",
    "sg:address":"219 Quarry Rd",
    "sg:city":"Peach Bottom",
    "sg:classifiers":[
        {
            "category":"Mining & Drilling",
            "type":"Manufacturing & Wholesale Goods"
        }
    ],
    "sg:phone":"+1 717 548 2191",
    "sg:postcode":"17563",
    "sg:province":"PA",
    "sg:tags":[
        "limestone"
    ],
    "wof:name":"D M Stoltzfus & Son Inc",
    "wof:placetype":"venue"
},
  "geometry": {"coordinates":[-76.15160400000001,39.721863],"type":"Point"}
}