{
  "type": "Feature",
  "properties": {
    "iso:country":"US",
    "sg:address":"203 Chestnut St",
    "sg:city":"Mt Holly Springs",
    "sg:classifiers":[
        {
            "category":"Arts & Performance",
            "subcategory":"Theater",
            "type":"Entertainment"
        },
        {
            "category":"Shopping",
            "type":"Retail Goods"
        }
    ],
    "sg:phone":"+1 717 486 5812",
    "sg:postcode":"17065",
    "sg:province":"PA",
    "sg:tags":[
        "house",
        "live",
        "music",
        "merchandise",
        "mail"
    ],
    "wof:name":"Layback Lenny Music",
    "wof:placetype":"venue"
},
  "geometry": {"coordinates":[-77.19128000000001,40.117755],"type":"Point"}
}