{
  "type": "Feature",
  "properties": {
    "iso:country":"US",
    "sg:address":"1909 Ligonier St",
    "sg:city":"Latrobe",
    "sg:classifiers":[
        {
            "category":"Retail",
            "subcategory":"Repair Shop",
            "type":"Services"
        },
        {
            "category":"Home & Garden",
            "subcategory":"Household Appliances",
            "type":"Retail Goods"
        }
    ],
    "sg:phone":"+1 724 539 2959",
    "sg:postcode":"15650",
    "sg:province":"PA",
    "sg:tags":[
        "cleaners",
        "parts",
        "vacuum"
    ],
    "wof:name":"Scheeren Wisneski Sweeper Sale",
    "wof:placetype":"venue"
},
  "geometry": {"coordinates":[-79.375502,40.307007],"type":"Point"}
}