{
  "type": "Feature",
  "properties": {
    "addr:full":"890 S Irvine Ave Brookfield PA 44438",
    "addr:housenumber":"890",
    "addr:postcode":"44438",
    "addr:street":"S Irvine Ave",
    "iso:country":"US",
    "sg:address":"890 S Irvine Ave",
    "sg:city":"Brookfield",
    "sg:classifiers":[
        {
            "category":"Autos & Motor Vehicles",
            "subcategory":"Automobile Sales",
            "type":"Retail Goods"
        }
    ],
    "sg:phone":"+1 330 448 0202",
    "sg:postcode":"44438",
    "sg:province":"PA",
    "sg:tags":[
        "car",
        "used",
        "dealer"
    ],
    "wof:name":"Cars For Less",
    "wof:placetype":"venue"
},
  "geometry": {"coordinates":[-80.51992199999999,41.219387],"type":"Point"}
}