{
  "type": "Feature",
  "properties": {
    "addr:full":"20397 Route 19 Cranberry Twp PA 16066",
    "addr:housenumber":"20397",
    "addr:postcode":"16066",
    "addr:street":"Route 19",
    "iso:country":"US",
    "sg:address":"20397 Route 19",
    "sg:city":"Cranberry Twp",
    "sg:classifiers":[
        {
            "category":"Health Services",
            "subcategory":"Doctor",
            "type":"Services"
        }
    ],
    "sg:phone":"+1 724 776 6030",
    "sg:postcode":"16066",
    "sg:province":"PA",
    "sg:website":"www.pediatricalliance.com",
    "wof:name":"Lamb Kathleen MD",
    "wof:placetype":"venue"
},
  "geometry": {"coordinates":[-80.10459899999999,40.698799],"type":"Point"}
}