{
  "type": "Feature",
  "properties": {
    "addr:full":"1045 Woodstock Ave Hopwood PA 15445",
    "addr:housenumber":"1045",
    "addr:postcode":"15445",
    "addr:street":"Woodstock Ave",
    "iso:country":"US",
    "sg:address":"1045 Woodstock Ave",
    "sg:city":"Hopwood",
    "sg:classifiers":[
        {
            "category":"Manufacturing",
            "subcategory":"Signs",
            "type":"Manufacturing & Wholesale Goods"
        },
        {
            "category":"Professional",
            "subcategory":"Advertising",
            "type":"Services"
        }
    ],
    "sg:phone":"+1 724 439 4658",
    "sg:postcode":"15445",
    "sg:province":"PA",
    "sg:tags":[
        "outdoor",
        "spec",
        "mfg"
    ],
    "wof:name":"Workman Signs",
    "wof:placetype":"venue"
},
  "geometry": {"coordinates":[-79.69745899999999,39.874169],"type":"Point"}
}