{
  "type": "Feature",
  "properties": {
    "iso:country":"US",
    "sg:address":"76 Greenfield Rd",
    "sg:city":"Lancaster",
    "sg:classifiers":[
        {
            "category":"Home & Garden",
            "subcategory":"Home Furnishings",
            "type":"Retail Goods"
        }
    ],
    "sg:phone":"+1 717 392 0208",
    "sg:postcode":"17602",
    "sg:province":"PA",
    "sg:tags":[
        "blanket"
    ],
    "wof:name":"Rachel's Of Greenfield",
    "wof:placetype":"venue"
},
  "geometry": {"coordinates":[-76.252122,40.038693],"type":"Point"}
}