{
  "type": "Feature",
  "properties": {
    "iso:country":"US",
    "sg:address":"212 Wood St",
    "sg:city":"New Bethlehem",
    "sg:classifiers":[
        {
            "category":"Home & Garden",
            "subcategory":"Furniture",
            "type":"Retail Goods"
        }
    ],
    "sg:phone":"+1   ",
    "sg:postcode":"16242",
    "sg:province":"PA",
    "wof:name":"Value Buyers",
    "wof:placetype":"venue"
},
  "geometry": {"coordinates":[-79.331377,41.001519],"type":"Point"}
}