{
  "type": "Feature",
  "properties": {
    "addr:full":"872 N 40th St Philadelphia PA 19104",
    "addr:housenumber":"872",
    "addr:postcode":"19104",
    "addr:street":"N 40Th St",
    "iso:country":"US",
    "sg:address":"872 N 40th St",
    "sg:city":"Philadelphia",
    "sg:classifiers":[
        {
            "category":"Organizations",
            "subcategory":"Religious Organization",
            "type":"Services"
        }
    ],
    "sg:phone":"+1 215 222 4294",
    "sg:postcode":"19104",
    "sg:province":"PA",
    "sg:tags":[
        "place",
        "worship",
        "church"
    ],
    "wof:name":"True Holiness Temple Inc",
    "wof:placetype":"venue"
},
  "geometry": {"coordinates":[-75.20344900000001,39.96961],"type":"Point"}
}