{
  "type": "Feature",
  "properties": {
    "addr:full":"599 3rd St Beaver PA 15009",
    "addr:housenumber":"599",
    "addr:postcode":"15009",
    "addr:street":"3Rd St",
    "iso:country":"US",
    "sg:address":"599 3rd St",
    "sg:city":"Beaver",
    "sg:classifiers":[
        {
            "category":"Banks & Credit Unions",
            "subcategory":"Bank",
            "type":"Services"
        }
    ],
    "sg:phone":"+1 724 774 5650",
    "sg:postcode":"15009",
    "sg:province":"PA",
    "sg:tags":[
        "state",
        "commercial"
    ],
    "wof:name":"National City Bank",
    "wof:placetype":"venue"
},
  "geometry": {"coordinates":[-80.303144,40.695933],"type":"Point"}
}