{
  "type": "Feature",
  "properties": {
    "iso:country":"US",
    "sg:address":"613 W Oak Ln",
    "sg:city":"Glenolden",
    "sg:classifiers":[
        {
            "category":"Manufacturing",
            "subcategory":"Glass & Minerals",
            "type":"Manufacturing & Wholesale Goods"
        }
    ],
    "sg:phone":"+1 610 461 2182",
    "sg:postcode":"19036",
    "sg:province":"PA",
    "sg:tags":[
        "ready",
        "concrete",
        "mfg"
    ],
    "wof:name":"Advance Transit Mix Inc",
    "wof:placetype":"venue"
},
  "geometry": {"coordinates":[-75.290133,39.911863],"type":"Point"}
}