{
  "type": "Feature",
  "properties": {
    "addr:full":"629 Conchester Hwy Marcus Hook PA 19061",
    "addr:housenumber":"629",
    "addr:postcode":"19061",
    "addr:street":"Conchester Hwy",
    "iso:country":"US",
    "sg:address":"629 Conchester Hwy",
    "sg:city":"Marcus Hook",
    "sg:classifiers":[
        {
            "category":"Shopping",
            "subcategory":"Shoes",
            "type":"Retail Goods"
        }
    ],
    "sg:phone":"+1 610 494 9073",
    "sg:postcode":"19061",
    "sg:province":"PA",
    "wof:name":"Shoe Department",
    "wof:placetype":"venue"
},
  "geometry": {"coordinates":[-75.451125,39.850363],"type":"Point"}
}