{
  "type": "Feature",
  "properties": {
    "iso:country":"US",
    "sg:address":"38 Francis Rd",
    "sg:city":"Burgettstown",
    "sg:classifiers":[
        {
            "category":"Shopping",
            "type":"Retail Goods"
        }
    ],
    "sg:phone":"+1 724 947 0213",
    "sg:postcode":"15021",
    "sg:province":"PA",
    "sg:tags":[
        "merchandise"
    ],
    "wof:name":"Omband Company",
    "wof:placetype":"venue"
},
  "geometry": {"coordinates":[-80.414058,40.384612],"type":"Point"}
}