{
  "type": "Feature",
  "properties": {
    "addr:full":"6227 Mellon Park Ct Pittsburgh PA 15232",
    "addr:housenumber":"6227",
    "addr:postcode":"15232",
    "addr:street":"Mellon Park Ct",
    "iso:country":"US",
    "sg:address":"6227 Mellon Park Ct",
    "sg:city":"Pittsburgh",
    "sg:classifiers":[
        {
            "category":"Banks & Credit Unions",
            "subcategory":"Financial Services",
            "type":"Services"
        }
    ],
    "sg:phone":"+1   ",
    "sg:postcode":"15232",
    "sg:province":"PA",
    "sg:tags":[
        "real estate"
    ],
    "wof:name":"M Rosenblum Agency Inc",
    "wof:placetype":"venue"
},
  "geometry": {"coordinates":[-79.920877,40.451309],"type":"Point"}
}