{
  "type": "Feature",
  "properties": {
    "addr:full":"201 S 7th St Easton PA 18042",
    "addr:housenumber":"201",
    "addr:postcode":"18042",
    "addr:street":"S 7Th St",
    "iso:country":"US",
    "sg:address":"201 S 7th St",
    "sg:city":"Easton",
    "sg:classifiers":[
        {
            "category":"Real Estate",
            "subcategory":"Real Estate Services",
            "type":"Services"
        }
    ],
    "sg:phone":"+1 610 258 3773",
    "sg:postcode":"18042",
    "sg:province":"PA",
    "sg:tags":[
        "company",
        "title"
    ],
    "sg:website":"www.greaterpaabstract.com",
    "wof:name":"Greater Pennsylvania Abstract",
    "wof:placetype":"venue"
},
  "geometry": {"coordinates":[-75.21786899999999,40.687027],"type":"Point"}
}