{
  "type": "Feature",
  "properties": {
    "iso:country":"US",
    "sg:address":"278 Beverly Rd",
    "sg:city":"Pittsburgh",
    "sg:classifiers":[
        {
            "category":"Professional",
            "subcategory":"Accounting & Tax Preparation",
            "type":"Services"
        }
    ],
    "sg:phone":"+1 412 343 4880",
    "sg:postcode":"15216",
    "sg:province":"PA",
    "sg:tags":[
        "accountant"
    ],
    "wof:name":"Keiser George F Jr CPA",
    "wof:placetype":"venue"
},
  "geometry": {"coordinates":[-80.047798,40.3904],"type":"Point"}
}