{
  "type": "Feature",
  "properties": {
    "iso:country":"US",
    "sg:address":"575 Memorial Hwy",
    "sg:city":"Dallas",
    "sg:classifiers":[
        {
            "category":"Insurance",
            "subcategory":"Insurance Agent",
            "type":"Services"
        }
    ],
    "sg:phone":"+1 570 675 1167",
    "sg:postcode":"18612",
    "sg:province":"PA",
    "wof:name":"Slocum Insurance Inc",
    "wof:placetype":"venue"
},
  "geometry": {"coordinates":[-75.965474,41.336316],"type":"Point"}
}