{
  "type": "Feature",
  "properties": {
    "iso:country":"US",
    "sg:address":"300 Wolfs Hollow Dr",
    "sg:city":"Atglen",
    "sg:classifiers":[
        {
            "category":"Government",
            "subcategory":"Office",
            "type":"Public Place"
        }
    ],
    "sg:phone":"+1   ",
    "sg:postcode":"19310",
    "sg:province":"PA",
    "sg:tags":[
        "conservation"
    ],
    "wof:name":"County of Chester",
    "wof:placetype":"venue"
},
  "geometry": {"coordinates":[-75.98379300000001,39.924628],"type":"Point"}
}