{
  "type": "Feature",
  "properties": {
    "addr:full":"775 N Laurel St Hazleton PA 18201",
    "addr:housenumber":"775",
    "addr:postcode":"18201",
    "addr:street":"N Laurel St",
    "iso:country":"US",
    "sg:address":"775 N Laurel St",
    "sg:city":"Hazleton",
    "sg:classifiers":[
        {
            "category":"Building & Trades",
            "subcategory":"Construction",
            "type":"Services"
        }
    ],
    "sg:phone":"+1 570 454 9795",
    "sg:postcode":"18201",
    "sg:province":"PA",
    "sg:tags":[
        "concrete",
        "contractor"
    ],
    "wof:name":"Scitney Paving",
    "wof:placetype":"venue"
},
  "geometry": {"coordinates":[-75.974653,40.967467],"type":"Point"}
}