{
  "type": "Feature",
  "properties": {
    "iso:country":"US",
    "sg:address":"121 Passmore Rd",
    "sg:city":"Bechtelsville",
    "sg:classifiers":[
        {
            "category":"Building & Trades",
            "subcategory":"Landscaping Services",
            "type":"Services"
        }
    ],
    "sg:phone":"+1   ",
    "sg:postcode":"19505",
    "sg:province":"PA",
    "sg:tags":[
        "lawn",
        "maintenance"
    ],
    "wof:name":"David D Moyer",
    "wof:placetype":"venue"
},
  "geometry": {"coordinates":[-75.613038,40.370923],"type":"Point"}
}