{
  "type": "Feature",
  "properties": {
    "iso:country":"US",
    "sg:address":"200 N 16th St",
    "sg:city":"Philadelphia",
    "sg:classifiers":[
        {
            "category":"Manufacturing",
            "subcategory":"Chemicals & Compounds",
            "type":"Manufacturing & Wholesale Goods"
        }
    ],
    "sg:phone":"+1   ",
    "sg:postcode":"19102",
    "sg:province":"PA",
    "sg:tags":[
        "product",
        "consumer",
        "mfg"
    ],
    "wof:name":"S B International Trading D E",
    "wof:placetype":"venue"
},
  "geometry": {"coordinates":[-75.165881,39.957117],"type":"Point"}
}