{
  "type": "Feature",
  "properties": {
    "iso:country":"US",
    "sg:address":"347 Water St",
    "sg:city":"Northumberland",
    "sg:classifiers":[
        {
            "category":"Insurance",
            "subcategory":"Insurance Agent",
            "type":"Services"
        }
    ],
    "sg:phone":"+1 570 473 3544",
    "sg:postcode":"17857",
    "sg:province":"PA",
    "wof:name":"Kratzer Insurance",
    "wof:placetype":"venue"
},
  "geometry": {"coordinates":[-76.792452,40.889238],"type":"Point"}
}