{
  "type": "Feature",
  "properties": {
    "addr:full":"278 Fort Lebanon Rd Auburn PA 17922",
    "addr:housenumber":"278",
    "addr:postcode":"17922",
    "addr:street":"Fort Lebanon Rd",
    "iso:country":"US",
    "sg:address":"278 Fort Lebanon Rd",
    "sg:city":"Auburn",
    "sg:classifiers":[
        {
            "category":"Building & Trades",
            "subcategory":"Construction",
            "type":"Services"
        }
    ],
    "sg:phone":"+1   ",
    "sg:postcode":"17922",
    "sg:province":"PA",
    "sg:tags":[
        "masonry",
        "excavating",
        "contractor"
    ],
    "wof:name":"Nevin A Breiner & Sons Inc",
    "wof:placetype":"venue"
},
  "geometry": {"coordinates":[-76.073263,40.608211],"type":"Point"}
}