{
  "type": "Feature",
  "properties": {
    "addr:full":"1010 N 4th St Altoona PA 16601",
    "addr:housenumber":"1010",
    "addr:postcode":"16601",
    "addr:street":"N 4Th St",
    "iso:country":"US",
    "sg:address":"1010 N 4th St",
    "sg:city":"Altoona",
    "sg:classifiers":[
        {
            "category":"Retail",
            "subcategory":"Laundry & Dry Cleaning",
            "type":"Services"
        }
    ],
    "sg:phone":"+1 814 941 0500",
    "sg:postcode":"16601",
    "sg:province":"PA",
    "sg:tags":[
        "cleaners",
        "rug",
        "carpet"
    ],
    "wof:name":"Knowles Cleaning",
    "wof:placetype":"venue"
},
  "geometry": {"coordinates":[-78.390197,40.538633],"type":"Point"}
}