{
  "type": "Feature",
  "properties": {
    "addr:full":"3291 N George St Emigsville PA 17318",
    "addr:housenumber":"3291",
    "addr:postcode":"17318",
    "addr:street":"N George St",
    "iso:country":"US",
    "sg:address":"3291 N George St",
    "sg:city":"Emigsville",
    "sg:classifiers":[
        {
            "category":"Personal",
            "type":"Services"
        }
    ],
    "sg:phone":"+1 717 767 6686",
    "sg:postcode":"17318",
    "sg:province":"PA",
    "sg:tags":[
        "therapist",
        "massage"
    ],
    "wof:name":"Therapeutic Massage",
    "wof:placetype":"venue"
},
  "geometry": {"coordinates":[-76.729041,40.017223],"type":"Point"}
}