{
  "type": "Feature",
  "properties": {
    "addr:full":"451 Gregory Ln Bellefonte PA 16823",
    "addr:housenumber":"451",
    "addr:postcode":"16823",
    "addr:street":"Gregory Ln",
    "iso:country":"US",
    "sg:address":"451 Gregory Ln",
    "sg:city":"Bellefonte",
    "sg:classifiers":[
        {
            "category":"Building & Trades",
            "subcategory":"Construction",
            "type":"Services"
        }
    ],
    "sg:phone":"+1 814 357 8122",
    "sg:postcode":"16823",
    "sg:province":"PA",
    "sg:tags":[
        "contractor"
    ],
    "wof:name":"Reitz Vern Construction",
    "wof:placetype":"venue"
},
  "geometry": {"coordinates":[-77.766899,40.905998],"type":"Point"}
}