{
  "type": "Feature",
  "properties": {
    "iso:country":"US",
    "sg:address":"509 S 1st St",
    "sg:city":"Bangor",
    "sg:classifiers":[
        {
            "category":"Real Estate",
            "subcategory":"Real Estate Agent",
            "type":"Services"
        }
    ],
    "sg:phone":"+1   ",
    "sg:postcode":"18013",
    "sg:province":"PA",
    "wof:name":"C & B Realty Co",
    "wof:placetype":"venue"
},
  "geometry": {"coordinates":[-75.206574,40.859665],"type":"Point"}
}