{
  "type": "Feature",
  "properties": {
    "iso:country":"US",
    "sg:address":"16 Dock St",
    "sg:city":"Schuylkill Haven",
    "sg:classifiers":[
        {
            "category":"Travel",
            "subcategory":"Hotels & Motels",
            "type":"Entertainment"
        }
    ],
    "sg:phone":"+1 570 385 2115",
    "sg:postcode":"17972",
    "sg:province":"PA",
    "sg:tags":[
        "breakfast",
        "accommodation",
        "bed"
    ],
    "wof:name":"Stone House Bed & Breakfast",
    "wof:placetype":"venue"
},
  "geometry": {"coordinates":[-76.17171399999999,40.6313],"type":"Point"}
}