{
  "type": "Feature",
  "properties": {
    "iso:country":"US",
    "sg:address":"740 Ogden Ave",
    "sg:city":"Swarthmore",
    "sg:classifiers":[
        {
            "category":"Health Services",
            "subcategory":"Doctor",
            "type":"Services"
        }
    ],
    "sg:phone":"+1 610 544 4826",
    "sg:postcode":"19081",
    "sg:province":"PA",
    "sg:tags":[
        "physician",
        "surgeon"
    ],
    "wof:name":"John J Ruffini Md",
    "wof:placetype":"venue"
},
  "geometry": {"coordinates":[-75.355316,39.910437],"type":"Point"}
}