{
  "type": "Feature",
  "properties": {
    "addr:full":"103 Grohman Rd Butler PA 16002",
    "addr:housenumber":"103",
    "addr:postcode":"16002",
    "addr:street":"Grohman Rd",
    "iso:country":"US",
    "sg:address":"103 Grohman Rd",
    "sg:city":"Butler",
    "sg:classifiers":[
        {
            "category":"Professional",
            "subcategory":"Advertising",
            "type":"Services"
        }
    ],
    "sg:phone":"+1 724 285 5241",
    "sg:postcode":"16002",
    "sg:province":"PA",
    "sg:tags":[
        "counselor"
    ],
    "sg:website":"www.advertising-concepts.com",
    "wof:name":"Advertising Concepts",
    "wof:placetype":"venue"
},
  "geometry": {"coordinates":[-79.86636900000001,40.833058],"type":"Point"}
}