{
  "type": "Feature",
  "properties": {
    "addr:full":"326 Newell Rd Fayette City PA 15438",
    "addr:housenumber":"326",
    "addr:postcode":"15438",
    "addr:street":"Newell Rd",
    "iso:country":"US",
    "sg:address":"326 Newell Rd",
    "sg:city":"Fayette City",
    "sg:classifiers":[
        {
            "category":"Retail",
            "subcategory":"Veterinary Services",
            "type":"Services"
        }
    ],
    "sg:phone":"+1 724 938 3006",
    "sg:postcode":"15438",
    "sg:province":"PA",
    "sg:tags":[
        "veterinarian"
    ],
    "wof:name":"Fayette Veterinary Hospital",
    "wof:placetype":"venue"
},
  "geometry": {"coordinates":[-79.858268,40.067747],"type":"Point"}
}