{
  "type": "Feature",
  "properties": {
    "addr:full":"520 Market St Sunbury PA 17801",
    "addr:housenumber":"520",
    "addr:postcode":"17801",
    "addr:street":"Market St",
    "iso:country":"US",
    "sg:address":"520 Market St",
    "sg:city":"Sunbury",
    "sg:classifiers":[
        {
            "category":"Personal",
            "subcategory":"Beauty Salon",
            "type":"Services"
        }
    ],
    "sg:phone":"+1 570 286 8717",
    "sg:postcode":"17801",
    "sg:province":"PA",
    "wof:name":"Hair Creations By Joan Swartz",
    "wof:placetype":"venue"
},
  "geometry": {"coordinates":[-76.789129,40.860641],"type":"Point"}
}