{
  "type": "Feature",
  "properties": {
    "iso:country":"US",
    "sg:address":"1003 Mifflin St",
    "sg:city":"Huntingdon",
    "sg:classifiers":[
        {
            "category":"Government",
            "subcategory":"Office",
            "type":"Public Place"
        }
    ],
    "sg:phone":"+1 814 643 5203",
    "sg:postcode":"16652",
    "sg:province":"PA",
    "sg:tags":[
        "village"
    ],
    "wof:name":"Huntingdon Ambulance Div",
    "wof:placetype":"venue"
},
  "geometry": {"coordinates":[-78.016452,40.491092],"type":"Point"}
}