{
  "type": "Feature",
  "properties": {
    "iso:country":"US",
    "sg:address":"50 W North St",
    "sg:city":"Bethlehem",
    "sg:classifiers":[
        {
            "category":"Shopping",
            "subcategory":"Florist",
            "type":"Retail Goods"
        }
    ],
    "sg:phone":"+1 610 868 6300",
    "sg:postcode":"18018",
    "sg:province":"PA",
    "wof:name":"Custom Gift Baskets & Florals",
    "wof:placetype":"venue"
},
  "geometry": {"coordinates":[-75.3803,40.6239],"type":"Point"}
}