{
  "type": "Feature",
  "properties": {
    "addr:full":"968 Postal Rd Ste 120 Allentown PA 18109",
    "addr:housenumber":"968",
    "addr:postcode":"18109",
    "addr:street":"Postal Rd Ste 120",
    "iso:country":"US",
    "sg:address":"968 Postal Rd Ste 120",
    "sg:city":"Allentown",
    "sg:classifiers":[
        {
            "category":"Taxi",
            "type":"Transportation"
        }
    ],
    "sg:phone":"+1 610 266 0640",
    "sg:postcode":"18109",
    "sg:province":"PA",
    "sg:tags":[
        "delivery"
    ],
    "wof:name":"Worldwide Express Inc",
    "wof:placetype":"venue"
},
  "geometry": {"coordinates":[-75.44094800000001,40.645748],"type":"Point"}
}