{
  "type": "Feature",
  "properties": {
    "addr:full":"1606 Embreeville Rd Coatesville PA 19320",
    "addr:housenumber":"1606",
    "addr:postcode":"19320",
    "addr:street":"Embreeville Rd",
    "iso:country":"US",
    "sg:address":"1606 Embreeville Rd",
    "sg:city":"Coatesville",
    "sg:classifiers":[
        {
            "category":"Building & Trades",
            "subcategory":"Plumbing",
            "type":"Services"
        }
    ],
    "sg:phone":"+1 610 444 8857",
    "sg:postcode":"19320",
    "sg:province":"PA",
    "sg:tags":[
        "septic"
    ],
    "wof:name":"J Gallagher Septic & Waste",
    "wof:placetype":"venue"
},
  "geometry": {"coordinates":[-75.73177099999999,39.924594],"type":"Point"}
}