{
  "type": "Feature",
  "properties": {
    "iso:country":"US",
    "sg:address":"1821 Franklin Ave",
    "sg:city":"Erie",
    "sg:classifiers":[
        {
            "category":"Retail",
            "subcategory":"Repair Shop",
            "type":"Services"
        }
    ],
    "sg:phone":"+1 814 899 0271",
    "sg:postcode":"16510",
    "sg:province":"PA",
    "sg:tags":[
        "equipment",
        "pneumatic",
        "hydraulic"
    ],
    "wof:name":"Leo's Pneumatics & Hydraulics",
    "wof:placetype":"venue"
},
  "geometry": {"coordinates":[-80.03021099999999,42.136463],"type":"Point"}
}