{
  "type": "Feature",
  "properties": {
    "iso:country":"US",
    "sg:address":"121 Sunday Rd",
    "sg:city":"Lenhartsville",
    "sg:classifiers":[
        {
            "category":"Manufacturing",
            "subcategory":"Pet Food",
            "type":"Manufacturing & Wholesale Goods"
        },
        {
            "category":"Farming",
            "subcategory":"Farm",
            "type":"Manufacturing & Wholesale Goods"
        }
    ],
    "sg:phone":"+1 610 562 3702",
    "sg:postcode":"19534",
    "sg:province":"PA",
    "sg:tags":[
        "hay"
    ],
    "wof:name":"Carl Davis",
    "wof:placetype":"venue"
},
  "geometry": {"coordinates":[-75.934957,40.544265],"type":"Point"}
}