{
  "type": "Feature",
  "properties": {
    "addr:full":"1001 Darby Rd Havertown PA 19083",
    "addr:housenumber":"1001",
    "addr:postcode":"19083",
    "addr:street":"Darby Rd",
    "iso:country":"US",
    "sg:address":"1001 Darby Rd",
    "sg:city":"Havertown",
    "sg:classifiers":[
        {
            "category":"Professional",
            "subcategory":"Lawyer & Legal Services",
            "type":"Services"
        }
    ],
    "sg:phone":"+1 610 853 6400",
    "sg:postcode":"19083",
    "sg:province":"PA",
    "sg:tags":[
        "attorney"
    ],
    "wof:name":"Dibenedetto Forrest Henry",
    "wof:placetype":"venue"
},
  "geometry": {"coordinates":[-75.30329999999999,39.977125],"type":"Point"}
}