{
  "type": "Feature",
  "properties": {
    "iso:country":"US",
    "sg:address":"537 E Girard Ave",
    "sg:city":"Philadelphia",
    "sg:classifiers":[
        {
            "category":"Personal",
            "subcategory":"Massage",
            "type":"Services"
        },
        {
            "category":"Personal",
            "subcategory":"Hair Removal",
            "type":"Services"
        },
        {
            "category":"Personal",
            "subcategory":"Skin Care",
            "type":"Services"
        }
    ],
    "sg:phone":"+1 215 203 0995",
    "sg:postcode":"19125",
    "sg:province":"PA",
    "sg:website":"affordableskincaresalon.com/",
    "wof:name":"Affordable Skin Care",
    "wof:placetype":"venue"
},
  "geometry": {"coordinates":[-75.12748499999999,39.971471],"type":"Point"}
}