{
  "type": "Feature",
  "properties": {
    "iso:country":"US",
    "sg:address":"208 Washington Ave",
    "sg:city":"Newtown",
    "sg:classifiers":[
        {
            "category":"Health Services",
            "subcategory":"Doctor",
            "type":"Services"
        }
    ],
    "sg:phone":"+1 215 860 1550",
    "sg:postcode":"18940",
    "sg:province":"PA",
    "sg:tags":[
        "dentist"
    ],
    "wof:name":"Blaine N Garner DDS",
    "wof:placetype":"venue"
},
  "geometry": {"coordinates":[-74.93303,40.229061],"type":"Point"}
}