{
  "type": "Feature",
  "properties": {
    "iso:country":"US",
    "sg:address":"100 Industrial Dr",
    "sg:city":"Edinboro",
    "sg:classifiers":[
        {
            "category":"Professional",
            "subcategory":"Business Services",
            "type":"Services"
        }
    ],
    "sg:phone":"+1   ",
    "sg:postcode":"16412",
    "sg:province":"PA",
    "sg:tags":[
        "fund",
        "raiser"
    ],
    "wof:name":"Superb Fundraising Inc",
    "wof:placetype":"venue"
},
  "geometry": {"coordinates":[-80.125778,41.890977],"type":"Point"}
}