{
  "type": "Feature",
  "properties": {
    "addr:full":"18 E Morris St Philadelphia PA 19148",
    "addr:housenumber":"18",
    "addr:postcode":"19148",
    "addr:street":"E Morris St",
    "iso:country":"US",
    "sg:address":"18 E Morris St",
    "sg:city":"Philadelphia",
    "sg:classifiers":[
        {
            "category":"Professional",
            "subcategory":"Research",
            "type":"Services"
        }
    ],
    "sg:phone":"+1   ",
    "sg:postcode":"19148",
    "sg:province":"PA",
    "sg:tags":[
        "nonphysical",
        "commercial"
    ],
    "wof:name":"Reads Inc",
    "wof:placetype":"venue"
},
  "geometry": {"coordinates":[-75.145006,39.926736],"type":"Point"}
}