{
  "type": "Feature",
  "properties": {
    "addr:full":"1489 Baltimore Pike # 400 Springfield PA 19064",
    "addr:housenumber":"1489",
    "addr:postcode":"19064",
    "addr:street":"Baltimore Pike # 400",
    "iso:country":"US",
    "sg:address":"1489 Baltimore Pike # 400",
    "sg:city":"Springfield",
    "sg:classifiers":[
        {
            "category":"Health Services",
            "subcategory":"Hospital",
            "type":"Services"
        }
    ],
    "sg:phone":"+1 610 543 0805",
    "sg:postcode":"19064",
    "sg:province":"PA",
    "sg:tags":[
        "sleep",
        "treatment",
        "disorders-information"
    ],
    "wof:name":"Sunamerica Wellness Centers",
    "wof:placetype":"venue"
},
  "geometry": {"coordinates":[-75.35832499999999,39.912803],"type":"Point"}
}