{
  "type": "Feature",
  "properties": {
    "iso:country":"US",
    "sg:address":"4 Beechwood Cir",
    "sg:city":"Chadds Ford",
    "sg:classifiers":[
        {
            "category":"Banks & Credit Unions",
            "subcategory":"Financial Services",
            "type":"Services"
        }
    ],
    "sg:phone":"+1   ",
    "sg:postcode":"19317",
    "sg:province":"PA",
    "sg:tags":[
        "company",
        "holding"
    ],
    "wof:name":"CN International",
    "wof:placetype":"venue"
},
  "geometry": {"coordinates":[-75.567466,39.859406],"type":"Point"}
}