{
  "type": "Feature",
  "properties": {
    "addr:full":"25 N Laurel St Hazleton PA 18201",
    "addr:housenumber":"25",
    "addr:postcode":"18201",
    "addr:street":"N Laurel St",
    "iso:country":"US",
    "sg:address":"25 N Laurel St",
    "sg:city":"Hazleton",
    "sg:classifiers":[
        {
            "category":"Restaurant",
            "type":"Food & Drink"
        }
    ],
    "sg:phone":"+1   ",
    "sg:postcode":"18201",
    "sg:province":"PA",
    "sg:tags":[
        "eating"
    ],
    "wof:name":"Georgios Family Restaurant",
    "wof:placetype":"venue"
},
  "geometry": {"coordinates":[-75.975145,40.954985],"type":"Point"}
}