{
  "type": "Feature",
  "properties": {
    "iso:country":"US",
    "sg:address":"8000 Rowland Ave",
    "sg:city":"Philadelphia",
    "sg:classifiers":[
        {
            "category":"Retail",
            "subcategory":"Funeral Services",
            "type":"Services"
        }
    ],
    "sg:phone":"+1 215 332 6110",
    "sg:postcode":"19136",
    "sg:province":"PA",
    "wof:name":"Lambie Funeral Home",
    "wof:placetype":"venue"
},
  "geometry": {"coordinates":[-75.029113,40.046769],"type":"Point"}
}