{
  "type": "Feature",
  "properties": {
    "iso:country":"US",
    "sg:address":"171 Maytown Rd",
    "sg:city":"Elizabethtown",
    "sg:classifiers":[
        {
            "category":"Building & Trades",
            "subcategory":"Pest Control",
            "type":"Services"
        }
    ],
    "sg:phone":"+1 717 361 8119",
    "sg:postcode":"17022",
    "sg:province":"PA",
    "wof:name":"Powers Pest Management",
    "wof:placetype":"venue"
},
  "geometry": {"coordinates":[-76.60051199999999,40.139164],"type":"Point"}
}