{
  "type": "Feature",
  "properties": {
    "addr:full":"339 E Lancaster Ave Wynnewood PA 19096",
    "addr:housenumber":"339",
    "addr:postcode":"19096",
    "addr:street":"E Lancaster Ave",
    "iso:country":"US",
    "sg:address":"339 E Lancaster Ave",
    "sg:city":"Wynnewood",
    "sg:classifiers":[
        {
            "category":"Health Services",
            "subcategory":"Doctor",
            "type":"Services"
        },
        {
            "category":"Personal",
            "subcategory":"Hair Removal",
            "type":"Services"
        },
        {
            "category":"Personal",
            "subcategory":"Skin Care",
            "type":"Services"
        }
    ],
    "sg:phone":"+1 610 943 2383",
    "sg:postcode":"19096",
    "sg:province":"PA",
    "sg:tags":[
        "surgeon",
        "laser",
        "cosmetic",
        "dermatologist"
    ],
    "sg:website":"www.ringpfeildermatology.com",
    "wof:name":"Ringpfeil Advanced Dermatology",
    "wof:placetype":"venue"
},
  "geometry": {"coordinates":[-75.26553699999999,39.993606],"type":"Point"}
}