{
  "type": "Feature",
  "properties": {
    "addr:full":"354 Spring St Reading PA 19601",
    "addr:housenumber":"354",
    "addr:postcode":"19601",
    "addr:street":"Spring St",
    "iso:country":"US",
    "sg:address":"354 Spring St",
    "sg:city":"Reading",
    "sg:classifiers":[
        {
            "category":"Retail",
            "subcategory":"Portrait Studio",
            "type":"Services"
        }
    ],
    "sg:phone":"+1 610 372 6489",
    "sg:postcode":"19601",
    "sg:province":"PA",
    "sg:tags":[
        "photographer"
    ],
    "wof:name":"Richard B Broadbelt",
    "wof:placetype":"venue"
},
  "geometry": {"coordinates":[-75.92963899999999,40.3504],"type":"Point"}
}