{
  "type": "Feature",
  "properties": {
    "iso:country":"US",
    "sg:address":"2950 Harding Ave",
    "sg:city":"Sharpsville",
    "sg:classifiers":[
        {
            "category":"Building & Trades",
            "subcategory":"Landscaping Services",
            "type":"Services"
        }
    ],
    "sg:phone":"+1   ",
    "sg:postcode":"16150",
    "sg:province":"OH",
    "sg:tags":[
        "lawn",
        "mowing"
    ],
    "wof:name":"Bobs Lawn & Landscaping",
    "wof:placetype":"venue"
},
  "geometry": {"coordinates":[-80.476907,41.273736],"type":"Point"}
}