{
  "type": "Feature",
  "properties": {
    "iso:country":"US",
    "sg:address":"1815 Buttermore Blvd",
    "sg:city":"Connellsville",
    "sg:classifiers":[
        {
            "category":"Professional",
            "subcategory":"Accounting & Tax Preparation",
            "type":"Services"
        }
    ],
    "sg:phone":"+1 724 628 7289",
    "sg:postcode":"15425",
    "sg:province":"PA",
    "sg:tags":[
        "return",
        "preparation-business"
    ],
    "wof:name":"Daniels & Associates Tax Service",
    "wof:placetype":"venue"
},
  "geometry": {"coordinates":[-79.576336,40.038937],"type":"Point"}
}