{
  "type": "Feature",
  "properties": {
    "addr:full":"1873 Lincoln Hwy E Lancaster PA 17602",
    "addr:housenumber":"1873",
    "addr:postcode":"17602",
    "addr:street":"Lincoln Hwy E",
    "iso:country":"US",
    "sg:address":"1873 Lincoln Hwy E",
    "sg:city":"Lancaster",
    "sg:classifiers":[
        {
            "category":"Health Services",
            "subcategory":"Chiropractor",
            "type":"Services"
        }
    ],
    "sg:phone":"+1 717 299 9758",
    "sg:postcode":"17602",
    "sg:province":"PA",
    "wof:name":"Accident & Injury Chiropractic",
    "wof:placetype":"venue"
},
  "geometry": {"coordinates":[-76.250513,40.034227],"type":"Point"}
}