{
  "type": "Feature",
  "properties": {
    "iso:country":"US",
    "sg:address":"805 BALTIMORE ST STE 225",
    "sg:city":"HANOVER",
    "sg:phone":"+1 717 637 0803",
    "sg:postcode":"17331",
    "sg:province":"PA",
    "sg:website":"http://www.rentacenter.com/",
    "wof:name":"Rent-A-Center",
    "wof:placetype":"venue"
},
  "geometry": {"coordinates":[-76.968753,39.78716],"type":"Point"}
}