{
  "type": "Feature",
  "properties": {
    "addr:full":"4204 N 8th St Philadelphia PA 19140",
    "addr:housenumber":"4204",
    "addr:postcode":"19140",
    "addr:street":"N 8Th St",
    "iso:country":"US",
    "sg:address":"4204 N 8th St",
    "sg:city":"Philadelphia",
    "sg:classifiers":[
        {
            "category":"Building & Trades",
            "subcategory":"Plumbing",
            "type":"Services"
        }
    ],
    "sg:phone":"+1 267 687 2547",
    "sg:postcode":"19140",
    "sg:province":"PA",
    "sg:tags":[
        "plumber",
        "industrial",
        "contractors-commercial"
    ],
    "wof:name":"Yolanda Plumber",
    "wof:placetype":"venue"
},
  "geometry": {"coordinates":[-75.14007700000001,40.015765],"type":"Point"}
}