{
  "type": "Feature",
  "properties": {
    "iso:country":"US",
    "sg:address":"1517 Bluestone Dr",
    "sg:city":"Glenshaw",
    "sg:classifiers":[
        {
            "category":"Health Services",
            "subcategory":"Health Practitioner",
            "type":"Services"
        }
    ],
    "sg:phone":"+1 412 486 5924",
    "sg:postcode":"15116",
    "sg:province":"PA",
    "sg:tags":[
        "nurse",
        "registry"
    ],
    "wof:name":"Lorraine Gillespie",
    "wof:placetype":"venue"
},
  "geometry": {"coordinates":[-79.943905,40.541676],"type":"Point"}
}