{
  "type": "Feature",
  "properties": {
    "addr:full":"6910 Ludlow St Upper Darby PA 19082",
    "addr:housenumber":"6910",
    "addr:postcode":"19082",
    "addr:street":"Ludlow St",
    "iso:country":"US",
    "sg:address":"6910 Ludlow St",
    "sg:city":"Upper Darby",
    "sg:classifiers":[
        {
            "category":"Health Services",
            "subcategory":"Dentist",
            "type":"Services"
        }
    ],
    "sg:phone":"+1 610 352 7270",
    "sg:postcode":"19082",
    "sg:province":"PA",
    "wof:name":"Sidlick Leonard DDS",
    "wof:placetype":"venue"
},
  "geometry": {"coordinates":[-75.25959400000001,39.961073],"type":"Point"}
}