{
  "type": "Feature",
  "properties": {
    "addr:full":"5000 Paschall Ave Philadelphia PA 19143",
    "addr:postcode":"5000;19143",
    "addr:street":"Paschall Ave",
    "iso:country":"US",
    "sg:address":"5000 Paschall Ave",
    "sg:city":"Philadelphia",
    "sg:classifiers":[
        {
            "category":"Manufacturing",
            "subcategory":"Apparel",
            "type":"Manufacturing & Wholesale Goods"
        }
    ],
    "sg:phone":"+1 215 727 4791",
    "sg:postcode":"19143",
    "sg:province":"PA",
    "sg:tags":[
        "sewing",
        "contractor"
    ],
    "wof:name":"Clayton L Hagy & Sons",
    "wof:placetype":"venue"
},
  "geometry": {"coordinates":[-75.21138500000001,39.939834],"type":"Point"}
}