{
  "type": "Feature",
  "properties": {
    "addr:full":"202 Parrish St Wilkes Barre PA 18702",
    "addr:housenumber":"202",
    "addr:postcode":"18702",
    "addr:street":"Parrish St",
    "iso:country":"US",
    "sg:address":"202 Parrish St",
    "sg:city":"Wilkes Barre",
    "sg:classifiers":[
        {
            "category":"Professional",
            "type":"Services"
        }
    ],
    "sg:phone":"+1   ",
    "sg:postcode":"18702",
    "sg:province":"PA",
    "wof:name":"Robert Szocozzo",
    "wof:placetype":"venue"
},
  "geometry": {"coordinates":[-75.897665,41.23138],"type":"Point"}
}