{
  "type": "Feature",
  "properties": {
    "addr:full":"103 S Main St Coopersburg PA 18036",
    "addr:housenumber":"103",
    "addr:postcode":"18036",
    "addr:street":"S Main St",
    "iso:country":"US",
    "sg:address":"103 S Main St",
    "sg:city":"Coopersburg",
    "sg:classifiers":[
        {
            "category":"Retail",
            "subcategory":"Repair Shop",
            "type":"Services"
        }
    ],
    "sg:phone":"+1 610 282 5725",
    "sg:postcode":"18036",
    "sg:province":"PA",
    "sg:tags":[
        "related"
    ],
    "wof:name":"Southern Exposure Cam Repair",
    "wof:placetype":"venue"
},
  "geometry": {"coordinates":[-75.39197900000001,40.509192],"type":"Point"}
}