{
  "type": "Feature",
  "properties": {
    "addr:full":"4030 William Penn Hwy Monroeville PA 15146",
    "addr:housenumber":"4030",
    "addr:postcode":"15146",
    "addr:street":"William Penn Hwy",
    "iso:country":"US",
    "sg:address":"4030 William Penn Hwy",
    "sg:city":"Monroeville",
    "sg:classifiers":[
        {
            "category":"Autos & Motor Vehicles",
            "subcategory":"Fuel & Gas Station",
            "type":"Retail Goods"
        }
    ],
    "sg:phone":"+1   ",
    "sg:postcode":"15146",
    "sg:province":"PA",
    "sg:tags":[
        "grocery",
        "station",
        "gasoline"
    ],
    "wof:name":"BP",
    "wof:placetype":"venue"
},
  "geometry": {"coordinates":[-79.766854,40.438769],"type":"Point"}
}