{
  "type": "Feature",
  "properties": {
    "iso:country":"US",
    "sg:address":"50 W Wheeling St",
    "sg:city":"Washington",
    "sg:classifiers":[
        {
            "category":"Real Estate",
            "subcategory":"Real Estate Operator",
            "type":"Services"
        }
    ],
    "sg:phone":"+1   ",
    "sg:postcode":"15301",
    "sg:province":"PA",
    "sg:tags":[
        "building",
        "apartment"
    ],
    "wof:name":"Cardinal Apartments",
    "wof:placetype":"venue"
},
  "geometry": {"coordinates":[-80.246227,40.169057],"type":"Point"}
}