{
  "type": "Feature",
  "properties": {
    "iso:country":"US",
    "sg:address":"17 W Howard St",
    "sg:city":"Dallastown",
    "sg:classifiers":[
        {
            "category":"Building & Trades",
            "subcategory":"Construction",
            "type":"Services"
        }
    ],
    "sg:phone":"+1   ",
    "sg:postcode":"17313",
    "sg:province":"PA",
    "sg:tags":[
        "house"
    ],
    "wof:name":"Fabie Homes LLC",
    "wof:placetype":"venue"
},
  "geometry": {"coordinates":[-76.64517499999999,39.900085],"type":"Point"}
}