{
  "type": "Feature",
  "properties": {
    "iso:country":"US",
    "sg:address":"561 W Roosevelt Blvd",
    "sg:city":"Philadelphia",
    "sg:classifiers":[
        {
            "category":"Personal",
            "type":"Services"
        }
    ],
    "sg:phone":"+1 215 455 3300",
    "sg:postcode":"19120",
    "sg:province":"PA",
    "sg:tags":[
        "local"
    ],
    "sg:website":"www.globalwastellc.com",
    "wof:name":"Global Waste Management LLC",
    "wof:placetype":"venue"
},
  "geometry": {"coordinates":[-75.13509500000001,40.023996],"type":"Point"}
}