{
  "type": "Feature",
  "properties": {
    "iso:country":"US",
    "sg:address":"119 E Boundary St",
    "sg:city":"Butler",
    "sg:classifiers":[
        {
            "category":"Retail",
            "subcategory":"Laundry & Dry Cleaning",
            "type":"Services"
        }
    ],
    "sg:phone":"+1 724 282 1120",
    "sg:postcode":"16001",
    "sg:province":"PA",
    "sg:tags":[
        "cleaner",
        "rug",
        "carpet"
    ],
    "wof:name":"Ultra Carpets & Upholstery Clg",
    "wof:placetype":"venue"
},
  "geometry": {"coordinates":[-79.926773,40.853512],"type":"Point"}
}