{
  "type": "Feature",
  "properties": {
    "addr:full":"528 E Church Ln Philadelphia PA 19144",
    "addr:housenumber":"528",
    "addr:postcode":"19144",
    "addr:street":"E Church Ln",
    "iso:country":"US",
    "sg:address":"528 E Church Ln",
    "sg:city":"Philadelphia",
    "sg:classifiers":[
        {
            "category":"Organizations",
            "subcategory":"Religious Organization",
            "type":"Services"
        }
    ],
    "sg:phone":"+1   ",
    "sg:postcode":"19144",
    "sg:province":"PA",
    "wof:name":"Have Christ Will Trvl Ministry",
    "wof:placetype":"venue"
},
  "geometry": {"coordinates":[-75.16388499999999,40.04063],"type":"Point"}
}