{
  "type": "Feature",
  "properties": {
    "iso:country":"US",
    "sg:address":"8333 Germantown Ave",
    "sg:city":"Philadelphia",
    "sg:classifiers":[
        {
            "category":"Professional",
            "subcategory":"Detective & Security Services",
            "type":"Services"
        }
    ],
    "sg:phone":"+1   ",
    "sg:postcode":"19118",
    "sg:province":"PA",
    "sg:tags":[
        "system"
    ],
    "wof:name":"Pro Guard",
    "wof:placetype":"venue"
},
  "geometry": {"coordinates":[-75.203457,40.07428],"type":"Point"}
}