{
  "type": "Feature",
  "properties": {
    "addr:full":"322 Moyhend St Springdale PA 15144",
    "addr:housenumber":"322",
    "addr:postcode":"15144",
    "addr:street":"Moyhend St",
    "iso:country":"US",
    "sg:address":"322 Moyhend St",
    "sg:city":"Springdale",
    "sg:classifiers":[
        {
            "category":"Personal",
            "subcategory":"Beauty Salon",
            "type":"Services"
        }
    ],
    "sg:phone":"+1 724 274 8988",
    "sg:postcode":"15144",
    "sg:province":"PA",
    "wof:name":"Cathy Wilhelm's Hair Styling",
    "wof:placetype":"venue"
},
  "geometry": {"coordinates":[-79.776158,40.542366],"type":"Point"}
}