{
  "type": "Feature",
  "properties": {
    "addr:full":"228 E Street Rd Warminster PA 18974",
    "addr:housenumber":"228",
    "addr:postcode":"18974",
    "addr:street":"E Street Rd",
    "iso:country":"US",
    "sg:address":"228 E Street Rd",
    "sg:city":"Warminster",
    "sg:classifiers":[
        {
            "category":"Retail",
            "subcategory":"Auto Repair",
            "type":"Services"
        }
    ],
    "sg:phone":"+1 215 675 9462",
    "sg:postcode":"18974",
    "sg:province":"PA",
    "sg:tags":[
        "repairing",
        "automobile"
    ],
    "wof:name":"Sam's Auto Svc & Repair Ctr",
    "wof:placetype":"venue"
},
  "geometry": {"coordinates":[-75.08631200000001,40.198885],"type":"Point"}
}