{
  "type": "Feature",
  "properties": {
    "iso:country":"US",
    "sg:address":"15 W 4th St",
    "sg:city":"Bethlehem",
    "sg:classifiers":[
        {
            "category":"Organizations",
            "subcategory":"Religious Organization",
            "type":"Services"
        }
    ],
    "sg:phone":"+1 610 866 1872",
    "sg:postcode":"18015",
    "sg:province":"PA",
    "wof:name":"First United Church Of Christ",
    "wof:placetype":"venue"
},
  "geometry": {"coordinates":[-75.379535,40.61049],"type":"Point"}
}