{
  "type": "Feature",
  "properties": {
    "iso:country":"US",
    "sg:address":"40 W 1st street",
    "sg:city":"McKees Rocks",
    "sg:classifiers":[
        {
            "category":"Shopping",
            "subcategory":"Hobbies, Toys, & Games",
            "type":"Retail Goods"
        }
    ],
    "sg:phone":"+1 610 863 6272",
    "sg:postcode":"15136",
    "sg:province":"PA",
    "sg:tags":[
        "shop",
        "hobby"
    ],
    "sg:website":"nascarbillpa.com",
    "wof:name":"Nascar Collectables",
    "wof:placetype":"venue"
},
  "geometry": {"coordinates":[-80.06505799999999,40.466676],"type":"Point"}
}