{
  "type": "Feature",
  "properties": {
    "iso:country":"US",
    "sg:address":"3215 Souderton Pike",
    "sg:city":"Hatfield",
    "sg:classifiers":[
        {
            "category":"Freight",
            "type":"Transportation"
        }
    ],
    "sg:phone":"+1   ",
    "sg:postcode":"19440",
    "sg:province":"PA",
    "sg:tags":[
        "operator",
        "local",
        "trucking"
    ],
    "wof:name":"Edge Transportation Company",
    "wof:placetype":"venue"
},
  "geometry": {"coordinates":[-75.3078,40.291157],"type":"Point"}
}