{
  "type": "Feature",
  "properties": {
    "iso:country":"US",
    "sg:address":"342 S Wayne St",
    "sg:city":"Lewistown",
    "sg:classifiers":[
        {
            "category":"Freight",
            "type":"Transportation"
        }
    ],
    "sg:phone":"+1   ",
    "sg:postcode":"17044",
    "sg:province":"PA",
    "wof:name":"Anytime Escort",
    "wof:placetype":"venue"
},
  "geometry": {"coordinates":[-77.570791,40.592753],"type":"Point"}
}