{
  "type": "Feature",
  "properties": {
    "iso:country":"US",
    "sg:address":"15227 Sunset Ave",
    "sg:city":"Blue Ridge Smt",
    "sg:classifiers":[
        {
            "category":"Wholesale",
            "subcategory":"Auto Parts",
            "type":"Manufacturing & Wholesale Goods"
        }
    ],
    "sg:phone":"+1 717 794 2744",
    "sg:postcode":"17214",
    "sg:province":"PA",
    "sg:tags":[
        "equipment",
        "towing"
    ],
    "wof:name":"Keystone Garage",
    "wof:placetype":"venue"
},
  "geometry": {"coordinates":[-77.471423,39.724359],"type":"Point"}
}