{
  "type": "Feature",
  "properties": {
    "addr:full":"529 Court Pl Pittsburgh PA 15219",
    "addr:housenumber":"529",
    "addr:postcode":"15219",
    "addr:street":"Court Pl",
    "iso:country":"US",
    "sg:address":"529 Court Pl",
    "sg:city":"Pittsburgh",
    "sg:classifiers":[
        {
            "category":"Restaurant",
            "type":"Food & Drink"
        }
    ],
    "sg:phone":"+1   ",
    "sg:postcode":"15219",
    "sg:province":"PA",
    "sg:tags":[
        "organization",
        "membership",
        "eating"
    ],
    "wof:name":"Hong Kong Express II Ltd",
    "wof:placetype":"venue"
},
  "geometry": {"coordinates":[-79.99738600000001,40.436648],"type":"Point"}
}