{
  "type": "Feature",
  "properties": {
    "iso:country":"US",
    "sg:address":"4110 Butler Pike",
    "sg:city":"Plymouth Meeting",
    "sg:classifiers":[
        {
            "category":"Wholesale",
            "subcategory":"Computers",
            "type":"Manufacturing & Wholesale Goods"
        }
    ],
    "sg:phone":"+1 610 825 8330",
    "sg:postcode":"19462",
    "sg:province":"PA",
    "wof:name":"Mid Atlantic Computers Inc",
    "wof:placetype":"venue"
},
  "geometry": {"coordinates":[-75.272679,40.10887],"type":"Point"}
}