{
  "type": "Feature",
  "properties": {
    "addr:full":"309 Browntown Rd New Kensington PA 15068",
    "addr:housenumber":"309",
    "addr:postcode":"15068",
    "addr:street":"Browntown Rd",
    "iso:country":"US",
    "sg:address":"309 Browntown Rd",
    "sg:city":"New Kensington",
    "sg:classifiers":[
        {
            "category":"Retail",
            "subcategory":"Auto Repair",
            "type":"Services"
        }
    ],
    "sg:phone":"+1 724 335 4973",
    "sg:postcode":"15068",
    "sg:province":"PA",
    "sg:tags":[
        "wrecker"
    ],
    "wof:name":"Paul's Towing Svc",
    "wof:placetype":"venue"
},
  "geometry": {"coordinates":[-79.747248,40.539461],"type":"Point"}
}