{
  "type": "Feature",
  "properties": {
    "iso:country":"US",
    "sg:address":"403 Gordon Dr",
    "sg:city":"Exton",
    "sg:classifiers":[
        {
            "category":"Wholesale",
            "subcategory":"Computers",
            "type":"Manufacturing & Wholesale Goods"
        }
    ],
    "sg:phone":"+1 610 594 0601",
    "sg:postcode":"19341",
    "sg:province":"PA",
    "sg:tags":[
        "computer-wholesale",
        "manufacturer"
    ],
    "wof:name":"Trinity Tech",
    "wof:placetype":"venue"
},
  "geometry": {"coordinates":[-75.651752,40.062516],"type":"Point"}
}