{
  "type": "Feature",
  "properties": {
    "iso:country":"US",
    "sg:address":"1499 Spring Garden Dr",
    "sg:city":"Middletown",
    "sg:classifiers":[
        {
            "category":"Government",
            "subcategory":"Police Station",
            "type":"Public Place"
        }
    ],
    "sg:phone":"+1 717 939 0463",
    "sg:postcode":"17057",
    "sg:province":"PA",
    "sg:tags":[
        "department"
    ],
    "wof:name":"Lower Swatara Twp Police Dept",
    "wof:placetype":"venue"
},
  "geometry": {"coordinates":[-76.76563899999999,40.220549],"type":"Point"}
}