{
  "type": "Feature",
  "properties": {
    "addr:full":"535 Pheasant Run Coatesville PA 19320",
    "addr:housenumber":"535",
    "addr:postcode":"19320",
    "addr:street":"Pheasant Run",
    "iso:country":"US",
    "sg:address":"535 Pheasant Run",
    "sg:city":"Coatesville",
    "sg:classifiers":[
        {
            "category":"Building & Trades",
            "subcategory":"Construction",
            "type":"Services"
        }
    ],
    "sg:phone":"+1   ",
    "sg:postcode":"19320",
    "sg:province":"PA",
    "sg:tags":[
        "painting",
        "contractor"
    ],
    "wof:name":"Jeffrey Brown Contracting",
    "wof:placetype":"venue"
},
  "geometry": {"coordinates":[-75.770509,39.974989],"type":"Point"}
}