{
  "type": "Feature",
  "properties": {
    "iso:country":"US",
    "sg:address":"5060 William Penn Hwy",
    "sg:city":"Monroeville",
    "sg:classifiers":[
        {
            "category":"Shopping",
            "subcategory":"Computers & Home Electronics",
            "type":"Retail Goods"
        }
    ],
    "sg:phone":"+1   ",
    "sg:postcode":"15146",
    "sg:province":"PA",
    "sg:tags":[
        "software"
    ],
    "wof:name":"Gamestop",
    "wof:placetype":"venue"
},
  "geometry": {"coordinates":[-79.71016899999999,40.430249],"type":"Point"}
}