{
  "type": "Feature",
  "properties": {
    "iso:country":"US",
    "sg:address":"1000 Rohrerstown Rd",
    "sg:city":"Lancaster",
    "sg:classifiers":[
        {
            "category":"Autos & Motor Vehicles",
            "subcategory":"Automobile Sales",
            "type":"Retail Goods"
        }
    ],
    "sg:phone":"+1 800 573 0961",
    "sg:postcode":"17601",
    "sg:province":"PA",
    "sg:tags":[
        "dealers-used",
        "car",
        "used",
        "cars-wholesale",
        "new"
    ],
    "sg:website":"http://www.faulknerchevy.com",
    "wof:name":"Faulkner Chevrolet",
    "wof:placetype":"venue"
},
  "geometry": {"coordinates":[-76.359951,40.059425],"type":"Point"}
}