{
  "type": "Feature",
  "properties": {
    "addr:full":"939 Trimble Rd Trout Run PA 17771",
    "addr:housenumber":"939",
    "addr:postcode":"17771",
    "addr:street":"Trimble Rd",
    "iso:country":"US",
    "sg:address":"939 Trimble Rd",
    "sg:city":"Trout Run",
    "sg:classifiers":[
        {
            "category":"Farming",
            "subcategory":"Dairy Farm",
            "type":"Manufacturing & Wholesale Goods"
        }
    ],
    "sg:phone":"+1   ",
    "sg:postcode":"17771",
    "sg:province":"PA",
    "wof:name":"Jay Kreider",
    "wof:placetype":"venue"
},
  "geometry": {"coordinates":[-76.98964100000001,41.379647],"type":"Point"}
}