{
  "type": "Feature",
  "properties": {
    "addr:full":"412 Sunrise Ave Honesdale PA 18431",
    "addr:housenumber":"412",
    "addr:postcode":"18431",
    "addr:street":"Sunrise Ave",
    "iso:country":"US",
    "sg:address":"412 Sunrise Ave",
    "sg:city":"Honesdale",
    "sg:classifiers":[
        {
            "category":"Retail",
            "subcategory":"Auto Repair",
            "type":"Services"
        }
    ],
    "sg:phone":"+1   ",
    "sg:postcode":"18431",
    "sg:province":"PA",
    "sg:tags":[
        "automotive",
        "general"
    ],
    "wof:name":"Ryder",
    "wof:placetype":"venue"
},
  "geometry": {"coordinates":[-75.24971499999999,41.555127],"type":"Point"}
}