{
  "type": "Feature",
  "properties": {
    "iso:country":"US",
    "sg:address":"333 Rouser Rd",
    "sg:city":"Coraopolis",
    "sg:classifiers":[
        {
            "category":"Wholesale",
            "subcategory":"Metals & Minerals",
            "type":"Manufacturing & Wholesale Goods"
        }
    ],
    "sg:phone":"+1 412 264 8414",
    "sg:postcode":"15108",
    "sg:province":"PA",
    "sg:tags":[
        "steel",
        "warehouse"
    ],
    "wof:name":"Pinnacle Steel Resources",
    "wof:placetype":"venue"
},
  "geometry": {"coordinates":[-80.211196,40.501447],"type":"Point"}
}