{
  "type": "Feature",
  "properties": {
    "iso:country":"US",
    "sg:address":"1701 Farragut Ave",
    "sg:city":"Bristol",
    "sg:classifiers":[
        {
            "category":"Restaurant",
            "type":"Food & Drink"
        },
        {
            "category":"Food & Beverages",
            "subcategory":"Groceries & Convenience Stores",
            "type":"Retail Goods"
        }
    ],
    "sg:phone":"+1 215 788 0777",
    "sg:postcode":"19007",
    "sg:province":"PA",
    "sg:tags":[
        "shop",
        "sandwich"
    ],
    "wof:name":"Philly Phamous",
    "wof:placetype":"venue"
},
  "geometry": {"coordinates":[-74.843109,40.10648],"type":"Point"}
}