{
  "type": "Feature",
  "properties": {
    "iso:country":"US",
    "sg:address":"1295 N Providence Rd",
    "sg:city":"Media",
    "sg:classifiers":[
        {
            "category":"Real Estate",
            "subcategory":"Real Estate Operator",
            "type":"Services"
        }
    ],
    "sg:phone":"+1   ",
    "sg:postcode":"19063",
    "sg:province":"PA",
    "sg:tags":[
        "building",
        "apartment"
    ],
    "wof:name":"Westover Builders Inc",
    "wof:placetype":"venue"
},
  "geometry": {"coordinates":[-75.38993000000001,39.933672],"type":"Point"}
}