{
  "type": "Feature",
  "properties": {
    "addr:full":"1301 Wendover Rd Bryn Mawr PA 19010",
    "addr:housenumber":"1301",
    "addr:postcode":"19010",
    "addr:street":"Wendover Rd",
    "iso:country":"US",
    "sg:address":"1301 Wendover Rd",
    "sg:city":"Bryn Mawr",
    "sg:classifiers":[
        {
            "category":"Professional",
            "subcategory":"Management & Consulting",
            "type":"Services"
        }
    ],
    "sg:phone":"+1 610 525 7611",
    "sg:postcode":"19010",
    "sg:province":"PA",
    "sg:tags":[
        "international",
        "consultant"
    ],
    "wof:name":"International Business Assoc",
    "wof:placetype":"venue"
},
  "geometry": {"coordinates":[-75.32763799999999,40.031575],"type":"Point"}
}