{
  "type": "Feature",
  "properties": {
    "iso:country":"US",
    "sg:address":"15 Saint Albans Ave",
    "sg:city":"Newtown Square",
    "sg:classifiers":[
        {
            "category":"Health Services",
            "subcategory":"Health Practitioner",
            "type":"Services"
        }
    ],
    "sg:phone":"+1   ",
    "sg:postcode":"19073",
    "sg:province":"PA",
    "wof:name":"Pennsylvania Agency of Nurses",
    "wof:placetype":"venue"
},
  "geometry": {"coordinates":[-75.400437,39.989823],"type":"Point"}
}