{
  "type": "Feature",
  "properties": {
    "iso:country":"US",
    "sg:address":"1442 Pennsylvania Ave",
    "sg:city":"Pittsburgh",
    "sg:classifiers":[
        {
            "category":"Professional",
            "subcategory":"Lawyer & Legal Services",
            "type":"Services"
        }
    ],
    "sg:phone":"+1 412 322 9800",
    "sg:postcode":"15233",
    "sg:province":"PA",
    "wof:name":"Williams Joseph K III Attorney",
    "wof:placetype":"venue"
},
  "geometry": {"coordinates":[-80.028099,40.453899],"type":"Point"}
}