{
  "type": "Feature",
  "properties": {
    "addr:full":"6010 Cedarhurst St Philadelphia PA 19143",
    "addr:housenumber":"6010",
    "addr:postcode":"19143",
    "addr:street":"Cedarhurst St",
    "iso:country":"US",
    "sg:address":"6010 Cedarhurst St",
    "sg:city":"Philadelphia",
    "sg:classifiers":[
        {
            "category":"Social Services",
            "subcategory":"Child Care",
            "type":"Services"
        }
    ],
    "sg:phone":"+1 215 747 3498",
    "sg:postcode":"19143",
    "sg:province":"PA",
    "sg:tags":[
        "baby",
        "sitter"
    ],
    "wof:name":"Big Mom's Family Day Care",
    "wof:placetype":"venue"
},
  "geometry": {"coordinates":[-75.24326499999999,39.943976],"type":"Point"}
}