{
  "type": "Feature",
  "properties": {
    "iso:country":"US",
    "sg:address":"142 Reno St",
    "sg:city":"New Cumberland",
    "sg:classifiers":[
        {
            "category":"Wholesale",
            "subcategory":"Construction Materials",
            "type":"Manufacturing & Wholesale Goods"
        },
        {
            "category":"Home & Garden",
            "subcategory":"Building Materials",
            "type":"Retail Goods"
        }
    ],
    "sg:phone":"+1 717 774 8849",
    "sg:postcode":"17070",
    "sg:province":"PA",
    "sg:tags":[
        "door",
        "aluminum",
        "windows",
        "metal",
        "hollow",
        "wood",
        "vinyl"
    ],
    "wof:name":"Master Manufacturing Inds",
    "wof:placetype":"venue"
},
  "geometry": {"coordinates":[-76.862775,40.223563],"type":"Point"}
}