{
  "type": "Feature",
  "properties": {
    "iso:country":"US",
    "sg:address":"3008 New Butler Rd",
    "sg:city":"New Castle",
    "sg:classifiers":[
        {
            "category":"Retail",
            "subcategory":"Auto Repair",
            "type":"Services"
        }
    ],
    "sg:phone":"+1 724 924 1649",
    "sg:postcode":"16101",
    "sg:province":"PA",
    "sg:tags":[
        "recreational",
        "vehicle"
    ],
    "wof:name":"New Castle Truck",
    "wof:placetype":"venue"
},
  "geometry": {"coordinates":[-80.279636,40.975509],"type":"Point"}
}