{
  "type": "Feature",
  "properties": {
    "addr:full":"440 N Reading Rd Ephrata PA 17522",
    "addr:housenumber":"440",
    "addr:postcode":"17522",
    "addr:street":"N Reading Rd",
    "iso:country":"US",
    "sg:address":"440 N Reading Rd",
    "sg:city":"Ephrata",
    "sg:classifiers":[
        {
            "category":"Freight",
            "type":"Transportation"
        }
    ],
    "sg:phone":"+1 717 733 8594",
    "sg:postcode":"17522",
    "sg:province":"PA",
    "sg:tags":[
        "hauling",
        "trucking"
    ],
    "sg:website":"www.eliteattitude.com",
    "wof:name":"Elite Service",
    "wof:placetype":"venue"
},
  "geometry": {"coordinates":[-76.17104500000001,40.195442],"type":"Point"}
}