{
  "type": "Feature",
  "properties": {
    "iso:country":"US",
    "sg:address":"75 W Broad St",
    "sg:city":"Hatfield",
    "sg:classifiers":[
        {
            "category":"Organizations",
            "subcategory":"Religious Organization",
            "type":"Services"
        }
    ],
    "sg:phone":"+1 215 855 2449",
    "sg:postcode":"19440",
    "sg:province":"PA",
    "sg:website":"www.bethanybfc.org",
    "wof:name":"Bethany Bible Fellowship Church",
    "wof:placetype":"venue"
},
  "geometry": {"coordinates":[-75.30090300000001,40.278198],"type":"Point"}
}