{
  "type": "Feature",
  "properties": {
    "iso:country":"US",
    "sg:address":"305 Salt St",
    "sg:city":"Saltsburg",
    "sg:classifiers":[
        {
            "category":"Professional",
            "subcategory":"Business Services",
            "type":"Services"
        }
    ],
    "sg:phone":"+1   ",
    "sg:postcode":"15681",
    "sg:province":"PA",
    "wof:name":"Saltsburg Notary Service",
    "wof:placetype":"venue"
},
  "geometry": {"coordinates":[-79.450935,40.488661],"type":"Point"}
}