{
  "type": "Feature",
  "properties": {
    "iso:country":"US",
    "sg:address":"1079 West Ave",
    "sg:city":"Springfield",
    "sg:classifiers":[
        {
            "category":"Arts & Performance",
            "subcategory":"Arts Center",
            "type":"Entertainment"
        },
        {
            "category":"Building & Trades",
            "subcategory":"Cleaning & Sanitation",
            "type":"Services"
        },
        {
            "category":"Professional",
            "subcategory":"Art Services",
            "type":"Services"
        },
        {
            "category":"Building & Trades",
            "subcategory":"Construction",
            "type":"Services"
        }
    ],
    "sg:phone":"+1 866 797 9350",
    "sg:postcode":"19064",
    "sg:province":"PA",
    "sg:tags":[
        "roofing",
        "washing",
        "power",
        "handyman",
        "contractor",
        "faux",
        "finishing",
        "hand",
        "painting",
        "decorating"
    ],
    "wof:name":"Milt Hendrick Painting",
    "wof:placetype":"venue"
},
  "geometry": {"coordinates":[-75.322177,39.915332],"type":"Point"}
}