{
  "type": "Feature",
  "properties": {
    "iso:country":"US",
    "sg:address":"6 S Main St",
    "sg:city":"Coopersburg",
    "sg:classifiers":[
        {
            "category":"Government",
            "subcategory":"Fire Station",
            "type":"Public Place"
        }
    ],
    "sg:phone":"+1   ",
    "sg:postcode":"18036",
    "sg:province":"PA",
    "sg:tags":[
        "protection"
    ],
    "wof:name":"Coopersberg Fire Co",
    "wof:placetype":"venue"
},
  "geometry": {"coordinates":[-75.391336,40.510951],"type":"Point"}
}