{
  "type": "Feature",
  "properties": {
    "iso:country":"US",
    "sg:address":"2530 W Chester Pike",
    "sg:city":"Broomall",
    "sg:classifiers":[
        {
            "category":"Shopping",
            "subcategory":"Pharmacy",
            "type":"Retail Goods"
        }
    ],
    "sg:phone":"+1 610 356 6491",
    "sg:postcode":"19008",
    "sg:province":"PA",
    "sg:tags":[
        "equipment",
        "medical",
        "rental"
    ],
    "wof:name":"Mel's Marple Pharmacy",
    "wof:placetype":"venue"
},
  "geometry": {"coordinates":[-75.35839,39.981322],"type":"Point"}
}