{
  "type": "Feature",
  "properties": {
    "iso:country":"US",
    "sg:address":"1503 Potomac Ave",
    "sg:city":"Pittsburgh",
    "sg:classifiers":[
        {
            "category":"Health Services",
            "subcategory":"Doctor",
            "type":"Services"
        }
    ],
    "sg:phone":"+1 412 563 1611",
    "sg:postcode":"15216",
    "sg:province":"PA",
    "sg:tags":[
        "dentist",
        "dental"
    ],
    "wof:name":"Mecs Andras DMD Ofc",
    "wof:placetype":"venue"
},
  "geometry": {"coordinates":[-80.035599,40.396599],"type":"Point"}
}