{
  "type": "Feature",
  "properties": {
    "iso:country":"US",
    "sg:address":"1 S Main St",
    "sg:city":"Wilkes Barre",
    "sg:classifiers":[
        {
            "category":"Travel",
            "subcategory":"Travel Agent",
            "type":"Entertainment"
        }
    ],
    "sg:phone":"+1 570 208 1000",
    "sg:postcode":"18701",
    "sg:province":"PA",
    "sg:tags":[
        "agency"
    ],
    "wof:name":"Vacation Station",
    "wof:placetype":"venue"
},
  "geometry": {"coordinates":[-75.884901,41.244198],"type":"Point"}
}