{
  "type": "Feature",
  "properties": {
    "iso:country":"US",
    "sg:address":"330 Main Rd",
    "sg:city":"Pitman",
    "sg:phone":"+1   ",
    "sg:postcode":"17964",
    "sg:province":"PA",
    "sg:tags":[
        "farm",
        "irish",
        "wheat",
        "corn",
        "potato"
    ],
    "wof:name":"Tim Joy Farms",
    "wof:placetype":"venue"
},
  "geometry": {"coordinates":[-76.54071399999999,40.713267],"type":"Point"}
}