{
  "type": "Feature",
  "properties": {
    "iso:country":"US",
    "sg:address":"161 Trego Rd",
    "sg:city":"Glenmoore",
    "sg:classifiers":[
        {
            "category":"Farming",
            "subcategory":"Farm",
            "type":"Manufacturing & Wholesale Goods"
        }
    ],
    "sg:phone":"+1   ",
    "sg:postcode":"19343",
    "sg:province":"PA",
    "sg:tags":[
        "crop",
        "general"
    ],
    "wof:name":"Merrythought Farm Inc",
    "wof:placetype":"venue"
},
  "geometry": {"coordinates":[-75.704947,40.12412],"type":"Point"}
}