{
  "type": "Feature",
  "properties": {
    "iso:country":"US",
    "sg:address":"538 Putnam St",
    "sg:city":"West Hazleton",
    "sg:classifiers":[
        {
            "category":"Building & Trades",
            "subcategory":"Construction",
            "type":"Services"
        }
    ],
    "sg:phone":"+1 570 454 0744",
    "sg:postcode":"18202",
    "sg:province":"PA",
    "sg:tags":[
        "excavating",
        "contractor"
    ],
    "wof:name":"Piacenti Trucking & Excavating",
    "wof:placetype":"venue"
},
  "geometry": {"coordinates":[-75.99628199999999,40.966308],"type":"Point"}
}