{
  "type": "Feature",
  "properties": {
    "iso:country":"US",
    "sg:address":"1116 Marfield Dr",
    "sg:city":"Nazareth",
    "sg:classifiers":[
        {
            "category":"Professional",
            "subcategory":"Management & Consulting",
            "type":"Services"
        }
    ],
    "sg:phone":"+1   ",
    "sg:postcode":"18064",
    "sg:province":"PA",
    "sg:tags":[
        "consultation",
        "business"
    ],
    "wof:name":"Marketingprosecom Incorporated",
    "wof:placetype":"venue"
},
  "geometry": {"coordinates":[-75.33612100000001,40.80306],"type":"Point"}
}