{
  "type": "Feature",
  "properties": {
    "iso:country":"US",
    "sg:address":"65 Dallas Shopping Center",
    "sg:city":"Dallas",
    "sg:classifiers":[
        {
            "category":"Wholesale",
            "subcategory":"Beer",
            "type":"Manufacturing & Wholesale Goods"
        }
    ],
    "sg:phone":"+1 570 675 0110",
    "sg:postcode":"18612",
    "sg:province":"PA",
    "sg:tags":[
        "ale"
    ],
    "wof:name":"KERN Brothers",
    "wof:placetype":"venue"
},
  "geometry": {"coordinates":[-75.954977,41.334186],"type":"Point"}
}