{
  "type": "Feature",
  "properties": {
    "iso:country":"US",
    "sg:address":"708 Philadelphia Ave",
    "sg:city":"Chambersburg",
    "sg:classifiers":[
        {
            "category":"Shopping",
            "subcategory":"Computers & Home Electronics",
            "type":"Retail Goods"
        }
    ],
    "sg:phone":"+1 717 267 2554",
    "sg:postcode":"17201",
    "sg:province":"PA",
    "sg:tags":[
        "equipment"
    ],
    "sg:website":"http://www.cashcard.net",
    "wof:name":"Web-Creditcard",
    "wof:placetype":"venue"
},
  "geometry": {"coordinates":[-77.655312,39.945498],"type":"Point"}
}