{
  "type": "Feature",
  "properties": {
    "iso:country":"US",
    "sg:address":"717 Northampton St",
    "sg:city":"Easton",
    "sg:classifiers":[
        {
            "category":"Shopping",
            "subcategory":"Optical Goods",
            "type":"Retail Goods"
        }
    ],
    "sg:phone":"+1   ",
    "sg:postcode":"18042",
    "sg:province":"PA",
    "wof:name":"Denaldi Eyewear Inc",
    "wof:placetype":"venue"
},
  "geometry": {"coordinates":[-75.21938400000001,40.69081],"type":"Point"}
}