{
  "type": "Feature",
  "properties": {
    "iso:country":"US",
    "sg:address":"112 S Dawes Ave",
    "sg:city":"Kingston",
    "sg:classifiers":[
        {
            "category":"Professional",
            "subcategory":"Accounting & Tax Preparation",
            "type":"Services"
        }
    ],
    "sg:phone":"+1 570 287 2793",
    "sg:postcode":"18704",
    "sg:province":"PA",
    "sg:tags":[
        "accountant"
    ],
    "wof:name":"John Kotch CPA",
    "wof:placetype":"venue"
},
  "geometry": {"coordinates":[-75.88475,41.253587],"type":"Point"}
}