{
  "type": "Feature",
  "properties": {
    "addr:full":"1212 W Sunbury Rd West Sunbury PA 16061",
    "addr:housenumber":"1212",
    "addr:postcode":"16061",
    "addr:street":"W Sunbury Rd",
    "iso:country":"US",
    "sg:address":"1212 W Sunbury Rd",
    "sg:city":"West Sunbury",
    "sg:classifiers":[
        {
            "category":"Insurance",
            "subcategory":"Insurance Agent",
            "type":"Services"
        }
    ],
    "sg:phone":"+1 724 637 2300",
    "sg:postcode":"16061",
    "sg:province":"PA",
    "wof:name":"Eshenbaugh Insurance Agency",
    "wof:placetype":"venue"
},
  "geometry": {"coordinates":[-79.89757,40.998433],"type":"Point"}
}