{
  "type": "Feature",
  "properties": {
    "addr:full":"7331 Rising Sun Ave Philadelphia PA 19111",
    "addr:housenumber":"7331",
    "addr:postcode":"19111",
    "addr:street":"Rising Sun Ave",
    "iso:country":"US",
    "sg:address":"7331 Rising Sun Ave",
    "sg:city":"Philadelphia",
    "sg:classifiers":[
        {
            "category":"Shopping",
            "type":"Retail Goods"
        }
    ],
    "sg:phone":"+1 215 742 2105",
    "sg:postcode":"19111",
    "sg:province":"PA",
    "sg:tags":[
        "merchandise"
    ],
    "wof:name":"Joe Long Awards",
    "wof:placetype":"venue"
},
  "geometry": {"coordinates":[-75.083547,40.061657],"type":"Point"}
}