{
  "type": "Feature",
  "properties": {
    "iso:country":"US",
    "sg:address":"1 S Morton Ave",
    "sg:city":"Morton",
    "sg:classifiers":[
        {
            "category":"Personal",
            "type":"Services"
        }
    ],
    "sg:phone":"+1 610 604 1550",
    "sg:postcode":"19070",
    "sg:province":"PA",
    "sg:tags":[
        "wear",
        "formal"
    ],
    "wof:name":"D L Iacobucci Inc Tuxedo Rntl",
    "wof:placetype":"venue"
},
  "geometry": {"coordinates":[-75.32749,39.908201],"type":"Point"}
}