{
  "type": "Feature",
  "properties": {
    "iso:country":"US",
    "sg:address":"116 E 2nd Ave",
    "sg:city":"Derry",
    "sg:classifiers":[
        {
            "category":"Government",
            "subcategory":"Fire Station",
            "type":"Public Place"
        }
    ],
    "sg:phone":"+1   ",
    "sg:postcode":"15627",
    "sg:province":"PA",
    "sg:tags":[
        "protection"
    ],
    "wof:name":"Derry Volunteer Fire Co",
    "wof:placetype":"venue"
},
  "geometry": {"coordinates":[-79.298115,40.333796],"type":"Point"}
}