{
  "type": "Feature",
  "properties": {
    "iso:country":"US",
    "sg:address":"66 Kimberly Dr",
    "sg:city":"Hanover",
    "sg:classifiers":[
        {
            "category":"Building & Trades",
            "subcategory":"Construction",
            "type":"Services"
        }
    ],
    "sg:phone":"+1 717 646 9029",
    "sg:postcode":"17331",
    "sg:province":"PA",
    "sg:tags":[
        "mason",
        "masonry",
        "industrial",
        "contractors-commercial",
        "contractor"
    ],
    "wof:name":"Marchio Masonry",
    "wof:placetype":"venue"
},
  "geometry": {"coordinates":[-76.965226,39.766679],"type":"Point"}
}