{
  "type": "Feature",
  "properties": {
    "iso:country":"US",
    "sg:address":"2244 W 38th St",
    "sg:city":"Erie",
    "sg:classifiers":[
        {
            "category":"Insurance",
            "subcategory":"Insurance Agent",
            "type":"Services"
        }
    ],
    "sg:phone":"+1 814 838 9650",
    "sg:postcode":"16506",
    "sg:province":"PA",
    "wof:name":"State Farm Insurance",
    "wof:placetype":"venue"
},
  "geometry": {"coordinates":[-80.11847,42.083078],"type":"Point"}
}