{
  "type": "Feature",
  "properties": {
    "iso:country":"US",
    "sg:address":"124 Main St",
    "sg:city":"Greenville",
    "sg:classifiers":[
        {
            "category":"Autos & Motor Vehicles",
            "subcategory":"Automobile Sales",
            "type":"Retail Goods"
        },
        {
            "category":"Retail",
            "subcategory":"Auto Repair",
            "type":"Services"
        }
    ],
    "sg:phone":"+1 724 588 1500",
    "sg:postcode":"16125",
    "sg:province":"PA",
    "sg:tags":[
        "a",
        "body",
        "used",
        "painting",
        "general"
    ],
    "sg:website":"www.philgodfreyford.com",
    "wof:name":"Phil Godfrey Ford-Mercury",
    "wof:placetype":"venue"
},
  "geometry": {"coordinates":[-80.390669,41.404575],"type":"Point"}
}