{
  "type": "Feature",
  "properties": {
    "addr:full":"1375 Friedensburg Rd Reading PA 19606",
    "addr:housenumber":"1375",
    "addr:postcode":"19606",
    "addr:street":"Friedensburg Rd",
    "iso:country":"US",
    "sg:address":"1375 Friedensburg Rd",
    "sg:city":"Reading",
    "sg:classifiers":[
        {
            "category":"Organizations",
            "subcategory":"Religious Organization",
            "type":"Services"
        }
    ],
    "sg:phone":"+1   ",
    "sg:postcode":"19606",
    "sg:province":"PA",
    "wof:name":"Bethany Evang Lutheran Church",
    "wof:placetype":"venue"
},
  "geometry": {"coordinates":[-75.873628,40.3457],"type":"Point"}
}