{
  "type": "Feature",
  "properties": {
    "iso:country":"US",
    "sg:address":"841 Vogelsong Rd",
    "sg:city":"York",
    "sg:classifiers":[
        {
            "category":"Professional",
            "subcategory":"Employment Agencies",
            "type":"Services"
        }
    ],
    "sg:phone":"+1   ",
    "sg:postcode":"17404",
    "sg:province":"PA",
    "sg:tags":[
        "temporary",
        "help"
    ],
    "wof:name":"Aerotek Inc",
    "wof:placetype":"venue"
},
  "geometry": {"coordinates":[-76.754244,39.982545],"type":"Point"}
}