{
  "type": "Feature",
  "properties": {
    "iso:country":"US",
    "sg:address":"5452 Rosetta St",
    "sg:city":"Pittsburgh",
    "sg:classifiers":[
        {
            "category":"Building & Trades",
            "subcategory":"Electrical",
            "type":"Services"
        }
    ],
    "sg:phone":"+1   ",
    "sg:postcode":"15206",
    "sg:province":"PA",
    "sg:tags":[
        "electrical",
        "contractor"
    ],
    "wof:name":"Arthur L Burt Electric",
    "wof:placetype":"venue"
},
  "geometry": {"coordinates":[-79.932076,40.466403],"type":"Point"}
}