{
  "type": "Feature",
  "properties": {
    "iso:country":"US",
    "sg:address":"100 W Lancaster Ave",
    "sg:city":"Ardmore",
    "sg:classifiers":[
        {
            "category":"Building & Trades",
            "subcategory":"Construction",
            "type":"Services"
        }
    ],
    "sg:phone":"+1 610 658 1940",
    "sg:postcode":"19003",
    "sg:province":"PA",
    "sg:tags":[
        "floor",
        "laying",
        "contractor"
    ],
    "wof:name":"Ardmore Hardwood Floors",
    "wof:placetype":"venue"
},
  "geometry": {"coordinates":[-75.295174,40.010003],"type":"Point"}
}