{
  "type": "Feature",
  "properties": {
    "addr:full":"1387 Mohawk Ln Easton PA 18040",
    "addr:housenumber":"1387",
    "addr:postcode":"18040",
    "addr:street":"Mohawk Ln",
    "iso:country":"US",
    "sg:address":"1387 Mohawk Ln",
    "sg:city":"Easton",
    "sg:classifiers":[
        {
            "category":"Insurance",
            "subcategory":"Hazard Insurance",
            "type":"Services"
        }
    ],
    "sg:phone":"+1 610 559 9001",
    "sg:postcode":"18040",
    "sg:province":"PA",
    "sg:tags":[
        "commercial",
        "business"
    ],
    "wof:name":"Jam Family Ventures",
    "wof:placetype":"venue"
},
  "geometry": {"coordinates":[-75.23157,40.70992],"type":"Point"}
}