{
  "type": "Feature",
  "properties": {
    "iso:country":"US",
    "sg:address":"2083 N Oak Ln",
    "sg:city":"State College",
    "sg:classifiers":[
        {
            "category":"Insurance",
            "subcategory":"Insurance Agent",
            "type":"Services"
        }
    ],
    "sg:phone":"+1 814 238 6633",
    "sg:postcode":"16803",
    "sg:province":"PA",
    "wof:name":"ARLAN Temeles Insurance",
    "wof:placetype":"venue"
},
  "geometry": {"coordinates":[-77.91718,40.806579],"type":"Point"}
}