{
  "type": "Feature",
  "properties": {
    "iso:country":"US",
    "sg:address":"348 Budfield St",
    "sg:city":"Johnstown",
    "sg:classifiers":[
        {
            "category":"Health Services",
            "subcategory":"Doctor",
            "type":"Services"
        }
    ],
    "sg:phone":"+1 814 266 4102",
    "sg:postcode":"15904",
    "sg:province":"PA",
    "wof:name":"Womancare Imaging At UPMC",
    "wof:placetype":"venue"
},
  "geometry": {"coordinates":[-78.84680899999999,40.270223],"type":"Point"}
}