{
  "type": "Feature",
  "properties": {
    "iso:country":"US",
    "sg:address":"2409 Market St",
    "sg:city":"Harrisburg",
    "sg:classifiers":[
        {
            "category":"Wholesale",
            "subcategory":"Construction Materials",
            "type":"Manufacturing & Wholesale Goods"
        }
    ],
    "sg:phone":"+1 717 236 6655",
    "sg:postcode":"17103",
    "sg:province":"PA",
    "sg:tags":[
        "control",
        "manufacturer",
        "system",
        "controls",
        "regulators-wholesale"
    ],
    "wof:name":"Andrea Sullivan",
    "wof:placetype":"venue"
},
  "geometry": {"coordinates":[-76.84925800000001,40.271629],"type":"Point"}
}