{
  "type": "Feature",
  "properties": {
    "iso:country":"US",
    "sg:address":"6 Beaver Rd",
    "sg:city":"Jeannette",
    "sg:classifiers":[
        {
            "category":"Health Services",
            "subcategory":"Chiropractor",
            "type":"Services"
        }
    ],
    "sg:phone":"+1 724 523 4856",
    "sg:postcode":"15644",
    "sg:province":"PA",
    "wof:name":"John R Dent DC",
    "wof:placetype":"venue"
},
  "geometry": {"coordinates":[-79.61882900000001,40.309654],"type":"Point"}
}