{
  "type": "Feature",
  "properties": {
    "addr:full":"5895 Wilson Dr Bethel Park PA 15102",
    "addr:housenumber":"5895",
    "addr:postcode":"15102",
    "addr:street":"Wilson Dr",
    "iso:country":"US",
    "sg:address":"5895 Wilson Dr",
    "sg:city":"Bethel Park",
    "sg:classifiers":[
        {
            "category":"Personal",
            "type":"Services"
        }
    ],
    "sg:phone":"+1 412 854 0878",
    "sg:postcode":"15102",
    "sg:province":"PA",
    "sg:tags":[
        "consultant",
        "wedding"
    ],
    "wof:name":"Buchwald Photography",
    "wof:placetype":"venue"
},
  "geometry": {"coordinates":[-80.039925,40.307895],"type":"Point"}
}