{
  "type": "Feature",
  "properties": {
    "iso:country":"US",
    "sg:address":"9000 Gateway Campus Blvd",
    "sg:city":"Monroeville",
    "sg:classifiers":[
        {
            "category":"Education",
            "subcategory":"School",
            "type":"Public Place"
        }
    ],
    "sg:phone":"+1   ",
    "sg:postcode":"15146",
    "sg:province":"PA",
    "wof:name":"Unverisal Park Elementary",
    "wof:placetype":"venue"
},
  "geometry": {"coordinates":[-79.757187,40.429362],"type":"Point"}
}