{
  "type": "Feature",
  "properties": {
    "iso:country":"US",
    "sg:address":"1724 Lincoln Hwy",
    "sg:city":"North Versailles",
    "sg:classifiers":[
        {
            "category":"Personal",
            "subcategory":"Beauty Salon",
            "type":"Services"
        }
    ],
    "sg:phone":"+1 412 824 5303",
    "sg:postcode":"15137",
    "sg:province":"PA",
    "wof:name":"Mediate's Styling Ctr",
    "wof:placetype":"venue"
},
  "geometry": {"coordinates":[-79.785856,40.370246],"type":"Point"}
}