{
  "type": "Feature",
  "properties": {
    "iso:country":"US",
    "sg:address":"3430 Pheasant Chase",
    "sg:city":"Hermitage",
    "sg:classifiers":[
        {
            "category":"Freight",
            "type":"Transportation"
        }
    ],
    "sg:phone":"+1   ",
    "sg:postcode":"16148",
    "sg:province":"PA",
    "sg:tags":[
        "local",
        "storage",
        "trucking"
    ],
    "wof:name":"Chadderton & Trucking Inc",
    "wof:placetype":"venue"
},
  "geometry": {"coordinates":[-80.445611,41.251401],"type":"Point"}
}