{
  "type": "Feature",
  "properties": {
    "iso:country":"US",
    "sg:address":"3364 Scranton Carbondale Hwy",
    "sg:city":"Olyphant",
    "sg:phone":"+1 570 489 4961",
    "sg:postcode":"18447",
    "sg:province":"PA",
    "sg:website":"http://WWW.PeckvilleAG.org",
    "wof:name":"Peckville Assembly of God",
    "wof:placetype":"venue"
},
  "geometry": {"coordinates":[-75.594269,41.456919],"type":"Point"}
}