{
  "type": "Feature",
  "properties": {
    "addr:full":"101 N Main St Shenandoah PA 17976",
    "addr:housenumber":"101",
    "addr:postcode":"17976",
    "addr:street":"N Main St",
    "iso:country":"US",
    "sg:address":"101 N Main St",
    "sg:city":"Shenandoah",
    "sg:classifiers":[
        {
            "category":"Banks & Credit Unions",
            "subcategory":"Bank",
            "type":"Services"
        }
    ],
    "sg:phone":"+1 570 462 1983",
    "sg:postcode":"17976",
    "sg:province":"PA",
    "sg:tags":[
        "state"
    ],
    "wof:name":"Legacy Bank",
    "wof:placetype":"venue"
},
  "geometry": {"coordinates":[-76.201718,40.82243],"type":"Point"}
}