{
  "type": "Feature",
  "properties": {
    "addr:full":"4341 Lycoming Creek Rd Cogan Station PA 17728",
    "addr:housenumber":"4341",
    "addr:postcode":"17728",
    "addr:street":"Lycoming Creek Rd Cogan Station",
    "iso:country":"US",
    "sg:address":"4341 Lycoming Creek Rd",
    "sg:city":"Cogan Station",
    "sg:classifiers":[
        {
            "category":"Autos & Motor Vehicles",
            "subcategory":"Auto Supplies",
            "type":"Retail Goods"
        }
    ],
    "sg:phone":"+1 570 494 0870",
    "sg:postcode":"17728",
    "sg:province":"PA",
    "sg:tags":[
        "tire"
    ],
    "wof:name":"Bill's Tire Shop",
    "wof:placetype":"venue"
},
  "geometry": {"coordinates":[-77.06961699999999,41.308293],"type":"Point"}
}