{
  "type": "Feature",
  "properties": {
    "iso:country":"US",
    "sg:address":"214 N 2nd St",
    "sg:city":"Clearfield",
    "sg:classifiers":[
        {
            "category":"Banks & Credit Unions",
            "subcategory":"Bank",
            "type":"Services"
        }
    ],
    "sg:phone":"+1   ",
    "sg:postcode":"16830",
    "sg:province":"PA",
    "sg:tags":[
        "state"
    ],
    "wof:name":"Clearfeld Stnwrkers Fdral Cr U",
    "wof:placetype":"venue"
},
  "geometry": {"coordinates":[-78.43809400000001,41.02484],"type":"Point"}
}