{
  "type": "Feature",
  "properties": {
    "iso:country":"US",
    "sg:address":"15 E Allen St",
    "sg:city":"Mechanicsburg",
    "sg:classifiers":[
        {
            "category":"Building & Trades",
            "subcategory":"Plumbing",
            "type":"Services"
        }
    ],
    "sg:phone":"+1 717 697 5464",
    "sg:postcode":"17055",
    "sg:province":"PA",
    "sg:tags":[
        "plumbing",
        "contractor"
    ],
    "wof:name":"Heffelbower's Plumbing & Htg",
    "wof:placetype":"venue"
},
  "geometry": {"coordinates":[-77.008334,40.214614],"type":"Point"}
}