{
  "type": "Feature",
  "properties": {
    "iso:country":"US",
    "sg:address":"5506 Woods Dr",
    "sg:city":"Edinboro",
    "sg:classifiers":[
        {
            "category":"Professional",
            "type":"Services"
        }
    ],
    "sg:phone":"+1   ",
    "sg:postcode":"16412",
    "sg:province":"PA",
    "wof:name":"Darrell E Stoner",
    "wof:placetype":"venue"
},
  "geometry": {"coordinates":[-80.153278,41.896249],"type":"Point"}
}