{
  "type": "Feature",
  "properties": {
    "iso:country":"US",
    "sg:address":"624 Baltimore Pike",
    "sg:city":"Springfield",
    "sg:classifiers":[
        {
            "category":"Travel",
            "subcategory":"Travel Agent",
            "type":"Entertainment"
        }
    ],
    "sg:phone":"+1 610 544 6222",
    "sg:postcode":"19064",
    "sg:province":"PA",
    "sg:tags":[
        "agency",
        "tours",
        "promoter"
    ],
    "wof:name":"Touriffic Travel Inc",
    "wof:placetype":"venue"
},
  "geometry": {"coordinates":[-75.326527,39.919721],"type":"Point"}
}