{
  "type": "Feature",
  "properties": {
    "iso:country":"US",
    "sg:address":"2420 MacArthur Rd",
    "sg:city":"Whitehall",
    "sg:classifiers":[
        {
            "category":"Shopping",
            "subcategory":"Clothing, Apparel, & Fashions",
            "type":"Retail Goods"
        },
        {
            "category":"Shopping",
            "subcategory":"Hobbies, Toys, & Games",
            "type":"Retail Goods"
        }
    ],
    "sg:phone":"+1 610 435 7450",
    "sg:postcode":"18052",
    "sg:province":"PA",
    "sg:tags":[
        "toy",
        "maternity",
        "wear",
        "store"
    ],
    "sg:website":"www.rbbk.com",
    "wof:name":"Rock-A-Bye Baby",
    "wof:placetype":"venue"
},
  "geometry": {"coordinates":[-75.490799,40.642502],"type":"Point"}
}