{
  "type": "Feature",
  "properties": {
    "addr:full":"1240 Washington Rd Pittsburgh PA 15228",
    "addr:housenumber":"1240",
    "addr:postcode":"15228",
    "addr:street":"Washington Rd",
    "iso:country":"US",
    "sg:address":"1240 Washington Rd",
    "sg:city":"Pittsburgh",
    "sg:classifiers":[
        {
            "category":"Organizations",
            "subcategory":"Religious Organization",
            "type":"Services"
        }
    ],
    "sg:phone":"+1 412 561 6277",
    "sg:postcode":"15228",
    "sg:province":"PA",
    "sg:tags":[
        "church"
    ],
    "wof:name":"Unitarian Universalist Church",
    "wof:placetype":"venue"
},
  "geometry": {"coordinates":[-80.04854899999999,40.365957],"type":"Point"}
}