{
  "type": "Feature",
  "properties": {
    "addr:full":"502 Eden Park Blvd Mckeesport PA 15132",
    "addr:housenumber":"502",
    "addr:postcode":"15132",
    "addr:street":"Eden Park Blvd",
    "iso:country":"US",
    "sg:address":"502 Eden Park Blvd",
    "sg:city":"Mckeesport",
    "sg:classifiers":[
        {
            "category":"Bars & Pubs",
            "type":"Food & Drink"
        }
    ],
    "sg:phone":"+1 412 751 3285",
    "sg:postcode":"15132",
    "sg:province":"PA",
    "sg:tags":[
        "drinking"
    ],
    "wof:name":"Mellon's Pub",
    "wof:placetype":"venue"
},
  "geometry": {"coordinates":[-79.833331,40.329711],"type":"Point"}
}