{
  "type": "Feature",
  "properties": {
    "addr:full":"1212 Montier St Pittsburgh PA 15221",
    "addr:housenumber":"1212",
    "addr:postcode":"15221",
    "addr:street":"Montier St",
    "iso:country":"US",
    "sg:address":"1212 Montier St",
    "sg:city":"Pittsburgh",
    "sg:classifiers":[
        {
            "category":"Retail",
            "subcategory":"Auto Repair",
            "type":"Services"
        }
    ],
    "sg:phone":"+1 412 244 9547",
    "sg:postcode":"15221",
    "sg:province":"PA",
    "sg:tags":[
        "repairing",
        "automobile"
    ],
    "wof:name":"Belmont Auto Svc",
    "wof:placetype":"venue"
},
  "geometry": {"coordinates":[-79.875152,40.443222],"type":"Point"}
}