{
  "type": "Feature",
  "properties": {
    "iso:country":"US",
    "sg:address":"839 E Lutton St",
    "sg:city":"New Castle",
    "sg:classifiers":[
        {
            "category":"Shopping",
            "subcategory":"Gifts & Souvenirs",
            "type":"Retail Goods"
        }
    ],
    "sg:phone":"+1 724 652 4106",
    "sg:postcode":"16101",
    "sg:province":"PA",
    "sg:tags":[
        "novelty"
    ],
    "wof:name":"Ed's Enjoyables",
    "wof:placetype":"venue"
},
  "geometry": {"coordinates":[-80.33035099999999,40.990499],"type":"Point"}
}