{
  "type": "Feature",
  "properties": {
    "addr:full":"135 N Reading Ave Boyertown PA 19512",
    "addr:housenumber":"135",
    "addr:postcode":"19512",
    "addr:street":"N Reading Ave",
    "iso:country":"US",
    "sg:address":"135 N Reading Ave",
    "sg:city":"Boyertown",
    "sg:classifiers":[
        {
            "category":"Health Services",
            "subcategory":"Optometrist",
            "type":"Services"
        }
    ],
    "sg:phone":"+1   ",
    "sg:postcode":"19512",
    "sg:province":"PA",
    "wof:name":"Edward Furman Od",
    "wof:placetype":"venue"
},
  "geometry": {"coordinates":[-75.63508400000001,40.336007],"type":"Point"}
}