{
  "type": "Feature",
  "properties": {
    "iso:country":"US",
    "sg:address":"333 N 8th St",
    "sg:city":"Reading",
    "sg:classifiers":[
        {
            "category":"Autos & Motor Vehicles",
            "subcategory":"Automobile Sales",
            "type":"Retail Goods"
        }
    ],
    "sg:phone":"+1   ",
    "sg:postcode":"19601",
    "sg:province":"PA",
    "sg:tags":[
        "used"
    ],
    "wof:name":"XEL Auto Sales & Service",
    "wof:placetype":"venue"
},
  "geometry": {"coordinates":[-75.92178800000001,40.340936],"type":"Point"}
}