{
  "type": "Feature",
  "properties": {
    "iso:country":"US",
    "sg:address":"555 Hulton Rd",
    "sg:city":"New Kensington",
    "sg:classifiers":[
        {
            "category":"Building & Trades",
            "subcategory":"Construction",
            "type":"Services"
        }
    ],
    "sg:phone":"+1   ",
    "sg:postcode":"15068",
    "sg:province":"PA",
    "sg:tags":[
        "contractor"
    ],
    "wof:name":"Pollick Masonry",
    "wof:placetype":"venue"
},
  "geometry": {"coordinates":[-79.68024,40.621353],"type":"Point"}
}