{
  "type": "Feature",
  "properties": {
    "addr:full":"2908 State Hill Rd Reading PA 19610",
    "addr:housenumber":"2908",
    "addr:postcode":"19610",
    "addr:street":"State Hill Rd",
    "iso:country":"US",
    "sg:address":"2908 State Hill Rd",
    "sg:city":"Reading",
    "sg:classifiers":[
        {
            "category":"Real Estate",
            "subcategory":"Real Estate Operator",
            "type":"Services"
        }
    ],
    "sg:phone":"+1 610 670 2520",
    "sg:postcode":"19610",
    "sg:province":"PA",
    "sg:tags":[
        "condominium"
    ],
    "wof:name":"Berkshire Estates Condos",
    "wof:placetype":"venue"
},
  "geometry": {"coordinates":[-75.994883,40.342839],"type":"Point"}
}