{
  "type": "Feature",
  "properties": {
    "iso:country":"US",
    "sg:address":"20 Depot St",
    "sg:city":"Lewistown",
    "sg:classifiers":[
        {
            "category":"Insurance",
            "subcategory":"Insurance Agent",
            "type":"Services"
        }
    ],
    "sg:phone":"+1 717 247 6291",
    "sg:postcode":"17044",
    "sg:province":"PA",
    "wof:name":"New York Ins Wade E Curry",
    "wof:placetype":"venue"
},
  "geometry": {"coordinates":[-77.568904,40.599525],"type":"Point"}
}