{
  "type": "Feature",
  "properties": {
    "iso:country":"US",
    "sg:address":"415 W 3rd St",
    "sg:city":"Williamsport",
    "sg:classifiers":[
        {
            "category":"Manufacturing",
            "subcategory":"Furniture",
            "type":"Manufacturing & Wholesale Goods"
        }
    ],
    "sg:phone":"+1 570 327 1500",
    "sg:postcode":"17701",
    "sg:province":"PA",
    "sg:website":"www.supplysource.info",
    "wof:name":"Supply Source Inc",
    "wof:placetype":"venue"
},
  "geometry": {"coordinates":[-77.010778,41.237952],"type":"Point"}
}