{
  "type": "Feature",
  "properties": {
    "iso:country":"US",
    "sg:address":"403 E Main St Suite B",
    "sg:city":"Hummelstown",
    "sg:classifiers":[
        {
            "category":"Banks & Credit Unions",
            "subcategory":"Investment Brokerage",
            "type":"Services"
        },
        {
            "category":"Banks & Credit Unions",
            "subcategory":"Bank",
            "type":"Services"
        },
        {
            "category":"Banks & Credit Unions",
            "subcategory":"Financial Services",
            "type":"Services"
        }
    ],
    "sg:phone":"+1 717 583 8884",
    "sg:postcode":"17036",
    "sg:province":"PA",
    "sg:tags":[
        "advisory",
        "mutual",
        "retirement",
        "annuity",
        "broker",
        "fund",
        "planning",
        "plan",
        "consultant",
        "security",
        "bond",
        "insurance",
        "stock"
    ],
    "sg:website":"http://edwardjones.com",
    "wof:name":"Edward Jones - MATTHEW L LOWRY",
    "wof:placetype":"venue"
},
  "geometry": {"coordinates":[-76.698527,40.265879],"type":"Point"}
}