{
  "type": "Feature",
  "properties": {
    "iso:country":"US",
    "sg:address":"2042 N Main St",
    "sg:city":"Punxsutawney",
    "sg:classifiers":[
        {
            "category":"Autos & Motor Vehicles",
            "subcategory":"Automobile Sales",
            "type":"Retail Goods"
        }
    ],
    "sg:phone":"+1 814 938 2520",
    "sg:postcode":"15767",
    "sg:province":"PA",
    "sg:tags":[
        "car",
        "dealer"
    ],
    "wof:name":"Anthony J Seliga Auto Sales",
    "wof:placetype":"venue"
},
  "geometry": {"coordinates":[-79.013363,40.971085],"type":"Point"}
}