{
  "type": "Feature",
  "properties": {
    "addr:full":"103 N Broadway Wind Gap PA 18091",
    "addr:housenumber":"103",
    "addr:postcode":"18091",
    "addr:street":"N Broadway;Gap",
    "iso:country":"US",
    "sg:address":"103 N Broadway",
    "sg:city":"Wind Gap",
    "sg:classifiers":[
        {
            "category":"Home & Garden",
            "subcategory":"Carpets & Floor Coverings",
            "type":"Retail Goods"
        }
    ],
    "sg:phone":"+1 610 863 8303",
    "sg:postcode":"18091",
    "sg:province":"PA",
    "sg:tags":[
        "dealer",
        "rug"
    ],
    "wof:name":"Reto's Paint Wallpaper Carpet",
    "wof:placetype":"venue"
},
  "geometry": {"coordinates":[-75.2914,40.851532],"type":"Point"}
}