{
  "type": "Feature",
  "properties": {
    "iso:country":"US",
    "sg:address":"6 S Bacton Hill Rd",
    "sg:city":"Malvern",
    "sg:classifiers":[
        {
            "category":"Manufacturing",
            "subcategory":"Tools & Machinery",
            "type":"Manufacturing & Wholesale Goods"
        }
    ],
    "sg:phone":"+1 610 644 3450",
    "sg:postcode":"19355",
    "sg:province":"PA",
    "sg:tags":[
        "springs-wholesale",
        "manufacturer"
    ],
    "wof:name":"James Spring & Wire Co",
    "wof:placetype":"venue"
},
  "geometry": {"coordinates":[-75.579053,40.042059],"type":"Point"}
}