{
  "type": "Feature",
  "properties": {
    "iso:country":"US",
    "sg:address":"17 Crailo Ave",
    "sg:city":"Pittsburgh",
    "sg:classifiers":[
        {
            "category":"Building & Trades",
            "subcategory":"Plumbing",
            "type":"Services"
        }
    ],
    "sg:phone":"+1   ",
    "sg:postcode":"15210",
    "sg:province":"PA",
    "sg:tags":[
        "contractor"
    ],
    "wof:name":"Daves Heating & A/C",
    "wof:placetype":"venue"
},
  "geometry": {"coordinates":[-79.98766500000001,40.396689],"type":"Point"}
}