{
  "type": "Feature",
  "properties": {
    "iso:country":"US",
    "sg:address":"3318 Rodney Dr",
    "sg:city":"Newtown Square",
    "sg:classifiers":[
        {
            "category":"Professional",
            "type":"Services"
        }
    ],
    "sg:phone":"+1   ",
    "sg:postcode":"19073",
    "sg:province":"PA",
    "wof:name":"Smith Thomas P Jr and John K S",
    "wof:placetype":"venue"
},
  "geometry": {"coordinates":[-75.38411600000001,39.985687],"type":"Point"}
}