{
  "type": "Feature",
  "properties": {
    "iso:country":"US",
    "sg:address":"1875 Franklin Mills Cir",
    "sg:city":"Philadelphia",
    "sg:classifiers":[
        {
            "category":"Shopping",
            "subcategory":"Clothing, Apparel, & Fashions",
            "type":"Retail Goods"
        }
    ],
    "sg:phone":"+1 215 612 8950",
    "sg:postcode":"19154",
    "sg:province":"PA",
    "sg:tags":[
        "accessory",
        "clothing",
        "women's"
    ],
    "sg:website":"www.bananarepublic.com",
    "wof:name":"Banana Republic",
    "wof:placetype":"venue"
},
  "geometry": {"coordinates":[-74.95760300000001,40.092999],"type":"Point"}
}