{
  "type": "Feature",
  "properties": {
    "addr:full":"116 E High St Bellefonte PA 16823",
    "addr:housenumber":"116",
    "addr:postcode":"16823",
    "addr:street":"E High St",
    "iso:country":"US",
    "sg:address":"116 E High St",
    "sg:city":"Bellefonte",
    "sg:classifiers":[
        {
            "category":"Cinema",
            "subcategory":"Movie Theater",
            "type":"Entertainment"
        }
    ],
    "sg:phone":"+1 814 353 8803",
    "sg:postcode":"16823",
    "sg:province":"PA",
    "wof:name":"Garman Opera House Theatre",
    "wof:placetype":"venue"
},
  "geometry": {"coordinates":[-77.777603,40.9118],"type":"Point"}
}