{
  "type": "Feature",
  "properties": {
    "iso:country":"US",
    "sg:address":"140 N Macdade Blvd",
    "sg:city":"Glenolden",
    "sg:classifiers":[
        {
            "category":"Restaurant",
            "type":"Food & Drink"
        }
    ],
    "sg:menulink":"http://www.allmenus.com/pa/glenolden/107128-soup-man/menu/",
    "sg:phone":"+1 610 522 1213",
    "sg:postcode":"19036",
    "sg:province":"PA",
    "sg:tags":[
        "soup",
        "american",
        "salad"
    ],
    "wof:name":"Soup Man",
    "wof:placetype":"venue"
},
  "geometry": {"coordinates":[-75.287701,39.907091],"type":"Point"}
}