{
  "type": "Feature",
  "properties": {
    "addr:full":"532 Christian St Philadelphia PA 19147",
    "addr:housenumber":"532",
    "addr:postcode":"19147",
    "addr:street":"Christian St",
    "iso:country":"US",
    "sg:address":"532 Christian St",
    "sg:city":"Philadelphia",
    "sg:classifiers":[
        {
            "category":"Building & Trades",
            "subcategory":"Construction",
            "type":"Services"
        }
    ],
    "sg:phone":"+1 215 465 0445",
    "sg:postcode":"19147",
    "sg:province":"PA",
    "sg:tags":[
        "home",
        "builder"
    ],
    "wof:name":"Sunshine Court",
    "wof:placetype":"venue"
},
  "geometry": {"coordinates":[-75.152928,39.937533],"type":"Point"}
}