{
  "type": "Feature",
  "properties": {
    "addr:full":"Great Southern Shopp Bridgeville PA 15017",
    "addr:postcode":"15017",
    "iso:country":"US",
    "sg:address":"Great Southern Shopp",
    "sg:city":"Bridgeville",
    "sg:classifiers":[
        {
            "category":"Shopping",
            "subcategory":"Shoes",
            "type":"Retail Goods"
        }
    ],
    "sg:phone":"+1 412 221 4460",
    "sg:postcode":"15017",
    "sg:province":"PA",
    "sg:tags":[
        "store"
    ],
    "sg:website":"www.payless.com",
    "wof:name":"Payless Shoes",
    "wof:placetype":"venue"
},
  "geometry": {"coordinates":[-80.121803,40.3395],"type":"Point"}
}