{
  "type": "Feature",
  "properties": {
    "iso:country":"US",
    "sg:address":"232 S George St",
    "sg:city":"York",
    "sg:classifiers":[
        {
            "category":"Government",
            "subcategory":"Court House",
            "type":"Public Place"
        }
    ],
    "sg:phone":"+1 717 771 4798",
    "sg:postcode":"17403",
    "sg:province":"PA",
    "sg:tags":[
        "county"
    ],
    "wof:name":"York County District Court",
    "wof:placetype":"venue"
},
  "geometry": {"coordinates":[-76.725917,39.959012],"type":"Point"}
}