{
  "type": "Feature",
  "properties": {
    "iso:country":"US",
    "sg:address":"638 N 66th St",
    "sg:city":"Philadelphia",
    "sg:classifiers":[
        {
            "category":"Bars & Pubs",
            "type":"Food & Drink"
        }
    ],
    "sg:phone":"+1 215 476 1600",
    "sg:postcode":"19151",
    "sg:province":"PA",
    "wof:name":"Club Damani",
    "wof:placetype":"venue"
},
  "geometry": {"coordinates":[-75.251643,39.973135],"type":"Point"}
}