{
  "type": "Feature",
  "properties": {
    "addr:full":"307 W Chester Rd West Chester PA 19382",
    "addr:housenumber":"307",
    "addr:postcode":"19382",
    "addr:street":"W Chester Rd",
    "iso:country":"US",
    "sg:address":"307 W Chester Rd",
    "sg:city":"West Chester",
    "sg:classifiers":[
        {
            "category":"Building & Trades",
            "subcategory":"Construction",
            "type":"Services"
        }
    ],
    "sg:phone":"+1 610 696 7200",
    "sg:postcode":"19382",
    "sg:province":"PA",
    "sg:tags":[
        "roofing",
        "contractor"
    ],
    "wof:name":"Springer Roofing",
    "wof:placetype":"venue"
},
  "geometry": {"coordinates":[-75.544703,39.910872],"type":"Point"}
}