{
  "type": "Feature",
  "properties": {
    "addr:full":"1924 N Main Ave Scranton PA 18508",
    "addr:housenumber":"1924",
    "addr:postcode":"18508",
    "addr:street":"N Main Ave",
    "iso:country":"US",
    "sg:address":"1924 N Main Ave",
    "sg:city":"Scranton",
    "sg:classifiers":[
        {
            "category":"Organizations",
            "subcategory":"Religious Organization",
            "type":"Services"
        }
    ],
    "sg:phone":"+1 570 342 3935",
    "sg:postcode":"18508",
    "sg:province":"PA",
    "sg:tags":[
        "church"
    ],
    "wof:name":"Providence United Methodist",
    "wof:placetype":"venue"
},
  "geometry": {"coordinates":[-75.655918,41.438161],"type":"Point"}
}