{
  "type": "Feature",
  "properties": {
    "iso:country":"US",
    "sg:address":"1 Broad St",
    "sg:city":"Ashland",
    "sg:classifiers":[
        {
            "category":"Education",
            "subcategory":"School",
            "type":"Public Place"
        }
    ],
    "sg:phone":"+1 570 875 2371",
    "sg:postcode":"17921",
    "sg:province":"PA",
    "wof:name":"Ashland Area Elementary School",
    "wof:placetype":"venue"
},
  "geometry": {"coordinates":[-76.33874900000001,40.777087],"type":"Point"}
}