{
  "type": "Feature",
  "properties": {
    "addr:full":"210 Pennsylvania Ave Shenandoah PA 17976",
    "addr:housenumber":"210",
    "addr:postcode":"17976",
    "addr:street":"Pennsylvania Ave",
    "iso:country":"US",
    "sg:address":"210 Pennsylvania Ave",
    "sg:city":"Shenandoah",
    "sg:classifiers":[
        {
            "category":"Social Services",
            "type":"Services"
        }
    ],
    "sg:phone":"+1 570 462 0204",
    "sg:postcode":"17976",
    "sg:province":"PA",
    "sg:tags":[
        "care",
        "center",
        "day"
    ],
    "wof:name":"Evergreen Adult Day Care Ctr",
    "wof:placetype":"venue"
},
  "geometry": {"coordinates":[-76.216173,40.823985],"type":"Point"}
}