{
  "type": "Feature",
  "properties": {
    "iso:country":"US",
    "sg:address":"801 Shaw Ave",
    "sg:city":"Mckeesport",
    "sg:classifiers":[
        {
            "category":"Professional",
            "type":"Services"
        },
        {
            "category":"Health Services",
            "subcategory":"Hospital",
            "type":"Services"
        }
    ],
    "sg:phone":"+1 412 664 1730",
    "sg:postcode":"15132",
    "sg:province":"PA",
    "sg:tags":[
        "establishment",
        "psychiatric"
    ],
    "wof:name":"Community Living Arrangement",
    "wof:placetype":"venue"
},
  "geometry": {"coordinates":[-79.85553299999999,40.349818],"type":"Point"}
}