{
  "type": "Feature",
  "properties": {
    "iso:country":"US",
    "sg:address":"3050 Hempland Rd",
    "sg:city":"Lancaster",
    "sg:classifiers":[
        {
            "category":"Education",
            "subcategory":"School",
            "type":"Public Place"
        }
    ],
    "sg:phone":"+1 717 295 1100",
    "sg:postcode":"17601",
    "sg:province":"PA",
    "sg:website":"www.yti.edu",
    "wof:name":"York Technical Institute",
    "wof:placetype":"venue"
},
  "geometry": {"coordinates":[-76.404595,40.04773],"type":"Point"}
}