{
  "type": "Feature",
  "properties": {
    "iso:country":"US",
    "sg:address":"2346 Magnolia Way",
    "sg:city":"Jamison",
    "sg:classifiers":[
        {
            "category":"Professional",
            "subcategory":"Lawyer & Legal Services",
            "type":"Services"
        }
    ],
    "sg:phone":"+1   ",
    "sg:postcode":"18929",
    "sg:province":"PA",
    "wof:name":"Eric J Linder",
    "wof:placetype":"venue"
},
  "geometry": {"coordinates":[-75.082729,40.257581],"type":"Point"}
}