{
  "type": "Feature",
  "properties": {
    "iso:country":"US",
    "sg:address":"117 N 10th St",
    "sg:city":"Philadelphia",
    "sg:classifiers":[
        {
            "category":"Professional",
            "type":"Services"
        },
        {
            "category":"Restaurant",
            "type":"Food & Drink"
        },
        {
            "category":"Food & Beverages",
            "subcategory":"Ethnic Foods",
            "type":"Retail Goods"
        }
    ],
    "sg:phone":"+1 215 413 2531",
    "sg:postcode":"19107",
    "sg:province":"PA",
    "sg:tags":[
        "style",
        "family",
        "vietnamese",
        "seafood",
        "malaysian",
        "lunch",
        "asian",
        "caterer",
        "brunch",
        "breakfast",
        "pan"
    ],
    "sg:website":"www.penangusa.com/location_phill...",
    "wof:name":"Penang",
    "wof:placetype":"venue"
},
  "geometry": {"coordinates":[-75.155907,39.954019],"type":"Point"}
}