{
  "type": "Feature",
  "properties": {
    "iso:country":"US",
    "sg:address":"902 Wood St",
    "sg:city":"New Eagle",
    "sg:classifiers":[
        {
            "category":"Building & Trades",
            "subcategory":"Construction",
            "type":"Services"
        }
    ],
    "sg:phone":"+1   ",
    "sg:postcode":"15067",
    "sg:province":"PA",
    "sg:tags":[
        "house"
    ],
    "wof:name":"Kent Shaffer Home Improvement",
    "wof:placetype":"venue"
},
  "geometry": {"coordinates":[-79.944785,40.204762],"type":"Point"}
}