{
  "type": "Feature",
  "properties": {
    "addr:full":"270 S River St Plains PA 18705",
    "addr:housenumber":"270",
    "addr:postcode":"18705",
    "addr:street":"S River St",
    "iso:country":"US",
    "sg:address":"270 S River St",
    "sg:city":"Plains",
    "sg:classifiers":[
        {
            "category":"Health Services",
            "subcategory":"Doctor",
            "type":"Services"
        }
    ],
    "sg:phone":"+1 570 824 2032",
    "sg:postcode":"18705",
    "sg:province":"PA",
    "sg:tags":[
        "dentist"
    ],
    "wof:name":"Childrens Dental Center",
    "wof:placetype":"venue"
},
  "geometry": {"coordinates":[-75.86256899999999,41.26909],"type":"Point"}
}