{
  "type": "Feature",
  "properties": {
    "iso:country":"US",
    "sg:address":"1601 Medical Dr",
    "sg:city":"Pottstown",
    "sg:classifiers":[
        {
            "category":"Health Services",
            "subcategory":"Doctor",
            "type":"Services"
        }
    ],
    "sg:phone":"+1   ",
    "sg:postcode":"19464",
    "sg:province":"PA",
    "sg:tags":[
        "medical"
    ],
    "wof:name":"Alan E Cooper MD",
    "wof:placetype":"venue"
},
  "geometry": {"coordinates":[-75.613733,40.239049],"type":"Point"}
}