{
  "type": "Feature",
  "properties": {
    "addr:full":"718 W Walnut St Allentown PA 18101",
    "addr:housenumber":"718",
    "addr:postcode":"18101",
    "addr:street":"W Walnut St",
    "iso:country":"US",
    "sg:address":"718 W Walnut St",
    "sg:city":"Allentown",
    "sg:classifiers":[
        {
            "category":"Personal",
            "subcategory":"Beauty Salon",
            "type":"Services"
        }
    ],
    "sg:phone":"+1 610 432 0172",
    "sg:postcode":"18101",
    "sg:province":"PA",
    "sg:tags":[
        "hair"
    ],
    "wof:name":"Bob Ford Beauty Salon",
    "wof:placetype":"venue"
},
  "geometry": {"coordinates":[-75.471298,40.6008],"type":"Point"}
}