{
  "type": "Feature",
  "properties": {
    "addr:full":"1052 Girard Rd Pittsburgh PA 15227",
    "addr:housenumber":"1052",
    "addr:postcode":"15227",
    "addr:street":"Girard Rd",
    "iso:country":"US",
    "sg:address":"1052 Girard Rd",
    "sg:city":"Pittsburgh",
    "sg:classifiers":[
        {
            "category":"Building & Trades",
            "subcategory":"Plumbing",
            "type":"Services"
        }
    ],
    "sg:phone":"+1   ",
    "sg:postcode":"15227",
    "sg:province":"PA",
    "sg:tags":[
        "contractor"
    ],
    "wof:name":"Fas Heating & Cooling",
    "wof:placetype":"venue"
},
  "geometry": {"coordinates":[-79.9761,40.360451],"type":"Point"}
}