{
  "type": "Feature",
  "properties": {
    "iso:country":"US",
    "sg:address":"20 Wabash Ave",
    "sg:city":"Hickory",
    "sg:classifiers":[
        {
            "category":"Social Services",
            "subcategory":"Child Care",
            "type":"Services"
        }
    ],
    "sg:phone":"+1 724 356 4004",
    "sg:postcode":"15340",
    "sg:province":"PA",
    "wof:name":"Precious Years Day Care",
    "wof:placetype":"venue"
},
  "geometry": {"coordinates":[-80.310016,40.300854],"type":"Point"}
}