{
  "type": "Feature",
  "properties": {
    "addr:full":"513 Miller Rd Halifax PA 17032",
    "addr:housenumber":"513",
    "addr:postcode":"17032",
    "addr:street":"Miller Rd",
    "iso:country":"US",
    "sg:address":"513 Miller Rd",
    "sg:city":"Halifax",
    "sg:classifiers":[
        {
            "category":"Personal",
            "type":"Services"
        }
    ],
    "sg:phone":"+1 717 362 6964",
    "sg:postcode":"17032",
    "sg:province":"PA",
    "sg:tags":[
        "control",
        "weight"
    ],
    "wof:name":"Herbalife Distributor",
    "wof:placetype":"venue"
},
  "geometry": {"coordinates":[-76.821862,40.476431],"type":"Point"}
}