{
  "type": "Feature",
  "properties": {
    "iso:country":"US",
    "sg:address":"7720 Valleyview Ave",
    "sg:city":"Harrisburg",
    "sg:classifiers":[
        {
            "category":"Wholesale",
            "subcategory":"Computers",
            "type":"Manufacturing & Wholesale Goods"
        }
    ],
    "sg:phone":"+1   ",
    "sg:postcode":"17112",
    "sg:province":"PA",
    "wof:name":"Dxb Computer Enterprises",
    "wof:placetype":"venue"
},
  "geometry": {"coordinates":[-76.72156099999999,40.333731],"type":"Point"}
}