{
  "type": "Feature",
  "properties": {
    "addr:full":"2200 W Liberty Ave Pittsburgh PA 15226",
    "addr:housenumber":"2200",
    "addr:postcode":"15226",
    "addr:street":"W Liberty Ave",
    "iso:country":"US",
    "sg:address":"2200 W Liberty Ave",
    "sg:city":"Pittsburgh",
    "sg:classifiers":[
        {
            "category":"Social Services",
            "subcategory":"Job Training",
            "type":"Services"
        }
    ],
    "sg:phone":"+1 412 531 0126",
    "sg:postcode":"15226",
    "sg:province":"PA",
    "sg:tags":[
        "rehabilitation"
    ],
    "wof:name":"Weston Group Inc",
    "wof:placetype":"venue"
},
  "geometry": {"coordinates":[-80.023814,40.400124],"type":"Point"}
}