{
  "type": "Feature",
  "properties": {
    "addr:full":"135 Woodward Ave Lock Haven PA 17745",
    "addr:housenumber":"135",
    "addr:postcode":"17745",
    "addr:street":"Woodward Ave",
    "iso:country":"US",
    "sg:address":"135 Woodward Ave",
    "sg:city":"Lock Haven",
    "sg:classifiers":[
        {
            "category":"Banks & Credit Unions",
            "subcategory":"Bank",
            "type":"Services"
        }
    ],
    "sg:phone":"+1   ",
    "sg:postcode":"17745",
    "sg:province":"PA",
    "sg:tags":[
        "state",
        "commercial"
    ],
    "wof:name":"M&T",
    "wof:placetype":"venue"
},
  "geometry": {"coordinates":[-77.422977,41.144559],"type":"Point"}
}