{
  "type": "Feature",
  "properties": {
    "addr:full":"2320 Trenton Rd Levittown PA 19056",
    "addr:housenumber":"2320",
    "addr:postcode":"19056",
    "addr:street":"Trenton Rd Levittown",
    "iso:country":"US",
    "sg:address":"2320 Trenton Rd",
    "sg:city":"Levittown",
    "sg:classifiers":[
        {
            "category":"Communications",
            "subcategory":"Television Station",
            "type":"Services"
        }
    ],
    "sg:phone":"+1 215 547 3819",
    "sg:postcode":"19056",
    "sg:province":"PA",
    "sg:tags":[
        "satellite",
        "cable"
    ],
    "sg:website":"http://www.comcast.com",
    "wof:name":"Comcast",
    "wof:placetype":"venue"
},
  "geometry": {"coordinates":[-74.88331700000001,40.163348],"type":"Point"}
}