{
  "type": "Feature",
  "properties": {
    "addr:full":"6110 Lansdowne Ave Philadelphia PA 19151",
    "addr:housenumber":"6110",
    "addr:postcode":"19151",
    "addr:street":"Lansdowne Ave",
    "iso:country":"US",
    "sg:address":"6110 Lansdowne Ave",
    "sg:city":"Philadelphia",
    "sg:classifiers":[
        {
            "category":"Retail",
            "subcategory":"Laundry & Dry Cleaning",
            "type":"Services"
        }
    ],
    "sg:phone":"+1 215 477 0100",
    "sg:postcode":"19151",
    "sg:province":"PA",
    "sg:tags":[
        "cleaner",
        "plant",
        "drycleaning"
    ],
    "wof:name":"Lee Cleaners",
    "wof:placetype":"venue"
},
  "geometry": {"coordinates":[-75.242203,39.9758],"type":"Point"}
}