{
  "type": "Feature",
  "properties": {
    "iso:country":"US",
    "sg:address":"205 E Street Rd",
    "sg:city":"Feastervl Trvs",
    "sg:classifiers":[
        {
            "category":"Shopping",
            "subcategory":"Clothing, Apparel, & Fashions",
            "type":"Retail Goods"
        }
    ],
    "sg:phone":"+1 215 357 4696",
    "sg:postcode":"19053",
    "sg:province":"PA",
    "sg:tags":[
        "shop",
        "bridal"
    ],
    "sg:website":"www.coronetbridal.com",
    "wof:name":"Coronet Bridal Shop",
    "wof:placetype":"venue"
},
  "geometry": {"coordinates":[-75.00922300000001,40.154742],"type":"Point"}
}