{
  "type": "Feature",
  "properties": {
    "iso:country":"US",
    "sg:address":"993 Greentree Rd",
    "sg:city":"Pittsburgh",
    "sg:classifiers":[
        {
            "category":"Health Services",
            "subcategory":"Doctor",
            "type":"Services"
        }
    ],
    "sg:phone":"+1 412 922 8672",
    "sg:postcode":"15220",
    "sg:province":"PA",
    "sg:tags":[
        "obstetrician",
        "gynecologist"
    ],
    "wof:name":"Deitrick",
    "wof:placetype":"venue"
},
  "geometry": {"coordinates":[-80.045403,40.4179],"type":"Point"}
}