{
  "type": "Feature",
  "properties": {
    "iso:country":"US",
    "sg:address":"106 Agnes St",
    "sg:city":"Harrisburg",
    "sg:classifiers":[
        {
            "category":"Retail",
            "subcategory":"Funeral Services",
            "type":"Services"
        }
    ],
    "sg:phone":"+1 717 939 9950",
    "sg:postcode":"17104",
    "sg:province":"PA",
    "sg:tags":[
        "director",
        "cemetery"
    ],
    "sg:website":"www.wallacefuneraldirectorsinc.com",
    "wof:name":"Wallace Funeral Directors Inc",
    "wof:placetype":"venue"
},
  "geometry": {"coordinates":[-76.846605,40.240931],"type":"Point"}
}