{
  "type": "Feature",
  "properties": {
    "iso:country":"US",
    "sg:address":"1510 Centerville Rd",
    "sg:city":"Newville",
    "sg:classifiers":[
        {
            "category":"Building & Trades",
            "subcategory":"Construction",
            "type":"Services"
        }
    ],
    "sg:phone":"+1 717 486 4165",
    "sg:postcode":"17241",
    "sg:province":"PA",
    "sg:tags":[
        "woodworker"
    ],
    "wof:name":"B & W Woodworks",
    "wof:placetype":"venue"
},
  "geometry": {"coordinates":[-77.31224400000001,40.080473],"type":"Point"}
}