{
  "type": "Feature",
  "properties": {
    "iso:country":"US",
    "sg:address":"75 Baltimore Pike",
    "sg:city":"Media",
    "sg:classifiers":[
        {
            "category":"Building & Trades",
            "subcategory":"Construction",
            "type":"Services"
        }
    ],
    "sg:phone":"+1 610 358 4935",
    "sg:postcode":"19063",
    "sg:province":"PA",
    "sg:tags":[
        "contractor"
    ],
    "wof:name":"F Tropea Builders",
    "wof:placetype":"venue"
},
  "geometry": {"coordinates":[-75.390827,39.917073],"type":"Point"}
}