{
  "type": "Feature",
  "properties": {
    "iso:country":"US",
    "sg:address":"2638 Stephens St",
    "sg:city":"Easton",
    "sg:classifiers":[
        {
            "category":"Retail",
            "subcategory":"Auto Repair",
            "type":"Services"
        }
    ],
    "sg:phone":"+1 610 252 2174",
    "sg:postcode":"18045",
    "sg:province":"PA",
    "sg:tags":[
        "repairing",
        "automobile",
        "general"
    ],
    "wof:name":"Kocher's Garage Inc",
    "wof:placetype":"venue"
},
  "geometry": {"coordinates":[-75.257587,40.689336],"type":"Point"}
}