{
  "type": "Feature",
  "properties": {
    "addr:full":"2 Jorrocks Ln Malvern PA 19355",
    "addr:housenumber":"2",
    "addr:postcode":"19355",
    "addr:street":"Jorrocks Ln",
    "iso:country":"US",
    "sg:address":"2 Jorrocks Ln",
    "sg:city":"Malvern",
    "sg:classifiers":[
        {
            "category":"Professional",
            "subcategory":"Business Services",
            "type":"Services"
        }
    ],
    "sg:phone":"+1 610 640 9414",
    "sg:postcode":"19355",
    "sg:province":"PA",
    "sg:tags":[
        "interior",
        "consultant",
        "design",
        "decorator"
    ],
    "wof:name":"G Elizabeth Hines Interior",
    "wof:placetype":"venue"
},
  "geometry": {"coordinates":[-75.507532,39.994223],"type":"Point"}
}