{
  "type": "Feature",
  "properties": {
    "iso:country":"US",
    "sg:address":"820 Corinthian Ave",
    "sg:city":"Philadelphia",
    "sg:classifiers":[
        {
            "category":"Retail",
            "subcategory":"Animal Services",
            "type":"Services"
        }
    ],
    "sg:phone":"+1 215 665 1216",
    "sg:postcode":"19130",
    "sg:province":"PA",
    "sg:tags":[
        "boarding",
        "sitting",
        "pet",
        "supply",
        "dog",
        "cat",
        "furnishing"
    ],
    "wof:name":"Executive Pet Care",
    "wof:placetype":"venue"
},
  "geometry": {"coordinates":[-75.170907,39.969727],"type":"Point"}
}