{
  "type": "Feature",
  "properties": {
    "addr:full":"561 W 31st St Erie PA 16508",
    "addr:housenumber":"561",
    "addr:postcode":"16508",
    "addr:street":"W 31St St",
    "iso:country":"US",
    "sg:address":"561 W 31st St",
    "sg:city":"Erie",
    "sg:classifiers":[
        {
            "category":"Manufacturing",
            "subcategory":"Apparel",
            "type":"Manufacturing & Wholesale Goods"
        }
    ],
    "sg:phone":"+1 814 454 6038",
    "sg:postcode":"16508",
    "sg:province":"PA",
    "sg:tags":[
        "embroidery"
    ],
    "wof:name":"Embroidery Shoppe",
    "wof:placetype":"venue"
},
  "geometry": {"coordinates":[-80.08278799999999,42.103531],"type":"Point"}
}