{
  "type": "Feature",
  "properties": {
    "addr:full":"643 Fernfield Cir Wayne PA 19087",
    "addr:housenumber":"643",
    "addr:postcode":"19087",
    "addr:street":"Fernfield Cir",
    "iso:country":"US",
    "sg:address":"643 Fernfield Cir",
    "sg:city":"Wayne",
    "sg:classifiers":[
        {
            "category":"Real Estate",
            "subcategory":"Real Estate Operator",
            "type":"Services"
        }
    ],
    "sg:phone":"+1   ",
    "sg:postcode":"19087",
    "sg:province":"PA",
    "sg:tags":[
        "building",
        "nonresidential"
    ],
    "wof:name":"Payne Integrated Businesses",
    "wof:placetype":"venue"
},
  "geometry": {"coordinates":[-75.402424,40.06194],"type":"Point"}
}