{
  "type": "Feature",
  "properties": {
    "addr:full":"55 State Rd Media PA 19063",
    "addr:housenumber":"55",
    "addr:postcode":"19063",
    "addr:street":"State Rd",
    "iso:country":"US",
    "sg:address":"55 State Rd",
    "sg:city":"Media",
    "sg:classifiers":[
        {
            "category":"Health Services",
            "subcategory":"Hospital",
            "type":"Services"
        }
    ],
    "sg:phone":"+1 610 566 2525",
    "sg:postcode":"19063",
    "sg:province":"PA",
    "sg:tags":[
        "sleep",
        "treatment",
        "disorders-information"
    ],
    "sg:website":"http://www.classic-sculpture.com",
    "wof:name":"Susan Wagner",
    "wof:placetype":"venue"
},
  "geometry": {"coordinates":[-75.382408,39.929176],"type":"Point"}
}