{
  "type": "Feature",
  "properties": {
    "iso:country":"US",
    "sg:address":"1717 Arch Street Suite 3220",
    "sg:city":"Philadelphia",
    "sg:classifiers":[
        {
            "category":"Professional",
            "type":"Services"
        }
    ],
    "sg:phone":"+1 215 979 8030",
    "sg:postcode":"19103",
    "sg:province":"PA",
    "sg:website":"www.peoplemetrics.com",
    "wof:name":"Peoplemetrics",
    "wof:placetype":"venue"
},
  "geometry": {"coordinates":[-75.169101,39.955313],"type":"Point"}
}