{
  "type": "Feature",
  "properties": {
    "addr:full":"6359 Mitch Haven Dr Bethel Park PA 15102",
    "addr:housenumber":"6359",
    "addr:postcode":"15102",
    "addr:street":"Mitch Haven Dr",
    "iso:country":"US",
    "sg:address":"6359 Mitch Haven Dr",
    "sg:city":"Bethel Park",
    "sg:classifiers":[
        {
            "category":"Manufacturing",
            "subcategory":"Tools & Machinery",
            "type":"Manufacturing & Wholesale Goods"
        }
    ],
    "sg:phone":"+1 412 833 8810",
    "sg:postcode":"15102",
    "sg:province":"PA",
    "sg:tags":[
        "transmission",
        "equipment",
        "power",
        "mfg"
    ],
    "wof:name":"Horsburgh & Scott Co",
    "wof:placetype":"venue"
},
  "geometry": {"coordinates":[-80.03959399999999,40.291677],"type":"Point"}
}