{
  "type": "Feature",
  "properties": {
    "iso:country":"US",
    "sg:address":"14007 Clifford Ln",
    "sg:city":"Philadelphia",
    "sg:classifiers":[
        {
            "category":"Food & Beverages",
            "subcategory":"Specialty",
            "type":"Retail Goods"
        },
        {
            "category":"Food & Beverages",
            "subcategory":"Groceries & Convenience Stores",
            "type":"Retail Goods"
        }
    ],
    "sg:phone":"+1 215 744 2880",
    "sg:postcode":"19116",
    "sg:province":"PA",
    "sg:tags":[
        "grocers-specialty"
    ],
    "wof:name":"Didos Circle Market Inc",
    "wof:placetype":"venue"
},
  "geometry": {"coordinates":[-75.02368,40.129412],"type":"Point"}
}