{
  "type": "Feature",
  "properties": {
    "iso:country":"US",
    "sg:address":"1413 W Moyamensing Ave",
    "sg:city":"Philadelphia",
    "sg:classifiers":[
        {
            "category":"Health Services",
            "subcategory":"Doctor",
            "type":"Services"
        }
    ],
    "sg:phone":"+1 215 468 5004",
    "sg:postcode":"19145",
    "sg:province":"PA",
    "wof:name":"Ambulatory Care Center",
    "wof:placetype":"venue"
},
  "geometry": {"coordinates":[-75.17214300000001,39.917146],"type":"Point"}
}