{
  "type": "Feature",
  "properties": {
    "iso:country":"US",
    "sg:address":"2501 N Atherton St",
    "sg:city":"State College",
    "sg:classifiers":[
        {
            "category":"Building & Trades",
            "subcategory":"Construction",
            "type":"Services"
        }
    ],
    "sg:phone":"+1 814 237 1586",
    "sg:postcode":"16803",
    "sg:province":"PA",
    "sg:tags":[
        "excavating",
        "excavation",
        "contractor",
        "water",
        "concrete",
        "sewer",
        "u"
    ],
    "sg:website":"www.ameronconstruction.com",
    "wof:name":"Ameron Construction Company",
    "wof:placetype":"venue"
},
  "geometry": {"coordinates":[-77.914734,40.810306],"type":"Point"}
}