{
  "type": "Feature",
  "properties": {
    "iso:country":"US",
    "sg:address":"951 Weadley Rd",
    "sg:city":"Wayne",
    "sg:classifiers":[
        {
            "category":"Banks & Credit Unions",
            "subcategory":"Financial Services",
            "type":"Services"
        }
    ],
    "sg:phone":"+1   ",
    "sg:postcode":"19087",
    "sg:province":"PA",
    "sg:tags":[
        "company",
        "holding"
    ],
    "wof:name":"Laird Family Ltd Partners",
    "wof:placetype":"venue"
},
  "geometry": {"coordinates":[-75.37204699999999,40.066421],"type":"Point"}
}