{
  "type": "Feature",
  "properties": {
    "addr:full":"3849 Union Deposit Rd Harrisburg PA 17109",
    "addr:housenumber":"3849",
    "addr:postcode":"17109",
    "addr:street":"Union Deposit Rd",
    "iso:country":"US",
    "sg:address":"3849 Union Deposit Rd",
    "sg:city":"Harrisburg",
    "sg:classifiers":[
        {
            "category":"Shopping",
            "subcategory":"Gifts & Souvenirs",
            "type":"Retail Goods"
        }
    ],
    "sg:phone":"+1 717 561 6988",
    "sg:postcode":"17109",
    "sg:province":"PA",
    "sg:tags":[
        "shop"
    ],
    "sg:website":"www.tuesdaymorning.com",
    "wof:name":"Tuesday Morning Inc",
    "wof:placetype":"venue"
},
  "geometry": {"coordinates":[-76.825554,40.27825],"type":"Point"}
}