{
  "type": "Feature",
  "properties": {
    "iso:country":"US",
    "sg:address":"505 Woodcrest Ave",
    "sg:city":"Lititz",
    "sg:classifiers":[
        {
            "category":"Organizations",
            "subcategory":"Religious Organization",
            "type":"Services"
        }
    ],
    "sg:phone":"+1 717 626 5580",
    "sg:postcode":"17543",
    "sg:province":"PA",
    "wof:name":"St James Catholic Church",
    "wof:placetype":"venue"
},
  "geometry": {"coordinates":[-76.312335,40.146571],"type":"Point"}
}