{
  "type": "Feature",
  "properties": {
    "iso:country":"US",
    "sg:address":"1000 E Oak St",
    "sg:city":"Palmyra",
    "sg:classifiers":[
        {
            "category":"Organizations",
            "subcategory":"Religious Organization",
            "type":"Services"
        }
    ],
    "sg:phone":"+1 717 838 5248",
    "sg:postcode":"17078",
    "sg:province":"PA",
    "sg:tags":[
        "church"
    ],
    "wof:name":"United Zion Church",
    "wof:placetype":"venue"
},
  "geometry": {"coordinates":[-76.578801,40.312068],"type":"Point"}
}