{
  "type": "Feature",
  "properties": {
    "iso:country":"US",
    "sg:address":"7348 Manor Dr",
    "sg:city":"Harrisburg",
    "sg:classifiers":[
        {
            "category":"Building & Trades",
            "subcategory":"Equipment Rental",
            "type":"Services"
        }
    ],
    "sg:phone":"+1   ",
    "sg:postcode":"17112",
    "sg:province":"PA",
    "wof:name":"Alices Rentals",
    "wof:placetype":"venue"
},
  "geometry": {"coordinates":[-76.744299,40.348673],"type":"Point"}
}