{
  "type": "Feature",
  "properties": {
    "addr:full":"805 Floral Vale Blvd Morrisville PA 19067",
    "addr:housenumber":"805",
    "addr:postcode":"19067",
    "addr:street":"Floral Vale Blvd",
    "iso:country":"US",
    "sg:address":"805 Floral Vale Blvd",
    "sg:city":"Morrisville",
    "sg:classifiers":[
        {
            "category":"Health Services",
            "subcategory":"Doctor",
            "type":"Services"
        }
    ],
    "sg:phone":"+1   ",
    "sg:postcode":"19067",
    "sg:province":"PA",
    "sg:tags":[
        "medical"
    ],
    "wof:name":"Guillermo J Bernal MD PC",
    "wof:placetype":"venue"
},
  "geometry": {"coordinates":[-74.882245,40.21971],"type":"Point"}
}