{
  "type": "Feature",
  "properties": {
    "iso:country":"US",
    "sg:address":"144 Serrill Rd",
    "sg:city":"Elkins Park",
    "sg:classifiers":[
        {
            "category":"Professional",
            "type":"Services"
        }
    ],
    "sg:phone":"+1 215 885 8020",
    "sg:postcode":"19027",
    "sg:province":"PA",
    "wof:name":"Jeri Hauptman",
    "wof:placetype":"venue"
},
  "geometry": {"coordinates":[-75.11150499999999,40.081217],"type":"Point"}
}