{
  "type": "Feature",
  "properties": {
    "iso:country":"US",
    "sg:address":"57 S Commerce Way Ste. 140",
    "sg:city":"Bethlehem",
    "sg:classifiers":[
        {
            "category":"Health Services",
            "subcategory":"Dentist",
            "type":"Services"
        }
    ],
    "sg:phone":"+1 610 865 2018",
    "sg:postcode":"18017",
    "sg:province":"PA",
    "sg:website":"http://www.underneathitallus.com",
    "wof:name":"Underneath It All",
    "wof:placetype":"venue"
},
  "geometry": {"coordinates":[-75.381168,40.672724],"type":"Point"}
}