{
  "type": "Feature",
  "properties": {
    "iso:country":"US",
    "sg:address":"3900 Ford Rd",
    "sg:city":"Philadelphia",
    "sg:classifiers":[
        {
            "category":"Organizations",
            "subcategory":"Religious Organization",
            "type":"Services"
        }
    ],
    "sg:phone":"+1 215 477 1818",
    "sg:postcode":"19131",
    "sg:province":"PA",
    "sg:tags":[
        "clergy"
    ],
    "wof:name":"Samuel R Kinder",
    "wof:placetype":"venue"
},
  "geometry": {"coordinates":[-75.209695,39.999649],"type":"Point"}
}