{
  "type": "Feature",
  "properties": {
    "addr:full":"568 Franklin St Clymer PA 15728",
    "addr:housenumber":"568",
    "addr:postcode":"15728",
    "addr:street":"Franklin St",
    "iso:country":"US",
    "sg:address":"568 Franklin St",
    "sg:city":"Clymer",
    "sg:classifiers":[
        {
            "category":"Cinema",
            "subcategory":"Movie Rental",
            "type":"Entertainment"
        }
    ],
    "sg:phone":"+1 724 254 0111",
    "sg:postcode":"15728",
    "sg:province":"PA",
    "sg:tags":[
        "video",
        "tape"
    ],
    "wof:name":"Clymer Video",
    "wof:placetype":"venue"
},
  "geometry": {"coordinates":[-79.01130999999999,40.66865],"type":"Point"}
}