{
  "type": "Feature",
  "properties": {
    "addr:full":"208 Carter Dr Ste 11 West Chester PA 19382",
    "addr:housenumber":"208",
    "addr:postcode":"19382",
    "addr:street":"Carter Dr Ste 11",
    "iso:country":"US",
    "sg:address":"208 Carter Dr Ste 11",
    "sg:city":"West Chester",
    "sg:classifiers":[
        {
            "category":"Building & Trades",
            "subcategory":"Construction",
            "type":"Services"
        }
    ],
    "sg:phone":"+1 610 429 4560",
    "sg:postcode":"19382",
    "sg:province":"PA",
    "sg:tags":[
        "contractor"
    ],
    "wof:name":"Reinhardt R H Co",
    "wof:placetype":"venue"
},
  "geometry": {"coordinates":[-75.590599,39.950699],"type":"Point"}
}