{
  "type": "Feature",
  "properties": {
    "iso:country":"US",
    "sg:address":"311 W Avondale Rd",
    "sg:city":"West Grove",
    "sg:classifiers":[
        {
            "category":"Professional",
            "subcategory":"Management & Consulting",
            "type":"Services"
        }
    ],
    "sg:phone":"+1 610 869 3066",
    "sg:postcode":"19390",
    "sg:province":"PA",
    "sg:tags":[
        "business"
    ],
    "wof:name":"Lanchester Soil Consultants",
    "wof:placetype":"venue"
},
  "geometry": {"coordinates":[-75.841166,39.797635],"type":"Point"}
}