{
  "type": "Feature",
  "properties": {
    "iso:country":"US",
    "sg:address":"4501 Castor Ave",
    "sg:city":"Philadelphia",
    "sg:classifiers":[
        {
            "category":"Home & Garden",
            "subcategory":"Furniture",
            "type":"Retail Goods"
        }
    ],
    "sg:phone":"+1 215 288 7800",
    "sg:postcode":"19124",
    "sg:province":"PA",
    "wof:name":"Universal Factory Liquidation",
    "wof:placetype":"venue"
},
  "geometry": {"coordinates":[-75.096744,40.01873],"type":"Point"}
}