{
  "type": "Feature",
  "properties": {
    "iso:country":"US",
    "sg:address":"550 California Rd Ste 7",
    "sg:city":"Quakertown",
    "sg:classifiers":[
        {
            "category":"Professional",
            "subcategory":"Business Services",
            "type":"Services"
        }
    ],
    "sg:phone":"+1 215 538 9400",
    "sg:postcode":"18951",
    "sg:province":"PA",
    "sg:tags":[
        "equipment",
        "bank",
        "supply"
    ],
    "wof:name":"Apple Global Mobile",
    "wof:placetype":"venue"
},
  "geometry": {"coordinates":[-75.35516200000001,40.458746],"type":"Point"}
}