{
  "type": "Feature",
  "properties": {
    "iso:country":"US",
    "sg:address":"21 Ladnor Ln",
    "sg:city":"Carlisle",
    "sg:classifiers":[
        {
            "category":"Building & Trades",
            "subcategory":"Plumbing",
            "type":"Services"
        }
    ],
    "sg:phone":"+1 717 486 3319",
    "sg:postcode":"17015",
    "sg:province":"PA",
    "sg:tags":[
        "contractor"
    ],
    "wof:name":"Bennett Heating & Cooling",
    "wof:placetype":"venue"
},
  "geometry": {"coordinates":[-77.190279,40.130595],"type":"Point"}
}