{
  "type": "Feature",
  "properties": {
    "addr:full":"400 S Washington St Butler PA 16001",
    "addr:housenumber":"400",
    "addr:postcode":"16001",
    "addr:street":"S Washington St",
    "iso:country":"US",
    "sg:address":"400 S Washington St",
    "sg:city":"Butler",
    "sg:classifiers":[
        {
            "category":"Professional",
            "type":"Services"
        }
    ],
    "sg:phone":"+1   ",
    "sg:postcode":"16001",
    "sg:province":"PA",
    "wof:name":"Island Bar",
    "wof:placetype":"venue"
},
  "geometry": {"coordinates":[-79.89699400000001,40.857082],"type":"Point"}
}