{
  "type": "Feature",
  "properties": {
    "addr:full":"129 S McKean St Butler PA 16001",
    "addr:housenumber":"129",
    "addr:postcode":"16001",
    "addr:street":"S Mckean St",
    "iso:country":"US",
    "sg:address":"129 S McKean St",
    "sg:city":"Butler",
    "sg:classifiers":[
        {
            "category":"Professional",
            "subcategory":"Lawyer & Legal Services",
            "type":"Services"
        }
    ],
    "sg:phone":"+1 724 285 3040",
    "sg:postcode":"16001",
    "sg:province":"PA",
    "wof:name":"Givan & Price",
    "wof:placetype":"venue"
},
  "geometry": {"coordinates":[-79.893563,40.86033],"type":"Point"}
}