{
  "type": "Feature",
  "properties": {
    "addr:full":"1120 W Main St Plymouth PA 18651",
    "addr:housenumber":"1120",
    "addr:postcode":"18651",
    "addr:street":"W Main St",
    "iso:country":"US",
    "sg:address":"1120 W Main St",
    "sg:city":"Plymouth",
    "sg:classifiers":[
        {
            "category":"Government",
            "subcategory":"Fire Station",
            "type":"Public Place"
        }
    ],
    "sg:phone":"+1   ",
    "sg:postcode":"18651",
    "sg:province":"PA",
    "sg:tags":[
        "protection"
    ],
    "wof:name":"Plymouth Township Vlntr Fire",
    "wof:placetype":"venue"
},
  "geometry": {"coordinates":[-75.97048599999999,41.229839],"type":"Point"}
}