{
  "type": "Feature",
  "properties": {
    "iso:country":"US",
    "sg:address":"3829 Hilltop Dr",
    "sg:city":"Gibsonia",
    "sg:classifiers":[
        {
            "category":"Building & Trades",
            "subcategory":"Plumbing",
            "type":"Services"
        }
    ],
    "sg:phone":"+1 724 443 5031",
    "sg:postcode":"15044",
    "sg:province":"PA",
    "sg:tags":[
        "plumbing",
        "contractor"
    ],
    "wof:name":"Russ Bob Plumbing & Heating",
    "wof:placetype":"venue"
},
  "geometry": {"coordinates":[-79.960988,40.647281],"type":"Point"}
}