{
  "type": "Feature",
  "properties": {
    "iso:country":"US",
    "sg:address":"26 Chelton Ave",
    "sg:city":"Morrisville",
    "sg:classifiers":[
        {
            "category":"Utilities",
            "subcategory":"Fuel Oil & Lpg",
            "type":"Services"
        }
    ],
    "sg:phone":"+1   ",
    "sg:postcode":"19067",
    "sg:province":"PA",
    "sg:tags":[
        "repair",
        "dealer"
    ],
    "wof:name":"Yost Heating",
    "wof:placetype":"venue"
},
  "geometry": {"coordinates":[-74.780822,40.204286],"type":"Point"}
}