{
  "type": "Feature",
  "properties": {
    "iso:country":"US",
    "sg:address":"8 Station St",
    "sg:city":"Sykesville",
    "sg:classifiers":[
        {
            "category":"Banks & Credit Unions",
            "subcategory":"Investment Brokerage",
            "type":"Services"
        }
    ],
    "sg:phone":"+1   ",
    "sg:postcode":"15865",
    "sg:province":"PA",
    "sg:tags":[
        "security"
    ],
    "wof:name":"Purist Investment Club",
    "wof:placetype":"venue"
},
  "geometry": {"coordinates":[-78.818708,41.051376],"type":"Point"}
}