{
  "type": "Feature",
  "properties": {
    "iso:country":"US",
    "sg:address":"26 S 11th St",
    "sg:city":"Mifflinburg",
    "sg:classifiers":[
        {
            "category":"Building & Trades",
            "subcategory":"Construction",
            "type":"Services"
        }
    ],
    "sg:phone":"+1 570 966 1411",
    "sg:postcode":"17844",
    "sg:province":"PA",
    "sg:tags":[
        "excavation",
        "contractor"
    ],
    "wof:name":"Clair R Boop",
    "wof:placetype":"venue"
},
  "geometry": {"coordinates":[-77.056512,40.912105],"type":"Point"}
}