{
  "type": "Feature",
  "properties": {
    "iso:country":"US",
    "sg:address":"1445 Anderson Ave",
    "sg:city":"Oreland",
    "sg:classifiers":[
        {
            "category":"Professional",
            "type":"Services"
        }
    ],
    "sg:phone":"+1 215 884 0600",
    "sg:postcode":"19075",
    "sg:province":"PA",
    "sg:tags":[
        "establishment"
    ],
    "wof:name":"Lightman Bros Inc Batries",
    "wof:placetype":"venue"
},
  "geometry": {"coordinates":[-75.188621,40.115612],"type":"Point"}
}