{
  "type": "Feature",
  "properties": {
    "iso:country":"US",
    "sg:address":"615 Howard Ave 1st Fl",
    "sg:city":"Altoona",
    "sg:classifiers":[
        {
            "category":"Health Services",
            "subcategory":"Clinic",
            "type":"Services"
        },
        {
            "category":"Health Services",
            "subcategory":"Medical Lab",
            "type":"Services"
        },
        {
            "category":"Professional",
            "subcategory":"Business Services",
            "type":"Services"
        }
    ],
    "sg:phone":"+1 866 659 7494",
    "sg:postcode":"16601",
    "sg:province":"PA",
    "sg:tags":[
        "information",
        "testing",
        "aid",
        "welfare"
    ],
    "sg:website":"http://national.citysearch.com/profile/external/603798532/altoona_pa/std_test_express_altoona.html?publisher=yellowpages&reference_id=1&placement=ypwebsitemip",
    "wof:name":"STD Test Express Altoona",
    "wof:placetype":"venue"
},
  "geometry": {"coordinates":[-78.398122,40.52122],"type":"Point"}
}