{
  "type": "Feature",
  "properties": {
    "iso:country":"US",
    "sg:address":"643 S 63rd St",
    "sg:city":"Philadelphia",
    "sg:classifiers":[
        {
            "category":"Retail",
            "subcategory":"Auto Repair",
            "type":"Services"
        }
    ],
    "sg:phone":"+1 215 474 3323",
    "sg:postcode":"19143",
    "sg:province":"PA",
    "sg:tags":[
        "wheel",
        "axle",
        "alignment"
    ],
    "wof:name":"Alex Portable Autobody & Frame",
    "wof:placetype":"venue"
},
  "geometry": {"coordinates":[-75.248884,39.952167],"type":"Point"}
}