{
  "type": "Feature",
  "properties": {
    "iso:country":"US",
    "sg:address":"5940 Torresdale Ave",
    "sg:city":"Philadelphia",
    "sg:classifiers":[
        {
            "category":"Shopping",
            "type":"Retail Goods"
        },
        {
            "category":"Education",
            "subcategory":"Special Training",
            "type":"Public Place"
        }
    ],
    "sg:phone":"+1 215 288 7070",
    "sg:postcode":"19135",
    "sg:province":"PA",
    "sg:tags":[
        "cake",
        "equipment",
        "decorating",
        "merchandise",
        "supply"
    ],
    "sg:website":"www.swtcreations.com",
    "wof:name":"Sweet Creations Unlimited Inc",
    "wof:placetype":"venue"
},
  "geometry": {"coordinates":[-75.059769,40.017412],"type":"Point"}
}