{
  "type": "Feature",
  "properties": {
    "addr:full":"5253 New Falls Rd Levittown PA 19056",
    "addr:housenumber":"5253",
    "addr:postcode":"19056",
    "addr:street":"New Falls Rd Levittown",
    "iso:country":"US",
    "sg:address":"5253 New Falls Rd",
    "sg:city":"Levittown",
    "sg:classifiers":[
        {
            "category":"Professional",
            "subcategory":"Lawyer & Legal Services",
            "type":"Services"
        }
    ],
    "sg:phone":"+1 215 547 4433",
    "sg:postcode":"19056",
    "sg:province":"PA",
    "sg:tags":[
        "notary"
    ],
    "wof:name":"A-1 Quick Tags",
    "wof:placetype":"venue"
},
  "geometry": {"coordinates":[-74.881798,40.1362],"type":"Point"}
}