{
  "type": "Feature",
  "properties": {
    "iso:country":"US",
    "sg:address":"21 S 12th St",
    "sg:city":"Philadelphia",
    "sg:classifiers":[
        {
            "category":"Professional",
            "subcategory":"Lawyer & Legal Services",
            "type":"Services"
        }
    ],
    "sg:phone":"+1 215 568 7600",
    "sg:postcode":"19107",
    "sg:province":"PA",
    "sg:tags":[
        "attorney"
    ],
    "wof:name":"Ronald J Pressley",
    "wof:placetype":"venue"
},
  "geometry": {"coordinates":[-75.159998,39.951048],"type":"Point"}
}