{
  "type": "Feature",
  "properties": {
    "iso:country":"US",
    "sg:address":"4005 N 10th St",
    "sg:city":"Philadelphia",
    "sg:classifiers":[
        {
            "category":"Building & Trades",
            "subcategory":"Cleaning & Sanitation",
            "type":"Services"
        }
    ],
    "sg:phone":"+1   ",
    "sg:postcode":"19140",
    "sg:province":"PA",
    "sg:tags":[
        "maintenance"
    ],
    "wof:name":"Barefield Cleaning Service",
    "wof:placetype":"venue"
},
  "geometry": {"coordinates":[-75.143128,40.013474],"type":"Point"}
}