{
  "type": "Feature",
  "properties": {
    "iso:country":"US",
    "sg:address":"3158 Brynwood Dr",
    "sg:city":"Whitehall",
    "sg:classifiers":[
        {
            "category":"Building & Trades",
            "subcategory":"Construction",
            "type":"Services"
        }
    ],
    "sg:phone":"+1 484 553 0490",
    "sg:postcode":"18052",
    "sg:province":"PA",
    "sg:tags":[
        "excavation",
        "contractor"
    ],
    "wof:name":"Jc Sons Excavating Company",
    "wof:placetype":"venue"
},
  "geometry": {"coordinates":[-75.509483,40.643009],"type":"Point"}
}