{
  "type": "Feature",
  "properties": {
    "iso:country":"US",
    "sg:address":"918 Walnut St",
    "sg:city":"Philadelphia",
    "sg:classifiers":[
        {
            "category":"Building & Trades",
            "subcategory":"Construction",
            "type":"Services"
        }
    ],
    "sg:phone":"+1   ",
    "sg:postcode":"19107",
    "sg:province":"PA",
    "sg:tags":[
        "contractor"
    ],
    "wof:name":"Acorn Construction Co Inc",
    "wof:placetype":"venue"
},
  "geometry": {"coordinates":[-75.157377,39.948411],"type":"Point"}
}