{
  "type": "Feature",
  "properties": {
    "addr:full":"1087 Gates Hill Rd Summerhill PA 15958",
    "addr:housenumber":"1087",
    "addr:postcode":"15958",
    "addr:street":"Gates Hill Rd",
    "iso:country":"US",
    "sg:address":"1087 Gates Hill Rd",
    "sg:city":"Summerhill",
    "sg:classifiers":[
        {
            "category":"Banks & Credit Unions",
            "subcategory":"Investment Brokerage",
            "type":"Services"
        }
    ],
    "sg:phone":"+1   ",
    "sg:postcode":"15958",
    "sg:province":"PA",
    "sg:tags":[
        "advisory"
    ],
    "wof:name":"Investor Capital",
    "wof:placetype":"venue"
},
  "geometry": {"coordinates":[-78.752066,40.410069],"type":"Point"}
}