{
  "type": "Feature",
  "properties": {
    "iso:country":"US",
    "sg:address":"1440 Conchester Hwy",
    "sg:city":"Boothwyn",
    "sg:classifiers":[
        {
            "category":"Health Services",
            "subcategory":"Doctor",
            "type":"Services"
        }
    ],
    "sg:phone":"+1 610 459 0845",
    "sg:postcode":"19061",
    "sg:province":"PA",
    "sg:tags":[
        "dentist"
    ],
    "wof:name":"Bethel Family Dental Inc",
    "wof:placetype":"venue"
},
  "geometry": {"coordinates":[-75.47427399999999,39.857074],"type":"Point"}
}