{
  "type": "Feature",
  "properties": {
    "iso:country":"US",
    "sg:address":"9763 Roosevelt Blvd",
    "sg:city":"Philadelphia",
    "sg:classifiers":[
        {
            "category":"Restaurant",
            "type":"Food & Drink"
        }
    ],
    "sg:menulink":"http://www.allmenus.com/pa/philadelphia/10165-famous-daves/menu/",
    "sg:phone":"+1 215 856 7611",
    "sg:postcode":"19114",
    "sg:province":"PA",
    "sg:tags":[
        "barbecue",
        "american"
    ],
    "wof:name":"Famous Dave's",
    "wof:placetype":"venue"
},
  "geometry": {"coordinates":[-75.02313100000001,40.085965],"type":"Point"}
}