{
  "type": "Feature",
  "properties": {
    "iso:country":"US",
    "sg:address":"1291 Reading Ave",
    "sg:city":"Boyertown",
    "sg:classifiers":[
        {
            "category":"Building & Trades",
            "subcategory":"Construction",
            "type":"Services"
        }
    ],
    "sg:phone":"+1   ",
    "sg:postcode":"19512",
    "sg:province":"PA",
    "sg:tags":[
        "hole",
        "blast",
        "drilling"
    ],
    "wof:name":"Blast Whole Drilling",
    "wof:placetype":"venue"
},
  "geometry": {"coordinates":[-75.689065,40.315327],"type":"Point"}
}