{
  "type": "Feature",
  "properties": {
    "iso:country":"US",
    "sg:address":"126 S McDonald St",
    "sg:city":"Mc Donald",
    "sg:classifiers":[
        {
            "category":"Retail",
            "subcategory":"Veterinary Services",
            "type":"Services"
        }
    ],
    "sg:phone":"+1 724 926 4112",
    "sg:postcode":"15057",
    "sg:province":"PA",
    "sg:tags":[
        "veterinarian"
    ],
    "wof:name":"Sacksteder Michelle DVM",
    "wof:placetype":"venue"
},
  "geometry": {"coordinates":[-80.2351,40.367199],"type":"Point"}
}