{
  "type": "Feature",
  "properties": {
    "iso:country":"US",
    "sg:address":"3347 Forbes Ave",
    "sg:city":"Pittsburgh",
    "sg:classifiers":[
        {
            "category":"Health Services",
            "subcategory":"Podiatrist",
            "type":"Services"
        }
    ],
    "sg:phone":"+1 412 681 5555",
    "sg:postcode":"15213",
    "sg:province":"PA",
    "wof:name":"Joseph E Jani DPM",
    "wof:placetype":"venue"
},
  "geometry": {"coordinates":[-79.96123900000001,40.438465],"type":"Point"}
}