{
  "type": "Feature",
  "properties": {
    "iso:country":"US",
    "sg:address":"320 Allegheny St",
    "sg:city":"Hollidaysburg",
    "sg:classifiers":[
        {
            "category":"Shopping",
            "type":"Retail Goods"
        },
        {
            "category":"Shopping",
            "subcategory":"Gifts & Souvenirs",
            "type":"Retail Goods"
        }
    ],
    "sg:phone":"+1 814 696 5766",
    "sg:postcode":"16648",
    "sg:province":"PA",
    "sg:tags":[
        "craft",
        "gallery",
        "dealer"
    ],
    "wof:name":"Rispoli's Country Collectables",
    "wof:placetype":"venue"
},
  "geometry": {"coordinates":[-78.393446,40.429405],"type":"Point"}
}