{
  "type": "Feature",
  "properties": {
    "iso:country":"US",
    "sg:address":"301 1st St",
    "sg:city":"Charleroi",
    "sg:classifiers":[
        {
            "category":"Retail",
            "subcategory":"Self-service Laundry",
            "type":"Services"
        }
    ],
    "sg:phone":"+1 724 483 1030",
    "sg:postcode":"15022",
    "sg:province":"PA",
    "wof:name":"Charleroi Coin Operated Lndrmt",
    "wof:placetype":"venue"
},
  "geometry": {"coordinates":[-79.89370599999999,40.133894],"type":"Point"}
}