{
  "type": "Feature",
  "properties": {
    "addr:full":"2900 Noblestown Rd Pittsburgh PA 15205",
    "addr:housenumber":"2900",
    "addr:postcode":"15205",
    "addr:street":"Noblestown Rd",
    "iso:country":"US",
    "sg:address":"2900 Noblestown Rd",
    "sg:city":"Pittsburgh",
    "sg:classifiers":[
        {
            "category":"Wholesale",
            "subcategory":"Office Equipment",
            "type":"Manufacturing & Wholesale Goods"
        }
    ],
    "sg:phone":"+1 412 922 6400",
    "sg:postcode":"15205",
    "sg:province":"PA",
    "sg:tags":[
        "food",
        "agency",
        "purchasing"
    ],
    "sg:website":"www.dpcpitt.org",
    "wof:name":"Diocesan Purchasing Commission",
    "wof:placetype":"venue"
},
  "geometry": {"coordinates":[-80.066846,40.42047],"type":"Point"}
}