{
  "type": "Feature",
  "properties": {
    "iso:country":"US",
    "sg:address":"320 Race St",
    "sg:city":"Philadelphia",
    "sg:classifiers":[
        {
            "category":"Shopping",
            "subcategory":"Used Merchandise",
            "type":"Retail Goods"
        }
    ],
    "sg:phone":"+1 215 627 0588",
    "sg:postcode":"19106",
    "sg:province":"PA",
    "sg:tags":[
        "antique"
    ],
    "wof:name":"Sheppard Corp",
    "wof:placetype":"venue"
},
  "geometry": {"coordinates":[-75.14484,39.954007],"type":"Point"}
}