{
  "type": "Feature",
  "properties": {
    "iso:country":"US",
    "sg:address":"728 Dorseyville Rd",
    "sg:city":"Pittsburgh",
    "sg:classifiers":[
        {
            "category":"Retail",
            "subcategory":"Veterinary Services",
            "type":"Services"
        }
    ],
    "sg:phone":"+1 412 963 8889",
    "sg:postcode":"15238",
    "sg:province":"PA",
    "sg:tags":[
        "veterinarian"
    ],
    "wof:name":"Harts Run Veterinary Hospital",
    "wof:placetype":"venue"
},
  "geometry": {"coordinates":[-79.90374799999999,40.543908],"type":"Point"}
}