{
  "type": "Feature",
  "properties": {
    "iso:country":"US",
    "sg:address":"3 Moxley Rd",
    "sg:city":"Avondale",
    "sg:classifiers":[
        {
            "category":"Government",
            "subcategory":"Jail",
            "type":"Public Place"
        }
    ],
    "sg:phone":"+1   ",
    "sg:postcode":"19311",
    "sg:province":"PA",
    "sg:tags":[
        "correctional",
        "institution"
    ],
    "wof:name":"Adult Probation- Avondale Off",
    "wof:placetype":"venue"
},
  "geometry": {"coordinates":[-75.79818899999999,39.839018],"type":"Point"}
}