{
  "type": "Feature",
  "properties": {
    "iso:country":"US",
    "sg:address":"2708 Limestone St",
    "sg:city":"Coplay",
    "sg:classifiers":[
        {
            "category":"Wholesale",
            "subcategory":"Auto Parts",
            "type":"Manufacturing & Wholesale Goods"
        }
    ],
    "sg:phone":"+1 610 261 2284",
    "sg:postcode":"18037",
    "sg:province":"PA",
    "sg:tags":[
        "body",
        "shop",
        "rebuilt",
        "automobile"
    ],
    "wof:name":"Future Cars",
    "wof:placetype":"venue"
},
  "geometry": {"coordinates":[-75.554497,40.6703],"type":"Point"}
}