{
  "type": "Feature",
  "properties": {
    "iso:country":"US",
    "sg:address":"193 Kutz Rd",
    "sg:city":"Carlisle",
    "sg:classifiers":[
        {
            "category":"Professional",
            "subcategory":"Computer Services",
            "type":"Services"
        }
    ],
    "sg:phone":"+1 717 776 4949",
    "sg:postcode":"17015",
    "sg:province":"PA",
    "sg:tags":[
        "internet"
    ],
    "wof:name":"E-Commerce Business Solutions",
    "wof:placetype":"venue"
},
  "geometry": {"coordinates":[-77.321774,40.13301],"type":"Point"}
}