{
  "type": "Feature",
  "properties": {
    "iso:country":"US",
    "sg:address":"1 Hawkfield Rd",
    "sg:city":"Kempton",
    "sg:classifiers":[
        {
            "category":"Real Estate",
            "subcategory":"Real Estate Agent",
            "type":"Services"
        }
    ],
    "sg:phone":"+1 610 756 4005",
    "sg:postcode":"19529",
    "sg:province":"PA",
    "wof:name":"Kutztown Heritage Properties",
    "wof:placetype":"venue"
},
  "geometry": {"coordinates":[-75.830338,40.596076],"type":"Point"}
}