{
  "type": "Feature",
  "properties": {
    "addr:full":"501 Meade Dr Coraopolis PA 15108",
    "addr:housenumber":"501",
    "addr:postcode":"15108",
    "addr:street":"Meade Dr",
    "iso:country":"US",
    "sg:address":"501 Meade Dr",
    "sg:city":"Coraopolis",
    "sg:classifiers":[
        {
            "category":"Professional",
            "subcategory":"Employment Agencies",
            "type":"Services"
        }
    ],
    "sg:phone":"+1   ",
    "sg:postcode":"15108",
    "sg:province":"PA",
    "sg:tags":[
        "staffing"
    ],
    "wof:name":"Speciality Staffing Services",
    "wof:placetype":"venue"
},
  "geometry": {"coordinates":[-80.248496,40.538266],"type":"Point"}
}