{
  "type": "Feature",
  "properties": {
    "iso:country":"US",
    "sg:address":"513 Beech Rd",
    "sg:city":"Pittsburgh",
    "sg:phone":"+1 412 793 8210",
    "sg:postcode":"15239",
    "sg:province":"PA",
    "sg:website":"http://diamondconstructioninc.net/home.html",
    "wof:name":"Diamond Construction & Remodeling, Inc",
    "wof:placetype":"venue"
},
  "geometry": {"coordinates":[-79.751492,40.481242],"type":"Point"}
}