{
  "type": "Feature",
  "properties": {
    "addr:full":"420 Hudson St Mayfield PA 18433",
    "addr:housenumber":"420",
    "addr:postcode":"18433",
    "addr:street":"Hudson St",
    "iso:country":"US",
    "sg:address":"420 Hudson St",
    "sg:city":"Mayfield",
    "sg:classifiers":[
        {
            "category":"Organizations",
            "subcategory":"Religious Organization",
            "type":"Services"
        }
    ],
    "sg:phone":"+1 570 876 1950",
    "sg:postcode":"18433",
    "sg:province":"PA",
    "sg:tags":[
        "clergy"
    ],
    "wof:name":"Sacred Heart Of Jesus Rectory",
    "wof:placetype":"venue"
},
  "geometry": {"coordinates":[-75.538014,41.533958],"type":"Point"}
}