{
  "type": "Feature",
  "properties": {
    "iso:country":"US",
    "sg:address":"501 Penn Grant Rd",
    "sg:city":"Lancaster",
    "sg:classifiers":[
        {
            "category":"Building & Trades",
            "subcategory":"Landscaping Services",
            "type":"Services"
        }
    ],
    "sg:phone":"+1   ",
    "sg:postcode":"17602",
    "sg:province":"PA",
    "wof:name":"Mann Landscaping",
    "wof:placetype":"venue"
},
  "geometry": {"coordinates":[-76.25561399999999,39.973841],"type":"Point"}
}