{
  "type": "Feature",
  "properties": {
    "addr:full":"2948 Conestoga Rd Glenmoore PA 19343",
    "addr:housenumber":"2948",
    "addr:postcode":"19343",
    "addr:street":"Conestoga Rd",
    "iso:country":"US",
    "sg:address":"2948 Conestoga Rd",
    "sg:city":"Glenmoore",
    "sg:classifiers":[
        {
            "category":"Manufacturing",
            "subcategory":"Building Materials",
            "type":"Manufacturing & Wholesale Goods"
        },
        {
            "category":"Professional",
            "subcategory":"Business Services",
            "type":"Services"
        }
    ],
    "sg:phone":"+1 610 458 4428",
    "sg:postcode":"19343",
    "sg:province":"PA",
    "sg:tags":[
        "interior",
        "consultant",
        "design",
        "decorator",
        "cabinet"
    ],
    "wof:name":"Whole House Cabinetry Inc",
    "wof:placetype":"venue"
},
  "geometry": {"coordinates":[-75.69488200000001,40.116026],"type":"Point"}
}