{
  "type": "Feature",
  "properties": {
    "iso:country":"US",
    "sg:address":"900 W Trenton Ave",
    "sg:city":"Morrisville",
    "sg:classifiers":[
        {
            "category":"Personal",
            "subcategory":"Beauty Salon",
            "type":"Services"
        }
    ],
    "sg:phone":"+1 215 295 2805",
    "sg:postcode":"19067",
    "sg:province":"PA",
    "sg:tags":[
        "manicuring"
    ],
    "wof:name":"Sophia's Nails",
    "wof:placetype":"venue"
},
  "geometry": {"coordinates":[-74.81033600000001,40.200703],"type":"Point"}
}