{
  "type": "Feature",
  "properties": {
    "addr:full":"3587 Old Harrisburg Rd Gettysburg PA 17325",
    "addr:housenumber":"3587",
    "addr:postcode":"17325",
    "addr:street":"Old Harrisburg Rd",
    "iso:country":"US",
    "sg:address":"3587 Old Harrisburg Rd",
    "sg:city":"Gettysburg",
    "sg:classifiers":[
        {
            "category":"Home & Garden",
            "subcategory":"Garden Supply",
            "type":"Retail Goods"
        }
    ],
    "sg:phone":"+1 717 334 0849",
    "sg:postcode":"17325",
    "sg:province":"PA",
    "sg:tags":[
        "mulch"
    ],
    "wof:name":"Nolt Mulch Products",
    "wof:placetype":"venue"
},
  "geometry": {"coordinates":[-77.171314,39.916067],"type":"Point"}
}