{
  "type": "Feature",
  "properties": {
    "iso:country":"US",
    "sg:address":"295 N Clay Rd",
    "sg:city":"Lititz",
    "sg:classifiers":[
        {
            "category":"Organizations",
            "subcategory":"Religious Organization",
            "type":"Services"
        }
    ],
    "sg:phone":"+1 717 738 1444",
    "sg:postcode":"17543",
    "sg:province":"PA",
    "sg:tags":[
        "church"
    ],
    "sg:website":"www.hopelandumc.org",
    "wof:name":"Hopeland United Methodist Chr",
    "wof:placetype":"venue"
},
  "geometry": {"coordinates":[-76.25855,40.228185],"type":"Point"}
}