{
  "type": "Feature",
  "properties": {
    "addr:full":"77 W Laurel St Bethlehem PA 18018",
    "addr:housenumber":"77",
    "addr:postcode":"18018",
    "addr:street":"W Laurel St",
    "iso:country":"US",
    "sg:address":"77 W Laurel St",
    "sg:city":"Bethlehem",
    "sg:classifiers":[
        {
            "category":"Wholesale",
            "subcategory":"Groceries",
            "type":"Manufacturing & Wholesale Goods"
        }
    ],
    "sg:phone":"+1   ",
    "sg:postcode":"18018",
    "sg:province":"PA",
    "sg:tags":[
        "food",
        "specialty",
        "broker"
    ],
    "wof:name":"Harding & Co",
    "wof:placetype":"venue"
},
  "geometry": {"coordinates":[-75.381429,40.628875],"type":"Point"}
}