{
  "type": "Feature",
  "properties": {
    "iso:country":"US",
    "sg:address":"3839 N Broad St",
    "sg:city":"Philadelphia",
    "sg:classifiers":[
        {
            "category":"Personal",
            "subcategory":"Beauty Salon",
            "type":"Services"
        }
    ],
    "sg:phone":"+1 215 223 3388",
    "sg:postcode":"19140",
    "sg:province":"PA",
    "sg:tags":[
        "shop"
    ],
    "wof:name":"Lyons Hair Unique",
    "wof:placetype":"venue"
},
  "geometry": {"coordinates":[-75.150599,40.01171],"type":"Point"}
}