{
  "type": "Feature",
  "properties": {
    "iso:country":"US",
    "sg:address":"1850 Big Sewickley Creek Rd",
    "sg:city":"Sewickley",
    "sg:classifiers":[
        {
            "category":"Organizations",
            "subcategory":"Professional Association",
            "type":"Services"
        }
    ],
    "sg:phone":"+1 724 266 6151",
    "sg:postcode":"15143",
    "sg:province":"PA",
    "wof:name":"Big Sewickley Creek Volunteer",
    "wof:placetype":"venue"
},
  "geometry": {"coordinates":[-80.158694,40.609182],"type":"Point"}
}