{
  "type": "Feature",
  "properties": {
    "addr:full":"1822 Orthodox St Philadelphia PA 19124",
    "addr:housenumber":"1822",
    "addr:postcode":"19124",
    "addr:street":"Orthodox St",
    "iso:country":"US",
    "sg:address":"1822 Orthodox St",
    "sg:city":"Philadelphia",
    "sg:classifiers":[
        {
            "category":"Organizations",
            "subcategory":"Religious Organization",
            "type":"Services"
        }
    ],
    "sg:phone":"+1 215 533 1415",
    "sg:postcode":"19124",
    "sg:province":"PA",
    "sg:tags":[
        "testament",
        "churches-church",
        "christ-new",
        "church"
    ],
    "wof:name":"Holy Cross Church Of Christ",
    "wof:placetype":"venue"
},
  "geometry": {"coordinates":[-75.08148799999999,40.012526],"type":"Point"}
}