{
  "type": "Feature",
  "properties": {
    "addr:full":"193 Indian Cave Rd Shickshinny PA 18655",
    "addr:housenumber":"193",
    "addr:postcode":"18655",
    "addr:street":"Indian Cave Rd",
    "iso:country":"US",
    "sg:address":"193 Indian Cave Rd",
    "sg:city":"Shickshinny",
    "sg:classifiers":[
        {
            "category":"Transit Center",
            "subcategory":"Freight",
            "type":"Transportation"
        },
        {
            "category":"Freight",
            "type":"Transportation"
        }
    ],
    "sg:phone":"+1 570 744 1952",
    "sg:postcode":"18655",
    "sg:province":"PA",
    "sg:tags":[
        "local",
        "trucking-motor",
        "trucking"
    ],
    "wof:name":"J And M Deyo Trucking",
    "wof:placetype":"venue"
},
  "geometry": {"coordinates":[-76.13143700000001,41.219357],"type":"Point"}
}