{
  "type": "Feature",
  "properties": {
    "iso:country":"US",
    "sg:address":"1024 Capouse Ave",
    "sg:city":"Scranton",
    "sg:classifiers":[
        {
            "category":"Mining & Drilling",
            "type":"Manufacturing & Wholesale Goods"
        }
    ],
    "sg:phone":"+1 570 344 2226",
    "sg:postcode":"18509",
    "sg:province":"PA",
    "sg:tags":[
        "coal",
        "shipping"
    ],
    "wof:name":"Diamond Coal Co",
    "wof:placetype":"venue"
},
  "geometry": {"coordinates":[-75.655804,41.420557],"type":"Point"}
}