{
  "type": "Feature",
  "properties": {
    "addr:full":"12 McClane St Cuddy PA 15031",
    "addr:housenumber":"12",
    "addr:postcode":"15031",
    "addr:street":"Mcclane St",
    "iso:country":"US",
    "sg:address":"12 McClane St",
    "sg:city":"Cuddy",
    "sg:classifiers":[
        {
            "category":"Building & Trades",
            "subcategory":"Construction",
            "type":"Services"
        }
    ],
    "sg:phone":"+1   ",
    "sg:postcode":"15031",
    "sg:province":"PA",
    "sg:tags":[
        "company",
        "through",
        "sub",
        "holding",
        "contractor"
    ],
    "wof:name":"Rodio Inc",
    "wof:placetype":"venue"
},
  "geometry": {"coordinates":[-80.170635,40.344893],"type":"Point"}
}