{
  "type": "Feature",
  "properties": {
    "addr:full":"750 Meldon Ave Donora PA 15033",
    "addr:housenumber":"750",
    "addr:postcode":"15033",
    "addr:street":"Meldon Ave",
    "iso:country":"US",
    "sg:address":"750 Meldon Ave",
    "sg:city":"Donora",
    "sg:classifiers":[
        {
            "category":"Shopping",
            "subcategory":"Discount & Variety Stores",
            "type":"Retail Goods"
        },
        {
            "category":"Shopping",
            "subcategory":"Department Store",
            "type":"Retail Goods"
        }
    ],
    "sg:phone":"+1 724 379 9011",
    "sg:postcode":"15033",
    "sg:province":"PA",
    "sg:tags":[
        "shop"
    ],
    "wof:name":"Family Dollar Stores",
    "wof:placetype":"venue"
},
  "geometry": {"coordinates":[-79.85493200000001,40.179943],"type":"Point"}
}