{
  "type": "Feature",
  "properties": {
    "iso:country":"US",
    "sg:address":"4 N Shore Ctr",
    "sg:city":"Pittsburgh",
    "sg:classifiers":[
        {
            "category":"Professional",
            "subcategory":"Lawyer & Legal Services",
            "type":"Services"
        }
    ],
    "sg:phone":"+1 412 918 7929",
    "sg:postcode":"15212",
    "sg:province":"PA",
    "wof:name":"Schweers Timothy J ESQ",
    "wof:placetype":"venue"
},
  "geometry": {"coordinates":[-80.0181,40.445674],"type":"Point"}
}