{
  "type": "Feature",
  "properties": {
    "iso:country":"US",
    "sg:address":"8 S Village Cir",
    "sg:city":"Reinholds",
    "sg:classifiers":[
        {
            "category":"Shopping",
            "subcategory":"Hobbies, Toys, & Games",
            "type":"Retail Goods"
        }
    ],
    "sg:phone":"+1 717 484 1137",
    "sg:postcode":"17569",
    "sg:province":"PA",
    "sg:tags":[
        "doll"
    ],
    "wof:name":"My Dolly Dearest",
    "wof:placetype":"venue"
},
  "geometry": {"coordinates":[-76.073859,40.238201],"type":"Point"}
}