{
  "type": "Feature",
  "properties": {
    "addr:full":"406 Mary St Jeannette PA 15644",
    "addr:housenumber":"406",
    "addr:postcode":"15644",
    "addr:street":"Mary St",
    "iso:country":"US",
    "sg:address":"406 Mary St",
    "sg:city":"Jeannette",
    "sg:classifiers":[
        {
            "category":"Professional",
            "type":"Services"
        }
    ],
    "sg:phone":"+1   ",
    "sg:postcode":"15644",
    "sg:province":"PA",
    "wof:name":"Jeannette Chapter 3572 of AMR",
    "wof:placetype":"venue"
},
  "geometry": {"coordinates":[-79.605256,40.319584],"type":"Point"}
}