{
  "type": "Feature",
  "properties": {
    "iso:country":"US",
    "sg:address":"2805 N 47th St Ste B",
    "sg:city":"Philadelphia",
    "sg:classifiers":[
        {
            "category":"Real Estate",
            "subcategory":"Real Estate Operator",
            "type":"Services"
        }
    ],
    "sg:phone":"+1 215 473 7755",
    "sg:postcode":"19131",
    "sg:province":"PA",
    "sg:tags":[
        "apartment"
    ],
    "wof:name":"Iroquois Apts",
    "wof:placetype":"venue"
},
  "geometry": {"coordinates":[-75.22339599999999,40.001801],"type":"Point"}
}