{
  "type": "Feature",
  "properties": {
    "addr:full":"704 Braddock Ave Braddock PA 15104",
    "addr:housenumber":"704",
    "addr:postcode":"15104",
    "addr:street":"Braddock Ave",
    "iso:country":"US",
    "sg:address":"704 Braddock Ave",
    "sg:city":"Braddock",
    "sg:classifiers":[
        {
            "category":"Personal",
            "subcategory":"Beauty Salon",
            "type":"Services"
        }
    ],
    "sg:phone":"+1   ",
    "sg:postcode":"15104",
    "sg:province":"PA",
    "sg:tags":[
        "shop"
    ],
    "wof:name":"Fabulous TS",
    "wof:placetype":"venue"
},
  "geometry": {"coordinates":[-79.86627799999999,40.401508],"type":"Point"}
}