{
  "type": "Feature",
  "properties": {
    "addr:full":"50 E Germantown Pike Norristown PA 19401",
    "addr:housenumber":"50",
    "addr:postcode":"19401",
    "addr:street":"E Germantown Pike",
    "iso:country":"US",
    "sg:address":"50 E Germantown Pike",
    "sg:city":"Norristown",
    "sg:phone":"+1 610 279 6628",
    "sg:postcode":"19401",
    "sg:province":"PA",
    "sg:website":"http://www.pennchristian.org",
    "wof:name":"Penn Christian Academy",
    "wof:placetype":"venue"
},
  "geometry": {"coordinates":[-75.308407,40.138876],"type":"Point"}
}