{
  "type": "Feature",
  "properties": {
    "addr:full":"139 Beacon Ln Butler PA 16001",
    "addr:housenumber":"139",
    "addr:postcode":"16001",
    "addr:street":"Beacon Ln",
    "iso:country":"US",
    "sg:address":"139 Beacon Ln",
    "sg:city":"Butler",
    "sg:classifiers":[
        {
            "category":"Professional",
            "subcategory":"Advertising",
            "type":"Services"
        }
    ],
    "sg:phone":"+1 724 360 5091",
    "sg:postcode":"16001",
    "sg:province":"PA",
    "sg:tags":[
        "counselor"
    ],
    "wof:name":"Bill's Promotional Advertising",
    "wof:placetype":"venue"
},
  "geometry": {"coordinates":[-79.966145,40.946879],"type":"Point"}
}