{
  "type": "Feature",
  "properties": {
    "iso:country":"US",
    "sg:address":"4614 E Street Rd",
    "sg:city":"Feastervl Trvs",
    "sg:classifiers":[
        {
            "category":"Professional",
            "subcategory":"Employment Agencies",
            "type":"Services"
        }
    ],
    "sg:phone":"+1 215 322 8700",
    "sg:postcode":"19053",
    "sg:province":"PA",
    "sg:tags":[
        "opportunity"
    ],
    "wof:name":"Express Personnel Svc",
    "wof:placetype":"venue"
},
  "geometry": {"coordinates":[-74.98224500000001,40.136101],"type":"Point"}
}