{
  "type": "Feature",
  "properties": {
    "addr:full":"2641 E Cumberland St Lebanon PA 17042",
    "addr:housenumber":"2641",
    "addr:postcode":"17042",
    "addr:street":"E Cumberland St",
    "iso:country":"US",
    "sg:address":"2641 E Cumberland St",
    "sg:city":"Lebanon",
    "sg:classifiers":[
        {
            "category":"Shopping",
            "type":"Retail Goods"
        }
    ],
    "sg:phone":"+1   ",
    "sg:postcode":"17042",
    "sg:province":"PA",
    "sg:tags":[
        "merchandise"
    ],
    "wof:name":"Paradise Island of Pets",
    "wof:placetype":"venue"
},
  "geometry": {"coordinates":[-76.357563,40.361057],"type":"Point"}
}