{
  "type": "Feature",
  "properties": {
    "addr:full":"249 E Roy Furman Hwy Waynesburg PA 15370",
    "addr:housenumber":"249",
    "addr:postcode":"15370",
    "addr:street":"E Roy Furman Hwy",
    "iso:country":"US",
    "sg:address":"249 E Roy Furman Hwy",
    "sg:city":"Waynesburg",
    "sg:classifiers":[
        {
            "category":"Autos & Motor Vehicles",
            "subcategory":"Automobile Sales",
            "type":"Retail Goods"
        }
    ],
    "sg:phone":"+1 724 627 6171",
    "sg:postcode":"15370",
    "sg:province":"PA",
    "sg:tags":[
        "car",
        "dealer"
    ],
    "sg:website":"www.bortzauto.com",
    "wof:name":"Bortz Chevrolet-Cadillac Inc",
    "wof:placetype":"venue"
},
  "geometry": {"coordinates":[-80.155844,39.897969],"type":"Point"}
}