{
  "type": "Feature",
  "properties": {
    "addr:full":"832 Lancaster Rd Manheim PA 17545",
    "addr:housenumber":"832",
    "addr:postcode":"17545",
    "addr:street":"Lancaster Rd",
    "iso:country":"US",
    "sg:address":"832 Lancaster Rd",
    "sg:city":"Manheim",
    "sg:classifiers":[
        {
            "category":"Industrial Area",
            "type":"Public Place"
        }
    ],
    "sg:phone":"+1 717 665 7145",
    "sg:postcode":"17545",
    "sg:province":"PA",
    "sg:tags":[
        "development"
    ],
    "wof:name":"Hamilton Motor Sports",
    "wof:placetype":"venue"
},
  "geometry": {"coordinates":[-76.380315,40.146537],"type":"Point"}
}