{
  "type": "Feature",
  "properties": {
    "iso:country":"US",
    "sg:address":"40 N Church St",
    "sg:city":"Hazleton",
    "sg:classifiers":[
        {
            "category":"Government",
            "subcategory":"Police Station",
            "type":"Public Place"
        }
    ],
    "sg:phone":"+1   ",
    "sg:postcode":"18201",
    "sg:province":"PA",
    "sg:tags":[
        "protection"
    ],
    "wof:name":"Police Department",
    "wof:placetype":"venue"
},
  "geometry": {"coordinates":[-75.97628400000001,40.956334],"type":"Point"}
}