{
  "type": "Feature",
  "properties": {
    "iso:country":"US",
    "sg:address":"1217 1st Ave",
    "sg:city":"Media",
    "sg:classifiers":[
        {
            "category":"Building & Trades",
            "subcategory":"Electrical",
            "type":"Services"
        }
    ],
    "sg:phone":"+1 610 892 2802",
    "sg:postcode":"19063",
    "sg:province":"PA",
    "sg:tags":[
        "electrical",
        "contractor"
    ],
    "wof:name":"DGE Electric",
    "wof:placetype":"venue"
},
  "geometry": {"coordinates":[-75.389197,39.934101],"type":"Point"}
}