{
  "type": "Feature",
  "properties": {
    "iso:country":"US",
    "sg:address":"7276 Union Deposit Rd",
    "sg:city":"Hummelstown",
    "sg:classifiers":[
        {
            "category":"Manufacturing",
            "subcategory":"Tools & Machinery",
            "type":"Manufacturing & Wholesale Goods"
        }
    ],
    "sg:phone":"+1   ",
    "sg:postcode":"17036",
    "sg:province":"PA",
    "sg:tags":[
        "machine",
        "shop",
        "job"
    ],
    "wof:name":"Doug Walters Machine Shop",
    "wof:placetype":"venue"
},
  "geometry": {"coordinates":[-76.68774500000001,40.2893],"type":"Point"}
}