{
  "type": "Feature",
  "properties": {
    "iso:country":"US",
    "sg:address":"520 Long Meadow Rd",
    "sg:city":"Norristown",
    "sg:classifiers":[
        {
            "category":"Wholesale",
            "subcategory":"Machinery & Supplies",
            "type":"Manufacturing & Wholesale Goods"
        }
    ],
    "sg:phone":"+1   ",
    "sg:postcode":"19403",
    "sg:province":"PA",
    "sg:tags":[
        "janitorial"
    ],
    "wof:name":"Montco Indus Sanitation Pdts",
    "wof:placetype":"venue"
},
  "geometry": {"coordinates":[-75.38927099999999,40.156637],"type":"Point"}
}