{
  "type": "Feature",
  "properties": {
    "iso:country":"US",
    "sg:address":"19 S Macdade Blvd",
    "sg:city":"Darby",
    "sg:classifiers":[
        {
            "category":"Shopping",
            "subcategory":"Pawn Shop",
            "type":"Retail Goods"
        }
    ],
    "sg:phone":"+1 610 532 1919",
    "sg:postcode":"19023",
    "sg:province":"PA",
    "sg:tags":[
        "pawnbroker"
    ],
    "wof:name":"Darby Pawn Shop",
    "wof:placetype":"venue"
},
  "geometry": {"coordinates":[-75.264308,39.920868],"type":"Point"}
}