{
  "type": "Feature",
  "properties": {
    "addr:full":"829 Ridge Rd Telford PA 18969",
    "addr:housenumber":"829",
    "addr:postcode":"18969",
    "addr:street":"Ridge Rd",
    "iso:country":"US",
    "sg:address":"829 Ridge Rd",
    "sg:city":"Telford",
    "sg:classifiers":[
        {
            "category":"Farming",
            "subcategory":"Farm",
            "type":"Manufacturing & Wholesale Goods"
        }
    ],
    "sg:phone":"+1 215 234 4835",
    "sg:postcode":"18969",
    "sg:province":"PA",
    "wof:name":"Cedar Lane Farm",
    "wof:placetype":"venue"
},
  "geometry": {"coordinates":[-75.42911700000001,40.318718],"type":"Point"}
}