{
  "type": "Feature",
  "properties": {
    "iso:country":"US",
    "sg:address":"212 Dumont Pl",
    "sg:city":"Philadelphia",
    "sg:classifiers":[
        {
            "category":"Restaurant",
            "type":"Food & Drink"
        }
    ],
    "sg:phone":"+1   ",
    "sg:postcode":"19116",
    "sg:province":"PA",
    "sg:tags":[
        "chinese"
    ],
    "wof:name":"Taste Queen Chinese Restaurant",
    "wof:placetype":"venue"
},
  "geometry": {"coordinates":[-75.029635,40.123012],"type":"Point"}
}