{
  "type": "Feature",
  "properties": {
    "addr:full":"228 E Lincoln Hwy Coatesville PA 19320",
    "addr:housenumber":"228",
    "addr:postcode":"19320",
    "addr:street":"E Lincoln Hwy",
    "iso:country":"US",
    "sg:address":"228 E Lincoln Hwy",
    "sg:city":"Coatesville",
    "sg:phone":"+1 610 384 1683",
    "sg:postcode":"19320",
    "sg:province":"PA",
    "sg:website":"http://www.coatesvillearmynavy.com",
    "wof:name":"Coatesville Army & Navy Store",
    "wof:placetype":"venue"
},
  "geometry": {"coordinates":[-75.821448,39.983479],"type":"Point"}
}