{
  "type": "Feature",
  "properties": {
    "iso:country":"US",
    "sg:address":"104 Beaumont Ter",
    "sg:city":"Lansdale",
    "sg:classifiers":[
        {
            "category":"Banks & Credit Unions",
            "subcategory":"Bank",
            "type":"Services"
        }
    ],
    "sg:phone":"+1 215 368 5500",
    "sg:postcode":"19446",
    "sg:province":"PA",
    "sg:tags":[
        "loan",
        "real estate"
    ],
    "wof:name":"LITTLE Hill Inc",
    "wof:placetype":"venue"
},
  "geometry": {"coordinates":[-75.228301,40.253643],"type":"Point"}
}