{
  "type": "Feature",
  "properties": {
    "iso:country":"US",
    "sg:address":"3000 Library Rd",
    "sg:city":"Pittsburgh",
    "sg:classifiers":[
        {
            "category":"Food & Beverages",
            "subcategory":"Meat & Fish",
            "type":"Retail Goods"
        }
    ],
    "sg:phone":"+1   ",
    "sg:postcode":"15234",
    "sg:province":"PA",
    "sg:tags":[
        "market"
    ],
    "wof:name":"Barkers Meats & Poultry Inc",
    "wof:placetype":"venue"
},
  "geometry": {"coordinates":[-80.006362,40.373771],"type":"Point"}
}