{
  "type": "Feature",
  "properties": {
    "iso:country":"US",
    "sg:address":"952 W 25th St",
    "sg:city":"Erie",
    "sg:classifiers":[
        {
            "category":"Building & Trades",
            "subcategory":"Electrical",
            "type":"Services"
        }
    ],
    "sg:phone":"+1   ",
    "sg:postcode":"16502",
    "sg:province":"PA",
    "sg:tags":[
        "electrical",
        "contractor"
    ],
    "wof:name":"Rci Electrical System",
    "wof:placetype":"venue"
},
  "geometry": {"coordinates":[-80.09385399999999,42.105694],"type":"Point"}
}