{
  "type": "Feature",
  "properties": {
    "addr:full":"201 E Green St Mechanicsburg PA 17055",
    "addr:housenumber":"201",
    "addr:postcode":"17055",
    "addr:street":"E Green St",
    "iso:country":"US",
    "sg:address":"201 E Green St",
    "sg:city":"Mechanicsburg",
    "sg:classifiers":[
        {
            "category":"Organizations",
            "subcategory":"Religious Organization",
            "type":"Services"
        }
    ],
    "sg:phone":"+1 717 697 1153",
    "sg:postcode":"17055",
    "sg:province":"PA",
    "sg:website":"www.churchofgod.cc",
    "wof:name":"Worship House Church of God",
    "wof:placetype":"venue"
},
  "geometry": {"coordinates":[-77.005291,40.216474],"type":"Point"}
}