{
  "type": "Feature",
  "properties": {
    "addr:full":"426 Gaskill St Philadelphia PA 19147",
    "addr:housenumber":"426",
    "addr:postcode":"19147",
    "addr:street":"Gaskill St",
    "iso:country":"US",
    "sg:address":"426 Gaskill St",
    "sg:city":"Philadelphia",
    "sg:classifiers":[
        {
            "category":"Wholesale",
            "subcategory":"Durable Goods & Equipment",
            "type":"Manufacturing & Wholesale Goods"
        }
    ],
    "sg:phone":"+1   ",
    "sg:postcode":"19147",
    "sg:province":"PA",
    "wof:name":"Kmb Trading",
    "wof:placetype":"venue"
},
  "geometry": {"coordinates":[-75.150497,39.94224],"type":"Point"}
}