{
  "type": "Feature",
  "properties": {
    "iso:country":"US",
    "sg:address":"463 Brownsdale Rd",
    "sg:city":"Renfrew",
    "sg:classifiers":[
        {
            "category":"Wholesale",
            "subcategory":"Drugs",
            "type":"Manufacturing & Wholesale Goods"
        }
    ],
    "sg:phone":"+1 724 586 2321",
    "sg:postcode":"16053",
    "sg:province":"PA",
    "sg:tags":[
        "cosmetic"
    ],
    "wof:name":"FCD Inc",
    "wof:placetype":"venue"
},
  "geometry": {"coordinates":[-79.968199,40.776686],"type":"Point"}
}