{
  "type": "Feature",
  "properties": {
    "iso:country":"US",
    "sg:address":"3552 Witte St",
    "sg:city":"Philadelphia",
    "sg:classifiers":[
        {
            "category":"Retail",
            "subcategory":"Repair Shop",
            "type":"Services"
        }
    ],
    "sg:phone":"+1 215 288 5100",
    "sg:postcode":"19134",
    "sg:province":"PA",
    "sg:tags":[
        "refrigeration",
        "equipment",
        "employer",
        "commercial",
        "professional"
    ],
    "wof:name":"Almond Refrigeration",
    "wof:placetype":"venue"
},
  "geometry": {"coordinates":[-75.099996,39.995057],"type":"Point"}
}