{
  "type": "Feature",
  "properties": {
    "iso:country":"US",
    "sg:address":"628 Cedar St",
    "sg:city":"Easton",
    "sg:classifiers":[
        {
            "category":"Manufacturing",
            "subcategory":"Tools & Machinery",
            "type":"Manufacturing & Wholesale Goods"
        }
    ],
    "sg:phone":"+1   ",
    "sg:postcode":"18045",
    "sg:province":"PA",
    "sg:tags":[
        "control",
        "environmental",
        "mfg"
    ],
    "wof:name":"Bruce S Comm Refrig",
    "wof:placetype":"venue"
},
  "geometry": {"coordinates":[-75.247823,40.680607],"type":"Point"}
}