{
  "type": "Feature",
  "properties": {
    "iso:country":"US",
    "sg:address":"4929 Oxford Ct",
    "sg:city":"Bensalem",
    "sg:classifiers":[
        {
            "category":"Personal",
            "type":"Services"
        }
    ],
    "sg:phone":"+1 215 757 7498",
    "sg:postcode":"19020",
    "sg:province":"PA",
    "sg:tags":[
        "pet",
        "exercising"
    ],
    "wof:name":"Heart To Heart Pet Sitting",
    "wof:placetype":"venue"
},
  "geometry": {"coordinates":[-74.935205,40.137101],"type":"Point"}
}