{
  "type": "Feature",
  "properties": {
    "iso:country":"US",
    "sg:address":"609 W Porter St",
    "sg:city":"Philadelphia",
    "sg:classifiers":[
        {
            "category":"Health Services",
            "subcategory":"Clinic",
            "type":"Services"
        }
    ],
    "sg:phone":"+1 215 271 9699",
    "sg:postcode":"19148",
    "sg:province":"PA",
    "sg:tags":[
        "welfare"
    ],
    "wof:name":"South Philadelphia Health Center, Inc.",
    "wof:placetype":"venue"
},
  "geometry": {"coordinates":[-75.15803099999999,39.917744],"type":"Point"}
}