{
  "type": "Feature",
  "properties": {
    "iso:country":"US",
    "sg:address":"160 Grandview Rd",
    "sg:city":"Boyertown",
    "sg:classifiers":[
        {
            "category":"Manufacturing",
            "subcategory":"Pet Food",
            "type":"Manufacturing & Wholesale Goods"
        },
        {
            "category":"Farming",
            "subcategory":"Farm",
            "type":"Manufacturing & Wholesale Goods"
        }
    ],
    "sg:phone":"+1 610 367 6160",
    "sg:postcode":"19512",
    "sg:province":"PA",
    "sg:tags":[
        "hay"
    ],
    "wof:name":"Carl Johnson",
    "wof:placetype":"venue"
},
  "geometry": {"coordinates":[-75.684265,40.343998],"type":"Point"}
}