{
  "type": "Feature",
  "properties": {
    "iso:country":"US",
    "sg:address":"209 Powder Mill Rd",
    "sg:city":"Jessup",
    "sg:classifiers":[
        {
            "category":"Building & Trades",
            "subcategory":"Construction",
            "type":"Services"
        }
    ],
    "sg:phone":"+1   ",
    "sg:postcode":"18434",
    "sg:province":"PA",
    "sg:tags":[
        "contractor"
    ],
    "wof:name":"Mark Vanston",
    "wof:placetype":"venue"
},
  "geometry": {"coordinates":[-75.57733899999999,41.470047],"type":"Point"}
}