{
  "type": "Feature",
  "properties": {
    "addr:full":"416 Wanamaker Ave Essington PA 19029",
    "addr:housenumber":"416",
    "addr:postcode":"19029",
    "addr:street":"Wanamaker Ave",
    "iso:country":"US",
    "sg:address":"416 Wanamaker Ave",
    "sg:city":"Essington",
    "sg:classifiers":[
        {
            "category":"Restaurant",
            "type":"Food & Drink"
        }
    ],
    "sg:phone":"+1 610 521 6871",
    "sg:postcode":"19029",
    "sg:province":"PA",
    "sg:tags":[
        "sandwich",
        "eating"
    ],
    "wof:name":"Jim's Place",
    "wof:placetype":"venue"
},
  "geometry": {"coordinates":[-75.30076699999999,39.86559],"type":"Point"}
}