{
  "type": "Feature",
  "properties": {
    "addr:full":"11494 Airport Rd Meadville PA 16335",
    "addr:housenumber":"11494",
    "addr:postcode":"16335",
    "addr:street":"Airport Rd",
    "iso:country":"US",
    "sg:address":"11494 Airport Rd",
    "sg:city":"Meadville",
    "sg:classifiers":[
        {
            "category":"Manufacturing",
            "subcategory":"Tools & Machinery",
            "type":"Manufacturing & Wholesale Goods"
        }
    ],
    "sg:phone":"+1 814 724 2865",
    "sg:postcode":"16335",
    "sg:province":"PA",
    "sg:tags":[
        "die",
        "maker"
    ],
    "wof:name":"Canto Tool Corp",
    "wof:placetype":"venue"
},
  "geometry": {"coordinates":[-80.208198,41.625235],"type":"Point"}
}