{
  "type": "Feature",
  "properties": {
    "iso:country":"US",
    "sg:address":"124 W Airport Rd",
    "sg:city":"Lititz",
    "sg:classifiers":[
        {
            "category":"Manufacturing",
            "subcategory":"Food",
            "type":"Manufacturing & Wholesale Goods"
        }
    ],
    "sg:phone":"+1 717 560 1882",
    "sg:postcode":"17543",
    "sg:province":"PA",
    "sg:tags":[
        "product",
        "manufacturer",
        "mfg"
    ],
    "sg:website":"www.keystonepretzels.com",
    "wof:name":"Keystone Pretzel Bakery Inc",
    "wof:placetype":"venue"
},
  "geometry": {"coordinates":[-76.30906299999999,40.116935],"type":"Point"}
}