{
  "type": "Feature",
  "properties": {
    "addr:full":"1212 N Center Ave Somerset PA 15501",
    "addr:housenumber":"1212",
    "addr:postcode":"15501",
    "addr:street":"N Center Ave",
    "iso:country":"US",
    "sg:address":"1212 N Center Ave",
    "sg:city":"Somerset",
    "sg:classifiers":[
        {
            "category":"Food & Beverages",
            "subcategory":"Groceries & Convenience Stores",
            "type":"Retail Goods"
        }
    ],
    "sg:phone":"+1 814 443 4175",
    "sg:postcode":"15501",
    "sg:province":"PA",
    "wof:name":"Sheetz Inc",
    "wof:placetype":"venue"
},
  "geometry": {"coordinates":[-79.077102,40.022752],"type":"Point"}
}