{
  "type": "Feature",
  "properties": {
    "iso:country":"US",
    "sg:address":"5341 W Lake Rd",
    "sg:city":"Erie",
    "sg:classifiers":[
        {
            "category":"Building & Trades",
            "subcategory":"Landscaping Services",
            "type":"Services"
        },
        {
            "category":"Home & Garden",
            "subcategory":"Garden Supply",
            "type":"Retail Goods"
        },
        {
            "category":"Manufacturing",
            "subcategory":"Paper Products",
            "type":"Manufacturing & Wholesale Goods"
        }
    ],
    "sg:phone":"+1 814 835 6960",
    "sg:postcode":"16505",
    "sg:province":"PA",
    "sg:tags":[
        "consultant",
        "bamboo",
        "designer",
        "landscape"
    ],
    "wof:name":"Stan's Garden Ctr West",
    "wof:placetype":"venue"
},
  "geometry": {"coordinates":[-80.201934,42.076723],"type":"Point"}
}