{
  "type": "Feature",
  "properties": {
    "addr:full":"326 3rd Ave Pittsburgh PA 15222",
    "addr:housenumber":"326",
    "addr:postcode":"15222",
    "addr:street":"3Rd Ave",
    "iso:country":"US",
    "sg:address":"326 3rd Ave",
    "sg:city":"Pittsburgh",
    "sg:classifiers":[
        {
            "category":"Banks & Credit Unions",
            "subcategory":"Investment Brokerage",
            "type":"Services"
        }
    ],
    "sg:phone":"+1 412 642 6666",
    "sg:postcode":"15222",
    "sg:province":"PA",
    "sg:tags":[
        "investing"
    ],
    "wof:name":"Levine Arnold I Invstmnts",
    "wof:placetype":"venue"
},
  "geometry": {"coordinates":[-80.000801,40.4384],"type":"Point"}
}