{
  "type": "Feature",
  "properties": {
    "addr:full":"Doylestown Buckingham PA 18912",
    "addr:postcode":"18912",
    "iso:country":"US",
    "sg:address":"Doylestown",
    "sg:city":"Buckingham",
    "sg:classifiers":[
        {
            "category":"Building & Trades",
            "subcategory":"Plumbing",
            "type":"Services"
        }
    ],
    "sg:phone":"+1 215 794 3557",
    "sg:postcode":"18912",
    "sg:province":"PA",
    "wof:name":"American Leak Detection",
    "wof:placetype":"venue"
},
  "geometry": {"coordinates":[-75.0625,40.321701],"type":"Point"}
}