{
  "type": "Feature",
  "properties": {
    "iso:country":"US",
    "sg:address":"12 Scott Dr",
    "sg:city":"Bradford",
    "sg:classifiers":[
        {
            "category":"Building & Trades",
            "subcategory":"Construction",
            "type":"Services"
        }
    ],
    "sg:phone":"+1   ",
    "sg:postcode":"16701",
    "sg:province":"PA",
    "sg:tags":[
        "house"
    ],
    "wof:name":"Paul T Casey Construction",
    "wof:placetype":"venue"
},
  "geometry": {"coordinates":[-78.650823,41.972646],"type":"Point"}
}