{
  "type": "Feature",
  "properties": {
    "addr:full":"237 North St Millersburg PA 17061",
    "addr:housenumber":"237",
    "addr:postcode":"17061",
    "addr:street":"North St",
    "iso:country":"US",
    "sg:address":"237 North St",
    "sg:city":"Millersburg",
    "sg:classifiers":[
        {
            "category":"Professional",
            "type":"Services"
        }
    ],
    "sg:phone":"+1   ",
    "sg:postcode":"17061",
    "sg:province":"PA",
    "wof:name":"Joy E Breach",
    "wof:placetype":"venue"
},
  "geometry": {"coordinates":[-76.95998899999999,40.541542],"type":"Point"}
}