{
  "type": "Feature",
  "properties": {
    "iso:country":"US",
    "sg:address":"18 Terminal Way",
    "sg:city":"Pittsburgh",
    "sg:classifiers":[
        {
            "category":"Professional",
            "subcategory":"Computer Services",
            "type":"Services"
        }
    ],
    "sg:phone":"+1 412 381 7750",
    "sg:postcode":"15219",
    "sg:province":"PA",
    "sg:tags":[
        "internet"
    ],
    "wof:name":"Interservers Technology",
    "wof:placetype":"venue"
},
  "geometry": {"coordinates":[-79.996272,40.430721],"type":"Point"}
}