{
  "type": "Feature",
  "properties": {
    "iso:country":"US",
    "sg:address":"110 Stevens Ridge Dr",
    "sg:city":"Clairton",
    "sg:classifiers":[
        {
            "category":"Building & Trades",
            "subcategory":"Electrical",
            "type":"Services"
        }
    ],
    "sg:phone":"+1   ",
    "sg:postcode":"15025",
    "sg:province":"PA",
    "sg:tags":[
        "electrical",
        "contractor"
    ],
    "wof:name":"Sargent Electric Co",
    "wof:placetype":"venue"
},
  "geometry": {"coordinates":[-79.930691,40.294875],"type":"Point"}
}