{
  "type": "Feature",
  "properties": {
    "addr:full":"1549 Clark Dr Morrisville PA 19067",
    "addr:housenumber":"1549",
    "addr:postcode":"19067",
    "addr:street":"Clark Dr",
    "iso:country":"US",
    "sg:address":"1549 Clark Dr",
    "sg:city":"Morrisville",
    "sg:classifiers":[
        {
            "category":"Manufacturing",
            "subcategory":"Tools & Machinery",
            "type":"Manufacturing & Wholesale Goods"
        }
    ],
    "sg:phone":"+1   ",
    "sg:postcode":"19067",
    "sg:province":"PA",
    "sg:tags":[
        "electrical",
        "mfg"
    ],
    "wof:name":"Secheron USA Inc",
    "wof:placetype":"venue"
},
  "geometry": {"coordinates":[-74.867307,40.225978],"type":"Point"}
}