{
  "type": "Feature",
  "properties": {
    "iso:country":"US",
    "sg:address":"117 W Pike St",
    "sg:city":"Canonsburg",
    "sg:classifiers":[
        {
            "category":"Shopping",
            "subcategory":"Clothing, Apparel, & Fashions",
            "type":"Retail Goods"
        }
    ],
    "sg:phone":"+1 724 746 5424",
    "sg:postcode":"15317",
    "sg:province":"PA",
    "sg:tags":[
        "furnishing"
    ],
    "wof:name":"J M Camerseni Clothier",
    "wof:placetype":"venue"
},
  "geometry": {"coordinates":[-80.19001900000001,40.258255],"type":"Point"}
}