{
  "type": "Feature",
  "properties": {
    "addr:full":"460 Manor Ave Downingtown PA 19335",
    "addr:housenumber":"460",
    "addr:postcode":"19335",
    "addr:street":"Manor Ave",
    "iso:country":"US",
    "sg:address":"460 Manor Ave",
    "sg:city":"Downingtown",
    "sg:classifiers":[
        {
            "category":"Place Of Worship",
            "subcategory":"Church",
            "type":"Public Place"
        },
        {
            "category":"Place Of Worship",
            "type":"Public Place"
        }
    ],
    "sg:phone":"+1 610 269 8294",
    "sg:postcode":"19335",
    "sg:province":"PA",
    "sg:tags":[
        "testament",
        "churches-church",
        "christ",
        "christ-new"
    ],
    "wof:name":"St Joseph Church",
    "wof:placetype":"venue"
},
  "geometry": {"coordinates":[-75.718772,40.010208],"type":"Point"}
}