{
  "type": "Feature",
  "properties": {
    "addr:full":"2006 W 8th St Erie PA 16505",
    "addr:housenumber":"2006",
    "addr:postcode":"16505",
    "addr:street":"W 8Th St",
    "iso:country":"US",
    "sg:address":"2006 W 8th St",
    "sg:city":"Erie",
    "sg:classifiers":[
        {
            "category":"Professional",
            "type":"Services"
        },
        {
            "category":"Shopping",
            "type":"Retail Goods"
        }
    ],
    "sg:phone":"+1 814 456 4794",
    "sg:postcode":"16505",
    "sg:province":"PA",
    "sg:tags":[
        "art",
        "gallery",
        "dealer"
    ],
    "sg:website":"www.sabolgallery.com",
    "wof:name":"Sabol James E Studio/Gallery",
    "wof:placetype":"venue"
},
  "geometry": {"coordinates":[-80.12810399999999,42.111265],"type":"Point"}
}