{
  "type": "Feature",
  "properties": {
    "iso:country":"US",
    "sg:address":"5101 Unruh Ave",
    "sg:city":"Philadelphia",
    "sg:classifiers":[
        {
            "category":"Freight",
            "type":"Transportation"
        }
    ],
    "sg:phone":"+1 215 335 5500",
    "sg:postcode":"19135",
    "sg:province":"PA",
    "sg:tags":[
        "mover"
    ],
    "wof:name":"Superior Moving & Storage",
    "wof:placetype":"venue"
},
  "geometry": {"coordinates":[-75.04053399999999,40.017125],"type":"Point"}
}