{
  "type": "Feature",
  "properties": {
    "iso:country":"US",
    "sg:address":"202 S Broad St",
    "sg:city":"West Hazleton",
    "sg:classifiers":[
        {
            "category":"Bars & Pubs",
            "type":"Food & Drink"
        }
    ],
    "sg:phone":"+1 570 453 1699",
    "sg:postcode":"18202",
    "sg:province":"PA",
    "wof:name":"Iroc-K Cafe",
    "wof:placetype":"venue"
},
  "geometry": {"coordinates":[-75.995046,40.95659],"type":"Point"}
}