{
  "type": "Feature",
  "properties": {
    "iso:country":"US",
    "sg:address":"930 W Rte 897",
    "sg:city":"Reinholds",
    "sg:classifiers":[
        {
            "category":"Organizations",
            "subcategory":"Religious Organization",
            "type":"Services"
        }
    ],
    "sg:phone":"+1 717 336 3113",
    "sg:postcode":"17569",
    "sg:province":"PA",
    "sg:tags":[
        "church"
    ],
    "wof:name":"Bread Of Life Fellowship Chr",
    "wof:placetype":"venue"
},
  "geometry": {"coordinates":[-76.145,40.28101],"type":"Point"}
}