{
  "type": "Feature",
  "properties": {
    "addr:full":"671 Millcross Rd Lancaster PA 17601",
    "addr:housenumber":"671",
    "addr:postcode":"17601",
    "addr:street":"Millcross Rd",
    "iso:country":"US",
    "sg:address":"671 Millcross Rd",
    "sg:city":"Lancaster",
    "sg:classifiers":[
        {
            "category":"Professional",
            "subcategory":"Lawyer & Legal Services",
            "type":"Services"
        }
    ],
    "sg:phone":"+1 717 394 4025",
    "sg:postcode":"17601",
    "sg:province":"PA",
    "sg:tags":[
        "attorney"
    ],
    "wof:name":"Daniel J Mazaheri",
    "wof:placetype":"venue"
},
  "geometry": {"coordinates":[-76.259264,40.069388],"type":"Point"}
}