{
  "type": "Feature",
  "properties": {
    "iso:country":"US",
    "sg:address":"2992 Green Valley Rd",
    "sg:city":"Claysville",
    "sg:classifiers":[
        {
            "category":"Food & Beverages",
            "subcategory":"Meat & Fish",
            "type":"Retail Goods"
        }
    ],
    "sg:phone":"+1   ",
    "sg:postcode":"15323",
    "sg:province":"PA",
    "wof:name":"Alberts Meats",
    "wof:placetype":"venue"
},
  "geometry": {"coordinates":[-80.356087,40.146918],"type":"Point"}
}