{
  "type": "Feature",
  "properties": {
    "iso:country":"US",
    "sg:address":"1760 Market St Fl 8",
    "sg:city":"Philadelphia",
    "sg:classifiers":[
        {
            "category":"Professional",
            "subcategory":"Printing & Photocopies",
            "type":"Services"
        }
    ],
    "sg:phone":"+1 215 557 7070",
    "sg:postcode":"19103",
    "sg:province":"PA",
    "wof:name":"Ikon Office Solutions",
    "wof:placetype":"venue"
},
  "geometry": {"coordinates":[-75.16950199999999,39.953098],"type":"Point"}
}