{
  "type": "Feature",
  "properties": {
    "addr:full":"1315 E Crawford Ave Connellsville PA 15425",
    "addr:housenumber":"1315",
    "addr:postcode":"15425",
    "addr:street":"E Crawford Ave",
    "iso:country":"US",
    "sg:address":"1315 E Crawford Ave",
    "sg:city":"Connellsville",
    "sg:classifiers":[
        {
            "category":"Food & Beverages",
            "subcategory":"Specialty",
            "type":"Retail Goods"
        }
    ],
    "sg:phone":"+1   ",
    "sg:postcode":"15425",
    "sg:province":"PA",
    "wof:name":"Cornucopia Gourmet Market",
    "wof:placetype":"venue"
},
  "geometry": {"coordinates":[-79.58096,40.035083],"type":"Point"}
}