{
  "type": "Feature",
  "properties": {
    "addr:full":"317 W Lancaster Ave Exton PA 19341",
    "addr:housenumber":"317",
    "addr:postcode":"19341",
    "addr:street":"W Lancaster Ave",
    "iso:country":"US",
    "sg:address":"317 W Lancaster Ave",
    "sg:city":"Exton",
    "sg:classifiers":[
        {
            "category":"Shopping",
            "subcategory":"Used Merchandise",
            "type":"Retail Goods"
        }
    ],
    "sg:phone":"+1   ",
    "sg:postcode":"19341",
    "sg:province":"PA",
    "sg:tags":[
        "miscellaneous",
        "store"
    ],
    "wof:name":"Baby Thoughts",
    "wof:placetype":"venue"
},
  "geometry": {"coordinates":[-75.62110699999999,40.028787],"type":"Point"}
}