{
  "type": "Feature",
  "properties": {
    "iso:country":"US",
    "sg:address":"6034 Woodland Ave",
    "sg:city":"Philadelphia",
    "sg:classifiers":[
        {
            "category":"Banks & Credit Unions",
            "subcategory":"Bank",
            "type":"Services"
        }
    ],
    "sg:phone":"+1 215 727 6046",
    "sg:postcode":"19142",
    "sg:province":"PA",
    "sg:tags":[
        "machine",
        "teller",
        "automated"
    ],
    "wof:name":"ATM America",
    "wof:placetype":"venue"
},
  "geometry": {"coordinates":[-75.228737,39.929512],"type":"Point"}
}