{
  "type": "Feature",
  "properties": {
    "iso:country":"US",
    "sg:address":"11500 Roosevelt Blvd",
    "sg:city":"Philadelphia",
    "sg:classifiers":[
        {
            "category":"Wholesale",
            "subcategory":"Machinery & Supplies",
            "type":"Manufacturing & Wholesale Goods"
        },
        {
            "category":"Professional",
            "subcategory":"Business Services",
            "type":"Services"
        }
    ],
    "sg:phone":"+1 215 676 3667",
    "sg:postcode":"19116",
    "sg:province":"PA",
    "sg:tags":[
        "packaging",
        "equipment",
        "industrial"
    ],
    "wof:name":"Liso Packaging",
    "wof:placetype":"venue"
},
  "geometry": {"coordinates":[-75.005826,40.1021],"type":"Point"}
}