{
  "type": "Feature",
  "properties": {
    "addr:full":"717 S Trenton Ave Pittsburgh PA 15221",
    "addr:housenumber":"717",
    "addr:postcode":"15221",
    "addr:street":"S Trenton Ave",
    "iso:country":"US",
    "sg:address":"717 S Trenton Ave",
    "sg:city":"Pittsburgh",
    "sg:classifiers":[
        {
            "category":"Real Estate",
            "subcategory":"Real Estate Agent",
            "type":"Services"
        }
    ],
    "sg:phone":"+1 412 241 7144",
    "sg:postcode":"15221",
    "sg:province":"PA",
    "wof:name":"Kefalos & Assoc",
    "wof:placetype":"venue"
},
  "geometry": {"coordinates":[-79.892155,40.438105],"type":"Point"}
}