{
  "type": "Feature",
  "properties": {
    "iso:country":"US",
    "sg:address":"1516 Haine School Rd",
    "sg:city":"Cranberry Twp",
    "sg:classifiers":[
        {
            "category":"Social Services",
            "type":"Services"
        },
        {
            "category":"Social Services",
            "subcategory":"Child Care",
            "type":"Services"
        }
    ],
    "sg:phone":"+1 724 772 1944",
    "sg:postcode":"16066",
    "sg:province":"PA",
    "sg:tags":[
        "day",
        "welfare"
    ],
    "sg:website":"www.ymcacrs.org",
    "wof:name":"Butler YMCA Child Care",
    "wof:placetype":"venue"
},
  "geometry": {"coordinates":[-80.125801,40.6959],"type":"Point"}
}