{
  "type": "Feature",
  "properties": {
    "iso:country":"US",
    "sg:address":"500 Morgan Hwy",
    "sg:city":"Clarks Summit",
    "sg:classifiers":[
        {
            "category":"Recreation",
            "subcategory":"Amusement Park",
            "type":"Entertainment"
        }
    ],
    "sg:phone":"+1 570 586 5699",
    "sg:postcode":"18411",
    "sg:province":"PA",
    "sg:tags":[
        "park"
    ],
    "wof:name":"Lahey Family Fun Park",
    "wof:placetype":"venue"
},
  "geometry": {"coordinates":[-75.684775,41.460045],"type":"Point"}
}