{
  "type": "Feature",
  "properties": {
    "iso:country":"US",
    "sg:address":"20325 Rte 19",
    "sg:city":"Cranberry Township",
    "sg:classifiers":[
        {
            "category":"Shopping",
            "subcategory":"Clothing, Apparel, & Fashions",
            "type":"Retail Goods"
        }
    ],
    "sg:phone":"+1   ",
    "sg:postcode":"16066",
    "sg:province":"PA",
    "wof:name":"Sarah JS Inc",
    "wof:placetype":"venue"
},
  "geometry": {"coordinates":[-80.104102,40.693767],"type":"Point"}
}