{
  "type": "Feature",
  "properties": {
    "addr:full":"5645 N 5th St Philadelphia PA 19120",
    "addr:housenumber":"5645",
    "addr:postcode":"19120",
    "addr:street":"N 5Th St",
    "iso:country":"US",
    "sg:address":"5645 N 5th St",
    "sg:city":"Philadelphia",
    "sg:classifiers":[
        {
            "category":"Wholesale",
            "subcategory":"Jewelry",
            "type":"Manufacturing & Wholesale Goods"
        }
    ],
    "sg:phone":"+1   ",
    "sg:postcode":"19120",
    "sg:province":"PA",
    "wof:name":"Eastern Jewelry Inc",
    "wof:placetype":"venue"
},
  "geometry": {"coordinates":[-75.130211,40.037279],"type":"Point"}
}