{
  "type": "Feature",
  "properties": {
    "addr:full":"162 Cranbrooke Dr Coraopolis PA 15108",
    "addr:housenumber":"162",
    "addr:postcode":"15108",
    "addr:street":"Cranbrooke Dr",
    "iso:country":"US",
    "sg:address":"162 Cranbrooke Dr",
    "sg:city":"Coraopolis",
    "sg:classifiers":[
        {
            "category":"Wholesale",
            "subcategory":"Groceries",
            "type":"Manufacturing & Wholesale Goods"
        }
    ],
    "sg:phone":"+1   ",
    "sg:postcode":"15108",
    "sg:province":"PA",
    "sg:tags":[
        "farm",
        "distributes",
        "product",
        "snack"
    ],
    "wof:name":"Jason Nice Distributing Inc",
    "wof:placetype":"venue"
},
  "geometry": {"coordinates":[-80.20794100000001,40.458089],"type":"Point"}
}