{
  "type": "Feature",
  "properties": {
    "iso:country":"US",
    "sg:address":"3300 Ryan Ave",
    "sg:city":"Philadelphia",
    "sg:classifiers":[
        {
            "category":"Retail",
            "subcategory":"Laundry & Dry Cleaning",
            "type":"Services"
        }
    ],
    "sg:phone":"+1 215 333 9535",
    "sg:postcode":"19136",
    "sg:province":"PA",
    "sg:tags":[
        "cleaners"
    ],
    "wof:name":"Garden Cleaners",
    "wof:placetype":"venue"
},
  "geometry": {"coordinates":[-75.042609,40.039398],"type":"Point"}
}