{
  "type": "Feature",
  "properties": {
    "addr:full":"240 W Mahoning St Punxsutawney PA 15767",
    "addr:housenumber":"240",
    "addr:postcode":"15767",
    "addr:street":"W Mahoning St",
    "iso:country":"US",
    "sg:address":"240 W Mahoning St",
    "sg:city":"Punxsutawney",
    "sg:classifiers":[
        {
            "category":"Farming",
            "subcategory":"Farm",
            "type":"Manufacturing & Wholesale Goods"
        }
    ],
    "sg:phone":"+1 814 938 9800",
    "sg:postcode":"15767",
    "sg:province":"PA",
    "wof:name":"Andray Farm",
    "wof:placetype":"venue"
},
  "geometry": {"coordinates":[-79.04610099999999,40.917811],"type":"Point"}
}