{
  "type": "Feature",
  "properties": {
    "addr:full":"1392 Forest Hills Dr Salix PA 15952",
    "addr:housenumber":"1392",
    "addr:postcode":"15952",
    "addr:street":"Forest Hills Dr",
    "iso:country":"US",
    "sg:address":"1392 Forest Hills Dr",
    "sg:city":"Salix",
    "sg:classifiers":[
        {
            "category":"Recreation",
            "type":"Entertainment"
        }
    ],
    "sg:phone":"+1 814 266 4536",
    "sg:postcode":"15952",
    "sg:province":"PA",
    "sg:tags":[
        "golf",
        "restaurant",
        "club",
        "public",
        "course",
        "membership",
        "eat"
    ],
    "wof:name":"Windber Country Club",
    "wof:placetype":"venue"
},
  "geometry": {"coordinates":[-78.77734599999999,40.290983],"type":"Point"}
}