{
  "type": "Feature",
  "properties": {
    "addr:full":"235 Main St Catawissa PA 17820",
    "addr:housenumber":"235",
    "addr:postcode":"17820",
    "addr:street":"Main St",
    "iso:country":"US",
    "sg:address":"235 Main St",
    "sg:city":"Catawissa",
    "sg:classifiers":[
        {
            "category":"Food & Beverages",
            "subcategory":"Groceries & Convenience Stores",
            "type":"Retail Goods"
        }
    ],
    "sg:phone":"+1 570 356 2082",
    "sg:postcode":"17820",
    "sg:province":"PA",
    "sg:tags":[
        "grocer"
    ],
    "wof:name":"WEIS Markets Inc",
    "wof:placetype":"venue"
},
  "geometry": {"coordinates":[-76.462356,40.952788],"type":"Point"}
}