{
  "type": "Feature",
  "properties": {
    "addr:full":"104 Tippecanoe Dr Greensburg PA 15601",
    "addr:housenumber":"104",
    "addr:postcode":"15601",
    "addr:street":"Tippecanoe Dr",
    "iso:country":"US",
    "sg:address":"104 Tippecanoe Dr",
    "sg:city":"Greensburg",
    "sg:classifiers":[
        {
            "category":"Professional",
            "subcategory":"Advertising",
            "type":"Services"
        }
    ],
    "sg:phone":"+1 724 837 7544",
    "sg:postcode":"15601",
    "sg:province":"PA",
    "sg:tags":[
        "promotion",
        "sale"
    ],
    "wof:name":"E & L Promotions Inc",
    "wof:placetype":"venue"
},
  "geometry": {"coordinates":[-79.58086,40.281128],"type":"Point"}
}