{
  "type": "Feature",
  "properties": {
    "addr:full":"515 N 23rd St Lebanon PA 17046",
    "addr:housenumber":"515",
    "addr:postcode":"17046",
    "addr:street":"N 23Rd St",
    "iso:country":"US",
    "sg:address":"515 N 23rd St",
    "sg:city":"Lebanon",
    "sg:classifiers":[
        {
            "category":"Retail",
            "subcategory":"Auto Repair",
            "type":"Services"
        }
    ],
    "sg:phone":"+1 717 272 0547",
    "sg:postcode":"17046",
    "sg:province":"PA",
    "sg:tags":[
        "wrecker"
    ],
    "wof:name":"Ail's Recovery Svc",
    "wof:placetype":"venue"
},
  "geometry": {"coordinates":[-76.451095,40.347051],"type":"Point"}
}