{
  "type": "Feature",
  "properties": {
    "addr:full":"1803 Mount Rose Ave York PA 17403",
    "addr:housenumber":"1803",
    "addr:postcode":"17403",
    "addr:street":"Mount Rose Ave",
    "iso:country":"US",
    "sg:address":"1803 Mount Rose Ave",
    "sg:city":"York",
    "sg:classifiers":[
        {
            "category":"Government",
            "subcategory":"Office",
            "type":"Public Place"
        },
        {
            "category":"Health Services",
            "subcategory":"Doctor",
            "type":"Services"
        }
    ],
    "sg:phone":"+1 717 851 1486",
    "sg:postcode":"17403",
    "sg:province":"PA",
    "sg:tags":[
        "state",
        "program",
        "managed",
        "care",
        "behavioral"
    ],
    "wof:name":"Quest Behavioral Health",
    "wof:placetype":"venue"
},
  "geometry": {"coordinates":[-76.686516,39.958284],"type":"Point"}
}