{
  "type": "Feature",
  "properties": {
    "addr:full":"17 Kathryn Rd Chalfont PA 18914",
    "addr:housenumber":"17",
    "addr:postcode":"18914",
    "addr:street":"Kathryn Rd",
    "iso:country":"US",
    "sg:address":"17 Kathryn Rd",
    "sg:city":"Chalfont",
    "sg:classifiers":[
        {
            "category":"Building & Trades",
            "subcategory":"Construction",
            "type":"Services"
        }
    ],
    "sg:phone":"+1 215 822 8434",
    "sg:postcode":"18914",
    "sg:province":"PA",
    "sg:tags":[
        "contractor"
    ],
    "wof:name":"Sb Carpentry Contractor",
    "wof:placetype":"venue"
},
  "geometry": {"coordinates":[-75.22219800000001,40.298698],"type":"Point"}
}