{
  "type": "Feature",
  "properties": {
    "iso:country":"US",
    "sg:address":"935 E Hamilton St",
    "sg:city":"Allentown",
    "sg:classifiers":[
        {
            "category":"Restaurant",
            "type":"Food & Drink"
        }
    ],
    "sg:phone":"+1 610 433 4211",
    "sg:postcode":"18109",
    "sg:province":"PA",
    "wof:name":"Bay Leaf Restaurant",
    "wof:placetype":"venue"
},
  "geometry": {"coordinates":[-75.439042,40.612501],"type":"Point"}
}