{
  "type": "Feature",
  "properties": {
    "iso:country":"US",
    "sg:address":"474 Gravel Point Rd",
    "sg:city":"Howard",
    "sg:classifiers":[
        {
            "category":"Manufacturing",
            "subcategory":"Building Materials",
            "type":"Manufacturing & Wholesale Goods"
        }
    ],
    "sg:phone":"+1 814 625 2168",
    "sg:postcode":"16841",
    "sg:province":"PA",
    "wof:name":"WERT Co",
    "wof:placetype":"venue"
},
  "geometry": {"coordinates":[-77.67976299999999,41.024416],"type":"Point"}
}