{
  "type": "Feature",
  "properties": {
    "addr:full":"1980 Washington Rd Washington PA 15301",
    "addr:housenumber":"1980",
    "addr:postcode":"15301",
    "addr:street":"Washington Rd",
    "iso:country":"US",
    "sg:address":"1980 Washington Rd",
    "sg:city":"Washington",
    "sg:classifiers":[
        {
            "category":"Manufacturing",
            "subcategory":"Tools & Machinery",
            "type":"Manufacturing & Wholesale Goods"
        }
    ],
    "sg:phone":"+1 724 745 8540",
    "sg:postcode":"15301",
    "sg:province":"PA",
    "sg:tags":[
        "machine",
        "shop"
    ],
    "wof:name":"Tandem Metal Products Inc",
    "wof:placetype":"venue"
},
  "geometry": {"coordinates":[-80.18093500000001,40.229656],"type":"Point"}
}