{
  "type": "Feature",
  "properties": {
    "iso:country":"US",
    "sg:address":"210 Hostetter Rd",
    "sg:city":"Manheim",
    "sg:classifiers":[
        {
            "category":"Food & Beverages",
            "subcategory":"Meat & Fish",
            "type":"Retail Goods"
        },
        {
            "category":"Restaurant",
            "type":"Food & Drink"
        }
    ],
    "sg:phone":"+1 717 665 9494",
    "sg:postcode":"17545",
    "sg:province":"PA",
    "sg:tags":[
        "eating"
    ],
    "wof:name":"Metzler's Home Style Foods",
    "wof:placetype":"venue"
},
  "geometry": {"coordinates":[-76.38330000000001,40.162001],"type":"Point"}
}