{
  "type": "Feature",
  "properties": {
    "iso:country":"US",
    "sg:address":"3309 Elton Rd",
    "sg:city":"Johnstown",
    "sg:classifiers":[
        {
            "category":"Retail",
            "subcategory":"Repair Shop",
            "type":"Services"
        }
    ],
    "sg:phone":"+1   ",
    "sg:postcode":"15904",
    "sg:province":"PA",
    "sg:tags":[
        "machine",
        "operator",
        "vending"
    ],
    "wof:name":"R & S Vending",
    "wof:placetype":"venue"
},
  "geometry": {"coordinates":[-78.838307,40.278554],"type":"Point"}
}