{
  "type": "Feature",
  "properties": {
    "iso:country":"US",
    "sg:address":"107 Bassatt Dr",
    "sg:city":"Downingtown",
    "sg:classifiers":[
        {
            "category":"Professional",
            "subcategory":"Art Services",
            "type":"Services"
        }
    ],
    "sg:phone":"+1 610 518 2655",
    "sg:postcode":"19335",
    "sg:province":"PA",
    "sg:tags":[
        "designer",
        "display",
        "producer"
    ],
    "wof:name":"Meyer Klein Design",
    "wof:placetype":"venue"
},
  "geometry": {"coordinates":[-75.69611500000001,40.037625],"type":"Point"}
}