{
  "type": "Feature",
  "properties": {
    "iso:country":"US",
    "sg:address":"416 Stump Rd",
    "sg:city":"Montgomeryville",
    "sg:classifiers":[
        {
            "category":"Manufacturing",
            "subcategory":"Tools & Machinery",
            "type":"Manufacturing & Wholesale Goods"
        }
    ],
    "sg:phone":"+1   ",
    "sg:postcode":"18914",
    "sg:province":"PA",
    "sg:tags":[
        "transformer",
        "industrial",
        "mfg"
    ],
    "wof:name":"Marino Indus Systems & Svcs",
    "wof:placetype":"venue"
},
  "geometry": {"coordinates":[-75.193589,40.265354],"type":"Point"}
}