{
  "type": "Feature",
  "properties": {
    "addr:full":"2004 Waverly St Pittsburgh PA 15218",
    "addr:housenumber":"2004",
    "addr:postcode":"15218",
    "addr:street":"Waverly St",
    "iso:country":"US",
    "sg:address":"2004 Waverly St",
    "sg:city":"Pittsburgh",
    "sg:classifiers":[
        {
            "category":"Real Estate",
            "subcategory":"Real Estate Operator",
            "type":"Services"
        },
        {
            "category":"Insurance",
            "subcategory":"Hazard Insurance",
            "type":"Services"
        },
        {
            "category":"Insurance",
            "subcategory":"Title Insurance",
            "type":"Services"
        },
        {
            "category":"Real Estate",
            "subcategory":"Real Estate Agent",
            "type":"Services"
        }
    ],
    "sg:phone":"+1 412 436 3758",
    "sg:postcode":"15218",
    "sg:province":"PA",
    "sg:tags":[
        "apartment",
        "homeowner"
    ],
    "sg:website":"http://www.craigcraig.com",
    "wof:name":"Craig/Craig Inc.",
    "wof:placetype":"venue"
},
  "geometry": {"coordinates":[-79.88592300000001,40.422283],"type":"Point"}
}