{
  "type": "Feature",
  "properties": {
    "addr:full":"93 S West End Blvd Ste 101A Quakertown PA 18951",
    "addr:housenumber":"93",
    "addr:postcode":"18951",
    "addr:street":"S",
    "iso:country":"US",
    "sg:address":"93 S West End Blvd Ste 101A",
    "sg:city":"Quakertown",
    "sg:classifiers":[
        {
            "category":"Personal",
            "type":"Services"
        },
        {
            "category":"Building & Trades",
            "subcategory":"Cleaning & Sanitation",
            "type":"Services"
        }
    ],
    "sg:phone":"+1 215 529 7837",
    "sg:postcode":"18951",
    "sg:province":"PA",
    "sg:tags":[
        "house",
        "butlers'",
        "maids'",
        "contractor"
    ],
    "sg:website":"http://www.quakertownmaids.com",
    "wof:name":"You've Got Maids",
    "wof:placetype":"venue"
},
  "geometry": {"coordinates":[-75.355261,40.438563],"type":"Point"}
}