{
  "type": "Feature",
  "properties": {
    "iso:country":"US",
    "sg:address":"825 Summit Grove Ave",
    "sg:city":"Bryn Mawr",
    "sg:classifiers":[
        {
            "category":"Education",
            "subcategory":"Junior College",
            "type":"Public Place"
        }
    ],
    "sg:phone":"+1 610 519 1300",
    "sg:postcode":"19010",
    "sg:province":"PA",
    "sg:tags":[
        "technical",
        "institute"
    ],
    "wof:name":"Gestalt Therapy Institute",
    "wof:placetype":"venue"
},
  "geometry": {"coordinates":[-75.318883,40.020047],"type":"Point"}
}