{
  "type": "Feature",
  "properties": {
    "iso:country":"US",
    "sg:address":"11 Wooded Acres Dr",
    "sg:city":"Stroudsburg",
    "sg:classifiers":[
        {
            "category":"Building & Trades",
            "subcategory":"Plumbing",
            "type":"Services"
        }
    ],
    "sg:phone":"+1 570 620 9692",
    "sg:postcode":"18360",
    "sg:province":"PA",
    "sg:tags":[
        "plumbing",
        "contractor"
    ],
    "wof:name":"F & T Plumbing Inc",
    "wof:placetype":"venue"
},
  "geometry": {"coordinates":[-75.332202,41.011786],"type":"Point"}
}