{
  "type": "Feature",
  "properties": {
    "iso:country":"US",
    "sg:address":"3136 Brodhead Rd",
    "sg:city":"Aliquippa",
    "sg:classifiers":[
        {
            "category":"Personal",
            "type":"Services"
        }
    ],
    "sg:phone":"+1 724 375 5166",
    "sg:postcode":"15001",
    "sg:province":"PA",
    "sg:tags":[
        "wear",
        "formal"
    ],
    "wof:name":"Ziggy's Tux Shop & Mens Wear",
    "wof:placetype":"venue"
},
  "geometry": {"coordinates":[-80.2556,40.577399],"type":"Point"}
}