{
  "type": "Feature",
  "properties": {
    "iso:country":"US",
    "sg:address":"2301 Cherry St",
    "sg:city":"Philadelphia",
    "sg:classifiers":[
        {
            "category":"Real Estate",
            "subcategory":"Real Estate Operator",
            "type":"Services"
        },
        {
            "category":"Organizations",
            "subcategory":"Community Association",
            "type":"Services"
        }
    ],
    "sg:phone":"+1 215 561 9600",
    "sg:postcode":"19103",
    "sg:province":"PA",
    "sg:tags":[
        "owner",
        "condominium"
    ],
    "wof:name":"Rivers Edge Condominiums Assn",
    "wof:placetype":"venue"
},
  "geometry": {"coordinates":[-75.17828799999999,39.957243],"type":"Point"}
}