{
  "type": "Feature",
  "properties": {
    "addr:full":"9 N Main St Muncy PA 17756",
    "addr:housenumber":"9",
    "addr:postcode":"17756",
    "addr:street":"N Main St",
    "iso:country":"US",
    "sg:address":"9 N Main St",
    "sg:city":"Muncy",
    "sg:classifiers":[
        {
            "category":"Cinema",
            "subcategory":"Movie Theater",
            "type":"Entertainment"
        }
    ],
    "sg:phone":"+1 570 546 3740",
    "sg:postcode":"17756",
    "sg:province":"PA",
    "wof:name":"Ritz Theatre",
    "wof:placetype":"venue"
},
  "geometry": {"coordinates":[-76.786151,41.205738],"type":"Point"}
}