{
  "type": "Feature",
  "properties": {
    "iso:country":"US",
    "sg:address":"11104 E Troy Rd",
    "sg:city":"Titusville",
    "sg:classifiers":[
        {
            "category":"Government",
            "subcategory":"Office",
            "type":"Public Place"
        }
    ],
    "sg:phone":"+1   ",
    "sg:postcode":"16354",
    "sg:province":"PA",
    "sg:tags":[
        "legislative",
        "body"
    ],
    "wof:name":"Troy Township",
    "wof:placetype":"venue"
},
  "geometry": {"coordinates":[-79.757458,41.623359],"type":"Point"}
}