{
  "type": "Feature",
  "properties": {
    "iso:country":"US",
    "sg:address":"135 Kerr Ave",
    "sg:city":"Jersey Shore",
    "sg:classifiers":[
        {
            "category":"Personal",
            "subcategory":"Beauty Salon",
            "type":"Services"
        }
    ],
    "sg:phone":"+1   ",
    "sg:postcode":"17740",
    "sg:province":"PA",
    "sg:tags":[
        "shop"
    ],
    "wof:name":"Janice Nagle Beauty Shop",
    "wof:placetype":"venue"
},
  "geometry": {"coordinates":[-77.267527,41.202908],"type":"Point"}
}