{
  "type": "Feature",
  "properties": {
    "iso:country":"US",
    "sg:address":"219 Ruth Rd",
    "sg:city":"Harleysville",
    "sg:classifiers":[
        {
            "category":"Utilities",
            "type":"Services"
        }
    ],
    "sg:phone":"+1 215 513 9500",
    "sg:postcode":"19438",
    "sg:province":"PA",
    "sg:tags":[
        "locating"
    ],
    "sg:website":"www.chowns.com",
    "wof:name":"Chowns Communications Inc",
    "wof:placetype":"venue"
},
  "geometry": {"coordinates":[-75.36435899999999,40.268209],"type":"Point"}
}