{
  "type": "Feature",
  "properties": {
    "iso:country":"US",
    "sg:address":"60 Connellsville St",
    "sg:city":"Dunbar",
    "sg:classifiers":[
        {
            "category":"Education",
            "subcategory":"Library",
            "type":"Public Place"
        }
    ],
    "sg:phone":"+1 724 277 4775",
    "sg:postcode":"15431",
    "sg:province":"PA",
    "sg:tags":[
        "executive"
    ],
    "wof:name":"Dunbar Community Library",
    "wof:placetype":"venue"
},
  "geometry": {"coordinates":[-79.615674,39.975828],"type":"Point"}
}