{
  "type": "Feature",
  "properties": {
    "iso:country":"US",
    "sg:address":"2352 Main St",
    "sg:city":"Lake City",
    "sg:classifiers":[
        {
            "category":"Government",
            "subcategory":"Police Station",
            "type":"Public Place"
        }
    ],
    "sg:phone":"+1 814 774 8341",
    "sg:postcode":"16423",
    "sg:province":"PA",
    "sg:tags":[
        "department"
    ],
    "wof:name":"Lake City Police Dept",
    "wof:placetype":"venue"
},
  "geometry": {"coordinates":[-80.342303,42.013166],"type":"Point"}
}