{
  "type": "Feature",
  "properties": {
    "iso:country":"US",
    "sg:address":"2485 Brodhead Rd",
    "sg:city":"Aliquippa",
    "sg:classifiers":[
        {
            "category":"Health Services",
            "subcategory":"Clinic",
            "type":"Services"
        }
    ],
    "sg:phone":"+1 724 378 1013",
    "sg:postcode":"15001",
    "sg:province":"PA",
    "sg:tags":[
        "welfare"
    ],
    "sg:website":"http://www.mckennashealthshack.com",
    "wof:name":"Mckennas Health Shack",
    "wof:placetype":"venue"
},
  "geometry": {"coordinates":[-80.27350199999999,40.594768],"type":"Point"}
}