{
  "type": "Feature",
  "properties": {
    "addr:full":"337 E Gibson St Scranton PA 18509",
    "addr:housenumber":"337",
    "addr:postcode":"18509",
    "addr:street":"E Gibson St",
    "iso:country":"US",
    "sg:address":"337 E Gibson St",
    "sg:city":"Scranton",
    "sg:classifiers":[
        {
            "category":"Professional",
            "subcategory":"Advertising",
            "type":"Services"
        }
    ],
    "sg:phone":"+1 570 344 3331",
    "sg:postcode":"18509",
    "sg:province":"PA",
    "sg:tags":[
        "mail",
        "direct",
        "marketing"
    ],
    "wof:name":"Emmett Marketing Direct Mail",
    "wof:placetype":"venue"
},
  "geometry": {"coordinates":[-75.658283,41.416488],"type":"Point"}
}