{
  "type": "Feature",
  "properties": {
    "iso:country":"US",
    "sg:address":"858 S Washington St",
    "sg:city":"Greencastle",
    "sg:classifiers":[
        {
            "category":"Retail",
            "subcategory":"Auto Repair",
            "type":"Services"
        }
    ],
    "sg:phone":"+1 717 597 3258",
    "sg:postcode":"17225",
    "sg:province":"PA",
    "sg:tags":[
        "body",
        "automobile",
        "painting"
    ],
    "wof:name":"Best Of Show Auto Restorations",
    "wof:placetype":"venue"
},
  "geometry": {"coordinates":[-77.728737,39.77457],"type":"Point"}
}