{
  "type": "Feature",
  "properties": {
    "iso:country":"US",
    "sg:address":"1314 Howard Ln",
    "sg:city":"Easton",
    "sg:classifiers":[
        {
            "category":"Building & Trades",
            "subcategory":"Construction",
            "type":"Services"
        }
    ],
    "sg:phone":"+1 610 923 3578",
    "sg:postcode":"18045",
    "sg:province":"PA",
    "sg:tags":[
        "house",
        "general",
        "contractor"
    ],
    "wof:name":"Ken Do Construction",
    "wof:placetype":"venue"
},
  "geometry": {"coordinates":[-75.258499,40.710662],"type":"Point"}
}