{
  "type": "Feature",
  "properties": {
    "addr:full":"305 N Front St Harrisburg PA 17101",
    "addr:housenumber":"305",
    "addr:postcode":"17101",
    "addr:street":"N Front St",
    "iso:country":"US",
    "sg:address":"305 N Front St",
    "sg:city":"Harrisburg",
    "sg:classifiers":[
        {
            "category":"Professional",
            "subcategory":"Lawyer & Legal Services",
            "type":"Services"
        }
    ],
    "sg:phone":"+1 717 237 7100",
    "sg:postcode":"17101",
    "sg:province":"PA",
    "sg:tags":[
        "attorney"
    ],
    "wof:name":"Thomas Thomas & Hafer Llp",
    "wof:placetype":"venue"
},
  "geometry": {"coordinates":[-76.8871,40.261299],"type":"Point"}
}