{
  "type": "Feature",
  "properties": {
    "iso:country":"US",
    "sg:address":"210 York Rd",
    "sg:city":"Warminster",
    "sg:classifiers":[
        {
            "category":"Retail",
            "subcategory":"Funeral Services",
            "type":"Services"
        }
    ],
    "sg:phone":"+1 215 675 2390",
    "sg:postcode":"18974",
    "sg:province":"PA",
    "sg:tags":[
        "information"
    ],
    "wof:name":"Bux-Mont Cremation Svc Inc",
    "wof:placetype":"venue"
},
  "geometry": {"coordinates":[-75.102048,40.195705],"type":"Point"}
}