{
  "type": "Feature",
  "properties": {
    "iso:country":"US",
    "sg:address":"1070 69th Ave",
    "sg:city":"Philadelphia",
    "sg:classifiers":[
        {
            "category":"Organizations",
            "subcategory":"Religious Organization",
            "type":"Services"
        }
    ],
    "sg:phone":"+1 215 424 6588",
    "sg:postcode":"19126",
    "sg:province":"PA",
    "sg:tags":[
        "church"
    ],
    "wof:name":"Bethany House Of Worship",
    "wof:placetype":"venue"
},
  "geometry": {"coordinates":[-75.133213,40.057135],"type":"Point"}
}