{
  "type": "Feature",
  "properties": {
    "iso:country":"US",
    "sg:address":"208 S Main St",
    "sg:city":"Old Forge",
    "sg:classifiers":[
        {
            "category":"Personal",
            "subcategory":"Beauty Salon",
            "type":"Services"
        }
    ],
    "sg:phone":"+1 570 451 7474",
    "sg:postcode":"18518",
    "sg:province":"PA",
    "wof:name":"Naturally You Hair Design",
    "wof:placetype":"venue"
},
  "geometry": {"coordinates":[-75.735147,41.370772],"type":"Point"}
}