{
  "type": "Feature",
  "properties": {
    "addr:full":"36 Running Brook Rd Glen Mills PA 19342",
    "addr:housenumber":"36",
    "addr:postcode":"19342",
    "addr:street":"Running Brook Rd",
    "iso:country":"US",
    "sg:address":"36 Running Brook Rd",
    "sg:city":"Glen Mills",
    "sg:classifiers":[
        {
            "category":"Building & Trades",
            "subcategory":"Construction",
            "type":"Services"
        }
    ],
    "sg:phone":"+1   ",
    "sg:postcode":"19342",
    "sg:province":"PA",
    "sg:tags":[
        "residential",
        "remodeling",
        "com",
        "for",
        "general"
    ],
    "wof:name":"Steptoe Siedzkowski Cstm Bldrs",
    "wof:placetype":"venue"
},
  "geometry": {"coordinates":[-75.532991,39.854613],"type":"Point"}
}