{
  "type": "Feature",
  "properties": {
    "iso:country":"US",
    "sg:address":"666 Rte 18",
    "sg:city":"Monaca",
    "sg:classifiers":[
        {
            "category":"Health Services",
            "subcategory":"Optometrist",
            "type":"Services"
        }
    ],
    "sg:phone":"+1 724 770 0610",
    "sg:postcode":"15061",
    "sg:province":"PA",
    "wof:name":"Doctors Of Optometry",
    "wof:placetype":"venue"
},
  "geometry": {"coordinates":[-80.324251,40.667795],"type":"Point"}
}