{
  "type": "Feature",
  "properties": {
    "iso:country":"US",
    "sg:address":"5008 Mount Vernon Ave",
    "sg:city":"Temple",
    "sg:classifiers":[
        {
            "category":"Retail",
            "subcategory":"Auto Repair",
            "type":"Services"
        }
    ],
    "sg:phone":"+1 610 921 2505",
    "sg:postcode":"19560",
    "sg:province":"PA",
    "sg:tags":[
        "automobile",
        "inspection",
        "general"
    ],
    "wof:name":"Hoppes Auto Repair Inc",
    "wof:placetype":"venue"
},
  "geometry": {"coordinates":[-75.91376700000001,40.41092],"type":"Point"}
}