{
  "type": "Feature",
  "properties": {
    "addr:full":"51 W Chelten Ave Philadelphia PA 19144",
    "addr:housenumber":"51",
    "addr:postcode":"19144",
    "addr:street":"W Chelten Ave",
    "iso:country":"US",
    "sg:address":"51 W Chelten Ave",
    "sg:city":"Philadelphia",
    "sg:classifiers":[
        {
            "category":"Personal",
            "subcategory":"Shoe Repair & Shine",
            "type":"Services"
        }
    ],
    "sg:phone":"+1 215 849 3711",
    "sg:postcode":"19144",
    "sg:province":"PA",
    "sg:tags":[
        "repairing",
        "boot"
    ],
    "wof:name":"Anthony's Shoe Repair",
    "wof:placetype":"venue"
},
  "geometry": {"coordinates":[-75.17586300000001,40.035022],"type":"Point"}
}