{
  "type": "Feature",
  "properties": {
    "addr:full":"3305 Cobblestone Dr Washington PA 15301",
    "addr:housenumber":"3305",
    "addr:postcode":"15301",
    "addr:street":"Cobblestone Dr",
    "iso:country":"US",
    "sg:address":"3305 Cobblestone Dr",
    "sg:city":"Washington",
    "sg:classifiers":[
        {
            "category":"Science Facility",
            "type":"Public Place"
        }
    ],
    "sg:phone":"+1 724 249 2159",
    "sg:postcode":"15301",
    "sg:province":"PA",
    "sg:tags":[
        "development",
        "laboratories-research"
    ],
    "wof:name":"Keystone Ethanol",
    "wof:placetype":"venue"
},
  "geometry": {"coordinates":[-80.20600399999999,40.206182],"type":"Point"}
}