{
  "type": "Feature",
  "properties": {
    "addr:full":"412 Broad St Milford PA 18337",
    "addr:housenumber":"412",
    "addr:postcode":"18337",
    "addr:street":"Broad St",
    "iso:country":"US",
    "sg:address":"412 Broad St",
    "sg:city":"Milford",
    "sg:classifiers":[
        {
            "category":"Government",
            "subcategory":"Office",
            "type":"Public Place"
        }
    ],
    "sg:phone":"+1 570 296 3505",
    "sg:postcode":"18337",
    "sg:province":"PA",
    "wof:name":"Pike County Title Research Rm",
    "wof:placetype":"venue"
},
  "geometry": {"coordinates":[-74.80121200000001,41.324041],"type":"Point"}
}