{
  "type": "Feature",
  "properties": {
    "iso:country":"US",
    "sg:address":"110 N Washington St",
    "sg:city":"Butler",
    "sg:classifiers":[
        {
            "category":"Government",
            "subcategory":"Fire Station",
            "type":"Public Place"
        }
    ],
    "sg:phone":"+1 724 283 3100",
    "sg:postcode":"16001",
    "sg:province":"PA",
    "sg:tags":[
        "department",
        "protection"
    ],
    "wof:name":"Butler Bureau Fire Dept",
    "wof:placetype":"venue"
},
  "geometry": {"coordinates":[-79.89698300000001,40.8613],"type":"Point"}
}