{
  "type": "Feature",
  "properties": {
    "addr:full":"621 W Mahanoy St Mahanoy City PA 17948",
    "addr:housenumber":"621",
    "addr:postcode":"17948",
    "addr:street":"W Mahanoy St",
    "iso:country":"US",
    "sg:address":"621 W Mahanoy St",
    "sg:city":"Mahanoy City",
    "sg:classifiers":[
        {
            "category":"Organizations",
            "subcategory":"Religious Organization",
            "type":"Services"
        }
    ],
    "sg:phone":"+1 570 773 2631",
    "sg:postcode":"17948",
    "sg:province":"PA",
    "sg:tags":[
        "church"
    ],
    "wof:name":"St Mary's Catholic Church",
    "wof:placetype":"venue"
},
  "geometry": {"coordinates":[-76.147592,40.810138],"type":"Point"}
}