{
  "type": "Feature",
  "properties": {
    "addr:full":"254 W Lancaster Ave Paoli PA 19301",
    "addr:housenumber":"254",
    "addr:postcode":"19301",
    "addr:street":"W Lancaster Ave",
    "iso:country":"US",
    "sg:address":"254 W Lancaster Ave",
    "sg:city":"Paoli",
    "sg:classifiers":[
        {
            "category":"Health Services",
            "subcategory":"Doctor",
            "type":"Services"
        }
    ],
    "sg:phone":"+1 610 644 7755",
    "sg:postcode":"19301",
    "sg:province":"PA",
    "sg:tags":[
        "physician",
        "surgeon"
    ],
    "wof:name":"Orthopaedic Surgery & Sports",
    "wof:placetype":"venue"
},
  "geometry": {"coordinates":[-75.504588,40.042542],"type":"Point"}
}