{
  "type": "Feature",
  "properties": {
    "iso:country":"US",
    "sg:address":"622 Markley St",
    "sg:city":"Norristown",
    "sg:classifiers":[
        {
            "category":"Building & Trades",
            "subcategory":"Landscaping Services",
            "type":"Services"
        }
    ],
    "sg:phone":"+1 610 239 7460",
    "sg:postcode":"19401",
    "sg:province":"PA",
    "sg:tags":[
        "landscape",
        "contractor"
    ],
    "sg:website":"www.egralljrlandscape.com",
    "wof:name":"E G Rall Landscape Design",
    "wof:placetype":"venue"
},
  "geometry": {"coordinates":[-75.34365099999999,40.12167],"type":"Point"}
}