{
  "type": "Feature",
  "properties": {
    "iso:country":"US",
    "sg:address":"3021 Liberty Ave",
    "sg:city":"Pittsburgh",
    "sg:classifiers":[
        {
            "category":"Wholesale",
            "subcategory":"Electrical",
            "type":"Manufacturing & Wholesale Goods"
        }
    ],
    "sg:phone":"+1   ",
    "sg:postcode":"15201",
    "sg:province":"PA",
    "sg:tags":[
        "alarm",
        "system"
    ],
    "wof:name":"Alarmax Distributors Inc",
    "wof:placetype":"venue"
},
  "geometry": {"coordinates":[-79.971025,40.459079],"type":"Point"}
}