{
  "type": "Feature",
  "properties": {
    "iso:country":"US",
    "sg:address":"2231 5th St",
    "sg:city":"Bethlehem",
    "sg:classifiers":[
        {
            "category":"Personal",
            "subcategory":"Beauty Salon",
            "type":"Services"
        }
    ],
    "sg:phone":"+1 610 457 8546",
    "sg:postcode":"18020",
    "sg:province":"PA",
    "wof:name":"Shareen Lia's Hair Artistry",
    "wof:placetype":"venue"
},
  "geometry": {"coordinates":[-75.328833,40.64769],"type":"Point"}
}