{
  "type": "Feature",
  "properties": {
    "iso:country":"US",
    "sg:address":"665 E Main St",
    "sg:city":"Bradford",
    "sg:classifiers":[
        {
            "category":"Health Services",
            "subcategory":"Doctor",
            "type":"Services"
        }
    ],
    "sg:phone":"+1 814 362 7417",
    "sg:postcode":"16701",
    "sg:province":"PA",
    "sg:tags":[
        "clinic"
    ],
    "sg:website":"www.gambrohealthcare.com",
    "wof:name":"Gambro Healthcare",
    "wof:placetype":"venue"
},
  "geometry": {"coordinates":[-78.620773,41.970759],"type":"Point"}
}