{
  "type": "Feature",
  "properties": {
    "iso:country":"US",
    "sg:address":"130 Mill St",
    "sg:city":"Bristol",
    "sg:classifiers":[
        {
            "category":"Health Services",
            "subcategory":"Doctor",
            "type":"Services"
        }
    ],
    "sg:phone":"+1 215 788 3009",
    "sg:postcode":"19007",
    "sg:province":"PA",
    "sg:tags":[
        "dentist"
    ],
    "wof:name":"Daniels James DMD",
    "wof:placetype":"venue"
},
  "geometry": {"coordinates":[-74.856903,40.095001],"type":"Point"}
}