{
  "type": "Feature",
  "properties": {
    "iso:country":"US",
    "sg:address":"13942 Ridge Rd",
    "sg:city":"Waynesboro",
    "sg:classifiers":[
        {
            "category":"Building & Trades",
            "subcategory":"Construction",
            "type":"Services"
        }
    ],
    "sg:phone":"+1 717 597 9104",
    "sg:postcode":"17268",
    "sg:province":"PA",
    "sg:tags":[
        "altering",
        "remodeling",
        "contractor"
    ],
    "sg:website":"http://www.harrystile.com",
    "wof:name":"Harrys Home Repair",
    "wof:placetype":"venue"
},
  "geometry": {"coordinates":[-77.701965,39.75021],"type":"Point"}
}