{
  "type": "Feature",
  "properties": {
    "addr:full":"415 N Chestnut St Scottdale PA 15683",
    "addr:housenumber":"415",
    "addr:postcode":"15683",
    "addr:street":"N Chestnut St",
    "iso:country":"US",
    "sg:address":"415 N Chestnut St",
    "sg:city":"Scottdale",
    "sg:classifiers":[
        {
            "category":"Health Services",
            "subcategory":"Doctor",
            "type":"Services"
        }
    ],
    "sg:phone":"+1 724 887 0466",
    "sg:postcode":"15683",
    "sg:province":"PA",
    "sg:tags":[
        "dentist"
    ],
    "wof:name":"Richard F Gobbie DDS",
    "wof:placetype":"venue"
},
  "geometry": {"coordinates":[-79.587121,40.106272],"type":"Point"}
}