{
  "type": "Feature",
  "properties": {
    "iso:country":"US",
    "sg:address":"644 Central Ave",
    "sg:city":"Souderton",
    "sg:classifiers":[
        {
            "category":"Building & Trades",
            "subcategory":"Construction",
            "type":"Services"
        }
    ],
    "sg:phone":"+1   ",
    "sg:postcode":"18964",
    "sg:province":"PA",
    "sg:tags":[
        "house"
    ],
    "wof:name":"ARC Construction",
    "wof:placetype":"venue"
},
  "geometry": {"coordinates":[-75.318128,40.317264],"type":"Point"}
}