{
  "type": "Feature",
  "properties": {
    "iso:country":"US",
    "sg:address":"8250 Industrial Blvd",
    "sg:city":"Breinigsville",
    "sg:classifiers":[
        {
            "category":"Freight",
            "type":"Transportation"
        },
        {
            "category":"Local Transit",
            "type":"Transportation"
        }
    ],
    "sg:phone":"+1 610 398 7071",
    "sg:postcode":"18031",
    "sg:province":"PA",
    "sg:tags":[
        "provider",
        "broker",
        "trucking"
    ],
    "wof:name":"Jm Rapp",
    "wof:placetype":"venue"
},
  "geometry": {"coordinates":[-75.62489100000001,40.560731],"type":"Point"}
}