{
  "type": "Feature",
  "properties": {
    "iso:country":"US",
    "sg:address":"45 2nd St",
    "sg:city":"Brookville",
    "sg:classifiers":[
        {
            "category":"Health Services",
            "subcategory":"Doctor",
            "type":"Services"
        }
    ],
    "sg:phone":"+1 814 849 5386",
    "sg:postcode":"15825",
    "sg:province":"PA",
    "sg:tags":[
        "dentist"
    ],
    "wof:name":"William C Kerr DDS",
    "wof:placetype":"venue"
},
  "geometry": {"coordinates":[-79.081075,41.151558],"type":"Point"}
}