{
  "type": "Feature",
  "properties": {
    "iso:country":"US",
    "sg:address":"2171 Palomino Rd",
    "sg:city":"Dover",
    "sg:classifiers":[
        {
            "category":"Freight",
            "type":"Transportation"
        }
    ],
    "sg:phone":"+1 717 292 2707",
    "sg:postcode":"17315",
    "sg:province":"PA",
    "sg:tags":[
        "general"
    ],
    "wof:name":"Dover Auction Mini Storage",
    "wof:placetype":"venue"
},
  "geometry": {"coordinates":[-76.842251,39.993472],"type":"Point"}
}