{
  "type": "Feature",
  "properties": {
    "iso:country":"US",
    "sg:address":"5120 Clairton Rd",
    "sg:city":"Mc Keesport",
    "sg:classifiers":[
        {
            "category":"Insurance",
            "subcategory":"Life Insurance",
            "type":"Services"
        }
    ],
    "sg:phone":"+1   ",
    "sg:postcode":"15122",
    "sg:province":"PA",
    "sg:tags":[
        "carrier"
    ],
    "wof:name":"Equitable Life Assurance",
    "wof:placetype":"venue"
},
  "geometry": {"coordinates":[-79.93899,40.348215],"type":"Point"}
}