{
  "type": "Feature",
  "properties": {
    "iso:country":"US",
    "sg:address":"14 Marabee Ave",
    "sg:city":"Dallas",
    "sg:classifiers":[
        {
            "category":"Professional",
            "subcategory":"Accounting & Tax Preparation",
            "type":"Services"
        }
    ],
    "sg:phone":"+1 570 675 1557",
    "sg:postcode":"18612",
    "sg:province":"PA",
    "sg:tags":[
        "accountant"
    ],
    "wof:name":"AMF Accounting Svc",
    "wof:placetype":"venue"
},
  "geometry": {"coordinates":[-75.976747,41.337451],"type":"Point"}
}