{
  "type": "Feature",
  "properties": {
    "iso:country":"US",
    "sg:address":"3480 Grand Ave",
    "sg:city":"Neville Island",
    "sg:classifiers":[
        {
            "category":"Wholesale",
            "subcategory":"Metals & Minerals",
            "type":"Manufacturing & Wholesale Goods"
        }
    ],
    "sg:phone":"+1 412 331 7772",
    "sg:postcode":"15225",
    "sg:province":"PA",
    "sg:tags":[
        "steel",
        "broker"
    ],
    "wof:name":"Triad Metals Intl",
    "wof:placetype":"venue"
},
  "geometry": {"coordinates":[-80.12314000000001,40.509718],"type":"Point"}
}