{
  "type": "Feature",
  "properties": {
    "addr:full":"969 Catasauqua Rd Whitehall PA 18052",
    "addr:housenumber":"969",
    "addr:postcode":"18052",
    "addr:street":"Catasauqua Rd",
    "iso:country":"US",
    "sg:address":"969 Catasauqua Rd",
    "sg:city":"Whitehall",
    "sg:classifiers":[
        {
            "category":"Organizations",
            "subcategory":"Community Association",
            "type":"Services"
        }
    ],
    "sg:phone":"+1   ",
    "sg:postcode":"18052",
    "sg:province":"PA",
    "wof:name":"National Soc Painters Casein",
    "wof:placetype":"venue"
},
  "geometry": {"coordinates":[-75.47094199999999,40.637153],"type":"Point"}
}