{
  "type": "Feature",
  "properties": {
    "iso:country":"US",
    "sg:address":"1810 Smallman St",
    "sg:city":"Pittsburgh",
    "sg:classifiers":[
        {
            "category":"Food & Beverages",
            "subcategory":"Fruits & Vegetables",
            "type":"Retail Goods"
        }
    ],
    "sg:phone":"+1 412 232 0833",
    "sg:postcode":"15222",
    "sg:province":"PA",
    "sg:tags":[
        "produce"
    ],
    "wof:name":"Bill's Produce In The Strip",
    "wof:placetype":"venue"
},
  "geometry": {"coordinates":[-79.985381,40.451341],"type":"Point"}
}