{
  "type": "Feature",
  "properties": {
    "iso:country":"US",
    "sg:address":"211 Morewood Rd",
    "sg:city":"Glenshaw",
    "sg:classifiers":[
        {
            "category":"Wholesale",
            "subcategory":"Stationery",
            "type":"Manufacturing & Wholesale Goods"
        }
    ],
    "sg:phone":"+1 412 487 7997",
    "sg:postcode":"15116",
    "sg:province":"PA",
    "sg:tags":[
        "business",
        "system",
        "form",
        "supply"
    ],
    "wof:name":"Wright Business Systems Inc",
    "wof:placetype":"venue"
},
  "geometry": {"coordinates":[-79.977084,40.53419],"type":"Point"}
}