{
  "type": "Feature",
  "properties": {
    "iso:country":"US",
    "sg:address":"100 N Academy Ave Mc30-50",
    "sg:city":"Danville",
    "sg:classifiers":[
        {
            "category":"Health Services",
            "subcategory":"Hospital",
            "type":"Services"
        }
    ],
    "sg:phone":"+1 570 271 6624",
    "sg:postcode":"17822",
    "sg:province":"PA",
    "wof:name":"Marworth",
    "wof:placetype":"venue"
},
  "geometry": {"coordinates":[-76.603552,40.966621],"type":"Point"}
}