{
  "type": "Feature",
  "properties": {
    "iso:country":"US",
    "sg:address":"2200 Georgetown Dr",
    "sg:city":"Sewickley",
    "sg:classifiers":[
        {
            "category":"Professional",
            "subcategory":"Computer Services",
            "type":"Services"
        }
    ],
    "sg:phone":"+1 724 933 1300",
    "sg:postcode":"15143",
    "sg:province":"PA",
    "sg:tags":[
        "publisher",
        "developer",
        "software"
    ],
    "wof:name":"Adonix",
    "wof:placetype":"venue"
},
  "geometry": {"coordinates":[-80.102305,40.604031],"type":"Point"}
}