{
  "type": "Feature",
  "properties": {
    "iso:country":"US",
    "sg:address":"800 Roosevelt Ave",
    "sg:city":"Roseto",
    "sg:classifiers":[
        {
            "category":"Real Estate",
            "subcategory":"Surveying",
            "type":"Services"
        }
    ],
    "sg:phone":"+1 610 588 5849",
    "sg:postcode":"18013",
    "sg:province":"PA",
    "sg:tags":[
        "surveyor",
        "land",
        "engineer"
    ],
    "wof:name":"Collura George J",
    "wof:placetype":"venue"
},
  "geometry": {"coordinates":[-75.22020000000001,40.88372],"type":"Point"}
}