{
  "type": "Feature",
  "properties": {
    "iso:country":"US",
    "sg:address":"1 E Main St",
    "sg:city":"Corry",
    "sg:classifiers":[
        {
            "category":"Retail",
            "subcategory":"Car Wash",
            "type":"Services"
        }
    ],
    "sg:phone":"+1 814 664 2727",
    "sg:postcode":"16407",
    "sg:province":"PA",
    "sg:tags":[
        "polishing",
        "washing"
    ],
    "wof:name":"B & G Enterprise",
    "wof:placetype":"venue"
},
  "geometry": {"coordinates":[-79.63950699999999,41.920563],"type":"Point"}
}