{
  "type": "Feature",
  "properties": {
    "iso:country":"US",
    "sg:address":"15 S Main St",
    "sg:city":"Chambersburg",
    "sg:classifiers":[
        {
            "category":"Banks & Credit Unions",
            "subcategory":"Bank",
            "type":"Services"
        },
        {
            "category":"Banks & Credit Unions",
            "subcategory":"Financial Services",
            "type":"Services"
        }
    ],
    "sg:phone":"+1 717 217 3561",
    "sg:postcode":"17201",
    "sg:province":"PA",
    "sg:tags":[
        "saving",
        "loan",
        "commercial"
    ],
    "sg:website":"http://www.sovereignbank.com",
    "wof:name":"Sovereign Bank",
    "wof:placetype":"venue"
},
  "geometry": {"coordinates":[-77.661315,39.937294],"type":"Point"}
}