{
  "type": "Feature",
  "properties": {
    "iso:country":"US",
    "sg:address":"251 Poplar Ln",
    "sg:city":"Elizabethtown",
    "sg:classifiers":[
        {
            "category":"Manufacturing",
            "subcategory":"Tools & Machinery",
            "type":"Manufacturing & Wholesale Goods"
        }
    ],
    "sg:phone":"+1   ",
    "sg:postcode":"17022",
    "sg:province":"PA",
    "sg:tags":[
        "textile",
        "mfg",
        "trimming"
    ],
    "wof:name":"T-Shirt Printer The",
    "wof:placetype":"venue"
},
  "geometry": {"coordinates":[-76.645629,40.13689],"type":"Point"}
}