{
  "type": "Feature",
  "properties": {
    "iso:country":"US",
    "sg:address":"1709 Fox Chase Rd",
    "sg:city":"Philadelphia",
    "sg:classifiers":[
        {
            "category":"Organizations",
            "subcategory":"Religious Organization",
            "type":"Services"
        }
    ],
    "sg:phone":"+1 215 695 0531",
    "sg:postcode":"19152",
    "sg:province":"PA",
    "sg:tags":[
        "clergy"
    ],
    "wof:name":"James Kellstrom",
    "wof:placetype":"venue"
},
  "geometry": {"coordinates":[-75.05478599999999,40.069347],"type":"Point"}
}