{
  "type": "Feature",
  "properties": {
    "iso:country":"US",
    "sg:address":"2805 Main St",
    "sg:city":"Penn Hills",
    "sg:classifiers":[
        {
            "category":"Retail",
            "subcategory":"Repair Shop",
            "type":"Services"
        }
    ],
    "sg:phone":"+1 412 795 8413",
    "sg:postcode":"15235",
    "sg:province":"PA",
    "sg:tags":[
        "player",
        "recorder",
        "video"
    ],
    "wof:name":"Slagle Electronics",
    "wof:placetype":"venue"
},
  "geometry": {"coordinates":[-79.785326,40.477504],"type":"Point"}
}