{
  "type": "Feature",
  "properties": {
    "iso:country":"US",
    "sg:address":"58 Seneca St",
    "sg:city":"Wilkes Barre",
    "sg:classifiers":[
        {
            "category":"Organizations",
            "subcategory":"Religious Organization",
            "type":"Services"
        }
    ],
    "sg:phone":"+1 570 829 4462",
    "sg:postcode":"18702",
    "sg:province":"PA",
    "sg:tags":[
        "church"
    ],
    "wof:name":"St Nicholas Russian Orthodox",
    "wof:placetype":"venue"
},
  "geometry": {"coordinates":[-75.891346,41.227579],"type":"Point"}
}