{
  "type": "Feature",
  "properties": {
    "iso:country":"US",
    "sg:address":"66 E Meadow St",
    "sg:city":"Shavertown",
    "sg:classifiers":[
        {
            "category":"Shopping",
            "type":"Retail Goods"
        }
    ],
    "sg:phone":"+1   ",
    "sg:postcode":"18708",
    "sg:province":"PA",
    "sg:tags":[
        "merchandise"
    ],
    "wof:name":"Northeast Amigo",
    "wof:placetype":"venue"
},
  "geometry": {"coordinates":[-75.96844400000001,41.28305],"type":"Point"}
}