{
  "type": "Feature",
  "properties": {
    "iso:country":"US",
    "sg:address":"4365 Molly Pitcher Hwy",
    "sg:city":"Chambersburg",
    "sg:classifiers":[
        {
            "category":"Organizations",
            "subcategory":"Religious Organization",
            "type":"Services"
        }
    ],
    "sg:phone":"+1 717 375 4309",
    "sg:postcode":"17201",
    "sg:province":"PA",
    "sg:tags":[
        "church"
    ],
    "sg:website":"www.marionmennonite.org",
    "wof:name":"Marion Mennonite Church Inc",
    "wof:placetype":"venue"
},
  "geometry": {"coordinates":[-77.688924,39.87216],"type":"Point"}
}