{
  "type": "Feature",
  "properties": {
    "iso:country":"US",
    "sg:address":"4685 Lamor Rd",
    "sg:city":"Hermitage",
    "sg:classifiers":[
        {
            "category":"Restaurant",
            "type":"Food & Drink"
        }
    ],
    "sg:phone":"+1   ",
    "sg:postcode":"16148",
    "sg:province":"PA",
    "sg:tags":[
        "eating"
    ],
    "wof:name":"Achenbachs Catering",
    "wof:placetype":"venue"
},
  "geometry": {"coordinates":[-80.41892799999999,41.252655],"type":"Point"}
}