{
  "type": "Feature",
  "properties": {
    "iso:country":"US",
    "sg:address":"40 Lloyd Ave",
    "sg:city":"Malvern",
    "sg:classifiers":[
        {
            "category":"Personal",
            "subcategory":"Beauty Salon",
            "type":"Services"
        }
    ],
    "sg:phone":"+1 610 793 3552",
    "sg:postcode":"19355",
    "sg:province":"PA",
    "wof:name":"Electrolysis By Sara Picone",
    "wof:placetype":"venue"
},
  "geometry": {"coordinates":[-75.497315,40.037313],"type":"Point"}
}