{
  "type": "Feature",
  "properties": {
    "addr:full":"1567 Lehigh St Allentown PA 18103",
    "addr:housenumber":"1567",
    "addr:postcode":"18103",
    "addr:street":"Lehigh St",
    "iso:country":"US",
    "sg:address":"1567 Lehigh St",
    "sg:city":"Allentown",
    "sg:classifiers":[
        {
            "category":"Professional",
            "subcategory":"Accounting & Tax Preparation",
            "type":"Services"
        },
        {
            "category":"Banks & Credit Unions",
            "subcategory":"Financial Services",
            "type":"Services"
        }
    ],
    "sg:phone":"+1 610 791 3679",
    "sg:postcode":"18103",
    "sg:province":"PA",
    "sg:tags":[
        "return",
        "preparation-business",
        "taxes-consultants",
        "loan",
        "reporting",
        "representative",
        "alternative",
        "bookkeeping"
    ],
    "sg:website":"http://www.hrblock.com",
    "wof:name":"H&R Block",
    "wof:placetype":"venue"
},
  "geometry": {"coordinates":[-75.480756,40.578323],"type":"Point"}
}