{
  "type": "Feature",
  "properties": {
    "addr:full":"931 Washington Ln Jenkintown PA 19046",
    "addr:housenumber":"931",
    "addr:postcode":"19046",
    "addr:street":"Washington Ln",
    "iso:country":"US",
    "sg:address":"931 Washington Ln",
    "sg:city":"Jenkintown",
    "sg:classifiers":[
        {
            "category":"Organizations",
            "subcategory":"Membership Organization",
            "type":"Services"
        }
    ],
    "sg:phone":"+1   ",
    "sg:postcode":"19046",
    "sg:province":"PA",
    "sg:tags":[
        "charitable"
    ],
    "wof:name":"Pennypack Farm Education Cente",
    "wof:placetype":"venue"
},
  "geometry": {"coordinates":[-75.114378,40.103501],"type":"Point"}
}