{
  "type": "Feature",
  "properties": {
    "addr:full":"5000 Wegmans Dr Bethlehem PA 18017",
    "addr:postcode":"5000;18017",
    "addr:street":"Wegmans Dr",
    "iso:country":"US",
    "sg:address":"5000 Wegmans Dr",
    "sg:city":"Bethlehem",
    "sg:classifiers":[
        {
            "category":"Food & Beverages",
            "subcategory":"Groceries & Convenience Stores",
            "type":"Retail Goods"
        }
    ],
    "sg:phone":"+1 610 317 1300",
    "sg:postcode":"18017",
    "sg:province":"PA",
    "wof:name":"Wegmans Food Pharmacy",
    "wof:placetype":"venue"
},
  "geometry": {"coordinates":[-75.386101,40.666901],"type":"Point"}
}