{
  "type": "Feature",
  "properties": {
    "addr:full":"1875 Lititz Pike Lancaster PA 17601",
    "addr:housenumber":"1875",
    "addr:postcode":"17601",
    "addr:street":"Lititz Pike",
    "iso:country":"US",
    "sg:address":"1875 Lititz Pike",
    "sg:city":"Lancaster",
    "sg:classifiers":[
        {
            "category":"Professional",
            "subcategory":"Computer Services",
            "type":"Services"
        }
    ],
    "sg:phone":"+1 717 560 3490",
    "sg:postcode":"17601",
    "sg:province":"PA",
    "sg:tags":[
        "repair"
    ],
    "sg:website":"www.lehighvalleyrespiratorycare.com",
    "wof:name":"Poli Services",
    "wof:placetype":"venue"
},
  "geometry": {"coordinates":[-76.30855699999999,40.07531],"type":"Point"}
}