{
  "type": "Feature",
  "properties": {
    "iso:country":"US",
    "sg:address":"127 W Street Rd",
    "sg:city":"Kennett Square",
    "sg:classifiers":[
        {
            "category":"Personal",
            "type":"Services"
        }
    ],
    "sg:phone":"+1 610 444 7314",
    "sg:postcode":"19348",
    "sg:province":"PA",
    "sg:tags":[
        "trainer",
        "program",
        "fitness",
        "exercise",
        "physical"
    ],
    "sg:website":"www.pilatesfusioncenter.com",
    "wof:name":"Pilates Fusion Center",
    "wof:placetype":"venue"
},
  "geometry": {"coordinates":[-75.72152,39.874096],"type":"Point"}
}