{
  "type": "Feature",
  "properties": {
    "iso:country":"US",
    "sg:address":"216 N 3rd St",
    "sg:city":"Mifflinburg",
    "sg:classifiers":[
        {
            "category":"Personal",
            "subcategory":"Beauty Salon",
            "type":"Services"
        }
    ],
    "sg:phone":"+1 570 966 2381",
    "sg:postcode":"17844",
    "sg:province":"PA",
    "wof:name":"Amy Evers Beauty & Tanning",
    "wof:placetype":"venue"
},
  "geometry": {"coordinates":[-77.04598900000001,40.920857],"type":"Point"}
}