{
  "type": "Feature",
  "properties": {
    "iso:country":"US",
    "sg:address":"202 Plymouth Ave",
    "sg:city":"Oreland",
    "sg:classifiers":[
        {
            "category":"Building & Trades",
            "subcategory":"Construction",
            "type":"Services"
        }
    ],
    "sg:phone":"+1   ",
    "sg:postcode":"19075",
    "sg:province":"PA",
    "sg:tags":[
        "house"
    ],
    "wof:name":"Pennoak Co",
    "wof:placetype":"venue"
},
  "geometry": {"coordinates":[-75.189761,40.116166],"type":"Point"}
}