{
  "type": "Feature",
  "properties": {
    "iso:country":"US",
    "sg:address":"294 Wedgewood Rd",
    "sg:city":"Bethlehem",
    "sg:classifiers":[
        {
            "category":"Organizations",
            "subcategory":"Membership Organization",
            "type":"Services"
        }
    ],
    "sg:phone":"+1   ",
    "sg:postcode":"18017",
    "sg:province":"PA",
    "wof:name":"Little Creek Associates",
    "wof:placetype":"venue"
},
  "geometry": {"coordinates":[-75.390243,40.654593],"type":"Point"}
}