{
  "type": "Feature",
  "properties": {
    "iso:country":"US",
    "sg:address":"1229 Mifflin St",
    "sg:city":"Huntingdon",
    "sg:classifiers":[
        {
            "category":"Coffee & Tea",
            "type":"Food & Drink"
        }
    ],
    "sg:phone":"+1 814 643 3178",
    "sg:postcode":"16652",
    "sg:province":"PA",
    "wof:name":"Standing Stone Coffee Company",
    "wof:placetype":"venue"
},
  "geometry": {"coordinates":[-78.016979,40.492788],"type":"Point"}
}