{
  "type": "Feature",
  "properties": {
    "iso:country":"US",
    "sg:address":"1 Chautauqua Ct",
    "sg:city":"Oil City",
    "sg:classifiers":[
        {
            "category":"Professional",
            "type":"Services"
        }
    ],
    "sg:phone":"+1   ",
    "sg:postcode":"16301",
    "sg:province":"PA",
    "wof:name":"U C I P",
    "wof:placetype":"venue"
},
  "geometry": {"coordinates":[-79.67335799999999,41.450979],"type":"Point"}
}