{
  "type": "Feature",
  "properties": {
    "iso:country":"US",
    "sg:address":"7843 Sechler Rd",
    "sg:city":"New Tripoli",
    "sg:classifiers":[
        {
            "category":"Farming",
            "subcategory":"Livestock Farm",
            "type":"Manufacturing & Wholesale Goods"
        }
    ],
    "sg:phone":"+1   ",
    "sg:postcode":"18066",
    "sg:province":"PA",
    "sg:tags":[
        "equine"
    ],
    "wof:name":"William Klein Back Acres",
    "wof:placetype":"venue"
},
  "geometry": {"coordinates":[-75.763457,40.66276],"type":"Point"}
}