{
  "type": "Feature",
  "properties": {
    "addr:full":"1900 Spring Rd Carlisle PA 17013",
    "addr:housenumber":"1900",
    "addr:postcode":"17013",
    "addr:street":"Spring Rd",
    "iso:country":"US",
    "sg:address":"1900 Spring Rd",
    "sg:city":"Carlisle",
    "sg:classifiers":[
        {
            "category":"Restaurant",
            "type":"Food & Drink"
        }
    ],
    "sg:menulink":"http://www.allmenus.com/pa/north-middleton/67676-foxs-pizza-den/menu/",
    "sg:phone":"+1 717 258 1900",
    "sg:postcode":"17013",
    "sg:province":"PA",
    "sg:tags":[
        "american",
        "pizza"
    ],
    "wof:name":"Fox's Pizza Den",
    "wof:placetype":"venue"
},
  "geometry": {"coordinates":[-77.179936,40.231794],"type":"Point"}
}