{
  "type": "Feature",
  "properties": {
    "iso:country":"US",
    "sg:address":"259 Pittsburgh Rd",
    "sg:city":"Butler",
    "sg:classifiers":[
        {
            "category":"Wholesale",
            "subcategory":"Non-durable Goods",
            "type":"Manufacturing & Wholesale Goods"
        },
        {
            "category":"Professional",
            "subcategory":"Advertising",
            "type":"Services"
        }
    ],
    "sg:phone":"+1 724 287 1177",
    "sg:postcode":"16002",
    "sg:province":"PA",
    "sg:tags":[
        "counselor",
        "specialty"
    ],
    "sg:website":"www.keystonespecialties.com",
    "wof:name":"Keystone Specialties Inc",
    "wof:placetype":"venue"
},
  "geometry": {"coordinates":[-79.924284,40.83089],"type":"Point"}
}