{
  "type": "Feature",
  "properties": {
    "addr:full":"19495 Rte 322 Strattanville PA 16258",
    "addr:housenumber":"19495",
    "addr:postcode":"16258",
    "addr:street":"Rte 322 Strattanville",
    "iso:country":"US",
    "sg:address":"19495 Rte 322",
    "sg:city":"Strattanville",
    "sg:classifiers":[
        {
            "category":"Manufacturing",
            "subcategory":"Signs",
            "type":"Manufacturing & Wholesale Goods"
        },
        {
            "category":"Home & Garden",
            "subcategory":"Furniture",
            "type":"Retail Goods"
        }
    ],
    "sg:phone":"+1 814 764 5333",
    "sg:postcode":"16258",
    "sg:province":"PA",
    "sg:tags":[
        "advertising",
        "specialty"
    ],
    "wof:name":"Terry's Sales",
    "wof:placetype":"venue"
},
  "geometry": {"coordinates":[-79.27864099999999,41.189612],"type":"Point"}
}