{
  "type": "Feature",
  "properties": {
    "addr:full":"1143 E Chocolate Ave Hershey PA 17033",
    "addr:housenumber":"1143",
    "addr:postcode":"17033",
    "addr:street":"E Chocolate Ave",
    "iso:country":"US",
    "sg:address":"1143 E Chocolate Ave",
    "sg:city":"Hershey",
    "sg:classifiers":[
        {
            "category":"Autos & Motor Vehicles",
            "subcategory":"Automobile Sales",
            "type":"Retail Goods"
        }
    ],
    "sg:phone":"+1 717 312 1655",
    "sg:postcode":"17033",
    "sg:province":"PA",
    "sg:tags":[
        "car",
        "dealer"
    ],
    "wof:name":"Hershey Honda Hershey Dodge",
    "wof:placetype":"venue"
},
  "geometry": {"coordinates":[-76.623407,40.295846],"type":"Point"}
}