{
  "type": "Feature",
  "properties": {
    "iso:country":"US",
    "sg:address":"5435 Aspen Dr",
    "sg:city":"Erie",
    "sg:classifiers":[
        {
            "category":"Retail",
            "subcategory":"Repair Shop",
            "type":"Services"
        }
    ],
    "sg:phone":"+1 814 833 2188",
    "sg:postcode":"16506",
    "sg:province":"PA",
    "sg:tags":[
        "repairing",
        "piano",
        "refinishing"
    ],
    "wof:name":"Bob Sadowski Piano Tuning",
    "wof:placetype":"venue"
},
  "geometry": {"coordinates":[-80.192987,42.060689],"type":"Point"}
}