{
  "type": "Feature",
  "properties": {
    "iso:country":"US",
    "sg:address":"1 W James St",
    "sg:city":"Lancaster",
    "sg:classifiers":[
        {
            "category":"Personal",
            "subcategory":"Beauty Salon",
            "type":"Services"
        }
    ],
    "sg:phone":"+1 717 390 0601",
    "sg:postcode":"17603",
    "sg:province":"PA",
    "sg:tags":[
        "shop"
    ],
    "wof:name":"Spencer's Studio Of Hair",
    "wof:placetype":"venue"
},
  "geometry": {"coordinates":[-76.308196,40.045775],"type":"Point"}
}