{
  "type": "Feature",
  "properties": {
    "iso:country":"US",
    "sg:address":"2825 Earlystown Rd",
    "sg:city":"Centre Hall",
    "sg:classifiers":[
        {
            "category":"Health Services",
            "subcategory":"Health Practitioner",
            "type":"Services"
        }
    ],
    "sg:phone":"+1 814 364 3290",
    "sg:postcode":"16828",
    "sg:province":"PA",
    "sg:tags":[
        "therapy",
        "physical"
    ],
    "wof:name":"Procare Rehabilitation",
    "wof:placetype":"venue"
},
  "geometry": {"coordinates":[-77.6772,40.8335],"type":"Point"}
}