{
  "type": "Feature",
  "properties": {
    "addr:full":"132 Strickler Run Dr Columbia PA 17512",
    "addr:housenumber":"132",
    "addr:postcode":"17512",
    "addr:street":"Strickler Run Dr",
    "iso:country":"US",
    "sg:address":"132 Strickler Run Dr",
    "sg:city":"Columbia",
    "sg:classifiers":[
        {
            "category":"Building & Trades",
            "subcategory":"Plumbing",
            "type":"Services"
        }
    ],
    "sg:phone":"+1   ",
    "sg:postcode":"17512",
    "sg:province":"PA",
    "sg:tags":[
        "contractor"
    ],
    "wof:name":"Master Plumbing and Service",
    "wof:placetype":"venue"
},
  "geometry": {"coordinates":[-76.444323,40.037358],"type":"Point"}
}