{
  "type": "Feature",
  "properties": {
    "addr:full":"2832 Limekiln Pike Glenside PA 19038",
    "addr:housenumber":"2832",
    "addr:postcode":"19038",
    "addr:street":"Limekiln Pike",
    "iso:country":"US",
    "sg:address":"2832 Limekiln Pike",
    "sg:city":"Glenside",
    "sg:classifiers":[
        {
            "category":"Professional",
            "type":"Services"
        }
    ],
    "sg:phone":"+1 215 884 0737",
    "sg:postcode":"19038",
    "sg:province":"PA",
    "sg:tags":[
        "establishment"
    ],
    "wof:name":"R J Leary Paving",
    "wof:placetype":"venue"
},
  "geometry": {"coordinates":[-75.165288,40.111234],"type":"Point"}
}