{
  "type": "Feature",
  "properties": {
    "addr:full":"1045 State Park Rd Wind Gap PA 18091",
    "addr:housenumber":"1045",
    "addr:postcode":"18091",
    "addr:street":"State Park Rd",
    "iso:country":"US",
    "sg:address":"1045 State Park Rd",
    "sg:city":"Wind Gap",
    "sg:classifiers":[
        {
            "category":"Building & Trades",
            "subcategory":"Construction",
            "type":"Services"
        }
    ],
    "sg:phone":"+1   ",
    "sg:postcode":"18091",
    "sg:province":"PA",
    "sg:tags":[
        "concrete",
        "contractor"
    ],
    "wof:name":"John David Concrete",
    "wof:placetype":"venue"
},
  "geometry": {"coordinates":[-75.29002199999999,40.807153],"type":"Point"}
}