{
  "type": "Feature",
  "properties": {
    "iso:country":"US",
    "sg:address":"1058 E Lycoming St",
    "sg:city":"Philadelphia",
    "sg:classifiers":[
        {
            "category":"Personal",
            "subcategory":"Beauty Salon",
            "type":"Services"
        }
    ],
    "sg:phone":"+1   ",
    "sg:postcode":"19124",
    "sg:province":"PA",
    "sg:tags":[
        "shop"
    ],
    "wof:name":"Juniata",
    "wof:placetype":"venue"
},
  "geometry": {"coordinates":[-75.105768,40.009619],"type":"Point"}
}