{
  "type": "Feature",
  "properties": {
    "addr:full":"1165 New Castle Rd Prospect PA 16052",
    "addr:housenumber":"1165",
    "addr:postcode":"16052",
    "addr:street":"New Castle Rd",
    "iso:country":"US",
    "sg:address":"1165 New Castle Rd",
    "sg:city":"Prospect",
    "sg:classifiers":[
        {
            "category":"Professional",
            "type":"Services"
        }
    ],
    "sg:phone":"+1 724 865 3000",
    "sg:postcode":"16052",
    "sg:province":"PA",
    "sg:tags":[
        "establishment"
    ],
    "wof:name":"Power's Great American Midways",
    "wof:placetype":"venue"
},
  "geometry": {"coordinates":[-80.03536699999999,40.909717],"type":"Point"}
}