{
  "type": "Feature",
  "properties": {
    "iso:country":"US",
    "sg:address":"2725 W 3rd St",
    "sg:city":"Chester",
    "sg:classifiers":[
        {
            "category":"Shopping",
            "subcategory":"Department Store",
            "type":"Retail Goods"
        },
        {
            "category":"Shopping",
            "type":"Retail Goods"
        }
    ],
    "sg:phone":"+1 610 494 9061",
    "sg:postcode":"19013",
    "sg:province":"PA",
    "sg:tags":[
        "merchandising",
        "variety"
    ],
    "wof:name":"Evans Encounters",
    "wof:placetype":"venue"
},
  "geometry": {"coordinates":[-75.39018299999999,39.832214],"type":"Point"}
}