{
  "type": "Feature",
  "properties": {
    "iso:country":"US",
    "sg:address":"4812 Shamrogue Ct",
    "sg:city":"Allison Park",
    "sg:classifiers":[
        {
            "category":"Professional",
            "subcategory":"Engineering",
            "type":"Services"
        }
    ],
    "sg:phone":"+1 724 443 7840",
    "sg:postcode":"15101",
    "sg:province":"PA",
    "sg:tags":[
        "engineer"
    ],
    "wof:name":"Fustos Energy Svc Inc",
    "wof:placetype":"venue"
},
  "geometry": {"coordinates":[-79.93267,40.597035],"type":"Point"}
}