{
  "type": "Feature",
  "properties": {
    "addr:full":"757 Westerly Pkwy State College PA 16801",
    "addr:housenumber":"757",
    "addr:postcode":"16801",
    "addr:street":"Westerly Pkwy",
    "iso:country":"US",
    "sg:address":"757 Westerly Pkwy",
    "sg:city":"State College",
    "sg:classifiers":[
        {
            "category":"Building & Trades",
            "subcategory":"Construction",
            "type":"Services"
        }
    ],
    "sg:phone":"+1 814 234 0449",
    "sg:postcode":"16801",
    "sg:province":"PA",
    "sg:tags":[
        "house",
        "builder",
        "general",
        "operative",
        "contractor"
    ],
    "wof:name":"Donald E Coyne Contractor",
    "wof:placetype":"venue"
},
  "geometry": {"coordinates":[-77.86174699999999,40.782656],"type":"Point"}
}