{
  "type": "Feature",
  "properties": {
    "iso:country":"US",
    "sg:address":"100 Donnertown Rd",
    "sg:city":"Duncansville",
    "sg:classifiers":[
        {
            "category":"Building & Trades",
            "subcategory":"Construction",
            "type":"Services"
        }
    ],
    "sg:phone":"+1   ",
    "sg:postcode":"16635",
    "sg:province":"PA",
    "sg:tags":[
        "excavation",
        "contractor"
    ],
    "wof:name":"Krieger Contracting Company",
    "wof:placetype":"venue"
},
  "geometry": {"coordinates":[-78.434737,40.380827],"type":"Point"}
}