{
  "type": "Feature",
  "properties": {
    "iso:country":"US",
    "sg:address":"25 Johnson Rd",
    "sg:city":"Home",
    "sg:classifiers":[
        {
            "category":"Farming",
            "subcategory":"Dairy Farm",
            "type":"Manufacturing & Wholesale Goods"
        }
    ],
    "sg:phone":"+1   ",
    "sg:postcode":"15747",
    "sg:province":"PA",
    "wof:name":"Raymes Sinan",
    "wof:placetype":"venue"
},
  "geometry": {"coordinates":[-79.12328100000001,40.718948],"type":"Point"}
}