{
  "type": "Feature",
  "properties": {
    "addr:full":"4305 Locust St Philadelphia PA 19104",
    "addr:housenumber":"4305",
    "addr:postcode":"19104",
    "addr:street":"Locust St",
    "iso:country":"US",
    "sg:address":"4305 Locust St",
    "sg:city":"Philadelphia",
    "sg:classifiers":[
        {
            "category":"Retail",
            "subcategory":"Repair Shop",
            "type":"Services"
        }
    ],
    "sg:phone":"+1 215 386 4747",
    "sg:postcode":"19104",
    "sg:province":"PA",
    "sg:tags":[
        "television",
        "radio"
    ],
    "wof:name":"Master Electronics",
    "wof:placetype":"venue"
},
  "geometry": {"coordinates":[-75.210238,39.953963],"type":"Point"}
}