{
  "type": "Feature",
  "properties": {
    "iso:country":"US",
    "sg:address":"416 Wartman Rd",
    "sg:city":"Collegeville",
    "sg:classifiers":[
        {
            "category":"Building & Trades",
            "subcategory":"Cleaning & Sanitation",
            "type":"Services"
        }
    ],
    "sg:phone":"+1   ",
    "sg:postcode":"19426",
    "sg:province":"PA",
    "wof:name":"Iron Bridge Domestic Services",
    "wof:placetype":"venue"
},
  "geometry": {"coordinates":[-75.485231,40.222186],"type":"Point"}
}