{
  "type": "Feature",
  "properties": {
    "iso:country":"US",
    "sg:address":"1 Winding Dr",
    "sg:city":"Philadelphia",
    "sg:classifiers":[
        {
            "category":"Health Services",
            "subcategory":"Clinic",
            "type":"Services"
        }
    ],
    "sg:phone":"+1   ",
    "sg:postcode":"19131",
    "sg:province":"PA",
    "sg:tags":[
        "home",
        "care"
    ],
    "wof:name":"Communty Cre of The Vstng Nrse",
    "wof:placetype":"venue"
},
  "geometry": {"coordinates":[-75.206193,40.008587],"type":"Point"}
}