{
  "type": "Feature",
  "properties": {
    "iso:country":"US",
    "sg:address":"3502 Walnut St",
    "sg:city":"Harrisburg",
    "sg:classifiers":[
        {
            "category":"Bars & Pubs",
            "subcategory":"Nightclub",
            "type":"Food & Drink"
        }
    ],
    "sg:phone":"+1 717 545 8780",
    "sg:postcode":"17109",
    "sg:province":"PA",
    "sg:tags":[
        "nightlife"
    ],
    "wof:name":"Broadway Cafe",
    "wof:placetype":"venue"
},
  "geometry": {"coordinates":[-76.838799,40.2869],"type":"Point"}
}