{
  "type": "Feature",
  "properties": {
    "addr:full":"1198 Chipperfield Dr Stroudsburg PA 18360",
    "addr:housenumber":"1198",
    "addr:postcode":"18360",
    "addr:street":"Chipperfield Dr",
    "iso:country":"US",
    "sg:address":"1198 Chipperfield Dr",
    "sg:city":"Stroudsburg",
    "sg:classifiers":[
        {
            "category":"Education",
            "subcategory":"School",
            "type":"Public Place"
        }
    ],
    "sg:phone":"+1 570 424 4848",
    "sg:postcode":"18360",
    "sg:province":"PA",
    "sg:website":"www.stroudsburg.k12.pa.us",
    "wof:name":"Stroudsburg Junior High School",
    "wof:placetype":"venue"
},
  "geometry": {"coordinates":[-75.217934,40.993997],"type":"Point"}
}