{
  "type": "Feature",
  "properties": {
    "iso:country":"US",
    "sg:address":"6054 Old Philadelphia Pike",
    "sg:city":"Gap",
    "sg:classifiers":[
        {
            "category":"Retail",
            "subcategory":"Repair Shop",
            "type":"Services"
        }
    ],
    "sg:phone":"+1 717 768 3486",
    "sg:postcode":"17527",
    "sg:province":"PA",
    "sg:tags":[
        "appliance"
    ],
    "wof:name":"Buddy Trago's Appliance Repair",
    "wof:placetype":"venue"
},
  "geometry": {"coordinates":[-75.96090599999999,40.028296],"type":"Point"}
}