{
  "type": "Feature",
  "properties": {
    "iso:country":"US",
    "sg:address":"1069 2nd Street Pike",
    "sg:city":"Richboro",
    "sg:classifiers":[
        {
            "category":"Restaurant",
            "type":"Food & Drink"
        }
    ],
    "sg:phone":"+1   ",
    "sg:postcode":"18954",
    "sg:province":"PA",
    "sg:tags":[
        "eating"
    ],
    "wof:name":"Dominicks Pizza",
    "wof:placetype":"venue"
},
  "geometry": {"coordinates":[-75.010411,40.216261],"type":"Point"}
}