{
  "type": "Feature",
  "properties": {
    "addr:full":"2152 N Front St Philadelphia PA 19122",
    "addr:housenumber":"2152",
    "addr:postcode":"19122",
    "addr:street":"N Front St",
    "iso:country":"US",
    "sg:address":"2152 N Front St",
    "sg:city":"Philadelphia",
    "sg:classifiers":[
        {
            "category":"Travel",
            "subcategory":"Travel Agent",
            "type":"Entertainment"
        }
    ],
    "sg:phone":"+1   ",
    "sg:postcode":"19122",
    "sg:province":"PA",
    "sg:tags":[
        "agency"
    ],
    "wof:name":"Aval Multiservices",
    "wof:placetype":"venue"
},
  "geometry": {"coordinates":[-75.132755,39.982364],"type":"Point"}
}