{
  "type": "Feature",
  "properties": {
    "iso:country":"US",
    "sg:address":"740 N Manor Rd",
    "sg:city":"Elverson",
    "sg:classifiers":[
        {
            "category":"Manufacturing",
            "subcategory":"Metals",
            "type":"Manufacturing & Wholesale Goods"
        }
    ],
    "sg:phone":"+1 610 942 0500",
    "sg:postcode":"19520",
    "sg:province":"PA",
    "sg:tags":[
        "work",
        "iron"
    ],
    "sg:website":"http://www.advancedhardscape.com",
    "wof:name":"Advanced Hardscape Solutions",
    "wof:placetype":"venue"
},
  "geometry": {"coordinates":[-75.81026799999999,40.109221],"type":"Point"}
}