{
  "type": "Feature",
  "properties": {
    "iso:country":"US",
    "sg:address":"920 Madison Ave",
    "sg:city":"Norristown",
    "sg:classifiers":[
        {
            "category":"Professional",
            "type":"Services"
        }
    ],
    "sg:phone":"+1 610 650 9330",
    "sg:postcode":"19403",
    "sg:province":"PA",
    "sg:tags":[
        "establishment"
    ],
    "wof:name":"Syscom Technologies",
    "wof:placetype":"venue"
},
  "geometry": {"coordinates":[-75.412559,40.122131],"type":"Point"}
}