{
  "type": "Feature",
  "properties": {
    "iso:country":"US",
    "sg:address":"1708 Clay Ave",
    "sg:city":"Scranton",
    "sg:classifiers":[
        {
            "category":"Shopping",
            "type":"Retail Goods"
        },
        {
            "category":"Manufacturing",
            "subcategory":"Paper Products",
            "type":"Manufacturing & Wholesale Goods"
        }
    ],
    "sg:phone":"+1 570 347 2000",
    "sg:postcode":"18509",
    "sg:province":"PA",
    "sg:tags":[
        "packaging",
        "materials-wholesale",
        "material",
        "manufacturer"
    ],
    "wof:name":"Mann Packing Company",
    "wof:placetype":"venue"
},
  "geometry": {"coordinates":[-75.63603000000001,41.424086],"type":"Point"}
}