{
  "type": "Feature",
  "properties": {
    "iso:country":"US",
    "sg:address":"551 Main St Ste 204",
    "sg:city":"Johnstown",
    "sg:classifiers":[
        {
            "category":"Banks & Credit Unions",
            "subcategory":"Investment Brokerage",
            "type":"Services"
        },
        {
            "category":"Insurance",
            "subcategory":"Hazard Insurance",
            "type":"Services"
        }
    ],
    "sg:phone":"+1 814 532 0262",
    "sg:postcode":"15901",
    "sg:province":"PA",
    "sg:tags":[
        "commercial",
        "agent",
        "business",
        "resume"
    ],
    "wof:name":"The Gleason Agency Inc",
    "wof:placetype":"venue"
},
  "geometry": {"coordinates":[-78.916534,40.324595],"type":"Point"}
}