{
  "type": "Feature",
  "properties": {
    "addr:full":"6667 Memorial Rd New Tripoli PA 18066",
    "addr:housenumber":"6667",
    "addr:postcode":"18066",
    "addr:street":"Memorial Rd",
    "iso:country":"US",
    "sg:address":"6667 Memorial Rd",
    "sg:city":"New Tripoli",
    "sg:classifiers":[
        {
            "category":"Building & Trades",
            "subcategory":"Landscaping Services",
            "type":"Services"
        }
    ],
    "sg:phone":"+1   ",
    "sg:postcode":"18066",
    "sg:province":"PA",
    "wof:name":"Schleichers Lawn Care",
    "wof:placetype":"venue"
},
  "geometry": {"coordinates":[-75.73806399999999,40.69471],"type":"Point"}
}