{
  "type": "Feature",
  "properties": {
    "addr:full":"2227 Valley Rd Bloomsburg PA 17815",
    "addr:housenumber":"2227",
    "addr:postcode":"17815",
    "addr:street":"Valley Rd",
    "iso:country":"US",
    "sg:address":"2227 Valley Rd",
    "sg:city":"Bloomsburg",
    "sg:classifiers":[
        {
            "category":"Farming",
            "subcategory":"Dairy Farm",
            "type":"Manufacturing & Wholesale Goods"
        }
    ],
    "sg:phone":"+1   ",
    "sg:postcode":"17815",
    "sg:province":"PA",
    "wof:name":"Carl Crawford",
    "wof:placetype":"venue"
},
  "geometry": {"coordinates":[-76.610231,41.079035],"type":"Point"}
}