{
  "type": "Feature",
  "properties": {
    "iso:country":"US",
    "sg:address":"210 Elmwood Ave",
    "sg:city":"Feastervl Trvs",
    "sg:classifiers":[
        {
            "category":"Retail",
            "subcategory":"Auto Repair",
            "type":"Services"
        }
    ],
    "sg:phone":"+1 215 322 8410",
    "sg:postcode":"19053",
    "sg:province":"PA",
    "sg:tags":[
        "body",
        "automobile",
        "painting"
    ],
    "wof:name":"Z & M Auto Body & Repair",
    "wof:placetype":"venue"
},
  "geometry": {"coordinates":[-74.984706,40.156488],"type":"Point"}
}