{
  "type": "Feature",
  "properties": {
    "addr:full":"25 N Ridge Rd Elderton PA 15774",
    "addr:housenumber":"25",
    "addr:postcode":"15774",
    "addr:street":"N Ridge Rd",
    "iso:country":"US",
    "sg:address":"25 N Ridge Rd",
    "sg:city":"Elderton",
    "sg:classifiers":[
        {
            "category":"Utilities",
            "subcategory":"Natural Gas",
            "type":"Services"
        }
    ],
    "sg:phone":"+1 724 354 4118",
    "sg:postcode":"15774",
    "sg:province":"PA",
    "wof:name":"North Eastern Energy Conslnts",
    "wof:placetype":"venue"
},
  "geometry": {"coordinates":[-79.29218299999999,40.655157],"type":"Point"}
}