{
  "type": "Feature",
  "properties": {
    "iso:country":"US",
    "sg:address":"3351 Lincoln Hwy E",
    "sg:city":"Paradise",
    "sg:classifiers":[
        {
            "category":"Home & Garden",
            "subcategory":"Mobile Homes",
            "type":"Retail Goods"
        }
    ],
    "sg:phone":"+1 717 442 5225",
    "sg:postcode":"17562",
    "sg:province":"PA",
    "wof:name":"Signatures Homes",
    "wof:placetype":"venue"
},
  "geometry": {"coordinates":[-76.099526,40.003639],"type":"Point"}
}