{
  "type": "Feature",
  "properties": {
    "addr:full":"922 Walnut St Philadelphia PA 19176",
    "addr:housenumber":"922",
    "addr:postcode":"19176",
    "addr:street":"Walnut St",
    "iso:country":"US",
    "sg:address":"922 Walnut St",
    "sg:city":"Philadelphia",
    "sg:classifiers":[
        {
            "category":"Coffee & Tea",
            "type":"Food & Drink"
        }
    ],
    "sg:phone":"+1 215 238 7407",
    "sg:postcode":"19176",
    "sg:province":"PA",
    "sg:website":"www.mybonte.com",
    "wof:name":"Bonte",
    "wof:placetype":"venue"
},
  "geometry": {"coordinates":[-75.156136,39.948331],"type":"Point"}
}