{
  "type": "Feature",
  "properties": {
    "iso:country":"US",
    "sg:address":"225 W Oaks Rd",
    "sg:city":"Oxford",
    "sg:phone":"+1   ",
    "sg:postcode":"19363",
    "sg:province":"PA",
    "sg:tags":[
        "farm",
        "corn"
    ],
    "wof:name":"Robert Herr",
    "wof:placetype":"venue"
},
  "geometry": {"coordinates":[-76.007088,39.772043],"type":"Point"}
}