{
  "type": "Feature",
  "properties": {
    "iso:country":"US",
    "sg:address":"90 Mount Airy Rd",
    "sg:city":"New Providence",
    "sg:classifiers":[
        {
            "category":"Building & Trades",
            "subcategory":"Construction",
            "type":"Services"
        }
    ],
    "sg:phone":"+1 717 786 8057",
    "sg:postcode":"17560",
    "sg:province":"PA",
    "sg:tags":[
        "excavation",
        "excavating",
        "contractor"
    ],
    "wof:name":"Herr's Excavating",
    "wof:placetype":"venue"
},
  "geometry": {"coordinates":[-76.242763,39.91585],"type":"Point"}
}