{
  "type": "Feature",
  "properties": {
    "iso:country":"US",
    "sg:address":"1200 Locust St",
    "sg:city":"Philadelphia",
    "sg:classifiers":[
        {
            "category":"Health Services",
            "subcategory":"Doctor",
            "type":"Services"
        }
    ],
    "sg:phone":"+1 215 546 3666",
    "sg:postcode":"19107",
    "sg:province":"PA",
    "sg:tags":[
        "dermatologist"
    ],
    "sg:website":"www.benedettoderm.com",
    "wof:name":"Sklaroff Robt B MD",
    "wof:placetype":"venue"
},
  "geometry": {"coordinates":[-75.16089599999999,39.947899],"type":"Point"}
}