{
  "type": "Feature",
  "properties": {
    "iso:country":"US",
    "sg:address":"20 S Keyser Ave",
    "sg:city":"Taylor",
    "sg:classifiers":[
        {
            "category":"Freight",
            "type":"Transportation"
        },
        {
            "category":"Professional",
            "subcategory":"Employment Agencies",
            "type":"Services"
        }
    ],
    "sg:phone":"+1 570 562 7970",
    "sg:postcode":"18517",
    "sg:province":"PA",
    "sg:tags":[
        "help",
        "shipping",
        "agent",
        "supply"
    ],
    "sg:website":"www.odfl.com",
    "wof:name":"Old Dominion Freight Line",
    "wof:placetype":"venue"
},
  "geometry": {"coordinates":[-75.729147,41.395277],"type":"Point"}
}