{
  "type": "Feature",
  "properties": {
    "addr:full":"600 River Ave Ste 1 Pittsburgh PA 15212",
    "addr:housenumber":"600",
    "addr:postcode":"15212",
    "addr:street":"River Ave Ste 1",
    "iso:country":"US",
    "sg:address":"600 River Ave Ste 1",
    "sg:city":"Pittsburgh",
    "sg:classifiers":[
        {
            "category":"Professional",
            "subcategory":"Business Services",
            "type":"Services"
        }
    ],
    "sg:phone":"+1 412 621 9009",
    "sg:postcode":"15212",
    "sg:province":"PA",
    "sg:tags":[
        "commercial",
        "designers-industrial"
    ],
    "sg:website":"http://www.ballydesign.com",
    "wof:name":"Bally Exhibit",
    "wof:placetype":"venue"
},
  "geometry": {"coordinates":[-79.99791,40.44894],"type":"Point"}
}