{
  "type": "Feature",
  "properties": {
    "iso:country":"US",
    "sg:address":"2315 Byron Ct",
    "sg:city":"Indiana",
    "sg:classifiers":[
        {
            "category":"Organizations",
            "subcategory":"Religious Organization",
            "type":"Services"
        }
    ],
    "sg:phone":"+1 724 465 0458",
    "sg:postcode":"15701",
    "sg:province":"PA",
    "sg:tags":[
        "church"
    ],
    "wof:name":"Harvest Church",
    "wof:placetype":"venue"
},
  "geometry": {"coordinates":[-79.191506,40.616643],"type":"Point"}
}