{
  "type": "Feature",
  "properties": {
    "iso:country":"US",
    "sg:address":"1121 Welsh Rd",
    "sg:city":"Ambler",
    "sg:classifiers":[
        {
            "category":"Shopping",
            "subcategory":"Optical Goods",
            "type":"Retail Goods"
        }
    ],
    "sg:phone":"+1   ",
    "sg:postcode":"19002",
    "sg:province":"PA",
    "sg:tags":[
        "product",
        "retailer",
        "vision",
        "care"
    ],
    "wof:name":"Actin Industries",
    "wof:placetype":"venue"
},
  "geometry": {"coordinates":[-75.169561,40.172647],"type":"Point"}
}