{
  "type": "Feature",
  "properties": {
    "iso:country":"US",
    "sg:address":"937 4th Ave",
    "sg:city":"Ford City",
    "sg:classifiers":[
        {
            "category":"Personal",
            "subcategory":"Beauty Salon",
            "type":"Services"
        }
    ],
    "sg:phone":"+1 724 763 8196",
    "sg:postcode":"16226",
    "sg:province":"PA",
    "wof:name":"Hair By Grace Serene",
    "wof:placetype":"venue"
},
  "geometry": {"coordinates":[-79.531013,40.771153],"type":"Point"}
}