{
  "type": "Feature",
  "properties": {
    "addr:full":"1316 W Chester Rd West Chester PA 19382",
    "addr:housenumber":"1316",
    "addr:postcode":"19382",
    "addr:street":"W Chester Rd",
    "iso:country":"US",
    "sg:address":"1316 W Chester Rd",
    "sg:city":"West Chester",
    "sg:classifiers":[
        {
            "category":"Professional",
            "subcategory":"Advertising",
            "type":"Services"
        }
    ],
    "sg:phone":"+1   ",
    "sg:postcode":"19382",
    "sg:province":"PA",
    "sg:tags":[
        "mail",
        "direct"
    ],
    "wof:name":"Mail Service Center",
    "wof:placetype":"venue"
},
  "geometry": {"coordinates":[-75.547245,39.911069],"type":"Point"}
}