{
  "type": "Feature",
  "properties": {
    "iso:country":"US",
    "sg:address":"220 W Lancaster Ave",
    "sg:city":"Reading",
    "sg:classifiers":[
        {
            "category":"Autos & Motor Vehicles",
            "subcategory":"Fuel & Gas Station",
            "type":"Retail Goods"
        }
    ],
    "sg:phone":"+1   ",
    "sg:postcode":"19607",
    "sg:province":"PA",
    "sg:tags":[
        "station",
        "gasoline"
    ],
    "wof:name":"Ed Showalters Service Center",
    "wof:placetype":"venue"
},
  "geometry": {"coordinates":[-75.971783,40.304526],"type":"Point"}
}