{
  "type": "Feature",
  "properties": {
    "addr:full":"8029 Temple Rd Philadelphia PA 19150",
    "addr:housenumber":"8029",
    "addr:postcode":"19150",
    "addr:street":"Temple Rd",
    "iso:country":"US",
    "sg:address":"8029 Temple Rd",
    "sg:city":"Philadelphia",
    "sg:classifiers":[
        {
            "category":"Professional",
            "subcategory":"Accounting & Tax Preparation",
            "type":"Services"
        }
    ],
    "sg:phone":"+1   ",
    "sg:postcode":"19150",
    "sg:province":"PA",
    "wof:name":"Ethel S Parsons CPA",
    "wof:placetype":"venue"
},
  "geometry": {"coordinates":[-75.168903,40.075133],"type":"Point"}
}