{
  "type": "Feature",
  "properties": {
    "addr:full":"380 Norway St York PA 17403",
    "addr:housenumber":"380",
    "addr:postcode":"17403",
    "addr:street":"Norway St",
    "iso:country":"US",
    "sg:address":"380 Norway St",
    "sg:city":"York",
    "sg:classifiers":[
        {
            "category":"Wholesale",
            "subcategory":"Hardware",
            "type":"Manufacturing & Wholesale Goods"
        }
    ],
    "sg:phone":"+1 717 845 2671",
    "sg:postcode":"17403",
    "sg:province":"PA",
    "sg:website":"www.aaofpa.com",
    "wof:name":"A & A Of Pa Inc",
    "wof:placetype":"venue"
},
  "geometry": {"coordinates":[-76.708012,39.962719],"type":"Point"}
}