{
  "type": "Feature",
  "properties": {
    "iso:country":"US",
    "sg:address":"700 US Hwy 202",
    "sg:city":"King Of Prussia",
    "sg:classifiers":[
        {
            "category":"Professional",
            "subcategory":"Management & Consulting",
            "type":"Services"
        }
    ],
    "sg:phone":"+1   ",
    "sg:postcode":"19406",
    "sg:province":"PA",
    "sg:tags":[
        "business"
    ],
    "wof:name":"ONeil Group The",
    "wof:placetype":"venue"
},
  "geometry": {"coordinates":[-75.385086,40.08703],"type":"Point"}
}