{
  "type": "Feature",
  "properties": {
    "addr:full":"6049 Main St East Petersburg PA 17520",
    "addr:housenumber":"6049",
    "addr:postcode":"17520",
    "addr:street":"Main St",
    "iso:country":"US",
    "sg:address":"6049 Main St",
    "sg:city":"East Petersburg",
    "sg:classifiers":[
        {
            "category":"Restaurant",
            "type":"Food & Drink"
        }
    ],
    "sg:phone":"+1 717 581 5407",
    "sg:postcode":"17520",
    "sg:province":"PA",
    "wof:name":"Chancey's Pub",
    "wof:placetype":"venue"
},
  "geometry": {"coordinates":[-76.354084,40.100133],"type":"Point"}
}