{
  "type": "Feature",
  "properties": {
    "addr:full":"7607 Woodlawn Ave Elkins Park PA 19027",
    "addr:housenumber":"7607",
    "addr:postcode":"19027",
    "addr:street":"Woodlawn Ave",
    "iso:country":"US",
    "sg:address":"7607 Woodlawn Ave",
    "sg:city":"Elkins Park",
    "sg:classifiers":[
        {
            "category":"Organizations",
            "subcategory":"Community Association",
            "type":"Services"
        }
    ],
    "sg:phone":"+1   ",
    "sg:postcode":"19027",
    "sg:province":"PA",
    "wof:name":"Gyac",
    "wof:placetype":"venue"
},
  "geometry": {"coordinates":[-75.120192,40.06507],"type":"Point"}
}