{
  "type": "Feature",
  "properties": {
    "iso:country":"US",
    "sg:address":"306 Oak St",
    "sg:city":"Walnutport",
    "sg:classifiers":[
        {
            "category":"Autos & Motor Vehicles",
            "subcategory":"Fuel & Gas Station",
            "type":"Retail Goods"
        },
        {
            "category":"Retail",
            "subcategory":"Auto Repair",
            "type":"Services"
        }
    ],
    "sg:phone":"+1 610 767 9620",
    "sg:postcode":"18088",
    "sg:province":"PA",
    "sg:tags":[
        "automobile",
        "inspection",
        "diagnostic"
    ],
    "wof:name":"Donald Gogel's Garage",
    "wof:placetype":"venue"
},
  "geometry": {"coordinates":[-75.597567,40.757985],"type":"Point"}
}