{
  "type": "Feature",
  "properties": {
    "iso:country":"US",
    "sg:address":"2804 Walbert Ave",
    "sg:city":"Allentown",
    "sg:classifiers":[
        {
            "category":"Health Services",
            "subcategory":"Medical Lab",
            "type":"Services"
        }
    ],
    "sg:phone":"+1 610 432 6183",
    "sg:postcode":"18104",
    "sg:province":"PA",
    "sg:tags":[
        "laboratory",
        "dental"
    ],
    "wof:name":"Pro Dent Studio",
    "wof:placetype":"venue"
},
  "geometry": {"coordinates":[-75.528711,40.615983],"type":"Point"}
}