{
  "type": "Feature",
  "properties": {
    "iso:country":"US",
    "sg:address":"213 Crescent Ave",
    "sg:city":"Ellwood City",
    "sg:classifiers":[
        {
            "category":"Shopping",
            "subcategory":"Florist",
            "type":"Retail Goods"
        }
    ],
    "sg:phone":"+1 724 752 1645",
    "sg:postcode":"16117",
    "sg:province":"PA",
    "wof:name":"Flower Nook",
    "wof:placetype":"venue"
},
  "geometry": {"coordinates":[-80.28260400000001,40.857502],"type":"Point"}
}