{
  "type": "Feature",
  "properties": {
    "iso:country":"US",
    "sg:address":"121 Buckwheat Dr",
    "sg:city":"Gibsonia",
    "sg:classifiers":[
        {
            "category":"Real Estate",
            "subcategory":"Real Estate Services",
            "type":"Services"
        },
        {
            "category":"Building & Trades",
            "subcategory":"Construction",
            "type":"Services"
        }
    ],
    "sg:phone":"+1 412 427 5971",
    "sg:postcode":"15044",
    "sg:province":"PA",
    "sg:tags":[
        "interior",
        "home",
        "design",
        "staging"
    ],
    "wof:name":"Susan Muschweck Interior Design & Home Staging",
    "wof:placetype":"venue"
},
  "geometry": {"coordinates":[-80.019263,40.650573],"type":"Point"}
}