{
  "type": "Feature",
  "properties": {
    "iso:country":"US",
    "sg:address":"1915 Arch St",
    "sg:city":"Philadelphia",
    "sg:classifiers":[
        {
            "category":"Professional",
            "subcategory":"Business Services",
            "type":"Services"
        },
        {
            "category":"Wholesale",
            "subcategory":"Books, Periodicals, & Newspapers",
            "type":"Manufacturing & Wholesale Goods"
        }
    ],
    "sg:phone":"+1 215 568 2270",
    "sg:postcode":"19103",
    "sg:province":"PA",
    "sg:tags":[
        "consultant",
        "book",
        "publishing",
        "representative",
        "publisher"
    ],
    "sg:website":"http://www.fadavis.com",
    "wof:name":"F A Davis Company",
    "wof:placetype":"venue"
},
  "geometry": {"coordinates":[-75.171369,39.955419],"type":"Point"}
}