{
  "type": "Feature",
  "properties": {
    "addr:full":"1251 N Wales Rd North Wales PA 19454",
    "addr:housenumber":"1251",
    "addr:postcode":"19454",
    "addr:street":"N Wales Rd",
    "iso:country":"US",
    "sg:address":"1251 N Wales Rd",
    "sg:city":"North Wales",
    "sg:classifiers":[
        {
            "category":"Shopping",
            "subcategory":"Computers & Home Electronics",
            "type":"Retail Goods"
        }
    ],
    "sg:phone":"+1 215 616 5710",
    "sg:postcode":"19454",
    "sg:province":"PA",
    "sg:tags":[
        "equipment",
        "dealer"
    ],
    "wof:name":"Compusa",
    "wof:placetype":"venue"
},
  "geometry": {"coordinates":[-75.27195,40.220284],"type":"Point"}
}