{
  "type": "Feature",
  "properties": {
    "iso:country":"US",
    "sg:address":"502 William Penn Pl",
    "sg:city":"Pittsburgh",
    "sg:classifiers":[
        {
            "category":"Food & Beverages",
            "subcategory":"Candy",
            "type":"Retail Goods"
        }
    ],
    "sg:phone":"+1 412 391 2990",
    "sg:postcode":"15219",
    "sg:province":"PA",
    "sg:tags":[
        "confectionery"
    ],
    "wof:name":"Betsy Ann Chocolates",
    "wof:placetype":"venue"
},
  "geometry": {"coordinates":[-79.997187,40.440354],"type":"Point"}
}