{
  "type": "Feature",
  "properties": {
    "addr:full":"557 Main St Honesdale PA 18431",
    "addr:housenumber":"557",
    "addr:postcode":"18431",
    "addr:street":"Main St",
    "iso:country":"US",
    "sg:address":"557 Main St",
    "sg:city":"Honesdale",
    "sg:classifiers":[
        {
            "category":"Professional",
            "subcategory":"Employment Agencies",
            "type":"Services"
        }
    ],
    "sg:phone":"+1 570 251 9939",
    "sg:postcode":"18431",
    "sg:province":"PA",
    "wof:name":"Progressive Personnel Agency",
    "wof:placetype":"venue"
},
  "geometry": {"coordinates":[-75.254363,41.569893],"type":"Point"}
}