{
  "type": "Feature",
  "properties": {
    "addr:full":"1321 E Market St York PA 17403",
    "addr:housenumber":"1321",
    "addr:postcode":"17403",
    "addr:street":"E Market St",
    "iso:country":"US",
    "sg:address":"1321 E Market St",
    "sg:city":"York",
    "sg:classifiers":[
        {
            "category":"Personal",
            "subcategory":"Barber",
            "type":"Services"
        }
    ],
    "sg:phone":"+1 717 854 2884",
    "sg:postcode":"17403",
    "sg:province":"PA",
    "wof:name":"Mane Choice",
    "wof:placetype":"venue"
},
  "geometry": {"coordinates":[-76.702337,39.972129],"type":"Point"}
}