{
  "type": "Feature",
  "properties": {
    "iso:country":"US",
    "sg:address":"107 N Ridge St",
    "sg:city":"Taylor",
    "sg:classifiers":[
        {
            "category":"Building & Trades",
            "subcategory":"Construction",
            "type":"Services"
        }
    ],
    "sg:phone":"+1   ",
    "sg:postcode":"18517",
    "sg:province":"PA",
    "sg:tags":[
        "house"
    ],
    "wof:name":"Rich Juba Home",
    "wof:placetype":"venue"
},
  "geometry": {"coordinates":[-75.71189099999999,41.385904],"type":"Point"}
}