{
  "type": "Feature",
  "properties": {
    "iso:country":"US",
    "sg:address":"1401 W Schuylkill Rd",
    "sg:city":"Pottstown",
    "sg:classifiers":[
        {
            "category":"Autos & Motor Vehicles",
            "subcategory":"Automobile Sales",
            "type":"Retail Goods"
        }
    ],
    "sg:phone":"+1 610 970 4955",
    "sg:postcode":"19465",
    "sg:province":"PA",
    "sg:tags":[
        "car",
        "dealer"
    ],
    "wof:name":"John Ruckle's Auto Sales",
    "wof:placetype":"venue"
},
  "geometry": {"coordinates":[-75.68940499999999,40.235513],"type":"Point"}
}