{
  "type": "Feature",
  "properties": {
    "iso:country":"US",
    "sg:address":"52 Mack Ave",
    "sg:city":"Johnstown",
    "sg:classifiers":[
        {
            "category":"Building & Trades",
            "subcategory":"Construction",
            "type":"Services"
        }
    ],
    "sg:phone":"+1   ",
    "sg:postcode":"15906",
    "sg:province":"PA",
    "sg:tags":[
        "house"
    ],
    "wof:name":"Katanzik Building & Remodeling",
    "wof:placetype":"venue"
},
  "geometry": {"coordinates":[-78.924294,40.388381],"type":"Point"}
}