{
  "type": "Feature",
  "properties": {
    "iso:country":"US",
    "sg:address":"4012 Market St",
    "sg:city":"Philadelphia",
    "sg:classifiers":[
        {
            "category":"Sports & Exercise",
            "subcategory":"Gym",
            "type":"Entertainment"
        }
    ],
    "sg:phone":"+1 215 895 3422",
    "sg:postcode":"19104",
    "sg:province":"PA",
    "sg:tags":[
        "salon",
        "beauty",
        "facility",
        "fitness",
        "spa",
        "day",
        "physical"
    ],
    "sg:website":"www.itnojspa.com",
    "wof:name":"Itno-J Spa",
    "wof:placetype":"venue"
},
  "geometry": {"coordinates":[-75.202552,39.95693],"type":"Point"}
}