{
  "type": "Feature",
  "properties": {
    "iso:country":"US",
    "sg:address":"766 Ashton Rd",
    "sg:city":"Bensalem",
    "sg:classifiers":[
        {
            "category":"Wholesale",
            "subcategory":"Seafood",
            "type":"Manufacturing & Wholesale Goods"
        }
    ],
    "sg:phone":"+1   ",
    "sg:postcode":"19020",
    "sg:province":"PA",
    "wof:name":"Ted Mocarski Prime Meats",
    "wof:placetype":"venue"
},
  "geometry": {"coordinates":[-74.908805,40.103972],"type":"Point"}
}