{
  "type": "Feature",
  "properties": {
    "iso:country":"US",
    "sg:address":"120 N Chester Rd",
    "sg:city":"West Chester",
    "sg:classifiers":[
        {
            "category":"Professional",
            "subcategory":"Lawyer & Legal Services",
            "type":"Services"
        }
    ],
    "sg:phone":"+1   ",
    "sg:postcode":"19380",
    "sg:province":"PA",
    "wof:name":"James Porter",
    "wof:placetype":"venue"
},
  "geometry": {"coordinates":[-75.52737,39.969178],"type":"Point"}
}