{
  "type": "Feature",
  "properties": {
    "iso:country":"US",
    "sg:address":"229 E Union Blvd",
    "sg:city":"Bethlehem",
    "sg:classifiers":[
        {
            "category":"Education",
            "subcategory":"Dance Studio",
            "type":"Public Place"
        }
    ],
    "sg:phone":"+1 610 861 9676",
    "sg:postcode":"18018",
    "sg:province":"PA",
    "sg:tags":[
        "instruction",
        "dancing"
    ],
    "wof:name":"Danceging",
    "wof:placetype":"venue"
},
  "geometry": {"coordinates":[-75.372624,40.624874],"type":"Point"}
}