{
  "type": "Feature",
  "properties": {
    "iso:country":"US",
    "sg:address":"44 Swamp Pike",
    "sg:city":"Limerick",
    "sg:classifiers":[
        {
            "category":"Real Estate",
            "subcategory":"Developer",
            "type":"Services"
        }
    ],
    "sg:phone":"+1 610 495 6231",
    "sg:postcode":"19468",
    "sg:province":"PA",
    "sg:tags":[
        "cemetery"
    ],
    "wof:name":"Limerick Garden Of Memories",
    "wof:placetype":"venue"
},
  "geometry": {"coordinates":[-75.525325,40.233865],"type":"Point"}
}