{
  "type": "Feature",
  "properties": {
    "iso:country":"US",
    "sg:address":"3384 Babcock Blvd",
    "sg:city":"Pittsburgh",
    "sg:classifiers":[
        {
            "category":"Professional",
            "type":"Services"
        }
    ],
    "sg:phone":"+1   ",
    "sg:postcode":"15237",
    "sg:province":"PA",
    "wof:name":"Kurtco",
    "wof:placetype":"venue"
},
  "geometry": {"coordinates":[-80.021081,40.536131],"type":"Point"}
}