{
  "type": "Feature",
  "properties": {
    "iso:country":"US",
    "sg:address":"200 Center Way",
    "sg:city":"Beaver",
    "sg:classifiers":[
        {
            "category":"Retail",
            "subcategory":"Auto Repair",
            "type":"Services"
        }
    ],
    "sg:phone":"+1 724 728 4700",
    "sg:postcode":"15009",
    "sg:province":"PA",
    "sg:tags":[
        "body",
        "automobile",
        "painting"
    ],
    "wof:name":"R L Trushel Auto Body",
    "wof:placetype":"venue"
},
  "geometry": {"coordinates":[-80.297062,40.697493],"type":"Point"}
}