{
  "type": "Feature",
  "properties": {
    "iso:country":"US",
    "sg:address":"3181 Cape Horn Rd",
    "sg:city":"Red Lion",
    "sg:classifiers":[
        {
            "category":"Retail",
            "subcategory":"Laundry & Dry Cleaning",
            "type":"Services"
        }
    ],
    "sg:phone":"+1 717 244 9842",
    "sg:postcode":"17356",
    "sg:province":"PA",
    "sg:tags":[
        "cleaners"
    ],
    "wof:name":"Devono's Dry Cleaners & Shirt",
    "wof:placetype":"venue"
},
  "geometry": {"coordinates":[-76.64514699999999,39.941874],"type":"Point"}
}