{
  "type": "Feature",
  "properties": {
    "addr:full":"640 S Queen St Lancaster PA 17603",
    "addr:housenumber":"640",
    "addr:postcode":"17603",
    "addr:street":"S Queen St",
    "iso:country":"US",
    "sg:address":"640 S Queen St",
    "sg:city":"Lancaster",
    "sg:classifiers":[
        {
            "category":"Shopping",
            "type":"Retail Goods"
        }
    ],
    "sg:phone":"+1 717 509 3746",
    "sg:postcode":"17603",
    "sg:province":"PA",
    "sg:tags":[
        "factory",
        "outlet"
    ],
    "wof:name":"Spero's Outlet",
    "wof:placetype":"venue"
},
  "geometry": {"coordinates":[-76.303675,40.026787],"type":"Point"}
}