{
  "type": "Feature",
  "properties": {
    "iso:country":"US",
    "sg:address":"804 Evergreen Dr",
    "sg:city":"Reading",
    "sg:classifiers":[
        {
            "category":"Building & Trades",
            "subcategory":"Plumbing",
            "type":"Services"
        }
    ],
    "sg:phone":"+1 610 375 3132",
    "sg:postcode":"19610",
    "sg:province":"PA",
    "sg:tags":[
        "heating",
        "contractor"
    ],
    "wof:name":"Keystone Heating & Cooling",
    "wof:placetype":"venue"
},
  "geometry": {"coordinates":[-75.996607,40.337035],"type":"Point"}
}