{
  "type": "Feature",
  "properties": {
    "addr:full":"1318 Ridgewood Dr Allison Park PA 15101",
    "addr:housenumber":"1318",
    "addr:postcode":"15101",
    "addr:street":"Ridgewood Dr",
    "iso:country":"US",
    "sg:address":"1318 Ridgewood Dr",
    "sg:city":"Allison Park",
    "sg:classifiers":[
        {
            "category":"Banks & Credit Unions",
            "subcategory":"Bank",
            "type":"Services"
        }
    ],
    "sg:phone":"+1 412 364 5100",
    "sg:postcode":"15101",
    "sg:province":"PA",
    "sg:tags":[
        "loan",
        "real estate"
    ],
    "wof:name":"Quantum Mortgage Svc",
    "wof:placetype":"venue"
},
  "geometry": {"coordinates":[-80.01015200000001,40.582624],"type":"Point"}
}