{
  "type": "Feature",
  "properties": {
    "addr:full":"601 Fawn Cir King Of Prussia PA 19406",
    "addr:housenumber":"601",
    "addr:postcode":"19406",
    "addr:street":"Fawn Cir",
    "iso:country":"US",
    "sg:address":"601 Fawn Cir",
    "sg:city":"King Of Prussia",
    "sg:classifiers":[
        {
            "category":"Banks & Credit Unions",
            "subcategory":"Investment Brokerage",
            "type":"Services"
        }
    ],
    "sg:phone":"+1   ",
    "sg:postcode":"19406",
    "sg:province":"PA",
    "sg:tags":[
        "security"
    ],
    "wof:name":"D H Capital",
    "wof:placetype":"venue"
},
  "geometry": {"coordinates":[-75.395782,40.105083],"type":"Point"}
}