{
  "type": "Feature",
  "properties": {
    "iso:country":"US",
    "sg:address":"2128 Perkiomen Ave",
    "sg:city":"Reading",
    "sg:classifiers":[
        {
            "category":"Health Services",
            "subcategory":"Doctor",
            "type":"Services"
        }
    ],
    "sg:phone":"+1 610 779 5123",
    "sg:postcode":"19606",
    "sg:province":"PA",
    "sg:tags":[
        "dentist"
    ],
    "wof:name":"Dwayne A Lanz DDS",
    "wof:placetype":"venue"
},
  "geometry": {"coordinates":[-75.896017,40.327735],"type":"Point"}
}