{
  "type": "Feature",
  "properties": {
    "addr:full":"419 N 6th Ave Butler PA 16001",
    "addr:housenumber":"419",
    "addr:postcode":"16001",
    "addr:street":"N 6Th Ave",
    "iso:country":"US",
    "sg:address":"419 N 6th Ave",
    "sg:city":"Butler",
    "sg:classifiers":[
        {
            "category":"Shopping",
            "subcategory":"Florist",
            "type":"Retail Goods"
        }
    ],
    "sg:phone":"+1 724 285 8618",
    "sg:postcode":"16001",
    "sg:province":"PA",
    "wof:name":"Special Occasion Florals",
    "wof:placetype":"venue"
},
  "geometry": {"coordinates":[-79.910128,40.867177],"type":"Point"}
}