{
  "type": "Feature",
  "properties": {
    "addr:full":"4321 Beverly Dr Aliquippa PA 15001",
    "addr:housenumber":"4321",
    "addr:postcode":"15001",
    "addr:street":"Beverly Dr",
    "iso:country":"US",
    "sg:address":"4321 Beverly Dr",
    "sg:city":"Aliquippa",
    "sg:classifiers":[
        {
            "category":"Insurance",
            "subcategory":"Life Insurance",
            "type":"Services"
        }
    ],
    "sg:phone":"+1   ",
    "sg:postcode":"15001",
    "sg:province":"PA",
    "sg:tags":[
        "carrier"
    ],
    "wof:name":"Slovene National Benefit Soc",
    "wof:placetype":"venue"
},
  "geometry": {"coordinates":[-80.25689300000001,40.576352],"type":"Point"}
}