{
  "type": "Feature",
  "properties": {
    "iso:country":"US",
    "sg:address":"55 S Washington St",
    "sg:city":"Waynesburg",
    "sg:classifiers":[
        {
            "category":"Real Estate",
            "subcategory":"Real Estate Agent",
            "type":"Services"
        }
    ],
    "sg:phone":"+1 724 627 6123",
    "sg:postcode":"15370",
    "sg:province":"PA",
    "sg:tags":[
        "appraiser"
    ],
    "wof:name":"Baily Real Estate Agency",
    "wof:placetype":"venue"
},
  "geometry": {"coordinates":[-80.18701799999999,39.89571],"type":"Point"}
}