{
  "type": "Feature",
  "properties": {
    "addr:full":"411 Washington Ave Charleroi PA 15022",
    "addr:housenumber":"411",
    "addr:postcode":"15022",
    "addr:street":"Washington Ave",
    "iso:country":"US",
    "sg:address":"411 Washington Ave",
    "sg:city":"Charleroi",
    "sg:classifiers":[
        {
            "category":"Professional",
            "subcategory":"Lawyer & Legal Services",
            "type":"Services"
        }
    ],
    "sg:phone":"+1 724 489 9523",
    "sg:postcode":"15022",
    "sg:province":"PA",
    "sg:tags":[
        "attorney"
    ],
    "wof:name":"Melenyzer & Savona",
    "wof:placetype":"venue"
},
  "geometry": {"coordinates":[-79.898009,40.136574],"type":"Point"}
}