{
  "type": "Feature",
  "properties": {
    "iso:country":"US",
    "sg:address":"740 Upper State Rd",
    "sg:city":"North Wales",
    "sg:classifiers":[
        {
            "category":"Restaurant",
            "type":"Food & Drink"
        }
    ],
    "sg:menulink":"http://www.allmenus.com/pa/montgomery/107110-soup-man/menu/",
    "sg:phone":"+1 215 353 4153",
    "sg:postcode":"19454",
    "sg:province":"PA",
    "sg:tags":[
        "soup",
        "american",
        "salad"
    ],
    "wof:name":"Soup Man",
    "wof:placetype":"venue"
},
  "geometry": {"coordinates":[-75.23700599999999,40.238141],"type":"Point"}
}