{
  "type": "Feature",
  "properties": {
    "iso:country":"US",
    "sg:address":"102 Cooper Rd",
    "sg:city":"Harrisville",
    "sg:classifiers":[
        {
            "category":"Professional",
            "subcategory":"Business Services",
            "type":"Services"
        }
    ],
    "sg:phone":"+1 724 735 2863",
    "sg:postcode":"16057",
    "sg:province":"PA",
    "sg:tags":[
        "notary"
    ],
    "wof:name":"Sondra A Buchanan Notary Pub",
    "wof:placetype":"venue"
},
  "geometry": {"coordinates":[-80.134001,40.988408],"type":"Point"}
}