{
  "type": "Feature",
  "properties": {
    "iso:country":"US",
    "sg:address":"7813 Kiwanis Rd",
    "sg:city":"Harrisburg",
    "sg:classifiers":[
        {
            "category":"Building & Trades",
            "subcategory":"Landscaping Services",
            "type":"Services"
        }
    ],
    "sg:phone":"+1 717 943 7124",
    "sg:postcode":"17112",
    "sg:province":"PA",
    "sg:tags":[
        "lawn"
    ],
    "wof:name":"Full Draw Landscape Design Ser",
    "wof:placetype":"venue"
},
  "geometry": {"coordinates":[-76.731458,40.360242],"type":"Point"}
}