{
  "type": "Feature",
  "properties": {
    "iso:country":"US",
    "sg:address":"241 E Market St",
    "sg:city":"Hellam",
    "sg:classifiers":[
        {
            "category":"Professional",
            "subcategory":"Business Services",
            "type":"Services"
        }
    ],
    "sg:phone":"+1 717 755 6105",
    "sg:postcode":"17406",
    "sg:province":"PA",
    "sg:tags":[
        "auctioneer"
    ],
    "wof:name":"Frederick Toomey",
    "wof:placetype":"venue"
},
  "geometry": {"coordinates":[-76.599884,40.00693],"type":"Point"}
}