{
  "type": "Feature",
  "properties": {
    "addr:full":"3939 Butler St Pittsburgh PA 15201",
    "addr:housenumber":"3939",
    "addr:postcode":"15201",
    "addr:street":"Butler St",
    "iso:country":"US",
    "sg:address":"3939 Butler St",
    "sg:city":"Pittsburgh",
    "sg:classifiers":[
        {
            "category":"Shopping",
            "subcategory":"Pharmacy",
            "type":"Retail Goods"
        }
    ],
    "sg:phone":"+1 412 682 6970",
    "sg:postcode":"15201",
    "sg:province":"PA",
    "sg:tags":[
        "aid",
        "supply",
        "store",
        "drug",
        "first"
    ],
    "sg:website":"http://www.riteaid.com",
    "wof:name":"Rite Aid",
    "wof:placetype":"venue"
},
  "geometry": {"coordinates":[-79.962733,40.468312],"type":"Point"}
}