{
  "type": "Feature",
  "properties": {
    "iso:country":"US",
    "sg:address":"2012 Centre Ave",
    "sg:city":"Pittsburgh",
    "sg:classifiers":[
        {
            "category":"Organizations",
            "subcategory":"Non-profit Organization",
            "type":"Services"
        }
    ],
    "sg:phone":"+1 412 281 5080",
    "sg:postcode":"15219",
    "sg:province":"PA",
    "sg:tags":[
        "information",
        "alcoholism",
        "treatment"
    ],
    "wof:name":"House Of Crossroads",
    "wof:placetype":"venue"
},
  "geometry": {"coordinates":[-79.97962,40.443948],"type":"Point"}
}