{
  "type": "Feature",
  "properties": {
    "iso:country":"US",
    "sg:address":"720 Atlantic Ave",
    "sg:city":"Franklin",
    "sg:classifiers":[
        {
            "category":"Wholesale",
            "subcategory":"Vending Machines",
            "type":"Manufacturing & Wholesale Goods"
        }
    ],
    "sg:phone":"+1 814 432 3328",
    "sg:postcode":"16323",
    "sg:province":"PA",
    "sg:tags":[
        "operator"
    ],
    "wof:name":"Fort Venango Vending Ltd",
    "wof:placetype":"venue"
},
  "geometry": {"coordinates":[-79.850995,41.401728],"type":"Point"}
}