{
  "type": "Feature",
  "properties": {
    "addr:full":"2741 Warm Springs Ave Huntingdon PA 16652",
    "addr:housenumber":"2741",
    "addr:postcode":"16652",
    "addr:street":"Warm Springs Ave",
    "iso:country":"US",
    "sg:address":"2741 Warm Springs Ave",
    "sg:city":"Huntingdon",
    "sg:classifiers":[
        {
            "category":"Building & Trades",
            "subcategory":"Plumbing",
            "type":"Services"
        }
    ],
    "sg:phone":"+1 814 643 0977",
    "sg:postcode":"16652",
    "sg:province":"PA",
    "sg:tags":[
        "plumbing",
        "contractor"
    ],
    "wof:name":"Hess Plumbing & Heating",
    "wof:placetype":"venue"
},
  "geometry": {"coordinates":[-78.00609,40.50918],"type":"Point"}
}