{
  "type": "Feature",
  "properties": {
    "iso:country":"US",
    "sg:address":"1920 Quarry Rd",
    "sg:city":"Lebanon",
    "sg:classifiers":[
        {
            "category":"Building & Trades",
            "subcategory":"Construction",
            "type":"Services"
        }
    ],
    "sg:phone":"+1 717 865 3395",
    "sg:postcode":"17046",
    "sg:province":"PA",
    "sg:tags":[
        "industrial",
        "contractors-commercial",
        "contractor"
    ],
    "wof:name":"Shepherd's Fold Work Project",
    "wof:placetype":"venue"
},
  "geometry": {"coordinates":[-76.451643,40.392196],"type":"Point"}
}