{
  "type": "Feature",
  "properties": {
    "iso:country":"US",
    "sg:address":"826 Newtown Yardley Rd",
    "sg:city":"Newtown",
    "sg:classifiers":[
        {
            "category":"Professional",
            "subcategory":"Accounting & Tax Preparation",
            "type":"Services"
        }
    ],
    "sg:phone":"+1   ",
    "sg:postcode":"18940",
    "sg:province":"PA",
    "wof:name":"Barbagallo Joseph S CPA",
    "wof:placetype":"venue"
},
  "geometry": {"coordinates":[-74.907287,40.231153],"type":"Point"}
}