{
  "type": "Feature",
  "properties": {
    "iso:country":"US",
    "sg:address":"910 Market St",
    "sg:city":"Lewisburg",
    "sg:classifiers":[
        {
            "category":"Shopping",
            "type":"Retail Goods"
        },
        {
            "category":"Food & Beverages",
            "subcategory":"Liquor & Beverages",
            "type":"Retail Goods"
        }
    ],
    "sg:phone":"+1 570 523 7870",
    "sg:postcode":"17837",
    "sg:province":"PA",
    "sg:tags":[
        "beer",
        "ale",
        "merchandise"
    ],
    "wof:name":"Bison Beverage Inc",
    "wof:placetype":"venue"
},
  "geometry": {"coordinates":[-76.892258,40.9603],"type":"Point"}
}