{
  "type": "Feature",
  "properties": {
    "addr:full":"192 Circle Rd Scenery Hill PA 15360",
    "addr:housenumber":"192",
    "addr:postcode":"15360",
    "addr:street":"Circle Rd",
    "iso:country":"US",
    "sg:address":"192 Circle Rd",
    "sg:city":"Scenery Hill",
    "sg:classifiers":[
        {
            "category":"Farming",
            "subcategory":"Livestock Farm",
            "type":"Manufacturing & Wholesale Goods"
        }
    ],
    "sg:phone":"+1   ",
    "sg:postcode":"15360",
    "sg:province":"PA",
    "sg:tags":[
        "beef",
        "feedlot",
        "cattle"
    ],
    "wof:name":"Ralph Buckingham",
    "wof:placetype":"venue"
},
  "geometry": {"coordinates":[-80.043368,40.09035],"type":"Point"}
}