{
  "type": "Feature",
  "properties": {
    "iso:country":"US",
    "sg:address":"948 Whitner Rd",
    "sg:city":"Reading",
    "sg:classifiers":[
        {
            "category":"Building & Trades",
            "subcategory":"Plumbing",
            "type":"Services"
        }
    ],
    "sg:phone":"+1 610 929 9243",
    "sg:postcode":"19605",
    "sg:province":"PA",
    "sg:tags":[
        "contractor"
    ],
    "wof:name":"Robert H Hunsberger",
    "wof:placetype":"venue"
},
  "geometry": {"coordinates":[-75.957669,40.393558],"type":"Point"}
}