{
  "type": "Feature",
  "properties": {
    "addr:full":"1442 Power Plant Rd New Florence PA 15944",
    "addr:housenumber":"1442",
    "addr:postcode":"15944",
    "addr:street":"Power Plant Rd",
    "iso:country":"US",
    "sg:address":"1442 Power Plant Rd",
    "sg:city":"New Florence",
    "sg:classifiers":[
        {
            "category":"Utilities",
            "subcategory":"Electric",
            "type":"Services"
        }
    ],
    "sg:phone":"+1   ",
    "sg:postcode":"15944",
    "sg:province":"PA",
    "sg:tags":[
        "gas"
    ],
    "wof:name":"Conemaugh Power Plant",
    "wof:placetype":"venue"
},
  "geometry": {"coordinates":[-79.061486,40.388252],"type":"Point"}
}