{
  "type": "Feature",
  "properties": {
    "addr:full":"1701 Delancey Street Philadelphia PA 19103",
    "addr:housenumber":"1701",
    "addr:postcode":"19103",
    "addr:street":"Delancey Street",
    "iso:country":"US",
    "sg:address":"1701 Delancey Street",
    "sg:city":"Philadelphia",
    "sg:classifiers":[
        {
            "category":"Place Of Worship",
            "subcategory":"Church",
            "type":"Public Place"
        }
    ],
    "sg:phone":"+1 215 735 7688",
    "sg:postcode":"19103",
    "sg:province":"PA",
    "sg:website":"www.tenth.org",
    "wof:name":"Tenth Presbyterian Church Pca",
    "wof:placetype":"venue"
},
  "geometry": {"coordinates":[-75.169887,39.947541],"type":"Point"}
}