{
  "type": "Feature",
  "properties": {
    "iso:country":"US",
    "sg:address":"411 Doylestown Rd",
    "sg:city":"Montgomeryville",
    "sg:classifiers":[
        {
            "category":"Restaurant",
            "type":"Food & Drink"
        }
    ],
    "sg:menulink":"http://www.allmenus.com/pa/montgomery/97729-outback-steakhouse/menu/",
    "sg:phone":"+1 215 855 1060",
    "sg:postcode":"18936",
    "sg:province":"PA",
    "sg:tags":[
        "american",
        "steakhouse"
    ],
    "wof:name":"Outback Steakhouse",
    "wof:placetype":"venue"
},
  "geometry": {"coordinates":[-75.241164,40.249068],"type":"Point"}
}