{
  "type": "Feature",
  "properties": {
    "iso:country":"US",
    "sg:address":"3519 N 22nd St",
    "sg:city":"Philadelphia",
    "sg:classifiers":[
        {
            "category":"Organizations",
            "subcategory":"Professional Association",
            "type":"Services"
        }
    ],
    "sg:phone":"+1 215 227 9350",
    "sg:postcode":"19140",
    "sg:province":"PA",
    "wof:name":"Nehemiah Community Redevelop",
    "wof:placetype":"venue"
},
  "geometry": {"coordinates":[-75.164897,40.007844],"type":"Point"}
}