{
  "type": "Feature",
  "properties": {
    "iso:country":"US",
    "sg:address":"3 Mill Rd",
    "sg:city":"Sellersville",
    "sg:classifiers":[
        {
            "category":"Manufacturing",
            "subcategory":"Apparel",
            "type":"Manufacturing & Wholesale Goods"
        }
    ],
    "sg:phone":"+1   ",
    "sg:postcode":"18960",
    "sg:province":"PA",
    "wof:name":"Embroidery Depot",
    "wof:placetype":"venue"
},
  "geometry": {"coordinates":[-75.31249200000001,40.377098],"type":"Point"}
}