{
  "type": "Feature",
  "properties": {
    "addr:full":"2124 Stefko Blvd Bethlehem PA 18017",
    "addr:housenumber":"2124",
    "addr:postcode":"18017",
    "addr:street":"Stefko Blvd",
    "iso:country":"US",
    "sg:address":"2124 Stefko Blvd",
    "sg:city":"Bethlehem",
    "sg:classifiers":[
        {
            "category":"Building & Trades",
            "subcategory":"Construction",
            "type":"Services"
        }
    ],
    "sg:phone":"+1 610 866 9500",
    "sg:postcode":"18017",
    "sg:province":"PA",
    "sg:tags":[
        "window",
        "installation",
        "contractor"
    ],
    "wof:name":"Bethlehem Windows",
    "wof:placetype":"venue"
},
  "geometry": {"coordinates":[-75.34599900000001,40.642738],"type":"Point"}
}