{
  "type": "Feature",
  "properties": {
    "iso:country":"US",
    "sg:address":"3604 Greensburg Pike",
    "sg:city":"Pittsburgh",
    "sg:classifiers":[
        {
            "category":"Retail",
            "subcategory":"Funeral Services",
            "type":"Services"
        }
    ],
    "sg:phone":"+1 412 731 5001",
    "sg:postcode":"15221",
    "sg:province":"PA",
    "wof:name":"Wolfe Memorial Inc",
    "wof:placetype":"venue"
},
  "geometry": {"coordinates":[-79.848538,40.433602],"type":"Point"}
}