{
  "type": "Feature",
  "properties": {
    "iso:country":"US",
    "sg:address":"600 W Chester Rd",
    "sg:city":"West Chester",
    "sg:classifiers":[
        {
            "category":"Professional",
            "subcategory":"Accounting & Tax Preparation",
            "type":"Services"
        }
    ],
    "sg:phone":"+1   ",
    "sg:postcode":"19382",
    "sg:province":"PA",
    "sg:tags":[
        "medical",
        "management",
        "billing"
    ],
    "wof:name":"Perioperative Services LLC",
    "wof:placetype":"venue"
},
  "geometry": {"coordinates":[-75.54539,39.910821],"type":"Point"}
}