{
  "type": "Feature",
  "properties": {
    "iso:country":"US",
    "sg:address":"399 US Hwy 30",
    "sg:city":"Malvern",
    "sg:classifiers":[
        {
            "category":"Wholesale",
            "subcategory":"Office Equipment",
            "type":"Manufacturing & Wholesale Goods"
        }
    ],
    "sg:phone":"+1   ",
    "sg:postcode":"19355",
    "sg:province":"PA",
    "wof:name":"IKON Office Solutions",
    "wof:placetype":"venue"
},
  "geometry": {"coordinates":[-75.552948,40.038531],"type":"Point"}
}