{
  "type": "Feature",
  "properties": {
    "iso:country":"US",
    "sg:address":"227 W Broad St",
    "sg:city":"Bethlehem",
    "sg:classifiers":[
        {
            "category":"Insurance",
            "subcategory":"Hazard Insurance",
            "type":"Services"
        },
        {
            "category":"Professional",
            "subcategory":"Management & Consulting",
            "type":"Services"
        }
    ],
    "sg:phone":"+1 610 691 8091",
    "sg:postcode":"18018",
    "sg:province":"PA",
    "sg:tags":[
        "profit",
        "sharing",
        "pension",
        "business",
        "plan"
    ],
    "wof:name":"Compensation Compliance Concep",
    "wof:placetype":"venue"
},
  "geometry": {"coordinates":[-75.38545499999999,40.622408],"type":"Point"}
}