{
  "type": "Feature",
  "properties": {
    "iso:country":"US",
    "sg:address":"3017 Union Ave",
    "sg:city":"Altoona",
    "sg:classifiers":[
        {
            "category":"Organizations",
            "subcategory":"Religious Organization",
            "type":"Services"
        }
    ],
    "sg:phone":"+1 814 942 2131",
    "sg:postcode":"16602",
    "sg:province":"PA",
    "sg:tags":[
        "church"
    ],
    "sg:website":"www.altoonabible.org",
    "wof:name":"Altoona Bible Church Pre Schl",
    "wof:placetype":"venue"
},
  "geometry": {"coordinates":[-78.40621299999999,40.49301],"type":"Point"}
}