{
  "type": "Feature",
  "properties": {
    "iso:country":"US",
    "sg:address":"215 Morrison Dr",
    "sg:city":"Pittsburgh",
    "sg:classifiers":[
        {
            "category":"Professional",
            "subcategory":"Lawyer & Legal Services",
            "type":"Services"
        }
    ],
    "sg:phone":"+1 412 561 4721",
    "sg:postcode":"15216",
    "sg:province":"PA",
    "wof:name":"Stang William L",
    "wof:placetype":"venue"
},
  "geometry": {"coordinates":[-80.048498,40.393816],"type":"Point"}
}