{
  "type": "Feature",
  "properties": {
    "iso:country":"US",
    "sg:address":"720 Providence Rd",
    "sg:city":"Malvern",
    "sg:classifiers":[
        {
            "category":"Professional",
            "subcategory":"Research",
            "type":"Services"
        }
    ],
    "sg:phone":"+1 610 644 2212",
    "sg:postcode":"19355",
    "sg:province":"PA",
    "wof:name":"Insurance Research Council",
    "wof:placetype":"venue"
},
  "geometry": {"coordinates":[-75.500117,39.998894],"type":"Point"}
}