{
  "type": "Feature",
  "properties": {
    "addr:full":"6301 Chelton Ave Harrisburg PA 17112",
    "addr:housenumber":"6301",
    "addr:postcode":"17112",
    "addr:street":"Chelton Ave",
    "iso:country":"US",
    "sg:address":"6301 Chelton Ave",
    "sg:city":"Harrisburg",
    "sg:classifiers":[
        {
            "category":"Manufacturing",
            "subcategory":"Tools & Machinery",
            "type":"Manufacturing & Wholesale Goods"
        }
    ],
    "sg:phone":"+1 717 540 6868",
    "sg:postcode":"17112",
    "sg:province":"PA",
    "sg:tags":[
        "chemical",
        "chem",
        "sprayer",
        "mfg"
    ],
    "wof:name":"Abrasive Systems",
    "wof:placetype":"venue"
},
  "geometry": {"coordinates":[-76.778308,40.330076],"type":"Point"}
}