{
  "type": "Feature",
  "properties": {
    "addr:full":"1 Evergreen Ave Broomall PA 19008",
    "addr:housenumber":"1",
    "addr:postcode":"19008",
    "addr:street":"Evergreen Ave",
    "iso:country":"US",
    "sg:address":"1 Evergreen Ave",
    "sg:city":"Broomall",
    "sg:classifiers":[
        {
            "category":"Government",
            "subcategory":"Fire Station",
            "type":"Public Place"
        }
    ],
    "sg:phone":"+1 610 566 5891",
    "sg:postcode":"19008",
    "sg:province":"PA",
    "sg:tags":[
        "department"
    ],
    "wof:name":"Rose Tree Fire Co",
    "wof:placetype":"venue"
},
  "geometry": {"coordinates":[-75.379519,39.981688],"type":"Point"}
}