{
  "type": "Feature",
  "properties": {
    "iso:country":"US",
    "sg:address":"209 Gay St",
    "sg:city":"Phoenixville",
    "sg:classifiers":[
        {
            "category":"Health Services",
            "subcategory":"Doctor",
            "type":"Services"
        }
    ],
    "sg:phone":"+1   ",
    "sg:postcode":"19460",
    "sg:province":"PA",
    "sg:tags":[
        "osteopathic"
    ],
    "wof:name":"David H Solis Do",
    "wof:placetype":"venue"
},
  "geometry": {"coordinates":[-75.517425,40.129079],"type":"Point"}
}