{
  "type": "Feature",
  "properties": {
    "iso:country":"US",
    "sg:address":"216 N 9th St",
    "sg:city":"Allentown",
    "sg:classifiers":[
        {
            "category":"Personal",
            "subcategory":"Beauty Salon",
            "type":"Services"
        }
    ],
    "sg:phone":"+1   ",
    "sg:postcode":"18102",
    "sg:province":"PA",
    "sg:tags":[
        "shop"
    ],
    "wof:name":"From Head To Toe",
    "wof:placetype":"venue"
},
  "geometry": {"coordinates":[-75.477464,40.605405],"type":"Point"}
}