{
  "type": "Feature",
  "properties": {
    "addr:full":"400 Greentree Rd Pittsburgh PA 15220",
    "addr:housenumber":"400",
    "addr:postcode":"15220",
    "addr:street":"Greentree Rd",
    "iso:country":"US",
    "sg:address":"400 Greentree Rd",
    "sg:city":"Pittsburgh",
    "sg:classifiers":[
        {
            "category":"Home & Garden",
            "subcategory":"Building Materials",
            "type":"Retail Goods"
        }
    ],
    "sg:phone":"+1 412 921 3737",
    "sg:postcode":"15220",
    "sg:province":"PA",
    "sg:tags":[
        "paint"
    ],
    "wof:name":"PADCO Decorating Ctr",
    "wof:placetype":"venue"
},
  "geometry": {"coordinates":[-80.033878,40.435376],"type":"Point"}
}