{
  "type": "Feature",
  "properties": {
    "addr:full":"31 Clearfield Ave Norristown PA 19403",
    "addr:housenumber":"31",
    "addr:postcode":"19403",
    "addr:street":"Clearfield Ave",
    "iso:country":"US",
    "sg:address":"31 Clearfield Ave",
    "sg:city":"Norristown",
    "sg:classifiers":[
        {
            "category":"Building & Trades",
            "subcategory":"Construction",
            "type":"Services"
        },
        {
            "category":"Building & Trades",
            "subcategory":"Electrical",
            "type":"Services"
        }
    ],
    "sg:phone":"+1 610 631 6311",
    "sg:postcode":"19403",
    "sg:province":"PA",
    "sg:tags":[
        "contractor"
    ],
    "wof:name":"Brennan Renovations Inc",
    "wof:placetype":"venue"
},
  "geometry": {"coordinates":[-75.394203,40.141499],"type":"Point"}
}