{
  "type": "Feature",
  "properties": {
    "iso:country":"US",
    "sg:address":"1800 Lincoln Hwy E",
    "sg:city":"Lancaster",
    "sg:classifiers":[
        {
            "category":"Organizations",
            "subcategory":"Religious Organization",
            "type":"Services"
        }
    ],
    "sg:phone":"+1 717 295 4512",
    "sg:postcode":"17602",
    "sg:province":"PA",
    "sg:tags":[
        "church"
    ],
    "wof:name":"Souls For The Kingdom",
    "wof:placetype":"venue"
},
  "geometry": {"coordinates":[-76.255692,40.035675],"type":"Point"}
}