{
  "type": "Feature",
  "properties": {
    "iso:country":"US",
    "sg:address":"705 5th Ave",
    "sg:city":"Coraopolis",
    "sg:classifiers":[
        {
            "category":"Manufacturing",
            "subcategory":"Printing",
            "type":"Manufacturing & Wholesale Goods"
        }
    ],
    "sg:phone":"+1   ",
    "sg:postcode":"15108",
    "sg:province":"PA",
    "sg:tags":[
        "newspaper"
    ],
    "wof:name":"Gateway Publications",
    "wof:placetype":"venue"
},
  "geometry": {"coordinates":[-80.17033499999999,40.519903],"type":"Point"}
}