{
  "type": "Feature",
  "properties": {
    "addr:full":"3 Charles Ave Stewartstown PA 17363",
    "addr:housenumber":"3",
    "addr:postcode":"17363",
    "addr:street":"Charles Ave",
    "iso:country":"US",
    "sg:address":"3 Charles Ave",
    "sg:city":"Stewartstown",
    "sg:classifiers":[
        {
            "category":"Food & Beverages",
            "subcategory":"Groceries & Convenience Stores",
            "type":"Retail Goods"
        }
    ],
    "sg:phone":"+1 717 993 6654",
    "sg:postcode":"17363",
    "sg:province":"PA",
    "wof:name":"Rutter's Farm Store",
    "wof:placetype":"venue"
},
  "geometry": {"coordinates":[-76.59120900000001,39.761213],"type":"Point"}
}