{
  "type": "Feature",
  "properties": {
    "addr:full":"3012 Cape Cod Dr Media PA 19063",
    "addr:housenumber":"3012",
    "addr:postcode":"19063",
    "addr:street":"Cape Cod Dr",
    "iso:country":"US",
    "sg:address":"3012 Cape Cod Dr",
    "sg:city":"Media",
    "sg:classifiers":[
        {
            "category":"Real Estate",
            "subcategory":"Real Estate Agent",
            "type":"Services"
        }
    ],
    "sg:phone":"+1   ",
    "sg:postcode":"19063",
    "sg:province":"PA",
    "wof:name":"Joseph A ODonnell",
    "wof:placetype":"venue"
},
  "geometry": {"coordinates":[-75.423806,39.952333],"type":"Point"}
}