{
  "type": "Feature",
  "properties": {
    "addr:full":"903 Union St Millersburg PA 17061",
    "addr:housenumber":"903",
    "addr:postcode":"17061",
    "addr:street":"Union St",
    "iso:country":"US",
    "sg:address":"903 Union St",
    "sg:city":"Millersburg",
    "sg:classifiers":[
        {
            "category":"Retail",
            "subcategory":"Auto Rental",
            "type":"Services"
        }
    ],
    "sg:phone":"+1   ",
    "sg:postcode":"17061",
    "sg:province":"PA",
    "sg:tags":[
        "passenger",
        "car"
    ],
    "wof:name":"Eugene F Schaffer Renta",
    "wof:placetype":"venue"
},
  "geometry": {"coordinates":[-76.945638,40.540536],"type":"Point"}
}