{
  "type": "Feature",
  "properties": {
    "addr:full":"1423 S Broad St Philadelphia PA 19147",
    "addr:housenumber":"1423",
    "addr:postcode":"19147",
    "addr:street":"S Broad St",
    "iso:country":"US",
    "sg:address":"1423 S Broad St",
    "sg:city":"Philadelphia",
    "sg:classifiers":[
        {
            "category":"Wholesale",
            "subcategory":"Non-durable Goods",
            "type":"Manufacturing & Wholesale Goods"
        }
    ],
    "sg:phone":"+1   ",
    "sg:postcode":"19147",
    "sg:province":"PA",
    "wof:name":"Patco Distributors Inc",
    "wof:placetype":"venue"
},
  "geometry": {"coordinates":[-75.167928,39.93197],"type":"Point"}
}