{
  "type": "Feature",
  "properties": {
    "iso:country":"US",
    "sg:address":"1710 Greengarden Rd",
    "sg:city":"Erie",
    "sg:classifiers":[
        {
            "category":"Professional",
            "subcategory":"Business Services",
            "type":"Services"
        }
    ],
    "sg:phone":"+1   ",
    "sg:postcode":"16502",
    "sg:province":"PA",
    "wof:name":"Quest Tru TEC LP",
    "wof:placetype":"venue"
},
  "geometry": {"coordinates":[-80.11289499999999,42.105801],"type":"Point"}
}