{
  "type": "Feature",
  "properties": {
    "addr:full":"368 Broad St Waverly PA 14892",
    "addr:housenumber":"368",
    "addr:postcode":"14892",
    "addr:street":"Broad St",
    "iso:country":"US",
    "sg:address":"368 Broad St",
    "sg:city":"Waverly",
    "sg:classifiers":[
        {
            "category":"Shopping",
            "type":"Retail Goods"
        }
    ],
    "sg:phone":"+1 607 565 6669",
    "sg:postcode":"14892",
    "sg:province":"PA",
    "sg:tags":[
        "coin",
        "dealer",
        "supply"
    ],
    "wof:name":"Broad Street Exchange",
    "wof:placetype":"venue"
},
  "geometry": {"coordinates":[-76.53842899999999,42.001045],"type":"Point"}
}