{
  "type": "Feature",
  "properties": {
    "addr:full":"4 S Front St Steelton PA 17113",
    "addr:housenumber":"4",
    "addr:postcode":"17113",
    "addr:street":"S Front St",
    "iso:country":"US",
    "sg:address":"4 S Front St",
    "sg:city":"Steelton",
    "sg:classifiers":[
        {
            "category":"Personal",
            "subcategory":"Tattoo Parlor",
            "type":"Services"
        },
        {
            "category":"Personal",
            "subcategory":"Piercing",
            "type":"Services"
        }
    ],
    "sg:phone":"+1 717 939 2222",
    "sg:postcode":"17113",
    "sg:province":"PA",
    "sg:website":"www.rayzortattoos.com",
    "wof:name":"Rayzor Tattoos",
    "wof:placetype":"venue"
},
  "geometry": {"coordinates":[-76.840042,40.234503],"type":"Point"}
}