{
  "type": "Feature",
  "properties": {
    "iso:country":"US",
    "sg:address":"582 Middletown Blvd B10",
    "sg:city":"Langhorne",
    "sg:classifiers":[
        {
            "category":"Health Services",
            "subcategory":"Medical Lab",
            "type":"Services"
        }
    ],
    "sg:phone":"+1 215 702 8911",
    "sg:postcode":"19047",
    "sg:province":"PA",
    "sg:tags":[
        "examination",
        "insurance"
    ],
    "wof:name":"Radiologix Inc",
    "wof:placetype":"venue"
},
  "geometry": {"coordinates":[-74.876091,40.182919],"type":"Point"}
}