{
  "type": "Feature",
  "properties": {
    "iso:country":"US",
    "sg:address":"67 Woodlawn St",
    "sg:city":"Pittsburgh",
    "sg:classifiers":[
        {
            "category":"Home & Garden",
            "subcategory":"Building Materials",
            "type":"Retail Goods"
        }
    ],
    "sg:phone":"+1 412 921 7815",
    "sg:postcode":"15205",
    "sg:province":"PA",
    "sg:tags":[
        "glass",
        "leaded"
    ],
    "wof:name":"Creative Glassworks",
    "wof:placetype":"venue"
},
  "geometry": {"coordinates":[-80.075115,40.427939],"type":"Point"}
}