{
  "type": "Feature",
  "properties": {
    "addr:full":"1245 Harney Rd Littlestown PA 17340",
    "addr:housenumber":"1245",
    "addr:postcode":"17340",
    "addr:street":"Harney Rd",
    "iso:country":"US",
    "sg:address":"1245 Harney Rd",
    "sg:city":"Littlestown",
    "sg:classifiers":[
        {
            "category":"Autos & Motor Vehicles",
            "subcategory":"Automobile Sales",
            "type":"Retail Goods"
        }
    ],
    "sg:phone":"+1   ",
    "sg:postcode":"17340",
    "sg:province":"PA",
    "wof:name":"Topper Motors",
    "wof:placetype":"venue"
},
  "geometry": {"coordinates":[-77.159057,39.731266],"type":"Point"}
}