{
  "type": "Feature",
  "properties": {
    "iso:country":"US",
    "sg:address":"463 E Lancaster Ave",
    "sg:city":"Downingtown",
    "sg:classifiers":[
        {
            "category":"Shopping",
            "subcategory":"Used Merchandise",
            "type":"Retail Goods"
        }
    ],
    "sg:phone":"+1 610 269 4040",
    "sg:postcode":"19335",
    "sg:province":"PA",
    "sg:tags":[
        "antique"
    ],
    "sg:website":"www.pookandpook.com",
    "wof:name":"Pook & Pook Inc",
    "wof:placetype":"venue"
},
  "geometry": {"coordinates":[-75.69545599999999,40.011473],"type":"Point"}
}