{
  "type": "Feature",
  "properties": {
    "iso:country":"US",
    "sg:address":"3901 Market St",
    "sg:city":"Philadelphia",
    "sg:classifiers":[
        {
            "category":"Social Services",
            "subcategory":"Child Care",
            "type":"Services"
        }
    ],
    "sg:phone":"+1 215 382 1846",
    "sg:postcode":"19104",
    "sg:province":"PA",
    "wof:name":"Phila Child Care Resources",
    "wof:placetype":"venue"
},
  "geometry": {"coordinates":[-75.201953,39.957149],"type":"Point"}
}