{
  "type": "Feature",
  "properties": {
    "addr:full":"1199 Old Jordan Rd Southampton PA 18966",
    "addr:housenumber":"1199",
    "addr:postcode":"18966",
    "addr:street":"Old Jordan Rd",
    "iso:country":"US",
    "sg:address":"1199 Old Jordan Rd",
    "sg:city":"Southampton",
    "sg:classifiers":[
        {
            "category":"Professional",
            "subcategory":"Management & Consulting",
            "type":"Services"
        }
    ],
    "sg:phone":"+1   ",
    "sg:postcode":"18966",
    "sg:province":"PA",
    "sg:tags":[
        "business"
    ],
    "wof:name":"Beymar Inc",
    "wof:placetype":"venue"
},
  "geometry": {"coordinates":[-74.967938,40.198411],"type":"Point"}
}