{
  "type": "Feature",
  "properties": {
    "iso:country":"US",
    "sg:address":"1729 Rostraver Rd",
    "sg:city":"Belle Vernon",
    "sg:classifiers":[
        {
            "category":"Food & Beverages",
            "subcategory":"Groceries & Convenience Stores",
            "type":"Retail Goods"
        },
        {
            "category":"Professional",
            "type":"Services"
        }
    ],
    "sg:phone":"+1 724 929 2009",
    "sg:postcode":"15012",
    "sg:province":"PA",
    "sg:tags":[
        "grocer"
    ],
    "wof:name":"More For Less Foods",
    "wof:placetype":"venue"
},
  "geometry": {"coordinates":[-79.80581599999999,40.176604],"type":"Point"}
}