{
  "type": "Feature",
  "properties": {
    "iso:country":"US",
    "sg:address":"214 S Front St",
    "sg:city":"Wormleysburg",
    "sg:classifiers":[
        {
            "category":"Professional",
            "subcategory":"Management & Consulting",
            "type":"Services"
        }
    ],
    "sg:phone":"+1 717 763 9843",
    "sg:postcode":"17043",
    "sg:province":"PA",
    "sg:tags":[
        "construction"
    ],
    "wof:name":"2CM Inc",
    "wof:placetype":"venue"
},
  "geometry": {"coordinates":[-76.894567,40.252117],"type":"Point"}
}