{
  "type": "Feature",
  "properties": {
    "iso:country":"US",
    "sg:address":"282 Longstreet Dr",
    "sg:city":"Gettysburg",
    "sg:classifiers":[
        {
            "category":"Professional",
            "subcategory":"Testing Lab",
            "type":"Services"
        }
    ],
    "sg:phone":"+1   ",
    "sg:postcode":"17325",
    "sg:province":"PA",
    "sg:tags":[
        "laboratory"
    ],
    "wof:name":"Radon Protection Services",
    "wof:placetype":"venue"
},
  "geometry": {"coordinates":[-77.18905599999999,39.816574],"type":"Point"}
}