{
  "type": "Feature",
  "properties": {
    "iso:country":"US",
    "sg:address":"7 William St",
    "sg:city":"Pittston",
    "sg:classifiers":[
        {
            "category":"Shopping",
            "subcategory":"Florist",
            "type":"Retail Goods"
        }
    ],
    "sg:phone":"+1 570 654 7041",
    "sg:postcode":"18640",
    "sg:province":"PA",
    "wof:name":"Pittston Florist",
    "wof:placetype":"venue"
},
  "geometry": {"coordinates":[-75.789654,41.323242],"type":"Point"}
}