{
  "type": "Feature",
  "properties": {
    "iso:country":"US",
    "sg:address":"46 Hillcrest Ave",
    "sg:city":"Leola",
    "sg:classifiers":[
        {
            "category":"Education",
            "subcategory":"Library",
            "type":"Public Place"
        },
        {
            "category":"Government",
            "subcategory":"Office",
            "type":"Public Place"
        }
    ],
    "sg:phone":"+1 717 656 7920",
    "sg:postcode":"17540",
    "sg:province":"PA",
    "sg:tags":[
        "township",
        "government-city",
        "village"
    ],
    "wof:name":"Leola Library Cntr Branch",
    "wof:placetype":"venue"
},
  "geometry": {"coordinates":[-76.186672,40.086602],"type":"Point"}
}