{
  "type": "Feature",
  "properties": {
    "iso:country":"US",
    "sg:address":"463 Brown Ave",
    "sg:city":"Turtle Creek",
    "sg:classifiers":[
        {
            "category":"Retail",
            "subcategory":"Auto Repair",
            "type":"Services"
        }
    ],
    "sg:phone":"+1 412 823 3499",
    "sg:postcode":"15145",
    "sg:province":"PA",
    "sg:tags":[
        "body",
        "automobile",
        "used"
    ],
    "wof:name":"Staub Auto Sales",
    "wof:placetype":"venue"
},
  "geometry": {"coordinates":[-79.83107200000001,40.411975],"type":"Point"}
}