{
  "type": "Feature",
  "properties": {
    "iso:country":"US",
    "sg:address":"833 Columbia Blvd",
    "sg:city":"Bloomsburg",
    "sg:classifiers":[
        {
            "category":"Food & Beverages",
            "subcategory":"Groceries & Convenience Stores",
            "type":"Retail Goods"
        }
    ],
    "sg:phone":"+1 570 387 1101",
    "sg:postcode":"17815",
    "sg:province":"PA",
    "wof:name":"C R's Friendly Markets",
    "wof:placetype":"venue"
},
  "geometry": {"coordinates":[-76.44043499999999,41.003617],"type":"Point"}
}