{
  "type": "Feature",
  "properties": {
    "iso:country":"US",
    "sg:address":"20 Abbey Rd",
    "sg:city":"Coatesville",
    "sg:classifiers":[
        {
            "category":"Real Estate",
            "subcategory":"Real Estate Operator",
            "type":"Services"
        }
    ],
    "sg:phone":"+1 610 384 4133",
    "sg:postcode":"19320",
    "sg:province":"PA",
    "sg:tags":[
        "mobile",
        "home",
        "community"
    ],
    "wof:name":"Hidden Valley Estates",
    "wof:placetype":"venue"
},
  "geometry": {"coordinates":[-75.838537,39.962695],"type":"Point"}
}