{
  "type": "Feature",
  "properties": {
    "addr:full":"52 N Lehigh Ave Frackville PA 17931",
    "addr:housenumber":"52",
    "addr:postcode":"17931",
    "addr:street":"N Lehigh Ave",
    "iso:country":"US",
    "sg:address":"52 N Lehigh Ave",
    "sg:city":"Frackville",
    "sg:classifiers":[
        {
            "category":"Organizations",
            "subcategory":"Professional Association",
            "type":"Services"
        }
    ],
    "sg:phone":"+1 570 874 4381",
    "sg:postcode":"17931",
    "sg:province":"PA",
    "wof:name":"Knights Of Columbus",
    "wof:placetype":"venue"
},
  "geometry": {"coordinates":[-76.231336,40.785843],"type":"Point"}
}