{
  "type": "Feature",
  "properties": {
    "iso:country":"US",
    "sg:address":"301 5th St",
    "sg:city":"Reading",
    "sg:classifiers":[
        {
            "category":"Organizations",
            "subcategory":"Religious Organization",
            "type":"Services"
        }
    ],
    "sg:phone":"+1 610 372 1031",
    "sg:postcode":"19601",
    "sg:province":"PA",
    "sg:tags":[
        "church"
    ],
    "wof:name":"St Matthew's Greek Orthodox",
    "wof:placetype":"venue"
},
  "geometry": {"coordinates":[-75.927702,40.341561],"type":"Point"}
}