{
  "type": "Feature",
  "properties": {
    "iso:country":"US",
    "sg:address":"1134 Strawn Ave",
    "sg:city":"New Kensington",
    "sg:classifiers":[
        {
            "category":"Professional",
            "subcategory":"Computer Services",
            "type":"Services"
        }
    ],
    "sg:phone":"+1   ",
    "sg:postcode":"15068",
    "sg:province":"PA",
    "sg:tags":[
        "datum"
    ],
    "wof:name":"Robert P Mohr",
    "wof:placetype":"venue"
},
  "geometry": {"coordinates":[-79.752156,40.563113],"type":"Point"}
}