{
  "type": "Feature",
  "properties": {
    "addr:full":"100 Garrett Rd Upper Darby PA 19082",
    "addr:housenumber":"100",
    "addr:postcode":"19082",
    "addr:street":"Garrett Rd",
    "iso:country":"US",
    "sg:address":"100 Garrett Rd",
    "sg:city":"Upper Darby",
    "sg:classifiers":[
        {
            "category":"Government",
            "subcategory":"Office",
            "type":"Public Place"
        }
    ],
    "sg:phone":"+1 610 734 7716",
    "sg:postcode":"19082",
    "sg:province":"PA",
    "sg:tags":[
        "city",
        "planning",
        "dev"
    ],
    "wof:name":"Upper Darby Twp Community Dev",
    "wof:placetype":"venue"
},
  "geometry": {"coordinates":[-75.263577,39.960076],"type":"Point"}
}