{
  "type": "Feature",
  "properties": {
    "addr:full":"925 Providence Rd Secane PA 19018",
    "addr:housenumber":"925",
    "addr:postcode":"19018",
    "addr:street":"Providence Rd",
    "iso:country":"US",
    "sg:address":"925 Providence Rd",
    "sg:city":"Secane",
    "sg:classifiers":[
        {
            "category":"Shopping",
            "subcategory":"Optical Goods",
            "type":"Retail Goods"
        }
    ],
    "sg:phone":"+1 610 622 0310",
    "sg:postcode":"19018",
    "sg:province":"PA",
    "sg:tags":[
        "optician"
    ],
    "wof:name":"Eye Care Optical Ctr",
    "wof:placetype":"venue"
},
  "geometry": {"coordinates":[-75.301463,39.918056],"type":"Point"}
}