{
  "type": "Feature",
  "properties": {
    "addr:full":"1 E Main St North East PA 16428",
    "addr:housenumber":"1",
    "addr:postcode":"16428",
    "addr:street":"E Main St North",
    "iso:country":"US",
    "sg:address":"1 E Main St",
    "sg:city":"North East",
    "sg:classifiers":[
        {
            "category":"Professional",
            "subcategory":"Accounting & Tax Preparation",
            "type":"Services"
        }
    ],
    "sg:phone":"+1 814 725 0555",
    "sg:postcode":"16428",
    "sg:province":"PA",
    "sg:tags":[
        "billing"
    ],
    "wof:name":"Physician Billing & Consulting",
    "wof:placetype":"venue"
},
  "geometry": {"coordinates":[-79.83367200000001,42.216252],"type":"Point"}
}