{
  "type": "Feature",
  "properties": {
    "iso:country":"US",
    "sg:address":"101 Scottsdale Dr",
    "sg:city":"Coraopolis",
    "sg:classifiers":[
        {
            "category":"Shopping",
            "type":"Retail Goods"
        }
    ],
    "sg:phone":"+1 724 457 9916",
    "sg:postcode":"15108",
    "sg:province":"PA",
    "sg:tags":[
        "cosmetic",
        "perfume"
    ],
    "wof:name":"Mary Kay Cosmetics",
    "wof:placetype":"venue"
},
  "geometry": {"coordinates":[-80.260283,40.540696],"type":"Point"}
}