{
  "type": "Feature",
  "properties": {
    "addr:full":"425 Main St Dupont PA 18641",
    "addr:housenumber":"425",
    "addr:postcode":"18641",
    "addr:street":"Main St",
    "iso:country":"US",
    "sg:address":"425 Main St",
    "sg:city":"Dupont",
    "sg:classifiers":[
        {
            "category":"Freight",
            "type":"Transportation"
        },
        {
            "category":"Autos & Motor Vehicles",
            "subcategory":"Automobile Sales",
            "type":"Retail Goods"
        }
    ],
    "sg:phone":"+1 570 655 6007",
    "sg:postcode":"18641",
    "sg:province":"PA",
    "sg:tags":[
        "consultant",
        "trucking"
    ],
    "wof:name":"That's Truckin Inc",
    "wof:placetype":"venue"
},
  "geometry": {"coordinates":[-75.75134,41.321462],"type":"Point"}
}