{
  "type": "Feature",
  "properties": {
    "iso:country":"US",
    "sg:address":"335 S Main St",
    "sg:city":"Shenandoah",
    "sg:classifiers":[
        {
            "category":"Professional",
            "subcategory":"Detective & Security Services",
            "type":"Services"
        },
        {
            "category":"Building & Trades",
            "subcategory":"Locksmith",
            "type":"Services"
        }
    ],
    "sg:phone":"+1 570 908 6232",
    "sg:postcode":"17976",
    "sg:province":"PA",
    "sg:tags":[
        "locksmiths-commercial",
        "industrial",
        "referral",
        "lock"
    ],
    "sg:website":"http://www.yext.com/p/superpages/jrl-emergency-services-shenandoah-pennsylvania.html",
    "wof:name":"JRL Emergency Services",
    "wof:placetype":"venue"
},
  "geometry": {"coordinates":[-76.200244,40.816912],"type":"Point"}
}