{
  "type": "Feature",
  "properties": {
    "iso:country":"US",
    "sg:address":"111 Fieldcrest Dr",
    "sg:city":"Tunkhannock",
    "sg:classifiers":[
        {
            "category":"Farming",
            "subcategory":"Livestock Farm",
            "type":"Manufacturing & Wholesale Goods"
        }
    ],
    "sg:phone":"+1   ",
    "sg:postcode":"18657",
    "sg:province":"PA",
    "sg:tags":[
        "beef",
        "feedlot",
        "cattle"
    ],
    "wof:name":"Henry Plushanski",
    "wof:placetype":"venue"
},
  "geometry": {"coordinates":[-75.95005,41.564272],"type":"Point"}
}