{
  "type": "Feature",
  "properties": {
    "iso:country":"US",
    "sg:address":"724 Dekalb Pike",
    "sg:city":"Blue Bell",
    "sg:classifiers":[
        {
            "category":"Food & Beverages",
            "subcategory":"Bakery",
            "type":"Retail Goods"
        }
    ],
    "sg:phone":"+1   ",
    "sg:postcode":"19422",
    "sg:province":"PA",
    "wof:name":"Cookie Bouquet",
    "wof:placetype":"venue"
},
  "geometry": {"coordinates":[-75.287086,40.170143],"type":"Point"}
}