{
  "type": "Feature",
  "properties": {
    "iso:country":"US",
    "sg:address":"322 Alries St",
    "sg:city":"Pittsburgh",
    "sg:classifiers":[
        {
            "category":"Professional",
            "subcategory":"Lawyer & Legal Services",
            "type":"Services"
        }
    ],
    "sg:phone":"+1 412 391 6363",
    "sg:postcode":"15210",
    "sg:province":"PA",
    "wof:name":"Catalano Louis W Atty",
    "wof:placetype":"venue"
},
  "geometry": {"coordinates":[-79.982439,40.400156],"type":"Point"}
}