{
  "type": "Feature",
  "properties": {
    "addr:full":"2601 Pennsylvania Ave. #CU4 Philadelphia PA 19130",
    "addr:housenumber":"2601",
    "addr:postcode":"19130",
    "addr:street":"Pennsylvania Ave. # Cu4",
    "iso:country":"US",
    "sg:address":"2601 Pennsylvania Ave. #CU4",
    "sg:city":"Philadelphia",
    "sg:classifiers":[
        {
            "category":"Sports & Exercise",
            "subcategory":"Gym",
            "type":"Entertainment"
        }
    ],
    "sg:phone":"+1 215 769 9663",
    "sg:postcode":"19130",
    "sg:province":"PA",
    "sg:website":"www.rowzonefairmount.com/",
    "wof:name":"RowZone",
    "wof:placetype":"venue"
},
  "geometry": {"coordinates":[-75.18087,39.968627],"type":"Point"}
}