{
  "type": "Feature",
  "properties": {
    "iso:country":"US",
    "sg:address":"103 Overdale Rd",
    "sg:city":"Pittsburgh",
    "sg:classifiers":[
        {
            "category":"Restaurant",
            "type":"Food & Drink"
        }
    ],
    "sg:phone":"+1 412 621 5547",
    "sg:postcode":"15221",
    "sg:province":"PA",
    "wof:name":"Pasta Piatto",
    "wof:placetype":"venue"
},
  "geometry": {"coordinates":[-79.86657599999999,40.430787],"type":"Point"}
}