{
  "type": "Feature",
  "properties": {
    "iso:country":"US",
    "sg:address":"8500 Essington Ave",
    "sg:city":"Philadelphia",
    "sg:classifiers":[
        {
            "category":"Restaurant",
            "type":"Food & Drink"
        }
    ],
    "sg:phone":"+1 215 365 4155",
    "sg:postcode":"19153",
    "sg:province":"PA",
    "wof:name":"Le Petite Bistro",
    "wof:placetype":"venue"
},
  "geometry": {"coordinates":[-75.229202,39.894901],"type":"Point"}
}