{
  "type": "Feature",
  "properties": {
    "iso:country":"US",
    "sg:address":"347 Koebner Cir",
    "sg:city":"State College",
    "sg:classifiers":[
        {
            "category":"Insurance",
            "subcategory":"Insurance Agent",
            "type":"Services"
        }
    ],
    "sg:phone":"+1   ",
    "sg:postcode":"16801",
    "sg:province":"PA",
    "sg:tags":[
        "consulting",
        "legal"
    ],
    "wof:name":"Economic Aprsal Frnsic Ecnmics",
    "wof:placetype":"venue"
},
  "geometry": {"coordinates":[-77.881882,40.739749],"type":"Point"}
}