{
  "type": "Feature",
  "properties": {
    "addr:full":"112 Orndorff Rd Waynesburg PA 15370",
    "addr:housenumber":"112",
    "addr:postcode":"15370",
    "addr:street":"Orndorff Rd",
    "iso:country":"US",
    "sg:address":"112 Orndorff Rd",
    "sg:city":"Waynesburg",
    "sg:classifiers":[
        {
            "category":"Retail",
            "subcategory":"Animal Services",
            "type":"Services"
        }
    ],
    "sg:phone":"+1 724 627 5809",
    "sg:postcode":"15370",
    "sg:province":"PA",
    "sg:tags":[
        "breeder",
        "horse"
    ],
    "wof:name":"Orndorff's Belgians",
    "wof:placetype":"venue"
},
  "geometry": {"coordinates":[-80.18620300000001,39.856738],"type":"Point"}
}