{
  "type": "Feature",
  "properties": {
    "addr:full":"902 Skippack Pike Blue Bell PA 19422",
    "addr:housenumber":"902",
    "addr:postcode":"19422",
    "addr:street":"Skippack Pike",
    "iso:country":"US",
    "sg:address":"902 Skippack Pike",
    "sg:city":"Blue Bell",
    "sg:classifiers":[
        {
            "category":"Organizations",
            "subcategory":"Religious Organization",
            "type":"Services"
        }
    ],
    "sg:phone":"+1 215 646 0950",
    "sg:postcode":"19422",
    "sg:province":"PA",
    "sg:tags":[
        "church"
    ],
    "wof:name":"First Church Of Christian",
    "wof:placetype":"venue"
},
  "geometry": {"coordinates":[-75.27588299999999,40.158208],"type":"Point"}
}