{
  "type": "Feature",
  "properties": {
    "iso:country":"US",
    "sg:address":"401 N Keyser Ave",
    "sg:city":"Scranton",
    "sg:classifiers":[
        {
            "category":"Home & Garden",
            "subcategory":"Carpets & Floor Coverings",
            "type":"Retail Goods"
        }
    ],
    "sg:phone":"+1 570 346 4654",
    "sg:postcode":"18504",
    "sg:province":"PA",
    "sg:tags":[
        "dealer",
        "rug"
    ],
    "wof:name":"Jerry's Comfort Flooring",
    "wof:placetype":"venue"
},
  "geometry": {"coordinates":[-75.69744799999999,41.423735],"type":"Point"}
}