{
  "type": "Feature",
  "properties": {
    "iso:country":"US",
    "sg:address":"800 Montana Ave",
    "sg:city":"Natrona Heights",
    "sg:classifiers":[
        {
            "category":"Education",
            "subcategory":"School",
            "type":"Public Place"
        }
    ],
    "sg:phone":"+1   ",
    "sg:postcode":"15065",
    "sg:province":"PA",
    "wof:name":"Blessed Sacrament School",
    "wof:placetype":"venue"
},
  "geometry": {"coordinates":[-79.72748300000001,40.620314],"type":"Point"}
}