{
  "type": "Feature",
  "properties": {
    "iso:country":"US",
    "sg:address":"806 E Hamilton St",
    "sg:city":"Allentown",
    "sg:classifiers":[
        {
            "category":"Shopping",
            "subcategory":"Bicycles & Sporting Goods",
            "type":"Retail Goods"
        }
    ],
    "sg:phone":"+1 610 820 5353",
    "sg:postcode":"18109",
    "sg:province":"PA",
    "wof:name":"Big Apple Sneakers",
    "wof:placetype":"venue"
},
  "geometry": {"coordinates":[-75.441333,40.611934],"type":"Point"}
}