{
  "type": "Feature",
  "properties": {
    "addr:full":"978 E High St Pottstown PA 19464",
    "addr:housenumber":"978",
    "addr:postcode":"19464",
    "addr:street":"E High St",
    "iso:country":"US",
    "sg:address":"978 E High St",
    "sg:city":"Pottstown",
    "sg:classifiers":[
        {
            "category":"Professional",
            "subcategory":"Advertising",
            "type":"Services"
        }
    ],
    "sg:phone":"+1 610 326 3330",
    "sg:postcode":"19464",
    "sg:province":"PA",
    "sg:tags":[
        "mailing",
        "shipping"
    ],
    "wof:name":"A Perfect Secretary",
    "wof:placetype":"venue"
},
  "geometry": {"coordinates":[-75.628139,40.244178],"type":"Point"}
}