{
  "type": "Feature",
  "properties": {
    "iso:country":"US",
    "sg:address":"3701 Haverford Ave",
    "sg:city":"Philadelphia",
    "sg:classifiers":[
        {
            "category":"Restaurant",
            "type":"Food & Drink"
        }
    ],
    "sg:phone":"+1 215 386 2344",
    "sg:postcode":"19104",
    "sg:province":"PA",
    "sg:tags":[
        "pizza"
    ],
    "wof:name":"Chris'pizza",
    "wof:placetype":"venue"
},
  "geometry": {"coordinates":[-75.196297,39.963402],"type":"Point"}
}