{
  "type": "Feature",
  "properties": {
    "addr:full":"500 S 52nd St Philadelphia PA 19143",
    "addr:housenumber":"500",
    "addr:postcode":"19143",
    "addr:street":"S 52Nd St",
    "iso:country":"US",
    "sg:address":"500 S 52nd St",
    "sg:city":"Philadelphia",
    "sg:classifiers":[
        {
            "category":"Social Services",
            "subcategory":"Child Care",
            "type":"Services"
        }
    ],
    "sg:phone":"+1   ",
    "sg:postcode":"19143",
    "sg:province":"PA",
    "sg:tags":[
        "day"
    ],
    "wof:name":"Storeys Center Group Home",
    "wof:placetype":"venue"
},
  "geometry": {"coordinates":[-75.226657,39.951468],"type":"Point"}
}