{
  "type": "Feature",
  "properties": {
    "iso:country":"US",
    "sg:address":"1400 Lee Dr",
    "sg:city":"Coraopolis",
    "sg:classifiers":[
        {
            "category":"Professional",
            "subcategory":"Lawyer & Legal Services",
            "type":"Services"
        }
    ],
    "sg:phone":"+1   ",
    "sg:postcode":"15108",
    "sg:province":"PA",
    "sg:tags":[
        "building",
        "operator",
        "apartment"
    ],
    "wof:name":"Sharon Park Manor Building",
    "wof:placetype":"venue"
},
  "geometry": {"coordinates":[-80.190066,40.525522],"type":"Point"}
}