{
  "type": "Feature",
  "properties": {
    "addr:full":"285 Scarlet Rd Kennett Square PA 19348",
    "addr:housenumber":"285",
    "addr:postcode":"19348",
    "addr:street":"Scarlet Rd",
    "iso:country":"US",
    "sg:address":"285 Scarlet Rd",
    "sg:city":"Kennett Square",
    "sg:classifiers":[
        {
            "category":"Food & Beverages",
            "subcategory":"Meat & Fish",
            "type":"Retail Goods"
        }
    ],
    "sg:phone":"+1 610 444 7628",
    "sg:postcode":"19348",
    "sg:province":"PA",
    "sg:tags":[
        "seafood"
    ],
    "wof:name":"Michael W Phillips & Co",
    "wof:placetype":"venue"
},
  "geometry": {"coordinates":[-75.681788,39.826956],"type":"Point"}
}