{
  "type": "Feature",
  "properties": {
    "addr:full":"517 Wilmington Pike Glen Mills PA 19342",
    "addr:housenumber":"517",
    "addr:postcode":"19342",
    "addr:street":"Wilmington Pike",
    "iso:country":"US",
    "sg:address":"517 Wilmington Pike",
    "sg:city":"Glen Mills",
    "sg:classifiers":[
        {
            "category":"Shopping",
            "subcategory":"Clothing, Apparel, & Fashions",
            "type":"Retail Goods"
        }
    ],
    "sg:phone":"+1 610 358 0871",
    "sg:postcode":"19342",
    "sg:province":"PA",
    "sg:tags":[
        "infant",
        "wear"
    ],
    "sg:website":"www.gap.com",
    "wof:name":"Gap Kids",
    "wof:placetype":"venue"
},
  "geometry": {"coordinates":[-75.544325,39.866889],"type":"Point"}
}