{
  "type": "Feature",
  "properties": {
    "iso:country":"US",
    "sg:address":"2020 Woodbourne Rd",
    "sg:city":"Langhorne",
    "sg:classifiers":[
        {
            "category":"Professional",
            "subcategory":"Advertising",
            "type":"Services"
        },
        {
            "category":"Manufacturing",
            "subcategory":"Signs",
            "type":"Manufacturing & Wholesale Goods"
        }
    ],
    "sg:phone":"+1 215 953 8788",
    "sg:postcode":"19047",
    "sg:province":"PA",
    "sg:tags":[
        "specialty"
    ],
    "sg:website":"http://www.kbletterin.com",
    "wof:name":"Kb Letterin'",
    "wof:placetype":"venue"
},
  "geometry": {"coordinates":[-74.907624,40.21293],"type":"Point"}
}