{
  "type": "Feature",
  "properties": {
    "addr:full":"2116 Ritchie St Aliquippa PA 15001",
    "addr:housenumber":"2116",
    "addr:postcode":"15001",
    "addr:street":"Ritchie St",
    "iso:country":"US",
    "sg:address":"2116 Ritchie St",
    "sg:city":"Aliquippa",
    "sg:classifiers":[
        {
            "category":"Retail",
            "subcategory":"Laundry & Dry Cleaning",
            "type":"Services"
        }
    ],
    "sg:phone":"+1   ",
    "sg:postcode":"15001",
    "sg:province":"PA",
    "sg:tags":[
        "drycleaning",
        "plant"
    ],
    "wof:name":"Town & Cntry Cleaners & Speed",
    "wof:placetype":"venue"
},
  "geometry": {"coordinates":[-80.28344800000001,40.61053],"type":"Point"}
}