{
  "type": "Feature",
  "properties": {
    "iso:country":"US",
    "sg:address":"1410 E Carson St",
    "sg:city":"Pittsburgh",
    "sg:classifiers":[
        {
            "category":"Personal",
            "subcategory":"Tattoo Parlor",
            "type":"Services"
        }
    ],
    "sg:phone":"+1 412 488 8287",
    "sg:postcode":"15203",
    "sg:province":"PA",
    "sg:tags":[
        "tattooing"
    ],
    "sg:website":"www.jesterscourttattoos.com",
    "wof:name":"Jester's Court Tattoos & More",
    "wof:placetype":"venue"
},
  "geometry": {"coordinates":[-79.98380299999999,40.428699],"type":"Point"}
}