{
  "type": "Feature",
  "properties": {
    "iso:country":"US",
    "sg:address":"404A N 2nd St",
    "sg:city":"Harrisburg",
    "sg:classifiers":[
        {
            "category":"Home & Garden",
            "subcategory":"Garden Supply",
            "type":"Retail Goods"
        },
        {
            "category":"Shopping",
            "subcategory":"Florist",
            "type":"Retail Goods"
        }
    ],
    "sg:phone":"+1 717 232 5401",
    "sg:postcode":"17101",
    "sg:province":"PA",
    "sg:tags":[
        "nursery",
        "gardening"
    ],
    "wof:name":"Robert's Flowers",
    "wof:placetype":"venue"
},
  "geometry": {"coordinates":[-76.886392,40.262668],"type":"Point"}
}