{
  "type": "Feature",
  "properties": {
    "iso:country":"US",
    "sg:address":"231 Fort Pitt Blvd",
    "sg:city":"Pittsburgh",
    "sg:classifiers":[
        {
            "category":"Professional",
            "subcategory":"Art Services",
            "type":"Services"
        }
    ],
    "sg:phone":"+1   ",
    "sg:postcode":"15222",
    "sg:province":"PA",
    "sg:tags":[
        "commercial",
        "design",
        "mfg"
    ],
    "wof:name":"Clydes Camera Graphics",
    "wof:placetype":"venue"
},
  "geometry": {"coordinates":[-80.003111,40.43765],"type":"Point"}
}