{
  "type": "Feature",
  "properties": {
    "addr:full":"901 Loucks Rd York PA 17404",
    "addr:housenumber":"901",
    "addr:postcode":"17404",
    "addr:street":"Loucks Rd",
    "iso:country":"US",
    "sg:address":"901 Loucks Rd",
    "sg:city":"York",
    "sg:classifiers":[
        {
            "category":"Wholesale",
            "subcategory":"Farm Supplies",
            "type":"Manufacturing & Wholesale Goods"
        }
    ],
    "sg:phone":"+1 717 845 8200",
    "sg:postcode":"17404",
    "sg:province":"PA",
    "wof:name":"Tractor Supply Co",
    "wof:placetype":"venue"
},
  "geometry": {"coordinates":[-76.750558,39.9806],"type":"Point"}
}