{
  "type": "Feature",
  "properties": {
    "iso:country":"US",
    "sg:address":"112 N Middlesex Rd",
    "sg:city":"Carlisle",
    "sg:classifiers":[
        {
            "category":"Retail",
            "subcategory":"Photofinishing",
            "type":"Services"
        }
    ],
    "sg:phone":"+1 717 258 6268",
    "sg:postcode":"17013",
    "sg:province":"PA",
    "sg:tags":[
        "photo",
        "finishing"
    ],
    "wof:name":"Brave New World",
    "wof:placetype":"venue"
},
  "geometry": {"coordinates":[-77.14161300000001,40.237925],"type":"Point"}
}