{
  "type": "Feature",
  "properties": {
    "addr:full":"313 13th St Huntingdon PA 16652",
    "addr:housenumber":"313",
    "addr:postcode":"16652",
    "addr:street":"13Th St",
    "iso:country":"US",
    "sg:address":"313 13th St",
    "sg:city":"Huntingdon",
    "sg:classifiers":[
        {
            "category":"Personal",
            "subcategory":"Beauty Salon",
            "type":"Services"
        }
    ],
    "sg:phone":"+1 814 643 3201",
    "sg:postcode":"16652",
    "sg:province":"PA",
    "wof:name":"Linda F Harris Beauty Shop",
    "wof:placetype":"venue"
},
  "geometry": {"coordinates":[-78.01802000000001,40.493602],"type":"Point"}
}