{
  "type": "Feature",
  "properties": {
    "iso:country":"US",
    "sg:address":"2759 Adirondack Dr",
    "sg:city":"Blakeslee",
    "sg:classifiers":[
        {
            "category":"Wholesale",
            "subcategory":"Machinery & Supplies",
            "type":"Manufacturing & Wholesale Goods"
        }
    ],
    "sg:phone":"+1   ",
    "sg:postcode":"18610",
    "sg:province":"PA",
    "sg:tags":[
        "equipment",
        "establishment"
    ],
    "wof:name":"Value Bag Inc",
    "wof:placetype":"venue"
},
  "geometry": {"coordinates":[-75.45600399999999,41.001749],"type":"Point"}
}