{
  "type": "Feature",
  "properties": {
    "addr:full":"1101 W Dekalb Pike King Of Prussia PA 19406",
    "addr:housenumber":"1101",
    "addr:postcode":"19406",
    "addr:street":"W Dekalb Pike",
    "iso:country":"US",
    "sg:address":"1101 W Dekalb Pike",
    "sg:city":"King Of Prussia",
    "sg:classifiers":[
        {
            "category":"Insurance",
            "subcategory":"Insurance Agent",
            "type":"Services"
        }
    ],
    "sg:phone":"+1   ",
    "sg:postcode":"19406",
    "sg:province":"PA",
    "wof:name":"Metropolitan P&L Ins Co",
    "wof:placetype":"venue"
},
  "geometry": {"coordinates":[-75.392788,40.083767],"type":"Point"}
}