{
  "type": "Feature",
  "properties": {
    "iso:country":"US",
    "sg:address":"1908 Rockwell Rd",
    "sg:city":"Abington",
    "sg:classifiers":[
        {
            "category":"Shopping",
            "subcategory":"Computers & Home Electronics",
            "type":"Retail Goods"
        }
    ],
    "sg:phone":"+1 215 706 0901",
    "sg:postcode":"19001",
    "sg:province":"PA",
    "wof:name":"Contract Sound & Video",
    "wof:placetype":"venue"
},
  "geometry": {"coordinates":[-75.11523099999999,40.13897],"type":"Point"}
}