{
  "type": "Feature",
  "properties": {
    "addr:full":"147 Oreland Mill Rd Oreland PA 19075",
    "addr:housenumber":"147",
    "addr:postcode":"19075",
    "addr:street":"Oreland Mill Rd",
    "iso:country":"US",
    "sg:address":"147 Oreland Mill Rd",
    "sg:city":"Oreland",
    "sg:classifiers":[
        {
            "category":"Utilities",
            "subcategory":"Refuse",
            "type":"Services"
        },
        {
            "category":"Retail",
            "subcategory":"Auto Repair",
            "type":"Services"
        }
    ],
    "sg:phone":"+1 215 885 8199",
    "sg:postcode":"19075",
    "sg:province":"PA",
    "sg:tags":[
        "fire",
        "truck",
        "rubbish",
        "apparatus",
        "removal"
    ],
    "wof:name":"John Miller and Son Inc",
    "wof:placetype":"venue"
},
  "geometry": {"coordinates":[-75.19217399999999,40.120689],"type":"Point"}
}