{
  "type": "Feature",
  "properties": {
    "iso:country":"US",
    "sg:address":"711 Montgomery Ave",
    "sg:city":"Narberth",
    "sg:classifiers":[
        {
            "category":"Professional",
            "subcategory":"Engineering",
            "type":"Services"
        }
    ],
    "sg:phone":"+1   ",
    "sg:postcode":"19072",
    "sg:province":"PA",
    "wof:name":"Schade Engineering",
    "wof:placetype":"venue"
},
  "geometry": {"coordinates":[-75.256867,40.010294],"type":"Point"}
}