{
  "type": "Feature",
  "properties": {
    "addr:full":"699 E Lincoln Ave Myerstown PA 17067",
    "addr:housenumber":"699",
    "addr:postcode":"17067",
    "addr:street":"E Lincoln Ave",
    "iso:country":"US",
    "sg:address":"699 E Lincoln Ave",
    "sg:city":"Myerstown",
    "sg:classifiers":[
        {
            "category":"Autos & Motor Vehicles",
            "subcategory":"Automobile Sales",
            "type":"Retail Goods"
        }
    ],
    "sg:phone":"+1 717 866 8821",
    "sg:postcode":"17067",
    "sg:province":"PA",
    "sg:tags":[
        "car",
        "dealer"
    ],
    "wof:name":"Auto Experts Corp",
    "wof:placetype":"venue"
},
  "geometry": {"coordinates":[-76.28391999999999,40.383885],"type":"Point"}
}