{
  "type": "Feature",
  "properties": {
    "addr:full":"235 Partridge Dr Greensburg PA 15601",
    "addr:housenumber":"235",
    "addr:postcode":"15601",
    "addr:street":"Partridge Dr",
    "iso:country":"US",
    "sg:address":"235 Partridge Dr",
    "sg:city":"Greensburg",
    "sg:classifiers":[
        {
            "category":"Building & Trades",
            "subcategory":"Construction",
            "type":"Services"
        }
    ],
    "sg:phone":"+1 724 853 3160",
    "sg:postcode":"15601",
    "sg:province":"PA",
    "sg:tags":[
        "general",
        "contractor"
    ],
    "wof:name":"Fort Allen Contruction Co Inc",
    "wof:placetype":"venue"
},
  "geometry": {"coordinates":[-79.58528099999999,40.272921],"type":"Point"}
}