{
  "type": "Feature",
  "properties": {
    "addr:full":"4 Sandy Creek Rd Verona PA 15147",
    "addr:housenumber":"4",
    "addr:postcode":"15147",
    "addr:street":"Sandy Creek Rd",
    "iso:country":"US",
    "sg:address":"4 Sandy Creek Rd",
    "sg:city":"Verona",
    "sg:classifiers":[
        {
            "category":"Autos & Motor Vehicles",
            "subcategory":"Automobile Sales",
            "type":"Retail Goods"
        }
    ],
    "sg:phone":"+1 412 795 4686",
    "sg:postcode":"15147",
    "sg:province":"PA",
    "sg:tags":[
        "car",
        "used",
        "dealer"
    ],
    "wof:name":"G T Auto Sales",
    "wof:placetype":"venue"
},
  "geometry": {"coordinates":[-79.851722,40.482853],"type":"Point"}
}