{
  "type": "Feature",
  "properties": {
    "addr:full":"221 Barnard St Dunmore PA 18512",
    "addr:housenumber":"221",
    "addr:postcode":"18512",
    "addr:street":"Barnard St",
    "iso:country":"US",
    "sg:address":"221 Barnard St",
    "sg:city":"Dunmore",
    "sg:classifiers":[
        {
            "category":"Real Estate",
            "subcategory":"Surveying",
            "type":"Services"
        }
    ],
    "sg:phone":"+1 570 961 1227",
    "sg:postcode":"18512",
    "sg:province":"PA",
    "sg:tags":[
        "surveyor"
    ],
    "wof:name":"G Dunda Assoc",
    "wof:placetype":"venue"
},
  "geometry": {"coordinates":[-75.6181,41.420833],"type":"Point"}
}