{
  "type": "Feature",
  "properties": {
    "iso:country":"US",
    "sg:address":"120 Keighley",
    "sg:city":"Oliver",
    "sg:classifiers":[
        {
            "category":"Building & Trades",
            "subcategory":"Construction",
            "type":"Services"
        }
    ],
    "sg:phone":"+1 724 438 2080",
    "sg:postcode":"15472",
    "sg:province":"PA",
    "sg:tags":[
        "general",
        "contractor"
    ],
    "wof:name":"Highland Builders",
    "wof:placetype":"venue"
},
  "geometry": {"coordinates":[-79.71544900000001,39.917899],"type":"Point"}
}