{
  "type": "Feature",
  "properties": {
    "iso:country":"US",
    "sg:address":"17 Heather Highlands",
    "sg:city":"Pittston",
    "sg:classifiers":[
        {
            "category":"Wholesale",
            "subcategory":"Farm Supplies",
            "type":"Manufacturing & Wholesale Goods"
        }
    ],
    "sg:phone":"+1   ",
    "sg:postcode":"18640",
    "sg:province":"PA",
    "sg:tags":[
        "raw",
        "product",
        "material"
    ],
    "wof:name":"Bier Stables",
    "wof:placetype":"venue"
},
  "geometry": {"coordinates":[-75.817296,41.299324],"type":"Point"}
}