{
  "type": "Feature",
  "properties": {
    "iso:country":"US",
    "sg:address":"1480 State Rd",
    "sg:city":"Laurelton",
    "sg:classifiers":[
        {
            "category":"Retail",
            "subcategory":"Auto Repair",
            "type":"Services"
        }
    ],
    "sg:phone":"+1 570 922 1045",
    "sg:postcode":"17815",
    "sg:province":"PA",
    "sg:tags":[
        "repairing",
        "automobile"
    ],
    "wof:name":"Straub's Auto Repair",
    "wof:placetype":"venue"
},
  "geometry": {"coordinates":[-76.246129,40.933306],"type":"Point"}
}