{
  "type": "Feature",
  "properties": {
    "addr:full":"518 Main St 2nd Fl Bethlehem PA 18018",
    "addr:housenumber":"518",
    "addr:postcode":"18018",
    "addr:street":"Main St",
    "iso:country":"US",
    "sg:address":"518 Main St 2nd Fl",
    "sg:city":"Bethlehem",
    "sg:classifiers":[
        {
            "category":"Professional",
            "subcategory":"Advertising",
            "type":"Services"
        },
        {
            "category":"Communications",
            "subcategory":"Newspaper",
            "type":"Services"
        },
        {
            "category":"Communications",
            "type":"Services"
        }
    ],
    "sg:phone":"+1 610 419 4510",
    "sg:postcode":"18018",
    "sg:province":"PA",
    "sg:tags":[
        "marketing",
        "design",
        "web"
    ],
    "sg:website":"www.metterinteractive.com",
    "wof:name":"Metter Interactive",
    "wof:placetype":"venue"
},
  "geometry": {"coordinates":[-75.381946,40.621046],"type":"Point"}
}