{
  "type": "Feature",
  "properties": {
    "iso:country":"US",
    "sg:address":"3238 Greentree Cir",
    "sg:city":"New Castle",
    "sg:classifiers":[
        {
            "category":"Freight",
            "type":"Transportation"
        }
    ],
    "sg:phone":"+1   ",
    "sg:postcode":"16105",
    "sg:province":"PA",
    "sg:tags":[
        "operator",
        "local",
        "trucking"
    ],
    "wof:name":"Castle Trucking Inc",
    "wof:placetype":"venue"
},
  "geometry": {"coordinates":[-80.338635,41.05516],"type":"Point"}
}