{
  "type": "Feature",
  "properties": {
    "iso:country":"US",
    "sg:address":"657 Sandra Ave",
    "sg:city":"Harrisburg",
    "sg:classifiers":[
        {
            "category":"Professional",
            "subcategory":"Lawyer & Legal Services",
            "type":"Services"
        }
    ],
    "sg:phone":"+1 717 564 8719",
    "sg:postcode":"17109",
    "sg:province":"PA",
    "wof:name":"Peters Wm J Atty",
    "wof:placetype":"venue"
},
  "geometry": {"coordinates":[-76.834602,40.2733],"type":"Point"}
}