{
  "type": "Feature",
  "properties": {
    "addr:full":"6051 Allentown Blvd Harrisburg PA 17112",
    "addr:housenumber":"6051",
    "addr:postcode":"17112",
    "addr:street":"Allentown Blvd",
    "iso:country":"US",
    "sg:address":"6051 Allentown Blvd",
    "sg:city":"Harrisburg",
    "sg:classifiers":[
        {
            "category":"Restaurant",
            "type":"Food & Drink"
        }
    ],
    "sg:menulink":"http://www.allmenus.com/pa/lower-paxton/28065-brother-joes-pizza/menu/",
    "sg:phone":"+1 717 545 9209",
    "sg:postcode":"17112",
    "sg:province":"PA",
    "sg:tags":[
        "american",
        "pizza"
    ],
    "wof:name":"Brother Joe's Pizza",
    "wof:placetype":"venue"
},
  "geometry": {"coordinates":[-76.788331,40.322528],"type":"Point"}
}