{
  "type": "Feature",
  "properties": {
    "addr:full":"1410 Beaver Rd Julian PA 16844",
    "addr:housenumber":"1410",
    "addr:postcode":"16844",
    "addr:street":"Beaver Rd",
    "iso:country":"US",
    "sg:address":"1410 Beaver Rd",
    "sg:city":"Julian",
    "sg:classifiers":[
        {
            "category":"Building & Trades",
            "subcategory":"Landscaping Services",
            "type":"Services"
        },
        {
            "category":"Building & Trades",
            "subcategory":"Pest Control",
            "type":"Services"
        }
    ],
    "sg:phone":"+1 814 355 0538",
    "sg:postcode":"16844",
    "sg:province":"PA",
    "sg:tags":[
        "stump",
        "tree",
        "snow",
        "grinding",
        "removal",
        "arborist"
    ],
    "sg:website":"http://www.meektreeservice.com",
    "wof:name":"Meek's Tree Service",
    "wof:placetype":"venue"
},
  "geometry": {"coordinates":[-77.978477,40.887741],"type":"Point"}
}