{
  "type": "Feature",
  "properties": {
    "addr:full":"17 Henry Rd Fleetwood PA 19522",
    "addr:housenumber":"17",
    "addr:postcode":"19522",
    "addr:street":"Henry Rd",
    "iso:country":"US",
    "sg:address":"17 Henry Rd",
    "sg:city":"Fleetwood",
    "sg:classifiers":[
        {
            "category":"Personal",
            "subcategory":"Beauty Salon",
            "type":"Services"
        }
    ],
    "sg:phone":"+1 610 682 6725",
    "sg:postcode":"19522",
    "sg:province":"PA",
    "wof:name":"Linda Troop Beauty Salon",
    "wof:placetype":"venue"
},
  "geometry": {"coordinates":[-75.74214000000001,40.454962],"type":"Point"}
}