{
  "type": "Feature",
  "properties": {
    "iso:country":"US",
    "sg:address":"147 Market St",
    "sg:city":"Sunbury",
    "sg:classifiers":[
        {
            "category":"Food & Beverages",
            "subcategory":"Groceries & Convenience Stores",
            "type":"Retail Goods"
        }
    ],
    "sg:phone":"+1 570 286 4121",
    "sg:postcode":"17801",
    "sg:province":"PA",
    "sg:tags":[
        "grocer"
    ],
    "wof:name":"WEIS Markets Inc",
    "wof:placetype":"venue"
},
  "geometry": {"coordinates":[-76.79566,40.862499],"type":"Point"}
}