{
  "type": "Feature",
  "properties": {
    "iso:country":"US",
    "sg:address":"125 Prospect St",
    "sg:city":"Phoenixville",
    "sg:classifiers":[
        {
            "category":"Organizations",
            "subcategory":"Professional Association",
            "type":"Services"
        }
    ],
    "sg:phone":"+1   ",
    "sg:postcode":"19460",
    "sg:province":"PA",
    "sg:tags":[
        "membership"
    ],
    "wof:name":"Assoction For Intgrtive Mdcine",
    "wof:placetype":"venue"
},
  "geometry": {"coordinates":[-75.512646,40.133864],"type":"Point"}
}