{
  "type": "Feature",
  "properties": {
    "iso:country":"US",
    "sg:address":"4485 Heron Dr",
    "sg:city":"Reading",
    "sg:classifiers":[
        {
            "category":"Shopping",
            "subcategory":"Stationery & Office Supplies",
            "type":"Retail Goods"
        }
    ],
    "sg:phone":"+1 610 370 4923",
    "sg:postcode":"19606",
    "sg:province":"PA",
    "sg:tags":[
        "rubber",
        "stamp",
        "plastic"
    ],
    "wof:name":"Knock On Wood",
    "wof:placetype":"venue"
},
  "geometry": {"coordinates":[-75.871222,40.298865],"type":"Point"}
}