{
  "type": "Feature",
  "properties": {
    "addr:full":"4439 Whitaker Ave # 41 Philadelphia PA 19120",
    "addr:housenumber":"4439;41",
    "addr:postcode":"19120",
    "addr:street":"Whitaker Ave #",
    "iso:country":"US",
    "sg:address":"4439 Whitaker Ave # 41",
    "sg:city":"Philadelphia",
    "sg:classifiers":[
        {
            "category":"Autos & Motor Vehicles",
            "subcategory":"Auto Supplies",
            "type":"Retail Goods"
        }
    ],
    "sg:phone":"+1 215 455 2064",
    "sg:postcode":"19120",
    "sg:province":"PA",
    "sg:tags":[
        "tire"
    ],
    "wof:name":"Tire Net USA",
    "wof:placetype":"venue"
},
  "geometry": {"coordinates":[-75.116699,40.016899],"type":"Point"}
}