{
  "type": "Feature",
  "properties": {
    "addr:full":"3400 S Ruch St Whitehall PA 18052",
    "addr:housenumber":"3400",
    "addr:postcode":"18052",
    "addr:street":"S Ruch St",
    "iso:country":"US",
    "sg:address":"3400 S Ruch St",
    "sg:city":"Whitehall",
    "sg:classifiers":[
        {
            "category":"Communications",
            "subcategory":"Film & Video Production",
            "type":"Services"
        }
    ],
    "sg:phone":"+1 610 437 5244",
    "sg:postcode":"18052",
    "sg:province":"PA",
    "sg:tags":[
        "taping"
    ],
    "wof:name":"David Beedle",
    "wof:placetype":"venue"
},
  "geometry": {"coordinates":[-75.500663,40.66065],"type":"Point"}
}