{
  "type": "Feature",
  "properties": {
    "iso:country":"US",
    "sg:address":"104 Bavington Rd",
    "sg:city":"Burgettstown",
    "sg:classifiers":[
        {
            "category":"Education",
            "subcategory":"School",
            "type":"Public Place"
        }
    ],
    "sg:phone":"+1   ",
    "sg:postcode":"15021",
    "sg:province":"PA",
    "wof:name":"burgettstown jr/sr high school",
    "wof:placetype":"venue"
},
  "geometry": {"coordinates":[-80.390361,40.39264],"type":"Point"}
}