{
  "type": "Feature",
  "properties": {
    "addr:full":"7001 Ludlow St Upper Darby PA 19082",
    "addr:housenumber":"7001",
    "addr:postcode":"19082",
    "addr:street":"Ludlow St",
    "iso:country":"US",
    "sg:address":"7001 Ludlow St",
    "sg:city":"Upper Darby",
    "sg:classifiers":[
        {
            "category":"Personal",
            "subcategory":"Barber",
            "type":"Services"
        }
    ],
    "sg:phone":"+1 610 352 3380",
    "sg:postcode":"19082",
    "sg:province":"PA",
    "wof:name":"Dung Phung",
    "wof:placetype":"venue"
},
  "geometry": {"coordinates":[-75.26116399999999,39.961058],"type":"Point"}
}