{
  "type": "Feature",
  "properties": {
    "addr:full":"5728 Fritzinger Rd Germansville PA 18053",
    "addr:postcode":"5728;18053",
    "addr:street":"Fritzinger Rd",
    "iso:country":"US",
    "sg:address":"5728 Fritzinger Rd",
    "sg:city":"Germansville",
    "sg:classifiers":[
        {
            "category":"Recreation",
            "type":"Entertainment"
        }
    ],
    "sg:phone":"+1 610 767 8616",
    "sg:postcode":"18053",
    "sg:province":"PA",
    "sg:tags":[
        "farm",
        "equine"
    ],
    "wof:name":"Venture Farms",
    "wof:placetype":"venue"
},
  "geometry": {"coordinates":[-75.709051,40.723193],"type":"Point"}
}