{
  "type": "Feature",
  "properties": {
    "iso:country":"US",
    "sg:address":"106 Philomena Dr",
    "sg:city":"Coraopolis",
    "sg:classifiers":[
        {
            "category":"Building & Trades",
            "subcategory":"Construction",
            "type":"Services"
        }
    ],
    "sg:phone":"+1 412 262 8090",
    "sg:postcode":"15108",
    "sg:province":"PA",
    "sg:tags":[
        "system",
        "contractor",
        "air conditioning"
    ],
    "wof:name":"E V Didomenico Htg Ac",
    "wof:placetype":"venue"
},
  "geometry": {"coordinates":[-80.173683,40.498507],"type":"Point"}
}