{
  "type": "Feature",
  "properties": {
    "addr:full":"143 N Chester Rd West Chester PA 19380",
    "addr:housenumber":"143",
    "addr:postcode":"19380",
    "addr:street":"N Chester Rd",
    "iso:country":"US",
    "sg:address":"143 N Chester Rd",
    "sg:city":"West Chester",
    "sg:classifiers":[
        {
            "category":"Social Services",
            "type":"Services"
        }
    ],
    "sg:phone":"+1   ",
    "sg:postcode":"19380",
    "sg:province":"PA",
    "wof:name":"Glenn L Fricke",
    "wof:placetype":"venue"
},
  "geometry": {"coordinates":[-75.526915,39.969088],"type":"Point"}
}