{
  "type": "Feature",
  "properties": {
    "iso:country":"US",
    "sg:address":"2879 Truman Dr",
    "sg:city":"Hatfield",
    "sg:classifiers":[
        {
            "category":"Restaurant",
            "type":"Food & Drink"
        },
        {
            "category":"Food & Beverages",
            "subcategory":"Groceries & Convenience Stores",
            "type":"Retail Goods"
        }
    ],
    "sg:phone":"+1 215 444 9888",
    "sg:postcode":"19440",
    "sg:province":"PA",
    "sg:tags":[
        "shop",
        "sandwich"
    ],
    "wof:name":"Steak & Hoagie Factory",
    "wof:placetype":"venue"
},
  "geometry": {"coordinates":[-75.319332,40.275507],"type":"Point"}
}