{
  "type": "Feature",
  "properties": {
    "iso:country":"US",
    "sg:address":"4148 Deerhill Dr",
    "sg:city":"York",
    "sg:classifiers":[
        {
            "category":"Manufacturing",
            "subcategory":"Signs",
            "type":"Manufacturing & Wholesale Goods"
        }
    ],
    "sg:phone":"+1   ",
    "sg:postcode":"17406",
    "sg:province":"PA",
    "sg:tags":[
        "graphic",
        "design",
        "mfg"
    ],
    "wof:name":"Hainey Signs Inc",
    "wof:placetype":"venue"
},
  "geometry": {"coordinates":[-76.652962,40.027589],"type":"Point"}
}