{
  "type": "Feature",
  "properties": {
    "addr:full":"800 E High St Carlisle PA 17013",
    "addr:housenumber":"800",
    "addr:postcode":"17013",
    "addr:street":"E High St",
    "iso:country":"US",
    "sg:address":"800 E High St",
    "sg:city":"Carlisle",
    "sg:classifiers":[
        {
            "category":"Shopping",
            "subcategory":"Music",
            "type":"Retail Goods"
        }
    ],
    "sg:phone":"+1   ",
    "sg:postcode":"17013",
    "sg:province":"PA",
    "wof:name":"Wall The Store 1509",
    "wof:placetype":"venue"
},
  "geometry": {"coordinates":[-77.17357,40.20023],"type":"Point"}
}