{
  "type": "Feature",
  "properties": {
    "iso:country":"US",
    "sg:address":"4055 Ridge Ave Apt 6501",
    "sg:city":"Philadelphia",
    "sg:classifiers":[
        {
            "category":"Professional",
            "subcategory":"Management & Consulting",
            "type":"Services"
        }
    ],
    "sg:phone":"+1 215 477 3801",
    "sg:postcode":"19129",
    "sg:province":"PA",
    "sg:tags":[
        "consultant",
        "educational"
    ],
    "wof:name":"Behavioural Education Training Associates",
    "wof:placetype":"venue"
},
  "geometry": {"coordinates":[-75.18933800000001,40.007244],"type":"Point"}
}