{
  "type": "Feature",
  "properties": {
    "iso:country":"US",
    "sg:address":"100 W Metzler Rd",
    "sg:city":"Ephrata",
    "sg:classifiers":[
        {
            "category":"Professional",
            "subcategory":"Advertising",
            "type":"Services"
        }
    ],
    "sg:phone":"+1   ",
    "sg:postcode":"17522",
    "sg:province":"PA",
    "wof:name":"Timely Products",
    "wof:placetype":"venue"
},
  "geometry": {"coordinates":[-76.212062,40.131539],"type":"Point"}
}