{
  "type": "Feature",
  "properties": {
    "iso:country":"US",
    "sg:address":"40161 Archer Rd",
    "sg:city":"Titusville",
    "sg:classifiers":[
        {
            "category":"Farming",
            "subcategory":"Dairy Farm",
            "type":"Manufacturing & Wholesale Goods"
        }
    ],
    "sg:phone":"+1   ",
    "sg:postcode":"16354",
    "sg:province":"PA",
    "wof:name":"Richard Deeter Farm",
    "wof:placetype":"venue"
},
  "geometry": {"coordinates":[-79.74927700000001,41.649038],"type":"Point"}
}