{
  "type": "Feature",
  "properties": {
    "iso:country":"US",
    "sg:address":"735 Birkbeck St",
    "sg:city":"Freeland",
    "sg:classifiers":[
        {
            "category":"Retail",
            "subcategory":"Auto Repair",
            "type":"Services"
        }
    ],
    "sg:phone":"+1 570 636 3600",
    "sg:postcode":"18224",
    "sg:province":"PA",
    "sg:tags":[
        "repairing",
        "automobile"
    ],
    "wof:name":"Miamee's Alignment & Auto Rpr",
    "wof:placetype":"venue"
},
  "geometry": {"coordinates":[-75.89315999999999,41.018898],"type":"Point"}
}