{
  "type": "Feature",
  "properties": {
    "addr:full":"418 March St Ellwood City PA 16117",
    "addr:housenumber":"418",
    "addr:postcode":"16117",
    "addr:street":"March St",
    "iso:country":"US",
    "sg:address":"418 March St",
    "sg:city":"Ellwood City",
    "sg:classifiers":[
        {
            "category":"Arts & Performance",
            "subcategory":"Theater",
            "type":"Entertainment"
        }
    ],
    "sg:phone":"+1   ",
    "sg:postcode":"16117",
    "sg:province":"PA",
    "sg:tags":[
        "entertainer",
        "group"
    ],
    "wof:name":"West Jill & Blues Attack",
    "wof:placetype":"venue"
},
  "geometry": {"coordinates":[-80.277249,40.864724],"type":"Point"}
}