{
  "type": "Feature",
  "properties": {
    "iso:country":"US",
    "sg:address":"3rd & Spring Garden St.",
    "sg:city":"Philadelphia",
    "sg:classifiers":[
        {
            "category":"Bars & Pubs",
            "type":"Food & Drink"
        }
    ],
    "sg:phone":"+1 215 574 9317",
    "sg:postcode":"19123",
    "sg:province":"PA",
    "sg:website":"www.finnigans.com/",
    "wof:name":"Finnegan's Wake",
    "wof:placetype":"venue"
},
  "geometry": {"coordinates":[-75.143377,39.960909],"type":"Point"}
}