{
  "type": "Feature",
  "properties": {
    "iso:country":"US",
    "sg:address":"1039 Bear Gap Rd",
    "sg:city":"Elysburg",
    "sg:phone":"+1   ",
    "sg:postcode":"17824",
    "sg:province":"PA",
    "sg:tags":[
        "farm",
        "field",
        "crop"
    ],
    "wof:name":"Melvin Yeager",
    "wof:placetype":"venue"
},
  "geometry": {"coordinates":[-76.41531500000001,40.853667],"type":"Point"}
}