{
  "type": "Feature",
  "properties": {
    "addr:full":"414 Cross St Philadelphia PA 19147",
    "addr:housenumber":"414",
    "addr:postcode":"19147",
    "addr:street":"Cross St",
    "iso:country":"US",
    "sg:address":"414 Cross St",
    "sg:city":"Philadelphia",
    "sg:classifiers":[
        {
            "category":"Restaurant",
            "type":"Food & Drink"
        }
    ],
    "sg:phone":"+1 215 551 1313",
    "sg:postcode":"19147",
    "sg:province":"PA",
    "sg:tags":[
        "delicatessen"
    ],
    "wof:name":"Gimlis Deli Inc",
    "wof:placetype":"venue"
},
  "geometry": {"coordinates":[-75.153443,39.92887],"type":"Point"}
}