{
  "type": "Feature",
  "properties": {
    "iso:country":"US",
    "sg:address":"801 Katie Ct",
    "sg:city":"Harrisburg",
    "sg:classifiers":[
        {
            "category":"Professional",
            "type":"Services"
        },
        {
            "category":"Retail",
            "subcategory":"Auto Rental",
            "type":"Services"
        },
        {
            "category":"Building & Trades",
            "subcategory":"Equipment Rental",
            "type":"Services"
        },
        {
            "category":"Retail",
            "subcategory":"Storage",
            "type":"Services"
        }
    ],
    "sg:phone":"+1 866 205 7339",
    "sg:postcode":"17109",
    "sg:province":"PA",
    "sg:tags":[
        "renting",
        "moving-self",
        "leasing",
        "material",
        "moving",
        "services-labor",
        "truck",
        "trailer"
    ],
    "sg:website":"http://www.pensketruckrental.com/personal_rental/?cid=Yptmlist",
    "wof:name":"Penske Truck Rental",
    "wof:placetype":"venue"
},
  "geometry": {"coordinates":[-76.825028,40.272642],"type":"Point"}
}