{
  "type": "Feature",
  "properties": {
    "iso:country":"US",
    "sg:address":"1000 E Lawrence Ave",
    "sg:city":"Ellwood City",
    "sg:classifiers":[
        {
            "category":"Retail",
            "subcategory":"Auto Rental",
            "type":"Services"
        }
    ],
    "sg:phone":"+1   ",
    "sg:postcode":"16117",
    "sg:province":"PA",
    "sg:tags":[
        "passenger",
        "leasing",
        "car"
    ],
    "wof:name":"Penrac Inc",
    "wof:placetype":"venue"
},
  "geometry": {"coordinates":[-80.29552099999999,40.858367],"type":"Point"}
}