{
  "type": "Feature",
  "properties": {
    "iso:country":"US",
    "sg:address":"226 Grant St",
    "sg:city":"Franklin",
    "sg:classifiers":[
        {
            "category":"Personal",
            "subcategory":"Beauty Salon",
            "type":"Services"
        }
    ],
    "sg:phone":"+1 814 437 3220",
    "sg:postcode":"16323",
    "sg:province":"PA",
    "sg:tags":[
        "shop"
    ],
    "wof:name":"Top Priority Hair Care",
    "wof:placetype":"venue"
},
  "geometry": {"coordinates":[-79.837453,41.40506],"type":"Point"}
}