{
  "type": "Feature",
  "properties": {
    "iso:country":"US",
    "sg:address":"1600 Lehigh Pkwy E Ste 1E",
    "sg:city":"Allentown",
    "sg:classifiers":[
        {
            "category":"Professional",
            "subcategory":"Lawyer & Legal Services",
            "type":"Services"
        }
    ],
    "sg:phone":"+1 610 437 4595",
    "sg:postcode":"18103",
    "sg:province":"PA",
    "sg:tags":[
        "plan"
    ],
    "wof:name":"Peter P Perry",
    "wof:placetype":"venue"
},
  "geometry": {"coordinates":[-75.487235,40.588465],"type":"Point"}
}