{
  "type": "Feature",
  "properties": {
    "addr:full":"11 Stuart Ave Downingtown PA 19335",
    "addr:housenumber":"11",
    "addr:postcode":"19335",
    "addr:street":"Stuart Ave",
    "iso:country":"US",
    "sg:address":"11 Stuart Ave",
    "sg:city":"Downingtown",
    "sg:classifiers":[
        {
            "category":"Manufacturing",
            "subcategory":"Printing",
            "type":"Manufacturing & Wholesale Goods"
        }
    ],
    "sg:phone":"+1 610 269 0127",
    "sg:postcode":"19335",
    "sg:province":"PA",
    "sg:tags":[
        "printer",
        "commercial",
        "letterpress",
        "offset"
    ],
    "wof:name":"Downingtown Printing Co Inc",
    "wof:placetype":"venue"
},
  "geometry": {"coordinates":[-75.71056299999999,40.003218],"type":"Point"}
}