{
  "type": "Feature",
  "properties": {
    "iso:country":"US",
    "sg:address":"612 Jefferson St",
    "sg:city":"Pottsville",
    "sg:classifiers":[
        {
            "category":"Building & Trades",
            "subcategory":"Construction",
            "type":"Services"
        }
    ],
    "sg:phone":"+1   ",
    "sg:postcode":"17901",
    "sg:province":"PA",
    "sg:tags":[
        "builder",
        "operative"
    ],
    "wof:name":"Daniel M Sponenburg Contg",
    "wof:placetype":"venue"
},
  "geometry": {"coordinates":[-76.186729,40.685008],"type":"Point"}
}