{
  "type": "Feature",
  "properties": {
    "addr:full":"2300 S Atherton St State College PA 16801",
    "addr:housenumber":"2300",
    "addr:postcode":"16801",
    "addr:street":"S Atherton St",
    "iso:country":"US",
    "sg:address":"2300 S Atherton St",
    "sg:city":"State College",
    "sg:classifiers":[
        {
            "category":"Real Estate",
            "subcategory":"Real Estate Agent",
            "type":"Services"
        }
    ],
    "sg:phone":"+1 814 234 2166",
    "sg:postcode":"16801",
    "sg:province":"PA",
    "sg:tags":[
        "appraiser"
    ],
    "wof:name":"Crispell Associates",
    "wof:placetype":"venue"
},
  "geometry": {"coordinates":[-77.827474,40.784354],"type":"Point"}
}