{
  "type": "Feature",
  "properties": {
    "iso:country":"US",
    "sg:address":"3616 Forbes Ave",
    "sg:city":"Pittsburgh",
    "sg:classifiers":[
        {
            "category":"Shopping",
            "subcategory":"Jewelry",
            "type":"Retail Goods"
        }
    ],
    "sg:phone":"+1   ",
    "sg:postcode":"15213",
    "sg:province":"PA",
    "wof:name":"Touch of Gold",
    "wof:placetype":"venue"
},
  "geometry": {"coordinates":[-79.957661,40.440951],"type":"Point"}
}