{
  "type": "Feature",
  "properties": {
    "addr:full":"1764 S Center St Exd Grove City PA 16127",
    "addr:housenumber":"1764",
    "addr:postcode":"16127",
    "addr:street":"S Center St Exd",
    "iso:country":"US",
    "sg:address":"1764 S Center St Exd",
    "sg:city":"Grove City",
    "sg:classifiers":[
        {
            "category":"Autos & Motor Vehicles",
            "subcategory":"Motorcycle Sales",
            "type":"Retail Goods"
        }
    ],
    "sg:phone":"+1 724 748 5004",
    "sg:postcode":"16127",
    "sg:province":"PA",
    "sg:tags":[
        "quad",
        "scooter"
    ],
    "wof:name":"Grove City Motor Sports",
    "wof:placetype":"venue"
},
  "geometry": {"coordinates":[-80.14640799999999,41.144927],"type":"Point"}
}