{
  "type": "Feature",
  "properties": {
    "iso:country":"US",
    "sg:address":"794 Peach Orchard Rd",
    "sg:city":"Mc Connellsburg",
    "sg:classifiers":[
        {
            "category":"Shopping",
            "subcategory":"Gifts & Souvenirs",
            "type":"Retail Goods"
        }
    ],
    "sg:phone":"+1 717 485 4902",
    "sg:postcode":"17233",
    "sg:province":"PA",
    "sg:tags":[
        "shop"
    ],
    "wof:name":"Sheep Ridge Farm Gift Shop",
    "wof:placetype":"venue"
},
  "geometry": {"coordinates":[-78.007772,39.951942],"type":"Point"}
}