{
  "type": "Feature",
  "properties": {
    "iso:country":"US",
    "sg:address":"357 Ogden St",
    "sg:city":"Mineral Point",
    "sg:classifiers":[
        {
            "category":"Wholesale",
            "subcategory":"Sporting Goods",
            "type":"Manufacturing & Wholesale Goods"
        },
        {
            "category":"Building & Trades",
            "subcategory":"Construction",
            "type":"Services"
        }
    ],
    "sg:phone":"+1 814 472 6285",
    "sg:postcode":"15942",
    "sg:province":"PA",
    "sg:tags":[
        "swimming",
        "designer",
        "dealer",
        "pool",
        "contractor"
    ],
    "wof:name":"Jerry Gilkey Pools",
    "wof:placetype":"venue"
},
  "geometry": {"coordinates":[-78.794045,40.438291],"type":"Point"}
}