{
  "type": "Feature",
  "properties": {
    "addr:full":"617 Haudie Ann Rd Marcus Hook PA 19061",
    "addr:housenumber":"617",
    "addr:postcode":"19061",
    "addr:street":"Haudie Ann Rd",
    "iso:country":"US",
    "sg:address":"617 Haudie Ann Rd",
    "sg:city":"Marcus Hook",
    "sg:classifiers":[
        {
            "category":"Professional",
            "subcategory":"Employment Agencies",
            "type":"Services"
        }
    ],
    "sg:phone":"+1 610 497 5000",
    "sg:postcode":"19061",
    "sg:province":"PA",
    "sg:tags":[
        "opportunity"
    ],
    "wof:name":"Infotech Staffing Inc",
    "wof:placetype":"venue"
},
  "geometry": {"coordinates":[-75.45031400000001,39.847302],"type":"Point"}
}