{
  "type": "Feature",
  "properties": {
    "iso:country":"US",
    "sg:address":"3780 Trindle Rd",
    "sg:city":"Camp Hill",
    "sg:classifiers":[
        {
            "category":"Shopping",
            "subcategory":"Jewelry",
            "type":"Retail Goods"
        }
    ],
    "sg:phone":"+1 717 763 1199",
    "sg:postcode":"17011",
    "sg:province":"PA",
    "sg:website":"www.mountzjewelers.com",
    "wof:name":"Mountz Jewelers",
    "wof:placetype":"venue"
},
  "geometry": {"coordinates":[-76.945099,40.234798],"type":"Point"}
}