{
  "type": "Feature",
  "properties": {
    "addr:full":"95 Burns Rd Brogue PA 17309",
    "addr:housenumber":"95",
    "addr:postcode":"17309",
    "addr:street":"Burns Rd",
    "iso:country":"US",
    "sg:address":"95 Burns Rd",
    "sg:city":"Brogue",
    "sg:phone":"+1   ",
    "sg:postcode":"17309",
    "sg:province":"PA",
    "sg:tags":[
        "farm",
        "grain",
        "cash"
    ],
    "wof:name":"Miller Farms",
    "wof:placetype":"venue"
},
  "geometry": {"coordinates":[-76.4293,39.854409],"type":"Point"}
}