{
  "type": "Feature",
  "properties": {
    "iso:country":"US",
    "sg:address":"283 S 2nd St",
    "sg:city":"Chambersburg",
    "sg:classifiers":[
        {
            "category":"Shopping",
            "subcategory":"Used Merchandise",
            "type":"Retail Goods"
        }
    ],
    "sg:phone":"+1   ",
    "sg:postcode":"17201",
    "sg:province":"PA",
    "wof:name":"Antique Ord Preservation Soc",
    "wof:placetype":"venue"
},
  "geometry": {"coordinates":[-77.66017100000001,39.932996],"type":"Point"}
}