{
  "type": "Feature",
  "properties": {
    "addr:full":"7220 Schantz Rd Allentown PA 18104",
    "addr:housenumber":"7220",
    "addr:postcode":"18104",
    "addr:street":"Schantz Rd",
    "iso:country":"US",
    "sg:address":"7220 Schantz Rd",
    "sg:city":"Allentown",
    "sg:classifiers":[
        {
            "category":"Manufacturing",
            "subcategory":"Paper Products",
            "type":"Manufacturing & Wholesale Goods"
        }
    ],
    "sg:phone":"+1 610 706 0910",
    "sg:postcode":"18104",
    "sg:province":"PA",
    "sg:tags":[
        "converter"
    ],
    "sg:website":"www.laminationsonline.com",
    "wof:name":"Laminations East",
    "wof:placetype":"venue"
},
  "geometry": {"coordinates":[-75.606571,40.578791],"type":"Point"}
}