{
  "type": "Feature",
  "properties": {
    "iso:country":"US",
    "sg:address":"1077 N Wales Rd",
    "sg:city":"North Wales",
    "sg:classifiers":[
        {
            "category":"Utilities",
            "subcategory":"Refuse",
            "type":"Services"
        }
    ],
    "sg:phone":"+1   ",
    "sg:postcode":"19454",
    "sg:province":"PA",
    "sg:tags":[
        "system"
    ],
    "wof:name":"Moore Arhur Refuse",
    "wof:placetype":"venue"
},
  "geometry": {"coordinates":[-75.242603,40.241454],"type":"Point"}
}