{
  "type": "Feature",
  "properties": {
    "iso:country":"US",
    "sg:address":"405 Easton Rd",
    "sg:city":"Hermitage",
    "sg:classifiers":[
        {
            "category":"Professional",
            "type":"Services"
        }
    ],
    "sg:phone":"+1 724 981 4051",
    "sg:postcode":"16148",
    "sg:province":"PA",
    "sg:tags":[
        "establishment"
    ],
    "wof:name":"Derloni L S",
    "wof:placetype":"venue"
},
  "geometry": {"coordinates":[-80.44152099999999,41.230881],"type":"Point"}
}