{
  "type": "Feature",
  "properties": {
    "addr:full":"219 Chestnut St Meadville PA 16335",
    "addr:housenumber":"219",
    "addr:postcode":"16335",
    "addr:street":"Chestnut St",
    "iso:country":"US",
    "sg:address":"219 Chestnut St",
    "sg:city":"Meadville",
    "sg:classifiers":[
        {
            "category":"Professional",
            "type":"Services"
        }
    ],
    "sg:phone":"+1   ",
    "sg:postcode":"16335",
    "sg:province":"PA",
    "wof:name":"Kens Leather Loft",
    "wof:placetype":"venue"
},
  "geometry": {"coordinates":[-80.15424400000001,41.638495],"type":"Point"}
}