{
  "type": "Feature",
  "properties": {
    "iso:country":"US",
    "sg:address":"5117 Union St",
    "sg:city":"Finleyville",
    "sg:classifiers":[
        {
            "category":"Home & Garden",
            "subcategory":"Household Appliances",
            "type":"Retail Goods"
        }
    ],
    "sg:phone":"+1 412 833 8039",
    "sg:postcode":"15332",
    "sg:province":"PA",
    "sg:tags":[
        "cooling",
        "heating"
    ],
    "wof:name":"Precision Air Systems",
    "wof:placetype":"venue"
},
  "geometry": {"coordinates":[-79.995589,40.260359],"type":"Point"}
}