{
  "type": "Feature",
  "properties": {
    "addr:full":"751 W Lancaster Ave Downingtown PA 19335",
    "addr:housenumber":"751",
    "addr:postcode":"19335",
    "addr:street":"W Lancaster Ave",
    "iso:country":"US",
    "sg:address":"751 W Lancaster Ave",
    "sg:city":"Downingtown",
    "sg:classifiers":[
        {
            "category":"Shopping",
            "subcategory":"Pharmacy",
            "type":"Retail Goods"
        }
    ],
    "sg:phone":"+1   ",
    "sg:postcode":"19335",
    "sg:province":"PA",
    "wof:name":"CVS",
    "wof:placetype":"venue"
},
  "geometry": {"coordinates":[-75.72386,39.999224],"type":"Point"}
}