{
  "type": "Feature",
  "properties": {
    "iso:country":"US",
    "sg:address":"500 E 24th St",
    "sg:city":"Chester",
    "sg:classifiers":[
        {
            "category":"Home & Garden",
            "subcategory":"Garden Supply",
            "type":"Retail Goods"
        }
    ],
    "sg:phone":"+1 610 876 8710",
    "sg:postcode":"19013",
    "sg:province":"PA",
    "sg:tags":[
        "fountain",
        "display"
    ],
    "wof:name":"St James Gardens",
    "wof:placetype":"venue"
},
  "geometry": {"coordinates":[-75.363159,39.869417],"type":"Point"}
}