{
  "type": "Feature",
  "properties": {
    "addr:full":"4940 N 5th St Philadelphia PA 19120",
    "addr:housenumber":"4940",
    "addr:postcode":"19120",
    "addr:street":"N 5Th St",
    "iso:country":"US",
    "sg:address":"4940 N 5th St",
    "sg:city":"Philadelphia",
    "sg:classifiers":[
        {
            "category":"Restaurant",
            "type":"Food & Drink"
        }
    ],
    "sg:phone":"+1 215 329 0861",
    "sg:postcode":"19120",
    "sg:province":"PA",
    "sg:tags":[
        "eating"
    ],
    "wof:name":"El Bochinche Restaurante",
    "wof:placetype":"venue"
},
  "geometry": {"coordinates":[-75.13249999999999,40.026798],"type":"Point"}
}