{
  "type": "Feature",
  "properties": {
    "iso:country":"US",
    "sg:address":"300 Bridge St Ste 1RIGHT",
    "sg:city":"Beaver",
    "sg:classifiers":[
        {
            "category":"Shopping",
            "subcategory":"Gifts & Souvenirs",
            "type":"Retail Goods"
        },
        {
            "category":"Shopping",
            "subcategory":"Crafts & Fabrics",
            "type":"Retail Goods"
        }
    ],
    "sg:phone":"+1 724 775 1335",
    "sg:postcode":"15009",
    "sg:province":"PA",
    "sg:tags":[
        "shop"
    ],
    "wof:name":"Inside The Attic",
    "wof:placetype":"venue"
},
  "geometry": {"coordinates":[-80.294708,40.700169],"type":"Point"}
}