{
  "type": "Feature",
  "properties": {
    "addr:full":"196 W Dubois Ave Du Bois PA 15801",
    "addr:housenumber":"196",
    "addr:postcode":"15801",
    "addr:street":"W Dubois Ave Du Bois",
    "iso:country":"US",
    "sg:address":"196 W Dubois Ave",
    "sg:city":"Du Bois",
    "sg:classifiers":[
        {
            "category":"Professional",
            "subcategory":"Accounting & Tax Preparation",
            "type":"Services"
        }
    ],
    "sg:phone":"+1 814 371 8187",
    "sg:postcode":"15801",
    "sg:province":"PA",
    "sg:tags":[
        "accountant"
    ],
    "wof:name":"Barber Financial Co Inc",
    "wof:placetype":"venue"
},
  "geometry": {"coordinates":[-78.760002,41.128553],"type":"Point"}
}