{
  "type": "Feature",
  "properties": {
    "iso:country":"US",
    "sg:address":"133 W High St",
    "sg:city":"Bellefonte",
    "sg:classifiers":[
        {
            "category":"Banks & Credit Unions",
            "subcategory":"Bank",
            "type":"Services"
        }
    ],
    "sg:phone":"+1 814 355 2515",
    "sg:postcode":"16823",
    "sg:province":"PA",
    "sg:website":"statefarm.com",
    "wof:name":"Stone George",
    "wof:placetype":"venue"
},
  "geometry": {"coordinates":[-77.778397,40.9119],"type":"Point"}
}