{
  "type": "Feature",
  "properties": {
    "iso:country":"US",
    "sg:address":"217 Carverton Rd",
    "sg:city":"Shavertown",
    "sg:classifiers":[
        {
            "category":"Restaurant",
            "type":"Food & Drink"
        }
    ],
    "sg:phone":"+1 570 696 4973",
    "sg:postcode":"18708",
    "sg:province":"PA",
    "sg:tags":[
        "delicatessen"
    ],
    "wof:name":"Charlies Country Deli",
    "wof:placetype":"venue"
},
  "geometry": {"coordinates":[-75.921558,41.311263],"type":"Point"}
}