{
  "type": "Feature",
  "properties": {
    "addr:full":"13971 Higby Hill Rd Townville PA 16360",
    "addr:housenumber":"13971",
    "addr:postcode":"16360",
    "addr:street":"Higby Hill Rd",
    "iso:country":"US",
    "sg:address":"13971 Higby Hill Rd",
    "sg:city":"Townville",
    "sg:phone":"+1   ",
    "sg:postcode":"16360",
    "sg:province":"PA",
    "sg:tags":[
        "farm",
        "grain",
        "cash"
    ],
    "wof:name":"Little Beefer Farms",
    "wof:placetype":"venue"
},
  "geometry": {"coordinates":[-79.890518,41.658082],"type":"Point"}
}