{
  "type": "Feature",
  "properties": {
    "addr:full":"1711 Newbold Ln Glenside PA 19038",
    "addr:housenumber":"1711",
    "addr:postcode":"19038",
    "addr:street":"Newbold Ln",
    "iso:country":"US",
    "sg:address":"1711 Newbold Ln",
    "sg:city":"Glenside",
    "sg:classifiers":[
        {
            "category":"Professional",
            "subcategory":"Accounting & Tax Preparation",
            "type":"Services"
        }
    ],
    "sg:phone":"+1   ",
    "sg:postcode":"19038",
    "sg:province":"PA",
    "wof:name":"Cutler Camra 1 Hr Photo Video",
    "wof:placetype":"venue"
},
  "geometry": {"coordinates":[-75.185721,40.096534],"type":"Point"}
}