{
  "type": "Feature",
  "properties": {
    "iso:country":"US",
    "sg:address":"318 Springdale Ave",
    "sg:city":"Hatboro",
    "sg:classifiers":[
        {
            "category":"Wholesale",
            "subcategory":"Machinery & Supplies",
            "type":"Manufacturing & Wholesale Goods"
        }
    ],
    "sg:phone":"+1 215 672 7465",
    "sg:postcode":"19040",
    "sg:province":"PA",
    "wof:name":"Doyle Machine Tool Sales Inc",
    "wof:placetype":"venue"
},
  "geometry": {"coordinates":[-75.095662,40.180654],"type":"Point"}
}