{
  "type": "Feature",
  "properties": {
    "iso:country":"US",
    "sg:address":"4560 Sweetwater Pl",
    "sg:city":"Allison Park",
    "sg:classifiers":[
        {
            "category":"Recreation",
            "type":"Entertainment"
        }
    ],
    "sg:phone":"+1   ",
    "sg:postcode":"15101",
    "sg:province":"PA",
    "wof:name":"Hearts Run Hunt Pony Club",
    "wof:placetype":"venue"
},
  "geometry": {"coordinates":[-79.917056,40.588502],"type":"Point"}
}