{
  "type": "Feature",
  "properties": {
    "iso:country":"US",
    "sg:address":"200 Tumbleweed Way",
    "sg:city":"Birdsboro",
    "sg:classifiers":[
        {
            "category":"Banks & Credit Unions",
            "subcategory":"Bank",
            "type":"Services"
        }
    ],
    "sg:phone":"+1   ",
    "sg:postcode":"19508",
    "sg:province":"PA",
    "sg:tags":[
        "mortgage"
    ],
    "wof:name":"Green Hills Morgage Company",
    "wof:placetype":"venue"
},
  "geometry": {"coordinates":[-75.887282,40.269818],"type":"Point"}
}