{
  "type": "Feature",
  "properties": {
    "iso:country":"US",
    "sg:address":"115 E Broad St",
    "sg:city":"Palmyra",
    "sg:classifiers":[
        {
            "category":"Arena",
            "subcategory":"Sports Club",
            "type":"Entertainment"
        }
    ],
    "sg:phone":"+1 717 838 9996",
    "sg:postcode":"17078",
    "sg:province":"PA",
    "sg:tags":[
        "soccer"
    ],
    "wof:name":"Lebanon Valley Slow Pitch Leag",
    "wof:placetype":"venue"
},
  "geometry": {"coordinates":[-76.59631299999999,40.31052],"type":"Point"}
}