{
  "type": "Feature",
  "properties": {
    "iso:country":"US",
    "sg:address":"1426 Lombard St",
    "sg:city":"Philadelphia",
    "sg:classifiers":[
        {
            "category":"Travel",
            "subcategory":"Travel Agent",
            "type":"Entertainment"
        }
    ],
    "sg:phone":"+1 215 735 1515",
    "sg:postcode":"19146",
    "sg:province":"PA",
    "sg:tags":[
        "agency",
        "services-commercial"
    ],
    "wof:name":"Travel At Dorch",
    "wof:placetype":"venue"
},
  "geometry": {"coordinates":[-75.16629,39.944783],"type":"Point"}
}