{
  "type": "Feature",
  "properties": {
    "iso:country":"US",
    "sg:address":"408 York Rd",
    "sg:city":"New Hope",
    "sg:classifiers":[
        {
            "category":"Real Estate",
            "subcategory":"Real Estate Agent",
            "type":"Services"
        }
    ],
    "sg:phone":"+1 215 862 0300",
    "sg:postcode":"18938",
    "sg:province":"PA",
    "sg:website":"www.cbhearthside.com",
    "wof:name":"Coldwell Banker",
    "wof:placetype":"venue"
},
  "geometry": {"coordinates":[-74.969908,40.361459],"type":"Point"}
}