{
  "type": "Feature",
  "properties": {
    "addr:full":"1309 Bridge St New Cumberland PA 17070",
    "addr:housenumber":"1309",
    "addr:postcode":"17070",
    "addr:street":"Bridge St",
    "iso:country":"US",
    "sg:address":"1309 Bridge St",
    "sg:city":"New Cumberland",
    "sg:classifiers":[
        {
            "category":"Professional",
            "subcategory":"Testing Lab",
            "type":"Services"
        }
    ],
    "sg:phone":"+1   ",
    "sg:postcode":"17070",
    "sg:province":"PA",
    "sg:tags":[
        "water",
        "supplier",
        "association",
        "for",
        "trade"
    ],
    "wof:name":"Pennsylvania Water Works Assoc",
    "wof:placetype":"venue"
},
  "geometry": {"coordinates":[-76.87595399999999,40.234506],"type":"Point"}
}