{
  "type": "Feature",
  "properties": {
    "iso:country":"US",
    "sg:address":"553 Elm Ave",
    "sg:city":"Freedom",
    "sg:classifiers":[
        {
            "category":"Railroad",
            "type":"Transportation"
        }
    ],
    "sg:phone":"+1   ",
    "sg:postcode":"15042",
    "sg:province":"PA",
    "sg:tags":[
        "operator",
        "line"
    ],
    "wof:name":"Chuck Rosenberger",
    "wof:placetype":"venue"
},
  "geometry": {"coordinates":[-80.252137,40.690126],"type":"Point"}
}