{
  "type": "Feature",
  "properties": {
    "addr:full":"1328 N Main St Butler PA 16001",
    "addr:housenumber":"1328",
    "addr:postcode":"16001",
    "addr:street":"N Main St",
    "iso:country":"US",
    "sg:address":"1328 N Main St",
    "sg:city":"Butler",
    "sg:classifiers":[
        {
            "category":"Personal",
            "subcategory":"Massage",
            "type":"Services"
        }
    ],
    "sg:phone":"+1 724 285 4381",
    "sg:postcode":"16001",
    "sg:province":"PA",
    "wof:name":"Kneading Relaxation",
    "wof:placetype":"venue"
},
  "geometry": {"coordinates":[-79.905306,40.890979],"type":"Point"}
}