{
  "type": "Feature",
  "properties": {
    "iso:country":"US",
    "sg:address":"30 Ferry St",
    "sg:city":"Leetsdale",
    "sg:classifiers":[
        {
            "category":"Government",
            "subcategory":"Office",
            "type":"Public Place"
        }
    ],
    "sg:phone":"+1 724 266 6069",
    "sg:postcode":"15056",
    "sg:province":"PA",
    "sg:tags":[
        "village"
    ],
    "wof:name":"Borough Garage",
    "wof:placetype":"venue"
},
  "geometry": {"coordinates":[-80.207217,40.563677],"type":"Point"}
}