{
  "type": "Feature",
  "properties": {
    "iso:country":"US",
    "sg:address":"37 N Chestnut St",
    "sg:city":"Annville",
    "sg:classifiers":[
        {
            "category":"Manufacturing",
            "subcategory":"Buildings",
            "type":"Manufacturing & Wholesale Goods"
        },
        {
            "category":"Building & Trades",
            "subcategory":"Construction",
            "type":"Services"
        }
    ],
    "sg:phone":"+1 717 395 8928",
    "sg:postcode":"17003",
    "sg:province":"PA",
    "sg:tags":[
        "home",
        "builder",
        "contractor"
    ],
    "wof:name":"Bohun S Home Improvement",
    "wof:placetype":"venue"
},
  "geometry": {"coordinates":[-76.520563,40.329172],"type":"Point"}
}