{
  "type": "Feature",
  "properties": {
    "addr:full":"45 Brown St Honesdale PA 18431",
    "addr:housenumber":"45",
    "addr:postcode":"18431",
    "addr:street":"Brown St",
    "iso:country":"US",
    "sg:address":"45 Brown St",
    "sg:city":"Honesdale",
    "sg:classifiers":[
        {
            "category":"Professional",
            "subcategory":"Business Services",
            "type":"Services"
        }
    ],
    "sg:phone":"+1 570 253 0441",
    "sg:postcode":"18431",
    "sg:province":"PA",
    "sg:tags":[
        "lingerie"
    ],
    "wof:name":"Rohr Lingerie Inc",
    "wof:placetype":"venue"
},
  "geometry": {"coordinates":[-75.245149,41.563838],"type":"Point"}
}