{
  "type": "Feature",
  "properties": {
    "iso:country":"US",
    "sg:address":"13799 Lincoln Way",
    "sg:city":"Irwin",
    "sg:classifiers":[
        {
            "category":"Health Services",
            "subcategory":"Nursing And Care Facility",
            "type":"Services"
        }
    ],
    "sg:phone":"+1   ",
    "sg:postcode":"15642",
    "sg:province":"PA",
    "sg:tags":[
        "personal"
    ],
    "wof:name":"Hidden Acre Personal Care Home",
    "wof:placetype":"venue"
},
  "geometry": {"coordinates":[-79.77006,40.32186],"type":"Point"}
}