{
  "type": "Feature",
  "properties": {
    "iso:country":"US",
    "sg:address":"193 Broad Ave Exd",
    "sg:city":"Duncansville",
    "sg:classifiers":[
        {
            "category":"Building & Trades",
            "subcategory":"Plumbing",
            "type":"Services"
        }
    ],
    "sg:phone":"+1 814 696 9780",
    "sg:postcode":"16635",
    "sg:province":"PA",
    "sg:tags":[
        "plumbing",
        "contractor"
    ],
    "wof:name":"Barton's Plumbing & Heating",
    "wof:placetype":"venue"
},
  "geometry": {"coordinates":[-78.44851300000001,40.455721],"type":"Point"}
}