{
  "type": "Feature",
  "properties": {
    "addr:full":"135 Baltimore Ave Media PA 19063",
    "addr:housenumber":"135",
    "addr:postcode":"19063",
    "addr:street":"Baltimore Ave",
    "iso:country":"US",
    "sg:address":"135 Baltimore Ave",
    "sg:city":"Media",
    "sg:classifiers":[
        {
            "category":"Recreation",
            "type":"Entertainment"
        }
    ],
    "sg:phone":"+1   ",
    "sg:postcode":"19063",
    "sg:province":"PA",
    "sg:tags":[
        "fitness",
        "physical",
        "facility"
    ],
    "wof:name":"Body Works - Karate Center",
    "wof:placetype":"venue"
},
  "geometry": {"coordinates":[-75.386213,39.916433],"type":"Point"}
}