{
  "type": "Feature",
  "properties": {
    "iso:country":"US",
    "sg:address":"140 Wheatfield Rd",
    "sg:city":"Sinking Spring",
    "sg:classifiers":[
        {
            "category":"Wholesale",
            "subcategory":"Machinery & Supplies",
            "type":"Manufacturing & Wholesale Goods"
        }
    ],
    "sg:phone":"+1 610 670 5565",
    "sg:postcode":"19608",
    "sg:province":"PA",
    "sg:tags":[
        "equipment",
        "oil",
        "handling"
    ],
    "wof:name":"Big E's",
    "wof:placetype":"venue"
},
  "geometry": {"coordinates":[-76.01641499999999,40.293902],"type":"Point"}
}