{
  "type": "Feature",
  "properties": {
    "addr:full":"3870 Newburg Rd Easton PA 18045",
    "addr:housenumber":"3870",
    "addr:postcode":"18045",
    "addr:street":"Newburg Rd",
    "iso:country":"US",
    "sg:address":"3870 Newburg Rd",
    "sg:city":"Easton",
    "sg:classifiers":[
        {
            "category":"Farming",
            "subcategory":"Farm",
            "type":"Manufacturing & Wholesale Goods"
        }
    ],
    "sg:phone":"+1   ",
    "sg:postcode":"18045",
    "sg:province":"PA",
    "sg:tags":[
        "crop",
        "general"
    ],
    "wof:name":"Harvey Meixell",
    "wof:placetype":"venue"
},
  "geometry": {"coordinates":[-75.293426,40.704602],"type":"Point"}
}