{
  "type": "Feature",
  "properties": {
    "iso:country":"US",
    "sg:address":"623 Swedesford Rd",
    "sg:city":"Frazer",
    "sg:classifiers":[
        {
            "category":"Health Services",
            "subcategory":"Optometrist",
            "type":"Services"
        }
    ],
    "sg:phone":"+1 610 644 9300",
    "sg:postcode":"19355",
    "sg:province":"PA",
    "wof:name":"Great Valley Eye Associates",
    "wof:placetype":"venue"
},
  "geometry": {"coordinates":[-75.57701299999999,40.042394],"type":"Point"}
}