{
  "type": "Feature",
  "properties": {
    "iso:country":"US",
    "sg:address":"2 E State St",
    "sg:city":"Albion",
    "sg:classifiers":[
        {
            "category":"Shopping",
            "subcategory":"Music",
            "type":"Retail Goods"
        }
    ],
    "sg:phone":"+1 814 756 5651",
    "sg:postcode":"16401",
    "sg:province":"PA",
    "wof:name":"Lake Video Distributors Inc",
    "wof:placetype":"venue"
},
  "geometry": {"coordinates":[-80.366342,41.890887],"type":"Point"}
}