{
  "type": "Feature",
  "properties": {
    "iso:country":"US",
    "sg:address":"29 W Airy St",
    "sg:city":"Norristown",
    "sg:classifiers":[
        {
            "category":"Health Services",
            "subcategory":"Optometrist",
            "type":"Services"
        }
    ],
    "sg:phone":"+1 610 279 4055",
    "sg:postcode":"19401",
    "sg:province":"PA",
    "wof:name":"Rami Abdallah OD",
    "wof:placetype":"venue"
},
  "geometry": {"coordinates":[-75.344554,40.116554],"type":"Point"}
}