{
  "type": "Feature",
  "properties": {
    "iso:country":"US",
    "sg:address":"740 Lysle Blvd",
    "sg:city":"Mckeesport",
    "sg:classifiers":[
        {
            "category":"Restaurant",
            "type":"Food & Drink"
        }
    ],
    "sg:menulink":"http://www.allmenus.com/pa/mckeesport/211352-kfc---kentucky-fried-chicken/menu/",
    "sg:phone":"+1 412 673 7957",
    "sg:postcode":"15132",
    "sg:province":"PA",
    "sg:tags":[
        "american",
        "chicken"
    ],
    "wof:name":"KFC - Kentucky Fried Chicken",
    "wof:placetype":"venue"
},
  "geometry": {"coordinates":[-79.85763,40.352153],"type":"Point"}
}