{
  "type": "Feature",
  "properties": {
    "addr:full":"2011 Cato Ave State College PA 16801",
    "addr:housenumber":"2011",
    "addr:postcode":"16801",
    "addr:street":"Cato Ave",
    "iso:country":"US",
    "sg:address":"2011 Cato Ave",
    "sg:city":"State College",
    "sg:classifiers":[
        {
            "category":"Manufacturing",
            "subcategory":"Printing",
            "type":"Manufacturing & Wholesale Goods"
        }
    ],
    "sg:phone":"+1 814 867 2222",
    "sg:postcode":"16801",
    "sg:province":"PA",
    "sg:tags":[
        "publisher"
    ],
    "sg:website":"www.pabusinesscentral.com",
    "wof:name":"Pennsylvania Business Central",
    "wof:placetype":"venue"
},
  "geometry": {"coordinates":[-77.880093,40.763024],"type":"Point"}
}