{
  "type": "Feature",
  "properties": {
    "iso:country":"US",
    "sg:address":"18 Sherwood Dr Ste D",
    "sg:city":"Bloomsburg",
    "sg:classifiers":[
        {
            "category":"Wholesale",
            "subcategory":"Medical Equipment & Supplies",
            "type":"Manufacturing & Wholesale Goods"
        }
    ],
    "sg:phone":"+1 570 784 5405",
    "sg:postcode":"17815",
    "sg:province":"PA",
    "sg:tags":[
        "assistive",
        "aid",
        "device",
        "hearing"
    ],
    "sg:website":"http://www.miracle-ear.com",
    "wof:name":"Miracle-Ear",
    "wof:placetype":"venue"
},
  "geometry": {"coordinates":[-76.423485,41.001783],"type":"Point"}
}