{
  "type": "Feature",
  "properties": {
    "iso:country":"US",
    "sg:address":"1105 Cottman Ave",
    "sg:city":"Philadelphia",
    "sg:classifiers":[
        {
            "category":"Home & Garden",
            "subcategory":"Building Materials",
            "type":"Retail Goods"
        }
    ],
    "sg:phone":"+1   ",
    "sg:postcode":"19111",
    "sg:province":"PA",
    "wof:name":"Best Doors",
    "wof:placetype":"venue"
},
  "geometry": {"coordinates":[-75.081523,40.060219],"type":"Point"}
}