{
  "type": "Feature",
  "properties": {
    "iso:country":"US",
    "sg:address":"845 Perry Hwy",
    "sg:city":"Pittsburgh",
    "sg:classifiers":[
        {
            "category":"Education",
            "subcategory":"Special Training",
            "type":"Public Place"
        }
    ],
    "sg:phone":"+1 412 364 9965",
    "sg:postcode":"15229",
    "sg:province":"PA",
    "sg:tags":[
        "center"
    ],
    "wof:name":"Educational Building",
    "wof:placetype":"venue"
},
  "geometry": {"coordinates":[-80.03588000000001,40.532169],"type":"Point"}
}