{
  "type": "Feature",
  "properties": {
    "iso:country":"US",
    "sg:address":"5 Stonecroft Dr",
    "sg:city":"Easton",
    "sg:classifiers":[
        {
            "category":"Food & Beverages",
            "subcategory":"Specialty",
            "type":"Retail Goods"
        }
    ],
    "sg:phone":"+1 610 258 1894",
    "sg:postcode":"18045",
    "sg:province":"PA",
    "sg:tags":[
        "supplement",
        "vitamin"
    ],
    "sg:website":"http://www.nutritek.net",
    "wof:name":"Nutritional Technologies",
    "wof:placetype":"venue"
},
  "geometry": {"coordinates":[-75.251501,40.695269],"type":"Point"}
}