{
  "type": "Feature",
  "properties": {
    "iso:country":"US",
    "sg:address":"690 Shaffer Rd",
    "sg:city":"Du Bois",
    "sg:classifiers":[
        {
            "category":"Restaurant",
            "type":"Food & Drink"
        }
    ],
    "sg:menulink":"http://www.allmenus.com/pa/sandy/66174-dominos-pizza/menu/",
    "sg:phone":"+1 814 371 3300",
    "sg:postcode":"15801",
    "sg:province":"PA",
    "sg:tags":[
        "american",
        "wing",
        "pizza"
    ],
    "wof:name":"Domino's Pizza",
    "wof:placetype":"venue"
},
  "geometry": {"coordinates":[-78.72919899999999,41.122066],"type":"Point"}
}