{
  "type": "Feature",
  "properties": {
    "iso:country":"US",
    "sg:address":"42 S 15th St",
    "sg:city":"Philadelphia",
    "sg:classifiers":[
        {
            "category":"Professional",
            "subcategory":"Employment Agencies",
            "type":"Services"
        }
    ],
    "sg:phone":"+1 215 564 0700",
    "sg:postcode":"19102",
    "sg:province":"PA",
    "wof:name":"National Personnel Assocs",
    "wof:placetype":"venue"
},
  "geometry": {"coordinates":[-75.165497,39.951401],"type":"Point"}
}