{
  "type": "Feature",
  "properties": {
    "addr:full":"2345 Blair Mill Rd Willow Grove PA 19090",
    "addr:housenumber":"2345",
    "addr:postcode":"19090",
    "addr:street":"Blair Mill Rd",
    "iso:country":"US",
    "sg:address":"2345 Blair Mill Rd",
    "sg:city":"Willow Grove",
    "sg:classifiers":[
        {
            "category":"Real Estate",
            "subcategory":"Real Estate Agent",
            "type":"Services"
        }
    ],
    "sg:phone":"+1   ",
    "sg:postcode":"19090",
    "sg:province":"PA",
    "sg:tags":[
        "appraiser"
    ],
    "wof:name":"Wolford Real Estate Services",
    "wof:placetype":"venue"
},
  "geometry": {"coordinates":[-75.14016100000001,40.159657],"type":"Point"}
}