{
  "type": "Feature",
  "properties": {
    "addr:full":"1303 Main St Brockway PA 15824",
    "addr:housenumber":"1303",
    "addr:postcode":"15824",
    "addr:street":"Main St",
    "iso:country":"US",
    "sg:address":"1303 Main St",
    "sg:city":"Brockway",
    "sg:classifiers":[
        {
            "category":"Professional",
            "type":"Services"
        }
    ],
    "sg:phone":"+1   ",
    "sg:postcode":"15824",
    "sg:province":"PA",
    "wof:name":"Rachel Kuhar",
    "wof:placetype":"venue"
},
  "geometry": {"coordinates":[-78.787492,41.247081],"type":"Point"}
}