{
  "type": "Feature",
  "properties": {
    "iso:country":"US",
    "sg:address":"15233 Molly Pitcher Hwy",
    "sg:city":"Greencastle",
    "sg:classifiers":[
        {
            "category":"Retail",
            "subcategory":"Auto Repair",
            "type":"Services"
        }
    ],
    "sg:phone":"+1 717 597 4565",
    "sg:postcode":"17225",
    "sg:province":"PA",
    "sg:tags":[
        "truck"
    ],
    "wof:name":"Higman Truck & Trailer Repair",
    "wof:placetype":"venue"
},
  "geometry": {"coordinates":[-77.724811,39.729734],"type":"Point"}
}