{
  "type": "Feature",
  "properties": {
    "addr:full":"425 Highview Dr Wayne PA 19087",
    "addr:housenumber":"425",
    "addr:postcode":"19087",
    "addr:street":"Highview Dr",
    "iso:country":"US",
    "sg:address":"425 Highview Dr",
    "sg:city":"Wayne",
    "sg:classifiers":[
        {
            "category":"Building & Trades",
            "subcategory":"Construction",
            "type":"Services"
        }
    ],
    "sg:phone":"+1   ",
    "sg:postcode":"19087",
    "sg:province":"PA",
    "sg:tags":[
        "residential",
        "commercial",
        "renovation",
        "contractor"
    ],
    "wof:name":"Crj Construction Company",
    "wof:placetype":"venue"
},
  "geometry": {"coordinates":[-75.35862299999999,40.065056],"type":"Point"}
}