{
  "type": "Feature",
  "properties": {
    "iso:country":"US",
    "sg:address":"7 Conestoga St",
    "sg:city":"Pittsburgh",
    "sg:classifiers":[
        {
            "category":"Professional",
            "subcategory":"Advertising",
            "type":"Services"
        }
    ],
    "sg:phone":"+1   ",
    "sg:postcode":"15204",
    "sg:province":"PA",
    "sg:tags":[
        "motion",
        "production",
        "agency"
    ],
    "wof:name":"Pittsburgh Film Office",
    "wof:placetype":"venue"
},
  "geometry": {"coordinates":[-80.044107,40.453667],"type":"Point"}
}