{
  "type": "Feature",
  "properties": {
    "iso:country":"US",
    "sg:address":"1 W Main St",
    "sg:city":"Collegeville",
    "sg:classifiers":[
        {
            "category":"Building & Trades",
            "subcategory":"Electrical",
            "type":"Services"
        },
        {
            "category":"Building & Trades",
            "subcategory":"Plumbing",
            "type":"Services"
        }
    ],
    "sg:phone":"+1 610 831 9661",
    "sg:postcode":"19426",
    "sg:province":"PA",
    "sg:tags":[
        "electrical",
        "humidifying",
        "apparatus",
        "contractor"
    ],
    "wof:name":"Techquip Group Inc",
    "wof:placetype":"venue"
},
  "geometry": {"coordinates":[-75.471014,40.196662],"type":"Point"}
}