{
  "type": "Feature",
  "properties": {
    "iso:country":"US",
    "sg:address":"7120 Sladek Rd",
    "sg:city":"New Hope",
    "sg:classifiers":[
        {
            "category":"Professional",
            "subcategory":"Employment Agencies",
            "type":"Services"
        }
    ],
    "sg:phone":"+1 215 297 5009",
    "sg:postcode":"18938",
    "sg:province":"PA",
    "wof:name":"Dental Employment Services",
    "wof:placetype":"venue"
},
  "geometry": {"coordinates":[-75.062482,40.406859],"type":"Point"}
}