{
  "type": "Feature",
  "properties": {
    "iso:country":"US",
    "sg:address":"417 W Main St",
    "sg:city":"Smethport",
    "sg:classifiers":[
        {
            "category":"Organizations",
            "subcategory":"Community Association",
            "type":"Services"
        }
    ],
    "sg:phone":"+1 814 887 5151",
    "sg:postcode":"16749",
    "sg:province":"PA",
    "sg:tags":[
        "military"
    ],
    "wof:name":"American Legion",
    "wof:placetype":"venue"
},
  "geometry": {"coordinates":[-78.445635,41.809494],"type":"Point"}
}