{
  "type": "Feature",
  "properties": {
    "iso:country":"US",
    "sg:address":"720 N 4th St",
    "sg:city":"Philadelphia",
    "sg:classifiers":[
        {
            "category":"Wholesale",
            "subcategory":"Seafood",
            "type":"Manufacturing & Wholesale Goods"
        }
    ],
    "sg:phone":"+1   ",
    "sg:postcode":"19123",
    "sg:province":"PA",
    "wof:name":"Pride of The Sea Inc",
    "wof:placetype":"venue"
},
  "geometry": {"coordinates":[-75.144481,39.963741],"type":"Point"}
}