{
  "type": "Feature",
  "properties": {
    "addr:full":"209 Chestnut St Philadelphia PA 19106",
    "addr:housenumber":"209",
    "addr:postcode":"19106",
    "addr:street":"Chestnut St",
    "iso:country":"US",
    "sg:address":"209 Chestnut St",
    "sg:city":"Philadelphia",
    "sg:classifiers":[
        {
            "category":"Building & Trades",
            "subcategory":"Locksmith",
            "type":"Services"
        }
    ],
    "sg:phone":"+1 267 702 1013",
    "sg:postcode":"19106",
    "sg:province":"PA",
    "sg:tags":[
        "key"
    ],
    "wof:name":"A 1 Emergency Locksmith",
    "wof:placetype":"venue"
},
  "geometry": {"coordinates":[-75.14449399999999,39.948572],"type":"Point"}
}