{
  "type": "Feature",
  "properties": {
    "iso:country":"US",
    "sg:address":"1801 Market St",
    "sg:city":"Philadelphia",
    "sg:classifiers":[
        {
            "category":"Coffee & Tea",
            "type":"Food & Drink"
        }
    ],
    "sg:menulink":"http://www.allmenus.com/pa/philadelphia/125215-starbucks-coffee/menu/",
    "sg:phone":"+1 215 569 4223",
    "sg:postcode":"19103",
    "sg:province":"PA",
    "sg:tags":[
        "american"
    ],
    "wof:name":"Starbucks Coffee",
    "wof:placetype":"venue"
},
  "geometry": {"coordinates":[-75.16996,39.953183],"type":"Point"}
}