{
  "type": "Feature",
  "properties": {
    "iso:country":"US",
    "sg:address":"738 Main St",
    "sg:city":"Stroudsburg",
    "sg:classifiers":[
        {
            "category":"Real Estate",
            "subcategory":"Real Estate Services",
            "type":"Services"
        },
        {
            "category":"Insurance",
            "subcategory":"Insurance Agent",
            "type":"Services"
        }
    ],
    "sg:phone":"+1 570 424 6757",
    "sg:postcode":"18360",
    "sg:province":"PA",
    "sg:tags":[
        "abstract",
        "title"
    ],
    "wof:name":"National Land Transfer Corp",
    "wof:placetype":"venue"
},
  "geometry": {"coordinates":[-75.194811,40.985237],"type":"Point"}
}