{
  "type": "Feature",
  "properties": {
    "iso:country":"US",
    "sg:address":"1133 Beechwood Ave",
    "sg:city":"Lansdale",
    "sg:classifiers":[
        {
            "category":"Arts & Performance",
            "subcategory":"Theater",
            "type":"Entertainment"
        }
    ],
    "sg:phone":"+1 215 393 3073",
    "sg:postcode":"19446",
    "sg:province":"PA",
    "sg:tags":[
        "live",
        "music"
    ],
    "wof:name":"Sound FX Dee Jay's",
    "wof:placetype":"venue"
},
  "geometry": {"coordinates":[-75.296623,40.250535],"type":"Point"}
}