{
  "type": "Feature",
  "properties": {
    "iso:country":"US",
    "sg:address":"11695 Penn Hills Dr",
    "sg:city":"Pittsburgh",
    "sg:classifiers":[
        {
            "category":"Retail",
            "subcategory":"Laundry & Dry Cleaning",
            "type":"Services"
        }
    ],
    "sg:phone":"+1 412 731 8388",
    "sg:postcode":"15235",
    "sg:province":"PA",
    "sg:tags":[
        "cleaners"
    ],
    "wof:name":"Frank & John's Cleaners Inc",
    "wof:placetype":"venue"
},
  "geometry": {"coordinates":[-79.82729500000001,40.465421],"type":"Point"}
}