{
  "type": "Feature",
  "properties": {
    "addr:full":"237 Shirley Rd Upper Darby PA 19082",
    "addr:housenumber":"237",
    "addr:postcode":"19082",
    "addr:street":"Shirley Rd",
    "iso:country":"US",
    "sg:address":"237 Shirley Rd",
    "sg:city":"Upper Darby",
    "sg:classifiers":[
        {
            "category":"Retail",
            "subcategory":"Auto Repair",
            "type":"Services"
        }
    ],
    "sg:phone":"+1   ",
    "sg:postcode":"19082",
    "sg:province":"PA",
    "sg:tags":[
        "automotive"
    ],
    "wof:name":"R A Lube Repair",
    "wof:placetype":"venue"
},
  "geometry": {"coordinates":[-75.264872,39.955579],"type":"Point"}
}