{
  "type": "Feature",
  "properties": {
    "addr:full":"2642 Glenwood Park Ave Erie PA 16508",
    "addr:housenumber":"2642",
    "addr:postcode":"16508",
    "addr:street":"Glenwood Park Ave",
    "iso:country":"US",
    "sg:address":"2642 Glenwood Park Ave",
    "sg:city":"Erie",
    "sg:classifiers":[
        {
            "category":"Health Services",
            "subcategory":"Health Practitioner",
            "type":"Services"
        }
    ],
    "sg:phone":"+1   ",
    "sg:postcode":"16508",
    "sg:province":"PA",
    "wof:name":"Alpha Occupational Therapy",
    "wof:placetype":"venue"
},
  "geometry": {"coordinates":[-80.073601,42.110266],"type":"Point"}
}