{
  "type": "Feature",
  "properties": {
    "iso:country":"US",
    "sg:address":"1600 Nottingham Dr",
    "sg:city":"Hummelstown",
    "sg:classifiers":[
        {
            "category":"Professional",
            "subcategory":"Employment Agencies",
            "type":"Services"
        }
    ],
    "sg:phone":"+1   ",
    "sg:postcode":"17036",
    "sg:province":"PA",
    "sg:tags":[
        "help",
        "supply"
    ],
    "wof:name":"Terry Naccarelli",
    "wof:placetype":"venue"
},
  "geometry": {"coordinates":[-76.68736199999999,40.234543],"type":"Point"}
}