{
  "type": "Feature",
  "properties": {
    "iso:country":"US",
    "sg:address":"29 W Main St",
    "sg:city":"Galeton",
    "sg:classifiers":[
        {
            "category":"Travel",
            "subcategory":"Hotels & Motels",
            "type":"Entertainment"
        }
    ],
    "sg:phone":"+1   ",
    "sg:postcode":"16922",
    "sg:province":"PA",
    "sg:tags":[
        "operation"
    ],
    "wof:name":"Oxyoke Inn",
    "wof:placetype":"venue"
},
  "geometry": {"coordinates":[-77.643103,41.735559],"type":"Point"}
}