{
  "type": "Feature",
  "properties": {
    "iso:country":"US",
    "sg:address":"110 Woodland Rd",
    "sg:city":"Wyomissing",
    "sg:classifiers":[
        {
            "category":"Education",
            "subcategory":"School",
            "type":"Public Place"
        }
    ],
    "sg:phone":"+1 610 378 9431",
    "sg:postcode":"19610",
    "sg:province":"PA",
    "wof:name":"Wyomissing Hills Elem School",
    "wof:placetype":"venue"
},
  "geometry": {"coordinates":[-75.97734800000001,40.334952],"type":"Point"}
}