{
  "type": "Feature",
  "properties": {
    "iso:country":"US",
    "sg:address":"814 S 15th St",
    "sg:city":"Philadelphia",
    "sg:classifiers":[
        {
            "category":"Health Services",
            "subcategory":"Doctor",
            "type":"Services"
        }
    ],
    "sg:phone":"+1 215 732 1372",
    "sg:postcode":"19146",
    "sg:province":"PA",
    "sg:tags":[
        "medical",
        "group",
        "insurance"
    ],
    "wof:name":"Wellness Of You",
    "wof:placetype":"venue"
},
  "geometry": {"coordinates":[-75.167879,39.940612],"type":"Point"}
}