{
  "type": "Feature",
  "properties": {
    "addr:full":"139 Sycamore Rd Havertown PA 19083",
    "addr:housenumber":"139",
    "addr:postcode":"19083",
    "addr:street":"Sycamore Rd",
    "iso:country":"US",
    "sg:address":"139 Sycamore Rd",
    "sg:city":"Havertown",
    "sg:classifiers":[
        {
            "category":"Professional",
            "subcategory":"Research",
            "type":"Services"
        }
    ],
    "sg:phone":"+1 610 853 2799",
    "sg:postcode":"19083",
    "sg:province":"PA",
    "sg:tags":[
        "market",
        "analysis"
    ],
    "sg:website":"www.callahanresearch.com",
    "wof:name":"Callahan Research",
    "wof:placetype":"venue"
},
  "geometry": {"coordinates":[-75.311657,39.974763],"type":"Point"}
}