{
  "type": "Feature",
  "properties": {
    "addr:full":"2212 Perkiomen Ave Reading PA 19606",
    "addr:postcode":"2212;19606",
    "addr:street":"Perkiomen Ave",
    "iso:country":"US",
    "sg:address":"2212 Perkiomen Ave",
    "sg:city":"Reading",
    "sg:classifiers":[
        {
            "category":"Recreation",
            "subcategory":"Picnic Area",
            "type":"Entertainment"
        },
        {
            "category":"Community Center",
            "type":"Public Place"
        }
    ],
    "sg:phone":"+1 610 370 1999",
    "sg:postcode":"19606",
    "sg:province":"PA",
    "sg:tags":[
        "amusement",
        "arcade"
    ],
    "wof:name":"Eastern Arts & Holistic Health",
    "wof:placetype":"venue"
},
  "geometry": {"coordinates":[-75.89365100000001,40.327792],"type":"Point"}
}