{
  "type": "Feature",
  "properties": {
    "iso:country":"US",
    "sg:address":"163 Kutz Rd",
    "sg:city":"Carlisle",
    "sg:classifiers":[
        {
            "category":"Professional",
            "subcategory":"Detective & Security Services",
            "type":"Services"
        }
    ],
    "sg:phone":"+1 717 776 4041",
    "sg:postcode":"17015",
    "sg:province":"PA",
    "sg:tags":[
        "information",
        "bureau"
    ],
    "wof:name":"R. & C. Mowing Svc.",
    "wof:placetype":"venue"
},
  "geometry": {"coordinates":[-77.33313699999999,40.138056],"type":"Point"}
}