{
  "type": "Feature",
  "properties": {
    "iso:country":"US",
    "sg:address":"65 Interstate Pkwy",
    "sg:city":"Bradford",
    "sg:classifiers":[
        {
            "category":"Shopping",
            "subcategory":"Clothing, Apparel, & Fashions",
            "type":"Retail Goods"
        }
    ],
    "sg:phone":"+1 814 368 4495",
    "sg:postcode":"16701",
    "sg:province":"PA",
    "sg:tags":[
        "pattern",
        "maker"
    ],
    "wof:name":"Austin Pattern Work",
    "wof:placetype":"venue"
},
  "geometry": {"coordinates":[-78.658279,41.958456],"type":"Point"}
}