{
  "type": "Feature",
  "properties": {
    "iso:country":"US",
    "sg:address":"516 Lackawanna Ave",
    "sg:city":"Scranton",
    "sg:classifiers":[
        {
            "category":"Wholesale",
            "subcategory":"Hardware",
            "type":"Manufacturing & Wholesale Goods"
        }
    ],
    "sg:phone":"+1 570 347 3391",
    "sg:postcode":"18503",
    "sg:province":"PA",
    "sg:tags":[
        "equipment",
        "heating",
        "system"
    ],
    "wof:name":"Heberger's Wholesale Heating",
    "wof:placetype":"venue"
},
  "geometry": {"coordinates":[-75.663937,41.406012],"type":"Point"}
}