{
  "type": "Feature",
  "properties": {
    "iso:country":"US",
    "sg:address":"209 E Locust St",
    "sg:city":"Clearfield",
    "sg:classifiers":[
        {
            "category":"Government",
            "subcategory":"Office",
            "type":"Public Place"
        }
    ],
    "sg:phone":"+1   ",
    "sg:postcode":"16830",
    "sg:province":"PA",
    "sg:tags":[
        "job",
        "center"
    ],
    "wof:name":"Clearfield Job Center",
    "wof:placetype":"venue"
},
  "geometry": {"coordinates":[-78.43793100000001,41.023172],"type":"Point"}
}