{
  "type": "Feature",
  "properties": {
    "iso:country":"US",
    "sg:address":"1129 Leishman Ave",
    "sg:city":"New Kensington",
    "sg:classifiers":[
        {
            "category":"Education",
            "subcategory":"School",
            "type":"Public Place"
        }
    ],
    "sg:phone":"+1   ",
    "sg:postcode":"15068",
    "sg:province":"PA",
    "wof:name":"Saint Josephs School",
    "wof:placetype":"venue"
},
  "geometry": {"coordinates":[-79.762635,40.569598],"type":"Point"}
}