{
  "type": "Feature",
  "properties": {
    "iso:country":"US",
    "sg:address":"154 Walnut St",
    "sg:city":"King Of Prussia",
    "sg:classifiers":[
        {
            "category":"Manufacturing",
            "subcategory":"Printing",
            "type":"Manufacturing & Wholesale Goods"
        }
    ],
    "sg:phone":"+1   ",
    "sg:postcode":"19406",
    "sg:province":"PA",
    "sg:tags":[
        "newspaper"
    ],
    "wof:name":"35th Anniversary Corvette",
    "wof:placetype":"venue"
},
  "geometry": {"coordinates":[-75.348495,40.097499],"type":"Point"}
}