{
  "type": "Feature",
  "properties": {
    "addr:full":"433 Allison Ave Allison PA 15413",
    "addr:housenumber":"433",
    "addr:postcode":"15413",
    "addr:street":"Allison Ave",
    "iso:country":"US",
    "sg:address":"433 Allison Ave",
    "sg:city":"Allison",
    "sg:classifiers":[
        {
            "category":"Professional",
            "subcategory":"Detective & Security Services",
            "type":"Services"
        }
    ],
    "sg:phone":"+1 724 785 6517",
    "sg:postcode":"15413",
    "sg:province":"PA",
    "sg:tags":[
        "information",
        "bureau"
    ],
    "wof:name":"Bills Drafting Service",
    "wof:placetype":"venue"
},
  "geometry": {"coordinates":[-79.877922,39.985191],"type":"Point"}
}