{
  "type": "Feature",
  "properties": {
    "iso:country":"US",
    "sg:address":"255 Yoder Rd",
    "sg:city":"Harleysville",
    "sg:classifiers":[
        {
            "category":"Manufacturing",
            "subcategory":"Tools & Machinery",
            "type":"Manufacturing & Wholesale Goods"
        }
    ],
    "sg:phone":"+1 215 256 1551",
    "sg:postcode":"19438",
    "sg:province":"PA",
    "sg:tags":[
        "machine",
        "shop"
    ],
    "wof:name":"Keystone Machine and Tool Co",
    "wof:placetype":"venue"
},
  "geometry": {"coordinates":[-75.358571,40.274428],"type":"Point"}
}