{
  "type": "Feature",
  "properties": {
    "iso:country":"US",
    "sg:address":"54 Great Oak Dr",
    "sg:city":"Southampton",
    "sg:classifiers":[
        {
            "category":"Building & Trades",
            "subcategory":"Construction",
            "type":"Services"
        }
    ],
    "sg:phone":"+1   ",
    "sg:postcode":"18966",
    "sg:province":"PA",
    "sg:tags":[
        "house"
    ],
    "wof:name":"Hamm Michael Home Improvement",
    "wof:placetype":"venue"
},
  "geometry": {"coordinates":[-75.02646300000001,40.206211],"type":"Point"}
}