{
  "type": "Feature",
  "properties": {
    "iso:country":"US",
    "sg:address":"4538 Old York Rd",
    "sg:city":"Philadelphia",
    "sg:classifiers":[
        {
            "category":"Personal",
            "subcategory":"Beauty Salon",
            "type":"Services"
        }
    ],
    "sg:phone":"+1 215 455 3120",
    "sg:postcode":"19140",
    "sg:province":"PA",
    "wof:name":"Shear Perfection",
    "wof:placetype":"venue"
},
  "geometry": {"coordinates":[-75.147121,40.022223],"type":"Point"}
}