{
  "type": "Feature",
  "properties": {
    "iso:country":"US",
    "sg:address":"822 Marietta Ave Ste 21",
    "sg:city":"Lancaster",
    "sg:classifiers":[
        {
            "category":"Health Services",
            "subcategory":"Dentist",
            "type":"Services"
        }
    ],
    "sg:phone":"+1 717 393 5055",
    "sg:postcode":"17603",
    "sg:province":"PA",
    "sg:tags":[
        "dentists-oral",
        "maxillofacial",
        "denture",
        "dentists-prosthodontists",
        "dentists-orthodontists",
        "dentistry",
        "implant",
        "surgery",
        "dentists-implantology"
    ],
    "wof:name":"Ethel A Esianor-Mitchual Dds",
    "wof:placetype":"venue"
},
  "geometry": {"coordinates":[-76.321416,40.039773],"type":"Point"}
}