{
  "type": "Feature",
  "properties": {
    "iso:country":"US",
    "sg:address":"631 W Orange St",
    "sg:city":"Lititz",
    "sg:phone":"+1 717 626 9797",
    "sg:postcode":"17543",
    "sg:province":"PA",
    "sg:tags":[
        "oil"
    ],
    "wof:name":"Penn Fuel Oil Co",
    "wof:placetype":"venue"
},
  "geometry": {"coordinates":[-76.32971999999999,40.153807],"type":"Point"}
}