{
  "type": "Feature",
  "properties": {
    "addr:full":"2028 Willow Street Pike Lancaster PA 17602",
    "addr:housenumber":"2028",
    "addr:postcode":"17602",
    "addr:street":"Willow Street Pike",
    "iso:country":"US",
    "sg:address":"2028 Willow Street Pike",
    "sg:city":"Lancaster",
    "sg:classifiers":[
        {
            "category":"Building & Trades",
            "subcategory":"Construction",
            "type":"Services"
        }
    ],
    "sg:phone":"+1 717 299 4259",
    "sg:postcode":"17602",
    "sg:province":"PA",
    "sg:tags":[
        "hanging",
        "contractor"
    ],
    "wof:name":"Nagle Painting",
    "wof:placetype":"venue"
},
  "geometry": {"coordinates":[-76.294104,40.003846],"type":"Point"}
}