{
  "type": "Feature",
  "properties": {
    "iso:country":"US",
    "sg:address":"4338 Old Orchard Rd",
    "sg:city":"York",
    "sg:classifiers":[
        {
            "category":"Personal",
            "subcategory":"Beauty Salon",
            "type":"Services"
        }
    ],
    "sg:phone":"+1 717 755 0707",
    "sg:postcode":"17402",
    "sg:province":"PA",
    "wof:name":"Casa De Bella",
    "wof:placetype":"venue"
},
  "geometry": {"coordinates":[-76.619867,39.980561],"type":"Point"}
}