{
  "type": "Feature",
  "properties": {
    "iso:country":"US",
    "sg:address":"9 Lake Rd W",
    "sg:city":"Bear Creek",
    "sg:classifiers":[
        {
            "category":"Social Services",
            "type":"Services"
        }
    ],
    "sg:phone":"+1 570 472 3302",
    "sg:postcode":"18602",
    "sg:province":"PA",
    "sg:tags":[
        "instruction",
        "health",
        "care"
    ],
    "wof:name":"R S Group",
    "wof:placetype":"venue"
},
  "geometry": {"coordinates":[-75.757099,41.181715],"type":"Point"}
}