{
  "type": "Feature",
  "properties": {
    "addr:full":"242 Washington St Morrisville PA 19067",
    "addr:housenumber":"242",
    "addr:postcode":"19067",
    "addr:street":"Washington St",
    "iso:country":"US",
    "sg:address":"242 Washington St",
    "sg:city":"Morrisville",
    "sg:classifiers":[
        {
            "category":"Health Services",
            "subcategory":"Nursing And Care Facility",
            "type":"Services"
        }
    ],
    "sg:phone":"+1   ",
    "sg:postcode":"19067",
    "sg:province":"PA",
    "sg:tags":[
        "intermediate"
    ],
    "wof:name":"Augustin Personal Care Homes",
    "wof:placetype":"venue"
},
  "geometry": {"coordinates":[-74.77076700000001,40.203864],"type":"Point"}
}