{
  "type": "Feature",
  "properties": {
    "iso:country":"US",
    "sg:address":"951 1st Ave",
    "sg:city":"Coraopolis",
    "sg:classifiers":[
        {
            "category":"Real Estate",
            "subcategory":"Real Estate Agent",
            "type":"Services"
        }
    ],
    "sg:phone":"+1 412 262 5522",
    "sg:postcode":"15108",
    "sg:province":"PA",
    "sg:tags":[
        "property",
        "commercial",
        "apt"
    ],
    "wof:name":"Coraopolis Towers",
    "wof:placetype":"venue"
},
  "geometry": {"coordinates":[-80.163353,40.520847],"type":"Point"}
}