{
  "type": "Feature",
  "properties": {
    "iso:country":"US",
    "sg:address":"5828 Memorial Rd",
    "sg:city":"Allentown",
    "sg:classifiers":[
        {
            "category":"Travel",
            "subcategory":"Hotels & Motels",
            "type":"Entertainment"
        }
    ],
    "sg:phone":"+1 610 395 3331",
    "sg:postcode":"18104",
    "sg:province":"PA",
    "wof:name":"Lehigh Motor Inn",
    "wof:placetype":"venue"
},
  "geometry": {"coordinates":[-75.589732,40.591182],"type":"Point"}
}