{
  "type": "Feature",
  "properties": {
    "iso:country":"US",
    "sg:address":"5501 3rd St",
    "sg:city":"Verona",
    "sg:classifiers":[
        {
            "category":"Organizations",
            "subcategory":"Religious Organization",
            "type":"Services"
        }
    ],
    "sg:phone":"+1   ",
    "sg:postcode":"15147",
    "sg:province":"PA",
    "wof:name":"Rosedale United Methdst Church",
    "wof:placetype":"venue"
},
  "geometry": {"coordinates":[-79.83987999999999,40.483737],"type":"Point"}
}