{
  "type": "Feature",
  "properties": {
    "addr:full":"8631 Perch Ln Philadelphia PA 19136",
    "addr:housenumber":"8631",
    "addr:postcode":"19136",
    "addr:street":"Perch Ln",
    "iso:country":"US",
    "sg:address":"8631 Perch Ln",
    "sg:city":"Philadelphia",
    "sg:classifiers":[
        {
            "category":"Building & Trades",
            "subcategory":"Construction",
            "type":"Services"
        }
    ],
    "sg:phone":"+1 215 338 5147",
    "sg:postcode":"19136",
    "sg:province":"PA",
    "sg:tags":[
        "painter"
    ],
    "wof:name":"Francine Haddow",
    "wof:placetype":"venue"
},
  "geometry": {"coordinates":[-75.01826800000001,40.053809],"type":"Point"}
}