{
  "type": "Feature",
  "properties": {
    "iso:country":"US",
    "sg:address":"18 W State St",
    "sg:city":"Doylestown",
    "sg:classifiers":[
        {
            "category":"Communications",
            "type":"Services"
        }
    ],
    "sg:phone":"+1 215 348 7766",
    "sg:postcode":"18901",
    "sg:province":"PA",
    "sg:tags":[
        "web",
        "design"
    ],
    "wof:name":"C W Cameron",
    "wof:placetype":"venue"
},
  "geometry": {"coordinates":[-75.13069900000001,40.309898],"type":"Point"}
}