{
  "type": "Feature",
  "properties": {
    "iso:country":"US",
    "sg:address":"580 N Main St",
    "sg:city":"Wilkes Barre",
    "sg:classifiers":[
        {
            "category":"Professional",
            "subcategory":"Accounting & Tax Preparation",
            "type":"Services"
        }
    ],
    "sg:phone":"+1 570 822 2155",
    "sg:postcode":"18705",
    "sg:province":"PA",
    "sg:tags":[
        "accountant"
    ],
    "wof:name":"Grey & Assoc",
    "wof:placetype":"venue"
},
  "geometry": {"coordinates":[-75.84041499999999,41.287887],"type":"Point"}
}