{
  "type": "Feature",
  "properties": {
    "iso:country":"US",
    "sg:address":"3106 Vernon Ave",
    "sg:city":"Pittsburgh",
    "sg:classifiers":[
        {
            "category":"Professional",
            "subcategory":"Management & Consulting",
            "type":"Services"
        }
    ],
    "sg:phone":"+1   ",
    "sg:postcode":"15227",
    "sg:province":"PA",
    "sg:tags":[
        "retail",
        "direct",
        "sales"
    ],
    "wof:name":"Josies Enterprises",
    "wof:placetype":"venue"
},
  "geometry": {"coordinates":[-79.96571299999999,40.384175],"type":"Point"}
}