{
  "type": "Feature",
  "properties": {
    "addr:full":"1601 Cherry St Philadelphia PA 19102",
    "addr:housenumber":"1601",
    "addr:postcode":"19102",
    "addr:street":"Cherry St",
    "iso:country":"US",
    "sg:address":"1601 Cherry St",
    "sg:city":"Philadelphia",
    "sg:classifiers":[
        {
            "category":"Professional",
            "subcategory":"Lawyer & Legal Services",
            "type":"Services"
        }
    ],
    "sg:phone":"+1 267 402 3000",
    "sg:postcode":"19102",
    "sg:province":"PA",
    "wof:name":"Walsh Marguerite S ESQ",
    "wof:placetype":"venue"
},
  "geometry": {"coordinates":[-75.16570299999999,39.957802],"type":"Point"}
}