{
  "type": "Feature",
  "properties": {
    "iso:country":"US",
    "sg:address":"410 Laurel Blvd",
    "sg:city":"Pottsville",
    "sg:classifiers":[
        {
            "category":"Insurance",
            "subcategory":"Hazard Insurance",
            "type":"Services"
        }
    ],
    "sg:phone":"+1 570 628 3626",
    "sg:postcode":"17901",
    "sg:province":"PA",
    "sg:tags":[
        "commercial",
        "business"
    ],
    "wof:name":"Moraski Insurance Claims Services, Inc.",
    "wof:placetype":"venue"
},
  "geometry": {"coordinates":[-76.199912,40.686692],"type":"Point"}
}