{
  "type": "Feature",
  "properties": {
    "iso:country":"US",
    "sg:address":"240 S 18th St",
    "sg:city":"Camp Hill",
    "sg:classifiers":[
        {
            "category":"Professional",
            "subcategory":"Lawyer & Legal Services",
            "type":"Services"
        }
    ],
    "sg:phone":"+1 717 737 2390",
    "sg:postcode":"17011",
    "sg:province":"PA",
    "wof:name":"Patrick Eric D Law Ofc",
    "wof:placetype":"venue"
},
  "geometry": {"coordinates":[-76.91100299999999,40.2365],"type":"Point"}
}