{
  "type": "Feature",
  "properties": {
    "iso:country":"US",
    "sg:address":"160 N Gulph Rd",
    "sg:city":"King Of Prussia",
    "sg:classifiers":[
        {
            "category":"Restaurant",
            "type":"Food & Drink"
        }
    ],
    "sg:phone":"+1 610 337 7571",
    "sg:postcode":"19406",
    "sg:province":"PA",
    "sg:tags":[
        "parlor",
        "ice",
        "cream"
    ],
    "sg:website":"www.coldstonecreamery.com",
    "wof:name":"Cold Stone Creamery",
    "wof:placetype":"venue"
},
  "geometry": {"coordinates":[-75.391153,40.085802],"type":"Point"}
}