{
  "type": "Feature",
  "properties": {
    "addr:full":"202 Williams St Tionesta PA 16353",
    "addr:housenumber":"202",
    "addr:postcode":"16353",
    "addr:street":"Williams St",
    "iso:country":"US",
    "sg:address":"202 Williams St",
    "sg:city":"Tionesta",
    "sg:classifiers":[
        {
            "category":"Restaurant",
            "type":"Food & Drink"
        }
    ],
    "sg:phone":"+1 814 755 4766",
    "sg:postcode":"16353",
    "sg:province":"PA",
    "wof:name":"All American Dream Restaurant",
    "wof:placetype":"venue"
},
  "geometry": {"coordinates":[-79.457548,41.497206],"type":"Point"}
}