{
  "type": "Feature",
  "properties": {
    "addr:full":"4059 Skippack Pike Skippack PA 19474",
    "addr:postcode":"4059;19474",
    "addr:street":"Skippack Pike",
    "iso:country":"US",
    "sg:address":"4059 Skippack Pike",
    "sg:city":"Skippack",
    "sg:classifiers":[
        {
            "category":"Personal",
            "subcategory":"Beauty Salon",
            "type":"Services"
        }
    ],
    "sg:phone":"+1 610 584 6015",
    "sg:postcode":"19474",
    "sg:province":"PA",
    "sg:tags":[
        "hair"
    ],
    "sg:website":"www.salonrougeinc.net",
    "wof:name":"Salon Rouge Inc",
    "wof:placetype":"venue"
},
  "geometry": {"coordinates":[-75.40172099999999,40.225112],"type":"Point"}
}