{
  "type": "Feature",
  "properties": {
    "addr:full":"1094 Solomon Run Rd Johnstown PA 15904",
    "addr:housenumber":"1094",
    "addr:postcode":"15904",
    "addr:street":"Solomon Run Rd",
    "iso:country":"US",
    "sg:address":"1094 Solomon Run Rd",
    "sg:city":"Johnstown",
    "sg:classifiers":[
        {
            "category":"Wholesale",
            "subcategory":"Machinery & Supplies",
            "type":"Manufacturing & Wholesale Goods"
        }
    ],
    "sg:phone":"+1 814 536 7196",
    "sg:postcode":"15904",
    "sg:province":"PA",
    "sg:tags":[
        "equipment",
        "industrial",
        "truck"
    ],
    "wof:name":"T M T Forklift Repairs",
    "wof:placetype":"venue"
},
  "geometry": {"coordinates":[-78.81512499999999,40.313443],"type":"Point"}
}