{
  "type": "Feature",
  "properties": {
    "addr:full":"516 California Ave Pittsburgh PA 15202",
    "addr:housenumber":"516",
    "addr:postcode":"15202",
    "addr:street":"California Ave",
    "iso:country":"US",
    "sg:address":"516 California Ave",
    "sg:city":"Pittsburgh",
    "sg:classifiers":[
        {
            "category":"Building & Trades",
            "subcategory":"Construction",
            "type":"Services"
        }
    ],
    "sg:phone":"+1   ",
    "sg:postcode":"15202",
    "sg:province":"PA",
    "sg:tags":[
        "contractor"
    ],
    "wof:name":"Locke Contracting",
    "wof:placetype":"venue"
},
  "geometry": {"coordinates":[-80.069534,40.501941],"type":"Point"}
}