{
  "type": "Feature",
  "properties": {
    "iso:country":"US",
    "sg:address":"100 W Main St",
    "sg:city":"Mechanicsburg",
    "sg:classifiers":[
        {
            "category":"Professional",
            "type":"Services"
        }
    ],
    "sg:phone":"+1   ",
    "sg:postcode":"17055",
    "sg:province":"PA",
    "wof:name":"Milton R & Phyllis I Weber",
    "wof:placetype":"venue"
},
  "geometry": {"coordinates":[-77.011883,40.212149],"type":"Point"}
}