{
  "type": "Feature",
  "properties": {
    "iso:country":"US",
    "sg:address":"91 School Dr",
    "sg:city":"New Ringgold",
    "sg:classifiers":[
        {
            "category":"Freight",
            "type":"Transportation"
        }
    ],
    "sg:phone":"+1   ",
    "sg:postcode":"17960",
    "sg:province":"PA",
    "sg:tags":[
        "arrangement"
    ],
    "wof:name":"D & S Transportation Corp",
    "wof:placetype":"venue"
},
  "geometry": {"coordinates":[-75.87970300000001,40.745667],"type":"Point"}
}