{
  "type": "Feature",
  "properties": {
    "iso:country":"US",
    "sg:address":"543 Hudson St",
    "sg:city":"Hawley",
    "sg:classifiers":[
        {
            "category":"Professional",
            "subcategory":"Engineering",
            "type":"Services"
        }
    ],
    "sg:phone":"+1   ",
    "sg:postcode":"18428",
    "sg:province":"PA",
    "wof:name":"Things That Swing Inc",
    "wof:placetype":"venue"
},
  "geometry": {"coordinates":[-75.177021,41.479038],"type":"Point"}
}