{
  "type": "Feature",
  "properties": {
    "addr:full":"8700 Pennsylvania Ave Irwin PA 15642",
    "addr:housenumber":"8700",
    "addr:postcode":"15642",
    "addr:street":"Pennsylvania Ave",
    "iso:country":"US",
    "sg:address":"8700 Pennsylvania Ave",
    "sg:city":"Irwin",
    "sg:classifiers":[
        {
            "category":"Health Services",
            "subcategory":"Doctor",
            "type":"Services"
        }
    ],
    "sg:phone":"+1   ",
    "sg:postcode":"15642",
    "sg:province":"PA",
    "sg:tags":[
        "medical"
    ],
    "wof:name":"Center For Vascular Medicine",
    "wof:placetype":"venue"
},
  "geometry": {"coordinates":[-79.683493,40.319161],"type":"Point"}
}