{
  "type": "Feature",
  "properties": {
    "addr:full":"1377 N Charlotte St Pottstown PA 19464",
    "addr:housenumber":"1377",
    "addr:postcode":"19464",
    "addr:street":"N Charlotte St",
    "iso:country":"US",
    "sg:address":"1377 N Charlotte St",
    "sg:city":"Pottstown",
    "sg:classifiers":[
        {
            "category":"Insurance",
            "subcategory":"Insurance Agent",
            "type":"Services"
        }
    ],
    "sg:phone":"+1   ",
    "sg:postcode":"19464",
    "sg:province":"PA",
    "sg:tags":[
        "legal"
    ],
    "wof:name":"Weigner Insurance",
    "wof:placetype":"venue"
},
  "geometry": {"coordinates":[-75.626623,40.266577],"type":"Point"}
}