{
  "type": "Feature",
  "properties": {
    "iso:country":"US",
    "sg:address":"7709 Germantown Ave",
    "sg:city":"Philadelphia",
    "sg:classifiers":[
        {
            "category":"Shopping",
            "subcategory":"Clothing, Apparel, & Fashions",
            "type":"Retail Goods"
        }
    ],
    "sg:phone":"+1   ",
    "sg:postcode":"19118",
    "sg:province":"PA",
    "sg:tags":[
        "woman"
    ],
    "wof:name":"Houdini Lock and Services",
    "wof:placetype":"venue"
},
  "geometry": {"coordinates":[-75.19870899999999,40.068699],"type":"Point"}
}