{
  "type": "Feature",
  "properties": {
    "iso:country":"US",
    "sg:address":"2722 Rhawn St",
    "sg:city":"Philadelphia",
    "sg:classifiers":[
        {
            "category":"Professional",
            "subcategory":"Accounting & Tax Preparation",
            "type":"Services"
        }
    ],
    "sg:phone":"+1 215 335 9367",
    "sg:postcode":"19152",
    "sg:province":"PA",
    "sg:tags":[
        "insurance",
        "agency",
        "payment",
        "ce",
        "utility"
    ],
    "sg:website":"http://www.masonenergy.com",
    "wof:name":"Mason Financial Services",
    "wof:placetype":"venue"
},
  "geometry": {"coordinates":[-75.04438500000001,40.055406],"type":"Point"}
}