{
  "type": "Feature",
  "properties": {
    "addr:full":"3641 Locust Walk Philadelphia PA 19104",
    "addr:housenumber":"3641",
    "addr:postcode":"19104",
    "addr:street":"Locust Walk",
    "iso:country":"US",
    "sg:address":"3641 Locust Walk",
    "sg:city":"Philadelphia",
    "sg:classifiers":[
        {
            "category":"Retail",
            "subcategory":"Veterinary Services",
            "type":"Services"
        },
        {
            "category":"Education",
            "subcategory":"University",
            "type":"Public Place"
        }
    ],
    "sg:phone":"+1 215 898 7761",
    "sg:postcode":"19104",
    "sg:province":"PA",
    "sg:tags":[
        "college",
        "veterinarian"
    ],
    "wof:name":"University of Pennsylvania",
    "wof:placetype":"venue"
},
  "geometry": {"coordinates":[-75.195796,39.952248],"type":"Point"}
}