{
  "type": "Feature",
  "properties": {
    "iso:country":"US",
    "sg:address":"8014 Castor Ave",
    "sg:city":"Philadelphia",
    "sg:classifiers":[
        {
            "category":"Personal",
            "subcategory":"Beauty Salon",
            "type":"Services"
        }
    ],
    "sg:phone":"+1 215 722 5445",
    "sg:postcode":"19152",
    "sg:province":"PA",
    "sg:tags":[
        "shop"
    ],
    "wof:name":"Castor Nail Salon",
    "wof:placetype":"venue"
},
  "geometry": {"coordinates":[-75.05597,40.06201],"type":"Point"}
}