{
  "type": "Feature",
  "properties": {
    "iso:country":"US",
    "sg:address":"1000 Delaware Ave",
    "sg:city":"Philadelphia",
    "sg:classifiers":[
        {
            "category":"Autos & Motor Vehicles",
            "subcategory":"Auto Supplies",
            "type":"Retail Goods"
        }
    ],
    "sg:phone":"+1   ",
    "sg:postcode":"19147",
    "sg:province":"PA",
    "sg:tags":[
        "repair",
        "general"
    ],
    "wof:name":"Pep Boys",
    "wof:placetype":"venue"
},
  "geometry": {"coordinates":[-75.14417400000001,39.931155],"type":"Point"}
}