{
  "type": "Feature",
  "properties": {
    "addr:full":"112 E State St Kennett Square PA 19348",
    "addr:housenumber":"112",
    "addr:postcode":"19348",
    "addr:street":"E State St",
    "iso:country":"US",
    "sg:address":"112 E State St",
    "sg:city":"Kennett Square",
    "sg:classifiers":[
        {
            "category":"Manufacturing",
            "subcategory":"Printing",
            "type":"Manufacturing & Wholesale Goods"
        }
    ],
    "sg:phone":"+1   ",
    "sg:postcode":"19348",
    "sg:province":"PA",
    "sg:tags":[
        "newspaper",
        "publisher"
    ],
    "wof:name":"Community News Pape The",
    "wof:placetype":"venue"
},
  "geometry": {"coordinates":[-75.711457,39.846669],"type":"Point"}
}