{
  "type": "Feature",
  "properties": {
    "iso:country":"US",
    "sg:address":"2609 Ellwood Rd",
    "sg:city":"New Castle",
    "sg:classifiers":[
        {
            "category":"Food & Beverages",
            "subcategory":"Dairy",
            "type":"Retail Goods"
        }
    ],
    "sg:phone":"+1   ",
    "sg:postcode":"16101",
    "sg:province":"PA",
    "sg:tags":[
        "product",
        "store"
    ],
    "wof:name":"Handels Hmmade Ice Cream Ygurt",
    "wof:placetype":"venue"
},
  "geometry": {"coordinates":[-80.312223,40.96959],"type":"Point"}
}