{
  "type": "Feature",
  "properties": {
    "iso:country":"US",
    "sg:address":"3 S 9th St",
    "sg:city":"Akron",
    "sg:classifiers":[
        {
            "category":"Professional",
            "type":"Services"
        }
    ],
    "sg:phone":"+1 717 859 3144",
    "sg:postcode":"17501",
    "sg:province":"PA",
    "sg:tags":[
        "establishment"
    ],
    "wof:name":"H H The Agakhan Ismailia Jamat",
    "wof:placetype":"venue"
},
  "geometry": {"coordinates":[-76.202063,40.156421],"type":"Point"}
}