{
  "type": "Feature",
  "properties": {
    "addr:full":"2024 S 68th St Philadelphia PA 19142",
    "addr:housenumber":"2024",
    "addr:postcode":"19142",
    "addr:street":"S 68Th St",
    "iso:country":"US",
    "sg:address":"2024 S 68th St",
    "sg:city":"Philadelphia",
    "sg:classifiers":[
        {
            "category":"Food & Beverages",
            "subcategory":"Groceries & Convenience Stores",
            "type":"Retail Goods"
        }
    ],
    "sg:phone":"+1 215 726 9444",
    "sg:postcode":"19142",
    "sg:province":"PA",
    "wof:name":"J & S Grocery",
    "wof:placetype":"venue"
},
  "geometry": {"coordinates":[-75.239671,39.923778],"type":"Point"}
}