{
  "type": "Feature",
  "properties": {
    "iso:country":"US",
    "sg:address":"802 High Rock Rd N",
    "sg:city":"Hanover",
    "sg:classifiers":[
        {
            "category":"Professional",
            "type":"Services"
        }
    ],
    "sg:phone":"+1 717 632 9762",
    "sg:postcode":"17331",
    "sg:province":"PA",
    "sg:tags":[
        "establishment"
    ],
    "wof:name":"Nisource",
    "wof:placetype":"venue"
},
  "geometry": {"coordinates":[-76.95059000000001,39.858905],"type":"Point"}
}