{
  "type": "Feature",
  "properties": {
    "iso:country":"US",
    "sg:address":"496 Woodcrest Dr",
    "sg:city":"Mechanicsburg",
    "sg:classifiers":[
        {
            "category":"Building & Trades",
            "subcategory":"Plumbing",
            "type":"Services"
        }
    ],
    "sg:phone":"+1   ",
    "sg:postcode":"17050",
    "sg:province":"PA",
    "sg:tags":[
        "contractor"
    ],
    "wof:name":"Ty Poppe Plumbing",
    "wof:placetype":"venue"
},
  "geometry": {"coordinates":[-76.98426499999999,40.263466],"type":"Point"}
}