{
  "type": "Feature",
  "properties": {
    "iso:country":"US",
    "sg:address":"580 W Germantown Pike",
    "sg:city":"Plymouth Meeting",
    "sg:classifiers":[
        {
            "category":"Professional",
            "subcategory":"Advertising",
            "type":"Services"
        }
    ],
    "sg:phone":"+1 610 941 3555",
    "sg:postcode":"19462",
    "sg:province":"PA",
    "sg:tags":[
        "counselor"
    ],
    "wof:name":"Hitchings & Co",
    "wof:placetype":"venue"
},
  "geometry": {"coordinates":[-75.285698,40.116372],"type":"Point"}
}