{
  "type": "Feature",
  "properties": {
    "iso:country":"US",
    "sg:address":"611 Grier St",
    "sg:city":"Williamsport",
    "sg:classifiers":[
        {
            "category":"Insurance",
            "subcategory":"Insurance Agent",
            "type":"Services"
        }
    ],
    "sg:phone":"+1   ",
    "sg:postcode":"17701",
    "sg:province":"PA",
    "wof:name":"Marc A Jackson",
    "wof:placetype":"venue"
},
  "geometry": {"coordinates":[-77.029864,41.241161],"type":"Point"}
}