{
  "type": "Feature",
  "properties": {
    "iso:country":"US",
    "sg:address":"1908 Monongahela Ave",
    "sg:city":"Pittsburgh",
    "sg:classifiers":[
        {
            "category":"Personal",
            "subcategory":"Beauty Salon",
            "type":"Services"
        }
    ],
    "sg:phone":"+1 412 271 1116",
    "sg:postcode":"15218",
    "sg:province":"PA",
    "sg:tags":[
        "shop"
    ],
    "wof:name":"Gloria's Secrets",
    "wof:placetype":"venue"
},
  "geometry": {"coordinates":[-79.890276,40.421642],"type":"Point"}
}