{
  "type": "Feature",
  "properties": {
    "addr:full":"2 N 2nd St Harrisburg PA 17101",
    "addr:housenumber":"2",
    "addr:postcode":"17101",
    "addr:street":"N 2Nd St",
    "iso:country":"US",
    "sg:address":"2 N 2nd St",
    "sg:city":"Harrisburg",
    "sg:classifiers":[
        {
            "category":"Professional",
            "subcategory":"Lawyer & Legal Services",
            "type":"Services"
        }
    ],
    "sg:phone":"+1 717 257 7512",
    "sg:postcode":"17101",
    "sg:province":"PA",
    "wof:name":"Santos Daniel D Atty",
    "wof:placetype":"venue"
},
  "geometry": {"coordinates":[-76.88188700000001,40.259446],"type":"Point"}
}