{
  "type": "Feature",
  "properties": {
    "iso:country":"US",
    "sg:address":"27 Race St",
    "sg:city":"Jim Thorpe",
    "sg:classifiers":[
        {
            "category":"Manufacturing",
            "subcategory":"Food",
            "type":"Manufacturing & Wholesale Goods"
        }
    ],
    "sg:phone":"+1 570 325 8138",
    "sg:postcode":"18229",
    "sg:province":"PA",
    "sg:tags":[
        "winery"
    ],
    "wof:name":"Big Creek Vineyard",
    "wof:placetype":"venue"
},
  "geometry": {"coordinates":[-75.73863900000001,40.863014],"type":"Point"}
}