{
  "type": "Feature",
  "properties": {
    "addr:full":"1547 Hancock Ave Apollo PA 15613",
    "addr:housenumber":"1547",
    "addr:postcode":"15613",
    "addr:street":"Hancock Ave",
    "iso:country":"US",
    "sg:address":"1547 Hancock Ave",
    "sg:city":"Apollo",
    "sg:classifiers":[
        {
            "category":"Personal",
            "subcategory":"Beauty Salon",
            "type":"Services"
        }
    ],
    "sg:phone":"+1 724 568 5076",
    "sg:postcode":"15613",
    "sg:province":"PA",
    "sg:tags":[
        "shop"
    ],
    "wof:name":"Mane Idea",
    "wof:placetype":"venue"
},
  "geometry": {"coordinates":[-79.570842,40.57563],"type":"Point"}
}