{
  "type": "Feature",
  "properties": {
    "addr:full":"9910 Frankford Ave # 240 Philadelphia PA 19114",
    "addr:housenumber":"9910",
    "addr:postcode":"19114",
    "addr:street":"Frankford Ave # 240",
    "iso:country":"US",
    "sg:address":"9910 Frankford Ave # 240",
    "sg:city":"Philadelphia",
    "sg:classifiers":[
        {
            "category":"Food & Beverages",
            "subcategory":"Supermarket",
            "type":"Retail Goods"
        },
        {
            "category":"Food & Beverages",
            "subcategory":"Groceries & Convenience Stores",
            "type":"Retail Goods"
        }
    ],
    "sg:phone":"+1 215 637 1555",
    "sg:postcode":"19114",
    "sg:province":"PA",
    "sg:tags":[
        "super"
    ],
    "wof:name":"Mcmenamin Family Shop Rite",
    "wof:placetype":"venue"
},
  "geometry": {"coordinates":[-74.98649500000001,40.062813],"type":"Point"}
}