{
  "type": "Feature",
  "properties": {
    "iso:country":"US",
    "sg:address":"616 Reading Ave",
    "sg:city":"Reading",
    "sg:classifiers":[
        {
            "category":"Health Services",
            "subcategory":"Doctor",
            "type":"Services"
        }
    ],
    "sg:phone":"+1   ",
    "sg:postcode":"19611",
    "sg:province":"PA",
    "wof:name":"John H Muhr",
    "wof:placetype":"venue"
},
  "geometry": {"coordinates":[-75.951565,40.336969],"type":"Point"}
}