{
  "type": "Feature",
  "properties": {
    "addr:full":"723 Dresher Rd Horsham PA 19044",
    "addr:housenumber":"723",
    "addr:postcode":"19044",
    "addr:street":"Dresher Rd",
    "iso:country":"US",
    "sg:address":"723 Dresher Rd",
    "sg:city":"Horsham",
    "sg:classifiers":[
        {
            "category":"Professional",
            "subcategory":"Management & Consulting",
            "type":"Services"
        }
    ],
    "sg:phone":"+1 215 347 5700",
    "sg:postcode":"19044",
    "sg:province":"PA",
    "sg:tags":[
        "marketing",
        "program"
    ],
    "sg:website":"www.telerx.com",
    "wof:name":"Telerx Marketing Inc",
    "wof:placetype":"venue"
},
  "geometry": {"coordinates":[-75.14740399999999,40.165622],"type":"Point"}
}