{
  "type": "Feature",
  "properties": {
    "addr:full":"511 McKean Ave Charleroi PA 15022",
    "addr:housenumber":"511",
    "addr:postcode":"15022",
    "addr:street":"Mckean Ave",
    "iso:country":"US",
    "sg:address":"511 McKean Ave",
    "sg:city":"Charleroi",
    "sg:classifiers":[
        {
            "category":"Professional",
            "subcategory":"Accounting & Tax Preparation",
            "type":"Services"
        }
    ],
    "sg:phone":"+1 724 483 8040",
    "sg:postcode":"15022",
    "sg:province":"PA",
    "sg:tags":[
        "return",
        "filing"
    ],
    "wof:name":"H & R Block Tax Svc",
    "wof:placetype":"venue"
},
  "geometry": {"coordinates":[-79.89765199999999,40.138515],"type":"Point"}
}