{
  "type": "Feature",
  "properties": {
    "addr:full":"636 Scalp Ave Johnstown PA 15904",
    "addr:housenumber":"636",
    "addr:postcode":"15904",
    "addr:street":"Scalp Ave",
    "iso:country":"US",
    "sg:address":"636 Scalp Ave",
    "sg:city":"Johnstown",
    "sg:classifiers":[
        {
            "category":"Government",
            "subcategory":"Office",
            "type":"Public Place"
        }
    ],
    "sg:phone":"+1 814 262 7715",
    "sg:postcode":"15904",
    "sg:province":"PA",
    "sg:tags":[
        "state",
        "resource"
    ],
    "wof:name":"Public School Employees",
    "wof:placetype":"venue"
},
  "geometry": {"coordinates":[-78.87127599999999,40.293977],"type":"Point"}
}