{
  "type": "Feature",
  "properties": {
    "iso:country":"US",
    "sg:address":"226 Cheeseman Rd",
    "sg:city":"Portersville",
    "sg:classifiers":[
        {
            "category":"Farming",
            "subcategory":"Livestock Farm",
            "type":"Manufacturing & Wholesale Goods"
        }
    ],
    "sg:phone":"+1   ",
    "sg:postcode":"16051",
    "sg:province":"PA",
    "sg:tags":[
        "hog",
        "or",
        "feedlot"
    ],
    "wof:name":"Victor Cheeseman Farm",
    "wof:placetype":"venue"
},
  "geometry": {"coordinates":[-80.158022,40.937173],"type":"Point"}
}