{
  "type": "Feature",
  "properties": {
    "iso:country":"US",
    "sg:address":"2400 E Somerset St",
    "sg:city":"Philadelphia",
    "sg:classifiers":[
        {
            "category":"Professional",
            "subcategory":"Lawyer & Legal Services",
            "type":"Services"
        }
    ],
    "sg:phone":"+1 215 425 2200",
    "sg:postcode":"19134",
    "sg:province":"PA",
    "sg:tags":[
        "attorney"
    ],
    "wof:name":"Zohreh Nabavi Law Office",
    "wof:placetype":"venue"
},
  "geometry": {"coordinates":[-75.115358,39.98318],"type":"Point"}
}