{
  "type": "Feature",
  "properties": {
    "iso:country":"US",
    "sg:address":"142 Groff Rd",
    "sg:city":"Bechtelsville",
    "sg:classifiers":[
        {
            "category":"Building & Trades",
            "subcategory":"Construction",
            "type":"Services"
        }
    ],
    "sg:phone":"+1 610 473 1404",
    "sg:postcode":"19505",
    "sg:province":"PA",
    "sg:tags":[
        "home",
        "improvement"
    ],
    "wof:name":"Hughes & Son's Home Repairs",
    "wof:placetype":"venue"
},
  "geometry": {"coordinates":[-75.637231,40.399354],"type":"Point"}
}