{
  "type": "Feature",
  "properties": {
    "iso:country":"US",
    "sg:address":"7244 Rising Sun Ave",
    "sg:city":"Philadelphia",
    "sg:classifiers":[
        {
            "category":"Organizations",
            "subcategory":"Religious Organization",
            "type":"Services"
        }
    ],
    "sg:phone":"+1 215 742 6890",
    "sg:postcode":"19111",
    "sg:province":"PA",
    "sg:tags":[
        "church"
    ],
    "wof:name":"Mt Olive Church Of God",
    "wof:placetype":"venue"
},
  "geometry": {"coordinates":[-75.084225,40.061094],"type":"Point"}
}