{
  "type": "Feature",
  "properties": {
    "iso:country":"US",
    "sg:address":"117 Highland Ave",
    "sg:city":"Factoryville",
    "sg:classifiers":[
        {
            "category":"Banks & Credit Unions",
            "subcategory":"Investment Brokerage",
            "type":"Services"
        }
    ],
    "sg:phone":"+1 570 945 7980",
    "sg:postcode":"18419",
    "sg:province":"PA",
    "sg:tags":[
        "security"
    ],
    "wof:name":"Securities America",
    "wof:placetype":"venue"
},
  "geometry": {"coordinates":[-75.78729,41.559478],"type":"Point"}
}