{
  "type": "Feature",
  "properties": {
    "iso:country":"US",
    "sg:address":"313 Winding Way",
    "sg:city":"Womelsdorf",
    "sg:classifiers":[
        {
            "category":"Shopping",
            "subcategory":"Computers & Home Electronics",
            "type":"Retail Goods"
        }
    ],
    "sg:phone":"+1 610 589 9442",
    "sg:postcode":"19567",
    "sg:province":"PA",
    "sg:tags":[
        "high",
        "fidelity",
        "stereophonic"
    ],
    "wof:name":"Classic Entertainment Svc",
    "wof:placetype":"venue"
},
  "geometry": {"coordinates":[-76.194846,40.368778],"type":"Point"}
}