{
  "type": "Feature",
  "properties": {
    "addr:full":"783 W Front St Lewisberry PA 17339",
    "addr:housenumber":"783",
    "addr:postcode":"17339",
    "addr:street":"W Front St",
    "iso:country":"US",
    "sg:address":"783 W Front St",
    "sg:city":"Lewisberry",
    "sg:classifiers":[
        {
            "category":"Food & Beverages",
            "subcategory":"Groceries & Convenience Stores",
            "type":"Retail Goods"
        }
    ],
    "sg:phone":"+1 717 938 2962",
    "sg:postcode":"17339",
    "sg:province":"PA",
    "sg:tags":[
        "grocer"
    ],
    "wof:name":"L H Gross Manorette",
    "wof:placetype":"venue"
},
  "geometry": {"coordinates":[-76.864965,40.13526],"type":"Point"}
}