{
  "type": "Feature",
  "properties": {
    "iso:country":"US",
    "sg:address":"300 S Broad St",
    "sg:city":"Lansdale",
    "sg:classifiers":[
        {
            "category":"Manufacturing",
            "subcategory":"Printing",
            "type":"Manufacturing & Wholesale Goods"
        }
    ],
    "sg:phone":"+1 215 368 4140",
    "sg:postcode":"19446",
    "sg:province":"PA",
    "sg:tags":[
        "printer"
    ],
    "wof:name":"Bestway Printing",
    "wof:placetype":"venue"
},
  "geometry": {"coordinates":[-75.28780399999999,40.237801],"type":"Point"}
}