{
  "type": "Feature",
  "properties": {
    "iso:country":"US",
    "sg:address":"2688 E High St",
    "sg:city":"Pottstown",
    "sg:classifiers":[
        {
            "category":"Restaurant",
            "type":"Food & Drink"
        }
    ],
    "sg:phone":"+1 610 327 2910",
    "sg:postcode":"19464",
    "sg:province":"PA",
    "sg:website":"www.cutillos.com",
    "wof:name":"Cutillo's Restaurant",
    "wof:placetype":"venue"
},
  "geometry": {"coordinates":[-75.584974,40.244312],"type":"Point"}
}