{
  "type": "Feature",
  "properties": {
    "iso:country":"US",
    "sg:address":"29 2nd St",
    "sg:city":"Cecil",
    "sg:classifiers":[
        {
            "category":"Professional",
            "type":"Services"
        }
    ],
    "sg:phone":"+1 814 425 3256",
    "sg:postcode":"15378",
    "sg:province":"PA",
    "sg:tags":[
        "establishment"
    ],
    "wof:name":"Betler Brothers",
    "wof:placetype":"venue"
},
  "geometry": {"coordinates":[-80.273904,40.277862],"type":"Point"}
}