{
  "type": "Feature",
  "properties": {
    "addr:full":"267 Main St Slatington PA 18080",
    "addr:housenumber":"267",
    "addr:postcode":"18080",
    "addr:street":"Main St",
    "iso:country":"US",
    "sg:address":"267 Main St",
    "sg:city":"Slatington",
    "sg:classifiers":[
        {
            "category":"Personal",
            "subcategory":"Beauty Salon",
            "type":"Services"
        }
    ],
    "sg:phone":"+1 610 760 6111",
    "sg:postcode":"18080",
    "sg:province":"PA",
    "wof:name":"It's About Time Salon",
    "wof:placetype":"venue"
},
  "geometry": {"coordinates":[-75.60709199999999,40.752451],"type":"Point"}
}