{
  "type": "Feature",
  "properties": {
    "addr:full":"501 Bath Rd Bristol PA 19007",
    "addr:housenumber":"501",
    "addr:postcode":"19007",
    "addr:street":"Bath Rd",
    "iso:country":"US",
    "sg:address":"501 Bath Rd",
    "sg:city":"Bristol",
    "sg:classifiers":[
        {
            "category":"Health Services",
            "subcategory":"Doctor",
            "type":"Services"
        }
    ],
    "sg:phone":"+1   ",
    "sg:postcode":"19007",
    "sg:province":"PA",
    "sg:tags":[
        "medical"
    ],
    "wof:name":"Bednarek Joseph MD Facs",
    "wof:placetype":"venue"
},
  "geometry": {"coordinates":[-74.863343,40.102169],"type":"Point"}
}