{
  "type": "Feature",
  "properties": {
    "iso:country":"US",
    "sg:address":"819 Cross Roads Plz",
    "sg:city":"Mount Pleasant",
    "sg:classifiers":[
        {
            "category":"Restaurant",
            "type":"Food & Drink"
        }
    ],
    "sg:menulink":"http://www.allmenus.com/pa/east-huntingdon/200175-long-john-silvers/menu/",
    "sg:phone":"+1 724 547 3919",
    "sg:postcode":"15666",
    "sg:province":"PA",
    "sg:tags":[
        "seafood",
        "american"
    ],
    "wof:name":"Long John Silver's",
    "wof:placetype":"venue"
},
  "geometry": {"coordinates":[-79.55327200000001,40.124607],"type":"Point"}
}