{
  "type": "Feature",
  "properties": {
    "iso:country":"US",
    "sg:address":"430 Greenfield Ave",
    "sg:city":"Pittsburgh",
    "sg:classifiers":[
        {
            "category":"Organizations",
            "subcategory":"Non-profit Organization",
            "type":"Services"
        }
    ],
    "sg:phone":"+1 412 422 8885",
    "sg:postcode":"15207",
    "sg:province":"PA",
    "sg:tags":[
        "community"
    ],
    "sg:website":"http://www.greenfieldorg.com",
    "wof:name":"Greenfield Organization",
    "wof:placetype":"venue"
},
  "geometry": {"coordinates":[-79.943084,40.425366],"type":"Point"}
}