{
  "type": "Feature",
  "properties": {
    "iso:country":"US",
    "sg:address":"105 Himmelwright Rd",
    "sg:city":"Barto",
    "sg:classifiers":[
        {
            "category":"Building & Trades",
            "subcategory":"Construction",
            "type":"Services"
        }
    ],
    "sg:phone":"+1 610 845 9686",
    "sg:postcode":"19504",
    "sg:province":"PA",
    "sg:tags":[
        "house",
        "painter"
    ],
    "wof:name":"Frey's Remodeling",
    "wof:placetype":"venue"
},
  "geometry": {"coordinates":[-75.56961099999999,40.380945],"type":"Point"}
}