{
  "type": "Feature",
  "properties": {
    "iso:country":"US",
    "sg:address":"26 N 4th St",
    "sg:city":"Hamburg",
    "sg:classifiers":[
        {
            "category":"Personal",
            "subcategory":"Beauty Salon",
            "type":"Services"
        }
    ],
    "sg:phone":"+1 610 562 7598",
    "sg:postcode":"19526",
    "sg:province":"PA",
    "sg:tags":[
        "shop"
    ],
    "wof:name":"Loose's Beauty Shop",
    "wof:placetype":"venue"
},
  "geometry": {"coordinates":[-75.983008,40.556547],"type":"Point"}
}