{
  "type": "Feature",
  "properties": {
    "iso:country":"US",
    "sg:address":"7 W Canal St",
    "sg:city":"Dover",
    "sg:classifiers":[
        {
            "category":"Food & Beverages",
            "subcategory":"Meat & Fish",
            "type":"Retail Goods"
        }
    ],
    "sg:phone":"+1 717 292 1093",
    "sg:postcode":"17315",
    "sg:province":"PA",
    "wof:name":"Weaver's Quality Meats",
    "wof:placetype":"venue"
},
  "geometry": {"coordinates":[-76.850683,40.001316],"type":"Point"}
}