{
  "type": "Feature",
  "properties": {
    "addr:full":"1352 Cumberland St Lebanon PA 17042",
    "addr:housenumber":"1352",
    "addr:postcode":"17042",
    "addr:street":"Cumberland St",
    "iso:country":"US",
    "sg:address":"1352 Cumberland St",
    "sg:city":"Lebanon",
    "sg:classifiers":[
        {
            "category":"Restaurant",
            "type":"Food & Drink"
        }
    ],
    "sg:phone":"+1 717 273 8011",
    "sg:postcode":"17042",
    "sg:province":"PA",
    "wof:name":"Horn & Horn Family Restaurant",
    "wof:placetype":"venue"
},
  "geometry": {"coordinates":[-76.43321,40.338494],"type":"Point"}
}