{
  "type": "Feature",
  "properties": {
    "iso:country":"US",
    "sg:address":"6364 Library Rd",
    "sg:city":"Library",
    "sg:classifiers":[
        {
            "category":"Retail",
            "subcategory":"Funeral Services",
            "type":"Services"
        }
    ],
    "sg:phone":"+1 412 835 0616",
    "sg:postcode":"15129",
    "sg:province":"PA",
    "sg:tags":[
        "cemetery"
    ],
    "wof:name":"Ocepek Eugene C Funeral Home",
    "wof:placetype":"venue"
},
  "geometry": {"coordinates":[-80.0289,40.290901],"type":"Point"}
}