{
  "type": "Feature",
  "properties": {
    "iso:country":"US",
    "sg:address":"701 Allegheny St",
    "sg:city":"Jersey Shore",
    "sg:classifiers":[
        {
            "category":"Food & Beverages",
            "subcategory":"Groceries & Convenience Stores",
            "type":"Retail Goods"
        }
    ],
    "sg:phone":"+1   ",
    "sg:postcode":"17740",
    "sg:province":"PA",
    "wof:name":"Head Start Jersey Shore",
    "wof:placetype":"venue"
},
  "geometry": {"coordinates":[-77.26401199999999,41.204145],"type":"Point"}
}