{
  "type": "Feature",
  "properties": {
    "iso:country":"US",
    "sg:address":"2412 Charcot St",
    "sg:city":"Pittsburgh",
    "sg:classifiers":[
        {
            "category":"Building & Trades",
            "subcategory":"Construction",
            "type":"Services"
        }
    ],
    "sg:phone":"+1   ",
    "sg:postcode":"15210",
    "sg:province":"PA",
    "sg:tags":[
        "house"
    ],
    "wof:name":"Ews Home Improvement",
    "wof:placetype":"venue"
},
  "geometry": {"coordinates":[-79.9716,40.416771],"type":"Point"}
}