{
  "type": "Feature",
  "properties": {
    "iso:country":"US",
    "sg:address":"110 Ashley Rd",
    "sg:city":"Newtown Square",
    "sg:classifiers":[
        {
            "category":"Communications",
            "subcategory":"Film & Video Production",
            "type":"Services"
        }
    ],
    "sg:phone":"+1   ",
    "sg:postcode":"19073",
    "sg:province":"PA",
    "wof:name":"Ashley Productions",
    "wof:placetype":"venue"
},
  "geometry": {"coordinates":[-75.39456199999999,39.989248],"type":"Point"}
}