{
  "type": "Feature",
  "properties": {
    "iso:country":"US",
    "sg:address":"118 Armstrong Rd",
    "sg:city":"Pittston",
    "sg:classifiers":[
        {
            "category":"Professional",
            "subcategory":"Business Services",
            "type":"Services"
        }
    ],
    "sg:phone":"+1   ",
    "sg:postcode":"18640",
    "sg:province":"PA",
    "sg:tags":[
        "treatment",
        "sewage"
    ],
    "wof:name":"Clean Treatment Sewage Company",
    "wof:placetype":"venue"
},
  "geometry": {"coordinates":[-75.74338400000001,41.30971],"type":"Point"}
}