{
  "type": "Feature",
  "properties": {
    "iso:country":"US",
    "sg:address":"207 Sigma Dr",
    "sg:city":"Pittsburgh",
    "sg:classifiers":[
        {
            "category":"Organizations",
            "subcategory":"Professional Association",
            "type":"Services"
        }
    ],
    "sg:phone":"+1 412 963 1044",
    "sg:postcode":"15238",
    "sg:province":"PA",
    "wof:name":"Pennsylvania Automotive Assn",
    "wof:placetype":"venue"
},
  "geometry": {"coordinates":[-79.864864,40.503666],"type":"Point"}
}