{
  "type": "Feature",
  "properties": {
    "iso:country":"US",
    "sg:address":"500 Abbott Dr # 500A",
    "sg:city":"Broomall",
    "sg:classifiers":[
        {
            "category":"Building & Trades",
            "subcategory":"Plumbing",
            "type":"Services"
        },
        {
            "category":"Building & Trades",
            "subcategory":"Construction",
            "type":"Services"
        }
    ],
    "sg:phone":"+1 610 544 7999",
    "sg:postcode":"19008",
    "sg:province":"PA",
    "sg:tags":[
        "plumber",
        "plumbing-drain",
        "specialty",
        "system",
        "heating",
        "cleaning",
        "contractor",
        "air conditioning",
        "sewer"
    ],
    "sg:website":"http://www.wmhendersoninc.com",
    "wof:name":"William Henderson Plumbing Heating Cooling Services",
    "wof:placetype":"venue"
},
  "geometry": {"coordinates":[-75.338067,39.960022],"type":"Point"}
}