{
  "type": "Feature",
  "properties": {
    "addr:full":"371 N Sumner Ave Scranton PA 18504",
    "addr:housenumber":"371",
    "addr:postcode":"18504",
    "addr:street":"N Sumner Ave",
    "iso:country":"US",
    "sg:address":"371 N Sumner Ave",
    "sg:city":"Scranton",
    "sg:classifiers":[
        {
            "category":"Arts & Performance",
            "subcategory":"Theater",
            "type":"Entertainment"
        }
    ],
    "sg:phone":"+1 570 344 1087",
    "sg:postcode":"18504",
    "sg:province":"PA",
    "sg:tags":[
        "group"
    ],
    "wof:name":"Ed Curry Theatrical",
    "wof:placetype":"venue"
},
  "geometry": {"coordinates":[-75.681168,41.416826],"type":"Point"}
}