{
  "type": "Feature",
  "properties": {
    "iso:country":"US",
    "sg:address":"423 N 21st St Ste 300",
    "sg:city":"Camp Hill",
    "sg:classifiers":[
        {
            "category":"Health Services",
            "subcategory":"Doctor",
            "type":"Services"
        }
    ],
    "sg:phone":"+1 717 763 1174",
    "sg:postcode":"17011",
    "sg:province":"PA",
    "wof:name":"Mid Penn Urology",
    "wof:placetype":"venue"
},
  "geometry": {"coordinates":[-76.923103,40.250198],"type":"Point"}
}