{
  "type": "Feature",
  "properties": {
    "iso:country":"US",
    "sg:address":"602 Prince St",
    "sg:city":"Littlestown",
    "sg:classifiers":[
        {
            "category":"Professional",
            "type":"Services"
        }
    ],
    "sg:phone":"+1   ",
    "sg:postcode":"17340",
    "sg:province":"PA",
    "wof:name":"Valko",
    "wof:placetype":"venue"
},
  "geometry": {"coordinates":[-77.094448,39.752703],"type":"Point"}
}