{
  "type": "Feature",
  "properties": {
    "iso:country":"US",
    "sg:address":"68 Stamy Rd",
    "sg:city":"Newville",
    "sg:classifiers":[
        {
            "category":"Building & Trades",
            "subcategory":"Construction",
            "type":"Services"
        }
    ],
    "sg:phone":"+1 717 776 5706",
    "sg:postcode":"17241",
    "sg:province":"PA",
    "sg:tags":[
        "contractor"
    ],
    "wof:name":"Charley-Roger Construction Co",
    "wof:placetype":"venue"
},
  "geometry": {"coordinates":[-77.431561,40.171257],"type":"Point"}
}