{
  "type": "Feature",
  "properties": {
    "addr:full":"1515 Allison St Harrisburg PA 17104",
    "addr:housenumber":"1515",
    "addr:postcode":"17104",
    "addr:street":"Allison St",
    "iso:country":"US",
    "sg:address":"1515 Allison St",
    "sg:city":"Harrisburg",
    "sg:classifiers":[
        {
            "category":"Building & Trades",
            "subcategory":"Electrical",
            "type":"Services"
        }
    ],
    "sg:phone":"+1 717 443 3335",
    "sg:postcode":"17104",
    "sg:province":"PA",
    "sg:tags":[
        "electric",
        "contractor"
    ],
    "wof:name":"Apple Electric",
    "wof:placetype":"venue"
},
  "geometry": {"coordinates":[-76.857738,40.244232],"type":"Point"}
}