{
  "type": "Feature",
  "properties": {
    "iso:country":"US",
    "sg:address":"76 Mary St",
    "sg:city":"Doylestown",
    "sg:classifiers":[
        {
            "category":"Personal",
            "subcategory":"Day Spa",
            "type":"Services"
        }
    ],
    "sg:phone":"+1 215 340 1990",
    "sg:postcode":"18901",
    "sg:province":"PA",
    "wof:name":"B Spa Skin Care Center & Day Spa",
    "wof:placetype":"venue"
},
  "geometry": {"coordinates":[-75.132052,40.308321],"type":"Point"}
}