{
  "type": "Feature",
  "properties": {
    "addr:full":"2044 W Main St Ephrata PA 17522",
    "addr:housenumber":"2044",
    "addr:postcode":"17522",
    "addr:street":"W Main St",
    "iso:country":"US",
    "sg:address":"2044 W Main St",
    "sg:city":"Ephrata",
    "sg:classifiers":[
        {
            "category":"Building & Trades",
            "subcategory":"Equipment Rental",
            "type":"Services"
        }
    ],
    "sg:phone":"+1   ",
    "sg:postcode":"17522",
    "sg:province":"PA",
    "wof:name":"Sonlight Services",
    "wof:placetype":"venue"
},
  "geometry": {"coordinates":[-76.236518,40.212542],"type":"Point"}
}