{
  "type": "Feature",
  "properties": {
    "addr:full":"2137 Mosside Blvd Monroeville PA 15146",
    "addr:housenumber":"2137",
    "addr:postcode":"15146",
    "addr:street":"Mosside Blvd",
    "iso:country":"US",
    "sg:address":"2137 Mosside Blvd",
    "sg:city":"Monroeville",
    "sg:classifiers":[
        {
            "category":"Utilities",
            "subcategory":"Fuel Oil & Lpg",
            "type":"Services"
        }
    ],
    "sg:phone":"+1   ",
    "sg:postcode":"15146",
    "sg:province":"PA",
    "sg:tags":[
        "liquefied",
        "gas",
        "petroleum"
    ],
    "wof:name":"Duanes Propane & Supply",
    "wof:placetype":"venue"
},
  "geometry": {"coordinates":[-79.766779,40.400335],"type":"Point"}
}