{
  "type": "Feature",
  "properties": {
    "addr:full":"1702 Fredendall Cir Southampton PA 18966",
    "addr:housenumber":"1702",
    "addr:postcode":"18966",
    "addr:street":"Fredendall Cir",
    "iso:country":"US",
    "sg:address":"1702 Fredendall Cir",
    "sg:city":"Southampton",
    "sg:classifiers":[
        {
            "category":"Professional",
            "subcategory":"Accounting & Tax Preparation",
            "type":"Services"
        }
    ],
    "sg:phone":"+1 215 396 7231",
    "sg:postcode":"18966",
    "sg:province":"PA",
    "sg:tags":[
        "accountant"
    ],
    "wof:name":"Stanley Silverstein CPA",
    "wof:placetype":"venue"
},
  "geometry": {"coordinates":[-75.022668,40.161636],"type":"Point"}
}