{
  "type": "Feature",
  "properties": {
    "iso:country":"US",
    "sg:address":"1 Trimont Ln",
    "sg:city":"Pittsburgh",
    "sg:classifiers":[
        {
            "category":"Building & Trades",
            "subcategory":"Construction",
            "type":"Services"
        }
    ],
    "sg:phone":"+1   ",
    "sg:postcode":"15211",
    "sg:province":"PA",
    "sg:tags":[
        "hanging",
        "contractor"
    ],
    "wof:name":"Proffessional Paperhanging",
    "wof:placetype":"venue"
},
  "geometry": {"coordinates":[-80.01943799999999,40.438137],"type":"Point"}
}