{
  "type": "Feature",
  "properties": {
    "iso:country":"US",
    "sg:address":"2811 W Girard Ave",
    "sg:city":"Philadelphia",
    "sg:classifiers":[
        {
            "category":"Shopping",
            "subcategory":"Clothing, Apparel, & Fashions",
            "type":"Retail Goods"
        }
    ],
    "sg:phone":"+1 215 765 4791",
    "sg:postcode":"19130",
    "sg:province":"PA",
    "sg:tags":[
        "clothing",
        "women's"
    ],
    "wof:name":"New Style Ladies",
    "wof:placetype":"venue"
},
  "geometry": {"coordinates":[-75.182255,39.97467],"type":"Point"}
}