{
  "type": "Feature",
  "properties": {
    "addr:full":"310 Alpha Dr Pittsburgh PA 15238",
    "addr:housenumber":"310",
    "addr:postcode":"15238",
    "addr:street":"Alpha Dr",
    "iso:country":"US",
    "sg:address":"310 Alpha Dr",
    "sg:city":"Pittsburgh",
    "sg:classifiers":[
        {
            "category":"Banks & Credit Unions",
            "subcategory":"Financial Services",
            "type":"Services"
        }
    ],
    "sg:phone":"+1   ",
    "sg:postcode":"15238",
    "sg:province":"PA",
    "sg:tags":[
        "trust",
        "nonprofit",
        "management"
    ],
    "wof:name":"Miles Family Foundation",
    "wof:placetype":"venue"
},
  "geometry": {"coordinates":[-79.86918300000001,40.491754],"type":"Point"}
}