{
  "type": "Feature",
  "properties": {
    "iso:country":"US",
    "sg:address":"209 Chapel Ridge Rd",
    "sg:city":"Glenshaw",
    "sg:classifiers":[
        {
            "category":"Real Estate",
            "subcategory":"Real Estate Agent",
            "type":"Services"
        }
    ],
    "sg:phone":"+1   ",
    "sg:postcode":"15116",
    "sg:province":"PA",
    "wof:name":"Deborah Kahn Realty",
    "wof:placetype":"venue"
},
  "geometry": {"coordinates":[-79.96541000000001,40.545752],"type":"Point"}
}