{
  "type": "Feature",
  "properties": {
    "iso:country":"US",
    "sg:address":"6418 1/2 Elmwood Ave",
    "sg:city":"Philadelphia",
    "sg:classifiers":[
        {
            "category":"Social Services",
            "subcategory":"Child Care",
            "type":"Services"
        },
        {
            "category":"Education",
            "subcategory":"Preschool",
            "type":"Public Place"
        }
    ],
    "sg:phone":"+1 215 937 9847",
    "sg:postcode":"19142",
    "sg:province":"PA",
    "sg:tags":[
        "day"
    ],
    "wof:name":"Lene's Daily Childcare",
    "wof:placetype":"venue"
},
  "geometry": {"coordinates":[-75.229201,39.922815],"type":"Point"}
}