{
  "type": "Feature",
  "properties": {
    "iso:country":"US",
    "sg:address":"6334 Stenton Ave",
    "sg:city":"Philadelphia",
    "sg:classifiers":[
        {
            "category":"Social Services",
            "subcategory":"Job Training",
            "type":"Services"
        },
        {
            "category":"Health Services",
            "subcategory":"Hospital",
            "type":"Services"
        },
        {
            "category":"Health Services",
            "subcategory":"Nursing And Care Facility",
            "type":"Services"
        },
        {
            "category":"Education",
            "subcategory":"College",
            "type":"Public Place"
        }
    ],
    "sg:phone":"+1 215 549 4408",
    "sg:postcode":"19138",
    "sg:province":"PA",
    "sg:tags":[
        "school",
        "assistant",
        "medical",
        "registry",
        "technician",
        "nurse",
        "dental"
    ],
    "wof:name":"Professional Nurses Service Training Center Inc",
    "wof:placetype":"venue"
},
  "geometry": {"coordinates":[-75.165466,40.05957],"type":"Point"}
}