{
  "type": "Feature",
  "properties": {
    "addr:full":"25 N Main St Doylestown PA 18901",
    "addr:housenumber":"25",
    "addr:postcode":"18901",
    "addr:street":"N Main St",
    "iso:country":"US",
    "sg:address":"25 N Main St",
    "sg:city":"Doylestown",
    "sg:classifiers":[
        {
            "category":"Professional",
            "subcategory":"Lawyer & Legal Services",
            "type":"Services"
        }
    ],
    "sg:phone":"+1   ",
    "sg:postcode":"18901",
    "sg:province":"PA",
    "wof:name":"Marston John C",
    "wof:placetype":"venue"
},
  "geometry": {"coordinates":[-75.130571,40.310676],"type":"Point"}
}