{
  "type": "Feature",
  "properties": {
    "iso:country":"US",
    "sg:address":"704 State St",
    "sg:city":"Erie",
    "sg:classifiers":[
        {
            "category":"Organizations",
            "subcategory":"Community Association",
            "type":"Services"
        }
    ],
    "sg:phone":"+1   ",
    "sg:postcode":"16503",
    "sg:province":"PA",
    "sg:tags":[
        "fitness",
        "physical",
        "facility"
    ],
    "wof:name":"YWCA",
    "wof:placetype":"venue"
},
  "geometry": {"coordinates":[-80.08417300000001,42.1277],"type":"Point"}
}