{
  "type": "Feature",
  "properties": {
    "addr:full":"4111 Pilgrim Rd Plymouth Meeting PA 19462",
    "addr:housenumber":"4111",
    "addr:postcode":"19462",
    "addr:street":"Pilgrim Rd",
    "iso:country":"US",
    "sg:address":"4111 Pilgrim Rd",
    "sg:city":"Plymouth Meeting",
    "sg:classifiers":[
        {
            "category":"Professional",
            "type":"Services"
        }
    ],
    "sg:phone":"+1   ",
    "sg:postcode":"19462",
    "sg:province":"PA",
    "wof:name":"Fox Consulting",
    "wof:placetype":"venue"
},
  "geometry": {"coordinates":[-75.270158,40.103654],"type":"Point"}
}