{
  "type": "Feature",
  "properties": {
    "iso:country":"US",
    "sg:address":"173 Adamson Rd",
    "sg:city":"Marianna",
    "sg:classifiers":[
        {
            "category":"Building & Trades",
            "subcategory":"Construction",
            "type":"Services"
        }
    ],
    "sg:phone":"+1 724 267 3483",
    "sg:postcode":"15345",
    "sg:province":"PA",
    "sg:tags":[
        "home",
        "improvement"
    ],
    "wof:name":"Adamson Home Improvements",
    "wof:placetype":"venue"
},
  "geometry": {"coordinates":[-80.114079,40.010907],"type":"Point"}
}