{
  "type": "Feature",
  "properties": {
    "iso:country":"US",
    "sg:address":"608 N Railroad St",
    "sg:city":"Palmyra",
    "sg:classifiers":[
        {
            "category":"Insurance",
            "subcategory":"Hazard Insurance",
            "type":"Services"
        }
    ],
    "sg:phone":"+1 717 383 3661",
    "sg:postcode":"17078",
    "sg:province":"PA",
    "wof:name":"Troy Miller",
    "wof:placetype":"venue"
},
  "geometry": {"coordinates":[-76.601809,40.315406],"type":"Point"}
}