{
  "type": "Feature",
  "properties": {
    "addr:full":"1673 Long Run Rd Schuylkill Haven PA 17972",
    "addr:housenumber":"1673",
    "addr:postcode":"17972",
    "addr:street":"Long Run Rd",
    "iso:country":"US",
    "sg:address":"1673 Long Run Rd",
    "sg:city":"Schuylkill Haven",
    "sg:classifiers":[
        {
            "category":"Organizations",
            "subcategory":"Religious Organization",
            "type":"Services"
        },
        {
            "category":"Travel",
            "subcategory":"Campground",
            "type":"Entertainment"
        }
    ],
    "sg:phone":"+1 570 739 4425",
    "sg:postcode":"17972",
    "sg:province":"PA",
    "sg:tags":[
        "camp"
    ],
    "sg:website":"www.cefschpa.com",
    "wof:name":"Child Evnangelism Fellowship",
    "wof:placetype":"venue"
},
  "geometry": {"coordinates":[-76.216545,40.612215],"type":"Point"}
}