{
  "type": "Feature",
  "properties": {
    "iso:country":"US",
    "sg:address":"1322 Poplar St",
    "sg:city":"Lebanon",
    "sg:classifiers":[
        {
            "category":"Utilities",
            "subcategory":"Refuse",
            "type":"Services"
        }
    ],
    "sg:phone":"+1 717 272 7061",
    "sg:postcode":"17042",
    "sg:province":"PA",
    "sg:tags":[
        "garbage",
        "collection"
    ],
    "wof:name":"George F Weidle Sanitation Svc",
    "wof:placetype":"venue"
},
  "geometry": {"coordinates":[-76.431077,40.329938],"type":"Point"}
}