{
  "type": "Feature",
  "properties": {
    "addr:full":"564 Alpha Dr Pittsburgh PA 15238",
    "addr:housenumber":"564",
    "addr:postcode":"15238",
    "addr:street":"Alpha Dr",
    "iso:country":"US",
    "sg:address":"564 Alpha Dr",
    "sg:city":"Pittsburgh",
    "sg:classifiers":[
        {
            "category":"Professional",
            "subcategory":"Secretarial Services",
            "type":"Services"
        }
    ],
    "sg:phone":"+1   ",
    "sg:postcode":"15238",
    "sg:province":"PA",
    "sg:tags":[
        "computer",
        "programing",
        "reporting",
        "custom"
    ],
    "wof:name":"Webmedx Inc",
    "wof:placetype":"venue"
},
  "geometry": {"coordinates":[-79.86951000000001,40.508043],"type":"Point"}
}