{
  "type": "Feature",
  "properties": {
    "iso:country":"US",
    "sg:address":"125 Baltimore St",
    "sg:city":"Hanover",
    "sg:classifiers":[
        {
            "category":"Manufacturing",
            "subcategory":"Printing",
            "type":"Manufacturing & Wholesale Goods"
        }
    ],
    "sg:phone":"+1 717 637 1115",
    "sg:postcode":"17331",
    "sg:province":"PA",
    "sg:tags":[
        "multimedia"
    ],
    "wof:name":"Hanover Multimedia & Video Svc",
    "wof:placetype":"venue"
},
  "geometry": {"coordinates":[-76.98089899999999,39.79829],"type":"Point"}
}