{
  "type": "Feature",
  "properties": {
    "addr:full":"125 Grove Rd Prosperity PA 15329",
    "addr:housenumber":"125",
    "addr:postcode":"15329",
    "addr:street":"Grove Rd",
    "iso:country":"US",
    "sg:address":"125 Grove Rd",
    "sg:city":"Prosperity",
    "sg:classifiers":[
        {
            "category":"Mining & Drilling",
            "type":"Manufacturing & Wholesale Goods"
        }
    ],
    "sg:phone":"+1   ",
    "sg:postcode":"15329",
    "sg:province":"PA",
    "sg:tags":[
        "field"
    ],
    "wof:name":"Jsf Oil & Gas",
    "wof:placetype":"venue"
},
  "geometry": {"coordinates":[-80.281425,40.041772],"type":"Point"}
}