{
  "type": "Feature",
  "properties": {
    "addr:full":"135 E Chestnut St Hellertown PA 18055",
    "addr:housenumber":"135",
    "addr:postcode":"18055",
    "addr:street":"E Chestnut St",
    "iso:country":"US",
    "sg:address":"135 E Chestnut St",
    "sg:city":"Hellertown",
    "sg:classifiers":[
        {
            "category":"Shopping",
            "subcategory":"Antiques",
            "type":"Retail Goods"
        }
    ],
    "sg:phone":"+1 610 838 6212",
    "sg:postcode":"18055",
    "sg:province":"PA",
    "wof:name":"Achey's Antiques",
    "wof:placetype":"venue"
},
  "geometry": {"coordinates":[-75.33971099999999,40.583168],"type":"Point"}
}