{
  "type": "Feature",
  "properties": {
    "addr:full":"109 N Abington Rd Clarks Green PA 18411",
    "addr:housenumber":"109",
    "addr:postcode":"18411",
    "addr:street":"N Abington Rd",
    "iso:country":"US",
    "sg:address":"109 N Abington Rd",
    "sg:city":"Clarks Green",
    "sg:classifiers":[
        {
            "category":"Health Services",
            "subcategory":"Clinic",
            "type":"Services"
        }
    ],
    "sg:phone":"+1 570 585 2040",
    "sg:postcode":"18411",
    "sg:province":"PA",
    "wof:name":"Maximum Wellness",
    "wof:placetype":"venue"
},
  "geometry": {"coordinates":[-75.69619,41.498796],"type":"Point"}
}