{
  "type": "Feature",
  "properties": {
    "iso:country":"US",
    "sg:address":"233 Market St",
    "sg:city":"Bainbridge",
    "sg:classifiers":[
        {
            "category":"Building & Trades",
            "subcategory":"Plumbing",
            "type":"Services"
        }
    ],
    "sg:phone":"+1 717 426 9990",
    "sg:postcode":"17502",
    "sg:province":"PA",
    "sg:tags":[
        "mechanical",
        "contractor"
    ],
    "wof:name":"Susquehanna Services Corp",
    "wof:placetype":"venue"
},
  "geometry": {"coordinates":[-76.665747,40.090333],"type":"Point"}
}