{
  "type": "Feature",
  "properties": {
    "iso:country":"US",
    "sg:address":"251 Salem Church Rd",
    "sg:city":"Mechanicsburg",
    "sg:classifiers":[
        {
            "category":"Building & Trades",
            "subcategory":"Construction",
            "type":"Services"
        }
    ],
    "sg:phone":"+1   ",
    "sg:postcode":"17050",
    "sg:province":"PA",
    "sg:tags":[
        "contractor"
    ],
    "wof:name":"Dean G Keller",
    "wof:placetype":"venue"
},
  "geometry": {"coordinates":[-76.99600100000001,40.230702],"type":"Point"}
}