{
  "type": "Feature",
  "properties": {
    "iso:country":"US",
    "sg:address":"702 Broad St",
    "sg:city":"New Bethlehem",
    "sg:classifiers":[
        {
            "category":"Restaurant",
            "type":"Food & Drink"
        }
    ],
    "sg:menulink":"http://www.allmenus.com/pa/new-bethlehem/170739-burger-king/menu/",
    "sg:phone":"+1 814 275 7500",
    "sg:postcode":"16242",
    "sg:province":"PA",
    "sg:tags":[
        "burger",
        "american"
    ],
    "wof:name":"Burger King",
    "wof:placetype":"venue"
},
  "geometry": {"coordinates":[-79.326761,41.0023],"type":"Point"}
}