{
  "type": "Feature",
  "properties": {
    "iso:country":"US",
    "sg:address":"434 Lower Barbours Rd",
    "sg:city":"Williamsport",
    "sg:classifiers":[
        {
            "category":"Manufacturing",
            "subcategory":"Lumber",
            "type":"Manufacturing & Wholesale Goods"
        }
    ],
    "sg:phone":"+1 570 478 2888",
    "sg:postcode":"17701",
    "sg:province":"PA",
    "sg:tags":[
        "forester"
    ],
    "wof:name":"Aumen's Forest Mgt Svc",
    "wof:placetype":"venue"
},
  "geometry": {"coordinates":[-76.80266899999999,41.390371],"type":"Point"}
}