{
  "type": "Feature",
  "properties": {
    "addr:full":"2227 N 3rd Ave Whitehall PA 18052",
    "addr:housenumber":"2227",
    "addr:postcode":"18052",
    "addr:street":"N 3Rd Ave",
    "iso:country":"US",
    "sg:address":"2227 N 3rd Ave",
    "sg:city":"Whitehall",
    "sg:classifiers":[
        {
            "category":"Retail",
            "subcategory":"Auto Repair",
            "type":"Services"
        }
    ],
    "sg:phone":"+1 610 266 7767",
    "sg:postcode":"18052",
    "sg:province":"PA",
    "sg:website":"www.absoluteproformance.com",
    "wof:name":"Absolute Proformance",
    "wof:placetype":"venue"
},
  "geometry": {"coordinates":[-75.47974499999999,40.647471],"type":"Point"}
}