{
  "type": "Feature",
  "properties": {
    "iso:country":"US",
    "sg:address":"1101 Pittsburgh St",
    "sg:city":"Springdale",
    "sg:classifiers":[
        {
            "category":"Bars & Pubs",
            "type":"Food & Drink"
        },
        {
            "category":"Restaurant",
            "type":"Food & Drink"
        },
        {
            "category":"Bars & Pubs",
            "subcategory":"Lounge",
            "type":"Food & Drink"
        }
    ],
    "sg:phone":"+1 724 274 9500",
    "sg:postcode":"15144",
    "sg:province":"PA",
    "sg:tags":[
        "tavern",
        "style",
        "cocktail",
        "family"
    ],
    "sg:website":"http://www.rwv.com",
    "wof:name":"Valentine's Restaurant",
    "wof:placetype":"venue"
},
  "geometry": {"coordinates":[-79.77310199999999,40.542641],"type":"Point"}
}