{
  "type": "Feature",
  "properties": {
    "iso:country":"US",
    "sg:address":"2299 Brodhead Rd",
    "sg:city":"Bethlehem",
    "sg:classifiers":[
        {
            "category":"Health Services",
            "subcategory":"Dentist",
            "type":"Services"
        }
    ],
    "sg:phone":"+1 610 954 5400",
    "sg:postcode":"18020",
    "sg:province":"PA",
    "sg:tags":[
        "pediatric"
    ],
    "wof:name":"Sumar Dilshad DMD",
    "wof:placetype":"venue"
},
  "geometry": {"coordinates":[-75.37220000000001,40.6777],"type":"Point"}
}