{
  "type": "Feature",
  "properties": {
    "iso:country":"US",
    "sg:address":"800 Serrill Ave",
    "sg:city":"Lansdowne",
    "sg:classifiers":[
        {
            "category":"Banks & Credit Unions",
            "subcategory":"Bank",
            "type":"Services"
        }
    ],
    "sg:phone":"+1 610 284 1341",
    "sg:postcode":"19050",
    "sg:province":"PA",
    "sg:tags":[
        "loan",
        "real estate"
    ],
    "wof:name":"ADJ Mortgage Svc Inc",
    "wof:placetype":"venue"
},
  "geometry": {"coordinates":[-75.25044699999999,39.929535],"type":"Point"}
}