{
  "type": "Feature",
  "properties": {
    "addr:full":"1001 Erie Ave Philadelphia PA 19124",
    "addr:housenumber":"1001",
    "addr:postcode":"19124",
    "addr:street":"Erie Ave",
    "iso:country":"US",
    "sg:address":"1001 Erie Ave",
    "sg:city":"Philadelphia",
    "sg:classifiers":[
        {
            "category":"Banks & Credit Unions",
            "subcategory":"Bank",
            "type":"Services"
        },
        {
            "category":"Banks & Credit Unions",
            "subcategory":"Financial Services",
            "type":"Services"
        }
    ],
    "sg:phone":"+1 215 537 3090",
    "sg:postcode":"19124",
    "sg:province":"PA",
    "sg:tags":[
        "commercial",
        "loan",
        "saving"
    ],
    "sg:website":"http://www.pncbank.com",
    "wof:name":"PNC Bank",
    "wof:placetype":"venue"
},
  "geometry": {"coordinates":[-75.109297,40.005383],"type":"Point"}
}