{
  "type": "Feature",
  "properties": {
    "iso:country":"US",
    "sg:address":"718 Fox Hollow Rd",
    "sg:city":"Ambler",
    "sg:classifiers":[
        {
            "category":"Wholesale",
            "subcategory":"Home Furnishings",
            "type":"Manufacturing & Wholesale Goods"
        }
    ],
    "sg:phone":"+1 215 628 8565",
    "sg:postcode":"19002",
    "sg:province":"PA",
    "sg:tags":[
        "floor",
        "representative",
        "covering"
    ],
    "wof:name":"Diamond Carpet Marketers Inc",
    "wof:placetype":"venue"
},
  "geometry": {"coordinates":[-75.24022600000001,40.18455],"type":"Point"}
}