{
  "type": "Feature",
  "properties": {
    "iso:country":"US",
    "sg:address":"526 Fairview St",
    "sg:city":"Emmaus",
    "sg:classifiers":[
        {
            "category":"Organizations",
            "subcategory":"Religious Organization",
            "type":"Services"
        }
    ],
    "sg:phone":"+1   ",
    "sg:postcode":"18049",
    "sg:province":"PA",
    "wof:name":"Transfiguration Monestary",
    "wof:placetype":"venue"
},
  "geometry": {"coordinates":[-75.49123,40.528008],"type":"Point"}
}