{
  "type": "Feature",
  "properties": {
    "addr:full":"265 E Ridge St Coaldale PA 18218",
    "addr:housenumber":"265",
    "addr:postcode":"18218",
    "addr:street":"E Ridge St",
    "iso:country":"US",
    "sg:address":"265 E Ridge St",
    "sg:city":"Coaldale",
    "sg:classifiers":[
        {
            "category":"Building & Trades",
            "subcategory":"Plumbing",
            "type":"Services"
        }
    ],
    "sg:phone":"+1   ",
    "sg:postcode":"18218",
    "sg:province":"PA",
    "sg:tags":[
        "contractor"
    ],
    "wof:name":"Joseph A Smariga Plbg & Htg",
    "wof:placetype":"venue"
},
  "geometry": {"coordinates":[-75.904146,40.826005],"type":"Point"}
}