{
  "type": "Feature",
  "properties": {
    "iso:country":"US",
    "sg:address":"357 Stone Church Rd",
    "sg:city":"Prospect",
    "sg:classifiers":[
        {
            "category":"Wholesale",
            "subcategory":"Machinery & Supplies",
            "type":"Manufacturing & Wholesale Goods"
        }
    ],
    "sg:phone":"+1   ",
    "sg:postcode":"16052",
    "sg:province":"PA",
    "wof:name":"Flinner Equipment Co",
    "wof:placetype":"venue"
},
  "geometry": {"coordinates":[-80.08376800000001,40.891703],"type":"Point"}
}