{
  "type": "Feature",
  "properties": {
    "addr:full":"2234 S 56th St Philadelphia PA 19143",
    "addr:housenumber":"2234",
    "addr:postcode":"19143",
    "addr:street":"S 56Th St",
    "iso:country":"US",
    "sg:address":"2234 S 56th St",
    "sg:city":"Philadelphia",
    "sg:classifiers":[
        {
            "category":"Building & Trades",
            "subcategory":"Electrical",
            "type":"Services"
        }
    ],
    "sg:phone":"+1 215 726 7121",
    "sg:postcode":"19143",
    "sg:province":"PA",
    "sg:tags":[
        "electrician",
        "contractor"
    ],
    "wof:name":"J & D Electrical",
    "wof:placetype":"venue"
},
  "geometry": {"coordinates":[-75.218013,39.931314],"type":"Point"}
}