{
  "type": "Feature",
  "properties": {
    "iso:country":"US",
    "sg:address":"5414 Walnut St",
    "sg:city":"Pittsburgh",
    "sg:classifiers":[
        {
            "category":"Deli",
            "type":"Food & Drink"
        }
    ],
    "sg:menulink":"http://www.allmenus.com/pa/pittsburgh/37136-the-shadyside-market--gourmet-deli/menu/",
    "sg:phone":"+1 412 682 5420",
    "sg:postcode":"15232",
    "sg:province":"PA",
    "sg:tags":[
        "american"
    ],
    "wof:name":"The Shadyside Market & Gourmet Deli",
    "wof:placetype":"venue"
},
  "geometry": {"coordinates":[-79.934926,40.4508],"type":"Point"}
}