{
  "type": "Feature",
  "properties": {
    "addr:full":"540 North Ave Pittsburgh PA 15209",
    "addr:housenumber":"540",
    "addr:postcode":"15209",
    "addr:street":"North Ave",
    "iso:country":"US",
    "sg:address":"540 North Ave",
    "sg:city":"Pittsburgh",
    "sg:classifiers":[
        {
            "category":"Wholesale",
            "subcategory":"Non-durable Goods",
            "type":"Manufacturing & Wholesale Goods"
        }
    ],
    "sg:phone":"+1   ",
    "sg:postcode":"15209",
    "sg:province":"PA",
    "sg:tags":[
        "mfr",
        "durable",
        "representative"
    ],
    "wof:name":"McDonough & Associates Inc",
    "wof:placetype":"venue"
},
  "geometry": {"coordinates":[-79.97290700000001,40.48454],"type":"Point"}
}