{
  "type": "Feature",
  "properties": {
    "iso:country":"US",
    "sg:address":"906 6th St",
    "sg:city":"Saxton",
    "sg:classifiers":[
        {
            "category":"Autos & Motor Vehicles",
            "subcategory":"Auto Supplies",
            "type":"Retail Goods"
        }
    ],
    "sg:phone":"+1 814 635 2227",
    "sg:postcode":"16678",
    "sg:province":"PA",
    "sg:tags":[
        "automobile",
        "parts"
    ],
    "wof:name":"Raystown Automotive Parts",
    "wof:placetype":"venue"
},
  "geometry": {"coordinates":[-78.241339,40.217563],"type":"Point"}
}