{
  "type": "Feature",
  "properties": {
    "iso:country":"US",
    "sg:address":"5201 Ellsworth Ave",
    "sg:city":"Pittsburgh",
    "sg:classifiers":[
        {
            "category":"Organizations",
            "subcategory":"Religious Organization",
            "type":"Services"
        }
    ],
    "sg:phone":"+1 412 621 5529",
    "sg:postcode":"15232",
    "sg:province":"PA",
    "sg:tags":[
        "church"
    ],
    "sg:website":"www.odpgh.org",
    "wof:name":"Greek Orthodox Diocese-Pitts",
    "wof:placetype":"venue"
},
  "geometry": {"coordinates":[-79.938796,40.452034],"type":"Point"}
}