{
  "type": "Feature",
  "properties": {
    "iso:country":"US",
    "sg:address":"400 Shay Ln",
    "sg:city":"Matamoras",
    "sg:classifiers":[
        {
            "category":"Travel",
            "subcategory":"Hotels & Motels",
            "type":"Entertainment"
        }
    ],
    "sg:phone":"+1 570 491 2173",
    "sg:postcode":"18336",
    "sg:province":"PA",
    "sg:website":"www.riverviewinninc.com",
    "wof:name":"Riverview Inn Inc",
    "wof:placetype":"venue"
},
  "geometry": {"coordinates":[-74.698717,41.358579],"type":"Point"}
}