{
  "type": "Feature",
  "properties": {
    "iso:country":"US",
    "sg:address":"468 Shartlesville Rd",
    "sg:city":"Mohrsville",
    "sg:classifiers":[
        {
            "category":"Farming",
            "subcategory":"Dairy Farm",
            "type":"Manufacturing & Wholesale Goods"
        },
        {
            "category":"Farming",
            "subcategory":"Farm",
            "type":"Manufacturing & Wholesale Goods"
        }
    ],
    "sg:phone":"+1 610 926 4211",
    "sg:postcode":"19541",
    "sg:province":"PA",
    "wof:name":"David Haag Farm",
    "wof:placetype":"venue"
},
  "geometry": {"coordinates":[-76.017484,40.491032],"type":"Point"}
}