{
  "type": "Feature",
  "properties": {
    "addr:full":"2611 Oak Ave Altoona PA 16601",
    "addr:housenumber":"2611",
    "addr:postcode":"16601",
    "addr:street":"Oak Ave",
    "iso:country":"US",
    "sg:address":"2611 Oak Ave",
    "sg:city":"Altoona",
    "sg:classifiers":[
        {
            "category":"Building & Trades",
            "subcategory":"Construction",
            "type":"Services"
        }
    ],
    "sg:phone":"+1   ",
    "sg:postcode":"16601",
    "sg:province":"PA",
    "sg:tags":[
        "contractor"
    ],
    "wof:name":"Yingling Construction Co",
    "wof:placetype":"venue"
},
  "geometry": {"coordinates":[-78.41550599999999,40.503139],"type":"Point"}
}