{
  "type": "Feature",
  "properties": {
    "addr:full":"1617 Red Hill Rd Dauphin PA 17018",
    "addr:housenumber":"1617",
    "addr:postcode":"17018",
    "addr:street":"Red Hill Rd",
    "iso:country":"US",
    "sg:address":"1617 Red Hill Rd",
    "sg:city":"Dauphin",
    "sg:classifiers":[
        {
            "category":"Professional",
            "type":"Services"
        }
    ],
    "sg:phone":"+1   ",
    "sg:postcode":"17018",
    "sg:province":"PA",
    "wof:name":"C H Spade",
    "wof:placetype":"venue"
},
  "geometry": {"coordinates":[-76.994338,40.375018],"type":"Point"}
}