{
  "type": "Feature",
  "properties": {
    "addr:full":"59 N Ramona Rd Myerstown PA 17067",
    "addr:housenumber":"59",
    "addr:postcode":"17067",
    "addr:street":"N Ramona Rd",
    "iso:country":"US",
    "sg:address":"59 N Ramona Rd",
    "sg:city":"Myerstown",
    "sg:classifiers":[
        {
            "category":"Organizations",
            "subcategory":"Religious Organization",
            "type":"Services"
        }
    ],
    "sg:phone":"+1 717 866 5647",
    "sg:postcode":"17067",
    "sg:province":"PA",
    "sg:tags":[
        "church"
    ],
    "wof:name":"Myerstown Baptist Church",
    "wof:placetype":"venue"
},
  "geometry": {"coordinates":[-76.33448300000001,40.371239],"type":"Point"}
}