{
  "type": "Feature",
  "properties": {
    "iso:country":"US",
    "sg:address":"4083 Wimbledon Dr",
    "sg:city":"Harrisburg",
    "sg:classifiers":[
        {
            "category":"Wholesale",
            "subcategory":"Scrap",
            "type":"Manufacturing & Wholesale Goods"
        }
    ],
    "sg:phone":"+1   ",
    "sg:postcode":"17112",
    "sg:province":"PA",
    "sg:tags":[
        "material"
    ],
    "wof:name":"M Greenberg Company",
    "wof:placetype":"venue"
},
  "geometry": {"coordinates":[-76.83923,40.340165],"type":"Point"}
}