{
  "type": "Feature",
  "properties": {
    "iso:country":"US",
    "sg:address":"292 Monument Ave",
    "sg:city":"Wyoming",
    "sg:classifiers":[
        {
            "category":"Sports & Exercise",
            "subcategory":"Gym",
            "type":"Entertainment"
        }
    ],
    "sg:phone":"+1   ",
    "sg:postcode":"18644",
    "sg:province":"PA",
    "sg:tags":[
        "fitness",
        "physical",
        "facility"
    ],
    "wof:name":"Dial Fitness Inc",
    "wof:placetype":"venue"
},
  "geometry": {"coordinates":[-75.835545,41.310654],"type":"Point"}
}