{
  "type": "Feature",
  "properties": {
    "addr:full":"102 E Phil Ellena St Philadelphia PA 19119",
    "addr:housenumber":"102",
    "addr:postcode":"19119",
    "addr:street":"E Phil Ellena St",
    "iso:country":"US",
    "sg:address":"102 E Phil Ellena St",
    "sg:city":"Philadelphia",
    "sg:classifiers":[
        {
            "category":"Organizations",
            "subcategory":"Religious Organization",
            "type":"Services"
        }
    ],
    "sg:phone":"+1   ",
    "sg:postcode":"19119",
    "sg:province":"PA",
    "wof:name":"Church of God of Prophecy",
    "wof:placetype":"venue"
},
  "geometry": {"coordinates":[-75.182897,40.053926],"type":"Point"}
}