{
  "type": "Feature",
  "properties": {
    "iso:country":"US",
    "sg:address":"372 Center Ave",
    "sg:city":"Schuylkill Haven",
    "sg:classifiers":[
        {
            "category":"Communications",
            "subcategory":"Film & Video Production",
            "type":"Services"
        }
    ],
    "sg:phone":"+1   ",
    "sg:postcode":"17972",
    "sg:province":"PA",
    "sg:tags":[
        "motion"
    ],
    "wof:name":"Gala Productions LLC",
    "wof:placetype":"venue"
},
  "geometry": {"coordinates":[-76.171882,40.637715],"type":"Point"}
}