{
  "type": "Feature",
  "properties": {
    "addr:full":"416 E Main St Roaring Spring PA 16673",
    "addr:housenumber":"416",
    "addr:postcode":"16673",
    "addr:street":"E Main St",
    "iso:country":"US",
    "sg:address":"416 E Main St",
    "sg:city":"Roaring Spring",
    "sg:classifiers":[
        {
            "category":"Organizations",
            "subcategory":"Community Association",
            "type":"Services"
        }
    ],
    "sg:phone":"+1   ",
    "sg:postcode":"16673",
    "sg:province":"PA",
    "sg:tags":[
        "membership"
    ],
    "wof:name":"Trout Unlimited",
    "wof:placetype":"venue"
},
  "geometry": {"coordinates":[-78.401644,40.335406],"type":"Point"}
}