{
  "type": "Feature",
  "properties": {
    "iso:country":"US",
    "sg:address":"622 Ferry St",
    "sg:city":"Easton",
    "sg:classifiers":[
        {
            "category":"Building & Trades",
            "subcategory":"Construction",
            "type":"Services"
        }
    ],
    "sg:phone":"+1 610 253 7813",
    "sg:postcode":"18042",
    "sg:province":"PA",
    "sg:tags":[
        "remodeling",
        "contractor"
    ],
    "wof:name":"Metro Remodelers",
    "wof:placetype":"venue"
},
  "geometry": {"coordinates":[-75.21446899999999,40.689443],"type":"Point"}
}