{
  "type": "Feature",
  "properties": {
    "iso:country":"US",
    "sg:address":"220 E Main St",
    "sg:city":"Palmyra",
    "sg:classifiers":[
        {
            "category":"Health Services",
            "subcategory":"Doctor",
            "type":"Services"
        }
    ],
    "sg:phone":"+1 717 838 2151",
    "sg:postcode":"17078",
    "sg:province":"PA",
    "sg:tags":[
        "podiatrist"
    ],
    "wof:name":"Pauli C David DPM",
    "wof:placetype":"venue"
},
  "geometry": {"coordinates":[-76.593002,40.308899],"type":"Point"}
}