{
  "type": "Feature",
  "properties": {
    "addr:full":"323 Scott St Wilkes Barre PA 18702",
    "addr:housenumber":"323",
    "addr:postcode":"18702",
    "addr:street":"Scott St",
    "iso:country":"US",
    "sg:address":"323 Scott St",
    "sg:city":"Wilkes Barre",
    "sg:classifiers":[
        {
            "category":"Insurance",
            "subcategory":"Insurance Agent",
            "type":"Services"
        }
    ],
    "sg:phone":"+1 570 704 0020",
    "sg:postcode":"18702",
    "sg:province":"PA",
    "wof:name":"Tracy Thomas J Agency",
    "wof:placetype":"venue"
},
  "geometry": {"coordinates":[-75.86318,41.246905],"type":"Point"}
}