{
  "type": "Feature",
  "properties": {
    "iso:country":"US",
    "sg:address":"5701 5th Ave",
    "sg:city":"Pittsburgh",
    "sg:classifiers":[
        {
            "category":"Education",
            "subcategory":"Special Training",
            "type":"Public Place"
        }
    ],
    "sg:phone":"+1 412 661 7006",
    "sg:postcode":"15232",
    "sg:province":"PA",
    "sg:tags":[
        "tutoring"
    ],
    "wof:name":"Greater Pittsburgh Literacy",
    "wof:placetype":"venue"
},
  "geometry": {"coordinates":[-79.928437,40.450212],"type":"Point"}
}