{
  "type": "Feature",
  "properties": {
    "iso:country":"US",
    "sg:address":"4502 Hamilton Blvd",
    "sg:city":"Allentown",
    "sg:classifiers":[
        {
            "category":"Building & Trades",
            "subcategory":"Equipment Rental",
            "type":"Services"
        }
    ],
    "sg:phone":"+1 610 398 7368",
    "sg:postcode":"18103",
    "sg:province":"PA",
    "sg:tags":[
        "yard"
    ],
    "sg:website":"www.taylorallentown.com",
    "wof:name":"Taylor Rental Ctr",
    "wof:placetype":"venue"
},
  "geometry": {"coordinates":[-75.547911,40.568642],"type":"Point"}
}