{
  "type": "Feature",
  "properties": {
    "iso:country":"US",
    "sg:address":"4404 Fritchey St",
    "sg:city":"Harrisburg",
    "sg:classifiers":[
        {
            "category":"Personal",
            "subcategory":"Beauty Salon",
            "type":"Services"
        }
    ],
    "sg:phone":"+1 717 545 8180",
    "sg:postcode":"17109",
    "sg:province":"PA",
    "sg:tags":[
        "hair"
    ],
    "sg:website":"www.fourtresssalon.com",
    "wof:name":"Four Tress Salon",
    "wof:placetype":"venue"
},
  "geometry": {"coordinates":[-76.818642,40.298975],"type":"Point"}
}