{
  "type": "Feature",
  "properties": {
    "addr:full":"237 Pittsburgh St Scottdale PA 15683",
    "addr:housenumber":"237",
    "addr:postcode":"15683",
    "addr:street":"Pittsburgh St",
    "iso:country":"US",
    "sg:address":"237 Pittsburgh St",
    "sg:city":"Scottdale",
    "sg:classifiers":[
        {
            "category":"Insurance",
            "subcategory":"Hazard Insurance",
            "type":"Services"
        }
    ],
    "sg:phone":"+1 724 887 5505",
    "sg:postcode":"15683",
    "sg:province":"PA",
    "sg:tags":[
        "commercial",
        "business"
    ],
    "wof:name":"Westmore Insurance Service",
    "wof:placetype":"venue"
},
  "geometry": {"coordinates":[-79.58866999999999,40.10153],"type":"Point"}
}