{
  "type": "Feature",
  "properties": {
    "addr:full":"5338 Locust St Philadelphia PA 19139",
    "addr:housenumber":"5338",
    "addr:postcode":"19139",
    "addr:street":"Locust St",
    "iso:country":"US",
    "sg:address":"5338 Locust St",
    "sg:city":"Philadelphia",
    "sg:classifiers":[
        {
            "category":"Wholesale",
            "subcategory":"Non-durable Goods",
            "type":"Manufacturing & Wholesale Goods"
        }
    ],
    "sg:phone":"+1 215 763 0363",
    "sg:postcode":"19139",
    "sg:province":"PA",
    "sg:tags":[
        "dry",
        "goods-wholesale"
    ],
    "wof:name":"Casino Janitorial Supply",
    "wof:placetype":"venue"
},
  "geometry": {"coordinates":[-75.228425,39.956135],"type":"Point"}
}