{
  "type": "Feature",
  "properties": {
    "addr:full":"8215 Stenton Ave Philadelphia PA 19150",
    "addr:housenumber":"8215",
    "addr:postcode":"19150",
    "addr:street":"Stenton Ave",
    "iso:country":"US",
    "sg:address":"8215 Stenton Ave",
    "sg:city":"Philadelphia",
    "sg:classifiers":[
        {
            "category":"Restaurant",
            "type":"Food & Drink"
        }
    ],
    "sg:phone":"+1 215 247 5354",
    "sg:postcode":"19150",
    "sg:province":"PA",
    "sg:tags":[
        "eating"
    ],
    "wof:name":"Lakey's Restaurant",
    "wof:placetype":"venue"
},
  "geometry": {"coordinates":[-75.179305,40.067482],"type":"Point"}
}