{
  "type": "Feature",
  "properties": {
    "addr:full":"4301 N Broad St Philadelphia PA 19140",
    "addr:housenumber":"4301",
    "addr:postcode":"19140",
    "addr:street":"N Broad St",
    "iso:country":"US",
    "sg:address":"4301 N Broad St",
    "sg:city":"Philadelphia",
    "sg:classifiers":[
        {
            "category":"Organizations",
            "subcategory":"Community Association",
            "type":"Services"
        }
    ],
    "sg:phone":"+1 215 324 3533",
    "sg:postcode":"19140",
    "sg:province":"PA",
    "sg:tags":[
        "lodge",
        "masonic",
        "fraternal"
    ],
    "wof:name":"Royal & Select Masters Prince",
    "wof:placetype":"venue"
},
  "geometry": {"coordinates":[-75.148994,40.019572],"type":"Point"}
}