{
  "type": "Feature",
  "properties": {
    "addr:full":"90 Virginville Rd Hamburg PA 19526",
    "addr:housenumber":"90",
    "addr:postcode":"19526",
    "addr:street":"Virginville Rd",
    "iso:country":"US",
    "sg:address":"90 Virginville Rd",
    "sg:city":"Hamburg",
    "sg:classifiers":[
        {
            "category":"Recreation",
            "type":"Entertainment"
        }
    ],
    "sg:phone":"+1   ",
    "sg:postcode":"19526",
    "sg:province":"PA",
    "sg:tags":[
        "therapy",
        "massage",
        "therapeutic"
    ],
    "wof:name":"Touch of Life",
    "wof:placetype":"venue"
},
  "geometry": {"coordinates":[-75.883799,40.528937],"type":"Point"}
}