{
  "type": "Feature",
  "properties": {
    "addr:full":"1418 Society Hill Dr Bensalem PA 19020",
    "addr:housenumber":"1418",
    "addr:postcode":"19020",
    "addr:street":"Society Hill Dr",
    "iso:country":"US",
    "sg:address":"1418 Society Hill Dr",
    "sg:city":"Bensalem",
    "sg:classifiers":[
        {
            "category":"Building & Trades",
            "subcategory":"Electrical",
            "type":"Services"
        }
    ],
    "sg:phone":"+1 215 245 8004",
    "sg:postcode":"19020",
    "sg:province":"PA",
    "sg:tags":[
        "electrician"
    ],
    "wof:name":"Power Electric Inc",
    "wof:placetype":"venue"
},
  "geometry": {"coordinates":[-74.9562,40.0882],"type":"Point"}
}