{
  "type": "Feature",
  "properties": {
    "iso:country":"US",
    "sg:address":"13 Morgantown St",
    "sg:city":"Uniontown",
    "sg:classifiers":[
        {
            "category":"Restaurant",
            "type":"Food & Drink"
        }
    ],
    "sg:phone":"+1 724 439 3232",
    "sg:postcode":"15401",
    "sg:province":"PA",
    "sg:tags":[
        "eating"
    ],
    "wof:name":"Mid Towne Cafe",
    "wof:placetype":"venue"
},
  "geometry": {"coordinates":[-79.72726900000001,39.900539],"type":"Point"}
}