{
  "type": "Feature",
  "properties": {
    "iso:country":"US",
    "sg:address":"3303 Hartzdale Dr",
    "sg:city":"Camp Hill",
    "sg:classifiers":[
        {
            "category":"Retail",
            "subcategory":"Auto Repair",
            "type":"Services"
        }
    ],
    "sg:phone":"+1 717 761 5728",
    "sg:postcode":"17011",
    "sg:province":"PA",
    "sg:tags":[
        "truck"
    ],
    "wof:name":"Camp Hill Auto & Truck",
    "wof:placetype":"venue"
},
  "geometry": {"coordinates":[-76.92555,40.228309],"type":"Point"}
}