{
  "type": "Feature",
  "properties": {
    "iso:country":"US",
    "sg:address":"405 Beaver Dam Rd",
    "sg:city":"Spring Mills",
    "sg:classifiers":[
        {
            "category":"Farming",
            "subcategory":"Livestock Farm",
            "type":"Manufacturing & Wholesale Goods"
        }
    ],
    "sg:phone":"+1   ",
    "sg:postcode":"16875",
    "sg:province":"PA",
    "wof:name":"Dirk Wise",
    "wof:placetype":"venue"
},
  "geometry": {"coordinates":[-77.522527,40.850393],"type":"Point"}
}