{
  "type": "Feature",
  "properties": {
    "iso:country":"US",
    "sg:address":"216 W Beidler Rd",
    "sg:city":"King Of Prussia",
    "sg:classifiers":[
        {
            "category":"Education",
            "subcategory":"Dance Studio",
            "type":"Public Place"
        }
    ],
    "sg:phone":"+1 610 337 1772",
    "sg:postcode":"19406",
    "sg:province":"PA",
    "sg:tags":[
        "instruction",
        "dancing"
    ],
    "wof:name":"Valley Forge Dance Schools",
    "wof:placetype":"venue"
},
  "geometry": {"coordinates":[-75.37980899999999,40.111962],"type":"Point"}
}