{
  "type": "Feature",
  "properties": {
    "iso:country":"US",
    "sg:address":"5 S 69th St",
    "sg:city":"Upper Darby",
    "sg:classifiers":[
        {
            "category":"Restaurant",
            "type":"Food & Drink"
        }
    ],
    "sg:phone":"+1 610 352 7353",
    "sg:postcode":"19082",
    "sg:province":"PA",
    "sg:tags":[
        "eating"
    ],
    "wof:name":"Chun House",
    "wof:placetype":"venue"
},
  "geometry": {"coordinates":[-75.258797,39.9613],"type":"Point"}
}