{
  "type": "Feature",
  "properties": {
    "addr:full":"7310 Tilghman St Allentown PA 18106",
    "addr:housenumber":"7310",
    "addr:postcode":"18106",
    "addr:street":"Tilghman St",
    "iso:country":"US",
    "sg:address":"7310 Tilghman St",
    "sg:city":"Allentown",
    "sg:classifiers":[
        {
            "category":"Professional",
            "subcategory":"Management & Consulting",
            "type":"Services"
        },
        {
            "category":"Insurance",
            "subcategory":"Hazard Insurance",
            "type":"Services"
        },
        {
            "category":"Banks & Credit Unions",
            "subcategory":"Financial Services",
            "type":"Services"
        },
        {
            "category":"Real Estate",
            "subcategory":"Real Estate Services",
            "type":"Services"
        }
    ],
    "sg:phone":"+1 412 223 2343",
    "sg:postcode":"18106",
    "sg:province":"PA",
    "sg:tags":[
        "consultant",
        "financing",
        "planning",
        "loan",
        "mortgage"
    ],
    "sg:website":"http://www.primerica.com/public/",
    "wof:name":"Primerica",
    "wof:placetype":"venue"
},
  "geometry": {"coordinates":[-75.615988,40.586575],"type":"Point"}
}