{
  "type": "Feature",
  "properties": {
    "iso:country":"US",
    "sg:address":"34795 Mount Pleasant Rd",
    "sg:city":"Union City",
    "sg:classifiers":[
        {
            "category":"Building & Trades",
            "subcategory":"Landscaping Services",
            "type":"Services"
        }
    ],
    "sg:phone":"+1   ",
    "sg:postcode":"16438",
    "sg:province":"PA",
    "wof:name":"Five Oaks Tree Service",
    "wof:placetype":"venue"
},
  "geometry": {"coordinates":[-79.844386,41.827362],"type":"Point"}
}