{
  "type": "Feature",
  "properties": {
    "iso:country":"US",
    "sg:address":"1244 Birch Rd",
    "sg:city":"Upper Black Eddy",
    "sg:classifiers":[
        {
            "category":"Building & Trades",
            "subcategory":"Construction",
            "type":"Services"
        }
    ],
    "sg:phone":"+1   ",
    "sg:postcode":"18972",
    "sg:province":"PA",
    "sg:tags":[
        "general",
        "contractor"
    ],
    "wof:name":"Holland Construction",
    "wof:placetype":"venue"
},
  "geometry": {"coordinates":[-75.11714499999999,40.551364],"type":"Point"}
}