{
  "type": "Feature",
  "properties": {
    "addr:full":"83 E Forrest Ave Shrewsbury PA 17361",
    "addr:housenumber":"83",
    "addr:postcode":"17361",
    "addr:street":"E Forrest Ave",
    "iso:country":"US",
    "sg:address":"83 E Forrest Ave",
    "sg:city":"Shrewsbury",
    "sg:classifiers":[
        {
            "category":"Retail",
            "subcategory":"Repair Shop",
            "type":"Services"
        }
    ],
    "sg:phone":"+1 717 227 1631",
    "sg:postcode":"17361",
    "sg:province":"PA",
    "sg:tags":[
        "jewelry"
    ],
    "wof:name":"Elizabeth Kay The Jeweler",
    "wof:placetype":"venue"
},
  "geometry": {"coordinates":[-76.675223,39.769801],"type":"Point"}
}