{
  "type": "Feature",
  "properties": {
    "iso:country":"US",
    "sg:address":"244 W Queen Ln",
    "sg:city":"Philadelphia",
    "sg:classifiers":[
        {
            "category":"Building & Trades",
            "subcategory":"Construction",
            "type":"Services"
        }
    ],
    "sg:phone":"+1   ",
    "sg:postcode":"19144",
    "sg:province":"PA",
    "sg:tags":[
        "remodeling"
    ],
    "wof:name":"Nellas Construction Inc",
    "wof:placetype":"venue"
},
  "geometry": {"coordinates":[-75.17279600000001,40.027911],"type":"Point"}
}