{
  "type": "Feature",
  "properties": {
    "addr:full":"2 Doerr St Pittsburgh PA 15233",
    "addr:housenumber":"2",
    "addr:postcode":"15233",
    "addr:street":"Doerr St",
    "iso:country":"US",
    "sg:address":"2 Doerr St",
    "sg:city":"Pittsburgh",
    "sg:classifiers":[
        {
            "category":"Manufacturing",
            "subcategory":"Metals",
            "type":"Manufacturing & Wholesale Goods"
        },
        {
            "category":"Real Estate",
            "subcategory":"Real Estate Operator",
            "type":"Services"
        }
    ],
    "sg:phone":"+1 412 766 7757",
    "sg:postcode":"15233",
    "sg:province":"PA",
    "sg:tags":[
        "building",
        "plating",
        "nonresidential"
    ],
    "wof:name":"Cowan Metal Finishing Co",
    "wof:placetype":"venue"
},
  "geometry": {"coordinates":[-80.038737,40.469542],"type":"Point"}
}