{
  "type": "Feature",
  "properties": {
    "iso:country":"US",
    "sg:address":"8224 Perry Hwy",
    "sg:city":"Pittsburgh",
    "sg:classifiers":[
        {
            "category":"Personal",
            "subcategory":"Beauty Salon",
            "type":"Services"
        }
    ],
    "sg:phone":"+1 412 366 1510",
    "sg:postcode":"15237",
    "sg:province":"PA",
    "sg:tags":[
        "hair",
        "stylist"
    ],
    "wof:name":"Hair Studio 19",
    "wof:placetype":"venue"
},
  "geometry": {"coordinates":[-80.03924000000001,40.55677],"type":"Point"}
}