{
  "type": "Feature",
  "properties": {
    "iso:country":"US",
    "sg:address":"222 W Pike St",
    "sg:city":"Canonsburg",
    "sg:classifiers":[
        {
            "category":"Professional",
            "subcategory":"Lawyer & Legal Services",
            "type":"Services"
        }
    ],
    "sg:phone":"+1 724 746 1140",
    "sg:postcode":"15317",
    "sg:province":"PA",
    "wof:name":"Witherel Kovacik & Marchewka",
    "wof:placetype":"venue"
},
  "geometry": {"coordinates":[-80.193622,40.258147],"type":"Point"}
}