{
  "type": "Feature",
  "properties": {
    "iso:country":"US",
    "sg:address":"1755 Quentin Rd",
    "sg:city":"Lebanon",
    "sg:classifiers":[
        {
            "category":"Home & Garden",
            "subcategory":"Building Materials",
            "type":"Retail Goods"
        }
    ],
    "sg:phone":"+1 717 228 3300",
    "sg:postcode":"17042",
    "sg:province":"PA",
    "sg:tags":[
        "center"
    ],
    "wof:name":"Lowe's",
    "wof:placetype":"venue"
},
  "geometry": {"coordinates":[-76.42461400000001,40.313068],"type":"Point"}
}