{
  "type": "Feature",
  "properties": {
    "addr:full":"16 E Center St Elysburg PA 17824",
    "addr:housenumber":"16",
    "addr:postcode":"17824",
    "addr:street":"Center St",
    "iso:country":"US",
    "sg:address":"16 E Center St",
    "sg:city":"Elysburg",
    "sg:classifiers":[
        {
            "category":"Building & Trades",
            "subcategory":"Pest Control",
            "type":"Services"
        }
    ],
    "sg:phone":"+1   ",
    "sg:postcode":"17824",
    "sg:province":"PA",
    "wof:name":"Kibosh Pest Control LLC",
    "wof:placetype":"venue"
},
  "geometry": {"coordinates":[-76.54870099999999,40.866465],"type":"Point"}
}