{
  "type": "Feature",
  "properties": {
    "iso:country":"US",
    "sg:address":"525 Brusselles St",
    "sg:city":"St Marys",
    "sg:classifiers":[
        {
            "category":"Personal",
            "subcategory":"Beauty Salon",
            "type":"Services"
        }
    ],
    "sg:phone":"+1 814 834 1065",
    "sg:postcode":"15857",
    "sg:province":"PA",
    "sg:tags":[
        "manicuring"
    ],
    "wof:name":"Constable Nail Xtreme",
    "wof:placetype":"venue"
},
  "geometry": {"coordinates":[-78.551063,41.428583],"type":"Point"}
}