{
  "type": "Feature",
  "properties": {
    "addr:full":"285 Highland Ave Pittsburgh PA 15229",
    "addr:housenumber":"285",
    "addr:postcode":"15229",
    "addr:street":"Highland Ave",
    "iso:country":"US",
    "sg:address":"285 Highland Ave",
    "sg:city":"Pittsburgh",
    "sg:classifiers":[
        {
            "category":"Organizations",
            "subcategory":"Religious Organization",
            "type":"Services"
        }
    ],
    "sg:phone":"+1 412 931 4500",
    "sg:postcode":"15229",
    "sg:province":"PA",
    "sg:tags":[
        "church"
    ],
    "wof:name":"Mt Calvary Evangelical Luth",
    "wof:placetype":"venue"
},
  "geometry": {"coordinates":[-80.038504,40.522275],"type":"Point"}
}