{
  "type": "Feature",
  "properties": {
    "addr:full":"1515 Market St Philadelphia PA 19102",
    "addr:housenumber":"1515",
    "addr:postcode":"19102",
    "addr:street":"Market St",
    "iso:country":"US",
    "sg:address":"1515 Market St",
    "sg:city":"Philadelphia",
    "sg:classifiers":[
        {
            "category":"Ice Cream",
            "type":"Food & Drink"
        }
    ],
    "sg:menulink":"http://www.allmenus.com/pa/philadelphia/209251-tcby/menu/",
    "sg:phone":"+1 215 568 1978",
    "sg:postcode":"19102",
    "sg:province":"PA",
    "sg:tags":[
        "smoothy",
        "juice",
        "american"
    ],
    "wof:name":"TCBY",
    "wof:placetype":"venue"
},
  "geometry": {"coordinates":[-75.165475,39.952621],"type":"Point"}
}