{
  "type": "Feature",
  "properties": {
    "addr:full":"4616 Leiper St Philadelphia PA 19124",
    "addr:postcode":"4616;19124",
    "addr:street":"Leiper St",
    "iso:country":"US",
    "sg:address":"4616 Leiper St",
    "sg:city":"Philadelphia",
    "sg:classifiers":[
        {
            "category":"Real Estate",
            "subcategory":"Real Estate Agent",
            "type":"Services"
        }
    ],
    "sg:phone":"+1 215 535 5970",
    "sg:postcode":"19124",
    "sg:province":"PA",
    "wof:name":"Malita Realtors LLC",
    "wof:placetype":"venue"
},
  "geometry": {"coordinates":[-75.087484,40.016725],"type":"Point"}
}