{
  "type": "Feature",
  "properties": {
    "addr:full":"1580 McLaughlin Run Rd Pittsburgh PA 15241",
    "addr:housenumber":"1580",
    "addr:postcode":"15241",
    "addr:street":"Mclaughlin Run Rd",
    "iso:country":"US",
    "sg:address":"1580 McLaughlin Run Rd",
    "sg:city":"Pittsburgh",
    "sg:classifiers":[
        {
            "category":"Banks & Credit Unions",
            "subcategory":"Investment Brokerage",
            "type":"Services"
        }
    ],
    "sg:phone":"+1 412 257 9793",
    "sg:postcode":"15241",
    "sg:province":"PA",
    "sg:tags":[
        "security"
    ],
    "wof:name":"Raymond James Financial Svc",
    "wof:placetype":"venue"
},
  "geometry": {"coordinates":[-80.093671,40.356163],"type":"Point"}
}