{
  "type": "Feature",
  "properties": {
    "addr:full":"2101 Blair Mill Rd Horsham PA 19044",
    "addr:housenumber":"2101",
    "addr:postcode":"19044",
    "addr:street":"Blair Mill Rd",
    "iso:country":"US",
    "sg:address":"2101 Blair Mill Rd",
    "sg:city":"Horsham",
    "sg:classifiers":[
        {
            "category":"Banks & Credit Unions",
            "subcategory":"Bank",
            "type":"Services"
        }
    ],
    "sg:phone":"+1 215 706 2093",
    "sg:postcode":"19044",
    "sg:province":"PA",
    "sg:website":"http://www.woodforest.com/",
    "wof:name":"Woodforest National Bank",
    "wof:placetype":"venue"
},
  "geometry": {"coordinates":[-75.125664,40.173546],"type":"Point"}
}