{
  "type": "Feature",
  "properties": {
    "addr:full":"28 E Main St Plymouth PA 18651",
    "addr:housenumber":"28",
    "addr:postcode":"18651",
    "addr:street":"E Main St",
    "iso:country":"US",
    "sg:address":"28 E Main St",
    "sg:city":"Plymouth",
    "sg:classifiers":[
        {
            "category":"Retail",
            "subcategory":"Repair Shop",
            "type":"Services"
        }
    ],
    "sg:phone":"+1 570 779 4006",
    "sg:postcode":"18651",
    "sg:province":"PA",
    "sg:tags":[
        "radio",
        "television",
        "equipment-installation",
        "video"
    ],
    "wof:name":"Charlie's Tv",
    "wof:placetype":"venue"
},
  "geometry": {"coordinates":[-75.944664,41.240836],"type":"Point"}
}