{
  "type": "Feature",
  "properties": {
    "iso:country":"US",
    "sg:address":"1010 Pulinski Rd",
    "sg:city":"Warminster",
    "sg:classifiers":[
        {
            "category":"Manufacturing",
            "subcategory":"Glass & Minerals",
            "type":"Manufacturing & Wholesale Goods"
        }
    ],
    "sg:phone":"+1 215 956 9711",
    "sg:postcode":"18974",
    "sg:province":"PA",
    "sg:tags":[
        "product",
        "marble"
    ],
    "wof:name":"Suburban Marble & Granite",
    "wof:placetype":"venue"
},
  "geometry": {"coordinates":[-75.05649699999999,40.220531],"type":"Point"}
}