{
  "type": "Feature",
  "properties": {
    "iso:country":"US",
    "sg:address":"642 Beaver St",
    "sg:city":"Bristol",
    "sg:classifiers":[
        {
            "category":"Banks & Credit Unions",
            "subcategory":"Bank",
            "type":"Services"
        }
    ],
    "sg:phone":"+1 215 785 2530",
    "sg:postcode":"19007",
    "sg:province":"PA",
    "sg:tags":[
        "mortgage",
        "loan",
        "broker",
        "real estate"
    ],
    "sg:website":"www.brigantinemortgage.com",
    "wof:name":"Brigantine Mortgage",
    "wof:placetype":"venue"
},
  "geometry": {"coordinates":[-74.855964,40.102664],"type":"Point"}
}