{
  "type": "Feature",
  "properties": {
    "addr:full":"503 Luther St Windber PA 15963",
    "addr:housenumber":"503",
    "addr:postcode":"15963",
    "addr:street":"Luther St",
    "iso:country":"US",
    "sg:address":"503 Luther St",
    "sg:city":"Windber",
    "sg:classifiers":[
        {
            "category":"Manufacturing",
            "subcategory":"Glass & Minerals",
            "type":"Manufacturing & Wholesale Goods"
        }
    ],
    "sg:phone":"+1   ",
    "sg:postcode":"15963",
    "sg:province":"PA",
    "sg:tags":[
        "concrete",
        "product",
        "mfg"
    ],
    "wof:name":"Windber Pre Cast",
    "wof:placetype":"venue"
},
  "geometry": {"coordinates":[-78.842366,40.245399],"type":"Point"}
}