{
  "type": "Feature",
  "properties": {
    "iso:country":"US",
    "sg:address":"368 Moorheadville Rd",
    "sg:city":"North East",
    "sg:classifiers":[
        {
            "category":"Building & Trades",
            "subcategory":"Construction",
            "type":"Services"
        }
    ],
    "sg:phone":"+1   ",
    "sg:postcode":"16428",
    "sg:province":"PA",
    "sg:tags":[
        "house"
    ],
    "wof:name":"Stephen P Jones Bldg & Rmdlg",
    "wof:placetype":"venue"
},
  "geometry": {"coordinates":[-79.912567,42.202426],"type":"Point"}
}