{
  "type": "Feature",
  "properties": {
    "addr:full":"334 Washington St Johnstown PA 15901",
    "addr:housenumber":"334",
    "addr:postcode":"15901",
    "addr:street":"Washington St",
    "iso:country":"US",
    "sg:address":"334 Washington St",
    "sg:city":"Johnstown",
    "sg:classifiers":[
        {
            "category":"Government",
            "subcategory":"Office",
            "type":"Public Place"
        }
    ],
    "sg:phone":"+1 814 533 4464",
    "sg:postcode":"15901",
    "sg:province":"PA",
    "sg:tags":[
        "federal",
        "human"
    ],
    "wof:name":"US Social Security Adm",
    "wof:placetype":"venue"
},
  "geometry": {"coordinates":[-78.91898999999999,40.327457],"type":"Point"}
}