{
  "type": "Feature",
  "properties": {
    "iso:country":"US",
    "sg:address":"1250 Butler St",
    "sg:city":"Easton",
    "sg:classifiers":[
        {
            "category":"Restaurant",
            "type":"Food & Drink"
        }
    ],
    "sg:phone":"+1 610 559 5984",
    "sg:postcode":"18042",
    "sg:province":"PA",
    "sg:tags":[
        "eating"
    ],
    "wof:name":"Lutzi's Courtyard Cafe",
    "wof:placetype":"venue"
},
  "geometry": {"coordinates":[-75.227565,40.685587],"type":"Point"}
}