{
  "type": "Feature",
  "properties": {
    "iso:country":"US",
    "sg:address":"2370 Broadway Rd",
    "sg:city":"Hermitage",
    "sg:classifiers":[
        {
            "category":"Autos & Motor Vehicles",
            "subcategory":"Auto Supplies",
            "type":"Retail Goods"
        }
    ],
    "sg:phone":"+1   ",
    "sg:postcode":"16148",
    "sg:province":"PA",
    "sg:tags":[
        "parts"
    ],
    "wof:name":"Reville Warehouse",
    "wof:placetype":"venue"
},
  "geometry": {"coordinates":[-80.46243699999999,41.189768],"type":"Point"}
}