{
  "type": "Feature",
  "properties": {
    "iso:country":"US",
    "sg:address":"2228 Pleasant Ave",
    "sg:city":"Glenside",
    "sg:classifiers":[
        {
            "category":"Education",
            "subcategory":"Special Training",
            "type":"Public Place"
        }
    ],
    "sg:phone":"+1 215 885 0672",
    "sg:postcode":"19038",
    "sg:province":"PA",
    "sg:tags":[
        "educational"
    ],
    "sg:website":"www.know-power.com",
    "wof:name":"Know Power",
    "wof:placetype":"venue"
},
  "geometry": {"coordinates":[-75.14058300000001,40.111369],"type":"Point"}
}