{
  "type": "Feature",
  "properties": {
    "iso:country":"US",
    "sg:address":"45 Gateway Dr",
    "sg:city":"Mechanicsburg",
    "sg:classifiers":[
        {
            "category":"Home & Garden",
            "subcategory":"Household Appliances",
            "type":"Retail Goods"
        }
    ],
    "sg:phone":"+1 717 691 9638",
    "sg:postcode":"17050",
    "sg:province":"PA",
    "sg:tags":[
        "repair",
        "shopping",
        "cleaner",
        "sewing",
        "machine",
        "vacuum"
    ],
    "wof:name":"Discount Vacuum & Sewing Center",
    "wof:placetype":"venue"
},
  "geometry": {"coordinates":[-76.98049899999999,40.2379],"type":"Point"}
}