{
  "type": "Feature",
  "properties": {
    "iso:country":"US",
    "sg:address":"745 Acacia Ave",
    "sg:city":"Reading",
    "sg:classifiers":[
        {
            "category":"Professional",
            "subcategory":"Accounting & Tax Preparation",
            "type":"Services"
        }
    ],
    "sg:phone":"+1 610 929 3286",
    "sg:postcode":"19605",
    "sg:province":"PA",
    "sg:tags":[
        "accountant"
    ],
    "wof:name":"Harold E Wounderly CPA",
    "wof:placetype":"venue"
},
  "geometry": {"coordinates":[-75.949364,40.391519],"type":"Point"}
}