{
  "type": "Feature",
  "properties": {
    "iso:country":"US",
    "sg:address":"125 W Chester Rd",
    "sg:city":"West Chester",
    "sg:classifiers":[
        {
            "category":"Real Estate",
            "subcategory":"Architect",
            "type":"Services"
        }
    ],
    "sg:phone":"+1 610 692 9112",
    "sg:postcode":"19382",
    "sg:province":"PA",
    "sg:tags":[
        "architectural"
    ],
    "sg:website":"www.archerbuchanan.com",
    "wof:name":"Archer & Buchanan Architecture",
    "wof:placetype":"venue"
},
  "geometry": {"coordinates":[-75.54428299999999,39.910773],"type":"Point"}
}