{
  "type": "Feature",
  "properties": {
    "iso:country":"US",
    "sg:address":"7 Hunting Hills Dr",
    "sg:city":"Kemblesville",
    "sg:classifiers":[
        {
            "category":"Retail",
            "subcategory":"Repair Shop",
            "type":"Services"
        }
    ],
    "sg:phone":"+1 610 255 5466",
    "sg:postcode":"19350",
    "sg:province":"PA",
    "sg:tags":[
        "lock",
        "locksmith"
    ],
    "wof:name":"Cole's Lock & Key",
    "wof:placetype":"venue"
},
  "geometry": {"coordinates":[-75.81368999999999,39.779706],"type":"Point"}
}