{
  "type": "Feature",
  "properties": {
    "iso:country":"US",
    "sg:address":"110 Awesome Dr",
    "sg:city":"Nazareth",
    "sg:classifiers":[
        {
            "category":"Building & Trades",
            "subcategory":"Electrical",
            "type":"Services"
        }
    ],
    "sg:phone":"+1 610 746 0485",
    "sg:postcode":"18064",
    "sg:province":"PA",
    "sg:tags":[
        "electrical",
        "contractor"
    ],
    "wof:name":"Steve Miskowski",
    "wof:placetype":"venue"
},
  "geometry": {"coordinates":[-75.269136,40.784412],"type":"Point"}
}