{
  "type": "Feature",
  "properties": {
    "iso:country":"US",
    "sg:address":"335 W Main St",
    "sg:city":"Grove City",
    "sg:classifiers":[
        {
            "category":"Shopping",
            "subcategory":"Used Merchandise",
            "type":"Retail Goods"
        }
    ],
    "sg:phone":"+1   ",
    "sg:postcode":"16127",
    "sg:province":"PA",
    "wof:name":"Estella May Inn",
    "wof:placetype":"venue"
},
  "geometry": {"coordinates":[-80.09120299999999,41.15956],"type":"Point"}
}