{
  "type": "Feature",
  "properties": {
    "iso:country":"US",
    "sg:address":"514 Brunswick Dr",
    "sg:city":"Greensburg",
    "sg:classifiers":[
        {
            "category":"Professional",
            "subcategory":"Computer Services",
            "type":"Services"
        }
    ],
    "sg:phone":"+1 724 850 2420",
    "sg:postcode":"15601",
    "sg:province":"PA",
    "sg:tags":[
        "leasing"
    ],
    "wof:name":"Merrimak Capital Co",
    "wof:placetype":"venue"
},
  "geometry": {"coordinates":[-79.514578,40.263339],"type":"Point"}
}