{
  "type": "Feature",
  "properties": {
    "addr:full":"44 Monongahela Ave  Glassport PA 15045",
    "addr:housenumber":"44",
    "addr:postcode":"15045",
    "addr:street":"Monongahela Ave",
    "iso:country":"US",
    "sg:address":"44 Monongahela Ave ",
    "sg:city":"Glassport",
    "sg:classifiers":[
        {
            "category":"Restaurant",
            "type":"Food & Drink"
        }
    ],
    "sg:menulink":"http://www.allmenus.com/pa/glassport/287318-mama-pepinos-pizza--billiards/menu/",
    "sg:phone":"+1 412 672 0705",
    "sg:postcode":"15045",
    "sg:province":"PA",
    "sg:tags":[
        "american",
        "pizza"
    ],
    "wof:name":"Mama Pepino's Pizza & Billiards",
    "wof:placetype":"venue"
},
  "geometry": {"coordinates":[-79.890762,40.335665],"type":"Point"}
}