{
  "type": "Feature",
  "properties": {
    "iso:country":"US",
    "sg:address":"715 Pine St",
    "sg:city":"Montoursville",
    "sg:classifiers":[
        {
            "category":"Retail",
            "subcategory":"Auto Repair",
            "type":"Services"
        }
    ],
    "sg:phone":"+1   ",
    "sg:postcode":"17754",
    "sg:province":"PA",
    "sg:tags":[
        "transmission"
    ],
    "wof:name":"Carussos Transmissions",
    "wof:placetype":"venue"
},
  "geometry": {"coordinates":[-76.914748,41.259529],"type":"Point"}
}