{
  "type": "Feature",
  "properties": {
    "addr:full":"201 Stanwix St Pittsburgh PA 15222",
    "addr:housenumber":"201",
    "addr:postcode":"15222",
    "addr:street":"Stanwix St",
    "iso:country":"US",
    "sg:address":"201 Stanwix St",
    "sg:city":"Pittsburgh",
    "sg:classifiers":[
        {
            "category":"Utilities",
            "subcategory":"Telephone",
            "type":"Services"
        }
    ],
    "sg:phone":"+1   ",
    "sg:postcode":"15222",
    "sg:province":"PA",
    "sg:tags":[
        "communications",
        "radiotelephone",
        "merchandise",
        "communication"
    ],
    "wof:name":"Verizon",
    "wof:placetype":"venue"
},
  "geometry": {"coordinates":[-80.00382,40.441395],"type":"Point"}
}