{
  "type": "Feature",
  "properties": {
    "iso:country":"US",
    "sg:address":"3301 N Front St",
    "sg:city":"Philadelphia",
    "sg:classifiers":[
        {
            "category":"Building & Trades",
            "subcategory":"Locksmith",
            "type":"Services"
        }
    ],
    "sg:phone":"+1 267 773 5484",
    "sg:postcode":"19140",
    "sg:province":"PA",
    "sg:tags":[
        "key"
    ],
    "wof:name":"7 Day 24 Hours Emergency Locksmith",
    "wof:placetype":"venue"
},
  "geometry": {"coordinates":[-75.12873500000001,40.00009],"type":"Point"}
}