{
  "type": "Feature",
  "properties": {
    "addr:full":"433 Rehobeth Church Rd Perryopolis PA 15473",
    "addr:housenumber":"433",
    "addr:postcode":"15473",
    "addr:street":"Rehobeth Church Rd",
    "iso:country":"US",
    "sg:address":"433 Rehobeth Church Rd",
    "sg:city":"Perryopolis",
    "sg:classifiers":[
        {
            "category":"Utilities",
            "subcategory":"Refuse",
            "type":"Services"
        }
    ],
    "sg:phone":"+1 724 736 0937",
    "sg:postcode":"15473",
    "sg:province":"PA",
    "sg:tags":[
        "system"
    ],
    "wof:name":"D B Disposal Inc",
    "wof:placetype":"venue"
},
  "geometry": {"coordinates":[-79.78733,40.1106],"type":"Point"}
}