{
  "type": "Feature",
  "properties": {
    "addr:full":"101 Kurtz Ln Coatesville PA 19320",
    "addr:housenumber":"101",
    "addr:postcode":"19320",
    "addr:street":"Kurtz Ln",
    "iso:country":"US",
    "sg:address":"101 Kurtz Ln",
    "sg:city":"Coatesville",
    "sg:classifiers":[
        {
            "category":"Professional",
            "subcategory":"Lawyer & Legal Services",
            "type":"Services"
        }
    ],
    "sg:phone":"+1 610 380 5007",
    "sg:postcode":"19320",
    "sg:province":"PA",
    "sg:tags":[
        "clinic"
    ],
    "wof:name":"Medical Litigation Support",
    "wof:placetype":"venue"
},
  "geometry": {"coordinates":[-75.834457,40.03952],"type":"Point"}
}