{
  "type": "Feature",
  "properties": {
    "addr:full":"1429 Pleasant Valley Blvd Altoona PA 16602",
    "addr:housenumber":"1429",
    "addr:postcode":"16602",
    "addr:street":"Pleasant Valley Blvd",
    "iso:country":"US",
    "sg:address":"1429 Pleasant Valley Blvd",
    "sg:city":"Altoona",
    "sg:classifiers":[
        {
            "category":"Autos & Motor Vehicles",
            "subcategory":"Automobile Sales",
            "type":"Retail Goods"
        }
    ],
    "sg:phone":"+1   ",
    "sg:postcode":"16602",
    "sg:province":"PA",
    "sg:tags":[
        "used"
    ],
    "wof:name":"Unlimited Cycle Center",
    "wof:placetype":"venue"
},
  "geometry": {"coordinates":[-78.38836499999999,40.504469],"type":"Point"}
}