{
  "type": "Feature",
  "properties": {
    "iso:country":"US",
    "sg:address":"1539 Mount Rose Ave",
    "sg:city":"York",
    "sg:classifiers":[
        {
            "category":"Restaurant",
            "type":"Food & Drink"
        }
    ],
    "sg:menulink":"http://www.allmenus.com/pa/spring-garden/66201-dominos-pizza/menu/",
    "sg:phone":"+1 717 854 9515",
    "sg:postcode":"17403",
    "sg:province":"PA",
    "sg:tags":[
        "american",
        "wing",
        "pizza"
    ],
    "wof:name":"Domino's Pizza",
    "wof:placetype":"venue"
},
  "geometry": {"coordinates":[-76.692984,39.958622],"type":"Point"}
}