{
  "type": "Feature",
  "properties": {
    "iso:country":"US",
    "sg:address":"752 Main St",
    "sg:city":"Pennsburg",
    "sg:classifiers":[
        {
            "category":"Autos & Motor Vehicles",
            "subcategory":"Auto Supplies",
            "type":"Retail Goods"
        }
    ],
    "sg:phone":"+1 215 679 9521",
    "sg:postcode":"18073",
    "sg:province":"PA",
    "sg:tags":[
        "automobile",
        "parts"
    ],
    "wof:name":"NAPA Auto Parts",
    "wof:placetype":"venue"
},
  "geometry": {"coordinates":[-75.492261,40.391167],"type":"Point"}
}