{
  "type": "Feature",
  "properties": {
    "addr:full":"5975 Buman Rd Mc Kean PA 16426",
    "addr:housenumber":"5975",
    "addr:postcode":"16426",
    "addr:street":"Buman Rd",
    "iso:country":"US",
    "sg:address":"5975 Buman Rd",
    "sg:city":"Mc Kean",
    "sg:classifiers":[
        {
            "category":"Building & Trades",
            "subcategory":"Construction",
            "type":"Services"
        }
    ],
    "sg:phone":"+1 814 476 7886",
    "sg:postcode":"16426",
    "sg:province":"PA",
    "sg:tags":[
        "masonry",
        "contractor"
    ],
    "wof:name":"R Moran Company Inc",
    "wof:placetype":"venue"
},
  "geometry": {"coordinates":[-80.160177,42.019402],"type":"Point"}
}