{
  "type": "Feature",
  "properties": {
    "iso:country":"US",
    "sg:address":"320 Thomas St",
    "sg:city":"Jersey Shore",
    "sg:classifiers":[
        {
            "category":"Restaurant",
            "type":"Food & Drink"
        }
    ],
    "sg:phone":"+1   ",
    "sg:postcode":"17740",
    "sg:province":"PA",
    "sg:tags":[
        "eating"
    ],
    "wof:name":"Hot Stuff",
    "wof:placetype":"venue"
},
  "geometry": {"coordinates":[-77.27672099999999,41.206491],"type":"Point"}
}