{
  "type": "Feature",
  "properties": {
    "addr:full":"3480 York Haven Rd Manchester PA 17345",
    "addr:housenumber":"3480",
    "addr:postcode":"17345",
    "addr:street":"York Haven Rd",
    "iso:country":"US",
    "sg:address":"3480 York Haven Rd",
    "sg:city":"Manchester",
    "sg:classifiers":[
        {
            "category":"Restaurant",
            "type":"Food & Drink"
        }
    ],
    "sg:phone":"+1 717 266 1376",
    "sg:postcode":"17345",
    "sg:province":"PA",
    "wof:name":"Conewago Inn",
    "wof:placetype":"venue"
},
  "geometry": {"coordinates":[-76.71392899999999,40.105185],"type":"Point"}
}