{
  "type": "Feature",
  "properties": {
    "addr:full":"209 W Pine St Selinsgrove PA 17870",
    "addr:housenumber":"209",
    "addr:postcode":"17870",
    "addr:street":"W Pine St",
    "iso:country":"US",
    "sg:address":"209 W Pine St",
    "sg:city":"Selinsgrove",
    "sg:classifiers":[
        {
            "category":"Restaurant",
            "type":"Food & Drink"
        }
    ],
    "sg:phone":"+1 570 372 0805",
    "sg:postcode":"17870",
    "sg:province":"PA",
    "sg:tags":[
        "eating"
    ],
    "wof:name":"Campus Candlelight Cafe",
    "wof:placetype":"venue"
},
  "geometry": {"coordinates":[-76.864733,40.799756],"type":"Point"}
}