{
  "type": "Feature",
  "properties": {
    "iso:country":"US",
    "sg:address":"23568 Kunz Rd",
    "sg:city":"Pleasantville",
    "sg:classifiers":[
        {
            "category":"Transit Center",
            "subcategory":"Freight",
            "type":"Transportation"
        },
        {
            "category":"Freight",
            "type":"Transportation"
        }
    ],
    "sg:phone":"+1 814 827 1113",
    "sg:postcode":"16341",
    "sg:province":"PA",
    "sg:tags":[
        "local",
        "trucking-motor",
        "trucking"
    ],
    "wof:name":"Ralph A Walters Inc",
    "wof:placetype":"venue"
},
  "geometry": {"coordinates":[-79.633545,41.602798],"type":"Point"}
}