{
  "type": "Feature",
  "properties": {
    "addr:full":"5938 Spires Dr Erie PA 16509",
    "addr:housenumber":"5938",
    "addr:postcode":"16509",
    "addr:street":"Spires Dr",
    "iso:country":"US",
    "sg:address":"5938 Spires Dr",
    "sg:city":"Erie",
    "sg:classifiers":[
        {
            "category":"Retail",
            "subcategory":"Portrait Studio",
            "type":"Services"
        }
    ],
    "sg:phone":"+1 814 864 3088",
    "sg:postcode":"16509",
    "sg:province":"PA",
    "sg:tags":[
        "photographer"
    ],
    "wof:name":"Lifetouch National School Stu",
    "wof:placetype":"venue"
},
  "geometry": {"coordinates":[-80.094911,42.064606],"type":"Point"}
}