{
  "type": "Feature",
  "properties": {
    "iso:country":"US",
    "sg:address":"368 F Ave",
    "sg:city":"Pittsburgh",
    "sg:classifiers":[
        {
            "category":"Building & Trades",
            "subcategory":"Construction",
            "type":"Services"
        }
    ],
    "sg:phone":"+1   ",
    "sg:postcode":"15221",
    "sg:province":"PA",
    "sg:tags":[
        "hanging",
        "contractor"
    ],
    "wof:name":"Purdue Painting",
    "wof:placetype":"venue"
},
  "geometry": {"coordinates":[-79.842512,40.415006],"type":"Point"}
}