{
  "type": "Feature",
  "properties": {
    "addr:full":"1425 Arch St Lbby Philadelphia PA 19102",
    "addr:housenumber":"1425",
    "addr:postcode":"19102",
    "addr:street":"Arch St",
    "iso:country":"US",
    "sg:address":"1425 Arch St Lbby",
    "sg:city":"Philadelphia",
    "sg:classifiers":[
        {
            "category":"Health Services",
            "subcategory":"Chiropractor",
            "type":"Services"
        }
    ],
    "sg:phone":"+1 215 557 9090",
    "sg:postcode":"19102",
    "sg:province":"PA",
    "wof:name":"Shuffler Brian DC",
    "wof:placetype":"venue"
},
  "geometry": {"coordinates":[-75.163597,39.954605],"type":"Point"}
}