{
  "type": "Feature",
  "properties": {
    "iso:country":"US",
    "sg:address":"5 Front St",
    "sg:city":"Mohnton",
    "sg:classifiers":[
        {
            "category":"Manufacturing",
            "subcategory":"Tools & Machinery",
            "type":"Manufacturing & Wholesale Goods"
        }
    ],
    "sg:phone":"+1 610 775 3323",
    "sg:postcode":"19540",
    "sg:province":"PA",
    "sg:tags":[
        "a",
        "jobbing",
        "machine",
        "shop",
        "operates"
    ],
    "sg:website":"www.jomamachine.com",
    "wof:name":"Joma Machine Co Inc",
    "wof:placetype":"venue"
},
  "geometry": {"coordinates":[-75.978758,40.285329],"type":"Point"}
}