{
  "type": "Feature",
  "properties": {
    "iso:country":"US",
    "sg:address":"416 Main St",
    "sg:city":"Hellertown",
    "sg:classifiers":[
        {
            "category":"Professional",
            "subcategory":"Lawyer & Legal Services",
            "type":"Services"
        }
    ],
    "sg:phone":"+1 610 838 9288",
    "sg:postcode":"18055",
    "sg:province":"PA",
    "sg:tags":[
        "notary"
    ],
    "wof:name":"Krick S V Notary Public",
    "wof:placetype":"venue"
},
  "geometry": {"coordinates":[-75.34079800000001,40.576606],"type":"Point"}
}