{
  "type": "Feature",
  "properties": {
    "addr:full":"1749 Grandville Cir Jamison PA 18929",
    "addr:housenumber":"1749",
    "addr:postcode":"18929",
    "addr:street":"Grandville Cir",
    "iso:country":"US",
    "sg:address":"1749 Grandville Cir",
    "sg:city":"Jamison",
    "sg:classifiers":[
        {
            "category":"Wholesale",
            "subcategory":"Chemicals & Plastics",
            "type":"Manufacturing & Wholesale Goods"
        }
    ],
    "sg:phone":"+1   ",
    "sg:postcode":"18929",
    "sg:province":"PA",
    "wof:name":"Trelleborg Sealing Solutions",
    "wof:placetype":"venue"
},
  "geometry": {"coordinates":[-75.10799799999999,40.248454],"type":"Point"}
}