{
  "type": "Feature",
  "properties": {
    "addr:full":"12646 Reed Ave Conneaut Lake PA 16316",
    "addr:housenumber":"12646",
    "addr:postcode":"16316",
    "addr:street":"Reed Ave",
    "iso:country":"US",
    "sg:address":"12646 Reed Ave",
    "sg:city":"Conneaut Lake",
    "sg:classifiers":[
        {
            "category":"Shopping",
            "subcategory":"Gifts & Souvenirs",
            "type":"Retail Goods"
        }
    ],
    "sg:phone":"+1   ",
    "sg:postcode":"16316",
    "sg:province":"PA",
    "sg:tags":[
        "floral",
        "supply",
        "arrangement"
    ],
    "wof:name":"Surprise Package",
    "wof:placetype":"venue"
},
  "geometry": {"coordinates":[-80.322526,41.642114],"type":"Point"}
}