{
  "type": "Feature",
  "properties": {
    "iso:country":"US",
    "sg:address":"152 Mathers Rd",
    "sg:city":"Ambler",
    "sg:classifiers":[
        {
            "category":"Professional",
            "subcategory":"Management & Consulting",
            "type":"Services"
        }
    ],
    "sg:phone":"+1 215 591 9803",
    "sg:postcode":"19002",
    "sg:province":"PA",
    "sg:tags":[
        "consultant",
        "energy",
        "conservation"
    ],
    "wof:name":"Keystone Energy Technicians",
    "wof:placetype":"venue"
},
  "geometry": {"coordinates":[-75.23845799999999,40.16231],"type":"Point"}
}