{
  "type": "Feature",
  "properties": {
    "addr:full":"1005 N 5th St Philadelphia PA 19123",
    "addr:housenumber":"1005",
    "addr:postcode":"19123",
    "addr:street":"N 5Th St",
    "iso:country":"US",
    "sg:address":"1005 N 5th St",
    "sg:city":"Philadelphia",
    "sg:classifiers":[
        {
            "category":"Organizations",
            "subcategory":"Religious Organization",
            "type":"Services"
        }
    ],
    "sg:phone":"+1 215 627 4794",
    "sg:postcode":"19123",
    "sg:province":"PA",
    "sg:tags":[
        "monastery",
        "convent"
    ],
    "wof:name":"St Peter's Convent",
    "wof:placetype":"venue"
},
  "geometry": {"coordinates":[-75.144954,39.970125],"type":"Point"}
}