{
  "type": "Feature",
  "properties": {
    "iso:country":"US",
    "sg:address":"742 Wertzville Rd",
    "sg:city":"Enola",
    "sg:classifiers":[
        {
            "category":"Banks & Credit Unions",
            "subcategory":"Bank",
            "type":"Services"
        },
        {
            "category":"Banks & Credit Unions",
            "subcategory":"Financial Services",
            "type":"Services"
        }
    ],
    "sg:phone":"+1 717 909 6700",
    "sg:postcode":"17025",
    "sg:province":"PA",
    "sg:tags":[
        "commercial",
        "loan",
        "saving"
    ],
    "sg:website":"www.commercepc.com",
    "wof:name":"Commerce Bank",
    "wof:placetype":"venue"
},
  "geometry": {"coordinates":[-76.946701,40.2878],"type":"Point"}
}