{
  "type": "Feature",
  "properties": {
    "addr:full":"509 E High St Pottstown PA 19464",
    "addr:housenumber":"509",
    "addr:postcode":"19464",
    "addr:street":"E High St",
    "iso:country":"US",
    "sg:address":"509 E High St",
    "sg:city":"Pottstown",
    "sg:classifiers":[
        {
            "category":"Shopping",
            "type":"Retail Goods"
        }
    ],
    "sg:phone":"+1 610 326 8841",
    "sg:postcode":"19464",
    "sg:province":"PA",
    "sg:tags":[
        "trophy",
        "medal",
        "merchandise",
        "award"
    ],
    "wof:name":"Trophy & Plaque Shack",
    "wof:placetype":"venue"
},
  "geometry": {"coordinates":[-75.64173,40.244662],"type":"Point"}
}