{
  "type": "Feature",
  "properties": {
    "iso:country":"US",
    "sg:address":"363 S Negley Ave",
    "sg:city":"Pittsburgh",
    "sg:classifiers":[
        {
            "category":"Retail",
            "subcategory":"Auto Repair",
            "type":"Services"
        }
    ],
    "sg:phone":"+1 412 661 3960",
    "sg:postcode":"15232",
    "sg:province":"PA",
    "sg:tags":[
        "repairing",
        "automobile",
        "radiator"
    ],
    "wof:name":"Graham Radiator Repair",
    "wof:placetype":"venue"
},
  "geometry": {"coordinates":[-79.933003,40.459793],"type":"Point"}
}