{
  "type": "Feature",
  "properties": {
    "iso:country":"US",
    "sg:address":"1735 Sylvan Ave",
    "sg:city":"Natrona Heights",
    "sg:classifiers":[
        {
            "category":"Restaurant",
            "type":"Food & Drink"
        }
    ],
    "sg:phone":"+1   ",
    "sg:postcode":"15065",
    "sg:province":"PA",
    "sg:tags":[
        "eating"
    ],
    "wof:name":"P & M Pizza",
    "wof:placetype":"venue"
},
  "geometry": {"coordinates":[-79.723366,40.634043],"type":"Point"}
}