{
  "type": "Feature",
  "properties": {
    "iso:country":"US",
    "sg:address":"2 Cadwell Ave",
    "sg:city":"Waverly",
    "sg:classifiers":[
        {
            "category":"Retail",
            "subcategory":"Repair Shop",
            "type":"Services"
        }
    ],
    "sg:phone":"+1   ",
    "sg:postcode":"14892",
    "sg:province":"PA",
    "wof:name":"Plus Typewriter",
    "wof:placetype":"venue"
},
  "geometry": {"coordinates":[-76.54561699999999,42.006603],"type":"Point"}
}