{
  "type": "Feature",
  "properties": {
    "addr:full":"1035 N Ridge Rd Perkasie PA 18944",
    "addr:housenumber":"1035",
    "addr:postcode":"18944",
    "addr:street":"N Ridge Rd",
    "iso:country":"US",
    "sg:address":"1035 N Ridge Rd",
    "sg:city":"Perkasie",
    "sg:classifiers":[
        {
            "category":"Building & Trades",
            "subcategory":"Construction",
            "type":"Services"
        }
    ],
    "sg:phone":"+1 215 257 6044",
    "sg:postcode":"18944",
    "sg:province":"PA",
    "sg:tags":[
        "roofing",
        "contractor"
    ],
    "wof:name":"Pennridge Roofing & Siding Inc",
    "wof:placetype":"venue"
},
  "geometry": {"coordinates":[-75.28860299999999,40.384586],"type":"Point"}
}