{
  "type": "Feature",
  "properties": {
    "addr:full":"19 W Market St Jonestown PA 17038",
    "addr:housenumber":"19",
    "addr:postcode":"17038",
    "addr:street":"W Market St",
    "iso:country":"US",
    "sg:address":"19 W Market St",
    "sg:city":"Jonestown",
    "sg:classifiers":[
        {
            "category":"Cinema",
            "subcategory":"Movie Rental",
            "type":"Entertainment"
        }
    ],
    "sg:phone":"+1 717 865 5576",
    "sg:postcode":"17038",
    "sg:province":"PA",
    "sg:tags":[
        "leasing",
        "video",
        "disc",
        "tape"
    ],
    "wof:name":"Pop Video",
    "wof:placetype":"venue"
},
  "geometry": {"coordinates":[-76.47851199999999,40.413735],"type":"Point"}
}