{
  "type": "Feature",
  "properties": {
    "iso:country":"US",
    "sg:address":"121 Willow Mill Park Rd",
    "sg:city":"Mechanicsburg",
    "sg:classifiers":[
        {
            "category":"Building & Trades",
            "subcategory":"Construction",
            "type":"Services"
        }
    ],
    "sg:phone":"+1 717 691 8013",
    "sg:postcode":"17050",
    "sg:province":"PA",
    "sg:tags":[
        "company"
    ],
    "wof:name":"Crawford Construction",
    "wof:placetype":"venue"
},
  "geometry": {"coordinates":[-77.05075600000001,40.257574],"type":"Point"}
}