{
  "type": "Feature",
  "properties": {
    "iso:country":"US",
    "sg:address":"23 S Center St",
    "sg:city":"Coal Twp",
    "sg:classifiers":[
        {
            "category":"Recreation",
            "type":"Entertainment"
        }
    ],
    "sg:phone":"+1 570 648 4844",
    "sg:postcode":"17866",
    "sg:province":"PA",
    "sg:tags":[
        "bingo",
        "game",
        "card"
    ],
    "wof:name":"Mister Bingo",
    "wof:placetype":"venue"
},
  "geometry": {"coordinates":[-76.566149,40.798042],"type":"Point"}
}