{
  "type": "Feature",
  "properties": {
    "iso:country":"US",
    "sg:address":"102 Old Dublin Pike",
    "sg:city":"Doylestown",
    "sg:classifiers":[
        {
            "category":"Restaurant",
            "type":"Food & Drink"
        }
    ],
    "sg:phone":"+1   ",
    "sg:postcode":"18901",
    "sg:province":"PA",
    "sg:tags":[
        "eating"
    ],
    "wof:name":"Chambers Restaurant",
    "wof:placetype":"venue"
},
  "geometry": {"coordinates":[-75.137055,40.325956],"type":"Point"}
}