{
  "type": "Feature",
  "properties": {
    "iso:country":"US",
    "sg:address":"717 Saxonburg Blvd",
    "sg:city":"Saxonburg",
    "sg:classifiers":[
        {
            "category":"Food & Beverages",
            "subcategory":"Specialty",
            "type":"Retail Goods"
        }
    ],
    "sg:phone":"+1 724 352 9500",
    "sg:postcode":"16056",
    "sg:province":"PA",
    "sg:tags":[
        "health",
        "diet"
    ],
    "sg:website":"www.frankferd.com",
    "wof:name":"Frankferd Farms Foods",
    "wof:placetype":"venue"
},
  "geometry": {"coordinates":[-79.852451,40.714054],"type":"Point"}
}