{
  "type": "Feature",
  "properties": {
    "addr:full":"2585 Washington Rd Pittsburgh PA 15241",
    "addr:housenumber":"2585",
    "addr:postcode":"15241",
    "addr:street":"Washington Rd",
    "iso:country":"US",
    "sg:address":"2585 Washington Rd",
    "sg:city":"Pittsburgh",
    "sg:classifiers":[
        {
            "category":"Manufacturing",
            "subcategory":"Lumber",
            "type":"Manufacturing & Wholesale Goods"
        }
    ],
    "sg:phone":"+1   ",
    "sg:postcode":"15241",
    "sg:province":"PA",
    "sg:tags":[
        "a",
        "as",
        "sales",
        "operates"
    ],
    "wof:name":"Davidson Industries Inc",
    "wof:placetype":"venue"
},
  "geometry": {"coordinates":[-80.08890700000001,40.316014],"type":"Point"}
}