{
  "type": "Feature",
  "properties": {
    "addr:full":"103 Rader School Rd Renfrew PA 16053",
    "addr:housenumber":"103",
    "addr:postcode":"16053",
    "addr:street":"Rader School Rd",
    "iso:country":"US",
    "sg:address":"103 Rader School Rd",
    "sg:city":"Renfrew",
    "sg:classifiers":[
        {
            "category":"Travel",
            "subcategory":"Campground",
            "type":"Entertainment"
        }
    ],
    "sg:phone":"+1 724 789 9401",
    "sg:postcode":"16053",
    "sg:province":"PA",
    "sg:tags":[
        "camp"
    ],
    "wof:name":"Camp Redwing",
    "wof:placetype":"venue"
},
  "geometry": {"coordinates":[-79.981922,40.797935],"type":"Point"}
}