{
  "type": "Feature",
  "properties": {
    "iso:country":"US",
    "sg:address":"35 Mill St",
    "sg:city":"Port Carbon",
    "sg:classifiers":[
        {
            "category":"Recreation",
            "type":"Entertainment"
        }
    ],
    "sg:phone":"+1 570 622 6559",
    "sg:postcode":"17965",
    "sg:province":"PA",
    "sg:tags":[
        "club",
        "membership"
    ],
    "wof:name":"Port Carbon Baseball",
    "wof:placetype":"venue"
},
  "geometry": {"coordinates":[-76.164333,40.694869],"type":"Point"}
}