{
  "type": "Feature",
  "properties": {
    "iso:country":"US",
    "sg:address":"105 Franklin St",
    "sg:city":"Whitehall",
    "sg:classifiers":[
        {
            "category":"Shopping",
            "subcategory":"Antiques",
            "type":"Retail Goods"
        }
    ],
    "sg:phone":"+1 610 264 3353",
    "sg:postcode":"18052",
    "sg:province":"PA",
    "wof:name":"Old Dairy Furniture Refinishing & Restoration",
    "wof:placetype":"venue"
},
  "geometry": {"coordinates":[-75.46869700000001,40.638],"type":"Point"}
}