{
  "type": "Feature",
  "properties": {
    "iso:country":"US",
    "sg:address":"1557 Warwick Ave",
    "sg:city":"Folcroft",
    "sg:classifiers":[
        {
            "category":"Building & Trades",
            "subcategory":"Landscaping Services",
            "type":"Services"
        }
    ],
    "sg:phone":"+1 610 583 3377",
    "sg:postcode":"19032",
    "sg:province":"PA",
    "sg:tags":[
        "landscape",
        "contractor"
    ],
    "wof:name":"Thompson & Sons Landscaping Inc",
    "wof:placetype":"venue"
},
  "geometry": {"coordinates":[-75.276511,39.896979],"type":"Point"}
}