{
  "type": "Feature",
  "properties": {
    "iso:country":"US",
    "sg:address":"155 Dowlin Forge Rd",
    "sg:city":"Exton",
    "sg:classifiers":[
        {
            "category":"Personal",
            "subcategory":"Beauty Salon",
            "type":"Services"
        }
    ],
    "sg:phone":"+1 610 363 7141",
    "sg:postcode":"19341",
    "sg:province":"PA",
    "wof:name":"Normandy Salon And Spa",
    "wof:placetype":"venue"
},
  "geometry": {"coordinates":[-75.66695900000001,40.053697],"type":"Point"}
}