{
  "type": "Feature",
  "properties": {
    "iso:country":"US",
    "sg:address":"1370 Hahns Dairy Rd",
    "sg:city":"Palmerton",
    "sg:classifiers":[
        {
            "category":"Building & Trades",
            "subcategory":"Construction",
            "type":"Services"
        }
    ],
    "sg:phone":"+1 610 826 7467",
    "sg:postcode":"18071",
    "sg:province":"PA",
    "sg:tags":[
        "contractor"
    ],
    "wof:name":"Brian D Kistler Roofing Inc",
    "wof:placetype":"venue"
},
  "geometry": {"coordinates":[-75.56772100000001,40.826414],"type":"Point"}
}