{
  "type": "Feature",
  "properties": {
    "iso:country":"US",
    "sg:address":"8030 Lyon Valley Rd",
    "sg:city":"New Tripoli",
    "sg:classifiers":[
        {
            "category":"Professional",
            "subcategory":"Management & Consulting",
            "type":"Services"
        }
    ],
    "sg:phone":"+1 610 285 4515",
    "sg:postcode":"18066",
    "sg:province":"PA",
    "sg:tags":[
        "marketing",
        "consultant"
    ],
    "wof:name":"Big Bang",
    "wof:placetype":"venue"
},
  "geometry": {"coordinates":[-75.68024699999999,40.618262],"type":"Point"}
}