{
  "type": "Feature",
  "properties": {
    "iso:country":"US",
    "sg:address":"1362 Naamans Creek Rd",
    "sg:city":"Marcus Hook",
    "sg:classifiers":[
        {
            "category":"Restaurant",
            "type":"Food & Drink"
        }
    ],
    "sg:phone":"+1 610 485 0697",
    "sg:postcode":"19061",
    "sg:province":"PA",
    "sg:tags":[
        "delicatessen"
    ],
    "wof:name":"Christopher's Crabcake & Deli",
    "wof:placetype":"venue"
},
  "geometry": {"coordinates":[-75.498728,39.840042],"type":"Point"}
}