{
  "type": "Feature",
  "properties": {
    "addr:full":"2403 S 11th St Philadelphia PA 19148",
    "addr:housenumber":"2403",
    "addr:postcode":"19148",
    "addr:street":"S 11Th St",
    "iso:country":"US",
    "sg:address":"2403 S 11th St",
    "sg:city":"Philadelphia",
    "sg:classifiers":[
        {
            "category":"Professional",
            "subcategory":"Computer Services",
            "type":"Services"
        }
    ],
    "sg:phone":"+1 215 389 1427",
    "sg:postcode":"19148",
    "sg:province":"PA",
    "sg:tags":[
        "repair"
    ],
    "wof:name":"Absolute Computer Support",
    "wof:placetype":"venue"
},
  "geometry": {"coordinates":[-75.165092,39.919872],"type":"Point"}
}