{
  "type": "Feature",
  "properties": {
    "iso:country":"US",
    "sg:address":"501 Strasburg Ave",
    "sg:city":"Parkesburg",
    "sg:classifiers":[
        {
            "category":"Retail",
            "subcategory":"Auto Repair",
            "type":"Services"
        }
    ],
    "sg:phone":"+1 610 363 6665",
    "sg:postcode":"19365",
    "sg:province":"PA",
    "sg:tags":[
        "repairing",
        "automobile"
    ],
    "wof:name":"Rodkey's Automotive Svc",
    "wof:placetype":"venue"
},
  "geometry": {"coordinates":[-75.923346,39.962726],"type":"Point"}
}