{
  "type": "Feature",
  "properties": {
    "addr:full":"2815 Rock Rd Clarks Summit PA 18411",
    "addr:housenumber":"2815",
    "addr:postcode":"18411",
    "addr:street":"Rock Rd",
    "iso:country":"US",
    "sg:address":"2815 Rock Rd",
    "sg:city":"Clarks Summit",
    "sg:classifiers":[
        {
            "category":"Shopping",
            "subcategory":"Gifts & Souvenirs",
            "type":"Retail Goods"
        }
    ],
    "sg:phone":"+1   ",
    "sg:postcode":"18411",
    "sg:province":"PA",
    "wof:name":"Prazychs Cards",
    "wof:placetype":"venue"
},
  "geometry": {"coordinates":[-75.77859100000001,41.416342],"type":"Point"}
}