{
  "type": "Feature",
  "properties": {
    "iso:country":"US",
    "sg:address":"345 E Main St",
    "sg:city":"Collegeville",
    "sg:classifiers":[
        {
            "category":"Professional",
            "subcategory":"Advertising",
            "type":"Services"
        }
    ],
    "sg:phone":"+1 610 489 3001",
    "sg:postcode":"19426",
    "sg:province":"PA",
    "wof:name":"Independent",
    "wof:placetype":"venue"
},
  "geometry": {"coordinates":[-75.452629,40.187133],"type":"Point"}
}