{
  "type": "Feature",
  "properties": {
    "addr:full":"220 Farm Ln Doylestown PA 18901",
    "addr:housenumber":"220",
    "addr:postcode":"18901",
    "addr:street":"Farm Ln",
    "iso:country":"US",
    "sg:address":"220 Farm Ln",
    "sg:city":"Doylestown",
    "sg:classifiers":[
        {
            "category":"Insurance",
            "subcategory":"Insurance Agent",
            "type":"Services"
        }
    ],
    "sg:phone":"+1 215 230 9090",
    "sg:postcode":"18901",
    "sg:province":"PA",
    "wof:name":"Nationwide Insurance",
    "wof:placetype":"venue"
},
  "geometry": {"coordinates":[-75.11435400000001,40.310114],"type":"Point"}
}