{
  "type": "Feature",
  "properties": {
    "iso:country":"US",
    "sg:address":"320 N Rosina Ave",
    "sg:city":"Somerset",
    "sg:classifiers":[
        {
            "category":"Professional",
            "type":"Services"
        }
    ],
    "sg:phone":"+1   ",
    "sg:postcode":"15501",
    "sg:province":"PA",
    "wof:name":"Witt Pictures",
    "wof:placetype":"venue"
},
  "geometry": {"coordinates":[-79.082792,40.010909],"type":"Point"}
}