{
  "type": "Feature",
  "properties": {
    "iso:country":"US",
    "sg:address":"2738 E County Line Rd",
    "sg:city":"Ardmore",
    "sg:classifiers":[
        {
            "category":"Retail",
            "subcategory":"Repair Shop",
            "type":"Services"
        },
        {
            "category":"Building & Trades",
            "subcategory":"Electrical",
            "type":"Services"
        }
    ],
    "sg:phone":"+1 610 642 6261",
    "sg:postcode":"19003",
    "sg:province":"PA",
    "sg:tags":[
        "industrial",
        "electrician",
        "electric",
        "appliance",
        "contractors-commercial",
        "small"
    ],
    "wof:name":"Costello Electrical Service Inc",
    "wof:placetype":"venue"
},
  "geometry": {"coordinates":[-75.296661,40.001622],"type":"Point"}
}