{
  "type": "Feature",
  "properties": {
    "iso:country":"US",
    "sg:address":"3690 Lehigh St",
    "sg:city":"Whitehall",
    "sg:classifiers":[
        {
            "category":"Personal",
            "subcategory":"Nail Salon",
            "type":"Services"
        }
    ],
    "sg:phone":"+1 610 432 9589",
    "sg:postcode":"18052",
    "sg:province":"PA",
    "wof:name":"Nail Spa & Tanning",
    "wof:placetype":"venue"
},
  "geometry": {"coordinates":[-75.49711600000001,40.655051],"type":"Point"}
}