{
  "type": "Feature",
  "properties": {
    "addr:full":"118 N Broad St Philadelphia PA 19102",
    "addr:housenumber":"118",
    "addr:postcode":"19102",
    "addr:street":"N Broad St",
    "iso:country":"US",
    "sg:address":"118 N Broad St",
    "sg:city":"Philadelphia",
    "sg:classifiers":[
        {
            "category":"Restaurant",
            "type":"Food & Drink"
        }
    ],
    "sg:phone":"+1   ",
    "sg:postcode":"19102",
    "sg:province":"PA",
    "sg:tags":[
        "caterer"
    ],
    "wof:name":"Jimmy Duffy & Sons Inc",
    "wof:placetype":"venue"
},
  "geometry": {"coordinates":[-75.163015,39.955345],"type":"Point"}
}