{
  "type": "Feature",
  "properties": {
    "iso:country":"US",
    "sg:address":"6301 Grayson Rd",
    "sg:city":"Harrisburg",
    "sg:classifiers":[
        {
            "category":"Professional",
            "subcategory":"Business Services",
            "type":"Services"
        }
    ],
    "sg:phone":"+1 717 561 8000",
    "sg:postcode":"17111",
    "sg:province":"PA",
    "sg:tags":[
        "broker"
    ],
    "wof:name":"Commonwealth Business Brokers",
    "wof:placetype":"venue"
},
  "geometry": {"coordinates":[-76.775719,40.261956],"type":"Point"}
}