{
  "type": "Feature",
  "properties": {
    "iso:country":"US",
    "sg:address":"109 Meade St",
    "sg:city":"Tyrone",
    "sg:classifiers":[
        {
            "category":"Building & Trades",
            "subcategory":"Landscaping Services",
            "type":"Services"
        }
    ],
    "sg:phone":"+1   ",
    "sg:postcode":"16686",
    "sg:province":"PA",
    "wof:name":"Elmer Sprow",
    "wof:placetype":"venue"
},
  "geometry": {"coordinates":[-78.23128199999999,40.681914],"type":"Point"}
}