{
  "type": "Feature",
  "properties": {
    "addr:full":"101 Pine St Rillton PA 15678",
    "addr:housenumber":"101",
    "addr:postcode":"15678",
    "addr:street":"Pine St",
    "iso:country":"US",
    "sg:address":"101 Pine St",
    "sg:city":"Rillton",
    "sg:classifiers":[
        {
            "category":"Building & Trades",
            "subcategory":"Plumbing",
            "type":"Services"
        }
    ],
    "sg:phone":"+1 724 446 7007",
    "sg:postcode":"15678",
    "sg:province":"PA",
    "sg:tags":[
        "conditioning",
        "air",
        "system",
        "contractor"
    ],
    "wof:name":"William Beers Heating & Air",
    "wof:placetype":"venue"
},
  "geometry": {"coordinates":[-79.729145,40.289052],"type":"Point"}
}