{
  "type": "Feature",
  "properties": {
    "iso:country":"US",
    "sg:address":"4724 Springside Ct",
    "sg:city":"Allentown",
    "sg:classifiers":[
        {
            "category":"Home & Garden",
            "subcategory":"Building Materials",
            "type":"Retail Goods"
        }
    ],
    "sg:phone":"+1 610 481 0177",
    "sg:postcode":"18104",
    "sg:province":"PA",
    "sg:tags":[
        "supply"
    ],
    "wof:name":"Tri City Marble Co",
    "wof:placetype":"venue"
},
  "geometry": {"coordinates":[-75.55500000000001,40.577499],"type":"Point"}
}