{
  "type": "Feature",
  "properties": {
    "iso:country":"US",
    "sg:address":"1484 Ferndale Ave",
    "sg:city":"Johnstown",
    "sg:classifiers":[
        {
            "category":"Restaurant",
            "type":"Food & Drink"
        }
    ],
    "sg:phone":"+1 814 288 0144",
    "sg:postcode":"15905",
    "sg:province":"PA",
    "sg:tags":[
        "pizza"
    ],
    "wof:name":"A Noble Roman's Pizza",
    "wof:placetype":"venue"
},
  "geometry": {"coordinates":[-78.923592,40.287841],"type":"Point"}
}