{
  "type": "Feature",
  "properties": {
    "iso:country":"US",
    "sg:address":"1807 N Reading Rd",
    "sg:city":"Stevens",
    "sg:classifiers":[
        {
            "category":"Shopping",
            "subcategory":"Used Merchandise",
            "type":"Retail Goods"
        }
    ],
    "sg:phone":"+1 717 336 1919",
    "sg:postcode":"17517",
    "sg:province":"PA",
    "sg:tags":[
        "antique"
    ],
    "wof:name":"Railway Station",
    "wof:placetype":"venue"
},
  "geometry": {"coordinates":[-76.115117,40.217542],"type":"Point"}
}