{
  "type": "Feature",
  "properties": {
    "iso:country":"US",
    "sg:address":"221 Bridge St",
    "sg:city":"Phoenixville",
    "sg:classifiers":[
        {
            "category":"Insurance",
            "subcategory":"Insurance Agent",
            "type":"Services"
        },
        {
            "category":"Insurance",
            "subcategory":"Hazard Insurance",
            "type":"Services"
        },
        {
            "category":"Insurance",
            "subcategory":"Title Insurance",
            "type":"Services"
        },
        {
            "category":"Insurance",
            "subcategory":"Life Insurance",
            "type":"Services"
        }
    ],
    "sg:phone":"+1 610 935 4744",
    "sg:postcode":"19460",
    "sg:province":"PA",
    "sg:tags":[
        "business",
        "auto",
        "commercial",
        "homeowner",
        "motorcycle",
        "renter"
    ],
    "wof:name":"Allstate Insurance Company - Michael Gagliano",
    "wof:placetype":"venue"
},
  "geometry": {"coordinates":[-75.517005,40.133906],"type":"Point"}
}