{
  "type": "Feature",
  "properties": {
    "addr:full":"327 Ashbourne Rd Elkins Park PA 19027",
    "addr:housenumber":"327",
    "addr:postcode":"19027",
    "addr:street":"Ashbourne Rd",
    "iso:country":"US",
    "sg:address":"327 Ashbourne Rd",
    "sg:city":"Elkins Park",
    "sg:classifiers":[
        {
            "category":"Real Estate",
            "subcategory":"Real Estate Agent",
            "type":"Services"
        }
    ],
    "sg:phone":"+1   ",
    "sg:postcode":"19027",
    "sg:province":"PA",
    "sg:tags":[
        "business"
    ],
    "wof:name":"Bratman Appraisals",
    "wof:placetype":"venue"
},
  "geometry": {"coordinates":[-75.126254,40.068376],"type":"Point"}
}