{
  "type": "Feature",
  "properties": {
    "addr:full":"3377 Highland Rd Orefield PA 18069",
    "addr:housenumber":"3377",
    "addr:postcode":"18069",
    "addr:street":"Highland Rd",
    "iso:country":"US",
    "sg:address":"3377 Highland Rd",
    "sg:city":"Orefield",
    "sg:classifiers":[
        {
            "category":"Structure",
            "subcategory":"Office Building",
            "type":"Public Place"
        }
    ],
    "sg:phone":"+1 610 391 7276",
    "sg:postcode":"18069",
    "sg:province":"PA",
    "sg:tags":[
        "park"
    ],
    "wof:name":"Keldan Properties",
    "wof:placetype":"venue"
},
  "geometry": {"coordinates":[-75.63329899999999,40.634085],"type":"Point"}
}