{
  "type": "Feature",
  "properties": {
    "addr:full":"2868 Aramingo Ave Philadelphia PA 19134",
    "addr:housenumber":"2868",
    "addr:postcode":"19134",
    "addr:street":"Aramingo Ave",
    "iso:country":"US",
    "sg:address":"2868 Aramingo Ave",
    "sg:city":"Philadelphia",
    "sg:classifiers":[
        {
            "category":"Building & Trades",
            "subcategory":"Locksmith",
            "type":"Services"
        }
    ],
    "sg:phone":"+1 267 773 5965",
    "sg:postcode":"19134",
    "sg:province":"PA",
    "sg:tags":[
        "key"
    ],
    "wof:name":"A Aramingo Ave Locksmith Service",
    "wof:placetype":"venue"
},
  "geometry": {"coordinates":[-75.11407800000001,39.984655],"type":"Point"}
}