{
  "type": "Feature",
  "properties": {
    "iso:country":"US",
    "sg:address":"978 Bethlehem Pike",
    "sg:city":"Montgomeryville",
    "sg:classifiers":[
        {
            "category":"Home & Garden",
            "subcategory":"Furniture",
            "type":"Retail Goods"
        }
    ],
    "sg:phone":"+1 215 616 6600",
    "sg:postcode":"18936",
    "sg:province":"PA",
    "sg:tags":[
        "store"
    ],
    "wof:name":"Thomasville Home Furnishings of Montgomeryville",
    "wof:placetype":"venue"
},
  "geometry": {"coordinates":[-75.235023,40.226959],"type":"Point"}
}