{
  "type": "Feature",
  "properties": {
    "iso:country":"US",
    "sg:address":"619 Briarcliff Dr",
    "sg:city":"Aliquippa",
    "sg:classifiers":[
        {
            "category":"Building & Trades",
            "subcategory":"Construction",
            "type":"Services"
        }
    ],
    "sg:phone":"+1 724 378 0300",
    "sg:postcode":"15001",
    "sg:province":"PA",
    "sg:tags":[
        "painter"
    ],
    "wof:name":"Doug's BFA Painting",
    "wof:placetype":"venue"
},
  "geometry": {"coordinates":[-80.29866199999999,40.623337],"type":"Point"}
}