{
  "type": "Feature",
  "properties": {
    "iso:country":"US",
    "sg:address":"1050 N Hancock St Ste 90",
    "sg:city":"Philadelphia",
    "sg:classifiers":[
        {
            "category":"Home & Garden",
            "subcategory":"Home Furnishings",
            "type":"Retail Goods"
        }
    ],
    "sg:phone":"+1 267 455 0438",
    "sg:postcode":"19123",
    "sg:province":"PA",
    "sg:tags":[
        "decor"
    ],
    "sg:website":"www.lyladesigns.com",
    "wof:name":"Lyla designs, LLC",
    "wof:placetype":"venue"
},
  "geometry": {"coordinates":[-75.139273,39.965727],"type":"Point"}
}