{
  "type": "Feature",
  "properties": {
    "addr:full":"1945 Norristown Rd Ambler PA 19002",
    "addr:housenumber":"1945",
    "addr:postcode":"19002",
    "addr:street":"Norristown Rd",
    "iso:country":"US",
    "sg:address":"1945 Norristown Rd",
    "sg:city":"Ambler",
    "sg:classifiers":[
        {
            "category":"Professional",
            "subcategory":"Business Services",
            "type":"Services"
        }
    ],
    "sg:phone":"+1   ",
    "sg:postcode":"19002",
    "sg:province":"PA",
    "wof:name":"Yuh Kyu Won",
    "wof:placetype":"venue"
},
  "geometry": {"coordinates":[-75.181574,40.179072],"type":"Point"}
}