{
  "type": "Feature",
  "properties": {
    "iso:country":"US",
    "sg:address":"307 School St",
    "sg:city":"Butler",
    "sg:classifiers":[
        {
            "category":"Shopping",
            "subcategory":"Discount & Variety Stores",
            "type":"Retail Goods"
        }
    ],
    "sg:phone":"+1   ",
    "sg:postcode":"16001",
    "sg:province":"PA",
    "sg:tags":[
        "equipment",
        "supply",
        "army",
        "clothes"
    ],
    "wof:name":"The Army Outdoor Store Plus",
    "wof:placetype":"venue"
},
  "geometry": {"coordinates":[-79.884671,40.864335],"type":"Point"}
}