{
  "type": "Feature",
  "properties": {
    "addr:full":"7 S New St Nazareth PA 18064",
    "addr:housenumber":"7",
    "addr:postcode":"18064",
    "addr:street":"S New St",
    "iso:country":"US",
    "sg:address":"7 S New St",
    "sg:city":"Nazareth",
    "sg:classifiers":[
        {
            "category":"Health Services",
            "subcategory":"Nursing And Care Facility",
            "type":"Services"
        },
        {
            "category":"Social Services",
            "subcategory":"Retirement Home",
            "type":"Services"
        },
        {
            "category":"Social Services",
            "subcategory":"Adult Care",
            "type":"Services"
        }
    ],
    "sg:phone":"+1 610 759 4060",
    "sg:postcode":"18064",
    "sg:province":"PA",
    "sg:tags":[
        "living",
        "assisted",
        "convalescent",
        "elder",
        "residential"
    ],
    "sg:website":"http://www.alexandriamanor.com",
    "wof:name":"Alexandria Manor Senior Living",
    "wof:placetype":"venue"
},
  "geometry": {"coordinates":[-75.305937,40.742364],"type":"Point"}
}