{
  "type": "Feature",
  "properties": {
    "iso:country":"US",
    "sg:address":"318 Main St",
    "sg:city":"Greenville",
    "sg:classifiers":[
        {
            "category":"Restaurant",
            "type":"Food & Drink"
        }
    ],
    "sg:phone":"+1 724 588 7827",
    "sg:postcode":"16125",
    "sg:province":"PA",
    "sg:tags":[
        "sandwich"
    ],
    "wof:name":"Scelsi's Sub Construction",
    "wof:placetype":"venue"
},
  "geometry": {"coordinates":[-80.379794,41.408093],"type":"Point"}
}