{
  "type": "Feature",
  "properties": {
    "iso:country":"US",
    "sg:address":"720 Woodland Rd",
    "sg:city":"Bradfordwoods",
    "sg:classifiers":[
        {
            "category":"Professional",
            "subcategory":"Management & Consulting",
            "type":"Services"
        }
    ],
    "sg:phone":"+1 724 935 9244",
    "sg:postcode":"15015",
    "sg:province":"PA",
    "sg:tags":[
        "consultant",
        "business"
    ],
    "wof:name":"F H Bentzel Assoc Inc",
    "wof:placetype":"venue"
},
  "geometry": {"coordinates":[-80.08416200000001,40.629994],"type":"Point"}
}