{
  "type": "Feature",
  "properties": {
    "iso:country":"US",
    "sg:address":"191 Main St",
    "sg:city":"Donegal",
    "sg:classifiers":[
        {
            "category":"Food & Beverages",
            "subcategory":"Specialty",
            "type":"Retail Goods"
        }
    ],
    "sg:phone":"+1 724 593 4372",
    "sg:postcode":"15628",
    "sg:province":"PA",
    "sg:tags":[
        "health",
        "diet"
    ],
    "wof:name":"Mountain Herb Shoppe",
    "wof:placetype":"venue"
},
  "geometry": {"coordinates":[-79.38289399999999,40.112452],"type":"Point"}
}