{
  "type": "Feature",
  "properties": {
    "iso:country":"US",
    "sg:address":"207 Helen St",
    "sg:city":"Dunmore",
    "sg:classifiers":[
        {
            "category":"Building & Trades",
            "subcategory":"Construction",
            "type":"Services"
        }
    ],
    "sg:phone":"+1 570 489 6611",
    "sg:postcode":"18512",
    "sg:province":"PA",
    "sg:tags":[
        "system",
        "specialty",
        "heating",
        "contractor",
        "air conditioning"
    ],
    "sg:website":"http://www.nationalfurnace.com",
    "wof:name":"National Furnace Company",
    "wof:placetype":"venue"
},
  "geometry": {"coordinates":[-75.62733,41.411099],"type":"Point"}
}