{
  "type": "Feature",
  "properties": {
    "iso:country":"US",
    "sg:address":"5 W Manilla Ave",
    "sg:city":"Pittsburgh",
    "sg:classifiers":[
        {
            "category":"Health Services",
            "subcategory":"Doctor",
            "type":"Services"
        }
    ],
    "sg:phone":"+1 412 921 3433",
    "sg:postcode":"15220",
    "sg:province":"PA",
    "sg:tags":[
        "dentist"
    ],
    "wof:name":"Dennis W Szymaitis DDS",
    "wof:placetype":"venue"
},
  "geometry": {"coordinates":[-80.045951,40.418412],"type":"Point"}
}