{
  "type": "Feature",
  "properties": {
    "iso:country":"US",
    "sg:address":"737 Maple St",
    "sg:city":"Harwick",
    "sg:classifiers":[
        {
            "category":"Building & Trades",
            "subcategory":"Construction",
            "type":"Services"
        }
    ],
    "sg:phone":"+1   ",
    "sg:postcode":"15049",
    "sg:province":"PA",
    "sg:tags":[
        "house"
    ],
    "wof:name":"Philip Cicolini Contruction",
    "wof:placetype":"venue"
},
  "geometry": {"coordinates":[-79.805041,40.550467],"type":"Point"}
}