{
  "type": "Feature",
  "properties": {
    "iso:country":"US",
    "sg:address":"105 S 5th St",
    "sg:city":"Reading",
    "sg:classifiers":[
        {
            "category":"Organizations",
            "subcategory":"Non-profit Organization",
            "type":"Services"
        }
    ],
    "sg:phone":"+1   ",
    "sg:postcode":"19602",
    "sg:province":"PA",
    "sg:tags":[
        "religious",
        "social"
    ],
    "wof:name":"Mercy Cmnty Crsis Prgnancy Ctr",
    "wof:placetype":"venue"
},
  "geometry": {"coordinates":[-75.927899,40.33224],"type":"Point"}
}