{
  "type": "Feature",
  "properties": {
    "iso:country":"US",
    "sg:address":"8 E Pine Ave",
    "sg:city":"Washington",
    "sg:classifiers":[
        {
            "category":"Professional",
            "subcategory":"Lawyer & Legal Services",
            "type":"Services"
        }
    ],
    "sg:phone":"+1 724 228 6500",
    "sg:postcode":"15301",
    "sg:province":"PA",
    "sg:tags":[
        "attorney"
    ],
    "wof:name":"Jeffrey G Brooks",
    "wof:placetype":"venue"
},
  "geometry": {"coordinates":[-80.244784,40.17172],"type":"Point"}
}