{
  "type": "Feature",
  "properties": {
    "iso:country":"US",
    "sg:address":"20 Mauch Chunk St",
    "sg:city":"Tamaqua",
    "sg:classifiers":[
        {
            "category":"Bars & Pubs",
            "type":"Food & Drink"
        }
    ],
    "sg:phone":"+1 570 668 2113",
    "sg:postcode":"18252",
    "sg:province":"PA",
    "wof:name":"Tiki Inc",
    "wof:placetype":"venue"
},
  "geometry": {"coordinates":[-75.968447,40.798494],"type":"Point"}
}