{
  "type": "Feature",
  "properties": {
    "addr:full":"101 W Moreland Rd Willow Grove PA 19090",
    "addr:housenumber":"101",
    "addr:postcode":"19090",
    "addr:street":"W Moreland Rd",
    "iso:country":"US",
    "sg:address":"101 W Moreland Rd",
    "sg:city":"Willow Grove",
    "sg:classifiers":[
        {
            "category":"Restaurant",
            "type":"Food & Drink"
        }
    ],
    "sg:phone":"+1   ",
    "sg:postcode":"19090",
    "sg:province":"PA",
    "sg:tags":[
        "eating"
    ],
    "wof:name":"Little Caesars",
    "wof:placetype":"venue"
},
  "geometry": {"coordinates":[-75.119535,40.142851],"type":"Point"}
}