{
  "type": "Feature",
  "properties": {
    "iso:country":"US",
    "sg:address":"128 Lincoln Ave",
    "sg:city":"Meadville",
    "sg:classifiers":[
        {
            "category":"Retail",
            "subcategory":"Auto Repair",
            "type":"Services"
        }
    ],
    "sg:phone":"+1 814 336 3153",
    "sg:postcode":"16335",
    "sg:province":"PA",
    "sg:tags":[
        "body"
    ],
    "wof:name":"Dillaman Auto Body",
    "wof:placetype":"venue"
},
  "geometry": {"coordinates":[-80.16055,41.648537],"type":"Point"}
}