{
  "type": "Feature",
  "properties": {
    "addr:full":"801 Union Ave Pittsburgh PA 15212",
    "addr:housenumber":"801",
    "addr:postcode":"15212",
    "addr:street":"Union Ave",
    "iso:country":"US",
    "sg:address":"801 Union Ave",
    "sg:city":"Pittsburgh",
    "sg:classifiers":[
        {
            "category":"Organizations",
            "subcategory":"Professional Association",
            "type":"Services"
        }
    ],
    "sg:phone":"+1 412 268 1018",
    "sg:postcode":"15212",
    "sg:province":"PA",
    "wof:name":"Kuumba Trust",
    "wof:placetype":"venue"
},
  "geometry": {"coordinates":[-80.002616,40.453148],"type":"Point"}
}