{
  "type": "Feature",
  "properties": {
    "iso:country":"US",
    "sg:address":"301 W Chester Pike",
    "sg:city":"Havertown",
    "sg:classifiers":[
        {
            "category":"Health Services",
            "subcategory":"Hospital",
            "type":"Services"
        }
    ],
    "sg:phone":"+1 610 520 1700",
    "sg:postcode":"19083",
    "sg:province":"PA",
    "sg:tags":[
        "sleep",
        "treatment",
        "disorders-information"
    ],
    "wof:name":"Marc I Surkin Md",
    "wof:placetype":"venue"
},
  "geometry": {"coordinates":[-75.29991099999999,39.969681],"type":"Point"}
}