{
  "type": "Feature",
  "properties": {
    "iso:country":"US",
    "sg:address":"1818 Union Ave",
    "sg:city":"Natrona Heights",
    "sg:classifiers":[
        {
            "category":"Banks & Credit Unions",
            "subcategory":"Bank",
            "type":"Services"
        }
    ],
    "sg:phone":"+1 724 226 3250",
    "sg:postcode":"15065",
    "sg:province":"PA",
    "sg:tags":[
        "cashing",
        "check"
    ],
    "wof:name":"Flexcheck Cash Advance Ctr",
    "wof:placetype":"venue"
},
  "geometry": {"coordinates":[-79.724503,40.622102],"type":"Point"}
}