{
  "type": "Feature",
  "properties": {
    "iso:country":"US",
    "sg:address":"14983 Ridge Rd",
    "sg:city":"West Springfield",
    "sg:classifiers":[
        {
            "category":"Shopping",
            "subcategory":"Discount & Variety Stores",
            "type":"Retail Goods"
        }
    ],
    "sg:phone":"+1   ",
    "sg:postcode":"16443",
    "sg:province":"PA",
    "wof:name":"Himes State Line Beverage",
    "wof:placetype":"venue"
},
  "geometry": {"coordinates":[-80.518586,41.944004],"type":"Point"}
}