{
  "type": "Feature",
  "properties": {
    "iso:country":"US",
    "sg:address":"4583 Shimerville Rd",
    "sg:city":"Emmaus",
    "sg:classifiers":[
        {
            "category":"Building & Trades",
            "subcategory":"Landscaping Services",
            "type":"Services"
        }
    ],
    "sg:phone":"+1 610 967 2760",
    "sg:postcode":"18049",
    "sg:province":"PA",
    "sg:tags":[
        "specializing",
        "la",
        "work",
        "landscape",
        "contractor"
    ],
    "wof:name":"Gary's Tree & Shrubbery Svc",
    "wof:placetype":"venue"
},
  "geometry": {"coordinates":[-75.51544800000001,40.507572],"type":"Point"}
}