{
  "type": "Feature",
  "properties": {
    "iso:country":"US",
    "sg:address":"2553 Huntingdon Pike",
    "sg:city":"Huntingdon Vly",
    "sg:classifiers":[
        {
            "category":"Personal",
            "subcategory":"Beauty Salon",
            "type":"Services"
        }
    ],
    "sg:phone":"+1 215 947 9205",
    "sg:postcode":"19006",
    "sg:province":"PA",
    "sg:tags":[
        "shop"
    ],
    "wof:name":"Valley Hair Designs",
    "wof:placetype":"venue"
},
  "geometry": {"coordinates":[-75.063509,40.123541],"type":"Point"}
}