{
  "type": "Feature",
  "properties": {
    "iso:country":"US",
    "sg:address":"1654 Walnut St",
    "sg:city":"Harrisburg",
    "sg:classifiers":[
        {
            "category":"Social Services",
            "subcategory":"Child Care",
            "type":"Services"
        }
    ],
    "sg:phone":"+1 717 233 4220",
    "sg:postcode":"17103",
    "sg:province":"PA",
    "wof:name":"Capital Area Head Start",
    "wof:placetype":"venue"
},
  "geometry": {"coordinates":[-76.86612700000001,40.270123],"type":"Point"}
}