{
  "type": "Feature",
  "properties": {
    "iso:country":"US",
    "sg:address":"243 Elmbrook Rd",
    "sg:city":"Beaver Falls",
    "sg:classifiers":[
        {
            "category":"Recreation",
            "type":"Entertainment"
        }
    ],
    "sg:phone":"+1 724 846 7078",
    "sg:postcode":"15010",
    "sg:province":"PA",
    "sg:tags":[
        "instruction",
        "gymnastic"
    ],
    "wof:name":"Arcadia Gymnastics & Fitness",
    "wof:placetype":"venue"
},
  "geometry": {"coordinates":[-80.418211,40.769186],"type":"Point"}
}