{
  "type": "Feature",
  "properties": {
    "iso:country":"US",
    "sg:address":"155 Memorial Hwy",
    "sg:city":"Dallas",
    "sg:classifiers":[
        {
            "category":"Shopping",
            "subcategory":"Computers & Home Electronics",
            "type":"Retail Goods"
        }
    ],
    "sg:phone":"+1 570 674 4920",
    "sg:postcode":"18612",
    "sg:province":"PA",
    "sg:tags":[
        "equipment",
        "dealer"
    ],
    "wof:name":"Value Plus Svc",
    "wof:placetype":"venue"
},
  "geometry": {"coordinates":[-75.94672199999999,41.327548],"type":"Point"}
}