{
  "type": "Feature",
  "properties": {
    "iso:country":"US",
    "sg:address":"2001 Parade St",
    "sg:city":"Erie",
    "sg:classifiers":[
        {
            "category":"Wholesale",
            "subcategory":"Machinery & Supplies",
            "type":"Manufacturing & Wholesale Goods"
        },
        {
            "category":"Wholesale",
            "subcategory":"Hardware",
            "type":"Manufacturing & Wholesale Goods"
        }
    ],
    "sg:phone":"+1 814 454 0146",
    "sg:postcode":"16503",
    "sg:province":"PA",
    "sg:tags":[
        "plumbing",
        "industrial",
        "fixture"
    ],
    "sg:website":"www.trumbull.com",
    "wof:name":"Trumball Industries",
    "wof:placetype":"venue"
},
  "geometry": {"coordinates":[-80.067763,42.119417],"type":"Point"}
}