{
  "type": "Feature",
  "properties": {
    "addr:full":"1101 Market St Harrisburg PA 17103",
    "addr:housenumber":"1101",
    "addr:postcode":"17103",
    "addr:street":"Market St",
    "iso:country":"US",
    "sg:address":"1101 Market St",
    "sg:city":"Harrisburg",
    "sg:classifiers":[
        {
            "category":"Health Services",
            "subcategory":"Doctor",
            "type":"Services"
        }
    ],
    "sg:phone":"+1 717 782 6570",
    "sg:postcode":"17103",
    "sg:province":"PA",
    "sg:tags":[
        "practice",
        "family"
    ],
    "wof:name":"Allison Hill Family Practice Center",
    "wof:placetype":"venue"
},
  "geometry": {"coordinates":[-76.87449599999999,40.2644],"type":"Point"}
}