{
  "type": "Feature",
  "properties": {
    "iso:country":"US",
    "sg:address":"11 S 11th St",
    "sg:city":"Reading",
    "sg:classifiers":[
        {
            "category":"Professional",
            "type":"Services"
        }
    ],
    "sg:phone":"+1 610 378 5441",
    "sg:postcode":"19602",
    "sg:province":"PA",
    "sg:tags":[
        "establishment"
    ],
    "wof:name":"Bio-Proteus Corp",
    "wof:placetype":"venue"
},
  "geometry": {"coordinates":[-75.91613,40.334991],"type":"Point"}
}