{
  "type": "Feature",
  "properties": {
    "iso:country":"US",
    "sg:address":"1701 Cochran Rd Fl 1",
    "sg:city":"Pittsburgh",
    "sg:classifiers":[
        {
            "category":"Banks & Credit Unions",
            "subcategory":"Bank",
            "type":"Services"
        },
        {
            "category":"Banks & Credit Unions",
            "subcategory":"Financial Services",
            "type":"Services"
        }
    ],
    "sg:phone":"+1 412 344 7600",
    "sg:postcode":"15220",
    "sg:province":"PA",
    "sg:tags":[
        "saving",
        "loan",
        "commercial"
    ],
    "sg:website":"https://www.nationalcity.com",
    "wof:name":"National City Bank",
    "wof:placetype":"venue"
},
  "geometry": {"coordinates":[-80.062373,40.39253],"type":"Point"}
}