{
  "type": "Feature",
  "properties": {
    "iso:country":"US",
    "sg:address":"945 Sandbank Rd",
    "sg:city":"Mt Holly Springs",
    "sg:classifiers":[
        {
            "category":"Professional",
            "type":"Services"
        },
        {
            "category":"Manufacturing",
            "subcategory":"Tools & Machinery",
            "type":"Manufacturing & Wholesale Goods"
        }
    ],
    "sg:phone":"+1 717 486 4437",
    "sg:postcode":"17065",
    "sg:province":"PA",
    "sg:tags":[
        "machine",
        "shop"
    ],
    "wof:name":"Skovira Fabrication & Machine",
    "wof:placetype":"venue"
},
  "geometry": {"coordinates":[-77.216728,40.112876],"type":"Point"}
}