{
  "type": "Feature",
  "properties": {
    "addr:full":"250 Lenker Ave Sunbury PA 17801",
    "addr:housenumber":"250",
    "addr:postcode":"17801",
    "addr:street":"Lenker Ave",
    "iso:country":"US",
    "sg:address":"250 Lenker Ave",
    "sg:city":"Sunbury",
    "sg:classifiers":[
        {
            "category":"Social Services",
            "subcategory":"Child Care",
            "type":"Services"
        }
    ],
    "sg:phone":"+1   ",
    "sg:postcode":"17801",
    "sg:province":"PA",
    "sg:tags":[
        "day"
    ],
    "wof:name":"Kiddin Around Early Lrng Ctr",
    "wof:placetype":"venue"
},
  "geometry": {"coordinates":[-76.786107,40.855299],"type":"Point"}
}