{
  "type": "Feature",
  "properties": {
    "iso:country":"US",
    "sg:address":"6 Ave B",
    "sg:city":"Leetsdale",
    "sg:classifiers":[
        {
            "category":"Wholesale",
            "subcategory":"Machinery & Supplies",
            "type":"Manufacturing & Wholesale Goods"
        }
    ],
    "sg:phone":"+1   ",
    "sg:postcode":"15056",
    "sg:province":"PA",
    "sg:tags":[
        "industrial"
    ],
    "wof:name":"McJunkin Corporation",
    "wof:placetype":"venue"
},
  "geometry": {"coordinates":[-80.208065,40.558684],"type":"Point"}
}