{
  "type": "Feature",
  "properties": {
    "iso:country":"US",
    "sg:address":"308 E High St",
    "sg:city":"Pottstown",
    "sg:classifiers":[
        {
            "category":"Health Services",
            "subcategory":"Hospital",
            "type":"Services"
        }
    ],
    "sg:phone":"+1 610 970 5000",
    "sg:postcode":"19464",
    "sg:province":"PA",
    "sg:tags":[
        "mental"
    ],
    "wof:name":"Progressions Behavioral Ctr",
    "wof:placetype":"venue"
},
  "geometry": {"coordinates":[-75.646315,40.245083],"type":"Point"}
}