{
  "type": "Feature",
  "properties": {
    "addr:full":"40 N 7th St Allentown PA 18101",
    "addr:housenumber":"40",
    "addr:postcode":"18101",
    "addr:street":"N 7Th St",
    "iso:country":"US",
    "sg:address":"40 N 7th St",
    "sg:city":"Allentown",
    "sg:classifiers":[
        {
            "category":"Banks & Credit Unions",
            "subcategory":"Bank",
            "type":"Services"
        }
    ],
    "sg:phone":"+1   ",
    "sg:postcode":"18101",
    "sg:province":"PA",
    "sg:tags":[
        "depository",
        "banking"
    ],
    "wof:name":"Money Mart 118",
    "wof:placetype":"venue"
},
  "geometry": {"coordinates":[-75.472235,40.603055],"type":"Point"}
}