{
  "type": "Feature",
  "properties": {
    "addr:full":"5006 State Rd Drexel Hill PA 19026",
    "addr:housenumber":"5006",
    "addr:postcode":"19026",
    "addr:street":"State Rd",
    "iso:country":"US",
    "sg:address":"5006 State Rd",
    "sg:city":"Drexel Hill",
    "sg:classifiers":[
        {
            "category":"Shopping",
            "subcategory":"Pharmacy",
            "type":"Retail Goods"
        }
    ],
    "sg:phone":"+1 610 623 1393",
    "sg:postcode":"19026",
    "sg:province":"PA",
    "wof:name":"CVS Pharmacy",
    "wof:placetype":"venue"
},
  "geometry": {"coordinates":[-75.325582,39.945854],"type":"Point"}
}