{
  "type": "Feature",
  "properties": {
    "iso:country":"US",
    "sg:address":"12 N 8th St",
    "sg:city":"Stroudsburg",
    "sg:classifiers":[
        {
            "category":"Real Estate",
            "subcategory":"Real Estate Services",
            "type":"Services"
        },
        {
            "category":"Real Estate",
            "subcategory":"Developer",
            "type":"Services"
        },
        {
            "category":"Real Estate",
            "subcategory":"Real Estate Agent",
            "type":"Services"
        }
    ],
    "sg:phone":"+1 570 476 2413",
    "sg:postcode":"18360",
    "sg:province":"PA",
    "sg:tags":[
        "buyer",
        "consultant",
        "broker"
    ],
    "sg:website":"http://www.stevehornhomes.com/poconos.html",
    "wof:name":"Steve Horn Real Estate LLC",
    "wof:placetype":"venue"
},
  "geometry": {"coordinates":[-75.196078,40.984973],"type":"Point"}
}