{
  "type": "Feature",
  "properties": {
    "addr:full":"76 S Main St Doylestown PA 18901",
    "addr:housenumber":"76",
    "addr:postcode":"18901",
    "addr:street":"S Main St",
    "iso:country":"US",
    "sg:address":"76 S Main St",
    "sg:city":"Doylestown",
    "sg:classifiers":[
        {
            "category":"Personal",
            "subcategory":"Beauty Salon",
            "type":"Services"
        }
    ],
    "sg:phone":"+1 215 489 1844",
    "sg:postcode":"18901",
    "sg:province":"PA",
    "wof:name":"Inspirations Hair Salon",
    "wof:placetype":"venue"
},
  "geometry": {"coordinates":[-75.129734,40.308534],"type":"Point"}
}