{
  "type": "Feature",
  "properties": {
    "iso:country":"US",
    "sg:address":"2022 W Hunting Park Ave",
    "sg:city":"Philadelphia",
    "sg:classifiers":[
        {
            "category":"Restaurant",
            "type":"Food & Drink"
        }
    ],
    "sg:phone":"+1 215 228 2294",
    "sg:postcode":"19140",
    "sg:province":"PA",
    "wof:name":"Hunting Park Take-Out",
    "wof:placetype":"venue"
},
  "geometry": {"coordinates":[-75.161102,40.012699],"type":"Point"}
}