{
  "type": "Feature",
  "properties": {
    "iso:country":"US",
    "sg:address":"2047 N 16th St",
    "sg:city":"Philadelphia",
    "sg:classifiers":[
        {
            "category":"Building & Trades",
            "subcategory":"Locksmith",
            "type":"Services"
        }
    ],
    "sg:phone":"+1 267 702 1168",
    "sg:postcode":"19121",
    "sg:province":"PA",
    "sg:tags":[
        "key"
    ],
    "wof:name":"Always Available 24 Hour Emergency Locksmith",
    "wof:placetype":"venue"
},
  "geometry": {"coordinates":[-75.159739,39.984642],"type":"Point"}
}