{
  "type": "Feature",
  "properties": {
    "iso:country":"US",
    "sg:address":"3501 Paxton St",
    "sg:city":"Harrisburg",
    "sg:classifiers":[
        {
            "category":"Shopping",
            "subcategory":"Department Store",
            "type":"Retail Goods"
        }
    ],
    "sg:phone":"+1 717 561 1869",
    "sg:postcode":"17111",
    "sg:province":"PA",
    "wof:name":"Pac Sun",
    "wof:placetype":"venue"
},
  "geometry": {"coordinates":[-76.830246,40.253726],"type":"Point"}
}