{
  "type": "Feature",
  "properties": {
    "iso:country":"US",
    "sg:address":"677 Millers Run Rd",
    "sg:city":"Cuddy",
    "sg:classifiers":[
        {
            "category":"Wholesale",
            "subcategory":"Machinery & Supplies",
            "type":"Manufacturing & Wholesale Goods"
        }
    ],
    "sg:phone":"+1 412 220 3140",
    "sg:postcode":"15031",
    "sg:province":"PA",
    "sg:tags":[
        "sheet",
        "metal",
        "working"
    ],
    "wof:name":"Demmler Machinery Inc",
    "wof:placetype":"venue"
},
  "geometry": {"coordinates":[-80.169116,40.34702],"type":"Point"}
}