{
  "type": "Feature",
  "properties": {
    "iso:country":"US",
    "sg:address":"4640 Campbells Run Rd",
    "sg:city":"Pittsburgh",
    "sg:classifiers":[
        {
            "category":"Building & Trades",
            "subcategory":"Plumbing",
            "type":"Services"
        }
    ],
    "sg:phone":"+1 412 787 3899",
    "sg:postcode":"15205",
    "sg:province":"PA",
    "sg:tags":[
        "conditioning",
        "air",
        "system",
        "contractor"
    ],
    "wof:name":"Tobey-Karg Svc & Sales",
    "wof:placetype":"venue"
},
  "geometry": {"coordinates":[-80.13346,40.430523],"type":"Point"}
}