{
  "type": "Feature",
  "properties": {
    "addr:full":"80 W Baltimore Ave Lansdowne PA 19050",
    "addr:housenumber":"80",
    "addr:postcode":"19050",
    "addr:street":"W Baltimore Ave",
    "iso:country":"US",
    "sg:address":"80 W Baltimore Ave",
    "sg:city":"Lansdowne",
    "sg:classifiers":[
        {
            "category":"Home & Garden",
            "subcategory":"Carpets & Floor Coverings",
            "type":"Retail Goods"
        }
    ],
    "sg:phone":"+1   ",
    "sg:postcode":"19050",
    "sg:province":"PA",
    "wof:name":"Philadelphia Carpets Online",
    "wof:placetype":"venue"
},
  "geometry": {"coordinates":[-75.272381,39.938144],"type":"Point"}
}