{
  "type": "Feature",
  "properties": {
    "addr:full":"2247 W Cumberland St Harrisburg PA 17101",
    "addr:housenumber":"2247",
    "addr:postcode":"17101",
    "addr:street":"W Cumberland St",
    "iso:country":"US",
    "sg:address":"2247 W Cumberland St",
    "sg:city":"Harrisburg",
    "sg:classifiers":[
        {
            "category":"Retail",
            "subcategory":"Auto Rental",
            "type":"Services"
        }
    ],
    "sg:phone":"+1 800 272 4524",
    "sg:postcode":"17101",
    "sg:province":"PA",
    "sg:tags":[
        "car"
    ],
    "wof:name":"Cocoa Auto Leasing",
    "wof:placetype":"venue"
},
  "geometry": {"coordinates":[-76.867661,40.276778],"type":"Point"}
}