{
  "type": "Feature",
  "properties": {
    "iso:country":"US",
    "sg:address":"524 Camp Hill Mall",
    "sg:city":"Camp Hill",
    "sg:classifiers":[
        {
            "category":"Shopping Center",
            "type":"Public Place"
        }
    ],
    "sg:phone":"+1 717 737 6527",
    "sg:postcode":"17011",
    "sg:province":"PA",
    "wof:name":"Camp Hill Mall",
    "wof:placetype":"venue"
},
  "geometry": {"coordinates":[-76.935097,40.237],"type":"Point"}
}