{
  "type": "Feature",
  "properties": {
    "addr:full":"400 E High St Ebensburg PA 15931",
    "addr:housenumber":"400",
    "addr:postcode":"15931",
    "addr:street":"E High St",
    "iso:country":"US",
    "sg:address":"400 E High St",
    "sg:city":"Ebensburg",
    "sg:classifiers":[
        {
            "category":"Retail",
            "subcategory":"Auto Repair",
            "type":"Services"
        }
    ],
    "sg:phone":"+1 814 472 9441",
    "sg:postcode":"15931",
    "sg:province":"PA",
    "sg:tags":[
        "supply"
    ],
    "wof:name":"Hoover's Fred Garage",
    "wof:placetype":"venue"
},
  "geometry": {"coordinates":[-78.72171,40.485142],"type":"Point"}
}