{
  "type": "Feature",
  "properties": {
    "addr:full":"334 Broad St Waverly PA 14892",
    "addr:housenumber":"334",
    "addr:postcode":"14892",
    "addr:street":"Broad St",
    "iso:country":"US",
    "sg:address":"334 Broad St",
    "sg:city":"Waverly",
    "sg:classifiers":[
        {
            "category":"Home & Garden",
            "subcategory":"Household Appliances",
            "type":"Retail Goods"
        }
    ],
    "sg:phone":"+1 607 565 3199",
    "sg:postcode":"14892",
    "sg:province":"PA",
    "sg:tags":[
        "cleaners",
        "vacuum"
    ],
    "wof:name":"Kirby Co",
    "wof:placetype":"venue"
},
  "geometry": {"coordinates":[-76.54149099999999,42.000965],"type":"Point"}
}