{
  "type": "Feature",
  "properties": {
    "iso:country":"US",
    "sg:address":"2250 S 66th St",
    "sg:city":"Philadelphia",
    "sg:classifiers":[
        {
            "category":"Retail",
            "subcategory":"Laundry & Dry Cleaning",
            "type":"Services"
        }
    ],
    "sg:phone":"+1   ",
    "sg:postcode":"19142",
    "sg:province":"PA",
    "sg:tags":[
        "cleaner",
        "tailor"
    ],
    "wof:name":"Massis One Hour",
    "wof:placetype":"venue"
},
  "geometry": {"coordinates":[-75.234994,39.924155],"type":"Point"}
}