{
  "type": "Feature",
  "properties": {
    "iso:country":"US",
    "sg:address":"1089 E College Ave",
    "sg:city":"Bellefonte",
    "sg:classifiers":[
        {
            "category":"Organizations",
            "subcategory":"Religious Organization",
            "type":"Services"
        }
    ],
    "sg:phone":"+1 814 359 9818",
    "sg:postcode":"16823",
    "sg:province":"PA",
    "wof:name":"Maranatha Assembly Of God",
    "wof:placetype":"venue"
},
  "geometry": {"coordinates":[-77.684499,40.906797],"type":"Point"}
}