{
  "type": "Feature",
  "properties": {
    "addr:full":"1901 John F Kennedy Blvd Apt 2412 Philadelphia PA 19103",
    "addr:housenumber":"1901",
    "addr:postcode":"2412;19103",
    "addr:street":"John F Kennedy Blvd Apt",
    "iso:country":"US",
    "sg:address":"1901 John F Kennedy Blvd Apt 2412",
    "sg:city":"Philadelphia",
    "sg:classifiers":[
        {
            "category":"Professional",
            "subcategory":"Lawyer & Legal Services",
            "type":"Services"
        }
    ],
    "sg:phone":"+1 215 665 1021",
    "sg:postcode":"19103",
    "sg:province":"PA",
    "wof:name":"Harrison David C",
    "wof:placetype":"venue"
},
  "geometry": {"coordinates":[-75.171331,39.954526],"type":"Point"}
}