{
  "type": "Feature",
  "properties": {
    "iso:country":"US",
    "sg:address":"2800 Sarah St",
    "sg:city":"Pittsburgh",
    "sg:classifiers":[
        {
            "category":"Professional",
            "subcategory":"Accounting & Tax Preparation",
            "type":"Services"
        }
    ],
    "sg:phone":"+1   ",
    "sg:postcode":"15203",
    "sg:province":"PA",
    "wof:name":"D W Oster",
    "wof:placetype":"venue"
},
  "geometry": {"coordinates":[-79.96524599999999,40.424755],"type":"Point"}
}