{
  "type": "Feature",
  "properties": {
    "iso:country":"US",
    "sg:address":"11 Ann St",
    "sg:city":"Oakmont",
    "sg:classifiers":[
        {
            "category":"Home & Garden",
            "subcategory":"Building Materials",
            "type":"Retail Goods"
        },
        {
            "category":"Building & Trades",
            "subcategory":"Construction",
            "type":"Services"
        }
    ],
    "sg:phone":"+1 412 828 1016",
    "sg:postcode":"15139",
    "sg:province":"PA",
    "sg:tags":[
        "windows-repair",
        "installation",
        "replacement"
    ],
    "sg:website":"http://www.alliedbuilding.net",
    "wof:name":"Allied Building Products Corp.",
    "wof:placetype":"venue"
},
  "geometry": {"coordinates":[-79.847318,40.521083],"type":"Point"}
}