{
  "type": "Feature",
  "properties": {
    "iso:country":"US",
    "sg:address":"310 Neptune Pl",
    "sg:city":"Scranton",
    "sg:classifiers":[
        {
            "category":"Building & Trades",
            "subcategory":"Electrical",
            "type":"Services"
        }
    ],
    "sg:phone":"+1   ",
    "sg:postcode":"18505",
    "sg:province":"PA",
    "sg:tags":[
        "electrical",
        "contractor"
    ],
    "wof:name":"Koslosky Electric",
    "wof:placetype":"venue"
},
  "geometry": {"coordinates":[-75.66884,41.398126],"type":"Point"}
}