{
  "type": "Feature",
  "properties": {
    "iso:country":"US",
    "sg:address":"230 Peterson Dr",
    "sg:city":"Bolivar",
    "sg:classifiers":[
        {
            "category":"Manufacturing",
            "subcategory":"Printing",
            "type":"Manufacturing & Wholesale Goods"
        }
    ],
    "sg:phone":"+1   ",
    "sg:postcode":"15905",
    "sg:province":"PA",
    "wof:name":"Thomas Gonda Printer",
    "wof:placetype":"venue"
},
  "geometry": {"coordinates":[-78.934333,40.280228],"type":"Point"}
}