{
  "type": "Feature",
  "properties": {
    "addr:full":"59 W Linfield Rd Royersford PA 19468",
    "addr:housenumber":"59",
    "addr:postcode":"19468",
    "addr:street":"W Linfield Rd",
    "iso:country":"US",
    "sg:address":"59 W Linfield Rd",
    "sg:city":"Royersford",
    "sg:classifiers":[
        {
            "category":"Building & Trades",
            "subcategory":"Electrical",
            "type":"Services"
        }
    ],
    "sg:phone":"+1 215 493 1499",
    "sg:postcode":"19468",
    "sg:province":"PA",
    "sg:tags":[
        "electrician"
    ],
    "wof:name":"Vision Electrical Contractors",
    "wof:placetype":"venue"
},
  "geometry": {"coordinates":[-75.511652,40.207827],"type":"Point"}
}