{
  "type": "Feature",
  "properties": {
    "addr:full":"2363 Polk Valley Rd Hellertown PA 18055",
    "addr:housenumber":"2363",
    "addr:postcode":"18055",
    "addr:street":"Polk Valley Rd",
    "iso:country":"US",
    "sg:address":"2363 Polk Valley Rd",
    "sg:city":"Hellertown",
    "sg:classifiers":[
        {
            "category":"Building & Trades",
            "subcategory":"Construction",
            "type":"Services"
        }
    ],
    "sg:phone":"+1   ",
    "sg:postcode":"18055",
    "sg:province":"PA",
    "sg:tags":[
        "roofing",
        "siding",
        "contractor"
    ],
    "wof:name":"B & W Siding & Roofing Co",
    "wof:placetype":"venue"
},
  "geometry": {"coordinates":[-75.308361,40.569992],"type":"Point"}
}