{
  "type": "Feature",
  "properties": {
    "iso:country":"US",
    "sg:address":"3249 Millers Run Rd",
    "sg:city":"Cecil",
    "sg:classifiers":[
        {
            "category":"Insurance",
            "subcategory":"Hazard Insurance",
            "type":"Services"
        }
    ],
    "sg:phone":"+1 412 221 0666",
    "sg:postcode":"15321",
    "sg:province":"PA",
    "wof:name":"Jesse J White",
    "wof:placetype":"venue"
},
  "geometry": {"coordinates":[-80.192477,40.326439],"type":"Point"}
}