{
  "type": "Feature",
  "properties": {
    "addr:full":"4412 Tyson Ave Philadelphia PA 19135",
    "addr:housenumber":"4412",
    "addr:postcode":"19135",
    "addr:street":"Tyson Ave",
    "iso:country":"US",
    "sg:address":"4412 Tyson Ave",
    "sg:city":"Philadelphia",
    "sg:classifiers":[
        {
            "category":"Food & Beverages",
            "subcategory":"Groceries & Convenience Stores",
            "type":"Retail Goods"
        },
        {
            "category":"Restaurant",
            "type":"Food & Drink"
        }
    ],
    "sg:phone":"+1 215 333 9882",
    "sg:postcode":"19135",
    "sg:province":"PA",
    "sg:tags":[
        "grocer",
        "eating"
    ],
    "wof:name":"Lidia's Deli",
    "wof:placetype":"venue"
},
  "geometry": {"coordinates":[-75.042928,40.029154],"type":"Point"}
}