{
  "type": "Feature",
  "properties": {
    "iso:country":"US",
    "sg:address":"30383 Guys Mills Rd",
    "sg:city":"Guys Mills",
    "sg:classifiers":[
        {
            "category":"Education",
            "subcategory":"School",
            "type":"Public Place"
        }
    ],
    "sg:phone":"+1 814 789 3666",
    "sg:postcode":"16327",
    "sg:province":"PA",
    "sg:tags":[
        "high"
    ],
    "wof:name":"Maplewood Jr-Sr High School",
    "wof:placetype":"venue"
},
  "geometry": {"coordinates":[-79.952181,41.648636],"type":"Point"}
}