{
  "type": "Feature",
  "properties": {
    "iso:country":"US",
    "sg:address":"3 Preston Rd",
    "sg:city":"Warren",
    "sg:classifiers":[
        {
            "category":"Manufacturing",
            "subcategory":"Glass & Minerals",
            "type":"Manufacturing & Wholesale Goods"
        }
    ],
    "sg:phone":"+1   ",
    "sg:postcode":"16365",
    "sg:province":"PA",
    "sg:tags":[
        "ready",
        "concrete",
        "mfg"
    ],
    "wof:name":"Whitmire Block Co",
    "wof:placetype":"venue"
},
  "geometry": {"coordinates":[-79.20054399999999,41.840552],"type":"Point"}
}