{
  "type": "Feature",
  "properties": {
    "iso:country":"US",
    "sg:address":"4 Casey Ct",
    "sg:city":"Newtown",
    "sg:classifiers":[
        {
            "category":"Professional",
            "type":"Services"
        }
    ],
    "sg:phone":"+1   ",
    "sg:postcode":"18940",
    "sg:province":"PA",
    "wof:name":"Jonathan Gold",
    "wof:placetype":"venue"
},
  "geometry": {"coordinates":[-74.89779299999999,40.284873],"type":"Point"}
}