{
  "type": "Feature",
  "properties": {
    "addr:full":"1555 Joel Dr Lebanon PA 17046",
    "addr:housenumber":"1555",
    "addr:postcode":"17046",
    "addr:street":"Joel Dr",
    "iso:country":"US",
    "sg:address":"1555 Joel Dr",
    "sg:city":"Lebanon",
    "sg:classifiers":[
        {
            "category":"Freight",
            "type":"Transportation"
        }
    ],
    "sg:phone":"+1   ",
    "sg:postcode":"17046",
    "sg:province":"PA",
    "sg:tags":[
        "general"
    ],
    "wof:name":"Meeting International Whse",
    "wof:placetype":"venue"
},
  "geometry": {"coordinates":[-76.385465,40.351917],"type":"Point"}
}