{
  "type": "Feature",
  "properties": {
    "iso:country":"US",
    "sg:address":"427 Main St",
    "sg:city":"Knox",
    "sg:classifiers":[
        {
            "category":"Personal",
            "subcategory":"Barber",
            "type":"Services"
        }
    ],
    "sg:phone":"+1 814 797 1127",
    "sg:postcode":"16232",
    "sg:province":"PA",
    "wof:name":"Lewis Barber Shop",
    "wof:placetype":"venue"
},
  "geometry": {"coordinates":[-79.537327,41.235681],"type":"Point"}
}