{
  "type": "Feature",
  "properties": {
    "iso:country":"US",
    "sg:address":"329 Cassatt Rd",
    "sg:city":"Berwyn",
    "sg:classifiers":[
        {
            "category":"Real Estate",
            "subcategory":"Real Estate Services",
            "type":"Services"
        },
        {
            "category":"Real Estate",
            "subcategory":"Real Estate Agent",
            "type":"Services"
        }
    ],
    "sg:phone":"+1 610 640 2766",
    "sg:postcode":"19312",
    "sg:province":"PA",
    "sg:tags":[
        "buyer",
        "broker"
    ],
    "wof:name":"Samuels Vf Real Estate In",
    "wof:placetype":"venue"
},
  "geometry": {"coordinates":[-75.452223,40.051859],"type":"Point"}
}