{
  "type": "Feature",
  "properties": {
    "addr:full":"5068 Sandy Lake Rd Carlton PA 16311",
    "addr:housenumber":"5068",
    "addr:postcode":"16311",
    "addr:street":"Sandy Lake Rd",
    "iso:country":"US",
    "sg:address":"5068 Sandy Lake Rd",
    "sg:city":"Carlton",
    "sg:classifiers":[
        {
            "category":"Organizations",
            "subcategory":"Religious Organization",
            "type":"Services"
        }
    ],
    "sg:phone":"+1 814 425 1892",
    "sg:postcode":"16311",
    "sg:province":"PA",
    "sg:tags":[
        "church"
    ],
    "wof:name":"Milledgeville Community Church",
    "wof:placetype":"venue"
},
  "geometry": {"coordinates":[-80.062704,41.46944],"type":"Point"}
}