{
  "type": "Feature",
  "properties": {
    "addr:full":"814 Rennard Cir Philadelphia PA 19116",
    "addr:housenumber":"814",
    "addr:postcode":"19116",
    "addr:street":"Rennard Cir",
    "iso:country":"US",
    "sg:address":"814 Rennard Cir",
    "sg:city":"Philadelphia",
    "sg:classifiers":[
        {
            "category":"Building & Trades",
            "subcategory":"Electrical",
            "type":"Services"
        }
    ],
    "sg:phone":"+1 215 464 1212",
    "sg:postcode":"19116",
    "sg:province":"PA",
    "sg:tags":[
        "electric",
        "contractor"
    ],
    "wof:name":"B J Shemesh",
    "wof:placetype":"venue"
},
  "geometry": {"coordinates":[-75.017557,40.114247],"type":"Point"}
}