{
  "type": "Feature",
  "properties": {
    "iso:country":"US",
    "sg:address":"2 Interchange Pl",
    "sg:city":"York",
    "sg:classifiers":[
        {
            "category":"Wholesale",
            "subcategory":"Hardware",
            "type":"Manufacturing & Wholesale Goods"
        }
    ],
    "sg:phone":"+1   ",
    "sg:postcode":"17406",
    "sg:province":"PA",
    "sg:tags":[
        "filter",
        "air",
        "for",
        "contamination"
    ],
    "wof:name":"Acia",
    "wof:placetype":"venue"
},
  "geometry": {"coordinates":[-76.74029299999999,40.019043],"type":"Point"}
}