{
  "type": "Feature",
  "properties": {
    "iso:country":"US",
    "sg:address":"312 W Riverwoods Dr",
    "sg:city":"New Hope",
    "sg:classifiers":[
        {
            "category":"Professional",
            "subcategory":"Research",
            "type":"Services"
        }
    ],
    "sg:phone":"+1 215 862 5610",
    "sg:postcode":"18938",
    "sg:province":"PA",
    "sg:tags":[
        "nonphysical",
        "commercial"
    ],
    "wof:name":"Carlsen Resources",
    "wof:placetype":"venue"
},
  "geometry": {"coordinates":[-74.95916800000001,40.353002],"type":"Point"}
}