{
  "type": "Feature",
  "properties": {
    "iso:country":"US",
    "sg:address":"1210 Perkiomen Ave",
    "sg:city":"Reading",
    "sg:classifiers":[
        {
            "category":"Health Services",
            "subcategory":"Medical Lab",
            "type":"Services"
        }
    ],
    "sg:phone":"+1 610 372 4401",
    "sg:postcode":"19602",
    "sg:province":"PA",
    "sg:tags":[
        "laboratory"
    ],
    "wof:name":"Imperial Dental Labs",
    "wof:placetype":"venue"
},
  "geometry": {"coordinates":[-75.91307999999999,40.332782],"type":"Point"}
}