{
  "type": "Feature",
  "properties": {
    "addr:full":"2415 E Orvilla Rd Hatfield PA 19440",
    "addr:housenumber":"2415",
    "addr:postcode":"19440",
    "addr:street":"E Orvilla Rd",
    "iso:country":"US",
    "sg:address":"2415 E Orvilla Rd",
    "sg:city":"Hatfield",
    "sg:classifiers":[
        {
            "category":"Building & Trades",
            "subcategory":"Plumbing",
            "type":"Services"
        }
    ],
    "sg:phone":"+1 215 362 1389",
    "sg:postcode":"19440",
    "sg:province":"PA",
    "sg:tags":[
        "plumber",
        "industrial",
        "contractors-commercial"
    ],
    "wof:name":"Robert W Pfeifle Plumbing & Heating",
    "wof:placetype":"venue"
},
  "geometry": {"coordinates":[-75.28063899999999,40.275827],"type":"Point"}
}