{
  "type": "Feature",
  "properties": {
    "iso:country":"US",
    "sg:address":"806 Fayette Ave",
    "sg:city":"Belle Vernon",
    "sg:classifiers":[
        {
            "category":"Professional",
            "subcategory":"Accounting & Tax Preparation",
            "type":"Services"
        }
    ],
    "sg:phone":"+1 724 929 5695",
    "sg:postcode":"15012",
    "sg:province":"PA",
    "sg:tags":[
        "bookkeeping",
        "general"
    ],
    "wof:name":"A & B Accounting Svc",
    "wof:placetype":"venue"
},
  "geometry": {"coordinates":[-79.84961,40.12631],"type":"Point"}
}