{
  "type": "Feature",
  "properties": {
    "iso:country":"US",
    "sg:address":"1608 Pennsylvania Ave E",
    "sg:city":"Warren",
    "sg:classifiers":[
        {
            "category":"Professional",
            "type":"Services"
        }
    ],
    "sg:phone":"+1   ",
    "sg:postcode":"16365",
    "sg:province":"PA",
    "wof:name":"Rauenzahn Cues",
    "wof:placetype":"venue"
},
  "geometry": {"coordinates":[-79.126155,41.832526],"type":"Point"}
}