{
  "type": "Feature",
  "properties": {
    "addr:full":"96 Creek Rd Volant PA 16156",
    "addr:housenumber":"96",
    "addr:postcode":"16156",
    "addr:street":"Creek Rd",
    "iso:country":"US",
    "sg:address":"96 Creek Rd",
    "sg:city":"Volant",
    "sg:classifiers":[
        {
            "category":"Wholesale",
            "subcategory":"Photographic Equipment",
            "type":"Manufacturing & Wholesale Goods"
        },
        {
            "category":"Shopping",
            "subcategory":"Photographic Equipment",
            "type":"Retail Goods"
        }
    ],
    "sg:phone":"+1 724 533 3155",
    "sg:postcode":"16156",
    "sg:province":"PA",
    "sg:tags":[
        "equipment-repair",
        "supply"
    ],
    "sg:website":"http://www.usa.canon.com",
    "wof:name":"Pat's Camera Cottage",
    "wof:placetype":"venue"
},
  "geometry": {"coordinates":[-80.25557499999999,41.120741],"type":"Point"}
}