{
  "type": "Feature",
  "properties": {
    "iso:country":"US",
    "sg:address":"6015 W Ridge Rd",
    "sg:city":"Erie",
    "sg:classifiers":[
        {
            "category":"Place Of Worship",
            "type":"Public Place"
        },
        {
            "category":"Place Of Worship",
            "subcategory":"Temple",
            "type":"Public Place"
        }
    ],
    "sg:phone":"+1 814 838 7515",
    "sg:postcode":"16506",
    "sg:province":"PA",
    "sg:tags":[
        "church"
    ],
    "wof:name":"Erie Baptist Temple",
    "wof:placetype":"venue"
},
  "geometry": {"coordinates":[-80.210819,42.05943],"type":"Point"}
}