{
  "type": "Feature",
  "properties": {
    "iso:country":"US",
    "sg:address":"E Steuben St & Lincoln Ave",
    "sg:city":"Pittsburgh",
    "sg:classifiers":[
        {
            "category":"Organizations",
            "subcategory":"Religious Organization",
            "type":"Services"
        }
    ],
    "sg:phone":"+1 412 921 1125",
    "sg:postcode":"15205",
    "sg:province":"PA",
    "wof:name":"St Matthew's Lutheran Church",
    "wof:placetype":"venue"
},
  "geometry": {"coordinates":[-80.065197,40.438066],"type":"Point"}
}