{
  "type": "Feature",
  "properties": {
    "iso:country":"US",
    "sg:address":"718 Stratford Dr",
    "sg:city":"Philadelphia",
    "sg:classifiers":[
        {
            "category":"Real Estate",
            "subcategory":"Real Estate Operator",
            "type":"Services"
        }
    ],
    "sg:phone":"+1   ",
    "sg:postcode":"19115",
    "sg:province":"PA",
    "sg:tags":[
        "building",
        "dwelling",
        "nonresidential"
    ],
    "wof:name":"Holme-Dale Corp",
    "wof:placetype":"venue"
},
  "geometry": {"coordinates":[-75.04761000000001,40.099091],"type":"Point"}
}