{
  "type": "Feature",
  "properties": {
    "iso:country":"US",
    "sg:address":"5082 Jonestown Rd",
    "sg:city":"Harrisburg",
    "sg:classifiers":[
        {
            "category":"Professional",
            "type":"Services"
        }
    ],
    "sg:phone":"+1 717 671 9697",
    "sg:postcode":"17112",
    "sg:province":"PA",
    "sg:tags":[
        "establishment"
    ],
    "wof:name":"2nd Swing",
    "wof:placetype":"venue"
},
  "geometry": {"coordinates":[-76.802252,40.310561],"type":"Point"}
}