{
  "type": "Feature",
  "properties": {
    "addr:full":"1315 Walnut St Fl 3 Philadelphia PA 19107",
    "addr:housenumber":"1315;3",
    "addr:postcode":"19107",
    "addr:street":"Walnut St",
    "iso:country":"US",
    "sg:address":"1315 Walnut St Fl 3",
    "sg:city":"Philadelphia",
    "sg:classifiers":[
        {
            "category":"Organizations",
            "subcategory":"Community Association",
            "type":"Services"
        }
    ],
    "sg:phone":"+1 215 940 3900",
    "sg:postcode":"19107",
    "sg:province":"PA",
    "sg:website":"http://www.ourturn.net",
    "wof:name":"Tenant Union Representative Ne",
    "wof:placetype":"venue"
},
  "geometry": {"coordinates":[-75.162828,39.94918],"type":"Point"}
}