{
  "type": "Feature",
  "properties": {
    "iso:country":"US",
    "sg:address":"103 Chesley Dr Ste 200",
    "sg:city":"Media",
    "sg:classifiers":[
        {
            "category":"Social Services",
            "subcategory":"Job Training",
            "type":"Services"
        }
    ],
    "sg:phone":"+1 610 566 1535",
    "sg:postcode":"19063",
    "sg:province":"PA",
    "sg:tags":[
        "sale"
    ],
    "wof:name":"High Probability Selling",
    "wof:placetype":"venue"
},
  "geometry": {"coordinates":[-75.377174,39.915974],"type":"Point"}
}