{
  "type": "Feature",
  "properties": {
    "iso:country":"US",
    "sg:address":"762 Bethlehem Pike",
    "sg:city":"Montgomeryville",
    "sg:classifiers":[
        {
            "category":"Shopping",
            "type":"Retail Goods"
        },
        {
            "category":"Wholesale",
            "subcategory":"Sporting Goods",
            "type":"Manufacturing & Wholesale Goods"
        }
    ],
    "sg:phone":"+1 215 368 5199",
    "sg:postcode":"18915",
    "sg:province":"PA",
    "sg:tags":[
        "equipment",
        "merchandise",
        "pool",
        "swimming"
    ],
    "wof:name":"Leslies Swimming Pool Supplies",
    "wof:placetype":"venue"
},
  "geometry": {"coordinates":[-75.261595,40.280199],"type":"Point"}
}