{
  "type": "Feature",
  "properties": {
    "addr:full":"631 E Warrington Ave Pittsburgh PA 15210",
    "addr:housenumber":"631",
    "addr:postcode":"15210",
    "addr:street":"E Warrington Ave",
    "iso:country":"US",
    "sg:address":"631 E Warrington Ave",
    "sg:city":"Pittsburgh",
    "sg:classifiers":[
        {
            "category":"Social Services",
            "type":"Services"
        }
    ],
    "sg:phone":"+1   ",
    "sg:postcode":"15210",
    "sg:province":"PA",
    "wof:name":"Allentown Senior Center Inc",
    "wof:placetype":"venue"
},
  "geometry": {"coordinates":[-79.996268,40.421819],"type":"Point"}
}