{
  "type": "Feature",
  "properties": {
    "iso:country":"US",
    "sg:address":"516 Main St Fl 6",
    "sg:city":"Johnstown",
    "sg:classifiers":[
        {
            "category":"Professional",
            "subcategory":"Business Services",
            "type":"Services"
        }
    ],
    "sg:phone":"+1 814 539 7141",
    "sg:postcode":"15901",
    "sg:province":"PA",
    "sg:tags":[
        "medical",
        "administration"
    ],
    "wof:name":"Capcc Program",
    "wof:placetype":"venue"
},
  "geometry": {"coordinates":[-78.917419,40.324984],"type":"Point"}
}