{
  "type": "Feature",
  "properties": {
    "iso:country":"US",
    "sg:address":"1208 Kelton Ave",
    "sg:city":"Pittsburgh",
    "sg:classifiers":[
        {
            "category":"Building & Trades",
            "subcategory":"Construction",
            "type":"Services"
        }
    ],
    "sg:phone":"+1   ",
    "sg:postcode":"15216",
    "sg:province":"PA",
    "sg:tags":[
        "house"
    ],
    "wof:name":"Kbh Painting",
    "wof:placetype":"venue"
},
  "geometry": {"coordinates":[-80.036483,40.391629],"type":"Point"}
}