{
  "type": "Feature",
  "properties": {
    "iso:country":"US",
    "sg:address":"200 Wildwood Ave",
    "sg:city":"Lansdowne",
    "sg:classifiers":[
        {
            "category":"Building & Trades",
            "subcategory":"Landscaping Services",
            "type":"Services"
        },
        {
            "category":"Home & Garden",
            "subcategory":"Building Materials",
            "type":"Retail Goods"
        },
        {
            "category":"Building & Trades",
            "subcategory":"Construction",
            "type":"Services"
        }
    ],
    "sg:phone":"+1 610 259 6106",
    "sg:postcode":"19050",
    "sg:province":"PA",
    "sg:tags":[
        "lawn",
        "builder",
        "contractor",
        "landscape",
        "maintenance",
        "gazebo",
        "patio",
        "gardener"
    ],
    "sg:website":"http://www.kleinberg.com",
    "wof:name":"Robert J Kleinberg Landscape",
    "wof:placetype":"venue"
},
  "geometry": {"coordinates":[-75.258842,39.945889],"type":"Point"}
}