{
  "type": "Feature",
  "properties": {
    "iso:country":"US",
    "sg:address":"528 Linden St",
    "sg:city":"Bethlehem",
    "sg:classifiers":[
        {
            "category":"Organizations",
            "subcategory":"Labor Organization",
            "type":"Services"
        }
    ],
    "sg:phone":"+1 610 866 3030",
    "sg:postcode":"18018",
    "sg:province":"PA",
    "wof:name":"Lehigh Valley Carpenter Union",
    "wof:placetype":"venue"
},
  "geometry": {"coordinates":[-75.37044400000001,40.622127],"type":"Point"}
}