{
  "type": "Feature",
  "properties": {
    "iso:country":"US",
    "sg:address":"225 S 15th St",
    "sg:city":"Philadelphia",
    "sg:classifiers":[
        {
            "category":"Health Services",
            "subcategory":"Doctor",
            "type":"Services"
        }
    ],
    "sg:phone":"+1 215 545 9162",
    "sg:postcode":"19102",
    "sg:province":"PA",
    "sg:tags":[
        "physician",
        "surgeon"
    ],
    "wof:name":"Women's Therapy Network",
    "wof:placetype":"venue"
},
  "geometry": {"coordinates":[-75.166042,39.948831],"type":"Point"}
}