{
  "type": "Feature",
  "properties": {
    "iso:country":"US",
    "sg:address":"4173 Howell Rd",
    "sg:city":"Malvern",
    "sg:classifiers":[
        {
            "category":"Professional",
            "subcategory":"Engineering",
            "type":"Services"
        }
    ],
    "sg:phone":"+1 610 933 7911",
    "sg:postcode":"19355",
    "sg:province":"PA",
    "sg:tags":[
        "engineer"
    ],
    "sg:website":"www.guntergeigersystems.com",
    "wof:name":"Geiger Gunter Systems LTD",
    "wof:placetype":"venue"
},
  "geometry": {"coordinates":[-75.507756,40.084669],"type":"Point"}
}