{
  "type": "Feature",
  "properties": {
    "iso:country":"US",
    "sg:address":"357 Park Ave",
    "sg:city":"Harleysville",
    "sg:classifiers":[
        {
            "category":"Professional",
            "subcategory":"Business Services",
            "type":"Services"
        }
    ],
    "sg:phone":"+1   ",
    "sg:postcode":"19438",
    "sg:province":"PA",
    "wof:name":"Ramage Music Production",
    "wof:placetype":"venue"
},
  "geometry": {"coordinates":[-75.37554799999999,40.274298],"type":"Point"}
}