{
  "type": "Feature",
  "properties": {
    "iso:country":"US",
    "sg:address":"15 Mill Race Ln",
    "sg:city":"Fayetteville",
    "sg:classifiers":[
        {
            "category":"Shopping",
            "subcategory":"Used Merchandise",
            "type":"Retail Goods"
        }
    ],
    "sg:phone":"+1   ",
    "sg:postcode":"17222",
    "sg:province":"PA",
    "wof:name":"American Victorian Dream",
    "wof:placetype":"venue"
},
  "geometry": {"coordinates":[-77.548458,39.91168],"type":"Point"}
}