{
  "type": "Feature",
  "properties": {
    "addr:full":"3751 School Ln Newtown Square PA 19073",
    "addr:housenumber":"3751",
    "addr:postcode":"19073",
    "addr:street":"School Ln",
    "iso:country":"US",
    "sg:address":"3751 School Ln",
    "sg:city":"Newtown Square",
    "sg:classifiers":[
        {
            "category":"Building & Trades",
            "subcategory":"Construction",
            "type":"Services"
        }
    ],
    "sg:phone":"+1   ",
    "sg:postcode":"19073",
    "sg:province":"PA",
    "sg:tags":[
        "house"
    ],
    "wof:name":"Home Builders Inc",
    "wof:placetype":"venue"
},
  "geometry": {"coordinates":[-75.40612900000001,39.985303],"type":"Point"}
}