{
  "type": "Feature",
  "properties": {
    "iso:country":"US",
    "sg:address":"1021 5th St",
    "sg:city":"Catasauqua",
    "sg:classifiers":[
        {
            "category":"Organizations",
            "subcategory":"Religious Organization",
            "type":"Services"
        }
    ],
    "sg:phone":"+1 610 264 0822",
    "sg:postcode":"18032",
    "sg:province":"PA",
    "sg:tags":[
        "church"
    ],
    "wof:name":"Holy Trinity Orthodox Church",
    "wof:placetype":"venue"
},
  "geometry": {"coordinates":[-75.473316,40.659009],"type":"Point"}
}