{
  "type": "Feature",
  "properties": {
    "iso:country":"US",
    "sg:address":"1063 Washington Rd",
    "sg:city":"Pittsburgh",
    "sg:classifiers":[
        {
            "category":"Banks & Credit Unions",
            "subcategory":"Bank",
            "type":"Services"
        }
    ],
    "sg:phone":"+1 412 429 2036",
    "sg:postcode":"15228",
    "sg:province":"PA",
    "sg:tags":[
        "loan"
    ],
    "wof:name":"Citi Financial",
    "wof:placetype":"venue"
},
  "geometry": {"coordinates":[-80.04935399999999,40.371734],"type":"Point"}
}