{
  "type": "Feature",
  "properties": {
    "iso:country":"US",
    "sg:address":"1106 Castle Shannon Blvd",
    "sg:city":"Pittsburgh",
    "sg:classifiers":[
        {
            "category":"Wholesale",
            "subcategory":"Non-durable Goods",
            "type":"Manufacturing & Wholesale Goods"
        }
    ],
    "sg:phone":"+1 412 343 0550",
    "sg:postcode":"15234",
    "sg:province":"PA",
    "sg:tags":[
        "fund",
        "raising",
        "merchandise"
    ],
    "wof:name":"C & R Marketing",
    "wof:placetype":"venue"
},
  "geometry": {"coordinates":[-80.02357499999999,40.364669],"type":"Point"}
}