{
  "type": "Feature",
  "properties": {
    "addr:full":"1705 Chestnut St New Ringgold PA 17960",
    "addr:housenumber":"1705",
    "addr:postcode":"17960",
    "addr:street":"Chestnut St",
    "iso:country":"US",
    "sg:address":"1705 Chestnut St",
    "sg:city":"New Ringgold",
    "sg:classifiers":[
        {
            "category":"Farming",
            "subcategory":"Orchard",
            "type":"Manufacturing & Wholesale Goods"
        }
    ],
    "sg:phone":"+1 570 943 2572",
    "sg:postcode":"17960",
    "sg:province":"PA",
    "sg:tags":[
        "fruit",
        "tree"
    ],
    "wof:name":"Heims Fruit Farm",
    "wof:placetype":"venue"
},
  "geometry": {"coordinates":[-76.033433,40.676741],"type":"Point"}
}