{
  "type": "Feature",
  "properties": {
    "iso:country":"US",
    "sg:address":"20 McDonald Blvd",
    "sg:city":"Aston",
    "sg:classifiers":[
        {
            "category":"Home & Garden",
            "subcategory":"Furniture",
            "type":"Retail Goods"
        }
    ],
    "sg:phone":"+1 610 497 9120",
    "sg:postcode":"19014",
    "sg:province":"PA",
    "wof:name":"Office Furniture Plus",
    "wof:placetype":"venue"
},
  "geometry": {"coordinates":[-75.40634,39.8503],"type":"Point"}
}