{
  "type": "Feature",
  "properties": {
    "iso:country":"US",
    "sg:address":"600 Fayette Ave",
    "sg:city":"Belle Vernon",
    "sg:classifiers":[
        {
            "category":"Retail",
            "subcategory":"Auto Repair",
            "type":"Services"
        }
    ],
    "sg:phone":"+1 724 930 9885",
    "sg:postcode":"15012",
    "sg:province":"PA",
    "sg:tags":[
        "repairing",
        "automobile"
    ],
    "wof:name":"Taylor Auto Care",
    "wof:placetype":"venue"
},
  "geometry": {"coordinates":[-79.86041,40.131049],"type":"Point"}
}