{
  "type": "Feature",
  "properties": {
    "addr:full":"2585 Grandview Dr York Haven PA 17370",
    "addr:housenumber":"2585",
    "addr:postcode":"17370",
    "addr:street":"Grandview Dr",
    "iso:country":"US",
    "sg:address":"2585 Grandview Dr",
    "sg:city":"York Haven",
    "sg:classifiers":[
        {
            "category":"Professional",
            "subcategory":"Engineering",
            "type":"Services"
        }
    ],
    "sg:phone":"+1   ",
    "sg:postcode":"17370",
    "sg:province":"PA",
    "wof:name":"Rettew Associates Inc",
    "wof:placetype":"venue"
},
  "geometry": {"coordinates":[-76.773099,40.121702],"type":"Point"}
}