{
  "type": "Feature",
  "properties": {
    "iso:country":"US",
    "sg:address":"1800 John F Kennedy Blvd",
    "sg:city":"Philadelphia",
    "sg:classifiers":[
        {
            "category":"Health Services",
            "subcategory":"Doctor",
            "type":"Services"
        }
    ],
    "sg:phone":"+1 215 640 0600",
    "sg:postcode":"19103",
    "sg:province":"PA",
    "wof:name":"Griffin Jeanne Gemmill",
    "wof:placetype":"venue"
},
  "geometry": {"coordinates":[-75.169741,39.954064],"type":"Point"}
}