{
  "type": "Feature",
  "properties": {
    "addr:full":"452 W 3rd St Wyoming PA 18644",
    "addr:housenumber":"452",
    "addr:postcode":"18644",
    "addr:street":"W 3Rd St",
    "iso:country":"US",
    "sg:address":"452 W 3rd St",
    "sg:city":"Wyoming",
    "sg:classifiers":[
        {
            "category":"Organizations",
            "subcategory":"Religious Organization",
            "type":"Services"
        }
    ],
    "sg:phone":"+1   ",
    "sg:postcode":"18644",
    "sg:province":"PA",
    "wof:name":"Apostolic Church",
    "wof:placetype":"venue"
},
  "geometry": {"coordinates":[-75.836609,41.320299],"type":"Point"}
}