{
  "type": "Feature",
  "properties": {
    "addr:full":"238 S Pittsburgh St Connellsville PA 15425",
    "addr:housenumber":"238",
    "addr:postcode":"15425",
    "addr:street":"S Pittsburgh St",
    "iso:country":"US",
    "sg:address":"238 S Pittsburgh St",
    "sg:city":"Connellsville",
    "sg:classifiers":[
        {
            "category":"Building & Trades",
            "subcategory":"Pest Control",
            "type":"Services"
        }
    ],
    "sg:phone":"+1 724 628 6280",
    "sg:postcode":"15425",
    "sg:province":"PA",
    "wof:name":"Bug Trap",
    "wof:placetype":"venue"
},
  "geometry": {"coordinates":[-79.58904200000001,40.016415],"type":"Point"}
}