{
  "type": "Feature",
  "properties": {
    "iso:country":"US",
    "sg:address":"270 Valley Forge Lookout Pl",
    "sg:city":"Wayne",
    "sg:classifiers":[
        {
            "category":"Restaurant",
            "type":"Food & Drink"
        }
    ],
    "sg:phone":"+1   ",
    "sg:postcode":"19087",
    "sg:province":"PA",
    "sg:tags":[
        "eating"
    ],
    "wof:name":"D J F Food Services Inc",
    "wof:placetype":"venue"
},
  "geometry": {"coordinates":[-75.33775199999999,40.065365],"type":"Point"}
}