{
  "type": "Feature",
  "properties": {
    "iso:country":"US",
    "sg:address":"151 Gray Valley Rd",
    "sg:city":"Mainesburg",
    "sg:classifiers":[
        {
            "category":"Real Estate",
            "subcategory":"Real Estate Operator",
            "type":"Services"
        }
    ],
    "sg:phone":"+1   ",
    "sg:postcode":"16932",
    "sg:province":"PA",
    "sg:tags":[
        "property",
        "lessor"
    ],
    "wof:name":"Rodney Sherman",
    "wof:placetype":"venue"
},
  "geometry": {"coordinates":[-76.93136800000001,41.799409],"type":"Point"}
}