{
  "type": "Feature",
  "properties": {
    "addr:full":"7854 Craig St Philadelphia PA 19136",
    "addr:housenumber":"7854",
    "addr:postcode":"19136",
    "addr:street":"Craig St",
    "iso:country":"US",
    "sg:address":"7854 Craig St",
    "sg:city":"Philadelphia",
    "sg:classifiers":[
        {
            "category":"Retail",
            "subcategory":"Laundry & Dry Cleaning",
            "type":"Services"
        }
    ],
    "sg:phone":"+1 215 725 7787",
    "sg:postcode":"19136",
    "sg:province":"PA",
    "sg:tags":[
        "cleaners",
        "rug",
        "carpet"
    ],
    "wof:name":"Service Star Restoration Co",
    "wof:placetype":"venue"
},
  "geometry": {"coordinates":[-75.030804,40.041661],"type":"Point"}
}