{
  "type": "Feature",
  "properties": {
    "iso:country":"US",
    "sg:address":"106 Arch St Ste 2",
    "sg:city":"Sunbury",
    "sg:classifiers":[
        {
            "category":"Shopping",
            "type":"Retail Goods"
        }
    ],
    "sg:phone":"+1 570 286 5885",
    "sg:postcode":"17801",
    "sg:province":"PA",
    "sg:tags":[
        "merchandise"
    ],
    "wof:name":"Merle H Phillips",
    "wof:placetype":"venue"
},
  "geometry": {"coordinates":[-76.795717,40.86427],"type":"Point"}
}