{
  "type": "Feature",
  "properties": {
    "iso:country":"US",
    "sg:address":"9315 Banes St",
    "sg:city":"Philadelphia",
    "sg:classifiers":[
        {
            "category":"Personal",
            "subcategory":"Beauty Salon",
            "type":"Services"
        }
    ],
    "sg:phone":"+1 215 969 6400",
    "sg:postcode":"19115",
    "sg:province":"PA",
    "sg:tags":[
        "nail",
        "shop",
        "manicuring"
    ],
    "wof:name":"C K Nails",
    "wof:placetype":"venue"
},
  "geometry": {"coordinates":[-75.04095,40.083486],"type":"Point"}
}