{
  "type": "Feature",
  "properties": {
    "addr:full":"606 Corporate Dr Reading PA 19605",
    "addr:housenumber":"606",
    "addr:postcode":"19605",
    "addr:street":"Corporate Dr",
    "iso:country":"US",
    "sg:address":"606 Corporate Dr",
    "sg:city":"Reading",
    "sg:classifiers":[
        {
            "category":"Home & Garden",
            "subcategory":"Hardware",
            "type":"Retail Goods"
        }
    ],
    "sg:phone":"+1 610 926 2102",
    "sg:postcode":"19605",
    "sg:province":"PA",
    "wof:name":"General Supply Co",
    "wof:placetype":"venue"
},
  "geometry": {"coordinates":[-75.94009800000001,40.407115],"type":"Point"}
}