{
  "type": "Feature",
  "properties": {
    "addr:full":"1301 Belmont Ave Philadelphia PA 19104",
    "addr:housenumber":"1301",
    "addr:postcode":"19104",
    "addr:street":"Belmont Ave",
    "iso:country":"US",
    "sg:address":"1301 Belmont Ave",
    "sg:city":"Philadelphia",
    "sg:classifiers":[
        {
            "category":"Education",
            "subcategory":"School",
            "type":"Public Place"
        }
    ],
    "sg:phone":"+1 215 581 5500",
    "sg:postcode":"19104",
    "sg:province":"PA",
    "sg:tags":[
        "high",
        "middle",
        "elementary"
    ],
    "wof:name":"Philadelphia School District",
    "wof:placetype":"venue"
},
  "geometry": {"coordinates":[-75.21247700000001,39.974815],"type":"Point"}
}