{
  "type": "Feature",
  "properties": {
    "addr:full":"3416 Baring St Apt 2R Philadelphia PA 19104",
    "addr:housenumber":"3416",
    "addr:postcode":"19104",
    "addr:street":"Baring St Apt 2R",
    "iso:country":"US",
    "sg:address":"3416 Baring St Apt 2R",
    "sg:city":"Philadelphia",
    "sg:classifiers":[
        {
            "category":"Cinema",
            "subcategory":"Movie Rental",
            "type":"Entertainment"
        }
    ],
    "sg:phone":"+1 215 387 3543",
    "sg:postcode":"19104",
    "sg:province":"PA",
    "sg:tags":[
        "picture",
        "exchange",
        "motion",
        "distributor",
        "film"
    ],
    "wof:name":"Showoff Productions",
    "wof:placetype":"venue"
},
  "geometry": {"coordinates":[-75.19136,39.961412],"type":"Point"}
}