{
  "type": "Feature",
  "properties": {
    "iso:country":"US",
    "sg:address":"2905 Banksville Rd",
    "sg:city":"Pittsburgh",
    "sg:classifiers":[
        {
            "category":"Building & Trades",
            "subcategory":"Locksmith",
            "type":"Services"
        }
    ],
    "sg:phone":"+1 412 253 6125",
    "sg:postcode":"15216",
    "sg:province":"PA",
    "sg:tags":[
        "key"
    ],
    "wof:name":"Locksmith & Locks-24 7 Emergency",
    "wof:placetype":"venue"
},
  "geometry": {"coordinates":[-80.04065900000001,40.403201],"type":"Point"}
}