{
  "type": "Feature",
  "properties": {
    "addr:full":"2012 Naudain St Philadelphia PA 19146",
    "addr:housenumber":"2012",
    "addr:postcode":"19146",
    "addr:street":"Naudain St",
    "iso:country":"US",
    "sg:address":"2012 Naudain St",
    "sg:city":"Philadelphia",
    "sg:classifiers":[
        {
            "category":"Wholesale",
            "subcategory":"Non-durable Goods",
            "type":"Manufacturing & Wholesale Goods"
        }
    ],
    "sg:phone":"+1   ",
    "sg:postcode":"19146",
    "sg:province":"PA",
    "wof:name":"Harpo Trading LLC",
    "wof:placetype":"venue"
},
  "geometry": {"coordinates":[-75.17669100000001,39.945502],"type":"Point"}
}