{
  "type": "Feature",
  "properties": {
    "iso:country":"US",
    "sg:address":"318 W Spring St",
    "sg:city":"Titusville",
    "sg:classifiers":[
        {
            "category":"Real Estate",
            "subcategory":"Real Estate Agent",
            "type":"Services"
        }
    ],
    "sg:phone":"+1   ",
    "sg:postcode":"16354",
    "sg:province":"PA",
    "wof:name":"Marsh Realty Inc",
    "wof:placetype":"venue"
},
  "geometry": {"coordinates":[-79.675106,41.626528],"type":"Point"}
}