{
  "type": "Feature",
  "properties": {
    "iso:country":"US",
    "sg:address":"4022 Woodhaven Rd",
    "sg:city":"Philadelphia",
    "sg:classifiers":[
        {
            "category":"Shopping",
            "subcategory":"Clothing, Apparel, & Fashions",
            "type":"Retail Goods"
        }
    ],
    "sg:phone":"+1 215 612 9188",
    "sg:postcode":"19154",
    "sg:province":"PA",
    "wof:name":"Scrub Shop Inc",
    "wof:placetype":"venue"
},
  "geometry": {"coordinates":[-74.969572,40.084821],"type":"Point"}
}