{
  "type": "Feature",
  "properties": {
    "addr:full":"2801 N Howard St Philadelphia PA 19133",
    "addr:housenumber":"2801",
    "addr:postcode":"19133",
    "addr:street":"N Howard St",
    "iso:country":"US",
    "sg:address":"2801 N Howard St",
    "sg:city":"Philadelphia",
    "sg:classifiers":[
        {
            "category":"Food & Beverages",
            "subcategory":"Groceries & Convenience Stores",
            "type":"Retail Goods"
        }
    ],
    "sg:phone":"+1 215 423 4449",
    "sg:postcode":"19133",
    "sg:province":"PA",
    "wof:name":"Rodriguez Grocery",
    "wof:placetype":"venue"
},
  "geometry": {"coordinates":[-75.131699,39.992699],"type":"Point"}
}