{
  "type": "Feature",
  "properties": {
    "iso:country":"US",
    "sg:address":"8320 Schantz Rd",
    "sg:city":"Breinigsville",
    "sg:classifiers":[
        {
            "category":"Government",
            "subcategory":"Police Station",
            "type":"Public Place"
        }
    ],
    "sg:phone":"+1 610 395 1438",
    "sg:postcode":"18031",
    "sg:province":"PA",
    "sg:tags":[
        "department"
    ],
    "wof:name":"Penna State Police",
    "wof:placetype":"venue"
},
  "geometry": {"coordinates":[-75.628997,40.567065],"type":"Point"}
}