{
  "type": "Feature",
  "properties": {
    "iso:country":"US",
    "sg:address":"706 Autumn Dr",
    "sg:city":"Feasterville Trevose",
    "sg:classifiers":[
        {
            "category":"Professional",
            "subcategory":"Lawyer & Legal Services",
            "type":"Services"
        }
    ],
    "sg:phone":"+1   ",
    "sg:postcode":"19053",
    "sg:province":"PA",
    "wof:name":"Perloff Steven Atty At Law",
    "wof:placetype":"venue"
},
  "geometry": {"coordinates":[-74.964619,40.164337],"type":"Point"}
}