{
  "type": "Feature",
  "properties": {
    "iso:country":"US",
    "sg:address":"35 W Pittsburgh St",
    "sg:city":"Greensburg",
    "sg:classifiers":[
        {
            "category":"Professional",
            "subcategory":"Lawyer & Legal Services",
            "type":"Services"
        }
    ],
    "sg:phone":"+1 724 836 3848",
    "sg:postcode":"15601",
    "sg:province":"PA",
    "sg:tags":[
        "attorney"
    ],
    "wof:name":"Deborah L Jackson",
    "wof:placetype":"venue"
},
  "geometry": {"coordinates":[-79.544349,40.302502],"type":"Point"}
}