{
  "type": "Feature",
  "properties": {
    "iso:country":"US",
    "sg:address":"4752 Mill Rd",
    "sg:city":"Emmaus",
    "sg:classifiers":[
        {
            "category":"Real Estate",
            "subcategory":"Surveying",
            "type":"Services"
        }
    ],
    "sg:phone":"+1   ",
    "sg:postcode":"18049",
    "sg:province":"PA",
    "wof:name":"Home Choice-Surveying Services",
    "wof:placetype":"venue"
},
  "geometry": {"coordinates":[-75.522712,40.514569],"type":"Point"}
}