{
  "type": "Feature",
  "properties": {
    "iso:country":"US",
    "sg:address":"19 Belvidere St",
    "sg:city":"Nazareth",
    "sg:classifiers":[
        {
            "category":"Insurance",
            "subcategory":"Insurance Agent",
            "type":"Services"
        }
    ],
    "sg:phone":"+1 610 759 6400",
    "sg:postcode":"18064",
    "sg:province":"PA",
    "sg:tags":[
        "financial"
    ],
    "sg:website":"http://www.statefarm.com",
    "wof:name":"John F Little",
    "wof:placetype":"venue"
},
  "geometry": {"coordinates":[-75.31113499999999,40.740595],"type":"Point"}
}