{
  "type": "Feature",
  "properties": {
    "iso:country":"US",
    "sg:address":"101 E Front St",
    "sg:city":"Berwick",
    "sg:classifiers":[
        {
            "category":"Banks & Credit Unions",
            "subcategory":"Bank",
            "type":"Services"
        }
    ],
    "sg:phone":"+1 570 759 6000",
    "sg:postcode":"18603",
    "sg:province":"PA",
    "wof:name":"Pnc Bank",
    "wof:placetype":"venue"
},
  "geometry": {"coordinates":[-76.23183299999999,41.05562],"type":"Point"}
}