{
  "type": "Feature",
  "properties": {
    "iso:country":"US",
    "sg:address":"112 Irwin Ave",
    "sg:city":"Pittsburgh",
    "sg:classifiers":[
        {
            "category":"Home & Garden",
            "subcategory":"Building Materials",
            "type":"Retail Goods"
        }
    ],
    "sg:phone":"+1 412 215 4577",
    "sg:postcode":"15202",
    "sg:province":"PA",
    "sg:tags":[
        "insulation",
        "heat"
    ],
    "wof:name":"Temp/Con Systems Inc",
    "wof:placetype":"venue"
},
  "geometry": {"coordinates":[-80.083169,40.506357],"type":"Point"}
}