{
  "type": "Feature",
  "properties": {
    "iso:country":"US",
    "sg:address":"6434 Castor Ave",
    "sg:city":"Philadelphia",
    "sg:classifiers":[
        {
            "category":"Home & Garden",
            "subcategory":"Household Appliances",
            "type":"Retail Goods"
        },
        {
            "category":"Retail",
            "subcategory":"Repair Shop",
            "type":"Services"
        },
        {
            "category":"Shopping",
            "subcategory":"Computers & Home Electronics",
            "type":"Retail Goods"
        }
    ],
    "sg:phone":"+1 215 289 0700",
    "sg:postcode":"19149",
    "sg:province":"PA",
    "sg:tags":[
        "television",
        "refinishing",
        "major",
        "appliances-small",
        "radio",
        "small",
        "consumer",
        "store"
    ],
    "sg:website":"http://www.singersappliance.com",
    "wof:name":"Singers Appliances & Tv's",
    "wof:placetype":"venue"
},
  "geometry": {"coordinates":[-75.07662999999999,40.040302],"type":"Point"}
}