{
  "type": "Feature",
  "properties": {
    "iso:country":"US",
    "sg:address":"1264 Mid-Valley Dr",
    "sg:city":"Jessup",
    "sg:classifiers":[
        {
            "category":"Wholesale",
            "subcategory":"Machinery & Supplies",
            "type":"Manufacturing & Wholesale Goods"
        },
        {
            "category":"Manufacturing",
            "subcategory":"Metals",
            "type":"Manufacturing & Wholesale Goods"
        }
    ],
    "sg:phone":"+1 570 383 7244",
    "sg:postcode":"18434",
    "sg:province":"PA",
    "sg:tags":[
        "barrels",
        "drum"
    ],
    "sg:website":"www.scrantoncooperage.com",
    "wof:name":"Scranton Cooperage Inc",
    "wof:placetype":"venue"
},
  "geometry": {"coordinates":[-75.57380000000001,41.460971],"type":"Point"}
}