{
  "type": "Feature",
  "properties": {
    "iso:country":"US",
    "sg:address":"5249 D St",
    "sg:city":"Philadelphia",
    "sg:classifiers":[
        {
            "category":"Wholesale",
            "subcategory":"Electrical",
            "type":"Manufacturing & Wholesale Goods"
        },
        {
            "category":"Shopping",
            "subcategory":"Computers & Home Electronics",
            "type":"Retail Goods"
        }
    ],
    "sg:phone":"+1 215 455 2121",
    "sg:postcode":"19120",
    "sg:province":"PA",
    "sg:tags":[
        "equipment",
        "supply",
        "electronic",
        "merchandise",
        "re"
    ],
    "wof:name":"Fertik's Electronics",
    "wof:placetype":"venue"
},
  "geometry": {"coordinates":[-75.115279,40.029813],"type":"Point"}
}