{
  "type": "Feature",
  "properties": {
    "iso:country":"US",
    "sg:address":"171 E Elizabeth Ln",
    "sg:city":"Richboro",
    "sg:classifiers":[
        {
            "category":"Professional",
            "type":"Services"
        }
    ],
    "sg:phone":"+1   ",
    "sg:postcode":"18954",
    "sg:province":"PA",
    "wof:name":"Futura Inc",
    "wof:placetype":"venue"
},
  "geometry": {"coordinates":[-75.01680500000001,40.210261],"type":"Point"}
}