{
  "type": "Feature",
  "properties": {
    "iso:country":"US",
    "sg:address":"1421 Selinger Ave",
    "sg:city":"Erie",
    "sg:classifiers":[
        {
            "category":"Manufacturing",
            "subcategory":"Tools & Machinery",
            "type":"Manufacturing & Wholesale Goods"
        }
    ],
    "sg:phone":"+1   ",
    "sg:postcode":"16505",
    "sg:province":"PA",
    "sg:tags":[
        "control",
        "mfg",
        "process",
        "instrument",
        "printed",
        "circuit",
        "boa"
    ],
    "wof:name":"Custom Electronic Assemblies",
    "wof:placetype":"venue"
},
  "geometry": {"coordinates":[-80.136357,42.099283],"type":"Point"}
}