{
  "type": "Feature",
  "properties": {
    "iso:country":"US",
    "sg:address":"255 Winter Mountain Dr",
    "sg:city":"Andreas",
    "sg:classifiers":[
        {
            "category":"Farming",
            "subcategory":"Farm & Veterinary Services",
            "type":"Manufacturing & Wholesale Goods"
        }
    ],
    "sg:phone":"+1   ",
    "sg:postcode":"18211",
    "sg:province":"PA",
    "sg:tags":[
        "vineyard",
        "winery"
    ],
    "wof:name":"Galen Glen Vineyard & Winery",
    "wof:placetype":"venue"
},
  "geometry": {"coordinates":[-75.811795,40.7557],"type":"Point"}
}