{
  "type": "Feature",
  "properties": {
    "addr:full":"9852 Bustleton Ave Philadelphia PA 19115",
    "addr:housenumber":"9852",
    "addr:postcode":"19115",
    "addr:street":"Bustleton Ave",
    "iso:country":"US",
    "sg:address":"9852 Bustleton Ave",
    "sg:city":"Philadelphia",
    "sg:classifiers":[
        {
            "category":"Shopping",
            "subcategory":"Pharmacy",
            "type":"Retail Goods"
        }
    ],
    "sg:phone":"+1   ",
    "sg:postcode":"19115",
    "sg:province":"PA",
    "sg:tags":[
        "drug",
        "store"
    ],
    "wof:name":"Eckerd",
    "wof:placetype":"venue"
},
  "geometry": {"coordinates":[-75.030705,40.096641],"type":"Point"}
}