{
  "type": "Feature",
  "properties": {
    "addr:full":"626 Caroline Dr Norristown PA 19401",
    "addr:housenumber":"626",
    "addr:postcode":"19401",
    "addr:street":"Caroline Dr",
    "iso:country":"US",
    "sg:address":"626 Caroline Dr",
    "sg:city":"Norristown",
    "sg:classifiers":[
        {
            "category":"Social Services",
            "subcategory":"Child Care",
            "type":"Services"
        }
    ],
    "sg:phone":"+1 610 277 5235",
    "sg:postcode":"19401",
    "sg:province":"PA",
    "sg:tags":[
        "day"
    ],
    "wof:name":"Tiny Tykes",
    "wof:placetype":"venue"
},
  "geometry": {"coordinates":[-75.323144,40.12064],"type":"Point"}
}