{
  "type": "Feature",
  "properties": {
    "iso:country":"US",
    "sg:address":"9987 Perry Hwy",
    "sg:city":"Wexford",
    "sg:classifiers":[
        {
            "category":"Retail",
            "subcategory":"Storage",
            "type":"Services"
        }
    ],
    "sg:phone":"+1 724 934 2842",
    "sg:postcode":"15090",
    "sg:province":"PA",
    "sg:tags":[
        "self"
    ],
    "sg:website":"www.atticselfstorage.com",
    "wof:name":"Attic Self Storage the",
    "wof:placetype":"venue"
},
  "geometry": {"coordinates":[-80.04769899999999,40.597698],"type":"Point"}
}