{
  "type": "Feature",
  "properties": {
    "iso:country":"US",
    "sg:address":"3025 Church Rd",
    "sg:city":"Lafayette Hill",
    "sg:classifiers":[
        {
            "category":"Organizations",
            "subcategory":"Religious Organization",
            "type":"Services"
        }
    ],
    "sg:phone":"+1 610 828 3098",
    "sg:postcode":"19444",
    "sg:province":"PA",
    "sg:tags":[
        "lutheran",
        "church"
    ],
    "sg:website":"www.stpeterslafayettehill.org",
    "wof:name":"Saint Peters Lutheran Church",
    "wof:placetype":"venue"
},
  "geometry": {"coordinates":[-75.251448,40.082634],"type":"Point"}
}