{
  "type": "Feature",
  "properties": {
    "iso:country":"US",
    "sg:address":"901 Willow St",
    "sg:city":"Lebanon",
    "sg:classifiers":[
        {
            "category":"Health Services",
            "subcategory":"Nursing And Care Facility",
            "type":"Services"
        }
    ],
    "sg:phone":"+1 717 272 0749",
    "sg:postcode":"17046",
    "sg:province":"PA",
    "sg:tags":[
        "personal",
        "home"
    ],
    "wof:name":"Jack Shirk's Willow Square",
    "wof:placetype":"venue"
},
  "geometry": {"coordinates":[-76.426417,40.340472],"type":"Point"}
}