{
  "type": "Feature",
  "properties": {
    "iso:country":"US",
    "sg:address":"350 Red Well Rd",
    "sg:city":"New Holland",
    "sg:classifiers":[
        {
            "category":"Organizations",
            "subcategory":"Community Association",
            "type":"Services"
        }
    ],
    "sg:phone":"+1 717 354 6688",
    "sg:postcode":"17557",
    "sg:province":"PA",
    "sg:tags":[
        "club"
    ],
    "wof:name":"Welsh Mountaineers",
    "wof:placetype":"venue"
},
  "geometry": {"coordinates":[-76.05119500000001,40.062158],"type":"Point"}
}