{
  "type": "Feature",
  "properties": {
    "iso:country":"US",
    "sg:address":"712 Church St",
    "sg:city":"Indiana",
    "sg:classifiers":[
        {
            "category":"Organizations",
            "subcategory":"Religious Organization",
            "type":"Services"
        }
    ],
    "sg:phone":"+1 724 463 8535",
    "sg:postcode":"15701",
    "sg:province":"PA",
    "sg:tags":[
        "church"
    ],
    "wof:name":"Grace United Methodist Church",
    "wof:placetype":"venue"
},
  "geometry": {"coordinates":[-79.15424400000001,40.621547],"type":"Point"}
}