{
  "type": "Feature",
  "properties": {
    "addr:full":"1110 Washington Ave Philadelphia PA 19147",
    "addr:housenumber":"1110",
    "addr:postcode":"19147",
    "addr:street":"Washington Ave",
    "iso:country":"US",
    "sg:address":"1110 Washington Ave",
    "sg:city":"Philadelphia",
    "sg:classifiers":[
        {
            "category":"Food & Beverages",
            "subcategory":"Specialty",
            "type":"Retail Goods"
        },
        {
            "category":"Ice Cream",
            "type":"Food & Drink"
        }
    ],
    "sg:phone":"+1 215 463 1108",
    "sg:postcode":"19147",
    "sg:province":"PA",
    "sg:tags":[
        "frozen",
        "yogurt"
    ],
    "wof:name":"Just Dip",
    "wof:placetype":"venue"
},
  "geometry": {"coordinates":[-75.161743,39.937138],"type":"Point"}
}