{
  "type": "Feature",
  "properties": {
    "iso:country":"US",
    "sg:address":"1880 John F Kennedy Blvd",
    "sg:city":"Philadelphia",
    "sg:classifiers":[
        {
            "category":"Professional",
            "subcategory":"Secretarial Services",
            "type":"Services"
        }
    ],
    "sg:phone":"+1 215 972 0326",
    "sg:postcode":"19103",
    "sg:province":"PA",
    "sg:tags":[
        "convention",
        "court",
        "reporter"
    ],
    "wof:name":"Ann Marie Kelly",
    "wof:placetype":"venue"
},
  "geometry": {"coordinates":[-75.17039,39.954155],"type":"Point"}
}