{
  "type": "Feature",
  "properties": {
    "addr:full":"8514 Germantown Ave Philadelphia PA 19118",
    "addr:housenumber":"8514",
    "addr:postcode":"19118",
    "addr:street":"Germantown Ave",
    "iso:country":"US",
    "sg:address":"8514 Germantown Ave",
    "sg:city":"Philadelphia",
    "sg:classifiers":[
        {
            "category":"Shopping",
            "subcategory":"Clothing, Apparel, & Fashions",
            "type":"Retail Goods"
        }
    ],
    "sg:phone":"+1 215 248 9008",
    "sg:postcode":"19118",
    "sg:province":"PA",
    "sg:tags":[
        "infant",
        "wear",
        "accessory"
    ],
    "wof:name":"Children's Place",
    "wof:placetype":"venue"
},
  "geometry": {"coordinates":[-75.207273,40.076424],"type":"Point"}
}