{
  "type": "Feature",
  "properties": {
    "iso:country":"US",
    "sg:address":"1044 Tinkerhill Rd",
    "sg:city":"Malvern",
    "sg:classifiers":[
        {
            "category":"Personal",
            "type":"Services"
        }
    ],
    "sg:phone":"+1 610 296 9091",
    "sg:postcode":"19355",
    "sg:province":"PA",
    "sg:tags":[
        "control",
        "weight"
    ],
    "wof:name":"Specialty Diets Inc",
    "wof:placetype":"venue"
},
  "geometry": {"coordinates":[-75.531994,40.095432],"type":"Point"}
}