{
  "type": "Feature",
  "properties": {
    "iso:country":"US",
    "sg:address":"270 Cove Rd",
    "sg:city":"Duncannon",
    "sg:classifiers":[
        {
            "category":"Shopping",
            "subcategory":"Computers & Home Electronics",
            "type":"Retail Goods"
        }
    ],
    "sg:phone":"+1 717 834 9831",
    "sg:postcode":"17020",
    "sg:province":"PA",
    "sg:tags":[
        "equipment"
    ],
    "sg:website":"http://www.simmonsdata.com",
    "wof:name":"Simmons Data Services",
    "wof:placetype":"venue"
},
  "geometry": {"coordinates":[-77.04792500000001,40.356059],"type":"Point"}
}