{
  "type": "Feature",
  "properties": {
    "iso:country":"US",
    "sg:address":"5607 Bensalem Blvd",
    "sg:city":"Bensalem",
    "sg:classifiers":[
        {
            "category":"Retail",
            "subcategory":"Self-service Laundry",
            "type":"Services"
        }
    ],
    "sg:phone":"+1 215 245 8403",
    "sg:postcode":"19020",
    "sg:province":"PA",
    "wof:name":"We Wash It Laundry Svc",
    "wof:placetype":"venue"
},
  "geometry": {"coordinates":[-74.905306,40.121477],"type":"Point"}
}