{
  "type": "Feature",
  "properties": {
    "iso:country":"US",
    "sg:address":"917 Race St",
    "sg:city":"Philadelphia",
    "sg:classifiers":[
        {
            "category":"Restaurant",
            "type":"Food & Drink"
        }
    ],
    "sg:phone":"+1 215 925 9388",
    "sg:postcode":"19107",
    "sg:province":"PA",
    "sg:tags":[
        "chinese"
    ],
    "wof:name":"Xiao Guan Garden",
    "wof:placetype":"venue"
},
  "geometry": {"coordinates":[-75.15498700000001,39.95529],"type":"Point"}
}