{
  "type": "Feature",
  "properties": {
    "addr:full":"1509 S 13th St Philadelphia PA 19147",
    "addr:housenumber":"1509",
    "addr:postcode":"19147",
    "addr:street":"S 13Th St",
    "iso:country":"US",
    "sg:address":"1509 S 13th St",
    "sg:city":"Philadelphia",
    "sg:classifiers":[
        {
            "category":"Personal",
            "type":"Services"
        }
    ],
    "sg:phone":"+1 215 463 2311",
    "sg:postcode":"19147",
    "sg:province":"PA",
    "sg:tags":[
        "sewing",
        "alteration"
    ],
    "wof:name":"Pasco Chas Shirtmkr",
    "wof:placetype":"venue"
},
  "geometry": {"coordinates":[-75.16590100000001,39.931198],"type":"Point"}
}