{
  "type": "Feature",
  "properties": {
    "addr:full":"662 W Neversink Rd Reading PA 19606",
    "addr:housenumber":"662",
    "addr:postcode":"19606",
    "addr:street":"W Neversink Rd",
    "iso:country":"US",
    "sg:address":"662 W Neversink Rd",
    "sg:city":"Reading",
    "sg:classifiers":[
        {
            "category":"Wholesale",
            "subcategory":"Construction Materials",
            "type":"Manufacturing & Wholesale Goods"
        }
    ],
    "sg:phone":"+1 610 779 1716",
    "sg:postcode":"19606",
    "sg:province":"PA",
    "sg:tags":[
        "sand",
        "gravel"
    ],
    "wof:name":"Stoudt's Ferry Preparation Co",
    "wof:placetype":"venue"
},
  "geometry": {"coordinates":[-75.887348,40.302994],"type":"Point"}
}