{
  "type": "Feature",
  "properties": {
    "addr:full":"7410 Bristol Pike Levittown PA 19057",
    "addr:housenumber":"7410",
    "addr:postcode":"19057",
    "addr:street":"Bristol Pike Levittown",
    "iso:country":"US",
    "sg:address":"7410 Bristol Pike",
    "sg:city":"Levittown",
    "sg:classifiers":[
        {
            "category":"Building & Trades",
            "subcategory":"Pest Control",
            "type":"Services"
        }
    ],
    "sg:phone":"+1   ",
    "sg:postcode":"19057",
    "sg:province":"PA",
    "wof:name":"Deadant Termite & Pest Control",
    "wof:placetype":"venue"
},
  "geometry": {"coordinates":[-74.832491,40.131118],"type":"Point"}
}