{
  "type": "Feature",
  "properties": {
    "iso:country":"US",
    "sg:address":"293 Schooley Ave",
    "sg:city":"Exeter",
    "sg:classifiers":[
        {
            "category":"Food & Beverages",
            "subcategory":"Meat & Fish",
            "type":"Retail Goods"
        }
    ],
    "sg:phone":"+1 570 883 9422",
    "sg:postcode":"18643",
    "sg:province":"PA",
    "wof:name":"Hatfield Quality Meats",
    "wof:placetype":"venue"
},
  "geometry": {"coordinates":[-75.823705,41.324779],"type":"Point"}
}