{
  "type": "Feature",
  "properties": {
    "iso:country":"US",
    "sg:address":"3400 Harts Run Rd",
    "sg:city":"Glenshaw",
    "sg:classifiers":[
        {
            "category":"Home & Garden",
            "subcategory":"Furniture",
            "type":"Retail Goods"
        }
    ],
    "sg:phone":"+1 412 767 5114",
    "sg:postcode":"15116",
    "sg:province":"PA",
    "wof:name":"Your Hearts Desire",
    "wof:placetype":"venue"
},
  "geometry": {"coordinates":[-79.91760499999999,40.553653],"type":"Point"}
}