{
  "type": "Feature",
  "properties": {
    "addr:full":"102 Pickering Way Exton PA 19341",
    "addr:housenumber":"102",
    "addr:postcode":"19341",
    "addr:street":"Pickering Way",
    "iso:country":"US",
    "sg:address":"102 Pickering Way",
    "sg:city":"Exton",
    "sg:classifiers":[
        {
            "category":"Real Estate",
            "subcategory":"Real Estate Operator",
            "type":"Services"
        }
    ],
    "sg:phone":"+1 484 875 3000",
    "sg:postcode":"19341",
    "sg:province":"PA",
    "sg:tags":[
        "sublease",
        "suite",
        "executive",
        "commercial",
        "space"
    ],
    "wof:name":"American Executive Centers",
    "wof:placetype":"venue"
},
  "geometry": {"coordinates":[-75.647891,40.057861],"type":"Point"}
}