{
  "type": "Feature",
  "properties": {
    "iso:country":"US",
    "sg:address":"4611 Norma Dr",
    "sg:city":"Pittsburgh",
    "sg:classifiers":[
        {
            "category":"Retail",
            "subcategory":"Animal Services",
            "type":"Services"
        }
    ],
    "sg:phone":"+1 412 884 2679",
    "sg:postcode":"15236",
    "sg:province":"PA",
    "sg:tags":[
        "personal"
    ],
    "wof:name":"Pet Tender",
    "wof:placetype":"venue"
},
  "geometry": {"coordinates":[-80.00564900000001,40.350873],"type":"Point"}
}