{
  "type": "Feature",
  "properties": {
    "iso:country":"US",
    "sg:address":"75 Hickle St",
    "sg:city":"Uniontown",
    "sg:classifiers":[
        {
            "category":"Health Services",
            "subcategory":"Nursing And Care Facility",
            "type":"Services"
        }
    ],
    "sg:phone":"+1   ",
    "sg:postcode":"15401",
    "sg:province":"PA",
    "sg:tags":[
        "skilled",
        "intermediate"
    ],
    "wof:name":"Genesis",
    "wof:placetype":"venue"
},
  "geometry": {"coordinates":[-79.71297300000001,39.8936],"type":"Point"}
}