{
  "type": "Feature",
  "properties": {
    "addr:full":"2650 S Dewey St Philadelphia PA 19142",
    "addr:housenumber":"2650",
    "addr:postcode":"19142",
    "addr:street":"S Dewey St",
    "iso:country":"US",
    "sg:address":"2650 S Dewey St",
    "sg:city":"Philadelphia",
    "sg:classifiers":[
        {
            "category":"Social Services",
            "subcategory":"Child Care",
            "type":"Services"
        }
    ],
    "sg:phone":"+1 215 729 5531",
    "sg:postcode":"19142",
    "sg:province":"PA",
    "sg:tags":[
        "day"
    ],
    "wof:name":"Alston-Carter Starreth Ms",
    "wof:placetype":"venue"
},
  "geometry": {"coordinates":[-75.22334600000001,39.923873],"type":"Point"}
}