{
  "type": "Feature",
  "properties": {
    "iso:country":"US",
    "sg:address":"418 10th St",
    "sg:city":"New Kensington",
    "sg:classifiers":[
        {
            "category":"Wholesale",
            "subcategory":"Computers",
            "type":"Manufacturing & Wholesale Goods"
        }
    ],
    "sg:phone":"+1   ",
    "sg:postcode":"15068",
    "sg:province":"PA",
    "wof:name":"Hbx Networks",
    "wof:placetype":"venue"
},
  "geometry": {"coordinates":[-79.766526,40.566615],"type":"Point"}
}