{
  "type": "Feature",
  "properties": {
    "addr:full":"43 W Lancaster Ave Downingtown PA 19335",
    "addr:housenumber":"43",
    "addr:postcode":"19335",
    "addr:street":"W Lancaster Ave",
    "iso:country":"US",
    "sg:address":"43 W Lancaster Ave",
    "sg:city":"Downingtown",
    "sg:classifiers":[
        {
            "category":"Retail",
            "subcategory":"Funeral Services",
            "type":"Services"
        }
    ],
    "sg:phone":"+1 610 269 3080",
    "sg:postcode":"19335",
    "sg:province":"PA",
    "sg:tags":[
        "director"
    ],
    "wof:name":"Donohue Funeral Homes Inc",
    "wof:placetype":"venue"
},
  "geometry": {"coordinates":[-75.70813,40.004044],"type":"Point"}
}