{
  "type": "Feature",
  "properties": {
    "iso:country":"US",
    "sg:address":"401 Park City Center",
    "sg:city":"Lancaster",
    "sg:classifiers":[
        {
            "category":"Shopping",
            "subcategory":"Jewelry",
            "type":"Retail Goods"
        }
    ],
    "sg:phone":"+1 717 291 5420",
    "sg:postcode":"17601",
    "sg:province":"PA",
    "sg:tags":[
        "jeweler"
    ],
    "wof:name":"Silver & Gold Connection 777",
    "wof:placetype":"venue"
},
  "geometry": {"coordinates":[-76.337453,40.06503],"type":"Point"}
}