{
  "type": "Feature",
  "properties": {
    "iso:country":"US",
    "sg:address":"322 Delaney Dr",
    "sg:city":"Pittsburgh",
    "sg:classifiers":[
        {
            "category":"Building & Trades",
            "subcategory":"Landscaping Services",
            "type":"Services"
        }
    ],
    "sg:phone":"+1   ",
    "sg:postcode":"15235",
    "sg:province":"PA",
    "sg:tags":[
        "landscape"
    ],
    "wof:name":"Linsenbigler Landscaping",
    "wof:placetype":"venue"
},
  "geometry": {"coordinates":[-79.80722400000001,40.435862],"type":"Point"}
}