{
  "type": "Feature",
  "properties": {
    "addr:full":"1657 The Fairway Jenkintown PA 19046",
    "addr:housenumber":"1657",
    "addr:postcode":"19046",
    "addr:street":"The Fairway",
    "iso:country":"US",
    "sg:address":"1657 The Fairway",
    "sg:city":"Jenkintown",
    "sg:classifiers":[
        {
            "category":"Professional",
            "subcategory":"Management & Consulting",
            "type":"Services"
        }
    ],
    "sg:phone":"+1   ",
    "sg:postcode":"19046",
    "sg:province":"PA",
    "wof:name":"Site View Co",
    "wof:placetype":"venue"
},
  "geometry": {"coordinates":[-75.117499,40.10666],"type":"Point"}
}