{
  "type": "Feature",
  "properties": {
    "iso:country":"US",
    "sg:address":"6100 Ardleigh St",
    "sg:city":"Philadelphia",
    "sg:classifiers":[
        {
            "category":"Professional",
            "subcategory":"Art Services",
            "type":"Services"
        }
    ],
    "sg:phone":"+1   ",
    "sg:postcode":"19138",
    "sg:province":"PA",
    "sg:tags":[
        "commercial",
        "design",
        "business"
    ],
    "wof:name":"J Delconner Design",
    "wof:placetype":"venue"
},
  "geometry": {"coordinates":[-75.166275,40.053208],"type":"Point"}
}