{
  "type": "Feature",
  "properties": {
    "addr:full":"5612 Greene St Philadelphia PA 19144",
    "addr:housenumber":"5612",
    "addr:postcode":"19144",
    "addr:street":"Greene St",
    "iso:country":"US",
    "sg:address":"5612 Greene St",
    "sg:city":"Philadelphia",
    "sg:classifiers":[
        {
            "category":"Professional",
            "subcategory":"Accounting & Tax Preparation",
            "type":"Services"
        }
    ],
    "sg:phone":"+1 215 843 9979",
    "sg:postcode":"19144",
    "sg:province":"PA",
    "sg:tags":[
        "return",
        "filing"
    ],
    "wof:name":"Jackson Hewitt Tax Svc",
    "wof:placetype":"venue"
},
  "geometry": {"coordinates":[-75.176518,40.034016],"type":"Point"}
}