{
  "type": "Feature",
  "properties": {
    "iso:country":"US",
    "sg:address":"172 Burnside Rd",
    "sg:city":"Portersville",
    "sg:classifiers":[
        {
            "category":"Professional",
            "type":"Services"
        }
    ],
    "sg:phone":"+1 724 368 8782",
    "sg:postcode":"16051",
    "sg:province":"PA",
    "sg:tags":[
        "establishment"
    ],
    "wof:name":"Applied Inovations",
    "wof:placetype":"venue"
},
  "geometry": {"coordinates":[-80.15140599999999,40.956887],"type":"Point"}
}