{
  "type": "Feature",
  "properties": {
    "iso:country":"US",
    "sg:address":"1 Liberty Ave",
    "sg:city":"Norristown",
    "sg:classifiers":[
        {
            "category":"Health Services",
            "subcategory":"Doctor",
            "type":"Services"
        }
    ],
    "sg:phone":"+1 610 539 5373",
    "sg:postcode":"19403",
    "sg:province":"PA",
    "sg:tags":[
        "oncologist"
    ],
    "wof:name":"Liberty Oncology",
    "wof:placetype":"venue"
},
  "geometry": {"coordinates":[-75.37426499999999,40.134471],"type":"Point"}
}