{
  "type": "Feature",
  "properties": {
    "iso:country":"US",
    "sg:address":"312 Macdade Blvd",
    "sg:city":"Collingdale",
    "sg:classifiers":[
        {
            "category":"Food & Beverages",
            "subcategory":"Candy",
            "type":"Retail Goods"
        }
    ],
    "sg:phone":"+1 610 461 4676",
    "sg:postcode":"19023",
    "sg:province":"PA",
    "sg:tags":[
        "confectionery"
    ],
    "wof:name":"Kelly's Kandy & Nuts",
    "wof:placetype":"venue"
},
  "geometry": {"coordinates":[-75.27046199999999,39.914806],"type":"Point"}
}