{
  "type": "Feature",
  "properties": {
    "iso:country":"US",
    "sg:address":"209 6th St",
    "sg:city":"Dravosburg",
    "sg:classifiers":[
        {
            "category":"Organizations",
            "subcategory":"Membership Organization",
            "type":"Services"
        }
    ],
    "sg:phone":"+1   ",
    "sg:postcode":"15034",
    "sg:province":"PA",
    "wof:name":"Womans Club of Dravosburg",
    "wof:placetype":"venue"
},
  "geometry": {"coordinates":[-79.89517600000001,40.350456],"type":"Point"}
}