{
  "type": "Feature",
  "properties": {
    "iso:country":"US",
    "sg:address":"711 Harrison Ave",
    "sg:city":"Jeannette",
    "sg:classifiers":[
        {
            "category":"Personal",
            "subcategory":"Beauty Salon",
            "type":"Services"
        }
    ],
    "sg:phone":"+1 724 523 1500",
    "sg:postcode":"15644",
    "sg:province":"PA",
    "wof:name":"Salon De Ron",
    "wof:placetype":"venue"
},
  "geometry": {"coordinates":[-79.60734600000001,40.334007],"type":"Point"}
}