{
  "type": "Feature",
  "properties": {
    "iso:country":"US",
    "sg:address":"93 Great Valley Pkwy",
    "sg:city":"Malvern",
    "sg:classifiers":[
        {
            "category":"Communications",
            "type":"Services"
        }
    ],
    "sg:phone":"+1 610 695 9868",
    "sg:postcode":"19355",
    "sg:province":"PA",
    "wof:name":"LA Calhene Inc",
    "wof:placetype":"venue"
},
  "geometry": {"coordinates":[-75.541703,40.060874],"type":"Point"}
}