{
  "type": "Feature",
  "properties": {
    "addr:full":"7620 City Ave Philadelphia PA 19151",
    "addr:housenumber":"7620",
    "addr:postcode":"19151",
    "addr:street":"City Ave",
    "iso:country":"US",
    "sg:address":"7620 City Ave",
    "sg:city":"Philadelphia",
    "sg:classifiers":[
        {
            "category":"Insurance",
            "subcategory":"Insurance Agent",
            "type":"Services"
        }
    ],
    "sg:phone":"+1 215 879 8906",
    "sg:postcode":"19151",
    "sg:province":"PA",
    "wof:name":"Nationwide Insurance",
    "wof:placetype":"venue"
},
  "geometry": {"coordinates":[-75.271525,39.979169],"type":"Point"}
}