{
  "type": "Feature",
  "properties": {
    "iso:country":"US",
    "sg:address":"501 Howard Ave Ste F2",
    "sg:city":"Altoona",
    "sg:classifiers":[
        {
            "category":"Health Services",
            "subcategory":"Doctor",
            "type":"Services"
        }
    ],
    "sg:phone":"+1 814 946 2701",
    "sg:postcode":"16601",
    "sg:province":"PA",
    "sg:tags":[
        "medicine",
        "physician",
        "practice",
        "surgeons",
        "family"
    ],
    "sg:website":"http://www.altoonafp.org",
    "wof:name":"Ruhl, Terry S Md",
    "wof:placetype":"venue"
},
  "geometry": {"coordinates":[-78.397673,40.521736],"type":"Point"}
}