{
  "type": "Feature",
  "properties": {
    "iso:country":"US",
    "sg:address":"440 Main St",
    "sg:city":"Latrobe",
    "sg:classifiers":[
        {
            "category":"Organizations",
            "subcategory":"Religious Organization",
            "type":"Services"
        }
    ],
    "sg:phone":"+1 724 537 8141",
    "sg:postcode":"15650",
    "sg:province":"PA",
    "sg:tags":[
        "church"
    ],
    "sg:website":"www.latrobeumc.org",
    "wof:name":"Latrobe United Methodist Chr",
    "wof:placetype":"venue"
},
  "geometry": {"coordinates":[-79.381844,40.318179],"type":"Point"}
}