{
  "type": "Feature",
  "properties": {
    "iso:country":"US",
    "sg:address":"1241 Blakeslee Boulevard Dr E",
    "sg:city":"Lehighton",
    "sg:classifiers":[
        {
            "category":"Food & Beverages",
            "subcategory":"Groceries & Convenience Stores",
            "type":"Retail Goods"
        }
    ],
    "sg:phone":"+1 570 386 4146",
    "sg:postcode":"18235",
    "sg:province":"PA",
    "sg:tags":[
        "grocer"
    ],
    "sg:website":"www.giantpa.com",
    "wof:name":"Giant Foodstore",
    "wof:placetype":"venue"
},
  "geometry": {"coordinates":[-75.72771400000001,40.818106],"type":"Point"}
}