{
  "type": "Feature",
  "properties": {
    "iso:country":"US",
    "sg:address":"1151 Cornwall Rd",
    "sg:city":"Lebanon",
    "sg:classifiers":[
        {
            "category":"Health Services",
            "subcategory":"Doctor",
            "type":"Services"
        }
    ],
    "sg:phone":"+1 717 272 6953",
    "sg:postcode":"17042",
    "sg:province":"PA",
    "sg:tags":[
        "dentist"
    ],
    "wof:name":"Thomas J Thompson DDS",
    "wof:placetype":"venue"
},
  "geometry": {"coordinates":[-76.42115,40.323302],"type":"Point"}
}