{
  "type": "Feature",
  "properties": {
    "addr:full":"3863 Union Deposit Rd Harrisburg PA 17109",
    "addr:housenumber":"3863",
    "addr:postcode":"17109",
    "addr:street":"Union Deposit Rd",
    "iso:country":"US",
    "sg:address":"3863 Union Deposit Rd",
    "sg:city":"Harrisburg",
    "sg:classifiers":[
        {
            "category":"Building & Trades",
            "subcategory":"Construction",
            "type":"Services"
        }
    ],
    "sg:phone":"+1   ",
    "sg:postcode":"17109",
    "sg:province":"PA",
    "sg:tags":[
        "new",
        "remodeling",
        "family",
        "home"
    ],
    "wof:name":"Teddys Siding & Windows Inc",
    "wof:placetype":"venue"
},
  "geometry": {"coordinates":[-76.825897,40.278236],"type":"Point"}
}