{
  "type": "Feature",
  "properties": {
    "addr:full":"1100 E Hector St Ste 225 Conshohocken PA 19428",
    "addr:housenumber":"1100",
    "addr:postcode":"19428",
    "addr:street":"E Hector St Ste 225",
    "iso:country":"US",
    "sg:address":"1100 E Hector St Ste 225",
    "sg:city":"Conshohocken",
    "sg:classifiers":[
        {
            "category":"Wholesale",
            "subcategory":"Books, Periodicals, & Newspapers",
            "type":"Manufacturing & Wholesale Goods"
        }
    ],
    "sg:phone":"+1 610 940 6940",
    "sg:postcode":"19428",
    "sg:province":"PA",
    "sg:tags":[
        "distributor",
        "publisher",
        "maps-designers"
    ],
    "wof:name":"Navteq North America",
    "wof:placetype":"venue"
},
  "geometry": {"coordinates":[-75.28717,40.07555],"type":"Point"}
}