{
  "type": "Feature",
  "properties": {
    "iso:country":"US",
    "sg:address":"2615 Johnson Rd",
    "sg:city":"Marcus Hook",
    "sg:classifiers":[
        {
            "category":"Building & Trades",
            "subcategory":"Construction",
            "type":"Services"
        }
    ],
    "sg:phone":"+1 610 494 0638",
    "sg:postcode":"19061",
    "sg:province":"PA",
    "sg:tags":[
        "roofing",
        "contractor"
    ],
    "wof:name":"Jim Valentine Roofing & Siding",
    "wof:placetype":"venue"
},
  "geometry": {"coordinates":[-75.437288,39.832683],"type":"Point"}
}