{
  "type": "Feature",
  "properties": {
    "iso:country":"US",
    "sg:address":"444 Railroad Ave",
    "sg:city":"Ambler",
    "sg:classifiers":[
        {
            "category":"Organizations",
            "subcategory":"Religious Organization",
            "type":"Services"
        }
    ],
    "sg:phone":"+1 215 793 0568",
    "sg:postcode":"19002",
    "sg:province":"PA",
    "sg:tags":[
        "clergy"
    ],
    "wof:name":"Dennis E Joell",
    "wof:placetype":"venue"
},
  "geometry": {"coordinates":[-75.235136,40.161318],"type":"Point"}
}