{
  "type": "Feature",
  "properties": {
    "iso:country":"US",
    "sg:address":"2101 Greentree Rd",
    "sg:city":"Carnegie",
    "sg:classifiers":[
        {
            "category":"Health Services",
            "subcategory":"Health Practitioner",
            "type":"Services"
        }
    ],
    "sg:phone":"+1 412 279 1881",
    "sg:postcode":"15106",
    "sg:province":"PA",
    "sg:tags":[
        "therapy",
        "physical"
    ],
    "wof:name":"Moses Dr Todd J",
    "wof:placetype":"venue"
},
  "geometry": {"coordinates":[-80.08228099999999,40.387749],"type":"Point"}
}