{
  "type": "Feature",
  "properties": {
    "iso:country":"US",
    "sg:address":"18015 Path Valley Rd",
    "sg:city":"Spring Run",
    "sg:classifiers":[
        {
            "category":"Health Services",
            "subcategory":"Nursing And Care Facility",
            "type":"Services"
        }
    ],
    "sg:phone":"+1 717 349 7329",
    "sg:postcode":"17262",
    "sg:province":"PA",
    "sg:tags":[
        "home",
        "retirement",
        "community"
    ],
    "wof:name":"Aprontree Large Personal Care",
    "wof:placetype":"venue"
},
  "geometry": {"coordinates":[-77.75933499999999,40.160602],"type":"Point"}
}