{
  "type": "Feature",
  "properties": {
    "iso:country":"US",
    "sg:address":"175 Strafford Ave",
    "sg:city":"Wayne",
    "sg:classifiers":[
        {
            "category":"Manufacturing",
            "subcategory":"Printing",
            "type":"Manufacturing & Wholesale Goods"
        }
    ],
    "sg:phone":"+1 610 975 9230",
    "sg:postcode":"19087",
    "sg:province":"PA",
    "sg:tags":[
        "printer"
    ],
    "wof:name":"Advanced Business Systems",
    "wof:placetype":"venue"
},
  "geometry": {"coordinates":[-75.398426,40.045541],"type":"Point"}
}