{
  "type": "Feature",
  "properties": {
    "addr:full":"3637 Morrell Cir Philadelphia PA 19114",
    "addr:housenumber":"3637",
    "addr:postcode":"19114",
    "addr:street":"Morrell Cir",
    "iso:country":"US",
    "sg:address":"3637 Morrell Cir",
    "sg:city":"Philadelphia",
    "sg:classifiers":[
        {
            "category":"Professional",
            "type":"Services"
        }
    ],
    "sg:phone":"+1   ",
    "sg:postcode":"19114",
    "sg:province":"PA",
    "wof:name":"Baobob Tree",
    "wof:placetype":"venue"
},
  "geometry": {"coordinates":[-74.98745700000001,40.069282],"type":"Point"}
}