{
  "type": "Feature",
  "properties": {
    "iso:country":"US",
    "sg:address":"365 Penn Ests",
    "sg:city":"East Stroudsburg",
    "sg:classifiers":[
        {
            "category":"Wholesale",
            "subcategory":"Machinery & Supplies",
            "type":"Manufacturing & Wholesale Goods"
        }
    ],
    "sg:phone":"+1 570 421 5151",
    "sg:postcode":"18301",
    "sg:province":"PA",
    "sg:tags":[
        "equipment",
        "industrial"
    ],
    "wof:name":"Eagle Lift Truck",
    "wof:placetype":"venue"
},
  "geometry": {"coordinates":[-75.238288,41.038988],"type":"Point"}
}