{
  "type": "Feature",
  "properties": {
    "addr:full":"4060 Lycoming Creek Rd Cogan Station PA 17728",
    "addr:housenumber":"4060",
    "addr:postcode":"17728",
    "addr:street":"Lycoming Creek Rd Cogan Station",
    "iso:country":"US",
    "sg:address":"4060 Lycoming Creek Rd",
    "sg:city":"Cogan Station",
    "sg:classifiers":[
        {
            "category":"Home & Garden",
            "subcategory":"Hardware",
            "type":"Retail Goods"
        }
    ],
    "sg:phone":"+1 570 494 0340",
    "sg:postcode":"17728",
    "sg:province":"PA",
    "wof:name":"Schon Brothers Hardware",
    "wof:placetype":"venue"
},
  "geometry": {"coordinates":[-77.063919,41.304115],"type":"Point"}
}