{
  "type": "Feature",
  "properties": {
    "iso:country":"US",
    "sg:address":"519 N Lancaster St",
    "sg:city":"Jonestown",
    "sg:classifiers":[
        {
            "category":"Building & Trades",
            "subcategory":"Construction",
            "type":"Services"
        }
    ],
    "sg:phone":"+1   ",
    "sg:postcode":"17038",
    "sg:province":"PA",
    "sg:tags":[
        "house"
    ],
    "wof:name":"Earnest E Shuey",
    "wof:placetype":"venue"
},
  "geometry": {"coordinates":[-76.482277,40.438225],"type":"Point"}
}