{
  "type": "Feature",
  "properties": {
    "addr:full":"950 W Valley Rd Wayne PA 19087",
    "addr:housenumber":"950",
    "addr:postcode":"19087",
    "addr:street":"W Valley Rd",
    "iso:country":"US",
    "sg:address":"950 W Valley Rd",
    "sg:city":"Wayne",
    "sg:classifiers":[
        {
            "category":"Banks & Credit Unions",
            "subcategory":"Financial Services",
            "type":"Services"
        }
    ],
    "sg:phone":"+1   ",
    "sg:postcode":"19087",
    "sg:province":"PA",
    "sg:tags":[
        "investor",
        "private"
    ],
    "wof:name":"Argosy Investment Partners LP",
    "wof:placetype":"venue"
},
  "geometry": {"coordinates":[-75.424257,40.069108],"type":"Point"}
}