{
  "type": "Feature",
  "properties": {
    "addr:full":"5757 Ellsworth Ave Pittsburgh PA 15232",
    "addr:housenumber":"5757",
    "addr:postcode":"15232",
    "addr:street":"Ellsworth Ave",
    "iso:country":"US",
    "sg:address":"5757 Ellsworth Ave",
    "sg:city":"Pittsburgh",
    "sg:classifiers":[
        {
            "category":"Retail",
            "subcategory":"Car Wash",
            "type":"Services"
        }
    ],
    "sg:phone":"+1 412 441 4405",
    "sg:postcode":"15232",
    "sg:province":"PA",
    "sg:tags":[
        "automobile",
        "detail",
        "clean"
    ],
    "wof:name":"Shady Side Detail",
    "wof:placetype":"venue"
},
  "geometry": {"coordinates":[-79.931383,40.455547],"type":"Point"}
}