{
  "type": "Feature",
  "properties": {
    "addr:full":"1010 Murry Ridge Ln Murrysville PA 15668",
    "addr:housenumber":"1010",
    "addr:postcode":"15668",
    "addr:street":"Murry Ridge Ln",
    "iso:country":"US",
    "sg:address":"1010 Murry Ridge Ln",
    "sg:city":"Murrysville",
    "sg:classifiers":[
        {
            "category":"Insurance",
            "subcategory":"Health Insurance",
            "type":"Services"
        }
    ],
    "sg:phone":"+1   ",
    "sg:postcode":"15668",
    "sg:province":"PA",
    "sg:tags":[
        "carrier"
    ],
    "wof:name":"RI Assurance",
    "wof:placetype":"venue"
},
  "geometry": {"coordinates":[-79.692268,40.48636],"type":"Point"}
}