{
  "type": "Feature",
  "properties": {
    "iso:country":"US",
    "sg:address":"1015 Chestnut St",
    "sg:city":"Philadelphia",
    "sg:classifiers":[
        {
            "category":"Social Services",
            "type":"Services"
        }
    ],
    "sg:phone":"+1 215 271 7802",
    "sg:postcode":"19107",
    "sg:province":"PA",
    "sg:tags":[
        "counselor",
        "marriage",
        "family"
    ],
    "wof:name":"Primavira Pyschologist Assoc",
    "wof:placetype":"venue"
},
  "geometry": {"coordinates":[-75.158449,39.950248],"type":"Point"}
}