{
  "type": "Feature",
  "properties": {
    "addr:full":"2173 E Gore Rd Erie PA 16510",
    "addr:housenumber":"2173",
    "addr:postcode":"16510",
    "addr:street":"E Gore Rd",
    "iso:country":"US",
    "sg:address":"2173 E Gore Rd",
    "sg:city":"Erie",
    "sg:classifiers":[
        {
            "category":"Real Estate",
            "subcategory":"Real Estate Agent",
            "type":"Services"
        }
    ],
    "sg:phone":"+1   ",
    "sg:postcode":"16510",
    "sg:province":"PA",
    "wof:name":"Lakeshore Rentals",
    "wof:placetype":"venue"
},
  "geometry": {"coordinates":[-80.01402400000001,42.111724],"type":"Point"}
}