{
  "type": "Feature",
  "properties": {
    "addr:full":"2910 N 5th Street Hwy Reading PA 19605",
    "addr:housenumber":"2910",
    "addr:postcode":"19605",
    "addr:street":"N 5Th Street Hwy",
    "iso:country":"US",
    "sg:address":"2910 N 5th Street Hwy",
    "sg:city":"Reading",
    "sg:classifiers":[
        {
            "category":"Food & Beverages",
            "subcategory":"Meat & Fish",
            "type":"Retail Goods"
        }
    ],
    "sg:phone":"+1 610 929 5483",
    "sg:postcode":"19605",
    "sg:province":"PA",
    "wof:name":"Sprecher Family Meats",
    "wof:placetype":"venue"
},
  "geometry": {"coordinates":[-75.927255,40.378268],"type":"Point"}
}