{
  "type": "Feature",
  "properties": {
    "addr:full":"2845 Tyson Ave Philadelphia PA 19149",
    "addr:housenumber":"2845",
    "addr:postcode":"19149",
    "addr:street":"Tyson Ave",
    "iso:country":"US",
    "sg:address":"2845 Tyson Ave",
    "sg:city":"Philadelphia",
    "sg:classifiers":[
        {
            "category":"Food & Beverages",
            "subcategory":"Groceries & Convenience Stores",
            "type":"Retail Goods"
        }
    ],
    "sg:phone":"+1 215 335 3780",
    "sg:postcode":"19149",
    "sg:province":"PA",
    "wof:name":"Wawa Food Market",
    "wof:placetype":"venue"
},
  "geometry": {"coordinates":[-75.056939,40.039604],"type":"Point"}
}