{
  "type": "Feature",
  "properties": {
    "iso:country":"US",
    "sg:address":"680 Heacock Rd",
    "sg:city":"Yardley",
    "sg:classifiers":[
        {
            "category":"Health Services",
            "subcategory":"Doctor",
            "type":"Services"
        }
    ],
    "sg:phone":"+1 215 860 7795",
    "sg:postcode":"19067",
    "sg:province":"PA",
    "sg:tags":[
        "physician",
        "surgeon"
    ],
    "wof:name":"Norman Lamonsoff MD",
    "wof:placetype":"venue"
},
  "geometry": {"coordinates":[-74.871064,40.222605],"type":"Point"}
}