{
  "type": "Feature",
  "properties": {
    "iso:country":"US",
    "sg:address":"5100 Campus Dr",
    "sg:city":"Plymouth Meeting",
    "sg:classifiers":[
        {
            "category":"Shopping",
            "subcategory":"Pharmacy",
            "type":"Retail Goods"
        }
    ],
    "sg:phone":"+1 610 941 6456",
    "sg:postcode":"19462",
    "sg:province":"PA",
    "wof:name":"Phar Merica Inc",
    "wof:placetype":"venue"
},
  "geometry": {"coordinates":[-75.25948099999999,40.114991],"type":"Point"}
}