{
  "type": "Feature",
  "properties": {
    "iso:country":"US",
    "sg:address":"51 E South St",
    "sg:city":"Uniontown",
    "sg:classifiers":[
        {
            "category":"Professional",
            "subcategory":"Lawyer & Legal Services",
            "type":"Services"
        }
    ],
    "sg:phone":"+1 724 438 1555",
    "sg:postcode":"15401",
    "sg:province":"PA",
    "wof:name":"Anthony S Dedola Jr",
    "wof:placetype":"venue"
},
  "geometry": {"coordinates":[-79.72417,39.900749],"type":"Point"}
}