{
  "type": "Feature",
  "properties": {
    "iso:country":"US",
    "sg:address":"113 N Hancock St",
    "sg:city":"Mcadoo",
    "sg:classifiers":[
        {
            "category":"Retail",
            "subcategory":"Auto Repair",
            "type":"Services"
        }
    ],
    "sg:phone":"+1 570 929 1504",
    "sg:postcode":"18237",
    "sg:province":"PA",
    "sg:tags":[
        "body",
        "vehicle"
    ],
    "wof:name":"Miller Motors",
    "wof:placetype":"venue"
},
  "geometry": {"coordinates":[-75.994552,40.90409],"type":"Point"}
}