{
  "type": "Feature",
  "properties": {
    "iso:country":"US",
    "sg:address":"1119 Woodland Ave",
    "sg:city":"Masury",
    "sg:classifiers":[
        {
            "category":"Professional",
            "subcategory":"Management & Consulting",
            "type":"Services"
        }
    ],
    "sg:phone":"+1 330 448 4184",
    "sg:postcode":"44438",
    "sg:province":"PA",
    "sg:tags":[
        "consultant",
        "safety"
    ],
    "wof:name":"Safety Dynamics Inc",
    "wof:placetype":"venue"
},
  "geometry": {"coordinates":[-80.53815400000001,41.211832],"type":"Point"}
}