{
  "type": "Feature",
  "properties": {
    "iso:country":"US",
    "sg:address":"834 W Spring St",
    "sg:city":"Titusville",
    "sg:classifiers":[
        {
            "category":"Building & Trades",
            "subcategory":"Construction",
            "type":"Services"
        }
    ],
    "sg:phone":"+1   ",
    "sg:postcode":"16354",
    "sg:province":"PA",
    "sg:tags":[
        "floor",
        "laying",
        "contractor"
    ],
    "wof:name":"Strawbridge Fencing",
    "wof:placetype":"venue"
},
  "geometry": {"coordinates":[-79.67889700000001,41.6265],"type":"Point"}
}