{
  "type": "Feature",
  "properties": {
    "iso:country":"US",
    "sg:address":"7541 Valley Ave",
    "sg:city":"Philadelphia",
    "sg:classifiers":[
        {
            "category":"Building & Trades",
            "subcategory":"Landscaping Services",
            "type":"Services"
        }
    ],
    "sg:phone":"+1 215 487 2330",
    "sg:postcode":"19128",
    "sg:province":"PA",
    "wof:name":"Blackthorne Landscaping",
    "wof:placetype":"venue"
},
  "geometry": {"coordinates":[-75.234133,40.051022],"type":"Point"}
}