{
  "type": "Feature",
  "properties": {
    "iso:country":"US",
    "sg:address":"300 Bilmar Dr",
    "sg:city":"Mc Kees Rocks",
    "sg:classifiers":[
        {
            "category":"Health Services",
            "subcategory":"Optometrist",
            "type":"Services"
        }
    ],
    "sg:phone":"+1 412 920 4228",
    "sg:postcode":"15136",
    "sg:province":"PA",
    "sg:tags":[
        "ophthalmologist"
    ],
    "wof:name":"Associates In Ophthalmology Ltd",
    "wof:placetype":"venue"
},
  "geometry": {"coordinates":[-80.077003,40.4729],"type":"Point"}
}