{
  "type": "Feature",
  "properties": {
    "iso:country":"US",
    "sg:address":"4027 Jordan St",
    "sg:city":"South Heights",
    "sg:classifiers":[
        {
            "category":"Professional",
            "subcategory":"Testing Lab",
            "type":"Services"
        }
    ],
    "sg:phone":"+1 724 375 1700",
    "sg:postcode":"15081",
    "sg:province":"PA",
    "sg:tags":[
        "correction",
        "radon"
    ],
    "sg:website":"www.radondetectionandcontrol.com",
    "wof:name":"Radon Detection & Control",
    "wof:placetype":"venue"
},
  "geometry": {"coordinates":[-80.23559299999999,40.574394],"type":"Point"}
}