{
  "type": "Feature",
  "properties": {
    "iso:country":"US",
    "sg:address":"920 S 12th St Fl 2",
    "sg:city":"Philadelphia",
    "sg:classifiers":[
        {
            "category":"Organizations",
            "subcategory":"Political Organization",
            "type":"Services"
        }
    ],
    "sg:phone":"+1 267 243 1468",
    "sg:postcode":"19147",
    "sg:province":"PA",
    "wof:name":"Minority Political Action Cooperation For America",
    "wof:placetype":"venue"
},
  "geometry": {"coordinates":[-75.16267000000001,39.939091],"type":"Point"}
}