{
  "type": "Feature",
  "properties": {
    "addr:full":"147 Cemetery Ln Pittsburgh PA 15237",
    "addr:housenumber":"147",
    "addr:postcode":"15237",
    "addr:street":"Cemetery Ln",
    "iso:country":"US",
    "sg:address":"147 Cemetery Ln",
    "sg:city":"Pittsburgh",
    "sg:classifiers":[
        {
            "category":"Shopping",
            "type":"Retail Goods"
        }
    ],
    "sg:phone":"+1 412 931 1317",
    "sg:postcode":"15237",
    "sg:province":"PA",
    "sg:tags":[
        "monument"
    ],
    "wof:name":"Fred Donatelli & Son Cemetery",
    "wof:placetype":"venue"
},
  "geometry": {"coordinates":[-80.017684,40.508302],"type":"Point"}
}