{
  "type": "Feature",
  "properties": {
    "iso:country":"US",
    "sg:address":"2005 Sarah St",
    "sg:city":"Pittsburgh",
    "sg:classifiers":[
        {
            "category":"Social Services",
            "subcategory":"Child Care",
            "type":"Services"
        }
    ],
    "sg:phone":"+1 412 481 1780",
    "sg:postcode":"15203",
    "sg:province":"PA",
    "wof:name":"Learning Tree Schools",
    "wof:placetype":"venue"
},
  "geometry": {"coordinates":[-79.976382,40.427667],"type":"Point"}
}