{
  "type": "Feature",
  "properties": {
    "addr:full":"102 Arla Dr Pittsburgh PA 15220",
    "addr:housenumber":"102",
    "addr:postcode":"15220",
    "addr:street":"Arla Dr",
    "iso:country":"US",
    "sg:address":"102 Arla Dr",
    "sg:city":"Pittsburgh",
    "sg:classifiers":[
        {
            "category":"Real Estate",
            "subcategory":"Real Estate Agent",
            "type":"Services"
        }
    ],
    "sg:phone":"+1   ",
    "sg:postcode":"15220",
    "sg:province":"PA",
    "wof:name":"Hargraves",
    "wof:placetype":"venue"
},
  "geometry": {"coordinates":[-80.059578,40.406569],"type":"Point"}
}