{
  "type": "Feature",
  "properties": {
    "addr:full":"5148 Locust St. Philadelphia PA 19139",
    "addr:housenumber":"5148",
    "addr:postcode":"19139",
    "addr:street":"Locust St.",
    "iso:country":"US",
    "sg:address":"5148 Locust St.",
    "sg:city":"Philadelphia",
    "sg:classifiers":[
        {
            "category":"Restaurant",
            "type":"Food & Drink"
        }
    ],
    "sg:phone":"+1 215 220 8623",
    "sg:postcode":"19139",
    "sg:province":"PA",
    "sg:tags":[
        "african"
    ],
    "sg:website":"www.greatafricanfood.com",
    "wof:name":"Soleil De Minuit",
    "wof:placetype":"venue"
},
  "geometry": {"coordinates":[-75.22551799999999,39.95556],"type":"Point"}
}