{
  "type": "Feature",
  "properties": {
    "iso:country":"US",
    "sg:address":"560 Blossom View Hts",
    "sg:city":"Somerset",
    "sg:classifiers":[
        {
            "category":"Farming",
            "subcategory":"Livestock Farm",
            "type":"Manufacturing & Wholesale Goods"
        }
    ],
    "sg:phone":"+1   ",
    "sg:postcode":"15501",
    "sg:province":"PA",
    "sg:tags":[
        "corn",
        "beef",
        "feedlot",
        "cattle"
    ],
    "wof:name":"Bluehaven Farm",
    "wof:placetype":"venue"
},
  "geometry": {"coordinates":[-79.097078,40.050279],"type":"Point"}
}