{
  "type": "Feature",
  "properties": {
    "addr:full":"3400 Market St Philadelphia PA 19104",
    "addr:housenumber":"3400",
    "addr:postcode":"19104",
    "addr:street":"Market St",
    "iso:country":"US",
    "sg:address":"3400 Market St",
    "sg:city":"Philadelphia",
    "sg:classifiers":[
        {
            "category":"Health Services",
            "subcategory":"Hospital",
            "type":"Services"
        }
    ],
    "sg:phone":"+1   ",
    "sg:postcode":"19104",
    "sg:province":"PA",
    "sg:tags":[
        "general"
    ],
    "wof:name":"Hospital Cancer Center",
    "wof:placetype":"venue"
},
  "geometry": {"coordinates":[-75.194152,39.956179],"type":"Point"}
}