{
  "type": "Feature",
  "properties": {
    "addr:full":"902 Horseshoe Pike Lebanon PA 17042",
    "addr:housenumber":"902",
    "addr:postcode":"17042",
    "addr:street":"Horseshoe Pike",
    "iso:country":"US",
    "sg:address":"902 Horseshoe Pike",
    "sg:city":"Lebanon",
    "sg:classifiers":[
        {
            "category":"Education",
            "subcategory":"School",
            "type":"Public Place"
        }
    ],
    "sg:phone":"+1 717 867 1506",
    "sg:postcode":"17042",
    "sg:province":"PA",
    "wof:name":"Fontana Parochial School",
    "wof:placetype":"venue"
},
  "geometry": {"coordinates":[-76.493252,40.284558],"type":"Point"}
}