{
  "type": "Feature",
  "properties": {
    "iso:country":"US",
    "sg:address":"490 E North Ave",
    "sg:city":"Pittsburgh",
    "sg:classifiers":[
        {
            "category":"Health Services",
            "subcategory":"Doctor",
            "type":"Services"
        }
    ],
    "sg:phone":"+1 412 231 1110",
    "sg:postcode":"15212",
    "sg:province":"PA",
    "sg:tags":[
        "physician",
        "surgeon",
        "medical"
    ],
    "wof:name":"Scott R Serbin MD",
    "wof:placetype":"venue"
},
  "geometry": {"coordinates":[-80.00183199999999,40.456447],"type":"Point"}
}