{
  "type": "Feature",
  "properties": {
    "addr:full":"1509 Chichester Ave Linwood PA 19061",
    "addr:housenumber":"1509",
    "addr:postcode":"19061",
    "addr:street":"Chichester Ave",
    "iso:country":"US",
    "sg:address":"1509 Chichester Ave",
    "sg:city":"Linwood",
    "sg:classifiers":[
        {
            "category":"Professional",
            "subcategory":"Advertising",
            "type":"Services"
        }
    ],
    "sg:phone":"+1 610 497 5610",
    "sg:postcode":"19061",
    "sg:province":"PA",
    "sg:tags":[
        "distribution"
    ],
    "wof:name":"Jenigere Trading Co",
    "wof:placetype":"venue"
},
  "geometry": {"coordinates":[-75.421896,39.825428],"type":"Point"}
}