{
  "type": "Feature",
  "properties": {
    "iso:country":"US",
    "sg:address":"181 Montour Run Rd",
    "sg:city":"Coraopolis",
    "sg:classifiers":[
        {
            "category":"Professional",
            "subcategory":"Computer Services",
            "type":"Services"
        }
    ],
    "sg:phone":"+1 412 788 3900",
    "sg:postcode":"15108",
    "sg:province":"PA",
    "sg:tags":[
        "processing",
        "datum"
    ],
    "sg:website":"www.ecsi.net",
    "wof:name":"Educational Computer Systems",
    "wof:placetype":"venue"
},
  "geometry": {"coordinates":[-80.15589799999999,40.466477],"type":"Point"}
}