{
  "type": "Feature",
  "properties": {
    "iso:country":"US",
    "sg:address":"601 N Seneca St",
    "sg:city":"Oil City",
    "sg:classifiers":[
        {
            "category":"Building & Trades",
            "subcategory":"Construction",
            "type":"Services"
        }
    ],
    "sg:phone":"+1 814 676 7451",
    "sg:postcode":"16301",
    "sg:province":"PA",
    "sg:tags":[
        "painter"
    ],
    "wof:name":"Pennewell Sandblasting & Paint",
    "wof:placetype":"venue"
},
  "geometry": {"coordinates":[-79.70005399999999,41.444822],"type":"Point"}
}