{
  "type": "Feature",
  "properties": {
    "iso:country":"US",
    "sg:address":"841 S Center Ave",
    "sg:city":"Somerset",
    "sg:classifiers":[
        {
            "category":"Manufacturing",
            "subcategory":"Leather Goods",
            "type":"Manufacturing & Wholesale Goods"
        }
    ],
    "sg:phone":"+1 814 445 6545",
    "sg:postcode":"15501",
    "sg:province":"PA",
    "sg:tags":[
        "footwear",
        "mfg"
    ],
    "wof:name":"Abilene Boot Co Inc",
    "wof:placetype":"venue"
},
  "geometry": {"coordinates":[-79.077834,39.997558],"type":"Point"}
}