{
  "type": "Feature",
  "properties": {
    "iso:country":"US",
    "sg:address":"31 N 9th St",
    "sg:city":"Stroudsburg",
    "sg:classifiers":[
        {
            "category":"Manufacturing",
            "subcategory":"Motor Vehicles & Parts",
            "type":"Manufacturing & Wholesale Goods"
        }
    ],
    "sg:phone":"+1 570 424 7477",
    "sg:postcode":"18360",
    "sg:province":"PA",
    "sg:tags":[
        "t-shirt",
        "automotive",
        "finding"
    ],
    "wof:name":"Srb Sportswear",
    "wof:placetype":"venue"
},
  "geometry": {"coordinates":[-75.19812899999999,40.984814],"type":"Point"}
}