{
  "type": "Feature",
  "properties": {
    "iso:country":"US",
    "sg:address":"1200 17th St",
    "sg:city":"Altoona",
    "sg:classifiers":[
        {
            "category":"Banks & Credit Unions",
            "subcategory":"Investment Brokerage",
            "type":"Services"
        }
    ],
    "sg:phone":"+1 814 941 4411",
    "sg:postcode":"16601",
    "sg:province":"PA",
    "sg:tags":[
        "security"
    ],
    "sg:website":"www.raymondjames.com",
    "wof:name":"Raymond James Financial Svc",
    "wof:placetype":"venue"
},
  "geometry": {"coordinates":[-78.408289,40.513684],"type":"Point"}
}