{
  "type": "Feature",
  "properties": {
    "addr:full":"724 Dekalb Pike Blue Bell PA 19422",
    "addr:housenumber":"724",
    "addr:postcode":"19422",
    "addr:street":"Dekalb Pike",
    "iso:country":"US",
    "sg:address":"724 Dekalb Pike",
    "sg:city":"Blue Bell",
    "sg:classifiers":[
        {
            "category":"Food & Beverages",
            "subcategory":"Bakery",
            "type":"Retail Goods"
        }
    ],
    "sg:phone":"+1 610 668 1488",
    "sg:postcode":"19422",
    "sg:province":"PA",
    "sg:tags":[
        "cookie",
        "cracker"
    ],
    "wof:name":"Cookies By Design",
    "wof:placetype":"venue"
},
  "geometry": {"coordinates":[-75.287086,40.170143],"type":"Point"}
}