{
  "type": "Feature",
  "properties": {
    "iso:country":"US",
    "sg:address":"250 Mercer St",
    "sg:city":"Cranberry Township",
    "sg:classifiers":[
        {
            "category":"Building & Trades",
            "subcategory":"Construction",
            "type":"Services"
        }
    ],
    "sg:phone":"+1   ",
    "sg:postcode":"16001",
    "sg:province":"PA",
    "sg:tags":[
        "contractor"
    ],
    "wof:name":"Rambo Welding",
    "wof:placetype":"venue"
},
  "geometry": {"coordinates":[-79.90712600000001,40.865005],"type":"Point"}
}