{
  "type": "Feature",
  "properties": {
    "addr:full":"4782 E Berlin Rd Thomasville PA 17364",
    "addr:housenumber":"4782",
    "addr:postcode":"17364",
    "addr:street":"E Berlin Rd",
    "iso:country":"US",
    "sg:address":"4782 E Berlin Rd",
    "sg:city":"Thomasville",
    "sg:classifiers":[
        {
            "category":"Professional",
            "type":"Services"
        }
    ],
    "sg:phone":"+1   ",
    "sg:postcode":"17364",
    "sg:province":"PA",
    "wof:name":"Larry L McKinley Inc",
    "wof:placetype":"venue"
},
  "geometry": {"coordinates":[-76.90172800000001,39.938329],"type":"Point"}
}