{
  "type": "Feature",
  "properties": {
    "iso:country":"US",
    "sg:address":"201 Stackpole St",
    "sg:city":"Saint Marys",
    "sg:classifiers":[
        {
            "category":"Professional",
            "subcategory":"Engineering",
            "type":"Services"
        }
    ],
    "sg:phone":"+1   ",
    "sg:postcode":"15857",
    "sg:province":"PA",
    "wof:name":"Signal Power and Grounding Spe",
    "wof:placetype":"venue"
},
  "geometry": {"coordinates":[-78.553133,41.431034],"type":"Point"}
}