{
  "type": "Feature",
  "properties": {
    "addr:full":"48 Blakeslee Boulevard Dr E Lehighton PA 18235",
    "addr:housenumber":"48",
    "addr:postcode":"18235",
    "addr:street":"Blakeslee Boulevard Dr E",
    "iso:country":"US",
    "sg:address":"48 Blakeslee Boulevard Dr E",
    "sg:city":"Lehighton",
    "sg:classifiers":[
        {
            "category":"Restaurant",
            "type":"Food & Drink"
        }
    ],
    "sg:phone":"+1 610 377 6598",
    "sg:postcode":"18235",
    "sg:province":"PA",
    "sg:tags":[
        "eating"
    ],
    "wof:name":"China House",
    "wof:placetype":"venue"
},
  "geometry": {"coordinates":[-75.70674099999999,40.824761],"type":"Point"}
}