{
  "type": "Feature",
  "properties": {
    "iso:country":"US",
    "sg:address":"28 W State St",
    "sg:city":"Doylestown",
    "sg:classifiers":[
        {
            "category":"Shopping",
            "subcategory":"Jewelry",
            "type":"Retail Goods"
        }
    ],
    "sg:phone":"+1 215 230 9045",
    "sg:postcode":"18901",
    "sg:province":"PA",
    "sg:tags":[
        "jeweler"
    ],
    "wof:name":"Nicholas & Alexandra Jewelers-Gemologists",
    "wof:placetype":"venue"
},
  "geometry": {"coordinates":[-75.130798,40.310001],"type":"Point"}
}