{
  "type": "Feature",
  "properties": {
    "addr:full":"528 Hill Dr Hamburg PA 19526",
    "addr:housenumber":"528",
    "addr:postcode":"19526",
    "addr:street":"Hill Dr",
    "iso:country":"US",
    "sg:address":"528 Hill Dr",
    "sg:city":"Hamburg",
    "sg:classifiers":[
        {
            "category":"Freight",
            "type":"Transportation"
        }
    ],
    "sg:phone":"+1   ",
    "sg:postcode":"19526",
    "sg:province":"PA",
    "sg:tags":[
        "operator",
        "local",
        "trucking"
    ],
    "wof:name":"Chris Merkel Trucking",
    "wof:placetype":"venue"
},
  "geometry": {"coordinates":[-75.993594,40.532206],"type":"Point"}
}