{
  "type": "Feature",
  "properties": {
    "addr:full":"6853 Horrocks St Philadelphia PA 19149",
    "addr:housenumber":"6853",
    "addr:postcode":"19149",
    "addr:street":"Horrocks St",
    "iso:country":"US",
    "sg:address":"6853 Horrocks St",
    "sg:city":"Philadelphia",
    "sg:classifiers":[
        {
            "category":"Banks & Credit Unions",
            "subcategory":"Bank",
            "type":"Services"
        }
    ],
    "sg:phone":"+1 215 745 7489",
    "sg:postcode":"19149",
    "sg:province":"PA",
    "sg:tags":[
        "loan",
        "real estate"
    ],
    "wof:name":"Michael Cohen Note Buyers",
    "wof:placetype":"venue"
},
  "geometry": {"coordinates":[-75.06817100000001,40.042827],"type":"Point"}
}