{
  "type": "Feature",
  "properties": {
    "addr:full":"1464 Manheim Pike Lancaster PA 17601",
    "addr:housenumber":"1464",
    "addr:postcode":"17601",
    "addr:street":"Manheim Pike",
    "iso:country":"US",
    "sg:address":"1464 Manheim Pike",
    "sg:city":"Lancaster",
    "sg:classifiers":[
        {
            "category":"Retail",
            "subcategory":"Auto Repair",
            "type":"Services"
        }
    ],
    "sg:phone":"+1   ",
    "sg:postcode":"17601",
    "sg:province":"PA",
    "sg:tags":[
        "exhaust",
        "general",
        "automotive"
    ],
    "wof:name":"Tuffy Auto Service Centers",
    "wof:placetype":"venue"
},
  "geometry": {"coordinates":[-76.335167,40.072759],"type":"Point"}
}