{
  "type": "Feature",
  "properties": {
    "addr:full":"806 Park City Center Lancaster PA 17601",
    "addr:housenumber":"806",
    "addr:postcode":"17601",
    "addr:street":"Park",
    "iso:country":"US",
    "sg:address":"806 Park City Center",
    "sg:city":"Lancaster",
    "sg:classifiers":[
        {
            "category":"Restaurant",
            "type":"Food & Drink"
        }
    ],
    "sg:phone":"+1 717 295 5770",
    "sg:postcode":"17601",
    "sg:province":"PA",
    "sg:tags":[
        "shop",
        "coffee"
    ],
    "wof:name":"Seattle's Best Coffee",
    "wof:placetype":"venue"
},
  "geometry": {"coordinates":[-76.340878,40.064696],"type":"Point"}
}