{
  "type": "Feature",
  "properties": {
    "addr:full":"41 N Main St Greensburg PA 15601",
    "addr:housenumber":"41",
    "addr:postcode":"15601",
    "addr:street":"N Main St",
    "iso:country":"US",
    "sg:address":"41 N Main St",
    "sg:city":"Greensburg",
    "sg:classifiers":[
        {
            "category":"Communications",
            "subcategory":"Television Station",
            "type":"Services"
        }
    ],
    "sg:phone":"+1   ",
    "sg:postcode":"15601",
    "sg:province":"PA",
    "wof:name":"CBS",
    "wof:placetype":"venue"
},
  "geometry": {"coordinates":[-79.54465500000001,40.303837],"type":"Point"}
}