{
  "type": "Feature",
  "properties": {
    "addr:full":"6985 Walnut St Northampton PA 18067",
    "addr:housenumber":"6985",
    "addr:postcode":"18067",
    "addr:street":"Walnut St",
    "iso:country":"US",
    "sg:address":"6985 Walnut St",
    "sg:city":"Northampton",
    "sg:classifiers":[
        {
            "category":"Insurance",
            "subcategory":"Hazard Insurance",
            "type":"Services"
        }
    ],
    "sg:phone":"+1 610 262 1117",
    "sg:postcode":"18067",
    "sg:province":"PA",
    "wof:name":"Michael S Walker",
    "wof:placetype":"venue"
},
  "geometry": {"coordinates":[-75.453337,40.692307],"type":"Point"}
}