{
  "type": "Feature",
  "properties": {
    "addr:full":"1430 Manning Blvd Levittown PA 19057",
    "addr:housenumber":"1430",
    "addr:postcode":"19057",
    "addr:street":"Manning Blvd",
    "iso:country":"US",
    "sg:address":"1430 Manning Blvd",
    "sg:city":"Levittown",
    "sg:classifiers":[
        {
            "category":"Building & Trades",
            "subcategory":"Construction",
            "type":"Services"
        }
    ],
    "sg:phone":"+1 215 946 7540",
    "sg:postcode":"19057",
    "sg:province":"PA",
    "sg:tags":[
        "contractor"
    ],
    "wof:name":"Fiori & Bauer Construction",
    "wof:placetype":"venue"
},
  "geometry": {"coordinates":[-74.842201,40.12476],"type":"Point"}
}