{
  "type": "Feature",
  "properties": {
    "iso:country":"US",
    "sg:address":"4921 Wyoming Ave",
    "sg:city":"Harrisburg",
    "sg:classifiers":[
        {
            "category":"Bars & Pubs",
            "type":"Food & Drink"
        }
    ],
    "sg:phone":"+1   ",
    "sg:postcode":"17109",
    "sg:province":"PA",
    "sg:tags":[
        "tavern"
    ],
    "wof:name":"Pink Lizard Inc",
    "wof:placetype":"venue"
},
  "geometry": {"coordinates":[-76.80762199999999,40.296231],"type":"Point"}
}