{
  "type": "Feature",
  "properties": {
    "iso:country":"US",
    "sg:address":"4242 Carlisle Pike",
    "sg:city":"Camp Hill",
    "sg:classifiers":[
        {
            "category":"Health Services",
            "subcategory":"Health Practitioner",
            "type":"Services"
        }
    ],
    "sg:phone":"+1 717 730 2300",
    "sg:postcode":"17011",
    "sg:province":"PA",
    "sg:tags":[
        "physician",
        "assistant"
    ],
    "wof:name":"Central PA Market Dept",
    "wof:placetype":"venue"
},
  "geometry": {"coordinates":[-76.955527,40.237938],"type":"Point"}
}