{
  "type": "Feature",
  "properties": {
    "addr:full":"126 Liberty St Jamestown PA 16134",
    "addr:housenumber":"126",
    "addr:postcode":"16134",
    "addr:street":"Liberty St",
    "iso:country":"US",
    "sg:address":"126 Liberty St",
    "sg:city":"Jamestown",
    "sg:classifiers":[
        {
            "category":"Banks & Credit Unions",
            "subcategory":"Bank",
            "type":"Services"
        }
    ],
    "sg:phone":"+1 724 932 3564",
    "sg:postcode":"16134",
    "sg:province":"PA",
    "sg:tags":[
        "commercial",
        "saving"
    ],
    "sg:website":"http://www.firstnational.com",
    "wof:name":"First National Bank",
    "wof:placetype":"venue"
},
  "geometry": {"coordinates":[-80.440725,41.484619],"type":"Point"}
}