{
  "type": "Feature",
  "properties": {
    "iso:country":"US",
    "sg:address":"9640 Downing Pl",
    "sg:city":"Irwin",
    "sg:classifiers":[
        {
            "category":"Health Services",
            "subcategory":"Doctor",
            "type":"Services"
        }
    ],
    "sg:phone":"+1 724 515 7104",
    "sg:postcode":"15642",
    "sg:province":"PA",
    "sg:tags":[
        "physician",
        "surgeon",
        "surgeons",
        "pathology"
    ],
    "wof:name":"T Pleasant Pathology",
    "wof:placetype":"venue"
},
  "geometry": {"coordinates":[-79.70679,40.311045],"type":"Point"}
}