{
  "type": "Feature",
  "properties": {
    "addr:full":"353 E New St Lancaster PA 17602",
    "addr:housenumber":"353",
    "addr:postcode":"17602",
    "addr:street":"E New St",
    "iso:country":"US",
    "sg:address":"353 E New St",
    "sg:city":"Lancaster",
    "sg:classifiers":[
        {
            "category":"Professional",
            "subcategory":"Accounting & Tax Preparation",
            "type":"Services"
        }
    ],
    "sg:phone":"+1 717 295 1455",
    "sg:postcode":"17602",
    "sg:province":"PA",
    "sg:tags":[
        "return"
    ],
    "wof:name":"Kimber Accounting & Notary",
    "wof:placetype":"venue"
},
  "geometry": {"coordinates":[-76.29942699999999,40.049773],"type":"Point"}
}