{
  "type": "Feature",
  "properties": {
    "iso:country":"US",
    "sg:address":"951 Old National Pike",
    "sg:city":"Brownsville",
    "sg:classifiers":[
        {
            "category":"Shopping",
            "type":"Retail Goods"
        }
    ],
    "sg:phone":"+1   ",
    "sg:postcode":"15417",
    "sg:province":"PA",
    "sg:tags":[
        "merchandise"
    ],
    "wof:name":"Modars Candy & Cake Supplies",
    "wof:placetype":"venue"
},
  "geometry": {"coordinates":[-79.97896900000001,40.045326],"type":"Point"}
}