{
  "type": "Feature",
  "properties": {
    "iso:country":"US",
    "sg:address":"605 W High St",
    "sg:city":"Ebensburg",
    "sg:classifiers":[
        {
            "category":"Retail",
            "subcategory":"Laundry & Dry Cleaning",
            "type":"Services"
        }
    ],
    "sg:phone":"+1 814 472 7667",
    "sg:postcode":"15931",
    "sg:province":"PA",
    "sg:tags":[
        "garment",
        "power",
        "agent"
    ],
    "wof:name":"Top Hat Cleaners",
    "wof:placetype":"venue"
},
  "geometry": {"coordinates":[-78.73074800000001,40.485296],"type":"Point"}
}