{
  "type": "Feature",
  "properties": {
    "addr:full":"166 Seghi Rd Smithfield PA 15478",
    "addr:housenumber":"166",
    "addr:postcode":"15478",
    "addr:street":"Seghi Rd",
    "iso:country":"US",
    "sg:address":"166 Seghi Rd",
    "sg:city":"Smithfield",
    "sg:phone":"+1   ",
    "sg:postcode":"15478",
    "sg:province":"PA",
    "sg:tags":[
        "farm",
        "grain"
    ],
    "wof:name":"Dorazio Farms Inc",
    "wof:placetype":"venue"
},
  "geometry": {"coordinates":[-79.789795,39.77527],"type":"Point"}
}