{
  "type": "Feature",
  "properties": {
    "iso:country":"US",
    "sg:address":"408 E 4th St Ste 201",
    "sg:city":"Bridgeport",
    "sg:classifiers":[
        {
            "category":"Building & Trades",
            "subcategory":"Construction",
            "type":"Services"
        }
    ],
    "sg:phone":"+1 610 279 3434",
    "sg:postcode":"19405",
    "sg:province":"PA",
    "sg:tags":[
        "painting",
        "contractor"
    ],
    "wof:name":"Cpc Enterprises",
    "wof:placetype":"venue"
},
  "geometry": {"coordinates":[-75.33304,40.104662],"type":"Point"}
}