{
  "type": "Feature",
  "properties": {
    "iso:country":"US",
    "sg:address":"25 Highland Rd",
    "sg:city":"Bethel Park",
    "sg:classifiers":[
        {
            "category":"Restaurant",
            "type":"Food & Drink"
        }
    ],
    "sg:menulink":"http://www.allmenus.com/pa/bethel-park/170607-burger-king/menu/",
    "sg:phone":"+1 412 831 5289",
    "sg:postcode":"15102",
    "sg:province":"PA",
    "sg:tags":[
        "burger",
        "american"
    ],
    "wof:name":"Burger King",
    "wof:placetype":"venue"
},
  "geometry": {"coordinates":[-80.050608,40.348922],"type":"Point"}
}