{
  "type": "Feature",
  "properties": {
    "iso:country":"US",
    "sg:address":"104 Old Dorwart St",
    "sg:city":"Lancaster",
    "sg:classifiers":[
        {
            "category":"Organizations",
            "subcategory":"Religious Organization",
            "type":"Services"
        }
    ],
    "sg:phone":"+1 717 207 0240",
    "sg:postcode":"17603",
    "sg:province":"PA",
    "sg:tags":[
        "clergy"
    ],
    "wof:name":"Alberto Hernandez",
    "wof:placetype":"venue"
},
  "geometry": {"coordinates":[-76.315973,40.035971],"type":"Point"}
}