{
  "type": "Feature",
  "properties": {
    "iso:country":"US",
    "sg:address":"417 W Main St",
    "sg:city":"Bloomsburg",
    "sg:classifiers":[
        {
            "category":"Food & Beverages",
            "subcategory":"Bakery",
            "type":"Retail Goods"
        }
    ],
    "sg:phone":"+1 570 784 4390",
    "sg:postcode":"17815",
    "sg:province":"PA",
    "wof:name":"Rising Dough Bakery Inc",
    "wof:placetype":"venue"
},
  "geometry": {"coordinates":[-76.46258400000001,41.000521],"type":"Point"}
}