{
  "type": "Feature",
  "properties": {
    "addr:full":"29 Wyoming Valley Mall Wilkes Barre PA 18702",
    "addr:housenumber":"29",
    "addr:postcode":"18702",
    "addr:street":"Wyoming Valley Mall",
    "iso:country":"US",
    "sg:address":"29 Wyoming Valley Mall",
    "sg:city":"Wilkes Barre",
    "sg:classifiers":[
        {
            "category":"Shopping",
            "subcategory":"Clothing, Apparel, & Fashions",
            "type":"Retail Goods"
        }
    ],
    "sg:phone":"+1   ",
    "sg:postcode":"18702",
    "sg:province":"PA",
    "wof:name":"Mothers Work",
    "wof:placetype":"venue"
},
  "geometry": {"coordinates":[-75.842406,41.24958],"type":"Point"}
}