{
  "type": "Feature",
  "properties": {
    "iso:country":"US",
    "sg:address":"475 McFarlan Rd",
    "sg:city":"Kennett Square",
    "sg:classifiers":[
        {
            "category":"Home & Garden",
            "subcategory":"Building Materials",
            "type":"Retail Goods"
        }
    ],
    "sg:phone":"+1 610 444 1200",
    "sg:postcode":"19348",
    "sg:province":"PA",
    "sg:tags":[
        "supply"
    ],
    "wof:name":"Danby Lumber & Millwork Company Inc",
    "wof:placetype":"venue"
},
  "geometry": {"coordinates":[-75.69229900000001,39.847698],"type":"Point"}
}