{
  "type": "Feature",
  "properties": {
    "iso:country":"US",
    "sg:address":"281 Suedberg Rd",
    "sg:city":"Pine Grove",
    "sg:classifiers":[
        {
            "category":"Building & Trades",
            "subcategory":"Construction",
            "type":"Services"
        }
    ],
    "sg:phone":"+1   ",
    "sg:postcode":"17963",
    "sg:province":"PA",
    "sg:tags":[
        "commercial"
    ],
    "wof:name":"Superior 3 Construction Inc",
    "wof:placetype":"venue"
},
  "geometry": {"coordinates":[-76.41189199999999,40.535347],"type":"Point"}
}