{
  "type": "Feature",
  "properties": {
    "addr:full":"125 N 3rd St Philadelphia PA 19106",
    "addr:housenumber":"125",
    "addr:postcode":"19106",
    "addr:street":"N 3Rd St",
    "iso:country":"US",
    "sg:address":"125 N 3rd St",
    "sg:city":"Philadelphia",
    "sg:classifiers":[
        {
            "category":"Manufacturing",
            "subcategory":"Printing",
            "type":"Manufacturing & Wholesale Goods"
        }
    ],
    "sg:phone":"+1 215 925 4748",
    "sg:postcode":"19106",
    "sg:province":"PA",
    "sg:tags":[
        "lithographer",
        "commercial",
        "letterpress",
        "offset"
    ],
    "wof:name":"Silverman Printing",
    "wof:placetype":"venue"
},
  "geometry": {"coordinates":[-75.145082,39.952884],"type":"Point"}
}