{
  "type": "Feature",
  "properties": {
    "addr:full":"222 Linden St Scranton PA 18503",
    "addr:housenumber":"222",
    "addr:postcode":"18503",
    "addr:street":"Linden St",
    "iso:country":"US",
    "sg:address":"222 Linden St",
    "sg:city":"Scranton",
    "sg:classifiers":[
        {
            "category":"Government",
            "subcategory":"Office",
            "type":"Public Place"
        }
    ],
    "sg:phone":"+1   ",
    "sg:postcode":"18503",
    "sg:province":"PA",
    "sg:tags":[
        "national",
        "security"
    ],
    "wof:name":"US Dept of the Air Force",
    "wof:placetype":"venue"
},
  "geometry": {"coordinates":[-75.66508899999999,41.410742],"type":"Point"}
}