{
  "type": "Feature",
  "properties": {
    "iso:country":"US",
    "sg:address":"1431 E Grand Ave",
    "sg:city":"Tower City",
    "sg:classifiers":[
        {
            "category":"Health Services",
            "subcategory":"Doctor",
            "type":"Services"
        }
    ],
    "sg:phone":"+1 717 647 7146",
    "sg:postcode":"17980",
    "sg:province":"PA",
    "sg:tags":[
        "medical"
    ],
    "wof:name":"Thomas G Watson MD",
    "wof:placetype":"venue"
},
  "geometry": {"coordinates":[-76.53868799999999,40.591376],"type":"Point"}
}