{
  "type": "Feature",
  "properties": {
    "iso:country":"US",
    "sg:address":"28 N 52nd St",
    "sg:city":"Philadelphia",
    "sg:classifiers":[
        {
            "category":"Shopping",
            "subcategory":"Pharmacy",
            "type":"Retail Goods"
        }
    ],
    "sg:phone":"+1   ",
    "sg:postcode":"19139",
    "sg:province":"PA",
    "sg:tags":[
        "drug",
        "store"
    ],
    "wof:name":"Right On Discount Inc",
    "wof:placetype":"venue"
},
  "geometry": {"coordinates":[-75.22486499999999,39.960269],"type":"Point"}
}