{
  "type": "Feature",
  "properties": {
    "iso:country":"US",
    "sg:address":"221 Conestoga Rd",
    "sg:city":"Wayne",
    "sg:classifiers":[
        {
            "category":"Professional",
            "subcategory":"Accounting & Tax Preparation",
            "type":"Services"
        }
    ],
    "sg:phone":"+1   ",
    "sg:postcode":"19087",
    "sg:province":"PA",
    "wof:name":"Charles P McGeever CPA",
    "wof:placetype":"venue"
},
  "geometry": {"coordinates":[-75.39127999999999,40.039916],"type":"Point"}
}