{
  "type": "Feature",
  "properties": {
    "iso:country":"US",
    "sg:address":"406 7th St",
    "sg:city":"Altoona",
    "sg:classifiers":[
        {
            "category":"Personal",
            "subcategory":"Beauty Salon",
            "type":"Services"
        }
    ],
    "sg:phone":"+1 814 941 7344",
    "sg:postcode":"16602",
    "sg:province":"PA",
    "wof:name":"Rebecca Bosserman's Styling",
    "wof:placetype":"venue"
},
  "geometry": {"coordinates":[-78.390671,40.516207],"type":"Point"}
}