{
  "type": "Feature",
  "properties": {
    "iso:country":"US",
    "sg:address":"956 Schuylkill Mall",
    "sg:city":"Frackville",
    "sg:classifiers":[
        {
            "category":"Travel",
            "subcategory":"Hotels & Motels",
            "type":"Entertainment"
        }
    ],
    "sg:phone":"+1 570 874 1700",
    "sg:postcode":"17931",
    "sg:province":"PA",
    "sg:website":"http://www.hiexpress.com",
    "wof:name":"Holiday Inn Express",
    "wof:placetype":"venue"
},
  "geometry": {"coordinates":[-76.22252,40.769628],"type":"Point"}
}