{
  "type": "Feature",
  "properties": {
    "iso:country":"US",
    "sg:address":"108 Irish Meetinghouse Rd",
    "sg:city":"Perkasie",
    "sg:phone":"+1   ",
    "sg:postcode":"18944",
    "sg:province":"PA",
    "sg:tags":[
        "farm",
        "field",
        "crop"
    ],
    "wof:name":"James Crooke",
    "wof:placetype":"venue"
},
  "geometry": {"coordinates":[-75.200557,40.398771],"type":"Point"}
}