{
  "type": "Feature",
  "properties": {
    "iso:country":"US",
    "sg:address":"9130 State Route 30",
    "sg:city":"Irwin",
    "sg:classifiers":[
        {
            "category":"Restaurant",
            "type":"Food & Drink"
        }
    ],
    "sg:menulink":"http://www.allmenus.com/pa/irwin/172997-wendys/menu/",
    "sg:phone":"+1 724 864 1948",
    "sg:postcode":"15642",
    "sg:province":"PA",
    "sg:tags":[
        "burger",
        "american",
        "soup"
    ],
    "wof:name":"Wendy's",
    "wof:placetype":"venue"
},
  "geometry": {"coordinates":[-79.693933,40.321077],"type":"Point"}
}