{
  "type": "Feature",
  "properties": {
    "iso:country":"US",
    "sg:address":"840 Walnut St",
    "sg:city":"Philadelphia",
    "sg:classifiers":[
        {
            "category":"Health Services",
            "subcategory":"Doctor",
            "type":"Services"
        }
    ],
    "sg:phone":"+1 215 625 6630",
    "sg:postcode":"19107",
    "sg:province":"PA",
    "wof:name":"Fox James W IV MD",
    "wof:placetype":"venue"
},
  "geometry": {"coordinates":[-75.154916,39.948051],"type":"Point"}
}