{
  "type": "Feature",
  "properties": {
    "iso:country":"US",
    "sg:address":"317 Carlisle Ave",
    "sg:city":"York",
    "sg:classifiers":[
        {
            "category":"Health Services",
            "subcategory":"Chiropractor",
            "type":"Services"
        }
    ],
    "sg:phone":"+1 717 848 2236",
    "sg:postcode":"17404",
    "sg:province":"PA",
    "wof:name":"Holder Specific Chiropractic",
    "wof:placetype":"venue"
},
  "geometry": {"coordinates":[-76.750947,39.958495],"type":"Point"}
}