{
  "type": "Feature",
  "properties": {
    "addr:full":"1 Orchard Ln Muse PA 15340",
    "addr:housenumber":"1",
    "addr:postcode":"15340",
    "addr:street":"Orchard Ln",
    "iso:country":"US",
    "sg:address":"1 Orchard Ln",
    "sg:city":"Muse",
    "sg:classifiers":[
        {
            "category":"Organizations",
            "subcategory":"Religious Organization",
            "type":"Services"
        }
    ],
    "sg:phone":"+1 724 745 3531",
    "sg:postcode":"15340",
    "sg:province":"PA",
    "sg:tags":[
        "church"
    ],
    "wof:name":"Holy Rosary Church",
    "wof:placetype":"venue"
},
  "geometry": {"coordinates":[-80.314279,40.300259],"type":"Point"}
}