{
  "type": "Feature",
  "properties": {
    "iso:country":"US",
    "sg:address":"568 Galiffa Dr",
    "sg:city":"Donora",
    "sg:classifiers":[
        {
            "category":"Social Services",
            "type":"Services"
        }
    ],
    "sg:phone":"+1 724 379 6115",
    "sg:postcode":"15033",
    "sg:province":"PA",
    "sg:tags":[
        "organization",
        "welfare"
    ],
    "wof:name":"Area Agency On Aging",
    "wof:placetype":"venue"
},
  "geometry": {"coordinates":[-79.857958,40.170425],"type":"Point"}
}