{
  "type": "Feature",
  "properties": {
    "addr:full":"53 E Earlham St Philadelphia PA 19144",
    "addr:housenumber":"53",
    "addr:postcode":"19144",
    "addr:street":"E Earlham St",
    "iso:country":"US",
    "sg:address":"53 E Earlham St",
    "sg:city":"Philadelphia",
    "sg:classifiers":[
        {
            "category":"Building & Trades",
            "subcategory":"Construction",
            "type":"Services"
        }
    ],
    "sg:phone":"+1   ",
    "sg:postcode":"19144",
    "sg:province":"PA",
    "sg:tags":[
        "contractor"
    ],
    "wof:name":"Germantown Contractors",
    "wof:placetype":"venue"
},
  "geometry": {"coordinates":[-75.169837,40.034818],"type":"Point"}
}