{
  "type": "Feature",
  "properties": {
    "addr:full":"2185 Macdade Blvd Holmes PA 19043",
    "addr:housenumber":"2185",
    "addr:postcode":"19043",
    "addr:street":"Macdade Blvd",
    "iso:country":"US",
    "sg:address":"2185 Macdade Blvd",
    "sg:city":"Holmes",
    "sg:classifiers":[
        {
            "category":"Government",
            "subcategory":"Office",
            "type":"Public Place"
        }
    ],
    "sg:phone":"+1   ",
    "sg:postcode":"19043",
    "sg:province":"PA",
    "sg:tags":[
        "national",
        "security"
    ],
    "wof:name":"United States Marine Corps",
    "wof:placetype":"venue"
},
  "geometry": {"coordinates":[-75.310541,39.897574],"type":"Point"}
}