{
  "type": "Feature",
  "properties": {
    "iso:country":"US",
    "sg:address":"404 Middletown Blvd",
    "sg:city":"Langhorne",
    "sg:classifiers":[
        {
            "category":"Health Services",
            "subcategory":"Doctor",
            "type":"Services"
        }
    ],
    "sg:phone":"+1   ",
    "sg:postcode":"19047",
    "sg:province":"PA",
    "sg:tags":[
        "osteopathic"
    ],
    "wof:name":"Richard L Turner Do",
    "wof:placetype":"venue"
},
  "geometry": {"coordinates":[-74.880878,40.186635],"type":"Point"}
}