{
  "type": "Feature",
  "properties": {
    "iso:country":"US",
    "sg:address":"3407 N 2nd St",
    "sg:city":"Philadelphia",
    "sg:classifiers":[
        {
            "category":"Organizations",
            "subcategory":"Religious Organization",
            "type":"Services"
        }
    ],
    "sg:phone":"+1 215 423 5998",
    "sg:postcode":"19140",
    "sg:province":"PA",
    "sg:tags":[
        "clergy"
    ],
    "wof:name":"Wesley Howell",
    "wof:placetype":"venue"
},
  "geometry": {"coordinates":[-75.132195,40.003527],"type":"Point"}
}