{
  "type": "Feature",
  "properties": {
    "iso:country":"US",
    "sg:address":"107 Cherry Run Rd",
    "sg:city":"Homer City",
    "sg:classifiers":[
        {
            "category":"Retail",
            "subcategory":"Portrait Studio",
            "type":"Services"
        }
    ],
    "sg:phone":"+1 724 479 3632",
    "sg:postcode":"15748",
    "sg:province":"PA",
    "sg:tags":[
        "photographer"
    ],
    "wof:name":"Steve L Skuff Photography",
    "wof:placetype":"venue"
},
  "geometry": {"coordinates":[-79.17425299999999,40.537742],"type":"Point"}
}