{
  "type": "Feature",
  "properties": {
    "iso:country":"US",
    "sg:address":"142 Buss Rd",
    "sg:city":"Aliquippa",
    "sg:classifiers":[
        {
            "category":"Building & Trades",
            "subcategory":"Construction",
            "type":"Services"
        }
    ],
    "sg:phone":"+1   ",
    "sg:postcode":"15001",
    "sg:province":"PA",
    "sg:tags":[
        "plumbing",
        "demolition",
        "wiring",
        "contractor"
    ],
    "wof:name":"Bologna Contracting",
    "wof:placetype":"venue"
},
  "geometry": {"coordinates":[-80.27231399999999,40.568539],"type":"Point"}
}