{
  "type": "Feature",
  "properties": {
    "addr:full":"1825 S 12th St Allentown PA 18103",
    "addr:housenumber":"1825",
    "addr:postcode":"18103",
    "addr:street":"S 12Th St",
    "iso:country":"US",
    "sg:address":"1825 S 12th St",
    "sg:city":"Allentown",
    "sg:classifiers":[
        {
            "category":"Wholesale",
            "subcategory":"Hardware",
            "type":"Manufacturing & Wholesale Goods"
        }
    ],
    "sg:phone":"+1 610 289 2660",
    "sg:postcode":"18103",
    "sg:province":"PA",
    "sg:tags":[
        "purifying",
        "cleaning",
        "air"
    ],
    "sg:website":"www.hepafilters.com",
    "wof:name":"Cleanroom Filters & Supls",
    "wof:placetype":"venue"
},
  "geometry": {"coordinates":[-75.476545,40.579329],"type":"Point"}
}