{
  "type": "Feature",
  "properties": {
    "addr:full":"127 E 14th St Erie PA 16503",
    "addr:housenumber":"127",
    "addr:postcode":"16503",
    "addr:street":"E 14Th St",
    "iso:country":"US",
    "sg:address":"127 E 14th St",
    "sg:city":"Erie",
    "sg:classifiers":[
        {
            "category":"Banks & Credit Unions",
            "subcategory":"Bank",
            "type":"Services"
        }
    ],
    "sg:phone":"+1 814 455 5150",
    "sg:postcode":"16503",
    "sg:province":"PA",
    "wof:name":"Emta Federal Credit Union",
    "wof:placetype":"venue"
},
  "geometry": {"coordinates":[-80.077983,42.122414],"type":"Point"}
}