{
  "type": "Feature",
  "properties": {
    "iso:country":"US",
    "sg:address":"2 N Main St",
    "sg:city":"Coopersburg",
    "sg:classifiers":[
        {
            "category":"Real Estate",
            "subcategory":"Real Estate Services",
            "type":"Services"
        }
    ],
    "sg:phone":"+1 610 282 4444",
    "sg:postcode":"18036",
    "sg:province":"PA",
    "wof:name":"Patt-White GMAC Real Estate",
    "wof:placetype":"venue"
},
  "geometry": {"coordinates":[-75.39070100000001,40.511398],"type":"Point"}
}