{
  "type": "Feature",
  "properties": {
    "iso:country":"US",
    "sg:address":"1312 Sutton Rd",
    "sg:city":"Shavertown",
    "sg:classifiers":[
        {
            "category":"Real Estate",
            "subcategory":"Real Estate Operator",
            "type":"Services"
        }
    ],
    "sg:phone":"+1   ",
    "sg:postcode":"18708",
    "sg:province":"PA",
    "sg:tags":[
        "building",
        "nonresidential"
    ],
    "wof:name":"Whitfield Properties",
    "wof:placetype":"venue"
},
  "geometry": {"coordinates":[-75.957106,41.304977],"type":"Point"}
}