{
  "type": "Feature",
  "properties": {
    "iso:country":"US",
    "sg:address":"1170 Hunter Rd",
    "sg:city":"Verona",
    "sg:classifiers":[
        {
            "category":"Wholesale",
            "subcategory":"Electrical",
            "type":"Manufacturing & Wholesale Goods"
        }
    ],
    "sg:phone":"+1 412 795 2207",
    "sg:postcode":"15147",
    "sg:province":"PA",
    "sg:tags":[
        "equipment",
        "lighting"
    ],
    "wof:name":"Platt Lighting",
    "wof:placetype":"venue"
},
  "geometry": {"coordinates":[-79.812352,40.504206],"type":"Point"}
}