{
  "type": "Feature",
  "properties": {
    "addr:full":"525 E Broad St Hazleton PA 18201",
    "addr:housenumber":"525",
    "addr:postcode":"18201",
    "addr:street":"E Broad St",
    "iso:country":"US",
    "sg:address":"525 E Broad St",
    "sg:city":"Hazleton",
    "sg:classifiers":[
        {
            "category":"Government",
            "subcategory":"Fire Station",
            "type":"Public Place"
        }
    ],
    "sg:phone":"+1   ",
    "sg:postcode":"18201",
    "sg:province":"PA",
    "sg:tags":[
        "protection"
    ],
    "wof:name":"Fire Department",
    "wof:placetype":"venue"
},
  "geometry": {"coordinates":[-75.965019,40.951326],"type":"Point"}
}