{
  "type": "Feature",
  "properties": {
    "iso:country":"US",
    "sg:address":"401 N 5th St",
    "sg:city":"Stroudsburg",
    "sg:classifiers":[
        {
            "category":"Retail",
            "subcategory":"Funeral Services",
            "type":"Services"
        }
    ],
    "sg:phone":"+1 570 421 2999",
    "sg:postcode":"18360",
    "sg:province":"PA",
    "wof:name":"Thomas Funeral Home",
    "wof:placetype":"venue"
},
  "geometry": {"coordinates":[-75.192711,40.992747],"type":"Point"}
}