{
  "type": "Feature",
  "properties": {
    "addr:full":"6735 Cetronia Rd Allentown PA 18106",
    "addr:housenumber":"6735",
    "addr:postcode":"18106",
    "addr:street":"Cetronia Rd",
    "iso:country":"US",
    "sg:address":"6735 Cetronia Rd",
    "sg:city":"Allentown",
    "sg:classifiers":[
        {
            "category":"Social Services",
            "type":"Services"
        }
    ],
    "sg:phone":"+1   ",
    "sg:postcode":"18106",
    "sg:province":"PA",
    "sg:tags":[
        "organization",
        "religious"
    ],
    "wof:name":"Trinity Wesleyan Church",
    "wof:placetype":"venue"
},
  "geometry": {"coordinates":[-75.589141,40.563284],"type":"Point"}
}