{
  "type": "Feature",
  "properties": {
    "iso:country":"US",
    "sg:address":"4320 Perkiomen Ave",
    "sg:city":"Reading",
    "sg:classifiers":[
        {
            "category":"Personal",
            "subcategory":"Beauty Salon",
            "type":"Services"
        }
    ],
    "sg:phone":"+1   ",
    "sg:postcode":"19606",
    "sg:province":"PA",
    "sg:tags":[
        "shop"
    ],
    "wof:name":"Outlooks For Hair",
    "wof:placetype":"venue"
},
  "geometry": {"coordinates":[-75.863851,40.308093],"type":"Point"}
}