{
  "type": "Feature",
  "properties": {
    "iso:country":"US",
    "sg:address":"1457 Roselawn Dr",
    "sg:city":"Bethlehem",
    "sg:classifiers":[
        {
            "category":"Shopping",
            "type":"Retail Goods"
        }
    ],
    "sg:phone":"+1   ",
    "sg:postcode":"18017",
    "sg:province":"PA",
    "sg:tags":[
        "optical",
        "merchandise"
    ],
    "wof:name":"Visual World",
    "wof:placetype":"venue"
},
  "geometry": {"coordinates":[-75.40450199999999,40.645268],"type":"Point"}
}