{
  "type": "Feature",
  "properties": {
    "iso:country":"US",
    "sg:address":"4883 Hamilton Blvd",
    "sg:city":"Allentown",
    "sg:classifiers":[
        {
            "category":"Retail",
            "subcategory":"Repair Shop",
            "type":"Services"
        }
    ],
    "sg:phone":"+1 610 395 7196",
    "sg:postcode":"18106",
    "sg:province":"PA",
    "sg:tags":[
        "upholsterer"
    ],
    "wof:name":"Ritters Reupholstery & Repairs",
    "wof:placetype":"venue"
},
  "geometry": {"coordinates":[-75.552556,40.566827],"type":"Point"}
}