{
  "type": "Feature",
  "properties": {
    "iso:country":"US",
    "sg:address":"1500 Market Street",
    "sg:city":"Philadelphia",
    "sg:classifiers":[
        {
            "category":"Restaurant",
            "type":"Food & Drink"
        }
    ],
    "sg:phone":"+1 215 568 0809",
    "sg:postcode":"19102",
    "sg:province":"PA",
    "wof:name":"Raindrop Cafe",
    "wof:placetype":"venue"
},
  "geometry": {"coordinates":[-75.16619300000001,39.952393],"type":"Point"}
}