{
  "type": "Feature",
  "properties": {
    "iso:country":"US",
    "sg:address":"1432 S 56th St",
    "sg:city":"Philadelphia",
    "sg:classifiers":[
        {
            "category":"Health Services",
            "subcategory":"Hospital",
            "type":"Services"
        }
    ],
    "sg:phone":"+1 267 455 1498",
    "sg:postcode":"19143",
    "sg:province":"PA",
    "wof:name":"N Route 2 U",
    "wof:placetype":"venue"
},
  "geometry": {"coordinates":[-75.228655,39.940327],"type":"Point"}
}