{
  "type": "Feature",
  "properties": {
    "addr:full":"16738 Mercer Rd Townville PA 16360",
    "addr:housenumber":"16738",
    "addr:postcode":"16360",
    "addr:street":"Mercer Rd",
    "iso:country":"US",
    "sg:address":"16738 Mercer Rd",
    "sg:city":"Townville",
    "sg:classifiers":[
        {
            "category":"Manufacturing",
            "subcategory":"Tools & Machinery",
            "type":"Manufacturing & Wholesale Goods"
        }
    ],
    "sg:phone":"+1 814 967 5247",
    "sg:postcode":"16360",
    "sg:province":"PA",
    "sg:tags":[
        "die",
        "maker",
        "mfg"
    ],
    "wof:name":"Rumzie Tool",
    "wof:placetype":"venue"
},
  "geometry": {"coordinates":[-79.901529,41.700081],"type":"Point"}
}