{
  "type": "Feature",
  "properties": {
    "iso:country":"US",
    "sg:address":"2800 Easton Ave",
    "sg:city":"Bethlehem",
    "sg:classifiers":[
        {
            "category":"Food & Beverages",
            "subcategory":"Groceries & Convenience Stores",
            "type":"Retail Goods"
        },
        {
            "category":"Food & Beverages",
            "subcategory":"Liquor & Beverages",
            "type":"Retail Goods"
        },
        {
            "category":"Wholesale",
            "subcategory":"Beer",
            "type":"Manufacturing & Wholesale Goods"
        },
        {
            "category":"Ice Cream",
            "type":"Food & Drink"
        },
        {
            "category":"Wholesale",
            "subcategory":"Wine & Distilled Alcoholic Beverages",
            "type":"Manufacturing & Wholesale Goods"
        }
    ],
    "sg:phone":"+1 610 866 7722",
    "sg:postcode":"18017",
    "sg:province":"PA",
    "sg:tags":[
        "ale",
        "broker",
        "ale-wholesale",
        "manufacturer"
    ],
    "sg:website":"http://www.pavlishbev.com",
    "wof:name":"Pavlish Ice Co",
    "wof:placetype":"venue"
},
  "geometry": {"coordinates":[-75.343086,40.64642],"type":"Point"}
}