{
  "type": "Feature",
  "properties": {
    "addr:full":"19 Silver Maple Dr Boiling Springs PA 17007",
    "addr:housenumber":"19",
    "addr:postcode":"17007",
    "addr:street":"Silver Maple Dr",
    "iso:country":"US",
    "sg:address":"19 Silver Maple Dr",
    "sg:city":"Boiling Springs",
    "sg:classifiers":[
        {
            "category":"Real Estate",
            "subcategory":"Real Estate Agent",
            "type":"Services"
        }
    ],
    "sg:phone":"+1 717 243 2739",
    "sg:postcode":"17007",
    "sg:province":"PA",
    "sg:tags":[
        "appraiser"
    ],
    "wof:name":"Apex Appraisals",
    "wof:placetype":"venue"
},
  "geometry": {"coordinates":[-77.14578,40.159728],"type":"Point"}
}