{
  "type": "Feature",
  "properties": {
    "addr:full":"14834 Old Wattsburg Rd Union City PA 16438",
    "addr:housenumber":"14834",
    "addr:postcode":"16438",
    "addr:street":"Old Wattsburg Rd",
    "iso:country":"US",
    "sg:address":"14834 Old Wattsburg Rd",
    "sg:city":"Union City",
    "sg:classifiers":[
        {
            "category":"Professional",
            "subcategory":"Management & Consulting",
            "type":"Services"
        }
    ],
    "sg:phone":"+1   ",
    "sg:postcode":"16438",
    "sg:province":"PA",
    "wof:name":"Sideco Assoc",
    "wof:placetype":"venue"
},
  "geometry": {"coordinates":[-79.816126,41.978544],"type":"Point"}
}