{
  "type": "Feature",
  "properties": {
    "iso:country":"US",
    "sg:address":"725 Scalp Ave",
    "sg:city":"Johnstown",
    "sg:classifiers":[
        {
            "category":"Restaurant",
            "type":"Food & Drink"
        }
    ],
    "sg:phone":"+1   ",
    "sg:postcode":"15904",
    "sg:province":"PA",
    "sg:tags":[
        "drinking",
        "eating"
    ],
    "wof:name":"Anthonys Restaurant",
    "wof:placetype":"venue"
},
  "geometry": {"coordinates":[-78.86793900000001,40.289975],"type":"Point"}
}