{
  "type": "Feature",
  "properties": {
    "iso:country":"US",
    "sg:address":"5041 N Main St",
    "sg:city":"Mc Kean",
    "sg:classifiers":[
        {
            "category":"Organizations",
            "subcategory":"Religious Organization",
            "type":"Services"
        }
    ],
    "sg:phone":"+1 814 476 7538",
    "sg:postcode":"16426",
    "sg:province":"PA",
    "sg:tags":[
        "church"
    ],
    "wof:name":"Mc KEAN United Methodist Chr",
    "wof:placetype":"venue"
},
  "geometry": {"coordinates":[-80.135777,42.003471],"type":"Point"}
}