{
  "type": "Feature",
  "properties": {
    "iso:country":"US",
    "sg:address":"233 W Pittsburgh St",
    "sg:city":"Greensburg",
    "sg:classifiers":[
        {
            "category":"Insurance",
            "subcategory":"Insurance Agent",
            "type":"Services"
        }
    ],
    "sg:phone":"+1 724 836 1904",
    "sg:postcode":"15601",
    "sg:province":"PA",
    "wof:name":"Laurel Highlands Benefits",
    "wof:placetype":"venue"
},
  "geometry": {"coordinates":[-79.548362,40.30169],"type":"Point"}
}