{
  "type": "Feature",
  "properties": {
    "iso:country":"US",
    "sg:address":"7414 Trevanion Ave",
    "sg:city":"Pittsburgh",
    "sg:classifiers":[
        {
            "category":"Professional",
            "subcategory":"Computer Services",
            "type":"Services"
        }
    ],
    "sg:phone":"+1   ",
    "sg:postcode":"15218",
    "sg:province":"PA",
    "sg:tags":[
        "datum",
        "research"
    ],
    "wof:name":"Madden Research",
    "wof:placetype":"venue"
},
  "geometry": {"coordinates":[-79.895161,40.428503],"type":"Point"}
}