{
  "type": "Feature",
  "properties": {
    "iso:country":"US",
    "sg:address":"4952 Hoopes St",
    "sg:city":"Philadelphia",
    "sg:classifiers":[
        {
            "category":"Social Services",
            "type":"Services"
        }
    ],
    "sg:phone":"+1 215 425 5621",
    "sg:postcode":"19139",
    "sg:province":"PA",
    "sg:tags":[
        "shelter",
        "homeless"
    ],
    "wof:name":"Orchaids For Life",
    "wof:placetype":"venue"
},
  "geometry": {"coordinates":[-75.219718,39.96814],"type":"Point"}
}