{
  "type": "Feature",
  "properties": {
    "iso:country":"US",
    "sg:address":"1801 Mill Rd",
    "sg:city":"Hilltown",
    "sg:classifiers":[
        {
            "category":"Recreation",
            "type":"Entertainment"
        }
    ],
    "sg:phone":"+1 215 822 9899",
    "sg:postcode":"18944",
    "sg:province":"PA",
    "sg:tags":[
        "stable"
    ],
    "wof:name":"Windy Willow Farm Inc",
    "wof:placetype":"venue"
},
  "geometry": {"coordinates":[-75.242553,40.328638],"type":"Point"}
}