{
  "type": "Feature",
  "properties": {
    "iso:country":"US",
    "sg:address":"521 W Uwchlan Ave",
    "sg:city":"Downingtown",
    "sg:classifiers":[
        {
            "category":"Wholesale",
            "subcategory":"Computers",
            "type":"Manufacturing & Wholesale Goods"
        }
    ],
    "sg:phone":"+1 610 594 6270",
    "sg:postcode":"19335",
    "sg:province":"PA",
    "sg:tags":[
        "equipment"
    ],
    "sg:website":"http://pcdirect.net",
    "wof:name":"Pc Direct",
    "wof:placetype":"venue"
},
  "geometry": {"coordinates":[-75.665802,40.04171],"type":"Point"}
}