{
  "type": "Feature",
  "properties": {
    "iso:country":"US",
    "sg:address":"2370 Conestoga Creek Rd",
    "sg:city":"Narvon",
    "sg:classifiers":[
        {
            "category":"Manufacturing",
            "subcategory":"Tools & Machinery",
            "type":"Manufacturing & Wholesale Goods"
        }
    ],
    "sg:phone":"+1   ",
    "sg:postcode":"17555",
    "sg:province":"PA",
    "sg:tags":[
        "industrial"
    ],
    "wof:name":"Stauffer Edward Mch Wldg Sp",
    "wof:placetype":"venue"
},
  "geometry": {"coordinates":[-75.934575,40.132393],"type":"Point"}
}