{
  "type": "Feature",
  "properties": {
    "iso:country":"US",
    "sg:address":"500 Hansen Ave",
    "sg:city":"Lyndora",
    "sg:classifiers":[
        {
            "category":"Food & Beverages",
            "subcategory":"Liquor & Beverages",
            "type":"Retail Goods"
        },
        {
            "category":"Wholesale",
            "subcategory":"Wine & Distilled Alcoholic Beverages",
            "type":"Manufacturing & Wholesale Goods"
        }
    ],
    "sg:phone":"+1 724 287 5020",
    "sg:postcode":"16045",
    "sg:province":"PA",
    "sg:tags":[
        "liquors-wholesale",
        "beer",
        "ale"
    ],
    "wof:name":"Lyndora Beverage Co",
    "wof:placetype":"venue"
},
  "geometry": {"coordinates":[-79.91114,40.85791],"type":"Point"}
}