{
  "type": "Feature",
  "properties": {
    "addr:full":"111 Council St Wheatland PA 16161",
    "addr:housenumber":"111",
    "addr:postcode":"16161",
    "addr:street":"Council St",
    "iso:country":"US",
    "sg:address":"111 Council St",
    "sg:city":"Wheatland",
    "sg:classifiers":[
        {
            "category":"Government",
            "subcategory":"Post Office",
            "type":"Public Place"
        }
    ],
    "sg:phone":"+1 724 346 4501",
    "sg:postcode":"16161",
    "sg:province":"PA",
    "wof:name":"US Post Office",
    "wof:placetype":"venue"
},
  "geometry": {"coordinates":[-80.492418,41.200213],"type":"Point"}
}