{
  "type": "Feature",
  "properties": {
    "addr:full":"7360 Castor Ave Philadelphia PA 19152",
    "addr:housenumber":"7360",
    "addr:postcode":"19152",
    "addr:street":"Castor Ave",
    "iso:country":"US",
    "sg:address":"7360 Castor Ave",
    "sg:city":"Philadelphia",
    "sg:classifiers":[
        {
            "category":"Home & Garden",
            "subcategory":"Carpets & Floor Coverings",
            "type":"Retail Goods"
        }
    ],
    "sg:phone":"+1   ",
    "sg:postcode":"19152",
    "sg:province":"PA",
    "wof:name":"Ten Henry Carpets",
    "wof:placetype":"venue"
},
  "geometry": {"coordinates":[-75.065202,40.051951],"type":"Point"}
}