{
  "type": "Feature",
  "properties": {
    "iso:country":"US",
    "sg:address":"622 Church St",
    "sg:city":"Kingston",
    "sg:classifiers":[
        {
            "category":"Manufacturing",
            "subcategory":"Printing",
            "type":"Manufacturing & Wholesale Goods"
        }
    ],
    "sg:phone":"+1   ",
    "sg:postcode":"18704",
    "sg:province":"PA",
    "sg:tags":[
        "magazine",
        "publishing",
        "real estate"
    ],
    "wof:name":"Homebuyer Magazine",
    "wof:placetype":"venue"
},
  "geometry": {"coordinates":[-75.879229,41.291034],"type":"Point"}
}