{
  "type": "Feature",
  "properties": {
    "iso:country":"US",
    "sg:address":"1008 Upper Gulph Rd",
    "sg:city":"Wayne",
    "sg:classifiers":[
        {
            "category":"Real Estate",
            "subcategory":"Real Estate Agent",
            "type":"Services"
        }
    ],
    "sg:phone":"+1 610 975 0300",
    "sg:postcode":"19087",
    "sg:province":"PA",
    "sg:tags":[
        "management"
    ],
    "wof:name":"Strategic Realty Investments",
    "wof:placetype":"venue"
},
  "geometry": {"coordinates":[-75.384671,40.060129],"type":"Point"}
}