{
  "type": "Feature",
  "properties": {
    "iso:country":"US",
    "sg:address":"911 Fruitville Pike",
    "sg:city":"Lititz",
    "sg:classifiers":[
        {
            "category":"Building & Trades",
            "subcategory":"Construction",
            "type":"Services"
        }
    ],
    "sg:phone":"+1 717 627 7227",
    "sg:postcode":"17543",
    "sg:province":"PA",
    "sg:tags":[
        "contractor"
    ],
    "wof:name":"Zeiset & Martin Construction",
    "wof:placetype":"venue"
},
  "geometry": {"coordinates":[-76.345316,40.129903],"type":"Point"}
}