{
  "type": "Feature",
  "properties": {
    "iso:country":"US",
    "sg:address":"9 Logan Blvd",
    "sg:city":"Altoona",
    "sg:classifiers":[
        {
            "category":"Real Estate",
            "subcategory":"Architect",
            "type":"Services"
        }
    ],
    "sg:phone":"+1 814 944 4664",
    "sg:postcode":"16602",
    "sg:province":"PA",
    "wof:name":"David B Albright",
    "wof:placetype":"venue"
},
  "geometry": {"coordinates":[-78.40884699999999,40.487744],"type":"Point"}
}