{
  "type": "Feature",
  "properties": {
    "iso:country":"US",
    "sg:address":"5973 Old State Rd",
    "sg:city":"Edinboro",
    "sg:classifiers":[
        {
            "category":"Real Estate",
            "subcategory":"Real Estate Agent",
            "type":"Services"
        }
    ],
    "sg:phone":"+1 814 734 9004",
    "sg:postcode":"16412",
    "sg:province":"PA",
    "sg:tags":[
        "inspection"
    ],
    "wof:name":"Michael's Home Inspection",
    "wof:placetype":"venue"
},
  "geometry": {"coordinates":[-80.166147,41.934505],"type":"Point"}
}