{
  "type": "Feature",
  "properties": {
    "addr:full":"617 Wendy Cir Berwyn PA 19312",
    "addr:housenumber":"617",
    "addr:postcode":"19312",
    "addr:street":"Wendy Cir",
    "iso:country":"US",
    "sg:address":"617 Wendy Cir",
    "sg:city":"Berwyn",
    "sg:classifiers":[
        {
            "category":"Professional",
            "subcategory":"Business Services",
            "type":"Services"
        }
    ],
    "sg:phone":"+1   ",
    "sg:postcode":"19312",
    "sg:province":"PA",
    "wof:name":"Pat Smith Design Associates",
    "wof:placetype":"venue"
},
  "geometry": {"coordinates":[-75.45902100000001,40.056686],"type":"Point"}
}