{
  "type": "Feature",
  "properties": {
    "addr:full":"4536 Perrysville Ave Pittsburgh PA 15229",
    "addr:housenumber":"4536",
    "addr:postcode":"15229",
    "addr:street":"Perrysville Ave",
    "iso:country":"US",
    "sg:address":"4536 Perrysville Ave",
    "sg:city":"Pittsburgh",
    "sg:classifiers":[
        {
            "category":"Health Services",
            "subcategory":"Nursing And Care Facility",
            "type":"Services"
        }
    ],
    "sg:phone":"+1   ",
    "sg:postcode":"15229",
    "sg:province":"PA",
    "wof:name":"Mercy Behavioral Health",
    "wof:placetype":"venue"
},
  "geometry": {"coordinates":[-80.021472,40.499881],"type":"Point"}
}