{
  "type": "Feature",
  "properties": {
    "iso:country":"US",
    "sg:address":"1635 Main St",
    "sg:city":"Pittsburgh",
    "sg:classifiers":[
        {
            "category":"Manufacturing",
            "subcategory":"Rubber & Plastics",
            "type":"Manufacturing & Wholesale Goods"
        },
        {
            "category":"Autos & Motor Vehicles",
            "subcategory":"Auto Supplies",
            "type":"Retail Goods"
        },
        {
            "category":"Retail",
            "subcategory":"Auto Repair",
            "type":"Services"
        }
    ],
    "sg:phone":"+1 610 489 4050",
    "sg:postcode":"15215",
    "sg:province":"PA",
    "sg:tags":[
        "recap",
        "retread",
        "tires-wholesale",
        "tire",
        "manufacturer"
    ],
    "sg:website":"http://www.coopertire.com/html/",
    "wof:name":"Wynne's Express Lube",
    "wof:placetype":"venue"
},
  "geometry": {"coordinates":[-79.924504,40.494748],"type":"Point"}
}