{
  "type": "Feature",
  "properties": {
    "iso:country":"US",
    "sg:address":"2058 Sproul Rd",
    "sg:city":"Broomall",
    "sg:classifiers":[
        {
            "category":"Food & Beverages",
            "subcategory":"Bakery",
            "type":"Retail Goods"
        }
    ],
    "sg:phone":"+1 610 356 0553",
    "sg:postcode":"19008",
    "sg:province":"PA",
    "sg:tags":[
        "baker"
    ],
    "wof:name":"Pepperidge Farm Inc",
    "wof:placetype":"venue"
},
  "geometry": {"coordinates":[-75.359461,39.967034],"type":"Point"}
}