{
  "type": "Feature",
  "properties": {
    "iso:country":"US",
    "sg:address":"168 Leister Rd",
    "sg:city":"Fairhope",
    "sg:classifiers":[
        {
            "category":"Farming",
            "subcategory":"Farm",
            "type":"Manufacturing & Wholesale Goods"
        }
    ],
    "sg:phone":"+1   ",
    "sg:postcode":"15538",
    "sg:province":"PA",
    "sg:tags":[
        "crop",
        "general"
    ],
    "wof:name":"Hillside Farm",
    "wof:placetype":"venue"
},
  "geometry": {"coordinates":[-78.85479599999999,39.878353],"type":"Point"}
}