{
  "type": "Feature",
  "properties": {
    "addr:full":"4 E Main St Hummelstown PA 17036",
    "addr:housenumber":"4",
    "addr:postcode":"17036",
    "addr:street":"E Main St",
    "iso:country":"US",
    "sg:address":"4 E Main St",
    "sg:city":"Hummelstown",
    "sg:classifiers":[
        {
            "category":"Home & Garden",
            "subcategory":"Furniture",
            "type":"Retail Goods"
        }
    ],
    "sg:phone":"+1   ",
    "sg:postcode":"17036",
    "sg:province":"PA",
    "sg:tags":[
        "household"
    ],
    "wof:name":"Bowser Furniture Store Inc",
    "wof:placetype":"venue"
},
  "geometry": {"coordinates":[-76.70696599999999,40.265434],"type":"Point"}
}