{
  "type": "Feature",
  "properties": {
    "iso:country":"US",
    "sg:address":"1798 Broadway",
    "sg:city":"Bethlehem",
    "sg:classifiers":[
        {
            "category":"Education",
            "subcategory":"Dance Studio",
            "type":"Public Place"
        }
    ],
    "sg:phone":"+1 610 814 6000",
    "sg:postcode":"18015",
    "sg:province":"PA",
    "sg:tags":[
        "party",
        "planning",
        "instruction",
        "event",
        "dancing"
    ],
    "sg:website":"www.dynamixdance.com",
    "wof:name":"Dynamix Dance Center",
    "wof:placetype":"venue"
},
  "geometry": {"coordinates":[-75.411174,40.595143],"type":"Point"}
}