{
  "type": "Feature",
  "properties": {
    "iso:country":"US",
    "sg:address":"244 Main St",
    "sg:city":"Blossburg",
    "sg:classifiers":[
        {
            "category":"Social Services",
            "subcategory":"Child Care",
            "type":"Services"
        }
    ],
    "sg:phone":"+1 570 638 3459",
    "sg:postcode":"16912",
    "sg:province":"PA",
    "wof:name":"Toddler University Daycare",
    "wof:placetype":"venue"
},
  "geometry": {"coordinates":[-77.064987,41.679565],"type":"Point"}
}