{
  "type": "Feature",
  "properties": {
    "iso:country":"US",
    "sg:address":"106 Hawthorne St",
    "sg:city":"Hollidaysburg",
    "sg:classifiers":[
        {
            "category":"Professional",
            "subcategory":"Employment Agencies",
            "type":"Services"
        },
        {
            "category":"Professional",
            "subcategory":"Lawyer & Legal Services",
            "type":"Services"
        }
    ],
    "sg:phone":"+1 814 946 0998",
    "sg:postcode":"16648",
    "sg:province":"PA",
    "sg:tags":[
        "convention",
        "secretarial",
        "reporters-court"
    ],
    "wof:name":"Bonnie Botteicher",
    "wof:placetype":"venue"
},
  "geometry": {"coordinates":[-78.394104,40.45355],"type":"Point"}
}