{
  "type": "Feature",
  "properties": {
    "iso:country":"US",
    "sg:address":"10 Oak Tree Rd",
    "sg:city":"Manheim",
    "sg:classifiers":[
        {
            "category":"Wholesale",
            "subcategory":"Hardware",
            "type":"Manufacturing & Wholesale Goods"
        }
    ],
    "sg:phone":"+1 717 354 6048",
    "sg:postcode":"17545",
    "sg:province":"PA",
    "sg:tags":[
        "mobile",
        "recreational",
        "vehicle",
        "plumbing",
        "home",
        "campers-repair"
    ],
    "wof:name":"Young's Mobile Home Service",
    "wof:placetype":"venue"
},
  "geometry": {"coordinates":[-76.420168,40.197174],"type":"Point"}
}