{
  "type": "Feature",
  "properties": {
    "addr:full":"100 Greensburg St Delmont PA 15626",
    "addr:housenumber":"100",
    "addr:postcode":"15626",
    "addr:street":"Greensburg St",
    "iso:country":"US",
    "sg:address":"100 Greensburg St",
    "sg:city":"Delmont",
    "sg:classifiers":[
        {
            "category":"Health Services",
            "subcategory":"Podiatrist",
            "type":"Services"
        }
    ],
    "sg:phone":"+1 724 468 5368",
    "sg:postcode":"15626",
    "sg:province":"PA",
    "wof:name":"Academy Of Podiatry",
    "wof:placetype":"venue"
},
  "geometry": {"coordinates":[-79.57253799999999,40.410285],"type":"Point"}
}