{
  "type": "Feature",
  "properties": {
    "addr:full":"2268 New Holland Pike Lancaster PA 17601",
    "addr:housenumber":"2268",
    "addr:postcode":"17601",
    "addr:street":"New Holland Pike",
    "iso:country":"US",
    "sg:address":"2268 New Holland Pike",
    "sg:city":"Lancaster",
    "sg:classifiers":[
        {
            "category":"Personal",
            "type":"Services"
        }
    ],
    "sg:phone":"+1 717 661 7474",
    "sg:postcode":"17601",
    "sg:province":"PA",
    "sg:tags":[
        "program",
        "physical",
        "exercise",
        "fitness"
    ],
    "wof:name":"Curves For Women",
    "wof:placetype":"venue"
},
  "geometry": {"coordinates":[-76.236892,40.081354],"type":"Point"}
}