{
  "type": "Feature",
  "properties": {
    "iso:country":"US",
    "sg:address":"60 Mountain Ave",
    "sg:city":"Nanticoke",
    "sg:classifiers":[
        {
            "category":"Wholesale",
            "subcategory":"Electrical",
            "type":"Manufacturing & Wholesale Goods"
        }
    ],
    "sg:phone":"+1 570 735 5924",
    "sg:postcode":"18634",
    "sg:province":"PA",
    "sg:tags":[
        "lighting"
    ],
    "wof:name":"Phair Theatre & Stage Supply",
    "wof:placetype":"venue"
},
  "geometry": {"coordinates":[-76.008064,41.220971],"type":"Point"}
}