{
  "type": "Feature",
  "properties": {
    "iso:country":"US",
    "sg:address":"1464 E Queen St",
    "sg:city":"Annville",
    "sg:classifiers":[
        {
            "category":"Organizations",
            "subcategory":"Community Association",
            "type":"Services"
        }
    ],
    "sg:phone":"+1   ",
    "sg:postcode":"17003",
    "sg:province":"PA",
    "wof:name":"Arthur King Scouts Inc",
    "wof:placetype":"venue"
},
  "geometry": {"coordinates":[-76.48792400000001,40.33392],"type":"Point"}
}