{
  "type": "Feature",
  "properties": {
    "iso:country":"US",
    "sg:address":"321 Unity Center Rd",
    "sg:city":"Pittsburgh",
    "sg:classifiers":[
        {
            "category":"Shopping",
            "subcategory":"Gifts & Souvenirs",
            "type":"Retail Goods"
        }
    ],
    "sg:phone":"+1 412 795 2232",
    "sg:postcode":"15239",
    "sg:province":"PA",
    "wof:name":"Greeting Gallery",
    "wof:placetype":"venue"
},
  "geometry": {"coordinates":[-79.77493200000001,40.488955],"type":"Point"}
}