{
  "type": "Feature",
  "properties": {
    "addr:full":"3620 Millers Run Rd Mc Donald PA 15057",
    "addr:housenumber":"3620",
    "addr:postcode":"15057",
    "addr:street":"Millers Run Rd",
    "iso:country":"US",
    "sg:address":"3620 Millers Run Rd",
    "sg:city":"Mc Donald",
    "sg:classifiers":[
        {
            "category":"Building & Trades",
            "subcategory":"Construction",
            "type":"Services"
        }
    ],
    "sg:phone":"+1   ",
    "sg:postcode":"15057",
    "sg:province":"PA",
    "sg:tags":[
        "house"
    ],
    "wof:name":"Adamski Construction",
    "wof:placetype":"venue"
},
  "geometry": {"coordinates":[-80.221103,40.318186],"type":"Point"}
}