{
  "type": "Feature",
  "properties": {
    "iso:country":"US",
    "sg:address":"263 N Jefferson Ave",
    "sg:city":"Canonsburg",
    "sg:classifiers":[
        {
            "category":"Real Estate",
            "subcategory":"Real Estate Agent",
            "type":"Services"
        }
    ],
    "sg:phone":"+1   ",
    "sg:postcode":"15317",
    "sg:province":"PA",
    "wof:name":"Pheenix Realty Investment",
    "wof:placetype":"venue"
},
  "geometry": {"coordinates":[-80.189493,40.261815],"type":"Point"}
}