{
  "type": "Feature",
  "properties": {
    "iso:country":"US",
    "sg:address":"55 Germania St",
    "sg:city":"Galeton",
    "sg:classifiers":[
        {
            "category":"Insurance",
            "subcategory":"Insurance Agent",
            "type":"Services"
        }
    ],
    "sg:phone":"+1 814 435 6524",
    "sg:postcode":"16922",
    "sg:province":"PA",
    "wof:name":"William R Karschner & Sons",
    "wof:placetype":"venue"
},
  "geometry": {"coordinates":[-77.645954,41.732201],"type":"Point"}
}