{
  "type": "Feature",
  "properties": {
    "iso:country":"US",
    "sg:address":"1373 Manheim Pike # 4825",
    "sg:city":"Lancaster",
    "sg:classifiers":[
        {
            "category":"Retail",
            "subcategory":"Auto Repair",
            "type":"Services"
        }
    ],
    "sg:phone":"+1 717 299 2801",
    "sg:postcode":"17601",
    "sg:province":"PA",
    "sg:tags":[
        "automotive",
        "tune"
    ],
    "sg:website":"http://nitra.vwdealer.com/autohaus-lancaster/en_US",
    "wof:name":"Autohaus Lancaster Inc",
    "wof:placetype":"venue"
},
  "geometry": {"coordinates":[-76.330776,40.069171],"type":"Point"}
}