{
  "type": "Feature",
  "properties": {
    "addr:full":"409 Winfield Rd Cabot PA 16023",
    "addr:housenumber":"409",
    "addr:postcode":"16023",
    "addr:street":"Winfield Rd",
    "iso:country":"US",
    "sg:address":"409 Winfield Rd",
    "sg:city":"Cabot",
    "sg:classifiers":[
        {
            "category":"Freight",
            "type":"Transportation"
        }
    ],
    "sg:phone":"+1   ",
    "sg:postcode":"16023",
    "sg:province":"PA",
    "sg:tags":[
        "operator",
        "local",
        "trucking"
    ],
    "wof:name":"Denny S Delivery and Excav",
    "wof:placetype":"venue"
},
  "geometry": {"coordinates":[-79.772403,40.762933],"type":"Point"}
}