{
  "type": "Feature",
  "properties": {
    "addr:full":"213 Pembroke Rd Wallingford PA 19086",
    "addr:housenumber":"213",
    "addr:postcode":"19086",
    "addr:street":"Pembroke Rd",
    "iso:country":"US",
    "sg:address":"213 Pembroke Rd",
    "sg:city":"Wallingford",
    "sg:classifiers":[
        {
            "category":"Manufacturing",
            "subcategory":"Retail Goods",
            "type":"Manufacturing & Wholesale Goods"
        }
    ],
    "sg:phone":"+1   ",
    "sg:postcode":"19086",
    "sg:province":"PA",
    "sg:tags":[
        "product",
        "mfg"
    ],
    "wof:name":"P S Originals",
    "wof:placetype":"venue"
},
  "geometry": {"coordinates":[-75.367626,39.907423],"type":"Point"}
}