{
  "type": "Feature",
  "properties": {
    "addr:full":"223 Bridge St Homestead PA 15148",
    "addr:housenumber":"223",
    "addr:postcode":"15148",
    "addr:street":"Bridge St",
    "iso:country":"US",
    "sg:address":"223 Bridge St",
    "sg:city":"Homestead",
    "sg:classifiers":[
        {
            "category":"Shopping",
            "subcategory":"Clothing, Apparel, & Fashions",
            "type":"Retail Goods"
        }
    ],
    "sg:phone":"+1   ",
    "sg:postcode":"15148",
    "sg:province":"PA",
    "sg:tags":[
        "wear"
    ],
    "wof:name":"Childrens Place Ret Stores Inc",
    "wof:placetype":"venue"
},
  "geometry": {"coordinates":[-79.79787399999999,40.39379],"type":"Point"}
}