{
  "type": "Feature",
  "properties": {
    "iso:country":"US",
    "sg:address":"742 Washington St Fl 2",
    "sg:city":"Easton",
    "sg:classifiers":[
        {
            "category":"Real Estate",
            "subcategory":"Real Estate Services",
            "type":"Services"
        },
        {
            "category":"Banks & Credit Unions",
            "subcategory":"Financial Services",
            "type":"Services"
        }
    ],
    "sg:phone":"+1 610 330 6930",
    "sg:postcode":"18042",
    "sg:province":"PA",
    "sg:tags":[
        "loan",
        "processing"
    ],
    "sg:website":"http://www.paylessmortgage.com",
    "wof:name":"Payless Mortgage Corp",
    "wof:placetype":"venue"
},
  "geometry": {"coordinates":[-75.218912,40.686975],"type":"Point"}
}