{
  "type": "Feature",
  "properties": {
    "iso:country":"US",
    "sg:address":"206 E Wallace Ave",
    "sg:city":"New Castle",
    "sg:classifiers":[
        {
            "category":"Shopping",
            "type":"Retail Goods"
        }
    ],
    "sg:phone":"+1   ",
    "sg:postcode":"16101",
    "sg:province":"PA",
    "sg:tags":[
        "miscellaneous",
        "store"
    ],
    "wof:name":"Grand Book & Bible",
    "wof:placetype":"venue"
},
  "geometry": {"coordinates":[-80.341858,41.006525],"type":"Point"}
}