{
  "type": "Feature",
  "properties": {
    "iso:country":"US",
    "sg:address":"5550 E State St",
    "sg:city":"Hermitage",
    "sg:classifiers":[
        {
            "category":"Organizations",
            "subcategory":"Community Association",
            "type":"Services"
        }
    ],
    "sg:phone":"+1   ",
    "sg:postcode":"16148",
    "sg:province":"PA",
    "wof:name":"V F W Post 6166",
    "wof:placetype":"venue"
},
  "geometry": {"coordinates":[-80.408017,41.237231],"type":"Point"}
}