{
  "type": "Feature",
  "properties": {
    "addr:full":"1288 Reynoldsdale Rd New Paris PA 15554",
    "addr:housenumber":"1288",
    "addr:postcode":"15554",
    "addr:street":"Reynoldsdale Rd",
    "iso:country":"US",
    "sg:address":"1288 Reynoldsdale Rd",
    "sg:city":"New Paris",
    "sg:phone":"+1   ",
    "sg:postcode":"15554",
    "sg:province":"PA",
    "sg:tags":[
        "farm",
        "corn"
    ],
    "wof:name":"David Bowser",
    "wof:placetype":"venue"
},
  "geometry": {"coordinates":[-78.54803800000001,40.127508],"type":"Point"}
}