{
  "type": "Feature",
  "properties": {
    "iso:country":"US",
    "sg:address":"419 S 48th St",
    "sg:city":"Philadelphia",
    "sg:classifiers":[
        {
            "category":"Professional",
            "subcategory":"Art Services",
            "type":"Services"
        }
    ],
    "sg:phone":"+1 215 748 3120",
    "sg:postcode":"19143",
    "sg:province":"PA",
    "sg:tags":[
        "graphic",
        "designer"
    ],
    "wof:name":"Center Photographix Inc",
    "wof:placetype":"venue"
},
  "geometry": {"coordinates":[-75.218361,39.952265],"type":"Point"}
}