{
  "type": "Feature",
  "properties": {
    "iso:country":"US",
    "sg:address":"1028 S Braddock Ave",
    "sg:city":"Pittsburgh",
    "sg:classifiers":[
        {
            "category":"Real Estate",
            "subcategory":"Real Estate Services",
            "type":"Services"
        },
        {
            "category":"Real Estate",
            "subcategory":"Real Estate Agent",
            "type":"Services"
        }
    ],
    "sg:phone":"+1 412 241 4700",
    "sg:postcode":"15218",
    "sg:province":"PA",
    "sg:tags":[
        "buyer",
        "management",
        "broker"
    ],
    "sg:website":"http://www.neighborhoodrealtyservices.com",
    "wof:name":"Neighborhood Realty Services",
    "wof:placetype":"venue"
},
  "geometry": {"coordinates":[-79.894544,40.433519],"type":"Point"}
}