{
  "type": "Feature",
  "properties": {
    "iso:country":"US",
    "sg:address":"24 N 3rd St",
    "sg:city":"Easton",
    "sg:classifiers":[
        {
            "category":"Building & Trades",
            "subcategory":"Plumbing",
            "type":"Services"
        }
    ],
    "sg:phone":"+1 610 252 5567",
    "sg:postcode":"18042",
    "sg:province":"PA",
    "sg:tags":[
        "plumbing",
        "contractor"
    ],
    "wof:name":"Durnin's Fast Plumbing",
    "wof:placetype":"venue"
},
  "geometry": {"coordinates":[-75.209344,40.693086],"type":"Point"}
}