{
  "type": "Feature",
  "properties": {
    "iso:country":"US",
    "sg:address":"219 Sugartown Rd Apt N203",
    "sg:city":"Wayne",
    "sg:classifiers":[
        {
            "category":"Real Estate",
            "subcategory":"Architect",
            "type":"Services"
        }
    ],
    "sg:phone":"+1 610 405 1548",
    "sg:postcode":"19087",
    "sg:province":"PA",
    "sg:tags":[
        "architects'",
        "specification",
        "construction",
        "builders'",
        "architectural"
    ],
    "wof:name":"Dlc Architecture",
    "wof:placetype":"venue"
},
  "geometry": {"coordinates":[-75.406097,40.044842],"type":"Point"}
}