{
  "type": "Feature",
  "properties": {
    "iso:country":"US",
    "sg:address":"8150 Perry Hwy",
    "sg:city":"Pittsburgh",
    "sg:classifiers":[
        {
            "category":"Real Estate",
            "subcategory":"Real Estate Operator",
            "type":"Services"
        }
    ],
    "sg:phone":"+1 412 369 9620",
    "sg:postcode":"15237",
    "sg:province":"PA",
    "sg:tags":[
        "building",
        "parks"
    ],
    "wof:name":"Executive Office Building",
    "wof:placetype":"venue"
},
  "geometry": {"coordinates":[-80.038737,40.555387],"type":"Point"}
}