{
  "type": "Feature",
  "properties": {
    "iso:country":"US",
    "sg:address":"3804 Lisburn Rd",
    "sg:city":"Mechanicsburg",
    "sg:classifiers":[
        {
            "category":"Restaurant",
            "type":"Food & Drink"
        }
    ],
    "sg:phone":"+1 717 795 9880",
    "sg:postcode":"17055",
    "sg:province":"PA",
    "sg:website":"www.lfgc.net",
    "wof:name":"KOOL Beans Cafe-Liberty Forge",
    "wof:placetype":"venue"
},
  "geometry": {"coordinates":[-76.92786,40.179734],"type":"Point"}
}