{
  "type": "Feature",
  "properties": {
    "iso:country":"US",
    "sg:address":"723 Stradone Rd",
    "sg:city":"Bala Cynwyd",
    "sg:classifiers":[
        {
            "category":"Building & Trades",
            "subcategory":"Landscaping Services",
            "type":"Services"
        }
    ],
    "sg:phone":"+1   ",
    "sg:postcode":"19004",
    "sg:province":"PA",
    "wof:name":"McCoy",
    "wof:placetype":"venue"
},
  "geometry": {"coordinates":[-75.238165,40.018515],"type":"Point"}
}