{
  "type": "Feature",
  "properties": {
    "iso:country":"US",
    "sg:address":"707 Church St",
    "sg:city":"Honesdale",
    "sg:classifiers":[
        {
            "category":"Banks & Credit Unions",
            "subcategory":"Investment Brokerage",
            "type":"Services"
        }
    ],
    "sg:phone":"+1 570 253 6610",
    "sg:postcode":"18431",
    "sg:province":"PA",
    "sg:tags":[
        "security"
    ],
    "wof:name":"Martin Goodenough & Co",
    "wof:placetype":"venue"
},
  "geometry": {"coordinates":[-75.254401,41.572424],"type":"Point"}
}