{
  "type": "Feature",
  "properties": {
    "iso:country":"US",
    "sg:address":"3140B W Tilghman St # 250",
    "sg:city":"Allentown",
    "sg:classifiers":[
        {
            "category":"Professional",
            "subcategory":"Computer Services",
            "type":"Services"
        }
    ],
    "sg:phone":"+1 610 740 0665",
    "sg:postcode":"18104",
    "sg:province":"PA",
    "sg:tags":[
        "design",
        "system",
        "network"
    ],
    "wof:name":"P C Support Etc",
    "wof:placetype":"venue"
},
  "geometry": {"coordinates":[-75.527385,40.597833],"type":"Point"}
}