{
  "type": "Feature",
  "properties": {
    "iso:country":"US",
    "sg:address":"1001 Woodcircle Dr",
    "sg:city":"Wynnewood",
    "sg:classifiers":[
        {
            "category":"Building & Trades",
            "subcategory":"Construction",
            "type":"Services"
        }
    ],
    "sg:phone":"+1   ",
    "sg:postcode":"19096",
    "sg:province":"PA",
    "sg:tags":[
        "hanging",
        "contractor"
    ],
    "wof:name":"ONeill Painting",
    "wof:placetype":"venue"
},
  "geometry": {"coordinates":[-75.26257099999999,39.990148],"type":"Point"}
}