{
  "type": "Feature",
  "properties": {
    "iso:country":"US",
    "sg:address":"41 Woodlynn Dr",
    "sg:city":"Selinsgrove",
    "sg:classifiers":[
        {
            "category":"Professional",
            "type":"Services"
        }
    ],
    "sg:phone":"+1 570 372 0936",
    "sg:postcode":"17870",
    "sg:province":"PA",
    "sg:tags":[
        "establishment"
    ],
    "wof:name":"Girl Scouts Of The USA",
    "wof:placetype":"venue"
},
  "geometry": {"coordinates":[-76.879434,40.805778],"type":"Point"}
}