{
  "type": "Feature",
  "properties": {
    "iso:country":"US",
    "sg:address":"10 Lowther St",
    "sg:city":"Lemoyne",
    "sg:classifiers":[
        {
            "category":"Autos & Motor Vehicles",
            "subcategory":"Fuel & Gas Station",
            "type":"Retail Goods"
        }
    ],
    "sg:phone":"+1 717 761 1545",
    "sg:postcode":"17043",
    "sg:province":"PA",
    "sg:tags":[
        "oil"
    ],
    "wof:name":"Mobil",
    "wof:placetype":"venue"
},
  "geometry": {"coordinates":[-76.885392,40.243394],"type":"Point"}
}