{
  "type": "Feature",
  "properties": {
    "addr:full":"1121 Harvey Ave Greensburg PA 15601",
    "addr:housenumber":"1121",
    "addr:postcode":"15601",
    "addr:street":"Harvey Ave",
    "iso:country":"US",
    "sg:address":"1121 Harvey Ave",
    "sg:city":"Greensburg",
    "sg:classifiers":[
        {
            "category":"Professional",
            "subcategory":"Management & Consulting",
            "type":"Services"
        }
    ],
    "sg:phone":"+1 724 850 7979",
    "sg:postcode":"15601",
    "sg:province":"PA",
    "sg:tags":[
        "consultant",
        "telecommunication"
    ],
    "wof:name":"Smith Communications Group PC",
    "wof:placetype":"venue"
},
  "geometry": {"coordinates":[-79.532455,40.338528],"type":"Point"}
}