{
  "type": "Feature",
  "properties": {
    "iso:country":"US",
    "sg:address":"1230 Plymouth Ave",
    "sg:city":"Bristol",
    "sg:classifiers":[
        {
            "category":"Organizations",
            "subcategory":"Religious Organization",
            "type":"Services"
        }
    ],
    "sg:phone":"+1 215 781 9698",
    "sg:postcode":"19007",
    "sg:province":"PA",
    "sg:tags":[
        "church"
    ],
    "wof:name":"Refuge For The Perishing Holy",
    "wof:placetype":"venue"
},
  "geometry": {"coordinates":[-74.85024199999999,40.118003],"type":"Point"}
}