{
  "type": "Feature",
  "properties": {
    "iso:country":"US",
    "sg:address":"71 Red Church Rd",
    "sg:city":"Kempton",
    "sg:classifiers":[
        {
            "category":"Retail",
            "subcategory":"Portrait Studio",
            "type":"Services"
        }
    ],
    "sg:phone":"+1 610 756 6490",
    "sg:postcode":"19529",
    "sg:province":"PA",
    "sg:tags":[
        "photographer"
    ],
    "wof:name":"Stone House Studios",
    "wof:placetype":"venue"
},
  "geometry": {"coordinates":[-75.825723,40.630687],"type":"Point"}
}