{
  "type": "Feature",
  "properties": {
    "iso:country":"US",
    "sg:address":"1250 W Valley Rd",
    "sg:city":"Wayne",
    "sg:classifiers":[
        {
            "category":"Building & Trades",
            "subcategory":"Electrical",
            "type":"Services"
        }
    ],
    "sg:phone":"+1   ",
    "sg:postcode":"19087",
    "sg:province":"PA",
    "sg:tags":[
        "electrical",
        "contractor"
    ],
    "wof:name":"Richard Kompas & Sons",
    "wof:placetype":"venue"
},
  "geometry": {"coordinates":[-75.429114,40.074922],"type":"Point"}
}