{
  "type": "Feature",
  "properties": {
    "iso:country":"US",
    "sg:address":"114 Nagles Ct",
    "sg:city":"Ebensburg",
    "sg:classifiers":[
        {
            "category":"Building & Trades",
            "subcategory":"Construction",
            "type":"Services"
        }
    ],
    "sg:phone":"+1   ",
    "sg:postcode":"15931",
    "sg:province":"PA",
    "sg:tags":[
        "excavation",
        "contractor"
    ],
    "wof:name":"Nagle Excavating",
    "wof:placetype":"venue"
},
  "geometry": {"coordinates":[-78.71906799999999,40.525541],"type":"Point"}
}