{
  "type": "Feature",
  "properties": {
    "addr:full":"3231 E Prospect Rd York PA 17402",
    "addr:housenumber":"3231",
    "addr:postcode":"17402",
    "addr:street":"E Prospect Rd",
    "iso:country":"US",
    "sg:address":"3231 E Prospect Rd",
    "sg:city":"York",
    "sg:classifiers":[
        {
            "category":"Shopping",
            "subcategory":"Gifts & Souvenirs",
            "type":"Retail Goods"
        }
    ],
    "sg:phone":"+1 717 755 4007",
    "sg:postcode":"17402",
    "sg:province":"PA",
    "sg:tags":[
        "shop"
    ],
    "wof:name":"Gift Pleasers",
    "wof:placetype":"venue"
},
  "geometry": {"coordinates":[-76.633161,39.960747],"type":"Point"}
}