{
  "type": "Feature",
  "properties": {
    "iso:country":"US",
    "sg:address":"2 Winter St",
    "sg:city":"Pittston",
    "sg:classifiers":[
        {
            "category":"Bars & Pubs",
            "type":"Food & Drink"
        }
    ],
    "sg:phone":"+1   ",
    "sg:postcode":"18640",
    "sg:province":"PA",
    "sg:tags":[
        "drinking"
    ],
    "wof:name":"Lithuanian Club Inkerman",
    "wof:placetype":"venue"
},
  "geometry": {"coordinates":[-75.81515400000001,41.298623],"type":"Point"}
}