{
  "type": "Feature",
  "properties": {
    "addr:full":"1500 N George St York PA 17404",
    "addr:housenumber":"1500",
    "addr:postcode":"17404",
    "addr:street":"N George St",
    "iso:country":"US",
    "sg:address":"1500 N George St",
    "sg:city":"York",
    "sg:classifiers":[
        {
            "category":"Restaurant",
            "type":"Food & Drink"
        }
    ],
    "sg:phone":"+1 717 852 1005",
    "sg:postcode":"17404",
    "sg:province":"PA",
    "sg:tags":[
        "eating"
    ],
    "wof:name":"China Kitchen",
    "wof:placetype":"venue"
},
  "geometry": {"coordinates":[-76.734489,39.98233],"type":"Point"}
}