{
  "type": "Feature",
  "properties": {
    "addr:full":"160 Gerry Ln Johnstown PA 15904",
    "addr:housenumber":"160",
    "addr:postcode":"15904",
    "addr:street":"Gerry Ln",
    "iso:country":"US",
    "sg:address":"160 Gerry Ln",
    "sg:city":"Johnstown",
    "sg:classifiers":[
        {
            "category":"Freight",
            "type":"Transportation"
        }
    ],
    "sg:phone":"+1 814 266 0380",
    "sg:postcode":"15904",
    "sg:province":"PA",
    "sg:tags":[
        "storage"
    ],
    "wof:name":"Adaptive Technologies Inc",
    "wof:placetype":"venue"
},
  "geometry": {"coordinates":[-78.860411,40.296519],"type":"Point"}
}