{
  "type": "Feature",
  "properties": {
    "iso:country":"US",
    "sg:address":"137 S Pugh St",
    "sg:city":"State College",
    "sg:classifiers":[
        {
            "category":"Health Services",
            "subcategory":"Doctor",
            "type":"Services"
        }
    ],
    "sg:phone":"+1   ",
    "sg:postcode":"16801",
    "sg:province":"PA",
    "wof:name":"Williams Ben G DMD & Assoc",
    "wof:placetype":"venue"
},
  "geometry": {"coordinates":[-77.859251,40.794472],"type":"Point"}
}