{
  "type": "Feature",
  "properties": {
    "iso:country":"US",
    "sg:address":"4701 Pine St",
    "sg:city":"Philadelphia",
    "sg:classifiers":[
        {
            "category":"Travel",
            "subcategory":"Travel Agent",
            "type":"Entertainment"
        }
    ],
    "sg:phone":"+1 267 531 0550",
    "sg:postcode":"19143",
    "sg:province":"PA",
    "sg:tags":[
        "tours",
        "promoter"
    ],
    "wof:name":"Perls Tour & Travel",
    "wof:placetype":"venue"
},
  "geometry": {"coordinates":[-75.21834699999999,39.952552],"type":"Point"}
}