{
  "type": "Feature",
  "properties": {
    "addr:full":"64 Robinson St Pottstown PA 19464",
    "addr:housenumber":"64",
    "addr:postcode":"19464",
    "addr:street":"Robinson St",
    "iso:country":"US",
    "sg:address":"64 Robinson St",
    "sg:city":"Pottstown",
    "sg:classifiers":[
        {
            "category":"Manufacturing",
            "subcategory":"Tools & Machinery",
            "type":"Manufacturing & Wholesale Goods"
        }
    ],
    "sg:phone":"+1   ",
    "sg:postcode":"19464",
    "sg:province":"PA",
    "sg:tags":[
        "machine",
        "vending"
    ],
    "wof:name":"Valley Vending",
    "wof:placetype":"venue"
},
  "geometry": {"coordinates":[-75.660186,40.257127],"type":"Point"}
}