{
  "type": "Feature",
  "properties": {
    "iso:country":"US",
    "sg:address":"166 E Levering Mill Rd",
    "sg:city":"Bala Cynwyd",
    "sg:classifiers":[
        {
            "category":"Retail",
            "subcategory":"Auto Rental",
            "type":"Services"
        }
    ],
    "sg:phone":"+1 610 664 1166",
    "sg:postcode":"19004",
    "sg:province":"PA",
    "sg:tags":[
        "automobile",
        "leasing"
    ],
    "wof:name":"Dak Auto Assoc",
    "wof:placetype":"venue"
},
  "geometry": {"coordinates":[-75.227898,40.016087],"type":"Point"}
}