{
  "type": "Feature",
  "properties": {
    "iso:country":"US",
    "sg:address":"1010 Buffalo St",
    "sg:city":"Franklin",
    "sg:classifiers":[
        {
            "category":"Government",
            "subcategory":"Office",
            "type":"Public Place"
        }
    ],
    "sg:phone":"+1 814 437 3016",
    "sg:postcode":"16323",
    "sg:province":"PA",
    "wof:name":"County Coroner",
    "wof:placetype":"venue"
},
  "geometry": {"coordinates":[-79.82732,41.393909],"type":"Point"}
}