{
  "type": "Feature",
  "properties": {
    "addr:full":"9280 Old Tyburn Rd Morrisville PA 19067",
    "addr:housenumber":"9280",
    "addr:postcode":"19067",
    "addr:street":"Old Tyburn Rd",
    "iso:country":"US",
    "sg:address":"9280 Old Tyburn Rd",
    "sg:city":"Morrisville",
    "sg:classifiers":[
        {
            "category":"Retail",
            "subcategory":"Auto Repair",
            "type":"Services"
        }
    ],
    "sg:phone":"+1 215 295 2210",
    "sg:postcode":"19067",
    "sg:province":"PA",
    "sg:tags":[
        "truck"
    ],
    "wof:name":"Kennys Truck & Trailer Svc",
    "wof:placetype":"venue"
},
  "geometry": {"coordinates":[-74.79439600000001,40.180231],"type":"Point"}
}