{
  "type": "Feature",
  "properties": {
    "addr:full":"95 Louise Dr Warminster PA 18974",
    "addr:housenumber":"95",
    "addr:postcode":"18974",
    "addr:street":"Louise Dr",
    "iso:country":"US",
    "sg:address":"95 Louise Dr",
    "sg:city":"Warminster",
    "sg:classifiers":[
        {
            "category":"Wholesale",
            "subcategory":"Hardware",
            "type":"Manufacturing & Wholesale Goods"
        }
    ],
    "sg:phone":"+1   ",
    "sg:postcode":"18974",
    "sg:province":"PA",
    "sg:tags":[
        "equipment",
        "industrial"
    ],
    "wof:name":"Doall Company",
    "wof:placetype":"venue"
},
  "geometry": {"coordinates":[-75.063926,40.219324],"type":"Point"}
}