{
  "type": "Feature",
  "properties": {
    "iso:country":"US",
    "sg:address":"3205 Hazel St",
    "sg:city":"Erie",
    "sg:classifiers":[
        {
            "category":"Home & Garden",
            "subcategory":"Home Furnishings",
            "type":"Retail Goods"
        },
        {
            "category":"Manufacturing",
            "subcategory":"Glass & Minerals",
            "type":"Manufacturing & Wholesale Goods"
        }
    ],
    "sg:phone":"+1 814 454 7111",
    "sg:postcode":"16508",
    "sg:province":"PA",
    "sg:tags":[
        "plate",
        "window",
        "glass-wholesale",
        "glass-auto",
        "shape",
        "mirror",
        "circle",
        "glass-block",
        "special",
        "manufacturer"
    ],
    "wof:name":"Hoffman Glass Company Inc",
    "wof:placetype":"venue"
},
  "geometry": {"coordinates":[-80.085297,42.101508],"type":"Point"}
}