{
  "type": "Feature",
  "properties": {
    "addr:full":"609 W Main St Palmyra PA 17078",
    "addr:housenumber":"609",
    "addr:postcode":"17078",
    "addr:street":"W Main St",
    "iso:country":"US",
    "sg:address":"609 W Main St",
    "sg:city":"Palmyra",
    "sg:classifiers":[
        {
            "category":"Wholesale",
            "subcategory":"Computers",
            "type":"Manufacturing & Wholesale Goods"
        },
        {
            "category":"Utilities",
            "subcategory":"Mobile Phone",
            "type":"Services"
        },
        {
            "category":"Retail",
            "subcategory":"Repair Shop",
            "type":"Services"
        },
        {
            "category":"Professional",
            "subcategory":"Computer Services",
            "type":"Services"
        }
    ],
    "sg:phone":"+1 717 473 3401",
    "sg:postcode":"17078",
    "sg:province":"PA",
    "sg:tags":[
        "repair-business",
        "equipment-service",
        "telephone",
        "cellular",
        "equipment"
    ],
    "sg:website":"http://www.jandstc.com",
    "wof:name":"J&S Computer Sales & Service w/ Sprint",
    "wof:placetype":"venue"
},
  "geometry": {"coordinates":[-76.604274,40.303444],"type":"Point"}
}