{
  "type": "Feature",
  "properties": {
    "addr:full":"3043 College Hts Blvd Allentown PA 18104",
    "addr:housenumber":"3043",
    "addr:postcode":"18104",
    "addr:street":"College Hts Blvd",
    "iso:country":"US",
    "sg:address":"3043 College Hts Blvd",
    "sg:city":"Allentown",
    "sg:classifiers":[
        {
            "category":"Food & Beverages",
            "subcategory":"Groceries & Convenience Stores",
            "type":"Retail Goods"
        }
    ],
    "sg:phone":"+1 610 820 0133",
    "sg:postcode":"18104",
    "sg:province":"PA",
    "wof:name":"Seven-Ten Food Store",
    "wof:placetype":"venue"
},
  "geometry": {"coordinates":[-75.52388500000001,40.593595],"type":"Point"}
}