{
  "type": "Feature",
  "properties": {
    "iso:country":"US",
    "sg:address":"551 Paxon Hollow Rd",
    "sg:city":"Broomall",
    "sg:classifiers":[
        {
            "category":"Organizations",
            "subcategory":"Religious Organization",
            "type":"Services"
        }
    ],
    "sg:phone":"+1 610 356 8211",
    "sg:postcode":"19008",
    "sg:province":"PA",
    "sg:website":"www.belmontbaptistchurch.net",
    "wof:name":"Belmont Baptist Church",
    "wof:placetype":"venue"
},
  "geometry": {"coordinates":[-75.35647299999999,39.964515],"type":"Point"}
}