{
  "type": "Feature",
  "properties": {
    "iso:country":"US",
    "sg:address":"317 W Ave",
    "sg:city":"Mount Carmel",
    "sg:classifiers":[
        {
            "category":"Professional",
            "type":"Services"
        }
    ],
    "sg:phone":"+1   ",
    "sg:postcode":"17851",
    "sg:province":"PA",
    "wof:name":"Mark Reichwein",
    "wof:placetype":"venue"
},
  "geometry": {"coordinates":[-76.41826,40.798359],"type":"Point"}
}