{
  "type": "Feature",
  "properties": {
    "iso:country":"US",
    "sg:address":"220 Laurel Ave",
    "sg:city":"Gibsonia",
    "sg:classifiers":[
        {
            "category":"Building & Trades",
            "subcategory":"Construction",
            "type":"Services"
        }
    ],
    "sg:phone":"+1 724 444 4540",
    "sg:postcode":"15044",
    "sg:province":"PA",
    "sg:tags":[
        "paving",
        "contractor"
    ],
    "wof:name":"Slebodnik Paving Inc",
    "wof:placetype":"venue"
},
  "geometry": {"coordinates":[-79.969076,40.667664],"type":"Point"}
}