{
  "type": "Feature",
  "properties": {
    "iso:country":"US",
    "sg:address":"108 E Broad St",
    "sg:city":"Quakertown",
    "sg:classifiers":[
        {
            "category":"Shopping",
            "subcategory":"Used Merchandise",
            "type":"Retail Goods"
        }
    ],
    "sg:phone":"+1 215 538 7733",
    "sg:postcode":"18951",
    "sg:province":"PA",
    "wof:name":"Trolley House Emporium",
    "wof:placetype":"venue"
},
  "geometry": {"coordinates":[-75.377465,40.411227],"type":"Point"}
}