{
  "type": "Feature",
  "properties": {
    "addr:full":"1205 E Cumberland St Lebanon PA 17042",
    "addr:housenumber":"1205",
    "addr:postcode":"17042",
    "addr:street":"E Cumberland St",
    "iso:country":"US",
    "sg:address":"1205 E Cumberland St",
    "sg:city":"Lebanon",
    "sg:classifiers":[
        {
            "category":"Organizations",
            "subcategory":"Religious Organization",
            "type":"Services"
        }
    ],
    "sg:phone":"+1 717 272 5555",
    "sg:postcode":"17042",
    "sg:province":"PA",
    "sg:tags":[
        "church"
    ],
    "wof:name":"Avon Zion United Methodist",
    "wof:placetype":"venue"
},
  "geometry": {"coordinates":[-76.38946900000001,40.346715],"type":"Point"}
}