{
  "type": "Feature",
  "properties": {
    "addr:full":"729 E Grand Ave Tower City PA 17980",
    "addr:housenumber":"729",
    "addr:postcode":"17980",
    "addr:street":"E Grand Ave",
    "iso:country":"US",
    "sg:address":"729 E Grand Ave",
    "sg:city":"Tower City",
    "sg:classifiers":[
        {
            "category":"Building & Trades",
            "subcategory":"Construction",
            "type":"Services"
        }
    ],
    "sg:phone":"+1 717 647 4467",
    "sg:postcode":"17980",
    "sg:province":"PA",
    "sg:tags":[
        "general",
        "contractor"
    ],
    "wof:name":"K Contracting",
    "wof:placetype":"venue"
},
  "geometry": {"coordinates":[-76.54854899999999,40.589871],"type":"Point"}
}