{
  "type": "Feature",
  "properties": {
    "iso:country":"US",
    "sg:address":"40 N Queen St",
    "sg:city":"Littlestown",
    "sg:classifiers":[
        {
            "category":"Shopping",
            "subcategory":"Used Merchandise",
            "type":"Retail Goods"
        }
    ],
    "sg:phone":"+1 717 359 4527",
    "sg:postcode":"17340",
    "sg:province":"PA",
    "sg:tags":[
        "antique"
    ],
    "wof:name":"Grandma Whitman's Cupboard",
    "wof:placetype":"venue"
},
  "geometry": {"coordinates":[-77.089049,39.745731],"type":"Point"}
}