{
  "type": "Feature",
  "properties": {
    "iso:country":"US",
    "sg:address":"449 Irish Hollow Rd",
    "sg:city":"Bellefonte",
    "sg:classifiers":[
        {
            "category":"Professional",
            "type":"Services"
        },
        {
            "category":"Home & Garden",
            "subcategory":"Home Furnishings",
            "type":"Retail Goods"
        }
    ],
    "sg:phone":"+1 814 355 8323",
    "sg:postcode":"16823",
    "sg:province":"PA",
    "sg:tags":[
        "window",
        "covering"
    ],
    "wof:name":"Heritage Innovations Inc",
    "wof:placetype":"venue"
},
  "geometry": {"coordinates":[-77.753199,40.89105],"type":"Point"}
}