{
  "type": "Feature",
  "properties": {
    "addr:full":"739 S 26th St Harrisburg PA 17111",
    "addr:housenumber":"739",
    "addr:postcode":"17111",
    "addr:street":"S 26Th St",
    "iso:country":"US",
    "sg:address":"739 S 26th St",
    "sg:city":"Harrisburg",
    "sg:classifiers":[
        {
            "category":"Building & Trades",
            "subcategory":"Cleaning & Sanitation",
            "type":"Services"
        }
    ],
    "sg:phone":"+1 717 564 2216",
    "sg:postcode":"17111",
    "sg:province":"PA",
    "sg:tags":[
        "janitor"
    ],
    "wof:name":"M & J Janitorial Svc",
    "wof:placetype":"venue"
},
  "geometry": {"coordinates":[-76.84245,40.260309],"type":"Point"}
}