{
  "type": "Feature",
  "properties": {
    "iso:country":"US",
    "sg:address":"427 N New St",
    "sg:city":"Bethlehem",
    "sg:classifiers":[
        {
            "category":"Museum",
            "type":"Entertainment"
        }
    ],
    "sg:phone":"+1 610 868 6868",
    "sg:postcode":"18018",
    "sg:province":"PA",
    "wof:name":"Historic Bethlehem Partnership",
    "wof:placetype":"venue"
},
  "geometry": {"coordinates":[-75.37871,40.619442],"type":"Point"}
}