{
  "type": "Feature",
  "properties": {
    "addr:full":"320 Darby Rd Ste 1 Havertown PA 19083",
    "addr:housenumber":"320",
    "addr:postcode":"19083",
    "addr:street":"Darby Rd Ste 1",
    "iso:country":"US",
    "sg:address":"320 Darby Rd Ste 1",
    "sg:city":"Havertown",
    "sg:classifiers":[
        {
            "category":"Wholesale",
            "subcategory":"Medical Equipment & Supplies",
            "type":"Manufacturing & Wholesale Goods"
        }
    ],
    "sg:phone":"+1 610 853 1985",
    "sg:postcode":"19083",
    "sg:province":"PA",
    "sg:tags":[
        "oxygen"
    ],
    "wof:name":"Pulmocare",
    "wof:placetype":"venue"
},
  "geometry": {"coordinates":[-75.298907,39.970799],"type":"Point"}
}