{
  "type": "Feature",
  "properties": {
    "iso:country":"US",
    "sg:address":"209 W Lehigh St",
    "sg:city":"Bethlehem",
    "sg:classifiers":[
        {
            "category":"Professional",
            "type":"Services"
        }
    ],
    "sg:phone":"+1   ",
    "sg:postcode":"18018",
    "sg:province":"PA",
    "wof:name":"Aled Corp",
    "wof:placetype":"venue"
},
  "geometry": {"coordinates":[-75.385316,40.616822],"type":"Point"}
}