{
  "type": "Feature",
  "properties": {
    "iso:country":"US",
    "sg:address":"331 Hickory Grade Rd",
    "sg:city":"Bridgeville",
    "sg:classifiers":[
        {
            "category":"Health Services",
            "subcategory":"Clinic",
            "type":"Services"
        }
    ],
    "sg:phone":"+1 412 838 0034",
    "sg:postcode":"15017",
    "sg:province":"PA",
    "sg:website":"www.pyramidhealthcarepa.com",
    "wof:name":"Pyramid Healthcare",
    "wof:placetype":"venue"
},
  "geometry": {"coordinates":[-80.14108,40.350838],"type":"Point"}
}