{
  "type": "Feature",
  "properties": {
    "iso:country":"US",
    "sg:address":"532 Main St",
    "sg:city":"Schwenksville",
    "sg:classifiers":[
        {
            "category":"Social Services",
            "type":"Services"
        }
    ],
    "sg:phone":"+1 610 489 1555",
    "sg:postcode":"19473",
    "sg:province":"PA",
    "sg:tags":[
        "organization",
        "welfare"
    ],
    "wof:name":"Retired Senior Volunteer Progr",
    "wof:placetype":"venue"
},
  "geometry": {"coordinates":[-75.463905,40.257734],"type":"Point"}
}