{
  "type": "Feature",
  "properties": {
    "iso:country":"US",
    "sg:address":"2250 York Rd",
    "sg:city":"York",
    "sg:classifiers":[
        {
            "category":"Professional",
            "subcategory":"Business Services",
            "type":"Services"
        }
    ],
    "sg:phone":"+1   ",
    "sg:postcode":"17407",
    "sg:province":"PA",
    "wof:name":"Col Vision",
    "wof:placetype":"venue"
},
  "geometry": {"coordinates":[-76.707247,39.894191],"type":"Point"}
}