{
  "type": "Feature",
  "properties": {
    "addr:full":"1113 Frankford Ave Philadelphia PA 19125",
    "addr:housenumber":"1113",
    "addr:postcode":"19125",
    "addr:street":"Frankford Ave",
    "iso:country":"US",
    "sg:address":"1113 Frankford Ave",
    "sg:city":"Philadelphia",
    "sg:classifiers":[
        {
            "category":"Shopping",
            "subcategory":"Books",
            "type":"Retail Goods"
        }
    ],
    "sg:phone":"+1 215 291 5880",
    "sg:postcode":"19125",
    "sg:province":"PA",
    "sg:tags":[
        "bookstore"
    ],
    "sg:website":"phillybookspace.com",
    "wof:name":"Bookspace",
    "wof:placetype":"venue"
},
  "geometry": {"coordinates":[-75.13440799999999,39.968018],"type":"Point"}
}