{
  "type": "Feature",
  "properties": {
    "iso:country":"US",
    "sg:address":"3450 Hamilton Walk",
    "sg:city":"Philadelphia",
    "sg:classifiers":[
        {
            "category":"Education",
            "subcategory":"College",
            "type":"Public Place"
        }
    ],
    "sg:phone":"+1   ",
    "sg:postcode":"19104",
    "sg:province":"PA",
    "wof:name":"University PA Medical School",
    "wof:placetype":"venue"
},
  "geometry": {"coordinates":[-75.19503899999999,39.949593],"type":"Point"}
}