{
  "type": "Feature",
  "properties": {
    "iso:country":"US",
    "sg:address":"3035 Franks Rd",
    "sg:city":"Huntingdon Vly",
    "sg:classifiers":[
        {
            "category":"Manufacturing",
            "subcategory":"Metals",
            "type":"Manufacturing & Wholesale Goods"
        }
    ],
    "sg:phone":"+1 215 938 8920",
    "sg:postcode":"19006",
    "sg:province":"PA",
    "sg:tags":[
        "fabricator",
        "sheet"
    ],
    "sg:website":"www.rhoadsinc.com",
    "wof:name":"Rhoads Industries",
    "wof:placetype":"venue"
},
  "geometry": {"coordinates":[-75.038393,40.121659],"type":"Point"}
}