{
  "type": "Feature",
  "properties": {
    "addr:full":"685 E Christine Rd Nottingham PA 19362",
    "addr:housenumber":"685",
    "addr:postcode":"19362",
    "addr:street":"E Christine Rd",
    "iso:country":"US",
    "sg:address":"685 E Christine Rd",
    "sg:city":"Nottingham",
    "sg:classifiers":[
        {
            "category":"Building & Trades",
            "subcategory":"Construction",
            "type":"Services"
        }
    ],
    "sg:phone":"+1 610 932 3566",
    "sg:postcode":"19362",
    "sg:province":"PA",
    "sg:tags":[
        "excavating",
        "contractor"
    ],
    "wof:name":"Tri State Paving",
    "wof:placetype":"venue"
},
  "geometry": {"coordinates":[-76.006423,39.743965],"type":"Point"}
}