{
  "type": "Feature",
  "properties": {
    "iso:country":"US",
    "sg:address":"6934 Old York Rd",
    "sg:city":"Philadelphia",
    "sg:classifiers":[
        {
            "category":"Organizations",
            "subcategory":"Religious Organization",
            "type":"Services"
        }
    ],
    "sg:phone":"+1 215 224 8422",
    "sg:postcode":"19126",
    "sg:province":"PA",
    "sg:tags":[
        "church"
    ],
    "wof:name":"Anna's House",
    "wof:placetype":"venue"
},
  "geometry": {"coordinates":[-75.13738499999999,40.060883],"type":"Point"}
}