{
  "type": "Feature",
  "properties": {
    "addr:full":"49 S Main St Montrose PA 18801",
    "addr:housenumber":"49",
    "addr:postcode":"18801",
    "addr:street":"S Main St",
    "iso:country":"US",
    "sg:address":"49 S Main St",
    "sg:city":"Montrose",
    "sg:classifiers":[
        {
            "category":"Building & Trades",
            "subcategory":"Construction",
            "type":"Services"
        }
    ],
    "sg:phone":"+1   ",
    "sg:postcode":"18801",
    "sg:province":"PA",
    "sg:tags":[
        "contractor"
    ],
    "wof:name":"Albertus Engineering Inc",
    "wof:placetype":"venue"
},
  "geometry": {"coordinates":[-75.880827,41.830511],"type":"Point"}
}