{
  "type": "Feature",
  "properties": {
    "iso:country":"US",
    "sg:address":"10900 Perry Hwy",
    "sg:city":"Wexford",
    "sg:classifiers":[
        {
            "category":"Professional",
            "subcategory":"Employment Agencies",
            "type":"Services"
        }
    ],
    "sg:phone":"+1 724 934 2228",
    "sg:postcode":"15090",
    "sg:province":"PA",
    "sg:tags":[
        "consultant",
        "search",
        "executive"
    ],
    "wof:name":"J T Brady & Assoc",
    "wof:placetype":"venue"
},
  "geometry": {"coordinates":[-80.05397000000001,40.622288],"type":"Point"}
}