{
  "type": "Feature",
  "properties": {
    "iso:country":"US",
    "sg:address":"3910 Caughey Rd",
    "sg:city":"Erie",
    "sg:classifiers":[
        {
            "category":"Health Services",
            "subcategory":"Clinic",
            "type":"Services"
        }
    ],
    "sg:phone":"+1 814 464 9200",
    "sg:postcode":"16506",
    "sg:province":"PA",
    "sg:tags":[
        "home",
        "care"
    ],
    "wof:name":"Home Instead Senior Care",
    "wof:placetype":"venue"
},
  "geometry": {"coordinates":[-80.14566600000001,42.07208],"type":"Point"}
}