{
  "type": "Feature",
  "properties": {
    "iso:country":"US",
    "sg:address":"225 Church St",
    "sg:city":"Phoenixville",
    "sg:classifiers":[
        {
            "category":"Shopping",
            "subcategory":"Florist",
            "type":"Retail Goods"
        }
    ],
    "sg:phone":"+1   ",
    "sg:postcode":"19460",
    "sg:province":"PA",
    "wof:name":"Nichols Flower Shop",
    "wof:placetype":"venue"
},
  "geometry": {"coordinates":[-75.51782900000001,40.132743],"type":"Point"}
}