{
  "type": "Feature",
  "properties": {
    "iso:country":"US",
    "sg:address":"1815 9th Ave",
    "sg:city":"Altoona",
    "sg:classifiers":[
        {
            "category":"Restaurant",
            "type":"Food & Drink"
        }
    ],
    "sg:phone":"+1 814 943 2299",
    "sg:postcode":"16602",
    "sg:province":"PA",
    "wof:name":"Pittsburgh Companies North Inc",
    "wof:placetype":"venue"
},
  "geometry": {"coordinates":[-78.403393,40.508835],"type":"Point"}
}