{
  "type": "Feature",
  "properties": {
    "addr:full":"2717 Estella Ave Montoursville PA 17754",
    "addr:housenumber":"2717",
    "addr:postcode":"17754",
    "addr:street":"Estella Ave",
    "iso:country":"US",
    "sg:address":"2717 Estella Ave",
    "sg:city":"Montoursville",
    "sg:classifiers":[
        {
            "category":"Shopping",
            "type":"Retail Goods"
        }
    ],
    "sg:phone":"+1 570 322 9754",
    "sg:postcode":"17754",
    "sg:province":"PA",
    "sg:tags":[
        "pet",
        "supply"
    ],
    "wof:name":"Kismet Enterprises",
    "wof:placetype":"venue"
},
  "geometry": {"coordinates":[-76.94965500000001,41.265116],"type":"Point"}
}