{
  "type": "Feature",
  "properties": {
    "addr:full":"22 Progress St East Stroudsburg PA 18301",
    "addr:housenumber":"22",
    "addr:postcode":"18301",
    "addr:street":"Progress St",
    "iso:country":"US",
    "sg:address":"22 Progress St",
    "sg:city":"East Stroudsburg",
    "sg:classifiers":[
        {
            "category":"Retail",
            "subcategory":"Auto Repair",
            "type":"Services"
        }
    ],
    "sg:phone":"+1   ",
    "sg:postcode":"18301",
    "sg:province":"PA",
    "sg:tags":[
        "glass",
        "replacement"
    ],
    "wof:name":"Safelite Autoglass",
    "wof:placetype":"venue"
},
  "geometry": {"coordinates":[-75.190849,41.018913],"type":"Point"}
}