{
  "type": "Feature",
  "properties": {
    "addr:full":"904 N Chester Rd West Chester PA 19380",
    "addr:housenumber":"904",
    "addr:postcode":"19380",
    "addr:street":"N Chester Rd",
    "iso:country":"US",
    "sg:address":"904 N Chester Rd",
    "sg:city":"West Chester",
    "sg:classifiers":[
        {
            "category":"Manufacturing",
            "subcategory":"Printing",
            "type":"Manufacturing & Wholesale Goods"
        }
    ],
    "sg:phone":"+1 610 696 2837",
    "sg:postcode":"19380",
    "sg:province":"PA",
    "sg:tags":[
        "commercial"
    ],
    "wof:name":"Maran Enterprises",
    "wof:placetype":"venue"
},
  "geometry": {"coordinates":[-75.544873,39.996051],"type":"Point"}
}