{
  "type": "Feature",
  "properties": {
    "iso:country":"US",
    "sg:address":"158 Grandview Rd",
    "sg:city":"Curwensville",
    "sg:classifiers":[
        {
            "category":"Building & Trades",
            "subcategory":"Construction",
            "type":"Services"
        }
    ],
    "sg:phone":"+1 814 236 2745",
    "sg:postcode":"16833",
    "sg:province":"PA",
    "sg:tags":[
        "paving",
        "asphalt",
        "contractor"
    ],
    "wof:name":"Donahue Asphalt Sealing",
    "wof:placetype":"venue"
},
  "geometry": {"coordinates":[-78.584046,40.927388],"type":"Point"}
}