{
  "type": "Feature",
  "properties": {
    "iso:country":"US",
    "sg:address":"8 Race St # &",
    "sg:city":"Philadelphia",
    "sg:classifiers":[
        {
            "category":"Health Services",
            "subcategory":"Doctor",
            "type":"Services"
        }
    ],
    "sg:phone":"+1 215 238 1330",
    "sg:postcode":"19106",
    "sg:province":"PA",
    "sg:tags":[
        "podiatrist"
    ],
    "wof:name":"Spadone Saml J DPM",
    "wof:placetype":"venue"
},
  "geometry": {"coordinates":[-75.147301,39.9473],"type":"Point"}
}