{
  "type": "Feature",
  "properties": {
    "iso:country":"US",
    "sg:address":"772 Pine Valley Dr",
    "sg:city":"Pittsburgh",
    "sg:classifiers":[
        {
            "category":"Real Estate",
            "subcategory":"Developer",
            "type":"Services"
        }
    ],
    "sg:phone":"+1 724 327 5755",
    "sg:postcode":"15239",
    "sg:province":"PA",
    "wof:name":"The Meritage Group",
    "wof:placetype":"venue"
},
  "geometry": {"coordinates":[-79.713284,40.455656],"type":"Point"}
}