{
  "type": "Feature",
  "properties": {
    "iso:country":"US",
    "sg:address":"275 Sugar Run Rd",
    "sg:city":"Waynesburg",
    "sg:classifiers":[
        {
            "category":"Building & Trades",
            "subcategory":"Construction",
            "type":"Services"
        }
    ],
    "sg:phone":"+1   ",
    "sg:postcode":"15370",
    "sg:province":"PA",
    "sg:tags":[
        "house"
    ],
    "wof:name":"Harold D Hennen",
    "wof:placetype":"venue"
},
  "geometry": {"coordinates":[-80.17591899999999,39.886132],"type":"Point"}
}