{
  "type": "Feature",
  "properties": {
    "iso:country":"US",
    "sg:address":"61 Statement St",
    "sg:city":"Washington",
    "sg:classifiers":[
        {
            "category":"Autos & Motor Vehicles",
            "subcategory":"Auto Supplies",
            "type":"Retail Goods"
        },
        {
            "category":"Retail",
            "subcategory":"Auto Repair",
            "type":"Services"
        }
    ],
    "sg:phone":"+1 724 222 2580",
    "sg:postcode":"15301",
    "sg:province":"PA",
    "sg:tags":[
        "automobile",
        "part",
        "truck"
    ],
    "sg:website":"http://clickserve.dartsearch.net/link/click?lid=43000000313868429&ds_s_kwgid=58000000006820725&ds_e_matchtype={MatchType}&ds_e_kwdid={OrderItemId}&ds_e_adid={AdId}&ds_url_v=2",
    "wof:name":"Marchand Auto",
    "wof:placetype":"venue"
},
  "geometry": {"coordinates":[-80.211749,40.157018],"type":"Point"}
}