{
  "type": "Feature",
  "properties": {
    "iso:country":"US",
    "sg:address":"455 N Main St",
    "sg:city":"Pittston",
    "sg:classifiers":[
        {
            "category":"Health Services",
            "subcategory":"Hospital",
            "type":"Services"
        }
    ],
    "sg:phone":"+1 570 655 4115",
    "sg:postcode":"18640",
    "sg:province":"PA",
    "sg:tags":[
        "dialysis"
    ],
    "wof:name":"Bma Pittston",
    "wof:placetype":"venue"
},
  "geometry": {"coordinates":[-75.786507,41.335309],"type":"Point"}
}