{
  "type": "Feature",
  "properties": {
    "iso:country":"US",
    "sg:address":"4793 W Chester Pike",
    "sg:city":"Newtown Square",
    "sg:classifiers":[
        {
            "category":"Wholesale",
            "subcategory":"Painting Supplies",
            "type":"Manufacturing & Wholesale Goods"
        }
    ],
    "sg:phone":"+1   ",
    "sg:postcode":"19073",
    "sg:province":"PA",
    "wof:name":"Sun-Ron Paint & Varnish Co",
    "wof:placetype":"venue"
},
  "geometry": {"coordinates":[-75.43924699999999,39.975445],"type":"Point"}
}