{
  "type": "Feature",
  "properties": {
    "iso:country":"US",
    "sg:address":"1284 Conewango Ave",
    "sg:city":"Warren",
    "sg:classifiers":[
        {
            "category":"Real Estate",
            "subcategory":"Real Estate Services",
            "type":"Services"
        },
        {
            "category":"Real Estate",
            "subcategory":"Real Estate Operator",
            "type":"Services"
        }
    ],
    "sg:phone":"+1 814 726 3030",
    "sg:postcode":"16365",
    "sg:province":"PA",
    "sg:tags":[
        "vacancy",
        "apartment",
        "rental",
        "finder",
        "listing"
    ],
    "wof:name":"Holly Apartments",
    "wof:placetype":"venue"
},
  "geometry": {"coordinates":[-79.146469,41.86937],"type":"Point"}
}