{
  "type": "Feature",
  "properties": {
    "iso:country":"US",
    "sg:address":"Cavasina Dr",
    "sg:city":"Canonsburg",
    "sg:classifiers":[
        {
            "category":"Restaurant",
            "type":"Food & Drink"
        }
    ],
    "sg:phone":"+1 724 745 3672",
    "sg:postcode":"15317",
    "sg:province":"PA",
    "sg:website":"www.ljsilvers.com",
    "wof:name":"Long John Silver's Seafood Shop",
    "wof:placetype":"venue"
},
  "geometry": {"coordinates":[-80.160896,40.270802],"type":"Point"}
}