{
  "type": "Feature",
  "properties": {
    "addr:full":"1459 Zarker St Harrisburg PA 17104",
    "addr:housenumber":"1459",
    "addr:postcode":"17104",
    "addr:street":"Zarker St",
    "iso:country":"US",
    "sg:address":"1459 Zarker St",
    "sg:city":"Harrisburg",
    "sg:classifiers":[
        {
            "category":"Restaurant",
            "type":"Food & Drink"
        }
    ],
    "sg:phone":"+1   ",
    "sg:postcode":"17104",
    "sg:province":"PA",
    "sg:tags":[
        "eating"
    ],
    "wof:name":"St Francis Soup Kitchen",
    "wof:placetype":"venue"
},
  "geometry": {"coordinates":[-76.86774200000001,40.265817],"type":"Point"}
}