{
  "type": "Feature",
  "properties": {
    "addr:full":"325 3rd St California PA 15419",
    "addr:housenumber":"325",
    "addr:postcode":"15419",
    "addr:street":"3Rd St",
    "iso:country":"US",
    "sg:address":"325 3rd St",
    "sg:city":"California",
    "sg:classifiers":[
        {
            "category":"Government",
            "subcategory":"Office",
            "type":"Public Place"
        }
    ],
    "sg:phone":"+1 724 938 8786",
    "sg:postcode":"15419",
    "sg:province":"PA",
    "sg:tags":[
        "city",
        "planning",
        "dev"
    ],
    "wof:name":"California Zoning Officer",
    "wof:placetype":"venue"
},
  "geometry": {"coordinates":[-79.89093699999999,40.066538],"type":"Point"}
}