{
  "type": "Feature",
  "properties": {
    "iso:country":"US",
    "sg:address":"5649 Brownsville Rd",
    "sg:city":"Pleasant Hills",
    "sg:classifiers":[
        {
            "category":"Travel",
            "subcategory":"Hotels & Motels",
            "type":"Entertainment"
        },
        {
            "category":"Bars & Pubs",
            "type":"Food & Drink"
        }
    ],
    "sg:phone":"+1 412 655 1913",
    "sg:postcode":"15236",
    "sg:province":"PA",
    "sg:tags":[
        "drinking",
        "eating",
        "operation"
    ],
    "wof:name":"Curry Hotel",
    "wof:placetype":"venue"
},
  "geometry": {"coordinates":[-79.985213,40.332664],"type":"Point"}
}