{
  "type": "Feature",
  "properties": {
    "iso:country":"US",
    "sg:address":"1115 Sembling Ave",
    "sg:city":"Pottstown",
    "sg:classifiers":[
        {
            "category":"Manufacturing",
            "subcategory":"Tools & Machinery",
            "type":"Manufacturing & Wholesale Goods"
        }
    ],
    "sg:phone":"+1   ",
    "sg:postcode":"19464",
    "sg:province":"PA",
    "sg:tags":[
        "shop",
        "job"
    ],
    "wof:name":"K & M Machine",
    "wof:placetype":"venue"
},
  "geometry": {"coordinates":[-75.627476,40.238763],"type":"Point"}
}