{
  "type": "Feature",
  "properties": {
    "addr:full":"1708 Wolfe Ave Braddock PA 15104",
    "addr:housenumber":"1708",
    "addr:postcode":"15104",
    "addr:street":"Wolfe Ave",
    "iso:country":"US",
    "sg:address":"1708 Wolfe Ave",
    "sg:city":"Braddock",
    "sg:classifiers":[
        {
            "category":"Building & Trades",
            "subcategory":"Construction",
            "type":"Services"
        }
    ],
    "sg:phone":"+1   ",
    "sg:postcode":"15104",
    "sg:province":"PA",
    "sg:tags":[
        "house"
    ],
    "wof:name":"Kozarian Construction",
    "wof:placetype":"venue"
},
  "geometry": {"coordinates":[-79.84279600000001,40.402125],"type":"Point"}
}