{
  "type": "Feature",
  "properties": {
    "addr:full":"256 Monocacy Dr Bath PA 18014",
    "addr:housenumber":"256",
    "addr:postcode":"18014",
    "addr:street":"Monocacy Dr",
    "iso:country":"US",
    "sg:address":"256 Monocacy Dr",
    "sg:city":"Bath",
    "sg:classifiers":[
        {
            "category":"Shopping",
            "subcategory":"Used Merchandise",
            "type":"Retail Goods"
        }
    ],
    "sg:phone":"+1 610 837 1761",
    "sg:postcode":"18014",
    "sg:province":"PA",
    "wof:name":"Red Barn",
    "wof:placetype":"venue"
},
  "geometry": {"coordinates":[-75.400338,40.747808],"type":"Point"}
}