{
  "type": "Feature",
  "properties": {
    "iso:country":"US",
    "sg:address":"3602 Golfview Dr",
    "sg:city":"Mechanicsburg",
    "sg:classifiers":[
        {
            "category":"Professional",
            "subcategory":"Computer Services",
            "type":"Services"
        }
    ],
    "sg:phone":"+1   ",
    "sg:postcode":"17050",
    "sg:province":"PA",
    "sg:tags":[
        "development",
        "software"
    ],
    "wof:name":"Strategic Trading Systems Inc",
    "wof:placetype":"venue"
},
  "geometry": {"coordinates":[-76.95754599999999,40.268013],"type":"Point"}
}