{
  "type": "Feature",
  "properties": {
    "iso:country":"US",
    "sg:address":"38 York St",
    "sg:city":"Newtown",
    "sg:classifiers":[
        {
            "category":"Building & Trades",
            "subcategory":"Construction",
            "type":"Services"
        }
    ],
    "sg:phone":"+1   ",
    "sg:postcode":"18940",
    "sg:province":"PA",
    "sg:tags":[
        "house"
    ],
    "wof:name":"Building Rnovation Specialists",
    "wof:placetype":"venue"
},
  "geometry": {"coordinates":[-74.95405700000001,40.218199],"type":"Point"}
}