{
  "type": "Feature",
  "properties": {
    "iso:country":"US",
    "sg:address":"1646 S 4th St",
    "sg:city":"Philadelphia",
    "sg:classifiers":[
        {
            "category":"Personal",
            "subcategory":"Adult",
            "type":"Services"
        }
    ],
    "sg:phone":"+1 215 218 0200",
    "sg:postcode":"19148",
    "sg:province":"PA",
    "sg:tags":[
        "escort"
    ],
    "wof:name":"Adam & Eve",
    "wof:placetype":"venue"
},
  "geometry": {"coordinates":[-75.152382,39.927709],"type":"Point"}
}