{
  "type": "Feature",
  "properties": {
    "iso:country":"US",
    "sg:address":"155 Hepler Rd",
    "sg:city":"Sarver",
    "sg:classifiers":[
        {
            "category":"Building & Trades",
            "subcategory":"Construction",
            "type":"Services"
        }
    ],
    "sg:phone":"+1   ",
    "sg:postcode":"16055",
    "sg:province":"PA",
    "sg:tags":[
        "carpentry",
        "contractor"
    ],
    "wof:name":"Timothy A Markwell",
    "wof:placetype":"venue"
},
  "geometry": {"coordinates":[-79.76172,40.715405],"type":"Point"}
}