{
  "type": "Feature",
  "properties": {
    "addr:full":"3602 Broadway Allentown PA 18104",
    "addr:housenumber":"3602",
    "addr:postcode":"18104",
    "addr:street":"Broadway",
    "iso:country":"US",
    "sg:address":"3602 Broadway",
    "sg:city":"Allentown",
    "sg:classifiers":[
        {
            "category":"Home & Garden",
            "subcategory":"Household Appliances",
            "type":"Retail Goods"
        }
    ],
    "sg:phone":"+1 610 395 3721",
    "sg:postcode":"18104",
    "sg:province":"PA",
    "wof:name":"Joseph I Haines Maytag Home",
    "wof:placetype":"venue"
},
  "geometry": {"coordinates":[-75.534156,40.58491],"type":"Point"}
}