{
  "type": "Feature",
  "properties": {
    "iso:country":"US",
    "sg:address":"4017 Washington Rd",
    "sg:city":"Mc Murray",
    "sg:classifiers":[
        {
            "category":"Professional",
            "type":"Services"
        }
    ],
    "sg:phone":"+1 724 942 4688",
    "sg:postcode":"15317",
    "sg:province":"PA",
    "sg:website":"www.seskeller.com",
    "wof:name":"Self-Empowerment Services",
    "wof:placetype":"venue"
},
  "geometry": {"coordinates":[-80.128236,40.270323],"type":"Point"}
}