{
  "type": "Feature",
  "properties": {
    "addr:full":"2159 Galloway Rd Bensalem PA 19020",
    "addr:housenumber":"2159",
    "addr:postcode":"19020",
    "addr:street":"Galloway Rd",
    "iso:country":"US",
    "sg:address":"2159 Galloway Rd",
    "sg:city":"Bensalem",
    "sg:classifiers":[
        {
            "category":"Shopping",
            "type":"Retail Goods"
        }
    ],
    "sg:phone":"+1 215 638 9004",
    "sg:postcode":"19020",
    "sg:province":"PA",
    "sg:tags":[
        "monument"
    ],
    "wof:name":"De Christopher Bros Inc",
    "wof:placetype":"venue"
},
  "geometry": {"coordinates":[-74.93638300000001,40.111067],"type":"Point"}
}