{
  "type": "Feature",
  "properties": {
    "addr:full":"1450 N 5th St Stroudsburg PA 18360",
    "addr:housenumber":"1450",
    "addr:postcode":"18360",
    "addr:street":"N 5Th St",
    "iso:country":"US",
    "sg:address":"1450 N 5th St",
    "sg:city":"Stroudsburg",
    "sg:classifiers":[
        {
            "category":"Food & Beverages",
            "subcategory":"Groceries & Convenience Stores",
            "type":"Retail Goods"
        },
        {
            "category":"Autos & Motor Vehicles",
            "subcategory":"Fuel & Gas Station",
            "type":"Retail Goods"
        }
    ],
    "sg:phone":"+1 570 424 8866",
    "sg:postcode":"18360",
    "sg:province":"PA",
    "sg:tags":[
        "gasoline"
    ],
    "wof:name":"Square One Markets Inc",
    "wof:placetype":"venue"
},
  "geometry": {"coordinates":[-75.19934499999999,41.00305],"type":"Point"}
}