{
  "type": "Feature",
  "properties": {
    "iso:country":"US",
    "sg:address":"301 S 4th St",
    "sg:city":"Emmaus",
    "sg:classifiers":[
        {
            "category":"Manufacturing",
            "subcategory":"Tools & Machinery",
            "type":"Manufacturing & Wholesale Goods"
        }
    ],
    "sg:phone":"+1 610 967 3550",
    "sg:postcode":"18049",
    "sg:province":"PA",
    "sg:tags":[
        "machine",
        "shop"
    ],
    "wof:name":"Schiller-Pfeiffer Machine Shop",
    "wof:placetype":"venue"
},
  "geometry": {"coordinates":[-75.488598,40.5305],"type":"Point"}
}