{
  "type": "Feature",
  "properties": {
    "iso:country":"US",
    "sg:address":"71 Pleasant Ln",
    "sg:city":"Levittown",
    "sg:classifiers":[
        {
            "category":"Manufacturing",
            "subcategory":"Tools & Machinery",
            "type":"Manufacturing & Wholesale Goods"
        }
    ],
    "sg:phone":"+1   ",
    "sg:postcode":"19054",
    "sg:province":"PA",
    "sg:tags":[
        "industrial",
        "mfg"
    ],
    "wof:name":"Wg Transport Inc",
    "wof:placetype":"venue"
},
  "geometry": {"coordinates":[-74.81859300000001,40.156405],"type":"Point"}
}