{
  "type": "Feature",
  "properties": {
    "iso:country":"US",
    "sg:address":"7464 Sharon-Mercer Rd",
    "sg:city":"Mercer",
    "sg:classifiers":[
        {
            "category":"Autos & Motor Vehicles",
            "subcategory":"Auto Supplies",
            "type":"Retail Goods"
        }
    ],
    "sg:phone":"+1 724 346 3559",
    "sg:postcode":"16137",
    "sg:province":"PA",
    "sg:tags":[
        "tire"
    ],
    "wof:name":"Flynn's Tire & Svc Ctr",
    "wof:placetype":"venue"
},
  "geometry": {"coordinates":[-80.33451100000001,41.23407],"type":"Point"}
}