{
  "type": "Feature",
  "properties": {
    "addr:full":"101 Herman Ave Lemoyne PA 17043",
    "addr:housenumber":"101",
    "addr:postcode":"17043",
    "addr:street":"Herman Ave",
    "iso:country":"US",
    "sg:address":"101 Herman Ave",
    "sg:city":"Lemoyne",
    "sg:classifiers":[
        {
            "category":"Building & Trades",
            "subcategory":"Construction",
            "type":"Services"
        }
    ],
    "sg:phone":"+1   ",
    "sg:postcode":"17043",
    "sg:province":"PA",
    "sg:tags":[
        "carpentry",
        "contractor"
    ],
    "wof:name":"Cary L Engle",
    "wof:placetype":"venue"
},
  "geometry": {"coordinates":[-76.88967,40.244274],"type":"Point"}
}