{
  "type": "Feature",
  "properties": {
    "addr:full":"2410 Swede Rd Norristown PA 19401",
    "addr:housenumber":"2410",
    "addr:postcode":"19401",
    "addr:street":"Swede Rd",
    "iso:country":"US",
    "sg:address":"2410 Swede Rd",
    "sg:city":"Norristown",
    "sg:classifiers":[
        {
            "category":"Building & Trades",
            "subcategory":"Construction",
            "type":"Services"
        }
    ],
    "sg:phone":"+1 610 275 8560",
    "sg:postcode":"19401",
    "sg:province":"PA",
    "sg:tags":[
        "installs",
        "equipment",
        "lift",
        "hydraulic"
    ],
    "sg:website":"www.ingerdog.com",
    "wof:name":"Norriton Hydraulics Inc",
    "wof:placetype":"venue"
},
  "geometry": {"coordinates":[-75.32802100000001,40.13896],"type":"Point"}
}