{
  "type": "Feature",
  "properties": {
    "iso:country":"US",
    "sg:address":"199 Folly Rd",
    "sg:city":"Chalfont",
    "sg:classifiers":[
        {
            "category":"Professional",
            "type":"Services"
        }
    ],
    "sg:phone":"+1   ",
    "sg:postcode":"18914",
    "sg:province":"PA",
    "wof:name":"Christmas Kingdom Inc",
    "wof:placetype":"venue"
},
  "geometry": {"coordinates":[-75.174525,40.24188],"type":"Point"}
}