{
  "type": "Feature",
  "properties": {
    "iso:country":"US",
    "sg:address":"117 Timber Rd",
    "sg:city":"Lebanon",
    "sg:classifiers":[
        {
            "category":"Restaurant",
            "type":"Food & Drink"
        }
    ],
    "sg:phone":"+1 717 964 1853",
    "sg:postcode":"17042",
    "sg:province":"PA",
    "sg:tags":[
        "pizza"
    ],
    "wof:name":"Mount Gretna Pizzeria",
    "wof:placetype":"venue"
},
  "geometry": {"coordinates":[-76.477547,40.248954],"type":"Point"}
}