{
  "type": "Feature",
  "properties": {
    "iso:country":"US",
    "sg:address":"264 Laurel Hill Rd",
    "sg:city":"Bangor",
    "sg:classifiers":[
        {
            "category":"Travel",
            "subcategory":"Campground",
            "type":"Entertainment"
        }
    ],
    "sg:phone":"+1 570 897 5811",
    "sg:postcode":"18013",
    "sg:province":"PA",
    "wof:name":"Hickory Lake Campground",
    "wof:placetype":"venue"
},
  "geometry": {"coordinates":[-75.148606,40.926141],"type":"Point"}
}