{
  "type": "Feature",
  "properties": {
    "iso:country":"US",
    "sg:address":"126 N Jefferson St",
    "sg:city":"Kittanning",
    "sg:classifiers":[
        {
            "category":"Autos & Motor Vehicles",
            "subcategory":"Automobile Sales",
            "type":"Retail Goods"
        }
    ],
    "sg:phone":"+1 724 543 1068",
    "sg:postcode":"16201",
    "sg:province":"PA",
    "sg:website":"www.walkermotor.com",
    "wof:name":"Walker Motor Co",
    "wof:placetype":"venue"
},
  "geometry": {"coordinates":[-79.519768,40.814177],"type":"Point"}
}