{
  "type": "Feature",
  "properties": {
    "addr:full":"2000 Market St Philadelphia PA 19103",
    "addr:housenumber":"2000",
    "addr:postcode":"19103",
    "addr:street":"Market St",
    "iso:country":"US",
    "sg:address":"2000 Market St",
    "sg:city":"Philadelphia",
    "sg:classifiers":[
        {
            "category":"Professional",
            "subcategory":"Detective & Security Services",
            "type":"Services"
        }
    ],
    "sg:phone":"+1 215 569 1730",
    "sg:postcode":"19103",
    "sg:province":"PA",
    "sg:tags":[
        "guard",
        "patrol"
    ],
    "wof:name":"Harvard Protection Services",
    "wof:placetype":"venue"
},
  "geometry": {"coordinates":[-75.17318,39.953571],"type":"Point"}
}