{
  "type": "Feature",
  "properties": {
    "addr:full":"638 Powder Mill Hollow Rd Boyertown PA 19512",
    "addr:housenumber":"638",
    "addr:postcode":"19512",
    "addr:street":"Powder Mill Hollow Rd",
    "iso:country":"US",
    "sg:address":"638 Powder Mill Hollow Rd",
    "sg:city":"Boyertown",
    "sg:classifiers":[
        {
            "category":"Professional",
            "subcategory":"Management & Consulting",
            "type":"Services"
        }
    ],
    "sg:phone":"+1 610 369 0004",
    "sg:postcode":"19512",
    "sg:province":"PA",
    "wof:name":"Furst Realty",
    "wof:placetype":"venue"
},
  "geometry": {"coordinates":[-75.68069199999999,40.340065],"type":"Point"}
}