{
  "type": "Feature",
  "properties": {
    "addr:full":"1513 E Woodlawn St Allentown PA 18109",
    "addr:housenumber":"1513",
    "addr:postcode":"18109",
    "addr:street":"E Woodlawn St",
    "iso:country":"US",
    "sg:address":"1513 E Woodlawn St",
    "sg:city":"Allentown",
    "sg:classifiers":[
        {
            "category":"Building & Trades",
            "subcategory":"Cleaning & Sanitation",
            "type":"Services"
        }
    ],
    "sg:phone":"+1 610 821 4916",
    "sg:postcode":"18109",
    "sg:province":"PA",
    "sg:tags":[
        "carpet"
    ],
    "sg:website":"www.cdtricity.com",
    "wof:name":"Chem Dry Tri-City",
    "wof:placetype":"venue"
},
  "geometry": {"coordinates":[-75.433998,40.6301],"type":"Point"}
}