{
  "type": "Feature",
  "properties": {
    "iso:country":"US",
    "sg:address":"137 Lakewood Rd",
    "sg:city":"New Castle",
    "sg:classifiers":[
        {
            "category":"Insurance",
            "subcategory":"Health Insurance",
            "type":"Services"
        }
    ],
    "sg:phone":"+1   ",
    "sg:postcode":"16101",
    "sg:province":"PA",
    "sg:tags":[
        "carrier"
    ],
    "wof:name":"Henrys Intarsia",
    "wof:placetype":"venue"
},
  "geometry": {"coordinates":[-80.300051,41.030294],"type":"Point"}
}