{
  "type": "Feature",
  "properties": {
    "addr:full":"1052 Darby Dr Morrisville PA 19067",
    "addr:housenumber":"1052",
    "addr:postcode":"19067",
    "addr:street":"Darby Dr",
    "iso:country":"US",
    "sg:address":"1052 Darby Dr",
    "sg:city":"Morrisville",
    "sg:classifiers":[
        {
            "category":"Real Estate",
            "subcategory":"Developer",
            "type":"Services"
        }
    ],
    "sg:phone":"+1   ",
    "sg:postcode":"19067",
    "sg:province":"PA",
    "wof:name":"CV Associates Inc",
    "wof:placetype":"venue"
},
  "geometry": {"coordinates":[-74.837965,40.215996],"type":"Point"}
}