{
  "type": "Feature",
  "properties": {
    "iso:country":"US",
    "sg:address":"207 Pennsylvania Ave",
    "sg:city":"Athens",
    "sg:classifiers":[
        {
            "category":"Organizations",
            "subcategory":"Religious Organization",
            "type":"Services"
        }
    ],
    "sg:phone":"+1 570 888 4000",
    "sg:postcode":"18810",
    "sg:province":"PA",
    "sg:tags":[
        "church"
    ],
    "wof:name":"His Majesty Fellowship",
    "wof:placetype":"venue"
},
  "geometry": {"coordinates":[-76.52557899999999,41.964376],"type":"Point"}
}