{
  "type": "Feature",
  "properties": {
    "iso:country":"US",
    "sg:address":"7034 Pleasant Valley Rd",
    "sg:city":"Irwin",
    "sg:classifiers":[
        {
            "category":"Home & Garden",
            "subcategory":"Building Materials",
            "type":"Retail Goods"
        },
        {
            "category":"Building & Trades",
            "subcategory":"Construction",
            "type":"Services"
        }
    ],
    "sg:phone":"+1 724 744 4361",
    "sg:postcode":"15642",
    "sg:province":"PA",
    "sg:tags":[
        "concrete",
        "staining",
        "contractor"
    ],
    "wof:name":"Stephen Tabak",
    "wof:placetype":"venue"
},
  "geometry": {"coordinates":[-79.67781100000001,40.368321],"type":"Point"}
}