{
  "type": "Feature",
  "properties": {
    "iso:country":"US",
    "sg:address":"1050 Saxonburg Blvd",
    "sg:city":"Glenshaw",
    "sg:classifiers":[
        {
            "category":"Real Estate",
            "subcategory":"Real Estate Operator",
            "type":"Services"
        }
    ],
    "sg:phone":"+1   ",
    "sg:postcode":"15116",
    "sg:province":"PA",
    "sg:tags":[
        "building",
        "apartment"
    ],
    "wof:name":"River Oaks Apts",
    "wof:placetype":"venue"
},
  "geometry": {"coordinates":[-79.937765,40.521616],"type":"Point"}
}