{
  "type": "Feature",
  "properties": {
    "iso:country":"US",
    "sg:address":"115 Gun Club Rd",
    "sg:city":"New Oxford",
    "sg:classifiers":[
        {
            "category":"Building & Trades",
            "subcategory":"Electrical",
            "type":"Services"
        }
    ],
    "sg:phone":"+1 717 624 8163",
    "sg:postcode":"17350",
    "sg:province":"PA",
    "sg:tags":[
        "electric",
        "contractor"
    ],
    "wof:name":"BEST Mechanical Contr",
    "wof:placetype":"venue"
},
  "geometry": {"coordinates":[-77.05197200000001,39.882593],"type":"Point"}
}