{
  "type": "Feature",
  "properties": {
    "iso:country":"US",
    "sg:address":"600 Willow Ave",
    "sg:city":"Honesdale",
    "sg:classifiers":[
        {
            "category":"Building & Trades",
            "subcategory":"Electrical",
            "type":"Services"
        }
    ],
    "sg:phone":"+1 570 226 1407",
    "sg:postcode":"18431",
    "sg:province":"PA",
    "sg:tags":[
        "electric",
        "contractor"
    ],
    "wof:name":"Cris-Tal Electric",
    "wof:placetype":"venue"
},
  "geometry": {"coordinates":[-75.239121,41.553112],"type":"Point"}
}