{
  "type": "Feature",
  "properties": {
    "iso:country":"US",
    "sg:address":"1900 Greentree Rd",
    "sg:city":"Pittsburgh",
    "sg:classifiers":[
        {
            "category":"Shopping",
            "subcategory":"Department Store",
            "type":"Retail Goods"
        }
    ],
    "sg:phone":"+1 412 341 1855",
    "sg:postcode":"15220",
    "sg:province":"PA",
    "sg:website":"www.marshallsonline.com",
    "wof:name":"Marshalls Department Store",
    "wof:placetype":"venue"
},
  "geometry": {"coordinates":[-80.067001,40.392899],"type":"Point"}
}