{
  "type": "Feature",
  "properties": {
    "iso:country":"US",
    "sg:address":"19 N Railroad St",
    "sg:city":"Myerstown",
    "sg:classifiers":[
        {
            "category":"Professional",
            "subcategory":"Computer Services",
            "type":"Services"
        }
    ],
    "sg:phone":"+1   ",
    "sg:postcode":"17067",
    "sg:province":"PA",
    "sg:tags":[
        "related"
    ],
    "wof:name":"Kingdom Consulting Ltd",
    "wof:placetype":"venue"
},
  "geometry": {"coordinates":[-76.30355900000001,40.376645],"type":"Point"}
}