{
  "type": "Feature",
  "properties": {
    "addr:full":"12 Leapson Ln Doylestown PA 18901",
    "addr:housenumber":"12",
    "addr:postcode":"18901",
    "addr:street":"Leapson Ln",
    "iso:country":"US",
    "sg:address":"12 Leapson Ln",
    "sg:city":"Doylestown",
    "sg:classifiers":[
        {
            "category":"Health Services",
            "subcategory":"Clinic",
            "type":"Services"
        },
        {
            "category":"Community Center",
            "type":"Public Place"
        }
    ],
    "sg:phone":"+1 215 489 0619",
    "sg:postcode":"18901",
    "sg:province":"PA",
    "sg:tags":[
        "medical"
    ],
    "wof:name":"Go For Services Inc",
    "wof:placetype":"venue"
},
  "geometry": {"coordinates":[-75.179474,40.285072],"type":"Point"}
}