{
  "type": "Feature",
  "properties": {
    "iso:country":"US",
    "sg:address":"21 S Main St",
    "sg:city":"Coopersburg",
    "sg:classifiers":[
        {
            "category":"Wholesale",
            "subcategory":"Farm Supplies",
            "type":"Manufacturing & Wholesale Goods"
        }
    ],
    "sg:phone":"+1 610 462 9731",
    "sg:postcode":"18036",
    "sg:province":"PA",
    "sg:tags":[
        "grain"
    ],
    "wof:name":"Good Earth Grains & Creamery, Inc.",
    "wof:placetype":"venue"
},
  "geometry": {"coordinates":[-75.391312,40.51078],"type":"Point"}
}