{
  "type": "Feature",
  "properties": {
    "iso:country":"US",
    "sg:address":"2545 Market St",
    "sg:city":"Aston",
    "sg:classifiers":[
        {
            "category":"Retail",
            "subcategory":"Auto Repair",
            "type":"Services"
        }
    ],
    "sg:phone":"+1 610 485 7090",
    "sg:postcode":"19014",
    "sg:province":"PA",
    "sg:tags":[
        "alternator",
        "automobile",
        "electrical",
        "truck",
        "generator"
    ],
    "wof:name":"Interstate Auto Electric Inc",
    "wof:placetype":"venue"
},
  "geometry": {"coordinates":[-75.424431,39.835944],"type":"Point"}
}