{
  "type": "Feature",
  "properties": {
    "iso:country":"US",
    "sg:address":"4701 Pine St",
    "sg:city":"Philadelphia",
    "sg:classifiers":[
        {
            "category":"Shopping",
            "subcategory":"Gifts & Souvenirs",
            "type":"Retail Goods"
        }
    ],
    "sg:phone":"+1 215 748 2244",
    "sg:postcode":"19143",
    "sg:province":"PA",
    "sg:tags":[
        "shop"
    ],
    "wof:name":"Nicole's Gifts",
    "wof:placetype":"venue"
},
  "geometry": {"coordinates":[-75.21834699999999,39.952552],"type":"Point"}
}