{
  "type": "Feature",
  "properties": {
    "iso:country":"US",
    "sg:address":"1897 Hanover Pike",
    "sg:city":"Littlestown",
    "sg:classifiers":[
        {
            "category":"Shopping",
            "subcategory":"Gifts & Souvenirs",
            "type":"Retail Goods"
        }
    ],
    "sg:phone":"+1   ",
    "sg:postcode":"17340",
    "sg:province":"PA",
    "sg:tags":[
        "sewing"
    ],
    "wof:name":"Quilt Patch Inc",
    "wof:placetype":"venue"
},
  "geometry": {"coordinates":[-77.031969,39.759832],"type":"Point"}
}