{
  "type": "Feature",
  "properties": {
    "iso:country":"US",
    "sg:address":"135 W Allen St",
    "sg:city":"Mechanicsburg",
    "sg:classifiers":[
        {
            "category":"Home & Garden",
            "subcategory":"Building Materials",
            "type":"Retail Goods"
        }
    ],
    "sg:phone":"+1 717 766 4773",
    "sg:postcode":"17055",
    "sg:province":"PA",
    "sg:tags":[
        "lumber"
    ],
    "sg:website":"www.eberlylumber.com",
    "wof:name":"Eberly Lumber Co",
    "wof:placetype":"venue"
},
  "geometry": {"coordinates":[-77.012063,40.213431],"type":"Point"}
}