{
  "type": "Feature",
  "properties": {
    "addr:full":"6409 Guyer Ave Philadelphia PA 19142",
    "addr:housenumber":"6409",
    "addr:postcode":"19142",
    "addr:street":"Guyer Ave",
    "iso:country":"US",
    "sg:address":"6409 Guyer Ave",
    "sg:city":"Philadelphia",
    "sg:classifiers":[
        {
            "category":"Professional",
            "type":"Services"
        }
    ],
    "sg:phone":"+1   ",
    "sg:postcode":"19142",
    "sg:province":"PA",
    "wof:name":"Joseph C Kolavage",
    "wof:placetype":"venue"
},
  "geometry": {"coordinates":[-75.227014,39.919567],"type":"Point"}
}