{
  "type": "Feature",
  "properties": {
    "iso:country":"US",
    "sg:address":"1602 N 52nd St",
    "sg:city":"Philadelphia",
    "sg:classifiers":[
        {
            "category":"Banks & Credit Unions",
            "subcategory":"Atm",
            "type":"Services"
        }
    ],
    "sg:phone":"+1 215 877 3657",
    "sg:postcode":"19131",
    "sg:province":"PA",
    "sg:tags":[
        "location"
    ],
    "wof:name":"Fast Cash Atm",
    "wof:placetype":"venue"
},
  "geometry": {"coordinates":[-75.22532099999999,39.97949],"type":"Point"}
}