{
  "type": "Feature",
  "properties": {
    "addr:full":"110 Atwood St Pittsburgh PA 15213",
    "addr:housenumber":"110",
    "addr:postcode":"15213",
    "addr:street":"Atwood St",
    "iso:country":"US",
    "sg:address":"110 Atwood St",
    "sg:city":"Pittsburgh",
    "sg:classifiers":[
        {
            "category":"Professional",
            "subcategory":"Accounting & Tax Preparation",
            "type":"Services"
        }
    ],
    "sg:phone":"+1 412 687 3602",
    "sg:postcode":"15213",
    "sg:province":"PA",
    "sg:tags":[
        "return",
        "filing"
    ],
    "wof:name":"Liberty Tax Svc",
    "wof:placetype":"venue"
},
  "geometry": {"coordinates":[-79.95818,40.441439],"type":"Point"}
}