{
  "type": "Feature",
  "properties": {
    "addr:full":"34 State St Erie PA 16501",
    "addr:housenumber":"34",
    "addr:postcode":"16501",
    "addr:street":"State St",
    "iso:country":"US",
    "sg:address":"34 State St",
    "sg:city":"Erie",
    "sg:classifiers":[
        {
            "category":"Recreation",
            "subcategory":"Marina",
            "type":"Entertainment"
        }
    ],
    "sg:phone":"+1 814 874 0698",
    "sg:postcode":"16501",
    "sg:province":"PA",
    "sg:tags":[
        "operation"
    ],
    "wof:name":"Wolverine Park Marina",
    "wof:placetype":"venue"
},
  "geometry": {"coordinates":[-80.08937,42.135847],"type":"Point"}
}