{
  "type": "Feature",
  "properties": {
    "addr:full":"941 Federal Ct Meadville PA 16335",
    "addr:housenumber":"941",
    "addr:postcode":"16335",
    "addr:street":"Federal Ct",
    "iso:country":"US",
    "sg:address":"941 Federal Ct",
    "sg:city":"Meadville",
    "sg:classifiers":[
        {
            "category":"Professional",
            "subcategory":"Lawyer & Legal Services",
            "type":"Services"
        }
    ],
    "sg:phone":"+1 814 337 7662",
    "sg:postcode":"16335",
    "sg:province":"PA",
    "sg:tags":[
        "attorney"
    ],
    "wof:name":"Mary Ann Kirkpatrick",
    "wof:placetype":"venue"
},
  "geometry": {"coordinates":[-80.151832,41.637226],"type":"Point"}
}