{
  "type": "Feature",
  "properties": {
    "iso:country":"US",
    "sg:address":"24 S New St",
    "sg:city":"West Chester",
    "sg:classifiers":[
        {
            "category":"Real Estate",
            "subcategory":"Real Estate Agent",
            "type":"Services"
        }
    ],
    "sg:phone":"+1 610 692 2755",
    "sg:postcode":"19382",
    "sg:province":"PA",
    "wof:name":"Glenn Associates Realtor",
    "wof:placetype":"venue"
},
  "geometry": {"coordinates":[-75.60770599999999,39.956796],"type":"Point"}
}