{
  "type": "Feature",
  "properties": {
    "addr:full":"111 W 2nd Ave Derry PA 15627",
    "addr:housenumber":"111",
    "addr:postcode":"15627",
    "addr:street":"W 2Nd Ave",
    "iso:country":"US",
    "sg:address":"111 W 2nd Ave",
    "sg:city":"Derry",
    "sg:classifiers":[
        {
            "category":"Organizations",
            "subcategory":"Community Association",
            "type":"Services"
        }
    ],
    "sg:phone":"+1 724 694 2410",
    "sg:postcode":"15627",
    "sg:province":"PA",
    "wof:name":"American Legion",
    "wof:placetype":"venue"
},
  "geometry": {"coordinates":[-79.299446,40.33267],"type":"Point"}
}