{
  "type": "Feature",
  "properties": {
    "iso:country":"US",
    "sg:address":"721 Philadelphia St",
    "sg:city":"Indiana",
    "sg:classifiers":[
        {
            "category":"Shopping",
            "subcategory":"Florist",
            "type":"Retail Goods"
        }
    ],
    "sg:phone":"+1   ",
    "sg:postcode":"15701",
    "sg:province":"PA",
    "wof:name":"Flower Boutique",
    "wof:placetype":"venue"
},
  "geometry": {"coordinates":[-79.154455,40.623047],"type":"Point"}
}