{
  "type": "Feature",
  "properties": {
    "addr:full":"1513 N Cameron St Harrisburg PA 17101",
    "addr:housenumber":"1513",
    "addr:postcode":"17101",
    "addr:street":"N Cameron St",
    "iso:country":"US",
    "sg:address":"1513 N Cameron St",
    "sg:city":"Harrisburg",
    "sg:classifiers":[
        {
            "category":"Building & Trades",
            "subcategory":"Construction",
            "type":"Services"
        }
    ],
    "sg:phone":"+1 717 233 2552",
    "sg:postcode":"17101",
    "sg:province":"PA",
    "sg:tags":[
        "general",
        "contractor"
    ],
    "wof:name":"B K Engineers & Constructors",
    "wof:placetype":"venue"
},
  "geometry": {"coordinates":[-76.879695,40.279565],"type":"Point"}
}