{
  "type": "Feature",
  "properties": {
    "iso:country":"US",
    "sg:address":"719 Marietta Ave",
    "sg:city":"Lancaster",
    "sg:classifiers":[
        {
            "category":"Organizations",
            "subcategory":"Religious Organization",
            "type":"Services"
        }
    ],
    "sg:phone":"+1 717 392 7021",
    "sg:postcode":"17603",
    "sg:province":"PA",
    "sg:tags":[
        "church"
    ],
    "wof:name":"St Luke's United Church-Christ",
    "wof:placetype":"venue"
},
  "geometry": {"coordinates":[-76.318489,40.038395],"type":"Point"}
}