{
  "type": "Feature",
  "properties": {
    "iso:country":"US",
    "sg:address":"5563 Acorn Dr",
    "sg:city":"Emmaus",
    "sg:classifiers":[
        {
            "category":"Manufacturing",
            "subcategory":"Toys & Sporting Goods",
            "type":"Manufacturing & Wholesale Goods"
        }
    ],
    "sg:phone":"+1 610 967 2964",
    "sg:postcode":"18049",
    "sg:province":"PA",
    "sg:tags":[
        "s",
        "mfg"
    ],
    "sg:website":"www.tranquilitytreefarm.com",
    "wof:name":"Tranquility Tree Farm",
    "wof:placetype":"venue"
},
  "geometry": {"coordinates":[-75.47828,40.506339],"type":"Point"}
}