{
  "type": "Feature",
  "properties": {
    "iso:country":"US",
    "sg:address":"290 Hilltop Dr",
    "sg:city":"Cheswick",
    "sg:classifiers":[
        {
            "category":"Insurance",
            "subcategory":"Hazard Insurance",
            "type":"Services"
        }
    ],
    "sg:phone":"+1 412 767 4325",
    "sg:postcode":"15024",
    "sg:province":"PA",
    "wof:name":"Rodney Young",
    "wof:placetype":"venue"
},
  "geometry": {"coordinates":[-79.877664,40.582347],"type":"Point"}
}