{
  "type": "Feature",
  "properties": {
    "iso:country":"US",
    "sg:address":"355 E Main St",
    "sg:city":"Norristown",
    "sg:classifiers":[
        {
            "category":"Professional",
            "subcategory":"Accounting & Tax Preparation",
            "type":"Services"
        }
    ],
    "sg:phone":"+1 610 239 0400",
    "sg:postcode":"19401",
    "sg:province":"PA",
    "sg:tags":[
        "return",
        "filing"
    ],
    "wof:name":"Liberty Tax Svc",
    "wof:placetype":"venue"
},
  "geometry": {"coordinates":[-75.338921,40.112611],"type":"Point"}
}