{
  "type": "Feature",
  "properties": {
    "iso:country":"US",
    "sg:address":"7921 Grayson Rd",
    "sg:city":"Harrisburg",
    "sg:classifiers":[
        {
            "category":"Education",
            "subcategory":"Dance Studio",
            "type":"Public Place"
        }
    ],
    "sg:phone":"+1 717 558 0519",
    "sg:postcode":"17111",
    "sg:province":"PA",
    "sg:tags":[
        "instruction",
        "dancing"
    ],
    "wof:name":"Company Dance",
    "wof:placetype":"venue"
},
  "geometry": {"coordinates":[-76.749768,40.26289],"type":"Point"}
}