{
  "type": "Feature",
  "properties": {
    "addr:full":"241 Church Rd Wexford PA 15090",
    "addr:housenumber":"241",
    "addr:postcode":"15090",
    "addr:street":"Church Rd",
    "iso:country":"US",
    "sg:address":"241 Church Rd",
    "sg:city":"Wexford",
    "sg:classifiers":[
        {
            "category":"Retail",
            "subcategory":"Auto Repair",
            "type":"Services"
        }
    ],
    "sg:phone":"+1 724 935 3790",
    "sg:postcode":"15090",
    "sg:province":"PA",
    "sg:tags":[
        "body",
        "shop",
        "painting",
        "automobile"
    ],
    "wof:name":"Palermo Guy R Auto Body",
    "wof:placetype":"venue"
},
  "geometry": {"coordinates":[-80.056099,40.627701],"type":"Point"}
}