{
  "type": "Feature",
  "properties": {
    "addr:full":"100 Club House Ln Pittsburgh PA 15237",
    "addr:housenumber":"100",
    "addr:postcode":"15237",
    "addr:street":"Club House Ln",
    "iso:country":"US",
    "sg:address":"100 Club House Ln",
    "sg:city":"Pittsburgh",
    "sg:classifiers":[
        {
            "category":"Real Estate",
            "subcategory":"Real Estate Agent",
            "type":"Services"
        }
    ],
    "sg:phone":"+1 412 487 3087",
    "sg:postcode":"15237",
    "sg:province":"PA",
    "wof:name":"Woodbridge Council",
    "wof:placetype":"venue"
},
  "geometry": {"coordinates":[-79.991215,40.515409],"type":"Point"}
}