{
  "type": "Feature",
  "properties": {
    "iso:country":"US",
    "sg:address":"4017 Washington Rd",
    "sg:city":"Canonsburg",
    "sg:classifiers":[
        {
            "category":"Place Of Worship",
            "subcategory":"Church",
            "type":"Public Place"
        },
        {
            "category":"Place Of Worship",
            "type":"Public Place"
        }
    ],
    "sg:phone":"+1 724 941 2024",
    "sg:postcode":"15317",
    "sg:province":"PA",
    "sg:tags":[
        "christ",
        "churches-community"
    ],
    "wof:name":"Chartiers Creek Community",
    "wof:placetype":"venue"
},
  "geometry": {"coordinates":[-80.12896600000001,40.267215],"type":"Point"}
}