{
  "type": "Feature",
  "properties": {
    "iso:country":"US",
    "sg:address":"223 N Duke St",
    "sg:city":"Lancaster",
    "sg:classifiers":[
        {
            "category":"Professional",
            "subcategory":"Lawyer & Legal Services",
            "type":"Services"
        }
    ],
    "sg:phone":"+1   ",
    "sg:postcode":"17602",
    "sg:province":"PA",
    "wof:name":"Hagelgans James D",
    "wof:placetype":"venue"
},
  "geometry": {"coordinates":[-76.30425099999999,40.041435],"type":"Point"}
}