{
  "type": "Feature",
  "properties": {
    "iso:country":"US",
    "sg:address":"925 Lewisberry Rd",
    "sg:city":"Lewisberry",
    "sg:classifiers":[
        {
            "category":"Autos & Motor Vehicles",
            "subcategory":"Automobile Sales",
            "type":"Retail Goods"
        }
    ],
    "sg:phone":"+1 717 932 5061",
    "sg:postcode":"17339",
    "sg:province":"PA",
    "sg:tags":[
        "classic"
    ],
    "wof:name":"ABC Auto II Inc",
    "wof:placetype":"venue"
},
  "geometry": {"coordinates":[-76.869664,40.140283],"type":"Point"}
}