{
  "type": "Feature",
  "properties": {
    "iso:country":"US",
    "sg:address":"401 Lysle Blvd",
    "sg:city":"Mckeesport",
    "sg:classifiers":[
        {
            "category":"Retail",
            "subcategory":"Car Wash",
            "type":"Services"
        },
        {
            "category":"Retail",
            "subcategory":"Auto Repair",
            "type":"Services"
        }
    ],
    "sg:phone":"+1 412 673 4098",
    "sg:postcode":"15132",
    "sg:province":"PA",
    "sg:tags":[
        "body",
        "repairing",
        "painting",
        "carwash",
        "automobile"
    ],
    "wof:name":"Bill Andrejko Auto Detailing &",
    "wof:placetype":"venue"
},
  "geometry": {"coordinates":[-79.86322,40.351749],"type":"Point"}
}