{
  "type": "Feature",
  "properties": {
    "iso:country":"US",
    "sg:address":"7929 Mc Gill Rd",
    "sg:city":"Harborcreek",
    "sg:classifiers":[
        {
            "category":"Organizations",
            "subcategory":"Religious Organization",
            "type":"Services"
        }
    ],
    "sg:phone":"+1 814 899 5962",
    "sg:postcode":"16421",
    "sg:province":"PA",
    "sg:tags":[
        "church"
    ],
    "sg:website":"www.southharborcreek.org",
    "wof:name":"South Harborcreek United Methd",
    "wof:placetype":"venue"
},
  "geometry": {"coordinates":[-79.93877500000001,42.151127],"type":"Point"}
}