{
  "type": "Feature",
  "properties": {
    "iso:country":"US",
    "sg:address":"4375 Newburg Rd",
    "sg:city":"Nazareth",
    "sg:classifiers":[
        {
            "category":"Retail",
            "subcategory":"Auto Repair",
            "type":"Services"
        }
    ],
    "sg:phone":"+1   ",
    "sg:postcode":"18064",
    "sg:province":"PA",
    "sg:tags":[
        "transmission",
        "general"
    ],
    "wof:name":"Stahleys Garage",
    "wof:placetype":"venue"
},
  "geometry": {"coordinates":[-75.334101,40.70454],"type":"Point"}
}