{
  "type": "Feature",
  "properties": {
    "addr:full":"702 S Prince St Lancaster PA 17603",
    "addr:housenumber":"702",
    "addr:postcode":"17603",
    "addr:street":"S Prince St",
    "iso:country":"US",
    "sg:address":"702 S Prince St",
    "sg:city":"Lancaster",
    "sg:classifiers":[
        {
            "category":"Wholesale",
            "subcategory":"Scrap",
            "type":"Manufacturing & Wholesale Goods"
        }
    ],
    "sg:phone":"+1 717 396 9999",
    "sg:postcode":"17603",
    "sg:province":"PA",
    "sg:tags":[
        "material"
    ],
    "sg:website":"www.wastemanagement.com",
    "wof:name":"Dixon Recyclers",
    "wof:placetype":"venue"
},
  "geometry": {"coordinates":[-76.30538199999999,40.025062],"type":"Point"}
}