{
  "type": "Feature",
  "properties": {
    "iso:country":"US",
    "sg:address":"410 Jacksonville Rd",
    "sg:city":"Warminster",
    "sg:classifiers":[
        {
            "category":"Restaurant",
            "type":"Food & Drink"
        }
    ],
    "sg:menulink":"http://www.allmenus.com/pa/northampton/37427-joe--tinas-pizzeria-italian-restaurant-iii/menu/",
    "sg:phone":"+1 215 328 9113",
    "sg:postcode":"18974",
    "sg:province":"PA",
    "sg:tags":[
        "american",
        "pizza"
    ],
    "wof:name":"Joe & Tina's Pizzeria Italian Restaurant III",
    "wof:placetype":"venue"
},
  "geometry": {"coordinates":[-75.053974,40.222526],"type":"Point"}
}