{
  "type": "Feature",
  "properties": {
    "iso:country":"US",
    "sg:address":"291 Oaktree Dr",
    "sg:city":"Levittown",
    "sg:classifiers":[
        {
            "category":"Retail",
            "subcategory":"Repair Shop",
            "type":"Services"
        }
    ],
    "sg:phone":"+1   ",
    "sg:postcode":"19055",
    "sg:province":"PA",
    "wof:name":"All Pro Tank Service Inc",
    "wof:placetype":"venue"
},
  "geometry": {"coordinates":[-74.842181,40.147338],"type":"Point"}
}