{
  "type": "Feature",
  "properties": {
    "iso:country":"US",
    "sg:address":"170 N Depaoli Rd",
    "sg:city":"Mc Donald",
    "sg:classifiers":[
        {
            "category":"Building & Trades",
            "subcategory":"Construction",
            "type":"Services"
        }
    ],
    "sg:phone":"+1   ",
    "sg:postcode":"15057",
    "sg:province":"PA",
    "sg:tags":[
        "house"
    ],
    "wof:name":"Andreis GA Home Rmdlg & Bldg",
    "wof:placetype":"venue"
},
  "geometry": {"coordinates":[-80.200688,40.335652],"type":"Point"}
}