{
  "type": "Feature",
  "properties": {
    "iso:country":"US",
    "sg:address":"4716 Ellsworth Ave",
    "sg:city":"Pittsburgh",
    "sg:classifiers":[
        {
            "category":"Health Services",
            "subcategory":"Health Practitioner",
            "type":"Services"
        }
    ],
    "sg:phone":"+1 412 682 0433",
    "sg:postcode":"15213",
    "sg:province":"PA",
    "wof:name":"Lorrie E Rabin PHD",
    "wof:placetype":"venue"
},
  "geometry": {"coordinates":[-79.946684,40.448789],"type":"Point"}
}