{
  "type": "Feature",
  "properties": {
    "iso:country":"US",
    "sg:address":"1802 E Ohio St ",
    "sg:city":"Pittsburgh",
    "sg:classifiers":[
        {
            "category":"Restaurant",
            "type":"Food & Drink"
        }
    ],
    "sg:menulink":"http://www.allmenus.com/pa/pittsburgh/287525-rons-pizza-palace/menu/",
    "sg:phone":"+1 412 231 7699",
    "sg:postcode":"15212",
    "sg:province":"PA",
    "sg:tags":[
        "american",
        "pizza"
    ],
    "wof:name":"Ron's Pizza Palace",
    "wof:placetype":"venue"
},
  "geometry": {"coordinates":[-79.98044299999999,40.464245],"type":"Point"}
}