{
  "type": "Feature",
  "properties": {
    "addr:full":"1109 Collegeville Rd Collegeville PA 19426",
    "addr:housenumber":"1109",
    "addr:postcode":"19426",
    "addr:street":"Collegeville Rd",
    "iso:country":"US",
    "sg:address":"1109 Collegeville Rd",
    "sg:city":"Collegeville",
    "sg:classifiers":[
        {
            "category":"Professional",
            "subcategory":"Business Services",
            "type":"Services"
        }
    ],
    "sg:phone":"+1   ",
    "sg:postcode":"19426",
    "sg:province":"PA",
    "wof:name":"Tla Signs",
    "wof:placetype":"venue"
},
  "geometry": {"coordinates":[-75.407815,40.214673],"type":"Point"}
}