{
  "type": "Feature",
  "properties": {
    "addr:full":"715 Arlington Ave Jeannette PA 15644",
    "addr:housenumber":"715",
    "addr:postcode":"15644",
    "addr:street":"Arlington Ave",
    "iso:country":"US",
    "sg:address":"715 Arlington Ave",
    "sg:city":"Jeannette",
    "sg:phone":"+1 724 523 2633",
    "sg:postcode":"15644",
    "sg:province":"PA",
    "sg:tags":[
        "equipment",
        "station"
    ],
    "wof:name":"Kifer & Son-Robert E De Lozier",
    "wof:placetype":"venue"
},
  "geometry": {"coordinates":[-79.60618700000001,40.332919],"type":"Point"}
}