{
  "type": "Feature",
  "properties": {
    "iso:country":"US",
    "sg:address":"284 Kernel Ln",
    "sg:city":"Etters",
    "sg:classifiers":[
        {
            "category":"Autos & Motor Vehicles",
            "subcategory":"Automobile Sales",
            "type":"Retail Goods"
        }
    ],
    "sg:phone":"+1   ",
    "sg:postcode":"17319",
    "sg:province":"PA",
    "wof:name":"Taylor Sales & Marketing",
    "wof:placetype":"venue"
},
  "geometry": {"coordinates":[-76.803675,40.170902],"type":"Point"}
}