{
  "type": "Feature",
  "properties": {
    "iso:country":"US",
    "sg:address":"850 N Church St",
    "sg:city":"Hazleton",
    "sg:classifiers":[
        {
            "category":"Retail",
            "subcategory":"Laundry & Dry Cleaning",
            "type":"Services"
        },
        {
            "category":"Shopping",
            "subcategory":"Clothing, Apparel, & Fashions",
            "type":"Retail Goods"
        }
    ],
    "sg:phone":"+1 570 459 1350",
    "sg:postcode":"18201",
    "sg:province":"PA",
    "sg:tags":[
        "alteration"
    ],
    "wof:name":"J D Sewing Productions",
    "wof:placetype":"venue"
},
  "geometry": {"coordinates":[-75.977099,40.969493],"type":"Point"}
}