{
  "type": "Feature",
  "properties": {
    "iso:country":"US",
    "sg:address":"2400 Chestnut St",
    "sg:city":"Philadelphia",
    "sg:classifiers":[
        {
            "category":"Building & Trades",
            "subcategory":"Locksmith",
            "type":"Services"
        }
    ],
    "sg:phone":"+1 267 238 9835",
    "sg:postcode":"19103",
    "sg:province":"PA",
    "sg:tags":[
        "key"
    ],
    "wof:name":"Always Available Emergency Locksmith",
    "wof:placetype":"venue"
},
  "geometry": {"coordinates":[-75.179174,39.952614],"type":"Point"}
}