{
  "type": "Feature",
  "properties": {
    "addr:full":"226 Mulberry St Darby PA 19023",
    "addr:housenumber":"226",
    "addr:postcode":"19023",
    "addr:street":"Mulberry St",
    "iso:country":"US",
    "sg:address":"226 Mulberry St",
    "sg:city":"Darby",
    "sg:classifiers":[
        {
            "category":"Personal",
            "subcategory":"Beauty Salon",
            "type":"Services"
        }
    ],
    "sg:phone":"+1 610 583 9220",
    "sg:postcode":"19023",
    "sg:province":"PA",
    "wof:name":"Rose Segars Beauty Shop",
    "wof:placetype":"venue"
},
  "geometry": {"coordinates":[-75.259179,39.923228],"type":"Point"}
}