{
  "type": "Feature",
  "properties": {
    "addr:full":"100 Arentzen Blvd Charleroi PA 15022",
    "addr:housenumber":"100",
    "addr:postcode":"15022",
    "addr:street":"Arentzen Blvd",
    "iso:country":"US",
    "sg:address":"100 Arentzen Blvd",
    "sg:city":"Charleroi",
    "sg:classifiers":[
        {
            "category":"Bus Charters",
            "type":"Transportation"
        }
    ],
    "sg:phone":"+1 724 489 4418",
    "sg:postcode":"15022",
    "sg:province":"PA",
    "wof:name":"88 Transit Lines Inc",
    "wof:placetype":"venue"
},
  "geometry": {"coordinates":[-79.88766699999999,40.126103],"type":"Point"}
}