{
  "type": "Feature",
  "properties": {
    "iso:country":"US",
    "sg:address":"51 E Main St",
    "sg:city":"Plainfield",
    "sg:classifiers":[
        {
            "category":"Organizations",
            "subcategory":"Religious Organization",
            "type":"Services"
        }
    ],
    "sg:phone":"+1 717 243 1134",
    "sg:postcode":"17013",
    "sg:province":"PA",
    "sg:tags":[
        "church"
    ],
    "wof:name":"Living Waters Tabernacle",
    "wof:placetype":"venue"
},
  "geometry": {"coordinates":[-77.27613100000001,40.201979],"type":"Point"}
}