{
  "type": "Feature",
  "properties": {
    "iso:country":"US",
    "sg:address":"577 Kromer Ave",
    "sg:city":"Berwyn",
    "sg:classifiers":[
        {
            "category":"Professional",
            "type":"Services"
        }
    ],
    "sg:phone":"+1   ",
    "sg:postcode":"19312",
    "sg:province":"PA",
    "wof:name":"Santoleri Associates",
    "wof:placetype":"venue"
},
  "geometry": {"coordinates":[-75.440298,40.050184],"type":"Point"}
}