{
  "type": "Feature",
  "properties": {
    "iso:country":"US",
    "sg:address":"1373 Washington Pike",
    "sg:city":"Bridgeville",
    "sg:classifiers":[
        {
            "category":"Professional",
            "subcategory":"Accounting & Tax Preparation",
            "type":"Services"
        }
    ],
    "sg:phone":"+1   ",
    "sg:postcode":"15017",
    "sg:province":"PA",
    "wof:name":"Jackley Larry W CPA",
    "wof:placetype":"venue"
},
  "geometry": {"coordinates":[-80.097855,40.376177],"type":"Point"}
}