{
  "type": "Feature",
  "properties": {
    "iso:country":"US",
    "sg:address":"2101 N 59th St",
    "sg:city":"Philadelphia",
    "sg:classifiers":[
        {
            "category":"Restaurant",
            "type":"Food & Drink"
        }
    ],
    "sg:phone":"+1 215 879 8100",
    "sg:postcode":"19131",
    "sg:province":"PA",
    "wof:name":"Three Stars Pizza",
    "wof:placetype":"venue"
},
  "geometry": {"coordinates":[-75.24109199999999,39.986404],"type":"Point"}
}