{
  "type": "Feature",
  "properties": {
    "addr:full":"4 Terry Dr Newtown PA 18940",
    "addr:housenumber":"4",
    "addr:postcode":"18940",
    "addr:street":"Terry Dr",
    "iso:country":"US",
    "sg:address":"4 Terry Dr",
    "sg:city":"Newtown",
    "sg:classifiers":[
        {
            "category":"Professional",
            "type":"Services"
        },
        {
            "category":"Professional",
            "subcategory":"Lawyer & Legal Services",
            "type":"Services"
        }
    ],
    "sg:phone":"+1 215 860 8200",
    "sg:postcode":"18940",
    "sg:province":"PA",
    "sg:tags":[
        "attorney",
        "family",
        "divorce",
        "assistance",
        "mediation",
        "child",
        "law",
        "custody"
    ],
    "sg:website":"http://www.pgordonlawoffice.com",
    "wof:name":"Gordon Patricia",
    "wof:placetype":"venue"
},
  "geometry": {"coordinates":[-74.918494,40.229114],"type":"Point"}
}