{
  "type": "Feature",
  "properties": {
    "iso:country":"US",
    "sg:address":"3406 State Rte 136",
    "sg:city":"Finleyville",
    "sg:classifiers":[
        {
            "category":"Professional",
            "type":"Services"
        }
    ],
    "sg:phone":"+1   ",
    "sg:postcode":"15332",
    "sg:province":"PA",
    "wof:name":"Michael Thieret",
    "wof:placetype":"venue"
},
  "geometry": {"coordinates":[-80.00256,40.19606],"type":"Point"}
}