{
  "type": "Feature",
  "properties": {
    "addr:full":"1 S Market St Selinsgrove PA 17870",
    "addr:housenumber":"1",
    "addr:postcode":"17870",
    "addr:street":"S Market St",
    "iso:country":"US",
    "sg:address":"1 S Market St",
    "sg:city":"Selinsgrove",
    "sg:classifiers":[
        {
            "category":"Restaurant",
            "type":"Food & Drink"
        }
    ],
    "sg:phone":"+1 570 374 7885",
    "sg:postcode":"17870",
    "sg:province":"PA",
    "sg:tags":[
        "eating"
    ],
    "wof:name":"Kinfolks Family Restaurant",
    "wof:placetype":"venue"
},
  "geometry": {"coordinates":[-76.861964,40.799389],"type":"Point"}
}