{
  "type": "Feature",
  "properties": {
    "iso:country":"US",
    "sg:address":"3501 W Chester Pike",
    "sg:city":"Newtown Square",
    "sg:classifiers":[
        {
            "category":"Health Services",
            "subcategory":"Doctor",
            "type":"Services"
        }
    ],
    "sg:phone":"+1   ",
    "sg:postcode":"19073",
    "sg:province":"PA",
    "sg:tags":[
        "surgeon",
        "oral"
    ],
    "wof:name":"Maxillo Facial Surgeons Ltd",
    "wof:placetype":"venue"
},
  "geometry": {"coordinates":[-75.394308,39.985419],"type":"Point"}
}