{
  "type": "Feature",
  "properties": {
    "iso:country":"US",
    "sg:address":"92 School House Ln",
    "sg:city":"Turbotville",
    "sg:classifiers":[
        {
            "category":"Manufacturing",
            "subcategory":"Food",
            "type":"Manufacturing & Wholesale Goods"
        },
        {
            "category":"Farming",
            "subcategory":"Farm",
            "type":"Manufacturing & Wholesale Goods"
        }
    ],
    "sg:phone":"+1 570 649 5725",
    "sg:postcode":"17772",
    "sg:province":"PA",
    "sg:tags":[
        "corn",
        "product"
    ],
    "wof:name":"Leroy Cotner",
    "wof:placetype":"venue"
},
  "geometry": {"coordinates":[-76.705016,41.111512],"type":"Point"}
}