{
  "type": "Feature",
  "properties": {
    "addr:full":"607 Stamford Dr Greensburg PA 15601",
    "addr:housenumber":"607",
    "addr:postcode":"15601",
    "addr:street":"Stamford Dr",
    "iso:country":"US",
    "sg:address":"607 Stamford Dr",
    "sg:city":"Greensburg",
    "sg:classifiers":[
        {
            "category":"Insurance",
            "subcategory":"Hazard Insurance",
            "type":"Services"
        }
    ],
    "sg:phone":"+1 724 837 0598",
    "sg:postcode":"15601",
    "sg:province":"PA",
    "sg:tags":[
        "commercial",
        "business"
    ],
    "wof:name":"Davidson Insurance Service",
    "wof:placetype":"venue"
},
  "geometry": {"coordinates":[-79.51483,40.26971],"type":"Point"}
}