{
  "type": "Feature",
  "properties": {
    "iso:country":"US",
    "sg:address":"2 Ppg Pl Ste 400",
    "sg:city":"Pittsburgh",
    "sg:classifiers":[
        {
            "category":"Professional",
            "subcategory":"Lawyer & Legal Services",
            "type":"Services"
        }
    ],
    "sg:phone":"+1 412 392 5264",
    "sg:postcode":"15222",
    "sg:province":"PA",
    "wof:name":"Mroz Kenneth S",
    "wof:placetype":"venue"
},
  "geometry": {"coordinates":[-80.005699,40.438702],"type":"Point"}
}