{
  "type": "Feature",
  "properties": {
    "iso:country":"US",
    "sg:address":"113 N Olive St",
    "sg:city":"Media",
    "sg:classifiers":[
        {
            "category":"Professional",
            "subcategory":"Lawyer & Legal Services",
            "type":"Services"
        }
    ],
    "sg:phone":"+1 610 565 6760",
    "sg:postcode":"19063",
    "sg:province":"PA",
    "sg:tags":[
        "information",
        "attorney",
        "referral"
    ],
    "sg:website":"http://hstrial-AList.homestead.com",
    "wof:name":"List & List",
    "wof:placetype":"venue"
},
  "geometry": {"coordinates":[-75.390771,39.919159],"type":"Point"}
}