{
  "type": "Feature",
  "properties": {
    "iso:country":"US",
    "sg:address":"3780 Willow Ave",
    "sg:city":"Pittsburgh",
    "sg:classifiers":[
        {
            "category":"Professional",
            "subcategory":"Lawyer & Legal Services",
            "type":"Services"
        }
    ],
    "sg:phone":"+1 412 561 7500",
    "sg:postcode":"15234",
    "sg:province":"PA",
    "wof:name":"Sciullo",
    "wof:placetype":"venue"
},
  "geometry": {"coordinates":[-80.023102,40.365501],"type":"Point"}
}