{
  "type": "Feature",
  "properties": {
    "iso:country":"US",
    "sg:address":"119 Gamma Dr",
    "sg:city":"Pittsburgh",
    "sg:classifiers":[
        {
            "category":"Real Estate",
            "subcategory":"Real Estate Agent",
            "type":"Services"
        }
    ],
    "sg:phone":"+1   ",
    "sg:postcode":"15238",
    "sg:province":"PA",
    "sg:tags":[
        "loan",
        "broker"
    ],
    "wof:name":"Howard Hanna Co Realtors",
    "wof:placetype":"venue"
},
  "geometry": {"coordinates":[-79.866798,40.499445],"type":"Point"}
}