{
  "type": "Feature",
  "properties": {
    "iso:country":"US",
    "sg:address":"4527 N 5th St",
    "sg:city":"Philadelphia",
    "sg:classifiers":[
        {
            "category":"Health Services",
            "subcategory":"Dentist",
            "type":"Services"
        }
    ],
    "sg:phone":"+1 215 329 5962",
    "sg:postcode":"19140",
    "sg:province":"PA",
    "wof:name":"Family Dentistry",
    "wof:placetype":"venue"
},
  "geometry": {"coordinates":[-75.133844,40.020325],"type":"Point"}
}