{
  "type": "Feature",
  "properties": {
    "iso:country":"US",
    "sg:address":"1526 Walton St",
    "sg:city":"Philipsburg",
    "sg:classifiers":[
        {
            "category":"Retail",
            "subcategory":"Storage",
            "type":"Services"
        }
    ],
    "sg:phone":"+1 814 339 7694",
    "sg:postcode":"16866",
    "sg:province":"PA",
    "sg:tags":[
        "self",
        "commercial",
        "household"
    ],
    "wof:name":"M&C Storage",
    "wof:placetype":"venue"
},
  "geometry": {"coordinates":[-78.23634800000001,40.885342],"type":"Point"}
}