{
  "type": "Feature",
  "properties": {
    "iso:country":"US",
    "sg:address":"415 S 2nd St",
    "sg:city":"Saint Clair",
    "sg:classifiers":[
        {
            "category":"Personal",
            "subcategory":"Barber",
            "type":"Services"
        }
    ],
    "sg:phone":"+1   ",
    "sg:postcode":"17970",
    "sg:province":"PA",
    "sg:tags":[
        "shop"
    ],
    "wof:name":"Chizmars Barber Shop",
    "wof:placetype":"venue"
},
  "geometry": {"coordinates":[-76.186921,40.714858],"type":"Point"}
}