{
  "type": "Feature",
  "properties": {
    "addr:full":"1005 Centre St Ashland PA 17921",
    "addr:housenumber":"1005",
    "addr:postcode":"17921",
    "addr:street":"Centre St",
    "iso:country":"US",
    "sg:address":"1005 Centre St",
    "sg:city":"Ashland",
    "sg:classifiers":[
        {
            "category":"Shopping",
            "subcategory":"Used Merchandise",
            "type":"Retail Goods"
        }
    ],
    "sg:phone":"+1 570 875 2944",
    "sg:postcode":"17921",
    "sg:province":"PA",
    "sg:tags":[
        "shop",
        "thrift"
    ],
    "wof:name":"Helping Hands Thrift Shop",
    "wof:placetype":"venue"
},
  "geometry": {"coordinates":[-76.34426499999999,40.782142],"type":"Point"}
}