{
  "type": "Feature",
  "properties": {
    "iso:country":"US",
    "sg:address":"600 E Maiden St",
    "sg:city":"Washington",
    "sg:classifiers":[
        {
            "category":"Professional",
            "subcategory":"Accounting & Tax Preparation",
            "type":"Services"
        }
    ],
    "sg:phone":"+1   ",
    "sg:postcode":"15301",
    "sg:province":"PA",
    "sg:tags":[
        "return"
    ],
    "wof:name":"McWreath Tax & Bookkeeping Svc",
    "wof:placetype":"venue"
},
  "geometry": {"coordinates":[-80.229991,40.164293],"type":"Point"}
}