{
  "type": "Feature",
  "properties": {
    "iso:country":"US",
    "sg:address":"145 E Fayette St",
    "sg:city":"Uniontown",
    "sg:classifiers":[
        {
            "category":"Restaurant",
            "type":"Food & Drink"
        }
    ],
    "sg:phone":"+1 724 439 1770",
    "sg:postcode":"15401",
    "sg:province":"PA",
    "sg:tags":[
        "eating",
        "out"
    ],
    "wof:name":"Canton Chinese Restaurant",
    "wof:placetype":"venue"
},
  "geometry": {"coordinates":[-79.719679,39.896389],"type":"Point"}
}