{
  "type": "Feature",
  "properties": {
    "addr:full":"564 Lancaster Ave Berwyn PA 19312",
    "addr:housenumber":"564",
    "addr:postcode":"19312",
    "addr:street":"Lancaster Ave",
    "iso:country":"US",
    "sg:address":"564 Lancaster Ave",
    "sg:city":"Berwyn",
    "sg:classifiers":[
        {
            "category":"Banks & Credit Unions",
            "subcategory":"Bank",
            "type":"Services"
        }
    ],
    "sg:phone":"+1 610 889 0261",
    "sg:postcode":"19312",
    "sg:province":"PA",
    "sg:tags":[
        "saving",
        "commercial"
    ],
    "wof:name":"Allegiance Bank",
    "wof:placetype":"venue"
},
  "geometry": {"coordinates":[-75.438436,40.048211],"type":"Point"}
}