{
  "type": "Feature",
  "properties": {
    "addr:full":"230 Ohio River Blvd Sewickley PA 15143",
    "addr:housenumber":"230",
    "addr:postcode":"15143",
    "addr:street":"Ohio River Blvd",
    "iso:country":"US",
    "sg:address":"230 Ohio River Blvd",
    "sg:city":"Sewickley",
    "sg:classifiers":[
        {
            "category":"Retail",
            "subcategory":"Auto Repair",
            "type":"Services"
        }
    ],
    "sg:phone":"+1   ",
    "sg:postcode":"15143",
    "sg:province":"PA",
    "sg:tags":[
        "automotive",
        "exhaust"
    ],
    "wof:name":"Midas Muffler",
    "wof:placetype":"venue"
},
  "geometry": {"coordinates":[-80.193636,40.545022],"type":"Point"}
}