{
  "type": "Feature",
  "properties": {
    "iso:country":"US",
    "sg:address":"110 Brimmer Ave",
    "sg:city":"New Holland",
    "sg:classifiers":[
        {
            "category":"Shopping",
            "subcategory":"Computers & Home Electronics",
            "type":"Retail Goods"
        }
    ],
    "sg:phone":"+1   ",
    "sg:postcode":"17557",
    "sg:province":"PA",
    "wof:name":"AV Computers",
    "wof:placetype":"venue"
},
  "geometry": {"coordinates":[-76.083786,40.102772],"type":"Point"}
}