{
  "type": "Feature",
  "properties": {
    "addr:full":"400 Stoke Park Rd Bethlehem PA 18017",
    "addr:housenumber":"400",
    "addr:postcode":"18017",
    "addr:street":"Stoke Park Rd",
    "iso:country":"US",
    "sg:address":"400 Stoke Park Rd",
    "sg:city":"Bethlehem",
    "sg:classifiers":[
        {
            "category":"Wholesale",
            "subcategory":"Machinery & Supplies",
            "type":"Manufacturing & Wholesale Goods"
        }
    ],
    "sg:phone":"+1 610 867 4657",
    "sg:postcode":"18017",
    "sg:province":"PA",
    "sg:tags":[
        "contractor"
    ],
    "sg:website":"www.plasterer.com",
    "wof:name":"Plasterer Equipment Co Inc",
    "wof:placetype":"venue"
},
  "geometry": {"coordinates":[-75.39255199999999,40.660452],"type":"Point"}
}