{
  "type": "Feature",
  "properties": {
    "iso:country":"US",
    "sg:address":"199 E Tabor Rd",
    "sg:city":"Philadelphia",
    "sg:classifiers":[
        {
            "category":"Organizations",
            "subcategory":"Religious Organization",
            "type":"Services"
        }
    ],
    "sg:phone":"+1 215 329 2851",
    "sg:postcode":"19120",
    "sg:province":"PA",
    "sg:tags":[
        "church"
    ],
    "wof:name":"St James United Methodist Chr",
    "wof:placetype":"venue"
},
  "geometry": {"coordinates":[-75.120938,40.031581],"type":"Point"}
}