{
  "type": "Feature",
  "properties": {
    "iso:country":"US",
    "sg:address":"220 W Plum St",
    "sg:city":"Edinboro",
    "sg:classifiers":[
        {
            "category":"Shopping",
            "subcategory":"Gifts & Souvenirs",
            "type":"Retail Goods"
        }
    ],
    "sg:phone":"+1   ",
    "sg:postcode":"16412",
    "sg:province":"PA",
    "wof:name":"Mrs Jones Attic",
    "wof:placetype":"venue"
},
  "geometry": {"coordinates":[-80.132729,41.875914],"type":"Point"}
}