{
  "type": "Feature",
  "properties": {
    "iso:country":"US",
    "sg:address":"6384 Lincoln Hwy",
    "sg:city":"Wrightsville",
    "sg:classifiers":[
        {
            "category":"Autos & Motor Vehicles",
            "subcategory":"Automobile Sales",
            "type":"Retail Goods"
        }
    ],
    "sg:phone":"+1   ",
    "sg:postcode":"17406",
    "sg:province":"PA",
    "sg:tags":[
        "used"
    ],
    "wof:name":"Americars",
    "wof:placetype":"venue"
},
  "geometry": {"coordinates":[-76.550078,40.021269],"type":"Point"}
}