{
  "type": "Feature",
  "properties": {
    "iso:country":"US",
    "sg:address":"610 Cedar Ave",
    "sg:city":"Scranton",
    "sg:classifiers":[
        {
            "category":"Shopping",
            "subcategory":"Florist",
            "type":"Retail Goods"
        }
    ],
    "sg:phone":"+1 570 346 2055",
    "sg:postcode":"18505",
    "sg:province":"PA",
    "sg:tags":[
        "shop"
    ],
    "wof:name":"Buchner S Flower & Gift Shop",
    "wof:placetype":"venue"
},
  "geometry": {"coordinates":[-75.667783,41.399635],"type":"Point"}
}