{
  "type": "Feature",
  "properties": {
    "iso:country":"US",
    "sg:address":"664 Westbrooke Dr",
    "sg:city":"Elizabethtown",
    "sg:classifiers":[
        {
            "category":"Organizations",
            "subcategory":"Non-profit Organization",
            "type":"Services"
        }
    ],
    "sg:phone":"+1 717 361 8429",
    "sg:postcode":"17022",
    "sg:province":"PA",
    "wof:name":"Center For Parent-Youth Unders",
    "wof:placetype":"venue"
},
  "geometry": {"coordinates":[-76.564662,40.138363],"type":"Point"}
}