{
  "type": "Feature",
  "properties": {
    "iso:country":"US",
    "sg:address":"230 E Pomfret St",
    "sg:city":"Carlisle",
    "sg:classifiers":[
        {
            "category":"Building & Trades",
            "subcategory":"Construction",
            "type":"Services"
        }
    ],
    "sg:phone":"+1   ",
    "sg:postcode":"17013",
    "sg:province":"PA",
    "sg:tags":[
        "glass",
        "installation"
    ],
    "wof:name":"Carlisle Glass Service",
    "wof:placetype":"venue"
},
  "geometry": {"coordinates":[-77.184347,40.199417],"type":"Point"}
}