{
  "type": "Feature",
  "properties": {
    "addr:full":"1105 Lindsay Rd Carnegie PA 15106",
    "addr:housenumber":"1105",
    "addr:postcode":"15106",
    "addr:street":"Lindsay Rd",
    "iso:country":"US",
    "sg:address":"1105 Lindsay Rd",
    "sg:city":"Carnegie",
    "sg:classifiers":[
        {
            "category":"Restaurant",
            "type":"Food & Drink"
        }
    ],
    "sg:phone":"+1   ",
    "sg:postcode":"15106",
    "sg:province":"PA",
    "sg:tags":[
        "eating"
    ],
    "wof:name":"Yummys Catering Co",
    "wof:placetype":"venue"
},
  "geometry": {"coordinates":[-80.071871,40.384497],"type":"Point"}
}