{
  "type": "Feature",
  "properties": {
    "iso:country":"US",
    "sg:address":"5011 Torresdale Ave",
    "sg:city":"Philadelphia",
    "sg:classifiers":[
        {
            "category":"Autos & Motor Vehicles",
            "subcategory":"Automobile Sales",
            "type":"Retail Goods"
        }
    ],
    "sg:phone":"+1 215 535 5544",
    "sg:postcode":"19124",
    "sg:province":"PA",
    "sg:tags":[
        "car",
        "used"
    ],
    "wof:name":"Haworth Motors",
    "wof:placetype":"venue"
},
  "geometry": {"coordinates":[-75.07296599999999,40.012624],"type":"Point"}
}