{
  "type": "Feature",
  "properties": {
    "addr:full":"3501 Solly Ave Philadelphia PA 19136",
    "addr:housenumber":"3501",
    "addr:postcode":"19136",
    "addr:street":"Solly Ave",
    "iso:country":"US",
    "sg:address":"3501 Solly Ave",
    "sg:city":"Philadelphia",
    "sg:classifiers":[
        {
            "category":"Government",
            "subcategory":"Police Station",
            "type":"Public Place"
        }
    ],
    "sg:phone":"+1 215 335 1670",
    "sg:postcode":"19136",
    "sg:province":"PA",
    "sg:tags":[
        "department"
    ],
    "wof:name":"Retired Police Firemen",
    "wof:placetype":"venue"
},
  "geometry": {"coordinates":[-75.022358,40.044758],"type":"Point"}
}