{
  "type": "Feature",
  "properties": {
    "addr:full":"300 Lycoming Mall Cir Muncy PA 17756",
    "addr:housenumber":"300",
    "addr:postcode":"17756",
    "addr:street":"Lycoming Mall Cir",
    "iso:country":"US",
    "sg:address":"300 Lycoming Mall Cir",
    "sg:city":"Muncy",
    "sg:classifiers":[
        {
            "category":"Banks & Credit Unions",
            "subcategory":"Bank",
            "type":"Services"
        }
    ],
    "sg:phone":"+1   ",
    "sg:postcode":"17756",
    "sg:province":"PA",
    "sg:tags":[
        "state",
        "commercial"
    ],
    "wof:name":"M&T",
    "wof:placetype":"venue"
},
  "geometry": {"coordinates":[-76.824792,41.23798],"type":"Point"}
}