{
  "type": "Feature",
  "properties": {
    "addr:full":"1000 Washington Ave Carnegie PA 15106",
    "addr:housenumber":"1000",
    "addr:postcode":"15106",
    "addr:street":"Washington Ave",
    "iso:country":"US",
    "sg:address":"1000 Washington Ave",
    "sg:city":"Carnegie",
    "sg:classifiers":[
        {
            "category":"Retail",
            "subcategory":"Auto Repair",
            "type":"Services"
        }
    ],
    "sg:phone":"+1 412 276 3800",
    "sg:postcode":"15106",
    "sg:province":"PA",
    "sg:tags":[
        "body"
    ],
    "wof:name":"Carnegie Motors",
    "wof:placetype":"venue"
},
  "geometry": {"coordinates":[-80.082577,40.398469],"type":"Point"}
}