{
  "type": "Feature",
  "properties": {
    "iso:country":"US",
    "sg:address":"3555 Sardis Rd",
    "sg:city":"Murrysville",
    "sg:classifiers":[
        {
            "category":"Shopping",
            "subcategory":"Beauty & Cosmetics",
            "type":"Retail Goods"
        }
    ],
    "sg:phone":"+1   ",
    "sg:postcode":"15668",
    "sg:province":"PA",
    "sg:tags":[
        "merchandise"
    ],
    "wof:name":"Mary Kay Cosmetic Director",
    "wof:placetype":"venue"
},
  "geometry": {"coordinates":[-79.69201700000001,40.439636],"type":"Point"}
}