{
  "type": "Feature",
  "properties": {
    "iso:country":"US",
    "sg:address":"90 E High St",
    "sg:city":"Carlisle",
    "sg:classifiers":[
        {
            "category":"Utilities",
            "subcategory":"Mobile Phone",
            "type":"Services"
        }
    ],
    "sg:phone":"+1 717 258 8878",
    "sg:postcode":"17013",
    "sg:province":"PA",
    "sg:tags":[
        "telephone",
        "cellular"
    ],
    "wof:name":"Wireless World",
    "wof:placetype":"venue"
},
  "geometry": {"coordinates":[-77.187226,40.201207],"type":"Point"}
}