{
  "type": "Feature",
  "properties": {
    "iso:country":"US",
    "sg:address":"2121 Ebco Dr",
    "sg:city":"Erie",
    "sg:classifiers":[
        {
            "category":"Building & Trades",
            "subcategory":"Construction",
            "type":"Services"
        }
    ],
    "sg:phone":"+1   ",
    "sg:postcode":"16506",
    "sg:province":"PA",
    "sg:tags":[
        "wholesale",
        "floor",
        "installation",
        "covering"
    ],
    "wof:name":"Carpet and Window Trends Inc",
    "wof:placetype":"venue"
},
  "geometry": {"coordinates":[-80.139495,42.092776],"type":"Point"}
}