{
  "type": "Feature",
  "properties": {
    "iso:country":"US",
    "sg:address":"318 Main St",
    "sg:city":"White Haven",
    "sg:classifiers":[
        {
            "category":"Personal",
            "subcategory":"Beauty Salon",
            "type":"Services"
        }
    ],
    "sg:phone":"+1 570 443 8514",
    "sg:postcode":"18661",
    "sg:province":"PA",
    "wof:name":"Connie Job Beauty Shop",
    "wof:placetype":"venue"
},
  "geometry": {"coordinates":[-75.77325999999999,41.061067],"type":"Point"}
}