{
  "type": "Feature",
  "properties": {
    "iso:country":"US",
    "sg:address":"2805 N Taylor St",
    "sg:city":"Philadelphia",
    "sg:classifiers":[
        {
            "category":"Shopping",
            "subcategory":"Computers & Home Electronics",
            "type":"Retail Goods"
        },
        {
            "category":"Professional",
            "subcategory":"Computer Services",
            "type":"Services"
        }
    ],
    "sg:phone":"+1 215 221 1024",
    "sg:postcode":"19132",
    "sg:province":"PA",
    "sg:tags":[
        "hardware",
        "software",
        "supply"
    ],
    "wof:name":"Interactive Communications, Inc.",
    "wof:placetype":"venue"
},
  "geometry": {"coordinates":[-75.171434,39.997821],"type":"Point"}
}