{
  "type": "Feature",
  "properties": {
    "addr:full":"258 Semple St Pittsburgh PA 15213",
    "addr:housenumber":"258",
    "addr:postcode":"15213",
    "addr:street":"Semple St",
    "iso:country":"US",
    "sg:address":"258 Semple St",
    "sg:city":"Pittsburgh",
    "sg:classifiers":[
        {
            "category":"Government",
            "subcategory":"Office",
            "type":"Public Place"
        }
    ],
    "sg:phone":"+1 412 622 6962",
    "sg:postcode":"15213",
    "sg:province":"PA",
    "sg:tags":[
        "village"
    ],
    "wof:name":"Senior Citizen Ctr",
    "wof:placetype":"venue"
},
  "geometry": {"coordinates":[-79.957475,40.43904],"type":"Point"}
}