{
  "type": "Feature",
  "properties": {
    "iso:country":"US",
    "sg:address":"1735 Market St 51st Floor",
    "sg:city":"Philadelphia",
    "sg:classifiers":[
        {
            "category":"Professional",
            "subcategory":"Lawyer & Legal Services",
            "type":"Services"
        }
    ],
    "sg:phone":"+1 215 864 8771",
    "sg:postcode":"19103",
    "sg:province":"PA",
    "sg:tags":[
        "attorney",
        "real estate"
    ],
    "wof:name":"Mc Clure, Matthew N - Ballard Spahr Andrews",
    "wof:placetype":"venue"
},
  "geometry": {"coordinates":[-75.168981,39.953045],"type":"Point"}
}