{
  "type": "Feature",
  "properties": {
    "iso:country":"US",
    "sg:address":"317 E Wyoming Ave",
    "sg:city":"Philadelphia",
    "sg:classifiers":[
        {
            "category":"Health Services",
            "subcategory":"Optometrist",
            "type":"Services"
        },
        {
            "category":"Shopping",
            "subcategory":"Optician",
            "type":"Retail Goods"
        }
    ],
    "sg:phone":"+1 215 455 4515",
    "sg:postcode":"19120",
    "sg:province":"PA",
    "sg:tags":[
        "eyewear"
    ],
    "wof:name":"Clear Vision Optical",
    "wof:placetype":"venue"
},
  "geometry": {"coordinates":[-75.11981900000001,40.021136],"type":"Point"}
}