{
  "type": "Feature",
  "properties": {
    "iso:country":"US",
    "sg:address":"783 White Oak Ln",
    "sg:city":"Leesport",
    "sg:classifiers":[
        {
            "category":"Building & Trades",
            "subcategory":"Construction",
            "type":"Services"
        }
    ],
    "sg:phone":"+1 610 926 3790",
    "sg:postcode":"19533",
    "sg:province":"PA",
    "sg:tags":[
        "home",
        "contractor",
        "residential",
        "new"
    ],
    "wof:name":"Don Mc Cullough Construction",
    "wof:placetype":"venue"
},
  "geometry": {"coordinates":[-76.014898,40.406232],"type":"Point"}
}