{
  "type": "Feature",
  "properties": {
    "iso:country":"US",
    "sg:address":"221 Ohio River Blvd",
    "sg:city":"Sewickley",
    "sg:classifiers":[
        {
            "category":"Retail",
            "subcategory":"Auto Repair",
            "type":"Services"
        }
    ],
    "sg:phone":"+1 412 741 5140",
    "sg:postcode":"15143",
    "sg:province":"PA",
    "sg:tags":[
        "automotive",
        "agency"
    ],
    "wof:name":"Jiffy Lube",
    "wof:placetype":"venue"
},
  "geometry": {"coordinates":[-80.193811,40.545215],"type":"Point"}
}