{
  "type": "Feature",
  "properties": {
    "iso:country":"US",
    "sg:address":"616 Beatty Rd",
    "sg:city":"Monroeville",
    "sg:classifiers":[
        {
            "category":"Wholesale",
            "subcategory":"Office Equipment",
            "type":"Manufacturing & Wholesale Goods"
        }
    ],
    "sg:phone":"+1 412 374 7100",
    "sg:postcode":"15146",
    "sg:province":"PA",
    "sg:tags":[
        "machine",
        "facsimile",
        "duplicating",
        "copying",
        "furn"
    ],
    "wof:name":"Connected Office Products Inc",
    "wof:placetype":"venue"
},
  "geometry": {"coordinates":[-79.75355,40.452019],"type":"Point"}
}