{
  "type": "Feature",
  "properties": {
    "iso:country":"US",
    "sg:address":"1330 N Broad St",
    "sg:city":"Montgomeryville",
    "sg:classifiers":[
        {
            "category":"Wholesale",
            "subcategory":"Auto Parts",
            "type":"Manufacturing & Wholesale Goods"
        }
    ],
    "sg:phone":"+1   ",
    "sg:postcode":"18901",
    "sg:province":"PA",
    "wof:name":"Bergeys Wholesale Parts",
    "wof:placetype":"venue"
},
  "geometry": {"coordinates":[-75.137912,40.318027],"type":"Point"}
}