{
  "type": "Feature",
  "properties": {
    "iso:country":"US",
    "sg:address":"1725 State St",
    "sg:city":"East Petersburg",
    "sg:classifiers":[
        {
            "category":"Restaurant",
            "type":"Food & Drink"
        }
    ],
    "sg:phone":"+1   ",
    "sg:postcode":"17520",
    "sg:province":"PA",
    "sg:tags":[
        "eating"
    ],
    "wof:name":"Eugene L Buckwalter",
    "wof:placetype":"venue"
},
  "geometry": {"coordinates":[-76.35729600000001,40.099172],"type":"Point"}
}