{
  "type": "Feature",
  "properties": {
    "addr:full":"329 Turkey Path Rd Summerhill PA 15958",
    "addr:housenumber":"329",
    "addr:postcode":"15958",
    "addr:street":"Turkey Path Rd",
    "iso:country":"US",
    "sg:address":"329 Turkey Path Rd",
    "sg:city":"Summerhill",
    "sg:classifiers":[
        {
            "category":"Manufacturing",
            "subcategory":"Building Materials",
            "type":"Manufacturing & Wholesale Goods"
        }
    ],
    "sg:phone":"+1   ",
    "sg:postcode":"15958",
    "sg:province":"PA",
    "sg:tags":[
        "mfg"
    ],
    "wof:name":"Tri-K Wood Products Inc",
    "wof:placetype":"venue"
},
  "geometry": {"coordinates":[-78.74071000000001,40.404001],"type":"Point"}
}