{
  "type": "Feature",
  "properties": {
    "addr:full":"700 Smithfield St Pittsburgh PA 15222",
    "addr:housenumber":"700",
    "addr:postcode":"15222",
    "addr:street":"Smithfield St",
    "iso:country":"US",
    "sg:address":"700 Smithfield St",
    "sg:city":"Pittsburgh",
    "sg:classifiers":[
        {
            "category":"Building & Trades",
            "subcategory":"Cleaning & Sanitation",
            "type":"Services"
        }
    ],
    "sg:phone":"+1 724 934 9322",
    "sg:postcode":"15222",
    "sg:province":"PA",
    "sg:tags":[
        "janitor"
    ],
    "wof:name":"American Building Maintenance",
    "wof:placetype":"venue"
},
  "geometry": {"coordinates":[-79.99653000000001,40.44331],"type":"Point"}
}