{
  "type": "Feature",
  "properties": {
    "iso:country":"US",
    "sg:address":"780 Hazle St",
    "sg:city":"Hanover Twp",
    "sg:classifiers":[
        {
            "category":"Personal",
            "subcategory":"Beauty Salon",
            "type":"Services"
        }
    ],
    "sg:phone":"+1 570 822 7776",
    "sg:postcode":"18706",
    "sg:province":"PA",
    "wof:name":"For Heads Only",
    "wof:placetype":"venue"
},
  "geometry": {"coordinates":[-75.89673999999999,41.219854],"type":"Point"}
}