{
  "type": "Feature",
  "properties": {
    "addr:full":"6240 Germantown Ave Philadelphia PA 19144",
    "addr:housenumber":"6240",
    "addr:postcode":"19144",
    "addr:street":"Germantown Ave",
    "iso:country":"US",
    "sg:address":"6240 Germantown Ave",
    "sg:city":"Philadelphia",
    "sg:classifiers":[
        {
            "category":"Food & Beverages",
            "subcategory":"Groceries & Convenience Stores",
            "type":"Retail Goods"
        }
    ],
    "sg:phone":"+1 215 848 7485",
    "sg:postcode":"19144",
    "sg:province":"PA",
    "sg:tags":[
        "station",
        "gasoline"
    ],
    "wof:name":"A Plus Mini Market",
    "wof:placetype":"venue"
},
  "geometry": {"coordinates":[-75.180665,40.042737],"type":"Point"}
}