{
  "type": "Feature",
  "properties": {
    "iso:country":"US",
    "sg:address":"132 Circle Dr",
    "sg:city":"Pittsburgh",
    "sg:classifiers":[
        {
            "category":"Manufacturing",
            "subcategory":"Wood Products",
            "type":"Manufacturing & Wholesale Goods"
        }
    ],
    "sg:phone":"+1   ",
    "sg:postcode":"15237",
    "sg:province":"PA",
    "sg:tags":[
        "mfg"
    ],
    "wof:name":"Apprentice T Woodpeckers",
    "wof:placetype":"venue"
},
  "geometry": {"coordinates":[-80.03153399999999,40.547829],"type":"Point"}
}