{
  "type": "Feature",
  "properties": {
    "addr:full":"82 Port Access Rd Erie PA 16507",
    "addr:housenumber":"82",
    "addr:postcode":"16507",
    "addr:street":"Port Access Rd",
    "iso:country":"US",
    "sg:address":"82 Port Access Rd",
    "sg:city":"Erie",
    "sg:classifiers":[
        {
            "category":"Government",
            "subcategory":"Office",
            "type":"Public Place"
        }
    ],
    "sg:phone":"+1 814 456 1931",
    "sg:postcode":"16507",
    "sg:province":"PA",
    "sg:tags":[
        "state",
        "program"
    ],
    "sg:website":"www.porterie.org",
    "wof:name":"Erie Port Auth Mntnc Bldg",
    "wof:placetype":"venue"
},
  "geometry": {"coordinates":[-80.073364,42.142889],"type":"Point"}
}