{
  "type": "Feature",
  "properties": {
    "iso:country":"US",
    "sg:address":"205 Palmer Rd",
    "sg:city":"Bangor",
    "sg:classifiers":[
        {
            "category":"Manufacturing",
            "subcategory":"Pet Food",
            "type":"Manufacturing & Wholesale Goods"
        },
        {
            "category":"Farming",
            "subcategory":"Farm",
            "type":"Manufacturing & Wholesale Goods"
        }
    ],
    "sg:phone":"+1 610 588 5337",
    "sg:postcode":"18013",
    "sg:province":"PA",
    "sg:tags":[
        "hay"
    ],
    "wof:name":"Louis Palmer",
    "wof:placetype":"venue"
},
  "geometry": {"coordinates":[-75.187053,40.850037],"type":"Point"}
}