{
  "type": "Feature",
  "properties": {
    "iso:country":"US",
    "sg:address":"250 W 21st St",
    "sg:city":"Hazleton",
    "sg:classifiers":[
        {
            "category":"Bars & Pubs",
            "type":"Food & Drink"
        }
    ],
    "sg:phone":"+1 570 454 1882",
    "sg:postcode":"18201",
    "sg:province":"PA",
    "sg:tags":[
        "lounge",
        "drinking",
        "cocktail"
    ],
    "wof:name":"Fireside Lounge",
    "wof:placetype":"venue"
},
  "geometry": {"coordinates":[-75.978967,40.972254],"type":"Point"}
}