{
  "type": "Feature",
  "properties": {
    "addr:full":"5842 Main St Center Valley PA 18034",
    "addr:housenumber":"5842",
    "addr:postcode":"18034",
    "addr:street":"Main St",
    "iso:country":"US",
    "sg:address":"5842 Main St",
    "sg:city":"Center Valley",
    "sg:classifiers":[
        {
            "category":"Food & Beverages",
            "subcategory":"Groceries & Convenience Stores",
            "type":"Retail Goods"
        },
        {
            "category":"Restaurant",
            "type":"Food & Drink"
        }
    ],
    "sg:phone":"+1 610 282 5857",
    "sg:postcode":"18034",
    "sg:province":"PA",
    "sg:tags":[
        "delicatessen"
    ],
    "wof:name":"Kim's Deli",
    "wof:placetype":"venue"
},
  "geometry": {"coordinates":[-75.39999899999999,40.531363],"type":"Point"}
}