{
  "type": "Feature",
  "properties": {
    "iso:country":"US",
    "sg:address":"3319 Cherry St",
    "sg:city":"Philadelphia",
    "sg:classifiers":[
        {
            "category":"Real Estate",
            "subcategory":"Real Estate Services",
            "type":"Services"
        }
    ],
    "sg:phone":"+1 215 349 6900",
    "sg:postcode":"19104",
    "sg:province":"PA",
    "sg:tags":[
        "management",
        "property"
    ],
    "wof:name":"Cjp Management Co Inc",
    "wof:placetype":"venue"
},
  "geometry": {"coordinates":[-75.189598,39.958199],"type":"Point"}
}