{
  "type": "Feature",
  "properties": {
    "addr:full":"415 Mill St Coraopolis PA 15108",
    "addr:housenumber":"415",
    "addr:postcode":"15108",
    "addr:street":"Mill St",
    "iso:country":"US",
    "sg:address":"415 Mill St",
    "sg:city":"Coraopolis",
    "sg:classifiers":[
        {
            "category":"Health Services",
            "subcategory":"Doctor",
            "type":"Services"
        }
    ],
    "sg:phone":"+1 412 264 0606",
    "sg:postcode":"15108",
    "sg:province":"PA",
    "sg:tags":[
        "dentist"
    ],
    "wof:name":"Lionel Carlos DDS",
    "wof:placetype":"venue"
},
  "geometry": {"coordinates":[-80.163723,40.518295],"type":"Point"}
}