{
  "type": "Feature",
  "properties": {
    "iso:country":"US",
    "sg:address":"17 Vincent Cir",
    "sg:city":"Warminster",
    "sg:classifiers":[
        {
            "category":"Manufacturing",
            "subcategory":"Printing",
            "type":"Manufacturing & Wholesale Goods"
        }
    ],
    "sg:phone":"+1 215 443 7250",
    "sg:postcode":"18974",
    "sg:province":"PA",
    "sg:tags":[
        "bookbinding"
    ],
    "wof:name":"Hoster Bindery Inc",
    "wof:placetype":"venue"
},
  "geometry": {"coordinates":[-75.05892299999999,40.221793],"type":"Point"}
}