{
  "type": "Feature",
  "properties": {
    "addr:full":"113 S Main St Mercersburg PA 17236",
    "addr:housenumber":"113",
    "addr:postcode":"17236",
    "addr:street":"S Main St",
    "iso:country":"US",
    "sg:address":"113 S Main St",
    "sg:city":"Mercersburg",
    "sg:classifiers":[
        {
            "category":"Government",
            "subcategory":"Court House",
            "type":"Public Place"
        }
    ],
    "sg:phone":"+1   ",
    "sg:postcode":"17236",
    "sg:province":"PA",
    "sg:tags":[
        "state"
    ],
    "wof:name":"Magisterial District 39-3-06",
    "wof:placetype":"venue"
},
  "geometry": {"coordinates":[-77.903651,39.826742],"type":"Point"}
}