{
  "type": "Feature",
  "properties": {
    "addr:full":"526 Indian Run Rd Millersville PA 17551",
    "addr:housenumber":"526",
    "addr:postcode":"17551",
    "addr:street":"Indian Run Rd",
    "iso:country":"US",
    "sg:address":"526 Indian Run Rd",
    "sg:city":"Millersville",
    "sg:classifiers":[
        {
            "category":"Professional",
            "subcategory":"Lawyer & Legal Services",
            "type":"Services"
        }
    ],
    "sg:phone":"+1 717 871 1194",
    "sg:postcode":"17551",
    "sg:province":"PA",
    "sg:tags":[
        "plan"
    ],
    "wof:name":"Timothy Martin",
    "wof:placetype":"venue"
},
  "geometry": {"coordinates":[-76.39688099999999,39.966601],"type":"Point"}
}