{
  "type": "Feature",
  "properties": {
    "addr:full":"1008 N Washington Ave Scranton PA 18509",
    "addr:housenumber":"1008",
    "addr:postcode":"18509",
    "addr:street":"N Washington Ave",
    "iso:country":"US",
    "sg:address":"1008 N Washington Ave",
    "sg:city":"Scranton",
    "sg:classifiers":[
        {
            "category":"Home & Garden",
            "subcategory":"Furniture",
            "type":"Retail Goods"
        }
    ],
    "sg:phone":"+1   ",
    "sg:postcode":"18509",
    "sg:province":"PA",
    "sg:tags":[
        "store"
    ],
    "wof:name":"Blatts Furniture Galleries",
    "wof:placetype":"venue"
},
  "geometry": {"coordinates":[-75.651876,41.41842],"type":"Point"}
}