{
  "type": "Feature",
  "properties": {
    "addr:full":"252 N Prince St Lancaster PA 17603",
    "addr:housenumber":"252",
    "addr:postcode":"17603",
    "addr:street":"N Prince St",
    "iso:country":"US",
    "sg:address":"252 N Prince St",
    "sg:city":"Lancaster",
    "sg:classifiers":[
        {
            "category":"Professional",
            "subcategory":"Employment Agencies",
            "type":"Services"
        }
    ],
    "sg:phone":"+1 215 579 5997",
    "sg:postcode":"17603",
    "sg:province":"PA",
    "sg:tags":[
        "employer"
    ],
    "wof:name":"Pennsylvania Guild-Craftsmen",
    "wof:placetype":"venue"
},
  "geometry": {"coordinates":[-76.30847300000001,40.041755],"type":"Point"}
}