{
  "type": "Feature",
  "properties": {
    "iso:country":"US",
    "sg:address":"252 N Prince St",
    "sg:city":"Lancaster",
    "sg:classifiers":[
        {
            "category":"Professional",
            "subcategory":"Employment Agencies",
            "type":"Services"
        }
    ],
    "sg:phone":"+1 215 579 5997",
    "sg:postcode":"17603",
    "sg:province":"PA",
    "sg:tags":[
        "employer"
    ],
    "wof:name":"Pennsylvania Guild-Craftsmen",
    "wof:placetype":"venue"
},
  "geometry": {"coordinates":[-76.308473,40.041755],"type":"Point"}
}