{
  "type": "Feature",
  "properties": {
    "iso:country":"US",
    "sg:address":"1500 Market St",
    "sg:city":"Philadelphia",
    "sg:classifiers":[
        {
            "category":"Building & Trades",
            "subcategory":"Construction",
            "type":"Services"
        }
    ],
    "sg:phone":"+1 215 563 7577",
    "sg:postcode":"19102",
    "sg:province":"PA",
    "sg:tags":[
        "system",
        "contractor",
        "air conditioning"
    ],
    "sg:website":"http://www.hvacheatingandcooling.com",
    "wof:name":"Eastern Heating and Cooling",
    "wof:placetype":"venue"
},
  "geometry": {"coordinates":[-75.165222,39.95261],"type":"Point"}
}