{
  "type": "Feature",
  "properties": {
    "iso:country":"US",
    "sg:address":"1515 Shoemaker St",
    "sg:city":"Nanty Glo",
    "sg:classifiers":[
        {
            "category":"Shopping",
            "subcategory":"Discount & Variety Stores",
            "type":"Retail Goods"
        }
    ],
    "sg:phone":"+1 814 749 5254",
    "sg:postcode":"15943",
    "sg:province":"PA",
    "wof:name":"Dollar General",
    "wof:placetype":"venue"
},
  "geometry": {"coordinates":[-78.836901,40.462969],"type":"Point"}
}