{
  "type": "Feature",
  "properties": {
    "iso:country":"US",
    "sg:address":"264 W South St",
    "sg:city":"Carlisle",
    "sg:classifiers":[
        {
            "category":"Manufacturing",
            "subcategory":"Wood Products",
            "type":"Manufacturing & Wholesale Goods"
        }
    ],
    "sg:phone":"+1 717 249 7942",
    "sg:postcode":"17013",
    "sg:province":"PA",
    "sg:tags":[
        "millwork-wholesale",
        "millwork",
        "manufacturer"
    ],
    "wof:name":"Round River Woodworking Inc",
    "wof:placetype":"venue"
},
  "geometry": {"coordinates":[-77.196006,40.198944],"type":"Point"}
}