{
  "type": "Feature",
  "properties": {
    "addr:full":"8794 W Chester Pike Upper Darby PA 19082",
    "addr:housenumber":"8794",
    "addr:postcode":"19082",
    "addr:street":"W Chester Pike",
    "iso:country":"US",
    "sg:address":"8794 W Chester Pike",
    "sg:city":"Upper Darby",
    "sg:classifiers":[
        {
            "category":"Professional",
            "type":"Services"
        }
    ],
    "sg:phone":"+1 610 853 9400",
    "sg:postcode":"19082",
    "sg:province":"PA",
    "sg:tags":[
        "establishment"
    ],
    "wof:name":"Just For Women",
    "wof:placetype":"venue"
},
  "geometry": {"coordinates":[-75.287989,39.967143],"type":"Point"}
}