{
  "type": "Feature",
  "properties": {
    "addr:full":"422 N Croton Ave New Castle PA 16101",
    "addr:housenumber":"422",
    "addr:postcode":"16101",
    "addr:street":"N Croton Ave",
    "iso:country":"US",
    "sg:address":"422 N Croton Ave",
    "sg:city":"New Castle",
    "sg:classifiers":[
        {
            "category":"Retail",
            "subcategory":"Auto Repair",
            "type":"Services"
        }
    ],
    "sg:phone":"+1 724 657 0303",
    "sg:postcode":"16101",
    "sg:province":"PA",
    "sg:tags":[
        "wrecker"
    ],
    "wof:name":"Angelo's Towing & Recovery",
    "wof:placetype":"venue"
},
  "geometry": {"coordinates":[-80.340209,41.000638],"type":"Point"}
}