{
  "type": "Feature",
  "properties": {
    "addr:full":"6620 Castor Ave Philadelphia PA 19149",
    "addr:postcode":"6620;19149",
    "addr:street":"Castor Ave",
    "iso:country":"US",
    "sg:address":"6620 Castor Ave",
    "sg:city":"Philadelphia",
    "sg:classifiers":[
        {
            "category":"Restaurant",
            "type":"Food & Drink"
        }
    ],
    "sg:phone":"+1 215 722 8866",
    "sg:postcode":"19149",
    "sg:province":"PA",
    "sg:tags":[
        "asian",
        "chinese",
        "pan"
    ],
    "wof:name":"China Star Enterprise Inc.",
    "wof:placetype":"venue"
},
  "geometry": {"coordinates":[-75.07446299999999,40.042549],"type":"Point"}
}