{
  "type": "Feature",
  "properties": {
    "addr:full":"1307 Hilltown Pike Line Lexington PA 18932",
    "addr:housenumber":"1307",
    "addr:postcode":"18932",
    "addr:street":"Hilltown Pike",
    "iso:country":"US",
    "sg:address":"1307 Hilltown Pike",
    "sg:city":"Line Lexington",
    "sg:classifiers":[
        {
            "category":"Building & Trades",
            "subcategory":"Plumbing",
            "type":"Services"
        }
    ],
    "sg:phone":"+1 215 822 0808",
    "sg:postcode":"18932",
    "sg:province":"PA",
    "sg:tags":[
        "plumbing",
        "contractor"
    ],
    "wof:name":"Mc Mackin's Plumbing",
    "wof:placetype":"venue"
},
  "geometry": {"coordinates":[-75.249692,40.313251],"type":"Point"}
}