{
  "type": "Feature",
  "properties": {
    "iso:country":"US",
    "sg:address":"314 W Park St",
    "sg:city":"Franklin",
    "sg:classifiers":[
        {
            "category":"Personal",
            "subcategory":"Beauty Salon",
            "type":"Services"
        }
    ],
    "sg:phone":"+1   ",
    "sg:postcode":"16323",
    "sg:province":"PA",
    "sg:tags":[
        "shop"
    ],
    "wof:name":"Artistic Dimensions Hair",
    "wof:placetype":"venue"
},
  "geometry": {"coordinates":[-79.82915199999999,41.398532],"type":"Point"}
}