{
  "type": "Feature",
  "properties": {
    "iso:country":"US",
    "sg:address":"615 W Erie Ave",
    "sg:city":"Philadelphia",
    "sg:classifiers":[
        {
            "category":"Building & Trades",
            "subcategory":"Locksmith",
            "type":"Services"
        }
    ],
    "sg:phone":"+1 267 773 5940",
    "sg:postcode":"19140",
    "sg:province":"PA",
    "sg:tags":[
        "key"
    ],
    "wof:name":"24 Hour Available Locksmith",
    "wof:placetype":"venue"
},
  "geometry": {"coordinates":[-75.139382,40.007856],"type":"Point"}
}