{
  "type": "Feature",
  "properties": {
    "iso:country":"US",
    "sg:address":"2849 N 22nd St",
    "sg:city":"Philadelphia",
    "sg:classifiers":[
        {
            "category":"Shopping",
            "subcategory":"Clothing, Apparel, & Fashions",
            "type":"Retail Goods"
        }
    ],
    "sg:phone":"+1 215 225 3075",
    "sg:postcode":"19132",
    "sg:province":"PA",
    "sg:tags":[
        "wear",
        "accessory"
    ],
    "wof:name":"Fe-Male Fashions",
    "wof:placetype":"venue"
},
  "geometry": {"coordinates":[-75.167198,39.998299],"type":"Point"}
}