{
  "type": "Feature",
  "properties": {
    "addr:full":"1537 S 6th St Philadelphia PA 19147",
    "addr:housenumber":"1537",
    "addr:postcode":"19147",
    "addr:street":"S 6Th St",
    "iso:country":"US",
    "sg:address":"1537 S 6th St",
    "sg:city":"Philadelphia",
    "sg:classifiers":[
        {
            "category":"Wholesale",
            "subcategory":"Electrical",
            "type":"Manufacturing & Wholesale Goods"
        }
    ],
    "sg:phone":"+1 215 551 5035",
    "sg:postcode":"19147",
    "sg:province":"PA",
    "sg:tags":[
        "control",
        "security",
        "system"
    ],
    "wof:name":"Ronin Protection & Security",
    "wof:placetype":"venue"
},
  "geometry": {"coordinates":[-75.15518899999999,39.92881],"type":"Point"}
}