{
  "type": "Feature",
  "properties": {
    "iso:country":"US",
    "sg:address":"465 4th Ave",
    "sg:city":"Warminster",
    "sg:classifiers":[
        {
            "category":"Local Transit",
            "type":"Transportation"
        }
    ],
    "sg:phone":"+1 215 672 8444",
    "sg:postcode":"18974",
    "sg:province":"PA",
    "sg:tags":[
        "limousine"
    ],
    "wof:name":"Brenner Coach & Limousine",
    "wof:placetype":"venue"
},
  "geometry": {"coordinates":[-75.102503,40.193937],"type":"Point"}
}