{
  "type": "Feature",
  "properties": {
    "iso:country":"US",
    "sg:address":"8539 Bustleton Ave",
    "sg:city":"Philadelphia",
    "sg:classifiers":[
        {
            "category":"Health Services",
            "subcategory":"Doctor",
            "type":"Services"
        }
    ],
    "sg:phone":"+1 215 342 5740",
    "sg:postcode":"19152",
    "sg:province":"PA",
    "sg:tags":[
        "dentist"
    ],
    "wof:name":"A-1 Family Dental Care PC",
    "wof:placetype":"venue"
},
  "geometry": {"coordinates":[-75.048823,40.07175],"type":"Point"}
}