{
  "type": "Feature",
  "properties": {
    "addr:full":"850 W Chester Pike Havertown PA 19083",
    "addr:housenumber":"850",
    "addr:postcode":"19083",
    "addr:street":"W Chester Pike",
    "iso:country":"US",
    "sg:address":"850 W Chester Pike",
    "sg:city":"Havertown",
    "sg:classifiers":[
        {
            "category":"Professional",
            "subcategory":"Management & Consulting",
            "type":"Services"
        }
    ],
    "sg:phone":"+1 610 789 7660",
    "sg:postcode":"19083",
    "sg:province":"PA",
    "sg:tags":[
        "consultant",
        "lighting"
    ],
    "sg:website":"www.hklighting.com",
    "wof:name":"H K Lighting Design Inc",
    "wof:placetype":"venue"
},
  "geometry": {"coordinates":[-75.31037600000001,39.971277],"type":"Point"}
}