{
  "type": "Feature",
  "properties": {
    "iso:country":"US",
    "sg:address":"2276 S Harwood Ave",
    "sg:city":"Upper Darby",
    "sg:classifiers":[
        {
            "category":"Building & Trades",
            "subcategory":"Landscaping Services",
            "type":"Services"
        }
    ],
    "sg:phone":"+1 610 446 5800",
    "sg:postcode":"19082",
    "sg:province":"PA",
    "sg:tags":[
        "landscape",
        "contractor"
    ],
    "wof:name":"Faso's Landscape & Tree",
    "wof:placetype":"venue"
},
  "geometry": {"coordinates":[-75.294093,39.96529],"type":"Point"}
}