{
  "type": "Feature",
  "properties": {
    "iso:country":"US",
    "sg:address":"442 Magee Ave",
    "sg:city":"Patton",
    "sg:classifiers":[
        {
            "category":"Home & Garden",
            "subcategory":"Furniture",
            "type":"Retail Goods"
        }
    ],
    "sg:phone":"+1   ",
    "sg:postcode":"16668",
    "sg:province":"PA",
    "wof:name":"Gene L Gates & Sons",
    "wof:placetype":"venue"
},
  "geometry": {"coordinates":[-78.648707,40.633977],"type":"Point"}
}