{
  "type": "Feature",
  "properties": {
    "iso:country":"US",
    "sg:address":"201 Strawberry Sq",
    "sg:city":"Harrisburg",
    "sg:classifiers":[
        {
            "category":"Sports & Exercise",
            "subcategory":"Gym",
            "type":"Entertainment"
        }
    ],
    "sg:phone":"+1 717 236 3476",
    "sg:postcode":"17101",
    "sg:province":"PA",
    "sg:tags":[
        "trainer"
    ],
    "wof:name":"Fitness Firm the",
    "wof:placetype":"venue"
},
  "geometry": {"coordinates":[-76.88249999999999,40.260101],"type":"Point"}
}