{
  "type": "Feature",
  "properties": {
    "iso:country":"US",
    "sg:address":"1918 Cottman Ave",
    "sg:city":"Philadelphia",
    "sg:classifiers":[
        {
            "category":"Health Services",
            "subcategory":"Optometrist",
            "type":"Services"
        }
    ],
    "sg:phone":"+1   ",
    "sg:postcode":"19111",
    "sg:province":"PA",
    "wof:name":"Platt & Platt Doctors PC",
    "wof:placetype":"venue"
},
  "geometry": {"coordinates":[-75.066326,40.051298],"type":"Point"}
}