{
  "type": "Feature",
  "properties": {
    "iso:country":"US",
    "sg:address":"1464 Frankstown Rd",
    "sg:city":"Johnstown",
    "sg:classifiers":[
        {
            "category":"Manufacturing",
            "subcategory":"Buildings",
            "type":"Manufacturing & Wholesale Goods"
        },
        {
            "category":"Building & Trades",
            "subcategory":"Construction",
            "type":"Services"
        }
    ],
    "sg:phone":"+1 814 536 5303",
    "sg:postcode":"15902",
    "sg:province":"PA",
    "sg:tags":[
        "industrial",
        "specialty",
        "grading",
        "excavation",
        "builder",
        "system",
        "heating",
        "contractors-commercial",
        "home",
        "contractor",
        "air conditioning"
    ],
    "wof:name":"Sheesley Co., Frank M.",
    "wof:placetype":"venue"
},
  "geometry": {"coordinates":[-78.871567,40.325975],"type":"Point"}
}