{
  "type": "Feature",
  "properties": {
    "addr:full":"6228 Revere St Philadelphia PA 19149",
    "addr:housenumber":"6228",
    "addr:postcode":"19149",
    "addr:street":"Revere St",
    "iso:country":"US",
    "sg:address":"6228 Revere St",
    "sg:city":"Philadelphia",
    "sg:classifiers":[
        {
            "category":"Building & Trades",
            "subcategory":"Construction",
            "type":"Services"
        }
    ],
    "sg:phone":"+1 215 743 4714",
    "sg:postcode":"19149",
    "sg:province":"PA",
    "sg:tags":[
        "carpenter"
    ],
    "wof:name":"Award Carpentry",
    "wof:placetype":"venue"
},
  "geometry": {"coordinates":[-75.06661800000001,40.03103],"type":"Point"}
}