{
  "type": "Feature",
  "properties": {
    "addr:full":"208 Virginia Rd Plymouth Meeting PA 19462",
    "addr:housenumber":"208",
    "addr:postcode":"19462",
    "addr:street":"Virginia Rd",
    "iso:country":"US",
    "sg:address":"208 Virginia Rd",
    "sg:city":"Plymouth Meeting",
    "sg:classifiers":[
        {
            "category":"Restaurant",
            "type":"Food & Drink"
        }
    ],
    "sg:phone":"+1   ",
    "sg:postcode":"19462",
    "sg:province":"PA",
    "sg:tags":[
        "eating"
    ],
    "wof:name":"Dinos Deli",
    "wof:placetype":"venue"
},
  "geometry": {"coordinates":[-75.303676,40.124817],"type":"Point"}
}