{
  "type": "Feature",
  "properties": {
    "addr:full":"1019 W Broad St Bethlehem PA 18018",
    "addr:housenumber":"1019",
    "addr:postcode":"18018",
    "addr:street":"W Broad St",
    "iso:country":"US",
    "sg:address":"1019 W Broad St",
    "sg:city":"Bethlehem",
    "sg:classifiers":[
        {
            "category":"Shopping",
            "subcategory":"Musical Instruments",
            "type":"Retail Goods"
        }
    ],
    "sg:phone":"+1 610 691 3484",
    "sg:postcode":"18018",
    "sg:province":"PA",
    "sg:tags":[
        "school",
        "music",
        "dealer"
    ],
    "wof:name":"Lehigh Conservatory Inc",
    "wof:placetype":"venue"
},
  "geometry": {"coordinates":[-75.39733099999999,40.622506],"type":"Point"}
}