{
  "type": "Feature",
  "properties": {
    "addr:full":"32 N 2nd St Easton PA 18042",
    "addr:housenumber":"32",
    "addr:postcode":"18042",
    "addr:street":"N 2Nd St",
    "iso:country":"US",
    "sg:address":"32 N 2nd St",
    "sg:city":"Easton",
    "sg:classifiers":[
        {
            "category":"Real Estate",
            "subcategory":"Architect",
            "type":"Services"
        }
    ],
    "sg:phone":"+1 610 258 3193",
    "sg:postcode":"18042",
    "sg:province":"PA",
    "wof:name":"Archive",
    "wof:placetype":"venue"
},
  "geometry": {"coordinates":[-75.207318,40.692782],"type":"Point"}
}