{
  "type": "Feature",
  "properties": {
    "iso:country":"US",
    "sg:address":"7939 Humboldt Dr",
    "sg:city":"Hummelstown",
    "sg:classifiers":[
        {
            "category":"Real Estate",
            "subcategory":"Real Estate Operator",
            "type":"Services"
        }
    ],
    "sg:phone":"+1 717 561 0615",
    "sg:postcode":"17036",
    "sg:province":"PA",
    "sg:tags":[
        "apartment"
    ],
    "wof:name":"Rutherford Park Townhouses",
    "wof:placetype":"venue"
},
  "geometry": {"coordinates":[-76.756151,40.268572],"type":"Point"}
}