{
  "type": "Feature",
  "properties": {
    "iso:country":"US",
    "sg:address":"424 Wyoming Ave",
    "sg:city":"Scranton",
    "sg:classifiers":[
        {
            "category":"Real Estate",
            "subcategory":"Real Estate Operator",
            "type":"Services"
        }
    ],
    "sg:phone":"+1 570 342 6606",
    "sg:postcode":"18503",
    "sg:province":"PA",
    "sg:tags":[
        "apartment"
    ],
    "wof:name":"Finch Towers Apartments",
    "wof:placetype":"venue"
},
  "geometry": {"coordinates":[-75.66133499999999,41.412047],"type":"Point"}
}