{
  "type": "Feature",
  "properties": {
    "addr:full":"1908 5th St Altoona PA 16601",
    "addr:housenumber":"1908",
    "addr:postcode":"16601",
    "addr:street":"5Th St",
    "iso:country":"US",
    "sg:address":"1908 5th St",
    "sg:city":"Altoona",
    "sg:classifiers":[
        {
            "category":"Bars & Pubs",
            "type":"Food & Drink"
        }
    ],
    "sg:phone":"+1   ",
    "sg:postcode":"16601",
    "sg:province":"PA",
    "sg:tags":[
        "drinking"
    ],
    "wof:name":"Mikes Court",
    "wof:placetype":"venue"
},
  "geometry": {"coordinates":[-78.40303900000001,40.525262],"type":"Point"}
}