{
  "type": "Feature",
  "properties": {
    "iso:country":"US",
    "sg:address":"5515 Main St",
    "sg:city":"East Petersburg",
    "sg:classifiers":[
        {
            "category":"Utilities",
            "subcategory":"Mobile Phone",
            "type":"Services"
        }
    ],
    "sg:phone":"+1 717 569 6656",
    "sg:postcode":"17520",
    "sg:province":"PA",
    "sg:tags":[
        "communication",
        "telephone",
        "cellular",
        "radiotelephone"
    ],
    "wof:name":"Diverse Wireless Solutions Inc",
    "wof:placetype":"venue"
},
  "geometry": {"coordinates":[-76.351162,40.094281],"type":"Point"}
}