{
  "type": "Feature",
  "properties": {
    "addr:full":"306 W Main St Clarion PA 16214",
    "addr:housenumber":"306",
    "addr:postcode":"16214",
    "addr:street":"W Main St",
    "iso:country":"US",
    "sg:address":"306 W Main St",
    "sg:city":"Clarion",
    "sg:classifiers":[
        {
            "category":"Real Estate",
            "subcategory":"Real Estate Agent",
            "type":"Services"
        }
    ],
    "sg:phone":"+1 814 226 5131",
    "sg:postcode":"16214",
    "sg:province":"PA",
    "wof:name":"Gates & Burns Realty",
    "wof:placetype":"venue"
},
  "geometry": {"coordinates":[-79.388847,41.215868],"type":"Point"}
}