{
  "type": "Feature",
  "properties": {
    "addr:full":"8620 Rochester Rd Pittsburgh PA 15237",
    "addr:housenumber":"8620",
    "addr:postcode":"15237",
    "addr:street":"Rochester Rd",
    "iso:country":"US",
    "sg:address":"8620 Rochester Rd",
    "sg:city":"Pittsburgh",
    "sg:classifiers":[
        {
            "category":"Professional",
            "subcategory":"Business Services",
            "type":"Services"
        }
    ],
    "sg:phone":"+1 412 366 0171",
    "sg:postcode":"15237",
    "sg:province":"PA",
    "wof:name":"Home Pro Inc",
    "wof:placetype":"venue"
},
  "geometry": {"coordinates":[-80.060243,40.562837],"type":"Point"}
}