{
  "type": "Feature",
  "properties": {
    "iso:country":"US",
    "sg:address":"1838 E Passyunk Ave",
    "sg:city":"Philadelphia",
    "sg:classifiers":[
        {
            "category":"Personal",
            "subcategory":"Beauty Salon",
            "type":"Services"
        }
    ],
    "sg:phone":"+1 215 465 4788",
    "sg:postcode":"19148",
    "sg:province":"PA",
    "wof:name":"Feng Beauty Salon",
    "wof:placetype":"venue"
},
  "geometry": {"coordinates":[-75.166691,39.927274],"type":"Point"}
}