{
  "type": "Feature",
  "properties": {
    "iso:country":"US",
    "sg:address":"955 Norland Ave",
    "sg:city":"Chambersburg",
    "sg:classifiers":[
        {
            "category":"Shopping",
            "subcategory":"Department Store",
            "type":"Retail Goods"
        }
    ],
    "sg:phone":"+1 717 261 9940",
    "sg:postcode":"17201",
    "sg:province":"PA",
    "sg:website":"http://www.kohls.com",
    "wof:name":"Kohl's",
    "wof:placetype":"venue"
},
  "geometry": {"coordinates":[-77.630364,39.940819],"type":"Point"}
}