{
  "type": "Feature",
  "properties": {
    "iso:country":"US",
    "sg:address":"Gallery 2",
    "sg:city":"Philadelphia",
    "sg:classifiers":[
        {
            "category":"Communications",
            "subcategory":"Newspaper",
            "type":"Services"
        }
    ],
    "sg:phone":"+1 215 574 0824",
    "sg:postcode":"19107",
    "sg:province":"PA",
    "sg:tags":[
        "print",
        "medium"
    ],
    "wof:name":"Kim's News Center",
    "wof:placetype":"venue"
},
  "geometry": {"coordinates":[-75.1567,39.9515],"type":"Point"}
}