{
  "type": "Feature",
  "properties": {
    "iso:country":"US",
    "sg:address":"15 Quarter Turn West Rd",
    "sg:city":"Levittown",
    "sg:classifiers":[
        {
            "category":"Building & Trades",
            "subcategory":"Construction",
            "type":"Services"
        }
    ],
    "sg:phone":"+1   ",
    "sg:postcode":"19057",
    "sg:province":"PA",
    "sg:tags":[
        "nonresidential"
    ],
    "wof:name":"L P Builders Inc",
    "wof:placetype":"venue"
},
  "geometry": {"coordinates":[-74.86958799999999,40.147379],"type":"Point"}
}