{
  "type": "Feature",
  "properties": {
    "iso:country":"US",
    "sg:address":"3904 Morrisdale Allport Hwy",
    "sg:city":"Morrisdale",
    "sg:classifiers":[
        {
            "category":"Food & Beverages",
            "subcategory":"Groceries & Convenience Stores",
            "type":"Retail Goods"
        }
    ],
    "sg:phone":"+1 814 342 1870",
    "sg:postcode":"16858",
    "sg:province":"PA",
    "wof:name":"Country Convenience",
    "wof:placetype":"venue"
},
  "geometry": {"coordinates":[-78.224222,40.949326],"type":"Point"}
}