{
  "type": "Feature",
  "properties": {
    "iso:country":"US",
    "sg:address":"400 Fairway Dr",
    "sg:city":"Coraopolis",
    "sg:classifiers":[
        {
            "category":"Manufacturing",
            "subcategory":"Glass & Minerals",
            "type":"Manufacturing & Wholesale Goods"
        }
    ],
    "sg:phone":"+1 412 375 6600",
    "sg:postcode":"15108",
    "sg:province":"PA",
    "sg:tags":[
        "refractory"
    ],
    "wof:name":"ANH Refractories Co",
    "wof:placetype":"venue"
},
  "geometry": {"coordinates":[-80.203108,40.494879],"type":"Point"}
}