{
  "type": "Feature",
  "properties": {
    "iso:country":"US",
    "sg:address":"110 Main Street",
    "sg:city":"Hellertown",
    "sg:classifiers":[
        {
            "category":"Shopping",
            "subcategory":"Pharmacy",
            "type":"Retail Goods"
        }
    ],
    "sg:phone":"+1 610 838 7371",
    "sg:postcode":"18055",
    "sg:province":"PA",
    "sg:tags":[
        "drugstore"
    ],
    "sg:website":"www.eckerd.com",
    "wof:name":"Eckerd Drugs",
    "wof:placetype":"venue"
},
  "geometry": {"coordinates":[-75.341499,40.572701],"type":"Point"}
}