{
  "type": "Feature",
  "properties": {
    "iso:country":"US",
    "sg:address":"2885 Denbeigh Dr",
    "sg:city":"Hatfield",
    "sg:classifiers":[
        {
            "category":"Shopping",
            "subcategory":"Jewelry",
            "type":"Retail Goods"
        },
        {
            "category":"Manufacturing",
            "subcategory":"Jewelry",
            "type":"Manufacturing & Wholesale Goods"
        }
    ],
    "sg:phone":"+1 215 368 5197",
    "sg:postcode":"19440",
    "sg:province":"PA",
    "sg:tags":[
        "designer",
        "jeweler"
    ],
    "wof:name":"V And V Jewelry",
    "wof:placetype":"venue"
},
  "geometry": {"coordinates":[-75.312056,40.280807],"type":"Point"}
}