{
  "type": "Feature",
  "properties": {
    "iso:country":"US",
    "sg:address":"1304 Old West Chester Pike",
    "sg:city":"Havertown",
    "sg:classifiers":[
        {
            "category":"Restaurant",
            "type":"Food & Drink"
        }
    ],
    "sg:phone":"+1 610 449 0132",
    "sg:postcode":"19083",
    "sg:province":"PA",
    "sg:tags":[
        "italian"
    ],
    "wof:name":"Sabrina's",
    "wof:placetype":"venue"
},
  "geometry": {"coordinates":[-75.33206199999999,39.97625],"type":"Point"}
}