{
  "type": "Feature",
  "properties": {
    "addr:full":"2438 E County Line Rd Ardmore PA 19003",
    "addr:housenumber":"2438",
    "addr:postcode":"19003",
    "addr:street":"E County Line Rd",
    "iso:country":"US",
    "sg:address":"2438 E County Line Rd",
    "sg:city":"Ardmore",
    "sg:classifiers":[
        {
            "category":"Professional",
            "type":"Services"
        }
    ],
    "sg:phone":"+1   ",
    "sg:postcode":"19003",
    "sg:province":"PA",
    "wof:name":"All Seasons Greenhouse Company",
    "wof:placetype":"venue"
},
  "geometry": {"coordinates":[-75.293544,39.997571],"type":"Point"}
}