{
  "type": "Feature",
  "properties": {
    "addr:full":"2535 W Lehigh Ave Philadelphia PA 19132",
    "addr:housenumber":"2535",
    "addr:postcode":"19132",
    "addr:street":"W Lehigh Ave",
    "iso:country":"US",
    "sg:address":"2535 W Lehigh Ave",
    "sg:city":"Philadelphia",
    "sg:classifiers":[
        {
            "category":"Building & Trades",
            "subcategory":"Locksmith",
            "type":"Services"
        }
    ],
    "sg:phone":"+1 267 702 1136",
    "sg:postcode":"19132",
    "sg:province":"PA",
    "sg:tags":[
        "key"
    ],
    "wof:name":"Anytime Any Place Locksmith",
    "wof:placetype":"venue"
},
  "geometry": {"coordinates":[-75.172865,39.996439],"type":"Point"}
}