{
  "type": "Feature",
  "properties": {
    "iso:country":"US",
    "sg:address":"127 W 3rd St",
    "sg:city":"Bethlehem",
    "sg:classifiers":[
        {
            "category":"Wholesale",
            "subcategory":"Seafood",
            "type":"Manufacturing & Wholesale Goods"
        }
    ],
    "sg:phone":"+1 610 865 3611",
    "sg:postcode":"18015",
    "sg:province":"PA",
    "sg:tags":[
        "grocery",
        "meat"
    ],
    "wof:name":"Orchard Knoll Market",
    "wof:placetype":"venue"
},
  "geometry": {"coordinates":[-75.381698,40.611919],"type":"Point"}
}