{
  "type": "Feature",
  "properties": {
    "iso:country":"US",
    "sg:address":"158 Bower Hill Rd",
    "sg:city":"Pittsburgh",
    "sg:classifiers":[
        {
            "category":"Building & Trades",
            "subcategory":"Plumbing",
            "type":"Services"
        }
    ],
    "sg:phone":"+1 724 693 2533",
    "sg:postcode":"15228",
    "sg:province":"PA",
    "sg:tags":[
        "plumbing",
        "contractor"
    ],
    "wof:name":"St Clair Plumbing Htg & Air",
    "wof:placetype":"venue"
},
  "geometry": {"coordinates":[-80.045682,40.3868],"type":"Point"}
}