{
  "type": "Feature",
  "properties": {
    "addr:full":"60 Commerce Dr Reading PA 19610",
    "addr:housenumber":"60",
    "addr:postcode":"19610",
    "addr:street":"Commerce Dr",
    "iso:country":"US",
    "sg:address":"60 Commerce Dr",
    "sg:city":"Reading",
    "sg:classifiers":[
        {
            "category":"Insurance",
            "subcategory":"Insurance Agent",
            "type":"Services"
        },
        {
            "category":"Insurance",
            "subcategory":"Hazard Insurance",
            "type":"Services"
        },
        {
            "category":"Insurance",
            "subcategory":"Title Insurance",
            "type":"Services"
        },
        {
            "category":"Insurance",
            "subcategory":"Life Insurance",
            "type":"Services"
        }
    ],
    "sg:phone":"+1 610 378 8681",
    "sg:postcode":"19610",
    "sg:province":"PA",
    "sg:tags":[
        "business",
        "auto",
        "commercial",
        "homeowner",
        "motorcycle",
        "renter"
    ],
    "wof:name":"Allstate Insurance Company - Albert Leach",
    "wof:placetype":"venue"
},
  "geometry": {"coordinates":[-75.99008499999999,40.346592],"type":"Point"}
}