{
  "type": "Feature",
  "properties": {
    "addr:full":"3001 Fairway Dr Altoona PA 16602",
    "addr:housenumber":"3001",
    "addr:postcode":"16602",
    "addr:street":"Fairway Dr",
    "iso:country":"US",
    "sg:address":"3001 Fairway Dr",
    "sg:city":"Altoona",
    "sg:classifiers":[
        {
            "category":"Social Services",
            "subcategory":"Job Training",
            "type":"Services"
        }
    ],
    "sg:phone":"+1 814 949 9395",
    "sg:postcode":"16602",
    "sg:province":"PA",
    "sg:tags":[
        "employment"
    ],
    "wof:name":"Goodwill Industries",
    "wof:placetype":"venue"
},
  "geometry": {"coordinates":[-78.39527,40.486081],"type":"Point"}
}