{
  "type": "Feature",
  "properties": {
    "iso:country":"US",
    "sg:address":"250 Grandview Way",
    "sg:city":"Charleroi",
    "sg:classifiers":[
        {
            "category":"Health Services",
            "subcategory":"Doctor",
            "type":"Services"
        }
    ],
    "sg:phone":"+1 724 483 6413",
    "sg:postcode":"15022",
    "sg:province":"PA",
    "sg:tags":[
        "physician",
        "medical",
        "surgeon"
    ],
    "wof:name":"Eugene E Costa MD",
    "wof:placetype":"venue"
},
  "geometry": {"coordinates":[-79.893584,40.130239],"type":"Point"}
}