{
  "type": "Feature",
  "properties": {
    "iso:country":"US",
    "sg:address":"5604 Germantown Ave",
    "sg:city":"Philadelphia",
    "sg:classifiers":[
        {
            "category":"Health Services",
            "subcategory":"Clinic",
            "type":"Services"
        }
    ],
    "sg:phone":"+1   ",
    "sg:postcode":"19144",
    "sg:province":"PA",
    "wof:name":"Total Medical Rehabilitation",
    "wof:placetype":"venue"
},
  "geometry": {"coordinates":[-75.17391600000001,40.035067],"type":"Point"}
}