{
  "type": "Feature",
  "properties": {
    "iso:country":"US",
    "sg:address":"4316 Mechanicsville Rd",
    "sg:city":"Mechanicsville",
    "sg:phone":"+1 215 794 7655",
    "sg:postcode":"18934",
    "sg:province":"PA",
    "wof:name":"Mc Ardle's Holiday Farm",
    "wof:placetype":"venue"
},
  "geometry": {"coordinates":[-75.043762,40.375561],"type":"Point"}
}