{
  "type": "Feature",
  "properties": {
    "addr:full":"1441 N East St York PA 17406",
    "addr:housenumber":"1441",
    "addr:postcode":"17406",
    "addr:street":"N East St",
    "iso:country":"US",
    "sg:address":"1441 N East St",
    "sg:city":"York",
    "sg:classifiers":[
        {
            "category":"Social Services",
            "subcategory":"Adult Care",
            "type":"Services"
        }
    ],
    "sg:phone":"+1 717 840 3256",
    "sg:postcode":"17406",
    "sg:province":"PA",
    "sg:tags":[
        "residential"
    ],
    "wof:name":"Mission Home Ministry",
    "wof:placetype":"venue"
},
  "geometry": {"coordinates":[-76.70249699999999,39.982683],"type":"Point"}
}