{
  "type": "Feature",
  "properties": {
    "iso:country":"US",
    "sg:address":"3580 Progress Dr Ste C",
    "sg:city":"Bensalem",
    "sg:classifiers":[
        {
            "category":"Health Services",
            "subcategory":"Hospital",
            "type":"Services"
        }
    ],
    "sg:phone":"+1 215 245 8007",
    "sg:postcode":"19020",
    "sg:province":"PA",
    "wof:name":"Alpine Medical Inc",
    "wof:placetype":"venue"
},
  "geometry": {"coordinates":[-74.92710099999999,40.0853],"type":"Point"}
}