{
  "type": "Feature",
  "properties": {
    "iso:country":"US",
    "sg:address":"627 S Wayne St",
    "sg:city":"Lewistown",
    "sg:classifiers":[
        {
            "category":"Personal",
            "subcategory":"Beauty Salon",
            "type":"Services"
        }
    ],
    "sg:phone":"+1 717 248 5066",
    "sg:postcode":"17044",
    "sg:province":"PA",
    "wof:name":"Jane's Styling Salon For Men",
    "wof:placetype":"venue"
},
  "geometry": {"coordinates":[-77.56572,40.589213],"type":"Point"}
}