{
  "type": "Feature",
  "properties": {
    "iso:country":"US",
    "sg:address":"4617 Liberty Ave",
    "sg:city":"Pittsburgh",
    "sg:classifiers":[
        {
            "category":"Restaurant",
            "type":"Food & Drink"
        }
    ],
    "sg:menulink":"http://www.allmenus.com/pa/pittsburgh/32333-lot-17/menu/",
    "sg:phone":"+1 412 687 8117",
    "sg:postcode":"15224",
    "sg:province":"PA",
    "sg:tags":[
        "new",
        "american"
    ],
    "wof:name":"Lot 17",
    "wof:placetype":"venue"
},
  "geometry": {"coordinates":[-79.950204,40.462512],"type":"Point"}
}