{
  "type": "Feature",
  "properties": {
    "iso:country":"US",
    "sg:address":"5827 Colony Dr",
    "sg:city":"Bethlehem",
    "sg:classifiers":[
        {
            "category":"Wholesale",
            "subcategory":"Toys & Hobbies",
            "type":"Manufacturing & Wholesale Goods"
        },
        {
            "category":"Wholesale",
            "subcategory":"Vending Machines",
            "type":"Manufacturing & Wholesale Goods"
        }
    ],
    "sg:phone":"+1 610 837 9240",
    "sg:postcode":"18017",
    "sg:province":"PA",
    "sg:tags":[
        "park",
        "amusement"
    ],
    "wof:name":"Jackpot Amusements",
    "wof:placetype":"venue"
},
  "geometry": {"coordinates":[-75.42240099999999,40.683498],"type":"Point"}
}