{
  "type": "Feature",
  "properties": {
    "iso:country":"US",
    "sg:address":"559 Shawmont Ave",
    "sg:city":"Philadelphia",
    "sg:phone":"+1 267 236 6654",
    "sg:postcode":"19128",
    "sg:province":"PA",
    "wof:name":"Weather Tight Roofing",
    "wof:placetype":"venue"
},
  "geometry": {"coordinates":[-75.237476,40.052496],"type":"Point"}
}