{
  "type": "Feature",
  "properties": {
    "iso:country":"US",
    "sg:address":"240 W Fulton St",
    "sg:city":"Ephrata",
    "sg:classifiers":[
        {
            "category":"Retail",
            "subcategory":"Auto Repair",
            "type":"Services"
        }
    ],
    "sg:phone":"+1 717 733 0171",
    "sg:postcode":"17522",
    "sg:province":"PA",
    "sg:tags":[
        "repairing",
        "automobile"
    ],
    "wof:name":"Hallingan's Auto Repair",
    "wof:placetype":"venue"
},
  "geometry": {"coordinates":[-76.18360199999999,40.180971],"type":"Point"}
}