{
  "type": "Feature",
  "properties": {
    "iso:country":"US",
    "sg:address":"51 Newgate Rd",
    "sg:city":"Pittsburgh",
    "sg:classifiers":[
        {
            "category":"Health Services",
            "subcategory":"Doctor",
            "type":"Services"
        }
    ],
    "sg:phone":"+1 412 761 5617",
    "sg:postcode":"15202",
    "sg:province":"PA",
    "sg:tags":[
        "physician",
        "surgeon"
    ],
    "wof:name":"John K Hulm Dr",
    "wof:placetype":"venue"
},
  "geometry": {"coordinates":[-80.081387,40.51529],"type":"Point"}
}