{
  "type": "Feature",
  "properties": {
    "addr:full":"54 S Commerce Way Ste 172 Bethlehem PA 18017",
    "addr:housenumber":"54",
    "addr:postcode":"18017",
    "addr:street":"S Commerce Way Ste 172",
    "iso:country":"US",
    "sg:address":"54 S Commerce Way Ste 172",
    "sg:city":"Bethlehem",
    "sg:classifiers":[
        {
            "category":"Professional",
            "subcategory":"Lawyer & Legal Services",
            "type":"Services"
        }
    ],
    "sg:phone":"+1 610 866 7716",
    "sg:postcode":"18017",
    "sg:province":"PA",
    "wof:name":"Zumas Nicholas M Atty",
    "wof:placetype":"venue"
},
  "geometry": {"coordinates":[-75.378304,40.673],"type":"Point"}
}