{
  "type": "Feature",
  "properties": {
    "iso:country":"US",
    "sg:address":"2085 Old Harrisburg Rd",
    "sg:city":"Gettysburg",
    "sg:classifiers":[
        {
            "category":"Autos & Motor Vehicles",
            "subcategory":"Fuel & Gas Station",
            "type":"Retail Goods"
        }
    ],
    "sg:phone":"+1 717 334 8497",
    "sg:postcode":"17325",
    "sg:province":"PA",
    "sg:tags":[
        "oil"
    ],
    "wof:name":"Gary R Miller Svc Station",
    "wof:placetype":"venue"
},
  "geometry": {"coordinates":[-77.201172,39.875115],"type":"Point"}
}