{
  "type": "Feature",
  "properties": {
    "iso:country":"US",
    "sg:address":"1226 Stoltz Rd",
    "sg:city":"Bethel Park",
    "sg:classifiers":[
        {
            "category":"Health Services",
            "subcategory":"Medical Lab",
            "type":"Services"
        }
    ],
    "sg:phone":"+1 412 835 6600",
    "sg:postcode":"15102",
    "sg:province":"PA",
    "sg:tags":[
        "x"
    ],
    "wof:name":"South Hills Radiology Inc",
    "wof:placetype":"venue"
},
  "geometry": {"coordinates":[-80.022981,40.322549],"type":"Point"}
}