{
  "type": "Feature",
  "properties": {
    "iso:country":"US",
    "sg:address":"140 Spring Ln",
    "sg:city":"Baden",
    "sg:classifiers":[
        {
            "category":"Building & Trades",
            "subcategory":"Plumbing",
            "type":"Services"
        }
    ],
    "sg:phone":"+1   ",
    "sg:postcode":"15009",
    "sg:province":"PA",
    "sg:tags":[
        "plumbing",
        "repair"
    ],
    "wof:name":"Mark Malchano Mechanical",
    "wof:placetype":"venue"
},
  "geometry": {"coordinates":[-80.327539,40.696705],"type":"Point"}
}