{
  "type": "Feature",
  "properties": {
    "iso:country":"US",
    "sg:address":"544 East St",
    "sg:city":"Bloomsburg",
    "sg:classifiers":[
        {
            "category":"Professional",
            "subcategory":"Art Services",
            "type":"Services"
        }
    ],
    "sg:phone":"+1 570 784 1212",
    "sg:postcode":"17815",
    "sg:province":"PA",
    "sg:tags":[
        "design",
        "business"
    ],
    "wof:name":"Central Sports & Grafix",
    "wof:placetype":"venue"
},
  "geometry": {"coordinates":[-76.448708,41.001535],"type":"Point"}
}