{
  "type": "Feature",
  "properties": {
    "addr:full":"1036 S Broadway Wind Gap PA 18091",
    "addr:housenumber":"1036",
    "addr:postcode":"18091",
    "addr:street":"S Broadway;Gap",
    "iso:country":"US",
    "sg:address":"1036 S Broadway",
    "sg:city":"Wind Gap",
    "sg:classifiers":[
        {
            "category":"Restaurant",
            "type":"Food & Drink"
        }
    ],
    "sg:phone":"+1 610 863 9800",
    "sg:postcode":"18091",
    "sg:province":"PA",
    "wof:name":"Mc Donald's",
    "wof:placetype":"venue"
},
  "geometry": {"coordinates":[-75.29676000000001,40.836052],"type":"Point"}
}