{
  "type": "Feature",
  "properties": {
    "addr:full":"1403 Chester Pike  Folcroft PA 19032",
    "addr:housenumber":"1403",
    "addr:postcode":"19032",
    "addr:street":"Chester Pike",
    "iso:country":"US",
    "sg:address":"1403 Chester Pike ",
    "sg:city":"Folcroft",
    "sg:classifiers":[
        {
            "category":"Restaurant",
            "type":"Food & Drink"
        }
    ],
    "sg:menulink":"http://www.allmenus.com/pa/sharon-hill/289044-leos-steak-shop/menu/",
    "sg:phone":"+1 610 586 1199",
    "sg:postcode":"19032",
    "sg:province":"PA",
    "sg:tags":[
        "american"
    ],
    "wof:name":"Leo's Steak Shop",
    "wof:placetype":"venue"
},
  "geometry": {"coordinates":[-75.279472,39.905432],"type":"Point"}
}