{
  "type": "Feature",
  "properties": {
    "iso:country":"US",
    "sg:address":"1260 Little Mountain Rd",
    "sg:city":"Myerstown",
    "sg:classifiers":[
        {
            "category":"Retail",
            "subcategory":"Auto Repair",
            "type":"Services"
        }
    ],
    "sg:phone":"+1 717 933 5839",
    "sg:postcode":"17067",
    "sg:province":"PA",
    "sg:tags":[
        "truck"
    ],
    "wof:name":"Ron's Truck Repair",
    "wof:placetype":"venue"
},
  "geometry": {"coordinates":[-76.35455399999999,40.466954],"type":"Point"}
}