{
  "type": "Feature",
  "properties": {
    "addr:full":"105 Cascades Ct Blue Bell PA 19422",
    "addr:housenumber":"105",
    "addr:postcode":"19422",
    "addr:street":"Cascades Ct",
    "iso:country":"US",
    "sg:address":"105 Cascades Ct",
    "sg:city":"Blue Bell",
    "sg:classifiers":[
        {
            "category":"Professional",
            "subcategory":"Engineering",
            "type":"Services"
        }
    ],
    "sg:phone":"+1   ",
    "sg:postcode":"19422",
    "sg:province":"PA",
    "wof:name":"John Douglas Inc",
    "wof:placetype":"venue"
},
  "geometry": {"coordinates":[-75.28112900000001,40.178872],"type":"Point"}
}