{
  "type": "Feature",
  "properties": {
    "iso:country":"US",
    "sg:address":"42 Mall Pkwy",
    "sg:city":"Muncy",
    "sg:classifiers":[
        {
            "category":"Food & Beverages",
            "subcategory":"Candy",
            "type":"Retail Goods"
        }
    ],
    "sg:phone":"+1   ",
    "sg:postcode":"17756",
    "sg:province":"PA",
    "wof:name":"Gertude Hawk Candies Inc",
    "wof:placetype":"venue"
},
  "geometry": {"coordinates":[-76.82928200000001,41.23846],"type":"Point"}
}