{
  "type": "Feature",
  "properties": {
    "addr:full":"1140 Cord Dr Hummelstown PA 17036",
    "addr:housenumber":"1140",
    "addr:postcode":"17036",
    "addr:street":"Cord Dr",
    "iso:country":"US",
    "sg:address":"1140 Cord Dr",
    "sg:city":"Hummelstown",
    "sg:classifiers":[
        {
            "category":"Professional",
            "subcategory":"Accounting & Tax Preparation",
            "type":"Services"
        }
    ],
    "sg:phone":"+1 717 220 1194",
    "sg:postcode":"17036",
    "sg:province":"PA",
    "sg:tags":[
        "return"
    ],
    "wof:name":"Donna L Lang",
    "wof:placetype":"venue"
},
  "geometry": {"coordinates":[-76.71929799999999,40.233531],"type":"Point"}
}