{
  "type": "Feature",
  "properties": {
    "iso:country":"US",
    "sg:address":"1 S Sugan Rd",
    "sg:city":"New Hope",
    "sg:classifiers":[
        {
            "category":"Banks & Credit Unions",
            "subcategory":"Bank",
            "type":"Services"
        }
    ],
    "sg:phone":"+1   ",
    "sg:postcode":"18938",
    "sg:province":"PA",
    "sg:tags":[
        "broker",
        "mortgage"
    ],
    "wof:name":"Spring Willow Financial Svcs",
    "wof:placetype":"venue"
},
  "geometry": {"coordinates":[-74.965317,40.361709],"type":"Point"}
}