{
  "type": "Feature",
  "properties": {
    "iso:country":"US",
    "sg:address":"135 Yacht Club Dr",
    "sg:city":"Greentown",
    "sg:classifiers":[
        {
            "category":"Professional",
            "subcategory":"Art Services",
            "type":"Services"
        }
    ],
    "sg:phone":"+1 570 510 4735",
    "sg:postcode":"18426",
    "sg:province":"PA",
    "sg:tags":[
        "designer",
        "display",
        "producer"
    ],
    "wof:name":"Yacht Club Designs",
    "wof:placetype":"venue"
},
  "geometry": {"coordinates":[-75.247337,41.374931],"type":"Point"}
}