{
  "type": "Feature",
  "properties": {
    "addr:full":"1233 Lakemont Dr Pittsburgh PA 15243",
    "addr:housenumber":"1233",
    "addr:postcode":"15243",
    "addr:street":"Lakemont Dr",
    "iso:country":"US",
    "sg:address":"1233 Lakemont Dr",
    "sg:city":"Pittsburgh",
    "sg:classifiers":[
        {
            "category":"Shopping",
            "subcategory":"Catalog Store",
            "type":"Retail Goods"
        }
    ],
    "sg:phone":"+1   ",
    "sg:postcode":"15243",
    "sg:province":"PA",
    "sg:tags":[
        "mail",
        "house"
    ],
    "wof:name":"Bonnies Collectibles",
    "wof:placetype":"venue"
},
  "geometry": {"coordinates":[-80.06518699999999,40.368169],"type":"Point"}
}