{
  "type": "Feature",
  "properties": {
    "iso:country":"US",
    "sg:address":"859 Rettew Mill Rd",
    "sg:city":"Ephrata",
    "sg:classifiers":[
        {
            "category":"Professional",
            "subcategory":"Business Services",
            "type":"Services"
        }
    ],
    "sg:phone":"+1 717 721 6757",
    "sg:postcode":"17522",
    "sg:province":"PA",
    "sg:tags":[
        "drafting"
    ],
    "wof:name":"Brubaker Building Design",
    "wof:placetype":"venue"
},
  "geometry": {"coordinates":[-76.211038,40.178853],"type":"Point"}
}