{
  "type": "Feature",
  "properties": {
    "iso:country":"US",
    "sg:address":"209 Mine Bank Rd",
    "sg:city":"Wellsville",
    "sg:classifiers":[
        {
            "category":"Farming",
            "subcategory":"Livestock Farm",
            "type":"Manufacturing & Wholesale Goods"
        }
    ],
    "sg:phone":"+1   ",
    "sg:postcode":"17365",
    "sg:province":"PA",
    "sg:tags":[
        "general"
    ],
    "wof:name":"Cedar Hill Farm",
    "wof:placetype":"venue"
},
  "geometry": {"coordinates":[-76.96562299999999,40.040424],"type":"Point"}
}