{
  "type": "Feature",
  "properties": {
    "iso:country":"US",
    "sg:address":"2826 W Wishart St",
    "sg:city":"Philadelphia",
    "sg:classifiers":[
        {
            "category":"Recreation",
            "subcategory":"Fishing",
            "type":"Entertainment"
        }
    ],
    "sg:phone":"+1 215 223 8741",
    "sg:postcode":"19132",
    "sg:province":"PA",
    "sg:tags":[
        "tackle-wholesale",
        "manufacturer"
    ],
    "wof:name":"Dilmar Lure",
    "wof:placetype":"venue"
},
  "geometry": {"coordinates":[-75.17586,40.003913],"type":"Point"}
}