{
  "type": "Feature",
  "properties": {
    "iso:country":"US",
    "sg:address":"1461 Hayden Blvd",
    "sg:city":"Elizabeth",
    "sg:classifiers":[
        {
            "category":"Retail",
            "subcategory":"Auto Repair",
            "type":"Services"
        }
    ],
    "sg:phone":"+1 412 384 2420",
    "sg:postcode":"15037",
    "sg:province":"PA",
    "sg:tags":[
        "body",
        "shop"
    ],
    "wof:name":"Day Toyota Automotive Collision Center",
    "wof:placetype":"venue"
},
  "geometry": {"coordinates":[-79.87249799999999,40.245201],"type":"Point"}
}