{
  "type": "Feature",
  "properties": {
    "addr:full":"1005 N Mountain Rd Harrisburg PA 17112",
    "addr:housenumber":"1005",
    "addr:postcode":"17112",
    "addr:street":"N Mountain Rd",
    "iso:country":"US",
    "sg:address":"1005 N Mountain Rd",
    "sg:city":"Harrisburg",
    "sg:classifiers":[
        {
            "category":"Shopping",
            "subcategory":"Books",
            "type":"Retail Goods"
        }
    ],
    "sg:phone":"+1 717 541 1300",
    "sg:postcode":"17112",
    "sg:province":"PA",
    "sg:tags":[
        "dealer"
    ],
    "wof:name":"Christian Publications Inc",
    "wof:placetype":"venue"
},
  "geometry": {"coordinates":[-76.791281,40.337067],"type":"Point"}
}