{
  "type": "Feature",
  "properties": {
    "addr:full":"5400 Rising Sun Ave Philadelphia PA 19120",
    "addr:housenumber":"5400",
    "addr:postcode":"19120",
    "addr:street":"Rising Sun Ave",
    "iso:country":"US",
    "sg:address":"5400 Rising Sun Ave",
    "sg:city":"Philadelphia",
    "sg:classifiers":[
        {
            "category":"Professional",
            "type":"Services"
        }
    ],
    "sg:phone":"+1   ",
    "sg:postcode":"19120",
    "sg:province":"PA",
    "wof:name":"Schwarzwald Quartett Inc",
    "wof:placetype":"venue"
},
  "geometry": {"coordinates":[-75.116919,40.032058],"type":"Point"}
}