{
  "type": "Feature",
  "properties": {
    "iso:country":"US",
    "sg:address":"221 E Sunbury St",
    "sg:city":"Shamokin",
    "sg:classifiers":[
        {
            "category":"Health Services",
            "subcategory":"Podiatrist",
            "type":"Services"
        }
    ],
    "sg:phone":"+1 570 648 6331",
    "sg:postcode":"17872",
    "sg:province":"PA",
    "sg:tags":[
        "physician",
        "surgeons"
    ],
    "wof:name":"Steven D Ravert",
    "wof:placetype":"venue"
},
  "geometry": {"coordinates":[-76.553517,40.793188],"type":"Point"}
}