{
  "type": "Feature",
  "properties": {
    "iso:country":"US",
    "sg:address":"1200 Broadcasting Rd Ste 202",
    "sg:city":"Reading",
    "sg:classifiers":[
        {
            "category":"Professional",
            "subcategory":"Advertising",
            "type":"Services"
        }
    ],
    "sg:phone":"+1 610 375 2206",
    "sg:postcode":"19610",
    "sg:province":"PA",
    "sg:tags":[
        "mail",
        "direct"
    ],
    "wof:name":"Berks Direct",
    "wof:placetype":"venue"
},
  "geometry": {"coordinates":[-75.98782300000001,40.348621],"type":"Point"}
}