{
  "type": "Feature",
  "properties": {
    "addr:full":"231 Matt Dales Rd Blairsville PA 15717",
    "addr:housenumber":"231",
    "addr:postcode":"15717",
    "addr:street":"Matt Dales Rd",
    "iso:country":"US",
    "sg:address":"231 Matt Dales Rd",
    "sg:city":"Blairsville",
    "sg:classifiers":[
        {
            "category":"Farming",
            "subcategory":"Farm",
            "type":"Manufacturing & Wholesale Goods"
        }
    ],
    "sg:phone":"+1 724 694 9115",
    "sg:postcode":"15717",
    "sg:province":"PA",
    "wof:name":"Norman Frye",
    "wof:placetype":"venue"
},
  "geometry": {"coordinates":[-79.31757,40.398641],"type":"Point"}
}