{
  "type": "Feature",
  "properties": {
    "iso:country":"US",
    "sg:address":"10997 Edgeview Ave",
    "sg:city":"Conneaut Lake",
    "sg:classifiers":[
        {
            "category":"Professional",
            "subcategory":"Engineering",
            "type":"Services"
        }
    ],
    "sg:phone":"+1   ",
    "sg:postcode":"16316",
    "sg:province":"PA",
    "sg:tags":[
        "consultant",
        "instructor"
    ],
    "wof:name":"William J Petraitis",
    "wof:placetype":"venue"
},
  "geometry": {"coordinates":[-80.295922,41.614685],"type":"Point"}
}