{
  "type": "Feature",
  "properties": {
    "addr:full":"845 Bangor Rd Nazareth PA 18064",
    "addr:housenumber":"845",
    "addr:postcode":"18064",
    "addr:street":"Bangor Rd",
    "iso:country":"US",
    "sg:address":"845 Bangor Rd",
    "sg:city":"Nazareth",
    "sg:classifiers":[
        {
            "category":"Transit Center",
            "subcategory":"Freight",
            "type":"Transportation"
        },
        {
            "category":"Freight",
            "type":"Transportation"
        }
    ],
    "sg:phone":"+1 610 759 6386",
    "sg:postcode":"18064",
    "sg:province":"PA",
    "sg:tags":[
        "local",
        "trucking-motor",
        "trucking"
    ],
    "wof:name":"Ronald Mumaw Trucking",
    "wof:placetype":"venue"
},
  "geometry": {"coordinates":[-75.26607799999999,40.785712],"type":"Point"}
}