{
  "type": "Feature",
  "properties": {
    "iso:country":"US",
    "sg:address":"247 Maple St",
    "sg:city":"Slippery Rock",
    "sg:classifiers":[
        {
            "category":"Education",
            "subcategory":"School",
            "type":"Public Place"
        }
    ],
    "sg:phone":"+1   ",
    "sg:postcode":"16057",
    "sg:province":"PA",
    "wof:name":"Womens Inst On Sport & Educatn",
    "wof:placetype":"venue"
},
  "geometry": {"coordinates":[-80.05398,41.063559],"type":"Point"}
}