{
  "type": "Feature",
  "properties": {
    "iso:country":"US",
    "sg:address":"129 E King St",
    "sg:city":"Shippensburg",
    "sg:classifiers":[
        {
            "category":"Government",
            "subcategory":"Fire Station",
            "type":"Public Place"
        }
    ],
    "sg:phone":"+1 717 532 2345",
    "sg:postcode":"17257",
    "sg:province":"PA",
    "sg:tags":[
        "department",
        "volunteer"
    ],
    "sg:website":"http://www.vigilanthose.com",
    "wof:name":"Shippensburg Vlntr Fire Dept",
    "wof:placetype":"venue"
},
  "geometry": {"coordinates":[-77.517573,40.051706],"type":"Point"}
}