{
  "type": "Feature",
  "properties": {
    "addr:full":"116 Washington St East Stroudsburg PA 18301",
    "addr:housenumber":"116",
    "addr:postcode":"18301",
    "addr:street":"Washington St",
    "iso:country":"US",
    "sg:address":"116 Washington St",
    "sg:city":"East Stroudsburg",
    "sg:classifiers":[
        {
            "category":"Health Services",
            "subcategory":"Doctor",
            "type":"Services"
        }
    ],
    "sg:phone":"+1 570 424 7390",
    "sg:postcode":"18301",
    "sg:province":"PA",
    "sg:tags":[
        "medical"
    ],
    "wof:name":"Robert C Wallen MD",
    "wof:placetype":"venue"
},
  "geometry": {"coordinates":[-75.18362,40.996506],"type":"Point"}
}