{
  "type": "Feature",
  "properties": {
    "iso:country":"US",
    "sg:address":"9 W Church St",
    "sg:city":"Lock Haven",
    "sg:classifiers":[
        {
            "category":"Building & Trades",
            "subcategory":"Landscaping Services",
            "type":"Services"
        }
    ],
    "sg:phone":"+1   ",
    "sg:postcode":"17745",
    "sg:province":"PA",
    "wof:name":"Big Bobs Lawn Care & Service",
    "wof:placetype":"venue"
},
  "geometry": {"coordinates":[-77.449838,41.136816],"type":"Point"}
}