{
  "type": "Feature",
  "properties": {
    "iso:country":"US",
    "sg:address":"32 N Nescopec St",
    "sg:city":"Tamaqua",
    "sg:phone":"+1 570 668 1410",
    "sg:postcode":"18252",
    "sg:province":"PA",
    "sg:tags":[
        "oil"
    ],
    "wof:name":"Rarick's Coal & National Oil",
    "wof:placetype":"venue"
},
  "geometry": {"coordinates":[-75.973237,40.798146],"type":"Point"}
}