{
  "type": "Feature",
  "properties": {
    "iso:country":"US",
    "sg:address":"1760 Market St Ste 600",
    "sg:city":"Philadelphia",
    "sg:classifiers":[
        {
            "category":"Professional",
            "subcategory":"Lawyer & Legal Services",
            "type":"Services"
        }
    ],
    "sg:phone":"+1 215 564 2031",
    "sg:postcode":"19103",
    "sg:province":"PA",
    "wof:name":"Gordin & Berger PC",
    "wof:placetype":"venue"
},
  "geometry": {"coordinates":[-75.16950199999999,39.953098],"type":"Point"}
}