{
  "type": "Feature",
  "properties": {
    "iso:country":"US",
    "sg:address":"34 S Hanover St",
    "sg:city":"Carlisle",
    "sg:classifiers":[
        {
            "category":"Real Estate",
            "subcategory":"Real Estate Services",
            "type":"Services"
        }
    ],
    "sg:phone":"+1 717 249 0020",
    "sg:postcode":"17013",
    "sg:province":"PA",
    "sg:tags":[
        "company",
        "title"
    ],
    "wof:name":"Big Spring Land Transfer Co",
    "wof:placetype":"venue"
},
  "geometry": {"coordinates":[-77.189306,40.200561],"type":"Point"}
}