{
  "type": "Feature",
  "properties": {
    "addr:full":"3401 Spruce St Philadelphia PA 19104",
    "addr:housenumber":"3401",
    "addr:postcode":"19104",
    "addr:street":"Spruce St",
    "iso:country":"US",
    "sg:address":"3401 Spruce St",
    "sg:city":"Philadelphia",
    "sg:classifiers":[
        {
            "category":"Building & Trades",
            "subcategory":"Equipment Rental",
            "type":"Services"
        },
        {
            "category":"Shopping",
            "subcategory":"Computers & Home Electronics",
            "type":"Retail Goods"
        }
    ],
    "sg:phone":"+1 215 387 4616",
    "sg:postcode":"19104",
    "sg:province":"PA",
    "sg:tags":[
        "stereo",
        "leasing",
        "video",
        "audio",
        "equipment-renting",
        "audio-visual"
    ],
    "wof:name":"Visual Sound Inc",
    "wof:placetype":"venue"
},
  "geometry": {"coordinates":[-75.19259599999999,39.950439],"type":"Point"}
}