{
  "type": "Feature",
  "properties": {
    "iso:country":"US",
    "sg:address":"342 Spring Rd",
    "sg:city":"Havertown",
    "sg:classifiers":[
        {
            "category":"Building & Trades",
            "subcategory":"Construction",
            "type":"Services"
        }
    ],
    "sg:phone":"+1   ",
    "sg:postcode":"19083",
    "sg:province":"PA",
    "sg:tags":[
        "house"
    ],
    "wof:name":"Filano Home Improvement",
    "wof:placetype":"venue"
},
  "geometry": {"coordinates":[-75.289689,39.971755],"type":"Point"}
}