{
  "type": "Feature",
  "properties": {
    "iso:country":"US",
    "sg:address":"1665 Spring Garden Ave",
    "sg:city":"Berwick",
    "sg:classifiers":[
        {
            "category":"Wholesale",
            "subcategory":"Fruits & Vegetables",
            "type":"Manufacturing & Wholesale Goods"
        }
    ],
    "sg:phone":"+1 570 752 2062",
    "sg:postcode":"18603",
    "sg:province":"PA",
    "wof:name":"Berwick Vegetable Co-Op",
    "wof:placetype":"venue"
},
  "geometry": {"coordinates":[-76.26280300000001,41.049557],"type":"Point"}
}