{
  "type": "Feature",
  "properties": {
    "addr:full":"Philadelphia International Philadelphia PA 19153",
    "addr:postcode":"19153",
    "iso:country":"US",
    "sg:address":"Philadelphia International",
    "sg:city":"Philadelphia",
    "sg:classifiers":[
        {
            "category":"Restaurant",
            "type":"Food & Drink"
        }
    ],
    "sg:phone":"+1 215 365 6000",
    "sg:postcode":"19153",
    "sg:province":"PA",
    "sg:tags":[
        "pizza"
    ],
    "wof:name":"Famous Famiglia",
    "wof:placetype":"venue"
},
  "geometry": {"coordinates":[-75.24952,39.875311],"type":"Point"}
}