{
  "type": "Feature",
  "properties": {
    "addr:full":"613 Pocono Blvd Mount Pocono PA 18344",
    "addr:housenumber":"613",
    "addr:postcode":"18344",
    "addr:street":"Pocono Blvd",
    "iso:country":"US",
    "sg:address":"613 Pocono Blvd",
    "sg:city":"Mount Pocono",
    "sg:classifiers":[
        {
            "category":"Ice Cream",
            "type":"Food & Drink"
        }
    ],
    "sg:menulink":"http://www.allmenus.com/pa/mount-pocono/234890-ritas-ice-custard-happiness/menu/",
    "sg:phone":"+1 570 839 6955",
    "sg:postcode":"18344",
    "sg:province":"PA",
    "sg:tags":[
        "american"
    ],
    "wof:name":"Rita's Ice Custard Happiness",
    "wof:placetype":"venue"
},
  "geometry": {"coordinates":[-75.36156099999999,41.129008],"type":"Point"}
}