{
  "type": "Feature",
  "properties": {
    "iso:country":"US",
    "sg:address":"2347 Silver Creek Rd",
    "sg:city":"Hellertown",
    "sg:classifiers":[
        {
            "category":"Professional",
            "subcategory":"Research",
            "type":"Services"
        }
    ],
    "sg:phone":"+1   ",
    "sg:postcode":"18055",
    "sg:province":"PA",
    "sg:tags":[
        "nonphysical",
        "commercial"
    ],
    "wof:name":"Media Research",
    "wof:placetype":"venue"
},
  "geometry": {"coordinates":[-75.30898000000001,40.574863],"type":"Point"}
}