{
  "type": "Feature",
  "properties": {
    "iso:country":"US",
    "sg:address":"2980 Ave B",
    "sg:city":"Bethlehem",
    "sg:classifiers":[
        {
            "category":"Manufacturing",
            "subcategory":"Tools & Machinery",
            "type":"Manufacturing & Wholesale Goods"
        }
    ],
    "sg:phone":"+1 610 694 9494",
    "sg:postcode":"18017",
    "sg:province":"PA",
    "sg:website":"www.gma.com",
    "wof:name":"GMA",
    "wof:placetype":"venue"
},
  "geometry": {"coordinates":[-75.422433,40.646683],"type":"Point"}
}