{
  "type": "Feature",
  "properties": {
    "iso:country":"US",
    "sg:address":"43686 Buells Corners Rd",
    "sg:city":"Spartansburg",
    "sg:classifiers":[
        {
            "category":"Manufacturing",
            "subcategory":"Lumber",
            "type":"Manufacturing & Wholesale Goods"
        }
    ],
    "sg:phone":"+1   ",
    "sg:postcode":"16434",
    "sg:province":"PA",
    "sg:tags":[
        "logging"
    ],
    "wof:name":"D & D Custom Signs",
    "wof:placetype":"venue"
},
  "geometry": {"coordinates":[-79.671869,41.752151],"type":"Point"}
}