{
  "type": "Feature",
  "properties": {
    "iso:country":"US",
    "sg:address":"270 Tennyson Ave",
    "sg:city":"Pittsburgh",
    "sg:classifiers":[
        {
            "category":"Health Services",
            "subcategory":"Doctor",
            "type":"Services"
        }
    ],
    "sg:phone":"+1   ",
    "sg:postcode":"15213",
    "sg:province":"PA",
    "sg:tags":[
        "medical"
    ],
    "wof:name":"Alagar Medical Associates PC",
    "wof:placetype":"venue"
},
  "geometry": {"coordinates":[-79.95551,40.447363],"type":"Point"}
}