{
  "type": "Feature",
  "properties": {
    "iso:country":"US",
    "sg:address":"350 Mall Circle Dr",
    "sg:city":"Monroeville",
    "sg:classifiers":[
        {
            "category":"Utilities",
            "subcategory":"Mobile Phone",
            "type":"Services"
        }
    ],
    "sg:phone":"+1 412 373 7810",
    "sg:postcode":"15146",
    "sg:province":"PA",
    "sg:tags":[
        "telephone",
        "cellular"
    ],
    "wof:name":"Joe Wireless",
    "wof:placetype":"venue"
},
  "geometry": {"coordinates":[-79.79839200000001,40.431563],"type":"Point"}
}