{
  "type": "Feature",
  "properties": {
    "addr:full":"2909 Edgemont Dr Allentown PA 18103",
    "addr:housenumber":"2909",
    "addr:postcode":"18103",
    "addr:street":"Edgemont Dr",
    "iso:country":"US",
    "sg:address":"2909 Edgemont Dr",
    "sg:city":"Allentown",
    "sg:classifiers":[
        {
            "category":"Restaurant",
            "type":"Food & Drink"
        }
    ],
    "sg:phone":"+1   ",
    "sg:postcode":"18103",
    "sg:province":"PA",
    "sg:tags":[
        "eating"
    ],
    "wof:name":"Richd Home Shaffer",
    "wof:placetype":"venue"
},
  "geometry": {"coordinates":[-75.508939,40.57083],"type":"Point"}
}