{
  "type": "Feature",
  "properties": {
    "iso:country":"US",
    "sg:address":"463 N Duffy Rd",
    "sg:city":"Butler",
    "sg:classifiers":[
        {
            "category":"Recreation",
            "type":"Entertainment"
        }
    ],
    "sg:phone":"+1 724 283 6492",
    "sg:postcode":"16001",
    "sg:province":"PA",
    "sg:tags":[
        "sporting"
    ],
    "wof:name":"Perfect Swing",
    "wof:placetype":"venue"
},
  "geometry": {"coordinates":[-79.941163,40.892805],"type":"Point"}
}