{
  "type": "Feature",
  "properties": {
    "iso:country":"US",
    "sg:address":"1735 Market St Ste A-418",
    "sg:city":"Philadelphia",
    "sg:classifiers":[
        {
            "category":"Government",
            "subcategory":"Post Office",
            "type":"Public Place"
        }
    ],
    "sg:phone":"+1 800 672 2590",
    "sg:postcode":"19103",
    "sg:province":"PA",
    "sg:website":"www.sirlancellotcourier.com/",
    "wof:name":"Sir Lancellot Courier Service",
    "wof:placetype":"venue"
},
  "geometry": {"coordinates":[-75.169578,39.953372],"type":"Point"}
}