{
  "type": "Feature",
  "properties": {
    "addr:full":"54 N Mount Vernon Ave Uniontown PA 15401",
    "addr:housenumber":"54",
    "addr:postcode":"15401",
    "addr:street":"N Mount Vernon Ave",
    "iso:country":"US",
    "sg:address":"54 N Mount Vernon Ave",
    "sg:city":"Uniontown",
    "sg:classifiers":[
        {
            "category":"Shopping",
            "subcategory":"Used Merchandise",
            "type":"Retail Goods"
        }
    ],
    "sg:phone":"+1   ",
    "sg:postcode":"15401",
    "sg:province":"PA",
    "sg:tags":[
        "shop",
        "thrift"
    ],
    "wof:name":"Salvation Army Thrift Store",
    "wof:placetype":"venue"
},
  "geometry": {"coordinates":[-79.729629,39.902781],"type":"Point"}
}