{
  "type": "Feature",
  "properties": {
    "addr:full":"Store # 1735 2539 E. Castor Ave. Philadelphia PA 19134",
    "addr:housenumber":"2539",
    "addr:postcode":"19134",
    "addr:street":"E. Castor Ave.",
    "iso:country":"US",
    "sg:address":"Store # 1735 2539 E. Castor Ave.",
    "sg:city":"Philadelphia",
    "sg:classifiers":[
        {
            "category":"Shopping",
            "subcategory":"Hobbies, Toys, & Games",
            "type":"Retail Goods"
        }
    ],
    "sg:phone":"+1 215 288 0248",
    "sg:postcode":"19134",
    "sg:province":"PA",
    "sg:tags":[
        "toy",
        "store"
    ],
    "sg:website":"www.gamestop.com",
    "wof:name":"Gamestop",
    "wof:placetype":"venue"
},
  "geometry": {"coordinates":[-75.09061800000001,39.991938],"type":"Point"}
}