{
  "type": "Feature",
  "properties": {
    "iso:country":"US",
    "sg:address":"1740 N 2nd St",
    "sg:city":"Philadelphia",
    "sg:classifiers":[
        {
            "category":"Professional",
            "subcategory":"Business Services",
            "type":"Services"
        }
    ],
    "sg:phone":"+1 215 203 1912",
    "sg:postcode":"19122",
    "sg:province":"PA",
    "sg:tags":[
        "messenger"
    ],
    "wof:name":"Route Messengers Of Pa",
    "wof:placetype":"venue"
},
  "geometry": {"coordinates":[-75.137933,39.977378],"type":"Point"}
}