{
  "type": "Feature",
  "properties": {
    "addr:full":"10847 Bustleton Ave Philadelphia PA 19116",
    "addr:housenumber":"10847",
    "addr:postcode":"19116",
    "addr:street":"Bustleton Ave",
    "iso:country":"US",
    "sg:address":"10847 Bustleton Ave",
    "sg:city":"Philadelphia",
    "sg:classifiers":[
        {
            "category":"Health Services",
            "subcategory":"Doctor",
            "type":"Services"
        }
    ],
    "sg:phone":"+1 215 552 9800",
    "sg:postcode":"19116",
    "sg:province":"PA",
    "sg:tags":[
        "dentist"
    ],
    "wof:name":"Northeast Dental Ctr",
    "wof:placetype":"venue"
},
  "geometry": {"coordinates":[-75.024564,40.110563],"type":"Point"}
}