{
  "type": "Feature",
  "properties": {
    "iso:country":"US",
    "sg:address":"126 W Pittsburgh St",
    "sg:city":"Greensburg",
    "sg:classifiers":[
        {
            "category":"Banks & Credit Unions",
            "subcategory":"Investment Brokerage",
            "type":"Services"
        }
    ],
    "sg:phone":"+1 724 834 1800",
    "sg:postcode":"15601",
    "sg:province":"PA",
    "sg:tags":[
        "security"
    ],
    "sg:website":"www.edwardjones.com",
    "wof:name":"Edward Jones Co",
    "wof:placetype":"venue"
},
  "geometry": {"coordinates":[-79.547254,40.301842],"type":"Point"}
}