{
  "type": "Feature",
  "properties": {
    "iso:country":"US",
    "sg:address":"1608 Walnut St",
    "sg:city":"Philadelphia",
    "sg:classifiers":[
        {
            "category":"Professional",
            "subcategory":"Lawyer & Legal Services",
            "type":"Services"
        }
    ],
    "sg:phone":"+1 215 546 8200",
    "sg:postcode":"19103",
    "sg:province":"PA",
    "wof:name":"O'shea Robt J Jr Atty",
    "wof:placetype":"venue"
},
  "geometry": {"coordinates":[-75.16770200000001,39.9496],"type":"Point"}
}