{
  "type": "Feature",
  "properties": {
    "addr:full":"225 Columbia Mall Dr Bloomsburg PA 17815",
    "addr:housenumber":"225",
    "addr:postcode":"17815",
    "addr:street":"Columbia Mall Dr",
    "iso:country":"US",
    "sg:address":"225 Columbia Mall Dr",
    "sg:city":"Bloomsburg",
    "sg:classifiers":[
        {
            "category":"Shopping",
            "subcategory":"Hobbies, Toys, & Games",
            "type":"Retail Goods"
        }
    ],
    "sg:phone":"+1   ",
    "sg:postcode":"17815",
    "sg:province":"PA",
    "sg:tags":[
        "store"
    ],
    "wof:name":"Kb Toys",
    "wof:placetype":"venue"
},
  "geometry": {"coordinates":[-76.485938,41.015996],"type":"Point"}
}