{
  "type": "Feature",
  "properties": {
    "iso:country":"US",
    "sg:address":"2909 N American St",
    "sg:city":"Philadelphia",
    "sg:classifiers":[
        {
            "category":"Building & Trades",
            "subcategory":"Construction",
            "type":"Services"
        }
    ],
    "sg:phone":"+1 215 423 6656",
    "sg:postcode":"19133",
    "sg:province":"PA",
    "sg:tags":[
        "demolition",
        "contractor"
    ],
    "wof:name":"Thorne Equipment Corp",
    "wof:placetype":"venue"
},
  "geometry": {"coordinates":[-75.135465,39.99522],"type":"Point"}
}