{
  "type": "Feature",
  "properties": {
    "iso:country":"US",
    "sg:address":"11 Diana Cir",
    "sg:city":"Nottingham",
    "sg:classifiers":[
        {
            "category":"Restaurant",
            "type":"Food & Drink"
        }
    ],
    "sg:phone":"+1 610 932 7213",
    "sg:postcode":"19362",
    "sg:province":"PA",
    "wof:name":"Jim Fries",
    "wof:placetype":"venue"
},
  "geometry": {"coordinates":[-76.043342,39.76333],"type":"Point"}
}