{
  "type": "Feature",
  "properties": {
    "iso:country":"US",
    "sg:address":"47 S Old Trl",
    "sg:city":"Selinsgrove",
    "sg:classifiers":[
        {
            "category":"Health Services",
            "subcategory":"Chiropractor",
            "type":"Services"
        }
    ],
    "sg:phone":"+1 570 743 4333",
    "sg:postcode":"17870",
    "sg:province":"PA",
    "wof:name":"Shamokin Dam Chiropractic Ctr",
    "wof:placetype":"venue"
},
  "geometry": {"coordinates":[-76.820678,40.845751],"type":"Point"}
}