{
  "type": "Feature",
  "properties": {
    "addr:full":"2100 Byberry Rd Ste 5 Philadelphia PA 19116",
    "addr:housenumber":"2100",
    "addr:postcode":"19116",
    "addr:street":"Byberry Rd Ste 5",
    "iso:country":"US",
    "sg:address":"2100 Byberry Rd Ste 5",
    "sg:city":"Philadelphia",
    "sg:classifiers":[
        {
            "category":"Building & Trades",
            "subcategory":"Construction",
            "type":"Services"
        },
        {
            "category":"Retail",
            "subcategory":"Storage",
            "type":"Services"
        },
        {
            "category":"Transit Center",
            "subcategory":"Freight",
            "type":"Transportation"
        },
        {
            "category":"Manufacturing",
            "subcategory":"Tools & Machinery",
            "type":"Manufacturing & Wholesale Goods"
        },
        {
            "category":"Freight",
            "type":"Transportation"
        },
        {
            "category":"Home & Garden",
            "subcategory":"Carpets & Floor Coverings",
            "type":"Retail Goods"
        }
    ],
    "sg:phone":"+1 215 673 1936",
    "sg:postcode":"19116",
    "sg:province":"PA",
    "sg:tags":[
        "aerial",
        "scaffolding",
        "self",
        "millwright",
        "rigger",
        "trucking",
        "lift",
        "erectors",
        "mover",
        "local",
        "trucking-motor"
    ],
    "wof:name":"Benjamin Brothers Trml Whse",
    "wof:placetype":"venue"
},
  "geometry": {"coordinates":[-75.00172600000001,40.108928],"type":"Point"}
}