{
  "type": "Feature",
  "properties": {
    "iso:country":"US",
    "sg:address":"2728 Custer Ave",
    "sg:city":"Pittsburgh",
    "sg:classifiers":[
        {
            "category":"Organizations",
            "subcategory":"Religious Organization",
            "type":"Services"
        }
    ],
    "sg:phone":"+1   ",
    "sg:postcode":"15227",
    "sg:province":"PA",
    "sg:tags":[
        "catholic",
        "church"
    ],
    "wof:name":"Saint Wendelins Cathlic Church",
    "wof:placetype":"venue"
},
  "geometry": {"coordinates":[-79.97412799999999,40.393395],"type":"Point"}
}