{
  "type": "Feature",
  "properties": {
    "iso:country":"US",
    "sg:address":"223 Yarmouth Ln",
    "sg:city":"Media",
    "sg:classifiers":[
        {
            "category":"Retail",
            "subcategory":"Laundry & Dry Cleaning",
            "type":"Services"
        }
    ],
    "sg:phone":"+1   ",
    "sg:postcode":"19063",
    "sg:province":"PA",
    "wof:name":"G&F Services",
    "wof:placetype":"venue"
},
  "geometry": {"coordinates":[-75.425527,39.951132],"type":"Point"}
}