{
  "type": "Feature",
  "properties": {
    "iso:country":"US",
    "sg:address":"155 Thomas Covered Bridge Rd",
    "sg:city":"Indiana",
    "sg:classifiers":[
        {
            "category":"Food & Beverages",
            "subcategory":"Fruits & Vegetables",
            "type":"Retail Goods"
        }
    ],
    "sg:phone":"+1 724 349 3904",
    "sg:postcode":"15701",
    "sg:province":"PA",
    "sg:tags":[
        "farm",
        "market"
    ],
    "wof:name":"Yarnick's Farm",
    "wof:placetype":"venue"
},
  "geometry": {"coordinates":[-79.23594900000001,40.662272],"type":"Point"}
}