{
  "type": "Feature",
  "properties": {
    "iso:country":"US",
    "sg:address":"26 Park Ave",
    "sg:city":"Upper Darby",
    "sg:classifiers":[
        {
            "category":"Government",
            "subcategory":"Fire Station",
            "type":"Public Place"
        }
    ],
    "sg:phone":"+1 610 449 8144",
    "sg:postcode":"19082",
    "sg:province":"PA",
    "sg:tags":[
        "department"
    ],
    "wof:name":"Highland Park Fire Co #2",
    "wof:placetype":"venue"
},
  "geometry": {"coordinates":[-75.28029600000001,39.965749],"type":"Point"}
}