{
  "type": "Feature",
  "properties": {
    "addr:full":"990 4th St Exd Charleroi PA 15022",
    "addr:housenumber":"990",
    "addr:postcode":"15022",
    "addr:street":"4Th St Exd",
    "iso:country":"US",
    "sg:address":"990 4th St Exd",
    "sg:city":"Charleroi",
    "sg:classifiers":[
        {
            "category":"Organizations",
            "subcategory":"Religious Organization",
            "type":"Services"
        }
    ],
    "sg:phone":"+1 724 483 6108",
    "sg:postcode":"15022",
    "sg:province":"PA",
    "sg:tags":[
        "church"
    ],
    "wof:name":"Calvary Bible Church Inc",
    "wof:placetype":"venue"
},
  "geometry": {"coordinates":[-79.920669,40.151085],"type":"Point"}
}