{
  "type": "Feature",
  "properties": {
    "addr:full":"950 Walnut Bottom Rd Ste 12 Carlisle PA 17015",
    "addr:housenumber":"950;12",
    "addr:postcode":"17015",
    "addr:street":"Walnut Bottom Rd Ste",
    "iso:country":"US",
    "sg:address":"950 Walnut Bottom Rd Ste 12",
    "sg:city":"Carlisle",
    "sg:classifiers":[
        {
            "category":"Shopping",
            "subcategory":"Optician",
            "type":"Retail Goods"
        }
    ],
    "sg:phone":"+1 717 249 5436",
    "sg:postcode":"17015",
    "sg:province":"PA",
    "sg:tags":[
        "eyewear"
    ],
    "wof:name":"Brown Optical and Hearing Aid Service",
    "wof:placetype":"venue"
},
  "geometry": {"coordinates":[-77.213266,40.182286],"type":"Point"}
}