{
  "type": "Feature",
  "properties": {
    "addr:full":"56 Gill Hall Rd Clairton PA 15025",
    "addr:housenumber":"56",
    "addr:postcode":"15025",
    "addr:street":"Gill Hall Rd",
    "iso:country":"US",
    "sg:address":"56 Gill Hall Rd",
    "sg:city":"Clairton",
    "sg:classifiers":[
        {
            "category":"Retail",
            "subcategory":"Repair Shop",
            "type":"Services"
        }
    ],
    "sg:phone":"+1 412 445 0087",
    "sg:postcode":"15025",
    "sg:province":"PA",
    "sg:tags":[
        "lock",
        "locksmith"
    ],
    "wof:name":"Ace Lock",
    "wof:placetype":"venue"
},
  "geometry": {"coordinates":[-79.962092,40.317725],"type":"Point"}
}