{
  "type": "Feature",
  "properties": {
    "iso:country":"US",
    "sg:address":"34 Bridge Ave",
    "sg:city":"Berwyn",
    "sg:classifiers":[
        {
            "category":"Home & Garden",
            "subcategory":"Building Materials",
            "type":"Retail Goods"
        }
    ],
    "sg:phone":"+1 610 296 4040",
    "sg:postcode":"19312",
    "sg:province":"PA",
    "sg:tags":[
        "windows"
    ],
    "wof:name":"Delaware Valley Aluminum Corp",
    "wof:placetype":"venue"
},
  "geometry": {"coordinates":[-75.444925,40.045903],"type":"Point"}
}