{
  "type": "Feature",
  "properties": {
    "addr:full":"229 N 7th St Emmaus PA 18049",
    "addr:housenumber":"229",
    "addr:postcode":"18049",
    "addr:street":"N 7Th St",
    "iso:country":"US",
    "sg:address":"229 N 7th St",
    "sg:city":"Emmaus",
    "sg:classifiers":[
        {
            "category":"Shopping",
            "subcategory":"Bicycles & Sporting Goods",
            "type":"Retail Goods"
        },
        {
            "category":"Manufacturing",
            "subcategory":"Toys & Sporting Goods",
            "type":"Manufacturing & Wholesale Goods"
        }
    ],
    "sg:phone":"+1 610 967 4588",
    "sg:postcode":"18049",
    "sg:province":"PA",
    "sg:tags":[
        "equipment",
        "mfg",
        "hunting",
        "supply"
    ],
    "wof:name":"X-Treme Hunting Products",
    "wof:placetype":"venue"
},
  "geometry": {"coordinates":[-75.500606,40.534553],"type":"Point"}
}