{
  "type": "Feature",
  "properties": {
    "iso:country":"US",
    "sg:address":"527 Haverford Ave",
    "sg:city":"Philadelphia",
    "sg:classifiers":[
        {
            "category":"Place Of Worship",
            "subcategory":"Church",
            "type":"Public Place"
        }
    ],
    "sg:phone":"+1 215 222 5707",
    "sg:postcode":"19139",
    "sg:province":"PA",
    "wof:name":"West Philadelphia Seventh Day Adventist Church",
    "wof:placetype":"venue"
},
  "geometry": {"coordinates":[-75.231965,39.967461],"type":"Point"}
}