{
  "type": "Feature",
  "properties": {
    "addr:full":"120 Lytton Ave Pittsburgh PA 15213",
    "addr:housenumber":"120",
    "addr:postcode":"15213",
    "addr:street":"Lytton Ave",
    "iso:country":"US",
    "sg:address":"120 Lytton Ave",
    "sg:city":"Pittsburgh",
    "sg:classifiers":[
        {
            "category":"Health Services",
            "subcategory":"Doctor",
            "type":"Services"
        }
    ],
    "sg:phone":"+1 412 647 9494",
    "sg:postcode":"15213",
    "sg:province":"PA",
    "sg:tags":[
        "physician",
        "surgeon",
        "medical"
    ],
    "wof:name":"Headache Center",
    "wof:placetype":"venue"
},
  "geometry": {"coordinates":[-79.955151,40.44611],"type":"Point"}
}