{
  "type": "Feature",
  "properties": {
    "iso:country":"US",
    "sg:address":"105 Quaker Ln",
    "sg:city":"Malvern",
    "sg:classifiers":[
        {
            "category":"Building & Trades",
            "subcategory":"Cleaning & Sanitation",
            "type":"Services"
        }
    ],
    "sg:phone":"+1 610 688 7022",
    "sg:postcode":"19355",
    "sg:province":"PA",
    "wof:name":"Judge Mobile Wash",
    "wof:placetype":"venue"
},
  "geometry": {"coordinates":[-75.521114,40.038056],"type":"Point"}
}