{
  "type": "Feature",
  "properties": {
    "addr:full":"234 Delaware Ave Palmerton PA 18071",
    "addr:housenumber":"234",
    "addr:postcode":"18071",
    "addr:street":"Delaware Ave",
    "iso:country":"US",
    "sg:address":"234 Delaware Ave",
    "sg:city":"Palmerton",
    "sg:classifiers":[
        {
            "category":"Shopping",
            "subcategory":"Clothing, Apparel, & Fashions",
            "type":"Retail Goods"
        }
    ],
    "sg:phone":"+1 610 826 3670",
    "sg:postcode":"18071",
    "sg:province":"PA",
    "sg:tags":[
        "shop",
        "bridal",
        "wear"
    ],
    "wof:name":"Ann Margaret's Bridal Boutique",
    "wof:placetype":"venue"
},
  "geometry": {"coordinates":[-75.612234,40.800763],"type":"Point"}
}