{
  "type": "Feature",
  "properties": {
    "iso:country":"US",
    "sg:address":"9230 Germantown Ave",
    "sg:city":"Philadelphia",
    "sg:classifiers":[
        {
            "category":"Professional",
            "subcategory":"Management & Consulting",
            "type":"Services"
        }
    ],
    "sg:phone":"+1 215 242 0731",
    "sg:postcode":"19118",
    "sg:province":"PA",
    "sg:tags":[
        "business"
    ],
    "wof:name":"David Mallery",
    "wof:placetype":"venue"
},
  "geometry": {"coordinates":[-75.22794399999999,40.084219],"type":"Point"}
}