{
  "type": "Feature",
  "properties": {
    "iso:country":"US",
    "sg:address":"5109 N Broad St",
    "sg:city":"Philadelphia",
    "sg:classifiers":[
        {
            "category":"Organizations",
            "subcategory":"Religious Organization",
            "type":"Services"
        }
    ],
    "sg:phone":"+1 215 457 6343",
    "sg:postcode":"19141",
    "sg:province":"PA",
    "wof:name":"Legion of Mary Philadelphia Senatus",
    "wof:placetype":"venue"
},
  "geometry": {"coordinates":[-75.14659899999999,40.031101],"type":"Point"}
}