{
  "type": "Feature",
  "properties": {
    "addr:full":"2429 Nazareth Rd Easton PA 18045",
    "addr:postcode":"2429;18045",
    "addr:street":"Nazareth Rd",
    "iso:country":"US",
    "sg:address":"2429 Nazareth Rd",
    "sg:city":"Easton",
    "sg:classifiers":[
        {
            "category":"Banks & Credit Unions",
            "subcategory":"Bank",
            "type":"Services"
        }
    ],
    "sg:phone":"+1 610 330 9910",
    "sg:postcode":"18045",
    "sg:province":"PA",
    "sg:tags":[
        "cashing",
        "personal",
        "check",
        "institution"
    ],
    "wof:name":"Advance America",
    "wof:placetype":"venue"
},
  "geometry": {"coordinates":[-75.25292899999999,40.687631],"type":"Point"}
}