{
  "type": "Feature",
  "properties": {
    "iso:country":"US",
    "sg:address":"721 Valley Dr",
    "sg:city":"Dallastown",
    "sg:classifiers":[
        {
            "category":"Insurance",
            "subcategory":"Insurance Agent",
            "type":"Services"
        }
    ],
    "sg:phone":"+1 717 246 8080",
    "sg:postcode":"17313",
    "sg:province":"PA",
    "wof:name":"Patton Group",
    "wof:placetype":"venue"
},
  "geometry": {"coordinates":[-76.635627,39.880776],"type":"Point"}
}