{
  "type": "Feature",
  "properties": {
    "iso:country":"US",
    "sg:address":"320 Town Centre Dr",
    "sg:city":"Johnstown",
    "sg:classifiers":[
        {
            "category":"Home & Garden",
            "subcategory":"Home Furnishings",
            "type":"Retail Goods"
        },
        {
            "category":"Home & Garden",
            "subcategory":"Kitchen Supply",
            "type":"Retail Goods"
        },
        {
            "category":"Home & Garden",
            "subcategory":"Furniture",
            "type":"Retail Goods"
        }
    ],
    "sg:phone":"+1 814 266 0310",
    "sg:postcode":"15904",
    "sg:province":"PA",
    "sg:tags":[
        "decor",
        "house",
        "bedding",
        "accessory",
        "housewares",
        "store"
    ],
    "sg:website":"http://www.homegoods.com",
    "wof:name":"Homegoods",
    "wof:placetype":"venue"
},
  "geometry": {"coordinates":[-78.844674,40.27559],"type":"Point"}
}