{
  "type": "Feature",
  "properties": {
    "iso:country":"US",
    "sg:address":"342 E Main St",
    "sg:city":"New Holland",
    "sg:classifiers":[
        {
            "category":"Professional",
            "subcategory":"Lawyer & Legal Services",
            "type":"Services"
        }
    ],
    "sg:phone":"+1 717 656 2626",
    "sg:postcode":"17557",
    "sg:province":"PA",
    "sg:tags":[
        "attorney"
    ],
    "sg:website":"www.eabylaw.com",
    "wof:name":"Accident & Personal Injury Law",
    "wof:placetype":"venue"
},
  "geometry": {"coordinates":[-76.08194399999999,40.104042],"type":"Point"}
}