{
  "type": "Feature",
  "properties": {
    "iso:country":"US",
    "sg:address":"44 W Pettebone St",
    "sg:city":"Kingston",
    "sg:classifiers":[
        {
            "category":"Social Services",
            "type":"Services"
        }
    ],
    "sg:phone":"+1   ",
    "sg:postcode":"18704",
    "sg:province":"PA",
    "wof:name":"Rhoden James MA Lsw",
    "wof:placetype":"venue"
},
  "geometry": {"coordinates":[-75.882895,41.280083],"type":"Point"}
}