{
  "type": "Feature",
  "properties": {
    "addr:full":"955 Bellefonte Ave Lock Haven PA 17745",
    "addr:housenumber":"955",
    "addr:postcode":"17745",
    "addr:street":"Bellefonte Ave",
    "iso:country":"US",
    "sg:address":"955 Bellefonte Ave",
    "sg:city":"Lock Haven",
    "sg:classifiers":[
        {
            "category":"Health Services",
            "subcategory":"Doctor",
            "type":"Services"
        }
    ],
    "sg:phone":"+1 570 748 7714",
    "sg:postcode":"17745",
    "sg:province":"PA",
    "sg:tags":[
        "physician",
        "surgeon",
        "medical"
    ],
    "wof:name":"Geisinger Medical Group",
    "wof:placetype":"venue"
},
  "geometry": {"coordinates":[-77.465046,41.129919],"type":"Point"}
}