{
  "type": "Feature",
  "properties": {
    "iso:country":"US",
    "sg:address":"146 Hawthorne Rd",
    "sg:city":"Pittsburgh",
    "sg:classifiers":[
        {
            "category":"Education",
            "subcategory":"School",
            "type":"Public Place"
        }
    ],
    "sg:phone":"+1 412 821 3858",
    "sg:postcode":"15209",
    "sg:province":"PA",
    "sg:tags":[
        "organization",
        "religious"
    ],
    "sg:website":"www.mtalvernia.com",
    "wof:name":"Mt Alvernia High School",
    "wof:placetype":"venue"
},
  "geometry": {"coordinates":[-79.968661,40.494403],"type":"Point"}
}