{
  "type": "Feature",
  "properties": {
    "iso:country":"US",
    "sg:address":"5823 Bedford Valley Rd",
    "sg:city":"Bedford",
    "sg:classifiers":[
        {
            "category":"Farming",
            "subcategory":"Dairy Farm",
            "type":"Manufacturing & Wholesale Goods"
        },
        {
            "category":"Farming",
            "subcategory":"Farm",
            "type":"Manufacturing & Wholesale Goods"
        }
    ],
    "sg:phone":"+1 814 356 3561",
    "sg:postcode":"15522",
    "sg:province":"PA",
    "wof:name":"Patience Valley Dairy Farms",
    "wof:placetype":"venue"
},
  "geometry": {"coordinates":[-78.617714,39.865389],"type":"Point"}
}