{
  "type": "Feature",
  "properties": {
    "addr:full":"617 Audubon Ave Pittsburgh PA 15228",
    "addr:housenumber":"617",
    "addr:postcode":"15228",
    "addr:street":"Audubon Ave",
    "iso:country":"US",
    "sg:address":"617 Audubon Ave",
    "sg:city":"Pittsburgh",
    "sg:classifiers":[
        {
            "category":"Museum",
            "type":"Entertainment"
        }
    ],
    "sg:phone":"+1 412 561 3353",
    "sg:postcode":"15228",
    "sg:province":"PA",
    "sg:tags":[
        "organization",
        "arts",
        "information"
    ],
    "wof:name":"Mendelssohn Choir-Pittsburgh",
    "wof:placetype":"venue"
},
  "geometry": {"coordinates":[-80.028897,40.376784],"type":"Point"}
}