{
  "type": "Feature",
  "properties": {
    "iso:country":"US",
    "sg:address":"900 Main St",
    "sg:city":"Royersford",
    "sg:classifiers":[
        {
            "category":"Retail",
            "subcategory":"Auto Repair",
            "type":"Services"
        }
    ],
    "sg:phone":"+1 610 792 9014",
    "sg:postcode":"19468",
    "sg:province":"PA",
    "sg:tags":[
        "wrecker"
    ],
    "wof:name":"Pron-Tow",
    "wof:placetype":"venue"
},
  "geometry": {"coordinates":[-75.529416,40.193245],"type":"Point"}
}