{
  "type": "Feature",
  "properties": {
    "iso:country":"US",
    "sg:address":"3036 Valjo Dr",
    "sg:city":"New Kensington",
    "sg:classifiers":[
        {
            "category":"Organizations",
            "subcategory":"Community Association",
            "type":"Services"
        }
    ],
    "sg:phone":"+1   ",
    "sg:postcode":"15068",
    "sg:province":"PA",
    "wof:name":"Sharing & Caring Inc",
    "wof:placetype":"venue"
},
  "geometry": {"coordinates":[-79.722492,40.582058],"type":"Point"}
}