{
  "type": "Feature",
  "properties": {
    "addr:full":"1616 W Allen St Allentown PA 18102",
    "addr:housenumber":"1616",
    "addr:postcode":"18102",
    "addr:street":"W Allen St",
    "iso:country":"US",
    "sg:address":"1616 W Allen St",
    "sg:city":"Allentown",
    "sg:classifiers":[
        {
            "category":"Shopping",
            "subcategory":"Optical Goods",
            "type":"Retail Goods"
        }
    ],
    "sg:phone":"+1 610 432 1458",
    "sg:postcode":"18102",
    "sg:province":"PA",
    "wof:name":"Plaza West Optical",
    "wof:placetype":"venue"
},
  "geometry": {"coordinates":[-75.494899,40.605147],"type":"Point"}
}