{
  "type": "Feature",
  "properties": {
    "iso:country":"US",
    "sg:address":"145 Broad St",
    "sg:city":"Elizabethtown",
    "sg:classifiers":[
        {
            "category":"Health Services",
            "subcategory":"Nursing And Care Facility",
            "type":"Services"
        }
    ],
    "sg:phone":"+1   ",
    "sg:postcode":"17053",
    "sg:province":"PA",
    "sg:tags":[
        "intermediate"
    ],
    "wof:name":"Mount Vernon Assisted Living R",
    "wof:placetype":"venue"
},
  "geometry": {"coordinates":[-76.93339,40.341556],"type":"Point"}
}