{
  "type": "Feature",
  "properties": {
    "iso:country":"US",
    "sg:address":"105 W King St",
    "sg:city":"Shippensburg",
    "sg:classifiers":[
        {
            "category":"Travel",
            "subcategory":"Hotels & Motels",
            "type":"Entertainment"
        }
    ],
    "sg:phone":"+1   ",
    "sg:postcode":"17257",
    "sg:province":"PA",
    "sg:tags":[
        "operation"
    ],
    "wof:name":"Fort Morris Hotel",
    "wof:placetype":"venue"
},
  "geometry": {"coordinates":[-77.524439,40.049083],"type":"Point"}
}