{
  "type": "Feature",
  "properties": {
    "iso:country":"US",
    "sg:address":"142 W Main St",
    "sg:city":"Monongahela",
    "sg:classifiers":[
        {
            "category":"Home & Garden",
            "subcategory":"Furniture",
            "type":"Retail Goods"
        }
    ],
    "sg:phone":"+1 724 258 5905",
    "sg:postcode":"15063",
    "sg:province":"PA",
    "sg:tags":[
        "store"
    ],
    "wof:name":"C J's Furniture Company",
    "wof:placetype":"venue"
},
  "geometry": {"coordinates":[-79.923401,40.2006],"type":"Point"}
}