{
  "type": "Feature",
  "properties": {
    "iso:country":"US",
    "sg:address":"845 Greentree Rd",
    "sg:city":"Pittsburgh",
    "sg:classifiers":[
        {
            "category":"Government",
            "subcategory":"Office",
            "type":"Public Place"
        }
    ],
    "sg:phone":"+1 412 922 0264",
    "sg:postcode":"15220",
    "sg:province":"PA",
    "sg:tags":[
        "state",
        "inspection"
    ],
    "wof:name":"Liquor Control Enforcement",
    "wof:placetype":"venue"
},
  "geometry": {"coordinates":[-80.041403,40.427361],"type":"Point"}
}