{
  "type": "Feature",
  "properties": {
    "addr:full":"6116 Footmill Rd Erie PA 16509",
    "addr:housenumber":"6116",
    "addr:postcode":"16509",
    "addr:street":"Footmill Rd",
    "iso:country":"US",
    "sg:address":"6116 Footmill Rd",
    "sg:city":"Erie",
    "sg:classifiers":[
        {
            "category":"Building & Trades",
            "subcategory":"Construction",
            "type":"Services"
        }
    ],
    "sg:phone":"+1   ",
    "sg:postcode":"16509",
    "sg:province":"PA",
    "sg:tags":[
        "house"
    ],
    "wof:name":"Hayford Contracting",
    "wof:placetype":"venue"
},
  "geometry": {"coordinates":[-80.041518,42.088806],"type":"Point"}
}