{
  "type": "Feature",
  "properties": {
    "iso:country":"US",
    "sg:address":"9445 Molly Pitcher Hwy",
    "sg:city":"Shippensburg",
    "sg:classifiers":[
        {
            "category":"Manufacturing",
            "subcategory":"Food",
            "type":"Manufacturing & Wholesale Goods"
        },
        {
            "category":"Farming",
            "subcategory":"Farm",
            "type":"Manufacturing & Wholesale Goods"
        }
    ],
    "sg:phone":"+1 717 530 5523",
    "sg:postcode":"17257",
    "sg:province":"PA",
    "sg:tags":[
        "corn",
        "product"
    ],
    "wof:name":"Alvin Farmer Oberholtzer",
    "wof:placetype":"venue"
},
  "geometry": {"coordinates":[-77.554666,40.029792],"type":"Point"}
}