{
  "type": "Feature",
  "properties": {
    "iso:country":"US",
    "sg:address":"21 Geisinger Ln",
    "sg:city":"Lewistown",
    "sg:classifiers":[
        {
            "category":"Health Services",
            "subcategory":"Doctor",
            "type":"Services"
        }
    ],
    "sg:phone":"+1 717 242 4200",
    "sg:postcode":"17044",
    "sg:province":"PA",
    "sg:tags":[
        "physician",
        "surgeon"
    ],
    "wof:name":"Gushue Maryann MD",
    "wof:placetype":"venue"
},
  "geometry": {"coordinates":[-77.556808,40.601551],"type":"Point"}
}