{
  "type": "Feature",
  "properties": {
    "iso:country":"US",
    "sg:address":"Front Street",
    "sg:city":"New Cumberland",
    "sg:classifiers":[
        {
            "category":"Park",
            "type":"Public Place"
        }
    ],
    "sg:postcode":"17070",
    "sg:province":"PA",
    "sg:website":"www.newcumberlandpa.com",
    "wof:name":"New Cumberland Borough Park",
    "wof:placetype":"venue"
},
  "geometry": {"coordinates":[-76.86302,40.222881],"type":"Point"}
}