{
  "type": "Feature",
  "properties": {
    "iso:country":"US",
    "sg:address":"1614 Washington Rd",
    "sg:city":"Pittsburgh",
    "sg:classifiers":[
        {
            "category":"Health Services",
            "subcategory":"Doctor",
            "type":"Services"
        }
    ],
    "sg:phone":"+1 412 835 5550",
    "sg:postcode":"15241",
    "sg:province":"PA",
    "sg:tags":[
        "surgeon",
        "cosmetic"
    ],
    "sg:website":"www.premierplasticsurgerypa.com/",
    "wof:name":"Premier Plastic Surgery",
    "wof:placetype":"venue"
},
  "geometry": {"coordinates":[-80.051209,40.352449],"type":"Point"}
}