{
  "type": "Feature",
  "properties": {
    "addr:full":"433 W Tabor Rd Philadelphia PA 19120",
    "addr:housenumber":"433",
    "addr:postcode":"19120",
    "addr:street":"W Tabor Rd",
    "iso:country":"US",
    "sg:address":"433 W Tabor Rd",
    "sg:city":"Philadelphia",
    "sg:classifiers":[
        {
            "category":"Wholesale",
            "subcategory":"Hardware",
            "type":"Manufacturing & Wholesale Goods"
        }
    ],
    "sg:phone":"+1 215 224 0733",
    "sg:postcode":"19120",
    "sg:province":"PA",
    "wof:name":"Tajar",
    "wof:placetype":"venue"
},
  "geometry": {"coordinates":[-75.130698,40.034745],"type":"Point"}
}