{
  "type": "Feature",
  "properties": {
    "iso:country":"US",
    "sg:address":"1512 E Wingohocking St",
    "sg:city":"Philadelphia",
    "sg:classifiers":[
        {
            "category":"Building & Trades",
            "subcategory":"Construction",
            "type":"Services"
        }
    ],
    "sg:phone":"+1 215 535 0700",
    "sg:postcode":"19124",
    "sg:province":"PA",
    "sg:tags":[
        "general",
        "industrial",
        "commercial",
        "contractor"
    ],
    "wof:name":"James J Clearkin Inc",
    "wof:placetype":"venue"
},
  "geometry": {"coordinates":[-75.09551500000001,40.014473],"type":"Point"}
}