{
  "type": "Feature",
  "properties": {
    "iso:country":"US",
    "sg:address":"103 E George St",
    "sg:city":"Emmaus",
    "sg:classifiers":[
        {
            "category":"Professional",
            "type":"Services"
        }
    ],
    "sg:phone":"+1 610 967 9790",
    "sg:postcode":"18049",
    "sg:province":"PA",
    "sg:tags":[
        "establishment"
    ],
    "wof:name":"Victrex USA Inc",
    "wof:placetype":"venue"
},
  "geometry": {"coordinates":[-75.488686,40.545022],"type":"Point"}
}