{
  "type": "Feature",
  "properties": {
    "iso:country":"US",
    "sg:address":"2060 Minesite Rd",
    "sg:city":"Allentown",
    "sg:classifiers":[
        {
            "category":"Health Services",
            "subcategory":"Doctor",
            "type":"Services"
        }
    ],
    "sg:phone":"+1   ",
    "sg:postcode":"18103",
    "sg:province":"PA",
    "sg:tags":[
        "medical"
    ],
    "wof:name":"Leon A Skweir MD",
    "wof:placetype":"venue"
},
  "geometry": {"coordinates":[-75.524778,40.555718],"type":"Point"}
}