{
  "type": "Feature",
  "properties": {
    "addr:full":"5470 Carlisle Pike Mechanicsburg PA 17050",
    "addr:housenumber":"5470",
    "addr:postcode":"17050",
    "addr:street":"Carlisle Pike",
    "iso:country":"US",
    "sg:address":"5470 Carlisle Pike",
    "sg:city":"Mechanicsburg",
    "sg:classifiers":[
        {
            "category":"Restaurant",
            "type":"Food & Drink"
        }
    ],
    "sg:menulink":"http://www.allmenus.com/pa/hampden/75851-tgi-fridays/menu/",
    "sg:phone":"+1 717 766 1851",
    "sg:postcode":"17050",
    "sg:province":"PA",
    "sg:tags":[
        "american"
    ],
    "wof:name":"T.G.I. Friday's",
    "wof:placetype":"venue"
},
  "geometry": {"coordinates":[-76.983546,40.240118],"type":"Point"}
}