{
  "type": "Feature",
  "properties": {
    "addr:full":"717 Constitution Dr Exton PA 19341",
    "addr:housenumber":"717",
    "addr:postcode":"19341",
    "addr:street":"Constitution Dr",
    "iso:country":"US",
    "sg:address":"717 Constitution Dr",
    "sg:city":"Exton",
    "sg:classifiers":[
        {
            "category":"Wholesale",
            "subcategory":"Electrical",
            "type":"Manufacturing & Wholesale Goods"
        }
    ],
    "sg:phone":"+1   ",
    "sg:postcode":"19341",
    "sg:province":"PA",
    "sg:tags":[
        "lighting",
        "fixture"
    ],
    "wof:name":"GE",
    "wof:placetype":"venue"
},
  "geometry": {"coordinates":[-75.677802,40.067508],"type":"Point"}
}