{
  "type": "Feature",
  "properties": {
    "iso:country":"US",
    "sg:address":"50 Monument Rd",
    "sg:city":"Bala Cynwyd",
    "sg:classifiers":[
        {
            "category":"Health Services",
            "subcategory":"Chiropractor",
            "type":"Services"
        }
    ],
    "sg:phone":"+1 610 667 5705",
    "sg:postcode":"19004",
    "sg:province":"PA",
    "wof:name":"Health One Chiropractic",
    "wof:placetype":"venue"
},
  "geometry": {"coordinates":[-75.214986,40.008383],"type":"Point"}
}