{
  "type": "Feature",
  "properties": {
    "iso:country":"US",
    "sg:address":"26 Waverly Dr",
    "sg:city":"Stroudsburg",
    "sg:classifiers":[
        {
            "category":"Real Estate",
            "subcategory":"Real Estate Operator",
            "type":"Services"
        }
    ],
    "sg:phone":"+1 570 420 9390",
    "sg:postcode":"18360",
    "sg:province":"PA",
    "sg:tags":[
        "apartment"
    ],
    "wof:name":"Glenbrook East Apartments",
    "wof:placetype":"venue"
},
  "geometry": {"coordinates":[-75.199952,40.981732],"type":"Point"}
}