{
  "type": "Feature",
  "properties": {
    "iso:country":"US",
    "sg:address":"145 N Narberth Ave",
    "sg:city":"Narberth",
    "sg:classifiers":[
        {
            "category":"Real Estate",
            "subcategory":"Real Estate Services",
            "type":"Services"
        },
        {
            "category":"Real Estate",
            "subcategory":"Real Estate Agent",
            "type":"Services"
        }
    ],
    "sg:phone":"+1 610 664 9872",
    "sg:postcode":"19072",
    "sg:province":"PA",
    "sg:tags":[
        "buyer",
        "broker"
    ],
    "wof:name":"Jul Realty Corp",
    "wof:placetype":"venue"
},
  "geometry": {"coordinates":[-75.26034199999999,40.006347],"type":"Point"}
}