{
  "type": "Feature",
  "properties": {
    "iso:country":"US",
    "sg:address":"311 S Northampton St",
    "sg:city":"Bangor",
    "sg:classifiers":[
        {
            "category":"Professional",
            "subcategory":"Business Services",
            "type":"Services"
        }
    ],
    "sg:phone":"+1   ",
    "sg:postcode":"18013",
    "sg:province":"PA",
    "wof:name":"Youngkin Assoc",
    "wof:placetype":"venue"
},
  "geometry": {"coordinates":[-75.203458,40.863104],"type":"Point"}
}