{
  "type": "Feature",
  "properties": {
    "iso:country":"US",
    "sg:address":"808 Old Zelienople Rd",
    "sg:city":"Ellwood City",
    "sg:classifiers":[
        {
            "category":"Government",
            "subcategory":"Fire Station",
            "type":"Public Place"
        }
    ],
    "sg:phone":"+1   ",
    "sg:postcode":"16117",
    "sg:province":"PA",
    "sg:tags":[
        "department",
        "volunteer"
    ],
    "wof:name":"Franklin Township Volunteer FI",
    "wof:placetype":"venue"
},
  "geometry": {"coordinates":[-80.268576,40.84787],"type":"Point"}
}