{
  "type": "Feature",
  "properties": {
    "iso:country":"US",
    "sg:address":"105 3rd St",
    "sg:city":"Charleroi",
    "sg:classifiers":[
        {
            "category":"Food & Beverages",
            "subcategory":"Liquor & Beverages",
            "type":"Retail Goods"
        }
    ],
    "sg:phone":"+1   ",
    "sg:postcode":"15022",
    "sg:province":"PA",
    "sg:tags":[
        "regulation",
        "commercial",
        "sect",
        "alcoholic"
    ],
    "wof:name":"Wine & Spirits Shoppe 6304",
    "wof:placetype":"venue"
},
  "geometry": {"coordinates":[-79.894886,40.136681],"type":"Point"}
}