{
  "type": "Feature",
  "properties": {
    "iso:country":"US",
    "sg:address":"5620 Riverview Rd",
    "sg:city":"Slatington",
    "sg:classifiers":[
        {
            "category":"Banks & Credit Unions",
            "subcategory":"Investment Brokerage",
            "type":"Services"
        },
        {
            "category":"Banks & Credit Unions",
            "subcategory":"Financial Services",
            "type":"Services"
        }
    ],
    "sg:phone":"+1 610 366 9499",
    "sg:postcode":"18080",
    "sg:province":"PA",
    "sg:tags":[
        "advisory",
        "planner"
    ],
    "wof:name":"Maron Financial Solutions",
    "wof:placetype":"venue"
},
  "geometry": {"coordinates":[-75.564252,40.714612],"type":"Point"}
}