{
  "type": "Feature",
  "properties": {
    "addr:full":"207 E 8th St Pittsburgh PA 15215",
    "addr:housenumber":"207",
    "addr:postcode":"15215",
    "addr:street":"E 8Th St",
    "iso:country":"US",
    "sg:address":"207 E 8th St",
    "sg:city":"Pittsburgh",
    "sg:classifiers":[
        {
            "category":"Building & Trades",
            "subcategory":"Construction",
            "type":"Services"
        }
    ],
    "sg:phone":"+1   ",
    "sg:postcode":"15215",
    "sg:province":"PA",
    "sg:tags":[
        "house"
    ],
    "wof:name":"Olson Home Improvement",
    "wof:placetype":"venue"
},
  "geometry": {"coordinates":[-79.902843,40.496384],"type":"Point"}
}