{
  "type": "Feature",
  "properties": {
    "addr:full":"7000 State Rd Philadelphia PA 19135",
    "addr:housenumber":"7000",
    "addr:postcode":"19135",
    "addr:street":"State Rd",
    "iso:country":"US",
    "sg:address":"7000 State Rd",
    "sg:city":"Philadelphia",
    "sg:classifiers":[
        {
            "category":"Wholesale",
            "subcategory":"Motor Vehicles",
            "type":"Manufacturing & Wholesale Goods"
        }
    ],
    "sg:phone":"+1 215 335 4884",
    "sg:postcode":"19135",
    "sg:province":"PA",
    "sg:tags":[
        "auction",
        "automotive",
        "automobile"
    ],
    "sg:website":"http://www.aspiteauto.com",
    "wof:name":"Aspite Auto Auction",
    "wof:placetype":"venue"
},
  "geometry": {"coordinates":[-75.03716300000001,40.023109],"type":"Point"}
}