{
  "type": "Feature",
  "properties": {
    "addr:full":"217 Scholl St State College PA 16801",
    "addr:housenumber":"217",
    "addr:postcode":"16801",
    "addr:street":"Scholl St",
    "iso:country":"US",
    "sg:address":"217 Scholl St",
    "sg:city":"State College",
    "sg:classifiers":[
        {
            "category":"Education",
            "subcategory":"School",
            "type":"Public Place"
        }
    ],
    "sg:phone":"+1 814 231 5026",
    "sg:postcode":"16801",
    "sg:province":"PA",
    "sg:website":"www.scasd.k12.pa.us",
    "wof:name":"Houserville Elementary School",
    "wof:placetype":"venue"
},
  "geometry": {"coordinates":[-77.82994600000001,40.825326],"type":"Point"}
}