{
  "type": "Feature",
  "properties": {
    "addr:full":"1310 Farren Ln West Chester PA 19380",
    "addr:housenumber":"1310",
    "addr:postcode":"19380",
    "addr:street":"Farren Ln",
    "iso:country":"US",
    "sg:address":"1310 Farren Ln",
    "sg:city":"West Chester",
    "sg:classifiers":[
        {
            "category":"Professional",
            "type":"Services"
        }
    ],
    "sg:phone":"+1   ",
    "sg:postcode":"19380",
    "sg:province":"PA",
    "wof:name":"Truewireless Inc",
    "wof:placetype":"venue"
},
  "geometry": {"coordinates":[-75.61123600000001,39.997927],"type":"Point"}
}