{
  "type": "Feature",
  "properties": {
    "iso:country":"US",
    "sg:address":"432 Cascade St",
    "sg:city":"Erie",
    "sg:classifiers":[
        {
            "category":"Bars & Pubs",
            "type":"Food & Drink"
        }
    ],
    "sg:phone":"+1 814 455 6351",
    "sg:postcode":"16507",
    "sg:province":"PA",
    "wof:name":"Tivoli Tavern",
    "wof:placetype":"venue"
},
  "geometry": {"coordinates":[-80.106922,42.123093],"type":"Point"}
}