{
  "type": "Feature",
  "properties": {
    "iso:country":"US",
    "sg:address":"616 Picnic Ln",
    "sg:city":"Selinsgrove",
    "sg:classifiers":[
        {
            "category":"Health Services",
            "subcategory":"Doctor",
            "type":"Services"
        }
    ],
    "sg:phone":"+1 570 286 7754",
    "sg:postcode":"17870",
    "sg:province":"PA",
    "sg:tags":[
        "physician",
        "surgeon"
    ],
    "wof:name":"P J Bruno MD",
    "wof:placetype":"venue"
},
  "geometry": {"coordinates":[-76.843951,40.837606],"type":"Point"}
}