{
  "type": "Feature",
  "properties": {
    "iso:country":"US",
    "sg:address":"1019 N 5th St",
    "sg:city":"Philadelphia",
    "sg:classifiers":[
        {
            "category":"Education",
            "subcategory":"School",
            "type":"Public Place"
        },
        {
            "category":"Organizations",
            "subcategory":"Religious Organization",
            "type":"Services"
        }
    ],
    "sg:phone":"+1 215 627 3954",
    "sg:postcode":"19123",
    "sg:province":"PA",
    "wof:name":"Saint Peter's Roman Catholic Church",
    "wof:placetype":"venue"
},
  "geometry": {"coordinates":[-75.14503999999999,39.969267],"type":"Point"}
}