{
  "type": "Feature",
  "properties": {
    "addr:full":"1586 Old Forge Rd Annville PA 17003",
    "addr:housenumber":"1586",
    "addr:postcode":"17003",
    "addr:street":"Old Forge Rd",
    "iso:country":"US",
    "sg:address":"1586 Old Forge Rd",
    "sg:city":"Annville",
    "sg:classifiers":[
        {
            "category":"Building & Trades",
            "subcategory":"Plumbing",
            "type":"Services"
        }
    ],
    "sg:phone":"+1 717 838 2210",
    "sg:postcode":"17003",
    "sg:province":"PA",
    "sg:tags":[
        "plumber",
        "industrial",
        "contractors-commercial"
    ],
    "wof:name":"John Habecker Inc",
    "wof:placetype":"venue"
},
  "geometry": {"coordinates":[-76.593403,40.341258],"type":"Point"}
}