{
  "type": "Feature",
  "properties": {
    "iso:country":"US",
    "sg:address":"90 Commerce Dr",
    "sg:city":"Aston",
    "sg:classifiers":[
        {
            "category":"Professional",
            "subcategory":"Advertising",
            "type":"Services"
        }
    ],
    "sg:phone":"+1 610 859 0500",
    "sg:postcode":"19014",
    "sg:province":"PA",
    "sg:tags":[
        "mail",
        "direct"
    ],
    "sg:website":"www.actionmailer.com",
    "wof:name":"Action Mailers Inc",
    "wof:placetype":"venue"
},
  "geometry": {"coordinates":[-75.404358,39.851114],"type":"Point"}
}