{
  "type": "Feature",
  "properties": {
    "iso:country":"US",
    "sg:address":"224 Stark Rd",
    "sg:city":"Sarver",
    "sg:classifiers":[
        {
            "category":"Shopping",
            "subcategory":"Shoes",
            "type":"Retail Goods"
        }
    ],
    "sg:phone":"+1   ",
    "sg:postcode":"16055",
    "sg:province":"PA",
    "wof:name":"T K Ridge Contracting",
    "wof:placetype":"venue"
},
  "geometry": {"coordinates":[-79.798703,40.690011],"type":"Point"}
}