{
  "type": "Feature",
  "properties": {
    "iso:country":"US",
    "sg:address":"954 Beechwood Dr",
    "sg:city":"Lansdale",
    "sg:classifiers":[
        {
            "category":"Shopping",
            "type":"Retail Goods"
        }
    ],
    "sg:phone":"+1 215 855 3662",
    "sg:postcode":"19446",
    "sg:province":"PA",
    "sg:tags":[
        "merchandise"
    ],
    "wof:name":"Flag Center",
    "wof:placetype":"venue"
},
  "geometry": {"coordinates":[-75.261528,40.243348],"type":"Point"}
}