{
  "type": "Feature",
  "properties": {
    "iso:country":"US",
    "sg:address":"783 Illini Dr",
    "sg:city":"Monroeville",
    "sg:classifiers":[
        {
            "category":"Banks & Credit Unions",
            "subcategory":"Bank",
            "type":"Services"
        }
    ],
    "sg:phone":"+1   ",
    "sg:postcode":"15146",
    "sg:province":"PA",
    "sg:tags":[
        "personal",
        "institution"
    ],
    "wof:name":"Creative Funding Solutions",
    "wof:placetype":"venue"
},
  "geometry": {"coordinates":[-79.722809,40.436177],"type":"Point"}
}