{
  "type": "Feature",
  "properties": {
    "addr:full":"10009 S Watson Run Rd Meadville PA 16335",
    "addr:housenumber":"10009",
    "addr:postcode":"16335",
    "addr:street":"S Watson Run Rd",
    "iso:country":"US",
    "sg:address":"10009 S Watson Run Rd",
    "sg:city":"Meadville",
    "sg:classifiers":[
        {
            "category":"Utilities",
            "subcategory":"Electric",
            "type":"Services"
        },
        {
            "category":"Manufacturing",
            "subcategory":"Electronics",
            "type":"Manufacturing & Wholesale Goods"
        },
        {
            "category":"Building & Trades",
            "subcategory":"Construction",
            "type":"Services"
        },
        {
            "category":"Building & Trades",
            "subcategory":"Electrical",
            "type":"Services"
        }
    ],
    "sg:phone":"+1 814 336 5249",
    "sg:postcode":"16335",
    "sg:province":"PA",
    "sg:tags":[
        "industrial",
        "electrician",
        "altering",
        "equipment-testing",
        "contractor",
        "contractors-commercial",
        "remodeling"
    ],
    "wof:name":"Mailliard Electric Co",
    "wof:placetype":"venue"
},
  "geometry": {"coordinates":[-80.226349,41.602625],"type":"Point"}
}