{
  "type": "Feature",
  "properties": {
    "iso:country":"US",
    "sg:address":"456 Penn Ave",
    "sg:city":"Midland",
    "sg:classifiers":[
        {
            "category":"Professional",
            "subcategory":"Management & Consulting",
            "type":"Services"
        }
    ],
    "sg:phone":"+1 724 643 4839",
    "sg:postcode":"15059",
    "sg:province":"PA",
    "sg:tags":[
        "marketing",
        "program"
    ],
    "wof:name":"Testaments In Black",
    "wof:placetype":"venue"
},
  "geometry": {"coordinates":[-80.45592499999999,40.64133],"type":"Point"}
}