{
  "type": "Feature",
  "properties": {
    "addr:full":"701 E Spring St Titusville PA 16354",
    "addr:housenumber":"701",
    "addr:postcode":"16354",
    "addr:street":"E Spring St",
    "iso:country":"US",
    "sg:address":"701 E Spring St",
    "sg:city":"Titusville",
    "sg:classifiers":[
        {
            "category":"Professional",
            "subcategory":"Business Services",
            "type":"Services"
        }
    ],
    "sg:phone":"+1 814 827 2540",
    "sg:postcode":"16354",
    "sg:province":"PA",
    "sg:tags":[
        "development",
        "product",
        "designers-industrial",
        "marketing",
        "commercial",
        "design"
    ],
    "wof:name":"Titusville Design Service",
    "wof:placetype":"venue"
},
  "geometry": {"coordinates":[-79.666612,41.62645],"type":"Point"}
}