{
  "type": "Feature",
  "properties": {
    "addr:full":"1012 E Carson St Pittsburgh PA 15203",
    "addr:housenumber":"1012",
    "addr:postcode":"15203",
    "addr:street":"E Carson St",
    "iso:country":"US",
    "sg:address":"1012 E Carson St",
    "sg:city":"Pittsburgh",
    "sg:classifiers":[
        {
            "category":"Real Estate",
            "subcategory":"Real Estate Agent",
            "type":"Services"
        }
    ],
    "sg:phone":"+1 412 381 1166",
    "sg:postcode":"15203",
    "sg:province":"PA",
    "sg:tags":[
        "rental"
    ],
    "sg:website":"www.realtycounseling.com",
    "wof:name":"Realty Counseling Co",
    "wof:placetype":"venue"
},
  "geometry": {"coordinates":[-79.98844200000001,40.428742],"type":"Point"}
}