{
  "type": "Feature",
  "properties": {
    "iso:country":"US",
    "sg:address":"109 Fairground St",
    "sg:city":"Muncy",
    "sg:classifiers":[
        {
            "category":"Retail",
            "subcategory":"Auto Repair",
            "type":"Services"
        }
    ],
    "sg:phone":"+1 570 546 7533",
    "sg:postcode":"17756",
    "sg:province":"PA",
    "sg:tags":[
        "repairing",
        "automobile"
    ],
    "wof:name":"B & R East Muncy Garage",
    "wof:placetype":"venue"
},
  "geometry": {"coordinates":[-76.774191,41.207156],"type":"Point"}
}