{
  "type": "Feature",
  "properties": {
    "iso:country":"US",
    "sg:address":"158 N County Line Rd",
    "sg:city":"Souderton",
    "sg:classifiers":[
        {
            "category":"Personal",
            "subcategory":"Beauty Salon",
            "type":"Services"
        }
    ],
    "sg:phone":"+1   ",
    "sg:postcode":"18964",
    "sg:province":"PA",
    "sg:tags":[
        "shop"
    ],
    "wof:name":"Galen L Nash",
    "wof:placetype":"venue"
},
  "geometry": {"coordinates":[-75.315712,40.317718],"type":"Point"}
}