{
  "type": "Feature",
  "properties": {
    "addr:full":"902 Allegheny St Jersey Shore PA 17740",
    "addr:housenumber":"902",
    "addr:postcode":"17740",
    "addr:street":"Allegheny St",
    "iso:country":"US",
    "sg:address":"902 Allegheny St",
    "sg:city":"Jersey Shore",
    "sg:classifiers":[
        {
            "category":"Manufacturing",
            "subcategory":"Printing",
            "type":"Manufacturing & Wholesale Goods"
        }
    ],
    "sg:phone":"+1 570 398 2117",
    "sg:postcode":"17740",
    "sg:province":"PA",
    "sg:tags":[
        "lithographic",
        "commercial"
    ],
    "wof:name":"Ye Olde Print Shoppe",
    "wof:placetype":"venue"
},
  "geometry": {"coordinates":[-77.26548,41.204253],"type":"Point"}
}