{
  "type": "Feature",
  "properties": {
    "iso:country":"US",
    "sg:address":"110 N Reading Ave",
    "sg:city":"Boyertown",
    "sg:classifiers":[
        {
            "category":"Wholesale",
            "subcategory":"Durable Goods & Equipment",
            "type":"Manufacturing & Wholesale Goods"
        }
    ],
    "sg:phone":"+1 610 473 1455",
    "sg:postcode":"19512",
    "sg:province":"PA",
    "sg:tags":[
        "representative",
        "manufacturer"
    ],
    "wof:name":"Dia Tek",
    "wof:placetype":"venue"
},
  "geometry": {"coordinates":[-75.63472,40.336238],"type":"Point"}
}