{
  "type": "Feature",
  "properties": {
    "iso:country":"US",
    "sg:address":"108 W Main St",
    "sg:city":"Fairfield",
    "sg:classifiers":[
        {
            "category":"Utilities",
            "subcategory":"Sewage",
            "type":"Services"
        }
    ],
    "sg:phone":"+1 717 642 6557",
    "sg:postcode":"17320",
    "sg:province":"PA",
    "sg:tags":[
        "disposal",
        "system"
    ],
    "wof:name":"Fairfield Municipal Authority",
    "wof:placetype":"venue"
},
  "geometry": {"coordinates":[-77.371167,39.785575],"type":"Point"}
}