{
  "type": "Feature",
  "properties": {
    "addr:full":"803 E Pittsburgh Mall East Pittsburgh PA 15112",
    "addr:housenumber":"803",
    "addr:postcode":"15112",
    "addr:street":"E Pittsburgh Mall",
    "iso:country":"US",
    "sg:address":"803 E Pittsburgh Mall",
    "sg:city":"East Pittsburgh",
    "sg:classifiers":[
        {
            "category":"Organizations",
            "subcategory":"Non-profit Organization",
            "type":"Services"
        }
    ],
    "sg:phone":"+1 412 829 3910",
    "sg:postcode":"15112",
    "sg:province":"PA",
    "sg:tags":[
        "human"
    ],
    "wof:name":"Supportive Housing Management",
    "wof:placetype":"venue"
},
  "geometry": {"coordinates":[-79.834586,40.401005],"type":"Point"}
}