{
  "type": "Feature",
  "properties": {
    "iso:country":"US",
    "sg:address":"47 Pheasant Rd",
    "sg:city":"Saylorsburg",
    "sg:classifiers":[
        {
            "category":"Professional",
            "type":"Services"
        }
    ],
    "sg:phone":"+1   ",
    "sg:postcode":"18353",
    "sg:province":"PA",
    "wof:name":"Esther Queen Originals",
    "wof:placetype":"venue"
},
  "geometry": {"coordinates":[-75.38738600000001,40.885598],"type":"Point"}
}