{
  "type": "Feature",
  "properties": {
    "iso:country":"US",
    "sg:address":"202 Jefferson Ct",
    "sg:city":"Quakertown",
    "sg:classifiers":[
        {
            "category":"Arts & Performance",
            "subcategory":"Theater",
            "type":"Entertainment"
        }
    ],
    "sg:phone":"+1 215 529 5309",
    "sg:postcode":"18951",
    "sg:province":"PA",
    "sg:tags":[
        "entertainer"
    ],
    "wof:name":"Caricatures By Kathy Bailey",
    "wof:placetype":"venue"
},
  "geometry": {"coordinates":[-75.346485,40.427939],"type":"Point"}
}