{
  "type": "Feature",
  "properties": {
    "addr:full":"4201 Jonathan Ln Harrisburg PA 17110",
    "addr:housenumber":"4201",
    "addr:postcode":"17110",
    "addr:street":"Jonathan Ln",
    "iso:country":"US",
    "sg:address":"4201 Jonathan Ln",
    "sg:city":"Harrisburg",
    "sg:classifiers":[
        {
            "category":"Sports & Exercise",
            "subcategory":"Gym",
            "type":"Entertainment"
        }
    ],
    "sg:phone":"+1   ",
    "sg:postcode":"17110",
    "sg:province":"PA",
    "sg:tags":[
        "fitness",
        "physical",
        "facility"
    ],
    "wof:name":"Slim N Trim Figure Salon",
    "wof:placetype":"venue"
},
  "geometry": {"coordinates":[-76.870628,40.324873],"type":"Point"}
}