{
  "type": "Feature",
  "properties": {
    "iso:country":"US",
    "sg:address":"1200 Market St",
    "sg:city":"Lemoyne",
    "sg:classifiers":[
        {
            "category":"Personal",
            "subcategory":"Beauty Salon",
            "type":"Services"
        }
    ],
    "sg:phone":"+1 717 737 3544",
    "sg:postcode":"17043",
    "sg:province":"PA",
    "wof:name":"Just For You Salon",
    "wof:placetype":"venue"
},
  "geometry": {"coordinates":[-76.908051,40.241779],"type":"Point"}
}