{
  "type": "Feature",
  "properties": {
    "iso:country":"US",
    "sg:address":"445 N Queen St",
    "sg:city":"Littlestown",
    "sg:classifiers":[
        {
            "category":"Restaurant",
            "type":"Food & Drink"
        }
    ],
    "sg:phone":"+1 717 359 8889",
    "sg:postcode":"17340",
    "sg:province":"PA",
    "wof:name":"LaBella Italia",
    "wof:placetype":"venue"
},
  "geometry": {"coordinates":[-77.092913,39.749684],"type":"Point"}
}