{
  "type": "Feature",
  "properties": {
    "addr:full":"260 S 18th St Philadelphia PA 19103",
    "addr:housenumber":"260",
    "addr:postcode":"19103",
    "addr:street":"S 18Th St",
    "iso:country":"US",
    "sg:address":"260 S 18th St",
    "sg:city":"Philadelphia",
    "sg:classifiers":[
        {
            "category":"Shopping",
            "type":"Retail Goods"
        }
    ],
    "sg:phone":"+1 215 735 2922",
    "sg:postcode":"19103",
    "sg:province":"PA",
    "sg:tags":[
        "antique",
        "appraisal",
        "consultation",
        "painting"
    ],
    "wof:name":"David David Gallery",
    "wof:placetype":"venue"
},
  "geometry": {"coordinates":[-75.17130299999999,39.948101],"type":"Point"}
}