{
  "type": "Feature",
  "properties": {
    "addr:full":"2401 W Emaus Ave Allentown PA 18103",
    "addr:housenumber":"2401",
    "addr:postcode":"18103",
    "addr:street":"W Emaus Ave",
    "iso:country":"US",
    "sg:address":"2401 W Emaus Ave",
    "sg:city":"Allentown",
    "sg:classifiers":[
        {
            "category":"Wholesale",
            "subcategory":"Non-durable Goods",
            "type":"Manufacturing & Wholesale Goods"
        }
    ],
    "sg:phone":"+1 610 791 5250",
    "sg:postcode":"18103",
    "sg:province":"PA",
    "wof:name":"Comfoot Brand Products",
    "wof:placetype":"venue"
},
  "geometry": {"coordinates":[-75.47481999999999,40.565442],"type":"Point"}
}