{
  "type": "Feature",
  "properties": {
    "addr:full":"1149 Parkwood Rd Indiana PA 15701",
    "addr:housenumber":"1149",
    "addr:postcode":"15701",
    "addr:street":"Parkwood Rd",
    "iso:country":"US",
    "sg:address":"1149 Parkwood Rd",
    "sg:city":"Indiana",
    "sg:classifiers":[
        {
            "category":"Professional",
            "subcategory":"Business Services",
            "type":"Services"
        }
    ],
    "sg:phone":"+1 724 349 2076",
    "sg:postcode":"15701",
    "sg:province":"PA",
    "sg:tags":[
        "notary"
    ],
    "wof:name":"Clawson's Notary Svc",
    "wof:placetype":"venue"
},
  "geometry": {"coordinates":[-79.259427,40.620085],"type":"Point"}
}