{
  "type": "Feature",
  "properties": {
    "iso:country":"US",
    "sg:address":"105 Brookwood Dr",
    "sg:city":"Carlisle",
    "sg:classifiers":[
        {
            "category":"Building & Trades",
            "subcategory":"Construction",
            "type":"Services"
        }
    ],
    "sg:phone":"+1   ",
    "sg:postcode":"17013",
    "sg:province":"PA",
    "sg:tags":[
        "residential"
    ],
    "wof:name":"R Downing",
    "wof:placetype":"venue"
},
  "geometry": {"coordinates":[-77.178673,40.235908],"type":"Point"}
}