{
  "type": "Feature",
  "properties": {
    "iso:country":"US",
    "sg:address":"1526 W Duncannon Ave",
    "sg:city":"Philadelphia",
    "sg:classifiers":[
        {
            "category":"Bars & Pubs",
            "type":"Food & Drink"
        }
    ],
    "sg:phone":"+1 215 329 8010",
    "sg:postcode":"19141",
    "sg:province":"PA",
    "sg:tags":[
        "lounge",
        "drinking",
        "cocktail"
    ],
    "wof:name":"Casey's Lounge Inc",
    "wof:placetype":"venue"
},
  "geometry": {"coordinates":[-75.148762,40.03252],"type":"Point"}
}