{
  "type": "Feature",
  "properties": {
    "iso:country":"US",
    "sg:address":"1510 Bryant Ln",
    "sg:city":"Jenkintown",
    "sg:classifiers":[
        {
            "category":"Manufacturing",
            "subcategory":"Buildings",
            "type":"Manufacturing & Wholesale Goods"
        },
        {
            "category":"Building & Trades",
            "subcategory":"Construction",
            "type":"Services"
        }
    ],
    "sg:phone":"+1 215 884 2448",
    "sg:postcode":"19046",
    "sg:province":"PA",
    "sg:tags":[
        "home",
        "builder",
        "contractor"
    ],
    "wof:name":"Dove Weiner Construction",
    "wof:placetype":"venue"
},
  "geometry": {"coordinates":[-75.088639,40.10743],"type":"Point"}
}