{
  "type": "Feature",
  "properties": {
    "iso:country":"US",
    "sg:address":"1204 Reins Cir",
    "sg:city":"New Hope",
    "sg:classifiers":[
        {
            "category":"Professional",
            "subcategory":"Business Services",
            "type":"Services"
        }
    ],
    "sg:phone":"+1 215 794 1114",
    "sg:postcode":"18938",
    "sg:province":"PA",
    "sg:website":"www.directcardprocessing.com",
    "wof:name":"Payment Processing Direct",
    "wof:placetype":"venue"
},
  "geometry": {"coordinates":[-75.02545499999999,40.347229],"type":"Point"}
}