{
  "type": "Feature",
  "properties": {
    "iso:country":"US",
    "sg:address":"963 S Eighty Eight Rd",
    "sg:city":"Carmichaels",
    "sg:classifiers":[
        {
            "category":"Building & Trades",
            "subcategory":"Cleaning & Sanitation",
            "type":"Services"
        }
    ],
    "sg:phone":"+1 724 966 9025",
    "sg:postcode":"15320",
    "sg:province":"PA",
    "sg:tags":[
        "janitor"
    ],
    "wof:name":"Carletta's Cleaning Svc",
    "wof:placetype":"venue"
},
  "geometry": {"coordinates":[-79.954559,39.861643],"type":"Point"}
}