{
  "type": "Feature",
  "properties": {
    "addr:full":"102 W Pike St Canonsburg PA 15317",
    "addr:housenumber":"102",
    "addr:postcode":"15317",
    "addr:street":"W Pike St",
    "iso:country":"US",
    "sg:address":"102 W Pike St",
    "sg:city":"Canonsburg",
    "sg:classifiers":[
        {
            "category":"Professional",
            "subcategory":"Lawyer & Legal Services",
            "type":"Services"
        }
    ],
    "sg:phone":"+1 724 745 6590",
    "sg:postcode":"15317",
    "sg:province":"PA",
    "sg:tags":[
        "notary"
    ],
    "wof:name":"Rakoczy's Notary Service",
    "wof:placetype":"venue"
},
  "geometry": {"coordinates":[-80.188519,40.258609],"type":"Point"}
}