{
  "type": "Feature",
  "properties": {
    "iso:country":"US",
    "sg:address":"736 S Oakland Ave",
    "sg:city":"Sharon",
    "sg:classifiers":[
        {
            "category":"Organizations",
            "subcategory":"Religious Organization",
            "type":"Services"
        }
    ],
    "sg:phone":"+1   ",
    "sg:postcode":"16146",
    "sg:province":"PA",
    "wof:name":"Corporation of President of Th",
    "wof:placetype":"venue"
},
  "geometry": {"coordinates":[-80.499484,41.224202],"type":"Point"}
}