{
  "type": "Feature",
  "properties": {
    "iso:country":"US",
    "sg:address":"102 Timber Village Center",
    "sg:city":"Mercer",
    "sg:classifiers":[
        {
            "category":"Personal",
            "subcategory":"Beauty Salon",
            "type":"Services"
        }
    ],
    "sg:phone":"+1 724 662 4252",
    "sg:postcode":"16137",
    "sg:province":"PA",
    "wof:name":"Sandy's Hair Biz",
    "wof:placetype":"venue"
},
  "geometry": {"coordinates":[-80.25739799999999,41.226896],"type":"Point"}
}