{
  "type": "Feature",
  "properties": {
    "addr:full":"655 Wheatlyn Dr York PA 17403",
    "addr:housenumber":"655",
    "addr:postcode":"17403",
    "addr:street":"Wheatlyn Dr",
    "iso:country":"US",
    "sg:address":"655 Wheatlyn Dr",
    "sg:city":"York",
    "sg:classifiers":[
        {
            "category":"Banks & Credit Unions",
            "subcategory":"Bank",
            "type":"Services"
        }
    ],
    "sg:phone":"+1   ",
    "sg:postcode":"17403",
    "sg:province":"PA",
    "sg:tags":[
        "mortgage"
    ],
    "wof:name":"South Central Mortgage Group I",
    "wof:placetype":"venue"
},
  "geometry": {"coordinates":[-76.705974,39.960175],"type":"Point"}
}