{
  "type": "Feature",
  "properties": {
    "iso:country":"US",
    "sg:address":"1314 Burke Rd",
    "sg:city":"West Chester",
    "sg:classifiers":[
        {
            "category":"Education",
            "subcategory":"School",
            "type":"Public Place"
        }
    ],
    "sg:phone":"+1 610 436 7250",
    "sg:postcode":"19380",
    "sg:province":"PA",
    "sg:website":"www.wcasd.k12.pa.us",
    "wof:name":"E N Peirce Middle School",
    "wof:placetype":"venue"
},
  "geometry": {"coordinates":[-75.61940199999999,39.997313],"type":"Point"}
}