{
  "type": "Feature",
  "properties": {
    "iso:country":"US",
    "sg:address":"601 Rte 18",
    "sg:city":"Monaca",
    "sg:classifiers":[
        {
            "category":"Restaurant",
            "type":"Food & Drink"
        }
    ],
    "sg:phone":"+1 724 728 6932",
    "sg:postcode":"15061",
    "sg:province":"PA",
    "sg:tags":[
        "sandwich"
    ],
    "wof:name":"Jody's Gyros",
    "wof:placetype":"venue"
},
  "geometry": {"coordinates":[-80.32287700000001,40.667941],"type":"Point"}
}