{
  "type": "Feature",
  "properties": {
    "addr:full":"317 E Street Rd Feastervl Trvs PA 19053",
    "addr:housenumber":"317",
    "addr:postcode":"19053",
    "addr:street":"E Street Rd",
    "iso:country":"US",
    "sg:address":"317 E Street Rd",
    "sg:city":"Feastervl Trvs",
    "sg:classifiers":[
        {
            "category":"Home & Garden",
            "subcategory":"Building Materials",
            "type":"Retail Goods"
        }
    ],
    "sg:phone":"+1 215 355 3646",
    "sg:postcode":"19053",
    "sg:province":"PA",
    "sg:tags":[
        "paint"
    ],
    "wof:name":"MAB Paint Store",
    "wof:placetype":"venue"
},
  "geometry": {"coordinates":[-75.010987,40.155793],"type":"Point"}
}