{
  "type": "Feature",
  "properties": {
    "addr:full":"1716 Crystal Lake Rd Hughesville PA 17737",
    "addr:housenumber":"1716",
    "addr:postcode":"17737",
    "addr:street":"Crystal Lake Rd",
    "iso:country":"US",
    "sg:address":"1716 Crystal Lake Rd",
    "sg:city":"Hughesville",
    "sg:classifiers":[
        {
            "category":"Travel",
            "subcategory":"Hotels & Motels",
            "type":"Entertainment"
        }
    ],
    "sg:phone":"+1 570 584 2698",
    "sg:postcode":"17737",
    "sg:province":"PA",
    "sg:tags":[
        "resort",
        "center",
        "skiing"
    ],
    "sg:website":"www.crystallakeskicenter.com",
    "wof:name":"Crystal Lake Camps & Ski Ctr",
    "wof:placetype":"venue"
},
  "geometry": {"coordinates":[-76.69738099999999,41.372527],"type":"Point"}
}