{
  "type": "Feature",
  "properties": {
    "iso:country":"US",
    "sg:address":"6411 Union Deposit Rd",
    "sg:city":"Harrisburg",
    "sg:classifiers":[
        {
            "category":"Building & Trades",
            "subcategory":"Construction",
            "type":"Services"
        }
    ],
    "sg:phone":"+1   ",
    "sg:postcode":"17111",
    "sg:province":"PA",
    "sg:tags":[
        "contractor"
    ],
    "wof:name":"Dynamic Drywall",
    "wof:placetype":"venue"
},
  "geometry": {"coordinates":[-76.761438,40.289335],"type":"Point"}
}