{
  "type": "Feature",
  "properties": {
    "iso:country":"US",
    "sg:address":"1638 Lincoln Way",
    "sg:city":"Mc Keesport",
    "sg:classifiers":[
        {
            "category":"Retail",
            "subcategory":"Funeral Services",
            "type":"Services"
        }
    ],
    "sg:phone":"+1 412 672 6322",
    "sg:postcode":"15131",
    "sg:province":"PA",
    "sg:tags":[
        "director"
    ],
    "wof:name":"Jennifer S Jordan Funeral Home",
    "wof:placetype":"venue"
},
  "geometry": {"coordinates":[-79.81564299999999,40.34557],"type":"Point"}
}