{
  "type": "Feature",
  "properties": {
    "addr:full":"228 Sylvania Ave Glenside PA 19038",
    "addr:housenumber":"228",
    "addr:postcode":"19038",
    "addr:street":"Sylvania Ave",
    "iso:country":"US",
    "sg:address":"228 Sylvania Ave",
    "sg:city":"Glenside",
    "sg:classifiers":[
        {
            "category":"Real Estate",
            "subcategory":"Real Estate Operator",
            "type":"Services"
        }
    ],
    "sg:phone":"+1   ",
    "sg:postcode":"19038",
    "sg:province":"PA",
    "sg:tags":[
        "building",
        "nonresidential"
    ],
    "wof:name":"Souderton Shopping Center Inc",
    "wof:placetype":"venue"
},
  "geometry": {"coordinates":[-75.151792,40.105392],"type":"Point"}
}