{
  "type": "Feature",
  "properties": {
    "iso:country":"US",
    "sg:address":"96 Hickory Bridge Rd",
    "sg:city":"Orrtanna",
    "sg:classifiers":[
        {
            "category":"Restaurant",
            "type":"Food & Drink"
        }
    ],
    "sg:phone":"+1 717 642 5261",
    "sg:postcode":"17353",
    "sg:province":"PA",
    "sg:website":"www.hickorybridgefarm.com",
    "wof:name":"Hickory Bridge Farm",
    "wof:placetype":"venue"
},
  "geometry": {"coordinates":[-77.371032,39.842229],"type":"Point"}
}