{
  "type": "Feature",
  "properties": {
    "iso:country":"US",
    "sg:address":"907 W Union Blvd",
    "sg:city":"Bethlehem",
    "sg:classifiers":[
        {
            "category":"Farming",
            "subcategory":"Farm & Veterinary Services",
            "type":"Manufacturing & Wholesale Goods"
        }
    ],
    "sg:phone":"+1 610 867 7139",
    "sg:postcode":"18018",
    "sg:province":"PA",
    "sg:tags":[
        "control",
        "weed"
    ],
    "wof:name":"Weeds Inc",
    "wof:placetype":"venue"
},
  "geometry": {"coordinates":[-75.39612700000001,40.625246],"type":"Point"}
}