{
  "type": "Feature",
  "properties": {
    "iso:country":"US",
    "sg:address":"3617 E Market St",
    "sg:city":"York",
    "sg:classifiers":[
        {
            "category":"Personal",
            "subcategory":"Beauty Salon",
            "type":"Services"
        }
    ],
    "sg:phone":"+1 717 755 4051",
    "sg:postcode":"17402",
    "sg:province":"PA",
    "sg:tags":[
        "shop"
    ],
    "wof:name":"York Hair Stylists",
    "wof:placetype":"venue"
},
  "geometry": {"coordinates":[-76.649573,39.983458],"type":"Point"}
}