{
  "type": "Feature",
  "properties": {
    "iso:country":"US",
    "sg:address":"250 Mount Lebanon Blvd",
    "sg:city":"Pittsburgh",
    "sg:classifiers":[
        {
            "category":"Social Services",
            "type":"Services"
        }
    ],
    "sg:phone":"+1 412 344 0247",
    "sg:postcode":"15234",
    "sg:province":"PA",
    "sg:tags":[
        "probation"
    ],
    "wof:name":"Allegheny Cnty Adult Probation",
    "wof:placetype":"venue"
},
  "geometry": {"coordinates":[-80.040053,40.367575],"type":"Point"}
}