{
  "type": "Feature",
  "properties": {
    "iso:country":"US",
    "sg:address":"2038 Race St",
    "sg:city":"Philadelphia",
    "sg:classifiers":[
        {
            "category":"Taxi",
            "type":"Transportation"
        }
    ],
    "sg:phone":"+1   ",
    "sg:postcode":"19103",
    "sg:province":"PA",
    "sg:tags":[
        "taxicab"
    ],
    "wof:name":"Skyline Taxicab Assoc Inc",
    "wof:placetype":"venue"
},
  "geometry": {"coordinates":[-75.174206,39.957576],"type":"Point"}
}