{
  "type": "Feature",
  "properties": {
    "iso:country":"US",
    "sg:address":"300 N Center Ave",
    "sg:city":"Somerset",
    "sg:classifiers":[
        {
            "category":"Government",
            "subcategory":"Office",
            "type":"Public Place"
        }
    ],
    "sg:phone":"+1   ",
    "sg:postcode":"15501",
    "sg:province":"PA",
    "sg:tags":[
        "general"
    ],
    "wof:name":"Redevlpment Auth Somerset Cnty",
    "wof:placetype":"venue"
},
  "geometry": {"coordinates":[-79.078587,40.011071],"type":"Point"}
}