{
  "type": "Feature",
  "properties": {
    "addr:full":"122 Woodcutter St Exton PA 19341",
    "addr:housenumber":"122",
    "addr:postcode":"19341",
    "addr:street":"Woodcutter St",
    "iso:country":"US",
    "sg:address":"122 Woodcutter St",
    "sg:city":"Exton",
    "sg:classifiers":[
        {
            "category":"Fast Food",
            "type":"Food & Drink"
        },
        {
            "category":"Restaurant",
            "type":"Food & Drink"
        }
    ],
    "sg:phone":"+1 610 590 4584",
    "sg:postcode":"19341",
    "sg:province":"PA",
    "sg:tags":[
        "hot",
        "hamburger",
        "dog"
    ],
    "sg:website":"http://www.buddysbbf.com",
    "wof:name":"Buddy's Burgers, Breasts and Fries",
    "wof:placetype":"venue"
},
  "geometry": {"coordinates":[-75.628912,40.023214],"type":"Point"}
}