{
  "type": "Feature",
  "properties": {
    "addr:full":"28 W Montgomery Ave Ardmore PA 19003",
    "addr:housenumber":"28",
    "addr:postcode":"19003",
    "addr:street":"W Montgomery Ave",
    "iso:country":"US",
    "sg:address":"28 W Montgomery Ave",
    "sg:city":"Ardmore",
    "sg:classifiers":[
        {
            "category":"Communications",
            "type":"Services"
        }
    ],
    "sg:phone":"+1   ",
    "sg:postcode":"19003",
    "sg:province":"PA",
    "sg:tags":[
        "communication"
    ],
    "wof:name":"Campbell Westlind",
    "wof:placetype":"venue"
},
  "geometry": {"coordinates":[-75.292841,40.010805],"type":"Point"}
}