{
  "type": "Feature",
  "properties": {
    "addr:full":"110 Main St Delaware Wtr Gap PA 18327",
    "addr:housenumber":"110",
    "addr:postcode":"18327",
    "addr:street":"Main St;Wtr",
    "iso:country":"US",
    "sg:address":"110 Main St",
    "sg:city":"Delaware Wtr Gap",
    "sg:classifiers":[
        {
            "category":"Professional",
            "subcategory":"Art Services",
            "type":"Services"
        }
    ],
    "sg:phone":"+1 570 424 0552",
    "sg:postcode":"18327",
    "sg:province":"PA",
    "sg:tags":[
        "graphic",
        "designer"
    ],
    "sg:website":"www.mantisdesign.com",
    "wof:name":"Mantis Design",
    "wof:placetype":"venue"
},
  "geometry": {"coordinates":[-75.14425799999999,40.984817],"type":"Point"}
}