{
  "type": "Feature",
  "properties": {
    "iso:country":"US",
    "sg:address":"4724 Pennell Rd",
    "sg:city":"Aston",
    "sg:classifiers":[
        {
            "category":"Restaurant",
            "type":"Food & Drink"
        }
    ],
    "sg:phone":"+1 610 497 9385",
    "sg:postcode":"19014",
    "sg:province":"PA",
    "wof:name":"Laspada's Original Steaks",
    "wof:placetype":"venue"
},
  "geometry": {"coordinates":[-75.428764,39.870172],"type":"Point"}
}