{
  "type": "Feature",
  "properties": {
    "iso:country":"US",
    "sg:address":"12298 Townsend Rd Fl 2",
    "sg:city":"Philadelphia",
    "sg:classifiers":[
        {
            "category":"Insurance",
            "subcategory":"Hazard Insurance",
            "type":"Services"
        }
    ],
    "sg:phone":"+1 215 969 1012",
    "sg:postcode":"19154",
    "sg:province":"PA",
    "sg:tags":[
        "group"
    ],
    "sg:website":"http://www.team830.org",
    "wof:name":"Teamsters Local Number 830 Employees Benefit Funds",
    "wof:placetype":"venue"
},
  "geometry": {"coordinates":[-74.96953600000001,40.113203],"type":"Point"}
}