{
  "type": "Feature",
  "properties": {
    "addr:full":"142 W Mount Kirk Ave Norristown PA 19403",
    "addr:housenumber":"142",
    "addr:postcode":"19403",
    "addr:street":"W Mount Kirk Ave",
    "iso:country":"US",
    "sg:address":"142 W Mount Kirk Ave",
    "sg:city":"Norristown",
    "sg:classifiers":[
        {
            "category":"Building & Trades",
            "subcategory":"Locksmith",
            "type":"Services"
        }
    ],
    "sg:phone":"+1 267 354 5013",
    "sg:postcode":"19403",
    "sg:province":"PA",
    "sg:tags":[
        "key"
    ],
    "wof:name":"A Express Locksmith",
    "wof:placetype":"venue"
},
  "geometry": {"coordinates":[-75.406448,40.150483],"type":"Point"}
}