{
  "type": "Feature",
  "properties": {
    "addr:full":"9 Lacrue Ave Concordville PA 19331",
    "addr:housenumber":"9",
    "addr:postcode":"19331",
    "addr:street":"Lacrue Ave",
    "iso:country":"US",
    "sg:address":"9 Lacrue Ave",
    "sg:city":"Concordville",
    "sg:classifiers":[
        {
            "category":"Real Estate",
            "subcategory":"Real Estate Operator",
            "type":"Services"
        }
    ],
    "sg:phone":"+1 610 358 9012",
    "sg:postcode":"19331",
    "sg:province":"PA",
    "sg:tags":[
        "apartment"
    ],
    "wof:name":"Mre",
    "wof:placetype":"venue"
},
  "geometry": {"coordinates":[-75.5317,39.884602],"type":"Point"}
}