{
  "type": "Feature",
  "properties": {
    "iso:country":"US",
    "sg:address":"316 Shingle Mill Dr",
    "sg:city":"Drums",
    "sg:classifiers":[
        {
            "category":"Professional",
            "subcategory":"Employment Agencies",
            "type":"Services"
        }
    ],
    "sg:phone":"+1   ",
    "sg:postcode":"18222",
    "sg:province":"PA",
    "sg:tags":[
        "help",
        "supply"
    ],
    "wof:name":"John J Stoffa",
    "wof:placetype":"venue"
},
  "geometry": {"coordinates":[-75.921367,41.045373],"type":"Point"}
}