{
  "type": "Feature",
  "properties": {
    "iso:country":"US",
    "sg:address":"195 Main St",
    "sg:city":"Vintondale",
    "sg:classifiers":[
        {
            "category":"Professional",
            "subcategory":"Business Services",
            "type":"Services"
        },
        {
            "category":"Government",
            "subcategory":"Post Office",
            "type":"Public Place"
        }
    ],
    "sg:phone":"+1 814 749 7313",
    "sg:postcode":"15961",
    "sg:province":"PA",
    "sg:tags":[
        "mail",
        "shipping"
    ],
    "sg:website":"http://www.usps.com",
    "wof:name":"USPS - United States Post Office",
    "wof:placetype":"venue"
},
  "geometry": {"coordinates":[-78.911913,40.478065],"type":"Point"}
}