{
  "type": "Feature",
  "properties": {
    "addr:full":"525 Broad Ave Belle Vernon PA 15012",
    "addr:housenumber":"525",
    "addr:postcode":"15012",
    "addr:street":"Broad Ave",
    "iso:country":"US",
    "sg:address":"525 Broad Ave",
    "sg:city":"Belle Vernon",
    "sg:classifiers":[
        {
            "category":"Retail",
            "subcategory":"Auto Repair",
            "type":"Services"
        }
    ],
    "sg:phone":"+1 724 929 6068",
    "sg:postcode":"15012",
    "sg:province":"PA",
    "sg:tags":[
        "repairing",
        "automobile"
    ],
    "wof:name":"F & N Auto Repair",
    "wof:placetype":"venue"
},
  "geometry": {"coordinates":[-79.864518,40.130721],"type":"Point"}
}