{
  "type": "Feature",
  "properties": {
    "iso:country":"US",
    "sg:address":"15 Alpine Dr",
    "sg:city":"Mohnton",
    "sg:classifiers":[
        {
            "category":"Professional",
            "subcategory":"Business Services",
            "type":"Services"
        }
    ],
    "sg:phone":"+1   ",
    "sg:postcode":"19540",
    "sg:province":"PA",
    "wof:name":"D S Designs",
    "wof:placetype":"venue"
},
  "geometry": {"coordinates":[-76.00026800000001,40.291819],"type":"Point"}
}