{
  "type": "Feature",
  "properties": {
    "iso:country":"US",
    "sg:address":"385 McCorkel Rd",
    "sg:city":"Hummelstown",
    "sg:classifiers":[
        {
            "category":"Professional",
            "subcategory":"Research",
            "type":"Services"
        }
    ],
    "sg:phone":"+1   ",
    "sg:postcode":"17036",
    "sg:province":"PA",
    "sg:tags":[
        "organization",
        "noncommercial"
    ],
    "wof:name":"American Institute of Che",
    "wof:placetype":"venue"
},
  "geometry": {"coordinates":[-76.643833,40.250562],"type":"Point"}
}