{
  "type": "Feature",
  "properties": {
    "iso:country":"US",
    "sg:address":"167 Anderson Rd",
    "sg:city":"Cranberry Twp",
    "sg:classifiers":[
        {
            "category":"Building & Trades",
            "subcategory":"Construction",
            "type":"Services"
        }
    ],
    "sg:phone":"+1 724 453 2800",
    "sg:postcode":"16066",
    "sg:province":"PA",
    "sg:tags":[
        "contractor"
    ],
    "wof:name":"Naes Power Contractors",
    "wof:placetype":"venue"
},
  "geometry": {"coordinates":[-80.098456,40.718017],"type":"Point"}
}