{
  "type": "Feature",
  "properties": {
    "addr:full":"527 Baltimore Pike Springfield PA 19064",
    "addr:housenumber":"527",
    "addr:postcode":"19064",
    "addr:street":"Baltimore Pike Springfield",
    "iso:country":"US",
    "sg:address":"527 Baltimore Pike",
    "sg:city":"Springfield",
    "sg:classifiers":[
        {
            "category":"Real Estate",
            "subcategory":"Real Estate Agent",
            "type":"Services"
        }
    ],
    "sg:phone":"+1   ",
    "sg:postcode":"19064",
    "sg:province":"PA",
    "wof:name":"Lesniak Coulston & McRinney",
    "wof:placetype":"venue"
},
  "geometry": {"coordinates":[-75.323933,39.920436],"type":"Point"}
}