{
  "type": "Feature",
  "properties": {
    "addr:full":"501 N US Hwy 15 Dillsburg PA 17019",
    "addr:housenumber":"501",
    "addr:postcode":"17019",
    "addr:street":"N Us Hwy 15",
    "iso:country":"US",
    "sg:address":"501 N US Hwy 15",
    "sg:city":"Dillsburg",
    "sg:classifiers":[
        {
            "category":"Sports & Exercise",
            "subcategory":"Gym",
            "type":"Entertainment"
        }
    ],
    "sg:phone":"+1 717 502 1772",
    "sg:postcode":"17019",
    "sg:province":"PA",
    "sg:tags":[
        "spa",
        "health"
    ],
    "wof:name":"Spa Works",
    "wof:placetype":"venue"
},
  "geometry": {"coordinates":[-77.03668399999999,40.118183],"type":"Point"}
}