{
  "type": "Feature",
  "properties": {
    "addr:full":"192 Hill St Smethport PA 16749",
    "addr:housenumber":"192",
    "addr:postcode":"16749",
    "addr:street":"Hill St",
    "iso:country":"US",
    "sg:address":"192 Hill St",
    "sg:city":"Smethport",
    "sg:classifiers":[
        {
            "category":"Wholesale",
            "subcategory":"Beer",
            "type":"Manufacturing & Wholesale Goods"
        }
    ],
    "sg:phone":"+1   ",
    "sg:postcode":"16749",
    "sg:province":"PA",
    "sg:tags":[
        "beverage",
        "alcoholic"
    ],
    "wof:name":"Barr Key Inc",
    "wof:placetype":"venue"
},
  "geometry": {"coordinates":[-78.44068799999999,41.809846],"type":"Point"}
}