{
  "type": "Feature",
  "properties": {
    "iso:country":"US",
    "sg:address":"105 Glick Rd",
    "sg:city":"Narvon",
    "sg:classifiers":[
        {
            "category":"Building & Trades",
            "subcategory":"Construction",
            "type":"Services"
        }
    ],
    "sg:phone":"+1 610 286 5770",
    "sg:postcode":"17555",
    "sg:province":"PA",
    "sg:tags":[
        "builder",
        "operative"
    ],
    "wof:name":"Morgan Homes",
    "wof:placetype":"venue"
},
  "geometry": {"coordinates":[-75.945899,40.143775],"type":"Point"}
}