{
  "type": "Feature",
  "properties": {
    "addr:full":"105 Lombard Rd Red Lion PA 17356",
    "addr:housenumber":"105",
    "addr:postcode":"17356",
    "addr:street":"Lombard Rd",
    "iso:country":"US",
    "sg:address":"105 Lombard Rd",
    "sg:city":"Red Lion",
    "sg:classifiers":[
        {
            "category":"Banks & Credit Unions",
            "subcategory":"Bank",
            "type":"Services"
        }
    ],
    "sg:phone":"+1 717 244 8541",
    "sg:postcode":"17356",
    "sg:province":"PA",
    "wof:name":"M & T Bank",
    "wof:placetype":"venue"
},
  "geometry": {"coordinates":[-76.606889,39.924792],"type":"Point"}
}