{
  "type": "Feature",
  "properties": {
    "iso:country":"US",
    "sg:address":"589 Coon Hollow Rd",
    "sg:city":"Riegelsville",
    "sg:classifiers":[
        {
            "category":"Bars & Pubs",
            "type":"Food & Drink"
        }
    ],
    "sg:phone":"+1   ",
    "sg:postcode":"18077",
    "sg:province":"PA",
    "sg:tags":[
        "drinking"
    ],
    "wof:name":"Olde Towne Resteraunt and Tav",
    "wof:placetype":"venue"
},
  "geometry": {"coordinates":[-75.222236,40.56681],"type":"Point"}
}