{
  "type": "Feature",
  "properties": {
    "addr:full":"1015 Chestnut St Ste 515 Philadelphia PA 19107",
    "addr:housenumber":"1015",
    "addr:postcode":"19107",
    "addr:street":"Chestnut St Ste 515",
    "iso:country":"US",
    "sg:address":"1015 Chestnut St Ste 515",
    "sg:city":"Philadelphia",
    "sg:classifiers":[
        {
            "category":"Social Services",
            "type":"Services"
        },
        {
            "category":"Professional",
            "subcategory":"Employment Agencies",
            "type":"Services"
        }
    ],
    "sg:phone":"+1 215 923 3722",
    "sg:postcode":"19107",
    "sg:province":"PA",
    "sg:tags":[
        "workers'",
        "placement",
        "volunteer"
    ],
    "wof:name":"Intl Brotherhood Elect Wrkrs Sc7",
    "wof:placetype":"venue"
},
  "geometry": {"coordinates":[-75.15724899999999,39.950047],"type":"Point"}
}