{
  "type": "Feature",
  "properties": {
    "iso:country":"US",
    "sg:address":"465 N Main St",
    "sg:city":"Doylestown",
    "sg:classifiers":[
        {
            "category":"Health Services",
            "subcategory":"Health Practitioner",
            "type":"Services"
        }
    ],
    "sg:phone":"+1 215 340 7581",
    "sg:postcode":"18901",
    "sg:province":"PA",
    "wof:name":"Cloud Nine Massage Therapy",
    "wof:placetype":"venue"
},
  "geometry": {"coordinates":[-75.130638,40.319895],"type":"Point"}
}