{
  "type": "Feature",
  "properties": {
    "addr:full":"251 Watters Station Rd Evans City PA 16033",
    "addr:housenumber":"251",
    "addr:postcode":"16033",
    "addr:street":"Watters Station Rd",
    "iso:country":"US",
    "sg:address":"251 Watters Station Rd",
    "sg:city":"Evans City",
    "sg:classifiers":[
        {
            "category":"Shopping",
            "subcategory":"Florist",
            "type":"Retail Goods"
        }
    ],
    "sg:phone":"+1 724 538 0555",
    "sg:postcode":"16033",
    "sg:province":"PA",
    "wof:name":"Clifford Keepsakes",
    "wof:placetype":"venue"
},
  "geometry": {"coordinates":[-80.027006,40.758323],"type":"Point"}
}