{
  "type": "Feature",
  "properties": {
    "iso:country":"US",
    "sg:address":"101 N State St",
    "sg:city":"Clarks Summit",
    "sg:classifiers":[
        {
            "category":"Autos & Motor Vehicles",
            "subcategory":"Fuel & Gas Station",
            "type":"Retail Goods"
        }
    ],
    "sg:phone":"+1   ",
    "sg:postcode":"18411",
    "sg:province":"PA",
    "sg:tags":[
        "convenience",
        "station",
        "store"
    ],
    "wof:name":"Texaco",
    "wof:placetype":"venue"
},
  "geometry": {"coordinates":[-75.70520399999999,41.495729],"type":"Point"}
}