{
  "type": "Feature",
  "properties": {
    "iso:country":"US",
    "sg:address":"932 Arch St",
    "sg:city":"Philadelphia",
    "sg:classifiers":[
        {
            "category":"Professional",
            "subcategory":"Detective & Security Services",
            "type":"Services"
        }
    ],
    "sg:phone":"+1 215 238 1558",
    "sg:postcode":"19107",
    "sg:province":"PA",
    "sg:tags":[
        "information",
        "bureau"
    ],
    "wof:name":"Brenda's Interpreting & Business Service",
    "wof:placetype":"venue"
},
  "geometry": {"coordinates":[-75.155682,39.95347],"type":"Point"}
}