{
  "type": "Feature",
  "properties": {
    "iso:country":"US",
    "sg:address":"631 Penn Ave",
    "sg:city":"Glenside",
    "sg:classifiers":[
        {
            "category":"Building & Trades",
            "subcategory":"Construction",
            "type":"Services"
        }
    ],
    "sg:phone":"+1   ",
    "sg:postcode":"19038",
    "sg:province":"PA",
    "sg:tags":[
        "house"
    ],
    "wof:name":"Dougherty Brothers Inc",
    "wof:placetype":"venue"
},
  "geometry": {"coordinates":[-75.16025999999999,40.121238],"type":"Point"}
}