{
  "type": "Feature",
  "properties": {
    "iso:country":"US",
    "sg:address":"402 Locust Ln",
    "sg:city":"Danville",
    "sg:classifiers":[
        {
            "category":"Building & Trades",
            "subcategory":"Pest Control",
            "type":"Services"
        }
    ],
    "sg:phone":"+1 570 275 8745",
    "sg:postcode":"17821",
    "sg:province":"PA",
    "wof:name":"Giant Termite & Pest Control",
    "wof:placetype":"venue"
},
  "geometry": {"coordinates":[-76.588537,40.969619],"type":"Point"}
}