{
  "type": "Feature",
  "properties": {
    "addr:full":"8111 Pettis Rd Meadville PA 16335",
    "addr:housenumber":"8111",
    "addr:postcode":"16335",
    "addr:street":"Pettis Rd",
    "iso:country":"US",
    "sg:address":"8111 Pettis Rd",
    "sg:city":"Meadville",
    "sg:classifiers":[
        {
            "category":"Manufacturing",
            "subcategory":"Tools & Machinery",
            "type":"Manufacturing & Wholesale Goods"
        }
    ],
    "sg:phone":"+1 814 336 3420",
    "sg:postcode":"16335",
    "sg:province":"PA",
    "sg:tags":[
        "die",
        "maker"
    ],
    "wof:name":"P & C Tool",
    "wof:placetype":"venue"
},
  "geometry": {"coordinates":[-80.095112,41.612269],"type":"Point"}
}