{
  "type": "Feature",
  "properties": {
    "iso:country":"US",
    "sg:address":"1330 Kimberly Rd",
    "sg:city":"Sharon",
    "sg:classifiers":[
        {
            "category":"Health Services",
            "subcategory":"Health Practitioner",
            "type":"Services"
        },
        {
            "category":"Social Services",
            "subcategory":"Adult Care",
            "type":"Services"
        }
    ],
    "sg:phone":"+1 724 347 4000",
    "sg:postcode":"16146",
    "sg:province":"PA",
    "sg:tags":[
        "home",
        "living",
        "assisted",
        "elder"
    ],
    "wof:name":"Juniper Village At The Shenango Inn",
    "wof:placetype":"venue"
},
  "geometry": {"coordinates":[-80.485139,41.237161],"type":"Point"}
}