{
  "type": "Feature",
  "properties": {
    "iso:country":"US",
    "sg:address":"409 Shipwrighter Way",
    "sg:city":"Lansdale",
    "sg:classifiers":[
        {
            "category":"Professional",
            "subcategory":"Business Services",
            "type":"Services"
        }
    ],
    "sg:phone":"+1 215 368 6105",
    "sg:postcode":"19446",
    "sg:province":"PA",
    "sg:tags":[
        "consultant",
        "coach"
    ],
    "wof:name":"Property Tax Consulting",
    "wof:placetype":"venue"
},
  "geometry": {"coordinates":[-75.308268,40.254122],"type":"Point"}
}