{
  "type": "Feature",
  "properties": {
    "addr:full":"1200 Carsonia Ave Reading PA 19606",
    "addr:housenumber":"1200",
    "addr:postcode":"19606",
    "addr:street":"Carsonia Ave",
    "iso:country":"US",
    "sg:address":"1200 Carsonia Ave",
    "sg:city":"Reading",
    "sg:classifiers":[
        {
            "category":"Government",
            "subcategory":"Office",
            "type":"Public Place"
        }
    ],
    "sg:phone":"+1   ",
    "sg:postcode":"19606",
    "sg:province":"PA",
    "sg:tags":[
        "executive"
    ],
    "wof:name":"Lower Alsace Township Inc",
    "wof:placetype":"venue"
},
  "geometry": {"coordinates":[-75.872773,40.345827],"type":"Point"}
}