{
  "type": "Feature",
  "properties": {
    "iso:country":"US",
    "sg:address":"1091 Powell St",
    "sg:city":"Norristown",
    "sg:classifiers":[
        {
            "category":"Restaurant",
            "type":"Food & Drink"
        }
    ],
    "sg:phone":"+1 610 272 3227",
    "sg:postcode":"19401",
    "sg:province":"PA",
    "sg:tags":[
        "eating"
    ],
    "wof:name":"Golden Dragon",
    "wof:placetype":"venue"
},
  "geometry": {"coordinates":[-75.339646,40.12159],"type":"Point"}
}