{
  "type": "Feature",
  "properties": {
    "addr:full":"885 Viewmont Dr Dickson City PA 18519",
    "addr:housenumber":"885",
    "addr:postcode":"18519",
    "addr:street":"Viewmont Dr",
    "iso:country":"US",
    "sg:address":"885 Viewmont Dr",
    "sg:city":"Dickson City",
    "sg:classifiers":[
        {
            "category":"Restaurant",
            "type":"Food & Drink"
        }
    ],
    "sg:menulink":"http://www.allmenus.com/pa/dickson-city/172935-wendys/menu/",
    "sg:phone":"+1 570 558 0776",
    "sg:postcode":"18519",
    "sg:province":"PA",
    "sg:tags":[
        "burger",
        "american",
        "soup"
    ],
    "wof:name":"Wendy's",
    "wof:placetype":"venue"
},
  "geometry": {"coordinates":[-75.64503999999999,41.454459],"type":"Point"}
}