{
  "type": "Feature",
  "properties": {
    "addr:full":"620 S Cambria St Bellwood PA 16617",
    "addr:housenumber":"620",
    "addr:postcode":"16617",
    "addr:street":"S Cambria St",
    "iso:country":"US",
    "sg:address":"620 S Cambria St",
    "sg:city":"Bellwood",
    "sg:classifiers":[
        {
            "category":"Real Estate",
            "subcategory":"Real Estate Services",
            "type":"Services"
        },
        {
            "category":"Insurance",
            "subcategory":"Hazard Insurance",
            "type":"Services"
        },
        {
            "category":"Real Estate",
            "subcategory":"Surveying",
            "type":"Services"
        },
        {
            "category":"Insurance",
            "subcategory":"Insurance Agent",
            "type":"Services"
        }
    ],
    "sg:phone":"+1 814 742 8765",
    "sg:postcode":"16617",
    "sg:province":"PA",
    "sg:tags":[
        "industrial",
        "business",
        "commercial",
        "appraisers-commercial",
        "broker",
        "consultant",
        "buyer",
        "analyst",
        "appraiser"
    ],
    "wof:name":"Mackey, D B Insurance Agency",
    "wof:placetype":"venue"
},
  "geometry": {"coordinates":[-78.33219099999999,40.600053],"type":"Point"}
}