{
  "type": "Feature",
  "properties": {
    "addr:full":"3220 Tillman Dr Ste 201 Bensalem PA 19020",
    "addr:housenumber":"3220",
    "addr:postcode":"19020",
    "addr:street":"Tillman Dr Ste 201",
    "iso:country":"US",
    "sg:address":"3220 Tillman Dr Ste 201",
    "sg:city":"Bensalem",
    "sg:classifiers":[
        {
            "category":"Professional",
            "subcategory":"Lawyer & Legal Services",
            "type":"Services"
        }
    ],
    "sg:phone":"+1 215 638 9900",
    "sg:postcode":"19020",
    "sg:province":"PA",
    "wof:name":"Oxman Goodstadt Krevitz & Kuritz",
    "wof:placetype":"venue"
},
  "geometry": {"coordinates":[-74.9618,40.1147],"type":"Point"}
}