{
  "type": "Feature",
  "properties": {
    "iso:country":"US",
    "sg:address":"2300 S 18th St",
    "sg:city":"Philadelphia",
    "sg:classifiers":[
        {
            "category":"Organizations",
            "subcategory":"Religious Organization",
            "type":"Services"
        },
        {
            "category":"Education",
            "subcategory":"School",
            "type":"Public Place"
        }
    ],
    "sg:phone":"+1 215 334 6657",
    "sg:postcode":"19145",
    "sg:province":"PA",
    "sg:tags":[
        "church"
    ],
    "wof:name":"Trinity Christian Preschool",
    "wof:placetype":"venue"
},
  "geometry": {"coordinates":[-75.176906,39.921464],"type":"Point"}
}