{
  "type": "Feature",
  "properties": {
    "iso:country":"US",
    "sg:address":"11 E Main St",
    "sg:city":"Palmyra",
    "sg:classifiers":[
        {
            "category":"Shopping",
            "subcategory":"Antiques",
            "type":"Retail Goods"
        }
    ],
    "sg:phone":"+1 717 832 1000",
    "sg:postcode":"17078",
    "sg:province":"PA",
    "sg:website":"www.topgunmilitary.com",
    "wof:name":"Top Gun Military Apparel",
    "wof:placetype":"venue"
},
  "geometry": {"coordinates":[-76.595596,40.307598],"type":"Point"}
}