{
  "type": "Feature",
  "properties": {
    "iso:country":"US",
    "sg:address":"901 E Market St",
    "sg:city":"York",
    "sg:phone":"+1 717 845 7326",
    "sg:postcode":"17403",
    "sg:province":"PA",
    "wof:name":"Brenda's Mirrored Images",
    "wof:placetype":"venue"
},
  "geometry": {"coordinates":[-76.709503,39.969151],"type":"Point"}
}