{
  "type": "Feature",
  "properties": {
    "iso:country":"US",
    "sg:address":"12 W Lancaster Ave",
    "sg:city":"Ardmore",
    "sg:classifiers":[
        {
            "category":"Restaurant",
            "type":"Food & Drink"
        }
    ],
    "sg:phone":"+1 610 645 9595",
    "sg:postcode":"19003",
    "sg:province":"PA",
    "sg:tags":[
        "eating",
        "pizza"
    ],
    "wof:name":"Luciano's Pizza",
    "wof:placetype":"venue"
},
  "geometry": {"coordinates":[-75.291146,40.007847],"type":"Point"}
}