{
  "type": "Feature",
  "properties": {
    "iso:country":"US",
    "sg:address":"807 Crosby St",
    "sg:city":"Chester",
    "sg:classifiers":[
        {
            "category":"Professional",
            "type":"Services"
        }
    ],
    "sg:phone":"+1 610 872 5978",
    "sg:postcode":"19013",
    "sg:province":"PA",
    "sg:tags":[
        "establishment"
    ],
    "wof:name":"TFC Chester 1999 Partnership",
    "wof:placetype":"venue"
},
  "geometry": {"coordinates":[-75.359056,39.852734],"type":"Point"}
}