{
  "type": "Feature",
  "properties": {
    "iso:country":"US",
    "sg:address":"148 3 Ponds Ln",
    "sg:city":"Malvern",
    "sg:classifiers":[
        {
            "category":"Insurance",
            "subcategory":"Insurance Agent",
            "type":"Services"
        }
    ],
    "sg:phone":"+1 610 917 2284",
    "sg:postcode":"19355",
    "sg:province":"PA",
    "wof:name":"PLICA",
    "wof:placetype":"venue"
},
  "geometry": {"coordinates":[-75.507982,39.999831],"type":"Point"}
}