{
  "type": "Feature",
  "properties": {
    "iso:country":"US",
    "sg:address":"623 Spring St",
    "sg:city":"Mars",
    "sg:classifiers":[
        {
            "category":"Animal Shelter",
            "type":"Public Place"
        },
        {
            "category":"Building & Trades",
            "subcategory":"Equipment Rental",
            "type":"Services"
        }
    ],
    "sg:phone":"+1 724 625 3577",
    "sg:postcode":"16046",
    "sg:province":"PA",
    "sg:tags":[
        "seals-o-ring",
        "hydraulic",
        "supply"
    ],
    "wof:name":"Fluid Power Sealing",
    "wof:placetype":"venue"
},
  "geometry": {"coordinates":[-80.00644699999999,40.69611],"type":"Point"}
}