{
  "type": "Feature",
  "properties": {
    "iso:country":"US",
    "sg:address":"11 Western Ave.",
    "sg:city":"Parkesburg",
    "sg:phone":"+1 610 857 4759",
    "sg:postcode":"19365",
    "sg:province":"PA",
    "sg:website":"http://www.embspecialty.com",
    "wof:name":"EMB Specialty Insurance",
    "wof:placetype":"venue"
},
  "geometry": {"coordinates":[-75.90434399999999,39.960711],"type":"Point"}
}