{
  "type": "Feature",
  "properties": {
    "addr:full":"1539 Lincoln Ave Pittsburgh PA 15206",
    "addr:housenumber":"1539",
    "addr:postcode":"15206",
    "addr:street":"Lincoln Ave",
    "iso:country":"US",
    "sg:address":"1539 Lincoln Ave",
    "sg:city":"Pittsburgh",
    "sg:classifiers":[
        {
            "category":"Health Services",
            "subcategory":"Doctor",
            "type":"Services"
        }
    ],
    "sg:phone":"+1   ",
    "sg:postcode":"15206",
    "sg:province":"PA",
    "sg:tags":[
        "medical"
    ],
    "wof:name":"Edwards Robert G MD",
    "wof:placetype":"venue"
},
  "geometry": {"coordinates":[-79.89583,40.468973],"type":"Point"}
}