{
  "type": "Feature",
  "properties": {
    "iso:country":"US",
    "sg:address":"100 Nina Dr",
    "sg:city":"York",
    "sg:classifiers":[
        {
            "category":"Professional",
            "type":"Services"
        }
    ],
    "sg:phone":"+1 717 600 8221",
    "sg:postcode":"17402",
    "sg:province":"PA",
    "sg:tags":[
        "establishment"
    ],
    "wof:name":"ATC Assoc",
    "wof:placetype":"venue"
},
  "geometry": {"coordinates":[-76.62345500000001,39.96088],"type":"Point"}
}