{
  "type": "Feature",
  "properties": {
    "addr:full":"14 Union Hill Rd W Conshohocken PA 19428",
    "addr:housenumber":"14",
    "addr:postcode":"19428",
    "addr:street":"Union Hill Rd W",
    "iso:country":"US",
    "sg:address":"14 Union Hill Rd",
    "sg:city":"W Conshohocken",
    "sg:classifiers":[
        {
            "category":"Manufacturing",
            "subcategory":"Metals",
            "type":"Manufacturing & Wholesale Goods"
        }
    ],
    "sg:phone":"+1 610 397 0772",
    "sg:postcode":"19428",
    "sg:province":"PA",
    "sg:tags":[
        "production",
        "grinding"
    ],
    "wof:name":"Eastern Components",
    "wof:placetype":"venue"
},
  "geometry": {"coordinates":[-75.325675,40.068769],"type":"Point"}
}