{
  "type": "Feature",
  "properties": {
    "iso:country":"US",
    "sg:address":"2450 Schukraft Rd",
    "sg:city":"Quakertown",
    "sg:classifiers":[
        {
            "category":"Autos & Motor Vehicles",
            "subcategory":"Fuel & Gas Station",
            "type":"Retail Goods"
        }
    ],
    "sg:phone":"+1 267 373 9138",
    "sg:postcode":"18951",
    "sg:province":"PA",
    "wof:name":"Bp Balls",
    "wof:placetype":"venue"
},
  "geometry": {"coordinates":[-75.3664,40.386331],"type":"Point"}
}