{
  "type": "Feature",
  "properties": {
    "iso:country":"US",
    "sg:address":"2530 Koons Rd",
    "sg:city":"Quakertown",
    "sg:classifiers":[
        {
            "category":"Manufacturing",
            "subcategory":"Petroleum Products",
            "type":"Manufacturing & Wholesale Goods"
        }
    ],
    "sg:phone":"+1 267 671 7081",
    "sg:postcode":"18951",
    "sg:province":"PA",
    "sg:tags":[
        "candles-wholesale",
        "manufacturer"
    ],
    "wof:name":"Chandler House Candles",
    "wof:placetype":"venue"
},
  "geometry": {"coordinates":[-75.385347,40.46693],"type":"Point"}
}