{
  "type": "Feature",
  "properties": {
    "iso:country":"US",
    "sg:address":"640 Avondale Rd",
    "sg:city":"Glenside",
    "sg:classifiers":[
        {
            "category":"Insurance",
            "subcategory":"Health Insurance",
            "type":"Services"
        }
    ],
    "sg:phone":"+1 215 233 1994",
    "sg:postcode":"19038",
    "sg:province":"PA",
    "sg:tags":[
        "surgical",
        "hospitalization",
        "plan"
    ],
    "wof:name":"Edward N Swanson & Co",
    "wof:placetype":"venue"
},
  "geometry": {"coordinates":[-75.206028,40.09518],"type":"Point"}
}