{
  "type": "Feature",
  "properties": {
    "addr:full":"5815 Ferree St Pittsburgh PA 15217",
    "addr:housenumber":"5815",
    "addr:postcode":"15217",
    "addr:street":"Ferree St",
    "iso:country":"US",
    "sg:address":"5815 Ferree St",
    "sg:city":"Pittsburgh",
    "sg:classifiers":[
        {
            "category":"Wholesale",
            "subcategory":"Home Furnishings",
            "type":"Manufacturing & Wholesale Goods"
        }
    ],
    "sg:phone":"+1 412 422 8597",
    "sg:postcode":"15217",
    "sg:province":"PA",
    "sg:tags":[
        "manufacturer",
        "baskets-wholesale"
    ],
    "wof:name":"Basket Expressions By Jacy",
    "wof:placetype":"venue"
},
  "geometry": {"coordinates":[-79.922889,40.440738],"type":"Point"}
}