{
  "type": "Feature",
  "properties": {
    "addr:full":"7343 Saltsburg Rd Pittsburgh PA 15235",
    "addr:housenumber":"7343",
    "addr:postcode":"15235",
    "addr:street":"Saltsburg Rd",
    "iso:country":"US",
    "sg:address":"7343 Saltsburg Rd",
    "sg:city":"Pittsburgh",
    "sg:classifiers":[
        {
            "category":"Retail",
            "subcategory":"Auto Repair",
            "type":"Services"
        }
    ],
    "sg:phone":"+1 412 793 6228",
    "sg:postcode":"15235",
    "sg:province":"PA",
    "sg:tags":[
        "trim",
        "automobile",
        "top",
        "upholstery",
        "shop"
    ],
    "wof:name":"Michael's Auto Trim",
    "wof:placetype":"venue"
},
  "geometry": {"coordinates":[-79.78534500000001,40.477709],"type":"Point"}
}