{
  "type": "Feature",
  "properties": {
    "iso:country":"US",
    "sg:address":"2165 Swamp Pike",
    "sg:city":"Gilbertsville",
    "sg:classifiers":[
        {
            "category":"Professional",
            "type":"Services"
        }
    ],
    "sg:phone":"+1   ",
    "sg:postcode":"19525",
    "sg:province":"PA",
    "wof:name":"Gaugler",
    "wof:placetype":"venue"
},
  "geometry": {"coordinates":[-75.57359099999999,40.286927],"type":"Point"}
}