{
  "type": "Feature",
  "properties": {
    "addr:full":"517 W Southern Ave Williamsport PA 17702",
    "addr:housenumber":"517",
    "addr:postcode":"17702",
    "addr:street":"W Southern Ave",
    "iso:country":"US",
    "sg:address":"517 W Southern Ave",
    "sg:city":"Williamsport",
    "sg:classifiers":[
        {
            "category":"Shopping",
            "subcategory":"Gifts & Souvenirs",
            "type":"Retail Goods"
        }
    ],
    "sg:phone":"+1   ",
    "sg:postcode":"17702",
    "sg:province":"PA",
    "wof:name":"Pit Shop",
    "wof:placetype":"venue"
},
  "geometry": {"coordinates":[-77.00101600000001,41.231155],"type":"Point"}
}