{
  "type": "Feature",
  "properties": {
    "addr:full":"1190 Lancaster Rd Manheim PA 17545",
    "addr:housenumber":"1190",
    "addr:postcode":"17545",
    "addr:street":"Lancaster Rd",
    "iso:country":"US",
    "sg:address":"1190 Lancaster Rd",
    "sg:city":"Manheim",
    "sg:classifiers":[
        {
            "category":"Retail",
            "subcategory":"Auto Repair",
            "type":"Services"
        }
    ],
    "sg:phone":"+1 717 665 5027",
    "sg:postcode":"17545",
    "sg:province":"PA",
    "sg:tags":[
        "automobile",
        "inspection"
    ],
    "wof:name":"SGS Automotive Svc Inc",
    "wof:placetype":"venue"
},
  "geometry": {"coordinates":[-76.38276399999999,40.139907],"type":"Point"}
}