{
  "type": "Feature",
  "properties": {
    "iso:country":"US",
    "sg:address":"1170 Mars Evans City Rd",
    "sg:city":"Mars",
    "sg:classifiers":[
        {
            "category":"Personal",
            "type":"Services"
        }
    ],
    "sg:phone":"+1 724 538 0168",
    "sg:postcode":"16046",
    "sg:province":"PA",
    "sg:tags":[
        "mover"
    ],
    "wof:name":"Mobile Attic",
    "wof:placetype":"venue"
},
  "geometry": {"coordinates":[-80.024079,40.725403],"type":"Point"}
}