{
  "type": "Feature",
  "properties": {
    "addr:full":"4302 Main St Erie PA 16511",
    "addr:housenumber":"4302",
    "addr:postcode":"16511",
    "addr:street":"Main St",
    "iso:country":"US",
    "sg:address":"4302 Main St",
    "sg:city":"Erie",
    "sg:classifiers":[
        {
            "category":"Autos & Motor Vehicles",
            "subcategory":"Fuel & Gas Station",
            "type":"Retail Goods"
        }
    ],
    "sg:phone":"+1   ",
    "sg:postcode":"16511",
    "sg:province":"PA",
    "sg:tags":[
        "station",
        "gasoline"
    ],
    "wof:name":"Sunoco",
    "wof:placetype":"venue"
},
  "geometry": {"coordinates":[-80.013099,42.151191],"type":"Point"}
}