{
  "type": "Feature",
  "properties": {
    "iso:country":"US",
    "sg:address":"20 N Gallatin Ave",
    "sg:city":"Uniontown",
    "sg:classifiers":[
        {
            "category":"Government",
            "subcategory":"Office",
            "type":"Public Place"
        }
    ],
    "sg:phone":"+1 724 430 2931",
    "sg:postcode":"15401",
    "sg:province":"PA",
    "sg:tags":[
        "village"
    ],
    "wof:name":"Uniontown Street Commissioner",
    "wof:placetype":"venue"
},
  "geometry": {"coordinates":[-79.72410600000001,39.901948],"type":"Point"}
}