{
  "type": "Feature",
  "properties": {
    "iso:country":"US",
    "sg:address":"125 Strafford Ave",
    "sg:city":"Wayne",
    "sg:classifiers":[
        {
            "category":"Manufacturing",
            "subcategory":"Paper Products",
            "type":"Manufacturing & Wholesale Goods"
        },
        {
            "category":"Professional",
            "subcategory":"Business Services",
            "type":"Services"
        }
    ],
    "sg:phone":"+1 610 687 1355",
    "sg:postcode":"19087",
    "sg:province":"PA",
    "sg:tags":[
        "packaging",
        "mill"
    ],
    "wof:name":"Anderson Packaging Inc",
    "wof:placetype":"venue"
},
  "geometry": {"coordinates":[-75.39801199999999,40.044532],"type":"Point"}
}