{
  "type": "Feature",
  "properties": {
    "addr:full":"416 Main St Dickson City PA 18519",
    "addr:housenumber":"416",
    "addr:postcode":"18519",
    "addr:street":"Main St",
    "iso:country":"US",
    "sg:address":"416 Main St",
    "sg:city":"Dickson City",
    "sg:classifiers":[
        {
            "category":"Food & Beverages",
            "subcategory":"Groceries & Convenience Stores",
            "type":"Retail Goods"
        }
    ],
    "sg:phone":"+1   ",
    "sg:postcode":"18519",
    "sg:province":"PA",
    "wof:name":"Supermarket Service",
    "wof:placetype":"venue"
},
  "geometry": {"coordinates":[-75.629858,41.455728],"type":"Point"}
}