{
  "type": "Feature",
  "properties": {
    "iso:country":"US",
    "sg:address":"1599 Bobali Dr",
    "sg:city":"Harrisburg",
    "sg:classifiers":[
        {
            "category":"Home & Garden",
            "subcategory":"Building Materials",
            "type":"Retail Goods"
        }
    ],
    "sg:phone":"+1 717 986 1177",
    "sg:postcode":"17104",
    "sg:province":"PA",
    "sg:tags":[
        "supply"
    ],
    "wof:name":"K & K Distributers Inc",
    "wof:placetype":"venue"
},
  "geometry": {"coordinates":[-76.848801,40.2486],"type":"Point"}
}