{
  "type": "Feature",
  "properties": {
    "addr:full":"813 Bowman St Lebanon PA 17046",
    "addr:housenumber":"813",
    "addr:postcode":"17046",
    "addr:street":"Bowman St",
    "iso:country":"US",
    "sg:address":"813 Bowman St",
    "sg:city":"Lebanon",
    "sg:classifiers":[
        {
            "category":"Restaurant",
            "type":"Food & Drink"
        }
    ],
    "sg:menulink":"http://www.allmenus.com/pa/lebanon/123136-quiznos-sub/menu/",
    "sg:phone":"+1 717 270 6116",
    "sg:postcode":"17046",
    "sg:province":"PA",
    "sg:tags":[
        "wrap",
        "american",
        "sandwich"
    ],
    "wof:name":"Quiznos Sub",
    "wof:placetype":"venue"
},
  "geometry": {"coordinates":[-76.397504,40.345071],"type":"Point"}
}