{
  "type": "Feature",
  "properties": {
    "iso:country":"US",
    "sg:address":"614 Village Center",
    "sg:city":"Spring House",
    "sg:classifiers":[
        {
            "category":"Personal",
            "subcategory":"Beauty Salon",
            "type":"Services"
        }
    ],
    "sg:phone":"+1 215 643 5206",
    "sg:postcode":"19477",
    "sg:province":"PA",
    "wof:name":"Glam Hair Studio",
    "wof:placetype":"venue"
},
  "geometry": {"coordinates":[-75.227073,40.18071],"type":"Point"}
}