{
  "type": "Feature",
  "properties": {
    "iso:country":"US",
    "sg:address":"2547 26th St SW",
    "sg:city":"Allentown",
    "sg:classifiers":[
        {
            "category":"Restaurant",
            "type":"Food & Drink"
        }
    ],
    "sg:phone":"+1   ",
    "sg:postcode":"18103",
    "sg:province":"PA",
    "sg:tags":[
        "family"
    ],
    "wof:name":"Nicks Family Restaurant",
    "wof:placetype":"venue"
},
  "geometry": {"coordinates":[-75.473662,40.56213],"type":"Point"}
}