{
  "type": "Feature",
  "properties": {
    "iso:country":"US",
    "sg:address":"332 School Rd",
    "sg:city":"Denver",
    "sg:classifiers":[
        {
            "category":"Shopping",
            "type":"Retail Goods"
        }
    ],
    "sg:phone":"+1 717 445 5578",
    "sg:postcode":"17517",
    "sg:province":"PA",
    "sg:tags":[
        "ice"
    ],
    "wof:name":"Dennis' Ice Svc",
    "wof:placetype":"venue"
},
  "geometry": {"coordinates":[-76.03156300000001,40.196679],"type":"Point"}
}