{
  "type": "Feature",
  "properties": {
    "iso:country":"US",
    "sg:address":"1229 W Minor St",
    "sg:city":"Emmaus",
    "sg:classifiers":[
        {
            "category":"Building & Trades",
            "subcategory":"Landscaping Services",
            "type":"Services"
        }
    ],
    "sg:phone":"+1 610 967 2710",
    "sg:postcode":"18049",
    "sg:province":"PA",
    "sg:tags":[
        "landscape",
        "contractor"
    ],
    "wof:name":"Frederick's Landscaping Svc",
    "wof:placetype":"venue"
},
  "geometry": {"coordinates":[-75.50739299999999,40.524639],"type":"Point"}
}