{
  "type": "Feature",
  "properties": {
    "addr:full":"490 Hickernell Rd Ellwood City PA 16117",
    "addr:housenumber":"490",
    "addr:postcode":"16117",
    "addr:street":"Hickernell Rd",
    "iso:country":"US",
    "sg:address":"490 Hickernell Rd",
    "sg:city":"Ellwood City",
    "sg:classifiers":[
        {
            "category":"Building & Trades",
            "subcategory":"Construction",
            "type":"Services"
        }
    ],
    "sg:phone":"+1   ",
    "sg:postcode":"16117",
    "sg:province":"PA",
    "sg:tags":[
        "excavation",
        "contractor"
    ],
    "wof:name":"Peffer Excavating",
    "wof:placetype":"venue"
},
  "geometry": {"coordinates":[-80.23755800000001,40.845815],"type":"Point"}
}