{
  "type": "Feature",
  "properties": {
    "addr:full":"536 E Poplar St Mc Connellsburg PA 17233",
    "addr:housenumber":"536",
    "addr:postcode":"17233",
    "addr:street":"E Poplar St",
    "iso:country":"US",
    "sg:address":"536 E Poplar St",
    "sg:city":"Mc Connellsburg",
    "sg:classifiers":[
        {
            "category":"Organizations",
            "subcategory":"Professional Association",
            "type":"Services"
        }
    ],
    "sg:phone":"+1 717 485 4064",
    "sg:postcode":"17233",
    "sg:province":"PA",
    "sg:tags":[
        "chambers",
        "commerce"
    ],
    "wof:name":"Fulton County Chamber Or Comm",
    "wof:placetype":"venue"
},
  "geometry": {"coordinates":[-77.99354,39.931536],"type":"Point"}
}