{
  "type": "Feature",
  "properties": {
    "addr:full":"53 E Wister St Apt 310 Philadelphia PA 19144",
    "addr:housenumber":"53;310",
    "addr:postcode":"19144",
    "addr:street":"E Wister St Apt",
    "iso:country":"US",
    "sg:address":"53 E Wister St Apt 310",
    "sg:city":"Philadelphia",
    "sg:classifiers":[
        {
            "category":"Real Estate",
            "subcategory":"Real Estate Operator",
            "type":"Services"
        }
    ],
    "sg:phone":"+1 215 842 3000",
    "sg:postcode":"19144",
    "sg:province":"PA",
    "sg:tags":[
        "apartment"
    ],
    "wof:name":"Elders Place Inc",
    "wof:placetype":"venue"
},
  "geometry": {"coordinates":[-75.164001,40.030899],"type":"Point"}
}