{
  "type": "Feature",
  "properties": {
    "addr:full":"2056 Newark Rd Lincoln University PA 19352",
    "addr:housenumber":"2056",
    "addr:postcode":"19352",
    "addr:street":"Newark Rd",
    "iso:country":"US",
    "sg:address":"2056 Newark Rd",
    "sg:city":"Lincoln University",
    "sg:classifiers":[
        {
            "category":"Health Services",
            "subcategory":"Health Practitioner",
            "type":"Services"
        }
    ],
    "sg:phone":"+1 610 869 0993",
    "sg:postcode":"19352",
    "sg:province":"PA",
    "sg:tags":[
        "therapy",
        "physical"
    ],
    "wof:name":"Peak Physical Therapy Llc",
    "wof:placetype":"venue"
},
  "geometry": {"coordinates":[-75.876497,39.78283],"type":"Point"}
}