{
  "type": "Feature",
  "properties": {
    "iso:country":"US",
    "sg:address":"300 Pottstown Pike",
    "sg:city":"Exton",
    "sg:classifiers":[
        {
            "category":"Wholesale",
            "subcategory":"Stationery",
            "type":"Manufacturing & Wholesale Goods"
        },
        {
            "category":"Wholesale",
            "subcategory":"Non-durable Goods",
            "type":"Manufacturing & Wholesale Goods"
        }
    ],
    "sg:phone":"+1 610 594 8434",
    "sg:postcode":"19341",
    "sg:province":"PA",
    "sg:tags":[
        "box"
    ],
    "wof:name":"Andre Boas",
    "wof:placetype":"venue"
},
  "geometry": {"coordinates":[-75.63227500000001,40.03552],"type":"Point"}
}