{
  "type": "Feature",
  "properties": {
    "iso:country":"US",
    "sg:address":"2586 Cummings Dr",
    "sg:city":"Cochranton",
    "sg:classifiers":[
        {
            "category":"Government",
            "subcategory":"Office",
            "type":"Public Place"
        }
    ],
    "sg:phone":"+1 814 425 1554",
    "sg:postcode":"16314",
    "sg:province":"PA",
    "sg:tags":[
        "village"
    ],
    "wof:name":"Fairfield Twp Secretary",
    "wof:placetype":"venue"
},
  "geometry": {"coordinates":[-80.071083,41.488319],"type":"Point"}
}