{
  "type": "Feature",
  "properties": {
    "iso:country":"US",
    "sg:address":"3 Hospital Dr",
    "sg:city":"Lewisburg",
    "sg:classifiers":[
        {
            "category":"Health Services",
            "subcategory":"Doctor",
            "type":"Services"
        }
    ],
    "sg:phone":"+1   ",
    "sg:postcode":"17837",
    "sg:province":"PA",
    "sg:tags":[
        "medical"
    ],
    "wof:name":"Normington Ernest MD",
    "wof:placetype":"venue"
},
  "geometry": {"coordinates":[-76.885306,40.979889],"type":"Point"}
}