{
  "type": "Feature",
  "properties": {
    "iso:country":"US",
    "sg:address":"1264 E State St",
    "sg:city":"Sharon",
    "sg:classifiers":[
        {
            "category":"Insurance",
            "subcategory":"Insurance Agent",
            "type":"Services"
        }
    ],
    "sg:phone":"+1 724 346 3362",
    "sg:postcode":"16146",
    "sg:province":"PA",
    "wof:name":"Davis Insurance",
    "wof:placetype":"venue"
},
  "geometry": {"coordinates":[-80.485215,41.23306],"type":"Point"}
}