{
  "type": "Feature",
  "properties": {
    "iso:country":"US",
    "sg:address":"63 New Charlotte St",
    "sg:city":"Manheim",
    "sg:classifiers":[
        {
            "category":"Manufacturing",
            "subcategory":"Pet Food",
            "type":"Manufacturing & Wholesale Goods"
        }
    ],
    "sg:phone":"+1   ",
    "sg:postcode":"17545",
    "sg:province":"PA",
    "sg:tags":[
        "poultry",
        "feed",
        "livestock",
        "mfg",
        "hog",
        "dairy"
    ],
    "wof:name":"Pet Feed and Supply",
    "wof:placetype":"venue"
},
  "geometry": {"coordinates":[-76.39117899999999,40.158691],"type":"Point"}
}