{
  "type": "Feature",
  "properties": {
    "iso:country":"US",
    "sg:address":"29 Highview Dr",
    "sg:city":"Telford",
    "sg:classifiers":[
        {
            "category":"Professional",
            "subcategory":"Engineering",
            "type":"Services"
        },
        {
            "category":"Building & Trades",
            "subcategory":"Electrical",
            "type":"Services"
        },
        {
            "category":"Professional",
            "subcategory":"Computer Services",
            "type":"Services"
        }
    ],
    "sg:phone":"+1 215 723 4040",
    "sg:postcode":"18969",
    "sg:province":"PA",
    "sg:tags":[
        "designer",
        "electrician",
        "electric",
        "consultant",
        "integration",
        "system",
        "industrial",
        "contractors-commercial",
        "engineer"
    ],
    "sg:website":"http://www.kolb-electric.com",
    "wof:name":"Kolb Electric",
    "wof:placetype":"venue"
},
  "geometry": {"coordinates":[-75.40548200000001,40.326922],"type":"Point"}
}