{
  "type": "Feature",
  "properties": {
    "addr:full":"970 Cape Horn Rd York PA 17402",
    "addr:housenumber":"970",
    "addr:postcode":"17402",
    "addr:street":"Cape Horn Rd",
    "iso:country":"US",
    "sg:address":"970 Cape Horn Rd",
    "sg:city":"York",
    "sg:classifiers":[
        {
            "category":"Organizations",
            "subcategory":"Community Association",
            "type":"Services"
        }
    ],
    "sg:phone":"+1 717 757 3990",
    "sg:postcode":"17402",
    "sg:province":"PA",
    "sg:tags":[
        "club"
    ],
    "wof:name":"Loyal Order Of Moose",
    "wof:placetype":"venue"
},
  "geometry": {"coordinates":[-76.65103999999999,39.954435],"type":"Point"}
}