{
  "type": "Feature",
  "properties": {
    "iso:country":"US",
    "sg:address":"1225 Carlisle St",
    "sg:city":"Hanover",
    "sg:classifiers":[
        {
            "category":"Retail",
            "subcategory":"Laundry & Dry Cleaning",
            "type":"Services"
        }
    ],
    "sg:phone":"+1 717 637 6080",
    "sg:postcode":"17331",
    "sg:province":"PA",
    "sg:tags":[
        "cleaners"
    ],
    "wof:name":"Eddie's Cleaners & Launderers",
    "wof:placetype":"venue"
},
  "geometry": {"coordinates":[-76.999045,39.826399],"type":"Point"}
}