{
  "type": "Feature",
  "properties": {
    "addr:full":"808 Farwell Ave Renovo PA 17764",
    "addr:housenumber":"808",
    "addr:postcode":"17764",
    "addr:street":"Farwell Ave",
    "iso:country":"US",
    "sg:address":"808 Farwell Ave",
    "sg:city":"Renovo",
    "sg:classifiers":[
        {
            "category":"Manufacturing",
            "subcategory":"Printing",
            "type":"Manufacturing & Wholesale Goods"
        }
    ],
    "sg:phone":"+1 570 923 1500",
    "sg:postcode":"17764",
    "sg:province":"PA",
    "sg:tags":[
        "newspaper"
    ],
    "wof:name":"Record",
    "wof:placetype":"venue"
},
  "geometry": {"coordinates":[-77.710314,41.338691],"type":"Point"}
}