{
  "type": "Feature",
  "properties": {
    "addr:full":"101 Smith Dr Ste 10 Cranberry Twp PA 16066",
    "addr:housenumber":"101;10",
    "addr:postcode":"16066",
    "addr:street":"Smith Dr Ste",
    "iso:country":"US",
    "sg:address":"101 Smith Dr Ste 10",
    "sg:city":"Cranberry Twp",
    "sg:classifiers":[
        {
            "category":"Professional",
            "subcategory":"Lawyer & Legal Services",
            "type":"Services"
        }
    ],
    "sg:phone":"+1 724 776 8000",
    "sg:postcode":"16066",
    "sg:province":"PA",
    "wof:name":"Lynch Daniel P & Associates PC",
    "wof:placetype":"venue"
},
  "geometry": {"coordinates":[-80.104401,40.6978],"type":"Point"}
}