{
  "type": "Feature",
  "properties": {
    "addr:full":"3026 Cherry St Erie PA 16508",
    "addr:housenumber":"3026",
    "addr:postcode":"16508",
    "addr:street":"Cherry St",
    "iso:country":"US",
    "sg:address":"3026 Cherry St",
    "sg:city":"Erie",
    "sg:classifiers":[
        {
            "category":"Shopping",
            "type":"Retail Goods"
        },
        {
            "category":"Shopping",
            "subcategory":"Gifts & Souvenirs",
            "type":"Retail Goods"
        }
    ],
    "sg:phone":"+1 814 459 5797",
    "sg:postcode":"16508",
    "sg:province":"PA",
    "sg:tags":[
        "importer"
    ],
    "sg:website":"www.tipperarywest.com",
    "wof:name":"Tipperary West Irish Imports",
    "wof:placetype":"venue"
},
  "geometry": {"coordinates":[-80.084546,42.103531],"type":"Point"}
}