{
  "type": "Feature",
  "properties": {
    "addr:full":"103 S Perry St Titusville PA 16354",
    "addr:housenumber":"103",
    "addr:postcode":"16354",
    "addr:street":"S Perry St",
    "iso:country":"US",
    "sg:address":"103 S Perry St",
    "sg:city":"Titusville",
    "sg:classifiers":[
        {
            "category":"Food & Beverages",
            "subcategory":"Groceries & Convenience Stores",
            "type":"Retail Goods"
        }
    ],
    "sg:phone":"+1 814 827 1812",
    "sg:postcode":"16354",
    "sg:province":"PA",
    "wof:name":"Country Fair 8",
    "wof:placetype":"venue"
},
  "geometry": {"coordinates":[-79.676959,41.620091],"type":"Point"}
}