{
  "type": "Feature",
  "properties": {
    "addr:full":"334 S Burrowes St State College PA 16801",
    "addr:housenumber":"334",
    "addr:postcode":"16801",
    "addr:street":"S Burrowes St",
    "iso:country":"US",
    "sg:address":"334 S Burrowes St",
    "sg:city":"State College",
    "sg:classifiers":[
        {
            "category":"Social Services",
            "type":"Services"
        }
    ],
    "sg:phone":"+1   ",
    "sg:postcode":"16801",
    "sg:province":"PA",
    "sg:tags":[
        "youth"
    ],
    "wof:name":"Stepping Stones",
    "wof:placetype":"venue"
},
  "geometry": {"coordinates":[-77.860302,40.78986],"type":"Point"}
}