{
  "type": "Feature",
  "properties": {
    "iso:country":"US",
    "sg:address":"1 W Penn Ave",
    "sg:city":"Robesonia",
    "sg:classifiers":[
        {
            "category":"Banks & Credit Unions",
            "subcategory":"Bank",
            "type":"Services"
        }
    ],
    "sg:phone":"+1 610 693 3141",
    "sg:postcode":"19551",
    "sg:province":"PA",
    "wof:name":"Wachovia Bank",
    "wof:placetype":"venue"
},
  "geometry": {"coordinates":[-76.13604599999999,40.352264],"type":"Point"}
}