{
  "type": "Feature",
  "properties": {
    "addr:full":"46 S 3rd St Oxford PA 19363",
    "addr:housenumber":"46",
    "addr:postcode":"19363",
    "addr:street":"S 3Rd St",
    "iso:country":"US",
    "sg:address":"46 S 3rd St",
    "sg:city":"Oxford",
    "sg:classifiers":[
        {
            "category":"Shopping",
            "subcategory":"Department Store",
            "type":"Retail Goods"
        }
    ],
    "sg:phone":"+1   ",
    "sg:postcode":"19363",
    "sg:province":"PA",
    "wof:name":"JC Penney",
    "wof:placetype":"venue"
},
  "geometry": {"coordinates":[-75.979508,39.783636],"type":"Point"}
}