{
  "type": "Feature",
  "properties": {
    "iso:country":"US",
    "sg:address":"3367 Babcock Blvd",
    "sg:city":"Pittsburgh",
    "sg:classifiers":[
        {
            "category":"Building & Trades",
            "subcategory":"Construction",
            "type":"Services"
        }
    ],
    "sg:phone":"+1 412 939 3220",
    "sg:postcode":"15237",
    "sg:province":"PA",
    "sg:tags":[
        "tile",
        "dealer"
    ],
    "wof:name":"Crystal Tile Inc",
    "wof:placetype":"venue"
},
  "geometry": {"coordinates":[-80.021377,40.536268],"type":"Point"}
}