{
  "type": "Feature",
  "properties": {
    "iso:country":"US",
    "sg:address":"656 Loretta St",
    "sg:city":"Pittsburgh",
    "sg:classifiers":[
        {
            "category":"Health Services",
            "subcategory":"Health Practitioner",
            "type":"Services"
        }
    ],
    "sg:phone":"+1   ",
    "sg:postcode":"15217",
    "sg:province":"PA",
    "sg:tags":[
        "specialty",
        "outpatient"
    ],
    "wof:name":"George Pappas",
    "wof:placetype":"venue"
},
  "geometry": {"coordinates":[-79.93563,40.421103],"type":"Point"}
}