{
  "type": "Feature",
  "properties": {
    "iso:country":"US",
    "sg:address":"1700 Jackson St",
    "sg:city":"Philadelphia",
    "sg:classifiers":[
        {
            "category":"Building & Trades",
            "subcategory":"Locksmith",
            "type":"Services"
        }
    ],
    "sg:phone":"+1 267 238 9809",
    "sg:postcode":"19145",
    "sg:province":"PA",
    "sg:tags":[
        "key"
    ],
    "wof:name":"24 Hour Locksmith Service",
    "wof:placetype":"venue"
},
  "geometry": {"coordinates":[-75.17477599999999,39.923624],"type":"Point"}
}