{
  "type": "Feature",
  "properties": {
    "addr:full":"640 Buttonwood Rd York Springs PA 17372",
    "addr:housenumber":"640",
    "addr:postcode":"17372",
    "addr:street":"Buttonwood Rd",
    "iso:country":"US",
    "sg:address":"640 Buttonwood Rd",
    "sg:city":"York Springs",
    "sg:classifiers":[
        {
            "category":"Farming",
            "subcategory":"Dairy Farm",
            "type":"Manufacturing & Wholesale Goods"
        }
    ],
    "sg:phone":"+1   ",
    "sg:postcode":"17372",
    "sg:province":"PA",
    "wof:name":"Buttonwood Farms",
    "wof:placetype":"venue"
},
  "geometry": {"coordinates":[-77.08681300000001,39.972605],"type":"Point"}
}