{
  "type": "Feature",
  "properties": {
    "iso:country":"US",
    "sg:address":"1705 Christian St",
    "sg:city":"Philadelphia",
    "sg:classifiers":[
        {
            "category":"Building & Trades",
            "subcategory":"Equipment Rental",
            "type":"Services"
        }
    ],
    "sg:phone":"+1 215 735 1371",
    "sg:postcode":"19146",
    "sg:province":"PA",
    "sg:tags":[
        "yard",
        "leasing",
        "store"
    ],
    "wof:name":"M & S Rentals",
    "wof:placetype":"venue"
},
  "geometry": {"coordinates":[-75.17119099999999,39.940629],"type":"Point"}
}