{
  "type": "Feature",
  "properties": {
    "addr:full":"5651 Malcolm St Philadelphia PA 19143",
    "addr:housenumber":"5651",
    "addr:postcode":"19143",
    "addr:street":"Malcolm St",
    "iso:country":"US",
    "sg:address":"5651 Malcolm St",
    "sg:city":"Philadelphia",
    "sg:classifiers":[
        {
            "category":"Organizations",
            "subcategory":"Religious Organization",
            "type":"Services"
        }
    ],
    "sg:phone":"+1 215 727 1095",
    "sg:postcode":"19143",
    "sg:province":"PA",
    "sg:tags":[
        "church"
    ],
    "wof:name":"Tabernacle-Praise Outreach",
    "wof:placetype":"venue"
},
  "geometry": {"coordinates":[-75.23324599999999,39.942089],"type":"Point"}
}