{
  "type": "Feature",
  "properties": {
    "iso:country":"US",
    "sg:address":"120 E Station Ave",
    "sg:city":"Coopersburg",
    "sg:classifiers":[
        {
            "category":"Manufacturing",
            "subcategory":"Toys & Sporting Goods",
            "type":"Manufacturing & Wholesale Goods"
        }
    ],
    "sg:phone":"+1   ",
    "sg:postcode":"18036",
    "sg:province":"PA",
    "sg:tags":[
        "athletic",
        "product",
        "wood",
        "sport",
        "mfg"
    ],
    "wof:name":"Coopersburg Sports",
    "wof:placetype":"venue"
},
  "geometry": {"coordinates":[-75.382808,40.508945],"type":"Point"}
}