{
  "type": "Feature",
  "properties": {
    "iso:country":"US",
    "sg:address":"255 Wilson Ave",
    "sg:city":"Hellertown",
    "sg:classifiers":[
        {
            "category":"Organizations",
            "subcategory":"Religious Organization",
            "type":"Services"
        }
    ],
    "sg:phone":"+1   ",
    "sg:postcode":"18055",
    "sg:province":"PA",
    "wof:name":"Saint Theresas Convent",
    "wof:placetype":"venue"
},
  "geometry": {"coordinates":[-75.335841,40.588771],"type":"Point"}
}