{
  "type": "Feature",
  "properties": {
    "addr:full":"18 E 8th St Chester PA 19013",
    "addr:housenumber":"18",
    "addr:postcode":"19013",
    "addr:street":"E 8Th St",
    "iso:country":"US",
    "sg:address":"18 E 8th St",
    "sg:city":"Chester",
    "sg:classifiers":[
        {
            "category":"Professional",
            "type":"Services"
        }
    ],
    "sg:phone":"+1 610 876 9912",
    "sg:postcode":"19013",
    "sg:province":"PA",
    "sg:tags":[
        "establishment"
    ],
    "wof:name":"Lav Tele Inc",
    "wof:placetype":"venue"
},
  "geometry": {"coordinates":[-75.362696,39.85097],"type":"Point"}
}