{
  "type": "Feature",
  "properties": {
    "addr:full":"24 N Bryn Mawr Ave Bryn Mawr PA 19010",
    "addr:housenumber":"24",
    "addr:postcode":"19010",
    "addr:street":"N Bryn Mawr Ave",
    "iso:country":"US",
    "sg:address":"24 N Bryn Mawr Ave",
    "sg:city":"Bryn Mawr",
    "sg:classifiers":[
        {
            "category":"Professional",
            "subcategory":"Business Services",
            "type":"Services"
        }
    ],
    "sg:phone":"+1 610 617 9745",
    "sg:postcode":"19010",
    "sg:province":"PA",
    "sg:tags":[
        "broker"
    ],
    "wof:name":"Delaware Valley Bus Network",
    "wof:placetype":"venue"
},
  "geometry": {"coordinates":[-75.316351,40.02176],"type":"Point"}
}