{
  "type": "Feature",
  "properties": {
    "iso:country":"US",
    "sg:address":"6 Gordon Farr St",
    "sg:city":"Ulster",
    "sg:classifiers":[
        {
            "category":"Retail",
            "subcategory":"Funeral Services",
            "type":"Services"
        }
    ],
    "sg:phone":"+1 570 358 3456",
    "sg:postcode":"18850",
    "sg:province":"PA",
    "sg:tags":[
        "director"
    ],
    "wof:name":"Bowen-Farr Funeral Home",
    "wof:placetype":"venue"
},
  "geometry": {"coordinates":[-76.50199000000001,41.848478],"type":"Point"}
}