{
  "type": "Feature",
  "properties": {
    "iso:country":"US",
    "sg:address":"100 W High St",
    "sg:city":"Carlisle",
    "sg:classifiers":[
        {
            "category":"Government",
            "subcategory":"Fire Station",
            "type":"Public Place"
        },
        {
            "category":"Building & Trades",
            "subcategory":"Cleaning & Sanitation",
            "type":"Services"
        },
        {
            "category":"Retail",
            "subcategory":"Laundry & Dry Cleaning",
            "type":"Services"
        }
    ],
    "sg:phone":"+1 717 243 7582",
    "sg:postcode":"17013",
    "sg:province":"PA",
    "sg:tags":[
        "cleaner",
        "disaster",
        "house",
        "rug",
        "damage",
        "water",
        "restoration",
        "relief",
        "carpet",
        "recovery"
    ],
    "wof:name":"Vaport Jet Professional Cleani",
    "wof:placetype":"venue"
},
  "geometry": {"coordinates":[-77.19154399999999,40.201679],"type":"Point"}
}