{
  "type": "Feature",
  "properties": {
    "addr:full":"4397 Sturbridge Dr Harrisburg PA 17110",
    "addr:housenumber":"4397",
    "addr:postcode":"17110",
    "addr:street":"Sturbridge Dr",
    "iso:country":"US",
    "sg:address":"4397 Sturbridge Dr",
    "sg:city":"Harrisburg",
    "sg:classifiers":[
        {
            "category":"Social Services",
            "subcategory":"Child Care",
            "type":"Services"
        }
    ],
    "sg:phone":"+1 717 526 0404",
    "sg:postcode":"17110",
    "sg:province":"PA",
    "sg:tags":[
        "kindergarten",
        "academic",
        "school",
        "preschool"
    ],
    "sg:website":"http://www.goddardschool.com",
    "wof:name":"The Goddard School",
    "wof:placetype":"venue"
},
  "geometry": {"coordinates":[-76.851727,40.330218],"type":"Point"}
}