{
  "type": "Feature",
  "properties": {
    "iso:country":"US",
    "sg:address":"14200 State Rte 226",
    "sg:city":"Albion",
    "sg:classifiers":[
        {
            "category":"Manufacturing",
            "subcategory":"Tools & Machinery",
            "type":"Manufacturing & Wholesale Goods"
        }
    ],
    "sg:phone":"+1 814 756 3578",
    "sg:postcode":"16401",
    "sg:province":"PA",
    "sg:tags":[
        "industrial",
        "mfg"
    ],
    "wof:name":"Thornton Industries Inc",
    "wof:placetype":"venue"
},
  "geometry": {"coordinates":[-80.493426,41.876342],"type":"Point"}
}