{
  "type": "Feature",
  "properties": {
    "addr:full":"405 N Grant St Waynesboro PA 17268",
    "addr:housenumber":"405",
    "addr:postcode":"17268",
    "addr:street":"N Grant St",
    "iso:country":"US",
    "sg:address":"405 N Grant St",
    "sg:city":"Waynesboro",
    "sg:classifiers":[
        {
            "category":"Building & Trades",
            "subcategory":"Equipment Rental",
            "type":"Services"
        }
    ],
    "sg:phone":"+1 717 762 6146",
    "sg:postcode":"17268",
    "sg:province":"PA",
    "sg:tags":[
        "moving",
        "supply"
    ],
    "wof:name":"U-Haul Co",
    "wof:placetype":"venue"
},
  "geometry": {"coordinates":[-77.578987,39.761888],"type":"Point"}
}