{
  "type": "Feature",
  "properties": {
    "iso:country":"US",
    "sg:address":"277 Mulberry Dr",
    "sg:city":"Mechanicsburg",
    "sg:classifiers":[
        {
            "category":"Retail",
            "subcategory":"Auto Repair",
            "type":"Services"
        }
    ],
    "sg:phone":"+1 717 691 8339",
    "sg:postcode":"17050",
    "sg:province":"PA",
    "sg:tags":[
        "truck"
    ],
    "wof:name":"Keystone Fleet Svc",
    "wof:placetype":"venue"
},
  "geometry": {"coordinates":[-77.02830299999999,40.215263],"type":"Point"}
}