{
  "type": "Feature",
  "properties": {
    "addr:full":"1392 Ben Franklin Hwy E Douglassville PA 19518",
    "addr:housenumber":"1392",
    "addr:postcode":"19518",
    "addr:street":"Ben Franklin Hwy E",
    "iso:country":"US",
    "sg:address":"1392 Ben Franklin Hwy E",
    "sg:city":"Douglassville",
    "sg:classifiers":[
        {
            "category":"Autos & Motor Vehicles",
            "subcategory":"Fuel & Gas Station",
            "type":"Retail Goods"
        }
    ],
    "sg:phone":"+1 610 326 5667",
    "sg:postcode":"19518",
    "sg:province":"PA",
    "sg:tags":[
        "oil"
    ],
    "wof:name":"Speedway",
    "wof:placetype":"venue"
},
  "geometry": {"coordinates":[-75.719773,40.254263],"type":"Point"}
}