{
  "type": "Feature",
  "properties": {
    "iso:country":"US",
    "sg:address":"48 1st St",
    "sg:city":"Grampian",
    "sg:classifiers":[
        {
            "category":"Building & Trades",
            "subcategory":"Construction",
            "type":"Services"
        }
    ],
    "sg:phone":"+1 814 236 3713",
    "sg:postcode":"16838",
    "sg:province":"PA",
    "sg:tags":[
        "contractor"
    ],
    "wof:name":"Asphalt Doctor",
    "wof:placetype":"venue"
},
  "geometry": {"coordinates":[-78.61170199999999,40.95786],"type":"Point"}
}