{
  "type": "Feature",
  "properties": {
    "iso:country":"US",
    "sg:address":"1859 Strasburg Rd",
    "sg:city":"Coatesville",
    "sg:classifiers":[
        {
            "category":"Organizations",
            "subcategory":"Religious Organization",
            "type":"Services"
        }
    ],
    "sg:phone":"+1   ",
    "sg:postcode":"19320",
    "sg:province":"PA",
    "wof:name":"Romansvlle Untd Methdst Church",
    "wof:placetype":"venue"
},
  "geometry": {"coordinates":[-75.737807,39.951135],"type":"Point"}
}