{
  "type": "Feature",
  "properties": {
    "iso:country":"US",
    "sg:address":"19 N 12th Ave",
    "sg:city":"Coatesville",
    "sg:classifiers":[
        {
            "category":"Manufacturing",
            "subcategory":"Metals",
            "type":"Manufacturing & Wholesale Goods"
        }
    ],
    "sg:phone":"+1 610 384 5048",
    "sg:postcode":"19320",
    "sg:province":"PA",
    "sg:tags":[
        "shop",
        "plate",
        "golf",
        "repair",
        "work",
        "fabricated",
        "welding",
        "public",
        "structural"
    ],
    "sg:website":"www.peletwelding.com",
    "wof:name":"Pelet's Welding Inc",
    "wof:placetype":"venue"
},
  "geometry": {"coordinates":[-75.801641,39.987264],"type":"Point"}
}