{
  "type": "Feature",
  "properties": {
    "addr:full":"1455 Valley Center Pkwy Bethlehem PA 18017",
    "addr:housenumber":"1455",
    "addr:postcode":"18017",
    "addr:street":"Valley Center Pkwy",
    "iso:country":"US",
    "sg:address":"1455 Valley Center Pkwy",
    "sg:city":"Bethlehem",
    "sg:classifiers":[
        {
            "category":"Insurance",
            "subcategory":"Insurance Agent",
            "type":"Services"
        }
    ],
    "sg:phone":"+1 610 866 7122",
    "sg:postcode":"18017",
    "sg:province":"PA",
    "wof:name":"CIGNA Co",
    "wof:placetype":"venue"
},
  "geometry": {"coordinates":[-75.415954,40.655646],"type":"Point"}
}