{
  "type": "Feature",
  "properties": {
    "iso:country":"US",
    "sg:address":"813 Ventre Rd",
    "sg:city":"Altoona",
    "sg:classifiers":[
        {
            "category":"Building & Trades",
            "subcategory":"Construction",
            "type":"Services"
        }
    ],
    "sg:phone":"+1 814 946 9047",
    "sg:postcode":"16602",
    "sg:province":"PA",
    "sg:tags":[
        "residential",
        "excavating",
        "commercial",
        "contractor"
    ],
    "wof:name":"Michael Ventre Excavating",
    "wof:placetype":"venue"
},
  "geometry": {"coordinates":[-78.38096400000001,40.527711],"type":"Point"}
}