{
  "type": "Feature",
  "properties": {
    "addr:full":"612 N Wales Rd North Wales PA 19454",
    "addr:housenumber":"612",
    "addr:postcode":"19454",
    "addr:street":"N Wales Rd",
    "iso:country":"US",
    "sg:address":"612 N Wales Rd",
    "sg:city":"North Wales",
    "sg:classifiers":[
        {
            "category":"Banks & Credit Unions",
            "subcategory":"Bank",
            "type":"Services"
        }
    ],
    "sg:phone":"+1 215 699 0480",
    "sg:postcode":"19454",
    "sg:province":"PA",
    "sg:tags":[
        "loan",
        "real estate"
    ],
    "wof:name":"North Penn Mortgage",
    "wof:placetype":"venue"
},
  "geometry": {"coordinates":[-75.285016,40.203158],"type":"Point"}
}