{
  "type": "Feature",
  "properties": {
    "iso:country":"US",
    "sg:address":"80 Union Ave",
    "sg:city":"Bellevue",
    "sg:classifiers":[
        {
            "category":"Building & Trades",
            "subcategory":"Construction",
            "type":"Services"
        }
    ],
    "sg:phone":"+1 412 766 4630",
    "sg:postcode":"15202",
    "sg:province":"PA",
    "sg:tags":[
        "general",
        "contractor"
    ],
    "wof:name":"Sota Construction Svc",
    "wof:placetype":"venue"
},
  "geometry": {"coordinates":[-80.058576,40.507746],"type":"Point"}
}