{
  "type": "Feature",
  "properties": {
    "iso:country":"US",
    "sg:address":"1924 W Hunting Park Ave",
    "sg:city":"Philadelphia",
    "sg:classifiers":[
        {
            "category":"Manufacturing",
            "subcategory":"Printing",
            "type":"Manufacturing & Wholesale Goods"
        }
    ],
    "sg:phone":"+1 215 223 1929",
    "sg:postcode":"19140",
    "sg:province":"PA",
    "sg:tags":[
        "work",
        "bookbinding",
        "related"
    ],
    "wof:name":"T & M Bindery",
    "wof:placetype":"venue"
},
  "geometry": {"coordinates":[-75.158733,40.013589],"type":"Point"}
}