{
  "type": "Feature",
  "properties": {
    "iso:country":"US",
    "sg:address":"17 Valley View Dr",
    "sg:city":"Elysburg",
    "sg:classifiers":[
        {
            "category":"Building & Trades",
            "subcategory":"Electrical",
            "type":"Services"
        }
    ],
    "sg:phone":"+1   ",
    "sg:postcode":"17824",
    "sg:province":"PA",
    "sg:tags":[
        "electrical",
        "contractor"
    ],
    "wof:name":"Eljay Electric",
    "wof:placetype":"venue"
},
  "geometry": {"coordinates":[-76.565387,40.860554],"type":"Point"}
}