{
  "type": "Feature",
  "properties": {
    "iso:country":"US",
    "sg:address":"302 Vermont Ave",
    "sg:city":"Burnham",
    "sg:classifiers":[
        {
            "category":"Manufacturing",
            "subcategory":"Signs",
            "type":"Manufacturing & Wholesale Goods"
        }
    ],
    "sg:phone":"+1 717 242 0278",
    "sg:postcode":"17009",
    "sg:province":"PA",
    "sg:tags":[
        "specialty",
        "mfg"
    ],
    "wof:name":"Leeper Signs",
    "wof:placetype":"venue"
},
  "geometry": {"coordinates":[-77.568128,40.629161],"type":"Point"}
}