{
  "type": "Feature",
  "properties": {
    "iso:country":"US",
    "sg:address":"3626 Poplar Ave",
    "sg:city":"Pittsburgh",
    "sg:classifiers":[
        {
            "category":"Manufacturing",
            "subcategory":"Printing",
            "type":"Manufacturing & Wholesale Goods"
        }
    ],
    "sg:phone":"+1   ",
    "sg:postcode":"15234",
    "sg:province":"PA",
    "sg:tags":[
        "lithographic",
        "commercial"
    ],
    "wof:name":"Proforma Grphic Communications",
    "wof:placetype":"venue"
},
  "geometry": {"coordinates":[-80.019758,40.366735],"type":"Point"}
}