{
  "type": "Feature",
  "properties": {
    "iso:country":"US",
    "sg:address":"1440 Bridgetown Pike",
    "sg:city":"Feastervl Trvs",
    "sg:classifiers":[
        {
            "category":"Local Transit",
            "type":"Transportation"
        },
        {
            "category":"Government",
            "subcategory":"Fire Station",
            "type":"Public Place"
        }
    ],
    "sg:phone":"+1 215 357 2771",
    "sg:postcode":"19053",
    "sg:province":"PA",
    "sg:tags":[
        "department",
        "passenger"
    ],
    "wof:name":"Tri-Hampton Rescue Squad",
    "wof:placetype":"venue"
},
  "geometry": {"coordinates":[-74.997621,40.155623],"type":"Point"}
}