{
  "type": "Feature",
  "properties": {
    "iso:country":"US",
    "sg:address":"505 Broad St",
    "sg:city":"Sewickley",
    "sg:classifiers":[
        {
            "category":"Food & Beverages",
            "subcategory":"Specialty",
            "type":"Retail Goods"
        }
    ],
    "sg:phone":"+1   ",
    "sg:postcode":"15143",
    "sg:province":"PA",
    "wof:name":"Olefins Rejuvenation Center",
    "wof:placetype":"venue"
},
  "geometry": {"coordinates":[-80.180228,40.540473],"type":"Point"}
}