{
  "type": "Feature",
  "properties": {
    "iso:country":"US",
    "sg:address":"2170 Larkspur Ln S",
    "sg:city":"York",
    "sg:classifiers":[
        {
            "category":"Wholesale",
            "subcategory":"Hardware",
            "type":"Manufacturing & Wholesale Goods"
        }
    ],
    "sg:phone":"+1   ",
    "sg:postcode":"17403",
    "sg:province":"PA",
    "wof:name":"William L Latchaw Co",
    "wof:placetype":"venue"
},
  "geometry": {"coordinates":[-76.70856000000001,39.922298],"type":"Point"}
}