{
  "type": "Feature",
  "properties": {
    "addr:full":"2525 W 38th St Erie PA 16506",
    "addr:housenumber":"2525",
    "addr:postcode":"16506",
    "addr:street":"W 38Th St",
    "iso:country":"US",
    "sg:address":"2525 W 38th St",
    "sg:city":"Erie",
    "sg:classifiers":[
        {
            "category":"Organizations",
            "subcategory":"Religious Organization",
            "type":"Services"
        }
    ],
    "sg:phone":"+1   ",
    "sg:postcode":"16506",
    "sg:province":"PA",
    "sg:tags":[
        "temple"
    ],
    "wof:name":"Zez Zem Council",
    "wof:placetype":"venue"
},
  "geometry": {"coordinates":[-80.12358500000001,42.081264],"type":"Point"}
}