{
  "type": "Feature",
  "properties": {
    "iso:country":"US",
    "sg:address":"312 Baltimore St",
    "sg:city":"Gettysburg",
    "sg:classifiers":[
        {
            "category":"Shopping",
            "subcategory":"Gifts & Souvenirs",
            "type":"Retail Goods"
        }
    ],
    "sg:phone":"+1 717 334 9995",
    "sg:postcode":"17325",
    "sg:province":"PA",
    "wof:name":"Just Friends Gift Emporium",
    "wof:placetype":"venue"
},
  "geometry": {"coordinates":[-77.230985,39.826401],"type":"Point"}
}