{
  "type": "Feature",
  "properties": {
    "addr:full":"675 Glass Run Rd Pittsburgh PA 15236",
    "addr:housenumber":"675",
    "addr:postcode":"15236",
    "addr:street":"Glass Run Rd",
    "iso:country":"US",
    "sg:address":"675 Glass Run Rd",
    "sg:city":"Pittsburgh",
    "sg:classifiers":[
        {
            "category":"Bars & Pubs",
            "type":"Food & Drink"
        }
    ],
    "sg:phone":"+1 412 881 9947",
    "sg:postcode":"15236",
    "sg:province":"PA",
    "sg:tags":[
        "drinking"
    ],
    "wof:name":"Tush's Tavern",
    "wof:placetype":"venue"
},
  "geometry": {"coordinates":[-79.94264,40.389813],"type":"Point"}
}