{
  "type": "Feature",
  "properties": {
    "addr:full":"418 E 4th St Bethlehem PA 18015",
    "addr:housenumber":"418",
    "addr:postcode":"18015",
    "addr:street":"E 4Th St",
    "iso:country":"US",
    "sg:address":"418 E 4th St",
    "sg:city":"Bethlehem",
    "sg:classifiers":[
        {
            "category":"Autos & Motor Vehicles",
            "subcategory":"Fuel & Gas Station",
            "type":"Retail Goods"
        }
    ],
    "sg:phone":"+1   ",
    "sg:postcode":"18015",
    "sg:province":"PA",
    "sg:tags":[
        "station",
        "gasoline"
    ],
    "wof:name":"Texaco",
    "wof:placetype":"venue"
},
  "geometry": {"coordinates":[-75.372066,40.61053],"type":"Point"}
}