{
  "type": "Feature",
  "properties": {
    "addr:full":"1101 State St Mertztown PA 19539",
    "addr:housenumber":"1101",
    "addr:postcode":"19539",
    "addr:street":"State St",
    "iso:country":"US",
    "sg:address":"1101 State St",
    "sg:city":"Mertztown",
    "sg:classifiers":[
        {
            "category":"Building & Trades",
            "subcategory":"Landscaping Services",
            "type":"Services"
        }
    ],
    "sg:phone":"+1   ",
    "sg:postcode":"19539",
    "sg:province":"PA",
    "sg:tags":[
        "landscape"
    ],
    "wof:name":"Fulton Lawn Service",
    "wof:placetype":"venue"
},
  "geometry": {"coordinates":[-75.664232,40.505195],"type":"Point"}
}