{
  "type": "Feature",
  "properties": {
    "addr:full":"3901 N Front St Harrisburg PA 17110",
    "addr:housenumber":"3901",
    "addr:postcode":"17110",
    "addr:street":"N Front St",
    "iso:country":"US",
    "sg:address":"3901 N Front St",
    "sg:city":"Harrisburg",
    "sg:classifiers":[
        {
            "category":"Professional",
            "subcategory":"Management & Consulting",
            "type":"Services"
        }
    ],
    "sg:phone":"+1 717 234 8800",
    "sg:postcode":"17110",
    "sg:province":"PA",
    "sg:tags":[
        "administrative"
    ],
    "sg:website":"www.krcpension.com",
    "wof:name":"Pension Alliance Inc",
    "wof:placetype":"venue"
},
  "geometry": {"coordinates":[-76.899265,40.314756],"type":"Point"}
}