{
  "type": "Feature",
  "properties": {
    "iso:country":"US",
    "sg:address":"4700 Brown St",
    "sg:city":"Philadelphia",
    "sg:phone":"+1 215 685 0260",
    "sg:postcode":"19139",
    "sg:province":"PA",
    "wof:name":"Mill Creek Playground",
    "wof:placetype":"venue"
},
  "geometry": {"coordinates":[-75.215431,39.966412],"type":"Point"}
}