{
  "type": "Feature",
  "properties": {
    "iso:country":"US",
    "sg:address":"355 Glade Mill Rd",
    "sg:city":"Valencia",
    "sg:classifiers":[
        {
            "category":"Building & Trades",
            "subcategory":"Construction",
            "type":"Services"
        }
    ],
    "sg:phone":"+1 724 898 2900",
    "sg:postcode":"16059",
    "sg:province":"PA",
    "wof:name":"Marshall Stamping Co",
    "wof:placetype":"venue"
},
  "geometry": {"coordinates":[-79.892869,40.720494],"type":"Point"}
}