{
  "type": "Feature",
  "properties": {
    "iso:country":"US",
    "sg:address":"728 Franklin St",
    "sg:city":"Johnstown",
    "sg:classifiers":[
        {
            "category":"Organizations",
            "subcategory":"Non-profit Organization",
            "type":"Services"
        }
    ],
    "sg:phone":"+1 814 536 1569",
    "sg:postcode":"15901",
    "sg:province":"PA",
    "wof:name":"Flood City Lodge",
    "wof:placetype":"venue"
},
  "geometry": {"coordinates":[-78.91578199999999,40.317203],"type":"Point"}
}