{
  "type": "Feature",
  "properties": {
    "addr:full":"370 Montgomery Ave Bala Cynwyd PA 19004",
    "addr:housenumber":"370",
    "addr:postcode":"19004",
    "addr:street":"Montgomery Ave",
    "iso:country":"US",
    "sg:address":"370 Montgomery Ave",
    "sg:city":"Bala Cynwyd",
    "sg:classifiers":[
        {
            "category":"Personal",
            "subcategory":"Tanning Parlor",
            "type":"Services"
        }
    ],
    "sg:phone":"+1 610 668 1104",
    "sg:postcode":"19004",
    "sg:province":"PA",
    "wof:name":"Hollywood Tans",
    "wof:placetype":"venue"
},
  "geometry": {"coordinates":[-75.231697,40.014099],"type":"Point"}
}