{
  "type": "Feature",
  "properties": {
    "iso:country":"US",
    "sg:address":"10175 Northeast Ave",
    "sg:city":"Philadelphia",
    "sg:classifiers":[
        {
            "category":"Home & Garden",
            "subcategory":"Furniture",
            "type":"Retail Goods"
        }
    ],
    "sg:phone":"+1 215 969 2997",
    "sg:postcode":"19116",
    "sg:province":"PA",
    "wof:name":"Black Red White Furniture Inc",
    "wof:placetype":"venue"
},
  "geometry": {"coordinates":[-75.02417,40.104708],"type":"Point"}
}