{
  "type": "Feature",
  "properties": {
    "iso:country":"US",
    "sg:address":"65 Valley Stream Pkwy",
    "sg:city":"Malvern",
    "sg:classifiers":[
        {
            "category":"Real Estate",
            "subcategory":"Real Estate Operator",
            "type":"Services"
        }
    ],
    "sg:phone":"+1   ",
    "sg:postcode":"19355",
    "sg:province":"PA",
    "sg:tags":[
        "development",
        "commercial"
    ],
    "wof:name":"Rouse & Associates Inc",
    "wof:placetype":"venue"
},
  "geometry": {"coordinates":[-75.524722,40.058193],"type":"Point"}
}