{
  "type": "Feature",
  "properties": {
    "iso:country":"US",
    "sg:address":"4166 Nantucket Dr",
    "sg:city":"Mechanicsburg",
    "sg:classifiers":[
        {
            "category":"Wholesale",
            "subcategory":"Durable Goods & Equipment",
            "type":"Manufacturing & Wholesale Goods"
        }
    ],
    "sg:phone":"+1   ",
    "sg:postcode":"17050",
    "sg:province":"PA",
    "wof:name":"Matthew S Gamber",
    "wof:placetype":"venue"
},
  "geometry": {"coordinates":[-76.971047,40.269322],"type":"Point"}
}