{
  "type": "Feature",
  "properties": {
    "iso:country":"US",
    "sg:address":"106 Lucille St",
    "sg:city":"Glenshaw",
    "sg:classifiers":[
        {
            "category":"Building & Trades",
            "subcategory":"Electrical",
            "type":"Services"
        }
    ],
    "sg:phone":"+1 412 487 7420",
    "sg:postcode":"15116",
    "sg:province":"PA",
    "sg:tags":[
        "electrician"
    ],
    "wof:name":"Keller Electric Company Inc",
    "wof:placetype":"venue"
},
  "geometry": {"coordinates":[-79.977413,40.534194],"type":"Point"}
}