{
  "type": "Feature",
  "properties": {
    "iso:country":"US",
    "sg:address":"201 N 8th St Unit 902",
    "sg:city":"Philadelphia",
    "sg:classifiers":[
        {
            "category":"Professional",
            "subcategory":"Computer Services",
            "type":"Services"
        },
        {
            "category":"Internet Cafe",
            "subcategory":"None",
            "type":"Food & Drink"
        }
    ],
    "sg:phone":"+1 607 242 5555",
    "sg:postcode":"19106",
    "sg:province":"PA",
    "sg:tags":[
        "product",
        "software"
    ],
    "wof:name":"L Morris Inc.",
    "wof:placetype":"venue"
},
  "geometry": {"coordinates":[-75.152672,39.955009],"type":"Point"}
}