{
  "type": "Feature",
  "properties": {
    "iso:country":"US",
    "sg:address":"109 Sunrise Dr",
    "sg:city":"Irwin",
    "sg:classifiers":[
        {
            "category":"Wholesale",
            "subcategory":"Construction Materials",
            "type":"Manufacturing & Wholesale Goods"
        },
        {
            "category":"Building & Trades",
            "subcategory":"Construction",
            "type":"Services"
        }
    ],
    "sg:phone":"+1 724 744 4655",
    "sg:postcode":"15642",
    "sg:province":"PA",
    "sg:tags":[
        "product",
        "asphalt"
    ],
    "wof:name":"Danesi Asphalt Sealing Co",
    "wof:placetype":"venue"
},
  "geometry": {"coordinates":[-79.686143,40.369674],"type":"Point"}
}