{
  "type": "Feature",
  "properties": {
    "addr:full":"422 Carolina Ave Whitehall PA 18052",
    "addr:housenumber":"422",
    "addr:postcode":"18052",
    "addr:street":"Carolina Ave",
    "iso:country":"US",
    "sg:address":"422 Carolina Ave",
    "sg:city":"Whitehall",
    "sg:classifiers":[
        {
            "category":"Building & Trades",
            "subcategory":"Construction",
            "type":"Services"
        }
    ],
    "sg:phone":"+1 610 820 5542",
    "sg:postcode":"18052",
    "sg:province":"PA",
    "sg:tags":[
        "painter"
    ],
    "wof:name":"J C Kessler Painting Plus",
    "wof:placetype":"venue"
},
  "geometry": {"coordinates":[-75.476862,40.626421],"type":"Point"}
}