{
  "type": "Feature",
  "properties": {
    "iso:country":"US",
    "sg:address":"374 Wellington Ter",
    "sg:city":"Jenkintown",
    "sg:classifiers":[
        {
            "category":"Shopping",
            "type":"Retail Goods"
        }
    ],
    "sg:phone":"+1   ",
    "sg:postcode":"19046",
    "sg:province":"PA",
    "sg:tags":[
        "merchandise"
    ],
    "wof:name":"Buckingham Mountain",
    "wof:placetype":"venue"
},
  "geometry": {"coordinates":[-75.119699,40.089024],"type":"Point"}
}