{
  "type": "Feature",
  "properties": {
    "addr:full":"1310 Monastery Dr Latrobe PA 15650",
    "addr:housenumber":"1310",
    "addr:postcode":"15650",
    "addr:street":"Monastery Dr",
    "iso:country":"US",
    "sg:address":"1310 Monastery Dr",
    "sg:city":"Latrobe",
    "sg:classifiers":[
        {
            "category":"Food & Beverages",
            "subcategory":"Groceries & Convenience Stores",
            "type":"Retail Goods"
        }
    ],
    "sg:phone":"+1 724 539 5591",
    "sg:postcode":"15650",
    "sg:province":"PA",
    "sg:tags":[
        "grocer"
    ],
    "wof:name":"Joe's Store",
    "wof:placetype":"venue"
},
  "geometry": {"coordinates":[-79.38219700000001,40.293246],"type":"Point"}
}