{
  "type": "Feature",
  "properties": {
    "addr:full":"6075 State Rte 308 Kennerdell PA 16374",
    "addr:housenumber":"6075",
    "addr:postcode":"16374",
    "addr:street":"State Rte 308 Kennerdell",
    "iso:country":"US",
    "sg:address":"6075 State Rte 308",
    "sg:city":"Kennerdell",
    "sg:classifiers":[
        {
            "category":"Freight",
            "type":"Transportation"
        }
    ],
    "sg:phone":"+1 814 385 4130",
    "sg:postcode":"16374",
    "sg:province":"PA",
    "sg:tags":[
        "general"
    ],
    "wof:name":"Evening Sun Self Storage",
    "wof:placetype":"venue"
},
  "geometry": {"coordinates":[-79.89776999999999,41.24644],"type":"Point"}
}