{
  "type": "Feature",
  "properties": {
    "addr:full":"707 N New St Bethlehem PA 18018",
    "addr:housenumber":"707",
    "addr:postcode":"18018",
    "addr:street":"N New St",
    "iso:country":"US",
    "sg:address":"707 N New St",
    "sg:city":"Bethlehem",
    "sg:classifiers":[
        {
            "category":"Personal",
            "subcategory":"Beauty Salon",
            "type":"Services"
        }
    ],
    "sg:phone":"+1 610 861 9497",
    "sg:postcode":"18018",
    "sg:province":"PA",
    "wof:name":"Shear Creations Inc",
    "wof:placetype":"venue"
},
  "geometry": {"coordinates":[-75.378435,40.624078],"type":"Point"}
}