{
  "type": "Feature",
  "properties": {
    "addr:full":"2100 State Rte 819 Mount Pleasant PA 15666",
    "addr:housenumber":"2100",
    "addr:postcode":"15666",
    "addr:street":"State Rte 819",
    "iso:country":"US",
    "sg:address":"2100 State Rte 819",
    "sg:city":"Mount Pleasant",
    "sg:classifiers":[
        {
            "category":"Wholesale",
            "subcategory":"Electrical",
            "type":"Manufacturing & Wholesale Goods"
        }
    ],
    "sg:phone":"+1   ",
    "sg:postcode":"15666",
    "sg:province":"PA",
    "sg:tags":[
        "equipment",
        "parts",
        "electronic",
        "telephone"
    ],
    "wof:name":"A T S",
    "wof:placetype":"venue"
},
  "geometry": {"coordinates":[-79.54585,40.171479],"type":"Point"}
}