{
  "type": "Feature",
  "properties": {
    "addr:full":"750 S 6th St Chambersburg PA 17201",
    "addr:housenumber":"750",
    "addr:postcode":"17201",
    "addr:street":"S 6Th St",
    "iso:country":"US",
    "sg:address":"750 S 6th St",
    "sg:city":"Chambersburg",
    "sg:classifiers":[
        {
            "category":"Organizations",
            "subcategory":"Religious Organization",
            "type":"Services"
        }
    ],
    "sg:phone":"+1   ",
    "sg:postcode":"17201",
    "sg:province":"PA",
    "wof:name":"First Baptist Church",
    "wof:placetype":"venue"
},
  "geometry": {"coordinates":[-77.65158700000001,39.925265],"type":"Point"}
}