{
  "type": "Feature",
  "properties": {
    "addr:full":"317 E 6th Ave Tarentum PA 15084",
    "addr:housenumber":"317",
    "addr:postcode":"15084",
    "addr:street":"E 6Th Ave",
    "iso:country":"US",
    "sg:address":"317 E 6th Ave",
    "sg:city":"Tarentum",
    "sg:classifiers":[
        {
            "category":"Shopping",
            "subcategory":"Florist",
            "type":"Retail Goods"
        }
    ],
    "sg:phone":"+1 724 224 2774",
    "sg:postcode":"15084",
    "sg:province":"PA",
    "wof:name":"Tarentum Floral",
    "wof:placetype":"venue"
},
  "geometry": {"coordinates":[-79.75427500000001,40.602621],"type":"Point"}
}