{
  "type": "Feature",
  "properties": {
    "iso:country":"US",
    "sg:address":"756 S Coldbrook Ave",
    "sg:city":"Chambersburg",
    "sg:classifiers":[
        {
            "category":"Education",
            "subcategory":"School",
            "type":"Public Place"
        }
    ],
    "sg:phone":"+1 717 261 3433",
    "sg:postcode":"17201",
    "sg:province":"PA",
    "wof:name":"Coldbrook Elementary School",
    "wof:placetype":"venue"
},
  "geometry": {"coordinates":[-77.651499,39.924047],"type":"Point"}
}