{
  "type": "Feature",
  "properties": {
    "iso:country":"US",
    "sg:address":"1011 N Main Ave",
    "sg:city":"Scranton",
    "sg:classifiers":[
        {
            "category":"Restaurant",
            "type":"Food & Drink"
        }
    ],
    "sg:phone":"+1 570 961 3317",
    "sg:postcode":"18508",
    "sg:province":"PA",
    "sg:tags":[
        "banquet",
        "rooms"
    ],
    "wof:name":"Tripp House",
    "wof:placetype":"venue"
},
  "geometry": {"coordinates":[-75.67081,41.425425],"type":"Point"}
}