{
  "type": "Feature",
  "properties": {
    "iso:country":"US",
    "sg:address":"2936 McNeal Rd",
    "sg:city":"Allison Park",
    "sg:classifiers":[
        {
            "category":"Professional",
            "subcategory":"Secretarial Services",
            "type":"Services"
        }
    ],
    "sg:phone":"+1 724 443 5730",
    "sg:postcode":"15101",
    "sg:province":"PA",
    "sg:tags":[
        "convention",
        "court",
        "reporter"
    ],
    "wof:name":"Urbash Professional Reporting",
    "wof:placetype":"venue"
},
  "geometry": {"coordinates":[-79.94209499999999,40.597735],"type":"Point"}
}