{
  "type": "Feature",
  "properties": {
    "iso:country":"US",
    "sg:address":"117 Maple Ave",
    "sg:city":"East Stroudsburg",
    "sg:classifiers":[
        {
            "category":"Home & Garden",
            "subcategory":"Furniture",
            "type":"Retail Goods"
        }
    ],
    "sg:phone":"+1 570 421 2428",
    "sg:postcode":"18301",
    "sg:province":"PA",
    "wof:name":"T G Goodstuff",
    "wof:placetype":"venue"
},
  "geometry": {"coordinates":[-75.186311,41.007643],"type":"Point"}
}