{
  "type": "Feature",
  "properties": {
    "iso:country":"US",
    "sg:address":"364 Jubilee Dr",
    "sg:city":"Bridgeville",
    "sg:classifiers":[
        {
            "category":"Communications",
            "type":"Services"
        }
    ],
    "sg:phone":"+1   ",
    "sg:postcode":"15017",
    "sg:province":"PA",
    "sg:tags":[
        "communication"
    ],
    "wof:name":"Freedom Village Media LLC",
    "wof:placetype":"venue"
},
  "geometry": {"coordinates":[-80.14448899999999,40.318703],"type":"Point"}
}