{
  "type": "Feature",
  "properties": {
    "addr:full":"5360 William Flynn Hwy Gibsonia PA 15044",
    "addr:housenumber":"5360",
    "addr:postcode":"15044",
    "addr:street":"William Flynn Hwy",
    "iso:country":"US",
    "sg:address":"5360 William Flynn Hwy",
    "sg:city":"Gibsonia",
    "sg:classifiers":[
        {
            "category":"Home & Garden",
            "subcategory":"Garden Supply",
            "type":"Retail Goods"
        },
        {
            "category":"Home & Garden",
            "subcategory":"Building Materials",
            "type":"Retail Goods"
        },
        {
            "category":"Manufacturing",
            "subcategory":"Building Materials",
            "type":"Manufacturing & Wholesale Goods"
        }
    ],
    "sg:phone":"+1 724 638 4815",
    "sg:postcode":"15044",
    "sg:province":"PA",
    "sg:tags":[
        "product",
        "landscaping",
        "wall",
        "equipment",
        "concrete",
        "retaining"
    ],
    "sg:website":"http://www.omnipropittsburgh.com",
    "wof:name":"OmniPro",
    "wof:placetype":"venue"
},
  "geometry": {"coordinates":[-79.94546099999999,40.618065],"type":"Point"}
}