{
  "type": "Feature",
  "properties": {
    "iso:country":"US",
    "sg:address":"320 S 2nd St",
    "sg:city":"Bangor",
    "sg:classifiers":[
        {
            "category":"Professional",
            "type":"Services"
        }
    ],
    "sg:phone":"+1 610 588 3059",
    "sg:postcode":"18013",
    "sg:province":"PA",
    "sg:tags":[
        "establishment"
    ],
    "wof:name":"Presbyterian Manse",
    "wof:placetype":"venue"
},
  "geometry": {"coordinates":[-75.20781700000001,40.863675],"type":"Point"}
}