{
  "type": "Feature",
  "properties": {
    "iso:country":"US",
    "sg:address":"2100 E Allegheny Ave",
    "sg:city":"Philadelphia",
    "sg:classifiers":[
        {
            "category":"Autos & Motor Vehicles",
            "subcategory":"Fuel & Gas Station",
            "type":"Retail Goods"
        }
    ],
    "sg:phone":"+1 215 426 1543",
    "sg:postcode":"19134",
    "sg:province":"PA",
    "sg:tags":[
        "gasoline"
    ],
    "wof:name":"Atlantic Service Station",
    "wof:placetype":"venue"
},
  "geometry": {"coordinates":[-75.109596,39.992001],"type":"Point"}
}