{
  "type": "Feature",
  "properties": {
    "iso:country":"US",
    "sg:address":"29 W Blaine St",
    "sg:city":"Mcadoo",
    "sg:classifiers":[
        {
            "category":"Retail",
            "subcategory":"Laundry & Dry Cleaning",
            "type":"Services"
        }
    ],
    "sg:phone":"+1 570 929 2411",
    "sg:postcode":"18237",
    "sg:province":"PA",
    "sg:tags":[
        "gown",
        "bridal",
        "preservation"
    ],
    "wof:name":"Deluxe Cleaners",
    "wof:placetype":"venue"
},
  "geometry": {"coordinates":[-75.994004,40.902213],"type":"Point"}
}