{
  "type": "Feature",
  "properties": {
    "iso:country":"US",
    "sg:address":"815 N 5th St",
    "sg:city":"Philadelphia",
    "sg:classifiers":[
        {
            "category":"Real Estate",
            "subcategory":"Architect",
            "type":"Services"
        }
    ],
    "sg:phone":"+1 215 922 3082",
    "sg:postcode":"19123",
    "sg:province":"PA",
    "wof:name":"K C Architects",
    "wof:placetype":"venue"
},
  "geometry": {"coordinates":[-75.14616100000001,39.964643],"type":"Point"}
}