{
  "type": "Feature",
  "properties": {
    "iso:country":"US",
    "sg:address":"4918 Cedar Ave",
    "sg:city":"Philadelphia",
    "sg:classifiers":[
        {
            "category":"Professional",
            "subcategory":"Business Services",
            "type":"Services"
        },
        {
            "category":"Conference Center",
            "type":"Public Place"
        }
    ],
    "sg:phone":"+1 215 747 6577",
    "sg:postcode":"19143",
    "sg:province":"PA",
    "sg:tags":[
        "facility",
        "supply",
        "convention"
    ],
    "sg:website":"http://www.caobadoors.com",
    "wof:name":"Caoba Doors",
    "wof:placetype":"venue"
},
  "geometry": {"coordinates":[-75.2213,39.949763],"type":"Point"}
}