{
  "type": "Feature",
  "properties": {
    "addr:full":"8016 Steubenville Pike Oakdale PA 15071",
    "addr:housenumber":"8016",
    "addr:postcode":"15071",
    "addr:street":"Steubenville Pike",
    "iso:country":"US",
    "sg:address":"8016 Steubenville Pike",
    "sg:city":"Oakdale",
    "sg:classifiers":[
        {
            "category":"Retail",
            "subcategory":"Auto Repair",
            "type":"Services"
        }
    ],
    "sg:phone":"+1 724 695 2700",
    "sg:postcode":"15071",
    "sg:province":"PA",
    "sg:tags":[
        "body",
        "automobile",
        "painting"
    ],
    "wof:name":"Bastaroli's Auto Body",
    "wof:placetype":"venue"
},
  "geometry": {"coordinates":[-80.245606,40.440985],"type":"Point"}
}