{
  "type": "Feature",
  "properties": {
    "addr:full":"1601 N 15th St Philadelphia PA 19121",
    "addr:housenumber":"1601",
    "addr:postcode":"19121",
    "addr:street":"N 15Th St",
    "iso:country":"US",
    "sg:address":"1601 N 15th St",
    "sg:city":"Philadelphia",
    "sg:classifiers":[
        {
            "category":"Professional",
            "type":"Services"
        }
    ],
    "sg:phone":"+1 267 902 5373",
    "sg:postcode":"19121",
    "sg:province":"PA",
    "sg:tags":[
        "planning",
        "event"
    ],
    "sg:website":"www.festivefotobooths.com",
    "wof:name":"Festive Fotobooths",
    "wof:placetype":"venue"
},
  "geometry": {"coordinates":[-75.159852,39.977513],"type":"Point"}
}