{
  "type": "Feature",
  "properties": {
    "iso:country":"US",
    "sg:address":"457 Locust St",
    "sg:city":"Columbia",
    "sg:classifiers":[
        {
            "category":"Professional",
            "subcategory":"Lawyer & Legal Services",
            "type":"Services"
        }
    ],
    "sg:phone":"+1 877 302 5486",
    "sg:postcode":"17512",
    "sg:province":"PA",
    "sg:tags":[
        "attorney",
        "death",
        "personal",
        "wrongful",
        "injury",
        "law"
    ],
    "sg:website":"http://www.lawyers.com",
    "wof:name":"Zimmerman, Pfannebecker, Nuffort & Albert",
    "wof:placetype":"venue"
},
  "geometry": {"coordinates":[-76.500064,40.033555],"type":"Point"}
}