{
  "type": "Feature",
  "properties": {
    "iso:country":"US",
    "sg:address":"2115 Colebrook Rd",
    "sg:city":"Lebanon",
    "sg:classifiers":[
        {
            "category":"Organizations",
            "subcategory":"Religious Organization",
            "type":"Services"
        }
    ],
    "sg:phone":"+1 717 273 5199",
    "sg:postcode":"17042",
    "sg:province":"PA",
    "sg:tags":[
        "clergy"
    ],
    "wof:name":"Calvin T Reed",
    "wof:placetype":"venue"
},
  "geometry": {"coordinates":[-76.460639,40.297993],"type":"Point"}
}