{
  "type": "Feature",
  "properties": {
    "iso:country":"US",
    "sg:address":"1010 N 7th St Ste 304",
    "sg:city":"Harrisburg",
    "sg:classifiers":[
        {
            "category":"Education",
            "subcategory":"University",
            "type":"Public Place"
        }
    ],
    "sg:phone":"+1 717 772 3590",
    "sg:postcode":"17102",
    "sg:province":"PA",
    "sg:tags":[
        "college"
    ],
    "wof:name":"Penn State Eastgate Ctr",
    "wof:placetype":"venue"
},
  "geometry": {"coordinates":[-76.882301,40.2696],"type":"Point"}
}