{
  "type": "Feature",
  "properties": {
    "iso:country":"US",
    "sg:address":"987 Eisenhower Blvd",
    "sg:city":"Harrisburg",
    "sg:classifiers":[
        {
            "category":"Restaurant",
            "type":"Food & Drink"
        }
    ],
    "sg:menulink":"http://www.allmenus.com/pa/swatara/28015-gilligans/menu/",
    "sg:phone":"+1 717 939 9575",
    "sg:postcode":"17111",
    "sg:province":"PA",
    "sg:tags":[
        "american",
        "pub"
    ],
    "wof:name":"Gilligan's",
    "wof:placetype":"venue"
},
  "geometry": {"coordinates":[-76.805024,40.239104],"type":"Point"}
}