{
  "type": "Feature",
  "properties": {
    "addr:full":"7215 McKnight Rd Pittsburgh PA 15237",
    "addr:housenumber":"7215",
    "addr:postcode":"15237",
    "addr:street":"Mcknight Rd",
    "iso:country":"US",
    "sg:address":"7215 McKnight Rd",
    "sg:city":"Pittsburgh",
    "sg:classifiers":[
        {
            "category":"Home & Garden",
            "subcategory":"Furniture",
            "type":"Retail Goods"
        }
    ],
    "sg:phone":"+1   ",
    "sg:postcode":"15237",
    "sg:province":"PA",
    "wof:name":"Roomfull Express Furniture",
    "wof:placetype":"venue"
},
  "geometry": {"coordinates":[-80.01387699999999,40.542977],"type":"Point"}
}