{
  "type": "Feature",
  "properties": {
    "iso:country":"US",
    "sg:address":"308 N Lewis Rd",
    "sg:city":"Royersford",
    "sg:classifiers":[
        {
            "category":"Restaurant",
            "type":"Food & Drink"
        }
    ],
    "sg:menulink":"http://www.allmenus.com/pa/limerick/206814-mcdonalds/menu/",
    "sg:phone":"+1 610 948 9472",
    "sg:postcode":"19468",
    "sg:province":"PA",
    "sg:tags":[
        "burger",
        "american"
    ],
    "wof:name":"McDonald's",
    "wof:placetype":"venue"
},
  "geometry": {"coordinates":[-75.534068,40.194352],"type":"Point"}
}