{
  "type": "Feature",
  "properties": {
    "addr:full":"1424 Connellsville Rd Lemont Furnace PA 15456",
    "addr:housenumber":"1424",
    "addr:postcode":"15456",
    "addr:street":"Connellsville Rd",
    "iso:country":"US",
    "sg:address":"1424 Connellsville Rd",
    "sg:city":"Lemont Furnace",
    "sg:classifiers":[
        {
            "category":"Retail",
            "subcategory":"Auto Repair",
            "type":"Services"
        }
    ],
    "sg:phone":"+1 724 438 4189",
    "sg:postcode":"15456",
    "sg:province":"PA",
    "sg:tags":[
        "transmission"
    ],
    "wof:name":"Hi Performance Auto Svc",
    "wof:placetype":"venue"
},
  "geometry": {"coordinates":[-79.667965,39.930584],"type":"Point"}
}