{
  "type": "Feature",
  "properties": {
    "iso:country":"US",
    "sg:address":"101 Shelbourne Dr",
    "sg:city":"Coraopolis",
    "sg:classifiers":[
        {
            "category":"Building & Trades",
            "subcategory":"Construction",
            "type":"Services"
        }
    ],
    "sg:phone":"+1 724 457 6747",
    "sg:postcode":"15108",
    "sg:province":"PA",
    "sg:tags":[
        "home",
        "builder"
    ],
    "wof:name":"Maronda Homes Inc",
    "wof:placetype":"venue"
},
  "geometry": {"coordinates":[-80.253698,40.530187],"type":"Point"}
}