{
  "type": "Feature",
  "properties": {
    "iso:country":"US",
    "sg:address":"122 N Central Ave",
    "sg:city":"Canonsburg",
    "sg:classifiers":[
        {
            "category":"Recreation",
            "type":"Entertainment"
        }
    ],
    "sg:phone":"+1   ",
    "sg:postcode":"15317",
    "sg:province":"PA",
    "sg:tags":[
        "club",
        "membership"
    ],
    "wof:name":"Foe 861",
    "wof:placetype":"venue"
},
  "geometry": {"coordinates":[-80.1866,40.25947],"type":"Point"}
}