{
  "type": "Feature",
  "properties": {
    "addr:full":"12 E Washington St New Castle PA 16101",
    "addr:housenumber":"12",
    "addr:postcode":"16101",
    "addr:street":"E Washington St",
    "iso:country":"US",
    "sg:address":"12 E Washington St",
    "sg:city":"New Castle",
    "sg:classifiers":[
        {
            "category":"Wholesale",
            "subcategory":"Vending Machines",
            "type":"Manufacturing & Wholesale Goods"
        }
    ],
    "sg:phone":"+1   ",
    "sg:postcode":"16101",
    "sg:province":"PA",
    "sg:tags":[
        "operator"
    ],
    "wof:name":"M J C Vending Company Inc",
    "wof:placetype":"venue"
},
  "geometry": {"coordinates":[-80.346934,40.999998],"type":"Point"}
}