{
  "type": "Feature",
  "properties": {
    "addr:full":"2080 W State St New Castle PA 16101",
    "addr:housenumber":"2080",
    "addr:postcode":"16101",
    "addr:street":"W State St",
    "iso:country":"US",
    "sg:address":"2080 W State St",
    "sg:city":"New Castle",
    "sg:classifiers":[
        {
            "category":"Shopping",
            "subcategory":"Department Store",
            "type":"Retail Goods"
        }
    ],
    "sg:phone":"+1 724 658 4500",
    "sg:postcode":"16101",
    "sg:province":"PA",
    "sg:tags":[
        "shop"
    ],
    "wof:name":"Family Dollar Store",
    "wof:placetype":"venue"
},
  "geometry": {"coordinates":[-80.383579,41.008213],"type":"Point"}
}