{
  "type": "Feature",
  "properties": {
    "iso:country":"US",
    "sg:address":"387 Theatre Rd",
    "sg:city":"Carrolltown",
    "sg:classifiers":[
        {
            "category":"Sports & Exercise",
            "subcategory":"Gym",
            "type":"Entertainment"
        }
    ],
    "sg:phone":"+1 814 344 8665",
    "sg:postcode":"15722",
    "sg:province":"PA",
    "sg:tags":[
        "fitness",
        "physical",
        "facility"
    ],
    "wof:name":"Curves For Women",
    "wof:placetype":"venue"
},
  "geometry": {"coordinates":[-78.716916,40.619745],"type":"Point"}
}