{
  "type": "Feature",
  "properties": {
    "iso:country":"US",
    "sg:address":"757 E Street Rd",
    "sg:city":"Southampton",
    "sg:classifiers":[
        {
            "category":"Shopping",
            "subcategory":"Florist",
            "type":"Retail Goods"
        }
    ],
    "sg:phone":"+1 215 355 6430",
    "sg:postcode":"18966",
    "sg:province":"PA",
    "wof:name":"Cherry Lane Florist",
    "wof:placetype":"venue"
},
  "geometry": {"coordinates":[-75.041815,40.173356],"type":"Point"}
}