{
  "type": "Feature",
  "properties": {
    "addr:full":"777 Dekalb Pike Blue Bell PA 19422",
    "addr:housenumber":"777",
    "addr:postcode":"19422",
    "addr:street":"Dekalb Pike",
    "iso:country":"US",
    "sg:address":"777 Dekalb Pike",
    "sg:city":"Blue Bell",
    "sg:classifiers":[
        {
            "category":"Social Services",
            "subcategory":"Retirement Home",
            "type":"Services"
        }
    ],
    "sg:phone":"+1 610 277 6443",
    "sg:postcode":"19422",
    "sg:province":"PA",
    "wof:name":"Blue Bell Place",
    "wof:placetype":"venue"
},
  "geometry": {"coordinates":[-75.288803,40.1684],"type":"Point"}
}