{
  "type": "Feature",
  "properties": {
    "iso:country":"US",
    "sg:address":"451 Stoystown Rd",
    "sg:city":"Somerset",
    "sg:classifiers":[
        {
            "category":"Mining & Drilling",
            "type":"Manufacturing & Wholesale Goods"
        }
    ],
    "sg:phone":"+1 814 445 1010",
    "sg:postcode":"15501",
    "sg:province":"PA",
    "sg:tags":[
        "stone"
    ],
    "wof:name":"Garrett Limestone Inc",
    "wof:placetype":"venue"
},
  "geometry": {"coordinates":[-79.069924,40.014674],"type":"Point"}
}