{
  "type": "Feature",
  "properties": {
    "iso:country":"US",
    "sg:address":"390 Forest Inn Rd",
    "sg:city":"Lehighton",
    "sg:classifiers":[
        {
            "category":"Real Estate",
            "subcategory":"Real Estate Agent",
            "type":"Services"
        }
    ],
    "sg:phone":"+1 610 377 8000",
    "sg:postcode":"18235",
    "sg:province":"PA",
    "wof:name":"Koehler-Marvin Realty Assoc",
    "wof:placetype":"venue"
},
  "geometry": {"coordinates":[-75.59417500000001,40.852926],"type":"Point"}
}