{
  "type": "Feature",
  "properties": {
    "addr:full":"206 E Main St Sykesville PA 15865",
    "addr:housenumber":"206",
    "addr:postcode":"15865",
    "addr:street":"E Main St",
    "iso:country":"US",
    "sg:address":"206 E Main St",
    "sg:city":"Sykesville",
    "sg:classifiers":[
        {
            "category":"Restaurant",
            "type":"Food & Drink"
        }
    ],
    "sg:menulink":"http://www.allmenus.com/pa/sykesville/67754-foxs-pizza-den/menu/",
    "sg:phone":"+1 814 894 7777",
    "sg:postcode":"15865",
    "sg:province":"PA",
    "sg:tags":[
        "american",
        "pizza"
    ],
    "wof:name":"Fox's Pizza Den",
    "wof:placetype":"venue"
},
  "geometry": {"coordinates":[-78.818511,41.051853],"type":"Point"}
}