{
  "type": "Feature",
  "properties": {
    "iso:country":"US",
    "sg:address":"418 Archer St",
    "sg:city":"Mckeesport",
    "sg:classifiers":[
        {
            "category":"Retail",
            "subcategory":"Auto Repair",
            "type":"Services"
        }
    ],
    "sg:phone":"+1 412 678 8414",
    "sg:postcode":"15132",
    "sg:province":"PA",
    "wof:name":"Bob's Auto",
    "wof:placetype":"venue"
},
  "geometry": {"coordinates":[-79.875558,40.347201],"type":"Point"}
}