{
  "type": "Feature",
  "properties": {
    "iso:country":"US",
    "sg:address":"1127 E Stafford St",
    "sg:city":"Philadelphia",
    "sg:classifiers":[
        {
            "category":"Freight",
            "type":"Transportation"
        }
    ],
    "sg:phone":"+1   ",
    "sg:postcode":"19138",
    "sg:province":"PA",
    "sg:tags":[
        "mover"
    ],
    "wof:name":"Apris Movers",
    "wof:placetype":"venue"
},
  "geometry": {"coordinates":[-75.160062,40.051188],"type":"Point"}
}