{
  "type": "Feature",
  "properties": {
    "iso:country":"US",
    "sg:address":"60 Shenango Ave",
    "sg:city":"Sharon",
    "sg:classifiers":[
        {
            "category":"Restaurant",
            "type":"Food & Drink"
        }
    ],
    "sg:phone":"+1 724 342 1444",
    "sg:postcode":"16146",
    "sg:province":"PA",
    "sg:website":"www.svbanquets.com",
    "wof:name":"Echoes",
    "wof:placetype":"venue"
},
  "geometry": {"coordinates":[-80.508353,41.23438],"type":"Point"}
}