{
  "type": "Feature",
  "properties": {
    "iso:country":"US",
    "sg:address":"1691 Horseshoe Pike",
    "sg:city":"Glenmoore",
    "sg:classifiers":[
        {
            "category":"Professional",
            "subcategory":"Research",
            "type":"Services"
        }
    ],
    "sg:phone":"+1 610 942 9010",
    "sg:postcode":"19343",
    "sg:province":"PA",
    "sg:tags":[
        "environmental",
        "ecological"
    ],
    "sg:website":"www.mcenvironmental.com",
    "wof:name":"Mulry & Creswell Environmental",
    "wof:placetype":"venue"
},
  "geometry": {"coordinates":[-75.807125,40.060029],"type":"Point"}
}