{
  "type": "Feature",
  "properties": {
    "iso:country":"US",
    "sg:address":"4319 Washington Ave",
    "sg:city":"Erie",
    "sg:classifiers":[
        {
            "category":"Real Estate",
            "subcategory":"Architect",
            "type":"Services"
        }
    ],
    "sg:phone":"+1 814 866 6080",
    "sg:postcode":"16509",
    "sg:province":"PA",
    "wof:name":"Dominick P Sicari",
    "wof:placetype":"venue"
},
  "geometry": {"coordinates":[-80.09446800000001,42.086006],"type":"Point"}
}