{
  "type": "Feature",
  "properties": {
    "iso:country":"US",
    "sg:address":"3842 Post Dr",
    "sg:city":"Bethlehem",
    "sg:classifiers":[
        {
            "category":"Building & Trades",
            "subcategory":"Construction",
            "type":"Services"
        }
    ],
    "sg:phone":"+1 610 691 3476",
    "sg:postcode":"18017",
    "sg:province":"PA",
    "sg:tags":[
        "resurfacing",
        "laying",
        "refinishing",
        "floor"
    ],
    "wof:name":"Michael J Kratzer",
    "wof:placetype":"venue"
},
  "geometry": {"coordinates":[-75.38648000000001,40.671512],"type":"Point"}
}