{
  "type": "Feature",
  "properties": {
    "iso:country":"US",
    "sg:address":"1232 Brinton Rd",
    "sg:city":"Pittsburgh",
    "sg:classifiers":[
        {
            "category":"Professional",
            "subcategory":"Business Services",
            "type":"Services"
        }
    ],
    "sg:phone":"+1   ",
    "sg:postcode":"15221",
    "sg:province":"PA",
    "sg:tags":[
        "appraisal"
    ],
    "wof:name":"Rfh Appraisal Service",
    "wof:placetype":"venue"
},
  "geometry": {"coordinates":[-79.86724,40.423095],"type":"Point"}
}