{
  "type": "Feature",
  "properties": {
    "iso:country":"US",
    "sg:address":"600 Pine Hollow Rd",
    "sg:city":"Pittsburgh",
    "sg:classifiers":[
        {
            "category":"Restaurant",
            "type":"Food & Drink"
        }
    ],
    "sg:phone":"+1 412 771 9570",
    "sg:postcode":"15203",
    "sg:province":"PA",
    "wof:name":"McDonald's Restaurants",
    "wof:placetype":"venue"
},
  "geometry": {"coordinates":[-80.07729,40.470308],"type":"Point"}
}