{
  "type": "Feature",
  "properties": {
    "iso:country":"US",
    "sg:address":"1921 Clark Rd",
    "sg:city":"Erie",
    "sg:classifiers":[
        {
            "category":"Professional",
            "subcategory":"Advertising",
            "type":"Services"
        },
        {
            "category":"Manufacturing",
            "subcategory":"Signs",
            "type":"Manufacturing & Wholesale Goods"
        }
    ],
    "sg:phone":"+1 814 898 4666",
    "sg:postcode":"16510",
    "sg:province":"PA",
    "sg:tags":[
        "specialty"
    ],
    "wof:name":"Graphic Details Inc",
    "wof:placetype":"venue"
},
  "geometry": {"coordinates":[-79.979373,42.155028],"type":"Point"}
}