{
  "type": "Feature",
  "properties": {
    "iso:country":"US",
    "sg:address":"2036 W Main St",
    "sg:city":"Ephrata",
    "sg:classifiers":[
        {
            "category":"Autos & Motor Vehicles",
            "subcategory":"Automobile Sales",
            "type":"Retail Goods"
        }
    ],
    "sg:phone":"+1 717 733 5060",
    "sg:postcode":"17522",
    "sg:province":"PA",
    "sg:tags":[
        "used"
    ],
    "wof:name":"Rides Auto Sales",
    "wof:placetype":"venue"
},
  "geometry": {"coordinates":[-76.235388,40.21214],"type":"Point"}
}