{
  "type": "Feature",
  "properties": {
    "iso:country":"US",
    "sg:address":"212 South St",
    "sg:city":"Philadelphia",
    "sg:classifiers":[
        {
            "category":"Restaurant",
            "type":"Food & Drink"
        }
    ],
    "sg:phone":"+1 215 923 2630",
    "sg:postcode":"19147",
    "sg:province":"PA",
    "sg:tags":[
        "health"
    ],
    "wof:name":"Rhino Coffee",
    "wof:placetype":"venue"
},
  "geometry": {"coordinates":[-75.146151,39.941303],"type":"Point"}
}