{
  "type": "Feature",
  "properties": {
    "addr:full":"485 Franklin St Clymer PA 15728",
    "addr:housenumber":"485",
    "addr:postcode":"15728",
    "addr:street":"Franklin St",
    "iso:country":"US",
    "sg:address":"485 Franklin St",
    "sg:city":"Clymer",
    "sg:classifiers":[
        {
            "category":"Organizations",
            "subcategory":"Community Association",
            "type":"Services"
        }
    ],
    "sg:phone":"+1 724 254 4710",
    "sg:postcode":"15728",
    "sg:province":"PA",
    "sg:tags":[
        "military"
    ],
    "wof:name":"American Legion",
    "wof:placetype":"venue"
},
  "geometry": {"coordinates":[-79.010481,40.669238],"type":"Point"}
}