{
  "type": "Feature",
  "properties": {
    "iso:country":"US",
    "sg:address":"RR 1",
    "sg:city":"Concordville",
    "sg:classifiers":[
        {
            "category":"Banks & Credit Unions",
            "subcategory":"Bank",
            "type":"Services"
        }
    ],
    "sg:phone":"+1 610 459 0977",
    "sg:postcode":"19331",
    "sg:province":"PA",
    "wof:name":"M & T Bank",
    "wof:placetype":"venue"
},
  "geometry": {"coordinates":[-75.5317,39.884602],"type":"Point"}
}