{
  "type": "Feature",
  "properties": {
    "iso:country":"US",
    "sg:address":"2000 Penn Ave",
    "sg:city":"Jeannette",
    "sg:classifiers":[
        {
            "category":"Food & Beverages",
            "subcategory":"Groceries & Convenience Stores",
            "type":"Retail Goods"
        }
    ],
    "sg:phone":"+1 724 744 6113",
    "sg:postcode":"15644",
    "sg:province":"PA",
    "sg:website":"www.festivalfoods.com",
    "wof:name":"Festival Foods",
    "wof:placetype":"venue"
},
  "geometry": {"coordinates":[-79.633189,40.33032],"type":"Point"}
}