{
  "type": "Feature",
  "properties": {
    "iso:country":"US",
    "sg:address":"1324 W 3rd St",
    "sg:city":"Williamsport",
    "sg:classifiers":[
        {
            "category":"Restaurant",
            "type":"Food & Drink"
        }
    ],
    "sg:phone":"+1 570 321 9800",
    "sg:postcode":"17701",
    "sg:province":"PA",
    "wof:name":"Smokey Jo's",
    "wof:placetype":"venue"
},
  "geometry": {"coordinates":[-77.033558,41.237299],"type":"Point"}
}