{
  "type": "Feature",
  "properties": {
    "iso:country":"US",
    "sg:address":"14795 Charmian Rd",
    "sg:city":"Blue Ridge Summit",
    "sg:classifiers":[
        {
            "category":"Travel",
            "subcategory":"Hotels & Motels",
            "type":"Entertainment"
        }
    ],
    "sg:phone":"+1 717 794 2962",
    "sg:postcode":"17214",
    "sg:province":"PA",
    "sg:tags":[
        "breakfast",
        "operation",
        "bed",
        "accommodation"
    ],
    "wof:name":"Monte Vista Bed & Breakfast",
    "wof:placetype":"venue"
},
  "geometry": {"coordinates":[-77.46584799999999,39.739791],"type":"Point"}
}