{
  "type": "Feature",
  "properties": {
    "addr:full":"5300 Library Rd Bethel Park PA 15102",
    "addr:housenumber":"5300",
    "addr:postcode":"15102",
    "addr:street":"Library Rd",
    "iso:country":"US",
    "sg:address":"5300 Library Rd",
    "sg:city":"Bethel Park",
    "sg:classifiers":[
        {
            "category":"Restaurant",
            "type":"Food & Drink"
        }
    ],
    "sg:menulink":"http://www.allmenus.com/pa/bethel-park/38653-papa-johns-pizza/menu/",
    "sg:phone":"+1 412 833 7171",
    "sg:postcode":"15102",
    "sg:province":"PA",
    "sg:tags":[
        "american",
        "pizza"
    ],
    "wof:name":"Papa John's Pizza",
    "wof:placetype":"venue"
},
  "geometry": {"coordinates":[-80.022023,40.330321],"type":"Point"}
}