{
  "type": "Feature",
  "properties": {
    "addr:full":"1374 Peninsula Dr Central City PA 15926",
    "addr:housenumber":"1374",
    "addr:postcode":"15926",
    "addr:street":"Peninsula Dr",
    "iso:country":"US",
    "sg:address":"1374 Peninsula Dr",
    "sg:city":"Central City",
    "sg:classifiers":[
        {
            "category":"Mining & Drilling",
            "type":"Manufacturing & Wholesale Goods"
        }
    ],
    "sg:phone":"+1   ",
    "sg:postcode":"15926",
    "sg:province":"PA",
    "sg:tags":[
        "reclamation",
        "mine"
    ],
    "wof:name":"East Ridge Mining Inc",
    "wof:placetype":"venue"
},
  "geometry": {"coordinates":[-78.872666,40.036385],"type":"Point"}
}