{
  "type": "Feature",
  "properties": {
    "iso:country":"US",
    "sg:address":"115 Big Shannon Run Rd",
    "sg:city":"Mount Morris",
    "sg:classifiers":[
        {
            "category":"Professional",
            "subcategory":"Art Services",
            "type":"Services"
        }
    ],
    "sg:phone":"+1   ",
    "sg:postcode":"15349",
    "sg:province":"PA",
    "sg:tags":[
        "photography",
        "commercial"
    ],
    "wof:name":"JC Enterprises",
    "wof:placetype":"venue"
},
  "geometry": {"coordinates":[-80.07408,39.733814],"type":"Point"}
}