{
  "type": "Feature",
  "properties": {
    "iso:country":"US",
    "sg:address":"999 Postal Rd",
    "sg:city":"Allentown",
    "sg:classifiers":[
        {
            "category":"Manufacturing",
            "subcategory":"Printing",
            "type":"Manufacturing & Wholesale Goods"
        }
    ],
    "sg:phone":"+1 610 231 1860",
    "sg:postcode":"18109",
    "sg:province":"PA",
    "sg:tags":[
        "printer"
    ],
    "sg:website":"www.crdpersol.com",
    "wof:name":"Card Personalization Solutions",
    "wof:placetype":"venue"
},
  "geometry": {"coordinates":[-75.44211900000001,40.645499],"type":"Point"}
}