{
  "type": "Feature",
  "properties": {
    "iso:country":"US",
    "sg:address":"360 E Main St",
    "sg:city":"Carnegie",
    "sg:classifiers":[
        {
            "category":"Insurance",
            "subcategory":"Hazard Insurance",
            "type":"Services"
        }
    ],
    "sg:phone":"+1 412 279 2429",
    "sg:postcode":"15106",
    "sg:province":"PA",
    "sg:tags":[
        "commercial",
        "business"
    ],
    "wof:name":"Bradley Sheasley",
    "wof:placetype":"venue"
},
  "geometry": {"coordinates":[-80.083185,40.409699],"type":"Point"}
}