{
  "type": "Feature",
  "properties": {
    "addr:full":"728 N Centre St Pottsville PA 17901",
    "addr:housenumber":"728",
    "addr:postcode":"17901",
    "addr:street":"N Centre St",
    "iso:country":"US",
    "sg:address":"728 N Centre St",
    "sg:city":"Pottsville",
    "sg:classifiers":[
        {
            "category":"Organizations",
            "subcategory":"Religious Organization",
            "type":"Services"
        }
    ],
    "sg:phone":"+1 570 622 7004",
    "sg:postcode":"17901",
    "sg:province":"PA",
    "wof:name":"Mary Queen Of Peace Church",
    "wof:placetype":"venue"
},
  "geometry": {"coordinates":[-76.198229,40.690305],"type":"Point"}
}