{
  "type": "Feature",
  "properties": {
    "addr:full":"3473 Main St Conestoga PA 17516",
    "addr:housenumber":"3473",
    "addr:postcode":"17516",
    "addr:street":"Main St",
    "iso:country":"US",
    "sg:address":"3473 Main St",
    "sg:city":"Conestoga",
    "sg:classifiers":[
        {
            "category":"Building & Trades",
            "subcategory":"Landscaping Services",
            "type":"Services"
        }
    ],
    "sg:phone":"+1 717 871 8424",
    "sg:postcode":"17516",
    "sg:province":"PA",
    "wof:name":"Next To Nature Landscaping",
    "wof:placetype":"venue"
},
  "geometry": {"coordinates":[-76.345916,39.940834],"type":"Point"}
}