{
  "type": "Feature",
  "properties": {
    "iso:country":"US",
    "sg:address":"1005 Old Montgomery Pike Rd",
    "sg:city":"Williamsport",
    "sg:classifiers":[
        {
            "category":"Freight",
            "type":"Transportation"
        }
    ],
    "sg:phone":"+1   ",
    "sg:postcode":"17702",
    "sg:province":"PA",
    "sg:tags":[
        "operator",
        "local",
        "trucking"
    ],
    "wof:name":"Millers Trucking Inc",
    "wof:placetype":"venue"
},
  "geometry": {"coordinates":[-76.947911,41.22885],"type":"Point"}
}