{
  "type": "Feature",
  "properties": {
    "iso:country":"US",
    "sg:address":"732 Red Lion Rd",
    "sg:city":"Philadelphia",
    "sg:classifiers":[
        {
            "category":"Retail",
            "subcategory":"Laundry & Dry Cleaning",
            "type":"Services"
        }
    ],
    "sg:phone":"+1 215 673 0961",
    "sg:postcode":"19115",
    "sg:province":"PA",
    "sg:tags":[
        "drycleaning",
        "plant"
    ],
    "wof:name":"Northeast Cleaners",
    "wof:placetype":"venue"
},
  "geometry": {"coordinates":[-75.033103,40.1051],"type":"Point"}
}