{
  "type": "Feature",
  "properties": {
    "addr:full":"216 Church Rd Milton PA 17815",
    "addr:housenumber":"216",
    "addr:postcode":"17815",
    "addr:street":"Church Rd",
    "iso:country":"US",
    "sg:address":"216 Church Rd",
    "sg:city":"Milton",
    "sg:classifiers":[
        {
            "category":"Building & Trades",
            "subcategory":"Construction",
            "type":"Services"
        }
    ],
    "sg:phone":"+1   ",
    "sg:postcode":"17815",
    "sg:province":"PA",
    "sg:tags":[
        "carpenter"
    ],
    "wof:name":"Rodney Yoder Carpentry Inc",
    "wof:placetype":"venue"
},
  "geometry": {"coordinates":[-76.375711,40.991246],"type":"Point"}
}