{
  "type": "Feature",
  "properties": {
    "iso:country":"US",
    "sg:address":"12 Kirby Ave",
    "sg:city":"Mountain Top",
    "sg:classifiers":[
        {
            "category":"Health Services",
            "subcategory":"Doctor",
            "type":"Services"
        }
    ],
    "sg:phone":"+1 570 474 5978",
    "sg:postcode":"18707",
    "sg:province":"PA",
    "sg:tags":[
        "physician",
        "surgeon"
    ],
    "wof:name":"Geisinger Health System",
    "wof:placetype":"venue"
},
  "geometry": {"coordinates":[-75.88389100000001,41.161028],"type":"Point"}
}