{
  "type": "Feature",
  "properties": {
    "addr:full":"2000 S Chadwick St Philadelphia PA 19145",
    "addr:housenumber":"2000",
    "addr:postcode":"19145",
    "addr:street":"S Chadwick St",
    "iso:country":"US",
    "sg:address":"2000 S Chadwick St",
    "sg:city":"Philadelphia",
    "sg:classifiers":[
        {
            "category":"Personal",
            "subcategory":"Barber",
            "type":"Services"
        }
    ],
    "sg:phone":"+1 215 462 2207",
    "sg:postcode":"19145",
    "sg:province":"PA",
    "wof:name":"Frank's Barber Shop",
    "wof:placetype":"venue"
},
  "geometry": {"coordinates":[-75.173963,39.924924],"type":"Point"}
}