{
  "type": "Feature",
  "properties": {
    "addr:full":"321 S Bellevue Ave Langhorne PA 19047",
    "addr:housenumber":"321",
    "addr:postcode":"19047",
    "addr:street":"S Bellevue Ave Langhorne Pa",
    "iso:country":"US",
    "sg:address":"321 S Bellevue Ave",
    "sg:city":"Langhorne",
    "sg:phone":"+1 215 478 6181",
    "sg:postcode":"19047",
    "sg:province":"PA",
    "sg:website":"http://www.bellatori.com",
    "wof:name":"Bella Tori At The Mansion",
    "wof:placetype":"venue"
},
  "geometry": {"coordinates":[-74.91863499999999,40.172562],"type":"Point"}
}