{
  "type": "Feature",
  "properties": {
    "iso:country":"US",
    "sg:address":"221 W Brady St",
    "sg:city":"Butler",
    "sg:classifiers":[
        {
            "category":"Health Services",
            "subcategory":"Hospital",
            "type":"Services"
        }
    ],
    "sg:phone":"+1 724 283 1704",
    "sg:postcode":"16001",
    "sg:province":"PA",
    "sg:tags":[
        "mental"
    ],
    "wof:name":"Grapevine Center",
    "wof:placetype":"venue"
},
  "geometry": {"coordinates":[-79.89634700000001,40.863387],"type":"Point"}
}