{
  "type": "Feature",
  "properties": {
    "iso:country":"US",
    "sg:address":"7 Glassworks Rd",
    "sg:city":"Greensboro",
    "sg:classifiers":[
        {
            "category":"Health Services",
            "subcategory":"Clinic",
            "type":"Services"
        }
    ],
    "sg:phone":"+1 724 943 3308",
    "sg:postcode":"15338",
    "sg:province":"PA",
    "sg:tags":[
        "specialty",
        "outpatient"
    ],
    "wof:name":"Cornerstone Care",
    "wof:placetype":"venue"
},
  "geometry": {"coordinates":[-79.914452,39.800945],"type":"Point"}
}