{
  "type": "Feature",
  "properties": {
    "iso:country":"US",
    "sg:address":"999 N Chester Rd",
    "sg:city":"West Chester",
    "sg:classifiers":[
        {
            "category":"Banks & Credit Unions",
            "subcategory":"Bank",
            "type":"Services"
        }
    ],
    "sg:phone":"+1 610 436 7766",
    "sg:postcode":"19380",
    "sg:province":"PA",
    "wof:name":"Wachovia Bank",
    "wof:placetype":"venue"
},
  "geometry": {"coordinates":[-75.546638,40.000291],"type":"Point"}
}