{
  "type": "Feature",
  "properties": {
    "addr:full":"1050 Scenery Dr Harrisburg PA 17109",
    "addr:housenumber":"1050",
    "addr:postcode":"17109",
    "addr:street":"Scenery Dr",
    "iso:country":"US",
    "sg:address":"1050 Scenery Dr",
    "sg:city":"Harrisburg",
    "sg:classifiers":[
        {
            "category":"Retail",
            "subcategory":"Self-service Laundry",
            "type":"Services"
        }
    ],
    "sg:phone":"+1 717 761 3251",
    "sg:postcode":"17109",
    "sg:province":"PA",
    "wof:name":"Morris Laundromation Svc Inc",
    "wof:placetype":"venue"
},
  "geometry": {"coordinates":[-76.812972,40.28076],"type":"Point"}
}