{
  "type": "Feature",
  "properties": {
    "addr:full":"1104 Carlisle Rd Camp Hill PA 17011",
    "addr:housenumber":"1104",
    "addr:postcode":"17011",
    "addr:street":"Carlisle Rd",
    "iso:country":"US",
    "sg:address":"1104 Carlisle Rd",
    "sg:city":"Camp Hill",
    "sg:classifiers":[
        {
            "category":"Travel",
            "subcategory":"Travel Agent",
            "type":"Entertainment"
        }
    ],
    "sg:phone":"+1 717 761 0827",
    "sg:postcode":"17011",
    "sg:province":"PA",
    "sg:tags":[
        "agency",
        "bureau"
    ],
    "wof:name":"East Mall Travel Service Inc",
    "wof:placetype":"venue"
},
  "geometry": {"coordinates":[-76.894423,40.230639],"type":"Point"}
}