{
  "type": "Feature",
  "properties": {
    "addr:full":"1177 Pittsburgh Rd Valencia PA 16059",
    "addr:housenumber":"1177",
    "addr:postcode":"16059",
    "addr:street":"Pittsburgh Rd",
    "iso:country":"US",
    "sg:address":"1177 Pittsburgh Rd",
    "sg:city":"Valencia",
    "sg:classifiers":[
        {
            "category":"Wholesale",
            "subcategory":"Hardware",
            "type":"Manufacturing & Wholesale Goods"
        }
    ],
    "sg:phone":"+1 724 898 1220",
    "sg:postcode":"16059",
    "sg:province":"PA",
    "sg:tags":[
        "control",
        "equipment",
        "air",
        "pollution"
    ],
    "wof:name":"Pinnacle Air Pollution Control",
    "wof:placetype":"venue"
},
  "geometry": {"coordinates":[-79.93433899999999,40.706579],"type":"Point"}
}