{
  "type": "Feature",
  "properties": {
    "iso:country":"US",
    "sg:address":"621 Dewalt Dr",
    "sg:city":"Pittsburgh",
    "sg:classifiers":[
        {
            "category":"Building & Trades",
            "subcategory":"Plumbing",
            "type":"Services"
        }
    ],
    "sg:phone":"+1   ",
    "sg:postcode":"15234",
    "sg:province":"PA",
    "sg:tags":[
        "contractor"
    ],
    "wof:name":"Ferris Plumbing & Heating",
    "wof:placetype":"venue"
},
  "geometry": {"coordinates":[-80.017837,40.376696],"type":"Point"}
}