{
  "type": "Feature",
  "properties": {
    "addr:full":"2060 E Wellington Rd Newtown PA 18940",
    "addr:housenumber":"2060",
    "addr:postcode":"18940",
    "addr:street":"E Wellington Rd",
    "iso:country":"US",
    "sg:address":"2060 E Wellington Rd",
    "sg:city":"Newtown",
    "sg:classifiers":[
        {
            "category":"Professional",
            "type":"Services"
        }
    ],
    "sg:phone":"+1   ",
    "sg:postcode":"18940",
    "sg:province":"PA",
    "wof:name":"Abington Open GP Inc",
    "wof:placetype":"venue"
},
  "geometry": {"coordinates":[-74.897964,40.24459],"type":"Point"}
}