{
  "type": "Feature",
  "properties": {
    "addr:full":"718 Logan Blvd Hollidaysburg PA 16648",
    "addr:housenumber":"718",
    "addr:postcode":"16648",
    "addr:street":"Logan Blvd",
    "iso:country":"US",
    "sg:address":"718 Logan Blvd",
    "sg:city":"Hollidaysburg",
    "sg:classifiers":[
        {
            "category":"Insurance",
            "subcategory":"Insurance Agent",
            "type":"Services"
        }
    ],
    "sg:phone":"+1   ",
    "sg:postcode":"16648",
    "sg:province":"PA",
    "wof:name":"Lisa M Mancinelli",
    "wof:placetype":"venue"
},
  "geometry": {"coordinates":[-78.393545,40.448423],"type":"Point"}
}