{
  "type": "Feature",
  "properties": {
    "addr:full":"1425 Jackson St Scranton PA 18504",
    "addr:housenumber":"1425",
    "addr:postcode":"18504",
    "addr:street":"Jackson St",
    "iso:country":"US",
    "sg:address":"1425 Jackson St",
    "sg:city":"Scranton",
    "sg:classifiers":[
        {
            "category":"Education",
            "subcategory":"School",
            "type":"Public Place"
        }
    ],
    "sg:phone":"+1 570 343 8114",
    "sg:postcode":"18504",
    "sg:province":"PA",
    "wof:name":"All Saints Academy",
    "wof:placetype":"venue"
},
  "geometry": {"coordinates":[-75.684349,41.414407],"type":"Point"}
}