{
  "type": "Feature",
  "properties": {
    "iso:country":"US",
    "sg:address":"106 Carpenter St",
    "sg:city":"Blossburg",
    "sg:classifiers":[
        {
            "category":"Building & Trades",
            "subcategory":"Construction",
            "type":"Services"
        }
    ],
    "sg:phone":"+1   ",
    "sg:postcode":"16912",
    "sg:province":"PA",
    "sg:tags":[
        "house"
    ],
    "wof:name":"Blossburg Improvement Assn",
    "wof:placetype":"venue"
},
  "geometry": {"coordinates":[-77.063007,41.680863],"type":"Point"}
}