{
  "type": "Feature",
  "properties": {
    "iso:country":"US",
    "sg:address":"1400 Saxonburg Blvd",
    "sg:city":"Glenshaw",
    "sg:classifiers":[
        {
            "category":"Bars & Pubs",
            "type":"Food & Drink"
        }
    ],
    "sg:phone":"+1   ",
    "sg:postcode":"15116",
    "sg:province":"PA",
    "sg:tags":[
        "drinking",
        "eating",
        "membership"
    ],
    "wof:name":"J DS Pub",
    "wof:placetype":"venue"
},
  "geometry": {"coordinates":[-79.918905,40.543976],"type":"Point"}
}