{
  "type": "Feature",
  "properties": {
    "iso:country":"US",
    "sg:address":"2202 26th St SW",
    "sg:city":"Allentown",
    "sg:classifiers":[
        {
            "category":"Professional",
            "subcategory":"Business Services",
            "type":"Services"
        }
    ],
    "sg:phone":"+1 610 798 0300",
    "sg:postcode":"18103",
    "sg:province":"PA",
    "sg:tags":[
        "delivery",
        "courier"
    ],
    "wof:name":"Eti Company",
    "wof:placetype":"venue"
},
  "geometry": {"coordinates":[-75.4786,40.567101],"type":"Point"}
}