{
  "type": "Feature",
  "properties": {
    "iso:country":"US",
    "sg:address":"317 Mertz Rd",
    "sg:city":"Fleetwood",
    "sg:classifiers":[
        {
            "category":"Farming",
            "subcategory":"Dairy Farm",
            "type":"Manufacturing & Wholesale Goods"
        }
    ],
    "sg:phone":"+1   ",
    "sg:postcode":"19522",
    "sg:province":"PA",
    "wof:name":"Larry L Mertz",
    "wof:placetype":"venue"
},
  "geometry": {"coordinates":[-75.784311,40.476906],"type":"Point"}
}