{
  "type": "Feature",
  "properties": {
    "iso:country":"US",
    "sg:address":"97 Ye Old Dam Rd",
    "sg:city":"Tamaqua",
    "sg:classifiers":[
        {
            "category":"Government",
            "subcategory":"Office",
            "type":"Public Place"
        }
    ],
    "sg:phone":"+1 570 668 1000",
    "sg:postcode":"18252",
    "sg:province":"PA",
    "sg:tags":[
        "village"
    ],
    "wof:name":"Tamaqua Borough Dam",
    "wof:placetype":"venue"
},
  "geometry": {"coordinates":[-75.997443,40.850156],"type":"Point"}
}