{
  "type": "Feature",
  "properties": {
    "iso:country":"US",
    "sg:address":"2948 Wilson School Ln",
    "sg:city":"Sinking Spring",
    "sg:classifiers":[
        {
            "category":"Professional",
            "type":"Services"
        }
    ],
    "sg:phone":"+1 610 670 8568",
    "sg:postcode":"19608",
    "sg:province":"PA",
    "sg:tags":[
        "establishment"
    ],
    "wof:name":"Bhullar Pirtpal",
    "wof:placetype":"venue"
},
  "geometry": {"coordinates":[-76.01199800000001,40.316544],"type":"Point"}
}