{
  "type": "Feature",
  "properties": {
    "iso:country":"US",
    "sg:address":"2008 Eden Park Blvd",
    "sg:city":"Mckeesport",
    "sg:classifiers":[
        {
            "category":"Shopping",
            "subcategory":"Florist",
            "type":"Retail Goods"
        },
        {
            "category":"Education",
            "subcategory":"Special Training",
            "type":"Public Place"
        }
    ],
    "sg:phone":"+1 412 673 9550",
    "sg:postcode":"15132",
    "sg:province":"PA",
    "wof:name":"Dorothy's Floral Designs",
    "wof:placetype":"venue"
},
  "geometry": {"coordinates":[-79.82856200000001,40.342298],"type":"Point"}
}