{
  "type": "Feature",
  "properties": {
    "addr:full":"Roberts Hollow Rd Monongahela PA 15063",
    "addr:postcode":"15063",
    "addr:street":"Roberts Hollow Rd",
    "iso:country":"US",
    "sg:address":"Roberts Hollow Rd",
    "sg:city":"Monongahela",
    "sg:classifiers":[
        {
            "category":"Shopping",
            "subcategory":"Pets & Pet Supplies",
            "type":"Retail Goods"
        },
        {
            "category":"Retail",
            "subcategory":"Pet Boarding",
            "type":"Services"
        }
    ],
    "sg:phone":"+1 412 384 6445",
    "sg:postcode":"15063",
    "sg:province":"PA",
    "sg:tags":[
        "training",
        "boarding/pet",
        "sitting"
    ],
    "wof:name":"Brizes Boarding Kennels",
    "wof:placetype":"venue"
},
  "geometry": {"coordinates":[-79.9226,40.2001],"type":"Point"}
}