{
  "type": "Feature",
  "properties": {
    "iso:country":"US",
    "sg:address":"121 Middle Creek Rd",
    "sg:city":"Lititz",
    "sg:classifiers":[
        {
            "category":"Farming",
            "subcategory":"Nursery",
            "type":"Manufacturing & Wholesale Goods"
        }
    ],
    "sg:phone":"+1 717 733 4647",
    "sg:postcode":"17543",
    "sg:province":"PA",
    "sg:tags":[
        "corn",
        "greenhouse"
    ],
    "wof:name":"Newswanger Floyd Greenhouse",
    "wof:placetype":"venue"
},
  "geometry": {"coordinates":[-76.23333,40.165655],"type":"Point"}
}