{
  "type": "Feature",
  "properties": {
    "addr:full":"800 Chestnut St Philadelphia PA 19107",
    "addr:housenumber":"800",
    "addr:postcode":"19107",
    "addr:street":"Chestnut St",
    "iso:country":"US",
    "sg:address":"800 Chestnut St",
    "sg:city":"Philadelphia",
    "sg:classifiers":[
        {
            "category":"Shopping",
            "subcategory":"Jewelry",
            "type":"Retail Goods"
        }
    ],
    "sg:phone":"+1 215 925 1090",
    "sg:postcode":"19107",
    "sg:province":"PA",
    "wof:name":"F & G Stock Unlimited Inc",
    "wof:placetype":"venue"
},
  "geometry": {"coordinates":[-75.15389999999999,39.949699],"type":"Point"}
}