{
  "type": "Feature",
  "properties": {
    "iso:country":"US",
    "sg:address":"1801 N 27th St",
    "sg:city":"Philadelphia",
    "sg:classifiers":[
        {
            "category":"Bars & Pubs",
            "type":"Food & Drink"
        }
    ],
    "sg:phone":"+1   ",
    "sg:postcode":"19121",
    "sg:province":"PA",
    "sg:tags":[
        "bar"
    ],
    "wof:name":"27th Street Cafe Inc",
    "wof:placetype":"venue"
},
  "geometry": {"coordinates":[-75.17819799999999,39.984413],"type":"Point"}
}