{
  "type": "Feature",
  "properties": {
    "iso:country":"US",
    "sg:address":"5159 Merilee Dr",
    "sg:city":"Erie",
    "sg:classifiers":[
        {
            "category":"Professional",
            "subcategory":"Advertising",
            "type":"Services"
        }
    ],
    "sg:phone":"+1 814 838 6505",
    "sg:postcode":"16506",
    "sg:province":"PA",
    "sg:tags":[
        "counselor"
    ],
    "wof:name":"Moree' Advertising",
    "wof:placetype":"venue"
},
  "geometry": {"coordinates":[-80.129002,42.064534],"type":"Point"}
}