{
  "type": "Feature",
  "properties": {
    "iso:country":"US",
    "sg:address":"132 N Reamstown Rd",
    "sg:city":"Stevens",
    "sg:classifiers":[
        {
            "category":"Professional",
            "subcategory":"Business Services",
            "type":"Services"
        }
    ],
    "sg:phone":"+1 717 336 7368",
    "sg:postcode":"17578",
    "sg:province":"PA",
    "wof:name":"G W Martin Trucking",
    "wof:placetype":"venue"
},
  "geometry": {"coordinates":[-76.115995,40.216529],"type":"Point"}
}