{
  "type": "Feature",
  "properties": {
    "iso:country":"US",
    "sg:address":"323 Wolf Creek Rd",
    "sg:city":"Bernville",
    "sg:classifiers":[
        {
            "category":"Building & Trades",
            "subcategory":"Construction",
            "type":"Services"
        }
    ],
    "sg:phone":"+1   ",
    "sg:postcode":"19506",
    "sg:province":"PA",
    "sg:tags":[
        "contractor"
    ],
    "wof:name":"G Miller & Sons Welding Inc",
    "wof:placetype":"venue"
},
  "geometry": {"coordinates":[-76.110986,40.492012],"type":"Point"}
}