{
  "type": "Feature",
  "properties": {
    "iso:country":"US",
    "sg:address":"1209 Chester Pike",
    "sg:city":"Crum Lynne",
    "sg:classifiers":[
        {
            "category":"Retail",
            "subcategory":"Auto Repair",
            "type":"Services"
        }
    ],
    "sg:phone":"+1 610 490 6914",
    "sg:postcode":"19022",
    "sg:province":"PA",
    "sg:tags":[
        "repairing",
        "automobile",
        "general"
    ],
    "wof:name":"Manera's Auto & Truck Repair",
    "wof:placetype":"venue"
},
  "geometry": {"coordinates":[-75.33599,39.869226],"type":"Point"}
}