{
  "type": "Feature",
  "properties": {
    "iso:country":"US",
    "sg:address":"1167 Freedom Rd",
    "sg:city":"Cranberry Twp",
    "sg:classifiers":[
        {
            "category":"Retail",
            "subcategory":"Laundry & Dry Cleaning",
            "type":"Services"
        }
    ],
    "sg:phone":"+1 724 778 8999",
    "sg:postcode":"16066",
    "sg:province":"PA",
    "sg:tags":[
        "cleaner",
        "plant",
        "drycleaning"
    ],
    "wof:name":"Dan Camp Cleaners",
    "wof:placetype":"venue"
},
  "geometry": {"coordinates":[-80.128304,40.681999],"type":"Point"}
}