{
  "type": "Feature",
  "properties": {
    "addr:full":"117 N Franklin St Titusville PA 16354",
    "addr:housenumber":"117",
    "addr:postcode":"16354",
    "addr:street":"N Franklin St",
    "iso:country":"US",
    "sg:address":"117 N Franklin St",
    "sg:city":"Titusville",
    "sg:classifiers":[
        {
            "category":"Banks & Credit Unions",
            "subcategory":"Investment Brokerage",
            "type":"Services"
        }
    ],
    "sg:phone":"+1 814 827 7441",
    "sg:postcode":"16354",
    "sg:province":"PA",
    "sg:tags":[
        "stock",
        "bond"
    ],
    "wof:name":"AIG Royal Alliance",
    "wof:placetype":"venue"
},
  "geometry": {"coordinates":[-79.67334099999999,41.627672],"type":"Point"}
}