{
  "type": "Feature",
  "properties": {
    "iso:country":"US",
    "sg:address":"2836 Horseshoe Pike",
    "sg:city":"Campbelltown",
    "sg:classifiers":[
        {
            "category":"Health Services",
            "subcategory":"Chiropractor",
            "type":"Services"
        }
    ],
    "sg:phone":"+1 717 838 5944",
    "sg:postcode":"17010",
    "sg:province":"PA",
    "wof:name":"Campbelltown Family Chiro",
    "wof:placetype":"venue"
},
  "geometry": {"coordinates":[-76.58525299999999,40.277317],"type":"Point"}
}