{
  "type": "Feature",
  "properties": {
    "addr:full":"95 Highland Ave Ste 210 Bethlehem PA 18017",
    "addr:housenumber":"95",
    "addr:postcode":"18017",
    "addr:street":"Highland Ave Ste 210",
    "iso:country":"US",
    "sg:address":"95 Highland Ave Ste 210",
    "sg:city":"Bethlehem",
    "sg:classifiers":[
        {
            "category":"Professional",
            "subcategory":"Employment Agencies",
            "type":"Services"
        }
    ],
    "sg:phone":"+1 610 866 9661",
    "sg:postcode":"18017",
    "sg:province":"PA",
    "sg:website":"kellyservices.com/Yp",
    "wof:name":"Kelly Services",
    "wof:placetype":"venue"
},
  "geometry": {"coordinates":[-75.384,40.6671],"type":"Point"}
}