{
  "type": "Feature",
  "properties": {
    "addr:full":"5430 Jonestown Rd Harrisburg PA 17112",
    "addr:housenumber":"5430",
    "addr:postcode":"17112",
    "addr:street":"Jonestown Rd",
    "iso:country":"US",
    "sg:address":"5430 Jonestown Rd",
    "sg:city":"Harrisburg",
    "sg:classifiers":[
        {
            "category":"Home & Garden",
            "subcategory":"Home Furnishings",
            "type":"Retail Goods"
        }
    ],
    "sg:phone":"+1 717 671 7130",
    "sg:postcode":"17112",
    "sg:province":"PA",
    "wof:name":"Sofa Selections",
    "wof:placetype":"venue"
},
  "geometry": {"coordinates":[-76.794211,40.317477],"type":"Point"}
}