{
  "type": "Feature",
  "properties": {
    "iso:country":"US",
    "sg:address":"15 Poma St",
    "sg:city":"Russellton",
    "sg:classifiers":[
        {
            "category":"Restaurant",
            "type":"Food & Drink"
        }
    ],
    "sg:phone":"+1 724 265 4699",
    "sg:postcode":"15076",
    "sg:province":"PA",
    "sg:tags":[
        "banquet",
        "rooms"
    ],
    "wof:name":"Transfiguration Church Hall",
    "wof:placetype":"venue"
},
  "geometry": {"coordinates":[-79.83568699999999,40.620512],"type":"Point"}
}