{
  "type": "Feature",
  "properties": {
    "iso:country":"US",
    "sg:address":"420 State Rte 22",
    "sg:city":"Delmont",
    "sg:classifiers":[
        {
            "category":"Autos & Motor Vehicles",
            "subcategory":"Auto Supplies",
            "type":"Retail Goods"
        }
    ],
    "sg:phone":"+1 724 468 5966",
    "sg:postcode":"15626",
    "sg:province":"PA",
    "wof:name":"Carquest Auto Parts",
    "wof:placetype":"venue"
},
  "geometry": {"coordinates":[-79.575011,40.398319],"type":"Point"}
}