{
  "type": "Feature",
  "properties": {
    "iso:country":"US",
    "sg:address":"748 Linden St",
    "sg:city":"Bethlehem",
    "sg:classifiers":[
        {
            "category":"Shopping",
            "subcategory":"Shoes",
            "type":"Retail Goods"
        }
    ],
    "sg:phone":"+1 610 865 3214",
    "sg:postcode":"18018",
    "sg:province":"PA",
    "sg:tags":[
        "boot"
    ],
    "wof:name":"Bootgirl",
    "wof:placetype":"venue"
},
  "geometry": {"coordinates":[-75.370374,40.624672],"type":"Point"}
}