{
  "type": "Feature",
  "properties": {
    "addr:full":"88 Houston Rd Lansdowne PA 19050",
    "addr:housenumber":"88",
    "addr:postcode":"19050",
    "addr:street":"Houston Rd",
    "iso:country":"US",
    "sg:address":"88 Houston Rd",
    "sg:city":"Lansdowne",
    "sg:classifiers":[
        {
            "category":"Banks & Credit Unions",
            "subcategory":"Bank",
            "type":"Services"
        }
    ],
    "sg:phone":"+1   ",
    "sg:postcode":"19050",
    "sg:province":"PA",
    "sg:tags":[
        "mortgage"
    ],
    "wof:name":"Victory Associates",
    "wof:placetype":"venue"
},
  "geometry": {"coordinates":[-75.266974,39.945721],"type":"Point"}
}