{
  "type": "Feature",
  "properties": {
    "iso:country":"US",
    "sg:address":"2340 Duncan St",
    "sg:city":"Philadelphia",
    "sg:classifiers":[
        {
            "category":"Bars & Pubs",
            "type":"Food & Drink"
        }
    ],
    "sg:phone":"+1 215 744 2850",
    "sg:postcode":"19124",
    "sg:province":"PA",
    "sg:tags":[
        "drinking"
    ],
    "wof:name":"Victor Stankiewicz",
    "wof:placetype":"venue"
},
  "geometry": {"coordinates":[-75.080693,40.006212],"type":"Point"}
}