{
  "type": "Feature",
  "properties": {
    "addr:full":"567 Church St Royersford PA 19468",
    "addr:housenumber":"567",
    "addr:postcode":"19468",
    "addr:street":"Church St",
    "iso:country":"US",
    "sg:address":"567 Church St",
    "sg:city":"Royersford",
    "sg:classifiers":[
        {
            "category":"Health Services",
            "subcategory":"Chiropractor",
            "type":"Services"
        },
        {
            "category":"Building & Trades",
            "subcategory":"Equipment Rental",
            "type":"Services"
        }
    ],
    "sg:phone":"+1 610 948 4161",
    "sg:postcode":"19468",
    "sg:province":"PA",
    "wof:name":"All Health Chiropractic Inc",
    "wof:placetype":"venue"
},
  "geometry": {"coordinates":[-75.53805199999999,40.187858],"type":"Point"}
}