{
  "type": "Feature",
  "properties": {
    "iso:country":"US",
    "sg:address":"1006 Pittston Ave",
    "sg:city":"Scranton",
    "sg:classifiers":[
        {
            "category":"Professional",
            "subcategory":"Lawyer & Legal Services",
            "type":"Services"
        }
    ],
    "sg:phone":"+1 570 348 0200",
    "sg:postcode":"18505",
    "sg:province":"PA",
    "sg:tags":[
        "attorney",
        "law",
        "business",
        "personal",
        "practice",
        "planning",
        "real estate",
        "injury",
        "criminal"
    ],
    "wof:name":"Abrahamsen Conaboy Abrahamsen, PC",
    "wof:placetype":"venue"
},
  "geometry": {"coordinates":[-75.668887,41.395807],"type":"Point"}
}