{
  "type": "Feature",
  "properties": {
    "iso:country":"US",
    "sg:address":"2537 N 5th St",
    "sg:city":"Harrisburg",
    "sg:classifiers":[
        {
            "category":"Education",
            "subcategory":"School",
            "type":"Public Place"
        }
    ],
    "sg:phone":"+1 717 255 2640",
    "sg:postcode":"17110",
    "sg:province":"PA",
    "wof:name":"Steele Elementary School",
    "wof:placetype":"venue"
},
  "geometry": {"coordinates":[-76.895869,40.286535],"type":"Point"}
}