{
  "type": "Feature",
  "properties": {
    "addr:full":"2902 Merwyn Ave Pittsburgh PA 15204",
    "addr:housenumber":"2902",
    "addr:postcode":"15204",
    "addr:street":"Merwyn Ave",
    "iso:country":"US",
    "sg:address":"2902 Merwyn Ave",
    "sg:city":"Pittsburgh",
    "sg:classifiers":[
        {
            "category":"Arts & Performance",
            "subcategory":"Theater",
            "type":"Entertainment"
        }
    ],
    "sg:phone":"+1 412 331 8368",
    "sg:postcode":"15204",
    "sg:province":"PA",
    "sg:tags":[
        "entertainer"
    ],
    "wof:name":"Ray Ryan Riverside Dance Band",
    "wof:placetype":"venue"
},
  "geometry": {"coordinates":[-80.05186500000001,40.457113],"type":"Point"}
}