{
  "type": "Feature",
  "properties": {
    "iso:country":"US",
    "sg:address":"455 Grant St",
    "sg:city":"Indiana",
    "sg:classifiers":[
        {
            "category":"Professional",
            "subcategory":"Computer Services",
            "type":"Services"
        }
    ],
    "sg:phone":"+1   ",
    "sg:postcode":"15701",
    "sg:province":"PA",
    "sg:tags":[
        "datum"
    ],
    "wof:name":"Hubert W Hamacher Inc",
    "wof:placetype":"venue"
},
  "geometry": {"coordinates":[-79.14688,40.615956],"type":"Point"}
}