{
  "type": "Feature",
  "properties": {
    "addr:full":"116 Cricket Ave Ardmore PA 19003",
    "addr:housenumber":"116",
    "addr:postcode":"19003",
    "addr:street":"Cricket Ave",
    "iso:country":"US",
    "sg:address":"116 Cricket Ave",
    "sg:city":"Ardmore",
    "sg:classifiers":[
        {
            "category":"Professional",
            "subcategory":"Management & Consulting",
            "type":"Services"
        }
    ],
    "sg:phone":"+1   ",
    "sg:postcode":"19003",
    "sg:province":"PA",
    "sg:tags":[
        "i",
        "via",
        "vitamin",
        "business"
    ],
    "wof:name":"Intermark Online Inc",
    "wof:placetype":"venue"
},
  "geometry": {"coordinates":[-75.296924,40.004895],"type":"Point"}
}