{
  "type": "Feature",
  "properties": {
    "iso:country":"US",
    "sg:address":"840 Drexel Ave",
    "sg:city":"Drexel Hill",
    "sg:classifiers":[
        {
            "category":"Shopping",
            "subcategory":"Shoes",
            "type":"Retail Goods"
        }
    ],
    "sg:phone":"+1   ",
    "sg:postcode":"19026",
    "sg:province":"PA",
    "wof:name":"Instep Shoes Inc",
    "wof:placetype":"venue"
},
  "geometry": {"coordinates":[-75.30919299999999,39.952541],"type":"Point"}
}