{
  "type": "Feature",
  "properties": {
    "iso:country":"US",
    "sg:address":"239 US Hwy 6",
    "sg:city":"Coudersport",
    "sg:classifiers":[
        {
            "category":"Professional",
            "subcategory":"Business Services",
            "type":"Services"
        }
    ],
    "sg:phone":"+1   ",
    "sg:postcode":"16915",
    "sg:province":"PA",
    "wof:name":"Potter County Visitors Assn",
    "wof:placetype":"venue"
},
  "geometry": {"coordinates":[-78.015709,41.774419],"type":"Point"}
}