{
  "type": "Feature",
  "properties": {
    "iso:country":"US",
    "sg:address":"2 W State St",
    "sg:city":"Quarryville",
    "sg:classifiers":[
        {
            "category":"Real Estate",
            "subcategory":"Real Estate Agent",
            "type":"Services"
        }
    ],
    "sg:phone":"+1   ",
    "sg:postcode":"17566",
    "sg:province":"PA",
    "sg:tags":[
        "broker"
    ],
    "wof:name":"Century 21",
    "wof:placetype":"venue"
},
  "geometry": {"coordinates":[-76.16354699999999,39.897179],"type":"Point"}
}