{
  "type": "Feature",
  "properties": {
    "iso:country":"US",
    "sg:address":"922 W Sunbury Rd",
    "sg:city":"West Sunbury",
    "sg:classifiers":[
        {
            "category":"Building & Trades",
            "subcategory":"Construction",
            "type":"Services"
        }
    ],
    "sg:phone":"+1 724 283 4579",
    "sg:postcode":"16061",
    "sg:province":"PA",
    "sg:tags":[
        "carpentry",
        "contractor"
    ],
    "wof:name":"Creative Cabinetry",
    "wof:placetype":"venue"
},
  "geometry": {"coordinates":[-79.900053,40.962589],"type":"Point"}
}