{
  "type": "Feature",
  "properties": {
    "addr:full":"33 E Philadelphia St York PA 17401",
    "addr:housenumber":"33 e",
    "addr:postcode":"17401",
    "addr:street":"Philadelphia St",
    "iso:country":"US",
    "sg:address":"33 E Philadelphia St",
    "sg:city":"York",
    "sg:classifiers":[
        {
            "category":"Professional",
            "subcategory":"Lawyer & Legal Services",
            "type":"Services"
        }
    ],
    "sg:phone":"+1 717 846 9773",
    "sg:postcode":"17401",
    "sg:province":"PA",
    "sg:tags":[
        "attorney"
    ],
    "wof:name":"Susan A Docktor",
    "wof:placetype":"venue"
},
  "geometry": {"coordinates":[-76.728476,39.963847],"type":"Point"}
}