{
  "type": "Feature",
  "properties": {
    "iso:country":"US",
    "sg:address":"1580 Sleepy Hollow Rd",
    "sg:city":"Quakertown",
    "sg:classifiers":[
        {
            "category":"Professional",
            "subcategory":"Research",
            "type":"Services"
        }
    ],
    "sg:phone":"+1 215 538 8101",
    "sg:postcode":"18951",
    "sg:province":"PA",
    "sg:tags":[
        "historical"
    ],
    "wof:name":"Milford Twp Historical Society",
    "wof:placetype":"venue"
},
  "geometry": {"coordinates":[-75.442853,40.432562],"type":"Point"}
}