{
  "type": "Feature",
  "properties": {
    "iso:country":"US",
    "sg:address":"357 Righters Mill Rd",
    "sg:city":"Ardmore",
    "sg:classifiers":[
        {
            "category":"Restaurant",
            "type":"Food & Drink"
        }
    ],
    "sg:phone":"+1 610 642 7120",
    "sg:postcode":"19072",
    "sg:province":"PA",
    "sg:tags":[
        "caterer"
    ],
    "sg:website":"www.delawaremarket.com",
    "wof:name":"Delaware Market House",
    "wof:placetype":"venue"
},
  "geometry": {"coordinates":[-75.264546,40.020903],"type":"Point"}
}