{
  "type": "Feature",
  "properties": {
    "addr:full":"240 New York Dr Fort Washington PA 19034",
    "addr:housenumber":"240",
    "addr:postcode":"19034",
    "addr:street":"New York Dr",
    "iso:country":"US",
    "sg:address":"240 New York Dr",
    "sg:city":"Fort Washington",
    "sg:classifiers":[
        {
            "category":"Education",
            "subcategory":"School",
            "type":"Public Place"
        }
    ],
    "sg:phone":"+1 215 654 9207",
    "sg:postcode":"19034",
    "sg:province":"PA",
    "wof:name":"Lakeside Educational Network",
    "wof:placetype":"venue"
},
  "geometry": {"coordinates":[-75.198908,40.13914],"type":"Point"}
}