{
  "type": "Feature",
  "properties": {
    "iso:country":"US",
    "sg:address":"303 Curtin St",
    "sg:city":"Osceola Mills",
    "sg:classifiers":[
        {
            "category":"Organizations",
            "subcategory":"Religious Organization",
            "type":"Services"
        }
    ],
    "sg:phone":"+1 814 339 6139",
    "sg:postcode":"16666",
    "sg:province":"PA",
    "sg:tags":[
        "church"
    ],
    "sg:website":"www.osceolamillsumc.org",
    "wof:name":"United Methodist Church",
    "wof:placetype":"venue"
},
  "geometry": {"coordinates":[-78.27011299999999,40.851995],"type":"Point"}
}