{
  "type": "Feature",
  "properties": {
    "iso:country":"US",
    "sg:address":"1062 Manheim Pike",
    "sg:city":"Lancaster",
    "sg:classifiers":[
        {
            "category":"Professional",
            "subcategory":"Research",
            "type":"Services"
        }
    ],
    "sg:phone":"+1 717 735 2043",
    "sg:postcode":"17601",
    "sg:province":"PA",
    "sg:tags":[
        "environmental",
        "ecological"
    ],
    "wof:name":"Neimety Inc",
    "wof:placetype":"venue"
},
  "geometry": {"coordinates":[-76.31316,40.057057],"type":"Point"}
}