{
  "type": "Feature",
  "properties": {
    "iso:country":"US",
    "sg:address":"10 S Morehall Rd",
    "sg:city":"Malvern",
    "sg:classifiers":[
        {
            "category":"Recreation",
            "type":"Entertainment"
        }
    ],
    "sg:phone":"+1 610 644 7772",
    "sg:postcode":"19355",
    "sg:province":"PA",
    "sg:tags":[
        "tennis",
        "court"
    ],
    "wof:name":"Great Valley Racquet Club",
    "wof:placetype":"venue"
},
  "geometry": {"coordinates":[-75.52331100000001,40.045908],"type":"Point"}
}