{
  "type": "Feature",
  "properties": {
    "addr:full":"2600 Perrysville Ave Pittsburgh PA 15214",
    "addr:housenumber":"2600",
    "addr:postcode":"15214",
    "addr:street":"Perrysville Ave",
    "iso:country":"US",
    "sg:address":"2600 Perrysville Ave",
    "sg:city":"Pittsburgh",
    "sg:classifiers":[
        {
            "category":"Home & Garden",
            "subcategory":"Building Materials",
            "type":"Retail Goods"
        }
    ],
    "sg:phone":"+1 412 231 2466",
    "sg:postcode":"15214",
    "sg:province":"PA",
    "sg:tags":[
        "plumbing",
        "fixture",
        "supply"
    ],
    "wof:name":"Franklin's Kitchen",
    "wof:placetype":"venue"
},
  "geometry": {"coordinates":[-80.008734,40.471384],"type":"Point"}
}