{
  "type": "Feature",
  "properties": {
    "iso:country":"US",
    "sg:address":"928 New Market St",
    "sg:city":"Philadelphia",
    "sg:classifiers":[
        {
            "category":"Building & Trades",
            "subcategory":"Construction",
            "type":"Services"
        }
    ],
    "sg:phone":"+1 215 627 0844",
    "sg:postcode":"19123",
    "sg:province":"PA",
    "sg:tags":[
        "work",
        "iron"
    ],
    "wof:name":"Ben's Iron Works",
    "wof:placetype":"venue"
},
  "geometry": {"coordinates":[-75.139212,39.963799],"type":"Point"}
}