{
  "type": "Feature",
  "properties": {
    "addr:full":"570 Rolling Meadows Rd Waynesburg PA 15370",
    "addr:housenumber":"570",
    "addr:postcode":"15370",
    "addr:street":"Rolling Meadows Rd",
    "iso:country":"US",
    "sg:address":"570 Rolling Meadows Rd",
    "sg:city":"Waynesburg",
    "sg:classifiers":[
        {
            "category":"Utilities",
            "subcategory":"Sewage",
            "type":"Services"
        }
    ],
    "sg:phone":"+1 724 627 9728",
    "sg:postcode":"15370",
    "sg:province":"PA",
    "sg:tags":[
        "disposal",
        "system"
    ],
    "wof:name":"Franklin Twp Sewer",
    "wof:placetype":"venue"
},
  "geometry": {"coordinates":[-80.14334100000001,39.889449],"type":"Point"}
}