{
  "type": "Feature",
  "properties": {
    "iso:country":"US",
    "sg:address":"669 Coleman Ave",
    "sg:city":"Johnstown",
    "sg:classifiers":[
        {
            "category":"Food & Beverages",
            "subcategory":"Groceries & Convenience Stores",
            "type":"Retail Goods"
        }
    ],
    "sg:phone":"+1   ",
    "sg:postcode":"15902",
    "sg:province":"PA",
    "wof:name":"Dnr Foodworld",
    "wof:placetype":"venue"
},
  "geometry": {"coordinates":[-78.91252900000001,40.2966],"type":"Point"}
}