{
  "type": "Feature",
  "properties": {
    "iso:country":"US",
    "sg:address":"120 W Tioga St",
    "sg:city":"Tunkhannock",
    "sg:classifiers":[
        {
            "category":"Education",
            "subcategory":"School",
            "type":"Public Place"
        }
    ],
    "sg:phone":"+1 570 836 8223",
    "sg:postcode":"18657",
    "sg:province":"PA",
    "sg:tags":[
        "high"
    ],
    "wof:name":"Tunkhannock High School",
    "wof:placetype":"venue"
},
  "geometry": {"coordinates":[-75.955872,41.541],"type":"Point"}
}