{
  "type": "Feature",
  "properties": {
    "iso:country":"US",
    "sg:address":"5000 Woodland Ave",
    "sg:city":"Philadelphia",
    "sg:classifiers":[
        {
            "category":"Health Services",
            "subcategory":"Doctor",
            "type":"Services"
        }
    ],
    "sg:phone":"+1 215 726 9807",
    "sg:postcode":"19143",
    "sg:province":"PA",
    "sg:tags":[
        "clinic"
    ],
    "wof:name":"Woodland Avenue Health Ctr",
    "wof:placetype":"venue"
},
  "geometry": {"coordinates":[-75.214536,39.939496],"type":"Point"}
}