{
  "type": "Feature",
  "properties": {
    "iso:country":"US",
    "sg:address":"228 1st St",
    "sg:city":"Aspinwall",
    "sg:classifiers":[
        {
            "category":"Personal",
            "subcategory":"Beauty Salon",
            "type":"Services"
        }
    ],
    "sg:phone":"+1 412 782 3232",
    "sg:postcode":"15215",
    "sg:province":"PA",
    "sg:tags":[
        "shop"
    ],
    "wof:name":"Lu Chic Hair Design",
    "wof:placetype":"venue"
},
  "geometry": {"coordinates":[-79.9037,40.490378],"type":"Point"}
}