{
  "type": "Feature",
  "properties": {
    "iso:country":"US",
    "sg:address":"18 Woodside Ln",
    "sg:city":"New Hope",
    "sg:classifiers":[
        {
            "category":"Professional",
            "type":"Services"
        }
    ],
    "sg:phone":"+1   ",
    "sg:postcode":"18938",
    "sg:province":"PA",
    "wof:name":"Russian Antiquity Inc",
    "wof:placetype":"venue"
},
  "geometry": {"coordinates":[-74.92821499999999,40.320609],"type":"Point"}
}