{
  "type": "Feature",
  "properties": {
    "addr:full":"150 Yorktown Plz  Elkins Park PA 19027",
    "addr:housenumber":"150",
    "addr:postcode":"19027",
    "addr:street":"Yorktown Plz",
    "iso:country":"US",
    "sg:address":"150 Yorktown Plz ",
    "sg:city":"Elkins Park",
    "sg:classifiers":[
        {
            "category":"Restaurant",
            "type":"Food & Drink"
        }
    ],
    "sg:menulink":"http://www.allmenus.com/pa/cheltenham/288289-max--davids-restaurant/menu/",
    "sg:phone":"+1 215 885 2400",
    "sg:postcode":"19027",
    "sg:province":"PA",
    "sg:tags":[
        "american"
    ],
    "wof:name":"Max & David's Restaurant",
    "wof:placetype":"venue"
},
  "geometry": {"coordinates":[-75.126665,40.07814],"type":"Point"}
}