{
  "type": "Feature",
  "properties": {
    "addr:full":"1104 Leslie St Sharon OH 16146",
    "addr:housenumber":"1104",
    "addr:postcode":"16146",
    "addr:street":"Leslie St",
    "iso:country":"US",
    "sg:address":"1104 Leslie St",
    "sg:city":"Sharon",
    "sg:classifiers":[
        {
            "category":"Professional",
            "type":"Services"
        }
    ],
    "sg:phone":"+1   ",
    "sg:postcode":"16146",
    "sg:province":"OH",
    "wof:name":"Chrobak",
    "wof:placetype":"venue"
},
  "geometry": {"coordinates":[-80.488479,41.226168],"type":"Point"}
}