{
  "type": "Feature",
  "properties": {
    "addr:full":"429 Greenridge Rd Glenmoore PA 19343",
    "addr:housenumber":"429",
    "addr:postcode":"19343",
    "addr:street":"Greenridge Rd",
    "iso:country":"US",
    "sg:address":"429 Greenridge Rd",
    "sg:city":"Glenmoore",
    "sg:classifiers":[
        {
            "category":"Education",
            "subcategory":"School",
            "type":"Public Place"
        }
    ],
    "sg:phone":"+1 610 458 5138",
    "sg:postcode":"19343",
    "sg:province":"PA",
    "sg:tags":[
        "k-",
        "private"
    ],
    "wof:name":"Upattina's School",
    "wof:placetype":"venue"
},
  "geometry": {"coordinates":[-75.72555199999999,40.100682],"type":"Point"}
}