{
  "type": "Feature",
  "properties": {
    "addr:full":"165 Monroe St Prospect PA 16052",
    "addr:housenumber":"165",
    "addr:postcode":"16052",
    "addr:street":"Monroe St",
    "iso:country":"US",
    "sg:address":"165 Monroe St",
    "sg:city":"Prospect",
    "sg:classifiers":[
        {
            "category":"Government",
            "subcategory":"Office",
            "type":"Public Place"
        }
    ],
    "sg:phone":"+1 724 865 2235",
    "sg:postcode":"16052",
    "sg:province":"PA",
    "sg:tags":[
        "village"
    ],
    "wof:name":"Prospect Burough Office",
    "wof:placetype":"venue"
},
  "geometry": {"coordinates":[-80.04257699999999,40.906702],"type":"Point"}
}