{
  "type": "Feature",
  "properties": {
    "addr:full":"162 Scott Ridge Rd Harmony PA 16037",
    "addr:housenumber":"162",
    "addr:postcode":"16037",
    "addr:street":"Scott Ridge Rd",
    "iso:country":"US",
    "sg:address":"162 Scott Ridge Rd",
    "sg:city":"Harmony",
    "sg:classifiers":[
        {
            "category":"Professional",
            "subcategory":"Management & Consulting",
            "type":"Services"
        }
    ],
    "sg:phone":"+1   ",
    "sg:postcode":"16037",
    "sg:province":"PA",
    "sg:tags":[
        "business"
    ],
    "wof:name":"Pds LLC",
    "wof:placetype":"venue"
},
  "geometry": {"coordinates":[-80.13299499999999,40.827864],"type":"Point"}
}