{
  "type": "Feature",
  "properties": {
    "iso:country":"US",
    "sg:address":"1 Lawtons Hill",
    "sg:city":"Pottsville",
    "sg:classifiers":[
        {
            "category":"Education",
            "subcategory":"School",
            "type":"Public Place"
        }
    ],
    "sg:phone":"+1 570 622 8110",
    "sg:postcode":"17901",
    "sg:province":"PA",
    "sg:website":"www.nativitybvm.net",
    "wof:name":"Nativity BVM High School",
    "wof:placetype":"venue"
},
  "geometry": {"coordinates":[-76.191486,40.690699],"type":"Point"}
}