{
  "type": "Feature",
  "properties": {
    "iso:country":"US",
    "sg:address":"301 Brushton Ave",
    "sg:city":"Pittsburgh",
    "sg:classifiers":[
        {
            "category":"Manufacturing",
            "subcategory":"Metals",
            "type":"Manufacturing & Wholesale Goods"
        }
    ],
    "sg:phone":"+1 412 244 6400",
    "sg:postcode":"15221",
    "sg:province":"PA",
    "sg:tags":[
        "windows",
        "mfg",
        "vinyl",
        "replacement"
    ],
    "sg:website":"www.thermalindustries.com",
    "wof:name":"Thermal Industries Inc",
    "wof:placetype":"venue"
},
  "geometry": {"coordinates":[-79.891679,40.449256],"type":"Point"}
}