{
  "type": "Feature",
  "properties": {
    "addr:full":"3718 E Newport Rd Intercourse PA 17529",
    "addr:housenumber":"3718",
    "addr:postcode":"17529",
    "addr:street":"E Newport Rd",
    "iso:country":"US",
    "sg:address":"3718 E Newport Rd",
    "sg:city":"Intercourse",
    "sg:classifiers":[
        {
            "category":"Restaurant",
            "type":"Food & Drink"
        }
    ],
    "sg:phone":"+1   ",
    "sg:postcode":"17529",
    "sg:province":"PA",
    "sg:tags":[
        "drinking",
        "eating"
    ],
    "wof:name":"Stoltzfus Farm Restaurant",
    "wof:placetype":"venue"
},
  "geometry": {"coordinates":[-76.099585,40.036183],"type":"Point"}
}