{
  "type": "Feature",
  "properties": {
    "iso:country":"US",
    "sg:address":"3017 W Oxford St",
    "sg:city":"Philadelphia",
    "sg:classifiers":[
        {
            "category":"Real Estate",
            "subcategory":"Real Estate Agent",
            "type":"Services"
        }
    ],
    "sg:phone":"+1 215 236 0800",
    "sg:postcode":"19121",
    "sg:province":"PA",
    "sg:tags":[
        "management",
        "property"
    ],
    "wof:name":"Sartain Apartments Rental Ofc",
    "wof:placetype":"venue"
},
  "geometry": {"coordinates":[-75.18440200000001,39.980701],"type":"Point"}
}