{
  "type": "Feature",
  "properties": {
    "addr:full":"10 Quarry Rd Downingtown PA 19335",
    "addr:housenumber":"10",
    "addr:postcode":"19335",
    "addr:street":"Quarry Rd",
    "iso:country":"US",
    "sg:address":"10 Quarry Rd",
    "sg:city":"Downingtown",
    "sg:classifiers":[
        {
            "category":"Home & Garden",
            "subcategory":"Home Furnishings",
            "type":"Retail Goods"
        }
    ],
    "sg:phone":"+1   ",
    "sg:postcode":"19335",
    "sg:province":"PA",
    "wof:name":"Linens n Things",
    "wof:placetype":"venue"
},
  "geometry": {"coordinates":[-75.67376400000001,40.016675],"type":"Point"}
}