{
  "type": "Feature",
  "properties": {
    "iso:country":"US",
    "sg:address":"117 Storrs St",
    "sg:city":"Taylor",
    "sg:classifiers":[
        {
            "category":"Retail",
            "subcategory":"Repair Shop",
            "type":"Services"
        }
    ],
    "sg:phone":"+1   ",
    "sg:postcode":"18517",
    "sg:province":"PA",
    "sg:tags":[
        "fuel",
        "refrigeration",
        "dealer"
    ],
    "wof:name":"Summit Ridge",
    "wof:placetype":"venue"
},
  "geometry": {"coordinates":[-75.71550000000001,41.385076],"type":"Point"}
}