{
  "type": "Feature",
  "properties": {
    "iso:country":"US",
    "sg:address":"196 Anselm Dr",
    "sg:city":"Richboro",
    "sg:classifiers":[
        {
            "category":"Professional",
            "subcategory":"Computer Services",
            "type":"Services"
        }
    ],
    "sg:phone":"+1 215 942 2030",
    "sg:postcode":"18954",
    "sg:province":"PA",
    "sg:tags":[
        "consultant",
        "designer"
    ],
    "wof:name":"Quality Software Solutions",
    "wof:placetype":"venue"
},
  "geometry": {"coordinates":[-75.00776999999999,40.233783],"type":"Point"}
}