{
  "type": "Feature",
  "properties": {
    "iso:country":"US",
    "sg:address":"44 W Main St",
    "sg:city":"Waynesboro",
    "sg:classifiers":[
        {
            "category":"Shopping",
            "subcategory":"Crafts & Fabrics",
            "type":"Retail Goods"
        },
        {
            "category":"Building & Trades",
            "subcategory":"Construction",
            "type":"Services"
        }
    ],
    "sg:phone":"+1 717 765 8888",
    "sg:postcode":"17268",
    "sg:province":"PA",
    "sg:tags":[
        "interior",
        "design",
        "store"
    ],
    "wof:name":"Castle Fabrics and Home Decor",
    "wof:placetype":"venue"
},
  "geometry": {"coordinates":[-77.579962,39.7568],"type":"Point"}
}