{
  "type": "Feature",
  "properties": {
    "iso:country":"US",
    "sg:address":"5552 Bartlett St",
    "sg:city":"Pittsburgh",
    "sg:classifiers":[
        {
            "category":"Food & Beverages",
            "subcategory":"Groceries & Convenience Stores",
            "type":"Retail Goods"
        }
    ],
    "sg:phone":"+1   ",
    "sg:postcode":"15217",
    "sg:province":"PA",
    "wof:name":"Blumenfeld Specialty Food",
    "wof:placetype":"venue"
},
  "geometry": {"coordinates":[-79.929001,40.435491],"type":"Point"}
}