{
  "type": "Feature",
  "properties": {
    "addr:full":"232 Johnson Dr Fairless Hills PA 19030",
    "addr:housenumber":"232",
    "addr:postcode":"19030",
    "addr:street":"Johnson Dr",
    "iso:country":"US",
    "sg:address":"232 Johnson Dr",
    "sg:city":"Fairless Hills",
    "sg:classifiers":[
        {
            "category":"Building & Trades",
            "subcategory":"Landscaping Services",
            "type":"Services"
        }
    ],
    "sg:phone":"+1 215 946 3444",
    "sg:postcode":"19030",
    "sg:province":"PA",
    "sg:tags":[
        "lawn",
        "maintenance",
        "grounds"
    ],
    "wof:name":"Matts Mowing & More",
    "wof:placetype":"venue"
},
  "geometry": {"coordinates":[-74.84900399999999,40.184112],"type":"Point"}
}