{
  "type": "Feature",
  "properties": {
    "addr:full":"1813 West St Homestead PA 15120",
    "addr:housenumber":"1813",
    "addr:postcode":"15120",
    "addr:street":"West St",
    "iso:country":"US",
    "sg:address":"1813 West St",
    "sg:city":"Homestead",
    "sg:classifiers":[
        {
            "category":"Health Services",
            "subcategory":"Doctor",
            "type":"Services"
        }
    ],
    "sg:phone":"+1   ",
    "sg:postcode":"15120",
    "sg:province":"PA",
    "sg:tags":[
        "medical"
    ],
    "wof:name":"Edward Tirpak DDS PC",
    "wof:placetype":"venue"
},
  "geometry": {"coordinates":[-79.904439,40.399437],"type":"Point"}
}