{
  "type": "Feature",
  "properties": {
    "iso:country":"US",
    "sg:address":"1251 Lodi Hill Rd",
    "sg:city":"Upper Black Eddy",
    "sg:classifiers":[
        {
            "category":"Food & Beverages",
            "subcategory":"Groceries & Convenience Stores",
            "type":"Retail Goods"
        }
    ],
    "sg:phone":"+1   ",
    "sg:postcode":"18972",
    "sg:province":"PA",
    "wof:name":"Deli On The Spot Inc",
    "wof:placetype":"venue"
},
  "geometry": {"coordinates":[-75.111231,40.540033],"type":"Point"}
}