{
  "type": "Feature",
  "properties": {
    "iso:country":"US",
    "sg:address":"4903 Buckboard Ln",
    "sg:city":"Pipersville",
    "sg:classifiers":[
        {
            "category":"Manufacturing",
            "subcategory":"Apparel",
            "type":"Manufacturing & Wholesale Goods"
        }
    ],
    "sg:phone":"+1   ",
    "sg:postcode":"18947",
    "sg:province":"PA",
    "wof:name":"Art of Embroidery",
    "wof:placetype":"venue"
},
  "geometry": {"coordinates":[-75.15206000000001,40.385258],"type":"Point"}
}