{
  "type": "Feature",
  "properties": {
    "addr:full":"1408 Market St Harrisburg PA 17103",
    "addr:housenumber":"1408",
    "addr:postcode":"17103",
    "addr:street":"Market St",
    "iso:country":"US",
    "sg:address":"1408 Market St",
    "sg:city":"Harrisburg",
    "sg:classifiers":[
        {
            "category":"Shopping",
            "subcategory":"Discount & Variety Stores",
            "type":"Retail Goods"
        }
    ],
    "sg:phone":"+1 717 233 1970",
    "sg:postcode":"17103",
    "sg:province":"PA",
    "wof:name":"Variety Goods",
    "wof:placetype":"venue"
},
  "geometry": {"coordinates":[-76.867097,40.266717],"type":"Point"}
}