{
  "type": "Feature",
  "properties": {
    "iso:country":"US",
    "sg:address":"101 S 2nd St",
    "sg:city":"Clearfield",
    "sg:classifiers":[
        {
            "category":"Professional",
            "subcategory":"Lawyer & Legal Services",
            "type":"Services"
        }
    ],
    "sg:phone":"+1 814 765 2611",
    "sg:postcode":"16830",
    "sg:province":"PA",
    "sg:tags":[
        "planning",
        "plan",
        "estate"
    ],
    "wof:name":"John A Ayres",
    "wof:placetype":"venue"
},
  "geometry": {"coordinates":[-78.438042,41.020908],"type":"Point"}
}