{
  "type": "Feature",
  "properties": {
    "iso:country":"US",
    "sg:address":"2522 State Rte 29",
    "sg:city":"Tunkhannock",
    "sg:classifiers":[
        {
            "category":"Health Services",
            "subcategory":"Chiropractor",
            "type":"Services"
        }
    ],
    "sg:phone":"+1 570 298 2635",
    "sg:postcode":"18657",
    "sg:province":"PA",
    "wof:name":"Family Chiropractic Clinic",
    "wof:placetype":"venue"
},
  "geometry": {"coordinates":[-76.03192300000001,41.451224],"type":"Point"}
}