{
  "type": "Feature",
  "properties": {
    "iso:country":"US",
    "sg:address":"408 E Main St",
    "sg:city":"Roaring Spring",
    "sg:classifiers":[
        {
            "category":"Manufacturing",
            "subcategory":"Tools & Machinery",
            "type":"Manufacturing & Wholesale Goods"
        }
    ],
    "sg:phone":"+1 814 224 5173",
    "sg:postcode":"16673",
    "sg:province":"PA",
    "sg:tags":[
        "shop",
        "industrial",
        "mfg",
        "die",
        "grinding",
        "machine",
        "knife"
    ],
    "wof:name":"Spring Tool & Die Co Inc",
    "wof:placetype":"venue"
},
  "geometry": {"coordinates":[-78.40176700000001,40.335463],"type":"Point"}
}