{
  "type": "Feature",
  "properties": {
    "iso:country":"US",
    "sg:address":"1815 Schadt Ave",
    "sg:city":"Whitehall",
    "sg:classifiers":[
        {
            "category":"Professional",
            "subcategory":"Lawyer & Legal Services",
            "type":"Services"
        }
    ],
    "sg:phone":"+1 610 439 3881",
    "sg:postcode":"18052",
    "sg:province":"PA",
    "wof:name":"Gormley John C Atty",
    "wof:placetype":"venue"
},
  "geometry": {"coordinates":[-75.493607,40.640963],"type":"Point"}
}