{
  "type": "Feature",
  "properties": {
    "iso:country":"US",
    "sg:address":"2301 Penrose Ave",
    "sg:city":"Philadelphia",
    "sg:classifiers":[
        {
            "category":"Bars & Pubs",
            "type":"Food & Drink"
        }
    ],
    "sg:phone":"+1 215 271 1441",
    "sg:postcode":"19145",
    "sg:province":"PA",
    "wof:name":"PAR Four",
    "wof:placetype":"venue"
},
  "geometry": {"coordinates":[-75.191276,39.906931],"type":"Point"}
}