{
  "type": "Feature",
  "properties": {
    "addr:full":"545 Lamour St York PA 17403",
    "addr:housenumber":"545",
    "addr:postcode":"17403",
    "addr:street":"Lamour St",
    "iso:country":"US",
    "sg:address":"545 Lamour St",
    "sg:city":"York",
    "sg:classifiers":[
        {
            "category":"Retail",
            "subcategory":"Car Wash",
            "type":"Services"
        }
    ],
    "sg:phone":"+1   ",
    "sg:postcode":"17403",
    "sg:province":"PA",
    "sg:tags":[
        "carwash"
    ],
    "wof:name":"Brooks Family Car Wash",
    "wof:placetype":"venue"
},
  "geometry": {"coordinates":[-76.71532999999999,39.960375],"type":"Point"}
}