{
  "type": "Feature",
  "properties": {
    "iso:country":"US",
    "sg:address":"301 5th Ave",
    "sg:city":"Mckeesport",
    "sg:classifiers":[
        {
            "category":"Banks & Credit Unions",
            "subcategory":"Bank",
            "type":"Services"
        }
    ],
    "sg:phone":"+1 412 675 5060",
    "sg:postcode":"15132",
    "sg:province":"PA",
    "wof:name":"City Of Mckeesport Emp FCU",
    "wof:placetype":"venue"
},
  "geometry": {"coordinates":[-79.864271,40.351071],"type":"Point"}
}