{
  "type": "Feature",
  "properties": {
    "iso:country":"US",
    "sg:address":"750 Washington Rd",
    "sg:city":"Pittsburgh",
    "sg:classifiers":[
        {
            "category":"Health Services",
            "subcategory":"Doctor",
            "type":"Services"
        }
    ],
    "sg:phone":"+1 412 563 7224",
    "sg:postcode":"15228",
    "sg:province":"PA",
    "sg:tags":[
        "dentist"
    ],
    "wof:name":"H Ivan Shnorkian DMD",
    "wof:placetype":"venue"
},
  "geometry": {"coordinates":[-80.046212,40.377993],"type":"Point"}
}