{
  "type": "Feature",
  "properties": {
    "iso:country":"US",
    "sg:address":"428 Blvd of the Allies",
    "sg:city":"Pittsburgh",
    "sg:classifiers":[
        {
            "category":"Professional",
            "subcategory":"Lawyer & Legal Services",
            "type":"Services"
        }
    ],
    "sg:phone":"+1 412 471 0677",
    "sg:postcode":"15219",
    "sg:province":"PA",
    "wof:name":"Gatewood Carol Jean Atty",
    "wof:placetype":"venue"
},
  "geometry": {"coordinates":[-79.999287,40.437327],"type":"Point"}
}