{
  "type": "Feature",
  "properties": {
    "iso:country":"US",
    "sg:address":"1415 Radcliffe St",
    "sg:city":"Bristol",
    "sg:classifiers":[
        {
            "category":"Manufacturing",
            "subcategory":"Signs",
            "type":"Manufacturing & Wholesale Goods"
        }
    ],
    "sg:phone":"+1 215 785 6231",
    "sg:postcode":"19007",
    "sg:province":"PA",
    "wof:name":"Atomic Graphics",
    "wof:placetype":"venue"
},
  "geometry": {"coordinates":[-74.84192,40.103865],"type":"Point"}
}