{
  "type": "Feature",
  "properties": {
    "addr:full":"5050 Jonestown Rd Harrisburg PA 17112",
    "addr:housenumber":"5050",
    "addr:postcode":"17112",
    "addr:street":"Jonestown Rd",
    "iso:country":"US",
    "sg:address":"5050 Jonestown Rd",
    "sg:city":"Harrisburg",
    "sg:classifiers":[
        {
            "category":"Retail",
            "subcategory":"Portrait Studio",
            "type":"Services"
        }
    ],
    "sg:phone":"+1   ",
    "sg:postcode":"17112",
    "sg:province":"PA",
    "wof:name":"Olan Mills Studios",
    "wof:placetype":"venue"
},
  "geometry": {"coordinates":[-76.804799,40.307371],"type":"Point"}
}