{
  "type": "Feature",
  "properties": {
    "iso:country":"US",
    "sg:address":"902 S 10th St",
    "sg:city":"Allentown",
    "sg:classifiers":[
        {
            "category":"Retail",
            "subcategory":"Laundry & Dry Cleaning",
            "type":"Services"
        }
    ],
    "sg:phone":"+1 610 435 9934",
    "sg:postcode":"18103",
    "sg:province":"PA",
    "sg:tags":[
        "cleaner"
    ],
    "wof:name":"Liberty Dry Cleaners",
    "wof:placetype":"venue"
},
  "geometry": {"coordinates":[-75.474503,40.5905],"type":"Point"}
}