{
  "type": "Feature",
  "properties": {
    "addr:full":"801 10th Ave Altoona PA 16601",
    "addr:housenumber":"801",
    "addr:postcode":"16601",
    "addr:street":"10Th Ave",
    "iso:country":"US",
    "sg:address":"801 10th Ave",
    "sg:city":"Altoona",
    "sg:classifiers":[
        {
            "category":"Banks & Credit Unions",
            "subcategory":"Bank",
            "type":"Services"
        }
    ],
    "sg:phone":"+1   ",
    "sg:postcode":"16601",
    "sg:province":"PA",
    "sg:tags":[
        "state"
    ],
    "wof:name":"Blair County Federal Credit Un",
    "wof:placetype":"venue"
},
  "geometry": {"coordinates":[-78.39668,40.518174],"type":"Point"}
}