{
  "type": "Feature",
  "properties": {
    "iso:country":"US",
    "sg:address":"43 W Mine St",
    "sg:city":"Hazleton",
    "sg:classifiers":[
        {
            "category":"Wholesale",
            "subcategory":"Drugs",
            "type":"Manufacturing & Wholesale Goods"
        }
    ],
    "sg:phone":"+1   ",
    "sg:postcode":"18201",
    "sg:province":"PA",
    "sg:tags":[
        "pharmaceutical"
    ],
    "wof:name":"Pharmahouse Inc",
    "wof:placetype":"venue"
},
  "geometry": {"coordinates":[-75.975189,40.953765],"type":"Point"}
}