{
  "type": "Feature",
  "properties": {
    "iso:country":"US",
    "sg:address":"1859 Beans Cove Rd",
    "sg:city":"Clearville",
    "sg:phone":"+1   ",
    "sg:postcode":"15535",
    "sg:province":"PA",
    "sg:tags":[
        "farm",
        "field",
        "crop"
    ],
    "wof:name":"Jay Tarleton",
    "wof:placetype":"venue"
},
  "geometry": {"coordinates":[-78.594491,39.787018],"type":"Point"}
}