{
  "type": "Feature",
  "properties": {
    "iso:country":"US",
    "sg:address":"100 N State St",
    "sg:city":"Ephrata",
    "sg:classifiers":[
        {
            "category":"Home & Garden",
            "subcategory":"Building Materials",
            "type":"Retail Goods"
        }
    ],
    "sg:phone":"+1 717 738 9598",
    "sg:postcode":"17522",
    "sg:province":"PA",
    "sg:tags":[
        "glass",
        "window",
        "plate"
    ],
    "wof:name":"Glass Accents Etc",
    "wof:placetype":"venue"
},
  "geometry": {"coordinates":[-76.17549,40.179652],"type":"Point"}
}