{
  "type": "Feature",
  "properties": {
    "addr:full":"35 Camp Rd Gettysburg PA 17327",
    "addr:housenumber":"35",
    "addr:postcode":"17327",
    "addr:street":"Camp Rd",
    "iso:country":"US",
    "sg:address":"35 Camp Rd",
    "sg:city":"Gettysburg",
    "sg:classifiers":[
        {
            "category":"Personal",
            "subcategory":"Beauty Salon",
            "type":"Services"
        }
    ],
    "sg:phone":"+1 717 334 9923",
    "sg:postcode":"17327",
    "sg:province":"PA",
    "sg:tags":[
        "manicuring"
    ],
    "wof:name":"Hollywood Nails",
    "wof:placetype":"venue"
},
  "geometry": {"coordinates":[-76.724598,39.794019],"type":"Point"}
}