{
  "type": "Feature",
  "properties": {
    "addr:full":"623 Howertown Rd Catasauqua PA 18032",
    "addr:housenumber":"623",
    "addr:postcode":"18032",
    "addr:street":"Howertown Rd",
    "iso:country":"US",
    "sg:address":"623 Howertown Rd",
    "sg:city":"Catasauqua",
    "sg:classifiers":[
        {
            "category":"Arts & Performance",
            "subcategory":"Arts Center",
            "type":"Entertainment"
        },
        {
            "category":"Personal",
            "type":"Services"
        }
    ],
    "sg:phone":"+1 610 264 4115",
    "sg:postcode":"18032",
    "sg:province":"PA",
    "sg:tags":[
        "performing",
        "towing"
    ],
    "wof:name":"Kroope Brian J Home Improvements",
    "wof:placetype":"venue"
},
  "geometry": {"coordinates":[-75.471298,40.6591],"type":"Point"}
}