{
  "type": "Feature",
  "properties": {
    "iso:country":"US",
    "sg:address":"1909 E Keats St",
    "sg:city":"Allentown",
    "sg:classifiers":[
        {
            "category":"Building & Trades",
            "subcategory":"Plumbing",
            "type":"Services"
        }
    ],
    "sg:phone":"+1 610 433 0366",
    "sg:postcode":"18109",
    "sg:province":"PA",
    "sg:tags":[
        "contractor"
    ],
    "wof:name":"Raudabaugh Plumbing & Heating",
    "wof:placetype":"venue"
},
  "geometry": {"coordinates":[-75.426422,40.62614],"type":"Point"}
}