{
  "type": "Feature",
  "properties": {
    "iso:country":"US",
    "sg:address":"39 Olde Mill Ct",
    "sg:city":"Lititz",
    "sg:classifiers":[
        {
            "category":"Travel",
            "subcategory":"Travel Agent",
            "type":"Entertainment"
        }
    ],
    "sg:phone":"+1   ",
    "sg:postcode":"17543",
    "sg:province":"PA",
    "sg:tags":[
        "agency"
    ],
    "wof:name":"Cruiseone",
    "wof:placetype":"venue"
},
  "geometry": {"coordinates":[-76.31853,40.10961],"type":"Point"}
}