{
  "type": "Feature",
  "properties": {
    "iso:country":"US",
    "sg:address":"100 Park Ave",
    "sg:city":"Carmichaels",
    "sg:classifiers":[
        {
            "category":"Government",
            "subcategory":"Court House",
            "type":"Public Place"
        }
    ],
    "sg:phone":"+1   ",
    "sg:postcode":"15320",
    "sg:province":"PA",
    "wof:name":"Judicary Crts of The Commwl PA",
    "wof:placetype":"venue"
},
  "geometry": {"coordinates":[-79.96699099999999,39.880369],"type":"Point"}
}