{
  "type": "Feature",
  "properties": {
    "iso:country":"US",
    "sg:address":"239 Market St",
    "sg:city":"Lewisburg",
    "sg:classifiers":[
        {
            "category":"Banks & Credit Unions",
            "subcategory":"Bank",
            "type":"Services"
        }
    ],
    "sg:phone":"+1 570 000 1111",
    "sg:postcode":"17837",
    "sg:province":"PA",
    "wof:name":"Sovereign Bank",
    "wof:placetype":"venue"
},
  "geometry": {"coordinates":[-76.88394599999999,40.964741],"type":"Point"}
}