{
  "type": "Feature",
  "properties": {
    "iso:country":"US",
    "sg:address":"100 Grant St",
    "sg:city":"Butler",
    "sg:classifiers":[
        {
            "category":"Retail",
            "subcategory":"Auto Repair",
            "type":"Services"
        }
    ],
    "sg:phone":"+1 724 285 9908",
    "sg:postcode":"16001",
    "sg:province":"PA",
    "sg:tags":[
        "repairing",
        "automobile"
    ],
    "wof:name":"Mc Cune Garage",
    "wof:placetype":"venue"
},
  "geometry": {"coordinates":[-79.885707,40.856365],"type":"Point"}
}