{
  "type": "Feature",
  "properties": {
    "addr:full":"115 Tennis Ave Glenside PA 19038",
    "addr:housenumber":"115",
    "addr:postcode":"19038",
    "addr:street":"Tennis Ave",
    "iso:country":"US",
    "sg:address":"115 Tennis Ave",
    "sg:city":"Glenside",
    "sg:classifiers":[
        {
            "category":"Shopping",
            "subcategory":"Gifts & Souvenirs",
            "type":"Retail Goods"
        }
    ],
    "sg:phone":"+1 215 884 4477",
    "sg:postcode":"19038",
    "sg:province":"PA",
    "sg:tags":[
        "party",
        "supply"
    ],
    "wof:name":"Great American Party Store",
    "wof:placetype":"venue"
},
  "geometry": {"coordinates":[-75.166443,40.114614],"type":"Point"}
}