{
  "type": "Feature",
  "properties": {
    "iso:country":"US",
    "sg:address":"808 Overland Ave",
    "sg:city":"Duquesne",
    "sg:classifiers":[
        {
            "category":"Building & Trades",
            "subcategory":"Construction",
            "type":"Services"
        }
    ],
    "sg:phone":"+1   ",
    "sg:postcode":"15110",
    "sg:province":"PA",
    "sg:tags":[
        "contractor"
    ],
    "wof:name":"Welschs Extrior Clg Hm Rnvtion",
    "wof:placetype":"venue"
},
  "geometry": {"coordinates":[-79.859604,40.381542],"type":"Point"}
}