{
  "type": "Feature",
  "properties": {
    "addr:full":"12069 Lay Rd Edinboro PA 16412",
    "addr:postcode":"12069;16412",
    "addr:street":"Lay Rd",
    "iso:country":"US",
    "sg:address":"12069 Lay Rd",
    "sg:city":"Edinboro",
    "sg:classifiers":[
        {
            "category":"Wholesale",
            "subcategory":"Sporting Goods",
            "type":"Manufacturing & Wholesale Goods"
        }
    ],
    "sg:phone":"+1 814 734 1959",
    "sg:postcode":"16412",
    "sg:province":"PA",
    "wof:name":"Protective Sports Equipment",
    "wof:placetype":"venue"
},
  "geometry": {"coordinates":[-80.14889700000001,41.899296],"type":"Point"}
}