{
  "type": "Feature",
  "properties": {
    "iso:country":"US",
    "sg:address":"240 S West End Blvd Ste 6",
    "sg:city":"Quakertown",
    "sg:classifiers":[
        {
            "category":"Professional",
            "type":"Services"
        },
        {
            "category":"Restaurant",
            "type":"Food & Drink"
        },
        {
            "category":"Fast Food",
            "type":"Food & Drink"
        }
    ],
    "sg:phone":"+1 215 538 0900",
    "sg:postcode":"18951",
    "sg:province":"PA",
    "sg:tags":[
        "delivery",
        "take",
        "pizza"
    ],
    "sg:website":"http://www.dominospizza.com",
    "wof:name":"Domino's Pizza",
    "wof:placetype":"venue"
},
  "geometry": {"coordinates":[-75.35415,40.436754],"type":"Point"}
}