{
  "type": "Feature",
  "properties": {
    "addr:full":"865 40th St Altoona PA 16601",
    "addr:housenumber":"865",
    "addr:postcode":"16601",
    "addr:street":"40Th St",
    "iso:country":"US",
    "sg:address":"865 40th St",
    "sg:city":"Altoona",
    "sg:classifiers":[
        {
            "category":"Restaurant",
            "type":"Food & Drink"
        }
    ],
    "sg:phone":"+1 814 949 2630",
    "sg:postcode":"16601",
    "sg:province":"PA",
    "wof:name":"Southside Subs & Billiards",
    "wof:placetype":"venue"
},
  "geometry": {"coordinates":[-78.42282899999999,40.487007],"type":"Point"}
}