{
  "type": "Feature",
  "properties": {
    "addr:full":"634 W State St Kennett Square PA 19348",
    "addr:housenumber":"634",
    "addr:postcode":"19348",
    "addr:street":"W State St",
    "iso:country":"US",
    "sg:address":"634 W State St",
    "sg:city":"Kennett Square",
    "sg:classifiers":[
        {
            "category":"Autos & Motor Vehicles",
            "subcategory":"Automobile Sales",
            "type":"Retail Goods"
        }
    ],
    "sg:phone":"+1 610 444 3400",
    "sg:postcode":"19348",
    "sg:province":"PA",
    "sg:tags":[
        "car"
    ],
    "wof:name":"Chevrolet Oldsmobile of Kennett Square Inc",
    "wof:placetype":"venue"
},
  "geometry": {"coordinates":[-75.7192,39.845798],"type":"Point"}
}