{
  "type": "Feature",
  "properties": {
    "iso:country":"US",
    "sg:address":"258 Haverford Ave",
    "sg:city":"Narberth",
    "sg:classifiers":[
        {
            "category":"Shopping",
            "subcategory":"Used Merchandise",
            "type":"Retail Goods"
        }
    ],
    "sg:phone":"+1 610 660 8119",
    "sg:postcode":"19072",
    "sg:province":"PA",
    "wof:name":"Revivals",
    "wof:placetype":"venue"
},
  "geometry": {"coordinates":[-75.261076,40.00542],"type":"Point"}
}