{
  "type": "Feature",
  "properties": {
    "iso:country":"US",
    "sg:address":"1005 24th St",
    "sg:city":"Beaver Falls",
    "sg:classifiers":[
        {
            "category":"Personal",
            "subcategory":"Beauty Salon",
            "type":"Services"
        }
    ],
    "sg:phone":"+1 724 846 8173",
    "sg:postcode":"15010",
    "sg:province":"PA",
    "sg:tags":[
        "shop"
    ],
    "wof:name":"Headliners Salon",
    "wof:placetype":"venue"
},
  "geometry": {"coordinates":[-80.32370899999999,40.764617],"type":"Point"}
}