{
  "type": "Feature",
  "properties": {
    "addr:full":"175 2nd Ave Kingston PA 18704",
    "addr:housenumber":"175",
    "addr:postcode":"18704",
    "addr:street":"2Nd Ave",
    "iso:country":"US",
    "sg:address":"175 2nd Ave",
    "sg:city":"Kingston",
    "sg:classifiers":[
        {
            "category":"Health Services",
            "subcategory":"Doctor",
            "type":"Services"
        }
    ],
    "sg:phone":"+1 570 823 0744",
    "sg:postcode":"18704",
    "sg:province":"PA",
    "sg:tags":[
        "physician",
        "surgeon"
    ],
    "wof:name":"Neil Wesner MD",
    "wof:placetype":"venue"
},
  "geometry": {"coordinates":[-75.883723,41.256949],"type":"Point"}
}