{
  "type": "Feature",
  "properties": {
    "addr:full":"35 Bucknell Ave Johnstown PA 15905",
    "addr:housenumber":"35",
    "addr:postcode":"15905",
    "addr:street":"Bucknell Ave",
    "iso:country":"US",
    "sg:address":"35 Bucknell Ave",
    "sg:city":"Johnstown",
    "sg:classifiers":[
        {
            "category":"Retail",
            "subcategory":"Auto Repair",
            "type":"Services"
        }
    ],
    "sg:phone":"+1 814 539 5001",
    "sg:postcode":"15905",
    "sg:province":"PA",
    "sg:tags":[
        "repairing",
        "automobile"
    ],
    "wof:name":"Sharkey's Service Sta",
    "wof:placetype":"venue"
},
  "geometry": {"coordinates":[-78.926401,40.317115],"type":"Point"}
}