{
  "type": "Feature",
  "properties": {
    "iso:country":"US",
    "sg:address":"133 N 2nd St",
    "sg:city":"Sunbury",
    "sg:classifiers":[
        {
            "category":"Professional",
            "subcategory":"Lawyer & Legal Services",
            "type":"Services"
        }
    ],
    "sg:phone":"+1 570 286 5687",
    "sg:postcode":"17801",
    "sg:province":"PA",
    "sg:tags":[
        "attorney"
    ],
    "wof:name":"North Penn Legal Svc",
    "wof:placetype":"venue"
},
  "geometry": {"coordinates":[-76.793395,40.865027],"type":"Point"}
}