{
  "type": "Feature",
  "properties": {
    "iso:country":"US",
    "sg:address":"1000 Northampton St",
    "sg:city":"Easton",
    "sg:classifiers":[
        {
            "category":"Health Services",
            "subcategory":"Chiropractor",
            "type":"Services"
        }
    ],
    "sg:phone":"+1 610 253 0611",
    "sg:postcode":"18042",
    "sg:province":"PA",
    "wof:name":"Cavallo Chiropractic Center",
    "wof:placetype":"venue"
},
  "geometry": {"coordinates":[-75.223466,40.690537],"type":"Point"}
}