{
  "type": "Feature",
  "properties": {
    "iso:country":"US",
    "sg:address":"20 W Myrtle Ave",
    "sg:city":"Feasterville Trevose",
    "sg:classifiers":[
        {
            "category":"Insurance",
            "subcategory":"Insurance Agent",
            "type":"Services"
        }
    ],
    "sg:phone":"+1 215 357 3638",
    "sg:postcode":"19053",
    "sg:province":"PA",
    "wof:name":"Knauth Insurance Agency Inc",
    "wof:placetype":"venue"
},
  "geometry": {"coordinates":[-74.99439700000001,40.160825],"type":"Point"}
}