{
  "type": "Feature",
  "properties": {
    "iso:country":"US",
    "sg:address":"126 Locust St",
    "sg:city":"Harrisburg",
    "sg:classifiers":[
        {
            "category":"Professional",
            "subcategory":"Lawyer & Legal Services",
            "type":"Services"
        }
    ],
    "sg:phone":"+1 717 236 0781",
    "sg:postcode":"17101",
    "sg:province":"PA",
    "wof:name":"Beshore Marvin Atty",
    "wof:placetype":"venue"
},
  "geometry": {"coordinates":[-76.884598,40.260601],"type":"Point"}
}