{
  "type": "Feature",
  "properties": {
    "addr:full":"829 Shenley Dr Erie PA 16505",
    "addr:housenumber":"829",
    "addr:postcode":"16505",
    "addr:street":"Shenley Dr",
    "iso:country":"US",
    "sg:address":"829 Shenley Dr",
    "sg:city":"Erie",
    "sg:classifiers":[
        {
            "category":"Health Services",
            "subcategory":"Clinic",
            "type":"Services"
        }
    ],
    "sg:phone":"+1   ",
    "sg:postcode":"16505",
    "sg:province":"PA",
    "sg:tags":[
        "specialty",
        "outpatient"
    ],
    "wof:name":"Al-Anon Family Services",
    "wof:placetype":"venue"
},
  "geometry": {"coordinates":[-80.12893200000001,42.110882],"type":"Point"}
}