{
  "type": "Feature",
  "properties": {
    "iso:country":"US",
    "sg:address":"25 Bala Ave Ste 203",
    "sg:city":"Bala Cynwyd",
    "sg:classifiers":[
        {
            "category":"Professional",
            "subcategory":"Accounting & Tax Preparation",
            "type":"Services"
        }
    ],
    "sg:phone":"+1 610 664 2482",
    "sg:postcode":"19004",
    "sg:province":"PA",
    "sg:tags":[
        "accountant"
    ],
    "wof:name":"Levick Gene H CPA",
    "wof:placetype":"venue"
},
  "geometry": {"coordinates":[-75.233096,40.007712],"type":"Point"}
}