{
  "type": "Feature",
  "properties": {
    "addr:full":"4808 Sardis Rd New Kensington PA 15068",
    "addr:housenumber":"4808",
    "addr:postcode":"15068",
    "addr:street":"Sardis Rd",
    "iso:country":"US",
    "sg:address":"4808 Sardis Rd",
    "sg:city":"New Kensington",
    "sg:classifiers":[
        {
            "category":"Home & Garden",
            "subcategory":"Garden Supply",
            "type":"Retail Goods"
        }
    ],
    "sg:phone":"+1   ",
    "sg:postcode":"15068",
    "sg:province":"PA",
    "wof:name":"Mc Kinley Landscape Nurseries",
    "wof:placetype":"venue"
},
  "geometry": {"coordinates":[-79.740493,40.522372],"type":"Point"}
}