{
  "type": "Feature",
  "properties": {
    "iso:country":"US",
    "sg:address":"1818 Foxcroft Ln",
    "sg:city":"Allison Park",
    "sg:classifiers":[
        {
            "category":"Real Estate",
            "subcategory":"Real Estate Operator",
            "type":"Services"
        }
    ],
    "sg:phone":"+1   ",
    "sg:postcode":"15101",
    "sg:province":"PA",
    "sg:tags":[
        "building",
        "apartment"
    ],
    "wof:name":"Investment Group",
    "wof:placetype":"venue"
},
  "geometry": {"coordinates":[-79.996538,40.564356],"type":"Point"}
}