{
  "type": "Feature",
  "properties": {
    "iso:country":"US",
    "sg:address":"730 E Haverford Rd",
    "sg:city":"Bryn Mawr",
    "sg:classifiers":[
        {
            "category":"Manufacturing",
            "subcategory":"Retail Goods",
            "type":"Manufacturing & Wholesale Goods"
        }
    ],
    "sg:phone":"+1   ",
    "sg:postcode":"19010",
    "sg:province":"PA",
    "sg:tags":[
        "industry",
        "printing",
        "publishing",
        "allied"
    ],
    "wof:name":"Garman Sign & Decal Co",
    "wof:placetype":"venue"
},
  "geometry": {"coordinates":[-75.315978,40.012445],"type":"Point"}
}