{
  "type": "Feature",
  "properties": {
    "addr:full":"700 Green St Harrisburg PA 17102",
    "addr:housenumber":"700",
    "addr:postcode":"17102",
    "addr:street":"Green St",
    "iso:country":"US",
    "sg:address":"700 Green St",
    "sg:city":"Harrisburg",
    "sg:classifiers":[
        {
            "category":"Professional",
            "subcategory":"Lawyer & Legal Services",
            "type":"Services"
        }
    ],
    "sg:phone":"+1   ",
    "sg:postcode":"17102",
    "sg:province":"PA",
    "sg:tags":[
        "building",
        "operator",
        "apartment",
        "dwell"
    ],
    "wof:name":"Georgetown Townhouses",
    "wof:placetype":"venue"
},
  "geometry": {"coordinates":[-76.887158,40.264889],"type":"Point"}
}