{
  "type": "Feature",
  "properties": {
    "iso:country":"US",
    "sg:address":"1410 Ackermanville Rd",
    "sg:city":"Bangor",
    "sg:classifiers":[
        {
            "category":"Place Of Worship",
            "subcategory":"Church",
            "type":"Public Place"
        },
        {
            "category":"Place Of Worship",
            "type":"Public Place"
        }
    ],
    "sg:phone":"+1 610 588 7818",
    "sg:postcode":"18013",
    "sg:province":"PA",
    "sg:tags":[
        "churches-methodist"
    ],
    "wof:name":"Ackermanville United Methodist Church",
    "wof:placetype":"venue"
},
  "geometry": {"coordinates":[-75.216564,40.833655],"type":"Point"}
}