{
  "type": "Feature",
  "properties": {
    "addr:full":"362 S Carlisle St Greencastle PA 17225",
    "addr:housenumber":"362",
    "addr:postcode":"17225",
    "addr:street":"S Carlisle St",
    "iso:country":"US",
    "sg:address":"362 S Carlisle St",
    "sg:city":"Greencastle",
    "sg:classifiers":[
        {
            "category":"Wholesale",
            "subcategory":"Machinery & Supplies",
            "type":"Manufacturing & Wholesale Goods"
        }
    ],
    "sg:phone":"+1 717 597 9150",
    "sg:postcode":"17225",
    "sg:province":"PA",
    "sg:tags":[
        "compressor",
        "gas"
    ],
    "wof:name":"R L Bentley Machinery Repair",
    "wof:placetype":"venue"
},
  "geometry": {"coordinates":[-77.73023499999999,39.785065],"type":"Point"}
}