{
  "type": "Feature",
  "properties": {
    "iso:country":"US",
    "sg:address":"23 White Spruce Ln",
    "sg:city":"Levittown",
    "sg:classifiers":[
        {
            "category":"Professional",
            "type":"Services"
        }
    ],
    "sg:phone":"+1 267 338 5387",
    "sg:postcode":"19054",
    "sg:province":"PA",
    "sg:tags":[
        "transportation"
    ],
    "wof:name":"Onur Transportation",
    "wof:placetype":"venue"
},
  "geometry": {"coordinates":[-74.82892200000001,40.157992],"type":"Point"}
}