{
  "type": "Feature",
  "properties": {
    "iso:country":"US",
    "sg:address":"72 Mechanic St",
    "sg:city":"Bradford",
    "sg:classifiers":[
        {
            "category":"Building & Trades",
            "subcategory":"Construction",
            "type":"Services"
        }
    ],
    "sg:phone":"+1 814 368 7813",
    "sg:postcode":"16701",
    "sg:province":"PA",
    "sg:tags":[
        "marking",
        "maintenance",
        "parking"
    ],
    "wof:name":"Public Works Barn",
    "wof:placetype":"venue"
},
  "geometry": {"coordinates":[-78.651397,41.958519],"type":"Point"}
}