{
  "type": "Feature",
  "properties": {
    "iso:country":"US",
    "sg:address":"328 E Burd St",
    "sg:city":"Shippensburg",
    "sg:classifiers":[
        {
            "category":"Wholesale",
            "subcategory":"Machinery & Supplies",
            "type":"Manufacturing & Wholesale Goods"
        }
    ],
    "sg:phone":"+1 717 530 1160",
    "sg:postcode":"17257",
    "sg:province":"PA",
    "sg:tags":[
        "tractor"
    ],
    "wof:name":"Ingersoll-Rand Co",
    "wof:placetype":"venue"
},
  "geometry": {"coordinates":[-77.514392,40.055783],"type":"Point"}
}