{
  "type": "Feature",
  "properties": {
    "iso:country":"US",
    "sg:address":"2600 Dysart Ave",
    "sg:city":"Altoona",
    "sg:classifiers":[
        {
            "category":"Building & Trades",
            "subcategory":"Construction",
            "type":"Services"
        }
    ],
    "sg:phone":"+1 814 941 2674",
    "sg:postcode":"16602",
    "sg:province":"PA",
    "sg:tags":[
        "painter"
    ],
    "wof:name":"Burr Quality Painting",
    "wof:placetype":"venue"
},
  "geometry": {"coordinates":[-78.405135,40.49807],"type":"Point"}
}