{
  "type": "Feature",
  "properties": {
    "addr:full":"3375 E State St Hermitage PA 16148",
    "addr:housenumber":"3375",
    "addr:postcode":"16148",
    "addr:street":"E State St",
    "iso:country":"US",
    "sg:address":"3375 E State St",
    "sg:city":"Hermitage",
    "sg:classifiers":[
        {
            "category":"Food & Beverages",
            "subcategory":"Specialty",
            "type":"Retail Goods"
        }
    ],
    "sg:phone":"+1   ",
    "sg:postcode":"16148",
    "sg:province":"PA",
    "wof:name":"GNC",
    "wof:placetype":"venue"
},
  "geometry": {"coordinates":[-80.446198,41.233522],"type":"Point"}
}