{
  "type": "Feature",
  "properties": {
    "addr:full":"344 Industrial Rd Nesquehoning PA 18240",
    "addr:housenumber":"344",
    "addr:postcode":"18240",
    "addr:street":"Industrial Rd",
    "iso:country":"US",
    "sg:address":"344 Industrial Rd",
    "sg:city":"Nesquehoning",
    "sg:classifiers":[
        {
            "category":"Manufacturing",
            "subcategory":"Signs",
            "type":"Manufacturing & Wholesale Goods"
        }
    ],
    "sg:phone":"+1 570 645 8701",
    "sg:postcode":"18240",
    "sg:province":"PA",
    "wof:name":"Heritage Sign & Display",
    "wof:placetype":"venue"
},
  "geometry": {"coordinates":[-75.85306300000001,40.856654],"type":"Point"}
}