{
  "type": "Feature",
  "properties": {
    "addr:full":"404 W Grant St New Castle PA 16101",
    "addr:housenumber":"404",
    "addr:postcode":"16101",
    "addr:street":"W Grant St",
    "iso:country":"US",
    "sg:address":"404 W Grant St",
    "sg:city":"New Castle",
    "sg:classifiers":[
        {
            "category":"Government",
            "subcategory":"Office",
            "type":"Public Place"
        }
    ],
    "sg:phone":"+1 724 656 5111",
    "sg:postcode":"16101",
    "sg:province":"PA",
    "wof:name":"Lawrence Area Management Ofcs",
    "wof:placetype":"venue"
},
  "geometry": {"coordinates":[-80.352769,41.003324],"type":"Point"}
}