{
  "type": "Feature",
  "properties": {
    "addr:full":"9100 Kuhl Rd Erie PA 16510",
    "addr:postcode":"9100;16510",
    "addr:street":"Kuhl Rd",
    "iso:country":"US",
    "sg:address":"9100 Kuhl Rd",
    "sg:city":"Erie",
    "sg:classifiers":[
        {
            "category":"Farming",
            "subcategory":"Farm",
            "type":"Manufacturing & Wholesale Goods"
        }
    ],
    "sg:phone":"+1   ",
    "sg:postcode":"16510",
    "sg:province":"PA",
    "sg:tags":[
        "crop",
        "general"
    ],
    "wof:name":"George Kerecman",
    "wof:placetype":"venue"
},
  "geometry": {"coordinates":[-79.964535,42.078486],"type":"Point"}
}