{
  "type": "Feature",
  "properties": {
    "iso:country":"US",
    "sg:address":"709 Lawn Ave",
    "sg:city":"Sellersville",
    "sg:classifiers":[
        {
            "category":"Professional",
            "type":"Services"
        }
    ],
    "sg:phone":"+1   ",
    "sg:postcode":"18960",
    "sg:province":"PA",
    "wof:name":"Robert A Hamburger",
    "wof:placetype":"venue"
},
  "geometry": {"coordinates":[-75.32380000000001,40.362444],"type":"Point"}
}