{
  "type": "Feature",
  "properties": {
    "addr:full":"1711 Chestnut St Erie PA 16502",
    "addr:housenumber":"1711",
    "addr:postcode":"16502",
    "addr:street":"Chestnut St",
    "iso:country":"US",
    "sg:address":"1711 Chestnut St",
    "sg:city":"Erie",
    "sg:classifiers":[
        {
            "category":"Building & Trades",
            "subcategory":"Electrical",
            "type":"Services"
        },
        {
            "category":"Utilities",
            "subcategory":"Electric",
            "type":"Services"
        }
    ],
    "sg:phone":"+1 814 455 6750",
    "sg:postcode":"16502",
    "sg:province":"PA",
    "sg:tags":[
        "electrical",
        "contractor"
    ],
    "wof:name":"Dobrich Electric & Svc",
    "wof:placetype":"venue"
},
  "geometry": {"coordinates":[-80.086416,42.115498],"type":"Point"}
}