{
  "type": "Feature",
  "properties": {
    "addr:full":"988 Perry Hwy Pittsburgh PA 15237",
    "addr:housenumber":"988",
    "addr:postcode":"15237",
    "addr:street":"Perry Hwy",
    "iso:country":"US",
    "sg:address":"988 Perry Hwy",
    "sg:city":"Pittsburgh",
    "sg:classifiers":[
        {
            "category":"Building & Trades",
            "subcategory":"Construction",
            "type":"Services"
        }
    ],
    "sg:phone":"+1 412 920 6501",
    "sg:postcode":"15237",
    "sg:province":"PA",
    "sg:tags":[
        "general",
        "contractor"
    ],
    "wof:name":"Angel Contracting LP",
    "wof:placetype":"venue"
},
  "geometry": {"coordinates":[-80.03622799999999,40.537793],"type":"Point"}
}