{
  "type": "Feature",
  "properties": {
    "addr:full":"8970 Edinboro Rd Mc Kean PA 16426",
    "addr:housenumber":"8970",
    "addr:postcode":"16426",
    "addr:street":"Edinboro Rd",
    "iso:country":"US",
    "sg:address":"8970 Edinboro Rd",
    "sg:city":"Mc Kean",
    "sg:classifiers":[
        {
            "category":"Shopping",
            "subcategory":"Bicycles & Sporting Goods",
            "type":"Retail Goods"
        }
    ],
    "sg:phone":"+1   ",
    "sg:postcode":"16426",
    "sg:province":"PA",
    "sg:tags":[
        "repair"
    ],
    "wof:name":"Bobs Gun Shop",
    "wof:placetype":"venue"
},
  "geometry": {"coordinates":[-80.14299200000001,41.997653],"type":"Point"}
}