{
  "type": "Feature",
  "properties": {
    "addr:full":"260 Johnson St Wilkes Barre PA 18702",
    "addr:housenumber":"260",
    "addr:postcode":"18702",
    "addr:street":"Johnson St",
    "iso:country":"US",
    "sg:address":"260 Johnson St",
    "sg:city":"Wilkes Barre",
    "sg:classifiers":[
        {
            "category":"Utilities",
            "subcategory":"Refuse",
            "type":"Services"
        }
    ],
    "sg:phone":"+1 570 820 9912",
    "sg:postcode":"18702",
    "sg:province":"PA",
    "sg:tags":[
        "management",
        "for",
        "medical",
        "removal",
        "regulated",
        "th",
        "waste",
        "integrated"
    ],
    "wof:name":"Stericycle Inc (de)",
    "wof:placetype":"venue"
},
  "geometry": {"coordinates":[-75.879012,41.222607],"type":"Point"}
}