{
  "type": "Feature",
  "properties": {
    "addr:full":"920 Pennsylvania Ave W Warren PA 16365",
    "addr:housenumber":"920",
    "addr:postcode":"16365",
    "addr:street":"Pennsylvania Ave W",
    "iso:country":"US",
    "sg:address":"920 Pennsylvania Ave W",
    "sg:city":"Warren",
    "sg:classifiers":[
        {
            "category":"Real Estate",
            "subcategory":"Real Estate Agent",
            "type":"Services"
        }
    ],
    "sg:phone":"+1   ",
    "sg:postcode":"16365",
    "sg:province":"PA",
    "wof:name":"Bvk Inc",
    "wof:placetype":"venue"
},
  "geometry": {"coordinates":[-79.158711,41.844274],"type":"Point"}
}