{
  "type": "Feature",
  "properties": {
    "iso:country":"US",
    "sg:address":"227 N Broad St",
    "sg:city":"Philadelphia",
    "sg:classifiers":[
        {
            "category":"Health Services",
            "subcategory":"Doctor",
            "type":"Services"
        }
    ],
    "sg:phone":"+1 215 563 1199",
    "sg:postcode":"19107",
    "sg:province":"PA",
    "wof:name":"Amster Melanie I MD",
    "wof:placetype":"venue"
},
  "geometry": {"coordinates":[-75.16241100000001,39.956652],"type":"Point"}
}