{
  "type": "Feature",
  "properties": {
    "iso:country":"US",
    "sg:address":"39 Lake Rd",
    "sg:city":"Hadley",
    "sg:classifiers":[
        {
            "category":"Government",
            "subcategory":"Office",
            "type":"Public Place"
        }
    ],
    "sg:phone":"+1 724 253 3361",
    "sg:postcode":"16130",
    "sg:province":"PA",
    "sg:tags":[
        "village"
    ],
    "wof:name":"Sandy Creek Twp Building",
    "wof:placetype":"venue"
},
  "geometry": {"coordinates":[-80.20970199999999,41.447591],"type":"Point"}
}