{
  "type": "Feature",
  "properties": {
    "iso:country":"US",
    "sg:address":"3751 W 4th Ave",
    "sg:city":"Beaver Falls",
    "sg:classifiers":[
        {
            "category":"Manufacturing",
            "subcategory":"Metals",
            "type":"Manufacturing & Wholesale Goods"
        }
    ],
    "sg:phone":"+1 724 846 0660",
    "sg:postcode":"15010",
    "sg:province":"PA",
    "sg:tags":[
        "foundry"
    ],
    "wof:name":"Lunar Fusion Inc",
    "wof:placetype":"venue"
},
  "geometry": {"coordinates":[-80.33394199999999,40.781901],"type":"Point"}
}