{
  "type": "Feature",
  "properties": {
    "iso:country":"US",
    "sg:address":"430 N Main St",
    "sg:city":"Spring Grove",
    "sg:classifiers":[
        {
            "category":"Insurance",
            "subcategory":"Insurance Agent",
            "type":"Services"
        }
    ],
    "sg:phone":"+1 717 225 3526",
    "sg:postcode":"17362",
    "sg:province":"PA",
    "wof:name":"Mc Neil & Co",
    "wof:placetype":"venue"
},
  "geometry": {"coordinates":[-76.864891,39.879916],"type":"Point"}
}