{
  "type": "Feature",
  "properties": {
    "addr:full":"2005 Market St Ste 3510 Philadelphia PA 19103",
    "addr:housenumber":"2005",
    "addr:postcode":"19103",
    "addr:street":"Market St Ste 3510",
    "iso:country":"US",
    "sg:address":"2005 Market St Ste 3510",
    "sg:city":"Philadelphia",
    "sg:classifiers":[
        {
            "category":"Structure",
            "subcategory":"Office Building",
            "type":"Public Place"
        }
    ],
    "sg:phone":"+1 215 851 6000",
    "sg:postcode":"19103",
    "sg:province":"PA",
    "sg:tags":[
        "park"
    ],
    "wof:name":"Commerce Square Partners-Philadelphia Plaza Lp",
    "wof:placetype":"venue"
},
  "geometry": {"coordinates":[-75.17326199999999,39.95358],"type":"Point"}
}