{
  "type": "Feature",
  "properties": {
    "addr:full":"112 S 10th St Akron PA 17501",
    "addr:housenumber":"112",
    "addr:postcode":"17501",
    "addr:street":"S 10Th St",
    "iso:country":"US",
    "sg:address":"112 S 10th St",
    "sg:city":"Akron",
    "sg:classifiers":[
        {
            "category":"Building & Trades",
            "subcategory":"Construction",
            "type":"Services"
        }
    ],
    "sg:phone":"+1 717 859 2586",
    "sg:postcode":"17501",
    "sg:province":"PA",
    "sg:tags":[
        "painter"
    ],
    "wof:name":"Weaver's Painting & Paperhang",
    "wof:placetype":"venue"
},
  "geometry": {"coordinates":[-76.200766,40.15435],"type":"Point"}
}