{
  "type": "Feature",
  "properties": {
    "iso:country":"US",
    "sg:address":"875 Park Ave",
    "sg:city":"Shavertown",
    "sg:classifiers":[
        {
            "category":"Retail",
            "subcategory":"Self-service Laundry",
            "type":"Services"
        }
    ],
    "sg:phone":"+1   ",
    "sg:postcode":"18708",
    "sg:province":"PA",
    "sg:tags":[
        "coin"
    ],
    "wof:name":"Dundee Laundromat",
    "wof:placetype":"venue"
},
  "geometry": {"coordinates":[-75.96810499999999,41.302977],"type":"Point"}
}