{
  "type": "Feature",
  "properties": {
    "iso:country":"US",
    "sg:address":"13788 Ridge Rd",
    "sg:city":"West Springfield",
    "sg:classifiers":[
        {
            "category":"Government",
            "subcategory":"Post Office",
            "type":"Public Place"
        }
    ],
    "sg:phone":"+1   ",
    "sg:postcode":"16443",
    "sg:province":"PA",
    "sg:tags":[
        "postal",
        "us"
    ],
    "wof:name":"West Springfield M O",
    "wof:placetype":"venue"
},
  "geometry": {"coordinates":[-80.473789,41.946189],"type":"Point"}
}