{
  "type": "Feature",
  "properties": {
    "addr:full":"319 Cheswold Rd Drexel Hill PA 19026",
    "addr:housenumber":"319",
    "addr:postcode":"19026",
    "addr:street":"Cheswold Rd",
    "iso:country":"US",
    "sg:address":"319 Cheswold Rd",
    "sg:city":"Drexel Hill",
    "sg:classifiers":[
        {
            "category":"Professional",
            "type":"Services"
        }
    ],
    "sg:phone":"+1   ",
    "sg:postcode":"19026",
    "sg:province":"PA",
    "wof:name":"Wicker Workshop Inc",
    "wof:placetype":"venue"
},
  "geometry": {"coordinates":[-75.29709099999999,39.940284],"type":"Point"}
}