{
  "type": "Feature",
  "properties": {
    "iso:country":"US",
    "sg:address":"20 S Lancaster Ln",
    "sg:city":"Newtown",
    "sg:classifiers":[
        {
            "category":"Professional",
            "type":"Services"
        }
    ],
    "sg:phone":"+1   ",
    "sg:postcode":"18940",
    "sg:province":"PA",
    "wof:name":"Domitron Products",
    "wof:placetype":"venue"
},
  "geometry": {"coordinates":[-74.96077,40.22299],"type":"Point"}
}