{
  "type": "Feature",
  "properties": {
    "addr:full":"808 E 17th St Chester PA 19013",
    "addr:housenumber":"808",
    "addr:postcode":"19013",
    "addr:street":"E 17Th St",
    "iso:country":"US",
    "sg:address":"808 E 17th St",
    "sg:city":"Chester",
    "sg:classifiers":[
        {
            "category":"Education",
            "subcategory":"School",
            "type":"Public Place"
        }
    ],
    "sg:phone":"+1   ",
    "sg:postcode":"19013",
    "sg:province":"PA",
    "wof:name":"Stetser Community Academy",
    "wof:placetype":"venue"
},
  "geometry": {"coordinates":[-75.355638,39.864217],"type":"Point"}
}