{
  "type": "Feature",
  "properties": {
    "iso:country":"US",
    "sg:address":"30 W Club Dr",
    "sg:city":"Pittsburgh",
    "sg:classifiers":[
        {
            "category":"Wholesale",
            "subcategory":"Machinery & Supplies",
            "type":"Manufacturing & Wholesale Goods"
        }
    ],
    "sg:phone":"+1 412 884 6552",
    "sg:postcode":"15236",
    "sg:province":"PA",
    "sg:tags":[
        "bearing"
    ],
    "wof:name":"Budd Co Bearing Sales",
    "wof:placetype":"venue"
},
  "geometry": {"coordinates":[-79.99248299999999,40.357209],"type":"Point"}
}