{
  "type": "Feature",
  "properties": {
    "addr:full":"162 W Chestnut St Washington PA 15301",
    "addr:housenumber":"162",
    "addr:postcode":"15301",
    "addr:street":"W Chestnut St",
    "iso:country":"US",
    "sg:address":"162 W Chestnut St",
    "sg:city":"Washington",
    "sg:classifiers":[
        {
            "category":"Government",
            "subcategory":"Office",
            "type":"Public Place"
        }
    ],
    "sg:phone":"+1   ",
    "sg:postcode":"15301",
    "sg:province":"PA",
    "sg:tags":[
        "internal",
        "revenue"
    ],
    "wof:name":"Internal Revenue Service",
    "wof:placetype":"venue"
},
  "geometry": {"coordinates":[-80.250163,40.171697],"type":"Point"}
}