{
  "type": "Feature",
  "properties": {
    "iso:country":"US",
    "sg:address":"114 S Main St",
    "sg:city":"Homer City",
    "sg:classifiers":[
        {
            "category":"Restaurant",
            "type":"Food & Drink"
        }
    ],
    "sg:phone":"+1 724 479 3595",
    "sg:postcode":"15748",
    "sg:province":"PA",
    "sg:tags":[
        "eating"
    ],
    "wof:name":"Dugout Pizzaria",
    "wof:placetype":"venue"
},
  "geometry": {"coordinates":[-79.160439,40.541032],"type":"Point"}
}