{
  "type": "Feature",
  "properties": {
    "addr:full":"2000 Waterdam Plaza Dr Canonsburg PA 15317",
    "addr:postcode":"15317",
    "addr:street":"Waterdam Plaza Dr",
    "iso:country":"US",
    "sg:address":"2000 Waterdam Plaza Dr",
    "sg:city":"Canonsburg",
    "sg:classifiers":[
        {
            "category":"Health Services",
            "subcategory":"Dentist",
            "type":"Services"
        }
    ],
    "sg:phone":"+1 724 942 5130",
    "sg:postcode":"15317",
    "sg:province":"PA",
    "wof:name":"Cartwright Gary E DMD",
    "wof:placetype":"venue"
},
  "geometry": {"coordinates":[-80.133852,40.262918],"type":"Point"}
}