{
  "type": "Feature",
  "properties": {
    "iso:country":"US",
    "sg:address":"2490 Mosside Blvd",
    "sg:city":"Monroeville",
    "sg:classifiers":[
        {
            "category":"Health Services",
            "subcategory":"Doctor",
            "type":"Services"
        }
    ],
    "sg:phone":"+1   ",
    "sg:postcode":"15146",
    "sg:province":"PA",
    "sg:tags":[
        "outpatient",
        "cardiology"
    ],
    "wof:name":"Med Health Services",
    "wof:placetype":"venue"
},
  "geometry": {"coordinates":[-79.755627,40.420435],"type":"Point"}
}