{
  "type": "Feature",
  "properties": {
    "iso:country":"US",
    "sg:address":"832 S 55th St",
    "sg:city":"Philadelphia",
    "sg:classifiers":[
        {
            "category":"Retail",
            "subcategory":"Car Wash",
            "type":"Services"
        }
    ],
    "sg:phone":"+1 215 471 3522",
    "sg:postcode":"19143",
    "sg:province":"PA",
    "sg:tags":[
        "automobile",
        "detail",
        "clean"
    ],
    "wof:name":"Friendly's Auto Detailing",
    "wof:placetype":"venue"
},
  "geometry": {"coordinates":[-75.233762,39.946813],"type":"Point"}
}