{
  "type": "Feature",
  "properties": {
    "addr:full":"1919 Chestnut St Apt 517 Philadelphia PA 19103",
    "addr:housenumber":"1919;517",
    "addr:postcode":"19103",
    "addr:street":"Chestnut St Apt",
    "iso:country":"US",
    "sg:address":"1919 Chestnut St Apt 517",
    "sg:city":"Philadelphia",
    "sg:classifiers":[
        {
            "category":"Health Services",
            "subcategory":"Dentist",
            "type":"Services"
        }
    ],
    "sg:phone":"+1 215 567 1566",
    "sg:postcode":"19103",
    "sg:province":"PA",
    "wof:name":"Silverblatt Salvin Dds",
    "wof:placetype":"venue"
},
  "geometry": {"coordinates":[-75.17219900000001,39.951896],"type":"Point"}
}