{
  "type": "Feature",
  "properties": {
    "iso:country":"US",
    "sg:address":"273 Stahl Dr",
    "sg:city":"Huntingdon Valley",
    "sg:classifiers":[
        {
            "category":"Professional",
            "subcategory":"Management & Consulting",
            "type":"Services"
        }
    ],
    "sg:phone":"+1   ",
    "sg:postcode":"19006",
    "sg:province":"PA",
    "sg:tags":[
        "procurement",
        "augmentation",
        "staff"
    ],
    "wof:name":"Capital Supply Management LLC",
    "wof:placetype":"venue"
},
  "geometry": {"coordinates":[-75.057213,40.116363],"type":"Point"}
}