{
  "type": "Feature",
  "properties": {
    "iso:country":"US",
    "sg:address":"901 Lawrence Dr",
    "sg:city":"Duncansville",
    "sg:classifiers":[
        {
            "category":"Banks & Credit Unions",
            "subcategory":"Financial Services",
            "type":"Services"
        }
    ],
    "sg:phone":"+1   ",
    "sg:postcode":"16635",
    "sg:province":"PA",
    "sg:tags":[
        "investor"
    ],
    "wof:name":"Vassalotti Investment",
    "wof:placetype":"venue"
},
  "geometry": {"coordinates":[-78.421283,40.415476],"type":"Point"}
}