{
  "type": "Feature",
  "properties": {
    "iso:country":"US",
    "sg:address":"1824 Perrott St",
    "sg:city":"Pittsburgh",
    "sg:classifiers":[
        {
            "category":"Professional",
            "subcategory":"Art Services",
            "type":"Services"
        }
    ],
    "sg:phone":"+1 412 761 4040",
    "sg:postcode":"15212",
    "sg:province":"PA",
    "sg:tags":[
        "photographer"
    ],
    "wof:name":"Bill Exler",
    "wof:placetype":"venue"
},
  "geometry": {"coordinates":[-80.0411,40.486837],"type":"Point"}
}