{
  "type": "Feature",
  "properties": {
    "addr:full":"133 E 3rd St Williamsport PA 17701",
    "addr:housenumber":"133",
    "addr:postcode":"17701",
    "addr:street":"E 3Rd St",
    "iso:country":"US",
    "sg:address":"133 E 3rd St",
    "sg:city":"Williamsport",
    "sg:classifiers":[
        {
            "category":"Retail",
            "subcategory":"Funeral Services",
            "type":"Services"
        }
    ],
    "sg:phone":"+1 570 322 4706",
    "sg:postcode":"17701",
    "sg:province":"PA",
    "wof:name":"Crouse Funeral Home",
    "wof:placetype":"venue"
},
  "geometry": {"coordinates":[-76.999225,41.242005],"type":"Point"}
}