{
  "type": "Feature",
  "properties": {
    "iso:country":"US",
    "sg:address":"8361 Hamot Rd",
    "sg:city":"Erie",
    "sg:classifiers":[
        {
            "category":"Home & Garden",
            "subcategory":"Carpets & Floor Coverings",
            "type":"Retail Goods"
        }
    ],
    "sg:phone":"+1 814 864 2785",
    "sg:postcode":"16509",
    "sg:province":"PA",
    "sg:tags":[
        "material"
    ],
    "wof:name":"John Lander Ceramic Tile",
    "wof:placetype":"venue"
},
  "geometry": {"coordinates":[-80.09303800000001,42.031344],"type":"Point"}
}