{
  "type": "Feature",
  "properties": {
    "iso:country":"US",
    "sg:address":"1006 W 8th Ave",
    "sg:city":"King Of Prussia",
    "sg:classifiers":[
        {
            "category":"Wholesale",
            "subcategory":"Medical Equipment & Supplies",
            "type":"Manufacturing & Wholesale Goods"
        }
    ],
    "sg:phone":"+1 610 630 9200",
    "sg:postcode":"19406",
    "sg:province":"PA",
    "sg:tags":[
        "optical"
    ],
    "wof:name":"Topcon Omni Systems Inc",
    "wof:placetype":"venue"
},
  "geometry": {"coordinates":[-75.415789,40.098681],"type":"Point"}
}