{
  "type": "Feature",
  "properties": {
    "iso:country":"US",
    "sg:address":"1713 Wrights Way",
    "sg:city":"Pittsburgh",
    "sg:classifiers":[
        {
            "category":"Shopping",
            "type":"Retail Goods"
        }
    ],
    "sg:phone":"+1 412 431 1460",
    "sg:postcode":"15203",
    "sg:province":"PA",
    "sg:tags":[
        "art",
        "gallery",
        "dealer"
    ],
    "wof:name":"LA Fond Galleries",
    "wof:placetype":"venue"
},
  "geometry": {"coordinates":[-79.98064599999999,40.429314],"type":"Point"}
}