{
  "type": "Feature",
  "properties": {
    "iso:country":"US",
    "sg:address":"211 N Whitfield St",
    "sg:city":"Pittsburgh",
    "sg:classifiers":[
        {
            "category":"Health Services",
            "subcategory":"Doctor",
            "type":"Services"
        }
    ],
    "sg:phone":"+1 724 443 2770",
    "sg:postcode":"15206",
    "sg:province":"PA",
    "sg:tags":[
        "dentist"
    ],
    "wof:name":"Frank A Ranalli DDS",
    "wof:placetype":"venue"
},
  "geometry": {"coordinates":[-79.925146,40.462856],"type":"Point"}
}