{
  "type": "Feature",
  "properties": {
    "iso:country":"US",
    "sg:address":"201 Wilmington Pike",
    "sg:city":"Glen Mills",
    "sg:classifiers":[
        {
            "category":"Health Services",
            "subcategory":"Doctor",
            "type":"Services"
        }
    ],
    "sg:phone":"+1 610 459 2066",
    "sg:postcode":"19342",
    "sg:province":"PA",
    "sg:tags":[
        "obstetrician",
        "gynecologist"
    ],
    "wof:name":"Raunio Anne MD",
    "wof:placetype":"venue"
},
  "geometry": {"coordinates":[-75.54450199999999,39.8703],"type":"Point"}
}