{
  "type": "Feature",
  "properties": {
    "addr:full":"927 S State St Clarks Summit PA 18411",
    "addr:housenumber":"927",
    "addr:postcode":"18411",
    "addr:street":"S State St",
    "iso:country":"US",
    "sg:address":"927 S State St",
    "sg:city":"Clarks Summit",
    "sg:classifiers":[
        {
            "category":"Bakery",
            "type":"Food & Drink"
        },
        {
            "category":"Coffee & Tea",
            "type":"Food & Drink"
        },
        {
            "category":"Bagels",
            "type":"Food & Drink"
        },
        {
            "category":"Donuts",
            "type":"Food & Drink"
        }
    ],
    "sg:menulink":"http://www.allmenus.com/pa/clarks-summit/143919-dunkin-donuts/menu/",
    "sg:phone":"+1 570 587 0103",
    "sg:postcode":"18411",
    "sg:province":"PA",
    "sg:tags":[
        "american",
        "diner",
        "pastry"
    ],
    "wof:name":"Dunkin' Donuts",
    "wof:placetype":"venue"
},
  "geometry": {"coordinates":[-75.697243,41.48963],"type":"Point"}
}