{
  "type": "Feature",
  "properties": {
    "iso:country":"US",
    "sg:address":"39 E Main St",
    "sg:city":"New Bloomfield",
    "sg:classifiers":[
        {
            "category":"Building & Trades",
            "subcategory":"Cleaning & Sanitation",
            "type":"Services"
        }
    ],
    "sg:phone":"+1 717 582 8187",
    "sg:postcode":"17068",
    "sg:province":"PA",
    "sg:tags":[
        "janitor"
    ],
    "wof:name":"Dorundo's Cleaning Svc",
    "wof:placetype":"venue"
},
  "geometry": {"coordinates":[-77.18509299999999,40.420542],"type":"Point"}
}