{
  "type": "Feature",
  "properties": {
    "addr:full":"909 Mountain Rd Pine Grove PA 17963",
    "addr:housenumber":"909",
    "addr:postcode":"17963",
    "addr:street":"Mountain Rd",
    "iso:country":"US",
    "sg:address":"909 Mountain Rd",
    "sg:city":"Pine Grove",
    "sg:classifiers":[
        {
            "category":"Farming",
            "subcategory":"Livestock Farm",
            "type":"Manufacturing & Wholesale Goods"
        }
    ],
    "sg:phone":"+1   ",
    "sg:postcode":"17963",
    "sg:province":"PA",
    "sg:tags":[
        "beef",
        "feedlot",
        "cattle"
    ],
    "wof:name":"Samuel Kutz",
    "wof:placetype":"venue"
},
  "geometry": {"coordinates":[-76.32664,40.595344],"type":"Point"}
}