{
  "type": "Feature",
  "properties": {
    "iso:country":"US",
    "sg:address":"757 Science Park Rd",
    "sg:city":"State College",
    "sg:classifiers":[
        {
            "category":"Freight",
            "type":"Transportation"
        }
    ],
    "sg:phone":"+1 814 235 7867",
    "sg:postcode":"16803",
    "sg:province":"PA",
    "sg:tags":[
        "commercial",
        "storage",
        "special"
    ],
    "wof:name":"Stor-All Self Storage",
    "wof:placetype":"venue"
},
  "geometry": {"coordinates":[-77.90254299999999,40.785184],"type":"Point"}
}