{
  "type": "Feature",
  "properties": {
    "iso:country":"US",
    "sg:address":"612 Austin Dr",
    "sg:city":"Fairless Hills",
    "sg:classifiers":[
        {
            "category":"Social Services",
            "subcategory":"Child Care",
            "type":"Services"
        }
    ],
    "sg:phone":"+1   ",
    "sg:postcode":"19030",
    "sg:province":"PA",
    "sg:tags":[
        "day"
    ],
    "wof:name":"Roberta Petock Group Home",
    "wof:placetype":"venue"
},
  "geometry": {"coordinates":[-74.840942,40.183862],"type":"Point"}
}