{
  "type": "Feature",
  "properties": {
    "addr:full":"1360 Industrial Hwy Ste 3 Southampton PA 18966",
    "addr:housenumber":"1360",
    "addr:postcode":"18966",
    "addr:street":"Industrial Hwy Ste 3",
    "iso:country":"US",
    "sg:address":"1360 Industrial Hwy Ste 3",
    "sg:city":"Southampton",
    "sg:classifiers":[
        {
            "category":"Autos & Motor Vehicles",
            "subcategory":"Automobile Sales",
            "type":"Retail Goods"
        },
        {
            "category":"Autos & Motor Vehicles",
            "subcategory":"Auto Supplies",
            "type":"Retail Goods"
        }
    ],
    "sg:phone":"+1 215 355 2800",
    "sg:postcode":"18966",
    "sg:province":"PA",
    "sg:tags":[
        "accessory",
        "equipment",
        "parts",
        "electrical",
        "accessories-wholesale",
        "part",
        "manufacturer"
    ],
    "sg:website":"http://www.napaonline.com",
    "wof:name":"Weldon Auto Parts Inc",
    "wof:placetype":"venue"
},
  "geometry": {"coordinates":[-75.032781,40.161425],"type":"Point"}
}