{
  "type": "Feature",
  "properties": {
    "iso:country":"US",
    "sg:address":"69 W Summit Dr",
    "sg:city":"Littlestown",
    "sg:classifiers":[
        {
            "category":"Building & Trades",
            "subcategory":"Landscaping Services",
            "type":"Services"
        }
    ],
    "sg:phone":"+1 717 359 0051",
    "sg:postcode":"17340",
    "sg:province":"PA",
    "sg:tags":[
        "tree"
    ],
    "wof:name":"Seasons Tree Svc",
    "wof:placetype":"venue"
},
  "geometry": {"coordinates":[-77.073927,39.735261],"type":"Point"}
}