{
  "type": "Feature",
  "properties": {
    "iso:country":"US",
    "sg:address":"1948 E 3rd St",
    "sg:city":"Williamsport",
    "sg:classifiers":[
        {
            "category":"Professional",
            "subcategory":"Management & Consulting",
            "type":"Services"
        }
    ],
    "sg:phone":"+1   ",
    "sg:postcode":"17701",
    "sg:province":"PA",
    "sg:tags":[
        "insurance"
    ],
    "wof:name":"Malvern Benefits Corp",
    "wof:placetype":"venue"
},
  "geometry": {"coordinates":[-76.962476,41.248564],"type":"Point"}
}