{
  "type": "Feature",
  "properties": {
    "addr:full":"228 Blvd of the Allies Pittsburgh PA 15222",
    "addr:housenumber":"228",
    "addr:postcode":"15222",
    "addr:street":"Blvd Of The Allies",
    "iso:country":"US",
    "sg:address":"228 Blvd of the Allies",
    "sg:city":"Pittsburgh",
    "sg:classifiers":[
        {
            "category":"Government",
            "subcategory":"Office",
            "type":"Public Place"
        }
    ],
    "sg:phone":"+1 412 560 7230",
    "sg:postcode":"15222",
    "sg:province":"PA",
    "sg:tags":[
        "village"
    ],
    "wof:name":"Parking Authority-Garage",
    "wof:placetype":"venue"
},
  "geometry": {"coordinates":[-80.00241699999999,40.438553],"type":"Point"}
}