{
  "type": "Feature",
  "properties": {
    "iso:country":"US",
    "sg:address":"221 Wayne Ave",
    "sg:city":"Springfield",
    "sg:classifiers":[
        {
            "category":"Recreation",
            "type":"Entertainment"
        }
    ],
    "sg:phone":"+1   ",
    "sg:postcode":"19064",
    "sg:province":"PA",
    "sg:tags":[
        "club",
        "membership"
    ],
    "wof:name":"Bore Mill Game Assoc Inc",
    "wof:placetype":"venue"
},
  "geometry": {"coordinates":[-75.323398,39.934237],"type":"Point"}
}