{
  "type": "Feature",
  "properties": {
    "addr:full":"106 Stitzer Rd Fleetwood PA 19522",
    "addr:housenumber":"106",
    "addr:postcode":"19522",
    "addr:street":"Stitzer Rd",
    "iso:country":"US",
    "sg:address":"106 Stitzer Rd",
    "sg:city":"Fleetwood",
    "sg:classifiers":[
        {
            "category":"Wholesale",
            "subcategory":"Vending Machines",
            "type":"Manufacturing & Wholesale Goods"
        }
    ],
    "sg:phone":"+1 610 944 9456",
    "sg:postcode":"19522",
    "sg:province":"PA",
    "sg:tags":[
        "operator",
        "merchandise"
    ],
    "wof:name":"Page Enterprises",
    "wof:placetype":"venue"
},
  "geometry": {"coordinates":[-75.823699,40.434319],"type":"Point"}
}