{
  "type": "Feature",
  "properties": {
    "addr:full":"1002 Main St Bethlehem PA 18018",
    "addr:housenumber":"1002",
    "addr:postcode":"18018",
    "addr:street":"Main St",
    "iso:country":"US",
    "sg:address":"1002 Main St",
    "sg:city":"Bethlehem",
    "sg:classifiers":[
        {
            "category":"Education",
            "subcategory":"School",
            "type":"Public Place"
        }
    ],
    "sg:phone":"+1 610 694 0116",
    "sg:postcode":"18018",
    "sg:province":"PA",
    "sg:tags":[
        "high",
        "middle",
        "elementary"
    ],
    "wof:name":"Bethlehem Area School District",
    "wof:placetype":"venue"
},
  "geometry": {"coordinates":[-75.381556,40.627782],"type":"Point"}
}