{
  "type": "Feature",
  "properties": {
    "iso:country":"US",
    "sg:address":"8312 State Rd Ste 9",
    "sg:city":"Philadelphia",
    "sg:classifiers":[
        {
            "category":"Building & Trades",
            "subcategory":"Equipment Rental",
            "type":"Services"
        },
        {
            "category":"Home & Garden",
            "subcategory":"Hardware",
            "type":"Retail Goods"
        }
    ],
    "sg:phone":"+1 215 941 7615",
    "sg:postcode":"19136",
    "sg:province":"PA",
    "sg:tags":[
        "furniture",
        "leasing",
        "equipment-renting",
        "store",
        "contractors'"
    ],
    "sg:website":"http://www.dependablecontractorsequipmentservice.vpweb.com",
    "wof:name":"Dependable Contractors Equipment Service",
    "wof:placetype":"venue"
},
  "geometry": {"coordinates":[-75.01652900000001,40.034157],"type":"Point"}
}