{
  "type": "Feature",
  "properties": {
    "iso:country":"US",
    "sg:address":"1601 Marys Ave",
    "sg:city":"Pittsburgh",
    "sg:classifiers":[
        {
            "category":"Building & Trades",
            "subcategory":"Construction",
            "type":"Services"
        }
    ],
    "sg:phone":"+1   ",
    "sg:postcode":"15215",
    "sg:province":"PA",
    "sg:tags":[
        "design",
        "organizer",
        "installation",
        "closet"
    ],
    "wof:name":"Closet Factory The",
    "wof:placetype":"venue"
},
  "geometry": {"coordinates":[-79.923367,40.496026],"type":"Point"}
}