{
  "type": "Feature",
  "properties": {
    "iso:country":"US",
    "sg:address":"3 N Old Trl",
    "sg:city":"Selinsgrove",
    "sg:classifiers":[
        {
            "category":"Professional",
            "type":"Services"
        }
    ],
    "sg:phone":"+1   ",
    "sg:postcode":"17870",
    "sg:province":"PA",
    "wof:name":"Truck Power Inc",
    "wof:placetype":"venue"
},
  "geometry": {"coordinates":[-76.816818,40.848012],"type":"Point"}
}