{
  "type": "Feature",
  "properties": {
    "addr:full":"215 S 5th Ave Reading PA 19611",
    "addr:housenumber":"215",
    "addr:postcode":"19611",
    "addr:street":"S 5Th Ave",
    "iso:country":"US",
    "sg:address":"215 S 5th Ave",
    "sg:city":"Reading",
    "sg:classifiers":[
        {
            "category":"Building & Trades",
            "subcategory":"Construction",
            "type":"Services"
        },
        {
            "category":"Home & Garden",
            "subcategory":"Carpets & Floor Coverings",
            "type":"Retail Goods"
        }
    ],
    "sg:phone":"+1 800 394 3064",
    "sg:postcode":"19611",
    "sg:province":"PA",
    "sg:tags":[
        "material",
        "tile-contractors",
        "rug",
        "flooring",
        "contractor"
    ],
    "sg:website":"http://www.filitrac.com/Click.aspx?tid=BDEDC5D5EF8BAE3541B5938870DA3DDECE60F60FEE115906&FiliAff=15016&sid=99202&utm_source=YellowPages&utm_medium=ppc&utm_campaign=national&utm_term=19611",
    "wof:name":"Berks Carpet One Floor & Home",
    "wof:placetype":"venue"
},
  "geometry": {"coordinates":[-75.947929,40.332939],"type":"Point"}
}