{
  "type": "Feature",
  "properties": {
    "iso:country":"US",
    "sg:address":"1 Bessemer Ave",
    "sg:city":"Lyndora",
    "sg:classifiers":[
        {
            "category":"Bars & Pubs",
            "type":"Food & Drink"
        }
    ],
    "sg:phone":"+1 724 282 1369",
    "sg:postcode":"16045",
    "sg:province":"PA",
    "sg:tags":[
        "tavern"
    ],
    "wof:name":"Bessemer Inn Inc",
    "wof:placetype":"venue"
},
  "geometry": {"coordinates":[-79.91248299999999,40.849063],"type":"Point"}
}