{
  "type": "Feature",
  "properties": {
    "addr:full":"56 Peacock Dr Lancaster PA 17601",
    "addr:housenumber":"56",
    "addr:postcode":"17601",
    "addr:street":"Peacock Dr",
    "iso:country":"US",
    "sg:address":"56 Peacock Dr",
    "sg:city":"Lancaster",
    "sg:classifiers":[
        {
            "category":"Professional",
            "subcategory":"Business Services",
            "type":"Services"
        }
    ],
    "sg:phone":"+1 717 898 9522",
    "sg:postcode":"17601",
    "sg:province":"PA",
    "sg:tags":[
        "foreground",
        "music"
    ],
    "wof:name":"Circuit Shop",
    "wof:placetype":"venue"
},
  "geometry": {"coordinates":[-76.393244,40.055356],"type":"Point"}
}