{
  "type": "Feature",
  "properties": {
    "iso:country":"US",
    "sg:address":"1208 Mason Ave",
    "sg:city":"Upper Darby",
    "sg:classifiers":[
        {
            "category":"Manufacturing",
            "subcategory":"Retail Goods",
            "type":"Manufacturing & Wholesale Goods"
        }
    ],
    "sg:phone":"+1 484 452 6286",
    "sg:postcode":"19026",
    "sg:province":"PA",
    "sg:tags":[
        "manufacturer"
    ],
    "wof:name":"Graphix Factory Inc",
    "wof:placetype":"venue"
},
  "geometry": {"coordinates":[-75.30702599999999,39.96052],"type":"Point"}
}