{
  "type": "Feature",
  "properties": {
    "iso:country":"US",
    "sg:address":"1030 Macdade Blvd ",
    "sg:city":"Darby",
    "sg:classifiers":[
        {
            "category":"Restaurant",
            "type":"Food & Drink"
        }
    ],
    "sg:menulink":"http://www.allmenus.com/pa/collingdale/291540-menas-kitchen-family-restaurant/menu/",
    "sg:phone":"+1 484 494 0097",
    "sg:postcode":"19023",
    "sg:province":"PA",
    "sg:tags":[
        "burger",
        "seafood",
        "sandwich"
    ],
    "wof:name":"Mena's Kitchen Family Restaurant",
    "wof:placetype":"venue"
},
  "geometry": {"coordinates":[-75.281632,39.909675],"type":"Point"}
}