{
  "type": "Feature",
  "properties": {
    "iso:country":"US",
    "sg:address":"124 Chestnut St",
    "sg:city":"Philadelphia",
    "sg:classifiers":[
        {
            "category":"Building & Trades",
            "subcategory":"Cleaning & Sanitation",
            "type":"Services"
        }
    ],
    "sg:phone":"+1 215 925 5277",
    "sg:postcode":"19106",
    "sg:province":"PA",
    "sg:tags":[
        "janitor"
    ],
    "wof:name":"Kasscon Cleaning Svc",
    "wof:placetype":"venue"
},
  "geometry": {"coordinates":[-75.144047,39.948296],"type":"Point"}
}