{
  "type": "Feature",
  "properties": {
    "iso:country":"US",
    "sg:address":"204 Raymond Dr",
    "sg:city":"Jermyn",
    "sg:classifiers":[
        {
            "category":"Building & Trades",
            "subcategory":"Construction",
            "type":"Services"
        }
    ],
    "sg:phone":"+1 570 876 5676",
    "sg:postcode":"18433",
    "sg:province":"PA",
    "sg:tags":[
        "wallcoverings-installation",
        "wallpaper",
        "painting",
        "contractor"
    ],
    "wof:name":"Monster Painters",
    "wof:placetype":"venue"
},
  "geometry": {"coordinates":[-75.55294600000001,41.532444],"type":"Point"}
}