{
  "type": "Feature",
  "properties": {
    "iso:country":"US",
    "sg:address":"2445 N Delaware Dr",
    "sg:city":"Easton",
    "sg:classifiers":[
        {
            "category":"Building & Trades",
            "subcategory":"Construction",
            "type":"Services"
        }
    ],
    "sg:phone":"+1 610 252 2300",
    "sg:postcode":"18040",
    "sg:province":"PA",
    "sg:tags":[
        "contractor"
    ],
    "wof:name":"Gerald Adsit Construction",
    "wof:placetype":"venue"
},
  "geometry": {"coordinates":[-75.187471,40.726014],"type":"Point"}
}