{
  "type": "Feature",
  "properties": {
    "addr:full":"1327 Lindley Ave Philadelphia PA 19141",
    "addr:housenumber":"1327",
    "addr:postcode":"19141",
    "addr:street":"Lindley Ave",
    "iso:country":"US",
    "sg:address":"1327 Lindley Ave",
    "sg:city":"Philadelphia",
    "sg:classifiers":[
        {
            "category":"Professional",
            "type":"Services"
        }
    ],
    "sg:phone":"+1 215 329 3408",
    "sg:postcode":"19141",
    "sg:province":"PA",
    "sg:tags":[
        "establishment"
    ],
    "wof:name":"M A F Systems",
    "wof:placetype":"venue"
},
  "geometry": {"coordinates":[-75.146024,40.030368],"type":"Point"}
}