{
  "type": "Feature",
  "properties": {
    "addr:full":"402 McFarlan Rd Ste 302 Kennett Square PA 19348",
    "addr:housenumber":"402",
    "addr:postcode":"19348",
    "addr:street":"Mcfarlan Rd Ste 302",
    "iso:country":"US",
    "sg:address":"402 McFarlan Rd Ste 302",
    "sg:city":"Kennett Square",
    "sg:classifiers":[
        {
            "category":"Health Services",
            "subcategory":"Doctor",
            "type":"Services"
        }
    ],
    "sg:phone":"+1 610 444 7455",
    "sg:postcode":"19348",
    "sg:province":"PA",
    "wof:name":"Surgical Specialist",
    "wof:placetype":"venue"
},
  "geometry": {"coordinates":[-75.693364,39.855293],"type":"Point"}
}