{
  "type": "Feature",
  "properties": {
    "iso:country":"US",
    "sg:address":"725 N 6th St",
    "sg:city":"Philadelphia",
    "sg:classifiers":[
        {
            "category":"Recreation",
            "type":"Entertainment"
        },
        {
            "category":"Sports & Exercise",
            "subcategory":"Gym",
            "type":"Entertainment"
        }
    ],
    "sg:phone":"+1 215 238 0771",
    "sg:postcode":"19123",
    "sg:province":"PA",
    "sg:tags":[
        "judo",
        "instr",
        "facility",
        "karate",
        "fitness",
        "physical"
    ],
    "wof:name":"Urban Defense Fitness Center",
    "wof:placetype":"venue"
},
  "geometry": {"coordinates":[-75.1476,39.964262],"type":"Point"}
}