{
  "type": "Feature",
  "properties": {
    "iso:country":"US",
    "sg:address":"240 Allegheny Blvd",
    "sg:city":"Brookville",
    "sg:classifiers":[
        {
            "category":"Health Services",
            "subcategory":"Doctor",
            "type":"Services"
        }
    ],
    "sg:phone":"+1 814 849 2022",
    "sg:postcode":"15825",
    "sg:province":"PA",
    "sg:tags":[
        "physician",
        "surgeon"
    ],
    "wof:name":"Creston Baumunk MD",
    "wof:placetype":"venue"
},
  "geometry": {"coordinates":[-79.098223,41.174775],"type":"Point"}
}