{
  "type": "Feature",
  "properties": {
    "iso:country":"US",
    "sg:address":"136 Jaycee Dr Ste 40",
    "sg:city":"Johnstown",
    "sg:classifiers":[
        {
            "category":"Insurance",
            "subcategory":"Hazard Insurance",
            "type":"Services"
        }
    ],
    "sg:phone":"+1 814 467 1888",
    "sg:postcode":"15904",
    "sg:province":"PA",
    "sg:tags":[
        "commercial",
        "business"
    ],
    "sg:website":"http://www.erieinsurance.com",
    "wof:name":"Erie Insurance Exchange",
    "wof:placetype":"venue"
},
  "geometry": {"coordinates":[-78.84926,40.25993],"type":"Point"}
}