{
  "type": "Feature",
  "properties": {
    "iso:country":"US",
    "sg:address":"723 E Railroad Ave",
    "sg:city":"Verona",
    "sg:classifiers":[
        {
            "category":"Wholesale",
            "subcategory":"Groceries",
            "type":"Manufacturing & Wholesale Goods"
        }
    ],
    "sg:phone":"+1 412 828 7510",
    "sg:postcode":"15147",
    "sg:province":"PA",
    "sg:tags":[
        "grocers-wholesale"
    ],
    "sg:website":"http://www.hthackney.com",
    "wof:name":"H. T. Hackney Co. (The)",
    "wof:placetype":"venue"
},
  "geometry": {"coordinates":[-79.844294,40.505293],"type":"Point"}
}