{
  "type": "Feature",
  "properties": {
    "iso:country":"US",
    "sg:address":"25 Monument Rd",
    "sg:city":"York",
    "sg:classifiers":[
        {
            "category":"Health Services",
            "subcategory":"Doctor",
            "type":"Services"
        }
    ],
    "sg:phone":"+1 717 851 2443",
    "sg:postcode":"17403",
    "sg:province":"PA",
    "sg:tags":[
        "physician",
        "surgeon"
    ],
    "wof:name":"Urogynecology",
    "wof:placetype":"venue"
},
  "geometry": {"coordinates":[-76.717809,39.922992],"type":"Point"}
}