{
  "type": "Feature",
  "properties": {
    "addr:full":"342 E Girard Ave Philadelphia PA 19125",
    "addr:housenumber":"342",
    "addr:postcode":"19125",
    "addr:street":"E Girard Ave",
    "iso:country":"US",
    "sg:address":"342 E Girard Ave",
    "sg:city":"Philadelphia",
    "sg:classifiers":[
        {
            "category":"Building & Trades",
            "subcategory":"Locksmith",
            "type":"Services"
        }
    ],
    "sg:phone":"+1 215 525 5988",
    "sg:postcode":"19125",
    "sg:province":"PA",
    "sg:tags":[
        "key"
    ],
    "wof:name":"Aaron Locksmith",
    "wof:placetype":"venue"
},
  "geometry": {"coordinates":[-75.130853,39.969899],"type":"Point"}
}