{
  "type": "Feature",
  "properties": {
    "iso:country":"US",
    "sg:address":"7420 Sycamore Ave",
    "sg:city":"Elkins Park",
    "sg:classifiers":[
        {
            "category":"Recreation",
            "type":"Entertainment"
        }
    ],
    "sg:phone":"+1 215 635 3255",
    "sg:postcode":"19027",
    "sg:province":"PA",
    "sg:tags":[
        "center"
    ],
    "wof:name":"LA Mott Community Ctr",
    "wof:placetype":"venue"
},
  "geometry": {"coordinates":[-75.14137700000001,40.067302],"type":"Point"}
}