{
  "type": "Feature",
  "properties": {
    "iso:country":"US",
    "sg:address":"2072 Pittsburgh Rd",
    "sg:city":"Smock",
    "sg:classifiers":[
        {
            "category":"Bars & Pubs",
            "type":"Food & Drink"
        },
        {
            "category":"Restaurant",
            "type":"Food & Drink"
        }
    ],
    "sg:phone":"+1 724 677 9983",
    "sg:postcode":"15480",
    "sg:province":"PA",
    "sg:tags":[
        "tavern"
    ],
    "wof:name":"White Tavern",
    "wof:placetype":"venue"
},
  "geometry": {"coordinates":[-79.763747,39.997042],"type":"Point"}
}