{
  "type": "Feature",
  "properties": {
    "addr:full":"215 E Penn St Bedford PA 15522",
    "addr:housenumber":"215",
    "addr:postcode":"15522",
    "addr:street":"E Penn St",
    "iso:country":"US",
    "sg:address":"215 E Penn St",
    "sg:city":"Bedford",
    "sg:classifiers":[
        {
            "category":"Organizations",
            "subcategory":"Religious Organization",
            "type":"Services"
        }
    ],
    "sg:phone":"+1 814 623 5526",
    "sg:postcode":"15522",
    "sg:province":"PA",
    "sg:tags":[
        "church"
    ],
    "wof:name":"St Thomas Catholic Church",
    "wof:placetype":"venue"
},
  "geometry": {"coordinates":[-78.501509,40.01761],"type":"Point"}
}