{
  "type": "Feature",
  "properties": {
    "iso:country":"US",
    "sg:address":"109 Windswept Dr",
    "sg:city":"Feastervl Trvs",
    "sg:classifiers":[
        {
            "category":"Health Services",
            "subcategory":"Medical Lab",
            "type":"Services"
        }
    ],
    "sg:phone":"+1 215 396 7770",
    "sg:postcode":"19053",
    "sg:province":"PA",
    "sg:tags":[
        "laboratory",
        "dental"
    ],
    "wof:name":"Perfect Fit Dental Lab Inc",
    "wof:placetype":"venue"
},
  "geometry": {"coordinates":[-75.007752,40.139699],"type":"Point"}
}