{
  "type": "Feature",
  "properties": {
    "addr:full":"308 Shughart Ave Boiling Springs PA 17007",
    "addr:housenumber":"308",
    "addr:postcode":"17007",
    "addr:street":"Shughart Ave",
    "iso:country":"US",
    "sg:address":"308 Shughart Ave",
    "sg:city":"Boiling Springs",
    "sg:classifiers":[
        {
            "category":"Retail",
            "subcategory":"Animal Services",
            "type":"Services"
        }
    ],
    "sg:phone":"+1 717 258 5054",
    "sg:postcode":"17007",
    "sg:province":"PA",
    "sg:tags":[
        "pet",
        "grooming",
        "washing"
    ],
    "wof:name":"K-9 Image",
    "wof:placetype":"venue"
},
  "geometry": {"coordinates":[-77.140004,40.15649],"type":"Point"}
}