{
  "type": "Feature",
  "properties": {
    "iso:country":"US",
    "sg:address":"206 Pennsylvania Ave",
    "sg:city":"Matamoras",
    "sg:classifiers":[
        {
            "category":"Wholesale",
            "subcategory":"Office Equipment",
            "type":"Manufacturing & Wholesale Goods"
        }
    ],
    "sg:phone":"+1 570 491 4573",
    "sg:postcode":"18336",
    "sg:province":"PA",
    "sg:tags":[
        "vault",
        "safe"
    ],
    "wof:name":"Michelson Locksmith",
    "wof:placetype":"venue"
},
  "geometry": {"coordinates":[-74.69939100000001,41.369471],"type":"Point"}
}