{
  "type": "Feature",
  "properties": {
    "addr:full":"98 Madison Ave Herminie PA 15637",
    "addr:housenumber":"98",
    "addr:postcode":"15637",
    "addr:street":"Madison Ave",
    "iso:country":"US",
    "sg:address":"98 Madison Ave",
    "sg:city":"Herminie",
    "sg:classifiers":[
        {
            "category":"Organizations",
            "subcategory":"Community Association",
            "type":"Services"
        }
    ],
    "sg:phone":"+1 724 446 9955",
    "sg:postcode":"15637",
    "sg:province":"PA",
    "sg:tags":[
        "club"
    ],
    "wof:name":"Loyal Order Of Moose",
    "wof:placetype":"venue"
},
  "geometry": {"coordinates":[-79.71728899999999,40.262446],"type":"Point"}
}