{
  "type": "Feature",
  "properties": {
    "addr:full":"2605 Columbia Blvd Bloomsburg PA 17815",
    "addr:housenumber":"2605",
    "addr:postcode":"17815",
    "addr:street":"Columbia Blvd",
    "iso:country":"US",
    "sg:address":"2605 Columbia Blvd",
    "sg:city":"Bloomsburg",
    "sg:classifiers":[
        {
            "category":"Shopping",
            "subcategory":"Department Store",
            "type":"Retail Goods"
        }
    ],
    "sg:phone":"+1 570 389 5750",
    "sg:postcode":"17815",
    "sg:province":"PA",
    "wof:name":"Wal-Mart",
    "wof:placetype":"venue"
},
  "geometry": {"coordinates":[-76.40716500000001,41.013095],"type":"Point"}
}