{
  "type": "Feature",
  "properties": {
    "iso:country":"US",
    "sg:address":"275 Mundy St",
    "sg:city":"Wilkes Barre",
    "sg:classifiers":[
        {
            "category":"Real Estate",
            "subcategory":"Real Estate Services",
            "type":"Services"
        }
    ],
    "sg:phone":"+1 570 821 4600",
    "sg:postcode":"18702",
    "sg:province":"PA",
    "sg:tags":[
        "loan",
        "title",
        "company",
        "abstract",
        "broker"
    ],
    "wof:name":"Tiger Abstract Inc",
    "wof:placetype":"venue"
},
  "geometry": {"coordinates":[-75.842124,41.243019],"type":"Point"}
}