{
  "type": "Feature",
  "properties": {
    "iso:country":"US",
    "sg:address":"683 Dick Rd",
    "sg:city":"Greenville",
    "sg:classifiers":[
        {
            "category":"Retail",
            "subcategory":"Repair Shop",
            "type":"Services"
        }
    ],
    "sg:phone":"+1 724 588 9426",
    "sg:postcode":"16125",
    "sg:province":"PA",
    "sg:tags":[
        "taxidermist"
    ],
    "wof:name":"Long's Taxidermy",
    "wof:placetype":"venue"
},
  "geometry": {"coordinates":[-80.28913900000001,41.463008],"type":"Point"}
}