{
  "type": "Feature",
  "properties": {
    "addr:full":"25032 Hwy 98 Springboro PA 16433",
    "addr:housenumber":"25032",
    "addr:postcode":"16433",
    "addr:street":"Hwy 98",
    "iso:country":"US",
    "sg:address":"25032 Hwy 98",
    "sg:city":"Springboro",
    "sg:classifiers":[
        {
            "category":"Retail",
            "subcategory":"Auto Repair",
            "type":"Services"
        }
    ],
    "sg:phone":"+1 814 763 4151",
    "sg:postcode":"16433",
    "sg:province":"PA",
    "sg:tags":[
        "repairing",
        "automobile"
    ],
    "wof:name":"Sunny Valley Garage",
    "wof:placetype":"venue"
},
  "geometry": {"coordinates":[-80.244693,41.824966],"type":"Point"}
}