{
  "type": "Feature",
  "properties": {
    "iso:country":"US",
    "sg:address":"22631 Rte 68",
    "sg:city":"Clarion",
    "sg:classifiers":[
        {
            "category":"Personal",
            "subcategory":"Beauty Salon",
            "type":"Services"
        }
    ],
    "sg:phone":"+1 814 226 4181",
    "sg:postcode":"16214",
    "sg:province":"PA",
    "wof:name":"Styling Salon",
    "wof:placetype":"venue"
},
  "geometry": {"coordinates":[-79.39230499999999,41.194777],"type":"Point"}
}