{
  "type": "Feature",
  "properties": {
    "iso:country":"US",
    "sg:address":"200 S Broad St",
    "sg:city":"Philadelphia",
    "sg:classifiers":[
        {
            "category":"Organizations",
            "subcategory":"Professional Association",
            "type":"Services"
        }
    ],
    "sg:phone":"+1   ",
    "sg:postcode":"19102",
    "sg:province":"PA",
    "sg:tags":[
        "arts",
        "business",
        "council"
    ],
    "wof:name":"Arts Bus Cncil Grter Phldlphia",
    "wof:placetype":"venue"
},
  "geometry": {"coordinates":[-75.164468,39.948733],"type":"Point"}
}