{
  "type": "Feature",
  "properties": {
    "iso:country":"US",
    "sg:address":"1699 Spring Garden St",
    "sg:city":"Philadelphia",
    "sg:classifiers":[
        {
            "category":"Education",
            "subcategory":"School",
            "type":"Public Place"
        }
    ],
    "sg:postcode":"19130",
    "sg:province":"PA",
    "sg:tags":[
        "high",
        "middle"
    ],
    "sg:website":"masterman.phila.k12.pa.us",
    "wof:name":"J. R. Masterman Laboratory and Preparation School",
    "wof:placetype":"venue"
},
  "geometry": {"coordinates":[-75.16622099999999,39.963104],"type":"Point"}
}