{
  "type": "Feature",
  "properties": {
    "iso:country":"US",
    "sg:address":"1545 Pinehurst Dr",
    "sg:city":"Pittsburgh",
    "sg:classifiers":[
        {
            "category":"Restaurant",
            "type":"Food & Drink"
        }
    ],
    "sg:phone":"+1 412 973 3442",
    "sg:postcode":"15241",
    "sg:province":"PA",
    "wof:name":"Ham Heavenly",
    "wof:placetype":"venue"
},
  "geometry": {"coordinates":[-80.084091,40.34657],"type":"Point"}
}