{
  "type": "Feature",
  "properties": {
    "addr:full":"352 3rd St California PA 15419",
    "addr:housenumber":"352",
    "addr:postcode":"15419",
    "addr:street":"3Rd St",
    "iso:country":"US",
    "sg:address":"352 3rd St",
    "sg:city":"California",
    "sg:classifiers":[
        {
            "category":"Restaurant",
            "type":"Food & Drink"
        }
    ],
    "sg:menulink":"http://www.allmenus.com/pa/california/133323-subway/menu/",
    "sg:phone":"+1 724 938 8338",
    "sg:postcode":"15419",
    "sg:province":"PA",
    "sg:tags":[
        "american",
        "sandwich"
    ],
    "wof:name":"Subway",
    "wof:placetype":"venue"
},
  "geometry": {"coordinates":[-79.89060000000001,40.066541],"type":"Point"}
}