{
  "type": "Feature",
  "properties": {
    "iso:country":"US",
    "sg:address":"4103 W Weaver Rd",
    "sg:city":"Greencastle",
    "sg:classifiers":[
        {
            "category":"Retail",
            "subcategory":"Repair Shop",
            "type":"Services"
        },
        {
            "category":"Building & Trades",
            "subcategory":"Plumbing",
            "type":"Services"
        }
    ],
    "sg:phone":"+1 717 597 8663",
    "sg:postcode":"17225",
    "sg:province":"PA",
    "sg:tags":[
        "septic"
    ],
    "wof:name":"S R Daley & Sons",
    "wof:placetype":"venue"
},
  "geometry": {"coordinates":[-77.79519000000001,39.771788],"type":"Point"}
}