{
  "type": "Feature",
  "properties": {
    "iso:country":"US",
    "sg:address":"4616 Allegheny River Blvd",
    "sg:city":"Verona",
    "sg:classifiers":[
        {
            "category":"Insurance",
            "subcategory":"Hazard Insurance",
            "type":"Services"
        }
    ],
    "sg:phone":"+1 412 793 3367",
    "sg:postcode":"15147",
    "sg:province":"PA",
    "sg:tags":[
        "commercial",
        "business"
    ],
    "wof:name":"Turain Enterprises Inc",
    "wof:placetype":"venue"
},
  "geometry": {"coordinates":[-79.842678,40.50827],"type":"Point"}
}