{
  "type": "Feature",
  "properties": {
    "iso:country":"US",
    "sg:address":"260 N 7th St",
    "sg:city":"Chambersburg",
    "sg:classifiers":[
        {
            "category":"Health Services",
            "subcategory":"Hospital",
            "type":"Services"
        }
    ],
    "sg:phone":"+1 717 262 4660",
    "sg:postcode":"17201",
    "sg:province":"PA",
    "sg:tags":[
        "treatment",
        "cancer",
        "center"
    ],
    "wof:name":"Summit Cancer Svc",
    "wof:placetype":"venue"
},
  "geometry": {"coordinates":[-77.646055,39.936891],"type":"Point"}
}