{
  "type": "Feature",
  "properties": {
    "iso:country":"US",
    "sg:address":"1 Dietz Pl",
    "sg:city":"Clarion",
    "sg:classifiers":[
        {
            "category":"Government",
            "subcategory":"Office",
            "type":"Public Place"
        }
    ],
    "sg:phone":"+1 814 226 4122",
    "sg:postcode":"16214",
    "sg:province":"PA",
    "wof:name":"Clarion County Infant Program",
    "wof:placetype":"venue"
},
  "geometry": {"coordinates":[-79.383079,41.213691],"type":"Point"}
}