{
  "type": "Feature",
  "properties": {
    "iso:country":"US",
    "sg:address":"145 W 5th St",
    "sg:city":"Lansdale",
    "sg:classifiers":[
        {
            "category":"Wholesale",
            "subcategory":"Plants",
            "type":"Manufacturing & Wholesale Goods"
        }
    ],
    "sg:phone":"+1 215 362 2828",
    "sg:postcode":"19446",
    "sg:province":"PA",
    "sg:tags":[
        "florist",
        "supply"
    ],
    "wof:name":"Younger & Son Inc",
    "wof:placetype":"venue"
},
  "geometry": {"coordinates":[-75.2826,40.246201],"type":"Point"}
}