{
  "type": "Feature",
  "properties": {
    "iso:country":"US",
    "sg:address":"1745 South St",
    "sg:city":"Philadelphia",
    "sg:classifiers":[
        {
            "category":"Shopping",
            "subcategory":"Pharmacy",
            "type":"Retail Goods"
        }
    ],
    "sg:phone":"+1 215 546 3479",
    "sg:postcode":"19146",
    "sg:province":"PA",
    "sg:tags":[
        "drugstore"
    ],
    "wof:name":"D & H Professional Pharmaci Es",
    "wof:placetype":"venue"
},
  "geometry": {"coordinates":[-75.17179899999999,39.944302],"type":"Point"}
}