{
  "type": "Feature",
  "properties": {
    "iso:country":"US",
    "sg:address":"107 Majestic Dr",
    "sg:city":"Mars",
    "sg:classifiers":[
        {
            "category":"Professional",
            "subcategory":"Lawyer & Legal Services",
            "type":"Services"
        }
    ],
    "sg:phone":"+1 724 625 1662",
    "sg:postcode":"16046",
    "sg:province":"PA",
    "wof:name":"Viola Rocco Jr Atty",
    "wof:placetype":"venue"
},
  "geometry": {"coordinates":[-80.053011,40.713426],"type":"Point"}
}