{
  "type": "Feature",
  "properties": {
    "iso:country":"US",
    "sg:address":"3595 Lemar Rd",
    "sg:city":"Mercersburg",
    "sg:classifiers":[
        {
            "category":"Building & Trades",
            "subcategory":"Construction",
            "type":"Services"
        }
    ],
    "sg:phone":"+1   ",
    "sg:postcode":"17236",
    "sg:province":"PA",
    "wof:name":"Clever & Son",
    "wof:placetype":"venue"
},
  "geometry": {"coordinates":[-77.870424,39.873101],"type":"Point"}
}