{
  "type": "Feature",
  "properties": {
    "iso:country":"US",
    "sg:address":"4013 Scotland Main St",
    "sg:city":"Scotland",
    "sg:classifiers":[
        {
            "category":"Retail",
            "subcategory":"Auto Repair",
            "type":"Services"
        }
    ],
    "sg:phone":"+1 717 263 1442",
    "sg:postcode":"17254",
    "sg:province":"PA",
    "sg:tags":[
        "automobile",
        "inspection"
    ],
    "wof:name":"Eddie's Automotive",
    "wof:placetype":"venue"
},
  "geometry": {"coordinates":[-77.587064,39.971168],"type":"Point"}
}