{
  "type": "Feature",
  "properties": {
    "iso:country":"US",
    "sg:address":"1450 Ben Franklin Hwy E",
    "sg:city":"Douglassville",
    "sg:classifiers":[
        {
            "category":"Science Facility",
            "type":"Public Place"
        }
    ],
    "sg:phone":"+1 610 705 1780",
    "sg:postcode":"19518",
    "sg:province":"PA",
    "sg:tags":[
        "development",
        "laboratories-research"
    ],
    "wof:name":"Advanced Fiber Technologies Inc",
    "wof:placetype":"venue"
},
  "geometry": {"coordinates":[-75.720596,40.254459],"type":"Point"}
}