{
  "type": "Feature",
  "properties": {
    "iso:country":"US",
    "sg:address":"1000 Dorothy St",
    "sg:city":"Coraopolis",
    "sg:classifiers":[
        {
            "category":"Real Estate",
            "subcategory":"Real Estate Operator",
            "type":"Services"
        }
    ],
    "sg:phone":"+1 412 331 3132",
    "sg:postcode":"15108",
    "sg:province":"PA",
    "sg:tags":[
        "building",
        "apartment"
    ],
    "wof:name":"Acadia Court Apartments",
    "wof:placetype":"venue"
},
  "geometry": {"coordinates":[-80.105564,40.482153],"type":"Point"}
}