{
  "type": "Feature",
  "properties": {
    "iso:country":"US",
    "sg:address":"1030 6th Ave",
    "sg:city":"Steelton",
    "sg:classifiers":[
        {
            "category":"Building & Trades",
            "subcategory":"Cleaning & Sanitation",
            "type":"Services"
        }
    ],
    "sg:phone":"+1 717 986 1171",
    "sg:postcode":"17113",
    "sg:province":"PA",
    "wof:name":"Absolute Pressure Cleaning",
    "wof:placetype":"venue"
},
  "geometry": {"coordinates":[-76.824839,40.241585],"type":"Point"}
}