{
  "type": "Feature",
  "properties": {
    "addr:full":"124 Legion Rd Bloomsburg PA 17815",
    "addr:housenumber":"124",
    "addr:postcode":"17815",
    "addr:street":"Legion Rd",
    "iso:country":"US",
    "sg:address":"124 Legion Rd",
    "sg:city":"Bloomsburg",
    "sg:classifiers":[
        {
            "category":"Building & Trades",
            "subcategory":"Construction",
            "type":"Services"
        }
    ],
    "sg:phone":"+1   ",
    "sg:postcode":"17815",
    "sg:province":"PA",
    "sg:tags":[
        "hanging",
        "contractor"
    ],
    "wof:name":"PA Painting and Wall Covering",
    "wof:placetype":"venue"
},
  "geometry": {"coordinates":[-76.478922,40.953172],"type":"Point"}
}