{
  "type": "Feature",
  "properties": {
    "iso:country":"US",
    "sg:address":"119 Lloyd Rd",
    "sg:city":"West Grove",
    "sg:classifiers":[
        {
            "category":"Professional",
            "type":"Services"
        }
    ],
    "sg:phone":"+1 610 869 3300",
    "sg:postcode":"19390",
    "sg:province":"PA",
    "sg:tags":[
        "establishment"
    ],
    "wof:name":"Chatham Instruments Inc",
    "wof:placetype":"venue"
},
  "geometry": {"coordinates":[-75.829926,39.847066],"type":"Point"}
}