{
  "type": "Feature",
  "properties": {
    "iso:country":"US",
    "sg:address":"6014 Steubenville Pike",
    "sg:city":"Mc Kees Rocks",
    "sg:classifiers":[
        {
            "category":"Building & Trades",
            "subcategory":"Construction",
            "type":"Services"
        }
    ],
    "sg:phone":"+1 412 787 7400",
    "sg:postcode":"15136",
    "sg:province":"PA",
    "sg:tags":[
        "handyman"
    ],
    "wof:name":"Case Handyman Svc-Pittsburgh",
    "wof:placetype":"venue"
},
  "geometry": {"coordinates":[-80.144977,40.44477],"type":"Point"}
}