{
  "type": "Feature",
  "properties": {
    "iso:country":"US",
    "sg:address":"7591 Lake Raystown Shopping Center",
    "sg:city":"Huntingdon",
    "sg:classifiers":[
        {
            "category":"Professional",
            "type":"Services"
        }
    ],
    "sg:phone":"+1   ",
    "sg:postcode":"16652",
    "sg:province":"PA",
    "wof:name":"Libby Hl Corp",
    "wof:placetype":"venue"
},
  "geometry": {"coordinates":[-78.009148,40.478328],"type":"Point"}
}