{
  "type": "Feature",
  "properties": {
    "iso:country":"US",
    "sg:address":"336 E Penn Ave",
    "sg:city":"Robesonia",
    "sg:classifiers":[
        {
            "category":"Professional",
            "subcategory":"Employment Agencies",
            "type":"Services"
        }
    ],
    "sg:phone":"+1 610 693 1158",
    "sg:postcode":"19551",
    "sg:province":"PA",
    "sg:tags":[
        "labor",
        "contractor"
    ],
    "wof:name":"Labor Management Svc",
    "wof:placetype":"venue"
},
  "geometry": {"coordinates":[-76.130111,40.350187],"type":"Point"}
}