{
  "type": "Feature",
  "properties": {
    "iso:country":"US",
    "sg:address":"4927 William Flynn Hwy",
    "sg:city":"Allison Park",
    "sg:classifiers":[
        {
            "category":"Health Services",
            "subcategory":"Doctor",
            "type":"Services"
        }
    ],
    "sg:phone":"+1 724 444 0444",
    "sg:postcode":"15101",
    "sg:province":"PA",
    "sg:tags":[
        "physician",
        "surgeon"
    ],
    "wof:name":"Shadyside Medical Assoc",
    "wof:placetype":"venue"
},
  "geometry": {"coordinates":[-79.947852,40.59279],"type":"Point"}
}