{
  "type": "Feature",
  "properties": {
    "iso:country":"US",
    "sg:address":"312 Washington Ave",
    "sg:city":"Downingtown",
    "sg:classifiers":[
        {
            "category":"Building & Trades",
            "subcategory":"Landscaping Services",
            "type":"Services"
        }
    ],
    "sg:phone":"+1 610 269 4114",
    "sg:postcode":"19335",
    "sg:province":"PA",
    "sg:tags":[
        "landscape",
        "contractor"
    ],
    "wof:name":"Vince Mazzula Lawn Svc",
    "wof:placetype":"venue"
},
  "geometry": {"coordinates":[-75.696684,40.008533],"type":"Point"}
}