{
  "type": "Feature",
  "properties": {
    "addr:full":"1413 Jacobsburg Rd Wind Gap PA 18091",
    "addr:housenumber":"1413",
    "addr:postcode":"18091",
    "addr:street":"Jacobsburg Rd",
    "iso:country":"US",
    "sg:address":"1413 Jacobsburg Rd",
    "sg:city":"Wind Gap",
    "sg:classifiers":[
        {
            "category":"Professional",
            "subcategory":"Business Services",
            "type":"Services"
        }
    ],
    "sg:phone":"+1 610 863 2880",
    "sg:postcode":"18091",
    "sg:province":"PA",
    "sg:tags":[
        "notary"
    ],
    "wof:name":"Gordon Notary Svc",
    "wof:placetype":"venue"
},
  "geometry": {"coordinates":[-75.30069,40.831382],"type":"Point"}
}