{
  "type": "Feature",
  "properties": {
    "iso:country":"US",
    "sg:address":"80 N Main St",
    "sg:city":"Red Lion",
    "sg:classifiers":[
        {
            "category":"Retail",
            "subcategory":"Auto Repair",
            "type":"Services"
        }
    ],
    "sg:phone":"+1 717 246 1847",
    "sg:postcode":"17356",
    "sg:province":"PA",
    "sg:tags":[
        "repairing",
        "automobile",
        "general"
    ],
    "wof:name":"Channell's Garage",
    "wof:placetype":"venue"
},
  "geometry": {"coordinates":[-76.606217,39.900953],"type":"Point"}
}