{
  "type": "Feature",
  "properties": {
    "iso:country":"US",
    "sg:address":"4000 Orangemans Rd",
    "sg:city":"Willow Grove",
    "sg:classifiers":[
        {
            "category":"Professional",
            "type":"Services"
        }
    ],
    "sg:phone":"+1 215 674 4296",
    "sg:postcode":"19040",
    "sg:province":"PA",
    "sg:tags":[
        "establishment"
    ],
    "wof:name":"Montco Teacher's Fed Cu",
    "wof:placetype":"venue"
},
  "geometry": {"coordinates":[-75.086415,40.171465],"type":"Point"}
}