{
  "type": "Feature",
  "properties": {
    "addr:full":"1835 Golden Mile Hwy Plum PA 15239",
    "addr:housenumber":"1835",
    "addr:postcode":"15239",
    "addr:street":"Golden Mile Hwy",
    "iso:country":"US",
    "sg:address":"1835 Golden Mile Hwy",
    "sg:city":"Plum",
    "sg:classifiers":[
        {
            "category":"Retail",
            "subcategory":"Animal Services",
            "type":"Services"
        }
    ],
    "sg:phone":"+1 724 327 7734",
    "sg:postcode":"15239",
    "sg:province":"PA",
    "sg:tags":[
        "pet",
        "grooming",
        "washing"
    ],
    "wof:name":"Hound Haven Complete Pet Groom",
    "wof:placetype":"venue"
},
  "geometry": {"coordinates":[-79.712754,40.452685],"type":"Point"}
}