{
  "type": "Feature",
  "properties": {
    "iso:country":"US",
    "sg:address":"1401 Newton Rd",
    "sg:city":"Lancaster",
    "sg:classifiers":[
        {
            "category":"Manufacturing",
            "subcategory":"Rubber & Plastics",
            "type":"Manufacturing & Wholesale Goods"
        }
    ],
    "sg:phone":"+1 717 392 3488",
    "sg:postcode":"17603",
    "sg:province":"PA",
    "sg:tags":[
        "plastics-finished-wholesale",
        "manufacturer"
    ],
    "wof:name":"Ecw Marketing Group",
    "wof:placetype":"venue"
},
  "geometry": {"coordinates":[-76.332069,40.051201],"type":"Point"}
}