{
  "type": "Feature",
  "properties": {
    "iso:country":"US",
    "sg:address":"2063 N 8th St",
    "sg:city":"Philadelphia",
    "sg:classifiers":[
        {
            "category":"Food & Beverages",
            "subcategory":"Groceries & Convenience Stores",
            "type":"Retail Goods"
        }
    ],
    "sg:phone":"+1 215 978 4085",
    "sg:postcode":"19122",
    "sg:province":"PA",
    "wof:name":"Friend's Mini Market",
    "wof:placetype":"venue"
},
  "geometry": {"coordinates":[-75.147301,39.983398],"type":"Point"}
}