{
  "type": "Feature",
  "properties": {
    "iso:country":"US",
    "sg:address":"1057 Hildebidle Dr",
    "sg:city":"Collegeville",
    "sg:classifiers":[
        {
            "category":"Professional",
            "subcategory":"Management & Consulting",
            "type":"Services"
        }
    ],
    "sg:phone":"+1 610 454 9756",
    "sg:postcode":"19426",
    "sg:province":"PA",
    "wof:name":"Telesis Management",
    "wof:placetype":"venue"
},
  "geometry": {"coordinates":[-75.442312,40.192565],"type":"Point"}
}