{
  "type": "Feature",
  "properties": {
    "addr:full":"1450 Kuhn Rd Boiling Springs PA 17007",
    "addr:housenumber":"1450",
    "addr:postcode":"17007",
    "addr:street":"Kuhn Rd",
    "iso:country":"US",
    "sg:address":"1450 Kuhn Rd",
    "sg:city":"Boiling Springs",
    "sg:classifiers":[
        {
            "category":"Retail",
            "subcategory":"Animal Services",
            "type":"Services"
        }
    ],
    "sg:phone":"+1   ",
    "sg:postcode":"17007",
    "sg:province":"PA",
    "wof:name":"Making Friends",
    "wof:placetype":"venue"
},
  "geometry": {"coordinates":[-77.09039,40.137283],"type":"Point"}
}