{
  "type": "Feature",
  "properties": {
    "addr:full":"1429 N 2nd St Philadelphia PA 19122",
    "addr:housenumber":"1429",
    "addr:postcode":"19122",
    "addr:street":"N 2Nd St",
    "iso:country":"US",
    "sg:address":"1429 N 2nd St",
    "sg:city":"Philadelphia",
    "sg:classifiers":[
        {
            "category":"Education",
            "subcategory":"School",
            "type":"Public Place"
        }
    ],
    "sg:phone":"+1   ",
    "sg:postcode":"19122",
    "sg:province":"PA",
    "wof:name":"Saint Michael Elementary Schl",
    "wof:placetype":"venue"
},
  "geometry": {"coordinates":[-75.13864700000001,39.973293],"type":"Point"}
}