{
  "type": "Feature",
  "properties": {
    "addr:full":"5921 Colony Dr Bethlehem PA 18017",
    "addr:housenumber":"5921",
    "addr:postcode":"18017",
    "addr:street":"Colony Dr",
    "iso:country":"US",
    "sg:address":"5921 Colony Dr",
    "sg:city":"Bethlehem",
    "sg:classifiers":[
        {
            "category":"Professional",
            "subcategory":"Management & Consulting",
            "type":"Services"
        }
    ],
    "sg:phone":"+1   ",
    "sg:postcode":"18017",
    "sg:province":"PA",
    "sg:tags":[
        "promotion"
    ],
    "wof:name":"Arai Helmets",
    "wof:placetype":"venue"
},
  "geometry": {"coordinates":[-75.417869,40.684022],"type":"Point"}
}