{
  "type": "Feature",
  "properties": {
    "iso:country":"US",
    "sg:address":"410 Cranberry St",
    "sg:city":"Erie",
    "sg:classifiers":[
        {
            "category":"Banks & Credit Unions",
            "subcategory":"Investment Brokerage",
            "type":"Services"
        }
    ],
    "sg:phone":"+1 814 459 6669",
    "sg:postcode":"16502",
    "sg:province":"PA",
    "sg:tags":[
        "consultant",
        "planning",
        "financial"
    ],
    "wof:name":"T Baer Investment Advisors",
    "wof:placetype":"venue"
},
  "geometry": {"coordinates":[-80.111831,42.121529],"type":"Point"}
}