{
  "type": "Feature",
  "properties": {
    "iso:country":"US",
    "sg:address":"3008 Germantown Ave",
    "sg:city":"Philadelphia",
    "sg:classifiers":[
        {
            "category":"Organizations",
            "subcategory":"Religious Organization",
            "type":"Services"
        }
    ],
    "sg:phone":"+1 215 229 7657",
    "sg:postcode":"19133",
    "sg:province":"PA",
    "sg:tags":[
        "church"
    ],
    "wof:name":"Maranatha Ministries",
    "wof:placetype":"venue"
},
  "geometry": {"coordinates":[-75.14715700000001,39.998433],"type":"Point"}
}