{
  "type": "Feature",
  "properties": {
    "iso:country":"US",
    "sg:address":"101 W Rose Tree Rd",
    "sg:city":"Media",
    "sg:classifiers":[
        {
            "category":"Professional",
            "subcategory":"Management & Consulting",
            "type":"Services"
        }
    ],
    "sg:phone":"+1   ",
    "sg:postcode":"19063",
    "sg:province":"PA",
    "sg:tags":[
        "construction"
    ],
    "wof:name":"Scungio Borst & Associates LLC",
    "wof:placetype":"venue"
},
  "geometry": {"coordinates":[-75.398607,39.932767],"type":"Point"}
}