{
  "type": "Feature",
  "properties": {
    "iso:country":"US",
    "sg:address":"2697 Brodhead Rd",
    "sg:city":"Aliquippa",
    "sg:classifiers":[
        {
            "category":"Restaurant",
            "type":"Food & Drink"
        }
    ],
    "sg:phone":"+1 724 375 1339",
    "sg:postcode":"15001",
    "sg:province":"PA",
    "wof:name":"House Of Hunan",
    "wof:placetype":"venue"
},
  "geometry": {"coordinates":[-80.282286,40.607314],"type":"Point"}
}