{
  "type": "Feature",
  "properties": {
    "addr:full":"312 W Centre St Mahanoy City PA 17948",
    "addr:housenumber":"312",
    "addr:postcode":"17948",
    "addr:street":"W Centre St",
    "iso:country":"US",
    "sg:address":"312 W Centre St",
    "sg:city":"Mahanoy City",
    "sg:classifiers":[
        {
            "category":"Restaurant",
            "type":"Food & Drink"
        }
    ],
    "sg:phone":"+1 570 773 2775",
    "sg:postcode":"17948",
    "sg:province":"PA",
    "wof:name":"Silver Spoon Restaurant & Pub",
    "wof:placetype":"venue"
},
  "geometry": {"coordinates":[-76.144971,40.812044],"type":"Point"}
}