{
  "type": "Feature",
  "properties": {
    "iso:country":"US",
    "sg:address":"5756 Kennedy Ave",
    "sg:city":"Export",
    "sg:classifiers":[
        {
            "category":"Banks & Credit Unions",
            "subcategory":"Bank",
            "type":"Services"
        },
        {
            "category":"Shopping",
            "subcategory":"Used Merchandise",
            "type":"Retail Goods"
        }
    ],
    "sg:phone":"+1 724 325 1559",
    "sg:postcode":"15632",
    "sg:province":"PA",
    "sg:tags":[
        "shop",
        "second",
        "resale",
        "hand"
    ],
    "wof:name":"Friends Thrift Shop",
    "wof:placetype":"venue"
},
  "geometry": {"coordinates":[-79.62799800000001,40.418822],"type":"Point"}
}