{
  "type": "Feature",
  "properties": {
    "addr:full":"5053 Impala Dr Murrysville PA 15668",
    "addr:housenumber":"5053",
    "addr:postcode":"15668",
    "addr:street":"Impala Dr",
    "iso:country":"US",
    "sg:address":"5053 Impala Dr",
    "sg:city":"Murrysville",
    "sg:classifiers":[
        {
            "category":"Professional",
            "type":"Services"
        }
    ],
    "sg:phone":"+1   ",
    "sg:postcode":"15668",
    "sg:province":"PA",
    "wof:name":"Chetnadarsh Inc",
    "wof:placetype":"venue"
},
  "geometry": {"coordinates":[-79.699361,40.467462],"type":"Point"}
}