{
  "type": "Feature",
  "properties": {
    "addr:full":"901 E Butler Pike  Ambler PA 19002",
    "addr:housenumber":"901",
    "addr:postcode":"19002",
    "addr:street":"E Butler Pike",
    "iso:country":"US",
    "sg:address":"901 E Butler Pike ",
    "sg:city":"Ambler",
    "sg:classifiers":[
        {
            "category":"Deli",
            "type":"Food & Drink"
        }
    ],
    "sg:menulink":"http://www.allmenus.com/pa/upper-dublin/288390-costa-deli/menu/",
    "sg:phone":"+1 215 646 6173",
    "sg:postcode":"19002",
    "sg:province":"PA",
    "sg:tags":[
        "american"
    ],
    "wof:name":"Costa Deli",
    "wof:placetype":"venue"
},
  "geometry": {"coordinates":[-75.21402,40.160545],"type":"Point"}
}