{
  "type": "Feature",
  "properties": {
    "iso:country":"US",
    "sg:address":"813 E Chocolate Ave",
    "sg:city":"Hershey",
    "sg:classifiers":[
        {
            "category":"Professional",
            "subcategory":"Business Services",
            "type":"Services"
        }
    ],
    "sg:phone":"+1 717 534 1900",
    "sg:postcode":"17033",
    "sg:province":"PA",
    "wof:name":"Interiors With Style",
    "wof:placetype":"venue"
},
  "geometry": {"coordinates":[-76.630363,40.29322],"type":"Point"}
}