{
  "type": "Feature",
  "properties": {
    "addr:full":"4518 Benner St Philadelphia PA 19135",
    "addr:housenumber":"4518",
    "addr:postcode":"19135",
    "addr:street":"Benner St",
    "iso:country":"US",
    "sg:address":"4518 Benner St",
    "sg:city":"Philadelphia",
    "sg:classifiers":[
        {
            "category":"Building & Trades",
            "subcategory":"Pest Control",
            "type":"Services"
        }
    ],
    "sg:phone":"+1 215 533 5572",
    "sg:postcode":"19135",
    "sg:province":"PA",
    "wof:name":"Integrity Pest Management",
    "wof:placetype":"venue"
},
  "geometry": {"coordinates":[-75.058756,40.019707],"type":"Point"}
}