{
  "type": "Feature",
  "properties": {
    "addr:full":"306 E Lancaster Ave Wynnewood PA 19003",
    "addr:housenumber":"306",
    "addr:postcode":"19003",
    "addr:street":"E Lancaster Ave",
    "iso:country":"US",
    "sg:address":"306 E Lancaster Ave",
    "sg:city":"Wynnewood",
    "sg:classifiers":[
        {
            "category":"Professional",
            "subcategory":"Management & Consulting",
            "type":"Services"
        }
    ],
    "sg:phone":"+1   ",
    "sg:postcode":"19003",
    "sg:province":"PA",
    "sg:tags":[
        "hospital",
        "administrative",
        "for"
    ],
    "wof:name":"Main Line Health Patient Fincl",
    "wof:placetype":"venue"
},
  "geometry": {"coordinates":[-75.263988,39.99219],"type":"Point"}
}