{
  "type": "Feature",
  "properties": {
    "iso:country":"US",
    "sg:address":"610 S Cedar Ln",
    "sg:city":"Upper Darby",
    "sg:classifiers":[
        {
            "category":"Travel",
            "subcategory":"Travel Agent",
            "type":"Entertainment"
        }
    ],
    "sg:phone":"+1 610 446 2110",
    "sg:postcode":"19082",
    "sg:province":"PA",
    "sg:tags":[
        "agency"
    ],
    "wof:name":"Gilmartin Travel Inc",
    "wof:placetype":"venue"
},
  "geometry": {"coordinates":[-75.288578,39.96108],"type":"Point"}
}