{
  "type": "Feature",
  "properties": {
    "addr:full":"183 Eisaman Rd Irwin PA 15642",
    "addr:housenumber":"183",
    "addr:postcode":"15642",
    "addr:street":"Eisaman Rd",
    "iso:country":"US",
    "sg:address":"183 Eisaman Rd",
    "sg:city":"Irwin",
    "sg:classifiers":[
        {
            "category":"Building & Trades",
            "subcategory":"Construction",
            "type":"Services"
        }
    ],
    "sg:phone":"+1 724 863 0435",
    "sg:postcode":"15642",
    "sg:province":"PA",
    "sg:tags":[
        "lining",
        "membrane"
    ],
    "wof:name":"J H Water Systems",
    "wof:placetype":"venue"
},
  "geometry": {"coordinates":[-79.671729,40.289432],"type":"Point"}
}