{
  "type": "Feature",
  "properties": {
    "addr:full":"4139 Woerner Ave Levittown PA 19057",
    "addr:postcode":"4139;19057",
    "addr:street":"Woerner Ave",
    "iso:country":"US",
    "sg:address":"4139 Woerner Ave",
    "sg:city":"Levittown",
    "sg:classifiers":[
        {
            "category":"Organizations",
            "subcategory":"Professional Association",
            "type":"Services"
        }
    ],
    "sg:phone":"+1 215 547 1710",
    "sg:postcode":"19057",
    "sg:province":"PA",
    "wof:name":"Joint Christian Chior Assn",
    "wof:placetype":"venue"
},
  "geometry": {"coordinates":[-74.858355,40.151387],"type":"Point"}
}