{
  "type": "Feature",
  "properties": {
    "iso:country":"US",
    "sg:address":"2336 Kenderton Ave",
    "sg:city":"Abington",
    "sg:classifiers":[
        {
            "category":"Professional",
            "subcategory":"Business Services",
            "type":"Services"
        }
    ],
    "sg:phone":"+1 215 947 8900",
    "sg:postcode":"19001",
    "sg:province":"PA",
    "sg:tags":[
        "recording",
        "studio"
    ],
    "wof:name":"Craig Recording Studios",
    "wof:placetype":"venue"
},
  "geometry": {"coordinates":[-75.131991,40.125351],"type":"Point"}
}