{
  "type": "Feature",
  "properties": {
    "addr:full":"1040 Lemans Rd St Marys PA 15857",
    "addr:housenumber":"1040",
    "addr:postcode":"15857",
    "addr:street":"Lemans Rd",
    "iso:country":"US",
    "sg:address":"1040 Lemans Rd",
    "sg:city":"St Marys",
    "sg:classifiers":[
        {
            "category":"Retail",
            "subcategory":"Laundry & Dry Cleaning",
            "type":"Services"
        }
    ],
    "sg:phone":"+1 814 781 1155",
    "sg:postcode":"15857",
    "sg:province":"PA",
    "sg:tags":[
        "cleaners",
        "rug",
        "carpet"
    ],
    "wof:name":"Proclean Service",
    "wof:placetype":"venue"
},
  "geometry": {"coordinates":[-78.53421299999999,41.406644],"type":"Point"}
}