{
  "type": "Feature",
  "properties": {
    "iso:country":"US",
    "sg:address":"1500 Walnut St",
    "sg:city":"Philadelphia",
    "sg:classifiers":[
        {
            "category":"Real Estate",
            "subcategory":"Real Estate Agent",
            "type":"Services"
        }
    ],
    "sg:phone":"+1 215 732 0502",
    "sg:postcode":"19102",
    "sg:province":"PA",
    "sg:tags":[
        "investment"
    ],
    "wof:name":"Investment Property Exchange Services",
    "wof:placetype":"venue"
},
  "geometry": {"coordinates":[-75.16593899999999,39.949551],"type":"Point"}
}