{
  "type": "Feature",
  "properties": {
    "iso:country":"US",
    "sg:address":"404 Geisler Dr",
    "sg:city":"Pittsburgh",
    "sg:classifiers":[
        {
            "category":"Building & Trades",
            "subcategory":"Construction",
            "type":"Services"
        }
    ],
    "sg:phone":"+1 412 731 9330",
    "sg:postcode":"15221",
    "sg:province":"PA",
    "sg:tags":[
        "contractor"
    ],
    "wof:name":"Mann Construction Inc",
    "wof:placetype":"venue"
},
  "geometry": {"coordinates":[-79.851191,40.423661],"type":"Point"}
}