{
  "type": "Feature",
  "properties": {
    "addr:full":"4346 N George Street Ext Manchester PA 17345",
    "addr:housenumber":"4346",
    "addr:postcode":"17345",
    "addr:street":"N George Street Ext",
    "iso:country":"US",
    "sg:address":"4346 N George Street Ext",
    "sg:city":"Manchester",
    "sg:classifiers":[
        {
            "category":"Restaurant",
            "type":"Food & Drink"
        }
    ],
    "sg:menulink":"http://www.allmenus.com/pa/east-manchester/123146-quiznos-sub/menu/",
    "sg:phone":"+1 717 266 9777",
    "sg:postcode":"17345",
    "sg:province":"PA",
    "sg:tags":[
        "wrap",
        "american",
        "sandwich"
    ],
    "wof:name":"Quiznos Sub",
    "wof:placetype":"venue"
},
  "geometry": {"coordinates":[-76.723787,40.046559],"type":"Point"}
}