{
  "type": "Feature",
  "properties": {
    "iso:country":"US",
    "sg:address":"571 State Rd",
    "sg:city":"Barnesville",
    "sg:classifiers":[
        {
            "category":"Transit Center",
            "subcategory":"Freight",
            "type":"Transportation"
        },
        {
            "category":"Freight",
            "type":"Transportation"
        }
    ],
    "sg:phone":"+1 570 467 0519",
    "sg:postcode":"18214",
    "sg:province":"PA",
    "sg:tags":[
        "trucking-motor",
        "trucking"
    ],
    "wof:name":"Hoppes Darrin",
    "wof:placetype":"venue"
},
  "geometry": {"coordinates":[-76.059324,40.806183],"type":"Point"}
}