{
  "type": "Feature",
  "properties": {
    "iso:country":"US",
    "sg:address":"1 W High St Ste 208",
    "sg:city":"Carlisle",
    "sg:classifiers":[
        {
            "category":"Professional",
            "subcategory":"Lawyer & Legal Services",
            "type":"Services"
        }
    ],
    "sg:phone":"+1 717 241 6363",
    "sg:postcode":"17013",
    "sg:province":"PA",
    "sg:tags":[
        "personal",
        "injury"
    ],
    "wof:name":"Mislitsky Richard P",
    "wof:placetype":"venue"
},
  "geometry": {"coordinates":[-77.199699,40.203201],"type":"Point"}
}