{
  "type": "Feature",
  "properties": {
    "iso:country":"US",
    "sg:address":"207 Carter Dr",
    "sg:city":"West Chester",
    "sg:classifiers":[
        {
            "category":"Shopping",
            "subcategory":"Computers & Home Electronics",
            "type":"Retail Goods"
        }
    ],
    "sg:phone":"+1 610 692 9062",
    "sg:postcode":"19382",
    "sg:province":"PA",
    "sg:tags":[
        "software"
    ],
    "wof:name":"Summit Data Systems",
    "wof:placetype":"venue"
},
  "geometry": {"coordinates":[-75.588528,39.950401],"type":"Point"}
}