{
  "type": "Feature",
  "properties": {
    "iso:country":"US",
    "sg:address":"5534 Hanover Rd",
    "sg:city":"Hanover",
    "sg:classifiers":[
        {
            "category":"Shopping",
            "subcategory":"Bicycles & Sporting Goods",
            "type":"Retail Goods"
        }
    ],
    "sg:phone":"+1 717 637 8449",
    "sg:postcode":"17331",
    "sg:province":"PA",
    "wof:name":"Bud's Bike Barn",
    "wof:placetype":"venue"
},
  "geometry": {"coordinates":[-77.05006400000001,39.798324],"type":"Point"}
}