{
  "type": "Feature",
  "properties": {
    "iso:country":"US",
    "sg:address":"1120 Richmond St",
    "sg:city":"Reading",
    "sg:classifiers":[
        {
            "category":"Food & Beverages",
            "subcategory":"Specialty",
            "type":"Retail Goods"
        }
    ],
    "sg:phone":"+1 610 939 0414",
    "sg:postcode":"19604",
    "sg:province":"PA",
    "sg:tags":[
        "vitamin"
    ],
    "sg:website":"www.propernutrition.com",
    "wof:name":"Proper Nutrition Inc",
    "wof:placetype":"venue"
},
  "geometry": {"coordinates":[-75.914985,40.363674],"type":"Point"}
}