{
  "type": "Feature",
  "properties": {
    "iso:country":"US",
    "sg:address":"1741 N Broad St",
    "sg:city":"Lansdale",
    "sg:classifiers":[
        {
            "category":"Personal",
            "subcategory":"Nail Salon",
            "type":"Services"
        }
    ],
    "sg:phone":"+1 215 393 9300",
    "sg:postcode":"19446",
    "sg:province":"PA",
    "wof:name":"Inter Nail Salon",
    "wof:placetype":"venue"
},
  "geometry": {"coordinates":[-75.27010300000001,40.255299],"type":"Point"}
}