{
  "type": "Feature",
  "properties": {
    "iso:country":"US",
    "sg:address":"2690 W Liberty Ave",
    "sg:city":"Pittsburgh",
    "sg:classifiers":[
        {
            "category":"Autos & Motor Vehicles",
            "subcategory":"Automobile Sales",
            "type":"Retail Goods"
        },
        {
            "category":"Retail",
            "subcategory":"Auto Repair",
            "type":"Services"
        }
    ],
    "sg:phone":"+1 412 344 3600",
    "sg:postcode":"15216",
    "sg:province":"PA",
    "sg:tags":[
        "car"
    ],
    "wof:name":"Rohrich Vw Mazda",
    "wof:placetype":"venue"
},
  "geometry": {"coordinates":[-80.028801,40.397598],"type":"Point"}
}