{
  "type": "Feature",
  "properties": {
    "addr:full":"1228 State Rte 309 Sellersville PA 18951",
    "addr:housenumber":"1228",
    "addr:postcode":"18951",
    "addr:street":"State Rte 309",
    "iso:country":"US",
    "sg:address":"1228 State Rte 309",
    "sg:city":"Sellersville",
    "sg:classifiers":[
        {
            "category":"Building & Trades",
            "subcategory":"Construction",
            "type":"Services"
        }
    ],
    "sg:phone":"+1   ",
    "sg:postcode":"18951",
    "sg:province":"PA",
    "sg:tags":[
        "residential",
        "house"
    ],
    "wof:name":"Souder and Souder Contracting",
    "wof:placetype":"venue"
},
  "geometry": {"coordinates":[-75.372562,40.47664],"type":"Point"}
}