{
  "type": "Feature",
  "properties": {
    "iso:country":"US",
    "sg:address":"3117 Washington Pike",
    "sg:city":"Bridgeville",
    "sg:classifiers":[
        {
            "category":"Utilities",
            "subcategory":"Electric",
            "type":"Services"
        }
    ],
    "sg:phone":"+1 412 257 9070",
    "sg:postcode":"15017",
    "sg:province":"PA",
    "sg:tags":[
        "company"
    ],
    "wof:name":"Optimum Power Technology",
    "wof:placetype":"venue"
},
  "geometry": {"coordinates":[-80.113514,40.34653],"type":"Point"}
}