{
  "type": "Feature",
  "properties": {
    "iso:country":"US",
    "sg:address":"1501 E Lackawanna St",
    "sg:city":"Olyphant",
    "sg:classifiers":[
        {
            "category":"Building & Trades",
            "subcategory":"Cleaning & Sanitation",
            "type":"Services"
        }
    ],
    "sg:phone":"+1 570 820 7651",
    "sg:postcode":"18447",
    "sg:province":"PA",
    "sg:tags":[
        "ventilating",
        "system"
    ],
    "wof:name":"Enviro-Tek Duct Cleaning",
    "wof:placetype":"venue"
},
  "geometry": {"coordinates":[-75.592989,41.461704],"type":"Point"}
}