{
  "type": "Feature",
  "properties": {
    "addr:full":"3 State Rd Media PA 19063",
    "addr:housenumber":"3",
    "addr:postcode":"19063",
    "addr:street":"State Rd",
    "iso:country":"US",
    "sg:address":"3 State Rd",
    "sg:city":"Media",
    "sg:classifiers":[
        {
            "category":"Banks & Credit Unions",
            "subcategory":"Bank",
            "type":"Services"
        }
    ],
    "sg:phone":"+1 610 565 7044",
    "sg:postcode":"19063",
    "sg:province":"PA",
    "sg:tags":[
        "savings",
        "loan",
        "association"
    ],
    "wof:name":"Iron Worker's Bank",
    "wof:placetype":"venue"
},
  "geometry": {"coordinates":[-75.383843,39.928048],"type":"Point"}
}