{
  "type": "Feature",
  "properties": {
    "iso:country":"US",
    "sg:address":"724 Fitzwatertown Rd",
    "sg:city":"Willow Grove",
    "sg:classifiers":[
        {
            "category":"Professional",
            "subcategory":"Management & Consulting",
            "type":"Services"
        }
    ],
    "sg:phone":"+1 215 902 0200",
    "sg:postcode":"19090",
    "sg:province":"PA",
    "sg:tags":[
        "fuel"
    ],
    "wof:name":"Source One",
    "wof:placetype":"venue"
},
  "geometry": {"coordinates":[-75.115703,40.158328],"type":"Point"}
}