{
  "type": "Feature",
  "properties": {
    "addr:full":"2674 Egypt Rd Norristown PA 19403",
    "addr:housenumber":"2674",
    "addr:postcode":"19403",
    "addr:street":"Egypt Rd",
    "iso:country":"US",
    "sg:address":"2674 Egypt Rd",
    "sg:city":"Norristown",
    "sg:classifiers":[
        {
            "category":"Wholesale",
            "subcategory":"Medical Equipment & Supplies",
            "type":"Manufacturing & Wholesale Goods"
        },
        {
            "category":"Shopping",
            "subcategory":"Beauty & Cosmetics",
            "type":"Retail Goods"
        },
        {
            "category":"Food & Beverages",
            "subcategory":"Specialty",
            "type":"Retail Goods"
        },
        {
            "category":"Shopping",
            "subcategory":"Gifts & Souvenirs",
            "type":"Retail Goods"
        },
        {
            "category":"Retail",
            "subcategory":"Photofinishing",
            "type":"Services"
        },
        {
            "category":"Shopping",
            "subcategory":"Pharmacy",
            "type":"Retail Goods"
        }
    ],
    "sg:phone":"+1 610 650 8490",
    "sg:postcode":"19403",
    "sg:province":"PA",
    "sg:tags":[
        "product",
        "photo",
        "vitamin",
        "perfume",
        "supplement",
        "health",
        "wellness",
        "aid",
        "finishing",
        "first",
        "card",
        "greeting"
    ],
    "sg:website":"http://www.riteaid.com",
    "wof:name":"Rite Aid",
    "wof:placetype":"venue"
},
  "geometry": {"coordinates":[-75.40964700000001,40.130216],"type":"Point"}
}