{
  "type": "Feature",
  "properties": {
    "addr:full":"219 Marlboro Rd Morrisville PA 19067",
    "addr:housenumber":"219",
    "addr:postcode":"19067",
    "addr:street":"Marlboro Rd",
    "iso:country":"US",
    "sg:address":"219 Marlboro Rd",
    "sg:city":"Morrisville",
    "sg:classifiers":[
        {
            "category":"Health Services",
            "subcategory":"Chiropractor",
            "type":"Services"
        }
    ],
    "sg:phone":"+1   ",
    "sg:postcode":"19067",
    "sg:province":"PA",
    "wof:name":"Giordano Chiropractic",
    "wof:placetype":"venue"
},
  "geometry": {"coordinates":[-74.80639600000001,40.208508],"type":"Point"}
}