{
  "type": "Feature",
  "properties": {
    "addr:full":"1618 Harper Rd Erie PA 16505",
    "addr:housenumber":"1618",
    "addr:postcode":"16505",
    "addr:street":"Harper Rd",
    "iso:country":"US",
    "sg:address":"1618 Harper Rd",
    "sg:city":"Erie",
    "sg:classifiers":[
        {
            "category":"Wholesale",
            "subcategory":"Vending Machines",
            "type":"Manufacturing & Wholesale Goods"
        }
    ],
    "sg:phone":"+1 814 833 4035",
    "sg:postcode":"16505",
    "sg:province":"PA",
    "sg:tags":[
        "operator"
    ],
    "wof:name":"Moser Vending Co",
    "wof:placetype":"venue"
},
  "geometry": {"coordinates":[-80.14776000000001,42.095057],"type":"Point"}
}