{
  "type": "Feature",
  "properties": {
    "iso:country":"US",
    "sg:address":"4936 N Front St",
    "sg:city":"Philadelphia",
    "sg:classifiers":[
        {
            "category":"Freight",
            "type":"Transportation"
        }
    ],
    "sg:phone":"+1   ",
    "sg:postcode":"19120",
    "sg:province":"PA",
    "wof:name":"Jensen Movers",
    "wof:placetype":"venue"
},
  "geometry": {"coordinates":[-75.123158,40.027118],"type":"Point"}
}