{
  "type": "Feature",
  "properties": {
    "iso:country":"US",
    "sg:address":"540 Pennsylvania Ave",
    "sg:city":"Fort Washington",
    "sg:classifiers":[
        {
            "category":"Professional",
            "subcategory":"Engineering",
            "type":"Services"
        }
    ],
    "sg:phone":"+1 215 233 9019",
    "sg:postcode":"19034",
    "sg:province":"PA",
    "sg:tags":[
        "engineer"
    ],
    "wof:name":"Mitra & Assoc",
    "wof:placetype":"venue"
},
  "geometry": {"coordinates":[-75.205427,40.13363],"type":"Point"}
}