{
  "type": "Feature",
  "properties": {
    "addr:full":"10 Colten Dr Cochranville PA 19330",
    "addr:housenumber":"10",
    "addr:postcode":"19330",
    "addr:street":"Colten Dr Cochranville",
    "iso:country":"US",
    "sg:address":"10 Colten Dr",
    "sg:city":"Cochranville",
    "sg:classifiers":[
        {
            "category":"Wholesale",
            "subcategory":"Stationery",
            "type":"Manufacturing & Wholesale Goods"
        }
    ],
    "sg:phone":"+1 610 869 2500",
    "sg:postcode":"19330",
    "sg:province":"PA",
    "sg:tags":[
        "business",
        "form",
        "system"
    ],
    "wof:name":"Xpert Printing Svc",
    "wof:placetype":"venue"
},
  "geometry": {"coordinates":[-75.875164,39.860848],"type":"Point"}
}