{
  "type": "Feature",
  "properties": {
    "iso:country":"US",
    "sg:address":"1 Lan Creek Rd",
    "sg:city":"Wilkes Barre",
    "sg:classifiers":[
        {
            "category":"Retail",
            "subcategory":"Laundry & Dry Cleaning",
            "type":"Services"
        }
    ],
    "sg:phone":"+1 570 829 0142",
    "sg:postcode":"18702",
    "sg:province":"PA",
    "wof:name":"Grimefighters",
    "wof:placetype":"venue"
},
  "geometry": {"coordinates":[-75.80575,41.263336],"type":"Point"}
}