{
  "type": "Feature",
  "properties": {
    "iso:country":"US",
    "sg:address":"1525 N American St",
    "sg:city":"Philadelphia",
    "sg:classifiers":[
        {
            "category":"Utilities",
            "subcategory":"Refuse",
            "type":"Services"
        }
    ],
    "sg:phone":"+1   ",
    "sg:postcode":"19122",
    "sg:province":"PA",
    "sg:tags":[
        "system"
    ],
    "wof:name":"Recycle Authority Inc",
    "wof:placetype":"venue"
},
  "geometry": {"coordinates":[-75.139686,39.974621],"type":"Point"}
}