{
  "type": "Feature",
  "properties": {
    "iso:country":"US",
    "sg:address":"130 E Baltimore Ave",
    "sg:city":"Lansdowne",
    "sg:classifiers":[
        {
            "category":"Communications",
            "type":"Services"
        }
    ],
    "sg:phone":"+1 610 284 0980",
    "sg:postcode":"19050",
    "sg:province":"PA",
    "wof:name":"Wright Communications Inc",
    "wof:placetype":"venue"
},
  "geometry": {"coordinates":[-75.266695,39.939191],"type":"Point"}
}