{
  "type": "Feature",
  "properties": {
    "iso:country":"US",
    "sg:address":"6904 Landfill Rd",
    "sg:city":"Waynesboro",
    "sg:classifiers":[
        {
            "category":"Government",
            "subcategory":"Office",
            "type":"Public Place"
        }
    ],
    "sg:phone":"+1 717 762 2808",
    "sg:postcode":"17268",
    "sg:province":"PA",
    "sg:tags":[
        "government-state",
        "government-united",
        "state"
    ],
    "sg:website":"http://www.penndotcrm.org",
    "wof:name":"Pennsylvania Dept Of Transportation",
    "wof:placetype":"venue"
},
  "geometry": {"coordinates":[-77.56192799999999,39.821906],"type":"Point"}
}