{
  "type": "Feature",
  "properties": {
    "iso:country":"US",
    "sg:address":"734 Brookline Blvd",
    "sg:city":"Pittsburgh",
    "sg:classifiers":[
        {
            "category":"Government",
            "subcategory":"Office",
            "type":"Public Place"
        }
    ],
    "sg:phone":"+1   ",
    "sg:postcode":"15226",
    "sg:province":"PA",
    "sg:tags":[
        "executive"
    ],
    "wof:name":"Diven McHael State Rprsntative",
    "wof:placetype":"venue"
},
  "geometry": {"coordinates":[-80.02051,40.394056],"type":"Point"}
}