{
  "type": "Feature",
  "properties": {
    "addr:full":"3861 Quaker Valley Rd Alum Bank PA 15521",
    "addr:housenumber":"3861",
    "addr:postcode":"15521",
    "addr:street":"Quaker Valley Rd",
    "iso:country":"US",
    "sg:address":"3861 Quaker Valley Rd",
    "sg:city":"Alum Bank",
    "sg:classifiers":[
        {
            "category":"Autos & Motor Vehicles",
            "subcategory":"Automobile Sales",
            "type":"Retail Goods"
        }
    ],
    "sg:phone":"+1 814 839 4504",
    "sg:postcode":"15521",
    "sg:province":"PA",
    "sg:tags":[
        "car",
        "dealer"
    ],
    "wof:name":"Paul's Auto Village",
    "wof:placetype":"venue"
},
  "geometry": {"coordinates":[-78.598787,40.171603],"type":"Point"}
}