{
  "type": "Feature",
  "properties": {
    "addr:full":"210 Hunter St Media PA 19063",
    "addr:housenumber":"210",
    "addr:postcode":"19063",
    "addr:street":"Hunter St",
    "iso:country":"US",
    "sg:address":"210 Hunter St",
    "sg:city":"Media",
    "sg:classifiers":[
        {
            "category":"Manufacturing",
            "subcategory":"Furniture",
            "type":"Manufacturing & Wholesale Goods"
        }
    ],
    "sg:phone":"+1   ",
    "sg:postcode":"19063",
    "sg:province":"PA",
    "sg:tags":[
        "mfg",
        "wood",
        "cabinet"
    ],
    "wof:name":"Sunrise Triad",
    "wof:placetype":"venue"
},
  "geometry": {"coordinates":[-75.442071,39.909272],"type":"Point"}
}