{
  "type": "Feature",
  "properties": {
    "addr:full":"6070 Carpenter St East Petersburg PA 17520",
    "addr:housenumber":"6070",
    "addr:postcode":"17520",
    "addr:street":"Carpenter St",
    "iso:country":"US",
    "sg:address":"6070 Carpenter St",
    "sg:city":"East Petersburg",
    "sg:classifiers":[
        {
            "category":"Professional",
            "type":"Services"
        }
    ],
    "sg:phone":"+1 717 581 8119",
    "sg:postcode":"17520",
    "sg:province":"PA",
    "sg:tags":[
        "arranger",
        "music",
        "composer"
    ],
    "wof:name":"Randall Zwally",
    "wof:placetype":"venue"
},
  "geometry": {"coordinates":[-76.357192,40.099992],"type":"Point"}
}