{
  "type": "Feature",
  "properties": {
    "iso:country":"US",
    "sg:address":"82 Lo Bell Dr",
    "sg:city":"Washington",
    "sg:classifiers":[
        {
            "category":"Health Services",
            "subcategory":"Doctor",
            "type":"Services"
        }
    ],
    "sg:phone":"+1   ",
    "sg:postcode":"15301",
    "sg:province":"PA",
    "sg:tags":[
        "medical"
    ],
    "wof:name":"Equirace Health & Speed",
    "wof:placetype":"venue"
},
  "geometry": {"coordinates":[-80.27605200000001,40.196595],"type":"Point"}
}