{
  "type": "Feature",
  "properties": {
    "iso:country":"US",
    "sg:address":"1583 Breining St",
    "sg:city":"Pittsburgh",
    "sg:classifiers":[
        {
            "category":"Education",
            "subcategory":"School",
            "type":"Public Place"
        }
    ],
    "sg:phone":"+1 412 885 7760",
    "sg:postcode":"15226",
    "sg:province":"PA",
    "sg:tags":[
        "high",
        "middle",
        "elementary"
    ],
    "sg:website":"www.pghboe.net",
    "wof:name":"Pittsburgh Public Schools",
    "wof:placetype":"venue"
},
  "geometry": {"coordinates":[-80.006596,40.388556],"type":"Point"}
}