{
  "type": "Feature",
  "properties": {
    "iso:country":"US",
    "sg:address":"84 E Broad St",
    "sg:city":"Bethlehem",
    "sg:classifiers":[
        {
            "category":"Banks & Credit Unions",
            "subcategory":"Bank",
            "type":"Services"
        }
    ],
    "sg:phone":"+1   ",
    "sg:postcode":"18018",
    "sg:province":"PA",
    "sg:tags":[
        "broker",
        "mortgage"
    ],
    "wof:name":"Glenn Mortgage Service",
    "wof:placetype":"venue"
},
  "geometry": {"coordinates":[-75.375643,40.62217],"type":"Point"}
}