{
  "type": "Feature",
  "properties": {
    "iso:country":"US",
    "sg:address":"2921 E State St",
    "sg:city":"Hermitage",
    "sg:classifiers":[
        {
            "category":"Retail",
            "subcategory":"Auto Rental",
            "type":"Services"
        }
    ],
    "sg:phone":"+1 724 347 7222",
    "sg:postcode":"16148",
    "sg:province":"PA",
    "sg:tags":[
        "renting",
        "automobile",
        "passenger",
        "car"
    ],
    "wof:name":"Enterprise Rent-A-Car Company",
    "wof:placetype":"venue"
},
  "geometry": {"coordinates":[-80.455181,41.23345],"type":"Point"}
}