{
  "type": "Feature",
  "properties": {
    "iso:country":"US",
    "sg:address":"265 Rochester Rd",
    "sg:city":"Freedom",
    "sg:classifiers":[
        {
            "category":"Building & Trades",
            "subcategory":"Plumbing",
            "type":"Services"
        }
    ],
    "sg:phone":"+1 724 728 1181",
    "sg:postcode":"15042",
    "sg:province":"PA",
    "sg:tags":[
        "plumbing",
        "contractor"
    ],
    "wof:name":"Rooter-Man",
    "wof:placetype":"venue"
},
  "geometry": {"coordinates":[-80.168975,40.702896],"type":"Point"}
}