{
  "type": "Feature",
  "properties": {
    "iso:country":"US",
    "sg:address":"3 Main St",
    "sg:city":"Leechburg",
    "sg:classifiers":[
        {
            "category":"Food & Beverages",
            "subcategory":"Groceries & Convenience Stores",
            "type":"Retail Goods"
        }
    ],
    "sg:phone":"+1 724 845 2671",
    "sg:postcode":"15656",
    "sg:province":"PA",
    "sg:tags":[
        "grocer"
    ],
    "wof:name":"Leechburg IGA",
    "wof:placetype":"venue"
},
  "geometry": {"coordinates":[-79.608812,40.628574],"type":"Point"}
}