{
  "type": "Feature",
  "properties": {
    "addr:full":"566 N Derr Dr Lewisburg PA 17837",
    "addr:housenumber":"566",
    "addr:postcode":"17837",
    "addr:street":"N Derr Dr",
    "iso:country":"US",
    "sg:address":"566 N Derr Dr",
    "sg:city":"Lewisburg",
    "sg:classifiers":[
        {
            "category":"Home & Garden",
            "subcategory":"Home Furnishings",
            "type":"Retail Goods"
        }
    ],
    "sg:phone":"+1 570 522 8383",
    "sg:postcode":"17837",
    "sg:province":"PA",
    "sg:tags":[
        "curtain",
        "made",
        "drapery"
    ],
    "sg:website":"www.therichscott.com",
    "wof:name":"Rich Scott Design Studios",
    "wof:placetype":"venue"
},
  "geometry": {"coordinates":[-76.892805,40.968347],"type":"Point"}
}