{
  "type": "Feature",
  "properties": {
    "addr:full":"1817 N Main Ave Scranton PA 18508",
    "addr:housenumber":"1817",
    "addr:postcode":"18508",
    "addr:street":"N Main Ave",
    "iso:country":"US",
    "sg:address":"1817 N Main Ave",
    "sg:city":"Scranton",
    "sg:classifiers":[
        {
            "category":"Recreation",
            "type":"Entertainment"
        }
    ],
    "sg:phone":"+1 570 961 3547",
    "sg:postcode":"18508",
    "sg:province":"PA",
    "sg:tags":[
        "instruction",
        "gymnastic"
    ],
    "wof:name":"Alpha Gymnastics Inc",
    "wof:placetype":"venue"
},
  "geometry": {"coordinates":[-75.65742,41.437738],"type":"Point"}
}