{
  "type": "Feature",
  "properties": {
    "iso:country":"US",
    "sg:address":"5652 Upper Ridge Rd",
    "sg:city":"Pennsburg",
    "sg:classifiers":[
        {
            "category":"Health Services",
            "subcategory":"Nursing And Care Facility",
            "type":"Services"
        }
    ],
    "sg:phone":"+1   ",
    "sg:postcode":"18073",
    "sg:province":"PA",
    "wof:name":"Life Path",
    "wof:placetype":"venue"
},
  "geometry": {"coordinates":[-75.448216,40.350071],"type":"Point"}
}