{
  "type": "Feature",
  "properties": {
    "iso:country":"US",
    "sg:address":"1314 Logan Blvd",
    "sg:city":"Altoona",
    "sg:classifiers":[
        {
            "category":"Personal",
            "subcategory":"Beauty Salon",
            "type":"Services"
        }
    ],
    "sg:phone":"+1 814 942 1395",
    "sg:postcode":"16602",
    "sg:province":"PA",
    "sg:tags":[
        "shop"
    ],
    "wof:name":"All About You Inc",
    "wof:placetype":"venue"
},
  "geometry": {"coordinates":[-78.40005499999999,40.471894],"type":"Point"}
}