{
  "type": "Feature",
  "properties": {
    "iso:country":"US",
    "sg:address":"6081 Kingsessing Ave",
    "sg:city":"Philadelphia",
    "sg:classifiers":[
        {
            "category":"Wholesale",
            "subcategory":"Seafood",
            "type":"Manufacturing & Wholesale Goods"
        }
    ],
    "sg:phone":"+1 215 724 3120",
    "sg:postcode":"19142",
    "sg:province":"PA",
    "sg:tags":[
        "market"
    ],
    "wof:name":"Seafood Sensations",
    "wof:placetype":"venue"
},
  "geometry": {"coordinates":[-75.232105,39.93148],"type":"Point"}
}