{
  "type": "Feature",
  "properties": {
    "addr:full":"530 McClelland Rd Finleyville PA 15332",
    "addr:housenumber":"530",
    "addr:postcode":"15332",
    "addr:street":"Mcclelland Rd",
    "iso:country":"US",
    "sg:address":"530 McClelland Rd",
    "sg:city":"Finleyville",
    "sg:classifiers":[
        {
            "category":"Real Estate",
            "subcategory":"Real Estate Operator",
            "type":"Services"
        }
    ],
    "sg:phone":"+1   ",
    "sg:postcode":"15332",
    "sg:province":"PA",
    "sg:tags":[
        "property",
        "lessor"
    ],
    "wof:name":"Rental Pro",
    "wof:placetype":"venue"
},
  "geometry": {"coordinates":[-80.019757,40.258601],"type":"Point"}
}