{
  "type": "Feature",
  "properties": {
    "addr:full":"100 Rosslyn Rd Carnegie PA 15106",
    "addr:housenumber":"100",
    "addr:postcode":"15106",
    "addr:street":"Rosslyn Rd",
    "iso:country":"US",
    "sg:address":"100 Rosslyn Rd",
    "sg:city":"Carnegie",
    "sg:classifiers":[
        {
            "category":"Manufacturing",
            "subcategory":"Metals",
            "type":"Manufacturing & Wholesale Goods"
        }
    ],
    "sg:phone":"+1 412 722 0440",
    "sg:postcode":"15106",
    "sg:province":"PA",
    "sg:tags":[
        "coating"
    ],
    "wof:name":"Permanent Coatings",
    "wof:placetype":"venue"
},
  "geometry": {"coordinates":[-80.08832099999999,40.41936],"type":"Point"}
}