{
  "type": "Feature",
  "properties": {
    "addr:full":"528 E Main St Carnegie PA 15106",
    "addr:housenumber":"528",
    "addr:postcode":"15106",
    "addr:street":"E Main St",
    "iso:country":"US",
    "sg:address":"528 E Main St",
    "sg:city":"Carnegie",
    "sg:classifiers":[
        {
            "category":"Home & Garden",
            "subcategory":"Hardware",
            "type":"Retail Goods"
        }
    ],
    "sg:phone":"+1 412 279 4646",
    "sg:postcode":"15106",
    "sg:province":"PA",
    "wof:name":"Carnegie Supply Co",
    "wof:placetype":"venue"
},
  "geometry": {"coordinates":[-80.07938,40.412485],"type":"Point"}
}