{
  "type": "Feature",
  "properties": {
    "iso:country":"US",
    "sg:address":"8135 Elberon Ave",
    "sg:city":"Philadelphia",
    "sg:classifiers":[
        {
            "category":"Building & Trades",
            "subcategory":"Construction",
            "type":"Services"
        }
    ],
    "sg:phone":"+1 215 725 8759",
    "sg:postcode":"19111",
    "sg:province":"PA",
    "sg:tags":[
        "house"
    ],
    "wof:name":"John Venneri Construction",
    "wof:placetype":"venue"
},
  "geometry": {"coordinates":[-75.08181,40.078689],"type":"Point"}
}