{
  "type": "Feature",
  "properties": {
    "iso:country":"US",
    "sg:address":"4 Trenton Road",
    "sg:city":"Langhorne",
    "sg:classifiers":[
        {
            "category":"Bars & Pubs",
            "type":"Food & Drink"
        },
        {
            "category":"Restaurant",
            "type":"Food & Drink"
        }
    ],
    "sg:phone":"+1 215 750 6893",
    "sg:postcode":"19047",
    "sg:province":"PA",
    "sg:tags":[
        "traditional",
        "american"
    ],
    "sg:website":"www.hulmevilleinn.com",
    "wof:name":"Hulmeville Inn",
    "wof:placetype":"venue"
},
  "geometry": {"coordinates":[-74.91167299999999,40.142549],"type":"Point"}
}