{
  "type": "Feature",
  "properties": {
    "iso:country":"US",
    "sg:address":"820 Ingomar Rd",
    "sg:city":"Ingomar",
    "sg:classifiers":[
        {
            "category":"Wholesale",
            "subcategory":"Durable Goods & Equipment",
            "type":"Manufacturing & Wholesale Goods"
        }
    ],
    "sg:phone":"+1 412 367 2272",
    "sg:postcode":"15101",
    "sg:province":"PA",
    "sg:tags":[
        "laser"
    ],
    "wof:name":"Mazak Laser Systems",
    "wof:placetype":"venue"
},
  "geometry": {"coordinates":[-80.00738800000001,40.594263],"type":"Point"}
}