{
  "type": "Feature",
  "properties": {
    "iso:country":"US",
    "sg:address":"1417 Deepwood Dr",
    "sg:city":"Pittsburgh",
    "sg:classifiers":[
        {
            "category":"Banks & Credit Unions",
            "subcategory":"Financial Services",
            "type":"Services"
        }
    ],
    "sg:phone":"+1   ",
    "sg:postcode":"15241",
    "sg:province":"PA",
    "sg:tags":[
        "trust",
        "investment",
        "real estate"
    ],
    "wof:name":"Jerry Gobb",
    "wof:placetype":"venue"
},
  "geometry": {"coordinates":[-80.089375,40.348215],"type":"Point"}
}