{
  "type": "Feature",
  "properties": {
    "iso:country":"US",
    "sg:address":"716 E Sunbury St",
    "sg:city":"Millerstown",
    "sg:classifiers":[
        {
            "category":"Wholesale",
            "subcategory":"Farm Supplies",
            "type":"Manufacturing & Wholesale Goods"
        }
    ],
    "sg:phone":"+1 717 589 7183",
    "sg:postcode":"17062",
    "sg:province":"PA",
    "sg:tags":[
        "product",
        "health",
        "animal"
    ],
    "wof:name":"Minor Inc",
    "wof:placetype":"venue"
},
  "geometry": {"coordinates":[-77.15065800000001,40.551466],"type":"Point"}
}