{
  "type": "Feature",
  "properties": {
    "addr:full":"300 Hartman Bridge Rd Ronks PA 17572",
    "addr:housenumber":"300",
    "addr:postcode":"17572",
    "addr:street":"Hartman Bridge Rd",
    "iso:country":"US",
    "sg:address":"300 Hartman Bridge Rd",
    "sg:city":"Ronks",
    "sg:classifiers":[
        {
            "category":"Arts & Performance",
            "subcategory":"Theater",
            "type":"Entertainment"
        }
    ],
    "sg:phone":"+1 717 687 7800",
    "sg:postcode":"17572",
    "sg:province":"PA",
    "wof:name":"Sight & Sound Theatres",
    "wof:placetype":"venue"
},
  "geometry": {"coordinates":[-76.182148,39.994456],"type":"Point"}
}