{
  "type": "Feature",
  "properties": {
    "addr:full":"211 Conestoga Rd Wayne PA 19087",
    "addr:housenumber":"211",
    "addr:postcode":"19087",
    "addr:street":"Conestoga Rd",
    "iso:country":"US",
    "sg:address":"211 Conestoga Rd",
    "sg:city":"Wayne",
    "sg:classifiers":[
        {
            "category":"Building & Trades",
            "subcategory":"Electrical",
            "type":"Services"
        }
    ],
    "sg:phone":"+1 610 527 1442",
    "sg:postcode":"19087",
    "sg:province":"PA",
    "sg:tags":[
        "work",
        "electrical",
        "electric",
        "contractor"
    ],
    "wof:name":"Keith Martin Electrical Contrs",
    "wof:placetype":"venue"
},
  "geometry": {"coordinates":[-75.39336400000001,40.041008],"type":"Point"}
}