{
  "type": "Feature",
  "properties": {
    "addr:full":"45 Broadway St Milton PA 17847",
    "addr:housenumber":"45",
    "addr:postcode":"17847",
    "addr:street":"Broadway St",
    "iso:country":"US",
    "sg:address":"45 Broadway St",
    "sg:city":"Milton",
    "sg:classifiers":[
        {
            "category":"Shopping",
            "subcategory":"Stationery & Office Supplies",
            "type":"Retail Goods"
        }
    ],
    "sg:phone":"+1 570 742 7312",
    "sg:postcode":"17847",
    "sg:province":"PA",
    "wof:name":"Fullmer Office Supply",
    "wof:placetype":"venue"
},
  "geometry": {"coordinates":[-76.85420000000001,41.020299],"type":"Point"}
}