{
  "type": "Feature",
  "properties": {
    "addr:full":"128 Valley View Dr Butler PA 16002",
    "addr:housenumber":"128",
    "addr:postcode":"16002",
    "addr:street":"Valley View Dr",
    "iso:country":"US",
    "sg:address":"128 Valley View Dr",
    "sg:city":"Butler",
    "sg:classifiers":[
        {
            "category":"Building & Trades",
            "subcategory":"Construction",
            "type":"Services"
        }
    ],
    "sg:phone":"+1 724 287 2434",
    "sg:postcode":"16002",
    "sg:province":"PA",
    "sg:tags":[
        "masonry",
        "contractor"
    ],
    "wof:name":"Swidzinski Masonry Inc",
    "wof:placetype":"venue"
},
  "geometry": {"coordinates":[-79.83382899999999,40.859445],"type":"Point"}
}