{
  "type": "Feature",
  "properties": {
    "iso:country":"US",
    "sg:address":"8 Elizabeth Ct",
    "sg:city":"Downingtown",
    "sg:classifiers":[
        {
            "category":"Freight",
            "type":"Transportation"
        }
    ],
    "sg:phone":"+1 610 518 5226",
    "sg:postcode":"19335",
    "sg:province":"PA",
    "sg:tags":[
        "trucking"
    ],
    "wof:name":"Carrera Auto Transport",
    "wof:placetype":"venue"
},
  "geometry": {"coordinates":[-75.728435,40.010101],"type":"Point"}
}