{
  "type": "Feature",
  "properties": {
    "iso:country":"US",
    "sg:address":"101 E Broad St",
    "sg:city":"Tamaqua",
    "sg:classifiers":[
        {
            "category":"Shopping",
            "subcategory":"Clothing, Apparel, & Fashions",
            "type":"Retail Goods"
        }
    ],
    "sg:phone":"+1 570 668 2618",
    "sg:postcode":"18252",
    "sg:province":"PA",
    "sg:tags":[
        "sportswear"
    ],
    "wof:name":"The Company Store",
    "wof:placetype":"venue"
},
  "geometry": {"coordinates":[-75.96874,40.797335],"type":"Point"}
}