{
  "type": "Feature",
  "properties": {
    "iso:country":"US",
    "sg:address":"2661 S 69th St",
    "sg:city":"Philadelphia",
    "sg:classifiers":[
        {
            "category":"Restaurant",
            "type":"Food & Drink"
        }
    ],
    "sg:phone":"+1 215 492 1680",
    "sg:postcode":"19142",
    "sg:province":"PA",
    "sg:tags":[
        "beverage"
    ],
    "wof:name":"LCE Beer Distr",
    "wof:placetype":"venue"
},
  "geometry": {"coordinates":[-75.234058,39.916612],"type":"Point"}
}