{
  "type": "Feature",
  "properties": {
    "iso:country":"US",
    "sg:address":"138 Shannon Rd",
    "sg:city":"Renfrew",
    "sg:classifiers":[
        {
            "category":"Building & Trades",
            "subcategory":"Plumbing",
            "type":"Services"
        }
    ],
    "sg:phone":"+1 724 789 9476",
    "sg:postcode":"16053",
    "sg:province":"PA",
    "sg:tags":[
        "septic"
    ],
    "wof:name":"H W Kaltenbaugh Excavating",
    "wof:placetype":"venue"
},
  "geometry": {"coordinates":[-80.008554,40.834349],"type":"Point"}
}