{
  "type": "Feature",
  "properties": {
    "iso:country":"US",
    "sg:address":"828 Newtown Yardley Rd",
    "sg:city":"Newtown",
    "sg:classifiers":[
        {
            "category":"Professional",
            "subcategory":"Management & Consulting",
            "type":"Services"
        },
        {
            "category":"Manufacturing",
            "subcategory":"Printing",
            "type":"Manufacturing & Wholesale Goods"
        }
    ],
    "sg:phone":"+1 215 867 0044",
    "sg:postcode":"18940",
    "sg:province":"PA",
    "sg:tags":[
        "marketing",
        "program",
        "book"
    ],
    "wof:name":"Engel Publishing Partners",
    "wof:placetype":"venue"
},
  "geometry": {"coordinates":[-74.90731100000001,40.231156],"type":"Point"}
}