{
  "type": "Feature",
  "properties": {
    "addr:full":"1107 N Howard St Philadelphia PA 19123",
    "addr:housenumber":"1107",
    "addr:postcode":"19123",
    "addr:street":"N Howard St",
    "iso:country":"US",
    "sg:address":"1107 N Howard St",
    "sg:city":"Philadelphia",
    "sg:classifiers":[
        {
            "category":"Wholesale",
            "subcategory":"Chemicals & Plastics",
            "type":"Manufacturing & Wholesale Goods"
        }
    ],
    "sg:phone":"+1   ",
    "sg:postcode":"19123",
    "sg:province":"PA",
    "sg:tags":[
        "refrigerant",
        "gas",
        "sterilizing",
        "package"
    ],
    "wof:name":"Pennco Engineering Company",
    "wof:placetype":"venue"
},
  "geometry": {"coordinates":[-75.137405,39.968313],"type":"Point"}
}