{
  "type": "Feature",
  "properties": {
    "iso:country":"US",
    "sg:address":"713 Martha Ave",
    "sg:city":"Lancaster",
    "sg:classifiers":[
        {
            "category":"Wholesale",
            "subcategory":"Toys & Hobbies",
            "type":"Manufacturing & Wholesale Goods"
        }
    ],
    "sg:phone":"+1 717 394 7921",
    "sg:postcode":"17601",
    "sg:province":"PA",
    "sg:tags":[
        "doll"
    ],
    "wof:name":"Great Gifts",
    "wof:placetype":"venue"
},
  "geometry": {"coordinates":[-76.29294899999999,40.056463],"type":"Point"}
}