{
  "type": "Feature",
  "properties": {
    "addr:full":"701 Wheatland St Phoenixville PA 19460",
    "addr:housenumber":"701",
    "addr:postcode":"19460",
    "addr:street":"Wheatland St",
    "iso:country":"US",
    "sg:address":"701 Wheatland St",
    "sg:city":"Phoenixville",
    "sg:classifiers":[
        {
            "category":"Wholesale",
            "subcategory":"Beer",
            "type":"Manufacturing & Wholesale Goods"
        }
    ],
    "sg:phone":"+1 610 935 3111",
    "sg:postcode":"19460",
    "sg:province":"PA",
    "sg:tags":[
        "ale"
    ],
    "wof:name":"Superior Value Beverage Ctr",
    "wof:placetype":"venue"
},
  "geometry": {"coordinates":[-75.52865199999999,40.131955],"type":"Point"}
}