{
  "type": "Feature",
  "properties": {
    "addr:full":"101 W City Ave Jenkintown PA 19004",
    "addr:housenumber":"101",
    "addr:postcode":"19004",
    "addr:street":"W City Ave",
    "iso:country":"US",
    "sg:address":"101 W City Ave",
    "sg:city":"Jenkintown",
    "sg:classifiers":[
        {
            "category":"Professional",
            "subcategory":"Management & Consulting",
            "type":"Services"
        }
    ],
    "sg:phone":"+1   ",
    "sg:postcode":"19004",
    "sg:province":"PA",
    "wof:name":"Cbiz Accointing Tax Advisory -",
    "wof:placetype":"venue"
},
  "geometry": {"coordinates":[-75.23214900000001,39.998549],"type":"Point"}
}