{
  "type": "Feature",
  "properties": {
    "addr:full":"433 S Memorial Hwy Shavertown PA 18708",
    "addr:housenumber":"433",
    "addr:postcode":"18708",
    "addr:street":"S Memorial Hwy",
    "iso:country":"US",
    "sg:address":"433 S Memorial Hwy",
    "sg:city":"Shavertown",
    "sg:classifiers":[
        {
            "category":"Autos & Motor Vehicles",
            "subcategory":"Automobile Sales",
            "type":"Retail Goods"
        }
    ],
    "sg:phone":"+1 570 696 3092",
    "sg:postcode":"18708",
    "sg:province":"PA",
    "sg:tags":[
        "car",
        "used",
        "dealer"
    ],
    "wof:name":"Russell's Auto Sales",
    "wof:placetype":"venue"
},
  "geometry": {"coordinates":[-75.920525,41.292676],"type":"Point"}
}