{
  "type": "Feature",
  "properties": {
    "addr:full":"25 W 2nd St Hummelstown PA 17036",
    "addr:housenumber":"25",
    "addr:postcode":"17036",
    "addr:street":"W 2Nd St",
    "iso:country":"US",
    "sg:address":"25 W 2nd St",
    "sg:city":"Hummelstown",
    "sg:classifiers":[
        {
            "category":"Professional",
            "subcategory":"Lawyer & Legal Services",
            "type":"Services"
        }
    ],
    "sg:phone":"+1 717 230 9555",
    "sg:postcode":"17036",
    "sg:province":"PA",
    "sg:tags":[
        "attorney"
    ],
    "wof:name":"Craig A Doll",
    "wof:placetype":"venue"
},
  "geometry": {"coordinates":[-76.70968499999999,40.266416],"type":"Point"}
}