{
  "type": "Feature",
  "properties": {
    "iso:country":"US",
    "sg:address":"950 Swamp Bridge Rd",
    "sg:city":"Denver",
    "sg:classifiers":[
        {
            "category":"Real Estate",
            "subcategory":"Developer",
            "type":"Services"
        }
    ],
    "sg:phone":"+1   ",
    "sg:postcode":"17517",
    "sg:province":"PA",
    "sg:tags":[
        "cemetery"
    ],
    "wof:name":"Mohlers Cemetery Association",
    "wof:placetype":"venue"
},
  "geometry": {"coordinates":[-76.155486,40.253838],"type":"Point"}
}