{
  "type": "Feature",
  "properties": {
    "iso:country":"US",
    "sg:address":"1210 Charlestown Rd",
    "sg:city":"Phoenixville",
    "sg:classifiers":[
        {
            "category":"Building & Trades",
            "subcategory":"Construction",
            "type":"Services"
        }
    ],
    "sg:phone":"+1   ",
    "sg:postcode":"19460",
    "sg:province":"PA",
    "sg:tags":[
        "house"
    ],
    "wof:name":"Spring Meadows Quality Homes",
    "wof:placetype":"venue"
},
  "geometry": {"coordinates":[-75.538417,40.122175],"type":"Point"}
}