{
  "type": "Feature",
  "properties": {
    "addr:full":"110 E Main St Carnegie PA 15106",
    "addr:housenumber":"110",
    "addr:postcode":"15106",
    "addr:street":"E Main St",
    "iso:country":"US",
    "sg:address":"110 E Main St",
    "sg:city":"Carnegie",
    "sg:classifiers":[
        {
            "category":"Professional",
            "subcategory":"Business Services",
            "type":"Services"
        }
    ],
    "sg:phone":"+1 412 276 1223",
    "sg:postcode":"15106",
    "sg:province":"PA",
    "sg:tags":[
        "notary"
    ],
    "wof:name":"Plaza Realty",
    "wof:placetype":"venue"
},
  "geometry": {"coordinates":[-80.0868,40.407396],"type":"Point"}
}