{
  "type": "Feature",
  "properties": {
    "addr:full":"3341 Eastmont AVe. Pittsburgh PA 15289",
    "addr:housenumber":"3341",
    "addr:postcode":"15289",
    "addr:street":"Eastmont Ave.",
    "iso:country":"US",
    "sg:address":"3341 Eastmont AVe.",
    "sg:city":"Pittsburgh",
    "sg:classifiers":[
        {
            "category":"Arts & Performance",
            "subcategory":"Jazz & Blues",
            "type":"Entertainment"
        }
    ],
    "sg:phone":"+1 412 563 3865",
    "sg:postcode":"15289",
    "sg:province":"PA",
    "wof:name":"South Hills Guitar Lessons",
    "wof:placetype":"venue"
},
  "geometry": {"coordinates":[-80.03888999999999,40.385309],"type":"Point"}
}