{
  "type": "Feature",
  "properties": {
    "addr:full":"1266 E State St Sharon PA 16146",
    "addr:housenumber":"1266",
    "addr:postcode":"16146",
    "addr:street":"E State St",
    "iso:country":"US",
    "sg:address":"1266 E State St",
    "sg:city":"Sharon",
    "sg:classifiers":[
        {
            "category":"Banks & Credit Unions",
            "subcategory":"Investment Brokerage",
            "type":"Services"
        }
    ],
    "sg:phone":"+1 724 346 0645",
    "sg:postcode":"16146",
    "sg:province":"PA",
    "sg:tags":[
        "consultant",
        "planning",
        "financial"
    ],
    "wof:name":"Kelly & Assoc",
    "wof:placetype":"venue"
},
  "geometry": {"coordinates":[-80.485308,41.233058],"type":"Point"}
}