{
  "type": "Feature",
  "properties": {
    "iso:country":"US",
    "sg:address":"1910 Kenneth Rd",
    "sg:city":"York",
    "sg:classifiers":[
        {
            "category":"Health Services",
            "subcategory":"Doctor",
            "type":"Services"
        }
    ],
    "sg:phone":"+1   ",
    "sg:postcode":"17408",
    "sg:province":"PA",
    "wof:name":"Michael G Linebaugh DMD Ms",
    "wof:placetype":"venue"
},
  "geometry": {"coordinates":[-76.78147300000001,39.982476],"type":"Point"}
}