{
  "type": "Feature",
  "properties": {
    "addr:full":"20106 Valley Forge Cir King Of Prussia PA 19406",
    "addr:housenumber":"20106",
    "addr:postcode":"19406",
    "addr:street":"Valley Forge Cir",
    "iso:country":"US",
    "sg:address":"20106 Valley Forge Cir",
    "sg:city":"King Of Prussia",
    "sg:classifiers":[
        {
            "category":"Professional",
            "subcategory":"Computer Services",
            "type":"Services"
        }
    ],
    "sg:phone":"+1   ",
    "sg:postcode":"19406",
    "sg:province":"PA",
    "sg:tags":[
        "security",
        "product",
        "internet"
    ],
    "wof:name":"Accessit Training Services Inc",
    "wof:placetype":"venue"
},
  "geometry": {"coordinates":[-75.413757,40.104294],"type":"Point"}
}