{
  "type": "Feature",
  "properties": {
    "addr:full":"364 Tunnelhill St Gallitzin PA 16641",
    "addr:housenumber":"364",
    "addr:postcode":"16641",
    "addr:street":"Tunnelhill St",
    "iso:country":"US",
    "sg:address":"364 Tunnelhill St",
    "sg:city":"Gallitzin",
    "sg:classifiers":[
        {
            "category":"Manufacturing",
            "subcategory":"Food",
            "type":"Manufacturing & Wholesale Goods"
        },
        {
            "category":"Wholesale",
            "subcategory":"Groceries",
            "type":"Manufacturing & Wholesale Goods"
        }
    ],
    "sg:phone":"+1 814 886 8179",
    "sg:postcode":"16641",
    "sg:province":"PA",
    "sg:tags":[
        "baker",
        "product",
        "mfg"
    ],
    "wof:name":"Taddei's Cookies",
    "wof:placetype":"venue"
},
  "geometry": {"coordinates":[-78.541828,40.470027],"type":"Point"}
}