{
  "type": "Feature",
  "properties": {
    "iso:country":"US",
    "sg:address":"116 Byron Ave",
    "sg:city":"Altoona",
    "sg:classifiers":[
        {
            "category":"Professional",
            "subcategory":"Management & Consulting",
            "type":"Services"
        },
        {
            "category":"Personal",
            "type":"Services"
        },
        {
            "category":"Professional",
            "subcategory":"Detective & Security Services",
            "type":"Services"
        },
        {
            "category":"Professional",
            "subcategory":"Employment Agencies",
            "type":"Services"
        }
    ],
    "sg:phone":"+1 814 944 8500",
    "sg:postcode":"16602",
    "sg:province":"PA",
    "sg:tags":[
        "patrol",
        "consultant",
        "guard",
        "safety",
        "maintenance",
        "property",
        "opportunity"
    ],
    "sg:website":"http://www.securitasusa.com",
    "wof:name":"Securitas Security Services USA",
    "wof:placetype":"venue"
},
  "geometry": {"coordinates":[-78.402062,40.480879],"type":"Point"}
}