{
  "type": "Feature",
  "properties": {
    "iso:country":"US",
    "sg:address":"4740 Baltimore Ave",
    "sg:city":"Philadelphia",
    "sg:classifiers":[
        {
            "category":"Place Of Worship",
            "subcategory":"Church",
            "type":"Public Place"
        },
        {
            "category":"Place Of Worship",
            "type":"Public Place"
        },
        {
            "category":"Organizations",
            "subcategory":"Religious Organization",
            "type":"Services"
        }
    ],
    "sg:phone":"+1 215 729 2050",
    "sg:postcode":"19143",
    "sg:province":"PA",
    "sg:tags":[
        "churches-interdenominational",
        "denomination",
        "churches-various",
        "churches-mennonite",
        "brother"
    ],
    "wof:name":"West Philadelphia Mennonite Fellowship",
    "wof:placetype":"venue"
},
  "geometry": {"coordinates":[-75.217972,39.948546],"type":"Point"}
}