{
  "type": "Feature",
  "properties": {
    "iso:country":"US",
    "sg:address":"400 King of Prussia Rd",
    "sg:city":"Wayne",
    "sg:classifiers":[
        {
            "category":"Organizations",
            "subcategory":"Religious Organization",
            "type":"Services"
        }
    ],
    "sg:phone":"+1   ",
    "sg:postcode":"19087",
    "sg:province":"PA",
    "wof:name":"St Martins Church",
    "wof:placetype":"venue"
},
  "geometry": {"coordinates":[-75.362279,40.047278],"type":"Point"}
}