{
  "type": "Feature",
  "properties": {
    "addr:full":"1408 Reed St Philadelphia PA 19146",
    "addr:housenumber":"1408",
    "addr:postcode":"19146",
    "addr:street":"Reed St",
    "iso:country":"US",
    "sg:address":"1408 Reed St",
    "sg:city":"Philadelphia",
    "sg:classifiers":[
        {
            "category":"Retail",
            "subcategory":"Auto Repair",
            "type":"Services"
        }
    ],
    "sg:phone":"+1 215 389 3125",
    "sg:postcode":"19146",
    "sg:province":"PA",
    "wof:name":"Woodlyn Jas Auto Repair",
    "wof:placetype":"venue"
},
  "geometry": {"coordinates":[-75.168198,39.933102],"type":"Point"}
}