{
  "type": "Feature",
  "properties": {
    "addr:full":"3453 Sharon Rd West Middlesex PA 16159",
    "addr:housenumber":"3453",
    "addr:postcode":"16159",
    "addr:street":"Sharon Rd",
    "iso:country":"US",
    "sg:address":"3453 Sharon Rd",
    "sg:city":"West Middlesex",
    "sg:classifiers":[
        {
            "category":"Bars & Pubs",
            "type":"Food & Drink"
        }
    ],
    "sg:phone":"+1 724 528 3454",
    "sg:postcode":"16159",
    "sg:province":"PA",
    "wof:name":"Middlesex Inn",
    "wof:placetype":"venue"
},
  "geometry": {"coordinates":[-80.45545199999999,41.179824],"type":"Point"}
}