{
  "type": "Feature",
  "properties": {
    "iso:country":"US",
    "sg:address":"1457 Radcliffe St",
    "sg:city":"Bristol",
    "sg:classifiers":[
        {
            "category":"Professional",
            "subcategory":"Business Services",
            "type":"Services"
        }
    ],
    "sg:phone":"+1   ",
    "sg:postcode":"19007",
    "sg:province":"PA",
    "wof:name":"T S Fusco Inc",
    "wof:placetype":"venue"
},
  "geometry": {"coordinates":[-74.842575,40.103183],"type":"Point"}
}