{
  "type": "Feature",
  "properties": {
    "addr:full":"524 Simpson Rd Trafford PA 15085",
    "addr:housenumber":"524",
    "addr:postcode":"15085",
    "addr:street":"Simpson Rd",
    "iso:country":"US",
    "sg:address":"524 Simpson Rd",
    "sg:city":"Trafford",
    "sg:classifiers":[
        {
            "category":"Wholesale",
            "subcategory":"Electrical",
            "type":"Manufacturing & Wholesale Goods"
        }
    ],
    "sg:phone":"+1 724 864 8545",
    "sg:postcode":"15085",
    "sg:province":"PA",
    "sg:tags":[
        "equipment",
        "electric",
        "supply"
    ],
    "wof:name":"Square D",
    "wof:placetype":"venue"
},
  "geometry": {"coordinates":[-79.71418199999999,40.362736],"type":"Point"}
}