{
  "type": "Feature",
  "properties": {
    "iso:country":"US",
    "sg:address":"427 E Vernon Rd",
    "sg:city":"Philadelphia",
    "sg:classifiers":[
        {
            "category":"Professional",
            "subcategory":"Lawyer & Legal Services",
            "type":"Services"
        }
    ],
    "sg:phone":"+1 215 849 2328",
    "sg:postcode":"19119",
    "sg:province":"PA",
    "sg:tags":[
        "convention",
        "reporters-court"
    ],
    "wof:name":"Evelyn Carpenter",
    "wof:placetype":"venue"
},
  "geometry": {"coordinates":[-75.18006699999999,40.057913],"type":"Point"}
}