{
  "type": "Feature",
  "properties": {
    "addr:full":"273 East St Bloomsburg PA 17815",
    "addr:housenumber":"273",
    "addr:postcode":"17815",
    "addr:street":"East St",
    "iso:country":"US",
    "sg:address":"273 East St",
    "sg:city":"Bloomsburg",
    "sg:classifiers":[
        {
            "category":"Health Services",
            "subcategory":"Health Practitioner",
            "type":"Services"
        }
    ],
    "sg:phone":"+1 570 380 8980",
    "sg:postcode":"17815",
    "sg:province":"PA",
    "sg:tags":[
        "psychologist"
    ],
    "wof:name":"Kathryn M Psy D Lindenfeld",
    "wof:placetype":"venue"
},
  "geometry": {"coordinates":[-76.45174,41.003334],"type":"Point"}
}