{
  "type": "Feature",
  "properties": {
    "addr:full":"247 S Main St Greensburg PA 15601",
    "addr:housenumber":"247",
    "addr:postcode":"15601",
    "addr:street":"S Main St",
    "iso:country":"US",
    "sg:address":"247 S Main St",
    "sg:city":"Greensburg",
    "sg:classifiers":[
        {
            "category":"Insurance",
            "subcategory":"Insurance Agent",
            "type":"Services"
        }
    ],
    "sg:phone":"+1 724 832 8001",
    "sg:postcode":"15601",
    "sg:province":"PA",
    "wof:name":"Diversified Brokerage Svc Inc",
    "wof:placetype":"venue"
},
  "geometry": {"coordinates":[-79.54360800000001,40.300832],"type":"Point"}
}