{
  "type": "Feature",
  "properties": {
    "iso:country":"US",
    "sg:address":"551 Mahoning St",
    "sg:city":"Milton",
    "sg:classifiers":[
        {
            "category":"Food & Beverages",
            "subcategory":"Liquor & Beverages",
            "type":"Retail Goods"
        }
    ],
    "sg:phone":"+1   ",
    "sg:postcode":"17847",
    "sg:province":"PA",
    "sg:tags":[
        "regulation",
        "commercial",
        "sect",
        "alcoholic"
    ],
    "wof:name":"Wine & Spirits Shoppe 4904",
    "wof:placetype":"venue"
},
  "geometry": {"coordinates":[-76.84464800000001,41.011539],"type":"Point"}
}