{
  "type": "Feature",
  "properties": {
    "iso:country":"US",
    "sg:address":"5562 Evans Rd",
    "sg:city":"Export",
    "sg:classifiers":[
        {
            "category":"Building & Trades",
            "subcategory":"Construction",
            "type":"Services"
        }
    ],
    "sg:phone":"+1 724 733 2742",
    "sg:postcode":"15632",
    "sg:province":"PA",
    "sg:tags":[
        "contractor",
        "painting",
        "hanging"
    ],
    "wof:name":"Pennington Papering",
    "wof:placetype":"venue"
},
  "geometry": {"coordinates":[-79.63756600000001,40.455843],"type":"Point"}
}