{
  "type": "Feature",
  "properties": {
    "iso:country":"US",
    "sg:address":"421 Cochran Rd",
    "sg:city":"Pittsburgh",
    "sg:classifiers":[
        {
            "category":"Insurance",
            "subcategory":"Insurance Agent",
            "type":"Services"
        }
    ],
    "sg:phone":"+1 412 563 5900",
    "sg:postcode":"15228",
    "sg:province":"PA",
    "sg:tags":[
        "auto"
    ],
    "sg:website":"http://www.kartsonasinsurance.com?utm_source=yp&utm_medium=cpc&utm_campaign=ck_yp",
    "wof:name":"KARTSONAS AGENCY, INC.",
    "wof:placetype":"venue"
},
  "geometry": {"coordinates":[-80.05307999999999,40.384419],"type":"Point"}
}