{
  "type": "Feature",
  "properties": {
    "iso:country":"US",
    "sg:address":"4985 Pennway St",
    "sg:city":"Philadelphia",
    "sg:classifiers":[
        {
            "category":"Professional",
            "type":"Services"
        }
    ],
    "sg:phone":"+1 215 535 0460",
    "sg:postcode":"19124",
    "sg:province":"PA",
    "sg:tags":[
        "establishment"
    ],
    "wof:name":"Comhar Inc",
    "wof:placetype":"venue"
},
  "geometry": {"coordinates":[-75.110187,40.023701],"type":"Point"}
}