{
  "type": "Feature",
  "properties": {
    "addr:full":"6121 Ridge Ave Philadelphia PA 19128",
    "addr:housenumber":"6121",
    "addr:postcode":"19128",
    "addr:street":"Ridge Ave",
    "iso:country":"US",
    "sg:address":"6121 Ridge Ave",
    "sg:city":"Philadelphia",
    "sg:classifiers":[
        {
            "category":"Banks & Credit Unions",
            "subcategory":"Bank",
            "type":"Services"
        }
    ],
    "sg:phone":"+1 215 483 4445",
    "sg:postcode":"19128",
    "sg:province":"PA",
    "sg:tags":[
        "cashing",
        "money",
        "order",
        "check"
    ],
    "sg:website":"http://www.acecashexpress.com",
    "wof:name":"Ace Check Cashing",
    "wof:placetype":"venue"
},
  "geometry": {"coordinates":[-75.215923,40.034109],"type":"Point"}
}