{
  "type": "Feature",
  "properties": {
    "iso:country":"US",
    "sg:address":"136 Allen St",
    "sg:city":"Beaver Falls",
    "sg:classifiers":[
        {
            "category":"Professional",
            "type":"Services"
        }
    ],
    "sg:phone":"+1   ",
    "sg:postcode":"15010",
    "sg:province":"PA",
    "wof:name":"Pierce Ss Associate",
    "wof:placetype":"venue"
},
  "geometry": {"coordinates":[-80.396069,40.767576],"type":"Point"}
}