{
  "type": "Feature",
  "properties": {
    "addr:full":"4415 Nittany Valley Dr Howard PA 16841",
    "addr:housenumber":"4415",
    "addr:postcode":"16841",
    "addr:street":"Nittany Valley Dr",
    "iso:country":"US",
    "sg:address":"4415 Nittany Valley Dr",
    "sg:city":"Howard",
    "sg:classifiers":[
        {
            "category":"Professional",
            "subcategory":"Business Services",
            "type":"Services"
        }
    ],
    "sg:phone":"+1 570 726 3498",
    "sg:postcode":"16841",
    "sg:province":"PA",
    "sg:tags":[
        "paralegal"
    ],
    "wof:name":"Central Paralegal Svc",
    "wof:placetype":"venue"
},
  "geometry": {"coordinates":[-77.55721200000001,40.997082],"type":"Point"}
}