{
  "type": "Feature",
  "properties": {
    "iso:country":"US",
    "sg:address":"213 Trading Post Rd",
    "sg:city":"Stoystown",
    "sg:classifiers":[
        {
            "category":"Wholesale",
            "subcategory":"Machinery & Supplies",
            "type":"Manufacturing & Wholesale Goods"
        }
    ],
    "sg:phone":"+1   ",
    "sg:postcode":"15563",
    "sg:province":"PA",
    "sg:tags":[
        "equipment"
    ],
    "wof:name":"Larry L Hemminger",
    "wof:placetype":"venue"
},
  "geometry": {"coordinates":[-79.024046,40.133363],"type":"Point"}
}