{
  "type": "Feature",
  "properties": {
    "iso:country":"US",
    "sg:address":"26 Valley Rd",
    "sg:city":"Shrewsbury",
    "sg:phone":"+1   ",
    "sg:postcode":"17361",
    "sg:province":"PA",
    "sg:tags":[
        "farm",
        "grain",
        "cash"
    ],
    "wof:name":"Jerry Walker",
    "wof:placetype":"venue"
},
  "geometry": {"coordinates":[-76.682042,39.784083],"type":"Point"}
}