{
  "type": "Feature",
  "properties": {
    "addr:full":"640 W Dekalb Pike King Of Prussia PA 19406",
    "addr:housenumber":"640",
    "addr:postcode":"19406",
    "addr:street":"W Dekalb Pike",
    "iso:country":"US",
    "sg:address":"640 W Dekalb Pike",
    "sg:city":"King Of Prussia",
    "sg:classifiers":[
        {
            "category":"Shopping",
            "subcategory":"Clothing, Apparel, & Fashions",
            "type":"Retail Goods"
        }
    ],
    "sg:phone":"+1 610 337 8636",
    "sg:postcode":"19406",
    "sg:province":"PA",
    "sg:website":"www.hm.com",
    "wof:name":"H & M",
    "wof:placetype":"venue"
},
  "geometry": {"coordinates":[-75.38329899999999,40.087908],"type":"Point"}
}