{
  "type": "Feature",
  "properties": {
    "iso:country":"US",
    "sg:address":"401 S Main St",
    "sg:city":"Zelienople",
    "sg:classifiers":[
        {
            "category":"Real Estate",
            "subcategory":"Real Estate Operator",
            "type":"Services"
        }
    ],
    "sg:phone":"+1 724 452 7448",
    "sg:postcode":"16063",
    "sg:province":"PA",
    "sg:tags":[
        "apartment"
    ],
    "wof:name":"Luther Court Inc",
    "wof:placetype":"venue"
},
  "geometry": {"coordinates":[-80.13622599999999,40.791404],"type":"Point"}
}