{
  "type": "Feature",
  "properties": {
    "iso:country":"US",
    "sg:address":"1580 Derry Dr",
    "sg:city":"Dresher",
    "sg:classifiers":[
        {
            "category":"Shopping",
            "type":"Retail Goods"
        }
    ],
    "sg:phone":"+1   ",
    "sg:postcode":"19025",
    "sg:province":"PA",
    "sg:tags":[
        "merchandise"
    ],
    "wof:name":"E M P Engineering Services",
    "wof:placetype":"venue"
},
  "geometry": {"coordinates":[-75.166736,40.155008],"type":"Point"}
}