{
  "type": "Feature",
  "properties": {
    "iso:country":"US",
    "sg:address":"830 E Baltimore Pike",
    "sg:city":"Kennett Square",
    "sg:classifiers":[
        {
            "category":"Banks & Credit Unions",
            "subcategory":"Bank",
            "type":"Services"
        }
    ],
    "sg:phone":"+1 610 925 5000",
    "sg:postcode":"19348",
    "sg:province":"PA",
    "wof:name":"Wsfs Bank",
    "wof:placetype":"venue"
},
  "geometry": {"coordinates":[-75.687302,39.859699],"type":"Point"}
}