{
  "type": "Feature",
  "properties": {
    "iso:country":"US",
    "sg:address":"135 Race St",
    "sg:city":"Clearfield",
    "sg:classifiers":[
        {
            "category":"Home & Garden",
            "subcategory":"Furniture",
            "type":"Retail Goods"
        }
    ],
    "sg:phone":"+1 814 765 7447",
    "sg:postcode":"16830",
    "sg:province":"PA",
    "sg:tags":[
        "store"
    ],
    "wof:name":"Rowles Family Furniture Inc",
    "wof:placetype":"venue"
},
  "geometry": {"coordinates":[-78.438514,41.029812],"type":"Point"}
}