{
  "type": "Feature",
  "properties": {
    "iso:country":"US",
    "sg:address":"106 Meadow Dr",
    "sg:city":"Ligonier",
    "sg:classifiers":[
        {
            "category":"Shopping",
            "subcategory":"Hobbies, Toys, & Games",
            "type":"Retail Goods"
        },
        {
            "category":"Shopping",
            "subcategory":"Crafts & Fabrics",
            "type":"Retail Goods"
        }
    ],
    "sg:phone":"+1 724 238 8557",
    "sg:postcode":"15658",
    "sg:province":"PA",
    "sg:tags":[
        "shop",
        "hobby",
        "model",
        "supply"
    ],
    "wof:name":"Celtic Craft And Quillery By Patrice",
    "wof:placetype":"venue"
},
  "geometry": {"coordinates":[-79.218371,40.248397],"type":"Point"}
}