{
  "type": "Feature",
  "properties": {
    "iso:country":"US",
    "sg:address":"703 Wilmington Rd",
    "sg:city":"New Castle",
    "sg:classifiers":[
        {
            "category":"Manufacturing",
            "subcategory":"Printing",
            "type":"Manufacturing & Wholesale Goods"
        }
    ],
    "sg:phone":"+1 724 652 6802",
    "sg:postcode":"16101",
    "sg:province":"PA",
    "sg:tags":[
        "printer"
    ],
    "sg:website":"www.quickprintnc.com",
    "wof:name":"Quik Print",
    "wof:placetype":"venue"
},
  "geometry": {"coordinates":[-80.348308,41.008574],"type":"Point"}
}