{
  "type": "Feature",
  "properties": {
    "iso:country":"US",
    "sg:address":"776 Caldwell Ave",
    "sg:city":"New Kensington",
    "sg:classifiers":[
        {
            "category":"Shopping",
            "subcategory":"Clothing, Apparel, & Fashions",
            "type":"Retail Goods"
        }
    ],
    "sg:phone":"+1 724 337 9449",
    "sg:postcode":"15068",
    "sg:province":"PA",
    "sg:tags":[
        "personal",
        "shop",
        "bridal"
    ],
    "wof:name":"Babe's Broadway Bridal & Btq",
    "wof:placetype":"venue"
},
  "geometry": {"coordinates":[-79.751682,40.589874],"type":"Point"}
}