{
  "type": "Feature",
  "properties": {
    "iso:country":"US",
    "sg:address":"475 Vine St",
    "sg:city":"Lebanon",
    "sg:classifiers":[
        {
            "category":"Home & Garden",
            "subcategory":"Carpets & Floor Coverings",
            "type":"Retail Goods"
        }
    ],
    "sg:phone":"+1 717 273 7271",
    "sg:postcode":"17042",
    "sg:province":"PA",
    "sg:tags":[
        "cleaning"
    ],
    "wof:name":"United Rug",
    "wof:placetype":"venue"
},
  "geometry": {"coordinates":[-76.41739,40.330117],"type":"Point"}
}