{
  "type": "Feature",
  "properties": {
    "iso:country":"US",
    "sg:address":"9381 Pembroke Cir",
    "sg:city":"Irwin",
    "sg:classifiers":[
        {
            "category":"Professional",
            "subcategory":"Management & Consulting",
            "type":"Services"
        }
    ],
    "sg:phone":"+1 724 863 2363",
    "sg:postcode":"15642",
    "sg:province":"PA",
    "sg:tags":[
        "consultant",
        "business"
    ],
    "wof:name":"SHS Group Holdings LLC",
    "wof:placetype":"venue"
},
  "geometry": {"coordinates":[-79.701087,40.313813],"type":"Point"}
}