{
  "type": "Feature",
  "properties": {
    "iso:country":"US",
    "sg:address":"357 Deckards Run Rd",
    "sg:city":"Utica",
    "sg:classifiers":[
        {
            "category":"Government",
            "subcategory":"Office",
            "type":"Public Place"
        }
    ],
    "sg:phone":"+1 814 425 8338",
    "sg:postcode":"16362",
    "sg:province":"PA",
    "sg:tags":[
        "village"
    ],
    "wof:name":"Canal Twp Supervisor",
    "wof:placetype":"venue"
},
  "geometry": {"coordinates":[-79.949017,41.483091],"type":"Point"}
}