{
  "type": "Feature",
  "properties": {
    "iso:country":"US",
    "sg:address":"1223 Markley St",
    "sg:city":"Norristown",
    "sg:classifiers":[
        {
            "category":"Building & Trades",
            "subcategory":"Construction",
            "type":"Services"
        }
    ],
    "sg:phone":"+1 610 275 7432",
    "sg:postcode":"19401",
    "sg:province":"PA",
    "sg:tags":[
        "home",
        "improvement"
    ],
    "wof:name":"RKE Svc",
    "wof:placetype":"venue"
},
  "geometry": {"coordinates":[-75.340889,40.124503],"type":"Point"}
}