{
  "type": "Feature",
  "properties": {
    "iso:country":"US",
    "sg:address":"109 Carre Ave",
    "sg:city":"Essington",
    "sg:classifiers":[
        {
            "category":"Building & Trades",
            "subcategory":"Construction",
            "type":"Services"
        }
    ],
    "sg:phone":"+1 610 453 3500",
    "sg:postcode":"19029",
    "sg:province":"PA",
    "sg:tags":[
        "contractor",
        "mechanical"
    ],
    "wof:name":"Mechanical Machine Systems",
    "wof:placetype":"venue"
},
  "geometry": {"coordinates":[-75.29798,39.861505],"type":"Point"}
}