{
  "type": "Feature",
  "properties": {
    "addr:full":"332 4th St Freeport PA 16229",
    "addr:housenumber":"332",
    "addr:postcode":"16229",
    "addr:street":"4Th St",
    "iso:country":"US",
    "sg:address":"332 4th St",
    "sg:city":"Freeport",
    "sg:classifiers":[
        {
            "category":"Health Services",
            "subcategory":"Optometrist",
            "type":"Services"
        }
    ],
    "sg:phone":"+1 724 295 5127",
    "sg:postcode":"16229",
    "sg:province":"PA",
    "wof:name":"Eye Care Ctr",
    "wof:placetype":"venue"
},
  "geometry": {"coordinates":[-79.687513,40.675438],"type":"Point"}
}