{
  "type": "Feature",
  "properties": {
    "addr:full":"415 Cedar Hill Rd Birdsboro PA 19508",
    "addr:housenumber":"415",
    "addr:postcode":"19508",
    "addr:street":"Cedar Hill Rd",
    "iso:country":"US",
    "sg:address":"415 Cedar Hill Rd",
    "sg:city":"Birdsboro",
    "sg:classifiers":[
        {
            "category":"Education",
            "subcategory":"Vocational School",
            "type":"Public Place"
        }
    ],
    "sg:phone":"+1 610 404 4192",
    "sg:postcode":"19508",
    "sg:province":"PA",
    "sg:tags":[
        "training",
        "computer"
    ],
    "wof:name":"Sls Consulting LLC",
    "wof:placetype":"venue"
},
  "geometry": {"coordinates":[-75.84406799999999,40.264933],"type":"Point"}
}