{
  "type": "Feature",
  "properties": {
    "iso:country":"US",
    "sg:address":"66 N Church St",
    "sg:city":"Carbondale",
    "sg:classifiers":[
        {
            "category":"Social Services",
            "subcategory":"Adult Care",
            "type":"Services"
        },
        {
            "category":"Social Services",
            "type":"Services"
        }
    ],
    "sg:phone":"+1 570 282 6167",
    "sg:postcode":"18407",
    "sg:province":"PA",
    "sg:tags":[
        "organization",
        "senior",
        "citizen"
    ],
    "wof:name":"Carbondale Senior Activity Ctr",
    "wof:placetype":"venue"
},
  "geometry": {"coordinates":[-75.49922100000001,41.574504],"type":"Point"}
}