{
  "type": "Feature",
  "properties": {
    "addr:full":"1985 Wenger Ln Chambersburg PA 17201",
    "addr:housenumber":"1985",
    "addr:postcode":"17201",
    "addr:street":"Wenger Ln",
    "iso:country":"US",
    "sg:address":"1985 Wenger Ln",
    "sg:city":"Chambersburg",
    "sg:classifiers":[
        {
            "category":"Place Of Worship",
            "subcategory":"Church",
            "type":"Public Place"
        },
        {
            "category":"Place Of Worship",
            "type":"Public Place"
        }
    ],
    "sg:phone":"+1 717 267 1346",
    "sg:postcode":"17201",
    "sg:province":"PA",
    "sg:tags":[
        "churches-non-denominational",
        "christ",
        "churches-community"
    ],
    "sg:website":"http://www.spiritofchristonline.com",
    "wof:name":"Spirit Of Christ Community Church",
    "wof:placetype":"venue"
},
  "geometry": {"coordinates":[-77.652209,39.95324],"type":"Point"}
}