{
  "type": "Feature",
  "properties": {
    "iso:country":"US",
    "sg:address":"4220 Ogden St",
    "sg:city":"Philadelphia",
    "sg:classifiers":[
        {
            "category":"Building & Trades",
            "subcategory":"Construction",
            "type":"Services"
        }
    ],
    "sg:phone":"+1 215 823 6775",
    "sg:postcode":"19104",
    "sg:province":"PA",
    "sg:tags":[
        "general",
        "contractor"
    ],
    "wof:name":"One Man Gang Construction LLC",
    "wof:placetype":"venue"
},
  "geometry": {"coordinates":[-75.20842500000001,39.968885],"type":"Point"}
}