{
  "type": "Feature",
  "properties": {
    "iso:country":"US",
    "sg:address":"81 S Main St",
    "sg:city":"Morrisville",
    "sg:classifiers":[
        {
            "category":"Health Services",
            "subcategory":"Chiropractor",
            "type":"Services"
        }
    ],
    "sg:phone":"+1   ",
    "sg:postcode":"19067",
    "sg:province":"PA",
    "wof:name":"Lieber Matthew",
    "wof:placetype":"venue"
},
  "geometry": {"coordinates":[-74.837838,40.241616],"type":"Point"}
}