{
  "type": "Feature",
  "properties": {
    "iso:country":"US",
    "sg:address":"1730 State Rte 72",
    "sg:city":"Lebanon",
    "sg:classifiers":[
        {
            "category":"Food & Beverages",
            "subcategory":"Specialty",
            "type":"Retail Goods"
        }
    ],
    "sg:phone":"+1 717 273 2370",
    "sg:postcode":"17046",
    "sg:province":"PA",
    "sg:tags":[
        "water",
        "bulk",
        "company"
    ],
    "wof:name":"Wissahickon Spring Water Co",
    "wof:placetype":"venue"
},
  "geometry": {"coordinates":[-76.464296,40.363818],"type":"Point"}
}