{
  "type": "Feature",
  "properties": {
    "addr:full":"2429 Saratoga Dr Hermitage PA 16148",
    "addr:housenumber":"2429",
    "addr:postcode":"16148",
    "addr:street":"Saratoga Dr",
    "iso:country":"US",
    "sg:address":"2429 Saratoga Dr",
    "sg:city":"Hermitage",
    "sg:classifiers":[
        {
            "category":"Professional",
            "type":"Services"
        }
    ],
    "sg:phone":"+1   ",
    "sg:postcode":"16148",
    "sg:province":"PA",
    "wof:name":"Free & Accepted Masons of",
    "wof:placetype":"venue"
},
  "geometry": {"coordinates":[-80.464736,41.255592],"type":"Point"}
}