{
  "type": "Feature",
  "properties": {
    "iso:country":"US",
    "sg:address":"6545 N Uber St",
    "sg:city":"Philadelphia",
    "sg:classifiers":[
        {
            "category":"Shopping",
            "subcategory":"Florist",
            "type":"Retail Goods"
        }
    ],
    "sg:phone":"+1 215 276 3707",
    "sg:postcode":"19138",
    "sg:province":"PA",
    "sg:tags":[
        "shop",
        "gift"
    ],
    "wof:name":"Jafel Florists",
    "wof:placetype":"venue"
},
  "geometry": {"coordinates":[-75.15064700000001,40.053804],"type":"Point"}
}