{
  "type": "Feature",
  "properties": {
    "iso:country":"US",
    "sg:address":"207 Lincoln Way E",
    "sg:city":"New Oxford",
    "sg:classifiers":[
        {
            "category":"Professional",
            "subcategory":"Accounting & Tax Preparation",
            "type":"Services"
        }
    ],
    "sg:phone":"+1 717 624 3300",
    "sg:postcode":"17350",
    "sg:province":"PA",
    "sg:tags":[
        "accountant"
    ],
    "wof:name":"New Oxford Accounting & Tax",
    "wof:placetype":"venue"
},
  "geometry": {"coordinates":[-77.05256,39.864646],"type":"Point"}
}