{
  "type": "Feature",
  "properties": {
    "iso:country":"US",
    "sg:address":"2911 Schoenersville Rd",
    "sg:city":"Bethlehem",
    "sg:classifiers":[
        {
            "category":"Building & Trades",
            "subcategory":"Construction",
            "type":"Services"
        }
    ],
    "sg:phone":"+1 610 865 2560",
    "sg:postcode":"18017",
    "sg:province":"PA",
    "sg:tags":[
        "carpenter"
    ],
    "wof:name":"Don Longenbach's Carpentry",
    "wof:placetype":"venue"
},
  "geometry": {"coordinates":[-75.40838599999999,40.647774],"type":"Point"}
}