{
  "type": "Feature",
  "properties": {
    "iso:country":"US",
    "sg:address":"162 Miller Rd",
    "sg:city":"New Providence",
    "sg:classifiers":[
        {
            "category":"Building & Trades",
            "subcategory":"Construction",
            "type":"Services"
        }
    ],
    "sg:phone":"+1 717 284 0933",
    "sg:postcode":"17560",
    "sg:province":"PA",
    "sg:tags":[
        "resurfacing",
        "refinishing",
        "floor"
    ],
    "wof:name":"Tennant Co",
    "wof:placetype":"venue"
},
  "geometry": {"coordinates":[-76.264257,39.920959],"type":"Point"}
}