{
  "type": "Feature",
  "properties": {
    "iso:country":"US",
    "sg:address":"1044 Centre Tpke",
    "sg:city":"Orwigsburg",
    "sg:classifiers":[
        {
            "category":"Travel",
            "subcategory":"Hotels & Motels",
            "type":"Entertainment"
        }
    ],
    "sg:phone":"+1 570 366 2091",
    "sg:postcode":"17961",
    "sg:province":"PA",
    "sg:tags":[
        "lodging"
    ],
    "wof:name":"Fort Motel",
    "wof:placetype":"venue"
},
  "geometry": {"coordinates":[-76.06610999999999,40.632895],"type":"Point"}
}