{
  "type": "Feature",
  "properties": {
    "iso:country":"US",
    "sg:address":"232 Kathleen Dr",
    "sg:city":"Peckville",
    "sg:classifiers":[
        {
            "category":"Personal",
            "subcategory":"Beauty Salon",
            "type":"Services"
        }
    ],
    "sg:phone":"+1 570 489 5440",
    "sg:postcode":"18452",
    "sg:province":"PA",
    "wof:name":"Carrie Stefursky's Beauty Shop",
    "wof:placetype":"venue"
},
  "geometry": {"coordinates":[-75.582815,41.482227],"type":"Point"}
}