{
  "type": "Feature",
  "properties": {
    "iso:country":"US",
    "sg:address":"212 Gristmill Rd",
    "sg:city":"New Holland",
    "sg:classifiers":[
        {
            "category":"Home & Garden",
            "subcategory":"Furniture",
            "type":"Retail Goods"
        }
    ],
    "sg:phone":"+1 717 354 6729",
    "sg:postcode":"17557",
    "sg:province":"PA",
    "sg:tags":[
        "builder",
        "custom"
    ],
    "wof:name":"Grist Mill Custom Furniture",
    "wof:placetype":"venue"
},
  "geometry": {"coordinates":[-76.10128,40.137655],"type":"Point"}
}