{
  "type": "Feature",
  "properties": {
    "addr:full":"737 Greenville Rd Mercer PA 16137",
    "addr:housenumber":"737",
    "addr:postcode":"16137",
    "addr:street":"Greenville Rd",
    "iso:country":"US",
    "sg:address":"737 Greenville Rd",
    "sg:city":"Mercer",
    "sg:classifiers":[
        {
            "category":"Health Services",
            "subcategory":"Health Practitioner",
            "type":"Services"
        }
    ],
    "sg:phone":"+1   ",
    "sg:postcode":"16137",
    "sg:province":"PA",
    "wof:name":"Counseling Psychological Assoc",
    "wof:placetype":"venue"
},
  "geometry": {"coordinates":[-80.248622,41.248593],"type":"Point"}
}