{
  "type": "Feature",
  "properties": {
    "addr:full":"329 Basin Park Bristol PA 19007",
    "addr:housenumber":"329",
    "addr:postcode":"19007",
    "addr:street":"Basin Park",
    "iso:country":"US",
    "sg:address":"329 Basin Park",
    "sg:city":"Bristol",
    "sg:classifiers":[
        {
            "category":"Building & Trades",
            "subcategory":"Locksmith",
            "type":"Services"
        }
    ],
    "sg:phone":"+1 267 543 3658",
    "sg:postcode":"19007",
    "sg:province":"PA",
    "sg:tags":[
        "key"
    ],
    "wof:name":"Locksmith",
    "wof:placetype":"venue"
},
  "geometry": {"coordinates":[-74.859171,40.09558],"type":"Point"}
}