{
  "type": "Feature",
  "properties": {
    "iso:country":"US",
    "sg:address":"409 Yetter Rd",
    "sg:city":"Muncy",
    "sg:classifiers":[
        {
            "category":"Building & Trades",
            "subcategory":"Landscaping Services",
            "type":"Services"
        }
    ],
    "sg:phone":"+1 570 546 8538",
    "sg:postcode":"17756",
    "sg:province":"PA",
    "sg:tags":[
        "lawn",
        "maintenance"
    ],
    "wof:name":"Smith's Lawn Care, Inc.",
    "wof:placetype":"venue"
},
  "geometry": {"coordinates":[-76.805402,41.230917],"type":"Point"}
}