{
  "type": "Feature",
  "properties": {
    "addr:full":"3100 Shillington Rd Reading PA 19608",
    "addr:housenumber":"3100",
    "addr:postcode":"19608",
    "addr:street":"Shillington Rd",
    "iso:country":"US",
    "sg:address":"3100 Shillington Rd",
    "sg:city":"Reading",
    "sg:classifiers":[
        {
            "category":"Retail",
            "subcategory":"Auto Repair",
            "type":"Services"
        }
    ],
    "sg:phone":"+1   ",
    "sg:postcode":"19608",
    "sg:province":"PA",
    "sg:tags":[
        "automotive"
    ],
    "wof:name":"A 1 Auto Towing",
    "wof:placetype":"venue"
},
  "geometry": {"coordinates":[-76.009311,40.32096],"type":"Point"}
}