{
  "type": "Feature",
  "properties": {
    "iso:country":"US",
    "sg:address":"981 5th Ave",
    "sg:city":"New Kensington",
    "sg:classifiers":[
        {
            "category":"Manufacturing",
            "subcategory":"Food",
            "type":"Manufacturing & Wholesale Goods"
        }
    ],
    "sg:phone":"+1 724 335 4371",
    "sg:postcode":"15068",
    "sg:province":"PA",
    "sg:tags":[
        "mfg",
        "chocolate"
    ],
    "wof:name":"Catoris Candies Inc",
    "wof:placetype":"venue"
},
  "geometry": {"coordinates":[-79.765315,40.565652],"type":"Point"}
}