{
  "type": "Feature",
  "properties": {
    "iso:country":"US",
    "sg:address":"917 Cadet St",
    "sg:city":"New Castle",
    "sg:classifiers":[
        {
            "category":"Home & Garden",
            "subcategory":"Furniture",
            "type":"Retail Goods"
        }
    ],
    "sg:phone":"+1 724 652 6731",
    "sg:postcode":"16101",
    "sg:province":"PA",
    "sg:tags":[
        "builder",
        "custom"
    ],
    "wof:name":"Moosewood Furniture",
    "wof:placetype":"venue"
},
  "geometry": {"coordinates":[-80.32647299999999,40.992519],"type":"Point"}
}