{
  "type": "Feature",
  "properties": {
    "addr:full":"203 Kline Ave Evans City PA 16033",
    "addr:housenumber":"203",
    "addr:postcode":"16033",
    "addr:street":"Kline Ave",
    "iso:country":"US",
    "sg:address":"203 Kline Ave",
    "sg:city":"Evans City",
    "sg:classifiers":[
        {
            "category":"Building & Trades",
            "subcategory":"Construction",
            "type":"Services"
        }
    ],
    "sg:phone":"+1   ",
    "sg:postcode":"16033",
    "sg:province":"PA",
    "sg:tags":[
        "excavation",
        "contractor"
    ],
    "wof:name":"Backhoe Service Joe Buttermore",
    "wof:placetype":"venue"
},
  "geometry": {"coordinates":[-80.03865399999999,40.73981],"type":"Point"}
}