{
  "type": "Feature",
  "properties": {
    "iso:country":"US",
    "sg:address":"2139 Catharine St",
    "sg:city":"Philadelphia",
    "sg:classifiers":[
        {
            "category":"Professional",
            "subcategory":"Management & Consulting",
            "type":"Services"
        }
    ],
    "sg:phone":"+1 215 545 8581",
    "sg:postcode":"19146",
    "sg:province":"PA",
    "sg:tags":[
        "promotion",
        "sales"
    ],
    "wof:name":"Tech Info Providers",
    "wof:placetype":"venue"
},
  "geometry": {"coordinates":[-75.17870000000001,39.942421],"type":"Point"}
}