{
  "type": "Feature",
  "properties": {
    "iso:country":"US",
    "sg:address":"520 Diamond Dr",
    "sg:city":"Lebanon",
    "sg:classifiers":[
        {
            "category":"Sports & Exercise",
            "subcategory":"Stables",
            "type":"Entertainment"
        }
    ],
    "sg:phone":"+1 717 867 5306",
    "sg:postcode":"17042",
    "sg:province":"PA",
    "sg:tags":[
        "horse"
    ],
    "wof:name":"Graystone Stables",
    "wof:placetype":"venue"
},
  "geometry": {"coordinates":[-76.491147,40.270644],"type":"Point"}
}