{
  "type": "Feature",
  "properties": {
    "addr:full":"211 Charles St Pittsburgh PA 15210",
    "addr:housenumber":"211",
    "addr:postcode":"15210",
    "addr:street":"Charles St",
    "iso:country":"US",
    "sg:address":"211 Charles St",
    "sg:city":"Pittsburgh",
    "sg:classifiers":[
        {
            "category":"Professional",
            "type":"Services"
        }
    ],
    "sg:phone":"+1   ",
    "sg:postcode":"15210",
    "sg:province":"PA",
    "wof:name":"Hegerle Inc",
    "wof:placetype":"venue"
},
  "geometry": {"coordinates":[-79.992898,40.416602],"type":"Point"}
}