{
  "type": "Feature",
  "properties": {
    "iso:country":"US",
    "sg:address":"1019 W View Park Dr",
    "sg:city":"Pittsburgh",
    "sg:classifiers":[
        {
            "category":"Restaurant",
            "type":"Food & Drink"
        }
    ],
    "sg:phone":"+1 412 931 7102",
    "sg:postcode":"15229",
    "sg:province":"PA",
    "sg:tags":[
        "eating"
    ],
    "wof:name":"Madison's Pizzeria West-View",
    "wof:placetype":"venue"
},
  "geometry": {"coordinates":[-80.034403,40.516562],"type":"Point"}
}