{
  "type": "Feature",
  "properties": {
    "iso:country":"US",
    "sg:address":"7289 Airport Rd",
    "sg:city":"Bath",
    "sg:classifiers":[
        {
            "category":"Banks & Credit Unions",
            "subcategory":"Bank",
            "type":"Services"
        }
    ],
    "sg:phone":"+1   ",
    "sg:postcode":"18014",
    "sg:province":"PA",
    "sg:tags":[
        "loan",
        "broker"
    ],
    "wof:name":"CFI",
    "wof:placetype":"venue"
},
  "geometry": {"coordinates":[-75.41803299999999,40.703283],"type":"Point"}
}