{
  "type": "Feature",
  "properties": {
    "iso:country":"US",
    "sg:address":"1284 Gap Newport Pike",
    "sg:city":"Avondale",
    "sg:classifiers":[
        {
            "category":"Professional",
            "type":"Services"
        }
    ],
    "sg:phone":"+1   ",
    "sg:postcode":"19311",
    "sg:province":"PA",
    "wof:name":"J D Eckman Inc",
    "wof:placetype":"venue"
},
  "geometry": {"coordinates":[-75.796019,39.835618],"type":"Point"}
}