{
  "type": "Feature",
  "properties": {
    "iso:country":"US",
    "sg:address":"57 Main St",
    "sg:city":"Falls Creek",
    "sg:classifiers":[
        {
            "category":"Restaurant",
            "type":"Food & Drink"
        }
    ],
    "sg:phone":"+1   ",
    "sg:postcode":"15840",
    "sg:province":"PA",
    "sg:tags":[
        "eating"
    ],
    "wof:name":"Coffee Shop",
    "wof:placetype":"venue"
},
  "geometry": {"coordinates":[-78.79821800000001,41.144126],"type":"Point"}
}