{
  "type": "Feature",
  "properties": {
    "addr:full":"26 N Antrim Way Greencastle PA 17225",
    "addr:housenumber":"26",
    "addr:postcode":"17225",
    "addr:street":"N Antrim Way",
    "iso:country":"US",
    "sg:address":"26 N Antrim Way",
    "sg:city":"Greencastle",
    "sg:classifiers":[
        {
            "category":"Restaurant",
            "type":"Food & Drink"
        }
    ],
    "sg:phone":"+1   ",
    "sg:postcode":"17225",
    "sg:province":"PA",
    "sg:tags":[
        "eating"
    ],
    "wof:name":"Welcome In Family Restaurant",
    "wof:placetype":"venue"
},
  "geometry": {"coordinates":[-77.730451,39.792133],"type":"Point"}
}