{
  "type": "Feature",
  "properties": {
    "addr:full":"119 Aid Dr Darlington PA 16115",
    "addr:housenumber":"119",
    "addr:postcode":"16115",
    "addr:street":"Aid Dr",
    "iso:country":"US",
    "sg:address":"119 Aid Dr",
    "sg:city":"Darlington",
    "sg:classifiers":[
        {
            "category":"Manufacturing",
            "subcategory":"Lumber",
            "type":"Manufacturing & Wholesale Goods"
        }
    ],
    "sg:phone":"+1 724 827 8366",
    "sg:postcode":"16115",
    "sg:province":"PA",
    "sg:tags":[
        "hardwood",
        "mills",
        "dimension",
        "flooring"
    ],
    "sg:website":"www.interforest.com",
    "wof:name":"Interforest Corp",
    "wof:placetype":"venue"
},
  "geometry": {"coordinates":[-80.465845,40.795859],"type":"Point"}
}