{
  "type": "Feature",
  "properties": {
    "iso:country":"US",
    "sg:address":"1409 State St",
    "sg:city":"Pottstown",
    "sg:classifiers":[
        {
            "category":"Shopping",
            "type":"Retail Goods"
        }
    ],
    "sg:phone":"+1 610 323 5561",
    "sg:postcode":"19464",
    "sg:province":"PA",
    "sg:tags":[
        "picture",
        "frame"
    ],
    "wof:name":"Anvil Studio & Frameshop",
    "wof:placetype":"venue"
},
  "geometry": {"coordinates":[-75.645116,40.278203],"type":"Point"}
}