{
  "type": "Feature",
  "properties": {
    "addr:full":"250 Mount Lebanon Blvd Pittsburgh PA 15234",
    "addr:housenumber":"250",
    "addr:postcode":"15234",
    "addr:street":"Mount Lebanon Blvd",
    "iso:country":"US",
    "sg:address":"250 Mount Lebanon Blvd",
    "sg:city":"Pittsburgh",
    "sg:classifiers":[
        {
            "category":"Real Estate",
            "subcategory":"Real Estate Services",
            "type":"Services"
        }
    ],
    "sg:phone":"+1 412 561 4206",
    "sg:postcode":"15234",
    "sg:province":"PA",
    "sg:tags":[
        "management",
        "property"
    ],
    "wof:name":"H-Squared Properties",
    "wof:placetype":"venue"
},
  "geometry": {"coordinates":[-80.038696,40.368],"type":"Point"}
}