{
  "type": "Feature",
  "properties": {
    "iso:country":"US",
    "sg:address":"31 Market St",
    "sg:city":"Brownsville",
    "sg:classifiers":[
        {
            "category":"Professional",
            "type":"Services"
        }
    ],
    "sg:phone":"+1 724 785 3042",
    "sg:postcode":"15417",
    "sg:province":"PA",
    "sg:tags":[
        "establishment"
    ],
    "wof:name":"Moskovitz Nervin Vac Clnr Rprg",
    "wof:placetype":"venue"
},
  "geometry": {"coordinates":[-79.88802200000001,40.021547],"type":"Point"}
}