{
  "type": "Feature",
  "properties": {
    "iso:country":"US",
    "sg:address":"18 E Essex Ave",
    "sg:city":"Lansdowne",
    "sg:classifiers":[
        {
            "category":"Building & Trades",
            "subcategory":"Construction",
            "type":"Services"
        }
    ],
    "sg:phone":"+1   ",
    "sg:postcode":"19050",
    "sg:province":"PA",
    "sg:tags":[
        "carpentry",
        "contractor"
    ],
    "wof:name":"John J Carney",
    "wof:placetype":"venue"
},
  "geometry": {"coordinates":[-75.274809,39.94493],"type":"Point"}
}