{
  "type": "Feature",
  "properties": {
    "iso:country":"US",
    "sg:address":"601 Walnut St",
    "sg:city":"Philadelphia",
    "sg:classifiers":[
        {
            "category":"Shopping",
            "subcategory":"Department Store",
            "type":"Retail Goods"
        }
    ],
    "sg:phone":"+1 215 238 6492",
    "sg:postcode":"19106",
    "sg:province":"PA",
    "sg:tags":[
        "variety"
    ],
    "wof:name":"Shaan Enterprises",
    "wof:placetype":"venue"
},
  "geometry": {"coordinates":[-75.1511,39.947689],"type":"Point"}
}