{
  "type": "Feature",
  "properties": {
    "addr:full":"956 Church St Reading PA 19601",
    "addr:housenumber":"956",
    "addr:postcode":"19601",
    "addr:street":"Church St",
    "iso:country":"US",
    "sg:address":"956 Church St",
    "sg:city":"Reading",
    "sg:classifiers":[
        {
            "category":"Place Of Worship",
            "type":"Public Place"
        }
    ],
    "sg:phone":"+1 610 372 3157",
    "sg:postcode":"19601",
    "sg:province":"PA",
    "sg:tags":[
        "church"
    ],
    "wof:name":"Universal Life Church",
    "wof:placetype":"venue"
},
  "geometry": {"coordinates":[-75.926473,40.349792],"type":"Point"}
}