{
  "type": "Feature",
  "properties": {
    "addr:full":"495 School House Rd Nazareth PA 18064",
    "addr:housenumber":"495",
    "addr:postcode":"18064",
    "addr:street":"School House Rd",
    "iso:country":"US",
    "sg:address":"495 School House Rd",
    "sg:city":"Nazareth",
    "sg:classifiers":[
        {
            "category":"Building & Trades",
            "subcategory":"Construction",
            "type":"Services"
        }
    ],
    "sg:phone":"+1   ",
    "sg:postcode":"18064",
    "sg:province":"PA",
    "sg:tags":[
        "house"
    ],
    "wof:name":"Geiger & Lesher Construction",
    "wof:placetype":"venue"
},
  "geometry": {"coordinates":[-75.334001,40.706683],"type":"Point"}
}