{
  "type": "Feature",
  "properties": {
    "iso:country":"US",
    "sg:address":"2199 S Eagle Valley Rd",
    "sg:city":"Julian",
    "sg:classifiers":[
        {
            "category":"Government",
            "subcategory":"Office",
            "type":"Public Place"
        }
    ],
    "sg:phone":"+1   ",
    "sg:postcode":"16844",
    "sg:province":"PA",
    "sg:tags":[
        "executive"
    ],
    "wof:name":"Union Township",
    "wof:placetype":"venue"
},
  "geometry": {"coordinates":[-77.85862,40.916772],"type":"Point"}
}