{
  "type": "Feature",
  "properties": {
    "iso:country":"US",
    "sg:address":"1229 Pericles Pl",
    "sg:city":"Whitehall",
    "sg:classifiers":[
        {
            "category":"Real Estate",
            "subcategory":"Real Estate Operator",
            "type":"Services"
        }
    ],
    "sg:phone":"+1 610 433 4265",
    "sg:postcode":"18052",
    "sg:province":"PA",
    "sg:tags":[
        "apartment"
    ],
    "wof:name":"Olympic Gardens",
    "wof:placetype":"venue"
},
  "geometry": {"coordinates":[-75.491302,40.622501],"type":"Point"}
}