{
  "type": "Feature",
  "properties": {
    "iso:country":"US",
    "sg:address":"476 Henninger Rd",
    "sg:city":"Elizabethville",
    "sg:classifiers":[
        {
            "category":"Food & Beverages",
            "subcategory":"Meat & Fish",
            "type":"Retail Goods"
        },
        {
            "category":"Wholesale",
            "subcategory":"Meat",
            "type":"Manufacturing & Wholesale Goods"
        }
    ],
    "sg:phone":"+1 717 362 9204",
    "sg:postcode":"17023",
    "sg:province":"PA",
    "sg:tags":[
        "butchering"
    ],
    "wof:name":"Henninger's Meat Market",
    "wof:placetype":"venue"
},
  "geometry": {"coordinates":[-76.79315699999999,40.585418],"type":"Point"}
}