{
  "type": "Feature",
  "properties": {
    "iso:country":"US",
    "sg:address":"4410 Spruce St",
    "sg:city":"Whitehall",
    "sg:classifiers":[
        {
            "category":"Professional",
            "subcategory":"Business Services",
            "type":"Services"
        }
    ],
    "sg:phone":"+1   ",
    "sg:postcode":"18052",
    "sg:province":"PA",
    "wof:name":"PD Balascki Ea",
    "wof:placetype":"venue"
},
  "geometry": {"coordinates":[-75.52875,40.687362],"type":"Point"}
}