{
  "type": "Feature",
  "properties": {
    "addr:full":"112 E Main St Pen Argyl PA 18072",
    "addr:housenumber":"112",
    "addr:postcode":"18072",
    "addr:street":"E Main St",
    "iso:country":"US",
    "sg:address":"112 E Main St",
    "sg:city":"Pen Argyl",
    "sg:classifiers":[
        {
            "category":"Professional",
            "type":"Services"
        }
    ],
    "sg:phone":"+1   ",
    "sg:postcode":"18072",
    "sg:province":"PA",
    "wof:name":"Pennsylvania Society of P",
    "wof:placetype":"venue"
},
  "geometry": {"coordinates":[-75.250843,40.87027],"type":"Point"}
}