{
  "type": "Feature",
  "properties": {
    "iso:country":"US",
    "sg:address":"571 3rd St",
    "sg:city":"Pitcairn",
    "sg:classifiers":[
        {
            "category":"Building & Trades",
            "subcategory":"Construction",
            "type":"Services"
        }
    ],
    "sg:phone":"+1   ",
    "sg:postcode":"15140",
    "sg:province":"PA",
    "sg:tags":[
        "hanging",
        "contractor"
    ],
    "wof:name":"Schades Painting Co",
    "wof:placetype":"venue"
},
  "geometry": {"coordinates":[-79.777136,40.403312],"type":"Point"}
}