{
  "type": "Feature",
  "properties": {
    "addr:full":"10114 Saltsburg Rd Pittsburgh PA 15239",
    "addr:housenumber":"10114",
    "addr:postcode":"15239",
    "addr:street":"Saltsburg Rd",
    "iso:country":"US",
    "sg:address":"10114 Saltsburg Rd",
    "sg:city":"Pittsburgh",
    "sg:classifiers":[
        {
            "category":"Restaurant",
            "type":"Food & Drink"
        }
    ],
    "sg:phone":"+1 412 793 3135",
    "sg:postcode":"15239",
    "sg:province":"PA",
    "sg:tags":[
        "parlor",
        "ice",
        "cream"
    ],
    "wof:name":"Elly's Ice Cream",
    "wof:placetype":"venue"
},
  "geometry": {"coordinates":[-79.703508,40.48941],"type":"Point"}
}