{
  "type": "Feature",
  "properties": {
    "iso:country":"US",
    "sg:address":"848 N 24th St",
    "sg:city":"Philadelphia",
    "sg:classifiers":[
        {
            "category":"Communications",
            "type":"Services"
        }
    ],
    "sg:phone":"+1   ",
    "sg:postcode":"19130",
    "sg:province":"PA",
    "sg:tags":[
        "communication"
    ],
    "wof:name":"Senior Communications Exec",
    "wof:placetype":"venue"
},
  "geometry": {"coordinates":[-75.17604900000001,39.972075],"type":"Point"}
}