{
  "type": "Feature",
  "properties": {
    "iso:country":"US",
    "sg:address":"781 Hoffmeier Rd",
    "sg:city":"Gap",
    "sg:classifiers":[
        {
            "category":"Banks & Credit Unions",
            "subcategory":"Investment Brokerage",
            "type":"Services"
        }
    ],
    "sg:phone":"+1 717 442 3222",
    "sg:postcode":"17527",
    "sg:province":"PA",
    "sg:tags":[
        "advisory"
    ],
    "wof:name":"Heritage Investment Group Inc",
    "wof:placetype":"venue"
},
  "geometry": {"coordinates":[-76.001001,39.992175],"type":"Point"}
}