{
  "type": "Feature",
  "properties": {
    "iso:country":"US",
    "sg:address":"1175 W 4th St",
    "sg:city":"Lock Haven",
    "sg:classifiers":[
        {
            "category":"Organizations",
            "subcategory":"Religious Organization",
            "type":"Services"
        }
    ],
    "sg:phone":"+1   ",
    "sg:postcode":"17745",
    "sg:province":"PA",
    "wof:name":"Saint Lukes Untd Church Christ",
    "wof:placetype":"venue"
},
  "geometry": {"coordinates":[-77.46919200000001,41.130478],"type":"Point"}
}