{
  "type": "Feature",
  "properties": {
    "iso:country":"US",
    "sg:address":"1160 Bethel Church Rd",
    "sg:city":"Spring City",
    "sg:classifiers":[
        {
            "category":"Food & Beverages",
            "subcategory":"Meat & Fish",
            "type":"Retail Goods"
        }
    ],
    "sg:phone":"+1   ",
    "sg:postcode":"19475",
    "sg:province":"PA",
    "wof:name":"Spera Meats",
    "wof:placetype":"venue"
},
  "geometry": {"coordinates":[-75.610375,40.178943],"type":"Point"}
}