{
  "type": "Feature",
  "properties": {
    "iso:country":"US",
    "sg:address":"493 Castle Shannon Blvd",
    "sg:city":"Pittsburgh",
    "sg:classifiers":[
        {
            "category":"Organizations",
            "subcategory":"Religious Organization",
            "type":"Services"
        }
    ],
    "sg:phone":"+1 412 563 6566",
    "sg:postcode":"15234",
    "sg:province":"PA",
    "sg:tags":[
        "church"
    ],
    "wof:name":"Baptist Homes Of Western Pa",
    "wof:placetype":"venue"
},
  "geometry": {"coordinates":[-80.033427,40.372113],"type":"Point"}
}