{
  "type": "Feature",
  "properties": {
    "iso:country":"US",
    "sg:address":"89 Junewood Dr",
    "sg:city":"Levittown",
    "sg:classifiers":[
        {
            "category":"Building & Trades",
            "subcategory":"Electrical",
            "type":"Services"
        }
    ],
    "sg:phone":"+1 215 547 7116",
    "sg:postcode":"19055",
    "sg:province":"PA",
    "sg:tags":[
        "electric",
        "contractor"
    ],
    "wof:name":"Delaware Electrical Contractor",
    "wof:placetype":"venue"
},
  "geometry": {"coordinates":[-74.83677900000001,40.135248],"type":"Point"}
}