{
  "type": "Feature",
  "properties": {
    "iso:country":"US",
    "sg:address":"Upper York Rd",
    "sg:city":"Solebury",
    "sg:classifiers":[
        {
            "category":"Health Services",
            "subcategory":"Chiropractor",
            "type":"Services"
        }
    ],
    "sg:phone":"+1 215 862 5681",
    "sg:postcode":"18963",
    "sg:province":"PA",
    "wof:name":"Vincent Anthony G Dr Chiropractor",
    "wof:placetype":"venue"
},
  "geometry": {"coordinates":[-75.007797,40.380901],"type":"Point"}
}