{
  "type": "Feature",
  "properties": {
    "addr:full":"35 E Chelten Ave Philadelphia PA 19144",
    "addr:housenumber":"35",
    "addr:postcode":"19144",
    "addr:street":"E Chelten Ave",
    "iso:country":"US",
    "sg:address":"35 E Chelten Ave",
    "sg:city":"Philadelphia",
    "sg:classifiers":[
        {
            "category":"Shopping",
            "subcategory":"Department Store",
            "type":"Retail Goods"
        }
    ],
    "sg:phone":"+1 215 844 4020",
    "sg:postcode":"19144",
    "sg:province":"PA",
    "sg:tags":[
        "club",
        "wholesale"
    ],
    "wof:name":"Mahoo Corp",
    "wof:placetype":"venue"
},
  "geometry": {"coordinates":[-75.174187,40.036367],"type":"Point"}
}