{
  "type": "Feature",
  "properties": {
    "addr:full":"1550 W Ingomar Rd Pittsburgh PA 15237",
    "addr:housenumber":"1550",
    "addr:postcode":"15237",
    "addr:street":"W Ingomar Rd",
    "iso:country":"US",
    "sg:address":"1550 W Ingomar Rd",
    "sg:city":"Pittsburgh",
    "sg:classifiers":[
        {
            "category":"Building & Trades",
            "subcategory":"Construction",
            "type":"Services"
        }
    ],
    "sg:phone":"+1   ",
    "sg:postcode":"15237",
    "sg:province":"PA",
    "sg:tags":[
        "floor",
        "laying",
        "contractor"
    ],
    "wof:name":"Nova Flooring",
    "wof:placetype":"venue"
},
  "geometry": {"coordinates":[-80.076437,40.585065],"type":"Point"}
}