{
  "type": "Feature",
  "properties": {
    "iso:country":"US",
    "sg:address":"303 Hamilton Cir",
    "sg:city":"Harrisburg",
    "sg:classifiers":[
        {
            "category":"Real Estate",
            "subcategory":"Real Estate Operator",
            "type":"Services"
        }
    ],
    "sg:phone":"+1 717 564 3100",
    "sg:postcode":"17111",
    "sg:province":"PA",
    "sg:tags":[
        "apartment"
    ],
    "wof:name":"Hamilton Park Apartments",
    "wof:placetype":"venue"
},
  "geometry": {"coordinates":[-76.79639,40.262644],"type":"Point"}
}