{
  "type": "Feature",
  "properties": {
    "addr:full":"2081 Hartel Ave Levittown PA 19057",
    "addr:housenumber":"2081",
    "addr:postcode":"19057",
    "addr:street":"Hartel Ave",
    "iso:country":"US",
    "sg:address":"2081 Hartel Ave",
    "sg:city":"Levittown",
    "sg:classifiers":[
        {
            "category":"Manufacturing",
            "subcategory":"Signs",
            "type":"Manufacturing & Wholesale Goods"
        }
    ],
    "sg:phone":"+1 215 547 1722",
    "sg:postcode":"19057",
    "sg:province":"PA",
    "sg:tags":[
        "advertising",
        "specialty"
    ],
    "wof:name":"Sign Edge Group LLC",
    "wof:placetype":"venue"
},
  "geometry": {"coordinates":[-74.839867,40.129215],"type":"Point"}
}