{
  "type": "Feature",
  "properties": {
    "iso:country":"US",
    "sg:address":"450 Eger Ln",
    "sg:city":"Duncansville",
    "sg:classifiers":[
        {
            "category":"Building & Trades",
            "subcategory":"Construction",
            "type":"Services"
        }
    ],
    "sg:phone":"+1   ",
    "sg:postcode":"16635",
    "sg:province":"PA",
    "sg:tags":[
        "general",
        "contractor"
    ],
    "wof:name":"Luthers Construction",
    "wof:placetype":"venue"
},
  "geometry": {"coordinates":[-78.44368299999999,40.460644],"type":"Point"}
}