{
  "type": "Feature",
  "properties": {
    "iso:country":"US",
    "sg:address":"2226 Cottman Ave",
    "sg:city":"Philadelphia",
    "sg:classifiers":[
        {
            "category":"Organizations",
            "subcategory":"Religious Organization",
            "type":"Services"
        }
    ],
    "sg:phone":"+1   ",
    "sg:postcode":"19149",
    "sg:province":"PA",
    "wof:name":"Centro Internacional",
    "wof:placetype":"venue"
},
  "geometry": {"coordinates":[-75.061623,40.048673],"type":"Point"}
}