{
  "type": "Feature",
  "properties": {
    "iso:country":"US",
    "sg:address":"131 E 8th Ave",
    "sg:city":"Homestead",
    "sg:classifiers":[
        {
            "category":"Manufacturing",
            "subcategory":"Tools & Machinery",
            "type":"Manufacturing & Wholesale Goods"
        }
    ],
    "sg:phone":"+1 412 462 7181",
    "sg:postcode":"15120",
    "sg:province":"PA",
    "sg:tags":[
        "orthopedic",
        "appliance",
        "braces",
        "mfg"
    ],
    "wof:name":"Bill Merletti Brace Company",
    "wof:placetype":"venue"
},
  "geometry": {"coordinates":[-79.91130099999999,40.40678],"type":"Point"}
}