{
  "type": "Feature",
  "properties": {
    "iso:country":"US",
    "sg:address":"463 Montgomery Ave",
    "sg:city":"Chambersburg",
    "sg:classifiers":[
        {
            "category":"Organizations",
            "subcategory":"Professional Association",
            "type":"Services"
        }
    ],
    "sg:phone":"+1 717 263 0879",
    "sg:postcode":"17201",
    "sg:province":"PA",
    "wof:name":"Chambersburg Little League",
    "wof:placetype":"venue"
},
  "geometry": {"coordinates":[-77.650929,39.938586],"type":"Point"}
}