{
  "type": "Feature",
  "properties": {
    "iso:country":"US",
    "sg:address":"12 Beechwood Rd",
    "sg:city":"Brookhaven",
    "sg:classifiers":[
        {
            "category":"Food & Beverages",
            "subcategory":"Bakery",
            "type":"Retail Goods"
        }
    ],
    "sg:phone":"+1 610 874 7757",
    "sg:postcode":"19015",
    "sg:province":"PA",
    "sg:tags":[
        "doughnut"
    ],
    "wof:name":"Country Doughnut & Bagel",
    "wof:placetype":"venue"
},
  "geometry": {"coordinates":[-75.37661,39.864935],"type":"Point"}
}