{
  "type": "Feature",
  "properties": {
    "iso:country":"US",
    "sg:address":"670 Store Rd",
    "sg:city":"Harleysville",
    "sg:classifiers":[
        {
            "category":"Building & Trades",
            "subcategory":"Landscaping Services",
            "type":"Services"
        }
    ],
    "sg:phone":"+1 215 513 7414",
    "sg:postcode":"19438",
    "sg:province":"PA",
    "sg:tags":[
        "landscape",
        "contractor"
    ],
    "wof:name":"Dunsmore Landscaping",
    "wof:placetype":"venue"
},
  "geometry": {"coordinates":[-75.371011,40.244751],"type":"Point"}
}