{
  "type": "Feature",
  "properties": {
    "iso:country":"US",
    "sg:address":"4 Mulberry St",
    "sg:city":"Towanda",
    "sg:classifiers":[
        {
            "category":"Education",
            "subcategory":"School",
            "type":"Public Place"
        }
    ],
    "sg:phone":"+1 570 265 6626",
    "sg:postcode":"18848",
    "sg:province":"PA",
    "wof:name":"Mulberry Street School",
    "wof:placetype":"venue"
},
  "geometry": {"coordinates":[-76.45059500000001,41.766064],"type":"Point"}
}