{
  "type": "Feature",
  "properties": {
    "iso:country":"US",
    "sg:address":"109 Johns Ave",
    "sg:city":"Hazleton",
    "sg:classifiers":[
        {
            "category":"Restaurant",
            "type":"Food & Drink"
        }
    ],
    "sg:phone":"+1   ",
    "sg:postcode":"18201",
    "sg:province":"PA",
    "sg:tags":[
        "eating"
    ],
    "wof:name":"Sugar Cone",
    "wof:placetype":"venue"
},
  "geometry": {"coordinates":[-75.958457,40.941798],"type":"Point"}
}