{
  "type": "Feature",
  "properties": {
    "iso:country":"US",
    "sg:address":"5400 Eadom St",
    "sg:city":"Philadelphia",
    "sg:classifiers":[
        {
            "category":"Freight",
            "type":"Transportation"
        }
    ],
    "sg:phone":"+1 215 533 5300",
    "sg:postcode":"19137",
    "sg:province":"PA",
    "sg:tags":[
        "commercial",
        "storage"
    ],
    "wof:name":"Devon Self-Storage",
    "wof:placetype":"venue"
},
  "geometry": {"coordinates":[-75.065983,40.010571],"type":"Point"}
}