{
  "type": "Feature",
  "properties": {
    "iso:country":"US",
    "sg:address":"17 West 2nd St",
    "sg:city":"Bethlehem",
    "sg:classifiers":[
        {
            "category":"Fast Food",
            "type":"Food & Drink"
        },
        {
            "category":"Restaurant",
            "type":"Food & Drink"
        }
    ],
    "sg:phone":"+1 610 625 2300",
    "sg:postcode":"18015",
    "sg:province":"PA",
    "sg:tags":[
        "burger",
        "american",
        "new"
    ],
    "sg:website":"www.startersriverport.com",
    "wof:name":"Starters Riverport",
    "wof:placetype":"venue"
},
  "geometry": {"coordinates":[-75.379501,40.612801],"type":"Point"}
}