{
  "type": "Feature",
  "properties": {
    "iso:country":"US",
    "sg:address":"171 N Market St",
    "sg:city":"Fawn Grove",
    "sg:classifiers":[
        {
            "category":"Professional",
            "type":"Services"
        }
    ],
    "sg:phone":"+1 717 382 4153",
    "sg:postcode":"17321",
    "sg:province":"PA",
    "sg:tags":[
        "establishment"
    ],
    "wof:name":"Fawn Grove Borough",
    "wof:placetype":"venue"
},
  "geometry": {"coordinates":[-76.451646,39.73111],"type":"Point"}
}