{
  "type": "Feature",
  "properties": {
    "iso:country":"US",
    "sg:address":"275 Pleasant Valley Rd",
    "sg:city":"Connellsville",
    "sg:classifiers":[
        {
            "category":"Restaurant",
            "type":"Food & Drink"
        }
    ],
    "sg:phone":"+1 724 626 2100",
    "sg:postcode":"15425",
    "sg:province":"PA",
    "wof:name":"Walnut Hill",
    "wof:placetype":"venue"
},
  "geometry": {"coordinates":[-79.549582,40.060782],"type":"Point"}
}