{
  "type": "Feature",
  "properties": {
    "iso:country":"US",
    "sg:address":"335 W Rte 897",
    "sg:city":"Reinholds",
    "sg:classifiers":[
        {
            "category":"Banks & Credit Unions",
            "subcategory":"Bank",
            "type":"Services"
        }
    ],
    "sg:phone":"+1 717 336 3692",
    "sg:postcode":"17569",
    "sg:province":"PA",
    "wof:name":"Fulton Bank",
    "wof:placetype":"venue"
},
  "geometry": {"coordinates":[-76.128529,40.267962],"type":"Point"}
}