{
  "type": "Feature",
  "properties": {
    "iso:country":"US",
    "sg:address":"109 E Bishop St",
    "sg:city":"Bellefonte",
    "sg:classifiers":[
        {
            "category":"Real Estate",
            "subcategory":"Real Estate Agent",
            "type":"Services"
        },
        {
            "category":"Professional",
            "subcategory":"Management & Consulting",
            "type":"Services"
        }
    ],
    "sg:phone":"+1 814 355 2021",
    "sg:postcode":"16823",
    "sg:province":"PA",
    "wof:name":"Jabco Reality Management",
    "wof:placetype":"venue"
},
  "geometry": {"coordinates":[-77.776044,40.91112],"type":"Point"}
}