{
  "type": "Feature",
  "properties": {
    "iso:country":"US",
    "sg:address":"5932 Penn Cir S",
    "sg:city":"Pittsburgh",
    "sg:classifiers":[
        {
            "category":"Coffee & Tea",
            "type":"Food & Drink"
        }
    ],
    "sg:menulink":"http://www.allmenus.com/pa/pittsburgh/35027-starbucks-coffee/menu/",
    "sg:phone":"+1 412 361 1350",
    "sg:postcode":"15206",
    "sg:province":"PA",
    "sg:tags":[
        "american"
    ],
    "wof:name":"Starbucks Coffee",
    "wof:placetype":"venue"
},
  "geometry": {"coordinates":[-79.928347,40.458991],"type":"Point"}
}