{
  "type": "Feature",
  "properties": {
    "iso:country":"US",
    "sg:address":"601 Michigan Ave",
    "sg:city":"Jeannette",
    "sg:classifiers":[
        {
            "category":"Shopping",
            "subcategory":"Pharmacy",
            "type":"Retail Goods"
        }
    ],
    "sg:phone":"+1 724 527 2211",
    "sg:postcode":"15644",
    "sg:province":"PA",
    "wof:name":"Aleos Professional Pharmacy",
    "wof:placetype":"venue"
},
  "geometry": {"coordinates":[-79.61447,40.319269],"type":"Point"}
}