{
  "type": "Feature",
  "properties": {
    "iso:country":"US",
    "sg:address":"4651 Howes Run Rd",
    "sg:city":"Tarentum",
    "sg:classifiers":[
        {
            "category":"Wholesale",
            "subcategory":"Apparel",
            "type":"Manufacturing & Wholesale Goods"
        }
    ],
    "sg:phone":"+1   ",
    "sg:postcode":"15084",
    "sg:province":"PA",
    "sg:tags":[
        "man",
        "woman",
        "sp",
        "promotional"
    ],
    "wof:name":"DE Rihn Specialties",
    "wof:placetype":"venue"
},
  "geometry": {"coordinates":[-79.764042,40.669832],"type":"Point"}
}