{
  "type": "Feature",
  "properties": {
    "iso:country":"US",
    "sg:address":"924 Cherry St",
    "sg:city":"Philadelphia",
    "sg:classifiers":[
        {
            "category":"Professional",
            "subcategory":"Research",
            "type":"Services"
        },
        {
            "category":"Building & Trades",
            "subcategory":"Construction",
            "type":"Services"
        }
    ],
    "sg:phone":"+1 215 627 4122",
    "sg:postcode":"19107",
    "sg:province":"PA",
    "sg:tags":[
        "hardware",
        "designer",
        "market",
        "software"
    ],
    "sg:website":"www.dscience.com",
    "wof:name":"Design Science",
    "wof:placetype":"venue"
},
  "geometry": {"coordinates":[-75.155035,39.954258],"type":"Point"}
}