{
  "type": "Feature",
  "properties": {
    "iso:country":"US",
    "sg:address":"28 Tippy Ln",
    "sg:city":"Tunkhannock",
    "sg:classifiers":[
        {
            "category":"Personal",
            "subcategory":"Beauty Salon",
            "type":"Services"
        }
    ],
    "sg:phone":"+1 570 298 2200",
    "sg:postcode":"18657",
    "sg:province":"PA",
    "wof:name":"Barbara Ann Dymond Beauty Salo",
    "wof:placetype":"venue"
},
  "geometry": {"coordinates":[-76.023409,41.439683],"type":"Point"}
}