{
  "type": "Feature",
  "properties": {
    "addr:full":"104 Cumberland Dr 5R Coatesville PA 19320",
    "addr:housenumber":"104;5r",
    "addr:postcode":"19320",
    "addr:street":"Cumberland Dr",
    "iso:country":"US",
    "sg:address":"104 Cumberland Dr 5R",
    "sg:city":"Coatesville",
    "sg:classifiers":[
        {
            "category":"Banks & Credit Unions",
            "subcategory":"Investment Brokerage",
            "type":"Services"
        }
    ],
    "sg:phone":"+1 610 383 5732",
    "sg:postcode":"19320",
    "sg:province":"PA",
    "sg:tags":[
        "tape",
        "video",
        "sale",
        "dvds-rental"
    ],
    "wof:name":"Akl Video Prdctns",
    "wof:placetype":"venue"
},
  "geometry": {"coordinates":[-75.834846,39.94894],"type":"Point"}
}