{
  "type": "Feature",
  "properties": {
    "iso:country":"US",
    "sg:address":"6530 Rising Sun Ave",
    "sg:city":"Philadelphia",
    "sg:classifiers":[
        {
            "category":"Insurance",
            "subcategory":"Insurance Agent",
            "type":"Services"
        },
        {
            "category":"Insurance",
            "subcategory":"Hazard Insurance",
            "type":"Services"
        },
        {
            "category":"Insurance",
            "subcategory":"Title Insurance",
            "type":"Services"
        },
        {
            "category":"Insurance",
            "subcategory":"Life Insurance",
            "type":"Services"
        }
    ],
    "sg:phone":"+1 215 342 5400",
    "sg:postcode":"19111",
    "sg:province":"PA",
    "sg:tags":[
        "business",
        "auto",
        "commercial",
        "homeowner",
        "motorcycle",
        "renter"
    ],
    "wof:name":"Allstate Insurance Company - Ronald Krier",
    "wof:placetype":"venue"
},
  "geometry": {"coordinates":[-75.093552,40.051716],"type":"Point"}
}