{
  "type": "Feature",
  "properties": {
    "iso:country":"US",
    "sg:address":"1628 N 18th St",
    "sg:city":"Allentown",
    "sg:classifiers":[
        {
            "category":"Freight",
            "type":"Transportation"
        }
    ],
    "sg:phone":"+1 610 439 7240",
    "sg:postcode":"18104",
    "sg:province":"PA",
    "sg:tags":[
        "delivery"
    ],
    "wof:name":"Worldwide Express",
    "wof:placetype":"venue"
},
  "geometry": {"coordinates":[-75.50631199999999,40.621102],"type":"Point"}
}