{
  "type": "Feature",
  "properties": {
    "iso:country":"US",
    "sg:address":"1707 Pennsylvania Ave",
    "sg:city":"Pittsburgh",
    "sg:classifiers":[
        {
            "category":"Utilities",
            "subcategory":"Telephone",
            "type":"Services"
        }
    ],
    "sg:phone":"+1 412 633 4112",
    "sg:postcode":"15233",
    "sg:province":"PA",
    "sg:tags":[
        "telecommunication"
    ],
    "wof:name":"Decision One",
    "wof:placetype":"venue"
},
  "geometry": {"coordinates":[-80.031508,40.452735],"type":"Point"}
}