{
  "type": "Feature",
  "properties": {
    "iso:country":"US",
    "sg:address":"3930 Pottsville Pike",
    "sg:city":"Reading",
    "sg:classifiers":[
        {
            "category":"Autos & Motor Vehicles",
            "subcategory":"Automobile Sales",
            "type":"Retail Goods"
        }
    ],
    "sg:phone":"+1 610 939 0660",
    "sg:postcode":"19605",
    "sg:province":"PA",
    "sg:tags":[
        "car",
        "used",
        "dealer"
    ],
    "sg:website":"www.masanousa.com",
    "wof:name":"Masano Auto Retailers USA",
    "wof:placetype":"venue"
},
  "geometry": {"coordinates":[-75.935418,40.393184],"type":"Point"}
}