{
  "type": "Feature",
  "properties": {
    "addr:full":"15 Strawberry Ln Lititz PA 17543",
    "addr:housenumber":"15",
    "addr:postcode":"17543",
    "addr:street":"Strawberry Ln",
    "iso:country":"US",
    "sg:address":"15 Strawberry Ln",
    "sg:city":"Lititz",
    "sg:classifiers":[
        {
            "category":"Manufacturing",
            "subcategory":"Chemicals & Compounds",
            "type":"Manufacturing & Wholesale Goods"
        }
    ],
    "sg:phone":"+1   ",
    "sg:postcode":"17543",
    "sg:province":"PA",
    "sg:tags":[
        "preparation",
        "toilet",
        "mfg"
    ],
    "wof:name":"Gillette",
    "wof:placetype":"venue"
},
  "geometry": {"coordinates":[-76.27089700000001,40.178966],"type":"Point"}
}