{
  "type": "Feature",
  "properties": {
    "iso:country":"US",
    "sg:address":"7100 Church Ave",
    "sg:city":"Pittsburgh",
    "sg:classifiers":[
        {
            "category":"Health Services",
            "subcategory":"Doctor",
            "type":"Services"
        }
    ],
    "sg:phone":"+1   ",
    "sg:postcode":"15202",
    "sg:province":"PA",
    "sg:tags":[
        "clinic",
        "dentist"
    ],
    "wof:name":"Dentice Julia M DMD",
    "wof:placetype":"venue"
},
  "geometry": {"coordinates":[-80.083702,40.50859],"type":"Point"}
}