{
  "type": "Feature",
  "properties": {
    "iso:country":"US",
    "sg:address":"3570 Bristol Pike",
    "sg:city":"Bensalem",
    "sg:classifiers":[
        {
            "category":"Retail",
            "subcategory":"Photofinishing",
            "type":"Services"
        }
    ],
    "sg:phone":"+1 215 245 4811",
    "sg:postcode":"19020",
    "sg:province":"PA",
    "sg:tags":[
        "photo",
        "restoration",
        "retouching"
    ],
    "wof:name":"Digital One Imaging",
    "wof:placetype":"venue"
},
  "geometry": {"coordinates":[-74.925403,40.090131],"type":"Point"}
}