{
  "type": "Feature",
  "properties": {
    "addr:full":"1021 Parade St Erie PA 16503",
    "addr:housenumber":"1021",
    "addr:postcode":"16503",
    "addr:street":"Parade St",
    "iso:country":"US",
    "sg:address":"1021 Parade St",
    "sg:city":"Erie",
    "sg:classifiers":[
        {
            "category":"Government",
            "subcategory":"Office",
            "type":"Public Place"
        }
    ],
    "sg:phone":"+1 814 451 6530",
    "sg:postcode":"16503",
    "sg:province":"PA",
    "wof:name":"Erie County District Justices",
    "wof:placetype":"venue"
},
  "geometry": {"coordinates":[-80.073452,42.127894],"type":"Point"}
}