{
  "type": "Feature",
  "properties": {
    "addr:full":"3190 Daniels Rd Nazareth PA 18064",
    "addr:housenumber":"3190",
    "addr:postcode":"18064",
    "addr:street":"Daniels Rd",
    "iso:country":"US",
    "sg:address":"3190 Daniels Rd",
    "sg:city":"Nazareth",
    "sg:classifiers":[
        {
            "category":"Freight",
            "type":"Transportation"
        }
    ],
    "sg:phone":"+1 610 759 9783",
    "sg:postcode":"18064",
    "sg:province":"PA",
    "sg:tags":[
        "hauling",
        "trucking"
    ],
    "wof:name":"North America Bulk Transport",
    "wof:placetype":"venue"
},
  "geometry": {"coordinates":[-75.34618399999999,40.737529],"type":"Point"}
}