{
  "type": "Feature",
  "properties": {
    "addr:full":"5753 State Route 8 Harrisville PA 16038",
    "addr:housenumber":"5753",
    "addr:postcode":"16038",
    "addr:street":"State Route 8",
    "iso:country":"US",
    "sg:address":"5753 State Route 8",
    "sg:city":"Harrisville",
    "sg:classifiers":[
        {
            "category":"Restaurant",
            "type":"Food & Drink"
        }
    ],
    "sg:menulink":"http://www.allmenus.com/pa/barkeyville/170685-burger-king/menu/",
    "sg:phone":"+1 814 786 9785",
    "sg:postcode":"16038",
    "sg:province":"PA",
    "sg:tags":[
        "burger",
        "american"
    ],
    "wof:name":"Burger King",
    "wof:placetype":"venue"
},
  "geometry": {"coordinates":[-79.973687,41.203131],"type":"Point"}
}