{
  "type": "Feature",
  "properties": {
    "iso:country":"US",
    "sg:address":"130 Surrey Dr",
    "sg:city":"Delmont",
    "sg:classifiers":[
        {
            "category":"Shopping",
            "subcategory":"Bicycles & Sporting Goods",
            "type":"Retail Goods"
        }
    ],
    "sg:phone":"+1   ",
    "sg:postcode":"15626",
    "sg:province":"PA",
    "wof:name":"Pro Sports Reports Inc",
    "wof:placetype":"venue"
},
  "geometry": {"coordinates":[-79.58538900000001,40.410146],"type":"Point"}
}