{
  "type": "Feature",
  "properties": {
    "addr:full":"102 E Main St Mount Joy PA 17552",
    "addr:housenumber":"102",
    "addr:postcode":"17552",
    "addr:street":"E Main St",
    "iso:country":"US",
    "sg:address":"102 E Main St",
    "sg:city":"Mount Joy",
    "sg:classifiers":[
        {
            "category":"Shopping",
            "subcategory":"Florist",
            "type":"Retail Goods"
        }
    ],
    "sg:phone":"+1   ",
    "sg:postcode":"17552",
    "sg:province":"PA",
    "wof:name":"Floral Designs of Mount Joy",
    "wof:placetype":"venue"
},
  "geometry": {"coordinates":[-76.49737500000001,40.109106],"type":"Point"}
}