{
  "type": "Feature",
  "properties": {
    "addr:full":"2232 Mount Carmel Ave Glenside PA 19038",
    "addr:housenumber":"2232",
    "addr:postcode":"19038",
    "addr:street":"Mount Carmel Ave",
    "iso:country":"US",
    "sg:address":"2232 Mount Carmel Ave",
    "sg:city":"Glenside",
    "sg:classifiers":[
        {
            "category":"Utilities",
            "subcategory":"Mobile Phone",
            "type":"Services"
        }
    ],
    "sg:phone":"+1 215 884 6341",
    "sg:postcode":"19038",
    "sg:province":"PA",
    "sg:tags":[
        "telephone",
        "cellular"
    ],
    "sg:website":"www.dtiwireless.com",
    "wof:name":"DTI Wireless Inc",
    "wof:placetype":"venue"
},
  "geometry": {"coordinates":[-75.149788,40.10068],"type":"Point"}
}