{
  "type": "Feature",
  "properties": {
    "iso:country":"US",
    "sg:address":"415 Brisbin St",
    "sg:city":"Houtzdale",
    "sg:classifiers":[
        {
            "category":"Organizations",
            "subcategory":"Religious Organization",
            "type":"Services"
        }
    ],
    "sg:phone":"+1 814 378 5359",
    "sg:postcode":"16651",
    "sg:province":"PA",
    "sg:tags":[
        "church"
    ],
    "wof:name":"Son Rise Fellowship",
    "wof:placetype":"venue"
},
  "geometry": {"coordinates":[-78.35097399999999,40.82761],"type":"Point"}
}