{
  "type": "Feature",
  "properties": {
    "iso:country":"US",
    "sg:address":"312 Adams Ave",
    "sg:city":"Scranton",
    "sg:classifiers":[
        {
            "category":"Professional",
            "subcategory":"Lawyer & Legal Services",
            "type":"Services"
        }
    ],
    "sg:phone":"+1   ",
    "sg:postcode":"18503",
    "sg:province":"PA",
    "wof:name":"Patrick M Rogan",
    "wof:placetype":"venue"
},
  "geometry": {"coordinates":[-75.65977100000001,41.409266],"type":"Point"}
}