{
  "type": "Feature",
  "properties": {
    "addr:full":"274 North St Harrisburg PA 17101",
    "addr:housenumber":"274",
    "addr:postcode":"17101",
    "addr:street":"North St",
    "iso:country":"US",
    "sg:address":"274 North St",
    "sg:city":"Harrisburg",
    "sg:classifiers":[
        {
            "category":"Restaurant",
            "type":"Food & Drink"
        }
    ],
    "sg:phone":"+1 717 232 9232",
    "sg:postcode":"17101",
    "sg:province":"PA",
    "sg:tags":[
        "eating"
    ],
    "wof:name":"Roxy's Cafe",
    "wof:placetype":"venue"
},
  "geometry": {"coordinates":[-76.885696,40.2649],"type":"Point"}
}