{
  "type": "Feature",
  "properties": {
    "iso:country":"US",
    "sg:address":"4201 Paul St",
    "sg:city":"Philadelphia",
    "sg:classifiers":[
        {
            "category":"Food & Beverages",
            "subcategory":"Groceries & Convenience Stores",
            "type":"Retail Goods"
        }
    ],
    "sg:phone":"+1 215 289 3141",
    "sg:postcode":"19124",
    "sg:province":"PA",
    "wof:name":"Luz Grocery",
    "wof:placetype":"venue"
},
  "geometry": {"coordinates":[-75.08762299999999,40.009599],"type":"Point"}
}