{
  "type": "Feature",
  "properties": {
    "iso:country":"US",
    "sg:address":"876 York St",
    "sg:city":"Hanover",
    "sg:classifiers":[
        {
            "category":"Building & Trades",
            "subcategory":"Construction",
            "type":"Services"
        }
    ],
    "sg:phone":"+1 717 633 5518",
    "sg:postcode":"17331",
    "sg:province":"PA",
    "sg:tags":[
        "painter"
    ],
    "wof:name":"Messersmiths Painting & Rmdlng",
    "wof:placetype":"venue"
},
  "geometry": {"coordinates":[-76.96205500000001,39.800059],"type":"Point"}
}