{
  "type": "Feature",
  "properties": {
    "iso:country":"US",
    "sg:address":"708 College St",
    "sg:city":"Pittsburgh",
    "sg:classifiers":[
        {
            "category":"Real Estate",
            "subcategory":"Architect",
            "type":"Services"
        }
    ],
    "sg:phone":"+1 412 365 0563",
    "sg:postcode":"15232",
    "sg:province":"PA",
    "wof:name":"Andrew Novak",
    "wof:placetype":"venue"
},
  "geometry": {"coordinates":[-79.92809800000001,40.454988],"type":"Point"}
}