{
  "type": "Feature",
  "properties": {
    "iso:country":"US",
    "sg:address":"45 S West St",
    "sg:city":"Carlisle",
    "sg:classifiers":[
        {
            "category":"Organizations",
            "subcategory":"Religious Organization",
            "type":"Services"
        }
    ],
    "sg:phone":"+1   ",
    "sg:postcode":"17013",
    "sg:province":"PA",
    "wof:name":"Gods Little Ones",
    "wof:placetype":"venue"
},
  "geometry": {"coordinates":[-77.193904,40.200926],"type":"Point"}
}