{
  "type": "Feature",
  "properties": {
    "iso:country":"US",
    "sg:address":"904 Sunset Dr",
    "sg:city":"Butler",
    "sg:classifiers":[
        {
            "category":"Sports & Exercise",
            "subcategory":"Golf",
            "type":"Entertainment"
        }
    ],
    "sg:phone":"+1 724 285 3633",
    "sg:postcode":"16001",
    "sg:province":"PA",
    "sg:tags":[
        "course"
    ],
    "wof:name":"Stoughton Acres Golf Course",
    "wof:placetype":"venue"
},
  "geometry": {"coordinates":[-79.94830899999999,40.931257],"type":"Point"}
}