{
  "type": "Feature",
  "properties": {
    "addr:full":"309 S Pike Rd Sarver PA 16055",
    "addr:housenumber":"309",
    "addr:postcode":"16055",
    "addr:street":"S Pike Rd",
    "iso:country":"US",
    "sg:address":"309 S Pike Rd",
    "sg:city":"Sarver",
    "sg:classifiers":[
        {
            "category":"Insurance",
            "subcategory":"Insurance Agent",
            "type":"Services"
        }
    ],
    "sg:phone":"+1 724 353 9670",
    "sg:postcode":"16055",
    "sg:province":"PA",
    "wof:name":"State Farm Insurance",
    "wof:placetype":"venue"
},
  "geometry": {"coordinates":[-79.746836,40.713498],"type":"Point"}
}