{
  "type": "Feature",
  "properties": {
    "iso:country":"US",
    "sg:address":"150 Main St",
    "sg:city":"Claysville",
    "sg:classifiers":[
        {
            "category":"Professional",
            "subcategory":"Lawyer & Legal Services",
            "type":"Services"
        }
    ],
    "sg:phone":"+1 724 663 7374",
    "sg:postcode":"15323",
    "sg:province":"PA",
    "sg:tags":[
        "attorney",
        "plan"
    ],
    "wof:name":"Susan P Moser",
    "wof:placetype":"venue"
},
  "geometry": {"coordinates":[-80.412903,40.117039],"type":"Point"}
}