{
  "type": "Feature",
  "properties": {
    "iso:country":"US",
    "sg:address":"3436 W Lake Rd",
    "sg:city":"Erie",
    "sg:classifiers":[
        {
            "category":"Shopping",
            "type":"Retail Goods"
        }
    ],
    "sg:phone":"+1 814 836 0737",
    "sg:postcode":"16505",
    "sg:province":"PA",
    "sg:tags":[
        "candle"
    ],
    "wof:name":"Oregon Kandle Kitchen",
    "wof:placetype":"venue"
},
  "geometry": {"coordinates":[-80.164154,42.100764],"type":"Point"}
}