{
  "type": "Feature",
  "properties": {
    "iso:country":"US",
    "sg:address":"231 E Canal St",
    "sg:city":"Hershey",
    "sg:classifiers":[
        {
            "category":"Building & Trades",
            "subcategory":"Construction",
            "type":"Services"
        }
    ],
    "sg:phone":"+1   ",
    "sg:postcode":"17033",
    "sg:province":"PA",
    "sg:tags":[
        "house",
        "co"
    ],
    "wof:name":"John Lingle Contracting",
    "wof:placetype":"venue"
},
  "geometry": {"coordinates":[-76.66630600000001,40.311529],"type":"Point"}
}