{
  "type": "Feature",
  "properties": {
    "iso:country":"US",
    "sg:address":"18 E Athens Ave",
    "sg:city":"Ardmore",
    "sg:classifiers":[
        {
            "category":"Professional",
            "type":"Services"
        }
    ],
    "sg:phone":"+1 610 642 9100",
    "sg:postcode":"19003",
    "sg:province":"PA",
    "sg:tags":[
        "establishment"
    ],
    "wof:name":"Main Line Executive Management",
    "wof:placetype":"venue"
},
  "geometry": {"coordinates":[-75.292051,40.005694],"type":"Point"}
}