{
  "type": "Feature",
  "properties": {
    "iso:country":"US",
    "sg:address":"916 New Castle Rd",
    "sg:city":"Butler",
    "sg:classifiers":[
        {
            "category":"Autos & Motor Vehicles",
            "subcategory":"Auto Supplies",
            "type":"Retail Goods"
        },
        {
            "category":"Wholesale",
            "subcategory":"Electrical",
            "type":"Manufacturing & Wholesale Goods"
        },
        {
            "category":"Wholesale",
            "subcategory":"Auto Parts",
            "type":"Manufacturing & Wholesale Goods"
        }
    ],
    "sg:phone":"+1 724 865 9218",
    "sg:postcode":"16001",
    "sg:province":"PA",
    "sg:tags":[
        "battery",
        "automobile",
        "accessory",
        "equipment",
        "truck",
        "engines-supplies"
    ],
    "sg:website":"http://ad.doubleclick.net/clk;221862232;45455595;j?http://www.carquest.com/carquest/store_locator.html",
    "wof:name":"CARQUEST Auto Parts",
    "wof:placetype":"venue"
},
  "geometry": {"coordinates":[-80.004835,40.896737],"type":"Point"}
}