{
  "type": "Feature",
  "properties": {
    "iso:country":"US",
    "sg:address":"1049 E Lancaster Ave",
    "sg:city":"Berwyn",
    "sg:classifiers":[
        {
            "category":"Shopping",
            "type":"Retail Goods"
        }
    ],
    "sg:phone":"+1 610 647 8888",
    "sg:postcode":"19312",
    "sg:province":"PA",
    "sg:tags":[
        "picture",
        "frame"
    ],
    "wof:name":"Inprints",
    "wof:placetype":"venue"
},
  "geometry": {"coordinates":[-75.44699799999999,40.045304],"type":"Point"}
}