{
  "type": "Feature",
  "properties": {
    "iso:country":"US",
    "sg:address":"550 Wiconisco St",
    "sg:city":"Harrisburg",
    "sg:classifiers":[
        {
            "category":"Organizations",
            "subcategory":"Religious Organization",
            "type":"Services"
        }
    ],
    "sg:phone":"+1 717 236 6107",
    "sg:postcode":"17110",
    "sg:province":"PA",
    "sg:tags":[
        "church"
    ],
    "wof:name":"New Jerusalem Christian Church",
    "wof:placetype":"venue"
},
  "geometry": {"coordinates":[-76.89553600000001,40.290087],"type":"Point"}
}