{
  "type": "Feature",
  "properties": {
    "iso:country":"US",
    "sg:address":"200 Locust Street Suite 17B",
    "sg:city":"Philadelphia",
    "sg:classifiers":[
        {
            "category":"Health Services",
            "subcategory":"Clinic",
            "type":"Services"
        }
    ],
    "sg:phone":"+1 215 922 0204",
    "sg:postcode":"19106",
    "sg:province":"PA",
    "sg:tags":[
        "counseling",
        "mental"
    ],
    "sg:website":"mauriepressman.com",
    "wof:name":"Maurie Pressman Psychiatrist Center City",
    "wof:placetype":"venue"
},
  "geometry": {"coordinates":[-75.144884,39.945066],"type":"Point"}
}