{
  "type": "Feature",
  "properties": {
    "iso:country":"US",
    "sg:address":"1500 Meerschaum Ln",
    "sg:city":"Coraopolis",
    "sg:classifiers":[
        {
            "category":"Building & Trades",
            "subcategory":"Construction",
            "type":"Services"
        }
    ],
    "sg:phone":"+1   ",
    "sg:postcode":"15108",
    "sg:province":"PA",
    "sg:tags":[
        "residential"
    ],
    "wof:name":"Forest Grove Estates",
    "wof:placetype":"venue"
},
  "geometry": {"coordinates":[-80.104433,40.482071],"type":"Point"}
}