{
  "type": "Feature",
  "properties": {
    "addr:full":"230 N Dauphin St Allentown PA 18109",
    "addr:housenumber":"230",
    "addr:postcode":"18109",
    "addr:street":"N Dauphin St",
    "iso:country":"US",
    "sg:address":"230 N Dauphin St",
    "sg:city":"Allentown",
    "sg:classifiers":[
        {
            "category":"Government",
            "subcategory":"Police Station",
            "type":"Public Place"
        }
    ],
    "sg:phone":"+1 610 433 0758",
    "sg:postcode":"18109",
    "sg:province":"PA",
    "sg:tags":[
        "department"
    ],
    "wof:name":"Allentown Police Dept",
    "wof:placetype":"venue"
},
  "geometry": {"coordinates":[-75.44913,40.613254],"type":"Point"}
}