{
  "type": "Feature",
  "properties": {
    "iso:country":"US",
    "sg:address":"891 Baltimore Pike",
    "sg:city":"Springfield",
    "sg:classifiers":[
        {
            "category":"Health Services",
            "subcategory":"Doctor",
            "type":"Services"
        }
    ],
    "sg:phone":"+1 610 543 8860",
    "sg:postcode":"19064",
    "sg:province":"PA",
    "sg:tags":[
        "physician",
        "medical",
        "radiology",
        "surgeons",
        "imaging"
    ],
    "wof:name":"Springfield Diagnostic Imaging",
    "wof:placetype":"venue"
},
  "geometry": {"coordinates":[-75.33760100000001,39.915611],"type":"Point"}
}