{
  "type": "Feature",
  "properties": {
    "iso:country":"US",
    "sg:address":"120 Dugans Mill Rd",
    "sg:city":"Duncannon",
    "sg:classifiers":[
        {
            "category":"Building & Trades",
            "subcategory":"Construction",
            "type":"Services"
        }
    ],
    "sg:phone":"+1 717 834 3700",
    "sg:postcode":"17020",
    "sg:province":"PA",
    "sg:tags":[
        "altering",
        "house",
        "remodeling",
        "contractor"
    ],
    "wof:name":"David P Barrick",
    "wof:placetype":"venue"
},
  "geometry": {"coordinates":[-77.109273,40.362703],"type":"Point"}
}