{
  "type": "Feature",
  "properties": {
    "addr:full":"57 Christman Rd Kutztown PA 19530",
    "addr:housenumber":"57",
    "addr:postcode":"19530",
    "addr:street":"Christman Rd",
    "iso:country":"US",
    "sg:address":"57 Christman Rd",
    "sg:city":"Kutztown",
    "sg:classifiers":[
        {
            "category":"Farming",
            "subcategory":"Nursery",
            "type":"Manufacturing & Wholesale Goods"
        },
        {
            "category":"Home & Garden",
            "subcategory":"Garden Supply",
            "type":"Retail Goods"
        }
    ],
    "sg:phone":"+1 610 683 6585",
    "sg:postcode":"19530",
    "sg:province":"PA",
    "sg:tags":[
        "ornamental",
        "nurseryman"
    ],
    "wof:name":"Foliage Farms",
    "wof:placetype":"venue"
},
  "geometry": {"coordinates":[-75.717612,40.539823],"type":"Point"}
}