{
  "type": "Feature",
  "properties": {
    "addr:full":"12 Leon Rd Pittsburgh PA 15220",
    "addr:housenumber":"12",
    "addr:postcode":"15220",
    "addr:street":"Leon Rd",
    "iso:country":"US",
    "sg:address":"12 Leon Rd",
    "sg:city":"Pittsburgh",
    "sg:classifiers":[
        {
            "category":"Retail",
            "subcategory":"Repair Shop",
            "type":"Services"
        }
    ],
    "sg:phone":"+1   ",
    "sg:postcode":"15220",
    "sg:province":"PA",
    "sg:tags":[
        "consultant",
        "furniture",
        "sales",
        "telemarketing"
    ],
    "wof:name":"American Heritage Furniture",
    "wof:placetype":"venue"
},
  "geometry": {"coordinates":[-80.041037,40.419972],"type":"Point"}
}