{
  "type": "Feature",
  "properties": {
    "addr:full":"604 N Geary St Mount Pleasant PA 15666",
    "addr:housenumber":"604",
    "addr:postcode":"15666",
    "addr:street":"N Geary St",
    "iso:country":"US",
    "sg:address":"604 N Geary St",
    "sg:city":"Mount Pleasant",
    "sg:classifiers":[
        {
            "category":"Wholesale",
            "subcategory":"Home Furnishings",
            "type":"Manufacturing & Wholesale Goods"
        }
    ],
    "sg:phone":"+1   ",
    "sg:postcode":"15666",
    "sg:province":"PA",
    "sg:tags":[
        "stone"
    ],
    "wof:name":"Crystal Concepts",
    "wof:placetype":"venue"
},
  "geometry": {"coordinates":[-79.538732,40.154236],"type":"Point"}
}