{
  "type": "Feature",
  "properties": {
    "iso:country":"US",
    "sg:address":"50 S Wyoming Ave",
    "sg:city":"Edwardsville",
    "sg:classifiers":[
        {
            "category":"Retail",
            "subcategory":"Auto Repair",
            "type":"Services"
        }
    ],
    "sg:phone":"+1 570 288 9329",
    "sg:postcode":"18704",
    "sg:province":"PA",
    "sg:tags":[
        "muffler",
        "exhaust",
        "system"
    ],
    "wof:name":"Cole Muffler",
    "wof:placetype":"venue"
},
  "geometry": {"coordinates":[-75.898723,41.260471],"type":"Point"}
}