{
  "type": "Feature",
  "properties": {
    "iso:country":"US",
    "sg:address":"301 Brentwood Rd",
    "sg:city":"Havertown",
    "sg:classifiers":[
        {
            "category":"Manufacturing",
            "subcategory":"Metals",
            "type":"Manufacturing & Wholesale Goods"
        },
        {
            "category":"Manufacturing",
            "subcategory":"Building Materials",
            "type":"Manufacturing & Wholesale Goods"
        }
    ],
    "sg:phone":"+1 610 449 9324",
    "sg:postcode":"19083",
    "sg:province":"PA",
    "sg:tags":[
        "product",
        "aluminum"
    ],
    "wof:name":"Bill Simon Associates Inc",
    "wof:placetype":"venue"
},
  "geometry": {"coordinates":[-75.28945400000001,39.975112],"type":"Point"}
}