{
  "type": "Feature",
  "properties": {
    "iso:country":"US",
    "sg:address":"34 Bridge St",
    "sg:city":"Etna",
    "sg:classifiers":[
        {
            "category":"Restaurant",
            "type":"Food & Drink"
        },
        {
            "category":"Bars & Pubs",
            "type":"Food & Drink"
        }
    ],
    "sg:phone":"+1 412 781 1109",
    "sg:postcode":"15223",
    "sg:province":"PA",
    "sg:tags":[
        "drinking",
        "eating"
    ],
    "wof:name":"Porky's Plain Old Bar",
    "wof:placetype":"venue"
},
  "geometry": {"coordinates":[-79.942904,40.497357],"type":"Point"}
}