{
  "type": "Feature",
  "properties": {
    "iso:country":"US",
    "sg:address":"431 W 7th Ave",
    "sg:city":"Homestead",
    "sg:classifiers":[
        {
            "category":"Retail",
            "subcategory":"Car Wash",
            "type":"Services"
        }
    ],
    "sg:phone":"+1 412 364 2200",
    "sg:postcode":"15120",
    "sg:province":"PA",
    "sg:tags":[
        "polishing",
        "washing"
    ],
    "wof:name":"Aquajet Carwash",
    "wof:placetype":"venue"
},
  "geometry": {"coordinates":[-79.919034,40.40162],"type":"Point"}
}