{
  "type": "Feature",
  "properties": {
    "addr:full":"3046 Knights Rd Bensalem PA 19020",
    "addr:housenumber":"3046",
    "addr:postcode":"19020",
    "addr:street":"Knights Rd",
    "iso:country":"US",
    "sg:address":"3046 Knights Rd",
    "sg:city":"Bensalem",
    "sg:classifiers":[
        {
            "category":"Health Services",
            "subcategory":"Optometrist",
            "type":"Services"
        }
    ],
    "sg:phone":"+1 215 639 4500",
    "sg:postcode":"19020",
    "sg:province":"PA",
    "sg:tags":[
        "ophthalmologist"
    ],
    "sg:website":"www.iclaser.com",
    "wof:name":"I C Laser Eye Care",
    "wof:placetype":"venue"
},
  "geometry": {"coordinates":[-74.949799,40.105598],"type":"Point"}
}