{
  "type": "Feature",
  "properties": {
    "iso:country":"US",
    "sg:address":"1140 York Rd",
    "sg:city":"Warminster",
    "sg:classifiers":[
        {
            "category":"Real Estate",
            "subcategory":"Real Estate Operator",
            "type":"Services"
        }
    ],
    "sg:phone":"+1   ",
    "sg:postcode":"18974",
    "sg:province":"PA",
    "sg:tags":[
        "building",
        "nonresidential"
    ],
    "wof:name":"Toll House Properties",
    "wof:placetype":"venue"
},
  "geometry": {"coordinates":[-75.097078,40.223578],"type":"Point"}
}