{
  "type": "Feature",
  "properties": {
    "iso:country":"US",
    "sg:address":"105 Irish Hollow Rd",
    "sg:city":"Bellefonte",
    "sg:classifiers":[
        {
            "category":"Building & Trades",
            "subcategory":"Construction",
            "type":"Services"
        }
    ],
    "sg:phone":"+1   ",
    "sg:postcode":"16823",
    "sg:province":"PA",
    "sg:tags":[
        "floor",
        "laying",
        "contractor"
    ],
    "wof:name":"Fellows Flooring Carpentr",
    "wof:placetype":"venue"
},
  "geometry": {"coordinates":[-77.748988,40.890724],"type":"Point"}
}