{
  "type": "Feature",
  "properties": {
    "addr:full":"1840 Washington Rd Washington PA 15301",
    "addr:housenumber":"1840",
    "addr:postcode":"15301",
    "addr:street":"Washington Rd",
    "iso:country":"US",
    "sg:address":"1840 Washington Rd",
    "sg:city":"Washington",
    "sg:classifiers":[
        {
            "category":"Building & Trades",
            "subcategory":"Landscaping Services",
            "type":"Services"
        },
        {
            "category":"Home & Garden",
            "subcategory":"Garden Supply",
            "type":"Retail Goods"
        },
        {
            "category":"Home & Garden",
            "subcategory":"Building Materials",
            "type":"Retail Goods"
        }
    ],
    "sg:phone":"+1 724 746 2151",
    "sg:postcode":"15301",
    "sg:province":"PA",
    "sg:tags":[
        "designer",
        "concrete",
        "consultant",
        "mulch",
        "contractor",
        "equipment",
        "landscape"
    ],
    "sg:website":"http://www.aslandscaping.net",
    "wof:name":"A & S Landscaping",
    "wof:placetype":"venue"
},
  "geometry": {"coordinates":[-80.185773,40.223975],"type":"Point"}
}