{
  "type": "Feature",
  "properties": {
    "iso:country":"US",
    "sg:address":"10455 Lincoln Hwy",
    "sg:city":"Everett",
    "sg:classifiers":[
        {
            "category":"Health Services",
            "subcategory":"Doctor",
            "type":"Services"
        }
    ],
    "sg:phone":"+1 814 623 3513",
    "sg:postcode":"15537",
    "sg:province":"PA",
    "sg:tags":[
        "physician",
        "surgeon"
    ],
    "wof:name":"King & Maceyko",
    "wof:placetype":"venue"
},
  "geometry": {"coordinates":[-78.433538,40.024726],"type":"Point"}
}