{
  "type": "Feature",
  "properties": {
    "addr:full":"2314 W Deerfield Dr Media PA 19063",
    "addr:housenumber":"2314",
    "addr:postcode":"19063",
    "addr:street":"W Deerfield Dr",
    "iso:country":"US",
    "sg:address":"2314 W Deerfield Dr",
    "sg:city":"Media",
    "sg:classifiers":[
        {
            "category":"Real Estate",
            "subcategory":"Real Estate Services",
            "type":"Services"
        },
        {
            "category":"Real Estate",
            "subcategory":"Real Estate Agent",
            "type":"Services"
        }
    ],
    "sg:phone":"+1 610 565 1661",
    "sg:postcode":"19063",
    "sg:province":"PA",
    "sg:tags":[
        "buyer",
        "broker"
    ],
    "wof:name":"Deerfield Investment Group Inc",
    "wof:placetype":"venue"
},
  "geometry": {"coordinates":[-75.408085,39.949214],"type":"Point"}
}