{
  "type": "Feature",
  "properties": {
    "addr:full":"324 Arch St Verona PA 15147",
    "addr:housenumber":"324",
    "addr:postcode":"15147",
    "addr:street":"Arch St",
    "iso:country":"US",
    "sg:address":"324 Arch St",
    "sg:city":"Verona",
    "sg:classifiers":[
        {
            "category":"Recreation",
            "subcategory":"Marina",
            "type":"Entertainment"
        }
    ],
    "sg:phone":"+1   ",
    "sg:postcode":"15147",
    "sg:province":"PA",
    "sg:tags":[
        "pub"
    ],
    "wof:name":"Allegeny River Boat Club",
    "wof:placetype":"venue"
},
  "geometry": {"coordinates":[-79.846828,40.500376],"type":"Point"}
}