{
  "type": "Feature",
  "properties": {
    "iso:country":"US",
    "sg:address":"5074 W Chester Pike",
    "sg:city":"Edgemont",
    "sg:classifiers":[
        {
            "category":"Manufacturing",
            "subcategory":"Paper Products",
            "type":"Manufacturing & Wholesale Goods"
        }
    ],
    "sg:phone":"+1 610 353 3530",
    "sg:postcode":"19073",
    "sg:province":"PA",
    "sg:tags":[
        "die",
        "paperboard"
    ],
    "sg:website":"www.apogeeindustries.com",
    "wof:name":"Apogee Industries",
    "wof:placetype":"venue"
},
  "geometry": {"coordinates":[-75.45365099999999,39.973983],"type":"Point"}
}