{
  "type": "Feature",
  "properties": {
    "addr:full":"901 Capouse Ave Scranton PA 18509",
    "addr:housenumber":"901",
    "addr:postcode":"18509",
    "addr:street":"Capouse Ave",
    "iso:country":"US",
    "sg:address":"901 Capouse Ave",
    "sg:city":"Scranton",
    "sg:classifiers":[
        {
            "category":"Real Estate",
            "subcategory":"Real Estate Operator",
            "type":"Services"
        }
    ],
    "sg:phone":"+1   ",
    "sg:postcode":"18509",
    "sg:province":"PA",
    "sg:tags":[
        "building",
        "apartment"
    ],
    "wof:name":"North East Rental Assoc",
    "wof:placetype":"venue"
},
  "geometry": {"coordinates":[-75.65789599999999,41.418554],"type":"Point"}
}