{
  "type": "Feature",
  "properties": {
    "addr:full":"600 E Township Line Rd Havertown PA 19083",
    "addr:housenumber":"600",
    "addr:postcode":"19083",
    "addr:street":"E Township Line Rd",
    "iso:country":"US",
    "sg:address":"600 E Township Line Rd",
    "sg:city":"Havertown",
    "sg:classifiers":[
        {
            "category":"Health Services",
            "subcategory":"Doctor",
            "type":"Services"
        }
    ],
    "sg:phone":"+1 610 449 0382",
    "sg:postcode":"19083",
    "sg:province":"PA",
    "sg:tags":[
        "physician",
        "surgeon"
    ],
    "wof:name":"Delaware Valley Imaging LTD",
    "wof:placetype":"venue"
},
  "geometry": {"coordinates":[-75.28501900000001,39.972802],"type":"Point"}
}