{
  "type": "Feature",
  "properties": {
    "addr:full":"226 Folk St Easton PA 18042",
    "addr:housenumber":"226",
    "addr:postcode":"18042",
    "addr:street":"Folk St",
    "iso:country":"US",
    "sg:address":"226 Folk St",
    "sg:city":"Easton",
    "sg:classifiers":[
        {
            "category":"Organizations",
            "subcategory":"Religious Organization",
            "type":"Services"
        }
    ],
    "sg:phone":"+1   ",
    "sg:postcode":"18042",
    "sg:province":"PA",
    "wof:name":"Corporation of President of Th",
    "wof:placetype":"venue"
},
  "geometry": {"coordinates":[-75.208495,40.682513],"type":"Point"}
}