{
  "type": "Feature",
  "properties": {
    "iso:country":"US",
    "sg:address":"400 Hollow Horn Rd",
    "sg:city":"Pipersville",
    "sg:classifiers":[
        {
            "category":"Building & Trades",
            "subcategory":"Construction",
            "type":"Services"
        }
    ],
    "sg:phone":"+1   ",
    "sg:postcode":"18947",
    "sg:province":"PA",
    "sg:tags":[
        "house"
    ],
    "wof:name":"Morgan Builders",
    "wof:placetype":"venue"
},
  "geometry": {"coordinates":[-75.128947,40.456878],"type":"Point"}
}