{
  "type": "Feature",
  "properties": {
    "addr:full":"6864 Chrisphalt Dr Bath PA 18014",
    "addr:housenumber":"6864",
    "addr:postcode":"18014",
    "addr:street":"Chrisphalt Dr",
    "iso:country":"US",
    "sg:address":"6864 Chrisphalt Dr",
    "sg:city":"Bath",
    "sg:classifiers":[
        {
            "category":"Professional",
            "subcategory":"Advertising",
            "type":"Services"
        }
    ],
    "sg:phone":"+1 610 837 8805",
    "sg:postcode":"18014",
    "sg:province":"PA",
    "sg:tags":[
        "mailing",
        "shipping"
    ],
    "sg:website":"www.ravendirect.com",
    "wof:name":"Direct Mail Assoc",
    "wof:placetype":"venue"
},
  "geometry": {"coordinates":[-75.388136,40.719392],"type":"Point"}
}