{
  "type": "Feature",
  "properties": {
    "addr:full":"77 McBride Rd Canonsburg PA 15317",
    "addr:housenumber":"77",
    "addr:postcode":"15317",
    "addr:street":"Mcbride Rd",
    "iso:country":"US",
    "sg:address":"77 McBride Rd",
    "sg:city":"Canonsburg",
    "sg:classifiers":[
        {
            "category":"Recreation",
            "type":"Entertainment"
        }
    ],
    "sg:phone":"+1   ",
    "sg:postcode":"15317",
    "sg:province":"PA",
    "sg:tags":[
        "farm",
        "specialty",
        "animal"
    ],
    "wof:name":"Western PA Kennel Assoc",
    "wof:placetype":"venue"
},
  "geometry": {"coordinates":[-80.198189,40.229831],"type":"Point"}
}