{
  "type": "Feature",
  "properties": {
    "iso:country":"US",
    "sg:address":"153 Brodhead Rd",
    "sg:city":"Bethlehem",
    "sg:classifiers":[
        {
            "category":"Social Services",
            "type":"Services"
        }
    ],
    "sg:phone":"+1   ",
    "sg:postcode":"18020",
    "sg:province":"PA",
    "wof:name":"St Lukes Hosp Lfestyle MGT Ctr",
    "wof:placetype":"venue"
},
  "geometry": {"coordinates":[-75.38557400000001,40.673848],"type":"Point"}
}