{
  "type": "Feature",
  "properties": {
    "iso:country":"US",
    "sg:address":"301 Station St",
    "sg:city":"Wilmerding",
    "sg:classifiers":[
        {
            "category":"Government",
            "subcategory":"Fire Station",
            "type":"Public Place"
        }
    ],
    "sg:phone":"+1   ",
    "sg:postcode":"15148",
    "sg:province":"PA",
    "sg:tags":[
        "department",
        "volunteer"
    ],
    "wof:name":"Wilmerbing Volunteer Fire Dept",
    "wof:placetype":"venue"
},
  "geometry": {"coordinates":[-79.80809600000001,40.39326],"type":"Point"}
}