{
  "type": "Feature",
  "properties": {
    "addr:full":"1030 W Hamilton St Allentown PA 18101",
    "addr:housenumber":"1030",
    "addr:postcode":"18101",
    "addr:street":"W Hamilton St",
    "iso:country":"US",
    "sg:address":"1030 W Hamilton St",
    "sg:city":"Allentown",
    "sg:classifiers":[
        {
            "category":"Banks & Credit Unions",
            "subcategory":"Financial Services",
            "type":"Services"
        }
    ],
    "sg:phone":"+1 610 351 7510",
    "sg:postcode":"18101",
    "sg:province":"PA",
    "sg:tags":[
        "broker",
        "mortgage"
    ],
    "wof:name":"Novastar Home Mortgage",
    "wof:placetype":"venue"
},
  "geometry": {"coordinates":[-75.474098,40.6031],"type":"Point"}
}