{
  "type": "Feature",
  "properties": {
    "iso:country":"US",
    "sg:address":"739 W Cypress St",
    "sg:city":"Kennett Square",
    "sg:classifiers":[
        {
            "category":"Banks & Credit Unions",
            "subcategory":"Bank",
            "type":"Services"
        }
    ],
    "sg:phone":"+1 610 444 8570",
    "sg:postcode":"19348",
    "sg:province":"PA",
    "wof:name":"Wood Clayton P State Farm Insurance",
    "wof:placetype":"venue"
},
  "geometry": {"coordinates":[-75.7257,39.843601],"type":"Point"}
}