{
  "type": "Feature",
  "properties": {
    "addr:full":"682 Heyer Mill Rd Nazareth PA 18064",
    "addr:housenumber":"682",
    "addr:postcode":"18064",
    "addr:street":"Heyer Mill Rd",
    "iso:country":"US",
    "sg:address":"682 Heyer Mill Rd",
    "sg:city":"Nazareth",
    "sg:classifiers":[
        {
            "category":"Retail",
            "subcategory":"Animal Services",
            "type":"Services"
        }
    ],
    "sg:phone":"+1 610 759 7629",
    "sg:postcode":"18064",
    "sg:province":"PA",
    "sg:tags":[
        "pet",
        "grooming",
        "washing"
    ],
    "wof:name":"Dogs Day Out",
    "wof:placetype":"venue"
},
  "geometry": {"coordinates":[-75.36249100000001,40.787604],"type":"Point"}
}