{
  "type": "Feature",
  "properties": {
    "iso:country":"US",
    "sg:address":"1600 Wildlife Dr",
    "sg:city":"Chester Springs",
    "sg:classifiers":[
        {
            "category":"Recreation",
            "type":"Entertainment"
        }
    ],
    "sg:phone":"+1   ",
    "sg:postcode":"19425",
    "sg:province":"PA",
    "wof:name":"Pixie Denver",
    "wof:placetype":"venue"
},
  "geometry": {"coordinates":[-75.602503,40.101161],"type":"Point"}
}