{
  "type": "Feature",
  "properties": {
    "addr:full":"219 North Ave Pittsburgh PA 15209",
    "addr:housenumber":"219",
    "addr:postcode":"15209",
    "addr:street":"North Ave",
    "iso:country":"US",
    "sg:address":"219 North Ave",
    "sg:city":"Pittsburgh",
    "sg:classifiers":[
        {
            "category":"Shopping",
            "subcategory":"Hobbies, Toys, & Games",
            "type":"Retail Goods"
        }
    ],
    "sg:phone":"+1   ",
    "sg:postcode":"15209",
    "sg:province":"PA",
    "wof:name":"Esthers",
    "wof:placetype":"venue"
},
  "geometry": {"coordinates":[-79.97446100000001,40.481554],"type":"Point"}
}