{
  "type": "Feature",
  "properties": {
    "addr:full":"149 Boyd Rd Hookstown PA 15043",
    "addr:housenumber":"149",
    "addr:postcode":"15043",
    "addr:street":"Boyd Rd",
    "iso:country":"US",
    "sg:address":"149 Boyd Rd",
    "sg:city":"Hookstown",
    "sg:classifiers":[
        {
            "category":"Building & Trades",
            "subcategory":"Construction",
            "type":"Services"
        }
    ],
    "sg:phone":"+1   ",
    "sg:postcode":"15043",
    "sg:province":"PA",
    "sg:tags":[
        "contractor"
    ],
    "wof:name":"Rjs Building Systems",
    "wof:placetype":"venue"
},
  "geometry": {"coordinates":[-80.440006,40.542211],"type":"Point"}
}