{
  "type": "Feature",
  "properties": {
    "addr:full":"4100 Sardis Rd Murrysville PA 15668",
    "addr:housenumber":"4100",
    "addr:postcode":"15668",
    "addr:street":"Sardis Rd",
    "iso:country":"US",
    "sg:address":"4100 Sardis Rd",
    "sg:city":"Murrysville",
    "sg:classifiers":[
        {
            "category":"Government",
            "subcategory":"City Hall",
            "type":"Public Place"
        },
        {
            "category":"Government",
            "subcategory":"Office",
            "type":"Public Place"
        }
    ],
    "sg:phone":"+1 724 327 2100",
    "sg:postcode":"15668",
    "sg:province":"PA",
    "sg:tags":[
        "town",
        "township",
        "planner",
        "government-city",
        "village"
    ],
    "sg:website":"http://www.murrysville.com",
    "wof:name":"Municipality Of Murrysville",
    "wof:placetype":"venue"
},
  "geometry": {"coordinates":[-79.667686,40.454251],"type":"Point"}
}