{
  "type": "Feature",
  "properties": {
    "addr:full":"1111 N 5th St Stroudsburg PA 18360",
    "addr:housenumber":"1111",
    "addr:postcode":"18360",
    "addr:street":"N 5Th St",
    "iso:country":"US",
    "sg:address":"1111 N 5th St",
    "sg:city":"Stroudsburg",
    "sg:classifiers":[
        {
            "category":"Real Estate",
            "subcategory":"Real Estate Agent",
            "type":"Services"
        }
    ],
    "sg:phone":"+1   ",
    "sg:postcode":"18360",
    "sg:province":"PA",
    "wof:name":"Re/Max",
    "wof:placetype":"venue"
},
  "geometry": {"coordinates":[-75.19695,41.000078],"type":"Point"}
}