{
  "type": "Feature",
  "properties": {
    "iso:country":"US",
    "sg:address":"3396 Washington Rd",
    "sg:city":"Canonsburg",
    "sg:classifiers":[
        {
            "category":"Professional",
            "subcategory":"Accounting & Tax Preparation",
            "type":"Services"
        }
    ],
    "sg:phone":"+1 724 941 3110",
    "sg:postcode":"15317",
    "sg:province":"PA",
    "sg:tags":[
        "accountant"
    ],
    "wof:name":"Kamman Otterness & Company Inc",
    "wof:placetype":"venue"
},
  "geometry": {"coordinates":[-80.120102,40.284901],"type":"Point"}
}