{
  "type": "Feature",
  "properties": {
    "iso:country":"US",
    "sg:address":"801 N 12th St",
    "sg:city":"Allentown",
    "sg:classifiers":[
        {
            "category":"Professional",
            "subcategory":"Employment Agencies",
            "type":"Services"
        }
    ],
    "sg:phone":"+1 610 433 5448",
    "sg:postcode":"18102",
    "sg:province":"PA",
    "sg:tags":[
        "modeling"
    ],
    "sg:website":"www.chartreusetalent.com",
    "wof:name":"Chartreuse Talent Agency",
    "wof:placetype":"venue"
},
  "geometry": {"coordinates":[-75.487436,40.611497],"type":"Point"}
}