{
  "type": "Feature",
  "properties": {
    "addr:full":"3556 37th St Exd Beaver Falls PA 15010",
    "addr:housenumber":"3556",
    "addr:postcode":"15010",
    "addr:street":"37Th St Exd",
    "iso:country":"US",
    "sg:address":"3556 37th St Exd",
    "sg:city":"Beaver Falls",
    "sg:classifiers":[
        {
            "category":"Building & Trades",
            "subcategory":"Cleaning & Sanitation",
            "type":"Services"
        }
    ],
    "sg:phone":"+1 724 847 1915",
    "sg:postcode":"15010",
    "sg:province":"PA",
    "sg:tags":[
        "fireplace",
        "chimney"
    ],
    "wof:name":"Soot Seekers Chimney Service",
    "wof:placetype":"venue"
},
  "geometry": {"coordinates":[-80.375338,40.788429],"type":"Point"}
}