{
  "type": "Feature",
  "properties": {
    "iso:country":"US",
    "sg:address":"3645 Germantown Ave",
    "sg:city":"Philadelphia",
    "sg:classifiers":[
        {
            "category":"Shopping",
            "subcategory":"Clothing, Apparel, & Fashions",
            "type":"Retail Goods"
        }
    ],
    "sg:phone":"+1   ",
    "sg:postcode":"19140",
    "sg:province":"PA",
    "sg:tags":[
        "juvenile",
        "wear",
        "furniture"
    ],
    "wof:name":"Fashion Plaza",
    "wof:placetype":"venue"
},
  "geometry": {"coordinates":[-75.150654,40.008863],"type":"Point"}
}