{
  "type": "Feature",
  "properties": {
    "iso:country":"US",
    "sg:address":"9645 Shirley Dr",
    "sg:city":"Allison Park",
    "sg:classifiers":[
        {
            "category":"Building & Trades",
            "subcategory":"Construction",
            "type":"Services"
        }
    ],
    "sg:phone":"+1   ",
    "sg:postcode":"15101",
    "sg:province":"PA",
    "sg:tags":[
        "swimming",
        "pool",
        "contractor"
    ],
    "wof:name":"Ecol-O-Pack Systems Inc",
    "wof:placetype":"venue"
},
  "geometry": {"coordinates":[-80.001136,40.582973],"type":"Point"}
}