{
  "type": "Feature",
  "properties": {
    "iso:country":"US",
    "sg:address":"833 N Park Rd",
    "sg:city":"Reading",
    "sg:classifiers":[
        {
            "category":"Building & Trades",
            "subcategory":"Construction",
            "type":"Services"
        }
    ],
    "sg:phone":"+1 610 376 2310",
    "sg:postcode":"19610",
    "sg:province":"PA",
    "sg:tags":[
        "wallcoverings-installation",
        "wallpaper",
        "painting",
        "contractor"
    ],
    "wof:name":"Northstar Painting",
    "wof:placetype":"venue"
},
  "geometry": {"coordinates":[-75.958359,40.346611],"type":"Point"}
}