{
  "type": "Feature",
  "properties": {
    "iso:country":"US",
    "sg:address":"1549 Bobali Dr",
    "sg:city":"Harrisburg",
    "sg:classifiers":[
        {
            "category":"Freight",
            "type":"Transportation"
        }
    ],
    "sg:phone":"+1   ",
    "sg:postcode":"17104",
    "sg:province":"PA",
    "sg:tags":[
        "general"
    ],
    "wof:name":"Keystone Onan Power",
    "wof:placetype":"venue"
},
  "geometry": {"coordinates":[-76.847526,40.245748],"type":"Point"}
}