{
  "type": "Feature",
  "properties": {
    "iso:country":"US",
    "sg:address":"701 E Cathedral Rd",
    "sg:city":"Philadelphia",
    "sg:classifiers":[
        {
            "category":"Sports & Exercise",
            "subcategory":"Gym",
            "type":"Entertainment"
        }
    ],
    "sg:phone":"+1 215 482 4088",
    "sg:postcode":"19128",
    "sg:province":"PA",
    "sg:tags":[
        "club",
        "health",
        "studio",
        "gymnasium"
    ],
    "wof:name":"L A Fitness Sports Club",
    "wof:placetype":"venue"
},
  "geometry": {"coordinates":[-75.237212,40.06511],"type":"Point"}
}