{
  "type": "Feature",
  "properties": {
    "addr:full":"1810 Parkway View Drive Pittsburgh PA 15205",
    "addr:housenumber":"1810",
    "addr:postcode":"15205",
    "addr:street":"Parkway View Drive",
    "iso:country":"US",
    "sg:address":"1810 Parkway View Drive",
    "sg:city":"Pittsburgh",
    "sg:classifiers":[
        {
            "category":"Shopping",
            "subcategory":"Stationery & Office Supplies",
            "type":"Retail Goods"
        },
        {
            "category":"Retail",
            "subcategory":"Repair Shop",
            "type":"Services"
        }
    ],
    "sg:phone":"+1 412 788 6262",
    "sg:postcode":"15205",
    "sg:province":"PA",
    "sg:tags":[
        "machine",
        "copy"
    ],
    "sg:website":"http://www.axis-bc.com",
    "wof:name":"Axis Business Consultants",
    "wof:placetype":"venue"
},
  "geometry": {"coordinates":[-80.128067,40.43335],"type":"Point"}
}