{
  "type": "Feature",
  "properties": {
    "iso:country":"US",
    "sg:address":"116 Woody Dr",
    "sg:city":"Butler",
    "sg:classifiers":[
        {
            "category":"Health Services",
            "subcategory":"Podiatrist",
            "type":"Services"
        }
    ],
    "sg:phone":"+1 724 283 7177",
    "sg:postcode":"16001",
    "sg:province":"PA",
    "sg:tags":[
        "physician",
        "surgeons"
    ],
    "wof:name":"Smaldino, Anthony, Dpm - Family Foot Care Assoc",
    "wof:placetype":"venue"
},
  "geometry": {"coordinates":[-79.909682,40.854687],"type":"Point"}
}