{
  "type": "Feature",
  "properties": {
    "addr:full":"3131 Wilmington Rd New Castle PA 16105",
    "addr:housenumber":"3131",
    "addr:postcode":"16105",
    "addr:street":"Wilmington Rd New",
    "iso:country":"US",
    "sg:address":"3131 Wilmington Rd",
    "sg:city":"New Castle",
    "sg:classifiers":[
        {
            "category":"Health Services",
            "subcategory":"Doctor",
            "type":"Services"
        }
    ],
    "sg:phone":"+1 724 658 9984",
    "sg:postcode":"16105",
    "sg:province":"PA",
    "sg:tags":[
        "dentist"
    ],
    "wof:name":"Family Dentistry",
    "wof:placetype":"venue"
},
  "geometry": {"coordinates":[-80.357321,41.04094],"type":"Point"}
}