{
  "type": "Feature",
  "properties": {
    "addr:full":"6013 Hazelhurst St Philadelphia PA 19151",
    "addr:housenumber":"6013",
    "addr:postcode":"19151",
    "addr:street":"Hazelhurst St",
    "iso:country":"US",
    "sg:address":"6013 Hazelhurst St",
    "sg:city":"Philadelphia",
    "sg:classifiers":[
        {
            "category":"Professional",
            "type":"Services"
        }
    ],
    "sg:phone":"+1   ",
    "sg:postcode":"19151",
    "sg:province":"PA",
    "wof:name":"Berry Earl 6226",
    "wof:placetype":"venue"
},
  "geometry": {"coordinates":[-75.242896,39.982413],"type":"Point"}
}