{
  "type": "Feature",
  "properties": {
    "addr:full":"28 W Lloyd St Shenandoah PA 17976",
    "addr:housenumber":"28",
    "addr:postcode":"17976",
    "addr:street":"W Lloyd St",
    "iso:country":"US",
    "sg:address":"28 W Lloyd St",
    "sg:city":"Shenandoah",
    "sg:classifiers":[
        {
            "category":"Government",
            "subcategory":"Office",
            "type":"Public Place"
        }
    ],
    "sg:phone":"+1   ",
    "sg:postcode":"17976",
    "sg:province":"PA",
    "sg:tags":[
        "water",
        "urban",
        "supply"
    ],
    "wof:name":"Municipal Auth Boro Shenandoah",
    "wof:placetype":"venue"
},
  "geometry": {"coordinates":[-76.202179,40.821305],"type":"Point"}
}