{
  "type": "Feature",
  "properties": {
    "iso:country":"US",
    "sg:address":"4244 Macalester St",
    "sg:city":"Philadelphia",
    "sg:classifiers":[
        {
            "category":"Wholesale",
            "subcategory":"Hardware",
            "type":"Manufacturing & Wholesale Goods"
        }
    ],
    "sg:phone":"+1   ",
    "sg:postcode":"19124",
    "sg:province":"PA",
    "sg:tags":[
        "p",
        "conditioning",
        "refrigeration",
        "heating",
        "air"
    ],
    "wof:name":"Sid Harveys 98",
    "wof:placetype":"venue"
},
  "geometry": {"coordinates":[-75.120148,40.01451],"type":"Point"}
}