{
  "type": "Feature",
  "properties": {
    "iso:country":"US",
    "sg:address":"101 Pine St",
    "sg:city":"Holmes",
    "sg:classifiers":[
        {
            "category":"Home & Garden",
            "subcategory":"Building Materials",
            "type":"Retail Goods"
        },
        {
            "category":"Manufacturing",
            "subcategory":"Building Materials",
            "type":"Manufacturing & Wholesale Goods"
        },
        {
            "category":"Home & Garden",
            "subcategory":"Carpets & Floor Coverings",
            "type":"Retail Goods"
        }
    ],
    "sg:phone":"+1 610 461 5300",
    "sg:postcode":"19043",
    "sg:province":"PA",
    "sg:tags":[
        "hardwood",
        "materials-wholesale",
        "rug",
        "manufacturer"
    ],
    "wof:name":"General Floor Covering",
    "wof:placetype":"venue"
},
  "geometry": {"coordinates":[-75.311378,39.89542],"type":"Point"}
}