{
  "type": "Feature",
  "properties": {
    "iso:country":"US",
    "sg:address":"4400 Franklin St",
    "sg:city":"Harrisburg",
    "sg:classifiers":[
        {
            "category":"Education",
            "subcategory":"School",
            "type":"Public Place"
        }
    ],
    "sg:phone":"+1 717 558 9430",
    "sg:postcode":"17111",
    "sg:province":"PA",
    "sg:website":"www.cdsd.k12.pa.us",
    "wof:name":"Lawnton Elementary School",
    "wof:placetype":"venue"
},
  "geometry": {"coordinates":[-76.80798,40.260304],"type":"Point"}
}