{
  "type": "Feature",
  "properties": {
    "iso:country":"US",
    "sg:address":"2 Main St",
    "sg:city":"Tidioute",
    "sg:classifiers":[
        {
            "category":"Wholesale",
            "subcategory":"Machinery & Supplies",
            "type":"Manufacturing & Wholesale Goods"
        }
    ],
    "sg:phone":"+1   ",
    "sg:postcode":"16351",
    "sg:province":"PA",
    "sg:tags":[
        "equipment",
        "industrial"
    ],
    "wof:name":"Swcma",
    "wof:placetype":"venue"
},
  "geometry": {"coordinates":[-79.41696899999999,41.682342],"type":"Point"}
}