{
  "type": "Feature",
  "properties": {
    "iso:country":"US",
    "sg:address":"960 Hidden Hollow Dr",
    "sg:city":"Gap",
    "sg:classifiers":[
        {
            "category":"Wholesale",
            "subcategory":"Vending Machines",
            "type":"Manufacturing & Wholesale Goods"
        }
    ],
    "sg:phone":"+1 717 442 9589",
    "sg:postcode":"17527",
    "sg:province":"PA",
    "sg:tags":[
        "merchandise"
    ],
    "wof:name":"Dream Enterprises",
    "wof:placetype":"venue"
},
  "geometry": {"coordinates":[-76.009651,39.98278],"type":"Point"}
}