{
  "type": "Feature",
  "properties": {
    "addr:full":"22 S Pearl St Shamokin PA 17872",
    "addr:housenumber":"22",
    "addr:postcode":"17872",
    "addr:street":"S Pearl St",
    "iso:country":"US",
    "sg:address":"22 S Pearl St",
    "sg:city":"Shamokin",
    "sg:classifiers":[
        {
            "category":"Recreation",
            "type":"Entertainment"
        }
    ],
    "sg:phone":"+1 570 648 1059",
    "sg:postcode":"17872",
    "sg:province":"PA",
    "wof:name":"Daniel Kolody",
    "wof:placetype":"venue"
},
  "geometry": {"coordinates":[-76.549656,40.787582],"type":"Point"}
}