{
  "type": "Feature",
  "properties": {
    "addr:full":"250 E Girard Ave Philadelphia PA 19125",
    "addr:housenumber":"250",
    "addr:postcode":"19125",
    "addr:street":"E Girard Ave",
    "iso:country":"US",
    "sg:address":"250 E Girard Ave",
    "sg:city":"Philadelphia",
    "sg:classifiers":[
        {
            "category":"Restaurant",
            "type":"Food & Drink"
        }
    ],
    "sg:phone":"+1 215 423 2788",
    "sg:postcode":"19125",
    "sg:province":"PA",
    "sg:tags":[
        "eating",
        "chinese"
    ],
    "wof:name":"Panda Chinese Food & Take-Out",
    "wof:placetype":"venue"
},
  "geometry": {"coordinates":[-75.13200399999999,39.969501],"type":"Point"}
}