{
  "type": "Feature",
  "properties": {
    "iso:country":"US",
    "sg:address":"1070 3rd St",
    "sg:city":"North Versailles",
    "sg:classifiers":[
        {
            "category":"Shopping",
            "subcategory":"Discount & Variety Stores",
            "type":"Retail Goods"
        }
    ],
    "sg:phone":"+1 412 824 7777",
    "sg:postcode":"15137",
    "sg:province":"PA",
    "sg:tags":[
        "merchandise",
        "general"
    ],
    "wof:name":"Vangura Laminated Products",
    "wof:placetype":"venue"
},
  "geometry": {"coordinates":[-79.807654,40.376521],"type":"Point"}
}