{
  "type": "Feature",
  "properties": {
    "iso:country":"US",
    "sg:address":"500 Lingle St",
    "sg:city":"Osceola Mills",
    "sg:classifiers":[
        {
            "category":"Shopping",
            "subcategory":"Discount & Variety Stores",
            "type":"Retail Goods"
        }
    ],
    "sg:phone":"+1 814 339 7200",
    "sg:postcode":"16666",
    "sg:province":"PA",
    "wof:name":"Hertlein's Surplus & More",
    "wof:placetype":"venue"
},
  "geometry": {"coordinates":[-78.26883599999999,40.85162],"type":"Point"}
}