{
  "type": "Feature",
  "properties": {
    "addr:full":"558 Dorseyville Rd Pittsburgh PA 15238",
    "addr:housenumber":"558",
    "addr:postcode":"15238",
    "addr:street":"Dorseyville Rd",
    "iso:country":"US",
    "sg:address":"558 Dorseyville Rd",
    "sg:city":"Pittsburgh",
    "sg:classifiers":[
        {
            "category":"Manufacturing",
            "subcategory":"Tools & Machinery",
            "type":"Manufacturing & Wholesale Goods"
        }
    ],
    "sg:phone":"+1   ",
    "sg:postcode":"15238",
    "sg:province":"PA",
    "sg:tags":[
        "surgeon",
        "transplant"
    ],
    "wof:name":"Jorge Reyes",
    "wof:placetype":"venue"
},
  "geometry": {"coordinates":[-79.914771,40.530432],"type":"Point"}
}