{
  "type": "Feature",
  "properties": {
    "iso:country":"US",
    "sg:address":"644 Eastside Dr",
    "sg:city":"Landisville",
    "sg:classifiers":[
        {
            "category":"Restaurant",
            "type":"Food & Drink"
        }
    ],
    "sg:phone":"+1 717 892 7477",
    "sg:postcode":"17538",
    "sg:province":"PA",
    "sg:tags":[
        "eating"
    ],
    "sg:website":"http://www.wanderingchef.com",
    "wof:name":"Wandering Chef Inc",
    "wof:placetype":"venue"
},
  "geometry": {"coordinates":[-76.410032,40.07876],"type":"Point"}
}