{
  "type": "Feature",
  "properties": {
    "iso:country":"US",
    "sg:address":"305 Woodcrest Cir",
    "sg:city":"Royersford",
    "sg:classifiers":[
        {
            "category":"Home & Garden",
            "subcategory":"Furniture",
            "type":"Retail Goods"
        }
    ],
    "sg:phone":"+1   ",
    "sg:postcode":"19468",
    "sg:province":"PA",
    "wof:name":"Educational Furn Solutions LLC",
    "wof:placetype":"venue"
},
  "geometry": {"coordinates":[-75.54268999999999,40.226982],"type":"Point"}
}