{
  "type": "Feature",
  "properties": {
    "addr:full":"116 Maine St Lower Burrell PA 15068",
    "addr:housenumber":"116",
    "addr:postcode":"15068",
    "addr:street":"Maine St",
    "iso:country":"US",
    "sg:address":"116 Maine St",
    "sg:city":"Lower Burrell",
    "sg:classifiers":[
        {
            "category":"Retail",
            "subcategory":"Repair Shop",
            "type":"Services"
        },
        {
            "category":"Building & Trades",
            "subcategory":"Construction",
            "type":"Services"
        }
    ],
    "sg:phone":"+1 724 335 1134",
    "sg:postcode":"15068",
    "sg:province":"PA",
    "sg:tags":[
        "welding",
        "contractor"
    ],
    "wof:name":"Burrell Welding",
    "wof:placetype":"venue"
},
  "geometry": {"coordinates":[-79.7124,40.585055],"type":"Point"}
}