{
  "type": "Feature",
  "properties": {
    "iso:country":"US",
    "sg:address":"411 Jackson Ave",
    "sg:city":"Vandergrift",
    "sg:classifiers":[
        {
            "category":"Food & Beverages",
            "subcategory":"Dairy",
            "type":"Retail Goods"
        }
    ],
    "sg:phone":"+1   ",
    "sg:postcode":"15690",
    "sg:province":"PA",
    "sg:tags":[
        "product"
    ],
    "wof:name":"Loftisofti",
    "wof:placetype":"venue"
},
  "geometry": {"coordinates":[-79.568068,40.600242],"type":"Point"}
}