{
  "type": "Feature",
  "properties": {
    "iso:country":"US",
    "sg:address":"510 N Broad St",
    "sg:city":"Emporium",
    "sg:classifiers":[
        {
            "category":"Health Services",
            "subcategory":"Nursing And Care Facility",
            "type":"Services"
        },
        {
            "category":"Travel",
            "subcategory":"Bed & Breakfast",
            "type":"Entertainment"
        }
    ],
    "sg:phone":"+1 814 486 0221",
    "sg:postcode":"15834",
    "sg:province":"PA",
    "sg:tags":[
        "personal",
        "home",
        "house"
    ],
    "wof:name":"MJM Victorian Home Inc",
    "wof:placetype":"venue"
},
  "geometry": {"coordinates":[-78.237863,41.513494],"type":"Point"}
}