{
  "type": "Feature",
  "properties": {
    "iso:country":"US",
    "sg:address":"518 W 4th St",
    "sg:city":"Lewistown",
    "sg:classifiers":[
        {
            "category":"Home & Garden",
            "subcategory":"Carpets & Floor Coverings",
            "type":"Retail Goods"
        }
    ],
    "sg:phone":"+1 717 248 8681",
    "sg:postcode":"17044",
    "sg:province":"PA",
    "sg:tags":[
        "installs"
    ],
    "wof:name":"Lewistown Floor Co",
    "wof:placetype":"venue"
},
  "geometry": {"coordinates":[-77.590076,40.593337],"type":"Point"}
}