{
  "type": "Feature",
  "properties": {
    "iso:country":"US",
    "sg:address":"900 N Park Ave",
    "sg:city":"Norristown",
    "sg:classifiers":[
        {
            "category":"Retail",
            "subcategory":"Auto Repair",
            "type":"Services"
        }
    ],
    "sg:phone":"+1 610 539 5034",
    "sg:postcode":"19403",
    "sg:province":"PA",
    "sg:tags":[
        "automobile",
        "top",
        "upholstery"
    ],
    "wof:name":"Barron Auto Tops & Upholstery",
    "wof:placetype":"venue"
},
  "geometry": {"coordinates":[-75.379797,40.161746],"type":"Point"}
}