{
  "type": "Feature",
  "properties": {
    "addr:full":"800 Walnut Dr Ellwood City PA 16117",
    "addr:housenumber":"800",
    "addr:postcode":"16117",
    "addr:street":"Walnut Dr",
    "iso:country":"US",
    "sg:address":"800 Walnut Dr",
    "sg:city":"Ellwood City",
    "sg:classifiers":[
        {
            "category":"Personal",
            "type":"Services"
        }
    ],
    "sg:phone":"+1   ",
    "sg:postcode":"16117",
    "sg:province":"PA",
    "wof:name":"Super Marketing",
    "wof:placetype":"venue"
},
  "geometry": {"coordinates":[-80.274732,40.87425],"type":"Point"}
}