{
  "type": "Feature",
  "properties": {
    "addr:full":"82 Main St Clifford PA 18407",
    "addr:housenumber":"82",
    "addr:postcode":"18407",
    "addr:street":"Main St",
    "iso:country":"US",
    "sg:address":"82 Main St",
    "sg:city":"Clifford",
    "sg:classifiers":[
        {
            "category":"Retail",
            "subcategory":"Car Wash",
            "type":"Services"
        }
    ],
    "sg:phone":"+1 570 222 5713",
    "sg:postcode":"18407",
    "sg:province":"PA",
    "sg:tags":[
        "automobile",
        "detail",
        "clean"
    ],
    "wof:name":"Kochmer Graphics",
    "wof:placetype":"venue"
},
  "geometry": {"coordinates":[-75.53018899999999,41.551057],"type":"Point"}
}