{
  "type": "Feature",
  "properties": {
    "iso:country":"US",
    "sg:address":"1118 Market St",
    "sg:city":"Philadelphia",
    "sg:classifiers":[
        {
            "category":"Education",
            "subcategory":"School",
            "type":"Public Place"
        }
    ],
    "sg:phone":"+1 215 299 3510",
    "sg:postcode":"19107",
    "sg:province":"PA",
    "sg:tags":[
        "high",
        "9"
    ],
    "wof:name":"Philadlphia Regional High Schl",
    "wof:placetype":"venue"
},
  "geometry": {"coordinates":[-75.15967499999999,39.951802],"type":"Point"}
}