{
  "type": "Feature",
  "properties": {
    "iso:country":"US",
    "sg:address":"204 Bentley Ln",
    "sg:city":"Coatesville",
    "sg:classifiers":[
        {
            "category":"Building & Trades",
            "subcategory":"Cleaning & Sanitation",
            "type":"Services"
        }
    ],
    "sg:phone":"+1   ",
    "sg:postcode":"19320",
    "sg:province":"PA",
    "sg:tags":[
        "maintenance"
    ],
    "wof:name":"Snowhill Enterprises Inc",
    "wof:placetype":"venue"
},
  "geometry": {"coordinates":[-75.845665,39.927196],"type":"Point"}
}