{
  "type": "Feature",
  "properties": {
    "iso:country":"US",
    "sg:address":"521 Spencer Ln",
    "sg:city":"Warminster",
    "sg:classifiers":[
        {
            "category":"Restaurant",
            "type":"Food & Drink"
        }
    ],
    "sg:phone":"+1 215 441 8801",
    "sg:postcode":"18974",
    "sg:province":"PA",
    "sg:tags":[
        "caterer"
    ],
    "wof:name":"Nancy's Home Style Catering",
    "wof:placetype":"venue"
},
  "geometry": {"coordinates":[-75.088294,40.212946],"type":"Point"}
}