{
  "type": "Feature",
  "properties": {
    "addr:full":"6 E Lancaster Ave Ardmore PA 19003",
    "addr:housenumber":"6",
    "addr:postcode":"19003",
    "addr:street":"E Lancaster Ave",
    "iso:country":"US",
    "sg:address":"6 E Lancaster Ave",
    "sg:city":"Ardmore",
    "sg:classifiers":[
        {
            "category":"Shopping",
            "subcategory":"Florist",
            "type":"Retail Goods"
        }
    ],
    "sg:phone":"+1 610 642 4943",
    "sg:postcode":"19003",
    "sg:province":"PA",
    "wof:name":"The Flower Market",
    "wof:placetype":"venue"
},
  "geometry": {"coordinates":[-75.290688,40.007721],"type":"Point"}
}