{
  "type": "Feature",
  "properties": {
    "iso:country":"US",
    "sg:address":"1901 S 9th St",
    "sg:city":"Philadelphia",
    "sg:classifiers":[
        {
            "category":"Education",
            "subcategory":"School",
            "type":"Public Place"
        }
    ],
    "sg:phone":"+1 215 952 6200",
    "sg:postcode":"19148",
    "sg:province":"PA",
    "sg:tags":[
        "high",
        "middle",
        "elementary"
    ],
    "wof:name":"School District of Philadelphia",
    "wof:placetype":"venue"
},
  "geometry": {"coordinates":[-75.160606,39.92569],"type":"Point"}
}