{
  "type": "Feature",
  "properties": {
    "addr:full":"1801 Market St Philadelphia PA 19103",
    "addr:housenumber":"1801",
    "addr:postcode":"19103",
    "addr:street":"Market St",
    "iso:country":"US",
    "sg:address":"1801 Market St",
    "sg:city":"Philadelphia",
    "sg:classifiers":[
        {
            "category":"Retail",
            "subcategory":"Photofinishing",
            "type":"Services"
        }
    ],
    "sg:phone":"+1   ",
    "sg:postcode":"19103",
    "sg:province":"PA",
    "sg:tags":[
        "laboratory"
    ],
    "wof:name":"Creator",
    "wof:placetype":"venue"
},
  "geometry": {"coordinates":[-75.171593,39.953368],"type":"Point"}
}