{
  "type": "Feature",
  "properties": {
    "iso:country":"US",
    "sg:address":"3764 Layfield Rd",
    "sg:city":"Pennsburg",
    "sg:classifiers":[
        {
            "category":"Food & Beverages",
            "subcategory":"Fruits & Vegetables",
            "type":"Retail Goods"
        }
    ],
    "sg:phone":"+1   ",
    "sg:postcode":"18073",
    "sg:province":"PA",
    "sg:tags":[
        "farm",
        "tree",
        "o"
    ],
    "wof:name":"Stauffer Fruit Stand",
    "wof:placetype":"venue"
},
  "geometry": {"coordinates":[-75.523248,40.365007],"type":"Point"}
}