{
  "type": "Feature",
  "properties": {
    "iso:country":"US",
    "sg:address":"1069 York Ave",
    "sg:city":"Lansdale",
    "sg:classifiers":[
        {
            "category":"Building & Trades",
            "subcategory":"Construction",
            "type":"Services"
        }
    ],
    "sg:phone":"+1   ",
    "sg:postcode":"19446",
    "sg:province":"PA",
    "sg:tags":[
        "carpentry",
        "contractor"
    ],
    "wof:name":"Michalik Gary Crpntr/Cntractor",
    "wof:placetype":"venue"
},
  "geometry": {"coordinates":[-75.298672,40.246411],"type":"Point"}
}