{
  "type": "Feature",
  "properties": {
    "iso:country":"US",
    "sg:address":"3718 W Lake Rd",
    "sg:city":"Erie",
    "sg:classifiers":[
        {
            "category":"Professional",
            "subcategory":"Management & Consulting",
            "type":"Services"
        }
    ],
    "sg:phone":"+1 814 836 9237",
    "sg:postcode":"16505",
    "sg:province":"PA",
    "sg:tags":[
        "consultant",
        "business"
    ],
    "wof:name":"ITZ Solutions",
    "wof:placetype":"venue"
},
  "geometry": {"coordinates":[-80.168571,42.097812],"type":"Point"}
}