{
  "type": "Feature",
  "properties": {
    "iso:country":"US",
    "sg:address":"13 Front St",
    "sg:city":"Brookhaven",
    "sg:classifiers":[
        {
            "category":"Building & Trades",
            "subcategory":"Construction",
            "type":"Services"
        }
    ],
    "sg:phone":"+1   ",
    "sg:postcode":"19015",
    "sg:province":"PA",
    "sg:tags":[
        "house"
    ],
    "wof:name":"Merwin Construction Co",
    "wof:placetype":"venue"
},
  "geometry": {"coordinates":[-75.382296,39.851704],"type":"Point"}
}