{
  "type": "Feature",
  "properties": {
    "addr:full":"121 E Diamond Ave Hazleton PA 18201",
    "addr:housenumber":"121",
    "addr:postcode":"18201",
    "addr:street":"E Diamond Ave",
    "iso:country":"US",
    "sg:address":"121 E Diamond Ave",
    "sg:city":"Hazleton",
    "sg:classifiers":[
        {
            "category":"Real Estate",
            "subcategory":"Real Estate Agent",
            "type":"Services"
        }
    ],
    "sg:phone":"+1   ",
    "sg:postcode":"18201",
    "sg:province":"PA",
    "sg:tags":[
        "realty"
    ],
    "wof:name":"Anmar Realty Company",
    "wof:placetype":"venue"
},
  "geometry": {"coordinates":[-75.96803300000001,40.961106],"type":"Point"}
}