{
  "type": "Feature",
  "properties": {
    "iso:country":"US",
    "sg:address":"105 Stone Quarry Rd",
    "sg:city":"Monaca",
    "sg:classifiers":[
        {
            "category":"Travel",
            "subcategory":"Hotels & Motels",
            "type":"Entertainment"
        }
    ],
    "sg:phone":"+1 724 728 5121",
    "sg:postcode":"15061",
    "sg:province":"PA",
    "wof:name":"Holiday Inn Express Ctr Twnshp",
    "wof:placetype":"venue"
},
  "geometry": {"coordinates":[-80.309465,40.673474],"type":"Point"}
}