{
  "type": "Feature",
  "properties": {
    "addr:full":"110 North St York PA 17403",
    "addr:housenumber":"110",
    "addr:postcode":"17403",
    "addr:street":"North St",
    "iso:country":"US",
    "sg:address":"110 North St",
    "sg:city":"York",
    "sg:classifiers":[
        {
            "category":"Government",
            "subcategory":"Police Station",
            "type":"Public Place"
        }
    ],
    "sg:phone":"+1 717 428 1011",
    "sg:postcode":"17403",
    "sg:province":"PA",
    "sg:tags":[
        "state"
    ],
    "sg:website":"www.psp.state.pa.us",
    "wof:name":"State Police",
    "wof:placetype":"venue"
},
  "geometry": {"coordinates":[-76.701359,39.863723],"type":"Point"}
}