{
  "type": "Feature",
  "properties": {
    "iso:country":"US",
    "sg:address":"841 California Ave",
    "sg:city":"Allegheny",
    "sg:classifiers":[
        {
            "category":"Social Services",
            "type":"Services"
        }
    ],
    "sg:phone":"+1 412 323 9800",
    "sg:postcode":"15212",
    "sg:province":"PA",
    "sg:tags":[
        "probation"
    ],
    "wof:name":"Adult Probation Office",
    "wof:placetype":"venue"
},
  "geometry": {"coordinates":[-80.01779999999999,40.45942],"type":"Point"}
}