{
  "type": "Feature",
  "properties": {
    "addr:full":"1701 Columbia Ave Tyrone PA 16686",
    "addr:housenumber":"1701",
    "addr:postcode":"16686",
    "addr:street":"Columbia Ave",
    "iso:country":"US",
    "sg:address":"1701 Columbia Ave",
    "sg:city":"Tyrone",
    "sg:classifiers":[
        {
            "category":"Place Of Worship",
            "type":"Public Place"
        }
    ],
    "sg:phone":"+1 814 684 5424",
    "sg:postcode":"16686",
    "sg:province":"PA",
    "sg:tags":[
        "church"
    ],
    "wof:name":"Rock Of Ages Church",
    "wof:placetype":"venue"
},
  "geometry": {"coordinates":[-78.24031100000001,40.680481],"type":"Point"}
}