{
  "type": "Feature",
  "properties": {
    "addr:full":"401 Phillips St Baden PA 15005",
    "addr:housenumber":"401",
    "addr:postcode":"15005",
    "addr:street":"Phillips St",
    "iso:country":"US",
    "sg:address":"401 Phillips St",
    "sg:city":"Baden",
    "sg:classifiers":[
        {
            "category":"Personal",
            "subcategory":"Beauty Salon",
            "type":"Services"
        }
    ],
    "sg:phone":"+1 724 869 8830",
    "sg:postcode":"15005",
    "sg:province":"PA",
    "wof:name":"Scissor Wizards",
    "wof:placetype":"venue"
},
  "geometry": {"coordinates":[-80.230283,40.638992],"type":"Point"}
}