{
  "type": "Feature",
  "properties": {
    "iso:country":"US",
    "sg:address":"32 N 6th St",
    "sg:city":"Allentown",
    "sg:classifiers":[
        {
            "category":"Real Estate",
            "subcategory":"Real Estate Services",
            "type":"Services"
        }
    ],
    "sg:phone":"+1   ",
    "sg:postcode":"18101",
    "sg:province":"PA",
    "sg:tags":[
        "abstract",
        "title"
    ],
    "wof:name":"William E Doyle",
    "wof:placetype":"venue"
},
  "geometry": {"coordinates":[-75.47053099999999,40.604121],"type":"Point"}
}