{
  "type": "Feature",
  "properties": {
    "addr:full":"279 US Hwy 6 Coudersport PA 16915",
    "addr:housenumber":"279",
    "addr:postcode":"16915",
    "addr:street":"Us Hwy 6",
    "iso:country":"US",
    "sg:address":"279 US Hwy 6",
    "sg:city":"Coudersport",
    "sg:classifiers":[
        {
            "category":"Health Services",
            "subcategory":"Health Practitioner",
            "type":"Services"
        }
    ],
    "sg:phone":"+1 814 274 1121",
    "sg:postcode":"16915",
    "sg:province":"PA",
    "sg:tags":[
        "psychologist"
    ],
    "wof:name":"Sagewood Inc",
    "wof:placetype":"venue"
},
  "geometry": {"coordinates":[-78.029697,41.767173],"type":"Point"}
}