{
  "type": "Feature",
  "properties": {
    "iso:country":"US",
    "sg:address":"510 Maple St",
    "sg:city":"Honey Brook",
    "sg:classifiers":[
        {
            "category":"Building & Trades",
            "subcategory":"Construction",
            "type":"Services"
        }
    ],
    "sg:phone":"+1 610 273 2415",
    "sg:postcode":"19344",
    "sg:province":"PA",
    "sg:tags":[
        "masonry",
        "contractor"
    ],
    "wof:name":"Creative Masonry",
    "wof:placetype":"venue"
},
  "geometry": {"coordinates":[-75.908338,40.096569],"type":"Point"}
}