{
  "type": "Feature",
  "properties": {
    "addr:full":"730 Shenango Rd Beaver Falls PA 15010",
    "addr:housenumber":"730",
    "addr:postcode":"15010",
    "addr:street":"Shenango Rd",
    "iso:country":"US",
    "sg:address":"730 Shenango Rd",
    "sg:city":"Beaver Falls",
    "sg:classifiers":[
        {
            "category":"Shopping",
            "subcategory":"Shoes",
            "type":"Retail Goods"
        }
    ],
    "sg:phone":"+1 724 846 1822",
    "sg:postcode":"15010",
    "sg:province":"PA",
    "wof:name":"Payless Shoe Source",
    "wof:placetype":"venue"
},
  "geometry": {"coordinates":[-80.375103,40.773458],"type":"Point"}
}