{
  "type": "Feature",
  "properties": {
    "iso:country":"US",
    "sg:address":"22 S Clifton Ave",
    "sg:city":"Clifton Heights",
    "sg:classifiers":[
        {
            "category":"Manufacturing",
            "subcategory":"Apparel",
            "type":"Manufacturing & Wholesale Goods"
        }
    ],
    "sg:phone":"+1 610 623 2620",
    "sg:postcode":"19018",
    "sg:province":"PA",
    "sg:tags":[
        "hat"
    ],
    "sg:website":"www.hatcrafters.com",
    "wof:name":"Hatcrafters",
    "wof:placetype":"venue"
},
  "geometry": {"coordinates":[-75.28668,39.921872],"type":"Point"}
}