{
  "type": "Feature",
  "properties": {
    "addr:full":"3174 Old Philadelphia Pike Manheim PA 17505",
    "addr:housenumber":"3174",
    "addr:postcode":"17505",
    "addr:street":"Old Philadelphia Pike",
    "iso:country":"US",
    "sg:address":"3174 Old Philadelphia Pike",
    "sg:city":"Manheim",
    "sg:classifiers":[
        {
            "category":"Recreation",
            "type":"Entertainment"
        }
    ],
    "sg:phone":"+1   ",
    "sg:postcode":"17505",
    "sg:province":"PA",
    "sg:tags":[
        "mfg"
    ],
    "wof:name":"Mount Hope Estate & Winery",
    "wof:placetype":"venue"
},
  "geometry": {"coordinates":[-76.141334,40.038647],"type":"Point"}
}