{
  "type": "Feature",
  "properties": {
    "iso:country":"US",
    "sg:address":"235 E Freedom Ave",
    "sg:city":"Burnham",
    "sg:classifiers":[
        {
            "category":"Real Estate",
            "subcategory":"Real Estate Operator",
            "type":"Services"
        }
    ],
    "sg:phone":"+1 717 248 7071",
    "sg:postcode":"17009",
    "sg:province":"PA",
    "sg:tags":[
        "apartment"
    ],
    "wof:name":"Heckard Apartments",
    "wof:placetype":"venue"
},
  "geometry": {"coordinates":[-77.562065,40.635008],"type":"Point"}
}