{
  "type": "Feature",
  "properties": {
    "iso:country":"US",
    "sg:address":"660 Penn St",
    "sg:city":"Pennsburg",
    "sg:classifiers":[
        {
            "category":"Retail",
            "subcategory":"Laundry & Dry Cleaning",
            "type":"Services"
        },
        {
            "category":"Building & Trades",
            "subcategory":"Cleaning & Sanitation",
            "type":"Services"
        }
    ],
    "sg:phone":"+1 215 541 4157",
    "sg:postcode":"18073",
    "sg:province":"PA",
    "sg:tags":[
        "cleaner",
        "house"
    ],
    "wof:name":"Marks Quality Cleaning",
    "wof:placetype":"venue"
},
  "geometry": {"coordinates":[-75.49315199999999,40.394829],"type":"Point"}
}