{
  "type": "Feature",
  "properties": {
    "iso:country":"US",
    "sg:address":"105 Cub Rd",
    "sg:city":"Greeley",
    "sg:classifiers":[
        {
            "category":"Building & Trades",
            "subcategory":"Plumbing",
            "type":"Services"
        }
    ],
    "sg:phone":"+1   ",
    "sg:postcode":"18436",
    "sg:province":"PA",
    "sg:tags":[
        "contractor"
    ],
    "wof:name":"JNj Plumbing & Heating Inc",
    "wof:placetype":"venue"
},
  "geometry": {"coordinates":[-75.334509,41.376091],"type":"Point"}
}