{
  "type": "Feature",
  "properties": {
    "iso:country":"US",
    "sg:address":"213 E Union Rd",
    "sg:city":"Cheswick",
    "sg:classifiers":[
        {
            "category":"Professional",
            "subcategory":"Advertising",
            "type":"Services"
        }
    ],
    "sg:phone":"+1   ",
    "sg:postcode":"15024",
    "sg:province":"PA",
    "sg:tags":[
        "outdoor"
    ],
    "wof:name":"Safari Outdoor Advertising",
    "wof:placetype":"venue"
},
  "geometry": {"coordinates":[-79.853544,40.614852],"type":"Point"}
}