{
  "type": "Feature",
  "properties": {
    "iso:country":"US",
    "sg:address":"116 E Lincoln Ave",
    "sg:city":"Mc Donald",
    "sg:classifiers":[
        {
            "category":"Manufacturing",
            "subcategory":"Printing",
            "type":"Manufacturing & Wholesale Goods"
        }
    ],
    "sg:phone":"+1   ",
    "sg:postcode":"15057",
    "sg:province":"PA",
    "sg:tags":[
        "newspaper"
    ],
    "wof:name":"Record Enterprise New",
    "wof:placetype":"venue"
},
  "geometry": {"coordinates":[-80.234813,40.368805],"type":"Point"}
}