{
  "type": "Feature",
  "properties": {
    "addr:full":"1515 Locust St Philadelphia PA 19102",
    "addr:housenumber":"1515",
    "addr:postcode":"19102",
    "addr:street":"Locust St",
    "iso:country":"US",
    "sg:address":"1515 Locust St",
    "sg:city":"Philadelphia",
    "sg:classifiers":[
        {
            "category":"Real Estate",
            "subcategory":"Real Estate Operator",
            "type":"Services"
        }
    ],
    "sg:phone":"+1   ",
    "sg:postcode":"19102",
    "sg:province":"PA",
    "sg:tags":[
        "building",
        "nonresidential"
    ],
    "wof:name":"Tinkelman Holdings Inc",
    "wof:placetype":"venue"
},
  "geometry": {"coordinates":[-75.16643999999999,39.948501],"type":"Point"}
}