{
  "type": "Feature",
  "properties": {
    "iso:country":"US",
    "sg:address":"846 Medway Rd",
    "sg:city":"Philadelphia",
    "sg:classifiers":[
        {
            "category":"Building & Trades",
            "subcategory":"Electrical",
            "type":"Services"
        }
    ],
    "sg:phone":"+1   ",
    "sg:postcode":"19115",
    "sg:province":"PA",
    "sg:tags":[
        "electrical",
        "contractor"
    ],
    "wof:name":"K A Brown Electric",
    "wof:placetype":"venue"
},
  "geometry": {"coordinates":[-75.038945,40.102661],"type":"Point"}
}