{
  "type": "Feature",
  "properties": {
    "iso:country":"US",
    "sg:address":"119 W Lincoln Ave",
    "sg:city":"Mc Donald",
    "sg:classifiers":[
        {
            "category":"Health Services",
            "subcategory":"Nursing And Care Facility",
            "type":"Services"
        }
    ],
    "sg:phone":"+1 724 926 3526",
    "sg:postcode":"15057",
    "sg:province":"PA",
    "sg:tags":[
        "home",
        "retirement",
        "community"
    ],
    "wof:name":"Paulin Personal Care Home",
    "wof:placetype":"venue"
},
  "geometry": {"coordinates":[-80.235055,40.368695],"type":"Point"}
}