{
  "type": "Feature",
  "properties": {
    "iso:country":"US",
    "sg:address":"11119 Buchanan Trl E",
    "sg:city":"Waynesboro",
    "sg:classifiers":[
        {
            "category":"Restaurant",
            "type":"Food & Drink"
        }
    ],
    "sg:phone":"+1 717 762 1477",
    "sg:postcode":"17268",
    "sg:province":"PA",
    "wof:name":"Cafe del Sol",
    "wof:placetype":"venue"
},
  "geometry": {"coordinates":[-77.546771,39.742327],"type":"Point"}
}