{
  "type": "Feature",
  "properties": {
    "iso:country":"US",
    "sg:address":"30 Wessex Ln",
    "sg:city":"Oxford",
    "sg:classifiers":[
        {
            "category":"Professional",
            "subcategory":"Research",
            "type":"Services"
        }
    ],
    "sg:phone":"+1 610 932 7200",
    "sg:postcode":"19363",
    "sg:province":"PA",
    "sg:tags":[
        "foundation",
        "philanthropic"
    ],
    "wof:name":"Oxford Educational Foundation",
    "wof:placetype":"venue"
},
  "geometry": {"coordinates":[-75.984185,39.784431],"type":"Point"}
}