{
  "type": "Feature",
  "properties": {
    "iso:country":"US",
    "sg:address":"601 W Chester Rd",
    "sg:city":"West Chester",
    "sg:classifiers":[
        {
            "category":"Government",
            "subcategory":"Office",
            "type":"Public Place"
        }
    ],
    "sg:phone":"+1   ",
    "sg:postcode":"19382",
    "sg:province":"PA",
    "sg:tags":[
        "executive"
    ],
    "wof:name":"Aging Services Dept of",
    "wof:placetype":"venue"
},
  "geometry": {"coordinates":[-75.545365,39.910969],"type":"Point"}
}