{
  "type": "Feature",
  "properties": {
    "iso:country":"US",
    "sg:address":"22 N Main St",
    "sg:city":"Mansfield",
    "sg:classifiers":[
        {
            "category":"Utilities",
            "subcategory":"Electric",
            "type":"Services"
        }
    ],
    "sg:phone":"+1 570 662 2175",
    "sg:postcode":"16933",
    "sg:province":"PA",
    "sg:tags":[
        "company"
    ],
    "sg:website":"www.tri-countyrec.com",
    "wof:name":"Tri-County Rural Electric",
    "wof:placetype":"venue"
},
  "geometry": {"coordinates":[-77.078126,41.807296],"type":"Point"}
}