{
  "type": "Feature",
  "properties": {
    "iso:country":"US",
    "sg:address":"125 E Sellers Ave",
    "sg:city":"Ridley Park",
    "sg:classifiers":[
        {
            "category":"Retail",
            "subcategory":"Laundry & Dry Cleaning",
            "type":"Services"
        }
    ],
    "sg:phone":"+1 610 521 1483",
    "sg:postcode":"19078",
    "sg:province":"PA",
    "sg:tags":[
        "cleaners"
    ],
    "wof:name":"Yi Cleaners & Alterations",
    "wof:placetype":"venue"
},
  "geometry": {"coordinates":[-75.322458,39.879497],"type":"Point"}
}