{
  "type": "Feature",
  "properties": {
    "iso:country":"US",
    "sg:address":"747 Mifflin Rd",
    "sg:city":"Pittsburgh",
    "sg:classifiers":[
        {
            "category":"Autos & Motor Vehicles",
            "subcategory":"Automobile Sales",
            "type":"Retail Goods"
        }
    ],
    "sg:phone":"+1 412 461 8711",
    "sg:postcode":"15207",
    "sg:province":"PA",
    "sg:tags":[
        "used"
    ],
    "wof:name":"Marshall Auto Sales",
    "wof:placetype":"venue"
},
  "geometry": {"coordinates":[-79.92428,40.37925],"type":"Point"}
}