{
  "type": "Feature",
  "properties": {
    "iso:country":"US",
    "sg:address":"1100 E Philadelphia Ave",
    "sg:city":"Gilbertsville",
    "sg:classifiers":[
        {
            "category":"Food & Beverages",
            "subcategory":"Meat & Fish",
            "type":"Retail Goods"
        }
    ],
    "sg:phone":"+1 610 367 8791",
    "sg:postcode":"19525",
    "sg:province":"PA",
    "wof:name":"Burt's Farms",
    "wof:placetype":"venue"
},
  "geometry": {"coordinates":[-75.61615999999999,40.322353],"type":"Point"}
}