{
  "type": "Feature",
  "properties": {
    "addr:full":"220 W College Ave Pleasant Gap PA 16823",
    "addr:housenumber":"220",
    "addr:postcode":"16823",
    "addr:street":"W College Ave Pleasant",
    "iso:country":"US",
    "sg:address":"220 W College Ave",
    "sg:city":"Pleasant Gap",
    "sg:classifiers":[
        {
            "category":"Retail",
            "subcategory":"Repair Shop",
            "type":"Services"
        }
    ],
    "sg:phone":"+1 814 359 3022",
    "sg:postcode":"16823",
    "sg:province":"PA",
    "sg:tags":[
        "repairing",
        "saw"
    ],
    "wof:name":"Rod's Sales & Svc",
    "wof:placetype":"venue"
},
  "geometry": {"coordinates":[-77.750213,40.86513],"type":"Point"}
}