{
  "type": "Feature",
  "properties": {
    "addr:full":"232 S 45th St Philadelphia PA 19104",
    "addr:housenumber":"232",
    "addr:postcode":"19104",
    "addr:street":"S 45Th St",
    "iso:country":"US",
    "sg:address":"232 S 45th St",
    "sg:city":"Philadelphia",
    "sg:classifiers":[
        {
            "category":"Bars & Pubs",
            "subcategory":"Dive Bar",
            "type":"Food & Drink"
        }
    ],
    "sg:phone":"+1 215 243 9389",
    "sg:postcode":"19104",
    "sg:province":"PA",
    "wof:name":"Watutsi II Pub",
    "wof:placetype":"venue"
},
  "geometry": {"coordinates":[-75.21199799999999,39.954201],"type":"Point"}
}