{
  "type": "Feature",
  "properties": {
    "iso:country":"US",
    "sg:address":"Coulter & Statn Sts",
    "sg:city":"Bridgeville",
    "sg:classifiers":[
        {
            "category":"Building & Trades",
            "subcategory":"Construction",
            "type":"Services"
        }
    ],
    "sg:phone":"+1 412 221 1800",
    "sg:postcode":"15017",
    "sg:province":"PA",
    "sg:tags":[
        "painter"
    ],
    "wof:name":"Conomos John B Inc",
    "wof:placetype":"venue"
},
  "geometry": {"coordinates":[-80.121803,40.3395],"type":"Point"}
}