{
  "type": "Feature",
  "properties": {
    "iso:country":"US",
    "sg:address":"601 Penn St Ste 160",
    "sg:city":"Reading",
    "sg:classifiers":[
        {
            "category":"Coffee & Tea",
            "type":"Food & Drink"
        },
        {
            "category":"Restaurant",
            "type":"Food & Drink"
        }
    ],
    "sg:phone":"+1 610 374 9385",
    "sg:postcode":"19601",
    "sg:province":"PA",
    "sg:tags":[
        "shop",
        "style",
        "espresso",
        "family"
    ],
    "wof:name":"American Coffee House Inc",
    "wof:placetype":"venue"
},
  "geometry": {"coordinates":[-75.92588000000001,40.335331],"type":"Point"}
}