{
  "type": "Feature",
  "properties": {
    "iso:country":"US",
    "sg:address":"142 E College Ave",
    "sg:city":"State College",
    "sg:classifiers":[
        {
            "category":"Cafe",
            "type":"Food & Drink"
        },
        {
            "category":"Restaurant",
            "type":"Food & Drink"
        }
    ],
    "sg:menulink":"http://www.allmenus.com/pa/state-college/242009-spats-cafe-and-speakeasy/menu/",
    "sg:phone":"+1 814 238 7010",
    "sg:postcode":"16801",
    "sg:province":"PA",
    "sg:tags":[
        "american",
        "creole",
        "cajun"
    ],
    "wof:name":"Spats Cafe And Speakeasy",
    "wof:placetype":"venue"
},
  "geometry": {"coordinates":[-77.861172,40.794854],"type":"Point"}
}