{
  "type": "Feature",
  "properties": {
    "iso:country":"US",
    "sg:address":"510 Beaver St",
    "sg:city":"Sewickley",
    "sg:classifiers":[
        {
            "category":"Banks & Credit Unions",
            "subcategory":"Bank",
            "type":"Services"
        }
    ],
    "sg:phone":"+1 412 749 8120",
    "sg:postcode":"15143",
    "sg:province":"PA",
    "sg:tags":[
        "commercial"
    ],
    "wof:name":"Le Salle Bank",
    "wof:placetype":"venue"
},
  "geometry": {"coordinates":[-80.180187,40.539979],"type":"Point"}
}