{
  "type": "Feature",
  "properties": {
    "iso:country":"US",
    "sg:address":"227 Grandview Rd",
    "sg:city":"Media",
    "sg:classifiers":[
        {
            "category":"Real Estate",
            "subcategory":"Architect",
            "type":"Services"
        }
    ],
    "sg:phone":"+1 610 565 1161",
    "sg:postcode":"19063",
    "sg:province":"PA",
    "wof:name":"Linderman Group Architects",
    "wof:placetype":"venue"
},
  "geometry": {"coordinates":[-75.36836599999999,39.910451],"type":"Point"}
}