{
  "type": "Feature",
  "properties": {
    "iso:country":"US",
    "sg:address":"471 E Church St",
    "sg:city":"Stevens",
    "sg:classifiers":[
        {
            "category":"Farming",
            "subcategory":"Livestock Farm",
            "type":"Manufacturing & Wholesale Goods"
        }
    ],
    "sg:phone":"+1   ",
    "sg:postcode":"17578",
    "sg:province":"PA",
    "wof:name":"Wildflower Goat Farm",
    "wof:placetype":"venue"
},
  "geometry": {"coordinates":[-76.107792,40.188799],"type":"Point"}
}