{
  "type": "Feature",
  "properties": {
    "iso:country":"US",
    "sg:address":"1345 W Chester Rd",
    "sg:city":"West Chester",
    "sg:classifiers":[
        {
            "category":"Home & Garden",
            "subcategory":"Building Materials",
            "type":"Retail Goods"
        }
    ],
    "sg:phone":"+1 610 399 3606",
    "sg:postcode":"19382",
    "sg:province":"PA",
    "sg:tags":[
        "supply",
        "fireplace",
        "accessory"
    ],
    "wof:name":"Brandywine Patio",
    "wof:placetype":"venue"
},
  "geometry": {"coordinates":[-75.547268,39.911227],"type":"Point"}
}