{
  "type": "Feature",
  "properties": {
    "iso:country":"US",
    "sg:address":"2121 Shelly Dr",
    "sg:city":"Indiana",
    "sg:classifiers":[
        {
            "category":"Health Services",
            "subcategory":"Doctor",
            "type":"Services"
        }
    ],
    "sg:phone":"+1   ",
    "sg:postcode":"15701",
    "sg:province":"PA",
    "sg:tags":[
        "medical"
    ],
    "wof:name":"Durre Ahmed MD",
    "wof:placetype":"venue"
},
  "geometry": {"coordinates":[-79.18937200000001,40.620358],"type":"Point"}
}