{
  "type": "Feature",
  "properties": {
    "addr:full":"2109 Market St Camp Hill PA 17011",
    "addr:housenumber":"2109",
    "addr:postcode":"17011",
    "addr:street":"Market St",
    "iso:country":"US",
    "sg:address":"2109 Market St",
    "sg:city":"Camp Hill",
    "sg:classifiers":[
        {
            "category":"Professional",
            "subcategory":"Lawyer & Legal Services",
            "type":"Services"
        }
    ],
    "sg:phone":"+1 717 737 3405",
    "sg:postcode":"17011",
    "sg:province":"PA",
    "sg:tags":[
        "divorce",
        "law",
        "family"
    ],
    "wof:name":"Shuff Geoffrey S Atty",
    "wof:placetype":"venue"
},
  "geometry": {"coordinates":[-76.920097,40.240002],"type":"Point"}
}