{
  "type": "Feature",
  "properties": {
    "iso:country":"US",
    "sg:address":"321 Hazel Kirk Rd",
    "sg:city":"Monongahela",
    "sg:classifiers":[
        {
            "category":"Retail",
            "subcategory":"Veterinary Services",
            "type":"Services"
        }
    ],
    "sg:phone":"+1 724 258 8406",
    "sg:postcode":"15063",
    "sg:province":"PA",
    "sg:tags":[
        "veterinarian"
    ],
    "sg:website":"www.monongahelavet.com",
    "wof:name":"Monongahela Animal Hospital",
    "wof:placetype":"venue"
},
  "geometry": {"coordinates":[-79.97049699999999,40.192799],"type":"Point"}
}