{
  "type": "Feature",
  "properties": {
    "iso:country":"US",
    "sg:address":"186 42nd St",
    "sg:city":"Pittsburgh",
    "sg:classifiers":[
        {
            "category":"Government",
            "subcategory":"Post Office",
            "type":"Public Place"
        }
    ],
    "sg:phone":"+1 412 000 1111",
    "sg:postcode":"15201",
    "sg:province":"PA",
    "wof:name":"US Post Office",
    "wof:placetype":"venue"
},
  "geometry": {"coordinates":[-79.962019,40.471181],"type":"Point"}
}