{
  "type": "Feature",
  "properties": {
    "iso:country":"US",
    "sg:address":"1400 Locust St",
    "sg:city":"Pittsburgh",
    "sg:classifiers":[
        {
            "category":"Health Services",
            "subcategory":"Clinic",
            "type":"Services"
        }
    ],
    "sg:phone":"+1 412 281 0322",
    "sg:postcode":"15219",
    "sg:province":"PA",
    "sg:tags":[
        "physician",
        "surgeon",
        "bureau",
        "information"
    ],
    "wof:name":"Metropolitan ENT Assoc",
    "wof:placetype":"venue"
},
  "geometry": {"coordinates":[-79.98519899999999,40.43683],"type":"Point"}
}