{
  "type": "Feature",
  "properties": {
    "iso:country":"US",
    "sg:address":"20300 Route 19",
    "sg:city":"Cranberry Twp",
    "sg:classifiers":[
        {
            "category":"Health Services",
            "subcategory":"Dentist",
            "type":"Services"
        }
    ],
    "sg:phone":"+1 724 776 6670",
    "sg:postcode":"16066",
    "sg:province":"PA",
    "sg:tags":[
        "orthodontist"
    ],
    "wof:name":"Cranberry Orthodontics",
    "wof:placetype":"venue"
},
  "geometry": {"coordinates":[-80.1035,40.692001],"type":"Point"}
}