{
  "type": "Feature",
  "properties": {
    "iso:country":"US",
    "sg:address":"152 W Montgomery Ave",
    "sg:city":"Ardmore",
    "sg:classifiers":[
        {
            "category":"Building & Trades",
            "subcategory":"Landscaping Services",
            "type":"Services"
        }
    ],
    "sg:phone":"+1 610 667 0367",
    "sg:postcode":"19003",
    "sg:province":"PA",
    "sg:tags":[
        "tree"
    ],
    "wof:name":"BTE",
    "wof:placetype":"venue"
},
  "geometry": {"coordinates":[-75.294017,40.011324],"type":"Point"}
}