{
  "type": "Feature",
  "properties": {
    "iso:country":"US",
    "sg:address":"680 Allendale Rd",
    "sg:city":"King Of Prussia",
    "sg:classifiers":[
        {
            "category":"Professional",
            "subcategory":"Research",
            "type":"Services"
        },
        {
            "category":"Manufacturing",
            "subcategory":"Chemicals & Compounds",
            "type":"Manufacturing & Wholesale Goods"
        }
    ],
    "sg:phone":"+1 610 992 1880",
    "sg:postcode":"19406",
    "sg:province":"PA",
    "sg:tags":[
        "res",
        "miller",
        "commercial",
        "drug",
        "nonphysical",
        "physical"
    ],
    "wof:name":"Immune Response Corporation",
    "wof:placetype":"venue"
},
  "geometry": {"coordinates":[-75.394825,40.098912],"type":"Point"}
}