{
  "type": "Feature",
  "properties": {
    "iso:country":"US",
    "sg:address":"250 Lefever Rd",
    "sg:city":"Newville",
    "sg:classifiers":[
        {
            "category":"Freight",
            "type":"Transportation"
        }
    ],
    "sg:phone":"+1   ",
    "sg:postcode":"17241",
    "sg:province":"PA",
    "sg:tags":[
        "operator",
        "local",
        "trucking"
    ],
    "wof:name":"P Burruss Trucking",
    "wof:placetype":"venue"
},
  "geometry": {"coordinates":[-77.370251,40.181469],"type":"Point"}
}