{
  "type": "Feature",
  "properties": {
    "iso:country":"US",
    "sg:address":"536 E Penn Ave",
    "sg:city":"Cleona",
    "sg:classifiers":[
        {
            "category":"Health Services",
            "subcategory":"Chiropractor",
            "type":"Services"
        }
    ],
    "sg:phone":"+1 717 228 1330",
    "sg:postcode":"17042",
    "sg:province":"PA",
    "wof:name":"Fields Chiropractic",
    "wof:placetype":"venue"
},
  "geometry": {"coordinates":[-76.46602799999999,40.338743],"type":"Point"}
}