{
  "type": "Feature",
  "properties": {
    "iso:country":"US",
    "sg:address":"801 Yale Ave",
    "sg:city":"Swarthmore",
    "sg:classifiers":[
        {
            "category":"Banks & Credit Unions",
            "subcategory":"Investment Brokerage",
            "type":"Services"
        },
        {
            "category":"Banks & Credit Unions",
            "subcategory":"Financial Services",
            "type":"Services"
        }
    ],
    "sg:phone":"+1 610 541 6790",
    "sg:postcode":"19081",
    "sg:province":"PA",
    "sg:tags":[
        "security",
        "investor"
    ],
    "wof:name":"Swarthmore Investment Manageme",
    "wof:placetype":"venue"
},
  "geometry": {"coordinates":[-75.35709199999999,39.894341],"type":"Point"}
}