{
  "type": "Feature",
  "properties": {
    "iso:country":"US",
    "sg:address":"1840 County Line Rd",
    "sg:city":"Huntingdon Vly",
    "sg:classifiers":[
        {
            "category":"Building & Trades",
            "subcategory":"Construction",
            "type":"Services"
        },
        {
            "category":"Wholesale",
            "subcategory":"Furniture",
            "type":"Manufacturing & Wholesale Goods"
        }
    ],
    "sg:phone":"+1 215 322 8240",
    "sg:postcode":"19006",
    "sg:province":"PA",
    "sg:tags":[
        "modular",
        "installation"
    ],
    "sg:website":"www.tenaska.com",
    "wof:name":"Cutting Edge Installations LLC",
    "wof:placetype":"venue"
},
  "geometry": {"coordinates":[-75.03005400000001,40.147184],"type":"Point"}
}