{
  "type": "Feature",
  "properties": {
    "iso:country":"US",
    "sg:address":"1120 Anderson Ferry Rd",
    "sg:city":"Mount Joy",
    "sg:classifiers":[
        {
            "category":"Professional",
            "subcategory":"Management & Consulting",
            "type":"Services"
        }
    ],
    "sg:phone":"+1   ",
    "sg:postcode":"17552",
    "sg:province":"PA",
    "sg:tags":[
        "retail",
        "direct",
        "sales"
    ],
    "wof:name":"Shaklee Corp",
    "wof:placetype":"venue"
},
  "geometry": {"coordinates":[-76.52401999999999,40.085223],"type":"Point"}
}