{
  "type": "Feature",
  "properties": {
    "iso:country":"US",
    "sg:address":"1739 Quarry Rd",
    "sg:city":"Jersey Shore",
    "sg:classifiers":[
        {
            "category":"Building & Trades",
            "subcategory":"Construction",
            "type":"Services"
        }
    ],
    "sg:phone":"+1 570 745 3323",
    "sg:postcode":"17740",
    "sg:province":"PA",
    "sg:tags":[
        "excavation",
        "excavating",
        "contractor"
    ],
    "wof:name":"D L Duke Lehman Excavating",
    "wof:placetype":"venue"
},
  "geometry": {"coordinates":[-77.20821100000001,41.132616],"type":"Point"}
}