{
  "type": "Feature",
  "properties": {
    "iso:country":"US",
    "sg:address":"300 Flint Ct",
    "sg:city":"Morrisville",
    "sg:classifiers":[
        {
            "category":"Manufacturing",
            "subcategory":"Printing",
            "type":"Manufacturing & Wholesale Goods"
        }
    ],
    "sg:phone":"+1   ",
    "sg:postcode":"19067",
    "sg:province":"PA",
    "sg:tags":[
        "publishing"
    ],
    "wof:name":"Priority Press Ltd",
    "wof:placetype":"venue"
},
  "geometry": {"coordinates":[-74.849737,40.209267],"type":"Point"}
}