{
  "type": "Feature",
  "properties": {
    "iso:country":"US",
    "sg:address":"640 Nutt Rd",
    "sg:city":"Phoenixville",
    "sg:classifiers":[
        {
            "category":"Real Estate",
            "subcategory":"Real Estate Operator",
            "type":"Services"
        }
    ],
    "sg:phone":"+1 610 933 3455",
    "sg:postcode":"19460",
    "sg:province":"PA",
    "sg:tags":[
        "building",
        "apartment"
    ],
    "wof:name":"Holly Court Apartments",
    "wof:placetype":"venue"
},
  "geometry": {"coordinates":[-75.532832,40.131216],"type":"Point"}
}