{
  "type": "Feature",
  "properties": {
    "iso:country":"US",
    "sg:address":"999 Glencoe Ave",
    "sg:city":"Pittsburgh",
    "sg:classifiers":[
        {
            "category":"Shopping",
            "subcategory":"Hobbies, Toys, & Games",
            "type":"Retail Goods"
        }
    ],
    "sg:phone":"+1 412 922 4367",
    "sg:postcode":"15220",
    "sg:province":"PA",
    "sg:tags":[
        "craft"
    ],
    "wof:name":"Selective Giftware",
    "wof:placetype":"venue"
},
  "geometry": {"coordinates":[-80.046583,40.416903],"type":"Point"}
}