{
  "type": "Feature",
  "properties": {
    "iso:country":"US",
    "sg:address":"180 Lincoln Ave",
    "sg:city":"Bellevue",
    "sg:classifiers":[
        {
            "category":"Health Services",
            "subcategory":"Podiatrist",
            "type":"Services"
        }
    ],
    "sg:phone":"+1 412 734 3200",
    "sg:postcode":"15202",
    "sg:province":"PA",
    "wof:name":"Ankle & Foot Care",
    "wof:placetype":"venue"
},
  "geometry": {"coordinates":[-80.04827299999999,40.49089],"type":"Point"}
}