{
  "type": "Feature",
  "properties": {
    "iso:country":"US",
    "sg:address":"35 S Willowdale Dr # 721",
    "sg:city":"Lancaster",
    "sg:classifiers":[
        {
            "category":"Shopping",
            "subcategory":"Clothing, Apparel, & Fashions",
            "type":"Retail Goods"
        }
    ],
    "sg:phone":"+1 717 299 8925",
    "sg:postcode":"17602",
    "sg:province":"PA",
    "sg:tags":[
        "apparel",
        "women's"
    ],
    "wof:name":"Deb",
    "wof:placetype":"venue"
},
  "geometry": {"coordinates":[-76.197029,40.023071],"type":"Point"}
}