{
  "type": "Feature",
  "properties": {
    "iso:country":"US",
    "sg:address":"211 N 13th St",
    "sg:city":"Philadelphia",
    "sg:classifiers":[
        {
            "category":"Real Estate",
            "subcategory":"Real Estate Operator",
            "type":"Services"
        }
    ],
    "sg:phone":"+1 215 963 1491",
    "sg:postcode":"19107",
    "sg:province":"PA",
    "sg:tags":[
        "building",
        "parks"
    ],
    "wof:name":"Bellmont Building",
    "wof:placetype":"venue"
},
  "geometry": {"coordinates":[-75.160444,39.956744],"type":"Point"}
}