{
  "type": "Feature",
  "properties": {
    "iso:country":"US",
    "sg:address":"352 Harshaw Dr",
    "sg:city":"Chester Springs",
    "sg:classifiers":[
        {
            "category":"Manufacturing",
            "subcategory":"Tools & Machinery",
            "type":"Manufacturing & Wholesale Goods"
        }
    ],
    "sg:phone":"+1   ",
    "sg:postcode":"19425",
    "sg:province":"PA",
    "sg:tags":[
        "engine",
        "lock",
        "standard",
        "mfg"
    ],
    "wof:name":"Ingersoll-Rand",
    "wof:placetype":"venue"
},
  "geometry": {"coordinates":[-75.665668,40.074547],"type":"Point"}
}