{
  "type": "Feature",
  "properties": {
    "iso:country":"US",
    "sg:address":"4808 Liberty Ave",
    "sg:city":"Pittsburgh",
    "sg:classifiers":[
        {
            "category":"Professional",
            "subcategory":"Lawyer & Legal Services",
            "type":"Services"
        }
    ],
    "sg:phone":"+1 412 802 6422",
    "sg:postcode":"15224",
    "sg:province":"PA",
    "sg:tags":[
        "attorney"
    ],
    "wof:name":"Richard Haft Law Offices",
    "wof:placetype":"venue"
},
  "geometry": {"coordinates":[-79.94607600000001,40.459992],"type":"Point"}
}