{
  "type": "Feature",
  "properties": {
    "addr:full":"RR 413 Buckingham PA 18912",
    "addr:housenumber":"413",
    "addr:postcode":"18912",
    "addr:street":"Buckingham Pa",
    "iso:country":"US",
    "sg:address":"RR 413",
    "sg:city":"Buckingham",
    "sg:classifiers":[
        {
            "category":"Deli",
            "type":"Food & Drink"
        }
    ],
    "sg:phone":"+1 215 794 7394",
    "sg:postcode":"18912",
    "sg:province":"PA",
    "sg:website":"www.wawa.com",
    "wof:name":"Wawa Food Markets",
    "wof:placetype":"venue"
},
  "geometry": {"coordinates":[-75.0625,40.321701],"type":"Point"}
}