{
  "type": "Feature",
  "properties": {
    "iso:country":"US",
    "sg:address":"1301 Race St",
    "sg:city":"Philadelphia",
    "sg:classifiers":[
        {
            "category":"Travel",
            "subcategory":"Hotels & Motels",
            "type":"Entertainment"
        }
    ],
    "sg:phone":"+1 215 238 0518",
    "sg:postcode":"19107",
    "sg:province":"PA",
    "wof:name":"Hersha Hosp Mgmnt-Hampton Inn",
    "wof:placetype":"venue"
},
  "geometry": {"coordinates":[-75.160797,39.955898],"type":"Point"}
}