{
  "type": "Feature",
  "properties": {
    "iso:country":"US",
    "sg:address":"4700 5th Ave",
    "sg:city":"Pittsburgh",
    "sg:classifiers":[
        {
            "category":"Social Services",
            "subcategory":"Adult Care",
            "type":"Services"
        }
    ],
    "sg:phone":"+1 412 621 0900",
    "sg:postcode":"15213",
    "sg:province":"PA",
    "sg:tags":[
        "residential",
        "intermediate",
        "facility"
    ],
    "wof:name":"Independence Court Of Oakland",
    "wof:placetype":"venue"
},
  "geometry": {"coordinates":[-79.946873,40.447185],"type":"Point"}
}