{
  "type": "Feature",
  "properties": {
    "iso:country":"US",
    "sg:address":"421 Redgate Rd",
    "sg:city":"Sewickley",
    "sg:classifiers":[
        {
            "category":"Building & Trades",
            "subcategory":"Pest Control",
            "type":"Services"
        }
    ],
    "sg:phone":"+1   ",
    "sg:postcode":"15143",
    "sg:province":"PA",
    "sg:tags":[
        "business"
    ],
    "wof:name":"Home Incpection",
    "wof:placetype":"venue"
},
  "geometry": {"coordinates":[-80.152663,40.530154],"type":"Point"}
}