{
  "type": "Feature",
  "properties": {
    "addr:full":"175 Penn St Huntingdon PA 16652",
    "addr:housenumber":"175",
    "addr:postcode":"16652",
    "addr:street":"Penn St",
    "iso:country":"US",
    "sg:address":"175 Penn St",
    "sg:city":"Huntingdon",
    "sg:classifiers":[
        {
            "category":"Recreation",
            "type":"Entertainment"
        }
    ],
    "sg:phone":"+1 814 643 2530",
    "sg:postcode":"16652",
    "sg:province":"PA",
    "wof:name":"Isett Community Swimming Pool",
    "wof:placetype":"venue"
},
  "geometry": {"coordinates":[-78.004305,40.481709],"type":"Point"}
}