{
  "type": "Feature",
  "properties": {
    "iso:country":"US",
    "sg:address":"826 E Baltimore Pike Unit 1",
    "sg:city":"Kennett Square",
    "sg:classifiers":[
        {
            "category":"Shopping",
            "subcategory":"Hobbies, Toys, & Games",
            "type":"Retail Goods"
        },
        {
            "category":"Shopping",
            "subcategory":"Books",
            "type":"Retail Goods"
        }
    ],
    "sg:phone":"+1 610 444 7114",
    "sg:postcode":"19348",
    "sg:province":"PA",
    "sg:tags":[
        "bookstore",
        "toy",
        "store"
    ],
    "sg:website":"www.thetoypad.com",
    "wof:name":"The Toy Pad",
    "wof:placetype":"venue"
},
  "geometry": {"coordinates":[-75.68395,39.861174],"type":"Point"}
}