{
  "type": "Feature",
  "properties": {
    "iso:country":"US",
    "sg:address":"210 Main St",
    "sg:city":"Slickville",
    "sg:classifiers":[
        {
            "category":"Autos & Motor Vehicles",
            "subcategory":"Auto Supplies",
            "type":"Retail Goods"
        }
    ],
    "sg:phone":"+1 724 468 6668",
    "sg:postcode":"15656",
    "sg:province":"PA",
    "sg:tags":[
        "automobile",
        "parts"
    ],
    "wof:name":"Slickville Auto Body & Truck",
    "wof:placetype":"venue"
},
  "geometry": {"coordinates":[-79.605087,40.627362],"type":"Point"}
}