{
  "type": "Feature",
  "properties": {
    "iso:country":"US",
    "sg:address":"5 S Main St Ste Frnt",
    "sg:city":"Coudersport",
    "sg:classifiers":[
        {
            "category":"Restaurant",
            "type":"Food & Drink"
        }
    ],
    "sg:phone":"+1 814 274 8777",
    "sg:postcode":"16915",
    "sg:province":"PA",
    "sg:tags":[
        "asian",
        "chinese",
        "pan"
    ],
    "wof:name":"China Garden",
    "wof:placetype":"venue"
},
  "geometry": {"coordinates":[-78.02118299999999,41.772314],"type":"Point"}
}