{
  "type": "Feature",
  "properties": {
    "addr:full":"623 W Union Blvd Bethlehem PA 18018",
    "addr:housenumber":"623",
    "addr:postcode":"18018",
    "addr:street":"W Union Blvd",
    "iso:country":"US",
    "sg:address":"623 W Union Blvd",
    "sg:city":"Bethlehem",
    "sg:classifiers":[
        {
            "category":"Health Services",
            "subcategory":"Nursing And Care Facility",
            "type":"Services"
        },
        {
            "category":"Social Services",
            "type":"Services"
        }
    ],
    "sg:phone":"+1 610 867 2030",
    "sg:postcode":"18018",
    "sg:province":"PA",
    "sg:tags":[
        "organization",
        "management",
        "out",
        "specialty",
        "welfare"
    ],
    "sg:website":"www.stepbystepusa.com",
    "wof:name":"Step-By-Step Inc",
    "wof:placetype":"venue"
},
  "geometry": {"coordinates":[-75.39137700000001,40.62516],"type":"Point"}
}