{
  "type": "Feature",
  "properties": {
    "addr:full":"406 Broad Ave Belle Vernon PA 15012",
    "addr:housenumber":"406",
    "addr:postcode":"15012",
    "addr:street":"Broad Ave",
    "iso:country":"US",
    "sg:address":"406 Broad Ave",
    "sg:city":"Belle Vernon",
    "sg:classifiers":[
        {
            "category":"Education",
            "subcategory":"Dance Studio",
            "type":"Public Place"
        }
    ],
    "sg:phone":"+1 724 929 7827",
    "sg:postcode":"15012",
    "sg:province":"PA",
    "sg:tags":[
        "instruction",
        "dancing"
    ],
    "wof:name":"Attitudes In Motion",
    "wof:placetype":"venue"
},
  "geometry": {"coordinates":[-79.86771400000001,40.129506],"type":"Point"}
}