{
  "type": "Feature",
  "properties": {
    "iso:country":"US",
    "sg:address":"1343 Newport Ave",
    "sg:city":"Northampton",
    "sg:classifiers":[
        {
            "category":"Organizations",
            "subcategory":"Religious Organization",
            "type":"Services"
        }
    ],
    "sg:phone":"+1 610 262 4104",
    "sg:postcode":"18067",
    "sg:province":"PA",
    "sg:tags":[
        "church",
        "ukrainian"
    ],
    "wof:name":"St Johns The Baptist Ukranian",
    "wof:placetype":"venue"
},
  "geometry": {"coordinates":[-75.49239300000001,40.679691],"type":"Point"}
}