{
  "type": "Feature",
  "properties": {
    "iso:country":"US",
    "sg:address":"1001 Brinton Rd",
    "sg:city":"Pittsburgh",
    "sg:classifiers":[
        {
            "category":"Utilities",
            "subcategory":"Telephone",
            "type":"Services"
        }
    ],
    "sg:phone":"+1 412 244 2000",
    "sg:postcode":"15221",
    "sg:province":"PA",
    "sg:tags":[
        "telecommunication"
    ],
    "sg:website":"www.wins.com",
    "wof:name":"Westinghouse Communications",
    "wof:placetype":"venue"
},
  "geometry": {"coordinates":[-79.87317899999999,40.427817],"type":"Point"}
}