{
  "type": "Feature",
  "properties": {
    "addr:full":"1009 Old Berwick Rd Bloomsburg PA 17815",
    "addr:housenumber":"1009",
    "addr:postcode":"17815",
    "addr:street":"Old Berwick Rd",
    "iso:country":"US",
    "sg:address":"1009 Old Berwick Rd",
    "sg:city":"Bloomsburg",
    "sg:classifiers":[
        {
            "category":"Personal",
            "subcategory":"Beauty Salon",
            "type":"Services"
        }
    ],
    "sg:phone":"+1 570 784 0105",
    "sg:postcode":"17815",
    "sg:province":"PA",
    "wof:name":"Shear Creations By Nicole",
    "wof:placetype":"venue"
},
  "geometry": {"coordinates":[-76.435661,41.001862],"type":"Point"}
}