{
  "type": "Feature",
  "properties": {
    "iso:country":"US",
    "sg:address":"2837 Herr St",
    "sg:city":"Harrisburg",
    "sg:classifiers":[
        {
            "category":"Wholesale",
            "subcategory":"Electrical",
            "type":"Manufacturing & Wholesale Goods"
        }
    ],
    "sg:phone":"+1 717 234 6513",
    "sg:postcode":"17103",
    "sg:province":"PA",
    "sg:tags":[
        "alarm",
        "burglar",
        "system"
    ],
    "wof:name":"Harrisburg Alarms",
    "wof:placetype":"venue"
},
  "geometry": {"coordinates":[-76.84631,40.281899],"type":"Point"}
}