{
  "type": "Feature",
  "properties": {
    "iso:country":"US",
    "sg:address":"458 Bushkill Center Rd",
    "sg:city":"Nazareth",
    "sg:classifiers":[
        {
            "category":"Food & Beverages",
            "subcategory":"Groceries & Convenience Stores",
            "type":"Retail Goods"
        }
    ],
    "sg:phone":"+1   ",
    "sg:postcode":"18064",
    "sg:province":"PA",
    "wof:name":"Hill Top Deli & Market",
    "wof:placetype":"venue"
},
  "geometry": {"coordinates":[-75.309482,40.759334],"type":"Point"}
}