{
  "type": "Feature",
  "properties": {
    "addr:full":"4024 Higbee St Philadelphia PA 19135",
    "addr:postcode":"4024;19135",
    "addr:street":"Higbee St",
    "iso:country":"US",
    "sg:address":"4024 Higbee St",
    "sg:city":"Philadelphia",
    "sg:classifiers":[
        {
            "category":"Real Estate",
            "subcategory":"Real Estate Services",
            "type":"Services"
        },
        {
            "category":"Social Services",
            "subcategory":"Retirement Home",
            "type":"Services"
        }
    ],
    "sg:phone":"+1 267 241 7228",
    "sg:postcode":"19135",
    "sg:province":"PA",
    "sg:tags":[
        "boarding",
        "house",
        "rooming"
    ],
    "wof:name":"All Most Home",
    "wof:placetype":"venue"
},
  "geometry": {"coordinates":[-75.06496,40.025977],"type":"Point"}
}