{
  "type": "Feature",
  "properties": {
    "addr:full":"415 6th St Braddock PA 15104",
    "addr:housenumber":"415",
    "addr:postcode":"15104",
    "addr:street":"6Th St",
    "iso:country":"US",
    "sg:address":"415 6th St",
    "sg:city":"Braddock",
    "sg:classifiers":[
        {
            "category":"Arena",
            "subcategory":"Sports Club",
            "type":"Entertainment"
        }
    ],
    "sg:phone":"+1   ",
    "sg:postcode":"15104",
    "sg:province":"PA",
    "wof:name":"Turtle Creek Vly Cncl Govts",
    "wof:placetype":"venue"
},
  "geometry": {"coordinates":[-79.868588,40.403283],"type":"Point"}
}