{
  "type": "Feature",
  "properties": {
    "iso:country":"US",
    "sg:address":"237 Johns St",
    "sg:city":"Johnstown",
    "sg:classifiers":[
        {
            "category":"Building & Trades",
            "subcategory":"Construction",
            "type":"Services"
        }
    ],
    "sg:phone":"+1 814 534 4445",
    "sg:postcode":"15901",
    "sg:province":"PA",
    "sg:tags":[
        "carpenter"
    ],
    "wof:name":"Carpenter Financial Svc",
    "wof:placetype":"venue"
},
  "geometry": {"coordinates":[-78.92497,40.326795],"type":"Point"}
}