{
  "type": "Feature",
  "properties": {
    "iso:country":"US",
    "sg:address":"63 Main St",
    "sg:city":"York",
    "sg:classifiers":[
        {
            "category":"Freight",
            "type":"Transportation"
        }
    ],
    "sg:phone":"+1   ",
    "sg:postcode":"17406",
    "sg:province":"PA",
    "sg:tags":[
        "operator",
        "local",
        "trucking"
    ],
    "wof:name":"Hildebrands Trucking",
    "wof:placetype":"venue"
},
  "geometry": {"coordinates":[-76.579465,39.980491],"type":"Point"}
}