{
  "type": "Feature",
  "properties": {
    "iso:country":"US",
    "sg:address":"1112 Galveston Ave",
    "sg:city":"Pittsburgh",
    "sg:classifiers":[
        {
            "category":"Food & Beverages",
            "subcategory":"Groceries & Convenience Stores",
            "type":"Retail Goods"
        }
    ],
    "sg:phone":"+1 412 231 2101",
    "sg:postcode":"15233",
    "sg:province":"PA",
    "sg:tags":[
        "product"
    ],
    "wof:name":"Chips Value Added Foods",
    "wof:placetype":"venue"
},
  "geometry": {"coordinates":[-80.016899,40.453701],"type":"Point"}
}