{
  "type": "Feature",
  "properties": {
    "iso:country":"US",
    "sg:address":"447 3rd St",
    "sg:city":"Beaver",
    "sg:classifiers":[
        {
            "category":"Shopping",
            "type":"Retail Goods"
        }
    ],
    "sg:phone":"+1   ",
    "sg:postcode":"15009",
    "sg:province":"PA",
    "sg:tags":[
        "art",
        "framing"
    ],
    "wof:name":"Highland Laurel Gallery",
    "wof:placetype":"venue"
},
  "geometry": {"coordinates":[-80.302488,40.696128],"type":"Point"}
}