{
  "type": "Feature",
  "properties": {
    "iso:country":"US",
    "sg:address":"432 E Main St",
    "sg:city":"Youngsville",
    "sg:classifiers":[
        {
            "category":"Health Services",
            "subcategory":"Nursing And Care Facility",
            "type":"Services"
        }
    ],
    "sg:phone":"+1   ",
    "sg:postcode":"16371",
    "sg:province":"PA",
    "sg:tags":[
        "intermediate"
    ],
    "wof:name":"Tracy Jos Personal Care Home",
    "wof:placetype":"venue"
},
  "geometry": {"coordinates":[-79.310484,41.849911],"type":"Point"}
}