{
  "type": "Feature",
  "properties": {
    "iso:country":"US",
    "sg:address":"255 W Lancaster Ave",
    "sg:city":"Paoli",
    "sg:classifiers":[
        {
            "category":"Health Services",
            "subcategory":"Hospital",
            "type":"Services"
        },
        {
            "category":"Banks & Credit Unions",
            "subcategory":"Bank",
            "type":"Services"
        }
    ],
    "sg:phone":"+1 610 648 1000",
    "sg:postcode":"19301",
    "sg:province":"PA",
    "sg:website":"www.mainlinehealth.org",
    "wof:name":"Paoli Memorial Hospital",
    "wof:placetype":"venue"
},
  "geometry": {"coordinates":[-75.49927099999999,40.042004],"type":"Point"}
}