{
  "type": "Feature",
  "properties": {
    "iso:country":"US",
    "sg:address":"77 Creek Rd",
    "sg:city":"Volant",
    "sg:classifiers":[
        {
            "category":"Manufacturing",
            "subcategory":"Signs",
            "type":"Manufacturing & Wholesale Goods"
        }
    ],
    "sg:phone":"+1   ",
    "sg:postcode":"16156",
    "sg:province":"PA",
    "sg:tags":[
        "advertising",
        "specialty"
    ],
    "wof:name":"Anderson Sign & Design",
    "wof:placetype":"venue"
},
  "geometry": {"coordinates":[-80.257293,41.11826],"type":"Point"}
}