{
  "type": "Feature",
  "properties": {
    "addr:full":"5834 Overbrook Ave Philadelphia PA 19131",
    "addr:housenumber":"5834",
    "addr:postcode":"19131",
    "addr:street":"Overbrook Ave",
    "iso:country":"US",
    "sg:address":"5834 Overbrook Ave",
    "sg:city":"Philadelphia",
    "sg:classifiers":[
        {
            "category":"Organizations",
            "subcategory":"Religious Organization",
            "type":"Services"
        }
    ],
    "sg:phone":"+1 215 477 3020",
    "sg:postcode":"19131",
    "sg:province":"PA",
    "sg:tags":[
        "church"
    ],
    "wof:name":"Overbrook Avenue Gospel Hall",
    "wof:placetype":"venue"
},
  "geometry": {"coordinates":[-75.24333799999999,39.99051],"type":"Point"}
}