{
  "type": "Feature",
  "properties": {
    "iso:country":"US",
    "sg:address":"303 Pittsburgh Rd",
    "sg:city":"Butler",
    "sg:classifiers":[
        {
            "category":"Real Estate",
            "subcategory":"Real Estate Agent",
            "type":"Services"
        }
    ],
    "sg:phone":"+1 724 282 7680",
    "sg:postcode":"16002",
    "sg:province":"PA",
    "wof:name":"Northwood Realty Co/Better Hms",
    "wof:placetype":"venue"
},
  "geometry": {"coordinates":[-79.92758499999999,40.807865],"type":"Point"}
}