{
  "type": "Feature",
  "properties": {
    "addr:full":"37 Covered Bridge Rd Pine Grove PA 17963",
    "addr:housenumber":"37",
    "addr:postcode":"17963",
    "addr:street":"Covered Bridge Rd",
    "iso:country":"US",
    "sg:address":"37 Covered Bridge Rd",
    "sg:city":"Pine Grove",
    "sg:classifiers":[
        {
            "category":"Personal",
            "subcategory":"Beauty Salon",
            "type":"Services"
        }
    ],
    "sg:phone":"+1 570 345 4690",
    "sg:postcode":"17963",
    "sg:province":"PA",
    "wof:name":"Harvey W Sutton Family Hair Cr",
    "wof:placetype":"venue"
},
  "geometry": {"coordinates":[-76.325103,40.542933],"type":"Point"}
}