{
  "type": "Feature",
  "properties": {
    "iso:country":"US",
    "sg:address":"2501 W Sterner St",
    "sg:city":"Philadelphia",
    "sg:classifiers":[
        {
            "category":"Restaurant",
            "type":"Food & Drink"
        }
    ],
    "sg:phone":"+1   ",
    "sg:postcode":"19132",
    "sg:province":"PA",
    "sg:tags":[
        "eating"
    ],
    "wof:name":"2501 Sterner Inc",
    "wof:placetype":"venue"
},
  "geometry": {"coordinates":[-75.173846,39.996911],"type":"Point"}
}