{
  "type": "Feature",
  "properties": {
    "addr:full":"1501 N Broad St Philadelphia PA 19122",
    "addr:housenumber":"1501",
    "addr:postcode":"19122",
    "addr:street":"N Broad St",
    "iso:country":"US",
    "sg:address":"1501 N Broad St",
    "sg:city":"Philadelphia",
    "sg:classifiers":[
        {
            "category":"Shopping",
            "subcategory":"Clothing, Apparel, & Fashions",
            "type":"Retail Goods"
        }
    ],
    "sg:phone":"+1 215 235 9889",
    "sg:postcode":"19122",
    "sg:province":"PA",
    "sg:tags":[
        "apparel",
        "women's"
    ],
    "wof:name":"Avenue",
    "wof:placetype":"venue"
},
  "geometry": {"coordinates":[-75.158478,39.97583],"type":"Point"}
}