{
  "type": "Feature",
  "properties": {
    "addr:full":"3 W Woods Dr Lititz PA 17543",
    "addr:housenumber":"3",
    "addr:postcode":"17543",
    "addr:street":"W Woods Dr",
    "iso:country":"US",
    "sg:address":"3 W Woods Dr",
    "sg:city":"Lititz",
    "sg:classifiers":[
        {
            "category":"Autos & Motor Vehicles",
            "subcategory":"Automobile Sales",
            "type":"Retail Goods"
        }
    ],
    "sg:phone":"+1 717 627 0800",
    "sg:postcode":"17543",
    "sg:province":"PA",
    "sg:tags":[
        "used"
    ],
    "wof:name":"West Wood Motors",
    "wof:placetype":"venue"
},
  "geometry": {"coordinates":[-76.303996,40.135488],"type":"Point"}
}