{
  "type": "Feature",
  "properties": {
    "iso:country":"US",
    "sg:address":"1900 Northway Rd",
    "sg:city":"Williamsport",
    "sg:classifiers":[
        {
            "category":"Retail",
            "subcategory":"Veterinary Services",
            "type":"Services"
        }
    ],
    "sg:phone":"+1   ",
    "sg:postcode":"17701",
    "sg:province":"PA",
    "wof:name":"Knoebel Thomas H Vmd",
    "wof:placetype":"venue"
},
  "geometry": {"coordinates":[-76.96988399999999,41.259627],"type":"Point"}
}