{
  "type": "Feature",
  "properties": {
    "iso:country":"US",
    "sg:address":"116 The Mall at Steamtown",
    "sg:city":"Scranton",
    "sg:classifiers":[
        {
            "category":"Shopping",
            "subcategory":"Shoes",
            "type":"Retail Goods"
        }
    ],
    "sg:phone":"+1 570 941 9277",
    "sg:postcode":"18503",
    "sg:province":"PA",
    "wof:name":"Payless Shoe Source",
    "wof:placetype":"venue"
},
  "geometry": {"coordinates":[-75.668527,41.407474],"type":"Point"}
}