{
  "type": "Feature",
  "properties": {
    "addr:full":"526 Settlers Ridge Rd Osterburg PA 16667",
    "addr:housenumber":"526",
    "addr:postcode":"16667",
    "addr:street":"Settlers Ridge Rd",
    "iso:country":"US",
    "sg:address":"526 Settlers Ridge Rd",
    "sg:city":"Osterburg",
    "sg:classifiers":[
        {
            "category":"Building & Trades",
            "subcategory":"Construction",
            "type":"Services"
        }
    ],
    "sg:phone":"+1   ",
    "sg:postcode":"16667",
    "sg:province":"PA",
    "sg:tags":[
        "house"
    ],
    "wof:name":"Sp Builders",
    "wof:placetype":"venue"
},
  "geometry": {"coordinates":[-78.50602000000001,40.19858],"type":"Point"}
}