{
  "type": "Feature",
  "properties": {
    "addr:full":"1800 Park Manor Blvd Pittsburgh PA 15205",
    "addr:housenumber":"1800",
    "addr:postcode":"15205",
    "addr:street":"Park Manor Blvd",
    "iso:country":"US",
    "sg:address":"1800 Park Manor Blvd",
    "sg:city":"Pittsburgh",
    "sg:classifiers":[
        {
            "category":"Manufacturing",
            "subcategory":"Apparel",
            "type":"Manufacturing & Wholesale Goods"
        }
    ],
    "sg:phone":"+1 412 788 8490",
    "sg:postcode":"15205",
    "sg:province":"PA",
    "sg:tags":[
        "sewing",
        "contractor"
    ],
    "wof:name":"Gloria Horn Sewing Studios",
    "wof:placetype":"venue"
},
  "geometry": {"coordinates":[-80.163268,40.455922],"type":"Point"}
}