{
  "type": "Feature",
  "properties": {
    "iso:country":"US",
    "sg:address":"2110 Mclean St",
    "sg:city":"Aliquippa",
    "sg:classifiers":[
        {
            "category":"Health Services",
            "subcategory":"Dentist",
            "type":"Services"
        }
    ],
    "sg:phone":"+1 724 375 5088",
    "sg:postcode":"15001",
    "sg:province":"PA",
    "wof:name":"Charles F Zammerilla Dds",
    "wof:placetype":"venue"
},
  "geometry": {"coordinates":[-80.276883,40.603317],"type":"Point"}
}