{
  "type": "Feature",
  "properties": {
    "iso:country":"US",
    "sg:address":"450 James St",
    "sg:city":"King Of Prussia",
    "sg:classifiers":[
        {
            "category":"Building & Trades",
            "subcategory":"Electrical",
            "type":"Services"
        }
    ],
    "sg:phone":"+1 610 337 0456",
    "sg:postcode":"19406",
    "sg:province":"PA",
    "sg:tags":[
        "equipment",
        "protection",
        "lightning"
    ],
    "wof:name":"Zeus Lightning Rods",
    "wof:placetype":"venue"
},
  "geometry": {"coordinates":[-75.385626,40.098298],"type":"Point"}
}