{
  "type": "Feature",
  "properties": {
    "addr:full":"824 E Walnut St Allentown PA 18109",
    "addr:housenumber":"824",
    "addr:postcode":"18109",
    "addr:street":"E Walnut St",
    "iso:country":"US",
    "sg:address":"824 E Walnut St",
    "sg:city":"Allentown",
    "sg:classifiers":[
        {
            "category":"Organizations",
            "subcategory":"Non-profit Organization",
            "type":"Services"
        }
    ],
    "sg:phone":"+1   ",
    "sg:postcode":"18109",
    "sg:province":"PA",
    "sg:tags":[
        "executive",
        "social"
    ],
    "wof:name":"Lehigh County Advocate Program",
    "wof:placetype":"venue"
},
  "geometry": {"coordinates":[-75.441164,40.611059],"type":"Point"}
}