{
  "type": "Feature",
  "properties": {
    "addr:full":"230 Danielle Ct York PA 17404",
    "addr:housenumber":"230",
    "addr:postcode":"17404",
    "addr:street":"Danielle Ct",
    "iso:country":"US",
    "sg:address":"230 Danielle Ct",
    "sg:city":"York",
    "sg:classifiers":[
        {
            "category":"Insurance",
            "subcategory":"Life Insurance",
            "type":"Services"
        }
    ],
    "sg:phone":"+1   ",
    "sg:postcode":"17404",
    "sg:province":"PA",
    "sg:tags":[
        "carrier"
    ],
    "wof:name":"AFLAC",
    "wof:placetype":"venue"
},
  "geometry": {"coordinates":[-76.756995,40.000253],"type":"Point"}
}