{
  "type": "Feature",
  "properties": {
    "iso:country":"US",
    "sg:address":"1260 Martin Ave",
    "sg:city":"New Kensington",
    "sg:classifiers":[
        {
            "category":"Health Services",
            "subcategory":"Doctor",
            "type":"Services"
        }
    ],
    "sg:phone":"+1   ",
    "sg:postcode":"15068",
    "sg:province":"PA",
    "sg:tags":[
        "clinic",
        "medical"
    ],
    "wof:name":"Song Young Jo MD",
    "wof:placetype":"venue"
},
  "geometry": {"coordinates":[-79.74734599999999,40.565322],"type":"Point"}
}