{
  "type": "Feature",
  "properties": {
    "iso:country":"US",
    "sg:address":"2428 Elizabeth Ave",
    "sg:city":"Temple",
    "sg:classifiers":[
        {
            "category":"Building & Trades",
            "subcategory":"Construction",
            "type":"Services"
        }
    ],
    "sg:phone":"+1 610 921 2317",
    "sg:postcode":"19560",
    "sg:province":"PA",
    "sg:tags":[
        "general",
        "contractor"
    ],
    "wof:name":"Paul Soja Pro Remodeling Inc",
    "wof:placetype":"venue"
},
  "geometry": {"coordinates":[-75.893174,40.389748],"type":"Point"}
}