{
  "type": "Feature",
  "properties": {
    "addr:full":"2125 Cumberland St Lebanon PA 17042",
    "addr:housenumber":"2125",
    "addr:postcode":"17042",
    "addr:street":"Cumberland St",
    "iso:country":"US",
    "sg:address":"2125 Cumberland St",
    "sg:city":"Lebanon",
    "sg:classifiers":[
        {
            "category":"Restaurant",
            "type":"Food & Drink"
        }
    ],
    "sg:phone":"+1 717 270 1233",
    "sg:postcode":"17042",
    "sg:province":"PA",
    "sg:tags":[
        "seafood"
    ],
    "wof:name":"A1 Steak Seafood",
    "wof:placetype":"venue"
},
  "geometry": {"coordinates":[-76.448992,40.338915],"type":"Point"}
}