{
  "type": "Feature",
  "properties": {
    "iso:country":"US",
    "sg:address":"611 Seville St",
    "sg:city":"Philadelphia",
    "sg:classifiers":[
        {
            "category":"Professional",
            "subcategory":"Lawyer & Legal Services",
            "type":"Services"
        }
    ],
    "sg:phone":"+1 215 482 1213",
    "sg:postcode":"19128",
    "sg:province":"PA",
    "wof:name":"Bak Joseph Atty",
    "wof:placetype":"venue"
},
  "geometry": {"coordinates":[-75.20459700000001,40.026402],"type":"Point"}
}