{
  "type": "Feature",
  "properties": {
    "addr:full":"2104 Bath Rd Bristol PA 19007",
    "addr:housenumber":"2104",
    "addr:postcode":"19007",
    "addr:street":"Bath Rd",
    "iso:country":"US",
    "sg:address":"2104 Bath Rd",
    "sg:city":"Bristol",
    "sg:classifiers":[
        {
            "category":"Banks & Credit Unions",
            "subcategory":"Bank",
            "type":"Services"
        },
        {
            "category":"Banks & Credit Unions",
            "subcategory":"Financial Services",
            "type":"Services"
        },
        {
            "category":"Manufacturing",
            "subcategory":"Paper Products",
            "type":"Manufacturing & Wholesale Goods"
        }
    ],
    "sg:phone":"+1 215 788 5270",
    "sg:postcode":"19007",
    "sg:province":"PA",
    "sg:tags":[
        "consultant",
        "financing",
        "planning",
        "commercial"
    ],
    "sg:website":"bucksfirstfcu.org",
    "wof:name":"Bucks First Federal Credit Union",
    "wof:placetype":"venue"
},
  "geometry": {"coordinates":[-74.865402,40.120201],"type":"Point"}
}