{
  "type": "Feature",
  "properties": {
    "iso:country":"US",
    "sg:address":"150 Stone Rd",
    "sg:city":"Womelsdorf",
    "sg:classifiers":[
        {
            "category":"Building & Trades",
            "subcategory":"Construction",
            "type":"Services"
        }
    ],
    "sg:phone":"+1 610 589 4785",
    "sg:postcode":"19567",
    "sg:province":"PA",
    "sg:tags":[
        "contractor"
    ],
    "wof:name":"Wessner Contracting",
    "wof:placetype":"venue"
},
  "geometry": {"coordinates":[-76.199344,40.413952],"type":"Point"}
}