{
  "type": "Feature",
  "properties": {
    "iso:country":"US",
    "sg:address":"101 Glenbrook Dr",
    "sg:city":"Cranberry Township",
    "sg:classifiers":[
        {
            "category":"Real Estate",
            "subcategory":"Real Estate Agent",
            "type":"Services"
        }
    ],
    "sg:phone":"+1   ",
    "sg:postcode":"16066",
    "sg:province":"PA",
    "wof:name":"Hanna Howard Real Estate Svcs",
    "wof:placetype":"venue"
},
  "geometry": {"coordinates":[-80.12248,40.725975],"type":"Point"}
}