{
  "type": "Feature",
  "properties": {
    "iso:country":"US",
    "sg:address":"517 W Gordon St",
    "sg:city":"Allentown",
    "sg:classifiers":[
        {
            "category":"Arena",
            "subcategory":"Sports Club",
            "type":"Entertainment"
        }
    ],
    "sg:phone":"+1 610 437 0254",
    "sg:postcode":"18102",
    "sg:province":"PA",
    "sg:tags":[
        "martial art"
    ],
    "wof:name":"Yong Kim",
    "wof:placetype":"venue"
},
  "geometry": {"coordinates":[-75.471216,40.608858],"type":"Point"}
}