{
  "type": "Feature",
  "properties": {
    "iso:country":"US",
    "sg:address":"2636 Emmitsburg Rd",
    "sg:city":"Gettysburg",
    "sg:classifiers":[
        {
            "category":"Real Estate",
            "subcategory":"Real Estate Operator",
            "type":"Services"
        }
    ],
    "sg:phone":"+1   ",
    "sg:postcode":"17325",
    "sg:province":"PA",
    "sg:tags":[
        "building",
        "apartment",
        "n"
    ],
    "wof:name":"Devonshire Village",
    "wof:placetype":"venue"
},
  "geometry": {"coordinates":[-77.27267399999999,39.765168],"type":"Point"}
}