{
  "type": "Feature",
  "properties": {
    "addr:full":"1309 Bridge St New Cumberland PA 17070",
    "addr:housenumber":"1309",
    "addr:postcode":"17070",
    "addr:street":"Bridge St",
    "iso:country":"US",
    "sg:address":"1309 Bridge St",
    "sg:city":"New Cumberland",
    "sg:classifiers":[
        {
            "category":"Banks & Credit Unions",
            "subcategory":"Investment Brokerage",
            "type":"Services"
        }
    ],
    "sg:phone":"+1 717 901 2940",
    "sg:postcode":"17070",
    "sg:province":"PA",
    "sg:tags":[
        "security",
        "broker",
        "mortgage"
    ],
    "wof:name":"Safe Harbor Mortgage Inc",
    "wof:placetype":"venue"
},
  "geometry": {"coordinates":[-76.875227,40.234087],"type":"Point"}
}