{
  "type": "Feature",
  "properties": {
    "iso:country":"US",
    "sg:address":"1380 W Chestnut St",
    "sg:city":"Washington",
    "sg:classifiers":[
        {
            "category":"Restaurant",
            "type":"Food & Drink"
        }
    ],
    "sg:menulink":"http://www.allmenus.com/pa/canton/41895-bob-evans/menu/",
    "sg:phone":"+1 724 229 3347",
    "sg:postcode":"15301",
    "sg:province":"PA",
    "sg:tags":[
        "american"
    ],
    "wof:name":"Bob Evans",
    "wof:placetype":"venue"
},
  "geometry": {"coordinates":[-80.27307,40.164918],"type":"Point"}
}