{
  "type": "Feature",
  "properties": {
    "iso:country":"US",
    "sg:address":"145 Mall Blvd",
    "sg:city":"Monroeville",
    "sg:classifiers":[
        {
            "category":"Professional",
            "type":"Services"
        }
    ],
    "sg:phone":"+1 412 349 0024",
    "sg:postcode":"15146",
    "sg:province":"PA",
    "sg:tags":[
        "establishment"
    ],
    "wof:name":"Kitchen Shelf",
    "wof:placetype":"venue"
},
  "geometry": {"coordinates":[-79.79238599999999,40.430887],"type":"Point"}
}