{
  "type": "Feature",
  "properties": {
    "iso:country":"US",
    "sg:address":"2529 W State St",
    "sg:city":"New Castle",
    "sg:classifiers":[
        {
            "category":"Personal",
            "subcategory":"Beauty Salon",
            "type":"Services"
        }
    ],
    "sg:phone":"+1 724 654 3457",
    "sg:postcode":"16101",
    "sg:province":"PA",
    "sg:tags":[
        "shop"
    ],
    "wof:name":"Famous Hair 76",
    "wof:placetype":"venue"
},
  "geometry": {"coordinates":[-80.390281,41.010391],"type":"Point"}
}