{
  "type": "Feature",
  "properties": {
    "iso:country":"US",
    "sg:address":"46 S 4th St",
    "sg:city":"Hamburg",
    "sg:classifiers":[
        {
            "category":"Shopping",
            "subcategory":"Shoes",
            "type":"Retail Goods"
        }
    ],
    "sg:phone":"+1 610 562 3239",
    "sg:postcode":"19526",
    "sg:province":"PA",
    "wof:name":"Ely's Shoe Store",
    "wof:placetype":"venue"
},
  "geometry": {"coordinates":[-75.982225,40.554412],"type":"Point"}
}