{
  "type": "Feature",
  "properties": {
    "iso:country":"US",
    "sg:address":"57 W Katherine Ave",
    "sg:city":"Washington",
    "sg:classifiers":[
        {
            "category":"Wholesale",
            "subcategory":"Stationery",
            "type":"Manufacturing & Wholesale Goods"
        }
    ],
    "sg:phone":"+1   ",
    "sg:postcode":"15301",
    "sg:province":"PA",
    "sg:tags":[
        "supply"
    ],
    "wof:name":"West Mountain Forms",
    "wof:placetype":"venue"
},
  "geometry": {"coordinates":[-80.24972699999999,40.178314],"type":"Point"}
}