{
  "type": "Feature",
  "properties": {
    "iso:country":"US",
    "sg:address":"6310 Market St",
    "sg:city":"Upper Darby",
    "sg:classifiers":[
        {
            "category":"Social Services",
            "type":"Services"
        }
    ],
    "sg:phone":"+1 610 734 5770",
    "sg:postcode":"19082",
    "sg:province":"PA",
    "sg:tags":[
        "organization",
        "welfare"
    ],
    "wof:name":"Life Center-Eastern Delaware",
    "wof:placetype":"venue"
},
  "geometry": {"coordinates":[-75.24813399999999,39.962764],"type":"Point"}
}