{
  "type": "Feature",
  "properties": {
    "iso:country":"US",
    "sg:address":"602 Willow St",
    "sg:city":"Lebanon",
    "sg:classifiers":[
        {
            "category":"Organizations",
            "subcategory":"Religious Organization",
            "type":"Services"
        }
    ],
    "sg:phone":"+1 717 279 0598",
    "sg:postcode":"17046",
    "sg:province":"PA",
    "wof:name":"Missionaries Mormon",
    "wof:placetype":"venue"
},
  "geometry": {"coordinates":[-76.421295,40.340792],"type":"Point"}
}