{
  "type": "Feature",
  "properties": {
    "addr:full":"341 S 4th St Philadelphia PA 19106",
    "addr:housenumber":"341",
    "addr:postcode":"19106",
    "addr:street":"S 4Th St",
    "iso:country":"US",
    "sg:address":"341 S 4th St",
    "sg:city":"Philadelphia",
    "sg:classifiers":[
        {
            "category":"Professional",
            "type":"Services"
        }
    ],
    "sg:phone":"+1   ",
    "sg:postcode":"19106",
    "sg:province":"PA",
    "wof:name":"O AP Co",
    "wof:placetype":"venue"
},
  "geometry": {"coordinates":[-75.148764,39.943523],"type":"Point"}
}