{
  "type": "Feature",
  "properties": {
    "addr:full":"21 S 12th St Philadelphia PA 19107",
    "addr:housenumber":"21",
    "addr:postcode":"19107",
    "addr:street":"S 12Th St",
    "iso:country":"US",
    "sg:address":"21 S 12th St",
    "sg:city":"Philadelphia",
    "sg:classifiers":[
        {
            "category":"Professional",
            "subcategory":"Lawyer & Legal Services",
            "type":"Services"
        }
    ],
    "sg:phone":"+1 215 496 9464",
    "sg:postcode":"19107",
    "sg:province":"PA",
    "sg:tags":[
        "divorce",
        "law",
        "family"
    ],
    "wof:name":"Law Offices of Yancey Jordan & Assoc",
    "wof:placetype":"venue"
},
  "geometry": {"coordinates":[-75.159897,39.951599],"type":"Point"}
}