{
  "type": "Feature",
  "properties": {
    "addr:full":"261 S Walnut St Blairsville PA 15717",
    "addr:housenumber":"261",
    "addr:postcode":"15717",
    "addr:street":"S Walnut St",
    "iso:country":"US",
    "sg:address":"261 S Walnut St",
    "sg:city":"Blairsville",
    "sg:classifiers":[
        {
            "category":"Organizations",
            "subcategory":"Religious Organization",
            "type":"Services"
        }
    ],
    "sg:phone":"+1 724 459 9068",
    "sg:postcode":"15717",
    "sg:province":"PA",
    "sg:tags":[
        "clergy"
    ],
    "wof:name":"Kitner Charles S Rev",
    "wof:placetype":"venue"
},
  "geometry": {"coordinates":[-79.193775,40.471088],"type":"Point"}
}