{
  "type": "Feature",
  "properties": {
    "iso:country":"US",
    "sg:address":"340 Mercer St",
    "sg:city":"Butler",
    "sg:classifiers":[
        {
            "category":"Retail",
            "subcategory":"Laundry & Dry Cleaning",
            "type":"Services"
        }
    ],
    "sg:phone":"+1   ",
    "sg:postcode":"16001",
    "sg:province":"PA",
    "sg:tags":[
        "drycleaning",
        "plant"
    ],
    "wof:name":"Bartolis Cleaners Inc",
    "wof:placetype":"venue"
},
  "geometry": {"coordinates":[-79.90812699999999,40.866267],"type":"Point"}
}