{
  "type": "Feature",
  "properties": {
    "addr:full":"10 S Plum St Media PA 19063",
    "addr:housenumber":"10",
    "addr:postcode":"19063",
    "addr:street":"S Plum St",
    "iso:country":"US",
    "sg:address":"10 S Plum St",
    "sg:city":"Media",
    "sg:classifiers":[
        {
            "category":"Health Services",
            "subcategory":"Health Practitioner",
            "type":"Services"
        }
    ],
    "sg:phone":"+1   ",
    "sg:postcode":"19063",
    "sg:province":"PA",
    "wof:name":"Ericka Surkin",
    "wof:placetype":"venue"
},
  "geometry": {"coordinates":[-75.390191,39.918798],"type":"Point"}
}