{
  "type": "Feature",
  "properties": {
    "iso:country":"US",
    "sg:address":"200 Scott Ave",
    "sg:city":"Coraopolis",
    "sg:classifiers":[
        {
            "category":"Retail",
            "subcategory":"Portrait Studio",
            "type":"Services"
        }
    ],
    "sg:phone":"+1 412 859 0234",
    "sg:postcode":"15116",
    "sg:province":"PA",
    "sg:tags":[
        "photographer"
    ],
    "wof:name":"Olan Mills Portrait Studio",
    "wof:placetype":"venue"
},
  "geometry": {"coordinates":[-79.97493299999999,40.539108],"type":"Point"}
}