{
  "type": "Feature",
  "properties": {
    "addr:full":"402 E Ridley Ave Ridley Park PA 19078",
    "addr:housenumber":"402",
    "addr:postcode":"19078",
    "addr:street":"E Ridley Ave;Park",
    "iso:country":"US",
    "sg:address":"402 E Ridley Ave",
    "sg:city":"Ridley Park",
    "sg:classifiers":[
        {
            "category":"Professional",
            "type":"Services"
        }
    ],
    "sg:phone":"+1   ",
    "sg:postcode":"19078",
    "sg:province":"PA",
    "wof:name":"Laurie Arnold",
    "wof:placetype":"venue"
},
  "geometry": {"coordinates":[-75.319969,39.882407],"type":"Point"}
}