{
  "type": "Feature",
  "properties": {
    "addr:full":"3804 Elmwood Ave Erie PA 16509",
    "addr:housenumber":"3804",
    "addr:postcode":"16509",
    "addr:street":"Elmwood Ave",
    "iso:country":"US",
    "sg:address":"3804 Elmwood Ave",
    "sg:city":"Erie",
    "sg:classifiers":[
        {
            "category":"Bars & Pubs",
            "type":"Food & Drink"
        }
    ],
    "sg:phone":"+1 814 868 0395",
    "sg:postcode":"16509",
    "sg:province":"PA",
    "wof:name":"Coach's Sports Bar & Grill",
    "wof:placetype":"venue"
},
  "geometry": {"coordinates":[-80.09249199999999,42.091661],"type":"Point"}
}