{
  "type": "Feature",
  "properties": {
    "iso:country":"US",
    "sg:address":"936 Logan Valley Mall",
    "sg:city":"Altoona",
    "sg:classifiers":[
        {
            "category":"Shopping",
            "subcategory":"Books",
            "type":"Retail Goods"
        }
    ],
    "sg:phone":"+1 814 946 9167",
    "sg:postcode":"16602",
    "sg:province":"PA",
    "sg:tags":[
        "news"
    ],
    "wof:name":"Waldenbooks",
    "wof:placetype":"venue"
},
  "geometry": {"coordinates":[-78.406741,40.472153],"type":"Point"}
}