{
  "type": "Feature",
  "properties": {
    "iso:country":"US",
    "sg:address":"2047 Church View Rd",
    "sg:city":"Coopersburg",
    "sg:classifiers":[
        {
            "category":"Professional",
            "subcategory":"Employment Agencies",
            "type":"Services"
        }
    ],
    "sg:phone":"+1 610 966 3300",
    "sg:postcode":"18036",
    "sg:province":"PA",
    "sg:tags":[
        "consultant",
        "search",
        "executive"
    ],
    "wof:name":"Sanford Rose Assoc",
    "wof:placetype":"venue"
},
  "geometry": {"coordinates":[-75.44949800000001,40.497814],"type":"Point"}
}