{
  "type": "Feature",
  "properties": {
    "iso:country":"US",
    "sg:address":"1904 Nicole Dr",
    "sg:city":"Dresher",
    "sg:classifiers":[
        {
            "category":"Wholesale",
            "subcategory":"Electrical",
            "type":"Manufacturing & Wholesale Goods"
        }
    ],
    "sg:phone":"+1   ",
    "sg:postcode":"19025",
    "sg:province":"PA",
    "sg:tags":[
        "electronic"
    ],
    "wof:name":"Todays Technologies LLC",
    "wof:placetype":"venue"
},
  "geometry": {"coordinates":[-75.152693,40.154512],"type":"Point"}
}