{
  "type": "Feature",
  "properties": {
    "iso:country":"US",
    "sg:address":"1607 Pine Ridge",
    "sg:city":"Bushkill",
    "sg:classifiers":[
        {
            "category":"Retail",
            "subcategory":"Repair Shop",
            "type":"Services"
        }
    ],
    "sg:phone":"+1 570 588 0969",
    "sg:postcode":"18324",
    "sg:province":"PA",
    "sg:tags":[
        "upholsterer"
    ],
    "wof:name":"Concours D'Elegance Upholstery",
    "wof:placetype":"venue"
},
  "geometry": {"coordinates":[-74.98684,41.128457],"type":"Point"}
}