{
  "type": "Feature",
  "properties": {
    "iso:country":"US",
    "sg:address":"45 Alan Ave",
    "sg:city":"Greenville",
    "sg:classifiers":[
        {
            "category":"Organizations",
            "subcategory":"Membership Organization",
            "type":"Services"
        }
    ],
    "sg:phone":"+1   ",
    "sg:postcode":"16125",
    "sg:province":"PA",
    "wof:name":"Galsa",
    "wof:placetype":"venue"
},
  "geometry": {"coordinates":[-80.38805499999999,41.410738],"type":"Point"}
}