{
  "type": "Feature",
  "properties": {
    "addr:full":"1110 Towncrest Rd Williamsport PA 17701",
    "addr:housenumber":"1110",
    "addr:postcode":"17701",
    "addr:street":"Towncrest Rd",
    "iso:country":"US",
    "sg:address":"1110 Towncrest Rd",
    "sg:city":"Williamsport",
    "sg:classifiers":[
        {
            "category":"Professional",
            "subcategory":"Art Services",
            "type":"Services"
        }
    ],
    "sg:phone":"+1 570 326 1165",
    "sg:postcode":"17701",
    "sg:province":"PA",
    "sg:tags":[
        "graphic",
        "commercial",
        "designer",
        "artist"
    ],
    "wof:name":"Sarah Brady Desktop Publishing",
    "wof:placetype":"venue"
},
  "geometry": {"coordinates":[-77.08425699999999,41.236284],"type":"Point"}
}