{
  "type": "Feature",
  "properties": {
    "iso:country":"US",
    "sg:address":"22 Choctaw Trl",
    "sg:city":"Gouldsboro",
    "sg:classifiers":[
        {
            "category":"Building & Trades",
            "subcategory":"Construction",
            "type":"Services"
        }
    ],
    "sg:phone":"+1 570 676 5596",
    "sg:postcode":"18424",
    "sg:province":"PA",
    "sg:tags":[
        "excavation",
        "contractor"
    ],
    "wof:name":"Wr Reese Jr Landscaping & Excavating",
    "wof:placetype":"venue"
},
  "geometry": {"coordinates":[-75.406801,41.268856],"type":"Point"}
}