{
  "type": "Feature",
  "properties": {
    "iso:country":"US",
    "sg:address":"3508 Greenway St",
    "sg:city":"Easton",
    "sg:classifiers":[
        {
            "category":"Place Of Worship",
            "subcategory":"Church",
            "type":"Public Place"
        },
        {
            "category":"Place Of Worship",
            "type":"Public Place"
        },
        {
            "category":"Organizations",
            "subcategory":"Religious Organization",
            "type":"Services"
        }
    ],
    "sg:phone":"+1 610 758 8018",
    "sg:postcode":"18045",
    "sg:province":"PA",
    "sg:tags":[
        "churches-baptist-general",
        "churches-baptist"
    ],
    "wof:name":"Fellowship Baptist Church",
    "wof:placetype":"venue"
},
  "geometry": {"coordinates":[-75.261313,40.663092],"type":"Point"}
}