{
  "type": "Feature",
  "properties": {
    "iso:country":"US",
    "sg:address":"163 Hallam Rd",
    "sg:city":"Washington",
    "sg:classifiers":[
        {
            "category":"Building & Trades",
            "subcategory":"Plumbing",
            "type":"Services"
        }
    ],
    "sg:phone":"+1 724 229 6000",
    "sg:postcode":"15301",
    "sg:province":"PA",
    "sg:tags":[
        "product",
        "management",
        "energy",
        "system"
    ],
    "wof:name":"Console Energy",
    "wof:placetype":"venue"
},
  "geometry": {"coordinates":[-80.18485099999999,40.138367],"type":"Point"}
}