{
  "type": "Feature",
  "properties": {
    "addr:full":"3111 Babcock Blvd Pittsburgh PA 15237",
    "addr:housenumber":"3111",
    "addr:postcode":"15237",
    "addr:street":"Babcock Blvd",
    "iso:country":"US",
    "sg:address":"3111 Babcock Blvd",
    "sg:city":"Pittsburgh",
    "sg:classifiers":[
        {
            "category":"Health Services",
            "subcategory":"Nursing And Care Facility",
            "type":"Services"
        }
    ],
    "sg:phone":"+1   ",
    "sg:postcode":"15237",
    "sg:province":"PA",
    "sg:tags":[
        "intermediate",
        "legal"
    ],
    "wof:name":"Just Hello",
    "wof:placetype":"venue"
},
  "geometry": {"coordinates":[-80.012101,40.517136],"type":"Point"}
}