{
  "type": "Feature",
  "properties": {
    "iso:country":"US",
    "sg:address":"639 S 52nd St",
    "sg:city":"Philadelphia",
    "sg:classifiers":[
        {
            "category":"Professional",
            "type":"Services"
        }
    ],
    "sg:phone":"+1 215 747 9088",
    "sg:postcode":"19143",
    "sg:province":"PA",
    "sg:tags":[
        "establishment"
    ],
    "wof:name":"Med-Graph",
    "wof:placetype":"venue"
},
  "geometry": {"coordinates":[-75.22708,39.949053],"type":"Point"}
}