{
  "type": "Feature",
  "properties": {
    "iso:country":"US",
    "sg:address":"1126 7th Ave",
    "sg:city":"Beaver Falls",
    "sg:classifiers":[
        {
            "category":"Shopping",
            "subcategory":"Music",
            "type":"Retail Goods"
        }
    ],
    "sg:phone":"+1 724 847 1776",
    "sg:postcode":"15010",
    "sg:province":"PA",
    "sg:tags":[
        "compact",
        "cassette",
        "disc",
        "tape"
    ],
    "wof:name":"Music Express",
    "wof:placetype":"venue"
},
  "geometry": {"coordinates":[-80.319428,40.752709],"type":"Point"}
}