{
  "type": "Feature",
  "properties": {
    "iso:country":"US",
    "sg:address":"4529 Meadow Dr",
    "sg:city":"Nazareth",
    "sg:classifiers":[
        {
            "category":"Wholesale",
            "subcategory":"Non-durable Goods",
            "type":"Manufacturing & Wholesale Goods"
        }
    ],
    "sg:phone":"+1 610 746 9546",
    "sg:postcode":"18064",
    "sg:province":"PA",
    "sg:tags":[
        "merchandise-wholesale"
    ],
    "wof:name":"Trader Miata",
    "wof:placetype":"venue"
},
  "geometry": {"coordinates":[-75.343255,40.703635],"type":"Point"}
}