{
  "type": "Feature",
  "properties": {
    "addr:full":"125 E North St New Castle PA 16101",
    "addr:housenumber":"125",
    "addr:postcode":"16101",
    "addr:street":"E North St",
    "iso:country":"US",
    "sg:address":"125 E North St",
    "sg:city":"New Castle",
    "sg:classifiers":[
        {
            "category":"Professional",
            "subcategory":"Lawyer & Legal Services",
            "type":"Services"
        }
    ],
    "sg:phone":"+1 724 654 7281",
    "sg:postcode":"16101",
    "sg:province":"PA",
    "sg:tags":[
        "attorney"
    ],
    "wof:name":"Paul W Johnson",
    "wof:placetype":"venue"
},
  "geometry": {"coordinates":[-80.345176,41.001417],"type":"Point"}
}