{
  "type": "Feature",
  "properties": {
    "addr:full":"2078 Bennett Ave Lancaster PA 17601",
    "addr:housenumber":"2078",
    "addr:postcode":"17601",
    "addr:street":"Bennett Ave",
    "iso:country":"US",
    "sg:address":"2078 Bennett Ave",
    "sg:city":"Lancaster",
    "sg:classifiers":[
        {
            "category":"Home & Garden",
            "subcategory":"Home Furnishings",
            "type":"Retail Goods"
        },
        {
            "category":"Home & Garden",
            "subcategory":"Carpets & Floor Coverings",
            "type":"Retail Goods"
        },
        {
            "category":"Wholesale",
            "subcategory":"Home Furnishings",
            "type":"Manufacturing & Wholesale Goods"
        }
    ],
    "sg:phone":"+1 717 397 5863",
    "sg:postcode":"17601",
    "sg:province":"PA",
    "sg:tags":[
        "linen",
        "bedding",
        "waterbeds",
        "mattress"
    ],
    "sg:website":"http://www.thomasburger.com",
    "wof:name":"Bedstead, The",
    "wof:placetype":"venue"
},
  "geometry": {"coordinates":[-76.358448,40.059671],"type":"Point"}
}