{
  "type": "Feature",
  "properties": {
    "iso:country":"US",
    "sg:address":"304 Carlisle Rd",
    "sg:city":"Biglerville",
    "sg:classifiers":[
        {
            "category":"Food & Beverages",
            "subcategory":"Fruits & Vegetables",
            "type":"Retail Goods"
        }
    ],
    "sg:phone":"+1 717 677 8310",
    "sg:postcode":"17307",
    "sg:province":"PA",
    "sg:tags":[
        "produce"
    ],
    "wof:name":"Sandoe's Fruit Market Packing",
    "wof:placetype":"venue"
},
  "geometry": {"coordinates":[-77.24829,39.942207],"type":"Point"}
}