{
  "type": "Feature",
  "properties": {
    "iso:country":"US",
    "sg:address":"344 N 21st St",
    "sg:city":"Lebanon",
    "sg:classifiers":[
        {
            "category":"Organizations",
            "subcategory":"Religious Organization",
            "type":"Services"
        }
    ],
    "sg:phone":"+1 717 274 5002",
    "sg:postcode":"17046",
    "sg:province":"PA",
    "wof:name":"Clifford K Rauch Pastor",
    "wof:placetype":"venue"
},
  "geometry": {"coordinates":[-76.448648,40.344078],"type":"Point"}
}