{
  "type": "Feature",
  "properties": {
    "addr:full":"344 N 21st St Lebanon PA 17046",
    "addr:housenumber":"344",
    "addr:postcode":"17046",
    "addr:street":"N 21St St",
    "iso:country":"US",
    "sg:address":"344 N 21st St",
    "sg:city":"Lebanon",
    "sg:classifiers":[
        {
            "category":"Organizations",
            "subcategory":"Religious Organization",
            "type":"Services"
        }
    ],
    "sg:phone":"+1 717 274 5002",
    "sg:postcode":"17046",
    "sg:province":"PA",
    "wof:name":"Clifford K Rauch Pastor",
    "wof:placetype":"venue"
},
  "geometry": {"coordinates":[-76.44864800000001,40.344078],"type":"Point"}
}