{
  "type": "Feature",
  "properties": {
    "iso:country":"US",
    "sg:address":"536 3rd Ave",
    "sg:city":"Duncansville",
    "sg:classifiers":[
        {
            "category":"Banks & Credit Unions",
            "subcategory":"Bank",
            "type":"Services"
        }
    ],
    "sg:phone":"+1 814 696 8732",
    "sg:postcode":"16635",
    "sg:province":"PA",
    "sg:tags":[
        "financing"
    ],
    "wof:name":"Citi Financial",
    "wof:placetype":"venue"
},
  "geometry": {"coordinates":[-78.42021,40.427314],"type":"Point"}
}