{
  "type": "Feature",
  "properties": {
    "addr:full":"334 Walnut St Danville PA 17821",
    "addr:housenumber":"334",
    "addr:postcode":"17821",
    "addr:street":"Walnut St",
    "iso:country":"US",
    "sg:address":"334 Walnut St",
    "sg:city":"Danville",
    "sg:classifiers":[
        {
            "category":"Restaurant",
            "type":"Food & Drink"
        }
    ],
    "sg:phone":"+1 570 275 1310",
    "sg:postcode":"17821",
    "sg:province":"PA",
    "wof:name":"L T Evans",
    "wof:placetype":"venue"
},
  "geometry": {"coordinates":[-76.61086299999999,40.962632],"type":"Point"}
}