{
  "type": "Feature",
  "properties": {
    "iso:country":"US",
    "sg:address":"410 Harrisburg Ave",
    "sg:city":"Lancaster",
    "sg:classifiers":[
        {
            "category":"Retail",
            "subcategory":"Auto Repair",
            "type":"Services"
        }
    ],
    "sg:phone":"+1 717 393 7516",
    "sg:postcode":"17603",
    "sg:province":"PA",
    "sg:tags":[
        "repairing",
        "automobile"
    ],
    "wof:name":"Accurate Automotive",
    "wof:placetype":"venue"
},
  "geometry": {"coordinates":[-76.315494,40.048667],"type":"Point"}
}