{
  "type": "Feature",
  "properties": {
    "iso:country":"US",
    "sg:address":"3060 Delta Rd",
    "sg:city":"Brogue",
    "sg:classifiers":[
        {
            "category":"Building & Trades",
            "subcategory":"Construction",
            "type":"Services"
        }
    ],
    "sg:phone":"+1   ",
    "sg:postcode":"17309",
    "sg:province":"PA",
    "sg:tags":[
        "house"
    ],
    "wof:name":"Tdk Construction Services",
    "wof:placetype":"venue"
},
  "geometry": {"coordinates":[-76.483921,39.872114],"type":"Point"}
}