{
  "type": "Feature",
  "properties": {
    "iso:country":"US",
    "sg:address":"5721 N Fairhill St",
    "sg:city":"Philadelphia",
    "sg:classifiers":[
        {
            "category":"Shopping",
            "subcategory":"Comic Books",
            "type":"Retail Goods"
        }
    ],
    "sg:phone":"+1 215 549 6397",
    "sg:postcode":"19120",
    "sg:province":"PA",
    "wof:name":"A Comics",
    "wof:placetype":"venue"
},
  "geometry": {"coordinates":[-75.13111000000001,40.038417],"type":"Point"}
}