{
  "type": "Feature",
  "properties": {
    "iso:country":"US",
    "sg:address":"1935 Fruitville Pike",
    "sg:city":"Lancaster",
    "sg:classifiers":[
        {
            "category":"Building & Trades",
            "subcategory":"Cleaning & Sanitation",
            "type":"Services"
        }
    ],
    "sg:phone":"+1   ",
    "sg:postcode":"17601",
    "sg:province":"PA",
    "sg:tags":[
        "distributor",
        "floor",
        "janitorial",
        "maintenance",
        "supply"
    ],
    "wof:name":"Floor Medix LLC",
    "wof:placetype":"venue"
},
  "geometry": {"coordinates":[-76.32210000000001,40.075051],"type":"Point"}
}