{
  "type": "Feature",
  "properties": {
    "iso:country":"US",
    "sg:address":"40 N Market St",
    "sg:city":"Nanticoke",
    "sg:classifiers":[
        {
            "category":"Health Services",
            "subcategory":"Doctor",
            "type":"Services"
        }
    ],
    "sg:phone":"+1 570 735 2315",
    "sg:postcode":"18634",
    "sg:province":"PA",
    "sg:tags":[
        "dentist"
    ],
    "wof:name":"Tracey Neary DDS",
    "wof:placetype":"venue"
},
  "geometry": {"coordinates":[-76.00977899999999,41.20593],"type":"Point"}
}