{
  "type": "Feature",
  "properties": {
    "addr:full":"736 Burmont Rd Drexel Hill PA 19026",
    "addr:housenumber":"736",
    "addr:postcode":"19026",
    "addr:street":"Burmont Rd",
    "iso:country":"US",
    "sg:address":"736 Burmont Rd",
    "sg:city":"Drexel Hill",
    "sg:classifiers":[
        {
            "category":"Personal",
            "subcategory":"Beauty Salon",
            "type":"Services"
        }
    ],
    "sg:phone":"+1 610 259 2044",
    "sg:postcode":"19026",
    "sg:province":"PA",
    "wof:name":"Chuck Longo Hair Cutting",
    "wof:placetype":"venue"
},
  "geometry": {"coordinates":[-75.30775,39.949546],"type":"Point"}
}