{
  "type": "Feature",
  "properties": {
    "iso:country":"US",
    "sg:address":"1302 Weavertown Rd",
    "sg:city":"Lebanon",
    "sg:classifiers":[
        {
            "category":"Building & Trades",
            "subcategory":"Landscaping Services",
            "type":"Services"
        }
    ],
    "sg:phone":"+1 717 273 4381",
    "sg:postcode":"17046",
    "sg:province":"PA",
    "sg:tags":[
        "lawn",
        "maintenance"
    ],
    "wof:name":"Ebersoles Lawn Care",
    "wof:placetype":"venue"
},
  "geometry": {"coordinates":[-76.394048,40.355936],"type":"Point"}
}