{
  "type": "Feature",
  "properties": {
    "addr:full":"36 S Main St Perkasie PA 18944",
    "addr:housenumber":"36",
    "addr:postcode":"18944",
    "addr:street":"S Main St",
    "iso:country":"US",
    "sg:address":"36 S Main St",
    "sg:city":"Perkasie",
    "sg:classifiers":[
        {
            "category":"Building & Trades",
            "subcategory":"Construction",
            "type":"Services"
        }
    ],
    "sg:phone":"+1   ",
    "sg:postcode":"18944",
    "sg:province":"PA",
    "sg:tags":[
        "contractor"
    ],
    "wof:name":"R&R Morano",
    "wof:placetype":"venue"
},
  "geometry": {"coordinates":[-75.283863,40.367005],"type":"Point"}
}