{
  "type": "Feature",
  "properties": {
    "iso:country":"US",
    "sg:address":"251 9th St",
    "sg:city":"Charleroi",
    "sg:classifiers":[
        {
            "category":"Real Estate",
            "subcategory":"Real Estate Operator",
            "type":"Services"
        }
    ],
    "sg:phone":"+1   ",
    "sg:postcode":"15022",
    "sg:province":"PA",
    "sg:tags":[
        "building",
        "apartment"
    ],
    "wof:name":"Char House",
    "wof:placetype":"venue"
},
  "geometry": {"coordinates":[-79.90252099999999,40.142389],"type":"Point"}
}