{
  "type": "Feature",
  "properties": {
    "iso:country":"US",
    "sg:address":"4365 Rising Sun Ave",
    "sg:city":"Philadelphia",
    "sg:classifiers":[
        {
            "category":"Home & Garden",
            "subcategory":"Building Materials",
            "type":"Retail Goods"
        }
    ],
    "sg:phone":"+1 215 324 8030",
    "sg:postcode":"19140",
    "sg:province":"PA",
    "sg:tags":[
        "hardware",
        "lumber"
    ],
    "wof:name":"Torres Lumber Co Inc",
    "wof:placetype":"venue"
},
  "geometry": {"coordinates":[-75.128719,40.016487],"type":"Point"}
}