{
  "type": "Feature",
  "properties": {
    "iso:country":"US",
    "sg:address":"1230 Brunnerville Rd",
    "sg:city":"Lititz",
    "sg:classifiers":[
        {
            "category":"Professional",
            "subcategory":"Business Services",
            "type":"Services"
        },
        {
            "category":"Government",
            "subcategory":"Post Office",
            "type":"Public Place"
        }
    ],
    "sg:phone":"+1 800 275 8777",
    "sg:postcode":"17543",
    "sg:province":"PA",
    "sg:tags":[
        "mail",
        "shipping"
    ],
    "sg:website":"http://www.usps.com",
    "wof:name":"USPS - United States Post Office - Brunnerville",
    "wof:placetype":"venue"
},
  "geometry": {"coordinates":[-76.287198,40.182631],"type":"Point"}
}