{
  "type": "Feature",
  "properties": {
    "addr:full":"2121 Sir Lancelot Dr Harrisburg PA 17110",
    "addr:housenumber":"2121",
    "addr:postcode":"17110",
    "addr:street":"Sir Lancelot Dr",
    "iso:country":"US",
    "sg:address":"2121 Sir Lancelot Dr",
    "sg:city":"Harrisburg",
    "sg:classifiers":[
        {
            "category":"Manufacturing",
            "subcategory":"Printing",
            "type":"Manufacturing & Wholesale Goods"
        }
    ],
    "sg:phone":"+1   ",
    "sg:postcode":"17110",
    "sg:province":"PA",
    "sg:tags":[
        "book"
    ],
    "wof:name":"National Family Matters",
    "wof:placetype":"venue"
},
  "geometry": {"coordinates":[-76.855313,40.312646],"type":"Point"}
}