{
  "type": "Feature",
  "properties": {
    "addr:full":"1405 Dupont St Conway PA 15027",
    "addr:housenumber":"1405",
    "addr:postcode":"15027",
    "addr:street":"Dupont St",
    "iso:country":"US",
    "sg:address":"1405 Dupont St",
    "sg:city":"Conway",
    "sg:classifiers":[
        {
            "category":"Building & Trades",
            "subcategory":"Construction",
            "type":"Services"
        }
    ],
    "sg:phone":"+1 724 242 0703",
    "sg:postcode":"15027",
    "sg:province":"PA",
    "sg:tags":[
        "system",
        "contractor",
        "air conditioning"
    ],
    "wof:name":"Holly Talerico Devincent",
    "wof:placetype":"venue"
},
  "geometry": {"coordinates":[-80.235169,40.664972],"type":"Point"}
}