{
  "type": "Feature",
  "properties": {
    "iso:country":"US",
    "sg:address":"352 Stouffer Ave",
    "sg:city":"Chambersburg",
    "sg:classifiers":[
        {
            "category":"Wholesale",
            "subcategory":"Construction Materials",
            "type":"Manufacturing & Wholesale Goods"
        }
    ],
    "sg:phone":"+1 717 267 1212",
    "sg:postcode":"17201",
    "sg:province":"PA",
    "sg:tags":[
        "flat",
        "glass"
    ],
    "wof:name":"Winfield Glass",
    "wof:placetype":"venue"
},
  "geometry": {"coordinates":[-77.63906299999999,39.928618],"type":"Point"}
}