{
  "type": "Feature",
  "properties": {
    "addr:full":"716 Broad St New Bethlehem PA 16242",
    "addr:housenumber":"716",
    "addr:postcode":"16242",
    "addr:street":"Broad St",
    "iso:country":"US",
    "sg:address":"716 Broad St",
    "sg:city":"New Bethlehem",
    "sg:classifiers":[
        {
            "category":"Restaurant",
            "type":"Food & Drink"
        }
    ],
    "sg:menulink":"http://www.allmenus.com/pa/new-bethlehem/133426-subway/menu/",
    "sg:phone":"+1 814 275 7827",
    "sg:postcode":"16242",
    "sg:province":"PA",
    "sg:tags":[
        "american",
        "sandwich"
    ],
    "wof:name":"Subway",
    "wof:placetype":"venue"
},
  "geometry": {"coordinates":[-79.326419,41.002358],"type":"Point"}
}