{
  "type": "Feature",
  "properties": {
    "addr:full":"4710 Clairton Blvd Pittsburgh PA 15236",
    "addr:housenumber":"4710",
    "addr:postcode":"15236",
    "addr:street":"Clairton Blvd",
    "iso:country":"US",
    "sg:address":"4710 Clairton Blvd",
    "sg:city":"Pittsburgh",
    "sg:classifiers":[
        {
            "category":"Real Estate",
            "subcategory":"Real Estate Agent",
            "type":"Services"
        }
    ],
    "sg:phone":"+1   ",
    "sg:postcode":"15236",
    "sg:province":"PA",
    "wof:name":"Arec-Llccom",
    "wof:placetype":"venue"
},
  "geometry": {"coordinates":[-79.977863,40.352569],"type":"Point"}
}