{
  "type": "Feature",
  "properties": {
    "addr:full":"121 Edgewood Ave Pittsburgh PA 15218",
    "addr:housenumber":"121",
    "addr:postcode":"15218",
    "addr:street":"Edgewood Ave",
    "iso:country":"US",
    "sg:address":"121 Edgewood Ave",
    "sg:city":"Pittsburgh",
    "sg:classifiers":[
        {
            "category":"Professional",
            "subcategory":"Engineering",
            "type":"Services"
        }
    ],
    "sg:phone":"+1   ",
    "sg:postcode":"15218",
    "sg:province":"PA",
    "sg:tags":[
        "consultant"
    ],
    "wof:name":"Engineering Mtls & Processes",
    "wof:placetype":"venue"
},
  "geometry": {"coordinates":[-79.884652,40.432801],"type":"Point"}
}