{
  "type": "Feature",
  "properties": {
    "addr:full":"1770 Wheatfield Ct Middletown PA 17057",
    "addr:housenumber":"1770",
    "addr:postcode":"17057",
    "addr:street":"Wheatfield Ct",
    "iso:country":"US",
    "sg:address":"1770 Wheatfield Ct",
    "sg:city":"Middletown",
    "sg:classifiers":[
        {
            "category":"Building & Trades",
            "subcategory":"Construction",
            "type":"Services"
        }
    ],
    "sg:phone":"+1 717 773 0863",
    "sg:postcode":"17057",
    "sg:province":"PA",
    "sg:tags":[
        "waterproofing",
        "contractor"
    ],
    "wof:name":"Diamond Black Sealcoating",
    "wof:placetype":"venue"
},
  "geometry": {"coordinates":[-76.76212700000001,40.235],"type":"Point"}
}