{
  "type": "Feature",
  "properties": {
    "iso:country":"US",
    "sg:address":"1800 Sheridan St",
    "sg:city":"Braddock",
    "sg:classifiers":[
        {
            "category":"Manufacturing",
            "subcategory":"Signs",
            "type":"Manufacturing & Wholesale Goods"
        }
    ],
    "sg:phone":"+1   ",
    "sg:postcode":"15104",
    "sg:province":"PA",
    "sg:tags":[
        "specialty",
        "mfg"
    ],
    "wof:name":"Ten Graphix",
    "wof:placetype":"venue"
},
  "geometry": {"coordinates":[-79.844257,40.404851],"type":"Point"}
}