{
  "type": "Feature",
  "properties": {
    "addr:full":"552 Meetinghouse Rd Gap PA 17527",
    "addr:housenumber":"552",
    "addr:postcode":"17527",
    "addr:street":"Meetinghouse Rd",
    "iso:country":"US",
    "sg:address":"552 Meetinghouse Rd",
    "sg:city":"Gap",
    "sg:phone":"+1   ",
    "sg:postcode":"17527",
    "sg:province":"PA",
    "sg:tags":[
        "farm",
        "corn",
        "soybean"
    ],
    "wof:name":"Kenneth Eberly",
    "wof:placetype":"venue"
},
  "geometry": {"coordinates":[-76.00004,40.066178],"type":"Point"}
}