{
  "type": "Feature",
  "properties": {
    "addr:full":"886 E Prospect St York PA 17403",
    "addr:housenumber":"886",
    "addr:postcode":"17403",
    "addr:street":"E Prospect St",
    "iso:country":"US",
    "sg:address":"886 E Prospect St",
    "sg:city":"York",
    "sg:classifiers":[
        {
            "category":"Organizations",
            "subcategory":"Religious Organization",
            "type":"Services"
        }
    ],
    "sg:phone":"+1 717 854 5918",
    "sg:postcode":"17403",
    "sg:province":"PA",
    "sg:tags":[
        "church"
    ],
    "wof:name":"Cathedral Of Praise",
    "wof:placetype":"venue"
},
  "geometry": {"coordinates":[-76.707634,39.961296],"type":"Point"}
}