{
  "type": "Feature",
  "properties": {
    "iso:country":"US",
    "sg:address":"18 Andrew Ln",
    "sg:city":"Lansdale",
    "sg:classifiers":[
        {
            "category":"Personal",
            "subcategory":"Beauty Salon",
            "type":"Services"
        }
    ],
    "sg:phone":"+1 215 393 1241",
    "sg:postcode":"19446",
    "sg:province":"PA",
    "wof:name":"Belle Mariposa Salon",
    "wof:placetype":"venue"
},
  "geometry": {"coordinates":[-75.233507,40.262053],"type":"Point"}
}