{
  "type": "Feature",
  "properties": {
    "iso:country":"US",
    "sg:address":"211 W High St",
    "sg:city":"Bellefonte",
    "sg:classifiers":[
        {
            "category":"Bars & Pubs",
            "type":"Food & Drink"
        },
        {
            "category":"Restaurant",
            "type":"Food & Drink"
        }
    ],
    "sg:phone":"+1 814 353 1008",
    "sg:postcode":"16823",
    "sg:province":"PA",
    "sg:tags":[
        "new",
        "american"
    ],
    "sg:website":"thegovernorspub.com/",
    "wof:name":"The Governors' Pub",
    "wof:placetype":"venue"
},
  "geometry": {"coordinates":[-77.780136,40.911594],"type":"Point"}
}