{
  "type": "Feature",
  "properties": {
    "addr:full":"124 E Main St Ephrata PA 17522",
    "addr:housenumber":"124",
    "addr:postcode":"17522",
    "addr:street":"E Main St",
    "iso:country":"US",
    "sg:address":"124 E Main St",
    "sg:city":"Ephrata",
    "sg:classifiers":[
        {
            "category":"Professional",
            "subcategory":"Computer Services",
            "type":"Services"
        }
    ],
    "sg:phone":"+1 717 738 7000",
    "sg:postcode":"17522",
    "sg:province":"PA",
    "sg:tags":[
        "telecommunication"
    ],
    "wof:name":"Kiv De Telephone",
    "wof:placetype":"venue"
},
  "geometry": {"coordinates":[-76.175331,40.177158],"type":"Point"}
}