{
  "type": "Feature",
  "properties": {
    "iso:country":"US",
    "sg:address":"566 N Esbenshade Rd",
    "sg:city":"Manheim",
    "sg:phone":"+1   ",
    "sg:postcode":"17545",
    "sg:province":"PA",
    "sg:tags":[
        "farm",
        "field",
        "corn",
        "crop"
    ],
    "wof:name":"Seibel Farms",
    "wof:placetype":"venue"
},
  "geometry": {"coordinates":[-76.452685,40.140701],"type":"Point"}
}