{
  "type": "Feature",
  "properties": {
    "addr:full":"426 6th St Glassport PA 15045",
    "addr:housenumber":"426",
    "addr:postcode":"15045",
    "addr:street":"6Th St",
    "iso:country":"US",
    "sg:address":"426 6th St",
    "sg:city":"Glassport",
    "sg:classifiers":[
        {
            "category":"Food & Beverages",
            "subcategory":"Groceries & Convenience Stores",
            "type":"Retail Goods"
        },
        {
            "category":"Restaurant",
            "type":"Food & Drink"
        }
    ],
    "sg:phone":"+1 412 678 8233",
    "sg:postcode":"15045",
    "sg:province":"PA",
    "sg:tags":[
        "delicatessen",
        "engineering"
    ],
    "wof:name":"Fuzzy's Confectionery",
    "wof:placetype":"venue"
},
  "geometry": {"coordinates":[-79.8897,40.325943],"type":"Point"}
}