{
  "type": "Feature",
  "properties": {
    "iso:country":"US",
    "sg:address":"777 Bristol Pike",
    "sg:city":"Bensalem",
    "sg:classifiers":[
        {
            "category":"Retail",
            "subcategory":"Self-service Laundry",
            "type":"Services"
        }
    ],
    "sg:phone":"+1   ",
    "sg:postcode":"19020",
    "sg:province":"PA",
    "wof:name":"Launder Mart",
    "wof:placetype":"venue"
},
  "geometry": {"coordinates":[-74.97532699999999,40.065668],"type":"Point"}
}