{
  "type": "Feature",
  "properties": {
    "iso:country":"US",
    "sg:address":"1492 Main St",
    "sg:city":"Catasauqua",
    "sg:classifiers":[
        {
            "category":"Health Services",
            "subcategory":"Dentist",
            "type":"Services"
        }
    ],
    "sg:phone":"+1 610 266 0466",
    "sg:postcode":"18032",
    "sg:province":"PA",
    "wof:name":"Gyory Thomas R DMD",
    "wof:placetype":"venue"
},
  "geometry": {"coordinates":[-75.48085,40.667029],"type":"Point"}
}