{
  "type": "Feature",
  "properties": {
    "addr:full":"10530 US Hwy 6n Albion PA 16401",
    "addr:housenumber":"10530",
    "addr:postcode":"16401",
    "addr:street":"Us Hwy 6N",
    "iso:country":"US",
    "sg:address":"10530 US Hwy 6n",
    "sg:city":"Albion",
    "sg:classifiers":[
        {
            "category":"Retail",
            "subcategory":"Car Wash",
            "type":"Services"
        }
    ],
    "sg:phone":"+1 814 756 4055",
    "sg:postcode":"16401",
    "sg:province":"PA",
    "sg:tags":[
        "carwash",
        "polishing",
        "washing"
    ],
    "wof:name":"Steve's Auto Wash",
    "wof:placetype":"venue"
},
  "geometry": {"coordinates":[-80.350509,41.891045],"type":"Point"}
}