{
  "type": "Feature",
  "properties": {
    "addr:full":"230 S 4th St Mt Wolf PA 17347",
    "addr:housenumber":"230",
    "addr:postcode":"17347",
    "addr:street":"S 4Th St",
    "iso:country":"US",
    "sg:address":"230 S 4th St",
    "sg:city":"Mt Wolf",
    "sg:classifiers":[
        {
            "category":"Retail",
            "subcategory":"Animal Services",
            "type":"Services"
        }
    ],
    "sg:phone":"+1 717 266 4152",
    "sg:postcode":"17347",
    "sg:province":"PA",
    "sg:tags":[
        "pet",
        "boarding",
        "sitting"
    ],
    "wof:name":"Pets Plus",
    "wof:placetype":"venue"
},
  "geometry": {"coordinates":[-76.707688,40.059091],"type":"Point"}
}