{
  "type": "Feature",
  "properties": {
    "addr:full":"1625 Spruce St Philadelphia PA 19103",
    "addr:housenumber":"1625",
    "addr:postcode":"19103",
    "addr:street":"Spruce St",
    "iso:country":"US",
    "sg:address":"1625 Spruce St",
    "sg:city":"Philadelphia",
    "sg:classifiers":[
        {
            "category":"Shopping",
            "subcategory":"Musical Instruments",
            "type":"Retail Goods"
        },
        {
            "category":"Education",
            "subcategory":"Music School",
            "type":"Public Place"
        },
        {
            "category":"Arts & Performance",
            "subcategory":"Music",
            "type":"Entertainment"
        }
    ],
    "sg:phone":"+1 215 545 2500",
    "sg:postcode":"19103",
    "sg:province":"PA",
    "sg:tags":[
        "violin",
        "teacher"
    ],
    "sg:website":"www.germainviolins.com",
    "wof:name":"Christopher Germain Violin Maker",
    "wof:placetype":"venue"
},
  "geometry": {"coordinates":[-75.168729,39.947606],"type":"Point"}
}