{
  "type": "Feature",
  "properties": {
    "addr:full":"1330 Old Freeport Rd Pittsburgh PA 15238",
    "addr:housenumber":"1330",
    "addr:postcode":"15238",
    "addr:street":"Old Freeport Rd",
    "iso:country":"US",
    "sg:address":"1330 Old Freeport Rd",
    "sg:city":"Pittsburgh",
    "sg:classifiers":[
        {
            "category":"Health Services",
            "subcategory":"Doctor",
            "type":"Services"
        }
    ],
    "sg:phone":"+1 412 967 0885",
    "sg:postcode":"15238",
    "sg:province":"PA",
    "sg:tags":[
        "physician",
        "surgeon"
    ],
    "wof:name":"Obstetrical & Gynelogical",
    "wof:placetype":"venue"
},
  "geometry": {"coordinates":[-79.877426,40.488013],"type":"Point"}
}