{
  "type": "Feature",
  "properties": {
    "iso:country":"US",
    "sg:address":"1 Fayette St",
    "sg:city":"Conshohocken",
    "sg:classifiers":[
        {
            "category":"Banks & Credit Unions",
            "subcategory":"Investment Brokerage",
            "type":"Services"
        },
        {
            "category":"Professional",
            "type":"Services"
        }
    ],
    "sg:phone":"+1 610 834 1624",
    "sg:postcode":"19428",
    "sg:province":"PA",
    "sg:tags":[
        "security",
        "establishment"
    ],
    "wof:name":"Two Tower Bridge Assoc",
    "wof:placetype":"venue"
},
  "geometry": {"coordinates":[-75.308036,40.072015],"type":"Point"}
}