{
  "type": "Feature",
  "properties": {
    "addr:full":"1726 N Sydenham St Philadelphia PA 19121",
    "addr:housenumber":"1726",
    "addr:postcode":"19121",
    "addr:street":"N Sydenham St",
    "iso:country":"US",
    "sg:address":"1726 N Sydenham St",
    "sg:city":"Philadelphia",
    "sg:classifiers":[
        {
            "category":"Arts & Performance",
            "subcategory":"Theater",
            "type":"Entertainment"
        }
    ],
    "sg:phone":"+1   ",
    "sg:postcode":"19121",
    "sg:province":"PA",
    "sg:tags":[
        "group"
    ],
    "wof:name":"Dixie Hummingbirds",
    "wof:placetype":"venue"
},
  "geometry": {"coordinates":[-75.16014800000001,39.980137],"type":"Point"}
}