{
  "type": "Feature",
  "properties": {
    "addr:full":"1721 Walnut St Philadelphia PA 19103",
    "addr:housenumber":"1721",
    "addr:postcode":"19103",
    "addr:street":"Walnut St",
    "iso:country":"US",
    "sg:address":"1721 Walnut St",
    "sg:city":"Philadelphia",
    "sg:phone":"+1 215 569 8088",
    "sg:postcode":"19103",
    "sg:province":"PA",
    "sg:website":"http://www.talbots.com",
    "wof:name":"Talbots",
    "wof:placetype":"venue"
},
  "geometry": {"coordinates":[-75.169405,39.949992],"type":"Point"}
}