{
  "type": "Feature",
  "properties": {
    "iso:country":"US",
    "sg:address":"2001 S 29th St Ste 5",
    "sg:city":"Philadelphia",
    "sg:classifiers":[
        {
            "category":"Shopping",
            "subcategory":"Pets & Pet Supplies",
            "type":"Retail Goods"
        }
    ],
    "sg:phone":"+1 888 672 2757",
    "sg:postcode":"19145",
    "sg:province":"PA",
    "sg:tags":[
        "training"
    ],
    "sg:website":"www.opbarks.com",
    "wof:name":"Opportunity Barks Dog Behavior & Training",
    "wof:placetype":"venue"
},
  "geometry": {"coordinates":[-75.193893,39.928709],"type":"Point"}
}