{
  "type": "Feature",
  "properties": {
    "iso:country":"US",
    "sg:address":"1102 Brynhill Ct",
    "sg:city":"Ambler",
    "sg:classifiers":[
        {
            "category":"Real Estate",
            "subcategory":"Real Estate Agent",
            "type":"Services"
        }
    ],
    "sg:phone":"+1   ",
    "sg:postcode":"19002",
    "sg:province":"PA",
    "wof:name":"N L R Properties Inc",
    "wof:placetype":"venue"
},
  "geometry": {"coordinates":[-75.20399500000001,40.199538],"type":"Point"}
}