{
  "type": "Feature",
  "properties": {
    "iso:country":"US",
    "sg:address":"4359 Remo Crescent Rd",
    "sg:city":"Bensalem",
    "sg:classifiers":[
        {
            "category":"Building & Trades",
            "subcategory":"Cleaning & Sanitation",
            "type":"Services"
        }
    ],
    "sg:phone":"+1 215 245 7925",
    "sg:postcode":"19020",
    "sg:province":"PA",
    "sg:tags":[
        "maintenance"
    ],
    "wof:name":"Omni Janitorial",
    "wof:placetype":"venue"
},
  "geometry": {"coordinates":[-74.933578,40.116422],"type":"Point"}
}