{
  "type": "Feature",
  "properties": {
    "addr:full":"517 E Lincoln Hwy Langhorne PA 19047",
    "addr:housenumber":"517",
    "addr:postcode":"19047",
    "addr:street":"E Lincoln Hwy Langhorne Pa",
    "iso:country":"US",
    "sg:address":"517 E Lincoln Hwy",
    "sg:city":"Langhorne",
    "sg:classifiers":[
        {
            "category":"Social Services",
            "subcategory":"Child Care",
            "type":"Services"
        },
        {
            "category":"Education",
            "subcategory":"Preschool",
            "type":"Public Place"
        }
    ],
    "sg:phone":"+1 215 752 1132",
    "sg:postcode":"19047",
    "sg:province":"PA",
    "sg:tags":[
        "kindergarten",
        "nursery",
        "day"
    ],
    "wof:name":"Baby Genius Daycare Cente",
    "wof:placetype":"venue"
},
  "geometry": {"coordinates":[-74.90616300000001,40.162895],"type":"Point"}
}