{
  "type": "Feature",
  "properties": {
    "iso:country":"US",
    "sg:address":"8 Arlington St",
    "sg:city":"Carnegie",
    "sg:classifiers":[
        {
            "category":"Professional",
            "subcategory":"Lawyer & Legal Services",
            "type":"Services"
        }
    ],
    "sg:phone":"+1 412 276 6216",
    "sg:postcode":"15106",
    "sg:province":"PA",
    "sg:tags":[
        "attorney"
    ],
    "wof:name":"Michael B Kaleugher",
    "wof:placetype":"venue"
},
  "geometry": {"coordinates":[-80.136411,40.396944],"type":"Point"}
}