{
  "type": "Feature",
  "properties": {
    "iso:country":"US",
    "sg:address":"1817 Parkway View Dr",
    "sg:city":"Pittsburgh",
    "sg:classifiers":[
        {
            "category":"Shopping",
            "subcategory":"Jewelry",
            "type":"Retail Goods"
        }
    ],
    "sg:phone":"+1 412 722 1277",
    "sg:postcode":"15205",
    "sg:province":"PA",
    "sg:tags":[
        "watch"
    ],
    "wof:name":"Kobold Watch Co",
    "wof:placetype":"venue"
},
  "geometry": {"coordinates":[-80.13018700000001,40.435376],"type":"Point"}
}