{
  "type": "Feature",
  "properties": {
    "addr:full":"1426 Walnut St Philadelphia PA 19102",
    "addr:housenumber":"1426",
    "addr:postcode":"19102",
    "addr:street":"Walnut St",
    "iso:country":"US",
    "sg:address":"1426 Walnut St",
    "sg:city":"Philadelphia",
    "sg:phone":"+1 215 545 5055",
    "sg:postcode":"19102",
    "sg:province":"PA",
    "wof:name":"02 Skincare Lounge @ Jason Matthew Salon",
    "wof:placetype":"venue"
},
  "geometry": {"coordinates":[-75.16525300000001,39.949468],"type":"Point"}
}