{
  "type": "Feature",
  "properties": {
    "iso:country":"US",
    "sg:address":"2168 Galloway Rd",
    "sg:city":"Bensalem",
    "sg:classifiers":[
        {
            "category":"Travel",
            "subcategory":"Travel Agent",
            "type":"Entertainment"
        }
    ],
    "sg:phone":"+1 215 245 6161",
    "sg:postcode":"19020",
    "sg:province":"PA",
    "sg:tags":[
        "agency",
        "bureau"
    ],
    "wof:name":"Trans World Travel",
    "wof:placetype":"venue"
},
  "geometry": {"coordinates":[-74.93634900000001,40.110812],"type":"Point"}
}