{
  "type": "Feature",
  "properties": {
    "iso:country":"US",
    "sg:address":"720 Delaware St",
    "sg:city":"Scranton",
    "sg:classifiers":[
        {
            "category":"Organizations",
            "subcategory":"Religious Organization",
            "type":"Services"
        }
    ],
    "sg:phone":"+1 570 343 1035",
    "sg:postcode":"18509",
    "sg:province":"PA",
    "sg:tags":[
        "church"
    ],
    "wof:name":"Asbury United Methodist Church",
    "wof:placetype":"venue"
},
  "geometry": {"coordinates":[-75.64925599999999,41.429991],"type":"Point"}
}