{
  "type": "Feature",
  "properties": {
    "iso:country":"US",
    "sg:address":"458 Indian Run Rd",
    "sg:city":"Glenmoore",
    "sg:classifiers":[
        {
            "category":"Building & Trades",
            "subcategory":"Landscaping Services",
            "type":"Services"
        }
    ],
    "sg:phone":"+1 610 942 3296",
    "sg:postcode":"19343",
    "sg:province":"PA",
    "sg:tags":[
        "lawn"
    ],
    "wof:name":"Community Maintenance Corp",
    "wof:placetype":"venue"
},
  "geometry": {"coordinates":[-75.809832,40.083254],"type":"Point"}
}