{
  "type": "Feature",
  "properties": {
    "iso:country":"US",
    "sg:address":"235 N Madison St",
    "sg:city":"Allentown",
    "sg:classifiers":[
        {
            "category":"Shopping",
            "subcategory":"Bicycles & Sporting Goods",
            "type":"Retail Goods"
        }
    ],
    "sg:phone":"+1 610 434 1140",
    "sg:postcode":"18102",
    "sg:province":"PA",
    "wof:name":"Community Bike Works",
    "wof:placetype":"venue"
},
  "geometry": {"coordinates":[-75.486885,40.602805],"type":"Point"}
}