{
  "type": "Feature",
  "properties": {
    "iso:country":"US",
    "sg:address":"2041 Herr St",
    "sg:city":"Harrisburg",
    "sg:classifiers":[
        {
            "category":"Professional",
            "subcategory":"Lawyer & Legal Services",
            "type":"Services"
        }
    ],
    "sg:phone":"+1 717 238 5707",
    "sg:postcode":"17103",
    "sg:province":"PA",
    "wof:name":"McCarthy Weisberg Cummings Llc",
    "wof:placetype":"venue"
},
  "geometry": {"coordinates":[-76.861557,40.277567],"type":"Point"}
}