{
  "type": "Feature",
  "properties": {
    "addr:full":"2207 Gordon St Allentown PA 18104",
    "addr:housenumber":"2207",
    "addr:postcode":"18104",
    "addr:street":"Gordon St",
    "iso:country":"US",
    "sg:address":"2207 Gordon St",
    "sg:city":"Allentown",
    "sg:classifiers":[
        {
            "category":"Health Services",
            "subcategory":"Health Practitioner",
            "type":"Services"
        }
    ],
    "sg:phone":"+1 610 437 6187",
    "sg:postcode":"18104",
    "sg:province":"PA",
    "wof:name":"Myotherapy Center",
    "wof:placetype":"venue"
},
  "geometry": {"coordinates":[-75.506274,40.599139],"type":"Point"}
}