{
  "type": "Feature",
  "properties": {
    "iso:country":"US",
    "sg:address":"50 E Chocolate Ave",
    "sg:city":"Hershey",
    "sg:classifiers":[
        {
            "category":"Social Services",
            "subcategory":"Child Care",
            "type":"Services"
        },
        {
            "category":"Education",
            "subcategory":"Preschool",
            "type":"Public Place"
        },
        {
            "category":"Education",
            "subcategory":"School",
            "type":"Public Place"
        }
    ],
    "sg:phone":"+1 717 533 1466",
    "sg:postcode":"17033",
    "sg:province":"PA",
    "sg:tags":[
        "elementary",
        "day"
    ],
    "wof:name":"Tender Years Inc Child Development Centers",
    "wof:placetype":"venue"
},
  "geometry": {"coordinates":[-76.648697,40.285999],"type":"Point"}
}