{
  "type": "Feature",
  "properties": {
    "iso:country":"US",
    "sg:address":"87 Tarentum Bridge Rd",
    "sg:city":"New Kensington",
    "sg:classifiers":[
        {
            "category":"Retail",
            "subcategory":"Auto Repair",
            "type":"Services"
        }
    ],
    "sg:phone":"+1   ",
    "sg:postcode":"15068",
    "sg:province":"PA",
    "sg:tags":[
        "general"
    ],
    "wof:name":"Grease Monkey",
    "wof:placetype":"venue"
},
  "geometry": {"coordinates":[-79.74885999999999,40.5858],"type":"Point"}
}