{
  "type": "Feature",
  "properties": {
    "iso:country":"US",
    "sg:address":"179 W Berks St",
    "sg:city":"Philadelphia",
    "sg:classifiers":[
        {
            "category":"Wholesale",
            "subcategory":"Machinery & Supplies",
            "type":"Manufacturing & Wholesale Goods"
        },
        {
            "category":"Manufacturing",
            "subcategory":"Tools & Machinery",
            "type":"Manufacturing & Wholesale Goods"
        }
    ],
    "sg:phone":"+1 215 426 5473",
    "sg:postcode":"19122",
    "sg:province":"PA",
    "sg:tags":[
        "mfg",
        "process",
        "photo",
        "screen",
        "equipment",
        "printing",
        "design",
        "silk"
    ],
    "sg:website":"www.ppsilkscreen.com",
    "wof:name":"Photo Processing Screen Mfg Co",
    "wof:placetype":"venue"
},
  "geometry": {"coordinates":[-75.13596200000001,39.978961],"type":"Point"}
}