{
  "type": "Feature",
  "properties": {
    "addr:full":"12 W Southern Ave S Williamsport PA 17702",
    "addr:housenumber":"12",
    "addr:postcode":"17702",
    "addr:street":"W Southern Ave S",
    "iso:country":"US",
    "sg:address":"12 W Southern Ave",
    "sg:city":"S Williamsport",
    "sg:phone":"+1 570 321 9190",
    "sg:postcode":"17702",
    "sg:province":"PA",
    "sg:tags":[
        "oil"
    ],
    "wof:name":"A-1 Oil Co",
    "wof:placetype":"venue"
},
  "geometry": {"coordinates":[-76.995769,41.233294],"type":"Point"}
}