{
  "type": "Feature",
  "properties": {
    "addr:full":"123 Adams Ave Mineral Point PA 15942",
    "addr:housenumber":"123",
    "addr:postcode":"15942",
    "addr:street":"Adams Ave",
    "iso:country":"US",
    "sg:address":"123 Adams Ave",
    "sg:city":"Mineral Point",
    "sg:classifiers":[
        {
            "category":"Organizations",
            "subcategory":"Religious Organization",
            "type":"Services"
        }
    ],
    "sg:phone":"+1 814 322 1177",
    "sg:postcode":"15942",
    "sg:province":"PA",
    "wof:name":"Vinco Brethren Church",
    "wof:placetype":"venue"
},
  "geometry": {"coordinates":[-78.85596200000001,40.404749],"type":"Point"}
}