{
  "type": "Feature",
  "properties": {
    "iso:country":"US",
    "sg:address":"1000 S Mountain Blvd",
    "sg:city":"Wilkes Barre",
    "sg:classifiers":[
        {
            "category":"Health Services",
            "subcategory":"Doctor",
            "type":"Services"
        }
    ],
    "sg:phone":"+1   ",
    "sg:postcode":"18707",
    "sg:province":"PA",
    "sg:tags":[
        "medical"
    ],
    "wof:name":"Orthopedic Center of Geisinger",
    "wof:placetype":"venue"
},
  "geometry": {"coordinates":[-75.93335399999999,41.095766],"type":"Point"}
}