{
  "type": "Feature",
  "properties": {
    "iso:country":"US",
    "sg:address":"2806 Cascade St",
    "sg:city":"Erie",
    "sg:classifiers":[
        {
            "category":"Communications",
            "subcategory":"Film & Video Production",
            "type":"Services"
        }
    ],
    "sg:phone":"+1 814 864 2295",
    "sg:postcode":"16508",
    "sg:province":"PA",
    "sg:tags":[
        "consultant",
        "audio"
    ],
    "wof:name":"J C Media Svc Inc",
    "wof:placetype":"venue"
},
  "geometry": {"coordinates":[-80.09279100000001,42.101867],"type":"Point"}
}