{
  "type": "Feature",
  "properties": {
    "iso:country":"US",
    "sg:address":"4229 Glenn Ave",
    "sg:city":"Fairview",
    "sg:classifiers":[
        {
            "category":"Wholesale",
            "subcategory":"Non-durable Goods",
            "type":"Manufacturing & Wholesale Goods"
        }
    ],
    "sg:phone":"+1 814 474 2275",
    "sg:postcode":"16415",
    "sg:province":"PA",
    "sg:tags":[
        "advertising"
    ],
    "wof:name":"Fall Distributing",
    "wof:placetype":"venue"
},
  "geometry": {"coordinates":[-80.26176700000001,42.02677],"type":"Point"}
}