{
  "type": "Feature",
  "properties": {
    "iso:country":"US",
    "sg:address":"3200 Paxton St",
    "sg:city":"Harrisburg",
    "sg:classifiers":[
        {
            "category":"Banks & Credit Unions",
            "subcategory":"Bank",
            "type":"Services"
        }
    ],
    "sg:phone":"+1 717 564 3383",
    "sg:postcode":"17104",
    "sg:province":"PA",
    "sg:tags":[
        "lottery",
        "cashing",
        "telegram",
        "sales",
        "ticket",
        "check"
    ],
    "wof:name":"United Check Cashing Co",
    "wof:placetype":"venue"
},
  "geometry": {"coordinates":[-76.83423999999999,40.254998],"type":"Point"}
}