{
  "type": "Feature",
  "properties": {
    "iso:country":"US",
    "sg:address":"121 E Peters Ln",
    "sg:city":"Aston",
    "sg:classifiers":[
        {
            "category":"Shopping",
            "subcategory":"Catalog Store",
            "type":"Retail Goods"
        }
    ],
    "sg:phone":"+1   ",
    "sg:postcode":"19014",
    "sg:province":"PA",
    "sg:tags":[
        "mail",
        "house"
    ],
    "wof:name":"Innocoll Inc",
    "wof:placetype":"venue"
},
  "geometry": {"coordinates":[-75.467428,39.872217],"type":"Point"}
}