{
  "type": "Feature",
  "properties": {
    "iso:country":"US",
    "sg:address":"2620 Springwood Rd",
    "sg:city":"York",
    "sg:classifiers":[
        {
            "category":"Education",
            "subcategory":"School",
            "type":"Public Place"
        }
    ],
    "sg:phone":"+1 717 505 5051",
    "sg:postcode":"17402",
    "sg:province":"PA",
    "wof:name":"Ore Valley Elementary School",
    "wof:placetype":"venue"
},
  "geometry": {"coordinates":[-76.660301,39.930942],"type":"Point"}
}