{
  "type": "Feature",
  "properties": {
    "addr:full":"517 Evansburg Rd Collegeville PA 19426",
    "addr:housenumber":"517",
    "addr:postcode":"19426",
    "addr:street":"Evansburg Rd",
    "iso:country":"US",
    "sg:address":"517 Evansburg Rd",
    "sg:city":"Collegeville",
    "sg:classifiers":[
        {
            "category":"Shopping",
            "subcategory":"Used Merchandise",
            "type":"Retail Goods"
        }
    ],
    "sg:phone":"+1   ",
    "sg:postcode":"19426",
    "sg:province":"PA",
    "sg:tags":[
        "contractor"
    ],
    "wof:name":"Jerrys Antq U Furn New Carpets",
    "wof:placetype":"venue"
},
  "geometry": {"coordinates":[-75.41924,40.195386],"type":"Point"}
}