{
  "type": "Feature",
  "properties": {
    "iso:country":"US",
    "sg:address":"1611 Potter Dr",
    "sg:city":"Pottstown",
    "sg:classifiers":[
        {
            "category":"Professional",
            "type":"Services"
        }
    ],
    "sg:phone":"+1   ",
    "sg:postcode":"19464",
    "sg:province":"PA",
    "wof:name":"Tomasetti Joseph C Mpt LLC",
    "wof:placetype":"venue"
},
  "geometry": {"coordinates":[-75.608756,40.253248],"type":"Point"}
}