{
  "type": "Feature",
  "properties": {
    "addr:full":"30 W 3rd St Williamsport PA 17701",
    "addr:housenumber":"30",
    "addr:postcode":"17701",
    "addr:street":"W 3Rd St",
    "iso:country":"US",
    "sg:address":"30 W 3rd St",
    "sg:city":"Williamsport",
    "sg:classifiers":[
        {
            "category":"Shopping",
            "subcategory":"Florist",
            "type":"Retail Goods"
        }
    ],
    "sg:phone":"+1 570 323 8525",
    "sg:postcode":"17701",
    "sg:province":"PA",
    "wof:name":"J C Floral & Gift",
    "wof:placetype":"venue"
},
  "geometry": {"coordinates":[-77.00137700000001,41.241112],"type":"Point"}
}