{
  "type": "Feature",
  "properties": {
    "iso:country":"US",
    "sg:address":"999 N Gallatin Ave Exd",
    "sg:city":"Uniontown",
    "sg:classifiers":[
        {
            "category":"Restaurant",
            "type":"Food & Drink"
        }
    ],
    "sg:phone":"+1 724 439 5589",
    "sg:postcode":"15401",
    "sg:province":"PA",
    "wof:name":"Smitty's Bar & Restaurant",
    "wof:placetype":"venue"
},
  "geometry": {"coordinates":[-79.68168,39.92894],"type":"Point"}
}