{
  "type": "Feature",
  "properties": {
    "iso:country":"US",
    "sg:address":"1103 W Chester Rd",
    "sg:city":"West Chester",
    "sg:classifiers":[
        {
            "category":"Sports & Exercise",
            "subcategory":"Gym",
            "type":"Entertainment"
        }
    ],
    "sg:phone":"+1   ",
    "sg:postcode":"19382",
    "sg:province":"PA",
    "sg:tags":[
        "fitness",
        "physical",
        "facility"
    ],
    "wof:name":"Mc Dermotts Athletic Clubs",
    "wof:placetype":"venue"
},
  "geometry": {"coordinates":[-75.546345,39.911131],"type":"Point"}
}