{
  "type": "Feature",
  "properties": {
    "iso:country":"US",
    "sg:address":"7114 State Rd",
    "sg:city":"Philadelphia",
    "sg:classifiers":[
        {
            "category":"Autos & Motor Vehicles",
            "subcategory":"Auto Supplies",
            "type":"Retail Goods"
        }
    ],
    "sg:phone":"+1 215 335 1666",
    "sg:postcode":"19135",
    "sg:province":"PA",
    "sg:tags":[
        "automobile",
        "parts"
    ],
    "wof:name":"Mechanic's Auto Parts Inc",
    "wof:placetype":"venue"
},
  "geometry": {"coordinates":[-75.035101,40.02408],"type":"Point"}
}