{
  "type": "Feature",
  "properties": {
    "iso:country":"US",
    "sg:address":"421 W Hazel Ave",
    "sg:city":"Marietta",
    "sg:classifiers":[
        {
            "category":"Wholesale",
            "subcategory":"Machinery & Supplies",
            "type":"Manufacturing & Wholesale Goods"
        }
    ],
    "sg:phone":"+1 717 426 2250",
    "sg:postcode":"17547",
    "sg:province":"PA",
    "sg:tags":[
        "equipment",
        "material",
        "handling"
    ],
    "wof:name":"Diversified Liquidators Inc",
    "wof:placetype":"venue"
},
  "geometry": {"coordinates":[-76.564643,40.054802],"type":"Point"}
}