{
  "type": "Feature",
  "properties": {
    "iso:country":"US",
    "sg:address":"247 E Penn Ave",
    "sg:city":"Wernersville",
    "sg:classifiers":[
        {
            "category":"Shopping",
            "subcategory":"Optical Goods",
            "type":"Retail Goods"
        }
    ],
    "sg:phone":"+1 610 678 7202",
    "sg:postcode":"19565",
    "sg:province":"PA",
    "wof:name":"Berks Family Eyecare",
    "wof:placetype":"venue"
},
  "geometry": {"coordinates":[-76.073774,40.328672],"type":"Point"}
}