{
  "type": "Feature",
  "properties": {
    "addr:full":"227 Market St Kittanning PA 16201",
    "addr:housenumber":"227",
    "addr:postcode":"16201",
    "addr:street":"Market St",
    "iso:country":"US",
    "sg:address":"227 Market St",
    "sg:city":"Kittanning",
    "sg:classifiers":[
        {
            "category":"Banks & Credit Unions",
            "subcategory":"Bank",
            "type":"Services"
        }
    ],
    "sg:phone":"+1 724 548 1555",
    "sg:postcode":"16201",
    "sg:province":"PA",
    "wof:name":"First National Bank",
    "wof:placetype":"venue"
},
  "geometry": {"coordinates":[-79.519471,40.814406],"type":"Point"}
}