{
  "type": "Feature",
  "properties": {
    "iso:country":"US",
    "sg:address":"881 Enders Rd",
    "sg:city":"Halifax",
    "sg:classifiers":[
        {
            "category":"Manufacturing",
            "subcategory":"Tools & Machinery",
            "type":"Manufacturing & Wholesale Goods"
        }
    ],
    "sg:phone":"+1 717 362 4031",
    "sg:postcode":"17032",
    "sg:province":"PA",
    "sg:tags":[
        "mowers-sharpening",
        "repairing",
        "lawn"
    ],
    "wof:name":"Bob Straw's Sharp All",
    "wof:placetype":"venue"
},
  "geometry": {"coordinates":[-76.851194,40.49331],"type":"Point"}
}