{
  "type": "Feature",
  "properties": {
    "addr:full":"1 Education Dr Seneca PA 16346",
    "addr:housenumber":"1",
    "addr:postcode":"16346",
    "addr:street":"Education Dr",
    "iso:country":"US",
    "sg:address":"1 Education Dr",
    "sg:city":"Seneca",
    "sg:classifiers":[
        {
            "category":"Professional",
            "type":"Services"
        }
    ],
    "sg:phone":"+1 814 676 1141",
    "sg:postcode":"16346",
    "sg:province":"PA",
    "sg:tags":[
        "establishment"
    ],
    "wof:name":"Channel One",
    "wof:placetype":"venue"
},
  "geometry": {"coordinates":[-79.708961,41.36721],"type":"Point"}
}