{
  "type": "Feature",
  "properties": {
    "iso:country":"US",
    "sg:address":"2010 Beaver Ave",
    "sg:city":"Monaca",
    "sg:classifiers":[
        {
            "category":"Recreation",
            "subcategory":"Marina",
            "type":"Entertainment"
        }
    ],
    "sg:phone":"+1 724 775 2526",
    "sg:postcode":"15061",
    "sg:province":"PA",
    "sg:tags":[
        "repairing",
        "boat"
    ],
    "wof:name":"Three Rivers Marine Svc",
    "wof:placetype":"venue"
},
  "geometry": {"coordinates":[-80.271698,40.685519],"type":"Point"}
}