{
  "type": "Feature",
  "properties": {
    "iso:country":"US",
    "sg:address":"801 Arch St",
    "sg:city":"Philadelphia",
    "sg:classifiers":[
        {
            "category":"Restaurant",
            "type":"Food & Drink"
        }
    ],
    "sg:phone":"+1 215 574 4243",
    "sg:postcode":"19107",
    "sg:province":"PA",
    "wof:name":"Quiznos Sub",
    "wof:placetype":"venue"
},
  "geometry": {"coordinates":[-75.15471599999999,39.953348],"type":"Point"}
}