{
  "type": "Feature",
  "properties": {
    "iso:country":"US",
    "sg:address":"555 Business Park Ln",
    "sg:city":"Allentown",
    "sg:classifiers":[
        {
            "category":"Professional",
            "subcategory":"Computer Services",
            "type":"Services"
        }
    ],
    "sg:phone":"+1 610 820 5820",
    "sg:postcode":"18109",
    "sg:province":"PA",
    "sg:tags":[
        "repair"
    ],
    "wof:name":"Microapex Computer Systems Inc",
    "wof:placetype":"venue"
},
  "geometry": {"coordinates":[-75.454498,40.629799],"type":"Point"}
}