{
  "type": "Feature",
  "properties": {
    "iso:country":"US",
    "sg:address":"184 Overcash Rd",
    "sg:city":"Chambersburg",
    "sg:classifiers":[
        {
            "category":"Building & Trades",
            "subcategory":"Construction",
            "type":"Services"
        }
    ],
    "sg:phone":"+1 717 375 4122",
    "sg:postcode":"17202",
    "sg:province":"PA",
    "sg:tags":[
        "altering",
        "bathroom",
        "remodeling",
        "contractor"
    ],
    "wof:name":"Dale Shank",
    "wof:placetype":"venue"
},
  "geometry": {"coordinates":[-77.68751399999999,39.872541],"type":"Point"}
}