{
  "type": "Feature",
  "properties": {
    "iso:country":"US",
    "sg:address":"3430 Tulip St",
    "sg:city":"Philadelphia",
    "sg:classifiers":[
        {
            "category":"Wholesale",
            "subcategory":"Machinery & Supplies",
            "type":"Manufacturing & Wholesale Goods"
        },
        {
            "category":"Wholesale",
            "subcategory":"Hardware",
            "type":"Manufacturing & Wholesale Goods"
        }
    ],
    "sg:phone":"+1 215 289 3515",
    "sg:postcode":"19134",
    "sg:province":"PA",
    "sg:tags":[
        "pipe",
        "fitting",
        "sup"
    ],
    "wof:name":"A D Surplus Sales",
    "wof:placetype":"venue"
},
  "geometry": {"coordinates":[-75.100883,39.993016],"type":"Point"}
}