{
  "type": "Feature",
  "properties": {
    "iso:country":"US",
    "sg:address":"16 Entrance Dr",
    "sg:city":"Johnstown",
    "sg:classifiers":[
        {
            "category":"Banks & Credit Unions",
            "subcategory":"Investment Brokerage",
            "type":"Services"
        }
    ],
    "sg:phone":"+1   ",
    "sg:postcode":"15905",
    "sg:province":"PA",
    "sg:tags":[
        "security"
    ],
    "wof:name":"Edward Jones 06288",
    "wof:placetype":"venue"
},
  "geometry": {"coordinates":[-78.955901,40.321507],"type":"Point"}
}