{
  "type": "Feature",
  "properties": {
    "iso:country":"US",
    "sg:address":"4900 Torresdale Ave",
    "sg:city":"Philadelphia",
    "sg:classifiers":[
        {
            "category":"Education",
            "subcategory":"School",
            "type":"Public Place"
        }
    ],
    "sg:phone":"+1 215 537 2932",
    "sg:postcode":"19124",
    "sg:province":"PA",
    "sg:tags":[
        "k-",
        "private"
    ],
    "wof:name":"School District Of Philadelphia",
    "wof:placetype":"venue"
},
  "geometry": {"coordinates":[-75.075259,40.012107],"type":"Point"}
}