{
  "type": "Feature",
  "properties": {
    "addr:full":"1182 Pittsburgh Rd Valencia PA 16059",
    "addr:housenumber":"1182",
    "addr:postcode":"16059",
    "addr:street":"Pittsburgh Rd",
    "iso:country":"US",
    "sg:address":"1182 Pittsburgh Rd",
    "sg:city":"Valencia",
    "sg:classifiers":[
        {
            "category":"Home & Garden",
            "subcategory":"Carpets & Floor Coverings",
            "type":"Retail Goods"
        }
    ],
    "sg:phone":"+1 724 898 2145",
    "sg:postcode":"16059",
    "sg:province":"PA",
    "sg:tags":[
        "carpeting"
    ],
    "wof:name":"Robco Floor Covering Inc",
    "wof:placetype":"venue"
},
  "geometry": {"coordinates":[-79.93380000000001,40.708],"type":"Point"}
}