{
  "type": "Feature",
  "properties": {
    "addr:full":"920 Bethlehem Pike Glenside PA 19038",
    "addr:housenumber":"920",
    "addr:postcode":"19038",
    "addr:street":"Bethlehem Pike",
    "iso:country":"US",
    "sg:address":"920 Bethlehem Pike",
    "sg:city":"Glenside",
    "sg:classifiers":[
        {
            "category":"Shopping",
            "subcategory":"Pharmacy",
            "type":"Retail Goods"
        }
    ],
    "sg:phone":"+1 215 233 4485",
    "sg:postcode":"19038",
    "sg:province":"PA",
    "sg:tags":[
        "aid",
        "supply",
        "first"
    ],
    "sg:website":"http://www.cvs.com",
    "wof:name":"CVS/pharmacy",
    "wof:placetype":"venue"
},
  "geometry": {"coordinates":[-75.213187,40.095913],"type":"Point"}
}