{
  "type": "Feature",
  "properties": {
    "iso:country":"US",
    "sg:address":"622 Park City Center",
    "sg:city":"Lancaster",
    "sg:classifiers":[
        {
            "category":"Shopping",
            "subcategory":"Clothing, Apparel, & Fashions",
            "type":"Retail Goods"
        }
    ],
    "sg:phone":"+1 717 390 7203",
    "sg:postcode":"17601",
    "sg:province":"PA",
    "sg:tags":[
        "retailer"
    ],
    "sg:website":"www.petitesophisticate.com",
    "wof:name":"Petite Sophisticate",
    "wof:placetype":"venue"
},
  "geometry": {"coordinates":[-76.340878,40.064696],"type":"Point"}
}