{
  "type": "Feature",
  "properties": {
    "iso:country":"US",
    "sg:address":"419 Impounding Dam Rd",
    "sg:city":"Hanover",
    "sg:classifiers":[
        {
            "category":"Retail",
            "subcategory":"Auto Repair",
            "type":"Services"
        }
    ],
    "sg:phone":"+1   ",
    "sg:postcode":"17331",
    "sg:province":"PA",
    "sg:tags":[
        "general"
    ],
    "wof:name":"Morningstar Auto Repair",
    "wof:placetype":"venue"
},
  "geometry": {"coordinates":[-76.983261,39.752251],"type":"Point"}
}