{
  "type": "Feature",
  "properties": {
    "addr:full":"1 Saylor Rd Schwenksville PA 19473",
    "addr:housenumber":"1",
    "addr:postcode":"19473",
    "addr:street":"Saylor Rd",
    "iso:country":"US",
    "sg:address":"1 Saylor Rd",
    "sg:city":"Schwenksville",
    "sg:classifiers":[
        {
            "category":"Farming",
            "subcategory":"Livestock Farm",
            "type":"Manufacturing & Wholesale Goods"
        }
    ],
    "sg:phone":"+1   ",
    "sg:postcode":"19473",
    "sg:province":"PA",
    "sg:tags":[
        "equine"
    ],
    "wof:name":"Little Saylors Farm",
    "wof:placetype":"venue"
},
  "geometry": {"coordinates":[-75.483621,40.24047],"type":"Point"}
}