{
  "type": "Feature",
  "properties": {
    "iso:country":"US",
    "sg:address":"2126 S 58th St",
    "sg:city":"Philadelphia",
    "sg:classifiers":[
        {
            "category":"Retail",
            "subcategory":"Auto Rental",
            "type":"Services"
        }
    ],
    "sg:phone":"+1 215 724 7920",
    "sg:postcode":"19143",
    "sg:province":"PA",
    "sg:tags":[
        "car"
    ],
    "wof:name":"Philadelphia Auto Repair",
    "wof:placetype":"venue"
},
  "geometry": {"coordinates":[-75.22561399999999,39.933113],"type":"Point"}
}