{
  "type": "Feature",
  "properties": {
    "addr:full":"105 Gerald St State College PA 16801",
    "addr:housenumber":"105",
    "addr:postcode":"16801",
    "addr:street":"Gerald St",
    "iso:country":"US",
    "sg:address":"105 Gerald St",
    "sg:city":"State College",
    "sg:classifiers":[
        {
            "category":"Shopping",
            "subcategory":"Used Merchandise",
            "type":"Retail Goods"
        }
    ],
    "sg:phone":"+1 814 238 2980",
    "sg:postcode":"16801",
    "sg:province":"PA",
    "sg:tags":[
        "antique"
    ],
    "wof:name":"Apple Hill Antiques",
    "wof:placetype":"venue"
},
  "geometry": {"coordinates":[-77.80944,40.827091],"type":"Point"}
}