{
  "type": "Feature",
  "properties": {
    "iso:country":"US",
    "sg:address":"849 W Baltimore Pike",
    "sg:city":"West Grove",
    "sg:classifiers":[
        {
            "category":"Food & Beverages",
            "subcategory":"Groceries & Convenience Stores",
            "type":"Retail Goods"
        }
    ],
    "sg:phone":"+1 610 345 0183",
    "sg:postcode":"19390",
    "sg:province":"PA",
    "wof:name":"Giant Food Stores",
    "wof:placetype":"venue"
},
  "geometry": {"coordinates":[-75.877197,39.823799],"type":"Point"}
}