{
  "type": "Feature",
  "properties": {
    "iso:country":"US",
    "sg:address":"409 Shoemaker St",
    "sg:city":"Kingston",
    "sg:classifiers":[
        {
            "category":"Bars & Pubs",
            "type":"Food & Drink"
        }
    ],
    "sg:phone":"+1 570 287 9202",
    "sg:postcode":"18704",
    "sg:province":"PA",
    "wof:name":"Bayo's Cafe",
    "wof:placetype":"venue"
},
  "geometry": {"coordinates":[-75.88286600000001,41.295088],"type":"Point"}
}