{
  "type": "Feature",
  "properties": {
    "iso:country":"US",
    "sg:address":"10032 Hillwood Dr",
    "sg:city":"Wattsburg",
    "sg:classifiers":[
        {
            "category":"Health Services",
            "subcategory":"Nursing And Care Facility",
            "type":"Services"
        }
    ],
    "sg:phone":"+1 814 739 2153",
    "sg:postcode":"16442",
    "sg:province":"PA",
    "sg:tags":[
        "personal",
        "home"
    ],
    "wof:name":"Mandaville's Country Care",
    "wof:placetype":"venue"
},
  "geometry": {"coordinates":[-79.793167,42.008091],"type":"Point"}
}