{
  "type": "Feature",
  "properties": {
    "iso:country":"US",
    "sg:address":"122 W 4th Ave",
    "sg:city":"Tarentum",
    "sg:classifiers":[
        {
            "category":"Shopping",
            "subcategory":"Clothing, Apparel, & Fashions",
            "type":"Retail Goods"
        }
    ],
    "sg:phone":"+1 724 224 4877",
    "sg:postcode":"15084",
    "sg:province":"PA",
    "sg:tags":[
        "shop",
        "bridal"
    ],
    "wof:name":"Ribbon Of Love Bridal Boutique",
    "wof:placetype":"venue"
},
  "geometry": {"coordinates":[-79.757863,40.600044],"type":"Point"}
}