{
  "type": "Feature",
  "properties": {
    "addr:full":"1027 N Valley Forge Rd Devon PA 19333",
    "addr:housenumber":"1027",
    "addr:postcode":"19333",
    "addr:street":"N Valley Forge Rd",
    "iso:country":"US",
    "sg:address":"1027 N Valley Forge Rd",
    "sg:city":"Devon",
    "sg:classifiers":[
        {
            "category":"Banks & Credit Unions",
            "subcategory":"Bank",
            "type":"Services"
        }
    ],
    "sg:phone":"+1   ",
    "sg:postcode":"19333",
    "sg:province":"PA",
    "sg:tags":[
        "loan",
        "broker"
    ],
    "wof:name":"Lenders Inc",
    "wof:placetype":"venue"
},
  "geometry": {"coordinates":[-75.432509,40.065166],"type":"Point"}
}