{
  "type": "Feature",
  "properties": {
    "iso:country":"US",
    "sg:address":"545 Broxton Ct",
    "sg:city":"Lansdale",
    "sg:classifiers":[
        {
            "category":"Professional",
            "type":"Services"
        }
    ],
    "sg:phone":"+1 215 361 3760",
    "sg:postcode":"19438",
    "sg:province":"PA",
    "sg:tags":[
        "establishment"
    ],
    "wof:name":"Allison Campbell Div",
    "wof:placetype":"venue"
},
  "geometry": {"coordinates":[-75.353239,40.238355],"type":"Point"}
}