{
  "type": "Feature",
  "properties": {
    "iso:country":"US",
    "sg:address":"3218 E Market St",
    "sg:city":"York",
    "sg:classifiers":[
        {
            "category":"Health Services",
            "subcategory":"Doctor",
            "type":"Services"
        }
    ],
    "sg:phone":"+1 717 755 3061",
    "sg:postcode":"17402",
    "sg:province":"PA",
    "sg:tags":[
        "dentist"
    ],
    "wof:name":"Depasquale & Depasquale",
    "wof:placetype":"venue"
},
  "geometry": {"coordinates":[-76.661001,39.978524],"type":"Point"}
}