{
  "type": "Feature",
  "properties": {
    "addr:full":"436 7th Ave Pittsburgh PA 15219",
    "addr:housenumber":"436",
    "addr:postcode":"15219",
    "addr:street":"7Th Ave",
    "iso:country":"US",
    "sg:address":"436 7th Ave",
    "sg:city":"Pittsburgh",
    "sg:classifiers":[
        {
            "category":"Professional",
            "subcategory":"Lawyer & Legal Services",
            "type":"Services"
        }
    ],
    "sg:phone":"+1 412 227 8815",
    "sg:postcode":"15219",
    "sg:province":"PA",
    "sg:tags":[
        "attorney"
    ],
    "wof:name":"WEBB Ziesenheim & Bruening",
    "wof:placetype":"venue"
},
  "geometry": {"coordinates":[-79.99505000000001,40.442119],"type":"Point"}
}