{
  "type": "Feature",
  "properties": {
    "addr:full":"2633 S Marshall St Philadelphia PA 19148",
    "addr:housenumber":"2633",
    "addr:postcode":"19148",
    "addr:street":"S Marshall St",
    "iso:country":"US",
    "sg:address":"2633 S Marshall St",
    "sg:city":"Philadelphia",
    "sg:classifiers":[
        {
            "category":"Manufacturing",
            "subcategory":"Electronics",
            "type":"Manufacturing & Wholesale Goods"
        }
    ],
    "sg:phone":"+1   ",
    "sg:postcode":"19148",
    "sg:province":"PA",
    "sg:tags":[
        "communication",
        "public",
        "equipment"
    ],
    "wof:name":"Valfri Electronic Engineering",
    "wof:placetype":"venue"
},
  "geometry": {"coordinates":[-75.158655,39.915593],"type":"Point"}
}