{
  "type": "Feature",
  "properties": {
    "iso:country":"US",
    "sg:address":"321 Snyder Rd",
    "sg:city":"Oley",
    "sg:classifiers":[
        {
            "category":"Shopping",
            "subcategory":"Used Merchandise",
            "type":"Retail Goods"
        }
    ],
    "sg:phone":"+1 610 987 9703",
    "sg:postcode":"19547",
    "sg:province":"PA",
    "wof:name":"Bertolet House Antiques",
    "wof:placetype":"venue"
},
  "geometry": {"coordinates":[-75.752993,40.390024],"type":"Point"}
}