{
  "type": "Feature",
  "properties": {
    "iso:country":"US",
    "sg:address":"6060 Briar Dr",
    "sg:city":"Erie",
    "sg:classifiers":[
        {
            "category":"Building & Trades",
            "subcategory":"Construction",
            "type":"Services"
        }
    ],
    "sg:phone":"+1   ",
    "sg:postcode":"16506",
    "sg:province":"PA",
    "sg:tags":[
        "contractor"
    ],
    "wof:name":"Di Bartolomeo & Orlando Bldrs",
    "wof:placetype":"venue"
},
  "geometry": {"coordinates":[-80.138324,42.046163],"type":"Point"}
}