{
  "type": "Feature",
  "properties": {
    "addr:full":"2315 Babcock Blvd Pittsburgh PA 15237",
    "addr:housenumber":"2315",
    "addr:postcode":"15237",
    "addr:street":"Babcock Blvd",
    "iso:country":"US",
    "sg:address":"2315 Babcock Blvd",
    "sg:city":"Pittsburgh",
    "sg:classifiers":[
        {
            "category":"Shopping",
            "subcategory":"Clothing, Apparel, & Fashions",
            "type":"Retail Goods"
        }
    ],
    "sg:phone":"+1   ",
    "sg:postcode":"15237",
    "sg:province":"PA",
    "wof:name":"Life Uniform 132",
    "wof:placetype":"venue"
},
  "geometry": {"coordinates":[-79.998817,40.513016],"type":"Point"}
}