{
  "type": "Feature",
  "properties": {
    "addr:full":"1100 Vine St Philadelphia PA 19107",
    "addr:housenumber":"1100",
    "addr:postcode":"19107",
    "addr:street":"Vine St",
    "iso:country":"US",
    "sg:address":"1100 Vine St",
    "sg:city":"Philadelphia",
    "sg:classifiers":[
        {
            "category":"Utilities",
            "subcategory":"Telephone",
            "type":"Services"
        }
    ],
    "sg:phone":"+1   ",
    "sg:postcode":"19107",
    "sg:province":"PA",
    "sg:tags":[
        "internet"
    ],
    "wof:name":"Poboxcom",
    "wof:placetype":"venue"
},
  "geometry": {"coordinates":[-75.157174,39.956987],"type":"Point"}
}