{
  "type": "Feature",
  "properties": {
    "addr:full":"25801 Pinewoods Rd Waterford PA 16403",
    "addr:housenumber":"25801",
    "addr:postcode":"16403",
    "addr:street":"Pinewoods Rd",
    "iso:country":"US",
    "sg:address":"25801 Pinewoods Rd",
    "sg:city":"Waterford",
    "sg:classifiers":[
        {
            "category":"Building & Trades",
            "subcategory":"Construction",
            "type":"Services"
        }
    ],
    "sg:phone":"+1   ",
    "sg:postcode":"16403",
    "sg:province":"PA",
    "sg:tags":[
        "house"
    ],
    "wof:name":"Hull Construction Gary",
    "wof:placetype":"venue"
},
  "geometry": {"coordinates":[-79.97366599999999,41.827053],"type":"Point"}
}