{
  "type": "Feature",
  "properties": {
    "iso:country":"US",
    "sg:address":"208 Diamond Ave",
    "sg:city":"Brownsville",
    "sg:classifiers":[
        {
            "category":"Bars & Pubs",
            "type":"Food & Drink"
        }
    ],
    "sg:phone":"+1 724 785 2587",
    "sg:postcode":"15417",
    "sg:province":"PA",
    "sg:tags":[
        "tavern"
    ],
    "wof:name":"Twin Star Tavern Inc",
    "wof:placetype":"venue"
},
  "geometry": {"coordinates":[-79.916498,40.024259],"type":"Point"}
}