{
  "type": "Feature",
  "properties": {
    "addr:full":"2145 N 6th St Philadelphia PA 19122",
    "addr:housenumber":"2145",
    "addr:postcode":"19122",
    "addr:street":"N 6Th St",
    "iso:country":"US",
    "sg:address":"2145 N 6th St",
    "sg:city":"Philadelphia",
    "sg:classifiers":[
        {
            "category":"Organizations",
            "subcategory":"Community Association",
            "type":"Services"
        }
    ],
    "sg:phone":"+1 215 235 8646",
    "sg:postcode":"19122",
    "sg:province":"PA",
    "sg:tags":[
        "club"
    ],
    "wof:name":"ASSN Puertorriquenos En Marcha",
    "wof:placetype":"venue"
},
  "geometry": {"coordinates":[-75.14382500000001,39.984358],"type":"Point"}
}