{
  "type": "Feature",
  "properties": {
    "iso:country":"US",
    "sg:address":"2079 W Penn Pike",
    "sg:city":"New Ringgold",
    "sg:classifiers":[
        {
            "category":"Wholesale",
            "subcategory":"Hardware",
            "type":"Manufacturing & Wholesale Goods"
        }
    ],
    "sg:phone":"+1 570 386 2386",
    "sg:postcode":"17960",
    "sg:province":"PA",
    "sg:tags":[
        "purifying",
        "cleaning",
        "air"
    ],
    "wof:name":"Effective Controls Inc",
    "wof:placetype":"venue"
},
  "geometry": {"coordinates":[-75.85563500000001,40.719757],"type":"Point"}
}