{
  "type": "Feature",
  "properties": {
    "addr:full":"335 Main St Duryea PA 18642",
    "addr:housenumber":"335",
    "addr:postcode":"18642",
    "addr:street":"Main St",
    "iso:country":"US",
    "sg:address":"335 Main St",
    "sg:city":"Duryea",
    "sg:classifiers":[
        {
            "category":"Shopping",
            "subcategory":"Pharmacy",
            "type":"Retail Goods"
        }
    ],
    "sg:phone":"+1 570 457 6789",
    "sg:postcode":"18642",
    "sg:province":"PA",
    "wof:name":"Family Pharmacy",
    "wof:placetype":"venue"
},
  "geometry": {"coordinates":[-75.762996,41.35114],"type":"Point"}
}