{
  "type": "Feature",
  "properties": {
    "iso:country":"US",
    "sg:address":"2848 S 16th St",
    "sg:city":"Philadelphia",
    "sg:classifiers":[
        {
            "category":"Real Estate",
            "subcategory":"Real Estate Agent",
            "type":"Services"
        }
    ],
    "sg:phone":"+1 215 462 5758",
    "sg:postcode":"19145",
    "sg:province":"PA",
    "wof:name":"Lanciano Real Estate",
    "wof:placetype":"venue"
},
  "geometry": {"coordinates":[-75.174775,39.915266],"type":"Point"}
}