{
  "type": "Feature",
  "properties": {
    "iso:country":"US",
    "sg:address":"5300 Umbria St",
    "sg:city":"Philadelphia",
    "sg:classifiers":[
        {
            "category":"Building & Trades",
            "subcategory":"Construction",
            "type":"Services"
        }
    ],
    "sg:phone":"+1 215 482 3567",
    "sg:postcode":"19128",
    "sg:province":"PA",
    "sg:tags":[
        "excavation",
        "contractor"
    ],
    "wof:name":"Richard W Fox",
    "wof:placetype":"venue"
},
  "geometry": {"coordinates":[-75.241882,40.040548],"type":"Point"}
}