{
  "type": "Feature",
  "properties": {
    "iso:country":"US",
    "sg:address":"2 Northview Rd",
    "sg:city":"Pittston",
    "sg:classifiers":[
        {
            "category":"Freight",
            "type":"Transportation"
        }
    ],
    "sg:phone":"+1   ",
    "sg:postcode":"18640",
    "sg:province":"PA",
    "sg:tags":[
        "local",
        "storage",
        "trucking"
    ],
    "wof:name":"Quality Transportation",
    "wof:placetype":"venue"
},
  "geometry": {"coordinates":[-75.77713799999999,41.326485],"type":"Point"}
}