{
  "type": "Feature",
  "properties": {
    "iso:country":"US",
    "sg:address":"Oliver Building",
    "sg:city":"Pittsburgh",
    "sg:classifiers":[
        {
            "category":"Professional",
            "subcategory":"Lawyer & Legal Services",
            "type":"Services"
        }
    ],
    "sg:phone":"+1 412 434 8859",
    "sg:postcode":"15222",
    "sg:province":"PA",
    "wof:name":"Ashbaugh Brian W Atty",
    "wof:placetype":"venue"
},
  "geometry": {"coordinates":[-79.9981,40.440899],"type":"Point"}
}