{
  "type": "Feature",
  "properties": {
    "iso:country":"US",
    "sg:address":"6861 Spring Rd",
    "sg:city":"Shermans Dale",
    "sg:classifiers":[
        {
            "category":"Organizations",
            "subcategory":"Religious Organization",
            "type":"Services"
        }
    ],
    "sg:phone":"+1 717 582 9099",
    "sg:postcode":"17090",
    "sg:province":"PA",
    "wof:name":"Perry Alliance Church",
    "wof:placetype":"venue"
},
  "geometry": {"coordinates":[-77.168209,40.363374],"type":"Point"}
}