{
  "type": "Feature",
  "properties": {
    "iso:country":"US",
    "sg:address":"287 Laureldale Rd",
    "sg:city":"Perryopolis",
    "sg:classifiers":[
        {
            "category":"Manufacturing",
            "subcategory":"Food",
            "type":"Manufacturing & Wholesale Goods"
        },
        {
            "category":"Farming",
            "subcategory":"Farm",
            "type":"Manufacturing & Wholesale Goods"
        }
    ],
    "sg:phone":"+1 724 677 2225",
    "sg:postcode":"15473",
    "sg:province":"PA",
    "sg:tags":[
        "corn",
        "product"
    ],
    "wof:name":"Jane Smetanka",
    "wof:placetype":"venue"
},
  "geometry": {"coordinates":[-79.799728,40.036549],"type":"Point"}
}