{
  "type": "Feature",
  "properties": {
    "addr:full":"2707 Lincoln Hwy Thorndale PA 19365",
    "addr:housenumber":"2707",
    "addr:postcode":"19365",
    "addr:street":"Lincoln Hwy",
    "iso:country":"US",
    "sg:address":"2707 Lincoln Hwy",
    "sg:city":"Thorndale",
    "sg:classifiers":[
        {
            "category":"Retail",
            "subcategory":"Auto Rental",
            "type":"Services"
        }
    ],
    "sg:phone":"+1 610 380 9022",
    "sg:postcode":"19365",
    "sg:province":"PA",
    "sg:tags":[
        "renting",
        "automobile"
    ],
    "wof:name":"Hertz Rent A Car",
    "wof:placetype":"venue"
},
  "geometry": {"coordinates":[-75.930665,39.983232],"type":"Point"}
}