{
  "type": "Feature",
  "properties": {
    "iso:country":"US",
    "sg:address":"746 Lehigh Ave",
    "sg:city":"Lancaster",
    "sg:classifiers":[
        {
            "category":"Professional",
            "subcategory":"Computer Services",
            "type":"Services"
        }
    ],
    "sg:phone":"+1 610 621 4973",
    "sg:postcode":"17602",
    "sg:province":"PA",
    "sg:tags":[
        "isp",
        "provider",
        "internet"
    ],
    "wof:name":"Vndataweb, Inc.",
    "wof:placetype":"venue"
},
  "geometry": {"coordinates":[-76.29146,40.045663],"type":"Point"}
}