{
  "type": "Feature",
  "properties": {
    "iso:country":"US",
    "sg:address":"9601 Ashton Rd",
    "sg:city":"Philadelphia",
    "sg:classifiers":[
        {
            "category":"Wholesale",
            "subcategory":"Computers",
            "type":"Manufacturing & Wholesale Goods"
        }
    ],
    "sg:phone":"+1   ",
    "sg:postcode":"19114",
    "sg:province":"PA",
    "sg:tags":[
        "parts"
    ],
    "wof:name":"L Tron Corp",
    "wof:placetype":"venue"
},
  "geometry": {"coordinates":[-75.014223,40.070488],"type":"Point"}
}