{
  "type": "Feature",
  "properties": {
    "iso:country":"US",
    "sg:address":"1114 Gap Rd",
    "sg:city":"Kinzers",
    "sg:classifiers":[
        {
            "category":"Freight",
            "type":"Transportation"
        }
    ],
    "sg:phone":"+1 610 593 4322",
    "sg:postcode":"17535",
    "sg:province":"PA",
    "sg:tags":[
        "trucking"
    ],
    "wof:name":"ZST Inc",
    "wof:placetype":"venue"
},
  "geometry": {"coordinates":[-76.02274199999999,39.962703],"type":"Point"}
}