{
  "type": "Feature",
  "properties": {
    "iso:country":"US",
    "sg:address":"107 S Main St",
    "sg:city":"Carrolltown",
    "sg:classifiers":[
        {
            "category":"Restaurant",
            "type":"Food & Drink"
        }
    ],
    "sg:phone":"+1 814 344 2007",
    "sg:postcode":"15722",
    "sg:province":"PA",
    "wof:name":"Cheesecakes Cafe",
    "wof:placetype":"venue"
},
  "geometry": {"coordinates":[-78.70935799999999,40.60156],"type":"Point"}
}