{
  "type": "Feature",
  "properties": {
    "iso:country":"US",
    "sg:address":"11171 Perry Hwy",
    "sg:city":"Wexford",
    "sg:classifiers":[
        {
            "category":"Home & Garden",
            "subcategory":"Home Furnishings",
            "type":"Retail Goods"
        }
    ],
    "sg:phone":"+1   ",
    "sg:postcode":"15090",
    "sg:province":"PA",
    "sg:tags":[
        "specializing",
        "b",
        "equipment",
        "coal",
        "wood",
        "fireplace"
    ],
    "wof:name":"Howard",
    "wof:placetype":"venue"
},
  "geometry": {"coordinates":[-80.05500499999999,40.626626],"type":"Point"}
}