{
  "type": "Feature",
  "properties": {
    "addr:full":"2033 Midland Beaver Rd Industry PA 15052",
    "addr:housenumber":"2033",
    "addr:postcode":"15052",
    "addr:street":"Midland Beaver Rd",
    "iso:country":"US",
    "sg:address":"2033 Midland Beaver Rd",
    "sg:city":"Industry",
    "sg:classifiers":[
        {
            "category":"Organizations",
            "subcategory":"Religious Organization",
            "type":"Services"
        }
    ],
    "sg:phone":"+1 724 643 0603",
    "sg:postcode":"15052",
    "sg:province":"PA",
    "sg:tags":[
        "church"
    ],
    "wof:name":"Greater Faith Family Worship",
    "wof:placetype":"venue"
},
  "geometry": {"coordinates":[-80.409907,40.649935],"type":"Point"}
}