{
  "type": "Feature",
  "properties": {
    "iso:country":"US",
    "sg:address":"4017 Eastbrook Rd",
    "sg:city":"Harrisburg",
    "sg:classifiers":[
        {
            "category":"Retail",
            "subcategory":"Repair Shop",
            "type":"Services"
        }
    ],
    "sg:phone":"+1   ",
    "sg:postcode":"17109",
    "sg:province":"PA",
    "sg:tags":[
        "custom",
        "art",
        "gallery",
        "framing"
    ],
    "wof:name":"Hawk Gallery & Framing Studio",
    "wof:placetype":"venue"
},
  "geometry": {"coordinates":[-76.823123,40.281457],"type":"Point"}
}