{
  "type": "Feature",
  "properties": {
    "iso:country":"US",
    "sg:address":"1 Fnb Blvd",
    "sg:city":"Hermitage",
    "sg:classifiers":[
        {
            "category":"Banks & Credit Unions",
            "subcategory":"Financial Services",
            "type":"Services"
        }
    ],
    "sg:phone":"+1 724 981 6000",
    "sg:postcode":"16148",
    "sg:province":"PA",
    "sg:tags":[
        "company",
        "holding"
    ],
    "sg:website":"www.fnbcorporation.com",
    "wof:name":"FNB Corp",
    "wof:placetype":"venue"
},
  "geometry": {"coordinates":[-80.4512,41.231415],"type":"Point"}
}