{
  "type": "Feature",
  "properties": {
    "addr:full":"33 Silver Lake Rd Hancock PA 13783",
    "addr:housenumber":"33",
    "addr:postcode":"13783",
    "addr:street":"Silver Lake Rd",
    "iso:country":"US",
    "sg:address":"33 Silver Lake Rd",
    "sg:city":"Hancock",
    "sg:classifiers":[
        {
            "category":"Manufacturing",
            "subcategory":"Buildings",
            "type":"Manufacturing & Wholesale Goods"
        }
    ],
    "sg:phone":"+1 607 467 5995",
    "sg:postcode":"13783",
    "sg:province":"PA",
    "sg:tags":[
        "home",
        "log",
        "cabin"
    ],
    "wof:name":"Lok-N-Logs Inc",
    "wof:placetype":"venue"
},
  "geometry": {"coordinates":[-75.36072799999999,42.034953],"type":"Point"}
}