{
  "type": "Feature",
  "properties": {
    "addr:full":"101 S 2nd St Wrightsville PA 17368",
    "addr:housenumber":"101",
    "addr:postcode":"17368",
    "addr:street":"S 2Nd St",
    "iso:country":"US",
    "sg:address":"101 S 2nd St",
    "sg:city":"Wrightsville",
    "sg:classifiers":[
        {
            "category":"Organizations",
            "subcategory":"Professional Association",
            "type":"Services"
        }
    ],
    "sg:phone":"+1 717 252 3412",
    "sg:postcode":"17368",
    "sg:province":"PA",
    "sg:tags":[
        "business"
    ],
    "wof:name":"American Legion",
    "wof:placetype":"venue"
},
  "geometry": {"coordinates":[-76.529721,40.025203],"type":"Point"}
}