{
  "type": "Feature",
  "properties": {
    "iso:country":"US",
    "sg:address":"2923 W 11th St",
    "sg:city":"Chester",
    "sg:classifiers":[
        {
            "category":"Wholesale",
            "subcategory":"Beer",
            "type":"Manufacturing & Wholesale Goods"
        }
    ],
    "sg:phone":"+1 610 494 9498",
    "sg:postcode":"19013",
    "sg:province":"PA",
    "sg:tags":[
        "ale"
    ],
    "wof:name":"Mc Ginn's Beer Distr",
    "wof:placetype":"venue"
},
  "geometry": {"coordinates":[-75.398201,39.836788],"type":"Point"}
}