{
  "type": "Feature",
  "properties": {
    "addr:full":"220 W High St Bellefonte PA 16823",
    "addr:housenumber":"220",
    "addr:postcode":"16823",
    "addr:street":"W High St",
    "iso:country":"US",
    "sg:address":"220 W High St",
    "sg:city":"Bellefonte",
    "sg:classifiers":[
        {
            "category":"Shopping",
            "subcategory":"Hobbies, Toys, & Games",
            "type":"Retail Goods"
        }
    ],
    "sg:phone":"+1 814 355 5612",
    "sg:postcode":"16823",
    "sg:province":"PA",
    "sg:tags":[
        "toy",
        "store"
    ],
    "wof:name":"Go-Velo-City",
    "wof:placetype":"venue"
},
  "geometry": {"coordinates":[-77.779746,40.911505],"type":"Point"}
}