{
  "type": "Feature",
  "properties": {
    "iso:country":"US",
    "sg:address":"103 N Clifton Ave",
    "sg:city":"Clifton Heights",
    "sg:classifiers":[
        {
            "category":"Organizations",
            "subcategory":"Community Association",
            "type":"Services"
        }
    ],
    "sg:phone":"+1 610 626 7598",
    "sg:postcode":"19018",
    "sg:province":"PA",
    "sg:tags":[
        "military"
    ],
    "wof:name":"Vietnam Veterans Of America",
    "wof:placetype":"venue"
},
  "geometry": {"coordinates":[-75.288844,39.924822],"type":"Point"}
}