{
  "type": "Feature",
  "properties": {
    "addr:full":"101 S Hartman St Manchester PA 17345",
    "addr:housenumber":"101",
    "addr:postcode":"17345",
    "addr:street":"S Hartman St",
    "iso:country":"US",
    "sg:address":"101 S Hartman St",
    "sg:city":"Manchester",
    "sg:classifiers":[
        {
            "category":"Education",
            "subcategory":"School",
            "type":"Public Place"
        }
    ],
    "sg:phone":"+1   ",
    "sg:postcode":"17345",
    "sg:province":"PA",
    "wof:name":"Orendorf Elem School",
    "wof:placetype":"venue"
},
  "geometry": {"coordinates":[-76.71472799999999,40.061129],"type":"Point"}
}