{
  "type": "Feature",
  "properties": {
    "addr:full":"50 Yorkshire Ct Elizabethtown PA 17022",
    "addr:housenumber":"50",
    "addr:postcode":"17022",
    "addr:street":"Yorkshire Ct",
    "iso:country":"US",
    "sg:address":"50 Yorkshire Ct",
    "sg:city":"Elizabethtown",
    "sg:classifiers":[
        {
            "category":"Social Services",
            "subcategory":"Child Care",
            "type":"Services"
        }
    ],
    "sg:phone":"+1   ",
    "sg:postcode":"17022",
    "sg:province":"PA",
    "sg:tags":[
        "day"
    ],
    "wof:name":"Gingerbread House",
    "wof:placetype":"venue"
},
  "geometry": {"coordinates":[-76.60812900000001,40.142502],"type":"Point"}
}