{
  "type": "Feature",
  "properties": {
    "iso:country":"US",
    "sg:address":"1776 S Meadow Dr",
    "sg:city":"Mechanicsburg",
    "sg:classifiers":[
        {
            "category":"Restaurant",
            "type":"Food & Drink"
        }
    ],
    "sg:phone":"+1 717 691 1950",
    "sg:postcode":"17055",
    "sg:province":"PA",
    "sg:tags":[
        "eating",
        "caterer"
    ],
    "wof:name":"Patty Armbrust & Co Inc",
    "wof:placetype":"venue"
},
  "geometry": {"coordinates":[-77.00032,40.177231],"type":"Point"}
}