{
  "type": "Feature",
  "properties": {
    "iso:country":"US",
    "sg:address":"197 E Silver St",
    "sg:city":"Sharon",
    "sg:classifiers":[
        {
            "category":"Government",
            "subcategory":"Office",
            "type":"Public Place"
        }
    ],
    "sg:phone":"+1 724 983 5712",
    "sg:postcode":"16146",
    "sg:province":"PA",
    "wof:name":"Unemploymnt Compensatn Ref Ofc",
    "wof:placetype":"venue"
},
  "geometry": {"coordinates":[-80.505611,41.234498],"type":"Point"}
}