{
  "type": "Feature",
  "properties": {
    "iso:country":"US",
    "sg:address":"445 Bethlehem Pike",
    "sg:city":"Colmar",
    "sg:classifiers":[
        {
            "category":"Professional",
            "type":"Services"
        }
    ],
    "sg:phone":"+1   ",
    "sg:postcode":"18915",
    "sg:province":"PA",
    "wof:name":"K-Stat Static Controll Company",
    "wof:placetype":"venue"
},
  "geometry": {"coordinates":[-75.25975200000001,40.275825],"type":"Point"}
}