{
  "type": "Feature",
  "properties": {
    "addr:full":"4730 Friendship Ave Pittsburgh PA 15224",
    "addr:housenumber":"4730",
    "addr:postcode":"15224",
    "addr:street":"Friendship Ave",
    "iso:country":"US",
    "sg:address":"4730 Friendship Ave",
    "sg:city":"Pittsburgh",
    "sg:classifiers":[
        {
            "category":"Retail",
            "subcategory":"Funeral Services",
            "type":"Services"
        }
    ],
    "sg:phone":"+1 412 682 3615",
    "sg:postcode":"15224",
    "sg:province":"PA",
    "sg:tags":[
        "director"
    ],
    "wof:name":"Winter Funeral Home",
    "wof:placetype":"venue"
},
  "geometry": {"coordinates":[-79.948472,40.463176],"type":"Point"}
}