{
  "type": "Feature",
  "properties": {
    "addr:full":"262 E Market St Bethlehem PA 18018",
    "addr:housenumber":"262",
    "addr:postcode":"18018",
    "addr:street":"E Market St",
    "iso:country":"US",
    "sg:address":"262 E Market St",
    "sg:city":"Bethlehem",
    "sg:classifiers":[
        {
            "category":"Building & Trades",
            "subcategory":"Construction",
            "type":"Services"
        }
    ],
    "sg:phone":"+1   ",
    "sg:postcode":"18018",
    "sg:province":"PA",
    "sg:tags":[
        "wallpaper",
        "painting",
        "contractor"
    ],
    "wof:name":"MPS Walpapering & Painting",
    "wof:placetype":"venue"
},
  "geometry": {"coordinates":[-75.371341,40.620534],"type":"Point"}
}