{
  "type": "Feature",
  "properties": {
    "iso:country":"US",
    "sg:address":"172 Shine Ln",
    "sg:city":"Jamestown",
    "sg:classifiers":[
        {
            "category":"Wholesale",
            "subcategory":"Construction Materials",
            "type":"Manufacturing & Wholesale Goods"
        },
        {
            "category":"Mining & Drilling",
            "type":"Manufacturing & Wholesale Goods"
        }
    ],
    "sg:phone":"+1 724 932 5600",
    "sg:postcode":"16134",
    "sg:province":"PA",
    "sg:tags":[
        "sand",
        "gravel",
        "pit"
    ],
    "wof:name":"Shenango Vallley Sand & Gravel",
    "wof:placetype":"venue"
},
  "geometry": {"coordinates":[-80.42710099999999,41.466506],"type":"Point"}
}