{
  "type": "Feature",
  "properties": {
    "iso:country":"US",
    "sg:address":"2 S Saint Marys St",
    "sg:city":"St Marys",
    "sg:classifiers":[
        {
            "category":"Shopping",
            "subcategory":"Computers & Home Electronics",
            "type":"Retail Goods"
        },
        {
            "category":"Cinema",
            "subcategory":"Movie Rental",
            "type":"Entertainment"
        }
    ],
    "sg:phone":"+1 814 834 4111",
    "sg:postcode":"15857",
    "sg:province":"PA",
    "sg:tags":[
        "video",
        "game",
        "leasing"
    ],
    "wof:name":"Take Two Video",
    "wof:placetype":"venue"
},
  "geometry": {"coordinates":[-78.561368,41.42666],"type":"Point"}
}