{
  "type": "Feature",
  "properties": {
    "addr:full":"1151 E Rittenhouse St Philadelphia PA 19138",
    "addr:housenumber":"1151",
    "addr:postcode":"19138",
    "addr:street":"E Rittenhouse St",
    "iso:country":"US",
    "sg:address":"1151 E Rittenhouse St",
    "sg:city":"Philadelphia",
    "sg:classifiers":[
        {
            "category":"Restaurant",
            "type":"Food & Drink"
        }
    ],
    "sg:phone":"+1   ",
    "sg:postcode":"19138",
    "sg:province":"PA",
    "sg:tags":[
        "eating"
    ],
    "wof:name":"A Childs Place Family",
    "wof:placetype":"venue"
},
  "geometry": {"coordinates":[-75.161585,40.051583],"type":"Point"}
}