{
  "type": "Feature",
  "properties": {
    "iso:country":"US",
    "sg:address":"9155 Marshall Rd",
    "sg:city":"Cranberry Twp",
    "sg:classifiers":[
        {
            "category":"Building & Trades",
            "subcategory":"Construction",
            "type":"Services"
        }
    ],
    "sg:phone":"+1 724 452 2210",
    "sg:postcode":"16066",
    "sg:province":"PA",
    "sg:tags":[
        "family",
        "builder",
        "general",
        "new",
        "home",
        "contractor"
    ],
    "wof:name":"William Jack Homes Inc",
    "wof:placetype":"venue"
},
  "geometry": {"coordinates":[-80.10039,40.714835],"type":"Point"}
}