{
  "type": "Feature",
  "properties": {
    "iso:country":"US",
    "sg:address":"98 Scarboro Dr",
    "sg:city":"York",
    "sg:classifiers":[
        {
            "category":"Shopping",
            "subcategory":"Gifts & Souvenirs",
            "type":"Retail Goods"
        }
    ],
    "sg:phone":"+1 717 848 4817",
    "sg:postcode":"17403",
    "sg:province":"PA",
    "sg:tags":[
        "balloon",
        "artist"
    ],
    "wof:name":"Balloons Instead",
    "wof:placetype":"venue"
},
  "geometry": {"coordinates":[-76.71608000000001,39.942407],"type":"Point"}
}