{
  "type": "Feature",
  "properties": {
    "addr:full":"618 Delaware Ave Fountain Hill PA 18015",
    "addr:housenumber":"618",
    "addr:postcode":"18015",
    "addr:street":"Delaware Ave",
    "iso:country":"US",
    "sg:address":"618 Delaware Ave",
    "sg:city":"Fountain Hill",
    "sg:classifiers":[
        {
            "category":"Health Services",
            "subcategory":"Doctor",
            "type":"Services"
        }
    ],
    "sg:phone":"+1 610 694 8111",
    "sg:postcode":"18015",
    "sg:province":"PA",
    "sg:tags":[
        "cardiologist"
    ],
    "wof:name":"Puleo Peter R MD",
    "wof:placetype":"venue"
},
  "geometry": {"coordinates":[-75.39009900000001,40.609798],"type":"Point"}
}