{
  "type": "Feature",
  "properties": {
    "addr:full":"30 E Front St Media PA 19063",
    "addr:housenumber":"30",
    "addr:postcode":"19063",
    "addr:street":"E Front St",
    "iso:country":"US",
    "sg:address":"30 E Front St",
    "sg:city":"Media",
    "sg:classifiers":[
        {
            "category":"Real Estate",
            "subcategory":"Real Estate Agent",
            "type":"Services"
        }
    ],
    "sg:phone":"+1   ",
    "sg:postcode":"19063",
    "sg:province":"PA",
    "wof:name":"Phillip McCloskey",
    "wof:placetype":"venue"
},
  "geometry": {"coordinates":[-75.387925,39.918583],"type":"Point"}
}