{
  "type": "Feature",
  "properties": {
    "iso:country":"US",
    "sg:address":"2299 Radcliffe St",
    "sg:city":"Bristol",
    "sg:classifiers":[
        {
            "category":"Organizations",
            "subcategory":"Membership Organization",
            "type":"Services"
        }
    ],
    "sg:phone":"+1 215 785 2033",
    "sg:postcode":"19007",
    "sg:province":"PA",
    "sg:tags":[
        "fraternal"
    ],
    "sg:website":"http://www.mooseintl.org",
    "wof:name":"Loyal Order of Moose Lodges",
    "wof:placetype":"venue"
},
  "geometry": {"coordinates":[-74.83689099999999,40.109341],"type":"Point"}
}