{
  "type": "Feature",
  "properties": {
    "iso:country":"US",
    "sg:address":"5000 Linglestown Rd",
    "sg:city":"Harrisburg",
    "sg:classifiers":[
        {
            "category":"Restaurant",
            "type":"Food & Drink"
        }
    ],
    "sg:menulink":"http://www.allmenus.com/pa/lower-paxton/64632-papa-johns-pizza/menu/",
    "sg:phone":"+1 717 651 5000",
    "sg:postcode":"17112",
    "sg:province":"PA",
    "sg:tags":[
        "american",
        "pizza"
    ],
    "wof:name":"Papa John's Pizza",
    "wof:placetype":"venue"
},
  "geometry": {"coordinates":[-76.81297000000001,40.338672],"type":"Point"}
}