{
  "type": "Feature",
  "properties": {
    "iso:country":"US",
    "sg:address":"820 University Dr",
    "sg:city":"University Park",
    "sg:classifiers":[
        {
            "category":"Manufacturing",
            "subcategory":"Printing",
            "type":"Manufacturing & Wholesale Goods"
        }
    ],
    "sg:phone":"+1   ",
    "sg:postcode":"16801",
    "sg:province":"PA",
    "sg:tags":[
        "book",
        "publishing"
    ],
    "wof:name":"Penn State Press",
    "wof:placetype":"venue"
},
  "geometry": {"coordinates":[-77.84524399999999,40.797606],"type":"Point"}
}