{
  "type": "Feature",
  "properties": {
    "iso:country":"US",
    "sg:address":"471 Delaware Ave",
    "sg:city":"Palmerton",
    "sg:classifiers":[
        {
            "category":"Professional",
            "type":"Services"
        }
    ],
    "sg:phone":"+1   ",
    "sg:postcode":"18071",
    "sg:province":"PA",
    "wof:name":"Sound Source Inc",
    "wof:placetype":"venue"
},
  "geometry": {"coordinates":[-75.60648999999999,40.803131],"type":"Point"}
}