{
  "type": "Feature",
  "properties": {
    "iso:country":"US",
    "sg:address":"7010 Elmwood Ave",
    "sg:city":"Philadelphia",
    "sg:classifiers":[
        {
            "category":"Government",
            "subcategory":"Office",
            "type":"Public Place"
        }
    ],
    "sg:phone":"+1 215 492 5811",
    "sg:postcode":"19142",
    "sg:province":"PA",
    "sg:tags":[
        "legislative",
        "body"
    ],
    "wof:name":"Robert C Donnatucci",
    "wof:placetype":"venue"
},
  "geometry": {"coordinates":[-75.237702,39.916974],"type":"Point"}
}