{
  "type": "Feature",
  "properties": {
    "addr:full":"257 Horseshoe Dr Freeport PA 16229",
    "addr:housenumber":"257",
    "addr:postcode":"16229",
    "addr:street":"Horseshoe Dr",
    "iso:country":"US",
    "sg:address":"257 Horseshoe Dr",
    "sg:city":"Freeport",
    "sg:classifiers":[
        {
            "category":"Farming",
            "subcategory":"Farm",
            "type":"Manufacturing & Wholesale Goods"
        }
    ],
    "sg:phone":"+1 724 295 5415",
    "sg:postcode":"16229",
    "sg:province":"PA",
    "wof:name":"Otterman Farm",
    "wof:placetype":"venue"
},
  "geometry": {"coordinates":[-79.68292599999999,40.723064],"type":"Point"}
}