{
  "type": "Feature",
  "properties": {
    "addr:full":"421 Locust St Johnstown PA 15901",
    "addr:housenumber":"421",
    "addr:postcode":"15901",
    "addr:street":"Locust St",
    "iso:country":"US",
    "sg:address":"421 Locust St",
    "sg:city":"Johnstown",
    "sg:classifiers":[
        {
            "category":"Restaurant",
            "type":"Food & Drink"
        }
    ],
    "sg:phone":"+1   ",
    "sg:postcode":"15901",
    "sg:province":"PA",
    "sg:tags":[
        "personal",
        "eating"
    ],
    "wof:name":"Snappy Chef",
    "wof:placetype":"venue"
},
  "geometry": {"coordinates":[-78.918937,40.326639],"type":"Point"}
}