{
  "type": "Feature",
  "properties": {
    "iso:country":"US",
    "sg:address":"1000 Township Line Rd",
    "sg:city":"Phoenixville",
    "sg:classifiers":[
        {
            "category":"Manufacturing",
            "subcategory":"Printing",
            "type":"Manufacturing & Wholesale Goods"
        }
    ],
    "sg:phone":"+1 610 917 9765",
    "sg:postcode":"19460",
    "sg:province":"PA",
    "sg:tags":[
        "printer"
    ],
    "wof:name":"Eastern Diecutting & Finishing",
    "wof:placetype":"venue"
},
  "geometry": {"coordinates":[-75.54283599999999,40.133268],"type":"Point"}
}